{
  "type": "Feature",
  "properties": {
    "addr:full":"1640 NE 148th St Miami FL 33181",
    "addr:housenumber":"1640",
    "addr:postcode":"33181",
    "addr:street":"Ne 148Th St",
    "iso:country":"US",
    "sg:address":"1640 NE 148th St",
    "sg:city":"Miami",
    "sg:classifiers":[
        {
            "category":"Wholesale",
            "subcategory":"Machinery & Supplies",
            "type":"Manufacturing & Wholesale Goods"
        }
    ],
    "sg:phone":"+1 800 234 5451",
    "sg:postcode":"33181",
    "sg:province":"FL",
    "sg:tags":[
        "distributor",
        "packaging",
        "mar",
        "sales"
    ],
    "wof:name":"Nationwide Lqdators Distrs LLC",
    "wof:placetype":"venue"
},
  "geometry": {"coordinates":[-80.163507,25.912002],"type":"Point"}
}