{
  "type": "Feature",
  "properties": {
    "iso:country":"US",
    "sg:address":"1250 S Miami Ave Apt 2001",
    "sg:city":"Miami",
    "sg:classifiers":[
        {
            "category":"Real Estate",
            "subcategory":"Real Estate Services",
            "type":"Services"
        },
        {
            "category":"Banks & Credit Unions",
            "subcategory":"Financial Services",
            "type":"Services"
        }
    ],
    "sg:phone":"+1 305 358 3934",
    "sg:postcode":"33130",
    "sg:province":"FL",
    "sg:tags":[
        "loan",
        "processing"
    ],
    "wof:name":"Gova Financial",
    "wof:placetype":"venue"
},
  "geometry": {"coordinates":[-80.19319400000001,25.76188],"type":"Point"}
}