{
  "type": "Feature",
  "properties": {
    "addr:full":"5460 W 16th Ave Hialeah FL 33012",
    "addr:housenumber":"5460",
    "addr:postcode":"33012",
    "addr:street":"W 16Th Ave",
    "iso:country":"US",
    "sg:address":"5460 W 16th Ave",
    "sg:city":"Hialeah",
    "sg:classifiers":[
        {
            "category":"Professional",
            "subcategory":"Employment Agencies",
            "type":"Services"
        }
    ],
    "sg:phone":"+1 305 822 7761",
    "sg:postcode":"33012",
    "sg:province":"FL",
    "wof:name":"Youth Co-Op Inc",
    "wof:placetype":"venue"
},
  "geometry": {"coordinates":[-80.31510299999999,25.872022],"type":"Point"}
}