{
  "type": "Feature",
  "properties": {
    "iso:country":"US",
    "sg:address":"2226 Hammock Oaks Dr N",
    "sg:city":"Jacksonville",
    "sg:classifiers":[
        {
            "category":"Community Center",
            "subcategory":"Senior",
            "type":"Public Place"
        }
    ],
    "sg:phone":"+1 904 647 8074",
    "sg:postcode":"32223",
    "sg:province":"FL",
    "sg:tags":[
        "citizen"
    ],
    "wof:name":"Signature Senior Care",
    "wof:placetype":"venue"
},
  "geometry": {"coordinates":[-81.65139000000001,30.152611],"type":"Point"}
}