{
  "type": "Feature",
  "properties": {
    "iso:country":"US",
    "sg:address":"6913 Oldgate Cir",
    "sg:city":"New Port Richey",
    "sg:classifiers":[
        {
            "category":"Shopping",
            "type":"Retail Goods"
        }
    ],
    "sg:phone":"+1 727 375 7932",
    "sg:postcode":"34655",
    "sg:province":"FL",
    "sg:tags":[
        "merchandise"
    ],
    "wof:name":"Organic Pet Pantry",
    "wof:placetype":"venue"
},
  "geometry": {"coordinates":[-82.699674,28.197778],"type":"Point"}
}