{
  "type": "Feature",
  "properties": {
    "addr:full":"10837 SE US Hwy 441 Belleview FL 34420",
    "addr:housenumber":"10837",
    "addr:postcode":"34420",
    "addr:street":"Se Us Hwy 441",
    "iso:country":"US",
    "sg:address":"10837 SE US Hwy 441",
    "sg:city":"Belleview",
    "sg:classifiers":[
        {
            "category":"Bars & Pubs",
            "type":"Food & Drink"
        }
    ],
    "sg:phone":"+1 352 347 1448",
    "sg:postcode":"34420",
    "sg:province":"FL",
    "wof:name":"Bumpers Pub",
    "wof:placetype":"venue"
},
  "geometry": {"coordinates":[-82.067581,29.064355],"type":"Point"}
}