{
  "type": "Feature",
  "properties": {
    "addr:full":"200 S State Road 434 Altamonte Springs FL 32714",
    "addr:housenumber":"200",
    "addr:postcode":"32714",
    "addr:street":"S State Road 434",
    "iso:country":"US",
    "sg:address":"200 S State Road 434",
    "sg:city":"Altamonte Springs",
    "sg:classifiers":[
        {
            "category":"Shopping",
            "subcategory":"Department Store",
            "type":"Retail Goods"
        },
        {
            "category":"Shopping",
            "subcategory":"Mobile Phones",
            "type":"Retail Goods"
        },
        {
            "category":"Food & Beverages",
            "subcategory":"Groceries & Convenience Stores",
            "type":"Retail Goods"
        }
    ],
    "sg:phone":"+1 407 774 9966",
    "sg:postcode":"32714",
    "sg:province":"FL",
    "sg:website":"www.walmart.com",
    "wof:name":"Walmart",
    "wof:placetype":"venue"
},
  "geometry": {"coordinates":[-81.419133,28.661848],"type":"Point"}
}