{
  "type": "Feature",
  "properties": {
    "addr:full":"531 Anclote Rd Tarpon Springs FL 34689",
    "addr:housenumber":"531",
    "addr:postcode":"34689",
    "addr:street":"Anclote Rd",
    "iso:country":"US",
    "sg:address":"531 Anclote Rd",
    "sg:city":"Tarpon Springs",
    "sg:classifiers":[
        {
            "category":"Professional",
            "subcategory":"Lawyer & Legal Services",
            "type":"Services"
        }
    ],
    "sg:phone":"+1 727 938 6117",
    "sg:postcode":"34689",
    "sg:province":"FL",
    "sg:tags":[
        "attorney"
    ],
    "wof:name":"Michael A Houllis",
    "wof:placetype":"venue"
},
  "geometry": {"coordinates":[-82.766884,28.163543],"type":"Point"}
}