{
  "type": "Feature",
  "properties": {
    "iso:country":"US",
    "sg:address":"4906 Old Pleasant Hill Rd",
    "sg:city":"Kissimmee",
    "sg:classifiers":[
        {
            "category":"Place Of Worship",
            "subcategory":"Church",
            "type":"Public Place"
        },
        {
            "category":"Place Of Worship",
            "type":"Public Place"
        }
    ],
    "sg:phone":"+1 407 518 1468",
    "sg:postcode":"34759",
    "sg:province":"FL",
    "sg:tags":[
        "churches-pentecostal-independent",
        "churches-pentecostal"
    ],
    "wof:name":"Iglesia De Dios Pentecostal Mi",
    "wof:placetype":"venue"
},
  "geometry": {"coordinates":[-81.447264,28.139476],"type":"Point"}
}