{
  "type": "Feature",
  "properties": {
    "addr:full":"13244 SW 87th Ter Miami FL 33183",
    "addr:housenumber":"13244",
    "addr:postcode":"33183",
    "addr:street":"Sw 87Th Ter",
    "iso:country":"US",
    "sg:address":"13244 SW 87th Ter",
    "sg:city":"Miami",
    "sg:classifiers":[
        {
            "category":"Professional",
            "subcategory":"Computer Services",
            "type":"Services"
        }
    ],
    "sg:phone":"+1 305 382 8109",
    "sg:postcode":"33183",
    "sg:province":"FL",
    "sg:tags":[
        "consultant",
        "designer",
        "system"
    ],
    "sg:website":"http://www.dmsdata.com",
    "wof:name":"Digital Micro Systems Corp",
    "wof:placetype":"venue"
},
  "geometry": {"coordinates":[-80.40454,25.686222],"type":"Point"}
}