{
  "type": "Feature",
  "properties": {
    "addr:full":"6155 S Florida Ave Lakeland FL 33813",
    "addr:housenumber":"6155",
    "addr:postcode":"33813",
    "addr:street":"S Florida Ave",
    "iso:country":"US",
    "sg:address":"6155 S Florida Ave",
    "sg:city":"Lakeland",
    "sg:classifiers":[
        {
            "category":"Professional",
            "subcategory":"Lawyer & Legal Services",
            "type":"Services"
        }
    ],
    "sg:phone":"+1 863 646 3135",
    "sg:postcode":"33813",
    "sg:province":"FL",
    "wof:name":"Kamp Gregg S PA",
    "wof:placetype":"venue"
},
  "geometry": {"coordinates":[-81.970393,27.951038],"type":"Point"}
}