{
  "type": "Feature",
  "properties": {
    "iso:country":"US",
    "sg:address":"3909 SE Lake Weir Ave",
    "sg:city":"Ocala",
    "sg:classifiers":[
        {
            "category":"Restaurant",
            "type":"Food & Drink"
        }
    ],
    "sg:phone":"+1 352 620 8820",
    "sg:postcode":"34480",
    "sg:province":"FL",
    "sg:tags":[
        "eating",
        "italian"
    ],
    "wof:name":"Labellas Italian Piatto & Pizzeria",
    "wof:placetype":"venue"
},
  "geometry": {"coordinates":[-82.11551799999999,29.148578],"type":"Point"}
}