{
  "type": "Feature",
  "properties": {
    "iso:country":"US",
    "sg:address":"7777 131st St N",
    "sg:city":"Seminole",
    "sg:classifiers":[
        {
            "category":"Banks & Credit Unions",
            "subcategory":"Bank",
            "type":"Services"
        }
    ],
    "sg:phone":"+1 727 392 0510",
    "sg:postcode":"33776",
    "sg:province":"FL",
    "sg:tags":[
        "loan",
        "real estate"
    ],
    "wof:name":"Apex Lending",
    "wof:placetype":"venue"
},
  "geometry": {"coordinates":[-82.81988,27.840727],"type":"Point"}
}