{
  "type": "Feature",
  "properties": {
    "addr:full":"580 Howe St SE Palm Bay FL 32909",
    "addr:housenumber":"580",
    "addr:postcode":"32909",
    "addr:street":"Howe St Se",
    "iso:country":"US",
    "sg:address":"580 Howe St SE",
    "sg:city":"Palm Bay",
    "sg:classifiers":[
        {
            "category":"Building & Trades",
            "subcategory":"Construction",
            "type":"Services"
        }
    ],
    "sg:phone":"+1 321 676 9140",
    "sg:postcode":"32909",
    "sg:province":"FL",
    "sg:tags":[
        "contractor"
    ],
    "wof:name":"American Built Drywall",
    "wof:placetype":"venue"
},
  "geometry": {"coordinates":[-80.659733,27.984991],"type":"Point"}
}