{
  "type": "Feature",
  "properties": {
    "iso:country":"US",
    "sg:address":"18163 SW 154th Ave",
    "sg:city":"Miami",
    "sg:classifiers":[
        {
            "category":"Restaurant",
            "type":"Food & Drink"
        }
    ],
    "sg:phone":"+1 305 233 6670",
    "sg:postcode":"33187",
    "sg:province":"FL",
    "sg:tags":[
        "shop",
        "coffee"
    ],
    "wof:name":"D & N Enterprises Inc",
    "wof:placetype":"venue"
},
  "geometry": {"coordinates":[-80.44192200000001,25.599922],"type":"Point"}
}