{
  "type": "Feature",
  "properties": {
    "addr:full":"14286 Beach Blvd Jacksonville Beach FL 32250",
    "addr:housenumber":"14286",
    "addr:postcode":"32250",
    "addr:street":"Beach Blvd",
    "iso:country":"US",
    "sg:address":"14286 Beach Blvd",
    "sg:city":"Jacksonville Beach",
    "sg:classifiers":[
        {
            "category":"Manufacturing",
            "subcategory":"Printing",
            "type":"Manufacturing & Wholesale Goods"
        }
    ],
    "sg:phone":"+1 904 220 5528",
    "sg:postcode":"32250",
    "sg:province":"FL",
    "sg:tags":[
        "periodical"
    ],
    "wof:name":"Newsweek",
    "wof:placetype":"venue"
},
  "geometry": {"coordinates":[-81.441652,30.287774],"type":"Point"}
}