{
  "type": "Feature",
  "properties": {
    "iso:country":"US",
    "sg:address":"436 NE 3rd Ave",
    "sg:city":"Fort Lauderdale",
    "sg:classifiers":[
        {
            "category":"Professional",
            "type":"Services"
        }
    ],
    "sg:phone":"+1 954 764 7631",
    "sg:postcode":"33301",
    "sg:province":"FL",
    "sg:tags":[
        "arts",
        "artist"
    ],
    "wof:name":"Tin Ly Studio",
    "wof:placetype":"venue"
},
  "geometry": {"coordinates":[-80.140624,26.127265],"type":"Point"}
}