{
  "type": "Feature",
  "properties": {
    "iso:country":"US",
    "sg:address":"12893 SW 50th Ln",
    "sg:city":"Miami",
    "sg:classifiers":[
        {
            "category":"Shopping",
            "type":"Retail Goods"
        }
    ],
    "sg:phone":"+1 305 553 7254",
    "sg:postcode":"33175",
    "sg:province":"FL",
    "sg:tags":[
        "merchandise"
    ],
    "wof:name":"Windscapes",
    "wof:placetype":"venue"
},
  "geometry": {"coordinates":[-80.40410900000001,25.71892],"type":"Point"}
}