{
  "type": "Feature",
  "properties": {
    "addr:full":"13735 Bellamy Brothers Blvd Dade City FL 33525",
    "addr:housenumber":"13735",
    "addr:postcode":"33525",
    "addr:street":"Bellamy Brothers Blvd",
    "iso:country":"US",
    "sg:address":"13735 Bellamy Brothers Blvd",
    "sg:city":"Dade City",
    "sg:classifiers":[
        {
            "category":"Building & Trades",
            "subcategory":"Construction",
            "type":"Services"
        },
        {
            "category":"Home & Garden",
            "subcategory":"Carpets & Floor Coverings",
            "type":"Retail Goods"
        }
    ],
    "sg:phone":"+1 352 588 2662",
    "sg:postcode":"33525",
    "sg:province":"FL",
    "sg:tags":[
        "material",
        "contractor"
    ],
    "wof:name":"Scaife Enterprises Inc",
    "wof:placetype":"venue"
},
  "geometry": {"coordinates":[-82.358153,28.360628],"type":"Point"}
}