{
  "type": "Feature",
  "properties": {
    "addr:full":"5008 34th St S St Petersburg FL 33711",
    "addr:housenumber":"5008",
    "addr:postcode":"33711",
    "addr:street":"34Th St S",
    "iso:country":"US",
    "sg:address":"5008 34th St S",
    "sg:city":"St Petersburg",
    "sg:classifiers":[
        {
            "category":"Utilities",
            "subcategory":"Mobile Phone",
            "type":"Services"
        }
    ],
    "sg:phone":"+1 727 867 9464",
    "sg:postcode":"33711",
    "sg:province":"FL",
    "sg:tags":[
        "repair",
        "beeper"
    ],
    "wof:name":"Beepers 'n Phones Inc",
    "wof:placetype":"venue"
},
  "geometry": {"coordinates":[-82.679185,27.719229],"type":"Point"}
}