{
  "type": "Feature",
  "properties": {
    "addr:full":"7333 NW 66th St Miami FL 33166",
    "addr:housenumber":"7333",
    "addr:postcode":"33166",
    "addr:street":"Nw 66Th St",
    "iso:country":"US",
    "sg:address":"7333 NW 66th St",
    "sg:city":"Miami",
    "sg:classifiers":[
        {
            "category":"Home & Garden",
            "subcategory":"Furniture",
            "type":"Retail Goods"
        }
    ],
    "sg:phone":"+1 305 885 5858",
    "sg:postcode":"33166",
    "sg:province":"FL",
    "sg:tags":[
        "equipment",
        "kitchen",
        "cabinet"
    ],
    "wof:name":"Alpha Designs Woodwork Inc",
    "wof:placetype":"venue"
},
  "geometry": {"coordinates":[-80.316163,25.83352],"type":"Point"}
}