{
  "type": "Feature",
  "properties": {
    "iso:country":"US",
    "sg:address":"110 E Tarpon Ave",
    "sg:city":"Tarpon Springs",
    "sg:classifiers":[
        {
            "category":"Restaurant",
            "type":"Food & Drink"
        }
    ],
    "sg:menulink":"http://www.allmenus.com/fl/tarpon-springs/34860-dcs-downtown/menu/",
    "sg:phone":"+1 727 942 1900",
    "sg:postcode":"34689",
    "sg:province":"FL",
    "sg:tags":[
        "american"
    ],
    "wof:name":"D.C.'s Downtown",
    "wof:placetype":"venue"
},
  "geometry": {"coordinates":[-82.75579500000001,28.146232],"type":"Point"}
}