{
  "type": "Feature",
  "properties": {
    "iso:country":"US",
    "sg:address":"701 93rd Ave N",
    "sg:city":"Naples",
    "sg:classifiers":[
        {
            "category":"Professional",
            "subcategory":"Management & Consulting",
            "type":"Services"
        }
    ],
    "sg:phone":"+1 239 592 5282",
    "sg:postcode":"34108",
    "sg:province":"FL",
    "sg:tags":[
        "break",
        "coffee",
        "supply"
    ],
    "wof:name":"Collier Coffee Svc",
    "wof:placetype":"venue"
},
  "geometry": {"coordinates":[-81.80507299999999,26.256134],"type":"Point"}
}