{
  "type": "Feature",
  "properties": {
    "iso:country":"US",
    "sg:address":"809 E Bloomingdale Ave #391",
    "sg:city":"Brandon",
    "sg:classifiers":[
        {
            "category":"Shopping",
            "subcategory":"Bicycles & Sporting Goods",
            "type":"Retail Goods"
        }
    ],
    "sg:phone":"+1 813 528 0509",
    "sg:postcode":"33511",
    "sg:province":"FL",
    "sg:tags":[
        "equipment",
        "supply",
        "archery"
    ],
    "sg:website":"http://www.archeryetc.com",
    "wof:name":"Archery Etc LLC",
    "wof:placetype":"venue"
},
  "geometry": {"coordinates":[-82.27120499999999,27.893662],"type":"Point"}
}