{
  "type": "Feature",
  "properties": {
    "addr:full":"2461 Greer Rd Tallahassee FL 32308",
    "addr:housenumber":"2461",
    "addr:postcode":"32308",
    "addr:street":"Greer Rd",
    "iso:country":"US",
    "sg:address":"2461 Greer Rd",
    "sg:city":"Tallahassee",
    "sg:classifiers":[
        {
            "category":"Retail",
            "subcategory":"Auto Repair",
            "type":"Services"
        }
    ],
    "sg:phone":"+1 850 386 6133",
    "sg:postcode":"32308",
    "sg:province":"FL",
    "sg:tags":[
        "automotive"
    ],
    "wof:name":"Ray Gordon Brake Service",
    "wof:placetype":"venue"
},
  "geometry": {"coordinates":[-84.236694,30.485268],"type":"Point"}
}