{
  "type": "Feature",
  "properties": {
    "iso:country":"US",
    "sg:address":"705 Leeland Heights Blvd E",
    "sg:city":"Lehigh Acres",
    "sg:classifiers":[
        {
            "category":"Social Services",
            "subcategory":"Child Care",
            "type":"Services"
        },
        {
            "category":"Organizations",
            "subcategory":"Religious Organization",
            "type":"Services"
        }
    ],
    "sg:phone":"+1 239 369 1361",
    "sg:postcode":"33936",
    "sg:province":"FL",
    "sg:tags":[
        "day",
        "church"
    ],
    "wof:name":"Learning Village",
    "wof:placetype":"venue"
},
  "geometry": {"coordinates":[-81.61927,26.603293],"type":"Point"}
}