{
  "type": "Feature",
  "properties": {
    "iso:country":"US",
    "sg:address":"13 Eloise Cir",
    "sg:city":"Ormond Beach",
    "sg:classifiers":[
        {
            "category":"Professional",
            "subcategory":"Employment Agencies",
            "type":"Services"
        }
    ],
    "sg:phone":"+1 386 441 8994",
    "sg:postcode":"32176",
    "sg:province":"FL",
    "wof:name":"Aceto Associates",
    "wof:placetype":"venue"
},
  "geometry": {"coordinates":[-81.08251300000001,29.374452],"type":"Point"}
}