{
  "type": "Feature",
  "properties": {
    "addr:full":"2800 SW 4th Ave Fort Lauderdale FL 33315",
    "addr:housenumber":"2800",
    "addr:postcode":"33315",
    "addr:street":"Sw 4Th Ave",
    "iso:country":"US",
    "sg:address":"2800 SW 4th Ave",
    "sg:city":"Fort Lauderdale",
    "sg:classifiers":[
        {
            "category":"Wholesale",
            "subcategory":"Tobacco Products",
            "type":"Manufacturing & Wholesale Goods"
        }
    ],
    "sg:phone":"+1 954 828 9201",
    "sg:postcode":"33315",
    "sg:province":"FL",
    "sg:tags":[
        "cigarette",
        "cigar",
        "dealer"
    ],
    "wof:name":"Third Millennium Tobacco",
    "wof:placetype":"venue"
},
  "geometry": {"coordinates":[-80.146542,26.085316],"type":"Point"}
}