{
  "type": "Feature",
  "properties": {
    "iso:country":"US",
    "sg:address":"211 Shore Dr E",
    "sg:city":"Oldsmar",
    "sg:classifiers":[
        {
            "category":"Wholesale",
            "subcategory":"Non-durable Goods",
            "type":"Manufacturing & Wholesale Goods"
        }
    ],
    "sg:phone":"+1 813 855 0083",
    "sg:postcode":"34677",
    "sg:province":"FL",
    "sg:tags":[
        "florist",
        "supply"
    ],
    "wof:name":"Lew Sokols Flowers Distributor",
    "wof:placetype":"venue"
},
  "geometry": {"coordinates":[-82.664731,28.030613],"type":"Point"}
}