{
  "type": "Feature",
  "properties": {
    "iso:country":"US",
    "sg:address":"533 Garden St",
    "sg:city":"Titusville",
    "sg:classifiers":[
        {
            "category":"Building & Trades",
            "subcategory":"Construction",
            "type":"Services"
        }
    ],
    "sg:phone":"+1 321 264 1312",
    "sg:postcode":"32796",
    "sg:province":"FL",
    "sg:tags":[
        "sewer",
        "contractor"
    ],
    "wof:name":"Ray Mar & Sons Inc",
    "wof:placetype":"venue"
},
  "geometry": {"coordinates":[-80.811868,28.615301],"type":"Point"}
}