{
  "type": "Feature",
  "properties": {
    "iso:country":"US",
    "sg:address":"104 NE 3rd St",
    "sg:city":"Satellite Beach",
    "sg:classifiers":[
        {
            "category":"Organizations",
            "subcategory":"Religious Organization",
            "type":"Services"
        }
    ],
    "sg:phone":"+1 321 779 4688",
    "sg:postcode":"32937",
    "sg:province":"FL",
    "sg:tags":[
        "church"
    ],
    "wof:name":"Church Of Christ",
    "wof:placetype":"venue"
},
  "geometry": {"coordinates":[-80.60215700000001,28.212209],"type":"Point"}
}