{
  "type": "Feature",
  "properties": {
    "addr:full":"5829 Blanding Blvd Jacksonville FL 32244",
    "addr:housenumber":"5829",
    "addr:postcode":"32244",
    "addr:street":"Blanding Blvd",
    "iso:country":"US",
    "sg:address":"5829 Blanding Blvd",
    "sg:city":"Jacksonville",
    "sg:classifiers":[
        {
            "category":"Organizations",
            "subcategory":"Religious Organization",
            "type":"Services"
        }
    ],
    "sg:phone":"+1 904 778 4875",
    "sg:postcode":"32244",
    "sg:province":"FL",
    "wof:name":"Wesconnett Assembly Of God",
    "wof:placetype":"venue"
},
  "geometry": {"coordinates":[-81.742497,30.243388],"type":"Point"}
}