{
  "type": "Feature",
  "properties": {
    "iso:country":"US",
    "sg:address":"100 Beacom Blvd",
    "sg:city":"Miami",
    "sg:classifiers":[
        {
            "category":"Organizations",
            "subcategory":"Religious Organization",
            "type":"Services"
        }
    ],
    "sg:phone":"+1 305 642 1600",
    "sg:postcode":"33135",
    "sg:province":"FL",
    "sg:website":"www.jewishcuba.org",
    "wof:name":"Jewish Soldiarity",
    "wof:placetype":"venue"
},
  "geometry": {"coordinates":[-80.2323,25.7714],"type":"Point"}
}