{
  "type": "Feature",
  "properties": {
    "iso:country":"US",
    "sg:address":"3021 NW 183rd St",
    "sg:city":"Opa Locka",
    "sg:classifiers":[
        {
            "category":"Professional",
            "subcategory":"Accounting & Tax Preparation",
            "type":"Services"
        }
    ],
    "sg:phone":"+1 305 623 2083",
    "sg:postcode":"33056",
    "sg:province":"FL",
    "sg:tags":[
        "return",
        "filing"
    ],
    "wof:name":"Tax Doctor LLC",
    "wof:placetype":"venue"
},
  "geometry": {"coordinates":[-80.251713,25.940748],"type":"Point"}
}