{
  "type": "Feature",
  "properties": {
    "addr:full":"7750 NW 40th St Hollywood FL 33024",
    "addr:housenumber":"7750",
    "addr:postcode":"33024",
    "addr:street":"Nw 40Th St",
    "iso:country":"US",
    "sg:address":"7750 NW 40th St",
    "sg:city":"Hollywood",
    "sg:classifiers":[
        {
            "category":"Building & Trades",
            "subcategory":"Pest Control",
            "type":"Services"
        }
    ],
    "sg:phone":"+1 954 437 8540",
    "sg:postcode":"33024",
    "sg:province":"FL",
    "wof:name":"Americana Pest Management Co",
    "wof:placetype":"venue"
},
  "geometry": {"coordinates":[-80.24391799999999,26.043341],"type":"Point"}
}