{
  "type": "Feature",
  "properties": {
    "addr:full":"1815 Griffin Rd Dania FL 33004",
    "addr:housenumber":"1815",
    "addr:postcode":"33004",
    "addr:street":"Griffin Rd",
    "iso:country":"US",
    "sg:address":"1815 Griffin Rd",
    "sg:city":"Dania",
    "sg:classifiers":[
        {
            "category":"Professional",
            "subcategory":"Advertising",
            "type":"Services"
        }
    ],
    "sg:phone":"+1 954 761 1600",
    "sg:postcode":"33004",
    "sg:province":"FL",
    "sg:tags":[
        "counselor"
    ],
    "sg:website":"www.starmarkintl.com",
    "wof:name":"Starmark International",
    "wof:placetype":"venue"
},
  "geometry": {"coordinates":[-80.15945600000001,26.063163],"type":"Point"}
}