{
  "type": "Feature",
  "properties": {
    "iso:country":"US",
    "sg:address":"2323 NE 17th Ter",
    "sg:city":"Gainesville",
    "sg:classifiers":[
        {
            "category":"Building & Trades",
            "subcategory":"Electrical",
            "type":"Services"
        }
    ],
    "sg:phone":"+1 352 376 0793",
    "sg:postcode":"32609",
    "sg:province":"FL",
    "sg:tags":[
        "contractor",
        "electrical",
        "electric",
        "general"
    ],
    "wof:name":"Mid-State Electric Co",
    "wof:placetype":"venue"
},
  "geometry": {"coordinates":[-82.303029,29.676644],"type":"Point"}
}