{
  "type": "Feature",
  "properties": {
    "iso:country":"US",
    "sg:address":"8770 SW 72nd St",
    "sg:city":"Miami",
    "sg:classifiers":[
        {
            "category":"Arts & Performance",
            "subcategory":"Music",
            "type":"Entertainment"
        }
    ],
    "sg:phone":"+1 305 661 0679",
    "sg:postcode":"33173",
    "sg:province":"FL",
    "sg:tags":[
        "jockey",
        "disc"
    ],
    "sg:website":"http://www.boogiemangeorge.com",
    "wof:name":"Boogie Man George",
    "wof:placetype":"venue"
},
  "geometry": {"coordinates":[-80.33537699999999,25.702206],"type":"Point"}
}