{
  "type": "Feature",
  "properties": {
    "iso:country":"US",
    "sg:address":"126 E New York Ave",
    "sg:city":"Deland",
    "sg:classifiers":[
        {
            "category":"Cemetery",
            "type":"Public Place"
        },
        {
            "category":"Retail",
            "subcategory":"Funeral Services",
            "type":"Services"
        }
    ],
    "sg:phone":"+1 386 734 4663",
    "sg:postcode":"32724",
    "sg:province":"FL",
    "sg:tags":[
        "crematory",
        "director",
        "casket",
        "plans-pre-arranged",
        "supply"
    ],
    "sg:website":"http://www.allensummerhillfuneralhome.com",
    "wof:name":"Allen Summerhill Funeral Homes & Crematory",
    "wof:placetype":"venue"
},
  "geometry": {"coordinates":[-81.302852,29.028078],"type":"Point"}
}