{
  "type": "Feature",
  "properties": {
    "iso:country":"US",
    "sg:address":"1345 79th Street Cswy",
    "sg:city":"North Bay Village",
    "sg:classifiers":[
        {
            "category":"Autos & Motor Vehicles",
            "subcategory":"Fuel & Gas Station",
            "type":"Retail Goods"
        }
    ],
    "sg:phone":"+1 305 756 0920",
    "sg:postcode":"33141",
    "sg:province":"FL",
    "wof:name":"Nbv Llc",
    "wof:placetype":"venue"
},
  "geometry": {"coordinates":[-80.158728,25.848685],"type":"Point"}
}