{
  "type": "Feature",
  "properties": {
    "addr:full":"6675 114th Ave Largo FL 33773",
    "addr:housenumber":"6675",
    "addr:postcode":"33773",
    "addr:street":"114Th Ave",
    "iso:country":"US",
    "sg:address":"6675 114th Ave",
    "sg:city":"Largo",
    "sg:classifiers":[
        {
            "category":"Retail",
            "subcategory":"Repair Shop",
            "type":"Services"
        },
        {
            "category":"Health Services",
            "subcategory":"Medical Lab",
            "type":"Services"
        }
    ],
    "sg:phone":"+1 727 548 8751",
    "sg:postcode":"33773",
    "sg:province":"FL",
    "sg:tags":[
        "laboratory",
        "dental",
        "refinishing",
        "equipment"
    ],
    "wof:name":"Florida Dental Repair Inc",
    "wof:placetype":"venue"
},
  "geometry": {"coordinates":[-82.73198600000001,27.875593],"type":"Point"}
}