{
  "type": "Feature",
  "properties": {
    "iso:country":"US",
    "sg:address":"303 State Hwy 26",
    "sg:city":"Melrose",
    "sg:classifiers":[
        {
            "category":"Shopping",
            "subcategory":"Used Merchandise",
            "type":"Retail Goods"
        }
    ],
    "sg:phone":"+1 352 475 5771",
    "sg:postcode":"32666",
    "sg:province":"FL",
    "sg:tags":[
        "antique"
    ],
    "wof:name":"East Coast Antiques",
    "wof:placetype":"venue"
},
  "geometry": {"coordinates":[-82.04706899999999,29.709604],"type":"Point"}
}