{
  "type": "Feature",
  "properties": {
    "addr:full":"1118 Wynn Dr Chipley FL 32428",
    "addr:housenumber":"1118",
    "addr:postcode":"32428",
    "addr:street":"Wynn Dr",
    "iso:country":"US",
    "sg:address":"1118 Wynn Dr",
    "sg:city":"Chipley",
    "sg:classifiers":[
        {
            "category":"Professional",
            "type":"Services"
        }
    ],
    "sg:phone":"+1 850 415 6261",
    "sg:postcode":"32428",
    "sg:province":"FL",
    "sg:tags":[
        "transportation"
    ],
    "wof:name":"Wynns Transport",
    "wof:placetype":"venue"
},
  "geometry": {"coordinates":[-85.527496,30.77523],"type":"Point"}
}