{
  "type": "Feature",
  "properties": {
    "iso:country":"US",
    "sg:address":"11400 SW 150th Dr",
    "sg:city":"Miami",
    "sg:classifiers":[
        {
            "category":"Building & Trades",
            "subcategory":"Landscaping Services",
            "type":"Services"
        }
    ],
    "sg:phone":"+1 305 232 4084",
    "sg:postcode":"33176",
    "sg:province":"FL",
    "wof:name":"Otis Mangham",
    "wof:placetype":"venue"
},
  "geometry": {"coordinates":[-80.378304,25.628741],"type":"Point"}
}