{
  "type": "Feature",
  "properties": {
    "addr:full":"12224 Siesta Dr Fort Myers Beach FL 33931",
    "addr:housenumber":"12224",
    "addr:postcode":"33931",
    "addr:street":"Siesta Dr",
    "iso:country":"US",
    "sg:address":"12224 Siesta Dr",
    "sg:city":"Fort Myers Beach",
    "sg:classifiers":[
        {
            "category":"Real Estate",
            "subcategory":"Real Estate Agent",
            "type":"Services"
        }
    ],
    "sg:phone":"+1 239 433 9101",
    "sg:postcode":"33931",
    "sg:province":"FL",
    "wof:name":"Old Pelican Bay",
    "wof:placetype":"venue"
},
  "geometry": {"coordinates":[-81.954843,26.479086],"type":"Point"}
}