{
  "type": "Feature",
  "properties": {
    "addr:full":"10201 W Beaver St Jacksonville FL 32220",
    "addr:housenumber":"10201",
    "addr:postcode":"32220",
    "addr:street":"W Beaver St",
    "iso:country":"US",
    "sg:address":"10201 W Beaver St",
    "sg:city":"Jacksonville",
    "sg:classifiers":[
        {
            "category":"Shopping",
            "subcategory":"Mobile Phones",
            "type":"Retail Goods"
        }
    ],
    "sg:phone":"+1 904 786 8626",
    "sg:postcode":"32220",
    "sg:province":"FL",
    "sg:tags":[
        "home"
    ],
    "wof:name":"Heritage Financial Group",
    "wof:placetype":"venue"
},
  "geometry": {"coordinates":[-81.827519,30.316606],"type":"Point"}
}