{
  "type": "Feature",
  "properties": {
    "iso:country":"US",
    "sg:address":"11653 Countryway Blvd",
    "sg:city":"Tampa",
    "sg:classifiers":[
        {
            "category":"Restaurant",
            "type":"Food & Drink"
        }
    ],
    "sg:phone":"+1 813 855 5178",
    "sg:postcode":"33626",
    "sg:province":"FL",
    "sg:tags":[
        "italian"
    ],
    "wof:name":"Zerillos Italian Grill",
    "wof:placetype":"venue"
},
  "geometry": {"coordinates":[-82.630565,28.06958],"type":"Point"}
}