{
  "type": "Feature",
  "properties": {
    "addr:full":"3485 Gulf Breeze Pkwy Gulf Breeze FL 32563",
    "addr:housenumber":"3485",
    "addr:postcode":"32563",
    "addr:street":"Gulf Breeze Pkwy",
    "iso:country":"US",
    "sg:address":"3485 Gulf Breeze Pkwy",
    "sg:city":"Gulf Breeze",
    "sg:classifiers":[
        {
            "category":"Autos & Motor Vehicles",
            "subcategory":"Boat Sales",
            "type":"Retail Goods"
        }
    ],
    "sg:phone":"+1 850 932 4404",
    "sg:postcode":"32563",
    "sg:province":"FL",
    "sg:tags":[
        "equipment",
        "marine",
        "supply"
    ],
    "wof:name":"West Marine",
    "wof:placetype":"venue"
},
  "geometry": {"coordinates":[-87.073718,30.388616],"type":"Point"}
}