{
  "type": "Feature",
  "properties": {
    "addr:full":"3732 Cleveland Ave Fort Myers FL 33901",
    "addr:housenumber":"3732",
    "addr:postcode":"33901",
    "addr:street":"Cleveland Ave",
    "iso:country":"US",
    "sg:address":"3732 Cleveland Ave",
    "sg:city":"Fort Myers",
    "sg:classifiers":[
        {
            "category":"Restaurant",
            "type":"Food & Drink"
        }
    ],
    "sg:phone":"+1 239 274 3223",
    "sg:postcode":"33901",
    "sg:province":"FL",
    "sg:tags":[
        "thai"
    ],
    "wof:name":"Suriya Thai",
    "wof:placetype":"venue"
},
  "geometry": {"coordinates":[-81.87234100000001,26.608186],"type":"Point"}
}