{
  "type": "Feature",
  "properties": {
    "iso:country":"US",
    "sg:address":"3718 Vineland Rd",
    "sg:city":"Orlando",
    "sg:classifiers":[
        {
            "category":"Shopping",
            "type":"Retail Goods"
        }
    ],
    "sg:phone":"+1 407 423 9011",
    "sg:postcode":"32811",
    "sg:province":"FL",
    "sg:tags":[
        "picture"
    ],
    "wof:name":"Theme Street Pictures",
    "wof:placetype":"venue"
},
  "geometry": {"coordinates":[-81.429793,28.502718],"type":"Point"}
}