{
  "type": "Feature",
  "properties": {
    "iso:country":"US",
    "sg:address":"10314 NW 55th St",
    "sg:city":"Sunrise",
    "sg:classifiers":[
        {
            "category":"Communications",
            "subcategory":"Television Station",
            "type":"Services"
        }
    ],
    "sg:phone":"+1 954 749 1112",
    "sg:postcode":"33351",
    "sg:province":"FL",
    "sg:tags":[
        "broadcast",
        "representative"
    ],
    "wof:name":"Almodovar Broadcasting Corp",
    "wof:placetype":"venue"
},
  "geometry": {"coordinates":[-80.28683700000001,26.192615],"type":"Point"}
}