{
  "type": "Feature",
  "properties": {
    "iso:country":"US",
    "sg:address":"1505 NW 119th St",
    "sg:city":"Miami",
    "sg:classifiers":[
        {
            "category":"Manufacturing",
            "subcategory":"Glass & Minerals",
            "type":"Manufacturing & Wholesale Goods"
        },
        {
            "category":"Retail",
            "subcategory":"Auto Repair",
            "type":"Services"
        }
    ],
    "sg:phone":"+1 305 681 1010",
    "sg:postcode":"33167",
    "sg:province":"FL",
    "sg:tags":[
        "plate",
        "window",
        "glass-auto"
    ],
    "sg:website":"www.cheapoautoglass.com",
    "wof:name":"Cheapo Auto Glass",
    "wof:placetype":"venue"
},
  "geometry": {"coordinates":[-80.2229,25.8832],"type":"Point"}
}