{
  "type": "Feature",
  "properties": {
    "addr:full":"3817 S Dale Mabry Hwy Tampa FL 33611",
    "addr:housenumber":"3817",
    "addr:postcode":"33611",
    "addr:street":"S Dale Mabry Hwy",
    "iso:country":"US",
    "sg:address":"3817 S Dale Mabry Hwy",
    "sg:city":"Tampa",
    "sg:classifiers":[
        {
            "category":"Professional",
            "subcategory":"Business Services",
            "type":"Services"
        }
    ],
    "sg:phone":"+1 813 835 0502",
    "sg:postcode":"33611",
    "sg:province":"FL",
    "sg:tags":[
        "screen",
        "printing",
        "embroidery"
    ],
    "wof:name":"Stitch N Print Specialties",
    "wof:placetype":"venue"
},
  "geometry": {"coordinates":[-82.506236,27.906843],"type":"Point"}
}