{
  "type": "Feature",
  "properties": {
    "addr:full":"12543 Ulmerton Rd Largo FL 33774",
    "addr:housenumber":"12543",
    "addr:postcode":"33774",
    "addr:street":"Ulmerton Rd",
    "iso:country":"US",
    "sg:address":"12543 Ulmerton Rd",
    "sg:city":"Largo",
    "sg:classifiers":[
        {
            "category":"Restaurant",
            "type":"Food & Drink"
        }
    ],
    "sg:phone":"+1 727 517 1845",
    "sg:postcode":"33774",
    "sg:province":"FL",
    "sg:tags":[
        "eating"
    ],
    "wof:name":"Cowboy Jhns Great Amrcn Brbque",
    "wof:placetype":"venue"
},
  "geometry": {"coordinates":[-82.81281,27.883044],"type":"Point"}
}