{
  "type": "Feature",
  "properties": {
    "addr:full":"711 N Hoagland Blvd Kissimmee FL 34741",
    "addr:housenumber":"711",
    "addr:postcode":"34741",
    "addr:street":"N Hoagland Blvd",
    "iso:country":"US",
    "sg:address":"711 N Hoagland Blvd",
    "sg:city":"Kissimmee",
    "sg:classifiers":[
        {
            "category":"Freight",
            "type":"Transportation"
        }
    ],
    "sg:phone":"+1 407 846 9050",
    "sg:postcode":"34741",
    "sg:province":"FL",
    "sg:tags":[
        "general"
    ],
    "wof:name":"Walt Disney World Co",
    "wof:placetype":"venue"
},
  "geometry": {"coordinates":[-81.448595,28.297142],"type":"Point"}
}