{
  "type": "Feature",
  "properties": {
    "iso:country":"US",
    "sg:address":"13650 Metropolis Ave",
    "sg:city":"Fort Myers",
    "sg:classifiers":[
        {
            "category":"Health Services",
            "subcategory":"Health Practitioner",
            "type":"Services"
        }
    ],
    "sg:phone":"+1 239 454 8288",
    "sg:postcode":"33912",
    "sg:province":"FL",
    "sg:tags":[
        "midwife"
    ],
    "wof:name":"Family Birth Center",
    "wof:placetype":"venue"
},
  "geometry": {"coordinates":[-81.85362000000001,26.543109],"type":"Point"}
}