{
  "type": "Feature",
  "properties": {
    "addr:full":"4250 Saint Johns Pkwy Sanford FL 32771",
    "addr:housenumber":"4250",
    "addr:postcode":"32771",
    "addr:street":"Saint Johns Pkwy",
    "iso:country":"US",
    "sg:address":"4250 Saint Johns Pkwy",
    "sg:city":"Sanford",
    "sg:classifiers":[
        {
            "category":"Wholesale",
            "subcategory":"Machinery & Supplies",
            "type":"Manufacturing & Wholesale Goods"
        }
    ],
    "sg:phone":"+1 407 302 0255",
    "sg:postcode":"32771",
    "sg:province":"FL",
    "sg:tags":[
        "machine",
        "financing",
        "tool",
        "wholesaling"
    ],
    "wof:name":"National Equipment Sls Co LLC",
    "wof:placetype":"venue"
},
  "geometry": {"coordinates":[-81.319453,28.803562],"type":"Point"}
}