{
  "type": "Feature",
  "properties": {
    "addr:full":"300 Beverly Pkwy Pensacola FL 32505",
    "addr:housenumber":"300",
    "addr:postcode":"32505",
    "addr:street":"Beverly Pkwy",
    "iso:country":"US",
    "sg:address":"300 Beverly Pkwy",
    "sg:city":"Pensacola",
    "sg:classifiers":[
        {
            "category":"Food & Beverages",
            "subcategory":"Groceries & Convenience Stores",
            "type":"Retail Goods"
        }
    ],
    "sg:phone":"+1 850 434 7389",
    "sg:postcode":"32505",
    "sg:province":"FL",
    "wof:name":"Mikes Petrol",
    "wof:placetype":"venue"
},
  "geometry": {"coordinates":[-87.24916399999999,30.46481],"type":"Point"}
}