{
  "type": "Feature",
  "properties": {
    "iso:country":"US",
    "sg:address":"6803 Mauna Loa Blvd",
    "sg:city":"Sarasota",
    "sg:classifiers":[
        {
            "category":"Building & Trades",
            "subcategory":"Construction",
            "type":"Services"
        }
    ],
    "sg:phone":"+1 941 780 8746",
    "sg:postcode":"34241",
    "sg:province":"FL",
    "sg:tags":[
        "carpentry",
        "contractor"
    ],
    "wof:name":"Ross Chuck F Carpenter",
    "wof:placetype":"venue"
},
  "geometry": {"coordinates":[-82.436401,27.293201],"type":"Point"}
}