{
  "type": "Feature",
  "properties": {
    "addr:full":"210 E Linebaugh Ave Tampa FL 33612",
    "addr:housenumber":"210",
    "addr:postcode":"33612",
    "addr:street":"E Linebaugh Ave",
    "iso:country":"US",
    "sg:address":"210 E Linebaugh Ave",
    "sg:city":"Tampa",
    "sg:classifiers":[
        {
            "category":"Education",
            "subcategory":"School",
            "type":"Public Place"
        }
    ],
    "sg:phone":"+1 813 935 0232",
    "sg:postcode":"33612",
    "sg:province":"FL",
    "wof:name":"Morning Star School",
    "wof:placetype":"venue"
},
  "geometry": {"coordinates":[-82.456563,28.040036],"type":"Point"}
}