{
  "type": "Feature",
  "properties": {
    "iso:country":"US",
    "sg:address":"1145 Belle Meade Isle Dr",
    "sg:city":"Miami",
    "sg:classifiers":[
        {
            "category":"Wholesale",
            "subcategory":"Dairy",
            "type":"Manufacturing & Wholesale Goods"
        }
    ],
    "sg:phone":"+1 305 681 7474",
    "sg:postcode":"33138",
    "sg:province":"FL",
    "sg:tags":[
        "product"
    ],
    "wof:name":"Pierson Distributor Inc",
    "wof:placetype":"venue"
},
  "geometry": {"coordinates":[-80.175072,25.844621],"type":"Point"}
}