{
  "type": "Feature",
  "properties": {
    "addr:full":"1501 W Brandon Blvd Brandon FL 33511",
    "addr:housenumber":"1501",
    "addr:postcode":"33511",
    "addr:street":"W Brandon Blvd",
    "iso:country":"US",
    "sg:address":"1501 W Brandon Blvd",
    "sg:city":"Brandon",
    "sg:classifiers":[
        {
            "category":"Autos & Motor Vehicles",
            "subcategory":"Auto Supplies",
            "type":"Retail Goods"
        }
    ],
    "sg:phone":"+1 813 685 4558",
    "sg:postcode":"33511",
    "sg:province":"FL",
    "sg:tags":[
        "tire"
    ],
    "sg:website":"www.bsf.com",
    "wof:name":"Firestone Tire & Svc Ctr",
    "wof:placetype":"venue"
},
  "geometry": {"coordinates":[-82.30927699999999,27.937756],"type":"Point"}
}