{
  "type": "Feature",
  "properties": {
    "iso:country":"US",
    "sg:address":"13573 42nd Rd N",
    "sg:city":"West Palm Beach",
    "sg:classifiers":[
        {
            "category":"Building & Trades",
            "subcategory":"Construction",
            "type":"Services"
        }
    ],
    "sg:phone":"+1 561 792 0126",
    "sg:postcode":"33411",
    "sg:province":"FL",
    "sg:tags":[
        "contractor"
    ],
    "wof:name":"Ingram Marble Tile Inc",
    "wof:placetype":"venue"
},
  "geometry": {"coordinates":[-80.256918,26.739519],"type":"Point"}
}