{
  "type": "Feature",
  "properties": {
    "iso:country":"US",
    "sg:address":"6242 W Oakland Park Blvd",
    "sg:city":"Fort Lauderdale",
    "sg:classifiers":[
        {
            "category":"Bars & Pubs",
            "type":"Food & Drink"
        }
    ],
    "sg:phone":"+1 954 742 3344",
    "sg:postcode":"33313",
    "sg:province":"FL",
    "sg:tags":[
        "drinking",
        "eating"
    ],
    "wof:name":"Banana Boat",
    "wof:placetype":"venue"
},
  "geometry": {"coordinates":[-80.23159,26.164842],"type":"Point"}
}