{
  "type": "Feature",
  "properties": {
    "iso:country":"US",
    "sg:address":"410 Somerset Way",
    "sg:city":"Fort Lauderdale",
    "sg:classifiers":[
        {
            "category":"Manufacturing",
            "subcategory":"Signs",
            "type":"Manufacturing & Wholesale Goods"
        }
    ],
    "sg:phone":"+1 954 385 1733",
    "sg:postcode":"33326",
    "sg:province":"FL",
    "sg:tags":[
        "specialty",
        "mfg"
    ],
    "wof:name":"Amazing Signs/Grphcs",
    "wof:placetype":"venue"
},
  "geometry": {"coordinates":[-80.389764,26.11387],"type":"Point"}
}