{
  "type": "Feature",
  "properties": {
    "addr:full":"9020 Silver Oak Ln Tallahassee FL 32311",
    "addr:housenumber":"9020",
    "addr:postcode":"32311",
    "addr:street":"Silver Oak Ln",
    "iso:country":"US",
    "sg:address":"9020 Silver Oak Ln",
    "sg:city":"Tallahassee",
    "sg:classifiers":[
        {
            "category":"Wholesale",
            "subcategory":"Electrical",
            "type":"Manufacturing & Wholesale Goods"
        }
    ],
    "sg:phone":"+1 850 878 0896",
    "sg:postcode":"32311",
    "sg:province":"FL",
    "sg:tags":[
        "alarm",
        "burglar",
        "system"
    ],
    "wof:name":"Alliance Security",
    "wof:placetype":"venue"
},
  "geometry": {"coordinates":[-84.12278499999999,30.38018],"type":"Point"}
}