{
  "type": "Feature",
  "properties": {
    "addr:full":"1813 Rising Sun Dr Holiday FL 34690",
    "addr:housenumber":"1813",
    "addr:postcode":"34690",
    "addr:street":"Rising Sun Dr",
    "iso:country":"US",
    "sg:address":"1813 Rising Sun Dr",
    "sg:city":"Holiday",
    "sg:classifiers":[
        {
            "category":"Education",
            "subcategory":"Junior College",
            "type":"Public Place"
        }
    ],
    "sg:phone":"+1 727 937 0855",
    "sg:postcode":"34690",
    "sg:province":"FL",
    "sg:tags":[
        "doll"
    ],
    "wof:name":"Tap 'N Dolls",
    "wof:placetype":"venue"
},
  "geometry": {"coordinates":[-82.734779,28.185309],"type":"Point"}
}