{
  "type": "Feature",
  "properties": {
    "addr:full":"31602 Singletary Rd Myakka City FL 34251",
    "addr:postcode":"31602;34251",
    "addr:street":"Singletary Rd",
    "iso:country":"US",
    "sg:address":"31602 Singletary Rd",
    "sg:city":"Myakka City",
    "sg:classifiers":[
        {
            "category":"Building & Trades",
            "subcategory":"Construction",
            "type":"Services"
        },
        {
            "category":"Retail",
            "subcategory":"Auto Repair",
            "type":"Services"
        }
    ],
    "sg:phone":"+1 941 322 1985",
    "sg:postcode":"34251",
    "sg:province":"FL",
    "sg:tags":[
        "water",
        "automobile",
        "well",
        "drilling",
        "repairing"
    ],
    "wof:name":"A1 Well Drilling & Pump Repair",
    "wof:placetype":"venue"
},
  "geometry": {"coordinates":[-82.21800399999999,27.344845],"type":"Point"}
}