{
  "type": "Feature",
  "properties": {
    "iso:country":"US",
    "sg:address":"1478 Santa Clara Dr",
    "sg:city":"Dunedin",
    "sg:classifiers":[
        {
            "category":"Retail",
            "subcategory":"Laundry & Dry Cleaning",
            "type":"Services"
        }
    ],
    "sg:phone":"+1 727 733 3259",
    "sg:postcode":"34698",
    "sg:province":"FL",
    "sg:tags":[
        "drycleaning",
        "plant"
    ],
    "wof:name":"Tabor Cleaners Inc",
    "wof:placetype":"venue"
},
  "geometry": {"coordinates":[-82.775037,28.025423],"type":"Point"}
}