{
  "type": "Feature",
  "properties": {
    "iso:country":"US",
    "sg:address":"1326 SW Biltmore St",
    "sg:city":"Port St Lucie",
    "sg:classifiers":[
        {
            "category":"Professional",
            "subcategory":"Business Services",
            "type":"Services"
        }
    ],
    "sg:phone":"+1 772 337 3116",
    "sg:postcode":"34983",
    "sg:province":"FL",
    "sg:tags":[
        "diver"
    ],
    "sg:website":"www.sgpinney.com",
    "wof:name":"Underwater Engineering Svc Inc",
    "wof:placetype":"venue"
},
  "geometry": {"coordinates":[-80.36967799999999,27.299448],"type":"Point"}
}