{
  "type": "Feature",
  "properties": {
    "iso:country":"US",
    "sg:address":"2401 Collins Ave",
    "sg:city":"Miami Beach",
    "sg:classifiers":[
        {
            "category":"Retail",
            "subcategory":"Auto Rental",
            "type":"Services"
        }
    ],
    "sg:phone":"+1 305 532 4390",
    "sg:postcode":"33140",
    "sg:province":"FL",
    "sg:tags":[
        "car"
    ],
    "sg:website":"www.nationalcar.com",
    "wof:name":"National Car Rental",
    "wof:placetype":"venue"
},
  "geometry": {"coordinates":[-80.127296,25.8001],"type":"Point"}
}