{
  "type": "Feature",
  "properties": {
    "addr:full":"315 S Palmetto Ave Daytona Beach FL 32114",
    "addr:housenumber":"315",
    "addr:postcode":"32114",
    "addr:street":"S Palmetto Ave",
    "iso:country":"US",
    "sg:address":"315 S Palmetto Ave",
    "sg:city":"Daytona Beach",
    "sg:classifiers":[
        {
            "category":"Professional",
            "subcategory":"Lawyer & Legal Services",
            "type":"Services"
        }
    ],
    "sg:phone":"+1 386 252 7634",
    "sg:postcode":"32114",
    "sg:province":"FL",
    "sg:tags":[
        "abstract",
        "title"
    ],
    "wof:name":"Walter E Foster III",
    "wof:placetype":"venue"
},
  "geometry": {"coordinates":[-81.01910700000001,29.207332],"type":"Point"}
}