{
  "type": "Feature",
  "properties": {
    "addr:full":"2803 Fruitville Rd Sarasota FL 34237",
    "addr:housenumber":"2803",
    "addr:postcode":"34237",
    "addr:street":"Fruitville Rd",
    "iso:country":"US",
    "sg:address":"2803 Fruitville Rd",
    "sg:city":"Sarasota",
    "sg:classifiers":[
        {
            "category":"Professional",
            "subcategory":"Engineering",
            "type":"Services"
        }
    ],
    "sg:phone":"+1 941 954 4036",
    "sg:postcode":"34237",
    "sg:province":"FL",
    "wof:name":"P B S & J",
    "wof:placetype":"venue"
},
  "geometry": {"coordinates":[-82.51205,27.337603],"type":"Point"}
}