{
  "type": "Feature",
  "properties": {
    "iso:country":"US",
    "sg:address":"420 NW 107th St",
    "sg:city":"Miami",
    "sg:classifiers":[
        {
            "category":"Manufacturing",
            "subcategory":"Petroleum Products",
            "type":"Manufacturing & Wholesale Goods"
        },
        {
            "category":"Wholesale",
            "subcategory":"Petroleum",
            "type":"Manufacturing & Wholesale Goods"
        }
    ],
    "sg:phone":"+1 305 751 2470",
    "sg:postcode":"33168",
    "sg:province":"FL",
    "sg:tags":[
        "manufacturer",
        "products-wholesale",
        "oils-petroleum"
    ],
    "wof:name":"Kabir Petroleum Usa Inc.",
    "wof:placetype":"venue"
},
  "geometry": {"coordinates":[-80.20520500000001,25.873006],"type":"Point"}
}