{
  "type": "Feature",
  "properties": {
    "addr:full":"114 Beechwood Ln Palm Coast FL 32137",
    "addr:housenumber":"114",
    "addr:postcode":"32137",
    "addr:street":"Beechwood Ln",
    "iso:country":"US",
    "sg:address":"114 Beechwood Ln",
    "sg:city":"Palm Coast",
    "sg:classifiers":[
        {
            "category":"Real Estate",
            "subcategory":"Real Estate Agent",
            "type":"Services"
        }
    ],
    "sg:phone":"+1 386 446 6429",
    "sg:postcode":"32137",
    "sg:province":"FL",
    "sg:tags":[
        "consultant"
    ],
    "wof:name":"RMF Consulting Svc",
    "wof:placetype":"venue"
},
  "geometry": {"coordinates":[-81.231351,29.555326],"type":"Point"}
}