{
  "type": "Feature",
  "properties": {
    "addr:full":"16040 S Post Rd Fort Lauderdale FL 33331",
    "addr:housenumber":"16040",
    "addr:postcode":"33331",
    "addr:street":"S Post Rd",
    "iso:country":"US",
    "sg:address":"16040 S Post Rd",
    "sg:city":"Fort Lauderdale",
    "sg:classifiers":[
        {
            "category":"Health Services",
            "subcategory":"Clinic",
            "type":"Services"
        }
    ],
    "sg:phone":"+1 954 298 4936",
    "sg:postcode":"33331",
    "sg:province":"FL",
    "sg:tags":[
        "care"
    ],
    "wof:name":"Jose V Coba MD PA",
    "wof:placetype":"venue"
},
  "geometry": {"coordinates":[-80.364514,26.074927],"type":"Point"}
}