{
  "type": "Feature",
  "properties": {
    "iso:country":"US",
    "sg:address":"3309 W Aileen St",
    "sg:city":"Tampa",
    "sg:classifiers":[
        {
            "category":"Real Estate",
            "subcategory":"Real Estate Services",
            "type":"Services"
        },
        {
            "category":"Professional",
            "subcategory":"Research",
            "type":"Services"
        }
    ],
    "sg:phone":"+1 813 263 9805",
    "sg:postcode":"33607",
    "sg:province":"FL",
    "sg:tags":[
        "abstracter",
        "title"
    ],
    "wof:name":"Universal Title Examiners",
    "wof:placetype":"venue"
},
  "geometry": {"coordinates":[-82.497444,27.96819],"type":"Point"}
}