{
  "type": "Feature",
  "properties": {
    "addr:full":"8323 NW 12th St Doral FL 33126",
    "addr:housenumber":"8323",
    "addr:postcode":"33126",
    "addr:street":"Nw 12Th St",
    "iso:country":"US",
    "sg:address":"8323 NW 12th St",
    "sg:city":"Doral",
    "sg:classifiers":[
        {
            "category":"Real Estate",
            "subcategory":"Architect",
            "type":"Services"
        }
    ],
    "sg:phone":"+1 305 592 1363",
    "sg:postcode":"33126",
    "sg:province":"FL",
    "wof:name":"Perez Pascual & Assoc",
    "wof:placetype":"venue"
},
  "geometry": {"coordinates":[-80.33457,25.783434],"type":"Point"}
}