{
  "type": "Feature",
  "properties": {
    "iso:country":"US",
    "sg:address":"3125 Ellis Dr",
    "sg:city":"Melbourne",
    "sg:classifiers":[
        {
            "category":"Wholesale",
            "subcategory":"Auto Parts",
            "type":"Manufacturing & Wholesale Goods"
        }
    ],
    "sg:phone":"+1 321 543 1235",
    "sg:postcode":"32904",
    "sg:province":"FL",
    "sg:tags":[
        "automotive",
        "tool"
    ],
    "wof:name":"Dennis Coulter",
    "wof:placetype":"venue"
},
  "geometry": {"coordinates":[-80.67314399999999,28.042207],"type":"Point"}
}