{
  "type": "Feature",
  "properties": {
    "iso:country":"US",
    "sg:address":"2175 Tamiami Trl",
    "sg:city":"Venice",
    "sg:classifiers":[
        {
            "category":"Professional",
            "subcategory":"Employment Agencies",
            "type":"Services"
        }
    ],
    "sg:phone":"+1 941 966 6441",
    "sg:postcode":"34293",
    "sg:province":"FL",
    "sg:tags":[
        "consultant",
        "search",
        "executive"
    ],
    "wof:name":"F-O-R-T-U-N-E Personnel CNSLTS",
    "wof:placetype":"venue"
},
  "geometry": {"coordinates":[-82.410571,27.054259],"type":"Point"}
}