{
  "type": "Feature",
  "properties": {
    "iso:country":"US",
    "sg:address":"489 Valparaiso Pkwy",
    "sg:city":"Valparaiso",
    "sg:classifiers":[
        {
            "category":"Building & Trades",
            "subcategory":"Landscaping Services",
            "type":"Services"
        }
    ],
    "sg:phone":"+1 850 897 4257",
    "sg:postcode":"32580",
    "sg:province":"FL",
    "sg:tags":[
        "landscape",
        "contractor"
    ],
    "sg:website":"www.bayoulawn.com",
    "wof:name":"Bayou Lawn & Landscape Svc",
    "wof:placetype":"venue"
},
  "geometry": {"coordinates":[-86.49974,30.509758],"type":"Point"}
}