{
  "type": "Feature",
  "properties": {
    "addr:full":"7591 Southwick St Orlando FL 32818",
    "addr:housenumber":"7591",
    "addr:postcode":"32818",
    "addr:street":"Southwick St",
    "iso:country":"US",
    "sg:address":"7591 Southwick St",
    "sg:city":"Orlando",
    "sg:classifiers":[
        {
            "category":"Shopping",
            "subcategory":"Gifts & Souvenirs",
            "type":"Retail Goods"
        }
    ],
    "sg:phone":"+1 407 297 9738",
    "sg:postcode":"32818",
    "sg:province":"FL",
    "sg:tags":[
        "shop",
        "novelty"
    ],
    "wof:name":"House of Ireland & Company Inc",
    "wof:placetype":"venue"
},
  "geometry": {"coordinates":[-81.485968,28.575428],"type":"Point"}
}