{
  "type": "Feature",
  "properties": {
    "iso:country":"US",
    "sg:address":"4427 Exchange Ave",
    "sg:city":"Naples",
    "sg:classifiers":[
        {
            "category":"Autos & Motor Vehicles",
            "subcategory":"Automobile Sales",
            "type":"Retail Goods"
        }
    ],
    "sg:phone":"+1 239 643 6601",
    "sg:postcode":"34104",
    "sg:province":"FL",
    "sg:tags":[
        "car",
        "dealer"
    ],
    "wof:name":"Collier Motors",
    "wof:placetype":"venue"
},
  "geometry": {"coordinates":[-81.756164,26.158915],"type":"Point"}
}