{
  "type": "Feature",
  "properties": {
    "addr:full":"12 Andros Ln Sebastian FL 32958",
    "addr:housenumber":"12",
    "addr:postcode":"32958",
    "addr:street":"Andros Ln",
    "iso:country":"US",
    "sg:address":"12 Andros Ln",
    "sg:city":"Sebastian",
    "sg:classifiers":[
        {
            "category":"Building & Trades",
            "subcategory":"Pest Control",
            "type":"Services"
        }
    ],
    "sg:phone":"+1 772 388 4573",
    "sg:postcode":"32958",
    "sg:province":"FL",
    "wof:name":"Action Environmental Svc",
    "wof:placetype":"venue"
},
  "geometry": {"coordinates":[-80.452741,27.769159],"type":"Point"}
}