{
  "type": "Feature",
  "properties": {
    "iso:country":"US",
    "sg:address":"11007 SE 66th Ter",
    "sg:city":"Belleview",
    "sg:classifiers":[
        {
            "category":"Restaurant",
            "type":"Food & Drink"
        }
    ],
    "sg:phone":"+1 352 347 7909",
    "sg:postcode":"34420",
    "sg:province":"FL",
    "wof:name":"Cal's Place",
    "wof:placetype":"venue"
},
  "geometry": {"coordinates":[-82.04164900000001,29.062111],"type":"Point"}
}