{
  "type": "Feature",
  "properties": {
    "addr:full":"6051 N Wickham Rd Melbourne FL 32940",
    "addr:housenumber":"6051",
    "addr:postcode":"32940",
    "addr:street":"N Wickham Rd",
    "iso:country":"US",
    "sg:address":"6051 N Wickham Rd",
    "sg:city":"Melbourne",
    "sg:classifiers":[
        {
            "category":"Building & Trades",
            "subcategory":"Construction",
            "type":"Services"
        }
    ],
    "sg:phone":"+1 321 757 9222",
    "sg:postcode":"32940",
    "sg:province":"FL",
    "sg:tags":[
        "contractor"
    ],
    "wof:name":"Frank Butler Inc",
    "wof:placetype":"venue"
},
  "geometry": {"coordinates":[-80.673231,28.215521],"type":"Point"}
}