{
  "type": "Feature",
  "properties": {
    "addr:full":"28425 Highgate Dr Bonita Springs FL 34135",
    "addr:housenumber":"28425",
    "addr:postcode":"34135",
    "addr:street":"Highgate Dr",
    "iso:country":"US",
    "sg:address":"28425 Highgate Dr",
    "sg:city":"Bonita Springs",
    "sg:classifiers":[
        {
            "category":"Professional",
            "subcategory":"Business Services",
            "type":"Services"
        }
    ],
    "sg:phone":"+1 239 495 8817",
    "sg:postcode":"34135",
    "sg:province":"FL",
    "sg:tags":[
        "messenger"
    ],
    "wof:name":"Hot Line Courier Svc",
    "wof:placetype":"venue"
},
  "geometry": {"coordinates":[-81.79155799999999,26.322091],"type":"Point"}
}