{
  "type": "Feature",
  "properties": {
    "iso:country":"US",
    "sg:address":"129 Wisteria Dr",
    "sg:city":"Longwood",
    "sg:classifiers":[
        {
            "category":"Banks & Credit Unions",
            "subcategory":"Financial Services",
            "type":"Services"
        }
    ],
    "sg:phone":"+1 407 786 0413",
    "sg:postcode":"32779",
    "sg:province":"FL",
    "sg:tags":[
        "trust",
        "management"
    ],
    "wof:name":"Big Cypress Associates Ltd",
    "wof:placetype":"venue"
},
  "geometry": {"coordinates":[-81.401928,28.699317],"type":"Point"}
}