{
  "type": "Feature",
  "properties": {
    "iso:country":"US",
    "sg:address":"1651 W 37th St",
    "sg:city":"Hialeah",
    "sg:classifiers":[
        {
            "category":"Manufacturing",
            "subcategory":"Furniture",
            "type":"Manufacturing & Wholesale Goods"
        }
    ],
    "sg:phone":"+1 305 819 5070",
    "sg:postcode":"33012",
    "sg:province":"FL",
    "sg:tags":[
        "manufacture",
        "blind"
    ],
    "wof:name":"Miami Deco Group Inc",
    "wof:placetype":"venue"
},
  "geometry": {"coordinates":[-80.31766,25.855348],"type":"Point"}
}