{
  "type": "Feature",
  "properties": {
    "iso:country":"US",
    "sg:address":"18330 NE 2nd Ave",
    "sg:city":"Miami",
    "sg:classifiers":[
        {
            "category":"Food & Beverages",
            "subcategory":"Bakery",
            "type":"Retail Goods"
        }
    ],
    "sg:phone":"+1 305 493 3922",
    "sg:postcode":"33179",
    "sg:province":"FL",
    "sg:tags":[
        "baker"
    ],
    "wof:name":"Pines Bakery Corp",
    "wof:placetype":"venue"
},
  "geometry": {"coordinates":[-80.19695900000001,25.945371],"type":"Point"}
}