{
  "type": "Feature",
  "properties": {
    "iso:country":"US",
    "sg:address":"642 NW Buck Hendry Way",
    "sg:city":"Stuart",
    "sg:classifiers":[
        {
            "category":"Building & Trades",
            "subcategory":"Construction",
            "type":"Services"
        }
    ],
    "sg:phone":"+1 772 692 2040",
    "sg:postcode":"34994",
    "sg:province":"FL",
    "sg:tags":[
        "excavating",
        "contractor"
    ],
    "wof:name":"Evergreen Land Svc Inc",
    "wof:placetype":"venue"
},
  "geometry": {"coordinates":[-80.261449,27.224419],"type":"Point"}
}