{
  "type": "Feature",
  "properties": {
    "iso:country":"US",
    "sg:address":"500 S Dixie Hwy",
    "sg:city":"Hallandale",
    "sg:classifiers":[
        {
            "category":"Wholesale",
            "subcategory":"Non-durable Goods",
            "type":"Manufacturing & Wholesale Goods"
        }
    ],
    "sg:phone":"+1 954 458 2334",
    "sg:postcode":"33009",
    "sg:province":"FL",
    "sg:tags":[
        "company",
        "advertising",
        "specialty"
    ],
    "wof:name":"Lehman Advertising & Ad Spc",
    "wof:placetype":"venue"
},
  "geometry": {"coordinates":[-80.148185,25.979037],"type":"Point"}
}