{
  "type": "Feature",
  "properties": {
    "iso:country":"US",
    "sg:address":"7797 N University Dr",
    "sg:city":"Tamarac",
    "sg:classifiers":[
        {
            "category":"Professional",
            "subcategory":"Lawyer & Legal Services",
            "type":"Services"
        }
    ],
    "sg:phone":"+1 954 722 6566",
    "sg:postcode":"33321",
    "sg:province":"FL",
    "sg:tags":[
        "attorney",
        "law",
        "family",
        "divorce",
        "child",
        "criminal",
        "custody"
    ],
    "sg:website":"http://www.zjblaw.com",
    "wof:name":"Zimmerman Joseph & Bayne PA",
    "wof:placetype":"venue"
},
  "geometry": {"coordinates":[-80.252731,26.218429],"type":"Point"}
}