{
  "type": "Feature",
  "properties": {
    "iso:country":"US",
    "sg:address":"1957 Allison Ave",
    "sg:city":"Panama City",
    "sg:classifiers":[
        {
            "category":"Travel",
            "subcategory":"Campground",
            "type":"Entertainment"
        }
    ],
    "sg:phone":"+1 850 235 0924",
    "sg:postcode":"32408",
    "sg:province":"FL",
    "sg:tags":[
        "trailer"
    ],
    "wof:name":"Emerald Coast Rv Beach Resort",
    "wof:placetype":"venue"
},
  "geometry": {"coordinates":[-85.786597,30.182871],"type":"Point"}
}