{
  "type": "Feature",
  "properties": {
    "iso:country":"US",
    "sg:address":"3119 SW 20th Ter",
    "sg:city":"Delray Beach",
    "sg:classifiers":[
        {
            "category":"Real Estate",
            "subcategory":"Real Estate Agent",
            "type":"Services"
        },
        {
            "category":"Real Estate",
            "subcategory":"Real Estate Operator",
            "type":"Services"
        }
    ],
    "sg:phone":"+1 561 272 5240",
    "sg:postcode":"33445",
    "sg:province":"FL",
    "sg:tags":[
        "condominium"
    ],
    "wof:name":"Delray Oaks Condominium Assoc",
    "wof:placetype":"venue"
},
  "geometry": {"coordinates":[-80.092994,26.42636],"type":"Point"}
}