{
  "type": "Feature",
  "properties": {
    "addr:full":"552 Arthur Godfrey Rd Miami Beach FL 33140",
    "addr:housenumber":"552",
    "addr:postcode":"33140",
    "addr:street":"Arthur Godfrey Rd",
    "iso:country":"US",
    "sg:address":"552 Arthur Godfrey Rd",
    "sg:city":"Miami Beach",
    "sg:classifiers":[
        {
            "category":"Shopping",
            "subcategory":"Optical Goods",
            "type":"Retail Goods"
        }
    ],
    "sg:phone":"+1 305 534 2288",
    "sg:postcode":"33140",
    "sg:province":"FL",
    "sg:tags":[
        "optician",
        "dispensing",
        "eyewear"
    ],
    "wof:name":"Eyeglass Emporium",
    "wof:placetype":"venue"
},
  "geometry": {"coordinates":[-80.130402,25.813999],"type":"Point"}
}