{
  "type": "Feature",
  "properties": {
    "addr:full":"4406 Guerlain Way Pensacola FL 32505",
    "addr:housenumber":"4406",
    "addr:postcode":"32505",
    "addr:street":"Guerlain Way",
    "iso:country":"US",
    "sg:address":"4406 Guerlain Way",
    "sg:city":"Pensacola",
    "sg:classifiers":[
        {
            "category":"Shopping",
            "subcategory":"Clothing, Apparel, & Fashions",
            "type":"Retail Goods"
        }
    ],
    "sg:phone":"+1 850 437 1245",
    "sg:postcode":"32505",
    "sg:province":"FL",
    "wof:name":"Behind Closed Doors",
    "wof:placetype":"venue"
},
  "geometry": {"coordinates":[-87.264955,30.454332],"type":"Point"}
}