{
  "type": "Feature",
  "properties": {
    "addr:full":"5941 Berryhill Rd Milton FL 32570",
    "addr:housenumber":"5941",
    "addr:postcode":"32570",
    "addr:street":"Berryhill Rd",
    "iso:country":"US",
    "sg:address":"5941 Berryhill Rd",
    "sg:city":"Milton",
    "sg:classifiers":[
        {
            "category":"Insurance",
            "subcategory":"Hazard Insurance",
            "type":"Services"
        },
        {
            "category":"Insurance",
            "subcategory":"Health Insurance",
            "type":"Services"
        }
    ],
    "sg:phone":"+1 850 623 3299",
    "sg:postcode":"32570",
    "sg:province":"FL",
    "wof:name":"Aflac",
    "wof:placetype":"venue"
},
  "geometry": {"coordinates":[-87.070464,30.633735],"type":"Point"}
}