{
  "type": "Feature",
  "properties": {
    "addr:full":"8434 Magnolia Dr Largo FL 33777",
    "addr:housenumber":"8434",
    "addr:postcode":"33777",
    "addr:street":"Magnolia Dr",
    "iso:country":"US",
    "sg:address":"8434 Magnolia Dr",
    "sg:city":"Largo",
    "sg:classifiers":[
        {
            "category":"Manufacturing",
            "subcategory":"Tools & Machinery",
            "type":"Manufacturing & Wholesale Goods"
        }
    ],
    "sg:phone":"+1 727 398 3405",
    "sg:postcode":"33777",
    "sg:province":"FL",
    "sg:tags":[
        "lift",
        "boat"
    ],
    "wof:name":"Bay Davit & Lift Svc & Repair",
    "wof:placetype":"venue"
},
  "geometry": {"coordinates":[-82.756371,27.851696],"type":"Point"}
}