{
  "type": "Feature",
  "properties": {
    "iso:country":"US",
    "sg:address":"14111 Mossy Glen Ln",
    "sg:city":"Tampa",
    "sg:classifiers":[
        {
            "category":"Food & Beverages",
            "subcategory":"Candy",
            "type":"Retail Goods"
        }
    ],
    "sg:phone":"+1 813 977 1634",
    "sg:postcode":"33613",
    "sg:province":"FL",
    "wof:name":"William G Fudge Jr",
    "wof:placetype":"venue"
},
  "geometry": {"coordinates":[-82.4119,28.074872],"type":"Point"}
}