{
  "type": "Feature",
  "properties": {
    "addr:full":"6801 University Blvd Winter Park FL 32792",
    "addr:housenumber":"6801",
    "addr:postcode":"32792",
    "addr:street":"University Blvd",
    "iso:country":"US",
    "sg:address":"6801 University Blvd",
    "sg:city":"Winter Park",
    "sg:classifiers":[
        {
            "category":"Wholesale",
            "subcategory":"Auto Parts",
            "type":"Manufacturing & Wholesale Goods"
        }
    ],
    "sg:phone":"+1 407 677 5444",
    "sg:postcode":"32792",
    "sg:province":"FL",
    "sg:tags":[
        "equipment",
        "truck"
    ],
    "wof:name":"A 1 Dynamic Svc & Supplies",
    "wof:placetype":"venue"
},
  "geometry": {"coordinates":[-81.29483399999999,28.597591],"type":"Point"}
}