{
  "type": "Feature",
  "properties": {
    "iso:country":"US",
    "sg:address":"5107 W Idlewild Ave",
    "sg:city":"Tampa",
    "sg:classifiers":[
        {
            "category":"Transit Center",
            "subcategory":"Freight",
            "type":"Transportation"
        },
        {
            "category":"Government",
            "subcategory":"Post Office",
            "type":"Public Place"
        }
    ],
    "sg:phone":"+1 813 388 0769",
    "sg:postcode":"33634",
    "sg:province":"FL",
    "sg:tags":[
        "cargo",
        "courier",
        "package",
        "express",
        "air",
        "delivery"
    ],
    "wof:name":"Express-It Messenger And Delivery Service Inc",
    "wof:placetype":"venue"
},
  "geometry": {"coordinates":[-82.52754299999999,28.002035],"type":"Point"}
}