{
  "type": "Feature",
  "properties": {
    "addr:full":"6447 Miami Lakes Dr E Hialeah FL 33014",
    "addr:housenumber":"6447",
    "addr:postcode":"33014",
    "addr:street":"Miami Lakes Dr E",
    "iso:country":"US",
    "sg:address":"6447 Miami Lakes Dr E",
    "sg:city":"Hialeah",
    "sg:classifiers":[
        {
            "category":"Real Estate",
            "subcategory":"Real Estate Agent",
            "type":"Services"
        }
    ],
    "sg:phone":"+1 786 621 6626",
    "sg:postcode":"33014",
    "sg:province":"FL",
    "wof:name":"A Plus Unltd Mtg & Real Est",
    "wof:placetype":"venue"
},
  "geometry": {"coordinates":[-80.3039,25.911162],"type":"Point"}
}