{
  "type": "Feature",
  "properties": {
    "iso:country":"US",
    "sg:address":"17310 Williamsburg Dr",
    "sg:city":"Fort Myers",
    "sg:classifiers":[
        {
            "category":"Building & Trades",
            "subcategory":"Construction",
            "type":"Services"
        }
    ],
    "sg:phone":"+1 239 543 6554",
    "sg:postcode":"33917",
    "sg:province":"FL",
    "sg:tags":[
        "house"
    ],
    "wof:name":"All Way Construction Inc",
    "wof:placetype":"venue"
},
  "geometry": {"coordinates":[-81.819998,26.718693],"type":"Point"}
}