{
  "type": "Feature",
  "properties": {
    "addr:full":"4933 Spring Park Rd Jacksonville FL 32207",
    "addr:housenumber":"4933",
    "addr:postcode":"32207",
    "addr:street":"Spring Park Rd",
    "iso:country":"US",
    "sg:address":"4933 Spring Park Rd",
    "sg:city":"Jacksonville",
    "sg:classifiers":[
        {
            "category":"Social Services",
            "type":"Services"
        }
    ],
    "sg:phone":"+1 904 733 6645",
    "sg:postcode":"32207",
    "sg:province":"FL",
    "sg:tags":[
        "organization",
        "welfare"
    ],
    "wof:name":"Pine Castle Residential House",
    "wof:placetype":"venue"
},
  "geometry": {"coordinates":[-81.611407,30.270862],"type":"Point"}
}