{
  "type": "Feature",
  "properties": {
    "addr:full":"804 Greenleaf Dr Tallahassee FL 32305",
    "addr:housenumber":"804",
    "addr:postcode":"32305",
    "addr:street":"Greenleaf Dr",
    "iso:country":"US",
    "sg:address":"804 Greenleaf Dr",
    "sg:city":"Tallahassee",
    "sg:classifiers":[
        {
            "category":"Wholesale",
            "subcategory":"Tobacco Products",
            "type":"Manufacturing & Wholesale Goods"
        }
    ],
    "sg:phone":"+1 850 309 7781",
    "sg:postcode":"32305",
    "sg:province":"FL",
    "sg:tags":[
        "cigarette",
        "cigar",
        "dealer"
    ],
    "wof:name":"Cig & Stop",
    "wof:placetype":"venue"
},
  "geometry": {"coordinates":[-84.271266,30.378456],"type":"Point"}
}