{
  "type": "Feature",
  "properties": {
    "iso:country":"US",
    "sg:address":"74 Pindo Palm St E",
    "sg:city":"Largo",
    "sg:classifiers":[
        {
            "category":"Retail",
            "subcategory":"Funeral Services",
            "type":"Services"
        }
    ],
    "sg:phone":"+1 727 586 5142",
    "sg:postcode":"33770",
    "sg:province":"FL",
    "sg:tags":[
        "burial",
        "vault"
    ],
    "wof:name":"Central Penn Wilbert Vault Works",
    "wof:placetype":"venue"
},
  "geometry": {"coordinates":[-82.791588,27.9058],"type":"Point"}
}