{
  "type": "Feature",
  "properties": {
    "addr:full":"2601 Saint Andrews Blvd Boca Raton FL 33433",
    "addr:housenumber":"2601",
    "addr:postcode":"33433",
    "addr:street":"Saint Andrews Blvd",
    "iso:country":"US",
    "sg:address":"2601 Saint Andrews Blvd",
    "sg:city":"Boca Raton",
    "sg:classifiers":[
        {
            "category":"Education",
            "subcategory":"School",
            "type":"Public Place"
        }
    ],
    "sg:phone":"+1 561 883 0999",
    "sg:postcode":"33433",
    "sg:province":"FL",
    "wof:name":"Institute For Learning Inc",
    "wof:placetype":"venue"
},
  "geometry": {"coordinates":[-80.13751499999999,26.372965],"type":"Point"}
}