{
  "type": "Feature",
  "properties": {
    "iso:country":"US",
    "sg:address":"119 Hales Rd",
    "sg:city":"Auburndale",
    "sg:classifiers":[
        {
            "category":"Wholesale",
            "subcategory":"Metals & Minerals",
            "type":"Manufacturing & Wholesale Goods"
        }
    ],
    "sg:phone":"+1 863 665 7123",
    "sg:postcode":"33823",
    "sg:province":"FL",
    "sg:tags":[
        "aluminum"
    ],
    "wof:name":"Anthony's Aluminum",
    "wof:placetype":"venue"
},
  "geometry": {"coordinates":[-81.841493,28.070666],"type":"Point"}
}