{
  "type": "Feature",
  "properties": {
    "iso:country":"US",
    "sg:address":"5097 University Blvd W",
    "sg:city":"Jacksonville",
    "sg:classifiers":[
        {
            "category":"Bars & Pubs",
            "type":"Food & Drink"
        }
    ],
    "sg:menulink":"http://www.allmenus.com/fl/jacksonville/101380-sonnys-bar-b-q/menu/",
    "sg:phone":"+1 904 737 4906",
    "sg:postcode":"32216",
    "sg:province":"FL",
    "sg:tags":[
        "barbecue",
        "american"
    ],
    "wof:name":"Sonny's Bar-B-Q",
    "wof:placetype":"venue"
},
  "geometry": {"coordinates":[-81.61575000000001,30.267675],"type":"Point"}
}