{
  "type": "Feature",
  "properties": {
    "iso:country":"US",
    "sg:address":"611 9th St W",
    "sg:city":"Bradenton",
    "sg:classifiers":[
        {
            "category":"Wholesale",
            "subcategory":"Electrical",
            "type":"Manufacturing & Wholesale Goods"
        }
    ],
    "sg:phone":"+1 941 750 0531",
    "sg:postcode":"34205",
    "sg:province":"FL",
    "sg:tags":[
        "assembler",
        "electronic",
        "parts"
    ],
    "wof:name":"Discount Radio Parts",
    "wof:placetype":"venue"
},
  "geometry": {"coordinates":[-82.571067,27.493536],"type":"Point"}
}