{
  "type": "Feature",
  "properties": {
    "iso:country":"US",
    "sg:address":"6 N Barbour St",
    "sg:city":"Beverly Hills",
    "sg:classifiers":[
        {
            "category":"Manufacturing",
            "subcategory":"Tools & Machinery",
            "type":"Manufacturing & Wholesale Goods"
        }
    ],
    "sg:phone":"+1 352 527 0493",
    "sg:postcode":"34465",
    "sg:province":"FL",
    "sg:tags":[
        "electric",
        "mfg"
    ],
    "wof:name":"E B Enterprises",
    "wof:placetype":"venue"
},
  "geometry": {"coordinates":[-82.455125,28.928529],"type":"Point"}
}