{
  "type": "Feature",
  "properties": {
    "iso:country":"US",
    "sg:address":"12955 Biscayne Blvd Ste 410",
    "sg:city":"North Miami",
    "sg:classifiers":[
        {
            "category":"Communications",
            "subcategory":"Newspaper",
            "type":"Services"
        }
    ],
    "sg:phone":"+1 305 891 6408",
    "sg:postcode":"33181",
    "sg:province":"FL",
    "sg:tags":[
        "print",
        "medium"
    ],
    "wof:name":"A Rt Nexus",
    "wof:placetype":"venue"
},
  "geometry": {"coordinates":[-80.161697,25.895901],"type":"Point"}
}