{
  "type": "Feature",
  "properties": {
    "addr:full":"6601 Park of Commerce Blvd Boca Raton FL 33487",
    "addr:housenumber":"6601",
    "addr:postcode":"33487",
    "addr:street":"Park;Blvd",
    "iso:country":"US",
    "sg:address":"6601 Park of Commerce Blvd",
    "sg:city":"Boca Raton",
    "sg:classifiers":[
        {
            "category":"Professional",
            "subcategory":"Computer Services",
            "type":"Services"
        }
    ],
    "sg:phone":"+1 561 893 8000",
    "sg:postcode":"33487",
    "sg:province":"FL",
    "sg:tags":[
        "information",
        "retrieval"
    ],
    "wof:name":"Accurint",
    "wof:placetype":"venue"
},
  "geometry": {"coordinates":[-80.096981,26.40719],"type":"Point"}
}