{
  "type": "Feature",
  "properties": {
    "addr:full":"23016 NW 202 St High Springs FL 32643",
    "addr:housenumber":"23016",
    "addr:postcode":"32643",
    "addr:street":"Nw 202 St",
    "iso:country":"US",
    "sg:address":"23016 NW 202 St",
    "sg:city":"High Springs",
    "sg:classifiers":[
        {
            "category":"Professional",
            "subcategory":"Lawyer & Legal Services",
            "type":"Services"
        }
    ],
    "sg:phone":"+1 386 454 7091",
    "sg:postcode":"32643",
    "sg:province":"FL",
    "sg:tags":[
        "attorney"
    ],
    "wof:name":"Rod Helmers",
    "wof:placetype":"venue"
},
  "geometry": {"coordinates":[-82.559556,29.862795],"type":"Point"}
}