{
  "type": "Feature",
  "properties": {
    "addr:full":"2624 Aurora Rd Melbourne FL 32935",
    "addr:housenumber":"2624",
    "addr:postcode":"32935",
    "addr:street":"Aurora Rd",
    "iso:country":"US",
    "sg:address":"2624 Aurora Rd",
    "sg:city":"Melbourne",
    "sg:classifiers":[
        {
            "category":"Building & Trades",
            "subcategory":"Construction",
            "type":"Services"
        }
    ],
    "sg:phone":"+1 321 752 6930",
    "sg:postcode":"32935",
    "sg:province":"FL",
    "sg:tags":[
        "carpenter"
    ],
    "wof:name":"Emeson Stenger Carpentry",
    "wof:placetype":"venue"
},
  "geometry": {"coordinates":[-80.665437,28.135789],"type":"Point"}
}