{
  "type": "Feature",
  "properties": {
    "addr:full":"1180 SW 6th St Miami FL 33130",
    "addr:housenumber":"1180",
    "addr:postcode":"33130",
    "addr:street":"Sw 6Th St",
    "iso:country":"US",
    "sg:address":"1180 SW 6th St",
    "sg:city":"Miami",
    "sg:classifiers":[
        {
            "category":"Personal",
            "subcategory":"Beauty Salon",
            "type":"Services"
        }
    ],
    "sg:phone":"+1 305 859 9487",
    "sg:postcode":"33130",
    "sg:province":"FL",
    "wof:name":"Spice Hair Concepts",
    "wof:placetype":"venue"
},
  "geometry": {"coordinates":[-80.21324799999999,25.767671],"type":"Point"}
}