{
  "type": "Feature",
  "properties": {
    "addr:full":"649 N Primrose Dr Orlando FL 32803",
    "addr:housenumber":"649",
    "addr:postcode":"32803",
    "addr:street":"N Primrose Dr",
    "iso:country":"US",
    "sg:address":"649 N Primrose Dr",
    "sg:city":"Orlando",
    "sg:classifiers":[
        {
            "category":"Restaurant",
            "type":"Food & Drink"
        }
    ],
    "sg:phone":"+1 407 896 5849",
    "sg:postcode":"32803",
    "sg:province":"FL",
    "wof:name":"Golden Thai Incorporated",
    "wof:placetype":"venue"
},
  "geometry": {"coordinates":[-81.34789600000001,28.552308],"type":"Point"}
}