{
  "type": "Feature",
  "properties": {
    "addr:full":"107 W Main St Inverness FL 34452",
    "addr:housenumber":"107",
    "addr:postcode":"34452",
    "addr:street":"W Main St",
    "iso:country":"US",
    "sg:address":"107 W Main St",
    "sg:city":"Inverness",
    "sg:classifiers":[
        {
            "category":"Government",
            "subcategory":"Office",
            "type":"Public Place"
        }
    ],
    "sg:phone":"+1 352 341 0000",
    "sg:postcode":"34452",
    "sg:province":"FL",
    "sg:tags":[
        "armed",
        "force",
        "recruiting"
    ],
    "wof:name":"US Marine Corps Recruiting",
    "wof:placetype":"venue"
},
  "geometry": {"coordinates":[-82.331439,28.835408],"type":"Point"}
}