{
  "type": "Feature",
  "properties": {
    "addr:full":"4000 Central Florida Blvd Orlando FL 32816",
    "addr:housenumber":"4000",
    "addr:postcode":"32816",
    "addr:street":"Central Florida Blvd",
    "iso:country":"US",
    "sg:address":"4000 Central Florida Blvd",
    "sg:city":"Orlando",
    "sg:classifiers":[
        {
            "category":"Banks & Credit Unions",
            "subcategory":"Bank",
            "type":"Services"
        },
        {
            "category":"Banks & Credit Unions",
            "subcategory":"Financial Services",
            "type":"Services"
        }
    ],
    "sg:phone":"+1 407 832 2802",
    "sg:postcode":"32816",
    "sg:province":"FL",
    "sg:tags":[
        "saving",
        "loan",
        "commercial"
    ],
    "sg:website":"https://www.chase.com/",
    "wof:name":"CHASE Bank",
    "wof:placetype":"venue"
},
  "geometry": {"coordinates":[-81.203576,28.597305],"type":"Point"}
}