{
  "type": "Feature",
  "properties": {
    "addr:full":"4131 NW Blitchton Rd Ocala FL 34482",
    "addr:housenumber":"4131",
    "addr:postcode":"34482",
    "addr:street":"Nw Blitchton Rd",
    "iso:country":"US",
    "sg:address":"4131 NW Blitchton Rd",
    "sg:city":"Ocala",
    "sg:classifiers":[
        {
            "category":"Wholesale",
            "subcategory":"Machinery & Supplies",
            "type":"Manufacturing & Wholesale Goods"
        },
        {
            "category":"Autos & Motor Vehicles",
            "subcategory":"Automobile Sales",
            "type":"Retail Goods"
        }
    ],
    "sg:phone":"+1 352 732 8908",
    "sg:postcode":"34482",
    "sg:province":"FL",
    "sg:tags":[
        "horse",
        "pickup",
        "trailer"
    ],
    "sg:website":"www.nelsonstrailers.com",
    "wof:name":"Nelson's Trailer Sales & Svc",
    "wof:placetype":"venue"
},
  "geometry": {"coordinates":[-82.18922999999999,29.20867],"type":"Point"}
}