{
  "type": "Feature",
  "properties": {
    "addr:full":"4343 Henderson Blvd Tampa FL 33629",
    "addr:housenumber":"4343",
    "addr:postcode":"33629",
    "addr:street":"Henderson Blvd",
    "iso:country":"US",
    "sg:address":"4343 Henderson Blvd",
    "sg:city":"Tampa",
    "sg:classifiers":[
        {
            "category":"Health Services",
            "subcategory":"Chiropractor",
            "type":"Services"
        }
    ],
    "sg:phone":"+1 813 254 1881",
    "sg:postcode":"33629",
    "sg:province":"FL",
    "wof:name":"Beytin Clinic of Chiropractic",
    "wof:placetype":"venue"
},
  "geometry": {"coordinates":[-82.51713599999999,27.924138],"type":"Point"}
}