{
  "type": "Feature",
  "properties": {
    "iso:country":"US",
    "sg:address":"1850 NW 82nd Ave",
    "sg:city":"Miami",
    "sg:classifiers":[
        {
            "category":"Freight",
            "type":"Transportation"
        }
    ],
    "sg:phone":"+1 305 477 4144",
    "sg:postcode":"33126",
    "sg:province":"FL",
    "sg:tags":[
        "forwarders"
    ],
    "wof:name":"T T G Intl Frt Forwarders",
    "wof:placetype":"venue"
},
  "geometry": {"coordinates":[-80.328858,25.790669],"type":"Point"}
}