{
  "type": "Feature",
  "properties": {
    "iso:country":"US",
    "sg:address":"14020 S Tamiami Trl",
    "sg:city":"Fort Myers",
    "sg:classifiers":[
        {
            "category":"Autos & Motor Vehicles",
            "subcategory":"Automobile Sales",
            "type":"Retail Goods"
        }
    ],
    "sg:phone":"+1 239 433 8383",
    "sg:postcode":"33912",
    "sg:province":"FL",
    "sg:tags":[
        "car"
    ],
    "sg:website":"www.hondaoffortmyers.com/",
    "wof:name":"Honda of Fort Myers",
    "wof:placetype":"venue"
},
  "geometry": {"coordinates":[-81.87130000000001,26.539],"type":"Point"}
}