{
  "type": "Feature",
  "properties": {
    "iso:country":"US",
    "sg:address":"13770 SW 145th Ct",
    "sg:city":"Miami",
    "sg:classifiers":[
        {
            "category":"Building & Trades",
            "subcategory":"Cleaning & Sanitation",
            "type":"Services"
        }
    ],
    "sg:phone":"+1 305 278 1477",
    "sg:postcode":"33186",
    "sg:province":"FL",
    "sg:tags":[
        "janitor"
    ],
    "wof:name":"Americamaid Cleaning Svc Inc",
    "wof:placetype":"venue"
},
  "geometry": {"coordinates":[-80.43014100000001,25.640253],"type":"Point"}
}