{
  "type": "Feature",
  "properties": {
    "addr:full":"4860 Verona Cir Melbourne FL 32940",
    "addr:housenumber":"4860",
    "addr:postcode":"32940",
    "addr:street":"Verona Cir",
    "iso:country":"US",
    "sg:address":"4860 Verona Cir",
    "sg:city":"Melbourne",
    "sg:classifiers":[
        {
            "category":"Communications",
            "type":"Services"
        },
        {
            "category":"Shopping",
            "subcategory":"Computers & Home Electronics",
            "type":"Retail Goods"
        }
    ],
    "sg:phone":"+1 321 757 7678",
    "sg:postcode":"32940",
    "sg:province":"FL",
    "sg:tags":[
        "sound",
        "television",
        "system",
        "equipment",
        "radio",
        "store"
    ],
    "wof:name":"Romeo HDTV",
    "wof:placetype":"venue"
},
  "geometry": {"coordinates":[-80.66515,28.188181],"type":"Point"}
}