{
  "type": "Feature",
  "properties": {
    "iso:country":"US",
    "sg:address":"200 Lakeshore Blvd",
    "sg:city":"Kissimmee",
    "sg:classifiers":[
        {
            "category":"Organizations",
            "subcategory":"Community Association",
            "type":"Services"
        }
    ],
    "sg:phone":"+1 407 847 4193",
    "sg:postcode":"34741",
    "sg:province":"FL",
    "sg:tags":[
        "military"
    ],
    "wof:name":"American Legion",
    "wof:placetype":"venue"
},
  "geometry": {"coordinates":[-81.40283599999999,28.29039],"type":"Point"}
}