{
  "type": "Feature",
  "properties": {
    "addr:full":"1342 N Galloway Rd Lakeland FL 33810",
    "addr:housenumber":"1342",
    "addr:postcode":"33810",
    "addr:street":"N Galloway Rd",
    "iso:country":"US",
    "sg:address":"1342 N Galloway Rd",
    "sg:city":"Lakeland",
    "sg:classifiers":[
        {
            "category":"Building & Trades",
            "subcategory":"Construction",
            "type":"Services"
        }
    ],
    "sg:phone":"+1 863 687 6368",
    "sg:postcode":"33810",
    "sg:province":"FL",
    "sg:tags":[
        "contractor"
    ],
    "wof:name":"Dans Masonry",
    "wof:placetype":"venue"
},
  "geometry": {"coordinates":[-82.00717,28.058832],"type":"Point"}
}