{
  "type": "Feature",
  "properties": {
    "addr:full":"13224 49th St N West Palm Beach FL 33411",
    "addr:housenumber":"13224",
    "addr:postcode":"33411",
    "addr:street":"49Th St N",
    "iso:country":"US",
    "sg:address":"13224 49th St N",
    "sg:city":"West Palm Beach",
    "sg:classifiers":[
        {
            "category":"Building & Trades",
            "subcategory":"Electrical",
            "type":"Services"
        }
    ],
    "sg:phone":"+1 561 863 5859",
    "sg:postcode":"33411",
    "sg:province":"FL",
    "sg:tags":[
        "electrical",
        "contractor"
    ],
    "wof:name":"Gem Electric",
    "wof:placetype":"venue"
},
  "geometry": {"coordinates":[-80.25121799999999,26.74918],"type":"Point"}
}