{
  "type": "Feature",
  "properties": {
    "iso:country":"US",
    "sg:address":"14587 Military Trl",
    "sg:city":"Delray Beach",
    "sg:classifiers":[
        {
            "category":"Shopping",
            "subcategory":"Clothing, Apparel, & Fashions",
            "type":"Retail Goods"
        }
    ],
    "sg:phone":"+1 561 637 0406",
    "sg:postcode":"33484",
    "sg:province":"FL",
    "wof:name":"Glitters",
    "wof:placetype":"venue"
},
  "geometry": {"coordinates":[-80.12260999999999,26.458049],"type":"Point"}
}