{
  "type": "Feature",
  "properties": {
    "addr:full":"357 Meadow Beauty Ter Sanford FL 32771",
    "addr:housenumber":"357",
    "addr:postcode":"32771",
    "addr:street":"Meadow Beauty Ter",
    "iso:country":"US",
    "sg:address":"357 Meadow Beauty Ter",
    "sg:city":"Sanford",
    "sg:classifiers":[
        {
            "category":"Professional",
            "subcategory":"Management & Consulting",
            "type":"Services"
        }
    ],
    "sg:phone":"+1 407 321 8623",
    "sg:postcode":"32771",
    "sg:province":"FL",
    "sg:tags":[
        "business"
    ],
    "wof:name":"Turtrade Inc",
    "wof:placetype":"venue"
},
  "geometry": {"coordinates":[-81.365887,28.801925],"type":"Point"}
}