{
  "type": "Feature",
  "properties": {
    "iso:country":"US",
    "sg:address":"1800 Eller Dr",
    "sg:city":"Fort Lauderdale",
    "sg:classifiers":[
        {
            "category":"Manufacturing",
            "subcategory":"Printing",
            "type":"Manufacturing & Wholesale Goods"
        }
    ],
    "sg:phone":"+1 954 764 5823",
    "sg:postcode":"33316",
    "sg:province":"FL",
    "sg:tags":[
        "newspaper"
    ],
    "wof:name":"Journal of Commerce",
    "wof:placetype":"venue"
},
  "geometry": {"coordinates":[-80.121213,26.082259],"type":"Point"}
}