{
  "type": "Feature",
  "properties": {
    "iso:country":"US",
    "sg:address":"300 71st St Ste 510",
    "sg:city":"Miami Beach",
    "sg:classifiers":[
        {
            "category":"Banks & Credit Unions",
            "subcategory":"Financial Services",
            "type":"Services"
        }
    ],
    "sg:phone":"+1 305 868 4966",
    "sg:postcode":"33141",
    "sg:province":"FL",
    "sg:tags":[
        "broker",
        "mortgage"
    ],
    "wof:name":"Oceanside Financial & Properties",
    "wof:placetype":"venue"
},
  "geometry": {"coordinates":[-80.12130000000001,25.856199],"type":"Point"}
}