{
  "type": "Feature",
  "properties": {
    "addr:full":"11823 SW 108th Ave Miami FL 33176",
    "addr:housenumber":"11823",
    "addr:postcode":"33176",
    "addr:street":"Sw 108Th Ave",
    "iso:country":"US",
    "sg:address":"11823 SW 108th Ave",
    "sg:city":"Miami",
    "sg:classifiers":[
        {
            "category":"Professional",
            "subcategory":"Computer Services",
            "type":"Services"
        }
    ],
    "sg:phone":"+1 305 232 7643",
    "sg:postcode":"33176",
    "sg:province":"FL",
    "sg:tags":[
        "related"
    ],
    "wof:name":"New Dimension Technologies",
    "wof:placetype":"venue"
},
  "geometry": {"coordinates":[-80.36993200000001,25.658494],"type":"Point"}
}