{
  "type": "Feature",
  "properties": {
    "iso:country":"US",
    "sg:address":"4180 S University Dr",
    "sg:city":"Davie",
    "sg:classifiers":[
        {
            "category":"Wholesale",
            "subcategory":"Hardware",
            "type":"Manufacturing & Wholesale Goods"
        },
        {
            "category":"Home & Garden",
            "subcategory":"Garden Supply",
            "type":"Retail Goods"
        },
        {
            "category":"Retail",
            "subcategory":"Repair Shop",
            "type":"Services"
        }
    ],
    "sg:phone":"+1 954 475 0310",
    "sg:postcode":"33328",
    "sg:province":"FL",
    "sg:tags":[
        "renting",
        "lawn",
        "outdoor",
        "power",
        "landscaping",
        "equipment-sales",
        "equipment",
        "saw"
    ],
    "sg:website":"http://www.stihldealer.net/default-dealer-010548.aspx",
    "wof:name":"Burkhards Tractor & Equipment",
    "wof:placetype":"venue"
},
  "geometry": {"coordinates":[-80.25220899999999,26.06714],"type":"Point"}
}