{
  "type": "Feature",
  "properties": {
    "iso:country":"US",
    "sg:address":"2770 Indian River Blvd",
    "sg:city":"Vero Beach",
    "sg:classifiers":[
        {
            "category":"Professional",
            "type":"Services"
        }
    ],
    "sg:phone":"+1 772 978 7558",
    "sg:postcode":"32960",
    "sg:province":"FL",
    "sg:tags":[
        "establishment"
    ],
    "wof:name":"Norchester Associates Inc",
    "wof:placetype":"venue"
},
  "geometry": {"coordinates":[-80.381997,27.647524],"type":"Point"}
}