{
  "type": "Feature",
  "properties": {
    "iso:country":"US",
    "sg:address":"2217 NW Pine Ave",
    "sg:city":"Ocala",
    "sg:classifiers":[
        {
            "category":"Building & Trades",
            "subcategory":"Construction",
            "type":"Services"
        }
    ],
    "sg:phone":"+1 352 622 8978",
    "sg:postcode":"34475",
    "sg:province":"FL",
    "sg:tags":[
        "contractor",
        "designer",
        "pool",
        "swimming"
    ],
    "sg:website":"http://www.fiestapoolsocala.net",
    "wof:name":"Fiesta Pools of Ocala",
    "wof:placetype":"venue"
},
  "geometry": {"coordinates":[-82.142734,29.209987],"type":"Point"}
}