{
  "type": "Feature",
  "properties": {
    "iso:country":"US",
    "sg:address":"4571 SW 74th Ave",
    "sg:city":"Miami",
    "sg:classifiers":[
        {
            "category":"Manufacturing",
            "subcategory":"Building Materials",
            "type":"Manufacturing & Wholesale Goods"
        }
    ],
    "sg:phone":"+1 305 265 1810",
    "sg:postcode":"33155",
    "sg:province":"FL",
    "wof:name":"Y&Y Wood Design",
    "wof:placetype":"venue"
},
  "geometry": {"coordinates":[-80.31481599999999,25.72825],"type":"Point"}
}