{
  "type": "Feature",
  "properties": {
    "iso:country":"US",
    "sg:address":"500 State Hwy 436",
    "sg:city":"Casselberry",
    "sg:classifiers":[
        {
            "category":"Health Services",
            "subcategory":"Clinic",
            "type":"Services"
        },
        {
            "category":"Health Services",
            "subcategory":"Health Practitioner",
            "type":"Services"
        }
    ],
    "sg:phone":"+1 407 834 1117",
    "sg:postcode":"32707",
    "sg:province":"FL",
    "sg:tags":[
        "home",
        "nurse",
        "registry",
        "care"
    ],
    "wof:name":"Quality Care Management",
    "wof:placetype":"venue"
},
  "geometry": {"coordinates":[-81.33103800000001,28.653706],"type":"Point"}
}