{
  "type": "Feature",
  "properties": {
    "iso:country":"US",
    "sg:address":"400 Mountain Dr",
    "sg:city":"Destin",
    "sg:classifiers":[
        {
            "category":"Retail",
            "subcategory":"Auto Repair",
            "type":"Services"
        }
    ],
    "sg:phone":"+1 850 269 4676",
    "sg:postcode":"32541",
    "sg:province":"FL",
    "sg:tags":[
        "repairing",
        "automobile"
    ],
    "wof:name":"Von Ahn's Auto Ctr Inc",
    "wof:placetype":"venue"
},
  "geometry": {"coordinates":[-86.50009,30.394526],"type":"Point"}
}