{
  "type": "Feature",
  "properties": {
    "addr:full":"99 Westglen Dr Fort Pierce FL 34981",
    "addr:housenumber":"99",
    "addr:postcode":"34981",
    "addr:street":"Westglen Dr",
    "iso:country":"US",
    "sg:address":"99 Westglen Dr",
    "sg:city":"Fort Pierce",
    "sg:classifiers":[
        {
            "category":"Freight",
            "type":"Transportation"
        }
    ],
    "sg:phone":"+1 772 519 0157",
    "sg:postcode":"34981",
    "sg:province":"FL",
    "sg:tags":[
        "trucking"
    ],
    "wof:name":"Oswaldo Garcia Trucking",
    "wof:placetype":"venue"
},
  "geometry": {"coordinates":[-80.37733900000001,27.40738],"type":"Point"}
}