{
  "type": "Feature",
  "properties": {
    "iso:country":"US",
    "sg:address":"669 NW 26th St",
    "sg:city":"Miami",
    "sg:classifiers":[
        {
            "category":"Retail",
            "subcategory":"Auto Repair",
            "type":"Services"
        }
    ],
    "sg:phone":"+1 305 634 6681",
    "sg:postcode":"33127",
    "sg:province":"FL",
    "sg:tags":[
        "body",
        "automobile",
        "painting"
    ],
    "wof:name":"Albe Motors Inc",
    "wof:placetype":"venue"
},
  "geometry": {"coordinates":[-80.206429,25.801262],"type":"Point"}
}