{
  "type": "Feature",
  "properties": {
    "iso:country":"US",
    "sg:address":"44 E 5th St",
    "sg:city":"Hialeah",
    "sg:classifiers":[
        {
            "category":"Health Services",
            "subcategory":"Doctor",
            "type":"Services"
        }
    ],
    "sg:phone":"+1 305 888 9786",
    "sg:postcode":"33010",
    "sg:province":"FL",
    "sg:tags":[
        "dermatologist"
    ],
    "wof:name":"Del Cristo E Gonzalo - CLOSED",
    "wof:placetype":"venue"
},
  "geometry": {"coordinates":[-80.28070099999999,25.8262],"type":"Point"}
}