{
  "type": "Feature",
  "properties": {
    "addr:full":"2740 Northridge Dr E Clearwater FL 33761",
    "addr:housenumber":"2740",
    "addr:postcode":"33761",
    "addr:street":"Northridge Dr E",
    "iso:country":"US",
    "sg:address":"2740 Northridge Dr E",
    "sg:city":"Clearwater",
    "sg:classifiers":[
        {
            "category":"Banks & Credit Unions",
            "subcategory":"Investment Brokerage",
            "type":"Services"
        }
    ],
    "sg:phone":"+1 727 789 1973",
    "sg:postcode":"33761",
    "sg:province":"FL",
    "sg:tags":[
        "security"
    ],
    "wof:name":"SunAmerica",
    "wof:placetype":"venue"
},
  "geometry": {"coordinates":[-82.72210200000001,28.04015],"type":"Point"}
}