{
  "type": "Feature",
  "properties": {
    "addr:full":"2955 Pineda Cswy Melbourne FL 32940",
    "addr:housenumber":"2955",
    "addr:postcode":"32940",
    "addr:street":"Pineda Cswy",
    "iso:country":"US",
    "sg:address":"2955 Pineda Cswy",
    "sg:city":"Melbourne",
    "sg:classifiers":[
        {
            "category":"Insurance",
            "subcategory":"Insurance Agent",
            "type":"Services"
        }
    ],
    "sg:phone":"+1 321 259 8523",
    "sg:postcode":"32940",
    "sg:province":"FL",
    "wof:name":"Western-Southern Life Ins Co",
    "wof:placetype":"venue"
},
  "geometry": {"coordinates":[-80.67017300000001,28.203046],"type":"Point"}
}