{
  "type": "Feature",
  "properties": {
    "iso:country":"US",
    "sg:address":"3941 Highway 77",
    "sg:city":"Chipley",
    "sg:classifiers":[
        {
            "category":"Farming",
            "subcategory":"Farm",
            "type":"Manufacturing & Wholesale Goods"
        }
    ],
    "sg:phone":"+1 850 773 2359",
    "sg:postcode":"32428",
    "sg:province":"FL",
    "wof:name":"Charles H Kolmetz",
    "wof:placetype":"venue"
},
  "geometry": {"coordinates":[-85.594239,30.612166],"type":"Point"}
}