{
  "type": "Feature",
  "properties": {
    "iso:country":"US",
    "sg:address":"2802 N Pearl St",
    "sg:city":"Jacksonville",
    "sg:classifiers":[
        {
            "category":"Organizations",
            "subcategory":"Religious Organization",
            "type":"Services"
        }
    ],
    "sg:phone":"+1 904 355 0490",
    "sg:postcode":"32206",
    "sg:province":"FL",
    "sg:tags":[
        "church"
    ],
    "wof:name":"Tombs & Bright Morning Star",
    "wof:placetype":"venue"
},
  "geometry": {"coordinates":[-81.658672,30.355661],"type":"Point"}
}