{
  "type": "Feature",
  "properties": {
    "addr:full":"2316 Dellwood Ave Jacksonville FL 32204",
    "addr:housenumber":"2316",
    "addr:postcode":"32204",
    "addr:street":"Dellwood Ave",
    "iso:country":"US",
    "sg:address":"2316 Dellwood Ave",
    "sg:city":"Jacksonville",
    "sg:classifiers":[
        {
            "category":"Shopping",
            "subcategory":"Used Merchandise",
            "type":"Retail Goods"
        }
    ],
    "sg:phone":"+1 904 387 5864",
    "sg:postcode":"32204",
    "sg:province":"FL",
    "wof:name":"McClure Street",
    "wof:placetype":"venue"
},
  "geometry": {"coordinates":[-81.689656,30.316626],"type":"Point"}
}