{
  "type": "Feature",
  "properties": {
    "iso:country":"US",
    "sg:address":"16850 Collins Ave",
    "sg:city":"Sunny Isles Beach",
    "sg:classifiers":[
        {
            "category":"Restaurant",
            "type":"Food & Drink"
        }
    ],
    "sg:phone":"+1 305 787 1530",
    "sg:postcode":"33160",
    "sg:province":"FL",
    "sg:tags":[
        "eating",
        "buffet"
    ],
    "wof:name":"Emerald Coast",
    "wof:placetype":"venue"
},
  "geometry": {"coordinates":[-80.12197500000001,25.932185],"type":"Point"}
}