{
  "type": "Feature",
  "properties": {
    "iso:country":"US",
    "sg:address":"201 6th Ave",
    "sg:city":"Indialantic",
    "sg:classifiers":[
        {
            "category":"Insurance",
            "subcategory":"Title Insurance",
            "type":"Services"
        }
    ],
    "sg:phone":"+1 321 984 0986",
    "sg:postcode":"32903",
    "sg:province":"FL",
    "sg:tags":[
        "carrier",
        "real estate"
    ],
    "wof:name":"Precise Title Inc",
    "wof:placetype":"venue"
},
  "geometry": {"coordinates":[-80.57068599999999,28.089641],"type":"Point"}
}