{
  "type": "Feature",
  "properties": {
    "addr:full":"3984 W 12th Ave Hialeah FL 33012",
    "addr:housenumber":"3984",
    "addr:postcode":"33012",
    "addr:street":"W 12Th Ave",
    "iso:country":"US",
    "sg:address":"3984 W 12th Ave",
    "sg:city":"Hialeah",
    "sg:classifiers":[
        {
            "category":"Building & Trades",
            "subcategory":"Equipment Rental",
            "type":"Services"
        }
    ],
    "sg:phone":"+1 305 557 2100",
    "sg:postcode":"33012",
    "sg:province":"FL",
    "sg:tags":[
        "leasing",
        "television",
        "radio-renting"
    ],
    "sg:website":"http://www.rentacenter.com/",
    "wof:name":"Rent-A-Center",
    "wof:placetype":"venue"
},
  "geometry": {"coordinates":[-80.30659799999999,25.858004],"type":"Point"}
}