{
  "type": "Feature",
  "properties": {
    "iso:country":"US",
    "sg:address":"1996 Teal Ln",
    "sg:city":"Middleburg",
    "sg:classifiers":[
        {
            "category":"Building & Trades",
            "subcategory":"Landscaping Services",
            "type":"Services"
        }
    ],
    "sg:phone":"+1 904 282 3935",
    "sg:postcode":"32068",
    "sg:province":"FL",
    "wof:name":"Richard Dupont Lawn Service",
    "wof:placetype":"venue"
},
  "geometry": {"coordinates":[-81.948205,30.086534],"type":"Point"}
}