{
  "type": "Feature",
  "properties": {
    "addr:full":"715 Crandon Blvd Key Biscayne FL 33149",
    "addr:housenumber":"715",
    "addr:postcode":"33149",
    "addr:street":"Crandon Blvd",
    "iso:country":"US",
    "sg:address":"715 Crandon Blvd",
    "sg:city":"Key Biscayne",
    "sg:classifiers":[
        {
            "category":"Wholesale",
            "subcategory":"Medical Equipment & Supplies",
            "type":"Manufacturing & Wholesale Goods"
        }
    ],
    "sg:phone":"+1 305 365 6153",
    "sg:postcode":"33149",
    "sg:province":"FL",
    "wof:name":"Prestige Medical Supplies Inc",
    "wof:placetype":"venue"
},
  "geometry": {"coordinates":[-80.161907,25.685847],"type":"Point"}
}