{
  "type": "Feature",
  "properties": {
    "iso:country":"US",
    "sg:address":"2 Dockside Ln",
    "sg:city":"Key Largo",
    "sg:classifiers":[
        {
            "category":"Shopping",
            "subcategory":"Clothing, Apparel, & Fashions",
            "type":"Retail Goods"
        }
    ],
    "sg:phone":"+1 305 367 4757",
    "sg:postcode":"33037",
    "sg:province":"FL",
    "sg:tags":[
        "dressmaker"
    ],
    "wof:name":"Y K Dressmaker",
    "wof:placetype":"venue"
},
  "geometry": {"coordinates":[-80.281893,25.312054],"type":"Point"}
}