{
  "type": "Feature",
  "properties": {
    "iso:country":"US",
    "sg:address":"265 S Federal Hwy",
    "sg:city":"Deerfield Beach",
    "sg:classifiers":[
        {
            "category":"Retail",
            "subcategory":"Auto Repair",
            "type":"Services"
        }
    ],
    "sg:phone":"+1 954 935 6999",
    "sg:postcode":"33441",
    "sg:province":"FL",
    "sg:tags":[
        "automotive",
        "refinishing"
    ],
    "wof:name":"Paint Shuttle",
    "wof:placetype":"venue"
},
  "geometry": {"coordinates":[-80.091459,26.314462],"type":"Point"}
}