{
  "type": "Feature",
  "properties": {
    "iso:country":"US",
    "sg:address":"1609 9th St N",
    "sg:city":"St Petersburg",
    "sg:classifiers":[
        {
            "category":"Real Estate",
            "subcategory":"Architect",
            "type":"Services"
        }
    ],
    "sg:phone":"+1 727 821 2986",
    "sg:postcode":"33704",
    "sg:province":"FL",
    "wof:name":"Renker-Eich-Parks Architects",
    "wof:placetype":"venue"
},
  "geometry": {"coordinates":[-82.64662199999999,27.787929],"type":"Point"}
}