{
  "type": "Feature",
  "properties": {
    "addr:full":"15404 Stone Creek Ln Tampa FL 33613",
    "addr:housenumber":"15404",
    "addr:postcode":"33613",
    "addr:street":"Stone Creek Ln",
    "iso:country":"US",
    "sg:address":"15404 Stone Creek Ln",
    "sg:city":"Tampa",
    "sg:classifiers":[
        {
            "category":"Manufacturing",
            "subcategory":"Metals",
            "type":"Manufacturing & Wholesale Goods"
        }
    ],
    "sg:phone":"+1 813 963 7453",
    "sg:postcode":"33613",
    "sg:province":"FL",
    "sg:tags":[
        "coating",
        "powder"
    ],
    "wof:name":"American Powder Coating",
    "wof:placetype":"venue"
},
  "geometry": {"coordinates":[-82.466202,28.092103],"type":"Point"}
}