{
  "type": "Feature",
  "properties": {
    "iso:country":"US",
    "sg:address":"5300 S Atlantic Ave",
    "sg:city":"New Smyrna Beach",
    "sg:classifiers":[
        {
            "category":"Building & Trades",
            "subcategory":"Construction",
            "type":"Services"
        }
    ],
    "sg:phone":"+1 386 423 9513",
    "sg:postcode":"32169",
    "sg:province":"FL",
    "sg:tags":[
        "contractor"
    ],
    "wof:name":"Dynamic Building",
    "wof:placetype":"venue"
},
  "geometry": {"coordinates":[-80.858594,28.97702],"type":"Point"}
}