{
  "type": "Feature",
  "properties": {
    "iso:country":"US",
    "sg:address":"917 Odoniel Dr",
    "sg:city":"Lakeland",
    "sg:classifiers":[
        {
            "category":"Building & Trades",
            "subcategory":"Construction",
            "type":"Services"
        }
    ],
    "sg:phone":"+1 863 853 8503",
    "sg:postcode":"33809",
    "sg:province":"FL",
    "sg:tags":[
        "house"
    ],
    "wof:name":"Matthew E Grothe Sr Home Repr",
    "wof:placetype":"venue"
},
  "geometry": {"coordinates":[-81.938177,28.130895],"type":"Point"}
}