{
  "type": "Feature",
  "properties": {
    "addr:full":"2402 Palm Ridge Rd Sanibel FL 33957",
    "addr:housenumber":"2402",
    "addr:postcode":"33957",
    "addr:street":"Palm Ridge Rd",
    "iso:country":"US",
    "sg:address":"2402 Palm Ridge Rd",
    "sg:city":"Sanibel",
    "sg:classifiers":[
        {
            "category":"Wholesale",
            "subcategory":"Medical Equipment & Supplies",
            "type":"Manufacturing & Wholesale Goods"
        }
    ],
    "sg:phone":"+1 239 395 3933",
    "sg:postcode":"33957",
    "sg:province":"FL",
    "wof:name":"Real Time Radiography Readout",
    "wof:placetype":"venue"
},
  "geometry": {"coordinates":[-82.080213,26.439872],"type":"Point"}
}