{
  "type": "Feature",
  "properties": {
    "iso:country":"US",
    "sg:address":"1519 N Woodland Blvd",
    "sg:city":"Deland",
    "sg:classifiers":[
        {
            "category":"Wholesale",
            "subcategory":"Non-durable Goods",
            "type":"Manufacturing & Wholesale Goods"
        }
    ],
    "sg:phone":"+1 386 734 5440",
    "sg:postcode":"32720",
    "sg:province":"FL",
    "sg:tags":[
        "dry",
        "goods-wholesale"
    ],
    "wof:name":"Equine Heaven Tack & Supply",
    "wof:placetype":"venue"
},
  "geometry": {"coordinates":[-81.30426799999999,29.055603],"type":"Point"}
}