{
  "type": "Feature",
  "properties": {
    "addr:full":"6303 S Dixie Hwy West Palm Beach FL 33405",
    "addr:housenumber":"6303",
    "addr:postcode":"33405",
    "addr:street":"S Dixie Hwy",
    "iso:country":"US",
    "sg:address":"6303 S Dixie Hwy",
    "sg:city":"West Palm Beach",
    "sg:classifiers":[
        {
            "category":"Personal",
            "subcategory":"Beauty Salon",
            "type":"Services"
        }
    ],
    "sg:phone":"+1 561 585 1797",
    "sg:postcode":"33405",
    "sg:province":"FL",
    "sg:tags":[
        "manicuring"
    ],
    "wof:name":"Teresa's Nail & Skin Care",
    "wof:placetype":"venue"
},
  "geometry": {"coordinates":[-80.055984,26.658034],"type":"Point"}
}