{
  "type": "Feature",
  "properties": {
    "addr:full":"1180 Bayshore Dr Englewood FL 34223",
    "addr:housenumber":"1180",
    "addr:postcode":"34223",
    "addr:street":"Bayshore Dr",
    "iso:country":"US",
    "sg:address":"1180 Bayshore Dr",
    "sg:city":"Englewood",
    "sg:classifiers":[
        {
            "category":"Building & Trades",
            "subcategory":"Plumbing",
            "type":"Services"
        }
    ],
    "sg:phone":"+1 941 474 8021",
    "sg:postcode":"34223",
    "sg:province":"FL",
    "sg:tags":[
        "contractor"
    ],
    "wof:name":"D Martin Plumbing Inc",
    "wof:placetype":"venue"
},
  "geometry": {"coordinates":[-82.384603,26.986092],"type":"Point"}
}