{
  "type": "Feature",
  "properties": {
    "iso:country":"US",
    "sg:address":"5711 Birch Dr",
    "sg:city":"Fort Pierce",
    "sg:classifiers":[
        {
            "category":"Building & Trades",
            "subcategory":"Construction",
            "type":"Services"
        }
    ],
    "sg:phone":"+1 772 465 7433",
    "sg:postcode":"34982",
    "sg:province":"FL",
    "sg:tags":[
        "house"
    ],
    "wof:name":"Custom Homes By Emil",
    "wof:placetype":"venue"
},
  "geometry": {"coordinates":[-80.30627200000001,27.358995],"type":"Point"}
}