{
  "type": "Feature",
  "properties": {
    "addr:full":"2505 Mason Oaks Dr Valrico FL 33596",
    "addr:housenumber":"2505",
    "addr:postcode":"33596",
    "addr:street":"Mason Oaks Dr",
    "iso:country":"US",
    "sg:address":"2505 Mason Oaks Dr",
    "sg:city":"Valrico",
    "sg:classifiers":[
        {
            "category":"Communications",
            "subcategory":"Film & Video Production",
            "type":"Services"
        }
    ],
    "sg:phone":"+1 813 653 9474",
    "sg:postcode":"33596",
    "sg:province":"FL",
    "sg:tags":[
        "motion"
    ],
    "wof:name":"Imedia",
    "wof:placetype":"venue"
},
  "geometry": {"coordinates":[-82.23464199999999,27.885441],"type":"Point"}
}