{
  "type": "Feature",
  "properties": {
    "iso:country":"US",
    "sg:address":"8200 S Orange Blossom Trl",
    "sg:city":"Orlando",
    "sg:classifiers":[
        {
            "category":"Home & Garden",
            "subcategory":"Furniture",
            "type":"Retail Goods"
        }
    ],
    "sg:phone":"+1 407 438 1488",
    "sg:postcode":"32809",
    "sg:province":"FL",
    "wof:name":"Leather Galleries Inc",
    "wof:placetype":"venue"
},
  "geometry": {"coordinates":[-81.402525,28.444495],"type":"Point"}
}