{
  "type": "Feature",
  "properties": {
    "iso:country":"US",
    "sg:address":"1320 N Ocean Blvd",
    "sg:city":"Delray Beach",
    "sg:classifiers":[
        {
            "category":"Banks & Credit Unions",
            "subcategory":"Financial Services",
            "type":"Services"
        }
    ],
    "sg:phone":"+1 561 274 2116",
    "sg:postcode":"33483",
    "sg:province":"FL",
    "sg:tags":[
        "trust",
        "nonprofit",
        "management"
    ],
    "wof:name":"Elmore Family Foundation",
    "wof:placetype":"venue"
},
  "geometry": {"coordinates":[-80.05632799999999,26.479689],"type":"Point"}
}