{
  "type": "Feature",
  "properties": {
    "addr:full":"1912 Silver Star Rd Orlando FL 32804",
    "addr:housenumber":"1912",
    "addr:postcode":"32804",
    "addr:street":"Silver Star Rd",
    "iso:country":"US",
    "sg:address":"1912 Silver Star Rd",
    "sg:city":"Orlando",
    "sg:classifiers":[
        {
            "category":"Retail",
            "subcategory":"Driving School",
            "type":"Services"
        }
    ],
    "sg:phone":"+1 407 494 6465",
    "sg:postcode":"32804",
    "sg:province":"FL",
    "sg:tags":[
        "instruction"
    ],
    "sg:website":"http://www.jbdrivingschool.com",
    "wof:name":"JB Driving School",
    "wof:placetype":"venue"
},
  "geometry": {"coordinates":[-81.407646,28.578177],"type":"Point"}
}