{
  "type": "Feature",
  "properties": {
    "addr:full":"1630 Club Dr Vero Beach FL 32963",
    "addr:housenumber":"1630",
    "addr:postcode":"32963",
    "addr:street":"Club Dr",
    "iso:country":"US",
    "sg:address":"1630 Club Dr",
    "sg:city":"Vero Beach",
    "sg:classifiers":[
        {
            "category":"Real Estate",
            "subcategory":"Real Estate Agent",
            "type":"Services"
        }
    ],
    "sg:phone":"+1 772 231 8480",
    "sg:postcode":"32963",
    "sg:province":"FL",
    "wof:name":"Sea Trek Realty Inc",
    "wof:placetype":"venue"
},
  "geometry": {"coordinates":[-80.356505,27.63175],"type":"Point"}
}