{
  "type": "Feature",
  "properties": {
    "addr:full":"7535 Andorra Pl Boca Raton FL 33433",
    "addr:housenumber":"7535",
    "addr:postcode":"33433",
    "addr:street":"Andorra Pl",
    "iso:country":"US",
    "sg:address":"7535 Andorra Pl",
    "sg:city":"Boca Raton",
    "sg:classifiers":[
        {
            "category":"Shopping",
            "subcategory":"Florist",
            "type":"Retail Goods"
        }
    ],
    "sg:phone":"+1 561 832 8133",
    "sg:postcode":"33433",
    "sg:province":"FL",
    "wof:name":"Edith The Florist",
    "wof:placetype":"venue"
},
  "geometry": {"coordinates":[-80.16195,26.344673],"type":"Point"}
}