{
  "type": "Feature",
  "properties": {
    "iso:country":"US",
    "sg:address":"225 S Temple Ave",
    "sg:city":"Starke",
    "sg:classifiers":[
        {
            "category":"Restaurant",
            "type":"Food & Drink"
        }
    ],
    "sg:menulink":"http://www.allmenus.com/fl/starke/241183-checkers/menu/",
    "sg:phone":"+1 904 964 8882",
    "sg:postcode":"32091",
    "sg:province":"FL",
    "sg:tags":[
        "burger",
        "american",
        "hot",
        "dog"
    ],
    "wof:name":"Checkers",
    "wof:placetype":"venue"
},
  "geometry": {"coordinates":[-82.111729,29.943499],"type":"Point"}
}