{
  "type": "Feature",
  "properties": {
    "addr:full":"8798 Commerce Dr Bonita Springs FL 34135",
    "addr:housenumber":"8798",
    "addr:postcode":"34135",
    "addr:street":"Commerce Dr",
    "iso:country":"US",
    "sg:address":"8798 Commerce Dr",
    "sg:city":"Bonita Springs",
    "sg:classifiers":[
        {
            "category":"Wholesale",
            "subcategory":"Electrical",
            "type":"Manufacturing & Wholesale Goods"
        }
    ],
    "sg:phone":"+1 239 948 3377",
    "sg:postcode":"34135",
    "sg:province":"FL",
    "sg:tags":[
        "equipment"
    ],
    "wof:name":"City Electric Supply Co",
    "wof:placetype":"venue"
},
  "geometry": {"coordinates":[-81.806977,26.387064],"type":"Point"}
}