{
  "type": "Feature",
  "properties": {
    "addr:full":"714 SW Pine Island Rd Cape Coral FL 33991",
    "addr:housenumber":"714",
    "addr:postcode":"33991",
    "addr:street":"Sw Pine Island Rd",
    "iso:country":"US",
    "sg:address":"714 SW Pine Island Rd",
    "sg:city":"Cape Coral",
    "sg:classifiers":[
        {
            "category":"Building & Trades",
            "subcategory":"Landscaping Services",
            "type":"Services"
        }
    ],
    "sg:phone":"+1 239 458 0966",
    "sg:postcode":"33991",
    "sg:province":"FL",
    "sg:tags":[
        "landscape",
        "contractor"
    ],
    "wof:name":"F D Growers",
    "wof:placetype":"venue"
},
  "geometry": {"coordinates":[-81.990042,26.645108],"type":"Point"}
}