{
  "type": "Feature",
  "properties": {
    "addr:full":"301 Lakedale Dr Auburndale FL 33823",
    "addr:housenumber":"301",
    "addr:postcode":"33823",
    "addr:street":"Lakedale Dr",
    "iso:country":"US",
    "sg:address":"301 Lakedale Dr",
    "sg:city":"Auburndale",
    "sg:classifiers":[
        {
            "category":"Building & Trades",
            "subcategory":"Construction",
            "type":"Services"
        }
    ],
    "sg:phone":"+1 863 551 1965",
    "sg:postcode":"33823",
    "sg:province":"FL",
    "sg:tags":[
        "farm",
        "contractor",
        "labor"
    ],
    "wof:name":"Crawford & Son Framing",
    "wof:placetype":"venue"
},
  "geometry": {"coordinates":[-81.812021,28.070539],"type":"Point"}
}