{
  "type": "Feature",
  "properties": {
    "addr:full":"1400 Old Dixie Hwy St Augustine FL 32084",
    "addr:housenumber":"1400",
    "addr:postcode":"32084",
    "addr:street":"Old Dixie Hwy St",
    "iso:country":"US",
    "sg:address":"1400 Old Dixie Hwy",
    "sg:city":"St Augustine",
    "sg:classifiers":[
        {
            "category":"Social Services",
            "type":"Services"
        }
    ],
    "sg:phone":"+1 904 829 2273",
    "sg:postcode":"32084",
    "sg:province":"FL",
    "sg:tags":[
        "counseling"
    ],
    "wof:name":"Epic Community Service Inc",
    "wof:placetype":"venue"
},
  "geometry": {"coordinates":[-81.326503,29.877012],"type":"Point"}
}