{
  "type": "Feature",
  "properties": {
    "iso:country":"US",
    "sg:address":"5195 Cortez Ct",
    "sg:city":"Delray Beach",
    "sg:classifiers":[
        {
            "category":"Professional",
            "type":"Services"
        }
    ],
    "sg:phone":"+1 561 381 4421",
    "sg:postcode":"33484",
    "sg:province":"FL",
    "wof:name":"Pick Ax Co",
    "wof:placetype":"venue"
},
  "geometry": {"coordinates":[-80.12444000000001,26.475242],"type":"Point"}
}