{
  "type": "Feature",
  "properties": {
    "iso:country":"US",
    "sg:address":"1161 NW 159th Dr",
    "sg:city":"Miami",
    "sg:classifiers":[
        {
            "category":"Communications",
            "type":"Services"
        }
    ],
    "sg:phone":"+1 305 621 9555",
    "sg:postcode":"33169",
    "sg:province":"FL",
    "sg:tags":[
        "consultant"
    ],
    "wof:name":"Vierge Group",
    "wof:placetype":"venue"
},
  "geometry": {"coordinates":[-80.220493,25.92006],"type":"Point"}
}