{
  "type": "Feature",
  "properties": {
    "iso:country":"US",
    "sg:address":"7721 Ellis Rd",
    "sg:city":"Melbourne",
    "sg:classifiers":[
        {
            "category":"Autos & Motor Vehicles",
            "subcategory":"Auto Supplies",
            "type":"Retail Goods"
        },
        {
            "category":"Retail",
            "subcategory":"Auto Repair",
            "type":"Services"
        }
    ],
    "sg:phone":"+1 321 724 6444",
    "sg:postcode":"32904",
    "sg:province":"FL",
    "sg:tags":[
        "body",
        "lettering",
        "automobile",
        "truck",
        "painting",
        "repairing"
    ],
    "wof:name":"Miller's Auto Repair",
    "wof:placetype":"venue"
},
  "geometry": {"coordinates":[-80.67834499999999,28.099547],"type":"Point"}
}