{
  "type": "Feature",
  "properties": {
    "addr:full":"3401 SW 58th St Ocala FL 34471",
    "addr:housenumber":"3401",
    "addr:postcode":"34471",
    "addr:street":"Sw 58Th St",
    "iso:country":"US",
    "sg:address":"3401 SW 58th St",
    "sg:city":"Ocala",
    "sg:classifiers":[
        {
            "category":"Building & Trades",
            "subcategory":"Construction",
            "type":"Services"
        }
    ],
    "sg:phone":"+1 352 624 1983",
    "sg:postcode":"34471",
    "sg:province":"FL",
    "sg:tags":[
        "specializing",
        "new",
        "contractor",
        "f"
    ],
    "sg:website":"www.owenconstruction.com",
    "wof:name":"David Owen Construction",
    "wof:placetype":"venue"
},
  "geometry": {"coordinates":[-82.170951,29.129318],"type":"Point"}
}