{
  "type": "Feature",
  "properties": {
    "iso:country":"US",
    "sg:address":"5509 NW 7th Ave",
    "sg:city":"Miami",
    "sg:classifiers":[
        {
            "category":"Building & Trades",
            "subcategory":"Locksmith",
            "type":"Services"
        }
    ],
    "sg:phone":"+1 786 718 1380",
    "sg:postcode":"33127",
    "sg:province":"FL",
    "sg:tags":[
        "key"
    ],
    "wof:name":"A-1 Locksmith",
    "wof:placetype":"venue"
},
  "geometry": {"coordinates":[-80.208032,25.825787],"type":"Point"}
}