{
  "type": "Feature",
  "properties": {
    "addr:full":"3985 Bentwood Ln Cantonment FL 32533",
    "addr:housenumber":"3985",
    "addr:postcode":"32533",
    "addr:street":"Bentwood Ln",
    "iso:country":"US",
    "sg:address":"3985 Bentwood Ln",
    "sg:city":"Cantonment",
    "sg:classifiers":[
        {
            "category":"Professional",
            "subcategory":"Engineering",
            "type":"Services"
        }
    ],
    "sg:phone":"+1 850 476 7722",
    "sg:postcode":"32533",
    "sg:province":"FL",
    "wof:name":"Land Mark Design and Cnstr",
    "wof:placetype":"venue"
},
  "geometry": {"coordinates":[-87.33516299999999,30.538725],"type":"Point"}
}