{
  "type": "Feature",
  "properties": {
    "addr:full":"518 E Memorial Blvd Lakeland FL 33801",
    "addr:housenumber":"518",
    "addr:postcode":"33801",
    "addr:street":"E Memorial Blvd",
    "iso:country":"US",
    "sg:address":"518 E Memorial Blvd",
    "sg:city":"Lakeland",
    "sg:classifiers":[
        {
            "category":"Professional",
            "type":"Services"
        }
    ],
    "sg:phone":"+1 863 802 8108",
    "sg:postcode":"33801",
    "sg:province":"FL",
    "sg:tags":[
        "establishment"
    ],
    "wof:name":"Eastern Dynasty",
    "wof:placetype":"venue"
},
  "geometry": {"coordinates":[-81.952343,28.054969],"type":"Point"}
}