{
  "type": "Feature",
  "properties": {
    "addr:full":"1079 Muriel Blvd La Belle FL 33935",
    "addr:housenumber":"1079",
    "addr:postcode":"33935",
    "addr:street":"Muriel Blvd La Belle",
    "iso:country":"US",
    "sg:address":"1079 Muriel Blvd",
    "sg:city":"La Belle",
    "sg:classifiers":[
        {
            "category":"Professional",
            "type":"Services"
        }
    ],
    "sg:phone":"+1 863 674 1433",
    "sg:postcode":"33935",
    "sg:province":"FL",
    "wof:name":"Steelman Gym Inc",
    "wof:placetype":"venue"
},
  "geometry": {"coordinates":[-81.454571,26.77877],"type":"Point"}
}