{
  "type": "Feature",
  "properties": {
    "iso:country":"US",
    "sg:address":"1625 SE 40th Ter",
    "sg:city":"Cape Coral",
    "sg:classifiers":[
        {
            "category":"Building & Trades",
            "subcategory":"Pest Control",
            "type":"Services"
        }
    ],
    "sg:phone":"+1 239 540 6800",
    "sg:postcode":"33904",
    "sg:province":"FL",
    "wof:name":"Absolute Pest Control",
    "wof:placetype":"venue"
},
  "geometry": {"coordinates":[-81.94226999999999,26.576697],"type":"Point"}
}