{
  "type": "Feature",
  "properties": {
    "iso:country":"US",
    "sg:address":"1630 S Orlando Ave",
    "sg:city":"Winter Park",
    "sg:classifiers":[
        {
            "category":"Professional",
            "subcategory":"Art Services",
            "type":"Services"
        }
    ],
    "sg:phone":"+1 407 629 8874",
    "sg:postcode":"32789",
    "sg:province":"FL",
    "sg:tags":[
        "photographer"
    ],
    "sg:website":"www.sterlingphotography.com",
    "wof:name":"Sterling Fine Arts-Phtgrphy",
    "wof:placetype":"venue"
},
  "geometry": {"coordinates":[-81.36490499999999,28.582212],"type":"Point"}
}