{
  "type": "Feature",
  "properties": {
    "addr:full":"1111 Port Blvd Miami FL 33132",
    "addr:housenumber":"1111",
    "addr:postcode":"33132",
    "addr:street":"Port Blvd",
    "iso:country":"US",
    "sg:address":"1111 Port Blvd",
    "sg:city":"Miami",
    "sg:classifiers":[
        {
            "category":"Shopping",
            "subcategory":"Gifts & Souvenirs",
            "type":"Retail Goods"
        }
    ],
    "sg:phone":"+1 305 666 7834",
    "sg:postcode":"33132",
    "sg:province":"FL",
    "sg:tags":[
        "s",
        "eating"
    ],
    "wof:name":"Parrot Jungle & Gardens",
    "wof:placetype":"venue"
},
  "geometry": {"coordinates":[-80.177196,25.777203],"type":"Point"}
}