{
  "type": "Feature",
  "properties": {
    "iso:country":"US",
    "sg:address":"12651 McGregor Blvd",
    "sg:city":"Fort Myers",
    "sg:classifiers":[
        {
            "category":"Health Services",
            "subcategory":"Hospital",
            "type":"Services"
        }
    ],
    "sg:phone":"+1 239 938 3360",
    "sg:postcode":"33919",
    "sg:province":"FL",
    "wof:name":"Hca of Florida Consult A Nurse",
    "wof:placetype":"venue"
},
  "geometry": {"coordinates":[-81.909223,26.559613],"type":"Point"}
}