{
  "type": "Feature",
  "properties": {
    "iso:country":"US",
    "sg:address":"7820 Congress St",
    "sg:city":"New Port Richey",
    "sg:classifiers":[
        {
            "category":"Social Services",
            "type":"Services"
        }
    ],
    "sg:phone":"+1 727 815 0433",
    "sg:postcode":"34653",
    "sg:province":"FL",
    "sg:tags":[
        "food",
        "banks",
        "bank"
    ],
    "wof:name":"Volunteer Way",
    "wof:placetype":"venue"
},
  "geometry": {"coordinates":[-82.70724300000001,28.269964],"type":"Point"}
}