{
  "type": "Feature",
  "properties": {
    "iso:country":"US",
    "sg:address":"117 Country Club Dr",
    "sg:city":"Lake Placid",
    "sg:classifiers":[
        {
            "category":"Professional",
            "type":"Services"
        }
    ],
    "sg:phone":"+1 863 465 0237",
    "sg:postcode":"33852",
    "sg:province":"FL",
    "sg:tags":[
        "establishment"
    ],
    "wof:name":"Lakeshore Tower I",
    "wof:placetype":"venue"
},
  "geometry": {"coordinates":[-81.330185,27.238668],"type":"Point"}
}