{
  "type": "Feature",
  "properties": {
    "addr:full":"39140 Orient Ave Zephyrhills FL 33542",
    "addr:postcode":"39140;33542",
    "addr:street":"Orient Ave",
    "iso:country":"US",
    "sg:address":"39140 Orient Ave",
    "sg:city":"Zephyrhills",
    "sg:classifiers":[
        {
            "category":"Personal",
            "subcategory":"Beauty Salon",
            "type":"Services"
        }
    ],
    "sg:phone":"+1 813 788 3030",
    "sg:postcode":"33542",
    "sg:province":"FL",
    "wof:name":"Simple Solutions Salon Inc",
    "wof:placetype":"venue"
},
  "geometry": {"coordinates":[-82.169082,28.252512],"type":"Point"}
}