{
  "type": "Feature",
  "properties": {
    "iso:country":"US",
    "sg:address":"201 N Orange St",
    "sg:city":"New Smyrna Beach",
    "sg:classifiers":[
        {
            "category":"Home & Garden",
            "subcategory":"Home Furnishings",
            "type":"Retail Goods"
        },
        {
            "category":"Building & Trades",
            "subcategory":"Construction",
            "type":"Services"
        }
    ],
    "sg:phone":"+1 386 428 6678",
    "sg:postcode":"32168",
    "sg:province":"FL",
    "sg:tags":[
        "glass",
        "window",
        "contractor",
        "installation",
        "mirror"
    ],
    "wof:name":"Indian River Glass Company",
    "wof:placetype":"venue"
},
  "geometry": {"coordinates":[-80.92653300000001,29.026123],"type":"Point"}
}