{
  "type": "Feature",
  "properties": {
    "iso:country":"US",
    "sg:address":"300 International Pkwy",
    "sg:city":"Lake Mary",
    "sg:classifiers":[
        {
            "category":"Insurance",
            "subcategory":"Insurance Agent",
            "type":"Services"
        }
    ],
    "sg:phone":"+1 407 333 2905",
    "sg:postcode":"32746",
    "sg:province":"FL",
    "sg:tags":[
        "firm",
        "brokerage",
        "consulting"
    ],
    "wof:name":"Newport Group Inc",
    "wof:placetype":"venue"
},
  "geometry": {"coordinates":[-81.363711,28.76344],"type":"Point"}
}