{
  "type": "Feature",
  "properties": {
    "iso:country":"US",
    "sg:address":"15 Via Verona",
    "sg:city":"Palm Beach Gardens",
    "sg:classifiers":[
        {
            "category":"Professional",
            "subcategory":"Management & Consulting",
            "type":"Services"
        }
    ],
    "sg:phone":"+1 561 694 1646",
    "sg:postcode":"33418",
    "sg:province":"FL",
    "sg:tags":[
        "project",
        "consultant"
    ],
    "wof:name":"Performance Management Assoc",
    "wof:placetype":"venue"
},
  "geometry": {"coordinates":[-80.134175,26.822733],"type":"Point"}
}