{
  "type": "Feature",
  "properties": {
    "addr:full":"19220 Immokalee Rd Naples FL 34120",
    "addr:postcode":"19220;34120",
    "addr:street":"Immokalee Rd",
    "iso:country":"US",
    "sg:address":"19220 Immokalee Rd",
    "sg:city":"Naples",
    "sg:classifiers":[
        {
            "category":"Place Of Worship",
            "type":"Public Place"
        }
    ],
    "sg:phone":"+1 239 348 9116",
    "sg:postcode":"34120",
    "sg:province":"FL",
    "sg:tags":[
        "church"
    ],
    "wof:name":"Church On Immokalee Road",
    "wof:placetype":"venue"
},
  "geometry": {"coordinates":[-81.579223,26.366133],"type":"Point"}
}