{
  "type": "Feature",
  "properties": {
    "addr:full":"4714 Wesconnett Blvd Jacksonville FL 32210",
    "addr:housenumber":"4714",
    "addr:postcode":"32210",
    "addr:street":"Wesconnett Blvd",
    "iso:country":"US",
    "sg:address":"4714 Wesconnett Blvd",
    "sg:city":"Jacksonville",
    "sg:classifiers":[
        {
            "category":"Freight",
            "type":"Transportation"
        }
    ],
    "sg:phone":"+1 904 778 4686",
    "sg:postcode":"32210",
    "sg:province":"FL",
    "sg:tags":[
        "commercial",
        "storage"
    ],
    "wof:name":"U-Stor",
    "wof:placetype":"venue"
},
  "geometry": {"coordinates":[-81.740087,30.258372],"type":"Point"}
}