{
  "type": "Feature",
  "properties": {
    "addr:full":"1005 Berean Ct Chipley FL 32428",
    "addr:housenumber":"1005",
    "addr:postcode":"32428",
    "addr:street":"Berean Ct",
    "iso:country":"US",
    "sg:address":"1005 Berean Ct",
    "sg:city":"Chipley",
    "sg:classifiers":[
        {
            "category":"Shopping",
            "subcategory":"Computers & Home Electronics",
            "type":"Retail Goods"
        }
    ],
    "sg:phone":"+1 850 638 1906",
    "sg:postcode":"32428",
    "sg:province":"FL",
    "wof:name":"Alive Productions",
    "wof:placetype":"venue"
},
  "geometry": {"coordinates":[-85.55327800000001,30.75607],"type":"Point"}
}