{
  "type": "Feature",
  "properties": {
    "addr:full":"1313 SW 32nd St Fort Lauderdale FL 33315",
    "addr:housenumber":"1313",
    "addr:postcode":"33315",
    "addr:street":"Sw 32Nd St",
    "iso:country":"US",
    "sg:address":"1313 SW 32nd St",
    "sg:city":"Fort Lauderdale",
    "sg:classifiers":[
        {
            "category":"Building & Trades",
            "subcategory":"Construction",
            "type":"Services"
        }
    ],
    "sg:phone":"+1 954 763 4376",
    "sg:postcode":"33315",
    "sg:province":"FL",
    "sg:tags":[
        "house",
        "nonresidential"
    ],
    "wof:name":"Wilco Construction Co Florida",
    "wof:placetype":"venue"
},
  "geometry": {"coordinates":[-80.159341,26.085597],"type":"Point"}
}