{
  "type": "Feature",
  "properties": {
    "addr:full":"7010 SW 79th Ter Miami FL 33143",
    "addr:housenumber":"7010",
    "addr:postcode":"33143",
    "addr:street":"Sw 79Th Ter",
    "iso:country":"US",
    "sg:address":"7010 SW 79th Ter",
    "sg:city":"Miami",
    "sg:classifiers":[
        {
            "category":"Wholesale",
            "subcategory":"Construction Materials",
            "type":"Manufacturing & Wholesale Goods"
        }
    ],
    "sg:phone":"+1 305 591 2220",
    "sg:postcode":"33143",
    "sg:province":"FL",
    "sg:tags":[
        "mixed",
        "concrete-ready"
    ],
    "wof:name":"Miami Readymix Inc",
    "wof:placetype":"venue"
},
  "geometry": {"coordinates":[-80.30723,25.696657],"type":"Point"}
}