{
  "type": "Feature",
  "properties": {
    "iso:country":"US",
    "sg:address":"2136 Ridge Dr",
    "sg:city":"Winter Park",
    "sg:classifiers":[
        {
            "category":"Manufacturing",
            "subcategory":"Printing",
            "type":"Manufacturing & Wholesale Goods"
        }
    ],
    "sg:phone":"+1 407 353 0315",
    "sg:postcode":"32792",
    "sg:province":"FL",
    "sg:tags":[
        "publisher"
    ],
    "wof:name":"BLS Publishing",
    "wof:placetype":"venue"
},
  "geometry": {"coordinates":[-81.317232,28.620144],"type":"Point"}
}