{
  "type": "Feature",
  "properties": {
    "iso:country":"US",
    "sg:address":"122 NE 17th St",
    "sg:city":"Homestead",
    "sg:classifiers":[
        {
            "category":"Building & Trades",
            "subcategory":"Plumbing",
            "type":"Services"
        }
    ],
    "sg:phone":"+1 305 248 6071",
    "sg:postcode":"33030",
    "sg:province":"FL",
    "sg:tags":[
        "contractor"
    ],
    "wof:name":"Tom Milner Plumbing",
    "wof:placetype":"venue"
},
  "geometry": {"coordinates":[-80.474299,25.486239],"type":"Point"}
}