{
  "type": "Feature",
  "properties": {
    "iso:country":"US",
    "sg:address":"1730 Shadowood Ln",
    "sg:city":"Jacksonville",
    "sg:classifiers":[
        {
            "category":"Real Estate",
            "subcategory":"Real Estate Agent",
            "type":"Services"
        }
    ],
    "sg:phone":"+1 904 396 2061",
    "sg:postcode":"32207",
    "sg:province":"FL",
    "sg:tags":[
        "management"
    ],
    "wof:name":"Property Investment Service",
    "wof:placetype":"venue"
},
  "geometry": {"coordinates":[-81.616384,30.307329],"type":"Point"}
}