{
  "type": "Feature",
  "properties": {
    "iso:country":"US",
    "sg:address":"5100 W Copans Rd",
    "sg:city":"Pompano Beach",
    "sg:classifiers":[
        {
            "category":"Utilities",
            "subcategory":"Telephone",
            "type":"Services"
        }
    ],
    "sg:phone":"+1 954 974 5818",
    "sg:postcode":"33063",
    "sg:province":"FL",
    "sg:tags":[
        "web",
        "host",
        "design",
        "page",
        "internet"
    ],
    "wof:name":"Medianet Group Tech Inc",
    "wof:placetype":"venue"
},
  "geometry": {"coordinates":[-80.19350900000001,26.256992],"type":"Point"}
}