{
  "type": "Feature",
  "properties": {
    "iso:country":"US",
    "sg:address":"7225 NW 25th St",
    "sg:city":"Miami",
    "sg:classifiers":[
        {
            "category":"Professional",
            "subcategory":"Business Services",
            "type":"Services"
        }
    ],
    "sg:phone":"+1 305 594 3047",
    "sg:postcode":"33122",
    "sg:province":"FL",
    "sg:tags":[
        "exporter"
    ],
    "wof:name":"M & R Associates",
    "wof:placetype":"venue"
},
  "geometry": {"coordinates":[-80.313445,25.797056],"type":"Point"}
}