{
  "type": "Feature",
  "properties": {
    "addr:full":"4712 Olive Branch Rd # 404 Orlando FL 32811",
    "addr:housenumber":"4712",
    "addr:postcode":"32811",
    "addr:street":"Olive Branch Rd # 404",
    "iso:country":"US",
    "sg:address":"4712 Olive Branch Rd # 404",
    "sg:city":"Orlando",
    "sg:classifiers":[
        {
            "category":"Shopping",
            "subcategory":"Pets & Pet Supplies",
            "type":"Retail Goods"
        }
    ],
    "sg:phone":"+1 407 903 0621",
    "sg:postcode":"32811",
    "sg:province":"FL",
    "sg:tags":[
        "furnishing",
        "dog",
        "store",
        "cat"
    ],
    "wof:name":"Whisker Watchers Pet Sitt",
    "wof:placetype":"venue"
},
  "geometry": {"coordinates":[-81.43828000000001,28.494269],"type":"Point"}
}