{
  "type": "Feature",
  "properties": {
    "addr:full":"9899 Springlake Cir Estero FL 33928",
    "addr:housenumber":"9899",
    "addr:postcode":"33928",
    "addr:street":"Springlake Cir",
    "iso:country":"US",
    "sg:address":"9899 Springlake Cir",
    "sg:city":"Estero",
    "sg:classifiers":[
        {
            "category":"Manufacturing",
            "subcategory":"Chemicals & Compounds",
            "type":"Manufacturing & Wholesale Goods"
        },
        {
            "category":"Building & Trades",
            "subcategory":"Cleaning & Sanitation",
            "type":"Services"
        },
        {
            "category":"Building & Trades",
            "subcategory":"Equipment Rental",
            "type":"Services"
        },
        {
            "category":"Organizations",
            "subcategory":"Professional Association",
            "type":"Services"
        }
    ],
    "sg:phone":"+1 239 992 7519",
    "sg:postcode":"33928",
    "sg:province":"FL",
    "sg:tags":[
        "industrial",
        "washing",
        "indust-wholesale",
        "power",
        "commercial",
        "systems-pressure",
        "steam",
        "manufacturer"
    ],
    "wof:name":"Advanced Pressure Cleaning Of Florida",
    "wof:placetype":"venue"
},
  "geometry": {"coordinates":[-81.790071,26.4238],"type":"Point"}
}