{
  "type": "Feature",
  "properties": {
    "iso:country":"US",
    "sg:address":"9701 E Highway 25 Lot 155",
    "sg:city":"Belleview",
    "sg:classifiers":[
        {
            "category":"Building & Trades",
            "subcategory":"Landscaping Services",
            "type":"Services"
        }
    ],
    "sg:phone":"+1 352 307 7343",
    "sg:postcode":"34420",
    "sg:province":"FL",
    "sg:tags":[
        "landscape",
        "contractor"
    ],
    "wof:name":"Jack Blakesslee Landscaping",
    "wof:placetype":"venue"
},
  "geometry": {"coordinates":[-81.991439,29.048176],"type":"Point"}
}