{
  "type": "Feature",
  "properties": {
    "iso:country":"US",
    "sg:address":"601 N Federal Hwy",
    "sg:city":"Boca Raton",
    "sg:classifiers":[
        {
            "category":"Home & Garden",
            "subcategory":"Furniture",
            "type":"Retail Goods"
        }
    ],
    "sg:phone":"+1 561 368 2565",
    "sg:postcode":"33432",
    "sg:province":"FL",
    "wof:name":"City Furniture Inc",
    "wof:placetype":"venue"
},
  "geometry": {"coordinates":[-80.086371,26.355964],"type":"Point"}
}