{
  "type": "Feature",
  "properties": {
    "iso:country":"US",
    "sg:address":"178 Golf Club Dr",
    "sg:city":"Longwood",
    "sg:classifiers":[
        {
            "category":"Professional",
            "subcategory":"Computer Services",
            "type":"Services"
        }
    ],
    "sg:phone":"+1 407 869 5394",
    "sg:postcode":"32779",
    "sg:province":"FL",
    "sg:tags":[
        "information",
        "retrieval"
    ],
    "wof:name":"Merlins Data Research",
    "wof:placetype":"venue"
},
  "geometry": {"coordinates":[-81.448668,28.691456],"type":"Point"}
}