{
  "type": "Feature",
  "properties": {
    "iso:country":"US",
    "sg:address":"17420 Butler Rd",
    "sg:city":"Fort Myers",
    "sg:classifiers":[
        {
            "category":"Professional",
            "type":"Services"
        }
    ],
    "sg:phone":"+1 239 267 1805",
    "sg:postcode":"33967",
    "sg:province":"FL",
    "wof:name":"Hewitt Services Inc",
    "wof:placetype":"venue"
},
  "geometry": {"coordinates":[-81.812228,26.482542],"type":"Point"}
}