{
  "type": "Feature",
  "properties": {
    "iso:country":"US",
    "sg:address":"10131 W Forest Hill Blvd # 201",
    "sg:city":"Wellington",
    "sg:classifiers":[
        {
            "category":"Health Services",
            "subcategory":"Doctor",
            "type":"Services"
        }
    ],
    "sg:phone":"+1 561 996 8017",
    "sg:postcode":"33414",
    "sg:province":"FL",
    "sg:tags":[
        "physician",
        "family",
        "practice",
        "surgeons",
        "medicine"
    ],
    "wof:name":"Sundaram, Dr V S Md",
    "wof:placetype":"venue"
},
  "geometry": {"coordinates":[-80.205056,26.650827],"type":"Point"}
}