{
  "type": "Feature",
  "properties": {
    "iso:country":"US",
    "sg:address":"2012 Sabal Palm Dr",
    "sg:city":"Edgewater",
    "sg:classifiers":[
        {
            "category":"Building & Trades",
            "subcategory":"Construction",
            "type":"Services"
        }
    ],
    "sg:phone":"+1 386 428 9342",
    "sg:postcode":"32141",
    "sg:province":"FL",
    "sg:tags":[
        "roofing",
        "contractor"
    ],
    "wof:name":"Ferguson Roofing Inc",
    "wof:placetype":"venue"
},
  "geometry": {"coordinates":[-80.91018,28.961105],"type":"Point"}
}