{
  "type": "Feature",
  "properties": {
    "addr:full":"1950 Tamiami Trl N Naples FL 34102",
    "addr:housenumber":"1950",
    "addr:postcode":"34102",
    "addr:street":"Tamiami Trl N",
    "iso:country":"US",
    "sg:address":"1950 Tamiami Trl N",
    "sg:city":"Naples",
    "sg:classifiers":[
        {
            "category":"Shopping",
            "type":"Retail Goods"
        }
    ],
    "sg:phone":"+1 239 261 2287",
    "sg:postcode":"34102",
    "sg:province":"FL",
    "sg:tags":[
        "cosmetic",
        "perfume"
    ],
    "wof:name":"Merle Norman Cosmetics",
    "wof:placetype":"venue"
},
  "geometry": {"coordinates":[-81.79929199999999,26.16886],"type":"Point"}
}