{
  "type": "Feature",
  "properties": {
    "addr:full":"1670 NW 119th St Miami FL 33167",
    "addr:housenumber":"1670",
    "addr:postcode":"33167",
    "addr:street":"Nw 119Th St",
    "iso:country":"US",
    "sg:address":"1670 NW 119th St",
    "sg:city":"Miami",
    "sg:classifiers":[
        {
            "category":"Food & Beverages",
            "subcategory":"Groceries & Convenience Stores",
            "type":"Retail Goods"
        }
    ],
    "sg:phone":"+1 305 681 5432",
    "sg:postcode":"33167",
    "sg:province":"FL",
    "wof:name":"119th St Grocery",
    "wof:placetype":"venue"
},
  "geometry": {"coordinates":[-80.22640199999999,25.8832],"type":"Point"}
}