{
  "type": "Feature",
  "properties": {
    "iso:country":"US",
    "sg:address":"1508 Cedar St",
    "sg:city":"Lake Placid",
    "sg:classifiers":[
        {
            "category":"Taxi",
            "type":"Transportation"
        }
    ],
    "sg:phone":"+1 863 699 6262",
    "sg:postcode":"33852",
    "sg:province":"FL",
    "sg:tags":[
        "taxicab"
    ],
    "wof:name":"Mr Taxi",
    "wof:placetype":"venue"
},
  "geometry": {"coordinates":[-81.31843499999999,27.32014],"type":"Point"}
}