{
  "type": "Feature",
  "properties": {
    "iso:country":"US",
    "sg:address":"146 Pondella Rd",
    "sg:city":"Fort Myers",
    "sg:classifiers":[
        {
            "category":"Building & Trades",
            "subcategory":"Construction",
            "type":"Services"
        }
    ],
    "sg:phone":"+1 239 652 0466",
    "sg:postcode":"33903",
    "sg:province":"FL",
    "sg:tags":[
        "contractor"
    ],
    "wof:name":"Affordable Gutters By Kyle Mul",
    "wof:placetype":"venue"
},
  "geometry": {"coordinates":[-81.88670399999999,26.667364],"type":"Point"}
}