{
  "type": "Feature",
  "properties": {
    "iso:country":"US",
    "sg:address":"321 Peruvian Ave",
    "sg:city":"Palm Beach",
    "sg:classifiers":[
        {
            "category":"Banks & Credit Unions",
            "subcategory":"Bank",
            "type":"Services"
        }
    ],
    "sg:phone":"+1 561 838 4320",
    "sg:postcode":"33480",
    "sg:province":"FL",
    "wof:name":"Fifth Third Bank",
    "wof:placetype":"venue"
},
  "geometry": {"coordinates":[-80.04067499999999,26.701816],"type":"Point"}
}