{
  "type": "Feature",
  "properties": {
    "iso:country":"US",
    "sg:address":"5407 W Irlo Bronson Memorial Hwy",
    "sg:city":"Kissimmee",
    "sg:classifiers":[
        {
            "category":"Professional",
            "type":"Services"
        }
    ],
    "sg:phone":"+1 407 787 4292",
    "sg:postcode":"34746",
    "sg:province":"FL",
    "sg:tags":[
        "establishment"
    ],
    "wof:name":"Sticker Station",
    "wof:placetype":"venue"
},
  "geometry": {"coordinates":[-81.499443,28.33281],"type":"Point"}
}