{
  "type": "Feature",
  "properties": {
    "addr:full":"3909 W Norfolk St Tampa FL 33614",
    "addr:housenumber":"3909",
    "addr:postcode":"33614",
    "addr:street":"W Norfolk St",
    "iso:country":"US",
    "sg:address":"3909 W Norfolk St",
    "sg:city":"Tampa",
    "sg:classifiers":[
        {
            "category":"Insurance",
            "subcategory":"Life Insurance",
            "type":"Services"
        }
    ],
    "sg:phone":"+1 813 888 5223",
    "sg:postcode":"33614",
    "sg:province":"FL",
    "sg:tags":[
        "carrier"
    ],
    "wof:name":"Linfernal Providencia Lif",
    "wof:placetype":"venue"
},
  "geometry": {"coordinates":[-82.50598599999999,28.011146],"type":"Point"}
}