{
  "type": "Feature",
  "properties": {
    "addr:full":"2901 W Broward Blvd Fort Lauderdale FL 33312",
    "addr:housenumber":"2901",
    "addr:postcode":"33312",
    "addr:street":"W Broward Blvd",
    "iso:country":"US",
    "sg:address":"2901 W Broward Blvd",
    "sg:city":"Fort Lauderdale",
    "sg:classifiers":[
        {
            "category":"Health Services",
            "subcategory":"Clinic",
            "type":"Services"
        }
    ],
    "sg:phone":"+1 954 327 0809",
    "sg:postcode":"33312",
    "sg:province":"FL",
    "sg:tags":[
        "banks",
        "blood",
        "center"
    ],
    "wof:name":"Continental Services Group Inc",
    "wof:placetype":"venue"
},
  "geometry": {"coordinates":[-80.18307900000001,26.121344],"type":"Point"}
}