{
  "type": "Feature",
  "properties": {
    "iso:country":"US",
    "sg:address":"910 3rd St",
    "sg:city":"Neptune Beach",
    "sg:classifiers":[
        {
            "category":"Health Services",
            "subcategory":"Health Practitioner",
            "type":"Services"
        }
    ],
    "sg:phone":"+1 904 247 5669",
    "sg:postcode":"32266",
    "sg:province":"FL",
    "sg:tags":[
        "psychotherapist"
    ],
    "wof:name":"Atlantic Family Institute",
    "wof:placetype":"venue"
},
  "geometry": {"coordinates":[-81.397188,30.316705],"type":"Point"}
}