{
  "type": "Feature",
  "properties": {
    "iso:country":"US",
    "sg:address":"2319 River Tree Cir",
    "sg:city":"Sanford",
    "sg:classifiers":[
        {
            "category":"Professional",
            "subcategory":"Business Services",
            "type":"Services"
        }
    ],
    "sg:phone":"+1 407 625 9593",
    "sg:postcode":"32771",
    "sg:province":"FL",
    "wof:name":"Love Design Inc",
    "wof:placetype":"venue"
},
  "geometry": {"coordinates":[-81.411247,28.795911],"type":"Point"}
}