{
  "type": "Feature",
  "properties": {
    "iso:country":"US",
    "sg:address":"675 W 83rd St",
    "sg:city":"Hialeah",
    "sg:classifiers":[
        {
            "category":"Retail",
            "subcategory":"Auto Repair",
            "type":"Services"
        }
    ],
    "sg:phone":"+1 305 558 3371",
    "sg:postcode":"33014",
    "sg:province":"FL",
    "sg:tags":[
        "repairing",
        "automobile"
    ],
    "wof:name":"Barlow's Complete Auto Service",
    "wof:placetype":"venue"
},
  "geometry": {"coordinates":[-80.29740099999999,25.8978],"type":"Point"}
}