{
  "type": "Feature",
  "properties": {
    "addr:full":"103200 Overseas Hwy Key Largo FL 33037",
    "addr:housenumber":"103200",
    "addr:postcode":"33037",
    "addr:street":"Overseas Hwy",
    "iso:country":"US",
    "sg:address":"103200 Overseas Hwy",
    "sg:city":"Key Largo",
    "sg:classifiers":[
        {
            "category":"Home & Garden",
            "subcategory":"Furniture",
            "type":"Retail Goods"
        }
    ],
    "sg:phone":"+1 305 453 0065",
    "sg:postcode":"33037",
    "sg:province":"FL",
    "wof:name":"White Rhino Consignments",
    "wof:placetype":"venue"
},
  "geometry": {"coordinates":[-80.405501,25.134057],"type":"Point"}
}