{
  "type": "Feature",
  "properties": {
    "addr:full":"21302 Front Beach Rd Panama City Bch FL 32413",
    "addr:housenumber":"21302",
    "addr:postcode":"32413",
    "addr:street":"Front Beach Rd",
    "iso:country":"US",
    "sg:address":"21302 Front Beach Rd",
    "sg:city":"Panama City Bch",
    "sg:classifiers":[
        {
            "category":"Freight",
            "type":"Transportation"
        }
    ],
    "sg:phone":"+1 850 233 6186",
    "sg:postcode":"32413",
    "sg:province":"FL",
    "sg:tags":[
        "commercial",
        "storage"
    ],
    "wof:name":"Coast To Coast Svc",
    "wof:placetype":"venue"
},
  "geometry": {"coordinates":[-85.949851,30.250983],"type":"Point"}
}