{
  "type": "Feature",
  "properties": {
    "iso:country":"US",
    "sg:address":"2710 Dupont Ave",
    "sg:city":"Jacksonville",
    "sg:classifiers":[
        {
            "category":"Education",
            "subcategory":"School",
            "type":"Public Place"
        }
    ],
    "sg:phone":"+1 904 739 5200",
    "sg:postcode":"32217",
    "sg:province":"FL",
    "sg:tags":[
        "middle"
    ],
    "sg:website":"http://www.duval.k12.fl.us",
    "wof:name":"Alfred I. Dupont Middle School",
    "wof:placetype":"venue"
},
  "geometry": {"coordinates":[-81.633545,30.250697],"type":"Point"}
}