{
  "type": "Feature",
  "properties": {
    "addr:full":"5043 Tamiami Trl Naples FL 34113",
    "addr:housenumber":"5043",
    "addr:postcode":"34113",
    "addr:street":"Tamiami Trl",
    "iso:country":"US",
    "sg:address":"5043 Tamiami Trl",
    "sg:city":"Naples",
    "sg:classifiers":[
        {
            "category":"Communications",
            "subcategory":"Radio Station",
            "type":"Services"
        }
    ],
    "sg:phone":"+1 239 530 1660",
    "sg:postcode":"34113",
    "sg:province":"FL",
    "sg:tags":[
        "company",
        "broadcasting"
    ],
    "wof:name":"News Radio",
    "wof:placetype":"venue"
},
  "geometry": {"coordinates":[-81.747918,26.107426],"type":"Point"}
}