{
  "type": "Feature",
  "properties": {
    "iso:country":"US",
    "sg:address":"3951 Mercantile Ave",
    "sg:city":"Naples",
    "sg:classifiers":[
        {
            "category":"Autos & Motor Vehicles",
            "subcategory":"Auto Supplies",
            "type":"Retail Goods"
        }
    ],
    "sg:phone":"+1 239 434 6330",
    "sg:postcode":"34104",
    "sg:province":"FL",
    "sg:tags":[
        "equipment",
        "racing",
        "car",
        "automobile"
    ],
    "wof:name":"Debold Performance Inc",
    "wof:placetype":"venue"
},
  "geometry": {"coordinates":[-81.764141,26.166123],"type":"Point"}
}