{
  "type": "Feature",
  "properties": {
    "addr:full":"1610 Palmland Dr Boynton Beach FL 33436",
    "addr:housenumber":"1610",
    "addr:postcode":"33436",
    "addr:street":"Palmland Dr",
    "iso:country":"US",
    "sg:address":"1610 Palmland Dr",
    "sg:city":"Boynton Beach",
    "sg:classifiers":[
        {
            "category":"Organizations",
            "subcategory":"Professional Association",
            "type":"Services"
        }
    ],
    "sg:phone":"+1 561 734 9393",
    "sg:postcode":"33436",
    "sg:province":"FL",
    "wof:name":"Chanteclair Villas Recreation",
    "wof:placetype":"venue"
},
  "geometry": {"coordinates":[-80.09473,26.498906],"type":"Point"}
}