{
  "type": "Feature",
  "properties": {
    "addr:full":"5375 N Eagle Rd Saint Cloud FL 34771",
    "addr:housenumber":"5375",
    "addr:postcode":"34771",
    "addr:street":"N Eagle Rd",
    "iso:country":"US",
    "sg:address":"5375 N Eagle Rd",
    "sg:city":"Saint Cloud",
    "sg:classifiers":[
        {
            "category":"Building & Trades",
            "subcategory":"Construction",
            "type":"Services"
        }
    ],
    "sg:phone":"+1 407 892 0048",
    "sg:postcode":"34771",
    "sg:province":"FL",
    "sg:tags":[
        "contractor"
    ],
    "wof:name":"Daniel Brockhaus Drywall",
    "wof:placetype":"venue"
},
  "geometry": {"coordinates":[-81.22511799999999,28.293101],"type":"Point"}
}