{
  "type": "Feature",
  "properties": {
    "iso:country":"US",
    "sg:address":"5335 Brown St",
    "sg:city":"Graceville",
    "sg:classifiers":[
        {
            "category":"Wholesale",
            "subcategory":"Apparel",
            "type":"Manufacturing & Wholesale Goods"
        }
    ],
    "sg:phone":"+1 850 263 3322",
    "sg:postcode":"32440",
    "sg:province":"FL",
    "sg:tags":[
        "piece"
    ],
    "wof:name":"Crafty Cats",
    "wof:placetype":"venue"
},
  "geometry": {"coordinates":[-85.514686,30.964855],"type":"Point"}
}