{
  "type": "Feature",
  "properties": {
    "iso:country":"US",
    "sg:address":"2220 SW Susset Ln",
    "sg:city":"Port St Lucie",
    "sg:classifiers":[
        {
            "category":"Airport",
            "type":"Transportation"
        }
    ],
    "sg:phone":"+1 772 336 7244",
    "sg:postcode":"34953",
    "sg:province":"FL",
    "sg:tags":[
        "aircraft",
        "maintenance"
    ],
    "wof:name":"Petri Professional Pilots",
    "wof:placetype":"venue"
},
  "geometry": {"coordinates":[-80.37387099999999,27.276018],"type":"Point"}
}