{
  "type": "Feature",
  "properties": {
    "addr:full":"1416 Casey Key Rd Nokomis FL 34275",
    "addr:housenumber":"1416",
    "addr:postcode":"34275",
    "addr:street":"Casey Key Rd",
    "iso:country":"US",
    "sg:address":"1416 Casey Key Rd",
    "sg:city":"Nokomis",
    "sg:classifiers":[
        {
            "category":"Manufacturing",
            "subcategory":"Printing",
            "type":"Manufacturing & Wholesale Goods"
        }
    ],
    "sg:phone":"+1 941 480 9644",
    "sg:postcode":"34275",
    "sg:province":"FL",
    "sg:tags":[
        "publisher"
    ],
    "wof:name":"Beacham Publishing",
    "wof:placetype":"venue"
},
  "geometry": {"coordinates":[-82.487437,27.161978],"type":"Point"}
}