{
  "type": "Feature",
  "properties": {
    "addr:full":"3501 S US Hwy 1 Fort Pierce FL 34982",
    "addr:housenumber":"3501",
    "addr:postcode":"34982",
    "addr:street":"S Us Hwy 1",
    "iso:country":"US",
    "sg:address":"3501 S US Hwy 1",
    "sg:city":"Fort Pierce",
    "sg:classifiers":[
        {
            "category":"Government",
            "subcategory":"Office",
            "type":"Public Place"
        }
    ],
    "sg:phone":"+1 772 468 3976",
    "sg:postcode":"34982",
    "sg:province":"FL",
    "wof:name":"Plant Industry Div",
    "wof:placetype":"venue"
},
  "geometry": {"coordinates":[-80.32562900000001,27.39661],"type":"Point"}
}