{
  "type": "Feature",
  "properties": {
    "iso:country":"US",
    "sg:address":"2425 SW 128th Ave",
    "sg:city":"Miami",
    "sg:classifiers":[
        {
            "category":"Professional",
            "subcategory":"Management & Consulting",
            "type":"Services"
        }
    ],
    "sg:phone":"+1 305 220 0547",
    "sg:postcode":"33175",
    "sg:province":"FL",
    "sg:tags":[
        "business"
    ],
    "wof:name":"K & E Holdings Group Inc",
    "wof:placetype":"venue"
},
  "geometry": {"coordinates":[-80.402137,25.745441],"type":"Point"}
}