{
  "type": "Feature",
  "properties": {
    "iso:country":"US",
    "sg:address":"7057 Holiday Dr",
    "sg:city":"Spring Hill",
    "sg:classifiers":[
        {
            "category":"Insurance",
            "subcategory":"Insurance Agent",
            "type":"Services"
        }
    ],
    "sg:phone":"+1 352 232 1471",
    "sg:postcode":"34606",
    "sg:province":"FL",
    "wof:name":"Excess Gear",
    "wof:placetype":"venue"
},
  "geometry": {"coordinates":[-82.60615300000001,28.451004],"type":"Point"}
}