{
  "type": "Feature",
  "properties": {
    "iso:country":"US",
    "sg:address":"5837 Main St",
    "sg:city":"New Port Richey",
    "sg:classifiers":[
        {
            "category":"Wholesale",
            "subcategory":"Drugs",
            "type":"Manufacturing & Wholesale Goods"
        }
    ],
    "sg:phone":"+1 727 849 8782",
    "sg:postcode":"34652",
    "sg:province":"FL",
    "wof:name":"NPR Canadian Meds",
    "wof:placetype":"venue"
},
  "geometry": {"coordinates":[-82.718007,28.250299],"type":"Point"}
}