{
  "type": "Feature",
  "properties": {
    "iso:country":"US",
    "sg:address":"12095 179th Ct N",
    "sg:city":"Jupiter",
    "sg:classifiers":[
        {
            "category":"Professional",
            "subcategory":"Business Services",
            "type":"Services"
        }
    ],
    "sg:phone":"+1 561 346 7997",
    "sg:postcode":"33478",
    "sg:province":"FL",
    "wof:name":"George G Simpson Jr",
    "wof:placetype":"venue"
},
  "geometry": {"coordinates":[-80.225263,26.941467],"type":"Point"}
}