{
  "type": "Feature",
  "properties": {
    "iso:country":"US",
    "sg:address":"535 Cassia Blvd",
    "sg:city":"Satellite Beach",
    "sg:classifiers":[
        {
            "category":"Organizations",
            "subcategory":"Religious Organization",
            "type":"Services"
        }
    ],
    "sg:phone":"+1 321 777 7118",
    "sg:postcode":"32937",
    "sg:province":"FL",
    "wof:name":"Heartsprings International Min",
    "wof:placetype":"venue"
},
  "geometry": {"coordinates":[-80.60336100000001,28.17229],"type":"Point"}
}