{
  "type": "Feature",
  "properties": {
    "iso:country":"US",
    "sg:address":"6089 W Hwy 98",
    "sg:city":"Panama City",
    "sg:classifiers":[
        {
            "category":"Building & Trades",
            "subcategory":"Electrical",
            "type":"Services"
        }
    ],
    "sg:phone":"+1 850 763 5657",
    "sg:postcode":"32405",
    "sg:province":"FL",
    "sg:tags":[
        "electrical",
        "contractor"
    ],
    "wof:name":"Miller Electric Co",
    "wof:placetype":"venue"
},
  "geometry": {"coordinates":[-85.73203700000001,30.185558],"type":"Point"}
}