{
  "type": "Feature",
  "properties": {
    "addr:full":"6601 8th St SW Miami FL 33144",
    "addr:housenumber":"6601",
    "addr:postcode":"33144",
    "addr:street":"8Th St Sw",
    "iso:country":"US",
    "sg:address":"6601 8th St SW",
    "sg:city":"Miami",
    "sg:classifiers":[
        {
            "category":"Retail",
            "subcategory":"Laundry & Dry Cleaning",
            "type":"Services"
        }
    ],
    "sg:phone":"+1 305 269 9664",
    "sg:postcode":"33144",
    "sg:province":"FL",
    "sg:tags":[
        "cleaners"
    ],
    "wof:name":"Cleaner R 'Us'",
    "wof:placetype":"venue"
},
  "geometry": {"coordinates":[-80.303901,25.763099],"type":"Point"}
}