{
  "type": "Feature",
  "properties": {
    "addr:full":"9734 Katy Dr Hudson FL 34667",
    "addr:housenumber":"9734",
    "addr:postcode":"34667",
    "addr:street":"Katy Dr",
    "iso:country":"US",
    "sg:address":"9734 Katy Dr",
    "sg:city":"Hudson",
    "sg:classifiers":[
        {
            "category":"Building & Trades",
            "subcategory":"Plumbing",
            "type":"Services"
        }
    ],
    "sg:phone":"+1 727 868 5339",
    "sg:postcode":"34667",
    "sg:province":"FL",
    "sg:tags":[
        "conditioning",
        "air",
        "system",
        "contractor"
    ],
    "wof:name":"Hudson Heating & Cooling",
    "wof:placetype":"venue"
},
  "geometry": {"coordinates":[-82.655028,28.403587],"type":"Point"}
}