{
  "type": "Feature",
  "properties": {
    "iso:country":"US",
    "sg:address":"2560 NE Dixie Hwy",
    "sg:city":"Jensen Beach",
    "sg:classifiers":[
        {
            "category":"Real Estate",
            "subcategory":"Real Estate Operator",
            "type":"Services"
        }
    ],
    "sg:phone":"+1 772 334 4588",
    "sg:postcode":"34957",
    "sg:province":"FL",
    "sg:tags":[
        "apartment"
    ],
    "wof:name":"Riverwatch Apartments",
    "wof:placetype":"venue"
},
  "geometry": {"coordinates":[-80.22008700000001,27.229016],"type":"Point"}
}