{
  "type": "Feature",
  "properties": {
    "iso:country":"US",
    "sg:address":"800 2nd Ave NE",
    "sg:city":"St Petersburg",
    "sg:classifiers":[
        {
            "category":"Restaurant",
            "type":"Food & Drink"
        }
    ],
    "sg:phone":"+1 727 822 6655",
    "sg:postcode":"33701",
    "sg:province":"FL",
    "wof:name":"Cha Cha Coconuts",
    "wof:placetype":"venue"
},
  "geometry": {"coordinates":[-82.630684,27.773648],"type":"Point"}
}