{
  "type": "Feature",
  "properties": {
    "iso:country":"US",
    "sg:address":"348 Chicago Woods Cir",
    "sg:city":"Orlando",
    "sg:classifiers":[
        {
            "category":"Building & Trades",
            "subcategory":"Construction",
            "type":"Services"
        }
    ],
    "sg:phone":"+1 321 299 5608",
    "sg:postcode":"32824",
    "sg:province":"FL",
    "sg:tags":[
        "contractor"
    ],
    "wof:name":"Wood Msters Multiservice Rmdlg",
    "wof:placetype":"venue"
},
  "geometry": {"coordinates":[-81.371498,28.374688],"type":"Point"}
}