{
  "type": "Feature",
  "properties": {
    "addr:full":"6160 SW 84th St Miami FL 33143",
    "addr:housenumber":"6160",
    "addr:postcode":"33143",
    "addr:street":"Sw 84Th St",
    "iso:country":"US",
    "sg:address":"6160 SW 84th St",
    "sg:city":"Miami",
    "sg:classifiers":[
        {
            "category":"Professional",
            "subcategory":"Lawyer & Legal Services",
            "type":"Services"
        }
    ],
    "sg:phone":"+1 305 577 7085",
    "sg:postcode":"33143",
    "sg:province":"FL",
    "wof:name":"Steel Hector & Davis",
    "wof:placetype":"venue"
},
  "geometry": {"coordinates":[-80.29243099999999,25.692996],"type":"Point"}
}