{
  "type": "Feature",
  "properties": {
    "addr:full":"Deland Deland FL 32720",
    "addr:postcode":"32720",
    "iso:country":"US",
    "sg:address":"Deland",
    "sg:city":"Deland",
    "sg:classifiers":[
        {
            "category":"Professional",
            "subcategory":"Lawyer & Legal Services",
            "type":"Services"
        }
    ],
    "sg:phone":"+1 386 734 7373",
    "sg:postcode":"32720",
    "sg:province":"FL",
    "sg:website":"www.stepniaklaw.com",
    "wof:name":"Stepniak Wrenn PA",
    "wof:placetype":"venue"
},
  "geometry": {"coordinates":[-81.317249,29.044596],"type":"Point"}
}