{
  "type": "Feature",
  "properties": {
    "addr:full":"380 N State Rd 434 Altamonte Springs FL 32714",
    "addr:housenumber":"380",
    "addr:postcode":"32714",
    "addr:street":"N State Rd 434",
    "iso:country":"US",
    "sg:address":"380 N State Rd 434",
    "sg:city":"Altamonte Springs",
    "sg:classifiers":[
        {
            "category":"Restaurant",
            "type":"Food & Drink"
        }
    ],
    "sg:phone":"+1 407 862 6688",
    "sg:postcode":"32714",
    "sg:province":"FL",
    "sg:tags":[
        "sushi",
        "bar",
        "chinese"
    ],
    "wof:name":"Asian Express",
    "wof:placetype":"venue"
},
  "geometry": {"coordinates":[-81.419723,28.667116],"type":"Point"}
}