{
  "type": "Feature",
  "properties": {
    "addr:full":"18471 Dixie Hwy Miami FL 33157",
    "addr:housenumber":"18471",
    "addr:postcode":"33157",
    "addr:street":"Dixie Hwy",
    "iso:country":"US",
    "sg:address":"18471 Dixie Hwy",
    "sg:city":"Miami",
    "sg:classifiers":[
        {
            "category":"Shopping",
            "subcategory":"Computers & Home Electronics",
            "type":"Retail Goods"
        }
    ],
    "sg:phone":"+1 954 325 1027",
    "sg:postcode":"33157",
    "sg:province":"FL",
    "sg:tags":[
        "rental"
    ],
    "wof:name":"Cyberlan Inc",
    "wof:placetype":"venue"
},
  "geometry": {"coordinates":[-80.35490299999999,25.596945],"type":"Point"}
}