{
  "type": "Feature",
  "properties": {
    "addr:full":"1225 SW Magnolia Bluff Dr Palm City FL 34990",
    "addr:housenumber":"1225",
    "addr:postcode":"34990",
    "addr:street":"Sw Magnolia Bluff Dr",
    "iso:country":"US",
    "sg:address":"1225 SW Magnolia Bluff Dr",
    "sg:city":"Palm City",
    "sg:classifiers":[
        {
            "category":"Building & Trades",
            "subcategory":"Construction",
            "type":"Services"
        }
    ],
    "sg:phone":"+1 772 260 6062",
    "sg:postcode":"34990",
    "sg:province":"FL",
    "sg:tags":[
        "concrete",
        "contractor"
    ],
    "wof:name":"Spears Industries Inc",
    "wof:placetype":"venue"
},
  "geometry": {"coordinates":[-80.29281400000001,27.191041],"type":"Point"}
}