{
  "type": "Feature",
  "properties": {
    "iso:country":"US",
    "sg:address":"8047 Hammond Blvd",
    "sg:city":"Jacksonville",
    "sg:classifiers":[
        {
            "category":"Building & Trades",
            "subcategory":"Electrical",
            "type":"Services"
        }
    ],
    "sg:phone":"+1 904 781 3381",
    "sg:postcode":"32220",
    "sg:province":"FL",
    "sg:tags":[
        "electrical",
        "contractor"
    ],
    "wof:name":"James E Partin",
    "wof:placetype":"venue"
},
  "geometry": {"coordinates":[-81.782686,30.319379],"type":"Point"}
}