{
  "type": "Feature",
  "properties": {
    "iso:country":"US",
    "sg:address":"901 Woodlawn St Ste A",
    "sg:city":"Clearwater",
    "sg:phone":"+1 727 678 0818",
    "sg:postcode":"33756",
    "sg:province":"FL",
    "wof:name":"Taxi Service/Servicio de Taxi",
    "wof:placetype":"venue"
},
  "geometry": {"coordinates":[-82.792896,27.942571],"type":"Point"}
}