{
  "type": "Feature",
  "properties": {
    "iso:country":"US",
    "sg:address":"361 SE 8th St",
    "sg:city":"Pompano Beach",
    "sg:classifiers":[
        {
            "category":"Building & Trades",
            "subcategory":"Electrical",
            "type":"Services"
        }
    ],
    "sg:phone":"+1 954 941 0678",
    "sg:postcode":"33060",
    "sg:province":"FL",
    "sg:tags":[
        "electrical",
        "contractor"
    ],
    "wof:name":"Shocking Pink Electric",
    "wof:placetype":"venue"
},
  "geometry": {"coordinates":[-80.11949199999999,26.219887],"type":"Point"}
}