{
  "type": "Feature",
  "properties": {
    "addr:full":"246 1st St Bonita Springs FL 34134",
    "addr:housenumber":"246",
    "addr:postcode":"34134",
    "addr:street":"1St St",
    "iso:country":"US",
    "sg:address":"246 1st St",
    "sg:city":"Bonita Springs",
    "sg:classifiers":[
        {
            "category":"Building & Trades",
            "subcategory":"Construction",
            "type":"Services"
        }
    ],
    "sg:phone":"+1 239 947 5354",
    "sg:postcode":"34134",
    "sg:province":"FL",
    "sg:tags":[
        "contractor"
    ],
    "wof:name":"Bonita Beach Home Svc Corp",
    "wof:placetype":"venue"
},
  "geometry": {"coordinates":[-81.828256,26.32933],"type":"Point"}
}