{
  "type": "Feature",
  "properties": {
    "iso:country":"US",
    "sg:address":"169 E Flagler St Ste 828",
    "sg:city":"Miami",
    "sg:classifiers":[
        {
            "category":"Real Estate",
            "subcategory":"Architect",
            "type":"Services"
        }
    ],
    "sg:phone":"+1 305 373 1960",
    "sg:postcode":"33131",
    "sg:province":"FL",
    "wof:name":"Trelles Architects",
    "wof:placetype":"venue"
},
  "geometry": {"coordinates":[-80.19090300000001,25.7742],"type":"Point"}
}