{
  "type": "Feature",
  "properties": {
    "iso:country":"US",
    "sg:address":"6323 NW 80th Ter",
    "sg:city":"Parkland",
    "sg:classifiers":[
        {
            "category":"Coffee & Tea",
            "type":"Food & Drink"
        },
        {
            "category":"Restaurant",
            "type":"Food & Drink"
        }
    ],
    "sg:phone":"+1 954 346 7830",
    "sg:postcode":"33067",
    "sg:province":"FL",
    "sg:tags":[
        "espresso"
    ],
    "wof:name":"Ritter S Cafe",
    "wof:placetype":"venue"
},
  "geometry": {"coordinates":[-80.233467,26.308688],"type":"Point"}
}