{
  "type": "Feature",
  "properties": {
    "addr:full":"3621 8th St SW Miami FL 33135",
    "addr:housenumber":"3621",
    "addr:postcode":"33135",
    "addr:street":"8Th St Sw",
    "iso:country":"US",
    "sg:address":"3621 8th St SW",
    "sg:city":"Miami",
    "sg:classifiers":[
        {
            "category":"Shopping",
            "subcategory":"Discount & Variety Stores",
            "type":"Retail Goods"
        },
        {
            "category":"Shopping",
            "subcategory":"Department Store",
            "type":"Retail Goods"
        }
    ],
    "sg:phone":"+1 305 461 2866",
    "sg:postcode":"33135",
    "sg:province":"FL",
    "sg:tags":[
        "shop"
    ],
    "wof:name":"Happy Dollar Inc",
    "wof:placetype":"venue"
},
  "geometry": {"coordinates":[-80.25373500000001,25.764809],"type":"Point"}
}