{
  "type": "Feature",
  "properties": {
    "addr:full":"1214 Memory Ln Lutz FL 33549",
    "addr:housenumber":"1214",
    "addr:postcode":"33549",
    "addr:street":"Memory Ln",
    "iso:country":"US",
    "sg:address":"1214 Memory Ln",
    "sg:city":"Lutz",
    "sg:classifiers":[
        {
            "category":"Building & Trades",
            "subcategory":"Construction",
            "type":"Services"
        }
    ],
    "sg:phone":"+1 813 909 1182",
    "sg:postcode":"33549",
    "sg:province":"FL",
    "sg:tags":[
        "carpentry",
        "contractor"
    ],
    "wof:name":"Joe Pero Carpentry Services In",
    "wof:placetype":"venue"
},
  "geometry": {"coordinates":[-82.446445,28.148453],"type":"Point"}
}