{
  "type": "Feature",
  "properties": {
    "iso:country":"US",
    "sg:address":"1 Alhambra Cir",
    "sg:city":"Coral Gables",
    "sg:classifiers":[
        {
            "category":"Manufacturing",
            "subcategory":"Tools & Machinery",
            "type":"Manufacturing & Wholesale Goods"
        }
    ],
    "sg:phone":"+1 786 552 1280",
    "sg:postcode":"33134",
    "sg:province":"FL",
    "sg:tags":[
        "computer"
    ],
    "wof:name":"IBM Power 9",
    "wof:placetype":"venue"
},
  "geometry": {"coordinates":[-80.255308,25.755065],"type":"Point"}
}