{
  "type": "Feature",
  "properties": {
    "iso:country":"US",
    "sg:address":"103 Highland Ave",
    "sg:city":"Pomona Park",
    "sg:classifiers":[
        {
            "category":"Government",
            "subcategory":"Office",
            "type":"Public Place"
        }
    ],
    "sg:phone":"+1 386 649 6094",
    "sg:postcode":"32157",
    "sg:province":"FL",
    "wof:name":"Supervisor Of Election",
    "wof:placetype":"venue"
},
  "geometry": {"coordinates":[-81.57268999999999,29.48155],"type":"Point"}
}