{
  "type": "Feature",
  "properties": {
    "addr:full":"11275 Felice Cir Boynton Beach FL 33437",
    "addr:housenumber":"11275",
    "addr:postcode":"33437",
    "addr:street":"Felice Cir",
    "iso:country":"US",
    "sg:address":"11275 Felice Cir",
    "sg:city":"Boynton Beach",
    "sg:classifiers":[
        {
            "category":"Professional",
            "type":"Services"
        }
    ],
    "sg:phone":"+1 561 733 2668",
    "sg:postcode":"33437",
    "sg:province":"FL",
    "sg:tags":[
        "arts",
        "artist"
    ],
    "wof:name":"Ruth Shapiro Artistry",
    "wof:placetype":"venue"
},
  "geometry": {"coordinates":[-80.16560200000001,26.508731],"type":"Point"}
}