{
  "type": "Feature",
  "properties": {
    "iso:country":"US",
    "sg:address":"4400 Inverrary Blvd",
    "sg:city":"Lauderhill",
    "sg:classifiers":[
        {
            "category":"Banks & Credit Unions",
            "subcategory":"Bank",
            "type":"Services"
        }
    ],
    "sg:phone":"+1 954 572 7078",
    "sg:postcode":"33319",
    "sg:province":"FL",
    "sg:tags":[
        "commercial",
        "national",
        "saving"
    ],
    "sg:website":"https://www.bankofamerica.com/",
    "wof:name":"Bank of America",
    "wof:placetype":"venue"
},
  "geometry": {"coordinates":[-80.239861,26.17926],"type":"Point"}
}