{
  "type": "Feature",
  "properties": {
    "iso:country":"US",
    "sg:address":"769 Dodecanese Blvd",
    "sg:city":"Tarpon Springs",
    "sg:classifiers":[
        {
            "category":"Restaurant",
            "type":"Food & Drink"
        }
    ],
    "sg:menulink":"http://www.allmenus.com/fl/tarpon-springs/33681-plaka-restaurant/menu/",
    "sg:phone":"+1 727 934 4752",
    "sg:postcode":"34689",
    "sg:province":"FL",
    "sg:tags":[
        "greek"
    ],
    "wof:name":"Plaka Restaurant",
    "wof:placetype":"venue"
},
  "geometry": {"coordinates":[-82.76154699999999,28.155565],"type":"Point"}
}