{
  "type": "Feature",
  "properties": {
    "iso:country":"US",
    "sg:address":"23601 Hardwood Ct",
    "sg:city":"Lutz",
    "sg:classifiers":[
        {
            "category":"Wholesale",
            "subcategory":"Hardware",
            "type":"Manufacturing & Wholesale Goods"
        }
    ],
    "sg:phone":"+1 813 948 1609",
    "sg:postcode":"33559",
    "sg:province":"FL",
    "wof:name":"Suncoast Business Svc",
    "wof:placetype":"venue"
},
  "geometry": {"coordinates":[-82.425724,28.182035],"type":"Point"}
}