{
  "type": "Feature",
  "properties": {
    "addr:full":"1323 James Ave Lehigh Acres FL 33972",
    "addr:housenumber":"1323",
    "addr:postcode":"33972",
    "addr:street":"James Ave",
    "iso:country":"US",
    "sg:address":"1323 James Ave",
    "sg:city":"Lehigh Acres",
    "sg:classifiers":[
        {
            "category":"Building & Trades",
            "subcategory":"Electrical",
            "type":"Services"
        }
    ],
    "sg:phone":"+1 239 369 7877",
    "sg:postcode":"33972",
    "sg:province":"FL",
    "sg:tags":[
        "electric",
        "contractor"
    ],
    "wof:name":"Pioneer Electric Co",
    "wof:placetype":"venue"
},
  "geometry": {"coordinates":[-81.601309,26.650559],"type":"Point"}
}