{
  "type": "Feature",
  "properties": {
    "iso:country":"US",
    "sg:address":"2201 N 55th Ave",
    "sg:city":"Hollywood",
    "sg:classifiers":[
        {
            "category":"Social Services",
            "subcategory":"Adult Care",
            "type":"Services"
        }
    ],
    "sg:phone":"+1 954 981 5862",
    "sg:postcode":"33021",
    "sg:province":"FL",
    "sg:tags":[
        "residential"
    ],
    "wof:name":"Heart To Heart Assisted Living",
    "wof:placetype":"venue"
},
  "geometry": {"coordinates":[-80.199105,26.029596],"type":"Point"}
}