{
  "type": "Feature",
  "properties": {
    "addr:full":"2889 SW 69th Ct Miami FL 33155",
    "addr:housenumber":"2889",
    "addr:postcode":"33155",
    "addr:street":"Sw 69Th Ct",
    "iso:country":"US",
    "sg:address":"2889 SW 69th Ct",
    "sg:city":"Miami",
    "sg:classifiers":[
        {
            "category":"Building & Trades",
            "subcategory":"Construction",
            "type":"Services"
        }
    ],
    "sg:phone":"+1 305 669 5529",
    "sg:postcode":"33155",
    "sg:province":"FL",
    "sg:tags":[
        "contractor"
    ],
    "sg:website":"www.fortuneconstructiongroup.net",
    "wof:name":"Fortune Roofing Inc",
    "wof:placetype":"venue"
},
  "geometry": {"coordinates":[-80.308244,25.743304],"type":"Point"}
}