{
  "type": "Feature",
  "properties": {
    "iso:country":"US",
    "sg:address":"1033 7th Ave N",
    "sg:city":"St Petersburg",
    "sg:classifiers":[
        {
            "category":"Health Services",
            "subcategory":"Doctor",
            "type":"Services"
        }
    ],
    "sg:phone":"+1 727 384 1000",
    "sg:postcode":"33705",
    "sg:province":"FL",
    "sg:tags":[
        "physician",
        "medical",
        "surgeon"
    ],
    "wof:name":"Howard Diamond MD",
    "wof:placetype":"venue"
},
  "geometry": {"coordinates":[-82.64973999999999,27.779419],"type":"Point"}
}