{
  "type": "Feature",
  "properties": {
    "iso:country":"US",
    "sg:address":"265 N Ivey Ln",
    "sg:city":"Orlando",
    "sg:classifiers":[
        {
            "category":"Building & Trades",
            "subcategory":"Construction",
            "type":"Services"
        }
    ],
    "sg:phone":"+1 407 292 0852",
    "sg:postcode":"32811",
    "sg:province":"FL",
    "sg:tags":[
        "steel",
        "fabrication",
        "structural"
    ],
    "wof:name":"International Engineering Svc",
    "wof:placetype":"venue"
},
  "geometry": {"coordinates":[-81.43459199999999,28.544578],"type":"Point"}
}