{
  "type": "Feature",
  "properties": {
    "iso:country":"US",
    "sg:address":"405 15th St",
    "sg:city":"Miami Beach",
    "sg:classifiers":[
        {
            "category":"Personal",
            "subcategory":"Tattoo Parlor",
            "type":"Services"
        }
    ],
    "sg:phone":"+1 305 673 0847",
    "sg:postcode":"33139",
    "sg:province":"FL",
    "sg:tags":[
        "tattooing"
    ],
    "wof:name":"Lucky Tattoo",
    "wof:placetype":"venue"
},
  "geometry": {"coordinates":[-80.132981,25.787623],"type":"Point"}
}