{
  "type": "Feature",
  "properties": {
    "addr:full":"4175 E Bay Dr Ste 242 Clearwater FL 33764",
    "addr:housenumber":"4175",
    "addr:postcode":"33764",
    "addr:street":"E Bay Dr Ste 242",
    "iso:country":"US",
    "sg:address":"4175 E Bay Dr Ste 242",
    "sg:city":"Clearwater",
    "sg:classifiers":[
        {
            "category":"Restaurant",
            "type":"Food & Drink"
        },
        {
            "category":"Ice Cream",
            "type":"Food & Drink"
        }
    ],
    "sg:phone":"+1 727 507 0665",
    "sg:postcode":"33764",
    "sg:province":"FL",
    "sg:tags":[
        "frozen",
        "dessert",
        "mix"
    ],
    "sg:website":"http://www.dippindots.com",
    "wof:name":"Dippin' Dots",
    "wof:placetype":"venue"
},
  "geometry": {"coordinates":[-82.743314,27.916349],"type":"Point"}
}