{
  "type": "Feature",
  "properties": {
    "iso:country":"US",
    "sg:address":"3115 48th Avenue Dr E",
    "sg:city":"Bradenton",
    "sg:classifiers":[
        {
            "category":"Manufacturing",
            "subcategory":"Printing",
            "type":"Manufacturing & Wholesale Goods"
        }
    ],
    "sg:phone":"+1 941 751 2360",
    "sg:postcode":"34203",
    "sg:province":"FL",
    "sg:tags":[
        "publishers-periodical",
        "periodical"
    ],
    "wof:name":"Magazine In Advance Diver",
    "wof:placetype":"venue"
},
  "geometry": {"coordinates":[-82.52345099999999,27.453618],"type":"Point"}
}