{
  "type": "Feature",
  "properties": {
    "addr:full":"21157 Clubside Dr Boca Raton FL 33434",
    "addr:postcode":"21157;33434",
    "addr:street":"Clubside Dr",
    "iso:country":"US",
    "sg:address":"21157 Clubside Dr",
    "sg:city":"Boca Raton",
    "sg:classifiers":[
        {
            "category":"Professional",
            "subcategory":"Management & Consulting",
            "type":"Services"
        }
    ],
    "sg:phone":"+1 561 488 1050",
    "sg:postcode":"33434",
    "sg:province":"FL",
    "sg:tags":[
        "fuel"
    ],
    "wof:name":"Lang Management Co",
    "wof:placetype":"venue"
},
  "geometry": {"coordinates":[-80.153482,26.378596],"type":"Point"}
}