{
  "type": "Feature",
  "properties": {
    "addr:full":"842 SW 9th St Fort Lauderdale FL 33315",
    "addr:housenumber":"842",
    "addr:postcode":"33315",
    "addr:street":"Sw 9Th St",
    "iso:country":"US",
    "sg:address":"842 SW 9th St",
    "sg:city":"Fort Lauderdale",
    "sg:classifiers":[
        {
            "category":"Restaurant",
            "type":"Food & Drink"
        }
    ],
    "sg:phone":"+1 954 764 2725",
    "sg:postcode":"33315",
    "sg:province":"FL",
    "sg:tags":[
        "eating"
    ],
    "wof:name":"Culinary Fusion",
    "wof:placetype":"venue"
},
  "geometry": {"coordinates":[-80.15323100000001,26.110941],"type":"Point"}
}