{
  "type": "Feature",
  "properties": {
    "addr:full":"4553 el Mar Dr Fort Lauderdale FL 33308",
    "addr:housenumber":"4553",
    "addr:postcode":"33308",
    "addr:street":"El Mar Dr",
    "iso:country":"US",
    "sg:address":"4553 el Mar Dr",
    "sg:city":"Fort Lauderdale",
    "sg:classifiers":[
        {
            "category":"Real Estate",
            "subcategory":"Real Estate Operator",
            "type":"Services"
        }
    ],
    "sg:phone":"+1 954 772 0514",
    "sg:postcode":"33308",
    "sg:province":"FL",
    "sg:tags":[
        "building",
        "apartment"
    ],
    "wof:name":"Rainbow By Sea Resort",
    "wof:placetype":"venue"
},
  "geometry": {"coordinates":[-80.095522,26.193486],"type":"Point"}
}