{
  "type": "Feature",
  "properties": {
    "iso:country":"US",
    "sg:address":"708 Del Prado Blvd S",
    "sg:city":"Cape Coral",
    "sg:classifiers":[
        {
            "category":"Health Services",
            "subcategory":"Doctor",
            "type":"Services"
        }
    ],
    "sg:phone":"+1 239 574 2644",
    "sg:postcode":"33990",
    "sg:province":"FL",
    "wof:name":"Keys Timothy C MD Fccp",
    "wof:placetype":"venue"
},
  "geometry": {"coordinates":[-81.941002,26.638399],"type":"Point"}
}