{
  "type": "Feature",
  "properties": {
    "iso:country":"US",
    "sg:address":"7825 Ellis Rd",
    "sg:city":"Melbourne",
    "sg:classifiers":[
        {
            "category":"Shopping",
            "subcategory":"Stationery & Office Supplies",
            "type":"Retail Goods"
        }
    ],
    "sg:phone":"+1 321 733 1020",
    "sg:postcode":"32904",
    "sg:province":"FL",
    "wof:name":"Martek",
    "wof:placetype":"venue"
},
  "geometry": {"coordinates":[-80.683655,28.099208],"type":"Point"}
}