{
  "type": "Feature",
  "properties": {
    "addr:full":"1215 W Jefferson St Orlando FL 32805",
    "addr:housenumber":"1215",
    "addr:postcode":"32805",
    "addr:street":"W Jefferson St",
    "iso:country":"US",
    "sg:address":"1215 W Jefferson St",
    "sg:city":"Orlando",
    "sg:classifiers":[
        {
            "category":"Wholesale",
            "subcategory":"Auto Parts",
            "type":"Manufacturing & Wholesale Goods"
        }
    ],
    "sg:phone":"+1 407 843 5980",
    "sg:postcode":"32805",
    "sg:province":"FL",
    "wof:name":"C&M Core Distributors",
    "wof:placetype":"venue"
},
  "geometry": {"coordinates":[-81.39705600000001,28.544987],"type":"Point"}
}