{
  "type": "Feature",
  "properties": {
    "addr:full":"8601 N Dale Mabry Hwy Tampa FL 33614",
    "addr:housenumber":"8601",
    "addr:postcode":"33614",
    "addr:street":"N Dale Mabry Hwy",
    "iso:country":"US",
    "sg:address":"8601 N Dale Mabry Hwy",
    "sg:city":"Tampa",
    "sg:classifiers":[
        {
            "category":"Retail",
            "subcategory":"Auto Rental",
            "type":"Services"
        }
    ],
    "sg:phone":"+1 813 915 0613",
    "sg:postcode":"33614",
    "sg:province":"FL",
    "sg:tags":[
        "truck"
    ],
    "wof:name":"7 Moving Centers",
    "wof:placetype":"venue"
},
  "geometry": {"coordinates":[-82.504931,28.030064],"type":"Point"}
}