{
  "type": "Feature",
  "properties": {
    "iso:country":"US",
    "sg:address":"1911 US Hwy 301",
    "sg:city":"Tampa",
    "sg:classifiers":[
        {
            "category":"Freight",
            "type":"Transportation"
        }
    ],
    "sg:phone":"+1 813 664 0684",
    "sg:postcode":"33619",
    "sg:province":"FL",
    "sg:tags":[
        "delivery",
        "equipment",
        "medical"
    ],
    "wof:name":"Medical Equipment Dept",
    "wof:placetype":"venue"
},
  "geometry": {"coordinates":[-82.358875,27.960151],"type":"Point"}
}