{
  "type": "Feature",
  "properties": {
    "addr:full":"5139 Gall Blvd Zephyrhills FL 33542",
    "addr:housenumber":"5139",
    "addr:postcode":"33542",
    "addr:street":"Gall Blvd",
    "iso:country":"US",
    "sg:address":"5139 Gall Blvd",
    "sg:city":"Zephyrhills",
    "sg:classifiers":[
        {
            "category":"Food & Beverages",
            "subcategory":"Meat & Fish",
            "type":"Retail Goods"
        }
    ],
    "sg:phone":"+1 813 783 2771",
    "sg:postcode":"33542",
    "sg:province":"FL",
    "wof:name":"Papa's Market",
    "wof:placetype":"venue"
},
  "geometry": {"coordinates":[-82.180635,28.231688],"type":"Point"}
}