{
  "type": "Feature",
  "properties": {
    "iso:country":"US",
    "sg:address":"2101 Ox Bottom Rd",
    "sg:city":"Tallahassee",
    "sg:classifiers":[
        {
            "category":"Building & Trades",
            "subcategory":"Cleaning & Sanitation",
            "type":"Services"
        }
    ],
    "sg:phone":"+1 850 668 5678",
    "sg:postcode":"32312",
    "sg:province":"FL",
    "sg:tags":[
        "maid"
    ],
    "wof:name":"Maid For You",
    "wof:placetype":"venue"
},
  "geometry": {"coordinates":[-84.242659,30.537834],"type":"Point"}
}