{
  "type": "Feature",
  "properties": {
    "iso:country":"US",
    "sg:address":"2900 E Cervantes St",
    "sg:city":"Pensacola",
    "sg:classifiers":[
        {
            "category":"Restaurant",
            "type":"Food & Drink"
        }
    ],
    "sg:phone":"+1 850 439 3005",
    "sg:postcode":"32503",
    "sg:province":"FL",
    "sg:tags":[
        "asian",
        "chinese",
        "pan"
    ],
    "wof:name":"Taste Of India",
    "wof:placetype":"venue"
},
  "geometry": {"coordinates":[-87.183578,30.425341],"type":"Point"}
}