{
  "type": "Feature",
  "properties": {
    "addr:full":"502 SW South Carolina Dr Stuart FL 34994",
    "addr:housenumber":"502",
    "addr:postcode":"34994",
    "addr:street":"Sw South Carolina Dr",
    "iso:country":"US",
    "sg:address":"502 SW South Carolina Dr",
    "sg:city":"Stuart",
    "sg:classifiers":[
        {
            "category":"Building & Trades",
            "subcategory":"Construction",
            "type":"Services"
        }
    ],
    "sg:phone":"+1 772 287 2752",
    "sg:postcode":"34994",
    "sg:province":"FL",
    "sg:tags":[
        "home",
        "improvement"
    ],
    "wof:name":"Four Corners Construction",
    "wof:placetype":"venue"
},
  "geometry": {"coordinates":[-80.259382,27.18182],"type":"Point"}
}