{
  "type": "Feature",
  "properties": {
    "addr:full":"16490 NW 14th St Hollywood FL 33028",
    "addr:housenumber":"16490",
    "addr:postcode":"33028",
    "addr:street":"Nw 14Th St",
    "iso:country":"US",
    "sg:address":"16490 NW 14th St",
    "sg:city":"Hollywood",
    "sg:classifiers":[
        {
            "category":"Freight",
            "type":"Transportation"
        }
    ],
    "sg:phone":"+1 954 443 9607",
    "sg:postcode":"33028",
    "sg:province":"FL",
    "sg:tags":[
        "international",
        "forwarding"
    ],
    "wof:name":"Ambrit USA Inc",
    "wof:placetype":"venue"
},
  "geometry": {"coordinates":[-80.361006,26.020016],"type":"Point"}
}