{
  "type": "Feature",
  "properties": {
    "addr:full":"1049 N Alhambra Cir Naples FL 34103",
    "addr:housenumber":"1049",
    "addr:postcode":"34103",
    "addr:street":"N Alhambra Cir",
    "iso:country":"US",
    "sg:address":"1049 N Alhambra Cir",
    "sg:city":"Naples",
    "sg:classifiers":[
        {
            "category":"Building & Trades",
            "subcategory":"Construction",
            "type":"Services"
        }
    ],
    "sg:phone":"+1 239 430 0331",
    "sg:postcode":"34103",
    "sg:province":"FL",
    "sg:tags":[
        "carpentry",
        "contractor"
    ],
    "wof:name":"Chad Haverkate Carpentry LLC",
    "wof:placetype":"venue"
},
  "geometry": {"coordinates":[-81.79763199999999,26.205431],"type":"Point"}
}