{
  "type": "Feature",
  "properties": {
    "addr:full":"7670 Starkey Rd Seminole FL 33777",
    "addr:housenumber":"7670",
    "addr:postcode":"33777",
    "addr:street":"Starkey Rd",
    "iso:country":"US",
    "sg:address":"7670 Starkey Rd",
    "sg:city":"Seminole",
    "sg:classifiers":[
        {
            "category":"Restaurant",
            "type":"Food & Drink"
        }
    ],
    "sg:menulink":"http://www.allmenus.com/fl/st-petersburg/158633-arbys/menu/",
    "sg:phone":"+1 727 397 1758",
    "sg:postcode":"33777",
    "sg:province":"FL",
    "sg:tags":[
        "burger",
        "american"
    ],
    "wof:name":"Arby's",
    "wof:placetype":"venue"
},
  "geometry": {"coordinates":[-82.76280199999999,27.841813],"type":"Point"}
}