{
  "type": "Feature",
  "properties": {
    "addr:full":"1015 Sunshine Ln Altamonte Spgs FL 32714",
    "addr:housenumber":"1015",
    "addr:postcode":"32714",
    "addr:street":"Sunshine Ln;Spgs",
    "iso:country":"US",
    "sg:address":"1015 Sunshine Ln",
    "sg:city":"Altamonte Spgs",
    "sg:classifiers":[
        {
            "category":"Wholesale",
            "subcategory":"Electrical",
            "type":"Manufacturing & Wholesale Goods"
        }
    ],
    "sg:phone":"+1 407 869 4700",
    "sg:postcode":"32714",
    "sg:province":"FL",
    "sg:tags":[
        "wire",
        "cable"
    ],
    "sg:website":"www.roycewire.com",
    "wof:name":"Royce Electronics Sales Inc",
    "wof:placetype":"venue"
},
  "geometry": {"coordinates":[-81.42242299999999,28.655574],"type":"Point"}
}