{
  "type": "Feature",
  "properties": {
    "iso:country":"US",
    "sg:address":"602 93rd Ave N",
    "sg:city":"Naples",
    "sg:classifiers":[
        {
            "category":"Building & Trades",
            "subcategory":"Construction",
            "type":"Services"
        }
    ],
    "sg:phone":"+1 239 287 6871",
    "sg:postcode":"34108",
    "sg:province":"FL",
    "sg:tags":[
        "handyman"
    ],
    "wof:name":"Steven Baughman Sills Handyman",
    "wof:placetype":"venue"
},
  "geometry": {"coordinates":[-81.80918200000001,26.25607],"type":"Point"}
}