{
  "type": "Feature",
  "properties": {
    "addr:full":"11920 SW 5th St Miami FL 33184",
    "addr:housenumber":"11920",
    "addr:postcode":"33184",
    "addr:street":"Sw 5Th St",
    "iso:country":"US",
    "sg:address":"11920 SW 5th St",
    "sg:city":"Miami",
    "sg:classifiers":[
        {
            "category":"Retail",
            "subcategory":"Repair Shop",
            "type":"Services"
        }
    ],
    "sg:phone":"+1 305 225 0033",
    "sg:postcode":"33184",
    "sg:province":"FL",
    "sg:tags":[
        "related"
    ],
    "wof:name":"Quick AC & Svc Repair Crp",
    "wof:placetype":"venue"
},
  "geometry": {"coordinates":[-80.388757,25.76326],"type":"Point"}
}