{
  "type": "Feature",
  "properties": {
    "iso:country":"US",
    "sg:address":"601 E 49th St",
    "sg:city":"Hialeah",
    "sg:classifiers":[
        {
            "category":"Health Services",
            "subcategory":"Doctor",
            "type":"Services"
        }
    ],
    "sg:phone":"+1 305 688 9732",
    "sg:postcode":"33013",
    "sg:province":"FL",
    "sg:tags":[
        "clinic",
        "medical"
    ],
    "wof:name":"Health Care Medical Group Inc",
    "wof:placetype":"venue"
},
  "geometry": {"coordinates":[-80.26875099999999,25.867279],"type":"Point"}
}