{
  "type": "Feature",
  "properties": {
    "addr:full":"6660 Beach Resort Dr Naples FL 34114",
    "addr:housenumber":"6660",
    "addr:postcode":"34114",
    "addr:street":"Beach Resort Dr",
    "iso:country":"US",
    "sg:address":"6660 Beach Resort Dr",
    "sg:city":"Naples",
    "sg:classifiers":[
        {
            "category":"Real Estate",
            "subcategory":"Real Estate Operator",
            "type":"Services"
        }
    ],
    "sg:phone":"+1 239 598 1035",
    "sg:postcode":"34114",
    "sg:province":"FL",
    "sg:tags":[
        "building",
        "nonresidential"
    ],
    "wof:name":"Aztec Properties Inc",
    "wof:placetype":"venue"
},
  "geometry": {"coordinates":[-81.696893,26.064916],"type":"Point"}
}