{
  "type": "Feature",
  "properties": {
    "addr:full":"46 Bodiford Ln Crawfordville FL 32327",
    "addr:housenumber":"46",
    "addr:postcode":"32327",
    "addr:street":"Bodiford Ln",
    "iso:country":"US",
    "sg:address":"46 Bodiford Ln",
    "sg:city":"Crawfordville",
    "sg:classifiers":[
        {
            "category":"Building & Trades",
            "subcategory":"Construction",
            "type":"Services"
        }
    ],
    "sg:phone":"+1 850 926 1801",
    "sg:postcode":"32327",
    "sg:province":"FL",
    "sg:tags":[
        "contractor"
    ],
    "wof:name":"Deacons Drywall Inc",
    "wof:placetype":"venue"
},
  "geometry": {"coordinates":[-84.351163,30.158859],"type":"Point"}
}