{
  "type": "Feature",
  "properties": {
    "iso:country":"US",
    "sg:address":"4000 SW 130th Ave",
    "sg:city":"Hollywood",
    "sg:classifiers":[
        {
            "category":"Real Estate",
            "subcategory":"Real Estate Agent",
            "type":"Services"
        },
        {
            "category":"Professional",
            "subcategory":"Management & Consulting",
            "type":"Services"
        }
    ],
    "sg:phone":"+1 954 435 5472",
    "sg:postcode":"33027",
    "sg:province":"FL",
    "sg:tags":[
        "food"
    ],
    "wof:name":"Aacon Contracting Co Inc",
    "wof:placetype":"venue"
},
  "geometry": {"coordinates":[-80.32144,25.978188],"type":"Point"}
}