{
  "type": "Feature",
  "properties": {
    "iso:country":"US",
    "sg:address":"545 W Flagler St",
    "sg:city":"Miami",
    "sg:classifiers":[
        {
            "category":"Home & Garden",
            "subcategory":"Building Materials",
            "type":"Retail Goods"
        },
        {
            "category":"Wholesale",
            "subcategory":"Painting Supplies",
            "type":"Manufacturing & Wholesale Goods"
        }
    ],
    "sg:phone":"+1 305 545 8700",
    "sg:postcode":"33130",
    "sg:province":"FL",
    "sg:tags":[
        "paint"
    ],
    "wof:name":"Stein Paint Company",
    "wof:placetype":"venue"
},
  "geometry": {"coordinates":[-80.20396,25.773964],"type":"Point"}
}