{
  "type": "Feature",
  "properties": {
    "iso:country":"US",
    "sg:address":"628 Delhi St",
    "sg:city":"Orlando",
    "sg:classifiers":[
        {
            "category":"Retail",
            "subcategory":"Auto Repair",
            "type":"Services"
        }
    ],
    "sg:phone":"+1 407 291 7937",
    "sg:postcode":"32808",
    "sg:province":"FL",
    "sg:tags":[
        "body",
        "general"
    ],
    "wof:name":"Top Choice Auto Repair Ctr",
    "wof:placetype":"venue"
},
  "geometry": {"coordinates":[-81.441812,28.552429],"type":"Point"}
}