{
  "type": "Feature",
  "properties": {
    "addr:full":"6170 Serene Run Lake Worth FL 33467",
    "addr:housenumber":"6170",
    "addr:postcode":"33467",
    "addr:street":"Serene Run",
    "iso:country":"US",
    "sg:address":"6170 Serene Run",
    "sg:city":"Lake Worth",
    "sg:classifiers":[
        {
            "category":"Building & Trades",
            "subcategory":"Landscaping Services",
            "type":"Services"
        }
    ],
    "sg:phone":"+1 561 966 7861",
    "sg:postcode":"33467",
    "sg:province":"FL",
    "wof:name":"A Plus Lawn Service",
    "wof:placetype":"venue"
},
  "geometry": {"coordinates":[-80.159876,26.588103],"type":"Point"}
}