{
  "type": "Feature",
  "properties": {
    "iso:country":"US",
    "sg:address":"1028 NW 13th St",
    "sg:city":"Gainesville",
    "sg:classifiers":[
        {
            "category":"Health Services",
            "subcategory":"Chiropractor",
            "type":"Services"
        }
    ],
    "sg:phone":"+1 352 373 9911",
    "sg:postcode":"32601",
    "sg:province":"FL",
    "wof:name":"Bensen Peter MA DC",
    "wof:placetype":"venue"
},
  "geometry": {"coordinates":[-82.339243,29.66176],"type":"Point"}
}