{
  "type": "Feature",
  "properties": {
    "iso:country":"US",
    "sg:address":"8741 NW 189th Ter",
    "sg:city":"Hialeah",
    "sg:classifiers":[
        {
            "category":"Personal",
            "type":"Services"
        }
    ],
    "sg:phone":"+1 305 829 8502",
    "sg:postcode":"33018",
    "sg:province":"FL",
    "wof:name":"Youre Officially Married",
    "wof:placetype":"venue"
},
  "geometry": {"coordinates":[-80.343346,25.944955],"type":"Point"}
}