{
  "type": "Feature",
  "properties": {
    "iso:country":"US",
    "sg:address":"450 Oakwood Ct",
    "sg:city":"Merritt Island",
    "sg:classifiers":[
        {
            "category":"Building & Trades",
            "subcategory":"Construction",
            "type":"Services"
        }
    ],
    "sg:phone":"+1 321 459 5002",
    "sg:postcode":"32953",
    "sg:province":"FL",
    "sg:tags":[
        "house"
    ],
    "wof:name":"Inovations",
    "wof:placetype":"venue"
},
  "geometry": {"coordinates":[-80.711163,28.371975],"type":"Point"}
}