{
  "type": "Feature",
  "properties": {
    "addr:full":"3216 Raven Rd Orlando FL 32803",
    "addr:housenumber":"3216",
    "addr:postcode":"32803",
    "addr:street":"Raven Rd",
    "iso:country":"US",
    "sg:address":"3216 Raven Rd",
    "sg:city":"Orlando",
    "sg:classifiers":[
        {
            "category":"Building & Trades",
            "subcategory":"Construction",
            "type":"Services"
        }
    ],
    "sg:phone":"+1 407 896 6725",
    "sg:postcode":"32803",
    "sg:province":"FL",
    "sg:tags":[
        "general",
        "contractor"
    ],
    "wof:name":"KSW Contracting Inc",
    "wof:placetype":"venue"
},
  "geometry": {"coordinates":[-81.343023,28.566876],"type":"Point"}
}