{
  "type": "Feature",
  "properties": {
    "addr:full":"6624 Wilson Rd West Palm Beach FL 33413",
    "addr:housenumber":"6624",
    "addr:postcode":"33413",
    "addr:street":"Wilson Rd",
    "iso:country":"US",
    "sg:address":"6624 Wilson Rd",
    "sg:city":"West Palm Beach",
    "sg:classifiers":[
        {
            "category":"Building & Trades",
            "subcategory":"Landscaping Services",
            "type":"Services"
        }
    ],
    "sg:phone":"+1 561 790 2832",
    "sg:postcode":"33413",
    "sg:province":"FL",
    "sg:tags":[
        "landscape"
    ],
    "wof:name":"Vellones Cmplete Landsape Nurs",
    "wof:placetype":"venue"
},
  "geometry": {"coordinates":[-80.151507,26.677152],"type":"Point"}
}