{
  "type": "Feature",
  "properties": {
    "iso:country":"US",
    "sg:address":"504 N Dixie Fwy",
    "sg:city":"New Smyrna Beach",
    "sg:classifiers":[
        {
            "category":"Insurance",
            "subcategory":"Insurance Agent",
            "type":"Services"
        }
    ],
    "sg:phone":"+1 386 423 9209",
    "sg:postcode":"32168",
    "sg:province":"FL",
    "wof:name":"Fair Insurance Svc",
    "wof:placetype":"venue"
},
  "geometry": {"coordinates":[-80.928378,29.02872],"type":"Point"}
}