{
  "type": "Feature",
  "properties": {
    "addr:full":"446 Lake Daisy Dr Winter Haven FL 33884",
    "addr:housenumber":"446",
    "addr:postcode":"33884",
    "addr:street":"Lake Daisy Dr",
    "iso:country":"US",
    "sg:address":"446 Lake Daisy Dr",
    "sg:city":"Winter Haven",
    "sg:classifiers":[
        {
            "category":"Health Services",
            "subcategory":"Hospital",
            "type":"Services"
        }
    ],
    "sg:phone":"+1 863 297 1844",
    "sg:postcode":"33884",
    "sg:province":"FL",
    "sg:tags":[
        "general"
    ],
    "wof:name":"Winter Haven Hospital",
    "wof:placetype":"venue"
},
  "geometry": {"coordinates":[-81.65746300000001,27.991723],"type":"Point"}
}