{
  "type": "Feature",
  "properties": {
    "addr:full":"891 E Palmetto Park Rd Boca Raton FL 33432",
    "addr:housenumber":"891",
    "addr:postcode":"33432",
    "addr:street":"E Palmetto Park Rd",
    "iso:country":"US",
    "sg:address":"891 E Palmetto Park Rd",
    "sg:city":"Boca Raton",
    "sg:classifiers":[
        {
            "category":"Personal",
            "subcategory":"Beauty Salon",
            "type":"Services"
        }
    ],
    "sg:phone":"+1 561 391 1220",
    "sg:postcode":"33432",
    "sg:province":"FL",
    "wof:name":"Kim Cunningham",
    "wof:placetype":"venue"
},
  "geometry": {"coordinates":[-80.072918,26.350711],"type":"Point"}
}