{
  "type": "Feature",
  "properties": {
    "addr:full":"714 S Dale Mabry Hwy Tampa FL 33609",
    "addr:housenumber":"714",
    "addr:postcode":"33609",
    "addr:street":"S Dale Mabry Hwy",
    "iso:country":"US",
    "sg:address":"714 S Dale Mabry Hwy",
    "sg:city":"Tampa",
    "sg:classifiers":[
        {
            "category":"Restaurant",
            "type":"Food & Drink"
        }
    ],
    "sg:phone":"+1 813 554 3354",
    "sg:postcode":"33609",
    "sg:province":"FL",
    "sg:tags":[
        "eating"
    ],
    "wof:name":"Schlotzskys Deli",
    "wof:placetype":"venue"
},
  "geometry": {"coordinates":[-82.505679,27.93746],"type":"Point"}
}