{
  "type": "Feature",
  "properties": {
    "addr:full":"1511 SW del Rio Blvd Port Saint Lucie FL 34953",
    "addr:housenumber":"1511",
    "addr:postcode":"34953",
    "addr:street":"Sw Del Rio Blvd",
    "iso:country":"US",
    "sg:address":"1511 SW del Rio Blvd",
    "sg:city":"Port Saint Lucie",
    "sg:classifiers":[
        {
            "category":"Organizations",
            "subcategory":"Religious Organization",
            "type":"Services"
        }
    ],
    "sg:phone":"+1 772 343 0401",
    "sg:postcode":"34953",
    "sg:province":"FL",
    "wof:name":"Episcopal Church of Nativity",
    "wof:placetype":"venue"
},
  "geometry": {"coordinates":[-80.391791,27.288545],"type":"Point"}
}