{
  "type": "Feature",
  "properties": {
    "addr:full":"2475 W Midway Rd Fort Pierce FL 34981",
    "addr:housenumber":"2475",
    "addr:postcode":"34981",
    "addr:street":"W Midway Rd",
    "iso:country":"US",
    "sg:address":"2475 W Midway Rd",
    "sg:city":"Fort Pierce",
    "sg:classifiers":[
        {
            "category":"Autos & Motor Vehicles",
            "subcategory":"Fuel & Gas Station",
            "type":"Retail Goods"
        }
    ],
    "sg:phone":"+1 772 489 4171",
    "sg:postcode":"34981",
    "sg:province":"FL",
    "sg:tags":[
        "oil"
    ],
    "wof:name":"Shell",
    "wof:placetype":"venue"
},
  "geometry": {"coordinates":[-80.34988199999999,27.374082],"type":"Point"}
}