{
  "type": "Feature",
  "properties": {
    "addr:full":"1851 Collier Pkwy Lutz FL 33549",
    "addr:housenumber":"1851",
    "addr:postcode":"33549",
    "addr:street":"Collier Pkwy",
    "iso:country":"US",
    "sg:address":"1851 Collier Pkwy",
    "sg:city":"Lutz",
    "sg:classifiers":[
        {
            "category":"Professional",
            "subcategory":"Management & Consulting",
            "type":"Services"
        },
        {
            "category":"Banks & Credit Unions",
            "subcategory":"Investment Brokerage",
            "type":"Services"
        },
        {
            "category":"Banks & Credit Unions",
            "subcategory":"Financial Services",
            "type":"Services"
        }
    ],
    "sg:phone":"+1 813 909 9550",
    "sg:postcode":"33549",
    "sg:province":"FL",
    "sg:tags":[
        "planning",
        "advisory",
        "financing",
        "planner",
        "consultant"
    ],
    "wof:name":"Amera Price Financial",
    "wof:placetype":"venue"
},
  "geometry": {"coordinates":[-82.43846499999999,28.18251],"type":"Point"}
}