{
  "type": "Feature",
  "properties": {
    "addr:full":"3650 W Sovereign Path 1 Lecanto FL 34461",
    "addr:housenumber":"3650;1",
    "addr:postcode":"34461",
    "addr:street":"W Sovereign Path",
    "iso:country":"US",
    "sg:address":"3650 W Sovereign Path 1",
    "sg:city":"Lecanto",
    "sg:classifiers":[
        {
            "category":"Sports & Exercise",
            "subcategory":"Race Track",
            "type":"Entertainment"
        }
    ],
    "sg:phone":"+1 352 726 9339",
    "sg:postcode":"34461",
    "sg:province":"FL",
    "wof:name":"Citrus County Speedway",
    "wof:placetype":"venue"
},
  "geometry": {"coordinates":[-82.49415999999999,28.823005],"type":"Point"}
}