{
  "type": "Feature",
  "properties": {
    "iso:country":"US",
    "sg:address":"451 NE 8th St",
    "sg:city":"Homestead",
    "sg:classifiers":[
        {
            "category":"Shopping",
            "subcategory":"Discount & Variety Stores",
            "type":"Retail Goods"
        }
    ],
    "sg:phone":"+1 305 248 1312",
    "sg:postcode":"33030",
    "sg:province":"FL",
    "sg:tags":[
        "cards",
        "funds",
        "transferring",
        "for",
        "manufacturing"
    ],
    "wof:name":"Netcard of Miami",
    "wof:placetype":"venue"
},
  "geometry": {"coordinates":[-80.47018,25.477279],"type":"Point"}
}