{
  "type": "Feature",
  "properties": {
    "iso:country":"US",
    "sg:address":"1283 NW 163rd Ter",
    "sg:city":"Hollywood",
    "sg:classifiers":[
        {
            "category":"Shopping",
            "subcategory":"Music",
            "type":"Retail Goods"
        }
    ],
    "sg:phone":"+1 954 438 5094",
    "sg:postcode":"33028",
    "sg:province":"FL",
    "wof:name":"24/7 Records LLC",
    "wof:placetype":"venue"
},
  "geometry": {"coordinates":[-80.362503,26.018028],"type":"Point"}
}