{
  "type": "Feature",
  "properties": {
    "iso:country":"US",
    "sg:address":"1470 Jamaica Rd",
    "sg:city":"Marco Island",
    "sg:classifiers":[
        {
            "category":"Communications",
            "subcategory":"Film & Video Production",
            "type":"Services"
        }
    ],
    "sg:phone":"+1 239 393 0839",
    "sg:postcode":"34145",
    "sg:province":"FL",
    "sg:tags":[
        "taping"
    ],
    "wof:name":"Black Knight Production",
    "wof:placetype":"venue"
},
  "geometry": {"coordinates":[-81.710323,25.942106],"type":"Point"}
}