{
  "type": "Feature",
  "properties": {
    "addr:full":"6015 Benjamin Rd Tampa FL 33634",
    "addr:housenumber":"6015",
    "addr:postcode":"33634",
    "addr:street":"Benjamin Rd",
    "iso:country":"US",
    "sg:address":"6015 Benjamin Rd",
    "sg:city":"Tampa",
    "sg:classifiers":[
        {
            "category":"Professional",
            "subcategory":"Business Services",
            "type":"Services"
        }
    ],
    "sg:phone":"+1 813 806 0500",
    "sg:postcode":"33634",
    "sg:province":"FL",
    "sg:tags":[
        "paging",
        "answering"
    ],
    "wof:name":"TCG",
    "wof:placetype":"venue"
},
  "geometry": {"coordinates":[-82.54195300000001,28.002724],"type":"Point"}
}