{
  "type": "Feature",
  "properties": {
    "addr:full":"102 S Shore Rd Stuart FL 34994",
    "addr:housenumber":"102",
    "addr:postcode":"34994",
    "addr:street":"S Shore Rd",
    "iso:country":"US",
    "sg:address":"102 S Shore Rd",
    "sg:city":"Stuart",
    "sg:classifiers":[
        {
            "category":"Building & Trades",
            "subcategory":"Construction",
            "type":"Services"
        }
    ],
    "sg:phone":"+1 772 335 9027",
    "sg:postcode":"34994",
    "sg:province":"FL",
    "sg:tags":[
        "house"
    ],
    "wof:name":"Resort Const",
    "wof:placetype":"venue"
},
  "geometry": {"coordinates":[-80.289603,27.238513],"type":"Point"}
}