{
  "type": "Feature",
  "properties": {
    "iso:country":"US",
    "sg:address":"2604 Powers Ave",
    "sg:city":"Jacksonville",
    "sg:classifiers":[
        {
            "category":"Professional",
            "type":"Services"
        }
    ],
    "sg:phone":"+1 904 737 4418",
    "sg:postcode":"32207",
    "sg:province":"FL",
    "sg:tags":[
        "establishment"
    ],
    "wof:name":"Customs & Classics",
    "wof:placetype":"venue"
},
  "geometry": {"coordinates":[-81.632161,30.268077],"type":"Point"}
}