{
  "type": "Feature",
  "properties": {
    "addr:full":"1705 US Hwy 27 Davenport FL 33837",
    "addr:housenumber":"1705",
    "addr:postcode":"33837",
    "addr:street":"Us Hwy 27",
    "iso:country":"US",
    "sg:address":"1705 US Hwy 27",
    "sg:city":"Davenport",
    "sg:classifiers":[
        {
            "category":"Health Services",
            "subcategory":"Doctor",
            "type":"Services"
        }
    ],
    "sg:phone":"+1 863 419 0104",
    "sg:postcode":"33837",
    "sg:province":"FL",
    "sg:tags":[
        "physician",
        "surgeon"
    ],
    "wof:name":"Pulmonary Disease Specialists",
    "wof:placetype":"venue"
},
  "geometry": {"coordinates":[-81.640024,28.181972],"type":"Point"}
}