{
  "type": "Feature",
  "properties": {
    "addr:full":"16248 Gulf Blvd Saint Petersburg FL 33708",
    "addr:housenumber":"16248",
    "addr:postcode":"33708",
    "addr:street":"Gulf Blvd",
    "iso:country":"US",
    "sg:address":"16248 Gulf Blvd",
    "sg:city":"Saint Petersburg",
    "sg:classifiers":[
        {
            "category":"Banks & Credit Unions",
            "subcategory":"Bank",
            "type":"Services"
        }
    ],
    "sg:phone":"+1 727 392 0364",
    "sg:postcode":"33708",
    "sg:province":"FL",
    "sg:tags":[
        "institution",
        "business"
    ],
    "wof:name":"J & W Ventures Inc",
    "wof:placetype":"venue"
},
  "geometry": {"coordinates":[-82.816395,27.811823],"type":"Point"}
}