{
  "type": "Feature",
  "properties": {
    "iso:country":"US",
    "sg:address":"12934 NW 7th Ave",
    "sg:city":"Miami",
    "sg:classifiers":[
        {
            "category":"Personal",
            "subcategory":"Beauty Salon",
            "type":"Services"
        }
    ],
    "sg:phone":"+1 305 685 7925",
    "sg:postcode":"33168",
    "sg:province":"FL",
    "sg:tags":[
        "shop"
    ],
    "wof:name":"First Impressions",
    "wof:placetype":"venue"
},
  "geometry": {"coordinates":[-80.21113,25.89341],"type":"Point"}
}