{
  "type": "Feature",
  "properties": {
    "addr:full":"1109 E Ridgewood St Orlando FL 32803",
    "addr:housenumber":"1109",
    "addr:postcode":"32803",
    "addr:street":"E Ridgewood St",
    "iso:country":"US",
    "sg:address":"1109 E Ridgewood St",
    "sg:city":"Orlando",
    "sg:classifiers":[
        {
            "category":"Health Services",
            "subcategory":"Doctor",
            "type":"Services"
        }
    ],
    "sg:phone":"+1 407 649 8677",
    "sg:postcode":"32803",
    "sg:province":"FL",
    "sg:tags":[
        "physician",
        "surgeon"
    ],
    "wof:name":"Central Florida Pulmonary Grp",
    "wof:placetype":"venue"
},
  "geometry": {"coordinates":[-81.36564199999999,28.546768],"type":"Point"}
}