{
  "type": "Feature",
  "properties": {
    "addr:full":"1450 Washington Ave Miami Beach FL 33109",
    "addr:housenumber":"1450",
    "addr:postcode":"33109",
    "addr:street":"Washington Ave",
    "iso:country":"US",
    "sg:address":"1450 Washington Ave",
    "sg:city":"Miami Beach",
    "sg:classifiers":[
        {
            "category":"Restaurant",
            "type":"Food & Drink"
        },
        {
            "category":"Bakery",
            "type":"Food & Drink"
        }
    ],
    "sg:phone":"+1 786 547 9590",
    "sg:postcode":"33109",
    "sg:province":"FL",
    "wof:name":"Mattarello Bakery Cafe",
    "wof:placetype":"venue"
},
  "geometry": {"coordinates":[-80.131832,25.787309],"type":"Point"}
}