{
  "type": "Feature",
  "properties": {
    "addr:full":"218 W King St St Augustine FL 32084",
    "addr:housenumber":"218",
    "addr:postcode":"32084",
    "addr:street":"W King St",
    "iso:country":"US",
    "sg:address":"218 W King St",
    "sg:city":"St Augustine",
    "sg:classifiers":[
        {
            "category":"Banks & Credit Unions",
            "subcategory":"Bank",
            "type":"Services"
        }
    ],
    "sg:phone":"+1 904 797 4140",
    "sg:postcode":"32084",
    "sg:province":"FL",
    "sg:tags":[
        "loan"
    ],
    "wof:name":"Hometown Payroll Advance II",
    "wof:placetype":"venue"
},
  "geometry": {"coordinates":[-81.32691199999999,29.890879],"type":"Point"}
}