{
  "type": "Feature",
  "properties": {
    "iso:country":"US",
    "sg:address":"12397 NW 90th Ave",
    "sg:city":"Reddick",
    "sg:classifiers":[
        {
            "category":"Retail",
            "subcategory":"Veterinary Services",
            "type":"Services"
        }
    ],
    "sg:phone":"+1 352 817 4997",
    "sg:postcode":"32686",
    "sg:province":"FL",
    "sg:tags":[
        "veterinarian"
    ],
    "wof:name":"Theodore E Specht DVM",
    "wof:placetype":"venue"
},
  "geometry": {"coordinates":[-82.272312,29.322701],"type":"Point"}
}