{
  "type": "Feature",
  "properties": {
    "addr:full":"231 Canal St New Smyrna Beach FL 32168",
    "addr:housenumber":"231",
    "addr:postcode":"32168",
    "addr:street":"Canal St",
    "iso:country":"US",
    "sg:address":"231 Canal St",
    "sg:city":"New Smyrna Beach",
    "sg:classifiers":[
        {
            "category":"Freight",
            "type":"Transportation"
        }
    ],
    "sg:phone":"+1 386 428 6339",
    "sg:postcode":"32168",
    "sg:province":"FL",
    "sg:tags":[
        "courier"
    ],
    "wof:name":"Parcel Pack & Ship",
    "wof:placetype":"venue"
},
  "geometry": {"coordinates":[-80.92247999999999,29.025134],"type":"Point"}
}