{
  "type": "Feature",
  "properties": {
    "iso:country":"US",
    "sg:address":"6210 S Harold Ave",
    "sg:city":"Tampa",
    "sg:classifiers":[
        {
            "category":"Shopping",
            "subcategory":"Hobbies, Toys, & Games",
            "type":"Retail Goods"
        }
    ],
    "sg:phone":"+1 813 839 7283",
    "sg:postcode":"33616",
    "sg:province":"FL",
    "sg:website":"www.emarbles.com",
    "wof:name":"Little Works Of Art Marbles",
    "wof:placetype":"venue"
},
  "geometry": {"coordinates":[-82.507501,27.875678],"type":"Point"}
}