{
  "type": "Feature",
  "properties": {
    "addr:full":"401 Little John Rd Mary Esther FL 32569",
    "addr:housenumber":"401",
    "addr:postcode":"32569",
    "addr:street":"Little John Rd Mary",
    "iso:country":"US",
    "sg:address":"401 Little John Rd",
    "sg:city":"Mary Esther",
    "sg:classifiers":[
        {
            "category":"Building & Trades",
            "subcategory":"Construction",
            "type":"Services"
        }
    ],
    "sg:phone":"+1 850 865 8732",
    "sg:postcode":"32569",
    "sg:province":"FL",
    "sg:tags":[
        "handyman"
    ],
    "wof:name":"Stan The Handyman",
    "wof:placetype":"venue"
},
  "geometry": {"coordinates":[-86.73777200000001,30.414955],"type":"Point"}
}