{
  "type": "Feature",
  "properties": {
    "addr:full":"1237 Roland Rd Chipley FL 32428",
    "addr:housenumber":"1237",
    "addr:postcode":"32428",
    "addr:street":"Roland Rd",
    "iso:country":"US",
    "sg:address":"1237 Roland Rd",
    "sg:city":"Chipley",
    "sg:classifiers":[
        {
            "category":"Freight",
            "type":"Transportation"
        }
    ],
    "sg:phone":"+1 850 415 1989",
    "sg:postcode":"32428",
    "sg:province":"FL",
    "sg:tags":[
        "operator",
        "local",
        "trucking"
    ],
    "wof:name":"M A P P Trucking LLC",
    "wof:placetype":"venue"
},
  "geometry": {"coordinates":[-85.55208,30.633524],"type":"Point"}
}