{
  "type": "Feature",
  "properties": {
    "iso:country":"US",
    "sg:address":"9235 SW 78th Ct",
    "sg:city":"Miami",
    "sg:classifiers":[
        {
            "category":"Professional",
            "type":"Services"
        }
    ],
    "sg:phone":"+1 305 951 6903",
    "sg:postcode":"33156",
    "sg:province":"FL",
    "wof:name":"Jccg Inc",
    "wof:placetype":"venue"
},
  "geometry": {"coordinates":[-80.32194800000001,25.68614],"type":"Point"}
}