{
  "type": "Feature",
  "properties": {
    "iso:country":"US",
    "sg:address":"1504 NE Jensen Beach Blvd",
    "sg:city":"Jensen Beach",
    "sg:classifiers":[
        {
            "category":"Home & Garden",
            "subcategory":"Building Materials",
            "type":"Retail Goods"
        }
    ],
    "sg:phone":"+1 772 223 5578",
    "sg:postcode":"34957",
    "sg:province":"FL",
    "sg:tags":[
        "shutter"
    ],
    "wof:name":"Budget Shutter",
    "wof:placetype":"venue"
},
  "geometry": {"coordinates":[-80.232161,27.243881],"type":"Point"}
}