{
  "type": "Feature",
  "properties": {
    "iso:country":"US",
    "sg:address":"123 NW 61st Ave",
    "sg:city":"Hollywood",
    "sg:classifiers":[
        {
            "category":"Real Estate",
            "subcategory":"Real Estate Operator",
            "type":"Services"
        }
    ],
    "sg:phone":"+1 954 472 2978",
    "sg:postcode":"33024",
    "sg:province":"FL",
    "sg:tags":[
        "apartment"
    ],
    "wof:name":"Alolill Apartments",
    "wof:placetype":"venue"
},
  "geometry": {"coordinates":[-80.210115,26.011224],"type":"Point"}
}