{
  "type": "Feature",
  "properties": {
    "iso:country":"US",
    "sg:address":"509 S Ocean Blvd",
    "sg:city":"Boca Raton",
    "sg:classifiers":[
        {
            "category":"Manufacturing",
            "subcategory":"Furniture",
            "type":"Manufacturing & Wholesale Goods"
        }
    ],
    "sg:phone":"+1 561 368 1476",
    "sg:postcode":"33432",
    "sg:province":"FL",
    "sg:tags":[
        "household",
        "wood",
        "mfg"
    ],
    "wof:name":"Dalling Additions Inc",
    "wof:placetype":"venue"
},
  "geometry": {"coordinates":[-80.071917,26.342354],"type":"Point"}
}