{
  "type": "Feature",
  "properties": {
    "iso:country":"US",
    "sg:address":"1413 Smith St",
    "sg:city":"Kissimmee",
    "sg:classifiers":[
        {
            "category":"Local Transit",
            "type":"Transportation"
        }
    ],
    "sg:phone":"+1 407 933 9999",
    "sg:postcode":"34744",
    "sg:province":"FL",
    "sg:tags":[
        "limousine"
    ],
    "wof:name":"First Florida Tours",
    "wof:placetype":"venue"
},
  "geometry": {"coordinates":[-81.399939,28.304981],"type":"Point"}
}