{
  "type": "Feature",
  "properties": {
    "addr:full":"512 Canal St New Smyrna Beach FL 32168",
    "addr:housenumber":"512",
    "addr:postcode":"32168",
    "addr:street":"Canal St",
    "iso:country":"US",
    "sg:address":"512 Canal St",
    "sg:city":"New Smyrna Beach",
    "sg:classifiers":[
        {
            "category":"Shopping",
            "subcategory":"Used Merchandise",
            "type":"Retail Goods"
        }
    ],
    "sg:phone":"+1 386 428 3331",
    "sg:postcode":"32168",
    "sg:province":"FL",
    "sg:tags":[
        "antique"
    ],
    "wof:name":"Coronado Antiques & Cllctbls",
    "wof:placetype":"venue"
},
  "geometry": {"coordinates":[-80.925444,29.02394],"type":"Point"}
}