{
  "type": "Feature",
  "properties": {
    "addr:full":"106 E 5th Ave Windermere FL 34786",
    "addr:housenumber":"106",
    "addr:postcode":"34786",
    "addr:street":"E 5Th Ave",
    "iso:country":"US",
    "sg:address":"106 E 5th Ave",
    "sg:city":"Windermere",
    "sg:classifiers":[
        {
            "category":"Wholesale",
            "subcategory":"Groceries",
            "type":"Manufacturing & Wholesale Goods"
        }
    ],
    "sg:phone":"+1 407 877 6944",
    "sg:postcode":"34786",
    "sg:province":"FL",
    "sg:tags":[
        "food",
        "broker"
    ],
    "wof:name":"Horizon Foods",
    "wof:placetype":"venue"
},
  "geometry": {"coordinates":[-81.53292500000001,28.496097],"type":"Point"}
}