{
  "type": "Feature",
  "properties": {
    "iso:country":"US",
    "sg:address":"8626 Leo Kidd Ave",
    "sg:city":"Port Richey",
    "sg:classifiers":[
        {
            "category":"Banks & Credit Unions",
            "subcategory":"Investment Brokerage",
            "type":"Services"
        }
    ],
    "sg:phone":"+1 727 845 5019",
    "sg:postcode":"34668",
    "sg:province":"FL",
    "wof:name":"Interstate Investments & Cnstr",
    "wof:placetype":"venue"
},
  "geometry": {"coordinates":[-82.715468,28.281929],"type":"Point"}
}