{
  "type": "Feature",
  "properties": {
    "addr:full":"131 S Pebble Beach Blvd Sun City FL 33573",
    "addr:housenumber":"131",
    "addr:postcode":"33573",
    "addr:street":"S Pebble Beach Blvd",
    "iso:country":"US",
    "sg:address":"131 S Pebble Beach Blvd",
    "sg:city":"Sun City",
    "sg:classifiers":[
        {
            "category":"Banks & Credit Unions",
            "subcategory":"Bank",
            "type":"Services"
        }
    ],
    "sg:phone":"+1 813 633 3321",
    "sg:postcode":"33573",
    "sg:province":"FL",
    "sg:tags":[
        "national",
        "commercial"
    ],
    "wof:name":"Regions Bank",
    "wof:placetype":"venue"
},
  "geometry": {"coordinates":[-82.35196000000001,27.711745],"type":"Point"}
}