{
  "type": "Feature",
  "properties": {
    "iso:country":"US",
    "sg:address":"281 Sabal Palm Ln",
    "sg:city":"Vero Beach",
    "sg:classifiers":[
        {
            "category":"Travel",
            "subcategory":"Travel Agent",
            "type":"Entertainment"
        }
    ],
    "sg:phone":"+1 772 231 3358",
    "sg:postcode":"32963",
    "sg:province":"FL",
    "sg:tags":[
        "agency"
    ],
    "wof:name":"Dd Travel",
    "wof:placetype":"venue"
},
  "geometry": {"coordinates":[-80.378664,27.702248],"type":"Point"}
}