{
  "type": "Feature",
  "properties": {
    "iso:country":"US",
    "sg:address":"5547 Garden Grove Cir",
    "sg:city":"Winter Park",
    "sg:classifiers":[
        {
            "category":"Freight",
            "type":"Transportation"
        }
    ],
    "sg:phone":"+1 407 678 2054",
    "sg:postcode":"32792",
    "sg:province":"FL",
    "sg:tags":[
        "operator",
        "trucking"
    ],
    "wof:name":"M A S & Sons Transport Inc",
    "wof:placetype":"venue"
},
  "geometry": {"coordinates":[-81.293189,28.622379],"type":"Point"}
}