{
  "type": "Feature",
  "properties": {
    "addr:full":"610 Northern Rd Daytona Beach FL 32119",
    "addr:housenumber":"610",
    "addr:postcode":"32119",
    "addr:street":"Northern Rd",
    "iso:country":"US",
    "sg:address":"610 Northern Rd",
    "sg:city":"Daytona Beach",
    "sg:classifiers":[
        {
            "category":"Building & Trades",
            "subcategory":"Construction",
            "type":"Services"
        }
    ],
    "sg:phone":"+1 386 761 0048",
    "sg:postcode":"32119",
    "sg:province":"FL",
    "sg:tags":[
        "house"
    ],
    "wof:name":"Handyman Services",
    "wof:placetype":"venue"
},
  "geometry": {"coordinates":[-81.014337,29.179955],"type":"Point"}
}