{
  "type": "Feature",
  "properties": {
    "addr:full":"6480 Crystal Ln Jay FL 32565",
    "addr:housenumber":"6480",
    "addr:postcode":"32565",
    "addr:street":"Crystal Ln",
    "iso:country":"US",
    "sg:address":"6480 Crystal Ln",
    "sg:city":"Jay",
    "sg:classifiers":[
        {
            "category":"Building & Trades",
            "subcategory":"Construction",
            "type":"Services"
        }
    ],
    "sg:phone":"+1 850 957 4445",
    "sg:postcode":"32565",
    "sg:province":"FL",
    "sg:tags":[
        "contractor"
    ],
    "wof:name":"Shawn Phillips Drywall",
    "wof:placetype":"venue"
},
  "geometry": {"coordinates":[-86.945578,30.992138],"type":"Point"}
}