{
  "type": "Feature",
  "properties": {
    "iso:country":"US",
    "sg:address":"9240 Blount Island Blvd",
    "sg:city":"Jacksonville",
    "sg:classifiers":[
        {
            "category":"Wholesale",
            "subcategory":"Motor Vehicles",
            "type":"Manufacturing & Wholesale Goods"
        }
    ],
    "sg:phone":"+1 904 751 4391",
    "sg:postcode":"32226",
    "sg:province":"FL",
    "sg:tags":[
        "import",
        "processing",
        "automobile",
        "facility"
    ],
    "wof:name":"Amports",
    "wof:placetype":"venue"
},
  "geometry": {"coordinates":[-81.543773,30.400437],"type":"Point"}
}