{
  "type": "Feature",
  "properties": {
    "addr:full":"669 Cortez Rd W Palmetto FL 34207",
    "addr:housenumber":"669",
    "addr:postcode":"34207",
    "addr:street":"Cortez Rd W",
    "iso:country":"US",
    "sg:address":"669 Cortez Rd W",
    "sg:city":"Palmetto",
    "sg:classifiers":[
        {
            "category":"Retail",
            "subcategory":"Self-service Laundry",
            "type":"Services"
        }
    ],
    "sg:phone":"+1 941 727 0366",
    "sg:postcode":"34207",
    "sg:province":"FL",
    "wof:name":"Cortez Plaza East Coin Laundry",
    "wof:placetype":"venue"
},
  "geometry": {"coordinates":[-82.567807,27.462239],"type":"Point"}
}