{
  "type": "Feature",
  "properties": {
    "addr:full":"23 Alafaya Woods Blvd Oviedo FL 32765",
    "addr:housenumber":"23",
    "addr:postcode":"32765",
    "addr:street":"Alafaya Woods Blvd",
    "iso:country":"US",
    "sg:address":"23 Alafaya Woods Blvd",
    "sg:city":"Oviedo",
    "sg:classifiers":[
        {
            "category":"Professional",
            "subcategory":"Business Services",
            "type":"Services"
        }
    ],
    "sg:phone":"+1 407 830 0996",
    "sg:postcode":"32765",
    "sg:province":"FL",
    "sg:tags":[
        "water",
        "treatment"
    ],
    "wof:name":"Aqua Cops",
    "wof:placetype":"venue"
},
  "geometry": {"coordinates":[-81.202989,28.649851],"type":"Point"}
}