{
  "type": "Feature",
  "properties": {
    "iso:country":"US",
    "sg:address":"7612 University Blvd",
    "sg:city":"Winter Park",
    "sg:classifiers":[
        {
            "category":"Shopping",
            "type":"Retail Goods"
        }
    ],
    "sg:phone":"+1 407 679 3312",
    "sg:postcode":"32792",
    "sg:province":"FL",
    "sg:tags":[
        "trophy",
        "medal",
        "award"
    ],
    "wof:name":"AAA Trophies & Baseball Crds",
    "wof:placetype":"venue"
},
  "geometry": {"coordinates":[-81.278695,28.597498],"type":"Point"}
}