{
  "type": "Feature",
  "properties": {
    "addr:full":"5508 N Armenia Ave Tampa FL 33603",
    "addr:housenumber":"5508",
    "addr:postcode":"33603",
    "addr:street":"N Armenia Ave",
    "iso:country":"US",
    "sg:address":"5508 N Armenia Ave",
    "sg:city":"Tampa",
    "sg:classifiers":[
        {
            "category":"Wholesale",
            "subcategory":"Office Equipment",
            "type":"Manufacturing & Wholesale Goods"
        }
    ],
    "sg:phone":"+1 813 871 1187",
    "sg:postcode":"33603",
    "sg:province":"FL",
    "sg:tags":[
        "register",
        "cash",
        "supply"
    ],
    "wof:name":"Cash Register Sales Inc",
    "wof:placetype":"venue"
},
  "geometry": {"coordinates":[-82.48446800000001,27.997542],"type":"Point"}
}