{
  "type": "Feature",
  "properties": {
    "iso:country":"US",
    "sg:address":"630 Holly St",
    "sg:city":"Monticello",
    "sg:classifiers":[
        {
            "category":"Place Of Worship",
            "subcategory":"Church",
            "type":"Public Place"
        },
        {
            "category":"Place Of Worship",
            "type":"Public Place"
        },
        {
            "category":"Organizations",
            "subcategory":"Religious Organization",
            "type":"Services"
        }
    ],
    "sg:phone":"+1 850 997 0028",
    "sg:postcode":"32344",
    "sg:province":"FL",
    "sg:tags":[
        "god",
        "churches-church",
        "churches-pentecostal"
    ],
    "wof:name":"Monticello Church Of God In Christ",
    "wof:placetype":"venue"
},
  "geometry": {"coordinates":[-83.864886,30.542317],"type":"Point"}
}