{
  "type": "Feature",
  "properties": {
    "iso:country":"US",
    "sg:address":"2300 NW 92nd St",
    "sg:city":"Miami",
    "sg:classifiers":[
        {
            "category":"Wholesale",
            "subcategory":"Fruits & Vegetables",
            "type":"Manufacturing & Wholesale Goods"
        }
    ],
    "sg:phone":"+1 305 593 6778",
    "sg:postcode":"33147",
    "sg:province":"FL",
    "sg:tags":[
        "veggie"
    ],
    "wof:name":"Miramar Fruit Trading Corp",
    "wof:placetype":"venue"
},
  "geometry": {"coordinates":[-80.235996,25.857713],"type":"Point"}
}