{
  "type": "Feature",
  "properties": {
    "addr:full":"823 N Woodland Blvd Deland FL 32720",
    "addr:housenumber":"823",
    "addr:postcode":"32720",
    "addr:street":"N Woodland Blvd",
    "iso:country":"US",
    "sg:address":"823 N Woodland Blvd",
    "sg:city":"Deland",
    "sg:classifiers":[
        {
            "category":"Organizations",
            "subcategory":"Religious Organization",
            "type":"Services"
        }
    ],
    "sg:phone":"+1 386 734 4311",
    "sg:postcode":"32720",
    "sg:province":"FL",
    "sg:tags":[
        "church"
    ],
    "wof:name":"Church Of Christ At De Land",
    "wof:placetype":"venue"
},
  "geometry": {"coordinates":[-81.30377799999999,29.04149],"type":"Point"}
}