{
  "type": "Feature",
  "properties": {
    "iso:country":"US",
    "sg:address":"201 S Biscayne Blvd Fl 28",
    "sg:city":"Miami",
    "sg:classifiers":[
        {
            "category":"Professional",
            "subcategory":"Engineering",
            "type":"Services"
        }
    ],
    "sg:phone":"+1 305 913 4636",
    "sg:postcode":"33131",
    "sg:province":"FL",
    "sg:tags":[
        "consulting",
        "engineer"
    ],
    "wof:name":"Inima Usa Corporation",
    "wof:placetype":"venue"
},
  "geometry": {"coordinates":[-80.187134,25.772663],"type":"Point"}
}