{
  "type": "Feature",
  "properties": {
    "iso:country":"US",
    "sg:address":"1731 Coral Way",
    "sg:city":"Miami",
    "sg:classifiers":[
        {
            "category":"Arts & Performance",
            "subcategory":"Art Gallery",
            "type":"Entertainment"
        },
        {
            "category":"Professional",
            "subcategory":"Art Services",
            "type":"Services"
        }
    ],
    "sg:phone":"+1 305 860 0255",
    "sg:postcode":"33145",
    "sg:province":"FL",
    "sg:tags":[
        "framing"
    ],
    "sg:website":"www.workofartgallery",
    "wof:name":"Work of Art Gallery & Custom Picture Framing",
    "wof:placetype":"venue"
},
  "geometry": {"coordinates":[-80.226066,25.750836],"type":"Point"}
}