{
  "type": "Feature",
  "properties": {
    "iso:country":"US",
    "sg:address":"10351 Thompson Pl",
    "sg:city":"Clermont",
    "sg:classifiers":[
        {
            "category":"Wholesale",
            "subcategory":"Toys & Hobbies",
            "type":"Manufacturing & Wholesale Goods"
        }
    ],
    "sg:phone":"+1 352 394 1129",
    "sg:postcode":"34711",
    "sg:province":"FL",
    "sg:tags":[
        "piece"
    ],
    "wof:name":"Hml International Inc",
    "wof:placetype":"venue"
},
  "geometry": {"coordinates":[-81.78431399999999,28.53669],"type":"Point"}
}