{
  "type": "Feature",
  "properties": {
    "addr:full":"619 Whitney Ave Lantana FL 33462",
    "addr:housenumber":"619",
    "addr:postcode":"33462",
    "addr:street":"Whitney Ave",
    "iso:country":"US",
    "sg:address":"619 Whitney Ave",
    "sg:city":"Lantana",
    "sg:classifiers":[
        {
            "category":"Home & Garden",
            "subcategory":"Home Furnishings",
            "type":"Retail Goods"
        },
        {
            "category":"Building & Trades",
            "subcategory":"Construction",
            "type":"Services"
        },
        {
            "category":"Manufacturing",
            "subcategory":"Building Materials",
            "type":"Manufacturing & Wholesale Goods"
        }
    ],
    "sg:phone":"+1 561 533 0054",
    "sg:postcode":"33462",
    "sg:province":"FL",
    "sg:tags":[
        "industrial",
        "cabinetmakers-commercial",
        "cabinet",
        "refacing",
        "resurfacing",
        "maker",
        "cabinets-refinishing",
        "kitchen"
    ],
    "wof:name":"MiLo Custom Contractors",
    "wof:placetype":"venue"
},
  "geometry": {"coordinates":[-80.056718,26.591821],"type":"Point"}
}