{
  "type": "Feature",
  "properties": {
    "iso:country":"US",
    "sg:address":"5091 Okeechobee Rd",
    "sg:city":"Fort Pierce",
    "sg:classifiers":[
        {
            "category":"Restaurant",
            "type":"Food & Drink"
        },
        {
            "category":"Bakery",
            "type":"Food & Drink"
        }
    ],
    "sg:menulink":"http://www.allmenus.com/fl/fort-pierce/99969-golden-corral/menu/",
    "sg:phone":"+1 772 489 8004",
    "sg:postcode":"34947",
    "sg:province":"FL",
    "sg:tags":[
        "american",
        "bakery",
        "pastry"
    ],
    "wof:name":"Golden Corral",
    "wof:placetype":"venue"
},
  "geometry": {"coordinates":[-80.37650600000001,27.419753],"type":"Point"}
}