{
  "type": "Feature",
  "properties": {
    "addr:full":"18130 Jorene Rd Odessa FL 33556",
    "addr:postcode":"18130;33556",
    "addr:street":"Jorene Rd",
    "iso:country":"US",
    "sg:address":"18130 Jorene Rd",
    "sg:city":"Odessa",
    "sg:classifiers":[
        {
            "category":"Professional",
            "subcategory":"Computer Services",
            "type":"Services"
        }
    ],
    "sg:phone":"+1 813 920 0788",
    "sg:postcode":"33556",
    "sg:province":"FL",
    "sg:tags":[
        "web"
    ],
    "sg:website":"www.launchpadonline.com",
    "wof:name":"Launch Pad",
    "wof:placetype":"venue"
},
  "geometry": {"coordinates":[-82.61524,28.14228],"type":"Point"}
}