{
  "type": "Feature",
  "properties": {
    "addr:full":"1313 Everest Pkwy Cape Coral FL 33904",
    "addr:housenumber":"1313",
    "addr:postcode":"33904",
    "addr:street":"Everest Pkwy",
    "iso:country":"US",
    "sg:address":"1313 Everest Pkwy",
    "sg:city":"Cape Coral",
    "sg:classifiers":[
        {
            "category":"Shopping",
            "type":"Retail Goods"
        }
    ],
    "sg:phone":"+1 239 699 4660",
    "sg:postcode":"33904",
    "sg:province":"FL",
    "sg:tags":[
        "movie",
        "game",
        "music"
    ],
    "wof:name":"Filmtradercom LLC",
    "wof:placetype":"venue"
},
  "geometry": {"coordinates":[-81.942584,26.606484],"type":"Point"}
}