{
  "type": "Feature",
  "properties": {
    "iso:country":"US",
    "sg:address":"6347 US Hwy 301",
    "sg:city":"Riverview",
    "sg:classifiers":[
        {
            "category":"Home & Garden",
            "subcategory":"Household Appliances",
            "type":"Retail Goods"
        }
    ],
    "sg:phone":"+1 813 741 0145",
    "sg:postcode":"33569",
    "sg:province":"FL",
    "wof:name":"William Klaue Appliances",
    "wof:placetype":"venue"
},
  "geometry": {"coordinates":[-82.337667,27.893255],"type":"Point"}
}