{
  "type": "Feature",
  "properties": {
    "iso:country":"US",
    "sg:address":"6513 NW 55th St",
    "sg:city":"Coral Springs",
    "sg:classifiers":[
        {
            "category":"Health Services",
            "subcategory":"Nursing And Care Facility",
            "type":"Services"
        },
        {
            "category":"Social Services",
            "subcategory":"Adult Care",
            "type":"Services"
        }
    ],
    "sg:phone":"+1 954 255 5588",
    "sg:postcode":"33067",
    "sg:province":"FL",
    "sg:tags":[
        "home",
        "intermediate",
        "residential"
    ],
    "wof:name":"Assisted Living Sunshine",
    "wof:placetype":"venue"
},
  "geometry": {"coordinates":[-80.21687900000001,26.296775],"type":"Point"}
}