{
  "type": "Feature",
  "properties": {
    "iso:country":"US",
    "sg:address":"11750 SW 40th St",
    "sg:city":"Miami",
    "sg:classifiers":[
        {
            "category":"Health Services",
            "subcategory":"Doctor",
            "type":"Services"
        }
    ],
    "sg:phone":"+1 305 228 9662",
    "sg:postcode":"33175",
    "sg:province":"FL",
    "wof:name":"Sheridan Healthcorp",
    "wof:placetype":"venue"
},
  "geometry": {"coordinates":[-80.384345,25.731843],"type":"Point"}
}