{
  "type": "Feature",
  "properties": {
    "addr:full":"135 S Acuff Rd Lake Wales FL 33859",
    "addr:housenumber":"135",
    "addr:postcode":"33859",
    "addr:street":"S Acuff Rd",
    "iso:country":"US",
    "sg:address":"135 S Acuff Rd",
    "sg:city":"Lake Wales",
    "sg:classifiers":[
        {
            "category":"Restaurant",
            "type":"Food & Drink"
        },
        {
            "category":"Building & Trades",
            "subcategory":"Plumbing",
            "type":"Services"
        }
    ],
    "sg:phone":"+1 863 421 9276",
    "sg:postcode":"33859",
    "sg:province":"FL",
    "sg:tags":[
        "drywall",
        "air",
        "refrigeration",
        "conditioning",
        "installer"
    ],
    "sg:website":"www.ridgeenergy.com",
    "wof:name":"Ridge Energy Savers Inc",
    "wof:placetype":"venue"
},
  "geometry": {"coordinates":[-81.626582,27.903364],"type":"Point"}
}