{
  "type": "Feature",
  "properties": {
    "iso:country":"US",
    "sg:address":"6624 SW 113th Ave",
    "sg:city":"Miami",
    "sg:classifiers":[
        {
            "category":"Home & Garden",
            "subcategory":"Carpets & Floor Coverings",
            "type":"Retail Goods"
        }
    ],
    "sg:phone":"+1 305 412 3038",
    "sg:postcode":"33173",
    "sg:province":"FL",
    "sg:tags":[
        "flooring",
        "contractor"
    ],
    "wof:name":"Achong Inc.",
    "wof:placetype":"venue"
},
  "geometry": {"coordinates":[-80.376395,25.705002],"type":"Point"}
}