{
  "type": "Feature",
  "properties": {
    "iso:country":"US",
    "sg:address":"1008 University Blvd N",
    "sg:city":"Jacksonville",
    "sg:classifiers":[
        {
            "category":"Autos & Motor Vehicles",
            "subcategory":"Auto Supplies",
            "type":"Retail Goods"
        }
    ],
    "sg:phone":"+1 904 743 2525",
    "sg:postcode":"32211",
    "sg:province":"FL",
    "sg:tags":[
        "tire"
    ],
    "wof:name":"Firestone Tire & Svc Ctr",
    "wof:placetype":"venue"
},
  "geometry": {"coordinates":[-81.60329299999999,30.331146],"type":"Point"}
}