{
  "type": "Feature",
  "properties": {
    "iso:country":"US",
    "sg:address":"13454 Chambord St",
    "sg:city":"Brooksville",
    "sg:classifiers":[
        {
            "category":"Communications",
            "type":"Services"
        }
    ],
    "sg:phone":"+1 352 796 2300",
    "sg:postcode":"34613",
    "sg:province":"FL",
    "sg:tags":[
        "communication"
    ],
    "wof:name":"C and D Communications Inc",
    "wof:placetype":"venue"
},
  "geometry": {"coordinates":[-82.501744,28.535507],"type":"Point"}
}