{
  "type": "Feature",
  "properties": {
    "addr:full":"5325 Frontage Rd S Lakeland FL 33815",
    "addr:housenumber":"5325",
    "addr:postcode":"33815",
    "addr:street":"Frontage Rd S",
    "iso:country":"US",
    "sg:address":"5325 Frontage Rd S",
    "sg:city":"Lakeland",
    "sg:classifiers":[
        {
            "category":"Restaurant",
            "type":"Food & Drink"
        }
    ],
    "sg:menulink":"http://www.allmenus.com/fl/lakeland/187320-mcdonalds/menu/",
    "sg:phone":"+1 863 603 0230",
    "sg:postcode":"33815",
    "sg:province":"FL",
    "sg:tags":[
        "burger",
        "american"
    ],
    "wof:name":"McDonald's",
    "wof:placetype":"venue"
},
  "geometry": {"coordinates":[-82.05139699999999,28.036201],"type":"Point"}
}