{
  "type": "Feature",
  "properties": {
    "iso:country":"US",
    "sg:address":"8761 SW 24th St",
    "sg:city":"Miami",
    "sg:classifiers":[
        {
            "category":"Shopping",
            "subcategory":"Used Merchandise",
            "type":"Retail Goods"
        }
    ],
    "sg:phone":"+1 305 485 8859",
    "sg:postcode":"33165",
    "sg:province":"FL",
    "sg:tags":[
        "clothing"
    ],
    "wof:name":"Namebrand Fashions Outlet",
    "wof:placetype":"venue"
},
  "geometry": {"coordinates":[-80.336572,25.74769],"type":"Point"}
}