{
  "type": "Feature",
  "properties": {
    "addr:full":"1136 E 9th St Jacksonville FL 32206",
    "addr:housenumber":"1136",
    "addr:postcode":"32206",
    "addr:street":"E 9Th St",
    "iso:country":"US",
    "sg:address":"1136 E 9th St",
    "sg:city":"Jacksonville",
    "sg:classifiers":[
        {
            "category":"Autos & Motor Vehicles",
            "subcategory":"Auto Supplies",
            "type":"Retail Goods"
        },
        {
            "category":"Personal",
            "type":"Services"
        },
        {
            "category":"Retail",
            "subcategory":"Auto Repair",
            "type":"Services"
        }
    ],
    "sg:phone":"+1 904 355 3636",
    "sg:postcode":"32206",
    "sg:province":"FL",
    "sg:tags":[
        "body",
        "automobile",
        "trailers-repair",
        "truck",
        "towing",
        "painting",
        "repairing"
    ],
    "sg:website":"http://www.realpagessites.com/universalbodyco",
    "wof:name":"Universal Body Co",
    "wof:placetype":"venue"
},
  "geometry": {"coordinates":[-81.640427,30.346023],"type":"Point"}
}