{
  "type": "Feature",
  "properties": {
    "addr:full":"12800 SW 188th St Miami FL 33177",
    "addr:housenumber":"12800",
    "addr:postcode":"33177",
    "addr:street":"Sw 188Th St",
    "iso:country":"US",
    "sg:address":"12800 SW 188th St",
    "sg:city":"Miami",
    "sg:classifiers":[
        {
            "category":"Building & Trades",
            "subcategory":"Construction",
            "type":"Services"
        }
    ],
    "sg:phone":"+1 305 970 5041",
    "sg:postcode":"33177",
    "sg:province":"FL",
    "sg:tags":[
        "house"
    ],
    "wof:name":"B C Arvizu Construction Inc",
    "wof:placetype":"venue"
},
  "geometry": {"coordinates":[-80.401105,25.592291],"type":"Point"}
}