{
  "type": "Feature",
  "properties": {
    "iso:country":"US",
    "sg:address":"2541 SW 27th Ave",
    "sg:city":"Miami",
    "sg:classifiers":[
        {
            "category":"Professional",
            "subcategory":"Lawyer & Legal Services",
            "type":"Services"
        }
    ],
    "sg:phone":"+1 305 856 1848",
    "sg:postcode":"33133",
    "sg:province":"FL",
    "wof:name":"Leeds Scott W Atty",
    "wof:placetype":"venue"
},
  "geometry": {"coordinates":[-80.237791,25.744399],"type":"Point"}
}