{
  "type": "Feature",
  "properties": {
    "addr:full":"3131 Holland Dr Orlando FL 32825",
    "addr:housenumber":"3131",
    "addr:postcode":"32825",
    "addr:street":"Holland Dr",
    "iso:country":"US",
    "sg:address":"3131 Holland Dr",
    "sg:city":"Orlando",
    "sg:classifiers":[
        {
            "category":"Home & Garden",
            "subcategory":"Furniture",
            "type":"Retail Goods"
        }
    ],
    "sg:phone":"+1 407 382 0697",
    "sg:postcode":"32825",
    "sg:province":"FL",
    "wof:name":"Bedroom Superstores Inc",
    "wof:placetype":"venue"
},
  "geometry": {"coordinates":[-81.236102,28.50528],"type":"Point"}
}