{
  "type": "Feature",
  "properties": {
    "addr:full":"2970 S Atlantic Ave Daytona Beach FL 32118",
    "addr:housenumber":"2970",
    "addr:postcode":"32118",
    "addr:street":"S Atlantic Ave",
    "iso:country":"US",
    "sg:address":"2970 S Atlantic Ave",
    "sg:city":"Daytona Beach",
    "sg:classifiers":[
        {
            "category":"Real Estate",
            "subcategory":"Developer",
            "type":"Services"
        }
    ],
    "sg:phone":"+1 386 322 1302",
    "sg:postcode":"32118",
    "sg:province":"FL",
    "wof:name":"Ocean West II LLC",
    "wof:placetype":"venue"
},
  "geometry": {"coordinates":[-80.979005,29.169394],"type":"Point"}
}