{
  "type": "Feature",
  "properties": {
    "addr:full":"11401 Dixie Hwy Miami FL 33156",
    "addr:housenumber":"11401",
    "addr:postcode":"33156",
    "addr:street":"Dixie Hwy",
    "iso:country":"US",
    "sg:address":"11401 Dixie Hwy",
    "sg:city":"Miami",
    "sg:classifiers":[
        {
            "category":"Shopping",
            "subcategory":"Tobacco",
            "type":"Retail Goods"
        }
    ],
    "sg:phone":"+1 305 252 9010",
    "sg:postcode":"33156",
    "sg:province":"FL",
    "sg:tags":[
        "product"
    ],
    "wof:name":"Harriels Tobacco Inc",
    "wof:placetype":"venue"
},
  "geometry": {"coordinates":[-80.324681,25.664449],"type":"Point"}
}