{
  "type": "Feature",
  "properties": {
    "iso:country":"US",
    "sg:address":"5781 Aurora Ct",
    "sg:city":"Lake Worth",
    "sg:classifiers":[
        {
            "category":"Building & Trades",
            "subcategory":"Cleaning & Sanitation",
            "type":"Services"
        }
    ],
    "sg:phone":"+1 561 642 6454",
    "sg:postcode":"33463",
    "sg:province":"FL",
    "sg:tags":[
        "janitor"
    ],
    "wof:name":"Affordable Services Rsdntl",
    "wof:placetype":"venue"
},
  "geometry": {"coordinates":[-80.135773,26.602453],"type":"Point"}
}