{
  "type": "Feature",
  "properties": {
    "iso:country":"US",
    "sg:address":"1811 SW 2nd Ave",
    "sg:city":"Okeechobee",
    "sg:classifiers":[
        {
            "category":"Social Services",
            "subcategory":"Child Care",
            "type":"Services"
        }
    ],
    "sg:phone":"+1 863 467 5000",
    "sg:postcode":"34974",
    "sg:province":"FL",
    "sg:tags":[
        "day"
    ],
    "wof:name":"Building Blocks Day Care Inc",
    "wof:placetype":"venue"
},
  "geometry": {"coordinates":[-80.831129,27.226293],"type":"Point"}
}