{
  "type": "Feature",
  "properties": {
    "iso:country":"US",
    "sg:address":"11440 N Kendall Dr",
    "sg:city":"Miami",
    "sg:classifiers":[
        {
            "category":"Social Services",
            "subcategory":"Child Care",
            "type":"Services"
        }
    ],
    "sg:phone":"+1 786 263 0001",
    "sg:postcode":"33176",
    "sg:province":"FL",
    "sg:tags":[
        "control",
        "information",
        "birth"
    ],
    "sg:website":"http://r.ppfa.org/hc?f=2258&a=90320",
    "wof:name":"Planned Parenthood Health Center",
    "wof:placetype":"venue"
},
  "geometry": {"coordinates":[-80.382075,25.686341],"type":"Point"}
}