{
  "type": "Feature",
  "properties": {
    "addr:full":"1008 S Dixie Hwy Hollywood FL 33020",
    "addr:housenumber":"1008",
    "addr:postcode":"33020",
    "addr:street":"S Dixie Hwy",
    "iso:country":"US",
    "sg:address":"1008 S Dixie Hwy",
    "sg:city":"Hollywood",
    "sg:classifiers":[
        {
            "category":"Autos & Motor Vehicles",
            "subcategory":"Auto Supplies",
            "type":"Retail Goods"
        },
        {
            "category":"Wholesale",
            "subcategory":"Electrical",
            "type":"Manufacturing & Wholesale Goods"
        }
    ],
    "sg:phone":"+1 954 457 9550",
    "sg:postcode":"33020",
    "sg:province":"FL",
    "sg:tags":[
        "battery",
        "automobile",
        "part",
        "batteries-storage",
        "accessory"
    ],
    "sg:website":"http://www.autozone.com",
    "wof:name":"AutoZone",
    "wof:placetype":"venue"
},
  "geometry": {"coordinates":[-80.14901500000001,26.003114],"type":"Point"}
}