{
  "type": "Feature",
  "properties": {
    "iso:country":"US",
    "sg:address":"6775 102nd Ave",
    "sg:city":"Pinellas Park",
    "sg:classifiers":[
        {
            "category":"Real Estate",
            "subcategory":"Real Estate Operator",
            "type":"Services"
        }
    ],
    "sg:phone":"+1 727 541 7789",
    "sg:postcode":"33782",
    "sg:province":"FL",
    "sg:tags":[
        "building",
        "nonresidential"
    ],
    "wof:name":"All Star Management",
    "wof:placetype":"venue"
},
  "geometry": {"coordinates":[-82.732799,27.864648],"type":"Point"}
}