{
  "type": "Feature",
  "properties": {
    "iso:country":"US",
    "sg:address":"2460 S Volusia Ave",
    "sg:city":"Orange City",
    "sg:classifiers":[
        {
            "category":"Shopping",
            "subcategory":"Hobbies, Toys, & Games",
            "type":"Retail Goods"
        }
    ],
    "sg:phone":"+1 386 775 1184",
    "sg:postcode":"32763",
    "sg:province":"FL",
    "sg:tags":[
        "supply",
        "craft",
        "framing",
        "custom"
    ],
    "wof:name":"Crafts & Stuff",
    "wof:placetype":"venue"
},
  "geometry": {"coordinates":[-81.30087399999999,28.918416],"type":"Point"}
}