{
  "type": "Feature",
  "properties": {
    "iso:country":"US",
    "sg:address":"9575 NW 3rd Ave",
    "sg:city":"Miami",
    "sg:classifiers":[
        {
            "category":"Retail",
            "subcategory":"Auto Repair",
            "type":"Services"
        }
    ],
    "sg:phone":"+1 305 754 2392",
    "sg:postcode":"33150",
    "sg:province":"FL",
    "sg:tags":[
        "automotive",
        "tune"
    ],
    "wof:name":"Supreme Tune & Lube",
    "wof:placetype":"venue"
},
  "geometry": {"coordinates":[-80.203523,25.862372],"type":"Point"}
}