{
  "type": "Feature",
  "properties": {
    "addr:full":"8055 Ironhorse Ct West Palm Beach FL 33412",
    "addr:postcode":"8055;33412",
    "addr:street":"Ironhorse Ct",
    "iso:country":"US",
    "sg:address":"8055 Ironhorse Ct",
    "sg:city":"West Palm Beach",
    "sg:classifiers":[
        {
            "category":"Recreation",
            "type":"Entertainment"
        }
    ],
    "sg:phone":"+1 561 624 5550",
    "sg:postcode":"33412",
    "sg:province":"FL",
    "sg:tags":[
        "course",
        "golf"
    ],
    "wof:name":"Iron Horse Country Club",
    "wof:placetype":"venue"
},
  "geometry": {"coordinates":[-80.13911,26.796254],"type":"Point"}
}