{
  "type": "Feature",
  "properties": {
    "addr:full":"1771 Sunset Harbour Dr Miami Beach FL 33139",
    "addr:housenumber":"1771",
    "addr:postcode":"33139",
    "addr:street":"Sunset Harbour Dr",
    "iso:country":"US",
    "sg:address":"1771 Sunset Harbour Dr",
    "sg:city":"Miami Beach",
    "sg:classifiers":[
        {
            "category":"Autos & Motor Vehicles",
            "subcategory":"Boat Sales",
            "type":"Retail Goods"
        }
    ],
    "sg:phone":"+1 305 535 1227",
    "sg:postcode":"33139",
    "sg:province":"FL",
    "wof:name":"Kayak Influence Inc",
    "wof:placetype":"venue"
},
  "geometry": {"coordinates":[-80.144276,25.792265],"type":"Point"}
}