{
  "type": "Feature",
  "properties": {
    "addr:full":"4625 Chandler Rd Apopka FL 32712",
    "addr:housenumber":"4625",
    "addr:postcode":"32712",
    "addr:street":"Chandler Rd",
    "iso:country":"US",
    "sg:address":"4625 Chandler Rd",
    "sg:city":"Apopka",
    "sg:classifiers":[
        {
            "category":"Farming",
            "subcategory":"Nursery",
            "type":"Manufacturing & Wholesale Goods"
        }
    ],
    "sg:phone":"+1 407 886 5553",
    "sg:postcode":"32712",
    "sg:province":"FL",
    "sg:tags":[
        "growing",
        "stock"
    ],
    "wof:name":"Frank Boudreau Nursery",
    "wof:placetype":"venue"
},
  "geometry": {"coordinates":[-81.550411,28.750177],"type":"Point"}
}