{
  "type": "Feature",
  "properties": {
    "addr:full":"5085 Pacific Ave Weeki Wachee FL 34607",
    "addr:housenumber":"5085",
    "addr:postcode":"34607",
    "addr:street":"Pacific Ave",
    "iso:country":"US",
    "sg:address":"5085 Pacific Ave",
    "sg:city":"Weeki Wachee",
    "sg:classifiers":[
        {
            "category":"Building & Trades",
            "subcategory":"Landscaping Services",
            "type":"Services"
        }
    ],
    "sg:phone":"+1 352 596 8318",
    "sg:postcode":"34607",
    "sg:province":"FL",
    "sg:tags":[
        "landscape",
        "contractor"
    ],
    "wof:name":"Land Crafters",
    "wof:placetype":"venue"
},
  "geometry": {"coordinates":[-82.59041499999999,28.502539],"type":"Point"}
}