{
  "type": "Feature",
  "properties": {
    "iso:country":"US",
    "sg:address":"13900 SW 71st Ln",
    "sg:city":"Miami",
    "sg:classifiers":[
        {
            "category":"Building & Trades",
            "subcategory":"Construction",
            "type":"Services"
        }
    ],
    "sg:phone":"+1 305 888 5221",
    "sg:postcode":"33183",
    "sg:province":"FL",
    "sg:tags":[
        "general",
        "contractor"
    ],
    "wof:name":"BDC Construction Corp",
    "wof:placetype":"venue"
},
  "geometry": {"coordinates":[-80.419093,25.700244],"type":"Point"}
}