{
  "type": "Feature",
  "properties": {
    "iso:country":"US",
    "sg:address":"915 70th Dr E",
    "sg:city":"Sarasota",
    "sg:classifiers":[
        {
            "category":"Professional",
            "subcategory":"Business Services",
            "type":"Services"
        }
    ],
    "sg:phone":"+1 941 727 7680",
    "sg:postcode":"34243",
    "sg:province":"FL",
    "sg:tags":[
        "consultant",
        "coach"
    ],
    "wof:name":"Gerald Goche Consulting",
    "wof:placetype":"venue"
},
  "geometry": {"coordinates":[-82.553962,27.416126],"type":"Point"}
}