{
  "type": "Feature",
  "properties": {
    "iso:country":"US",
    "sg:address":"4 Commerce Dr Ste 4",
    "sg:city":"Destin",
    "sg:classifiers":[
        {
            "category":"Professional",
            "subcategory":"Advertising",
            "type":"Services"
        },
        {
            "category":"Manufacturing",
            "subcategory":"Signs",
            "type":"Manufacturing & Wholesale Goods"
        }
    ],
    "sg:phone":"+1 850 837 1159",
    "sg:postcode":"32541",
    "sg:province":"FL",
    "sg:tags":[
        "specialty"
    ],
    "wof:name":"Himes Signs Inc",
    "wof:placetype":"venue"
},
  "geometry": {"coordinates":[-86.50675200000001,30.39706],"type":"Point"}
}