{
  "type": "Feature",
  "properties": {
    "iso:country":"US",
    "sg:address":"12460 Chelsey Rd",
    "sg:city":"Brooksville",
    "sg:classifiers":[
        {
            "category":"Manufacturing",
            "subcategory":"Lumber",
            "type":"Manufacturing & Wholesale Goods"
        }
    ],
    "sg:phone":"+1 352 597 1505",
    "sg:postcode":"34613",
    "sg:province":"FL",
    "sg:tags":[
        "forestry"
    ],
    "wof:name":"Forestry Div of",
    "wof:placetype":"venue"
},
  "geometry": {"coordinates":[-82.515648,28.535231],"type":"Point"}
}