{
  "type": "Feature",
  "properties": {
    "iso:country":"US",
    "sg:address":"8278 NW 70th St",
    "sg:city":"Miami",
    "sg:classifiers":[
        {
            "category":"Manufacturing",
            "subcategory":"Chemicals & Compounds",
            "type":"Manufacturing & Wholesale Goods"
        }
    ],
    "sg:phone":"+1 305 594 9388",
    "sg:postcode":"33166",
    "sg:province":"FL",
    "sg:tags":[
        "inorganic",
        "industrial",
        "mfg"
    ],
    "wof:name":"Cuda Chemical Inc",
    "wof:placetype":"venue"
},
  "geometry": {"coordinates":[-80.33269799999999,25.837011],"type":"Point"}
}