{
  "type": "Feature",
  "properties": {
    "iso:country":"US",
    "sg:address":"3714 Evans Ave",
    "sg:city":"Fort Myers",
    "sg:classifiers":[
        {
            "category":"Health Services",
            "subcategory":"Clinic",
            "type":"Services"
        }
    ],
    "sg:phone":"+1 239 939 1811",
    "sg:postcode":"33901",
    "sg:province":"FL",
    "sg:tags":[
        "blood",
        "bank"
    ],
    "wof:name":"Floridas Blood Ctrs Fort Myers",
    "wof:placetype":"venue"
},
  "geometry": {"coordinates":[-81.859859,26.606106],"type":"Point"}
}