{
  "type": "Feature",
  "properties": {
    "iso:country":"US",
    "sg:address":"1759 W Broadway St",
    "sg:city":"Oviedo",
    "sg:classifiers":[
        {
            "category":"Real Estate",
            "subcategory":"Real Estate Services",
            "type":"Services"
        }
    ],
    "sg:phone":"+1 407 365 1040",
    "sg:postcode":"32765",
    "sg:province":"FL",
    "sg:tags":[
        "company",
        "abstract",
        "title"
    ],
    "wof:name":"Southern Title & Abstract Inc",
    "wof:placetype":"venue"
},
  "geometry": {"coordinates":[-81.224485,28.662715],"type":"Point"}
}