{
  "type": "Feature",
  "properties": {
    "iso:country":"US",
    "sg:address":"4007 Greystone Dr",
    "sg:city":"Clermont",
    "sg:classifiers":[
        {
            "category":"Professional",
            "subcategory":"Business Services",
            "type":"Services"
        }
    ],
    "sg:phone":"+1 352 243 9598",
    "sg:postcode":"34711",
    "sg:province":"FL",
    "sg:tags":[
        "holding"
    ],
    "wof:name":"Nojjen Holdings",
    "wof:placetype":"venue"
},
  "geometry": {"coordinates":[-81.730964,28.503128],"type":"Point"}
}