{
  "type": "Feature",
  "properties": {
    "iso:country":"US",
    "sg:address":"1631 Hurst Pl",
    "sg:city":"Jacksonville",
    "sg:classifiers":[
        {
            "category":"Government",
            "subcategory":"Office",
            "type":"Public Place"
        }
    ],
    "sg:phone":"+1 904 630 0318",
    "sg:postcode":"32209",
    "sg:province":"FL",
    "sg:tags":[
        "village"
    ],
    "wof:name":"Jacksonville Joe James Ctr",
    "wof:placetype":"venue"
},
  "geometry": {"coordinates":[-81.68304500000001,30.350928],"type":"Point"}
}