{
  "type": "Feature",
  "properties": {
    "addr:full":"187 Old Park Way Lake Mary FL 32746",
    "addr:housenumber":"187",
    "addr:postcode":"32746",
    "addr:street":"Old Park Way",
    "iso:country":"US",
    "sg:address":"187 Old Park Way",
    "sg:city":"Lake Mary",
    "sg:classifiers":[
        {
            "category":"Government",
            "subcategory":"Office",
            "type":"Public Place"
        }
    ],
    "sg:phone":"+1 407 322 0960",
    "sg:postcode":"32746",
    "sg:province":"FL",
    "sg:tags":[
        "computer",
        "space",
        "related",
        "man"
    ],
    "wof:name":"Internet Business Consultant",
    "wof:placetype":"venue"
},
  "geometry": {"coordinates":[-81.321022,28.753141],"type":"Point"}
}