{
  "type": "Feature",
  "properties": {
    "iso:country":"US",
    "sg:address":"12155 Metro Pkwy",
    "sg:city":"Fort Myers",
    "sg:classifiers":[
        {
            "category":"Professional",
            "subcategory":"Management & Consulting",
            "type":"Services"
        },
        {
            "category":"Insurance",
            "subcategory":"Insurance Agent",
            "type":"Services"
        }
    ],
    "sg:phone":"+1 239 561 3400",
    "sg:postcode":"33966",
    "sg:province":"FL",
    "sg:tags":[
        "consultant",
        "business"
    ],
    "sg:website":"www.gsiinsurance.com",
    "wof:name":"Great Scott Insurance Inc",
    "wof:placetype":"venue"
},
  "geometry": {"coordinates":[-81.852885,26.568136],"type":"Point"}
}