{
  "type": "Feature",
  "properties": {
    "addr:full":"618 Brockton Dr Kissimmee FL 34758",
    "addr:housenumber":"618",
    "addr:postcode":"34758",
    "addr:street":"Brockton Dr",
    "iso:country":"US",
    "sg:address":"618 Brockton Dr",
    "sg:city":"Kissimmee",
    "sg:classifiers":[
        {
            "category":"Professional",
            "subcategory":"Business Services",
            "type":"Services"
        }
    ],
    "sg:phone":"+1 407 252 8899",
    "sg:postcode":"34758",
    "sg:province":"FL",
    "sg:tags":[
        "auto",
        "parts",
        "sales"
    ],
    "wof:name":"Lxc Custom Rides LLC",
    "wof:placetype":"venue"
},
  "geometry": {"coordinates":[-81.50284000000001,28.162319],"type":"Point"}
}