{
  "type": "Feature",
  "properties": {
    "iso:country":"US",
    "sg:address":"9659 Westview Dr",
    "sg:city":"Coral Springs",
    "sg:classifiers":[
        {
            "category":"Personal",
            "subcategory":"Beauty Salon",
            "type":"Services"
        }
    ],
    "sg:phone":"+1 954 753 2345",
    "sg:postcode":"33076",
    "sg:province":"FL",
    "sg:tags":[
        "shop"
    ],
    "wof:name":"Supercuts",
    "wof:placetype":"venue"
},
  "geometry": {"coordinates":[-80.255151,26.297923],"type":"Point"}
}