{
  "type": "Feature",
  "properties": {
    "iso:country":"US",
    "sg:address":"3001 W 12th Ave",
    "sg:city":"Hialeah",
    "sg:classifiers":[
        {
            "category":"Insurance",
            "subcategory":"Insurance Agent",
            "type":"Services"
        }
    ],
    "sg:phone":"+1 305 557 5756",
    "sg:postcode":"33012",
    "sg:province":"FL",
    "wof:name":"Ocean Insurance Inc",
    "wof:placetype":"venue"
},
  "geometry": {"coordinates":[-80.306361,25.849802],"type":"Point"}
}