{
  "type": "Feature",
  "properties": {
    "addr:full":"2920 Lake Saxon Dr Land O Lakes FL 34639",
    "addr:housenumber":"2920",
    "addr:postcode":"34639",
    "addr:street":"Lake Saxon Dr",
    "iso:country":"US",
    "sg:address":"2920 Lake Saxon Dr",
    "sg:city":"Land O Lakes",
    "sg:classifiers":[
        {
            "category":"Home & Garden",
            "subcategory":"Building Materials",
            "type":"Retail Goods"
        }
    ],
    "sg:phone":"+1 813 996 3152",
    "sg:postcode":"34639",
    "sg:province":"FL",
    "sg:tags":[
        "installs",
        "overhead",
        "door"
    ],
    "wof:name":"Dunn Doors",
    "wof:placetype":"venue"
},
  "geometry": {"coordinates":[-82.44556,28.199566],"type":"Point"}
}