{
  "type": "Feature",
  "properties": {
    "iso:country":"US",
    "sg:address":"7010 SW 46th St",
    "sg:city":"Miami",
    "sg:classifiers":[
        {
            "category":"Wholesale",
            "subcategory":"Medical Equipment & Supplies",
            "type":"Manufacturing & Wholesale Goods"
        },
        {
            "category":"Health Services",
            "subcategory":"Clinic",
            "type":"Services"
        }
    ],
    "sg:phone":"+1 305 661 6989",
    "sg:postcode":"33155",
    "sg:province":"FL",
    "sg:tags":[
        "home",
        "physician",
        "surgeon",
        "care"
    ],
    "wof:name":"First Rate Medical Corp",
    "wof:placetype":"venue"
},
  "geometry": {"coordinates":[-80.308656,25.727901],"type":"Point"}
}