{
  "type": "Feature",
  "properties": {
    "addr:full":"1424 NE 31st Ct Pompano Beach FL 33064",
    "addr:housenumber":"1424",
    "addr:postcode":"33064",
    "addr:street":"Ne 31St Ct",
    "iso:country":"US",
    "sg:address":"1424 NE 31st Ct",
    "sg:city":"Pompano Beach",
    "sg:classifiers":[
        {
            "category":"Retail",
            "subcategory":"Auto Repair",
            "type":"Services"
        }
    ],
    "sg:phone":"+1 954 325 5259",
    "sg:postcode":"33064",
    "sg:province":"FL",
    "sg:tags":[
        "glass",
        "coating",
        "tinting"
    ],
    "wof:name":"Universal Tinting & Sound",
    "wof:placetype":"venue"
},
  "geometry": {"coordinates":[-80.10338,26.269613],"type":"Point"}
}