{
  "type": "Feature",
  "properties": {
    "addr:full":"15165 NW 77th Ave Hialeah FL 33014",
    "addr:housenumber":"15165",
    "addr:postcode":"33014",
    "addr:street":"Nw 77Th Ave",
    "iso:country":"US",
    "sg:address":"15165 NW 77th Ave",
    "sg:city":"Hialeah",
    "sg:classifiers":[
        {
            "category":"Real Estate",
            "subcategory":"Real Estate Agent",
            "type":"Services"
        }
    ],
    "sg:phone":"+1 786 313 0013",
    "sg:postcode":"33014",
    "sg:province":"FL",
    "wof:name":"JLA Property Consultants",
    "wof:placetype":"venue"
},
  "geometry": {"coordinates":[-80.324181,25.906705],"type":"Point"}
}