{
  "type": "Feature",
  "properties": {
    "iso:country":"US",
    "sg:address":"545 Nicklaus Cir",
    "sg:city":"Cocoa",
    "sg:classifiers":[
        {
            "category":"Building & Trades",
            "subcategory":"Construction",
            "type":"Services"
        }
    ],
    "sg:phone":"+1 321 433 0890",
    "sg:postcode":"32927",
    "sg:province":"FL",
    "sg:tags":[
        "excavation",
        "contractor"
    ],
    "wof:name":"C B T Excavation Inc",
    "wof:placetype":"venue"
},
  "geometry": {"coordinates":[-80.77289500000001,28.452443],"type":"Point"}
}