{
  "type": "Feature",
  "properties": {
    "iso:country":"US",
    "sg:address":"1701 NW 103rd St",
    "sg:city":"Miami",
    "sg:classifiers":[
        {
            "category":"Government",
            "subcategory":"Office",
            "type":"Public Place"
        }
    ],
    "sg:phone":"+1 305 795 2240",
    "sg:postcode":"33147",
    "sg:province":"FL",
    "sg:tags":[
        "village"
    ],
    "wof:name":"Miami Shores Motor Pool",
    "wof:placetype":"venue"
},
  "geometry": {"coordinates":[-80.22773599999999,25.868548],"type":"Point"}
}