{
  "type": "Feature",
  "properties": {
    "iso:country":"US",
    "sg:address":"372 State Road 436",
    "sg:city":"Casselberry",
    "sg:classifiers":[
        {
            "category":"Home & Garden",
            "subcategory":"Building Materials",
            "type":"Retail Goods"
        },
        {
            "category":"Building & Trades",
            "subcategory":"Construction",
            "type":"Services"
        },
        {
            "category":"Home & Garden",
            "subcategory":"Carpets & Floor Coverings",
            "type":"Retail Goods"
        }
    ],
    "sg:phone":"+1 407 767 5490",
    "sg:postcode":"32707",
    "sg:province":"FL",
    "sg:tags":[
        "hardwood",
        "tile-contractors",
        "rug",
        "improvement"
    ],
    "sg:website":"http://www.realpagessites.com/colortileorlando",
    "wof:name":"Color Tile-Carpets Plus",
    "wof:placetype":"venue"
},
  "geometry": {"coordinates":[-81.334782,28.656701],"type":"Point"}
}