{
  "type": "Feature",
  "properties": {
    "iso:country":"US",
    "sg:address":"16809 SW 100th Ave",
    "sg:city":"Miami",
    "sg:classifiers":[
        {
            "category":"Organizations",
            "subcategory":"Religious Organization",
            "type":"Services"
        }
    ],
    "sg:phone":"+1 305 255 4430",
    "sg:postcode":"33157",
    "sg:province":"FL",
    "sg:website":"www.eac-perrine.org",
    "wof:name":"Emmanuel Apostolic Church",
    "wof:placetype":"venue"
},
  "geometry": {"coordinates":[-80.353059,25.613151],"type":"Point"}
}