{
  "type": "Feature",
  "properties": {
    "iso:country":"US",
    "sg:address":"6118 Allen Ln",
    "sg:city":"Lakeland",
    "sg:classifiers":[
        {
            "category":"Building & Trades",
            "subcategory":"Construction",
            "type":"Services"
        }
    ],
    "sg:phone":"+1 863 647 2759",
    "sg:postcode":"33811",
    "sg:province":"FL",
    "sg:tags":[
        "concrete",
        "contractor"
    ],
    "wof:name":"Don Robinson Concrete Inc",
    "wof:placetype":"venue"
},
  "geometry": {"coordinates":[-82.036869,27.954475],"type":"Point"}
}