{
  "type": "Feature",
  "properties": {
    "addr:full":"10404 W Flagler St Miami FL 33174",
    "addr:housenumber":"10404",
    "addr:postcode":"33174",
    "addr:street":"W Flagler St",
    "iso:country":"US",
    "sg:address":"10404 W Flagler St",
    "sg:city":"Miami",
    "sg:classifiers":[
        {
            "category":"Restaurant",
            "type":"Food & Drink"
        }
    ],
    "sg:phone":"+1 305 221 7001",
    "sg:postcode":"33174",
    "sg:province":"FL",
    "sg:tags":[
        "american",
        "latin"
    ],
    "wof:name":"Carne Asada Tortilleria Nicas",
    "wof:placetype":"venue"
},
  "geometry": {"coordinates":[-80.365154,25.768102],"type":"Point"}
}