{
  "type": "Feature",
  "properties": {
    "addr:full":"137 W Michigan Ave Deland FL 32720",
    "addr:housenumber":"137",
    "addr:postcode":"32720",
    "addr:street":"W Michigan Ave",
    "iso:country":"US",
    "sg:address":"137 W Michigan Ave",
    "sg:city":"Deland",
    "sg:classifiers":[
        {
            "category":"Museum",
            "type":"Entertainment"
        }
    ],
    "sg:phone":"+1 386 740 6813",
    "sg:postcode":"32720",
    "sg:province":"FL",
    "sg:tags":[
        "society",
        "historical"
    ],
    "wof:name":"West Volusia Historical Society",
    "wof:placetype":"venue"
},
  "geometry": {"coordinates":[-81.304199,29.0334],"type":"Point"}
}