{
  "type": "Feature",
  "properties": {
    "iso:country":"US",
    "sg:address":"320 N Cornish Pt",
    "sg:city":"Lecanto",
    "sg:classifiers":[
        {
            "category":"Building & Trades",
            "subcategory":"Landscaping Services",
            "type":"Services"
        }
    ],
    "sg:phone":"+1 352 220 9007",
    "sg:postcode":"34461",
    "sg:province":"FL",
    "sg:tags":[
        "lawn",
        "maintenance"
    ],
    "wof:name":"M & M Lawn Care",
    "wof:placetype":"venue"
},
  "geometry": {"coordinates":[-82.42270600000001,28.869761],"type":"Point"}
}