{
  "type": "Feature",
  "properties": {
    "addr:full":"5515 Dozier Rd Greenwood FL 32443",
    "addr:housenumber":"5515",
    "addr:postcode":"32443",
    "addr:street":"Dozier Rd",
    "iso:country":"US",
    "sg:address":"5515 Dozier Rd",
    "sg:city":"Greenwood",
    "sg:classifiers":[
        {
            "category":"Health Services",
            "subcategory":"Nursing And Care Facility",
            "type":"Services"
        }
    ],
    "sg:phone":"+1 850 569 1064",
    "sg:postcode":"32443",
    "sg:province":"FL",
    "sg:tags":[
        "skilled"
    ],
    "wof:name":"Sisters At Cllway-Helton Manor",
    "wof:placetype":"venue"
},
  "geometry": {"coordinates":[-85.156935,30.913422],"type":"Point"}
}