{
  "type": "Feature",
  "properties": {
    "iso:country":"US",
    "sg:address":"3201 Cornell Ave",
    "sg:city":"Orlando",
    "sg:classifiers":[
        {
            "category":"Travel",
            "subcategory":"Travel Agent",
            "type":"Entertainment"
        }
    ],
    "sg:phone":"+1 407 894 9115",
    "sg:postcode":"32804",
    "sg:province":"FL",
    "sg:tags":[
        "agency"
    ],
    "wof:name":"Travel Agents International",
    "wof:placetype":"venue"
},
  "geometry": {"coordinates":[-81.37664100000001,28.58194],"type":"Point"}
}