{
  "type": "Feature",
  "properties": {
    "iso:country":"US",
    "sg:address":"4000 N State Rd 7",
    "sg:city":"Fort Lauderdale",
    "sg:classifiers":[
        {
            "category":"Education",
            "subcategory":"Vocational School",
            "type":"Public Place"
        }
    ],
    "sg:phone":"+1 954 731 8880",
    "sg:postcode":"33319",
    "sg:province":"FL",
    "wof:name":"Concord Career Colleges",
    "wof:placetype":"venue"
},
  "geometry": {"coordinates":[-80.203337,26.17424],"type":"Point"}
}