{
  "type": "Feature",
  "properties": {
    "addr:full":"1511 US Hwy 1 Sebastian FL 32958",
    "addr:housenumber":"1511",
    "addr:postcode":"32958",
    "addr:street":"Us Hwy 1",
    "iso:country":"US",
    "sg:address":"1511 US Hwy 1",
    "sg:city":"Sebastian",
    "sg:classifiers":[
        {
            "category":"Health Services",
            "subcategory":"Clinic",
            "type":"Services"
        }
    ],
    "sg:phone":"+1 772 228 9584",
    "sg:postcode":"32958",
    "sg:province":"FL",
    "sg:tags":[
        "home"
    ],
    "wof:name":"Community Home Health Svc",
    "wof:placetype":"venue"
},
  "geometry": {"coordinates":[-80.472863,27.821998],"type":"Point"}
}