{
  "type": "Feature",
  "properties": {
    "addr:full":"204 Burns Ln Winter Haven FL 33884",
    "addr:housenumber":"204",
    "addr:postcode":"33884",
    "addr:street":"Burns Ln",
    "iso:country":"US",
    "sg:address":"204 Burns Ln",
    "sg:city":"Winter Haven",
    "sg:classifiers":[
        {
            "category":"Personal",
            "subcategory":"Shoe Repair & Shine",
            "type":"Services"
        }
    ],
    "sg:phone":"+1 863 318 0304",
    "sg:postcode":"33884",
    "sg:province":"FL",
    "sg:tags":[
        "repairing",
        "parlor",
        "boot"
    ],
    "wof:name":"Bill's Shoe Repair & Leather",
    "wof:placetype":"venue"
},
  "geometry": {"coordinates":[-81.674993,28.022229],"type":"Point"}
}