{
  "type": "Feature",
  "properties": {
    "iso:country":"US",
    "sg:address":"1455 W Landstreet Rd",
    "sg:city":"Orlando",
    "sg:classifiers":[
        {
            "category":"Retail",
            "subcategory":"Auto Repair",
            "type":"Services"
        }
    ],
    "sg:phone":"+1 407 851 5000",
    "sg:postcode":"32809",
    "sg:province":"FL",
    "sg:tags":[
        "body"
    ],
    "wof:name":"Jose Calmona",
    "wof:placetype":"venue"
},
  "geometry": {"coordinates":[-81.397898,28.436111],"type":"Point"}
}