{
  "type": "Feature",
  "properties": {
    "iso:country":"US",
    "sg:address":"2124 SW 34th St",
    "sg:city":"Gainesville",
    "sg:classifiers":[
        {
            "category":"Restaurant",
            "type":"Food & Drink"
        }
    ],
    "sg:menulink":"http://www.allmenus.com/fl/gainesville/285344-jdoobies/menu/",
    "sg:phone":"+1 352 672 6111",
    "sg:postcode":"32608",
    "sg:province":"FL",
    "sg:tags":[
        "american"
    ],
    "wof:name":"Jdoobies",
    "wof:placetype":"venue"
},
  "geometry": {"coordinates":[-82.37266,29.633005],"type":"Point"}
}