{
  "type": "Feature",
  "properties": {
    "iso:country":"US",
    "sg:address":"6568 Superior Ave",
    "sg:city":"Sarasota",
    "sg:classifiers":[
        {
            "category":"Retail",
            "subcategory":"Repair Shop",
            "type":"Services"
        }
    ],
    "sg:phone":"+1 941 925 2447",
    "sg:postcode":"34231",
    "sg:province":"FL",
    "sg:tags":[
        "upholsterer"
    ],
    "wof:name":"Frank Beck Upholstery",
    "wof:placetype":"venue"
},
  "geometry": {"coordinates":[-82.515632,27.259764],"type":"Point"}
}