{
  "type": "Feature",
  "properties": {
    "addr:full":"604 Bayshore Dr Pensacola FL 32507",
    "addr:housenumber":"604",
    "addr:postcode":"32507",
    "addr:street":"Bayshore Dr",
    "iso:country":"US",
    "sg:address":"604 Bayshore Dr",
    "sg:city":"Pensacola",
    "sg:classifiers":[
        {
            "category":"Arts & Performance",
            "subcategory":"Theater",
            "type":"Entertainment"
        }
    ],
    "sg:phone":"+1 850 457 4979",
    "sg:postcode":"32507",
    "sg:province":"FL",
    "sg:tags":[
        "band",
        "orchestra"
    ],
    "sg:website":"www.backporchseafood.com",
    "wof:name":"Clark & Co",
    "wof:placetype":"venue"
},
  "geometry": {"coordinates":[-87.25233299999999,30.393217],"type":"Point"}
}