{
  "type": "Feature",
  "properties": {
    "iso:country":"US",
    "sg:address":"3032 E Commercial Blvd",
    "sg:city":"Fort Lauderdale",
    "sg:classifiers":[
        {
            "category":"Professional",
            "subcategory":"Lawyer & Legal Services",
            "type":"Services"
        }
    ],
    "sg:phone":"+1 954 922 0555",
    "sg:postcode":"33308",
    "sg:province":"FL",
    "sg:tags":[
        "attorney"
    ],
    "wof:name":"Michael W Castoro",
    "wof:placetype":"venue"
},
  "geometry": {"coordinates":[-80.10404,26.189729],"type":"Point"}
}