{
  "type": "Feature",
  "properties": {
    "iso:country":"US",
    "sg:address":"16253 SW 78th Ter",
    "sg:city":"Miami",
    "sg:classifiers":[
        {
            "category":"Wholesale",
            "subcategory":"Hardware",
            "type":"Manufacturing & Wholesale Goods"
        }
    ],
    "sg:phone":"+1 305 382 4575",
    "sg:postcode":"33193",
    "sg:province":"FL",
    "sg:tags":[
        "hardware-wholesale",
        "manufacturer"
    ],
    "wof:name":"Adolfo Alvarez Sales Broker",
    "wof:placetype":"venue"
},
  "geometry": {"coordinates":[-80.455724,25.693612],"type":"Point"}
}