{
  "type": "Feature",
  "properties": {
    "addr:full":"5 Indian Mound Dr Saint Augustine FL 32084",
    "addr:housenumber":"5",
    "addr:postcode":"32084",
    "addr:street":"Indian Mound Dr",
    "iso:country":"US",
    "sg:address":"5 Indian Mound Dr",
    "sg:city":"Saint Augustine",
    "sg:classifiers":[
        {
            "category":"Building & Trades",
            "subcategory":"Construction",
            "type":"Services"
        }
    ],
    "sg:phone":"+1 904 826 0857",
    "sg:postcode":"32084",
    "sg:province":"FL",
    "sg:tags":[
        "house"
    ],
    "wof:name":"R&D Development",
    "wof:placetype":"venue"
},
  "geometry": {"coordinates":[-81.314908,29.908966],"type":"Point"}
}