{
  "type": "Feature",
  "properties": {
    "iso:country":"US",
    "sg:address":"1160 Wall Ave",
    "sg:city":"Ormond Beach",
    "sg:classifiers":[
        {
            "category":"Building & Trades",
            "subcategory":"Construction",
            "type":"Services"
        }
    ],
    "sg:phone":"+1 386 672 5211",
    "sg:postcode":"32174",
    "sg:province":"FL",
    "sg:tags":[
        "contractor"
    ],
    "wof:name":"E & M of Volusia Inc",
    "wof:placetype":"venue"
},
  "geometry": {"coordinates":[-81.102728,29.318679],"type":"Point"}
}