{
  "type": "Feature",
  "properties": {
    "addr:full":"1125 Melville Ave Lakeland FL 33805",
    "addr:housenumber":"1125",
    "addr:postcode":"33805",
    "addr:street":"Melville Ave",
    "iso:country":"US",
    "sg:address":"1125 Melville Ave",
    "sg:city":"Lakeland",
    "sg:classifiers":[
        {
            "category":"Social Services",
            "subcategory":"Child Care",
            "type":"Services"
        }
    ],
    "sg:phone":"+1 863 688 6072",
    "sg:postcode":"33805",
    "sg:province":"FL",
    "wof:name":"Andrew Family Daycare",
    "wof:placetype":"venue"
},
  "geometry": {"coordinates":[-81.99979,28.058106],"type":"Point"}
}