{
  "type": "Feature",
  "properties": {
    "iso:country":"US",
    "sg:address":"18360 NE 30th Pl",
    "sg:city":"Miami",
    "sg:classifiers":[
        {
            "category":"Professional",
            "subcategory":"Management & Consulting",
            "type":"Services"
        }
    ],
    "sg:phone":"+1 305 936 0608",
    "sg:postcode":"33180",
    "sg:province":"FL",
    "sg:tags":[
        "business"
    ],
    "wof:name":"Real World Results Inc",
    "wof:placetype":"venue"
},
  "geometry": {"coordinates":[-80.140179,25.967651],"type":"Point"}
}