{
  "type": "Feature",
  "properties": {
    "iso:country":"US",
    "sg:address":"2012 6th Ave SW",
    "sg:city":"Largo",
    "sg:classifiers":[
        {
            "category":"Wholesale",
            "subcategory":"Machinery & Supplies",
            "type":"Manufacturing & Wholesale Goods"
        }
    ],
    "sg:phone":"+1 727 588 0468",
    "sg:postcode":"33770",
    "sg:province":"FL",
    "sg:tags":[
        "freezers-wholesale",
        "refrigeration",
        "refrigerator",
        "equipment-parts",
        "manufacturer"
    ],
    "wof:name":"3 Sons Refrigeration",
    "wof:placetype":"venue"
},
  "geometry": {"coordinates":[-82.80904099999999,27.912672],"type":"Point"}
}