{
  "type": "Feature",
  "properties": {
    "iso:country":"US",
    "sg:address":"49 Banyan Course",
    "sg:city":"Ocala",
    "sg:classifiers":[
        {
            "category":"Organizations",
            "subcategory":"Religious Organization",
            "type":"Services"
        }
    ],
    "sg:phone":"+1 352 624 0380",
    "sg:postcode":"34472",
    "sg:province":"FL",
    "sg:tags":[
        "synagogue"
    ],
    "wof:name":"Temple B'Nai Darom",
    "wof:placetype":"venue"
},
  "geometry": {"coordinates":[-82.051833,29.162747],"type":"Point"}
}