{
  "type": "Feature",
  "properties": {
    "iso:country":"US",
    "sg:address":"2981 S McCall Rd",
    "sg:city":"Englewood",
    "sg:classifiers":[
        {
            "category":"Autos & Motor Vehicles",
            "subcategory":"Fuel & Gas Station",
            "type":"Retail Goods"
        }
    ],
    "sg:phone":"+1 941 473 9139",
    "sg:postcode":"34224",
    "sg:province":"FL",
    "sg:tags":[
        "station",
        "gasoline"
    ],
    "wof:name":"Murphy Oil USA Inc",
    "wof:placetype":"venue"
},
  "geometry": {"coordinates":[-82.311071,26.934459],"type":"Point"}
}