{
  "type": "Feature",
  "properties": {
    "iso:country":"US",
    "sg:address":"519 Wilbur St",
    "sg:city":"Brandon",
    "sg:classifiers":[
        {
            "category":"Professional",
            "subcategory":"Business Services",
            "type":"Services"
        }
    ],
    "sg:phone":"+1 813 653 1243",
    "sg:postcode":"33511",
    "sg:province":"FL",
    "sg:tags":[
        "paging",
        "answering"
    ],
    "sg:website":"www.elitetas.com",
    "wof:name":"Elite Communications",
    "wof:placetype":"venue"
},
  "geometry": {"coordinates":[-82.27789900000001,27.936304],"type":"Point"}
}