{
  "type": "Feature",
  "properties": {
    "addr:full":"10405 Countryway Blvd Tampa FL 33626",
    "addr:housenumber":"10405",
    "addr:postcode":"33626",
    "addr:street":"Countryway Blvd",
    "iso:country":"US",
    "sg:address":"10405 Countryway Blvd",
    "sg:city":"Tampa",
    "sg:classifiers":[
        {
            "category":"Recreation",
            "type":"Entertainment"
        }
    ],
    "sg:phone":"+1 813 855 0662",
    "sg:postcode":"33626",
    "sg:province":"FL",
    "sg:tags":[
        "tennis",
        "instruction"
    ],
    "wof:name":"Westchase Swim & Tennis Ctr",
    "wof:placetype":"venue"
},
  "geometry": {"coordinates":[-82.627922,28.046262],"type":"Point"}
}