{
  "type": "Feature",
  "properties": {
    "addr:full":"6935 Little Rd New Port Richey FL 34655",
    "addr:housenumber":"6935",
    "addr:postcode":"34655",
    "addr:street":"Little Rd",
    "iso:country":"US",
    "sg:address":"6935 Little Rd",
    "sg:city":"New Port Richey",
    "sg:classifiers":[
        {
            "category":"Banks & Credit Unions",
            "subcategory":"Bank",
            "type":"Services"
        }
    ],
    "sg:phone":"+1 727 815 8918",
    "sg:postcode":"34655",
    "sg:province":"FL",
    "sg:tags":[
        "depository",
        "banking"
    ],
    "wof:name":"ACE Cash Express",
    "wof:placetype":"venue"
},
  "geometry": {"coordinates":[-82.674376,28.258298],"type":"Point"}
}