{
  "type": "Feature",
  "properties": {
    "iso:country":"US",
    "sg:address":"2508 Ranchside Ter",
    "sg:city":"New Port Richey",
    "sg:classifiers":[
        {
            "category":"Real Estate",
            "subcategory":"Real Estate Operator",
            "type":"Services"
        }
    ],
    "sg:phone":"+1 727 372 8087",
    "sg:postcode":"34655",
    "sg:province":"FL",
    "sg:tags":[
        "apartment"
    ],
    "wof:name":"Ranchside Apartments",
    "wof:placetype":"venue"
},
  "geometry": {"coordinates":[-82.700318,28.196646],"type":"Point"}
}