{
  "type": "Feature",
  "properties": {
    "iso:country":"US",
    "sg:address":"1315 2nd Ave N",
    "sg:city":"Jacksonville Bch",
    "sg:classifiers":[
        {
            "category":"Professional",
            "subcategory":"Management & Consulting",
            "type":"Services"
        }
    ],
    "sg:phone":"+1 904 246 2737",
    "sg:postcode":"32250",
    "sg:province":"FL",
    "sg:tags":[
        "party",
        "planning"
    ],
    "wof:name":"Jacksonville Beaches Women's",
    "wof:placetype":"venue"
},
  "geometry": {"coordinates":[-81.40559500000001,30.2898],"type":"Point"}
}