{
  "type": "Feature",
  "properties": {
    "iso:country":"US",
    "sg:address":"515 Albatross St",
    "sg:city":"Merritt Island",
    "sg:classifiers":[
        {
            "category":"Organizations",
            "subcategory":"Religious Organization",
            "type":"Services"
        }
    ],
    "sg:phone":"+1 321 452 8216",
    "sg:postcode":"32952",
    "sg:province":"FL",
    "wof:name":"Symbol of The Living God Inc",
    "wof:placetype":"venue"
},
  "geometry": {"coordinates":[-80.665533,28.366376],"type":"Point"}
}