{
  "type": "Feature",
  "properties": {
    "iso:country":"US",
    "sg:address":"18350 SE Lakeside Dr",
    "sg:city":"Jupiter",
    "sg:classifiers":[
        {
            "category":"Professional",
            "subcategory":"Business Services",
            "type":"Services"
        }
    ],
    "sg:phone":"+1 561 575 0009",
    "sg:postcode":"33469",
    "sg:province":"FL",
    "sg:tags":[
        "interior",
        "consultant",
        "design",
        "decorator"
    ],
    "wof:name":"C K Designs",
    "wof:placetype":"venue"
},
  "geometry": {"coordinates":[-80.111046,26.979596],"type":"Point"}
}