{
  "type": "Feature",
  "properties": {
    "iso:country":"US",
    "sg:address":"2622 Crawfordville Hwy",
    "sg:city":"Crawfordville",
    "sg:classifiers":[
        {
            "category":"Shopping",
            "type":"Retail Goods"
        }
    ],
    "sg:phone":"+1 850 926 7283",
    "sg:postcode":"32327",
    "sg:province":"FL",
    "sg:tags":[
        "merchandise"
    ],
    "wof:name":"Spa Shoppe",
    "wof:placetype":"venue"
},
  "geometry": {"coordinates":[-84.37139999999999,30.19364],"type":"Point"}
}