{
  "type": "Feature",
  "properties": {
    "addr:full":"2706 Sunshine Blvd Miramar FL 33023",
    "addr:housenumber":"2706",
    "addr:postcode":"33023",
    "addr:street":"Sunshine Blvd",
    "iso:country":"US",
    "sg:address":"2706 Sunshine Blvd",
    "sg:city":"Miramar",
    "sg:classifiers":[
        {
            "category":"Travel",
            "subcategory":"Travel Agent",
            "type":"Entertainment"
        }
    ],
    "sg:phone":"+1 954 894 0464",
    "sg:postcode":"33023",
    "sg:province":"FL",
    "sg:tags":[
        "agency",
        "bureau"
    ],
    "wof:name":"Destin To Travel",
    "wof:placetype":"venue"
},
  "geometry": {"coordinates":[-80.22869799999999,25.985949],"type":"Point"}
}