{
  "type": "Feature",
  "properties": {
    "iso:country":"US",
    "sg:address":"4811 Highway 90",
    "sg:city":"Milton",
    "sg:classifiers":[
        {
            "category":"Banks & Credit Unions",
            "subcategory":"Bank",
            "type":"Services"
        }
    ],
    "sg:phone":"+1 850 436 7800",
    "sg:postcode":"32571",
    "sg:province":"FL",
    "sg:tags":[
        "saving",
        "commercial"
    ],
    "sg:website":"http://www.bankofpensacola.com",
    "wof:name":"Bank Of Pensacola",
    "wof:placetype":"venue"
},
  "geometry": {"coordinates":[-87.123526,30.603379],"type":"Point"}
}