{
  "type": "Feature",
  "properties": {
    "iso:country":"US",
    "sg:address":"3521 SE 30th Ter",
    "sg:city":"Okeechobee",
    "sg:classifiers":[
        {
            "category":"Personal",
            "subcategory":"Nail Salon",
            "type":"Services"
        }
    ],
    "sg:phone":"+1 863 467 8700",
    "sg:postcode":"34974",
    "sg:province":"FL",
    "wof:name":"The Place Hale And Nails",
    "wof:placetype":"venue"
},
  "geometry": {"coordinates":[-80.797214,27.210872],"type":"Point"}
}