{
  "type": "Feature",
  "properties": {
    "iso:country":"US",
    "sg:address":"415 S Federal Hwy",
    "sg:city":"Lake Worth",
    "sg:classifiers":[
        {
            "category":"Health Services",
            "subcategory":"Doctor",
            "type":"Services"
        }
    ],
    "sg:phone":"+1 561 547 9330",
    "sg:postcode":"33460",
    "sg:province":"FL",
    "wof:name":"Tomas Pino DDS",
    "wof:placetype":"venue"
},
  "geometry": {"coordinates":[-80.052531,26.610002],"type":"Point"}
}