{
  "type": "Feature",
  "properties": {
    "iso:country":"US",
    "sg:address":"2510 Pga Blvd",
    "sg:city":"Palm Beach Gdns",
    "sg:classifiers":[
        {
            "category":"Utilities",
            "subcategory":"Mobile Phone",
            "type":"Services"
        }
    ],
    "sg:phone":"+1 561 622 4747",
    "sg:postcode":"33410",
    "sg:province":"FL",
    "sg:tags":[
        "telephone",
        "cellular"
    ],
    "wof:name":"Wireless USA of Florida Inc",
    "wof:placetype":"venue"
},
  "geometry": {"coordinates":[-80.074833,26.84465],"type":"Point"}
}