{
  "type": "Feature",
  "properties": {
    "iso:country":"US",
    "sg:address":"6811 US Hwy 1",
    "sg:city":"Port St Lucie",
    "sg:classifiers":[
        {
            "category":"Recreation",
            "type":"Entertainment"
        }
    ],
    "sg:phone":"+1 772 489 2330",
    "sg:postcode":"34982",
    "sg:province":"FL",
    "sg:tags":[
        "parlor",
        "billiard"
    ],
    "wof:name":"Breakers Billiards",
    "wof:placetype":"venue"
},
  "geometry": {"coordinates":[-80.32589,27.338359],"type":"Point"}
}