{
  "type": "Feature",
  "properties": {
    "iso:country":"US",
    "sg:address":"7275 NW 68th St",
    "sg:city":"Miami",
    "sg:classifiers":[
        {
            "category":"Shopping",
            "subcategory":"Stationery & Office Supplies",
            "type":"Retail Goods"
        }
    ],
    "sg:phone":"+1 305 863 7900",
    "sg:postcode":"33166",
    "sg:province":"FL",
    "sg:tags":[
        "home",
        "furniture"
    ],
    "wof:name":"O.G. Office Furniture & Design",
    "wof:placetype":"venue"
},
  "geometry": {"coordinates":[-80.316211,25.835269],"type":"Point"}
}