{
  "type": "Feature",
  "properties": {
    "iso:country":"US",
    "sg:address":"4507 9th St W",
    "sg:city":"Bradenton",
    "sg:classifiers":[
        {
            "category":"Building & Trades",
            "subcategory":"Construction",
            "type":"Services"
        }
    ],
    "sg:phone":"+1 941 741 8600",
    "sg:postcode":"34207",
    "sg:province":"FL",
    "sg:tags":[
        "enclosure",
        "pool",
        "swimming"
    ],
    "wof:name":"Baby Safe Pool Fence",
    "wof:placetype":"venue"
},
  "geometry": {"coordinates":[-82.57113699999999,27.458405],"type":"Point"}
}