{
  "type": "Feature",
  "properties": {
    "addr:full":"4534 W Village Dr Tampa FL 33624",
    "addr:housenumber":"4534",
    "addr:postcode":"33624",
    "addr:street":"W Village Dr",
    "iso:country":"US",
    "sg:address":"4534 W Village Dr",
    "sg:city":"Tampa",
    "sg:classifiers":[
        {
            "category":"Restaurant",
            "type":"Food & Drink"
        }
    ],
    "sg:phone":"+1 813 968 3324",
    "sg:postcode":"33624",
    "sg:province":"FL",
    "sg:tags":[
        "eating"
    ],
    "wof:name":"New York Bagel & Bean",
    "wof:placetype":"venue"
},
  "geometry": {"coordinates":[-82.521811,28.073151],"type":"Point"}
}