{
  "type": "Feature",
  "properties": {
    "addr:full":"7007 Sea Harbor Dr Orlando FL 32821",
    "addr:housenumber":"7007",
    "addr:postcode":"32821",
    "addr:street":"Sea Harbor Dr",
    "iso:country":"US",
    "sg:address":"7007 Sea Harbor Dr",
    "sg:city":"Orlando",
    "sg:classifiers":[
        {
            "category":"Manufacturing",
            "subcategory":"Retail Goods",
            "type":"Manufacturing & Wholesale Goods"
        }
    ],
    "sg:phone":"+1 407 352 9750",
    "sg:postcode":"32821",
    "sg:province":"FL",
    "sg:tags":[
        "manufacturer"
    ],
    "wof:name":"Pearl Factory",
    "wof:placetype":"venue"
},
  "geometry": {"coordinates":[-81.470412,28.406517],"type":"Point"}
}