{
  "type": "Feature",
  "properties": {
    "iso:country":"US",
    "sg:address":"9401 N Century Blvd",
    "sg:city":"Century",
    "sg:classifiers":[
        {
            "category":"Shopping",
            "subcategory":"Used Merchandise",
            "type":"Retail Goods"
        }
    ],
    "sg:phone":"+1 850 256 0858",
    "sg:postcode":"32535",
    "sg:province":"FL",
    "wof:name":"Hometown Consignment",
    "wof:placetype":"venue"
},
  "geometry": {"coordinates":[-87.259433,30.996212],"type":"Point"}
}