{
  "type": "Feature",
  "properties": {
    "addr:full":"11426 SW 86th Ln Miami FL 33173",
    "addr:housenumber":"11426",
    "addr:postcode":"33173",
    "addr:street":"Sw 86Th Ln",
    "iso:country":"US",
    "sg:address":"11426 SW 86th Ln",
    "sg:city":"Miami",
    "sg:classifiers":[
        {
            "category":"Autos & Motor Vehicles",
            "subcategory":"Boat Sales",
            "type":"Retail Goods"
        }
    ],
    "sg:phone":"+1 305 279 6011",
    "sg:postcode":"33173",
    "sg:province":"FL",
    "wof:name":"L & H Marine Inc",
    "wof:placetype":"venue"
},
  "geometry": {"coordinates":[-80.37849900000001,25.687838],"type":"Point"}
}