{
  "type": "Feature",
  "properties": {
    "iso:country":"US",
    "sg:address":"18751 NW 5th St",
    "sg:city":"Hollywood",
    "sg:classifiers":[
        {
            "category":"Building & Trades",
            "subcategory":"Electrical",
            "type":"Services"
        }
    ],
    "sg:phone":"+1 954 432 2813",
    "sg:postcode":"33029",
    "sg:province":"FL",
    "sg:tags":[
        "general",
        "electrical",
        "contractor"
    ],
    "wof:name":"Lexi Group Inc",
    "wof:placetype":"venue"
},
  "geometry": {"coordinates":[-80.399484,26.011677],"type":"Point"}
}