{
  "type": "Feature",
  "properties": {
    "addr:full":"585 Technology Park Ste 100 Lake Mary FL 32746",
    "addr:housenumber":"585",
    "addr:postcode":"32746",
    "addr:street":"Technology Park Ste 100;Mary",
    "iso:country":"US",
    "sg:address":"585 Technology Park Ste 100",
    "sg:city":"Lake Mary",
    "sg:classifiers":[
        {
            "category":"Building & Trades",
            "subcategory":"Construction",
            "type":"Services"
        }
    ],
    "sg:phone":"+1 407 829 2257",
    "sg:postcode":"32746",
    "sg:province":"FL",
    "sg:tags":[
        "contractor"
    ],
    "wof:name":"Collage Companies the",
    "wof:placetype":"venue"
},
  "geometry": {"coordinates":[-81.360603,28.7355],"type":"Point"}
}