{
  "type": "Feature",
  "properties": {
    "iso:country":"US",
    "sg:address":"851 Bayway Blvd",
    "sg:city":"Clearwater",
    "sg:classifiers":[
        {
            "category":"Real Estate",
            "subcategory":"Real Estate Agent",
            "type":"Services"
        },
        {
            "category":"Real Estate",
            "subcategory":"Real Estate Operator",
            "type":"Services"
        }
    ],
    "sg:phone":"+1 727 441 8212",
    "sg:postcode":"33767",
    "sg:province":"FL",
    "sg:tags":[
        "condominium",
        "association"
    ],
    "wof:name":"Clearwater Point Seven Inc",
    "wof:placetype":"venue"
},
  "geometry": {"coordinates":[-82.820454,27.967042],"type":"Point"}
}