{
  "type": "Feature",
  "properties": {
    "iso:country":"US",
    "sg:address":"2643 Candler Dr",
    "sg:city":"Deltona",
    "sg:classifiers":[
        {
            "category":"Building & Trades",
            "subcategory":"Landscaping Services",
            "type":"Services"
        }
    ],
    "sg:phone":"+1 386 789 0250",
    "sg:postcode":"32725",
    "sg:province":"FL",
    "sg:tags":[
        "equipment",
        "industrial"
    ],
    "wof:name":"Ingram Pressure Clg & Lawn Svc",
    "wof:placetype":"venue"
},
  "geometry": {"coordinates":[-81.21957,28.936724],"type":"Point"}
}