{
  "type": "Feature",
  "properties": {
    "iso:country":"US",
    "sg:address":"2111 63rd Ave E",
    "sg:city":"Bradenton",
    "sg:classifiers":[
        {
            "category":"Manufacturing",
            "subcategory":"Printing",
            "type":"Manufacturing & Wholesale Goods"
        }
    ],
    "sg:phone":"+1 941 753 6688",
    "sg:postcode":"34203",
    "sg:province":"FL",
    "sg:tags":[
        "commercial",
        "offset"
    ],
    "sg:website":"www.proprintenterprises.com",
    "wof:name":"Pro Print Enterprises Inc",
    "wof:placetype":"venue"
},
  "geometry": {"coordinates":[-82.53726,27.429285],"type":"Point"}
}