{
  "type": "Feature",
  "properties": {
    "iso:country":"US",
    "sg:address":"1260 Deer Run Ln",
    "sg:city":"Naples",
    "sg:classifiers":[
        {
            "category":"Wholesale",
            "subcategory":"Plants",
            "type":"Manufacturing & Wholesale Goods"
        },
        {
            "category":"Home & Garden",
            "subcategory":"Garden Supply",
            "type":"Retail Goods"
        }
    ],
    "sg:phone":"+1 239 455 3111",
    "sg:postcode":"34120",
    "sg:province":"FL",
    "sg:tags":[
        "interior",
        "potted",
        "nursery",
        "center",
        "stock"
    ],
    "wof:name":"A Tropical Affair",
    "wof:placetype":"venue"
},
  "geometry": {"coordinates":[-81.63213,26.26382],"type":"Point"}
}