{
  "type": "Feature",
  "properties": {
    "iso:country":"US",
    "sg:address":"11964 SE 70th Avenue Rd",
    "sg:city":"Belleview",
    "sg:classifiers":[
        {
            "category":"Building & Trades",
            "subcategory":"Landscaping Services",
            "type":"Services"
        }
    ],
    "sg:phone":"+1 352 347 2309",
    "sg:postcode":"34420",
    "sg:province":"FL",
    "sg:tags":[
        "lawn",
        "maintenance",
        "grounds"
    ],
    "wof:name":"Rodolfo's Lawn Care Svc",
    "wof:placetype":"venue"
},
  "geometry": {"coordinates":[-82.034392,29.048247],"type":"Point"}
}