{
  "type": "Feature",
  "properties": {
    "addr:full":"5225 Enclave Dr Oldsmar FL 34677",
    "addr:housenumber":"5225",
    "addr:postcode":"34677",
    "addr:street":"Enclave Dr",
    "iso:country":"US",
    "sg:address":"5225 Enclave Dr",
    "sg:city":"Oldsmar",
    "sg:classifiers":[
        {
            "category":"Health Services",
            "subcategory":"Doctor",
            "type":"Services"
        }
    ],
    "sg:phone":"+1 727 861 7043",
    "sg:postcode":"34677",
    "sg:province":"FL",
    "sg:tags":[
        "medical"
    ],
    "wof:name":"A S G Doctors",
    "wof:placetype":"venue"
},
  "geometry": {"coordinates":[-82.683789,28.075228],"type":"Point"}
}