{
  "type": "Feature",
  "properties": {
    "iso:country":"US",
    "sg:address":"1513 S Harbor City Blvd",
    "sg:city":"Melbourne",
    "sg:classifiers":[
        {
            "category":"Health Services",
            "subcategory":"Doctor",
            "type":"Services"
        },
        {
            "category":"Health Services",
            "subcategory":"Health Practitioner",
            "type":"Services"
        }
    ],
    "sg:phone":"+1 321 956 4155",
    "sg:postcode":"32901",
    "sg:province":"FL",
    "sg:tags":[
        "control",
        "physician",
        "management",
        "weight",
        "loss",
        "surgeons"
    ],
    "wof:name":"Transformations International",
    "wof:placetype":"venue"
},
  "geometry": {"coordinates":[-80.60549899999999,28.083059],"type":"Point"}
}