{
  "type": "Feature",
  "properties": {
    "iso:country":"US",
    "sg:address":"1415 Lake Whitney Dr",
    "sg:city":"Windermere",
    "sg:classifiers":[
        {
            "category":"Social Services",
            "type":"Services"
        },
        {
            "category":"Professional",
            "subcategory":"Employment Agencies",
            "type":"Services"
        }
    ],
    "sg:phone":"+1 407 258 8018",
    "sg:postcode":"34786",
    "sg:province":"FL",
    "sg:tags":[
        "workers'",
        "placement",
        "volunteer"
    ],
    "wof:name":"The Griffith Foundation Inc",
    "wof:placetype":"venue"
},
  "geometry": {"coordinates":[-81.549538,28.523537],"type":"Point"}
}