{
  "type": "Feature",
  "properties": {
    "iso:country":"US",
    "sg:address":"351 N Biscayne River Dr",
    "sg:city":"Miami",
    "sg:classifiers":[
        {
            "category":"Real Estate",
            "subcategory":"Real Estate Operator",
            "type":"Services"
        }
    ],
    "sg:phone":"+1 305 956 5760",
    "sg:postcode":"33169",
    "sg:province":"FL",
    "sg:tags":[
        "building",
        "nonresidential"
    ],
    "wof:name":"Labonte Properties Inc",
    "wof:placetype":"venue"
},
  "geometry": {"coordinates":[-80.209391,25.917564],"type":"Point"}
}