{
  "type": "Feature",
  "properties": {
    "iso:country":"US",
    "sg:address":"9715 SW 148th Ct",
    "sg:city":"Miami",
    "sg:classifiers":[
        {
            "category":"Autos & Motor Vehicles",
            "subcategory":"Auto Supplies",
            "type":"Retail Goods"
        }
    ],
    "sg:phone":"+1 305 386 5338",
    "sg:postcode":"33196",
    "sg:province":"FL",
    "sg:tags":[
        "automotive",
        "parts",
        "export"
    ],
    "wof:name":"Logica Trading Inc",
    "wof:placetype":"venue"
},
  "geometry": {"coordinates":[-80.435244,25.677099],"type":"Point"}
}