{
  "type": "Feature",
  "properties": {
    "addr:full":"7439 NW 57th St Pompano Beach FL 33067",
    "addr:housenumber":"7439",
    "addr:postcode":"33067",
    "addr:street":"Nw 57Th St",
    "iso:country":"US",
    "sg:address":"7439 NW 57th St",
    "sg:city":"Pompano Beach",
    "sg:classifiers":[
        {
            "category":"Organizations",
            "subcategory":"Religious Organization",
            "type":"Services"
        }
    ],
    "sg:phone":"+1 954 718 6949",
    "sg:postcode":"33067",
    "sg:province":"FL",
    "sg:tags":[
        "church"
    ],
    "wof:name":"Daybreak Assembly Inc",
    "wof:placetype":"venue"
},
  "geometry": {"coordinates":[-80.23280099999999,26.300307],"type":"Point"}
}