{
  "type": "Feature",
  "properties": {
    "iso:country":"US",
    "sg:address":"4161 Aldergate Pl",
    "sg:city":"Winter Springs",
    "sg:classifiers":[
        {
            "category":"Professional",
            "type":"Services"
        }
    ],
    "sg:phone":"+1 407 699 5991",
    "sg:postcode":"32708",
    "sg:province":"FL",
    "sg:tags":[
        "establishment"
    ],
    "wof:name":"Rate Facts",
    "wof:placetype":"venue"
},
  "geometry": {"coordinates":[-81.275791,28.643472],"type":"Point"}
}