{
  "type": "Feature",
  "properties": {
    "addr:full":"7203 Lake Worth Rd Wellington FL 33467",
    "addr:housenumber":"7203",
    "addr:postcode":"33467",
    "addr:street":"Lake Worth Rd",
    "iso:country":"US",
    "sg:address":"7203 Lake Worth Rd",
    "sg:city":"Wellington",
    "sg:classifiers":[
        {
            "category":"Shopping",
            "subcategory":"Clothing, Apparel, & Fashions",
            "type":"Retail Goods"
        }
    ],
    "sg:phone":"+1 561 965 4665",
    "sg:postcode":"33467",
    "sg:province":"FL",
    "sg:website":"www.anthonysfla.com",
    "wof:name":"Anthony's Inc",
    "wof:placetype":"venue"
},
  "geometry": {"coordinates":[-80.158312,26.617717],"type":"Point"}
}