{
  "type": "Feature",
  "properties": {
    "iso:country":"US",
    "sg:address":"609 W 8th St",
    "sg:city":"Lakeland",
    "sg:classifiers":[
        {
            "category":"Arts & Performance",
            "subcategory":"Theater",
            "type":"Entertainment"
        }
    ],
    "sg:phone":"+1 863 686 7518",
    "sg:postcode":"33805",
    "sg:province":"FL",
    "sg:tags":[
        "group"
    ],
    "wof:name":"Tianyvu B Flowers",
    "wof:placetype":"venue"
},
  "geometry": {"coordinates":[-81.961839,28.061011],"type":"Point"}
}