{
  "type": "Feature",
  "properties": {
    "addr:full":"1500 Concord Ter Fort Lauderdale FL 33323",
    "addr:housenumber":"1500",
    "addr:postcode":"33323",
    "addr:street":"Concord Ter",
    "iso:country":"US",
    "sg:address":"1500 Concord Ter",
    "sg:city":"Fort Lauderdale",
    "sg:classifiers":[
        {
            "category":"Retail",
            "subcategory":"Repair Shop",
            "type":"Services"
        },
        {
            "category":"Wholesale",
            "subcategory":"Electrical",
            "type":"Manufacturing & Wholesale Goods"
        }
    ],
    "sg:phone":"+1 954 851 8000",
    "sg:postcode":"33323",
    "sg:province":"FL",
    "sg:tags":[
        "communication",
        "exporter",
        "equipment"
    ],
    "wof:name":"Nortel Network Cala Inc",
    "wof:placetype":"venue"
},
  "geometry": {"coordinates":[-80.34111900000001,26.133974],"type":"Point"}
}