{
  "type": "Feature",
  "properties": {
    "addr:full":"1904 W Sam Allen Rd Plant City FL 33565",
    "addr:housenumber":"1904",
    "addr:postcode":"33565",
    "addr:street":"W Sam Allen Rd",
    "iso:country":"US",
    "sg:address":"1904 W Sam Allen Rd",
    "sg:city":"Plant City",
    "sg:classifiers":[
        {
            "category":"Wholesale",
            "subcategory":"Fruits & Vegetables",
            "type":"Manufacturing & Wholesale Goods"
        }
    ],
    "sg:phone":"+1 813 719 1938",
    "sg:postcode":"33565",
    "sg:province":"FL",
    "sg:tags":[
        "produce"
    ],
    "wof:name":"Severt Sales LLC",
    "wof:placetype":"venue"
},
  "geometry": {"coordinates":[-82.147434,28.047252],"type":"Point"}
}