{
  "type": "Feature",
  "properties": {
    "iso:country":"US",
    "sg:address":"938 N Victoria Park Rd",
    "sg:city":"Fort Lauderdale",
    "sg:classifiers":[
        {
            "category":"Professional",
            "subcategory":"Advertising",
            "type":"Services"
        }
    ],
    "sg:phone":"+1 954 523 6262",
    "sg:postcode":"33304",
    "sg:province":"FL",
    "sg:tags":[
        "medium",
        "agency",
        "buying"
    ],
    "wof:name":"Myers Myers & Adams Advg",
    "wof:placetype":"venue"
},
  "geometry": {"coordinates":[-80.122893,26.136681],"type":"Point"}
}