{
  "type": "Feature",
  "properties": {
    "iso:country":"US",
    "sg:address":"11499 Old Saint Augustine Rd",
    "sg:city":"Jacksonville",
    "sg:classifiers":[
        {
            "category":"Insurance",
            "subcategory":"Insurance Agent",
            "type":"Services"
        }
    ],
    "sg:phone":"+1 904 260 6611",
    "sg:postcode":"32258",
    "sg:province":"FL",
    "wof:name":"Scott Agency",
    "wof:placetype":"venue"
},
  "geometry": {"coordinates":[-81.600917,30.164695],"type":"Point"}
}