{
  "type": "Feature",
  "properties": {
    "iso:country":"US",
    "sg:address":"1250 S Walnut St",
    "sg:city":"Starke",
    "sg:classifiers":[
        {
            "category":"Restaurant",
            "type":"Food & Drink"
        }
    ],
    "sg:phone":"+1 904 368 8158",
    "sg:postcode":"32091",
    "sg:province":"FL",
    "sg:tags":[
        "barbecue"
    ],
    "wof:name":"Dick's Wings",
    "wof:placetype":"venue"
},
  "geometry": {"coordinates":[-82.116525,29.9326],"type":"Point"}
}