{
  "type": "Feature",
  "properties": {
    "iso:country":"US",
    "sg:address":"413 Washington Ave",
    "sg:city":"Miami Beach",
    "sg:classifiers":[
        {
            "category":"Professional",
            "type":"Services"
        }
    ],
    "sg:phone":"+1 305 673 5713",
    "sg:postcode":"33139",
    "sg:province":"FL",
    "sg:tags":[
        "establishment"
    ],
    "wof:name":"Posto 5",
    "wof:placetype":"venue"
},
  "geometry": {"coordinates":[-80.13409,25.774397],"type":"Point"}
}