{
  "type": "Feature",
  "properties": {
    "iso:country":"US",
    "sg:address":"2564 Bottomridge Dr",
    "sg:city":"Orange Park",
    "sg:classifiers":[
        {
            "category":"Professional",
            "subcategory":"Business Services",
            "type":"Services"
        }
    ],
    "sg:phone":"+1 904 272 2180",
    "sg:postcode":"32065",
    "sg:province":"FL",
    "sg:tags":[
        "telephone"
    ],
    "wof:name":"Destiny Telecom International",
    "wof:placetype":"venue"
},
  "geometry": {"coordinates":[-81.77418299999999,30.155401],"type":"Point"}
}