{
  "type": "Feature",
  "properties": {
    "addr:full":"4105 Glen Rd Lakeland FL 33810",
    "addr:housenumber":"4105",
    "addr:postcode":"33810",
    "addr:street":"Glen Rd",
    "iso:country":"US",
    "sg:address":"4105 Glen Rd",
    "sg:city":"Lakeland",
    "sg:classifiers":[
        {
            "category":"Social Services",
            "subcategory":"Child Care",
            "type":"Services"
        },
        {
            "category":"Education",
            "subcategory":"School",
            "type":"Public Place"
        }
    ],
    "sg:phone":"+1 863 858 1063",
    "sg:postcode":"33810",
    "sg:province":"FL",
    "sg:tags":[
        "day"
    ],
    "wof:name":"Bobbie's Busy Bee Day Care",
    "wof:placetype":"venue"
},
  "geometry": {"coordinates":[-82.030325,28.083005],"type":"Point"}
}