{
  "type": "Feature",
  "properties": {
    "iso:country":"US",
    "sg:address":"1531 Hammondville Rd",
    "sg:city":"Pompano Beach",
    "sg:classifiers":[
        {
            "category":"Personal",
            "subcategory":"Tattoo Parlor",
            "type":"Services"
        }
    ],
    "sg:phone":"+1 954 979 4424",
    "sg:postcode":"33069",
    "sg:province":"FL",
    "sg:tags":[
        "tattooing"
    ],
    "wof:name":"Alex Bombay Inner City Tattoo",
    "wof:placetype":"venue"
},
  "geometry": {"coordinates":[-80.144277,26.239074],"type":"Point"}
}