{
  "type": "Feature",
  "properties": {
    "iso:country":"US",
    "sg:address":"1120 E Rose St",
    "sg:city":"Lakeland",
    "sg:classifiers":[
        {
            "category":"Home & Garden",
            "subcategory":"Hardware",
            "type":"Retail Goods"
        },
        {
            "category":"Wholesale",
            "subcategory":"Electrical",
            "type":"Manufacturing & Wholesale Goods"
        }
    ],
    "sg:phone":"+1 863 686 2171",
    "sg:postcode":"33801",
    "sg:province":"FL",
    "wof:name":"Hardy's Servistar Hardware",
    "wof:placetype":"venue"
},
  "geometry": {"coordinates":[-81.94319299999999,28.045446],"type":"Point"}
}