{
  "type": "Feature",
  "properties": {
    "iso:country":"US",
    "sg:address":"720 N 15th St",
    "sg:city":"Immokalee",
    "sg:classifiers":[
        {
            "category":"Shopping",
            "subcategory":"Florist",
            "type":"Retail Goods"
        }
    ],
    "sg:phone":"+1 239 657 5102",
    "sg:postcode":"34142",
    "sg:province":"FL",
    "wof:name":"B Hive Flowers & Gifts Inc",
    "wof:placetype":"venue"
},
  "geometry": {"coordinates":[-81.433678,26.429168],"type":"Point"}
}