{
  "type": "Feature",
  "properties": {
    "addr:full":"505 S State Road 19 Palatka FL 32177",
    "addr:housenumber":"505",
    "addr:postcode":"32177",
    "addr:street":"S State Road 19",
    "iso:country":"US",
    "sg:address":"505 S State Road 19",
    "sg:city":"Palatka",
    "sg:classifiers":[
        {
            "category":"Restaurant",
            "type":"Food & Drink"
        }
    ],
    "sg:menulink":"http://www.allmenus.com/fl/palatka/156378-krystal-burgers/menu/",
    "sg:phone":"+1 904 328 9020",
    "sg:postcode":"32177",
    "sg:province":"FL",
    "sg:tags":[
        "burger",
        "chicken",
        "american"
    ],
    "wof:name":"Krystal Burgers",
    "wof:placetype":"venue"
},
  "geometry": {"coordinates":[-81.67549200000001,29.643197],"type":"Point"}
}