{
  "type": "Feature",
  "properties": {
    "iso:country":"US",
    "sg:address":"8126 W Broward Blvd",
    "sg:city":"Plantation",
    "sg:classifiers":[
        {
            "category":"Shopping",
            "subcategory":"Clothing, Apparel, & Fashions",
            "type":"Retail Goods"
        }
    ],
    "sg:phone":"+1 954 693 4863",
    "sg:postcode":"33317",
    "sg:province":"FL",
    "wof:name":"Brasil USA Fashion",
    "wof:placetype":"venue"
},
  "geometry": {"coordinates":[-80.25854099999999,26.120673],"type":"Point"}
}