{
  "type": "Feature",
  "properties": {
    "iso:country":"US",
    "sg:address":"4865 W Gulf To Lake Hwy",
    "sg:city":"Lecanto",
    "sg:classifiers":[
        {
            "category":"Retail",
            "subcategory":"Animal Services",
            "type":"Services"
        }
    ],
    "sg:phone":"+1 352 746 3302",
    "sg:postcode":"34461",
    "sg:province":"FL",
    "sg:tags":[
        "grooming",
        "dog",
        "kennel"
    ],
    "wof:name":"J D P Kennel",
    "wof:placetype":"venue"
},
  "geometry": {"coordinates":[-82.516938,28.87257],"type":"Point"}
}