{
  "type": "Feature",
  "properties": {
    "iso:country":"US",
    "sg:address":"3201 SW 88th St",
    "sg:city":"Ocala",
    "sg:classifiers":[
        {
            "category":"Building & Trades",
            "subcategory":"Landscaping Services",
            "type":"Services"
        }
    ],
    "sg:phone":"+1 352 572 9139",
    "sg:postcode":"34476",
    "sg:province":"FL",
    "sg:tags":[
        "tree"
    ],
    "wof:name":"Donald Pellegrino Tree Svc.",
    "wof:placetype":"venue"
},
  "geometry": {"coordinates":[-82.17621,29.094545],"type":"Point"}
}