{
  "type": "Feature",
  "properties": {
    "iso:country":"US",
    "sg:address":"324 Covent Gardens Pl",
    "sg:city":"Deltona",
    "sg:classifiers":[
        {
            "category":"Building & Trades",
            "subcategory":"Cleaning & Sanitation",
            "type":"Services"
        }
    ],
    "sg:phone":"+1 321 508 1785",
    "sg:postcode":"32725",
    "sg:province":"FL",
    "sg:tags":[
        "cleaning-industrial",
        "contractor"
    ],
    "wof:name":"F B And I Janitorial Cleaning",
    "wof:placetype":"venue"
},
  "geometry": {"coordinates":[-81.258038,28.87241],"type":"Point"}
}