{
  "type": "Feature",
  "properties": {
    "iso:country":"US",
    "sg:address":"13309 SW 59th Ter",
    "sg:city":"Miami",
    "sg:classifiers":[
        {
            "category":"Communications",
            "subcategory":"Film & Video Production",
            "type":"Services"
        }
    ],
    "sg:phone":"+1 305 496 3771",
    "sg:postcode":"33183",
    "sg:province":"FL",
    "sg:tags":[
        "tv",
        "services-commercial",
        "companies-film",
        "radio"
    ],
    "wof:name":"Army Of Monks Productions",
    "wof:placetype":"venue"
},
  "geometry": {"coordinates":[-80.40923600000001,25.712993],"type":"Point"}
}