{
  "type": "Feature",
  "properties": {
    "iso:country":"US",
    "sg:address":"5757 SW 8th St",
    "sg:city":"West Miami",
    "sg:classifiers":[
        {
            "category":"Building & Trades",
            "subcategory":"Locksmith",
            "type":"Services"
        }
    ],
    "sg:phone":"+1 305 428 9091",
    "sg:postcode":"33144",
    "sg:province":"FL",
    "sg:tags":[
        "key"
    ],
    "wof:name":"24 7 Emergency Locksmith",
    "wof:placetype":"venue"
},
  "geometry": {"coordinates":[-80.289044,25.763667],"type":"Point"}
}