{
  "type": "Feature",
  "properties": {
    "iso:country":"US",
    "sg:address":"50 Black Bear Ln",
    "sg:city":"Palm Coast",
    "sg:classifiers":[
        {
            "category":"Freight",
            "type":"Transportation"
        }
    ],
    "sg:phone":"+1 386 447 3522",
    "sg:postcode":"32137",
    "sg:province":"FL",
    "sg:tags":[
        "operator",
        "local",
        "trucking"
    ],
    "wof:name":"Raymond S Hess Trucking",
    "wof:placetype":"venue"
},
  "geometry": {"coordinates":[-81.203113,29.545006],"type":"Point"}
}