{
  "type": "Feature",
  "properties": {
    "addr:full":"3475 NW 41st St Miami FL 33142",
    "addr:housenumber":"3475",
    "addr:postcode":"33142",
    "addr:street":"Nw 41St St",
    "iso:country":"US",
    "sg:address":"3475 NW 41st St",
    "sg:city":"Miami",
    "sg:classifiers":[
        {
            "category":"Manufacturing",
            "subcategory":"Apparel",
            "type":"Manufacturing & Wholesale Goods"
        },
        {
            "category":"Professional",
            "subcategory":"Business Services",
            "type":"Services"
        }
    ],
    "sg:phone":"+1 305 635 2588",
    "sg:postcode":"33142",
    "sg:province":"FL",
    "sg:tags":[
        "outerwear",
        "mfg"
    ],
    "wof:name":"Accurate Cutting Svc Inc",
    "wof:placetype":"venue"
},
  "geometry": {"coordinates":[-80.251912,25.812519],"type":"Point"}
}