{
  "type": "Feature",
  "properties": {
    "iso:country":"US",
    "sg:address":"14924 Oldham Dr",
    "sg:city":"Orlando",
    "sg:classifiers":[
        {
            "category":"Professional",
            "subcategory":"Business Services",
            "type":"Services"
        }
    ],
    "sg:phone":"+1 407 277 8239",
    "sg:postcode":"32826",
    "sg:province":"FL",
    "wof:name":"S2technical Sales Inc",
    "wof:placetype":"venue"
},
  "geometry": {"coordinates":[-81.17516000000001,28.60602],"type":"Point"}
}