{
  "type": "Feature",
  "properties": {
    "iso:country":"US",
    "sg:address":"6224 NW 180th Ter",
    "sg:city":"Hialeah",
    "sg:classifiers":[
        {
            "category":"Health Services",
            "subcategory":"Clinic",
            "type":"Services"
        }
    ],
    "sg:phone":"+1 305 822 6290",
    "sg:postcode":"33015",
    "sg:province":"FL",
    "wof:name":"Albertos Medical Equipment Co",
    "wof:placetype":"venue"
},
  "geometry": {"coordinates":[-80.30322200000001,25.937699],"type":"Point"}
}