{
  "type": "Feature",
  "properties": {
    "iso:country":"US",
    "sg:address":"5528 NE 4th Ct Suite 6b",
    "sg:city":"Miami",
    "sg:classifiers":[
        {
            "category":"Shopping",
            "subcategory":"Jewelry",
            "type":"Retail Goods"
        },
        {
            "category":"Shopping",
            "subcategory":"Used Merchandise",
            "type":"Retail Goods"
        }
    ],
    "sg:phone":"+1 305 989 9995",
    "sg:postcode":"33137",
    "sg:province":"FL",
    "sg:tags":[
        "vintage",
        "consignment"
    ],
    "sg:website":"www.the55thstreetstation.com",
    "wof:name":"Night Owl Vintage Accessories",
    "wof:placetype":"venue"
},
  "geometry": {"coordinates":[-80.187078,25.827038],"type":"Point"}
}