{
  "type": "Feature",
  "properties": {
    "iso:country":"US",
    "sg:address":"11345 Tamiami Trl",
    "sg:city":"Naples",
    "sg:classifiers":[
        {
            "category":"Retail",
            "subcategory":"Car Wash",
            "type":"Services"
        }
    ],
    "sg:phone":"+1 239 774 5427",
    "sg:postcode":"34113",
    "sg:province":"FL",
    "sg:tags":[
        "polishing",
        "washing"
    ],
    "wof:name":"Palm Car Wash",
    "wof:placetype":"venue"
},
  "geometry": {"coordinates":[-81.725266,26.082301],"type":"Point"}
}