{
  "type": "Feature",
  "properties": {
    "iso:country":"US",
    "sg:address":"8932 Whitemarsh Ave",
    "sg:city":"Sarasota",
    "sg:classifiers":[
        {
            "category":"Insurance",
            "subcategory":"Hazard Insurance",
            "type":"Services"
        }
    ],
    "sg:phone":"+1 941 918 9226",
    "sg:postcode":"34238",
    "sg:province":"FL",
    "wof:name":"Ray Rogers",
    "wof:placetype":"venue"
},
  "geometry": {"coordinates":[-82.47296,27.218649],"type":"Point"}
}