{
  "type": "Feature",
  "properties": {
    "addr:full":"724 Beach St Satellite Beach FL 32937",
    "addr:housenumber":"724",
    "addr:postcode":"32937",
    "addr:street":"Beach St",
    "iso:country":"US",
    "sg:address":"724 Beach St",
    "sg:city":"Satellite Beach",
    "sg:classifiers":[
        {
            "category":"Wholesale",
            "subcategory":"Electrical",
            "type":"Manufacturing & Wholesale Goods"
        }
    ],
    "sg:phone":"+1 321 254 0773",
    "sg:postcode":"32937",
    "sg:province":"FL",
    "sg:tags":[
        "electric",
        "motor"
    ],
    "wof:name":"Apple Motors Inc",
    "wof:placetype":"venue"
},
  "geometry": {"coordinates":[-80.58617700000001,28.159799],"type":"Point"}
}