{
  "type": "Feature",
  "properties": {
    "iso:country":"US",
    "sg:address":"19128 Shoreward Ct",
    "sg:city":"Jupiter",
    "sg:classifiers":[
        {
            "category":"Building & Trades",
            "subcategory":"Electrical",
            "type":"Services"
        }
    ],
    "sg:phone":"+1 561 741 0587",
    "sg:postcode":"33458",
    "sg:province":"FL",
    "sg:tags":[
        "electrical",
        "contractor"
    ],
    "wof:name":"Seaside Electric",
    "wof:placetype":"venue"
},
  "geometry": {"coordinates":[-80.13333900000001,26.957741],"type":"Point"}
}