{
  "type": "Feature",
  "properties": {
    "iso:country":"US",
    "sg:address":"7576 Cedar Hurst Ct",
    "sg:city":"Lake Worth",
    "sg:classifiers":[
        {
            "category":"Building & Trades",
            "subcategory":"Landscaping Services",
            "type":"Services"
        }
    ],
    "sg:phone":"+1 561 357 9024",
    "sg:postcode":"33467",
    "sg:province":"FL",
    "sg:tags":[
        "lawn",
        "maintenance",
        "grounds"
    ],
    "wof:name":"Palm Beach Lawn Maintenance",
    "wof:placetype":"venue"
},
  "geometry": {"coordinates":[-80.165194,26.560096],"type":"Point"}
}