{
  "type": "Feature",
  "properties": {
    "iso:country":"US",
    "sg:address":"1530 W Cleveland St",
    "sg:city":"Tampa",
    "sg:classifiers":[
        {
            "category":"Real Estate",
            "subcategory":"Developer",
            "type":"Services"
        }
    ],
    "sg:phone":"+1 813 254 6911",
    "sg:postcode":"33606",
    "sg:province":"FL",
    "wof:name":"Tepee Ventures Inc",
    "wof:placetype":"venue"
},
  "geometry": {"coordinates":[-82.475498,27.943158],"type":"Point"}
}