{
  "type": "Feature",
  "properties": {
    "addr:full":"501 E Cam Real Boca Raton FL 33432",
    "addr:housenumber":"501",
    "addr:postcode":"33432",
    "addr:street":"E Cam Real",
    "iso:country":"US",
    "sg:address":"501 E Cam Real",
    "sg:city":"Boca Raton",
    "sg:classifiers":[
        {
            "category":"Shopping",
            "type":"Retail Goods"
        }
    ],
    "sg:phone":"+1 561 394 7070",
    "sg:postcode":"33432",
    "sg:province":"FL",
    "sg:tags":[
        "art",
        "gallery",
        "dealer"
    ],
    "wof:name":"Curzon Gallery",
    "wof:placetype":"venue"
},
  "geometry": {"coordinates":[-80.07816099999999,26.339672],"type":"Point"}
}