{
  "type": "Feature",
  "properties": {
    "addr:full":"8039 Boca Rio Dr Boca Raton FL 33433",
    "addr:housenumber":"8039",
    "addr:postcode":"33433",
    "addr:street":"Boca Rio Dr",
    "iso:country":"US",
    "sg:address":"8039 Boca Rio Dr",
    "sg:city":"Boca Raton",
    "sg:classifiers":[
        {
            "category":"Building & Trades",
            "subcategory":"Construction",
            "type":"Services"
        }
    ],
    "sg:phone":"+1 772 260 6393",
    "sg:postcode":"33433",
    "sg:province":"FL",
    "sg:tags":[
        "contractor"
    ],
    "wof:name":"Saavedra Group",
    "wof:placetype":"venue"
},
  "geometry": {"coordinates":[-80.175263,26.341424],"type":"Point"}
}