{
  "type": "Feature",
  "properties": {
    "iso:country":"US",
    "sg:address":"3691 Seacrest Blvd",
    "sg:city":"Lantana",
    "sg:classifiers":[
        {
            "category":"Retail",
            "subcategory":"Funeral Services",
            "type":"Services"
        }
    ],
    "sg:phone":"+1 561 585 6444",
    "sg:postcode":"33462",
    "sg:province":"FL",
    "sg:tags":[
        "director",
        "cemetery"
    ],
    "wof:name":"Palm Beach Memorial Park",
    "wof:placetype":"venue"
},
  "geometry": {"coordinates":[-80.066497,26.565859],"type":"Point"}
}