{
  "type": "Feature",
  "properties": {
    "iso:country":"US",
    "sg:address":"1820 W 8th Ave",
    "sg:city":"Hialeah",
    "sg:classifiers":[
        {
            "category":"Shopping",
            "subcategory":"Clothing, Apparel, & Fashions",
            "type":"Retail Goods"
        },
        {
            "category":"Banks & Credit Unions",
            "subcategory":"Investment Brokerage",
            "type":"Services"
        },
        {
            "category":"Manufacturing",
            "subcategory":"Jewelry",
            "type":"Manufacturing & Wholesale Goods"
        },
        {
            "category":"Cinema",
            "subcategory":"Movie Rental",
            "type":"Entertainment"
        },
        {
            "category":"Personal",
            "subcategory":"Adult",
            "type":"Services"
        },
        {
            "category":"Shopping",
            "subcategory":"Adult",
            "type":"Retail Goods"
        },
        {
            "category":"Sports & Exercise",
            "subcategory":"Athletic Track",
            "type":"Entertainment"
        }
    ],
    "sg:phone":"+1 305 885 1100",
    "sg:postcode":"33010",
    "sg:province":"FL",
    "sg:tags":[
        "tape",
        "novelty",
        "sale",
        "dvds-rental",
        "discs-wholesale",
        "lingerie",
        "game",
        "apparel",
        "video",
        "bookstore",
        "women's",
        "store",
        "manufacturer"
    ],
    "sg:website":"www.bikini-shave.com",
    "wof:name":"Good Time Adult Store & Video",
    "wof:placetype":"venue"
},
  "geometry": {"coordinates":[-80.298024,25.83824],"type":"Point"}
}