{
  "type": "Feature",
  "properties": {
    "addr:full":"123 Miami Gardens Rd Hollywood FL 33023",
    "addr:housenumber":"123",
    "addr:postcode":"33023",
    "addr:street":"Miami Gardens Rd",
    "iso:country":"US",
    "sg:address":"123 Miami Gardens Rd",
    "sg:city":"Hollywood",
    "sg:classifiers":[
        {
            "category":"Retail",
            "subcategory":"Animal Services",
            "type":"Services"
        }
    ],
    "sg:phone":"+1 954 986 2365",
    "sg:postcode":"33023",
    "sg:province":"FL",
    "wof:name":"Abraxus School of Dog Training",
    "wof:placetype":"venue"
},
  "geometry": {"coordinates":[-80.198967,25.978519],"type":"Point"}
}