{
  "type": "Feature",
  "properties": {
    "addr:full":"939 N Magnolia Ave Ocala FL 34475",
    "addr:housenumber":"939",
    "addr:postcode":"34475",
    "addr:street":"N Magnolia Ave",
    "iso:country":"US",
    "sg:address":"939 N Magnolia Ave",
    "sg:city":"Ocala",
    "sg:classifiers":[
        {
            "category":"Professional",
            "subcategory":"Advertising",
            "type":"Services"
        }
    ],
    "sg:phone":"+1 352 351 4321",
    "sg:postcode":"34475",
    "sg:province":"FL",
    "sg:tags":[
        "counselor"
    ],
    "sg:website":"www.v12marketing.com",
    "wof:name":"V 12",
    "wof:placetype":"venue"
},
  "geometry": {"coordinates":[-82.136436,29.196543],"type":"Point"}
}