{
  "type": "Feature",
  "properties": {
    "iso:country":"US",
    "sg:address":"12701 N Florida Ave",
    "sg:city":"Tampa",
    "sg:classifiers":[
        {
            "category":"Social Services",
            "subcategory":"Child Care",
            "type":"Services"
        }
    ],
    "sg:phone":"+1 813 931 5397",
    "sg:postcode":"33612",
    "sg:province":"FL",
    "wof:name":"Tampa Early Childhood Ctr",
    "wof:placetype":"venue"
},
  "geometry": {"coordinates":[-82.45926799999999,28.062074],"type":"Point"}
}