{
  "type": "Feature",
  "properties": {
    "addr:full":"10036 University Blvd Orlando FL 32817",
    "addr:housenumber":"10036",
    "addr:postcode":"32817",
    "addr:street":"University Blvd",
    "iso:country":"US",
    "sg:address":"10036 University Blvd",
    "sg:city":"Orlando",
    "sg:classifiers":[
        {
            "category":"Sports & Exercise",
            "subcategory":"Gym",
            "type":"Entertainment"
        }
    ],
    "sg:phone":"+1 407 678 3200",
    "sg:postcode":"32817",
    "sg:province":"FL",
    "sg:tags":[
        "fitness",
        "physical",
        "facility"
    ],
    "wof:name":"Curves For Women",
    "wof:placetype":"venue"
},
  "geometry": {"coordinates":[-81.24248299999999,28.597406],"type":"Point"}
}