{
  "type": "Feature",
  "properties": {
    "iso:country":"US",
    "sg:address":"648 Helvenston St SE",
    "sg:city":"Live Oak",
    "sg:classifiers":[
        {
            "category":"Shopping",
            "type":"Retail Goods"
        }
    ],
    "sg:phone":"+1 386 362 3532",
    "sg:postcode":"32064",
    "sg:province":"FL",
    "sg:tags":[
        "merchandise",
        "animal"
    ],
    "wof:name":"Rianbow Bird Land Center",
    "wof:placetype":"venue"
},
  "geometry": {"coordinates":[-82.980071,30.288874],"type":"Point"}
}