{
  "type": "Feature",
  "properties": {
    "addr:full":"2200 S Andrews Ave Fort Lauderdale FL 33316",
    "addr:housenumber":"2200",
    "addr:postcode":"33316",
    "addr:street":"S Andrews Ave",
    "iso:country":"US",
    "sg:address":"2200 S Andrews Ave",
    "sg:city":"Fort Lauderdale",
    "sg:classifiers":[
        {
            "category":"Wholesale",
            "subcategory":"Sporting Goods",
            "type":"Manufacturing & Wholesale Goods"
        }
    ],
    "sg:phone":"+1 954 525 3379",
    "sg:postcode":"33316",
    "sg:province":"FL",
    "sg:tags":[
        "boat"
    ],
    "wof:name":"P F Brunger Export Company",
    "wof:placetype":"venue"
},
  "geometry": {"coordinates":[-80.14057,26.093721],"type":"Point"}
}