{
  "type": "Feature",
  "properties": {
    "addr:full":"4014 Gunn Hwy Tampa FL 33618",
    "addr:housenumber":"4014",
    "addr:postcode":"33618",
    "addr:street":"Gunn Hwy",
    "iso:country":"US",
    "sg:address":"4014 Gunn Hwy",
    "sg:city":"Tampa",
    "sg:classifiers":[
        {
            "category":"Banks & Credit Unions",
            "subcategory":"Bank",
            "type":"Services"
        }
    ],
    "sg:phone":"+1 813 936 0444",
    "sg:postcode":"33618",
    "sg:province":"FL",
    "sg:tags":[
        "loan",
        "real estate"
    ],
    "wof:name":"Dxs Mortgage",
    "wof:placetype":"venue"
},
  "geometry": {"coordinates":[-82.50879999999999,28.039661],"type":"Point"}
}