{
  "type": "Feature",
  "properties": {
    "iso:country":"US",
    "sg:address":"509 Derby Dr",
    "sg:city":"Altamonte Springs",
    "sg:classifiers":[
        {
            "category":"Building & Trades",
            "subcategory":"Construction",
            "type":"Services"
        }
    ],
    "sg:phone":"+1 407 834 9604",
    "sg:postcode":"32714",
    "sg:province":"FL",
    "sg:tags":[
        "nonresidential"
    ],
    "wof:name":"Peter G Madson Specifier",
    "wof:placetype":"venue"
},
  "geometry": {"coordinates":[-81.402997,28.663734],"type":"Point"}
}