{
  "type": "Feature",
  "properties": {
    "addr:full":"9841 State Rd 52 Hudson FL 34669",
    "addr:housenumber":"9841;52",
    "addr:postcode":"34669",
    "addr:street":"State Rd",
    "iso:country":"US",
    "sg:address":"9841 State Rd 52",
    "sg:city":"Hudson",
    "sg:classifiers":[
        {
            "category":"Building & Trades",
            "subcategory":"Cleaning & Sanitation",
            "type":"Services"
        }
    ],
    "sg:phone":"+1 727 819 2484",
    "sg:postcode":"34669",
    "sg:province":"FL",
    "sg:tags":[
        "butler",
        "maid"
    ],
    "wof:name":"Maidpro",
    "wof:placetype":"venue"
},
  "geometry": {"coordinates":[-82.653026,28.33045],"type":"Point"}
}