{
  "type": "Feature",
  "properties": {
    "iso:country":"US",
    "sg:address":"550 W Main St Fl 3",
    "sg:city":"Tavares",
    "sg:classifiers":[
        {
            "category":"Government",
            "subcategory":"Office",
            "type":"Public Place"
        }
    ],
    "sg:phone":"+1 352 742 4142",
    "sg:postcode":"32778",
    "sg:province":"FL",
    "sg:tags":[
        "township",
        "government-city",
        "village"
    ],
    "sg:website":"http://www.duvalclerk.com",
    "wof:name":"County Civil Department",
    "wof:placetype":"venue"
},
  "geometry": {"coordinates":[-81.732928,28.802304],"type":"Point"}
}