{
  "type": "Feature",
  "properties": {
    "addr:full":"5721 Hollywood Blvd Hollywood FL 33021",
    "addr:housenumber":"5721",
    "addr:postcode":"33021",
    "addr:street":"Hollywood Blvd",
    "iso:country":"US",
    "sg:address":"5721 Hollywood Blvd",
    "sg:city":"Hollywood",
    "sg:classifiers":[
        {
            "category":"Food & Beverages",
            "subcategory":"Specialty",
            "type":"Retail Goods"
        },
        {
            "category":"Food & Beverages",
            "subcategory":"Groceries & Convenience Stores",
            "type":"Retail Goods"
        }
    ],
    "sg:phone":"+1 954 962 4552",
    "sg:postcode":"33021",
    "sg:province":"FL",
    "sg:tags":[
        "grocers-specialty"
    ],
    "wof:name":"Damascus Mid East Food Market",
    "wof:placetype":"venue"
},
  "geometry": {"coordinates":[-80.201908,26.010194],"type":"Point"}
}