{
  "type": "Feature",
  "properties": {
    "iso:country":"US",
    "sg:address":"38 NE 167th St",
    "sg:city":"Miami",
    "sg:classifiers":[
        {
            "category":"Professional",
            "subcategory":"Accounting & Tax Preparation",
            "type":"Services"
        }
    ],
    "sg:phone":"+1 305 949 5644",
    "sg:postcode":"33162",
    "sg:province":"FL",
    "sg:tags":[
        "return",
        "filing"
    ],
    "wof:name":"Immigration & Income Tax Svc",
    "wof:placetype":"venue"
},
  "geometry": {"coordinates":[-80.194523,25.928242],"type":"Point"}
}