{
  "type": "Feature",
  "properties": {
    "iso:country":"US",
    "sg:address":"400 SE 16th Ave",
    "sg:city":"Pompano Beach",
    "sg:classifiers":[
        {
            "category":"Building & Trades",
            "subcategory":"Landscaping Services",
            "type":"Services"
        }
    ],
    "sg:phone":"+1 954 783 4677",
    "sg:postcode":"33060",
    "sg:province":"FL",
    "wof:name":"Nutra Green Pest Control Inc",
    "wof:placetype":"venue"
},
  "geometry": {"coordinates":[-80.10715,26.225952],"type":"Point"}
}