{
  "type": "Feature",
  "properties": {
    "iso:country":"US",
    "sg:address":"4052 US Hwy 17",
    "sg:city":"Haines City",
    "sg:classifiers":[
        {
            "category":"Autos & Motor Vehicles",
            "subcategory":"Automobile Sales",
            "type":"Retail Goods"
        }
    ],
    "sg:phone":"+1 863 419 0777",
    "sg:postcode":"33844",
    "sg:province":"FL",
    "sg:tags":[
        "car",
        "used",
        "dealer"
    ],
    "wof:name":"Kenny B's Auto Sales",
    "wof:placetype":"venue"
},
  "geometry": {"coordinates":[-81.669236,28.108195],"type":"Point"}
}