{
  "type": "Feature",
  "properties": {
    "addr:full":"104 SE 1 Ave Gainesville FL 32601",
    "addr:housenumber":"104",
    "addr:postcode":"32601",
    "addr:street":"Se 1 Ave",
    "iso:country":"US",
    "sg:address":"104 SE 1 Ave",
    "sg:city":"Gainesville",
    "sg:classifiers":[
        {
            "category":"Government",
            "subcategory":"Office",
            "type":"Public Place"
        }
    ],
    "sg:phone":"+1 352 334 2614",
    "sg:postcode":"32601",
    "sg:province":"FL",
    "sg:tags":[
        "city",
        "program"
    ],
    "wof:name":"Gainesville Regional Transit",
    "wof:placetype":"venue"
},
  "geometry": {"coordinates":[-82.323153,29.651122],"type":"Point"}
}