{
  "type": "Feature",
  "properties": {
    "addr:full":"2308 Tupelo Ter Tallahassee FL 32303",
    "addr:housenumber":"2308",
    "addr:postcode":"32303",
    "addr:street":"Tupelo Ter",
    "iso:country":"US",
    "sg:address":"2308 Tupelo Ter",
    "sg:city":"Tallahassee",
    "sg:classifiers":[
        {
            "category":"Professional",
            "subcategory":"Accounting & Tax Preparation",
            "type":"Services"
        }
    ],
    "sg:phone":"+1 850 219 9557",
    "sg:postcode":"32303",
    "sg:province":"FL",
    "sg:tags":[
        "bookkeeping",
        "billing"
    ],
    "wof:name":"Emma Phelps Bookkeeping",
    "wof:placetype":"venue"
},
  "geometry": {"coordinates":[-84.294715,30.472519],"type":"Point"}
}