{
  "type": "Feature",
  "properties": {
    "addr:full":"6400 US Hwy 27 Sebring FL 33876",
    "addr:housenumber":"6400",
    "addr:postcode":"33876",
    "addr:street":"Us Hwy 27",
    "iso:country":"US",
    "sg:address":"6400 US Hwy 27",
    "sg:city":"Sebring",
    "sg:classifiers":[
        {
            "category":"Freight",
            "type":"Transportation"
        }
    ],
    "sg:phone":"+1 863 382 6019",
    "sg:postcode":"33876",
    "sg:province":"FL",
    "sg:tags":[
        "warehouse",
        "public",
        "general"
    ],
    "wof:name":"Sunrise Mini Storage",
    "wof:placetype":"venue"
},
  "geometry": {"coordinates":[-81.419871,27.448913],"type":"Point"}
}