{
  "type": "Feature",
  "properties": {
    "addr:full":"798 10th St Lake Park FL 33403",
    "addr:housenumber":"798",
    "addr:postcode":"33403",
    "addr:street":"10Th St",
    "iso:country":"US",
    "sg:address":"798 10th St",
    "sg:city":"Lake Park",
    "sg:classifiers":[
        {
            "category":"Autos & Motor Vehicles",
            "subcategory":"Boat Sales",
            "type":"Retail Goods"
        }
    ],
    "sg:phone":"+1 561 848 0065",
    "sg:postcode":"33403",
    "sg:province":"FL",
    "sg:tags":[
        "top",
        "upholstery",
        "cover"
    ],
    "wof:name":"Donna Humphrey Inc",
    "wof:placetype":"venue"
},
  "geometry": {"coordinates":[-80.072642,26.798904],"type":"Point"}
}