{
  "type": "Feature",
  "properties": {
    "iso:country":"US",
    "sg:address":"3210 Lake Emma Rd",
    "sg:city":"Lake Mary",
    "sg:classifiers":[
        {
            "category":"Professional",
            "subcategory":"Management & Consulting",
            "type":"Services"
        }
    ],
    "sg:phone":"+1 407 804 9702",
    "sg:postcode":"32746",
    "sg:province":"FL",
    "wof:name":"American Management System",
    "wof:placetype":"venue"
},
  "geometry": {"coordinates":[-81.359379,28.746412],"type":"Point"}
}