{
  "type": "Feature",
  "properties": {
    "addr:full":"1 Blakefield Dr Palm Coast FL 32137",
    "addr:housenumber":"1",
    "addr:postcode":"32137",
    "addr:street":"Blakefield Dr",
    "iso:country":"US",
    "sg:address":"1 Blakefield Dr",
    "sg:city":"Palm Coast",
    "sg:classifiers":[
        {
            "category":"Personal",
            "subcategory":"Beauty Salon",
            "type":"Services"
        }
    ],
    "sg:phone":"+1 386 445 3605",
    "sg:postcode":"32137",
    "sg:province":"FL",
    "sg:tags":[
        "shop"
    ],
    "wof:name":"Sonyas Beauty Salon",
    "wof:placetype":"venue"
},
  "geometry": {"coordinates":[-81.20434899999999,29.551679],"type":"Point"}
}