{
  "type": "Feature",
  "properties": {
    "iso:country":"US",
    "sg:address":"990 Wendam Ct",
    "sg:city":"Daytona Beach",
    "sg:classifiers":[
        {
            "category":"Professional",
            "subcategory":"Management & Consulting",
            "type":"Services"
        }
    ],
    "sg:phone":"+1 386 760 3244",
    "sg:postcode":"32127",
    "sg:province":"FL",
    "wof:name":"QMS Quality Marketing Service",
    "wof:placetype":"venue"
},
  "geometry": {"coordinates":[-80.99804899999999,29.117103],"type":"Point"}
}