{
  "type": "Feature",
  "properties": {
    "iso:country":"US",
    "sg:address":"4409 Chiquita Blvd S",
    "sg:city":"Cape Coral",
    "sg:classifiers":[
        {
            "category":"Building & Trades",
            "subcategory":"Construction",
            "type":"Services"
        }
    ],
    "sg:phone":"+1 239 540 8245",
    "sg:postcode":"33914",
    "sg:province":"FL",
    "sg:tags":[
        "contractor"
    ],
    "sg:website":"www.mercedeshomes.com",
    "wof:name":"Mercedes Homes",
    "wof:placetype":"venue"
},
  "geometry": {"coordinates":[-82.006547,26.569222],"type":"Point"}
}