{
  "type": "Feature",
  "properties": {
    "addr:full":"1531 Atlantic Blvd Neptune Beach FL 32233",
    "addr:housenumber":"1531",
    "addr:postcode":"32233",
    "addr:street":"Atlantic Blvd",
    "iso:country":"US",
    "sg:address":"1531 Atlantic Blvd",
    "sg:city":"Neptune Beach",
    "sg:classifiers":[
        {
            "category":"Recreation",
            "type":"Entertainment"
        }
    ],
    "sg:phone":"+1 904 270 1239",
    "sg:postcode":"32233",
    "sg:province":"FL",
    "sg:tags":[
        "instruction",
        "yoga"
    ],
    "wof:name":"Bikram Yoga College of India",
    "wof:placetype":"venue"
},
  "geometry": {"coordinates":[-81.423914,30.32433],"type":"Point"}
}