{
  "type": "Feature",
  "properties": {
    "iso:country":"US",
    "sg:address":"10851 Bromley Ln",
    "sg:city":"Fort Myers",
    "sg:classifiers":[
        {
            "category":"Professional",
            "type":"Services"
        }
    ],
    "sg:phone":"+1 239 418 1075",
    "sg:postcode":"33966",
    "sg:province":"FL",
    "sg:tags":[
        "establishment"
    ],
    "wof:name":"Marvin & Helen Gralnick Fndtn",
    "wof:placetype":"venue"
},
  "geometry": {"coordinates":[-81.833197,26.587145],"type":"Point"}
}