{
  "type": "Feature",
  "properties": {
    "iso:country":"US",
    "sg:address":"4873 NW 113th Pl",
    "sg:city":"Doral",
    "sg:classifiers":[
        {
            "category":"Banks & Credit Unions",
            "subcategory":"Investment Brokerage",
            "type":"Services"
        }
    ],
    "sg:phone":"+1 305 477 0737",
    "sg:postcode":"33178",
    "sg:province":"FL",
    "wof:name":"Florida Green Mgmt & Invstmnt",
    "wof:placetype":"venue"
},
  "geometry": {"coordinates":[-80.38126099999999,25.817441],"type":"Point"}
}