{
  "type": "Feature",
  "properties": {
    "addr:full":"3034 SE Dominica Ter Stuart FL 34997",
    "addr:housenumber":"3034",
    "addr:postcode":"34997",
    "addr:street":"Se Dominica Ter",
    "iso:country":"US",
    "sg:address":"3034 SE Dominica Ter",
    "sg:city":"Stuart",
    "sg:classifiers":[
        {
            "category":"Autos & Motor Vehicles",
            "subcategory":"Automobile Sales",
            "type":"Retail Goods"
        }
    ],
    "sg:phone":"+1 772 463 8288",
    "sg:postcode":"34997",
    "sg:province":"FL",
    "sg:tags":[
        "used",
        "car",
        "broker",
        "dealers-used",
        "truck",
        "cars-wholesale"
    ],
    "wof:name":"A Star Auto Brokers",
    "wof:placetype":"venue"
},
  "geometry": {"coordinates":[-80.215397,27.150611],"type":"Point"}
}