{
  "type": "Feature",
  "properties": {
    "iso:country":"US",
    "sg:address":"1070 SE Federal Hwy",
    "sg:city":"Stuart",
    "sg:classifiers":[
        {
            "category":"Autos & Motor Vehicles",
            "subcategory":"Automobile Sales",
            "type":"Retail Goods"
        }
    ],
    "sg:phone":"+1 772 288 3392",
    "sg:postcode":"34994",
    "sg:province":"FL",
    "sg:tags":[
        "car",
        "used",
        "cars-wholesale",
        "dealers-used"
    ],
    "wof:name":"Good Rides Inc",
    "wof:placetype":"venue"
},
  "geometry": {"coordinates":[-80.24754799999999,27.18841],"type":"Point"}
}