{
  "type": "Feature",
  "properties": {
    "iso:country":"US",
    "sg:address":"8905 SW 108th Circle Ct",
    "sg:city":"Miami",
    "sg:classifiers":[
        {
            "category":"Professional",
            "subcategory":"Computer Services",
            "type":"Services"
        }
    ],
    "sg:phone":"+1 305 772 6616",
    "sg:postcode":"33176",
    "sg:province":"FL",
    "sg:tags":[
        "consultant",
        "designer",
        "system"
    ],
    "wof:name":"Mistry Computer Consultant",
    "wof:placetype":"venue"
},
  "geometry": {"coordinates":[-80.370817,25.685182],"type":"Point"}
}