{
  "type": "Feature",
  "properties": {
    "addr:full":"6602 SW 61st Ter Miami FL 33143",
    "addr:housenumber":"6602",
    "addr:postcode":"33143",
    "addr:street":"Sw 61St Ter",
    "iso:country":"US",
    "sg:address":"6602 SW 61st Ter",
    "sg:city":"Miami",
    "sg:classifiers":[
        {
            "category":"Banks & Credit Unions",
            "subcategory":"Financial Services",
            "type":"Services"
        }
    ],
    "sg:phone":"+1 305 667 6501",
    "sg:postcode":"33143",
    "sg:province":"FL",
    "sg:tags":[
        "investor"
    ],
    "wof:name":"Frs Investment Group LLC",
    "wof:placetype":"venue"
},
  "geometry": {"coordinates":[-80.301095,25.713135],"type":"Point"}
}