{
  "type": "Feature",
  "properties": {
    "addr:full":"17077 Newport Club Dr Boca Raton FL 33496",
    "addr:housenumber":"17077",
    "addr:postcode":"33496",
    "addr:street":"Newport Club Dr",
    "iso:country":"US",
    "sg:address":"17077 Newport Club Dr",
    "sg:city":"Boca Raton",
    "sg:classifiers":[
        {
            "category":"Wholesale",
            "subcategory":"Durable Goods & Equipment",
            "type":"Manufacturing & Wholesale Goods"
        }
    ],
    "sg:phone":"+1 561 994 9441",
    "sg:postcode":"33496",
    "sg:province":"FL",
    "sg:tags":[
        "exporter"
    ],
    "sg:website":"www.unitedforward.com",
    "wof:name":"United Forward",
    "wof:placetype":"venue"
},
  "geometry": {"coordinates":[-80.14817600000001,26.423529],"type":"Point"}
}