{
  "type": "Feature",
  "properties": {
    "iso:country":"US",
    "sg:address":"1665 Oviedo Marketplace Blvd",
    "sg:city":"Oviedo",
    "sg:classifiers":[
        {
            "category":"Shopping",
            "subcategory":"Clothing, Apparel, & Fashions",
            "type":"Retail Goods"
        }
    ],
    "sg:phone":"+1 407 359 3591",
    "sg:postcode":"32765",
    "sg:province":"FL",
    "wof:name":"Casual Corner",
    "wof:placetype":"venue"
},
  "geometry": {"coordinates":[-81.23566599999999,28.659635],"type":"Point"}
}