{
  "type": "Feature",
  "properties": {
    "iso:country":"US",
    "sg:address":"2708 Cranes Cove Dr",
    "sg:city":"Kissimmee",
    "sg:classifiers":[
        {
            "category":"Health Services",
            "subcategory":"Hospital",
            "type":"Services"
        }
    ],
    "sg:phone":"+1 407 849 6455",
    "sg:postcode":"34741",
    "sg:province":"FL",
    "sg:tags":[
        "equipment",
        "supply"
    ],
    "wof:name":"Osvaldo Burgos",
    "wof:placetype":"venue"
},
  "geometry": {"coordinates":[-81.433627,28.345109],"type":"Point"}
}