{
  "type": "Feature",
  "properties": {
    "iso:country":"US",
    "sg:address":"923 N Magnolia Ave",
    "sg:city":"Ocala",
    "sg:classifiers":[
        {
            "category":"Shopping",
            "subcategory":"Used Merchandise",
            "type":"Retail Goods"
        }
    ],
    "sg:phone":"+1 352 401 3733",
    "sg:postcode":"34475",
    "sg:province":"FL",
    "sg:tags":[
        "shop",
        "thrift"
    ],
    "wof:name":"Integrity House Of Bargains",
    "wof:placetype":"venue"
},
  "geometry": {"coordinates":[-82.136433,29.196772],"type":"Point"}
}