{
  "type": "Feature",
  "properties": {
    "addr:full":"330 N Beaumont Ave Kissimmee FL 34741",
    "addr:housenumber":"330",
    "addr:postcode":"34741",
    "addr:street":"N Beaumont Ave",
    "iso:country":"US",
    "sg:address":"330 N Beaumont Ave",
    "sg:city":"Kissimmee",
    "sg:classifiers":[
        {
            "category":"Government",
            "subcategory":"Office",
            "type":"Public Place"
        }
    ],
    "sg:phone":"+1 407 343 3900",
    "sg:postcode":"34741",
    "sg:province":"FL",
    "sg:tags":[
        "parish",
        "government-county"
    ],
    "wof:name":"Osceola County Voter Rgstrtn",
    "wof:placetype":"venue"
},
  "geometry": {"coordinates":[-81.409948,28.295097],"type":"Point"}
}