{
  "type": "Feature",
  "properties": {
    "addr:full":"4052 Mc Cullough Rd Mims FL 32754",
    "addr:housenumber":"4052",
    "addr:postcode":"32754",
    "addr:street":"Mc Cullough Rd",
    "iso:country":"US",
    "sg:address":"4052 Mc Cullough Rd",
    "sg:city":"Mims",
    "sg:classifiers":[
        {
            "category":"Freight",
            "type":"Transportation"
        }
    ],
    "sg:phone":"+1 321 264 1910",
    "sg:postcode":"32754",
    "sg:province":"FL",
    "sg:tags":[
        "operator",
        "trucking"
    ],
    "wof:name":"Raymel Direct",
    "wof:placetype":"venue"
},
  "geometry": {"coordinates":[-80.86769200000001,28.704846],"type":"Point"}
}