{
  "type": "Feature",
  "properties": {
    "addr:full":"901 US Hwy 27 Sebring FL 33870",
    "addr:housenumber":"901",
    "addr:postcode":"33870",
    "addr:street":"Us Hwy 27",
    "iso:country":"US",
    "sg:address":"901 US Hwy 27",
    "sg:city":"Sebring",
    "sg:classifiers":[
        {
            "category":"Building & Trades",
            "subcategory":"Construction",
            "type":"Services"
        }
    ],
    "sg:phone":"+1 863 382 6188",
    "sg:postcode":"33870",
    "sg:province":"FL",
    "sg:tags":[
        "contractor"
    ],
    "wof:name":"Oakview Construction",
    "wof:placetype":"venue"
},
  "geometry": {"coordinates":[-81.472081,27.475337],"type":"Point"}
}