{
  "type": "Feature",
  "properties": {
    "iso:country":"US",
    "sg:address":"404 Hawk St",
    "sg:city":"Rockledge",
    "sg:classifiers":[
        {
            "category":"Building & Trades",
            "subcategory":"Construction",
            "type":"Services"
        }
    ],
    "sg:phone":"+1 321 632 5460",
    "sg:postcode":"32955",
    "sg:province":"FL",
    "sg:tags":[
        "woodworker"
    ],
    "wof:name":"Woodcrafts By Ray",
    "wof:placetype":"venue"
},
  "geometry": {"coordinates":[-80.73230100000001,28.326873],"type":"Point"}
}