{
  "type": "Feature",
  "properties": {
    "addr:full":"14444 Beach Blvd Jacksonville Bch FL 32250",
    "addr:housenumber":"14444",
    "addr:postcode":"32250",
    "addr:street":"Beach Blvd",
    "iso:country":"US",
    "sg:address":"14444 Beach Blvd",
    "sg:city":"Jacksonville Bch",
    "sg:classifiers":[
        {
            "category":"Health Services",
            "subcategory":"Doctor",
            "type":"Services"
        }
    ],
    "sg:phone":"+1 904 223 6400",
    "sg:postcode":"32250",
    "sg:province":"FL",
    "sg:tags":[
        "physician",
        "surgeon"
    ],
    "wof:name":"Family Medical Ctr",
    "wof:placetype":"venue"
},
  "geometry": {"coordinates":[-81.435918,30.287855],"type":"Point"}
}