{
  "type": "Feature",
  "properties": {
    "iso:country":"US",
    "sg:address":"2709 Robinson Ave",
    "sg:city":"Sarasota",
    "sg:classifiers":[
        {
            "category":"Manufacturing",
            "subcategory":"Printing",
            "type":"Manufacturing & Wholesale Goods"
        }
    ],
    "sg:phone":"+1 941 953 6088",
    "sg:postcode":"34232",
    "sg:province":"FL",
    "sg:tags":[
        "publisher"
    ],
    "wof:name":"Jeff Robinson Publishing",
    "wof:placetype":"venue"
},
  "geometry": {"coordinates":[-82.49193699999999,27.311692],"type":"Point"}
}