{
  "type": "Feature",
  "properties": {
    "iso:country":"US",
    "sg:address":"9803 Gingerwood Dr",
    "sg:city":"Tampa",
    "sg:classifiers":[
        {
            "category":"Health Services",
            "subcategory":"Doctor",
            "type":"Services"
        }
    ],
    "sg:phone":"+1 813 920 6470",
    "sg:postcode":"33626",
    "sg:province":"FL",
    "sg:tags":[
        "medical"
    ],
    "wof:name":"Jovid Healthcare Solutions LLC",
    "wof:placetype":"venue"
},
  "geometry": {"coordinates":[-82.594819,28.045986],"type":"Point"}
}