{
  "type": "Feature",
  "properties": {
    "iso:country":"US",
    "sg:address":"2150 Cordes Way",
    "sg:city":"Osprey",
    "sg:classifiers":[
        {
            "category":"Education",
            "subcategory":"Special Training",
            "type":"Public Place"
        }
    ],
    "sg:phone":"+1 941 966 4825",
    "sg:postcode":"34229",
    "sg:province":"FL",
    "sg:tags":[
        "school",
        "instruction",
        "art"
    ],
    "wof:name":"Bascher's North Creek Art Schl",
    "wof:placetype":"venue"
},
  "geometry": {"coordinates":[-82.486746,27.209997],"type":"Point"}
}