{
  "type": "Feature",
  "properties": {
    "iso:country":"US",
    "sg:address":"8144 SW 82nd Pl",
    "sg:city":"Miami",
    "sg:classifiers":[
        {
            "category":"Wholesale",
            "subcategory":"Computers",
            "type":"Manufacturing & Wholesale Goods"
        }
    ],
    "sg:phone":"+1 305 595 2948",
    "sg:postcode":"33143",
    "sg:province":"FL",
    "sg:tags":[
        "export",
        "gen",
        "merchandise"
    ],
    "wof:name":"NT Trading Company Inc",
    "wof:placetype":"venue"
},
  "geometry": {"coordinates":[-80.326936,25.693151],"type":"Point"}
}