{
  "type": "Feature",
  "properties": {
    "iso:country":"US",
    "sg:address":"4055 Estancia Way",
    "sg:city":"Melbourne",
    "sg:classifiers":[
        {
            "category":"Manufacturing",
            "subcategory":"Food",
            "type":"Manufacturing & Wholesale Goods"
        }
    ],
    "sg:phone":"+1 321 751 0660",
    "sg:postcode":"32934",
    "sg:province":"FL",
    "sg:tags":[
        "product",
        "mfg"
    ],
    "wof:name":"Godiva",
    "wof:placetype":"venue"
},
  "geometry": {"coordinates":[-80.677268,28.175654],"type":"Point"}
}