{
  "type": "Feature",
  "properties": {
    "iso:country":"US",
    "sg:address":"13311 Boca Ciega Ave",
    "sg:city":"Saint Petersburg",
    "sg:classifiers":[
        {
            "category":"Building & Trades",
            "subcategory":"Construction",
            "type":"Services"
        }
    ],
    "sg:phone":"+1 727 391 4003",
    "sg:postcode":"33708",
    "sg:province":"FL",
    "sg:tags":[
        "contractor"
    ],
    "wof:name":"Florida Aquatics Inc",
    "wof:placetype":"venue"
},
  "geometry": {"coordinates":[-82.785212,27.791619],"type":"Point"}
}