{
  "type": "Feature",
  "properties": {
    "iso:country":"US",
    "sg:address":"22022 Martella Ave",
    "sg:city":"Boca Raton",
    "sg:classifiers":[
        {
            "category":"Building & Trades",
            "subcategory":"Construction",
            "type":"Services"
        }
    ],
    "sg:phone":"+1 561 218 8813",
    "sg:postcode":"33433",
    "sg:province":"FL",
    "sg:tags":[
        "contractor",
        "product",
        "wood",
        "mfg"
    ],
    "wof:name":"Buisness Has Not Opened Yet",
    "wof:placetype":"venue"
},
  "geometry": {"coordinates":[-80.181712,26.344088],"type":"Point"}
}