{
  "type": "Feature",
  "properties": {
    "addr:full":"7034 Slate St Orlando FL 32810",
    "addr:housenumber":"7034",
    "addr:postcode":"32810",
    "addr:street":"Slate St",
    "iso:country":"US",
    "sg:address":"7034 Slate St",
    "sg:city":"Orlando",
    "sg:classifiers":[
        {
            "category":"Real Estate",
            "subcategory":"Real Estate Agent",
            "type":"Services"
        }
    ],
    "sg:phone":"+1 407 291 4166",
    "sg:postcode":"32810",
    "sg:province":"FL",
    "wof:name":"Dondru Turton-Morris",
    "wof:placetype":"venue"
},
  "geometry": {"coordinates":[-81.478544,28.619377],"type":"Point"}
}