{
  "type": "Feature",
  "properties": {
    "iso:country":"US",
    "sg:address":"3740 20th St",
    "sg:city":"Vero Beach",
    "sg:classifiers":[
        {
            "category":"Manufacturing",
            "subcategory":"Aerospace",
            "type":"Manufacturing & Wholesale Goods"
        }
    ],
    "sg:phone":"+1 561 547 6007",
    "sg:postcode":"32960",
    "sg:province":"FL",
    "sg:tags":[
        "aircraft",
        "airframe",
        "mfg"
    ],
    "wof:name":"Pilatus Aircraft Limited",
    "wof:placetype":"venue"
},
  "geometry": {"coordinates":[-80.424093,27.638454],"type":"Point"}
}