{
  "type": "Feature",
  "properties": {
    "addr:full":"4606 Ashton Rd Sarasota FL 34233",
    "addr:housenumber":"4606",
    "addr:postcode":"34233",
    "addr:street":"Ashton Rd",
    "iso:country":"US",
    "sg:address":"4606 Ashton Rd",
    "sg:city":"Sarasota",
    "sg:classifiers":[
        {
            "category":"Wholesale",
            "subcategory":"Chemicals & Plastics",
            "type":"Manufacturing & Wholesale Goods"
        }
    ],
    "sg:phone":"+1 941 923 3468",
    "sg:postcode":"34233",
    "sg:province":"FL",
    "sg:tags":[
        "helium"
    ],
    "wof:name":"America's Helium & Balloons",
    "wof:placetype":"venue"
},
  "geometry": {"coordinates":[-82.47891199999999,27.276497],"type":"Point"}
}