{
  "type": "Feature",
  "properties": {
    "iso:country":"US",
    "sg:address":"55716 Front St",
    "sg:city":"Astor",
    "sg:classifiers":[
        {
            "category":"Fast Food",
            "type":"Food & Drink"
        },
        {
            "category":"Restaurant",
            "type":"Food & Drink"
        }
    ],
    "sg:phone":"+1 352 759 3450",
    "sg:postcode":"32102",
    "sg:province":"FL",
    "sg:tags":[
        "hot",
        "hamburger",
        "dog"
    ],
    "wof:name":"Karens Food Cart",
    "wof:placetype":"venue"
},
  "geometry": {"coordinates":[-81.52459500000001,29.163494],"type":"Point"}
}