{
  "type": "Feature",
  "properties": {
    "iso:country":"US",
    "sg:address":"3301 Tamiami Trl",
    "sg:city":"Naples",
    "sg:classifiers":[
        {
            "category":"Government",
            "subcategory":"Police Station",
            "type":"Public Place"
        }
    ],
    "sg:phone":"+1 239 695 2301",
    "sg:postcode":"34112",
    "sg:province":"FL",
    "sg:tags":[
        "sheriff"
    ],
    "wof:name":"Sheriff's Office-Sub Station",
    "wof:placetype":"venue"
},
  "geometry": {"coordinates":[-81.76283599999999,26.123549],"type":"Point"}
}