{
  "type": "Feature",
  "properties": {
    "addr:full":"2955 SW 8th St Miami FL 33135",
    "addr:housenumber":"2955",
    "addr:postcode":"33135",
    "addr:street":"Sw 8Th St",
    "iso:country":"US",
    "sg:address":"2955 SW 8th St",
    "sg:city":"Miami",
    "sg:classifiers":[
        {
            "category":"Travel",
            "subcategory":"Travel Agent",
            "type":"Entertainment"
        }
    ],
    "sg:phone":"+1 305 456 9758",
    "sg:postcode":"33135",
    "sg:province":"FL",
    "sg:tags":[
        "agency"
    ],
    "wof:name":"Cuba Travel Services",
    "wof:placetype":"venue"
},
  "geometry": {"coordinates":[-80.241983,25.765067],"type":"Point"}
}