{
  "type": "Feature",
  "properties": {
    "iso:country":"US",
    "sg:address":"655 Hollows Cir",
    "sg:city":"Deerfield Beach",
    "sg:classifiers":[
        {
            "category":"Professional",
            "subcategory":"Management & Consulting",
            "type":"Services"
        }
    ],
    "sg:phone":"+1 954 421 1086",
    "sg:postcode":"33442",
    "sg:province":"FL",
    "wof:name":"McM International",
    "wof:placetype":"venue"
},
  "geometry": {"coordinates":[-80.128714,26.327429],"type":"Point"}
}