{
  "type": "Feature",
  "properties": {
    "iso:country":"US",
    "sg:address":"3020 Cypress Gardens Rd",
    "sg:city":"Winter Haven",
    "sg:classifiers":[
        {
            "category":"Retail",
            "subcategory":"Auto Repair",
            "type":"Services"
        }
    ],
    "sg:phone":"+1 863 325 9191",
    "sg:postcode":"33884",
    "sg:province":"FL",
    "sg:tags":[
        "repairing",
        "automobile",
        "general"
    ],
    "wof:name":"Auto Dynamics Inc",
    "wof:placetype":"venue"
},
  "geometry": {"coordinates":[-81.685945,27.996708],"type":"Point"}
}