{
  "type": "Feature",
  "properties": {
    "iso:country":"US",
    "sg:address":"1 NE 40th St",
    "sg:city":"Miami",
    "sg:classifiers":[
        {
            "category":"Sports & Exercise",
            "subcategory":"Gym",
            "type":"Entertainment"
        }
    ],
    "sg:phone":"+1 305 573 4946",
    "sg:postcode":"33137",
    "sg:province":"FL",
    "sg:tags":[
        "trainer"
    ],
    "wof:name":"Pilates Method Alliance",
    "wof:placetype":"venue"
},
  "geometry": {"coordinates":[-80.19543400000001,25.813507],"type":"Point"}
}