{
  "type": "Feature",
  "properties": {
    "addr:full":"17 Mildred Dr Fort Myers FL 33901",
    "addr:housenumber":"17",
    "addr:postcode":"33901",
    "addr:street":"Mildred Dr",
    "iso:country":"US",
    "sg:address":"17 Mildred Dr",
    "sg:city":"Fort Myers",
    "sg:classifiers":[
        {
            "category":"Home & Garden",
            "subcategory":"Furniture",
            "type":"Retail Goods"
        }
    ],
    "sg:phone":"+1 239 938 0061",
    "sg:postcode":"33901",
    "sg:province":"FL",
    "sg:tags":[
        "cabinet"
    ],
    "wof:name":"Advanced Cabinet Designs Inc",
    "wof:placetype":"venue"
},
  "geometry": {"coordinates":[-81.87330799999999,26.599488],"type":"Point"}
}