{
  "type": "Feature",
  "properties": {
    "addr:full":"1118 E Atlantic Ave Delray Beach FL 33483",
    "addr:housenumber":"1118",
    "addr:postcode":"33483",
    "addr:street":"E Atlantic Ave",
    "iso:country":"US",
    "sg:address":"1118 E Atlantic Ave",
    "sg:city":"Delray Beach",
    "sg:classifiers":[
        {
            "category":"Banks & Credit Unions",
            "subcategory":"Bank",
            "type":"Services"
        }
    ],
    "sg:phone":"+1 561 243 1170",
    "sg:postcode":"33483",
    "sg:province":"FL",
    "sg:tags":[
        "loan",
        "real estate"
    ],
    "wof:name":"First Mortgage Corp",
    "wof:placetype":"venue"
},
  "geometry": {"coordinates":[-80.060475,26.461611],"type":"Point"}
}