{
  "type": "Feature",
  "properties": {
    "addr:full":"332 Lures Ln Saint Augustine FL 32095",
    "addr:housenumber":"332",
    "addr:postcode":"32095",
    "addr:street":"Lures Ln",
    "iso:country":"US",
    "sg:address":"332 Lures Ln",
    "sg:city":"Saint Augustine",
    "sg:classifiers":[
        {
            "category":"Building & Trades",
            "subcategory":"Electrical",
            "type":"Services"
        }
    ],
    "sg:phone":"+1 904 669 5611",
    "sg:postcode":"32095",
    "sg:province":"FL",
    "sg:tags":[
        "electrical",
        "contractor"
    ],
    "wof:name":"Bertrum and Company Inc",
    "wof:placetype":"venue"
},
  "geometry": {"coordinates":[-81.374921,30.004877],"type":"Point"}
}