{
  "type": "Feature",
  "properties": {
    "addr:full":"16504 NW 16th St Hollywood FL 33028",
    "addr:housenumber":"16504",
    "addr:postcode":"33028",
    "addr:street":"Nw 16Th St",
    "iso:country":"US",
    "sg:address":"16504 NW 16th St",
    "sg:city":"Hollywood",
    "sg:classifiers":[
        {
            "category":"Professional",
            "subcategory":"Advertising",
            "type":"Services"
        }
    ],
    "sg:phone":"+1 954 432 8651",
    "sg:postcode":"33028",
    "sg:province":"FL",
    "sg:tags":[
        "outdoor"
    ],
    "wof:name":"Please Heaven Inc",
    "wof:placetype":"venue"
},
  "geometry": {"coordinates":[-80.36260299999999,26.021991],"type":"Point"}
}