{
  "type": "Feature",
  "properties": {
    "iso:country":"US",
    "sg:address":"1382 Pawnee Pointe Ct",
    "sg:city":"Tallahassee",
    "sg:classifiers":[
        {
            "category":"Manufacturing",
            "subcategory":"Food",
            "type":"Manufacturing & Wholesale Goods"
        }
    ],
    "sg:phone":"+1 850 894 2618",
    "sg:postcode":"32312",
    "sg:province":"FL",
    "sg:tags":[
        "brewer"
    ],
    "wof:name":"Anheuser-Busch Inc",
    "wof:placetype":"venue"
},
  "geometry": {"coordinates":[-84.256141,30.509844],"type":"Point"}
}