{
  "type": "Feature",
  "properties": {
    "addr:full":"3460 NE Jacksonville Rd Ocala FL 34479",
    "addr:housenumber":"3460",
    "addr:postcode":"34479",
    "addr:street":"Ne Jacksonville Rd",
    "iso:country":"US",
    "sg:address":"3460 NE Jacksonville Rd",
    "sg:city":"Ocala",
    "sg:classifiers":[
        {
            "category":"Professional",
            "subcategory":"Business Services",
            "type":"Services"
        }
    ],
    "sg:phone":"+1 352 732 5073",
    "sg:postcode":"34479",
    "sg:province":"FL",
    "sg:tags":[
        "fire",
        "extinguisher"
    ],
    "wof:name":"All Counties Fire Extinguisher",
    "wof:placetype":"venue"
},
  "geometry": {"coordinates":[-82.124357,29.221523],"type":"Point"}
}