{
  "type": "Feature",
  "properties": {
    "iso:country":"US",
    "sg:address":"28250 County Rd",
    "sg:city":"Summerland Key",
    "sg:classifiers":[
        {
            "category":"Building & Trades",
            "subcategory":"Landscaping Services",
            "type":"Services"
        }
    ],
    "sg:phone":"+1 305 872 7204",
    "sg:postcode":"33042",
    "sg:province":"FL",
    "wof:name":"L&B Home Services Inc",
    "wof:placetype":"venue"
},
  "geometry": {"coordinates":[-81.390919,24.67601],"type":"Point"}
}