{
  "type": "Feature",
  "properties": {
    "addr:full":"36201 Co Rd 439 Eustis FL 32736",
    "addr:housenumber":"36201",
    "addr:postcode":"32736",
    "addr:street":"Co Rd 439",
    "iso:country":"US",
    "sg:address":"36201 Co Rd 439",
    "sg:city":"Eustis",
    "sg:classifiers":[
        {
            "category":"Retail",
            "subcategory":"Animal Services",
            "type":"Services"
        }
    ],
    "sg:phone":"+1 352 357 5628",
    "sg:postcode":"32736",
    "sg:province":"FL",
    "wof:name":"K Johnson Performance Horses",
    "wof:placetype":"venue"
},
  "geometry": {"coordinates":[-81.595848,28.88912],"type":"Point"}
}