{
  "type": "Feature",
  "properties": {
    "addr:full":"102245 Overseas Hwy Key Largo FL 33037",
    "addr:housenumber":"102245",
    "addr:postcode":"33037",
    "addr:street":"Overseas Hwy",
    "iso:country":"US",
    "sg:address":"102245 Overseas Hwy",
    "sg:city":"Key Largo",
    "sg:classifiers":[
        {
            "category":"Retail",
            "subcategory":"Repair Shop",
            "type":"Services"
        }
    ],
    "sg:phone":"+1 305 451 0031",
    "sg:postcode":"33037",
    "sg:province":"FL",
    "sg:tags":[
        "equipment",
        "transportation"
    ],
    "wof:name":"Total Ocean Performance Inc",
    "wof:placetype":"venue"
},
  "geometry": {"coordinates":[-80.41386300000001,25.123956],"type":"Point"}
}