{
  "type": "Feature",
  "properties": {
    "addr:full":"599 S Indiana Ave Englewood FL 34223",
    "addr:housenumber":"599",
    "addr:postcode":"34223",
    "addr:street":"S Indiana Ave",
    "iso:country":"US",
    "sg:address":"599 S Indiana Ave",
    "sg:city":"Englewood",
    "sg:classifiers":[
        {
            "category":"Utilities",
            "subcategory":"Mobile Phone",
            "type":"Services"
        }
    ],
    "sg:phone":"+1 941 474 1427",
    "sg:postcode":"34223",
    "sg:province":"FL",
    "sg:tags":[
        "telephone",
        "cellular"
    ],
    "wof:name":"Cellular One",
    "wof:placetype":"venue"
},
  "geometry": {"coordinates":[-82.35312399999999,26.952644],"type":"Point"}
}