{
  "type": "Feature",
  "properties": {
    "iso:country":"US",
    "sg:address":"7780 SW 117th Ave",
    "sg:city":"Miami",
    "sg:classifiers":[
        {
            "category":"Organizations",
            "subcategory":"Community Association",
            "type":"Services"
        }
    ],
    "sg:phone":"+1 305 238 7576",
    "sg:postcode":"33183",
    "sg:province":"FL",
    "sg:tags":[
        "detection",
        "lie"
    ],
    "sg:website":"http://www.josephwharper.com",
    "wof:name":"Harper Joseph W And Associates",
    "wof:placetype":"venue"
},
  "geometry": {"coordinates":[-80.38212799999999,25.69589],"type":"Point"}
}