{
  "type": "Feature",
  "properties": {
    "iso:country":"US",
    "sg:address":"5601 SE 66th St",
    "sg:city":"Ocala",
    "sg:classifiers":[
        {
            "category":"Government",
            "subcategory":"Office",
            "type":"Public Place"
        }
    ],
    "sg:phone":"+1 352 245 1580",
    "sg:postcode":"34476",
    "sg:province":"FL",
    "wof:name":"Marion County Recycling Dept",
    "wof:placetype":"venue"
},
  "geometry": {"coordinates":[-82.08896,29.124047],"type":"Point"}
}