{
  "type": "Feature",
  "properties": {
    "iso:country":"US",
    "sg:address":"155 E Church St",
    "sg:city":"Madison",
    "sg:classifiers":[
        {
            "category":"Organizations",
            "subcategory":"Religious Organization",
            "type":"Services"
        }
    ],
    "sg:phone":"+1 850 973 2828",
    "sg:postcode":"32348",
    "sg:province":"FL",
    "sg:tags":[
        "church"
    ],
    "wof:name":"Barbara Memorial Church",
    "wof:placetype":"venue"
},
  "geometry": {"coordinates":[-83.581585,30.105508],"type":"Point"}
}