{
  "type": "Feature",
  "properties": {
    "addr:full":"5015 W 1st Sq SW Vero Beach FL 32968",
    "addr:housenumber":"5015",
    "addr:postcode":"32968",
    "addr:street":"W 1St Sq Sw",
    "iso:country":"US",
    "sg:address":"5015 W 1st Sq SW",
    "sg:city":"Vero Beach",
    "sg:classifiers":[
        {
            "category":"Banks & Credit Unions",
            "subcategory":"Bank",
            "type":"Services"
        }
    ],
    "sg:phone":"+1 772 978 9609",
    "sg:postcode":"32968",
    "sg:province":"FL",
    "sg:tags":[
        "loan",
        "real estate"
    ],
    "wof:name":"Stan I AM Mortgage",
    "wof:placetype":"venue"
},
  "geometry": {"coordinates":[-80.440107,27.602015],"type":"Point"}
}