{
  "type": "Feature",
  "properties": {
    "addr:full":"6000 NW 12th Ave Miami FL 33127",
    "addr:housenumber":"6000",
    "addr:postcode":"33127",
    "addr:street":"Nw 12Th Ave",
    "iso:country":"US",
    "sg:address":"6000 NW 12th Ave",
    "sg:city":"Miami",
    "sg:classifiers":[
        {
            "category":"Food & Beverages",
            "subcategory":"Groceries & Convenience Stores",
            "type":"Retail Goods"
        }
    ],
    "sg:phone":"+1 305 758 5545",
    "sg:postcode":"33127",
    "sg:province":"FL",
    "sg:tags":[
        "grocer"
    ],
    "wof:name":"Betty's Market",
    "wof:placetype":"venue"
},
  "geometry": {"coordinates":[-80.21655199999999,25.831211],"type":"Point"}
}