{
  "type": "Feature",
  "properties": {
    "addr:full":"8803 W Gulf Blvd Treasure Island FL 33706",
    "addr:housenumber":"8803",
    "addr:postcode":"33706",
    "addr:street":"W Gulf Blvd",
    "iso:country":"US",
    "sg:address":"8803 W Gulf Blvd",
    "sg:city":"Treasure Island",
    "sg:classifiers":[
        {
            "category":"Shopping",
            "subcategory":"Computers & Home Electronics",
            "type":"Retail Goods"
        }
    ],
    "sg:phone":"+1 727 367 5472",
    "sg:postcode":"33706",
    "sg:province":"FL",
    "sg:tags":[
        "equipment",
        "electronic",
        "supply"
    ],
    "wof:name":"ECS Electronic Cash",
    "wof:placetype":"venue"
},
  "geometry": {"coordinates":[-82.763442,27.752668],"type":"Point"}
}