{
  "type": "Feature",
  "properties": {
    "iso:country":"US",
    "sg:address":"2137 W Pine St",
    "sg:city":"Orlando",
    "sg:classifiers":[
        {
            "category":"Wholesale",
            "subcategory":"Electrical",
            "type":"Manufacturing & Wholesale Goods"
        }
    ],
    "sg:phone":"+1 800 844 3101",
    "sg:postcode":"32805",
    "sg:province":"FL",
    "sg:tags":[
        "punch",
        "reader"
    ],
    "wof:name":"Products Worldwide Inc",
    "wof:placetype":"venue"
},
  "geometry": {"coordinates":[-81.40889199999999,28.541077],"type":"Point"}
}