{
  "type": "Feature",
  "properties": {
    "iso:country":"US",
    "sg:address":"826 E Yukon St",
    "sg:city":"Tampa",
    "sg:classifiers":[
        {
            "category":"Retail",
            "subcategory":"Auto Repair",
            "type":"Services"
        }
    ],
    "sg:phone":"+1 813 932 1354",
    "sg:postcode":"33604",
    "sg:province":"FL",
    "sg:tags":[
        "repairing",
        "automobile"
    ],
    "wof:name":"Certified Auto Repair Svc Inc",
    "wof:placetype":"venue"
},
  "geometry": {"coordinates":[-82.451707,28.02937],"type":"Point"}
}