{
  "type": "Feature",
  "properties": {
    "iso:country":"US",
    "sg:address":"1624 NE 7th St",
    "sg:city":"Fort Lauderdale",
    "sg:classifiers":[
        {
            "category":"Manufacturing",
            "subcategory":"Printing",
            "type":"Manufacturing & Wholesale Goods"
        }
    ],
    "sg:phone":"+1 954 452 2828",
    "sg:postcode":"33304",
    "sg:province":"FL",
    "sg:tags":[
        "publishing"
    ],
    "wof:name":"Press Box",
    "wof:placetype":"venue"
},
  "geometry": {"coordinates":[-80.126273,26.131914],"type":"Point"}
}