{
  "type": "Feature",
  "properties": {
    "iso:country":"US",
    "sg:address":"4625 Middlebrook Rd",
    "sg:city":"Orlando",
    "sg:classifiers":[
        {
            "category":"Recreation",
            "type":"Entertainment"
        }
    ],
    "sg:phone":"+1 407 999 5277",
    "sg:postcode":"32811",
    "sg:province":"FL",
    "sg:tags":[
        "martial",
        "arts",
        "instruction"
    ],
    "wof:name":"Aikido Kodokai Of Orlando",
    "wof:placetype":"venue"
},
  "geometry": {"coordinates":[-81.452766,28.495455],"type":"Point"}
}