{
  "type": "Feature",
  "properties": {
    "iso:country":"US",
    "sg:address":"4410 NW 74th Ave",
    "sg:city":"Miami",
    "sg:classifiers":[
        {
            "category":"Building & Trades",
            "subcategory":"Construction",
            "type":"Services"
        }
    ],
    "sg:phone":"+1 305 640 0313",
    "sg:postcode":"33166",
    "sg:province":"FL",
    "sg:tags":[
        "contractor"
    ],
    "wof:name":"Stone Exclusive",
    "wof:placetype":"venue"
},
  "geometry": {"coordinates":[-80.317395,25.814575],"type":"Point"}
}