{
  "type": "Feature",
  "properties": {
    "addr:full":"8401 Southside Blvd Jacksonville FL 32256",
    "addr:housenumber":"8401",
    "addr:postcode":"32256",
    "addr:street":"Southside Blvd",
    "iso:country":"US",
    "sg:address":"8401 Southside Blvd",
    "sg:city":"Jacksonville",
    "sg:classifiers":[
        {
            "category":"Banks & Credit Unions",
            "subcategory":"Bank",
            "type":"Services"
        }
    ],
    "sg:phone":"+1 904 646 0250",
    "sg:postcode":"32256",
    "sg:province":"FL",
    "sg:tags":[
        "loan",
        "real estate"
    ],
    "wof:name":"Custom Mortgage Svc",
    "wof:placetype":"venue"
},
  "geometry": {"coordinates":[-81.55192700000001,30.218532],"type":"Point"}
}