{
  "type": "Feature",
  "properties": {
    "iso:country":"US",
    "sg:address":"3164 W Pembroke Rd",
    "sg:city":"Hallandale",
    "sg:classifiers":[
        {
            "category":"Manufacturing",
            "subcategory":"Furniture",
            "type":"Manufacturing & Wholesale Goods"
        }
    ],
    "sg:phone":"+1 954 987 0287",
    "sg:postcode":"33009",
    "sg:province":"FL",
    "sg:tags":[
        "mfg"
    ],
    "wof:name":"Ciccone Cabinets and Interiors",
    "wof:placetype":"venue"
},
  "geometry": {"coordinates":[-80.169724,25.996132],"type":"Point"}
}