{
  "type": "Feature",
  "properties": {
    "iso:country":"US",
    "sg:address":"3444 McCrory Pl",
    "sg:city":"Orlando",
    "sg:classifiers":[
        {
            "category":"Professional",
            "type":"Services"
        }
    ],
    "sg:phone":"+1 407 877 0224",
    "sg:postcode":"32803",
    "sg:province":"FL",
    "sg:tags":[
        "establishment"
    ],
    "wof:name":"Buyer's Protection Plan",
    "wof:placetype":"venue"
},
  "geometry": {"coordinates":[-81.34186800000001,28.559209],"type":"Point"}
}