{
  "type": "Feature",
  "properties": {
    "iso:country":"US",
    "sg:address":"440 E 6th Ave",
    "sg:city":"Mount Dora",
    "sg:classifiers":[
        {
            "category":"Organizations",
            "subcategory":"Religious Organization",
            "type":"Services"
        }
    ],
    "sg:phone":"+1 352 383 2005",
    "sg:postcode":"32757",
    "sg:province":"FL",
    "wof:name":"First Untd Methdst Church Mt",
    "wof:placetype":"venue"
},
  "geometry": {"coordinates":[-81.641378,28.801379],"type":"Point"}
}