{
  "type": "Feature",
  "properties": {
    "addr:full":"8153 SW 163rd Ave Miami FL 33193",
    "addr:housenumber":"8153",
    "addr:postcode":"33193",
    "addr:street":"Sw 163Rd Ave",
    "iso:country":"US",
    "sg:address":"8153 SW 163rd Ave",
    "sg:city":"Miami",
    "sg:classifiers":[
        {
            "category":"Professional",
            "type":"Services"
        }
    ],
    "sg:phone":"+1 305 752 9706",
    "sg:postcode":"33193",
    "sg:province":"FL",
    "wof:name":"Clara Abril Ocampo",
    "wof:placetype":"venue"
},
  "geometry": {"coordinates":[-80.4564,25.689061],"type":"Point"}
}