{
  "type": "Feature",
  "properties": {
    "addr:full":"2023 Reston Cir Royal Palm Beach FL 33411",
    "addr:housenumber":"2023",
    "addr:postcode":"33411",
    "addr:street":"Reston Cir",
    "iso:country":"US",
    "sg:address":"2023 Reston Cir",
    "sg:city":"Royal Palm Beach",
    "sg:classifiers":[
        {
            "category":"Professional",
            "subcategory":"Employment Agencies",
            "type":"Services"
        }
    ],
    "sg:phone":"+1 561 784 0463",
    "sg:postcode":"33411",
    "sg:province":"FL",
    "sg:tags":[
        "opportunity"
    ],
    "wof:name":"Reliant Executive Staffing",
    "wof:placetype":"venue"
},
  "geometry": {"coordinates":[-80.233423,26.714792],"type":"Point"}
}