{
  "type": "Feature",
  "properties": {
    "iso:country":"US",
    "sg:address":"3444 Foxwood Blvd",
    "sg:city":"Zephyrhills",
    "sg:classifiers":[
        {
            "category":"Retail",
            "subcategory":"Repair Shop",
            "type":"Services"
        },
        {
            "category":"Retail",
            "subcategory":"Auto Repair",
            "type":"Services"
        }
    ],
    "sg:phone":"+1 813 783 2812",
    "sg:postcode":"33543",
    "sg:province":"FL",
    "sg:tags":[
        "mobile",
        "home",
        "truck"
    ],
    "wof:name":"Big Man's Diesel Repair",
    "wof:placetype":"venue"
},
  "geometry": {"coordinates":[-82.291848,28.206584],"type":"Point"}
}