{
  "type": "Feature",
  "properties": {
    "iso:country":"US",
    "sg:address":"605 S Boulevard",
    "sg:city":"Tampa",
    "sg:classifiers":[
        {
            "category":"Social Services",
            "type":"Services"
        },
        {
            "category":"Organizations",
            "subcategory":"Community Association",
            "type":"Services"
        }
    ],
    "sg:phone":"+1 813 636 9600",
    "sg:postcode":"33606",
    "sg:province":"FL",
    "sg:website":"http://www.voa.org",
    "wof:name":"Volunteers of America",
    "wof:placetype":"venue"
},
  "geometry": {"coordinates":[-82.468616,27.938529],"type":"Point"}
}