{
  "type": "Feature",
  "properties": {
    "iso:country":"US",
    "sg:address":"2201 NW 102nd Pl",
    "sg:city":"Doral",
    "sg:classifiers":[
        {
            "category":"Shopping",
            "type":"Retail Goods"
        }
    ],
    "sg:phone":"+1 305 994 7558",
    "sg:postcode":"33172",
    "sg:province":"FL",
    "sg:tags":[
        "cosmetic",
        "perfume"
    ],
    "wof:name":"Alban Muller Intl",
    "wof:placetype":"venue"
},
  "geometry": {"coordinates":[-80.362612,25.796014],"type":"Point"}
}