{
  "type": "Feature",
  "properties": {
    "addr:full":"4997 S Orange Ave Orlando FL 32806",
    "addr:housenumber":"4997",
    "addr:postcode":"32806",
    "addr:street":"S Orange Ave",
    "iso:country":"US",
    "sg:address":"4997 S Orange Ave",
    "sg:city":"Orlando",
    "sg:classifiers":[
        {
            "category":"Personal",
            "subcategory":"Beauty Salon",
            "type":"Services"
        }
    ],
    "sg:phone":"+1 407 286 4857",
    "sg:postcode":"32806",
    "sg:province":"FL",
    "sg:tags":[
        "hair",
        "stylist"
    ],
    "sg:website":"http://www.trueenvysalon.com",
    "wof:name":"True Envy Salon",
    "wof:placetype":"venue"
},
  "geometry": {"coordinates":[-81.373198,28.489243],"type":"Point"}
}