{
  "type": "Feature",
  "properties": {
    "addr:full":"900 SW Pine Island Rd Cape Coral FL 33991",
    "addr:housenumber":"900",
    "addr:postcode":"33991",
    "addr:street":"Sw Pine Island Rd",
    "iso:country":"US",
    "sg:address":"900 SW Pine Island Rd",
    "sg:city":"Cape Coral",
    "sg:classifiers":[
        {
            "category":"Arena",
            "subcategory":"Sports Club",
            "type":"Entertainment"
        }
    ],
    "sg:phone":"+1 239 458 2055",
    "sg:postcode":"33991",
    "sg:province":"FL",
    "sg:tags":[
        "martial art"
    ],
    "wof:name":"Kobayashi Dojo Inc",
    "wof:placetype":"venue"
},
  "geometry": {"coordinates":[-81.996173,26.64241],"type":"Point"}
}