{
  "type": "Feature",
  "properties": {
    "iso:country":"US",
    "sg:address":"238 SE Verada Ave",
    "sg:city":"Port Saint Lucie",
    "sg:classifiers":[
        {
            "category":"Building & Trades",
            "subcategory":"Construction",
            "type":"Services"
        }
    ],
    "sg:phone":"+1 772 785 5114",
    "sg:postcode":"34983",
    "sg:province":"FL",
    "sg:tags":[
        "contractor"
    ],
    "wof:name":"Bob Rice Construction",
    "wof:placetype":"venue"
},
  "geometry": {"coordinates":[-80.341312,27.314864],"type":"Point"}
}