{
  "type": "Feature",
  "properties": {
    "iso:country":"US",
    "sg:address":"520 NW 165th St",
    "sg:city":"Miami",
    "sg:classifiers":[
        {
            "category":"Professional",
            "subcategory":"Accounting & Tax Preparation",
            "type":"Services"
        }
    ],
    "sg:phone":"+1 305 949 4695",
    "sg:postcode":"33169",
    "sg:province":"FL",
    "sg:tags":[
        "accountant"
    ],
    "wof:name":"Marc S Einbinder CPA",
    "wof:placetype":"venue"
},
  "geometry": {"coordinates":[-80.205889,25.925971],"type":"Point"}
}