{
  "type": "Feature",
  "properties": {
    "iso:country":"US",
    "sg:address":"5633 West Rd",
    "sg:city":"Lake Worth",
    "sg:classifiers":[
        {
            "category":"Home & Garden",
            "subcategory":"Furniture",
            "type":"Retail Goods"
        }
    ],
    "sg:phone":"+1 561 278 1024",
    "sg:postcode":"33463",
    "sg:province":"FL",
    "wof:name":"Angelico Fray Studio",
    "wof:placetype":"venue"
},
  "geometry": {"coordinates":[-80.118138,26.594639],"type":"Point"}
}