{
  "type": "Feature",
  "properties": {
    "addr:full":"1288 NW 103rd St Miami FL 33147",
    "addr:housenumber":"1288",
    "addr:postcode":"33147",
    "addr:street":"Nw 103Rd St",
    "iso:country":"US",
    "sg:address":"1288 NW 103rd St",
    "sg:city":"Miami",
    "sg:classifiers":[
        {
            "category":"Building & Trades",
            "subcategory":"Landscaping Services",
            "type":"Services"
        }
    ],
    "sg:phone":"+1 305 694 9285",
    "sg:postcode":"33147",
    "sg:province":"FL",
    "wof:name":"Norberto Pagan",
    "wof:placetype":"venue"
},
  "geometry": {"coordinates":[-80.21846600000001,25.868835],"type":"Point"}
}