{
  "type": "Feature",
  "properties": {
    "iso:country":"US",
    "sg:address":"101 1st St SE",
    "sg:city":"Fort Meade",
    "sg:classifiers":[
        {
            "category":"Banks & Credit Unions",
            "subcategory":"Financial Services",
            "type":"Services"
        }
    ],
    "sg:phone":"+1 863 285 9585",
    "sg:postcode":"33841",
    "sg:province":"FL",
    "sg:tags":[
        "trust",
        "management"
    ],
    "wof:name":"Etoile Altman Trust",
    "wof:placetype":"venue"
},
  "geometry": {"coordinates":[-81.798733,27.750722],"type":"Point"}
}