{
  "type": "Feature",
  "properties": {
    "iso:country":"US",
    "sg:address":"5120 3rd Ave W",
    "sg:city":"Bradenton",
    "sg:classifiers":[
        {
            "category":"Professional",
            "subcategory":"Detective & Security Services",
            "type":"Services"
        },
        {
            "category":"Manufacturing",
            "subcategory":"Electronics",
            "type":"Manufacturing & Wholesale Goods"
        }
    ],
    "sg:phone":"+1 941 343 3103",
    "sg:postcode":"34209",
    "sg:province":"FL",
    "sg:tags":[
        "control",
        "equipment-wholesale",
        "monitoring",
        "system",
        "manufacturer"
    ],
    "wof:name":"Adt Security Svc",
    "wof:placetype":"venue"
},
  "geometry": {"coordinates":[-82.612264,27.497514],"type":"Point"}
}