{
  "type": "Feature",
  "properties": {
    "iso:country":"US",
    "sg:address":"2272 W 78th St",
    "sg:city":"Hialeah",
    "sg:classifiers":[
        {
            "category":"Professional",
            "subcategory":"Engineering",
            "type":"Services"
        }
    ],
    "sg:phone":"+1 305 820 9777",
    "sg:postcode":"33016",
    "sg:province":"FL",
    "sg:tags":[
        "doctor"
    ],
    "wof:name":"Medical Care Solutions Inc",
    "wof:placetype":"venue"
},
  "geometry": {"coordinates":[-80.329498,25.8934],"type":"Point"}
}