{
  "type": "Feature",
  "properties": {
    "addr:full":"601 N Flamingo Rd Pembroke Pines FL 33028",
    "addr:housenumber":"601",
    "addr:postcode":"33028",
    "addr:street":"N Flamingo Rd",
    "iso:country":"US",
    "sg:address":"601 N Flamingo Rd",
    "sg:city":"Pembroke Pines",
    "sg:classifiers":[
        {
            "category":"Health Services",
            "subcategory":"Doctor",
            "type":"Services"
        }
    ],
    "sg:phone":"+1 954 524 0860",
    "sg:postcode":"33028",
    "sg:province":"FL",
    "sg:tags":[
        "physician",
        "surgeon"
    ],
    "wof:name":"Ali Bazzi MD",
    "wof:placetype":"venue"
},
  "geometry": {"coordinates":[-80.312077,26.012604],"type":"Point"}
}