{
  "type": "Feature",
  "properties": {
    "iso:country":"US",
    "sg:address":"2431 Aloma Ave",
    "sg:city":"Winter Park",
    "sg:classifiers":[
        {
            "category":"Professional",
            "subcategory":"Lawyer & Legal Services",
            "type":"Services"
        }
    ],
    "sg:phone":"+1 407 677 4644",
    "sg:postcode":"32792",
    "sg:province":"FL",
    "sg:tags":[
        "attorney"
    ],
    "wof:name":"Maximilian Smith Law Office",
    "wof:placetype":"venue"
},
  "geometry": {"coordinates":[-81.320427,28.601476],"type":"Point"}
}