{
  "type": "Feature",
  "properties": {
    "iso:country":"US",
    "sg:address":"780 Florida Central Pkwy",
    "sg:city":"Longwood",
    "sg:classifiers":[
        {
            "category":"Communications",
            "subcategory":"Film & Video Production",
            "type":"Services"
        }
    ],
    "sg:phone":"+1 407 767 9774",
    "sg:postcode":"32750",
    "sg:province":"FL",
    "sg:tags":[
        "motion",
        "picture"
    ],
    "wof:name":"Visual Impact Communications",
    "wof:placetype":"venue"
},
  "geometry": {"coordinates":[-81.353523,28.691166],"type":"Point"}
}