{
  "type": "Feature",
  "properties": {
    "iso:country":"US",
    "sg:address":"612 17th St E",
    "sg:city":"Palmetto",
    "sg:classifiers":[
        {
            "category":"Building & Trades",
            "subcategory":"Plumbing",
            "type":"Services"
        }
    ],
    "sg:phone":"+1 941 729 1500",
    "sg:postcode":"34221",
    "sg:province":"FL",
    "sg:tags":[
        "conditioning",
        "air",
        "system",
        "contractor"
    ],
    "wof:name":"Snyder Air Conditioning & Htg",
    "wof:placetype":"venue"
},
  "geometry": {"coordinates":[-82.550738,27.528487],"type":"Point"}
}