{
  "type": "Feature",
  "properties": {
    "iso:country":"US",
    "sg:address":"8801 Lake Placid Dr E",
    "sg:city":"Jacksonville",
    "sg:classifiers":[
        {
            "category":"Education",
            "subcategory":"School",
            "type":"Public Place"
        }
    ],
    "sg:phone":"+1 904 924 3027",
    "sg:postcode":"32208",
    "sg:province":"FL",
    "wof:name":"Martin Luther King Elementary",
    "wof:placetype":"venue"
},
  "geometry": {"coordinates":[-81.711056,30.400918],"type":"Point"}
}