{
  "type": "Feature",
  "properties": {
    "addr:full":"1820 E End Ave Winter Park FL 32789",
    "addr:housenumber":"1820",
    "addr:postcode":"32789",
    "addr:street":"E End Ave",
    "iso:country":"US",
    "sg:address":"1820 E End Ave",
    "sg:city":"Winter Park",
    "sg:classifiers":[
        {
            "category":"Organizations",
            "subcategory":"Religious Organization",
            "type":"Services"
        }
    ],
    "sg:phone":"+1 407 644 5442",
    "sg:postcode":"32789",
    "sg:province":"FL",
    "sg:tags":[
        "church"
    ],
    "wof:name":"Maranatha Fellowship Church",
    "wof:placetype":"venue"
},
  "geometry": {"coordinates":[-81.344098,28.568575],"type":"Point"}
}