{
  "type": "Feature",
  "properties": {
    "addr:full":"840 Beach Dr NE St Petersburg FL 33701",
    "addr:housenumber":"840",
    "addr:postcode":"33701",
    "addr:street":"Beach Dr Ne",
    "iso:country":"US",
    "sg:address":"840 Beach Dr NE",
    "sg:city":"St Petersburg",
    "sg:classifiers":[
        {
            "category":"Education",
            "subcategory":"Special Training",
            "type":"Public Place"
        }
    ],
    "sg:phone":"+1 727 823 6400",
    "sg:postcode":"33701",
    "sg:province":"FL",
    "sg:tags":[
        "program"
    ],
    "wof:name":"Global Leadership Training Inc",
    "wof:placetype":"venue"
},
  "geometry": {"coordinates":[-82.629486,27.780962],"type":"Point"}
}