{
  "type": "Feature",
  "properties": {
    "iso:country":"US",
    "sg:address":"1541 N Powerline Rd",
    "sg:city":"Pompano Beach",
    "sg:classifiers":[
        {
            "category":"Freight",
            "type":"Transportation"
        }
    ],
    "sg:phone":"+1 954 956 9794",
    "sg:postcode":"33069",
    "sg:province":"FL",
    "sg:tags":[
        "storage",
        "portable"
    ],
    "wof:name":"Door To Door Storage Inc",
    "wof:placetype":"venue"
},
  "geometry": {"coordinates":[-80.151597,26.247357],"type":"Point"}
}