{
  "type": "Feature",
  "properties": {
    "iso:country":"US",
    "sg:address":"2565 Mayport Rd",
    "sg:city":"Atlantic Beach",
    "sg:classifiers":[
        {
            "category":"Restaurant",
            "type":"Food & Drink"
        }
    ],
    "sg:menulink":"http://www.allmenus.com/fl/jacksonville/207000-sonic/menu/",
    "sg:phone":"+1 904 242 9011",
    "sg:postcode":"32233",
    "sg:province":"FL",
    "sg:tags":[
        "burger",
        "american"
    ],
    "wof:name":"Sonic",
    "wof:placetype":"venue"
},
  "geometry": {"coordinates":[-81.412757,30.357665],"type":"Point"}
}