{
  "type": "Feature",
  "properties": {
    "addr:full":"10505 SE 25th Ave Ocala FL 34480",
    "addr:housenumber":"10505",
    "addr:postcode":"34480",
    "addr:street":"Se 25Th Ave",
    "iso:country":"US",
    "sg:address":"10505 SE 25th Ave",
    "sg:city":"Ocala",
    "sg:classifiers":[
        {
            "category":"Building & Trades",
            "subcategory":"Landscaping Services",
            "type":"Services"
        }
    ],
    "sg:phone":"+1 352 307 6315",
    "sg:postcode":"34480",
    "sg:province":"FL",
    "sg:tags":[
        "landscape",
        "contractor"
    ],
    "wof:name":"Baker, Mary Landscaping",
    "wof:placetype":"venue"
},
  "geometry": {"coordinates":[-82.102929,29.069819],"type":"Point"}
}