{
  "type": "Feature",
  "properties": {
    "addr:full":"8807 NW 146th Ln Hialeah FL 33018",
    "addr:housenumber":"8807",
    "addr:postcode":"33018",
    "addr:street":"Nw 146Th Ln",
    "iso:country":"US",
    "sg:address":"8807 NW 146th Ln",
    "sg:city":"Hialeah",
    "sg:classifiers":[
        {
            "category":"Autos & Motor Vehicles",
            "subcategory":"Automobile Sales",
            "type":"Retail Goods"
        }
    ],
    "sg:phone":"+1 305 821 1775",
    "sg:postcode":"33018",
    "sg:province":"FL",
    "wof:name":"Quality Export Inc",
    "wof:placetype":"venue"
},
  "geometry": {"coordinates":[-80.34136700000001,25.906661],"type":"Point"}
}