{
  "type": "Feature",
  "properties": {
    "addr:full":"38005 Arbor Ridge Dr Zephyrhills FL 33540",
    "addr:housenumber":"38005",
    "addr:postcode":"33540",
    "addr:street":"Arbor Ridge Dr",
    "iso:country":"US",
    "sg:address":"38005 Arbor Ridge Dr",
    "sg:city":"Zephyrhills",
    "sg:classifiers":[
        {
            "category":"Health Services",
            "subcategory":"Health Practitioner",
            "type":"Services"
        }
    ],
    "sg:phone":"+1 813 779 4044",
    "sg:postcode":"33540",
    "sg:province":"FL",
    "sg:tags":[
        "psychologist"
    ],
    "wof:name":"America's Sleep Network Inc",
    "wof:placetype":"venue"
},
  "geometry": {"coordinates":[-82.188031,28.259646],"type":"Point"}
}