{
  "type": "Feature",
  "properties": {
    "iso:country":"US",
    "sg:address":"1958 State Rd 44",
    "sg:city":"New Smyrna Beach",
    "sg:classifiers":[
        {
            "category":"Shopping",
            "type":"Retail Goods"
        }
    ],
    "sg:phone":"+1 386 423 8723",
    "sg:postcode":"32168",
    "sg:province":"FL",
    "sg:tags":[
        "pet",
        "shop",
        "merchandise",
        "animal"
    ],
    "wof:name":"Critter's Corner Pet Shop",
    "wof:placetype":"venue"
},
  "geometry": {"coordinates":[-80.946817,29.013483],"type":"Point"}
}