{
  "type": "Feature",
  "properties": {
    "addr:full":"354 Bridle Path Ln Ormond Beach FL 32174",
    "addr:housenumber":"354",
    "addr:postcode":"32174",
    "addr:street":"Bridle Path Ln",
    "iso:country":"US",
    "sg:address":"354 Bridle Path Ln",
    "sg:city":"Ormond Beach",
    "sg:classifiers":[
        {
            "category":"Building & Trades",
            "subcategory":"Landscaping Services",
            "type":"Services"
        }
    ],
    "sg:phone":"+1 386 677 8847",
    "sg:postcode":"32174",
    "sg:province":"FL",
    "wof:name":"A1a Lawn & Landscaping",
    "wof:placetype":"venue"
},
  "geometry": {"coordinates":[-81.216701,29.265844],"type":"Point"}
}