{
  "type": "Feature",
  "properties": {
    "iso:country":"US",
    "sg:address":"9750 Seminole Blvd",
    "sg:city":"Seminole",
    "sg:classifiers":[
        {
            "category":"Wholesale",
            "subcategory":"Hardware",
            "type":"Manufacturing & Wholesale Goods"
        }
    ],
    "sg:phone":"+1 727 399 1500",
    "sg:postcode":"33772",
    "sg:province":"FL",
    "sg:tags":[
        "equipment",
        "energy",
        "solar"
    ],
    "wof:name":"L C United Technology Corp",
    "wof:placetype":"venue"
},
  "geometry": {"coordinates":[-82.787111,27.861229],"type":"Point"}
}