{
  "type": "Feature",
  "properties": {
    "addr:full":"7001 S Dixie Hwy West Palm Beach FL 33405",
    "addr:housenumber":"7001",
    "addr:postcode":"33405",
    "addr:street":"S Dixie Hwy",
    "iso:country":"US",
    "sg:address":"7001 S Dixie Hwy",
    "sg:city":"West Palm Beach",
    "sg:classifiers":[
        {
            "category":"Social Services",
            "subcategory":"Adult Care",
            "type":"Services"
        }
    ],
    "sg:phone":"+1 561 588 7677",
    "sg:postcode":"33405",
    "sg:province":"FL",
    "sg:tags":[
        "home",
        "residential"
    ],
    "wof:name":"Southwinds A Zikna Assisted",
    "wof:placetype":"venue"
},
  "geometry": {"coordinates":[-80.05607999999999,26.652859],"type":"Point"}
}