{
  "type": "Feature",
  "properties": {
    "iso:country":"US",
    "sg:address":"7818 Country Run Pkwy",
    "sg:city":"Orlando",
    "sg:classifiers":[
        {
            "category":"Building & Trades",
            "subcategory":"Cleaning & Sanitation",
            "type":"Services"
        }
    ],
    "sg:phone":"+1 407 230 4313",
    "sg:postcode":"32818",
    "sg:province":"FL",
    "sg:tags":[
        "commercial",
        "up",
        "clean"
    ],
    "wof:name":"Committed To Cleaning Corp",
    "wof:placetype":"venue"
},
  "geometry": {"coordinates":[-81.489638,28.594661],"type":"Point"}
}