{
  "type": "Feature",
  "properties": {
    "addr:full":"12224 Beaver Run Dr Jacksonville FL 32225",
    "addr:housenumber":"12224",
    "addr:postcode":"32225",
    "addr:street":"Beaver Run Dr",
    "iso:country":"US",
    "sg:address":"12224 Beaver Run Dr",
    "sg:city":"Jacksonville",
    "sg:classifiers":[
        {
            "category":"Professional",
            "subcategory":"Art Services",
            "type":"Services"
        }
    ],
    "sg:phone":"+1 904 545 8541",
    "sg:postcode":"32225",
    "sg:province":"FL",
    "sg:tags":[
        "communications",
        "engineering",
        "cad",
        "design",
        "drafting"
    ],
    "wof:name":"Pics Cadd",
    "wof:placetype":"venue"
},
  "geometry": {"coordinates":[-81.494502,30.35435],"type":"Point"}
}