{
  "type": "Feature",
  "properties": {
    "iso:country":"US",
    "sg:address":"4431 Gunn Hwy",
    "sg:city":"Tampa",
    "sg:classifiers":[
        {
            "category":"Recreation",
            "type":"Entertainment"
        }
    ],
    "sg:phone":"+1 813 936 8855",
    "sg:postcode":"33618",
    "sg:province":"FL",
    "sg:tags":[
        "martial",
        "arts",
        "instruction"
    ],
    "wof:name":"Clear's Silat Of Carrollwood",
    "wof:placetype":"venue"
},
  "geometry": {"coordinates":[-82.517034,28.047118],"type":"Point"}
}