{
  "type": "Feature",
  "properties": {
    "addr:full":"3611 1st St Bradenton FL 34208",
    "addr:housenumber":"3611",
    "addr:postcode":"34208",
    "addr:street":"1St St",
    "iso:country":"US",
    "sg:address":"3611 1st St",
    "sg:city":"Bradenton",
    "sg:classifiers":[
        {
            "category":"Shopping",
            "subcategory":"Optical Goods",
            "type":"Retail Goods"
        }
    ],
    "sg:phone":"+1 941 747 5567",
    "sg:postcode":"34208",
    "sg:province":"FL",
    "sg:tags":[
        "optician"
    ],
    "wof:name":"Desoto Vision Ctr",
    "wof:placetype":"venue"
},
  "geometry": {"coordinates":[-82.56285699999999,27.469701],"type":"Point"}
}