{
  "type": "Feature",
  "properties": {
    "iso:country":"US",
    "sg:address":"3956 Maxine St",
    "sg:city":"Fort Myers",
    "sg:classifiers":[
        {
            "category":"Shopping",
            "subcategory":"Gifts & Souvenirs",
            "type":"Retail Goods"
        }
    ],
    "sg:phone":"+1 239 466 0643",
    "sg:postcode":"33901",
    "sg:province":"FL",
    "wof:name":"My Kell Angel OS",
    "wof:placetype":"venue"
},
  "geometry": {"coordinates":[-81.88045700000001,26.605439],"type":"Point"}
}