{
  "type": "Feature",
  "properties": {
    "iso:country":"US",
    "sg:address":"18011 S Tamiami Trl",
    "sg:city":"Fort Myers",
    "sg:classifiers":[
        {
            "category":"Food & Beverages",
            "subcategory":"Groceries & Convenience Stores",
            "type":"Retail Goods"
        }
    ],
    "sg:phone":"+1 239 415 0007",
    "sg:postcode":"33908",
    "sg:province":"FL",
    "sg:tags":[
        "grocer"
    ],
    "wof:name":"Winn-Dixie",
    "wof:placetype":"venue"
},
  "geometry": {"coordinates":[-81.83823700000001,26.477843],"type":"Point"}
}