{
  "type": "Feature",
  "properties": {
    "iso:country":"US",
    "sg:address":"35 San Marco Ave",
    "sg:city":"Saint Augustine",
    "sg:classifiers":[
        {
            "category":"Manufacturing",
            "subcategory":"Printing",
            "type":"Manufacturing & Wholesale Goods"
        }
    ],
    "sg:phone":"+1 904 829 1952",
    "sg:postcode":"32084",
    "sg:province":"FL",
    "sg:tags":[
        "cards",
        "greeting",
        "mfg"
    ],
    "wof:name":"Eastern Sun Printworks",
    "wof:placetype":"venue"
},
  "geometry": {"coordinates":[-81.315044,29.90039],"type":"Point"}
}