{
  "type": "Feature",
  "properties": {
    "addr:full":"2262 NW 20th St Miami FL 33142",
    "addr:housenumber":"2262",
    "addr:postcode":"33142",
    "addr:street":"Nw 20Th St",
    "iso:country":"US",
    "sg:address":"2262 NW 20th St",
    "sg:city":"Miami",
    "sg:classifiers":[
        {
            "category":"Shopping",
            "subcategory":"Clothing, Apparel, & Fashions",
            "type":"Retail Goods"
        }
    ],
    "sg:phone":"+1 305 635 5580",
    "sg:postcode":"33142",
    "sg:province":"FL",
    "sg:tags":[
        "clothing",
        "store"
    ],
    "wof:name":"Red Rose Ltd",
    "wof:placetype":"venue"
},
  "geometry": {"coordinates":[-80.233142,25.794476],"type":"Point"}
}