{
  "type": "Feature",
  "properties": {
    "iso:country":"US",
    "sg:address":"8720 Beach Blvd",
    "sg:city":"Jacksonville",
    "sg:classifiers":[
        {
            "category":"Shopping",
            "subcategory":"Bicycles & Sporting Goods",
            "type":"Retail Goods"
        }
    ],
    "sg:phone":"+1 904 641 7955",
    "sg:postcode":"32216",
    "sg:province":"FL",
    "sg:tags":[
        "apparel",
        "bowling",
        "accessory"
    ],
    "wof:name":"Perfect Fit Pro Shop",
    "wof:placetype":"venue"
},
  "geometry": {"coordinates":[-81.56088800000001,30.28661],"type":"Point"}
}