{
  "type": "Feature",
  "properties": {
    "addr:full":"10410 S Ocean Dr Jensen Beach FL 34957",
    "addr:housenumber":"10410",
    "addr:postcode":"34957",
    "addr:street":"S Ocean Dr",
    "iso:country":"US",
    "sg:address":"10410 S Ocean Dr",
    "sg:city":"Jensen Beach",
    "sg:classifiers":[
        {
            "category":"Organizations",
            "subcategory":"Community Association",
            "type":"Services"
        }
    ],
    "sg:phone":"+1 772 229 0357",
    "sg:postcode":"34957",
    "sg:province":"FL",
    "wof:name":"Hutchnson Island CLB Cndo Assn",
    "wof:placetype":"venue"
},
  "geometry": {"coordinates":[-80.205789,27.27255],"type":"Point"}
}