{
  "type": "Feature",
  "properties": {
    "iso:country":"US",
    "sg:address":"1804 Van Buren St",
    "sg:city":"Hollywood",
    "sg:classifiers":[
        {
            "category":"Organizations",
            "subcategory":"Religious Organization",
            "type":"Services"
        }
    ],
    "sg:phone":"+1 954 927 1773",
    "sg:postcode":"33020",
    "sg:province":"FL",
    "wof:name":"First United Methodist Church",
    "wof:placetype":"venue"
},
  "geometry": {"coordinates":[-80.14487099999999,26.009546],"type":"Point"}
}