{
  "type": "Feature",
  "properties": {
    "addr:full":"445 Stan Dr Melbourne FL 32904",
    "addr:housenumber":"445",
    "addr:postcode":"32904",
    "addr:street":"Stan Dr",
    "iso:country":"US",
    "sg:address":"445 Stan Dr",
    "sg:city":"Melbourne",
    "sg:classifiers":[
        {
            "category":"Recreation",
            "type":"Entertainment"
        },
        {
            "category":"Professional",
            "subcategory":"Employment Agencies",
            "type":"Services"
        }
    ],
    "sg:phone":"+1 321 725 1661",
    "sg:postcode":"32904",
    "sg:province":"FL",
    "sg:tags":[
        "instruction",
        "help",
        "gymnastic",
        "supply"
    ],
    "wof:name":"All Star Cheerleading Academy",
    "wof:placetype":"venue"
},
  "geometry": {"coordinates":[-80.692521,28.102078],"type":"Point"}
}