{
  "type": "Feature",
  "properties": {
    "iso:country":"US",
    "sg:address":"2388 NW 150th St",
    "sg:city":"Opa Locka",
    "sg:classifiers":[
        {
            "category":"Wholesale",
            "subcategory":"Electrical",
            "type":"Manufacturing & Wholesale Goods"
        }
    ],
    "sg:phone":"+1 305 685 6588",
    "sg:postcode":"33054",
    "sg:province":"FL",
    "sg:tags":[
        "equipment",
        "fixture",
        "lighting"
    ],
    "sg:website":"www.luraline.com",
    "wof:name":"Luraline Products Co",
    "wof:placetype":"venue"
},
  "geometry": {"coordinates":[-80.240303,25.911301],"type":"Point"}
}