{
  "type": "Feature",
  "properties": {
    "iso:country":"US",
    "sg:address":"7950 NW 155th St",
    "sg:city":"Hialeah",
    "sg:classifiers":[
        {
            "category":"Real Estate",
            "subcategory":"Real Estate Services",
            "type":"Services"
        }
    ],
    "sg:phone":"+1 305 779 1079",
    "sg:postcode":"33016",
    "sg:province":"FL",
    "sg:tags":[
        "company",
        "title"
    ],
    "wof:name":"Fortuny & Riveiro",
    "wof:placetype":"venue"
},
  "geometry": {"coordinates":[-80.333096,25.9146],"type":"Point"}
}