{
  "type": "Feature",
  "properties": {
    "addr:full":"4250 Palm Beach Blvd Fort Myers FL 33905",
    "addr:housenumber":"4250",
    "addr:postcode":"33905",
    "addr:street":"Palm Beach Blvd",
    "iso:country":"US",
    "sg:address":"4250 Palm Beach Blvd",
    "sg:city":"Fort Myers",
    "sg:classifiers":[
        {
            "category":"Building & Trades",
            "subcategory":"Construction",
            "type":"Services"
        }
    ],
    "sg:phone":"+1 239 693 2585",
    "sg:postcode":"33905",
    "sg:province":"FL",
    "sg:tags":[
        "general",
        "contractor"
    ],
    "wof:name":"J & S Development Svc Inc",
    "wof:placetype":"venue"
},
  "geometry": {"coordinates":[-81.827781,26.667686],"type":"Point"}
}