{
  "type": "Feature",
  "properties": {
    "addr:full":"201 Driggs Dr Winter Park FL 32792",
    "addr:housenumber":"201",
    "addr:postcode":"32792",
    "addr:street":"Driggs Dr",
    "iso:country":"US",
    "sg:address":"201 Driggs Dr",
    "sg:city":"Winter Park",
    "sg:classifiers":[
        {
            "category":"Building & Trades",
            "subcategory":"Locksmith",
            "type":"Services"
        }
    ],
    "sg:phone":"+1 407 702 1674",
    "sg:postcode":"32792",
    "sg:province":"FL",
    "sg:tags":[
        "key"
    ],
    "wof:name":"1 Action 7 Day Lock Service",
    "wof:placetype":"venue"
},
  "geometry": {"coordinates":[-81.304194,28.59733],"type":"Point"}
}