{
  "type": "Feature",
  "properties": {
    "addr:full":"2372 SW Island Creek Trl Palm City FL 34990",
    "addr:housenumber":"2372",
    "addr:postcode":"34990",
    "addr:street":"Sw Island Creek Trl",
    "iso:country":"US",
    "sg:address":"2372 SW Island Creek Trl",
    "sg:city":"Palm City",
    "sg:classifiers":[
        {
            "category":"Building & Trades",
            "subcategory":"Construction",
            "type":"Services"
        }
    ],
    "sg:phone":"+1 772 221 1008",
    "sg:postcode":"34990",
    "sg:province":"FL",
    "sg:tags":[
        "contractor"
    ],
    "sg:website":"www.symphonybuilders.net",
    "wof:name":"Symphony Builders At Palm Cove",
    "wof:placetype":"venue"
},
  "geometry": {"coordinates":[-80.285389,27.200172],"type":"Point"}
}