{
  "type": "Feature",
  "properties": {
    "addr:full":"31431 Walton Heath Ave Sorrento FL 32776",
    "addr:housenumber":"31431",
    "addr:postcode":"32776",
    "addr:street":"Walton Heath Ave",
    "iso:country":"US",
    "sg:address":"31431 Walton Heath Ave",
    "sg:city":"Sorrento",
    "sg:classifiers":[
        {
            "category":"Government",
            "subcategory":"Fire Station",
            "type":"Public Place"
        }
    ],
    "sg:phone":"+1 352 383 2844",
    "sg:postcode":"32776",
    "sg:province":"FL",
    "sg:tags":[
        "protection"
    ],
    "wof:name":"Lake County Fire Station 31",
    "wof:placetype":"venue"
},
  "geometry": {"coordinates":[-81.535963,28.806947],"type":"Point"}
}