{
  "type": "Feature",
  "properties": {
    "iso:country":"US",
    "sg:address":"9127 SW 123rd Ave Ct",
    "sg:city":"Miami",
    "sg:classifiers":[
        {
            "category":"Professional",
            "subcategory":"Computer Services",
            "type":"Services"
        }
    ],
    "sg:phone":"+1 305 274 2215",
    "sg:postcode":"33186",
    "sg:province":"FL",
    "sg:tags":[
        "prepackaged",
        "software"
    ],
    "wof:name":"Apple Polish Inc",
    "wof:placetype":"venue"
},
  "geometry": {"coordinates":[-80.39484400000001,25.682885],"type":"Point"}
}