{
  "type": "Feature",
  "properties": {
    "addr:full":"3751 NW 50 Ave Chiefland FL 32626",
    "addr:housenumber":"3751",
    "addr:postcode":"32626",
    "addr:street":"Nw 50 Ave",
    "iso:country":"US",
    "sg:address":"3751 NW 50 Ave",
    "sg:city":"Chiefland",
    "sg:classifiers":[
        {
            "category":"Farming",
            "subcategory":"Farm & Veterinary Services",
            "type":"Manufacturing & Wholesale Goods"
        }
    ],
    "sg:phone":"+1 352 493 0739",
    "sg:postcode":"32626",
    "sg:province":"FL",
    "sg:tags":[
        "preparation",
        "soil"
    ],
    "wof:name":"Spreading Oak Inc",
    "wof:placetype":"venue"
},
  "geometry": {"coordinates":[-82.85527500000001,29.383956],"type":"Point"}
}