{
  "type": "Feature",
  "properties": {
    "addr:full":"1291 SW Porter Rd Port Saint Lucie FL 34953",
    "addr:housenumber":"1291",
    "addr:postcode":"34953",
    "addr:street":"Sw Porter Rd",
    "iso:country":"US",
    "sg:address":"1291 SW Porter Rd",
    "sg:city":"Port Saint Lucie",
    "sg:classifiers":[
        {
            "category":"Home & Garden",
            "subcategory":"Building Materials",
            "type":"Retail Goods"
        }
    ],
    "sg:phone":"+1 772 336 0518",
    "sg:postcode":"34953",
    "sg:province":"FL",
    "sg:tags":[
        "product",
        "install"
    ],
    "wof:name":"St Onge Interiors",
    "wof:placetype":"venue"
},
  "geometry": {"coordinates":[-80.38681099999999,27.254205],"type":"Point"}
}