{
  "type": "Feature",
  "properties": {
    "addr:full":"2093 NE 160th St North Miami Beach FL 33162",
    "addr:housenumber":"2093",
    "addr:postcode":"33162",
    "addr:street":"Ne 160Th St",
    "iso:country":"US",
    "sg:address":"2093 NE 160th St",
    "sg:city":"North Miami Beach",
    "sg:classifiers":[
        {
            "category":"Retail",
            "subcategory":"Auto Repair",
            "type":"Services"
        }
    ],
    "sg:phone":"+1 305 947 4778",
    "sg:postcode":"33162",
    "sg:province":"FL",
    "sg:tags":[
        "body",
        "shop"
    ],
    "wof:name":"M S D Auto Body Inc",
    "wof:placetype":"venue"
},
  "geometry": {"coordinates":[-80.1567,25.9235],"type":"Point"}
}