{
  "type": "Feature",
  "properties": {
    "addr:full":"652 Welch Cswy Saint Petersburg FL 33708",
    "addr:housenumber":"652",
    "addr:postcode":"33708",
    "addr:street":"Welch Cswy",
    "iso:country":"US",
    "sg:address":"652 Welch Cswy",
    "sg:city":"Saint Petersburg",
    "sg:classifiers":[
        {
            "category":"Banks & Credit Unions",
            "subcategory":"Bank",
            "type":"Services"
        }
    ],
    "sg:phone":"+1 727 391 9703",
    "sg:postcode":"33708",
    "sg:province":"FL",
    "sg:tags":[
        "national",
        "commercial"
    ],
    "wof:name":"Citibank",
    "wof:placetype":"venue"
},
  "geometry": {"coordinates":[-82.79631999999999,27.805606],"type":"Point"}
}