{
  "type": "Feature",
  "properties": {
    "addr:full":"7830 NW 174th Ter Hialeah FL 33015",
    "addr:housenumber":"7830",
    "addr:postcode":"33015",
    "addr:street":"Nw 174Th Ter",
    "iso:country":"US",
    "sg:address":"7830 NW 174th Ter",
    "sg:city":"Hialeah",
    "sg:classifiers":[
        {
            "category":"Real Estate",
            "subcategory":"Surveying",
            "type":"Services"
        }
    ],
    "sg:phone":"+1 305 362 2742",
    "sg:postcode":"33015",
    "sg:province":"FL",
    "wof:name":"Sunshine United",
    "wof:placetype":"venue"
},
  "geometry": {"coordinates":[-80.32938,25.931943],"type":"Point"}
}