{
  "type": "Feature",
  "properties": {
    "addr:full":"578 E 9th St Hialeah FL 33010",
    "addr:housenumber":"578",
    "addr:postcode":"33010",
    "addr:street":"E 9Th St",
    "iso:country":"US",
    "sg:address":"578 E 9th St",
    "sg:city":"Hialeah",
    "sg:classifiers":[
        {
            "category":"Autos & Motor Vehicles",
            "subcategory":"Automobile Sales",
            "type":"Retail Goods"
        }
    ],
    "sg:phone":"+1 305 887 7737",
    "sg:postcode":"33010",
    "sg:province":"FL",
    "wof:name":"Tropical Auto Sales Hialeah",
    "wof:placetype":"venue"
},
  "geometry": {"coordinates":[-80.27097000000001,25.830179],"type":"Point"}
}