{
  "type": "Feature",
  "properties": {
    "addr:full":"5231 State Rd 54 New Port Richey FL 34652",
    "addr:housenumber":"5231;54",
    "addr:postcode":"34652",
    "addr:street":"State Rd",
    "iso:country":"US",
    "sg:address":"5231 State Rd 54",
    "sg:city":"New Port Richey",
    "sg:classifiers":[
        {
            "category":"Social Services",
            "subcategory":"Child Care",
            "type":"Services"
        }
    ],
    "sg:phone":"+1 727 841 7898",
    "sg:postcode":"34652",
    "sg:province":"FL",
    "sg:tags":[
        "day"
    ],
    "wof:name":"Building Blocks Preschool Chld",
    "wof:placetype":"venue"
},
  "geometry": {"coordinates":[-82.72477499999999,28.217017],"type":"Point"}
}