{
  "type": "Feature",
  "properties": {
    "addr:full":"759 SW Federal Hwy # 213 Stuart FL 34994",
    "addr:housenumber":"759",
    "addr:postcode":"34994",
    "addr:street":"Sw Federal Hwy # 213",
    "iso:country":"US",
    "sg:address":"759 SW Federal Hwy # 213",
    "sg:city":"Stuart",
    "sg:classifiers":[
        {
            "category":"Professional",
            "subcategory":"Business Services",
            "type":"Services"
        }
    ],
    "sg:phone":"+1 772 334 5551",
    "sg:postcode":"34994",
    "sg:province":"FL",
    "sg:tags":[
        "holding"
    ],
    "wof:name":"Cartagena Group Ltd",
    "wof:placetype":"venue"
},
  "geometry": {"coordinates":[-80.256339,27.193028],"type":"Point"}
}