{
  "type": "Feature",
  "properties": {
    "addr:full":"23321 Oak Cluster Dr Sorrento FL 32776",
    "addr:housenumber":"23321",
    "addr:postcode":"32776",
    "addr:street":"Oak Cluster Dr",
    "iso:country":"US",
    "sg:address":"23321 Oak Cluster Dr",
    "sg:city":"Sorrento",
    "sg:classifiers":[
        {
            "category":"Manufacturing",
            "subcategory":"Aerospace",
            "type":"Manufacturing & Wholesale Goods"
        },
        {
            "category":"Autos & Motor Vehicles",
            "subcategory":"Recreational Vehicle Sales",
            "type":"Retail Goods"
        }
    ],
    "sg:phone":"+1 352 504 4633",
    "sg:postcode":"32776",
    "sg:province":"FL",
    "sg:tags":[
        "equipment",
        "aircraft",
        "part",
        "supplies-wholesale",
        "manufacturer"
    ],
    "wof:name":"Crl",
    "wof:placetype":"venue"
},
  "geometry": {"coordinates":[-81.571018,28.821213],"type":"Point"}
}