{
  "type": "Feature",
  "properties": {
    "addr:full":"73 Commercial Blvd Naples FL 34104",
    "addr:housenumber":"73",
    "addr:postcode":"34104",
    "addr:street":"Commercial Blvd",
    "iso:country":"US",
    "sg:address":"73 Commercial Blvd",
    "sg:city":"Naples",
    "sg:classifiers":[
        {
            "category":"Retail",
            "subcategory":"Laundry & Dry Cleaning",
            "type":"Services"
        }
    ],
    "sg:phone":"+1 239 775 5110",
    "sg:postcode":"34104",
    "sg:province":"FL",
    "sg:tags":[
        "cleaners"
    ],
    "sg:website":"www.platinumdrycleaners.com",
    "wof:name":"Platinum Coast Dry Cleaners",
    "wof:placetype":"venue"
},
  "geometry": {"coordinates":[-81.752658,26.155435],"type":"Point"}
}