{
  "type": "Feature",
  "properties": {
    "iso:country":"US",
    "sg:address":"3333 Clark Rd",
    "sg:city":"Sarasota",
    "sg:classifiers":[
        {
            "category":"Health Services",
            "subcategory":"Clinic",
            "type":"Services"
        }
    ],
    "sg:phone":"+1 941 927 1199",
    "sg:postcode":"34231",
    "sg:province":"FL",
    "sg:tags":[
        "home"
    ],
    "wof:name":"Visiting Nurses Assn Inc",
    "wof:placetype":"venue"
},
  "geometry": {"coordinates":[-82.50191700000001,27.269306],"type":"Point"}
}