{
  "type": "Feature",
  "properties": {
    "addr:full":"5901 Tampa Shores Blvd Tampa FL 33615",
    "addr:housenumber":"5901",
    "addr:postcode":"33615",
    "addr:street":"Tampa Shores Blvd",
    "iso:country":"US",
    "sg:address":"5901 Tampa Shores Blvd",
    "sg:city":"Tampa",
    "sg:classifiers":[
        {
            "category":"Freight",
            "type":"Transportation"
        }
    ],
    "sg:phone":"+1 727 423 6649",
    "sg:postcode":"33615",
    "sg:province":"FL",
    "sg:tags":[
        "delivery",
        "furniture"
    ],
    "wof:name":"Excel Delivery Service",
    "wof:placetype":"venue"
},
  "geometry": {"coordinates":[-82.60615799999999,28.003767],"type":"Point"}
}