{
  "type": "Feature",
  "properties": {
    "iso:country":"US",
    "sg:address":"9107 NW 105th Way",
    "sg:city":"Medley",
    "sg:classifiers":[
        {
            "category":"Freight",
            "type":"Transportation"
        }
    ],
    "sg:phone":"+1 305 888 6400",
    "sg:postcode":"33178",
    "sg:province":"FL",
    "sg:website":"www.hyh-cargo.com",
    "wof:name":"HYH Intl Cargo Svc",
    "wof:placetype":"venue"
},
  "geometry": {"coordinates":[-80.345828,25.868439],"type":"Point"}
}