{
  "type": "Feature",
  "properties": {
    "iso:country":"US",
    "sg:address":"150 SE 17th St",
    "sg:city":"Ocala",
    "sg:classifiers":[
        {
            "category":"Health Services",
            "subcategory":"Clinic",
            "type":"Services"
        },
        {
            "category":"Health Services",
            "subcategory":"Medical Lab",
            "type":"Services"
        }
    ],
    "sg:phone":"+1 352 732 7584",
    "sg:postcode":"34471",
    "sg:province":"FL",
    "sg:tags":[
        "detection",
        "equipment",
        "drug"
    ],
    "wof:name":"Doctor's Laboratory Of Ocala",
    "wof:placetype":"venue"
},
  "geometry": {"coordinates":[-82.135088,29.171619],"type":"Point"}
}