{
  "type": "Feature",
  "properties": {
    "addr:full":"2655 S Le Jeune Rd Ste 904 Miami FL 33134",
    "addr:housenumber":"2655",
    "addr:postcode":"33134",
    "addr:street":"S Le Jeune Rd Ste 904",
    "iso:country":"US",
    "sg:address":"2655 S Le Jeune Rd Ste 904",
    "sg:city":"Miami",
    "sg:classifiers":[
        {
            "category":"Banks & Credit Unions",
            "subcategory":"Financial Services",
            "type":"Services"
        }
    ],
    "sg:phone":"+1 786 433 1722",
    "sg:postcode":"33134",
    "sg:province":"FL",
    "sg:tags":[
        "broker",
        "mortgage"
    ],
    "wof:name":"Acceptance Capital",
    "wof:placetype":"venue"
},
  "geometry": {"coordinates":[-80.26246399999999,25.747174],"type":"Point"}
}