{
  "type": "Feature",
  "properties": {
    "addr:full":"9909 Cove Ave Pensacola FL 32534",
    "addr:housenumber":"9909",
    "addr:postcode":"32534",
    "addr:street":"Cove Ave",
    "iso:country":"US",
    "sg:address":"9909 Cove Ave",
    "sg:city":"Pensacola",
    "sg:classifiers":[
        {
            "category":"Real Estate",
            "subcategory":"Surveying",
            "type":"Services"
        }
    ],
    "sg:phone":"+1 850 478 8783",
    "sg:postcode":"32534",
    "sg:province":"FL",
    "sg:tags":[
        "surveyor"
    ],
    "wof:name":"Southern Land Concepts",
    "wof:placetype":"venue"
},
  "geometry": {"coordinates":[-87.287713,30.540963],"type":"Point"}
}