{
  "type": "Feature",
  "properties": {
    "iso:country":"US",
    "sg:address":"6555 NW Chugwater Cir",
    "sg:city":"Port St Lucie",
    "sg:classifiers":[
        {
            "category":"Building & Trades",
            "subcategory":"Landscaping Services",
            "type":"Services"
        }
    ],
    "sg:phone":"+1 772 340 7845",
    "sg:postcode":"34983",
    "sg:province":"FL",
    "sg:tags":[
        "lawn",
        "maintenance",
        "grounds"
    ],
    "wof:name":"Mike & Nicks Lawn Svc",
    "wof:placetype":"venue"
},
  "geometry": {"coordinates":[-80.36783800000001,27.345671],"type":"Point"}
}