{
  "type": "Feature",
  "properties": {
    "iso:country":"US",
    "sg:address":"3663 Commercial Way",
    "sg:city":"Spring Hill",
    "sg:classifiers":[
        {
            "category":"Professional",
            "type":"Services"
        }
    ],
    "sg:phone":"+1 352 686 5571",
    "sg:postcode":"34606",
    "sg:province":"FL",
    "wof:name":"Gulfstream Internet Svc & Web",
    "wof:placetype":"venue"
},
  "geometry": {"coordinates":[-82.601995,28.488521],"type":"Point"}
}