{
  "type": "Feature",
  "properties": {
    "addr:full":"8916 N 56th St Tampa FL 33617",
    "addr:housenumber":"8916",
    "addr:postcode":"33617",
    "addr:street":"N 56Th St",
    "iso:country":"US",
    "sg:address":"8916 N 56th St",
    "sg:city":"Tampa",
    "sg:classifiers":[
        {
            "category":"Recreation",
            "type":"Entertainment"
        }
    ],
    "sg:phone":"+1 813 988 3349",
    "sg:postcode":"33617",
    "sg:province":"FL",
    "sg:tags":[
        "martial",
        "arts",
        "instruction"
    ],
    "wof:name":"Traditional Tae KWON Do Ctr",
    "wof:placetype":"venue"
},
  "geometry": {"coordinates":[-82.393539,28.031166],"type":"Point"}
}