{
  "type": "Feature",
  "properties": {
    "iso:country":"US",
    "sg:address":"6901 22nd Ave N",
    "sg:city":"Saint Petersburg",
    "sg:classifiers":[
        {
            "category":"Shopping",
            "type":"Retail Goods"
        }
    ],
    "sg:phone":"+1 727 384 0613",
    "sg:postcode":"33710",
    "sg:province":"FL",
    "sg:tags":[
        "sunglasses",
        "accessory"
    ],
    "wof:name":"Sunglass Hut 731",
    "wof:placetype":"venue"
},
  "geometry": {"coordinates":[-82.735962,27.791873],"type":"Point"}
}