{
  "type": "Feature",
  "properties": {
    "addr:full":"13922 SW 102nd Ter Miami FL 33186",
    "addr:housenumber":"13922",
    "addr:postcode":"33186",
    "addr:street":"Sw 102Nd Ter",
    "iso:country":"US",
    "sg:address":"13922 SW 102nd Ter",
    "sg:city":"Miami",
    "sg:classifiers":[
        {
            "category":"Wholesale",
            "subcategory":"Sporting Goods",
            "type":"Manufacturing & Wholesale Goods"
        }
    ],
    "sg:phone":"+1 305 385 7846",
    "sg:postcode":"33186",
    "sg:province":"FL",
    "wof:name":"X Sports Exports Inc",
    "wof:placetype":"venue"
},
  "geometry": {"coordinates":[-80.42036899999999,25.672652],"type":"Point"}
}