{
  "type": "Feature",
  "properties": {
    "iso:country":"US",
    "sg:address":"3049 Alhambra St ",
    "sg:city":"Fort Lauderdale",
    "sg:classifiers":[
        {
            "category":"Cafe",
            "type":"Food & Drink"
        },
        {
            "category":"Restaurant",
            "type":"Food & Drink"
        }
    ],
    "sg:menulink":"http://www.allmenus.com/fl/fort-lauderdale/16240-casablanca-cafe/menu/",
    "sg:phone":"+1 954 764 3500",
    "sg:postcode":"33304",
    "sg:province":"FL",
    "sg:tags":[
        "soup",
        "seafood",
        "american",
        "salad"
    ],
    "wof:name":"Casablanca Cafe",
    "wof:placetype":"venue"
},
  "geometry": {"coordinates":[-80.104086,26.125176],"type":"Point"}
}