{
  "type": "Feature",
  "properties": {
    "iso:country":"US",
    "sg:address":"1450 W 38th Pl",
    "sg:city":"Hialeah",
    "sg:classifiers":[
        {
            "category":"Manufacturing",
            "subcategory":"Retail Goods",
            "type":"Manufacturing & Wholesale Goods"
        }
    ],
    "sg:phone":"+1 305 828 1091",
    "sg:postcode":"33012",
    "sg:province":"FL",
    "sg:tags":[
        "product",
        "mfg"
    ],
    "wof:name":"Puerto & Assoc",
    "wof:placetype":"venue"
},
  "geometry": {"coordinates":[-80.31365,25.856602],"type":"Point"}
}