{
  "type": "Feature",
  "properties": {
    "addr:full":"2100 N University Dr Sunrise FL 33322",
    "addr:housenumber":"2100",
    "addr:postcode":"33322",
    "addr:street":"N University Dr",
    "iso:country":"US",
    "sg:address":"2100 N University Dr",
    "sg:city":"Sunrise",
    "sg:classifiers":[
        {
            "category":"Restaurant",
            "type":"Food & Drink"
        }
    ],
    "sg:phone":"+1 954 748 5660",
    "sg:postcode":"33322",
    "sg:province":"FL",
    "wof:name":"Udipi Cafe",
    "wof:placetype":"venue"
},
  "geometry": {"coordinates":[-80.256964,26.151478],"type":"Point"}
}