{
  "type": "Feature",
  "properties": {
    "addr:full":"2326 Hedgegate Ct Orlando FL 32828",
    "addr:housenumber":"2326",
    "addr:postcode":"32828",
    "addr:street":"Hedgegate Ct",
    "iso:country":"US",
    "sg:address":"2326 Hedgegate Ct",
    "sg:city":"Orlando",
    "sg:classifiers":[
        {
            "category":"Restaurant",
            "type":"Food & Drink"
        }
    ],
    "sg:phone":"+1 407 658 1218",
    "sg:postcode":"32828",
    "sg:province":"FL",
    "sg:tags":[
        "eating"
    ],
    "wof:name":"A Catered Affair Stoneybrook",
    "wof:placetype":"venue"
},
  "geometry": {"coordinates":[-81.16016,28.52078],"type":"Point"}
}