{
  "type": "Feature",
  "properties": {
    "addr:full":"2699 Collins Ave Ste 151 Miami Beach FL 33140",
    "addr:housenumber":"2699",
    "addr:postcode":"33140",
    "addr:street":"Collins Ave Ste 151",
    "iso:country":"US",
    "sg:address":"2699 Collins Ave Ste 151",
    "sg:city":"Miami Beach",
    "sg:classifiers":[
        {
            "category":"Communications",
            "subcategory":"Television Station",
            "type":"Services"
        }
    ],
    "sg:phone":"+1 305 531 6630",
    "sg:postcode":"33140",
    "sg:province":"FL",
    "wof:name":"Children's Tennis Network Inc",
    "wof:placetype":"venue"
},
  "geometry": {"coordinates":[-80.12550400000001,25.803801],"type":"Point"}
}