{
  "type": "Feature",
  "properties": {
    "iso:country":"US",
    "sg:address":"2699 Collins Ave Ste 151",
    "sg:city":"Miami Beach",
    "sg:classifiers":[
        {
            "category":"Communications",
            "subcategory":"Television Station",
            "type":"Services"
        }
    ],
    "sg:phone":"+1 305 531 6630",
    "sg:postcode":"33140",
    "sg:province":"FL",
    "wof:name":"Children's Tennis Network Inc",
    "wof:placetype":"venue"
},
  "geometry": {"coordinates":[-80.12550400000001,25.803801],"type":"Point"}
}