{
  "type": "Feature",
  "properties": {
    "iso:country":"US",
    "sg:address":"9117 SW 151st Ct",
    "sg:city":"Miami",
    "sg:classifiers":[
        {
            "category":"Building & Trades",
            "subcategory":"Electrical",
            "type":"Services"
        }
    ],
    "sg:phone":"+1 305 385 6347",
    "sg:postcode":"33196",
    "sg:province":"FL",
    "sg:tags":[
        "engineering",
        "electrical"
    ],
    "wof:name":"Florida Star Electric",
    "wof:placetype":"venue"
},
  "geometry": {"coordinates":[-80.4405,25.681084],"type":"Point"}
}