{
  "type": "Feature",
  "properties": {
    "iso:country":"US",
    "sg:address":"3510 NW 35th Ave",
    "sg:city":"Miami",
    "sg:classifiers":[
        {
            "category":"Retail",
            "subcategory":"Auto Repair",
            "type":"Services"
        }
    ],
    "sg:phone":"+1 305 635 7073",
    "sg:postcode":"33142",
    "sg:province":"FL",
    "sg:tags":[
        "repairing",
        "automobile"
    ],
    "wof:name":"Frank's Car Repair",
    "wof:placetype":"venue"
},
  "geometry": {"coordinates":[-80.252498,25.808151],"type":"Point"}
}