{
  "type": "Feature",
  "properties": {
    "addr:full":"2485 Dothan Ave Spring Hill FL 34609",
    "addr:postcode":"2485;34609",
    "addr:street":"Dothan Ave",
    "iso:country":"US",
    "sg:address":"2485 Dothan Ave",
    "sg:city":"Spring Hill",
    "sg:classifiers":[
        {
            "category":"Health Services",
            "subcategory":"Doctor",
            "type":"Services"
        }
    ],
    "sg:phone":"+1 352 860 2034",
    "sg:postcode":"34609",
    "sg:province":"FL",
    "sg:tags":[
        "medical"
    ],
    "wof:name":"Stanley P Kokocki MD",
    "wof:placetype":"venue"
},
  "geometry": {"coordinates":[-82.492574,28.473237],"type":"Point"}
}