{
  "type": "Feature",
  "properties": {
    "iso:country":"US",
    "sg:address":"25 W New Haven Ave",
    "sg:city":"Melbourne",
    "sg:classifiers":[
        {
            "category":"Personal",
            "type":"Services"
        }
    ],
    "sg:phone":"+1 321 728 2870",
    "sg:postcode":"32901",
    "sg:province":"FL",
    "sg:tags":[
        "therapist",
        "massage"
    ],
    "wof:name":"New Life Massage",
    "wof:placetype":"venue"
},
  "geometry": {"coordinates":[-80.621759,28.078626],"type":"Point"}
}