{
  "type": "Feature",
  "properties": {
    "iso:country":"US",
    "sg:address":"200 Helms Dr",
    "sg:city":"Interlachen",
    "sg:classifiers":[
        {
            "category":"Building & Trades",
            "subcategory":"Construction",
            "type":"Services"
        }
    ],
    "sg:phone":"+1 386 684 0967",
    "sg:postcode":"32148",
    "sg:province":"FL",
    "sg:tags":[
        "contractor"
    ],
    "wof:name":"Thomas Gore Drywall",
    "wof:placetype":"venue"
},
  "geometry": {"coordinates":[-81.864745,29.676529],"type":"Point"}
}