{
  "type": "Feature",
  "properties": {
    "addr:full":"322 Manatee Ln Tarpon Springs FL 34689",
    "addr:housenumber":"322",
    "addr:postcode":"34689",
    "addr:street":"Manatee Ln",
    "iso:country":"US",
    "sg:address":"322 Manatee Ln",
    "sg:city":"Tarpon Springs",
    "sg:classifiers":[
        {
            "category":"Shopping",
            "type":"Retail Goods"
        }
    ],
    "sg:phone":"+1 727 736 3001",
    "sg:postcode":"34689",
    "sg:province":"FL",
    "sg:tags":[
        "art",
        "traveling",
        "gallery"
    ],
    "wof:name":"Art For Charity Inc",
    "wof:placetype":"venue"
},
  "geometry": {"coordinates":[-82.76098399999999,28.140298],"type":"Point"}
}