{
  "type": "Feature",
  "properties": {
    "iso:country":"US",
    "sg:address":"945 Sunrise Rd",
    "sg:city":"Venice",
    "sg:classifiers":[
        {
            "category":"Manufacturing",
            "subcategory":"Building Materials",
            "type":"Manufacturing & Wholesale Goods"
        }
    ],
    "sg:phone":"+1 941 716 3985",
    "sg:postcode":"34293",
    "sg:province":"FL",
    "sg:tags":[
        "mfg"
    ],
    "wof:name":"Steve Breedlove",
    "wof:placetype":"venue"
},
  "geometry": {"coordinates":[-82.414688,27.040081],"type":"Point"}
}