{
  "type": "Feature",
  "properties": {
    "addr:full":"4 Old Kings Rd N Palm Coast FL 32137",
    "addr:housenumber":"4",
    "addr:postcode":"32137",
    "addr:street":"Old Kings Rd N",
    "iso:country":"US",
    "sg:address":"4 Old Kings Rd N",
    "sg:city":"Palm Coast",
    "sg:classifiers":[
        {
            "category":"Health Services",
            "subcategory":"Doctor",
            "type":"Services"
        }
    ],
    "sg:phone":"+1 386 445 6677",
    "sg:postcode":"32137",
    "sg:province":"FL",
    "sg:tags":[
        "dentist"
    ],
    "wof:name":"Dorne Rockey Secunda & Magee",
    "wof:placetype":"venue"
},
  "geometry": {"coordinates":[-81.23224999999999,29.581447],"type":"Point"}
}