{
  "type": "Feature",
  "properties": {
    "iso:country":"US",
    "sg:address":"13917 Lynmar Blvd",
    "sg:city":"Tampa",
    "sg:classifiers":[
        {
            "category":"Shopping",
            "type":"Retail Goods"
        },
        {
            "category":"Home & Garden",
            "subcategory":"Furniture",
            "type":"Retail Goods"
        }
    ],
    "sg:phone":"+1 813 864 1260",
    "sg:postcode":"33626",
    "sg:province":"FL",
    "sg:tags":[
        "merchandise",
        "store"
    ],
    "wof:name":"Stafford Demarco",
    "wof:placetype":"venue"
},
  "geometry": {"coordinates":[-82.63270900000001,28.06534],"type":"Point"}
}