{
  "type": "Feature",
  "properties": {
    "addr:full":"5430 Military Trl Jupiter FL 33458",
    "addr:housenumber":"5430",
    "addr:postcode":"33458",
    "addr:street":"Military Trl",
    "iso:country":"US",
    "sg:address":"5430 Military Trl",
    "sg:city":"Jupiter",
    "sg:classifiers":[
        {
            "category":"Food & Beverages",
            "subcategory":"Bakery",
            "type":"Retail Goods"
        }
    ],
    "sg:phone":"+1 561 624 9884",
    "sg:postcode":"33458",
    "sg:province":"FL",
    "sg:tags":[
        "bagel"
    ],
    "wof:name":"Bagel Boyz",
    "wof:placetype":"venue"
},
  "geometry": {"coordinates":[-80.10261300000001,26.907675],"type":"Point"}
}