{
  "type": "Feature",
  "properties": {
    "iso:country":"US",
    "sg:address":"811 SW 122nd Ave",
    "sg:city":"Miami",
    "sg:classifiers":[
        {
            "category":"Restaurant",
            "type":"Food & Drink"
        }
    ],
    "sg:phone":"+1 305 223 2285",
    "sg:postcode":"33184",
    "sg:province":"FL",
    "sg:tags":[
        "parlor",
        "ice",
        "cream"
    ],
    "wof:name":"Carvel Ice Cream Bakery",
    "wof:placetype":"venue"
},
  "geometry": {"coordinates":[-80.392602,25.758839],"type":"Point"}
}