{
  "type": "Feature",
  "properties": {
    "iso:country":"US",
    "sg:address":"2235 N Commerce Pkwy",
    "sg:city":"Weston",
    "sg:classifiers":[
        {
            "category":"Health Services",
            "subcategory":"Doctor",
            "type":"Services"
        }
    ],
    "sg:phone":"+1 954 389 2700",
    "sg:postcode":"33326",
    "sg:province":"FL",
    "sg:tags":[
        "physician",
        "surgeon"
    ],
    "wof:name":"Southeast Perinatal Assoc",
    "wof:placetype":"venue"
},
  "geometry": {"coordinates":[-80.365548,26.095625],"type":"Point"}
}