{
  "type": "Feature",
  "properties": {
    "iso:country":"US",
    "sg:address":"603 N 19th St",
    "sg:city":"Tampa",
    "sg:classifiers":[
        {
            "category":"Wholesale",
            "subcategory":"Metals & Minerals",
            "type":"Manufacturing & Wholesale Goods"
        }
    ],
    "sg:phone":"+1 813 247 2094",
    "sg:postcode":"33605",
    "sg:province":"FL",
    "sg:tags":[
        "center"
    ],
    "wof:name":"Elite Sales Inc",
    "wof:placetype":"venue"
},
  "geometry": {"coordinates":[-82.438007,27.954943],"type":"Point"}
}