{
  "type": "Feature",
  "properties": {
    "addr:full":"3560 SW 123rd Ct Miami FL 33175",
    "addr:housenumber":"3560",
    "addr:postcode":"33175",
    "addr:street":"Sw 123Rd Ct",
    "iso:country":"US",
    "sg:address":"3560 SW 123rd Ct",
    "sg:city":"Miami",
    "sg:classifiers":[
        {
            "category":"Health Services",
            "subcategory":"Doctor",
            "type":"Services"
        }
    ],
    "sg:phone":"+1 305 223 7280",
    "sg:postcode":"33175",
    "sg:province":"FL",
    "sg:tags":[
        "medical"
    ],
    "wof:name":"Mario A Pascual MD PA",
    "wof:placetype":"venue"
},
  "geometry": {"coordinates":[-80.394621,25.734709],"type":"Point"}
}