{
  "type": "Feature",
  "properties": {
    "iso:country":"US",
    "sg:address":"65th Street and Collins ave Miami Beach",
    "sg:city":"Miami Beach",
    "sg:classifiers":[
        {
            "category":"Travel",
            "subcategory":"Hotels & Motels",
            "type":"Entertainment"
        }
    ],
    "sg:phone":"+1 786 346 8080",
    "sg:postcode":"33141",
    "sg:province":"FL",
    "sg:website":"www.mimobeach.com",
    "wof:name":"MIMOBEACH \u00a0VACATION RENTAL",
    "wof:placetype":"venue"
},
  "geometry": {"coordinates":[-80.12027,25.848402],"type":"Point"}
}