{
  "type": "Feature",
  "properties": {
    "addr:full":"153 Harbor Dr Key Biscayne FL 33149",
    "addr:housenumber":"153",
    "addr:postcode":"33149",
    "addr:street":"Harbor Dr",
    "iso:country":"US",
    "sg:address":"153 Harbor Dr",
    "sg:city":"Key Biscayne",
    "sg:classifiers":[
        {
            "category":"Professional",
            "type":"Services"
        }
    ],
    "sg:phone":"+1 305 684 9095",
    "sg:postcode":"33149",
    "sg:province":"FL",
    "sg:tags":[
        "establishment"
    ],
    "wof:name":"Le Grange & Le Grange",
    "wof:placetype":"venue"
},
  "geometry": {"coordinates":[-80.16542699999999,25.699246],"type":"Point"}
}