{
  "type": "Feature",
  "properties": {
    "addr:full":"195 W Haines Blvd Lake Alfred FL 33850",
    "addr:housenumber":"195",
    "addr:postcode":"33850",
    "addr:street":"W Haines Blvd Lake",
    "iso:country":"US",
    "sg:address":"195 W Haines Blvd",
    "sg:city":"Lake Alfred",
    "sg:classifiers":[
        {
            "category":"Government",
            "subcategory":"Post Office",
            "type":"Public Place"
        }
    ],
    "sg:phone":"+1 863 956 4664",
    "sg:postcode":"33850",
    "sg:province":"FL",
    "sg:tags":[
        "postal",
        "us"
    ],
    "wof:name":"US Post Office",
    "wof:placetype":"venue"
},
  "geometry": {"coordinates":[-81.73093799999999,28.091837],"type":"Point"}
}