{
  "type": "Feature",
  "properties": {
    "iso:country":"US",
    "sg:address":"11100 NW 27th St",
    "sg:city":"Doral",
    "sg:classifiers":[
        {
            "category":"Education",
            "subcategory":"School",
            "type":"Public Place"
        }
    ],
    "sg:phone":"+1 305 418 2303",
    "sg:postcode":"33172",
    "sg:province":"FL",
    "sg:tags":[
        "high",
        "middle"
    ],
    "wof:name":"Doral Academy High School",
    "wof:placetype":"venue"
},
  "geometry": {"coordinates":[-80.37490099999999,25.798901],"type":"Point"}
}