{
  "type": "Feature",
  "properties": {
    "addr:full":"17724 Pines Blvd Hollywood FL 33029",
    "addr:housenumber":"17724",
    "addr:postcode":"33029",
    "addr:street":"Pines Blvd",
    "iso:country":"US",
    "sg:address":"17724 Pines Blvd",
    "sg:city":"Hollywood",
    "sg:classifiers":[
        {
            "category":"Restaurant",
            "type":"Food & Drink"
        }
    ],
    "sg:phone":"+1 954 704 2529",
    "sg:postcode":"33029",
    "sg:province":"FL",
    "sg:tags":[
        "eating"
    ],
    "wof:name":"Subway",
    "wof:placetype":"venue"
},
  "geometry": {"coordinates":[-80.382942,26.007652],"type":"Point"}
}