{
  "type": "Feature",
  "properties": {
    "iso:country":"US",
    "sg:address":"15777 SW 146th Terr.",
    "sg:city":"Miami",
    "sg:classifiers":[
        {
            "category":"Professional",
            "subcategory":"Advertising",
            "type":"Services"
        },
        {
            "category":"Professional",
            "subcategory":"Business Services",
            "type":"Services"
        },
        {
            "category":"Taxi",
            "type":"Transportation"
        },
        {
            "category":"Government",
            "subcategory":"Post Office",
            "type":"Public Place"
        }
    ],
    "sg:phone":"+1 786 797 8570",
    "sg:postcode":"33196",
    "sg:province":"FL",
    "sg:tags":[
        "delivery",
        "service-circular",
        "courier",
        "shipping",
        "distributing",
        "sample",
        "mail"
    ],
    "wof:name":"Fox Courier Services",
    "wof:placetype":"venue"
},
  "geometry": {"coordinates":[-80.449077,25.630678],"type":"Point"}
}