{
  "type": "Feature",
  "properties": {
    "iso:country":"US",
    "sg:address":"1514 E 11th St",
    "sg:city":"Panama City",
    "sg:classifiers":[
        {
            "category":"Building & Trades",
            "subcategory":"Construction",
            "type":"Services"
        }
    ],
    "sg:phone":"+1 850 784 6809",
    "sg:postcode":"32401",
    "sg:province":"FL",
    "sg:tags":[
        "designer",
        "marine",
        "contractor"
    ],
    "wof:name":"Grayson Marine Svc",
    "wof:placetype":"venue"
},
  "geometry": {"coordinates":[-85.639054,30.167643],"type":"Point"}
}