{
  "type": "Feature",
  "properties": {
    "addr:full":"250 Valencia Ave Miami FL 33134",
    "addr:housenumber":"250",
    "addr:postcode":"33134",
    "addr:street":"Valencia Ave",
    "iso:country":"US",
    "sg:address":"250 Valencia Ave",
    "sg:city":"Miami",
    "sg:classifiers":[
        {
            "category":"Shopping",
            "subcategory":"Used Merchandise",
            "type":"Retail Goods"
        }
    ],
    "sg:phone":"+1 305 448 6779",
    "sg:postcode":"33134",
    "sg:province":"FL",
    "wof:name":"Valerio Antiques Inc",
    "wof:placetype":"venue"
},
  "geometry": {"coordinates":[-80.259687,25.747742],"type":"Point"}
}