{
  "type": "Feature",
  "properties": {
    "iso:country":"US",
    "sg:address":"526 Oakfield Dr",
    "sg:city":"Brandon",
    "sg:classifiers":[
        {
            "category":"Deli",
            "type":"Food & Drink"
        },
        {
            "category":"Cafe",
            "type":"Food & Drink"
        }
    ],
    "sg:menulink":"http://www.allmenus.com/fl/brandon/33957-oakfield-cafe--catering-co/menu/",
    "sg:phone":"+1 813 681 5359",
    "sg:postcode":"33511",
    "sg:province":"FL",
    "sg:tags":[
        "american"
    ],
    "wof:name":"Oakfield Cafe & Catering Co.",
    "wof:placetype":"venue"
},
  "geometry": {"coordinates":[-82.291847,27.933769],"type":"Point"}
}