{
  "type": "Feature",
  "properties": {
    "iso:country":"US",
    "sg:address":"5335 Lenox Ave",
    "sg:city":"Jacksonville",
    "sg:classifiers":[
        {
            "category":"Home & Garden",
            "subcategory":"Furniture",
            "type":"Retail Goods"
        }
    ],
    "sg:phone":"+1 904 783 2215",
    "sg:postcode":"32205",
    "sg:province":"FL",
    "wof:name":"Factory Mattress Outlet",
    "wof:placetype":"venue"
},
  "geometry": {"coordinates":[-81.737645,30.310986],"type":"Point"}
}