{
  "type": "Feature",
  "properties": {
    "addr:full":"25 Belleview Blvd Belleair FL 33756",
    "addr:housenumber":"25",
    "addr:postcode":"33756",
    "addr:street":"Belleview Blvd",
    "iso:country":"US",
    "sg:address":"25 Belleview Blvd",
    "sg:city":"Belleair",
    "sg:classifiers":[
        {
            "category":"Building & Trades",
            "subcategory":"Equipment Rental",
            "type":"Services"
        },
        {
            "category":"Shopping",
            "subcategory":"Computers & Home Electronics",
            "type":"Retail Goods"
        }
    ],
    "sg:phone":"+1 727 446 3674",
    "sg:postcode":"33756",
    "sg:province":"FL",
    "sg:tags":[
        "stereo",
        "leasing",
        "video",
        "audio",
        "equipment-renting",
        "audio-visual"
    ],
    "sg:website":"http://www.avservicescorp.com",
    "wof:name":"Audio Visual Services Group, Inc.",
    "wof:placetype":"venue"
},
  "geometry": {"coordinates":[-82.809898,27.94511],"type":"Point"}
}