{
  "type": "Feature",
  "properties": {
    "iso:country":"US",
    "sg:address":"5881 NW 151st St",
    "sg:city":"Hialeah",
    "sg:classifiers":[
        {
            "category":"Building & Trades",
            "subcategory":"Construction",
            "type":"Services"
        }
    ],
    "sg:phone":"+1 305 512 6027",
    "sg:postcode":"33014",
    "sg:province":"FL",
    "sg:tags":[
        "home",
        "builder"
    ],
    "wof:name":"Safont Homes Corp",
    "wof:placetype":"venue"
},
  "geometry": {"coordinates":[-80.2948,25.910852],"type":"Point"}
}