{
  "type": "Feature",
  "properties": {
    "addr:full":"1823 Bel Ct Indialantic FL 32903",
    "addr:housenumber":"1823",
    "addr:postcode":"32903",
    "addr:street":"Bel Ct",
    "iso:country":"US",
    "sg:address":"1823 Bel Ct",
    "sg:city":"Indialantic",
    "sg:classifiers":[
        {
            "category":"Professional",
            "subcategory":"Art Services",
            "type":"Services"
        }
    ],
    "sg:phone":"+1 321 984 8403",
    "sg:postcode":"32903",
    "sg:province":"FL",
    "sg:tags":[
        "photographer"
    ],
    "sg:website":"www.jeffhuntphotography.com",
    "wof:name":"Jeff Hunt Photography",
    "wof:placetype":"venue"
},
  "geometry": {"coordinates":[-80.57361299999999,28.109484],"type":"Point"}
}