{
  "type": "Feature",
  "properties": {
    "iso:country":"US",
    "sg:address":"1777 Blount Rd",
    "sg:city":"Pompano Beach",
    "sg:classifiers":[
        {
            "category":"Building & Trades",
            "subcategory":"Electrical",
            "type":"Services"
        }
    ],
    "sg:phone":"+1 954 752 5393",
    "sg:postcode":"33069",
    "sg:province":"FL",
    "sg:tags":[
        "electric",
        "contractor"
    ],
    "wof:name":"Strickland Electric",
    "wof:placetype":"venue"
},
  "geometry": {"coordinates":[-80.16389700000001,26.251382],"type":"Point"}
}