{
  "type": "Feature",
  "properties": {
    "iso:country":"US",
    "sg:address":"414 E Sample Rd",
    "sg:city":"Pompano Beach",
    "sg:classifiers":[
        {
            "category":"Wholesale",
            "subcategory":"Machinery & Supplies",
            "type":"Manufacturing & Wholesale Goods"
        }
    ],
    "sg:phone":"+1 954 782 8311",
    "sg:postcode":"33064",
    "sg:province":"FL",
    "sg:tags":[
        "equipment",
        "establishment"
    ],
    "wof:name":"Bazzar Beauty Supply",
    "wof:placetype":"venue"
},
  "geometry": {"coordinates":[-80.119285,26.27509],"type":"Point"}
}