{
  "type": "Feature",
  "properties": {
    "iso:country":"US",
    "sg:address":"211 S College St",
    "sg:city":"Leesburg",
    "sg:classifiers":[
        {
            "category":"Building & Trades",
            "subcategory":"Plumbing",
            "type":"Services"
        }
    ],
    "sg:phone":"+1 352 748 2064",
    "sg:postcode":"34748",
    "sg:province":"FL",
    "sg:tags":[
        "plumber",
        "industrial",
        "contractors-commercial"
    ],
    "wof:name":"B S Plumbing Inc",
    "wof:placetype":"venue"
},
  "geometry": {"coordinates":[-81.890823,28.810033],"type":"Point"}
}