{
  "type": "Feature",
  "properties": {
    "iso:country":"US",
    "sg:address":"4348 Seagrape Dr",
    "sg:city":"Fort Lauderdale",
    "sg:classifiers":[
        {
            "category":"Shopping",
            "type":"Retail Goods"
        }
    ],
    "sg:phone":"+1 954 772 8177",
    "sg:postcode":"33308",
    "sg:province":"FL",
    "sg:tags":[
        "merchandise"
    ],
    "wof:name":"Pets Play Ground",
    "wof:placetype":"venue"
},
  "geometry": {"coordinates":[-80.098491,26.189798],"type":"Point"}
}