{
  "type": "Feature",
  "properties": {
    "addr:full":"4475 S Hopkins Ave Titusville FL 32780",
    "addr:housenumber":"4475",
    "addr:postcode":"32780",
    "addr:street":"S Hopkins Ave",
    "iso:country":"US",
    "sg:address":"4475 S Hopkins Ave",
    "sg:city":"Titusville",
    "sg:classifiers":[
        {
            "category":"Shopping",
            "subcategory":"Used Merchandise",
            "type":"Retail Goods"
        },
        {
            "category":"Social Services",
            "type":"Services"
        }
    ],
    "sg:phone":"+1 321 269 3272",
    "sg:postcode":"32780",
    "sg:province":"FL",
    "sg:tags":[
        "organization",
        "welfare"
    ],
    "wof:name":"North Brevard Charities Thrift",
    "wof:placetype":"venue"
},
  "geometry": {"coordinates":[-80.80135,28.559832],"type":"Point"}
}