{
  "type": "Feature",
  "properties": {
    "addr:full":"7440 Hood St Hollywood FL 33024",
    "addr:housenumber":"7440",
    "addr:postcode":"33024",
    "addr:street":"Hood St",
    "iso:country":"US",
    "sg:address":"7440 Hood St",
    "sg:city":"Hollywood",
    "sg:classifiers":[
        {
            "category":"Building & Trades",
            "subcategory":"Landscaping Services",
            "type":"Services"
        }
    ],
    "sg:phone":"+1 954 214 6646",
    "sg:postcode":"33024",
    "sg:province":"FL",
    "wof:name":"Archie Towles Lawn Maintence",
    "wof:placetype":"venue"
},
  "geometry": {"coordinates":[-80.237855,26.031996],"type":"Point"}
}