{
  "type": "Feature",
  "properties": {
    "iso:country":"US",
    "sg:address":"3470 Adrian Ave",
    "sg:city":"Largo",
    "sg:classifiers":[
        {
            "category":"Education",
            "subcategory":"School",
            "type":"Public Place"
        }
    ],
    "sg:phone":"+1 727 584 8200",
    "sg:postcode":"33774",
    "sg:province":"FL",
    "sg:tags":[
        "k-",
        "private"
    ],
    "wof:name":"Grad Academy Inc",
    "wof:placetype":"venue"
},
  "geometry": {"coordinates":[-82.822851,27.900992],"type":"Point"}
}