{
  "type": "Feature",
  "properties": {
    "iso:country":"US",
    "sg:address":"10421 Bet Mark Rd",
    "sg:city":"Pensacola",
    "sg:classifiers":[
        {
            "category":"Retail",
            "subcategory":"Auto Repair",
            "type":"Services"
        }
    ],
    "sg:phone":"+1 850 475 1850",
    "sg:postcode":"32534",
    "sg:province":"FL",
    "sg:tags":[
        "recreational",
        "trailers-repair",
        "campers-repair",
        "vehicle"
    ],
    "wof:name":"Grace & Sons RV & Auto Repair",
    "wof:placetype":"venue"
},
  "geometry": {"coordinates":[-87.274715,30.547967],"type":"Point"}
}