{
  "type": "Feature",
  "properties": {
    "iso:country":"US",
    "sg:address":"1781 Ludlam Rd",
    "sg:city":"Miami",
    "sg:classifiers":[
        {
            "category":"Food & Beverages",
            "subcategory":"Liquor & Beverages",
            "type":"Retail Goods"
        }
    ],
    "sg:phone":"+1 305 261 4757",
    "sg:postcode":"33155",
    "sg:province":"FL",
    "sg:tags":[
        "beer",
        "spirit",
        "wine"
    ],
    "wof:name":"Cruz's Liquors",
    "wof:placetype":"venue"
},
  "geometry": {"coordinates":[-80.30349699999999,25.754499],"type":"Point"}
}