{
  "type": "Feature",
  "properties": {
    "iso:country":"US",
    "sg:address":"6299 Powers Ave",
    "sg:city":"Jacksonville",
    "sg:classifiers":[
        {
            "category":"Banks & Credit Unions",
            "subcategory":"Bank",
            "type":"Services"
        }
    ],
    "sg:phone":"+1 904 731 8086",
    "sg:postcode":"32217",
    "sg:province":"FL",
    "sg:tags":[
        "loan",
        "real estate"
    ],
    "wof:name":"Metropolitan Mortgage Sltns",
    "wof:placetype":"venue"
},
  "geometry": {"coordinates":[-81.617503,30.256854],"type":"Point"}
}