{
  "type": "Feature",
  "properties": {
    "addr:full":"2158 58th Ave Vero Beach FL 32966",
    "addr:housenumber":"2158",
    "addr:postcode":"32966",
    "addr:street":"58Th Ave",
    "iso:country":"US",
    "sg:address":"2158 58th Ave",
    "sg:city":"Vero Beach",
    "sg:classifiers":[
        {
            "category":"Banks & Credit Unions",
            "subcategory":"Bank",
            "type":"Services"
        }
    ],
    "sg:phone":"+1 772 564 9190",
    "sg:postcode":"32966",
    "sg:province":"FL",
    "sg:tags":[
        "personal",
        "institution"
    ],
    "wof:name":"Advance America",
    "wof:placetype":"venue"
},
  "geometry": {"coordinates":[-80.44647500000001,27.640841],"type":"Point"}
}