{
  "type": "Feature",
  "properties": {
    "addr:full":"123 Atlantic Dr Maitland FL 32751",
    "addr:housenumber":"123",
    "addr:postcode":"32751",
    "addr:street":"Atlantic Dr",
    "iso:country":"US",
    "sg:address":"123 Atlantic Dr",
    "sg:city":"Maitland",
    "sg:classifiers":[
        {
            "category":"Building & Trades",
            "subcategory":"Landscaping Services",
            "type":"Services"
        }
    ],
    "sg:phone":"+1 407 331 8020",
    "sg:postcode":"32751",
    "sg:province":"FL",
    "sg:tags":[
        "lawn",
        "tree"
    ],
    "sg:website":"www.davey.com",
    "wof:name":"Davey Tree & Lawn Care",
    "wof:placetype":"venue"
},
  "geometry": {"coordinates":[-81.35693499999999,28.645809],"type":"Point"}
}