{
  "type": "Feature",
  "properties": {
    "iso:country":"US",
    "sg:address":"6255 Lake Gray Blvd",
    "sg:city":"Jacksonville",
    "sg:classifiers":[
        {
            "category":"Professional",
            "type":"Services"
        }
    ],
    "sg:phone":"+1 904 777 6318",
    "sg:postcode":"32244",
    "sg:province":"FL",
    "sg:tags":[
        "establishment"
    ],
    "wof:name":"Florida Digtial Network",
    "wof:placetype":"venue"
},
  "geometry": {"coordinates":[-81.747501,30.202368],"type":"Point"}
}