{
  "type": "Feature",
  "properties": {
    "addr:full":"5980 E Co Hwy 326 Silver Springs FL 34488",
    "addr:housenumber":"5980",
    "addr:postcode":"34488",
    "addr:street":"E Co Hwy 326",
    "iso:country":"US",
    "sg:address":"5980 E Co Hwy 326",
    "sg:city":"Silver Springs",
    "sg:classifiers":[
        {
            "category":"Banks & Credit Unions",
            "subcategory":"Investment Brokerage",
            "type":"Services"
        }
    ],
    "sg:phone":"+1 352 236 6082",
    "sg:postcode":"34488",
    "sg:province":"FL",
    "sg:tags":[
        "advisory"
    ],
    "wof:name":"Ocala Financial Credit Service",
    "wof:placetype":"venue"
},
  "geometry": {"coordinates":[-82.05188699999999,29.239527],"type":"Point"}
}