{
  "type": "Feature",
  "properties": {
    "iso:country":"US",
    "sg:address":"702 W Bay St",
    "sg:city":"Tampa",
    "sg:classifiers":[
        {
            "category":"Real Estate",
            "subcategory":"Architect",
            "type":"Services"
        }
    ],
    "sg:phone":"+1 813 251 5266",
    "sg:postcode":"33606",
    "sg:province":"FL",
    "wof:name":"Earl A Quenneville Archetect",
    "wof:placetype":"venue"
},
  "geometry": {"coordinates":[-82.468602,27.937982],"type":"Point"}
}