{
  "type": "Feature",
  "properties": {
    "addr:full":"5367 Broken Pine Cir Orlando FL 32818",
    "addr:housenumber":"5367",
    "addr:postcode":"32818",
    "addr:street":"Broken Pine Cir",
    "iso:country":"US",
    "sg:address":"5367 Broken Pine Cir",
    "sg:city":"Orlando",
    "sg:classifiers":[
        {
            "category":"Social Services",
            "type":"Services"
        }
    ],
    "sg:phone":"+1 407 862 1682",
    "sg:postcode":"32818",
    "sg:province":"FL",
    "sg:tags":[
        "disaster",
        "relief"
    ],
    "wof:name":"Disaster Masters",
    "wof:placetype":"venue"
},
  "geometry": {"coordinates":[-81.478858,28.60999],"type":"Point"}
}