{
  "type": "Feature",
  "properties": {
    "iso:country":"US",
    "sg:address":"911 S Woodland Blvd",
    "sg:city":"Deland",
    "sg:classifiers":[
        {
            "category":"Home & Garden",
            "subcategory":"Furniture",
            "type":"Retail Goods"
        }
    ],
    "sg:phone":"+1 386 736 0947",
    "sg:postcode":"32720",
    "sg:province":"FL",
    "sg:tags":[
        "furniture-unfinished",
        "used",
        "merchandise"
    ],
    "wof:name":"Furniture Shoppe",
    "wof:placetype":"venue"
},
  "geometry": {"coordinates":[-81.302887,29.012859],"type":"Point"}
}