{
  "type": "Feature",
  "properties": {
    "addr:full":"324 Newburyport Ave Altamonte Springs FL 32701",
    "addr:housenumber":"324",
    "addr:postcode":"32701",
    "addr:street":"Newburyport Ave",
    "iso:country":"US",
    "sg:address":"324 Newburyport Ave",
    "sg:city":"Altamonte Springs",
    "sg:classifiers":[
        {
            "category":"Insurance",
            "subcategory":"Insurance Agent",
            "type":"Services"
        }
    ],
    "sg:phone":"+1 407 265 1010",
    "sg:postcode":"32701",
    "sg:province":"FL",
    "sg:tags":[
        "broker",
        "business"
    ],
    "wof:name":"AAA Business Brokers",
    "wof:placetype":"venue"
},
  "geometry": {"coordinates":[-81.35991,28.667324],"type":"Point"}
}