{
  "type": "Feature",
  "properties": {
    "addr:full":"5661 Harborage Dr Fort Myers FL 33908",
    "addr:housenumber":"5661",
    "addr:postcode":"33908",
    "addr:street":"Harborage Dr",
    "iso:country":"US",
    "sg:address":"5661 Harborage Dr",
    "sg:city":"Fort Myers",
    "sg:classifiers":[
        {
            "category":"Professional",
            "subcategory":"Business Services",
            "type":"Services"
        }
    ],
    "sg:phone":"+1 239 267 0428",
    "sg:postcode":"33908",
    "sg:province":"FL",
    "sg:tags":[
        "interior",
        "consultant",
        "design",
        "decorator"
    ],
    "wof:name":"Elaine Tradd Interiors",
    "wof:placetype":"venue"
},
  "geometry": {"coordinates":[-81.85172900000001,26.481106],"type":"Point"}
}