{
  "type": "Feature",
  "properties": {
    "iso:country":"US",
    "sg:address":"3767 Lake Worth Rd",
    "sg:city":"Lake Worth",
    "sg:classifiers":[
        {
            "category":"Building & Trades",
            "subcategory":"Construction",
            "type":"Services"
        }
    ],
    "sg:phone":"+1 561 582 7575",
    "sg:postcode":"33461",
    "sg:province":"FL",
    "sg:tags":[
        "house",
        "help",
        "supply"
    ],
    "wof:name":"Construct Corps",
    "wof:placetype":"venue"
},
  "geometry": {"coordinates":[-80.09979300000001,26.617802],"type":"Point"}
}