{
  "type": "Feature",
  "properties": {
    "addr:full":"163 S Cleary Rd West Palm Beach FL 33413",
    "addr:housenumber":"163",
    "addr:postcode":"33413",
    "addr:street":"S Cleary Rd",
    "iso:country":"US",
    "sg:address":"163 S Cleary Rd",
    "sg:city":"West Palm Beach",
    "sg:classifiers":[
        {
            "category":"Home & Garden",
            "subcategory":"Furniture",
            "type":"Retail Goods"
        }
    ],
    "sg:phone":"+1 561 640 2788",
    "sg:postcode":"33413",
    "sg:province":"FL",
    "sg:tags":[
        "cabinet"
    ],
    "wof:name":"GJF Enterprise",
    "wof:placetype":"venue"
},
  "geometry": {"coordinates":[-80.15747,26.676537],"type":"Point"}
}