{
  "type": "Feature",
  "properties": {
    "iso:country":"US",
    "sg:address":"6907 20th St",
    "sg:city":"Vero Beach",
    "sg:classifiers":[
        {
            "category":"Professional",
            "type":"Services"
        }
    ],
    "sg:phone":"+1 772 778 1980",
    "sg:postcode":"32966",
    "sg:province":"FL",
    "sg:tags":[
        "establishment"
    ],
    "wof:name":"Lake In The Woods Community",
    "wof:placetype":"venue"
},
  "geometry": {"coordinates":[-80.47125699999999,27.638935],"type":"Point"}
}