{
  "type": "Feature",
  "properties": {
    "iso:country":"US",
    "sg:address":"501 Flagler Ave",
    "sg:city":"New Smyrna Beach",
    "sg:classifiers":[
        {
            "category":"Shopping",
            "subcategory":"Clothing, Apparel, & Fashions",
            "type":"Retail Goods"
        }
    ],
    "sg:phone":"+1 386 428 3577",
    "sg:postcode":"32169",
    "sg:province":"FL",
    "wof:name":"Sea Fox",
    "wof:placetype":"venue"
},
  "geometry": {"coordinates":[-80.896141,29.038553],"type":"Point"}
}