{
  "type": "Feature",
  "properties": {
    "iso:country":"US",
    "sg:address":"6803 Southpoint Pkwy",
    "sg:city":"Jacksonville",
    "sg:classifiers":[
        {
            "category":"Organizations",
            "subcategory":"Non-profit Organization",
            "type":"Services"
        }
    ],
    "sg:phone":"+1 904 296 3030",
    "sg:postcode":"32216",
    "sg:province":"FL",
    "sg:tags":[
        "human"
    ],
    "wof:name":"Dreams Come True",
    "wof:placetype":"venue"
},
  "geometry": {"coordinates":[-81.591245,30.258241],"type":"Point"}
}