{
  "type": "Feature",
  "properties": {
    "iso:country":"US",
    "sg:address":"204 E Martin Luther King Jr Blvd",
    "sg:city":"Tampa",
    "sg:classifiers":[
        {
            "category":"Wholesale",
            "subcategory":"Toys & Hobbies",
            "type":"Manufacturing & Wholesale Goods"
        },
        {
            "category":"Shopping",
            "type":"Retail Goods"
        }
    ],
    "sg:phone":"+1 813 234 2264",
    "sg:postcode":"33603",
    "sg:province":"FL",
    "sg:tags":[
        "firework"
    ],
    "sg:website":"www.galaxyfireworks.com",
    "wof:name":"Galaxy Fireworks Inc",
    "wof:placetype":"venue"
},
  "geometry": {"coordinates":[-82.458393,27.981597],"type":"Point"}
}