{
  "type": "Feature",
  "properties": {
    "iso:country":"US",
    "sg:address":"14546 Bruce B Downs Blvd",
    "sg:city":"Tampa",
    "sg:classifiers":[
        {
            "category":"Retail",
            "subcategory":"Laundry & Dry Cleaning",
            "type":"Services"
        }
    ],
    "sg:phone":"+1 813 975 8500",
    "sg:postcode":"33613",
    "sg:province":"FL",
    "sg:tags":[
        "cleaners"
    ],
    "wof:name":"Snowhite Dry Cleaners Inc",
    "wof:placetype":"venue"
},
  "geometry": {"coordinates":[-82.42012800000001,28.080714],"type":"Point"}
}