{
  "type": "Feature",
  "properties": {
    "iso:country":"US",
    "sg:address":"7600 S Red Rd Ste 215",
    "sg:city":"South Miami",
    "sg:classifiers":[
        {
            "category":"Health Services",
            "subcategory":"Clinic",
            "type":"Services"
        }
    ],
    "sg:phone":"+1 305 662 2952",
    "sg:postcode":"33143",
    "sg:province":"FL",
    "sg:tags":[
        "counseling",
        "mental"
    ],
    "wof:name":"Cohen Marsha Msw",
    "wof:placetype":"venue"
},
  "geometry": {"coordinates":[-80.285301,25.700701],"type":"Point"}
}