{
  "type": "Feature",
  "properties": {
    "iso:country":"US",
    "sg:address":"2898 Dusa Dr",
    "sg:city":"Melbourne",
    "sg:classifiers":[
        {
            "category":"Home & Garden",
            "subcategory":"Home Furnishings",
            "type":"Retail Goods"
        }
    ],
    "sg:phone":"+1 321 242 8817",
    "sg:postcode":"32934",
    "sg:province":"FL",
    "wof:name":"Top Drawer Custom Closets",
    "wof:placetype":"venue"
},
  "geometry": {"coordinates":[-80.671893,28.140498],"type":"Point"}
}