{
  "type": "Feature",
  "properties": {
    "addr:full":"3173 Riverhead Dr Deltona FL 32738",
    "addr:housenumber":"3173",
    "addr:postcode":"32738",
    "addr:street":"Riverhead Dr",
    "iso:country":"US",
    "sg:address":"3173 Riverhead Dr",
    "sg:city":"Deltona",
    "sg:classifiers":[
        {
            "category":"Shopping",
            "subcategory":"Shoes",
            "type":"Retail Goods"
        }
    ],
    "sg:phone":"+1 386 789 8795",
    "sg:postcode":"32738",
    "sg:province":"FL",
    "sg:tags":[
        "clothes"
    ],
    "wof:name":"B&B Shoe Fashions",
    "wof:placetype":"venue"
},
  "geometry": {"coordinates":[-81.176586,28.941476],"type":"Point"}
}