{
  "type": "Feature",
  "properties": {
    "addr:full":"122 N Alabama Ave Deland FL 32724",
    "addr:housenumber":"122",
    "addr:postcode":"32724",
    "addr:street":"N Alabama Ave",
    "iso:country":"US",
    "sg:address":"122 N Alabama Ave",
    "sg:city":"Deland",
    "sg:classifiers":[
        {
            "category":"Health Services",
            "subcategory":"Doctor",
            "type":"Services"
        }
    ],
    "sg:phone":"+1 386 734 3574",
    "sg:postcode":"32724",
    "sg:province":"FL",
    "sg:tags":[
        "physician",
        "surgeon"
    ],
    "wof:name":"Mary S Howarth MD",
    "wof:placetype":"venue"
},
  "geometry": {"coordinates":[-81.301418,29.028609],"type":"Point"}
}