{
  "type": "Feature",
  "properties": {
    "addr:full":"402 Lake Howell Rd Maitland FL 32751",
    "addr:housenumber":"402",
    "addr:postcode":"32751",
    "addr:street":"Lake Howell Rd",
    "iso:country":"US",
    "sg:address":"402 Lake Howell Rd",
    "sg:city":"Maitland",
    "sg:classifiers":[
        {
            "category":"Health Services",
            "subcategory":"Doctor",
            "type":"Services"
        }
    ],
    "sg:phone":"+1 407 628 4312",
    "sg:postcode":"32751",
    "sg:province":"FL",
    "sg:tags":[
        "medicine",
        "physician",
        "practice",
        "surgeons",
        "family"
    ],
    "wof:name":"Maitland Family Practice",
    "wof:placetype":"venue"
},
  "geometry": {"coordinates":[-81.323898,28.6252],"type":"Point"}
}