{
  "type": "Feature",
  "properties": {
    "iso:country":"US",
    "sg:address":"311 Main St",
    "sg:city":"Alturas",
    "sg:classifiers":[
        {
            "category":"Building & Trades",
            "subcategory":"Landscaping Services",
            "type":"Services"
        }
    ],
    "sg:phone":"+1 863 581 4762",
    "sg:postcode":"33823",
    "sg:province":"FL",
    "sg:tags":[
        "lawn",
        "maintenance",
        "grounds"
    ],
    "wof:name":"We Care Lawncare Owner",
    "wof:placetype":"venue"
},
  "geometry": {"coordinates":[-81.788614,28.060734],"type":"Point"}
}