{
  "type": "Feature",
  "properties": {
    "addr:full":"1034 Ridgewood Ave Daytona Beach FL 32117",
    "addr:housenumber":"1034",
    "addr:postcode":"32117",
    "addr:street":"Ridgewood Ave",
    "iso:country":"US",
    "sg:address":"1034 Ridgewood Ave",
    "sg:city":"Daytona Beach",
    "sg:classifiers":[
        {
            "category":"Personal",
            "subcategory":"Beauty Salon",
            "type":"Services"
        }
    ],
    "sg:phone":"+1 386 253 0325",
    "sg:postcode":"32117",
    "sg:province":"FL",
    "wof:name":"Delton's Hair Design",
    "wof:placetype":"venue"
},
  "geometry": {"coordinates":[-81.041056,29.244482],"type":"Point"}
}