{
  "type": "Feature",
  "properties": {
    "iso:country":"US",
    "sg:address":"3005 Pennsylvania St",
    "sg:city":"Melbourne",
    "sg:classifiers":[
        {
            "category":"Building & Trades",
            "subcategory":"Construction",
            "type":"Services"
        }
    ],
    "sg:phone":"+1 321 768 6793",
    "sg:postcode":"32904",
    "sg:province":"FL",
    "sg:tags":[
        "house",
        "improvement",
        "home"
    ],
    "wof:name":"Randy Meier Construction Inc",
    "wof:placetype":"venue"
},
  "geometry": {"coordinates":[-80.701564,28.059025],"type":"Point"}
}