{
  "type": "Feature",
  "properties": {
    "addr:full":"11018 Glenwood Dr Pompano Beach FL 33065",
    "addr:housenumber":"11018",
    "addr:postcode":"33065",
    "addr:street":"Glenwood Dr",
    "iso:country":"US",
    "sg:address":"11018 Glenwood Dr",
    "sg:city":"Pompano Beach",
    "sg:classifiers":[
        {
            "category":"Shopping",
            "subcategory":"Music",
            "type":"Retail Goods"
        }
    ],
    "sg:phone":"+1 954 341 7091",
    "sg:postcode":"33065",
    "sg:province":"FL",
    "wof:name":"Olmec Records",
    "wof:placetype":"venue"
},
  "geometry": {"coordinates":[-80.274997,26.281022],"type":"Point"}
}