{
  "type": "Feature",
  "properties": {
    "addr:full":"201 N Kirkman Rd Orlando FL 32811",
    "addr:housenumber":"201",
    "addr:postcode":"32811",
    "addr:street":"N Kirkman Rd",
    "iso:country":"US",
    "sg:address":"201 N Kirkman Rd",
    "sg:city":"Orlando",
    "sg:classifiers":[
        {
            "category":"Professional",
            "subcategory":"Management & Consulting",
            "type":"Services"
        }
    ],
    "sg:phone":"+1 407 522 8400",
    "sg:postcode":"32811",
    "sg:province":"FL",
    "sg:tags":[
        "retail",
        "direct",
        "sales"
    ],
    "wof:name":"Down Home Shopping TV",
    "wof:placetype":"venue"
},
  "geometry": {"coordinates":[-81.458219,28.544138],"type":"Point"}
}