{
  "type": "Feature",
  "properties": {
    "addr:full":"12157 W Linebaugh Ave Tampa FL 33626",
    "addr:housenumber":"12157",
    "addr:postcode":"33626",
    "addr:street":"W Linebaugh Ave",
    "iso:country":"US",
    "sg:address":"12157 W Linebaugh Ave",
    "sg:city":"Tampa",
    "sg:classifiers":[
        {
            "category":"Travel",
            "subcategory":"Travel Agent",
            "type":"Entertainment"
        }
    ],
    "sg:phone":"+1 813 926 7503",
    "sg:postcode":"33626",
    "sg:province":"FL",
    "sg:tags":[
        "cruise"
    ],
    "wof:name":"Cruise Planners",
    "wof:placetype":"venue"
},
  "geometry": {"coordinates":[-82.62436599999999,28.055692],"type":"Point"}
}