{
  "type": "Feature",
  "properties": {
    "addr:full":"3900 NW 79th Ave Suite 604 Doral FL 33166",
    "addr:housenumber":"3900",
    "addr:postcode":"33166",
    "addr:street":"Nw 79Th Ave Suite 604",
    "iso:country":"US",
    "sg:address":"3900 NW 79th Ave Suite 604",
    "sg:city":"Doral",
    "sg:classifiers":[
        {
            "category":"Health Services",
            "subcategory":"Nursing And Care Facility",
            "type":"Services"
        },
        {
            "category":"Health Services",
            "subcategory":"Health Practitioner",
            "type":"Services"
        },
        {
            "category":"Health Services",
            "subcategory":"Hospice",
            "type":"Services"
        }
    ],
    "sg:phone":"+1 305 718 0717",
    "sg:postcode":"33166",
    "sg:province":"FL",
    "sg:tags":[
        "home",
        "eldercare-home"
    ],
    "wof:name":"Training For Life",
    "wof:placetype":"venue"
},
  "geometry": {"coordinates":[-80.32531,25.809401],"type":"Point"}
}