{
  "type": "Feature",
  "properties": {
    "iso:country":"US",
    "sg:address":"3610 Crill Ave",
    "sg:city":"Palatka",
    "sg:classifiers":[
        {
            "category":"Retail",
            "subcategory":"Auto Repair",
            "type":"Services"
        }
    ],
    "sg:phone":"+1 386 325 9477",
    "sg:postcode":"32177",
    "sg:province":"FL",
    "sg:tags":[
        "repairing",
        "automobile"
    ],
    "wof:name":"J & W Auto Repair & Easy Ride",
    "wof:placetype":"venue"
},
  "geometry": {"coordinates":[-81.67153500000001,29.641314],"type":"Point"}
}