{
  "type": "Feature",
  "properties": {
    "iso:country":"US",
    "sg:address":"2583 N Orange Blossom Trl",
    "sg:city":"Orlando",
    "sg:classifiers":[
        {
            "category":"Food & Beverages",
            "subcategory":"Meat & Fish",
            "type":"Retail Goods"
        },
        {
            "category":"Wholesale",
            "subcategory":"Meat",
            "type":"Manufacturing & Wholesale Goods"
        }
    ],
    "sg:phone":"+1 407 426 9979",
    "sg:postcode":"32804",
    "sg:province":"FL",
    "sg:tags":[
        "grocery",
        "general"
    ],
    "wof:name":"King's Choice",
    "wof:placetype":"venue"
},
  "geometry": {"coordinates":[-81.40709,28.575827],"type":"Point"}
}