{
  "type": "Feature",
  "properties": {
    "addr:full":"358 San Lorenzo Ave Coral Gables FL 33146",
    "addr:housenumber":"358",
    "addr:postcode":"33146",
    "addr:street":"San Lorenzo Ave",
    "iso:country":"US",
    "sg:address":"358 San Lorenzo Ave",
    "sg:city":"Coral Gables",
    "sg:classifiers":[
        {
            "category":"Shopping",
            "type":"Retail Goods"
        }
    ],
    "sg:phone":"+1 305 576 1355",
    "sg:postcode":"33146",
    "sg:province":"FL",
    "sg:tags":[
        "art",
        "gallery",
        "dealer"
    ],
    "sg:website":"www.adamargallery.com",
    "wof:name":"Adamar Fine Arts",
    "wof:placetype":"venue"
},
  "geometry": {"coordinates":[-80.261571,25.732051],"type":"Point"}
}