{
  "type": "Feature",
  "properties": {
    "iso:country":"US",
    "sg:address":"1006 Malibu Ct",
    "sg:city":"Venice",
    "sg:classifiers":[
        {
            "category":"Manufacturing",
            "subcategory":"Furniture",
            "type":"Manufacturing & Wholesale Goods"
        }
    ],
    "sg:phone":"+1 941 492 6260",
    "sg:postcode":"34293",
    "sg:province":"FL",
    "sg:tags":[
        "drapery",
        "mfg"
    ],
    "wof:name":"Vertical Design",
    "wof:placetype":"venue"
},
  "geometry": {"coordinates":[-82.38923,27.071311],"type":"Point"}
}