{
  "type": "Feature",
  "properties": {
    "iso:country":"US",
    "sg:address":"4219 Narcissus Ave",
    "sg:city":"Lake Worth",
    "sg:classifiers":[
        {
            "category":"Building & Trades",
            "subcategory":"Construction",
            "type":"Services"
        }
    ],
    "sg:phone":"+1 561 471 2926",
    "sg:postcode":"33461",
    "sg:province":"FL",
    "sg:tags":[
        "carpenter"
    ],
    "wof:name":"Ernesto Campos Carpenter",
    "wof:placetype":"venue"
},
  "geometry": {"coordinates":[-80.10823499999999,26.625133],"type":"Point"}
}