{
  "type": "Feature",
  "properties": {
    "addr:full":"5363 Carisbrooke Ln Tallahassee FL 32309",
    "addr:housenumber":"5363",
    "addr:postcode":"32309",
    "addr:street":"Carisbrooke Ln",
    "iso:country":"US",
    "sg:address":"5363 Carisbrooke Ln",
    "sg:city":"Tallahassee",
    "sg:classifiers":[
        {
            "category":"Building & Trades",
            "subcategory":"Construction",
            "type":"Services"
        }
    ],
    "sg:phone":"+1 850 668 5552",
    "sg:postcode":"32309",
    "sg:province":"FL",
    "sg:tags":[
        "new",
        "housing",
        "family"
    ],
    "wof:name":"Adams Contracting Service Inc",
    "wof:placetype":"venue"
},
  "geometry": {"coordinates":[-84.217727,30.541039],"type":"Point"}
}