{
  "type": "Feature",
  "properties": {
    "addr:full":"1433 NE 153rd Ter Miami FL 33162",
    "addr:housenumber":"1433",
    "addr:postcode":"33162",
    "addr:street":"Ne 153Rd Ter",
    "iso:country":"US",
    "sg:address":"1433 NE 153rd Ter",
    "sg:city":"Miami",
    "sg:classifiers":[
        {
            "category":"Building & Trades",
            "subcategory":"Landscaping Services",
            "type":"Services"
        }
    ],
    "sg:phone":"+1 305 944 8914",
    "sg:postcode":"33162",
    "sg:province":"FL",
    "wof:name":"J C Lawn Service",
    "wof:placetype":"venue"
},
  "geometry": {"coordinates":[-80.170929,25.916712],"type":"Point"}
}