{
  "type": "Feature",
  "properties": {
    "addr:full":"843 W Birchwood Cir Kissimmee FL 34743",
    "addr:housenumber":"843",
    "addr:postcode":"34743",
    "addr:street":"W Birchwood Cir",
    "iso:country":"US",
    "sg:address":"843 W Birchwood Cir",
    "sg:city":"Kissimmee",
    "sg:classifiers":[
        {
            "category":"Building & Trades",
            "subcategory":"Landscaping Services",
            "type":"Services"
        }
    ],
    "sg:phone":"+1 407 344 1967",
    "sg:postcode":"34743",
    "sg:province":"FL",
    "wof:name":"Raphael Phillip Affordable",
    "wof:placetype":"venue"
},
  "geometry": {"coordinates":[-81.373289,28.326857],"type":"Point"}
}