{
  "type": "Feature",
  "properties": {
    "iso:country":"US",
    "sg:address":"16855 NW 37th Ave",
    "sg:city":"Opa Locka",
    "sg:classifiers":[
        {
            "category":"Autos & Motor Vehicles",
            "subcategory":"Auto Supplies",
            "type":"Retail Goods"
        }
    ],
    "sg:phone":"+1 305 620 0157",
    "sg:postcode":"33056",
    "sg:province":"FL",
    "sg:tags":[
        "tire"
    ],
    "wof:name":"Matos Motor Works Inc",
    "wof:placetype":"venue"
},
  "geometry": {"coordinates":[-80.26060200000001,25.926321],"type":"Point"}
}