{
  "type": "Feature",
  "properties": {
    "addr:full":"4511 Julington Creek Rd Jacksonville FL 32258",
    "addr:housenumber":"4511",
    "addr:postcode":"32258",
    "addr:street":"Julington Creek Rd",
    "iso:country":"US",
    "sg:address":"4511 Julington Creek Rd",
    "sg:city":"Jacksonville",
    "sg:classifiers":[
        {
            "category":"Organizations",
            "subcategory":"Labor Organization",
            "type":"Services"
        }
    ],
    "sg:phone":"+1 904 509 9978",
    "sg:postcode":"32258",
    "sg:province":"FL",
    "wof:name":"Firefighters Store",
    "wof:placetype":"venue"
},
  "geometry": {"coordinates":[-81.588336,30.137055],"type":"Point"}
}