{
  "type": "Feature",
  "properties": {
    "addr:full":"600 W Canton Ave Winter Park FL 32789",
    "addr:housenumber":"600",
    "addr:postcode":"32789",
    "addr:street":"W Canton Ave",
    "iso:country":"US",
    "sg:address":"600 W Canton Ave",
    "sg:city":"Winter Park",
    "sg:classifiers":[
        {
            "category":"Organizations",
            "subcategory":"Religious Organization",
            "type":"Services"
        }
    ],
    "sg:phone":"+1 407 647 2093",
    "sg:postcode":"32789",
    "sg:province":"FL",
    "sg:tags":[
        "church"
    ],
    "wof:name":"Church Of God",
    "wof:placetype":"venue"
},
  "geometry": {"coordinates":[-81.35895600000001,28.600395],"type":"Point"}
}