{
  "type": "Feature",
  "properties": {
    "iso:country":"US",
    "sg:address":"1417 Jackson Ave",
    "sg:city":"Chipley",
    "sg:classifiers":[
        {
            "category":"Manufacturing",
            "subcategory":"Signs",
            "type":"Manufacturing & Wholesale Goods"
        }
    ],
    "sg:phone":"+1 850 638 2999",
    "sg:postcode":"32428",
    "sg:province":"FL",
    "wof:name":"Auto Graphix",
    "wof:placetype":"venue"
},
  "geometry": {"coordinates":[-85.549273,30.77857],"type":"Point"}
}