{
  "type": "Feature",
  "properties": {
    "addr:full":"9340 N Florida Ave Tampa FL 33612",
    "addr:housenumber":"9340",
    "addr:postcode":"33612",
    "addr:street":"N Florida Ave",
    "iso:country":"US",
    "sg:address":"9340 N Florida Ave",
    "sg:city":"Tampa",
    "sg:classifiers":[
        {
            "category":"Insurance",
            "subcategory":"Hazard Insurance",
            "type":"Services"
        }
    ],
    "sg:phone":"+1 813 935 1037",
    "sg:postcode":"33612",
    "sg:province":"FL",
    "sg:tags":[
        "carrier"
    ],
    "wof:name":"Florida No-Fault",
    "wof:placetype":"venue"
},
  "geometry": {"coordinates":[-82.459541,28.035737],"type":"Point"}
}