{
  "type": "Feature",
  "properties": {
    "addr:full":"10300 W Midway Rd Fort Pierce FL 34945",
    "addr:housenumber":"10300",
    "addr:postcode":"34945",
    "addr:street":"W Midway Rd",
    "iso:country":"US",
    "sg:address":"10300 W Midway Rd",
    "sg:city":"Fort Pierce",
    "sg:classifiers":[
        {
            "category":"Wholesale",
            "subcategory":"Plants",
            "type":"Manufacturing & Wholesale Goods"
        }
    ],
    "sg:phone":"+1 772 466 0801",
    "sg:postcode":"34945",
    "sg:province":"FL",
    "sg:tags":[
        "potted",
        "installation",
        "landscape"
    ],
    "wof:name":"Plant Haven Wholesale Nursery",
    "wof:placetype":"venue"
},
  "geometry": {"coordinates":[-80.42389,27.37438],"type":"Point"}
}