{
  "type": "Feature",
  "properties": {
    "iso:country":"US",
    "sg:address":"14281 SW 37th St",
    "sg:city":"Miami",
    "sg:classifiers":[
        {
            "category":"Health Services",
            "subcategory":"Clinic",
            "type":"Services"
        }
    ],
    "sg:phone":"+1 305 485 5552",
    "sg:postcode":"33175",
    "sg:province":"FL",
    "sg:tags":[
        "wellness",
        "program"
    ],
    "wof:name":"Nature's Wellness Of America",
    "wof:placetype":"venue"
},
  "geometry": {"coordinates":[-80.424374,25.733308],"type":"Point"}
}