{
  "type": "Feature",
  "properties": {
    "iso:country":"US",
    "sg:address":"109 N Brush St",
    "sg:city":"Tampa",
    "sg:classifiers":[
        {
            "category":"Real Estate",
            "subcategory":"Developer",
            "type":"Services"
        }
    ],
    "sg:phone":"+1 813 228 7466",
    "sg:postcode":"33602",
    "sg:province":"FL",
    "wof:name":"Pinnacle Group Holdings Inc",
    "wof:placetype":"venue"
},
  "geometry": {"coordinates":[-82.450192,27.947873],"type":"Point"}
}