{
  "type": "Feature",
  "properties": {
    "iso:country":"US",
    "sg:address":"400 Kelly Plantation Dr",
    "sg:city":"Destin",
    "sg:classifiers":[
        {
            "category":"Health Services",
            "subcategory":"Doctor",
            "type":"Services"
        }
    ],
    "sg:phone":"+1 850 650 9049",
    "sg:postcode":"32541",
    "sg:province":"FL",
    "sg:tags":[
        "physician",
        "surgeon"
    ],
    "wof:name":"Mccrea, Erlinda",
    "wof:placetype":"venue"
},
  "geometry": {"coordinates":[-86.428749,30.39912],"type":"Point"}
}