{
  "type": "Feature",
  "properties": {
    "iso:country":"US",
    "sg:address":"4658 Commander Dr",
    "sg:city":"Orlando",
    "sg:classifiers":[
        {
            "category":"Building & Trades",
            "subcategory":"Construction",
            "type":"Services"
        }
    ],
    "sg:phone":"+1 321 303 8231",
    "sg:postcode":"32822",
    "sg:province":"FL",
    "sg:tags":[
        "contractor"
    ],
    "wof:name":"Tremucon Inc",
    "wof:placetype":"venue"
},
  "geometry": {"coordinates":[-81.30627699999999,28.497098],"type":"Point"}
}