{
  "type": "Feature",
  "properties": {
    "addr:full":"7907 Clark Moody Blvd Port Richey FL 34668",
    "addr:housenumber":"7907",
    "addr:postcode":"34668",
    "addr:street":"Clark Moody Blvd",
    "iso:country":"US",
    "sg:address":"7907 Clark Moody Blvd",
    "sg:city":"Port Richey",
    "sg:classifiers":[
        {
            "category":"Building & Trades",
            "subcategory":"Construction",
            "type":"Services"
        }
    ],
    "sg:phone":"+1 727 844 5870",
    "sg:postcode":"34668",
    "sg:province":"FL",
    "sg:tags":[
        "contractor"
    ],
    "wof:name":"Professional Drywall Of Pasco",
    "wof:placetype":"venue"
},
  "geometry": {"coordinates":[-82.714876,28.271521],"type":"Point"}
}