{
  "type": "Feature",
  "properties": {
    "addr:full":"4923 Tortuga Dr West Palm Beach FL 33407",
    "addr:housenumber":"4923",
    "addr:postcode":"33407",
    "addr:street":"Tortuga Dr",
    "iso:country":"US",
    "sg:address":"4923 Tortuga Dr",
    "sg:city":"West Palm Beach",
    "sg:classifiers":[
        {
            "category":"Freight",
            "type":"Transportation"
        }
    ],
    "sg:phone":"+1 561 615 5223",
    "sg:postcode":"33407",
    "sg:province":"FL",
    "sg:tags":[
        "operator",
        "local",
        "trucking"
    ],
    "wof:name":"Samuel Millner",
    "wof:placetype":"venue"
},
  "geometry": {"coordinates":[-80.113483,26.762185],"type":"Point"}
}