{
  "type": "Feature",
  "properties": {
    "addr:full":"8600 NW 46th Ct Fort Lauderdale FL 33351",
    "addr:housenumber":"8600",
    "addr:postcode":"33351",
    "addr:street":"Nw 46Th Ct",
    "iso:country":"US",
    "sg:address":"8600 NW 46th Ct",
    "sg:city":"Fort Lauderdale",
    "sg:classifiers":[
        {
            "category":"Wholesale",
            "subcategory":"Auto Parts",
            "type":"Manufacturing & Wholesale Goods"
        }
    ],
    "sg:phone":"+1 954 741 8519",
    "sg:postcode":"33351",
    "sg:province":"FL",
    "wof:name":"Buds Battery & Auto",
    "wof:placetype":"venue"
},
  "geometry": {"coordinates":[-80.266386,26.182333],"type":"Point"}
}