{
  "type": "Feature",
  "properties": {
    "addr:full":"3031 40th St Orlando FL 32839",
    "addr:housenumber":"3031",
    "addr:postcode":"32839",
    "addr:street":"40Th St",
    "iso:country":"US",
    "sg:address":"3031 40th St",
    "sg:city":"Orlando",
    "sg:classifiers":[
        {
            "category":"Building & Trades",
            "subcategory":"Plumbing",
            "type":"Services"
        }
    ],
    "sg:phone":"+1 407 841 8200",
    "sg:postcode":"32839",
    "sg:province":"FL",
    "sg:tags":[
        "septic"
    ],
    "sg:website":"www.lapinservices.com",
    "wof:name":"Lapin Services",
    "wof:placetype":"venue"
},
  "geometry": {"coordinates":[-81.417874,28.502326],"type":"Point"}
}