{
  "type": "Feature",
  "properties": {
    "iso:country":"US",
    "sg:address":"5100 Tamiami Trl N",
    "sg:city":"Naples",
    "sg:classifiers":[
        {
            "category":"Professional",
            "subcategory":"Lawyer & Legal Services",
            "type":"Services"
        }
    ],
    "sg:phone":"+1 239 594 8992",
    "sg:postcode":"34103",
    "sg:province":"FL",
    "wof:name":"Yale T Freeman PA",
    "wof:placetype":"venue"
},
  "geometry": {"coordinates":[-81.80040700000001,26.210209],"type":"Point"}
}