{
  "type": "Feature",
  "properties": {
    "addr:full":"4255 SE Seaward St Stuart FL 34997",
    "addr:housenumber":"4255",
    "addr:postcode":"34997",
    "addr:street":"Se Seaward St",
    "iso:country":"US",
    "sg:address":"4255 SE Seaward St",
    "sg:city":"Stuart",
    "sg:classifiers":[
        {
            "category":"Wholesale",
            "subcategory":"Jewelry",
            "type":"Manufacturing & Wholesale Goods"
        }
    ],
    "sg:phone":"+1 772 288 1514",
    "sg:postcode":"34997",
    "sg:province":"FL",
    "sg:tags":[
        "stone"
    ],
    "wof:name":"Yvonne D Davis",
    "wof:placetype":"venue"
},
  "geometry": {"coordinates":[-80.19790500000001,27.147235],"type":"Point"}
}