{
  "type": "Feature",
  "properties": {
    "iso:country":"US",
    "sg:address":"3874 N Canoe Creek Rd",
    "sg:city":"St Cloud",
    "sg:classifiers":[
        {
            "category":"Building & Trades",
            "subcategory":"Landscaping Services",
            "type":"Services"
        }
    ],
    "sg:phone":"+1 407 891 9100",
    "sg:postcode":"34772",
    "sg:province":"FL",
    "sg:tags":[
        "landscape",
        "contractor"
    ],
    "wof:name":"Ce Outdoor Svc Inc",
    "wof:placetype":"venue"
},
  "geometry": {"coordinates":[-81.282433,28.180464],"type":"Point"}
}