{
  "type": "Feature",
  "properties": {
    "addr:full":"7627 Little Rd New Port Richey FL 34654",
    "addr:housenumber":"7627",
    "addr:postcode":"34654",
    "addr:street":"Little Rd",
    "iso:country":"US",
    "sg:address":"7627 Little Rd",
    "sg:city":"New Port Richey",
    "sg:classifiers":[
        {
            "category":"Banks & Credit Unions",
            "subcategory":"Bank",
            "type":"Services"
        }
    ],
    "sg:phone":"+1 727 815 8908",
    "sg:postcode":"34654",
    "sg:province":"FL",
    "sg:tags":[
        "mortgage",
        "lender",
        "banking",
        "licensing",
        "real estate"
    ],
    "wof:name":"Williams and Assoc Intl Corp",
    "wof:placetype":"venue"
},
  "geometry": {"coordinates":[-82.674373,28.269902],"type":"Point"}
}