{
  "type": "Feature",
  "properties": {
    "iso:country":"US",
    "sg:address":"3220 Co Rd 305",
    "sg:city":"Bunnell",
    "sg:classifiers":[
        {
            "category":"Farming",
            "subcategory":"Farm",
            "type":"Manufacturing & Wholesale Goods"
        }
    ],
    "sg:phone":"+1 386 437 3522",
    "sg:postcode":"32110",
    "sg:province":"FL",
    "wof:name":"Greens Farms",
    "wof:placetype":"venue"
},
  "geometry": {"coordinates":[-81.371295,29.425355],"type":"Point"}
}