{
  "type": "Feature",
  "properties": {
    "iso:country":"US",
    "sg:address":"505 Pinegrove Ave",
    "sg:city":"Jupiter",
    "sg:classifiers":[
        {
            "category":"Personal",
            "subcategory":"Beauty Salon",
            "type":"Services"
        }
    ],
    "sg:phone":"+1 561 747 3868",
    "sg:postcode":"33458",
    "sg:province":"FL",
    "wof:name":"Jc Salon Inc",
    "wof:placetype":"venue"
},
  "geometry": {"coordinates":[-80.09853200000001,26.938805],"type":"Point"}
}