{
  "type": "Feature",
  "properties": {
    "iso:country":"US",
    "sg:address":"8160 49th Ave N",
    "sg:city":"Saint Petersburg",
    "sg:classifiers":[
        {
            "category":"Building & Trades",
            "subcategory":"Construction",
            "type":"Services"
        }
    ],
    "sg:phone":"+1 727 546 2339",
    "sg:postcode":"33709",
    "sg:province":"FL",
    "sg:tags":[
        "contractor"
    ],
    "wof:name":"Dans Tile and Marble",
    "wof:placetype":"venue"
},
  "geometry": {"coordinates":[-82.75166900000001,27.816295],"type":"Point"}
}