{
  "type": "Feature",
  "properties": {
    "iso:country":"US",
    "sg:address":"11157 Tamiami Trl",
    "sg:city":"Naples",
    "sg:classifiers":[
        {
            "category":"Restaurant",
            "type":"Food & Drink"
        }
    ],
    "sg:phone":"+1 239 793 1211",
    "sg:postcode":"34113",
    "sg:province":"FL",
    "sg:tags":[
        "eating"
    ],
    "wof:name":"El Tapatio Restaurante",
    "wof:placetype":"venue"
},
  "geometry": {"coordinates":[-81.731138,26.088693],"type":"Point"}
}