{
  "type": "Feature",
  "properties": {
    "iso:country":"US",
    "sg:address":"3935 NW 3rd St",
    "sg:city":"Miami",
    "sg:classifiers":[
        {
            "category":"Professional",
            "subcategory":"Engineering",
            "type":"Services"
        }
    ],
    "sg:phone":"+1 786 239 2567",
    "sg:postcode":"33126",
    "sg:province":"FL",
    "sg:tags":[
        "refrigeration",
        "engineer"
    ],
    "wof:name":"Jlc Air Conditioning Refrigeration And A",
    "wof:placetype":"venue"
},
  "geometry": {"coordinates":[-80.260965,25.775261],"type":"Point"}
}