{
  "type": "Feature",
  "properties": {
    "addr:full":"115 E Virginia Ave Bushnell FL 33513",
    "addr:housenumber":"115",
    "addr:postcode":"33513",
    "addr:street":"E Virginia Ave",
    "iso:country":"US",
    "sg:address":"115 E Virginia Ave",
    "sg:city":"Bushnell",
    "sg:classifiers":[
        {
            "category":"Organizations",
            "subcategory":"Community Association",
            "type":"Services"
        }
    ],
    "sg:phone":"+1 352 793 2173",
    "sg:postcode":"33513",
    "sg:province":"FL",
    "sg:tags":[
        "club"
    ],
    "wof:name":"Bushnell City Of Women Club",
    "wof:placetype":"venue"
},
  "geometry": {"coordinates":[-82.111648,28.663015],"type":"Point"}
}