{
  "type": "Feature",
  "properties": {
    "addr:full":"5465 S Oakridge Dr Homosassa FL 34448",
    "addr:housenumber":"5465",
    "addr:postcode":"34448",
    "addr:street":"S Oakridge Dr",
    "iso:country":"US",
    "sg:address":"5465 S Oakridge Dr",
    "sg:city":"Homosassa",
    "sg:classifiers":[
        {
            "category":"Bars & Pubs",
            "type":"Food & Drink"
        }
    ],
    "sg:phone":"+1 352 628 6896",
    "sg:postcode":"34448",
    "sg:province":"FL",
    "sg:tags":[
        "lounge",
        "cocktail"
    ],
    "wof:name":"Mike's Friendly Pub & Deli",
    "wof:placetype":"venue"
},
  "geometry": {"coordinates":[-82.560878,28.782582],"type":"Point"}
}