{
  "type": "Feature",
  "properties": {
    "iso:country":"US",
    "sg:address":"1190 Turnbull Bay Rd",
    "sg:city":"New Smyrna Beach",
    "sg:classifiers":[
        {
            "category":"Retail",
            "subcategory":"Repair Shop",
            "type":"Services"
        }
    ],
    "sg:phone":"+1 386 409 5440",
    "sg:postcode":"32168",
    "sg:province":"FL",
    "sg:tags":[
        "welding"
    ],
    "wof:name":"Jennings Weld & Fabrication",
    "wof:placetype":"venue"
},
  "geometry": {"coordinates":[-80.944157,29.043237],"type":"Point"}
}