{
  "type": "Feature",
  "properties": {
    "iso:country":"US",
    "sg:address":"14857 SW Indian Mound Dr",
    "sg:city":"Indiantown",
    "sg:classifiers":[
        {
            "category":"Building & Trades",
            "subcategory":"Landscaping Services",
            "type":"Services"
        }
    ],
    "sg:phone":"+1 772 597 5392",
    "sg:postcode":"34956",
    "sg:province":"FL",
    "wof:name":"Lopez Gaspar Lawn Service",
    "wof:placetype":"venue"
},
  "geometry": {"coordinates":[-80.457984,27.025141],"type":"Point"}
}