{
  "type": "Feature",
  "properties": {
    "iso:country":"US",
    "sg:address":"600 Bayou Blvd",
    "sg:city":"Pensacola",
    "sg:classifiers":[
        {
            "category":"Professional",
            "subcategory":"Management & Consulting",
            "type":"Services"
        }
    ],
    "sg:phone":"+1 850 438 2934",
    "sg:postcode":"32503",
    "sg:province":"FL",
    "sg:tags":[
        "business"
    ],
    "wof:name":"Berthelot Consulting Inc",
    "wof:placetype":"venue"
},
  "geometry": {"coordinates":[-87.18619099999999,30.428524],"type":"Point"}
}