{
  "type": "Feature",
  "properties": {
    "iso:country":"US",
    "sg:address":"38 N Charles Richard Beall Blvd",
    "sg:city":"Debary",
    "sg:classifiers":[
        {
            "category":"Health Services",
            "subcategory":"Optometrist",
            "type":"Services"
        },
        {
            "category":"Shopping",
            "subcategory":"Optician",
            "type":"Retail Goods"
        }
    ],
    "sg:phone":"+1 386 668 0600",
    "sg:postcode":"32713",
    "sg:province":"FL",
    "sg:tags":[
        "eyewear"
    ],
    "wof:name":"Debary Optical",
    "wof:placetype":"venue"
},
  "geometry": {"coordinates":[-81.306166,28.893117],"type":"Point"}
}