{
  "type": "Feature",
  "properties": {
    "addr:full":"50 Minnehaha Cir Maitland FL 32751",
    "addr:postcode":"32751",
    "addr:street":"50 Minnehaha Cir",
    "iso:country":"US",
    "sg:address":"50 Minnehaha Cir",
    "sg:city":"Maitland",
    "sg:classifiers":[
        {
            "category":"Restaurant",
            "type":"Food & Drink"
        }
    ],
    "sg:phone":"+1 407 648 2050",
    "sg:postcode":"32751",
    "sg:province":"FL",
    "sg:tags":[
        "drinking",
        "eating"
    ],
    "wof:name":"One-Eyed Jacks",
    "wof:placetype":"venue"
},
  "geometry": {"coordinates":[-81.356509,28.628562],"type":"Point"}
}