{
  "type": "Feature",
  "properties": {
    "addr:full":"8120 Nations Way Jacksonville FL 32256",
    "addr:housenumber":"8120",
    "addr:postcode":"32256",
    "addr:street":"Nations Way",
    "iso:country":"US",
    "sg:address":"8120 Nations Way",
    "sg:city":"Jacksonville",
    "sg:classifiers":[
        {
            "category":"Professional",
            "subcategory":"Business Services",
            "type":"Services"
        }
    ],
    "sg:phone":"+1 904 296 4772",
    "sg:postcode":"32256",
    "sg:province":"FL",
    "sg:tags":[
        "telemarketing"
    ],
    "wof:name":"Evergreen Sales & Marketing",
    "wof:placetype":"venue"
},
  "geometry": {"coordinates":[-81.590127,30.241163],"type":"Point"}
}