{
  "type": "Feature",
  "properties": {
    "iso:country":"US",
    "sg:address":"2645 SW 37th Ave",
    "sg:city":"Miami",
    "sg:classifiers":[
        {
            "category":"Health Services",
            "subcategory":"Doctor",
            "type":"Services"
        },
        {
            "category":"Health Services",
            "subcategory":"Dentist",
            "type":"Services"
        }
    ],
    "sg:phone":"+1 786 230 1568",
    "sg:postcode":"33133",
    "sg:province":"FL",
    "sg:tags":[
        "dentists-oral",
        "physician",
        "maxillofacial",
        "surgeons",
        "surgery",
        "oral"
    ],
    "wof:name":"Hernan Rodriquez Dmd Inc",
    "wof:placetype":"venue"
},
  "geometry": {"coordinates":[-80.254272,25.742109],"type":"Point"}
}