{
  "type": "Feature",
  "properties": {
    "iso:country":"US",
    "sg:address":"1800 W Tennessee St",
    "sg:city":"Tallahassee",
    "sg:phone":"+1 850 681 0731",
    "sg:postcode":"32304",
    "sg:province":"FL",
    "sg:website":"http://www.ajsports.com",
    "wof:name":"A J Sports",
    "wof:placetype":"venue"
},
  "geometry": {"coordinates":[-84.311869,30.449128],"type":"Point"}
}