{
  "type": "Feature",
  "properties": {
    "addr:full":"15760 NW 27th Ave Opa Locka FL 33054",
    "addr:housenumber":"15760",
    "addr:postcode":"33054",
    "addr:street":"Nw 27Th Ave;Locka",
    "iso:country":"US",
    "sg:address":"15760 NW 27th Ave",
    "sg:city":"Opa Locka",
    "sg:classifiers":[
        {
            "category":"Freight",
            "type":"Transportation"
        }
    ],
    "sg:phone":"+1 305 624 6228",
    "sg:postcode":"33054",
    "sg:province":"FL",
    "sg:tags":[
        "commercial",
        "storage",
        "general"
    ],
    "wof:name":"Public Storage Inc",
    "wof:placetype":"venue"
},
  "geometry": {"coordinates":[-80.244483,25.918379],"type":"Point"}
}