{
  "type": "Feature",
  "properties": {
    "addr:full":"600 Mount Vernon St Oldsmar FL 34677",
    "addr:housenumber":"600",
    "addr:postcode":"34677",
    "addr:street":"Mount Vernon St",
    "iso:country":"US",
    "sg:address":"600 Mount Vernon St",
    "sg:city":"Oldsmar",
    "sg:classifiers":[
        {
            "category":"Professional",
            "type":"Services"
        }
    ],
    "sg:phone":"+1 813 855 0847",
    "sg:postcode":"34677",
    "sg:province":"FL",
    "sg:tags":[
        "establishment"
    ],
    "wof:name":"Rock Your World",
    "wof:placetype":"venue"
},
  "geometry": {"coordinates":[-82.672866,28.040172],"type":"Point"}
}