{
  "type": "Feature",
  "properties": {
    "iso:country":"US",
    "sg:address":"104 Hickory Tree Rd",
    "sg:city":"Longwood",
    "sg:classifiers":[
        {
            "category":"Wholesale",
            "subcategory":"Machinery & Supplies",
            "type":"Manufacturing & Wholesale Goods"
        }
    ],
    "sg:phone":"+1 407 332 8340",
    "sg:postcode":"32750",
    "sg:province":"FL",
    "sg:tags":[
        "metal",
        "working"
    ],
    "wof:name":"Mc Kechnie Machinery Co",
    "wof:placetype":"venue"
},
  "geometry": {"coordinates":[-81.374889,28.711015],"type":"Point"}
}