{
  "type": "Feature",
  "properties": {
    "addr:full":"782 Hardwood St Orange Park FL 32065",
    "addr:housenumber":"782",
    "addr:postcode":"32065",
    "addr:street":"Hardwood St",
    "iso:country":"US",
    "sg:address":"782 Hardwood St",
    "sg:city":"Orange Park",
    "sg:classifiers":[
        {
            "category":"Restaurant",
            "type":"Food & Drink"
        }
    ],
    "sg:phone":"+1 904 298 2946",
    "sg:postcode":"32065",
    "sg:province":"FL",
    "sg:tags":[
        "eating"
    ],
    "wof:name":"Sweetie Pie",
    "wof:placetype":"venue"
},
  "geometry": {"coordinates":[-81.771226,30.147399],"type":"Point"}
}