{
  "type": "Feature",
  "properties": {
    "addr:full":"2515 N Monroe St Tallahassee FL 32303",
    "addr:housenumber":"2515",
    "addr:postcode":"32303",
    "addr:street":"N Monroe St",
    "iso:country":"US",
    "sg:address":"2515 N Monroe St",
    "sg:city":"Tallahassee",
    "sg:classifiers":[
        {
            "category":"Shopping",
            "subcategory":"Clothing, Apparel, & Fashions",
            "type":"Retail Goods"
        }
    ],
    "sg:phone":"+1 850 386 2308",
    "sg:postcode":"32303",
    "sg:province":"FL",
    "sg:tags":[
        "hat"
    ],
    "wof:name":"Hat World",
    "wof:placetype":"venue"
},
  "geometry": {"coordinates":[-84.29417599999999,30.474157],"type":"Point"}
}