{
  "type": "Feature",
  "properties": {
    "iso:country":"US",
    "sg:address":"1060 SW Biltmore St",
    "sg:city":"Port St Lucie",
    "sg:classifiers":[
        {
            "category":"Home & Garden",
            "subcategory":"Building Materials",
            "type":"Retail Goods"
        }
    ],
    "sg:phone":"+1 772 621 4585",
    "sg:postcode":"34983",
    "sg:province":"FL",
    "sg:tags":[
        "glass",
        "window",
        "plate"
    ],
    "wof:name":"Rapid Glass",
    "wof:placetype":"venue"
},
  "geometry": {"coordinates":[-80.371137,27.304944],"type":"Point"}
}