{
  "type": "Feature",
  "properties": {
    "addr:full":"775 W Martin Luther King Jr Blvd Tampa FL 33603",
    "addr:housenumber":"775",
    "addr:postcode":"33603",
    "addr:street":"W Martin Luther King Jr Blvd",
    "iso:country":"US",
    "sg:address":"775 W Martin Luther King Jr Blvd",
    "sg:city":"Tampa",
    "sg:classifiers":[
        {
            "category":"Health Services",
            "subcategory":"Doctor",
            "type":"Services"
        }
    ],
    "sg:phone":"+1 813 681 5411",
    "sg:postcode":"33603",
    "sg:province":"FL",
    "sg:tags":[
        "physician",
        "surgeon"
    ],
    "wof:name":"John Mubang MD",
    "wof:placetype":"venue"
},
  "geometry": {"coordinates":[-82.46901699999999,27.981641],"type":"Point"}
}