{
  "type": "Feature",
  "properties": {
    "addr:full":"6500 Prado Blvd Miami FL 33143",
    "addr:housenumber":"6500",
    "addr:postcode":"33143",
    "addr:street":"Prado Blvd",
    "iso:country":"US",
    "sg:address":"6500 Prado Blvd",
    "sg:city":"Miami",
    "sg:classifiers":[
        {
            "category":"Manufacturing",
            "subcategory":"Aerospace",
            "type":"Manufacturing & Wholesale Goods"
        }
    ],
    "sg:phone":"+1 305 740 7090",
    "sg:postcode":"33143",
    "sg:province":"FL",
    "sg:tags":[
        "aircraft",
        "mfg"
    ],
    "wof:name":"Pfm Avaiation Inc",
    "wof:placetype":"venue"
},
  "geometry": {"coordinates":[-80.25645799999999,25.703989],"type":"Point"}
}