{
  "type": "Feature",
  "properties": {
    "iso:country":"US",
    "sg:address":"13494 Carrick Green Ct",
    "sg:city":"Delray Beach",
    "sg:classifiers":[
        {
            "category":"Restaurant",
            "type":"Food & Drink"
        }
    ],
    "sg:phone":"+1 561 862 0900",
    "sg:postcode":"33446",
    "sg:province":"FL",
    "sg:tags":[
        "eating"
    ],
    "wof:name":"Cafe 777",
    "wof:placetype":"venue"
},
  "geometry": {"coordinates":[-80.16422900000001,26.47652],"type":"Point"}
}