{
  "type": "Feature",
  "properties": {
    "addr:full":"13511 Hollow Cove Tampa FL 33613",
    "addr:housenumber":"13511",
    "addr:postcode":"33613",
    "addr:street":"Hollow Cove",
    "iso:country":"US",
    "sg:address":"13511 Hollow Cove",
    "sg:city":"Tampa",
    "sg:classifiers":[
        {
            "category":"Professional",
            "subcategory":"Computer Services",
            "type":"Services"
        }
    ],
    "sg:phone":"+1 813 908 7096",
    "sg:postcode":"33613",
    "sg:province":"FL",
    "sg:tags":[
        "programing",
        "custom"
    ],
    "wof:name":"Digital Pepper",
    "wof:placetype":"venue"
},
  "geometry": {"coordinates":[-82.48357300000001,28.070804],"type":"Point"}
}