{
  "type": "Feature",
  "properties": {
    "addr:full":"6390 SW 8th St Miami FL 33144",
    "addr:housenumber":"6390",
    "addr:postcode":"33144",
    "addr:street":"Sw 8Th St",
    "iso:country":"US",
    "sg:address":"6390 SW 8th St",
    "sg:city":"Miami",
    "sg:classifiers":[
        {
            "category":"Retail",
            "subcategory":"Veterinary Services",
            "type":"Services"
        }
    ],
    "sg:phone":"+1 305 424 8585",
    "sg:postcode":"33144",
    "sg:province":"FL",
    "sg:tags":[
        "veterinarian"
    ],
    "sg:website":"www.vcacabrera.com",
    "wof:name":"VCA Cabrera Animal Hospital",
    "wof:placetype":"venue"
},
  "geometry": {"coordinates":[-80.29962999999999,25.76295],"type":"Point"}
}