{
  "type": "Feature",
  "properties": {
    "iso:country":"US",
    "sg:address":"1939 NE 147th Ln",
    "sg:city":"Miami",
    "sg:classifiers":[
        {
            "category":"Manufacturing",
            "subcategory":"Printing",
            "type":"Manufacturing & Wholesale Goods"
        }
    ],
    "sg:phone":"+1 305 947 6771",
    "sg:postcode":"33181",
    "sg:province":"FL",
    "sg:tags":[
        "lithographic",
        "commercial"
    ],
    "wof:name":"F D G Graphics Inc",
    "wof:placetype":"venue"
},
  "geometry": {"coordinates":[-80.159667,25.911562],"type":"Point"}
}