{
  "type": "Feature",
  "properties": {
    "iso:country":"US",
    "sg:address":"509 Canal St",
    "sg:city":"New Smyrna Beach",
    "sg:classifiers":[
        {
            "category":"Banks & Credit Unions",
            "subcategory":"Investment Brokerage",
            "type":"Services"
        },
        {
            "category":"Professional",
            "subcategory":"Management & Consulting",
            "type":"Services"
        }
    ],
    "sg:phone":"+1 386 426 2440",
    "sg:postcode":"32168",
    "sg:province":"FL",
    "sg:tags":[
        "security"
    ],
    "wof:name":"Perrott Mather & Gilday Inc",
    "wof:placetype":"venue"
},
  "geometry": {"coordinates":[-80.926072,29.023797],"type":"Point"}
}