{
  "type": "Feature",
  "properties": {
    "iso:country":"US",
    "sg:address":"1712 Reef Ct",
    "sg:city":"Venice",
    "sg:classifiers":[
        {
            "category":"Organizations",
            "subcategory":"Religious Organization",
            "type":"Services"
        }
    ],
    "sg:phone":"+1 941 496 4312",
    "sg:postcode":"34293",
    "sg:province":"FL",
    "wof:name":"Ucc Church",
    "wof:placetype":"venue"
},
  "geometry": {"coordinates":[-82.397232,27.070511],"type":"Point"}
}