{
  "type": "Feature",
  "properties": {
    "iso:country":"US",
    "sg:address":"2360 Potts Rd",
    "sg:city":"Tallahassee",
    "sg:classifiers":[
        {
            "category":"Retail",
            "subcategory":"Repair Shop",
            "type":"Services"
        }
    ],
    "sg:phone":"+1 850 385 1155",
    "sg:postcode":"32308",
    "sg:province":"FL",
    "sg:tags":[
        "repairing",
        "piano",
        "refinishing"
    ],
    "wof:name":"Ricks Piano Svc",
    "wof:placetype":"venue"
},
  "geometry": {"coordinates":[-84.243725,30.483908],"type":"Point"}
}