{
  "type": "Feature",
  "properties": {
    "addr:full":"1520 Pioneer Dr Lakeland FL 33809",
    "addr:housenumber":"1520",
    "addr:postcode":"33809",
    "addr:street":"Pioneer Dr",
    "iso:country":"US",
    "sg:address":"1520 Pioneer Dr",
    "sg:city":"Lakeland",
    "sg:classifiers":[
        {
            "category":"Building & Trades",
            "subcategory":"Construction",
            "type":"Services"
        }
    ],
    "sg:phone":"+1 863 859 2614",
    "sg:postcode":"33809",
    "sg:province":"FL",
    "sg:tags":[
        "contractor"
    ],
    "wof:name":"Rory Arbogast Drywall",
    "wof:placetype":"venue"
},
  "geometry": {"coordinates":[-81.992467,28.189197],"type":"Point"}
}