{
  "type": "Feature",
  "properties": {
    "iso:country":"US",
    "sg:address":"106 Mariners Dr",
    "sg:city":"Ormond Beach",
    "sg:classifiers":[
        {
            "category":"Manufacturing",
            "subcategory":"Toys & Sporting Goods",
            "type":"Manufacturing & Wholesale Goods"
        }
    ],
    "sg:phone":"+1 386 441 1826",
    "sg:postcode":"32176",
    "sg:province":"FL",
    "sg:tags":[
        "mfg"
    ],
    "wof:name":"Tuball",
    "wof:placetype":"venue"
},
  "geometry": {"coordinates":[-81.077184,29.361613],"type":"Point"}
}