{
  "type": "Feature",
  "properties": {
    "iso:country":"US",
    "sg:address":"2925 Sans Pareil St",
    "sg:city":"Jacksonville",
    "sg:classifiers":[
        {
            "category":"Building & Trades",
            "subcategory":"Construction",
            "type":"Services"
        }
    ],
    "sg:phone":"+1 904 642 4542",
    "sg:postcode":"32246",
    "sg:province":"FL",
    "sg:tags":[
        "concrete",
        "contractor"
    ],
    "wof:name":"S & S Shot Crete",
    "wof:placetype":"venue"
},
  "geometry": {"coordinates":[-81.499008,30.292848],"type":"Point"}
}