{
  "type": "Feature",
  "properties": {
    "iso:country":"US",
    "sg:address":"1177 College Blvd",
    "sg:city":"Pensacola",
    "sg:classifiers":[
        {
            "category":"Banks & Credit Unions",
            "subcategory":"Bank",
            "type":"Services"
        }
    ],
    "sg:phone":"+1 850 475 9300",
    "sg:postcode":"32504",
    "sg:province":"FL",
    "wof:name":"Gulf Coast Community Bank",
    "wof:placetype":"venue"
},
  "geometry": {"coordinates":[-87.199522,30.478222],"type":"Point"}
}