{
  "type": "Feature",
  "properties": {
    "addr:full":"5558 Commercial Blvd Winter Haven FL 33880",
    "addr:housenumber":"5558",
    "addr:postcode":"33880",
    "addr:street":"Commercial Blvd",
    "iso:country":"US",
    "sg:address":"5558 Commercial Blvd",
    "sg:city":"Winter Haven",
    "sg:classifiers":[
        {
            "category":"Manufacturing",
            "subcategory":"Printing",
            "type":"Manufacturing & Wholesale Goods"
        }
    ],
    "sg:phone":"+1 863 965 2576",
    "sg:postcode":"33880",
    "sg:province":"FL",
    "sg:tags":[
        "commercial"
    ],
    "sg:website":"www.ssdesigns.net",
    "wof:name":"S S Designs Inc",
    "wof:placetype":"venue"
},
  "geometry": {"coordinates":[-81.784344,28.035069],"type":"Point"}
}