{
  "type": "Feature",
  "properties": {
    "iso:country":"US",
    "sg:address":"415 NE Park St",
    "sg:city":"Okeechobee",
    "sg:classifiers":[
        {
            "category":"Shopping",
            "subcategory":"Computers & Home Electronics",
            "type":"Retail Goods"
        }
    ],
    "sg:phone":"+1 863 763 3197",
    "sg:postcode":"34972",
    "sg:province":"FL",
    "sg:tags":[
        "equipment",
        "electronic",
        "supply"
    ],
    "wof:name":"Wise TV",
    "wof:placetype":"venue"
},
  "geometry": {"coordinates":[-80.82542599999999,27.243809],"type":"Point"}
}