{
  "type": "Feature",
  "properties": {
    "addr:full":"907 Arabian Ave Winter Springs FL 32708",
    "addr:housenumber":"907",
    "addr:postcode":"32708",
    "addr:street":"Arabian Ave",
    "iso:country":"US",
    "sg:address":"907 Arabian Ave",
    "sg:city":"Winter Springs",
    "sg:classifiers":[
        {
            "category":"Building & Trades",
            "subcategory":"Construction",
            "type":"Services"
        }
    ],
    "sg:phone":"+1 407 971 6342",
    "sg:postcode":"32708",
    "sg:province":"FL",
    "sg:tags":[
        "contractor"
    ],
    "wof:name":"Joyce & Jack Lanier",
    "wof:placetype":"venue"
},
  "geometry": {"coordinates":[-81.26461399999999,28.660819],"type":"Point"}
}