{
  "type": "Feature",
  "properties": {
    "iso:country":"US",
    "sg:address":"8225 Los Pinos Cir",
    "sg:city":"Miami",
    "sg:classifiers":[
        {
            "category":"Real Estate",
            "subcategory":"Real Estate Agent",
            "type":"Services"
        }
    ],
    "sg:phone":"+1 305 666 3551",
    "sg:postcode":"33143",
    "sg:province":"FL",
    "wof:name":"Mc Realtime Corp",
    "wof:placetype":"venue"
},
  "geometry": {"coordinates":[-80.26134399999999,25.69738],"type":"Point"}
}