{
  "type": "Feature",
  "properties": {
    "iso:country":"US",
    "sg:address":"1029 Capital Cir NW",
    "sg:city":"Tallahassee",
    "sg:classifiers":[
        {
            "category":"Professional",
            "subcategory":"Engineering",
            "type":"Services"
        }
    ],
    "sg:phone":"+1 850 504 5970",
    "sg:postcode":"32304",
    "sg:province":"FL",
    "sg:tags":[
        "engineer"
    ],
    "wof:name":"Benedic Engineering Co LLC",
    "wof:placetype":"venue"
},
  "geometry": {"coordinates":[-84.35815700000001,30.450243],"type":"Point"}
}