{
  "type": "Feature",
  "properties": {
    "addr:full":"4445 Bryan Ave Kissimmee FL 34746",
    "addr:housenumber":"4445",
    "addr:postcode":"34746",
    "addr:street":"Bryan Ave",
    "iso:country":"US",
    "sg:address":"4445 Bryan Ave",
    "sg:city":"Kissimmee",
    "sg:classifiers":[
        {
            "category":"Building & Trades",
            "subcategory":"Construction",
            "type":"Services"
        }
    ],
    "sg:phone":"+1 407 846 4274",
    "sg:postcode":"34746",
    "sg:province":"FL",
    "sg:tags":[
        "painter"
    ],
    "wof:name":"Don's Painting & Wallpapering",
    "wof:placetype":"venue"
},
  "geometry": {"coordinates":[-81.460342,28.258514],"type":"Point"}
}