{
  "type": "Feature",
  "properties": {
    "addr:full":"3826 Victoria Dr West Palm Beach FL 33406",
    "addr:housenumber":"3826",
    "addr:postcode":"33406",
    "addr:street":"Victoria Dr",
    "iso:country":"US",
    "sg:address":"3826 Victoria Dr",
    "sg:city":"West Palm Beach",
    "sg:classifiers":[
        {
            "category":"Professional",
            "subcategory":"Advertising",
            "type":"Services"
        }
    ],
    "sg:phone":"+1 561 967 1987",
    "sg:postcode":"33406",
    "sg:province":"FL",
    "sg:tags":[
        "distribution"
    ],
    "wof:name":"Fenicios Distribution Inc",
    "wof:placetype":"venue"
},
  "geometry": {"coordinates":[-80.10119400000001,26.657134],"type":"Point"}
}