{
  "type": "Feature",
  "properties": {
    "addr:full":"1616 Palm Ave De Land FL 32724",
    "addr:housenumber":"1616",
    "addr:postcode":"32724",
    "addr:street":"Palm Ave",
    "iso:country":"US",
    "sg:address":"1616 Palm Ave",
    "sg:city":"De Land",
    "sg:classifiers":[
        {
            "category":"Professional",
            "type":"Services"
        }
    ],
    "sg:phone":"+1 386 738 5744",
    "sg:postcode":"32724",
    "sg:province":"FL",
    "wof:name":"Leo Aiken",
    "wof:placetype":"venue"
},
  "geometry": {"coordinates":[-81.26729899999999,29.071008],"type":"Point"}
}