{
  "type": "Feature",
  "properties": {
    "addr:full":"421 Saxony I Delray Beach FL 33446",
    "addr:housenumber":"421",
    "addr:postcode":"33446",
    "addr:street":"Saxony I",
    "iso:country":"US",
    "sg:address":"421 Saxony I",
    "sg:city":"Delray Beach",
    "sg:classifiers":[
        {
            "category":"Real Estate",
            "subcategory":"Real Estate Agent",
            "type":"Services"
        }
    ],
    "sg:phone":"+1 561 637 4354",
    "sg:postcode":"33446",
    "sg:province":"FL",
    "wof:name":"Kings Point Realty Corp",
    "wof:placetype":"venue"
},
  "geometry": {"coordinates":[-80.1511,26.440515],"type":"Point"}
}