{
  "type": "Feature",
  "properties": {
    "addr:full":"4614 Clover Lawn Dr Tampa FL 33624",
    "addr:housenumber":"4614",
    "addr:postcode":"33624",
    "addr:street":"Clover Lawn Dr",
    "iso:country":"US",
    "sg:address":"4614 Clover Lawn Dr",
    "sg:city":"Tampa",
    "sg:classifiers":[
        {
            "category":"Professional",
            "subcategory":"Business Services",
            "type":"Services"
        }
    ],
    "sg:phone":"+1 813 269 7912",
    "sg:postcode":"33624",
    "sg:province":"FL",
    "wof:name":"Orion Agency Inc",
    "wof:placetype":"venue"
},
  "geometry": {"coordinates":[-82.526512,28.101717],"type":"Point"}
}