{
  "type": "Feature",
  "properties": {
    "iso:country":"US",
    "sg:address":"68 E Flagler St",
    "sg:city":"Miami",
    "sg:classifiers":[
        {
            "category":"Shopping",
            "subcategory":"Clothing, Apparel, & Fashions",
            "type":"Retail Goods"
        }
    ],
    "sg:phone":"+1 305 577 0973",
    "sg:postcode":"33131",
    "sg:province":"FL",
    "sg:tags":[
        "accessory"
    ],
    "wof:name":"Kara Clothing",
    "wof:placetype":"venue"
},
  "geometry": {"coordinates":[-80.192902,25.774099],"type":"Point"}
}