{
  "type": "Feature",
  "properties": {
    "iso:country":"US",
    "sg:address":"6716 State Rd 471",
    "sg:city":"Bushnell",
    "sg:classifiers":[
        {
            "category":"Shopping",
            "subcategory":"Discount & Variety Stores",
            "type":"Retail Goods"
        }
    ],
    "sg:phone":"+1 352 793 7000",
    "sg:postcode":"33513",
    "sg:province":"FL",
    "sg:tags":[
        "merchandise",
        "general"
    ],
    "wof:name":"Shady Oak Country Store",
    "wof:placetype":"venue"
},
  "geometry": {"coordinates":[-82.054891,28.658498],"type":"Point"}
}