{
  "type": "Feature",
  "properties": {
    "addr:full":"3014 N John Young Pkwy Orlando FL 32804",
    "addr:housenumber":"3014",
    "addr:postcode":"32804",
    "addr:street":"N John Young Pkwy",
    "iso:country":"US",
    "sg:address":"3014 N John Young Pkwy",
    "sg:city":"Orlando",
    "sg:classifiers":[
        {
            "category":"Autos & Motor Vehicles",
            "subcategory":"Automobile Sales",
            "type":"Retail Goods"
        }
    ],
    "sg:phone":"+1 407 290 9292",
    "sg:postcode":"32804",
    "sg:province":"FL",
    "sg:tags":[
        "car",
        "used"
    ],
    "wof:name":"Action Auto Wholesalers",
    "wof:placetype":"venue"
},
  "geometry": {"coordinates":[-81.416568,28.57907],"type":"Point"}
}