{
  "type": "Feature",
  "properties": {
    "iso:country":"US",
    "sg:address":"1443 SW 10th St",
    "sg:city":"Fort Lauderdale",
    "sg:classifiers":[
        {
            "category":"Professional",
            "subcategory":"Management & Consulting",
            "type":"Services"
        }
    ],
    "sg:phone":"+1 954 832 9363",
    "sg:postcode":"33312",
    "sg:province":"FL",
    "sg:tags":[
        "retail",
        "direct",
        "sales"
    ],
    "wof:name":"Natural Selections",
    "wof:placetype":"venue"
},
  "geometry": {"coordinates":[-80.15981600000001,26.109886],"type":"Point"}
}