{
  "type": "Feature",
  "properties": {
    "iso:country":"US",
    "sg:address":"6014 13th Ave",
    "sg:city":"New Port Richey",
    "sg:classifiers":[
        {
            "category":"Retail",
            "subcategory":"Repair Shop",
            "type":"Services"
        }
    ],
    "sg:phone":"+1 727 934 9015",
    "sg:postcode":"34653",
    "sg:province":"FL",
    "sg:tags":[
        "lock",
        "locksmith"
    ],
    "wof:name":"Florida Safe & Lock",
    "wof:placetype":"venue"
},
  "geometry": {"coordinates":[-82.710448,28.225223],"type":"Point"}
}