{
  "type": "Feature",
  "properties": {
    "iso:country":"US",
    "sg:address":"5275 Red Bug Lake Rd",
    "sg:city":"Winter Springs",
    "sg:classifiers":[
        {
            "category":"Restaurant",
            "type":"Food & Drink"
        }
    ],
    "sg:phone":"+1 407 478 7821",
    "sg:postcode":"32708",
    "sg:province":"FL",
    "sg:website":"www.firehousesubs.com",
    "wof:name":"Firehouse Subs",
    "wof:placetype":"venue"
},
  "geometry": {"coordinates":[-81.274771,28.647695],"type":"Point"}
}