{
  "type": "Feature",
  "properties": {
    "iso:country":"US",
    "sg:address":"1709 Hill St",
    "sg:city":"Edgewater",
    "sg:classifiers":[
        {
            "category":"Building & Trades",
            "subcategory":"Construction",
            "type":"Services"
        }
    ],
    "sg:phone":"+1 386 689 0598",
    "sg:postcode":"32132",
    "sg:province":"FL",
    "sg:tags":[
        "contractor"
    ],
    "wof:name":"Bluewater Restorations",
    "wof:placetype":"venue"
},
  "geometry": {"coordinates":[-80.899022,28.974639],"type":"Point"}
}