{
  "type": "Feature",
  "properties": {
    "iso:country":"US",
    "sg:address":"10425 W Sample Rd",
    "sg:city":"Coral Springs",
    "sg:classifiers":[
        {
            "category":"Banks & Credit Unions",
            "subcategory":"Bank",
            "type":"Services"
        }
    ],
    "sg:phone":"+1 954 340 1764",
    "sg:postcode":"33065",
    "sg:province":"FL",
    "wof:name":"Bank Of America",
    "wof:placetype":"venue"
},
  "geometry": {"coordinates":[-80.265219,26.272722],"type":"Point"}
}