{
  "type": "Feature",
  "properties": {
    "iso:country":"US",
    "sg:address":"495 NW 77th St",
    "sg:city":"Miami",
    "sg:classifiers":[
        {
            "category":"Organizations",
            "subcategory":"Religious Organization",
            "type":"Services"
        }
    ],
    "sg:phone":"+1 305 757 1274",
    "sg:postcode":"33150",
    "sg:province":"FL",
    "sg:tags":[
        "child",
        "day",
        "care"
    ],
    "wof:name":"Child Day Care Center",
    "wof:placetype":"venue"
},
  "geometry": {"coordinates":[-80.20489600000001,25.845409],"type":"Point"}
}