{
  "type": "Feature",
  "properties": {
    "addr:full":"6700 Collins Ave Miami Beach FL 33141",
    "addr:housenumber":"6700",
    "addr:postcode":"33141",
    "addr:street":"Collins Ave",
    "iso:country":"US",
    "sg:address":"6700 Collins Ave",
    "sg:city":"Miami Beach",
    "sg:classifiers":[
        {
            "category":"Building & Trades",
            "subcategory":"Construction",
            "type":"Services"
        }
    ],
    "sg:phone":"+1 305 867 4242",
    "sg:postcode":"33141",
    "sg:province":"FL",
    "sg:tags":[
        "contractor"
    ],
    "wof:name":"Edward A Matson Inc",
    "wof:placetype":"venue"
},
  "geometry": {"coordinates":[-80.120369,25.852289],"type":"Point"}
}