{
  "type": "Feature",
  "properties": {
    "addr:full":"1355 Alton Rd Miami Beach FL 33139",
    "addr:housenumber":"1355",
    "addr:postcode":"33139",
    "addr:street":"Alton Rd",
    "iso:country":"US",
    "sg:address":"1355 Alton Rd",
    "sg:city":"Miami Beach",
    "sg:classifiers":[
        {
            "category":"Real Estate",
            "subcategory":"Real Estate Agent",
            "type":"Services"
        }
    ],
    "sg:phone":"+1 305 695 1515",
    "sg:postcode":"33139",
    "sg:province":"FL",
    "wof:name":"Remax Beach Properties",
    "wof:placetype":"venue"
},
  "geometry": {"coordinates":[-80.140959,25.784508],"type":"Point"}
}