{
  "type": "Feature",
  "properties": {
    "addr:full":"11825 Central Pkwy Jacksonville FL 32224",
    "addr:housenumber":"11825",
    "addr:postcode":"32224",
    "addr:street":"Central Pkwy",
    "iso:country":"US",
    "sg:address":"11825 Central Pkwy",
    "sg:city":"Jacksonville",
    "sg:classifiers":[
        {
            "category":"Professional",
            "subcategory":"Advertising",
            "type":"Services"
        }
    ],
    "sg:phone":"+1 904 642 9330",
    "sg:postcode":"32224",
    "sg:province":"FL",
    "sg:tags":[
        "agency"
    ],
    "wof:name":"Media Barnstorm Inc",
    "wof:placetype":"venue"
},
  "geometry": {"coordinates":[-81.510406,30.286694],"type":"Point"}
}