{
  "type": "Feature",
  "properties": {
    "addr:full":"1646 W 45th St Jacksonville FL 32208",
    "addr:housenumber":"1646",
    "addr:postcode":"32208",
    "addr:street":"W 45Th St",
    "iso:country":"US",
    "sg:address":"1646 W 45th St",
    "sg:city":"Jacksonville",
    "sg:classifiers":[
        {
            "category":"Personal",
            "subcategory":"Beauty Salon",
            "type":"Services"
        }
    ],
    "sg:phone":"+1 904 764 4000",
    "sg:postcode":"32208",
    "sg:province":"FL",
    "sg:tags":[
        "manicuring"
    ],
    "wof:name":"Nisha Nails",
    "wof:placetype":"venue"
},
  "geometry": {"coordinates":[-81.685564,30.373897],"type":"Point"}
}