{
  "type": "Feature",
  "properties": {
    "addr:full":"861 Ballough Rd Daytona Beach FL 32114",
    "addr:housenumber":"861",
    "addr:postcode":"32114",
    "addr:street":"Ballough Rd",
    "iso:country":"US",
    "sg:address":"861 Ballough Rd",
    "sg:city":"Daytona Beach",
    "sg:classifiers":[
        {
            "category":"Real Estate",
            "subcategory":"Real Estate Agent",
            "type":"Services"
        }
    ],
    "sg:phone":"+1 386 255 5400",
    "sg:postcode":"32114",
    "sg:province":"FL",
    "wof:name":"Sun Belt Realty",
    "wof:placetype":"venue"
},
  "geometry": {"coordinates":[-81.02340100000001,29.225885],"type":"Point"}
}