{
  "type": "Feature",
  "properties": {
    "addr:full":"2205 US Hwy 27 Sebring FL 33870",
    "addr:housenumber":"2205",
    "addr:postcode":"33870",
    "addr:street":"Us Hwy 27",
    "iso:country":"US",
    "sg:address":"2205 US Hwy 27",
    "sg:city":"Sebring",
    "sg:classifiers":[
        {
            "category":"Restaurant",
            "type":"Food & Drink"
        }
    ],
    "sg:phone":"+1 863 385 4844",
    "sg:postcode":"33870",
    "sg:province":"FL",
    "wof:name":"Burger King",
    "wof:placetype":"venue"
},
  "geometry": {"coordinates":[-81.491587,27.505078],"type":"Point"}
}