{
  "type": "Feature",
  "properties": {
    "iso:country":"US",
    "sg:address":"3599 University Blvd S",
    "sg:city":"Jacksonville",
    "sg:classifiers":[
        {
            "category":"Health Services",
            "subcategory":"Doctor",
            "type":"Services"
        }
    ],
    "sg:phone":"+1 904 306 0266",
    "sg:postcode":"32216",
    "sg:province":"FL",
    "sg:tags":[
        "medical"
    ],
    "wof:name":"Hossam A Hessen MD",
    "wof:placetype":"venue"
},
  "geometry": {"coordinates":[-81.60221,30.289752],"type":"Point"}
}