{
  "type": "Feature",
  "properties": {
    "addr:full":"4433 SW 14th Ave Cape Coral FL 33914",
    "addr:housenumber":"4433",
    "addr:postcode":"33914",
    "addr:street":"Sw 14Th Ave",
    "iso:country":"US",
    "sg:address":"4433 SW 14th Ave",
    "sg:city":"Cape Coral",
    "sg:classifiers":[
        {
            "category":"Organizations",
            "subcategory":"Religious Organization",
            "type":"Services"
        }
    ],
    "sg:phone":"+1 239 540 8710",
    "sg:postcode":"33914",
    "sg:province":"FL",
    "wof:name":"Templo Cristiano La Estrella",
    "wof:placetype":"venue"
},
  "geometry": {"coordinates":[-82.002825,26.567964],"type":"Point"}
}