{
  "type": "Feature",
  "properties": {
    "addr:full":"3048 Jog Rd Lake Worth FL 33467",
    "addr:housenumber":"3048",
    "addr:postcode":"33467",
    "addr:street":"Jog Rd",
    "iso:country":"US",
    "sg:address":"3048 Jog Rd",
    "sg:city":"Lake Worth",
    "sg:classifiers":[
        {
            "category":"Manufacturing",
            "subcategory":"Chemicals & Compounds",
            "type":"Manufacturing & Wholesale Goods"
        }
    ],
    "sg:phone":"+1 561 968 6017",
    "sg:postcode":"33467",
    "sg:province":"FL",
    "sg:tags":[
        "synthetic",
        "rubber",
        "mfg"
    ],
    "wof:name":"Triexe Management Inc",
    "wof:placetype":"venue"
},
  "geometry": {"coordinates":[-80.146044,26.631282],"type":"Point"}
}