{
  "type": "Feature",
  "properties": {
    "addr:full":"2020 E 3rd Ave Hialeah FL 33010",
    "addr:housenumber":"2020",
    "addr:postcode":"33010",
    "addr:street":"E 3Rd Ave",
    "iso:country":"US",
    "sg:address":"2020 E 3rd Ave",
    "sg:city":"Hialeah",
    "sg:classifiers":[
        {
            "category":"Banks & Credit Unions",
            "subcategory":"Financial Services",
            "type":"Services"
        }
    ],
    "sg:phone":"+1 305 887 4206",
    "sg:postcode":"33010",
    "sg:province":"FL",
    "sg:tags":[
        "investor"
    ],
    "wof:name":"Algil Investments Inc",
    "wof:placetype":"venue"
},
  "geometry": {"coordinates":[-80.276105,25.840831],"type":"Point"}
}