{
  "type": "Feature",
  "properties": {
    "addr:full":"1554 Royal Cir Apopka FL 32703",
    "addr:housenumber":"1554",
    "addr:postcode":"32703",
    "addr:street":"Royal Cir",
    "iso:country":"US",
    "sg:address":"1554 Royal Cir",
    "sg:city":"Apopka",
    "sg:classifiers":[
        {
            "category":"Autos & Motor Vehicles",
            "subcategory":"Auto Supplies",
            "type":"Retail Goods"
        }
    ],
    "sg:phone":"+1 407 290 1212",
    "sg:postcode":"32703",
    "sg:province":"FL",
    "sg:tags":[
        "equipment",
        "air",
        "conditioning",
        "automobile"
    ],
    "wof:name":"Protek Auto Air & Sound",
    "wof:placetype":"venue"
},
  "geometry": {"coordinates":[-81.44289499999999,28.652103],"type":"Point"}
}