{
  "type": "Feature",
  "properties": {
    "addr:full":"1531 W 23rd St Miami Beach FL 33140",
    "addr:housenumber":"1531",
    "addr:postcode":"33140",
    "addr:street":"W 23Rd St",
    "iso:country":"US",
    "sg:address":"1531 W 23rd St",
    "sg:city":"Miami Beach",
    "sg:classifiers":[
        {
            "category":"Professional",
            "type":"Services"
        }
    ],
    "sg:phone":"+1 305 604 9815",
    "sg:postcode":"33140",
    "sg:province":"FL",
    "wof:name":"Axle of Exus Tiara Saint",
    "wof:placetype":"venue"
},
  "geometry": {"coordinates":[-80.143745,25.799232],"type":"Point"}
}