{
  "type": "Feature",
  "properties": {
    "iso:country":"US",
    "sg:address":"8825 Biscayne Blvd",
    "sg:city":"Miami Shores",
    "sg:classifiers":[
        {
            "category":"Food & Beverages",
            "subcategory":"Groceries & Convenience Stores",
            "type":"Retail Goods"
        }
    ],
    "sg:phone":"+1 305 756 9999",
    "sg:postcode":"33138",
    "sg:province":"FL",
    "sg:tags":[
        "grocer"
    ],
    "wof:name":"Philippine Food Mart",
    "wof:placetype":"venue"
},
  "geometry": {"coordinates":[-80.184859,25.856117],"type":"Point"}
}