{
  "type": "Feature",
  "properties": {
    "addr:full":"5390 Brian Samuel Ln Milton FL 32570",
    "addr:housenumber":"5390",
    "addr:postcode":"32570",
    "addr:street":"Brian Samuel Ln",
    "iso:country":"US",
    "sg:address":"5390 Brian Samuel Ln",
    "sg:city":"Milton",
    "sg:classifiers":[
        {
            "category":"Building & Trades",
            "subcategory":"Construction",
            "type":"Services"
        }
    ],
    "sg:phone":"+1 850 623 1311",
    "sg:postcode":"32570",
    "sg:province":"FL",
    "sg:tags":[
        "house"
    ],
    "wof:name":"Bentley Builders",
    "wof:placetype":"venue"
},
  "geometry": {"coordinates":[-87.098682,30.629539],"type":"Point"}
}