{
  "type": "Feature",
  "properties": {
    "addr:full":"1370 Pinehurst Dr Spring Hill FL 34606",
    "addr:housenumber":"1370",
    "addr:postcode":"34606",
    "addr:street":"Pinehurst Dr",
    "iso:country":"US",
    "sg:address":"1370 Pinehurst Dr",
    "sg:city":"Spring Hill",
    "sg:classifiers":[
        {
            "category":"Personal",
            "subcategory":"Barber",
            "type":"Services"
        }
    ],
    "sg:phone":"+1 352 683 8174",
    "sg:postcode":"34606",
    "sg:province":"FL",
    "sg:tags":[
        "shop"
    ],
    "wof:name":"Spring Hill Barber Shop",
    "wof:placetype":"venue"
},
  "geometry": {"coordinates":[-82.625439,28.460458],"type":"Point"}
}