{
  "type": "Feature",
  "properties": {
    "iso:country":"US",
    "sg:address":"512 Commerce Dr",
    "sg:city":"Panama City",
    "sg:classifiers":[
        {
            "category":"Building & Trades",
            "subcategory":"Construction",
            "type":"Services"
        }
    ],
    "sg:phone":"+1 850 234 5228",
    "sg:postcode":"32408",
    "sg:province":"FL",
    "sg:tags":[
        "home",
        "builder"
    ],
    "sg:website":"www.tcresinc.com",
    "wof:name":"Town & Country Residences Inc",
    "wof:placetype":"venue"
},
  "geometry": {"coordinates":[-85.76194099999999,30.180711],"type":"Point"}
}