{
  "type": "Feature",
  "properties": {
    "addr:full":"515 E Altamonte Dr Altamonte Springs FL 32701",
    "addr:housenumber":"515",
    "addr:postcode":"32701",
    "addr:street":"E Altamonte Dr",
    "iso:country":"US",
    "sg:address":"515 E Altamonte Dr",
    "sg:city":"Altamonte Springs",
    "sg:classifiers":[
        {
            "category":"Home & Garden",
            "subcategory":"Household Appliances",
            "type":"Retail Goods"
        }
    ],
    "sg:phone":"+1 407 339 0801",
    "sg:postcode":"32701",
    "sg:province":"FL",
    "wof:name":"Oreck",
    "wof:placetype":"venue"
},
  "geometry": {"coordinates":[-81.37131599999999,28.663957],"type":"Point"}
}