{
  "type": "Feature",
  "properties": {
    "iso:country":"US",
    "sg:address":"7201 N Pine Island Rd",
    "sg:city":"Fort Lauderdale",
    "sg:classifiers":[
        {
            "category":"Health Services",
            "subcategory":"Medical Lab",
            "type":"Services"
        }
    ],
    "sg:phone":"+1 954 720 0903",
    "sg:postcode":"33321",
    "sg:province":"FL",
    "sg:tags":[
        "testing",
        "center"
    ],
    "wof:name":"Florida M R I",
    "wof:placetype":"venue"
},
  "geometry": {"coordinates":[-80.26942699999999,26.211779],"type":"Point"}
}