{
  "type": "Feature",
  "properties": {
    "iso:country":"US",
    "sg:address":"56 Franklin Ave",
    "sg:city":"Ponte Vedra Beach",
    "sg:classifiers":[
        {
            "category":"Real Estate",
            "subcategory":"Real Estate Agent",
            "type":"Services"
        }
    ],
    "sg:phone":"+1 904 285 6610",
    "sg:postcode":"32082",
    "sg:province":"FL",
    "wof:name":"Valerie H Shaw PA",
    "wof:placetype":"venue"
},
  "geometry": {"coordinates":[-81.383341,30.231004],"type":"Point"}
}