{
  "type": "Feature",
  "properties": {
    "iso:country":"US",
    "sg:address":"1723 SE 47th Ter",
    "sg:city":"Cape Coral",
    "sg:classifiers":[
        {
            "category":"Professional",
            "subcategory":"Computer Services",
            "type":"Services"
        }
    ],
    "sg:phone":"+1 239 945 6433",
    "sg:postcode":"33904",
    "sg:province":"FL",
    "sg:tags":[
        "programing",
        "custom"
    ],
    "wof:name":"Multisoft Corporation",
    "wof:placetype":"venue"
},
  "geometry": {"coordinates":[-81.940555,26.563801],"type":"Point"}
}