{
  "type": "Feature",
  "properties": {
    "iso:country":"US",
    "sg:address":"3269 Huntington Place Dr",
    "sg:city":"Sarasota",
    "sg:classifiers":[
        {
            "category":"Building & Trades",
            "subcategory":"Construction",
            "type":"Services"
        }
    ],
    "sg:phone":"+1 941 350 5551",
    "sg:postcode":"34237",
    "sg:province":"FL",
    "sg:tags":[
        "resurfacing",
        "laying",
        "refinishing",
        "floor"
    ],
    "wof:name":"Go 2 Guys",
    "wof:placetype":"venue"
},
  "geometry": {"coordinates":[-82.500441,27.34817],"type":"Point"}
}