{
  "type": "Feature",
  "properties": {
    "addr:full":"4160 Waterview Loop Winter Park FL 32792",
    "addr:housenumber":"4160",
    "addr:postcode":"32792",
    "addr:street":"Waterview Loop",
    "iso:country":"US",
    "sg:address":"4160 Waterview Loop",
    "sg:city":"Winter Park",
    "sg:classifiers":[
        {
            "category":"Professional",
            "subcategory":"Research",
            "type":"Services"
        }
    ],
    "sg:phone":"+1 407 673 4971",
    "sg:postcode":"32792",
    "sg:province":"FL",
    "sg:tags":[
        "commercial",
        "physical"
    ],
    "wof:name":"Omnicare",
    "wof:placetype":"venue"
},
  "geometry": {"coordinates":[-81.278246,28.630638],"type":"Point"}
}