{
  "type": "Feature",
  "properties": {
    "iso:country":"US",
    "sg:address":"231 3rd St SW",
    "sg:city":"Winter Haven",
    "sg:classifiers":[
        {
            "category":"Building & Trades",
            "subcategory":"Construction",
            "type":"Services"
        }
    ],
    "sg:phone":"+1 863 293 5291",
    "sg:postcode":"33880",
    "sg:province":"FL",
    "sg:tags":[
        "contractor"
    ],
    "wof:name":"Schneider Sheet Metal",
    "wof:placetype":"venue"
},
  "geometry": {"coordinates":[-81.73061199999999,28.020625],"type":"Point"}
}