{
  "type": "Feature",
  "properties": {
    "iso:country":"US",
    "sg:address":"2977 W Broward Blvd",
    "sg:city":"Fort Lauderdale",
    "sg:classifiers":[
        {
            "category":"Wholesale",
            "subcategory":"Seafood",
            "type":"Manufacturing & Wholesale Goods"
        }
    ],
    "sg:phone":"+1 954 587 0177",
    "sg:postcode":"33312",
    "sg:province":"FL",
    "wof:name":"Keystone Intl Seafoods Inc",
    "wof:placetype":"venue"
},
  "geometry": {"coordinates":[-80.183909,26.121397],"type":"Point"}
}