{
  "type": "Feature",
  "properties": {
    "addr:full":"228 Volusia Dr SE Winter Haven FL 33884",
    "addr:housenumber":"228",
    "addr:postcode":"33884",
    "addr:street":"Volusia Dr Se",
    "iso:country":"US",
    "sg:address":"228 Volusia Dr SE",
    "sg:city":"Winter Haven",
    "sg:classifiers":[
        {
            "category":"Communications",
            "subcategory":"Radio Station",
            "type":"Services"
        }
    ],
    "sg:phone":"+1 863 324 4437",
    "sg:postcode":"33884",
    "sg:province":"FL",
    "sg:tags":[
        "broadcast"
    ],
    "wof:name":"Liberty Broadcast Services",
    "wof:placetype":"venue"
},
  "geometry": {"coordinates":[-81.69964400000001,28.008457],"type":"Point"}
}