{
  "type": "Feature",
  "properties": {
    "iso:country":"US",
    "sg:address":"1775 W 60th St",
    "sg:city":"Hialeah",
    "sg:classifiers":[
        {
            "category":"Education",
            "subcategory":"School",
            "type":"Public Place"
        }
    ],
    "sg:phone":"+1 305 691 3960",
    "sg:postcode":"33012",
    "sg:province":"FL",
    "wof:name":"Miami-Dade County Public Schools-158",
    "wof:placetype":"venue"
},
  "geometry": {"coordinates":[-80.31872799999999,25.87702],"type":"Point"}
}