{
  "type": "Feature",
  "properties": {
    "addr:full":"8284 NW 68th St Miami FL 33166",
    "addr:housenumber":"8284",
    "addr:postcode":"33166",
    "addr:street":"Nw 68Th St",
    "iso:country":"US",
    "sg:address":"8284 NW 68th St",
    "sg:city":"Miami",
    "sg:classifiers":[
        {
            "category":"Wholesale",
            "subcategory":"Non-durable Goods",
            "type":"Manufacturing & Wholesale Goods"
        }
    ],
    "sg:phone":"+1 786 331 7400",
    "sg:postcode":"33166",
    "sg:province":"FL",
    "sg:tags":[
        "bank",
        "foreign"
    ],
    "wof:name":"Serlin LLC",
    "wof:placetype":"venue"
},
  "geometry": {"coordinates":[-80.332525,25.835195],"type":"Point"}
}