{
  "type": "Feature",
  "properties": {
    "addr:full":"800 N Charleston Ave Fort Meade FL 33841",
    "addr:housenumber":"800",
    "addr:postcode":"33841",
    "addr:street":"N Charleston Ave",
    "iso:country":"US",
    "sg:address":"800 N Charleston Ave",
    "sg:city":"Fort Meade",
    "sg:classifiers":[
        {
            "category":"Bars & Pubs",
            "type":"Food & Drink"
        }
    ],
    "sg:phone":"+1 863 285 8732",
    "sg:postcode":"33841",
    "sg:province":"FL",
    "sg:tags":[
        "lounge",
        "cocktail"
    ],
    "wof:name":"Pit Stop Lounge & Package",
    "wof:placetype":"venue"
},
  "geometry": {"coordinates":[-81.801519,27.761349],"type":"Point"}
}