{
  "type": "Feature",
  "properties": {
    "iso:country":"US",
    "sg:address":"6401 SW 87th Ave",
    "sg:city":"Miami",
    "sg:classifiers":[
        {
            "category":"Professional",
            "subcategory":"Lawyer & Legal Services",
            "type":"Services"
        }
    ],
    "sg:phone":"+1 305 275 8500",
    "sg:postcode":"33173",
    "sg:province":"FL",
    "wof:name":"Quintero Mario Atty",
    "wof:placetype":"venue"
},
  "geometry": {"coordinates":[-80.334503,25.709499],"type":"Point"}
}