{
  "type": "Feature",
  "properties": {
    "iso:country":"US",
    "sg:address":"Fl",
    "sg:city":"Winter Park",
    "sg:classifiers":[
        {
            "category":"Building & Trades",
            "subcategory":"Cleaning & Sanitation",
            "type":"Services"
        },
        {
            "category":"Personal",
            "type":"Services"
        }
    ],
    "sg:phone":"+1 407 645 5755",
    "sg:postcode":"32789",
    "sg:province":"FL",
    "sg:tags":[
        "party",
        "planning",
        "event",
        "home"
    ],
    "wof:name":"Anna's Housekeeping Personnel Service Inc",
    "wof:placetype":"venue"
},
  "geometry": {"coordinates":[-81.35230300000001,28.6005],"type":"Point"}
}