{
  "type": "Feature",
  "properties": {
    "iso:country":"US",
    "sg:address":"13833 Wellington Trce",
    "sg:city":"Wellington",
    "sg:classifiers":[
        {
            "category":"Professional",
            "subcategory":"Detective & Security Services",
            "type":"Services"
        }
    ],
    "sg:phone":"+1 561 792 8402",
    "sg:postcode":"33414",
    "sg:province":"FL",
    "wof:name":"James Price & Assoc",
    "wof:placetype":"venue"
},
  "geometry": {"coordinates":[-80.266177,26.662603],"type":"Point"}
}