{
  "type": "Feature",
  "properties": {
    "iso:country":"US",
    "sg:address":"12645 New Brittany Blvd",
    "sg:city":"Fort Myers",
    "sg:classifiers":[
        {
            "category":"Health Services",
            "subcategory":"Doctor",
            "type":"Services"
        }
    ],
    "sg:phone":"+1 239 278 0400",
    "sg:postcode":"33907",
    "sg:province":"FL",
    "sg:tags":[
        "medicine",
        "internal"
    ],
    "wof:name":"Troast Nancy M DO",
    "wof:placetype":"venue"
},
  "geometry": {"coordinates":[-81.88069900000001,26.5592],"type":"Point"}
}