{
  "type": "Feature",
  "properties": {
    "addr:full":"6000 Fall River Dr New Port Richey FL 34655",
    "addr:postcode":"6000;34655",
    "addr:street":"Fall River Dr",
    "iso:country":"US",
    "sg:address":"6000 Fall River Dr",
    "sg:city":"New Port Richey",
    "sg:classifiers":[
        {
            "category":"Organizations",
            "subcategory":"Religious Organization",
            "type":"Services"
        }
    ],
    "sg:phone":"+1 727 372 9077",
    "sg:postcode":"34655",
    "sg:province":"FL",
    "sg:tags":[
        "clergy"
    ],
    "wof:name":"Kenneth F Gruebel",
    "wof:placetype":"venue"
},
  "geometry": {"coordinates":[-82.665508,28.245365],"type":"Point"}
}