{
  "type": "Feature",
  "properties": {
    "addr:full":"2025 Wellington Green Dr West Palm Beach FL 33414",
    "addr:housenumber":"2025",
    "addr:postcode":"33414",
    "addr:street":"Wellington Green Dr",
    "iso:country":"US",
    "sg:address":"2025 Wellington Green Dr",
    "sg:city":"West Palm Beach",
    "sg:classifiers":[
        {
            "category":"Restaurant",
            "type":"Food & Drink"
        }
    ],
    "sg:menulink":"http://www.allmenus.com/fl/sunshine-parkway/223317-buca-di-beppo/menu/",
    "sg:phone":"+1 561 790 3287",
    "sg:postcode":"33414",
    "sg:province":"FL",
    "sg:tags":[
        "italian"
    ],
    "wof:name":"Buca Di Beppo",
    "wof:placetype":"venue"
},
  "geometry": {"coordinates":[-80.21810600000001,26.650632],"type":"Point"}
}