{
  "type": "Feature",
  "properties": {
    "iso:country":"US",
    "sg:address":"9075 US Hwy 1",
    "sg:city":"Port St Lucie",
    "sg:classifiers":[
        {
            "category":"Health Services",
            "subcategory":"Hospital",
            "type":"Services"
        }
    ],
    "sg:phone":"+1 772 398 9898",
    "sg:postcode":"34982",
    "sg:province":"FL",
    "wof:name":"Surgical Center Of-Treasure",
    "wof:placetype":"venue"
},
  "geometry": {"coordinates":[-80.301846,27.294305],"type":"Point"}
}