{
  "type": "Feature",
  "properties": {
    "iso:country":"US",
    "sg:address":"617 W Industrial Ave",
    "sg:city":"Boynton Beach",
    "sg:classifiers":[
        {
            "category":"Building & Trades",
            "subcategory":"Landscaping Services",
            "type":"Services"
        }
    ],
    "sg:phone":"+1 561 734 8769",
    "sg:postcode":"33426",
    "sg:province":"FL",
    "wof:name":"David Wagner",
    "wof:placetype":"venue"
},
  "geometry": {"coordinates":[-80.07652899999999,26.535638],"type":"Point"}
}