{
  "type": "Feature",
  "properties": {
    "iso:country":"US",
    "sg:address":"26811 S Bay Dr",
    "sg:city":"Bonita Springs",
    "sg:classifiers":[
        {
            "category":"Banks & Credit Unions",
            "subcategory":"Investment Brokerage",
            "type":"Services"
        }
    ],
    "sg:phone":"+1 239 948 1777",
    "sg:postcode":"34134",
    "sg:province":"FL",
    "sg:tags":[
        "security"
    ],
    "wof:name":"Stanford Group Company",
    "wof:placetype":"venue"
},
  "geometry": {"coordinates":[-81.808177,26.351363],"type":"Point"}
}