{
  "type": "Feature",
  "properties": {
    "iso:country":"US",
    "sg:address":"1909 E Livingston St",
    "sg:city":"Orlando",
    "sg:classifiers":[
        {
            "category":"Manufacturing",
            "subcategory":"Tools & Machinery",
            "type":"Manufacturing & Wholesale Goods"
        }
    ],
    "sg:phone":"+1 407 228 0191",
    "sg:postcode":"32803",
    "sg:province":"FL",
    "sg:tags":[
        "mfg",
        "ophthalmic"
    ],
    "wof:name":"Eye Care Wear Inc",
    "wof:placetype":"venue"
},
  "geometry": {"coordinates":[-81.356869,28.547761],"type":"Point"}
}