{
  "type": "Feature",
  "properties": {
    "addr:full":"5300 NW 12th Ave Fort Lauderdale FL 33309",
    "addr:housenumber":"5300",
    "addr:postcode":"33309",
    "addr:street":"Nw 12Th Ave",
    "iso:country":"US",
    "sg:address":"5300 NW 12th Ave",
    "sg:city":"Fort Lauderdale",
    "sg:classifiers":[
        {
            "category":"Home & Garden",
            "subcategory":"Building Materials",
            "type":"Retail Goods"
        }
    ],
    "sg:phone":"+1 954 772 5055",
    "sg:postcode":"33309",
    "sg:province":"FL",
    "sg:tags":[
        "screen",
        "window"
    ],
    "wof:name":"Eclipse Screens Of Florida Inc",
    "wof:placetype":"venue"
},
  "geometry": {"coordinates":[-80.159525,26.193462],"type":"Point"}
}