{
  "type": "Feature",
  "properties": {
    "iso:country":"US",
    "sg:address":"510 SE 74 St",
    "sg:city":"Gainesville",
    "sg:classifiers":[
        {
            "category":"Banks & Credit Unions",
            "subcategory":"Bank",
            "type":"Services"
        }
    ],
    "sg:phone":"+1 352 374 9808",
    "sg:postcode":"32641",
    "sg:province":"FL",
    "sg:tags":[
        "personal",
        "institution"
    ],
    "wof:name":"Associates Housing Finance LLC",
    "wof:placetype":"venue"
},
  "geometry": {"coordinates":[-82.23997199999999,29.647612],"type":"Point"}
}