{
  "type": "Feature",
  "properties": {
    "addr:full":"651 Carl Floyd Rd Winter Haven FL 33884",
    "addr:housenumber":"651",
    "addr:postcode":"33884",
    "addr:street":"Carl Floyd Rd",
    "iso:country":"US",
    "sg:address":"651 Carl Floyd Rd",
    "sg:city":"Winter Haven",
    "sg:classifiers":[
        {
            "category":"Organizations",
            "subcategory":"Religious Organization",
            "type":"Services"
        }
    ],
    "sg:phone":"+1 863 326 9110",
    "sg:postcode":"33884",
    "sg:province":"FL",
    "sg:tags":[
        "church"
    ],
    "wof:name":"New Hope Assembly",
    "wof:placetype":"venue"
},
  "geometry": {"coordinates":[-81.677496,28.015458],"type":"Point"}
}