{
  "type": "Feature",
  "properties": {
    "iso:country":"US",
    "sg:address":"3256 NW 24th Street Rd",
    "sg:city":"Miami",
    "sg:classifiers":[
        {
            "category":"Retail",
            "subcategory":"Auto Rental",
            "type":"Services"
        }
    ],
    "sg:phone":"+1 407 851 2202",
    "sg:postcode":"33142",
    "sg:province":"FL",
    "sg:tags":[
        "car"
    ],
    "wof:name":"Global Rent A Car",
    "wof:placetype":"venue"
},
  "geometry": {"coordinates":[-80.24749799999999,25.795601],"type":"Point"}
}