{
  "type": "Feature",
  "properties": {
    "addr:full":"429 W State Road 436 Altamonte Springs FL 32714",
    "addr:housenumber":"429",
    "addr:postcode":"32714",
    "addr:street":"W State Road 436",
    "iso:country":"US",
    "sg:address":"429 W State Road 436",
    "sg:city":"Altamonte Springs",
    "sg:classifiers":[
        {
            "category":"Restaurant",
            "type":"Food & Drink"
        }
    ],
    "sg:phone":"+1 407 862 8327",
    "sg:postcode":"32714",
    "sg:province":"FL",
    "sg:tags":[
        "traditional",
        "american"
    ],
    "sg:website":"www.bostonmarket.com",
    "wof:name":"Boston Market",
    "wof:placetype":"venue"
},
  "geometry": {"coordinates":[-81.39830000000001,28.6618],"type":"Point"}
}