{
  "type": "Feature",
  "properties": {
    "iso:country":"US",
    "sg:address":"8280 Marbella View Ct",
    "sg:city":"Orlando",
    "sg:classifiers":[
        {
            "category":"Organizations",
            "subcategory":"Non-profit Organization",
            "type":"Services"
        }
    ],
    "sg:phone":"+1 407 671 7582",
    "sg:postcode":"32817",
    "sg:province":"FL",
    "sg:tags":[
        "animal",
        "show"
    ],
    "wof:name":"Madkat Dressage",
    "wof:placetype":"venue"
},
  "geometry": {"coordinates":[-81.27317600000001,28.598995],"type":"Point"}
}