{
  "type": "Feature",
  "properties": {
    "iso:country":"US",
    "sg:address":"5874 W Flagler St",
    "sg:city":"Miami",
    "sg:classifiers":[
        {
            "category":"Shopping",
            "subcategory":"Party Supplies",
            "type":"Retail Goods"
        }
    ],
    "sg:phone":"+1 305 263 3353",
    "sg:postcode":"33144",
    "sg:province":"FL",
    "sg:tags":[
        "favors",
        "decoration",
        "rental"
    ],
    "wof:name":"A Ana Party Rental And Distributors",
    "wof:placetype":"venue"
},
  "geometry": {"coordinates":[-80.291292,25.770754],"type":"Point"}
}