{
  "type": "Feature",
  "properties": {
    "addr:full":"801 Dixon Blvd Ste 1137 Cocoa FL 32922",
    "addr:housenumber":"801",
    "addr:postcode":"32922",
    "addr:street":"Dixon Blvd Ste 1137",
    "iso:country":"US",
    "sg:address":"801 Dixon Blvd Ste 1137",
    "sg:city":"Cocoa",
    "sg:phone":"+1 321 639 8299",
    "sg:postcode":"32922",
    "sg:province":"FL",
    "wof:name":"China Garden",
    "wof:placetype":"venue"
},
  "geometry": {"coordinates":[-80.73906700000001,28.37776],"type":"Point"}
}