{
  "type": "Feature",
  "properties": {
    "addr:full":"2110 NE 206th St Miami FL 33179",
    "addr:housenumber":"2110",
    "addr:postcode":"33179",
    "addr:street":"Ne 206Th St",
    "iso:country":"US",
    "sg:address":"2110 NE 206th St",
    "sg:city":"Miami",
    "sg:classifiers":[
        {
            "category":"Education",
            "subcategory":"Special Training",
            "type":"Public Place"
        }
    ],
    "sg:phone":"+1 305 653 8777",
    "sg:postcode":"33179",
    "sg:province":"FL",
    "wof:name":"Prescrbing Psychlgsts Register",
    "wof:placetype":"venue"
},
  "geometry": {"coordinates":[-80.159373,25.965843],"type":"Point"}
}