{
  "type": "Feature",
  "properties": {
    "addr:full":"5625 Hollow Oak Rd Orlando FL 32808",
    "addr:housenumber":"5625",
    "addr:postcode":"32808",
    "addr:street":"Hollow Oak Rd",
    "iso:country":"US",
    "sg:address":"5625 Hollow Oak Rd",
    "sg:city":"Orlando",
    "sg:classifiers":[
        {
            "category":"Building & Trades",
            "subcategory":"Construction",
            "type":"Services"
        }
    ],
    "sg:phone":"+1 407 295 6370",
    "sg:postcode":"32808",
    "sg:province":"FL",
    "sg:tags":[
        "contractor"
    ],
    "wof:name":"Alpha Drywall Services",
    "wof:placetype":"venue"
},
  "geometry": {"coordinates":[-81.458838,28.584962],"type":"Point"}
}