{
  "type": "Feature",
  "properties": {
    "addr:full":"1950 NW 110th Ave Miami FL 33172",
    "addr:housenumber":"1950",
    "addr:postcode":"33172",
    "addr:street":"Nw 110Th Ave",
    "iso:country":"US",
    "sg:address":"1950 NW 110th Ave",
    "sg:city":"Miami",
    "sg:classifiers":[
        {
            "category":"Freight",
            "type":"Transportation"
        },
        {
            "category":"Retail",
            "subcategory":"Auto Repair",
            "type":"Services"
        }
    ],
    "sg:phone":"+1 305 718 8522",
    "sg:postcode":"33172",
    "sg:province":"FL",
    "sg:tags":[
        "repairing",
        "automobile",
        "local",
        "except",
        "trucking"
    ],
    "wof:name":"C J Menendez Co Inc",
    "wof:placetype":"venue"
},
  "geometry": {"coordinates":[-80.37436700000001,25.794664],"type":"Point"}
}