{
  "type": "Feature",
  "properties": {
    "addr:full":"11205 NW 10th Pl Coral Springs FL 33071",
    "addr:housenumber":"11205",
    "addr:postcode":"33071",
    "addr:street":"Nw 10Th Pl",
    "iso:country":"US",
    "sg:address":"11205 NW 10th Pl",
    "sg:city":"Coral Springs",
    "sg:classifiers":[
        {
            "category":"Building & Trades",
            "subcategory":"Construction",
            "type":"Services"
        }
    ],
    "sg:phone":"+1 954 575 4993",
    "sg:postcode":"33071",
    "sg:province":"FL",
    "sg:tags":[
        "painter"
    ],
    "wof:name":"Asa Pressure Cleaning",
    "wof:placetype":"venue"
},
  "geometry": {"coordinates":[-80.275401,26.243675],"type":"Point"}
}