{
  "type": "Feature",
  "properties": {
    "iso:country":"US",
    "sg:address":"2100 US Hwy 27",
    "sg:city":"Sebring",
    "sg:classifiers":[
        {
            "category":"Food & Beverages",
            "subcategory":"Groceries & Convenience Stores",
            "type":"Retail Goods"
        }
    ],
    "sg:phone":"+1 863 314 9074",
    "sg:postcode":"33870",
    "sg:province":"FL",
    "sg:tags":[
        "product"
    ],
    "wof:name":"G & G Food Corp",
    "wof:placetype":"venue"
},
  "geometry": {"coordinates":[-81.491846,27.506204],"type":"Point"}
}