{
  "type": "Feature",
  "properties": {
    "addr:full":"13881 Plantation Rd Ste 4 Fort Myers FL 33912",
    "addr:housenumber":"13881",
    "addr:postcode":"myers fl 33912",
    "addr:street":"Plantation Rd Ste 4",
    "iso:country":"US",
    "sg:address":"13881 Plantation Rd Ste 4",
    "sg:city":"Fort Myers",
    "sg:classifiers":[
        {
            "category":"Home & Garden",
            "subcategory":"Carpets & Floor Coverings",
            "type":"Retail Goods"
        }
    ],
    "sg:phone":"+1 239 939 2660",
    "sg:postcode":"33912",
    "sg:province":"FL",
    "sg:tags":[
        "flooring"
    ],
    "wof:name":"Turley Flooring Systems Inc",
    "wof:placetype":"venue"
},
  "geometry": {"coordinates":[-81.846784,26.540468],"type":"Point"}
}