{
  "type": "Feature",
  "properties": {
    "iso:country":"US",
    "sg:address":"1717 N Pace Blvd",
    "sg:city":"Pensacola",
    "sg:classifiers":[
        {
            "category":"Professional",
            "subcategory":"Management & Consulting",
            "type":"Services"
        }
    ],
    "sg:phone":"+1 850 432 8665",
    "sg:postcode":"32505",
    "sg:province":"FL",
    "sg:tags":[
        "construction"
    ],
    "sg:website":"www.gulfsouth-contractors.com",
    "wof:name":"Gulf South Contractors Inc",
    "wof:placetype":"venue"
},
  "geometry": {"coordinates":[-87.240729,30.430986],"type":"Point"}
}