{
  "type": "Feature",
  "properties": {
    "iso:country":"US",
    "sg:address":"126 N 32nd Ave",
    "sg:city":"Hollywood",
    "sg:classifiers":[
        {
            "category":"Personal",
            "subcategory":"Beauty Salon",
            "type":"Services"
        },
        {
            "category":"Personal",
            "subcategory":"Barber",
            "type":"Services"
        }
    ],
    "sg:phone":"+1 954 450 8419",
    "sg:postcode":"33021",
    "sg:province":"FL",
    "sg:tags":[
        "hair",
        "accessory",
        "stylist",
        "supply"
    ],
    "sg:website":"http://www.supercuts.com/",
    "wof:name":"Supercuts",
    "wof:placetype":"venue"
},
  "geometry": {"coordinates":[-80.172256,26.011395],"type":"Point"}
}