{
  "type": "Feature",
  "properties": {
    "addr:full":"12960 SW 103rd Ter Miami FL 33186",
    "addr:housenumber":"12960",
    "addr:postcode":"33186",
    "addr:street":"Sw 103Rd Ter",
    "iso:country":"US",
    "sg:address":"12960 SW 103rd Ter",
    "sg:city":"Miami",
    "sg:classifiers":[
        {
            "category":"Professional",
            "subcategory":"Engineering",
            "type":"Services"
        }
    ],
    "sg:phone":"+1 305 388 1952",
    "sg:postcode":"33186",
    "sg:province":"FL",
    "wof:name":"Tariche-Valderrama",
    "wof:placetype":"venue"
},
  "geometry": {"coordinates":[-80.404827,25.671606],"type":"Point"}
}