{
  "type": "Feature",
  "properties": {
    "iso:country":"US",
    "sg:address":"1230 Ocean Blvd",
    "sg:city":"Atlantic Beach",
    "sg:classifiers":[
        {
            "category":"Banks & Credit Unions",
            "subcategory":"Financial Services",
            "type":"Services"
        }
    ],
    "sg:phone":"+1 904 249 8513",
    "sg:postcode":"32233",
    "sg:province":"FL",
    "sg:tags":[
        "company",
        "holding"
    ],
    "wof:name":"Kelly Street Co",
    "wof:placetype":"venue"
},
  "geometry": {"coordinates":[-81.39795599999999,30.337721],"type":"Point"}
}