{
  "type": "Feature",
  "properties": {
    "iso:country":"US",
    "sg:address":"5584 NW 7th St",
    "sg:city":"Miami",
    "sg:classifiers":[
        {
            "category":"Wholesale",
            "subcategory":"Medical Equipment & Supplies",
            "type":"Manufacturing & Wholesale Goods"
        }
    ],
    "sg:phone":"+1 305 263 3547",
    "sg:postcode":"33126",
    "sg:province":"FL",
    "wof:name":"Yako Medical Equipment & Supplies Inc",
    "wof:placetype":"venue"
},
  "geometry": {"coordinates":[-80.28610999999999,25.778091],"type":"Point"}
}