{
  "type": "Feature",
  "properties": {
    "addr:full":"43 NW 65th Ave Miami FL 33126",
    "addr:housenumber":"43",
    "addr:postcode":"33126",
    "addr:street":"Nw 65Th Ave",
    "iso:country":"US",
    "sg:address":"43 NW 65th Ave",
    "sg:city":"Miami",
    "sg:classifiers":[
        {
            "category":"Building & Trades",
            "subcategory":"Electrical",
            "type":"Services"
        }
    ],
    "sg:phone":"+1 305 261 0951",
    "sg:postcode":"33126",
    "sg:province":"FL",
    "sg:tags":[
        "electrical",
        "contractor"
    ],
    "wof:name":"Eagle Electrical Contractor",
    "wof:placetype":"venue"
},
  "geometry": {"coordinates":[-80.302127,25.77073],"type":"Point"}
}