{
  "type": "Feature",
  "properties": {
    "iso:country":"US",
    "sg:address":"120 S Waukesha St",
    "sg:city":"Bonifay",
    "sg:classifiers":[
        {
            "category":"Health Services",
            "subcategory":"Health Practitioner",
            "type":"Services"
        }
    ],
    "sg:phone":"+1 850 547 4233",
    "sg:postcode":"32425",
    "sg:province":"FL",
    "sg:tags":[
        "therapist",
        "physical"
    ],
    "wof:name":"Family Physical Therapy Svc",
    "wof:placetype":"venue"
},
  "geometry": {"coordinates":[-85.67994,30.786229],"type":"Point"}
}