{
  "type": "Feature",
  "properties": {
    "iso:country":"US",
    "sg:address":"662 Murphy Rd",
    "sg:city":"Winter Springs",
    "sg:classifiers":[
        {
            "category":"Professional",
            "type":"Services"
        },
        {
            "category":"Home & Garden",
            "subcategory":"Furniture",
            "type":"Retail Goods"
        }
    ],
    "sg:phone":"+1 407 695 4796",
    "sg:postcode":"32708",
    "sg:province":"FL",
    "sg:tags":[
        "cabinet"
    ],
    "wof:name":"Franklin Bennett Inc",
    "wof:placetype":"venue"
},
  "geometry": {"coordinates":[-81.309946,28.681178],"type":"Point"}
}