{
  "type": "Feature",
  "properties": {
    "iso:country":"US",
    "sg:address":"6915 NW 49th St",
    "sg:city":"Gainesville",
    "sg:classifiers":[
        {
            "category":"Organizations",
            "subcategory":"Community Association",
            "type":"Services"
        }
    ],
    "sg:phone":"+1 352 379 3200",
    "sg:postcode":"32653",
    "sg:province":"FL",
    "wof:name":"Western Front Assoc",
    "wof:placetype":"venue"
},
  "geometry": {"coordinates":[-82.39482700000001,29.718411],"type":"Point"}
}