{
  "type": "Feature",
  "properties": {
    "addr:full":"1126 21st St Vero Beach FL 32960",
    "addr:housenumber":"1126",
    "addr:postcode":"32960",
    "addr:street":"21St St",
    "iso:country":"US",
    "sg:address":"1126 21st St",
    "sg:city":"Vero Beach",
    "sg:classifiers":[
        {
            "category":"Professional",
            "subcategory":"Business Services",
            "type":"Services"
        }
    ],
    "sg:phone":"+1 772 567 3185",
    "sg:postcode":"32960",
    "sg:province":"FL",
    "wof:name":"Abracadabra Bail Bonds",
    "wof:placetype":"venue"
},
  "geometry": {"coordinates":[-80.396749,27.639725],"type":"Point"}
}