{
  "type": "Feature",
  "properties": {
    "iso:country":"US",
    "sg:address":"2711 Park Windsor Dr",
    "sg:city":"Fort Myers",
    "sg:classifiers":[
        {
            "category":"Wholesale",
            "subcategory":"Office Equipment",
            "type":"Manufacturing & Wholesale Goods"
        }
    ],
    "sg:phone":"+1 239 337 3788",
    "sg:postcode":"33901",
    "sg:province":"FL",
    "sg:tags":[
        "machine",
        "duplicating",
        "copying"
    ],
    "wof:name":"Alpha Omega Business Systems",
    "wof:placetype":"venue"
},
  "geometry": {"coordinates":[-81.858676,26.609444],"type":"Point"}
}