{
  "type": "Feature",
  "properties": {
    "iso:country":"US",
    "sg:address":"455 S 19th St",
    "sg:city":"Defuniak Springs",
    "sg:classifiers":[
        {
            "category":"Social Services",
            "subcategory":"Child Care",
            "type":"Services"
        }
    ],
    "sg:phone":"+1 850 892 3484",
    "sg:postcode":"32435",
    "sg:province":"FL",
    "sg:tags":[
        "day"
    ],
    "wof:name":"Toy Box Child Care Center",
    "wof:placetype":"venue"
},
  "geometry": {"coordinates":[-86.128846,30.718478],"type":"Point"}
}