{
  "type": "Feature",
  "properties": {
    "addr:full":"7812 Granada Blvd Hollywood FL 33023",
    "addr:housenumber":"7812",
    "addr:postcode":"33023",
    "addr:street":"Granada Blvd",
    "iso:country":"US",
    "sg:address":"7812 Granada Blvd",
    "sg:city":"Hollywood",
    "sg:classifiers":[
        {
            "category":"Autos & Motor Vehicles",
            "subcategory":"Automobile Sales",
            "type":"Retail Goods"
        }
    ],
    "sg:phone":"+1 954 981 7035",
    "sg:postcode":"33023",
    "sg:province":"FL",
    "sg:tags":[
        "used"
    ],
    "wof:name":"Plus Auto Sales Corp",
    "wof:placetype":"venue"
},
  "geometry": {"coordinates":[-80.243255,25.980751],"type":"Point"}
}