{
  "type": "Feature",
  "properties": {
    "addr:full":"700 Boardwalk Dr Ponte Vedra Bch FL 32082",
    "addr:housenumber":"700",
    "addr:postcode":"32082",
    "addr:street":"Boardwalk Dr",
    "iso:country":"US",
    "sg:address":"700 Boardwalk Dr",
    "sg:city":"Ponte Vedra Bch",
    "sg:classifiers":[
        {
            "category":"Banks & Credit Unions",
            "subcategory":"Bank",
            "type":"Services"
        }
    ],
    "sg:phone":"+1 904 272 4558",
    "sg:postcode":"32082",
    "sg:province":"FL",
    "sg:tags":[
        "loan"
    ],
    "wof:name":"First Global Mortgage Brkrg",
    "wof:placetype":"venue"
},
  "geometry": {"coordinates":[-81.39818099999999,30.250288],"type":"Point"}
}