{
  "type": "Feature",
  "properties": {
    "addr:full":"4527 Arnold Ave Naples FL 34104",
    "addr:housenumber":"4527",
    "addr:postcode":"34104",
    "addr:street":"Arnold Ave",
    "iso:country":"US",
    "sg:address":"4527 Arnold Ave",
    "sg:city":"Naples",
    "sg:classifiers":[
        {
            "category":"Banks & Credit Unions",
            "subcategory":"Bank",
            "type":"Services"
        }
    ],
    "sg:phone":"+1 239 659 1126",
    "sg:postcode":"34104",
    "sg:province":"FL",
    "sg:tags":[
        "loan"
    ],
    "wof:name":"Naples Title Loans",
    "wof:placetype":"venue"
},
  "geometry": {"coordinates":[-81.757175,26.167336],"type":"Point"}
}