{
  "type": "Feature",
  "properties": {
    "addr:full":"1790 W 49th St Hialeah FL 33012",
    "addr:housenumber":"1790",
    "addr:postcode":"33012",
    "addr:street":"W 49Th St",
    "iso:country":"US",
    "sg:address":"1790 W 49th St",
    "sg:city":"Hialeah",
    "sg:classifiers":[
        {
            "category":"Shopping",
            "subcategory":"Clothing, Apparel, & Fashions",
            "type":"Retail Goods"
        }
    ],
    "sg:phone":"+1 305 557 8386",
    "sg:postcode":"33012",
    "sg:province":"FL",
    "sg:tags":[
        "tailor"
    ],
    "wof:name":"Manuel's Tailor Textile",
    "wof:placetype":"venue"
},
  "geometry": {"coordinates":[-80.318033,25.866511],"type":"Point"}
}