{
  "type": "Feature",
  "properties": {
    "iso:country":"US",
    "sg:address":"6905 E Martin Luther King Jr Blvd",
    "sg:city":"Tampa",
    "sg:classifiers":[
        {
            "category":"Autos & Motor Vehicles",
            "subcategory":"Automobile Sales",
            "type":"Retail Goods"
        }
    ],
    "sg:phone":"+1 813 623 2834",
    "sg:postcode":"33619",
    "sg:province":"FL",
    "sg:tags":[
        "truck"
    ],
    "wof:name":"Kenworth of Central Florida",
    "wof:placetype":"venue"
},
  "geometry": {"coordinates":[-82.37872900000001,27.981408],"type":"Point"}
}