{
  "type": "Feature",
  "properties": {
    "addr:full":"437 Santa Anna Dr Lake Worth FL 33461",
    "addr:housenumber":"437",
    "addr:postcode":"33461",
    "addr:street":"Santa Anna Dr",
    "iso:country":"US",
    "sg:address":"437 Santa Anna Dr",
    "sg:city":"Lake Worth",
    "sg:classifiers":[
        {
            "category":"Retail",
            "subcategory":"Repair Shop",
            "type":"Services"
        }
    ],
    "sg:phone":"+1 561 433 4729",
    "sg:postcode":"33461",
    "sg:province":"FL",
    "sg:tags":[
        "warranty",
        "electrical",
        "household",
        "appliance"
    ],
    "wof:name":"Care Appliance Service Inc",
    "wof:placetype":"venue"
},
  "geometry": {"coordinates":[-80.098349,26.641875],"type":"Point"}
}