{
  "type": "Feature",
  "properties": {
    "iso:country":"US",
    "sg:address":"3191 Kanner Hwy",
    "sg:city":"Stuart",
    "sg:classifiers":[
        {
            "category":"Home & Garden",
            "subcategory":"Garden Supply",
            "type":"Retail Goods"
        }
    ],
    "sg:phone":"+1 772 283 1553",
    "sg:postcode":"34994",
    "sg:province":"FL",
    "sg:tags":[
        "center"
    ],
    "wof:name":"All Seasons Nursery",
    "wof:placetype":"venue"
},
  "geometry": {"coordinates":[-80.250382,27.166914],"type":"Point"}
}