{
  "type": "Feature",
  "properties": {
    "iso:country":"US",
    "sg:address":"1730 NE 62nd St",
    "sg:city":"Fort Lauderdale",
    "sg:classifiers":[
        {
            "category":"Freight",
            "type":"Transportation"
        }
    ],
    "sg:phone":"+1 954 229 7080",
    "sg:postcode":"33334",
    "sg:province":"FL",
    "sg:tags":[
        "mover"
    ],
    "wof:name":"Arrow Star Moving Corp",
    "wof:placetype":"venue"
},
  "geometry": {"coordinates":[-80.125793,26.203666],"type":"Point"}
}