{
  "type": "Feature",
  "properties": {
    "addr:full":"7430 SW 41st St Miami FL 33155",
    "addr:housenumber":"7430",
    "addr:postcode":"33155",
    "addr:street":"Sw 41St St",
    "iso:country":"US",
    "sg:address":"7430 SW 41st St",
    "sg:city":"Miami",
    "sg:classifiers":[
        {
            "category":"Building & Trades",
            "subcategory":"Construction",
            "type":"Services"
        }
    ],
    "sg:phone":"+1 305 260 9777",
    "sg:postcode":"33155",
    "sg:province":"FL",
    "sg:tags":[
        "designer",
        "dealer",
        "pool",
        "swimming"
    ],
    "wof:name":"Genier Pools & Rock Waterfalls",
    "wof:placetype":"venue"
},
  "geometry": {"coordinates":[-80.315456,25.732208],"type":"Point"}
}