{
  "type": "Feature",
  "properties": {
    "addr:full":"1831 N Crystal Lake Dr Lakeland FL 33801",
    "addr:housenumber":"1831",
    "addr:postcode":"33801",
    "addr:street":"N Crystal Lake Dr",
    "iso:country":"US",
    "sg:address":"1831 N Crystal Lake Dr",
    "sg:city":"Lakeland",
    "sg:classifiers":[
        {
            "category":"Social Services",
            "type":"Services"
        }
    ],
    "sg:phone":"+1 863 667 4701",
    "sg:postcode":"33801",
    "sg:province":"FL",
    "sg:tags":[
        "youth",
        "organization",
        "center"
    ],
    "wof:name":"Bay Area Youth Svc Inc",
    "wof:placetype":"venue"
},
  "geometry": {"coordinates":[-81.926434,28.025877],"type":"Point"}
}