{
  "type": "Feature",
  "properties": {
    "iso:country":"US",
    "sg:address":"3003 W Azeele St",
    "sg:city":"Tampa",
    "sg:classifiers":[
        {
            "category":"Banks & Credit Unions",
            "subcategory":"Bank",
            "type":"Services"
        }
    ],
    "sg:phone":"+1 813 876 3113",
    "sg:postcode":"33609",
    "sg:province":"FL",
    "sg:tags":[
        "federal"
    ],
    "wof:name":"Henry Hicks T A",
    "wof:placetype":"venue"
},
  "geometry": {"coordinates":[-82.49196600000001,27.941217],"type":"Point"}
}