{
  "type": "Feature",
  "properties": {
    "iso:country":"US",
    "sg:address":"9150 SW 87th Ave",
    "sg:city":"Miami",
    "sg:classifiers":[
        {
            "category":"Real Estate",
            "subcategory":"Real Estate Agent",
            "type":"Services"
        }
    ],
    "sg:phone":"+1 305 595 1588",
    "sg:postcode":"33176",
    "sg:province":"FL",
    "wof:name":"Soundvest Properties",
    "wof:placetype":"venue"
},
  "geometry": {"coordinates":[-80.335475,25.684774],"type":"Point"}
}