{
  "type": "Feature",
  "properties": {
    "addr:full":"4716 Independence Dr Bradenton FL 34210",
    "addr:housenumber":"4716",
    "addr:postcode":"34210",
    "addr:street":"Independence Dr",
    "iso:country":"US",
    "sg:address":"4716 Independence Dr",
    "sg:city":"Bradenton",
    "sg:classifiers":[
        {
            "category":"Insurance",
            "subcategory":"Insurance Agent",
            "type":"Services"
        }
    ],
    "sg:phone":"+1 941 794 5021",
    "sg:postcode":"34210",
    "sg:province":"FL",
    "wof:name":"Medical Claims Svcs",
    "wof:placetype":"venue"
},
  "geometry": {"coordinates":[-82.660771,27.458832],"type":"Point"}
}