{
  "type": "Feature",
  "properties": {
    "iso:country":"US",
    "sg:address":"19 Ferry Pl",
    "sg:city":"St Augustine",
    "sg:classifiers":[
        {
            "category":"Autos & Motor Vehicles",
            "subcategory":"Automobile Sales",
            "type":"Retail Goods"
        }
    ],
    "sg:phone":"+1 904 827 0940",
    "sg:postcode":"32084",
    "sg:province":"FL",
    "sg:tags":[
        "car",
        "dealer"
    ],
    "wof:name":"Prestiage Car & Truck Sales",
    "wof:placetype":"venue"
},
  "geometry": {"coordinates":[-81.325909,29.88101],"type":"Point"}
}