{
  "type": "Feature",
  "properties": {
    "addr:full":"1732 Moro St Jacksonville FL 32207",
    "addr:housenumber":"1732",
    "addr:postcode":"32207",
    "addr:street":"Moro St",
    "iso:country":"US",
    "sg:address":"1732 Moro St",
    "sg:city":"Jacksonville",
    "sg:classifiers":[
        {
            "category":"Travel",
            "subcategory":"Travel Agent",
            "type":"Entertainment"
        }
    ],
    "sg:phone":"+1 904 475 0887",
    "sg:postcode":"32207",
    "sg:province":"FL",
    "sg:tags":[
        "agency",
        "bureau"
    ],
    "wof:name":"Itravelagent",
    "wof:placetype":"venue"
},
  "geometry": {"coordinates":[-81.65853,30.305977],"type":"Point"}
}