{
  "type": "Feature",
  "properties": {
    "iso:country":"US",
    "sg:address":"719 NE 83rd Ter",
    "sg:city":"Miami",
    "sg:classifiers":[
        {
            "category":"Shopping",
            "subcategory":"Baby Store",
            "type":"Retail Goods"
        }
    ],
    "sg:phone":"+1 305 747 8317",
    "sg:postcode":"33138",
    "sg:province":"FL",
    "sg:tags":[
        "gear",
        "furniture"
    ],
    "sg:website":"www.babystrollersandgifts.com",
    "wof:name":"Baby Strollers and Gifts",
    "wof:placetype":"venue"
},
  "geometry": {"coordinates":[-80.182278,25.852637],"type":"Point"}
}