{
  "type": "Feature",
  "properties": {
    "iso:country":"US",
    "sg:address":"1269 Fargo Dr",
    "sg:city":"Melbourne",
    "sg:classifiers":[
        {
            "category":"Building & Trades",
            "subcategory":"Electrical",
            "type":"Services"
        }
    ],
    "sg:phone":"+1 321 259 8296",
    "sg:postcode":"32940",
    "sg:province":"FL",
    "sg:tags":[
        "electric",
        "contractor"
    ],
    "wof:name":"Donald G Shrum Electric",
    "wof:placetype":"venue"
},
  "geometry": {"coordinates":[-80.691124,28.249425],"type":"Point"}
}