{
  "type": "Feature",
  "properties": {
    "iso:country":"US",
    "sg:address":"1949 NE 179th St",
    "sg:city":"North Miami Bch",
    "sg:classifiers":[
        {
            "category":"Wholesale",
            "subcategory":"Construction Materials",
            "type":"Manufacturing & Wholesale Goods"
        }
    ],
    "sg:phone":"+1 305 949 4486",
    "sg:postcode":"33162",
    "sg:province":"FL",
    "sg:tags":[
        "marble"
    ],
    "wof:name":"Super Marble Corp",
    "wof:placetype":"venue"
},
  "geometry": {"coordinates":[-80.161495,25.940793],"type":"Point"}
}