{
  "type": "Feature",
  "properties": {
    "iso:country":"US",
    "sg:address":"5759 Funston St",
    "sg:city":"Hollywood",
    "sg:classifiers":[
        {
            "category":"Wholesale",
            "subcategory":"Machinery & Supplies",
            "type":"Manufacturing & Wholesale Goods"
        },
        {
            "category":"Wholesale",
            "subcategory":"Durable Goods & Equipment",
            "type":"Manufacturing & Wholesale Goods"
        }
    ],
    "sg:phone":"+1 954 964 2880",
    "sg:postcode":"33023",
    "sg:province":"FL",
    "sg:tags":[
        "marine",
        "importer",
        "electrical"
    ],
    "wof:name":"Dynamic Marine Electric Corp",
    "wof:placetype":"venue"
},
  "geometry": {"coordinates":[-80.200091,26.000424],"type":"Point"}
}