{
  "type": "Feature",
  "properties": {
    "iso:country":"US",
    "sg:address":"4241 Baymeadows Rd",
    "sg:city":"Jacksonville",
    "sg:classifiers":[
        {
            "category":"Health Services",
            "subcategory":"Health Practitioner",
            "type":"Services"
        }
    ],
    "sg:phone":"+1 904 730 5158",
    "sg:postcode":"32217",
    "sg:province":"FL",
    "wof:name":"Alliance Occupational Health",
    "wof:placetype":"venue"
},
  "geometry": {"coordinates":[-81.60946,30.218973],"type":"Point"}
}