{
  "type": "Feature",
  "properties": {
    "iso:country":"US",
    "sg:address":"2035 W Pensacola St",
    "sg:city":"Tallahassee",
    "sg:classifiers":[
        {
            "category":"Restaurant",
            "type":"Food & Drink"
        }
    ],
    "sg:phone":"+1 850 224 5454",
    "sg:postcode":"32304",
    "sg:province":"FL",
    "wof:name":"Brooklyn Pizza",
    "wof:placetype":"venue"
},
  "geometry": {"coordinates":[-84.318827,30.440586],"type":"Point"}
}