{
  "type": "Feature",
  "properties": {
    "iso:country":"US",
    "sg:address":"24251 Branchwood Ct",
    "sg:city":"Lutz",
    "sg:classifiers":[
        {
            "category":"Shopping",
            "subcategory":"Florist",
            "type":"Retail Goods"
        }
    ],
    "sg:phone":"+1 813 909 1706",
    "sg:postcode":"33559",
    "sg:province":"FL",
    "wof:name":"Donald R Flowers",
    "wof:placetype":"venue"
},
  "geometry": {"coordinates":[-82.414429,28.176823],"type":"Point"}
}