{
  "type": "Feature",
  "properties": {
    "iso:country":"US",
    "sg:address":"1001 Brickell Bay Dr Ste 3104",
    "sg:city":"Miami",
    "sg:classifiers":[
        {
            "category":"Banks & Credit Unions",
            "subcategory":"Investment Brokerage",
            "type":"Services"
        },
        {
            "category":"Insurance",
            "subcategory":"Hazard Insurance",
            "type":"Services"
        },
        {
            "category":"Banks & Credit Unions",
            "subcategory":"Financial Services",
            "type":"Services"
        }
    ],
    "sg:phone":"+1 305 415 9633",
    "sg:postcode":"33131",
    "sg:province":"FL",
    "sg:tags":[
        "advisory",
        "planning",
        "commercial",
        "business",
        "consultant"
    ],
    "wof:name":"Vaccaro Corp",
    "wof:placetype":"venue"
},
  "geometry": {"coordinates":[-80.19006899999999,25.763619],"type":"Point"}
}