{
  "type": "Feature",
  "properties": {
    "addr:full":"2185 Meadowlane Ave Melbourne FL 32904",
    "addr:housenumber":"2185",
    "addr:postcode":"32904",
    "addr:street":"Meadowlane Ave",
    "iso:country":"US",
    "sg:address":"2185 Meadowlane Ave",
    "sg:city":"Melbourne",
    "sg:classifiers":[
        {
            "category":"Place Of Worship",
            "subcategory":"Church",
            "type":"Public Place"
        },
        {
            "category":"Place Of Worship",
            "type":"Public Place"
        }
    ],
    "sg:phone":"+1 321 725 6125",
    "sg:postcode":"32904",
    "sg:province":"FL",
    "sg:tags":[
        "churches-interdenominational",
        "churches-various",
        "denomination"
    ],
    "wof:name":"Unitarian Universalist Congrg",
    "wof:placetype":"venue"
},
  "geometry": {"coordinates":[-80.670751,28.07576],"type":"Point"}
}