{
  "type": "Feature",
  "properties": {
    "iso:country":"US",
    "sg:address":"326 Shamrock Rd",
    "sg:city":"St Augustine",
    "sg:classifiers":[
        {
            "category":"Building & Trades",
            "subcategory":"Landscaping Services",
            "type":"Services"
        }
    ],
    "sg:phone":"+1 904 794 1079",
    "sg:postcode":"32086",
    "sg:province":"FL",
    "sg:tags":[
        "tree"
    ],
    "wof:name":"K K Cutting Inc",
    "wof:placetype":"venue"
},
  "geometry": {"coordinates":[-81.31372500000001,29.838449],"type":"Point"}
}