{
  "type": "Feature",
  "properties": {
    "addr:full":"18061 NW 27th Ave Miami Gardens FL 33056",
    "addr:housenumber":"18061",
    "addr:postcode":"33056",
    "addr:street":"Nw 27Th Ave",
    "iso:country":"US",
    "sg:address":"18061 NW 27th Ave",
    "sg:city":"Miami Gardens",
    "sg:classifiers":[
        {
            "category":"Arena",
            "subcategory":"Sports Club",
            "type":"Entertainment"
        }
    ],
    "sg:phone":"+1 305 628 5588",
    "sg:postcode":"33056",
    "sg:province":"FL",
    "sg:tags":[
        "martial art"
    ],
    "wof:name":"Nisei Karate Center",
    "wof:placetype":"venue"
},
  "geometry": {"coordinates":[-80.244936,25.938781],"type":"Point"}
}