{
  "type": "Feature",
  "properties": {
    "addr:full":"1000 Ponce de Leon Blvd Miami FL 33134",
    "addr:housenumber":"1000",
    "addr:postcode":"33134",
    "addr:street":"Ponce De Leon Blvd",
    "iso:country":"US",
    "sg:address":"1000 Ponce de Leon Blvd",
    "sg:city":"Miami",
    "sg:classifiers":[
        {
            "category":"Building & Trades",
            "subcategory":"Equipment Rental",
            "type":"Services"
        }
    ],
    "sg:phone":"+1 305 529 6441",
    "sg:postcode":"33134",
    "sg:province":"FL",
    "sg:tags":[
        "electronics",
        "audio"
    ],
    "wof:name":"Automated Entrmt Systems",
    "wof:placetype":"venue"
},
  "geometry": {"coordinates":[-80.259063,25.761302],"type":"Point"}
}