{
  "type": "Feature",
  "properties": {
    "iso:country":"US",
    "sg:address":"321 SE 2nd St",
    "sg:city":"Delray Beach",
    "sg:classifiers":[
        {
            "category":"Local Transit",
            "type":"Transportation"
        }
    ],
    "sg:phone":"+1 561 276 2979",
    "sg:postcode":"33483",
    "sg:province":"FL",
    "sg:tags":[
        "limousine"
    ],
    "wof:name":"A Wiser Transportation",
    "wof:placetype":"venue"
},
  "geometry": {"coordinates":[-80.069181,26.458077],"type":"Point"}
}