{
  "type": "Feature",
  "properties": {
    "iso:country":"US",
    "sg:address":"4713 N 40th St",
    "sg:city":"Tampa",
    "sg:classifiers":[
        {
            "category":"Personal",
            "subcategory":"Beauty Salon",
            "type":"Services"
        }
    ],
    "sg:phone":"+1 813 626 2161",
    "sg:postcode":"33610",
    "sg:province":"FL",
    "wof:name":"Total Image Beauty Salon",
    "wof:placetype":"venue"
},
  "geometry": {"coordinates":[-82.41401500000001,27.987958],"type":"Point"}
}