{
  "type": "Feature",
  "properties": {
    "iso:country":"US",
    "sg:address":"7047 Henderson Rd",
    "sg:city":"Laurel Hill",
    "sg:classifiers":[
        {
            "category":"Home & Garden",
            "subcategory":"Household Appliances",
            "type":"Retail Goods"
        }
    ],
    "sg:phone":"+1 850 652 4019",
    "sg:postcode":"32567",
    "sg:province":"FL",
    "sg:tags":[
        "used",
        "merchandise"
    ],
    "wof:name":"Batson's Quality Used Applnce",
    "wof:placetype":"venue"
},
  "geometry": {"coordinates":[-86.510407,30.87915],"type":"Point"}
}