{
  "type": "Feature",
  "properties": {
    "iso:country":"US",
    "sg:address":"309 Gulf Blvd",
    "sg:city":"Indian Rocks Bch",
    "sg:classifiers":[
        {
            "category":"Real Estate",
            "subcategory":"Real Estate Agent",
            "type":"Services"
        }
    ],
    "sg:phone":"+1 727 596 0109",
    "sg:postcode":"33785",
    "sg:province":"FL",
    "sg:tags":[
        "management"
    ],
    "wof:name":"3 Palms Property Management",
    "wof:placetype":"venue"
},
  "geometry": {"coordinates":[-82.850382,27.88239],"type":"Point"}
}