{
  "type": "Feature",
  "properties": {
    "addr:full":"15849 US Hwy 301 Dade City FL 33523",
    "addr:postcode":"15849;33523",
    "addr:street":"Us Hwy 301",
    "iso:country":"US",
    "sg:address":"15849 US Hwy 301",
    "sg:city":"Dade City",
    "sg:classifiers":[
        {
            "category":"Retail",
            "subcategory":"Auto Repair",
            "type":"Services"
        }
    ],
    "sg:phone":"+1 352 521 0699",
    "sg:postcode":"33523",
    "sg:province":"FL",
    "sg:tags":[
        "body",
        "automobile",
        "painting"
    ],
    "wof:name":"Men From Mars Automotive",
    "wof:placetype":"venue"
},
  "geometry": {"coordinates":[-82.19459999999999,28.390087],"type":"Point"}
}