{
  "type": "Feature",
  "properties": {
    "addr:full":"339 N 8th St Quincy FL 32351",
    "addr:housenumber":"339",
    "addr:postcode":"32351",
    "addr:street":"N 8Th St",
    "iso:country":"US",
    "sg:address":"339 N 8th St",
    "sg:city":"Quincy",
    "sg:classifiers":[
        {
            "category":"Real Estate",
            "subcategory":"Real Estate Agent",
            "type":"Services"
        }
    ],
    "sg:phone":"+1 850 627 8922",
    "sg:postcode":"32351",
    "sg:province":"FL",
    "wof:name":"Bird Dog Realty Inc",
    "wof:placetype":"venue"
},
  "geometry": {"coordinates":[-84.584694,30.592143],"type":"Point"}
}