{
  "type": "Feature",
  "properties": {
    "iso:country":"US",
    "sg:address":"239 1st St N",
    "sg:city":"Jacksonville Bch",
    "sg:classifiers":[
        {
            "category":"Shopping",
            "subcategory":"Bicycles & Sporting Goods",
            "type":"Retail Goods"
        }
    ],
    "sg:phone":"+1 904 241 5088",
    "sg:postcode":"32250",
    "sg:province":"FL",
    "sg:tags":[
        "surfboard"
    ],
    "wof:name":"Surf & Skate Surf Shop",
    "wof:placetype":"venue"
},
  "geometry": {"coordinates":[-81.38993499999999,30.290957],"type":"Point"}
}