{
  "type": "Feature",
  "properties": {
    "addr:full":"39036 US Hwy 19 N Tarpon Springs FL 34689",
    "addr:postcode":"39036;34689",
    "addr:street":"Us Hwy 19 N",
    "iso:country":"US",
    "sg:address":"39036 US Hwy 19 N",
    "sg:city":"Tarpon Springs",
    "sg:classifiers":[
        {
            "category":"Personal",
            "type":"Services"
        }
    ],
    "sg:phone":"+1 727 934 1256",
    "sg:postcode":"34689",
    "sg:province":"FL",
    "sg:tags":[
        "control",
        "weight"
    ],
    "wof:name":"Americamom United",
    "wof:placetype":"venue"
},
  "geometry": {"coordinates":[-82.740165,28.126352],"type":"Point"}
}