{
  "type": "Feature",
  "properties": {
    "iso:country":"US",
    "sg:address":"4210 Dow Rd Ste A",
    "sg:city":"Melbourne",
    "sg:classifiers":[
        {
            "category":"Government",
            "subcategory":"Fire Station",
            "type":"Public Place"
        },
        {
            "category":"Professional",
            "subcategory":"Detective & Security Services",
            "type":"Services"
        }
    ],
    "sg:phone":"+1 888 300 4809",
    "sg:postcode":"32934",
    "sg:province":"FL",
    "sg:tags":[
        "control",
        "television",
        "monitoring",
        "supply",
        "consultant",
        "alarm",
        "system",
        "equipment",
        "protection",
        "systems-closed",
        "circuit",
        "telecasting"
    ],
    "sg:website":"http://www.adtfastresponse.com/fastresponse/offer.aspx?ecid=bgtyp100302",
    "wof:name":"ADT Security Services",
    "wof:placetype":"venue"
},
  "geometry": {"coordinates":[-80.695908,28.107502],"type":"Point"}
}