{
  "type": "Feature",
  "properties": {
    "iso:country":"US",
    "sg:address":"1415 10th St W",
    "sg:city":"Palmetto",
    "sg:classifiers":[
        {
            "category":"Home & Garden",
            "subcategory":"Building Materials",
            "type":"Retail Goods"
        },
        {
            "category":"Building & Trades",
            "subcategory":"Construction",
            "type":"Services"
        }
    ],
    "sg:phone":"+1 941 753 2284",
    "sg:postcode":"34221",
    "sg:province":"FL",
    "sg:tags":[
        "repair",
        "bathroom",
        "altering",
        "contractor",
        "planning",
        "maintenance",
        "improvement",
        "remodeling",
        "kitchen"
    ],
    "sg:website":"http://www.dreammaker-gci.com",
    "wof:name":"Dream Maker Bath & Kitchen",
    "wof:placetype":"venue"
},
  "geometry": {"coordinates":[-82.581328,27.521293],"type":"Point"}
}