{
  "type": "Feature",
  "properties": {
    "addr:full":"15900 NW 27th Ave Opa Locka FL 33054",
    "addr:housenumber":"15900",
    "addr:postcode":"33054",
    "addr:street":"Nw 27Th Ave;Locka",
    "iso:country":"US",
    "sg:address":"15900 NW 27th Ave",
    "sg:city":"Opa Locka",
    "sg:classifiers":[
        {
            "category":"Shopping",
            "subcategory":"Pharmacy",
            "type":"Retail Goods"
        }
    ],
    "sg:phone":"+1 305 624 4021",
    "sg:postcode":"33054",
    "sg:province":"FL",
    "sg:tags":[
        "drug",
        "store"
    ],
    "wof:name":"Walgreens",
    "wof:placetype":"venue"
},
  "geometry": {"coordinates":[-80.244456,25.92023],"type":"Point"}
}