{
  "type": "Feature",
  "properties": {
    "iso:country":"US",
    "sg:address":"16116 Livingston Ave",
    "sg:city":"Lutz",
    "sg:classifiers":[
        {
            "category":"Health Services",
            "subcategory":"Optometrist",
            "type":"Services"
        }
    ],
    "sg:phone":"+1 813 866 0025",
    "sg:postcode":"33559",
    "sg:province":"FL",
    "wof:name":"Center For Comprehensive Svc",
    "wof:placetype":"venue"
},
  "geometry": {"coordinates":[-82.430795,28.102866],"type":"Point"}
}