{
  "type": "Feature",
  "properties": {
    "iso:country":"US",
    "sg:address":"670 2nd Ln",
    "sg:city":"Vero Beach",
    "sg:classifiers":[
        {
            "category":"Professional",
            "type":"Services"
        }
    ],
    "sg:phone":"+1 772 770 9440",
    "sg:postcode":"32962",
    "sg:province":"FL",
    "wof:name":"Darlin of Vero Inc",
    "wof:placetype":"venue"
},
  "geometry": {"coordinates":[-80.387135,27.606362],"type":"Point"}
}