{
  "type": "Feature",
  "properties": {
    "addr:full":"2358 Riverside Ave Jacksonville FL 32204",
    "addr:housenumber":"2358",
    "addr:postcode":"32204",
    "addr:street":"Riverside Ave",
    "iso:country":"US",
    "sg:address":"2358 Riverside Ave",
    "sg:city":"Jacksonville",
    "sg:classifiers":[
        {
            "category":"Real Estate",
            "subcategory":"Real Estate Operator",
            "type":"Services"
        }
    ],
    "sg:phone":"+1 904 381 1041",
    "sg:postcode":"32204",
    "sg:province":"FL",
    "sg:tags":[
        "condominium"
    ],
    "wof:name":"Villariva Condominium Asso",
    "wof:placetype":"venue"
},
  "geometry": {"coordinates":[-81.68716000000001,30.309682],"type":"Point"}
}