{
  "type": "Feature",
  "properties": {
    "addr:full":"4815 Davis Rd Lake Worth FL 33461",
    "addr:housenumber":"4815",
    "addr:postcode":"33461",
    "addr:street":"Davis Rd",
    "iso:country":"US",
    "sg:address":"4815 Davis Rd",
    "sg:city":"Lake Worth",
    "sg:classifiers":[
        {
            "category":"Home & Garden",
            "subcategory":"Building Materials",
            "type":"Retail Goods"
        }
    ],
    "sg:phone":"+1 561 969 6710",
    "sg:postcode":"33461",
    "sg:province":"FL",
    "sg:tags":[
        "screen",
        "window"
    ],
    "wof:name":"Evodio Limon Luna Screen",
    "wof:placetype":"venue"
},
  "geometry": {"coordinates":[-80.09781099999999,26.604704],"type":"Point"}
}