{
  "type": "Feature",
  "properties": {
    "iso:country":"US",
    "sg:address":"601 Shreve St",
    "sg:city":"Punta Gorda",
    "sg:classifiers":[
        {
            "category":"Real Estate",
            "subcategory":"Real Estate Agent",
            "type":"Services"
        },
        {
            "category":"Real Estate",
            "subcategory":"Real Estate Operator",
            "type":"Services"
        }
    ],
    "sg:phone":"+1 941 637 1101",
    "sg:postcode":"33950",
    "sg:province":"FL",
    "sg:tags":[
        "condominium",
        "association"
    ],
    "wof:name":"Banyan Point Condominium Assoc",
    "wof:placetype":"venue"
},
  "geometry": {"coordinates":[-82.054221,26.924301],"type":"Point"}
}