{
  "type": "Feature",
  "properties": {
    "iso:country":"US",
    "sg:address":"9861 SW 47th St",
    "sg:city":"Miami",
    "sg:classifiers":[
        {
            "category":"Wholesale",
            "subcategory":"Fruits & Vegetables",
            "type":"Manufacturing & Wholesale Goods"
        }
    ],
    "sg:phone":"+1 305 229 0677",
    "sg:postcode":"33165",
    "sg:province":"FL",
    "sg:tags":[
        "veggie"
    ],
    "wof:name":"Festival Fruit & Produce Co",
    "wof:placetype":"venue"
},
  "geometry": {"coordinates":[-80.354698,25.724001],"type":"Point"}
}