{
  "type": "Feature",
  "properties": {
    "iso:country":"US",
    "sg:address":"15800 SW 102nd Ln",
    "sg:city":"Miami",
    "sg:classifiers":[
        {
            "category":"Building & Trades",
            "subcategory":"Construction",
            "type":"Services"
        }
    ],
    "sg:phone":"+1 305 382 5747",
    "sg:postcode":"33196",
    "sg:province":"FL",
    "sg:tags":[
        "real estate",
        "nonresidential"
    ],
    "wof:name":"Garden Hills",
    "wof:placetype":"venue"
},
  "geometry": {"coordinates":[-80.452123,25.670995],"type":"Point"}
}