{
  "type": "Feature",
  "properties": {
    "addr:full":"135 Weston Rd Weston FL 33326",
    "addr:housenumber":"135",
    "addr:postcode":"33326",
    "addr:street":"Weston Rd",
    "iso:country":"US",
    "sg:address":"135 Weston Rd",
    "sg:city":"Weston",
    "sg:classifiers":[
        {
            "category":"Health Services",
            "subcategory":"Chiropractor",
            "type":"Services"
        }
    ],
    "sg:phone":"+1 954 745 8740",
    "sg:postcode":"33326",
    "sg:province":"FL",
    "sg:tags":[
        "chiropractic"
    ],
    "wof:name":"Shumway Wellness Center",
    "wof:placetype":"venue"
},
  "geometry": {"coordinates":[-80.362075,26.120457],"type":"Point"}
}