{
  "type": "Feature",
  "properties": {
    "iso:country":"US",
    "sg:address":"520 S Hunt Club Blvd",
    "sg:city":"Apopka",
    "sg:classifiers":[
        {
            "category":"Shopping",
            "subcategory":"Tobacco",
            "type":"Retail Goods"
        }
    ],
    "sg:phone":"+1 407 869 8383",
    "sg:postcode":"32703",
    "sg:province":"FL",
    "sg:tags":[
        "cigarette",
        "cigar",
        "dealer"
    ],
    "wof:name":"Low Ball Louie's",
    "wof:placetype":"venue"
},
  "geometry": {"coordinates":[-81.44949699999999,28.671524],"type":"Point"}
}