{
  "type": "Feature",
  "properties": {
    "iso:country":"US",
    "sg:address":"863 N State Rd 434",
    "sg:city":"Altamonte Spgs",
    "sg:classifiers":[
        {
            "category":"Building & Trades",
            "subcategory":"Construction",
            "type":"Services"
        }
    ],
    "sg:phone":"+1 407 869 6143",
    "sg:postcode":"32714",
    "sg:province":"FL",
    "sg:tags":[
        "general",
        "contractor"
    ],
    "wof:name":"B C Clark Construction Group",
    "wof:placetype":"venue"
},
  "geometry": {"coordinates":[-81.419012,28.680047],"type":"Point"}
}