{
  "type": "Feature",
  "properties": {
    "iso:country":"US",
    "sg:address":"1287 E Newport Center Dr",
    "sg:city":"Deerfield Beach",
    "sg:classifiers":[
        {
            "category":"Building & Trades",
            "subcategory":"Construction",
            "type":"Services"
        }
    ],
    "sg:phone":"+1 954 427 6147",
    "sg:postcode":"33442",
    "sg:province":"FL",
    "sg:tags":[
        "fire",
        "restoration",
        "damage"
    ],
    "wof:name":"Servpro",
    "wof:placetype":"venue"
},
  "geometry": {"coordinates":[-80.123985,26.300591],"type":"Point"}
}