{
  "type": "Feature",
  "properties": {
    "addr:full":"9803 NW 80th Ave Hialeah FL 33016",
    "addr:housenumber":"9803",
    "addr:postcode":"33016",
    "addr:street":"Nw 80Th Ave",
    "iso:country":"US",
    "sg:address":"9803 NW 80th Ave",
    "sg:city":"Hialeah",
    "sg:classifiers":[
        {
            "category":"Autos & Motor Vehicles",
            "subcategory":"Automobile Sales",
            "type":"Retail Goods"
        }
    ],
    "sg:phone":"+1 305 823 5112",
    "sg:postcode":"33016",
    "sg:province":"FL",
    "sg:tags":[
        "car",
        "used",
        "truck"
    ],
    "sg:website":"http://www.ctcmotors.net",
    "wof:name":"CTC Sales Corp",
    "wof:placetype":"venue"
},
  "geometry": {"coordinates":[-80.32682800000001,25.862507],"type":"Point"}
}