{
  "type": "Feature",
  "properties": {
    "iso:country":"US",
    "sg:address":"4 Cook St",
    "sg:city":"West Palm Beach",
    "sg:classifiers":[
        {
            "category":"Building & Trades",
            "subcategory":"Construction",
            "type":"Services"
        }
    ],
    "sg:phone":"+1 561 842 3281",
    "sg:postcode":"33404",
    "sg:province":"FL",
    "sg:tags":[
        "carpentry",
        "contractor"
    ],
    "wof:name":"Larry Cruser Interior Trim",
    "wof:placetype":"venue"
},
  "geometry": {"coordinates":[-80.053939,26.786626],"type":"Point"}
}