{
  "type": "Feature",
  "properties": {
    "addr:full":"10115 Montague St Tampa FL 33626",
    "addr:housenumber":"10115",
    "addr:postcode":"33626",
    "addr:street":"Montague St",
    "iso:country":"US",
    "sg:address":"10115 Montague St",
    "sg:city":"Tampa",
    "sg:classifiers":[
        {
            "category":"Real Estate",
            "subcategory":"Real Estate Agent",
            "type":"Services"
        }
    ],
    "sg:phone":"+1 813 926 8005",
    "sg:postcode":"33626",
    "sg:province":"FL",
    "sg:website":"www.baywestrealestate.com",
    "wof:name":"Bay West Real Estate",
    "wof:placetype":"venue"
},
  "geometry": {"coordinates":[-82.596923,28.044129],"type":"Point"}
}