{
  "type": "Feature",
  "properties": {
    "iso:country":"US",
    "sg:address":"9096 Warbler Dr",
    "sg:city":"Tallahassee",
    "sg:classifiers":[
        {
            "category":"Professional",
            "subcategory":"Research",
            "type":"Services"
        }
    ],
    "sg:phone":"+1 850 421 1210",
    "sg:postcode":"32305",
    "sg:province":"FL",
    "sg:tags":[
        "environmental",
        "ecological"
    ],
    "wof:name":"Tom Greene Environmental Cnslt",
    "wof:placetype":"venue"
},
  "geometry": {"coordinates":[-84.28734300000001,30.314612],"type":"Point"}
}