{
  "type": "Feature",
  "properties": {
    "iso:country":"US",
    "sg:address":"1128 Beneva Rd",
    "sg:city":"Sarasota",
    "sg:classifiers":[
        {
            "category":"Building & Trades",
            "subcategory":"Landscaping Services",
            "type":"Services"
        }
    ],
    "sg:phone":"+1 941 951 0781",
    "sg:postcode":"34232",
    "sg:province":"FL",
    "wof:name":"Wengerd Lawn Services",
    "wof:placetype":"venue"
},
  "geometry": {"coordinates":[-82.49754900000001,27.32307],"type":"Point"}
}