{
  "type": "Feature",
  "properties": {
    "iso:country":"US",
    "sg:address":"547 NE 128th Ave",
    "sg:city":"Silver Springs",
    "sg:classifiers":[
        {
            "category":"Building & Trades",
            "subcategory":"Construction",
            "type":"Services"
        }
    ],
    "sg:phone":"+1 352 625 2919",
    "sg:postcode":"34488",
    "sg:province":"FL",
    "sg:tags":[
        "general",
        "contractor"
    ],
    "wof:name":"Jack Pate Framing & Repairs",
    "wof:placetype":"venue"
},
  "geometry": {"coordinates":[-81.941742,29.19241],"type":"Point"}
}