{
  "type": "Feature",
  "properties": {
    "iso:country":"US",
    "sg:address":"8289 Park Blvd N",
    "sg:city":"Seminole",
    "sg:classifiers":[
        {
            "category":"Food & Beverages",
            "subcategory":"Groceries & Convenience Stores",
            "type":"Retail Goods"
        }
    ],
    "sg:phone":"+1 727 399 1556",
    "sg:postcode":"33777",
    "sg:province":"FL",
    "wof:name":"Giant Food Mart No 3",
    "wof:placetype":"venue"
},
  "geometry": {"coordinates":[-82.752523,27.839214],"type":"Point"}
}