{
  "type": "Feature",
  "properties": {
    "iso:country":"US",
    "sg:address":"6438 Lake Worth Rd",
    "sg:city":"Greenacres",
    "sg:classifiers":[
        {
            "category":"Retail",
            "subcategory":"Repair Shop",
            "type":"Services"
        }
    ],
    "sg:phone":"+1 561 953 5167",
    "sg:postcode":"33463",
    "sg:province":"FL",
    "sg:tags":[
        "lock",
        "locksmith"
    ],
    "wof:name":"A Emergency A Locksmith",
    "wof:placetype":"venue"
},
  "geometry": {"coordinates":[-80.14619,26.618973],"type":"Point"}
}