{
  "type": "Feature",
  "properties": {
    "addr:full":"1835 Barber St Sebastian FL 32958",
    "addr:housenumber":"1835",
    "addr:postcode":"32958",
    "addr:street":"Barber",
    "iso:country":"US",
    "sg:address":"1835 Barber St",
    "sg:city":"Sebastian",
    "sg:classifiers":[
        {
            "category":"Building & Trades",
            "subcategory":"Construction",
            "type":"Services"
        }
    ],
    "sg:phone":"+1 772 778 8983",
    "sg:postcode":"32958",
    "sg:province":"FL",
    "sg:tags":[
        "contractor"
    ],
    "wof:name":"Perugini Construction Inc",
    "wof:placetype":"venue"
},
  "geometry": {"coordinates":[-80.46888300000001,27.76011],"type":"Point"}
}