{
  "type": "Feature",
  "properties": {
    "addr:full":"351 S Cypress Rd Pompano Beach FL 33060",
    "addr:housenumber":"351",
    "addr:postcode":"33060",
    "addr:street":"S Cypress Rd",
    "iso:country":"US",
    "sg:address":"351 S Cypress Rd",
    "sg:city":"Pompano Beach",
    "sg:classifiers":[
        {
            "category":"Professional",
            "subcategory":"Art Services",
            "type":"Services"
        }
    ],
    "sg:phone":"+1 954 942 5255",
    "sg:postcode":"33060",
    "sg:province":"FL",
    "sg:tags":[
        "commercial",
        "design"
    ],
    "wof:name":"Kall Graphics",
    "wof:placetype":"venue"
},
  "geometry": {"coordinates":[-80.123327,26.225514],"type":"Point"}
}