{
  "type": "Feature",
  "properties": {
    "iso:country":"US",
    "sg:address":"520 Artists Ave",
    "sg:city":"Englewood",
    "sg:classifiers":[
        {
            "category":"Retail",
            "subcategory":"Car Wash",
            "type":"Services"
        }
    ],
    "sg:phone":"+1 941 460 8668",
    "sg:postcode":"34223",
    "sg:province":"FL",
    "wof:name":"Anc Auto Mobile Detailing Salon",
    "wof:placetype":"venue"
},
  "geometry": {"coordinates":[-82.36354,26.975028],"type":"Point"}
}