{
  "type": "Feature",
  "properties": {
    "addr:full":"3545 Carriage Gate Dr Melbourne FL 32904",
    "addr:housenumber":"3545",
    "addr:postcode":"32904",
    "addr:street":"Carriage Gate Dr",
    "iso:country":"US",
    "sg:address":"3545 Carriage Gate Dr",
    "sg:city":"Melbourne",
    "sg:classifiers":[
        {
            "category":"Professional",
            "subcategory":"Engineering",
            "type":"Services"
        }
    ],
    "sg:phone":"+1 321 733 2691",
    "sg:postcode":"32904",
    "sg:province":"FL",
    "sg:tags":[
        "engineer"
    ],
    "wof:name":"Microstar Inc",
    "wof:placetype":"venue"
},
  "geometry": {"coordinates":[-80.672721,28.04817],"type":"Point"}
}