{
  "type": "Feature",
  "properties": {
    "iso:country":"US",
    "sg:address":"1455 NW 107th Ave",
    "sg:city":"Miami",
    "sg:classifiers":[
        {
            "category":"Restaurant",
            "type":"Food & Drink"
        },
        {
            "category":"Food & Beverages",
            "subcategory":"Bakery",
            "type":"Retail Goods"
        },
        {
            "category":"Bakery",
            "type":"Food & Drink"
        }
    ],
    "sg:menulink":"http://www.allmenus.com/fl/north-westside/223839-cinnabon/menu/",
    "sg:phone":"+1 305 499 9527",
    "sg:postcode":"33172",
    "sg:province":"FL",
    "sg:tags":[
        "american",
        "bakery",
        "pastry"
    ],
    "wof:name":"Cinnabon",
    "wof:placetype":"venue"
},
  "geometry": {"coordinates":[-80.368627,25.787189],"type":"Point"}
}