{
  "type": "Feature",
  "properties": {
    "addr:full":"1560 Clayton Rd Chipley FL 32428",
    "addr:housenumber":"1560",
    "addr:postcode":"32428",
    "addr:street":"Clayton Rd",
    "iso:country":"US",
    "sg:address":"1560 Clayton Rd",
    "sg:city":"Chipley",
    "sg:classifiers":[
        {
            "category":"Farming",
            "subcategory":"Farm",
            "type":"Manufacturing & Wholesale Goods"
        }
    ],
    "sg:phone":"+1 850 638 7628",
    "sg:postcode":"32428",
    "sg:province":"FL",
    "wof:name":"Jerry B Morris",
    "wof:placetype":"venue"
},
  "geometry": {"coordinates":[-85.55444300000001,30.698842],"type":"Point"}
}