{
  "type": "Feature",
  "properties": {
    "addr:full":"3550 University Blvd S Jacksonville FL 32216",
    "addr:housenumber":"3550",
    "addr:postcode":"32216",
    "addr:street":"University Blvd S",
    "iso:country":"US",
    "sg:address":"3550 University Blvd S",
    "sg:city":"Jacksonville",
    "sg:classifiers":[
        {
            "category":"Health Services",
            "subcategory":"Doctor",
            "type":"Services"
        }
    ],
    "sg:phone":"+1 904 737 5600",
    "sg:postcode":"32216",
    "sg:province":"FL",
    "sg:tags":[
        "physician",
        "surgeon"
    ],
    "wof:name":"Johnny Jada MD",
    "wof:placetype":"venue"
},
  "geometry": {"coordinates":[-81.60233100000001,30.289262],"type":"Point"}
}