{
  "type": "Feature",
  "properties": {
    "iso:country":"US",
    "sg:address":"41 N Dollins Ave",
    "sg:city":"Orlando",
    "sg:classifiers":[
        {
            "category":"Retail",
            "subcategory":"Auto Repair",
            "type":"Services"
        }
    ],
    "sg:phone":"+1 407 872 0029",
    "sg:postcode":"32805",
    "sg:province":"FL",
    "sg:tags":[
        "body",
        "automobile",
        "painting"
    ],
    "wof:name":"Platinum Plus",
    "wof:placetype":"venue"
},
  "geometry": {"coordinates":[-81.40751400000001,28.543006],"type":"Point"}
}