{
  "type": "Feature",
  "properties": {
    "addr:full":"5830 NW 21st Ave Miami FL 33142",
    "addr:housenumber":"5830",
    "addr:postcode":"33142",
    "addr:street":"Nw 21St Ave",
    "iso:country":"US",
    "sg:address":"5830 NW 21st Ave",
    "sg:city":"Miami",
    "sg:classifiers":[
        {
            "category":"Wholesale",
            "subcategory":"Medical Equipment & Supplies",
            "type":"Manufacturing & Wholesale Goods"
        }
    ],
    "sg:phone":"+1 305 638 7715",
    "sg:postcode":"33142",
    "sg:province":"FL",
    "sg:tags":[
        "physician",
        "surgeon"
    ],
    "wof:name":"Medical Supplies",
    "wof:placetype":"venue"
},
  "geometry": {"coordinates":[-80.230923,25.828518],"type":"Point"}
}