{
  "type": "Feature",
  "properties": {
    "iso:country":"US",
    "sg:address":"5503 W Spruce St",
    "sg:city":"Tampa",
    "sg:classifiers":[
        {
            "category":"Professional",
            "subcategory":"Management & Consulting",
            "type":"Services"
        }
    ],
    "sg:phone":"+1 813 877 6790",
    "sg:postcode":"33607",
    "sg:province":"FL",
    "sg:tags":[
        "construction"
    ],
    "wof:name":"Mathews Construction",
    "wof:placetype":"venue"
},
  "geometry": {"coordinates":[-82.53865,27.960098],"type":"Point"}
}