{
  "type": "Feature",
  "properties": {
    "iso:country":"US",
    "sg:address":"2801 W Waters Ave",
    "sg:city":"Tampa",
    "sg:classifiers":[
        {
            "category":"Health Services",
            "subcategory":"Health Practitioner",
            "type":"Services"
        }
    ],
    "sg:phone":"+1 813 933 6848",
    "sg:postcode":"33614",
    "sg:province":"FL",
    "sg:tags":[
        "equipment",
        "medical",
        "diagnostic"
    ],
    "wof:name":"Sonologics",
    "wof:placetype":"venue"
},
  "geometry": {"coordinates":[-82.489648,28.025343],"type":"Point"}
}