{
  "type": "Feature",
  "properties": {
    "iso:country":"US",
    "sg:address":"500 SE 17th St",
    "sg:city":"Fort Lauderdale",
    "sg:classifiers":[
        {
            "category":"Shopping",
            "subcategory":"Pharmacy",
            "type":"Retail Goods"
        }
    ],
    "sg:phone":"+1 954 525 5107",
    "sg:postcode":"33316",
    "sg:province":"FL",
    "sg:tags":[
        "drug",
        "store"
    ],
    "wof:name":"Tower Pharmacy",
    "wof:placetype":"venue"
},
  "geometry": {"coordinates":[-80.137682,26.100239],"type":"Point"}
}