{
  "type": "Feature",
  "properties": {
    "iso:country":"US",
    "sg:address":"7608 Gainesville Ave",
    "sg:city":"Jacksonville",
    "sg:classifiers":[
        {
            "category":"Retail",
            "subcategory":"Auto Repair",
            "type":"Services"
        }
    ],
    "sg:phone":"+1 904 924 9627",
    "sg:postcode":"32208",
    "sg:province":"FL",
    "sg:tags":[
        "automotive"
    ],
    "wof:name":"J and B Garage",
    "wof:placetype":"venue"
},
  "geometry": {"coordinates":[-81.684915,30.384357],"type":"Point"}
}