{
  "type": "Feature",
  "properties": {
    "iso:country":"US",
    "sg:address":"3405 NW 72nd Ave B",
    "sg:city":"Miami",
    "sg:classifiers":[
        {
            "category":"Marine",
            "type":"Transportation"
        }
    ],
    "sg:phone":"+1 305 463 8533",
    "sg:postcode":"33122",
    "sg:province":"FL",
    "sg:tags":[
        "terminals-river"
    ],
    "wof:name":"Cci",
    "wof:placetype":"venue"
},
  "geometry": {"coordinates":[-80.31308900000001,25.806188],"type":"Point"}
}