{
  "type": "Feature",
  "properties": {
    "addr:full":"7630 34th Ave N St Petersburg FL 33710",
    "addr:housenumber":"7630",
    "addr:postcode":"33710",
    "addr:street":"34Th Ave N",
    "iso:country":"US",
    "sg:address":"7630 34th Ave N",
    "sg:city":"St Petersburg",
    "sg:classifiers":[
        {
            "category":"Restaurant",
            "type":"Food & Drink"
        }
    ],
    "sg:phone":"+1 727 345 4215",
    "sg:postcode":"33710",
    "sg:province":"FL",
    "sg:tags":[
        "delicatessen"
    ],
    "wof:name":"Rosie's Deli",
    "wof:placetype":"venue"
},
  "geometry": {"coordinates":[-82.745361,27.802688],"type":"Point"}
}