{
  "type": "Feature",
  "properties": {
    "addr:full":"11270 4th St N St Petersburg FL 33716",
    "addr:housenumber":"11270",
    "addr:postcode":"33716",
    "addr:street":"4Th St N",
    "iso:country":"US",
    "sg:address":"11270 4th St N",
    "sg:city":"St Petersburg",
    "sg:classifiers":[
        {
            "category":"Real Estate",
            "subcategory":"Real Estate Agent",
            "type":"Services"
        }
    ],
    "sg:phone":"+1 727 563 9090",
    "sg:postcode":"33716",
    "sg:province":"FL",
    "wof:name":"Keen Realty LLC",
    "wof:placetype":"venue"
},
  "geometry": {"coordinates":[-82.638862,27.873826],"type":"Point"}
}