{
  "type": "Feature",
  "properties": {
    "iso:country":"US",
    "sg:address":"1045 Hickory Ln",
    "sg:city":"Cocoa",
    "sg:classifiers":[
        {
            "category":"Real Estate",
            "subcategory":"Real Estate Agent",
            "type":"Services"
        }
    ],
    "sg:phone":"+1 321 635 1992",
    "sg:postcode":"32922",
    "sg:province":"FL",
    "sg:tags":[
        "inspection"
    ],
    "wof:name":"Hometeam Inspection Svc",
    "wof:placetype":"venue"
},
  "geometry": {"coordinates":[-80.743774,28.368063],"type":"Point"}
}