{
  "type": "Feature",
  "properties": {
    "iso:country":"US",
    "sg:address":"57 NW 116th St",
    "sg:city":"Miami",
    "sg:classifiers":[
        {
            "category":"Taxi",
            "type":"Transportation"
        }
    ],
    "sg:phone":"+1 786 299 9576",
    "sg:postcode":"33168",
    "sg:province":"FL",
    "wof:name":"Frankz Taxi",
    "wof:placetype":"venue"
},
  "geometry": {"coordinates":[-80.199461,25.881473],"type":"Point"}
}