{
  "type": "Feature",
  "properties": {
    "iso:country":"US",
    "sg:address":"6505 N W St",
    "sg:city":"Pensacola",
    "sg:classifiers":[
        {
            "category":"Insurance",
            "subcategory":"Insurance Agent",
            "type":"Services"
        }
    ],
    "sg:phone":"+1 850 476 7570",
    "sg:postcode":"32505",
    "sg:province":"FL",
    "wof:name":"Allstate",
    "wof:placetype":"venue"
},
  "geometry": {"coordinates":[-87.25811899999999,30.480489],"type":"Point"}
}