{
  "type": "Feature",
  "properties": {
    "iso:country":"US",
    "sg:address":"7550 Hinson St",
    "sg:city":"Orlando",
    "sg:classifiers":[
        {
            "category":"Building & Trades",
            "subcategory":"Construction",
            "type":"Services"
        }
    ],
    "sg:phone":"+1 407 947 0697",
    "sg:postcode":"32819",
    "sg:province":"FL",
    "sg:tags":[
        "general",
        "contractor"
    ],
    "wof:name":"Mastercraft LLC",
    "wof:placetype":"venue"
},
  "geometry": {"coordinates":[-81.48612300000001,28.451848],"type":"Point"}
}