{
  "type": "Feature",
  "properties": {
    "addr:full":"15445 SW 137th Ave Miami FL 33177",
    "addr:housenumber":"15445",
    "addr:postcode":"33177",
    "addr:street":"Sw 137Th Ave",
    "iso:country":"US",
    "sg:address":"15445 SW 137th Ave",
    "sg:city":"Miami",
    "sg:classifiers":[
        {
            "category":"Personal",
            "subcategory":"Beauty Salon",
            "type":"Services"
        }
    ],
    "sg:phone":"+1 786 242 9940",
    "sg:postcode":"33177",
    "sg:province":"FL",
    "sg:tags":[
        "shop"
    ],
    "wof:name":"Ricardo's Hair Designers",
    "wof:placetype":"venue"
},
  "geometry": {"coordinates":[-80.41439200000001,25.623586],"type":"Point"}
}