{
  "type": "Feature",
  "properties": {
    "iso:country":"US",
    "sg:address":"10701 SW 56th St",
    "sg:city":"Miami",
    "sg:classifiers":[
        {
            "category":"Autos & Motor Vehicles",
            "subcategory":"Fuel & Gas Station",
            "type":"Retail Goods"
        }
    ],
    "sg:phone":"+1 305 279 3944",
    "sg:postcode":"33165",
    "sg:province":"FL",
    "sg:tags":[
        "oil"
    ],
    "wof:name":"BP",
    "wof:placetype":"venue"
},
  "geometry": {"coordinates":[-80.36906399999999,25.715373],"type":"Point"}
}