{
  "type": "Feature",
  "properties": {
    "iso:country":"US",
    "sg:address":"14301 Bruce B Downs Blvd",
    "sg:city":"Tampa",
    "sg:classifiers":[
        {
            "category":"Professional",
            "subcategory":"Business Services",
            "type":"Services"
        }
    ],
    "sg:phone":"+1 813 910 0624",
    "sg:postcode":"33613",
    "sg:province":"FL",
    "sg:tags":[
        "drafting"
    ],
    "wof:name":"Youngraphix Inc",
    "wof:placetype":"venue"
},
  "geometry": {"coordinates":[-82.42609400000001,28.075573],"type":"Point"}
}