{
  "type": "Feature",
  "properties": {
    "iso:country":"US",
    "sg:address":"2659 W 77th Pl",
    "sg:city":"Hialeah",
    "sg:classifiers":[
        {
            "category":"Building & Trades",
            "subcategory":"Construction",
            "type":"Services"
        }
    ],
    "sg:phone":"+1 305 364 0066",
    "sg:postcode":"33016",
    "sg:province":"FL",
    "sg:tags":[
        "installation",
        "glazier",
        "contractor",
        "window",
        "front",
        "store"
    ],
    "wof:name":"Allstate Glass & Aluminum Co",
    "wof:placetype":"venue"
},
  "geometry": {"coordinates":[-80.337126,25.89284],"type":"Point"}
}