{
  "type": "Feature",
  "properties": {
    "iso:country":"US",
    "sg:address":"6902 W Hillsborough Ave",
    "sg:city":"Tampa",
    "sg:classifiers":[
        {
            "category":"Personal",
            "type":"Services"
        },
        {
            "category":"Organizations",
            "subcategory":"Professional Association",
            "type":"Services"
        }
    ],
    "sg:phone":"+1 877 470 6554",
    "sg:postcode":"33634",
    "sg:province":"FL",
    "sg:tags":[
        "singles-organizations",
        "dating"
    ],
    "wof:name":"Emeraldcoast Goldenkeys, Inc.",
    "wof:placetype":"venue"
},
  "geometry": {"coordinates":[-82.55662700000001,27.99645],"type":"Point"}
}