{
  "type": "Feature",
  "properties": {
    "iso:country":"US",
    "sg:address":"13000 Bruce B Downs Blvd # 11",
    "sg:city":"Tampa",
    "sg:classifiers":[
        {
            "category":"Education",
            "subcategory":"University",
            "type":"Public Place"
        }
    ],
    "sg:phone":"+1 813 972 7631",
    "sg:postcode":"33612",
    "sg:province":"FL",
    "sg:tags":[
        "college"
    ],
    "sg:website":"http://www.usf.edu",
    "wof:name":"Allergy & Immunology",
    "wof:placetype":"venue"
},
  "geometry": {"coordinates":[-82.42614,28.064723],"type":"Point"}
}