{
  "type": "Feature",
  "properties": {
    "iso:country":"US",
    "sg:address":"10408 Sedgebrook Dr",
    "sg:city":"Riverview",
    "sg:classifiers":[
        {
            "category":"Real Estate",
            "subcategory":"Real Estate Agent",
            "type":"Services"
        }
    ],
    "sg:phone":"+1 813 672 2049",
    "sg:postcode":"33569",
    "sg:province":"FL",
    "wof:name":"J&M McCarty Inc",
    "wof:placetype":"venue"
},
  "geometry": {"coordinates":[-82.278728,27.852193],"type":"Point"}
}