{
  "type": "Feature",
  "properties": {
    "iso:country":"US",
    "sg:address":"4015 Post Rd",
    "sg:city":"Melbourne",
    "sg:classifiers":[
        {
            "category":"Insurance",
            "subcategory":"Insurance Agent",
            "type":"Services"
        }
    ],
    "sg:phone":"+1 321 253 2033",
    "sg:postcode":"32934",
    "sg:province":"FL",
    "wof:name":"Peggy Thompson",
    "wof:placetype":"venue"
},
  "geometry": {"coordinates":[-80.695329,28.171853],"type":"Point"}
}