{
  "type": "Feature",
  "properties": {
    "addr:full":"49 SW Flagler Ave Stuart FL 34994",
    "addr:housenumber":"49",
    "addr:postcode":"34994",
    "addr:street":"Sw Flagler Ave",
    "iso:country":"US",
    "sg:address":"49 SW Flagler Ave",
    "sg:city":"Stuart",
    "sg:classifiers":[
        {
            "category":"Health Services",
            "subcategory":"Health Practitioner",
            "type":"Services"
        }
    ],
    "sg:phone":"+1 772 283 4338",
    "sg:postcode":"34994",
    "sg:province":"FL",
    "sg:tags":[
        "nutritionist"
    ],
    "wof:name":"NTS",
    "wof:placetype":"venue"
},
  "geometry": {"coordinates":[-80.253939,27.198797],"type":"Point"}
}