{
  "type": "Feature",
  "properties": {
    "addr:full":"3560 Main Hwy Miami FL 33133",
    "addr:housenumber":"3560",
    "addr:postcode":"33133",
    "addr:street":"Main Hwy",
    "iso:country":"US",
    "sg:address":"3560 Main Hwy",
    "sg:city":"Miami",
    "sg:classifiers":[
        {
            "category":"Real Estate",
            "subcategory":"Real Estate Agent",
            "type":"Services"
        }
    ],
    "sg:phone":"+1 305 460 8282",
    "sg:postcode":"33133",
    "sg:province":"FL",
    "sg:website":"www.ewm.com",
    "wof:name":"Esslinger-Wooten-Maxwell Rltrs",
    "wof:placetype":"venue"
},
  "geometry": {"coordinates":[-80.24608000000001,25.724025],"type":"Point"}
}