{
  "type": "Feature",
  "properties": {
    "iso:country":"US",
    "sg:address":"369 Blanding Blvd",
    "sg:city":"Orange Park",
    "sg:classifiers":[
        {
            "category":"Banks & Credit Unions",
            "subcategory":"Bank",
            "type":"Services"
        }
    ],
    "sg:phone":"+1 904 276 2151",
    "sg:postcode":"32073",
    "sg:province":"FL",
    "sg:tags":[
        "cashing",
        "check"
    ],
    "wof:name":"Cars To Go Of North Florida",
    "wof:placetype":"venue"
},
  "geometry": {"coordinates":[-81.747635,30.16615],"type":"Point"}
}