{
  "type": "Feature",
  "properties": {
    "iso:country":"US",
    "sg:address":"4259 SW 69th Ave",
    "sg:city":"Miami",
    "sg:classifiers":[
        {
            "category":"Autos & Motor Vehicles",
            "subcategory":"Automobile Sales",
            "type":"Retail Goods"
        }
    ],
    "sg:phone":"+1 305 668 6740",
    "sg:postcode":"33155",
    "sg:province":"FL",
    "sg:tags":[
        "used"
    ],
    "wof:name":"Delgado Garcia International I",
    "wof:placetype":"venue"
},
  "geometry": {"coordinates":[-80.30635700000001,25.729657],"type":"Point"}
}