{
  "type": "Feature",
  "properties": {
    "addr:full":"2270 Sand Lake Rd Altamonte Spgs FL 32714",
    "addr:housenumber":"2270",
    "addr:postcode":"32714",
    "addr:street":"Sand Lake Rd",
    "iso:country":"US",
    "sg:address":"2270 Sand Lake Rd",
    "sg:city":"Altamonte Spgs",
    "sg:classifiers":[
        {
            "category":"Organizations",
            "subcategory":"Religious Organization",
            "type":"Services"
        }
    ],
    "sg:phone":"+1 407 855 9968",
    "sg:postcode":"32714",
    "sg:province":"FL",
    "sg:tags":[
        "church"
    ],
    "wof:name":"Church Of God Seventh Day",
    "wof:placetype":"venue"
},
  "geometry": {"coordinates":[-81.42320100000001,28.680128],"type":"Point"}
}