{
  "type": "Feature",
  "properties": {
    "iso:country":"US",
    "sg:address":"2533 Herschel St",
    "sg:city":"Jacksonville",
    "sg:classifiers":[
        {
            "category":"Health Services",
            "subcategory":"Health Practitioner",
            "type":"Services"
        }
    ],
    "sg:phone":"+1 904 387 4489",
    "sg:postcode":"32204",
    "sg:province":"FL",
    "sg:tags":[
        "hypnotist"
    ],
    "wof:name":"Ben G Edmonson",
    "wof:placetype":"venue"
},
  "geometry": {"coordinates":[-81.688782,30.311346],"type":"Point"}
}