{
  "type": "Feature",
  "properties": {
    "addr:full":"3030 SW 89th Pl Ocala FL 34476",
    "addr:housenumber":"3030",
    "addr:postcode":"34476",
    "addr:street":"Sw 89Th Pl",
    "iso:country":"US",
    "sg:address":"3030 SW 89th Pl",
    "sg:city":"Ocala",
    "sg:classifiers":[
        {
            "category":"Building & Trades",
            "subcategory":"Landscaping Services",
            "type":"Services"
        }
    ],
    "sg:phone":"+1 352 237 1933",
    "sg:postcode":"34476",
    "sg:province":"FL",
    "wof:name":"Deckard Bushhogging Inc",
    "wof:placetype":"venue"
},
  "geometry": {"coordinates":[-82.17546,29.092527],"type":"Point"}
}