{
  "type": "Feature",
  "properties": {
    "iso:country":"US",
    "sg:address":"1440 10th Ct",
    "sg:city":"West Palm Beach",
    "sg:classifiers":[
        {
            "category":"Retail",
            "subcategory":"Auto Repair",
            "type":"Services"
        }
    ],
    "sg:phone":"+1 561 881 8930",
    "sg:postcode":"33403",
    "sg:province":"FL",
    "sg:tags":[
        "trim",
        "conversion",
        "work",
        "van"
    ],
    "wof:name":"North Palm Auto Trim/Van Cnvrs",
    "wof:placetype":"venue"
},
  "geometry": {"coordinates":[-80.076188,26.8067],"type":"Point"}
}