{
  "type": "Feature",
  "properties": {
    "iso:country":"US",
    "sg:address":"175 Hialeah Dr",
    "sg:city":"Hialeah",
    "sg:classifiers":[
        {
            "category":"Building & Trades",
            "subcategory":"Locksmith",
            "type":"Services"
        }
    ],
    "sg:phone":"+1 305 908 8003",
    "sg:postcode":"33010",
    "sg:province":"FL",
    "sg:tags":[
        "key"
    ],
    "wof:name":"1 Day 1 Time Hialeah Locksmith",
    "wof:placetype":"venue"
},
  "geometry": {"coordinates":[-80.277693,25.822927],"type":"Point"}
}