{
  "type": "Feature",
  "properties": {
    "addr:full":"3555 Pineridge Cir Kissimmee FL 34746",
    "addr:housenumber":"3555",
    "addr:postcode":"34746",
    "addr:street":"Pineridge Cir",
    "iso:country":"US",
    "sg:address":"3555 Pineridge Cir",
    "sg:city":"Kissimmee",
    "sg:classifiers":[
        {
            "category":"Shopping",
            "subcategory":"Gifts & Souvenirs",
            "type":"Retail Goods"
        }
    ],
    "sg:phone":"+1 407 343 4651",
    "sg:postcode":"34746",
    "sg:province":"FL",
    "wof:name":"Lumania Corp",
    "wof:placetype":"venue"
},
  "geometry": {"coordinates":[-81.43780599999999,28.229844],"type":"Point"}
}