{
  "type": "Feature",
  "properties": {
    "iso:country":"US",
    "sg:address":"1834 Candlewood Dr",
    "sg:city":"Gulf Breeze",
    "sg:classifiers":[
        {
            "category":"Professional",
            "subcategory":"Detective & Security Services",
            "type":"Services"
        }
    ],
    "sg:phone":"+1 850 939 5879",
    "sg:postcode":"32566",
    "sg:province":"FL",
    "sg:tags":[
        "investigator"
    ],
    "wof:name":"Langdon Investigation",
    "wof:placetype":"venue"
},
  "geometry": {"coordinates":[-86.943116,30.405633],"type":"Point"}
}