{
  "type": "Feature",
  "properties": {
    "addr:full":"4000 Dow Rd Melbourne FL 32934",
    "addr:housenumber":"4000",
    "addr:postcode":"32934",
    "addr:street":"Dow Rd",
    "iso:country":"US",
    "sg:address":"4000 Dow Rd",
    "sg:city":"Melbourne",
    "sg:classifiers":[
        {
            "category":"Manufacturing",
            "subcategory":"Printing",
            "type":"Manufacturing & Wholesale Goods"
        }
    ],
    "sg:phone":"+1 321 255 2003",
    "sg:postcode":"32934",
    "sg:province":"FL",
    "sg:tags":[
        "trade"
    ],
    "wof:name":"My Letterpress Shop Inc",
    "wof:placetype":"venue"
},
  "geometry": {"coordinates":[-80.691053,28.107592],"type":"Point"}
}