{
  "type": "Feature",
  "properties": {
    "addr:full":"1363 E Tennessee St Tallahassee FL 32308",
    "addr:housenumber":"1363",
    "addr:postcode":"32308",
    "addr:street":"E Tennessee St",
    "iso:country":"US",
    "sg:address":"1363 E Tennessee St",
    "sg:city":"Tallahassee",
    "sg:classifiers":[
        {
            "category":"Communications",
            "subcategory":"Radio Station",
            "type":"Services"
        }
    ],
    "sg:phone":"+1 850 877 0105",
    "sg:postcode":"32308",
    "sg:province":"FL",
    "sg:tags":[
        "a",
        "as",
        "operates"
    ],
    "wof:name":"W T A L Radio Station",
    "wof:placetype":"venue"
},
  "geometry": {"coordinates":[-84.260488,30.448266],"type":"Point"}
}