{
  "type": "Feature",
  "properties": {
    "iso:country":"US",
    "sg:address":"5001 N 12th Ave",
    "sg:city":"Pensacola",
    "sg:classifiers":[
        {
            "category":"Retail",
            "subcategory":"Veterinary Services",
            "type":"Services"
        }
    ],
    "sg:phone":"+1 850 202 2020",
    "sg:postcode":"32503",
    "sg:province":"FL",
    "sg:tags":[
        "veterinarian"
    ],
    "wof:name":"Housecall Veterinarian",
    "wof:placetype":"venue"
},
  "geometry": {"coordinates":[-87.199994,30.47361],"type":"Point"}
}