{
  "type": "Feature",
  "properties": {
    "addr:full":"5225 Tech Data Dr Clearwater FL 33760",
    "addr:housenumber":"5225",
    "addr:postcode":"33760",
    "addr:street":"Data Dr",
    "iso:country":"US",
    "sg:address":"5225 Tech Data Dr",
    "sg:city":"Clearwater",
    "sg:classifiers":[
        {
            "category":"Utilities",
            "subcategory":"Electric",
            "type":"Services"
        },
        {
            "category":"Manufacturing",
            "subcategory":"Electronics",
            "type":"Manufacturing & Wholesale Goods"
        }
    ],
    "sg:phone":"+1 727 443 2641",
    "sg:postcode":"33760",
    "sg:province":"FL",
    "sg:tags":[
        "equipment-testing"
    ],
    "sg:website":"http://progress-energy.com/",
    "wof:name":"Progress Energy, Inc.",
    "wof:placetype":"venue"
},
  "geometry": {"coordinates":[-82.707339,27.917549],"type":"Point"}
}