{
  "type": "Feature",
  "properties": {
    "addr:full":"415 N Andrews Ave Fort Lauderdale FL 33301",
    "addr:housenumber":"415",
    "addr:postcode":"33301",
    "addr:street":"N Andrews Ave",
    "iso:country":"US",
    "sg:address":"415 N Andrews Ave",
    "sg:city":"Fort Lauderdale",
    "sg:classifiers":[
        {
            "category":"Professional",
            "subcategory":"Printing & Photocopies",
            "type":"Services"
        }
    ],
    "sg:phone":"+1 954 766 8883",
    "sg:postcode":"33301",
    "sg:province":"FL",
    "sg:tags":[
        "photocopying"
    ],
    "wof:name":"Benchmark Legal Solutions",
    "wof:placetype":"venue"
},
  "geometry": {"coordinates":[-80.143767,26.127581],"type":"Point"}
}