{
  "type": "Feature",
  "properties": {
    "addr:full":"17110 NW 12th Ave Miami FL 33169",
    "addr:housenumber":"17110",
    "addr:postcode":"33169",
    "addr:street":"Nw 12Th Ave",
    "iso:country":"US",
    "sg:address":"17110 NW 12th Ave",
    "sg:city":"Miami",
    "sg:classifiers":[
        {
            "category":"Professional",
            "subcategory":"Business Services",
            "type":"Services"
        }
    ],
    "sg:phone":"+1 305 623 4476",
    "sg:postcode":"33169",
    "sg:province":"FL",
    "wof:name":"North Dade Notary",
    "wof:placetype":"venue"
},
  "geometry": {"coordinates":[-80.22073899999999,25.931442],"type":"Point"}
}