{
  "type": "Feature",
  "properties": {
    "iso:country":"US",
    "sg:address":"7249 Abbey Ln",
    "sg:city":"Winter Park",
    "sg:classifiers":[
        {
            "category":"Building & Trades",
            "subcategory":"Construction",
            "type":"Services"
        }
    ],
    "sg:phone":"+1 407 678 6500",
    "sg:postcode":"32792",
    "sg:province":"FL",
    "sg:tags":[
        "painter"
    ],
    "wof:name":"J & J Chattahoochee Stone & Painting",
    "wof:placetype":"venue"
},
  "geometry": {"coordinates":[-81.2901,28.6201],"type":"Point"}
}