{
  "type": "Feature",
  "properties": {
    "addr:full":"2721 Capital Cir NE Tallahassee FL 32308",
    "addr:housenumber":"2721",
    "addr:postcode":"32308",
    "addr:street":"Capital Cir Ne",
    "iso:country":"US",
    "sg:address":"2721 Capital Cir NE",
    "sg:city":"Tallahassee",
    "sg:classifiers":[
        {
            "category":"Real Estate",
            "subcategory":"Real Estate Services",
            "type":"Services"
        },
        {
            "category":"Banks & Credit Unions",
            "subcategory":"Bank",
            "type":"Services"
        }
    ],
    "sg:phone":"+1 850 385 3221",
    "sg:postcode":"32308",
    "sg:province":"FL",
    "sg:tags":[
        "commercial",
        "loan",
        "saving"
    ],
    "sg:website":"http://www.superiorbank.com",
    "wof:name":"Superior Bank",
    "wof:placetype":"venue"
},
  "geometry": {"coordinates":[-84.239722,30.488771],"type":"Point"}
}