{
  "type": "Feature",
  "properties": {
    "addr:full":"927 W Oak St Kissimmee FL 34741",
    "addr:housenumber":"927",
    "addr:postcode":"34741",
    "addr:street":"W Oak St",
    "iso:country":"US",
    "sg:address":"927 W Oak St",
    "sg:city":"Kissimmee",
    "sg:classifiers":[
        {
            "category":"Shopping",
            "subcategory":"Computers & Home Electronics",
            "type":"Retail Goods"
        },
        {
            "category":"Professional",
            "subcategory":"Art Services",
            "type":"Services"
        },
        {
            "category":"Wholesale",
            "subcategory":"Office Equipment",
            "type":"Manufacturing & Wholesale Goods"
        },
        {
            "category":"Manufacturing",
            "subcategory":"Electronics",
            "type":"Manufacturing & Wholesale Goods"
        },
        {
            "category":"Professional",
            "subcategory":"Printing & Photocopies",
            "type":"Services"
        },
        {
            "category":"Professional",
            "subcategory":"Advertising",
            "type":"Services"
        }
    ],
    "sg:phone":"+1 407 847 5565",
    "sg:postcode":"34741",
    "sg:province":"FL",
    "sg:tags":[
        "scanning",
        "graphic",
        "supply",
        "services-commercial",
        "direct",
        "duplicating",
        "designer",
        "copying",
        "mail",
        "printers-equipment",
        "plotting",
        "printer"
    ],
    "sg:website":"http://bizsearch.tmpdm.com/P/pip-printing-kissimmee-fl.html",
    "wof:name":"PIP Printing of Kissimmee",
    "wof:placetype":"venue"
},
  "geometry": {"coordinates":[-81.413203,28.300867],"type":"Point"}
}