{
  "type": "Feature",
  "properties": {
    "iso:country":"US",
    "sg:address":"121 White Birch Dr",
    "sg:city":"Kissimmee",
    "sg:classifiers":[
        {
            "category":"Local Transit",
            "type":"Transportation"
        }
    ],
    "sg:phone":"+1 407 344 2334",
    "sg:postcode":"34743",
    "sg:province":"FL",
    "sg:tags":[
        "public"
    ],
    "wof:name":"Double D Transportation",
    "wof:placetype":"venue"
},
  "geometry": {"coordinates":[-81.370277,28.338262],"type":"Point"}
}