{
  "type": "Feature",
  "properties": {
    "addr:full":"2201 SE Indian St Stuart FL 34997",
    "addr:housenumber":"2201",
    "addr:postcode":"34997",
    "addr:street":"Se Indian St",
    "iso:country":"US",
    "sg:address":"2201 SE Indian St",
    "sg:city":"Stuart",
    "sg:classifiers":[
        {
            "category":"Shopping",
            "subcategory":"Clothing, Apparel, & Fashions",
            "type":"Retail Goods"
        }
    ],
    "sg:phone":"+1 772 221 0602",
    "sg:postcode":"34997",
    "sg:province":"FL",
    "sg:tags":[
        "navy",
        "army"
    ],
    "wof:name":"E & P Army Navy Surplus",
    "wof:placetype":"venue"
},
  "geometry": {"coordinates":[-80.225792,27.166494],"type":"Point"}
}