{
  "type": "Feature",
  "properties": {
    "iso:country":"US",
    "sg:address":"2910 NW 64th Ave",
    "sg:city":"Hollywood",
    "sg:classifiers":[
        {
            "category":"Organizations",
            "subcategory":"Religious Organization",
            "type":"Services"
        }
    ],
    "sg:phone":"+1 954 894 5651",
    "sg:postcode":"33024",
    "sg:province":"FL",
    "sg:tags":[
        "church"
    ],
    "sg:website":"www.chickeechurch.org",
    "wof:name":"Chickee Baptist Church",
    "wof:placetype":"venue"
},
  "geometry": {"coordinates":[-80.216666,26.035672],"type":"Point"}
}