{
  "type": "Feature",
  "properties": {
    "addr:full":"20010 NW 8th St Hollywood FL 33029",
    "addr:housenumber":"20010",
    "addr:postcode":"33029",
    "addr:street":"Nw 8Th St",
    "iso:country":"US",
    "sg:address":"20010 NW 8th St",
    "sg:city":"Hollywood",
    "sg:classifiers":[
        {
            "category":"Building & Trades",
            "subcategory":"Construction",
            "type":"Services"
        }
    ],
    "sg:phone":"+1 954 436 1550",
    "sg:postcode":"33029",
    "sg:province":"FL",
    "sg:tags":[
        "house"
    ],
    "wof:name":"Thm Construction LLC",
    "wof:placetype":"venue"
},
  "geometry": {"coordinates":[-80.41483700000001,26.014198],"type":"Point"}
}