{
  "type": "Feature",
  "properties": {
    "iso:country":"US",
    "sg:address":"101 N Federal Hwy",
    "sg:city":"Boca Raton",
    "sg:classifiers":[
        {
            "category":"Banks & Credit Unions",
            "subcategory":"Investment Brokerage",
            "type":"Services"
        }
    ],
    "sg:phone":"+1 561 893 9901",
    "sg:postcode":"33432",
    "sg:province":"FL",
    "sg:tags":[
        "advisory",
        "financial"
    ],
    "sg:website":"www.lcmadvisors.com",
    "wof:name":"Levitt Capital Management",
    "wof:placetype":"venue"
},
  "geometry": {"coordinates":[-80.086438,26.352342],"type":"Point"}
}