{
  "type": "Feature",
  "properties": {
    "addr:full":"2876 SW 128th Way Hollywood FL 33027",
    "addr:housenumber":"2876",
    "addr:postcode":"33027",
    "addr:street":"Sw 128Th Way",
    "iso:country":"US",
    "sg:address":"2876 SW 128th Way",
    "sg:city":"Hollywood",
    "sg:classifiers":[
        {
            "category":"Professional",
            "subcategory":"Business Services",
            "type":"Services"
        }
    ],
    "sg:phone":"+1 954 662 6251",
    "sg:postcode":"33027",
    "sg:province":"FL",
    "wof:name":"Jumping Minds Group Inc",
    "wof:placetype":"venue"
},
  "geometry": {"coordinates":[-80.31599799999999,25.982044],"type":"Point"}
}