{
  "type": "Feature",
  "properties": {
    "iso:country":"US",
    "sg:address":"13101 NW 14th St",
    "sg:city":"Miami",
    "sg:classifiers":[
        {
            "category":"Professional",
            "type":"Services"
        }
    ],
    "sg:phone":"+1 305 592 6927",
    "sg:postcode":"33182",
    "sg:province":"FL",
    "sg:tags":[
        "establishment"
    ],
    "sg:website":"www.tallowmasters.com",
    "wof:name":"Tallowmasters LLC",
    "wof:placetype":"venue"
},
  "geometry": {"coordinates":[-80.40701900000001,25.786252],"type":"Point"}
}