{
  "type": "Feature",
  "properties": {
    "iso:country":"US",
    "sg:address":"8321 Champions Gate Blvd",
    "sg:city":"Champions Gate",
    "sg:classifiers":[
        {
            "category":"Banks & Credit Unions",
            "subcategory":"Bank",
            "type":"Services"
        },
        {
            "category":"Banks & Credit Unions",
            "subcategory":"Financial Services",
            "type":"Services"
        }
    ],
    "sg:phone":"+1 407 397 7137",
    "sg:postcode":"33896",
    "sg:province":"FL",
    "sg:tags":[
        "broker",
        "mortgage"
    ],
    "sg:website":"www.rbcbankusa.com",
    "wof:name":"Rbc Bank",
    "wof:placetype":"venue"
},
  "geometry": {"coordinates":[-81.620295,28.261644],"type":"Point"}
}