{
  "type": "Feature",
  "properties": {
    "iso:country":"US",
    "sg:address":"3398 Southern Cay Dr",
    "sg:city":"Jupiter",
    "sg:classifiers":[
        {
            "category":"Wholesale",
            "subcategory":"Chemicals & Plastics",
            "type":"Manufacturing & Wholesale Goods"
        }
    ],
    "sg:phone":"+1 561 575 2641",
    "sg:postcode":"33477",
    "sg:province":"FL",
    "sg:tags":[
        "carbon"
    ],
    "wof:name":"Heritage Chemical Sales Inc",
    "wof:placetype":"venue"
},
  "geometry": {"coordinates":[-80.08456,26.920182],"type":"Point"}
}