{
  "type": "Feature",
  "properties": {
    "iso:country":"US",
    "sg:address":"12545 State Road 535",
    "sg:city":"Orlando",
    "sg:classifiers":[
        {
            "category":"Personal",
            "type":"Services"
        },
        {
            "category":"Sports & Exercise",
            "subcategory":"Golf",
            "type":"Entertainment"
        }
    ],
    "sg:phone":"+1 407 827 1242",
    "sg:postcode":"32836",
    "sg:province":"FL",
    "sg:tags":[
        "planning",
        "course",
        "instruction",
        "event",
        "party"
    ],
    "wof:name":"Pirate's Cove Adventure Golf",
    "wof:placetype":"venue"
},
  "geometry": {"coordinates":[-81.50533,28.382011],"type":"Point"}
}