{
  "type": "Feature",
  "properties": {
    "addr:full":"1038 Semoran Blvd Casselberry FL 32707",
    "addr:housenumber":"1038",
    "addr:postcode":"32707",
    "addr:street":"Semoran Blvd",
    "iso:country":"US",
    "sg:address":"1038 Semoran Blvd",
    "sg:city":"Casselberry",
    "sg:classifiers":[
        {
            "category":"Food & Beverages",
            "subcategory":"Specialty",
            "type":"Retail Goods"
        }
    ],
    "sg:phone":"+1 407 830 4993",
    "sg:postcode":"32707",
    "sg:province":"FL",
    "sg:tags":[
        "health",
        "diet"
    ],
    "wof:name":"GNC",
    "wof:placetype":"venue"
},
  "geometry": {"coordinates":[-81.322519,28.646239],"type":"Point"}
}