{
  "type": "Feature",
  "properties": {
    "iso:country":"US",
    "sg:address":"11218 SW 11th St",
    "sg:city":"Hollywood",
    "sg:classifiers":[
        {
            "category":"Manufacturing",
            "subcategory":"Signs",
            "type":"Manufacturing & Wholesale Goods"
        }
    ],
    "sg:phone":"+1 954 499 0349",
    "sg:postcode":"33025",
    "sg:province":"FL",
    "sg:tags":[
        "industry",
        "printing",
        "publishing",
        "allied"
    ],
    "wof:name":"SD Graphics Marketing",
    "wof:placetype":"venue"
},
  "geometry": {"coordinates":[-80.30941900000001,25.999166],"type":"Point"}
}