{
  "type": "Feature",
  "properties": {
    "addr:full":"342 Girvin Rd Jacksonville FL 32225",
    "addr:housenumber":"342",
    "addr:postcode":"32225",
    "addr:street":"Girvin Rd",
    "iso:country":"US",
    "sg:address":"342 Girvin Rd",
    "sg:city":"Jacksonville",
    "sg:classifiers":[
        {
            "category":"Manufacturing",
            "subcategory":"Furniture",
            "type":"Manufacturing & Wholesale Goods"
        }
    ],
    "sg:phone":"+1 904 221 5818",
    "sg:postcode":"32225",
    "sg:province":"FL",
    "sg:tags":[
        "household",
        "wood",
        "mfg"
    ],
    "wof:name":"Swampman Driftwood Center",
    "wof:placetype":"venue"
},
  "geometry": {"coordinates":[-81.471541,30.328578],"type":"Point"}
}