{
  "type": "Feature",
  "properties": {
    "addr:full":"7780 SW 118th St Miami FL 33156",
    "addr:housenumber":"7780",
    "addr:postcode":"33156",
    "addr:street":"Sw 118Th St",
    "iso:country":"US",
    "sg:address":"7780 SW 118th St",
    "sg:city":"Miami",
    "sg:classifiers":[
        {
            "category":"Building & Trades",
            "subcategory":"Electrical",
            "type":"Services"
        }
    ],
    "sg:phone":"+1 305 233 9765",
    "sg:postcode":"33156",
    "sg:province":"FL",
    "sg:tags":[
        "electrician"
    ],
    "wof:name":"Ray Brown Electric",
    "wof:placetype":"venue"
},
  "geometry": {"coordinates":[-80.319603,25.660801],"type":"Point"}
}