{
  "type": "Feature",
  "properties": {
    "iso:country":"US",
    "sg:address":"4101 E 10th Ln",
    "sg:city":"Hialeah",
    "sg:classifiers":[
        {
            "category":"Retail",
            "subcategory":"Auto Repair",
            "type":"Services"
        }
    ],
    "sg:phone":"+1 305 681 2626",
    "sg:postcode":"33013",
    "sg:province":"FL",
    "wof:name":"GM Express Racing",
    "wof:placetype":"venue"
},
  "geometry": {"coordinates":[-80.26114800000001,25.860112],"type":"Point"}
}