{
  "type": "Feature",
  "properties": {
    "iso:country":"US",
    "sg:address":"8246 SW 10th Ter",
    "sg:city":"Miami",
    "sg:classifiers":[
        {
            "category":"Professional",
            "subcategory":"Engineering",
            "type":"Services"
        }
    ],
    "sg:phone":"+1 305 553 0022",
    "sg:postcode":"33144",
    "sg:province":"FL",
    "sg:tags":[
        "consulting",
        "engineer"
    ],
    "wof:name":"Michelle Construction Corp",
    "wof:placetype":"venue"
},
  "geometry": {"coordinates":[-80.328773,25.760082],"type":"Point"}
}