{
  "type": "Feature",
  "properties": {
    "addr:full":"7311 Trade Ct Sarasota FL 34240",
    "addr:housenumber":"7311",
    "addr:postcode":"34240",
    "addr:street":"Trade Ct",
    "iso:country":"US",
    "sg:address":"7311 Trade Ct",
    "sg:city":"Sarasota",
    "sg:classifiers":[
        {
            "category":"Professional",
            "type":"Services"
        }
    ],
    "sg:phone":"+1 941 907 4116",
    "sg:postcode":"34240",
    "sg:province":"FL",
    "sg:tags":[
        "establishment"
    ],
    "wof:name":"Syncor International Corp",
    "wof:placetype":"venue"
},
  "geometry": {"coordinates":[-82.42457899999999,27.381387],"type":"Point"}
}