{
  "type": "Feature",
  "properties": {
    "addr:full":"18565 SW 42nd St Miramar FL 33029",
    "addr:housenumber":"18565",
    "addr:postcode":"33029",
    "addr:street":"Sw 42Nd St",
    "iso:country":"US",
    "sg:address":"18565 SW 42nd St",
    "sg:city":"Miramar",
    "sg:classifiers":[
        {
            "category":"Banks & Credit Unions",
            "subcategory":"Bank",
            "type":"Services"
        }
    ],
    "sg:phone":"+1 954 430 7026",
    "sg:postcode":"33029",
    "sg:province":"FL",
    "sg:tags":[
        "loan"
    ],
    "wof:name":"S & M Equity & Invstmnt Group",
    "wof:placetype":"venue"
},
  "geometry": {"coordinates":[-80.392639,25.969293],"type":"Point"}
}