{
  "type": "Feature",
  "properties": {
    "addr:full":"1819 Englewood Rd Englewood FL 34223",
    "addr:housenumber":"1819",
    "addr:postcode":"34223",
    "addr:street":"Englewood Rd",
    "iso:country":"US",
    "sg:address":"1819 Englewood Rd",
    "sg:city":"Englewood",
    "sg:classifiers":[
        {
            "category":"Coffee & Tea",
            "type":"Food & Drink"
        },
        {
            "category":"Restaurant",
            "type":"Food & Drink"
        }
    ],
    "sg:phone":"+1 941 474 8753",
    "sg:postcode":"34223",
    "sg:province":"FL",
    "sg:tags":[
        "espresso"
    ],
    "wof:name":"Sunrise Cafe",
    "wof:placetype":"venue"
},
  "geometry": {"coordinates":[-82.375207,26.998763],"type":"Point"}
}