{
  "type": "Feature",
  "properties": {
    "addr:full":"7611 Ilex Dr Port Richey FL 34668",
    "addr:housenumber":"7611",
    "addr:postcode":"34668",
    "addr:street":"Ilex Dr",
    "iso:country":"US",
    "sg:address":"7611 Ilex Dr",
    "sg:city":"Port Richey",
    "sg:classifiers":[
        {
            "category":"Building & Trades",
            "subcategory":"Construction",
            "type":"Services"
        }
    ],
    "sg:phone":"+1 727 819 2049",
    "sg:postcode":"34668",
    "sg:province":"FL",
    "sg:tags":[
        "concrete",
        "contractor"
    ],
    "wof:name":"Danny Russell",
    "wof:placetype":"venue"
},
  "geometry": {"coordinates":[-82.689187,28.318503],"type":"Point"}
}