{
  "type": "Feature",
  "properties": {
    "iso:country":"US",
    "sg:address":"2824 54th Ave S",
    "sg:city":"St Petersburg",
    "sg:classifiers":[
        {
            "category":"Restaurant",
            "type":"Food & Drink"
        }
    ],
    "sg:menulink":"http://www.allmenus.com/fl/st-petersburg/280978-westshore-pizza/menu/",
    "sg:phone":"+1 727 867 4140",
    "sg:postcode":"33712",
    "sg:province":"FL",
    "sg:tags":[
        "american",
        "pizza"
    ],
    "wof:name":"Westshore Pizza",
    "wof:placetype":"venue"
},
  "geometry": {"coordinates":[-82.67167000000001,27.71912],"type":"Point"}
}