{
  "type": "Feature",
  "properties": {
    "iso:country":"US",
    "sg:address":"1438 Druid Rd S",
    "sg:city":"Clearwater",
    "sg:classifiers":[
        {
            "category":"Building & Trades",
            "subcategory":"Construction",
            "type":"Services"
        }
    ],
    "sg:phone":"+1 727 443 5302",
    "sg:postcode":"33756",
    "sg:province":"FL",
    "sg:tags":[
        "masonry",
        "contractor"
    ],
    "wof:name":"Richard Johnson Masonry",
    "wof:placetype":"venue"
},
  "geometry": {"coordinates":[-82.805859,27.946898],"type":"Point"}
}