{
  "type": "Feature",
  "properties": {
    "iso:country":"US",
    "sg:address":"4370 Oakes Rd",
    "sg:city":"Davie",
    "sg:classifiers":[
        {
            "category":"Building & Trades",
            "subcategory":"Construction",
            "type":"Services"
        }
    ],
    "sg:phone":"+1 954 224 9689",
    "sg:postcode":"33314",
    "sg:province":"FL",
    "sg:tags":[
        "carpet",
        "installation",
        "floor",
        "laying",
        "contractor"
    ],
    "wof:name":"Joe Turk Specialty Installation",
    "wof:placetype":"venue"
},
  "geometry": {"coordinates":[-80.206202,26.07557],"type":"Point"}
}