{
  "type": "Feature",
  "properties": {
    "iso:country":"US",
    "sg:address":"228 SW 83rd Way",
    "sg:city":"Hollywood",
    "sg:classifiers":[
        {
            "category":"Professional",
            "subcategory":"Business Services",
            "type":"Services"
        }
    ],
    "sg:phone":"+1 954 517 0801",
    "sg:postcode":"33025",
    "sg:province":"FL",
    "wof:name":"Coast To Coast Management Inc",
    "wof:placetype":"venue"
},
  "geometry": {"coordinates":[-80.25273799999999,26.008127],"type":"Point"}
}