{
  "type": "Feature",
  "properties": {
    "iso:country":"US",
    "sg:address":"1226 Cheetah Trl",
    "sg:city":"Winter Springs",
    "sg:classifiers":[
        {
            "category":"Wholesale",
            "subcategory":"Machinery & Supplies",
            "type":"Manufacturing & Wholesale Goods"
        }
    ],
    "sg:phone":"+1 407 699 4939",
    "sg:postcode":"32708",
    "sg:province":"FL",
    "sg:tags":[
        "equipment",
        "industrial"
    ],
    "wof:name":"Ingersoll-Rand",
    "wof:placetype":"venue"
},
  "geometry": {"coordinates":[-81.263531,28.678112],"type":"Point"}
}