{
  "type": "Feature",
  "properties": {
    "iso:country":"US",
    "sg:address":"3301 McLemore Dr",
    "sg:city":"Pensacola",
    "sg:classifiers":[
        {
            "category":"Building & Trades",
            "subcategory":"Construction",
            "type":"Services"
        },
        {
            "category":"Home & Garden",
            "subcategory":"Furniture",
            "type":"Retail Goods"
        }
    ],
    "sg:phone":"+1 850 477 1367",
    "sg:postcode":"32514",
    "sg:province":"FL",
    "sg:tags":[
        "cabinet",
        "carpentry",
        "contractor"
    ],
    "wof:name":"West Florida Finishing Inc",
    "wof:placetype":"venue"
},
  "geometry": {"coordinates":[-87.190072,30.520073],"type":"Point"}
}