{
  "type": "Feature",
  "properties": {
    "addr:full":"2441 Omaha Dr Deltona FL 32738",
    "addr:housenumber":"2441",
    "addr:postcode":"32738",
    "addr:street":"Omaha Dr",
    "iso:country":"US",
    "sg:address":"2441 Omaha Dr",
    "sg:city":"Deltona",
    "sg:classifiers":[
        {
            "category":"Wholesale",
            "subcategory":"Stationery",
            "type":"Manufacturing & Wholesale Goods"
        }
    ],
    "sg:phone":"+1 386 789 9559",
    "sg:postcode":"32738",
    "sg:province":"FL",
    "sg:tags":[
        "business",
        "form",
        "system"
    ],
    "wof:name":"Wilmer Service Line",
    "wof:placetype":"venue"
},
  "geometry": {"coordinates":[-81.200203,28.942252],"type":"Point"}
}