{
  "type": "Feature",
  "properties": {
    "addr:full":"5645 S University Dr Davie FL 33328",
    "addr:housenumber":"5645",
    "addr:postcode":"33328",
    "addr:street":"S University Dr",
    "iso:country":"US",
    "sg:address":"5645 S University Dr",
    "sg:city":"Davie",
    "sg:classifiers":[
        {
            "category":"Restaurant",
            "type":"Food & Drink"
        }
    ],
    "sg:phone":"+1 954 680 0608",
    "sg:postcode":"33328",
    "sg:province":"FL",
    "sg:tags":[
        "style",
        "family",
        "lunch",
        "american",
        "brunch",
        "breakfast"
    ],
    "sg:website":"http://www.dennys.com",
    "wof:name":"Denny's",
    "wof:placetype":"venue"
},
  "geometry": {"coordinates":[-80.251881,26.049984],"type":"Point"}
}