{
  "type": "Feature",
  "properties": {
    "iso:country":"US",
    "sg:address":"3501 S Tamiami Trl",
    "sg:city":"Sarasota",
    "sg:classifiers":[
        {
            "category":"Shopping",
            "subcategory":"Clothing, Apparel, & Fashions",
            "type":"Retail Goods"
        }
    ],
    "sg:phone":"+1 941 366 2001",
    "sg:postcode":"34239",
    "sg:province":"FL",
    "sg:tags":[
        "furnishing"
    ],
    "wof:name":"Express Mens",
    "wof:placetype":"venue"
},
  "geometry": {"coordinates":[-82.530362,27.30212],"type":"Point"}
}