{
  "type": "Feature",
  "properties": {
    "addr:full":"108 Colonia Ln E Nokomis FL 34275",
    "addr:housenumber":"108",
    "addr:postcode":"34275",
    "addr:street":"Colonia Ln E",
    "iso:country":"US",
    "sg:address":"108 Colonia Ln E",
    "sg:city":"Nokomis",
    "sg:classifiers":[
        {
            "category":"Wholesale",
            "subcategory":"Machinery & Supplies",
            "type":"Manufacturing & Wholesale Goods"
        }
    ],
    "sg:phone":"+1 941 488 1994",
    "sg:postcode":"34275",
    "sg:province":"FL",
    "sg:tags":[
        "equipment",
        "industrial"
    ],
    "wof:name":"Davis Material Handling Inc",
    "wof:placetype":"venue"
},
  "geometry": {"coordinates":[-82.44918699999999,27.115907],"type":"Point"}
}