{
  "type": "Feature",
  "properties": {
    "iso:country":"US",
    "sg:address":"801 Seminole Blvd",
    "sg:city":"Largo",
    "sg:classifiers":[
        {
            "category":"Place Of Worship",
            "subcategory":"Church",
            "type":"Public Place"
        },
        {
            "category":"Place Of Worship",
            "type":"Public Place"
        }
    ],
    "sg:phone":"+1 727 397 4707",
    "sg:postcode":"33770",
    "sg:province":"FL",
    "sg:tags":[
        "churches-interdenominational",
        "churches-baptist",
        "churches-community"
    ],
    "sg:website":"http://www.pathwayscc.com",
    "wof:name":"Pathways Community Church",
    "wof:placetype":"venue"
},
  "geometry": {"coordinates":[-82.787598,27.909309],"type":"Point"}
}