{
  "type": "Feature",
  "properties": {
    "iso:country":"US",
    "sg:address":"17850 SW 152nd Ave",
    "sg:city":"Miami",
    "sg:classifiers":[
        {
            "category":"Professional",
            "subcategory":"Advertising",
            "type":"Services"
        },
        {
            "category":"Professional",
            "subcategory":"Printing & Photocopies",
            "type":"Services"
        },
        {
            "category":"Manufacturing",
            "subcategory":"Signs",
            "type":"Manufacturing & Wholesale Goods"
        }
    ],
    "sg:phone":"+1 305 223 6900",
    "sg:postcode":"33187",
    "sg:province":"FL",
    "sg:tags":[
        "banners",
        "flag",
        "specialty",
        "pennant"
    ],
    "wof:name":"Quick Signs Of Miami",
    "wof:placetype":"venue"
},
  "geometry": {"coordinates":[-80.437935,25.601153],"type":"Point"}
}