{
  "type": "Feature",
  "properties": {
    "addr:full":"3770 S Tuttle Ave Sarasota FL 34239",
    "addr:housenumber":"3770",
    "addr:postcode":"34239",
    "addr:street":"S Tuttle Ave",
    "iso:country":"US",
    "sg:address":"3770 S Tuttle Ave",
    "sg:city":"Sarasota",
    "sg:classifiers":[
        {
            "category":"Home & Garden",
            "subcategory":"Garden Supply",
            "type":"Retail Goods"
        }
    ],
    "sg:phone":"+1 941 921 6242",
    "sg:postcode":"34239",
    "sg:province":"FL",
    "wof:name":"Franks Nursery & Crafts 254",
    "wof:placetype":"venue"
},
  "geometry": {"coordinates":[-82.51424299999999,27.299803],"type":"Point"}
}