{
  "type": "Feature",
  "properties": {
    "iso:country":"US",
    "sg:address":"4373 Pearl St",
    "sg:city":"Marianna",
    "sg:classifiers":[
        {
            "category":"Social Services",
            "subcategory":"Child Care",
            "type":"Services"
        }
    ],
    "sg:phone":"+1 850 482 7112",
    "sg:postcode":"32448",
    "sg:province":"FL",
    "sg:tags":[
        "day"
    ],
    "wof:name":"Play Pen Christian Lrng Ctr",
    "wof:placetype":"venue"
},
  "geometry": {"coordinates":[-85.233003,30.770248],"type":"Point"}
}