{
  "type": "Feature",
  "properties": {
    "iso:country":"US",
    "sg:address":"16740 Monteverde Dr",
    "sg:city":"Spring Hill",
    "sg:classifiers":[
        {
            "category":"Professional",
            "subcategory":"Computer Services",
            "type":"Services"
        }
    ],
    "sg:phone":"+1 727 856 3025",
    "sg:postcode":"34610",
    "sg:province":"FL",
    "sg:tags":[
        "related"
    ],
    "wof:name":"Catherine Dolan",
    "wof:placetype":"venue"
},
  "geometry": {"coordinates":[-82.54319,28.399813],"type":"Point"}
}