{
  "type": "Feature",
  "properties": {
    "iso:country":"US",
    "sg:address":"162 SE 17th Ter",
    "sg:city":"Cape Coral",
    "sg:classifiers":[
        {
            "category":"Freight",
            "type":"Transportation"
        }
    ],
    "sg:phone":"+1 239 772 1251",
    "sg:postcode":"33990",
    "sg:province":"FL",
    "sg:tags":[
        "operator",
        "local",
        "trucking"
    ],
    "wof:name":"Rfh Hauling Inc",
    "wof:placetype":"venue"
},
  "geometry": {"coordinates":[-81.97166799999999,26.620021],"type":"Point"}
}