{
  "type": "Feature",
  "properties": {
    "addr:full":"12249 NW 2nd Pl Pompano Beach FL 33071",
    "addr:housenumber":"12249",
    "addr:postcode":"33071",
    "addr:street":"Nw 2Nd Pl",
    "iso:country":"US",
    "sg:address":"12249 NW 2nd Pl",
    "sg:city":"Pompano Beach",
    "sg:classifiers":[
        {
            "category":"Building & Trades",
            "subcategory":"Construction",
            "type":"Services"
        }
    ],
    "sg:phone":"+1 954 344 8813",
    "sg:postcode":"33071",
    "sg:province":"FL",
    "sg:tags":[
        "nonresidential"
    ],
    "wof:name":"Shaun Licari",
    "wof:placetype":"venue"
},
  "geometry": {"coordinates":[-80.291155,26.232404],"type":"Point"}
}