{
  "type": "Feature",
  "properties": {
    "iso:country":"US",
    "sg:address":"737 Louden Ave",
    "sg:city":"Dunedin",
    "sg:classifiers":[
        {
            "category":"Government",
            "subcategory":"Office",
            "type":"Public Place"
        }
    ],
    "sg:phone":"+1 727 298 3194",
    "sg:postcode":"34698",
    "sg:province":"FL",
    "sg:tags":[
        "city",
        "planning",
        "dev"
    ],
    "wof:name":"Dunedin City Zoning",
    "wof:placetype":"venue"
},
  "geometry": {"coordinates":[-82.784662,28.012193],"type":"Point"}
}