{
  "type": "Feature",
  "properties": {
    "addr:full":"21 9th St S Saint Petersburg FL 33705",
    "addr:housenumber":"21",
    "addr:postcode":"33705",
    "addr:street":"9Th St S",
    "iso:country":"US",
    "sg:address":"21 9th St S",
    "sg:city":"Saint Petersburg",
    "sg:classifiers":[
        {
            "category":"Health Services",
            "subcategory":"Doctor",
            "type":"Services"
        }
    ],
    "sg:phone":"+1 727 898 8199",
    "sg:postcode":"33705",
    "sg:province":"FL",
    "sg:tags":[
        "medical"
    ],
    "wof:name":"Planned Parenthood of South",
    "wof:placetype":"venue"
},
  "geometry": {"coordinates":[-82.646737,27.770457],"type":"Point"}
}