{
  "type": "Feature",
  "properties": {
    "addr:full":"1974 US Hwy 1 S Saint Augustine FL 32086",
    "addr:housenumber":"1974",
    "addr:postcode":"32086",
    "addr:street":"Us Hwy 1 S",
    "iso:country":"US",
    "sg:address":"1974 US Hwy 1 S",
    "sg:city":"Saint Augustine",
    "sg:classifiers":[
        {
            "category":"Restaurant",
            "type":"Food & Drink"
        }
    ],
    "sg:phone":"+1 904 826 1533",
    "sg:postcode":"32086",
    "sg:province":"FL",
    "sg:tags":[
        "eating"
    ],
    "wof:name":"Peking South Chinese Rest",
    "wof:placetype":"venue"
},
  "geometry": {"coordinates":[-81.32298299999999,29.865054],"type":"Point"}
}