{
  "type": "Feature",
  "properties": {
    "iso:country":"US",
    "sg:address":"435 Old Dixie Hwy",
    "sg:city":"Vero Beach",
    "sg:classifiers":[
        {
            "category":"Building & Trades",
            "subcategory":"Construction",
            "type":"Services"
        }
    ],
    "sg:phone":"+1 772 794 0786",
    "sg:postcode":"32962",
    "sg:province":"FL",
    "sg:tags":[
        "handyman"
    ],
    "wof:name":"Action Management Complete",
    "wof:placetype":"venue"
},
  "geometry": {"coordinates":[-80.38873100000001,27.609118],"type":"Point"}
}