{
  "type": "Feature",
  "properties": {
    "addr:full":"14500 NE 6th Ave North Miami FL 33161",
    "addr:housenumber":"14500",
    "addr:postcode":"33161",
    "addr:street":"Ne 6Th Ave",
    "iso:country":"US",
    "sg:address":"14500 NE 6th Ave",
    "sg:city":"North Miami",
    "sg:classifiers":[
        {
            "category":"Education",
            "subcategory":"School",
            "type":"Public Place"
        }
    ],
    "sg:phone":"+1 305 949 0998",
    "sg:postcode":"33161",
    "sg:province":"FL",
    "sg:tags":[
        "high",
        "middle",
        "elementary"
    ],
    "wof:name":"Miami-Dade County Public Schools",
    "wof:placetype":"venue"
},
  "geometry": {"coordinates":[-80.187432,25.908512],"type":"Point"}
}