{
  "type": "Feature",
  "properties": {
    "addr:full":"2101 Pinellas Dr Punta Gorda FL 33983",
    "addr:housenumber":"2101",
    "addr:postcode":"33983",
    "addr:street":"Pinellas Dr",
    "iso:country":"US",
    "sg:address":"2101 Pinellas Dr",
    "sg:city":"Punta Gorda",
    "sg:classifiers":[
        {
            "category":"Building & Trades",
            "subcategory":"Plumbing",
            "type":"Services"
        }
    ],
    "sg:phone":"+1 941 629 4341",
    "sg:postcode":"33983",
    "sg:province":"FL",
    "sg:tags":[
        "contractor"
    ],
    "wof:name":"Scott Warram",
    "wof:placetype":"venue"
},
  "geometry": {"coordinates":[-81.999931,26.999566],"type":"Point"}
}