{
  "type": "Feature",
  "properties": {
    "addr:full":"2760 S Hopkins Ave Titusville FL 32780",
    "addr:housenumber":"2760",
    "addr:postcode":"32780",
    "addr:street":"S Hopkins Ave",
    "iso:country":"US",
    "sg:address":"2760 S Hopkins Ave",
    "sg:city":"Titusville",
    "sg:classifiers":[
        {
            "category":"Restaurant",
            "type":"Food & Drink"
        }
    ],
    "sg:menulink":"http://www.allmenus.com/fl/titusville/87307-little-caesars-pizza/menu/",
    "sg:phone":"+1 321 269 1500",
    "sg:postcode":"32780",
    "sg:province":"FL",
    "sg:tags":[
        "american",
        "pizza"
    ],
    "wof:name":"Little Caesar's Pizza",
    "wof:placetype":"venue"
},
  "geometry": {"coordinates":[-80.80569800000001,28.58391],"type":"Point"}
}