{
  "type": "Feature",
  "properties": {
    "iso:country":"US",
    "sg:address":"12800 Griffing Blvd",
    "sg:city":"Miami",
    "sg:classifiers":[
        {
            "category":"Real Estate",
            "subcategory":"Real Estate Agent",
            "type":"Services"
        }
    ],
    "sg:phone":"+1 305 893 9308",
    "sg:postcode":"33161",
    "sg:province":"FL",
    "wof:name":"North Miami Investments Inc",
    "wof:placetype":"venue"
},
  "geometry": {"coordinates":[-80.19381300000001,25.892676],"type":"Point"}
}