{
  "type": "Feature",
  "properties": {
    "addr:full":"5249 Brosche Rd Orlando FL 32807",
    "addr:housenumber":"5249",
    "addr:postcode":"32807",
    "addr:street":"Brosche Rd",
    "iso:country":"US",
    "sg:address":"5249 Brosche Rd",
    "sg:city":"Orlando",
    "sg:classifiers":[
        {
            "category":"Building & Trades",
            "subcategory":"Landscaping Services",
            "type":"Services"
        }
    ],
    "sg:phone":"+1 407 658 0099",
    "sg:postcode":"32807",
    "sg:province":"FL",
    "sg:tags":[
        "landscape"
    ],
    "wof:name":"Bates Landscaping & Maint",
    "wof:placetype":"venue"
},
  "geometry": {"coordinates":[-81.317453,28.546788],"type":"Point"}
}