{
  "type": "Feature",
  "properties": {
    "addr:full":"805 W 1st St Sanford FL 32771",
    "addr:housenumber":"805",
    "addr:postcode":"32771",
    "addr:street":"W 1St St",
    "iso:country":"US",
    "sg:address":"805 W 1st St",
    "sg:city":"Sanford",
    "sg:classifiers":[
        {
            "category":"Retail",
            "subcategory":"Repair Shop",
            "type":"Services"
        }
    ],
    "sg:phone":"+1 407 323 6593",
    "sg:postcode":"32771",
    "sg:province":"FL",
    "sg:tags":[
        "appliance"
    ],
    "wof:name":"Ace Appliance Sales & Svc",
    "wof:placetype":"venue"
},
  "geometry": {"coordinates":[-81.27624299999999,28.811593],"type":"Point"}
}