{
  "type": "Feature",
  "properties": {
    "iso:country":"US",
    "sg:address":"508 NE 190th St",
    "sg:city":"Miami",
    "sg:classifiers":[
        {
            "category":"Wholesale",
            "subcategory":"Drugs",
            "type":"Manufacturing & Wholesale Goods"
        }
    ],
    "sg:phone":"+1 305 654 8015",
    "sg:postcode":"33179",
    "sg:province":"FL",
    "sg:tags":[
        "perfume"
    ],
    "wof:name":"Fragrance Outlet",
    "wof:placetype":"venue"
},
  "geometry": {"coordinates":[-80.18944,25.949525],"type":"Point"}
}