{
  "type": "Feature",
  "properties": {
    "addr:full":"130 Professional Dr Ponte Vedra Bch FL 32082",
    "addr:housenumber":"130",
    "addr:postcode":"32082",
    "addr:street":"Professional Dr",
    "iso:country":"US",
    "sg:address":"130 Professional Dr",
    "sg:city":"Ponte Vedra Bch",
    "sg:classifiers":[
        {
            "category":"Health Services",
            "subcategory":"Doctor",
            "type":"Services"
        }
    ],
    "sg:phone":"+1 904 285 1113",
    "sg:postcode":"32082",
    "sg:province":"FL",
    "sg:tags":[
        "physician",
        "surgeon",
        "medical"
    ],
    "wof:name":"Arthritic Diseases Clinic",
    "wof:placetype":"venue"
},
  "geometry": {"coordinates":[-81.389155,30.249773],"type":"Point"}
}