{
  "type": "Feature",
  "properties": {
    "addr:full":"911 E Commercial Blvd Oakland Park FL 33334",
    "addr:housenumber":"911",
    "addr:postcode":"33334",
    "addr:street":"E Commercial Blvd",
    "iso:country":"US",
    "sg:address":"911 E Commercial Blvd",
    "sg:city":"Oakland Park",
    "sg:classifiers":[
        {
            "category":"Restaurant",
            "type":"Food & Drink"
        }
    ],
    "sg:phone":"+1 954 771 7114",
    "sg:postcode":"33334",
    "sg:province":"FL",
    "wof:name":"Denny's",
    "wof:placetype":"venue"
},
  "geometry": {"coordinates":[-80.134275,26.188904],"type":"Point"}
}