{
  "type": "Feature",
  "properties": {
    "addr:full":"14878 Bonnybridge Dr Orlando FL 32826",
    "addr:housenumber":"14878",
    "addr:postcode":"32826",
    "addr:street":"Bonnybridge Dr",
    "iso:country":"US",
    "sg:address":"14878 Bonnybridge Dr",
    "sg:city":"Orlando",
    "sg:classifiers":[
        {
            "category":"Professional",
            "type":"Services"
        }
    ],
    "sg:phone":"+1 407 737 2666",
    "sg:postcode":"32826",
    "sg:province":"FL",
    "sg:tags":[
        "establishment"
    ],
    "wof:name":"Artse' Attic",
    "wof:placetype":"venue"
},
  "geometry": {"coordinates":[-81.17666,28.606989],"type":"Point"}
}