{
  "type": "Feature",
  "properties": {
    "addr:full":"10452 Autumn Glen Ct Orlando FL 32836",
    "addr:housenumber":"10452",
    "addr:postcode":"32836",
    "addr:street":"Autumn Glen Ct",
    "iso:country":"US",
    "sg:address":"10452 Autumn Glen Ct",
    "sg:city":"Orlando",
    "sg:classifiers":[
        {
            "category":"Health Services",
            "subcategory":"Clinic",
            "type":"Services"
        }
    ],
    "sg:phone":"+1 407 351 2164",
    "sg:postcode":"32836",
    "sg:province":"FL",
    "wof:name":"Metabolic Momentum",
    "wof:placetype":"venue"
},
  "geometry": {"coordinates":[-81.499808,28.416288],"type":"Point"}
}