{
  "type": "Feature",
  "properties": {
    "iso:country":"US",
    "sg:address":"517 Bayberry Dr",
    "sg:city":"West Palm Beach",
    "sg:classifiers":[
        {
            "category":"Professional",
            "subcategory":"Management & Consulting",
            "type":"Services"
        }
    ],
    "sg:phone":"+1 561 694 0600",
    "sg:postcode":"33403",
    "sg:province":"FL",
    "sg:tags":[
        "consultant",
        "educational"
    ],
    "wof:name":"Educational Resources Inc",
    "wof:placetype":"venue"
},
  "geometry": {"coordinates":[-80.064483,26.79388],"type":"Point"}
}