{
  "type": "Feature",
  "properties": {
    "addr:full":"1017 S State Rd 7 Fort Lauderdale FL 33317",
    "addr:housenumber":"1017",
    "addr:postcode":"33317",
    "addr:street":"S State Rd 7",
    "iso:country":"US",
    "sg:address":"1017 S State Rd 7",
    "sg:city":"Fort Lauderdale",
    "sg:classifiers":[
        {
            "category":"Autos & Motor Vehicles",
            "subcategory":"Automobile Sales",
            "type":"Retail Goods"
        }
    ],
    "sg:phone":"+1 954 791 8947",
    "sg:postcode":"33317",
    "sg:province":"FL",
    "sg:tags":[
        "used"
    ],
    "wof:name":"Hamid Export Inc",
    "wof:placetype":"venue"
},
  "geometry": {"coordinates":[-80.20161899999999,26.110368],"type":"Point"}
}