{
  "type": "Feature",
  "properties": {
    "addr:full":"14511 SW 115th Ter Miami FL 33186",
    "addr:housenumber":"14511",
    "addr:postcode":"33186",
    "addr:street":"Sw 115Th Ter",
    "iso:country":"US",
    "sg:address":"14511 SW 115th Ter",
    "sg:city":"Miami",
    "sg:classifiers":[
        {
            "category":"Building & Trades",
            "subcategory":"Cleaning & Sanitation",
            "type":"Services"
        }
    ],
    "sg:phone":"+1 305 382 1146",
    "sg:postcode":"33186",
    "sg:province":"FL",
    "sg:tags":[
        "janitor"
    ],
    "wof:name":"Dinora Andreu Cleaning Svc",
    "wof:placetype":"venue"
},
  "geometry": {"coordinates":[-80.430677,25.659626],"type":"Point"}
}