{
  "type": "Feature",
  "properties": {
    "iso:country":"US",
    "sg:address":"8300 NE 1st Pl",
    "sg:city":"Miami",
    "sg:classifiers":[
        {
            "category":"Real Estate",
            "subcategory":"Real Estate Services",
            "type":"Services"
        }
    ],
    "sg:phone":"+1 305 455 2760",
    "sg:postcode":"33138",
    "sg:province":"FL",
    "sg:tags":[
        "apartment",
        "rental",
        "finder"
    ],
    "wof:name":"Pinnacle Square",
    "wof:placetype":"venue"
},
  "geometry": {"coordinates":[-80.19381,25.85149],"type":"Point"}
}