{
  "type": "Feature",
  "properties": {
    "addr:full":"601 US Hwy 41 Ruskin FL 33570",
    "addr:housenumber":"601",
    "addr:postcode":"33570",
    "addr:street":"Us Hwy 41",
    "iso:country":"US",
    "sg:address":"601 US Hwy 41",
    "sg:city":"Ruskin",
    "sg:classifiers":[
        {
            "category":"Food & Beverages",
            "subcategory":"Groceries & Convenience Stores",
            "type":"Retail Goods"
        }
    ],
    "sg:phone":"+1 813 641 1895",
    "sg:postcode":"33570",
    "sg:province":"FL",
    "sg:tags":[
        "grocer"
    ],
    "wof:name":"Save A Penny",
    "wof:placetype":"venue"
},
  "geometry": {"coordinates":[-82.43411999999999,27.714143],"type":"Point"}
}