{
  "type": "Feature",
  "properties": {
    "addr:full":"2076 Sunnydale Blvd Clearwater FL 33765",
    "addr:housenumber":"2076",
    "addr:postcode":"33765",
    "addr:street":"Sunnydale Blvd",
    "iso:country":"US",
    "sg:address":"2076 Sunnydale Blvd",
    "sg:city":"Clearwater",
    "sg:classifiers":[
        {
            "category":"Wholesale",
            "subcategory":"Groceries",
            "type":"Manufacturing & Wholesale Goods"
        }
    ],
    "sg:phone":"+1 727 450 1061",
    "sg:postcode":"33765",
    "sg:province":"FL",
    "sg:tags":[
        "food",
        "product",
        "health"
    ],
    "wof:name":"Renew Life Products",
    "wof:placetype":"venue"
},
  "geometry": {"coordinates":[-82.75466299999999,27.987078],"type":"Point"}
}