{
  "type": "Feature",
  "properties": {
    "iso:country":"US",
    "sg:address":"2210 NW 192nd Ter",
    "sg:city":"Miami Gardens",
    "sg:classifiers":[
        {
            "category":"Education",
            "subcategory":"Special Training",
            "type":"Public Place"
        }
    ],
    "sg:phone":"+1 305 628 3664",
    "sg:postcode":"33056",
    "sg:province":"FL",
    "sg:tags":[
        "tutoring"
    ],
    "wof:name":"Speak Easy Tutors",
    "wof:placetype":"venue"
},
  "geometry": {"coordinates":[-80.238198,25.949774],"type":"Point"}
}