{
  "type": "Feature",
  "properties": {
    "iso:country":"US",
    "sg:address":"316 Main St",
    "sg:city":"Dunedin",
    "sg:classifiers":[
        {
            "category":"Shopping",
            "subcategory":"Florist",
            "type":"Retail Goods"
        }
    ],
    "sg:phone":"+1 727 733 4196",
    "sg:postcode":"34698",
    "sg:province":"FL",
    "wof:name":"Allens Florist Inc",
    "wof:placetype":"venue"
},
  "geometry": {"coordinates":[-82.789013,28.012015],"type":"Point"}
}