{
  "type": "Feature",
  "properties": {
    "addr:full":"10555 W Hwy 40 Ocala FL 34482",
    "addr:housenumber":"10555",
    "addr:postcode":"34482",
    "addr:street":"W Hwy 40",
    "iso:country":"US",
    "sg:address":"10555 W Hwy 40",
    "sg:city":"Ocala",
    "sg:classifiers":[
        {
            "category":"Farming",
            "subcategory":"Livestock Farm",
            "type":"Manufacturing & Wholesale Goods"
        },
        {
            "category":"Retail",
            "subcategory":"Animal Services",
            "type":"Services"
        }
    ],
    "sg:phone":"+1 352 854 7862",
    "sg:postcode":"34482",
    "sg:province":"FL",
    "sg:tags":[
        "training",
        "horse",
        "equine"
    ],
    "wof:name":"Mc Duffee Quarter Horses",
    "wof:placetype":"venue"
},
  "geometry": {"coordinates":[-82.29311,29.187087],"type":"Point"}
}