{
  "type": "Feature",
  "properties": {
    "addr:full":"1534 Licht St Cocoa FL 32922",
    "addr:housenumber":"1534",
    "addr:postcode":"32922",
    "addr:street":"Licht St",
    "iso:country":"US",
    "sg:address":"1534 Licht St",
    "sg:city":"Cocoa",
    "sg:classifiers":[
        {
            "category":"Personal",
            "type":"Services"
        }
    ],
    "sg:phone":"+1 321 863 5390",
    "sg:postcode":"32922",
    "sg:province":"FL",
    "wof:name":"Charles G Albright Jr",
    "wof:placetype":"venue"
},
  "geometry": {"coordinates":[-80.752621,28.380861],"type":"Point"}
}