{
  "type": "Feature",
  "properties": {
    "iso:country":"US",
    "sg:address":"2700 State Hwy 16",
    "sg:city":"Saint Augustine",
    "sg:classifiers":[
        {
            "category":"Shopping",
            "subcategory":"Clothing, Apparel, & Fashions",
            "type":"Retail Goods"
        }
    ],
    "sg:phone":"+1 904 826 1323",
    "sg:postcode":"32092",
    "sg:province":"FL",
    "wof:name":"David Brooks Outlet",
    "wof:placetype":"venue"
},
  "geometry": {"coordinates":[-81.414827,29.918839],"type":"Point"}
}