{
  "type": "Feature",
  "properties": {
    "addr:full":"1419 37th St S Saint Petersburg FL 33711",
    "addr:housenumber":"1419",
    "addr:postcode":"33711",
    "addr:street":"37Th St S",
    "iso:country":"US",
    "sg:address":"1419 37th St S",
    "sg:city":"Saint Petersburg",
    "sg:classifiers":[
        {
            "category":"Shopping",
            "type":"Retail Goods"
        }
    ],
    "sg:phone":"+1 727 327 0522",
    "sg:postcode":"33711",
    "sg:province":"FL",
    "sg:tags":[
        "merchandise"
    ],
    "wof:name":"Constance Hills",
    "wof:placetype":"venue"
},
  "geometry": {"coordinates":[-82.683542,27.755725],"type":"Point"}
}