{
  "type": "Feature",
  "properties": {
    "iso:country":"US",
    "sg:address":"1710 S Combee Rd",
    "sg:city":"Lakeland",
    "sg:classifiers":[
        {
            "category":"Shopping",
            "subcategory":"Jewelry",
            "type":"Retail Goods"
        }
    ],
    "sg:phone":"+1 863 665 7395",
    "sg:postcode":"33801",
    "sg:province":"FL",
    "sg:tags":[
        "jeweler"
    ],
    "wof:name":"South Combee Resale",
    "wof:placetype":"venue"
},
  "geometry": {"coordinates":[-81.907736,28.022207],"type":"Point"}
}