{
  "type": "Feature",
  "properties": {
    "iso:country":"US",
    "sg:address":"1857 Wells Rd",
    "sg:city":"Orange Park",
    "sg:classifiers":[
        {
            "category":"Building & Trades",
            "subcategory":"Construction",
            "type":"Services"
        }
    ],
    "sg:phone":"+1 904 215 5885",
    "sg:postcode":"32073",
    "sg:province":"FL",
    "sg:tags":[
        "utility"
    ],
    "wof:name":"Peters Utilities LLC",
    "wof:placetype":"venue"
},
  "geometry": {"coordinates":[-81.732474,30.186994],"type":"Point"}
}