{
  "type": "Feature",
  "properties": {
    "iso:country":"US",
    "sg:address":"4335 Olive Ave",
    "sg:city":"Sarasota",
    "sg:classifiers":[
        {
            "category":"Professional",
            "subcategory":"Accounting & Tax Preparation",
            "type":"Services"
        }
    ],
    "sg:phone":"+1 941 927 9415",
    "sg:postcode":"34231",
    "sg:province":"FL",
    "sg:tags":[
        "accountant"
    ],
    "wof:name":"West Coast Tax & Consulting",
    "wof:placetype":"venue"
},
  "geometry": {"coordinates":[-82.50683600000001,27.295141],"type":"Point"}
}