{
  "type": "Feature",
  "properties": {
    "addr:full":"51 Menendez Rd Saint Augustine FL 32080",
    "addr:housenumber":"51",
    "addr:postcode":"32080",
    "addr:street":"Menendez Rd",
    "iso:country":"US",
    "sg:address":"51 Menendez Rd",
    "sg:city":"Saint Augustine",
    "sg:classifiers":[
        {
            "category":"Real Estate",
            "subcategory":"Real Estate Agent",
            "type":"Services"
        }
    ],
    "sg:phone":"+1 904 819 0139",
    "sg:postcode":"32080",
    "sg:province":"FL",
    "wof:name":"Ashley B Casey Inc",
    "wof:placetype":"venue"
},
  "geometry": {"coordinates":[-81.29415899999999,29.886561],"type":"Point"}
}