{
  "type": "Feature",
  "properties": {
    "iso:country":"US",
    "sg:address":"10191 SW 137th Ct",
    "sg:city":"Miami",
    "sg:classifiers":[
        {
            "category":"Professional",
            "subcategory":"Detective & Security Services",
            "type":"Services"
        },
        {
            "category":"Manufacturing",
            "subcategory":"Electronics",
            "type":"Manufacturing & Wholesale Goods"
        }
    ],
    "sg:phone":"+1 305 383 2299",
    "sg:postcode":"33186",
    "sg:province":"FL",
    "sg:tags":[
        "control",
        "equipment-wholesale",
        "monitoring",
        "system",
        "manufacturer"
    ],
    "wof:name":"Sonerik Security",
    "wof:placetype":"venue"
},
  "geometry": {"coordinates":[-80.41764000000001,25.673234],"type":"Point"}
}