{
  "type": "Feature",
  "properties": {
    "iso:country":"US",
    "sg:address":"6447 Miami Lakes Dr E Ste 222E",
    "sg:city":"Hialeah",
    "sg:classifiers":[
        {
            "category":"Health Services",
            "subcategory":"Clinic",
            "type":"Services"
        },
        {
            "category":"Organizations",
            "subcategory":"Non-profit Organization",
            "type":"Services"
        }
    ],
    "sg:phone":"+1 305 825 4081",
    "sg:postcode":"33014",
    "sg:province":"FL",
    "sg:tags":[
        "community",
        "service/non-profit",
        "welfare"
    ],
    "wof:name":"Florida Breast Health Initiative",
    "wof:placetype":"venue"
},
  "geometry": {"coordinates":[-80.30522000000001,25.911314],"type":"Point"}
}