{
  "type": "Feature",
  "properties": {
    "addr:full":"723 E Wade St Trenton FL 32693",
    "addr:housenumber":"723",
    "addr:postcode":"32693",
    "addr:street":"E Wade St",
    "iso:country":"US",
    "sg:address":"723 E Wade St",
    "sg:city":"Trenton",
    "sg:classifiers":[
        {
            "category":"Banks & Credit Unions",
            "subcategory":"Bank",
            "type":"Services"
        }
    ],
    "sg:phone":"+1 352 463 1313",
    "sg:postcode":"32693",
    "sg:province":"FL",
    "sg:tags":[
        "loan",
        "real estate"
    ],
    "wof:name":"Primary Residential Mortgage",
    "wof:placetype":"venue"
},
  "geometry": {"coordinates":[-82.811032,29.61349],"type":"Point"}
}