{
  "type": "Feature",
  "properties": {
    "addr:full":"6210 Cleveland St Hollywood FL 33024",
    "addr:housenumber":"6210",
    "addr:postcode":"33024",
    "addr:street":"Cleveland St",
    "iso:country":"US",
    "sg:address":"6210 Cleveland St",
    "sg:city":"Hollywood",
    "sg:classifiers":[
        {
            "category":"Health Services",
            "subcategory":"Nursing And Care Facility",
            "type":"Services"
        },
        {
            "category":"Social Services",
            "subcategory":"Adult Care",
            "type":"Services"
        }
    ],
    "sg:phone":"+1 954 983 5174",
    "sg:postcode":"33024",
    "sg:province":"FL",
    "sg:tags":[
        "living",
        "life",
        "retirement",
        "assisted",
        "community",
        "elder",
        "bureau",
        "homes-information"
    ],
    "wof:name":"Serenity Gardens Retireme",
    "wof:placetype":"venue"
},
  "geometry": {"coordinates":[-80.21231,26.022096],"type":"Point"}
}