{
  "type": "Feature",
  "properties": {
    "addr:full":"3119 SW Martin Downs Blvd Palm City FL 34990",
    "addr:housenumber":"3119",
    "addr:postcode":"34990",
    "addr:street":"Sw Martin Downs Blvd",
    "iso:country":"US",
    "sg:address":"3119 SW Martin Downs Blvd",
    "sg:city":"Palm City",
    "sg:classifiers":[
        {
            "category":"Insurance",
            "subcategory":"Insurance Agent",
            "type":"Services"
        }
    ],
    "sg:phone":"+1 772 220 3399",
    "sg:postcode":"34990",
    "sg:province":"FL",
    "wof:name":"Allstate Insurance",
    "wof:placetype":"venue"
},
  "geometry": {"coordinates":[-80.297061,27.17196],"type":"Point"}
}