{
  "type": "Feature",
  "properties": {
    "iso:country":"US",
    "sg:address":"733 E 9th St",
    "sg:city":"Hialeah",
    "sg:classifiers":[
        {
            "category":"Retail",
            "subcategory":"Pet Boarding",
            "type":"Services"
        }
    ],
    "sg:phone":"+1 305 884 3371",
    "sg:postcode":"33010",
    "sg:province":"FL",
    "sg:tags":[
        "boarding/pet",
        "sitting"
    ],
    "wof:name":"Happy Doggie Inc",
    "wof:placetype":"venue"
},
  "geometry": {"coordinates":[-80.26699499999999,25.830477],"type":"Point"}
}