{
  "type": "Feature",
  "properties": {
    "addr:full":"19651 Bruce B Downs Blvd Tampa FL 33647",
    "addr:housenumber":"19651",
    "addr:postcode":"33647",
    "addr:street":"Bruce B Downs Blvd",
    "iso:country":"US",
    "sg:address":"19651 Bruce B Downs Blvd",
    "sg:city":"Tampa",
    "sg:classifiers":[
        {
            "category":"Personal",
            "subcategory":"Beauty Salon",
            "type":"Services"
        }
    ],
    "sg:phone":"+1 813 973 8819",
    "sg:postcode":"33647",
    "sg:province":"FL",
    "sg:tags":[
        "shop"
    ],
    "wof:name":"Mane Stop",
    "wof:placetype":"venue"
},
  "geometry": {"coordinates":[-82.353217,28.15333],"type":"Point"}
}