{
  "type": "Feature",
  "properties": {
    "iso:country":"US",
    "sg:address":"339 N Ridgewood Dr",
    "sg:city":"Sebring",
    "sg:classifiers":[
        {
            "category":"Professional",
            "subcategory":"Research",
            "type":"Services"
        }
    ],
    "sg:phone":"+1 863 382 4046",
    "sg:postcode":"33870",
    "sg:province":"FL",
    "sg:tags":[
        "laboratory"
    ],
    "wof:name":"Imperial Testing Lab",
    "wof:placetype":"venue"
},
  "geometry": {"coordinates":[-81.440315,27.498182],"type":"Point"}
}