{
  "type": "Feature",
  "properties": {
    "addr:full":"4333 S 50th St Tampa FL 33619",
    "addr:housenumber":"4333",
    "addr:postcode":"33619",
    "addr:street":"S 50Th St",
    "iso:country":"US",
    "sg:address":"4333 S 50th St",
    "sg:city":"Tampa",
    "sg:classifiers":[
        {
            "category":"Mining & Drilling",
            "type":"Manufacturing & Wholesale Goods"
        }
    ],
    "sg:phone":"+1 813 248 1775",
    "sg:postcode":"33619",
    "sg:province":"FL",
    "sg:tags":[
        "field"
    ],
    "wof:name":"Oiltest",
    "wof:placetype":"venue"
},
  "geometry": {"coordinates":[-82.40193499999999,27.90749],"type":"Point"}
}