{
  "type": "Feature",
  "properties": {
    "iso:country":"US",
    "sg:address":"1885 S US Highway 17 92",
    "sg:city":"Longwood",
    "sg:classifiers":[
        {
            "category":"Personal",
            "subcategory":"Massage",
            "type":"Services"
        }
    ],
    "sg:phone":"+1 407 699 4400",
    "sg:postcode":"32750",
    "sg:province":"FL",
    "wof:name":"Tokyo Spa",
    "wof:placetype":"venue"
},
  "geometry": {"coordinates":[-81.33125,28.686199],"type":"Point"}
}