{
  "type": "Feature",
  "properties": {
    "iso:country":"US",
    "sg:address":"1100 NW 23rd St",
    "sg:city":"Miami",
    "sg:classifiers":[
        {
            "category":"Wholesale",
            "subcategory":"Groceries",
            "type":"Manufacturing & Wholesale Goods"
        }
    ],
    "sg:phone":"+1 305 635 9311",
    "sg:postcode":"33127",
    "sg:province":"FL",
    "sg:tags":[
        "food",
        "products-wholesale"
    ],
    "wof:name":"Independent Food Brokers Inc",
    "wof:placetype":"venue"
},
  "geometry": {"coordinates":[-80.213249,25.799021],"type":"Point"}
}