{
  "type": "Feature",
  "properties": {
    "iso:country":"US",
    "sg:address":"1172 Dixie Hwy",
    "sg:city":"Miami",
    "sg:classifiers":[
        {
            "category":"Manufacturing",
            "subcategory":"Tools & Machinery",
            "type":"Manufacturing & Wholesale Goods"
        }
    ],
    "sg:phone":"+1 786 261 3880",
    "sg:postcode":"33146",
    "sg:province":"FL",
    "sg:tags":[
        "sound",
        "lighting"
    ],
    "wof:name":"Gigs Up Inc",
    "wof:placetype":"venue"
},
  "geometry": {"coordinates":[-80.275719,25.715414],"type":"Point"}
}