{
  "type": "Feature",
  "properties": {
    "iso:country":"US",
    "sg:address":"2519 Keystone Dr",
    "sg:city":"Orlando",
    "sg:classifiers":[
        {
            "category":"Building & Trades",
            "subcategory":"Landscaping Services",
            "type":"Services"
        }
    ],
    "sg:phone":"+1 407 481 8324",
    "sg:postcode":"32806",
    "sg:province":"FL",
    "sg:tags":[
        "tree"
    ],
    "wof:name":"Charles T Bailey Tree Svc",
    "wof:placetype":"venue"
},
  "geometry": {"coordinates":[-81.365953,28.51328],"type":"Point"}
}