{
  "type": "Feature",
  "properties": {
    "addr:full":"10075 Gate Pkwy N Jacksonville FL 32246",
    "addr:housenumber":"10075",
    "addr:postcode":"32246",
    "addr:street":"Gate Pkwy N",
    "iso:country":"US",
    "sg:address":"10075 Gate Pkwy N",
    "sg:city":"Jacksonville",
    "sg:classifiers":[
        {
            "category":"Professional",
            "type":"Services"
        }
    ],
    "sg:phone":"+1 904 997 8899",
    "sg:postcode":"32246",
    "sg:province":"FL",
    "sg:tags":[
        "establishment"
    ],
    "wof:name":"Dartalia Inc",
    "wof:placetype":"venue"
},
  "geometry": {"coordinates":[-81.53612800000001,30.252143],"type":"Point"}
}