{
  "type": "Feature",
  "properties": {
    "iso:country":"US",
    "sg:address":"1401 SW 21st St",
    "sg:city":"Miami",
    "sg:classifiers":[
        {
            "category":"Organizations",
            "subcategory":"Professional Association",
            "type":"Services"
        }
    ],
    "sg:phone":"+1 305 860 9716",
    "sg:postcode":"33145",
    "sg:province":"FL",
    "sg:tags":[
        "agency",
        "bureau",
        "entertainment"
    ],
    "wof:name":"Rafols Morales Enterprises Inc",
    "wof:placetype":"venue"
},
  "geometry": {"coordinates":[-80.218391,25.75234],"type":"Point"}
}