{
  "type": "Feature",
  "properties": {
    "iso:country":"US",
    "sg:address":"250 NE 33rd St",
    "sg:city":"Fort Lauderdale",
    "sg:classifiers":[
        {
            "category":"Social Services",
            "subcategory":"Child Care",
            "type":"Services"
        }
    ],
    "sg:phone":"+1 954 561 6275",
    "sg:postcode":"33334",
    "sg:province":"FL",
    "sg:tags":[
        "day"
    ],
    "wof:name":"Public Svc Tiny Tot Kollege",
    "wof:placetype":"venue"
},
  "geometry": {"coordinates":[-80.144161,26.168846],"type":"Point"}
}