{
  "type": "Feature",
  "properties": {
    "iso:country":"US",
    "sg:address":"5465 80th Avenue Cir E",
    "sg:city":"Palmetto",
    "sg:classifiers":[
        {
            "category":"Shopping",
            "subcategory":"Gifts & Souvenirs",
            "type":"Retail Goods"
        }
    ],
    "sg:phone":"+1 941 722 0013",
    "sg:postcode":"34221",
    "sg:province":"FL",
    "wof:name":"Our Countree House",
    "wof:placetype":"venue"
},
  "geometry": {"coordinates":[-82.48286299999999,27.562332],"type":"Point"}
}