{
  "type": "Feature",
  "properties": {
    "addr:full":"311 E Sunset St Groveland FL 34736",
    "addr:housenumber":"311",
    "addr:postcode":"34736",
    "addr:street":"E Sunset St",
    "iso:country":"US",
    "sg:address":"311 E Sunset St",
    "sg:city":"Groveland",
    "sg:classifiers":[
        {
            "category":"Freight",
            "type":"Transportation"
        }
    ],
    "sg:phone":"+1 321 436 8389",
    "sg:postcode":"34736",
    "sg:province":"FL",
    "sg:tags":[
        "operator",
        "local",
        "trucking"
    ],
    "wof:name":"Won By One Express Delivery",
    "wof:placetype":"venue"
},
  "geometry": {"coordinates":[-81.85827999999999,28.55193],"type":"Point"}
}