{
  "type": "Feature",
  "properties": {
    "iso:country":"US",
    "sg:address":"3321 Ivy Way",
    "sg:city":"Hollywood",
    "sg:classifiers":[
        {
            "category":"Shopping",
            "subcategory":"Florist",
            "type":"Retail Goods"
        }
    ],
    "sg:phone":"+1 954 392 1819",
    "sg:postcode":"33025",
    "sg:province":"FL",
    "wof:name":"Flowers & Fancier",
    "wof:placetype":"venue"
},
  "geometry": {"coordinates":[-80.276315,25.979375],"type":"Point"}
}