{
  "type": "Feature",
  "properties": {
    "iso:country":"US",
    "sg:address":"2590 Pine Ridge Rd",
    "sg:city":"Tallahassee",
    "sg:classifiers":[
        {
            "category":"Health Services",
            "subcategory":"Doctor",
            "type":"Services"
        }
    ],
    "sg:phone":"+1 850 222 5985",
    "sg:postcode":"32308",
    "sg:province":"FL",
    "sg:tags":[
        "dentist"
    ],
    "wof:name":"Orthodontic Lab Inc",
    "wof:placetype":"venue"
},
  "geometry": {"coordinates":[-84.223375,30.497194],"type":"Point"}
}