{
  "type": "Feature",
  "properties": {
    "iso:country":"US",
    "sg:address":"1464 Trune Way",
    "sg:city":"Venice",
    "sg:classifiers":[
        {
            "category":"Utilities",
            "subcategory":"Refuse",
            "type":"Services"
        }
    ],
    "sg:phone":"+1 941 484 9930",
    "sg:postcode":"34292",
    "sg:province":"FL",
    "sg:tags":[
        "truck",
        "dump"
    ],
    "wof:name":"Petro Enterprises Inc",
    "wof:placetype":"venue"
},
  "geometry": {"coordinates":[-82.403705,27.126353],"type":"Point"}
}