{
  "type": "Feature",
  "properties": {
    "iso:country":"US",
    "sg:address":"1627 SW 13th St",
    "sg:city":"Miami",
    "sg:classifiers":[
        {
            "category":"Shopping",
            "type":"Retail Goods"
        }
    ],
    "sg:phone":"+1 305 649 5030",
    "sg:postcode":"33145",
    "sg:province":"FL",
    "sg:tags":[
        "merchandise"
    ],
    "wof:name":"Hoyos Humberto",
    "wof:placetype":"venue"
},
  "geometry": {"coordinates":[-80.221895,25.760984],"type":"Point"}
}