{
  "type": "Feature",
  "properties": {
    "addr:full":"4011 W Linebaugh Ave Tampa FL 33624",
    "addr:housenumber":"4011",
    "addr:postcode":"33624",
    "addr:street":"W Linebaugh Ave",
    "iso:country":"US",
    "sg:address":"4011 W Linebaugh Ave",
    "sg:city":"Tampa",
    "sg:classifiers":[
        {
            "category":"Autos & Motor Vehicles",
            "subcategory":"Auto Supplies",
            "type":"Retail Goods"
        }
    ],
    "sg:phone":"+1 813 514 8500",
    "sg:postcode":"33624",
    "sg:province":"FL",
    "sg:tags":[
        "tire"
    ],
    "wof:name":"Central Florida Wheel Distribution",
    "wof:placetype":"venue"
},
  "geometry": {"coordinates":[-82.509034,28.040171],"type":"Point"}
}