{
  "type": "Feature",
  "properties": {
    "iso:country":"US",
    "sg:address":"4464 Fowler St",
    "sg:city":"Fort Myers",
    "sg:classifiers":[
        {
            "category":"Food & Beverages",
            "subcategory":"Bakery",
            "type":"Retail Goods"
        }
    ],
    "sg:phone":"+1 239 275 0668",
    "sg:postcode":"33901",
    "sg:province":"FL",
    "sg:tags":[
        "sandwich"
    ],
    "sg:website":"www.quiznos.com",
    "wof:name":"Quiznos Sub 9378",
    "wof:placetype":"venue"
},
  "geometry": {"coordinates":[-81.862224,26.598249],"type":"Point"}
}