{
  "type": "Feature",
  "properties": {
    "addr:full":"4900 NW 167th St Hialeah FL 33014",
    "addr:housenumber":"4900",
    "addr:postcode":"33014",
    "addr:street":"Nw 167Th St",
    "iso:country":"US",
    "sg:address":"4900 NW 167th St",
    "sg:city":"Hialeah",
    "sg:classifiers":[
        {
            "category":"Home & Garden",
            "subcategory":"Furniture",
            "type":"Retail Goods"
        }
    ],
    "sg:phone":"+1 305 622 9550",
    "sg:postcode":"33014",
    "sg:province":"FL",
    "sg:tags":[
        "store"
    ],
    "sg:website":"http://www.rattanshack.com",
    "wof:name":"Rattan Shack",
    "wof:placetype":"venue"
},
  "geometry": {"coordinates":[-80.28071199999999,25.924863],"type":"Point"}
}