{
  "type": "Feature",
  "properties": {
    "iso:country":"US",
    "sg:address":"54 Conifer Cir",
    "sg:city":"Middleburg",
    "sg:classifiers":[
        {
            "category":"Building & Trades",
            "subcategory":"Construction",
            "type":"Services"
        }
    ],
    "sg:phone":"+1 904 282 4900",
    "sg:postcode":"32068",
    "sg:province":"FL",
    "sg:tags":[
        "siding",
        "contractor"
    ],
    "wof:name":"J & T Siding",
    "wof:placetype":"venue"
},
  "geometry": {"coordinates":[-81.94386299999999,30.118887],"type":"Point"}
}