{
  "type": "Feature",
  "properties": {
    "iso:country":"US",
    "sg:address":"2101 Kanner Hwy",
    "sg:city":"Stuart",
    "sg:classifiers":[
        {
            "category":"Manufacturing",
            "subcategory":"Printing",
            "type":"Manufacturing & Wholesale Goods"
        }
    ],
    "sg:phone":"+1 772 223 3550",
    "sg:postcode":"34994",
    "sg:province":"FL",
    "sg:tags":[
        "newspaper"
    ],
    "wof:name":"Coast Editions",
    "wof:placetype":"venue"
},
  "geometry": {"coordinates":[-80.253034,27.17844],"type":"Point"}
}