{
  "type": "Feature",
  "properties": {
    "iso:country":"US",
    "sg:address":"2510 33rd St S",
    "sg:city":"St Petersburg",
    "sg:classifiers":[
        {
            "category":"Travel",
            "subcategory":"Travel Agent",
            "type":"Entertainment"
        }
    ],
    "sg:phone":"+1 727 328 0933",
    "sg:postcode":"33712",
    "sg:province":"FL",
    "sg:tags":[
        "cruise"
    ],
    "wof:name":"Travel Lovers Tours & Cruises",
    "wof:placetype":"venue"
},
  "geometry": {"coordinates":[-82.678213,27.745723],"type":"Point"}
}