{
  "type": "Feature",
  "properties": {
    "iso:country":"US",
    "sg:address":"5519 W Colonial Dr",
    "sg:city":"Orlando",
    "sg:classifiers":[
        {
            "category":"Personal",
            "subcategory":"Beauty Salon",
            "type":"Services"
        }
    ],
    "sg:phone":"+1 407 578 5564",
    "sg:postcode":"32808",
    "sg:province":"FL",
    "sg:tags":[
        "shop"
    ],
    "wof:name":"Hollywood Barbers",
    "wof:placetype":"venue"
},
  "geometry": {"coordinates":[-81.455246,28.5525],"type":"Point"}
}