{
  "type": "Feature",
  "properties": {
    "addr:full":"3020 Forghun Ave SE Palm Bay FL 32909",
    "addr:housenumber":"3020",
    "addr:postcode":"32909",
    "addr:street":"Forghun Ave Se",
    "iso:country":"US",
    "sg:address":"3020 Forghun Ave SE",
    "sg:city":"Palm Bay",
    "sg:classifiers":[
        {
            "category":"Freight",
            "type":"Transportation"
        }
    ],
    "sg:phone":"+1 321 728 1816",
    "sg:postcode":"32909",
    "sg:province":"FL",
    "sg:tags":[
        "operator",
        "local",
        "trucking"
    ],
    "wof:name":"Tjs Transport Inc",
    "wof:placetype":"venue"
},
  "geometry": {"coordinates":[-80.66029899999999,27.91661],"type":"Point"}
}