{
  "type": "Feature",
  "properties": {
    "addr:full":"1202 Panferio Dr Gulf Breeze FL 32561",
    "addr:housenumber":"1202",
    "addr:postcode":"32561",
    "addr:street":"Panferio Dr",
    "iso:country":"US",
    "sg:address":"1202 Panferio Dr",
    "sg:city":"Gulf Breeze",
    "sg:classifiers":[
        {
            "category":"Professional",
            "type":"Services"
        }
    ],
    "sg:phone":"+1 850 934 8655",
    "sg:postcode":"32561",
    "sg:province":"FL",
    "wof:name":"Original Sophies LLC",
    "wof:placetype":"venue"
},
  "geometry": {"coordinates":[-87.10135099999999,30.341049],"type":"Point"}
}