{
  "type": "Feature",
  "properties": {
    "iso:country":"US",
    "sg:address":"80 NE 168th St",
    "sg:city":"North Miami Bch",
    "sg:classifiers":[
        {
            "category":"Professional",
            "subcategory":"Lawyer & Legal Services",
            "type":"Services"
        }
    ],
    "sg:phone":"+1 305 493 1351",
    "sg:postcode":"33162",
    "sg:province":"FL",
    "sg:tags":[
        "attorney"
    ],
    "wof:name":"Fisher Lawrence & Malove Pa",
    "wof:placetype":"venue"
},
  "geometry": {"coordinates":[-80.199833,25.928946],"type":"Point"}
}