{
  "type": "Feature",
  "properties": {
    "iso:country":"US",
    "sg:address":"15696 Iona Lakes Dr",
    "sg:city":"Fort Myers",
    "sg:classifiers":[
        {
            "category":"Professional",
            "subcategory":"Advertising",
            "type":"Services"
        }
    ],
    "sg:phone":"+1 239 565 5421",
    "sg:postcode":"33908",
    "sg:province":"FL",
    "sg:tags":[
        "distribution"
    ],
    "wof:name":"Lee Sexton Enterprises",
    "wof:placetype":"venue"
},
  "geometry": {"coordinates":[-81.96199,26.515913],"type":"Point"}
}