{
  "type": "Feature",
  "properties": {
    "iso:country":"US",
    "sg:address":"315 Tarpon Rd",
    "sg:city":"Mary Esther",
    "sg:classifiers":[
        {
            "category":"Building & Trades",
            "subcategory":"Construction",
            "type":"Services"
        }
    ],
    "sg:phone":"+1 850 581 7226",
    "sg:postcode":"32569",
    "sg:province":"FL",
    "sg:tags":[
        "house"
    ],
    "wof:name":"Seal & Sons",
    "wof:placetype":"venue"
},
  "geometry": {"coordinates":[-86.738703,30.409404],"type":"Point"}
}