{
  "type": "Feature",
  "properties": {
    "addr:full":"3458 Old Keystone Rd Tarpon Springs FL 34688",
    "addr:housenumber":"3458",
    "addr:postcode":"34688",
    "addr:street":"Old Keystone Rd",
    "iso:country":"US",
    "sg:address":"3458 Old Keystone Rd",
    "sg:city":"Tarpon Springs",
    "sg:classifiers":[
        {
            "category":"Building & Trades",
            "subcategory":"Plumbing",
            "type":"Services"
        }
    ],
    "sg:phone":"+1 727 943 7586",
    "sg:postcode":"34688",
    "sg:province":"FL",
    "sg:tags":[
        "plumbing",
        "contractor"
    ],
    "wof:name":"Flagship Plumbing Inc",
    "wof:placetype":"venue"
},
  "geometry": {"coordinates":[-82.68116499999999,28.148205],"type":"Point"}
}