{
  "type": "Feature",
  "properties": {
    "addr:full":"5401 Hancock Rd Southwest Rnchs FL 33330",
    "addr:housenumber":"5401",
    "addr:postcode":"33330",
    "addr:street":"Hancock Rd Southwest Rnchs",
    "iso:country":"US",
    "sg:address":"5401 Hancock Rd",
    "sg:city":"Southwest Rnchs",
    "sg:classifiers":[
        {
            "category":"Wholesale",
            "subcategory":"Farm Supplies",
            "type":"Manufacturing & Wholesale Goods"
        }
    ],
    "sg:phone":"+1 954 434 4937",
    "sg:postcode":"33330",
    "sg:province":"FL",
    "sg:tags":[
        "horse",
        "dealer"
    ],
    "wof:name":"Springwater Farm Inc",
    "wof:placetype":"venue"
},
  "geometry": {"coordinates":[-80.338003,26.056048],"type":"Point"}
}