{
  "type": "Feature",
  "properties": {
    "addr:full":"20911 Johnson St Pembroke Pines FL 33029",
    "addr:housenumber":"20911",
    "addr:postcode":"33029",
    "addr:street":"Johnson St",
    "iso:country":"US",
    "sg:address":"20911 Johnson St",
    "sg:city":"Pembroke Pines",
    "sg:classifiers":[
        {
            "category":"Arts & Performance",
            "subcategory":"Theater",
            "type":"Entertainment"
        }
    ],
    "sg:phone":"+1 954 438 3488",
    "sg:postcode":"33029",
    "sg:province":"FL",
    "sg:tags":[
        "bureau"
    ],
    "wof:name":"USH Entertainment Corp",
    "wof:placetype":"venue"
},
  "geometry": {"coordinates":[-80.432502,26.015162],"type":"Point"}
}