{
  "type": "Feature",
  "properties": {
    "addr:full":"4106 3rd St S Jacksonville Bch FL 32250",
    "addr:housenumber":"4106",
    "addr:postcode":"32250",
    "addr:street":"3Rd St S",
    "iso:country":"US",
    "sg:address":"4106 3rd St S",
    "sg:city":"Jacksonville Bch",
    "sg:classifiers":[
        {
            "category":"Restaurant",
            "type":"Food & Drink"
        }
    ],
    "sg:phone":"+1 904 247 0600",
    "sg:postcode":"32250",
    "sg:province":"FL",
    "sg:tags":[
        "eating"
    ],
    "sg:website":"www.hooters.com",
    "wof:name":"Hooters",
    "wof:placetype":"venue"
},
  "geometry": {"coordinates":[-81.387935,30.25777],"type":"Point"}
}