{
  "type": "Feature",
  "properties": {
    "iso:country":"US",
    "sg:address":"5200 N Dixie Hwy",
    "sg:city":"Boca Raton",
    "sg:classifiers":[
        {
            "category":"Real Estate",
            "subcategory":"Real Estate Agent",
            "type":"Services"
        }
    ],
    "sg:phone":"+1 561 994 0409",
    "sg:postcode":"33487",
    "sg:province":"FL",
    "sg:tags":[
        "investment"
    ],
    "wof:name":"Stoltz Management",
    "wof:placetype":"venue"
},
  "geometry": {"coordinates":[-80.07960300000001,26.39726],"type":"Point"}
}