{
  "type": "Feature",
  "properties": {
    "addr:full":"1871 SW 22nd St Coral Gables FL 33145",
    "addr:housenumber":"1871",
    "addr:postcode":"33145",
    "addr:street":"Sw 22Nd St",
    "iso:country":"US",
    "sg:address":"1871 SW 22nd St",
    "sg:city":"Coral Gables",
    "sg:classifiers":[
        {
            "category":"Health Services",
            "subcategory":"Doctor",
            "type":"Services"
        }
    ],
    "sg:phone":"+1 305 856 8060",
    "sg:postcode":"33145",
    "sg:province":"FL",
    "sg:tags":[
        "physician",
        "surgeon"
    ],
    "wof:name":"Mario A Delgado MD",
    "wof:placetype":"venue"
},
  "geometry": {"coordinates":[-80.224763,25.750865],"type":"Point"}
}