{
  "type": "Feature",
  "properties": {
    "iso:country":"US",
    "sg:address":"8200 Vineland Ave",
    "sg:city":"Orlando",
    "sg:classifiers":[
        {
            "category":"Shopping",
            "subcategory":"Gifts & Souvenirs",
            "type":"Retail Goods"
        }
    ],
    "sg:phone":"+1 407 238 1358",
    "sg:postcode":"32821",
    "sg:province":"FL",
    "wof:name":"Country Adventures LLC",
    "wof:placetype":"venue"
},
  "geometry": {"coordinates":[-81.49289,28.389257],"type":"Point"}
}