{
  "type": "Feature",
  "properties": {
    "addr:full":"5151 Clark Rd Sarasota FL 34233",
    "addr:housenumber":"5151",
    "addr:postcode":"34233",
    "addr:street":"Clark Rd",
    "iso:country":"US",
    "sg:address":"5151 Clark Rd",
    "sg:city":"Sarasota",
    "sg:classifiers":[
        {
            "category":"Autos & Motor Vehicles",
            "subcategory":"Automobile Sales",
            "type":"Retail Goods"
        }
    ],
    "sg:phone":"+1 941 923 2700",
    "sg:postcode":"34233",
    "sg:province":"FL",
    "sg:tags":[
        "new",
        "used"
    ],
    "wof:name":"Southpointe BMW",
    "wof:placetype":"venue"
},
  "geometry": {"coordinates":[-82.46930500000001,27.26923],"type":"Point"}
}