{
  "type": "Feature",
  "properties": {
    "addr:full":"47 S Palm Ave Sarasota FL 34236",
    "addr:housenumber":"47",
    "addr:postcode":"34236",
    "addr:street":"S Palm Ave",
    "iso:country":"US",
    "sg:address":"47 S Palm Ave",
    "sg:city":"Sarasota",
    "sg:classifiers":[
        {
            "category":"Personal",
            "type":"Services"
        }
    ],
    "sg:phone":"+1 941 356 7768",
    "sg:postcode":"34236",
    "sg:province":"FL",
    "sg:tags":[
        "therapist",
        "massage"
    ],
    "wof:name":"Aromatic Healing Experience",
    "wof:placetype":"venue"
},
  "geometry": {"coordinates":[-82.540567,27.331872],"type":"Point"}
}