{
  "type": "Feature",
  "properties": {
    "iso:country":"US",
    "sg:address":"3301 S Dale Mabry Hwy",
    "sg:city":"Tampa",
    "sg:classifiers":[
        {
            "category":"Restaurant",
            "type":"Food & Drink"
        }
    ],
    "sg:phone":"+1 813 831 2525",
    "sg:postcode":"33629",
    "sg:province":"FL",
    "sg:tags":[
        "eating"
    ],
    "wof:name":"El Fogon",
    "wof:placetype":"venue"
},
  "geometry": {"coordinates":[-82.506047,27.914796],"type":"Point"}
}