{
  "type": "Feature",
  "properties": {
    "iso:country":"US",
    "sg:address":"2232 NW 82nd Ave",
    "sg:city":"Miami",
    "sg:classifiers":[
        {
            "category":"Airline",
            "type":"Transportation"
        }
    ],
    "sg:phone":"+1 305 477 6715",
    "sg:postcode":"33122",
    "sg:province":"FL",
    "sg:tags":[
        "courier",
        "air"
    ],
    "wof:name":"Domesa Courier Corp",
    "wof:placetype":"venue"
},
  "geometry": {"coordinates":[-80.329018,25.795794],"type":"Point"}
}