{
  "type": "Feature",
  "properties": {
    "addr:full":"165 Water St Lake Helen FL 32744",
    "addr:housenumber":"165",
    "addr:postcode":"32744",
    "addr:street":"Water St",
    "iso:country":"US",
    "sg:address":"165 Water St",
    "sg:city":"Lake Helen",
    "sg:classifiers":[
        {
            "category":"Building & Trades",
            "subcategory":"Construction",
            "type":"Services"
        }
    ],
    "sg:phone":"+1 386 228 2682",
    "sg:postcode":"32744",
    "sg:province":"FL",
    "sg:tags":[
        "roofing",
        "contractor"
    ],
    "wof:name":"Joe Conti Roofing",
    "wof:placetype":"venue"
},
  "geometry": {"coordinates":[-81.232957,28.978288],"type":"Point"}
}