{
  "type": "Feature",
  "properties": {
    "iso:country":"US",
    "sg:address":"51 SW 1st Ave Ste 424",
    "sg:city":"Miami",
    "sg:classifiers":[
        {
            "category":"Professional",
            "subcategory":"Lawyer & Legal Services",
            "type":"Services"
        }
    ],
    "sg:phone":"+1 305 536 5206",
    "sg:postcode":"33130",
    "sg:province":"FL",
    "sg:tags":[
        "plan"
    ],
    "wof:name":"Miami Field Office",
    "wof:placetype":"venue"
},
  "geometry": {"coordinates":[-80.19554100000001,25.773304],"type":"Point"}
}