{
  "type": "Feature",
  "properties": {
    "iso:country":"US",
    "sg:address":"1712 94th Dr",
    "sg:city":"Vero Beach",
    "sg:classifiers":[
        {
            "category":"Shopping",
            "subcategory":"Clothing, Apparel, & Fashions",
            "type":"Retail Goods"
        }
    ],
    "sg:phone":"+1 772 978 7223",
    "sg:postcode":"32966",
    "sg:province":"FL",
    "wof:name":"Dooney & Bourke Factory Store",
    "wof:placetype":"venue"
},
  "geometry": {"coordinates":[-80.524512,27.635386],"type":"Point"}
}