{
  "type": "Feature",
  "properties": {
    "iso:country":"US",
    "sg:address":"440 W 20th St",
    "sg:city":"Hialeah",
    "sg:classifiers":[
        {
            "category":"Professional",
            "subcategory":"Business Services",
            "type":"Services"
        }
    ],
    "sg:phone":"+1 305 863 4149",
    "sg:postcode":"33010",
    "sg:province":"FL",
    "sg:tags":[
        "sewing",
        "sportswear",
        "contractor"
    ],
    "wof:name":"R B Apparel Inc",
    "wof:placetype":"venue"
},
  "geometry": {"coordinates":[-80.290907,25.839738],"type":"Point"}
}