{
  "type": "Feature",
  "properties": {
    "iso:country":"US",
    "sg:address":"6500 Bowden Rd",
    "sg:city":"Jacksonville",
    "sg:classifiers":[
        {
            "category":"Building & Trades",
            "subcategory":"Construction",
            "type":"Services"
        }
    ],
    "sg:phone":"+1 904 448 4005",
    "sg:postcode":"32216",
    "sg:province":"FL",
    "sg:tags":[
        "contractor"
    ],
    "wof:name":"Ivey Mechanical",
    "wof:placetype":"venue"
},
  "geometry": {"coordinates":[-81.592539,30.264184],"type":"Point"}
}