{
  "type": "Feature",
  "properties": {
    "iso:country":"US",
    "sg:address":"2626 Care Dr",
    "sg:city":"Tallahassee",
    "sg:classifiers":[
        {
            "category":"Health Services",
            "subcategory":"Doctor",
            "type":"Services"
        }
    ],
    "sg:phone":"+1 850 219 2306",
    "sg:postcode":"32308",
    "sg:province":"FL",
    "sg:tags":[
        "physician",
        "family",
        "practice",
        "surgeons",
        "medicine",
        "surgery-general"
    ],
    "sg:website":"http://www.capitalregionalhealthcare.com",
    "wof:name":"Capital Regional Surgical Associates",
    "wof:placetype":"venue"
},
  "geometry": {"coordinates":[-84.233313,30.476066],"type":"Point"}
}