{
  "type": "Feature",
  "properties": {
    "addr:full":"4205 Bruton Rd Plant City FL 33565",
    "addr:housenumber":"4205",
    "addr:postcode":"33565",
    "addr:street":"Bruton Rd",
    "iso:country":"US",
    "sg:address":"4205 Bruton Rd",
    "sg:city":"Plant City",
    "sg:classifiers":[
        {
            "category":"Wholesale",
            "subcategory":"Plants",
            "type":"Manufacturing & Wholesale Goods"
        }
    ],
    "sg:phone":"+1 813 752 4519",
    "sg:postcode":"33565",
    "sg:province":"FL",
    "sg:tags":[
        "item",
        "nursery"
    ],
    "wof:name":"Sun Scape Tree Farm Inc",
    "wof:placetype":"venue"
},
  "geometry": {"coordinates":[-82.175501,28.108909],"type":"Point"}
}