{
  "type": "Feature",
  "properties": {
    "addr:full":"3140 Christo Ln Jacksonville FL 32277",
    "addr:housenumber":"3140",
    "addr:postcode":"32277",
    "addr:street":"Christo Ln",
    "iso:country":"US",
    "sg:address":"3140 Christo Ln",
    "sg:city":"Jacksonville",
    "sg:classifiers":[
        {
            "category":"Building & Trades",
            "subcategory":"Construction",
            "type":"Services"
        }
    ],
    "sg:phone":"+1 904 743 2461",
    "sg:postcode":"32277",
    "sg:province":"FL",
    "sg:tags":[
        "heavy"
    ],
    "wof:name":"Franklin Hartman",
    "wof:placetype":"venue"
},
  "geometry": {"coordinates":[-81.59333100000001,30.3582],"type":"Point"}
}