{
  "type": "Feature",
  "properties": {
    "iso:country":"US",
    "sg:address":"2802 E Martin Luther King Jr Blvd",
    "sg:city":"Tampa",
    "sg:classifiers":[
        {
            "category":"Personal",
            "subcategory":"Beauty Salon",
            "type":"Services"
        }
    ],
    "sg:phone":"+1 813 236 4490",
    "sg:postcode":"33610",
    "sg:province":"FL",
    "wof:name":"Pure Ways",
    "wof:placetype":"venue"
},
  "geometry": {"coordinates":[-82.428034,27.981505],"type":"Point"}
}