{
  "type": "Feature",
  "properties": {
    "iso:country":"US",
    "sg:address":"255 E 22nd Ct",
    "sg:city":"West Palm Beach",
    "sg:classifiers":[
        {
            "category":"Shopping",
            "subcategory":"Bicycles & Sporting Goods",
            "type":"Retail Goods"
        }
    ],
    "sg:phone":"+1 561 691 5808",
    "sg:postcode":"33404",
    "sg:province":"FL",
    "wof:name":"Jim Abrnethys Scuba Adventures",
    "wof:placetype":"venue"
},
  "geometry": {"coordinates":[-80.05093100000001,26.780598],"type":"Point"}
}