{
  "type": "Feature",
  "properties": {
    "addr:full":"2300 Stanford Rd Panama City FL 32405",
    "addr:housenumber":"2300",
    "addr:postcode":"32405",
    "addr:street":"Stanford Rd",
    "iso:country":"US",
    "sg:address":"2300 Stanford Rd",
    "sg:city":"Panama City",
    "sg:classifiers":[
        {
            "category":"Autos & Motor Vehicles",
            "subcategory":"Automobile Sales",
            "type":"Retail Goods"
        }
    ],
    "sg:phone":"+1 850 785 8666",
    "sg:postcode":"32405",
    "sg:province":"FL",
    "sg:tags":[
        "used"
    ],
    "wof:name":"Stl Auto Sales",
    "wof:placetype":"venue"
},
  "geometry": {"coordinates":[-85.675631,30.190216],"type":"Point"}
}