{
  "type": "Feature",
  "properties": {
    "addr:full":"263 NW 48th Pl Miami FL 33126",
    "addr:housenumber":"263",
    "addr:postcode":"33126",
    "addr:street":"Nw 48Th Pl",
    "iso:country":"US",
    "sg:address":"263 NW 48th Pl",
    "sg:city":"Miami",
    "sg:classifiers":[
        {
            "category":"Shopping",
            "type":"Retail Goods"
        }
    ],
    "sg:phone":"+1 305 443 4366",
    "sg:postcode":"33126",
    "sg:province":"FL",
    "sg:tags":[
        "merchandise"
    ],
    "wof:name":"Cristina Santamaria",
    "wof:placetype":"venue"
},
  "geometry": {"coordinates":[-80.275283,25.772699],"type":"Point"}
}