{
  "type": "Feature",
  "properties": {
    "iso:country":"US",
    "sg:address":"2549 Alclobe Cir",
    "sg:city":"Ocoee",
    "sg:classifiers":[
        {
            "category":"Real Estate",
            "subcategory":"Real Estate Operator",
            "type":"Services"
        }
    ],
    "sg:phone":"+1 407 521 2813",
    "sg:postcode":"34761",
    "sg:province":"FL",
    "sg:tags":[
        "building",
        "nonresidential"
    ],
    "wof:name":"Cantrell Properties LLC",
    "wof:placetype":"venue"
},
  "geometry": {"coordinates":[-81.506484,28.57318],"type":"Point"}
}