{
  "type": "Feature",
  "properties": {
    "iso:country":"US",
    "sg:address":"3349 Williamsburg St",
    "sg:city":"Sarasota",
    "sg:classifiers":[
        {
            "category":"Building & Trades",
            "subcategory":"Construction",
            "type":"Services"
        }
    ],
    "sg:phone":"+1 941 923 4280",
    "sg:postcode":"34231",
    "sg:province":"FL",
    "sg:tags":[
        "contractor"
    ],
    "wof:name":"Fox Roofing Inc",
    "wof:placetype":"venue"
},
  "geometry": {"coordinates":[-82.50270399999999,27.266098],"type":"Point"}
}