{
  "type": "Feature",
  "properties": {
    "iso:country":"US",
    "sg:address":"2628 Magnolia Way",
    "sg:city":"Punta Gorda",
    "sg:classifiers":[
        {
            "category":"Building & Trades",
            "subcategory":"Construction",
            "type":"Services"
        }
    ],
    "sg:phone":"+1 941 639 8677",
    "sg:postcode":"33950",
    "sg:province":"FL",
    "sg:tags":[
        "designer",
        "marine",
        "contractor"
    ],
    "wof:name":"Parr Marine Construction Inc",
    "wof:placetype":"venue"
},
  "geometry": {"coordinates":[-82.05022099999999,26.914815],"type":"Point"}
}