{
  "type": "Feature",
  "properties": {
    "iso:country":"US",
    "sg:address":"7007 N Nebraska Ave",
    "sg:city":"Tampa",
    "sg:classifiers":[
        {
            "category":"Travel",
            "subcategory":"Hotels & Motels",
            "type":"Entertainment"
        }
    ],
    "sg:phone":"+1 813 239 2432",
    "sg:postcode":"33604",
    "sg:province":"FL",
    "wof:name":"Haven Motel",
    "wof:placetype":"venue"
},
  "geometry": {"coordinates":[-82.451223,28.012411],"type":"Point"}
}