{
  "type": "Feature",
  "properties": {
    "iso:country":"US",
    "sg:address":"2220 S Ocean Blvd",
    "sg:city":"Delray Beach",
    "sg:classifiers":[
        {
            "category":"Building & Trades",
            "subcategory":"Construction",
            "type":"Services"
        }
    ],
    "sg:phone":"+1 561 272 9917",
    "sg:postcode":"33483",
    "sg:province":"FL",
    "sg:tags":[
        "company"
    ],
    "wof:name":"Lanzo Construction",
    "wof:placetype":"venue"
},
  "geometry": {"coordinates":[-80.06339699999999,26.432131],"type":"Point"}
}