{
  "type": "Feature",
  "properties": {
    "iso:country":"US",
    "sg:address":"634 Edgewater Dr",
    "sg:city":"Dunedin",
    "sg:classifiers":[
        {
            "category":"Autos & Motor Vehicles",
            "subcategory":"Auto Supplies",
            "type":"Retail Goods"
        }
    ],
    "sg:phone":"+1 727 736 2144",
    "sg:postcode":"34698",
    "sg:province":"FL",
    "wof:name":"Johns Truck and Parts",
    "wof:placetype":"venue"
},
  "geometry": {"coordinates":[-82.79197499999999,28.009392],"type":"Point"}
}