{
  "type": "Feature",
  "properties": {
    "iso:country":"US",
    "sg:address":"26750 US Hwy 19",
    "sg:city":"Clearwater",
    "sg:classifiers":[
        {
            "category":"Insurance",
            "subcategory":"Insurance Agent",
            "type":"Services"
        }
    ],
    "sg:phone":"+1 727 669 2314",
    "sg:postcode":"33761",
    "sg:province":"FL",
    "wof:name":"Met Life",
    "wof:placetype":"venue"
},
  "geometry": {"coordinates":[-82.733205,28.011003],"type":"Point"}
}