{
  "type": "Feature",
  "properties": {
    "addr:full":"11645 Biscayne Blvd # 407 Miami FL 33181",
    "addr:housenumber":"11645",
    "addr:postcode":"33181",
    "addr:street":"Biscayne Blvd # 407",
    "iso:country":"US",
    "sg:address":"11645 Biscayne Blvd # 407",
    "sg:city":"Miami",
    "sg:classifiers":[
        {
            "category":"Health Services",
            "subcategory":"Medical Lab",
            "type":"Services"
        }
    ],
    "sg:phone":"+1 305 891 2639",
    "sg:postcode":"33181",
    "sg:province":"FL",
    "sg:tags":[
        "laboratory",
        "dental"
    ],
    "wof:name":"L Efrom & Associates",
    "wof:placetype":"venue"
},
  "geometry": {"coordinates":[-80.165738,25.883195],"type":"Point"}
}