{
  "type": "Feature",
  "properties": {
    "iso:country":"US",
    "sg:address":"101 Flamingo Dr",
    "sg:city":"Apollo Beach",
    "sg:classifiers":[
        {
            "category":"Personal",
            "subcategory":"Beauty Salon",
            "type":"Services"
        }
    ],
    "sg:phone":"+1 813 645 8476",
    "sg:postcode":"33572",
    "sg:province":"FL",
    "wof:name":"Guys & Gals Hair Care",
    "wof:placetype":"venue"
},
  "geometry": {"coordinates":[-82.395473,27.765006],"type":"Point"}
}