{
  "type": "Feature",
  "properties": {
    "iso:country":"US",
    "sg:address":"112 E Concord St",
    "sg:city":"Orlando",
    "sg:classifiers":[
        {
            "category":"Airline",
            "type":"Transportation"
        }
    ],
    "sg:phone":"+1 407 628 8299",
    "sg:postcode":"32801",
    "sg:province":"FL",
    "wof:name":"Airline Management Consultants Inc",
    "wof:placetype":"venue"
},
  "geometry": {"coordinates":[-81.376274,28.550957],"type":"Point"}
}