{
  "type": "Feature",
  "properties": {
    "iso:country":"US",
    "sg:address":"15044 SW 35th Ter",
    "sg:city":"Miami",
    "sg:classifiers":[
        {
            "category":"Retail",
            "subcategory":"Laundry & Dry Cleaning",
            "type":"Services"
        },
        {
            "category":"Building & Trades",
            "subcategory":"Cleaning & Sanitation",
            "type":"Services"
        }
    ],
    "sg:phone":"+1 305 551 0145",
    "sg:postcode":"33185",
    "sg:province":"FL",
    "sg:tags":[
        "cleaner",
        "house"
    ],
    "wof:name":"Double A Pressure Cleaning",
    "wof:placetype":"venue"
},
  "geometry": {"coordinates":[-80.43852200000001,25.734367],"type":"Point"}
}