{
  "type": "Feature",
  "properties": {
    "iso:country":"US",
    "sg:address":"1701 S Atlantic Ave",
    "sg:city":"New Smyrna Beach",
    "sg:classifiers":[
        {
            "category":"Restaurant",
            "type":"Food & Drink"
        }
    ],
    "sg:phone":"+1 386 423 2669",
    "sg:postcode":"32169",
    "sg:province":"FL",
    "wof:name":"Sea Vista Tiki Bar",
    "wof:placetype":"venue"
},
  "geometry": {"coordinates":[-80.889172,29.025129],"type":"Point"}
}