{
  "type": "Feature",
  "properties": {
    "iso:country":"US",
    "sg:address":"12845 SW 42nd St",
    "sg:city":"Miami",
    "sg:classifiers":[
        {
            "category":"Shopping",
            "subcategory":"Clothing, Apparel, & Fashions",
            "type":"Retail Goods"
        }
    ],
    "sg:phone":"+1 305 559 6090",
    "sg:postcode":"33175",
    "sg:province":"FL",
    "sg:tags":[
        "item",
        "boutique"
    ],
    "wof:name":"Angel Boutique Inc",
    "wof:placetype":"venue"
},
  "geometry": {"coordinates":[-80.4028,25.729683],"type":"Point"}
}