{
  "type": "Feature",
  "properties": {
    "iso:country":"US",
    "sg:address":"6330 SW 41st Ct",
    "sg:city":"Fort Lauderdale",
    "sg:classifiers":[
        {
            "category":"Professional",
            "subcategory":"Accounting & Tax Preparation",
            "type":"Services"
        }
    ],
    "sg:phone":"+1 954 581 0801",
    "sg:postcode":"33314",
    "sg:province":"FL",
    "wof:name":"Goode Medvin & Weissman LLC",
    "wof:placetype":"venue"
},
  "geometry": {"coordinates":[-80.229376,26.069849],"type":"Point"}
}