{
  "type": "Feature",
  "properties": {
    "iso:country":"US",
    "sg:address":"539 Jimbay Dr",
    "sg:city":"Orange Park",
    "sg:classifiers":[
        {
            "category":"Professional",
            "subcategory":"Business Services",
            "type":"Services"
        }
    ],
    "sg:phone":"+1 904 449 6944",
    "sg:postcode":"32073",
    "sg:province":"FL",
    "wof:name":"CSI Solutions",
    "wof:placetype":"venue"
},
  "geometry": {"coordinates":[-81.80461099999999,30.184063],"type":"Point"}
}