{
  "type": "Feature",
  "properties": {
    "addr:full":"3363 Cedar Crst Lp Spring Hill FL 34609",
    "addr:housenumber":"3363",
    "addr:postcode":"34609",
    "addr:street":"Cedar Crst Lp",
    "iso:country":"US",
    "sg:address":"3363 Cedar Crst Lp",
    "sg:city":"Spring Hill",
    "sg:classifiers":[
        {
            "category":"Manufacturing",
            "subcategory":"Toys & Sporting Goods",
            "type":"Manufacturing & Wholesale Goods"
        }
    ],
    "sg:phone":"+1 352 684 7222",
    "sg:postcode":"34609",
    "sg:province":"FL",
    "sg:tags":[
        "mfg"
    ],
    "wof:name":"Home of Oggie Dolls",
    "wof:placetype":"venue"
},
  "geometry": {"coordinates":[-82.49597199999999,28.484507],"type":"Point"}
}