{
  "type": "Feature",
  "properties": {
    "iso:country":"US",
    "sg:address":"28327 US Hwy 27",
    "sg:city":"Leesburg",
    "sg:classifiers":[
        {
            "category":"Autos & Motor Vehicles",
            "subcategory":"Boat Sales",
            "type":"Retail Goods"
        }
    ],
    "sg:phone":"+1 352 728 6004",
    "sg:postcode":"34748",
    "sg:province":"FL",
    "sg:tags":[
        "dealer",
        "sales"
    ],
    "wof:name":"Davis Marine Sales & Svc",
    "wof:placetype":"venue"
},
  "geometry": {"coordinates":[-81.87968600000001,28.760347],"type":"Point"}
}