{
  "type": "Feature",
  "properties": {
    "iso:country":"US",
    "sg:address":"2148 Villa Way",
    "sg:city":"New Smyrna Beach",
    "sg:classifiers":[
        {
            "category":"Building & Trades",
            "subcategory":"Construction",
            "type":"Services"
        }
    ],
    "sg:phone":"+1 407 786 9525",
    "sg:postcode":"32169",
    "sg:province":"FL",
    "sg:tags":[
        "general",
        "contractor"
    ],
    "wof:name":"Dave Dumke Construction Inc",
    "wof:placetype":"venue"
},
  "geometry": {"coordinates":[-80.90922999999999,29.059965],"type":"Point"}
}