{
  "type": "Feature",
  "properties": {
    "addr:full":"3079 NW 79th St Miami FL 33147",
    "addr:housenumber":"3079",
    "addr:postcode":"33147",
    "addr:street":"Nw 79Th St",
    "iso:country":"US",
    "sg:address":"3079 NW 79th St",
    "sg:city":"Miami",
    "sg:classifiers":[
        {
            "category":"Utilities",
            "subcategory":"Mobile Phone",
            "type":"Services"
        },
        {
            "category":"Shopping",
            "subcategory":"Mobile Phones",
            "type":"Retail Goods"
        },
        {
            "category":"Communications",
            "type":"Services"
        }
    ],
    "sg:phone":"+1 305 694 1444",
    "sg:postcode":"33147",
    "sg:province":"FL",
    "sg:tags":[
        "equipment",
        "cellular",
        "telephone",
        "systems-repair"
    ],
    "wof:name":"United Wireless",
    "wof:placetype":"venue"
},
  "geometry": {"coordinates":[-80.247461,25.846061],"type":"Point"}
}