{
  "type": "Feature",
  "properties": {
    "addr:full":"3120 Miriam St S Gulfport FL 33711",
    "addr:housenumber":"3120",
    "addr:postcode":"33711",
    "addr:street":"Miriam St S",
    "iso:country":"US",
    "sg:address":"3120 Miriam St S",
    "sg:city":"Gulfport",
    "sg:classifiers":[
        {
            "category":"Government",
            "subcategory":"Office",
            "type":"Public Place"
        }
    ],
    "sg:phone":"+1 727 321 4455",
    "sg:postcode":"33711",
    "sg:province":"FL",
    "sg:tags":[
        "federal",
        "security"
    ],
    "wof:name":"United States Coast Guard",
    "wof:placetype":"venue"
},
  "geometry": {"coordinates":[-82.69460100000001,27.740263],"type":"Point"}
}