{
  "type": "Feature",
  "properties": {
    "addr:full":"2258 N Monroe St Tallahassee FL 32303",
    "addr:housenumber":"2258",
    "addr:postcode":"32303",
    "addr:street":"N Monroe St",
    "iso:country":"US",
    "sg:address":"2258 N Monroe St",
    "sg:city":"Tallahassee",
    "sg:classifiers":[
        {
            "category":"Fast Food",
            "type":"Food & Drink"
        },
        {
            "category":"Restaurant",
            "type":"Food & Drink"
        },
        {
            "category":"Professional",
            "type":"Services"
        }
    ],
    "sg:phone":"+1 850 385 7636",
    "sg:postcode":"32303",
    "sg:province":"FL",
    "sg:tags":[
        "delivery",
        "take",
        "pizza"
    ],
    "sg:website":"http://www.pizzahut.com",
    "wof:name":"Pizza Hut",
    "wof:placetype":"venue"
},
  "geometry": {"coordinates":[-84.28948200000001,30.47077],"type":"Point"}
}