{
  "type": "Feature",
  "properties": {
    "iso:country":"US",
    "sg:address":"8202 Stoner Woods Ct",
    "sg:city":"Riverview",
    "sg:classifiers":[
        {
            "category":"Building & Trades",
            "subcategory":"Plumbing",
            "type":"Services"
        }
    ],
    "sg:phone":"+1 813 677 6938",
    "sg:postcode":"33569",
    "sg:province":"FL",
    "sg:tags":[
        "electrical",
        "contractor"
    ],
    "wof:name":"Gulf Stream Mechanical Inc",
    "wof:placetype":"venue"
},
  "geometry": {"coordinates":[-82.309038,27.86864],"type":"Point"}
}