{
  "type": "Feature",
  "properties": {
    "iso:country":"US",
    "sg:address":"10270 Washingtonia Palm Way",
    "sg:city":"Fort Myers",
    "sg:classifiers":[
        {
            "category":"Real Estate",
            "subcategory":"Developer",
            "type":"Services"
        }
    ],
    "sg:phone":"+1 239 931 9800",
    "sg:postcode":"33966",
    "sg:province":"FL",
    "wof:name":"US Home",
    "wof:placetype":"venue"
},
  "geometry": {"coordinates":[-81.82853299999999,26.588784],"type":"Point"}
}