{
  "type": "Feature",
  "properties": {
    "iso:country":"US",
    "sg:address":"7210 NW 8th St",
    "sg:city":"Miami",
    "sg:classifiers":[
        {
            "category":"Manufacturing",
            "subcategory":"Retail Goods",
            "type":"Manufacturing & Wholesale Goods"
        }
    ],
    "sg:phone":"+1 305 266 2222",
    "sg:postcode":"33126",
    "sg:province":"FL",
    "sg:tags":[
        "item",
        "boutique"
    ],
    "wof:name":"Import Specialties",
    "wof:placetype":"venue"
},
  "geometry": {"coordinates":[-80.312648,25.779048],"type":"Point"}
}