{
  "type": "Feature",
  "properties": {
    "addr:full":"1620 SW 9th St Miami FL 33135",
    "addr:housenumber":"1620",
    "addr:postcode":"33135",
    "addr:street":"Sw 9Th St",
    "iso:country":"US",
    "sg:address":"1620 SW 9th St",
    "sg:city":"Miami",
    "sg:classifiers":[
        {
            "category":"Retail",
            "subcategory":"Car Wash",
            "type":"Services"
        }
    ],
    "sg:phone":"+1 305 246 4412",
    "sg:postcode":"33135",
    "sg:province":"FL",
    "sg:tags":[
        "carwash"
    ],
    "wof:name":"Justo P Perez Mobil Carwash",
    "wof:placetype":"venue"
},
  "geometry": {"coordinates":[-80.22213499999999,25.764787],"type":"Point"}
}