{
  "type": "Feature",
  "properties": {
    "iso:country":"US",
    "sg:address":"100 Squire Hill Rd",
    "sg:city":"Longwood",
    "sg:classifiers":[
        {
            "category":"Professional",
            "subcategory":"Business Services",
            "type":"Services"
        }
    ],
    "sg:phone":"+1 407 788 0098",
    "sg:postcode":"32779",
    "sg:province":"FL",
    "sg:tags":[
        "interior",
        "consultant",
        "design",
        "decorator"
    ],
    "wof:name":"Avs International Interiors",
    "wof:placetype":"venue"
},
  "geometry": {"coordinates":[-81.455529,28.700377],"type":"Point"}
}