{
  "type": "Feature",
  "properties": {
    "iso:country":"US",
    "sg:address":"910 28th St",
    "sg:city":"West Palm Beach",
    "sg:classifiers":[
        {
            "category":"Building & Trades",
            "subcategory":"Construction",
            "type":"Services"
        }
    ],
    "sg:phone":"+1 561 306 5226",
    "sg:postcode":"33407",
    "sg:province":"FL",
    "sg:tags":[
        "home",
        "builder"
    ],
    "wof:name":"C & D Custom Homes",
    "wof:placetype":"venue"
},
  "geometry": {"coordinates":[-80.063118,26.739531],"type":"Point"}
}