{
  "type": "Feature",
  "properties": {
    "iso:country":"US",
    "sg:address":"1501 Ridgewood Ave",
    "sg:city":"Daytona Beach",
    "sg:classifiers":[
        {
            "category":"Professional",
            "subcategory":"Business Services",
            "type":"Services"
        }
    ],
    "sg:phone":"+1 386 671 2032",
    "sg:postcode":"32117",
    "sg:province":"FL",
    "sg:tags":[
        "recording",
        "studio"
    ],
    "wof:name":"Modern Nostalgia",
    "wof:placetype":"venue"
},
  "geometry": {"coordinates":[-81.04677100000001,29.255539],"type":"Point"}
}