{
  "type": "Feature",
  "properties": {
    "iso:country":"US",
    "sg:address":"1960 US Hwy 1 S",
    "sg:city":"St Augustine",
    "sg:classifiers":[
        {
            "category":"Banks & Credit Unions",
            "subcategory":"Bank",
            "type":"Services"
        }
    ],
    "sg:phone":"+1 904 829 5310",
    "sg:postcode":"32086",
    "sg:province":"FL",
    "sg:tags":[
        "cashing",
        "check"
    ],
    "sg:website":"www.dispatchdepot.com",
    "wof:name":"Dispatch Depot",
    "wof:placetype":"venue"
},
  "geometry": {"coordinates":[-81.32298,29.865386],"type":"Point"}
}