{
  "type": "Feature",
  "properties": {
    "iso:country":"US",
    "sg:address":"3630 Shaw Blvd",
    "sg:city":"Naples",
    "sg:classifiers":[
        {
            "category":"Freight",
            "type":"Transportation"
        }
    ],
    "sg:phone":"+1 239 352 6266",
    "sg:postcode":"34117",
    "sg:province":"FL",
    "sg:tags":[
        "warehouse",
        "self",
        "storage"
    ],
    "wof:name":"Taray International Warehouse",
    "wof:placetype":"venue"
},
  "geometry": {"coordinates":[-81.68189599999999,26.162123],"type":"Point"}
}