{
  "type": "Feature",
  "properties": {
    "addr:full":"1004 27th Ave W Palmetto FL 34221",
    "addr:housenumber":"1004",
    "addr:postcode":"34221",
    "addr:street":"27Th Ave W",
    "iso:country":"US",
    "sg:address":"1004 27th Ave W",
    "sg:city":"Palmetto",
    "sg:classifiers":[
        {
            "category":"Professional",
            "subcategory":"Detective & Security Services",
            "type":"Services"
        }
    ],
    "sg:phone":"+1 941 915 0204",
    "sg:postcode":"34221",
    "sg:province":"FL",
    "sg:tags":[
        "information",
        "bureau"
    ],
    "wof:name":"S & C Services",
    "wof:placetype":"venue"
},
  "geometry": {"coordinates":[-82.59638200000001,27.521407],"type":"Point"}
}