{
  "type": "Feature",
  "properties": {
    "addr:full":"12901 McGregor Blvd Fort Myers FL 33919",
    "addr:housenumber":"12901",
    "addr:postcode":"33919",
    "addr:street":"Mcgregor Blvd",
    "iso:country":"US",
    "sg:address":"12901 McGregor Blvd",
    "sg:city":"Fort Myers",
    "sg:classifiers":[
        {
            "category":"Home & Garden",
            "subcategory":"Household Appliances",
            "type":"Retail Goods"
        }
    ],
    "sg:phone":"+1 239 489 2199",
    "sg:postcode":"33919",
    "sg:province":"FL",
    "sg:tags":[
        "cleaners",
        "vacuum"
    ],
    "wof:name":"Janitor Depot",
    "wof:placetype":"venue"
},
  "geometry": {"coordinates":[-81.909367,26.559547],"type":"Point"}
}