{
  "type": "Feature",
  "properties": {
    "iso:country":"US",
    "sg:address":"3100 Jog Rd",
    "sg:city":"Lake Worth",
    "sg:classifiers":[
        {
            "category":"Recreation",
            "type":"Entertainment"
        }
    ],
    "sg:phone":"+1 561 964 4300",
    "sg:postcode":"33467",
    "sg:province":"FL",
    "sg:tags":[
        "skating",
        "roller",
        "rink"
    ],
    "wof:name":"B Lo Inc",
    "wof:placetype":"venue"
},
  "geometry": {"coordinates":[-80.14602499999999,26.63172],"type":"Point"}
}