{
  "type": "Feature",
  "properties": {
    "iso:country":"US",
    "sg:address":"2048 Range Rd",
    "sg:city":"Clearwater",
    "sg:classifiers":[
        {
            "category":"Building & Trades",
            "subcategory":"Construction",
            "type":"Services"
        }
    ],
    "sg:phone":"+1 727 447 6815",
    "sg:postcode":"33765",
    "sg:province":"FL",
    "sg:tags":[
        "maker",
        "cabinet"
    ],
    "wof:name":"A-1 Custom Cabinets",
    "wof:placetype":"venue"
},
  "geometry": {"coordinates":[-82.752742,27.978944],"type":"Point"}
}