{
  "type": "Feature",
  "properties": {
    "iso:country":"US",
    "sg:address":"4611 Dignan St",
    "sg:city":"Jacksonville",
    "sg:classifiers":[
        {
            "category":"Home & Garden",
            "subcategory":"Household Appliances",
            "type":"Retail Goods"
        }
    ],
    "sg:phone":"+1 904 389 6114",
    "sg:postcode":"32254",
    "sg:province":"FL",
    "sg:tags":[
        "pump"
    ],
    "wof:name":"Myers Seth Pump Inc",
    "wof:placetype":"venue"
},
  "geometry": {"coordinates":[-81.72585100000001,30.324611],"type":"Point"}
}