{
  "type": "Feature",
  "properties": {
    "addr:full":"236 Commercial Blvd Fort Lauderdale FL 33308",
    "addr:housenumber":"236",
    "addr:postcode":"33308",
    "addr:street":"Commercial Blvd",
    "iso:country":"US",
    "sg:address":"236 Commercial Blvd",
    "sg:city":"Fort Lauderdale",
    "sg:classifiers":[
        {
            "category":"Shopping",
            "subcategory":"Stationery & Office Supplies",
            "type":"Retail Goods"
        }
    ],
    "sg:phone":"+1 954 491 3577",
    "sg:postcode":"33308",
    "sg:province":"FL",
    "sg:tags":[
        "store"
    ],
    "wof:name":"Jo-Ans Papers Inc",
    "wof:placetype":"venue"
},
  "geometry": {"coordinates":[-80.10107000000001,26.189786],"type":"Point"}
}