{
  "type": "Feature",
  "properties": {
    "iso:country":"US",
    "sg:address":"5919 Trouble Creek Rd",
    "sg:city":"New Port Richey",
    "sg:classifiers":[
        {
            "category":"Shopping",
            "subcategory":"Clothing, Apparel, & Fashions",
            "type":"Retail Goods"
        }
    ],
    "sg:phone":"+1 727 842 2000",
    "sg:postcode":"34652",
    "sg:province":"FL",
    "sg:tags":[
        "shop",
        "bridal",
        "accessory"
    ],
    "wof:name":"Bridal Creations By J & E",
    "wof:placetype":"venue"
},
  "geometry": {"coordinates":[-82.718276,28.224383],"type":"Point"}
}