{
  "type": "Feature",
  "properties": {
    "iso:country":"US",
    "sg:address":"65 Needle Blvd",
    "sg:city":"Merritt Island",
    "sg:classifiers":[
        {
            "category":"Education",
            "subcategory":"Preschool",
            "type":"Public Place"
        },
        {
            "category":"Education",
            "subcategory":"School",
            "type":"Public Place"
        }
    ],
    "sg:phone":"+1 321 452 4484",
    "sg:postcode":"32953",
    "sg:province":"FL",
    "sg:tags":[
        "elementary"
    ],
    "wof:name":"Grace United Methodist Kindergarten & Nursery Schl",
    "wof:placetype":"venue"
},
  "geometry": {"coordinates":[-80.6987,28.365801],"type":"Point"}
}