{
  "type": "Feature",
  "properties": {
    "iso:country":"US",
    "sg:address":"1180 Central Ave",
    "sg:city":"St Petersburg",
    "sg:classifiers":[
        {
            "category":"Shopping",
            "subcategory":"Clothing, Apparel, & Fashions",
            "type":"Retail Goods"
        }
    ],
    "sg:phone":"+1 727 898 6866",
    "sg:postcode":"33705",
    "sg:province":"FL",
    "sg:tags":[
        "shop",
        "bridal"
    ],
    "wof:name":"Malindy Elene Bridal Boutique",
    "wof:placetype":"venue"
},
  "geometry": {"coordinates":[-82.651016,27.77107],"type":"Point"}
}