{
  "type": "Feature",
  "properties": {
    "addr:full":"420 Lincoln Rd Miami Beach FL 33139",
    "addr:housenumber":"420",
    "addr:postcode":"33139",
    "addr:street":"Lincoln Rd",
    "iso:country":"US",
    "sg:address":"420 Lincoln Rd",
    "sg:city":"Miami Beach",
    "sg:classifiers":[
        {
            "category":"Professional",
            "subcategory":"Lawyer & Legal Services",
            "type":"Services"
        }
    ],
    "sg:phone":"+1 305 672 0045",
    "sg:postcode":"33139",
    "sg:province":"FL",
    "sg:tags":[
        "attorney"
    ],
    "wof:name":"Michael I Finesilver",
    "wof:placetype":"venue"
},
  "geometry": {"coordinates":[-80.132887,25.790583],"type":"Point"}
}