{
  "type": "Feature",
  "properties": {
    "iso:country":"US",
    "sg:address":"3961 SW 126th Ct",
    "sg:city":"Miami",
    "sg:classifiers":[
        {
            "category":"Personal",
            "type":"Services"
        }
    ],
    "sg:phone":"+1 305 226 7477",
    "sg:postcode":"33175",
    "sg:province":"FL",
    "sg:tags":[
        "party",
        "planning",
        "event"
    ],
    "wof:name":"Events By Two Whacky Sisters L",
    "wof:placetype":"venue"
},
  "geometry": {"coordinates":[-80.39881099999999,25.73229],"type":"Point"}
}