{
  "type": "Feature",
  "properties": {
    "addr:full":"295 Alabama Ave Merritt Island FL 32953",
    "addr:housenumber":"295",
    "addr:postcode":"32953",
    "addr:street":"Alabama Ave",
    "iso:country":"US",
    "sg:address":"295 Alabama Ave",
    "sg:city":"Merritt Island",
    "sg:classifiers":[
        {
            "category":"Social Services",
            "subcategory":"Adult Care",
            "type":"Services"
        }
    ],
    "sg:phone":"+1 321 452 6252",
    "sg:postcode":"32953",
    "sg:province":"FL",
    "sg:tags":[
        "residential"
    ],
    "wof:name":"Bethesda Reaves Group Home",
    "wof:placetype":"venue"
},
  "geometry": {"coordinates":[-80.694303,28.364416],"type":"Point"}
}