{
  "type": "Feature",
  "properties": {
    "addr:full":"1451 E 27th St Jacksonville FL 32206",
    "addr:housenumber":"1451",
    "addr:postcode":"32206",
    "addr:street":"E 27Th St",
    "iso:country":"US",
    "sg:address":"1451 E 27th St",
    "sg:city":"Jacksonville",
    "sg:classifiers":[
        {
            "category":"Shopping",
            "type":"Retail Goods"
        }
    ],
    "sg:phone":"+1 904 355 0120",
    "sg:postcode":"32206",
    "sg:province":"FL",
    "sg:tags":[
        "art",
        "gallery",
        "dealer"
    ],
    "wof:name":"Lamar Studio",
    "wof:placetype":"venue"
},
  "geometry": {"coordinates":[-81.63513399999999,30.361345],"type":"Point"}
}