{
  "type": "Feature",
  "properties": {
    "iso:country":"US",
    "sg:address":"7040 Stapoint Ct",
    "sg:city":"Winter Park",
    "sg:classifiers":[
        {
            "category":"Manufacturing",
            "subcategory":"Printing",
            "type":"Manufacturing & Wholesale Goods"
        }
    ],
    "sg:phone":"+1 407 677 8200",
    "sg:postcode":"32792",
    "sg:province":"FL",
    "sg:tags":[
        "printer",
        "commercial"
    ],
    "wof:name":"Action Wholesale Printers Inc",
    "wof:placetype":"venue"
},
  "geometry": {"coordinates":[-81.29557,28.589018],"type":"Point"}
}