{
  "type": "Feature",
  "properties": {
    "iso:country":"US",
    "sg:address":"1726 Medical Blvd",
    "sg:city":"Naples",
    "sg:classifiers":[
        {
            "category":"Health Services",
            "subcategory":"Doctor",
            "type":"Services"
        }
    ],
    "sg:phone":"+1 239 643 6203",
    "sg:postcode":"34110",
    "sg:province":"FL",
    "sg:tags":[
        "dentist"
    ],
    "wof:name":"Perfect Smile",
    "wof:placetype":"venue"
},
  "geometry": {"coordinates":[-81.787807,26.272429],"type":"Point"}
}