{
  "type": "Feature",
  "properties": {
    "addr:full":"1970 Dr Martin Luther King Way Sarasota FL 34234",
    "addr:housenumber":"1970",
    "addr:postcode":"34234",
    "addr:street":"Dr Martin Luther King Way",
    "iso:country":"US",
    "sg:address":"1970 Dr Martin Luther King Way",
    "sg:city":"Sarasota",
    "sg:classifiers":[
        {
            "category":"Restaurant",
            "type":"Food & Drink"
        }
    ],
    "sg:phone":"+1 941 955 3133",
    "sg:postcode":"34234",
    "sg:province":"FL",
    "wof:name":"Town Hall Restaurant",
    "wof:placetype":"venue"
},
  "geometry": {"coordinates":[-82.53103400000001,27.359579],"type":"Point"}
}