{
  "type": "Feature",
  "properties": {
    "iso:country":"US",
    "sg:address":"845 Lake Markham Rd",
    "sg:city":"Sanford",
    "sg:classifiers":[
        {
            "category":"Organizations",
            "subcategory":"Membership Organization",
            "type":"Services"
        }
    ],
    "sg:phone":"+1 407 688 8710",
    "sg:postcode":"32771",
    "sg:province":"FL",
    "sg:tags":[
        "athletic"
    ],
    "wof:name":"Football Of Orlando",
    "wof:placetype":"venue"
},
  "geometry": {"coordinates":[-81.391127,28.80702],"type":"Point"}
}