{
  "type": "Feature",
  "properties": {
    "addr:full":"14856 Main St Alachua FL 32615",
    "addr:housenumber":"14856",
    "addr:postcode":"32615",
    "addr:street":"Main St",
    "iso:country":"US",
    "sg:address":"14856 Main St",
    "sg:city":"Alachua",
    "sg:classifiers":[
        {
            "category":"Shopping",
            "type":"Retail Goods"
        }
    ],
    "sg:phone":"+1 386 462 9671",
    "sg:postcode":"32615",
    "sg:province":"FL",
    "sg:tags":[
        "item",
        "boutique"
    ],
    "wof:name":"Prissy Pals",
    "wof:placetype":"venue"
},
  "geometry": {"coordinates":[-82.494255,29.791713],"type":"Point"}
}