{
  "type": "Feature",
  "properties": {
    "addr:full":"1200 W South St Orlando FL 32805",
    "addr:housenumber":"1200",
    "addr:postcode":"32805",
    "addr:street":"W South St",
    "iso:country":"US",
    "sg:address":"1200 W South St",
    "sg:city":"Orlando",
    "sg:classifiers":[
        {
            "category":"Government",
            "subcategory":"Office",
            "type":"Public Place"
        }
    ],
    "sg:phone":"+1 407 841 2279",
    "sg:postcode":"32805",
    "sg:province":"FL",
    "sg:tags":[
        "transit",
        "authority"
    ],
    "wof:name":"Lynx",
    "wof:placetype":"venue"
},
  "geometry": {"coordinates":[-81.395293,28.538212],"type":"Point"}
}