{
  "type": "Feature",
  "properties": {
    "addr:full":"1430 Eden Dr Apopka FL 32703",
    "addr:housenumber":"1430",
    "addr:postcode":"32703",
    "addr:street":"Eden Dr",
    "iso:country":"US",
    "sg:address":"1430 Eden Dr",
    "sg:city":"Apopka",
    "sg:classifiers":[
        {
            "category":"Professional",
            "subcategory":"Detective & Security Services",
            "type":"Services"
        }
    ],
    "sg:phone":"+1 407 729 9039",
    "sg:postcode":"32703",
    "sg:province":"FL",
    "sg:tags":[
        "information",
        "bureau"
    ],
    "wof:name":"Andrew Estes Pool Service",
    "wof:placetype":"venue"
},
  "geometry": {"coordinates":[-81.483937,28.660126],"type":"Point"}
}