{
  "type": "Feature",
  "properties": {
    "iso:country":"US",
    "sg:address":"330 Clematis St",
    "sg:city":"West Palm Beach",
    "sg:classifiers":[
        {
            "category":"Restaurant",
            "type":"Food & Drink"
        }
    ],
    "sg:phone":"+1 561 837 9833",
    "sg:postcode":"33401",
    "sg:province":"FL",
    "wof:name":"New Orleans Cafe",
    "wof:placetype":"venue"
},
  "geometry": {"coordinates":[-80.053087,26.71327],"type":"Point"}
}