{
  "type": "Feature",
  "properties": {
    "iso:country":"US",
    "sg:address":"4899 NW 59th Way",
    "sg:city":"Pompano Beach",
    "sg:classifiers":[
        {
            "category":"Professional",
            "type":"Services"
        }
    ],
    "sg:phone":"+1 954 255 1757",
    "sg:postcode":"33067",
    "sg:province":"FL",
    "wof:name":"Giaspace",
    "wof:placetype":"venue"
},
  "geometry": {"coordinates":[-80.21279800000001,26.289659],"type":"Point"}
}