{
  "type": "Feature",
  "properties": {
    "addr:full":"3846 W Fletcher Ave Tampa FL 33618",
    "addr:housenumber":"3846",
    "addr:postcode":"33618",
    "addr:street":"W Fletcher Ave",
    "iso:country":"US",
    "sg:address":"3846 W Fletcher Ave",
    "sg:city":"Tampa",
    "sg:classifiers":[
        {
            "category":"Restaurant",
            "type":"Food & Drink"
        }
    ],
    "sg:menulink":"http://www.allmenus.com/fl/tampa/163246-rallys/menu/",
    "sg:phone":"+1 813 265 2027",
    "sg:postcode":"33618",
    "sg:province":"FL",
    "sg:tags":[
        "sandwich",
        "dog",
        "burger",
        "hot",
        "wrap",
        "american"
    ],
    "wof:name":"Rally's",
    "wof:placetype":"venue"
},
  "geometry": {"coordinates":[-82.502387,28.065024],"type":"Point"}
}