{
  "type": "Feature",
  "properties": {
    "iso:country":"US",
    "sg:address":"1600 W Eau Gallie Blvd",
    "sg:city":"Melbourne",
    "sg:classifiers":[
        {
            "category":"Shopping",
            "subcategory":"Computers & Home Electronics",
            "type":"Retail Goods"
        }
    ],
    "sg:phone":"+1 321 253 9221",
    "sg:postcode":"32935",
    "sg:province":"FL",
    "sg:tags":[
        "software"
    ],
    "wof:name":"AET Inc",
    "wof:placetype":"venue"
},
  "geometry": {"coordinates":[-80.645961,28.128901],"type":"Point"}
}