{
  "type": "Feature",
  "properties": {
    "iso:country":"US",
    "sg:address":"6944 NW 10th Pl",
    "sg:city":"Gainesville",
    "sg:classifiers":[
        {
            "category":"Restaurant",
            "type":"Food & Drink"
        }
    ],
    "sg:menulink":"http://www.allmenus.com/fl/gainesville/62948-mr-hans/menu/",
    "sg:phone":"+1 352 331 6400",
    "sg:postcode":"32605",
    "sg:province":"FL",
    "sg:tags":[
        "asian",
        "chinese"
    ],
    "wof:name":"Mr. Han's",
    "wof:placetype":"venue"
},
  "geometry": {"coordinates":[-82.414359,29.661473],"type":"Point"}
}