{
  "type": "Feature",
  "properties": {
    "addr:full":"130 Wisteria Dr Longwood FL 32779",
    "addr:housenumber":"130",
    "addr:postcode":"32779",
    "addr:street":"Wisteria Dr",
    "iso:country":"US",
    "sg:address":"130 Wisteria Dr",
    "sg:city":"Longwood",
    "sg:classifiers":[
        {
            "category":"Wholesale",
            "subcategory":"Construction Materials",
            "type":"Manufacturing & Wholesale Goods"
        }
    ],
    "sg:phone":"+1 407 862 2865",
    "sg:postcode":"32779",
    "sg:province":"FL",
    "sg:tags":[
        "marble"
    ],
    "wof:name":"Global Marble & Granite Inc",
    "wof:placetype":"venue"
},
  "geometry": {"coordinates":[-81.402163,28.698695],"type":"Point"}
}