{
  "type": "Feature",
  "properties": {
    "addr:full":"1392 SW 160th Ave Sunrise FL 33326",
    "addr:housenumber":"1392",
    "addr:postcode":"33326",
    "addr:street":"Sw 160Th Ave",
    "iso:country":"US",
    "sg:address":"1392 SW 160th Ave",
    "sg:city":"Sunrise",
    "sg:classifiers":[
        {
            "category":"Recreation",
            "subcategory":"Amusement Park",
            "type":"Entertainment"
        }
    ],
    "sg:phone":"+1 954 515 0161",
    "sg:postcode":"33326",
    "sg:province":"FL",
    "wof:name":"Way To Play",
    "wof:placetype":"venue"
},
  "geometry": {"coordinates":[-80.362505,26.102819],"type":"Point"}
}