{
  "type": "Feature",
  "properties": {
    "addr:full":"750 NE 55th Ter Miami FL 33137",
    "addr:housenumber":"750",
    "addr:postcode":"33137",
    "addr:street":"Ne 55Th Ter",
    "iso:country":"US",
    "sg:address":"750 NE 55th Ter",
    "sg:city":"Miami",
    "sg:classifiers":[
        {
            "category":"Park",
            "type":"Public Place"
        }
    ],
    "sg:phone":"+1 305 754 1242",
    "sg:postcode":"33137",
    "sg:province":"FL",
    "sg:website":"www.miamigov.com/parks/pages/par...",
    "wof:name":"Morningside Park",
    "wof:placetype":"venue"
},
  "geometry": {"coordinates":[-80.180284,25.826997],"type":"Point"}
}