{
  "type": "Feature",
  "properties": {
    "addr:full":"2550 Heatherly Oaks Ln Jacksonville FL 32226",
    "addr:housenumber":"2550",
    "addr:postcode":"32226",
    "addr:street":"Heatherly Oaks Ln",
    "iso:country":"US",
    "sg:address":"2550 Heatherly Oaks Ln",
    "sg:city":"Jacksonville",
    "sg:classifiers":[
        {
            "category":"Real Estate",
            "subcategory":"Real Estate Agent",
            "type":"Services"
        }
    ],
    "sg:phone":"+1 904 696 2480",
    "sg:postcode":"32226",
    "sg:province":"FL",
    "wof:name":"Carey W Hardin",
    "wof:placetype":"venue"
},
  "geometry": {"coordinates":[-81.58334499999999,30.430944],"type":"Point"}
}