{
  "type": "Feature",
  "properties": {
    "iso:country":"US",
    "sg:address":"1150 Motel Dr",
    "sg:city":"Chipley",
    "sg:classifiers":[
        {
            "category":"Travel",
            "subcategory":"Hotels & Motels",
            "type":"Entertainment"
        }
    ],
    "sg:phone":"+1 850 638 8530",
    "sg:postcode":"32428",
    "sg:province":"FL",
    "wof:name":"Super 8 Motel",
    "wof:placetype":"venue"
},
  "geometry": {"coordinates":[-85.551132,30.75169],"type":"Point"}
}