{
  "type": "Feature",
  "properties": {
    "iso:country":"US",
    "sg:address":"5855 Lakeside Woods Cir",
    "sg:city":"Sarasota",
    "sg:classifiers":[
        {
            "category":"Organizations",
            "subcategory":"Community Association",
            "type":"Services"
        }
    ],
    "sg:phone":"+1 941 358 8881",
    "sg:postcode":"34243",
    "sg:province":"FL",
    "wof:name":"Lakeside Woods HM Owners Assn",
    "wof:placetype":"venue"
},
  "geometry": {"coordinates":[-82.486755,27.397255],"type":"Point"}
}