{
  "type": "Feature",
  "properties": {
    "iso:country":"US",
    "sg:address":"10670 NW 17th Pl",
    "sg:city":"Fort Lauderdale",
    "sg:classifiers":[
        {
            "category":"Real Estate",
            "subcategory":"Real Estate Agent",
            "type":"Services"
        }
    ],
    "sg:phone":"+1 954 423 1676",
    "sg:postcode":"33322",
    "sg:province":"FL",
    "wof:name":"Iris Leibowitz PA",
    "wof:placetype":"venue"
},
  "geometry": {"coordinates":[-80.290402,26.145074],"type":"Point"}
}