{
  "type": "Feature",
  "properties": {
    "iso:country":"US",
    "sg:address":"604 Lake Ave",
    "sg:city":"Lake Worth",
    "sg:classifiers":[
        {
            "category":"Professional",
            "subcategory":"Lawyer & Legal Services",
            "type":"Services"
        }
    ],
    "sg:phone":"+1 561 533 6879",
    "sg:postcode":"33460",
    "sg:province":"FL",
    "sg:tags":[
        "attorney"
    ],
    "wof:name":"Andy M Custer",
    "wof:placetype":"venue"
},
  "geometry": {"coordinates":[-80.055322,26.615929],"type":"Point"}
}