{
  "type": "Feature",
  "properties": {
    "iso:country":"US",
    "sg:address":"123 Chobee Loop",
    "sg:city":"Okeechobee",
    "sg:classifiers":[
        {
            "category":"Organizations",
            "subcategory":"Religious Organization",
            "type":"Services"
        }
    ],
    "sg:phone":"+1 863 467 8930",
    "sg:postcode":"34974",
    "sg:province":"FL",
    "sg:tags":[
        "church"
    ],
    "wof:name":"St Teresa Of The Child Jesus",
    "wof:placetype":"venue"
},
  "geometry": {"coordinates":[-80.89617200000001,27.127429],"type":"Point"}
}