{
  "type": "Feature",
  "properties": {
    "iso:country":"US",
    "sg:address":"3330 NE 33rd St",
    "sg:city":"Fort Lauderdale",
    "sg:classifiers":[
        {
            "category":"Shopping",
            "subcategory":"Used Merchandise",
            "type":"Retail Goods"
        }
    ],
    "sg:phone":"+1 954 567 2226",
    "sg:postcode":"33308",
    "sg:province":"FL",
    "wof:name":"Milbito Antiques & Consignment",
    "wof:placetype":"venue"
},
  "geometry": {"coordinates":[-80.101986,26.169052],"type":"Point"}
}