{
  "type": "Feature",
  "properties": {
    "addr:full":"145 S Orlando Ave Maitland FL 32751",
    "addr:housenumber":"145",
    "addr:postcode":"32751",
    "addr:street":"S Orlando Ave",
    "iso:country":"US",
    "sg:address":"145 S Orlando Ave",
    "sg:city":"Maitland",
    "sg:classifiers":[
        {
            "category":"Real Estate",
            "subcategory":"Real Estate Agent",
            "type":"Services"
        }
    ],
    "sg:phone":"+1 407 252 7898",
    "sg:postcode":"32751",
    "sg:province":"FL",
    "wof:name":"Creative Solutions Real Estate",
    "wof:placetype":"venue"
},
  "geometry": {"coordinates":[-81.363574,28.626172],"type":"Point"}
}