{
  "type": "Feature",
  "properties": {
    "addr:full":"17835 US Hwy 41 Brooksville FL 34610",
    "addr:housenumber":"17835",
    "addr:postcode":"34610",
    "addr:street":"Us Hwy 41",
    "iso:country":"US",
    "sg:address":"17835 US Hwy 41",
    "sg:city":"Brooksville",
    "sg:classifiers":[
        {
            "category":"Retail",
            "subcategory":"Auto Repair",
            "type":"Services"
        }
    ],
    "sg:phone":"+1 352 796 9091",
    "sg:postcode":"34610",
    "sg:province":"FL",
    "sg:tags":[
        "repairing",
        "automobile"
    ],
    "wof:name":"Smith's Auto Repair",
    "wof:placetype":"venue"
},
  "geometry": {"coordinates":[-82.471548,28.416348],"type":"Point"}
}