{
  "type": "Feature",
  "properties": {
    "addr:full":"1807 Pioneer Trl New Smyrna Beach FL 32168",
    "addr:housenumber":"1807",
    "addr:postcode":"32168",
    "addr:street":"Pioneer Trl",
    "iso:country":"US",
    "sg:address":"1807 Pioneer Trl",
    "sg:city":"New Smyrna Beach",
    "sg:classifiers":[
        {
            "category":"Manufacturing",
            "subcategory":"Lumber",
            "type":"Manufacturing & Wholesale Goods"
        },
        {
            "category":"Building & Trades",
            "subcategory":"Landscaping Services",
            "type":"Services"
        }
    ],
    "sg:phone":"+1 386 427 0982",
    "sg:postcode":"32168",
    "sg:province":"FL",
    "sg:tags":[
        "operation",
        "timber",
        "tree",
        "tract"
    ],
    "wof:name":"Donnie Owens Tree Service",
    "wof:placetype":"venue"
},
  "geometry": {"coordinates":[-80.940647,29.018083],"type":"Point"}
}