{
  "type": "Feature",
  "properties": {
    "addr:full":"810 Thomasville Rd Tallahassee FL 32303",
    "addr:housenumber":"810",
    "addr:postcode":"32303",
    "addr:street":"Thomasville Rd",
    "iso:country":"US",
    "sg:address":"810 Thomasville Rd",
    "sg:city":"Tallahassee",
    "sg:classifiers":[
        {
            "category":"Banks & Credit Unions",
            "subcategory":"Financial Services",
            "type":"Services"
        }
    ],
    "sg:phone":"+1 850 577 3404",
    "sg:postcode":"32303",
    "sg:province":"FL",
    "sg:tags":[
        "company",
        "investor",
        "holding"
    ],
    "wof:name":"Consolidated Capital Resources",
    "wof:placetype":"venue"
},
  "geometry": {"coordinates":[-84.280219,30.450925],"type":"Point"}
}