{
  "type": "Feature",
  "properties": {
    "iso:country":"US",
    "sg:address":"13002 Seminole Blvd Ste 4",
    "sg:city":"Largo",
    "sg:classifiers":[
        {
            "category":"Health Services",
            "subcategory":"Chiropractor",
            "type":"Services"
        }
    ],
    "sg:phone":"+1 727 585 8888",
    "sg:postcode":"33778",
    "sg:province":"FL",
    "sg:tags":[
        "chiropractic"
    ],
    "wof:name":"Active Life Chiropractic Center",
    "wof:placetype":"venue"
},
  "geometry": {"coordinates":[-82.787193,27.891115],"type":"Point"}
}