{
  "type": "Feature",
  "properties": {
    "iso:country":"US",
    "sg:address":"1202 Co Rd 17 N",
    "sg:city":"Lake Placid",
    "sg:classifiers":[
        {
            "category":"Building & Trades",
            "subcategory":"Landscaping Services",
            "type":"Services"
        }
    ],
    "sg:phone":"+1 863 465 6160",
    "sg:postcode":"33852",
    "sg:province":"FL",
    "wof:name":"Shane White",
    "wof:placetype":"venue"
},
  "geometry": {"coordinates":[-81.365878,27.308552],"type":"Point"}
}