{
  "type": "Feature",
  "properties": {
    "iso:country":"US",
    "sg:address":"801 Anchor Rode Dr",
    "sg:city":"Naples",
    "sg:classifiers":[
        {
            "category":"Professional",
            "subcategory":"Accounting & Tax Preparation",
            "type":"Services"
        }
    ],
    "sg:phone":"+1 239 262 8993",
    "sg:postcode":"34103",
    "sg:province":"FL",
    "sg:tags":[
        "accountant"
    ],
    "wof:name":"Shaun N Kelly Cpa PA",
    "wof:placetype":"venue"
},
  "geometry": {"coordinates":[-81.79993899999999,26.188375],"type":"Point"}
}