{
  "type": "Feature",
  "properties": {
    "iso:country":"US",
    "sg:address":"10302 NW South River Dr",
    "sg:city":"Miami",
    "sg:classifiers":[
        {
            "category":"Shopping",
            "subcategory":"Crafts & Fabrics",
            "type":"Retail Goods"
        }
    ],
    "sg:phone":"+1 305 888 1205",
    "sg:postcode":"33125",
    "sg:province":"FL",
    "sg:tags":[
        "canvas"
    ],
    "wof:name":"Tarp Solution Inc A",
    "wof:placetype":"venue"
},
  "geometry": {"coordinates":[-80.225605,25.784545],"type":"Point"}
}