{
  "type": "Feature",
  "properties": {
    "iso:country":"US",
    "sg:address":"5445 Creeping Hammock Dr",
    "sg:city":"Sarasota",
    "sg:classifiers":[
        {
            "category":"Professional",
            "subcategory":"Business Services",
            "type":"Services"
        }
    ],
    "sg:phone":"+1 941 925 9745",
    "sg:postcode":"34231",
    "sg:province":"FL",
    "wof:name":"Vision Group",
    "wof:placetype":"venue"
},
  "geometry": {"coordinates":[-82.501015,27.275209],"type":"Point"}
}