{
  "type": "Feature",
  "properties": {
    "addr:full":"2571 Crawfordville Hwy Crawfordville FL 32327",
    "addr:housenumber":"2571",
    "addr:postcode":"32327",
    "addr:street":"Crawfordville Hwy",
    "iso:country":"US",
    "sg:address":"2571 Crawfordville Hwy",
    "sg:city":"Crawfordville",
    "sg:classifiers":[
        {
            "category":"Retail",
            "subcategory":"Veterinary Services",
            "type":"Services"
        },
        {
            "category":"Retail",
            "subcategory":"Animal Services",
            "type":"Services"
        }
    ],
    "sg:phone":"+1 850 391 2537",
    "sg:postcode":"32327",
    "sg:province":"FL",
    "sg:tags":[
        "pet",
        "hospital",
        "veterinarian",
        "clinic"
    ],
    "sg:website":"http://ad.doubleclick.net/clk;226007916;49913701;g?http://www.vcahospitals.com/main/offer?utm_source=iyp&utm_medium=iyp&utm_campaign=yellowpages",
    "wof:name":"VCA Wakulla Animal Hospital",
    "wof:placetype":"venue"
},
  "geometry": {"coordinates":[-84.37046100000001,30.1961],"type":"Point"}
}