{
  "type": "Feature",
  "properties": {
    "addr:full":"1125 N New York Ave Lakeland FL 33805",
    "addr:housenumber":"1125",
    "addr:postcode":"33805",
    "addr:street":"N New York Ave",
    "iso:country":"US",
    "sg:address":"1125 N New York Ave",
    "sg:city":"Lakeland",
    "sg:classifiers":[
        {
            "category":"Organizations",
            "subcategory":"Religious Organization",
            "type":"Services"
        }
    ],
    "sg:phone":"+1 863 686 8134",
    "sg:postcode":"33805",
    "sg:province":"FL",
    "sg:tags":[
        "church"
    ],
    "wof:name":"New Jerusalem Fellowship Hall",
    "wof:placetype":"venue"
},
  "geometry": {"coordinates":[-81.95892000000001,28.0587],"type":"Point"}
}