{
  "type": "Feature",
  "properties": {
    "addr:full":"223 Lithia Pinecrest Rd Brandon FL 33511",
    "addr:housenumber":"223",
    "addr:postcode":"33511",
    "addr:street":"Lithia Pinecrest Rd",
    "iso:country":"US",
    "sg:address":"223 Lithia Pinecrest Rd",
    "sg:city":"Brandon",
    "sg:classifiers":[
        {
            "category":"Professional",
            "subcategory":"Lawyer & Legal Services",
            "type":"Services"
        }
    ],
    "sg:phone":"+1 813 654 3444",
    "sg:postcode":"33511",
    "sg:province":"FL",
    "sg:tags":[
        "attorney"
    ],
    "wof:name":"Allen S Carman PA",
    "wof:placetype":"venue"
},
  "geometry": {"coordinates":[-82.279679,27.935145],"type":"Point"}
}