{
  "type": "Feature",
  "properties": {
    "addr:full":"3302 Co Rd 218 Middleburg FL 32068",
    "addr:housenumber":"3302",
    "addr:postcode":"32068",
    "addr:street":"Co Rd 218",
    "iso:country":"US",
    "sg:address":"3302 Co Rd 218",
    "sg:city":"Middleburg",
    "sg:classifiers":[
        {
            "category":"Home & Garden",
            "subcategory":"Garden Supply",
            "type":"Retail Goods"
        }
    ],
    "sg:phone":"+1 904 282 1180",
    "sg:postcode":"32068",
    "sg:province":"FL",
    "sg:tags":[
        "mulch"
    ],
    "wof:name":"Green's Rock Sand & Mulch",
    "wof:placetype":"venue"
},
  "geometry": {"coordinates":[-81.830072,30.03658],"type":"Point"}
}