{
  "type": "Feature",
  "properties": {
    "iso:country":"US",
    "sg:address":"107 Judy Lee Dr",
    "sg:city":"Largo",
    "sg:classifiers":[
        {
            "category":"Shopping",
            "subcategory":"Clothing, Apparel, & Fashions",
            "type":"Retail Goods"
        }
    ],
    "sg:phone":"+1 727 823 1550",
    "sg:postcode":"33771",
    "sg:province":"FL",
    "wof:name":"Short Clothiers",
    "wof:placetype":"venue"
},
  "geometry": {"coordinates":[-82.768501,27.914765],"type":"Point"}
}