{
  "type": "Feature",
  "properties": {
    "addr:full":"7955 SW 86th Ct Miami FL 33143",
    "addr:housenumber":"7955",
    "addr:postcode":"33143",
    "addr:street":"Sw 86Th Ct",
    "iso:country":"US",
    "sg:address":"7955 SW 86th Ct",
    "sg:city":"Miami",
    "sg:classifiers":[
        {
            "category":"Wholesale",
            "subcategory":"Machinery & Supplies",
            "type":"Manufacturing & Wholesale Goods"
        }
    ],
    "sg:phone":"+1 305 275 9152",
    "sg:postcode":"33143",
    "sg:province":"FL",
    "sg:tags":[
        "machine",
        "industrial",
        "parts",
        "exporter"
    ],
    "wof:name":"Spartan Trading Corporation",
    "wof:placetype":"venue"
},
  "geometry": {"coordinates":[-80.33322800000001,25.696825],"type":"Point"}
}