{
  "type": "Feature",
  "properties": {
    "iso:country":"US",
    "sg:address":"19015 Biscayne Blvd",
    "sg:city":"Aventura",
    "sg:classifiers":[
        {
            "category":"Food & Beverages",
            "subcategory":"Candy",
            "type":"Retail Goods"
        },
        {
            "category":"Food & Beverages",
            "subcategory":"Bakery",
            "type":"Retail Goods"
        }
    ],
    "sg:phone":"+1 305 931 4470",
    "sg:postcode":"33180",
    "sg:province":"FL",
    "sg:tags":[
        "dessert",
        "sandwich"
    ],
    "sg:website":"www.alisasbistro.com",
    "wof:name":"Alisa's Painted Bistro",
    "wof:placetype":"venue"
},
  "geometry": {"coordinates":[-80.146636,25.951719],"type":"Point"}
}