{
  "type": "Feature",
  "properties": {
    "addr:full":"7311 NE 1st Pl Miami FL 33138",
    "addr:housenumber":"7311",
    "addr:postcode":"33138",
    "addr:street":"Ne 1St Pl",
    "iso:country":"US",
    "sg:address":"7311 NE 1st Pl",
    "sg:city":"Miami",
    "sg:classifiers":[
        {
            "category":"Wholesale",
            "subcategory":"Scrap",
            "type":"Manufacturing & Wholesale Goods"
        }
    ],
    "sg:phone":"+1 305 757 9576",
    "sg:postcode":"33138",
    "sg:province":"FL",
    "sg:tags":[
        "recycling",
        "center"
    ],
    "wof:name":"Interamerican Metals Trading",
    "wof:placetype":"venue"
},
  "geometry": {"coordinates":[-80.193629,25.843723],"type":"Point"}
}