{
  "type": "Feature",
  "properties": {
    "addr:full":"133 SW 21st Way Fort Lauderdale FL 33312",
    "addr:housenumber":"133",
    "addr:postcode":"33312",
    "addr:street":"Sw 21St Way",
    "iso:country":"US",
    "sg:address":"133 SW 21st Way",
    "sg:city":"Fort Lauderdale",
    "sg:classifiers":[
        {
            "category":"Professional",
            "type":"Services"
        }
    ],
    "sg:phone":"+1 754 204 7525",
    "sg:postcode":"33312",
    "sg:province":"FL",
    "wof:name":"Discount Elecrical Supply Corp",
    "wof:placetype":"venue"
},
  "geometry": {"coordinates":[-80.171975,26.117888],"type":"Point"}
}