{
  "type": "Feature",
  "properties": {
    "addr:full":"6361 Mary Kitchens Rd Milton FL 32583",
    "addr:housenumber":"6361",
    "addr:postcode":"32583",
    "addr:street":"Mary Kitchens Rd",
    "iso:country":"US",
    "sg:address":"6361 Mary Kitchens Rd",
    "sg:city":"Milton",
    "sg:classifiers":[
        {
            "category":"Building & Trades",
            "subcategory":"Construction",
            "type":"Services"
        }
    ],
    "sg:phone":"+1 850 626 8457",
    "sg:postcode":"32583",
    "sg:province":"FL",
    "sg:tags":[
        "hanging",
        "contractor"
    ],
    "wof:name":"James Selman Painting",
    "wof:placetype":"venue"
},
  "geometry": {"coordinates":[-87.063711,30.509566],"type":"Point"}
}