{
  "type": "Feature",
  "properties": {
    "iso:country":"US",
    "sg:address":"4821 Blue Pine Cir",
    "sg:city":"Lake Worth",
    "sg:classifiers":[
        {
            "category":"Food & Beverages",
            "subcategory":"Groceries & Convenience Stores",
            "type":"Retail Goods"
        }
    ],
    "sg:phone":"+1 561 968 7937",
    "sg:postcode":"33463",
    "sg:province":"FL",
    "wof:name":"Tropical Shoppes Services",
    "wof:placetype":"venue"
},
  "geometry": {"coordinates":[-80.115641,26.584208],"type":"Point"}
}