{
  "type": "Feature",
  "properties": {
    "iso:country":"US",
    "sg:address":"360 Tangerine Ave",
    "sg:city":"Merritt Island",
    "sg:classifiers":[
        {
            "category":"Professional",
            "subcategory":"Accounting & Tax Preparation",
            "type":"Services"
        }
    ],
    "sg:phone":"+1 321 452 4441",
    "sg:postcode":"32953",
    "sg:province":"FL",
    "sg:tags":[
        "accountant"
    ],
    "sg:website":"www.garydovercpa.com",
    "wof:name":"Dover Gary CPA",
    "wof:placetype":"venue"
},
  "geometry": {"coordinates":[-80.7052,28.3594],"type":"Point"}
}