{
  "type": "Feature",
  "properties": {
    "addr:full":"5249 Tampa West Blvd Tampa FL 33634",
    "addr:housenumber":"5249",
    "addr:postcode":"33634",
    "addr:street":"Tampa West Blvd",
    "iso:country":"US",
    "sg:address":"5249 Tampa West Blvd",
    "sg:city":"Tampa",
    "sg:classifiers":[
        {
            "category":"Wholesale",
            "subcategory":"Machinery & Supplies",
            "type":"Manufacturing & Wholesale Goods"
        }
    ],
    "sg:phone":"+1 813 884 4232",
    "sg:postcode":"33634",
    "sg:province":"FL",
    "sg:tags":[
        "equipment",
        "welding"
    ],
    "wof:name":"Tri-Tech",
    "wof:placetype":"venue"
},
  "geometry": {"coordinates":[-82.532122,28.01883],"type":"Point"}
}