{
  "type": "Feature",
  "properties": {
    "addr:full":"2432 Greenwillow Dr Orlando FL 32825",
    "addr:housenumber":"2432",
    "addr:postcode":"32825",
    "addr:street":"Greenwillow Dr",
    "iso:country":"US",
    "sg:address":"2432 Greenwillow Dr",
    "sg:city":"Orlando",
    "sg:classifiers":[
        {
            "category":"Food & Beverages",
            "subcategory":"Groceries & Convenience Stores",
            "type":"Retail Goods"
        }
    ],
    "sg:phone":"+1 407 823 9053",
    "sg:postcode":"32825",
    "sg:province":"FL",
    "wof:name":"Lucky Super Store Inc",
    "wof:placetype":"venue"
},
  "geometry": {"coordinates":[-81.254547,28.518622],"type":"Point"}
}