{
  "type": "Feature",
  "properties": {
    "iso:country":"US",
    "sg:address":"4642 S Kirkman Rd",
    "sg:city":"Orlando",
    "sg:classifiers":[
        {
            "category":"Bars & Pubs",
            "type":"Food & Drink"
        },
        {
            "category":"Restaurant",
            "type":"Food & Drink"
        }
    ],
    "sg:phone":"+1 407 781 5440",
    "sg:postcode":"32811",
    "sg:province":"FL",
    "sg:tags":[
        "tavern"
    ],
    "sg:website":"http://www.franksbistro.com",
    "wof:name":"Franks Bistro",
    "wof:placetype":"venue"
},
  "geometry": {"coordinates":[-81.459091,28.494684],"type":"Point"}
}