{
  "type": "Feature",
  "properties": {
    "addr:full":"5450 10th Ave N Greenacres FL 33463",
    "addr:housenumber":"5450",
    "addr:postcode":"33463",
    "addr:street":"10Th Ave N",
    "iso:country":"US",
    "sg:address":"5450 10th Ave N",
    "sg:city":"Greenacres",
    "sg:classifiers":[
        {
            "category":"Building & Trades",
            "subcategory":"Construction",
            "type":"Services"
        }
    ],
    "sg:phone":"+1 561 965 8261",
    "sg:postcode":"33463",
    "sg:province":"FL",
    "sg:tags":[
        "roofing",
        "contractor"
    ],
    "wof:name":"Star Roofers",
    "wof:placetype":"venue"
},
  "geometry": {"coordinates":[-80.128463,26.631187],"type":"Point"}
}