{
  "type": "Feature",
  "properties": {
    "addr:full":"8197 Fairways Cir Ocala FL 34472",
    "addr:housenumber":"8197",
    "addr:postcode":"34472",
    "addr:street":"Fairways Cir",
    "iso:country":"US",
    "sg:address":"8197 Fairways Cir",
    "sg:city":"Ocala",
    "sg:classifiers":[
        {
            "category":"Sports & Exercise",
            "subcategory":"Sports Center",
            "type":"Entertainment"
        },
        {
            "category":"Organizations",
            "subcategory":"Membership Organization",
            "type":"Services"
        }
    ],
    "sg:phone":"+1 352 687 0829",
    "sg:postcode":"34472",
    "sg:province":"FL",
    "sg:tags":[
        "club",
        "private"
    ],
    "wof:name":"Country Club Village Condo Association",
    "wof:placetype":"venue"
},
  "geometry": {"coordinates":[-82.00653,29.117701],"type":"Point"}
}