{
  "type": "Feature",
  "properties": {
    "iso:country":"US",
    "sg:address":"2960 Ponce De Leon Blvd",
    "sg:city":"Coral Gables",
    "sg:classifiers":[
        {
            "category":"Building & Trades",
            "subcategory":"Locksmith",
            "type":"Services"
        }
    ],
    "sg:phone":"+1 786 228 5598",
    "sg:postcode":"33134",
    "sg:province":"FL",
    "sg:tags":[
        "key"
    ],
    "wof:name":"7 Day 24 Hours Emergency Locksmith In Coral Gables",
    "wof:placetype":"venue"
},
  "geometry": {"coordinates":[-80.25864199999999,25.745087],"type":"Point"}
}