{
  "type": "Feature",
  "properties": {
    "iso:country":"US",
    "sg:address":"2799 SW Savona Blvd",
    "sg:city":"Port Saint Lucie",
    "sg:classifiers":[
        {
            "category":"Building & Trades",
            "subcategory":"Construction",
            "type":"Services"
        }
    ],
    "sg:phone":"+1 772 336 0898",
    "sg:postcode":"34953",
    "sg:province":"FL",
    "sg:tags":[
        "house",
        "nonresidential"
    ],
    "wof:name":"James D Atkinson Inc",
    "wof:placetype":"venue"
},
  "geometry": {"coordinates":[-80.389484,27.259722],"type":"Point"}
}