{
  "type": "Feature",
  "properties": {
    "iso:country":"US",
    "sg:address":"2229 Main St",
    "sg:city":"Fort Myers",
    "sg:classifiers":[
        {
            "category":"Shopping",
            "subcategory":"Used Merchandise",
            "type":"Retail Goods"
        }
    ],
    "sg:phone":"+1 239 689 6246",
    "sg:postcode":"33901",
    "sg:province":"FL",
    "sg:tags":[
        "antique"
    ],
    "wof:name":"Main Street Antq & Cllctbls",
    "wof:placetype":"venue"
},
  "geometry": {"coordinates":[-81.87012300000001,26.643033],"type":"Point"}
}