{
  "type": "Feature",
  "properties": {
    "addr:full":"3754 Diamond Oak Way Zellwood FL 32798",
    "addr:housenumber":"3754",
    "addr:postcode":"32798",
    "addr:street":"Diamond Oak Way",
    "iso:country":"US",
    "sg:address":"3754 Diamond Oak Way",
    "sg:city":"Zellwood",
    "sg:classifiers":[
        {
            "category":"Autos & Motor Vehicles",
            "subcategory":"Auto Supplies",
            "type":"Retail Goods"
        }
    ],
    "sg:phone":"+1 407 889 5507",
    "sg:postcode":"32798",
    "sg:province":"FL",
    "sg:tags":[
        "accessories-wholesale",
        "automobile",
        "part",
        "parts",
        "manufacturer"
    ],
    "wof:name":"Dennis Hites",
    "wof:placetype":"venue"
},
  "geometry": {"coordinates":[-81.571703,28.71857],"type":"Point"}
}