{
  "type": "Feature",
  "properties": {
    "iso:country":"US",
    "sg:address":"26 Cypress St",
    "sg:city":"Fort Myers",
    "sg:classifiers":[
        {
            "category":"Building & Trades",
            "subcategory":"Landscaping Services",
            "type":"Services"
        }
    ],
    "sg:phone":"+1 239 656 4956",
    "sg:postcode":"33903",
    "sg:province":"FL",
    "sg:tags":[
        "landscape",
        "contractor"
    ],
    "wof:name":"Hurricane Herronen's Tree Svc",
    "wof:placetype":"venue"
},
  "geometry": {"coordinates":[-81.88303999999999,26.666373],"type":"Point"}
}