{
  "type": "Feature",
  "properties": {
    "iso:country":"US",
    "sg:address":"6708 Sloane Pl",
    "sg:city":"Naples",
    "sg:classifiers":[
        {
            "category":"Manufacturing",
            "subcategory":"Tools & Machinery",
            "type":"Manufacturing & Wholesale Goods"
        }
    ],
    "sg:phone":"+1 239 304 0219",
    "sg:postcode":"34104",
    "sg:province":"FL",
    "sg:tags":[
        "instrument",
        "mfg"
    ],
    "wof:name":"Avcan Manufacturing",
    "wof:placetype":"venue"
},
  "geometry": {"coordinates":[-81.73352199999999,26.15494],"type":"Point"}
}