{
  "type": "Feature",
  "properties": {
    "iso:country":"US",
    "sg:address":"1200 S Orlando Ave",
    "sg:city":"Winter Park",
    "sg:classifiers":[
        {
            "category":"Deli",
            "type":"Food & Drink"
        },
        {
            "category":"Food & Beverages",
            "subcategory":"Bakery",
            "type":"Retail Goods"
        },
        {
            "category":"Bagels",
            "type":"Food & Drink"
        }
    ],
    "sg:menulink":"http://www.allmenus.com/fl/orlando/40916-einstein-bros/menu/",
    "sg:phone":"+1 407 629 2334",
    "sg:postcode":"32789",
    "sg:province":"FL",
    "sg:tags":[
        "sandwich",
        "salad",
        "deli",
        "bagel",
        "soup",
        "american",
        "wrap"
    ],
    "wof:name":"Einstein Bros",
    "wof:placetype":"venue"
},
  "geometry": {"coordinates":[-81.36494,28.586136],"type":"Point"}
}