{
  "type": "Feature",
  "properties": {
    "iso:country":"US",
    "sg:address":"9538 171st St N",
    "sg:city":"Jupiter",
    "sg:classifiers":[
        {
            "category":"Building & Trades",
            "subcategory":"Construction",
            "type":"Services"
        }
    ],
    "sg:phone":"+1 561 746 3055",
    "sg:postcode":"33478",
    "sg:province":"FL",
    "sg:tags":[
        "clearing",
        "land",
        "leveling"
    ],
    "wof:name":"Country Mulch",
    "wof:placetype":"venue"
},
  "geometry": {"coordinates":[-80.18446,26.930174],"type":"Point"}
}