{
  "type": "Feature",
  "properties": {
    "addr:full":"4263 Olinger Farm Rd Lakeland FL 33810",
    "addr:housenumber":"4263",
    "addr:postcode":"33810",
    "addr:street":"Olinger Farm Rd",
    "iso:country":"US",
    "sg:address":"4263 Olinger Farm Rd",
    "sg:city":"Lakeland",
    "sg:classifiers":[
        {
            "category":"Retail",
            "subcategory":"Animal Services",
            "type":"Services"
        }
    ],
    "sg:phone":"+1 863 581 1895",
    "sg:postcode":"33810",
    "sg:province":"FL",
    "sg:tags":[
        "pet",
        "boarding",
        "sitting"
    ],
    "wof:name":"Double M Kennels",
    "wof:placetype":"venue"
},
  "geometry": {"coordinates":[-82.030697,28.104184],"type":"Point"}
}