{
  "type": "Feature",
  "properties": {
    "iso:country":"US",
    "sg:address":"17130 SW 118th Pl",
    "sg:city":"Miami",
    "sg:classifiers":[
        {
            "category":"Manufacturing",
            "subcategory":"Furniture",
            "type":"Manufacturing & Wholesale Goods"
        }
    ],
    "sg:phone":"+1 305 378 1473",
    "sg:postcode":"33177",
    "sg:province":"FL",
    "sg:tags":[
        "drapery",
        "mfg"
    ],
    "wof:name":"Vertical Selections Inc",
    "wof:placetype":"venue"
},
  "geometry": {"coordinates":[-80.38484800000001,25.608628],"type":"Point"}
}