{
  "type": "Feature",
  "properties": {
    "addr:full":"855 Mason Ave Daytona Beach FL 32117",
    "addr:housenumber":"855",
    "addr:postcode":"32117",
    "addr:street":"Mason Ave",
    "iso:country":"US",
    "sg:address":"855 Mason Ave",
    "sg:city":"Daytona Beach",
    "sg:classifiers":[
        {
            "category":"Food & Beverages",
            "subcategory":"Bakery",
            "type":"Retail Goods"
        }
    ],
    "sg:phone":"+1 386 252 2755",
    "sg:postcode":"32117",
    "sg:province":"FL",
    "sg:tags":[
        "baker"
    ],
    "wof:name":"Jack & Lou's Customer Bakery",
    "wof:placetype":"venue"
},
  "geometry": {"coordinates":[-81.043166,29.221461],"type":"Point"}
}