{
  "type": "Feature",
  "properties": {
    "iso:country":"US",
    "sg:address":"721 W 83rd St",
    "sg:city":"Hialeah",
    "sg:classifiers":[
        {
            "category":"Building & Trades",
            "subcategory":"Construction",
            "type":"Services"
        }
    ],
    "sg:phone":"+1 305 828 9601",
    "sg:postcode":"33014",
    "sg:province":"FL",
    "sg:tags":[
        "carpentry",
        "contractor"
    ],
    "wof:name":"R Giralt Kitchen Cabinets",
    "wof:placetype":"venue"
},
  "geometry": {"coordinates":[-80.300017,25.897997],"type":"Point"}
}