{
  "type": "Feature",
  "properties": {
    "iso:country":"US",
    "sg:address":"2780 NW 29th Ter",
    "sg:city":"Lauderdale Lakes",
    "sg:classifiers":[
        {
            "category":"Professional",
            "subcategory":"Business Services",
            "type":"Services"
        }
    ],
    "sg:phone":"+1 954 777 2845",
    "sg:postcode":"33311",
    "sg:province":"FL",
    "sg:tags":[
        "interior",
        "consultant",
        "design",
        "decorator"
    ],
    "wof:name":"Total Interior Solutions",
    "wof:placetype":"venue"
},
  "geometry": {"coordinates":[-80.183555,26.160522],"type":"Point"}
}