{
  "type": "Feature",
  "properties": {
    "addr:full":"12300 SW 1st St Pompano Beach FL 33071",
    "addr:housenumber":"12300",
    "addr:postcode":"33071",
    "addr:street":"Sw 1St St",
    "iso:country":"US",
    "sg:address":"12300 SW 1st St",
    "sg:city":"Pompano Beach",
    "sg:classifiers":[
        {
            "category":"Wholesale",
            "subcategory":"Non-durable Goods",
            "type":"Manufacturing & Wholesale Goods"
        }
    ],
    "sg:phone":"+1 954 341 4484",
    "sg:postcode":"33071",
    "sg:province":"FL",
    "wof:name":"Carbone Imports",
    "wof:placetype":"venue"
},
  "geometry": {"coordinates":[-80.287126,26.230382],"type":"Point"}
}