{
  "type": "Feature",
  "properties": {
    "iso:country":"US",
    "sg:address":"3845 S Nova Rd",
    "sg:city":"Port Orange",
    "sg:classifiers":[
        {
            "category":"Shopping",
            "subcategory":"Gifts & Souvenirs",
            "type":"Retail Goods"
        }
    ],
    "sg:phone":"+1 386 761 7096",
    "sg:postcode":"32127",
    "sg:province":"FL",
    "sg:tags":[
        "shop"
    ],
    "wof:name":"Ardie's Hallmark",
    "wof:placetype":"venue"
},
  "geometry": {"coordinates":[-81.004251,29.125978],"type":"Point"}
}