{
  "type": "Feature",
  "properties": {
    "iso:country":"US",
    "sg:address":"2801 SW 71st Ter",
    "sg:city":"Fort Lauderdale",
    "sg:classifiers":[
        {
            "category":"Communications",
            "subcategory":"Television Station",
            "type":"Services"
        }
    ],
    "sg:phone":"+1 954 474 2719",
    "sg:postcode":"33314",
    "sg:province":"FL",
    "sg:tags":[
        "broadcast",
        "medium",
        "production"
    ],
    "wof:name":"Infinity Media Group Inc",
    "wof:placetype":"venue"
},
  "geometry": {"coordinates":[-80.244619,26.085511],"type":"Point"}
}