{
  "type": "Feature",
  "properties": {
    "addr:full":"958 Country Club Blvd Unit A Cape Coral FL 33990",
    "addr:housenumber":"958",
    "addr:postcode":"33990",
    "addr:street":"Country Club Blvd Unit A",
    "iso:country":"US",
    "sg:address":"958 Country Club Blvd Unit A",
    "sg:city":"Cape Coral",
    "sg:classifiers":[
        {
            "category":"Restaurant",
            "type":"Food & Drink"
        }
    ],
    "sg:phone":"+1 239 772 7790",
    "sg:postcode":"33990",
    "sg:province":"FL",
    "sg:tags":[
        "cuban",
        "mexican"
    ],
    "wof:name":"Rincon Cubano",
    "wof:placetype":"venue"
},
  "geometry": {"coordinates":[-81.953334,26.633326],"type":"Point"}
}