{
  "type": "Feature",
  "properties": {
    "iso:country":"US",
    "sg:address":"7130 S Orange Blossom Trl",
    "sg:city":"Orlando",
    "sg:classifiers":[
        {
            "category":"Organizations",
            "subcategory":"Professional Association",
            "type":"Services"
        }
    ],
    "sg:phone":"+1 407 855 1705",
    "sg:postcode":"32809",
    "sg:province":"FL",
    "sg:tags":[
        "highway",
        "redevelopment"
    ],
    "wof:name":"Orange Blossom Trail Dev Board",
    "wof:placetype":"venue"
},
  "geometry": {"coordinates":[-81.397969,28.460687],"type":"Point"}
}