{
  "type": "Feature",
  "properties": {
    "iso:country":"US",
    "sg:address":"1250 Skipper Rd",
    "sg:city":"Tampa",
    "sg:classifiers":[
        {
            "category":"Real Estate",
            "subcategory":"Real Estate Operator",
            "type":"Services"
        }
    ],
    "sg:phone":"+1 813 972 5200",
    "sg:postcode":"33613",
    "sg:province":"FL",
    "sg:tags":[
        "apartment",
        "complex"
    ],
    "wof:name":"Lane Canterbury Apartments",
    "wof:placetype":"venue"
},
  "geometry": {"coordinates":[-82.445093,28.080536],"type":"Point"}
}