{
  "type": "Feature",
  "properties": {
    "iso:country":"US",
    "sg:address":"492 Floral Dr",
    "sg:city":"Kissimmee",
    "sg:classifiers":[
        {
            "category":"Building & Trades",
            "subcategory":"Construction",
            "type":"Services"
        }
    ],
    "sg:phone":"+1 407 344 3377",
    "sg:postcode":"34743",
    "sg:province":"FL",
    "sg:tags":[
        "house"
    ],
    "wof:name":"Val & Luis Construction Inc",
    "wof:placetype":"venue"
},
  "geometry": {"coordinates":[-81.349391,28.323436],"type":"Point"}
}