{
  "type": "Feature",
  "properties": {
    "iso:country":"US",
    "sg:address":"12100 Seminole Blvd",
    "sg:city":"Largo",
    "sg:classifiers":[
        {
            "category":"Real Estate",
            "subcategory":"Developer",
            "type":"Services"
        }
    ],
    "sg:phone":"+1 727 501 1700",
    "sg:postcode":"33778",
    "sg:province":"FL",
    "sg:tags":[
        "mobile",
        "home"
    ],
    "wof:name":"Stella Del Mar",
    "wof:placetype":"venue"
},
  "geometry": {"coordinates":[-82.787165,27.881978],"type":"Point"}
}