{
  "type": "Feature",
  "properties": {
    "iso:country":"US",
    "sg:address":"6732 67th Ln",
    "sg:city":"Pinellas Park",
    "sg:classifiers":[
        {
            "category":"Professional",
            "type":"Services"
        },
        {
            "category":"Building & Trades",
            "subcategory":"Plumbing",
            "type":"Services"
        }
    ],
    "sg:phone":"+1 727 545 2408",
    "sg:postcode":"33781",
    "sg:province":"FL",
    "sg:tags":[
        "establishment",
        "contractor"
    ],
    "wof:name":"Universal Aire Inc",
    "wof:placetype":"venue"
},
  "geometry": {"coordinates":[-82.731736,27.832137],"type":"Point"}
}