{
  "type": "Feature",
  "properties": {
    "addr:full":"5697 NW 194th Ln Opa Locka FL 33055",
    "addr:housenumber":"5697",
    "addr:postcode":"33055",
    "addr:street":"Nw 194Th Ln",
    "iso:country":"US",
    "sg:address":"5697 NW 194th Ln",
    "sg:city":"Opa Locka",
    "sg:classifiers":[
        {
            "category":"Building & Trades",
            "subcategory":"Construction",
            "type":"Services"
        }
    ],
    "sg:phone":"+1 305 621 4544",
    "sg:postcode":"33055",
    "sg:province":"FL",
    "sg:tags":[
        "hanging",
        "contractor"
    ],
    "wof:name":"A New Look Painting Inc",
    "wof:placetype":"venue"
},
  "geometry": {"coordinates":[-80.293798,25.950539],"type":"Point"}
}