{
  "type": "Feature",
  "properties": {
    "iso:country":"US",
    "sg:address":"2951 SE Hing Dr",
    "sg:city":"Arcadia",
    "sg:classifiers":[
        {
            "category":"Restaurant",
            "type":"Food & Drink"
        }
    ],
    "sg:phone":"+1 863 491 8637",
    "sg:postcode":"34266",
    "sg:province":"FL",
    "wof:name":"Cho Chung Hing Enterprises, Inc.",
    "wof:placetype":"venue"
},
  "geometry": {"coordinates":[-81.82898299999999,27.09988],"type":"Point"}
}