{
  "type": "Feature",
  "properties": {
    "iso:country":"US",
    "sg:address":"655 S Main St",
    "sg:city":"Belle Glade",
    "sg:classifiers":[
        {
            "category":"Professional",
            "subcategory":"Business Services",
            "type":"Services"
        }
    ],
    "sg:phone":"+1 561 996 2210",
    "sg:postcode":"33430",
    "sg:province":"FL",
    "wof:name":"Steve Sprague Inc",
    "wof:placetype":"venue"
},
  "geometry": {"coordinates":[-80.66959900000001,26.679221],"type":"Point"}
}