{
  "type": "Feature",
  "properties": {
    "iso:country":"US",
    "sg:address":"6309 Corporate Ct",
    "sg:city":"Fort Myers",
    "sg:classifiers":[
        {
            "category":"Professional",
            "subcategory":"Business Services",
            "type":"Services"
        }
    ],
    "sg:phone":"+1 239 437 2504",
    "sg:postcode":"33919",
    "sg:province":"FL",
    "sg:tags":[
        "telemarketing"
    ],
    "wof:name":"Advantage 500 Group",
    "wof:placetype":"venue"
},
  "geometry": {"coordinates":[-81.887643,26.55843],"type":"Point"}
}