{
  "type": "Feature",
  "properties": {
    "addr:full":"10019 N Dale Mabry Hwy Tampa FL 33618",
    "addr:housenumber":"10019",
    "addr:postcode":"33618",
    "addr:street":"N Dale Mabry Hwy",
    "iso:country":"US",
    "sg:address":"10019 N Dale Mabry Hwy",
    "sg:city":"Tampa",
    "sg:classifiers":[
        {
            "category":"Restaurant",
            "type":"Food & Drink"
        }
    ],
    "sg:menulink":"http://www.allmenus.com/fl/tampa/46548-china-garden/menu/",
    "sg:phone":"+1 813 968 4899",
    "sg:postcode":"33618",
    "sg:province":"FL",
    "sg:tags":[
        "asian",
        "chinese"
    ],
    "wof:name":"China Garden",
    "wof:placetype":"venue"
},
  "geometry": {"coordinates":[-82.504735,28.04187],"type":"Point"}
}