{
  "type": "Feature",
  "properties": {
    "iso:country":"US",
    "sg:address":"836 E Logan Dr",
    "sg:city":"Longwood",
    "sg:classifiers":[
        {
            "category":"Professional",
            "subcategory":"Art Services",
            "type":"Services"
        }
    ],
    "sg:phone":"+1 407 260 0530",
    "sg:postcode":"32750",
    "sg:province":"FL",
    "sg:tags":[
        "graphic",
        "designer"
    ],
    "wof:name":"James Tacketts Artistik WORX",
    "wof:placetype":"venue"
},
  "geometry": {"coordinates":[-81.33260199999999,28.71094],"type":"Point"}
}