{
  "type": "Feature",
  "properties": {
    "iso:country":"US",
    "sg:address":"6363 Taft St",
    "sg:city":"Hollywood",
    "sg:classifiers":[
        {
            "category":"Shopping",
            "subcategory":"Clothing, Apparel, & Fashions",
            "type":"Retail Goods"
        }
    ],
    "sg:phone":"+1 954 894 3400",
    "sg:postcode":"33024",
    "sg:province":"FL",
    "wof:name":"Tom James of Hollywood 233",
    "wof:placetype":"venue"
},
  "geometry": {"coordinates":[-80.21405799999999,26.024862],"type":"Point"}
}