{
  "type": "Feature",
  "properties": {
    "iso:country":"US",
    "sg:address":"3217 Pleasant Lake Dr",
    "sg:city":"Tampa",
    "sg:classifiers":[
        {
            "category":"Organizations",
            "subcategory":"Membership Organization",
            "type":"Services"
        }
    ],
    "sg:phone":"+1 813 960 7744",
    "sg:postcode":"33618",
    "sg:province":"FL",
    "sg:tags":[
        "athletic"
    ],
    "wof:name":"Tampa Lookouts Inc",
    "wof:placetype":"venue"
},
  "geometry": {"coordinates":[-82.49736300000001,28.109551],"type":"Point"}
}