{
  "type": "Feature",
  "properties": {
    "iso:country":"US",
    "sg:address":"5050 Muldoon Cir",
    "sg:city":"Pensacola",
    "sg:classifiers":[
        {
            "category":"Shopping",
            "subcategory":"Clothing, Apparel, & Fashions",
            "type":"Retail Goods"
        }
    ],
    "sg:phone":"+1 850 455 9074",
    "sg:postcode":"32526",
    "sg:province":"FL",
    "sg:tags":[
        "family"
    ],
    "wof:name":"Amelia Thomas Designers Horzn",
    "wof:placetype":"venue"
},
  "geometry": {"coordinates":[-87.319337,30.455983],"type":"Point"}
}