{
  "type": "Feature",
  "properties": {
    "addr:full":"4342 Playa Ct Orlando FL 32812",
    "addr:housenumber":"4342",
    "addr:postcode":"32812",
    "addr:street":"Playa Ct",
    "iso:country":"US",
    "sg:address":"4342 Playa Ct",
    "sg:city":"Orlando",
    "sg:classifiers":[
        {
            "category":"Professional",
            "subcategory":"Business Services",
            "type":"Services"
        }
    ],
    "sg:phone":"+1 407 243 2271",
    "sg:postcode":"32812",
    "sg:province":"FL",
    "sg:tags":[
        "transcribing",
        "disc"
    ],
    "wof:name":"Karen Chappell Transcription",
    "wof:placetype":"venue"
},
  "geometry": {"coordinates":[-81.33219099999999,28.472297],"type":"Point"}
}