{
  "type": "Feature",
  "properties": {
    "addr:full":"6578 30th Ave N Saint Petersburg FL 33710",
    "addr:housenumber":"6578",
    "addr:postcode":"33710",
    "addr:street":"30Th Ave N",
    "iso:country":"US",
    "sg:address":"6578 30th Ave N",
    "sg:city":"Saint Petersburg",
    "sg:classifiers":[
        {
            "category":"Recreation",
            "type":"Entertainment"
        }
    ],
    "sg:phone":"+1 727 344 3223",
    "sg:postcode":"33710",
    "sg:province":"FL",
    "wof:name":"St Petersburg Chinese Martial",
    "wof:placetype":"venue"
},
  "geometry": {"coordinates":[-82.727754,27.798974],"type":"Point"}
}