{
  "type": "Feature",
  "properties": {
    "addr:full":"1401 Centerville Rd Tallahassee FL 32308",
    "addr:housenumber":"1401",
    "addr:postcode":"32308",
    "addr:street":"Centerville Rd",
    "iso:country":"US",
    "sg:address":"1401 Centerville Rd",
    "sg:city":"Tallahassee",
    "sg:classifiers":[
        {
            "category":"Health Services",
            "subcategory":"Doctor",
            "type":"Services"
        }
    ],
    "sg:phone":"+1 866 246 8203",
    "sg:postcode":"32308",
    "sg:province":"FL",
    "sg:tags":[
        "physician",
        "family",
        "gynecology",
        "endocrinology",
        "practice",
        "surgeons",
        "obstetrics",
        "medicine",
        "metabolism",
        "diabetes"
    ],
    "sg:website":"http://www.firmjax.com",
    "wof:name":"Florida Institute For Reproductive Medicine",
    "wof:placetype":"venue"
},
  "geometry": {"coordinates":[-84.262692,30.458154],"type":"Point"}
}