{
  "type": "Feature",
  "properties": {
    "addr:full":"2344 W 77th St Hialeah FL 33016",
    "addr:housenumber":"2344",
    "addr:postcode":"33016",
    "addr:street":"W 77Th St",
    "iso:country":"US",
    "sg:address":"2344 W 77th St",
    "sg:city":"Hialeah",
    "sg:classifiers":[
        {
            "category":"Home & Garden",
            "subcategory":"Furniture",
            "type":"Retail Goods"
        }
    ],
    "sg:phone":"+1 305 828 5080",
    "sg:postcode":"33016",
    "sg:province":"FL",
    "sg:tags":[
        "equipment",
        "kitchen",
        "cabinet"
    ],
    "wof:name":"Champion Cabinets Design Corp",
    "wof:placetype":"venue"
},
  "geometry": {"coordinates":[-80.330646,25.892378],"type":"Point"}
}