{
  "type": "Feature",
  "properties": {
    "iso:country":"US",
    "sg:address":"510 SE 5th St",
    "sg:city":"Hialeah",
    "sg:classifiers":[
        {
            "category":"Professional",
            "subcategory":"Employment Agencies",
            "type":"Services"
        },
        {
            "category":"Professional",
            "subcategory":"Art Services",
            "type":"Services"
        },
        {
            "category":"Building & Trades",
            "subcategory":"Construction",
            "type":"Services"
        }
    ],
    "sg:phone":"+1 786 307 5691",
    "sg:postcode":"33010",
    "sg:province":"FL",
    "sg:tags":[
        "designer",
        "grading",
        "excavation",
        "demolition",
        "contractor",
        "equipment",
        "interior",
        "wrecker",
        "decorator"
    ],
    "wof:name":"Executive Demolition Inc",
    "wof:placetype":"venue"
},
  "geometry": {"coordinates":[-80.27088000000001,25.818375],"type":"Point"}
}