{
  "type": "Feature",
  "properties": {
    "addr:full":"3760 SE Santa Barbara Pl Cape Coral FL 33904",
    "addr:housenumber":"3760",
    "addr:postcode":"33904",
    "addr:street":"Se Santa Barbara Pl",
    "iso:country":"US",
    "sg:address":"3760 SE Santa Barbara Pl",
    "sg:city":"Cape Coral",
    "sg:classifiers":[
        {
            "category":"Food & Beverages",
            "subcategory":"Fruits & Vegetables",
            "type":"Retail Goods"
        }
    ],
    "sg:phone":"+1 239 945 1050",
    "sg:postcode":"33904",
    "sg:province":"FL",
    "wof:name":"Andre Valdes",
    "wof:placetype":"venue"
},
  "geometry": {"coordinates":[-81.973247,26.582193],"type":"Point"}
}