{
  "type": "Feature",
  "properties": {
    "addr:full":"2652 Sandicrest Dr Cantonment FL 32533",
    "addr:housenumber":"2652",
    "addr:postcode":"32533",
    "addr:street":"Sandicrest Dr",
    "iso:country":"US",
    "sg:address":"2652 Sandicrest Dr",
    "sg:city":"Cantonment",
    "sg:classifiers":[
        {
            "category":"Shopping",
            "subcategory":"Pharmacy",
            "type":"Retail Goods"
        }
    ],
    "sg:phone":"+1 850 479 3158",
    "sg:postcode":"32533",
    "sg:province":"FL",
    "wof:name":"McGaw Rx Inc",
    "wof:placetype":"venue"
},
  "geometry": {"coordinates":[-87.33396500000001,30.556465],"type":"Point"}
}