{
  "type": "Feature",
  "properties": {
    "iso:country":"US",
    "sg:address":"15395 78th Dr N",
    "sg:city":"Palm Beach Gardens",
    "sg:classifiers":[
        {
            "category":"Real Estate",
            "subcategory":"Real Estate Agent",
            "type":"Services"
        }
    ],
    "sg:phone":"+1 561 744 2260",
    "sg:postcode":"33418",
    "sg:province":"FL",
    "wof:name":"Df Matevia Realty Inc",
    "wof:placetype":"venue"
},
  "geometry": {"coordinates":[-80.15737,26.902272],"type":"Point"}
}