{
  "type": "Feature",
  "properties": {
    "addr:full":"110 Gaslight Ave Fort Myers FL 33917",
    "addr:housenumber":"110",
    "addr:postcode":"33917",
    "addr:street":"Gaslight Ave",
    "iso:country":"US",
    "sg:address":"110 Gaslight Ave",
    "sg:city":"Fort Myers",
    "sg:classifiers":[
        {
            "category":"Building & Trades",
            "subcategory":"Landscaping Services",
            "type":"Services"
        }
    ],
    "sg:phone":"+1 239 543 1989",
    "sg:postcode":"33917",
    "sg:province":"FL",
    "sg:tags":[
        "lawn",
        "maintenance",
        "grounds"
    ],
    "wof:name":"Carol R Julius Lawn Svc",
    "wof:placetype":"venue"
},
  "geometry": {"coordinates":[-81.86142,26.69498],"type":"Point"}
}