{
  "type": "Feature",
  "properties": {
    "iso:country":"US",
    "sg:address":"235 N Hunt Club Blvd # 201",
    "sg:city":"Longwood",
    "sg:classifiers":[
        {
            "category":"Manufacturing",
            "subcategory":"Rubber & Plastics",
            "type":"Manufacturing & Wholesale Goods"
        }
    ],
    "sg:phone":"+1 407 788 1699",
    "sg:postcode":"32779",
    "sg:province":"FL",
    "sg:tags":[
        "product"
    ],
    "sg:website":"http://www.uniplascorp.com",
    "wof:name":"Uniplas Corporation",
    "wof:placetype":"venue"
},
  "geometry": {"coordinates":[-81.447289,28.693804],"type":"Point"}
}