{
  "type": "Feature",
  "properties": {
    "iso:country":"US",
    "sg:address":"3964 Belmoor Dr",
    "sg:city":"Palm Harbor",
    "sg:classifiers":[
        {
            "category":"Wholesale",
            "subcategory":"Electrical",
            "type":"Manufacturing & Wholesale Goods"
        }
    ],
    "sg:phone":"+1 727 787 8370",
    "sg:postcode":"34685",
    "sg:province":"FL",
    "sg:tags":[
        "distributor",
        "chip",
        "computer"
    ],
    "wof:name":"Horizons of Tampa Inc",
    "wof:placetype":"venue"
},
  "geometry": {"coordinates":[-82.679191,28.097164],"type":"Point"}
}