{
  "type": "Feature",
  "properties": {
    "iso:country":"US",
    "sg:address":"5975 NW 82nd Ave",
    "sg:city":"Miami",
    "sg:classifiers":[
        {
            "category":"Autos & Motor Vehicles",
            "subcategory":"Auto Supplies",
            "type":"Retail Goods"
        }
    ],
    "sg:phone":"+1 305 592 9211",
    "sg:postcode":"33166",
    "sg:province":"FL",
    "sg:tags":[
        "tire"
    ],
    "wof:name":"Inter-City Tire Export Corp",
    "wof:placetype":"venue"
},
  "geometry": {"coordinates":[-80.329903,25.827499],"type":"Point"}
}