{
  "type": "Feature",
  "properties": {
    "addr:full":"4330 SW 75th Ave Miami FL 33155",
    "addr:housenumber":"4330",
    "addr:postcode":"33155",
    "addr:street":"Sw 75Th Ave",
    "iso:country":"US",
    "sg:address":"4330 SW 75th Ave",
    "sg:city":"Miami",
    "sg:classifiers":[
        {
            "category":"Arts & Performance",
            "subcategory":"Music",
            "type":"Entertainment"
        }
    ],
    "sg:phone":"+1 305 262 2932",
    "sg:postcode":"33155",
    "sg:province":"FL",
    "sg:tags":[
        "jockey",
        "disc"
    ],
    "wof:name":"RAMES Productions",
    "wof:placetype":"venue"
},
  "geometry": {"coordinates":[-80.316901,25.731074],"type":"Point"}
}