{
  "type": "Feature",
  "properties": {
    "addr:full":"1175 34th Ave SW Vero Beach FL 32968",
    "addr:housenumber":"1175",
    "addr:postcode":"32968",
    "addr:street":"34Th Ave Sw",
    "iso:country":"US",
    "sg:address":"1175 34th Ave SW",
    "sg:city":"Vero Beach",
    "sg:classifiers":[
        {
            "category":"Building & Trades",
            "subcategory":"Construction",
            "type":"Services"
        }
    ],
    "sg:phone":"+1 772 569 0352",
    "sg:postcode":"32968",
    "sg:province":"FL",
    "sg:tags":[
        "roofing",
        "contractor"
    ],
    "wof:name":"Frank Hulbert Roofing",
    "wof:placetype":"venue"
},
  "geometry": {"coordinates":[-80.421543,27.58211],"type":"Point"}
}