{
  "type": "Feature",
  "properties": {
    "iso:country":"US",
    "sg:address":"2938 Matthew Dr",
    "sg:city":"Rockledge",
    "sg:classifiers":[
        {
            "category":"Building & Trades",
            "subcategory":"Construction",
            "type":"Services"
        }
    ],
    "sg:phone":"+1 321 259 1620",
    "sg:postcode":"32955",
    "sg:province":"FL",
    "sg:tags":[
        "house"
    ],
    "wof:name":"A1 Stop Construction Co Inc",
    "wof:placetype":"venue"
},
  "geometry": {"coordinates":[-80.749048,28.311018],"type":"Point"}
}