{
  "type": "Feature",
  "properties": {
    "addr:full":"3810 Exchange Ave Naples FL 34104",
    "addr:housenumber":"3810",
    "addr:postcode":"34104",
    "addr:street":"Exchange Ave",
    "iso:country":"US",
    "sg:address":"3810 Exchange Ave",
    "sg:city":"Naples",
    "sg:classifiers":[
        {
            "category":"Building & Trades",
            "subcategory":"Construction",
            "type":"Services"
        }
    ],
    "sg:phone":"+1 239 430 2224",
    "sg:postcode":"34104",
    "sg:province":"FL",
    "sg:tags":[
        "contractor"
    ],
    "wof:name":"J D Allen Construction",
    "wof:placetype":"venue"
},
  "geometry": {"coordinates":[-81.764043,26.158637],"type":"Point"}
}