{
  "type": "Feature",
  "properties": {
    "iso:country":"US",
    "sg:address":"23 Mala Compra Rd",
    "sg:city":"Palm Coast",
    "sg:classifiers":[
        {
            "category":"Building & Trades",
            "subcategory":"Construction",
            "type":"Services"
        }
    ],
    "sg:phone":"+1 386 446 8721",
    "sg:postcode":"32137",
    "sg:province":"FL",
    "sg:tags":[
        "house"
    ],
    "wof:name":"Sunrise Custom Builders Inc",
    "wof:placetype":"venue"
},
  "geometry": {"coordinates":[-81.199201,29.616225],"type":"Point"}
}