{
  "type": "Feature",
  "properties": {
    "addr:full":"276 Blanding Blvd Orange Park FL 32073",
    "addr:housenumber":"276",
    "addr:postcode":"32073",
    "addr:street":"Blanding Blvd",
    "iso:country":"US",
    "sg:address":"276 Blanding Blvd",
    "sg:city":"Orange Park",
    "sg:classifiers":[
        {
            "category":"Shopping",
            "subcategory":"Used Merchandise",
            "type":"Retail Goods"
        }
    ],
    "sg:phone":"+1 904 276 4840",
    "sg:postcode":"32073",
    "sg:province":"FL",
    "sg:tags":[
        "pawnshop"
    ],
    "wof:name":"Big Cash Pawn Inc",
    "wof:placetype":"venue"
},
  "geometry": {"coordinates":[-81.74606,30.173469],"type":"Point"}
}