{
  "type": "Feature",
  "properties": {
    "iso:country":"US",
    "sg:address":"9091 SW 21st St",
    "sg:city":"Boca Raton",
    "sg:classifiers":[
        {
            "category":"Health Services",
            "subcategory":"Hospital",
            "type":"Services"
        }
    ],
    "sg:phone":"+1 954 428 4320",
    "sg:postcode":"33428",
    "sg:province":"FL",
    "sg:tags":[
        "mental"
    ],
    "wof:name":"Psyche To You Inc",
    "wof:placetype":"venue"
},
  "geometry": {"coordinates":[-80.188948,26.329614],"type":"Point"}
}