{
  "type": "Feature",
  "properties": {
    "addr:full":"1100 SW 57th Ave Ph 2 West Miami FL 33144",
    "addr:housenumber":"1100",
    "addr:postcode":"33144",
    "addr:street":"Sw 57Th Ave Ph",
    "iso:country":"US",
    "sg:address":"1100 SW 57th Ave Ph 2",
    "sg:city":"West Miami",
    "sg:classifiers":[
        {
            "category":"Health Services",
            "subcategory":"Doctor",
            "type":"Services"
        }
    ],
    "sg:phone":"+1 305 261 3635",
    "sg:postcode":"33144",
    "sg:province":"FL",
    "wof:name":"Serentill Luis H MD",
    "wof:placetype":"venue"
},
  "geometry": {"coordinates":[-80.28791200000001,25.760646],"type":"Point"}
}