{
  "type": "Feature",
  "properties": {
    "iso:country":"US",
    "sg:address":"3617 W de Leon St",
    "sg:city":"Tampa",
    "sg:classifiers":[
        {
            "category":"Retail",
            "subcategory":"Laundry & Dry Cleaning",
            "type":"Services"
        }
    ],
    "sg:phone":"+1 813 354 1025",
    "sg:postcode":"33609",
    "sg:province":"FL",
    "wof:name":"Riverside Cleaners",
    "wof:placetype":"venue"
},
  "geometry": {"coordinates":[-82.503362,27.938584],"type":"Point"}
}