{
  "type": "Feature",
  "properties": {
    "addr:full":"7362 W Atlantic Blvd Margate FL 33063",
    "addr:housenumber":"7362",
    "addr:postcode":"33063",
    "addr:street":"W Atlantic Blvd Margate",
    "iso:country":"US",
    "sg:address":"7362 W Atlantic Blvd",
    "sg:city":"Margate",
    "sg:classifiers":[
        {
            "category":"Education",
            "subcategory":"Special Training",
            "type":"Public Place"
        }
    ],
    "sg:phone":"+1 954 979 7718",
    "sg:postcode":"33063",
    "sg:province":"FL",
    "sg:tags":[
        "center"
    ],
    "wof:name":"Awareness Through Edu Inc",
    "wof:placetype":"venue"
},
  "geometry": {"coordinates":[-80.223415,26.235422],"type":"Point"}
}