{
  "type": "Feature",
  "properties": {
    "addr:full":"8000 Arlington Expy Jacksonville FL 32211",
    "addr:housenumber":"8000",
    "addr:postcode":"32211",
    "addr:street":"Arlington Expy",
    "iso:country":"US",
    "sg:address":"8000 Arlington Expy",
    "sg:city":"Jacksonville",
    "sg:classifiers":[
        {
            "category":"Professional",
            "type":"Services"
        }
    ],
    "sg:phone":"+1 904 721 9970",
    "sg:postcode":"32211",
    "sg:province":"FL",
    "sg:tags":[
        "establishment"
    ],
    "wof:name":"Jacksonville Urban League",
    "wof:placetype":"venue"
},
  "geometry": {"coordinates":[-81.577333,30.327358],"type":"Point"}
}