{
  "type": "Feature",
  "properties": {
    "iso:country":"US",
    "sg:address":"3101 Moncrief Rd",
    "sg:city":"Jacksonville",
    "sg:classifiers":[
        {
            "category":"Restaurant",
            "type":"Food & Drink"
        }
    ],
    "sg:phone":"+1 904 355 7888",
    "sg:postcode":"32209",
    "sg:province":"FL",
    "sg:tags":[
        "eating"
    ],
    "wof:name":"Denmarks Restaurant",
    "wof:placetype":"venue"
},
  "geometry": {"coordinates":[-81.674206,30.357343],"type":"Point"}
}