{
  "type": "Feature",
  "properties": {
    "iso:country":"US",
    "sg:address":"4810 Hayride Ct",
    "sg:city":"Tampa",
    "sg:classifiers":[
        {
            "category":"Building & Trades",
            "subcategory":"Construction",
            "type":"Services"
        }
    ],
    "sg:phone":"+1 813 963 2271",
    "sg:postcode":"33624",
    "sg:province":"FL",
    "sg:tags":[
        "nonresidential"
    ],
    "wof:name":"All In One Builders",
    "wof:placetype":"venue"
},
  "geometry": {"coordinates":[-82.52970999999999,28.097907],"type":"Point"}
}