{
  "type": "Feature",
  "properties": {
    "iso:country":"US",
    "sg:address":"1004 Jasmine Way",
    "sg:city":"Clearwater",
    "sg:classifiers":[
        {
            "category":"Professional",
            "subcategory":"Art Services",
            "type":"Services"
        }
    ],
    "sg:phone":"+1 727 447 7222",
    "sg:postcode":"33756",
    "sg:province":"FL",
    "sg:tags":[
        "artist"
    ],
    "wof:name":"Artafex Co",
    "wof:placetype":"venue"
},
  "geometry": {"coordinates":[-82.79176200000001,27.9564],"type":"Point"}
}