{
  "type": "Feature",
  "properties": {
    "iso:country":"US",
    "sg:address":"2930 Drane Field Rd",
    "sg:city":"Lakeland",
    "sg:classifiers":[
        {
            "category":"Manufacturing",
            "subcategory":"Metals",
            "type":"Manufacturing & Wholesale Goods"
        }
    ],
    "sg:phone":"+1 863 644 7758",
    "sg:postcode":"33811",
    "sg:province":"FL",
    "sg:tags":[
        "work"
    ],
    "wof:name":"Creative Specialties By Lyons",
    "wof:placetype":"venue"
},
  "geometry": {"coordinates":[-82.002899,27.996632],"type":"Point"}
}