{
  "type": "Feature",
  "properties": {
    "addr:full":"10519 Firestone Dr Bradenton FL 34202",
    "addr:housenumber":"10519",
    "addr:postcode":"34202",
    "addr:street":"Firestone Dr",
    "iso:country":"US",
    "sg:address":"10519 Firestone Dr",
    "sg:city":"Bradenton",
    "sg:classifiers":[
        {
            "category":"Banks & Credit Unions",
            "subcategory":"Financial Services",
            "type":"Services"
        }
    ],
    "sg:phone":"+1 941 359 4879",
    "sg:postcode":"34202",
    "sg:province":"FL",
    "sg:tags":[
        "investor"
    ],
    "wof:name":"Rlt Investments LLC",
    "wof:placetype":"venue"
},
  "geometry": {"coordinates":[-82.43415,27.412931],"type":"Point"}
}