{
  "type": "Feature",
  "properties": {
    "iso:country":"US",
    "sg:address":"2050 Tyrone Blvd N",
    "sg:city":"St Petersburg",
    "sg:classifiers":[
        {
            "category":"Shopping",
            "subcategory":"Department Store",
            "type":"Retail Goods"
        }
    ],
    "sg:phone":"+1 727 345 8111",
    "sg:postcode":"33710",
    "sg:province":"FL",
    "wof:name":"Ross Dress For Less",
    "wof:placetype":"venue"
},
  "geometry": {"coordinates":[-82.724891,27.789581],"type":"Point"}
}