{
  "type": "Feature",
  "properties": {
    "addr:full":"850 W Royal Palm Rd Boca Raton FL 33486",
    "addr:housenumber":"850",
    "addr:postcode":"33486",
    "addr:street":"W Royal Palm Rd",
    "iso:country":"US",
    "sg:address":"850 W Royal Palm Rd",
    "sg:city":"Boca Raton",
    "sg:classifiers":[
        {
            "category":"Real Estate",
            "subcategory":"Architect",
            "type":"Services"
        }
    ],
    "sg:phone":"+1 561 392 9216",
    "sg:postcode":"33486",
    "sg:province":"FL",
    "wof:name":"Winslow Elliott Wedin",
    "wof:placetype":"venue"
},
  "geometry": {"coordinates":[-80.103354,26.349478],"type":"Point"}
}