{
  "type": "Feature",
  "properties": {
    "addr:full":"4937 Cyprus Ln West Palm Beach FL 33417",
    "addr:housenumber":"4937",
    "addr:postcode":"33417",
    "addr:street":"Cyprus Ln",
    "iso:country":"US",
    "sg:address":"4937 Cyprus Ln",
    "sg:city":"West Palm Beach",
    "sg:classifiers":[
        {
            "category":"Building & Trades",
            "subcategory":"Construction",
            "type":"Services"
        }
    ],
    "sg:phone":"+1 954 422 5698",
    "sg:postcode":"33417",
    "sg:province":"FL",
    "sg:tags":[
        "general",
        "contractor"
    ],
    "wof:name":"CJM Construction",
    "wof:placetype":"venue"
},
  "geometry": {"coordinates":[-80.11838899999999,26.696248],"type":"Point"}
}