{
  "type": "Feature",
  "properties": {
    "iso:country":"US",
    "sg:address":"615 Cape Coral Pkwy suite 101",
    "sg:city":"Cape Coral",
    "sg:classifiers":[
        {
            "category":"Real Estate",
            "subcategory":"Real Estate Services",
            "type":"Services"
        }
    ],
    "sg:phone":"+1 239 945 8848",
    "sg:postcode":"33914",
    "sg:province":"FL",
    "sg:website":"www.TIME-Realty.com",
    "wof:name":"TIME Realty",
    "wof:placetype":"venue"
},
  "geometry": {"coordinates":[-81.987466,26.56281],"type":"Point"}
}