{
  "type": "Feature",
  "properties": {
    "iso:country":"US",
    "sg:address":"8081 Cypress Garden Ct",
    "sg:city":"Seminole",
    "sg:classifiers":[
        {
            "category":"Home & Garden",
            "subcategory":"Carpets & Floor Coverings",
            "type":"Retail Goods"
        }
    ],
    "sg:phone":"+1 727 639 5309",
    "sg:postcode":"33777",
    "sg:province":"FL",
    "sg:tags":[
        "installation",
        "rug"
    ],
    "wof:name":"Seiples Carpets Inc",
    "wof:placetype":"venue"
},
  "geometry": {"coordinates":[-82.750631,27.859127],"type":"Point"}
}