{
  "type": "Feature",
  "properties": {
    "addr:full":"1936 US Hwy 19 Holiday FL 34691",
    "addr:housenumber":"1936",
    "addr:postcode":"34691",
    "addr:street":"Us Hwy 19",
    "iso:country":"US",
    "sg:address":"1936 US Hwy 19",
    "sg:city":"Holiday",
    "sg:classifiers":[
        {
            "category":"Shopping",
            "subcategory":"Gifts & Souvenirs",
            "type":"Retail Goods"
        }
    ],
    "sg:phone":"+1 727 938 0903",
    "sg:postcode":"34691",
    "sg:province":"FL",
    "wof:name":"Linda A Radescky",
    "wof:placetype":"venue"
},
  "geometry": {"coordinates":[-82.740047,28.185739],"type":"Point"}
}