{
  "type": "Feature",
  "properties": {
    "addr:full":"5200 Okeechobee Rd Fort Pierce FL 34947",
    "addr:housenumber":"5200",
    "addr:postcode":"34947",
    "addr:street":"Okeechobee Rd",
    "iso:country":"US",
    "sg:address":"5200 Okeechobee Rd",
    "sg:city":"Fort Pierce",
    "sg:classifiers":[
        {
            "category":"Restaurant",
            "type":"Food & Drink"
        }
    ],
    "sg:phone":"+1 772 429 1944",
    "sg:postcode":"34947",
    "sg:province":"FL",
    "wof:name":"Tropical Smoothie Cafe",
    "wof:placetype":"venue"
},
  "geometry": {"coordinates":[-80.377107,27.4197],"type":"Point"}
}