{
  "type": "Feature",
  "properties": {
    "iso:country":"US",
    "sg:address":"2203 SE Sailfish Point Blvd",
    "sg:city":"Stuart",
    "sg:classifiers":[
        {
            "category":"Shopping",
            "subcategory":"Bicycles & Sporting Goods",
            "type":"Retail Goods"
        },
        {
            "category":"Sports & Exercise",
            "subcategory":"Golf",
            "type":"Entertainment"
        }
    ],
    "sg:phone":"+1 772 225 1500",
    "sg:postcode":"34996",
    "sg:province":"FL",
    "sg:tags":[
        "equipment",
        "courses-private",
        "course",
        "supply"
    ],
    "wof:name":"Tortorici Golf Inc",
    "wof:placetype":"venue"
},
  "geometry": {"coordinates":[-80.159988,27.17831],"type":"Point"}
}