{
  "type": "Feature",
  "properties": {
    "addr:full":"749 105th Ave N Naples FL 34108",
    "addr:housenumber":"749",
    "addr:postcode":"34108",
    "addr:street":"105Th Ave N",
    "iso:country":"US",
    "sg:address":"749 105th Ave N",
    "sg:city":"Naples",
    "sg:classifiers":[
        {
            "category":"Building & Trades",
            "subcategory":"Cleaning & Sanitation",
            "type":"Services"
        }
    ],
    "sg:phone":"+1 239 594 0386",
    "sg:postcode":"34108",
    "sg:province":"FL",
    "sg:tags":[
        "maintenance"
    ],
    "wof:name":"Finishing Touch",
    "wof:placetype":"venue"
},
  "geometry": {"coordinates":[-81.807278,26.267017],"type":"Point"}
}