{
  "type": "Feature",
  "properties": {
    "iso:country":"US",
    "sg:address":"3210 14th Ave W",
    "sg:city":"Bradenton",
    "sg:classifiers":[
        {
            "category":"Professional",
            "subcategory":"Advertising",
            "type":"Services"
        }
    ],
    "sg:phone":"+1 941 748 6222",
    "sg:postcode":"34205",
    "sg:province":"FL",
    "sg:tags":[
        "counselor"
    ],
    "wof:name":"Roodlecat Graphic Design Co",
    "wof:placetype":"venue"
},
  "geometry": {"coordinates":[-82.595642,27.487549],"type":"Point"}
}