{
  "type": "Feature",
  "properties": {
    "iso:country":"US",
    "sg:address":"44 W Ponkan Rd",
    "sg:city":"Apopka",
    "sg:classifiers":[
        {
            "category":"Wholesale",
            "subcategory":"Plants",
            "type":"Manufacturing & Wholesale Goods"
        }
    ],
    "sg:phone":"+1 407 886 8178",
    "sg:postcode":"32712",
    "sg:province":"FL",
    "sg:tags":[
        "ornamental",
        "nursery",
        "tree",
        "supply"
    ],
    "wof:name":"Fletcher's Foliage",
    "wof:placetype":"venue"
},
  "geometry": {"coordinates":[-81.512495,28.728287],"type":"Point"}
}