{
  "type": "Feature",
  "properties": {
    "addr:full":"3610 Havendale Blvd NW Winter Haven FL 33881",
    "addr:housenumber":"3610",
    "addr:postcode":"33881",
    "addr:street":"Havendale Blvd Nw",
    "iso:country":"US",
    "sg:address":"3610 Havendale Blvd NW",
    "sg:city":"Winter Haven",
    "sg:classifiers":[
        {
            "category":"Insurance",
            "subcategory":"Insurance Agent",
            "type":"Services"
        }
    ],
    "sg:phone":"+1 863 965 4421",
    "sg:postcode":"33881",
    "sg:province":"FL",
    "wof:name":"Access Insurance Svc Group Inc",
    "wof:placetype":"venue"
},
  "geometry": {"coordinates":[-81.755117,28.0462],"type":"Point"}
}