{
  "type": "Feature",
  "properties": {
    "iso:country":"US",
    "sg:address":"524 Washington Ave Ste 101",
    "sg:city":"Miami Beach",
    "sg:classifiers":[
        {
            "category":"Shopping",
            "subcategory":"Clothing, Apparel, & Fashions",
            "type":"Retail Goods"
        }
    ],
    "sg:phone":"+1 305 538 8262",
    "sg:postcode":"33139",
    "sg:province":"FL",
    "sg:tags":[
        "clothing",
        "women's"
    ],
    "sg:website":"www.crimsoncarbon.com",
    "wof:name":"Crimson Carbon",
    "wof:placetype":"venue"
},
  "geometry": {"coordinates":[-80.134159,25.774845],"type":"Point"}
}