{
  "type": "Feature",
  "properties": {
    "addr:full":"240 Seaview Ct Marco Island FL 34145",
    "addr:housenumber":"240",
    "addr:postcode":"34145",
    "addr:street":"Seaview Ct",
    "iso:country":"US",
    "sg:address":"240 Seaview Ct",
    "sg:city":"Marco Island",
    "sg:classifiers":[
        {
            "category":"Organizations",
            "subcategory":"Community Association",
            "type":"Services"
        }
    ],
    "sg:phone":"+1 239 394 7391",
    "sg:postcode":"34145",
    "sg:province":"FL",
    "sg:tags":[
        "condominium"
    ],
    "wof:name":"Sunset House North",
    "wof:placetype":"venue"
},
  "geometry": {"coordinates":[-81.735793,25.942953],"type":"Point"}
}