{
  "type": "Feature",
  "properties": {
    "iso:country":"US",
    "sg:address":"13207 Maple St",
    "sg:city":"Odessa",
    "sg:classifiers":[
        {
            "category":"Building & Trades",
            "subcategory":"Construction",
            "type":"Services"
        }
    ],
    "sg:phone":"+1 813 920 5426",
    "sg:postcode":"33556",
    "sg:province":"FL",
    "sg:tags":[
        "contractor"
    ],
    "wof:name":"Aquatic Formation",
    "wof:placetype":"venue"
},
  "geometry": {"coordinates":[-82.647137,28.144856],"type":"Point"}
}