{
  "type": "Feature",
  "properties": {
    "addr:full":"1243 Simpson St Pensacola FL 32526",
    "addr:housenumber":"1243",
    "addr:postcode":"32526",
    "addr:street":"Simpson St",
    "iso:country":"US",
    "sg:address":"1243 Simpson St",
    "sg:city":"Pensacola",
    "sg:classifiers":[
        {
            "category":"Real Estate",
            "subcategory":"Real Estate Agent",
            "type":"Services"
        }
    ],
    "sg:phone":"+1 850 944 7921",
    "sg:postcode":"32526",
    "sg:province":"FL",
    "sg:tags":[
        "management"
    ],
    "wof:name":"Metric Property Management",
    "wof:placetype":"venue"
},
  "geometry": {"coordinates":[-87.30059900000001,30.474911],"type":"Point"}
}