{
  "type": "Feature",
  "properties": {
    "iso:country":"US",
    "sg:address":"2017 Fiesta Dr",
    "sg:city":"Sarasota",
    "sg:classifiers":[
        {
            "category":"Sports & Exercise",
            "subcategory":"Gym",
            "type":"Entertainment"
        }
    ],
    "sg:phone":"+1 941 929 0999",
    "sg:postcode":"34231",
    "sg:province":"FL",
    "sg:tags":[
        "fitness",
        "physical",
        "facility"
    ],
    "sg:website":"www.ayurvedichealers.com",
    "wof:name":"Ayurvedic Center Inc",
    "wof:placetype":"venue"
},
  "geometry": {"coordinates":[-82.528885,27.286635],"type":"Point"}
}