{
  "type": "Feature",
  "properties": {
    "iso:country":"US",
    "sg:address":"908 Kings Cross Rd",
    "sg:city":"Safety Harbor",
    "sg:classifiers":[
        {
            "category":"Retail",
            "subcategory":"Animal Services",
            "type":"Services"
        }
    ],
    "sg:phone":"+1 727 712 3381",
    "sg:postcode":"34609",
    "sg:province":"FL",
    "wof:name":"Seaside Kennels Inc",
    "wof:placetype":"venue"
},
  "geometry": {"coordinates":[-82.52704900000001,28.44627],"type":"Point"}
}