{
  "type": "Feature",
  "properties": {
    "iso:country":"US",
    "sg:address":"530 E Voorhis Ave",
    "sg:city":"Deland",
    "sg:classifiers":[
        {
            "category":"Organizations",
            "subcategory":"Religious Organization",
            "type":"Services"
        }
    ],
    "sg:phone":"+1 386 734 3158",
    "sg:postcode":"32724",
    "sg:province":"FL",
    "sg:website":"www.umc.org",
    "wof:name":"St Joseph United Methodist Church",
    "wof:placetype":"venue"
},
  "geometry": {"coordinates":[-81.293936,29.023732],"type":"Point"}
}