{
  "type": "Feature",
  "properties": {
    "addr:full":"1926 Temple Dr Tallahassee FL 32303",
    "addr:housenumber":"1926",
    "addr:postcode":"32303",
    "addr:street":"Temple Dr",
    "iso:country":"US",
    "sg:address":"1926 Temple Dr",
    "sg:city":"Tallahassee",
    "sg:classifiers":[
        {
            "category":"Professional",
            "type":"Services"
        }
    ],
    "sg:phone":"+1 850 422 2207",
    "sg:postcode":"32303",
    "sg:province":"FL",
    "wof:name":"Big Sky Creations",
    "wof:placetype":"venue"
},
  "geometry": {"coordinates":[-84.27497200000001,30.465328],"type":"Point"}
}