{
  "type": "Feature",
  "properties": {
    "addr:full":"1305 N Combee Rd Lakeland FL 33801",
    "addr:housenumber":"1305",
    "addr:postcode":"33801",
    "addr:street":"N Combee Rd",
    "iso:country":"US",
    "sg:address":"1305 N Combee Rd",
    "sg:city":"Lakeland",
    "sg:classifiers":[
        {
            "category":"Government",
            "subcategory":"Police Station",
            "type":"Public Place"
        }
    ],
    "sg:phone":"+1 863 284 4365",
    "sg:postcode":"33801",
    "sg:province":"FL",
    "sg:tags":[
        "sheriff"
    ],
    "wof:name":"County Sheriff Policing Unit",
    "wof:placetype":"venue"
},
  "geometry": {"coordinates":[-81.907967,28.061701],"type":"Point"}
}