{
  "type": "Feature",
  "properties": {
    "iso:country":"US",
    "sg:address":"1030 Kings Way",
    "sg:city":"Naples",
    "sg:classifiers":[
        {
            "category":"Recreation",
            "type":"Entertainment"
        }
    ],
    "sg:phone":"+1 239 643 3139",
    "sg:postcode":"34104",
    "sg:province":"FL",
    "sg:tags":[
        "club",
        "membership"
    ],
    "wof:name":"Foxfire Country Club",
    "wof:placetype":"venue"
},
  "geometry": {"coordinates":[-81.743329,26.144938],"type":"Point"}
}