{
  "type": "Feature",
  "properties": {
    "addr:full":"23066 Sandalfoot Plaza Dr Boca Raton FL 33428",
    "addr:postcode":"23066;33428",
    "addr:street":"Sandalfoot Plaza Dr",
    "iso:country":"US",
    "sg:address":"23066 Sandalfoot Plaza Dr",
    "sg:city":"Boca Raton",
    "sg:classifiers":[
        {
            "category":"Shopping",
            "subcategory":"Books",
            "type":"Retail Goods"
        }
    ],
    "sg:phone":"+1 561 470 5700",
    "sg:postcode":"33428",
    "sg:province":"FL",
    "sg:tags":[
        "comic"
    ],
    "wof:name":"Lost Realms Inc",
    "wof:placetype":"venue"
},
  "geometry": {"coordinates":[-80.201643,26.331816],"type":"Point"}
}