{
  "type": "Feature",
  "properties": {
    "iso:country":"US",
    "sg:address":"6600 SW 57th Ave",
    "sg:city":"South Miami",
    "sg:classifiers":[
        {
            "category":"Real Estate",
            "subcategory":"Real Estate Services",
            "type":"Services"
        }
    ],
    "sg:phone":"+1 305 665 2222",
    "sg:postcode":"33143",
    "sg:province":"FL",
    "sg:tags":[
        "management",
        "property"
    ],
    "wof:name":"A & R Agency",
    "wof:placetype":"venue"
},
  "geometry": {"coordinates":[-80.285599,25.709299],"type":"Point"}
}