{
  "type": "Feature",
  "properties": {
    "addr:full":"4718 W Hwy 98 Panama City FL 32401",
    "addr:housenumber":"4718",
    "addr:postcode":"32401",
    "addr:street":"W Hwy 98",
    "iso:country":"US",
    "sg:address":"4718 W Hwy 98",
    "sg:city":"Panama City",
    "sg:classifiers":[
        {
            "category":"Autos & Motor Vehicles",
            "subcategory":"Automobile Sales",
            "type":"Retail Goods"
        }
    ],
    "sg:phone":"+1 850 215 3415",
    "sg:postcode":"32401",
    "sg:province":"FL",
    "sg:tags":[
        "car",
        "dealer"
    ],
    "wof:name":"Budget Car Sales",
    "wof:placetype":"venue"
},
  "geometry": {"coordinates":[-85.722477,30.181339],"type":"Point"}
}