{
  "type": "Feature",
  "properties": {
    "addr:full":"2881 N 50th St Tampa FL 33619",
    "addr:housenumber":"2881",
    "addr:postcode":"33619",
    "addr:street":"N 50Th St",
    "iso:country":"US",
    "sg:address":"2881 N 50th St",
    "sg:city":"Tampa",
    "sg:classifiers":[
        {
            "category":"Restaurant",
            "type":"Food & Drink"
        }
    ],
    "sg:phone":"+1 813 626 9493",
    "sg:postcode":"33619",
    "sg:province":"FL",
    "sg:tags":[
        "eating"
    ],
    "wof:name":"Waffle House",
    "wof:placetype":"venue"
},
  "geometry": {"coordinates":[-82.401563,27.969433],"type":"Point"}
}