{
  "type": "Feature",
  "properties": {
    "addr:full":"376 Spyglass Way Jupiter FL 33477",
    "addr:housenumber":"376",
    "addr:postcode":"33477",
    "addr:street":"Spyglass Way",
    "iso:country":"US",
    "sg:address":"376 Spyglass Way",
    "sg:city":"Jupiter",
    "sg:classifiers":[
        {
            "category":"Food & Beverages",
            "subcategory":"Specialty",
            "type":"Retail Goods"
        }
    ],
    "sg:phone":"+1 561 745 4450",
    "sg:postcode":"33477",
    "sg:province":"FL",
    "wof:name":"Wellington Health & Nutrition",
    "wof:placetype":"venue"
},
  "geometry": {"coordinates":[-80.08792200000001,26.912855],"type":"Point"}
}