{
  "type": "Feature",
  "properties": {
    "iso:country":"US",
    "sg:address":"1778 E 30th St",
    "sg:city":"Jacksonville",
    "sg:classifiers":[
        {
            "category":"Place Of Worship",
            "type":"Public Place"
        }
    ],
    "sg:phone":"+1 904 632 0533",
    "sg:postcode":"32206",
    "sg:province":"FL",
    "sg:tags":[
        "church"
    ],
    "wof:name":"God Speed Endeavors Inc",
    "wof:placetype":"venue"
},
  "geometry": {"coordinates":[-81.63182999999999,30.362618],"type":"Point"}
}