{
  "type": "Feature",
  "properties": {
    "iso:country":"US",
    "sg:address":"570 E International Speedway Blvd",
    "sg:city":"DeLand",
    "sg:classifiers":[
        {
            "category":"Home & Garden",
            "subcategory":"Garden Supply",
            "type":"Retail Goods"
        },
        {
            "category":"Shopping",
            "subcategory":"Florist",
            "type":"Retail Goods"
        }
    ],
    "sg:phone":"+1 386 748 5074",
    "sg:postcode":"32724",
    "sg:province":"FL",
    "sg:tags":[
        "nursery",
        "gardening"
    ],
    "wof:name":"Debby's Christmas & Firewood",
    "wof:placetype":"venue"
},
  "geometry": {"coordinates":[-81.29460400000001,29.054842],"type":"Point"}
}