{
  "type": "Feature",
  "properties": {
    "iso:country":"US",
    "sg:address":"694 Baldwin Ave",
    "sg:city":"Defuniak Springs",
    "sg:classifiers":[
        {
            "category":"Professional",
            "subcategory":"Lawyer & Legal Services",
            "type":"Services"
        }
    ],
    "sg:phone":"+1 850 892 5838",
    "sg:postcode":"32435",
    "sg:province":"FL",
    "sg:tags":[
        "attorney"
    ],
    "wof:name":"Andrews & Davis",
    "wof:placetype":"venue"
},
  "geometry": {"coordinates":[-86.113119,30.720211],"type":"Point"}
}