{
  "type": "Feature",
  "properties": {
    "iso:country":"US",
    "sg:address":"9300 S Dadeland Blvd",
    "sg:city":"Miami",
    "sg:classifiers":[
        {
            "category":"Professional",
            "subcategory":"Lawyer & Legal Services",
            "type":"Services"
        }
    ],
    "sg:phone":"+1 305 671 2260",
    "sg:postcode":"33156",
    "sg:province":"FL",
    "wof:name":"Abramson Stuart Atty",
    "wof:placetype":"venue"
},
  "geometry": {"coordinates":[-80.316383,25.682791],"type":"Point"}
}