{
  "type": "Feature",
  "properties": {
    "addr:full":"203 W Canal Dr Palm Harbor FL 34684",
    "addr:housenumber":"203",
    "addr:postcode":"34684",
    "addr:street":"W Canal Dr",
    "iso:country":"US",
    "sg:address":"203 W Canal Dr",
    "sg:city":"Palm Harbor",
    "sg:classifiers":[
        {
            "category":"Retail",
            "subcategory":"Repair Shop",
            "type":"Services"
        }
    ],
    "sg:phone":"+1 727 934 6810",
    "sg:postcode":"34684",
    "sg:province":"FL",
    "sg:tags":[
        "tank",
        "septic"
    ],
    "wof:name":"Billings Pumping & Septic Svc",
    "wof:placetype":"venue"
},
  "geometry": {"coordinates":[-82.731971,28.108257],"type":"Point"}
}