{
  "type": "Feature",
  "properties": {
    "iso:country":"US",
    "sg:address":"3815 Calvary Ct",
    "sg:city":"Middleburg",
    "sg:classifiers":[
        {
            "category":"Retail",
            "subcategory":"Repair Shop",
            "type":"Services"
        }
    ],
    "sg:phone":"+1 904 291 0735",
    "sg:postcode":"32068",
    "sg:province":"FL",
    "sg:tags":[
        "equipment",
        "telephone",
        "system"
    ],
    "wof:name":"Command Telephone Svc",
    "wof:placetype":"venue"
},
  "geometry": {"coordinates":[-81.867026,30.139214],"type":"Point"}
}