{
  "type": "Feature",
  "properties": {
    "iso:country":"US",
    "sg:address":"1802 US Hwy 19",
    "sg:city":"Holiday",
    "sg:classifiers":[
        {
            "category":"Restaurant",
            "type":"Food & Drink"
        }
    ],
    "sg:phone":"+1 727 938 1664",
    "sg:postcode":"34691",
    "sg:province":"FL",
    "sg:tags":[
        "shop",
        "eating",
        "beauty",
        "travel",
        "agency",
        "bu",
        "tour",
        "operator"
    ],
    "wof:name":"Great Subs & More",
    "wof:placetype":"venue"
},
  "geometry": {"coordinates":[-82.739998,28.187874],"type":"Point"}
}