{
  "type": "Feature",
  "properties": {
    "addr:full":"209 Van Gogh Cir Brandon FL 33511",
    "addr:housenumber":"209",
    "addr:postcode":"33511",
    "addr:street":"Van Gogh Cir",
    "iso:country":"US",
    "sg:address":"209 Van Gogh Cir",
    "sg:city":"Brandon",
    "sg:classifiers":[
        {
            "category":"Cinema",
            "subcategory":"Movie Rental",
            "type":"Entertainment"
        }
    ],
    "sg:phone":"+1 813 685 0391",
    "sg:postcode":"33511",
    "sg:province":"FL",
    "sg:tags":[
        "leasing",
        "video",
        "disc",
        "tape"
    ],
    "wof:name":"Seven Star Food & Video",
    "wof:placetype":"venue"
},
  "geometry": {"coordinates":[-82.28996600000001,27.896048],"type":"Point"}
}