{
  "type": "Feature",
  "properties": {
    "addr:full":"8703 NW 38th Dr Pompano Beach FL 33065",
    "addr:housenumber":"8703",
    "addr:postcode":"33065",
    "addr:street":"Nw 38Th Dr",
    "iso:country":"US",
    "sg:address":"8703 NW 38th Dr",
    "sg:city":"Pompano Beach",
    "sg:classifiers":[
        {
            "category":"Wholesale",
            "subcategory":"Durable Goods & Equipment",
            "type":"Manufacturing & Wholesale Goods"
        }
    ],
    "sg:phone":"+1 954 753 1295",
    "sg:postcode":"33065",
    "sg:province":"FL",
    "wof:name":"Giovanne Supplements Co",
    "wof:placetype":"venue"
},
  "geometry": {"coordinates":[-80.250148,26.277248],"type":"Point"}
}