{
  "type": "Feature",
  "properties": {
    "iso:country":"US",
    "sg:address":"2032 Thomasville Rd",
    "sg:city":"Tallahassee",
    "sg:classifiers":[
        {
            "category":"Real Estate",
            "subcategory":"Real Estate Services",
            "type":"Services"
        },
        {
            "category":"Banks & Credit Unions",
            "subcategory":"Financial Services",
            "type":"Services"
        }
    ],
    "sg:phone":"+1 850 681 0080",
    "sg:postcode":"32308",
    "sg:province":"FL",
    "sg:tags":[
        "loan",
        "processing"
    ],
    "wof:name":"Saint Johns Mortgage",
    "wof:placetype":"venue"
},
  "geometry": {"coordinates":[-84.267393,30.468685],"type":"Point"}
}