{
  "type": "Feature",
  "properties": {
    "addr:full":"205 E Graves Ave Orange City FL 32763",
    "addr:housenumber":"205",
    "addr:postcode":"32763",
    "addr:street":"E Graves Ave",
    "iso:country":"US",
    "sg:address":"205 E Graves Ave",
    "sg:city":"Orange City",
    "sg:classifiers":[
        {
            "category":"Government",
            "subcategory":"Office",
            "type":"Public Place"
        }
    ],
    "sg:phone":"+1 386 775 5400",
    "sg:postcode":"32763",
    "sg:province":"FL",
    "sg:tags":[
        "city",
        "village"
    ],
    "wof:name":"Orange City City Hall",
    "wof:placetype":"venue"
},
  "geometry": {"coordinates":[-81.29629799999999,28.948773],"type":"Point"}
}