{
  "type": "Feature",
  "properties": {
    "iso:country":"US",
    "sg:address":"821 Donald Ross Rd",
    "sg:city":"Juno Beach",
    "sg:classifiers":[
        {
            "category":"Retail",
            "subcategory":"Laundry & Dry Cleaning",
            "type":"Services"
        }
    ],
    "sg:phone":"+1 561 622 6581",
    "sg:postcode":"33410",
    "sg:province":"FL",
    "sg:tags":[
        "cleaners"
    ],
    "wof:name":"LA Mer Cleaners",
    "wof:placetype":"venue"
},
  "geometry": {"coordinates":[-80.05929399999999,26.881772],"type":"Point"}
}