{
  "type": "Feature",
  "properties": {
    "iso:country":"US",
    "sg:address":"1740 4th St S",
    "sg:city":"St Petersburg",
    "sg:classifiers":[
        {
            "category":"Restaurant",
            "type":"Food & Drink"
        }
    ],
    "sg:phone":"+1 727 898 7407",
    "sg:postcode":"33701",
    "sg:province":"FL",
    "sg:tags":[
        "eating"
    ],
    "wof:name":"Mini Chinese Restaurant",
    "wof:placetype":"venue"
},
  "geometry": {"coordinates":[-82.638419,27.752727],"type":"Point"}
}