{
  "type": "Feature",
  "properties": {
    "addr:full":"686 Bald Eagle Dr Marco Island FL 34145",
    "addr:housenumber":"686",
    "addr:postcode":"34145",
    "addr:street":"Bald Eagle Dr",
    "iso:country":"US",
    "sg:address":"686 Bald Eagle Dr",
    "sg:city":"Marco Island",
    "sg:classifiers":[
        {
            "category":"Sports & Exercise",
            "subcategory":"Gym",
            "type":"Entertainment"
        }
    ],
    "sg:phone":"+1 239 394 8104",
    "sg:postcode":"34145",
    "sg:province":"FL",
    "sg:tags":[
        "club",
        "health",
        "studio",
        "gymnasium"
    ],
    "wof:name":"Club Marco New Age Fitness",
    "wof:placetype":"venue"
},
  "geometry": {"coordinates":[-81.724987,25.954651],"type":"Point"}
}