{
  "type": "Feature",
  "properties": {
    "addr:full":"455 N Alafaya Trl Orlando FL 32828",
    "addr:housenumber":"455",
    "addr:postcode":"32828",
    "addr:street":"N Alafaya Trl",
    "iso:country":"US",
    "sg:address":"455 N Alafaya Trl",
    "sg:city":"Orlando",
    "sg:classifiers":[
        {
            "category":"Restaurant",
            "type":"Food & Drink"
        }
    ],
    "sg:phone":"+1 407 207 2088",
    "sg:postcode":"32828",
    "sg:province":"FL",
    "sg:tags":[
        "eating"
    ],
    "wof:name":"Subway",
    "wof:placetype":"venue"
},
  "geometry": {"coordinates":[-81.204633,28.5518],"type":"Point"}
}