{
  "type": "Feature",
  "properties": {
    "iso:country":"US",
    "sg:address":"6310 Blountstown Hwy",
    "sg:city":"Tallahassee",
    "sg:classifiers":[
        {
            "category":"Shopping",
            "subcategory":"Bicycles & Sporting Goods",
            "type":"Retail Goods"
        }
    ],
    "sg:phone":"+1 850 574 3909",
    "sg:postcode":"32310",
    "sg:province":"FL",
    "sg:tags":[
        "tackle",
        "fishing"
    ],
    "wof:name":"Wayside Farm General Store 2",
    "wof:placetype":"venue"
},
  "geometry": {"coordinates":[-84.38455500000001,30.439027],"type":"Point"}
}