{
  "type": "Feature",
  "properties": {
    "iso:country":"US",
    "sg:address":"4873 Roosevelt Blvd",
    "sg:city":"Jacksonville",
    "sg:classifiers":[
        {
            "category":"Wholesale",
            "subcategory":"Non-durable Goods",
            "type":"Manufacturing & Wholesale Goods"
        }
    ],
    "sg:phone":"+1 904 387 5095",
    "sg:postcode":"32210",
    "sg:province":"FL",
    "wof:name":"Horizon Airships",
    "wof:placetype":"venue"
},
  "geometry": {"coordinates":[-81.70795699999999,30.266095],"type":"Point"}
}