{
  "type": "Feature",
  "properties": {
    "addr:full":"6417 Gall Blvd Zephyrhills FL 33542",
    "addr:housenumber":"6417",
    "addr:postcode":"33542",
    "addr:street":"Gall Blvd",
    "iso:country":"US",
    "sg:address":"6417 Gall Blvd",
    "sg:city":"Zephyrhills",
    "sg:classifiers":[
        {
            "category":"Shopping",
            "type":"Retail Goods"
        }
    ],
    "sg:phone":"+1 813 788 6879",
    "sg:postcode":"33542",
    "sg:province":"FL",
    "sg:tags":[
        "surgical",
        "merchandise",
        "mfg"
    ],
    "wof:name":"Zephyrhills Brace & Limb Inc",
    "wof:placetype":"venue"
},
  "geometry": {"coordinates":[-82.188289,28.251712],"type":"Point"}
}