{
  "type": "Feature",
  "properties": {
    "addr:full":"6108 Village Oaks Dr Pensacola FL 32504",
    "addr:housenumber":"6108",
    "addr:postcode":"32504",
    "addr:street":"Village Oaks Dr",
    "iso:country":"US",
    "sg:address":"6108 Village Oaks Dr",
    "sg:city":"Pensacola",
    "sg:classifiers":[
        {
            "category":"Professional",
            "subcategory":"Computer Services",
            "type":"Services"
        }
    ],
    "sg:phone":"+1 850 479 3966",
    "sg:postcode":"32504",
    "sg:province":"FL",
    "sg:tags":[
        "internet"
    ],
    "sg:website":"www.ksinc.net",
    "wof:name":"Kaizen Solutions",
    "wof:placetype":"venue"
},
  "geometry": {"coordinates":[-87.226038,30.489132],"type":"Point"}
}