{
  "type": "Feature",
  "properties": {
    "addr:full":"403 Alcazar Ave Altamonte Spgs FL 32714",
    "addr:housenumber":"403",
    "addr:postcode":"32714",
    "addr:street":"Alcazar Ave;Spgs",
    "iso:country":"US",
    "sg:address":"403 Alcazar Ave",
    "sg:city":"Altamonte Spgs",
    "sg:classifiers":[
        {
            "category":"Shopping",
            "type":"Retail Goods"
        }
    ],
    "sg:phone":"+1 407 682 3792",
    "sg:postcode":"32714",
    "sg:province":"FL",
    "sg:tags":[
        "cosmetic",
        "perfume"
    ],
    "wof:name":"Beauti Control Cosmetics",
    "wof:placetype":"venue"
},
  "geometry": {"coordinates":[-81.41510700000001,28.671291],"type":"Point"}
}