{
  "type": "Feature",
  "properties": {
    "iso:country":"US",
    "sg:address":"3920 N Davis Hwy",
    "sg:city":"Pensacola",
    "sg:classifiers":[
        {
            "category":"Shopping",
            "type":"Retail Goods"
        }
    ],
    "sg:phone":"+1 850 435 1575",
    "sg:postcode":"32503",
    "sg:province":"FL",
    "sg:tags":[
        "chemical",
        "equipment",
        "swimming",
        "pool",
        "supply"
    ],
    "wof:name":"Family Pool & Spa Centers",
    "wof:placetype":"venue"
},
  "geometry": {"coordinates":[-87.22212500000001,30.454054],"type":"Point"}
}