{
  "type": "Feature",
  "properties": {
    "iso:country":"US",
    "sg:address":"344 Pinestraw Cir",
    "sg:city":"Altamonte Springs",
    "sg:classifiers":[
        {
            "category":"Professional",
            "type":"Services"
        }
    ],
    "sg:phone":"+1 407 880 2363",
    "sg:postcode":"32714",
    "sg:province":"FL",
    "wof:name":"Rebecca Menegat",
    "wof:placetype":"venue"
},
  "geometry": {"coordinates":[-81.42992,28.655864],"type":"Point"}
}