{
  "type": "Feature",
  "properties": {
    "iso:country":"US",
    "sg:address":"790 72nd Ave N",
    "sg:city":"Saint Petersburg",
    "sg:classifiers":[
        {
            "category":"Building & Trades",
            "subcategory":"Landscaping Services",
            "type":"Services"
        }
    ],
    "sg:phone":"+1 727 521 2251",
    "sg:postcode":"33702",
    "sg:province":"FL",
    "wof:name":"Champion Lawn Service",
    "wof:placetype":"venue"
},
  "geometry": {"coordinates":[-82.64322300000001,27.837009],"type":"Point"}
}