{
  "type": "Feature",
  "properties": {
    "iso:country":"US",
    "sg:address":"1919 Blanding Blvd",
    "sg:city":"Jacksonville",
    "sg:classifiers":[
        {
            "category":"Professional",
            "subcategory":"Lawyer & Legal Services",
            "type":"Services"
        }
    ],
    "sg:phone":"+1 904 387 0300",
    "sg:postcode":"32210",
    "sg:province":"FL",
    "wof:name":"Richard M Tierney",
    "wof:placetype":"venue"
},
  "geometry": {"coordinates":[-81.725356,30.28373],"type":"Point"}
}