{
  "type": "Feature",
  "properties": {
    "iso:country":"US",
    "sg:address":"7511 N 56th St",
    "sg:city":"Tampa",
    "sg:classifiers":[
        {
            "category":"Restaurant",
            "type":"Food & Drink"
        }
    ],
    "sg:phone":"+1 813 985 3449",
    "sg:postcode":"33617",
    "sg:province":"FL",
    "wof:name":"Down To The Bone Bar-B-Que",
    "wof:placetype":"venue"
},
  "geometry": {"coordinates":[-82.393389,28.017115],"type":"Point"}
}