{
  "type": "Feature",
  "properties": {
    "addr:full":"1419 NE Jensen Beach Blvd Jensen Beach FL 34957",
    "addr:housenumber":"1419",
    "addr:postcode":"34957",
    "addr:street":"Ne Jensen Beach Blvd",
    "iso:country":"US",
    "sg:address":"1419 NE Jensen Beach Blvd",
    "sg:city":"Jensen Beach",
    "sg:classifiers":[
        {
            "category":"Restaurant",
            "type":"Food & Drink"
        }
    ],
    "sg:menulink":"http://www.allmenus.com/fl/stuart/30562-new-england-fish-market--restaurant/menu/",
    "sg:phone":"+1 772 334 7328",
    "sg:postcode":"34957",
    "sg:province":"FL",
    "sg:tags":[
        "seafood",
        "american"
    ],
    "wof:name":"New England Fish Market & Restaurant",
    "wof:placetype":"venue"
},
  "geometry": {"coordinates":[-80.23409599999999,27.244279],"type":"Point"}
}