{
  "type": "Feature",
  "properties": {
    "iso:country":"US",
    "sg:address":"2120 King St",
    "sg:city":"Cocoa",
    "sg:classifiers":[
        {
            "category":"Building & Trades",
            "subcategory":"Construction",
            "type":"Services"
        }
    ],
    "sg:phone":"+1 321 639 9429",
    "sg:postcode":"32926",
    "sg:province":"FL",
    "sg:tags":[
        "handyman"
    ],
    "wof:name":"G M Poston Handyman",
    "wof:placetype":"venue"
},
  "geometry": {"coordinates":[-80.763694,28.355769],"type":"Point"}
}