{
  "type": "Feature",
  "properties": {
    "iso:country":"US",
    "sg:address":"726 Crandon Blvd",
    "sg:city":"Key Biscayne",
    "sg:classifiers":[
        {
            "category":"Restaurant",
            "type":"Food & Drink"
        }
    ],
    "sg:menulink":"http://www.allmenus.com/fl/key-biscayne/50669-chicken-kitchen/menu/",
    "sg:phone":"+1 305 365 6662",
    "sg:postcode":"33149",
    "sg:province":"FL",
    "sg:tags":[
        "american",
        "wing"
    ],
    "wof:name":"Chicken Kitchen",
    "wof:placetype":"venue"
},
  "geometry": {"coordinates":[-80.16376700000001,25.687784],"type":"Point"}
}