{
  "type": "Feature",
  "properties": {
    "addr:full":"4530 Deer Lodge Rd New Port Richey FL 34655",
    "addr:housenumber":"4530",
    "addr:postcode":"34655",
    "addr:street":"Deer Lodge Rd",
    "iso:country":"US",
    "sg:address":"4530 Deer Lodge Rd",
    "sg:city":"New Port Richey",
    "sg:classifiers":[
        {
            "category":"Manufacturing",
            "subcategory":"Tools & Machinery",
            "type":"Manufacturing & Wholesale Goods"
        }
    ],
    "sg:phone":"+1 727 372 5738",
    "sg:postcode":"34655",
    "sg:province":"FL",
    "sg:tags":[
        "devices",
        "mfg"
    ],
    "wof:name":"GE",
    "wof:placetype":"venue"
},
  "geometry": {"coordinates":[-82.656851,28.234098],"type":"Point"}
}