{
  "type": "Feature",
  "properties": {
    "iso:country":"US",
    "sg:address":"23324 Singer Ln",
    "sg:city":"Brooksville",
    "sg:classifiers":[
        {
            "category":"Wholesale",
            "subcategory":"Plants",
            "type":"Manufacturing & Wholesale Goods"
        }
    ],
    "sg:phone":"+1 352 799 0676",
    "sg:postcode":"34601",
    "sg:province":"FL",
    "sg:tags":[
        "nursery",
        "tree"
    ],
    "wof:name":"Brooksville Palms Inc",
    "wof:placetype":"venue"
},
  "geometry": {"coordinates":[-82.34731499999999,28.537318],"type":"Point"}
}