{
  "type": "Feature",
  "properties": {
    "iso:country":"US",
    "sg:address":"9635 Rebel Rd",
    "sg:city":"Pensacola",
    "sg:classifiers":[
        {
            "category":"Building & Trades",
            "subcategory":"Construction",
            "type":"Services"
        }
    ],
    "sg:phone":"+1 850 944 7221",
    "sg:postcode":"32526",
    "sg:province":"FL",
    "sg:tags":[
        "hanging",
        "contractor"
    ],
    "wof:name":"J&J Painting",
    "wof:placetype":"venue"
},
  "geometry": {"coordinates":[-87.388932,30.535788],"type":"Point"}
}