{
  "type": "Feature",
  "properties": {
    "iso:country":"US",
    "sg:address":"1521 Alton Rd",
    "sg:city":"Miami Beach",
    "sg:classifiers":[
        {
            "category":"Shopping",
            "subcategory":"Hobbies, Toys, & Games",
            "type":"Retail Goods"
        }
    ],
    "sg:phone":"+1 786 206 9020",
    "sg:postcode":"33139",
    "sg:province":"FL",
    "sg:tags":[
        "craft",
        "indian"
    ],
    "wof:name":"Dreamcatchercom Inc",
    "wof:placetype":"venue"
},
  "geometry": {"coordinates":[-80.14106099999999,25.787835],"type":"Point"}
}