{
  "type": "Feature",
  "properties": {
    "iso:country":"US",
    "sg:address":"1314 Sumter St",
    "sg:city":"Leesburg",
    "sg:classifiers":[
        {
            "category":"Building & Trades",
            "subcategory":"Equipment Rental",
            "type":"Services"
        }
    ],
    "sg:phone":"+1 352 728 2033",
    "sg:postcode":"34748",
    "sg:province":"FL",
    "sg:tags":[
        "medical"
    ],
    "wof:name":"Rotech",
    "wof:placetype":"venue"
},
  "geometry": {"coordinates":[-81.886279,28.805372],"type":"Point"}
}