{
  "type": "Feature",
  "properties": {
    "addr:full":"2233 Murphy Ct North Port FL 34289",
    "addr:housenumber":"2233",
    "addr:postcode":"34289",
    "addr:street":"Murphy Ct",
    "iso:country":"US",
    "sg:address":"2233 Murphy Ct",
    "sg:city":"North Port",
    "sg:classifiers":[
        {
            "category":"Home & Garden",
            "subcategory":"Building Materials",
            "type":"Retail Goods"
        },
        {
            "category":"Manufacturing",
            "subcategory":"Building Materials",
            "type":"Manufacturing & Wholesale Goods"
        }
    ],
    "sg:phone":"+1 941 429 1212",
    "sg:postcode":"34289",
    "sg:province":"FL",
    "sg:tags":[
        "member",
        "structural",
        "wood",
        "mfg"
    ],
    "wof:name":"Raymond Building Supply Corp",
    "wof:placetype":"venue"
},
  "geometry": {"coordinates":[-82.158995,27.078644],"type":"Point"}
}