{
  "type": "Feature",
  "properties": {
    "addr:full":"4747 Azalea Dr New Port Richey FL 34652",
    "addr:housenumber":"4747",
    "addr:postcode":"34652",
    "addr:street":"Azalea Dr",
    "iso:country":"US",
    "sg:address":"4747 Azalea Dr",
    "sg:city":"New Port Richey",
    "sg:classifiers":[
        {
            "category":"Professional",
            "type":"Services"
        }
    ],
    "sg:phone":"+1 727 845 5288",
    "sg:postcode":"34652",
    "sg:province":"FL",
    "wof:name":"Imperial Embassy Condo Two",
    "wof:placetype":"venue"
},
  "geometry": {"coordinates":[-82.72667199999999,28.228124],"type":"Point"}
}