{
  "type": "Feature",
  "properties": {
    "addr:full":"30549 Lettingwell Cir Wesley Chapel FL 33543",
    "addr:postcode":"30549;33543",
    "addr:street":"Lettingwell Cir",
    "iso:country":"US",
    "sg:address":"30549 Lettingwell Cir",
    "sg:city":"Wesley Chapel",
    "sg:classifiers":[
        {
            "category":"Professional",
            "subcategory":"Computer Services",
            "type":"Services"
        }
    ],
    "sg:phone":"+1 813 994 5995",
    "sg:postcode":"33543",
    "sg:province":"FL",
    "sg:tags":[
        "consultant",
        "designer",
        "datum",
        "system"
    ],
    "wof:name":"Agricultural & Business Svc",
    "wof:placetype":"venue"
},
  "geometry": {"coordinates":[-82.31647700000001,28.181049],"type":"Point"}
}