{
  "type": "Feature",
  "properties": {
    "iso:country":"US",
    "sg:address":"5318 Black Pine Dr",
    "sg:city":"Tampa",
    "sg:classifiers":[
        {
            "category":"Shopping",
            "subcategory":"Computers & Home Electronics",
            "type":"Retail Goods"
        }
    ],
    "sg:phone":"+1 813 264 1274",
    "sg:postcode":"33624",
    "sg:province":"FL",
    "wof:name":"Happy Mac",
    "wof:placetype":"venue"
},
  "geometry": {"coordinates":[-82.53609899999999,28.057661],"type":"Point"}
}