{
  "type": "Feature",
  "properties": {
    "addr:full":"6920 Benjamin Rd Tampa FL 33634",
    "addr:housenumber":"6920",
    "addr:postcode":"33634",
    "addr:street":"Benjamin Rd",
    "iso:country":"US",
    "sg:address":"6920 Benjamin Rd",
    "sg:city":"Tampa",
    "sg:classifiers":[
        {
            "category":"Building & Trades",
            "subcategory":"Construction",
            "type":"Services"
        }
    ],
    "sg:phone":"+1 813 884 9289",
    "sg:postcode":"33634",
    "sg:province":"FL",
    "sg:tags":[
        "paving",
        "contractor"
    ],
    "wof:name":"Art Stoltenberg Paving Co",
    "wof:placetype":"venue"
},
  "geometry": {"coordinates":[-82.54201500000001,28.011938],"type":"Point"}
}