{
  "type": "Feature",
  "properties": {
    "addr:full":"16616 Saddle Club Rd Fort Lauderdale FL 33326",
    "addr:housenumber":"16616",
    "addr:postcode":"33326",
    "addr:street":"Saddle Club Rd",
    "iso:country":"US",
    "sg:address":"16616 Saddle Club Rd",
    "sg:city":"Fort Lauderdale",
    "sg:classifiers":[
        {
            "category":"Insurance",
            "subcategory":"Insurance Agent",
            "type":"Services"
        }
    ],
    "sg:phone":"+1 954 473 4700",
    "sg:postcode":"33326",
    "sg:province":"FL",
    "wof:name":"Allstate",
    "wof:placetype":"venue"
},
  "geometry": {"coordinates":[-80.375072,26.115595],"type":"Point"}
}