{
  "type": "Feature",
  "properties": {
    "iso:country":"US",
    "sg:address":"4721 E Co Hwy 30A",
    "sg:city":"Santa Rosa Beach",
    "sg:classifiers":[
        {
            "category":"Shopping",
            "subcategory":"Hobbies, Toys, & Games",
            "type":"Retail Goods"
        }
    ],
    "sg:phone":"+1 850 231 0911",
    "sg:postcode":"32459",
    "sg:province":"FL",
    "wof:name":"House Of Angels",
    "wof:placetype":"venue"
},
  "geometry": {"coordinates":[-86.09882,30.312244],"type":"Point"}
}