{
  "type": "Feature",
  "properties": {
    "iso:country":"US",
    "sg:address":"3600 W Sovereign Path",
    "sg:city":"Lecanto",
    "sg:classifiers":[
        {
            "category":"Government",
            "subcategory":"Office",
            "type":"Public Place"
        }
    ],
    "sg:phone":"+1 352 527 5210",
    "sg:postcode":"34461",
    "sg:province":"FL",
    "sg:tags":[
        "educational",
        "program",
        "administrative",
        "dev"
    ],
    "wof:name":"Citrus Cnty Bd Cnty Cmmssoners",
    "wof:placetype":"venue"
},
  "geometry": {"coordinates":[-82.488619,28.824011],"type":"Point"}
}