{
  "type": "Feature",
  "properties": {
    "iso:country":"US",
    "sg:address":"9453 Aegean Dr",
    "sg:city":"Boca Raton",
    "sg:classifiers":[
        {
            "category":"Cinema",
            "subcategory":"Movie Rental",
            "type":"Entertainment"
        }
    ],
    "sg:phone":"+1 561 353 3353",
    "sg:postcode":"33496",
    "sg:province":"FL",
    "sg:tags":[
        "leasing",
        "video",
        "disc",
        "tape"
    ],
    "wof:name":"Accurate Video Svc",
    "wof:placetype":"venue"
},
  "geometry": {"coordinates":[-80.19537,26.395811],"type":"Point"}
}