{
  "type": "Feature",
  "properties": {
    "iso:country":"US",
    "sg:address":"4421 Gunn Hwy",
    "sg:city":"Tampa",
    "sg:classifiers":[
        {
            "category":"Autos & Motor Vehicles",
            "subcategory":"Auto Supplies",
            "type":"Retail Goods"
        }
    ],
    "sg:phone":"+1 813 960 9433",
    "sg:postcode":"33618",
    "sg:province":"FL",
    "sg:tags":[
        "tire"
    ],
    "wof:name":"M B Tires",
    "wof:placetype":"venue"
},
  "geometry": {"coordinates":[-82.516159,28.04632],"type":"Point"}
}