{
  "type": "Feature",
  "properties": {
    "addr:full":"2501 27th Ave Vero Beach FL 32960",
    "addr:housenumber":"2501",
    "addr:postcode":"32960",
    "addr:street":"27Th Ave",
    "iso:country":"US",
    "sg:address":"2501 27th Ave",
    "sg:city":"Vero Beach",
    "sg:classifiers":[
        {
            "category":"Social Services",
            "type":"Services"
        }
    ],
    "sg:phone":"+1 772 563 0505",
    "sg:postcode":"32960",
    "sg:province":"FL",
    "sg:tags":[
        "organization",
        "welfare"
    ],
    "wof:name":"Parkinson/Alzheimer Support",
    "wof:placetype":"venue"
},
  "geometry": {"coordinates":[-80.41372,27.64588],"type":"Point"}
}