{
  "type": "Feature",
  "properties": {
    "iso:country":"US",
    "sg:address":"914 SE 14th Ter",
    "sg:city":"Deerfield Beach",
    "sg:classifiers":[
        {
            "category":"Professional",
            "subcategory":"Business Services",
            "type":"Services"
        }
    ],
    "sg:phone":"+1 954 263 4927",
    "sg:postcode":"33441",
    "sg:province":"FL",
    "wof:name":"Gerard Arsenault Pool Svc",
    "wof:placetype":"venue"
},
  "geometry": {"coordinates":[-80.08351399999999,26.306116],"type":"Point"}
}