{
  "type": "Feature",
  "properties": {
    "iso:country":"US",
    "sg:address":"138 Miracle Strip Pkwy",
    "sg:city":"Fort Walton Bch",
    "sg:classifiers":[
        {
            "category":"Restaurant",
            "type":"Food & Drink"
        }
    ],
    "sg:phone":"+1 850 244 5515",
    "sg:postcode":"32548",
    "sg:province":"FL",
    "wof:name":"Barley's",
    "wof:placetype":"venue"
},
  "geometry": {"coordinates":[-86.608096,30.403724],"type":"Point"}
}