{
  "type": "Feature",
  "properties": {
    "addr:full":"3414 15th St W Lehigh Acres FL 33971",
    "addr:housenumber":"3414",
    "addr:postcode":"33971",
    "addr:street":"15Th St W",
    "iso:country":"US",
    "sg:address":"3414 15th St W",
    "sg:city":"Lehigh Acres",
    "sg:classifiers":[
        {
            "category":"Organizations",
            "subcategory":"Religious Organization",
            "type":"Services"
        }
    ],
    "sg:phone":"+1 239 694 1359",
    "sg:postcode":"33971",
    "sg:province":"FL",
    "sg:tags":[
        "church"
    ],
    "sg:website":"www.morningstarbaptistchurch.net",
    "wof:name":"Morningstar Baptist Church",
    "wof:placetype":"venue"
},
  "geometry": {"coordinates":[-81.687558,26.62677],"type":"Point"}
}