{
  "type": "Feature",
  "properties": {
    "addr:full":"7406 Fullerton St Jacksonville FL 32256",
    "addr:housenumber":"7406",
    "addr:postcode":"32256",
    "addr:street":"Fullerton St",
    "iso:country":"US",
    "sg:address":"7406 Fullerton St",
    "sg:city":"Jacksonville",
    "sg:classifiers":[
        {
            "category":"Professional",
            "subcategory":"Engineering",
            "type":"Services"
        }
    ],
    "sg:phone":"+1 904 363 6100",
    "sg:postcode":"32256",
    "sg:province":"FL",
    "sg:tags":[
        "engineer"
    ],
    "sg:website":"www.pbsj.com",
    "wof:name":"PBS & J",
    "wof:placetype":"venue"
},
  "geometry": {"coordinates":[-81.549311,30.188575],"type":"Point"}
}