{
  "type": "Feature",
  "properties": {
    "addr:full":"8855 SW 107th Ave Miami FL 33173",
    "addr:housenumber":"8855",
    "addr:postcode":"33173",
    "addr:street":"Sw 107Th Ave",
    "iso:country":"US",
    "sg:address":"8855 SW 107th Ave",
    "sg:city":"Miami",
    "sg:classifiers":[
        {
            "category":"Food & Beverages",
            "subcategory":"Specialty",
            "type":"Retail Goods"
        }
    ],
    "sg:phone":"+1 305 596 4533",
    "sg:postcode":"33173",
    "sg:province":"FL",
    "sg:tags":[
        "health",
        "store"
    ],
    "wof:name":"Vitamin Nutrition Depot",
    "wof:placetype":"venue"
},
  "geometry": {"coordinates":[-80.36706,25.684037],"type":"Point"}
}