{
  "type": "Feature",
  "properties": {
    "iso:country":"US",
    "sg:address":"1055 E 15th St",
    "sg:city":"Hialeah",
    "sg:classifiers":[
        {
            "category":"Manufacturing",
            "subcategory":"Apparel",
            "type":"Manufacturing & Wholesale Goods"
        }
    ],
    "sg:phone":"+1 305 885 8148",
    "sg:postcode":"33010",
    "sg:province":"FL",
    "sg:tags":[
        "contractor",
        "mfg",
        "clothing",
        "sewing",
        "man"
    ],
    "wof:name":"Leonora Fashions Inc",
    "wof:placetype":"venue"
},
  "geometry": {"coordinates":[-80.26076999999999,25.836452],"type":"Point"}
}