{
  "type": "Feature",
  "properties": {
    "addr:full":"12472 Mariah Ann Ct S Jacksonville FL 32225",
    "addr:housenumber":"12472",
    "addr:postcode":"32225",
    "addr:street":"Mariah Ann Ct",
    "iso:country":"US",
    "sg:address":"12472 Mariah Ann Ct S",
    "sg:city":"Jacksonville",
    "sg:classifiers":[
        {
            "category":"Freight",
            "type":"Transportation"
        }
    ],
    "sg:phone":"+1 904 221 0935",
    "sg:postcode":"32225",
    "sg:province":"FL",
    "sg:tags":[
        "operator",
        "local",
        "trucking"
    ],
    "wof:name":"Double Dump Delivery",
    "wof:placetype":"venue"
},
  "geometry": {"coordinates":[-81.472398,30.355753],"type":"Point"}
}