{
  "type": "Feature",
  "properties": {
    "addr:full":"1177 3rd St S Naples FL 34102",
    "addr:housenumber":"1177",
    "addr:postcode":"34102",
    "addr:street":"3Rd St S",
    "iso:country":"US",
    "sg:address":"1177 3rd St S",
    "sg:city":"Naples",
    "sg:classifiers":[
        {
            "category":"Restaurant",
            "type":"Food & Drink"
        }
    ],
    "sg:phone":"+1 239 435 9121",
    "sg:postcode":"34102",
    "sg:province":"FL",
    "sg:tags":[
        "eating"
    ],
    "sg:website":"www.campiello.damico.com",
    "wof:name":"Empori",
    "wof:placetype":"venue"
},
  "geometry": {"coordinates":[-81.801884,26.132679],"type":"Point"}
}