{
  "type": "Feature",
  "properties": {
    "addr:full":"2374 Ali Baba Ave Opa Locka FL 33054",
    "addr:housenumber":"2374",
    "addr:postcode":"33054",
    "addr:street":"Ali Baba Ave;Locka",
    "iso:country":"US",
    "sg:address":"2374 Ali Baba Ave",
    "sg:city":"Opa Locka",
    "sg:classifiers":[
        {
            "category":"Retail",
            "subcategory":"Auto Repair",
            "type":"Services"
        }
    ],
    "sg:phone":"+1 305 769 1900",
    "sg:postcode":"33054",
    "sg:province":"FL",
    "wof:name":"Ronald Car Care",
    "wof:placetype":"venue"
},
  "geometry": {"coordinates":[-80.239717,25.906927],"type":"Point"}
}