{
  "type": "Feature",
  "properties": {
    "addr:full":"7533 Garfield St Hollywood FL 33024",
    "addr:housenumber":"7533",
    "addr:postcode":"33024",
    "addr:street":"Garfield St",
    "iso:country":"US",
    "sg:address":"7533 Garfield St",
    "sg:city":"Hollywood",
    "sg:classifiers":[
        {
            "category":"Building & Trades",
            "subcategory":"Electrical",
            "type":"Services"
        }
    ],
    "sg:phone":"+1 954 961 2091",
    "sg:postcode":"33024",
    "sg:province":"FL",
    "sg:tags":[
        "electrical",
        "contractor"
    ],
    "wof:name":"TQ Electrical Contractors",
    "wof:placetype":"venue"
},
  "geometry": {"coordinates":[-80.239588,26.019727],"type":"Point"}
}