{
  "type": "Feature",
  "properties": {
    "iso:country":"US",
    "sg:address":"4 Signal Ave",
    "sg:city":"Ormond Beach",
    "sg:classifiers":[
        {
            "category":"Wholesale",
            "subcategory":"Durable Goods & Equipment",
            "type":"Manufacturing & Wholesale Goods"
        }
    ],
    "sg:phone":"+1 386 673 8900",
    "sg:postcode":"32174",
    "sg:province":"FL",
    "sg:tags":[
        "importer"
    ],
    "wof:name":"Broadway Limited Imports",
    "wof:placetype":"venue"
},
  "geometry": {"coordinates":[-81.11479,29.291804],"type":"Point"}
}