{
  "type": "Feature",
  "properties": {
    "addr:full":"11940 Pines Blvd Hollywood FL 33026",
    "addr:housenumber":"11940",
    "addr:postcode":"33026",
    "addr:street":"Pines Blvd",
    "iso:country":"US",
    "sg:address":"11940 Pines Blvd",
    "sg:city":"Hollywood",
    "sg:classifiers":[
        {
            "category":"Home & Garden",
            "subcategory":"Home Furnishings",
            "type":"Retail Goods"
        }
    ],
    "sg:phone":"+1 954 447 7079",
    "sg:postcode":"33026",
    "sg:province":"FL",
    "sg:tags":[
        "linen",
        "bedding",
        "bath",
        "accessory"
    ],
    "wof:name":"Linens n Things",
    "wof:placetype":"venue"
},
  "geometry": {"coordinates":[-80.307632,26.007769],"type":"Point"}
}