{
  "type": "Feature",
  "properties": {
    "iso:country":"US",
    "sg:address":"516 S Tyndall Pkwy",
    "sg:city":"Panama City",
    "sg:classifiers":[
        {
            "category":"Professional",
            "subcategory":"Lawyer & Legal Services",
            "type":"Services"
        }
    ],
    "sg:phone":"+1 850 763 9489",
    "sg:postcode":"32404",
    "sg:province":"FL",
    "sg:tags":[
        "attorney"
    ],
    "wof:name":"Robert H Conway Sr",
    "wof:placetype":"venue"
},
  "geometry": {"coordinates":[-85.59133,30.136718],"type":"Point"}
}