{
  "type": "Feature",
  "properties": {
    "addr:full":"7731 Lake Nellie Rd Clermont FL 34714",
    "addr:housenumber":"7731",
    "addr:postcode":"34714",
    "addr:street":"Lake Nellie Rd",
    "iso:country":"US",
    "sg:address":"7731 Lake Nellie Rd",
    "sg:city":"Clermont",
    "sg:classifiers":[
        {
            "category":"Education",
            "subcategory":"Special Training",
            "type":"Public Place"
        }
    ],
    "sg:phone":"+1 352 394 6605",
    "sg:postcode":"34714",
    "sg:province":"FL",
    "sg:tags":[
        "educational"
    ],
    "wof:name":"Astrological Research Guild",
    "wof:placetype":"venue"
},
  "geometry": {"coordinates":[-81.75784299999999,28.46142],"type":"Point"}
}