{
  "type": "Feature",
  "properties": {
    "addr:full":"3965 Investment Ln Riviera Beach FL 33404",
    "addr:housenumber":"3965",
    "addr:postcode":"33404",
    "addr:street":"Investment Ln",
    "iso:country":"US",
    "sg:address":"3965 Investment Ln",
    "sg:city":"Riviera Beach",
    "sg:classifiers":[
        {
            "category":"Manufacturing",
            "subcategory":"Tools & Machinery",
            "type":"Manufacturing & Wholesale Goods"
        }
    ],
    "sg:phone":"+1 561 842 8211",
    "sg:postcode":"33404",
    "sg:province":"FL",
    "sg:tags":[
        "instrument",
        "optical",
        "lense"
    ],
    "wof:name":"Lenzar Optics",
    "wof:placetype":"venue"
},
  "geometry": {"coordinates":[-80.096512,26.797766],"type":"Point"}
}