{
  "type": "Feature",
  "properties": {
    "iso:country":"US",
    "sg:address":"4506 Mcintosh Rd",
    "sg:city":"Sarasota",
    "sg:classifiers":[
        {
            "category":"Wholesale",
            "subcategory":"Home Furnishings",
            "type":"Manufacturing & Wholesale Goods"
        }
    ],
    "sg:phone":"+1 941 924 5425",
    "sg:postcode":"34233",
    "sg:province":"FL",
    "sg:tags":[
        "draperies",
        "shades-wholesale",
        "curtain",
        "manufacturer"
    ],
    "wof:name":"Lillian M Alderman",
    "wof:placetype":"venue"
},
  "geometry": {"coordinates":[-82.481003,27.289837],"type":"Point"}
}