{
  "type": "Feature",
  "properties": {
    "iso:country":"US",
    "sg:address":"201 S A St",
    "sg:city":"Pensacola",
    "sg:classifiers":[
        {
            "category":"Building & Trades",
            "subcategory":"Plumbing",
            "type":"Services"
        }
    ],
    "sg:phone":"+1 850 432 8118",
    "sg:postcode":"32501",
    "sg:province":"FL",
    "sg:tags":[
        "air",
        "refrigeration",
        "conditioning",
        "contractor"
    ],
    "wof:name":"Royco Air Conditioning & Rfrgn",
    "wof:placetype":"venue"
},
  "geometry": {"coordinates":[-87.22628,30.408113],"type":"Point"}
}