{
  "type": "Feature",
  "properties": {
    "iso:country":"US",
    "sg:address":"11209 Macaw Ct",
    "sg:city":"Windermere",
    "sg:classifiers":[
        {
            "category":"Building & Trades",
            "subcategory":"Construction",
            "type":"Services"
        }
    ],
    "sg:phone":"+1 407 729 8188",
    "sg:postcode":"34786",
    "sg:province":"FL",
    "sg:tags":[
        "house"
    ],
    "wof:name":"Orange Contracting Inc",
    "wof:placetype":"venue"
},
  "geometry": {"coordinates":[-81.54426599999999,28.456163],"type":"Point"}
}