{
  "type": "Feature",
  "properties": {
    "addr:full":"15665 71st Pl N Loxahatchee FL 33470",
    "addr:housenumber":"15665",
    "addr:postcode":"33470",
    "addr:street":"71St Pl N",
    "iso:country":"US",
    "sg:address":"15665 71st Pl N",
    "sg:city":"Loxahatchee",
    "sg:classifiers":[
        {
            "category":"Professional",
            "subcategory":"Detective & Security Services",
            "type":"Services"
        }
    ],
    "sg:phone":"+1 561 792 9275",
    "sg:postcode":"33470",
    "sg:province":"FL",
    "sg:tags":[
        "information",
        "bureau"
    ],
    "wof:name":"We'll Floor U Installation Services",
    "wof:placetype":"venue"
},
  "geometry": {"coordinates":[-80.28867099999999,26.782169],"type":"Point"}
}