{
  "type": "Feature",
  "properties": {
    "iso:country":"US",
    "sg:address":"1916 Nannette St",
    "sg:city":"Tallahassee",
    "sg:classifiers":[
        {
            "category":"Personal",
            "subcategory":"Beauty Salon",
            "type":"Services"
        }
    ],
    "sg:phone":"+1 850 385 0821",
    "sg:postcode":"32303",
    "sg:province":"FL",
    "sg:tags":[
        "hair",
        "stylist"
    ],
    "wof:name":"Barbara Roberts",
    "wof:placetype":"venue"
},
  "geometry": {"coordinates":[-84.29061,30.464868],"type":"Point"}
}