{
  "type": "Feature",
  "properties": {
    "addr:full":"12010 SW 190th Ter Miami FL 33177",
    "addr:housenumber":"12010",
    "addr:postcode":"33177",
    "addr:street":"Sw 190Th Ter",
    "iso:country":"US",
    "sg:address":"12010 SW 190th Ter",
    "sg:city":"Miami",
    "sg:classifiers":[
        {
            "category":"Restaurant",
            "type":"Food & Drink"
        },
        {
            "category":"Ice Cream",
            "type":"Food & Drink"
        }
    ],
    "sg:phone":"+1 305 234 8131",
    "sg:postcode":"33177",
    "sg:province":"FL",
    "sg:tags":[
        "frozen",
        "dessert"
    ],
    "wof:name":"Irene Gomez Ice Cream Sales",
    "wof:placetype":"venue"
},
  "geometry": {"coordinates":[-80.38663699999999,25.590183],"type":"Point"}
}