{
  "type": "Feature",
  "properties": {
    "iso:country":"US",
    "sg:address":"202 Fan Coral Dr",
    "sg:city":"Panama City",
    "sg:classifiers":[
        {
            "category":"Building & Trades",
            "subcategory":"Construction",
            "type":"Services"
        },
        {
            "category":"Building & Trades",
            "subcategory":"Plumbing",
            "type":"Services"
        }
    ],
    "sg:phone":"+1 850 234 3731",
    "sg:postcode":"32408",
    "sg:province":"FL",
    "sg:tags":[
        "plumbing",
        "house",
        "contractor"
    ],
    "wof:name":"Advanced Plumbing Service",
    "wof:placetype":"venue"
},
  "geometry": {"coordinates":[-85.78139299999999,30.170786],"type":"Point"}
}