{
  "type": "Feature",
  "properties": {
    "addr:full":"1132 SW 5th St Boca Raton FL 33486",
    "addr:housenumber":"1132",
    "addr:postcode":"33486",
    "addr:street":"Sw 5Th St",
    "iso:country":"US",
    "sg:address":"1132 SW 5th St",
    "sg:city":"Boca Raton",
    "sg:classifiers":[
        {
            "category":"Building & Trades",
            "subcategory":"Construction",
            "type":"Services"
        }
    ],
    "sg:phone":"+1 772 287 0070",
    "sg:postcode":"33486",
    "sg:province":"FL",
    "sg:tags":[
        "concrete",
        "contractor"
    ],
    "wof:name":"Big T East Coast Inc",
    "wof:placetype":"venue"
},
  "geometry": {"coordinates":[-80.110106,26.344865],"type":"Point"}
}