{
  "type": "Feature",
  "properties": {
    "addr:full":"16001 Miramar Pkwy Miramar FL 33027",
    "addr:housenumber":"16001",
    "addr:postcode":"33027",
    "addr:street":"Miramar Pkwy",
    "iso:country":"US",
    "sg:address":"16001 Miramar Pkwy",
    "sg:city":"Miramar",
    "sg:classifiers":[
        {
            "category":"Shopping",
            "subcategory":"Pharmacy",
            "type":"Retail Goods"
        }
    ],
    "sg:phone":"+1 954 441 3610",
    "sg:postcode":"33027",
    "sg:province":"FL",
    "wof:name":"CVS Pharmacy",
    "wof:placetype":"venue"
},
  "geometry": {"coordinates":[-80.35977699999999,25.978689],"type":"Point"}
}