{
  "type": "Feature",
  "properties": {
    "iso:country":"US",
    "sg:address":"291 20th Ave NW",
    "sg:city":"Naples",
    "sg:classifiers":[
        {
            "category":"Professional",
            "subcategory":"Art Services",
            "type":"Services"
        }
    ],
    "sg:phone":"+1 239 352 8574",
    "sg:postcode":"34120",
    "sg:province":"FL",
    "sg:tags":[
        "artist"
    ],
    "wof:name":"Canturk & Canturk Artist",
    "wof:placetype":"venue"
},
  "geometry": {"coordinates":[-81.61120099999999,26.266339],"type":"Point"}
}