{
  "type": "Feature",
  "properties": {
    "addr:full":"4800 S Le Jeune Rd Coral Gables FL 33146",
    "addr:housenumber":"4800",
    "addr:postcode":"33146",
    "addr:street":"S Le Jeune Rd",
    "iso:country":"US",
    "sg:address":"4800 S Le Jeune Rd",
    "sg:city":"Coral Gables",
    "sg:classifiers":[
        {
            "category":"Professional",
            "subcategory":"Lawyer & Legal Services",
            "type":"Services"
        }
    ],
    "sg:phone":"+1 305 662 4800",
    "sg:postcode":"33146",
    "sg:province":"FL",
    "wof:name":"Buchholz John R Atty",
    "wof:placetype":"venue"
},
  "geometry": {"coordinates":[-80.26190200000001,25.728071],"type":"Point"}
}