{
  "type": "Feature",
  "properties": {
    "iso:country":"US",
    "sg:address":"300 Lock Rd",
    "sg:city":"Deerfield Beach",
    "sg:classifiers":[
        {
            "category":"Building & Trades",
            "subcategory":"Construction",
            "type":"Services"
        }
    ],
    "sg:phone":"+1 954 421 0348",
    "sg:postcode":"33442",
    "sg:province":"FL",
    "sg:tags":[
        "owner",
        "builder",
        "apartment",
        "build",
        "operative"
    ],
    "wof:name":"Scott Properties",
    "wof:placetype":"venue"
},
  "geometry": {"coordinates":[-80.126344,26.324061],"type":"Point"}
}