{
  "type": "Feature",
  "properties": {
    "iso:country":"US",
    "sg:address":"128 Gulfwinds Dr E",
    "sg:city":"Palm Harbor",
    "sg:classifiers":[
        {
            "category":"Building & Trades",
            "subcategory":"Pest Control",
            "type":"Services"
        }
    ],
    "sg:phone":"+1 727 942 1345",
    "sg:postcode":"34683",
    "sg:province":"FL",
    "wof:name":"Sur-Mite",
    "wof:placetype":"venue"
},
  "geometry": {"coordinates":[-82.768236,28.117663],"type":"Point"}
}