{
  "type": "Feature",
  "properties": {
    "iso:country":"US",
    "sg:address":"3003 Hartley Rd",
    "sg:city":"Jacksonville",
    "sg:classifiers":[
        {
            "category":"Retail",
            "subcategory":"Veterinary Services",
            "type":"Services"
        }
    ],
    "sg:phone":"+1 904 268 0477",
    "sg:postcode":"32257",
    "sg:province":"FL",
    "sg:tags":[
        "veterinarian"
    ],
    "sg:website":"www.mandarinlandingah.com",
    "wof:name":"Mandarin Landing Animal Hosp",
    "wof:placetype":"venue"
},
  "geometry": {"coordinates":[-81.630714,30.185483],"type":"Point"}
}