{
  "type": "Feature",
  "properties": {
    "addr:full":"8 Plover Ave Orlando FL 32825",
    "addr:housenumber":"8",
    "addr:postcode":"32825",
    "addr:street":"Plover Ave",
    "iso:country":"US",
    "sg:address":"8 Plover Ave",
    "sg:city":"Orlando",
    "sg:classifiers":[
        {
            "category":"Real Estate",
            "subcategory":"Architect",
            "type":"Services"
        }
    ],
    "sg:phone":"+1 407 249 8811",
    "sg:postcode":"32825",
    "sg:province":"FL",
    "sg:tags":[
        "engineer"
    ],
    "wof:name":"Dewberry & Davis",
    "wof:placetype":"venue"
},
  "geometry": {"coordinates":[-81.272919,28.543171],"type":"Point"}
}