{
  "type": "Feature",
  "properties": {
    "iso:country":"US",
    "sg:address":"12805 Buckeye Dr",
    "sg:city":"Hudson",
    "sg:classifiers":[
        {
            "category":"Building & Trades",
            "subcategory":"Construction",
            "type":"Services"
        }
    ],
    "sg:phone":"+1 727 856 4573",
    "sg:postcode":"34669",
    "sg:province":"FL",
    "sg:tags":[
        "excavating",
        "contractor"
    ],
    "wof:name":"Reed's Truck & Tractor Svc",
    "wof:placetype":"venue"
},
  "geometry": {"coordinates":[-82.643996,28.342733],"type":"Point"}
}