{
  "type": "Feature",
  "properties": {
    "iso:country":"US",
    "sg:address":"6099 Cedartown Rd",
    "sg:city":"Molino",
    "sg:classifiers":[
        {
            "category":"Building & Trades",
            "subcategory":"Construction",
            "type":"Services"
        }
    ],
    "sg:phone":"+1 850 587 2742",
    "sg:postcode":"32577",
    "sg:province":"FL",
    "sg:tags":[
        "contractor"
    ],
    "wof:name":"Larry Bellamy Masonry",
    "wof:placetype":"venue"
},
  "geometry": {"coordinates":[-87.32310699999999,30.71365],"type":"Point"}
}