{
  "type": "Feature",
  "properties": {
    "iso:country":"US",
    "sg:address":"4935 Gulfport Blvd S",
    "sg:city":"Saint Petersburg",
    "sg:classifiers":[
        {
            "category":"Restaurant",
            "type":"Food & Drink"
        }
    ],
    "sg:menulink":"http://www.allmenus.com/fl/st-petersburg/33269-hong-kong-new-york-style-chinese-restaurant/menu/",
    "sg:phone":"+1 727 322 0888",
    "sg:postcode":"33707",
    "sg:province":"FL",
    "sg:tags":[
        "asian",
        "chinese"
    ],
    "wof:name":"Hong Kong New York Style Chinese Restaurant",
    "wof:placetype":"venue"
},
  "geometry": {"coordinates":[-82.700047,27.748298],"type":"Point"}
}