{
  "type": "Feature",
  "properties": {
    "iso:country":"US",
    "sg:address":"30312 SW 155th Pl",
    "sg:city":"Homestead",
    "sg:classifiers":[
        {
            "category":"Professional",
            "type":"Services"
        }
    ],
    "sg:phone":"+1 305 246 1313",
    "sg:postcode":"33033",
    "sg:province":"FL",
    "wof:name":"All America Wood Master Inc",
    "wof:placetype":"venue"
},
  "geometry": {"coordinates":[-80.443319,25.485434],"type":"Point"}
}