{
  "type": "Feature",
  "properties": {
    "addr:full":"30650 Tremont Dr Zephyrhills FL 33543",
    "addr:postcode":"30650;33543",
    "addr:street":"Tremont Dr",
    "iso:country":"US",
    "sg:address":"30650 Tremont Dr",
    "sg:city":"Zephyrhills",
    "sg:classifiers":[
        {
            "category":"Professional",
            "type":"Services"
        }
    ],
    "sg:phone":"+1 813 994 8547",
    "sg:postcode":"33543",
    "sg:province":"FL",
    "wof:name":"Mk Northdale Corp",
    "wof:placetype":"venue"
},
  "geometry": {"coordinates":[-82.309032,28.184604],"type":"Point"}
}