{
  "type": "Feature",
  "properties": {
    "addr:full":"906 Shore Dr St Augustine FL 32086",
    "addr:housenumber":"906",
    "addr:postcode":"32086",
    "addr:street":"Shore Dr St",
    "iso:country":"US",
    "sg:address":"906 Shore Dr",
    "sg:city":"St Augustine",
    "sg:classifiers":[
        {
            "category":"Health Services",
            "subcategory":"Health Practitioner",
            "type":"Services"
        }
    ],
    "sg:phone":"+1 904 829 5565",
    "sg:postcode":"32086",
    "sg:province":"FL",
    "sg:tags":[
        "therapist",
        "physical"
    ],
    "wof:name":"Ability Rehab Svc Inc",
    "wof:placetype":"venue"
},
  "geometry": {"coordinates":[-81.313829,29.859502],"type":"Point"}
}