{
  "type": "Feature",
  "properties": {
    "iso:country":"US",
    "sg:address":"5589 Commonwealth Ave",
    "sg:city":"Jacksonville",
    "sg:classifiers":[
        {
            "category":"Wholesale",
            "subcategory":"Hardware",
            "type":"Manufacturing & Wholesale Goods"
        }
    ],
    "sg:phone":"+1 904 783 6069",
    "sg:postcode":"32254",
    "sg:province":"FL",
    "sg:tags":[
        "industrial",
        "who",
        "commercial",
        "ice",
        "machine",
        "equipment",
        "making"
    ],
    "sg:website":"www.hoshizaki.com",
    "wof:name":"Hoshizaki Southeastern Distr",
    "wof:placetype":"venue"
},
  "geometry": {"coordinates":[-81.740048,30.336194],"type":"Point"}
}