{
  "type": "Feature",
  "properties": {
    "iso:country":"US",
    "sg:address":"6225 W Irlo Bronson Memorial Hwy",
    "sg:city":"Kissimmee",
    "sg:classifiers":[
        {
            "category":"Shopping",
            "subcategory":"Florist",
            "type":"Retail Goods"
        }
    ],
    "sg:phone":"+1 407 396 7535",
    "sg:postcode":"34747",
    "sg:province":"FL",
    "wof:name":"Great Horse Gifts",
    "wof:placetype":"venue"
},
  "geometry": {"coordinates":[-81.529948,28.333197],"type":"Point"}
}