{
  "type": "Feature",
  "properties": {
    "iso:country":"US",
    "sg:address":"1650 NE 168th Ter",
    "sg:city":"Silver Springs",
    "sg:classifiers":[
        {
            "category":"Building & Trades",
            "subcategory":"Construction",
            "type":"Services"
        }
    ],
    "sg:phone":"+1 352 625 2436",
    "sg:postcode":"34488",
    "sg:province":"FL",
    "sg:tags":[
        "contractor"
    ],
    "wof:name":"Greg Osborne Window Tinting",
    "wof:placetype":"venue"
},
  "geometry": {"coordinates":[-81.87343199999999,29.204987],"type":"Point"}
}