{
  "type": "Feature",
  "properties": {
    "iso:country":"US",
    "sg:address":"501 Bullard Pkwy",
    "sg:city":"Tampa",
    "sg:classifiers":[
        {
            "category":"Organizations",
            "subcategory":"Religious Organization",
            "type":"Services"
        }
    ],
    "sg:phone":"+1 813 988 4350",
    "sg:postcode":"33617",
    "sg:province":"FL",
    "sg:tags":[
        "church"
    ],
    "sg:website":"www.ttcoc.com",
    "wof:name":"Temple Terrace Church Christ",
    "wof:placetype":"venue"
},
  "geometry": {"coordinates":[-82.383973,28.032425],"type":"Point"}
}