{
  "type": "Feature",
  "properties": {
    "iso:country":"US",
    "sg:address":"1874 NW Britt Rd",
    "sg:city":"Stuart",
    "sg:classifiers":[
        {
            "category":"Wholesale",
            "subcategory":"Machinery & Supplies",
            "type":"Manufacturing & Wholesale Goods"
        },
        {
            "category":"Professional",
            "subcategory":"Business Services",
            "type":"Services"
        }
    ],
    "sg:phone":"+1 772 692 2212",
    "sg:postcode":"34994",
    "sg:province":"FL",
    "sg:tags":[
        "water",
        "equipment",
        "industrial",
        "treatment"
    ],
    "wof:name":"Astor Chemical Company",
    "wof:placetype":"venue"
},
  "geometry": {"coordinates":[-80.278155,27.234425],"type":"Point"}
}