{
  "type": "Feature",
  "properties": {
    "addr:full":"620 NW 93rd Ter Hollywood FL 33024",
    "addr:housenumber":"620",
    "addr:postcode":"33024",
    "addr:street":"Nw 93Rd Ter",
    "iso:country":"US",
    "sg:address":"620 NW 93rd Ter",
    "sg:city":"Hollywood",
    "sg:classifiers":[
        {
            "category":"Building & Trades",
            "subcategory":"Construction",
            "type":"Services"
        }
    ],
    "sg:phone":"+1 305 219 4600",
    "sg:postcode":"33024",
    "sg:province":"FL",
    "sg:tags":[
        "contractor"
    ],
    "wof:name":"Action Petroleum Enterprises",
    "wof:placetype":"venue"
},
  "geometry": {"coordinates":[-80.270295,26.014952],"type":"Point"}
}