{
  "type": "Feature",
  "properties": {
    "iso:country":"US",
    "sg:address":"2292 Mayport Rd",
    "sg:city":"Atlantic Beach",
    "sg:classifiers":[
        {
            "category":"Shopping",
            "subcategory":"Department Store",
            "type":"Retail Goods"
        }
    ],
    "sg:phone":"+1 904 241 9589",
    "sg:postcode":"32233",
    "sg:province":"FL",
    "sg:tags":[
        "shop"
    ],
    "wof:name":"Dollar General",
    "wof:placetype":"venue"
},
  "geometry": {"coordinates":[-81.41347,30.34511],"type":"Point"}
}