{
  "type": "Feature",
  "properties": {
    "iso:country":"US",
    "sg:address":"12195 SW 10th St Apt 7",
    "sg:city":"Miami",
    "sg:classifiers":[
        {
            "category":"Professional",
            "subcategory":"Management & Consulting",
            "type":"Services"
        }
    ],
    "sg:phone":"+1 786 385 1957",
    "sg:postcode":"33184",
    "sg:province":"FL",
    "wof:name":"Minorca Pk Condo",
    "wof:placetype":"venue"
},
  "geometry": {"coordinates":[-80.39263200000001,25.758722],"type":"Point"}
}