{
  "type": "Feature",
  "properties": {
    "addr:full":"2525 Aspinwall St Sarasota FL 34237",
    "addr:housenumber":"2525",
    "addr:postcode":"34237",
    "addr:street":"Aspinwall St",
    "iso:country":"US",
    "sg:address":"2525 Aspinwall St",
    "sg:city":"Sarasota",
    "sg:classifiers":[
        {
            "category":"Retail",
            "subcategory":"Repair Shop",
            "type":"Services"
        }
    ],
    "sg:phone":"+1 941 504 7508",
    "sg:postcode":"34237",
    "sg:province":"FL",
    "sg:tags":[
        "lock",
        "locksmith"
    ],
    "wof:name":"Finehout's Mobile Locksmith",
    "wof:placetype":"venue"
},
  "geometry": {"coordinates":[-82.519631,27.339395],"type":"Point"}
}