{
  "type": "Feature",
  "properties": {
    "addr:full":"6226 S Orange Ave Orlando FL 32809",
    "addr:housenumber":"6226",
    "addr:postcode":"32809",
    "addr:street":"S Orange Ave",
    "iso:country":"US",
    "sg:address":"6226 S Orange Ave",
    "sg:city":"Orlando",
    "sg:classifiers":[
        {
            "category":"Shopping",
            "subcategory":"Hobbies, Toys, & Games",
            "type":"Retail Goods"
        }
    ],
    "sg:phone":"+1 407 850 9889",
    "sg:postcode":"32809",
    "sg:province":"FL",
    "sg:tags":[
        "craft"
    ],
    "wof:name":"Correct Craft",
    "wof:placetype":"venue"
},
  "geometry": {"coordinates":[-81.36834399999999,28.469483],"type":"Point"}
}