{
  "type": "Feature",
  "properties": {
    "iso:country":"US",
    "sg:address":"3140 SW 123rd Ct",
    "sg:city":"Miami",
    "sg:classifiers":[
        {
            "category":"Wholesale",
            "subcategory":"Machinery & Supplies",
            "type":"Manufacturing & Wholesale Goods"
        }
    ],
    "sg:phone":"+1 305 227 1257",
    "sg:postcode":"33175",
    "sg:province":"FL",
    "sg:tags":[
        "truck"
    ],
    "wof:name":"Angel Master Forklift Inc",
    "wof:placetype":"venue"
},
  "geometry": {"coordinates":[-80.395404,25.739207],"type":"Point"}
}