{
  "type": "Feature",
  "properties": {
    "iso:country":"US",
    "sg:address":"621 2nd St SW",
    "sg:city":"Vero Beach",
    "sg:classifiers":[
        {
            "category":"Professional",
            "subcategory":"Advertising",
            "type":"Services"
        }
    ],
    "sg:phone":"+1 772 569 8412",
    "sg:postcode":"32962",
    "sg:province":"FL",
    "wof:name":"Morning Star Personalized",
    "wof:placetype":"venue"
},
  "geometry": {"coordinates":[-80.386548,27.599601],"type":"Point"}
}