{
  "type": "Feature",
  "properties": {
    "addr:full":"94 Ready Ave NW Fort Walton Bch FL 32548",
    "addr:housenumber":"94",
    "addr:postcode":"32548",
    "addr:street":"Ready Ave Nw Fort",
    "iso:country":"US",
    "sg:address":"94 Ready Ave NW",
    "sg:city":"Fort Walton Bch",
    "sg:classifiers":[
        {
            "category":"Retail",
            "subcategory":"Repair Shop",
            "type":"Services"
        }
    ],
    "sg:phone":"+1 850 301 3811",
    "sg:postcode":"32548",
    "sg:province":"FL",
    "sg:tags":[
        "welding"
    ],
    "wof:name":"Graham's Welding & Fabrication",
    "wof:placetype":"venue"
},
  "geometry": {"coordinates":[-86.67042600000001,30.418091],"type":"Point"}
}