{
  "type": "Feature",
  "properties": {
    "iso:country":"US",
    "sg:address":"7844 Orleans St",
    "sg:city":"Hollywood",
    "sg:classifiers":[
        {
            "category":"Professional",
            "type":"Services"
        }
    ],
    "sg:phone":"+1 954 986 1071",
    "sg:postcode":"33023",
    "sg:province":"FL",
    "wof:name":"Desousa Touch Inc",
    "wof:placetype":"venue"
},
  "geometry": {"coordinates":[-80.240498,25.989768],"type":"Point"}
}