{
  "type": "Feature",
  "properties": {
    "iso:country":"US",
    "sg:address":"2101 Waverly Pl",
    "sg:city":"Melbourne",
    "sg:classifiers":[
        {
            "category":"Professional",
            "subcategory":"Lawyer & Legal Services",
            "type":"Services"
        }
    ],
    "sg:phone":"+1 321 722 2006",
    "sg:postcode":"32901",
    "sg:province":"FL",
    "wof:name":"Edward J Kinberg P A",
    "wof:placetype":"venue"
},
  "geometry": {"coordinates":[-80.60775700000001,28.078138],"type":"Point"}
}