{
  "type": "Feature",
  "properties": {
    "iso:country":"US",
    "sg:address":"9789 Glades Rd",
    "sg:city":"Boca Raton",
    "sg:classifiers":[
        {
            "category":"Health Services",
            "subcategory":"Doctor",
            "type":"Services"
        }
    ],
    "sg:phone":"+1 561 487 4440",
    "sg:postcode":"33434",
    "sg:province":"FL",
    "sg:tags":[
        "dentist"
    ],
    "sg:website":"www.bocasmiles.com",
    "wof:name":"Dental Care Of Boca Raton",
    "wof:placetype":"venue"
},
  "geometry": {"coordinates":[-80.198168,26.367968],"type":"Point"}
}