{
  "type": "Feature",
  "properties": {
    "iso:country":"US",
    "sg:address":"2717 E 5th St",
    "sg:city":"Panama City",
    "sg:classifiers":[
        {
            "category":"Autos & Motor Vehicles",
            "subcategory":"Auto Supplies",
            "type":"Retail Goods"
        }
    ],
    "sg:phone":"+1 850 785 5885",
    "sg:postcode":"32401",
    "sg:province":"FL",
    "sg:tags":[
        "tire"
    ],
    "wof:name":"Olde 98 Tire & Automotive",
    "wof:placetype":"venue"
},
  "geometry": {"coordinates":[-85.62421000000001,30.156836],"type":"Point"}
}