{
  "type": "Feature",
  "properties": {
    "addr:full":"18257 Flagship Cir Jupiter FL 33458",
    "addr:housenumber":"18257",
    "addr:postcode":"33458",
    "addr:street":"Flagship Cir",
    "iso:country":"US",
    "sg:address":"18257 Flagship Cir",
    "sg:city":"Jupiter",
    "sg:classifiers":[
        {
            "category":"Building & Trades",
            "subcategory":"Construction",
            "type":"Services"
        }
    ],
    "sg:phone":"+1 561 575 2025",
    "sg:postcode":"33458",
    "sg:province":"FL",
    "sg:tags":[
        "house"
    ],
    "wof:name":"Mark McCleary Renovation",
    "wof:placetype":"venue"
},
  "geometry": {"coordinates":[-80.13284899999999,26.946828],"type":"Point"}
}