{
  "type": "Feature",
  "properties": {
    "addr:full":"2818 Apalachee Pkwy Tallahassee FL 32301",
    "addr:housenumber":"2818",
    "addr:postcode":"32301",
    "addr:street":"Apalachee Pkwy",
    "iso:country":"US",
    "sg:address":"2818 Apalachee Pkwy",
    "sg:city":"Tallahassee",
    "sg:classifiers":[
        {
            "category":"Education",
            "subcategory":"College",
            "type":"Public Place"
        },
        {
            "category":"Organizations",
            "subcategory":"Membership Organization",
            "type":"Services"
        }
    ],
    "sg:phone":"+1 850 656 2406",
    "sg:postcode":"32301",
    "sg:province":"FL",
    "sg:tags":[
        "fraternal",
        "sorority",
        "housing",
        "student",
        "fraternity"
    ],
    "wof:name":"York Rite Bodies Tallahassee",
    "wof:placetype":"venue"
},
  "geometry": {"coordinates":[-84.235641,30.42721],"type":"Point"}
}