{
  "type": "Feature",
  "properties": {
    "iso:country":"US",
    "sg:address":"350 W 34th St",
    "sg:city":"Hialeah",
    "sg:classifiers":[
        {
            "category":"Building & Trades",
            "subcategory":"Construction",
            "type":"Services"
        }
    ],
    "sg:phone":"+1 305 885 3099",
    "sg:postcode":"33012",
    "sg:province":"FL",
    "sg:tags":[
        "marking",
        "maintenance",
        "lot",
        "parking"
    ],
    "wof:name":"All State Striping Corp",
    "wof:placetype":"venue"
},
  "geometry": {"coordinates":[-80.28931,25.852789],"type":"Point"}
}