{
  "type": "Feature",
  "properties": {
    "addr:full":"27610 W Dixie Hwy Homestead FL 33032",
    "addr:housenumber":"27610",
    "addr:postcode":"33032",
    "addr:street":"W Dixie Hwy",
    "iso:country":"US",
    "sg:address":"27610 W Dixie Hwy",
    "sg:city":"Homestead",
    "sg:classifiers":[
        {
            "category":"Food & Beverages",
            "subcategory":"Meat & Fish",
            "type":"Retail Goods"
        }
    ],
    "sg:phone":"+1 305 246 8844",
    "sg:postcode":"33032",
    "sg:province":"FL",
    "wof:name":"Fishes Fish Market",
    "wof:placetype":"venue"
},
  "geometry": {"coordinates":[-80.43885,25.508814],"type":"Point"}
}