{
  "type": "Feature",
  "properties": {
    "iso:country":"US",
    "sg:address":"5380 SW 5th St",
    "sg:city":"Plantation",
    "sg:classifiers":[
        {
            "category":"Autos & Motor Vehicles",
            "subcategory":"Boat Sales",
            "type":"Retail Goods"
        }
    ],
    "sg:phone":"+1 954 235 0571",
    "sg:postcode":"33317",
    "sg:province":"FL",
    "sg:tags":[
        "equipment",
        "supply"
    ],
    "wof:name":"Dinh Yachts Interior Carpentry",
    "wof:placetype":"venue"
},
  "geometry": {"coordinates":[-80.22121799999999,26.113745],"type":"Point"}
}