{
  "type": "Feature",
  "properties": {
    "iso:country":"US",
    "sg:address":"1106 N Howard Ave",
    "sg:city":"Tampa",
    "sg:classifiers":[
        {
            "category":"Health Services",
            "subcategory":"Medical Lab",
            "type":"Services"
        }
    ],
    "sg:phone":"+1 813 251 3506",
    "sg:postcode":"33607",
    "sg:province":"FL",
    "sg:tags":[
        "laboratory",
        "dental"
    ],
    "wof:name":"Suarez Dental Laboratory",
    "wof:placetype":"venue"
},
  "geometry": {"coordinates":[-82.483041,27.953483],"type":"Point"}
}