{
  "type": "Feature",
  "properties": {
    "addr:full":"2425 Tamiami Trl N Naples FL 34103",
    "addr:housenumber":"2425",
    "addr:postcode":"34103",
    "addr:street":"Tamiami Trl N",
    "iso:country":"US",
    "sg:address":"2425 Tamiami Trl N",
    "sg:city":"Naples",
    "sg:classifiers":[
        {
            "category":"Restaurant",
            "type":"Food & Drink"
        }
    ],
    "sg:menulink":"http://www.allmenus.com/fl/naples/160209-burger-king/menu/",
    "sg:phone":"+1 941 261 5922",
    "sg:postcode":"34103",
    "sg:province":"FL",
    "sg:tags":[
        "burger",
        "american"
    ],
    "wof:name":"Burger King",
    "wof:placetype":"venue"
},
  "geometry": {"coordinates":[-81.799886,26.177322],"type":"Point"}
}