{
  "type": "Feature",
  "properties": {
    "iso:country":"US",
    "sg:address":"6913 SW Hwy 200",
    "sg:city":"Ocala",
    "sg:classifiers":[
        {
            "category":"Building & Trades",
            "subcategory":"Construction",
            "type":"Services"
        }
    ],
    "sg:phone":"+1 352 873 1343",
    "sg:postcode":"34476",
    "sg:province":"FL",
    "sg:tags":[
        "home",
        "general",
        "contractor"
    ],
    "wof:name":"Homes By Whittaker Inc",
    "wof:placetype":"venue"
},
  "geometry": {"coordinates":[-82.23429,29.101964],"type":"Point"}
}