{
  "type": "Feature",
  "properties": {
    "addr:full":"3542 Halegate Ct Oviedo FL 32765",
    "addr:housenumber":"3542",
    "addr:postcode":"32765",
    "addr:street":"Halegate Ct",
    "iso:country":"US",
    "sg:address":"3542 Halegate Ct",
    "sg:city":"Oviedo",
    "sg:classifiers":[
        {
            "category":"Wholesale",
            "subcategory":"Stationery",
            "type":"Manufacturing & Wholesale Goods"
        }
    ],
    "sg:phone":"+1 407 366 0100",
    "sg:postcode":"32765",
    "sg:province":"FL",
    "sg:tags":[
        "supply"
    ],
    "wof:name":"Simple Impressions",
    "wof:placetype":"venue"
},
  "geometry": {"coordinates":[-81.18855000000001,28.619907],"type":"Point"}
}