{
  "type": "Feature",
  "properties": {
    "addr:full":"8928 Gibson Rd Molino FL 32577",
    "addr:housenumber":"8928",
    "addr:postcode":"32577",
    "addr:street":"Gibson Rd",
    "iso:country":"US",
    "sg:address":"8928 Gibson Rd",
    "sg:city":"Molino",
    "sg:classifiers":[
        {
            "category":"Real Estate",
            "subcategory":"Real Estate Agent",
            "type":"Services"
        }
    ],
    "sg:phone":"+1 850 587 4249",
    "sg:postcode":"32577",
    "sg:province":"FL",
    "wof:name":"Mattin Max & Glenda",
    "wof:placetype":"venue"
},
  "geometry": {"coordinates":[-87.39939099999999,30.75446],"type":"Point"}
}