{
  "type": "Feature",
  "properties": {
    "addr:full":"1628 1st Ave N St Petersburg FL 33713",
    "addr:housenumber":"1628",
    "addr:postcode":"33713",
    "addr:street":"1St Ave N",
    "iso:country":"US",
    "sg:address":"1628 1st Ave N",
    "sg:city":"St Petersburg",
    "sg:classifiers":[
        {
            "category":"Professional",
            "subcategory":"Engineering",
            "type":"Services"
        }
    ],
    "sg:phone":"+1 727 822 2335",
    "sg:postcode":"33713",
    "sg:province":"FL",
    "sg:tags":[
        "engineer"
    ],
    "sg:website":"www.best-griner.com",
    "wof:name":"Best Griner & Assoc Engirs Inc",
    "wof:placetype":"venue"
},
  "geometry": {"coordinates":[-82.655942,27.771935],"type":"Point"}
}