{
  "type": "Feature",
  "properties": {
    "addr:full":"4123 Tamiami Trl Sarasota FL 34234",
    "addr:housenumber":"4123",
    "addr:postcode":"34234",
    "addr:street":"Tamiami Trl",
    "iso:country":"US",
    "sg:address":"4123 Tamiami Trl",
    "sg:city":"Sarasota",
    "sg:classifiers":[
        {
            "category":"Professional",
            "subcategory":"Research",
            "type":"Services"
        }
    ],
    "sg:phone":"+1 941 355 8500",
    "sg:postcode":"34234",
    "sg:province":"FL",
    "sg:tags":[
        "environmental",
        "ecological"
    ],
    "wof:name":"Indoor Environmental Testing",
    "wof:placetype":"venue"
},
  "geometry": {"coordinates":[-82.55299599999999,27.370802],"type":"Point"}
}