{
  "type": "Feature",
  "properties": {
    "addr:full":"6300 SW 25th St Miami FL 33155",
    "addr:housenumber":"6300",
    "addr:postcode":"33155",
    "addr:street":"Sw 25Th St",
    "iso:country":"US",
    "sg:address":"6300 SW 25th St",
    "sg:city":"Miami",
    "sg:classifiers":[
        {
            "category":"Building & Trades",
            "subcategory":"Construction",
            "type":"Services"
        }
    ],
    "sg:phone":"+1 305 669 1496",
    "sg:postcode":"33155",
    "sg:province":"FL",
    "sg:tags":[
        "general",
        "contractor"
    ],
    "wof:name":"Muro Construction Inc",
    "wof:placetype":"venue"
},
  "geometry": {"coordinates":[-80.29946099999999,25.747187],"type":"Point"}
}