{
  "type": "Feature",
  "properties": {
    "iso:country":"US",
    "sg:address":"24 W Chase St",
    "sg:city":"Pensacola",
    "sg:classifiers":[
        {
            "category":"Professional",
            "subcategory":"Lawyer & Legal Services",
            "type":"Services"
        }
    ],
    "sg:phone":"+1 850 469 0202",
    "sg:postcode":"32502",
    "sg:province":"FL",
    "sg:tags":[
        "attorney"
    ],
    "wof:name":"Lozier Thames & Frazier",
    "wof:placetype":"venue"
},
  "geometry": {"coordinates":[-87.21713699999999,30.414077],"type":"Point"}
}