{
  "type": "Feature",
  "properties": {
    "iso:country":"US",
    "sg:address":"4953 International Dr",
    "sg:city":"Orlando",
    "sg:classifiers":[
        {
            "category":"Personal",
            "subcategory":"Shoe Repair & Shine",
            "type":"Services"
        }
    ],
    "sg:phone":"+1 407 363 0290",
    "sg:postcode":"32819",
    "sg:province":"FL",
    "sg:tags":[
        "sunglass"
    ],
    "wof:name":"Soltice Sunglass Outlet",
    "wof:placetype":"venue"
},
  "geometry": {"coordinates":[-81.44946400000001,28.474144],"type":"Point"}
}