{
  "type": "Feature",
  "properties": {
    "iso:country":"US",
    "sg:address":"1100 Spirit Lake Rd",
    "sg:city":"Winter Haven",
    "sg:classifiers":[
        {
            "category":"Food & Beverages",
            "subcategory":"Liquor & Beverages",
            "type":"Retail Goods"
        }
    ],
    "sg:phone":"+1 863 299 5881",
    "sg:postcode":"33880",
    "sg:province":"FL",
    "wof:name":"Spirit Liquor & Tobacco",
    "wof:placetype":"venue"
},
  "geometry": {"coordinates":[-81.779507,28.004855],"type":"Point"}
}