{
  "type": "Feature",
  "properties": {
    "iso:country":"US",
    "sg:address":"1515 Pinellas Bayway S",
    "sg:city":"Saint Petersburg",
    "sg:classifiers":[
        {
            "category":"Shopping",
            "subcategory":"Bicycles & Sporting Goods",
            "type":"Retail Goods"
        }
    ],
    "sg:phone":"+1 727 864 6897",
    "sg:postcode":"33715",
    "sg:province":"FL",
    "wof:name":"Victory Sports Marketing Inc",
    "wof:placetype":"venue"
},
  "geometry": {"coordinates":[-82.725613,27.672388],"type":"Point"}
}