{
  "type": "Feature",
  "properties": {
    "iso:country":"US",
    "sg:address":"1059 NE Pine Island Rd",
    "sg:city":"Cape Coral",
    "sg:classifiers":[
        {
            "category":"Communications",
            "type":"Services"
        }
    ],
    "sg:phone":"+1 239 283 8777",
    "sg:postcode":"33909",
    "sg:province":"FL",
    "wof:name":"Total Communications",
    "wof:placetype":"venue"
},
  "geometry": {"coordinates":[-81.95525000000001,26.660739],"type":"Point"}
}