{
  "type": "Feature",
  "properties": {
    "iso:country":"US",
    "sg:address":"8801 NW 58th St",
    "sg:city":"Doral",
    "sg:classifiers":[
        {
            "category":"Bars & Pubs",
            "type":"Food & Drink"
        }
    ],
    "sg:phone":"+1 305 592 7186",
    "sg:postcode":"33178",
    "sg:province":"FL",
    "wof:name":"Non Pub",
    "wof:placetype":"venue"
},
  "geometry": {"coordinates":[-80.340157,25.826189],"type":"Point"}
}