{
  "type": "Feature",
  "properties": {
    "iso:country":"US",
    "sg:address":"11903 Gulf Blvd",
    "sg:city":"Treasure Island",
    "sg:classifiers":[
        {
            "category":"Travel",
            "subcategory":"Hotels & Motels",
            "type":"Entertainment"
        }
    ],
    "sg:phone":"+1 727 360 1733",
    "sg:postcode":"33706",
    "sg:province":"FL",
    "wof:name":"Ebb Tide Motel",
    "wof:placetype":"venue"
},
  "geometry": {"coordinates":[-82.777942,27.776411],"type":"Point"}
}