{
  "type": "Feature",
  "properties": {
    "iso:country":"US",
    "sg:address":"2448 US Hwy 92",
    "sg:city":"Lakeland",
    "sg:classifiers":[
        {
            "category":"Banks & Credit Unions",
            "subcategory":"Bank",
            "type":"Services"
        }
    ],
    "sg:phone":"+1 863 667 1499",
    "sg:postcode":"33801",
    "sg:province":"FL",
    "sg:tags":[
        "depository",
        "banking"
    ],
    "wof:name":"AAA Cash Fast",
    "wof:placetype":"venue"
},
  "geometry": {"coordinates":[-81.91098100000001,28.048023],"type":"Point"}
}