{
  "type": "Feature",
  "properties": {
    "addr:full":"621 Park St Jacksonville FL 32204",
    "addr:housenumber":"621",
    "addr:postcode":"32204",
    "addr:street":"Park St",
    "iso:country":"US",
    "sg:address":"621 Park St",
    "sg:city":"Jacksonville",
    "sg:classifiers":[
        {
            "category":"Autos & Motor Vehicles",
            "subcategory":"Recreational Vehicle Sales",
            "type":"Retail Goods"
        }
    ],
    "sg:phone":"+1 904 545 8303",
    "sg:postcode":"32204",
    "sg:province":"FL",
    "sg:tags":[
        "camper"
    ],
    "wof:name":"Anthony's RV Outlet",
    "wof:placetype":"venue"
},
  "geometry": {"coordinates":[-81.67861000000001,30.319464],"type":"Point"}
}