{
  "type": "Feature",
  "properties": {
    "addr:full":"3898 Tamiami Trl N Naples FL 34103",
    "addr:housenumber":"3898",
    "addr:postcode":"34103",
    "addr:street":"Tamiami Trl N",
    "iso:country":"US",
    "sg:address":"3898 Tamiami Trl N",
    "sg:city":"Naples",
    "sg:classifiers":[
        {
            "category":"Retail",
            "subcategory":"Portrait Studio",
            "type":"Services"
        }
    ],
    "sg:phone":"+1 239 659 5442",
    "sg:postcode":"34103",
    "sg:province":"FL",
    "sg:tags":[
        "photographer"
    ],
    "wof:name":"KERI Johnson Photography-Child",
    "wof:placetype":"venue"
},
  "geometry": {"coordinates":[-81.80001,26.192663],"type":"Point"}
}