{
  "type": "Feature",
  "properties": {
    "iso:country":"US",
    "sg:address":"1552 Cesery Blvd",
    "sg:city":"Jacksonville",
    "sg:classifiers":[
        {
            "category":"Autos & Motor Vehicles",
            "subcategory":"Fuel & Gas Station",
            "type":"Retail Goods"
        }
    ],
    "sg:phone":"+1 904 743 7144",
    "sg:postcode":"32211",
    "sg:province":"FL",
    "sg:tags":[
        "oil"
    ],
    "wof:name":"Amoco First Coast Energy",
    "wof:placetype":"venue"
},
  "geometry": {"coordinates":[-81.597123,30.336416],"type":"Point"}
}