{
  "type": "Feature",
  "properties": {
    "addr:full":"85104 Blackmon Rd Yulee FL 32097",
    "addr:postcode":"85104;32097",
    "addr:street":"Blackmon Rd",
    "iso:country":"US",
    "sg:address":"85104 Blackmon Rd",
    "sg:city":"Yulee",
    "sg:classifiers":[
        {
            "category":"Building & Trades",
            "subcategory":"Construction",
            "type":"Services"
        }
    ],
    "sg:phone":"+1 904 482 2840",
    "sg:postcode":"32097",
    "sg:province":"FL",
    "sg:tags":[
        "bathroom",
        "painting",
        "contractor",
        "planning",
        "remodeling",
        "kitchen"
    ],
    "wof:name":"Haney Homes",
    "wof:placetype":"venue"
},
  "geometry": {"coordinates":[-81.572372,30.58246],"type":"Point"}
}