{
  "type": "Feature",
  "properties": {
    "addr:full":"4000 NE Skyline Dr Jensen Beach FL 34957",
    "addr:housenumber":"4000",
    "addr:postcode":"34957",
    "addr:street":"Ne Skyline Dr",
    "iso:country":"US",
    "sg:address":"4000 NE Skyline Dr",
    "sg:city":"Jensen Beach",
    "sg:classifiers":[
        {
            "category":"Building & Trades",
            "subcategory":"Construction",
            "type":"Services"
        }
    ],
    "sg:phone":"+1 772 334 1634",
    "sg:postcode":"34957",
    "sg:province":"FL",
    "sg:tags":[
        "concrete",
        "contractor",
        "paving",
        "house"
    ],
    "wof:name":"Grand Entry Design & Constr",
    "wof:placetype":"venue"
},
  "geometry": {"coordinates":[-80.233159,27.253346],"type":"Point"}
}