{
  "type": "Feature",
  "properties": {
    "iso:country":"US",
    "sg:address":"2170 Andrea Ln",
    "sg:city":"Fort Myers",
    "sg:classifiers":[
        {
            "category":"Building & Trades",
            "subcategory":"Construction",
            "type":"Services"
        }
    ],
    "sg:phone":"+1 239 489 4449",
    "sg:postcode":"33912",
    "sg:province":"FL",
    "sg:tags":[
        "contractor",
        "wood",
        "mfg"
    ],
    "wof:name":"Wilsonart Custom Products",
    "wof:placetype":"venue"
},
  "geometry": {"coordinates":[-81.866468,26.534576],"type":"Point"}
}