{
  "type": "Feature",
  "properties": {
    "iso:country":"US",
    "sg:address":"2030 S Douglas Rd Apt 215",
    "sg:city":"Coral Gables",
    "sg:classifiers":[
        {
            "category":"Professional",
            "subcategory":"Lawyer & Legal Services",
            "type":"Services"
        }
    ],
    "sg:phone":"+1 305 444 7078",
    "sg:postcode":"33134",
    "sg:province":"FL",
    "wof:name":"Varela Karen PA",
    "wof:placetype":"venue"
},
  "geometry": {"coordinates":[-80.25484299999999,25.753704],"type":"Point"}
}