{
  "type": "Feature",
  "properties": {
    "addr:full":"302 Whetherbine Way E Tallahassee FL 32301",
    "addr:housenumber":"302",
    "addr:postcode":"32301",
    "addr:street":"Whetherbine Way E",
    "iso:country":"US",
    "sg:address":"302 Whetherbine Way E",
    "sg:city":"Tallahassee",
    "sg:classifiers":[
        {
            "category":"Building & Trades",
            "subcategory":"Construction",
            "type":"Services"
        }
    ],
    "sg:phone":"+1 850 942 4883",
    "sg:postcode":"32301",
    "sg:province":"FL",
    "sg:tags":[
        "carpentry",
        "contractor"
    ],
    "wof:name":"Robert Pierce Carpentry",
    "wof:placetype":"venue"
},
  "geometry": {"coordinates":[-84.23102,30.448935],"type":"Point"}
}