{
  "type": "Feature",
  "properties": {
    "addr:full":"7240 Isle of Capri Rd Naples FL 34114",
    "addr:housenumber":"7240",
    "addr:postcode":"34114",
    "addr:street":"Isle Of Capri Rd",
    "iso:country":"US",
    "sg:address":"7240 Isle of Capri Rd",
    "sg:city":"Naples",
    "sg:classifiers":[
        {
            "category":"Shopping",
            "subcategory":"Shoes",
            "type":"Retail Goods"
        }
    ],
    "sg:phone":"+1 239 775 2992",
    "sg:postcode":"34114",
    "sg:province":"FL",
    "wof:name":"Rack Room Shoes",
    "wof:placetype":"venue"
},
  "geometry": {"coordinates":[-81.70016,26.041865],"type":"Point"}
}