{
  "type": "Feature",
  "properties": {
    "addr:full":"1803 Edgewater Dr Orlando FL 32804",
    "addr:housenumber":"1803",
    "addr:postcode":"32804",
    "addr:street":"Edgewater Dr",
    "iso:country":"US",
    "sg:address":"1803 Edgewater Dr",
    "sg:city":"Orlando",
    "sg:classifiers":[
        {
            "category":"Banks & Credit Unions",
            "subcategory":"Bank",
            "type":"Services"
        }
    ],
    "sg:phone":"+1 407 426 7999",
    "sg:postcode":"32804",
    "sg:province":"FL",
    "sg:tags":[
        "loan",
        "real estate"
    ],
    "wof:name":"EMC Mortgage Solutions Inc",
    "wof:placetype":"venue"
},
  "geometry": {"coordinates":[-81.38931700000001,28.567877],"type":"Point"}
}