{
  "type": "Feature",
  "properties": {
    "iso:country":"US",
    "sg:address":"7695 SW 104th St Ste 220",
    "sg:city":"Miami",
    "sg:classifiers":[
        {
            "category":"Professional",
            "subcategory":"Accounting & Tax Preparation",
            "type":"Services"
        }
    ],
    "sg:phone":"+1 305 661 2222",
    "sg:postcode":"33156",
    "sg:province":"FL",
    "sg:tags":[
        "accountant"
    ],
    "wof:name":"Wolfe Larry CPA",
    "wof:placetype":"venue"
},
  "geometry": {"coordinates":[-80.31950399999999,25.673901],"type":"Point"}
}