{
  "type": "Feature",
  "properties": {
    "iso:country":"US",
    "sg:address":"2323 NE 26th Ave",
    "sg:city":"Pompano Beach",
    "sg:classifiers":[
        {
            "category":"Wholesale",
            "subcategory":"Medical Equipment & Supplies",
            "type":"Manufacturing & Wholesale Goods"
        }
    ],
    "sg:phone":"+1 954 784 2163",
    "sg:postcode":"33062",
    "sg:province":"FL",
    "sg:tags":[
        "physician",
        "surgeon"
    ],
    "sg:website":"www.diabeticnationalservices.com",
    "wof:name":"Diabetic National Svc Inc",
    "wof:placetype":"venue"
},
  "geometry": {"coordinates":[-80.097827,26.259193],"type":"Point"}
}