{
  "type": "Feature",
  "properties": {
    "addr:full":"957 N Krome Ave Homestead FL 33030",
    "addr:housenumber":"957",
    "addr:postcode":"33030",
    "addr:street":"N Krome Ave",
    "iso:country":"US",
    "sg:address":"957 N Krome Ave",
    "sg:city":"Homestead",
    "sg:classifiers":[
        {
            "category":"Health Services",
            "subcategory":"Doctor",
            "type":"Services"
        }
    ],
    "sg:phone":"+1 305 245 6866",
    "sg:postcode":"33030",
    "sg:province":"FL",
    "sg:tags":[
        "physician",
        "family",
        "practice",
        "surgeons",
        "orthopedics",
        "medicine",
        "surgeon"
    ],
    "wof:name":"Lang, Elliot N MD",
    "wof:placetype":"venue"
},
  "geometry": {"coordinates":[-80.477463,25.478979],"type":"Point"}
}