{
  "type": "Feature",
  "properties": {
    "addr:full":"60 Sunset St Satellite Beach FL 32937",
    "addr:housenumber":"60",
    "addr:postcode":"32937",
    "addr:street":"Sunset St",
    "iso:country":"US",
    "sg:address":"60 Sunset St",
    "sg:city":"Satellite Beach",
    "sg:classifiers":[
        {
            "category":"Retail",
            "subcategory":"Auto Repair",
            "type":"Services"
        }
    ],
    "sg:phone":"+1 321 591 1576",
    "sg:postcode":"32937",
    "sg:province":"FL",
    "sg:tags":[
        "general"
    ],
    "wof:name":"Contemporary Car Care",
    "wof:placetype":"venue"
},
  "geometry": {"coordinates":[-80.603876,28.184364],"type":"Point"}
}