{
  "type": "Feature",
  "properties": {
    "iso:country":"US",
    "sg:address":"1700 W Waters Ave",
    "sg:city":"Tampa",
    "sg:classifiers":[
        {
            "category":"Banks & Credit Unions",
            "subcategory":"Bank",
            "type":"Services"
        }
    ],
    "sg:phone":"+1 813 932 2292",
    "sg:postcode":"33604",
    "sg:province":"FL",
    "sg:tags":[
        "money",
        "transfer"
    ],
    "wof:name":"Viettex",
    "wof:placetype":"venue"
},
  "geometry": {"coordinates":[-82.477114,28.02534],"type":"Point"}
}