{
  "type": "Feature",
  "properties": {
    "iso:country":"US",
    "sg:address":"615 N Palm Ave",
    "sg:city":"Palatka",
    "sg:classifiers":[
        {
            "category":"Organizations",
            "subcategory":"Religious Organization",
            "type":"Services"
        }
    ],
    "sg:phone":"+1 386 328 5492",
    "sg:postcode":"32177",
    "sg:province":"FL",
    "sg:tags":[
        "church"
    ],
    "wof:name":"Shepherd's Way Outreach",
    "wof:placetype":"venue"
},
  "geometry": {"coordinates":[-81.662274,29.655388],"type":"Point"}
}