{
  "type": "Feature",
  "properties": {
    "addr:full":"1094 Hopkins Ln Zolfo Springs FL 33890",
    "addr:housenumber":"1094",
    "addr:postcode":"33890",
    "addr:street":"Hopkins Ln",
    "iso:country":"US",
    "sg:address":"1094 Hopkins Ln",
    "sg:city":"Zolfo Springs",
    "sg:classifiers":[
        {
            "category":"Building & Trades",
            "subcategory":"Construction",
            "type":"Services"
        }
    ],
    "sg:phone":"+1 863 735 1967",
    "sg:postcode":"33890",
    "sg:province":"FL",
    "sg:tags":[
        "contractor"
    ],
    "wof:name":"Chucks Masonry Inc",
    "wof:placetype":"venue"
},
  "geometry": {"coordinates":[-81.774394,27.342929],"type":"Point"}
}