{
  "type": "Feature",
  "properties": {
    "addr:full":"188 NW 36th St Miami FL 33127",
    "addr:housenumber":"188",
    "addr:postcode":"33127",
    "addr:street":"Nw 36Th St",
    "iso:country":"US",
    "sg:address":"188 NW 36th St",
    "sg:city":"Miami",
    "sg:classifiers":[
        {
            "category":"Home & Garden",
            "subcategory":"Home Furnishings",
            "type":"Retail Goods"
        },
        {
            "category":"Home & Garden",
            "subcategory":"Carpets & Floor Coverings",
            "type":"Retail Goods"
        }
    ],
    "sg:phone":"+1 305 403 2553",
    "sg:postcode":"33127",
    "sg:province":"FL",
    "sg:tags":[
        "set",
        "bedroom",
        "bed",
        "mattress"
    ],
    "wof:name":"Sleep Well Mattress Inc",
    "wof:placetype":"venue"
},
  "geometry": {"coordinates":[-80.19919400000001,25.810317],"type":"Point"}
}