{
  "type": "Feature",
  "properties": {
    "addr:full":"5663 Curry Ford Rd Orlando FL 32822",
    "addr:housenumber":"5663",
    "addr:postcode":"32822",
    "addr:street":"Curry Ford Rd",
    "iso:country":"US",
    "sg:address":"5663 Curry Ford Rd",
    "sg:city":"Orlando",
    "sg:classifiers":[
        {
            "category":"Banks & Credit Unions",
            "subcategory":"Bank",
            "type":"Services"
        }
    ],
    "sg:phone":"+1 321 235 9001",
    "sg:postcode":"32822",
    "sg:province":"FL",
    "sg:tags":[
        "financing",
        "broker",
        "mortgage"
    ],
    "wof:name":"Mister Money Mortgage Company",
    "wof:placetype":"venue"
},
  "geometry": {"coordinates":[-81.311537,28.524067],"type":"Point"}
}