{
  "type": "Feature",
  "properties": {
    "iso:country":"US",
    "sg:address":"4557 Chumuckla Hwy",
    "sg:city":"Milton",
    "sg:classifiers":[
        {
            "category":"Professional",
            "subcategory":"Lawyer & Legal Services",
            "type":"Services"
        }
    ],
    "sg:phone":"+1 850 995 1102",
    "sg:postcode":"32571",
    "sg:province":"FL",
    "sg:tags":[
        "corporation",
        "attorney",
        "partnership",
        "law"
    ],
    "wof:name":"Saba, Daniel P",
    "wof:placetype":"venue"
},
  "geometry": {"coordinates":[-87.16152200000001,30.60231],"type":"Point"}
}