{
  "type": "Feature",
  "properties": {
    "addr:full":"146 18th Ave SE St Petersburg FL 33705",
    "addr:housenumber":"146",
    "addr:postcode":"33705",
    "addr:street":"18Th Ave Se",
    "iso:country":"US",
    "sg:address":"146 18th Ave SE",
    "sg:city":"St Petersburg",
    "sg:classifiers":[
        {
            "category":"Personal",
            "subcategory":"Beauty Salon",
            "type":"Services"
        }
    ],
    "sg:phone":"+1 727 526 9654",
    "sg:postcode":"33705",
    "sg:province":"FL",
    "wof:name":"Artistic Hair Studio",
    "wof:placetype":"venue"
},
  "geometry": {"coordinates":[-82.632987,27.752608],"type":"Point"}
}