{
  "type": "Feature",
  "properties": {
    "iso:country":"US",
    "sg:address":"110 Bear Dr",
    "sg:city":"Gulf Breeze",
    "sg:classifiers":[
        {
            "category":"Shopping",
            "subcategory":"Clothing, Apparel, & Fashions",
            "type":"Retail Goods"
        }
    ],
    "sg:phone":"+1 850 932 4369",
    "sg:postcode":"32561",
    "sg:province":"FL",
    "sg:tags":[
        "printing",
        "shirt",
        "publishing"
    ],
    "wof:name":"Great American Classics Inc",
    "wof:placetype":"venue"
},
  "geometry": {"coordinates":[-87.183628,30.359313],"type":"Point"}
}