{
  "type": "Feature",
  "properties": {
    "iso:country":"US",
    "sg:address":"1974 Promenade Way",
    "sg:city":"Clearwater",
    "sg:classifiers":[
        {
            "category":"Personal",
            "subcategory":"Beauty Salon",
            "type":"Services"
        }
    ],
    "sg:phone":"+1 727 536 2636",
    "sg:postcode":"33760",
    "sg:province":"FL",
    "sg:tags":[
        "shop"
    ],
    "wof:name":"Fantastic Sans",
    "wof:placetype":"venue"
},
  "geometry": {"coordinates":[-82.708935,27.924618],"type":"Point"}
}