{
  "type": "Feature",
  "properties": {
    "addr:full":"3511 NW Federal Hwy Jensen Beach FL 34957",
    "addr:housenumber":"3511",
    "addr:postcode":"34957",
    "addr:street":"Nw Federal Hwy",
    "iso:country":"US",
    "sg:address":"3511 NW Federal Hwy",
    "sg:city":"Jensen Beach",
    "sg:classifiers":[
        {
            "category":"Shopping",
            "type":"Retail Goods"
        }
    ],
    "sg:phone":"+1 772 692 4080",
    "sg:postcode":"34957",
    "sg:province":"FL",
    "sg:tags":[
        "cosmetic",
        "perfume"
    ],
    "wof:name":"Bargain Buys Beauty Supplies",
    "wof:placetype":"venue"
},
  "geometry": {"coordinates":[-80.269644,27.238364],"type":"Point"}
}