{
  "type": "Feature",
  "properties": {
    "iso:country":"US",
    "sg:address":"4411 Beacon Way",
    "sg:city":"West Palm Beach",
    "sg:classifiers":[
        {
            "category":"Professional",
            "subcategory":"Management & Consulting",
            "type":"Services"
        }
    ],
    "sg:phone":"+1 561 841 4003",
    "sg:postcode":"33407",
    "sg:province":"FL",
    "sg:tags":[
        "business"
    ],
    "wof:name":"Redwing Technologies Inc",
    "wof:placetype":"venue"
},
  "geometry": {"coordinates":[-80.084718,26.758018],"type":"Point"}
}