{
  "type": "Feature",
  "properties": {
    "iso:country":"US",
    "sg:address":"3206 W Hillsborough Ave",
    "sg:city":"Tampa",
    "sg:classifiers":[
        {
            "category":"Travel",
            "subcategory":"Hotels & Motels",
            "type":"Entertainment"
        }
    ],
    "sg:phone":"+1 813 879 2055",
    "sg:postcode":"33614",
    "sg:province":"FL",
    "wof:name":"Sunny South Motel",
    "wof:placetype":"venue"
},
  "geometry": {"coordinates":[-82.495028,27.996048],"type":"Point"}
}