{
  "type": "Feature",
  "properties": {
    "iso:country":"US",
    "sg:address":"6921 NW 173rd Dr",
    "sg:city":"Hialeah",
    "sg:classifiers":[
        {
            "category":"Autos & Motor Vehicles",
            "subcategory":"Auto Supplies",
            "type":"Retail Goods"
        }
    ],
    "sg:phone":"+1 305 556 5781",
    "sg:postcode":"33015",
    "sg:province":"FL",
    "wof:name":"D Express Tires Services Corp",
    "wof:placetype":"venue"
},
  "geometry": {"coordinates":[-80.31351100000001,25.928621],"type":"Point"}
}