{
  "type": "Feature",
  "properties": {
    "iso:country":"US",
    "sg:address":"1750 W 10th St",
    "sg:city":"West Palm Beach",
    "sg:classifiers":[
        {
            "category":"Building & Trades",
            "subcategory":"Construction",
            "type":"Services"
        }
    ],
    "sg:phone":"+1 561 842 9205",
    "sg:postcode":"33404",
    "sg:province":"FL",
    "sg:tags":[
        "specializing",
        "concrete",
        "column",
        "wall",
        "contractor"
    ],
    "wof:name":"Axtell Construction Inc",
    "wof:placetype":"venue"
},
  "geometry": {"coordinates":[-80.084912,26.772713],"type":"Point"}
}