{
  "type": "Feature",
  "properties": {
    "addr:full":"530 S State Rd 7 Fort Lauderdale FL 33317",
    "addr:housenumber":"530",
    "addr:postcode":"33317",
    "addr:street":"S State Rd 7",
    "iso:country":"US",
    "sg:address":"530 S State Rd 7",
    "sg:city":"Fort Lauderdale",
    "sg:classifiers":[
        {
            "category":"Retail",
            "subcategory":"Repair Shop",
            "type":"Services"
        },
        {
            "category":"Wholesale",
            "subcategory":"Electrical",
            "type":"Manufacturing & Wholesale Goods"
        }
    ],
    "sg:phone":"+1 954 792 7157",
    "sg:postcode":"33317",
    "sg:province":"FL",
    "sg:tags":[
        "armature",
        "motor",
        "electric",
        "rewinding"
    ],
    "wof:name":"Sun Electric Motor Repair Co",
    "wof:placetype":"venue"
},
  "geometry": {"coordinates":[-80.20172100000001,26.114682],"type":"Point"}
}