{
  "type": "Feature",
  "properties": {
    "iso:country":"US",
    "sg:address":"825 US Hwy 1",
    "sg:city":"Sebastian",
    "sg:classifiers":[
        {
            "category":"Professional",
            "subcategory":"Business Services",
            "type":"Services"
        }
    ],
    "sg:phone":"+1 772 589 7771",
    "sg:postcode":"32958",
    "sg:province":"FL",
    "sg:tags":[
        "interior",
        "consultant",
        "design",
        "decorator"
    ],
    "wof:name":"Merriweather Art & Interiors",
    "wof:placetype":"venue"
},
  "geometry": {"coordinates":[-80.466927,27.810122],"type":"Point"}
}