{
  "type": "Feature",
  "properties": {
    "iso:country":"US",
    "sg:address":"880 Sand Lake Rd",
    "sg:city":"Orlando",
    "sg:classifiers":[
        {
            "category":"Retail",
            "subcategory":"Photofinishing",
            "type":"Services"
        }
    ],
    "sg:phone":"+1 407 240 1659",
    "sg:postcode":"32809",
    "sg:province":"FL",
    "sg:tags":[
        "laboratory"
    ],
    "wof:name":"Qualex",
    "wof:placetype":"venue"
},
  "geometry": {"coordinates":[-81.390028,28.450713],"type":"Point"}
}