{
  "type": "Feature",
  "properties": {
    "addr:full":"9214 N Main St Jacksonville FL 32218",
    "addr:housenumber":"9214",
    "addr:postcode":"32218",
    "addr:street":"N Main St",
    "iso:country":"US",
    "sg:address":"9214 N Main St",
    "sg:city":"Jacksonville",
    "sg:classifiers":[
        {
            "category":"Manufacturing",
            "subcategory":"Glass & Minerals",
            "type":"Manufacturing & Wholesale Goods"
        }
    ],
    "sg:phone":"+1 904 765 2868",
    "sg:postcode":"32218",
    "sg:province":"FL",
    "sg:tags":[
        "ready",
        "mixed",
        "mfg",
        "block",
        "concrete"
    ],
    "wof:name":"Kosmos Cenent Co",
    "wof:placetype":"venue"
},
  "geometry": {"coordinates":[-81.650268,30.407885],"type":"Point"}
}