{
  "type": "Feature",
  "properties": {
    "addr:full":"25 Old Kings Rd N Palm Coast FL 32137",
    "addr:housenumber":"25",
    "addr:postcode":"32137",
    "addr:street":"Old Kings Rd N",
    "iso:country":"US",
    "sg:address":"25 Old Kings Rd N",
    "sg:city":"Palm Coast",
    "sg:classifiers":[
        {
            "category":"Real Estate",
            "subcategory":"Real Estate Agent",
            "type":"Services"
        }
    ],
    "sg:phone":"+1 386 931 4068",
    "sg:postcode":"32137",
    "sg:province":"FL",
    "wof:name":"International Realty",
    "wof:placetype":"venue"
},
  "geometry": {"coordinates":[-81.232871,29.582909],"type":"Point"}
}