{
  "type": "Feature",
  "properties": {
    "addr:full":"3109 Ponce de Leon Blvd Coral Gables FL 33134",
    "addr:housenumber":"3109",
    "addr:postcode":"33134",
    "addr:street":"Ponce De Leon Blvd",
    "iso:country":"US",
    "sg:address":"3109 Ponce de Leon Blvd",
    "sg:city":"Coral Gables",
    "sg:classifiers":[
        {
            "category":"Real Estate",
            "subcategory":"Real Estate Agent",
            "type":"Services"
        }
    ],
    "sg:phone":"+1 305 443 5422",
    "sg:postcode":"33134",
    "sg:province":"FL",
    "wof:name":"Michael S Jones Realtor",
    "wof:placetype":"venue"
},
  "geometry": {"coordinates":[-80.25830999999999,25.743607],"type":"Point"}
}