{
  "type": "Feature",
  "properties": {
    "iso:country":"US",
    "sg:address":"4152 E 11th Ave",
    "sg:city":"Hialeah",
    "sg:classifiers":[
        {
            "category":"Retail",
            "subcategory":"Auto Repair",
            "type":"Services"
        }
    ],
    "sg:phone":"+1 305 688 4656",
    "sg:postcode":"33013",
    "sg:province":"FL",
    "sg:tags":[
        "repairing",
        "automobile",
        "general"
    ],
    "wof:name":"Florida Auto Repair Corp",
    "wof:placetype":"venue"
},
  "geometry": {"coordinates":[-80.260604,25.861487],"type":"Point"}
}