{
  "type": "Feature",
  "properties": {
    "iso:country":"US",
    "sg:address":"2700 N Ponce de Leon Blvd",
    "sg:city":"St Augustine",
    "sg:classifiers":[
        {
            "category":"Travel",
            "subcategory":"Hotels & Motels",
            "type":"Entertainment"
        }
    ],
    "sg:phone":"+1 904 824 2883",
    "sg:postcode":"32084",
    "sg:province":"FL",
    "sg:website":"www.alhambrainn.com",
    "wof:name":"Alhambra Inn & Suites",
    "wof:placetype":"venue"
},
  "geometry": {"coordinates":[-81.32461000000001,29.916822],"type":"Point"}
}