{
  "type": "Feature",
  "properties": {
    "iso:country":"US",
    "sg:address":"4401 NW 25th Pl",
    "sg:city":"Gainesville",
    "sg:classifiers":[
        {
            "category":"Restaurant",
            "type":"Food & Drink"
        }
    ],
    "sg:menulink":"http://www.allmenus.com/fl/gainesville/248380-ichiban-sushi/menu/",
    "sg:phone":"+1 352 375 8880",
    "sg:postcode":"32606",
    "sg:province":"FL",
    "sg:tags":[
        "japanese",
        "asian"
    ],
    "wof:name":"Ichiban Sushi",
    "wof:placetype":"venue"
},
  "geometry": {"coordinates":[-82.389118,29.675914],"type":"Point"}
}