{
  "type": "Feature",
  "properties": {
    "iso:country":"US",
    "sg:address":"2500 Lake Josephine Dr",
    "sg:city":"Sebring",
    "sg:classifiers":[
        {
            "category":"Building & Trades",
            "subcategory":"Electrical",
            "type":"Services"
        }
    ],
    "sg:phone":"+1 863 655 1125",
    "sg:postcode":"33875",
    "sg:province":"FL",
    "sg:tags":[
        "industrial",
        "electrician",
        "electric",
        "contractors-commercial"
    ],
    "wof:name":"Bennett Electrical Services Inc",
    "wof:placetype":"venue"
},
  "geometry": {"coordinates":[-81.45269,27.383459],"type":"Point"}
}