{
  "type": "Feature",
  "properties": {
    "iso:country":"US",
    "sg:address":"250 Co Rd 427 S",
    "sg:city":"Longwood",
    "sg:classifiers":[
        {
            "category":"Health Services",
            "subcategory":"Health Practitioner",
            "type":"Services"
        }
    ],
    "sg:phone":"+1 407 331 8990",
    "sg:postcode":"32750",
    "sg:province":"FL",
    "sg:tags":[
        "acupuncture"
    ],
    "wof:name":"Chinese Acupuncture & Herbs",
    "wof:placetype":"venue"
},
  "geometry": {"coordinates":[-81.346352,28.696243],"type":"Point"}
}