{
  "type": "Feature",
  "properties": {
    "addr:full":"5030 15th St E Bradenton FL 34203",
    "addr:housenumber":"5030",
    "addr:postcode":"34203",
    "addr:street":"15Th St",
    "iso:country":"US",
    "sg:address":"5030 15th St E",
    "sg:city":"Bradenton",
    "sg:classifiers":[
        {
            "category":"Home & Garden",
            "subcategory":"Garden Supply",
            "type":"Retail Goods"
        },
        {
            "category":"Shopping",
            "subcategory":"Gifts & Souvenirs",
            "type":"Retail Goods"
        },
        {
            "category":"Shopping",
            "subcategory":"Crafts & Fabrics",
            "type":"Retail Goods"
        },
        {
            "category":"Shopping",
            "subcategory":"Florist",
            "type":"Retail Goods"
        }
    ],
    "sg:phone":"+1 941 756 1556",
    "sg:postcode":"34203",
    "sg:province":"FL",
    "sg:tags":[
        "plant",
        "etc-retail",
        "dried",
        "basket",
        "trees-silk",
        "flowers"
    ],
    "sg:website":"http://www.onecoflorist.com",
    "wof:name":"Oneco Florist",
    "wof:placetype":"venue"
},
  "geometry": {"coordinates":[-82.546719,27.451399],"type":"Point"}
}