{
  "type": "Feature",
  "properties": {
    "iso:country":"US",
    "sg:address":"70 Butler Cir",
    "sg:city":"Leesburg",
    "sg:classifiers":[
        {
            "category":"Building & Trades",
            "subcategory":"Construction",
            "type":"Services"
        }
    ],
    "sg:phone":"+1 352 728 3085",
    "sg:postcode":"34788",
    "sg:province":"FL",
    "sg:tags":[
        "contractor"
    ],
    "wof:name":"David L Coggan Tile",
    "wof:placetype":"venue"
},
  "geometry": {"coordinates":[-81.781505,28.871803],"type":"Point"}
}