{
  "type": "Feature",
  "properties": {
    "iso:country":"US",
    "sg:address":"18798 W Dixie Hwy",
    "sg:city":"Miami",
    "sg:classifiers":[
        {
            "category":"Fast Food",
            "type":"Food & Drink"
        },
        {
            "category":"Restaurant",
            "type":"Food & Drink"
        },
        {
            "category":"Food & Beverages",
            "subcategory":"Bakery",
            "type":"Retail Goods"
        },
        {
            "category":"Food & Beverages",
            "subcategory":"Meat & Fish",
            "type":"Retail Goods"
        }
    ],
    "sg:phone":"+1 305 682 9692",
    "sg:postcode":"33180",
    "sg:province":"FL",
    "sg:tags":[
        "sandwich",
        "dog",
        "burger",
        "hot",
        "take",
        "pizza"
    ],
    "wof:name":"Famous Pita Burger Bar Inc the",
    "wof:placetype":"venue"
},
  "geometry": {"coordinates":[-80.148962,25.949342],"type":"Point"}
}