{
  "type": "Feature",
  "properties": {
    "addr:full":"3534 S University Dr Fort Lauderdale FL 33328",
    "addr:housenumber":"3534",
    "addr:postcode":"33328",
    "addr:street":"S University Dr",
    "iso:country":"US",
    "sg:address":"3534 S University Dr",
    "sg:city":"Fort Lauderdale",
    "sg:classifiers":[
        {
            "category":"Health Services",
            "subcategory":"Health Practitioner",
            "type":"Services"
        }
    ],
    "sg:phone":"+1 954 382 4343",
    "sg:postcode":"33328",
    "sg:province":"FL",
    "sg:tags":[
        "specialty",
        "outpatient"
    ],
    "wof:name":"Orthosport Inc",
    "wof:placetype":"venue"
},
  "geometry": {"coordinates":[-80.25235600000001,26.073379],"type":"Point"}
}