{
  "type": "Feature",
  "properties": {
    "iso:country":"US",
    "sg:address":"818 N Laura St",
    "sg:city":"Jacksonville",
    "sg:classifiers":[
        {
            "category":"Manufacturing",
            "subcategory":"Motor Vehicles & Parts",
            "type":"Manufacturing & Wholesale Goods"
        }
    ],
    "sg:phone":"+1 904 358 0211",
    "sg:postcode":"32202",
    "sg:province":"FL",
    "sg:tags":[
        "car",
        "transit",
        "mfg"
    ],
    "wof:name":"Bombardier Transit Corp",
    "wof:placetype":"venue"
},
  "geometry": {"coordinates":[-81.657605,30.3332],"type":"Point"}
}