{
  "type": "Feature",
  "properties": {
    "iso:country":"US",
    "sg:address":"2287 S Ridgewood Ave",
    "sg:city":"South Daytona",
    "sg:classifiers":[
        {
            "category":"Shopping",
            "subcategory":"Hobbies, Toys, & Games",
            "type":"Retail Goods"
        }
    ],
    "sg:phone":"+1 386 788 9940",
    "sg:postcode":"32119",
    "sg:province":"FL",
    "sg:tags":[
        "equipment",
        "ceramic",
        "supply"
    ],
    "wof:name":"Celestial Ceramics",
    "wof:placetype":"venue"
},
  "geometry": {"coordinates":[-81.00049199999999,29.168986],"type":"Point"}
}