{
  "type": "Feature",
  "properties": {
    "iso:country":"US",
    "sg:address":"1352 Manhattan Ave",
    "sg:city":"Sarasota",
    "sg:classifiers":[
        {
            "category":"Wholesale",
            "subcategory":"Groceries",
            "type":"Manufacturing & Wholesale Goods"
        }
    ],
    "sg:phone":"+1 941 362 7914",
    "sg:postcode":"34237",
    "sg:province":"FL",
    "sg:tags":[
        "tea",
        "coffee"
    ],
    "wof:name":"Latitude 23.5 Coffee & Tea",
    "wof:placetype":"venue"
},
  "geometry": {"coordinates":[-82.527033,27.349707],"type":"Point"}
}