{
  "type": "Feature",
  "properties": {
    "addr:full":"9460 SW 34th St Miami FL 33165",
    "addr:housenumber":"9460",
    "addr:postcode":"33165",
    "addr:street":"Sw 34Th St",
    "iso:country":"US",
    "sg:address":"9460 SW 34th St",
    "sg:city":"Miami",
    "sg:classifiers":[
        {
            "category":"Professional",
            "type":"Services"
        }
    ],
    "sg:phone":"+1 305 225 5263",
    "sg:postcode":"33165",
    "sg:province":"FL",
    "wof:name":"Cermar Inc",
    "wof:placetype":"venue"
},
  "geometry": {"coordinates":[-80.34914999999999,25.738139],"type":"Point"}
}