{
  "type": "Feature",
  "properties": {
    "iso:country":"US",
    "sg:address":"1920 S Babcock St",
    "sg:city":"Melbourne",
    "sg:phone":"+1 321 724 1727",
    "sg:postcode":"32901",
    "sg:province":"FL",
    "sg:website":"http://www.laserlightconnection.com",
    "wof:name":"Laser Light Connection",
    "wof:placetype":"venue"
},
  "geometry": {"coordinates":[-80.621461,28.079698],"type":"Point"}
}