{
  "type": "Feature",
  "properties": {
    "addr:full":"8322 Tangelo Tree Dr Orlando FL 32836",
    "addr:housenumber":"8322",
    "addr:postcode":"32836",
    "addr:street":"Tangelo Tree Dr",
    "iso:country":"US",
    "sg:address":"8322 Tangelo Tree Dr",
    "sg:city":"Orlando",
    "sg:classifiers":[
        {
            "category":"Health Services",
            "subcategory":"Health Practitioner",
            "type":"Services"
        },
        {
            "category":"Communications",
            "type":"Services"
        }
    ],
    "sg:phone":"+1 407 876 3423",
    "sg:postcode":"32836",
    "sg:province":"FL",
    "sg:tags":[
        "pathologist",
        "speech-language",
        "myofunctional",
        "therapy"
    ],
    "sg:website":"http://www.vantatenhove.com",
    "wof:name":"Gail Van Tatenhove",
    "wof:placetype":"venue"
},
  "geometry": {"coordinates":[-81.50184299999999,28.445318],"type":"Point"}
}