{
  "type": "Feature",
  "properties": {
    "addr:full":"715 NE 3rd Ave Delray Beach FL 33444",
    "addr:housenumber":"715",
    "addr:postcode":"33444",
    "addr:street":"Ne 3Rd Ave",
    "iso:country":"US",
    "sg:address":"715 NE 3rd Ave",
    "sg:city":"Delray Beach",
    "sg:classifiers":[
        {
            "category":"Health Services",
            "subcategory":"Doctor",
            "type":"Services"
        }
    ],
    "sg:phone":"+1 561 276 2020",
    "sg:postcode":"33444",
    "sg:province":"FL",
    "sg:tags":[
        "dentist"
    ],
    "wof:name":"Franklin M Boyar Pa",
    "wof:placetype":"venue"
},
  "geometry": {"coordinates":[-80.06902100000001,26.473087],"type":"Point"}
}