{
  "type": "Feature",
  "properties": {
    "iso:country":"US",
    "sg:address":"6705 SW Woodbine Way",
    "sg:city":"Palm City",
    "sg:classifiers":[
        {
            "category":"Real Estate",
            "subcategory":"Real Estate Agent",
            "type":"Services"
        }
    ],
    "sg:phone":"+1 772 781 8022",
    "sg:postcode":"34990",
    "sg:province":"FL",
    "wof:name":"Brady Properties LLC",
    "wof:placetype":"venue"
},
  "geometry": {"coordinates":[-80.345129,27.13982],"type":"Point"}
}