{
  "type": "Feature",
  "properties": {
    "addr:full":"1255 W Atlantic Blvd Pompano Beach FL 33069",
    "addr:housenumber":"1255",
    "addr:postcode":"33069",
    "addr:street":"W Atlantic Blvd",
    "iso:country":"US",
    "sg:address":"1255 W Atlantic Blvd",
    "sg:city":"Pompano Beach",
    "sg:classifiers":[
        {
            "category":"Food & Beverages",
            "subcategory":"Fruits & Vegetables",
            "type":"Retail Goods"
        }
    ],
    "sg:phone":"+1 954 784 8084",
    "sg:postcode":"33069",
    "sg:province":"FL",
    "sg:tags":[
        "produce"
    ],
    "wof:name":"Sunrise Produce Svc Inc",
    "wof:placetype":"venue"
},
  "geometry": {"coordinates":[-80.138679,26.231586],"type":"Point"}
}