{
  "type": "Feature",
  "properties": {
    "addr:full":"2601 McCoy Rd Orlando FL 32809",
    "addr:housenumber":"2601",
    "addr:postcode":"32809",
    "addr:street":"Mccoy Rd",
    "iso:country":"US",
    "sg:address":"2601 McCoy Rd",
    "sg:city":"Orlando",
    "sg:classifiers":[
        {
            "category":"Travel",
            "subcategory":"Hotels & Motels",
            "type":"Entertainment"
        }
    ],
    "sg:phone":"+1 407 856 4663",
    "sg:postcode":"32809",
    "sg:province":"FL",
    "wof:name":"Quality Inn",
    "wof:placetype":"venue"
},
  "geometry": {"coordinates":[-81.346869,28.451397],"type":"Point"}
}