{
  "type": "Feature",
  "properties": {
    "iso:country":"US",
    "sg:address":"2171 W 40th St",
    "sg:city":"Jacksonville",
    "sg:classifiers":[
        {
            "category":"Building & Trades",
            "subcategory":"Landscaping Services",
            "type":"Services"
        }
    ],
    "sg:phone":"+1 904 768 7072",
    "sg:postcode":"32209",
    "sg:province":"FL",
    "sg:tags":[
        "lawn",
        "maintenance",
        "grounds"
    ],
    "wof:name":"Handy Lawn Svc",
    "wof:placetype":"venue"
},
  "geometry": {"coordinates":[-81.696352,30.367485],"type":"Point"}
}