{
  "type": "Feature",
  "properties": {
    "addr:full":"9032 Jena Rd Spring Hill FL 34608",
    "addr:housenumber":"9032",
    "addr:postcode":"34608",
    "addr:street":"Jena Rd",
    "iso:country":"US",
    "sg:address":"9032 Jena Rd",
    "sg:city":"Spring Hill",
    "sg:classifiers":[
        {
            "category":"Building & Trades",
            "subcategory":"Landscaping Services",
            "type":"Services"
        }
    ],
    "sg:phone":"+1 352 686 7199",
    "sg:postcode":"34608",
    "sg:province":"FL",
    "sg:tags":[
        "lawn",
        "maintenance",
        "grounds"
    ],
    "wof:name":"Gerry Sutton Lawn Maintenance",
    "wof:placetype":"venue"
},
  "geometry": {"coordinates":[-82.571592,28.469197],"type":"Point"}
}