{
  "type": "Feature",
  "properties": {
    "addr:full":"10200 State Hwy 84 Davie FL 33324",
    "addr:housenumber":"10200",
    "addr:postcode":"33324",
    "addr:street":"State Hwy 84",
    "iso:country":"US",
    "sg:address":"10200 State Hwy 84",
    "sg:city":"Davie",
    "sg:classifiers":[
        {
            "category":"Recreation",
            "type":"Entertainment"
        }
    ],
    "sg:phone":"+1 954 473 8929",
    "sg:postcode":"33324",
    "sg:province":"FL",
    "sg:tags":[
        "instruction",
        "yoga"
    ],
    "wof:name":"Pure Yoga Studio",
    "wof:placetype":"venue"
},
  "geometry": {"coordinates":[-80.28321699999999,26.107524],"type":"Point"}
}