{
  "type": "Feature",
  "properties": {
    "iso:country":"US",
    "sg:address":"20325 Gator Ln",
    "sg:city":"Land O Lakes",
    "sg:classifiers":[
        {
            "category":"Education",
            "subcategory":"School",
            "type":"Public Place"
        }
    ],
    "sg:phone":"+1 813 794 9400",
    "sg:postcode":"34638",
    "sg:province":"FL",
    "wof:name":"Land O' Lakes High School",
    "wof:placetype":"venue"
},
  "geometry": {"coordinates":[-82.480191,28.261557],"type":"Point"}
}