{
  "type": "Feature",
  "properties": {
    "iso:country":"US",
    "sg:address":"2020 NE 163rd St",
    "sg:city":"North Miami Bch",
    "sg:classifiers":[
        {
            "category":"Real Estate",
            "subcategory":"Real Estate Agent",
            "type":"Services"
        }
    ],
    "sg:phone":"+1 305 944 2111",
    "sg:postcode":"33162",
    "sg:province":"FL",
    "wof:name":"Alpha Realty Management",
    "wof:placetype":"venue"
},
  "geometry": {"coordinates":[-80.160265,25.925945],"type":"Point"}
}