{
  "type": "Feature",
  "properties": {
    "addr:full":"5150 N Florida Ave Miami FL 33157",
    "addr:housenumber":"5150",
    "addr:postcode":"33157",
    "addr:street":"N Florida Ave",
    "iso:country":"US",
    "sg:address":"5150 N Florida Ave",
    "sg:city":"Miami",
    "sg:classifiers":[
        {
            "category":"Building & Trades",
            "subcategory":"Locksmith",
            "type":"Services"
        }
    ],
    "sg:phone":"+1 866 518 7775",
    "sg:postcode":"33157",
    "sg:province":"FL",
    "sg:tags":[
        "key"
    ],
    "wof:name":"Anytime Anywhere Emergency Locksmith",
    "wof:placetype":"venue"
},
  "geometry": {"coordinates":[-80.255698,25.728187],"type":"Point"}
}