{
  "type": "Feature",
  "properties": {
    "iso:country":"US",
    "sg:address":"3550 Biscayne Blvd # 602",
    "sg:city":"Miami",
    "sg:classifiers":[
        {
            "category":"Professional",
            "type":"Services"
        },
        {
            "category":"Professional",
            "subcategory":"Advertising",
            "type":"Services"
        }
    ],
    "sg:phone":"+1 305 576 1579",
    "sg:postcode":"33137",
    "sg:province":"FL",
    "sg:tags":[
        "product",
        "fair",
        "trade",
        "exposition",
        "advertising-promotional",
        "shows"
    ],
    "wof:name":"Lendleaders, Inc.",
    "wof:placetype":"venue"
},
  "geometry": {"coordinates":[-80.189491,25.81015],"type":"Point"}
}