{
  "type": "Feature",
  "properties": {
    "iso:country":"US",
    "sg:address":"50 Furness Pl",
    "sg:city":"Palm Coast",
    "sg:classifiers":[
        {
            "category":"Professional",
            "type":"Services"
        }
    ],
    "sg:phone":"+1 386 446 1885",
    "sg:postcode":"32137",
    "sg:province":"FL",
    "wof:name":"Cmsammonsinc",
    "wof:placetype":"venue"
},
  "geometry": {"coordinates":[-81.224374,29.57382],"type":"Point"}
}