{
  "type": "Feature",
  "properties": {
    "addr:full":"3111 Mahan Dr Tallahassee FL 32308",
    "addr:housenumber":"3111",
    "addr:postcode":"32308",
    "addr:street":"Mahan Dr",
    "iso:country":"US",
    "sg:address":"3111 Mahan Dr",
    "sg:city":"Tallahassee",
    "sg:classifiers":[
        {
            "category":"Restaurant",
            "type":"Food & Drink"
        }
    ],
    "sg:phone":"+1 850 656 9888",
    "sg:postcode":"32308",
    "sg:province":"FL",
    "sg:tags":[
        "house",
        "steak",
        "japanese"
    ],
    "sg:website":"http://www.japanicatally.com",
    "wof:name":"Japanica Steakhouse & Sushi Bar",
    "wof:placetype":"venue"
},
  "geometry": {"coordinates":[-84.225082,30.46105],"type":"Point"}
}