{
  "type": "Feature",
  "properties": {
    "addr:full":"26655 S Dixie Hwy Homestead FL 33032",
    "addr:housenumber":"26655",
    "addr:postcode":"33032",
    "addr:street":"S Dixie Hwy",
    "iso:country":"US",
    "sg:address":"26655 S Dixie Hwy",
    "sg:city":"Homestead",
    "sg:classifiers":[
        {
            "category":"Restaurant",
            "type":"Food & Drink"
        }
    ],
    "sg:menulink":"http://www.allmenus.com/fl/princeton-goulds/241570-yeung-ming-chinese-restaurant/menu/",
    "sg:phone":"+1 305 258 9283",
    "sg:postcode":"33032",
    "sg:province":"FL",
    "sg:tags":[
        "asian",
        "chinese"
    ],
    "wof:name":"Yeung Ming Chinese Restaurant",
    "wof:placetype":"venue"
},
  "geometry": {"coordinates":[-80.426563,25.518814],"type":"Point"}
}