{
  "type": "Feature",
  "properties": {
    "addr:full":"3190 Northlake Blvd Palm Beach Gdns FL 33403",
    "addr:housenumber":"3190",
    "addr:postcode":"33403",
    "addr:street":"Northlake Blvd Palm Beach Gdns",
    "iso:country":"US",
    "sg:address":"3190 Northlake Blvd",
    "sg:city":"Palm Beach Gdns",
    "sg:classifiers":[
        {
            "category":"Utilities",
            "subcategory":"Mobile Phone",
            "type":"Services"
        }
    ],
    "sg:phone":"+1 561 845 5411",
    "sg:postcode":"33403",
    "sg:province":"FL",
    "sg:tags":[
        "telephone",
        "cellular"
    ],
    "wof:name":"T Mobile",
    "wof:placetype":"venue"
},
  "geometry": {"coordinates":[-80.08611999999999,26.808394],"type":"Point"}
}