{
  "type": "Feature",
  "properties": {
    "iso:country":"US",
    "sg:address":"212 Jerome Dr",
    "sg:city":"Immokalee",
    "sg:classifiers":[
        {
            "category":"Wholesale",
            "subcategory":"Fruits & Vegetables",
            "type":"Manufacturing & Wholesale Goods"
        }
    ],
    "sg:phone":"+1 239 657 3147",
    "sg:postcode":"34142",
    "sg:province":"FL",
    "sg:tags":[
        "shipper"
    ],
    "wof:name":"Nobles-Collier Inc",
    "wof:placetype":"venue"
},
  "geometry": {"coordinates":[-81.413282,26.422694],"type":"Point"}
}