{
  "type": "Feature",
  "properties": {
    "iso:country":"US",
    "sg:address":"1913 Teepee Dr",
    "sg:city":"Tampa",
    "sg:classifiers":[
        {
            "category":"Shopping",
            "subcategory":"Clothing, Apparel, & Fashions",
            "type":"Retail Goods"
        }
    ],
    "sg:phone":"+1 813 962 8247",
    "sg:postcode":"33618",
    "sg:province":"FL",
    "sg:tags":[
        "garment"
    ],
    "wof:name":"Good Look",
    "wof:placetype":"venue"
},
  "geometry": {"coordinates":[-82.48411400000001,28.101295],"type":"Point"}
}