{
  "type": "Feature",
  "properties": {
    "iso:country":"US",
    "sg:address":"501 E Oak St",
    "sg:city":"Kissimmee",
    "sg:classifiers":[
        {
            "category":"Professional",
            "subcategory":"Engineering",
            "type":"Services"
        }
    ],
    "sg:phone":"+1 407 935 0649",
    "sg:postcode":"34744",
    "sg:province":"FL",
    "sg:tags":[
        "engineer"
    ],
    "wof:name":"Stottler Stagg & Assoc",
    "wof:placetype":"venue"
},
  "geometry": {"coordinates":[-81.396528,28.300543],"type":"Point"}
}