{
  "type": "Feature",
  "properties": {
    "addr:full":"8403 S Park Cir Orlando FL 32819",
    "addr:housenumber":"8403",
    "addr:postcode":"32819",
    "addr:street":"S Park Cir",
    "iso:country":"US",
    "sg:address":"8403 S Park Cir",
    "sg:city":"Orlando",
    "sg:classifiers":[
        {
            "category":"Professional",
            "subcategory":"Business Services",
            "type":"Services"
        }
    ],
    "sg:phone":"+1 407 226 8884",
    "sg:postcode":"32819",
    "sg:province":"FL",
    "sg:tags":[
        "arbitration"
    ],
    "wof:name":"Florida Department-Financial",
    "wof:placetype":"venue"
},
  "geometry": {"coordinates":[-81.425327,28.442219],"type":"Point"}
}