{
  "type": "Feature",
  "properties": {
    "iso:country":"US",
    "sg:address":"797 Port Side Dr",
    "sg:city":"Naples",
    "sg:classifiers":[
        {
            "category":"Building & Trades",
            "subcategory":"Cleaning & Sanitation",
            "type":"Services"
        }
    ],
    "sg:phone":"+1 239 649 1022",
    "sg:postcode":"34103",
    "sg:province":"FL",
    "sg:tags":[
        "house"
    ],
    "wof:name":"Gent-L Cleaning Svc",
    "wof:placetype":"venue"
},
  "geometry": {"coordinates":[-81.80663199999999,26.184273],"type":"Point"}
}