{
  "type": "Feature",
  "properties": {
    "addr:full":"1774 W 68th St Hialeah FL 33014",
    "addr:housenumber":"1774",
    "addr:postcode":"33014",
    "addr:street":"W 68Th St",
    "iso:country":"US",
    "sg:address":"1774 W 68th St",
    "sg:city":"Hialeah",
    "sg:classifiers":[
        {
            "category":"Retail",
            "subcategory":"Laundry & Dry Cleaning",
            "type":"Services"
        }
    ],
    "sg:phone":"+1 305 556 3411",
    "sg:postcode":"33014",
    "sg:province":"FL",
    "wof:name":"Diago Cleaners",
    "wof:placetype":"venue"
},
  "geometry": {"coordinates":[-80.318298,25.884199],"type":"Point"}
}