{
  "type": "Feature",
  "properties": {
    "addr:full":"493 Goodlette Rd N Naples FL 34102",
    "addr:housenumber":"493",
    "addr:postcode":"34102",
    "addr:street":"Goodlette Rd N",
    "iso:country":"US",
    "sg:address":"493 Goodlette Rd N",
    "sg:city":"Naples",
    "sg:classifiers":[
        {
            "category":"Restaurant",
            "type":"Food & Drink"
        }
    ],
    "sg:phone":"+1 239 435 3997",
    "sg:postcode":"34102",
    "sg:province":"FL",
    "sg:tags":[
        "eating"
    ],
    "wof:name":"Paradise Take Out Restaurant",
    "wof:placetype":"venue"
},
  "geometry": {"coordinates":[-81.79086700000001,26.153051],"type":"Point"}
}