{
  "type": "Feature",
  "properties": {
    "iso:country":"US",
    "sg:address":"540 The Rialto",
    "sg:city":"Venice",
    "sg:classifiers":[
        {
            "category":"Health Services",
            "subcategory":"Hospital",
            "type":"Services"
        },
        {
            "category":"Health Services",
            "subcategory":"Nursing And Care Facility",
            "type":"Services"
        }
    ],
    "sg:phone":"+1 941 483 7000",
    "sg:postcode":"34285",
    "sg:province":"FL",
    "sg:tags":[
        "urgent",
        "emergency"
    ],
    "wof:name":"Walk-In Care",
    "wof:placetype":"venue"
},
  "geometry": {"coordinates":[-82.44437499999999,27.090654],"type":"Point"}
}