{
  "type": "Feature",
  "properties": {
    "iso:country":"US",
    "sg:address":"701 NW 57th Pl",
    "sg:city":"Fort Lauderdale",
    "sg:classifiers":[
        {
            "category":"Professional",
            "type":"Services"
        }
    ],
    "sg:phone":"+1 954 489 1370",
    "sg:postcode":"33309",
    "sg:province":"FL",
    "sg:tags":[
        "establishment"
    ],
    "wof:name":"USAB Trade Bindery Inc",
    "wof:placetype":"venue"
},
  "geometry": {"coordinates":[-80.15553199999999,26.199012],"type":"Point"}
}