{
  "type": "Feature",
  "properties": {
    "iso:country":"US",
    "sg:address":"10004 N Dale Mabry Hwy",
    "sg:city":"Tampa",
    "sg:classifiers":[
        {
            "category":"Professional",
            "subcategory":"Computer Services",
            "type":"Services"
        }
    ],
    "sg:phone":"+1 813 963 0241",
    "sg:postcode":"33618",
    "sg:province":"FL",
    "sg:tags":[
        "software"
    ],
    "wof:name":"Colorbyte Software",
    "wof:placetype":"venue"
},
  "geometry": {"coordinates":[-82.504743,28.043288],"type":"Point"}
}