{
  "type": "Feature",
  "properties": {
    "iso:country":"US",
    "sg:address":"906 Verona Pl",
    "sg:city":"Tarpon Springs",
    "sg:classifiers":[
        {
            "category":"Manufacturing",
            "subcategory":"Rubber & Plastics",
            "type":"Manufacturing & Wholesale Goods"
        }
    ],
    "sg:phone":"+1 727 938 7855",
    "sg:postcode":"34689",
    "sg:province":"FL",
    "sg:tags":[
        "injection",
        "mfg",
        "product",
        "molding"
    ],
    "wof:name":"J & M Industries Inc",
    "wof:placetype":"venue"
},
  "geometry": {"coordinates":[-82.7454,28.154288],"type":"Point"}
}