{
  "type": "Feature",
  "properties": {
    "addr:full":"4477 E 11th Ave Hialeah FL 33013",
    "addr:housenumber":"4477",
    "addr:postcode":"33013",
    "addr:street":"E 11Th Ave",
    "iso:country":"US",
    "sg:address":"4477 E 11th Ave",
    "sg:city":"Hialeah",
    "sg:classifiers":[
        {
            "category":"Home & Garden",
            "subcategory":"Furniture",
            "type":"Retail Goods"
        }
    ],
    "sg:phone":"+1 305 953 4073",
    "sg:postcode":"33013",
    "sg:province":"FL",
    "sg:tags":[
        "cabinet"
    ],
    "wof:name":"General Custom Cabinet",
    "wof:placetype":"venue"
},
  "geometry": {"coordinates":[-80.260464,25.86218],"type":"Point"}
}