{
  "type": "Feature",
  "properties": {
    "addr:full":"2905 Oak Park Cir Fort Lauderdale FL 33328",
    "addr:housenumber":"2905",
    "addr:postcode":"33328",
    "addr:street":"Oak Park Cir",
    "iso:country":"US",
    "sg:address":"2905 Oak Park Cir",
    "sg:city":"Fort Lauderdale",
    "sg:classifiers":[
        {
            "category":"Professional",
            "type":"Services"
        }
    ],
    "sg:phone":"+1 954 474 8382",
    "sg:postcode":"33328",
    "sg:province":"FL",
    "wof:name":"Cfg Home Inc",
    "wof:placetype":"venue"
},
  "geometry": {"coordinates":[-80.271018,26.085659],"type":"Point"}
}