{
  "type": "Feature",
  "properties": {
    "iso:country":"US",
    "sg:address":"702 Anchor Dr",
    "sg:city":"Sanibel",
    "sg:classifiers":[
        {
            "category":"Professional",
            "type":"Services"
        }
    ],
    "sg:phone":"+1 239 395 9674",
    "sg:postcode":"33957",
    "sg:province":"FL",
    "wof:name":"Complexus Inc",
    "wof:placetype":"venue"
},
  "geometry": {"coordinates":[-82.031471,26.446584],"type":"Point"}
}