{
  "type": "Feature",
  "properties": {
    "addr:full":"305 NW 132nd Ter Ocala FL 34482",
    "addr:housenumber":"305",
    "addr:postcode":"34482",
    "addr:street":"Nw 132Nd Ter",
    "iso:country":"US",
    "sg:address":"305 NW 132nd Ter",
    "sg:city":"Ocala",
    "sg:classifiers":[
        {
            "category":"Building & Trades",
            "subcategory":"Landscaping Services",
            "type":"Services"
        }
    ],
    "sg:phone":"+1 352 237 1863",
    "sg:postcode":"34482",
    "sg:province":"FL",
    "sg:tags":[
        "lawn",
        "maintenance",
        "grounds"
    ],
    "wof:name":"Jon Jarrett Lawn Care Svc",
    "wof:placetype":"venue"
},
  "geometry": {"coordinates":[-82.339613,29.191823],"type":"Point"}
}