{
  "type": "Feature",
  "properties": {
    "addr:full":"1937 Grace Ave Fort Myers FL 33901",
    "addr:housenumber":"1937",
    "addr:postcode":"33901",
    "addr:street":"Grace Ave",
    "iso:country":"US",
    "sg:address":"1937 Grace Ave",
    "sg:city":"Fort Myers",
    "sg:classifiers":[
        {
            "category":"Professional",
            "subcategory":"Accounting & Tax Preparation",
            "type":"Services"
        }
    ],
    "sg:phone":"+1 239 939 0661",
    "sg:postcode":"33901",
    "sg:province":"FL",
    "sg:tags":[
        "accountant"
    ],
    "sg:website":"www.hissam.com",
    "wof:name":"Hissam & Associates",
    "wof:placetype":"venue"
},
  "geometry": {"coordinates":[-81.873199,26.618099],"type":"Point"}
}