{
  "type": "Feature",
  "properties": {
    "addr:full":"2015 8th St W Palmetto FL 34221",
    "addr:housenumber":"2015",
    "addr:postcode":"34221",
    "addr:street":"8Th St W",
    "iso:country":"US",
    "sg:address":"2015 8th St W",
    "sg:city":"Palmetto",
    "sg:classifiers":[
        {
            "category":"Professional",
            "subcategory":"Business Services",
            "type":"Services"
        }
    ],
    "sg:phone":"+1 941 722 3823",
    "sg:postcode":"34221",
    "sg:province":"FL",
    "wof:name":"Phone Solutions Inc",
    "wof:placetype":"venue"
},
  "geometry": {"coordinates":[-82.59016,27.518463],"type":"Point"}
}