{
  "type": "Feature",
  "properties": {
    "iso:country":"US",
    "sg:address":"10305 NW 41st St",
    "sg:city":"Doral",
    "sg:classifiers":[
        {
            "category":"Banks & Credit Unions",
            "subcategory":"Bank",
            "type":"Services"
        }
    ],
    "sg:phone":"+1 305 594 9494",
    "sg:postcode":"33178",
    "sg:province":"FL",
    "sg:tags":[
        "loan",
        "real estate"
    ],
    "wof:name":"City One Mortgage Financial",
    "wof:placetype":"venue"
},
  "geometry": {"coordinates":[-80.363643,25.811681],"type":"Point"}
}