{
  "type": "Feature",
  "properties": {
    "iso:country":"US",
    "sg:address":"6005 State Rd 29 S",
    "sg:city":"Labelle",
    "sg:classifiers":[
        {
            "category":"Bars & Pubs",
            "type":"Food & Drink"
        }
    ],
    "sg:phone":"+1 863 674 0019",
    "sg:postcode":"33935",
    "sg:province":"FL",
    "wof:name":"Los Amigos Bar",
    "wof:placetype":"venue"
},
  "geometry": {"coordinates":[-81.43764,26.729336],"type":"Point"}
}