{
  "type": "Feature",
  "properties": {
    "iso:country":"US",
    "sg:address":"9095 SW 87th Ave Ste 777",
    "sg:city":"Miami",
    "sg:classifiers":[
        {
            "category":"Real Estate",
            "subcategory":"Real Estate Services",
            "type":"Services"
        },
        {
            "category":"Real Estate",
            "subcategory":"Real Estate Operator",
            "type":"Services"
        }
    ],
    "sg:phone":"+1 305 885 3650",
    "sg:postcode":"33176",
    "sg:province":"FL",
    "sg:tags":[
        "apartment",
        "vacancy",
        "management",
        "listing",
        "property",
        "rental",
        "finder"
    ],
    "wof:name":"Professional Management Inc",
    "wof:placetype":"venue"
},
  "geometry": {"coordinates":[-80.334999,25.6856],"type":"Point"}
}