{
  "type": "Feature",
  "properties": {
    "iso:country":"US",
    "sg:address":"220 E Monument Ave",
    "sg:city":"Kissimmee",
    "sg:classifiers":[
        {
            "category":"Shopping",
            "subcategory":"Computers & Home Electronics",
            "type":"Retail Goods"
        }
    ],
    "sg:phone":"+1 407 518 1521",
    "sg:postcode":"34741",
    "sg:province":"FL",
    "sg:tags":[
        "software"
    ],
    "wof:name":"Medical Specialty Software",
    "wof:placetype":"venue"
},
  "geometry": {"coordinates":[-81.404843,28.291989],"type":"Point"}
}