{
  "type": "Feature",
  "properties": {
    "iso:country":"US",
    "sg:address":"6144 Stratton Rd",
    "sg:city":"Fort Myers",
    "sg:classifiers":[
        {
            "category":"Building & Trades",
            "subcategory":"Construction",
            "type":"Services"
        }
    ],
    "sg:phone":"+1 239 694 6032",
    "sg:postcode":"33905",
    "sg:province":"FL",
    "sg:tags":[
        "resurfacing",
        "laying",
        "refinishing",
        "floor"
    ],
    "wof:name":"Advantage Flooring",
    "wof:placetype":"venue"
},
  "geometry": {"coordinates":[-81.69622200000001,26.684043],"type":"Point"}
}