{
  "type": "Feature",
  "properties": {
    "iso:country":"US",
    "sg:address":"6820 N University Dr",
    "sg:city":"Tamarac",
    "sg:phone":"+1 954 722 3474",
    "sg:postcode":"33321",
    "sg:province":"FL",
    "sg:website":"http://www.bigalsaquariumstores.com/",
    "wof:name":"Big Al's Aquarium Supercenter",
    "wof:placetype":"venue"
},
  "geometry": {"coordinates":[-80.252253,26.206535],"type":"Point"}
}