{
  "type": "Feature",
  "properties": {
    "addr:full":"6880 46th Ave N St Petersburg FL 33709",
    "addr:housenumber":"6880",
    "addr:postcode":"33709",
    "addr:street":"46Th Ave N",
    "iso:country":"US",
    "sg:address":"6880 46th Ave N",
    "sg:city":"St Petersburg",
    "sg:classifiers":[
        {
            "category":"Personal",
            "subcategory":"Beauty Salon",
            "type":"Services"
        }
    ],
    "sg:phone":"+1 727 544 7400",
    "sg:postcode":"33709",
    "sg:province":"FL",
    "wof:name":"Lamar Beauty Shop",
    "wof:placetype":"venue"
},
  "geometry": {"coordinates":[-82.734088,27.813558],"type":"Point"}
}