{
  "type": "Feature",
  "properties": {
    "iso:country":"US",
    "sg:address":"2701 SW College Rd Ste 109",
    "sg:city":"Ocala",
    "sg:classifiers":[
        {
            "category":"Restaurant",
            "type":"Food & Drink"
        },
        {
            "category":"Ice Cream",
            "type":"Food & Drink"
        }
    ],
    "sg:phone":"+1 352 237 6553",
    "sg:postcode":"34474",
    "sg:province":"FL",
    "sg:tags":[
        "frozen",
        "dessert"
    ],
    "sg:website":"http://www.baskinrobbins.com",
    "wof:name":"Baskin Robbins",
    "wof:placetype":"venue"
},
  "geometry": {"coordinates":[-82.169281,29.165754],"type":"Point"}
}