{
  "type": "Feature",
  "properties": {
    "iso:country":"US",
    "sg:address":"1629 SE 47th St",
    "sg:city":"Cape Coral",
    "sg:classifiers":[
        {
            "category":"Organizations",
            "subcategory":"Religious Organization",
            "type":"Services"
        }
    ],
    "sg:phone":"+1 239 945 3005",
    "sg:postcode":"33904",
    "sg:province":"FL",
    "wof:name":"El Rey Jesus",
    "wof:placetype":"venue"
},
  "geometry": {"coordinates":[-81.943586,26.564727],"type":"Point"}
}