{
  "type": "Feature",
  "properties": {
    "iso:country":"US",
    "sg:address":"10790 Florence Ave",
    "sg:city":"Thonotosassa",
    "sg:classifiers":[
        {
            "category":"Wholesale",
            "subcategory":"Machinery & Supplies",
            "type":"Manufacturing & Wholesale Goods"
        },
        {
            "category":"Building & Trades",
            "subcategory":"Plumbing",
            "type":"Services"
        }
    ],
    "sg:phone":"+1 813 986 4556",
    "sg:postcode":"33592",
    "sg:province":"FL",
    "sg:tags":[
        "fire",
        "system",
        "sprinkler",
        "contractor"
    ],
    "wof:name":"Frontline Fire Protection Inc",
    "wof:placetype":"venue"
},
  "geometry": {"coordinates":[-82.297096,28.065423],"type":"Point"}
}