{
  "type": "Feature",
  "properties": {
    "addr:full":"1550 Lenox Ave Miami Beach FL 33139",
    "addr:housenumber":"1550",
    "addr:postcode":"33139",
    "addr:street":"Lenox Ave",
    "iso:country":"US",
    "sg:address":"1550 Lenox Ave",
    "sg:city":"Miami Beach",
    "sg:classifiers":[
        {
            "category":"Travel",
            "subcategory":"Campground",
            "type":"Entertainment"
        }
    ],
    "sg:phone":"+1 305 673 3310",
    "sg:postcode":"33139",
    "sg:province":"FL",
    "sg:tags":[
        "camp"
    ],
    "wof:name":"Kenmont & Kenwood Camps",
    "wof:placetype":"venue"
},
  "geometry": {"coordinates":[-80.139989,25.788131],"type":"Point"}
}