{
  "type": "Feature",
  "properties": {
    "addr:full":"18478 E Hwy 40 Silver Springs FL 34488",
    "addr:housenumber":"18478",
    "addr:postcode":"34488",
    "addr:street":"E Hwy 40",
    "iso:country":"US",
    "sg:address":"18478 E Hwy 40",
    "sg:city":"Silver Springs",
    "sg:classifiers":[
        {
            "category":"Restaurant",
            "type":"Food & Drink"
        }
    ],
    "sg:phone":"+1 352 625 6489",
    "sg:postcode":"34488",
    "sg:province":"FL",
    "sg:tags":[
        "eating"
    ],
    "wof:name":"Lenas Seafood Inc",
    "wof:placetype":"venue"
},
  "geometry": {"coordinates":[-81.844157,29.173118],"type":"Point"}
}