{
  "type": "Feature",
  "properties": {
    "addr:full":"5601 S Flamingo Rd Fort Lauderdale FL 33330",
    "addr:housenumber":"5601",
    "addr:postcode":"33330",
    "addr:street":"S Flamingo Rd",
    "iso:country":"US",
    "sg:address":"5601 S Flamingo Rd",
    "sg:city":"Fort Lauderdale",
    "sg:classifiers":[
        {
            "category":"Organizations",
            "subcategory":"Religious Organization",
            "type":"Services"
        }
    ],
    "sg:phone":"+1 954 434 3777",
    "sg:postcode":"33330",
    "sg:province":"FL",
    "sg:tags":[
        "catholic",
        "church"
    ],
    "wof:name":"Saint Marks Church",
    "wof:placetype":"venue"
},
  "geometry": {"coordinates":[-80.31319999999999,26.048762],"type":"Point"}
}