{
  "type": "Feature",
  "properties": {
    "addr:full":"2663 Airport Pulling Rd S Naples FL 34112",
    "addr:housenumber":"2663",
    "addr:postcode":"34112",
    "addr:street":"Airport Pulling Rd S",
    "iso:country":"US",
    "sg:address":"2663 Airport Pulling Rd S",
    "sg:city":"Naples",
    "sg:classifiers":[
        {
            "category":"Professional",
            "subcategory":"Lawyer & Legal Services",
            "type":"Services"
        }
    ],
    "sg:phone":"+1 239 643 4888",
    "sg:postcode":"34112",
    "sg:province":"FL",
    "sg:tags":[
        "attorney"
    ],
    "wof:name":"Edward R Bryant Jr",
    "wof:placetype":"venue"
},
  "geometry": {"coordinates":[-81.76637100000001,26.130545],"type":"Point"}
}