{
  "type": "Feature",
  "properties": {
    "iso:country":"US",
    "sg:address":"1 E Broward Blvd",
    "sg:city":"Fort Lauderdale",
    "sg:classifiers":[
        {
            "category":"Shopping",
            "subcategory":"News",
            "type":"Retail Goods"
        }
    ],
    "sg:phone":"+1 954 527 5566",
    "sg:postcode":"33301",
    "sg:province":"FL",
    "sg:tags":[
        "c",
        "toiletry",
        "gift",
        "greeting",
        "cigarette",
        "newspaper"
    ],
    "wof:name":"Long Drycleaners Inc",
    "wof:placetype":"venue"
},
  "geometry": {"coordinates":[-80.142483,26.12227],"type":"Point"}
}