{
  "type": "Feature",
  "properties": {
    "iso:country":"US",
    "sg:address":"1516 E Concord St",
    "sg:city":"Orlando",
    "sg:classifiers":[
        {
            "category":"Professional",
            "subcategory":"Lawyer & Legal Services",
            "type":"Services"
        }
    ],
    "sg:phone":"+1 407 898 1871",
    "sg:postcode":"32803",
    "sg:province":"FL",
    "sg:tags":[
        "attorney"
    ],
    "wof:name":"Edward R Gay Attorney At Law",
    "wof:placetype":"venue"
},
  "geometry": {"coordinates":[-81.36155599999999,28.551228],"type":"Point"}
}