{
  "type": "Feature",
  "properties": {
    "iso:country":"US",
    "sg:address":"3863 NW 35th St",
    "sg:city":"Pompano Beach",
    "sg:classifiers":[
        {
            "category":"Food & Beverages",
            "subcategory":"Groceries & Convenience Stores",
            "type":"Retail Goods"
        }
    ],
    "sg:phone":"+1 954 973 2481",
    "sg:postcode":"33066",
    "sg:province":"FL",
    "wof:name":"Great Art 4 Less Inc",
    "wof:placetype":"venue"
},
  "geometry": {"coordinates":[-80.18044,26.271334],"type":"Point"}
}