{
  "type": "Feature",
  "properties": {
    "iso:country":"US",
    "sg:address":"5612 SW 107th Ave",
    "sg:city":"Jasper",
    "sg:classifiers":[
        {
            "category":"Building & Trades",
            "subcategory":"Construction",
            "type":"Services"
        }
    ],
    "sg:phone":"+1 386 792 1133",
    "sg:postcode":"32052",
    "sg:province":"FL",
    "sg:tags":[
        "system",
        "specialty",
        "heating",
        "contractor",
        "air conditioning"
    ],
    "wof:name":"Lands Heating & Air",
    "wof:placetype":"venue"
},
  "geometry": {"coordinates":[-82.95504699999999,30.472946],"type":"Point"}
}