{
  "type": "Feature",
  "properties": {
    "iso:country":"US",
    "sg:address":"5340 Clark Rd",
    "sg:city":"Sarasota",
    "sg:classifiers":[
        {
            "category":"Shopping",
            "type":"Retail Goods"
        }
    ],
    "sg:phone":"+1 941 929 1029",
    "sg:postcode":"34233",
    "sg:province":"FL",
    "sg:tags":[
        "merchandise"
    ],
    "wof:name":"Stargazer Telecom Inc",
    "wof:placetype":"venue"
},
  "geometry": {"coordinates":[-82.46405300000001,27.269033],"type":"Point"}
}