{
  "type": "Feature",
  "properties": {
    "iso:country":"US",
    "sg:address":"44009 Highway 27",
    "sg:city":"Davenport",
    "sg:classifiers":[
        {
            "category":"Food & Beverages",
            "subcategory":"Groceries & Convenience Stores",
            "type":"Retail Goods"
        }
    ],
    "sg:phone":"+1 863 424 2222",
    "sg:postcode":"33897",
    "sg:province":"FL",
    "sg:website":"www.sunocoinc.com",
    "wof:name":"Speedway Sunoco",
    "wof:placetype":"venue"
},
  "geometry": {"coordinates":[-81.649399,28.2316],"type":"Point"}
}