{
  "type": "Feature",
  "properties": {
    "iso:country":"US",
    "sg:address":"505 Royal Palm Beach Blvd",
    "sg:city":"West Palm Beach",
    "sg:classifiers":[
        {
            "category":"Professional",
            "subcategory":"Lawyer & Legal Services",
            "type":"Services"
        }
    ],
    "sg:phone":"+1 561 792 1771",
    "sg:postcode":"33411",
    "sg:province":"FL",
    "wof:name":"Monica Caruso Kalker",
    "wof:placetype":"venue"
},
  "geometry": {"coordinates":[-80.23016699999999,26.684146],"type":"Point"}
}