{
  "type": "Feature",
  "properties": {
    "addr:full":"160 E Tarpon Ave Tarpon Springs FL 34689",
    "addr:housenumber":"160",
    "addr:postcode":"34689",
    "addr:street":"E Tarpon Ave",
    "iso:country":"US",
    "sg:address":"160 E Tarpon Ave",
    "sg:city":"Tarpon Springs",
    "sg:classifiers":[
        {
            "category":"Government",
            "subcategory":"Office",
            "type":"Public Place"
        }
    ],
    "sg:phone":"+1 727 943 4624",
    "sg:postcode":"34689",
    "sg:province":"FL",
    "sg:tags":[
        "village"
    ],
    "wof:name":"Tarpon Springs Historical Scty",
    "wof:placetype":"venue"
},
  "geometry": {"coordinates":[-82.75559,28.146161],"type":"Point"}
}