{
  "type": "Feature",
  "properties": {
    "addr:full":"9307 Vis del Lago Boca Raton FL 33428",
    "addr:housenumber":"9307",
    "addr:postcode":"33428",
    "addr:street":"Vis Del Lago",
    "iso:country":"US",
    "sg:address":"9307 Vis del Lago",
    "sg:city":"Boca Raton",
    "sg:classifiers":[
        {
            "category":"Shopping",
            "type":"Retail Goods"
        }
    ],
    "sg:phone":"+1 561 488 2664",
    "sg:postcode":"33428",
    "sg:province":"FL",
    "sg:tags":[
        "merchandise"
    ],
    "wof:name":"Michigan Hearing Instrs Inc",
    "wof:placetype":"venue"
},
  "geometry": {"coordinates":[-80.187878,26.353464],"type":"Point"}
}