{
  "type": "Feature",
  "properties": {
    "addr:full":"13102 Luntz Point Ln Windermere FL 34786",
    "addr:housenumber":"13102",
    "addr:postcode":"34786",
    "addr:street":"Luntz Point Ln",
    "iso:country":"US",
    "sg:address":"13102 Luntz Point Ln",
    "sg:city":"Windermere",
    "sg:classifiers":[
        {
            "category":"Arts & Performance",
            "subcategory":"Theater",
            "type":"Entertainment"
        }
    ],
    "sg:phone":"+1 407 876 6886",
    "sg:postcode":"34786",
    "sg:province":"FL",
    "sg:tags":[
        "theatrical"
    ],
    "wof:name":"Disconnected Inc",
    "wof:placetype":"venue"
},
  "geometry": {"coordinates":[-81.578834,28.5101],"type":"Point"}
}