{
  "type": "Feature",
  "properties": {
    "iso:country":"US",
    "sg:address":"8028 NW 68th St",
    "sg:city":"Miami",
    "sg:classifiers":[
        {
            "category":"Utilities",
            "subcategory":"Electric",
            "type":"Services"
        },
        {
            "category":"Home & Garden",
            "subcategory":"Building Materials",
            "type":"Retail Goods"
        }
    ],
    "sg:phone":"+1 305 591 8448",
    "sg:postcode":"33166",
    "sg:province":"FL",
    "sg:tags":[
        "equipment",
        "lighting",
        "fixture"
    ],
    "wof:name":"A & L Electrical Sales",
    "wof:placetype":"venue"
},
  "geometry": {"coordinates":[-80.32849899999999,25.8354],"type":"Point"}
}