{
  "type": "Feature",
  "properties": {
    "addr:full":"8000 S Orange Ave Orlando FL 32809",
    "addr:housenumber":"8000",
    "addr:postcode":"32809",
    "addr:street":"S Orange Ave",
    "iso:country":"US",
    "sg:address":"8000 S Orange Ave",
    "sg:city":"Orlando",
    "sg:classifiers":[
        {
            "category":"Freight",
            "type":"Transportation"
        }
    ],
    "sg:phone":"+1 407 855 4624",
    "sg:postcode":"32809",
    "sg:province":"FL",
    "sg:tags":[
        "local",
        "storage",
        "trucking"
    ],
    "wof:name":"A Christian Movers",
    "wof:placetype":"venue"
},
  "geometry": {"coordinates":[-81.36373399999999,28.450977],"type":"Point"}
}