{
  "type": "Feature",
  "properties": {
    "addr:full":"3001 SW 107th Ave Miami FL 33165",
    "addr:housenumber":"3001",
    "addr:postcode":"33165",
    "addr:street":"Sw 107Th Ave",
    "iso:country":"US",
    "sg:address":"3001 SW 107th Ave",
    "sg:city":"Miami",
    "sg:classifiers":[
        {
            "category":"Health Services",
            "subcategory":"Clinic",
            "type":"Services"
        }
    ],
    "sg:phone":"+1 305 220 9566",
    "sg:postcode":"33165",
    "sg:province":"FL",
    "sg:tags":[
        "home"
    ],
    "wof:name":"Marcos Home Health Svc Corp",
    "wof:placetype":"venue"
},
  "geometry": {"coordinates":[-80.36772999999999,25.740418],"type":"Point"}
}