{
  "type": "Feature",
  "properties": {
    "addr:full":"3950 Dixon St Zephyrhills FL 33542",
    "addr:housenumber":"3950",
    "addr:postcode":"33542",
    "addr:street":"Dixon St",
    "iso:country":"US",
    "sg:address":"3950 Dixon St",
    "sg:city":"Zephyrhills",
    "sg:classifiers":[
        {
            "category":"Real Estate",
            "subcategory":"Real Estate Operator",
            "type":"Services"
        }
    ],
    "sg:phone":"+1 813 782 3597",
    "sg:postcode":"33542",
    "sg:province":"FL",
    "sg:tags":[
        "mobile",
        "home",
        "site"
    ],
    "wof:name":"Zephyr Mobile Park",
    "wof:placetype":"venue"
},
  "geometry": {"coordinates":[-82.182188,28.215026],"type":"Point"}
}