{
  "type": "Feature",
  "properties": {
    "iso:country":"US",
    "sg:address":"130 SW Nassau St",
    "sg:city":"Lake City",
    "sg:classifiers":[
        {
            "category":"Retail",
            "subcategory":"Auto Repair",
            "type":"Services"
        }
    ],
    "sg:phone":"+1 386 755 1222",
    "sg:postcode":"32025",
    "sg:province":"FL",
    "sg:tags":[
        "repairing",
        "automobile"
    ],
    "wof:name":"Vistar Auto Glass",
    "wof:placetype":"venue"
},
  "geometry": {"coordinates":[-82.638445,30.188565],"type":"Point"}
}