{
  "type": "Feature",
  "properties": {
    "iso:country":"US",
    "sg:address":"5170 Coconut Creek Pkwy",
    "sg:city":"Margate",
    "sg:classifiers":[
        {
            "category":"Professional",
            "subcategory":"Accounting & Tax Preparation",
            "type":"Services"
        },
        {
            "category":"Insurance",
            "subcategory":"Hazard Insurance",
            "type":"Services"
        }
    ],
    "sg:phone":"+1 954 977 4201",
    "sg:postcode":"33063",
    "sg:province":"FL",
    "sg:tags":[
        "commercial",
        "return",
        "business",
        "preparation-business"
    ],
    "wof:name":"Mdax Insurance Service",
    "wof:placetype":"venue"
},
  "geometry": {"coordinates":[-80.196369,26.244523],"type":"Point"}
}