{
  "type": "Feature",
  "properties": {
    "addr:full":"908 NW 69th Ter Gainesville FL 32605",
    "addr:housenumber":"908",
    "addr:postcode":"32605",
    "addr:street":"Nw 69Th Ter",
    "iso:country":"US",
    "sg:address":"908 NW 69th Ter",
    "sg:city":"Gainesville",
    "sg:classifiers":[
        {
            "category":"Restaurant",
            "type":"Food & Drink"
        }
    ],
    "sg:phone":"+1 352 331 0069",
    "sg:postcode":"32605",
    "sg:province":"FL",
    "wof:name":"Mori Japanese Steak House",
    "wof:placetype":"venue"
},
  "geometry": {"coordinates":[-82.416512,29.660451],"type":"Point"}
}