{
  "type": "Feature",
  "properties": {
    "iso:country":"US",
    "sg:address":"324 W Van Buren St",
    "sg:city":"Tallahassee",
    "sg:classifiers":[
        {
            "category":"Professional",
            "subcategory":"Art Services",
            "type":"Services"
        }
    ],
    "sg:phone":"+1 850 224 6414",
    "sg:postcode":"32301",
    "sg:province":"FL",
    "sg:tags":[
        "graphic",
        "designer"
    ],
    "sg:website":"www.wildernessgraphics.com",
    "wof:name":"Wilderness Graphics",
    "wof:placetype":"venue"
},
  "geometry": {"coordinates":[-84.284897,30.432445],"type":"Point"}
}