{
  "type": "Feature",
  "properties": {
    "iso:country":"US",
    "sg:address":"2489 SW 17th St",
    "sg:city":"Miami",
    "sg:classifiers":[
        {
            "category":"Wholesale",
            "subcategory":"Medical Equipment & Supplies",
            "type":"Manufacturing & Wholesale Goods"
        }
    ],
    "sg:phone":"+1 305 856 4291",
    "sg:postcode":"33145",
    "sg:province":"FL",
    "wof:name":"L&I Medical Equipment Inc",
    "wof:placetype":"venue"
},
  "geometry": {"coordinates":[-80.234854,25.756145],"type":"Point"}
}