{
  "type": "Feature",
  "properties": {
    "iso:country":"US",
    "sg:address":"9801 Quail Hollow Rd",
    "sg:city":"Fort Myers",
    "sg:classifiers":[
        {
            "category":"Retail",
            "subcategory":"Laundry & Dry Cleaning",
            "type":"Services"
        }
    ],
    "sg:phone":"+1 239 731 6173",
    "sg:postcode":"33917",
    "sg:province":"FL",
    "sg:tags":[
        "cleaners",
        "rug",
        "carpet"
    ],
    "wof:name":"American Carpet Cleaning",
    "wof:placetype":"venue"
},
  "geometry": {"coordinates":[-81.798689,26.755393],"type":"Point"}
}