{
  "type": "Feature",
  "properties": {
    "iso:country":"US",
    "sg:address":"1730 Shadowood Ln",
    "sg:city":"Jacksonville",
    "sg:classifiers":[
        {
            "category":"Manufacturing",
            "subcategory":"Printing",
            "type":"Manufacturing & Wholesale Goods"
        }
    ],
    "sg:phone":"+1 904 348 0980",
    "sg:postcode":"32207",
    "sg:province":"FL",
    "sg:tags":[
        "publisher"
    ],
    "wof:name":"Mac Millian Mc Graw Hill",
    "wof:placetype":"venue"
},
  "geometry": {"coordinates":[-81.616384,30.307329],"type":"Point"}
}