{
  "type": "Feature",
  "properties": {
    "addr:full":"4600 S Ocean Blvd Boca Raton FL 33487",
    "addr:housenumber":"4600",
    "addr:postcode":"33487",
    "addr:street":"S Ocean Blvd",
    "iso:country":"US",
    "sg:address":"4600 S Ocean Blvd",
    "sg:city":"Boca Raton",
    "sg:classifiers":[
        {
            "category":"Real Estate",
            "subcategory":"Real Estate Operator",
            "type":"Services"
        },
        {
            "category":"Organizations",
            "subcategory":"Community Association",
            "type":"Services"
        }
    ],
    "sg:phone":"+1 561 395 9334",
    "sg:postcode":"33487",
    "sg:province":"FL",
    "sg:tags":[
        "condominium"
    ],
    "wof:name":"Canron House Condominium Assn",
    "wof:placetype":"venue"
},
  "geometry": {"coordinates":[-80.066537,26.394613],"type":"Point"}
}