{
  "type": "Feature",
  "properties": {
    "iso:country":"US",
    "sg:address":"5350 86th St W",
    "sg:city":"Bradenton",
    "sg:classifiers":[
        {
            "category":"Professional",
            "subcategory":"Detective & Security Services",
            "type":"Services"
        }
    ],
    "sg:phone":"+1 941 792 6453",
    "sg:postcode":"34210",
    "sg:province":"FL",
    "sg:tags":[
        "guard",
        "patrol"
    ],
    "wof:name":"Tidy Island Gate House",
    "wof:placetype":"venue"
},
  "geometry": {"coordinates":[-82.64864799999999,27.449658],"type":"Point"}
}