{
  "type": "Feature",
  "properties": {
    "addr:full":"326 S 2nd St Fort Pierce FL 34950",
    "addr:housenumber":"326",
    "addr:postcode":"34950",
    "addr:street":"S 2Nd St",
    "iso:country":"US",
    "sg:address":"326 S 2nd St",
    "sg:city":"Fort Pierce",
    "sg:classifiers":[
        {
            "category":"Professional",
            "subcategory":"Business Services",
            "type":"Services"
        }
    ],
    "sg:phone":"+1 772 461 2420",
    "sg:postcode":"34950",
    "sg:province":"FL",
    "wof:name":"Gallott-Hilburn Bail Bonds",
    "wof:placetype":"venue"
},
  "geometry": {"coordinates":[-80.32306,27.444869],"type":"Point"}
}