{
  "type": "Feature",
  "properties": {
    "iso:country":"US",
    "sg:address":"2653 Parrish Cemetery Rd",
    "sg:city":"Jacksonville",
    "sg:classifiers":[
        {
            "category":"Building & Trades",
            "subcategory":"Plumbing",
            "type":"Services"
        }
    ],
    "sg:phone":"+1 904 693 0250",
    "sg:postcode":"32221",
    "sg:province":"FL",
    "sg:tags":[
        "contractor"
    ],
    "wof:name":"Beckwith Plumbing Inc",
    "wof:placetype":"venue"
},
  "geometry": {"coordinates":[-81.82483999999999,30.269732],"type":"Point"}
}