{
  "type": "Feature",
  "properties": {
    "addr:full":"310 SW Ocean Blvd Stuart FL 34994",
    "addr:housenumber":"310",
    "addr:postcode":"34994",
    "addr:street":"Sw Ocean Blvd",
    "iso:country":"US",
    "sg:address":"310 SW Ocean Blvd",
    "sg:city":"Stuart",
    "sg:classifiers":[
        {
            "category":"Professional",
            "subcategory":"Lawyer & Legal Services",
            "type":"Services"
        }
    ],
    "sg:phone":"+1 772 287 0660",
    "sg:postcode":"34994",
    "sg:province":"FL",
    "sg:tags":[
        "attorney"
    ],
    "wof:name":"Woods Walter G",
    "wof:placetype":"venue"
},
  "geometry": {"coordinates":[-80.25555799999999,27.197494],"type":"Point"}
}