{
  "type": "Feature",
  "properties": {
    "addr:full":"12045 Us Highway 1 North Palm Beach FL 33408",
    "addr:housenumber":"12045",
    "addr:postcode":"33408",
    "addr:street":"Us Highway 1 North",
    "iso:country":"US",
    "sg:address":"12045 Us Highway 1",
    "sg:city":"North Palm Beach",
    "sg:classifiers":[
        {
            "category":"Restaurant",
            "type":"Food & Drink"
        }
    ],
    "sg:menulink":"http://www.allmenus.com/fl/riviera-beach/160051-burger-king/menu/",
    "sg:phone":"+1 561 694 0354",
    "sg:postcode":"33408",
    "sg:province":"FL",
    "sg:tags":[
        "burger",
        "american"
    ],
    "wof:name":"Burger King",
    "wof:placetype":"venue"
},
  "geometry": {"coordinates":[-80.05873099999999,26.853504],"type":"Point"}
}