{
  "type": "Feature",
  "properties": {
    "iso:country":"US",
    "sg:address":"1823 Longwood Lake Mary Rd",
    "sg:city":"Longwood",
    "sg:classifiers":[
        {
            "category":"Food & Beverages",
            "subcategory":"Groceries & Convenience Stores",
            "type":"Retail Goods"
        }
    ],
    "sg:phone":"+1 407 331 6530",
    "sg:postcode":"32750",
    "sg:province":"FL",
    "wof:name":"Circle K Store",
    "wof:placetype":"venue"
},
  "geometry": {"coordinates":[-81.33617099999999,28.72691],"type":"Point"}
}