{
  "type": "Feature",
  "properties": {
    "iso:country":"US",
    "sg:address":"3724 SW 49th Pl",
    "sg:city":"Fort Lauderdale",
    "sg:classifiers":[
        {
            "category":"Retail",
            "subcategory":"Repair Shop",
            "type":"Services"
        }
    ],
    "sg:phone":"+1 954 963 2991",
    "sg:postcode":"33312",
    "sg:province":"FL",
    "sg:tags":[
        "welding"
    ],
    "wof:name":"Becker Welding Svc",
    "wof:placetype":"venue"
},
  "geometry": {"coordinates":[-80.196856,26.060411],"type":"Point"}
}