{
  "type": "Feature",
  "properties": {
    "addr:full":"5327 Woods West Dr Lake Worth FL 33463",
    "addr:housenumber":"5327",
    "addr:postcode":"33463",
    "addr:street":"Woods West Dr",
    "iso:country":"US",
    "sg:address":"5327 Woods West Dr",
    "sg:city":"Lake Worth",
    "sg:classifiers":[
        {
            "category":"Manufacturing",
            "subcategory":"Motor Vehicles & Parts",
            "type":"Manufacturing & Wholesale Goods"
        }
    ],
    "sg:phone":"+1 561 704 4600",
    "sg:postcode":"33463",
    "sg:province":"FL",
    "sg:tags":[
        "body",
        "mfg"
    ],
    "wof:name":"Swamp Rat Inc",
    "wof:placetype":"venue"
},
  "geometry": {"coordinates":[-80.11931800000001,26.599583],"type":"Point"}
}