{
  "type": "Feature",
  "properties": {
    "iso:country":"US",
    "sg:address":"17480 SW 254th St",
    "sg:city":"Homestead",
    "sg:classifiers":[
        {
            "category":"Home & Garden",
            "subcategory":"Garden Supply",
            "type":"Retail Goods"
        },
        {
            "category":"Farming",
            "subcategory":"Nursery",
            "type":"Manufacturing & Wholesale Goods"
        }
    ],
    "sg:phone":"+1 305 248 0573",
    "sg:postcode":"33031",
    "sg:province":"FL",
    "sg:tags":[
        "equipment",
        "seed",
        "growers'",
        "bulb"
    ],
    "wof:name":"Stepping Stone Nursery Inc",
    "wof:placetype":"venue"
},
  "geometry": {"coordinates":[-80.47568800000001,25.53026],"type":"Point"}
}