{
  "type": "Feature",
  "properties": {
    "addr:full":"10500 NW 7th Ave Miami FL 33150",
    "addr:housenumber":"10500",
    "addr:postcode":"33150",
    "addr:street":"Nw 7Th Ave",
    "iso:country":"US",
    "sg:address":"10500 NW 7th Ave",
    "sg:city":"Miami",
    "sg:classifiers":[
        {
            "category":"Restaurant",
            "type":"Food & Drink"
        }
    ],
    "sg:phone":"+1 305 751 3594",
    "sg:postcode":"33150",
    "sg:province":"FL",
    "sg:tags":[
        "banquet",
        "rooms"
    ],
    "wof:name":"New Shiloh Missionary Baptist",
    "wof:placetype":"venue"
},
  "geometry": {"coordinates":[-80.21004000000001,25.871928],"type":"Point"}
}