{
  "type": "Feature",
  "properties": {
    "iso:country":"US",
    "sg:address":"512 Spencer Dr",
    "sg:city":"West Palm Beach",
    "sg:classifiers":[
        {
            "category":"Organizations",
            "subcategory":"Religious Organization",
            "type":"Services"
        },
        {
            "category":"Education",
            "subcategory":"School",
            "type":"Public Place"
        }
    ],
    "sg:phone":"+1 561 683 6266",
    "sg:postcode":"33409",
    "sg:province":"FL",
    "sg:website":"www.cardinalnewman.com",
    "wof:name":"Cardinal Newman High School",
    "wof:placetype":"venue"
},
  "geometry": {"coordinates":[-80.093636,26.709638],"type":"Point"}
}