{
  "type": "Feature",
  "properties": {
    "addr:full":"215 6th St SW Winter Haven FL 33880",
    "addr:housenumber":"215",
    "addr:postcode":"33880",
    "addr:street":"6Th St Sw",
    "iso:country":"US",
    "sg:address":"215 6th St SW",
    "sg:city":"Winter Haven",
    "sg:classifiers":[
        {
            "category":"Manufacturing",
            "subcategory":"Tools & Machinery",
            "type":"Manufacturing & Wholesale Goods"
        }
    ],
    "sg:phone":"+1 863 299 7839",
    "sg:postcode":"33880",
    "sg:province":"FL",
    "sg:tags":[
        "die",
        "cutting"
    ],
    "wof:name":"Container Graphics Corp",
    "wof:placetype":"venue"
},
  "geometry": {"coordinates":[-81.73330900000001,28.018937],"type":"Point"}
}