{
  "type": "Feature",
  "properties": {
    "iso:country":"US",
    "sg:address":"12461 Hobson Simmons Rd",
    "sg:city":"Lithia",
    "sg:classifiers":[
        {
            "category":"Shopping",
            "subcategory":"Gifts & Souvenirs",
            "type":"Retail Goods"
        }
    ],
    "sg:phone":"+1 813 684 7604",
    "sg:postcode":"33547",
    "sg:province":"FL",
    "wof:name":"Whatnots Gifts & More",
    "wof:placetype":"venue"
},
  "geometry": {"coordinates":[-82.215636,27.797736],"type":"Point"}
}