{
  "type": "Feature",
  "properties": {
    "addr:full":"8020 SW 13th Ter Miami FL 33144",
    "addr:housenumber":"8020",
    "addr:postcode":"33144",
    "addr:street":"Sw 13Th Ter",
    "iso:country":"US",
    "sg:address":"8020 SW 13th Ter",
    "sg:city":"Miami",
    "sg:classifiers":[
        {
            "category":"Wholesale",
            "subcategory":"Computers",
            "type":"Manufacturing & Wholesale Goods"
        }
    ],
    "sg:phone":"+1 305 261 5888",
    "sg:postcode":"33144",
    "sg:province":"FL",
    "wof:name":"Hq Computers Corp",
    "wof:placetype":"venue"
},
  "geometry": {"coordinates":[-80.327648,25.757253],"type":"Point"}
}