{
  "type": "Feature",
  "properties": {
    "addr:full":"420 S Harbor City Blvd Melbourne FL 32901",
    "addr:housenumber":"420",
    "addr:postcode":"32901",
    "addr:street":"S Harbor City Blvd",
    "iso:country":"US",
    "sg:address":"420 S Harbor City Blvd",
    "sg:city":"Melbourne",
    "sg:classifiers":[
        {
            "category":"Local Transit",
            "type":"Transportation"
        }
    ],
    "sg:phone":"+1 321 725 2225",
    "sg:postcode":"32901",
    "sg:province":"FL",
    "wof:name":"American Transportation Group",
    "wof:placetype":"venue"
},
  "geometry": {"coordinates":[-80.61309,28.100074],"type":"Point"}
}