{
  "type": "Feature",
  "properties": {
    "iso:country":"US",
    "sg:address":"706 SE 15 St",
    "sg:city":"Oak Ridge",
    "sg:classifiers":[
        {
            "category":"Building & Trades",
            "subcategory":"Construction",
            "type":"Services"
        }
    ],
    "sg:phone":"+1 973 663 4700",
    "sg:postcode":"32641",
    "sg:province":"FL",
    "sg:tags":[
        "concrete",
        "contractor"
    ],
    "wof:name":"Stephen Swentzel Concrete",
    "wof:placetype":"venue"
},
  "geometry": {"coordinates":[-82.30593399999999,29.644622],"type":"Point"}
}