{
  "type": "Feature",
  "properties": {
    "iso:country":"US",
    "sg:address":"216 S Center St",
    "sg:city":"Winter Park",
    "sg:classifiers":[
        {
            "category":"Professional",
            "subcategory":"Management & Consulting",
            "type":"Services"
        }
    ],
    "sg:phone":"+1 407 629 9002",
    "sg:postcode":"32789",
    "sg:province":"FL",
    "sg:tags":[
        "consultant",
        "business"
    ],
    "wof:name":"Thunder Road Management Group",
    "wof:placetype":"venue"
},
  "geometry": {"coordinates":[-81.35039500000001,28.596657],"type":"Point"}
}