{
  "type": "Feature",
  "properties": {
    "addr:full":"1516 S Woodland Blvd Deland FL 32720",
    "addr:housenumber":"1516",
    "addr:postcode":"32720",
    "addr:street":"S Woodland Blvd",
    "iso:country":"US",
    "sg:address":"1516 S Woodland Blvd",
    "sg:city":"Deland",
    "sg:classifiers":[
        {
            "category":"Shopping",
            "subcategory":"Books",
            "type":"Retail Goods"
        }
    ],
    "sg:phone":"+1 386 624 6963",
    "sg:postcode":"32720",
    "sg:province":"FL",
    "sg:tags":[
        "dealers-used",
        "rare"
    ],
    "wof:name":"Books Books Books",
    "wof:placetype":"venue"
},
  "geometry": {"coordinates":[-81.30274,29.002052],"type":"Point"}
}