{
  "type": "Feature",
  "properties": {
    "iso:country":"US",
    "sg:address":"3032 SW 23rd Ave",
    "sg:city":"Cape Coral",
    "sg:classifiers":[
        {
            "category":"Freight",
            "type":"Transportation"
        }
    ],
    "sg:phone":"+1 239 542 3574",
    "sg:postcode":"33914",
    "sg:province":"FL",
    "sg:tags":[
        "delivery",
        "janitorial"
    ],
    "wof:name":"Thomas Egbert",
    "wof:placetype":"venue"
},
  "geometry": {"coordinates":[-82.020411,26.595469],"type":"Point"}
}