{
  "type": "Feature",
  "properties": {
    "addr:full":"13476 Marquette Blvd Fort Myers FL 33905",
    "addr:housenumber":"13476",
    "addr:postcode":"33905",
    "addr:street":"Marquette Blvd",
    "iso:country":"US",
    "sg:address":"13476 Marquette Blvd",
    "sg:city":"Fort Myers",
    "sg:classifiers":[
        {
            "category":"Building & Trades",
            "subcategory":"Equipment Rental",
            "type":"Services"
        }
    ],
    "sg:phone":"+1 239 693 6746",
    "sg:postcode":"33905",
    "sg:province":"FL",
    "sg:tags":[
        "residential",
        "construction"
    ],
    "wof:name":"Royal Crown Enterprises",
    "wof:placetype":"venue"
},
  "geometry": {"coordinates":[-81.73568299999999,26.71425],"type":"Point"}
}