{
  "type": "Feature",
  "properties": {
    "iso:country":"US",
    "sg:address":"471 N Alafaya Trl",
    "sg:city":"Orlando",
    "sg:classifiers":[
        {
            "category":"Bakery",
            "type":"Food & Drink"
        }
    ],
    "sg:menulink":"http://www.allmenus.com/fl/union-park/30484-panera-bread/menu/",
    "sg:phone":"+1 407 737 3011",
    "sg:postcode":"32828",
    "sg:province":"FL",
    "sg:tags":[
        "american",
        "sandwich",
        "pastry"
    ],
    "wof:name":"Panera Bread",
    "wof:placetype":"venue"
},
  "geometry": {"coordinates":[-81.20531699999999,28.553105],"type":"Point"}
}