{
  "type": "Feature",
  "properties": {
    "addr:full":"24694 Nova Ln Port Charlotte FL 33980",
    "addr:housenumber":"24694",
    "addr:postcode":"33980",
    "addr:street":"Nova Ln",
    "iso:country":"US",
    "sg:address":"24694 Nova Ln",
    "sg:city":"Port Charlotte",
    "sg:classifiers":[
        {
            "category":"Building & Trades",
            "subcategory":"Construction",
            "type":"Services"
        }
    ],
    "sg:phone":"+1 941 764 0667",
    "sg:postcode":"33980",
    "sg:province":"FL",
    "sg:tags":[
        "roofing",
        "contractor"
    ],
    "wof:name":"L & L Roofing-Charlotte Cnty",
    "wof:placetype":"venue"
},
  "geometry": {"coordinates":[-82.038954,26.991715],"type":"Point"}
}