{
  "type": "Feature",
  "properties": {
    "addr:full":"2605 NW 175th St Miami Gardens FL 33056",
    "addr:housenumber":"2605",
    "addr:postcode":"33056",
    "addr:street":"Nw 175Th St",
    "iso:country":"US",
    "sg:address":"2605 NW 175th St",
    "sg:city":"Miami Gardens",
    "sg:classifiers":[
        {
            "category":"Food & Beverages",
            "subcategory":"Groceries & Convenience Stores",
            "type":"Retail Goods"
        }
    ],
    "sg:phone":"+1 305 620 2036",
    "sg:postcode":"33056",
    "sg:province":"FL",
    "wof:name":"Kwik Stop 600",
    "wof:placetype":"venue"
},
  "geometry": {"coordinates":[-80.244401,25.933834],"type":"Point"}
}