{
  "type": "Feature",
  "properties": {
    "addr:full":"1050 25th St N Saint Petersburg FL 33713",
    "addr:housenumber":"1050",
    "addr:postcode":"33713",
    "addr:street":"25Th St N",
    "iso:country":"US",
    "sg:address":"1050 25th St N",
    "sg:city":"Saint Petersburg",
    "sg:classifiers":[
        {
            "category":"Building & Trades",
            "subcategory":"Landscaping Services",
            "type":"Services"
        }
    ],
    "sg:phone":"+1 727 327 7455",
    "sg:postcode":"33713",
    "sg:province":"FL",
    "wof:name":"Florida Best Lawn Service Inc",
    "wof:placetype":"venue"
},
  "geometry": {"coordinates":[-82.66730200000001,27.783027],"type":"Point"}
}