{
  "type": "Feature",
  "properties": {
    "iso:country":"US",
    "sg:address":"1654 Floyd St",
    "sg:city":"Sarasota",
    "sg:classifiers":[
        {
            "category":"Manufacturing",
            "subcategory":"Printing",
            "type":"Manufacturing & Wholesale Goods"
        }
    ],
    "sg:phone":"+1 941 366 3635",
    "sg:postcode":"34239",
    "sg:province":"FL",
    "sg:tags":[
        "publishing"
    ],
    "wof:name":"Hack Publications",
    "wof:placetype":"venue"
},
  "geometry": {"coordinates":[-82.534762,27.320025],"type":"Point"}
}