{
  "type": "Feature",
  "properties": {
    "iso:country":"US",
    "sg:address":"1901 W 39th St",
    "sg:city":"Hialeah",
    "sg:classifiers":[
        {
            "category":"Sports & Exercise",
            "subcategory":"Gym",
            "type":"Entertainment"
        }
    ],
    "sg:phone":"+1 305 822 0227",
    "sg:postcode":"33012",
    "sg:province":"FL",
    "sg:website":"www.ballyfitness.com/",
    "wof:name":"Bally Total Fitness",
    "wof:placetype":"venue"
},
  "geometry": {"coordinates":[-80.320688,25.857963],"type":"Point"}
}