{
  "type": "Feature",
  "properties": {
    "addr:full":"20345 Old Cutler Rd Miami FL 33189",
    "addr:housenumber":"20345",
    "addr:postcode":"33189",
    "addr:street":"Old Cutler Rd",
    "iso:country":"US",
    "sg:address":"20345 Old Cutler Rd",
    "sg:city":"Miami",
    "sg:classifiers":[
        {
            "category":"Shopping",
            "subcategory":"Pharmacy",
            "type":"Retail Goods"
        }
    ],
    "sg:phone":"+1 305 232 9130",
    "sg:postcode":"33189",
    "sg:province":"FL",
    "wof:name":"Eckerd",
    "wof:placetype":"venue"
},
  "geometry": {"coordinates":[-80.339426,25.576862],"type":"Point"}
}