{
  "type": "Feature",
  "properties": {
    "iso:country":"US",
    "sg:address":"1120 Lee Blvd",
    "sg:city":"Lehigh Acres",
    "sg:classifiers":[
        {
            "category":"Health Services",
            "subcategory":"Doctor",
            "type":"Services"
        }
    ],
    "sg:phone":"+1 239 369 6295",
    "sg:postcode":"33936",
    "sg:province":"FL",
    "sg:tags":[
        "physician",
        "surgeon"
    ],
    "wof:name":"21st Century Oncology",
    "wof:placetype":"venue"
},
  "geometry": {"coordinates":[-81.645717,26.614884],"type":"Point"}
}