{
  "type": "Feature",
  "properties": {
    "iso:country":"US",
    "sg:address":"620 Lowell Ln",
    "sg:city":"Fort Lauderdale",
    "sg:classifiers":[
        {
            "category":"Health Services",
            "subcategory":"Clinic",
            "type":"Services"
        }
    ],
    "sg:phone":"+1 954 476 5090",
    "sg:postcode":"33325",
    "sg:province":"FL",
    "wof:name":"Florida Total Health LLC",
    "wof:placetype":"venue"
},
  "geometry": {"coordinates":[-80.33637899999999,26.112782],"type":"Point"}
}