{
  "type": "Feature",
  "properties": {
    "addr:full":"12535 66th St N Largo FL 33773",
    "addr:housenumber":"12535",
    "addr:postcode":"33773",
    "addr:street":"66Th St N",
    "iso:country":"US",
    "sg:address":"12535 66th St N",
    "sg:city":"Largo",
    "sg:classifiers":[
        {
            "category":"Shopping",
            "subcategory":"Clothing, Apparel, & Fashions",
            "type":"Retail Goods"
        }
    ],
    "sg:phone":"+1 727 536 4849",
    "sg:postcode":"33773",
    "sg:province":"FL",
    "sg:tags":[
        "lingerie"
    ],
    "wof:name":"Intimate Essentials",
    "wof:placetype":"venue"
},
  "geometry": {"coordinates":[-82.729044,27.885804],"type":"Point"}
}