{
  "type": "Feature",
  "properties": {
    "iso:country":"US",
    "sg:address":"915 NW 8th Street Rd",
    "sg:city":"Miami",
    "sg:classifiers":[
        {
            "category":"Government",
            "subcategory":"Court House",
            "type":"Public Place"
        }
    ],
    "sg:phone":"+1 305 672 5963",
    "sg:postcode":"33136",
    "sg:province":"FL",
    "sg:tags":[
        "justice"
    ],
    "wof:name":"Court Jefferson",
    "wof:placetype":"venue"
},
  "geometry": {"coordinates":[-80.207768,25.782549],"type":"Point"}
}