{
  "type": "Feature",
  "properties": {
    "iso:country":"US",
    "sg:address":"15404 N Co Rd 349",
    "sg:city":"Live Oak",
    "sg:classifiers":[
        {
            "category":"Building & Trades",
            "subcategory":"Construction",
            "type":"Services"
        }
    ],
    "sg:phone":"+1 386 364 5220",
    "sg:postcode":"32060",
    "sg:province":"FL",
    "sg:tags":[
        "builder",
        "patio",
        "deck"
    ],
    "wof:name":"Deck Masters",
    "wof:placetype":"venue"
},
  "geometry": {"coordinates":[-83.063705,30.173835],"type":"Point"}
}