{
  "type": "Feature",
  "properties": {
    "addr:full":"2302 James L Redman Pkwy Plant City FL 33563",
    "addr:housenumber":"2302",
    "addr:postcode":"33563",
    "addr:street":"James L Redman Pkwy",
    "iso:country":"US",
    "sg:address":"2302 James L Redman Pkwy",
    "sg:city":"Plant City",
    "sg:classifiers":[
        {
            "category":"Shopping",
            "subcategory":"Pharmacy",
            "type":"Retail Goods"
        }
    ],
    "sg:phone":"+1 813 754 0828",
    "sg:postcode":"33563",
    "sg:province":"FL",
    "sg:tags":[
        "drug",
        "store"
    ],
    "wof:name":"CVS",
    "wof:placetype":"venue"
},
  "geometry": {"coordinates":[-82.121493,27.990052],"type":"Point"}
}