{
  "type": "Feature",
  "properties": {
    "iso:country":"US",
    "sg:address":"4754 Young Rd",
    "sg:city":"Crestview",
    "sg:classifiers":[
        {
            "category":"Professional",
            "subcategory":"Accounting & Tax Preparation",
            "type":"Services"
        }
    ],
    "sg:phone":"+1 850 683 0308",
    "sg:postcode":"32539",
    "sg:province":"FL",
    "wof:name":"Melanie Guthrie CPA",
    "wof:placetype":"venue"
},
  "geometry": {"coordinates":[-86.540785,30.725206],"type":"Point"}
}