{
  "type": "Feature",
  "properties": {
    "iso:country":"US",
    "sg:address":"310 Banning Beach Rd",
    "sg:city":"Tavares",
    "sg:classifiers":[
        {
            "category":"Building & Trades",
            "subcategory":"Construction",
            "type":"Services"
        }
    ],
    "sg:phone":"+1 352 343 1936",
    "sg:postcode":"32778",
    "sg:province":"FL",
    "sg:tags":[
        "carpentry",
        "contractor"
    ],
    "wof:name":"Chris Lamoureux",
    "wof:placetype":"venue"
},
  "geometry": {"coordinates":[-81.733824,28.818304],"type":"Point"}
}