{
  "type": "Feature",
  "properties": {
    "addr:full":"100 W Cypress Creek Rd Fort Lauderdale FL 33309",
    "addr:housenumber":"100",
    "addr:postcode":"33309",
    "addr:street":"W Cypress Creek Rd",
    "iso:country":"US",
    "sg:address":"100 W Cypress Creek Rd",
    "sg:city":"Fort Lauderdale",
    "sg:classifiers":[
        {
            "category":"Professional",
            "subcategory":"Employment Agencies",
            "type":"Services"
        }
    ],
    "sg:phone":"+1 954 771 8777",
    "sg:postcode":"33309",
    "sg:province":"FL",
    "sg:tags":[
        "help",
        "supply"
    ],
    "wof:name":"Adecco Staffing",
    "wof:placetype":"venue"
},
  "geometry": {"coordinates":[-80.14832699999999,26.203467],"type":"Point"}
}