{
  "type": "Feature",
  "properties": {
    "addr:full":"396 S Mill View Way Ponte Vedra Beach FL 32082",
    "addr:housenumber":"396",
    "addr:postcode":"32082",
    "addr:street":"S Mill View Way",
    "iso:country":"US",
    "sg:address":"396 S Mill View Way",
    "sg:city":"Ponte Vedra Beach",
    "sg:classifiers":[
        {
            "category":"Health Services",
            "subcategory":"Doctor",
            "type":"Services"
        }
    ],
    "sg:phone":"+1 904 285 8152",
    "sg:postcode":"32082",
    "sg:province":"FL",
    "sg:tags":[
        "medical"
    ],
    "wof:name":"Glen F Martin M D P A",
    "wof:placetype":"venue"
},
  "geometry": {"coordinates":[-81.38269099999999,30.139962],"type":"Point"}
}