{
  "type": "Feature",
  "properties": {
    "addr:full":"12041 SE 57th Ave Belleview FL 34420",
    "addr:postcode":"12041;34420",
    "addr:street":"Se 57Th Ave",
    "iso:country":"US",
    "sg:address":"12041 SE 57th Ave",
    "sg:city":"Belleview",
    "sg:classifiers":[
        {
            "category":"Personal",
            "subcategory":"Beauty Salon",
            "type":"Services"
        }
    ],
    "sg:phone":"+1 352 347 1058",
    "sg:postcode":"34420",
    "sg:province":"FL",
    "wof:name":"No See Um Eliminators Inc",
    "wof:placetype":"venue"
},
  "geometry": {"coordinates":[-82.055573,29.04802],"type":"Point"}
}