{
  "type": "Feature",
  "properties": {
    "addr:full":"18836 NW 78th Pl Hialeah FL 33015",
    "addr:housenumber":"18836",
    "addr:postcode":"33015",
    "addr:street":"Nw 78Th Pl",
    "iso:country":"US",
    "sg:address":"18836 NW 78th Pl",
    "sg:city":"Hialeah",
    "sg:classifiers":[
        {
            "category":"Professional",
            "subcategory":"Management & Consulting",
            "type":"Services"
        }
    ],
    "sg:phone":"+1 305 829 9030",
    "sg:postcode":"33015",
    "sg:province":"FL",
    "sg:tags":[
        "business"
    ],
    "wof:name":"Marsoft Consulting Inc",
    "wof:placetype":"venue"
},
  "geometry": {"coordinates":[-80.329199,25.945747],"type":"Point"}
}