{
  "type": "Feature",
  "properties": {
    "addr:full":"907 S 8th St Leesburg FL 34748",
    "addr:housenumber":"907",
    "addr:postcode":"34748",
    "addr:street":"S 8Th St",
    "iso:country":"US",
    "sg:address":"907 S 8th St",
    "sg:city":"Leesburg",
    "sg:classifiers":[
        {
            "category":"Education",
            "subcategory":"Junior College",
            "type":"Public Place"
        }
    ],
    "sg:phone":"+1 352 978 3515",
    "sg:postcode":"34748",
    "sg:province":"FL",
    "sg:tags":[
        "doll"
    ],
    "wof:name":"Little Sister's Dolls",
    "wof:placetype":"venue"
},
  "geometry": {"coordinates":[-81.87777800000001,28.801703],"type":"Point"}
}