{
  "type": "Feature",
  "properties": {
    "addr:full":"4423 Lakewood Rd Lake Worth FL 33461",
    "addr:housenumber":"4423",
    "addr:postcode":"33461",
    "addr:street":"Lakewood Rd",
    "iso:country":"US",
    "sg:address":"4423 Lakewood Rd",
    "sg:city":"Lake Worth",
    "sg:classifiers":[
        {
            "category":"Restaurant",
            "type":"Food & Drink"
        }
    ],
    "sg:phone":"+1 561 965 2347",
    "sg:postcode":"33461",
    "sg:province":"FL",
    "sg:tags":[
        "eating"
    ],
    "wof:name":"Gilbert Ron Rib King Bbq",
    "wof:placetype":"venue"
},
  "geometry": {"coordinates":[-80.112876,26.622166],"type":"Point"}
}