{
  "type": "Feature",
  "properties": {
    "iso:country":"US",
    "sg:address":"5228 4th Rd N",
    "sg:city":"West Palm Beach",
    "sg:classifiers":[
        {
            "category":"Building & Trades",
            "subcategory":"Construction",
            "type":"Services"
        }
    ],
    "sg:phone":"+1 561 471 1787",
    "sg:postcode":"33415",
    "sg:province":"FL",
    "sg:tags":[
        "windows"
    ],
    "wof:name":"C Gerace Window Repair",
    "wof:placetype":"venue"
},
  "geometry": {"coordinates":[-80.12037100000001,26.684241],"type":"Point"}
}