{
  "type": "Feature",
  "properties": {
    "iso:country":"US",
    "sg:address":"2220 Hibiscus Dr Ste 5",
    "sg:city":"Edgewater",
    "sg:classifiers":[
        {
            "category":"Autos & Motor Vehicles",
            "subcategory":"Motorcycle Sales",
            "type":"Retail Goods"
        },
        {
            "category":"Retail",
            "subcategory":"Auto Repair",
            "type":"Services"
        }
    ],
    "sg:phone":"+1 386 428 5450",
    "sg:postcode":"32141",
    "sg:province":"FL",
    "sg:tags":[
        "scooters-repairing",
        "scooters-parts",
        "supply"
    ],
    "wof:name":"Hard Parts",
    "wof:placetype":"venue"
},
  "geometry": {"coordinates":[-80.899173,28.962174],"type":"Point"}
}