{
  "type": "Feature",
  "properties": {
    "iso:country":"US",
    "sg:address":"6353 Argyle Forest Blvd",
    "sg:city":"Jacksonville",
    "sg:classifiers":[
        {
            "category":"Building & Trades",
            "subcategory":"Construction",
            "type":"Services"
        }
    ],
    "sg:phone":"+1 904 777 5775",
    "sg:postcode":"32244",
    "sg:province":"FL",
    "sg:tags":[
        "contractor"
    ],
    "wof:name":"J KS Builders Inc",
    "wof:placetype":"venue"
},
  "geometry": {"coordinates":[-81.7394,30.192265],"type":"Point"}
}