{
  "type": "Feature",
  "properties": {
    "iso:country":"US",
    "sg:address":"20909 NE 132nd Ave",
    "sg:city":"Waldo",
    "sg:classifiers":[
        {
            "category":"Wholesale",
            "subcategory":"Medical Equipment & Supplies",
            "type":"Manufacturing & Wholesale Goods"
        }
    ],
    "sg:phone":"+1 352 468 1006",
    "sg:postcode":"32694",
    "sg:province":"FL",
    "sg:tags":[
        "electronics"
    ],
    "wof:name":"Neurotronics Inc",
    "wof:placetype":"venue"
},
  "geometry": {"coordinates":[-82.11159600000001,29.77616],"type":"Point"}
}