{
  "type": "Feature",
  "properties": {
    "iso:country":"US",
    "sg:address":"4357 SW 48th Ave",
    "sg:city":"Palm City",
    "sg:classifiers":[
        {
            "category":"Building & Trades",
            "subcategory":"Construction",
            "type":"Services"
        }
    ],
    "sg:phone":"+1 772 288 3595",
    "sg:postcode":"34990",
    "sg:province":"FL",
    "sg:tags":[
        "house"
    ],
    "wof:name":"Cabinets By Dave",
    "wof:placetype":"venue"
},
  "geometry": {"coordinates":[-80.3189,27.151643],"type":"Point"}
}