{
  "type": "Feature",
  "properties": {
    "iso:country":"US",
    "sg:address":"3429 Deltona Blvd",
    "sg:city":"Spring Hill",
    "sg:classifiers":[
        {
            "category":"Restaurant",
            "type":"Food & Drink"
        }
    ],
    "sg:phone":"+1 352 688 0444",
    "sg:postcode":"34606",
    "sg:province":"FL",
    "wof:name":"Spring Hill Grill",
    "wof:placetype":"venue"
},
  "geometry": {"coordinates":[-82.575153,28.484814],"type":"Point"}
}