{
  "type": "Feature",
  "properties": {
    "iso:country":"US",
    "sg:address":"16503 NE 5th Ave",
    "sg:city":"Miami",
    "sg:classifiers":[
        {
            "category":"Shopping",
            "subcategory":"Florist",
            "type":"Retail Goods"
        }
    ],
    "sg:phone":"+1 305 948 3454",
    "sg:postcode":"33162",
    "sg:province":"FL",
    "wof:name":"Davis Floral Inc",
    "wof:placetype":"venue"
},
  "geometry": {"coordinates":[-80.190224,25.927034],"type":"Point"}
}