{
  "type": "Feature",
  "properties": {
    "iso:country":"US",
    "sg:address":"1510 Sunset Village Blvd",
    "sg:city":"Clermont",
    "sg:classifiers":[
        {
            "category":"Farming",
            "subcategory":"Fish & Marine Products",
            "type":"Manufacturing & Wholesale Goods"
        },
        {
            "category":"Retail",
            "subcategory":"Repair Shop",
            "type":"Services"
        }
    ],
    "sg:phone":"+1 321 689 0282",
    "sg:postcode":"34711",
    "sg:province":"FL",
    "sg:tags":[
        "picture",
        "frame",
        "restoration",
        "framing"
    ],
    "wof:name":"David Schlobachs Framing",
    "wof:placetype":"venue"
},
  "geometry": {"coordinates":[-81.72995899999999,28.558714],"type":"Point"}
}