{
  "type": "Feature",
  "properties": {
    "addr:full":"2221 NE 164th St North Miami Beach FL 33160",
    "addr:housenumber":"2221",
    "addr:postcode":"33160",
    "addr:street":"Ne 164Th St",
    "iso:country":"US",
    "sg:address":"2221 NE 164th St",
    "sg:city":"North Miami Beach",
    "sg:classifiers":[
        {
            "category":"Professional",
            "subcategory":"Lawyer & Legal Services",
            "type":"Services"
        }
    ],
    "sg:phone":"+1 305 945 3222",
    "sg:postcode":"33160",
    "sg:province":"FL",
    "sg:tags":[
        "notary"
    ],
    "sg:website":"www.mailbags.org",
    "wof:name":"Mail Bags",
    "wof:placetype":"venue"
},
  "geometry": {"coordinates":[-80.15570099999999,25.927299],"type":"Point"}
}