{
  "type": "Feature",
  "properties": {
    "addr:full":"2701 Leonard Weaver Blvd Melbourne FL 32901",
    "addr:housenumber":"2701",
    "addr:postcode":"32901",
    "addr:street":"Leonard Weaver Blvd",
    "iso:country":"US",
    "sg:address":"2701 Leonard Weaver Blvd",
    "sg:city":"Melbourne",
    "sg:classifiers":[
        {
            "category":"Organizations",
            "subcategory":"Religious Organization",
            "type":"Services"
        }
    ],
    "sg:phone":"+1 321 768 9782",
    "sg:postcode":"32901",
    "sg:province":"FL",
    "sg:tags":[
        "church"
    ],
    "wof:name":"Greater Faith Temple Chrch God",
    "wof:placetype":"venue"
},
  "geometry": {"coordinates":[-80.612915,28.067922],"type":"Point"}
}