{
  "type": "Feature",
  "properties": {
    "addr:full":"8346 SW 37th St Miami FL 33155",
    "addr:housenumber":"8346",
    "addr:postcode":"33155",
    "addr:street":"Sw 37Th St",
    "iso:country":"US",
    "sg:address":"8346 SW 37th St",
    "sg:city":"Miami",
    "sg:classifiers":[
        {
            "category":"Real Estate",
            "subcategory":"Real Estate Agent",
            "type":"Services"
        }
    ],
    "sg:phone":"+1 305 222 2201",
    "sg:postcode":"33155",
    "sg:province":"FL",
    "wof:name":"Appraisals Express Inc",
    "wof:placetype":"venue"
},
  "geometry": {"coordinates":[-80.33077900000001,25.735866],"type":"Point"}
}