{
  "type": "Feature",
  "properties": {
    "iso:country":"US",
    "sg:address":"5576 International Dr",
    "sg:city":"Orlando",
    "sg:classifiers":[
        {
            "category":"Food & Beverages",
            "subcategory":"Bakery",
            "type":"Retail Goods"
        }
    ],
    "sg:phone":"+1 407 345 5215",
    "sg:postcode":"32819",
    "sg:province":"FL",
    "sg:tags":[
        "bagel"
    ],
    "wof:name":"Wholesale Bagel Shop",
    "wof:placetype":"venue"
},
  "geometry": {"coordinates":[-81.455799,28.462262],"type":"Point"}
}