{
  "type": "Feature",
  "properties": {
    "addr:full":"4385 Collins Ave Miami Beach FL 33140",
    "addr:housenumber":"4385",
    "addr:postcode":"33140",
    "addr:street":"Collins Ave",
    "iso:country":"US",
    "sg:address":"4385 Collins Ave",
    "sg:city":"Miami Beach",
    "sg:classifiers":[
        {
            "category":"Travel",
            "subcategory":"Hotels & Motels",
            "type":"Entertainment"
        }
    ],
    "sg:phone":"+1 305 531 3232",
    "sg:postcode":"33140",
    "sg:province":"FL",
    "sg:website":"www.miamibeachhotel.com",
    "wof:name":"Courtyard-Mia Bch Oceanfrnt/43",
    "wof:placetype":"venue"
},
  "geometry": {"coordinates":[-80.122641,25.814731],"type":"Point"}
}