{
  "type": "Feature",
  "properties": {
    "iso:country":"US",
    "sg:address":"1240 E Lime St",
    "sg:city":"Lakeland",
    "sg:classifiers":[
        {
            "category":"Professional",
            "subcategory":"Lawyer & Legal Services",
            "type":"Services"
        }
    ],
    "sg:phone":"+1 863 616 1515",
    "sg:postcode":"33801",
    "sg:province":"FL",
    "sg:tags":[
        "attorney"
    ],
    "wof:name":"Pincket & Pincket",
    "wof:placetype":"venue"
},
  "geometry": {"coordinates":[-81.939612,28.040632],"type":"Point"}
}