{
  "type": "Feature",
  "properties": {
    "addr:full":"729 SW Federal Hwy # 100 Stuart FL 34994",
    "addr:housenumber":"729",
    "addr:postcode":"34994",
    "addr:street":"Sw Federal Hwy # 100",
    "iso:country":"US",
    "sg:address":"729 SW Federal Hwy # 100",
    "sg:city":"Stuart",
    "sg:classifiers":[
        {
            "category":"Recreation",
            "subcategory":"Boat Charter",
            "type":"Entertainment"
        },
        {
            "category":"Marine",
            "type":"Transportation"
        }
    ],
    "sg:phone":"+1 772 201 1448",
    "sg:postcode":"34994",
    "sg:province":"FL",
    "sg:tags":[
        "watercraft-personal-renting",
        "boat-rental"
    ],
    "wof:name":"Share-A-Boat",
    "wof:placetype":"venue"
},
  "geometry": {"coordinates":[-80.256576,27.193347],"type":"Point"}
}