{
  "type": "Feature",
  "properties": {
    "iso:country":"US",
    "sg:address":"300 S Hyde Park Ave",
    "sg:city":"Tampa",
    "sg:classifiers":[
        {
            "category":"Professional",
            "subcategory":"Lawyer & Legal Services",
            "type":"Services"
        }
    ],
    "sg:phone":"+1 813 251 6838",
    "sg:postcode":"33606",
    "sg:province":"FL",
    "sg:tags":[
        "architectural"
    ],
    "wof:name":"Gresham Smith and Partners",
    "wof:placetype":"venue"
},
  "geometry": {"coordinates":[-82.463948,27.940535],"type":"Point"}
}