{
  "type": "Feature",
  "properties": {
    "addr:full":"5401 34th St W Bradenton FL 34210",
    "addr:housenumber":"5401",
    "addr:postcode":"34210",
    "addr:street":"34Th St W",
    "iso:country":"US",
    "sg:address":"5401 34th St W",
    "sg:city":"Bradenton",
    "sg:classifiers":[
        {
            "category":"Education",
            "subcategory":"School",
            "type":"Public Place"
        }
    ],
    "sg:phone":"+1 941 751 7004",
    "sg:postcode":"34210",
    "sg:province":"FL",
    "wof:name":"Bayshore High School",
    "wof:placetype":"venue"
},
  "geometry": {"coordinates":[-82.595716,27.444926],"type":"Point"}
}