{
  "type": "Feature",
  "properties": {
    "iso:country":"US",
    "sg:address":"110 E Van Fleet Dr",
    "sg:city":"Bartow",
    "sg:classifiers":[
        {
            "category":"Cinema",
            "subcategory":"Movie Rental",
            "type":"Entertainment"
        }
    ],
    "sg:phone":"+1 863 533 1293",
    "sg:postcode":"33830",
    "sg:province":"FL",
    "sg:tags":[
        "video",
        "tape"
    ],
    "wof:name":"Blockbuster",
    "wof:placetype":"venue"
},
  "geometry": {"coordinates":[-81.84052699999999,27.90413],"type":"Point"}
}