{
  "type": "Feature",
  "properties": {
    "addr:full":"1104 Central Ave St Petersburg FL 33705",
    "addr:housenumber":"1104",
    "addr:postcode":"33705",
    "addr:street":"Central Ave",
    "iso:country":"US",
    "sg:address":"1104 Central Ave",
    "sg:city":"St Petersburg",
    "sg:classifiers":[
        {
            "category":"Professional",
            "subcategory":"Business Services",
            "type":"Services"
        }
    ],
    "sg:phone":"+1 727 898 6061",
    "sg:postcode":"33705",
    "sg:province":"FL",
    "sg:tags":[
        "interior",
        "consultant",
        "design",
        "decorator"
    ],
    "wof:name":"Interior Motives",
    "wof:placetype":"venue"
},
  "geometry": {"coordinates":[-82.65170000000001,27.771045],"type":"Point"}
}