{
  "type": "Feature",
  "properties": {
    "iso:country":"US",
    "sg:address":"7003 NW 39th Ave",
    "sg:city":"Gainesville",
    "sg:classifiers":[
        {
            "category":"Organizations",
            "subcategory":"Religious Organization",
            "type":"Services"
        }
    ],
    "sg:phone":"+1 352 371 9646",
    "sg:postcode":"32606",
    "sg:province":"FL",
    "sg:tags":[
        "church"
    ],
    "wof:name":"Gainesville Church of God Inc",
    "wof:placetype":"venue"
},
  "geometry": {"coordinates":[-82.41738100000001,29.688693],"type":"Point"}
}