{
  "type": "Feature",
  "properties": {
    "addr:full":"6025 Mayo St Hollywood FL 33023",
    "addr:housenumber":"6025",
    "addr:postcode":"33023",
    "addr:street":"Mayo St",
    "iso:country":"US",
    "sg:address":"6025 Mayo St",
    "sg:city":"Hollywood",
    "sg:classifiers":[
        {
            "category":"Social Services",
            "subcategory":"Child Care",
            "type":"Services"
        }
    ],
    "sg:phone":"+1 954 921 2798",
    "sg:postcode":"33023",
    "sg:province":"FL",
    "sg:tags":[
        "day"
    ],
    "wof:name":"Day Care",
    "wof:placetype":"venue"
},
  "geometry": {"coordinates":[-80.208673,25.997617],"type":"Point"}
}