{
  "type": "Feature",
  "properties": {
    "iso:country":"US",
    "sg:address":"11850 9th St N",
    "sg:city":"St Petersburg",
    "sg:classifiers":[
        {
            "category":"Real Estate",
            "subcategory":"Real Estate Operator",
            "type":"Services"
        }
    ],
    "sg:phone":"+1 727 568 9200",
    "sg:postcode":"33716",
    "sg:province":"FL",
    "sg:tags":[
        "building",
        "apartment"
    ],
    "wof:name":"Bay Isle Key Apartments",
    "wof:placetype":"venue"
},
  "geometry": {"coordinates":[-82.647024,27.879351],"type":"Point"}
}