{
  "type": "Feature",
  "properties": {
    "iso:country":"US",
    "sg:address":"2109 Opa Locka Blvd",
    "sg:city":"Opa Locka",
    "sg:classifiers":[
        {
            "category":"Professional",
            "type":"Services"
        }
    ],
    "sg:phone":"+1 305 685 8818",
    "sg:postcode":"33054",
    "sg:province":"FL",
    "sg:tags":[
        "caterer"
    ],
    "wof:name":"Bobby's Meal",
    "wof:placetype":"venue"
},
  "geometry": {"coordinates":[-80.234497,25.8981],"type":"Point"}
}