{
  "type": "Feature",
  "properties": {
    "iso:country":"US",
    "sg:address":"1806 Turquoise Ct",
    "sg:city":"Kissimmee",
    "sg:classifiers":[
        {
            "category":"Professional",
            "subcategory":"Business Services",
            "type":"Services"
        }
    ],
    "sg:phone":"+1 407 729 9861",
    "sg:postcode":"34743",
    "sg:province":"FL",
    "sg:tags":[
        "inspection"
    ],
    "wof:name":"Central Florida Home Inspector",
    "wof:placetype":"venue"
},
  "geometry": {"coordinates":[-81.36651000000001,28.311699],"type":"Point"}
}