{
  "type": "Feature",
  "properties": {
    "iso:country":"US",
    "sg:address":"1851 N Powerline Rd",
    "sg:city":"Pompano Beach",
    "sg:classifiers":[
        {
            "category":"Shopping",
            "type":"Retail Goods"
        }
    ],
    "sg:phone":"+1 954 971 3176",
    "sg:postcode":"33069",
    "sg:province":"FL",
    "sg:tags":[
        "safety",
        "supply"
    ],
    "sg:website":"www.ritzsafety.com",
    "wof:name":"Ritz Safety Equipment Inc",
    "wof:placetype":"venue"
},
  "geometry": {"coordinates":[-80.15175600000001,26.255895],"type":"Point"}
}