{
  "type": "Feature",
  "properties": {
    "iso:country":"US",
    "sg:address":"7269 Oak Moss Dr",
    "sg:city":"Sarasota",
    "sg:classifiers":[
        {
            "category":"Health Services",
            "subcategory":"Health Practitioner",
            "type":"Services"
        }
    ],
    "sg:phone":"+1 941 342 8784",
    "sg:postcode":"34241",
    "sg:province":"FL",
    "sg:tags":[
        "pathologist",
        "speech"
    ],
    "wof:name":"Marcia M Rutberg",
    "wof:placetype":"venue"
},
  "geometry": {"coordinates":[-82.424147,27.287014],"type":"Point"}
}