{
  "type": "Feature",
  "properties": {
    "addr:full":"3330 NE 6th Ter Pompano Beach FL 33064",
    "addr:housenumber":"3330",
    "addr:postcode":"33064",
    "addr:street":"Ne 6Th Ter",
    "iso:country":"US",
    "sg:address":"3330 NE 6th Ter",
    "sg:city":"Pompano Beach",
    "sg:classifiers":[
        {
            "category":"Wholesale",
            "subcategory":"Non-durable Goods",
            "type":"Manufacturing & Wholesale Goods"
        }
    ],
    "sg:phone":"+1 954 941 4665",
    "sg:postcode":"33064",
    "sg:province":"FL",
    "sg:tags":[
        "bait",
        "fishing"
    ],
    "wof:name":"Bionic Bait",
    "wof:placetype":"venue"
},
  "geometry": {"coordinates":[-80.11369500000001,26.271828],"type":"Point"}
}