{
  "type": "Feature",
  "properties": {
    "iso:country":"US",
    "sg:address":"7008 Filbert Ln",
    "sg:city":"Tampa",
    "sg:classifiers":[
        {
            "category":"Building & Trades",
            "subcategory":"Plumbing",
            "type":"Services"
        }
    ],
    "sg:phone":"+1 813 985 2462",
    "sg:postcode":"33637",
    "sg:province":"FL",
    "sg:tags":[
        "contractor"
    ],
    "wof:name":"Franco Plumbing",
    "wof:placetype":"venue"
},
  "geometry": {"coordinates":[-82.37405200000001,28.029956],"type":"Point"}
}