{
  "type": "Feature",
  "properties": {
    "iso:country":"US",
    "sg:address":"5353 S Tamiami Trl",
    "sg:city":"Sarasota",
    "sg:classifiers":[
        {
            "category":"Restaurant",
            "type":"Food & Drink"
        },
        {
            "category":"Retail",
            "subcategory":"Event Space",
            "type":"Services"
        }
    ],
    "sg:phone":"+1 941 925 4444",
    "sg:postcode":"34231",
    "sg:province":"FL",
    "sg:tags":[
        "style",
        "family",
        "facility",
        "seafood",
        "hall",
        "american",
        "reception",
        "banquet"
    ],
    "sg:website":"http://www.creekseafood.com",
    "wof:name":"Phillippi Creek Village Oyster",
    "wof:placetype":"venue"
},
  "geometry": {"coordinates":[-82.530513,27.274653],"type":"Point"}
}