{
  "type": "Feature",
  "properties": {
    "addr:full":"106 Racetrack Rd NE Fort Walton Beach FL 32547",
    "addr:housenumber":"106",
    "addr:postcode":"32547",
    "addr:street":"Racetrack Rd Ne",
    "iso:country":"US",
    "sg:address":"106 Racetrack Rd NE",
    "sg:city":"Fort Walton Beach",
    "sg:classifiers":[
        {
            "category":"Recreation",
            "type":"Entertainment"
        }
    ],
    "sg:phone":"+1 850 864 4141",
    "sg:postcode":"32547",
    "sg:province":"FL",
    "sg:tags":[
        "bingo",
        "hall"
    ],
    "wof:name":"Fort Walton Bingo",
    "wof:placetype":"venue"
},
  "geometry": {"coordinates":[-86.60791399999999,30.44643],"type":"Point"}
}