{
  "type": "Feature",
  "properties": {
    "iso:country":"US",
    "sg:address":"4550 SW 71st Ave Ste B",
    "sg:city":"Miami",
    "sg:classifiers":[
        {
            "category":"Retail",
            "subcategory":"Repair Shop",
            "type":"Services"
        }
    ],
    "sg:phone":"+1 305 663 0470",
    "sg:postcode":"33155",
    "sg:province":"FL",
    "sg:tags":[
        "refinish",
        "upholsterer",
        "furniture"
    ],
    "wof:name":"Interiors By Jessi",
    "wof:placetype":"venue"
},
  "geometry": {"coordinates":[-80.308763,25.727777],"type":"Point"}
}