{
  "type": "Feature",
  "properties": {
    "addr:full":"5244 NW 7th Ave Miami FL 33127",
    "addr:housenumber":"5244",
    "addr:postcode":"33127",
    "addr:street":"Nw 7Th Ave",
    "iso:country":"US",
    "sg:address":"5244 NW 7th Ave",
    "sg:city":"Miami",
    "sg:classifiers":[
        {
            "category":"Food & Beverages",
            "subcategory":"Groceries & Convenience Stores",
            "type":"Retail Goods"
        }
    ],
    "sg:phone":"+1 305 758 0495",
    "sg:postcode":"33127",
    "sg:province":"FL",
    "wof:name":"Mommie's Mimi Market",
    "wof:placetype":"venue"
},
  "geometry": {"coordinates":[-80.208,25.823799],"type":"Point"}
}