{
  "type": "Feature",
  "properties": {
    "addr:full":"22265 135th Ct O Brien FL 32071",
    "addr:housenumber":"22265",
    "addr:postcode":"32071",
    "addr:street":"135Th Ct O Brien",
    "iso:country":"US",
    "sg:address":"22265 135th Ct",
    "sg:city":"O Brien",
    "sg:classifiers":[
        {
            "category":"Retail",
            "subcategory":"Repair Shop",
            "type":"Services"
        }
    ],
    "sg:phone":"+1 386 935 3494",
    "sg:postcode":"32071",
    "sg:province":"FL",
    "sg:tags":[
        "equipment",
        "hydraulic"
    ],
    "wof:name":"Certified Hydraulics Inc",
    "wof:placetype":"venue"
},
  "geometry": {"coordinates":[-83.028952,30.049488],"type":"Point"}
}