{
  "type": "Feature",
  "properties": {
    "addr:full":"1456 Whitewood Dr Deltona FL 32725",
    "addr:housenumber":"1456",
    "addr:postcode":"32725",
    "addr:street":"Whitewood Dr",
    "iso:country":"US",
    "sg:address":"1456 Whitewood Dr",
    "sg:city":"Deltona",
    "sg:classifiers":[
        {
            "category":"Building & Trades",
            "subcategory":"Construction",
            "type":"Services"
        }
    ],
    "sg:phone":"+1 386 860 0038",
    "sg:postcode":"32725",
    "sg:province":"FL",
    "sg:tags":[
        "handyman"
    ],
    "wof:name":"Nauta Handyman Svc",
    "wof:placetype":"venue"
},
  "geometry": {"coordinates":[-81.264359,28.903885],"type":"Point"}
}