{
  "type": "Feature",
  "properties": {
    "addr:full":"3870 Shipping Ave Miami FL 33146",
    "addr:postcode":"3870;33146",
    "addr:street":"Shipping Ave",
    "iso:country":"US",
    "sg:address":"3870 Shipping Ave",
    "sg:city":"Miami",
    "sg:classifiers":[
        {
            "category":"Professional",
            "type":"Services"
        }
    ],
    "sg:phone":"+1 305 448 1776",
    "sg:postcode":"33146",
    "sg:province":"FL",
    "wof:name":"Transamerica Oil Corp",
    "wof:placetype":"venue"
},
  "geometry": {"coordinates":[-80.25757900000001,25.733033],"type":"Point"}
}