{
  "type": "Feature",
  "properties": {
    "iso:country":"US",
    "sg:address":"320 N Love St",
    "sg:city":"Quincy",
    "sg:classifiers":[
        {
            "category":"Building & Trades",
            "subcategory":"Construction",
            "type":"Services"
        }
    ],
    "sg:phone":"+1 850 627 2825",
    "sg:postcode":"32351",
    "sg:province":"FL",
    "sg:tags":[
        "house"
    ],
    "wof:name":"Munroe Builders Inc",
    "wof:placetype":"venue"
},
  "geometry": {"coordinates":[-84.57281999999999,30.591801],"type":"Point"}
}