{
  "type": "Feature",
  "properties": {
    "iso:country":"US",
    "sg:address":"2854 Stirling Rd",
    "sg:city":"Hollywood",
    "sg:classifiers":[
        {
            "category":"Wholesale",
            "subcategory":"Non-durable Goods",
            "type":"Manufacturing & Wholesale Goods"
        }
    ],
    "sg:phone":"+1 954 925 0667",
    "sg:postcode":"33020",
    "sg:province":"FL",
    "sg:tags":[
        "dry",
        "goods-wholesale"
    ],
    "wof:name":"Manda Supply",
    "wof:placetype":"venue"
},
  "geometry": {"coordinates":[-80.1657,26.047889],"type":"Point"}
}