{
  "type": "Feature",
  "properties": {
    "addr:full":"4264 Barlow Rd Crestview FL 32536",
    "addr:housenumber":"4264",
    "addr:postcode":"32536",
    "addr:street":"Barlow Rd",
    "iso:country":"US",
    "sg:address":"4264 Barlow Rd",
    "sg:city":"Crestview",
    "sg:classifiers":[
        {
            "category":"Building & Trades",
            "subcategory":"Construction",
            "type":"Services"
        }
    ],
    "sg:phone":"+1 850 864 3658",
    "sg:postcode":"32536",
    "sg:province":"FL",
    "sg:tags":[
        "water",
        "well",
        "drilling"
    ],
    "wof:name":"Greg's Well Drilling & Irrgtn",
    "wof:placetype":"venue"
},
  "geometry": {"coordinates":[-86.634759,30.685043],"type":"Point"}
}