{
  "type": "Feature",
  "properties": {
    "addr:full":"210 23rd St Miami Beach FL 33139",
    "addr:housenumber":"210",
    "addr:postcode":"33139",
    "addr:street":"23Rd St",
    "iso:country":"US",
    "sg:address":"210 23rd St",
    "sg:city":"Miami Beach",
    "sg:classifiers":[
        {
            "category":"Restaurant",
            "type":"Food & Drink"
        }
    ],
    "sg:phone":"+1 305 397 8760",
    "sg:postcode":"33139",
    "sg:province":"FL",
    "sg:tags":[
        "new",
        "american"
    ],
    "sg:website":"www.edensouthbeach.com/",
    "wof:name":"Eden",
    "wof:placetype":"venue"
},
  "geometry": {"coordinates":[-80.128404,25.798206],"type":"Point"}
}