{
  "type": "Feature",
  "properties": {
    "addr:full":"4675 Ponce de Leon Blvd Coral Gables FL 33146",
    "addr:housenumber":"4675",
    "addr:postcode":"33146",
    "addr:street":"Ponce De Leon Blvd",
    "iso:country":"US",
    "sg:address":"4675 Ponce de Leon Blvd",
    "sg:city":"Coral Gables",
    "sg:classifiers":[
        {
            "category":"Real Estate",
            "subcategory":"Developer",
            "type":"Services"
        },
        {
            "category":"Real Estate",
            "subcategory":"Real Estate Operator",
            "type":"Services"
        }
    ],
    "sg:phone":"+1 305 668 6008",
    "sg:postcode":"33146",
    "sg:province":"FL",
    "sg:tags":[
        "building",
        "nonresidential"
    ],
    "sg:website":"www.spectorandsons.com",
    "wof:name":"Spector & Sons",
    "wof:placetype":"venue"
},
  "geometry": {"coordinates":[-80.262871,25.726929],"type":"Point"}
}