{
  "type": "Feature",
  "properties": {
    "addr:full":"590 Captain Hendry Dr Labelle FL 33935",
    "addr:housenumber":"590",
    "addr:postcode":"33935",
    "addr:street":"Captain Hendry Dr",
    "iso:country":"US",
    "sg:address":"590 Captain Hendry Dr",
    "sg:city":"Labelle",
    "sg:classifiers":[
        {
            "category":"Recreation",
            "type":"Entertainment"
        }
    ],
    "sg:phone":"+1 863 674 0797",
    "sg:postcode":"33935",
    "sg:province":"FL",
    "sg:tags":[
        "entertainers-family",
        "business"
    ],
    "wof:name":"Old Oaks Entertainment",
    "wof:placetype":"venue"
},
  "geometry": {"coordinates":[-81.455641,26.75405],"type":"Point"}
}