{
  "type": "Feature",
  "properties": {
    "iso:country":"US",
    "sg:address":"7215 159th Ct N",
    "sg:city":"Palm Beach Gardens",
    "sg:classifiers":[
        {
            "category":"Building & Trades",
            "subcategory":"Construction",
            "type":"Services"
        }
    ],
    "sg:phone":"+1 561 575 3877",
    "sg:postcode":"33418",
    "sg:province":"FL",
    "sg:tags":[
        "tile",
        "installation",
        "marble"
    ],
    "wof:name":"Deluca Tile Inc",
    "wof:placetype":"venue"
},
  "geometry": {"coordinates":[-80.148191,26.910406],"type":"Point"}
}