{
  "type": "Feature",
  "properties": {
    "iso:country":"US",
    "sg:address":"3235 Fairfield Ave S",
    "sg:city":"St Petersburg",
    "sg:classifiers":[
        {
            "category":"Wholesale",
            "subcategory":"Hardware",
            "type":"Manufacturing & Wholesale Goods"
        }
    ],
    "sg:phone":"+1 727 867 7777",
    "sg:postcode":"33712",
    "sg:province":"FL",
    "sg:tags":[
        "fastener"
    ],
    "wof:name":"Diamond Supply & Fastener",
    "wof:placetype":"venue"
},
  "geometry": {"coordinates":[-82.677629,27.763626],"type":"Point"}
}