{
  "type": "Feature",
  "properties": {
    "iso:country":"US",
    "sg:address":"403 E Davis Blvd",
    "sg:city":"Tampa",
    "sg:classifiers":[
        {
            "category":"Organizations",
            "subcategory":"Religious Organization",
            "type":"Services"
        }
    ],
    "sg:phone":"+1 813 254 1900",
    "sg:postcode":"33606",
    "sg:province":"FL",
    "sg:tags":[
        "church"
    ],
    "wof:name":"LA Mision USA",
    "wof:placetype":"venue"
},
  "geometry": {"coordinates":[-82.451554,27.923443],"type":"Point"}
}