{
  "type": "Feature",
  "properties": {
    "iso:country":"US",
    "sg:address":"7854 NW 62nd St",
    "sg:city":"Miami",
    "sg:classifiers":[
        {
            "category":"Banks & Credit Unions",
            "subcategory":"Financial Services",
            "type":"Services"
        }
    ],
    "sg:phone":"+1 305 463 8258",
    "sg:postcode":"33166",
    "sg:province":"FL",
    "sg:tags":[
        "international",
        "trade"
    ],
    "wof:name":"JKR Trading Corp",
    "wof:placetype":"venue"
},
  "geometry": {"coordinates":[-80.325671,25.829754],"type":"Point"}
}