{
  "type": "Feature",
  "properties": {
    "iso:country":"US",
    "sg:address":"6246 8th St SW",
    "sg:city":"West Miami",
    "sg:classifiers":[
        {
            "category":"Food & Beverages",
            "subcategory":"Groceries & Convenience Stores",
            "type":"Retail Goods"
        }
    ],
    "sg:phone":"+1 305 262 6244",
    "sg:postcode":"33144",
    "sg:province":"FL",
    "wof:name":"Estrella Corp",
    "wof:placetype":"venue"
},
  "geometry": {"coordinates":[-80.296018,25.763235],"type":"Point"}
}