{
  "type": "Feature",
  "properties": {
    "iso:country":"US",
    "sg:address":"6150 Silver Star Rd",
    "sg:city":"Orlando",
    "sg:classifiers":[
        {
            "category":"Retail",
            "subcategory":"Auto Repair",
            "type":"Services"
        }
    ],
    "sg:phone":"+1 407 293 0723",
    "sg:postcode":"32808",
    "sg:province":"FL",
    "sg:tags":[
        "repairing",
        "automobile"
    ],
    "wof:name":"Bel-Aire Auto Svc & Tire Ctr",
    "wof:placetype":"venue"
},
  "geometry": {"coordinates":[-81.467264,28.577648],"type":"Point"}
}