{
  "type": "Feature",
  "properties": {
    "iso:country":"US",
    "sg:address":"19 E Ave E",
    "sg:city":"Bradenton",
    "sg:classifiers":[
        {
            "category":"Manufacturing",
            "subcategory":"Retail Goods",
            "type":"Manufacturing & Wholesale Goods"
        }
    ],
    "sg:phone":"+1 941 727 9959",
    "sg:postcode":"34207",
    "sg:province":"FL",
    "sg:tags":[
        "assembly",
        "fabricating"
    ],
    "wof:name":"Gt Fabrication Weld & Design",
    "wof:placetype":"venue"
},
  "geometry": {"coordinates":[-82.56780999999999,27.431627],"type":"Point"}
}