{
  "type": "Feature",
  "properties": {
    "addr:full":"2890 W Airport Blvd Sanford FL 32771",
    "addr:housenumber":"2890",
    "addr:postcode":"32771",
    "addr:street":"W Airport Blvd",
    "iso:country":"US",
    "sg:address":"2890 W Airport Blvd",
    "sg:city":"Sanford",
    "sg:classifiers":[
        {
            "category":"Autos & Motor Vehicles",
            "subcategory":"Automobile Sales",
            "type":"Retail Goods"
        }
    ],
    "sg:phone":"+1 407 834 6400",
    "sg:postcode":"32771",
    "sg:province":"FL",
    "sg:tags":[
        "trucks-industrial"
    ],
    "wof:name":"Tampa Forklift",
    "wof:placetype":"venue"
},
  "geometry": {"coordinates":[-81.297982,28.808243],"type":"Point"}
}