{
  "type": "Feature",
  "properties": {
    "iso:country":"US",
    "sg:address":"6865 Thunder Ln",
    "sg:city":"Milton",
    "sg:classifiers":[
        {
            "category":"Building & Trades",
            "subcategory":"Construction",
            "type":"Services"
        }
    ],
    "sg:phone":"+1 850 626 5924",
    "sg:postcode":"32570",
    "sg:province":"FL",
    "sg:tags":[
        "contractor"
    ],
    "wof:name":"Bowman & Bass",
    "wof:placetype":"venue"
},
  "geometry": {"coordinates":[-87.036365,30.683507],"type":"Point"}
}