{
  "type": "Feature",
  "properties": {
    "iso:country":"US",
    "sg:address":"1173 Jo Jo Rd",
    "sg:city":"Pensacola",
    "sg:classifiers":[
        {
            "category":"Professional",
            "type":"Services"
        }
    ],
    "sg:phone":"+1 850 474 5203",
    "sg:postcode":"32514",
    "sg:province":"FL",
    "sg:tags":[
        "establishment"
    ],
    "wof:name":"Wayside Scriptures",
    "wof:placetype":"venue"
},
  "geometry": {"coordinates":[-87.24063700000001,30.525404],"type":"Point"}
}