{
  "type": "Feature",
  "properties": {
    "addr:full":"46 Minnehaha Cir Maitland FL 32751",
    "addr:postcode":"32751",
    "addr:street":"46 Minnehaha Cir",
    "iso:country":"US",
    "sg:address":"46 Minnehaha Cir",
    "sg:city":"Maitland",
    "sg:classifiers":[
        {
            "category":"Government",
            "subcategory":"Office",
            "type":"Public Place"
        }
    ],
    "sg:phone":"+1 407 628 2239",
    "sg:postcode":"32751",
    "sg:province":"FL",
    "sg:tags":[
        "executive"
    ],
    "wof:name":"Courthouse Executive Center",
    "wof:placetype":"venue"
},
  "geometry": {"coordinates":[-81.35471099999999,28.628138],"type":"Point"}
}