{
  "type": "Feature",
  "properties": {
    "addr:full":"280 Orange Ave Longwood FL 32750",
    "addr:housenumber":"280",
    "addr:postcode":"32750",
    "addr:street":"Orange Ave",
    "iso:country":"US",
    "sg:address":"280 Orange Ave",
    "sg:city":"Longwood",
    "sg:classifiers":[
        {
            "category":"Building & Trades",
            "subcategory":"Construction",
            "type":"Services"
        }
    ],
    "sg:phone":"+1 407 332 8022",
    "sg:postcode":"32750",
    "sg:province":"FL",
    "sg:tags":[
        "wall",
        "commercial",
        "covering",
        "painting",
        "contractor"
    ],
    "wof:name":"Apollo Painting Inc",
    "wof:placetype":"venue"
},
  "geometry": {"coordinates":[-81.34384300000001,28.703668],"type":"Point"}
}