{
  "type": "Feature",
  "properties": {
    "iso:country":"US",
    "sg:address":"11400 Quail Roost Dr",
    "sg:city":"Miami",
    "sg:classifiers":[
        {
            "category":"Fast Food",
            "type":"Food & Drink"
        },
        {
            "category":"Food & Beverages",
            "subcategory":"Meat & Fish",
            "type":"Retail Goods"
        }
    ],
    "sg:phone":"+1 305 233 5181",
    "sg:postcode":"33157",
    "sg:province":"FL",
    "sg:tags":[
        "burger",
        "hot",
        "dog"
    ],
    "sg:website":"www.burgerking.com",
    "wof:name":"Burger King Restaurants",
    "wof:placetype":"venue"
},
  "geometry": {"coordinates":[-80.378502,25.5928],"type":"Point"}
}