{
  "type": "Feature",
  "properties": {
    "iso:country":"US",
    "sg:address":"6412 1st Ave W",
    "sg:city":"Bradenton",
    "sg:classifiers":[
        {
            "category":"Manufacturing",
            "subcategory":"Tools & Machinery",
            "type":"Manufacturing & Wholesale Goods"
        },
        {
            "category":"Building & Trades",
            "subcategory":"Landscaping Services",
            "type":"Services"
        }
    ],
    "sg:phone":"+1 941 377 9142",
    "sg:postcode":"34209",
    "sg:province":"FL",
    "sg:tags":[
        "industrial",
        "tree",
        "mfg"
    ],
    "wof:name":"Ace Stump Grinding Service LLC",
    "wof:placetype":"venue"
},
  "geometry": {"coordinates":[-82.625531,27.4997],"type":"Point"}
}