{
  "type": "Feature",
  "properties": {
    "iso:country":"US",
    "sg:address":"3424 W State Rd 46",
    "sg:city":"Sanford",
    "sg:classifiers":[
        {
            "category":"Wholesale",
            "subcategory":"Electrical",
            "type":"Manufacturing & Wholesale Goods"
        }
    ],
    "sg:phone":"+1 407 322 7780",
    "sg:postcode":"32771",
    "sg:province":"FL",
    "sg:tags":[
        "utility"
    ],
    "wof:name":"Central Locating Svc",
    "wof:placetype":"venue"
},
  "geometry": {"coordinates":[-81.312764,28.811315],"type":"Point"}
}