{
  "type": "Feature",
  "properties": {
    "addr:full":"5167 Wellington Rd Spring Hill FL 34609",
    "addr:housenumber":"5167",
    "addr:postcode":"34609",
    "addr:street":"Wellington Rd",
    "iso:country":"US",
    "sg:address":"5167 Wellington Rd",
    "sg:city":"Spring Hill",
    "sg:classifiers":[
        {
            "category":"Building & Trades",
            "subcategory":"Landscaping Services",
            "type":"Services"
        }
    ],
    "sg:phone":"+1 352 666 0830",
    "sg:postcode":"34609",
    "sg:province":"FL",
    "wof:name":"Russell E Smith",
    "wof:placetype":"venue"
},
  "geometry": {"coordinates":[-82.51849199999999,28.505233],"type":"Point"}
}