{
  "type": "Feature",
  "properties": {
    "addr:full":"777 S Federal Hwy Boca Raton FL 33432",
    "addr:housenumber":"777",
    "addr:postcode":"33432",
    "addr:street":"S Federal Hwy",
    "iso:country":"US",
    "sg:address":"777 S Federal Hwy",
    "sg:city":"Boca Raton",
    "sg:classifiers":[
        {
            "category":"Bagels",
            "type":"Food & Drink"
        },
        {
            "category":"Coffee & Tea",
            "type":"Food & Drink"
        },
        {
            "category":"Food & Beverages",
            "subcategory":"Bakery",
            "type":"Retail Goods"
        },
        {
            "category":"Bakery",
            "type":"Food & Drink"
        },
        {
            "category":"Donuts",
            "type":"Food & Drink"
        }
    ],
    "sg:menulink":"http://www.allmenus.com/fl/boca-raton/137897-dunkin-donuts/menu/",
    "sg:phone":"+1 561 361 4009",
    "sg:postcode":"33432",
    "sg:province":"FL",
    "sg:tags":[
        "coffee",
        "tea",
        "american",
        "bagel",
        "bakery",
        "pastry"
    ],
    "wof:name":"Dunkin' Donuts",
    "wof:placetype":"venue"
},
  "geometry": {"coordinates":[-80.08631,26.34289],"type":"Point"}
}