{
  "type": "Feature",
  "properties": {
    "iso:country":"US",
    "sg:address":"6551 43rd St N",
    "sg:city":"Pinellas Park",
    "sg:classifiers":[
        {
            "category":"Wholesale",
            "subcategory":"Home Furnishings",
            "type":"Manufacturing & Wholesale Goods"
        }
    ],
    "sg:phone":"+1 727 528 6863",
    "sg:postcode":"33781",
    "sg:province":"FL",
    "sg:tags":[
        "decorating",
        "supply"
    ],
    "wof:name":"Tatouage Inc",
    "wof:placetype":"venue"
},
  "geometry": {"coordinates":[-82.69176299999999,27.828754],"type":"Point"}
}