{
  "type": "Feature",
  "properties": {
    "addr:full":"8481 75th Ave Seminole FL 33777",
    "addr:housenumber":"8481",
    "addr:postcode":"33777",
    "addr:street":"75Th Ave",
    "iso:country":"US",
    "sg:address":"8481 75th Ave",
    "sg:city":"Seminole",
    "sg:classifiers":[
        {
            "category":"Building & Trades",
            "subcategory":"Construction",
            "type":"Services"
        }
    ],
    "sg:phone":"+1 727 391 2429",
    "sg:postcode":"33777",
    "sg:province":"FL",
    "sg:tags":[
        "house"
    ],
    "wof:name":"Rooney Builders Inc",
    "wof:placetype":"venue"
},
  "geometry": {"coordinates":[-82.757577,27.840163],"type":"Point"}
}