{
  "type": "Feature",
  "properties": {
    "addr:full":"13620 Maria Dr Port Richey FL 34667",
    "addr:housenumber":"13620",
    "addr:postcode":"34667",
    "addr:street":"Maria Dr",
    "iso:country":"US",
    "sg:address":"13620 Maria Dr",
    "sg:city":"Port Richey",
    "sg:classifiers":[
        {
            "category":"Recreation",
            "subcategory":"Arcade",
            "type":"Entertainment"
        }
    ],
    "sg:phone":"+1 727 862 1007",
    "sg:postcode":"34667",
    "sg:province":"FL",
    "sg:tags":[
        "device",
        "operator",
        "telephone",
        "amusement",
        "communications"
    ],
    "wof:name":"Atlantic & Gulf Communication",
    "wof:placetype":"venue"
},
  "geometry": {"coordinates":[-82.710272,28.355637],"type":"Point"}
}