{
  "type": "Feature",
  "properties": {
    "iso:country":"US",
    "sg:address":"3300 W 84th St",
    "sg:city":"Hialeah",
    "sg:classifiers":[
        {
            "category":"Food & Beverages",
            "subcategory":"Specialty",
            "type":"Retail Goods"
        }
    ],
    "sg:phone":"+1 305 362 3484",
    "sg:postcode":"33018",
    "sg:province":"FL",
    "sg:tags":[
        "water",
        "bulk",
        "company"
    ],
    "wof:name":"Purewater Express Co",
    "wof:placetype":"venue"
},
  "geometry": {"coordinates":[-80.350685,25.896975],"type":"Point"}
}