{
  "type": "Feature",
  "properties": {
    "iso:country":"US",
    "sg:address":"1803 Park Center Dr # 210",
    "sg:city":"Orlando",
    "sg:classifiers":[
        {
            "category":"Health Services",
            "subcategory":"Doctor",
            "type":"Services"
        },
        {
            "category":"Health Services",
            "subcategory":"Clinic",
            "type":"Services"
        },
        {
            "category":"Health Services",
            "subcategory":"Podiatrist",
            "type":"Services"
        }
    ],
    "sg:phone":"+1 407 299 1335",
    "sg:postcode":"32835",
    "sg:province":"FL",
    "sg:tags":[
        "physician",
        "medical",
        "surgeons",
        "surgeon"
    ],
    "wof:name":"Metro West Foot And Ankle Cent",
    "wof:placetype":"venue"
},
  "geometry": {"coordinates":[-81.47069999999999,28.520697],"type":"Point"}
}