{
  "type": "Feature",
  "properties": {
    "iso:country":"US",
    "sg:address":"2220 Classic Ct",
    "sg:city":"Longwood",
    "sg:classifiers":[
        {
            "category":"Real Estate",
            "subcategory":"Real Estate Agent",
            "type":"Services"
        }
    ],
    "sg:phone":"+1 407 869 7083",
    "sg:postcode":"32779",
    "sg:province":"FL",
    "wof:name":"Next Estate Communic",
    "wof:placetype":"venue"
},
  "geometry": {"coordinates":[-81.426132,28.68327],"type":"Point"}
}