{
  "type": "Feature",
  "properties": {
    "iso:country":"US",
    "sg:address":"110 Mc Leod St",
    "sg:city":"Merritt Island",
    "sg:classifiers":[
        {
            "category":"Wholesale",
            "subcategory":"Home Furnishings",
            "type":"Manufacturing & Wholesale Goods"
        }
    ],
    "sg:phone":"+1 321 452 2922",
    "sg:postcode":"32953",
    "sg:province":"FL",
    "wof:name":"Lemuria",
    "wof:placetype":"venue"
},
  "geometry": {"coordinates":[-80.701194,28.359179],"type":"Point"}
}