{
  "type": "Feature",
  "properties": {
    "addr:full":"13031 NW 7th Ave Miami FL 33168",
    "addr:housenumber":"13031",
    "addr:postcode":"33168",
    "addr:street":"Nw 7Th Ave",
    "iso:country":"US",
    "sg:address":"13031 NW 7th Ave",
    "sg:city":"Miami",
    "sg:classifiers":[
        {
            "category":"Shopping",
            "subcategory":"Discount & Variety Stores",
            "type":"Retail Goods"
        }
    ],
    "sg:phone":"+1 305 681 7900",
    "sg:postcode":"33168",
    "sg:province":"FL",
    "wof:name":"99 Cent Plus",
    "wof:placetype":"venue"
},
  "geometry": {"coordinates":[-80.21101899999999,25.894364],"type":"Point"}
}