{
  "type": "Feature",
  "properties": {
    "iso:country":"US",
    "sg:address":"245 SW 6th St",
    "sg:city":"Belle Glade",
    "sg:classifiers":[
        {
            "category":"Food & Beverages",
            "subcategory":"Groceries & Convenience Stores",
            "type":"Retail Goods"
        }
    ],
    "sg:phone":"+1 561 996 0760",
    "sg:postcode":"33430",
    "sg:province":"FL",
    "sg:tags":[
        "grocer"
    ],
    "wof:name":"Family Food Market",
    "wof:placetype":"venue"
},
  "geometry": {"coordinates":[-80.673806,26.684555],"type":"Point"}
}