{
  "type": "Feature",
  "properties": {
    "iso:country":"US",
    "sg:address":"100 E Sybelia Ave Ste 165",
    "sg:city":"Maitland",
    "sg:classifiers":[
        {
            "category":"Health Services",
            "subcategory":"Clinic",
            "type":"Services"
        }
    ],
    "sg:phone":"+1 407 645 4111",
    "sg:postcode":"32751",
    "sg:province":"FL",
    "sg:tags":[
        "counseling",
        "mental"
    ],
    "wof:name":"Stoehr Catherine J MA Lmhc Ceds",
    "wof:placetype":"venue"
},
  "geometry": {"coordinates":[-81.365601,28.631201],"type":"Point"}
}