{
  "type": "Feature",
  "properties": {
    "addr:full":"5504 Island Walk Cir Naples FL 34119",
    "addr:housenumber":"5504",
    "addr:postcode":"34119",
    "addr:street":"Island Walk Cir",
    "iso:country":"US",
    "sg:address":"5504 Island Walk Cir",
    "sg:city":"Naples",
    "sg:classifiers":[
        {
            "category":"Freight",
            "type":"Transportation"
        }
    ],
    "sg:phone":"+1 239 596 6190",
    "sg:postcode":"34119",
    "sg:province":"FL",
    "sg:tags":[
        "mover"
    ],
    "wof:name":"Transmart Inc",
    "wof:placetype":"venue"
},
  "geometry": {"coordinates":[-81.717961,26.246254],"type":"Point"}
}