{
  "type": "Feature",
  "properties": {
    "addr:full":"2821 SW 124th Ct Miami FL 33175",
    "addr:housenumber":"2821",
    "addr:postcode":"33175",
    "addr:street":"Sw 124Th Ct",
    "iso:country":"US",
    "sg:address":"2821 SW 124th Ct",
    "sg:city":"Miami",
    "sg:classifiers":[
        {
            "category":"Professional",
            "subcategory":"Advertising",
            "type":"Services"
        }
    ],
    "sg:phone":"+1 305 220 6033",
    "sg:postcode":"33175",
    "sg:province":"FL",
    "wof:name":"Florida Export & Assistance",
    "wof:placetype":"venue"
},
  "geometry": {"coordinates":[-80.396539,25.741311],"type":"Point"}
}