{
  "type": "Feature",
  "properties": {
    "iso:country":"US",
    "sg:address":"24600 S Tamiami Trl",
    "sg:city":"Bonita Springs",
    "sg:classifiers":[
        {
            "category":"Restaurant",
            "type":"Food & Drink"
        }
    ],
    "sg:menulink":"http://www.allmenus.com/fl/bonita-springs/161185-cheeburger-cheeburger/menu/",
    "sg:phone":"+1 239 948 1399",
    "sg:postcode":"34134",
    "sg:province":"FL",
    "sg:tags":[
        "burger",
        "american",
        "diner"
    ],
    "wof:name":"Cheeburger Cheeburger",
    "wof:placetype":"venue"
},
  "geometry": {"coordinates":[-81.809364,26.382038],"type":"Point"}
}