{
  "type": "Feature",
  "properties": {
    "addr:full":"2740 SW Martin Downs Blvd Palm City FL 34990",
    "addr:housenumber":"2740",
    "addr:postcode":"34990",
    "addr:street":"Sw Martin Downs Blvd",
    "iso:country":"US",
    "sg:address":"2740 SW Martin Downs Blvd",
    "sg:city":"Palm City",
    "sg:classifiers":[
        {
            "category":"Local Transit",
            "type":"Transportation"
        }
    ],
    "sg:phone":"+1 772 286 2637",
    "sg:postcode":"34990",
    "sg:province":"FL",
    "sg:tags":[
        "limousine"
    ],
    "wof:name":"Cobblestone Limousine Svc",
    "wof:placetype":"venue"
},
  "geometry": {"coordinates":[-80.289996,27.172367],"type":"Point"}
}