{
  "type": "Feature",
  "properties": {
    "iso:country":"US",
    "sg:address":"10543 NW 6th Ave",
    "sg:city":"Miami",
    "sg:classifiers":[
        {
            "category":"Retail",
            "subcategory":"Self-service Laundry",
            "type":"Services"
        }
    ],
    "sg:phone":"+1 305 759 8701",
    "sg:postcode":"33150",
    "sg:province":"FL",
    "sg:tags":[
        "coin"
    ],
    "wof:name":"Napoles Alcibiades",
    "wof:placetype":"venue"
},
  "geometry": {"coordinates":[-80.207413,25.871639],"type":"Point"}
}