{
  "type": "Feature",
  "properties": {
    "addr:full":"370 Sweet Bay Ave New Smyrna Beach FL 32168",
    "addr:housenumber":"370",
    "addr:postcode":"32168",
    "addr:street":"Sweet Bay Ave",
    "iso:country":"US",
    "sg:address":"370 Sweet Bay Ave",
    "sg:city":"New Smyrna Beach",
    "sg:classifiers":[
        {
            "category":"Social Services",
            "type":"Services"
        }
    ],
    "sg:phone":"+1 386 427 4443",
    "sg:postcode":"32168",
    "sg:province":"FL",
    "sg:tags":[
        "senior",
        "citizen"
    ],
    "wof:name":"Caregiver Connections",
    "wof:placetype":"venue"
},
  "geometry": {"coordinates":[-80.983222,29.039909],"type":"Point"}
}