{
  "type": "Feature",
  "properties": {
    "iso:country":"US",
    "sg:address":"150 Ave B SE",
    "sg:city":"Winter Haven",
    "sg:classifiers":[
        {
            "category":"Health Services",
            "subcategory":"Clinic",
            "type":"Services"
        }
    ],
    "sg:phone":"+1 863 294 1429",
    "sg:postcode":"33880",
    "sg:province":"FL",
    "sg:tags":[
        "specialty",
        "outpatient"
    ],
    "wof:name":"Childrens Rehab",
    "wof:placetype":"venue"
},
  "geometry": {"coordinates":[-81.725852,28.020213],"type":"Point"}
}