{
  "type": "Feature",
  "properties": {
    "addr:full":"2605 Berryvine Pl Valrico FL 33596",
    "addr:housenumber":"2605",
    "addr:postcode":"33596",
    "addr:street":"Berryvine Pl",
    "iso:country":"US",
    "sg:address":"2605 Berryvine Pl",
    "sg:city":"Valrico",
    "sg:classifiers":[
        {
            "category":"Building & Trades",
            "subcategory":"Construction",
            "type":"Services"
        }
    ],
    "sg:phone":"+1 813 684 9265",
    "sg:postcode":"33596",
    "sg:province":"FL",
    "sg:tags":[
        "consulting"
    ],
    "wof:name":"Adams Roy Jr Consulting L",
    "wof:placetype":"venue"
},
  "geometry": {"coordinates":[-82.243454,27.907846],"type":"Point"}
}