{
  "type": "Feature",
  "properties": {
    "iso:country":"US",
    "sg:address":"3119 Spring Glen Rd",
    "sg:city":"Jacksonville",
    "sg:classifiers":[
        {
            "category":"Health Services",
            "subcategory":"Clinic",
            "type":"Services"
        }
    ],
    "sg:phone":"+1 904 306 1801",
    "sg:postcode":"32207",
    "sg:province":"FL",
    "sg:tags":[
        "home"
    ],
    "wof:name":"S R Alternative Homecare",
    "wof:placetype":"venue"
},
  "geometry": {"coordinates":[-81.60978799999999,30.292813],"type":"Point"}
}