{
  "type": "Feature",
  "properties": {
    "iso:country":"US",
    "sg:address":"19137 SE Federal Hwy",
    "sg:city":"Tequesta",
    "sg:classifiers":[
        {
            "category":"Real Estate",
            "subcategory":"Real Estate Agent",
            "type":"Services"
        }
    ],
    "sg:phone":"+1 561 747 9200",
    "sg:postcode":"33469",
    "sg:province":"FL",
    "wof:name":"Mc Roberts Real Estate Inc",
    "wof:placetype":"venue"
},
  "geometry": {"coordinates":[-80.087311,26.970735],"type":"Point"}
}