{
  "type": "Feature",
  "properties": {
    "addr:full":"17689 Summerlin Rd Fort Myers FL 33908",
    "addr:housenumber":"17689",
    "addr:postcode":"33908",
    "addr:street":"Summerlin Rd",
    "iso:country":"US",
    "sg:address":"17689 Summerlin Rd",
    "sg:city":"Fort Myers",
    "sg:classifiers":[
        {
            "category":"Home & Garden",
            "subcategory":"Building Materials",
            "type":"Retail Goods"
        }
    ],
    "sg:phone":"+1 239 489 3611",
    "sg:postcode":"33908",
    "sg:province":"FL",
    "wof:name":"Italian Kitchen Designs",
    "wof:placetype":"venue"
},
  "geometry": {"coordinates":[-81.959816,26.493879],"type":"Point"}
}