{
  "type": "Feature",
  "properties": {
    "iso:country":"US",
    "sg:address":"23215 Harbor View Rd",
    "sg:city":"Port Charlotte",
    "sg:classifiers":[
        {
            "category":"Freight",
            "type":"Transportation"
        }
    ],
    "sg:phone":"+1 941 624 3303",
    "sg:postcode":"33980",
    "sg:province":"FL",
    "sg:tags":[
        "storage",
        "public",
        "facility"
    ],
    "wof:name":"Storage USA",
    "wof:placetype":"venue"
},
  "geometry": {"coordinates":[-82.066068,26.96511],"type":"Point"}
}