{
  "type": "Feature",
  "properties": {
    "addr:full":"13136 Wexford Hollow Rd N Jacksonville FL 32224",
    "addr:housenumber":"13136",
    "addr:postcode":"32224",
    "addr:street":"Wexford Hollow Rd N",
    "iso:country":"US",
    "sg:address":"13136 Wexford Hollow Rd N",
    "sg:city":"Jacksonville",
    "sg:classifiers":[
        {
            "category":"Insurance",
            "subcategory":"Insurance Agent",
            "type":"Services"
        }
    ],
    "sg:phone":"+1 904 992 6604",
    "sg:postcode":"32224",
    "sg:province":"FL",
    "wof:name":"Senior Life Marketing",
    "wof:placetype":"venue"
},
  "geometry": {"coordinates":[-81.47432999999999,30.28189],"type":"Point"}
}