{
  "type": "Feature",
  "properties": {
    "iso:country":"US",
    "sg:address":"4720 53rd Ave E",
    "sg:city":"Bradenton",
    "sg:classifiers":[
        {
            "category":"Autos & Motor Vehicles",
            "subcategory":"Fuel & Gas Station",
            "type":"Retail Goods"
        }
    ],
    "sg:phone":"+1 941 755 2090",
    "sg:postcode":"34203",
    "sg:province":"FL",
    "sg:tags":[
        "oil"
    ],
    "wof:name":"Crazy Papa's Amoco",
    "wof:placetype":"venue"
},
  "geometry": {"coordinates":[-82.497513,27.446106],"type":"Point"}
}