{
  "type": "Feature",
  "properties": {
    "iso:country":"US",
    "sg:address":"20900 Taft St",
    "sg:city":"Hollywood",
    "sg:classifiers":[
        {
            "category":"Wholesale",
            "subcategory":"Machinery & Supplies",
            "type":"Manufacturing & Wholesale Goods"
        }
    ],
    "sg:phone":"+1 954 433 2800",
    "sg:postcode":"33029",
    "sg:province":"FL",
    "sg:tags":[
        "equipment",
        "industrial"
    ],
    "wof:name":"Linder Industrial Machinery Co",
    "wof:placetype":"venue"
},
  "geometry": {"coordinates":[-80.43052,26.022178],"type":"Point"}
}