{
  "type": "Feature",
  "properties": {
    "iso:country":"US",
    "sg:address":"11456 Paradise Cove Ln",
    "sg:city":"Wellington",
    "sg:classifiers":[
        {
            "category":"Building & Trades",
            "subcategory":"Construction",
            "type":"Services"
        }
    ],
    "sg:phone":"+1 561 204 2666",
    "sg:postcode":"33449",
    "sg:province":"FL",
    "sg:tags":[
        "sealing",
        "tile-cleaning",
        "refinishing"
    ],
    "sg:website":"http://www.aaatile.net",
    "wof:name":"AAA Tile And Marble Restoration",
    "wof:placetype":"venue"
},
  "geometry": {"coordinates":[-80.22958199999999,26.613253],"type":"Point"}
}