{
  "type": "Feature",
  "properties": {
    "iso:country":"US",
    "sg:address":"9831 Beach Blvd",
    "sg:city":"Jacksonville",
    "sg:classifiers":[
        {
            "category":"Communications",
            "subcategory":"Radio Station",
            "type":"Services"
        }
    ],
    "sg:phone":"+1 904 564 9000",
    "sg:postcode":"32246",
    "sg:province":"FL",
    "sg:tags":[
        "broadcast"
    ],
    "wof:name":"Wjxr 92 1 FM",
    "wof:placetype":"venue"
},
  "geometry": {"coordinates":[-81.554993,30.286647],"type":"Point"}
}