{
  "type": "Feature",
  "properties": {
    "addr:full":"9561 Satellite Blvd Ste 325 Orlando FL 32837",
    "addr:housenumber":"9561",
    "addr:postcode":"32837",
    "addr:street":"Satellite Blvd Ste 325",
    "iso:country":"US",
    "sg:address":"9561 Satellite Blvd Ste 325",
    "sg:city":"Orlando",
    "sg:classifiers":[
        {
            "category":"Manufacturing",
            "subcategory":"Building Materials",
            "type":"Manufacturing & Wholesale Goods"
        }
    ],
    "sg:phone":"+1 407 851 3300",
    "sg:postcode":"32837",
    "sg:province":"FL",
    "sg:tags":[
        "fireproofing"
    ],
    "sg:website":"http://www.abesco.net",
    "wof:name":"Abesco",
    "wof:placetype":"venue"
},
  "geometry": {"coordinates":[-81.401287,28.419852],"type":"Point"}
}