{
  "type": "Feature",
  "properties": {
    "addr:full":"4999 34th St N Saint Petersburg FL 33714",
    "addr:housenumber":"4999",
    "addr:postcode":"33714",
    "addr:street":"34Th St N",
    "iso:country":"US",
    "sg:address":"4999 34th St N",
    "sg:city":"Saint Petersburg",
    "sg:classifiers":[
        {
            "category":"Restaurant",
            "type":"Food & Drink"
        }
    ],
    "sg:menulink":"http://www.allmenus.com/fl/st-petersburg/11589-dennys/menu/",
    "sg:phone":"+1 813 522 1552",
    "sg:postcode":"33714",
    "sg:province":"FL",
    "sg:tags":[
        "american",
        "diner"
    ],
    "wof:name":"Denny's",
    "wof:placetype":"venue"
},
  "geometry": {"coordinates":[-82.67944199999999,27.817414],"type":"Point"}
}