{
  "type": "Feature",
  "properties": {
    "iso:country":"US",
    "sg:address":"275 Marco Way S",
    "sg:city":"Satellite Beach",
    "sg:classifiers":[
        {
            "category":"Professional",
            "subcategory":"Business Services",
            "type":"Services"
        },
        {
            "category":"Building & Trades",
            "subcategory":"Construction",
            "type":"Services"
        }
    ],
    "sg:phone":"+1 321 777 6060",
    "sg:postcode":"32937",
    "sg:province":"FL",
    "sg:tags":[
        "residential",
        "pool",
        "swimming"
    ],
    "wof:name":"Wetzel's Quality Finishing",
    "wof:placetype":"venue"
},
  "geometry": {"coordinates":[-80.593206,28.163311],"type":"Point"}
}