{
  "type": "Feature",
  "properties": {
    "iso:country":"US",
    "sg:address":"1238 N University Dr",
    "sg:city":"Fort Lauderdale",
    "sg:classifiers":[
        {
            "category":"Health Services",
            "subcategory":"Health Practitioner",
            "type":"Services"
        }
    ],
    "sg:phone":"+1 954 452 4424",
    "sg:postcode":"33322",
    "sg:province":"FL",
    "wof:name":"Yoga Institute of Broward",
    "wof:placetype":"venue"
},
  "geometry": {"coordinates":[-80.253046,26.247229],"type":"Point"}
}