{
  "type": "Feature",
  "properties": {
    "iso:country":"US",
    "sg:address":"7952 Horse Ferry Rd",
    "sg:city":"Orlando",
    "sg:classifiers":[
        {
            "category":"Shopping",
            "subcategory":"Stationery & Office Supplies",
            "type":"Retail Goods"
        },
        {
            "category":"Wholesale",
            "subcategory":"Office Equipment",
            "type":"Manufacturing & Wholesale Goods"
        },
        {
            "category":"Wholesale",
            "subcategory":"Computers",
            "type":"Manufacturing & Wholesale Goods"
        }
    ],
    "sg:phone":"+1 407 226 9880",
    "sg:postcode":"32835",
    "sg:province":"FL",
    "sg:tags":[
        "register",
        "autographic"
    ],
    "wof:name":"Cartridge Direct",
    "wof:placetype":"venue"
},
  "geometry": {"coordinates":[-81.50135899999999,28.505],"type":"Point"}
}