{
  "type": "Feature",
  "properties": {
    "iso:country":"US",
    "sg:address":"1560 N US Hwy 1",
    "sg:city":"Ormond Beach",
    "sg:classifiers":[
        {
            "category":"Autos & Motor Vehicles",
            "subcategory":"Fuel & Gas Station",
            "type":"Retail Goods"
        }
    ],
    "sg:phone":"+1 386 672 6666",
    "sg:postcode":"32174",
    "sg:province":"FL",
    "sg:tags":[
        "oil"
    ],
    "wof:name":"Valero Express Mart",
    "wof:placetype":"venue"
},
  "geometry": {"coordinates":[-81.127838,29.333573],"type":"Point"}
}