{
  "type": "Feature",
  "properties": {
    "iso:country":"US",
    "sg:address":"307 S Park Ave Ofc",
    "sg:city":"Winter Park",
    "sg:classifiers":[
        {
            "category":"Travel",
            "subcategory":"Hotels & Motels",
            "type":"Entertainment"
        }
    ],
    "sg:phone":"+1 407 647 1072",
    "sg:postcode":"32789",
    "sg:province":"FL",
    "wof:name":"Park Plaza Hotel",
    "wof:placetype":"venue"
},
  "geometry": {"coordinates":[-81.350998,28.5959],"type":"Point"}
}