{
  "type": "Feature",
  "properties": {
    "addr:full":"27014 Harbor Dr Bonita Springs FL 34135",
    "addr:housenumber":"27014",
    "addr:postcode":"34135",
    "addr:street":"Harbor Dr",
    "iso:country":"US",
    "sg:address":"27014 Harbor Dr",
    "sg:city":"Bonita Springs",
    "sg:classifiers":[
        {
            "category":"Building & Trades",
            "subcategory":"Construction",
            "type":"Services"
        }
    ],
    "sg:phone":"+1 239 947 7725",
    "sg:postcode":"34135",
    "sg:province":"FL",
    "sg:tags":[
        "general",
        "contractor"
    ],
    "wof:name":"J & L Peppers Construction Inc",
    "wof:placetype":"venue"
},
  "geometry": {"coordinates":[-81.799543,26.346607],"type":"Point"}
}