{
  "type": "Feature",
  "properties": {
    "addr:full":"3511 Plover Ave Unit 101 Naples FL 34117",
    "addr:housenumber":"3511;101",
    "addr:postcode":"34117",
    "addr:street":"Plover Ave Unit",
    "iso:country":"US",
    "sg:address":"3511 Plover Ave Unit 101",
    "sg:city":"Naples",
    "sg:classifiers":[
        {
            "category":"Manufacturing",
            "subcategory":"Chemicals & Compounds",
            "type":"Manufacturing & Wholesale Goods"
        },
        {
            "category":"Professional",
            "subcategory":"Business Services",
            "type":"Services"
        },
        {
            "category":"Building & Trades",
            "subcategory":"Pest Control",
            "type":"Services"
        }
    ],
    "sg:phone":"+1 239 234 1459",
    "sg:postcode":"34117",
    "sg:province":"FL",
    "sg:tags":[
        "industrial",
        "supply",
        "services-commercial",
        "termite",
        "bee",
        "equipment",
        "repellent",
        "mothproofing",
        "barriers",
        "removal",
        "inspection",
        "bird"
    ],
    "sg:website":"http://www.servicemaster.com",
    "wof:name":"Terminix",
    "wof:placetype":"venue"
},
  "geometry": {"coordinates":[-81.672346,26.157853],"type":"Point"}
}