{
  "type": "Feature",
  "properties": {
    "addr:full":"101 Palomino Dr Jupiter FL 33458",
    "addr:housenumber":"101",
    "addr:postcode":"33458",
    "addr:street":"Palomino Dr",
    "iso:country":"US",
    "sg:address":"101 Palomino Dr",
    "sg:city":"Jupiter",
    "sg:classifiers":[
        {
            "category":"Building & Trades",
            "subcategory":"Construction",
            "type":"Services"
        }
    ],
    "sg:phone":"+1 561 262 4074",
    "sg:postcode":"33458",
    "sg:province":"FL",
    "sg:tags":[
        "hanging",
        "contractor"
    ],
    "wof:name":"Joel B Michaud Inc",
    "wof:placetype":"venue"
},
  "geometry": {"coordinates":[-80.142269,26.915336],"type":"Point"}
}