{
  "type": "Feature",
  "properties": {
    "addr:full":"490 Allison Ave Longwood FL 32750",
    "addr:housenumber":"490",
    "addr:postcode":"32750",
    "addr:street":"Allison Ave",
    "iso:country":"US",
    "sg:address":"490 Allison Ave",
    "sg:city":"Longwood",
    "sg:classifiers":[
        {
            "category":"Wholesale",
            "subcategory":"Machinery & Supplies",
            "type":"Manufacturing & Wholesale Goods"
        }
    ],
    "sg:phone":"+1 407 831 9738",
    "sg:postcode":"32750",
    "sg:province":"FL",
    "sg:tags":[
        "distributor",
        "fitting",
        "industrial",
        "valve",
        "hose"
    ],
    "wof:name":"Southeast Service Co",
    "wof:placetype":"venue"
},
  "geometry": {"coordinates":[-81.369784,28.685048],"type":"Point"}
}