{
  "type": "Feature",
  "properties": {
    "iso:country":"US",
    "sg:address":"3620 NE 3rd Ave",
    "sg:city":"Fort Lauderdale",
    "sg:classifiers":[
        {
            "category":"Wholesale",
            "subcategory":"Hardware",
            "type":"Manufacturing & Wholesale Goods"
        },
        {
            "category":"Manufacturing",
            "subcategory":"Food",
            "type":"Manufacturing & Wholesale Goods"
        }
    ],
    "sg:phone":"+1 954 561 3103",
    "sg:postcode":"33334",
    "sg:province":"FL",
    "sg:tags":[
        "beverage",
        "syrup",
        "dispensing",
        "mfg"
    ],
    "wof:name":"Reese Brand Syrups Inc",
    "wof:placetype":"venue"
},
  "geometry": {"coordinates":[-80.142489,26.172386],"type":"Point"}
}