{
  "type": "Feature",
  "properties": {
    "addr:full":"1407 Banks Rd Margate FL 33063",
    "addr:housenumber":"1407",
    "addr:postcode":"33063",
    "addr:street":"Banks Rd Margate",
    "iso:country":"US",
    "sg:address":"1407 Banks Rd",
    "sg:city":"Margate",
    "sg:classifiers":[
        {
            "category":"Food & Beverages",
            "subcategory":"Fruits & Vegetables",
            "type":"Retail Goods"
        },
        {
            "category":"Wholesale",
            "subcategory":"Fruits & Vegetables",
            "type":"Manufacturing & Wholesale Goods"
        }
    ],
    "sg:phone":"+1 954 935 9213",
    "sg:postcode":"33063",
    "sg:province":"FL",
    "sg:tags":[
        "produce"
    ],
    "wof:name":"Royal Palm Produce Inc",
    "wof:placetype":"venue"
},
  "geometry": {"coordinates":[-80.194733,26.244961],"type":"Point"}
}