{
  "type": "Feature",
  "properties": {
    "iso:country":"US",
    "sg:address":"605 SW 79th Ave",
    "sg:city":"Miami",
    "sg:classifiers":[
        {
            "category":"Building & Trades",
            "subcategory":"Landscaping Services",
            "type":"Services"
        }
    ],
    "sg:phone":"+1 305 262 6652",
    "sg:postcode":"33144",
    "sg:province":"FL",
    "wof:name":"Rafael Lawn Maintence",
    "wof:placetype":"venue"
},
  "geometry": {"coordinates":[-80.324399,25.763923],"type":"Point"}
}