{
  "type": "Feature",
  "properties": {
    "iso:country":"US",
    "sg:address":"1900 Botree Ct",
    "sg:city":"Daytona Beach",
    "sg:classifiers":[
        {
            "category":"Shopping",
            "type":"Retail Goods"
        }
    ],
    "sg:phone":"+1 386 756 6385",
    "sg:postcode":"32128",
    "sg:province":"FL",
    "sg:tags":[
        "merchandise"
    ],
    "wof:name":"All Gods Animals Pet Sitting",
    "wof:placetype":"venue"
},
  "geometry": {"coordinates":[-81.05862399999999,29.087094],"type":"Point"}
}