{
  "type": "Feature",
  "properties": {
    "iso:country":"US",
    "sg:address":"2165 NW 19th St",
    "sg:city":"Fort Lauderdale",
    "sg:classifiers":[
        {
            "category":"Professional",
            "subcategory":"Advertising",
            "type":"Services"
        }
    ],
    "sg:phone":"+1 954 484 2134",
    "sg:postcode":"33311",
    "sg:province":"FL",
    "sg:tags":[
        "distribution"
    ],
    "wof:name":"Amigo Distributor Inc",
    "wof:placetype":"venue"
},
  "geometry": {"coordinates":[-80.170618,26.151331],"type":"Point"}
}