{
  "type": "Feature",
  "properties": {
    "addr:full":"109 S University Ave Archer FL 32618",
    "addr:housenumber":"109",
    "addr:postcode":"32618",
    "addr:street":"S University Ave",
    "iso:country":"US",
    "sg:address":"109 S University Ave",
    "sg:city":"Archer",
    "sg:classifiers":[
        {
            "category":"Food & Beverages",
            "subcategory":"Groceries & Convenience Stores",
            "type":"Retail Goods"
        }
    ],
    "sg:phone":"+1 352 495 2000",
    "sg:postcode":"32618",
    "sg:province":"FL",
    "wof:name":"Quick Corner",
    "wof:placetype":"venue"
},
  "geometry": {"coordinates":[-82.519047,29.531793],"type":"Point"}
}