{
  "type": "Feature",
  "properties": {
    "iso:country":"US",
    "sg:address":"1325 N Powerline Rd",
    "sg:city":"Pompano Beach",
    "sg:classifiers":[
        {
            "category":"Restaurant",
            "type":"Food & Drink"
        }
    ],
    "sg:phone":"+1 954 968 7260",
    "sg:postcode":"33069",
    "sg:province":"FL",
    "wof:name":"Brothers Delicatessen & Ctrng",
    "wof:placetype":"venue"
},
  "geometry": {"coordinates":[-80.15602800000001,26.215065],"type":"Point"}
}