{
  "type": "Feature",
  "properties": {
    "addr:full":"3817 Lake Joyce Dr Land O Lakes FL 34639",
    "addr:housenumber":"3817",
    "addr:postcode":"34639",
    "addr:street":"Lake Joyce Dr",
    "iso:country":"US",
    "sg:address":"3817 Lake Joyce Dr",
    "sg:city":"Land O Lakes",
    "sg:classifiers":[
        {
            "category":"Building & Trades",
            "subcategory":"Construction",
            "type":"Services"
        }
    ],
    "sg:phone":"+1 813 949 0366",
    "sg:postcode":"34639",
    "sg:province":"FL",
    "sg:tags":[
        "home",
        "family",
        "contractor"
    ],
    "wof:name":"Aziz Construction Co Inc",
    "wof:placetype":"venue"
},
  "geometry": {"coordinates":[-82.447453,28.213725],"type":"Point"}
}