{
  "type": "Feature",
  "properties": {
    "addr:full":"2031 Valencia Ave Vero Beach FL 32960",
    "addr:housenumber":"2031",
    "addr:postcode":"32960",
    "addr:street":"Valencia Ave",
    "iso:country":"US",
    "sg:address":"2031 Valencia Ave",
    "sg:city":"Vero Beach",
    "sg:classifiers":[
        {
            "category":"Real Estate",
            "subcategory":"Real Estate Operator",
            "type":"Services"
        }
    ],
    "sg:phone":"+1 772 562 1044",
    "sg:postcode":"32960",
    "sg:province":"FL",
    "sg:tags":[
        "building",
        "apartment"
    ],
    "wof:name":"Florida Aero Club Inc",
    "wof:placetype":"venue"
},
  "geometry": {"coordinates":[-80.40675,27.64104],"type":"Point"}
}