{
  "type": "Feature",
  "properties": {
    "iso:country":"US",
    "sg:address":"1041 N US Hwy 1",
    "sg:city":"Ormond Beach",
    "sg:classifiers":[
        {
            "category":"Food & Beverages",
            "subcategory":"Groceries & Convenience Stores",
            "type":"Retail Goods"
        }
    ],
    "sg:phone":"+1 386 677 6653",
    "sg:postcode":"32174",
    "sg:province":"FL",
    "sg:tags":[
        "station",
        "gasoline"
    ],
    "wof:name":"Charleys Jiffy Stores 2680",
    "wof:placetype":"venue"
},
  "geometry": {"coordinates":[-81.100808,29.311369],"type":"Point"}
}