{
  "type": "Feature",
  "properties": {
    "addr:full":"22991 US Hwy 19 Clearwater FL 33765",
    "addr:postcode":"22991;33765",
    "addr:street":"Us Hwy 19",
    "iso:country":"US",
    "sg:address":"22991 US Hwy 19",
    "sg:city":"Clearwater",
    "sg:classifiers":[
        {
            "category":"Autos & Motor Vehicles",
            "subcategory":"Auto Supplies",
            "type":"Retail Goods"
        }
    ],
    "sg:phone":"+1 727 797 9027",
    "sg:postcode":"33765",
    "sg:province":"FL",
    "sg:tags":[
        "automobile",
        "parts"
    ],
    "wof:name":"Discount Auto Parts Inc",
    "wof:placetype":"venue"
},
  "geometry": {"coordinates":[-82.72964899999999,27.981824],"type":"Point"}
}