{
  "type": "Feature",
  "properties": {
    "iso:country":"US",
    "sg:address":"11300 SW 125th St",
    "sg:city":"Miami",
    "sg:classifiers":[
        {
            "category":"Farming",
            "subcategory":"Nursery",
            "type":"Manufacturing & Wholesale Goods"
        }
    ],
    "sg:phone":"+1 305 232 1970",
    "sg:postcode":"33176",
    "sg:province":"FL",
    "sg:tags":[
        "plant",
        "grower",
        "foliage"
    ],
    "sg:website":"www.floridatuxedoplants.com",
    "wof:name":"Florida Tuxedo Plants Inc",
    "wof:placetype":"venue"
},
  "geometry": {"coordinates":[-80.378883,25.652406],"type":"Point"}
}