{
  "type": "Feature",
  "properties": {
    "iso:country":"US",
    "sg:address":"17100 Collins Ave",
    "sg:city":"Sunny Isles Bch",
    "sg:classifiers":[
        {
            "category":"Real Estate",
            "subcategory":"Real Estate Agent",
            "type":"Services"
        }
    ],
    "sg:phone":"+1 305 945 9556",
    "sg:postcode":"33160",
    "sg:province":"FL",
    "wof:name":"Re/Max",
    "wof:placetype":"venue"
},
  "geometry": {"coordinates":[-80.121771,25.934951],"type":"Point"}
}