{
  "type": "Feature",
  "properties": {
    "iso:country":"US",
    "sg:address":"902 Albee Rd W",
    "sg:city":"Nokomis",
    "sg:classifiers":[
        {
            "category":"Travel",
            "subcategory":"Travel Agent",
            "type":"Entertainment"
        }
    ],
    "sg:phone":"+1 941 488 2238",
    "sg:postcode":"34275",
    "sg:province":"FL",
    "sg:tags":[
        "agency"
    ],
    "wof:name":"Venice Travel Agency Inc",
    "wof:placetype":"venue"
},
  "geometry": {"coordinates":[-82.46746899999999,27.124557],"type":"Point"}
}