{
  "type": "Feature",
  "properties": {
    "addr:full":"7190 SW 98th St Miami FL 33156",
    "addr:housenumber":"7190",
    "addr:postcode":"33156",
    "addr:street":"Sw 98Th St",
    "iso:country":"US",
    "sg:address":"7190 SW 98th St",
    "sg:city":"Miami",
    "sg:classifiers":[
        {
            "category":"Health Services",
            "subcategory":"Doctor",
            "type":"Services"
        }
    ],
    "sg:phone":"+1 305 667 6072",
    "sg:postcode":"33156",
    "sg:province":"FL",
    "sg:tags":[
        "medical"
    ],
    "wof:name":"Interntnal Pdiatric Nephrology",
    "wof:placetype":"venue"
},
  "geometry": {"coordinates":[-80.310074,25.679595],"type":"Point"}
}