{
  "type": "Feature",
  "properties": {
    "iso:country":"US",
    "sg:address":"6663 Ryan Chase Ct",
    "sg:city":"Orlando",
    "sg:classifiers":[
        {
            "category":"Manufacturing",
            "subcategory":"Building Materials",
            "type":"Manufacturing & Wholesale Goods"
        }
    ],
    "sg:phone":"+1 407 522 1837",
    "sg:postcode":"32810",
    "sg:province":"FL",
    "sg:tags":[
        "mfg",
        "wood",
        "equipment-household",
        "kitchen",
        "cabinet"
    ],
    "wof:name":"Juniku Clirim",
    "wof:placetype":"venue"
},
  "geometry": {"coordinates":[-81.42688099999999,28.620509],"type":"Point"}
}