{
  "type": "Feature",
  "properties": {
    "iso:country":"US",
    "sg:address":"10915 SE Federal Hwy",
    "sg:city":"Hobe Sound",
    "sg:classifiers":[
        {
            "category":"Home & Garden",
            "subcategory":"Furniture",
            "type":"Retail Goods"
        }
    ],
    "sg:phone":"+1 772 546 9175",
    "sg:postcode":"33455",
    "sg:province":"FL",
    "wof:name":"Baron's Patio",
    "wof:placetype":"venue"
},
  "geometry": {"coordinates":[-80.141863,27.071663],"type":"Point"}
}