{
  "type": "Feature",
  "properties": {
    "addr:full":"645 Pierce St Clearwater FL 33756",
    "addr:housenumber":"645",
    "addr:postcode":"33756",
    "addr:street":"Pierce St",
    "iso:country":"US",
    "sg:address":"645 Pierce St",
    "sg:city":"Clearwater",
    "sg:classifiers":[
        {
            "category":"Government",
            "subcategory":"Police Station",
            "type":"Public Place"
        }
    ],
    "sg:phone":"+1 727 562 4420",
    "sg:postcode":"33756",
    "sg:province":"FL",
    "sg:tags":[
        "department"
    ],
    "wof:name":"Clearwater Police Dept",
    "wof:placetype":"venue"
},
  "geometry": {"coordinates":[-82.79765,27.963798],"type":"Point"}
}