{
  "type": "Feature",
  "properties": {
    "addr:full":"1 W Broadway St Fort Meade FL 33841",
    "addr:housenumber":"1",
    "addr:postcode":"33841",
    "addr:street":"W Broadway St",
    "iso:country":"US",
    "sg:address":"1 W Broadway St",
    "sg:city":"Fort Meade",
    "sg:classifiers":[
        {
            "category":"Personal",
            "subcategory":"Beauty Salon",
            "type":"Services"
        }
    ],
    "sg:phone":"+1 863 285 7795",
    "sg:postcode":"33841",
    "sg:province":"FL",
    "wof:name":"Shear Delight",
    "wof:placetype":"venue"
},
  "geometry": {"coordinates":[-81.801463,27.751924],"type":"Point"}
}