{
  "type": "Feature",
  "properties": {
    "iso:country":"US",
    "sg:address":"40 NE 158th St",
    "sg:city":"Miami",
    "sg:classifiers":[
        {
            "category":"Health Services",
            "subcategory":"Doctor",
            "type":"Services"
        }
    ],
    "sg:phone":"+1 305 944 7434",
    "sg:postcode":"33162",
    "sg:province":"FL",
    "sg:tags":[
        "clinic"
    ],
    "wof:name":"North Miami Medical",
    "wof:placetype":"venue"
},
  "geometry": {"coordinates":[-80.196654,25.919922],"type":"Point"}
}