{
  "type": "Feature",
  "properties": {
    "iso:country":"US",
    "sg:address":"230 S Dixie Hwy",
    "sg:city":"Boca Raton",
    "sg:classifiers":[
        {
            "category":"Home & Garden",
            "subcategory":"Garden Supply",
            "type":"Retail Goods"
        }
    ],
    "sg:phone":"+1 561 395 7731",
    "sg:postcode":"33432",
    "sg:province":"FL",
    "sg:tags":[
        "lawn",
        "mower"
    ],
    "wof:name":"Mc Gee Lawn Mower Svc",
    "wof:placetype":"venue"
},
  "geometry": {"coordinates":[-80.088188,26.347235],"type":"Point"}
}