{
  "type": "Feature",
  "properties": {
    "addr:full":"143 N Copeland St Tallahassee FL 32304",
    "addr:housenumber":"143",
    "addr:postcode":"32304",
    "addr:street":"N Copeland St",
    "iso:country":"US",
    "sg:address":"143 N Copeland St",
    "sg:city":"Tallahassee",
    "sg:classifiers":[
        {
            "category":"Travel",
            "subcategory":"Hotels & Motels",
            "type":"Entertainment"
        }
    ],
    "sg:phone":"+1 850 224 2461",
    "sg:postcode":"32304",
    "sg:province":"FL",
    "sg:tags":[
        "membership",
        "lodging"
    ],
    "wof:name":"Delta Gamma",
    "wof:placetype":"venue"
},
  "geometry": {"coordinates":[-84.290775,30.442853],"type":"Point"}
}