{
  "type": "Feature",
  "properties": {
    "iso:country":"US",
    "sg:address":"7430 Champagne Pl",
    "sg:city":"Boca Raton",
    "sg:classifiers":[
        {
            "category":"Shopping",
            "subcategory":"Florist",
            "type":"Retail Goods"
        }
    ],
    "sg:phone":"+1 561 394 3591",
    "sg:postcode":"33433",
    "sg:province":"FL",
    "wof:name":"J Morgan Flowers",
    "wof:placetype":"venue"
},
  "geometry": {"coordinates":[-80.16124000000001,26.350811],"type":"Point"}
}