{
  "type": "Feature",
  "properties": {
    "addr:full":"1591 Hayley Ln Ste 201 Fort Myers FL 33907",
    "addr:housenumber":"1591",
    "addr:postcode":"myers;33907",
    "addr:street":"Hayley Ln Ste 201",
    "iso:country":"US",
    "sg:address":"1591 Hayley Ln Ste 201",
    "sg:city":"Fort Myers",
    "sg:classifiers":[
        {
            "category":"Real Estate",
            "subcategory":"Architect",
            "type":"Services"
        }
    ],
    "sg:phone":"+1 239 481 0200",
    "sg:postcode":"33907",
    "sg:province":"FL",
    "wof:name":"Schenkel & Shultz Inc",
    "wof:placetype":"venue"
},
  "geometry": {"coordinates":[-81.880324,26.583857],"type":"Point"}
}