{
  "type": "Feature",
  "properties": {
    "iso:country":"US",
    "sg:address":"5471 E Mimosa Ln",
    "sg:city":"Inverness",
    "sg:classifiers":[
        {
            "category":"Shopping",
            "subcategory":"Used Merchandise",
            "type":"Retail Goods"
        }
    ],
    "sg:phone":"+1 352 726 9706",
    "sg:postcode":"34453",
    "sg:province":"FL",
    "wof:name":"Sisters Antiques Inc",
    "wof:placetype":"venue"
},
  "geometry": {"coordinates":[-82.346924,28.858684],"type":"Point"}
}