{
  "type": "Feature",
  "properties": {
    "addr:full":"18205 Biscayne Blvd Ste 2214 Aventura FL 33160",
    "addr:housenumber":"18205",
    "addr:postcode":"33160",
    "addr:street":"Biscayne Blvd Ste 2214",
    "iso:country":"US",
    "sg:address":"18205 Biscayne Blvd Ste 2214",
    "sg:city":"Aventura",
    "sg:classifiers":[
        {
            "category":"Health Services",
            "subcategory":"Doctor",
            "type":"Services"
        },
        {
            "category":"Health Services",
            "subcategory":"Health Practitioner",
            "type":"Services"
        }
    ],
    "sg:phone":"+1 305 466 1977",
    "sg:postcode":"33160",
    "sg:province":"FL",
    "sg:tags":[
        "acupuncture"
    ],
    "sg:website":"www.floridainegrativemedicine.com",
    "wof:name":"Center For Integrative Medicine",
    "wof:placetype":"venue"
},
  "geometry": {"coordinates":[-80.148015,25.943435],"type":"Point"}
}