{
  "type": "Feature",
  "properties": {
    "addr:full":"4135 Kings Hwy Port Charlotte FL 33980",
    "addr:housenumber":"4135",
    "addr:postcode":"33980",
    "addr:street":"Kings Hwy",
    "iso:country":"US",
    "sg:address":"4135 Kings Hwy",
    "sg:city":"Port Charlotte",
    "sg:classifiers":[
        {
            "category":"Building & Trades",
            "subcategory":"Landscaping Services",
            "type":"Services"
        }
    ],
    "sg:phone":"+1 941 625 7470",
    "sg:postcode":"33980",
    "sg:province":"FL",
    "sg:tags":[
        "tree"
    ],
    "wof:name":"Angel Care Tree Svc",
    "wof:placetype":"venue"
},
  "geometry": {"coordinates":[-82.069236,26.968027],"type":"Point"}
}