{
  "type": "Feature",
  "properties": {
    "iso:country":"US",
    "sg:address":"918 Ocean Dr",
    "sg:city":"Miami Beach",
    "sg:classifiers":[
        {
            "category":"Bars & Pubs",
            "subcategory":"Nightclub",
            "type":"Food & Drink"
        }
    ],
    "sg:phone":"+1 305 534 1328",
    "sg:postcode":"33139",
    "sg:province":"FL",
    "sg:tags":[
        "nightlife"
    ],
    "wof:name":"Fat Tuesday",
    "wof:placetype":"venue"
},
  "geometry": {"coordinates":[-80.130898,25.7794],"type":"Point"}
}