{
  "type": "Feature",
  "properties": {
    "addr:full":"13300 SW 108th Ct Miami FL 33176",
    "addr:housenumber":"13300",
    "addr:postcode":"33176",
    "addr:street":"Sw 108Th Ct",
    "iso:country":"US",
    "sg:address":"13300 SW 108th Ct",
    "sg:city":"Miami",
    "sg:classifiers":[
        {
            "category":"Professional",
            "type":"Services"
        }
    ],
    "sg:phone":"+1 305 259 0535",
    "sg:postcode":"33176",
    "sg:province":"FL",
    "wof:name":"Den Aire Inc",
    "wof:placetype":"venue"
},
  "geometry": {"coordinates":[-80.369457,25.64406],"type":"Point"}
}