{
  "type": "Feature",
  "properties": {
    "addr:full":"6100 US Hwy 1 N St Augustine FL 32095",
    "addr:housenumber":"6100",
    "addr:postcode":"32095",
    "addr:street":"Us Hwy 1 N St",
    "iso:country":"US",
    "sg:address":"6100 US Hwy 1 N",
    "sg:city":"St Augustine",
    "sg:classifiers":[
        {
            "category":"Government",
            "subcategory":"Office",
            "type":"Public Place"
        }
    ],
    "sg:phone":"+1 904 823 8500",
    "sg:postcode":"32095",
    "sg:province":"FL",
    "sg:tags":[
        "federal",
        "taxation"
    ],
    "wof:name":"US Customs Svc",
    "wof:placetype":"venue"
},
  "geometry": {"coordinates":[-81.364744,29.982158],"type":"Point"}
}