{
  "type": "Feature",
  "properties": {
    "addr:full":"27338 Elwood Dr Bonita Springs FL 34135",
    "addr:housenumber":"27338",
    "addr:postcode":"34135",
    "addr:street":"Elwood Dr",
    "iso:country":"US",
    "sg:address":"27338 Elwood Dr",
    "sg:city":"Bonita Springs",
    "sg:classifiers":[
        {
            "category":"Home & Garden",
            "subcategory":"Furniture",
            "type":"Retail Goods"
        }
    ],
    "sg:phone":"+1 239 495 1798",
    "sg:postcode":"34135",
    "sg:province":"FL",
    "sg:tags":[
        "cabinet"
    ],
    "wof:name":"Imus Enterprises Inc",
    "wof:placetype":"venue"
},
  "geometry": {"coordinates":[-81.772361,26.340363],"type":"Point"}
}