{
  "type": "Feature",
  "properties": {
    "iso:country":"US",
    "sg:address":"3426 Ehrlich Rd",
    "sg:city":"Tampa",
    "sg:classifiers":[
        {
            "category":"Building & Trades",
            "subcategory":"Electrical",
            "type":"Services"
        }
    ],
    "sg:phone":"+1 813 960 4823",
    "sg:postcode":"33618",
    "sg:province":"FL",
    "sg:tags":[
        "electrical",
        "contractor"
    ],
    "wof:name":"Parra Electrical Contractor",
    "wof:placetype":"venue"
},
  "geometry": {"coordinates":[-82.500137,28.073449],"type":"Point"}
}