{
  "type": "Feature",
  "properties": {
    "iso:country":"US",
    "sg:address":"6640 Congress St",
    "sg:city":"New Port Richey",
    "sg:classifiers":[
        {
            "category":"Organizations",
            "subcategory":"Professional Association",
            "type":"Services"
        }
    ],
    "sg:phone":"+1 727 298 8777",
    "sg:postcode":"34653",
    "sg:province":"FL",
    "sg:tags":[
        "education"
    ],
    "wof:name":"Abqaurp",
    "wof:placetype":"venue"
},
  "geometry": {"coordinates":[-82.707189,28.253794],"type":"Point"}
}