{
  "type": "Feature",
  "properties": {
    "addr:full":"3181 Tampa Rd Oldsmar FL 34677",
    "addr:housenumber":"3181",
    "addr:postcode":"34677",
    "addr:street":"Tampa Rd",
    "iso:country":"US",
    "sg:address":"3181 Tampa Rd",
    "sg:city":"Oldsmar",
    "sg:classifiers":[
        {
            "category":"Bakery",
            "type":"Food & Drink"
        }
    ],
    "sg:menulink":"http://www.allmenus.com/fl/tarpon-springs/103291-panera-bread/menu/",
    "sg:phone":"+1 813 849 6153",
    "sg:postcode":"34677",
    "sg:province":"FL",
    "sg:tags":[
        "american",
        "sandwich",
        "pastry"
    ],
    "wof:name":"Panera Bread",
    "wof:placetype":"venue"
},
  "geometry": {"coordinates":[-82.70193,28.05468],"type":"Point"}
}