{
  "type": "Feature",
  "properties": {
    "iso:country":"US",
    "sg:address":"1211 E Venice Ave",
    "sg:city":"Venice",
    "sg:classifiers":[
        {
            "category":"Personal",
            "subcategory":"Beauty Salon",
            "type":"Services"
        }
    ],
    "sg:phone":"+1 941 485 1887",
    "sg:postcode":"34285",
    "sg:province":"FL",
    "sg:tags":[
        "shop"
    ],
    "wof:name":"Ave Hair Design Co",
    "wof:placetype":"venue"
},
  "geometry": {"coordinates":[-82.421609,27.099634],"type":"Point"}
}