{
  "type": "Feature",
  "properties": {
    "iso:country":"US",
    "sg:address":"400 SE Flamingo Ave",
    "sg:city":"Stuart",
    "sg:classifiers":[
        {
            "category":"Professional",
            "subcategory":"Accounting & Tax Preparation",
            "type":"Services"
        }
    ],
    "sg:phone":"+1 772 283 8500",
    "sg:postcode":"34996",
    "sg:province":"FL",
    "sg:tags":[
        "accountant"
    ],
    "wof:name":"Robert J Flowers CPA PA",
    "wof:placetype":"venue"
},
  "geometry": {"coordinates":[-80.226349,27.197416],"type":"Point"}
}