{
  "type": "Feature",
  "properties": {
    "iso:country":"US",
    "sg:address":"15362 76th Rd N",
    "sg:city":"Loxahatchee",
    "sg:classifiers":[
        {
            "category":"Personal",
            "subcategory":"Beauty Salon",
            "type":"Services"
        }
    ],
    "sg:phone":"+1 561 784 1471",
    "sg:postcode":"33470",
    "sg:province":"FL",
    "wof:name":"Car Illusions",
    "wof:placetype":"venue"
},
  "geometry": {"coordinates":[-80.28319500000001,26.790215],"type":"Point"}
}