{
  "type": "Feature",
  "properties": {
    "iso:country":"US",
    "sg:address":"10920 Baymeadows Rd",
    "sg:city":"Jacksonville",
    "sg:classifiers":[
        {
            "category":"Manufacturing",
            "subcategory":"Printing",
            "type":"Manufacturing & Wholesale Goods"
        }
    ],
    "sg:phone":"+1 904 538 0880",
    "sg:postcode":"32256",
    "sg:province":"FL",
    "sg:tags":[
        "printer"
    ],
    "wof:name":"Pak Mail Ctr",
    "wof:placetype":"venue"
},
  "geometry": {"coordinates":[-81.51550899999999,30.215815],"type":"Point"}
}