{
  "type": "Feature",
  "properties": {
    "iso:country":"US",
    "sg:address":"1891 Beach Blvd",
    "sg:city":"Jacksonville Beach",
    "sg:classifiers":[
        {
            "category":"Health Services",
            "subcategory":"Doctor",
            "type":"Services"
        }
    ],
    "sg:phone":"+1 904 249 5801",
    "sg:postcode":"32250",
    "sg:province":"FL",
    "sg:tags":[
        "medical"
    ],
    "wof:name":"C W Randolph Jr MD",
    "wof:placetype":"venue"
},
  "geometry": {"coordinates":[-81.40997900000001,30.288247],"type":"Point"}
}