{
  "type": "Feature",
  "properties": {
    "iso:country":"US",
    "sg:address":"3945 Saint Johns Ave",
    "sg:city":"Jacksonville",
    "sg:classifiers":[
        {
            "category":"Banks & Credit Unions",
            "subcategory":"Investment Brokerage",
            "type":"Services"
        }
    ],
    "sg:phone":"+1 904 384 2440",
    "sg:postcode":"32205",
    "sg:province":"FL",
    "sg:tags":[
        "consultant",
        "planning",
        "financial"
    ],
    "wof:name":"Senior Security Financial Inc",
    "wof:placetype":"venue"
},
  "geometry": {"coordinates":[-81.69896,30.300602],"type":"Point"}
}