{
  "type": "Feature",
  "properties": {
    "iso:country":"US",
    "sg:address":"1975 SE 150th St",
    "sg:city":"Summerfield",
    "sg:classifiers":[
        {
            "category":"Building & Trades",
            "subcategory":"Construction",
            "type":"Services"
        }
    ],
    "sg:phone":"+1 352 245 0968",
    "sg:postcode":"34491",
    "sg:province":"FL",
    "sg:tags":[
        "contractor"
    ],
    "wof:name":"Mike Parkin Plastering Inc",
    "wof:placetype":"venue"
},
  "geometry": {"coordinates":[-82.111808,29.003882],"type":"Point"}
}