{
  "type": "Feature",
  "properties": {
    "addr:full":"95 Merrick Way Coral Gables FL 33134",
    "addr:housenumber":"95",
    "addr:postcode":"33134",
    "addr:street":"Merrick Way",
    "iso:country":"US",
    "sg:address":"95 Merrick Way",
    "sg:city":"Coral Gables",
    "sg:classifiers":[
        {
            "category":"Real Estate",
            "subcategory":"Real Estate Agent",
            "type":"Services"
        }
    ],
    "sg:phone":"+1 305 448 4410",
    "sg:postcode":"33134",
    "sg:province":"FL",
    "wof:name":"Hopkins Pilar & Assoc Realty",
    "wof:placetype":"venue"
},
  "geometry": {"coordinates":[-80.255725,25.75083],"type":"Point"}
}