{
  "type": "Feature",
  "properties": {
    "iso:country":"US",
    "sg:address":"3100 SW 62nd Ave",
    "sg:city":"Fort Lauderdale",
    "sg:classifiers":[
        {
            "category":"Building & Trades",
            "subcategory":"Construction",
            "type":"Services"
        }
    ],
    "sg:phone":"+1 561 745 5473",
    "sg:postcode":"33314",
    "sg:province":"FL",
    "wof:name":"Cabot Construction Co",
    "wof:placetype":"venue"
},
  "geometry": {"coordinates":[-80.22996999999999,26.081612],"type":"Point"}
}