{
  "type": "Feature",
  "properties": {
    "iso:country":"US",
    "sg:address":"702 E McNab Rd",
    "sg:city":"Pompano Beach",
    "sg:classifiers":[
        {
            "category":"Retail",
            "subcategory":"Auto Repair",
            "type":"Services"
        }
    ],
    "sg:phone":"+1 954 781 0881",
    "sg:postcode":"33060",
    "sg:province":"FL",
    "sg:tags":[
        "repairing",
        "automobile"
    ],
    "wof:name":"Buz Hahn's Garage",
    "wof:placetype":"venue"
},
  "geometry": {"coordinates":[-80.110163,26.211448],"type":"Point"}
}