{
  "type": "Feature",
  "properties": {
    "iso:country":"US",
    "sg:address":"2016 Lee Dr",
    "sg:city":"Valrico",
    "sg:classifiers":[
        {
            "category":"Communications",
            "type":"Services"
        }
    ],
    "sg:phone":"+1 813 655 3237",
    "sg:postcode":"33594",
    "sg:province":"FL",
    "wof:name":"Intermedia Communication",
    "wof:placetype":"venue"
},
  "geometry": {"coordinates":[-82.254828,27.922008],"type":"Point"}
}