{
  "type": "Feature",
  "properties": {
    "addr:full":"3794 Blanding Blvd Jacksonville FL 32210",
    "addr:housenumber":"3794",
    "addr:postcode":"32210",
    "addr:street":"Blanding Blvd",
    "iso:country":"US",
    "sg:address":"3794 Blanding Blvd",
    "sg:city":"Jacksonville",
    "sg:classifiers":[
        {
            "category":"Personal",
            "type":"Services"
        }
    ],
    "sg:phone":"+1 904 317 0608",
    "sg:postcode":"32210",
    "sg:province":"FL",
    "sg:tags":[
        "fitness",
        "physical",
        "facility"
    ],
    "wof:name":"Golds Gym Aerobics & Fitness",
    "wof:placetype":"venue"
},
  "geometry": {"coordinates":[-81.737404,30.267708],"type":"Point"}
}