{
  "type": "Feature",
  "properties": {
    "iso:country":"US",
    "sg:address":"2310 NE 40th Ave",
    "sg:city":"Ocala",
    "sg:classifiers":[
        {
            "category":"Professional",
            "subcategory":"Employment Agencies",
            "type":"Services"
        }
    ],
    "sg:phone":"+1 352 236 6632",
    "sg:postcode":"34470",
    "sg:province":"FL",
    "sg:tags":[
        "employer"
    ],
    "wof:name":"Good Samaritan Hospital",
    "wof:placetype":"venue"
},
  "geometry": {"coordinates":[-82.081093,29.210641],"type":"Point"}
}