{
  "type": "Feature",
  "properties": {
    "iso:country":"US",
    "sg:address":"848 S Broad St",
    "sg:city":"Brooksville",
    "sg:classifiers":[
        {
            "category":"Autos & Motor Vehicles",
            "subcategory":"Auto Supplies",
            "type":"Retail Goods"
        }
    ],
    "sg:phone":"+1 352 799 7474",
    "sg:postcode":"34601",
    "sg:province":"FL",
    "sg:tags":[
        "automobile",
        "part",
        "batteries-storage"
    ],
    "sg:website":"http://www.advanceautoparts.com",
    "wof:name":"Advance Auto Parts",
    "wof:placetype":"venue"
},
  "geometry": {"coordinates":[-82.399824,28.547223],"type":"Point"}
}