{
  "type": "Feature",
  "properties": {
    "iso:country":"US",
    "sg:address":"401 NW 29th St",
    "sg:city":"Miami",
    "sg:classifiers":[
        {
            "category":"Education",
            "subcategory":"School",
            "type":"Public Place"
        }
    ],
    "sg:phone":"+1 305 573 8181",
    "sg:postcode":"33127",
    "sg:province":"FL",
    "sg:tags":[
        "high",
        "middle",
        "elementary"
    ],
    "sg:website":"www.dade.k12.fl.us/hartner",
    "wof:name":"Miami-Dade County Public Schools",
    "wof:placetype":"venue"
},
  "geometry": {"coordinates":[-80.203245,25.803867],"type":"Point"}
}