{
  "type": "Feature",
  "properties": {
    "addr:full":"8760 Azalea Ct Fort Lauderdale FL 33321",
    "addr:housenumber":"8760",
    "addr:postcode":"33321",
    "addr:street":"Azalea Ct",
    "iso:country":"US",
    "sg:address":"8760 Azalea Ct",
    "sg:city":"Fort Lauderdale",
    "sg:classifiers":[
        {
            "category":"Professional",
            "type":"Services"
        }
    ],
    "sg:phone":"+1 954 724 1771",
    "sg:postcode":"33321",
    "sg:province":"FL",
    "wof:name":"Locarb Factory Inc",
    "wof:placetype":"venue"
},
  "geometry": {"coordinates":[-80.27207799999999,26.22186],"type":"Point"}
}