{
  "type": "Feature",
  "properties": {
    "addr:full":"144 Brandon Town Center Dr Brandon FL 33511",
    "addr:housenumber":"144",
    "addr:postcode":"33511",
    "addr:street":"Brandon Town Center Dr",
    "iso:country":"US",
    "sg:address":"144 Brandon Town Center Dr",
    "sg:city":"Brandon",
    "sg:classifiers":[
        {
            "category":"Restaurant",
            "type":"Food & Drink"
        }
    ],
    "sg:phone":"+1 813 681 7716",
    "sg:postcode":"33511",
    "sg:province":"FL",
    "wof:name":"Tia's Tex & Mex",
    "wof:placetype":"venue"
},
  "geometry": {"coordinates":[-82.32534200000001,27.936736],"type":"Point"}
}