{
  "type": "Feature",
  "properties": {
    "iso:country":"US",
    "sg:address":"4600 Touchton Rd E # 1150",
    "sg:city":"Jacksonville",
    "sg:classifiers":[
        {
            "category":"Professional",
            "subcategory":"Employment Agencies",
            "type":"Services"
        }
    ],
    "sg:phone":"+1 904 565 2643",
    "sg:postcode":"32246",
    "sg:province":"FL",
    "sg:tags":[
        "opportunity"
    ],
    "wof:name":"Global Personnel Associates",
    "wof:placetype":"venue"
},
  "geometry": {"coordinates":[-81.549221,30.263075],"type":"Point"}
}