{
  "type": "Feature",
  "properties": {
    "iso:country":"US",
    "sg:address":"5622 Marine Pkwy",
    "sg:city":"New Port Richey",
    "sg:classifiers":[
        {
            "category":"Health Services",
            "subcategory":"Doctor",
            "type":"Services"
        }
    ],
    "sg:phone":"+1 727 846 7031",
    "sg:postcode":"34652",
    "sg:province":"FL",
    "sg:tags":[
        "osteopathic"
    ],
    "wof:name":"Gastroenterology Assoc W Flor",
    "wof:placetype":"venue"
},
  "geometry": {"coordinates":[-82.72181999999999,28.234031],"type":"Point"}
}