{
  "type": "Feature",
  "properties": {
    "iso:country":"US",
    "sg:address":"6971 Bus Park Blvd N",
    "sg:city":"Jacksonville",
    "sg:classifiers":[
        {
            "category":"Real Estate",
            "subcategory":"Real Estate Agent",
            "type":"Services"
        }
    ],
    "sg:phone":"+1 904 268 1100",
    "sg:postcode":"32256",
    "sg:province":"FL",
    "wof:name":"Home Realty of Jacksonville",
    "wof:placetype":"venue"
},
  "geometry": {"coordinates":[-81.52553399999999,30.166575],"type":"Point"}
}