{
  "type": "Feature",
  "properties": {
    "iso:country":"US",
    "sg:address":"5505 SW 69 Ter",
    "sg:city":"Gainesville",
    "sg:classifiers":[
        {
            "category":"Building & Trades",
            "subcategory":"Construction",
            "type":"Services"
        }
    ],
    "sg:phone":"+1 352 373 7388",
    "sg:postcode":"32608",
    "sg:province":"FL",
    "sg:tags":[
        "contractor"
    ],
    "wof:name":"Dans Drywall",
    "wof:placetype":"venue"
},
  "geometry": {"coordinates":[-82.41619300000001,29.602542],"type":"Point"}
}