{
  "type": "Feature",
  "properties": {
    "iso:country":"US",
    "sg:address":"731 Wrights Creek Rd",
    "sg:city":"Caryville",
    "sg:classifiers":[
        {
            "category":"Place Of Worship",
            "subcategory":"Church",
            "type":"Public Place"
        },
        {
            "category":"Place Of Worship",
            "type":"Public Place"
        }
    ],
    "sg:phone":"+1 850 548 5946",
    "sg:postcode":"32427",
    "sg:province":"FL",
    "sg:tags":[
        "churches-evangelical",
        "churches-covenant",
        "covenant"
    ],
    "wof:name":"Caryville Evangelistic Center",
    "wof:placetype":"venue"
},
  "geometry": {"coordinates":[-85.804261,30.781273],"type":"Point"}
}