{
  "type": "Feature",
  "properties": {
    "addr:full":"258 Short Ave Longwood FL 32750",
    "addr:housenumber":"258",
    "addr:postcode":"32750",
    "addr:street":"Short Ave",
    "iso:country":"US",
    "sg:address":"258 Short Ave",
    "sg:city":"Longwood",
    "sg:classifiers":[
        {
            "category":"Wholesale",
            "subcategory":"Hardware",
            "type":"Manufacturing & Wholesale Goods"
        }
    ],
    "sg:phone":"+1 407 830 8988",
    "sg:postcode":"32750",
    "sg:province":"FL",
    "sg:tags":[
        "equipment",
        "rep",
        "for",
        "mfg"
    ],
    "wof:name":"Hendrix Sales Company",
    "wof:placetype":"venue"
},
  "geometry": {"coordinates":[-81.34943199999999,28.697046],"type":"Point"}
}