{
  "type": "Feature",
  "properties": {
    "addr:full":"338 Shore Dr Ellenton FL 34222",
    "addr:housenumber":"338",
    "addr:postcode":"34222",
    "addr:street":"Shore Dr",
    "iso:country":"US",
    "sg:address":"338 Shore Dr",
    "sg:city":"Ellenton",
    "sg:classifiers":[
        {
            "category":"Building & Trades",
            "subcategory":"Construction",
            "type":"Services"
        }
    ],
    "sg:phone":"+1 941 721 7338",
    "sg:postcode":"34222",
    "sg:province":"FL",
    "sg:tags":[
        "house"
    ],
    "wof:name":"FL Home Builders Inc",
    "wof:placetype":"venue"
},
  "geometry": {"coordinates":[-82.532264,27.515568],"type":"Point"}
}