{
  "type": "Feature",
  "properties": {
    "iso:country":"US",
    "sg:address":"1930 N Mission Rd",
    "sg:city":"Tallahassee",
    "sg:classifiers":[
        {
            "category":"Retail",
            "subcategory":"Auto Repair",
            "type":"Services"
        }
    ],
    "sg:phone":"+1 850 385 2044",
    "sg:postcode":"32303",
    "sg:province":"FL",
    "sg:tags":[
        "automotive"
    ],
    "wof:name":"Vauses 4x4 Inc",
    "wof:placetype":"venue"
},
  "geometry": {"coordinates":[-84.34452899999999,30.47447],"type":"Point"}
}