{
  "type": "Feature",
  "properties": {
    "iso:country":"US",
    "sg:address":"201 N Franklin St # 3800",
    "sg:city":"Tampa",
    "sg:classifiers":[
        {
            "category":"Bars & Pubs",
            "type":"Food & Drink"
        },
        {
            "category":"Professional",
            "subcategory":"Employment Agencies",
            "type":"Services"
        },
        {
            "category":"Organizations",
            "subcategory":"Community Association",
            "type":"Services"
        }
    ],
    "sg:phone":"+1 813 223 3737",
    "sg:postcode":"33602",
    "sg:province":"FL",
    "sg:tags":[
        "club",
        "workers'",
        "placement",
        "volunteer"
    ],
    "wof:name":"University Club Of Tampa",
    "wof:placetype":"venue"
},
  "geometry": {"coordinates":[-82.45760300000001,27.94696],"type":"Point"}
}