{
  "type": "Feature",
  "properties": {
    "iso:country":"US",
    "sg:address":"746 W Duval St",
    "sg:city":"Lake City",
    "sg:classifiers":[
        {
            "category":"Insurance",
            "subcategory":"Insurance Agent",
            "type":"Services"
        }
    ],
    "sg:phone":"+1 386 755 2630",
    "sg:postcode":"32055",
    "sg:province":"FL",
    "wof:name":"Brooke Insurance & Financial",
    "wof:placetype":"venue"
},
  "geometry": {"coordinates":[-82.64368399999999,30.18924],"type":"Point"}
}