{
  "type": "Feature",
  "properties": {
    "iso:country":"US",
    "sg:address":"16313 Ponce de Leon Blvd",
    "sg:city":"Brooksville",
    "sg:classifiers":[
        {
            "category":"Mining & Drilling",
            "type":"Manufacturing & Wholesale Goods"
        }
    ],
    "sg:phone":"+1 352 544 6280",
    "sg:postcode":"34614",
    "sg:province":"FL",
    "sg:tags":[
        "stone"
    ],
    "sg:website":"www.vulcanmaterials.com",
    "wof:name":"Vulcan Construction Material",
    "wof:placetype":"venue"
},
  "geometry": {"coordinates":[-82.47597399999999,28.66994],"type":"Point"}
}