{
  "type": "Feature",
  "properties": {
    "addr:full":"3520 NW 43 St Gainesville FL 32606",
    "addr:housenumber":"3520",
    "addr:postcode":"32606",
    "addr:street":"Nw 43 St",
    "iso:country":"US",
    "sg:address":"3520 NW 43 St",
    "sg:city":"Gainesville",
    "sg:classifiers":[
        {
            "category":"Professional",
            "subcategory":"Lawyer & Legal Services",
            "type":"Services"
        }
    ],
    "sg:phone":"+1 352 373 9780",
    "sg:postcode":"32606",
    "sg:province":"FL",
    "wof:name":"Daniel T Oconnell",
    "wof:placetype":"venue"
},
  "geometry": {"coordinates":[-82.389011,29.686821],"type":"Point"}
}