{
  "type": "Feature",
  "properties": {
    "addr:full":"1100 Banyan Blvd West Palm Beach FL 33401",
    "addr:housenumber":"1100",
    "addr:postcode":"33401",
    "addr:street":"Banyan Blvd",
    "iso:country":"US",
    "sg:address":"1100 Banyan Blvd",
    "sg:city":"West Palm Beach",
    "sg:classifiers":[
        {
            "category":"Communications",
            "subcategory":"Television Station",
            "type":"Services"
        }
    ],
    "sg:phone":"+1 561 655 5455",
    "sg:postcode":"33401",
    "sg:province":"FL",
    "sg:tags":[
        "broadcasting",
        "co"
    ],
    "sg:website":"www.wptv.com",
    "wof:name":"WPTV",
    "wof:placetype":"venue"
},
  "geometry": {"coordinates":[-80.054191,26.507998],"type":"Point"}
}