{
  "type": "Feature",
  "properties": {
    "iso:country":"US",
    "sg:address":"817 Southview Dr",
    "sg:city":"Jupiter",
    "sg:classifiers":[
        {
            "category":"Building & Trades",
            "subcategory":"Construction",
            "type":"Services"
        }
    ],
    "sg:phone":"+1 561 743 2606",
    "sg:postcode":"33458",
    "sg:province":"FL",
    "sg:tags":[
        "hanging",
        "contractor"
    ],
    "wof:name":"Allports Painting & Dctg Inc",
    "wof:placetype":"venue"
},
  "geometry": {"coordinates":[-80.109627,26.935384],"type":"Point"}
}