{
  "type": "Feature",
  "properties": {
    "iso:country":"US",
    "sg:address":"5404 Co Rd 218",
    "sg:city":"Middleburg",
    "sg:classifiers":[
        {
            "category":"Home & Garden",
            "subcategory":"Hardware",
            "type":"Retail Goods"
        }
    ],
    "sg:phone":"+1 904 282 4444",
    "sg:postcode":"32068",
    "sg:province":"FL",
    "wof:name":"C & L Ace Hardware",
    "wof:placetype":"venue"
},
  "geometry": {"coordinates":[-81.95163700000001,30.09668],"type":"Point"}
}