{
  "type": "Feature",
  "properties": {
    "iso:country":"US",
    "sg:address":"219 W Crawford St",
    "sg:city":"Quincy",
    "sg:classifiers":[
        {
            "category":"Shopping",
            "subcategory":"Clothing, Apparel, & Fashions",
            "type":"Retail Goods"
        }
    ],
    "sg:phone":"+1 850 627 2335",
    "sg:postcode":"32351",
    "sg:province":"FL",
    "sg:tags":[
        "shop",
        "bridal"
    ],
    "wof:name":"Powell's Bridal & Rental Svc",
    "wof:placetype":"venue"
},
  "geometry": {"coordinates":[-84.57924,30.587139],"type":"Point"}
}