{
  "type": "Feature",
  "properties": {
    "iso:country":"US",
    "sg:address":"27 de Luna Dr",
    "sg:city":"Gulf Breeze",
    "sg:classifiers":[
        {
            "category":"Travel",
            "subcategory":"Hotels & Motels",
            "type":"Entertainment"
        }
    ],
    "sg:phone":"+1 850 932 9723",
    "sg:postcode":"32506",
    "sg:province":"FL",
    "sg:tags":[
        "resort"
    ],
    "wof:name":"Sandcastles Properties",
    "wof:placetype":"venue"
},
  "geometry": {"coordinates":[-87.28780999999999,30.419048],"type":"Point"}
}