{
  "type": "Feature",
  "properties": {
    "iso:country":"US",
    "sg:address":"737 8th Ave W",
    "sg:city":"Palmetto",
    "sg:classifiers":[
        {
            "category":"Banks & Credit Unions",
            "subcategory":"Bank",
            "type":"Services"
        }
    ],
    "sg:phone":"+1 941 729 0093",
    "sg:postcode":"34221",
    "sg:province":"FL",
    "sg:tags":[
        "cashing",
        "check"
    ],
    "wof:name":"Amscot Corp",
    "wof:placetype":"venue"
},
  "geometry": {"coordinates":[-82.57302300000001,27.518586],"type":"Point"}
}