{
  "type": "Feature",
  "properties": {
    "iso:country":"US",
    "sg:address":"1710 SE 16th Ave",
    "sg:city":"Ocala",
    "sg:classifiers":[
        {
            "category":"Health Services",
            "subcategory":"Podiatrist",
            "type":"Services"
        }
    ],
    "sg:phone":"+1 352 867 1155",
    "sg:postcode":"34471",
    "sg:province":"FL",
    "sg:tags":[
        "physician",
        "surgeons"
    ],
    "wof:name":"Ocala Podiatry Center",
    "wof:placetype":"venue"
},
  "geometry": {"coordinates":[-82.116547,29.170779],"type":"Point"}
}