{
  "type": "Feature",
  "properties": {
    "addr:full":"1907 Industrial Park Dr Plant City FL 33566",
    "addr:housenumber":"1907",
    "addr:postcode":"33566",
    "addr:street":"Industrial Park Dr",
    "iso:country":"US",
    "sg:address":"1907 Industrial Park Dr",
    "sg:city":"Plant City",
    "sg:classifiers":[
        {
            "category":"Building & Trades",
            "subcategory":"Pest Control",
            "type":"Services"
        }
    ],
    "sg:phone":"+1 813 754 4170",
    "sg:postcode":"33566",
    "sg:province":"FL",
    "sg:website":"www.terminix.com",
    "wof:name":"Terminix International Co",
    "wof:placetype":"venue"
},
  "geometry": {"coordinates":[-82.15963499999999,27.99347],"type":"Point"}
}