{
  "type": "Feature",
  "properties": {
    "iso:country":"US",
    "sg:address":"7735 W 33rd Ave",
    "sg:city":"Hialeah",
    "sg:classifiers":[
        {
            "category":"Coffee & Tea",
            "type":"Food & Drink"
        }
    ],
    "sg:phone":"+1 305 822 1472",
    "sg:postcode":"33018",
    "sg:province":"FL",
    "sg:website":"www.starbucks.com",
    "wof:name":"Starbucks",
    "wof:placetype":"venue"
},
  "geometry": {"coordinates":[-80.350599,25.892574],"type":"Point"}
}