{
  "type": "Feature",
  "properties": {
    "addr:full":"2121 E Main St Lakeland FL 33801",
    "addr:housenumber":"2121",
    "addr:postcode":"33801",
    "addr:street":"E Main St",
    "iso:country":"US",
    "sg:address":"2121 E Main St",
    "sg:city":"Lakeland",
    "sg:classifiers":[
        {
            "category":"Retail",
            "subcategory":"Auto Repair",
            "type":"Services"
        }
    ],
    "sg:phone":"+1 863 666 2002",
    "sg:postcode":"33801",
    "sg:province":"FL",
    "sg:tags":[
        "transmission"
    ],
    "wof:name":"Recondition Transmission",
    "wof:placetype":"venue"
},
  "geometry": {"coordinates":[-81.91671599999999,28.045957],"type":"Point"}
}