{
  "type": "Feature",
  "properties": {
    "iso:country":"US",
    "sg:address":"7399 N Kendall Dr",
    "sg:city":"Miami",
    "sg:classifiers":[
        {
            "category":"Restaurant",
            "type":"Food & Drink"
        }
    ],
    "sg:menulink":"http://www.allmenus.com/fl/kendall-perrine/131117-the-cheesecake-factory/menu/",
    "sg:phone":"+1 305 665 5400",
    "sg:postcode":"33156",
    "sg:province":"FL",
    "sg:tags":[
        "new",
        "american"
    ],
    "wof:name":"The Cheesecake Factory",
    "wof:placetype":"venue"
},
  "geometry": {"coordinates":[-80.312764,25.688766],"type":"Point"}
}