{
  "type": "Feature",
  "properties": {
    "iso:country":"US",
    "sg:address":"1550 NW 17th Ave",
    "sg:city":"Miami",
    "sg:classifiers":[
        {
            "category":"Retail",
            "subcategory":"Auto Repair",
            "type":"Services"
        }
    ],
    "sg:phone":"+1 305 325 0116",
    "sg:postcode":"33125",
    "sg:province":"FL",
    "sg:website":"www.mobil.com",
    "wof:name":"J Mobil Inc",
    "wof:placetype":"venue"
},
  "geometry": {"coordinates":[-80.223,25.789499],"type":"Point"}
}