{
  "type": "Feature",
  "properties": {
    "iso:country":"US",
    "sg:address":"6740 Crosswinds Dr N",
    "sg:city":"St Petersburg",
    "sg:classifiers":[
        {
            "category":"Banks & Credit Unions",
            "subcategory":"Bank",
            "type":"Services"
        }
    ],
    "sg:phone":"+1 727 344 0404",
    "sg:postcode":"33710",
    "sg:province":"FL",
    "sg:tags":[
        "loan",
        "real estate"
    ],
    "wof:name":"Family Home Funding",
    "wof:placetype":"venue"
},
  "geometry": {"coordinates":[-82.731919,27.790101],"type":"Point"}
}