{
  "type": "Feature",
  "properties": {
    "iso:country":"US",
    "sg:address":"1098 SW Eckard Ave",
    "sg:city":"Port St Lucie",
    "sg:classifiers":[
        {
            "category":"Freight",
            "type":"Transportation"
        }
    ],
    "sg:phone":"+1 561 737 5685",
    "sg:postcode":"34953",
    "sg:province":"FL",
    "sg:tags":[
        "operator",
        "local",
        "trucking"
    ],
    "wof:name":"D & P Trucking Inc",
    "wof:placetype":"venue"
},
  "geometry": {"coordinates":[-80.38,27.21228],"type":"Point"}
}