{
  "type": "Feature",
  "properties": {
    "iso:country":"US",
    "sg:address":"108 S Old Dixie Hwy",
    "sg:city":"Lady Lake",
    "sg:classifiers":[
        {
            "category":"Building & Trades",
            "subcategory":"Construction",
            "type":"Services"
        }
    ],
    "sg:phone":"+1 352 753 9009",
    "sg:postcode":"32159",
    "sg:province":"FL",
    "sg:tags":[
        "general",
        "contractor"
    ],
    "sg:website":"www.steinmetzgrp.com",
    "wof:name":"Steinmetz Construction & Dev",
    "wof:placetype":"venue"
},
  "geometry": {"coordinates":[-81.923399,28.917288],"type":"Point"}
}