{
  "type": "Feature",
  "properties": {
    "iso:country":"US",
    "sg:address":"45 Abaco St",
    "sg:city":"Lehigh Acres",
    "sg:classifiers":[
        {
            "category":"Building & Trades",
            "subcategory":"Construction",
            "type":"Services"
        }
    ],
    "sg:phone":"+1 239 369 6999",
    "sg:postcode":"33936",
    "sg:province":"FL",
    "sg:tags":[
        "carpentry",
        "contractor"
    ],
    "wof:name":"Max Miller Enterprises",
    "wof:placetype":"venue"
},
  "geometry": {"coordinates":[-81.64847399999999,26.594547],"type":"Point"}
}