{
  "type": "Feature",
  "properties": {
    "addr:full":"312 E Broadway Ave Kissimmee FL 34741",
    "addr:housenumber":"312",
    "addr:postcode":"34741",
    "addr:street":"E Broadway Ave",
    "iso:country":"US",
    "sg:address":"312 E Broadway Ave",
    "sg:city":"Kissimmee",
    "sg:classifiers":[
        {
            "category":"Retail",
            "subcategory":"Auto Repair",
            "type":"Services"
        }
    ],
    "sg:phone":"+1 407 846 7045",
    "sg:postcode":"34741",
    "sg:province":"FL",
    "sg:tags":[
        "automotive",
        "rebuilds",
        "generator",
        "starter"
    ],
    "wof:name":"Msg Power Systems",
    "wof:placetype":"venue"
},
  "geometry": {"coordinates":[-81.404769,28.294681],"type":"Point"}
}