{
  "type": "Feature",
  "properties": {
    "iso:country":"US",
    "sg:address":"3 Foxrun Trl",
    "sg:city":"Ormond Beach",
    "sg:classifiers":[
        {
            "category":"Professional",
            "subcategory":"Management & Consulting",
            "type":"Services"
        }
    ],
    "sg:phone":"+1 386 615 6835",
    "sg:postcode":"32174",
    "sg:province":"FL",
    "sg:tags":[
        "consultant"
    ],
    "wof:name":"Bailey Consulting",
    "wof:placetype":"venue"
},
  "geometry": {"coordinates":[-81.086495,29.283475],"type":"Point"}
}