{
  "type": "Feature",
  "properties": {
    "addr:full":"1254 Ocala Rd Tallahassee FL 32304",
    "addr:housenumber":"1254",
    "addr:postcode":"32304",
    "addr:street":"Ocala Rd",
    "iso:country":"US",
    "sg:address":"1254 Ocala Rd",
    "sg:city":"Tallahassee",
    "sg:classifiers":[
        {
            "category":"Professional",
            "subcategory":"Computer Services",
            "type":"Services"
        }
    ],
    "sg:phone":"+1 850 575 0566",
    "sg:postcode":"32304",
    "sg:province":"FL",
    "sg:tags":[
        "publisher",
        "developer",
        "software"
    ],
    "wof:name":"Seven Hills Solution Specialists",
    "wof:placetype":"venue"
},
  "geometry": {"coordinates":[-84.317795,30.456024],"type":"Point"}
}