{
  "type": "Feature",
  "properties": {
    "iso:country":"US",
    "sg:address":"4440 Hendricks Ave",
    "sg:city":"Jacksonville",
    "sg:classifiers":[
        {
            "category":"Bars & Pubs",
            "type":"Food & Drink"
        }
    ],
    "sg:menulink":"http://www.allmenus.com/fl/jacksonville/106390-jimadores-mexican-bar-and-grill/menu/",
    "sg:phone":"+1 904 739 5828",
    "sg:postcode":"32207",
    "sg:province":"FL",
    "sg:tags":[
        "mexican"
    ],
    "wof:name":"Jimadores Mexican Bar And Grill",
    "wof:placetype":"venue"
},
  "geometry": {"coordinates":[-81.650206,30.274738],"type":"Point"}
}