{
  "type": "Feature",
  "properties": {
    "addr:full":"1642 Overview Dr New Port Richey FL 34655",
    "addr:housenumber":"1642",
    "addr:postcode":"34655",
    "addr:street":"Overview Dr",
    "iso:country":"US",
    "sg:address":"1642 Overview Dr",
    "sg:city":"New Port Richey",
    "sg:classifiers":[
        {
            "category":"Building & Trades",
            "subcategory":"Construction",
            "type":"Services"
        }
    ],
    "sg:phone":"+1 727 919 1494",
    "sg:postcode":"34655",
    "sg:province":"FL",
    "sg:tags":[
        "excavating",
        "contractor"
    ],
    "wof:name":"Swafford Excavating Inc",
    "wof:placetype":"venue"
},
  "geometry": {"coordinates":[-82.708282,28.18403],"type":"Point"}
}