{
  "type": "Feature",
  "properties": {
    "iso:country":"US",
    "sg:address":"632 Lakeside Dr",
    "sg:city":"Seminole",
    "sg:classifiers":[
        {
            "category":"Manufacturing",
            "subcategory":"Building Materials",
            "type":"Manufacturing & Wholesale Goods"
        }
    ],
    "sg:phone":"+1 727 399 9376",
    "sg:postcode":"33772",
    "sg:province":"FL",
    "sg:tags":[
        "mfg"
    ],
    "wof:name":"Exotic Wood Creations By Noah",
    "wof:placetype":"venue"
},
  "geometry": {"coordinates":[-82.784133,27.846721],"type":"Point"}
}