{
  "type": "Feature",
  "properties": {
    "addr:full":"6115 NW Ginger Ln Port Saint Lucie FL 34986",
    "addr:housenumber":"6115",
    "addr:postcode":"34986",
    "addr:street":"Nw Ginger Ln",
    "iso:country":"US",
    "sg:address":"6115 NW Ginger Ln",
    "sg:city":"Port Saint Lucie",
    "sg:classifiers":[
        {
            "category":"Shopping",
            "subcategory":"Gifts & Souvenirs",
            "type":"Retail Goods"
        }
    ],
    "sg:phone":"+1 772 336 5920",
    "sg:postcode":"34986",
    "sg:province":"FL",
    "wof:name":"House of Gift Baskets",
    "wof:placetype":"venue"
},
  "geometry": {"coordinates":[-80.411237,27.338474],"type":"Point"}
}