{
  "type": "Feature",
  "properties": {
    "addr:full":"5433 Airport Pulling Rd N Naples FL 34109",
    "addr:housenumber":"5433",
    "addr:postcode":"34109",
    "addr:street":"Airport Pulling Rd N",
    "iso:country":"US",
    "sg:address":"5433 Airport Pulling Rd N",
    "sg:city":"Naples",
    "sg:classifiers":[
        {
            "category":"Food & Beverages",
            "subcategory":"Groceries & Convenience Stores",
            "type":"Retail Goods"
        }
    ],
    "sg:phone":"+1 239 593 0696",
    "sg:postcode":"34109",
    "sg:province":"FL",
    "wof:name":"Qwik Pak Ship",
    "wof:placetype":"venue"
},
  "geometry": {"coordinates":[-81.768466,26.215004],"type":"Point"}
}