{
  "type": "Feature",
  "properties": {
    "addr:full":"3566 Blanding Blvd Jacksonville FL 32210",
    "addr:housenumber":"3566",
    "addr:postcode":"32210",
    "addr:street":"Blanding Blvd",
    "iso:country":"US",
    "sg:address":"3566 Blanding Blvd",
    "sg:city":"Jacksonville",
    "sg:classifiers":[
        {
            "category":"Cinema",
            "subcategory":"Movie Rental",
            "type":"Entertainment"
        }
    ],
    "sg:phone":"+1 904 908 0522",
    "sg:postcode":"32210",
    "sg:province":"FL",
    "sg:tags":[
        "video",
        "tape"
    ],
    "wof:name":"Blockbuster",
    "wof:placetype":"venue"
},
  "geometry": {"coordinates":[-81.735839,30.270867],"type":"Point"}
}