{
  "type": "Feature",
  "properties": {
    "addr:full":"4106 Gall Blvd Zephyrhills FL 33542",
    "addr:postcode":"4106;33542",
    "addr:street":"Gall Blvd",
    "iso:country":"US",
    "sg:address":"4106 Gall Blvd",
    "sg:city":"Zephyrhills",
    "sg:classifiers":[
        {
            "category":"Retail",
            "subcategory":"Repair Shop",
            "type":"Services"
        }
    ],
    "sg:phone":"+1 813 783 8896",
    "sg:postcode":"33542",
    "sg:province":"FL",
    "sg:tags":[
        "related"
    ],
    "wof:name":"Ackerman Services Enterprises",
    "wof:placetype":"venue"
},
  "geometry": {"coordinates":[-82.17981399999999,28.21732],"type":"Point"}
}