{
  "type": "Feature",
  "properties": {
    "iso:country":"US",
    "sg:address":"464 Cassat Ave",
    "sg:city":"Jacksonville",
    "sg:classifiers":[
        {
            "category":"Manufacturing",
            "subcategory":"Wood Products",
            "type":"Manufacturing & Wholesale Goods"
        }
    ],
    "sg:phone":"+1 904 783 1240",
    "sg:postcode":"32254",
    "sg:province":"FL",
    "wof:name":"Fleming & Sons Inc",
    "wof:placetype":"venue"
},
  "geometry": {"coordinates":[-81.73087599999999,30.320689],"type":"Point"}
}