{
  "type": "Feature",
  "properties": {
    "iso:country":"US",
    "sg:address":"412 Crossway Rd",
    "sg:city":"Tallahassee",
    "sg:classifiers":[
        {
            "category":"Home & Garden",
            "subcategory":"Building Materials",
            "type":"Retail Goods"
        },
        {
            "category":"Building & Trades",
            "subcategory":"Construction",
            "type":"Services"
        }
    ],
    "sg:phone":"+1 850 391 2787",
    "sg:postcode":"32305",
    "sg:province":"FL",
    "sg:tags":[
        "roofing",
        "window",
        "siding",
        "contractor"
    ],
    "sg:website":"http://mckeithenroofing.com",
    "wof:name":"Bob McKeithen & Sons",
    "wof:placetype":"venue"
},
  "geometry": {"coordinates":[-84.28667,30.377861],"type":"Point"}
}