{
  "type": "Feature",
  "properties": {
    "addr:full":"1678 Victoria Way Winter Garden FL 34787",
    "addr:housenumber":"1678",
    "addr:postcode":"34787",
    "addr:street":"Victoria Way",
    "iso:country":"US",
    "sg:address":"1678 Victoria Way",
    "sg:city":"Winter Garden",
    "sg:classifiers":[
        {
            "category":"Wholesale",
            "subcategory":"Groceries",
            "type":"Manufacturing & Wholesale Goods"
        }
    ],
    "sg:phone":"+1 407 656 2839",
    "sg:postcode":"34787",
    "sg:province":"FL",
    "sg:tags":[
        "food",
        "distributor"
    ],
    "wof:name":"Foods For Thought",
    "wof:placetype":"venue"
},
  "geometry": {"coordinates":[-81.564294,28.589689],"type":"Point"}
}