{
  "type": "Feature",
  "properties": {
    "iso:country":"US",
    "sg:address":"6006 E Colonial Dr",
    "sg:city":"Orlando",
    "sg:classifiers":[
        {
            "category":"Shopping",
            "subcategory":"Hobbies, Toys, & Games",
            "type":"Retail Goods"
        }
    ],
    "sg:phone":"+1 407 282 2292",
    "sg:postcode":"32807",
    "sg:province":"FL",
    "sg:tags":[
        "item",
        "novelty",
        "board"
    ],
    "wof:name":"SCI-FI City",
    "wof:placetype":"venue"
},
  "geometry": {"coordinates":[-81.306065,28.560446],"type":"Point"}
}