{
  "type": "Feature",
  "properties": {
    "iso:country":"US",
    "sg:address":"347 E Palmetto Park Rd",
    "sg:city":"Boca Raton",
    "sg:classifiers":[
        {
            "category":"Health Services",
            "subcategory":"Doctor",
            "type":"Services"
        }
    ],
    "sg:phone":"+1 561 417 7552",
    "sg:postcode":"33432",
    "sg:province":"FL",
    "sg:tags":[
        "physician",
        "surgeon"
    ],
    "wof:name":"Yintang",
    "wof:placetype":"venue"
},
  "geometry": {"coordinates":[-80.080456,26.350635],"type":"Point"}
}