{
  "type": "Feature",
  "properties": {
    "iso:country":"US",
    "sg:address":"130 Ridgewood Dr",
    "sg:city":"Longwood",
    "sg:classifiers":[
        {
            "category":"Wholesale",
            "subcategory":"Electrical",
            "type":"Manufacturing & Wholesale Goods"
        }
    ],
    "sg:phone":"+1 407 788 6619",
    "sg:postcode":"32779",
    "sg:province":"FL",
    "sg:tags":[
        "electronic"
    ],
    "wof:name":"Falcon Electronics Inc",
    "wof:placetype":"venue"
},
  "geometry": {"coordinates":[-81.43736,28.703565],"type":"Point"}
}