{
  "type": "Feature",
  "properties": {
    "addr:full":"4611 Lakeside Dr Jacksonville FL 32210",
    "addr:housenumber":"4611",
    "addr:postcode":"32210",
    "addr:street":"Lakeside Dr",
    "iso:country":"US",
    "sg:address":"4611 Lakeside Dr",
    "sg:city":"Jacksonville",
    "sg:classifiers":[
        {
            "category":"Building & Trades",
            "subcategory":"Construction",
            "type":"Services"
        }
    ],
    "sg:phone":"+1 904 387 4814",
    "sg:postcode":"32210",
    "sg:province":"FL",
    "sg:tags":[
        "marine",
        "pile",
        "driving",
        "contractor"
    ],
    "wof:name":"B & W Marine Construction Inc",
    "wof:placetype":"venue"
},
  "geometry": {"coordinates":[-81.718378,30.275837],"type":"Point"}
}