{
  "type": "Feature",
  "properties": {
    "addr:full":"13454 Twin Dolphin Dr Brooksville FL 34609",
    "addr:housenumber":"13454",
    "addr:postcode":"34609",
    "addr:street":"Twin Dolphin Dr",
    "iso:country":"US",
    "sg:address":"13454 Twin Dolphin Dr",
    "sg:city":"Brooksville",
    "sg:classifiers":[
        {
            "category":"Real Estate",
            "subcategory":"Real Estate Agent",
            "type":"Services"
        }
    ],
    "sg:phone":"+1 352 596 7400",
    "sg:postcode":"34609",
    "sg:province":"FL",
    "wof:name":"A-1 Realty Design Inc",
    "wof:placetype":"venue"
},
  "geometry": {"coordinates":[-82.49605,28.533617],"type":"Point"}
}