{
  "type": "Feature",
  "properties": {
    "addr:full":"2370 NW 87th St Miami FL 33147",
    "addr:housenumber":"2370",
    "addr:postcode":"33147",
    "addr:street":"Nw 87Th St",
    "iso:country":"US",
    "sg:address":"2370 NW 87th St",
    "sg:city":"Miami",
    "sg:classifiers":[
        {
            "category":"Place Of Worship",
            "subcategory":"Church",
            "type":"Public Place"
        },
        {
            "category":"Place Of Worship",
            "type":"Public Place"
        },
        {
            "category":"Communications",
            "subcategory":"Radio Station",
            "type":"Services"
        }
    ],
    "sg:phone":"+1 305 836 9081",
    "sg:postcode":"33147",
    "sg:province":"FL",
    "sg:tags":[
        "churches-interdenominational",
        "churches-various",
        "denomination"
    ],
    "wof:name":"Word of Faith",
    "wof:placetype":"venue"
},
  "geometry": {"coordinates":[-80.23733300000001,25.85344],"type":"Point"}
}