{
  "type": "Feature",
  "properties": {
    "addr:full":"5107 Lena Rd Bradenton FL 34211",
    "addr:postcode":"5107;34211",
    "addr:street":"Lena Rd",
    "iso:country":"US",
    "sg:address":"5107 Lena Rd",
    "sg:city":"Bradenton",
    "sg:classifiers":[
        {
            "category":"Building & Trades",
            "subcategory":"Electrical",
            "type":"Services"
        }
    ],
    "sg:phone":"+1 941 896 4934",
    "sg:postcode":"34211",
    "sg:province":"FL",
    "sg:tags":[
        "electrician"
    ],
    "wof:name":"Attaway Services",
    "wof:placetype":"venue"
},
  "geometry": {"coordinates":[-82.455842,27.445285],"type":"Point"}
}