{
  "type": "Feature",
  "properties": {
    "iso:country":"US",
    "sg:address":"1350 NW 14th St",
    "sg:city":"Miami",
    "sg:classifiers":[
        {
            "category":"Health Services",
            "subcategory":"Doctor",
            "type":"Services"
        }
    ],
    "sg:phone":"+1 305 324 2443",
    "sg:postcode":"33125",
    "sg:province":"FL",
    "sg:tags":[
        "physician",
        "family",
        "practice",
        "surgeons",
        "medicine"
    ],
    "wof:name":"Downtown Family Medical Center",
    "wof:placetype":"venue"
},
  "geometry": {"coordinates":[-80.217716,25.787512],"type":"Point"}
}