{
  "type": "Feature",
  "properties": {
    "iso:country":"US",
    "sg:address":"651 S Federal Hwy",
    "sg:city":"Pompano Beach",
    "sg:classifiers":[
        {
            "category":"Autos & Motor Vehicles",
            "subcategory":"Boat Sales",
            "type":"Retail Goods"
        }
    ],
    "sg:phone":"+1 954 783 8080",
    "sg:postcode":"33062",
    "sg:province":"FL",
    "sg:tags":[
        "marine",
        "supply"
    ],
    "wof:name":"Boatarama Inc",
    "wof:placetype":"venue"
},
  "geometry": {"coordinates":[-80.10288300000001,26.225299],"type":"Point"}
}