{
  "type": "Feature",
  "properties": {
    "iso:country":"US",
    "sg:address":"1726 W 68th St",
    "sg:city":"Hialeah",
    "sg:classifiers":[
        {
            "category":"Shopping",
            "subcategory":"Jewelry",
            "type":"Retail Goods"
        }
    ],
    "sg:phone":"+1 305 556 0117",
    "sg:postcode":"33014",
    "sg:province":"FL",
    "sg:tags":[
        "jeweler"
    ],
    "wof:name":"Cash America Pawn",
    "wof:placetype":"venue"
},
  "geometry": {"coordinates":[-80.316316,25.884083],"type":"Point"}
}