{
  "type": "Feature",
  "properties": {
    "iso:country":"US",
    "sg:address":"1505 N Dale Mabry Hwy",
    "sg:city":"Tampa",
    "sg:classifiers":[
        {
            "category":"Retail",
            "subcategory":"Portrait Studio",
            "type":"Services"
        }
    ],
    "sg:phone":"+1 813 877 2048",
    "sg:postcode":"33607",
    "sg:province":"FL",
    "sg:tags":[
        "photographer"
    ],
    "wof:name":"Wal-Mart Portrait Studio",
    "wof:placetype":"venue"
},
  "geometry": {"coordinates":[-82.505488,27.958565],"type":"Point"}
}