{
  "type": "Feature",
  "properties": {
    "addr:full":"10411 SW 184th St Miami FL 33157",
    "addr:housenumber":"10411",
    "addr:postcode":"33157",
    "addr:street":"Sw 184Th St",
    "iso:country":"US",
    "sg:address":"10411 SW 184th St",
    "sg:city":"Miami",
    "sg:classifiers":[
        {
            "category":"Professional",
            "subcategory":"Management & Consulting",
            "type":"Services"
        }
    ],
    "sg:phone":"+1 305 238 6470",
    "sg:postcode":"33157",
    "sg:province":"FL",
    "sg:tags":[
        "retail",
        "direct",
        "sales"
    ],
    "wof:name":"Kevin Snow Seafood",
    "wof:placetype":"venue"
},
  "geometry": {"coordinates":[-80.362297,25.598415],"type":"Point"}
}