{
  "type": "Feature",
  "properties": {
    "iso:country":"US",
    "sg:address":"10740 W Flagler St",
    "sg:city":"Miami",
    "sg:classifiers":[
        {
            "category":"Professional",
            "subcategory":"Lawyer & Legal Services",
            "type":"Services"
        }
    ],
    "sg:phone":"+1 305 228 6900",
    "sg:postcode":"33174",
    "sg:province":"FL",
    "sg:tags":[
        "naturalization",
        "immigration"
    ],
    "wof:name":"Salas Servicio De Immigracion",
    "wof:placetype":"venue"
},
  "geometry": {"coordinates":[-80.36935,25.768371],"type":"Point"}
}