{
  "type": "Feature",
  "properties": {
    "iso:country":"US",
    "sg:address":"50 Pine Dr",
    "sg:city":"Fort Myers",
    "sg:classifiers":[
        {
            "category":"Restaurant",
            "type":"Food & Drink"
        }
    ],
    "sg:phone":"+1 239 995 3444",
    "sg:postcode":"33908",
    "sg:province":"FL",
    "sg:tags":[
        "eating"
    ],
    "wof:name":"Englunds Deli",
    "wof:placetype":"venue"
},
  "geometry": {"coordinates":[-81.964467,26.500662],"type":"Point"}
}