{
  "type": "Feature",
  "properties": {
    "addr:full":"4900 Brittany Dr S Saint Petersburg FL 33715",
    "addr:housenumber":"4900",
    "addr:postcode":"33715",
    "addr:street":"Brittany Dr S",
    "iso:country":"US",
    "sg:address":"4900 Brittany Dr S",
    "sg:city":"Saint Petersburg",
    "sg:classifiers":[
        {
            "category":"Real Estate",
            "subcategory":"Real Estate Agent",
            "type":"Services"
        }
    ],
    "sg:phone":"+1 727 866 8806",
    "sg:postcode":"33715",
    "sg:province":"FL",
    "wof:name":"Graham Tedman",
    "wof:placetype":"venue"
},
  "geometry": {"coordinates":[-82.70017,27.715979],"type":"Point"}
}