{
  "type": "Feature",
  "properties": {
    "iso:country":"US",
    "sg:address":"3182 S Chaires Cross Roads",
    "sg:city":"Tallahassee",
    "sg:classifiers":[
        {
            "category":"Farming",
            "subcategory":"Nursery",
            "type":"Manufacturing & Wholesale Goods"
        },
        {
            "category":"Building & Trades",
            "subcategory":"Landscaping Services",
            "type":"Services"
        }
    ],
    "sg:phone":"+1 850 878 8303",
    "sg:postcode":"32317",
    "sg:province":"FL",
    "sg:tags":[
        "ornamental",
        "sod",
        "sodding"
    ],
    "wof:name":"Panther Creek Sod Farms",
    "wof:placetype":"venue"
},
  "geometry": {"coordinates":[-84.12558,30.476976],"type":"Point"}
}