{
  "type": "Feature",
  "properties": {
    "addr:full":"8440 NW 61st St Miami FL 33166",
    "addr:housenumber":"8440",
    "addr:postcode":"33166",
    "addr:street":"Nw 61St St",
    "iso:country":"US",
    "sg:address":"8440 NW 61st St",
    "sg:city":"Miami",
    "sg:classifiers":[
        {
            "category":"Home & Garden",
            "subcategory":"Building Materials",
            "type":"Retail Goods"
        },
        {
            "category":"Manufacturing",
            "subcategory":"Building Materials",
            "type":"Manufacturing & Wholesale Goods"
        }
    ],
    "sg:phone":"+1 305 436 9780",
    "sg:postcode":"33166",
    "sg:province":"FL",
    "sg:tags":[
        "shutters-wholesale",
        "shutter",
        "window",
        "doors",
        "frames",
        "accessory",
        "manufacturer"
    ],
    "sg:website":"http://strongshutters.com",
    "wof:name":"Strong Shutters",
    "wof:placetype":"venue"
},
  "geometry": {"coordinates":[-80.334428,25.828911],"type":"Point"}
}