{
  "type": "Feature",
  "properties": {
    "iso:country":"US",
    "sg:address":"50 Towne Center Cir",
    "sg:city":"Sanford",
    "sg:classifiers":[
        {
            "category":"Bars & Pubs",
            "type":"Food & Drink"
        }
    ],
    "sg:phone":"+1 407 328 7037",
    "sg:postcode":"32771",
    "sg:province":"FL",
    "sg:tags":[
        "drinking",
        "eating"
    ],
    "wof:name":"Jupiter Ale House Inc",
    "wof:placetype":"venue"
},
  "geometry": {"coordinates":[-81.33667699999999,28.810065],"type":"Point"}
}