{
  "type": "Feature",
  "properties": {
    "iso:country":"US",
    "sg:address":"6705 E 113th Ave",
    "sg:city":"Tampa",
    "sg:classifiers":[
        {
            "category":"Home & Garden",
            "subcategory":"Household Appliances",
            "type":"Retail Goods"
        },
        {
            "category":"Wholesale",
            "subcategory":"Durable Goods & Equipment",
            "type":"Manufacturing & Wholesale Goods"
        }
    ],
    "sg:phone":"+1 813 626 6655",
    "sg:postcode":"33617",
    "sg:province":"FL",
    "sg:tags":[
        "appliances-major-wholesale",
        "major",
        "manufacturer"
    ],
    "wof:name":"Appliance Specialty Of Florida Inc",
    "wof:placetype":"venue"
},
  "geometry": {"coordinates":[-82.371414,28.050721],"type":"Point"}
}