{
  "type": "Feature",
  "properties": {
    "addr:full":"2207 S Dale Mabry Hwy Tampa FL 33629",
    "addr:housenumber":"2207",
    "addr:postcode":"33629",
    "addr:street":"S Dale Mabry Hwy",
    "iso:country":"US",
    "sg:address":"2207 S Dale Mabry Hwy",
    "sg:city":"Tampa",
    "sg:classifiers":[
        {
            "category":"Home & Garden",
            "subcategory":"Furniture",
            "type":"Retail Goods"
        }
    ],
    "sg:phone":"+1 813 253 2421",
    "sg:postcode":"33629",
    "sg:province":"FL",
    "sg:tags":[
        "mattress"
    ],
    "sg:website":"www.famoustate.com",
    "wof:name":"Famous Tate Appliance/Bedding",
    "wof:placetype":"venue"
},
  "geometry": {"coordinates":[-82.505971,27.924782],"type":"Point"}
}