{
  "type": "Feature",
  "properties": {
    "iso:country":"US",
    "sg:address":"14462 SW 38th Ln",
    "sg:city":"Miami",
    "sg:classifiers":[
        {
            "category":"Building & Trades",
            "subcategory":"Construction",
            "type":"Services"
        }
    ],
    "sg:phone":"+1 305 485 5046",
    "sg:postcode":"33175",
    "sg:province":"FL",
    "sg:tags":[
        "equipment",
        "supply",
        "drywall",
        "contractor"
    ],
    "wof:name":"V Drywall Corp",
    "wof:placetype":"venue"
},
  "geometry": {"coordinates":[-80.42930200000001,25.730949],"type":"Point"}
}