{
  "type": "Feature",
  "properties": {
    "addr:full":"10837 NW 29th St Doral FL 33172",
    "addr:housenumber":"10837",
    "addr:postcode":"33172",
    "addr:street":"Nw 29Th St",
    "iso:country":"US",
    "sg:address":"10837 NW 29th St",
    "sg:city":"Doral",
    "sg:classifiers":[
        {
            "category":"Wholesale",
            "subcategory":"Durable Goods & Equipment",
            "type":"Manufacturing & Wholesale Goods"
        }
    ],
    "sg:phone":"+1 305 717 1513",
    "sg:postcode":"33172",
    "sg:province":"FL",
    "sg:tags":[
        "exporter"
    ],
    "wof:name":"Bit Max Intl",
    "wof:placetype":"venue"
},
  "geometry": {"coordinates":[-80.37282399999999,25.800646],"type":"Point"}
}