{
  "type": "Feature",
  "properties": {
    "iso:country":"US",
    "sg:address":"7330 Old Kings Rd",
    "sg:city":"Jacksonville",
    "sg:classifiers":[
        {
            "category":"Railroad",
            "type":"Transportation"
        }
    ],
    "sg:phone":"+1 904 366 1422",
    "sg:postcode":"32219",
    "sg:province":"FL",
    "wof:name":"Norfolk Southern Railway Co",
    "wof:placetype":"venue"
},
  "geometry": {"coordinates":[-81.751227,30.386421],"type":"Point"}
}