{
  "type": "Feature",
  "properties": {
    "addr:full":"6881 Kingspointe Pkwy # 11 Orlando FL 32819",
    "addr:housenumber":"6881;11",
    "addr:postcode":"32819",
    "addr:street":"Kingspointe Pkwy #",
    "iso:country":"US",
    "sg:address":"6881 Kingspointe Pkwy # 11",
    "sg:city":"Orlando",
    "sg:classifiers":[
        {
            "category":"Real Estate",
            "subcategory":"Real Estate Services",
            "type":"Services"
        },
        {
            "category":"Real Estate",
            "subcategory":"Developer",
            "type":"Services"
        },
        {
            "category":"Building & Trades",
            "subcategory":"Construction",
            "type":"Services"
        },
        {
            "category":"Real Estate",
            "subcategory":"Real Estate Agent",
            "type":"Services"
        }
    ],
    "sg:phone":"+1 407 996 5555",
    "sg:postcode":"32819",
    "sg:province":"FL",
    "sg:tags":[
        "management",
        "industrial",
        "contractors-commercial"
    ],
    "wof:name":"Drewtina Development",
    "wof:placetype":"venue"
},
  "geometry": {"coordinates":[-81.437079,28.459649],"type":"Point"}
}