{
  "type": "Feature",
  "properties": {
    "iso:country":"US",
    "sg:address":"10800 Temple Ter",
    "sg:city":"Seminole",
    "sg:classifiers":[
        {
            "category":"Health Services",
            "subcategory":"Nursing And Care Facility",
            "type":"Services"
        }
    ],
    "sg:phone":"+1 727 398 0123",
    "sg:postcode":"33772",
    "sg:province":"FL",
    "sg:tags":[
        "home",
        "convalescent"
    ],
    "wof:name":"Seminole Nursing Pavilion",
    "wof:placetype":"venue"
},
  "geometry": {"coordinates":[-82.79115,27.844251],"type":"Point"}
}