{
  "type": "Feature",
  "properties": {
    "addr:full":"9017 Adamo Dr Tampa FL 33619",
    "addr:postcode":"9017;33619",
    "addr:street":"Adamo Dr",
    "iso:country":"US",
    "sg:address":"9017 Adamo Dr",
    "sg:city":"Tampa",
    "sg:classifiers":[
        {
            "category":"Shopping",
            "subcategory":"Shoes",
            "type":"Retail Goods"
        }
    ],
    "sg:phone":"+1 813 627 0032",
    "sg:postcode":"33619",
    "sg:province":"FL",
    "wof:name":"Shoes That Work",
    "wof:placetype":"venue"
},
  "geometry": {"coordinates":[-82.355546,27.949213],"type":"Point"}
}