{
  "type": "Feature",
  "properties": {
    "addr:full":"5863 Sunset Dr South Miami FL 33143",
    "addr:housenumber":"5863",
    "addr:postcode":"33143",
    "addr:street":"Sunset Dr",
    "iso:country":"US",
    "sg:address":"5863 Sunset Dr",
    "sg:city":"South Miami",
    "sg:classifiers":[
        {
            "category":"Home & Garden",
            "subcategory":"Carpets & Floor Coverings",
            "type":"Retail Goods"
        }
    ],
    "sg:phone":"+1 305 662 1846",
    "sg:postcode":"33143",
    "sg:province":"FL",
    "sg:tags":[
        "carpeting"
    ],
    "wof:name":"Gables Oriental Rugs",
    "wof:placetype":"venue"
},
  "geometry": {"coordinates":[-80.288803,25.704201],"type":"Point"}
}