{
  "type": "Feature",
  "properties": {
    "addr:full":"18400 NE 5th Ave Miami FL 33179",
    "addr:housenumber":"18400",
    "addr:postcode":"33179",
    "addr:street":"Ne 5Th Ave",
    "iso:country":"US",
    "sg:address":"18400 NE 5th Ave",
    "sg:city":"Miami",
    "sg:classifiers":[
        {
            "category":"Professional",
            "subcategory":"Business Services",
            "type":"Services"
        }
    ],
    "sg:phone":"+1 305 652 7733",
    "sg:postcode":"33179",
    "sg:province":"FL",
    "sg:tags":[
        "interior",
        "consultant",
        "design",
        "decorator"
    ],
    "wof:name":"Interior Restoration Inc",
    "wof:placetype":"venue"
},
  "geometry": {"coordinates":[-80.19043499999999,25.944004],"type":"Point"}
}