{
  "type": "Feature",
  "properties": {
    "addr:full":"9666 167th Pl N Jupiter FL 33478",
    "addr:housenumber":"9666",
    "addr:postcode":"33478",
    "addr:street":"167Th Pl N",
    "iso:country":"US",
    "sg:address":"9666 167th Pl N",
    "sg:city":"Jupiter",
    "sg:classifiers":[
        {
            "category":"Recreation",
            "type":"Entertainment"
        }
    ],
    "sg:phone":"+1 561 744 6400",
    "sg:postcode":"33478",
    "sg:province":"FL",
    "sg:tags":[
        "stable"
    ],
    "wof:name":"Long Pond Stables Inc",
    "wof:placetype":"venue"
},
  "geometry": {"coordinates":[-80.18997400000001,26.923745],"type":"Point"}
}