{
  "type": "Feature",
  "properties": {
    "iso:country":"US",
    "sg:address":"12650 McIntosh Rd",
    "sg:city":"Thonotosassa",
    "sg:classifiers":[
        {
            "category":"Wholesale",
            "subcategory":"Farm Supplies",
            "type":"Manufacturing & Wholesale Goods"
        }
    ],
    "sg:phone":"+1 813 986 5611",
    "sg:postcode":"33592",
    "sg:province":"FL",
    "wof:name":"Antioch Feed & Farm Supply",
    "wof:placetype":"venue"
},
  "geometry": {"coordinates":[-82.249275,28.079208],"type":"Point"}
}