{
  "type": "Feature",
  "properties": {
    "iso:country":"US",
    "sg:address":"1 Warner Rd",
    "sg:city":"Green Cove Spgs",
    "sg:classifiers":[
        {
            "category":"Building & Trades",
            "subcategory":"Electrical",
            "type":"Services"
        }
    ],
    "sg:phone":"+1 904 284 2853",
    "sg:postcode":"32043",
    "sg:province":"FL",
    "sg:tags":[
        "electric",
        "contractor"
    ],
    "wof:name":"Salazar Electric",
    "wof:placetype":"venue"
},
  "geometry": {"coordinates":[-81.67010999999999,29.86799],"type":"Point"}
}