{
  "type": "Feature",
  "properties": {
    "addr:full":"4701 S Kenansville Rd Okeechobee FL 34972",
    "addr:housenumber":"4701",
    "addr:postcode":"34972",
    "addr:street":"S Kenansville Rd",
    "iso:country":"US",
    "sg:address":"4701 S Kenansville Rd",
    "sg:city":"Okeechobee",
    "sg:classifiers":[
        {
            "category":"Farming",
            "subcategory":"Livestock Farm",
            "type":"Manufacturing & Wholesale Goods"
        },
        {
            "category":"Farming",
            "subcategory":"Farm & Veterinary Services",
            "type":"Manufacturing & Wholesale Goods"
        },
        {
            "category":"Farming",
            "subcategory":"Farm",
            "type":"Manufacturing & Wholesale Goods"
        }
    ],
    "sg:phone":"+1 772 567 9001",
    "sg:postcode":"34972",
    "sg:province":"FL",
    "sg:tags":[
        "breeder",
        "ranch"
    ],
    "sg:website":"http://www.rollinsfamily.com",
    "wof:name":"Rollins Blue Cypress Ranch",
    "wof:placetype":"venue"
},
  "geometry": {"coordinates":[-80.90173900000001,27.748341],"type":"Point"}
}