{
  "type": "Feature",
  "properties": {
    "addr:full":"1500 San Remo Ave Coral Gables FL 33146",
    "addr:housenumber":"1500",
    "addr:postcode":"33146",
    "addr:street":"San Remo Ave",
    "iso:country":"US",
    "sg:address":"1500 San Remo Ave",
    "sg:city":"Coral Gables",
    "sg:classifiers":[
        {
            "category":"Real Estate",
            "subcategory":"Real Estate Agent",
            "type":"Services"
        }
    ],
    "sg:phone":"+1 305 667 4815",
    "sg:postcode":"33146",
    "sg:province":"FL",
    "sg:website":"www.coralgableswaterfront.com",
    "wof:name":"Coldwell Banker Residential",
    "wof:placetype":"venue"
},
  "geometry": {"coordinates":[-80.28545200000001,25.705935],"type":"Point"}
}