{
  "type": "Feature",
  "properties": {
    "iso:country":"US",
    "sg:address":"1720 Cortez Rd W",
    "sg:city":"Bradenton",
    "sg:classifiers":[
        {
            "category":"Restaurant",
            "type":"Food & Drink"
        }
    ],
    "sg:menulink":"http://www.allmenus.com/fl/bradenton/36376-demetrios-pizza-house/menu/",
    "sg:phone":"+1 941 758 6478",
    "sg:postcode":"34207",
    "sg:province":"FL",
    "sg:tags":[
        "american",
        "pizza"
    ],
    "wof:name":"Demetrios' Pizza House",
    "wof:placetype":"venue"
},
  "geometry": {"coordinates":[-82.578692,27.462469],"type":"Point"}
}