{
  "type": "Feature",
  "properties": {
    "iso:country":"US",
    "sg:address":"5320 Hutto Ln",
    "sg:city":"Jay",
    "sg:classifiers":[
        {
            "category":"Building & Trades",
            "subcategory":"Construction",
            "type":"Services"
        }
    ],
    "sg:phone":"+1 850 675 5062",
    "sg:postcode":"32565",
    "sg:province":"FL",
    "sg:tags":[
        "roofing",
        "contractor"
    ],
    "wof:name":"Edward Archer Roofing",
    "wof:placetype":"venue"
},
  "geometry": {"coordinates":[-87.16036200000001,30.954061],"type":"Point"}
}