{
  "type": "Feature",
  "properties": {
    "iso:country":"US",
    "sg:address":"3011 Maingate Ln",
    "sg:city":"Kissimmee",
    "sg:classifiers":[
        {
            "category":"Travel",
            "subcategory":"Resort",
            "type":"Entertainment"
        }
    ],
    "sg:phone":"+1 407 997 1220",
    "sg:postcode":"34747",
    "sg:province":"FL",
    "sg:tags":[
        "sharing",
        "plan",
        "vacation",
        "time"
    ],
    "wof:name":"Driftwood Vacations",
    "wof:placetype":"venue"
},
  "geometry": {"coordinates":[-81.588477,28.333902],"type":"Point"}
}