{
  "type": "Feature",
  "properties": {
    "iso:country":"US",
    "sg:address":"2948 Bay St",
    "sg:city":"Gulf Breeze",
    "sg:classifiers":[
        {
            "category":"Building & Trades",
            "subcategory":"Construction",
            "type":"Services"
        }
    ],
    "sg:phone":"+1 850 932 7412",
    "sg:postcode":"32563",
    "sg:province":"FL",
    "sg:tags":[
        "house"
    ],
    "wof:name":"Johnnie D Cox Services",
    "wof:placetype":"venue"
},
  "geometry": {"coordinates":[-87.100585,30.37275],"type":"Point"}
}