{
  "type": "Feature",
  "properties": {
    "iso:country":"US",
    "sg:address":"1120 NW 45 Ave",
    "sg:city":"Gainesville",
    "sg:classifiers":[
        {
            "category":"Building & Trades",
            "subcategory":"Construction",
            "type":"Services"
        }
    ],
    "sg:phone":"+1 352 381 9042",
    "sg:postcode":"32609",
    "sg:province":"FL",
    "sg:tags":[
        "house"
    ],
    "wof:name":"Rays Handyman Maint Svcs",
    "wof:placetype":"venue"
},
  "geometry": {"coordinates":[-82.336302,29.695887],"type":"Point"}
}