{
  "type": "Feature",
  "properties": {
    "iso:country":"US",
    "sg:address":"31840 US Hwy 19 N",
    "sg:city":"Palm Harbor",
    "sg:classifiers":[
        {
            "category":"Building & Trades",
            "subcategory":"Construction",
            "type":"Services"
        }
    ],
    "sg:phone":"+1 727 784 3636",
    "sg:postcode":"34684",
    "sg:province":"FL",
    "sg:tags":[
        "contractor"
    ],
    "wof:name":"Home Protection Center",
    "wof:placetype":"venue"
},
  "geometry": {"coordinates":[-82.738972,28.065599],"type":"Point"}
}