{
  "type": "Feature",
  "properties": {
    "addr:full":"373 SW Pinckney St Madison FL 32340",
    "addr:housenumber":"373",
    "addr:postcode":"32340",
    "addr:street":"Sw Pinckney St",
    "iso:country":"US",
    "sg:address":"373 SW Pinckney St",
    "sg:city":"Madison",
    "sg:classifiers":[
        {
            "category":"Autos & Motor Vehicles",
            "subcategory":"Fuel & Gas Station",
            "type":"Retail Goods"
        }
    ],
    "sg:phone":"+1 850 973 2973",
    "sg:postcode":"32340",
    "sg:province":"FL",
    "sg:tags":[
        "stop",
        "truck"
    ],
    "wof:name":"Jimmie's Truck Stop",
    "wof:placetype":"venue"
},
  "geometry": {"coordinates":[-83.414665,30.468593],"type":"Point"}
}