{
  "type": "Feature",
  "properties": {
    "iso:country":"US",
    "sg:address":"1001 Ives Dairy Rd",
    "sg:city":"Miami",
    "sg:classifiers":[
        {
            "category":"Health Services",
            "subcategory":"Dentist",
            "type":"Services"
        }
    ],
    "sg:phone":"+1 305 652 3412",
    "sg:postcode":"33179",
    "sg:province":"FL",
    "sg:tags":[
        "dentists-oral",
        "maxillofacial",
        "dental",
        "dentists-pediatric",
        "clinic",
        "dentistry",
        "surgery",
        "dentists-orthodontists"
    ],
    "sg:website":"http://www.greatexpressions.com/dental-centers/fl/Miami-Ives-Dairy",
    "wof:name":"Dental Health Group Miami - Ives Dairy",
    "wof:placetype":"venue"
},
  "geometry": {"coordinates":[-80.183222,25.964427],"type":"Point"}
}