{
  "type": "Feature",
  "properties": {
    "iso:country":"US",
    "sg:address":"545 NE 121st St",
    "sg:city":"North Miami",
    "sg:classifiers":[
        {
            "category":"Shopping",
            "subcategory":"Shoes",
            "type":"Retail Goods"
        }
    ],
    "sg:phone":"+1 305 899 6969",
    "sg:postcode":"33161",
    "sg:province":"FL",
    "wof:name":"J C Shoe Store",
    "wof:placetype":"venue"
},
  "geometry": {"coordinates":[-80.188846,25.886629],"type":"Point"}
}