{
  "type": "Feature",
  "properties": {
    "iso:country":"US",
    "sg:address":"2640 NE 135th St",
    "sg:city":"North Miami",
    "sg:classifiers":[
        {
            "category":"Real Estate",
            "subcategory":"Real Estate Agent",
            "type":"Services"
        }
    ],
    "sg:phone":"+1 305 949 6999",
    "sg:postcode":"33181",
    "sg:province":"FL",
    "sg:tags":[
        "management"
    ],
    "wof:name":"Personalized Building & Mgmt",
    "wof:placetype":"venue"
},
  "geometry": {"coordinates":[-80.14377500000001,25.900862],"type":"Point"}
}