{
  "type": "Feature",
  "properties": {
    "iso:country":"US",
    "sg:address":"927 Arlington Rd",
    "sg:city":"Palmetto",
    "sg:classifiers":[
        {
            "category":"Manufacturing",
            "subcategory":"Retail Goods",
            "type":"Manufacturing & Wholesale Goods"
        }
    ],
    "sg:phone":"+1 941 723 2954",
    "sg:postcode":"34221",
    "sg:province":"FL",
    "sg:tags":[
        "food",
        "product",
        "machinery",
        "mfg"
    ],
    "wof:name":"Elmar Industries",
    "wof:placetype":"venue"
},
  "geometry": {"coordinates":[-82.574549,27.560026],"type":"Point"}
}