{
  "type": "Feature",
  "properties": {
    "iso:country":"US",
    "sg:address":"390 E Dania Beach Blvd",
    "sg:city":"Dania",
    "sg:classifiers":[
        {
            "category":"Personal",
            "subcategory":"Beauty Salon",
            "type":"Services"
        }
    ],
    "sg:phone":"+1 954 922 1795",
    "sg:postcode":"33004",
    "sg:province":"FL",
    "wof:name":"Before & After Inc",
    "wof:placetype":"venue"
},
  "geometry": {"coordinates":[-80.139234,26.052462],"type":"Point"}
}