{
  "type": "Feature",
  "properties": {
    "iso:country":"US",
    "sg:address":"21637 State Hwy 7",
    "sg:city":"Boca Raton",
    "sg:classifiers":[
        {
            "category":"Shopping",
            "subcategory":"Department Store",
            "type":"Retail Goods"
        }
    ],
    "sg:phone":"+1 561 483 3400",
    "sg:postcode":"33428",
    "sg:province":"FL",
    "wof:name":"Target",
    "wof:placetype":"venue"
},
  "geometry": {"coordinates":[-80.203428,26.356091],"type":"Point"}
}