{
  "type": "Feature",
  "properties": {
    "addr:full":"408 Commerce Way Jupiter FL 33458",
    "addr:housenumber":"408",
    "addr:postcode":"33458",
    "addr:street":"Commerce Way",
    "iso:country":"US",
    "sg:address":"408 Commerce Way",
    "sg:city":"Jupiter",
    "sg:classifiers":[
        {
            "category":"Wholesale",
            "subcategory":"Machinery & Supplies",
            "type":"Manufacturing & Wholesale Goods"
        }
    ],
    "sg:phone":"+1 561 747 3838",
    "sg:postcode":"33458",
    "sg:province":"FL",
    "sg:tags":[
        "tubing",
        "hose",
        "plastic"
    ],
    "wof:name":"Power Hose & Hydraulics Inc",
    "wof:placetype":"venue"
},
  "geometry": {"coordinates":[-80.119833,26.930862],"type":"Point"}
}