{
  "type": "Feature",
  "properties": {
    "iso:country":"US",
    "sg:address":"604 Nautilus St",
    "sg:city":"Panama City Bch",
    "sg:classifiers":[
        {
            "category":"Recreation",
            "type":"Entertainment"
        }
    ],
    "sg:phone":"+1 850 236 7762",
    "sg:postcode":"32413",
    "sg:province":"FL",
    "sg:tags":[
        "parks"
    ],
    "wof:name":"Arvida Pier Park",
    "wof:placetype":"venue"
},
  "geometry": {"coordinates":[-85.853527,30.204539],"type":"Point"}
}