{
  "type": "Feature",
  "properties": {
    "iso:country":"US",
    "sg:address":"100 N Summerlin Ave",
    "sg:city":"Orlando",
    "sg:classifiers":[
        {
            "category":"Restaurant",
            "type":"Food & Drink"
        }
    ],
    "sg:menulink":"http://www.allmenus.com/fl/orlando/36613-anthonys-pizzeria/menu/",
    "sg:phone":"+1 407 648 0009",
    "sg:postcode":"32801",
    "sg:province":"FL",
    "sg:tags":[
        "american",
        "pizza"
    ],
    "wof:name":"Anthony's Pizzeria",
    "wof:placetype":"venue"
},
  "geometry": {"coordinates":[-81.368466,28.543647],"type":"Point"}
}