{
  "type": "Feature",
  "properties": {
    "iso:country":"US",
    "sg:address":"600 Three Islands Blvd",
    "sg:city":"Hallandale",
    "sg:classifiers":[
        {
            "category":"Professional",
            "subcategory":"Employment Agencies",
            "type":"Services"
        }
    ],
    "sg:phone":"+1 954 325 2904",
    "sg:postcode":"33009",
    "sg:province":"FL",
    "sg:tags":[
        "repair",
        "help",
        "supply",
        "mfg",
        "aircraft",
        "parts"
    ],
    "wof:name":"Hernan Turtula",
    "wof:placetype":"venue"
},
  "geometry": {"coordinates":[-80.126643,25.993916],"type":"Point"}
}