{
  "type": "Feature",
  "properties": {
    "iso:country":"US",
    "sg:address":"8379 NW 66th St",
    "sg:city":"Miami",
    "sg:classifiers":[
        {
            "category":"Wholesale",
            "subcategory":"Durable Goods & Equipment",
            "type":"Manufacturing & Wholesale Goods"
        }
    ],
    "sg:phone":"+1 305 629 8808",
    "sg:postcode":"33166",
    "sg:province":"FL",
    "sg:tags":[
        "bio",
        "ag",
        "supply",
        "lab",
        "export",
        "purchasing"
    ],
    "wof:name":"Y Corporation America Inc",
    "wof:placetype":"venue"
},
  "geometry": {"coordinates":[-80.333263,25.833543],"type":"Point"}
}