{
  "type": "Feature",
  "properties": {
    "iso:country":"US",
    "sg:address":"743 Kingston Ct",
    "sg:city":"Apollo Beach",
    "sg:classifiers":[
        {
            "category":"Autos & Motor Vehicles",
            "subcategory":"Boat Sales",
            "type":"Retail Goods"
        }
    ],
    "sg:phone":"+1 813 645 2803",
    "sg:postcode":"33572",
    "sg:province":"FL",
    "sg:tags":[
        "repair"
    ],
    "wof:name":"Eckardts Marine Inc",
    "wof:placetype":"venue"
},
  "geometry": {"coordinates":[-82.41423500000001,27.770923],"type":"Point"}
}