{
  "type": "Feature",
  "properties": {
    "iso:country":"US",
    "sg:address":"18921 NW 19th St",
    "sg:city":"Pembroke Pines",
    "sg:classifiers":[
        {
            "category":"Social Services",
            "type":"Services"
        }
    ],
    "sg:phone":"+1 954 499 3577",
    "sg:postcode":"33029",
    "sg:province":"FL",
    "sg:tags":[
        "info",
        "program",
        "referral"
    ],
    "wof:name":"Alternative Choice-Living Sprt",
    "wof:placetype":"venue"
},
  "geometry": {"coordinates":[-80.399884,26.019928],"type":"Point"}
}