{
  "type": "Feature",
  "properties": {
    "addr:full":"8428 W Oakland Park Blvd Fort Lauderdale FL 33313",
    "addr:housenumber":"8428",
    "addr:postcode":"33313",
    "addr:street":"W Oakland Park Blvd",
    "iso:country":"US",
    "sg:address":"8428 W Oakland Park Blvd",
    "sg:city":"Fort Lauderdale",
    "sg:classifiers":[
        {
            "category":"Professional",
            "subcategory":"Accounting & Tax Preparation",
            "type":"Services"
        }
    ],
    "sg:phone":"+1 954 746 5011",
    "sg:postcode":"33313",
    "sg:province":"FL",
    "wof:name":"Lass Accounting & Bus Svcs Inc",
    "wof:placetype":"venue"
},
  "geometry": {"coordinates":[-80.26249900000001,26.167626],"type":"Point"}
}