{
  "type": "Feature",
  "properties": {
    "iso:country":"US",
    "sg:address":"2400 W Commercial Blvd",
    "sg:city":"Fort Lauderdale",
    "sg:classifiers":[
        {
            "category":"Professional",
            "subcategory":"Employment Agencies",
            "type":"Services"
        }
    ],
    "sg:phone":"+1 954 731 4777",
    "sg:postcode":"33309",
    "sg:province":"FL",
    "sg:tags":[
        "opportunity"
    ],
    "wof:name":"Ablest Staffing Svc",
    "wof:placetype":"venue"
},
  "geometry": {"coordinates":[-80.174823,26.18793],"type":"Point"}
}