{
  "type": "Feature",
  "properties": {
    "addr:full":"5313 8th St Zephyrhills FL 33542",
    "addr:housenumber":"5313",
    "addr:postcode":"33542",
    "addr:street":"8Th St",
    "iso:country":"US",
    "sg:address":"5313 8th St",
    "sg:city":"Zephyrhills",
    "sg:classifiers":[
        {
            "category":"Real Estate",
            "subcategory":"Real Estate Agent",
            "type":"Services"
        }
    ],
    "sg:phone":"+1 813 783 9400",
    "sg:postcode":"33542",
    "sg:province":"FL",
    "wof:name":"Best Of The Bay Realty",
    "wof:placetype":"venue"
},
  "geometry": {"coordinates":[-82.180406,28.235038],"type":"Point"}
}