{
  "type": "Feature",
  "properties": {
    "addr:full":"3020 SW 14th Pl Boynton Beach FL 33426",
    "addr:housenumber":"3020",
    "addr:postcode":"33426",
    "addr:street":"Sw 14Th Pl",
    "iso:country":"US",
    "sg:address":"3020 SW 14th Pl",
    "sg:city":"Boynton Beach",
    "sg:classifiers":[
        {
            "category":"Building & Trades",
            "subcategory":"Construction",
            "type":"Services"
        }
    ],
    "sg:phone":"+1 561 738 5254",
    "sg:postcode":"33426",
    "sg:province":"FL",
    "sg:tags":[
        "general",
        "contractor"
    ],
    "wof:name":"Lifestyles Of Palm Beach Inc",
    "wof:placetype":"venue"
},
  "geometry": {"coordinates":[-80.087868,26.497283],"type":"Point"}
}