{
  "type": "Feature",
  "properties": {
    "iso:country":"US",
    "sg:address":"9149 Collins Ave Apt 205",
    "sg:city":"Surfside",
    "sg:classifiers":[
        {
            "category":"Health Services",
            "subcategory":"Doctor",
            "type":"Services"
        }
    ],
    "sg:phone":"+1 305 865 1608",
    "sg:postcode":"33154",
    "sg:province":"FL",
    "sg:tags":[
        "physician",
        "surgeon"
    ],
    "wof:name":"Alim A Krilov",
    "wof:placetype":"venue"
},
  "geometry": {"coordinates":[-80.121933,25.878862],"type":"Point"}
}