{
  "type": "Feature",
  "properties": {
    "iso:country":"US",
    "sg:address":"5090 Stacy St",
    "sg:city":"West Palm Beach",
    "sg:classifiers":[
        {
            "category":"Building & Trades",
            "subcategory":"Landscaping Services",
            "type":"Services"
        }
    ],
    "sg:phone":"+1 561 616 2554",
    "sg:postcode":"33417",
    "sg:province":"FL",
    "wof:name":"Terrys Uniq Lwn MAInt&tree Tr",
    "wof:placetype":"venue"
},
  "geometry": {"coordinates":[-80.11964399999999,26.697777],"type":"Point"}
}