{
  "type": "Feature",
  "properties": {
    "iso:country":"US",
    "sg:address":"10865 NW 29th St",
    "sg:city":"Doral",
    "sg:classifiers":[
        {
            "category":"Wholesale",
            "subcategory":"Durable Goods & Equipment",
            "type":"Manufacturing & Wholesale Goods"
        }
    ],
    "sg:phone":"+1 305 418 9498",
    "sg:postcode":"33172",
    "sg:province":"FL",
    "sg:tags":[
        "importer"
    ],
    "sg:website":"www.grazianoimport.com",
    "wof:name":"Graziano Import & Export",
    "wof:placetype":"venue"
},
  "geometry": {"coordinates":[-80.37209300000001,25.800648],"type":"Point"}
}