{
  "type": "Feature",
  "properties": {
    "iso:country":"US",
    "sg:address":"5941 Golden Pine Ct",
    "sg:city":"Oviedo",
    "sg:classifiers":[
        {
            "category":"Coffee & Tea",
            "type":"Food & Drink"
        },
        {
            "category":"Restaurant",
            "type":"Food & Drink"
        }
    ],
    "sg:phone":"+1 407 977 5253",
    "sg:postcode":"32765",
    "sg:province":"FL",
    "sg:tags":[
        "espresso"
    ],
    "wof:name":"Klem Furniture",
    "wof:placetype":"venue"
},
  "geometry": {"coordinates":[-81.244407,28.623338],"type":"Point"}
}