{
  "type": "Feature",
  "properties": {
    "addr:full":"2525 NW 20th St Fort Lauderdale FL 33311",
    "addr:housenumber":"2525",
    "addr:postcode":"33311",
    "addr:street":"Nw 20Th St",
    "iso:country":"US",
    "sg:address":"2525 NW 20th St",
    "sg:city":"Fort Lauderdale",
    "sg:classifiers":[
        {
            "category":"Organizations",
            "subcategory":"Religious Organization",
            "type":"Services"
        }
    ],
    "sg:phone":"+1 954 485 3004",
    "sg:postcode":"33311",
    "sg:province":"FL",
    "sg:tags":[
        "church"
    ],
    "wof:name":"Church Of Jesus Christ Apstlc",
    "wof:placetype":"venue"
},
  "geometry": {"coordinates":[-80.175892,26.152413],"type":"Point"}
}