{
  "type": "Feature",
  "properties": {
    "addr:full":"3 NE 3rd Ave Pompano Beach FL 33060",
    "addr:housenumber":"3",
    "addr:postcode":"33060",
    "addr:street":"Ne 3Rd Ave",
    "iso:country":"US",
    "sg:address":"3 NE 3rd Ave",
    "sg:city":"Pompano Beach",
    "sg:classifiers":[
        {
            "category":"Personal",
            "subcategory":"Beauty Salon",
            "type":"Services"
        }
    ],
    "sg:phone":"+1 954 294 1559",
    "sg:postcode":"33060",
    "sg:province":"FL",
    "sg:tags":[
        "shop"
    ],
    "wof:name":"Jessicas Beauty Salon",
    "wof:placetype":"venue"
},
  "geometry": {"coordinates":[-80.121594,26.232452],"type":"Point"}
}