{
  "type": "Feature",
  "properties": {
    "addr:full":"813 Deltona Blvd Deltona FL 32725",
    "addr:housenumber":"813",
    "addr:postcode":"32725",
    "addr:street":"Deltona Blvd",
    "iso:country":"US",
    "sg:address":"813 Deltona Blvd",
    "sg:city":"Deltona",
    "sg:classifiers":[
        {
            "category":"Real Estate",
            "subcategory":"Real Estate Services",
            "type":"Services"
        }
    ],
    "sg:phone":"+1 386 860 5532",
    "sg:postcode":"32725",
    "sg:province":"FL",
    "sg:tags":[
        "company",
        "abstract",
        "title"
    ],
    "wof:name":"First American Title Insur Co",
    "wof:placetype":"venue"
},
  "geometry": {"coordinates":[-81.27594999999999,28.888505],"type":"Point"}
}