{
  "type": "Feature",
  "properties": {
    "iso:country":"US",
    "sg:address":"5706 W Flagler St",
    "sg:city":"Miami",
    "sg:classifiers":[
        {
            "category":"Bars & Pubs",
            "subcategory":"Sports Bar",
            "type":"Food & Drink"
        },
        {
            "category":"Restaurant",
            "type":"Food & Drink"
        }
    ],
    "sg:phone":"+1 786 326 0222",
    "sg:postcode":"33144",
    "sg:province":"FL",
    "sg:tags":[
        "style",
        "latin",
        "family",
        "american",
        "health",
        "cafeteria"
    ],
    "wof:name":"La Esquinita restaurant tapas y vinos",
    "wof:placetype":"venue"
},
  "geometry": {"coordinates":[-80.288318,25.770784],"type":"Point"}
}