{
  "type": "Feature",
  "properties": {
    "iso:country":"US",
    "sg:address":"2454 N Forsyth Rd",
    "sg:city":"Orlando",
    "sg:classifiers":[
        {
            "category":"Wholesale",
            "subcategory":"Electrical",
            "type":"Manufacturing & Wholesale Goods"
        }
    ],
    "sg:phone":"+1 407 679 5960",
    "sg:postcode":"32807",
    "sg:province":"FL",
    "sg:tags":[
        "electronic"
    ],
    "wof:name":"ABSOLUTE Solutions",
    "wof:placetype":"venue"
},
  "geometry": {"coordinates":[-81.294614,28.579845],"type":"Point"}
}