{
  "type": "Feature",
  "properties": {
    "iso:country":"US",
    "sg:address":"34 Lake Success Dr",
    "sg:city":"Palm Coast",
    "sg:classifiers":[
        {
            "category":"Building & Trades",
            "subcategory":"Construction",
            "type":"Services"
        }
    ],
    "sg:phone":"+1 386 446 3895",
    "sg:postcode":"32137",
    "sg:province":"FL",
    "sg:tags":[
        "carpentry",
        "contractor"
    ],
    "wof:name":"Steven Weber",
    "wof:placetype":"venue"
},
  "geometry": {"coordinates":[-81.264601,29.617958],"type":"Point"}
}