{
  "type": "Feature",
  "properties": {
    "iso:country":"US",
    "sg:address":"4742 Kerle St",
    "sg:city":"Jacksonville",
    "sg:classifiers":[
        {
            "category":"Professional",
            "type":"Services"
        }
    ],
    "sg:phone":"+1 407 895 0148",
    "sg:postcode":"32205",
    "sg:province":"FL",
    "wof:name":"Soundguy Inc",
    "wof:placetype":"venue"
},
  "geometry": {"coordinates":[-81.72786600000001,30.311363],"type":"Point"}
}