{
  "type": "Feature",
  "properties": {
    "addr:full":"38300 11th Ave Zephyrhills FL 33542",
    "addr:housenumber":"38300",
    "addr:postcode":"33542",
    "addr:street":"11Th Ave",
    "iso:country":"US",
    "sg:address":"38300 11th Ave",
    "sg:city":"Zephyrhills",
    "sg:classifiers":[
        {
            "category":"Food & Beverages",
            "subcategory":"Bakery",
            "type":"Retail Goods"
        }
    ],
    "sg:phone":"+1 813 783 8011",
    "sg:postcode":"33542",
    "sg:province":"FL",
    "wof:name":"Daylight Donuts",
    "wof:placetype":"venue"
},
  "geometry": {"coordinates":[-82.181799,28.240077],"type":"Point"}
}