{
  "type": "Feature",
  "properties": {
    "addr:full":"4419 Rum Cay Cir Sarasota FL 34233",
    "addr:postcode":"4419;34233",
    "addr:street":"Cay Cir",
    "iso:country":"US",
    "sg:address":"4419 Rum Cay Cir",
    "sg:city":"Sarasota",
    "sg:classifiers":[
        {
            "category":"Organizations",
            "subcategory":"Professional Association",
            "type":"Services"
        }
    ],
    "sg:phone":"+1 941 341 9280",
    "sg:postcode":"34233",
    "sg:province":"FL",
    "wof:name":"Centergate Condominium Assn",
    "wof:placetype":"venue"
},
  "geometry": {"coordinates":[-82.45859299999999,27.291407],"type":"Point"}
}