{
  "type": "Feature",
  "properties": {
    "iso:country":"US",
    "sg:address":"3101 NW 46th St",
    "sg:city":"Miami",
    "sg:classifiers":[
        {
            "category":"Organizations",
            "subcategory":"Religious Organization",
            "type":"Services"
        }
    ],
    "sg:phone":"+1 305 638 1857",
    "sg:postcode":"33142",
    "sg:province":"FL",
    "sg:tags":[
        "church"
    ],
    "wof:name":"New Hopewell Missionary Church",
    "wof:placetype":"venue"
},
  "geometry": {"coordinates":[-80.247311,25.816312],"type":"Point"}
}