{
  "type": "Feature",
  "properties": {
    "addr:full":"1502 Main St Sarasota FL 34236",
    "addr:housenumber":"1502",
    "addr:postcode":"34236",
    "addr:street":"Main St",
    "iso:country":"US",
    "sg:address":"1502 Main St",
    "sg:city":"Sarasota",
    "sg:classifiers":[
        {
            "category":"Wholesale",
            "subcategory":"Groceries",
            "type":"Manufacturing & Wholesale Goods"
        }
    ],
    "sg:phone":"+1 941 330 2552",
    "sg:postcode":"34236",
    "sg:province":"FL",
    "sg:tags":[
        "cocoa",
        "chocolate"
    ],
    "wof:name":"LA Maison Des Chocolats",
    "wof:placetype":"venue"
},
  "geometry": {"coordinates":[-82.53864799999999,27.336391],"type":"Point"}
}