{
  "type": "Feature",
  "properties": {
    "iso:country":"US",
    "sg:address":"12277 Pembroke Rd",
    "sg:city":"Pembroke Pines",
    "sg:classifiers":[
        {
            "category":"Government",
            "subcategory":"Post Office",
            "type":"Public Place"
        }
    ],
    "sg:phone":"+1 954 000 1111",
    "sg:postcode":"33025",
    "sg:province":"FL",
    "wof:name":"US Post Office",
    "wof:placetype":"venue"
},
  "geometry": {"coordinates":[-80.30929399999999,25.993362],"type":"Point"}
}