{
  "type": "Feature",
  "properties": {
    "addr:full":"144 NW 20th St Boca Raton FL 33431",
    "addr:housenumber":"144",
    "addr:postcode":"33431",
    "addr:street":"Nw 20Th St",
    "iso:country":"US",
    "sg:address":"144 NW 20th St",
    "sg:city":"Boca Raton",
    "sg:classifiers":[
        {
            "category":"Building & Trades",
            "subcategory":"Plumbing",
            "type":"Services"
        }
    ],
    "sg:phone":"+1 561 392 8760",
    "sg:postcode":"33431",
    "sg:province":"FL",
    "sg:tags":[
        "inhibit",
        "tank",
        "installs",
        "chemical",
        "which",
        "rust"
    ],
    "wof:name":"Rust Free Of Palm Beach",
    "wof:placetype":"venue"
},
  "geometry": {"coordinates":[-80.087748,26.368014],"type":"Point"}
}