{
  "type": "Feature",
  "properties": {
    "iso:country":"US",
    "sg:address":"4181 Favorite Rd",
    "sg:city":"Fort Pierce",
    "sg:classifiers":[
        {
            "category":"Building & Trades",
            "subcategory":"Construction",
            "type":"Services"
        }
    ],
    "sg:phone":"+1 772 464 3212",
    "sg:postcode":"34981",
    "sg:province":"FL",
    "sg:tags":[
        "carpentry",
        "contractor"
    ],
    "wof:name":"Keith Robinson Carpentry",
    "wof:placetype":"venue"
},
  "geometry": {"coordinates":[-80.367363,27.377809],"type":"Point"}
}