{
  "type": "Feature",
  "properties": {
    "addr:full":"1212 NE 4th Ave Fort Lauderdale FL 33304",
    "addr:housenumber":"1212",
    "addr:postcode":"33304",
    "addr:street":"Ne 4Th Ave",
    "iso:country":"US",
    "sg:address":"1212 NE 4th Ave",
    "sg:city":"Fort Lauderdale",
    "sg:classifiers":[
        {
            "category":"Shopping",
            "type":"Retail Goods"
        }
    ],
    "sg:phone":"+1 954 527 7700",
    "sg:postcode":"33304",
    "sg:province":"FL",
    "sg:tags":[
        "art",
        "gallery",
        "dealer"
    ],
    "wof:name":"Art Expressions LLC",
    "wof:placetype":"venue"
},
  "geometry": {"coordinates":[-80.140449,26.142084],"type":"Point"}
}