{
  "type": "Feature",
  "properties": {
    "addr:full":"30331 US Hwy 19 Clearwater FL 33761",
    "addr:postcode":"30331;33761",
    "addr:street":"Us Hwy 19",
    "iso:country":"US",
    "sg:address":"30331 US Hwy 19",
    "sg:city":"Clearwater",
    "sg:classifiers":[
        {
            "category":"Shopping",
            "subcategory":"Gifts & Souvenirs",
            "type":"Retail Goods"
        }
    ],
    "sg:phone":"+1 727 784 2256",
    "sg:postcode":"33761",
    "sg:province":"FL",
    "sg:tags":[
        "collectible",
        "sport"
    ],
    "wof:name":"Wonder Water Inc",
    "wof:placetype":"venue"
},
  "geometry": {"coordinates":[-82.738388,28.045643],"type":"Point"}
}