{
  "type": "Feature",
  "properties": {
    "addr:full":"13997 Beach Blvd Jacksonville FL 32224",
    "addr:housenumber":"13997",
    "addr:postcode":"32224",
    "addr:street":"Beach Blvd",
    "iso:country":"US",
    "sg:address":"13997 Beach Blvd",
    "sg:city":"Jacksonville",
    "sg:classifiers":[
        {
            "category":"Building & Trades",
            "subcategory":"Plumbing",
            "type":"Services"
        }
    ],
    "sg:phone":"+1 904 223 3585",
    "sg:postcode":"32224",
    "sg:province":"FL",
    "sg:tags":[
        "plumbing",
        "contractor"
    ],
    "wof:name":"B & G Plumbing Co Inc",
    "wof:placetype":"venue"
},
  "geometry": {"coordinates":[-81.452449,30.287812],"type":"Point"}
}