{
  "type": "Feature",
  "properties": {
    "addr:full":"1833 Dean Rd Jacksonville FL 32216",
    "addr:housenumber":"1833",
    "addr:postcode":"32216",
    "addr:street":"Dean Rd",
    "iso:country":"US",
    "sg:address":"1833 Dean Rd",
    "sg:city":"Jacksonville",
    "sg:classifiers":[
        {
            "category":"Shopping",
            "subcategory":"Gifts & Souvenirs",
            "type":"Retail Goods"
        }
    ],
    "sg:phone":"+1 904 721 3939",
    "sg:postcode":"32216",
    "sg:province":"FL",
    "sg:tags":[
        "basket",
        "parcel"
    ],
    "wof:name":"Gift Basket",
    "wof:placetype":"venue"
},
  "geometry": {"coordinates":[-81.591853,30.287251],"type":"Point"}
}