{
  "type": "Feature",
  "properties": {
    "iso:country":"US",
    "sg:address":"1110 NW 27th St",
    "sg:city":"Miami",
    "sg:classifiers":[
        {
            "category":"Education",
            "subcategory":"School",
            "type":"Public Place"
        }
    ],
    "sg:phone":"+1 305 597 9950",
    "sg:postcode":"33127",
    "sg:province":"FL",
    "sg:tags":[
        "k-",
        "private"
    ],
    "sg:website":"http://www.miamicommunitycharterschool.com",
    "wof:name":"Doral Academy High School",
    "wof:placetype":"venue"
},
  "geometry": {"coordinates":[-80.213494,25.80166],"type":"Point"}
}