{
  "type": "Feature",
  "properties": {
    "addr:full":"5525 SW 85th St Miami FL 33143",
    "addr:housenumber":"5525",
    "addr:postcode":"33143",
    "addr:street":"Sw 85Th St",
    "iso:country":"US",
    "sg:address":"5525 SW 85th St",
    "sg:city":"Miami",
    "sg:classifiers":[
        {
            "category":"Professional",
            "subcategory":"Art Services",
            "type":"Services"
        }
    ],
    "sg:phone":"+1 305 665 2148",
    "sg:postcode":"33143",
    "sg:province":"FL",
    "sg:tags":[
        "interior",
        "designer",
        "decorator"
    ],
    "wof:name":"Maria Thomas Interiors",
    "wof:placetype":"venue"
},
  "geometry": {"coordinates":[-80.28315600000001,25.692159],"type":"Point"}
}