{
  "type": "Feature",
  "properties": {
    "addr:full":"1087 Edmiston Pl Longwood FL 32779",
    "addr:housenumber":"1087",
    "addr:postcode":"32779",
    "addr:street":"Edmiston Pl",
    "iso:country":"US",
    "sg:address":"1087 Edmiston Pl",
    "sg:city":"Longwood",
    "sg:classifiers":[
        {
            "category":"Banks & Credit Unions",
            "subcategory":"Financial Services",
            "type":"Services"
        }
    ],
    "sg:phone":"+1 407 774 4033",
    "sg:postcode":"32779",
    "sg:province":"FL",
    "sg:tags":[
        "investor"
    ],
    "wof:name":"Krb Investments",
    "wof:placetype":"venue"
},
  "geometry": {"coordinates":[-81.38313100000001,28.7148],"type":"Point"}
}