{
  "type": "Feature",
  "properties": {
    "iso:country":"US",
    "sg:address":"505 Main St",
    "sg:city":"Safety Harbor",
    "sg:classifiers":[
        {
            "category":"Shopping",
            "subcategory":"Used Merchandise",
            "type":"Retail Goods"
        }
    ],
    "sg:phone":"+1 727 725 1562",
    "sg:postcode":"34695",
    "sg:province":"FL",
    "sg:tags":[
        "antique"
    ],
    "wof:name":"Safety Harbor Antiques",
    "wof:placetype":"venue"
},
  "geometry": {"coordinates":[-82.693201,27.990891],"type":"Point"}
}