{
  "type": "Feature",
  "properties": {
    "addr:full":"220 Water Oak Blvd Lady Lake FL 32159",
    "addr:housenumber":"220",
    "addr:postcode":"32159",
    "addr:street":"Water Oak Blvd",
    "iso:country":"US",
    "sg:address":"220 Water Oak Blvd",
    "sg:city":"Lady Lake",
    "sg:classifiers":[
        {
            "category":"Organizations",
            "subcategory":"Community Association",
            "type":"Services"
        }
    ],
    "sg:phone":"+1 352 753 5245",
    "sg:postcode":"32159",
    "sg:province":"FL",
    "sg:tags":[
        "club"
    ],
    "wof:name":"Water Oak Country Club",
    "wof:placetype":"venue"
},
  "geometry": {"coordinates":[-81.921835,28.923161],"type":"Point"}
}