{
  "type": "Feature",
  "properties": {
    "iso:country":"US",
    "sg:address":"37 N Orange Ave",
    "sg:city":"Orlando",
    "sg:classifiers":[
        {
            "category":"Professional",
            "subcategory":"Printing & Photocopies",
            "type":"Services"
        }
    ],
    "sg:phone":"+1 321 285 2144",
    "sg:postcode":"32801",
    "sg:province":"FL",
    "sg:tags":[
        "document",
        "imaging"
    ],
    "sg:website":"http://www.orlandoscanning.com",
    "wof:name":"Orlando Scanning and Imaging",
    "wof:placetype":"venue"
},
  "geometry": {"coordinates":[-81.379053,28.542822],"type":"Point"}
}