{
  "type": "Feature",
  "properties": {
    "addr:full":"3546 Woodberry Ct Kissimmee FL 34746",
    "addr:housenumber":"3546",
    "addr:postcode":"34746",
    "addr:street":"Woodberry Ct",
    "iso:country":"US",
    "sg:address":"3546 Woodberry Ct",
    "sg:city":"Kissimmee",
    "sg:classifiers":[
        {
            "category":"Building & Trades",
            "subcategory":"Cleaning & Sanitation",
            "type":"Services"
        }
    ],
    "sg:phone":"+1 407 948 6888",
    "sg:postcode":"34746",
    "sg:province":"FL",
    "sg:tags":[
        "house"
    ],
    "wof:name":"Southern Home Svc",
    "wof:placetype":"venue"
},
  "geometry": {"coordinates":[-81.44256900000001,28.193865],"type":"Point"}
}