{
  "type": "Feature",
  "properties": {
    "addr:full":"9679 SW 1st Ct Pompano Beach FL 33071",
    "addr:housenumber":"9679",
    "addr:postcode":"33071",
    "addr:street":"Sw 1St Ct",
    "iso:country":"US",
    "sg:address":"9679 SW 1st Ct",
    "sg:city":"Pompano Beach",
    "sg:classifiers":[
        {
            "category":"Travel",
            "subcategory":"Campground",
            "type":"Entertainment"
        }
    ],
    "sg:phone":"+1 954 753 3731",
    "sg:postcode":"33071",
    "sg:province":"FL",
    "sg:tags":[
        "camp"
    ],
    "wof:name":"Positive Athletics LLC",
    "wof:placetype":"venue"
},
  "geometry": {"coordinates":[-80.254999,26.231358],"type":"Point"}
}