{
  "type": "Feature",
  "properties": {
    "iso:country":"US",
    "sg:address":"5415 Dahlia Reserve Dr",
    "sg:city":"Kissimmee",
    "sg:classifiers":[
        {
            "category":"Real Estate",
            "subcategory":"Real Estate Agent",
            "type":"Services"
        }
    ],
    "sg:phone":"+1 407 932 4079",
    "sg:postcode":"34758",
    "sg:province":"FL",
    "sg:tags":[
        "rental",
        "vacation"
    ],
    "wof:name":"Sun 'N' Fun Vacation Homes Inc",
    "wof:placetype":"venue"
},
  "geometry": {"coordinates":[-81.4991,28.218508],"type":"Point"}
}