{
  "type": "Feature",
  "properties": {
    "addr:full":"6320 Old Kings Rd Jacksonville FL 32254",
    "addr:housenumber":"6320",
    "addr:postcode":"32254",
    "addr:street":"Old Kings Rd",
    "iso:country":"US",
    "sg:address":"6320 Old Kings Rd",
    "sg:city":"Jacksonville",
    "sg:classifiers":[
        {
            "category":"Place Of Worship",
            "type":"Public Place"
        }
    ],
    "sg:phone":"+1 904 786 0083",
    "sg:postcode":"32254",
    "sg:province":"FL",
    "sg:tags":[
        "church"
    ],
    "wof:name":"Dyal, Paul",
    "wof:placetype":"venue"
},
  "geometry": {"coordinates":[-81.74705299999999,30.371863],"type":"Point"}
}