{
  "type": "Feature",
  "properties": {
    "iso:country":"US",
    "sg:address":"921 Golden Gate Blvd E",
    "sg:city":"Naples",
    "sg:classifiers":[
        {
            "category":"Manufacturing",
            "subcategory":"Signs",
            "type":"Manufacturing & Wholesale Goods"
        }
    ],
    "sg:phone":"+1 239 353 5107",
    "sg:postcode":"34120",
    "sg:province":"FL",
    "sg:tags":[
        "specialty",
        "mfg"
    ],
    "wof:name":"Adriana Signs Inc",
    "wof:placetype":"venue"
},
  "geometry": {"coordinates":[-81.588892,26.230173],"type":"Point"}
}