{
  "type": "Feature",
  "properties": {
    "iso:country":"US",
    "sg:address":"16126 Belle Meade Blvd",
    "sg:city":"Odessa",
    "sg:classifiers":[
        {
            "category":"Building & Trades",
            "subcategory":"Plumbing",
            "type":"Services"
        }
    ],
    "sg:phone":"+1 813 920 6605",
    "sg:postcode":"33556",
    "sg:province":"FL",
    "sg:tags":[
        "conditioning",
        "air",
        "system",
        "contractor"
    ],
    "wof:name":"Armex AC Refrig Appl",
    "wof:placetype":"venue"
},
  "geometry": {"coordinates":[-82.555418,28.10603],"type":"Point"}
}