{
  "type": "Feature",
  "properties": {
    "iso:country":"US",
    "sg:address":"2200 Lake Ida Rd",
    "sg:city":"Delray Beach",
    "sg:classifiers":[
        {
            "category":"Insurance",
            "subcategory":"Insurance Agent",
            "type":"Services"
        }
    ],
    "sg:phone":"+1 561 272 7601",
    "sg:postcode":"33445",
    "sg:province":"FL",
    "wof:name":"Thinking With Numbers",
    "wof:placetype":"venue"
},
  "geometry": {"coordinates":[-80.098448,26.473053],"type":"Point"}
}