{
  "type": "Feature",
  "properties": {
    "addr:full":"5026 Sawdust Cir Ocoee FL 34761",
    "addr:postcode":"5026;34761",
    "addr:street":"Sawdust Cir",
    "iso:country":"US",
    "sg:address":"5026 Sawdust Cir",
    "sg:city":"Ocoee",
    "sg:classifiers":[
        {
            "category":"Professional",
            "subcategory":"Business Services",
            "type":"Services"
        }
    ],
    "sg:phone":"+1 407 230 4917",
    "sg:postcode":"34761",
    "sg:province":"FL",
    "wof:name":"Scotts Interiors Inc",
    "wof:placetype":"venue"
},
  "geometry": {"coordinates":[-81.50186100000001,28.602143],"type":"Point"}
}