{
  "type": "Feature",
  "properties": {
    "addr:full":"800 N Main St Bushnell FL 33513",
    "addr:housenumber":"800",
    "addr:postcode":"33513",
    "addr:street":"N Main St",
    "iso:country":"US",
    "sg:address":"800 N Main St",
    "sg:city":"Bushnell",
    "sg:classifiers":[
        {
            "category":"Professional",
            "subcategory":"Business Services",
            "type":"Services"
        },
        {
            "category":"Government",
            "subcategory":"Post Office",
            "type":"Public Place"
        }
    ],
    "sg:phone":"+1 800 275 8777",
    "sg:postcode":"33513",
    "sg:province":"FL",
    "sg:tags":[
        "mail",
        "shipping"
    ],
    "sg:website":"http://www.usps.com",
    "wof:name":"United States Postal Service",
    "wof:placetype":"venue"
},
  "geometry": {"coordinates":[-82.111671,28.67486],"type":"Point"}
}