{
  "type": "Feature",
  "properties": {
    "addr:full":"11760 Scallop Dr Cape Coral FL 33991",
    "addr:housenumber":"11760",
    "addr:postcode":"33991",
    "addr:street":"Scallop Dr",
    "iso:country":"US",
    "sg:address":"11760 Scallop Dr",
    "sg:city":"Cape Coral",
    "sg:classifiers":[
        {
            "category":"Building & Trades",
            "subcategory":"Landscaping Services",
            "type":"Services"
        }
    ],
    "sg:phone":"+1 239 283 9540",
    "sg:postcode":"33991",
    "sg:province":"FL",
    "wof:name":"Mitchell Swenson",
    "wof:placetype":"venue"
},
  "geometry": {"coordinates":[-82.046082,26.63691],"type":"Point"}
}