{
  "type": "Feature",
  "properties": {
    "iso:country":"US",
    "sg:address":"2875 NE 191st St",
    "sg:city":"Aventura",
    "sg:classifiers":[
        {
            "category":"Professional",
            "subcategory":"Management & Consulting",
            "type":"Services"
        }
    ],
    "sg:phone":"+1 305 931 2005",
    "sg:postcode":"33180",
    "sg:province":"FL",
    "sg:tags":[
        "marketing",
        "consultant"
    ],
    "wof:name":"Ascent Investment Management",
    "wof:placetype":"venue"
},
  "geometry": {"coordinates":[-80.143317,25.952155],"type":"Point"}
}