{
  "type": "Feature",
  "properties": {
    "iso:country":"US",
    "sg:address":"4762 Placida Rd",
    "sg:city":"Englewood",
    "sg:classifiers":[
        {
            "category":"Freight",
            "type":"Transportation"
        }
    ],
    "sg:phone":"+1 941 697 0999",
    "sg:postcode":"34224",
    "sg:province":"FL",
    "sg:tags":[
        "commercial",
        "storage",
        "general"
    ],
    "wof:name":"All Ways Better Storage Inc",
    "wof:placetype":"venue"
},
  "geometry": {"coordinates":[-82.31274000000001,26.899279],"type":"Point"}
}