{
  "type": "Feature",
  "properties": {
    "iso:country":"US",
    "sg:address":"4461 Daugharty Rd",
    "sg:city":"Deland",
    "sg:classifiers":[
        {
            "category":"Insurance",
            "subcategory":"Hazard Insurance",
            "type":"Services"
        }
    ],
    "sg:phone":"+1 386 801 5809",
    "sg:postcode":"32724",
    "sg:province":"FL",
    "wof:name":"Dennis Scott Inc.",
    "wof:placetype":"venue"
},
  "geometry": {"coordinates":[-81.27982299999999,29.123697],"type":"Point"}
}