{
  "type": "Feature",
  "properties": {
    "iso:country":"US",
    "sg:address":"329 S Park Ave",
    "sg:city":"Winter Park",
    "sg:classifiers":[
        {
            "category":"Restaurant",
            "type":"Food & Drink"
        }
    ],
    "sg:phone":"+1 407 740 7227",
    "sg:postcode":"32789",
    "sg:province":"FL",
    "sg:tags":[
        "mexican"
    ],
    "wof:name":"Colony Restaurant The",
    "wof:placetype":"venue"
},
  "geometry": {"coordinates":[-81.35107000000001,28.595267],"type":"Point"}
}