{
  "type": "Feature",
  "properties": {
    "iso:country":"US",
    "sg:address":"1223 Lake Biscayne Way",
    "sg:city":"Orlando",
    "sg:classifiers":[
        {
            "category":"Organizations",
            "subcategory":"Religious Organization",
            "type":"Services"
        }
    ],
    "sg:phone":"+1 407 466 7343",
    "sg:postcode":"32824",
    "sg:province":"FL",
    "wof:name":"Luxury Interior Design Inc",
    "wof:placetype":"venue"
},
  "geometry": {"coordinates":[-81.36555,28.350637],"type":"Point"}
}