{
  "type": "Feature",
  "properties": {
    "addr:full":"311 Tequesta Dr Destin FL 32541",
    "addr:housenumber":"311",
    "addr:postcode":"32541",
    "addr:street":"Tequesta Dr",
    "iso:country":"US",
    "sg:address":"311 Tequesta Dr",
    "sg:city":"Destin",
    "sg:classifiers":[
        {
            "category":"Personal",
            "type":"Services"
        },
        {
            "category":"Sports & Exercise",
            "subcategory":"Gym",
            "type":"Entertainment"
        }
    ],
    "sg:phone":"+1 850 654 4784",
    "sg:postcode":"32541",
    "sg:province":"FL",
    "sg:tags":[
        "trainer",
        "consultant",
        "program",
        "physical",
        "fitness"
    ],
    "wof:name":"Resultz Personal Training Inc",
    "wof:placetype":"venue"
},
  "geometry": {"coordinates":[-86.403257,30.394579],"type":"Point"}
}