{
  "type": "Feature",
  "properties": {
    "addr:full":"901 N Lake Destiny Rd Maitland FL 32751",
    "addr:housenumber":"901",
    "addr:postcode":"32751",
    "addr:street":"N Lake Destiny Rd",
    "iso:country":"US",
    "sg:address":"901 N Lake Destiny Rd",
    "sg:city":"Maitland",
    "sg:classifiers":[
        {
            "category":"Professional",
            "subcategory":"Employment Agencies",
            "type":"Services"
        }
    ],
    "sg:phone":"+1 407 659 0808",
    "sg:postcode":"32751",
    "sg:province":"FL",
    "sg:tags":[
        "opportunity"
    ],
    "wof:name":"Unique Temporary Staffing",
    "wof:placetype":"venue"
},
  "geometry": {"coordinates":[-81.388294,28.6352],"type":"Point"}
}