{
  "type": "Feature",
  "properties": {
    "addr:full":"520 Brickell Key Dr Miami FL 33131",
    "addr:housenumber":"520",
    "addr:postcode":"33131",
    "addr:street":"Brickell Key Dr",
    "iso:country":"US",
    "sg:address":"520 Brickell Key Dr",
    "sg:city":"Miami",
    "sg:classifiers":[
        {
            "category":"Real Estate",
            "subcategory":"Architect",
            "type":"Services"
        }
    ],
    "sg:phone":"+1 305 371 2832",
    "sg:postcode":"33131",
    "sg:province":"FL",
    "wof:name":"Wade Robert C Aia Archt",
    "wof:placetype":"venue"
},
  "geometry": {"coordinates":[-80.18589799999999,25.7658],"type":"Point"}
}