{
  "type": "Feature",
  "properties": {
    "iso:country":"US",
    "sg:address":"38544 5th Ave",
    "sg:city":"Zephyrhills",
    "sg:classifiers":[
        {
            "category":"Food & Beverages",
            "subcategory":"Groceries & Convenience Stores",
            "type":"Retail Goods"
        }
    ],
    "sg:phone":"+1 813 782 9279",
    "sg:postcode":"33542",
    "sg:province":"FL",
    "sg:website":"www.7-11.com",
    "wof:name":"7-Eleven",
    "wof:placetype":"venue"
},
  "geometry": {"coordinates":[-82.179272,28.234415],"type":"Point"}
}