{
  "type": "Feature",
  "properties": {
    "iso:country":"US",
    "sg:address":"1745 W Oak Ridge Rd",
    "sg:city":"Orlando",
    "sg:classifiers":[
        {
            "category":"Restaurant",
            "type":"Food & Drink"
        }
    ],
    "sg:phone":"+1 407 855 3204",
    "sg:postcode":"32809",
    "sg:province":"FL",
    "sg:tags":[
        "family"
    ],
    "wof:name":"Bob's Family Restaurant",
    "wof:placetype":"venue"
},
  "geometry": {"coordinates":[-81.403465,28.472503],"type":"Point"}
}