{
  "type": "Feature",
  "properties": {
    "iso:country":"US",
    "sg:address":"13901 SW 33rd Ter",
    "sg:city":"Ocala",
    "sg:classifiers":[
        {
            "category":"Restaurant",
            "type":"Food & Drink"
        }
    ],
    "sg:phone":"+1 352 726 4191",
    "sg:postcode":"34473",
    "sg:province":"FL",
    "sg:tags":[
        "eating"
    ],
    "wof:name":"Family Tree",
    "wof:placetype":"venue"
},
  "geometry": {"coordinates":[-82.178968,29.021366],"type":"Point"}
}