{
  "type": "Feature",
  "properties": {
    "addr:full":"7211 State Rd 54 New Port Richey FL 34653",
    "addr:housenumber":"7211;54",
    "addr:postcode":"34653",
    "addr:street":"State Rd",
    "iso:country":"US",
    "sg:address":"7211 State Rd 54",
    "sg:city":"New Port Richey",
    "sg:classifiers":[
        {
            "category":"Health Services",
            "subcategory":"Doctor",
            "type":"Services"
        }
    ],
    "sg:phone":"+1 727 375 9288",
    "sg:postcode":"34653",
    "sg:province":"FL",
    "sg:tags":[
        "dentist"
    ],
    "wof:name":"Oasis Dental",
    "wof:placetype":"venue"
},
  "geometry": {"coordinates":[-82.692858,28.217122],"type":"Point"}
}