{
  "type": "Feature",
  "properties": {
    "addr:full":"11481 SW 32nd St Miami FL 33165",
    "addr:housenumber":"11481",
    "addr:postcode":"33165",
    "addr:street":"Sw 32Nd St",
    "iso:country":"US",
    "sg:address":"11481 SW 32nd St",
    "sg:city":"Miami",
    "sg:classifiers":[
        {
            "category":"Health Services",
            "subcategory":"Clinic",
            "type":"Services"
        }
    ],
    "sg:phone":"+1 305 552 1567",
    "sg:postcode":"33165",
    "sg:province":"FL",
    "sg:tags":[
        "osteopathic"
    ],
    "wof:name":"Jose F Gruneiro & Assoc Inc",
    "wof:placetype":"venue"
},
  "geometry": {"coordinates":[-80.381512,25.739275],"type":"Point"}
}