{
  "type": "Feature",
  "properties": {
    "iso:country":"US",
    "sg:address":"1288 Indian Hills Rd",
    "sg:city":"Monticello",
    "sg:classifiers":[
        {
            "category":"Professional",
            "subcategory":"Business Services",
            "type":"Services"
        }
    ],
    "sg:phone":"+1 850 997 0088",
    "sg:postcode":"32344",
    "sg:province":"FL",
    "sg:tags":[
        "drafting"
    ],
    "wof:name":"May Patent Drafting & Ilstrtn",
    "wof:placetype":"venue"
},
  "geometry": {"coordinates":[-83.93371999999999,30.523665],"type":"Point"}
}