{
  "type": "Feature",
  "properties": {
    "addr:full":"4219 70th Street Cir E Palmetto FL 34221",
    "addr:housenumber":"4219",
    "addr:postcode":"34221",
    "addr:street":"70Th Street Cir E",
    "iso:country":"US",
    "sg:address":"4219 70th Street Cir E",
    "sg:city":"Palmetto",
    "sg:classifiers":[
        {
            "category":"Personal",
            "subcategory":"Beauty Salon",
            "type":"Services"
        }
    ],
    "sg:phone":"+1 941 531 3700",
    "sg:postcode":"34221",
    "sg:province":"FL",
    "wof:name":"Groomed Spa",
    "wof:placetype":"venue"
},
  "geometry": {"coordinates":[-82.52275899999999,27.578998],"type":"Point"}
}