{
  "type": "Feature",
  "properties": {
    "addr:full":"19501 E Country Club Dr Miami FL 33180",
    "addr:housenumber":"19501",
    "addr:postcode":"33180",
    "addr:street":"E Country Club Dr",
    "iso:country":"US",
    "sg:address":"19501 E Country Club Dr",
    "sg:city":"Miami",
    "sg:classifiers":[
        {
            "category":"Health Services",
            "subcategory":"Clinic",
            "type":"Services"
        }
    ],
    "sg:phone":"+1 305 792 2369",
    "sg:postcode":"33180",
    "sg:province":"FL",
    "sg:tags":[
        "welfare"
    ],
    "wof:name":"Sangosanya Medical Associate P",
    "wof:placetype":"venue"
},
  "geometry": {"coordinates":[-80.129869,25.958163],"type":"Point"}
}