{
  "type": "Feature",
  "properties": {
    "addr:full":"1123 1st St S Winter Haven FL 33880",
    "addr:housenumber":"1123",
    "addr:postcode":"33880",
    "addr:street":"1St St S",
    "iso:country":"US",
    "sg:address":"1123 1st St S",
    "sg:city":"Winter Haven",
    "sg:classifiers":[
        {
            "category":"Personal",
            "subcategory":"Beauty Salon",
            "type":"Services"
        }
    ],
    "sg:phone":"+1 863 293 3336",
    "sg:postcode":"33880",
    "sg:province":"FL",
    "sg:tags":[
        "shop"
    ],
    "wof:name":"Blades",
    "wof:placetype":"venue"
},
  "geometry": {"coordinates":[-81.72685300000001,28.013044],"type":"Point"}
}