{
  "type": "Feature",
  "properties": {
    "addr:full":"6803 N Armenia Ave Tampa FL 33604",
    "addr:housenumber":"6803",
    "addr:postcode":"33604",
    "addr:street":"N Armenia Ave",
    "iso:country":"US",
    "sg:address":"6803 N Armenia Ave",
    "sg:city":"Tampa",
    "sg:classifiers":[
        {
            "category":"Shopping",
            "subcategory":"Clothing, Apparel, & Fashions",
            "type":"Retail Goods"
        },
        {
            "category":"Shopping",
            "subcategory":"Shoes",
            "type":"Retail Goods"
        }
    ],
    "sg:phone":"+1 813 454 5914",
    "sg:postcode":"33604",
    "sg:province":"FL",
    "sg:tags":[
        "handbag",
        "store"
    ],
    "wof:name":"Yasminy Shoes",
    "wof:placetype":"venue"
},
  "geometry": {"coordinates":[-82.48438299999999,28.009399],"type":"Point"}
}