{
  "type": "Feature",
  "properties": {
    "iso:country":"US",
    "sg:address":"680 Goodbar Ave",
    "sg:city":"Umatilla",
    "sg:classifiers":[
        {
            "category":"Retail",
            "subcategory":"Repair Shop",
            "type":"Services"
        }
    ],
    "sg:phone":"+1 352 669 9353",
    "sg:postcode":"32784",
    "sg:province":"FL",
    "sg:tags":[
        "welding"
    ],
    "wof:name":"Specialty Fabrication & Weld",
    "wof:placetype":"venue"
},
  "geometry": {"coordinates":[-81.663729,28.934961],"type":"Point"}
}