{
  "type": "Feature",
  "properties": {
    "iso:country":"US",
    "sg:address":"115 S Miami Ave",
    "sg:city":"Miami",
    "sg:classifiers":[
        {
            "category":"Shopping",
            "subcategory":"Shoes",
            "type":"Retail Goods"
        }
    ],
    "sg:phone":"+1 305 329 2517",
    "sg:postcode":"33130",
    "sg:province":"FL",
    "sg:tags":[
        "store"
    ],
    "wof:name":"The Shoe Service",
    "wof:placetype":"venue"
},
  "geometry": {"coordinates":[-80.19340800000001,25.773289],"type":"Point"}
}