{
  "type": "Feature",
  "properties": {
    "iso:country":"US",
    "sg:address":"823 Wildwood Cir",
    "sg:city":"Daytona Beach",
    "sg:classifiers":[
        {
            "category":"Building & Trades",
            "subcategory":"Construction",
            "type":"Services"
        }
    ],
    "sg:phone":"+1 386 761 8322",
    "sg:postcode":"32127",
    "sg:province":"FL",
    "sg:tags":[
        "concrete",
        "contractor"
    ],
    "wof:name":"Hassett Concrete Pumping",
    "wof:placetype":"venue"
},
  "geometry": {"coordinates":[-81.006213,29.110771],"type":"Point"}
}