{
  "type": "Feature",
  "properties": {
    "iso:country":"US",
    "sg:address":"2010 6th Ave",
    "sg:city":"Vero Beach",
    "sg:classifiers":[
        {
            "category":"Insurance",
            "subcategory":"Insurance Agent",
            "type":"Services"
        }
    ],
    "sg:phone":"+1 772 567 5051",
    "sg:postcode":"32960",
    "sg:province":"FL",
    "wof:name":"Florida Insurance Concepts Inc",
    "wof:placetype":"venue"
},
  "geometry": {"coordinates":[-80.384989,27.638641],"type":"Point"}
}