{
  "type": "Feature",
  "properties": {
    "addr:full":"708 NE 2nd Ave Fort Lauderdale FL 33304",
    "addr:housenumber":"708",
    "addr:postcode":"33304",
    "addr:street":"Ne 2Nd Ave",
    "iso:country":"US",
    "sg:address":"708 NE 2nd Ave",
    "sg:city":"Fort Lauderdale",
    "sg:classifiers":[
        {
            "category":"Manufacturing",
            "subcategory":"Paper Products",
            "type":"Manufacturing & Wholesale Goods"
        }
    ],
    "sg:phone":"+1 954 764 6910",
    "sg:postcode":"33304",
    "sg:province":"FL",
    "sg:tags":[
        "specializing",
        "i",
        "converted",
        "manufacturer"
    ],
    "wof:name":"Palmland Paper Co Inc",
    "wof:placetype":"venue"
},
  "geometry": {"coordinates":[-80.141828,26.133055],"type":"Point"}
}