{
  "type": "Feature",
  "properties": {
    "iso:country":"US",
    "sg:address":"7931 SW 45th St",
    "sg:city":"Fort Lauderdale",
    "sg:classifiers":[
        {
            "category":"Professional",
            "subcategory":"Lawyer & Legal Services",
            "type":"Services"
        }
    ],
    "sg:phone":"+1 954 475 1139",
    "sg:postcode":"33328",
    "sg:province":"FL",
    "wof:name":"Snyder & Kiar",
    "wof:placetype":"venue"
},
  "geometry": {"coordinates":[-80.252442,26.065354],"type":"Point"}
}