{
  "type": "Feature",
  "properties": {
    "iso:country":"US",
    "sg:address":"1205 S Collins St",
    "sg:city":"Plant City",
    "sg:classifiers":[
        {
            "category":"Autos & Motor Vehicles",
            "subcategory":"Auto Supplies",
            "type":"Retail Goods"
        }
    ],
    "sg:phone":"+1 813 752 0405",
    "sg:postcode":"33563",
    "sg:province":"FL",
    "sg:tags":[
        "automobile",
        "parts"
    ],
    "wof:name":"Rose Auto Stores",
    "wof:placetype":"venue"
},
  "geometry": {"coordinates":[-82.121365,28.004904],"type":"Point"}
}