{
  "type": "Feature",
  "properties": {
    "iso:country":"US",
    "sg:address":"500 Palm St",
    "sg:city":"West Palm Beach",
    "sg:classifiers":[
        {
            "category":"Banks & Credit Unions",
            "subcategory":"Financial Services",
            "type":"Services"
        }
    ],
    "sg:phone":"+1 561 655 3469",
    "sg:postcode":"33401",
    "sg:province":"FL",
    "sg:tags":[
        "a",
        "as",
        "company",
        "holding",
        "operates"
    ],
    "wof:name":"Florida Lappins Communications",
    "wof:placetype":"venue"
},
  "geometry": {"coordinates":[-80.056135,26.699341],"type":"Point"}
}