{
  "type": "Feature",
  "properties": {
    "addr:full":"4701 Distribution Ct Orlando FL 32822",
    "addr:housenumber":"4701",
    "addr:postcode":"32822",
    "addr:street":"Distribution Ct",
    "iso:country":"US",
    "sg:address":"4701 Distribution Ct",
    "sg:city":"Orlando",
    "sg:classifiers":[
        {
            "category":"Retail",
            "subcategory":"Auto Repair",
            "type":"Services"
        }
    ],
    "sg:phone":"+1 407 277 1999",
    "sg:postcode":"32822",
    "sg:province":"FL",
    "sg:tags":[
        "glass",
        "coating",
        "tinting"
    ],
    "wof:name":"Florida Solar Control",
    "wof:placetype":"venue"
},
  "geometry": {"coordinates":[-81.300799,28.478115],"type":"Point"}
}