{
  "type": "Feature",
  "properties": {
    "iso:country":"US",
    "sg:address":"1312 Highland Cir",
    "sg:city":"Kissimmee",
    "sg:classifiers":[
        {
            "category":"Building & Trades",
            "subcategory":"Construction",
            "type":"Services"
        }
    ],
    "sg:phone":"+1 407 846 6846",
    "sg:postcode":"34744",
    "sg:province":"FL",
    "sg:tags":[
        "contractor"
    ],
    "wof:name":"Osceola Exteriors",
    "wof:placetype":"venue"
},
  "geometry": {"coordinates":[-81.38989599999999,28.293623],"type":"Point"}
}