{
  "type": "Feature",
  "properties": {
    "iso:country":"US",
    "sg:address":"2550 NE Miami Gardens Dr",
    "sg:city":"Miami",
    "sg:classifiers":[
        {
            "category":"Home & Garden",
            "subcategory":"Home Furnishings",
            "type":"Retail Goods"
        }
    ],
    "sg:phone":"+1 305 466 1144",
    "sg:postcode":"33180",
    "sg:province":"FL",
    "sg:tags":[
        "draperies",
        "vertical",
        "blinds-venetian",
        "window",
        "treatment",
        "curtain"
    ],
    "wof:name":"Fine Shadings & Decor",
    "wof:placetype":"venue"
},
  "geometry": {"coordinates":[-80.150069,25.947354],"type":"Point"}
}