{
  "type": "Feature",
  "properties": {
    "iso:country":"US",
    "sg:address":"2145 14th St",
    "sg:city":"Vero Beach",
    "sg:classifiers":[
        {
            "category":"Professional",
            "subcategory":"Lawyer & Legal Services",
            "type":"Services"
        }
    ],
    "sg:phone":"+1 772 778 5400",
    "sg:postcode":"32960",
    "sg:province":"FL",
    "wof:name":"Brooker & Rooney PA",
    "wof:placetype":"venue"
},
  "geometry": {"coordinates":[-80.40885900000001,27.626916],"type":"Point"}
}