{
  "type": "Feature",
  "properties": {
    "addr:full":"3840 Lake Pickett Ct Orlando FL 32820",
    "addr:housenumber":"3840",
    "addr:postcode":"32820",
    "addr:street":"Lake Pickett Ct",
    "iso:country":"US",
    "sg:address":"3840 Lake Pickett Ct",
    "sg:city":"Orlando",
    "sg:classifiers":[
        {
            "category":"Organizations",
            "subcategory":"Religious Organization",
            "type":"Services"
        }
    ],
    "sg:phone":"+1 407 568 2688",
    "sg:postcode":"32820",
    "sg:province":"FL",
    "sg:tags":[
        "church"
    ],
    "wof:name":"Cornerstone Church",
    "wof:placetype":"venue"
},
  "geometry": {"coordinates":[-81.12175000000001,28.596826],"type":"Point"}
}