{
  "type": "Feature",
  "properties": {
    "addr:full":"3089 Gulf Breeze Pkwy Gulf Breeze FL 32563",
    "addr:housenumber":"3089",
    "addr:postcode":"32563",
    "addr:street":"Gulf Breeze Pkwy",
    "iso:country":"US",
    "sg:address":"3089 Gulf Breeze Pkwy",
    "sg:city":"Gulf Breeze",
    "sg:classifiers":[
        {
            "category":"Building & Trades",
            "subcategory":"Construction",
            "type":"Services"
        }
    ],
    "sg:phone":"+1 850 916 3514",
    "sg:postcode":"32563",
    "sg:province":"FL",
    "sg:tags":[
        "home",
        "general",
        "family",
        "contractor"
    ],
    "sg:website":"www.arthurrutenberghomes.com",
    "wof:name":"Arthur Rutenberg Homes Inc",
    "wof:placetype":"venue"
},
  "geometry": {"coordinates":[-87.092665,30.385873],"type":"Point"}
}