{
  "type": "Feature",
  "properties": {
    "iso:country":"US",
    "sg:address":"1210 Linton Blvd",
    "sg:city":"Delray Beach",
    "sg:classifiers":[
        {
            "category":"Ice Cream",
            "type":"Food & Drink"
        }
    ],
    "sg:menulink":"http://www.allmenus.com/fl/boynton-beach-delray-beach/46086-steak-n-shake/menu/",
    "sg:phone":"+1 561 272 1102",
    "sg:postcode":"33444",
    "sg:province":"FL",
    "sg:tags":[
        "burger",
        "american"
    ],
    "wof:name":"Steak 'n Shake",
    "wof:placetype":"venue"
},
  "geometry": {"coordinates":[-80.08511,26.439389],"type":"Point"}
}