{
  "type": "Feature",
  "properties": {
    "iso:country":"US",
    "sg:address":"14924 SW 104th St",
    "sg:city":"Miami",
    "sg:classifiers":[
        {
            "category":"Restaurant",
            "type":"Food & Drink"
        }
    ],
    "sg:phone":"+1 305 926 3395",
    "sg:postcode":"33196",
    "sg:province":"FL",
    "sg:tags":[
        "eating"
    ],
    "wof:name":"Taquitos",
    "wof:placetype":"venue"
},
  "geometry": {"coordinates":[-80.436027,25.670062],"type":"Point"}
}