{
  "type": "Feature",
  "properties": {
    "iso:country":"US",
    "sg:address":"8515 Sandberry Blvd",
    "sg:city":"Orlando",
    "sg:classifiers":[
        {
            "category":"Education",
            "subcategory":"Special Training",
            "type":"Public Place"
        }
    ],
    "sg:phone":"+1 407 248 8639",
    "sg:postcode":"32819",
    "sg:province":"FL",
    "sg:tags":[
        "school",
        "cooking",
        "instruction"
    ],
    "wof:name":"Veggie Chief Corp",
    "wof:placetype":"venue"
},
  "geometry": {"coordinates":[-81.502157,28.47217],"type":"Point"}
}