{
  "type": "Feature",
  "properties": {
    "iso:country":"US",
    "sg:address":"1046 Cassat Ave",
    "sg:city":"Jacksonville",
    "sg:classifiers":[
        {
            "category":"Bars & Pubs",
            "type":"Food & Drink"
        }
    ],
    "sg:phone":"+1 904 695 2527",
    "sg:postcode":"32205",
    "sg:province":"FL",
    "wof:name":"Bar-B Billards",
    "wof:placetype":"venue"
},
  "geometry": {"coordinates":[-81.730692,30.308111],"type":"Point"}
}