{
  "type": "Feature",
  "properties": {
    "iso:country":"US",
    "sg:address":"800 E Bay Dr",
    "sg:city":"Largo",
    "sg:classifiers":[
        {
            "category":"Real Estate",
            "subcategory":"Real Estate Services",
            "type":"Services"
        },
        {
            "category":"Real Estate",
            "subcategory":"Real Estate Agent",
            "type":"Services"
        }
    ],
    "sg:phone":"+1 727 595 4545",
    "sg:postcode":"33770",
    "sg:province":"FL",
    "sg:tags":[
        "buyer",
        "broker"
    ],
    "wof:name":"Alexandros Real Estate Group International",
    "wof:placetype":"venue"
},
  "geometry": {"coordinates":[-82.77911400000001,27.916639],"type":"Point"}
}