{
  "type": "Feature",
  "properties": {
    "iso:country":"US",
    "sg:address":"3061 NW 107th Ave",
    "sg:city":"Doral",
    "sg:classifiers":[
        {
            "category":"Shopping",
            "subcategory":"Mobile Phones",
            "type":"Retail Goods"
        }
    ],
    "sg:phone":"+1 305 513 8448",
    "sg:postcode":"33172",
    "sg:province":"FL",
    "wof:name":"Yam Wireless Inc",
    "wof:placetype":"venue"
},
  "geometry": {"coordinates":[-80.36750000000001,25.8022],"type":"Point"}
}