{
  "type": "Feature",
  "properties": {
    "iso:country":"US",
    "sg:address":"7035 Beracasa Way",
    "sg:city":"Boca Raton",
    "sg:classifiers":[
        {
            "category":"Education",
            "subcategory":"Vocational School",
            "type":"Public Place"
        }
    ],
    "sg:phone":"+1 561 368 0044",
    "sg:postcode":"33433",
    "sg:province":"FL",
    "wof:name":"Goldcoast School of Real Easte",
    "wof:placetype":"venue"
},
  "geometry": {"coordinates":[-80.155963,26.350889],"type":"Point"}
}