{
  "type": "Feature",
  "properties": {
    "addr:full":"5061 Dogwood Dr Milton FL 32570",
    "addr:housenumber":"5061",
    "addr:postcode":"32570",
    "addr:street":"Dogwood Dr",
    "iso:country":"US",
    "sg:address":"5061 Dogwood Dr",
    "sg:city":"Milton",
    "sg:classifiers":[
        {
            "category":"Shopping",
            "subcategory":"Clothing, Apparel, & Fashions",
            "type":"Retail Goods"
        }
    ],
    "sg:phone":"+1 850 623 8624",
    "sg:postcode":"32570",
    "sg:province":"FL",
    "sg:tags":[
        "family"
    ],
    "wof:name":"Nixons",
    "wof:placetype":"venue"
},
  "geometry": {"coordinates":[-87.056202,30.621151],"type":"Point"}
}