{
  "type": "Feature",
  "properties": {
    "iso:country":"US",
    "sg:address":"401 W 14th St",
    "sg:city":"Lynn Haven",
    "sg:classifiers":[
        {
            "category":"Building & Trades",
            "subcategory":"Construction",
            "type":"Services"
        }
    ],
    "sg:phone":"+1 850 277 0535",
    "sg:postcode":"32444",
    "sg:province":"FL",
    "sg:tags":[
        "dry wall",
        "contractor"
    ],
    "wof:name":"Marco Pro Drywall",
    "wof:placetype":"venue"
},
  "geometry": {"coordinates":[-85.653358,30.237661],"type":"Point"}
}