{
  "type": "Feature",
  "properties": {
    "iso:country":"US",
    "sg:address":"12401 Orange Grove Dr",
    "sg:city":"Tampa",
    "sg:classifiers":[
        {
            "category":"Professional",
            "type":"Services"
        }
    ],
    "sg:phone":"+1 813 643 3971",
    "sg:postcode":"33618",
    "sg:province":"FL",
    "sg:tags":[
        "establishment"
    ],
    "wof:name":"Florida Tampa Mission",
    "wof:placetype":"venue"
},
  "geometry": {"coordinates":[-82.50050299999999,28.060741],"type":"Point"}
}