{
  "type": "Feature",
  "properties": {
    "iso:country":"US",
    "sg:address":"255 N Federal Hwy",
    "sg:city":"Boca Raton",
    "sg:classifiers":[
        {
            "category":"Shopping",
            "subcategory":"Used Merchandise",
            "type":"Retail Goods"
        }
    ],
    "sg:phone":"+1 561 338 4706",
    "sg:postcode":"33432",
    "sg:province":"FL",
    "wof:name":"Consignment Gallery A Inc",
    "wof:placetype":"venue"
},
  "geometry": {"coordinates":[-80.086524,26.352738],"type":"Point"}
}