{
  "type": "Feature",
  "properties": {
    "iso:country":"US",
    "sg:address":"4220 Morelia Pl",
    "sg:city":"Pensacola",
    "sg:classifiers":[
        {
            "category":"Real Estate",
            "subcategory":"Developer",
            "type":"Services"
        }
    ],
    "sg:phone":"+1 850 476 5432",
    "sg:postcode":"32504",
    "sg:province":"FL",
    "wof:name":"Polhill Preston E Land Survey",
    "wof:placetype":"venue"
},
  "geometry": {"coordinates":[-87.16935599999999,30.486877],"type":"Point"}
}