{
  "type": "Feature",
  "properties": {
    "iso:country":"US",
    "sg:address":"117 NW 14th St",
    "sg:city":"Pompano Beach",
    "sg:classifiers":[
        {
            "category":"Building & Trades",
            "subcategory":"Electrical",
            "type":"Services"
        }
    ],
    "sg:phone":"+1 954 784 9876",
    "sg:postcode":"33060",
    "sg:province":"FL",
    "sg:tags":[
        "electric",
        "contractor"
    ],
    "wof:name":"Zack's Auto Tech Electric",
    "wof:placetype":"venue"
},
  "geometry": {"coordinates":[-80.123755,26.245147],"type":"Point"}
}