{
  "type": "Feature",
  "properties": {
    "addr:full":"7792 NW 166th Ter Hialeah FL 33016",
    "addr:housenumber":"7792",
    "addr:postcode":"33016",
    "addr:street":"Nw 166Th Ter",
    "iso:country":"US",
    "sg:address":"7792 NW 166th Ter",
    "sg:city":"Hialeah",
    "sg:classifiers":[
        {
            "category":"Restaurant",
            "type":"Food & Drink"
        }
    ],
    "sg:phone":"+1 305 785 1184",
    "sg:postcode":"33016",
    "sg:province":"FL",
    "sg:tags":[
        "eating"
    ],
    "wof:name":"Reliable Catering",
    "wof:placetype":"venue"
},
  "geometry": {"coordinates":[-80.32753200000001,25.924572],"type":"Point"}
}