{
  "type": "Feature",
  "properties": {
    "addr:full":"1318 N Pine Hills Rd Orlando FL 32808",
    "addr:housenumber":"1318",
    "addr:postcode":"32808",
    "addr:street":"N Pine Hills Rd",
    "iso:country":"US",
    "sg:address":"1318 N Pine Hills Rd",
    "sg:city":"Orlando",
    "sg:classifiers":[
        {
            "category":"Building & Trades",
            "subcategory":"Construction",
            "type":"Services"
        }
    ],
    "sg:phone":"+1 407 523 1458",
    "sg:postcode":"32808",
    "sg:province":"FL",
    "sg:tags":[
        "masonry",
        "contractor"
    ],
    "sg:website":"www.duncanenterprises.com",
    "wof:name":"Duncan Enterprise-Central Fl",
    "wof:placetype":"venue"
},
  "geometry": {"coordinates":[-81.452247,28.572201],"type":"Point"}
}