{
  "type": "Feature",
  "properties": {
    "iso:country":"US",
    "sg:address":"5565 Schenck Ave",
    "sg:city":"Rockledge",
    "sg:classifiers":[
        {
            "category":"Real Estate",
            "subcategory":"Real Estate Agent",
            "type":"Services"
        }
    ],
    "sg:phone":"+1 321 636 9003",
    "sg:postcode":"32955",
    "sg:province":"FL",
    "wof:name":"Apollo Realty Inc",
    "wof:placetype":"venue"
},
  "geometry": {"coordinates":[-80.691631,28.267125],"type":"Point"}
}