{
  "type": "Feature",
  "properties": {
    "iso:country":"US",
    "sg:address":"16475 Dixie Hwy",
    "sg:city":"Miami",
    "sg:classifiers":[
        {
            "category":"Autos & Motor Vehicles",
            "subcategory":"Automobile Sales",
            "type":"Retail Goods"
        }
    ],
    "sg:phone":"+1 305 255 6525",
    "sg:postcode":"33157",
    "sg:province":"FL",
    "sg:tags":[
        "car",
        "dealer"
    ],
    "wof:name":"Parkside Motors",
    "wof:placetype":"venue"
},
  "geometry": {"coordinates":[-80.346175,25.617119],"type":"Point"}
}