{
  "type": "Feature",
  "properties": {
    "iso:country":"US",
    "sg:address":"2104 Mud Lake Rd",
    "sg:city":"Plant City",
    "sg:classifiers":[
        {
            "category":"Organizations",
            "subcategory":"Religious Organization",
            "type":"Services"
        }
    ],
    "sg:phone":"+1 813 752 6064",
    "sg:postcode":"33566",
    "sg:province":"FL",
    "sg:tags":[
        "church"
    ],
    "sg:website":"www.lordoflifepc.org",
    "wof:name":"Lord Of Life Evangelical Luthe",
    "wof:placetype":"venue"
},
  "geometry": {"coordinates":[-82.137506,27.991646],"type":"Point"}
}