{
  "type": "Feature",
  "properties": {
    "addr:full":"3657 San Remo Ter Sarasota FL 34239",
    "addr:housenumber":"3657",
    "addr:postcode":"34239",
    "addr:street":"San Remo Ter",
    "iso:country":"US",
    "sg:address":"3657 San Remo Ter",
    "sg:city":"Sarasota",
    "sg:classifiers":[
        {
            "category":"Professional",
            "subcategory":"Printing & Photocopies",
            "type":"Services"
        }
    ],
    "sg:phone":"+1 941 330 8111",
    "sg:postcode":"34239",
    "sg:province":"FL",
    "sg:tags":[
        "lithographer"
    ],
    "wof:name":"Rustin Print Group, Inc.",
    "wof:placetype":"venue"
},
  "geometry": {"coordinates":[-82.541572,27.301618],"type":"Point"}
}