{
  "type": "Feature",
  "properties": {
    "addr:full":"4114 Sunbeam Rd Jacksonville FL 32257",
    "addr:housenumber":"4114",
    "addr:postcode":"32257",
    "addr:street":"Sunbeam Rd",
    "iso:country":"US",
    "sg:address":"4114 Sunbeam Rd",
    "sg:city":"Jacksonville",
    "sg:classifiers":[
        {
            "category":"Social Services",
            "type":"Services"
        }
    ],
    "sg:phone":"+1 904 891 9503",
    "sg:postcode":"32257",
    "sg:province":"FL",
    "sg:tags":[
        "cultural",
        "activity"
    ],
    "wof:name":"Centro Social",
    "wof:placetype":"venue"
},
  "geometry": {"coordinates":[-81.608509,30.205739],"type":"Point"}
}