{
  "type": "Feature",
  "properties": {
    "iso:country":"US",
    "sg:address":"2704 W Avery St",
    "sg:city":"Pensacola",
    "sg:classifiers":[
        {
            "category":"Shopping",
            "subcategory":"Clothing, Apparel, & Fashions",
            "type":"Retail Goods"
        }
    ],
    "sg:phone":"+1 850 433 2424",
    "sg:postcode":"32505",
    "sg:province":"FL",
    "wof:name":"Unique Fashions",
    "wof:placetype":"venue"
},
  "geometry": {"coordinates":[-87.248402,30.431546],"type":"Point"}
}