{
  "type": "Feature",
  "properties": {
    "iso:country":"US",
    "sg:address":"5300 SW 102nd Ave",
    "sg:city":"Miami",
    "sg:classifiers":[
        {
            "category":"Education",
            "subcategory":"School",
            "type":"Public Place"
        }
    ],
    "sg:phone":"+1 305 598 3184",
    "sg:postcode":"33165",
    "sg:province":"FL",
    "wof:name":"Sister Carolyn Learning Center",
    "wof:placetype":"venue"
},
  "geometry": {"coordinates":[-80.3591,25.7174],"type":"Point"}
}