{
  "type": "Feature",
  "properties": {
    "addr:full":"10 Cloister Cir West Palm Beach FL 33401",
    "addr:housenumber":"10",
    "addr:postcode":"33401",
    "addr:street":"Cloister Cir",
    "iso:country":"US",
    "sg:address":"10 Cloister Cir",
    "sg:city":"West Palm Beach",
    "sg:classifiers":[
        {
            "category":"Professional",
            "subcategory":"Management & Consulting",
            "type":"Services"
        }
    ],
    "sg:phone":"+1 561 682 9755",
    "sg:postcode":"33401",
    "sg:province":"FL",
    "sg:tags":[
        "consultant",
        "energy",
        "conservation"
    ],
    "wof:name":"Northview Power Systems",
    "wof:placetype":"venue"
},
  "geometry": {"coordinates":[-80.07846499999999,26.731182],"type":"Point"}
}