{
  "type": "Feature",
  "properties": {
    "iso:country":"US",
    "sg:address":"6231 14th St W",
    "sg:city":"Bradenton",
    "sg:classifiers":[
        {
            "category":"Personal",
            "subcategory":"Beauty Salon",
            "type":"Services"
        }
    ],
    "sg:phone":"+1 941 756 3330",
    "sg:postcode":"34207",
    "sg:province":"FL",
    "wof:name":"First Choice Haircutters",
    "wof:placetype":"venue"
},
  "geometry": {"coordinates":[-82.575401,27.429902],"type":"Point"}
}