{
  "type": "Feature",
  "properties": {
    "addr:full":"417 Flamingo Dr Apollo Beach FL 33572",
    "addr:housenumber":"417",
    "addr:postcode":"33572",
    "addr:street":"Flamingo Dr",
    "iso:country":"US",
    "sg:address":"417 Flamingo Dr",
    "sg:city":"Apollo Beach",
    "sg:classifiers":[
        {
            "category":"Building & Trades",
            "subcategory":"Landscaping Services",
            "type":"Services"
        }
    ],
    "sg:phone":"+1 813 645 9626",
    "sg:postcode":"33572",
    "sg:province":"FL",
    "wof:name":"Jims Lawn Service",
    "wof:placetype":"venue"
},
  "geometry": {"coordinates":[-82.403369,27.771083],"type":"Point"}
}