{
  "type": "Feature",
  "properties": {
    "iso:country":"US",
    "sg:address":"3452 Fowler St",
    "sg:city":"Fort Myers",
    "sg:classifiers":[
        {
            "category":"Wholesale",
            "subcategory":"Medical Equipment & Supplies",
            "type":"Manufacturing & Wholesale Goods"
        }
    ],
    "sg:phone":"+1 239 278 0005",
    "sg:postcode":"33901",
    "sg:province":"FL",
    "sg:tags":[
        "physician",
        "surgeon"
    ],
    "wof:name":"American Medical Mart",
    "wof:placetype":"venue"
},
  "geometry": {"coordinates":[-81.861904,26.61358],"type":"Point"}
}