{
  "type": "Feature",
  "properties": {
    "addr:full":"8171 Hwy 40 E Inglis FL 34449",
    "addr:housenumber":"8171",
    "addr:postcode":"34449",
    "addr:street":"Hwy 40 E",
    "iso:country":"US",
    "sg:address":"8171 Hwy 40 E",
    "sg:city":"Inglis",
    "sg:classifiers":[
        {
            "category":"Wholesale",
            "subcategory":"Groceries",
            "type":"Manufacturing & Wholesale Goods"
        }
    ],
    "sg:phone":"+1 352 683 6111",
    "sg:postcode":"34449",
    "sg:province":"FL",
    "sg:tags":[
        "confectionery"
    ],
    "wof:name":"Candy Bouquets",
    "wof:placetype":"venue"
},
  "geometry": {"coordinates":[-82.63424999999999,29.02639],"type":"Point"}
}