{
  "type": "Feature",
  "properties": {
    "iso:country":"US",
    "sg:address":"16120 Bay Pointe Blvd",
    "sg:city":"Fort Myers",
    "sg:classifiers":[
        {
            "category":"Real Estate",
            "subcategory":"Real Estate Operator",
            "type":"Services"
        }
    ],
    "sg:phone":"+1 239 543 6747",
    "sg:postcode":"33917",
    "sg:province":"FL",
    "sg:tags":[
        "condominium"
    ],
    "wof:name":"Bay Pointe Yacht & Raquet Club",
    "wof:placetype":"venue"
},
  "geometry": {"coordinates":[-81.77525900000001,26.712795],"type":"Point"}
}