{
  "type": "Feature",
  "properties": {
    "iso:country":"US",
    "sg:address":"7532 Dunbridge Dr",
    "sg:city":"Odessa",
    "sg:classifiers":[
        {
            "category":"Professional",
            "subcategory":"Management & Consulting",
            "type":"Services"
        }
    ],
    "sg:phone":"+1 813 920 6600",
    "sg:postcode":"33556",
    "sg:province":"FL",
    "sg:tags":[
        "consultant",
        "search",
        "executive"
    ],
    "wof:name":"Powell And Associates",
    "wof:placetype":"venue"
},
  "geometry": {"coordinates":[-82.56370099999999,28.150455],"type":"Point"}
}