{
  "type": "Feature",
  "properties": {
    "iso:country":"US",
    "sg:address":"14933 82nd Ln N",
    "sg:city":"Loxahatchee",
    "sg:classifiers":[
        {
            "category":"Building & Trades",
            "subcategory":"Construction",
            "type":"Services"
        }
    ],
    "sg:phone":"+1 561 795 7445",
    "sg:postcode":"33470",
    "sg:province":"FL",
    "sg:tags":[
        "house"
    ],
    "wof:name":"Home Repair & Maintenance",
    "wof:placetype":"venue"
},
  "geometry": {"coordinates":[-80.276115,26.799762],"type":"Point"}
}