{
  "type": "Feature",
  "properties": {
    "addr:full":"3993 W State Road 46 Sanford FL 32771",
    "addr:housenumber":"3993",
    "addr:postcode":"32771",
    "addr:street":"W State Road 46",
    "iso:country":"US",
    "sg:address":"3993 W State Road 46",
    "sg:city":"Sanford",
    "sg:classifiers":[
        {
            "category":"Real Estate",
            "subcategory":"Real Estate Services",
            "type":"Services"
        },
        {
            "category":"Real Estate",
            "subcategory":"Developer",
            "type":"Services"
        },
        {
            "category":"Real Estate",
            "subcategory":"Real Estate Agent",
            "type":"Services"
        }
    ],
    "sg:phone":"+1 407 302 7800",
    "sg:postcode":"32771",
    "sg:province":"FL",
    "sg:tags":[
        "buyer",
        "broker"
    ],
    "wof:name":"Maronda Homes Real Estate",
    "wof:placetype":"venue"
},
  "geometry": {"coordinates":[-81.319901,28.811459],"type":"Point"}
}