{
  "type": "Feature",
  "properties": {
    "addr:full":"3812 SE 25th St Okeechobee FL 34974",
    "addr:housenumber":"3812",
    "addr:postcode":"34974",
    "addr:street":"Se 25Th St",
    "iso:country":"US",
    "sg:address":"3812 SE 25th St",
    "sg:city":"Okeechobee",
    "sg:classifiers":[
        {
            "category":"Building & Trades",
            "subcategory":"Construction",
            "type":"Services"
        }
    ],
    "sg:phone":"+1 561 248 3035",
    "sg:postcode":"34974",
    "sg:province":"FL",
    "sg:tags":[
        "carpenter"
    ],
    "wof:name":"Rodney Mellette Carpenter",
    "wof:placetype":"venue"
},
  "geometry": {"coordinates":[-80.790246,27.221245],"type":"Point"}
}