{
  "type": "Feature",
  "properties": {
    "iso:country":"US",
    "sg:address":"1610 W 15th St",
    "sg:city":"Panama City",
    "sg:classifiers":[
        {
            "category":"Food & Beverages",
            "subcategory":"Groceries & Convenience Stores",
            "type":"Retail Goods"
        }
    ],
    "sg:phone":"+1 850 914 9866",
    "sg:postcode":"32401",
    "sg:province":"FL",
    "wof:name":"Dodge's Chicken Store",
    "wof:placetype":"venue"
},
  "geometry": {"coordinates":[-85.686843,30.175422],"type":"Point"}
}