{
  "type": "Feature",
  "properties": {
    "iso:country":"US",
    "sg:address":"14940 Cathy Ln",
    "sg:city":"Largo",
    "sg:classifiers":[
        {
            "category":"Real Estate",
            "subcategory":"Real Estate Agent",
            "type":"Services"
        }
    ],
    "sg:phone":"+1 727 595 6122",
    "sg:postcode":"33774",
    "sg:province":"FL",
    "wof:name":"Christine Coston",
    "wof:placetype":"venue"
},
  "geometry": {"coordinates":[-82.845377,27.870171],"type":"Point"}
}