{
  "type": "Feature",
  "properties": {
    "iso:country":"US",
    "sg:address":"373 N Congress Ave",
    "sg:city":"Boynton Beach",
    "sg:classifiers":[
        {
            "category":"Shopping",
            "subcategory":"Clothing, Apparel, & Fashions",
            "type":"Retail Goods"
        }
    ],
    "sg:phone":"+1 561 733 4449",
    "sg:postcode":"33426",
    "sg:province":"FL",
    "wof:name":"Old Navy 5877",
    "wof:placetype":"venue"
},
  "geometry": {"coordinates":[-80.090587,26.529128],"type":"Point"}
}