{
  "type": "Feature",
  "properties": {
    "iso:country":"US",
    "sg:address":"1231 W Flagler St",
    "sg:city":"Miami",
    "sg:classifiers":[
        {
            "category":"Food & Beverages",
            "subcategory":"Liquor & Beverages",
            "type":"Retail Goods"
        }
    ],
    "sg:phone":"+1 305 326 1115",
    "sg:postcode":"33135",
    "sg:province":"FL",
    "sg:tags":[
        "beer",
        "wine",
        "spirit",
        "alcoholic"
    ],
    "wof:name":"Latin Liquor",
    "wof:placetype":"venue"
},
  "geometry": {"coordinates":[-80.215698,25.773399],"type":"Point"}
}