{
  "type": "Feature",
  "properties": {
    "iso:country":"US",
    "sg:address":"12490 Metro Pkwy",
    "sg:city":"Fort Myers",
    "sg:classifiers":[
        {
            "category":"Retail",
            "subcategory":"Auto Repair",
            "type":"Services"
        }
    ],
    "sg:phone":"+1 239 561 1198",
    "sg:postcode":"33966",
    "sg:province":"FL",
    "sg:tags":[
        "body",
        "shop"
    ],
    "wof:name":"Fort Myers Collision Center",
    "wof:placetype":"venue"
},
  "geometry": {"coordinates":[-81.85381700000001,26.561202],"type":"Point"}
}