{
  "type": "Feature",
  "properties": {
    "addr:full":"115 Marion Rd Hollywood FL 33023",
    "addr:housenumber":"115",
    "addr:postcode":"33023",
    "addr:street":"Marion Rd",
    "iso:country":"US",
    "sg:address":"115 Marion Rd",
    "sg:city":"Hollywood",
    "sg:classifiers":[
        {
            "category":"Manufacturing",
            "subcategory":"Printing",
            "type":"Manufacturing & Wholesale Goods"
        }
    ],
    "sg:phone":"+1 954 983 6721",
    "sg:postcode":"33023",
    "sg:province":"FL",
    "sg:tags":[
        "lithographic",
        "commercial"
    ],
    "wof:name":"Printing & Copy Express",
    "wof:placetype":"venue"
},
  "geometry": {"coordinates":[-80.198482,25.981753],"type":"Point"}
}