{
  "type": "Feature",
  "properties": {
    "addr:full":"600 N Church Ave Mulberry FL 33860",
    "addr:housenumber":"600",
    "addr:postcode":"33860",
    "addr:street":"N Church Ave",
    "iso:country":"US",
    "sg:address":"600 N Church Ave",
    "sg:city":"Mulberry",
    "sg:classifiers":[
        {
            "category":"Manufacturing",
            "subcategory":"Tools & Machinery",
            "type":"Manufacturing & Wholesale Goods"
        }
    ],
    "sg:phone":"+1 863 425 4538",
    "sg:postcode":"33860",
    "sg:province":"FL",
    "sg:tags":[
        "control"
    ],
    "wof:name":"Selvidge Technology Inc",
    "wof:placetype":"venue"
},
  "geometry": {"coordinates":[-81.973741,27.90068],"type":"Point"}
}