{
  "type": "Feature",
  "properties": {
    "addr:full":"3165 N Canal Dr Palm Harbor FL 34684",
    "addr:housenumber":"3165",
    "addr:postcode":"34684",
    "addr:street":"N Canal Dr",
    "iso:country":"US",
    "sg:address":"3165 N Canal Dr",
    "sg:city":"Palm Harbor",
    "sg:classifiers":[
        {
            "category":"Professional",
            "type":"Services"
        }
    ],
    "sg:phone":"+1 727 771 0613",
    "sg:postcode":"34684",
    "sg:province":"FL",
    "wof:name":"RE Putnam Inc",
    "wof:placetype":"venue"
},
  "geometry": {"coordinates":[-82.726055,28.098854],"type":"Point"}
}