{
  "type": "Feature",
  "properties": {
    "addr:full":"3001 N 22nd St Tampa FL 33605",
    "addr:housenumber":"3001",
    "addr:postcode":"33605",
    "addr:street":"N 22Nd St",
    "iso:country":"US",
    "sg:address":"3001 N 22nd St",
    "sg:city":"Tampa",
    "sg:classifiers":[
        {
            "category":"Organizations",
            "subcategory":"Religious Organization",
            "type":"Services"
        }
    ],
    "sg:phone":"+1 813 247 3594",
    "sg:postcode":"33605",
    "sg:province":"FL",
    "sg:tags":[
        "church"
    ],
    "wof:name":"Deliverance Tabernacle",
    "wof:placetype":"venue"
},
  "geometry": {"coordinates":[-82.434748,27.971034],"type":"Point"}
}