{
  "type": "Feature",
  "properties": {
    "addr:full":"707 Grenada Ln Summerland Key FL 33042",
    "addr:housenumber":"707",
    "addr:postcode":"33042",
    "addr:street":"Grenada Ln",
    "iso:country":"US",
    "sg:address":"707 Grenada Ln",
    "sg:city":"Summerland Key",
    "sg:classifiers":[
        {
            "category":"Banks & Credit Unions",
            "subcategory":"Financial Services",
            "type":"Services"
        }
    ],
    "sg:phone":"+1 305 872 3278",
    "sg:postcode":"33042",
    "sg:province":"FL",
    "sg:tags":[
        "investor"
    ],
    "wof:name":"Emerging Mktg Inv Co",
    "wof:placetype":"venue"
},
  "geometry": {"coordinates":[-81.38969899999999,24.676173],"type":"Point"}
}