{
  "type": "Feature",
  "properties": {
    "iso:country":"US",
    "sg:address":"8399 NW 30th Ter",
    "sg:city":"Doral",
    "sg:classifiers":[
        {
            "category":"Professional",
            "subcategory":"Computer Services",
            "type":"Services"
        }
    ],
    "sg:phone":"+1 305 266 6533",
    "sg:postcode":"33122",
    "sg:province":"FL",
    "sg:website":"www.compuquip.com",
    "wof:name":"Compuquip Inc",
    "wof:placetype":"venue"
},
  "geometry": {"coordinates":[-80.334354,25.801995],"type":"Point"}
}