{
  "type": "Feature",
  "properties": {
    "iso:country":"US",
    "sg:address":"15110 Whetstone Way",
    "sg:city":"Fort Lauderdale",
    "sg:classifiers":[
        {
            "category":"Building & Trades",
            "subcategory":"Plumbing",
            "type":"Services"
        }
    ],
    "sg:phone":"+1 954 434 1857",
    "sg:postcode":"33331",
    "sg:province":"FL",
    "sg:tags":[
        "contractor"
    ],
    "wof:name":"Farthing Plumbing Inc",
    "wof:placetype":"venue"
},
  "geometry": {"coordinates":[-80.35068099999999,26.052367],"type":"Point"}
}