{
  "type": "Feature",
  "properties": {
    "iso:country":"US",
    "sg:address":"1465 Highridge Ave",
    "sg:city":"Daytona Beach",
    "sg:classifiers":[
        {
            "category":"Building & Trades",
            "subcategory":"Electrical",
            "type":"Services"
        }
    ],
    "sg:phone":"+1 386 527 9396",
    "sg:postcode":"32124",
    "sg:province":"FL",
    "sg:tags":[
        "electrical",
        "electric",
        "contractor"
    ],
    "wof:name":"Electrical Tech Services Inc",
    "wof:placetype":"venue"
},
  "geometry": {"coordinates":[-81.13542,29.133092],"type":"Point"}
}