{
  "type": "Feature",
  "properties": {
    "addr:full":"7008 59th St Pinellas Park FL 33781",
    "addr:housenumber":"7008",
    "addr:postcode":"33781",
    "addr:street":"59Th St",
    "iso:country":"US",
    "sg:address":"7008 59th St",
    "sg:city":"Pinellas Park",
    "sg:classifiers":[
        {
            "category":"Building & Trades",
            "subcategory":"Landscaping Services",
            "type":"Services"
        }
    ],
    "sg:phone":"+1 727 545 2494",
    "sg:postcode":"33781",
    "sg:province":"FL",
    "sg:tags":[
        "landscape"
    ],
    "wof:name":"Natural Art Landscapes",
    "wof:placetype":"venue"
},
  "geometry": {"coordinates":[-82.71438999999999,27.836667],"type":"Point"}
}