{
  "type": "Feature",
  "properties": {
    "iso:country":"US",
    "sg:address":"1239 Rogero Rd",
    "sg:city":"Jacksonville",
    "sg:classifiers":[
        {
            "category":"Sports & Exercise",
            "subcategory":"Gym",
            "type":"Entertainment"
        }
    ],
    "sg:phone":"+1 904 745 1688",
    "sg:postcode":"32211",
    "sg:province":"FL",
    "sg:tags":[
        "personal",
        "trainer",
        "fitness"
    ],
    "wof:name":"Matthews, Teresa CPT LMT",
    "wof:placetype":"venue"
},
  "geometry": {"coordinates":[-81.589142,30.333427],"type":"Point"}
}