{
  "type": "Feature",
  "properties": {
    "addr:full":"5345 Palm Way Lake Worth FL 33463",
    "addr:housenumber":"5345",
    "addr:postcode":"33463",
    "addr:street":"Palm Way",
    "iso:country":"US",
    "sg:address":"5345 Palm Way",
    "sg:city":"Lake Worth",
    "sg:classifiers":[
        {
            "category":"Building & Trades",
            "subcategory":"Construction",
            "type":"Services"
        }
    ],
    "sg:phone":"+1 561 439 6059",
    "sg:postcode":"33463",
    "sg:province":"FL",
    "sg:tags":[
        "carpentry",
        "contractor"
    ],
    "wof:name":"Gibb Lloyd P Carpenter",
    "wof:placetype":"venue"
},
  "geometry": {"coordinates":[-80.127922,26.561914],"type":"Point"}
}