{
  "type": "Feature",
  "properties": {
    "iso:country":"US",
    "sg:address":"8084 N Davis Hwy",
    "sg:city":"Pensacola",
    "sg:classifiers":[
        {
            "category":"Manufacturing",
            "subcategory":"Jewelry",
            "type":"Manufacturing & Wholesale Goods"
        },
        {
            "category":"Retail",
            "subcategory":"Repair Shop",
            "type":"Services"
        }
    ],
    "sg:phone":"+1 850 484 3642",
    "sg:postcode":"32514",
    "sg:province":"FL",
    "sg:tags":[
        "casting"
    ],
    "wof:name":"Artistic Jewelers Inc",
    "wof:placetype":"venue"
},
  "geometry": {"coordinates":[-87.22062200000001,30.510373],"type":"Point"}
}