{
  "type": "Feature",
  "properties": {
    "addr:full":"5905 Palmer Blvd Sarasota FL 34232",
    "addr:housenumber":"5905",
    "addr:postcode":"34232",
    "addr:street":"Palmer Blvd",
    "iso:country":"US",
    "sg:address":"5905 Palmer Blvd",
    "sg:city":"Sarasota",
    "sg:classifiers":[
        {
            "category":"Autos & Motor Vehicles",
            "subcategory":"Automobile Sales",
            "type":"Retail Goods"
        }
    ],
    "sg:phone":"+1 941 379 5990",
    "sg:postcode":"34232",
    "sg:province":"FL",
    "sg:tags":[
        "car",
        "dealer"
    ],
    "wof:name":"A To Z Autos",
    "wof:placetype":"venue"
},
  "geometry": {"coordinates":[-82.450108,27.326607],"type":"Point"}
}