{
  "type": "Feature",
  "properties": {
    "addr:full":"5240 Martinique Dr Lakeland FL 33812",
    "addr:housenumber":"5240",
    "addr:postcode":"33812",
    "addr:street":"Martinique Dr",
    "iso:country":"US",
    "sg:address":"5240 Martinique Dr",
    "sg:city":"Lakeland",
    "sg:classifiers":[
        {
            "category":"Retail",
            "subcategory":"Auto Repair",
            "type":"Services"
        }
    ],
    "sg:phone":"+1 863 646 7304",
    "sg:postcode":"33812",
    "sg:province":"FL",
    "sg:tags":[
        "recreational",
        "vehicle"
    ],
    "wof:name":"Rv Juvenator",
    "wof:placetype":"venue"
},
  "geometry": {"coordinates":[-81.90250899999999,27.970965],"type":"Point"}
}