{
  "type": "Feature",
  "properties": {
    "iso:country":"US",
    "sg:address":"107 Westward Dr",
    "sg:city":"Miami",
    "sg:classifiers":[
        {
            "category":"Government",
            "subcategory":"Post Office",
            "type":"Public Place"
        }
    ],
    "sg:phone":"+1 305 882 1352",
    "sg:postcode":"33166",
    "sg:province":"FL",
    "sg:tags":[
        "postal"
    ],
    "wof:name":"US Post Office",
    "wof:placetype":"venue"
},
  "geometry": {"coordinates":[-80.284279,25.821204],"type":"Point"}
}