{
  "type": "Feature",
  "properties": {
    "iso:country":"US",
    "sg:address":"115 Shadow Trl",
    "sg:city":"Longwood",
    "sg:classifiers":[
        {
            "category":"Education",
            "subcategory":"Junior College",
            "type":"Public Place"
        }
    ],
    "sg:phone":"+1 407 260 9390",
    "sg:postcode":"32750",
    "sg:province":"FL",
    "sg:tags":[
        "doll"
    ],
    "wof:name":"Grandma Goldies Dolls",
    "wof:placetype":"venue"
},
  "geometry": {"coordinates":[-81.365784,28.719549],"type":"Point"}
}