{
  "type": "Feature",
  "properties": {
    "iso:country":"US",
    "sg:address":"8008 Mandarin Dr",
    "sg:city":"Orlando",
    "sg:classifiers":[
        {
            "category":"Autos & Motor Vehicles",
            "subcategory":"Automobile Sales",
            "type":"Retail Goods"
        }
    ],
    "sg:phone":"+1 407 352 5129",
    "sg:postcode":"32819",
    "sg:province":"FL",
    "sg:tags":[
        "car",
        "dealer"
    ],
    "wof:name":"B & A Auto Sales Inc",
    "wof:placetype":"venue"
},
  "geometry": {"coordinates":[-81.446248,28.451449],"type":"Point"}
}