{
  "type": "Feature",
  "properties": {
    "iso:country":"US",
    "sg:address":"11290 Bonita Beach Rd",
    "sg:city":"Bonita Springs",
    "sg:classifiers":[
        {
            "category":"Recreation",
            "type":"Entertainment"
        }
    ],
    "sg:phone":"+1 239 949 7299",
    "sg:postcode":"34135",
    "sg:province":"FL",
    "sg:tags":[
        "psychic",
        "medium"
    ],
    "wof:name":"Psychic Consultants",
    "wof:placetype":"venue"
},
  "geometry": {"coordinates":[-81.76831300000001,26.331041],"type":"Point"}
}