{
  "type": "Feature",
  "properties": {
    "iso:country":"US",
    "sg:address":"8348 NW 66th St",
    "sg:city":"Miami",
    "sg:classifiers":[
        {
            "category":"Professional",
            "type":"Services"
        }
    ],
    "sg:phone":"+1 305 406 9443",
    "sg:postcode":"33166",
    "sg:province":"FL",
    "sg:tags":[
        "transportation"
    ],
    "wof:name":"Exfreight Systems",
    "wof:placetype":"venue"
},
  "geometry": {"coordinates":[-80.332992,25.833453],"type":"Point"}
}