{
  "type": "Feature",
  "properties": {
    "iso:country":"US",
    "sg:address":"2109 Honour Rd",
    "sg:city":"Orlando",
    "sg:classifiers":[
        {
            "category":"Food & Beverages",
            "subcategory":"Dairy",
            "type":"Retail Goods"
        }
    ],
    "sg:phone":"+1 407 858 3807",
    "sg:postcode":"32839",
    "sg:province":"FL",
    "sg:tags":[
        "egg"
    ],
    "wof:name":"The Golden Egg",
    "wof:placetype":"venue"
},
  "geometry": {"coordinates":[-81.407211,28.490696],"type":"Point"}
}