{
  "type": "Feature",
  "properties": {
    "iso:country":"US",
    "sg:address":"8614 Cherry Lake Rd",
    "sg:city":"Groveland",
    "sg:classifiers":[
        {
            "category":"Building & Trades",
            "subcategory":"Electrical",
            "type":"Services"
        }
    ],
    "sg:phone":"+1 352 394 6005",
    "sg:postcode":"34736",
    "sg:province":"FL",
    "sg:tags":[
        "industrial",
        "electrician",
        "electric",
        "contractors-commercial"
    ],
    "wof:name":"Moore Electric Service, Inc",
    "wof:placetype":"venue"
},
  "geometry": {"coordinates":[-81.812532,28.60516],"type":"Point"}
}