{
  "type": "Feature",
  "properties": {
    "iso:country":"US",
    "sg:address":"3601 S West Shore Blvd",
    "sg:city":"Tampa",
    "sg:classifiers":[
        {
            "category":"Retail",
            "subcategory":"Laundry & Dry Cleaning",
            "type":"Services"
        }
    ],
    "sg:phone":"+1 813 835 4370",
    "sg:postcode":"33629",
    "sg:province":"FL",
    "sg:tags":[
        "commercial"
    ],
    "sg:website":"http://www.mcnattscleaners.com",
    "wof:name":"Ncnatt's Cleaners",
    "wof:placetype":"venue"
},
  "geometry": {"coordinates":[-82.526718,27.911671],"type":"Point"}
}