{
  "type": "Feature",
  "properties": {
    "iso:country":"US",
    "sg:address":"712 E Turner Camp Rd",
    "sg:city":"Inverness",
    "sg:classifiers":[
        {
            "category":"Shopping",
            "subcategory":"Gifts & Souvenirs",
            "type":"Retail Goods"
        }
    ],
    "sg:phone":"+1 352 341 0238",
    "sg:postcode":"34453",
    "sg:province":"FL",
    "wof:name":"Merrywidow Gift Inc",
    "wof:placetype":"venue"
},
  "geometry": {"coordinates":[-82.33630100000001,28.847649],"type":"Point"}
}