{
  "type": "Feature",
  "properties": {
    "addr:full":"10808 90th Ter Seminole FL 33772",
    "addr:housenumber":"10808",
    "addr:postcode":"33772",
    "addr:street":"90Th Ter",
    "iso:country":"US",
    "sg:address":"10808 90th Ter",
    "sg:city":"Seminole",
    "sg:classifiers":[
        {
            "category":"Organizations",
            "subcategory":"Community Association",
            "type":"Services"
        }
    ],
    "sg:phone":"+1 727 392 6314",
    "sg:postcode":"33772",
    "sg:province":"FL",
    "wof:name":"First Catholic Slovak Assn",
    "wof:placetype":"venue"
},
  "geometry": {"coordinates":[-82.79275699999999,27.854802],"type":"Point"}
}