{
  "type": "Feature",
  "properties": {
    "iso:country":"US",
    "sg:address":"9130 S Dadeland Blvd",
    "sg:city":"Miami",
    "sg:classifiers":[
        {
            "category":"Health Services",
            "subcategory":"Doctor",
            "type":"Services"
        }
    ],
    "sg:phone":"+1 305 670 6735",
    "sg:postcode":"33156",
    "sg:province":"FL",
    "sg:tags":[
        "medical"
    ],
    "wof:name":"MD Datran II Inc",
    "wof:placetype":"venue"
},
  "geometry": {"coordinates":[-80.311947,25.687347],"type":"Point"}
}