{
  "type": "Feature",
  "properties": {
    "iso:country":"US",
    "sg:address":"1600 E Colonial Dr",
    "sg:city":"Orlando",
    "sg:classifiers":[
        {
            "category":"Autos & Motor Vehicles",
            "subcategory":"Fuel & Gas Station",
            "type":"Retail Goods"
        },
        {
            "category":"Food & Beverages",
            "subcategory":"Groceries & Convenience Stores",
            "type":"Retail Goods"
        }
    ],
    "sg:phone":"+1 407 894 3827",
    "sg:postcode":"32803",
    "sg:province":"FL",
    "sg:website":"http://www.mobil.com",
    "wof:name":"Mobil",
    "wof:placetype":"venue"
},
  "geometry": {"coordinates":[-81.360313,28.55312],"type":"Point"}
}