{
  "type": "Feature",
  "properties": {
    "iso:country":"US",
    "sg:address":"11651 56th Ct N",
    "sg:city":"Clearwater",
    "sg:classifiers":[
        {
            "category":"Wholesale",
            "subcategory":"Groceries",
            "type":"Manufacturing & Wholesale Goods"
        }
    ],
    "sg:phone":"+1 727 571 1466",
    "sg:postcode":"33760",
    "sg:province":"FL",
    "sg:tags":[
        "frozen",
        "food"
    ],
    "wof:name":"Tony's Pizza Svc",
    "wof:placetype":"venue"
},
  "geometry": {"coordinates":[-82.709062,27.87814],"type":"Point"}
}