{
  "type": "Feature",
  "properties": {
    "iso:country":"US",
    "sg:address":"440 Seminole Blvd",
    "sg:city":"Largo",
    "sg:classifiers":[
        {
            "category":"Professional",
            "subcategory":"Art Services",
            "type":"Services"
        }
    ],
    "sg:phone":"+1 727 459 6949",
    "sg:postcode":"33709",
    "sg:province":"FL",
    "sg:tags":[
        "artist"
    ],
    "wof:name":"Artistic Features",
    "wof:placetype":"venue"
},
  "geometry": {"coordinates":[-82.78786599999999,27.912265],"type":"Point"}
}