{
  "type": "Feature",
  "properties": {
    "addr:full":"3050 NW 12th St Fort Lauderdale FL 33311",
    "addr:housenumber":"3050",
    "addr:postcode":"33311",
    "addr:street":"Nw 12Th St",
    "iso:country":"US",
    "sg:address":"3050 NW 12th St",
    "sg:city":"Fort Lauderdale",
    "sg:classifiers":[
        {
            "category":"Organizations",
            "subcategory":"Religious Organization",
            "type":"Services"
        }
    ],
    "sg:phone":"+1 954 587 2035",
    "sg:postcode":"33311",
    "sg:province":"FL",
    "wof:name":"Washington Park Nat Church God",
    "wof:placetype":"venue"
},
  "geometry": {"coordinates":[-80.185107,26.139779],"type":"Point"}
}