{
  "type": "Feature",
  "properties": {
    "addr:full":"1085 E 16th St Hialeah FL 33010",
    "addr:housenumber":"1085",
    "addr:postcode":"33010",
    "addr:street":"E 16Th St",
    "iso:country":"US",
    "sg:address":"1085 E 16th St",
    "sg:city":"Hialeah",
    "sg:classifiers":[
        {
            "category":"Wholesale",
            "subcategory":"Machinery & Supplies",
            "type":"Manufacturing & Wholesale Goods"
        }
    ],
    "sg:phone":"+1 305 883 4466",
    "sg:postcode":"33010",
    "sg:province":"FL",
    "sg:tags":[
        "equipment",
        "industrial"
    ],
    "wof:name":"Garcia Equipment Corp",
    "wof:placetype":"venue"
},
  "geometry": {"coordinates":[-80.261385,25.837192],"type":"Point"}
}