{
  "type": "Feature",
  "properties": {
    "addr:full":"16556 SW 51st Ter Miami FL 33185",
    "addr:housenumber":"16556",
    "addr:postcode":"33185",
    "addr:street":"Sw 51St Ter",
    "iso:country":"US",
    "sg:address":"16556 SW 51st Ter",
    "sg:city":"Miami",
    "sg:classifiers":[
        {
            "category":"Professional",
            "type":"Services"
        },
        {
            "category":"Shopping",
            "subcategory":"Party Supplies",
            "type":"Retail Goods"
        },
        {
            "category":"Restaurant",
            "type":"Food & Drink"
        },
        {
            "category":"Retail",
            "subcategory":"Event Space",
            "type":"Services"
        },
        {
            "category":"Personal",
            "type":"Services"
        }
    ],
    "sg:phone":"+1 305 559 5147",
    "sg:postcode":"33185",
    "sg:province":"FL",
    "sg:tags":[
        "favors",
        "wedding",
        "planning",
        "location",
        "reception",
        "caterer",
        "rental"
    ],
    "sg:website":"http://www.paellatropical.com",
    "wof:name":"Paella Tropical Corp",
    "wof:placetype":"venue"
},
  "geometry": {"coordinates":[-80.46221799999999,25.717307],"type":"Point"}
}