{
  "type": "Feature",
  "properties": {
    "addr:full":"1400 US Hwy 441 Lady Lake FL 32159",
    "addr:housenumber":"1400",
    "addr:postcode":"32159",
    "addr:street":"Us Hwy 441",
    "iso:country":"US",
    "sg:address":"1400 US Hwy 441",
    "sg:city":"Lady Lake",
    "sg:classifiers":[
        {
            "category":"Health Services",
            "subcategory":"Doctor",
            "type":"Services"
        }
    ],
    "sg:phone":"+1 352 753 6566",
    "sg:postcode":"32159",
    "sg:province":"FL",
    "sg:tags":[
        "medical"
    ],
    "wof:name":"Workers Health Ctr At Villages",
    "wof:placetype":"venue"
},
  "geometry": {"coordinates":[-81.90758,28.892],"type":"Point"}
}