{
  "type": "Feature",
  "properties": {
    "iso:country":"US",
    "sg:address":"926 SE 23rd St",
    "sg:city":"Ocala",
    "sg:classifiers":[
        {
            "category":"Building & Trades",
            "subcategory":"Construction",
            "type":"Services"
        }
    ],
    "sg:phone":"+1 352 694 1724",
    "sg:postcode":"34471",
    "sg:province":"FL",
    "sg:tags":[
        "hanging",
        "contractor"
    ],
    "wof:name":"Mpsi",
    "wof:placetype":"venue"
},
  "geometry": {"coordinates":[-82.126631,29.165156],"type":"Point"}
}