{
  "type": "Feature",
  "properties": {
    "addr:full":"10055 Mcintosh Rd Dover FL 33527",
    "addr:housenumber":"10055",
    "addr:postcode":"33527",
    "addr:street":"Mcintosh Rd",
    "iso:country":"US",
    "sg:address":"10055 Mcintosh Rd",
    "sg:city":"Dover",
    "sg:classifiers":[
        {
            "category":"Shopping",
            "subcategory":"Computers & Home Electronics",
            "type":"Retail Goods"
        }
    ],
    "sg:phone":"+1 813 986 2846",
    "sg:postcode":"33527",
    "sg:province":"FL",
    "sg:tags":[
        "inventor"
    ],
    "wof:name":"Leon T Swilley Enterprises Inc",
    "wof:placetype":"venue"
},
  "geometry": {"coordinates":[-82.249123,28.040806],"type":"Point"}
}