{
  "type": "Feature",
  "properties": {
    "iso:country":"US",
    "sg:address":"80 W Michigan St",
    "sg:city":"Orlando",
    "sg:classifiers":[
        {
            "category":"Retail",
            "subcategory":"Auto Repair",
            "type":"Services"
        }
    ],
    "sg:phone":"+1 407 425 3061",
    "sg:postcode":"32806",
    "sg:province":"FL",
    "sg:tags":[
        "body",
        "repairing",
        "painting",
        "shop",
        "automobile"
    ],
    "wof:name":"National Paint & Body",
    "wof:placetype":"venue"
},
  "geometry": {"coordinates":[-81.379013,28.512835],"type":"Point"}
}