{
  "type": "Feature",
  "properties": {
    "addr:full":"153 Mills St Groveland FL 34736",
    "addr:housenumber":"153",
    "addr:postcode":"34736",
    "addr:street":"Mills St",
    "iso:country":"US",
    "sg:address":"153 Mills St",
    "sg:city":"Groveland",
    "sg:classifiers":[
        {
            "category":"Social Services",
            "type":"Services"
        }
    ],
    "sg:phone":"+1 352 429 9513",
    "sg:postcode":"34736",
    "sg:province":"FL",
    "wof:name":"Mid Florida Community Services",
    "wof:placetype":"venue"
},
  "geometry": {"coordinates":[-81.852458,28.556393],"type":"Point"}
}