{
  "type": "Feature",
  "properties": {
    "iso:country":"US",
    "sg:address":"13923 SW 140th St",
    "sg:city":"Miami",
    "sg:classifiers":[
        {
            "category":"Food & Beverages",
            "subcategory":"Groceries & Convenience Stores",
            "type":"Retail Goods"
        }
    ],
    "sg:phone":"+1 305 255 7420",
    "sg:postcode":"33186",
    "sg:province":"FL",
    "sg:tags":[
        "juice"
    ],
    "wof:name":"Island Joy Corp",
    "wof:placetype":"venue"
},
  "geometry": {"coordinates":[-80.422149,25.637288],"type":"Point"}
}