{
  "type": "Feature",
  "properties": {
    "iso:country":"US",
    "sg:address":"220 SW 16th Ct",
    "sg:city":"Fort Lauderdale",
    "sg:classifiers":[
        {
            "category":"Manufacturing",
            "subcategory":"Tools & Machinery",
            "type":"Manufacturing & Wholesale Goods"
        }
    ],
    "sg:phone":"+1 954 462 1122",
    "sg:postcode":"33315",
    "sg:province":"FL",
    "sg:tags":[
        "equipment",
        "lighting"
    ],
    "wof:name":"Soundteque International",
    "wof:placetype":"venue"
},
  "geometry": {"coordinates":[-80.144779,26.100963],"type":"Point"}
}