{
  "type": "Feature",
  "properties": {
    "iso:country":"US",
    "sg:address":"5550 Fountains Dr S",
    "sg:city":"Lake Worth",
    "sg:classifiers":[
        {
            "category":"Health Services",
            "subcategory":"Nursing And Care Facility",
            "type":"Services"
        }
    ],
    "sg:phone":"+1 561 433 6477",
    "sg:postcode":"33467",
    "sg:province":"FL",
    "sg:tags":[
        "home",
        "retirement",
        "community"
    ],
    "wof:name":"Retirement Benefits",
    "wof:placetype":"venue"
},
  "geometry": {"coordinates":[-80.15097799999999,26.591077],"type":"Point"}
}