{
  "type": "Feature",
  "properties": {
    "addr:full":"12701 Balm Boyette Rd Riverview FL 33579",
    "addr:housenumber":"12701",
    "addr:postcode":"33579",
    "addr:street":"Balm Boyette Rd",
    "iso:country":"US",
    "sg:address":"12701 Balm Boyette Rd",
    "sg:city":"Riverview",
    "sg:classifiers":[
        {
            "category":"Shopping",
            "subcategory":"Books",
            "type":"Retail Goods"
        }
    ],
    "sg:phone":"+1 813 681 9466",
    "sg:postcode":"33579",
    "sg:province":"FL",
    "sg:tags":[
        "dealer"
    ],
    "wof:name":"Zion's Arsenal",
    "wof:placetype":"venue"
},
  "geometry": {"coordinates":[-81.68732,30.406072],"type":"Point"}
}