{
  "type": "Feature",
  "properties": {
    "iso:country":"US",
    "sg:address":"14581 Walsingham Rd",
    "sg:city":"Largo",
    "sg:classifiers":[
        {
            "category":"Real Estate",
            "subcategory":"Real Estate Agent",
            "type":"Services"
        }
    ],
    "sg:phone":"+1 727 373 3948",
    "sg:postcode":"33774",
    "sg:province":"FL",
    "wof:name":"Exit Realty",
    "wof:placetype":"venue"
},
  "geometry": {"coordinates":[-82.83778100000001,27.880476],"type":"Point"}
}