{
  "type": "Feature",
  "properties": {
    "iso:country":"US",
    "sg:address":"2128 W Brandon Blvd",
    "sg:city":"Brandon",
    "sg:classifiers":[
        {
            "category":"Food & Beverages",
            "subcategory":"Bakery",
            "type":"Retail Goods"
        }
    ],
    "sg:phone":"+1 813 571 0080",
    "sg:postcode":"33511",
    "sg:province":"FL",
    "sg:tags":[
        "doughnut"
    ],
    "wof:name":"Brookhaven Donut Co",
    "wof:placetype":"venue"
},
  "geometry": {"coordinates":[-82.31998400000001,27.938002],"type":"Point"}
}