{
  "type": "Feature",
  "properties": {
    "iso:country":"US",
    "sg:address":"521 Mockingbird Ct",
    "sg:city":"Lake Mary",
    "sg:classifiers":[
        {
            "category":"Building & Trades",
            "subcategory":"Construction",
            "type":"Services"
        }
    ],
    "sg:phone":"+1 407 323 9601",
    "sg:postcode":"32746",
    "sg:province":"FL",
    "sg:tags":[
        "house"
    ],
    "wof:name":"McCombs General Contracting",
    "wof:placetype":"venue"
},
  "geometry": {"coordinates":[-81.315819,28.740697],"type":"Point"}
}