{
  "type": "Feature",
  "properties": {
    "addr:full":"5203 Sago Palm Blvd Tamarac FL 33319",
    "addr:housenumber":"5203",
    "addr:postcode":"33319",
    "addr:street":"Sago Palm Blvd",
    "iso:country":"US",
    "sg:address":"5203 Sago Palm Blvd",
    "sg:city":"Tamarac",
    "sg:classifiers":[
        {
            "category":"Wholesale",
            "subcategory":"Computers",
            "type":"Manufacturing & Wholesale Goods"
        }
    ],
    "sg:phone":"+1 954 731 4827",
    "sg:postcode":"33319",
    "sg:province":"FL",
    "sg:tags":[
        "computer-wholesale",
        "manufacturer"
    ],
    "wof:name":"Rmcs",
    "wof:placetype":"venue"
},
  "geometry": {"coordinates":[-80.219824,26.188481],"type":"Point"}
}