{
  "type": "Feature",
  "properties": {
    "addr:full":"1340 SW Biltmore St Port St Lucie FL 34983",
    "addr:housenumber":"1340",
    "addr:postcode":"34983",
    "addr:street":"Sw Biltmore St;St",
    "iso:country":"US",
    "sg:address":"1340 SW Biltmore St",
    "sg:city":"Port St Lucie",
    "sg:classifiers":[
        {
            "category":"Freight",
            "type":"Transportation"
        }
    ],
    "sg:phone":"+1 772 344 8480",
    "sg:postcode":"34983",
    "sg:province":"FL",
    "sg:tags":[
        "warehouse",
        "public"
    ],
    "wof:name":"American Warehouse Svc Inc",
    "wof:placetype":"venue"
},
  "geometry": {"coordinates":[-80.369834,27.299961],"type":"Point"}
}