{
  "type": "Feature",
  "properties": {
    "addr:full":"2100 Drew St Clearwater FL 33765",
    "addr:housenumber":"2100",
    "addr:postcode":"33765",
    "addr:street":"Drew St",
    "iso:country":"US",
    "sg:address":"2100 Drew St",
    "sg:city":"Clearwater",
    "sg:classifiers":[
        {
            "category":"Autos & Motor Vehicles",
            "subcategory":"Fuel & Gas Station",
            "type":"Retail Goods"
        }
    ],
    "sg:phone":"+1 727 442 1722",
    "sg:postcode":"33765",
    "sg:province":"FL",
    "sg:tags":[
        "oil"
    ],
    "wof:name":"Drew Chevron",
    "wof:placetype":"venue"
},
  "geometry": {"coordinates":[-82.751851,27.968037],"type":"Point"}
}