{
  "type": "Feature",
  "properties": {
    "iso:country":"US",
    "sg:address":"1416 Wilmar Ave",
    "sg:city":"Merritt Island",
    "sg:classifiers":[
        {
            "category":"Communications",
            "subcategory":"Film & Video Production",
            "type":"Services"
        }
    ],
    "sg:phone":"+1 321 453 0882",
    "sg:postcode":"32952",
    "sg:province":"FL",
    "sg:tags":[
        "taping"
    ],
    "wof:name":"Brad Lawrence Productions",
    "wof:placetype":"venue"
},
  "geometry": {"coordinates":[-80.66958099999999,28.376526],"type":"Point"}
}