{
  "type": "Feature",
  "properties": {
    "iso:country":"US",
    "sg:address":"1603 Travelers Palm Dr",
    "sg:city":"Edgewater",
    "sg:classifiers":[
        {
            "category":"Home & Garden",
            "subcategory":"Building Materials",
            "type":"Retail Goods"
        }
    ],
    "sg:phone":"+1 386 405 4544",
    "sg:postcode":"32132",
    "sg:province":"FL",
    "sg:tags":[
        "glass",
        "window",
        "plate"
    ],
    "wof:name":"Rockys Repair Svc",
    "wof:placetype":"venue"
},
  "geometry": {"coordinates":[-80.91481400000001,28.969724],"type":"Point"}
}