{
  "type": "Feature",
  "properties": {
    "addr:full":"1260 Malabar Rd Palm Bay FL 32907",
    "addr:housenumber":"1260",
    "addr:postcode":"32907",
    "addr:street":"Malabar Rd",
    "iso:country":"US",
    "sg:address":"1260 Malabar Rd",
    "sg:city":"Palm Bay",
    "sg:classifiers":[
        {
            "category":"Health Services",
            "subcategory":"Doctor",
            "type":"Services"
        }
    ],
    "sg:phone":"+1 321 727 2020",
    "sg:postcode":"32907",
    "sg:province":"FL",
    "sg:tags":[
        "physician",
        "surgeon"
    ],
    "wof:name":"Florida Eye Assoc",
    "wof:placetype":"venue"
},
  "geometry": {"coordinates":[-80.625544,27.998532],"type":"Point"}
}