{
  "type": "Feature",
  "properties": {
    "addr:full":"419 Poinsettia Rd Belleair FL 33756",
    "addr:housenumber":"419",
    "addr:postcode":"33756",
    "addr:street":"Poinsettia Rd",
    "iso:country":"US",
    "sg:address":"419 Poinsettia Rd",
    "sg:city":"Belleair",
    "sg:classifiers":[
        {
            "category":"Cafe",
            "type":"Food & Drink"
        }
    ],
    "sg:menulink":"http://www.allmenus.com/fl/clearwater/262326-frenchys-saltwater-cafe/menu/",
    "sg:phone":"+1 727 461 6295",
    "sg:postcode":"33756",
    "sg:province":"FL",
    "wof:name":"Frenchy's Saltwater Cafe",
    "wof:placetype":"venue"
},
  "geometry": {"coordinates":[-82.811227,27.932827],"type":"Point"}
}