{
  "type": "Feature",
  "properties": {
    "addr:full":"11234 Auburndale St Spring Hill FL 34609",
    "addr:postcode":"11234;34609",
    "addr:street":"Auburndale St",
    "iso:country":"US",
    "sg:address":"11234 Auburndale St",
    "sg:city":"Spring Hill",
    "sg:classifiers":[
        {
            "category":"Building & Trades",
            "subcategory":"Construction",
            "type":"Services"
        }
    ],
    "sg:phone":"+1 352 684 7652",
    "sg:postcode":"34609",
    "sg:province":"FL",
    "sg:tags":[
        "hanging",
        "contractor"
    ],
    "wof:name":"Lawrence Roberts Painting",
    "wof:placetype":"venue"
},
  "geometry": {"coordinates":[-82.536344,28.479411],"type":"Point"}
}