{
  "type": "Feature",
  "properties": {
    "addr:full":"709 Wechsler Cir Orlando FL 32824",
    "addr:housenumber":"709",
    "addr:postcode":"32824",
    "addr:street":"Wechsler Cir",
    "iso:country":"US",
    "sg:address":"709 Wechsler Cir",
    "sg:city":"Orlando",
    "sg:classifiers":[
        {
            "category":"Professional",
            "subcategory":"Business Services",
            "type":"Services"
        }
    ],
    "sg:phone":"+1 407 251 6357",
    "sg:postcode":"32824",
    "sg:province":"FL",
    "sg:tags":[
        "interior",
        "consultant",
        "design",
        "decorator"
    ],
    "wof:name":"Disegno Casa Bella",
    "wof:placetype":"venue"
},
  "geometry": {"coordinates":[-81.389667,28.395364],"type":"Point"}
}