{
  "type": "Feature",
  "properties": {
    "iso:country":"US",
    "sg:address":"1104 Balboa Ave",
    "sg:city":"Panama City",
    "sg:classifiers":[
        {
            "category":"Social Services",
            "subcategory":"Child Care",
            "type":"Services"
        },
        {
            "category":"Organizations",
            "subcategory":"Religious Organization",
            "type":"Services"
        }
    ],
    "sg:phone":"+1 850 769 6000",
    "sg:postcode":"32401",
    "sg:province":"FL",
    "wof:name":"Panama City Christian School",
    "wof:placetype":"venue"
},
  "geometry": {"coordinates":[-85.675376,30.168985],"type":"Point"}
}