{
  "type": "Feature",
  "properties": {
    "iso:country":"US",
    "sg:address":"201 W Canton Ave Ste 150",
    "sg:city":"Winter Park",
    "sg:classifiers":[
        {
            "category":"Banks & Credit Unions",
            "subcategory":"Investment Brokerage",
            "type":"Services"
        }
    ],
    "sg:phone":"+1 407 699 1515",
    "sg:postcode":"32789",
    "sg:province":"FL",
    "sg:tags":[
        "investing"
    ],
    "wof:name":"Moreno Peelen & Ruggie Winter Park",
    "wof:placetype":"venue"
},
  "geometry": {"coordinates":[-81.35268000000001,28.600463],"type":"Point"}
}