{
  "type": "Feature",
  "properties": {
    "addr:full":"6340 Sweet Maple Ln Boca Raton FL 33433",
    "addr:housenumber":"6340",
    "addr:postcode":"33433",
    "addr:street":"Sweet Maple Ln",
    "iso:country":"US",
    "sg:address":"6340 Sweet Maple Ln",
    "sg:city":"Boca Raton",
    "sg:classifiers":[
        {
            "category":"Wholesale",
            "subcategory":"Non-durable Goods",
            "type":"Manufacturing & Wholesale Goods"
        }
    ],
    "sg:phone":"+1 561 218 1538",
    "sg:postcode":"33433",
    "sg:province":"FL",
    "wof:name":"Allied Marketing Assoc Inc",
    "wof:placetype":"venue"
},
  "geometry": {"coordinates":[-80.142543,26.363938],"type":"Point"}
}