{
  "type": "Feature",
  "properties": {
    "iso:country":"US",
    "sg:address":"2600 NW 87th Ave Ste 12",
    "sg:city":"Doral",
    "sg:classifiers":[
        {
            "category":"Personal",
            "subcategory":"Beauty Salon",
            "type":"Services"
        }
    ],
    "sg:phone":"+1 305 471 4401",
    "sg:postcode":"33172",
    "sg:province":"FL",
    "wof:name":"Imani Santini Hair Studio Inc",
    "wof:placetype":"venue"
},
  "geometry": {"coordinates":[-80.337175,25.799337],"type":"Point"}
}