{
  "type": "Feature",
  "properties": {
    "iso:country":"US",
    "sg:address":"10728 Wiles Rd",
    "sg:city":"Pompano Beach",
    "sg:classifiers":[
        {
            "category":"Building & Trades",
            "subcategory":"Construction",
            "type":"Services"
        }
    ],
    "sg:phone":"+1 954 752 5672",
    "sg:postcode":"33076",
    "sg:province":"FL",
    "sg:tags":[
        "maintenance",
        "contractor"
    ],
    "wof:name":"Coral Tint",
    "wof:placetype":"venue"
},
  "geometry": {"coordinates":[-80.269345,26.287236],"type":"Point"}
}