{
  "type": "Feature",
  "properties": {
    "iso:country":"US",
    "sg:address":"240 SW 124th Ave",
    "sg:city":"Miami",
    "sg:classifiers":[
        {
            "category":"Real Estate",
            "subcategory":"Real Estate Agent",
            "type":"Services"
        }
    ],
    "sg:phone":"+1 305 222 9998",
    "sg:postcode":"33184",
    "sg:province":"FL",
    "sg:tags":[
        "consultant"
    ],
    "wof:name":"Property Tax Specialist Inc",
    "wof:placetype":"venue"
},
  "geometry": {"coordinates":[-80.396891,25.762654],"type":"Point"}
}