{
  "type": "Feature",
  "properties": {
    "iso:country":"US",
    "sg:address":"4107 Neptune Rd",
    "sg:city":"St Cloud",
    "sg:classifiers":[
        {
            "category":"Insurance",
            "subcategory":"Insurance Agent",
            "type":"Services"
        }
    ],
    "sg:phone":"+1 407 891 2324",
    "sg:postcode":"34769",
    "sg:province":"FL",
    "wof:name":"United Insurance & Investment",
    "wof:placetype":"venue"
},
  "geometry": {"coordinates":[-81.30994099999999,28.248673],"type":"Point"}
}