{
  "type": "Feature",
  "properties": {
    "iso:country":"US",
    "sg:address":"5079 W Beaver St",
    "sg:city":"Jacksonville",
    "sg:classifiers":[
        {
            "category":"Retail",
            "subcategory":"Auto Repair",
            "type":"Services"
        }
    ],
    "sg:phone":"+1 904 378 0444",
    "sg:postcode":"32254",
    "sg:province":"FL",
    "sg:tags":[
        "truck"
    ],
    "wof:name":"Michael's Diesel Svc",
    "wof:placetype":"venue"
},
  "geometry": {"coordinates":[-81.74194900000001,30.325748],"type":"Point"}
}