{
  "type": "Feature",
  "properties": {
    "iso:country":"US",
    "sg:address":"12028 S Williams St",
    "sg:city":"Dunnellon",
    "sg:classifiers":[
        {
            "category":"Wholesale",
            "subcategory":"Auto Parts",
            "type":"Manufacturing & Wholesale Goods"
        }
    ],
    "sg:phone":"+1 352 489 5474",
    "sg:postcode":"34432",
    "sg:province":"FL",
    "sg:tags":[
        "used"
    ],
    "wof:name":"Cooper Tire Store",
    "wof:placetype":"venue"
},
  "geometry": {"coordinates":[-82.46226900000001,29.048193],"type":"Point"}
}