{
  "type": "Feature",
  "properties": {
    "iso:country":"US",
    "sg:address":"1751 NW 110th Ave",
    "sg:city":"Miami",
    "sg:classifiers":[
        {
            "category":"Freight",
            "type":"Transportation"
        }
    ],
    "sg:phone":"+1 305 629 8400",
    "sg:postcode":"33172",
    "sg:province":"FL",
    "wof:name":"Green Eyes Express",
    "wof:placetype":"venue"
},
  "geometry": {"coordinates":[-80.374261,25.796441],"type":"Point"}
}