{
  "type": "Feature",
  "properties": {
    "addr:full":"225 Biscayne Blvd Miami FL 33131",
    "addr:housenumber":"225",
    "addr:postcode":"33131",
    "addr:street":"Biscayne Blvd",
    "iso:country":"US",
    "sg:address":"225 Biscayne Blvd",
    "sg:city":"Miami",
    "sg:classifiers":[
        {
            "category":"Building & Trades",
            "subcategory":"Construction",
            "type":"Services"
        }
    ],
    "sg:phone":"+1 305 379 4439",
    "sg:postcode":"33131",
    "sg:province":"FL",
    "sg:tags":[
        "masonry",
        "contractor"
    ],
    "wof:name":"Pompano Masonry",
    "wof:placetype":"venue"
},
  "geometry": {"coordinates":[-80.18720500000001,25.771943],"type":"Point"}
}