{
  "type": "Feature",
  "properties": {
    "iso:country":"US",
    "sg:address":"7600 SW 82nd St",
    "sg:city":"Miami",
    "sg:classifiers":[
        {
            "category":"Building & Trades",
            "subcategory":"Construction",
            "type":"Services"
        },
        {
            "category":"Utilities",
            "subcategory":"Natural Gas",
            "type":"Services"
        },
        {
            "category":"Sports & Exercise",
            "subcategory":"Skate Park",
            "type":"Entertainment"
        },
        {
            "category":"Home & Garden",
            "subcategory":"Household Appliances",
            "type":"Retail Goods"
        },
        {
            "category":"Building & Trades",
            "subcategory":"Plumbing",
            "type":"Services"
        },
        {
            "category":"Home & Garden",
            "subcategory":"Building Materials",
            "type":"Retail Goods"
        },
        {
            "category":"Building & Trades",
            "subcategory":"Cleaning & Sanitation",
            "type":"Services"
        }
    ],
    "sg:phone":"+1 786 525 8276",
    "sg:postcode":"33143",
    "sg:province":"FL",
    "sg:tags":[
        "heater",
        "repair",
        "heating",
        "boilers-repair",
        "system",
        "contractor",
        "equipment",
        "cooling",
        "pump",
        "handyman",
        "specialty",
        "water",
        "heat",
        "air conditioning",
        "supplying",
        "systems-repairing",
        "sale",
        "ventilation",
        "clean",
        "tower"
    ],
    "sg:website":"http://www.miamicooling.com",
    "wof:name":"Miami Cooling - Air Conditioning Repair Service",
    "wof:placetype":"venue"
},
  "geometry": {"coordinates":[-80.31661800000001,25.693948],"type":"Point"}
}