{
  "type": "Feature",
  "properties": {
    "iso:country":"US",
    "sg:address":"118 Jackson Ave",
    "sg:city":"Cape Canaveral",
    "sg:classifiers":[
        {
            "category":"Home & Garden",
            "subcategory":"Household Appliances",
            "type":"Retail Goods"
        },
        {
            "category":"Retail",
            "subcategory":"Repair Shop",
            "type":"Services"
        }
    ],
    "sg:phone":"+1 321 783 1319",
    "sg:postcode":"32920",
    "sg:province":"FL",
    "wof:name":"Canaveral Appliance Service",
    "wof:placetype":"venue"
},
  "geometry": {"coordinates":[-80.60438000000001,28.387206],"type":"Point"}
}