{
  "type": "Feature",
  "properties": {
    "iso:country":"US",
    "sg:address":"3211 Laurie Ave",
    "sg:city":"Panama City Bch",
    "sg:classifiers":[
        {
            "category":"Shopping",
            "subcategory":"Computers & Home Electronics",
            "type":"Retail Goods"
        },
        {
            "category":"Professional",
            "subcategory":"Computer Services",
            "type":"Services"
        }
    ],
    "sg:phone":"+1 850 236 2353",
    "sg:postcode":"32408",
    "sg:province":"FL",
    "sg:tags":[
        "repair"
    ],
    "wof:name":"Personal Computer Systems",
    "wof:placetype":"venue"
},
  "geometry": {"coordinates":[-85.782269,30.169481],"type":"Point"}
}