{
  "type": "Feature",
  "properties": {
    "iso:country":"US",
    "sg:address":"220 S University Dr",
    "sg:city":"Plantation",
    "sg:classifiers":[
        {
            "category":"Recreation",
            "type":"Entertainment"
        }
    ],
    "sg:phone":"+1 954 916 6116",
    "sg:postcode":"33324",
    "sg:province":"FL",
    "sg:tags":[
        "instruction",
        "yoga"
    ],
    "wof:name":"Temple Art Inc",
    "wof:placetype":"venue"
},
  "geometry": {"coordinates":[-80.248076,26.00895],"type":"Point"}
}