{
  "type": "Feature",
  "properties": {
    "iso:country":"US",
    "sg:address":"21 E Lee St",
    "sg:city":"Pensacola",
    "sg:classifiers":[
        {
            "category":"Retail",
            "subcategory":"Funeral Services",
            "type":"Services"
        }
    ],
    "sg:phone":"+1 850 432 7719",
    "sg:postcode":"32501",
    "sg:province":"FL",
    "wof:name":"Crematory Of Northwest Florida",
    "wof:placetype":"venue"
},
  "geometry": {"coordinates":[-87.21744700000001,30.427119],"type":"Point"}
}