{
  "type": "Feature",
  "properties": {
    "addr:full":"1132 Normandy Dr Miami FL 33141",
    "addr:housenumber":"1132",
    "addr:postcode":"33141",
    "addr:street":"Normandy Dr",
    "iso:country":"US",
    "sg:address":"1132 Normandy Dr",
    "sg:city":"Miami",
    "sg:classifiers":[
        {
            "category":"Personal",
            "subcategory":"Beauty Salon",
            "type":"Services"
        }
    ],
    "sg:phone":"+1 305 865 9143",
    "sg:postcode":"33141",
    "sg:province":"FL",
    "sg:tags":[
        "shop"
    ],
    "wof:name":"Hilda's Styling Salon",
    "wof:placetype":"venue"
},
  "geometry": {"coordinates":[-80.13034399999999,25.855639],"type":"Point"}
}