{
  "type": "Feature",
  "properties": {
    "addr:full":"101 N Woodland Blvd Ste 200 Deland FL 32720",
    "addr:housenumber":"101",
    "addr:postcode":"32720",
    "addr:street":"N Woodland Blvd Ste 200",
    "iso:country":"US",
    "sg:address":"101 N Woodland Blvd Ste 200",
    "sg:city":"Deland",
    "sg:classifiers":[
        {
            "category":"Banks & Credit Unions",
            "subcategory":"Atm",
            "type":"Services"
        }
    ],
    "sg:phone":"+1 386 738 1159",
    "sg:postcode":"32720",
    "sg:province":"FL",
    "sg:tags":[
        "bankruptcy"
    ],
    "wof:name":"Dempsey Donald B Jr Atty",
    "wof:placetype":"venue"
},
  "geometry": {"coordinates":[-81.303398,29.028799],"type":"Point"}
}