{
  "type": "Feature",
  "properties": {
    "iso:country":"US",
    "sg:address":"123 S Dixie Hwy",
    "sg:city":"Lake Worth",
    "sg:classifiers":[
        {
            "category":"Building & Trades",
            "subcategory":"Construction",
            "type":"Services"
        }
    ],
    "sg:phone":"+1 561 493 4305",
    "sg:postcode":"33460",
    "sg:province":"FL",
    "sg:tags":[
        "tile",
        "dealer"
    ],
    "wof:name":"Superior Interiors & Floors",
    "wof:placetype":"venue"
},
  "geometry": {"coordinates":[-80.057501,26.613736],"type":"Point"}
}