{
  "type": "Feature",
  "properties": {
    "addr:full":"7630 NW 88th Way Fort Lauderdale FL 33321",
    "addr:housenumber":"7630",
    "addr:postcode":"33321",
    "addr:street":"Nw 88Th Way",
    "iso:country":"US",
    "sg:address":"7630 NW 88th Way",
    "sg:city":"Fort Lauderdale",
    "sg:classifiers":[
        {
            "category":"Manufacturing",
            "subcategory":"Printing",
            "type":"Manufacturing & Wholesale Goods"
        }
    ],
    "sg:phone":"+1 954 726 7676",
    "sg:postcode":"33321",
    "sg:province":"FL",
    "sg:tags":[
        "newspaper"
    ],
    "wof:name":"Labor Tribune News Inc",
    "wof:placetype":"venue"
},
  "geometry": {"coordinates":[-80.274889,26.214719],"type":"Point"}
}