{
  "type": "Feature",
  "properties": {
    "iso:country":"US",
    "sg:address":"1303 Gulf Dr S",
    "sg:city":"Bradenton Beach",
    "sg:classifiers":[
        {
            "category":"Restaurant",
            "type":"Food & Drink"
        }
    ],
    "sg:phone":"+1 941 779 0248",
    "sg:postcode":"34217",
    "sg:province":"FL",
    "sg:tags":[
        "eating"
    ],
    "wof:name":"ORileys Cafe",
    "wof:placetype":"venue"
},
  "geometry": {"coordinates":[-82.695722,27.457651],"type":"Point"}
}