{
  "type": "Feature",
  "properties": {
    "addr:full":"1108 S Magnolia Dr Tallahassee FL 32301",
    "addr:housenumber":"1108",
    "addr:postcode":"32301",
    "addr:street":"S Magnolia Dr",
    "iso:country":"US",
    "sg:address":"1108 S Magnolia Dr",
    "sg:city":"Tallahassee",
    "sg:classifiers":[
        {
            "category":"Restaurant",
            "type":"Food & Drink"
        }
    ],
    "sg:phone":"+1 850 877 5543",
    "sg:postcode":"32301",
    "sg:province":"FL",
    "wof:name":"Catfish Pad",
    "wof:placetype":"venue"
},
  "geometry": {"coordinates":[-84.261848,30.432814],"type":"Point"}
}