{
  "type": "Feature",
  "properties": {
    "addr:full":"1815 University Blvd N Jacksonville FL 32211",
    "addr:housenumber":"1815",
    "addr:postcode":"32211",
    "addr:street":"University Blvd N",
    "iso:country":"US",
    "sg:address":"1815 University Blvd N",
    "sg:city":"Jacksonville",
    "sg:classifiers":[
        {
            "category":"Wholesale",
            "subcategory":"Electrical",
            "type":"Manufacturing & Wholesale Goods"
        }
    ],
    "sg:phone":"+1 904 744 7000",
    "sg:postcode":"32211",
    "sg:province":"FL",
    "sg:tags":[
        "equipment"
    ],
    "wof:name":"A S I",
    "wof:placetype":"venue"
},
  "geometry": {"coordinates":[-81.60248900000001,30.339031],"type":"Point"}
}