{
  "type": "Feature",
  "properties": {
    "iso:country":"US",
    "sg:address":"20449 State Rd 7",
    "sg:city":"Boca Raton",
    "sg:classifiers":[
        {
            "category":"Travel",
            "subcategory":"Travel Agent",
            "type":"Entertainment"
        }
    ],
    "sg:phone":"+1 561 482 0030",
    "sg:postcode":"33498",
    "sg:province":"FL",
    "sg:tags":[
        "agency"
    ],
    "wof:name":"Paace Travel Associates Inc",
    "wof:placetype":"venue"
},
  "geometry": {"coordinates":[-80.203559,26.370502],"type":"Point"}
}