{
  "type": "Feature",
  "properties": {
    "addr:full":"8016 NW 68th St Miami FL 33166",
    "addr:housenumber":"8016",
    "addr:postcode":"33166",
    "addr:street":"Nw 68Th St",
    "iso:country":"US",
    "sg:address":"8016 NW 68th St",
    "sg:city":"Miami",
    "sg:classifiers":[
        {
            "category":"Wholesale",
            "subcategory":"Hardware",
            "type":"Manufacturing & Wholesale Goods"
        },
        {
            "category":"Wholesale",
            "subcategory":"Home Furnishings",
            "type":"Manufacturing & Wholesale Goods"
        }
    ],
    "sg:phone":"+1 305 717 3330",
    "sg:postcode":"33166",
    "sg:province":"FL",
    "sg:tags":[
        "cutlery"
    ],
    "wof:name":"Incametal Products LLC",
    "wof:placetype":"venue"
},
  "geometry": {"coordinates":[-80.329774,25.835196],"type":"Point"}
}