{
  "type": "Feature",
  "properties": {
    "iso:country":"US",
    "sg:address":"1082 3rd St N",
    "sg:city":"Jacksonville Bch",
    "sg:classifiers":[
        {
            "category":"Real Estate",
            "subcategory":"Real Estate Agent",
            "type":"Services"
        }
    ],
    "sg:phone":"+1 904 249 8443",
    "sg:postcode":"32250",
    "sg:province":"FL",
    "wof:name":"Realty Management Group Inc",
    "wof:placetype":"venue"
},
  "geometry": {"coordinates":[-81.393765,30.297583],"type":"Point"}
}