{
  "type": "Feature",
  "properties": {
    "addr:full":"2743 US Hwy 27 Lake Placid FL 33852",
    "addr:housenumber":"2743",
    "addr:postcode":"33852",
    "addr:street":"Us Hwy 27",
    "iso:country":"US",
    "sg:address":"2743 US Hwy 27",
    "sg:city":"Lake Placid",
    "sg:classifiers":[
        {
            "category":"Real Estate",
            "subcategory":"Real Estate Agent",
            "type":"Services"
        }
    ],
    "sg:phone":"+1 863 699 6300",
    "sg:postcode":"33852",
    "sg:province":"FL",
    "wof:name":"Placid Lake Realty",
    "wof:placetype":"venue"
},
  "geometry": {"coordinates":[-81.32874200000001,27.210847],"type":"Point"}
}