{
  "type": "Feature",
  "properties": {
    "addr:full":"1000 Commercial Way Spring Hill FL 34606",
    "addr:housenumber":"1000",
    "addr:postcode":"34606",
    "addr:street":"Commercial Way",
    "iso:country":"US",
    "sg:address":"1000 Commercial Way",
    "sg:city":"Spring Hill",
    "sg:classifiers":[
        {
            "category":"Building & Trades",
            "subcategory":"Equipment Rental",
            "type":"Services"
        }
    ],
    "sg:phone":"+1 352 688 1784",
    "sg:postcode":"34606",
    "sg:province":"FL",
    "sg:tags":[
        "yard"
    ],
    "wof:name":"U-Haul Co",
    "wof:placetype":"venue"
},
  "geometry": {"coordinates":[-82.634429,28.444878],"type":"Point"}
}