{
  "type": "Feature",
  "properties": {
    "addr:full":"9205 133rd Ave N Largo FL 33773",
    "addr:housenumber":"9205",
    "addr:postcode":"33773",
    "addr:street":"133Rd Ave N",
    "iso:country":"US",
    "sg:address":"9205 133rd Ave N",
    "sg:city":"Largo",
    "sg:classifiers":[
        {
            "category":"Local Transit",
            "type":"Transportation"
        }
    ],
    "sg:phone":"+1 727 586 4412",
    "sg:postcode":"33773",
    "sg:province":"FL",
    "sg:tags":[
        "limousine"
    ],
    "wof:name":"National Limousine Inc",
    "wof:placetype":"venue"
},
  "geometry": {"coordinates":[-82.76741699999999,27.894438],"type":"Point"}
}