{
  "type": "Feature",
  "properties": {
    "addr:full":"865 N Courtenay Pkwy Merritt Island FL 32953",
    "addr:housenumber":"865",
    "addr:postcode":"32953",
    "addr:street":"N Courtenay Pkwy",
    "iso:country":"US",
    "sg:address":"865 N Courtenay Pkwy",
    "sg:city":"Merritt Island",
    "sg:classifiers":[
        {
            "category":"Home & Garden",
            "subcategory":"Household Appliances",
            "type":"Retail Goods"
        }
    ],
    "sg:phone":"+1 321 452 9260",
    "sg:postcode":"32953",
    "sg:province":"FL",
    "wof:name":"Al Booths Inc",
    "wof:placetype":"venue"
},
  "geometry": {"coordinates":[-80.70042100000001,28.369657],"type":"Point"}
}