{
  "type": "Feature",
  "properties": {
    "addr:full":"1882 Capital Cir NE Tallahassee FL 32308",
    "addr:housenumber":"1882",
    "addr:postcode":"32308",
    "addr:street":"Capital Cir Ne",
    "iso:country":"US",
    "sg:address":"1882 Capital Cir NE",
    "sg:city":"Tallahassee",
    "sg:classifiers":[
        {
            "category":"Health Services",
            "subcategory":"Clinic",
            "type":"Services"
        }
    ],
    "sg:phone":"+1 850 297 1897",
    "sg:postcode":"32308",
    "sg:province":"FL",
    "sg:tags":[
        "home",
        "care"
    ],
    "wof:name":"Home Instead Senior Care",
    "wof:placetype":"venue"
},
  "geometry": {"coordinates":[-84.23300399999999,30.472643],"type":"Point"}
}