{
  "type": "Feature",
  "properties": {
    "addr:full":"3636 W Flagler St Miami FL 33135",
    "addr:housenumber":"3636",
    "addr:postcode":"33135",
    "addr:street":"W Flagler St",
    "iso:country":"US",
    "sg:address":"3636 W Flagler St",
    "sg:city":"Miami",
    "sg:classifiers":[
        {
            "category":"Professional",
            "subcategory":"Lawyer & Legal Services",
            "type":"Services"
        }
    ],
    "sg:phone":"+1 305 448 8585",
    "sg:postcode":"33135",
    "sg:province":"FL",
    "wof:name":"Lao Raquel Y Atty",
    "wof:placetype":"venue"
},
  "geometry": {"coordinates":[-80.253871,25.771734],"type":"Point"}
}