{
  "type": "Feature",
  "properties": {
    "addr:full":"5545 8th St SW Coral Gables FL 33134",
    "addr:housenumber":"5545",
    "addr:postcode":"33134",
    "addr:street":"8Th St Sw",
    "iso:country":"US",
    "sg:address":"5545 8th St SW",
    "sg:city":"Coral Gables",
    "sg:classifiers":[
        {
            "category":"Organizations",
            "subcategory":"Religious Organization",
            "type":"Services"
        }
    ],
    "sg:phone":"+1 305 262 4744",
    "sg:postcode":"33134",
    "sg:province":"FL",
    "sg:tags":[
        "church"
    ],
    "wof:name":"Florida New Hope",
    "wof:placetype":"venue"
},
  "geometry": {"coordinates":[-80.284888,25.76375],"type":"Point"}
}