{
  "type": "Feature",
  "properties": {
    "addr:full":"10534 Little Rd New Port Richey FL 34654",
    "addr:housenumber":"10534",
    "addr:postcode":"34654",
    "addr:street":"Little Rd",
    "iso:country":"US",
    "sg:address":"10534 Little Rd",
    "sg:city":"New Port Richey",
    "sg:classifiers":[
        {
            "category":"Education",
            "subcategory":"School",
            "type":"Public Place"
        }
    ],
    "sg:phone":"+1 727 862 3852",
    "sg:postcode":"34654",
    "sg:province":"FL",
    "wof:name":"Gulf Coast Christian School",
    "wof:placetype":"venue"
},
  "geometry": {"coordinates":[-82.66594000000001,28.309851],"type":"Point"}
}