{
  "type": "Feature",
  "properties": {
    "iso:country":"US",
    "sg:address":"2146 Fish Eagle St",
    "sg:city":"Clermont",
    "sg:classifiers":[
        {
            "category":"Landmark",
            "subcategory":"Tourist Information",
            "type":"Public Place"
        }
    ],
    "sg:phone":"+1 407 460 4658",
    "sg:postcode":"34714",
    "sg:province":"FL",
    "sg:tags":[
        "promoter",
        "tours-operators"
    ],
    "wof:name":"Jc Town Car Tours Inc",
    "wof:placetype":"venue"
},
  "geometry": {"coordinates":[-81.68367000000001,28.377876],"type":"Point"}
}