{
  "type": "Feature",
  "properties": {
    "iso:country":"US",
    "sg:address":"1840 Peaches Ln",
    "sg:city":"Cantonment",
    "sg:classifiers":[
        {
            "category":"Building & Trades",
            "subcategory":"Construction",
            "type":"Services"
        }
    ],
    "sg:phone":"+1 850 968 6353",
    "sg:postcode":"32533",
    "sg:province":"FL",
    "wof:name":"Campbell Electric Construction",
    "wof:placetype":"venue"
},
  "geometry": {"coordinates":[-87.28000299999999,30.571471],"type":"Point"}
}