{
  "type": "Feature",
  "properties": {
    "iso:country":"US",
    "sg:address":"7960 SW 67th Ter",
    "sg:city":"Miami",
    "sg:classifiers":[
        {
            "category":"Real Estate",
            "subcategory":"Real Estate Services",
            "type":"Services"
        },
        {
            "category":"Real Estate",
            "subcategory":"Real Estate Agent",
            "type":"Services"
        }
    ],
    "sg:phone":"+1 305 270 0710",
    "sg:postcode":"33143",
    "sg:province":"FL",
    "sg:tags":[
        "management"
    ],
    "wof:name":"Paul White Coml Re Seminars",
    "wof:placetype":"venue"
},
  "geometry": {"coordinates":[-80.323448,25.70677],"type":"Point"}
}