{
  "type": "Feature",
  "properties": {
    "iso:country":"US",
    "sg:address":"2634 N Orange Blossom Trl",
    "sg:city":"Kissimmee",
    "sg:classifiers":[
        {
            "category":"Insurance",
            "subcategory":"Insurance Agent",
            "type":"Services"
        }
    ],
    "sg:phone":"+1 409 933 0071",
    "sg:postcode":"34744",
    "sg:province":"FL",
    "sg:tags":[
        "recreational",
        "vehicle"
    ],
    "sg:website":"http://www.apiinc.com",
    "wof:name":"All Purpose Insurance",
    "wof:placetype":"venue"
},
  "geometry": {"coordinates":[-81.403717,28.323947],"type":"Point"}
}