{
  "type": "Feature",
  "properties": {
    "iso:country":"US",
    "sg:address":"430 Packwood Ave",
    "sg:city":"Maitland",
    "sg:classifiers":[
        {
            "category":"Building & Trades",
            "subcategory":"Cleaning & Sanitation",
            "type":"Services"
        }
    ],
    "sg:phone":"+1 407 647 2855",
    "sg:postcode":"32751",
    "sg:province":"FL",
    "sg:tags":[
        "maintenance"
    ],
    "wof:name":"Eppy's General Maintenance",
    "wof:placetype":"venue"
},
  "geometry": {"coordinates":[-81.36247400000001,28.625727],"type":"Point"}
}