{
  "type": "Feature",
  "properties": {
    "addr:full":"1416 Tanager Dr Orlando FL 32803",
    "addr:housenumber":"1416",
    "addr:postcode":"32803",
    "addr:street":"Tanager Dr",
    "iso:country":"US",
    "sg:address":"1416 Tanager Dr",
    "sg:city":"Orlando",
    "sg:classifiers":[
        {
            "category":"Building & Trades",
            "subcategory":"Landscaping Services",
            "type":"Services"
        }
    ],
    "sg:phone":"+1 407 898 8419",
    "sg:postcode":"32803",
    "sg:province":"FL",
    "sg:tags":[
        "landscape"
    ],
    "wof:name":"Bloodwell Land Arch",
    "wof:placetype":"venue"
},
  "geometry": {"coordinates":[-81.339699,28.565131],"type":"Point"}
}