{
  "type": "Feature",
  "properties": {
    "iso:country":"US",
    "sg:address":"1185 Perch Dr",
    "sg:city":"Saint Cloud",
    "sg:classifiers":[
        {
            "category":"Building & Trades",
            "subcategory":"Construction",
            "type":"Services"
        }
    ],
    "sg:phone":"+1 407 498 0284",
    "sg:postcode":"34771",
    "sg:province":"FL",
    "sg:tags":[
        "concrete",
        "contractor"
    ],
    "wof:name":"Ted Springer & Assoc",
    "wof:placetype":"venue"
},
  "geometry": {"coordinates":[-81.182322,28.276956],"type":"Point"}
}