{
  "type": "Feature",
  "properties": {
    "iso:country":"US",
    "sg:address":"2525 S Monroe St",
    "sg:city":"Tallahassee",
    "sg:classifiers":[
        {
            "category":"Personal",
            "subcategory":"Beauty Salon",
            "type":"Services"
        }
    ],
    "sg:phone":"+1 850 878 1475",
    "sg:postcode":"32301",
    "sg:province":"FL",
    "wof:name":"Hair Revolutions",
    "wof:placetype":"venue"
},
  "geometry": {"coordinates":[-84.280551,30.415182],"type":"Point"}
}