{
  "type": "Feature",
  "properties": {
    "addr:full":"311 N Hebrides Pt Inverness FL 34450",
    "addr:housenumber":"311",
    "addr:postcode":"34450",
    "addr:street":"N Hebrides Pt",
    "iso:country":"US",
    "sg:address":"311 N Hebrides Pt",
    "sg:city":"Inverness",
    "sg:phone":"+1 352 344 2347",
    "sg:postcode":"34450",
    "sg:province":"FL",
    "sg:tags":[
        "oil"
    ],
    "wof:name":"Amsoil Dealer",
    "wof:placetype":"venue"
},
  "geometry": {"coordinates":[-82.286951,28.867393],"type":"Point"}
}