{
  "type": "Feature",
  "properties": {
    "iso:country":"US",
    "sg:address":"1222 N Harbor City Blvd",
    "sg:city":"Melbourne",
    "sg:classifiers":[
        {
            "category":"Professional",
            "subcategory":"Engineering",
            "type":"Services"
        }
    ],
    "sg:phone":"+1 321 254 9721",
    "sg:postcode":"32935",
    "sg:province":"FL",
    "sg:tags":[
        "consulting",
        "engineer",
        "surveying"
    ],
    "wof:name":"Outlawrice & Jones Inc",
    "wof:placetype":"venue"
},
  "geometry": {"coordinates":[-80.630312,28.126747],"type":"Point"}
}