{
  "type": "Feature",
  "properties": {
    "addr:full":"11051 SW 142nd Ct Miami FL 33186",
    "addr:housenumber":"11051",
    "addr:postcode":"33186",
    "addr:street":"Sw 142Nd Ct",
    "iso:country":"US",
    "sg:address":"11051 SW 142nd Ct",
    "sg:city":"Miami",
    "sg:classifiers":[
        {
            "category":"Shopping",
            "subcategory":"Discount & Variety Stores",
            "type":"Retail Goods"
        }
    ],
    "sg:phone":"+1 305 978 5329",
    "sg:postcode":"33186",
    "sg:province":"FL",
    "sg:tags":[
        "merchandise",
        "general"
    ],
    "wof:name":"Claudio Costa Pereira Retail",
    "wof:placetype":"venue"
},
  "geometry": {"coordinates":[-80.424758,25.664033],"type":"Point"}
}