{
  "type": "Feature",
  "properties": {
    "iso:country":"US",
    "sg:address":"10947 Beach Blvd",
    "sg:city":"Jacksonville",
    "sg:classifiers":[
        {
            "category":"Building & Trades",
            "subcategory":"Plumbing",
            "type":"Services"
        }
    ],
    "sg:phone":"+1 904 201 1507",
    "sg:postcode":"32246",
    "sg:province":"FL",
    "sg:tags":[
        "system",
        "heating",
        "contractor",
        "subcontractor",
        "air conditioning"
    ],
    "sg:website":"http://www.AirEngineers.com",
    "wof:name":"Air Engineers",
    "wof:placetype":"venue"
},
  "geometry": {"coordinates":[-81.53465,30.286909],"type":"Point"}
}