{
  "type": "Feature",
  "properties": {
    "iso:country":"US",
    "sg:address":"842 N Bronough St",
    "sg:city":"Tallahassee",
    "sg:classifiers":[
        {
            "category":"Building & Trades",
            "subcategory":"Construction",
            "type":"Services"
        }
    ],
    "sg:phone":"+1 850 222 5449",
    "sg:postcode":"32303",
    "sg:province":"FL",
    "sg:tags":[
        "contractor"
    ],
    "wof:name":"J M Tile",
    "wof:placetype":"venue"
},
  "geometry": {"coordinates":[-84.28443900000001,30.453616],"type":"Point"}
}