{
  "type": "Feature",
  "properties": {
    "iso:country":"US",
    "sg:address":"901 Mulberry Ave",
    "sg:city":"Panama City",
    "sg:phone":"+1 850 763 0731",
    "sg:postcode":"32401",
    "sg:province":"FL",
    "sg:tags":[
        "fixture",
        "store"
    ],
    "wof:name":"Store Fixtures",
    "wof:placetype":"venue"
},
  "geometry": {"coordinates":[-85.664863,30.166127],"type":"Point"}
}