{
  "type": "Feature",
  "properties": {
    "iso:country":"US",
    "sg:address":"10477 SW 108th Ave B132",
    "sg:city":"Miami",
    "sg:classifiers":[
        {
            "category":"Building & Trades",
            "subcategory":"Construction",
            "type":"Services"
        }
    ],
    "sg:phone":"+1 786 443 5535",
    "sg:postcode":"33176",
    "sg:province":"FL",
    "sg:tags":[
        "consultant",
        "industrial",
        "contractors-commercial"
    ],
    "wof:name":"Sewer Filters",
    "wof:placetype":"venue"
},
  "geometry": {"coordinates":[-80.369817,25.670506],"type":"Point"}
}