{
  "type": "Feature",
  "properties": {
    "addr:full":"1444 Biscayne Blvd Miami FL 33132",
    "addr:housenumber":"1444",
    "addr:postcode":"33132",
    "addr:street":"Biscayne Blvd",
    "iso:country":"US",
    "sg:address":"1444 Biscayne Blvd",
    "sg:city":"Miami",
    "sg:classifiers":[
        {
            "category":"Professional",
            "subcategory":"Management & Consulting",
            "type":"Services"
        }
    ],
    "sg:phone":"+1 305 372 7611",
    "sg:postcode":"33132",
    "sg:province":"FL",
    "wof:name":"Miami-Dade County Performing A",
    "wof:placetype":"venue"
},
  "geometry": {"coordinates":[-80.189161,25.789435],"type":"Point"}
}