{
  "type": "Feature",
  "properties": {
    "iso:country":"US",
    "sg:address":"1016 N Mcmullen Booth Rd",
    "sg:city":"Clearwater",
    "sg:classifiers":[
        {
            "category":"Shopping",
            "subcategory":"Gifts & Souvenirs",
            "type":"Retail Goods"
        }
    ],
    "sg:phone":"+1 727 796 4723",
    "sg:postcode":"33759",
    "sg:province":"FL",
    "sg:tags":[
        "shop"
    ],
    "wof:name":"Brass Interiors",
    "wof:placetype":"venue"
},
  "geometry": {"coordinates":[-82.709,27.975731],"type":"Point"}
}