{
  "type": "Feature",
  "properties": {
    "addr:full":"1010 S 69th St Tampa FL 33619",
    "addr:housenumber":"1010",
    "addr:postcode":"s;33619",
    "addr:street":"69Th St",
    "iso:country":"US",
    "sg:address":"1010 S 69th St",
    "sg:city":"Tampa",
    "sg:classifiers":[
        {
            "category":"Building & Trades",
            "subcategory":"Construction",
            "type":"Services"
        }
    ],
    "sg:phone":"+1 813 626 1602",
    "sg:postcode":"33619",
    "sg:province":"FL",
    "sg:tags":[
        "concrete",
        "contractor"
    ],
    "wof:name":"Caruso & Sons Inc",
    "wof:placetype":"venue"
},
  "geometry": {"coordinates":[-82.378224,27.940167],"type":"Point"}
}