{
  "type": "Feature",
  "properties": {
    "iso:country":"US",
    "sg:address":"1499 W Royal Palm Rd",
    "sg:city":"Boca Raton",
    "sg:classifiers":[
        {
            "category":"Building & Trades",
            "subcategory":"Equipment Rental",
            "type":"Services"
        }
    ],
    "sg:phone":"+1 561 392 5623",
    "sg:postcode":"33486",
    "sg:province":"FL",
    "wof:name":"Tropical Aviators Inc",
    "wof:placetype":"venue"
},
  "geometry": {"coordinates":[-80.114576,26.349731],"type":"Point"}
}