{
  "type": "Feature",
  "properties": {
    "addr:full":"30247 Emmetts Ct Zephyrhills FL 33543",
    "addr:postcode":"30247;33543",
    "addr:street":"Emmetts Ct",
    "iso:country":"US",
    "sg:address":"30247 Emmetts Ct",
    "sg:city":"Zephyrhills",
    "sg:classifiers":[
        {
            "category":"Professional",
            "subcategory":"Computer Services",
            "type":"Services"
        }
    ],
    "sg:phone":"+1 813 907 1449",
    "sg:postcode":"33543",
    "sg:province":"FL",
    "sg:tags":[
        "related"
    ],
    "wof:name":"Pope Enterprises",
    "wof:placetype":"venue"
},
  "geometry": {"coordinates":[-82.316464,28.185517],"type":"Point"}
}