{
  "type": "Feature",
  "properties": {
    "iso:country":"US",
    "sg:address":"2102 Shepherd Rd",
    "sg:city":"Mulberry",
    "sg:classifiers":[
        {
            "category":"Real Estate",
            "subcategory":"Real Estate Agent",
            "type":"Services"
        }
    ],
    "sg:phone":"+1 863 709 8400",
    "sg:postcode":"33860",
    "sg:province":"FL",
    "wof:name":"Premier Rental Properties",
    "wof:placetype":"venue"
},
  "geometry": {"coordinates":[-81.986735,27.938341],"type":"Point"}
}