{
  "type": "Feature",
  "properties": {
    "addr:full":"15033 S Dixie Hwy Miami FL 33176",
    "addr:housenumber":"15033",
    "addr:postcode":"33176",
    "addr:street":"S Dixie Hwy",
    "iso:country":"US",
    "sg:address":"15033 S Dixie Hwy",
    "sg:city":"Miami",
    "sg:classifiers":[
        {
            "category":"Wholesale",
            "subcategory":"Office Equipment",
            "type":"Manufacturing & Wholesale Goods"
        },
        {
            "category":"Shopping",
            "subcategory":"Stationery & Office Supplies",
            "type":"Retail Goods"
        },
        {
            "category":"Shopping",
            "subcategory":"Computers & Home Electronics",
            "type":"Retail Goods"
        },
        {
            "category":"Professional",
            "subcategory":"Printing & Photocopies",
            "type":"Services"
        },
        {
            "category":"Wholesale",
            "subcategory":"Computers",
            "type":"Manufacturing & Wholesale Goods"
        }
    ],
    "sg:phone":"+1 305 235 3295",
    "sg:postcode":"33176",
    "sg:province":"FL",
    "sg:tags":[
        "register",
        "autographic",
        "duplicating",
        "copying",
        "typewriter",
        "furniture"
    ],
    "sg:website":"http://www.officedepot.com",
    "wof:name":"Office Depot",
    "wof:placetype":"venue"
},
  "geometry": {"coordinates":[-80.340103,25.630501],"type":"Point"}
}