{
  "type": "Feature",
  "properties": {
    "iso:country":"US",
    "sg:address":"600 E New Haven Ave",
    "sg:city":"Melbourne",
    "sg:classifiers":[
        {
            "category":"Shopping",
            "subcategory":"Used Merchandise",
            "type":"Retail Goods"
        }
    ],
    "sg:phone":"+1 321 768 6668",
    "sg:postcode":"32901",
    "sg:province":"FL",
    "sg:tags":[
        "antique"
    ],
    "wof:name":"A-A Auctions & Antiques Inc",
    "wof:placetype":"venue"
},
  "geometry": {"coordinates":[-80.609557,28.078474],"type":"Point"}
}