{
  "type": "Feature",
  "properties": {
    "iso:country":"US",
    "sg:address":"3636 Palmarito St",
    "sg:city":"Miami",
    "sg:classifiers":[
        {
            "category":"Building & Trades",
            "subcategory":"Construction",
            "type":"Services"
        }
    ],
    "sg:phone":"+1 305 442 8468",
    "sg:postcode":"33134",
    "sg:province":"FL",
    "sg:tags":[
        "home",
        "general",
        "contractor"
    ],
    "wof:name":"H & G Construction Intl",
    "wof:placetype":"venue"
},
  "geometry": {"coordinates":[-80.268435,25.73643],"type":"Point"}
}