{
  "type": "Feature",
  "properties": {
    "addr:full":"21301 Powerline Rd Boca Raton FL 33433",
    "addr:housenumber":"21301",
    "addr:postcode":"33433",
    "addr:street":"Powerline Rd",
    "iso:country":"US",
    "sg:address":"21301 Powerline Rd",
    "sg:city":"Boca Raton",
    "sg:classifiers":[
        {
            "category":"Real Estate",
            "subcategory":"Real Estate Services",
            "type":"Services"
        }
    ],
    "sg:phone":"+1 561 470 0811",
    "sg:postcode":"33433",
    "sg:province":"FL",
    "sg:tags":[
        "company",
        "title"
    ],
    "wof:name":"Intracoastal Abstract Co Inc",
    "wof:placetype":"venue"
},
  "geometry": {"coordinates":[-80.15313399999999,26.359873],"type":"Point"}
}