{
  "type": "Feature",
  "properties": {
    "addr:full":"13703 Westshire Dr Tampa FL 33618",
    "addr:housenumber":"13703",
    "addr:postcode":"33618",
    "addr:street":"Westshire Dr",
    "iso:country":"US",
    "sg:address":"13703 Westshire Dr",
    "sg:city":"Tampa",
    "sg:classifiers":[
        {
            "category":"Personal",
            "subcategory":"Beauty Salon",
            "type":"Services"
        }
    ],
    "sg:phone":"+1 813 964 1338",
    "sg:postcode":"33618",
    "sg:province":"FL",
    "sg:tags":[
        "make",
        "studio"
    ],
    "wof:name":"Mary Kay Cosmetics",
    "wof:placetype":"venue"
},
  "geometry": {"coordinates":[-82.497728,28.075092],"type":"Point"}
}