{
  "type": "Feature",
  "properties": {
    "iso:country":"US",
    "sg:address":"6891 Stirling Rd",
    "sg:city":"Davie",
    "sg:classifiers":[
        {
            "category":"Retail",
            "subcategory":"Auto Rental",
            "type":"Services"
        }
    ],
    "sg:phone":"+1 954 321 1420",
    "sg:postcode":"33314",
    "sg:province":"FL",
    "sg:tags":[
        "renting",
        "truck",
        "leasing"
    ],
    "wof:name":"U-Haul Co",
    "wof:placetype":"venue"
},
  "geometry": {"coordinates":[-80.22581599999999,26.046309],"type":"Point"}
}