{
  "type": "Feature",
  "properties": {
    "iso:country":"US",
    "sg:address":"7085 Hennepin Blvd",
    "sg:city":"Orlando",
    "sg:classifiers":[
        {
            "category":"Personal",
            "subcategory":"Nail Salon",
            "type":"Services"
        }
    ],
    "sg:phone":"+1 407 299 4598",
    "sg:postcode":"32818",
    "sg:province":"FL",
    "wof:name":"Tip Top Nails",
    "wof:placetype":"venue"
},
  "geometry": {"coordinates":[-81.478973,28.568013],"type":"Point"}
}