{
  "type": "Feature",
  "properties": {
    "iso:country":"US",
    "sg:address":"7480 Cass Cir",
    "sg:city":"Sarasota",
    "sg:classifiers":[
        {
            "category":"Marine",
            "type":"Transportation"
        }
    ],
    "sg:phone":"+1 941 924 4152",
    "sg:postcode":"34231",
    "sg:province":"FL",
    "sg:tags":[
        "water",
        "transport"
    ],
    "wof:name":"Devil Woman Charters Inc",
    "wof:placetype":"venue"
},
  "geometry": {"coordinates":[-82.508427,27.250428],"type":"Point"}
}