{
  "type": "Feature",
  "properties": {
    "iso:country":"US",
    "sg:address":"4934 Mendavia Dr",
    "sg:city":"Sebring",
    "sg:classifiers":[
        {
            "category":"Building & Trades",
            "subcategory":"Construction",
            "type":"Services"
        }
    ],
    "sg:phone":"+1 863 382 8084",
    "sg:postcode":"33872",
    "sg:province":"FL",
    "sg:tags":[
        "hanging",
        "contractor"
    ],
    "wof:name":"Reimer Painting Plus Inc",
    "wof:placetype":"venue"
},
  "geometry": {"coordinates":[-81.518525,27.542525],"type":"Point"}
}