{
  "type": "Feature",
  "properties": {
    "iso:country":"US",
    "sg:address":"234 US Hwy 98",
    "sg:city":"Destin",
    "sg:classifiers":[
        {
            "category":"Home & Garden",
            "subcategory":"Carpets & Floor Coverings",
            "type":"Retail Goods"
        }
    ],
    "sg:phone":"+1 850 650 1732",
    "sg:postcode":"32541",
    "sg:province":"FL",
    "wof:name":"Bill Wendel Floors Inc",
    "wof:placetype":"venue"
},
  "geometry": {"coordinates":[-86.50751700000001,30.394596],"type":"Point"}
}