{
  "type": "Feature",
  "properties": {
    "iso:country":"US",
    "sg:address":"5866 SW 42nd St",
    "sg:city":"Miami",
    "sg:classifiers":[
        {
            "category":"Banks & Credit Unions",
            "subcategory":"Financial Services",
            "type":"Services"
        }
    ],
    "sg:phone":"+1 305 661 3696",
    "sg:postcode":"33155",
    "sg:province":"FL",
    "sg:tags":[
        "trust",
        "investment",
        "real estate"
    ],
    "wof:name":"Dema Inc",
    "wof:placetype":"venue"
},
  "geometry": {"coordinates":[-80.289269,25.732338],"type":"Point"}
}