{
  "type": "Feature",
  "properties": {
    "addr:full":"7501 Tl Cline Rd Groveland FL 34736",
    "addr:housenumber":"7501",
    "addr:postcode":"34736",
    "addr:street":"Tl Cline Rd",
    "iso:country":"US",
    "sg:address":"7501 Tl Cline Rd",
    "sg:city":"Groveland",
    "sg:classifiers":[
        {
            "category":"Shopping",
            "subcategory":"Jewelry",
            "type":"Retail Goods"
        }
    ],
    "sg:phone":"+1 352 429 8463",
    "sg:postcode":"34736",
    "sg:province":"FL",
    "sg:tags":[
        "clocks"
    ],
    "wof:name":"Central Florida Time Clock",
    "wof:placetype":"venue"
},
  "geometry": {"coordinates":[-81.828368,28.470718],"type":"Point"}
}