{
  "type": "Feature",
  "properties": {
    "addr:full":"6983 103rd St Jacksonville FL 32210",
    "addr:housenumber":"6983",
    "addr:postcode":"32210",
    "addr:street":"103Rd St",
    "iso:country":"US",
    "sg:address":"6983 103rd St",
    "sg:city":"Jacksonville",
    "sg:classifiers":[
        {
            "category":"Health Services",
            "subcategory":"Podiatrist",
            "type":"Services"
        }
    ],
    "sg:phone":"+1 904 778 3000",
    "sg:postcode":"32210",
    "sg:province":"FL",
    "wof:name":"Podiatry Assoc Of Ne Fl Inc",
    "wof:placetype":"venue"
},
  "geometry": {"coordinates":[-81.759603,30.248352],"type":"Point"}
}