{
  "type": "Feature",
  "properties": {
    "iso:country":"US",
    "sg:address":"15371 NE 21st Ave",
    "sg:city":"North Miami Bch",
    "sg:classifiers":[
        {
            "category":"Wholesale",
            "subcategory":"Durable Goods & Equipment",
            "type":"Manufacturing & Wholesale Goods"
        }
    ],
    "sg:phone":"+1 305 899 0999",
    "sg:postcode":"33162",
    "sg:province":"FL",
    "sg:tags":[
        "exporter"
    ],
    "wof:name":"Ruffneck Trailers",
    "wof:placetype":"venue"
},
  "geometry": {"coordinates":[-80.157702,25.91758],"type":"Point"}
}