{
  "type": "Feature",
  "properties": {
    "iso:country":"US",
    "sg:address":"6400 Camellia Garden Dr",
    "sg:city":"Orlando",
    "sg:classifiers":[
        {
            "category":"Real Estate",
            "subcategory":"Real Estate Operator",
            "type":"Services"
        }
    ],
    "sg:phone":"+1 407 996 8188",
    "sg:postcode":"32822",
    "sg:province":"FL",
    "sg:tags":[
        "apartment"
    ],
    "wof:name":"Camelia Pointe Apartments",
    "wof:placetype":"venue"
},
  "geometry": {"coordinates":[-81.29784600000001,28.520473],"type":"Point"}
}