{
  "type": "Feature",
  "properties": {
    "addr:full":"9530 SW 65th St Miami FL 33173",
    "addr:housenumber":"9530",
    "addr:postcode":"33173",
    "addr:street":"Sw 65Th St",
    "iso:country":"US",
    "sg:address":"9530 SW 65th St",
    "sg:city":"Miami",
    "sg:classifiers":[
        {
            "category":"Retail",
            "subcategory":"Auto Repair",
            "type":"Services"
        }
    ],
    "sg:phone":"+1 305 305 0463",
    "sg:postcode":"33173",
    "sg:province":"FL",
    "sg:tags":[
        "engine",
        "engines-rebuild",
        "exchange",
        "rebuilding"
    ],
    "wof:name":"Jorge's Small Engine Repair",
    "wof:placetype":"venue"
},
  "geometry": {"coordinates":[-80.348775,25.707917],"type":"Point"}
}