{
  "type": "Feature",
  "properties": {
    "iso:country":"US",
    "sg:address":"6401 Pumpkin Seed Cir",
    "sg:city":"Boca Raton",
    "sg:classifiers":[
        {
            "category":"Banks & Credit Unions",
            "subcategory":"Investment Brokerage",
            "type":"Services"
        }
    ],
    "sg:phone":"+1 561 394 3287",
    "sg:postcode":"33433",
    "sg:province":"FL",
    "sg:tags":[
        "advisory"
    ],
    "wof:name":"Investors Resource Inc",
    "wof:placetype":"venue"
},
  "geometry": {"coordinates":[-80.145099,26.348975],"type":"Point"}
}