{
  "type": "Feature",
  "properties": {
    "iso:country":"US",
    "sg:address":"104 Deville Dr",
    "sg:city":"Mary Esther",
    "sg:classifiers":[
        {
            "category":"Restaurant",
            "type":"Food & Drink"
        }
    ],
    "sg:phone":"+1 850 244 3344",
    "sg:postcode":"32569",
    "sg:province":"FL",
    "wof:name":"Okki Dokki Korean Restaurant",
    "wof:placetype":"venue"
},
  "geometry": {"coordinates":[-86.75342999999999,30.412025],"type":"Point"}
}