{
  "type": "Feature",
  "properties": {
    "addr:full":"9135 Suncoast Ter Hudson FL 34667",
    "addr:housenumber":"9135",
    "addr:postcode":"34667",
    "addr:street":"Suncoast Ter",
    "iso:country":"US",
    "sg:address":"9135 Suncoast Ter",
    "sg:city":"Hudson",
    "sg:classifiers":[
        {
            "category":"Building & Trades",
            "subcategory":"Cleaning & Sanitation",
            "type":"Services"
        }
    ],
    "sg:phone":"+1 727 860 4174",
    "sg:postcode":"34667",
    "sg:province":"FL",
    "sg:tags":[
        "property",
        "maintenance"
    ],
    "wof:name":"James R Spracklen Property",
    "wof:placetype":"venue"
},
  "geometry": {"coordinates":[-82.660465,28.394791],"type":"Point"}
}