{
  "type": "Feature",
  "properties": {
    "iso:country":"US",
    "sg:address":"337 Alcazar Ave",
    "sg:city":"Coral Gables",
    "sg:classifiers":[
        {
            "category":"Personal",
            "subcategory":"Beauty Salon",
            "type":"Services"
        }
    ],
    "sg:phone":"+1 305 476 8008",
    "sg:postcode":"33134",
    "sg:province":"FL",
    "wof:name":"Salon Bashe & Spa",
    "wof:placetype":"venue"
},
  "geometry": {"coordinates":[-80.262168,25.752825],"type":"Point"}
}