{
  "type": "Feature",
  "properties": {
    "iso:country":"US",
    "sg:address":"1711 Periwinkle Way",
    "sg:city":"Sanibel",
    "sg:classifiers":[
        {
            "category":"Banks & Credit Unions",
            "subcategory":"Bank",
            "type":"Services"
        }
    ],
    "sg:phone":"+1 239 472 8400",
    "sg:postcode":"33957",
    "sg:province":"FL",
    "sg:tags":[
        "loan",
        "real estate"
    ],
    "wof:name":"Pinnacle Mortgage & Capital",
    "wof:placetype":"venue"
},
  "geometry": {"coordinates":[-82.06258099999999,26.440295],"type":"Point"}
}