{
  "type": "Feature",
  "properties": {
    "iso:country":"US",
    "sg:address":"4758 US Hwy 90",
    "sg:city":"Pace",
    "sg:classifiers":[
        {
            "category":"Building & Trades",
            "subcategory":"Construction",
            "type":"Services"
        }
    ],
    "sg:phone":"+1 850 995 9525",
    "sg:postcode":"32571",
    "sg:province":"FL",
    "wof:name":"R & K Portable Buildings LC",
    "wof:placetype":"venue"
},
  "geometry": {"coordinates":[-87.124714,30.603492],"type":"Point"}
}