{
  "type": "Feature",
  "properties": {
    "addr:full":"5590 W Sample Rd Margate FL 33073",
    "addr:housenumber":"5590",
    "addr:postcode":"33073",
    "addr:street":"W Sample Rd Margate",
    "iso:country":"US",
    "sg:address":"5590 W Sample Rd",
    "sg:city":"Margate",
    "sg:classifiers":[
        {
            "category":"Banks & Credit Unions",
            "subcategory":"Bank",
            "type":"Services"
        }
    ],
    "sg:phone":"+1 954 974 9088",
    "sg:postcode":"33073",
    "sg:province":"FL",
    "sg:tags":[
        "national"
    ],
    "wof:name":"Bank Of America",
    "wof:placetype":"venue"
},
  "geometry": {"coordinates":[-80.19968799999999,26.274152],"type":"Point"}
}