{
  "type": "Feature",
  "properties": {
    "addr:full":"1880 Smith Dr North Palm Beach FL 33408",
    "addr:housenumber":"1880",
    "addr:postcode":"33408",
    "addr:street":"Smith Dr North",
    "iso:country":"US",
    "sg:address":"1880 Smith Dr",
    "sg:city":"North Palm Beach",
    "sg:classifiers":[
        {
            "category":"Professional",
            "subcategory":"Business Services",
            "type":"Services"
        }
    ],
    "sg:phone":"+1 561 624 1882",
    "sg:postcode":"33408",
    "sg:province":"FL",
    "sg:tags":[
        "auctioneer"
    ],
    "wof:name":"Advanced Auction Marketing",
    "wof:placetype":"venue"
},
  "geometry": {"coordinates":[-80.062894,26.845079],"type":"Point"}
}