{
  "type": "Feature",
  "properties": {
    "iso:country":"US",
    "sg:address":"10779 Grande Blvd",
    "sg:city":"West Palm Beach",
    "sg:classifiers":[
        {
            "category":"Manufacturing",
            "subcategory":"Rubber & Plastics",
            "type":"Manufacturing & Wholesale Goods"
        }
    ],
    "sg:phone":"+1 561 799 5317",
    "sg:postcode":"33412",
    "sg:province":"FL",
    "sg:tags":[
        "packaging",
        "distributor",
        "rigid"
    ],
    "wof:name":"Packaging Design Group Inc",
    "wof:placetype":"venue"
},
  "geometry": {"coordinates":[-80.21247,26.809423],"type":"Point"}
}