{
  "type": "Feature",
  "properties": {
    "addr:full":"1258 Spoonbill Landings Cir Bradenton FL 34209",
    "addr:housenumber":"1258",
    "addr:postcode":"34209",
    "addr:street":"Spoonbill Landings Cir",
    "iso:country":"US",
    "sg:address":"1258 Spoonbill Landings Cir",
    "sg:city":"Bradenton",
    "sg:classifiers":[
        {
            "category":"Building & Trades",
            "subcategory":"Construction",
            "type":"Services"
        }
    ],
    "sg:phone":"+1 941 794 5381",
    "sg:postcode":"34209",
    "sg:province":"FL",
    "sg:tags":[
        "house"
    ],
    "wof:name":"Walters Services",
    "wof:placetype":"venue"
},
  "geometry": {"coordinates":[-82.682748,27.488223],"type":"Point"}
}