{
  "type": "Feature",
  "properties": {
    "iso:country":"US",
    "sg:address":"2955 46th Ave N",
    "sg:city":"St Petersburg",
    "sg:classifiers":[
        {
            "category":"Wholesale",
            "subcategory":"Plants",
            "type":"Manufacturing & Wholesale Goods"
        }
    ],
    "sg:phone":"+1 727 525 7416",
    "sg:postcode":"33714",
    "sg:province":"FL",
    "sg:tags":[
        "silk",
        "flower",
        "artificial",
        "mfg"
    ],
    "wof:name":"Classic Florals Inc",
    "wof:placetype":"venue"
},
  "geometry": {"coordinates":[-82.673162,27.813885],"type":"Point"}
}