{
  "type": "Feature",
  "properties": {
    "addr:full":"8888 SW 136 St The Falls Miami FL 33176",
    "addr:housenumber":"8888",
    "addr:postcode":"33176",
    "addr:street":"Sw 136 St",
    "iso:country":"US",
    "sg:address":"8888 SW 136 St The Falls",
    "sg:city":"Miami",
    "sg:classifiers":[
        {
            "category":"Shopping",
            "subcategory":"Pets & Pet Supplies",
            "type":"Retail Goods"
        }
    ],
    "sg:phone":"+1 786 293 1222",
    "sg:postcode":"33176",
    "sg:province":"FL",
    "wof:name":"Lupita's Closet",
    "wof:placetype":"venue"
},
  "geometry": {"coordinates":[-80.338437,25.64474],"type":"Point"}
}