{
  "type": "Feature",
  "properties": {
    "addr:full":"12082 SE 61st Ct Belleview FL 34420",
    "addr:postcode":"12082;34420",
    "addr:street":"Se 61St Ct",
    "iso:country":"US",
    "sg:address":"12082 SE 61st Ct",
    "sg:city":"Belleview",
    "sg:classifiers":[
        {
            "category":"Building & Trades",
            "subcategory":"Construction",
            "type":"Services"
        }
    ],
    "sg:phone":"+1 352 266 6655",
    "sg:postcode":"34420",
    "sg:province":"FL",
    "sg:tags":[
        "masonry",
        "contractor"
    ],
    "wof:name":"Kendall Masonry Inc",
    "wof:placetype":"venue"
},
  "geometry": {"coordinates":[-82.049193,29.0461],"type":"Point"}
}