{
  "type": "Feature",
  "properties": {
    "iso:country":"US",
    "sg:address":"3580 66th Ave",
    "sg:city":"Pinellas Park",
    "sg:classifiers":[
        {
            "category":"Retail",
            "subcategory":"Auto Repair",
            "type":"Services"
        }
    ],
    "sg:phone":"+1 727 527 7640",
    "sg:postcode":"33781",
    "sg:province":"FL",
    "sg:tags":[
        "marine",
        "general"
    ],
    "wof:name":"Kens High Tech Auto & Marine",
    "wof:placetype":"venue"
},
  "geometry": {"coordinates":[-82.682861,27.831908],"type":"Point"}
}