{
  "type": "Feature",
  "properties": {
    "iso:country":"US",
    "sg:address":"1890 SW Health Pkwy",
    "sg:city":"Naples",
    "sg:classifiers":[
        {
            "category":"Building & Trades",
            "subcategory":"Construction",
            "type":"Services"
        }
    ],
    "sg:phone":"+1 239 514 4164",
    "sg:postcode":"34109",
    "sg:province":"FL",
    "sg:tags":[
        "contractor"
    ],
    "wof:name":"Chase Builders Corp",
    "wof:placetype":"venue"
},
  "geometry": {"coordinates":[-81.785185,26.272096],"type":"Point"}
}