{
  "type": "Feature",
  "properties": {
    "addr:full":"660 NE Bayberry Ln Jensen Beach FL 34957",
    "addr:housenumber":"660",
    "addr:postcode":"34957",
    "addr:street":"Ne Bayberry Ln",
    "iso:country":"US",
    "sg:address":"660 NE Bayberry Ln",
    "sg:city":"Jensen Beach",
    "sg:classifiers":[
        {
            "category":"Real Estate",
            "subcategory":"Real Estate Operator",
            "type":"Services"
        }
    ],
    "sg:phone":"+1 772 225 7796",
    "sg:postcode":"34957",
    "sg:province":"FL",
    "sg:tags":[
        "building",
        "nonresidential"
    ],
    "wof:name":"Cole Properties LLC",
    "wof:placetype":"venue"
},
  "geometry": {"coordinates":[-80.24370999999999,27.23875],"type":"Point"}
}