{
  "type": "Feature",
  "properties": {
    "iso:country":"US",
    "sg:address":"4618 N Goldenrod Rd",
    "sg:city":"Winter Park",
    "sg:classifiers":[
        {
            "category":"Building & Trades",
            "subcategory":"Construction",
            "type":"Services"
        }
    ],
    "sg:phone":"+1 407 657 4309",
    "sg:postcode":"32792",
    "sg:province":"FL",
    "sg:tags":[
        "hanging",
        "contractor"
    ],
    "wof:name":"Yettos Painting",
    "wof:placetype":"venue"
},
  "geometry": {"coordinates":[-81.285815,28.6066],"type":"Point"}
}