{
  "type": "Feature",
  "properties": {
    "iso:country":"US",
    "sg:address":"3501 SW Archer Rd",
    "sg:city":"Gainesville",
    "sg:classifiers":[
        {
            "category":"Food & Beverages",
            "subcategory":"Specialty",
            "type":"Retail Goods"
        },
        {
            "category":"Shopping",
            "type":"Retail Goods"
        }
    ],
    "sg:phone":"+1 352 372 4591",
    "sg:postcode":"32608",
    "sg:province":"FL",
    "sg:tags":[
        "oriental",
        "merchandise"
    ],
    "wof:name":"Oriental Food & Gift Market",
    "wof:placetype":"venue"
},
  "geometry": {"coordinates":[-82.374833,29.625061],"type":"Point"}
}