{
  "type": "Feature",
  "properties": {
    "iso:country":"US",
    "sg:address":"104 N Adams St",
    "sg:city":"Quincy",
    "sg:classifiers":[
        {
            "category":"Personal",
            "subcategory":"Beauty Salon",
            "type":"Services"
        }
    ],
    "sg:phone":"+1 850 875 3463",
    "sg:postcode":"32351",
    "sg:province":"FL",
    "wof:name":"Quincy's Finest",
    "wof:placetype":"venue"
},
  "geometry": {"coordinates":[-84.57697,30.58919],"type":"Point"}
}