{
  "type": "Feature",
  "properties": {
    "iso:country":"US",
    "sg:address":"6551 Palmer Park Cir",
    "sg:city":"Sarasota",
    "sg:classifiers":[
        {
            "category":"Retail",
            "subcategory":"Repair Shop",
            "type":"Services"
        }
    ],
    "sg:phone":"+1 941 927 3925",
    "sg:postcode":"34238",
    "sg:province":"FL",
    "sg:tags":[
        "cleaners",
        "parts",
        "vacuum"
    ],
    "wof:name":"Rainbow Of Sarasota",
    "wof:placetype":"venue"
},
  "geometry": {"coordinates":[-82.479152,27.25977],"type":"Point"}
}