{
  "type": "Feature",
  "properties": {
    "addr:full":"10948 Dearden Cir Orlando FL 32817",
    "addr:housenumber":"10948",
    "addr:postcode":"32817",
    "addr:street":"Dearden Cir",
    "iso:country":"US",
    "sg:address":"10948 Dearden Cir",
    "sg:city":"Orlando",
    "sg:classifiers":[
        {
            "category":"Insurance",
            "subcategory":"Insurance Agent",
            "type":"Services"
        }
    ],
    "sg:phone":"+1 407 681 6224",
    "sg:postcode":"32817",
    "sg:province":"FL",
    "wof:name":"Machock and Associates",
    "wof:placetype":"venue"
},
  "geometry": {"coordinates":[-81.228652,28.603899],"type":"Point"}
}