{
  "type": "Feature",
  "properties": {
    "addr:full":"1414 Co Hwy 283 N Santa Rosa Beach FL 32459",
    "addr:housenumber":"1414",
    "addr:postcode":"32459",
    "addr:street":"Co Hwy 283 N;Rosa",
    "iso:country":"US",
    "sg:address":"1414 Co Hwy 283 N",
    "sg:city":"Santa Rosa Beach",
    "sg:classifiers":[
        {
            "category":"Personal",
            "subcategory":"Beauty Salon",
            "type":"Services"
        }
    ],
    "sg:phone":"+1 850 231 0000",
    "sg:postcode":"32459",
    "sg:province":"FL",
    "sg:tags":[
        "shop"
    ],
    "wof:name":"Head To Toe Salon Grayton Bch",
    "wof:placetype":"venue"
},
  "geometry": {"coordinates":[-86.15353399999999,30.379416],"type":"Point"}
}