{
  "type": "Feature",
  "properties": {
    "addr:full":"220 W 4th St Apopka FL 32703",
    "addr:housenumber":"220",
    "addr:postcode":"32703",
    "addr:street":"W 4Th St",
    "iso:country":"US",
    "sg:address":"220 W 4th St",
    "sg:city":"Apopka",
    "sg:classifiers":[
        {
            "category":"Real Estate",
            "subcategory":"Real Estate Operator",
            "type":"Services"
        }
    ],
    "sg:phone":"+1 407 889 8555",
    "sg:postcode":"32703",
    "sg:province":"FL",
    "sg:tags":[
        "apartment"
    ],
    "wof:name":"Alabama Street Apartments",
    "wof:placetype":"venue"
},
  "geometry": {"coordinates":[-81.517313,28.673037],"type":"Point"}
}