{
  "type": "Feature",
  "properties": {
    "addr:full":"1725 N 50th St Tampa FL 33619",
    "addr:housenumber":"1725",
    "addr:postcode":"33619",
    "addr:street":"N 50Th St",
    "iso:country":"US",
    "sg:address":"1725 N 50th St",
    "sg:city":"Tampa",
    "sg:classifiers":[
        {
            "category":"Personal",
            "type":"Services"
        }
    ],
    "sg:phone":"+1 813 242 4477",
    "sg:postcode":"33619",
    "sg:province":"FL",
    "sg:tags":[
        "entertainment"
    ],
    "wof:name":"Pleasure Time",
    "wof:placetype":"venue"
},
  "geometry": {"coordinates":[-82.401777,27.961261],"type":"Point"}
}