{
  "type": "Feature",
  "properties": {
    "addr:full":"6009 N Armenia Ave Tampa FL 33604",
    "addr:housenumber":"6009",
    "addr:postcode":"33604",
    "addr:street":"N Armenia Ave",
    "iso:country":"US",
    "sg:address":"6009 N Armenia Ave",
    "sg:city":"Tampa",
    "sg:classifiers":[
        {
            "category":"Shopping",
            "subcategory":"Gifts & Souvenirs",
            "type":"Retail Goods"
        }
    ],
    "sg:phone":"+1 813 879 8733",
    "sg:postcode":"33604",
    "sg:province":"FL",
    "wof:name":"Peace Tree Trading",
    "wof:placetype":"venue"
},
  "geometry": {"coordinates":[-82.48432,28.001963],"type":"Point"}
}