{
  "type": "Feature",
  "properties": {
    "iso:country":"US",
    "sg:address":"5901 SW 74th St",
    "sg:city":"Miami",
    "sg:classifiers":[
        {
            "category":"Real Estate",
            "subcategory":"Real Estate Services",
            "type":"Services"
        }
    ],
    "sg:phone":"+1 305 661 6611",
    "sg:postcode":"33143",
    "sg:province":"FL",
    "sg:tags":[
        "broker",
        "mortgage",
        "title"
    ],
    "sg:website":"www.sunsettitle.com",
    "wof:name":"Sunset Title",
    "wof:placetype":"venue"
},
  "geometry": {"coordinates":[-80.289902,25.7024],"type":"Point"}
}