{
  "type": "Feature",
  "properties": {
    "iso:country":"US",
    "sg:address":"2025 Palm Beach Trace Dr",
    "sg:city":"West Palm Beach",
    "sg:classifiers":[
        {
            "category":"Travel",
            "subcategory":"Hotels & Motels",
            "type":"Entertainment"
        }
    ],
    "sg:phone":"+1 561 682 9990",
    "sg:postcode":"33411",
    "sg:province":"FL",
    "sg:website":"www.hospitality-group.com",
    "wof:name":"Hampton Inn",
    "wof:placetype":"venue"
},
  "geometry": {"coordinates":[-80.226539,26.712889],"type":"Point"}
}