{
  "type": "Feature",
  "properties": {
    "iso:country":"US",
    "sg:address":"101 Aldea Dr",
    "sg:city":"Sebastian",
    "sg:classifiers":[
        {
            "category":"Farming",
            "subcategory":"Fish & Marine Products",
            "type":"Manufacturing & Wholesale Goods"
        }
    ],
    "sg:phone":"+1 772 388 3629",
    "sg:postcode":"32958",
    "sg:province":"FL",
    "sg:tags":[
        "management"
    ],
    "wof:name":"Indian River Critter Getter",
    "wof:placetype":"venue"
},
  "geometry": {"coordinates":[-80.45631,27.759629],"type":"Point"}
}