{
  "type": "Feature",
  "properties": {
    "iso:country":"US",
    "sg:address":"1708 Gulf Beach Blvd",
    "sg:city":"Tarpon Springs",
    "sg:classifiers":[
        {
            "category":"Professional",
            "subcategory":"Management & Consulting",
            "type":"Services"
        }
    ],
    "sg:phone":"+1 727 938 8927",
    "sg:postcode":"34689",
    "sg:province":"FL",
    "sg:tags":[
        "business"
    ],
    "wof:name":"Banther Consulting Corp",
    "wof:placetype":"venue"
},
  "geometry": {"coordinates":[-82.78543500000001,28.147358],"type":"Point"}
}