{
  "type": "Feature",
  "properties": {
    "iso:country":"US",
    "sg:address":"714 Hillpoint Way",
    "sg:city":"Brandon",
    "sg:classifiers":[
        {
            "category":"Freight",
            "type":"Transportation"
        }
    ],
    "sg:phone":"+1 813 571 9561",
    "sg:postcode":"33510",
    "sg:province":"FL",
    "sg:tags":[
        "operator",
        "local",
        "trucking"
    ],
    "wof:name":"D & N Trucking Inc",
    "wof:placetype":"venue"
},
  "geometry": {"coordinates":[-82.272706,27.950982],"type":"Point"}
}