{
  "type": "Feature",
  "properties": {
    "iso:country":"US",
    "sg:address":"2160 NW 22nd St",
    "sg:city":"Pompano Beach",
    "sg:classifiers":[
        {
            "category":"Manufacturing",
            "subcategory":"Metals",
            "type":"Manufacturing & Wholesale Goods"
        }
    ],
    "sg:phone":"+1 954 984 4111",
    "sg:postcode":"33069",
    "sg:province":"FL",
    "sg:tags":[
        "hardware",
        "tool",
        "product",
        "flooring",
        "mfg"
    ],
    "wof:name":"9021-3042 Quebec - Ica Group",
    "wof:placetype":"venue"
},
  "geometry": {"coordinates":[-80.154511,26.25739],"type":"Point"}
}