{
  "type": "Feature",
  "properties": {
    "addr:full":"11180 S Florida Ave Floral City FL 34436",
    "addr:housenumber":"11180",
    "addr:postcode":"34436",
    "addr:street":"S Florida Ave",
    "iso:country":"US",
    "sg:address":"11180 S Florida Ave",
    "sg:city":"Floral City",
    "sg:classifiers":[
        {
            "category":"Retail",
            "subcategory":"Auto Repair",
            "type":"Services"
        }
    ],
    "sg:phone":"+1 352 726 0692",
    "sg:postcode":"34436",
    "sg:province":"FL",
    "sg:tags":[
        "repairing",
        "automobile"
    ],
    "wof:name":"Chilson's Garage",
    "wof:placetype":"venue"
},
  "geometry": {"coordinates":[-82.31456300000001,28.701925],"type":"Point"}
}