{
  "type": "Feature",
  "properties": {
    "addr:full":"8311 NW 64th St Miami FL 33166",
    "addr:housenumber":"8311",
    "addr:postcode":"33166",
    "addr:street":"Nw 64Th St",
    "iso:country":"US",
    "sg:address":"8311 NW 64th St",
    "sg:city":"Miami",
    "sg:classifiers":[
        {
            "category":"Building & Trades",
            "subcategory":"Plumbing",
            "type":"Services"
        }
    ],
    "sg:phone":"+1 305 477 8308",
    "sg:postcode":"33166",
    "sg:province":"FL",
    "sg:tags":[
        "air",
        "conditioning",
        "contractor"
    ],
    "wof:name":"Coastal A/C & Refrigeration",
    "wof:placetype":"venue"
},
  "geometry": {"coordinates":[-80.331948,25.831746],"type":"Point"}
}