{
  "type": "Feature",
  "properties": {
    "iso:country":"US",
    "sg:address":"601 Litchfield Rd",
    "sg:city":"Tallahassee",
    "sg:classifiers":[
        {
            "category":"Insurance",
            "subcategory":"Insurance Agent",
            "type":"Services"
        }
    ],
    "sg:phone":"+1 850 222 0050",
    "sg:postcode":"32312",
    "sg:province":"FL",
    "sg:tags":[
        "adjuster"
    ],
    "wof:name":"Property Damage Appraisers Inc",
    "wof:placetype":"venue"
},
  "geometry": {"coordinates":[-84.30091,30.495669],"type":"Point"}
}