{
  "type": "Feature",
  "properties": {
    "addr:full":"2760 Edgewood Ave W Jacksonville FL 32209",
    "addr:housenumber":"2760",
    "addr:postcode":"32209",
    "addr:street":"Edgewood Ave W",
    "iso:country":"US",
    "sg:address":"2760 Edgewood Ave W",
    "sg:city":"Jacksonville",
    "sg:classifiers":[
        {
            "category":"Social Services",
            "subcategory":"Child Care",
            "type":"Services"
        }
    ],
    "sg:phone":"+1 904 765 3225",
    "sg:postcode":"32209",
    "sg:province":"FL",
    "sg:tags":[
        "kindergarten",
        "academic",
        "school"
    ],
    "wof:name":"Ephesus Junior Academy",
    "wof:placetype":"venue"
},
  "geometry": {"coordinates":[-81.70997199999999,30.377547],"type":"Point"}
}