{
  "type": "Feature",
  "properties": {
    "addr:full":"86 Indian Trce Weston FL 33326",
    "addr:housenumber":"86",
    "addr:postcode":"33326",
    "addr:street":"Indian Trce",
    "iso:country":"US",
    "sg:address":"86 Indian Trce",
    "sg:city":"Weston",
    "sg:classifiers":[
        {
            "category":"Personal",
            "subcategory":"Nail Salon",
            "type":"Services"
        }
    ],
    "sg:phone":"+1 954 659 1224",
    "sg:postcode":"33326",
    "sg:province":"FL",
    "wof:name":"Akema Corp",
    "wof:placetype":"venue"
},
  "geometry": {"coordinates":[-80.40177,26.130911],"type":"Point"}
}