{
  "type": "Feature",
  "properties": {
    "addr:full":"515 Myrtle Ave Green Cove Spgs FL 32043",
    "addr:housenumber":"515",
    "addr:postcode":"32043",
    "addr:street":"Myrtle Ave Green Cove Spgs",
    "iso:country":"US",
    "sg:address":"515 Myrtle Ave",
    "sg:city":"Green Cove Spgs",
    "sg:classifiers":[
        {
            "category":"Building & Trades",
            "subcategory":"Cleaning & Sanitation",
            "type":"Services"
        }
    ],
    "sg:phone":"+1 904 284 5808",
    "sg:postcode":"32043",
    "sg:province":"FL",
    "sg:tags":[
        "house"
    ],
    "wof:name":"First Coast Home Svc",
    "wof:placetype":"venue"
},
  "geometry": {"coordinates":[-81.679766,30.000705],"type":"Point"}
}