{
  "type": "Feature",
  "properties": {
    "iso:country":"US",
    "sg:address":"1825 Hilltop Dr",
    "sg:city":"Mount Dora",
    "sg:classifiers":[
        {
            "category":"Home & Garden",
            "subcategory":"Carpets & Floor Coverings",
            "type":"Retail Goods"
        }
    ],
    "sg:phone":"+1 352 383 2488",
    "sg:postcode":"32757",
    "sg:province":"FL",
    "wof:name":"Extraordinary Floors Inc",
    "wof:placetype":"venue"
},
  "geometry": {"coordinates":[-81.65210399999999,28.812695],"type":"Point"}
}