{
  "type": "Feature",
  "properties": {
    "addr:full":"8831 W 58th St Hialeah FL 33012",
    "addr:housenumber":"8831",
    "addr:postcode":"33012",
    "addr:street":"W 58Th St",
    "iso:country":"US",
    "sg:address":"8831 W 58th St",
    "sg:city":"Hialeah",
    "sg:classifiers":[
        {
            "category":"Government",
            "subcategory":"Office",
            "type":"Public Place"
        }
    ],
    "sg:phone":"+1 305 594 1566",
    "sg:postcode":"33012",
    "sg:province":"FL",
    "sg:tags":[
        "parish",
        "government-county"
    ],
    "sg:website":"http://www.miamidade.gov",
    "wof:name":"Dade County Waste Management",
    "wof:placetype":"venue"
},
  "geometry": {"coordinates":[-80.299515,25.875215],"type":"Point"}
}