{
  "type": "Feature",
  "properties": {
    "addr:full":"4955 US Hwy 90 Milton FL 32571",
    "addr:housenumber":"4955",
    "addr:postcode":"32571",
    "addr:street":"Us Hwy 90",
    "iso:country":"US",
    "sg:address":"4955 US Hwy 90",
    "sg:city":"Milton",
    "sg:classifiers":[
        {
            "category":"Restaurant",
            "type":"Food & Drink"
        }
    ],
    "sg:phone":"+1 850 748 2872",
    "sg:postcode":"32571",
    "sg:province":"FL",
    "sg:tags":[
        "eating"
    ],
    "wof:name":"Ryans",
    "wof:placetype":"venue"
},
  "geometry": {"coordinates":[-87.11770199999999,30.603224],"type":"Point"}
}