{
  "type": "Feature",
  "properties": {
    "iso:country":"US",
    "sg:address":"480 Faith Ave",
    "sg:city":"Osprey",
    "sg:classifiers":[
        {
            "category":"Building & Trades",
            "subcategory":"Landscaping Services",
            "type":"Services"
        }
    ],
    "sg:phone":"+1 941 924 7132",
    "sg:postcode":"34229",
    "sg:province":"FL",
    "sg:tags":[
        "tree"
    ],
    "wof:name":"Sarasota Tree Svc Inc",
    "wof:placetype":"venue"
},
  "geometry": {"coordinates":[-82.476861,27.19295],"type":"Point"}
}