{
  "type": "Feature",
  "properties": {
    "iso:country":"US",
    "sg:address":"327 Horsetail Ave",
    "sg:city":"Middleburg",
    "sg:classifiers":[
        {
            "category":"Building & Trades",
            "subcategory":"Landscaping Services",
            "type":"Services"
        }
    ],
    "sg:phone":"+1 904 716 4279",
    "sg:postcode":"32068",
    "sg:province":"FL",
    "wof:name":"Janelle Lawn Service",
    "wof:placetype":"venue"
},
  "geometry": {"coordinates":[-81.90863299999999,30.064895],"type":"Point"}
}