{
  "type": "Feature",
  "properties": {
    "addr:full":"8932 SW 97th Ave Miami FL 33176",
    "addr:housenumber":"8932",
    "addr:postcode":"33176",
    "addr:street":"Sw 97Th Ave",
    "iso:country":"US",
    "sg:address":"8932 SW 97th Ave",
    "sg:city":"Miami",
    "sg:classifiers":[
        {
            "category":"Health Services",
            "subcategory":"Doctor",
            "type":"Services"
        }
    ],
    "sg:phone":"+1 305 270 3436",
    "sg:postcode":"33176",
    "sg:province":"FL",
    "sg:tags":[
        "physician",
        "radiology",
        "pediatrics-radiology",
        "surgeons",
        "surgeon"
    ],
    "wof:name":"Marisa Alonso Md",
    "wof:placetype":"venue"
},
  "geometry": {"coordinates":[-80.350128,25.686494],"type":"Point"}
}