{
  "type": "Feature",
  "properties": {
    "addr:full":"27212 Hickory Hill Rd Brooksville FL 34602",
    "addr:housenumber":"27212",
    "addr:postcode":"34602",
    "addr:street":"Hickory Hill Rd",
    "iso:country":"US",
    "sg:address":"27212 Hickory Hill Rd",
    "sg:city":"Brooksville",
    "sg:classifiers":[
        {
            "category":"Wholesale",
            "subcategory":"Seafood",
            "type":"Manufacturing & Wholesale Goods"
        }
    ],
    "sg:phone":"+1 352 799 1376",
    "sg:postcode":"34602",
    "sg:province":"FL",
    "wof:name":"Shoreline Sales",
    "wof:placetype":"venue"
},
  "geometry": {"coordinates":[-82.288957,28.4787],"type":"Point"}
}