{
  "type": "Feature",
  "properties": {
    "addr:full":"12450 SW 152nd St Miami FL 33177",
    "addr:housenumber":"12450",
    "addr:postcode":"33177",
    "addr:street":"Sw 152Nd St",
    "iso:country":"US",
    "sg:address":"12450 SW 152nd St",
    "sg:city":"Miami",
    "sg:classifiers":[
        {
            "category":"Museum",
            "type":"Entertainment"
        }
    ],
    "sg:phone":"+1 305 253 0063",
    "sg:postcode":"33177",
    "sg:province":"FL",
    "sg:website":"www.gcrm.org",
    "wof:name":"Gold Coast Railroad Museum",
    "wof:placetype":"venue"
},
  "geometry": {"coordinates":[-80.394203,25.6269],"type":"Point"}
}