{
  "type": "Feature",
  "properties": {
    "addr:city":"Miami",
    "addr:full":"12450 Sw 152Nd St Miami, Fl 33177-1402",
    "addr:house_number":"12450",
    "addr:housenumber":"12450",
    "addr:phone":"+1 305-253-0063",
    "addr:postcode":"33177-1402",
    "addr:road":"Sw 152Nd St",
    "addr:state":"FL",
    "addr:street":"Sw 152Nd St",
    "iso:country":"US",
    "sg:address":"12450 SW 152nd St",
    "sg:city":"Miami",
    "sg:classifiers":[
        {
            "category":"Museum",
            "type":"Entertainment"
        }
    ],
    "sg:phone":"+1 305 253 0063",
    "sg:postcode":"33177",
    "sg:province":"FL",
    "sg:website":"www.gcrm.org",
    "wof:airports":[
        102531023,
        102532907
    ],
    "wof:name":"Gold Coast Railroad Museum",
    "wof:placetype":"venue"
},
  "geometry": {"coordinates":[-80.39748,25.62127],"type":"Point"}
}