{
  "type": "Feature",
  "properties": {
    "iso:country":"US",
    "sg:address":"1882 Murrell Rd",
    "sg:city":"Rockledge",
    "sg:classifiers":[
        {
            "category":"Building & Trades",
            "subcategory":"Construction",
            "type":"Services"
        }
    ],
    "sg:phone":"+1 321 452 2917",
    "sg:postcode":"32955",
    "sg:province":"FL",
    "sg:tags":[
        "layer",
        "carpet"
    ],
    "wof:name":"Dominick S Giunta Carpet",
    "wof:placetype":"venue"
},
  "geometry": {"coordinates":[-80.723314,28.325765],"type":"Point"}
}