{
  "type": "Feature",
  "properties": {
    "iso:country":"US",
    "sg:address":"8249 NW 36th St",
    "sg:city":"Doral",
    "sg:classifiers":[
        {
            "category":"Health Services",
            "subcategory":"Health Practitioner",
            "type":"Services"
        }
    ],
    "sg:phone":"+1 305 599 1970",
    "sg:postcode":"33166",
    "sg:province":"FL",
    "sg:tags":[
        "psychologist"
    ],
    "wof:name":"Jose J Dergan",
    "wof:placetype":"venue"
},
  "geometry": {"coordinates":[-80.33007000000001,25.809875],"type":"Point"}
}