{
  "type": "Feature",
  "properties": {
    "addr:full":"5837 Windermere Dr Palm Harbor FL 34685",
    "addr:housenumber":"5837",
    "addr:postcode":"34685",
    "addr:street":"Windermere Dr",
    "iso:country":"US",
    "sg:address":"5837 Windermere Dr",
    "sg:city":"Palm Harbor",
    "sg:classifiers":[
        {
            "category":"Wholesale",
            "subcategory":"Non-durable Goods",
            "type":"Manufacturing & Wholesale Goods"
        }
    ],
    "sg:phone":"+1 727 787 1822",
    "sg:postcode":"34685",
    "sg:province":"FL",
    "wof:name":"Supply Line Distributors Inc",
    "wof:placetype":"venue"
},
  "geometry": {"coordinates":[-82.669371,28.10438],"type":"Point"}
}