{
  "type": "Feature",
  "properties": {
    "iso:country":"US",
    "sg:address":"4040 SE 20th Ter",
    "sg:city":"Ocala",
    "sg:classifiers":[
        {
            "category":"Arts & Performance",
            "subcategory":"Art Gallery",
            "type":"Entertainment"
        }
    ],
    "sg:phone":"+1 352 622 5125",
    "sg:postcode":"34480",
    "sg:province":"FL",
    "sg:tags":[
        "fine",
        "artist"
    ],
    "wof:name":"Free Spirit Rainbow Art",
    "wof:placetype":"venue"
},
  "geometry": {"coordinates":[-82.10961500000001,29.147946],"type":"Point"}
}