{
  "type": "Feature",
  "properties": {
    "addr:full":"1900 Tamiami Trl Port Charlotte FL 33948",
    "addr:postcode":"1900;33948",
    "addr:street":"Tamiami Trl",
    "iso:country":"US",
    "sg:address":"1900 Tamiami Trl",
    "sg:city":"Port Charlotte",
    "sg:classifiers":[
        {
            "category":"Personal",
            "type":"Services"
        }
    ],
    "sg:phone":"+1 941 613 2896",
    "sg:postcode":"33948",
    "sg:province":"FL",
    "sg:tags":[
        "control",
        "weight"
    ],
    "wof:name":"LA Weight Loss Ctr",
    "wof:placetype":"venue"
},
  "geometry": {"coordinates":[-82.130887,27.005332],"type":"Point"}
}