{
  "type": "Feature",
  "properties": {
    "addr:full":"43227 Ratliff Rd Callahan FL 32011",
    "addr:postcode":"43227;32011",
    "addr:street":"Ratliff Rd",
    "iso:country":"US",
    "sg:address":"43227 Ratliff Rd",
    "sg:city":"Callahan",
    "sg:classifiers":[
        {
            "category":"Personal",
            "subcategory":"Beauty Salon",
            "type":"Services"
        }
    ],
    "sg:phone":"+1 904 879 2125",
    "sg:postcode":"32011",
    "sg:province":"FL",
    "wof:name":"Ruby's Beauty Shop",
    "wof:placetype":"venue"
},
  "geometry": {"coordinates":[-81.83062700000001,30.488076],"type":"Point"}
}