{
  "type": "Feature",
  "properties": {
    "addr:full":"408 Manatee Ave E Bradenton FL 34208",
    "addr:housenumber":"408",
    "addr:postcode":"34208",
    "addr:street":"Manatee Ave E",
    "iso:country":"US",
    "sg:address":"408 Manatee Ave E",
    "sg:city":"Bradenton",
    "sg:classifiers":[
        {
            "category":"Health Services",
            "subcategory":"Doctor",
            "type":"Services"
        }
    ],
    "sg:phone":"+1 941 748 1331",
    "sg:postcode":"34208",
    "sg:province":"FL",
    "sg:tags":[
        "physician",
        "surgeon",
        "medical"
    ],
    "wof:name":"Manatee Internal Medicine PA",
    "wof:placetype":"venue"
},
  "geometry": {"coordinates":[-82.558785,27.49514],"type":"Point"}
}