{
  "type": "Feature",
  "properties": {
    "iso:country":"US",
    "sg:address":"143 Deerfield Dr",
    "sg:city":"Jupiter",
    "sg:classifiers":[
        {
            "category":"Retail",
            "subcategory":"Animal Services",
            "type":"Services"
        }
    ],
    "sg:phone":"+1 561 747 9408",
    "sg:postcode":"33458",
    "sg:province":"FL",
    "sg:tags":[
        "specialty"
    ],
    "wof:name":"Carls Orange Blossom Honey",
    "wof:placetype":"venue"
},
  "geometry": {"coordinates":[-80.13114899999999,26.919522],"type":"Point"}
}