{
  "type": "Feature",
  "properties": {
    "iso:country":"US",
    "sg:address":"4104 Dahoon Holly Ct",
    "sg:city":"Bonita Springs",
    "sg:classifiers":[
        {
            "category":"Banks & Credit Unions",
            "subcategory":"Investment Brokerage",
            "type":"Services"
        }
    ],
    "sg:phone":"+1 239 949 2773",
    "sg:postcode":"34134",
    "sg:province":"FL",
    "sg:tags":[
        "advisory"
    ],
    "wof:name":"Beach & Beach Financial Svc",
    "wof:placetype":"venue"
},
  "geometry": {"coordinates":[-81.821473,26.399831],"type":"Point"}
}