{
  "type": "Feature",
  "properties": {
    "iso:country":"US",
    "sg:address":"707 Pennsylvania Ave",
    "sg:city":"Altamonte Springs",
    "sg:classifiers":[
        {
            "category":"Health Services",
            "subcategory":"Dentist",
            "type":"Services"
        }
    ],
    "sg:phone":"+1 407 478 5002",
    "sg:postcode":"32701",
    "sg:province":"FL",
    "wof:name":"Krieger Jared DMD",
    "wof:placetype":"venue"
},
  "geometry": {"coordinates":[-81.365667,28.651183],"type":"Point"}
}