{
  "type": "Feature",
  "properties": {
    "addr:full":"2375 Ian Dr Tallahassee FL 32303",
    "addr:housenumber":"2375",
    "addr:postcode":"32303",
    "addr:street":"Ian Dr",
    "iso:country":"US",
    "sg:address":"2375 Ian Dr",
    "sg:city":"Tallahassee",
    "sg:classifiers":[
        {
            "category":"Restaurant",
            "type":"Food & Drink"
        }
    ],
    "sg:phone":"+1 850 422 1952",
    "sg:postcode":"32303",
    "sg:province":"FL",
    "sg:tags":[
        "eating"
    ],
    "wof:name":"Rafah African & Carribbean RES",
    "wof:placetype":"venue"
},
  "geometry": {"coordinates":[-84.328132,30.46956],"type":"Point"}
}