{
  "type": "Feature",
  "properties": {
    "iso:country":"US",
    "sg:address":"7699 S Orange Blossom Trl",
    "sg:city":"Orlando",
    "sg:classifiers":[
        {
            "category":"Restaurant",
            "type":"Food & Drink"
        }
    ],
    "sg:phone":"+1 407 888 2820",
    "sg:postcode":"32809",
    "sg:province":"FL",
    "wof:name":"Back Yard Burgers",
    "wof:placetype":"venue"
},
  "geometry": {"coordinates":[-81.399271,28.455773],"type":"Point"}
}