{
  "type": "Feature",
  "properties": {
    "iso:country":"US",
    "sg:address":"30 NE 1st Ave",
    "sg:city":"Hallandale",
    "sg:classifiers":[
        {
            "category":"Shopping",
            "subcategory":"Clothing, Apparel, & Fashions",
            "type":"Retail Goods"
        }
    ],
    "sg:phone":"+1 954 456 6999",
    "sg:postcode":"33009",
    "sg:province":"FL",
    "wof:name":"Glittering",
    "wof:placetype":"venue"
},
  "geometry": {"coordinates":[-80.147801,25.987691],"type":"Point"}
}