{
  "type": "Feature",
  "properties": {
    "addr:full":"9406 Atlantic Blvd Jacksonville FL 32225",
    "addr:housenumber":"9406",
    "addr:postcode":"32225",
    "addr:street":"Atlantic Blvd",
    "iso:country":"US",
    "sg:address":"9406 Atlantic Blvd",
    "sg:city":"Jacksonville",
    "sg:classifiers":[
        {
            "category":"Restaurant",
            "type":"Food & Drink"
        }
    ],
    "sg:menulink":"http://www.allmenus.com/fl/jacksonville/39451-tgi-fridays/menu/",
    "sg:phone":"+1 904 721 2200",
    "sg:postcode":"32225",
    "sg:province":"FL",
    "sg:tags":[
        "american"
    ],
    "wof:name":"T.G.I. Friday's",
    "wof:placetype":"venue"
},
  "geometry": {"coordinates":[-81.554458,30.318872],"type":"Point"}
}