{
  "type": "Feature",
  "properties": {
    "iso:country":"US",
    "sg:address":"4100 SW 20 Ave",
    "sg:city":"Gainesville",
    "sg:classifiers":[
        {
            "category":"Real Estate",
            "subcategory":"Real Estate Operator",
            "type":"Services"
        }
    ],
    "sg:phone":"+1 352 376 4002",
    "sg:postcode":"32607",
    "sg:province":"FL",
    "sg:tags":[
        "apartment"
    ],
    "wof:name":"Pinetree Gardens Apartments",
    "wof:placetype":"venue"
},
  "geometry": {"coordinates":[-82.386274,29.634836],"type":"Point"}
}