{
  "type": "Feature",
  "properties": {
    "addr:full":"13797 Le Bateau Isle Palm Beach Gardens FL 33410",
    "addr:housenumber":"13797",
    "addr:postcode":"33410",
    "addr:street":"Le Bateau Isle",
    "iso:country":"US",
    "sg:address":"13797 Le Bateau Isle",
    "sg:city":"Palm Beach Gardens",
    "sg:classifiers":[
        {
            "category":"Real Estate",
            "subcategory":"Real Estate Agent",
            "type":"Services"
        }
    ],
    "sg:phone":"+1 561 624 2492",
    "sg:postcode":"33410",
    "sg:province":"FL",
    "wof:name":"Hans Homburger",
    "wof:placetype":"venue"
},
  "geometry": {"coordinates":[-80.07807200000001,26.880551],"type":"Point"}
}