{
  "type": "Feature",
  "properties": {
    "addr:full":"9151 Kilgore Rd. Orlando FL 32836",
    "addr:housenumber":"9151",
    "addr:postcode":"32836",
    "addr:street":"Kilgore Rd.",
    "iso:country":"US",
    "sg:address":"9151 Kilgore Rd.",
    "sg:city":"Orlando",
    "sg:phone":"+1 407 876 9130",
    "sg:postcode":"32836",
    "sg:province":"FL",
    "sg:website":"http://www.PhantomCityStudio.com",
    "wof:name":"A Phantom City Studio",
    "wof:placetype":"venue"
},
  "geometry": {"coordinates":[-81.50990299999999,28.429001],"type":"Point"}
}