{
  "type": "Feature",
  "properties": {
    "addr:full":"4677 L B McLeod Rd Orlando FL 32811",
    "addr:housenumber":"4677;b",
    "addr:postcode":"32811",
    "addr:street":"L;Mcleod Rd",
    "iso:country":"US",
    "sg:address":"4677 L B McLeod Rd",
    "sg:city":"Orlando",
    "sg:classifiers":[
        {
            "category":"Autos & Motor Vehicles",
            "subcategory":"Auto Supplies",
            "type":"Retail Goods"
        }
    ],
    "sg:phone":"+1 407 425 7531",
    "sg:postcode":"32811",
    "sg:province":"FL",
    "sg:tags":[
        "automobile",
        "parts"
    ],
    "wof:name":"Keystone Automotive",
    "wof:placetype":"venue"
},
  "geometry": {"coordinates":[-81.437534,28.508705],"type":"Point"}
}