{
  "type": "Feature",
  "properties": {
    "addr:full":"4300 18th St W Bradenton FL 34205",
    "addr:housenumber":"4300",
    "addr:postcode":"34205",
    "addr:street":"18Th St W",
    "iso:country":"US",
    "sg:address":"4300 18th St W",
    "sg:city":"Bradenton",
    "sg:classifiers":[
        {
            "category":"Building & Trades",
            "subcategory":"Construction",
            "type":"Services"
        }
    ],
    "sg:phone":"+1 941 756 8927",
    "sg:postcode":"34205",
    "sg:province":"FL",
    "sg:tags":[
        "maintenance",
        "contractor"
    ],
    "wof:name":"Belmont Park Maintenance",
    "wof:placetype":"venue"
},
  "geometry": {"coordinates":[-82.578981,27.46247],"type":"Point"}
}