{
  "type": "Feature",
  "properties": {
    "addr:full":"546 Thames Cir Longwood FL 32750",
    "addr:housenumber":"546",
    "addr:postcode":"32750",
    "addr:street":"Thames Cir",
    "iso:country":"US",
    "sg:address":"546 Thames Cir",
    "sg:city":"Longwood",
    "sg:classifiers":[
        {
            "category":"Wholesale",
            "subcategory":"Machinery & Supplies",
            "type":"Manufacturing & Wholesale Goods"
        }
    ],
    "sg:phone":"+1 407 260 1030",
    "sg:postcode":"32750",
    "sg:province":"FL",
    "sg:tags":[
        "equipment",
        "system",
        "vacuum"
    ],
    "wof:name":"Gulfstream Air Inc",
    "wof:placetype":"venue"
},
  "geometry": {"coordinates":[-81.366283,28.705633],"type":"Point"}
}