{
  "type": "Feature",
  "properties": {
    "iso:country":"US",
    "sg:address":"1425 N Powerline Rd",
    "sg:city":"Pompano Beach",
    "sg:classifiers":[
        {
            "category":"Health Services",
            "subcategory":"Clinic",
            "type":"Services"
        }
    ],
    "sg:phone":"+1 954 590 3655",
    "sg:postcode":"33069",
    "sg:province":"FL",
    "sg:website":"www.americashealthchoice.com",
    "wof:name":"America's Health Choice",
    "wof:placetype":"venue"
},
  "geometry": {"coordinates":[-80.151557,26.245065],"type":"Point"}
}