{
  "type": "Feature",
  "properties": {
    "addr:full":"7543 NW 3rd Ct Fort Lauderdale FL 33317",
    "addr:housenumber":"7543",
    "addr:postcode":"33317",
    "addr:street":"Nw 3Rd Ct",
    "iso:country":"US",
    "sg:address":"7543 NW 3rd Ct",
    "sg:city":"Fort Lauderdale",
    "sg:classifiers":[
        {
            "category":"Shopping",
            "subcategory":"Books",
            "type":"Retail Goods"
        }
    ],
    "sg:phone":"+1 954 791 5945",
    "sg:postcode":"33317",
    "sg:province":"FL",
    "wof:name":"Roof Professor Inc",
    "wof:placetype":"venue"
},
  "geometry": {"coordinates":[-80.248717,26.126371],"type":"Point"}
}