{
  "type": "Feature",
  "properties": {
    "iso:country":"US",
    "sg:address":"1975 Wells Rd",
    "sg:city":"Orange Park",
    "sg:classifiers":[
        {
            "category":"Shopping",
            "subcategory":"Shoes",
            "type":"Retail Goods"
        }
    ],
    "sg:phone":"+1 904 276 7733",
    "sg:postcode":"32073",
    "sg:province":"FL",
    "wof:name":"D Mackey's Shoes & Apparel",
    "wof:placetype":"venue"
},
  "geometry": {"coordinates":[-81.732601,30.186997],"type":"Point"}
}