{
  "type": "Feature",
  "properties": {
    "iso:country":"US",
    "sg:address":"15409 US Hwy 19",
    "sg:city":"Port Richey",
    "sg:classifiers":[
        {
            "category":"Retail",
            "subcategory":"Auto Repair",
            "type":"Services"
        }
    ],
    "sg:phone":"+1 727 868 4553",
    "sg:postcode":"34667",
    "sg:province":"FL",
    "sg:tags":[
        "replacement",
        "contractor",
        "glass",
        "trade"
    ],
    "wof:name":"Pasco Auto Glass & Tinting",
    "wof:placetype":"venue"
},
  "geometry": {"coordinates":[-82.67738,28.381109],"type":"Point"}
}