{
  "type": "Feature",
  "properties": {
    "iso:country":"US",
    "sg:address":"216 Shady Hollow Ln",
    "sg:city":"Casselberry",
    "sg:classifiers":[
        {
            "category":"Building & Trades",
            "subcategory":"Construction",
            "type":"Services"
        }
    ],
    "sg:phone":"+1 407 331 8072",
    "sg:postcode":"32707",
    "sg:province":"FL",
    "sg:tags":[
        "floor",
        "laying",
        "contractor"
    ],
    "wof:name":"Ted Weeks",
    "wof:placetype":"venue"
},
  "geometry": {"coordinates":[-81.33004099999999,28.66342],"type":"Point"}
}