{
  "type": "Feature",
  "properties": {
    "iso:country":"US",
    "sg:address":"6118 Fort King Rd",
    "sg:city":"Zephyrhills",
    "sg:classifiers":[
        {
            "category":"Education",
            "subcategory":"Dance Studio",
            "type":"Public Place"
        }
    ],
    "sg:phone":"+1 813 782 4561",
    "sg:postcode":"33542",
    "sg:province":"FL",
    "sg:tags":[
        "instruction",
        "dancing"
    ],
    "wof:name":"Helen's Baton & Dance Studio",
    "wof:placetype":"venue"
},
  "geometry": {"coordinates":[-82.189087,28.247835],"type":"Point"}
}