{
  "type": "Feature",
  "properties": {
    "iso:country":"US",
    "sg:address":"18470 Hunters Glen Rd",
    "sg:city":"Fort Myers",
    "sg:classifiers":[
        {
            "category":"Building & Trades",
            "subcategory":"Construction",
            "type":"Services"
        }
    ],
    "sg:phone":"+1 239 543 7733",
    "sg:postcode":"33917",
    "sg:province":"FL",
    "sg:tags":[
        "general",
        "contractor"
    ],
    "wof:name":"J Pierson Construction Inc",
    "wof:placetype":"venue"
},
  "geometry": {"coordinates":[-81.823931,26.733932],"type":"Point"}
}