{
  "type": "Feature",
  "properties": {
    "iso:country":"US",
    "sg:address":"11757 Beach Blvd",
    "sg:city":"Jacksonville",
    "sg:phone":"+1 904 642 0303",
    "sg:postcode":"32246",
    "sg:province":"FL",
    "wof:name":"Direct Satellite Entertainment",
    "wof:placetype":"venue"
},
  "geometry": {"coordinates":[-81.513048,30.287164],"type":"Point"}
}