{
  "type": "Feature",
  "properties": {
    "iso:country":"US",
    "sg:address":"3229 S Atlantic Ave",
    "sg:city":"Daytona Beach",
    "sg:classifiers":[
        {
            "category":"Organizations",
            "subcategory":"Community Association",
            "type":"Services"
        }
    ],
    "sg:phone":"+1 386 767 2700",
    "sg:postcode":"32118",
    "sg:province":"FL",
    "sg:tags":[
        "condominium"
    ],
    "wof:name":"Sea Club IV",
    "wof:placetype":"venue"
},
  "geometry": {"coordinates":[-80.973162,29.158366],"type":"Point"}
}