{
  "type": "Feature",
  "properties": {
    "iso:country":"US",
    "sg:address":"405 N Reo St",
    "sg:city":"Tampa",
    "sg:classifiers":[
        {
            "category":"Utilities",
            "subcategory":"Telephone",
            "type":"Services"
        },
        {
            "category":"Professional",
            "type":"Services"
        }
    ],
    "sg:phone":"+1 813 639 9840",
    "sg:postcode":"33609",
    "sg:province":"FL",
    "sg:tags":[
        "communications",
        "establishment"
    ],
    "wof:name":"Sytex Inc",
    "wof:placetype":"venue"
},
  "geometry": {"coordinates":[-82.53645,27.947626],"type":"Point"}
}