{
  "type": "Feature",
  "properties": {
    "iso:country":"US",
    "sg:address":"1415 Burlington Ave N",
    "sg:city":"Saint Petersburg",
    "sg:classifiers":[
        {
            "category":"Manufacturing",
            "subcategory":"Tools & Machinery",
            "type":"Manufacturing & Wholesale Goods"
        }
    ],
    "sg:phone":"+1 727 896 8631",
    "sg:postcode":"33713",
    "sg:province":"FL",
    "sg:tags":[
        "machine",
        "shop",
        "engine",
        "auto",
        "repair"
    ],
    "wof:name":"Godwin-Singer Inc",
    "wof:placetype":"venue"
},
  "geometry": {"coordinates":[-82.65367000000001,27.773961],"type":"Point"}
}