{
  "type": "Feature",
  "properties": {
    "iso:country":"US",
    "sg:address":"3801 Mission Trace Blvd",
    "sg:city":"Tallahassee",
    "sg:classifiers":[
        {
            "category":"Building & Trades",
            "subcategory":"Construction",
            "type":"Services"
        }
    ],
    "sg:phone":"+1 850 322 8767",
    "sg:postcode":"32303",
    "sg:province":"FL",
    "sg:tags":[
        "restoration",
        "cleaning",
        "patio",
        "deck"
    ],
    "wof:name":"Insideout Cleaning Industries",
    "wof:placetype":"venue"
},
  "geometry": {"coordinates":[-84.34614500000001,30.487451],"type":"Point"}
}