{
  "type": "Feature",
  "properties": {
    "iso:country":"US",
    "sg:address":"1950 Cassat Ave",
    "sg:city":"Jacksonville",
    "sg:classifiers":[
        {
            "category":"Building & Trades",
            "subcategory":"Equipment Rental",
            "type":"Services"
        }
    ],
    "sg:phone":"+1 904 387 4436",
    "sg:postcode":"32210",
    "sg:province":"FL",
    "sg:tags":[
        "general"
    ],
    "wof:name":"Mc Stephensons Rental Service",
    "wof:placetype":"venue"
},
  "geometry": {"coordinates":[-81.73042100000001,30.282291],"type":"Point"}
}