{
  "type": "Feature",
  "properties": {
    "iso:country":"US",
    "sg:address":"15312 Sunset Dr",
    "sg:city":"Miami",
    "sg:classifiers":[
        {
            "category":"Wholesale",
            "subcategory":"Non-durable Goods",
            "type":"Manufacturing & Wholesale Goods"
        }
    ],
    "sg:phone":"+1 305 385 5093",
    "sg:postcode":"33193",
    "sg:province":"FL",
    "sg:tags":[
        "merchandise",
        "general"
    ],
    "wof:name":"National Promotions Inc",
    "wof:placetype":"venue"
},
  "geometry": {"coordinates":[-80.442656,25.699074],"type":"Point"}
}