{
  "type": "Feature",
  "properties": {
    "iso:country":"US",
    "sg:address":"4527 Lenox Ave",
    "sg:city":"Jacksonville",
    "sg:classifiers":[
        {
            "category":"Social Services",
            "type":"Services"
        }
    ],
    "sg:phone":"+1 904 384 1361",
    "sg:postcode":"32205",
    "sg:province":"FL",
    "sg:tags":[
        "organization",
        "welfare"
    ],
    "wof:name":"Goodwill Industries",
    "wof:placetype":"venue"
},
  "geometry": {"coordinates":[-81.72323799999999,30.319197],"type":"Point"}
}