{
  "type": "Feature",
  "properties": {
    "iso:country":"US",
    "sg:address":"15 SE 9th Ave",
    "sg:city":"Fort Lauderdale",
    "sg:classifiers":[
        {
            "category":"Real Estate",
            "subcategory":"Real Estate Agent",
            "type":"Services"
        }
    ],
    "sg:phone":"+1 954 768 9526",
    "sg:postcode":"33301",
    "sg:province":"FL",
    "wof:name":"South Bay Realty",
    "wof:placetype":"venue"
},
  "geometry": {"coordinates":[-80.134444,26.121246],"type":"Point"}
}