{
  "type": "Feature",
  "properties": {
    "addr:full":"21631 Coronado Ave Boca Raton FL 33433",
    "addr:housenumber":"21631",
    "addr:postcode":"33433",
    "addr:street":"Coronado Ave",
    "iso:country":"US",
    "sg:address":"21631 Coronado Ave",
    "sg:city":"Boca Raton",
    "sg:classifiers":[
        {
            "category":"Professional",
            "subcategory":"Accounting & Tax Preparation",
            "type":"Services"
        }
    ],
    "sg:phone":"+1 561 620 3025",
    "sg:postcode":"33433",
    "sg:province":"FL",
    "sg:tags":[
        "billing"
    ],
    "wof:name":"E Z Claims Inc",
    "wof:placetype":"venue"
},
  "geometry": {"coordinates":[-80.151112,26.356834],"type":"Point"}
}