{
  "type": "Feature",
  "properties": {
    "iso:country":"US",
    "sg:address":"1537 SE 14th St",
    "sg:city":"Fort Lauderdale",
    "sg:classifiers":[
        {
            "category":"Building & Trades",
            "subcategory":"Construction",
            "type":"Services"
        }
    ],
    "sg:phone":"+1 954 763 5545",
    "sg:postcode":"33316",
    "sg:province":"FL",
    "sg:tags":[
        "contractor"
    ],
    "wof:name":"Andrew Wall Rigging",
    "wof:placetype":"venue"
},
  "geometry": {"coordinates":[-80.12132,26.104644],"type":"Point"}
}