{
  "type": "Feature",
  "properties": {
    "iso:country":"US",
    "sg:address":"7272 NW 33rd St",
    "sg:city":"Miami",
    "sg:classifiers":[
        {
            "category":"Shopping",
            "subcategory":"Clothing, Apparel, & Fashions",
            "type":"Retail Goods"
        }
    ],
    "sg:phone":"+1 305 439 8077",
    "sg:postcode":"33122",
    "sg:province":"FL",
    "wof:name":"Uniform Place Inc",
    "wof:placetype":"venue"
},
  "geometry": {"coordinates":[-80.313811,25.804485],"type":"Point"}
}