{
  "type": "Feature",
  "properties": {
    "iso:country":"US",
    "sg:address":"446 Timber Ridge Dr",
    "sg:city":"Longwood",
    "sg:classifiers":[
        {
            "category":"Professional",
            "subcategory":"Computer Services",
            "type":"Services"
        }
    ],
    "sg:phone":"+1 407 786 7422",
    "sg:postcode":"32779",
    "sg:province":"FL",
    "sg:tags":[
        "consultant",
        "designer"
    ],
    "wof:name":"Breakthrough Usability",
    "wof:placetype":"venue"
},
  "geometry": {"coordinates":[-81.409848,28.710873],"type":"Point"}
}