{
  "type": "Feature",
  "properties": {
    "addr:full":"10481 N Kendall Dr Ste D204 Miami FL 33176",
    "addr:housenumber":"10481",
    "addr:postcode":"33176",
    "addr:street":"N Kendall Dr Ste D204",
    "iso:country":"US",
    "sg:address":"10481 N Kendall Dr Ste D204",
    "sg:city":"Miami",
    "sg:classifiers":[
        {
            "category":"Professional",
            "subcategory":"Lawyer & Legal Services",
            "type":"Services"
        }
    ],
    "sg:phone":"+1 305 598 8887",
    "sg:postcode":"33176",
    "sg:province":"FL",
    "wof:name":"Law Offices of Serra and Vemed",
    "wof:placetype":"venue"
},
  "geometry": {"coordinates":[-80.36366099999999,25.687218],"type":"Point"}
}