{
  "type": "Feature",
  "properties": {
    "iso:country":"US",
    "sg:address":"5317 Gulf Dr",
    "sg:city":"Holmes Beach",
    "sg:classifiers":[
        {
            "category":"Sports & Exercise",
            "subcategory":"Gym",
            "type":"Entertainment"
        }
    ],
    "sg:phone":"+1 941 778 5446",
    "sg:postcode":"34217",
    "sg:province":"FL",
    "sg:tags":[
        "club",
        "health",
        "studio",
        "gymnasium"
    ],
    "wof:name":"Island Fitness Ctr",
    "wof:placetype":"venue"
},
  "geometry": {"coordinates":[-82.714709,27.505947],"type":"Point"}
}