{
  "type": "Feature",
  "properties": {
    "iso:country":"US",
    "sg:address":"1458 Capital Cir NW",
    "sg:city":"Tallahassee",
    "sg:classifiers":[
        {
            "category":"Food & Beverages",
            "subcategory":"Groceries & Convenience Stores",
            "type":"Retail Goods"
        }
    ],
    "sg:phone":"+1 850 574 3594",
    "sg:postcode":"32303",
    "sg:province":"FL",
    "wof:name":"Inland Food Stores 592",
    "wof:placetype":"venue"
},
  "geometry": {"coordinates":[-84.36126,30.46165],"type":"Point"}
}