{
  "type": "Feature",
  "properties": {
    "iso:country":"US",
    "sg:address":"9835 SW 40th St",
    "sg:city":"Miami",
    "sg:classifiers":[
        {
            "category":"Recreation",
            "type":"Entertainment"
        }
    ],
    "sg:phone":"+1 305 553 5324",
    "sg:postcode":"33165",
    "sg:province":"FL",
    "sg:tags":[
        "martial",
        "arts",
        "instruction"
    ],
    "wof:name":"Seibu-Kan",
    "wof:placetype":"venue"
},
  "geometry": {"coordinates":[-80.355242,25.732708],"type":"Point"}
}