{
  "type": "Feature",
  "properties": {
    "iso:country":"US",
    "sg:address":"1896 Barrington Cir",
    "sg:city":"Rockledge",
    "sg:classifiers":[
        {
            "category":"Building & Trades",
            "subcategory":"Landscaping Services",
            "type":"Services"
        }
    ],
    "sg:phone":"+1 321 631 2714",
    "sg:postcode":"32955",
    "sg:province":"FL",
    "wof:name":"Attractive Turf",
    "wof:placetype":"venue"
},
  "geometry": {"coordinates":[-80.753074,28.32759],"type":"Point"}
}