{
  "type": "Feature",
  "properties": {
    "iso:country":"US",
    "sg:address":"6450 Albritton Rd",
    "sg:city":"Mc David",
    "sg:classifiers":[
        {
            "category":"Building & Trades",
            "subcategory":"Construction",
            "type":"Services"
        }
    ],
    "sg:phone":"+1 850 327 4872",
    "sg:postcode":"32568",
    "sg:province":"FL",
    "sg:tags":[
        "siding",
        "contractor"
    ],
    "wof:name":"Johnson's Siding",
    "wof:placetype":"venue"
},
  "geometry": {"coordinates":[-87.55840999999999,30.983425],"type":"Point"}
}