{
  "type": "Feature",
  "properties": {
    "addr:full":"1935 E Hallandale Beach Blvd Hallandale FL 33009",
    "addr:housenumber":"1935",
    "addr:postcode":"33009",
    "addr:street":"E Hallandale Beach Blvd",
    "iso:country":"US",
    "sg:address":"1935 E Hallandale Beach Blvd",
    "sg:city":"Hallandale",
    "sg:classifiers":[
        {
            "category":"Shopping",
            "subcategory":"Optical Goods",
            "type":"Retail Goods"
        }
    ],
    "sg:phone":"+1 954 458 0600",
    "sg:postcode":"33009",
    "sg:province":"FL",
    "wof:name":"Optical Inc",
    "wof:placetype":"venue"
},
  "geometry": {"coordinates":[-80.127962,25.986215],"type":"Point"}
}