{
  "type": "Feature",
  "properties": {
    "addr:full":"133 N Fort Harrison Ave Clearwater FL 33755",
    "addr:housenumber":"133",
    "addr:postcode":"33755",
    "addr:street":"N Fort Harrison Ave",
    "iso:country":"US",
    "sg:address":"133 N Fort Harrison Ave",
    "sg:city":"Clearwater",
    "sg:classifiers":[
        {
            "category":"Professional",
            "subcategory":"Lawyer & Legal Services",
            "type":"Services"
        }
    ],
    "sg:phone":"+1 727 441 4947",
    "sg:postcode":"33755",
    "sg:province":"FL",
    "sg:tags":[
        "attorney"
    ],
    "wof:name":"Kwall Showers & Coleman",
    "wof:placetype":"venue"
},
  "geometry": {"coordinates":[-82.79988400000001,27.96778],"type":"Point"}
}