{
  "type": "Feature",
  "properties": {
    "iso:country":"US",
    "sg:address":"1170 34th Ave",
    "sg:city":"Vero Beach",
    "sg:classifiers":[
        {
            "category":"Building & Trades",
            "subcategory":"Cleaning & Sanitation",
            "type":"Services"
        }
    ],
    "sg:phone":"+1 772 978 9827",
    "sg:postcode":"32960",
    "sg:province":"FL",
    "sg:tags":[
        "maintenance"
    ],
    "wof:name":"Hometrends",
    "wof:placetype":"venue"
},
  "geometry": {"coordinates":[-80.420447,27.62374],"type":"Point"}
}