{
  "type": "Feature",
  "properties": {
    "iso:country":"US",
    "sg:address":"13434 Chambord St",
    "sg:city":"Brooksville",
    "sg:classifiers":[
        {
            "category":"Building & Trades",
            "subcategory":"Landscaping Services",
            "type":"Services"
        }
    ],
    "sg:phone":"+1 352 592 1203",
    "sg:postcode":"34613",
    "sg:province":"FL",
    "sg:tags":[
        "tree"
    ],
    "sg:website":"www.tree-care.net",
    "wof:name":"Tree Care",
    "wof:placetype":"venue"
},
  "geometry": {"coordinates":[-82.502365,28.535502],"type":"Point"}
}