{
  "type": "Feature",
  "properties": {
    "iso:country":"US",
    "sg:address":"105 Ohio Ave N",
    "sg:city":"Live Oak",
    "sg:classifiers":[
        {
            "category":"Professional",
            "subcategory":"Lawyer & Legal Services",
            "type":"Services"
        }
    ],
    "sg:phone":"+1 386 362 4437",
    "sg:postcode":"32064",
    "sg:province":"FL",
    "sg:tags":[
        "attorney"
    ],
    "wof:name":"Sellers Prevalt & Robertson A",
    "wof:placetype":"venue"
},
  "geometry": {"coordinates":[-82.984148,30.296719],"type":"Point"}
}