{
  "type": "Feature",
  "properties": {
    "iso:country":"US",
    "sg:address":"2738 Bee Ridge Rd",
    "sg:city":"Sarasota",
    "sg:classifiers":[
        {
            "category":"Professional",
            "type":"Services"
        }
    ],
    "sg:phone":"+1 941 924 6458",
    "sg:postcode":"34239",
    "sg:province":"FL",
    "sg:tags":[
        "establishment"
    ],
    "wof:name":"Coastal Franchising Corp",
    "wof:placetype":"venue"
},
  "geometry": {"coordinates":[-82.51476700000001,27.298759],"type":"Point"}
}