{
  "type": "Feature",
  "properties": {
    "iso:country":"US",
    "sg:address":"4869 Montevista Dr",
    "sg:city":"Sarasota",
    "sg:classifiers":[
        {
            "category":"Building & Trades",
            "subcategory":"Plumbing",
            "type":"Services"
        }
    ],
    "sg:phone":"+1 941 925 3403",
    "sg:postcode":"34231",
    "sg:province":"FL",
    "sg:tags":[
        "plumbing",
        "contractor"
    ],
    "wof:name":"Nikolas J Loftus Plbg Contr",
    "wof:placetype":"venue"
},
  "geometry": {"coordinates":[-82.50018900000001,27.282883],"type":"Point"}
}