{
  "type": "Feature",
  "properties": {
    "addr:full":"1934 Dana Dr Fort Myers FL 33907",
    "addr:housenumber":"1934",
    "addr:postcode":"33907",
    "addr:street":"Dana Dr",
    "iso:country":"US",
    "sg:address":"1934 Dana Dr",
    "sg:city":"Fort Myers",
    "sg:classifiers":[
        {
            "category":"Wholesale",
            "subcategory":"Metals & Minerals",
            "type":"Manufacturing & Wholesale Goods"
        }
    ],
    "sg:phone":"+1 239 278 3637",
    "sg:postcode":"33907",
    "sg:province":"FL",
    "sg:tags":[
        "aluminum"
    ],
    "wof:name":"Inside Out Svc",
    "wof:placetype":"venue"
},
  "geometry": {"coordinates":[-81.875246,26.579537],"type":"Point"}
}