{
  "type": "Feature",
  "properties": {
    "addr:full":"2847 NW Co Rd 152 Jennings FL 32053",
    "addr:housenumber":"2847",
    "addr:postcode":"32053",
    "addr:street":"Nw Co Rd 152",
    "iso:country":"US",
    "sg:address":"2847 NW Co Rd 152",
    "sg:city":"Jennings",
    "sg:classifiers":[
        {
            "category":"Professional",
            "subcategory":"Employment Agencies",
            "type":"Services"
        }
    ],
    "sg:phone":"+1 386 938 2724",
    "sg:postcode":"32053",
    "sg:province":"FL",
    "sg:tags":[
        "help",
        "supply"
    ],
    "wof:name":"Bodacious Enterprises",
    "wof:placetype":"venue"
},
  "geometry": {"coordinates":[-83.224369,30.581301],"type":"Point"}
}