{
  "type": "Feature",
  "properties": {
    "iso:country":"US",
    "sg:address":"526 W Ohio Ave",
    "sg:city":"Orange City",
    "sg:classifiers":[
        {
            "category":"Building & Trades",
            "subcategory":"Construction",
            "type":"Services"
        }
    ],
    "sg:phone":"+1 386 801 4695",
    "sg:postcode":"32763",
    "sg:province":"FL",
    "sg:tags":[
        "masonry",
        "contractor"
    ],
    "wof:name":"T C Masonry Inc",
    "wof:placetype":"venue"
},
  "geometry": {"coordinates":[-81.306203,28.939522],"type":"Point"}
}