{
  "type": "Feature",
  "properties": {
    "iso:country":"US",
    "sg:address":"1350 W Bay Dr",
    "sg:city":"Largo",
    "sg:classifiers":[
        {
            "category":"Shopping",
            "subcategory":"Jewelry",
            "type":"Retail Goods"
        }
    ],
    "sg:phone":"+1 727 581 6827",
    "sg:postcode":"33770",
    "sg:province":"FL",
    "sg:tags":[
        "gift"
    ],
    "wof:name":"Silver Queen Inc",
    "wof:placetype":"venue"
},
  "geometry": {"coordinates":[-82.802644,27.916743],"type":"Point"}
}