{
  "type": "Feature",
  "properties": {
    "iso:country":"US",
    "sg:address":"1139 E Tennessee St",
    "sg:city":"Tallahassee",
    "sg:classifiers":[
        {
            "category":"Shopping",
            "type":"Retail Goods"
        }
    ],
    "sg:phone":"+1 850 668 9933",
    "sg:postcode":"32308",
    "sg:province":"FL",
    "sg:tags":[
        "trophy",
        "medal",
        "award"
    ],
    "wof:name":"Champions Engraving Trophies",
    "wof:placetype":"venue"
},
  "geometry": {"coordinates":[-84.265129,30.446587],"type":"Point"}
}