{
  "type": "Feature",
  "properties": {
    "addr:full":"5761 NW 37th Ave Miami FL 33142",
    "addr:housenumber":"5761",
    "addr:postcode":"33142",
    "addr:street":"Nw 37Th Ave",
    "iso:country":"US",
    "sg:address":"5761 NW 37th Ave",
    "sg:city":"Miami",
    "sg:classifiers":[
        {
            "category":"Manufacturing",
            "subcategory":"Furniture",
            "type":"Manufacturing & Wholesale Goods"
        }
    ],
    "sg:phone":"+1 305 634 5052",
    "sg:postcode":"33142",
    "sg:province":"FL",
    "sg:tags":[
        "shelving"
    ],
    "wof:name":"Allied Shelving & Equipment",
    "wof:placetype":"venue"
},
  "geometry": {"coordinates":[-80.25703,25.824528],"type":"Point"}
}