{
  "type": "Feature",
  "properties": {
    "addr:full":"1722 N Mills Ave Orlando FL 32803",
    "addr:housenumber":"1722",
    "addr:postcode":"32803",
    "addr:street":"N Mills Ave",
    "iso:country":"US",
    "sg:address":"1722 N Mills Ave",
    "sg:city":"Orlando",
    "sg:classifiers":[
        {
            "category":"Shopping",
            "subcategory":"Used Merchandise",
            "type":"Retail Goods"
        }
    ],
    "sg:phone":"+1 407 896 0181",
    "sg:postcode":"32803",
    "sg:province":"FL",
    "sg:tags":[
        "antique"
    ],
    "sg:website":"www.irongateantiques.com",
    "wof:name":"Iron Gate Antiques",
    "wof:placetype":"venue"
},
  "geometry": {"coordinates":[-81.364554,28.569666],"type":"Point"}
}