{
  "type": "Feature",
  "properties": {
    "addr:full":"4932 NW 66th Ave Fort Lauderdale FL 33319",
    "addr:housenumber":"4932",
    "addr:postcode":"33319",
    "addr:street":"Nw 66Th Ave",
    "iso:country":"US",
    "sg:address":"4932 NW 66th Ave",
    "sg:city":"Fort Lauderdale",
    "sg:classifiers":[
        {
            "category":"Banks & Credit Unions",
            "subcategory":"Financial Services",
            "type":"Services"
        }
    ],
    "sg:phone":"+1 954 747 8929",
    "sg:postcode":"33319",
    "sg:province":"FL",
    "sg:tags":[
        "company",
        "holding"
    ],
    "wof:name":"Level Line Holdings Inc",
    "wof:placetype":"venue"
},
  "geometry": {"coordinates":[-80.238173,26.186626],"type":"Point"}
}