{
  "type": "Feature",
  "properties": {
    "iso:country":"US",
    "sg:address":"13602 Glasser Ave",
    "sg:city":"Orlando",
    "sg:classifiers":[
        {
            "category":"Building & Trades",
            "subcategory":"Construction",
            "type":"Services"
        }
    ],
    "sg:phone":"+1 407 384 5682",
    "sg:postcode":"32826",
    "sg:province":"FL",
    "sg:tags":[
        "contractor"
    ],
    "wof:name":"Fix It Up",
    "wof:placetype":"venue"
},
  "geometry": {"coordinates":[-81.185034,28.583057],"type":"Point"}
}