{
  "type": "Feature",
  "properties": {
    "iso:country":"US",
    "sg:address":"23 Stone St",
    "sg:city":"Cocoa",
    "sg:classifiers":[
        {
            "category":"Shopping",
            "type":"Retail Goods"
        }
    ],
    "sg:phone":"+1 321 631 0454",
    "sg:postcode":"32922",
    "sg:province":"FL",
    "sg:tags":[
        "picture",
        "frame"
    ],
    "wof:name":"Jan's You-Frame-It",
    "wof:placetype":"venue"
},
  "geometry": {"coordinates":[-80.72765,28.354611],"type":"Point"}
}