{
  "type": "Feature",
  "properties": {
    "addr:full":"6560 NW 6th Ct Pompano Beach FL 33063",
    "addr:housenumber":"6560",
    "addr:postcode":"33063",
    "addr:street":"Nw 6Th Ct",
    "iso:country":"US",
    "sg:address":"6560 NW 6th Ct",
    "sg:city":"Pompano Beach",
    "sg:classifiers":[
        {
            "category":"Professional",
            "subcategory":"Management & Consulting",
            "type":"Services"
        }
    ],
    "sg:phone":"+1 954 974 3475",
    "sg:postcode":"33063",
    "sg:province":"FL",
    "sg:tags":[
        "business"
    ],
    "wof:name":"Piranha Inc",
    "wof:placetype":"venue"
},
  "geometry": {"coordinates":[-80.213065,26.236468],"type":"Point"}
}