{
  "type": "Feature",
  "properties": {
    "addr:full":"1448 NW 48th St Ocala FL 34475",
    "addr:housenumber":"1448",
    "addr:postcode":"34475",
    "addr:street":"Nw 48Th St",
    "iso:country":"US",
    "sg:address":"1448 NW 48th St",
    "sg:city":"Ocala",
    "sg:classifiers":[
        {
            "category":"Banks & Credit Unions",
            "subcategory":"Bank",
            "type":"Services"
        }
    ],
    "sg:phone":"+1 352 629 0550",
    "sg:postcode":"34475",
    "sg:province":"FL",
    "sg:tags":[
        "loan",
        "real estate"
    ],
    "wof:name":"Wells Fargo Home Mortgage",
    "wof:placetype":"venue"
},
  "geometry": {"coordinates":[-82.150308,29.236679],"type":"Point"}
}