{
  "type": "Feature",
  "properties": {
    "iso:country":"US",
    "sg:address":"115 College Dr",
    "sg:city":"Orange Park",
    "sg:classifiers":[
        {
            "category":"Building & Trades",
            "subcategory":"Electrical",
            "type":"Services"
        }
    ],
    "sg:phone":"+1 904 276 3833",
    "sg:postcode":"32065",
    "sg:province":"FL",
    "sg:tags":[
        "electric",
        "contractor"
    ],
    "wof:name":"Orange State Electric Inc",
    "wof:placetype":"venue"
},
  "geometry": {"coordinates":[-81.77436899999999,30.13308],"type":"Point"}
}