{
  "type": "Feature",
  "properties": {
    "iso:country":"US",
    "sg:address":"299 Alhambra Cir Ste 312",
    "sg:city":"Coral Gables",
    "sg:classifiers":[
        {
            "category":"Health Services",
            "subcategory":"Doctor",
            "type":"Services"
        }
    ],
    "sg:phone":"+1 305 448 7777",
    "sg:postcode":"33134",
    "sg:province":"FL",
    "sg:tags":[
        "psychiatrist"
    ],
    "wof:name":"Castiello Anastasio M MD",
    "wof:placetype":"venue"
},
  "geometry": {"coordinates":[-80.26046100000001,25.752356],"type":"Point"}
}