{
  "type": "Feature",
  "properties": {
    "iso:country":"US",
    "sg:address":"1224 NW 119th St",
    "sg:city":"Miami",
    "sg:classifiers":[
        {
            "category":"Building & Trades",
            "subcategory":"Construction",
            "type":"Services"
        }
    ],
    "sg:phone":"+1 305 688 1517",
    "sg:postcode":"33168",
    "sg:province":"FL",
    "sg:tags":[
        "tile",
        "dealer"
    ],
    "wof:name":"Coachman Tile",
    "wof:placetype":"venue"
},
  "geometry": {"coordinates":[-80.22023900000001,25.883283],"type":"Point"}
}