{
  "type": "Feature",
  "properties": {
    "addr:full":"223 N E St Lake Worth FL 33460",
    "addr:housenumber":"223",
    "addr:postcode":"33460",
    "addr:street":"N E St",
    "iso:country":"US",
    "sg:address":"223 N E St",
    "sg:city":"Lake Worth",
    "sg:classifiers":[
        {
            "category":"Real Estate",
            "subcategory":"Real Estate Agent",
            "type":"Services"
        }
    ],
    "sg:phone":"+1 561 585 1430",
    "sg:postcode":"33460",
    "sg:province":"FL",
    "wof:name":"Eric Ovaska",
    "wof:placetype":"venue"
},
  "geometry": {"coordinates":[-80.06126999999999,26.618914],"type":"Point"}
}