{
  "type": "Feature",
  "properties": {
    "iso:country":"US",
    "sg:address":"10057 Agave Cir N",
    "sg:city":"Jacksonville",
    "sg:classifiers":[
        {
            "category":"Shopping",
            "subcategory":"Discount & Variety Stores",
            "type":"Retail Goods"
        }
    ],
    "sg:phone":"+1 904 724 7783",
    "sg:postcode":"32246",
    "sg:province":"FL",
    "sg:tags":[
        "merchandise",
        "general"
    ],
    "wof:name":"Betty B Brown",
    "wof:placetype":"venue"
},
  "geometry": {"coordinates":[-81.53880599999999,30.318665],"type":"Point"}
}