{
  "type": "Feature",
  "properties": {
    "addr:full":"127 Miracle Strip Pkwy Fort Walton Beach FL 32548",
    "addr:housenumber":"127",
    "addr:postcode":"32548",
    "addr:street":"Miracle Strip Pkwy",
    "iso:country":"US",
    "sg:address":"127 Miracle Strip Pkwy",
    "sg:city":"Fort Walton Beach",
    "sg:classifiers":[
        {
            "category":"Insurance",
            "subcategory":"Insurance Agent",
            "type":"Services"
        }
    ],
    "sg:phone":"+1 850 269 0704",
    "sg:postcode":"32548",
    "sg:province":"FL",
    "wof:name":"Insurance Assocates of Destin",
    "wof:placetype":"venue"
},
  "geometry": {"coordinates":[-86.607485,30.403834],"type":"Point"}
}