{
  "type": "Feature",
  "properties": {
    "addr:full":"13842 SW 8th St Miami FL 33184",
    "addr:housenumber":"13842",
    "addr:postcode":"33184",
    "addr:street":"Sw 8Th St",
    "iso:country":"US",
    "sg:address":"13842 SW 8th St",
    "sg:city":"Miami",
    "sg:phone":"+1 305 229 2861",
    "sg:postcode":"33184",
    "sg:province":"FL",
    "wof:name":"Unlimited Real Estate Corp",
    "wof:placetype":"venue"
},
  "geometry": {"coordinates":[-80.419693,25.760889],"type":"Point"}
}