{
  "type": "Feature",
  "properties": {
    "iso:country":"US",
    "sg:address":"4537 Old Dixie Hwy",
    "sg:city":"Stuart",
    "sg:classifiers":[
        {
            "category":"Personal",
            "subcategory":"Barber",
            "type":"Services"
        }
    ],
    "sg:phone":"+1 772 220 3006",
    "sg:postcode":"34997",
    "sg:province":"FL",
    "wof:name":"Tom's Barber Shop & Men's",
    "wof:placetype":"venue"
},
  "geometry": {"coordinates":[-80.20229999999999,27.14929],"type":"Point"}
}