{
  "type": "Feature",
  "properties": {
    "iso:country":"US",
    "sg:address":"121 Emerald Loop",
    "sg:city":"Davenport",
    "sg:classifiers":[
        {
            "category":"Travel",
            "subcategory":"Hotels & Motels",
            "type":"Entertainment"
        }
    ],
    "sg:phone":"+1 863 420 3838",
    "sg:postcode":"33897",
    "sg:province":"FL",
    "sg:website":"www.orlandocondos.net",
    "wof:name":"Orlando Breeze Resort",
    "wof:placetype":"venue"
},
  "geometry": {"coordinates":[-81.673,28.338588],"type":"Point"}
}