{
  "type": "Feature",
  "properties": {
    "addr:full":"220 SW 64th Way Hollywood FL 33023",
    "addr:housenumber":"220",
    "addr:postcode":"33023",
    "addr:street":"Sw 64Th Way",
    "iso:country":"US",
    "sg:address":"220 SW 64th Way",
    "sg:city":"Hollywood",
    "sg:classifiers":[
        {
            "category":"Building & Trades",
            "subcategory":"Construction",
            "type":"Services"
        }
    ],
    "sg:phone":"+1 954 868 3724",
    "sg:postcode":"33023",
    "sg:province":"FL",
    "sg:tags":[
        "house"
    ],
    "wof:name":"Kea Construction",
    "wof:placetype":"venue"
},
  "geometry": {"coordinates":[-80.217078,26.007825],"type":"Point"}
}