{
  "type": "Feature",
  "properties": {
    "iso:country":"US",
    "sg:address":"8853 Commodity Cir",
    "sg:city":"Orlando",
    "sg:classifiers":[
        {
            "category":"Real Estate",
            "subcategory":"Real Estate Services",
            "type":"Services"
        },
        {
            "category":"Banks & Credit Unions",
            "subcategory":"Financial Services",
            "type":"Services"
        },
        {
            "category":"Professional",
            "subcategory":"Management & Consulting",
            "type":"Services"
        }
    ],
    "sg:phone":"+1 407 377 6320",
    "sg:postcode":"32819",
    "sg:province":"FL",
    "sg:tags":[
        "mortgage",
        "science",
        "loan",
        "processing",
        "academic",
        "consultant"
    ],
    "wof:name":"Florida Invest Consultants Inc",
    "wof:placetype":"venue"
},
  "geometry": {"coordinates":[-81.42907200000001,28.442348],"type":"Point"}
}