{
  "type": "Feature",
  "properties": {
    "addr:full":"2501 Harn Blvd Clearwater FL 33764",
    "addr:housenumber":"2501",
    "addr:postcode":"33764",
    "addr:street":"Harn Blvd",
    "iso:country":"US",
    "sg:address":"2501 Harn Blvd",
    "sg:city":"Clearwater",
    "sg:classifiers":[
        {
            "category":"Professional",
            "subcategory":"Business Services",
            "type":"Services"
        }
    ],
    "sg:phone":"+1 727 532 0641",
    "sg:postcode":"33764",
    "sg:province":"FL",
    "sg:tags":[
        "translation"
    ],
    "wof:name":"Connecting Link Bus Trnslation",
    "wof:placetype":"venue"
},
  "geometry": {"coordinates":[-82.730158,27.946588],"type":"Point"}
}