{
  "type": "Feature",
  "properties": {
    "iso:country":"US",
    "sg:address":"7594 W Sand Lake Rd",
    "sg:city":"Orlando",
    "sg:classifiers":[
        {
            "category":"Real Estate",
            "subcategory":"Developer",
            "type":"Services"
        }
    ],
    "sg:phone":"+1 407 226 8888",
    "sg:postcode":"32819",
    "sg:province":"FL",
    "wof:name":"Byblos Development Inc",
    "wof:placetype":"venue"
},
  "geometry": {"coordinates":[-81.487261,28.449872],"type":"Point"}
}