{
  "type": "Feature",
  "properties": {
    "addr:full":"1535 Lehall Sq N Lakeland FL 33810",
    "addr:housenumber":"1535",
    "addr:postcode":"33810",
    "addr:street":"Lehall Sq N",
    "iso:country":"US",
    "sg:address":"1535 Lehall Sq N",
    "sg:city":"Lakeland",
    "sg:classifiers":[
        {
            "category":"Building & Trades",
            "subcategory":"Construction",
            "type":"Services"
        }
    ],
    "sg:phone":"+1 863 853 2990",
    "sg:postcode":"33810",
    "sg:province":"FL",
    "sg:tags":[
        "contractor"
    ],
    "wof:name":"Andrew Riness Stucco",
    "wof:placetype":"venue"
},
  "geometry": {"coordinates":[-81.98127599999999,28.167212],"type":"Point"}
}