{
  "type": "Feature",
  "properties": {
    "iso:country":"US",
    "sg:address":"900 Buffalo Rd",
    "sg:city":"Titusville",
    "sg:classifiers":[
        {
            "category":"Building & Trades",
            "subcategory":"Construction",
            "type":"Services"
        }
    ],
    "sg:phone":"+1 321 269 9901",
    "sg:postcode":"32796",
    "sg:province":"FL",
    "sg:tags":[
        "insulation",
        "heat",
        "contractor"
    ],
    "wof:name":"New Age Insulation",
    "wof:placetype":"venue"
},
  "geometry": {"coordinates":[-80.81620599999999,28.624422],"type":"Point"}
}