{
  "type": "Feature",
  "properties": {
    "iso:country":"US",
    "sg:address":"6613 W Boynton Beach Blvd",
    "sg:city":"Boynton Beach",
    "sg:classifiers":[
        {
            "category":"Food & Beverages",
            "subcategory":"Bakery",
            "type":"Retail Goods"
        }
    ],
    "sg:phone":"+1 561 732 9595",
    "sg:postcode":"33437",
    "sg:province":"FL",
    "wof:name":"Bagels and",
    "wof:placetype":"venue"
},
  "geometry": {"coordinates":[-80.14890699999999,26.528211],"type":"Point"}
}