{
  "type": "Feature",
  "properties": {
    "iso:country":"US",
    "sg:address":"543 Normandy Rd",
    "sg:city":"Saint Petersburg",
    "sg:classifiers":[
        {
            "category":"Building & Trades",
            "subcategory":"Construction",
            "type":"Services"
        }
    ],
    "sg:phone":"+1 727 397 2684",
    "sg:postcode":"33708",
    "sg:province":"FL",
    "sg:tags":[
        "residential",
        "nonresidential"
    ],
    "wof:name":"Michael Daniell Enterprises",
    "wof:placetype":"venue"
},
  "geometry": {"coordinates":[-82.78474900000001,27.798003],"type":"Point"}
}