{
  "type": "Feature",
  "properties": {
    "addr:full":"5021 4th St E Bradenton FL 34203",
    "addr:housenumber":"5021",
    "addr:postcode":"34203",
    "addr:street":"4Th St",
    "iso:country":"US",
    "sg:address":"5021 4th St E",
    "sg:city":"Bradenton",
    "sg:classifiers":[
        {
            "category":"Retail",
            "subcategory":"Repair Shop",
            "type":"Services"
        }
    ],
    "sg:phone":"+1 941 751 3834",
    "sg:postcode":"34203",
    "sg:province":"FL",
    "sg:tags":[
        "house",
        "cleaning"
    ],
    "wof:name":"Abbott Cleaning Service",
    "wof:placetype":"venue"
},
  "geometry": {"coordinates":[-82.56018,27.452549],"type":"Point"}
}