{
  "type": "Feature",
  "properties": {
    "addr:full":"17306 NW 112th Blvd Alachua FL 32615",
    "addr:housenumber":"17306",
    "addr:postcode":"32615",
    "addr:street":"Nw 112Th Blvd",
    "iso:country":"US",
    "sg:address":"17306 NW 112th Blvd",
    "sg:city":"Alachua",
    "sg:classifiers":[
        {
            "category":"Place Of Worship",
            "subcategory":"Church",
            "type":"Public Place"
        },
        {
            "category":"Place Of Worship",
            "type":"Public Place"
        },
        {
            "category":"Organizations",
            "subcategory":"Religious Organization",
            "type":"Services"
        }
    ],
    "sg:phone":"+1 386 462 2017",
    "sg:postcode":"32615",
    "sg:province":"FL",
    "sg:tags":[
        "churches-interdenominational",
        "churches-various",
        "denomination"
    ],
    "wof:name":"Hare Krishna Temple",
    "wof:placetype":"venue"
},
  "geometry": {"coordinates":[-82.46632700000001,29.815975],"type":"Point"}
}