{
  "type": "Feature",
  "properties": {
    "iso:country":"US",
    "sg:address":"2615 Harris Blvd",
    "sg:city":"Kissimmee",
    "sg:classifiers":[
        {
            "category":"Manufacturing",
            "subcategory":"Tools & Machinery",
            "type":"Manufacturing & Wholesale Goods"
        }
    ],
    "sg:phone":"+1 407 932 1322",
    "sg:postcode":"34746",
    "sg:province":"FL",
    "sg:tags":[
        "cutting",
        "gear"
    ],
    "wof:name":"Mouse Gear Epcot",
    "wof:placetype":"venue"
},
  "geometry": {"coordinates":[-81.425887,28.264009],"type":"Point"}
}