{
  "type": "Feature",
  "properties": {
    "addr:full":"4020 NW 187th Ter Opa Locka FL 33055",
    "addr:housenumber":"4020",
    "addr:postcode":"33055",
    "addr:street":"Nw 187Th Ter;Locka",
    "iso:country":"US",
    "sg:address":"4020 NW 187th Ter",
    "sg:city":"Opa Locka",
    "sg:classifiers":[
        {
            "category":"Freight",
            "type":"Transportation"
        }
    ],
    "sg:phone":"+1 305 625 7081",
    "sg:postcode":"33055",
    "sg:province":"FL",
    "sg:tags":[
        "trucking"
    ],
    "wof:name":"Hiswill Logistics Inc",
    "wof:placetype":"venue"
},
  "geometry": {"coordinates":[-80.267037,25.944369],"type":"Point"}
}