{
  "type": "Feature",
  "properties": {
    "iso:country":"US",
    "sg:address":"670 N Yachtsman Dr",
    "sg:city":"Sanibel",
    "sg:classifiers":[
        {
            "category":"Manufacturing",
            "subcategory":"Buildings",
            "type":"Manufacturing & Wholesale Goods"
        },
        {
            "category":"Building & Trades",
            "subcategory":"Construction",
            "type":"Services"
        }
    ],
    "sg:phone":"+1 239 472 8481",
    "sg:postcode":"33957",
    "sg:province":"FL",
    "sg:tags":[
        "home",
        "builder",
        "contractor"
    ],
    "wof:name":"Bright Star Developers",
    "wof:placetype":"venue"
},
  "geometry": {"coordinates":[-82.0309,26.449537],"type":"Point"}
}