{
  "type": "Feature",
  "properties": {
    "addr:full":"4054 N Goldenrod Rd Winter Park FL 32792",
    "addr:housenumber":"4054",
    "addr:postcode":"32792",
    "addr:street":"N Goldenrod Rd",
    "iso:country":"US",
    "sg:address":"4054 N Goldenrod Rd",
    "sg:city":"Winter Park",
    "sg:classifiers":[
        {
            "category":"Shopping",
            "subcategory":"Used Merchandise",
            "type":"Retail Goods"
        }
    ],
    "sg:phone":"+1 407 673 7377",
    "sg:postcode":"32792",
    "sg:province":"FL",
    "wof:name":"Gentley Touched Furnishings",
    "wof:placetype":"venue"
},
  "geometry": {"coordinates":[-81.286686,28.598007],"type":"Point"}
}