{
  "type": "Feature",
  "properties": {
    "iso:country":"US",
    "sg:address":"2043 N Miami Ave",
    "sg:city":"Miami",
    "sg:classifiers":[
        {
            "category":"Retail",
            "subcategory":"Auto Repair",
            "type":"Services"
        }
    ],
    "sg:phone":"+1 305 576 7988",
    "sg:postcode":"33127",
    "sg:province":"FL",
    "wof:name":"Remy Transmissions",
    "wof:placetype":"venue"
},
  "geometry": {"coordinates":[-80.194828,25.797742],"type":"Point"}
}