{
  "type": "Feature",
  "properties": {
    "iso:country":"US",
    "sg:address":"2748 Capital Cir NE",
    "sg:city":"Tallahassee",
    "sg:classifiers":[
        {
            "category":"Professional",
            "subcategory":"Management & Consulting",
            "type":"Services"
        }
    ],
    "sg:phone":"+1 850 297 1520",
    "sg:postcode":"32308",
    "sg:province":"FL",
    "sg:tags":[
        "communications",
        "consultant"
    ],
    "wof:name":"Global Telecom Solutions",
    "wof:placetype":"venue"
},
  "geometry": {"coordinates":[-84.23991100000001,30.488536],"type":"Point"}
}