{
  "type": "Feature",
  "properties": {
    "iso:country":"US",
    "sg:address":"11219 Park Blvd",
    "sg:city":"Seminole",
    "sg:classifiers":[
        {
            "category":"Shopping",
            "subcategory":"Discount & Variety Stores",
            "type":"Retail Goods"
        }
    ],
    "sg:phone":"+1 727 319 3751",
    "sg:postcode":"33772",
    "sg:province":"FL",
    "wof:name":"Dollar Tree",
    "wof:placetype":"venue"
},
  "geometry": {"coordinates":[-82.79386599999999,27.840779],"type":"Point"}
}