{
  "type": "Feature",
  "properties": {
    "iso:country":"US",
    "sg:address":"451 E Altamonte Dr",
    "sg:city":"Altamonte Spgs",
    "sg:classifiers":[
        {
            "category":"Food & Beverages",
            "subcategory":"Candy",
            "type":"Retail Goods"
        }
    ],
    "sg:phone":"+1 407 767 7500",
    "sg:postcode":"32701",
    "sg:province":"FL",
    "sg:tags":[
        "confectionery"
    ],
    "wof:name":"Rocky Mountain Chocolate Fctry",
    "wof:placetype":"venue"
},
  "geometry": {"coordinates":[-81.374043,28.66385],"type":"Point"}
}