{
  "type": "Feature",
  "properties": {
    "addr:full":"1080 Eisenhower Dr Nokomis FL 34275",
    "addr:housenumber":"1080",
    "addr:postcode":"34275",
    "addr:street":"Eisenhower Dr",
    "iso:country":"US",
    "sg:address":"1080 Eisenhower Dr",
    "sg:city":"Nokomis",
    "sg:classifiers":[
        {
            "category":"Building & Trades",
            "subcategory":"Construction",
            "type":"Services"
        }
    ],
    "sg:phone":"+1 941 485 1230",
    "sg:postcode":"34275",
    "sg:province":"FL",
    "sg:tags":[
        "hanging",
        "contractor"
    ],
    "wof:name":"Barry Ziegler Painting",
    "wof:placetype":"venue"
},
  "geometry": {"coordinates":[-82.440288,27.141575],"type":"Point"}
}