{
  "type": "Feature",
  "properties": {
    "addr:full":"575 W 28th St Hialeah FL 33010",
    "addr:housenumber":"575",
    "addr:postcode":"33010",
    "addr:street":"W 28Th St",
    "iso:country":"US",
    "sg:address":"575 W 28th St",
    "sg:city":"Hialeah",
    "sg:classifiers":[
        {
            "category":"Manufacturing",
            "subcategory":"Furniture",
            "type":"Manufacturing & Wholesale Goods"
        }
    ],
    "sg:phone":"+1 305 888 8480",
    "sg:postcode":"33010",
    "sg:province":"FL",
    "sg:tags":[
        "household",
        "wood",
        "mfg"
    ],
    "wof:name":"Custom Mica Furniture Inc",
    "wof:placetype":"venue"
},
  "geometry": {"coordinates":[-80.292874,25.847168],"type":"Point"}
}