{
  "type": "Feature",
  "properties": {
    "iso:country":"US",
    "sg:address":"2867 W Trade Ave",
    "sg:city":"Miami",
    "sg:classifiers":[
        {
            "category":"Banks & Credit Unions",
            "subcategory":"Investment Brokerage",
            "type":"Services"
        }
    ],
    "sg:phone":"+1 305 648 1000",
    "sg:postcode":"33133",
    "sg:province":"FL",
    "sg:tags":[
        "broker",
        "commodity"
    ],
    "sg:website":"http://www.ecotradeonline.com",
    "wof:name":"Ecotrade Inc",
    "wof:placetype":"venue"
},
  "geometry": {"coordinates":[-80.239543,25.736312],"type":"Point"}
}