{
  "type": "Feature",
  "properties": {
    "iso:country":"US",
    "sg:address":"4760 NW 17th Ave",
    "sg:city":"Miami",
    "sg:classifiers":[
        {
            "category":"Retail",
            "subcategory":"Auto Repair",
            "type":"Services"
        }
    ],
    "sg:phone":"+1 305 635 7278",
    "sg:postcode":"33142",
    "sg:province":"FL",
    "sg:tags":[
        "automotive",
        "parts",
        "store"
    ],
    "wof:name":"Diagnostic and Performance",
    "wof:placetype":"venue"
},
  "geometry": {"coordinates":[-80.224412,25.81912],"type":"Point"}
}