{
  "type": "Feature",
  "properties": {
    "iso:country":"US",
    "sg:address":"5518 Horse Stable Ln",
    "sg:city":"Jacksonville",
    "sg:classifiers":[
        {
            "category":"Professional",
            "type":"Services"
        }
    ],
    "sg:phone":"+1 904 262 6010",
    "sg:postcode":"32258",
    "sg:province":"FL",
    "sg:tags":[
        "establishment"
    ],
    "wof:name":"Arline Washingon LLC Custom Hm",
    "wof:placetype":"venue"
},
  "geometry": {"coordinates":[-81.564954,30.163743],"type":"Point"}
}