{
  "type": "Feature",
  "properties": {
    "iso:country":"US",
    "sg:address":"16690 Gator Rd",
    "sg:city":"Fort Myers",
    "sg:classifiers":[
        {
            "category":"Professional",
            "type":"Services"
        }
    ],
    "sg:phone":"+1 239 415 0804",
    "sg:postcode":"33912",
    "sg:province":"FL",
    "sg:tags":[
        "establishment"
    ],
    "wof:name":"Premier Panel Processing",
    "wof:placetype":"venue"
},
  "geometry": {"coordinates":[-81.825329,26.49616],"type":"Point"}
}