{
  "type": "Feature",
  "properties": {
    "iso:country":"US",
    "sg:address":"2855 NW 75th Ave",
    "sg:city":"Miami",
    "sg:classifiers":[
        {
            "category":"Utilities",
            "subcategory":"Water",
            "type":"Services"
        },
        {
            "category":"Recreation",
            "subcategory":"Water Park",
            "type":"Entertainment"
        }
    ],
    "sg:phone":"+1 305 592 1000",
    "sg:postcode":"33122",
    "sg:province":"FL",
    "sg:tags":[
        "industrial",
        "supply-wholesale",
        "treatment",
        "supplies-commercial",
        "systems-equipment"
    ],
    "wof:name":"Ecolochem Inc",
    "wof:placetype":"venue"
},
  "geometry": {"coordinates":[-80.318578,25.800485],"type":"Point"}
}