{
  "type": "Feature",
  "properties": {
    "iso:country":"US",
    "sg:address":"729 W Flagler St",
    "sg:city":"Miami",
    "sg:classifiers":[
        {
            "category":"Personal",
            "subcategory":"Barber",
            "type":"Services"
        }
    ],
    "sg:phone":"+1 305 324 9393",
    "sg:postcode":"33130",
    "sg:province":"FL",
    "wof:name":"Tivoli Barber Shop",
    "wof:placetype":"venue"
},
  "geometry": {"coordinates":[-80.20639799999999,25.773701],"type":"Point"}
}