{
  "type": "Feature",
  "properties": {
    "iso:country":"US",
    "sg:address":"104 Portland St",
    "sg:city":"Eustis",
    "sg:classifiers":[
        {
            "category":"Real Estate",
            "subcategory":"Architect",
            "type":"Services"
        }
    ],
    "sg:phone":"+1 352 483 3881",
    "sg:postcode":"32726",
    "sg:province":"FL",
    "sg:tags":[
        "building",
        "designer"
    ],
    "wof:name":"Builders Choice",
    "wof:placetype":"venue"
},
  "geometry": {"coordinates":[-81.66292900000001,28.851931],"type":"Point"}
}