{
  "type": "Feature",
  "properties": {
    "addr:full":"12388 NW 80th Pl Parkland FL 33076",
    "addr:housenumber":"12388",
    "addr:postcode":"33076",
    "addr:street":"Nw 80Th Pl",
    "iso:country":"US",
    "sg:address":"12388 NW 80th Pl",
    "sg:city":"Parkland",
    "sg:classifiers":[
        {
            "category":"Retail",
            "subcategory":"Auto Repair",
            "type":"Services"
        }
    ],
    "sg:phone":"+1 954 755 8246",
    "sg:postcode":"33076",
    "sg:province":"FL",
    "sg:tags":[
        "body",
        "painting",
        "repairing",
        "automobile"
    ],
    "wof:name":"Nutrition For The Body & Soul, Inc.",
    "wof:placetype":"venue"
},
  "geometry": {"coordinates":[-80.291158,26.329847],"type":"Point"}
}