{
  "type": "Feature",
  "properties": {
    "iso:country":"US",
    "sg:address":"6815 S Orange Ave",
    "sg:city":"Orlando",
    "sg:classifiers":[
        {
            "category":"Retail",
            "subcategory":"Auto Rental",
            "type":"Services"
        }
    ],
    "sg:phone":"+1 407 855 9056",
    "sg:postcode":"32809",
    "sg:province":"FL",
    "sg:tags":[
        "renting",
        "truck",
        "leasing"
    ],
    "wof:name":"U-Haul Co",
    "wof:placetype":"venue"
},
  "geometry": {"coordinates":[-81.367419,28.464853],"type":"Point"}
}