{
  "type": "Feature",
  "properties": {
    "addr:full":"16540 SW 157th Ave Miami FL 33187",
    "addr:housenumber":"16540",
    "addr:postcode":"33187",
    "addr:street":"Sw 157Th Ave",
    "iso:country":"US",
    "sg:address":"16540 SW 157th Ave",
    "sg:city":"Miami",
    "sg:classifiers":[
        {
            "category":"Home & Garden",
            "subcategory":"Furniture",
            "type":"Retail Goods"
        }
    ],
    "sg:phone":"+1 305 969 1553",
    "sg:postcode":"33187",
    "sg:province":"FL",
    "wof:name":"Ortega Manuel Furniture",
    "wof:placetype":"venue"
},
  "geometry": {"coordinates":[-80.44663799999999,25.613902],"type":"Point"}
}