{
  "type": "Feature",
  "properties": {
    "addr:full":"7887 Bryan Dairy Rd Largo FL 33777",
    "addr:housenumber":"7887",
    "addr:postcode":"33777",
    "addr:street":"Bryan Dairy Rd",
    "iso:country":"US",
    "sg:address":"7887 Bryan Dairy Rd",
    "sg:city":"Largo",
    "sg:classifiers":[
        {
            "category":"Social Services",
            "subcategory":"Child Care",
            "type":"Services"
        }
    ],
    "sg:phone":"+1 727 541 8972",
    "sg:postcode":"33777",
    "sg:province":"FL",
    "sg:tags":[
        "day"
    ],
    "wof:name":"New Directions In Learning",
    "wof:placetype":"venue"
},
  "geometry": {"coordinates":[-82.747692,27.87234],"type":"Point"}
}