{
  "type": "Feature",
  "properties": {
    "addr:full":"580 Bloomington Ct Altamonte Spgs FL 32714",
    "addr:housenumber":"580",
    "addr:postcode":"32714",
    "addr:street":"Bloomington Ct;Spgs",
    "iso:country":"US",
    "sg:address":"580 Bloomington Ct",
    "sg:city":"Altamonte Spgs",
    "sg:classifiers":[
        {
            "category":"Building & Trades",
            "subcategory":"Construction",
            "type":"Services"
        }
    ],
    "sg:phone":"+1 407 788 7120",
    "sg:postcode":"32714",
    "sg:province":"FL",
    "sg:tags":[
        "general",
        "contractor"
    ],
    "wof:name":"R L Haines Construction",
    "wof:placetype":"venue"
},
  "geometry": {"coordinates":[-81.406243,28.680415],"type":"Point"}
}