{
  "type": "Feature",
  "properties": {
    "addr:full":"8180 NW 36th St Doral FL 33166",
    "addr:housenumber":"8180",
    "addr:postcode":"33166",
    "addr:street":"Nw 36Th St",
    "iso:country":"US",
    "sg:address":"8180 NW 36th St",
    "sg:city":"Doral",
    "sg:classifiers":[
        {
            "category":"Health Services",
            "subcategory":"Clinic",
            "type":"Services"
        }
    ],
    "sg:phone":"+1 305 593 9275",
    "sg:postcode":"33166",
    "sg:province":"FL",
    "sg:tags":[
        "home"
    ],
    "wof:name":"Florida Home Health Assn",
    "wof:placetype":"venue"
},
  "geometry": {"coordinates":[-80.329033,25.809726],"type":"Point"}
}