{
  "type": "Feature",
  "properties": {
    "iso:country":"US",
    "sg:address":"10112 Dartmouth Ave",
    "sg:city":"Tampa",
    "sg:classifiers":[
        {
            "category":"Banks & Credit Unions",
            "subcategory":"Financial Services",
            "type":"Services"
        }
    ],
    "sg:phone":"+1 813 935 1382",
    "sg:postcode":"33612",
    "sg:province":"FL",
    "sg:tags":[
        "trust",
        "management"
    ],
    "wof:name":"William J Artlip Trustee",
    "wof:placetype":"venue"
},
  "geometry": {"coordinates":[-82.462844,28.042619],"type":"Point"}
}