{
  "type": "Feature",
  "properties": {
    "iso:country":"US",
    "sg:address":"1221 E Robinson St",
    "sg:city":"Orlando",
    "sg:classifiers":[
        {
            "category":"Professional",
            "subcategory":"Accounting & Tax Preparation",
            "type":"Services"
        }
    ],
    "sg:phone":"+1 407 894 1557",
    "sg:postcode":"32801",
    "sg:province":"FL",
    "wof:name":"Fong David Y CPA",
    "wof:placetype":"venue"
},
  "geometry": {"coordinates":[-81.363224,28.5458],"type":"Point"}
}