{
  "type": "Feature",
  "properties": {
    "iso:country":"US",
    "sg:address":"847 Orange Ave",
    "sg:city":"Daytona Beach",
    "sg:classifiers":[
        {
            "category":"Banks & Credit Unions",
            "subcategory":"Bank",
            "type":"Services"
        }
    ],
    "sg:phone":"+1 386 258 7520",
    "sg:postcode":"32114",
    "sg:province":"FL",
    "sg:tags":[
        "loan",
        "company"
    ],
    "wof:name":"EC FBBIc",
    "wof:placetype":"venue"
},
  "geometry": {"coordinates":[-81.031913,29.202397],"type":"Point"}
}