{
  "type": "Feature",
  "properties": {
    "iso:country":"US",
    "sg:address":"270 N US Hwy 1",
    "sg:city":"Ormond Beach",
    "sg:classifiers":[
        {
            "category":"Banks & Credit Unions",
            "subcategory":"Bank",
            "type":"Services"
        }
    ],
    "sg:phone":"+1 386 673 2400",
    "sg:postcode":"32174",
    "sg:province":"FL",
    "sg:tags":[
        "loan",
        "real estate"
    ],
    "wof:name":"Hayes Mortgage Svc Co",
    "wof:placetype":"venue"
},
  "geometry": {"coordinates":[-81.06756900000001,29.289721],"type":"Point"}
}