{
  "type": "Feature",
  "properties": {
    "iso:country":"US",
    "sg:address":"17770 S Dixie Hwy",
    "sg:city":"Miami",
    "sg:classifiers":[
        {
            "category":"Banks & Credit Unions",
            "subcategory":"Bank",
            "type":"Services"
        },
        {
            "category":"Banks & Credit Unions",
            "subcategory":"Financial Services",
            "type":"Services"
        }
    ],
    "sg:phone":"+1 305 247 5541",
    "sg:postcode":"33157",
    "sg:province":"FL",
    "sg:tags":[
        "broker",
        "mortgage"
    ],
    "wof:name":"First National Bank of Homestead",
    "wof:placetype":"venue"
},
  "geometry": {"coordinates":[-80.351601,25.604601],"type":"Point"}
}