{
  "type": "Feature",
  "properties": {
    "iso:country":"US",
    "sg:address":"7520 W Waters Ave",
    "sg:city":"Tampa",
    "sg:classifiers":[
        {
            "category":"Shopping",
            "type":"Retail Goods"
        }
    ],
    "sg:phone":"+1 813 884 6300",
    "sg:postcode":"33615",
    "sg:province":"FL",
    "sg:tags":[
        "aids",
        "hearing"
    ],
    "wof:name":"Bell Tone",
    "wof:placetype":"venue"
},
  "geometry": {"coordinates":[-82.56495,28.025818],"type":"Point"}
}