{
  "type": "Feature",
  "properties": {
    "addr:full":"2847 Stone Ave Deland FL 32720",
    "addr:housenumber":"2847",
    "addr:postcode":"32720",
    "addr:street":"Stone Ave",
    "iso:country":"US",
    "sg:address":"2847 Stone Ave",
    "sg:city":"Deland",
    "sg:classifiers":[
        {
            "category":"Professional",
            "subcategory":"Business Services",
            "type":"Services"
        }
    ],
    "sg:phone":"+1 386 801 5634",
    "sg:postcode":"32720",
    "sg:province":"FL",
    "sg:tags":[
        "plant",
        "design",
        "maintenance"
    ],
    "wof:name":"Andi Plants",
    "wof:placetype":"venue"
},
  "geometry": {"coordinates":[-81.357094,29.077979],"type":"Point"}
}