{
  "type": "Feature",
  "properties": {
    "iso:country":"US",
    "sg:address":"2119 Oak St",
    "sg:city":"Jacksonville",
    "sg:classifiers":[
        {
            "category":"Health Services",
            "subcategory":"Doctor",
            "type":"Services"
        }
    ],
    "sg:phone":"+1 904 389 2300",
    "sg:postcode":"32204",
    "sg:province":"FL",
    "sg:tags":[
        "medical"
    ],
    "wof:name":"Arthritis Theumatology Clinic",
    "wof:placetype":"venue"
},
  "geometry": {"coordinates":[-81.684128,30.311446],"type":"Point"}
}