{
  "type": "Feature",
  "properties": {
    "iso:country":"US",
    "sg:address":"8425 Montravail Cir",
    "sg:city":"Tampa",
    "sg:phone":"+1 866 488 8801",
    "sg:postcode":"33637",
    "sg:province":"FL",
    "sg:website":"http://local.ingenio.com/Listings/Details.aspx?NUM=a%3a10270720%3a13%3a4859924%3a14%3a0%3a7",
    "wof:name":"Village Oaks Apartments",
    "wof:placetype":"venue"
},
  "geometry": {"coordinates":[-82.358935,28.065113],"type":"Point"}
}