{
  "type": "Feature",
  "properties": {
    "addr:full":"1745 Biarritz Dr Miami Beach FL 33141",
    "addr:housenumber":"1745",
    "addr:postcode":"33141",
    "addr:street":"Biarritz Dr",
    "iso:country":"US",
    "sg:address":"1745 Biarritz Dr",
    "sg:city":"Miami Beach",
    "sg:classifiers":[
        {
            "category":"Manufacturing",
            "subcategory":"Printing",
            "type":"Manufacturing & Wholesale Goods"
        }
    ],
    "sg:phone":"+1 305 866 9033",
    "sg:postcode":"33141",
    "sg:province":"FL",
    "sg:tags":[
        "publisher"
    ],
    "wof:name":"El Paracaidista",
    "wof:placetype":"venue"
},
  "geometry": {"coordinates":[-80.13939999999999,25.850569],"type":"Point"}
}