{
  "type": "Feature",
  "properties": {
    "iso:country":"US",
    "sg:address":"23036 US Hwy 331 N",
    "sg:city":"Laurel Hill",
    "sg:classifiers":[
        {
            "category":"Personal",
            "subcategory":"Beauty Salon",
            "type":"Services"
        }
    ],
    "sg:phone":"+1 850 834 2504",
    "sg:postcode":"32567",
    "sg:province":"FL",
    "sg:tags":[
        "manicuring"
    ],
    "wof:name":"Sherry's Nail Spot",
    "wof:placetype":"venue"
},
  "geometry": {"coordinates":[-86.30911999999999,30.993999],"type":"Point"}
}