{
  "type": "Feature",
  "properties": {
    "addr:full":"2335 Pacific Ave NE Palm Bay FL 32905",
    "addr:housenumber":"2335",
    "addr:postcode":"32905",
    "addr:street":"Pacific Ave Ne",
    "iso:country":"US",
    "sg:address":"2335 Pacific Ave NE",
    "sg:city":"Palm Bay",
    "sg:classifiers":[
        {
            "category":"Building & Trades",
            "subcategory":"Landscaping Services",
            "type":"Services"
        }
    ],
    "sg:phone":"+1 321 626 8733",
    "sg:postcode":"32905",
    "sg:province":"FL",
    "wof:name":"Thornton Prof Tree Svcs",
    "wof:placetype":"venue"
},
  "geometry": {"coordinates":[-80.601354,28.053015],"type":"Point"}
}