{
  "type": "Feature",
  "properties": {
    "addr:full":"128 Seashore Dr Islamorada FL 33036",
    "addr:housenumber":"128",
    "addr:postcode":"33036",
    "addr:street":"Seashore Dr",
    "iso:country":"US",
    "sg:address":"128 Seashore Dr",
    "sg:city":"Islamorada",
    "sg:classifiers":[
        {
            "category":"Building & Trades",
            "subcategory":"Electrical",
            "type":"Services"
        }
    ],
    "sg:phone":"+1 305 528 7452",
    "sg:postcode":"33036",
    "sg:province":"FL",
    "sg:tags":[
        "installation"
    ],
    "wof:name":"Ace Glass Security Inc",
    "wof:placetype":"venue"
},
  "geometry": {"coordinates":[-80.640332,24.911027],"type":"Point"}
}