{
  "type": "Feature",
  "properties": {
    "iso:country":"US",
    "sg:address":"2601 NW 42nd Ave",
    "sg:city":"Miami",
    "sg:classifiers":[
        {
            "category":"Local Transit",
            "type":"Transportation"
        }
    ],
    "sg:phone":"+1 305 790 1495",
    "sg:postcode":"33142",
    "sg:province":"FL",
    "sg:tags":[
        "limousine"
    ],
    "wof:name":"High Class Limousine Corp",
    "wof:placetype":"venue"
},
  "geometry": {"coordinates":[-80.26447400000001,25.800226],"type":"Point"}
}