{
  "type": "Feature",
  "properties": {
    "addr:full":"500 N Davis Hwy Pensacola FL 32501",
    "addr:housenumber":"500",
    "addr:postcode":"32501",
    "addr:street":"N Davis Hwy",
    "iso:country":"US",
    "sg:address":"500 N Davis Hwy",
    "sg:city":"Pensacola",
    "sg:classifiers":[
        {
            "category":"Organizations",
            "subcategory":"Religious Organization",
            "type":"Services"
        }
    ],
    "sg:phone":"+1 850 432 4414",
    "sg:postcode":"32501",
    "sg:province":"FL",
    "sg:tags":[
        "church"
    ],
    "sg:website":"www.members.aol.com/olive500",
    "wof:name":"Mt Olive Baptist Church",
    "wof:placetype":"venue"
},
  "geometry": {"coordinates":[-87.210487,30.420541],"type":"Point"}
}