{
  "type": "Feature",
  "properties": {
    "addr:full":"7681 Lake Worth Rd Wellington FL 33467",
    "addr:housenumber":"7681",
    "addr:postcode":"33467",
    "addr:street":"Lake Worth Rd",
    "iso:country":"US",
    "sg:address":"7681 Lake Worth Rd",
    "sg:city":"Wellington",
    "sg:classifiers":[
        {
            "category":"Banks & Credit Unions",
            "subcategory":"Bank",
            "type":"Services"
        }
    ],
    "sg:phone":"+1 561 439 4185",
    "sg:postcode":"33467",
    "sg:province":"FL",
    "sg:tags":[
        "loan",
        "real estate"
    ],
    "wof:name":"Homebanc",
    "wof:placetype":"venue"
},
  "geometry": {"coordinates":[-80.168063,26.617545],"type":"Point"}
}