{
  "type": "Feature",
  "properties": {
    "addr:full":"3400 S Tamiami Trl Sarasota FL 34239",
    "addr:housenumber":"3400",
    "addr:postcode":"34239",
    "addr:street":"S Tamiami Trl",
    "iso:country":"US",
    "sg:address":"3400 S Tamiami Trl",
    "sg:city":"Sarasota",
    "sg:classifiers":[
        {
            "category":"Shopping",
            "subcategory":"Pharmacy",
            "type":"Retail Goods"
        }
    ],
    "sg:phone":"+1 941 366 2949",
    "sg:postcode":"34239",
    "sg:province":"FL",
    "sg:tags":[
        "door",
        "closed"
    ],
    "wof:name":"Brunswick Pharmacy Services",
    "wof:placetype":"venue"
},
  "geometry": {"coordinates":[-82.53027899999999,27.303711],"type":"Point"}
}