{
  "type": "Feature",
  "properties": {
    "iso:country":"US",
    "sg:address":"761 Dodecanese Blvd",
    "sg:city":"Tarpon Springs",
    "sg:classifiers":[
        {
            "category":"Shopping",
            "subcategory":"Gifts & Souvenirs",
            "type":"Retail Goods"
        }
    ],
    "sg:phone":"+1 727 937 6231",
    "sg:postcode":"34689",
    "sg:province":"FL",
    "wof:name":"Dockside Imports",
    "wof:placetype":"venue"
},
  "geometry": {"coordinates":[-82.761034,28.155487],"type":"Point"}
}