{
  "type": "Feature",
  "properties": {
    "addr:full":"432 Cardinal Dr Satellite Beach FL 32937",
    "addr:housenumber":"432",
    "addr:postcode":"32937",
    "addr:street":"Cardinal Dr",
    "iso:country":"US",
    "sg:address":"432 Cardinal Dr",
    "sg:city":"Satellite Beach",
    "sg:classifiers":[
        {
            "category":"Utilities",
            "subcategory":"Telephone",
            "type":"Services"
        }
    ],
    "sg:phone":"+1 321 773 0622",
    "sg:postcode":"32937",
    "sg:province":"FL",
    "sg:tags":[
        "company"
    ],
    "wof:name":"A T & T Voice-Janet Ahlfeld",
    "wof:placetype":"venue"
},
  "geometry": {"coordinates":[-80.610787,28.207078],"type":"Point"}
}