{
  "type": "Feature",
  "properties": {
    "addr:full":"1623 W 32nd St Jacksonville FL 32209",
    "addr:housenumber":"1623",
    "addr:postcode":"32209",
    "addr:street":"W 32Nd St",
    "iso:country":"US",
    "sg:address":"1623 W 32nd St",
    "sg:city":"Jacksonville",
    "sg:classifiers":[
        {
            "category":"Shopping",
            "type":"Retail Goods"
        }
    ],
    "sg:phone":"+1 904 768 5670",
    "sg:postcode":"32209",
    "sg:province":"FL",
    "sg:tags":[
        "cosmetic",
        "perfume"
    ],
    "wof:name":"Avon By Demenia",
    "wof:placetype":"venue"
},
  "geometry": {"coordinates":[-81.68452000000001,30.364252],"type":"Point"}
}