{
  "type": "Feature",
  "properties": {
    "iso:country":"US",
    "sg:address":"1875 Aaron Ave",
    "sg:city":"Orlando",
    "sg:classifiers":[
        {
            "category":"Building & Trades",
            "subcategory":"Construction",
            "type":"Services"
        }
    ],
    "sg:phone":"+1 407 425 7396",
    "sg:postcode":"32811",
    "sg:province":"FL",
    "sg:tags":[
        "residential"
    ],
    "wof:name":"Benjamin Allen & Sons Cnstr",
    "wof:placetype":"venue"
},
  "geometry": {"coordinates":[-81.432166,28.518927],"type":"Point"}
}