{
  "type": "Feature",
  "properties": {
    "iso:country":"US",
    "sg:address":"446 SW 89th Ave",
    "sg:city":"Miami",
    "sg:classifiers":[
        {
            "category":"Professional",
            "subcategory":"Business Services",
            "type":"Services"
        }
    ],
    "sg:phone":"+1 305 221 6845",
    "sg:postcode":"33174",
    "sg:province":"FL",
    "sg:tags":[
        "record",
        "music",
        "dvd's",
        "label"
    ],
    "wof:name":"Begui Records",
    "wof:placetype":"venue"
},
  "geometry": {"coordinates":[-80.339555,25.765061],"type":"Point"}
}