{
  "type": "Feature",
  "properties": {
    "addr:full":"28646 W Dixie Hwy Homestead FL 33033",
    "addr:housenumber":"28646",
    "addr:postcode":"33033",
    "addr:street":"W Dixie Hwy",
    "iso:country":"US",
    "sg:address":"28646 W Dixie Hwy",
    "sg:city":"Homestead",
    "sg:classifiers":[
        {
            "category":"Shopping",
            "subcategory":"Clothing, Apparel, & Fashions",
            "type":"Retail Goods"
        }
    ],
    "sg:phone":"+1 305 245 4005",
    "sg:postcode":"33033",
    "sg:province":"FL",
    "sg:tags":[
        "family"
    ],
    "wof:name":"Getto Thang",
    "wof:placetype":"venue"
},
  "geometry": {"coordinates":[-80.445667,25.501927],"type":"Point"}
}