{
  "type": "Feature",
  "properties": {
    "iso:country":"US",
    "sg:address":"1060 Newton St",
    "sg:city":"Englewood",
    "sg:classifiers":[
        {
            "category":"Professional",
            "subcategory":"Computer Services",
            "type":"Services"
        }
    ],
    "sg:phone":"+1 941 474 5243",
    "sg:postcode":"34224",
    "sg:province":"FL",
    "sg:tags":[
        "consulting",
        "related",
        "business"
    ],
    "wof:name":"Gcc Inc",
    "wof:placetype":"venue"
},
  "geometry": {"coordinates":[-82.33016600000001,26.933955],"type":"Point"}
}