{
  "type": "Feature",
  "properties": {
    "addr:full":"3070 Cypress Gardens Rd Winter Haven FL 33884",
    "addr:housenumber":"3070",
    "addr:postcode":"33884",
    "addr:street":"Cypress Gardens Rd",
    "iso:country":"US",
    "sg:address":"3070 Cypress Gardens Rd",
    "sg:city":"Winter Haven",
    "sg:classifiers":[
        {
            "category":"Building & Trades",
            "subcategory":"Construction",
            "type":"Services"
        }
    ],
    "sg:phone":"+1 863 324 2444",
    "sg:postcode":"33884",
    "sg:province":"FL",
    "sg:tags":[
        "contractor"
    ],
    "wof:name":"Lloyd Bailey Bldg Contractor",
    "wof:placetype":"venue"
},
  "geometry": {"coordinates":[-81.684291,27.996793],"type":"Point"}
}