{
  "type": "Feature",
  "properties": {
    "addr:full":"15515 SW 170th St Archer FL 32618",
    "addr:housenumber":"15515",
    "addr:postcode":"32618",
    "addr:street":"Sw 170Th St",
    "iso:country":"US",
    "sg:address":"15515 SW 170th St",
    "sg:city":"Archer",
    "sg:classifiers":[
        {
            "category":"Retail",
            "subcategory":"Animal Services",
            "type":"Services"
        }
    ],
    "sg:phone":"+1 352 495 5040",
    "sg:postcode":"32618",
    "sg:province":"FL",
    "wof:name":"Equigen",
    "wof:placetype":"venue"
},
  "geometry": {"coordinates":[-82.523464,29.507585],"type":"Point"}
}