{
  "type": "Feature",
  "properties": {
    "addr:full":"912 SE 16th Ter Cape Coral FL 33990",
    "addr:housenumber":"912",
    "addr:postcode":"33990",
    "addr:street":"Se 16Th Ter",
    "iso:country":"US",
    "sg:address":"912 SE 16th Ter",
    "sg:city":"Cape Coral",
    "sg:classifiers":[
        {
            "category":"Building & Trades",
            "subcategory":"Construction",
            "type":"Services"
        }
    ],
    "sg:phone":"+1 239 573 7329",
    "sg:postcode":"33990",
    "sg:province":"FL",
    "sg:tags":[
        "driveway"
    ],
    "wof:name":"Deck-O-Drives",
    "wof:placetype":"venue"
},
  "geometry": {"coordinates":[-81.954515,26.622111],"type":"Point"}
}