{
  "type": "Feature",
  "properties": {
    "iso:country":"US",
    "sg:address":"1018 New York Ave",
    "sg:city":"Dunedin",
    "sg:classifiers":[
        {
            "category":"Shopping",
            "subcategory":"Used Merchandise",
            "type":"Retail Goods"
        },
        {
            "category":"Shopping",
            "type":"Retail Goods"
        }
    ],
    "sg:phone":"+1 727 733 7702",
    "sg:postcode":"34698",
    "sg:province":"FL",
    "sg:tags":[
        "decorative",
        "stencil",
        "unfinished",
        "mural",
        "furniture"
    ],
    "wof:name":"Main Street Mercantile",
    "wof:placetype":"venue"
},
  "geometry": {"coordinates":[-82.779813,28.016563],"type":"Point"}
}