{
  "type": "Feature",
  "properties": {
    "addr:full":"1520 Clermont Dr Naples FL 34109",
    "addr:housenumber":"1520",
    "addr:postcode":"34109",
    "addr:street":"Clermont Dr",
    "iso:country":"US",
    "sg:address":"1520 Clermont Dr",
    "sg:city":"Naples",
    "sg:classifiers":[
        {
            "category":"Real Estate",
            "subcategory":"Real Estate Agent",
            "type":"Services"
        }
    ],
    "sg:phone":"+1 239 514 1160",
    "sg:postcode":"34109",
    "sg:province":"FL",
    "wof:name":"A P M Services",
    "wof:placetype":"venue"
},
  "geometry": {"coordinates":[-81.784926,26.256823],"type":"Point"}
}