{
  "type": "Feature",
  "properties": {
    "addr:full":"320 Tamiami Trl Nokomis FL 34275",
    "addr:housenumber":"320",
    "addr:postcode":"34275",
    "addr:street":"Tamiami Trl",
    "iso:country":"US",
    "sg:address":"320 Tamiami Trl",
    "sg:city":"Nokomis",
    "sg:classifiers":[
        {
            "category":"Health Services",
            "subcategory":"Chiropractor",
            "type":"Services"
        }
    ],
    "sg:phone":"+1 941 484 0008",
    "sg:postcode":"34275",
    "sg:province":"FL",
    "wof:name":"Kim Keene DC",
    "wof:placetype":"venue"
},
  "geometry": {"coordinates":[-82.453389,27.12949],"type":"Point"}
}