{
  "type": "Feature",
  "properties": {
    "addr:full":"5440 Beach Blvd Jacksonville FL 32207",
    "addr:housenumber":"5440",
    "addr:postcode":"32207",
    "addr:street":"Beach Blvd",
    "iso:country":"US",
    "sg:address":"5440 Beach Blvd",
    "sg:city":"Jacksonville",
    "sg:classifiers":[
        {
            "category":"Food & Beverages",
            "subcategory":"Liquor & Beverages",
            "type":"Retail Goods"
        }
    ],
    "sg:phone":"+1 904 396 3679",
    "sg:postcode":"32207",
    "sg:province":"FL",
    "sg:tags":[
        "alcoholic"
    ],
    "wof:name":"A B C Fine Wine & Spirits 184",
    "wof:placetype":"venue"
},
  "geometry": {"coordinates":[-81.607742,30.294204],"type":"Point"}
}