{
  "type": "Feature",
  "properties": {
    "addr:full":"207 E Ilex Dr West Palm Beach FL 33403",
    "addr:housenumber":"207",
    "addr:postcode":"33403",
    "addr:street":"E Ilex Dr",
    "iso:country":"US",
    "sg:address":"207 E Ilex Dr",
    "sg:city":"West Palm Beach",
    "sg:classifiers":[
        {
            "category":"Personal",
            "subcategory":"Beauty Salon",
            "type":"Services"
        }
    ],
    "sg:phone":"+1 561 842 6263",
    "sg:postcode":"33403",
    "sg:province":"FL",
    "sg:tags":[
        "shop"
    ],
    "wof:name":"Magic Fingers Inc",
    "wof:placetype":"venue"
},
  "geometry": {"coordinates":[-80.058224,26.801183],"type":"Point"}
}