{
  "type": "Feature",
  "properties": {
    "iso:country":"US",
    "sg:address":"18611 NW 8th Ct",
    "sg:city":"Miami",
    "sg:classifiers":[
        {
            "category":"Building & Trades",
            "subcategory":"Locksmith",
            "type":"Services"
        }
    ],
    "sg:phone":"+1 786 718 1404",
    "sg:postcode":"33169",
    "sg:province":"FL",
    "sg:tags":[
        "key"
    ],
    "wof:name":"15 Minute Response Locksmith",
    "wof:placetype":"venue"
},
  "geometry": {"coordinates":[-80.21642300000001,25.946719],"type":"Point"}
}