{
  "type": "Feature",
  "properties": {
    "iso:country":"US",
    "sg:address":"3220 Canal Dr",
    "sg:city":"Pompano Beach",
    "sg:classifiers":[
        {
            "category":"Shopping",
            "type":"Retail Goods"
        }
    ],
    "sg:phone":"+1 954 931 6358",
    "sg:postcode":"33062",
    "sg:province":"FL",
    "sg:tags":[
        "merchandise"
    ],
    "wof:name":"Water Doctor of South Florida",
    "wof:placetype":"venue"
},
  "geometry": {"coordinates":[-80.08766900000001,26.252892],"type":"Point"}
}