{
  "type": "Feature",
  "properties": {
    "addr:full":"9276 Southampton Pl Boca Raton FL 33434",
    "addr:housenumber":"9276",
    "addr:postcode":"33434",
    "addr:street":"Southampton Pl",
    "iso:country":"US",
    "sg:address":"9276 Southampton Pl",
    "sg:city":"Boca Raton",
    "sg:classifiers":[
        {
            "category":"Building & Trades",
            "subcategory":"Landscaping Services",
            "type":"Services"
        }
    ],
    "sg:phone":"+1 561 477 2741",
    "sg:postcode":"33434",
    "sg:province":"FL",
    "sg:tags":[
        "lawn",
        "maintenance",
        "grounds"
    ],
    "wof:name":"Bohada Lawn Svc Inc",
    "wof:placetype":"venue"
},
  "geometry": {"coordinates":[-80.190371,26.382835],"type":"Point"}
}