{
  "type": "Feature",
  "properties": {
    "addr:full":"700 N Central Ave Umatilla FL 32784",
    "addr:housenumber":"700",
    "addr:postcode":"32784",
    "addr:street":"N Central Ave",
    "iso:country":"US",
    "sg:address":"700 N Central Ave",
    "sg:city":"Umatilla",
    "sg:classifiers":[
        {
            "category":"Banks & Credit Unions",
            "subcategory":"Bank",
            "type":"Services"
        }
    ],
    "sg:phone":"+1 352 669 0405",
    "sg:postcode":"32784",
    "sg:province":"FL",
    "wof:name":"Bank Of America",
    "wof:placetype":"venue"
},
  "geometry": {"coordinates":[-81.663889,28.940429],"type":"Point"}
}