{
  "type": "Feature",
  "properties": {
    "iso:country":"US",
    "sg:address":"15950 Bay Vista Dr",
    "sg:city":"Clearwater",
    "sg:classifiers":[
        {
            "category":"Utilities",
            "subcategory":"Telephone",
            "type":"Services"
        }
    ],
    "sg:phone":"+1 727 532 3948",
    "sg:postcode":"33760",
    "sg:province":"FL",
    "sg:tags":[
        "communication",
        "datum"
    ],
    "sg:website":"www.techforce.com",
    "wof:name":"Tech Force",
    "wof:placetype":"venue"
},
  "geometry": {"coordinates":[-82.710448,27.917202],"type":"Point"}
}