{
  "type": "Feature",
  "properties": {
    "iso:country":"US",
    "sg:address":"1411 N Betty Ln",
    "sg:city":"Clearwater",
    "sg:classifiers":[
        {
            "category":"Personal",
            "subcategory":"Beauty Salon",
            "type":"Services"
        }
    ],
    "sg:phone":"+1 727 442 3939",
    "sg:postcode":"33755",
    "sg:province":"FL",
    "wof:name":"Flawless Hair Nail & Barber",
    "wof:placetype":"venue"
},
  "geometry": {"coordinates":[-82.783562,27.979756],"type":"Point"}
}