{
  "type": "Feature",
  "properties": {
    "iso:country":"US",
    "sg:address":"3842 Newberry Rd",
    "sg:city":"Gainesville",
    "sg:classifiers":[
        {
            "category":"Banks & Credit Unions",
            "subcategory":"Bank",
            "type":"Services"
        }
    ],
    "sg:phone":"+1 352 333 0243",
    "sg:postcode":"32607",
    "sg:province":"FL",
    "sg:tags":[
        "loan",
        "real estate"
    ],
    "wof:name":"First Horizon Home Loan Corp",
    "wof:placetype":"venue"
},
  "geometry": {"coordinates":[-82.382237,29.652885],"type":"Point"}
}