{
  "type": "Feature",
  "properties": {
    "iso:country":"US",
    "sg:address":"13494 74th Ave N",
    "sg:city":"Seminole",
    "sg:classifiers":[
        {
            "category":"Retail",
            "subcategory":"Car Wash",
            "type":"Services"
        }
    ],
    "sg:phone":"+1 727 391 0360",
    "sg:postcode":"33776",
    "sg:province":"FL",
    "sg:tags":[
        "carwash"
    ],
    "wof:name":"Ride N Shine Inc",
    "wof:placetype":"venue"
},
  "geometry": {"coordinates":[-82.82475700000001,27.840039],"type":"Point"}
}