{
  "type": "Feature",
  "properties": {
    "addr:full":"2112 Lytham Ln Tallahassee FL 32308",
    "addr:housenumber":"2112",
    "addr:postcode":"32308",
    "addr:street":"Lytham Ln",
    "iso:country":"US",
    "sg:address":"2112 Lytham Ln",
    "sg:city":"Tallahassee",
    "sg:classifiers":[
        {
            "category":"Shopping",
            "subcategory":"Jewelry",
            "type":"Retail Goods"
        }
    ],
    "sg:phone":"+1 850 297 0014",
    "sg:postcode":"32308",
    "sg:province":"FL",
    "sg:tags":[
        "clocks"
    ],
    "wof:name":"Niesens Clocks Inc",
    "wof:placetype":"venue"
},
  "geometry": {"coordinates":[-84.240753,30.496273],"type":"Point"}
}