{
  "type": "Feature",
  "properties": {
    "addr:full":"223 E Hallandale Beach Blvd Hallandale Beach FL 33009",
    "addr:housenumber":"223",
    "addr:postcode":"33009",
    "addr:street":"E Hallandale Beach Blvd",
    "iso:country":"US",
    "sg:address":"223 E Hallandale Beach Blvd",
    "sg:city":"Hallandale Beach",
    "sg:classifiers":[
        {
            "category":"Health Services",
            "subcategory":"Podiatrist",
            "type":"Services"
        }
    ],
    "sg:phone":"+1 954 458 3668",
    "sg:postcode":"33009",
    "sg:province":"FL",
    "wof:name":"Semer Foot & Ankle Center",
    "wof:placetype":"venue"
},
  "geometry": {"coordinates":[-80.145426,25.985685],"type":"Point"}
}