{
  "type": "Feature",
  "properties": {
    "addr:full":"3701 NE 167th St North Miami Beach FL 33160",
    "addr:housenumber":"3701",
    "addr:postcode":"33160",
    "addr:street":"Ne 167Th St",
    "iso:country":"US",
    "sg:address":"3701 NE 167th St",
    "sg:city":"North Miami Beach",
    "sg:classifiers":[
        {
            "category":"Sports & Exercise",
            "subcategory":"Sports Center",
            "type":"Entertainment"
        },
        {
            "category":"Arena",
            "subcategory":"Sports Club",
            "type":"Entertainment"
        }
    ],
    "sg:phone":"+1 305 621 0855",
    "sg:postcode":"33160",
    "sg:province":"FL",
    "sg:tags":[
        "professional",
        "amateur",
        "team"
    ],
    "wof:name":"Palmetto Sports Fisherman Club Inc",
    "wof:placetype":"venue"
},
  "geometry": {"coordinates":[-80.13539900000001,25.933701],"type":"Point"}
}