{
  "type": "Feature",
  "properties": {
    "addr:full":"1940 N Commerce Pkwy Fort Lauderdale FL 33326",
    "addr:housenumber":"1940",
    "addr:postcode":"33326",
    "addr:street":"N Commerce Pkwy",
    "iso:country":"US",
    "sg:address":"1940 N Commerce Pkwy",
    "sg:city":"Fort Lauderdale",
    "sg:classifiers":[
        {
            "category":"Professional",
            "subcategory":"Lawyer & Legal Services",
            "type":"Services"
        }
    ],
    "sg:phone":"+1 954 349 2204",
    "sg:postcode":"33326",
    "sg:province":"FL",
    "wof:name":"Raudt Kvin A Attrney At Law PA",
    "wof:placetype":"venue"
},
  "geometry": {"coordinates":[-80.36511299999999,26.096987],"type":"Point"}
}