{
  "type": "Feature",
  "properties": {
    "iso:country":"US",
    "sg:address":"22631 Magnolia Trace Blvd",
    "sg:city":"Lutz",
    "sg:classifiers":[
        {
            "category":"Place Of Worship",
            "type":"Public Place"
        }
    ],
    "sg:phone":"+1 813 948 2044",
    "sg:postcode":"33549",
    "sg:province":"FL",
    "sg:tags":[
        "church"
    ],
    "wof:name":"Zion Church Inc",
    "wof:placetype":"venue"
},
  "geometry": {"coordinates":[-82.442087,28.175235],"type":"Point"}
}