{
  "type": "Feature",
  "properties": {
    "addr:full":"1181 S Rogers Cir Boca Raton FL 33487",
    "addr:housenumber":"1181",
    "addr:postcode":"33487",
    "addr:street":"S Rogers Cir",
    "iso:country":"US",
    "sg:address":"1181 S Rogers Cir",
    "sg:city":"Boca Raton",
    "sg:classifiers":[
        {
            "category":"Professional",
            "subcategory":"Management & Consulting",
            "type":"Services"
        }
    ],
    "sg:phone":"+1 561 994 3833",
    "sg:postcode":"33487",
    "sg:province":"FL",
    "sg:tags":[
        "marketing",
        "agency",
        "relations",
        "advertising",
        "consultant",
        "public"
    ],
    "wof:name":"Marketing Quorum Inc",
    "wof:placetype":"venue"
},
  "geometry": {"coordinates":[-80.11245599999999,26.403208],"type":"Point"}
}