{
  "type": "Feature",
  "properties": {
    "iso:country":"US",
    "sg:address":"821 NE 1st Pl",
    "sg:city":"Hialeah",
    "sg:classifiers":[
        {
            "category":"Building & Trades",
            "subcategory":"Construction",
            "type":"Services"
        }
    ],
    "sg:phone":"+1 305 884 4823",
    "sg:postcode":"33010",
    "sg:province":"FL",
    "sg:tags":[
        "house"
    ],
    "wof:name":"Remodeling Enterprises Inc",
    "wof:placetype":"venue"
},
  "geometry": {"coordinates":[-80.263542,25.824078],"type":"Point"}
}