{
  "type": "Feature",
  "properties": {
    "iso:country":"US",
    "sg:address":"2616 US-19",
    "sg:city":"Holiday",
    "sg:classifiers":[
        {
            "category":"Restaurant",
            "type":"Food & Drink"
        }
    ],
    "sg:menulink":"http://www.allmenus.com/fl/new-port-richey/111233-the-german-restaurant/menu/",
    "sg:phone":"+1 727 937 7400",
    "sg:postcode":"34690",
    "sg:province":"FL",
    "sg:tags":[
        "german"
    ],
    "wof:name":"The German Restaurant",
    "wof:placetype":"venue"
},
  "geometry": {"coordinates":[-82.739771,28.19686],"type":"Point"}
}