{
  "type": "Feature",
  "properties": {
    "iso:country":"US",
    "sg:address":"713 SE 6th Ct",
    "sg:city":"Fort Lauderdale",
    "sg:classifiers":[
        {
            "category":"Professional",
            "type":"Services"
        }
    ],
    "sg:phone":"+1 954 760 7664",
    "sg:postcode":"33301",
    "sg:province":"FL",
    "wof:name":"Boltar Marine Inc",
    "wof:placetype":"venue"
},
  "geometry": {"coordinates":[-80.135037,26.114117],"type":"Point"}
}