{
  "type": "Feature",
  "properties": {
    "addr:full":"3047 NW 26th St Fort Lauderdale FL 33311",
    "addr:housenumber":"3047",
    "addr:postcode":"33311",
    "addr:street":"Nw 26Th St",
    "iso:country":"US",
    "sg:address":"3047 NW 26th St",
    "sg:city":"Fort Lauderdale",
    "sg:classifiers":[
        {
            "category":"Wholesale",
            "subcategory":"Medical Equipment & Supplies",
            "type":"Manufacturing & Wholesale Goods"
        },
        {
            "category":"Shopping",
            "type":"Retail Goods"
        }
    ],
    "sg:phone":"+1 954 486 4403",
    "sg:postcode":"33311",
    "sg:province":"FL",
    "sg:tags":[
        "physician",
        "surgeon"
    ],
    "wof:name":"Reliant Medical Supplies Inc",
    "wof:placetype":"venue"
},
  "geometry": {"coordinates":[-80.185096,26.158132],"type":"Point"}
}