{
  "type": "Feature",
  "properties": {
    "iso:country":"US",
    "sg:address":"701 Brickell Ave Ste 2080",
    "sg:city":"Miami",
    "sg:classifiers":[
        {
            "category":"Banks & Credit Unions",
            "subcategory":"Investment Brokerage",
            "type":"Services"
        }
    ],
    "sg:phone":"+1 305 400 9982",
    "sg:postcode":"33131",
    "sg:province":"FL",
    "sg:tags":[
        "investing"
    ],
    "wof:name":"Colbert Investment Management",
    "wof:placetype":"venue"
},
  "geometry": {"coordinates":[-80.190223,25.767015],"type":"Point"}
}