{
  "type": "Feature",
  "properties": {
    "iso:country":"US",
    "sg:address":"4107 Hollow Trail Dr",
    "sg:city":"Tampa",
    "sg:classifiers":[
        {
            "category":"Manufacturing",
            "subcategory":"Apparel",
            "type":"Manufacturing & Wholesale Goods"
        }
    ],
    "sg:phone":"+1 813 963 6766",
    "sg:postcode":"33624",
    "sg:province":"FL",
    "wof:name":"Stitchcraft of Tampa Bay",
    "wof:placetype":"venue"
},
  "geometry": {"coordinates":[-82.51597099999999,28.103246],"type":"Point"}
}