{
  "type": "Feature",
  "properties": {
    "iso:country":"US",
    "sg:address":"14811 Turner Rd",
    "sg:city":"Tampa",
    "sg:classifiers":[
        {
            "category":"Restaurant",
            "type":"Food & Drink"
        }
    ],
    "sg:phone":"+1 813 968 9898",
    "sg:postcode":"33624",
    "sg:province":"FL",
    "sg:tags":[
        "eating"
    ],
    "wof:name":"Pastamore",
    "wof:placetype":"venue"
},
  "geometry": {"coordinates":[-82.54181199999999,28.082642],"type":"Point"}
}