{
  "type": "Feature",
  "properties": {
    "addr:full":"13311 44th Pl N West Palm Beach FL 33411",
    "addr:housenumber":"13311",
    "addr:postcode":"33411",
    "addr:street":"44Th Pl N",
    "iso:country":"US",
    "sg:address":"13311 44th Pl N",
    "sg:city":"West Palm Beach",
    "sg:classifiers":[
        {
            "category":"Building & Trades",
            "subcategory":"Construction",
            "type":"Services"
        }
    ],
    "sg:phone":"+1 561 798 4132",
    "sg:postcode":"33411",
    "sg:province":"FL",
    "sg:tags":[
        "floor",
        "laying",
        "contractor"
    ],
    "wof:name":"Keefe Tmothy Crpt Installation",
    "wof:placetype":"venue"
},
  "geometry": {"coordinates":[-80.253294,26.742403],"type":"Point"}
}