{
  "type": "Feature",
  "properties": {
    "iso:country":"US",
    "sg:address":"6215 N Kendall Dr",
    "sg:city":"Miami",
    "sg:classifiers":[
        {
            "category":"Wholesale",
            "subcategory":"Computers",
            "type":"Manufacturing & Wholesale Goods"
        }
    ],
    "sg:phone":"+1 786 287 4581",
    "sg:postcode":"33156",
    "sg:province":"FL",
    "sg:tags":[
        "hardware",
        "parts",
        "export",
        "software"
    ],
    "wof:name":"Aldo of Miami Inc",
    "wof:placetype":"venue"
},
  "geometry": {"coordinates":[-80.295362,25.689217],"type":"Point"}
}