{
  "type": "Feature",
  "properties": {
    "addr:full":"18505 SW 288th St Homestead FL 33030",
    "addr:housenumber":"18505",
    "addr:postcode":"33030",
    "addr:street":"Sw 288Th St",
    "iso:country":"US",
    "sg:address":"18505 SW 288th St",
    "sg:city":"Homestead",
    "sg:classifiers":[
        {
            "category":"Organizations",
            "subcategory":"Religious Organization",
            "type":"Services"
        }
    ],
    "sg:phone":"+1 305 246 0944",
    "sg:postcode":"33030",
    "sg:province":"FL",
    "sg:tags":[
        "church"
    ],
    "wof:name":"Jehovah's Witnesses",
    "wof:placetype":"venue"
},
  "geometry": {"coordinates":[-80.489762,25.498974],"type":"Point"}
}