{
  "type": "Feature",
  "properties": {
    "iso:country":"US",
    "sg:address":"126 N Montclair Ave",
    "sg:city":"Brandon",
    "sg:classifiers":[
        {
            "category":"Education",
            "subcategory":"Special Training",
            "type":"Public Place"
        }
    ],
    "sg:phone":"+1 813 643 2559",
    "sg:postcode":"33510",
    "sg:province":"FL",
    "wof:name":"Brandon Reading Clinic",
    "wof:placetype":"venue"
},
  "geometry": {"coordinates":[-82.279681,27.939407],"type":"Point"}
}