{
  "type": "Feature",
  "properties": {
    "iso:country":"US",
    "sg:address":"9555 Co Rd 733",
    "sg:city":"Webster",
    "sg:classifiers":[
        {
            "category":"Wholesale",
            "subcategory":"Non-durable Goods",
            "type":"Manufacturing & Wholesale Goods"
        }
    ],
    "sg:phone":"+1 352 569 0444",
    "sg:postcode":"33597",
    "sg:province":"FL",
    "sg:tags":[
        "merchandise",
        "general"
    ],
    "wof:name":"Webster Imports",
    "wof:placetype":"venue"
},
  "geometry": {"coordinates":[-82.065084,28.617196],"type":"Point"}
}