{
  "type": "Feature",
  "properties": {
    "addr:full":"7566 Hart Dr Fort Myers FL 33917",
    "addr:housenumber":"7566",
    "addr:postcode":"33917",
    "addr:street":"Hart Dr",
    "iso:country":"US",
    "sg:address":"7566 Hart Dr",
    "sg:city":"Fort Myers",
    "sg:classifiers":[
        {
            "category":"Freight",
            "type":"Transportation"
        }
    ],
    "sg:phone":"+1 239 731 9832",
    "sg:postcode":"33917",
    "sg:province":"FL",
    "wof:name":"Accel Transportation",
    "wof:placetype":"venue"
},
  "geometry": {"coordinates":[-81.86597500000001,26.701324],"type":"Point"}
}