{
  "type": "Feature",
  "properties": {
    "iso:country":"US",
    "sg:address":"1203 65th St NW",
    "sg:city":"Bradenton",
    "sg:classifiers":[
        {
            "category":"Personal",
            "subcategory":"Barber",
            "type":"Services"
        }
    ],
    "sg:phone":"+1 941 792 6847",
    "sg:postcode":"34209",
    "sg:province":"FL",
    "sg:tags":[
        "shop"
    ],
    "wof:name":"Fredericks Barber Shop",
    "wof:placetype":"venue"
},
  "geometry": {"coordinates":[-82.62582399999999,27.510348],"type":"Point"}
}