{
  "type": "Feature",
  "properties": {
    "iso:country":"US",
    "sg:address":"9120 Galleria Ct",
    "sg:city":"Naples",
    "sg:classifiers":[
        {
            "category":"Health Services",
            "subcategory":"Doctor",
            "type":"Services"
        }
    ],
    "sg:phone":"+1 239 594 8817",
    "sg:postcode":"34109",
    "sg:province":"FL",
    "sg:tags":[
        "dentist"
    ],
    "wof:name":"George Hoop DDS",
    "wof:placetype":"venue"
},
  "geometry": {"coordinates":[-81.770866,26.247669],"type":"Point"}
}