{
  "type": "Feature",
  "properties": {
    "iso:country":"US",
    "sg:address":"1741 Pine Ave",
    "sg:city":"Winter Park",
    "sg:classifiers":[
        {
            "category":"Communications",
            "subcategory":"Television Station",
            "type":"Services"
        }
    ],
    "sg:phone":"+1 407 644 7348",
    "sg:postcode":"32789",
    "sg:province":"FL",
    "wof:name":"Ledford Communications In",
    "wof:placetype":"venue"
},
  "geometry": {"coordinates":[-81.329387,28.610934],"type":"Point"}
}