{
  "type": "Feature",
  "properties": {
    "iso:country":"US",
    "sg:address":"432 E 35th St",
    "sg:city":"Hialeah",
    "sg:classifiers":[
        {
            "category":"Professional",
            "subcategory":"Management & Consulting",
            "type":"Services"
        }
    ],
    "sg:phone":"+1 305 693 3511",
    "sg:postcode":"33013",
    "sg:province":"FL",
    "sg:tags":[
        "party",
        "supply"
    ],
    "wof:name":"Party Works of Miami Inc",
    "wof:placetype":"venue"
},
  "geometry": {"coordinates":[-80.27323800000001,25.854173],"type":"Point"}
}