{
  "type": "Feature",
  "properties": {
    "addr:full":"4891 NW 109th Ct Miami FL 33178",
    "addr:housenumber":"4891",
    "addr:postcode":"33178",
    "addr:street":"Nw 109Th Ct",
    "iso:country":"US",
    "sg:address":"4891 NW 109th Ct",
    "sg:city":"Miami",
    "sg:classifiers":[
        {
            "category":"Shopping",
            "subcategory":"Beauty & Cosmetics",
            "type":"Retail Goods"
        }
    ],
    "sg:phone":"+1 305 470 2434",
    "sg:postcode":"33178",
    "sg:province":"FL",
    "sg:tags":[
        "merchandise"
    ],
    "wof:name":"Jafra Cosmetics International",
    "wof:placetype":"venue"
},
  "geometry": {"coordinates":[-80.37408000000001,25.817638],"type":"Point"}
}