{
  "type": "Feature",
  "properties": {
    "iso:country":"US",
    "sg:address":"7480 Fairway Dr",
    "sg:city":"Hialeah",
    "sg:classifiers":[
        {
            "category":"Health Services",
            "subcategory":"Doctor",
            "type":"Services"
        }
    ],
    "sg:phone":"+1 305 558 1598",
    "sg:postcode":"33014",
    "sg:province":"FL",
    "sg:tags":[
        "physician",
        "surgeon"
    ],
    "wof:name":"Childrens Medical Inc",
    "wof:placetype":"venue"
},
  "geometry": {"coordinates":[-80.320893,25.911743],"type":"Point"}
}