{
  "type": "Feature",
  "properties": {
    "addr:full":"2137 NW 29th St Fort Lauderdale FL 33311",
    "addr:housenumber":"2137",
    "addr:postcode":"33311",
    "addr:street":"Nw 29Th St",
    "iso:country":"US",
    "sg:address":"2137 NW 29th St",
    "sg:city":"Fort Lauderdale",
    "sg:classifiers":[
        {
            "category":"Building & Trades",
            "subcategory":"Construction",
            "type":"Services"
        }
    ],
    "sg:phone":"+1 954 563 6200",
    "sg:postcode":"33311",
    "sg:province":"FL",
    "sg:tags":[
        "roofing",
        "contractor",
        "water",
        "genus",
        "painting",
        "proofing"
    ],
    "wof:name":"Weather Guard Cnstr Svcs LLC",
    "wof:placetype":"venue"
},
  "geometry": {"coordinates":[-80.17221000000001,26.162475],"type":"Point"}
}