{
  "type": "Feature",
  "properties": {
    "iso:country":"US",
    "sg:address":"11136 English Moss Ln",
    "sg:city":"Jacksonville",
    "sg:classifiers":[
        {
            "category":"Wholesale",
            "subcategory":"Durable Goods & Equipment",
            "type":"Manufacturing & Wholesale Goods"
        }
    ],
    "sg:phone":"+1 904 571 2384",
    "sg:postcode":"32257",
    "sg:province":"FL",
    "wof:name":"A E Pierce Supply",
    "wof:placetype":"venue"
},
  "geometry": {"coordinates":[-81.57981599999999,30.171574],"type":"Point"}
}