{
  "type": "Feature",
  "properties": {
    "iso:country":"US",
    "sg:address":"1111 S 14th St",
    "sg:city":"Leesburg",
    "sg:classifiers":[
        {
            "category":"Shopping",
            "subcategory":"Used Merchandise",
            "type":"Retail Goods"
        }
    ],
    "sg:phone":"+1 352 365 9977",
    "sg:postcode":"34748",
    "sg:province":"FL",
    "wof:name":"Morning Glori Antique",
    "wof:placetype":"venue"
},
  "geometry": {"coordinates":[-81.887773,28.80031],"type":"Point"}
}