{
  "type": "Feature",
  "properties": {
    "iso:country":"US",
    "sg:address":"833 Votaw Rd",
    "sg:city":"Apopka",
    "sg:classifiers":[
        {
            "category":"Retail",
            "subcategory":"Photofinishing",
            "type":"Services"
        }
    ],
    "sg:phone":"+1 407 886 4647",
    "sg:postcode":"32703",
    "sg:province":"FL",
    "sg:tags":[
        "shop",
        "laboratory",
        "beauty"
    ],
    "wof:name":"Colour Lab Salon",
    "wof:placetype":"venue"
},
  "geometry": {"coordinates":[-81.493799,28.683942],"type":"Point"}
}