{
  "type": "Feature",
  "properties": {
    "addr:full":"2199 W Flagler St Miami FL 33135",
    "addr:housenumber":"2199",
    "addr:postcode":"33135",
    "addr:street":"W Flagler St",
    "iso:country":"US",
    "sg:address":"2199 W Flagler St",
    "sg:city":"Miami",
    "sg:classifiers":[
        {
            "category":"Shopping",
            "subcategory":"Shoes",
            "type":"Retail Goods"
        }
    ],
    "sg:phone":"+1 305 642 0038",
    "sg:postcode":"33135",
    "sg:province":"FL",
    "wof:name":"Payless Shoe Source",
    "wof:placetype":"venue"
},
  "geometry": {"coordinates":[-80.230271,25.772574],"type":"Point"}
}