{
  "type": "Feature",
  "properties": {
    "iso:country":"US",
    "sg:address":"6331 Roosevelt Blvd",
    "sg:city":"Jacksonville",
    "sg:classifiers":[
        {
            "category":"Utilities",
            "subcategory":"Mobile Phone",
            "type":"Services"
        }
    ],
    "sg:phone":"+1 904 771 0228",
    "sg:postcode":"32244",
    "sg:province":"FL",
    "sg:tags":[
        "telephone",
        "cellular"
    ],
    "wof:name":"Express Wireless Vi",
    "wof:placetype":"venue"
},
  "geometry": {"coordinates":[-81.698016,30.233815],"type":"Point"}
}