{
  "type": "Feature",
  "properties": {
    "iso:country":"US",
    "sg:address":"12 W Interlake Blvd",
    "sg:city":"Lake Placid",
    "sg:classifiers":[
        {
            "category":"Government",
            "subcategory":"Fire Station",
            "type":"Public Place"
        }
    ],
    "sg:phone":"+1 863 699 3753",
    "sg:postcode":"33852",
    "sg:province":"FL",
    "sg:tags":[
        "department"
    ],
    "wof:name":"Lake Placid Fire Dept",
    "wof:placetype":"venue"
},
  "geometry": {"coordinates":[-81.36710600000001,27.297168],"type":"Point"}
}