{
  "type": "Feature",
  "properties": {
    "iso:country":"US",
    "sg:address":"6691 SE 110th St",
    "sg:city":"Belleview",
    "sg:classifiers":[
        {
            "category":"Shopping",
            "subcategory":"Used Merchandise",
            "type":"Retail Goods"
        }
    ],
    "sg:phone":"+1 352 347 7107",
    "sg:postcode":"34420",
    "sg:province":"FL",
    "sg:tags":[
        "furniture"
    ],
    "wof:name":"Ziggy's New & Used Furniture",
    "wof:placetype":"venue"
},
  "geometry": {"coordinates":[-82.041372,29.062285],"type":"Point"}
}