{
  "type": "Feature",
  "properties": {
    "iso:country":"US",
    "sg:address":"650 Alabama Ave",
    "sg:city":"Apopka",
    "sg:classifiers":[
        {
            "category":"Organizations",
            "subcategory":"Religious Organization",
            "type":"Services"
        }
    ],
    "sg:phone":"+1 407 889 2636",
    "sg:postcode":"32703",
    "sg:province":"FL",
    "sg:tags":[
        "church"
    ],
    "wof:name":"Church Of Christ",
    "wof:placetype":"venue"
},
  "geometry": {"coordinates":[-81.502123,28.670102],"type":"Point"}
}