{
  "type": "Feature",
  "properties": {
    "iso:country":"US",
    "sg:address":"209 NW 8th Ave",
    "sg:city":"Dania",
    "sg:classifiers":[
        {
            "category":"Restaurant",
            "type":"Food & Drink"
        }
    ],
    "sg:phone":"+1 954 927 3139",
    "sg:postcode":"33004",
    "sg:province":"FL",
    "sg:tags":[
        "eating"
    ],
    "wof:name":"Perrys Soul Food Restaurant",
    "wof:placetype":"venue"
},
  "geometry": {"coordinates":[-80.14834399999999,26.057389],"type":"Point"}
}