{
  "type": "Feature",
  "properties": {
    "addr:full":"1729 E 7th Ave Tampa FL 33605",
    "addr:housenumber":"1729",
    "addr:postcode":"33605",
    "addr:street":"E 7Th Ave",
    "iso:country":"US",
    "sg:address":"1729 E 7th Ave",
    "sg:city":"Tampa",
    "sg:classifiers":[
        {
            "category":"Cafe",
            "type":"Food & Drink"
        }
    ],
    "sg:menulink":"http://www.allmenus.com/fl/tampa/271496-la-creperia-cafe/menu/",
    "sg:phone":"+1 813 248 9700",
    "sg:postcode":"33605",
    "sg:province":"FL",
    "sg:tags":[
        "american",
        "crepe"
    ],
    "wof:name":"LA Creperia Cafe",
    "wof:placetype":"venue"
},
  "geometry": {"coordinates":[-82.440077,27.960128],"type":"Point"}
}