{
  "type": "Feature",
  "properties": {
    "iso:country":"US",
    "sg:address":"5600 N US Hwy 1",
    "sg:city":"Melbourne",
    "sg:classifiers":[
        {
            "category":"Restaurant",
            "type":"Food & Drink"
        }
    ],
    "sg:phone":"+1 321 242 6333",
    "sg:postcode":"32940",
    "sg:province":"FL",
    "wof:name":"Blimpie Subs & Salads",
    "wof:placetype":"venue"
},
  "geometry": {"coordinates":[-80.66076099999999,28.201719],"type":"Point"}
}