{
  "type": "Feature",
  "properties": {
    "iso:country":"US",
    "sg:address":"845 Edgewood Ave W",
    "sg:city":"Jacksonville",
    "sg:classifiers":[
        {
            "category":"Real Estate",
            "subcategory":"Real Estate Agent",
            "type":"Services"
        }
    ],
    "sg:phone":"+1 904 713 0753",
    "sg:postcode":"32208",
    "sg:province":"FL",
    "wof:name":"James Daniels Realty Inc",
    "wof:placetype":"venue"
},
  "geometry": {"coordinates":[-81.670051,30.392476],"type":"Point"}
}