{
  "type": "Feature",
  "properties": {
    "addr:full":"7420 NW 5th St Plantation FL 33317",
    "addr:housenumber":"7420",
    "addr:postcode":"33317",
    "addr:street":"Nw 5Th St",
    "iso:country":"US",
    "sg:address":"7420 NW 5th St",
    "sg:city":"Plantation",
    "sg:classifiers":[
        {
            "category":"Professional",
            "subcategory":"Testing Lab",
            "type":"Services"
        }
    ],
    "sg:phone":"+1 954 797 1471",
    "sg:postcode":"33317",
    "sg:province":"FL",
    "sg:tags":[
        "analytical",
        "laboratory"
    ],
    "wof:name":"Litodent Lab Inc",
    "wof:placetype":"venue"
},
  "geometry": {"coordinates":[-80.247393,26.128253],"type":"Point"}
}