{
  "type": "Feature",
  "properties": {
    "iso:country":"US",
    "sg:address":"1095 US Hwy 92",
    "sg:city":"Auburndale",
    "sg:classifiers":[
        {
            "category":"Real Estate",
            "subcategory":"Real Estate Operator",
            "type":"Services"
        }
    ],
    "sg:phone":"+1 863 665 3855",
    "sg:postcode":"33823",
    "sg:province":"FL",
    "sg:tags":[
        "mobile",
        "home",
        "community"
    ],
    "wof:name":"Central Leisure Lake Mobile Hm",
    "wof:placetype":"venue"
},
  "geometry": {"coordinates":[-81.822236,28.056637],"type":"Point"}
}