{
  "type": "Feature",
  "properties": {
    "addr:full":"2617 Florida Keys Ave Tampa FL 33621",
    "addr:housenumber":"2617",
    "addr:postcode":"33621",
    "addr:street":"Florida Keys Ave",
    "iso:country":"US",
    "sg:address":"2617 Florida Keys Ave",
    "sg:city":"Tampa",
    "sg:classifiers":[
        {
            "category":"Government",
            "subcategory":"Office",
            "type":"Public Place"
        }
    ],
    "sg:phone":"+1 813 828 2663",
    "sg:postcode":"33621",
    "sg:province":"FL",
    "sg:tags":[
        "national",
        "security"
    ],
    "wof:name":"McDill Airforce Base",
    "wof:placetype":"venue"
},
  "geometry": {"coordinates":[-82.48459699999999,27.852566],"type":"Point"}
}