{
  "type": "Feature",
  "properties": {
    "addr:full":"814 Bald Eagle Dr Marco Island FL 34145",
    "addr:housenumber":"814",
    "addr:postcode":"34145",
    "addr:street":"Bald Eagle Dr",
    "iso:country":"US",
    "sg:address":"814 Bald Eagle Dr",
    "sg:city":"Marco Island",
    "sg:classifiers":[
        {
            "category":"Home & Garden",
            "subcategory":"Building Materials",
            "type":"Retail Goods"
        }
    ],
    "sg:phone":"+1 239 642 3236",
    "sg:postcode":"34145",
    "sg:province":"FL",
    "sg:tags":[
        "paint"
    ],
    "sg:website":"www.sherwinwilliams.com",
    "wof:name":"Sherwin-Williams Paints",
    "wof:placetype":"venue"
},
  "geometry": {"coordinates":[-81.727046,25.959471],"type":"Point"}
}