{
  "type": "Feature",
  "properties": {
    "iso:country":"US",
    "sg:address":"5000 Clyde Morris Blvd",
    "sg:city":"Port Orange",
    "sg:classifiers":[
        {
            "category":"Retail",
            "subcategory":"Laundry & Dry Cleaning",
            "type":"Services"
        }
    ],
    "sg:phone":"+1 386 788 6100",
    "sg:postcode":"32127",
    "sg:province":"FL",
    "sg:tags":[
        "cleaners"
    ],
    "wof:name":"Corner Cleaners",
    "wof:placetype":"venue"
},
  "geometry": {"coordinates":[-81.01849199999999,29.114258],"type":"Point"}
}