{
  "type": "Feature",
  "properties": {
    "addr:full":"1 S Orange Ave Orlando FL 32801",
    "addr:housenumber":"1",
    "addr:postcode":"32801",
    "addr:street":"S Orange Ave",
    "iso:country":"US",
    "sg:address":"1 S Orange Ave",
    "sg:city":"Orlando",
    "sg:classifiers":[
        {
            "category":"Food & Beverages",
            "subcategory":"Dairy",
            "type":"Retail Goods"
        }
    ],
    "sg:phone":"+1 407 426 8585",
    "sg:postcode":"32801",
    "sg:province":"FL",
    "sg:tags":[
        "product"
    ],
    "wof:name":"Philly Italian Ice",
    "wof:placetype":"venue"
},
  "geometry": {"coordinates":[-81.37904399999999,28.54213],"type":"Point"}
}