{
  "type": "Feature",
  "properties": {
    "iso:country":"US",
    "sg:address":"4701 N Himes Ave",
    "sg:city":"Tampa",
    "sg:classifiers":[
        {
            "category":"Education",
            "subcategory":"Special Training",
            "type":"Public Place"
        },
        {
            "category":"Education",
            "subcategory":"School",
            "type":"Public Place"
        }
    ],
    "sg:phone":"+1 813 877 5344",
    "sg:postcode":"33614",
    "sg:province":"FL",
    "sg:tags":[
        "high",
        "educational",
        "k-",
        "private"
    ],
    "sg:website":"http://www.jesuittampa.org",
    "wof:name":"Jesuit High School",
    "wof:placetype":"venue"
},
  "geometry": {"coordinates":[-82.501186,27.986842],"type":"Point"}
}