{
  "type": "Feature",
  "properties": {
    "iso:country":"US",
    "sg:address":"983 W Desoto St",
    "sg:city":"Clermont",
    "sg:classifiers":[
        {
            "category":"Social Services",
            "subcategory":"Child Care",
            "type":"Services"
        }
    ],
    "sg:phone":"+1 352 243 0993",
    "sg:postcode":"34711",
    "sg:province":"FL",
    "sg:tags":[
        "day"
    ],
    "wof:name":"South Lake Montessori School",
    "wof:placetype":"venue"
},
  "geometry": {"coordinates":[-81.770864,28.554207],"type":"Point"}
}