{
  "type": "Feature",
  "properties": {
    "iso:country":"US",
    "sg:address":"2209 75th St W",
    "sg:city":"Bradenton",
    "sg:classifiers":[
        {
            "category":"Organizations",
            "subcategory":"Religious Organization",
            "type":"Services"
        }
    ],
    "sg:phone":"+1 941 792 0870",
    "sg:postcode":"34209",
    "sg:province":"FL",
    "sg:tags":[
        "synagogue"
    ],
    "wof:name":"Temple Beth El",
    "wof:placetype":"venue"
},
  "geometry": {"coordinates":[-82.63670999999999,27.477933],"type":"Point"}
}