{
  "type": "Feature",
  "properties": {
    "iso:country":"US",
    "sg:address":"8203 World Center Dr",
    "sg:city":"Orlando",
    "sg:classifiers":[
        {
            "category":"Travel",
            "subcategory":"Travel Agent",
            "type":"Entertainment"
        }
    ],
    "sg:phone":"+1 407 809 0217",
    "sg:postcode":"32821",
    "sg:province":"FL",
    "sg:tags":[
        "agency",
        "bureau"
    ],
    "wof:name":"Premier Getaways",
    "wof:placetype":"venue"
},
  "geometry": {"coordinates":[-81.490951,28.357608],"type":"Point"}
}