{
  "type": "Feature",
  "properties": {
    "iso:country":"US",
    "sg:address":"15560 Gulf Blvd",
    "sg:city":"Saint Petersburg",
    "sg:classifiers":[
        {
            "category":"Real Estate",
            "subcategory":"Developer",
            "type":"Services"
        }
    ],
    "sg:phone":"+1 727 398 7837",
    "sg:postcode":"33708",
    "sg:province":"FL",
    "wof:name":"Afb Development Inc",
    "wof:placetype":"venue"
},
  "geometry": {"coordinates":[-82.807103,27.8054],"type":"Point"}
}