{
  "type": "Feature",
  "properties": {
    "iso:country":"US",
    "sg:address":"100 SW 62nd Ave",
    "sg:city":"Miami",
    "sg:classifiers":[
        {
            "category":"Shopping",
            "type":"Retail Goods"
        }
    ],
    "sg:phone":"+1 305 725 5567",
    "sg:postcode":"33144",
    "sg:province":"FL",
    "sg:tags":[
        "equipment",
        "telecommunication"
    ],
    "wof:name":"Elite Mobile Communications",
    "wof:placetype":"venue"
},
  "geometry": {"coordinates":[-80.29607799999999,25.768801],"type":"Point"}
}