{
  "type": "Feature",
  "properties": {
    "iso:country":"US",
    "sg:address":"523 Moon Rise Dr",
    "sg:city":"Daytona Beach",
    "sg:classifiers":[
        {
            "category":"Organizations",
            "subcategory":"Community Association",
            "type":"Services"
        }
    ],
    "sg:phone":"+1 386 756 6220",
    "sg:postcode":"32127",
    "sg:province":"FL",
    "wof:name":"Golden Pond Estates Assn",
    "wof:placetype":"venue"
},
  "geometry": {"coordinates":[-80.995186,29.084554],"type":"Point"}
}