{
  "type": "Feature",
  "properties": {
    "iso:country":"US",
    "sg:address":"4353 S Manhattan Ave",
    "sg:city":"Tampa",
    "sg:classifiers":[
        {
            "category":"Health Services",
            "subcategory":"Doctor",
            "type":"Services"
        }
    ],
    "sg:phone":"+1 813 805 0606",
    "sg:postcode":"33611",
    "sg:province":"FL",
    "sg:tags":[
        "dentist"
    ],
    "wof:name":"Melva G Ely DDS",
    "wof:placetype":"venue"
},
  "geometry": {"coordinates":[-82.518522,27.901795],"type":"Point"}
}