{
  "type": "Feature",
  "properties": {
    "iso:country":"US",
    "sg:address":"610 Capt'n Kate Ct",
    "sg:city":"Naples",
    "sg:classifiers":[
        {
            "category":"Building & Trades",
            "subcategory":"Construction",
            "type":"Services"
        }
    ],
    "sg:phone":"+1 239 514 4205",
    "sg:postcode":"34110",
    "sg:province":"FL",
    "sg:tags":[
        "maintenance",
        "contractor"
    ],
    "wof:name":"William H Moore Maintenance",
    "wof:placetype":"venue"
},
  "geometry": {"coordinates":[-81.81628000000001,26.276692],"type":"Point"}
}