{
  "type": "Feature",
  "properties": {
    "iso:country":"US",
    "sg:address":"7610 Industrial Ln",
    "sg:city":"Tampa",
    "sg:classifiers":[
        {
            "category":"Building & Trades",
            "subcategory":"Construction",
            "type":"Services"
        }
    ],
    "sg:phone":"+1 813 283 6595",
    "sg:postcode":"33637",
    "sg:province":"FL",
    "sg:tags":[
        "industrial",
        "altering",
        "consultant",
        "contractor",
        "planning",
        "contractors-commercial",
        "remodeling",
        "kitchen"
    ],
    "wof:name":"Sunset Construction Co Inc",
    "wof:placetype":"venue"
},
  "geometry": {"coordinates":[-82.359421,28.01713],"type":"Point"}
}