{
  "type": "Feature",
  "properties": {
    "addr:full":"2440 S Woodland Blvd Deland FL 32720",
    "addr:housenumber":"2440",
    "addr:postcode":"32720",
    "addr:street":"S Woodland Blvd",
    "iso:country":"US",
    "sg:address":"2440 S Woodland Blvd",
    "sg:city":"Deland",
    "sg:classifiers":[
        {
            "category":"Restaurant",
            "type":"Food & Drink"
        }
    ],
    "sg:phone":"+1 386 736 9993",
    "sg:postcode":"32720",
    "sg:province":"FL",
    "sg:tags":[
        "chinese"
    ],
    "wof:name":"China Dragon",
    "wof:placetype":"venue"
},
  "geometry": {"coordinates":[-81.299853,28.985458],"type":"Point"}
}