{
  "type": "Feature",
  "properties": {
    "iso:country":"US",
    "sg:address":"6396 Bridgeport Ln",
    "sg:city":"Lake Worth",
    "sg:classifiers":[
        {
            "category":"Health Services",
            "subcategory":"Health Practitioner",
            "type":"Services"
        }
    ],
    "sg:phone":"+1 561 967 9500",
    "sg:postcode":"33463",
    "sg:province":"FL",
    "wof:name":"Milestones Therapy Inc",
    "wof:placetype":"venue"
},
  "geometry": {"coordinates":[-80.14419700000001,26.581484],"type":"Point"}
}