{
  "type": "Feature",
  "properties": {
    "iso:country":"US",
    "sg:address":"315 Moody Blvd",
    "sg:city":"Flagler Beach",
    "sg:classifiers":[
        {
            "category":"Building & Trades",
            "subcategory":"Construction",
            "type":"Services"
        }
    ],
    "sg:phone":"+1 386 439 0533",
    "sg:postcode":"32136",
    "sg:province":"FL",
    "sg:tags":[
        "general",
        "contractor"
    ],
    "wof:name":"Wolfe General Contractors Inc",
    "wof:placetype":"venue"
},
  "geometry": {"coordinates":[-81.129464,29.480156],"type":"Point"}
}