{
  "type": "Feature",
  "properties": {
    "iso:country":"US",
    "sg:address":"36950 State Road 54",
    "sg:city":"Zephyrhills",
    "sg:classifiers":[
        {
            "category":"Insurance",
            "subcategory":"Hazard Insurance",
            "type":"Services"
        },
        {
            "category":"Insurance",
            "subcategory":"Insurance Agent",
            "type":"Services"
        },
        {
            "category":"Professional",
            "subcategory":"Lawyer & Legal Services",
            "type":"Services"
        },
        {
            "category":"Insurance",
            "subcategory":"Title Insurance",
            "type":"Services"
        }
    ],
    "sg:phone":"+1 813 780 8300",
    "sg:postcode":"33541",
    "sg:province":"FL",
    "sg:tags":[
        "attorney",
        "fire",
        "auto",
        "homeowner",
        "motorcycle",
        "renter"
    ],
    "sg:website":"http://www.gmacinsurance.com",
    "wof:name":"Gene Smith Insurance",
    "wof:placetype":"venue"
},
  "geometry": {"coordinates":[-82.206475,28.230006],"type":"Point"}
}