{
  "type": "Feature",
  "properties": {
    "iso:country":"US",
    "sg:address":"1122 Pennsylvania Ave",
    "sg:city":"St Cloud",
    "sg:classifiers":[
        {
            "category":"Professional",
            "subcategory":"Business Services",
            "type":"Services"
        }
    ],
    "sg:phone":"+1 407 891 3002",
    "sg:postcode":"34769",
    "sg:province":"FL",
    "sg:tags":[
        "embroidery"
    ],
    "wof:name":"Heith Yeager Embroidery",
    "wof:placetype":"venue"
},
  "geometry": {"coordinates":[-81.282523,28.247776],"type":"Point"}
}