{
  "type": "Feature",
  "properties": {
    "iso:country":"US",
    "sg:address":"7529 Garfield St",
    "sg:city":"Hollywood",
    "sg:classifiers":[
        {
            "category":"Professional",
            "type":"Services"
        }
    ],
    "sg:phone":"+1 954 967 3270",
    "sg:postcode":"33024",
    "sg:province":"FL",
    "wof:name":"A&M Docks Inc",
    "wof:placetype":"venue"
},
  "geometry": {"coordinates":[-80.23966900000001,26.019725],"type":"Point"}
}