{
  "type": "Feature",
  "properties": {
    "addr:full":"302 S Federal Hwy Pompano Beach FL 33062",
    "addr:housenumber":"302",
    "addr:postcode":"33062",
    "addr:street":"S Federal Hwy",
    "iso:country":"US",
    "sg:address":"302 S Federal Hwy",
    "sg:city":"Pompano Beach",
    "sg:classifiers":[
        {
            "category":"Retail",
            "subcategory":"Auto Repair",
            "type":"Services"
        }
    ],
    "sg:phone":"+1 954 946 3380",
    "sg:postcode":"33062",
    "sg:province":"FL",
    "sg:tags":[
        "general"
    ],
    "wof:name":"Auto Spot",
    "wof:placetype":"venue"
},
  "geometry": {"coordinates":[-80.102704,26.229204],"type":"Point"}
}