{
  "type": "Feature",
  "properties": {
    "iso:country":"US",
    "sg:address":"16388 75th Ave N",
    "sg:city":"Palm Beach Gardens",
    "sg:classifiers":[
        {
            "category":"Building & Trades",
            "subcategory":"Plumbing",
            "type":"Services"
        }
    ],
    "sg:phone":"+1 561 748 4553",
    "sg:postcode":"33418",
    "sg:province":"FL",
    "sg:tags":[
        "contractor"
    ],
    "wof:name":"Jeff Strobel AC LLC",
    "wof:placetype":"venue"
},
  "geometry": {"coordinates":[-80.15094000000001,26.917891],"type":"Point"}
}