{
  "type": "Feature",
  "properties": {
    "iso:country":"US",
    "sg:address":"4615 Sartillo St",
    "sg:city":"Saint Augustine",
    "sg:classifiers":[
        {
            "category":"Shopping",
            "subcategory":"Florist",
            "type":"Retail Goods"
        }
    ],
    "sg:phone":"+1 904 808 4671",
    "sg:postcode":"32095",
    "sg:province":"FL",
    "wof:name":"Dreaming of Petals & Lace",
    "wof:placetype":"venue"
},
  "geometry": {"coordinates":[-81.342445,29.941006],"type":"Point"}
}