{
  "type": "Feature",
  "properties": {
    "addr:full":"10449 Bernice Rd Milton FL 32583",
    "addr:housenumber":"10449",
    "addr:postcode":"32583",
    "addr:street":"Bernice Rd",
    "iso:country":"US",
    "sg:address":"10449 Bernice Rd",
    "sg:city":"Milton",
    "sg:classifiers":[
        {
            "category":"Professional",
            "type":"Services"
        }
    ],
    "sg:phone":"+1 850 626 7879",
    "sg:postcode":"32583",
    "sg:province":"FL",
    "wof:name":"Sharon Peacock Svc",
    "wof:placetype":"venue"
},
  "geometry": {"coordinates":[-86.88433499999999,30.627575],"type":"Point"}
}