{
  "type": "Feature",
  "properties": {
    "iso:country":"US",
    "sg:address":"4287 Frasier Ln",
    "sg:city":"Milton",
    "sg:classifiers":[
        {
            "category":"Insurance",
            "subcategory":"Hazard Insurance",
            "type":"Services"
        }
    ],
    "sg:phone":"+1 850 994 0634",
    "sg:postcode":"32571",
    "sg:province":"FL",
    "sg:tags":[
        "commercial",
        "business"
    ],
    "wof:name":"Burch Insurance Agency",
    "wof:placetype":"venue"
},
  "geometry": {"coordinates":[-87.141296,30.613236],"type":"Point"}
}