{
  "type": "Feature",
  "properties": {
    "addr:full":"1316 10th St W Palmetto FL 34221",
    "addr:housenumber":"1316",
    "addr:postcode":"34221",
    "addr:street":"10Th St W",
    "iso:country":"US",
    "sg:address":"1316 10th St W",
    "sg:city":"Palmetto",
    "sg:classifiers":[
        {
            "category":"Retail",
            "subcategory":"Auto Repair",
            "type":"Services"
        }
    ],
    "sg:phone":"+1 941 729 7066",
    "sg:postcode":"34221",
    "sg:province":"FL",
    "sg:tags":[
        "general"
    ],
    "wof:name":"Dole Automotive",
    "wof:placetype":"venue"
},
  "geometry": {"coordinates":[-82.579516,27.521279],"type":"Point"}
}