{
  "type": "Feature",
  "properties": {
    "addr:full":"10121 W Oakland Park Blvd Sunrise FL 33351",
    "addr:housenumber":"10121",
    "addr:postcode":"33351",
    "addr:street":"W Oakland Park Blvd",
    "iso:country":"US",
    "sg:address":"10121 W Oakland Park Blvd",
    "sg:city":"Sunrise",
    "sg:classifiers":[
        {
            "category":"Sports & Exercise",
            "subcategory":"Gym",
            "type":"Entertainment"
        }
    ],
    "sg:phone":"+1 954 746 4426",
    "sg:postcode":"33351",
    "sg:province":"FL",
    "sg:tags":[
        "club",
        "health",
        "studio",
        "gymnasium"
    ],
    "wof:name":"Curves For Women",
    "wof:placetype":"venue"
},
  "geometry": {"coordinates":[-80.292604,26.169926],"type":"Point"}
}