{
  "type": "Feature",
  "properties": {
    "iso:country":"US",
    "sg:address":"6712 Chevy Way",
    "sg:city":"Tallahassee",
    "sg:classifiers":[
        {
            "category":"Shopping",
            "subcategory":"Pharmacy",
            "type":"Retail Goods"
        }
    ],
    "sg:phone":"+1 850 656 9498",
    "sg:postcode":"32317",
    "sg:province":"FL",
    "wof:name":"Mcleskey, Kathy",
    "wof:placetype":"venue"
},
  "geometry": {"coordinates":[-84.16336099999999,30.45588],"type":"Point"}
}