{
  "type": "Feature",
  "properties": {
    "addr:full":"714 Vassar St Orlando FL 32804",
    "addr:housenumber":"714",
    "addr:postcode":"32804",
    "addr:street":"Vassar St",
    "iso:country":"US",
    "sg:address":"714 Vassar St",
    "sg:city":"Orlando",
    "sg:classifiers":[
        {
            "category":"Health Services",
            "subcategory":"Health Practitioner",
            "type":"Services"
        }
    ],
    "sg:phone":"+1 407 843 8014",
    "sg:postcode":"32804",
    "sg:province":"FL",
    "wof:name":"Vitality Anew",
    "wof:placetype":"venue"
},
  "geometry": {"coordinates":[-81.391316,28.572867],"type":"Point"}
}