{
  "type": "Feature",
  "properties": {
    "iso:country":"US",
    "sg:address":"10017 Vaughn St",
    "sg:city":"Gibsonton",
    "sg:classifiers":[
        {
            "category":"Government",
            "subcategory":"Office",
            "type":"Public Place"
        }
    ],
    "sg:phone":"+1 813 671 7601",
    "sg:postcode":"33534",
    "sg:province":"FL",
    "wof:name":"Hillsborough Cnty Sr Program",
    "wof:placetype":"venue"
},
  "geometry": {"coordinates":[-82.356521,27.851898],"type":"Point"}
}