{
  "type": "Feature",
  "properties": {
    "iso:country":"US",
    "sg:address":"401 Office Plz",
    "sg:city":"Tallahassee",
    "sg:classifiers":[
        {
            "category":"Professional",
            "subcategory":"Computer Services",
            "type":"Services"
        }
    ],
    "sg:phone":"+1 850 942 0388",
    "sg:postcode":"32301",
    "sg:province":"FL",
    "sg:tags":[
        "consultant",
        "designer",
        "internet"
    ],
    "sg:website":"www.vistech.net",
    "wof:name":"Vistech Communications",
    "wof:placetype":"venue"
},
  "geometry": {"coordinates":[-84.259654,30.447196],"type":"Point"}
}