{
  "type": "Feature",
  "properties": {
    "iso:country":"US",
    "sg:address":"9300 SW 40th St",
    "sg:city":"Miami",
    "sg:classifiers":[
        {
            "category":"Retail",
            "subcategory":"Funeral Services",
            "type":"Services"
        }
    ],
    "sg:phone":"+1 305 553 0064",
    "sg:postcode":"33165",
    "sg:province":"FL",
    "sg:tags":[
        "director",
        "casket",
        "plans-pre-arranged"
    ],
    "sg:website":"http://www.vanorsdelfuneralchapels.com",
    "wof:name":"Van Orsdel Mortuaries Inc",
    "wof:placetype":"venue"
},
  "geometry": {"coordinates":[-80.345703,25.73279],"type":"Point"}
}