{
  "type": "Feature",
  "properties": {
    "iso:country":"US",
    "sg:address":"3599 University Blvd S # 506",
    "sg:city":"Jacksonville",
    "sg:classifiers":[
        {
            "category":"Health Services",
            "subcategory":"Doctor",
            "type":"Services"
        },
        {
            "category":"Health Services",
            "subcategory":"Clinic",
            "type":"Services"
        }
    ],
    "sg:phone":"+1 904 396 8000",
    "sg:postcode":"32216",
    "sg:province":"FL",
    "sg:tags":[
        "physician",
        "medical",
        "surgeons",
        "surgery-general"
    ],
    "wof:name":"Yasrebi Hosein Md",
    "wof:placetype":"venue"
},
  "geometry": {"coordinates":[-81.602188,30.29007],"type":"Point"}
}