{
  "type": "Feature",
  "properties": {
    "iso:country":"US",
    "sg:address":"5135 W Fairfield Dr",
    "sg:city":"Pensacola",
    "sg:classifiers":[
        {
            "category":"Retail",
            "subcategory":"Auto Repair",
            "type":"Services"
        }
    ],
    "sg:phone":"+1 850 453 0830",
    "sg:postcode":"32506",
    "sg:province":"FL",
    "sg:tags":[
        "repairing",
        "automobile"
    ],
    "wof:name":"Knight's Automotive Svc",
    "wof:placetype":"venue"
},
  "geometry": {"coordinates":[-87.287302,30.43153],"type":"Point"}
}