{
  "type": "Feature",
  "properties": {
    "iso:country":"US",
    "sg:address":"5404 NW 72nd Ave",
    "sg:city":"Miami",
    "sg:classifiers":[
        {
            "category":"Shopping",
            "subcategory":"Clothing, Apparel, & Fashions",
            "type":"Retail Goods"
        }
    ],
    "sg:phone":"+1 305 888 6227",
    "sg:postcode":"33166",
    "sg:province":"FL",
    "sg:tags":[
        "furnishing"
    ],
    "wof:name":"Surreys Mens Ware",
    "wof:placetype":"venue"
},
  "geometry": {"coordinates":[-80.31372500000001,25.822974],"type":"Point"}
}