{
  "type": "Feature",
  "properties": {
    "addr:full":"4516 SE 16th Pl Cape Coral FL 33904",
    "addr:housenumber":"4516",
    "addr:postcode":"33904",
    "addr:street":"Se 16Th Pl",
    "iso:country":"US",
    "sg:address":"4516 SE 16th Pl",
    "sg:city":"Cape Coral",
    "sg:classifiers":[
        {
            "category":"Autos & Motor Vehicles",
            "subcategory":"Automobile Sales",
            "type":"Retail Goods"
        }
    ],
    "sg:phone":"+1 239 540 9402",
    "sg:postcode":"33904",
    "sg:province":"FL",
    "sg:tags":[
        "car",
        "dealer"
    ],
    "wof:name":"Jose's Auto",
    "wof:placetype":"venue"
},
  "geometry": {"coordinates":[-81.942623,26.569458],"type":"Point"}
}