{
  "type": "Feature",
  "properties": {
    "addr:full":"3175 Clewiston St Deltona FL 32738",
    "addr:postcode":"3175;32738",
    "addr:street":"Clewiston St",
    "iso:country":"US",
    "sg:address":"3175 Clewiston St",
    "sg:city":"Deltona",
    "sg:classifiers":[
        {
            "category":"Home & Garden",
            "subcategory":"Building Materials",
            "type":"Retail Goods"
        },
        {
            "category":"Building & Trades",
            "subcategory":"Construction",
            "type":"Services"
        }
    ],
    "sg:phone":"+1 407 322 0114",
    "sg:postcode":"32738",
    "sg:province":"FL",
    "sg:tags":[
        "concrete",
        "staining",
        "contractor"
    ],
    "wof:name":"Sand Leonard Masonry & Concrete",
    "wof:placetype":"venue"
},
  "geometry": {"coordinates":[-81.175258,28.897202],"type":"Point"}
}