{
  "type": "Feature",
  "properties": {
    "addr:full":"5144 Commercial Way Spring Hill FL 34606",
    "addr:housenumber":"5144",
    "addr:postcode":"34606",
    "addr:street":"Commercial Way",
    "iso:country":"US",
    "sg:address":"5144 Commercial Way",
    "sg:city":"Spring Hill",
    "sg:classifiers":[
        {
            "category":"Wholesale",
            "subcategory":"Toys & Hobbies",
            "type":"Manufacturing & Wholesale Goods"
        },
        {
            "category":"Shopping",
            "subcategory":"Hobbies, Toys, & Games",
            "type":"Retail Goods"
        }
    ],
    "sg:phone":"+1 352 596 8582",
    "sg:postcode":"34606",
    "sg:province":"FL",
    "sg:tags":[
        "supply",
        "ceramics"
    ],
    "wof:name":"Paper Playhouse Inc",
    "wof:placetype":"venue"
},
  "geometry": {"coordinates":[-82.585249,28.505787],"type":"Point"}
}