{
  "type": "Feature",
  "properties": {
    "iso:country":"US",
    "sg:address":"139 Shore Ct",
    "sg:city":"North Palm Beach",
    "sg:classifiers":[
        {
            "category":"Autos & Motor Vehicles",
            "subcategory":"Boat Sales",
            "type":"Retail Goods"
        }
    ],
    "sg:phone":"+1 561 848 0902",
    "sg:postcode":"33408",
    "sg:province":"FL",
    "wof:name":"Marine Max Bassett",
    "wof:placetype":"venue"
},
  "geometry": {"coordinates":[-80.055728,26.807461],"type":"Point"}
}