{
  "type": "Feature",
  "properties": {
    "iso:country":"US",
    "sg:address":"453 Huntington Ave",
    "sg:city":"Winter Park",
    "sg:classifiers":[
        {
            "category":"Building & Trades",
            "subcategory":"Construction",
            "type":"Services"
        }
    ],
    "sg:phone":"+1 407 740 6622",
    "sg:postcode":"32789",
    "sg:province":"FL",
    "sg:tags":[
        "hanging",
        "contractor"
    ],
    "wof:name":"Norvell Painting & Cleaning",
    "wof:placetype":"venue"
},
  "geometry": {"coordinates":[-81.35405299999999,28.590297],"type":"Point"}
}