{
  "type": "Feature",
  "properties": {
    "addr:full":"18744 Ocean Mist Dr Boca Raton FL 33498",
    "addr:housenumber":"18744",
    "addr:postcode":"33498",
    "addr:street":"Ocean Mist Dr",
    "iso:country":"US",
    "sg:address":"18744 Ocean Mist Dr",
    "sg:city":"Boca Raton",
    "sg:classifiers":[
        {
            "category":"Wholesale",
            "subcategory":"Office Equipment",
            "type":"Manufacturing & Wholesale Goods"
        },
        {
            "category":"Wholesale",
            "subcategory":"Durable Goods & Equipment",
            "type":"Manufacturing & Wholesale Goods"
        }
    ],
    "sg:phone":"+1 561 852 1200",
    "sg:postcode":"33498",
    "sg:province":"FL",
    "sg:tags":[
        "mach",
        "automatic",
        "teller",
        "bank",
        "supply"
    ],
    "wof:name":"Gold Coast Data Corporation",
    "wof:placetype":"venue"
},
  "geometry": {"coordinates":[-80.22363799999999,26.396775],"type":"Point"}
}