{
  "type": "Feature",
  "properties": {
    "addr:full":"3654 Bayview Rd Miami FL 33133",
    "addr:housenumber":"3654",
    "addr:postcode":"33133",
    "addr:street":"Bayview Rd",
    "iso:country":"US",
    "sg:address":"3654 Bayview Rd",
    "sg:city":"Miami",
    "sg:classifiers":[
        {
            "category":"Professional",
            "subcategory":"Lawyer & Legal Services",
            "type":"Services"
        }
    ],
    "sg:phone":"+1 305 442 0903",
    "sg:postcode":"33133",
    "sg:province":"FL",
    "wof:name":"Rosemond Elaine Doyle Atty",
    "wof:placetype":"venue"
},
  "geometry": {"coordinates":[-80.252098,25.717699],"type":"Point"}
}