{
  "type": "Feature",
  "properties": {
    "iso:country":"US",
    "sg:address":"10991 San Jose Blvd",
    "sg:city":"Jacksonville",
    "sg:classifiers":[
        {
            "category":"Home & Garden",
            "subcategory":"Home Furnishings",
            "type":"Retail Goods"
        }
    ],
    "sg:phone":"+1 904 880 8008",
    "sg:postcode":"32223",
    "sg:province":"FL",
    "sg:tags":[
        "equipment",
        "fireplace",
        "accessory"
    ],
    "wof:name":"Barbeques Galore",
    "wof:placetype":"venue"
},
  "geometry": {"coordinates":[-81.627765,30.175836],"type":"Point"}
}