{
  "type": "Feature",
  "properties": {
    "iso:country":"US",
    "sg:address":"2134 Mears Pkwy",
    "sg:city":"Pompano Beach",
    "sg:classifiers":[
        {
            "category":"Restaurant",
            "type":"Food & Drink"
        }
    ],
    "sg:phone":"+1 954 972 0700",
    "sg:postcode":"33063",
    "sg:province":"FL",
    "sg:tags":[
        "eating"
    ],
    "wof:name":"Sub Contractor",
    "wof:placetype":"venue"
},
  "geometry": {"coordinates":[-80.198306,26.251376],"type":"Point"}
}