{
  "type": "Feature",
  "properties": {
    "addr:full":"1628 Greenwood Dr Dunedin FL 34698",
    "addr:housenumber":"1628",
    "addr:postcode":"34698",
    "addr:street":"Greenwood Dr",
    "iso:country":"US",
    "sg:address":"1628 Greenwood Dr",
    "sg:city":"Dunedin",
    "sg:classifiers":[
        {
            "category":"Professional",
            "type":"Services"
        }
    ],
    "sg:phone":"+1 727 733 0233",
    "sg:postcode":"34698",
    "sg:province":"FL",
    "wof:name":"James Gero Music Inc",
    "wof:placetype":"venue"
},
  "geometry": {"coordinates":[-82.761428,28.026351],"type":"Point"}
}