{
  "type": "Feature",
  "properties": {
    "addr:full":"5704 Guava Drive Tamarac FL 33319",
    "addr:housenumber":"5704",
    "addr:postcode":"33319",
    "addr:street":"Guava Drive",
    "iso:country":"US",
    "sg:address":"5704 Guava Drive",
    "sg:city":"Tamarac",
    "sg:classifiers":[
        {
            "category":"Health Services",
            "subcategory":"Health Practitioner",
            "type":"Services"
        }
    ],
    "sg:phone":"+1 954 830 5422",
    "sg:postcode":"33319",
    "sg:province":"FL",
    "sg:tags":[
        "psychotherapist"
    ],
    "sg:website":"http://www.turtlemoontherapy.com",
    "wof:name":"Steven J Grossman, LCSW, CAP",
    "wof:placetype":"venue"
},
  "geometry": {"coordinates":[-80.227287,26.193599],"type":"Point"}
}