{
  "type": "Feature",
  "properties": {
    "iso:country":"US",
    "sg:address":"414 N Spring Garden Ave",
    "sg:city":"Deland",
    "sg:classifiers":[
        {
            "category":"Arts & Performance",
            "subcategory":"Arts Center",
            "type":"Entertainment"
        },
        {
            "category":"Arts & Performance",
            "subcategory":"Dance",
            "type":"Entertainment"
        }
    ],
    "sg:phone":"+1 386 734 5517",
    "sg:postcode":"32720",
    "sg:province":"FL",
    "sg:tags":[
        "performing",
        "instruction",
        "dancing"
    ],
    "wof:name":"The Little Studio",
    "wof:placetype":"venue"
},
  "geometry": {"coordinates":[-81.324567,29.033562],"type":"Point"}
}