{
  "type": "Feature",
  "properties": {
    "iso:country":"US",
    "sg:address":"450 SE Monterey Rd",
    "sg:city":"Stuart",
    "sg:classifiers":[
        {
            "category":"Retail",
            "subcategory":"Auto Repair",
            "type":"Services"
        }
    ],
    "sg:phone":"+1 772 287 8480",
    "sg:postcode":"34994",
    "sg:province":"FL",
    "sg:tags":[
        "automotive",
        "sup"
    ],
    "wof:name":"Buddys Radiator & AC Svc",
    "wof:placetype":"venue"
},
  "geometry": {"coordinates":[-80.24691300000001,27.17557],"type":"Point"}
}