{
  "type": "Feature",
  "properties": {
    "iso:country":"US",
    "sg:address":"3309 Lacewood Rd",
    "sg:city":"Tampa",
    "sg:classifiers":[
        {
            "category":"Freight",
            "type":"Transportation"
        }
    ],
    "sg:phone":"+1 813 935 8807",
    "sg:postcode":"33618",
    "sg:province":"FL",
    "sg:tags":[
        "warehouse"
    ],
    "wof:name":"Alex Cole Interiors Ltd Inc",
    "wof:placetype":"venue"
},
  "geometry": {"coordinates":[-82.496852,28.052748],"type":"Point"}
}