{
  "type": "Feature",
  "properties": {
    "addr:full":"1508 S Nova Rd Daytona Beach FL 32114",
    "addr:housenumber":"1508",
    "addr:postcode":"32114",
    "addr:street":"S Nova Rd",
    "iso:country":"US",
    "sg:address":"1508 S Nova Rd",
    "sg:city":"Daytona Beach",
    "sg:classifiers":[
        {
            "category":"Shopping",
            "type":"Retail Goods"
        }
    ],
    "sg:phone":"+1 386 255 3474",
    "sg:postcode":"32114",
    "sg:province":"FL",
    "sg:tags":[
        "merchandise"
    ],
    "wof:name":"Poseidon Aquarium",
    "wof:placetype":"venue"
},
  "geometry": {"coordinates":[-81.02869200000001,29.175495],"type":"Point"}
}