{
  "type": "Feature",
  "properties": {
    "iso:country":"US",
    "sg:address":"4757 Grandoaks Cir",
    "sg:city":"Marianna",
    "sg:classifiers":[
        {
            "category":"Real Estate",
            "subcategory":"Real Estate Operator",
            "type":"Services"
        }
    ],
    "sg:phone":"+1 850 482 8618",
    "sg:postcode":"32446",
    "sg:province":"FL",
    "sg:tags":[
        "mobile",
        "home",
        "site"
    ],
    "wof:name":"Quiet Haven Trailer Park",
    "wof:placetype":"venue"
},
  "geometry": {"coordinates":[-85.19916000000001,30.766569],"type":"Point"}
}