{
  "type": "Feature",
  "properties": {
    "iso:country":"US",
    "sg:address":"2800 SW 105th Ave",
    "sg:city":"Miami",
    "sg:classifiers":[
        {
            "category":"Professional",
            "subcategory":"Business Services",
            "type":"Services"
        }
    ],
    "sg:phone":"+1 305 592 6060",
    "sg:postcode":"33165",
    "sg:province":"FL",
    "sg:tags":[
        "shipping"
    ],
    "sg:website":"http://www.seafreightagencies.com",
    "wof:name":"Seafreight Agencies Inc",
    "wof:placetype":"venue"
},
  "geometry": {"coordinates":[-80.365196,25.74324],"type":"Point"}
}