{
  "type": "Feature",
  "properties": {
    "iso:country":"US",
    "sg:address":"1307 SE 16th St",
    "sg:city":"Cape Coral",
    "sg:classifiers":[
        {
            "category":"Freight",
            "type":"Transportation"
        }
    ],
    "sg:phone":"+1 239 573 1348",
    "sg:postcode":"33990",
    "sg:province":"FL",
    "sg:tags":[
        "operator",
        "local",
        "trucking"
    ],
    "wof:name":"J Fernandez Trucking",
    "wof:placetype":"venue"
},
  "geometry": {"coordinates":[-81.942663,26.623081],"type":"Point"}
}