{
  "type": "Feature",
  "properties": {
    "iso:country":"US",
    "sg:address":"520 W Lake Mary Blvd",
    "sg:city":"Sanford",
    "sg:classifiers":[
        {
            "category":"Real Estate",
            "subcategory":"Real Estate Operator",
            "type":"Services"
        }
    ],
    "sg:phone":"+1 407 330 2244",
    "sg:postcode":"32773",
    "sg:province":"FL",
    "sg:tags":[
        "building",
        "parks"
    ],
    "wof:name":"Reflections At Hidden Lake",
    "wof:placetype":"venue"
},
  "geometry": {"coordinates":[-81.293774,28.757588],"type":"Point"}
}