{
  "type": "Feature",
  "properties": {
    "iso:country":"US",
    "sg:address":"2463 N State Rd 7",
    "sg:city":"Lauderdale Lakes",
    "sg:classifiers":[
        {
            "category":"Shopping",
            "subcategory":"Clothing, Apparel, & Fashions",
            "type":"Retail Goods"
        }
    ],
    "sg:phone":"+1 954 733 2900",
    "sg:postcode":"33313",
    "sg:province":"FL",
    "sg:tags":[
        "tailor"
    ],
    "wof:name":"Custom Tailor",
    "wof:placetype":"venue"
},
  "geometry": {"coordinates":[-80.20311700000001,26.15783],"type":"Point"}
}