{
  "type": "Feature",
  "properties": {
    "addr:full":"24842 Wild Frontier Dr Land O Lakes FL 34639",
    "addr:housenumber":"24842",
    "addr:postcode":"34639",
    "addr:street":"Wild Frontier Dr",
    "iso:country":"US",
    "sg:address":"24842 Wild Frontier Dr",
    "sg:city":"Land O Lakes",
    "sg:classifiers":[
        {
            "category":"Professional",
            "type":"Services"
        }
    ],
    "sg:phone":"+1 813 907 9359",
    "sg:postcode":"34639",
    "sg:province":"FL",
    "sg:tags":[
        "establishment"
    ],
    "wof:name":"Twin Oaks Forensic Out Patient",
    "wof:placetype":"venue"
},
  "geometry": {"coordinates":[-82.405034,28.209007],"type":"Point"}
}