{
  "type": "Feature",
  "properties": {
    "addr:full":"590 NW 159th St Miami FL 33169",
    "addr:housenumber":"590",
    "addr:postcode":"33169",
    "addr:street":"Nw 159Th St",
    "iso:country":"US",
    "sg:address":"590 NW 159th St",
    "sg:city":"Miami",
    "sg:classifiers":[
        {
            "category":"Place Of Worship",
            "subcategory":"Church",
            "type":"Public Place"
        },
        {
            "category":"Place Of Worship",
            "type":"Public Place"
        },
        {
            "category":"Organizations",
            "subcategory":"Religious Organization",
            "type":"Services"
        }
    ],
    "sg:phone":"+1 305 945 4770",
    "sg:postcode":"33169",
    "sg:province":"FL",
    "sg:tags":[
        "god",
        "god-independent",
        "churches-assemblies"
    ],
    "sg:website":"http://www.lifeimpact.com",
    "wof:name":"Evangel Church International",
    "wof:placetype":"venue"
},
  "geometry": {"coordinates":[-80.209503,25.9205],"type":"Point"}
}