{
  "type": "Feature",
  "properties": {
    "iso:country":"US",
    "sg:address":"6206 Benjamin Rd Ste 310",
    "sg:city":"Tampa",
    "sg:classifiers":[
        {
            "category":"Building & Trades",
            "subcategory":"Equipment Rental",
            "type":"Services"
        }
    ],
    "sg:phone":"+1 813 884 7168",
    "sg:postcode":"33634",
    "sg:province":"FL",
    "sg:tags":[
        "leasing",
        "equipment-renting",
        "audio-visual"
    ],
    "sg:website":"http://www.avispl.com",
    "wof:name":"Avi-Spl",
    "wof:placetype":"venue"
},
  "geometry": {"coordinates":[-82.542,28.004604],"type":"Point"}
}