{
  "type": "Feature",
  "properties": {
    "iso:country":"US",
    "sg:address":"7134 N Nob Hill Rd",
    "sg:city":"Tamarac",
    "sg:classifiers":[
        {
            "category":"Deli",
            "type":"Food & Drink"
        },
        {
            "category":"Restaurant",
            "type":"Food & Drink"
        }
    ],
    "sg:phone":"+1 954 642 5225",
    "sg:postcode":"33321",
    "sg:province":"FL",
    "sg:tags":[
        "delicatessen"
    ],
    "wof:name":"Nosher?s Deli",
    "wof:placetype":"venue"
},
  "geometry": {"coordinates":[-80.284978,26.210629],"type":"Point"}
}