{
  "type": "Feature",
  "properties": {
    "addr:full":"1761 W Hillsboro Blvd Deerfield Beach FL 33442",
    "addr:housenumber":"1761",
    "addr:postcode":"33442",
    "addr:street":"W Hillsboro Blvd",
    "iso:country":"US",
    "sg:address":"1761 W Hillsboro Blvd",
    "sg:city":"Deerfield Beach",
    "sg:classifiers":[
        {
            "category":"Professional",
            "subcategory":"Lawyer & Legal Services",
            "type":"Services"
        }
    ],
    "sg:phone":"+1 954 425 7700",
    "sg:postcode":"33442",
    "sg:province":"FL",
    "sg:tags":[
        "attorney"
    ],
    "wof:name":"Routman & Mellinger",
    "wof:placetype":"venue"
},
  "geometry": {"coordinates":[-80.12757999999999,26.318115],"type":"Point"}
}