{
  "type": "Feature",
  "properties": {
    "iso:country":"US",
    "sg:address":"210 Johns Pl",
    "sg:city":"Palatka",
    "sg:classifiers":[
        {
            "category":"Organizations",
            "subcategory":"Membership Organization",
            "type":"Services"
        }
    ],
    "sg:phone":"+1 386 325 4406",
    "sg:postcode":"32177",
    "sg:province":"FL",
    "wof:name":"Blue Crab Festival",
    "wof:placetype":"venue"
},
  "geometry": {"coordinates":[-81.728959,29.793083],"type":"Point"}
}