{
  "type": "Feature",
  "properties": {
    "iso:country":"US",
    "sg:address":"6427 Milner Blvd Ste 3",
    "sg:city":"Orlando",
    "sg:classifiers":[
        {
            "category":"Wholesale",
            "subcategory":"Photographic Equipment",
            "type":"Manufacturing & Wholesale Goods"
        }
    ],
    "sg:phone":"+1 407 442 0340",
    "sg:postcode":"32809",
    "sg:province":"FL",
    "sg:tags":[
        "equipment-renting"
    ],
    "wof:name":"Evolve Media Group",
    "wof:placetype":"venue"
},
  "geometry": {"coordinates":[-81.368961,28.464573],"type":"Point"}
}