{
  "type": "Feature",
  "properties": {
    "addr:full":"1111 Lincoln Rd Ste 400 Miami Beach FL 33139",
    "addr:housenumber":"1111",
    "addr:postcode":"33139",
    "addr:street":"Lincoln Rd Ste 400",
    "iso:country":"US",
    "sg:address":"1111 Lincoln Rd Ste 400",
    "sg:city":"Miami Beach",
    "sg:classifiers":[
        {
            "category":"Professional",
            "subcategory":"Lawyer & Legal Services",
            "type":"Services"
        }
    ],
    "sg:phone":"+1 786 276 2444",
    "sg:postcode":"33139",
    "sg:province":"FL",
    "wof:name":"Mandler Bernard",
    "wof:placetype":"venue"
},
  "geometry": {"coordinates":[-80.140111,25.790487],"type":"Point"}
}