{
  "type": "Feature",
  "properties": {
    "addr:full":"1127 NE 14th Ave Fort Lauderdale FL 33304",
    "addr:housenumber":"1127",
    "addr:postcode":"33304",
    "addr:street":"Ne 14Th Ave",
    "iso:country":"US",
    "sg:address":"1127 NE 14th Ave",
    "sg:city":"Fort Lauderdale",
    "sg:classifiers":[
        {
            "category":"Building & Trades",
            "subcategory":"Cleaning & Sanitation",
            "type":"Services"
        }
    ],
    "sg:phone":"+1 954 522 2241",
    "sg:postcode":"33304",
    "sg:province":"FL",
    "sg:tags":[
        "janitor"
    ],
    "wof:name":"All County Maintenance Svc Inc",
    "wof:placetype":"venue"
},
  "geometry": {"coordinates":[-80.129835,26.14032],"type":"Point"}
}