{
  "type": "Feature",
  "properties": {
    "iso:country":"US",
    "sg:address":"1740 E Rd",
    "sg:city":"Loxahatchee",
    "sg:classifiers":[
        {
            "category":"Farming",
            "subcategory":"Nursery",
            "type":"Manufacturing & Wholesale Goods"
        }
    ],
    "sg:phone":"+1 561 792 3027",
    "sg:postcode":"33470",
    "sg:province":"FL",
    "sg:tags":[
        "ornamental"
    ],
    "wof:name":"AG Land Grassing Crop",
    "wof:placetype":"venue"
},
  "geometry": {"coordinates":[-80.265731,26.703505],"type":"Point"}
}