{
  "type": "Feature",
  "properties": {
    "addr:full":"413 SW 3rd St Hallandale Beach FL 33009",
    "addr:housenumber":"413",
    "addr:postcode":"33009",
    "addr:street":"Sw 3Rd St",
    "iso:country":"US",
    "sg:address":"413 SW 3rd St",
    "sg:city":"Hallandale Beach",
    "sg:classifiers":[
        {
            "category":"Health Services",
            "subcategory":"Health Practitioner",
            "type":"Services"
        }
    ],
    "sg:phone":"+1 954 455 9166",
    "sg:postcode":"33009",
    "sg:province":"FL",
    "sg:tags":[
        "paramedic"
    ],
    "wof:name":"A Better Paramedic",
    "wof:placetype":"venue"
},
  "geometry": {"coordinates":[-80.153052,25.981687],"type":"Point"}
}