{
  "type": "Feature",
  "properties": {
    "iso:country":"US",
    "sg:address":"265 S Federal Hwy",
    "sg:city":"Delray Beach",
    "sg:classifiers":[
        {
            "category":"Retail",
            "subcategory":"Repair Shop",
            "type":"Services"
        }
    ],
    "sg:phone":"+1 561 272 2044",
    "sg:postcode":"33483",
    "sg:province":"FL",
    "sg:tags":[
        "lock",
        "locksmith"
    ],
    "wof:name":"1O1A Emergency 24 Hour",
    "wof:placetype":"venue"
},
  "geometry": {"coordinates":[-80.066868,26.457412],"type":"Point"}
}