{
  "type": "Feature",
  "properties": {
    "addr:full":"220 NE 12th Ave Homestead FL 33030",
    "addr:housenumber":"220",
    "addr:postcode":"33030",
    "addr:street":"Ne 12Th Ave",
    "iso:country":"US",
    "sg:address":"220 NE 12th Ave",
    "sg:city":"Homestead",
    "sg:classifiers":[
        {
            "category":"Wholesale",
            "subcategory":"Durable Goods & Equipment",
            "type":"Manufacturing & Wholesale Goods"
        }
    ],
    "sg:phone":"+1 305 242 8069",
    "sg:postcode":"33030",
    "sg:province":"FL",
    "sg:tags":[
        "exporter"
    ],
    "wof:name":"Paramount Painting & Rstrtn",
    "wof:placetype":"venue"
},
  "geometry": {"coordinates":[-80.460898,25.471673],"type":"Point"}
}