{
  "type": "Feature",
  "properties": {
    "iso:country":"US",
    "sg:address":"2298 Lockwood Meadow Dr",
    "sg:city":"Sarasota",
    "sg:classifiers":[
        {
            "category":"Building & Trades",
            "subcategory":"Cleaning & Sanitation",
            "type":"Services"
        }
    ],
    "sg:phone":"+1 941 955 3705",
    "sg:postcode":"34234",
    "sg:province":"FL",
    "sg:tags":[
        "maintenance"
    ],
    "wof:name":"New Generation Cleaning Svcs",
    "wof:placetype":"venue"
},
  "geometry": {"coordinates":[-82.511909,27.357058],"type":"Point"}
}