{
  "type": "Feature",
  "properties": {
    "iso:country":"US",
    "sg:address":"3239 SW 139th Pl",
    "sg:city":"Miami",
    "sg:classifiers":[
        {
            "category":"Wholesale",
            "subcategory":"Apparel",
            "type":"Manufacturing & Wholesale Goods"
        }
    ],
    "sg:phone":"+1 305 551 4634",
    "sg:postcode":"33175",
    "sg:province":"FL",
    "sg:tags":[
        "shoes"
    ],
    "wof:name":"D'Rafael Imported Shoes",
    "wof:placetype":"venue"
},
  "geometry": {"coordinates":[-80.421459,25.736435],"type":"Point"}
}