{
  "type": "Feature",
  "properties": {
    "addr:full":"2784 Sadler Rd Fernandina Beach FL 32034",
    "addr:housenumber":"2784",
    "addr:postcode":"32034",
    "addr:street":"Sadler Rd",
    "iso:country":"US",
    "sg:address":"2784 Sadler Rd",
    "sg:city":"Fernandina Beach",
    "sg:classifiers":[
        {
            "category":"Restaurant",
            "type":"Food & Drink"
        },
        {
            "category":"Ice Cream",
            "type":"Food & Drink"
        }
    ],
    "sg:menulink":"http://www.allmenus.com/fl/fernandina-beach/172388-dairy-queen/menu/",
    "sg:phone":"+1 904 277 2113",
    "sg:postcode":"32034",
    "sg:province":"FL",
    "sg:tags":[
        "burger",
        "american",
        "ice",
        "cream"
    ],
    "wof:name":"Dairy Queen",
    "wof:placetype":"venue"
},
  "geometry": {"coordinates":[-81.438496,30.638829],"type":"Point"}
}