{
  "type": "Feature",
  "properties": {
    "iso:country":"US",
    "sg:address":"22nd St at Collins Ave",
    "sg:city":"Miami Beach",
    "sg:classifiers":[
        {
            "category":"Food & Beverages",
            "subcategory":"Farmers Market",
            "type":"Retail Goods"
        }
    ],
    "sg:phone":"+1 305 576 9790",
    "sg:postcode":"33139",
    "sg:province":"FL",
    "wof:name":"Collins Park Sunday Market",
    "wof:placetype":"venue"
},
  "geometry": {"coordinates":[-80.128319,25.797531],"type":"Point"}
}