{
  "type": "Feature",
  "properties": {
    "addr:full":"13202 W Colonial Dr Winter Garden FL 34787",
    "addr:housenumber":"13202",
    "addr:postcode":"34787",
    "addr:street":"W Colonial Dr",
    "iso:country":"US",
    "sg:address":"13202 W Colonial Dr",
    "sg:city":"Winter Garden",
    "sg:classifiers":[
        {
            "category":"Autos & Motor Vehicles",
            "subcategory":"Auto Supplies",
            "type":"Retail Goods"
        }
    ],
    "sg:phone":"+1 407 656 4141",
    "sg:postcode":"34787",
    "sg:province":"FL",
    "sg:tags":[
        "automobile",
        "parts"
    ],
    "wof:name":"Glenn Joiner & Son Automotive",
    "wof:placetype":"venue"
},
  "geometry": {"coordinates":[-81.578744,28.551009],"type":"Point"}
}