{
  "type": "Feature",
  "properties": {
    "addr:full":"5190 SE Seascape Way Stuart FL 34997",
    "addr:housenumber":"5190",
    "addr:postcode":"34997",
    "addr:street":"Se Seascape Way",
    "iso:country":"US",
    "sg:address":"5190 SE Seascape Way",
    "sg:city":"Stuart",
    "sg:classifiers":[
        {
            "category":"Restaurant",
            "type":"Food & Drink"
        }
    ],
    "sg:phone":"+1 561 743 7619",
    "sg:postcode":"34997",
    "sg:province":"FL",
    "sg:tags":[
        "eating"
    ],
    "wof:name":"Corner Cafe",
    "wof:placetype":"venue"
},
  "geometry": {"coordinates":[-80.18380500000001,27.160449],"type":"Point"}
}