{
  "type": "Feature",
  "properties": {
    "addr:full":"143 S Atlantic Ave Daytona Beach FL 32118",
    "addr:housenumber":"143",
    "addr:postcode":"32118",
    "addr:street":"S Atlantic Ave",
    "iso:country":"US",
    "sg:address":"143 S Atlantic Ave",
    "sg:city":"Daytona Beach",
    "sg:classifiers":[
        {
            "category":"Restaurant",
            "type":"Food & Drink"
        }
    ],
    "sg:phone":"+1 386 255 6465",
    "sg:postcode":"32118",
    "sg:province":"FL",
    "wof:name":"Noura's Pizza House",
    "wof:placetype":"venue"
},
  "geometry": {"coordinates":[-81.00617200000001,29.222901],"type":"Point"}
}