{
  "type": "Feature",
  "properties": {
    "iso:country":"US",
    "sg:address":"1230 Lake Lotela Dr",
    "sg:city":"Avon Park",
    "sg:phone":"+1 863 453 4606",
    "sg:postcode":"33825",
    "sg:province":"FL",
    "sg:tags":[
        "irrigation",
        "system"
    ],
    "wof:name":"Ldh Grove Service",
    "wof:placetype":"venue"
},
  "geometry": {"coordinates":[-81.47818700000001,27.56727],"type":"Point"}
}