{
  "type": "Feature",
  "properties": {
    "iso:country":"US",
    "sg:address":"1321 NW 14th Ave",
    "sg:city":"Miami",
    "sg:classifiers":[
        {
            "category":"Health Services",
            "subcategory":"Doctor",
            "type":"Services"
        }
    ],
    "sg:phone":"+1 305 548 4005",
    "sg:postcode":"33125",
    "sg:province":"FL",
    "sg:tags":[
        "physician",
        "surgeon"
    ],
    "wof:name":"Cedars Medical Ctr",
    "wof:placetype":"venue"
},
  "geometry": {"coordinates":[-80.21879800000001,25.786289],"type":"Point"}
}