{
  "type": "Feature",
  "properties": {
    "addr:full":"10611 Tamiami Trl N Naples FL 34108",
    "addr:housenumber":"10611",
    "addr:postcode":"34108",
    "addr:street":"Tamiami Trl N",
    "iso:country":"US",
    "sg:address":"10611 Tamiami Trl N",
    "sg:city":"Naples",
    "sg:classifiers":[
        {
            "category":"Travel",
            "subcategory":"Travel Agent",
            "type":"Entertainment"
        }
    ],
    "sg:phone":"+1 239 593 8291",
    "sg:postcode":"34108",
    "sg:province":"FL",
    "sg:tags":[
        "agency",
        "bureau"
    ],
    "wof:name":"Sambra Travel",
    "wof:placetype":"venue"
},
  "geometry": {"coordinates":[-81.80163400000001,26.26867],"type":"Point"}
}