{
  "type": "Feature",
  "properties": {
    "iso:country":"US",
    "sg:address":"23494 Westchester Blvd",
    "sg:city":"Port Charlotte",
    "sg:classifiers":[
        {
            "category":"Real Estate",
            "subcategory":"Real Estate Agent",
            "type":"Services"
        }
    ],
    "sg:phone":"+1 941 625 3115",
    "sg:postcode":"33980",
    "sg:province":"FL",
    "wof:name":"Hometown Touch Real Estate Co",
    "wof:placetype":"venue"
},
  "geometry": {"coordinates":[-82.06146200000001,26.973088],"type":"Point"}
}