{
  "type": "Feature",
  "properties": {
    "iso:country":"US",
    "sg:address":"3409 Devonshire Dr",
    "sg:city":"Holiday",
    "sg:classifiers":[
        {
            "category":"Building & Trades",
            "subcategory":"Construction",
            "type":"Services"
        }
    ],
    "sg:phone":"+1 727 842 9041",
    "sg:postcode":"34691",
    "sg:province":"FL",
    "sg:tags":[
        "contractor"
    ],
    "wof:name":"Warren Willie",
    "wof:placetype":"venue"
},
  "geometry": {"coordinates":[-82.75314,28.207211],"type":"Point"}
}