{
  "type": "Feature",
  "properties": {
    "addr:full":"316 Stadium Dr Tallahassee FL 32304",
    "addr:housenumber":"316",
    "addr:postcode":"32304",
    "addr:street":"Stadium Dr",
    "iso:country":"US",
    "sg:address":"316 Stadium Dr",
    "sg:city":"Tallahassee",
    "sg:classifiers":[
        {
            "category":"Professional",
            "subcategory":"Research",
            "type":"Services"
        }
    ],
    "sg:phone":"+1 850 222 1834",
    "sg:postcode":"32304",
    "sg:province":"FL",
    "sg:tags":[
        "foundation",
        "philanthropic"
    ],
    "wof:name":"Lastinger Scholarship House",
    "wof:placetype":"venue"
},
  "geometry": {"coordinates":[-84.306561,30.443881],"type":"Point"}
}