{
  "type": "Feature",
  "properties": {
    "iso:country":"US",
    "sg:address":"3042 Jog Rd",
    "sg:city":"Lake Worth",
    "sg:classifiers":[
        {
            "category":"Insurance",
            "subcategory":"Insurance Agent",
            "type":"Services"
        }
    ],
    "sg:phone":"+1 561 968 3400",
    "sg:postcode":"33467",
    "sg:province":"FL",
    "wof:name":"Allstate",
    "wof:placetype":"venue"
},
  "geometry": {"coordinates":[-80.146046,26.631232],"type":"Point"}
}