{
  "type": "Feature",
  "properties": {
    "addr:full":"1445 S Missouri Ave Clearwater FL 33756",
    "addr:housenumber":"1445",
    "addr:postcode":"33756",
    "addr:street":"S Missouri Ave",
    "iso:country":"US",
    "sg:address":"1445 S Missouri Ave",
    "sg:city":"Clearwater",
    "sg:classifiers":[
        {
            "category":"Retail",
            "subcategory":"Auto Rental",
            "type":"Services"
        }
    ],
    "sg:phone":"+1 727 447 8590",
    "sg:postcode":"33756",
    "sg:province":"FL",
    "sg:tags":[
        "renting",
        "truck",
        "leasing"
    ],
    "wof:name":"U-Haul Co",
    "wof:placetype":"venue"
},
  "geometry": {"coordinates":[-82.787404,27.946157],"type":"Point"}
}