{
  "type": "Feature",
  "properties": {
    "iso:country":"US",
    "sg:address":"1300 E New York Ave",
    "sg:city":"Deland",
    "sg:classifiers":[
        {
            "category":"Wholesale",
            "subcategory":"Electrical",
            "type":"Manufacturing & Wholesale Goods"
        },
        {
            "category":"Shopping",
            "subcategory":"Computers & Home Electronics",
            "type":"Retail Goods"
        }
    ],
    "sg:phone":"+1 386 740 1320",
    "sg:postcode":"32724",
    "sg:province":"FL",
    "sg:tags":[
        "equipment",
        "dealer"
    ],
    "sg:website":"www.2keane.com",
    "wof:name":"Keane Machines Inc",
    "wof:placetype":"venue"
},
  "geometry": {"coordinates":[-81.278559,29.028235],"type":"Point"}
}