{
  "type": "Feature",
  "properties": {
    "iso:country":"US",
    "sg:address":"17800 Panama City Beach Pkwy",
    "sg:city":"Panama City Bch",
    "sg:classifiers":[
        {
            "category":"Professional",
            "subcategory":"Engineering",
            "type":"Services"
        }
    ],
    "sg:phone":"+1 850 234 1730",
    "sg:postcode":"32413",
    "sg:province":"FL",
    "sg:tags":[
        "engineer"
    ],
    "wof:name":"Mc Neil Carroll Engineer Inc",
    "wof:placetype":"venue"
},
  "geometry": {"coordinates":[-85.91339000000001,30.240789],"type":"Point"}
}