{
  "type": "Feature",
  "properties": {
    "addr:full":"1350 Greenview Shores Blvd Wellington FL 33414",
    "addr:housenumber":"1350",
    "addr:postcode":"33414",
    "addr:street":"Greenview Shores Blvd",
    "iso:country":"US",
    "sg:address":"1350 Greenview Shores Blvd",
    "sg:city":"Wellington",
    "sg:classifiers":[
        {
            "category":"Autos & Motor Vehicles",
            "subcategory":"Fuel & Gas Station",
            "type":"Retail Goods"
        }
    ],
    "sg:phone":"+1 561 795 0061",
    "sg:postcode":"33414",
    "sg:province":"FL",
    "sg:tags":[
        "oil"
    ],
    "wof:name":"Chevron Food Mart",
    "wof:placetype":"venue"
},
  "geometry": {"coordinates":[-80.268737,26.662748],"type":"Point"}
}