{
  "type": "Feature",
  "properties": {
    "iso:country":"US",
    "sg:address":"222 S Westmonte Dr",
    "sg:city":"Altamonte Springs",
    "sg:classifiers":[
        {
            "category":"Building & Trades",
            "subcategory":"Pest Control",
            "type":"Services"
        }
    ],
    "sg:phone":"+1 407 774 5500",
    "sg:postcode":"32714",
    "sg:province":"FL",
    "sg:tags":[
        "disinfecting"
    ],
    "wof:name":"Orkin",
    "wof:placetype":"venue"
},
  "geometry": {"coordinates":[-81.393304,28.66089],"type":"Point"}
}