{
  "type": "Feature",
  "properties": {
    "addr:full":"781 US Hwy 41 Venice FL 34285",
    "addr:housenumber":"781",
    "addr:postcode":"34285",
    "addr:street":"Us Hwy 41",
    "iso:country":"US",
    "sg:address":"781 US Hwy 41",
    "sg:city":"Venice",
    "sg:classifiers":[
        {
            "category":"Shopping",
            "type":"Retail Goods"
        }
    ],
    "sg:phone":"+1 941 485 3440",
    "sg:postcode":"34285",
    "sg:province":"FL",
    "sg:tags":[
        "repair",
        "pump",
        "supply",
        "pool",
        "accessory"
    ],
    "wof:name":"Economy Pool Supplies & Svc",
    "wof:placetype":"venue"
},
  "geometry": {"coordinates":[-82.43997299999999,27.08597],"type":"Point"}
}