{
  "type": "Feature",
  "properties": {
    "iso:country":"US",
    "sg:address":"7709 W Henry Ave",
    "sg:city":"Tampa",
    "sg:classifiers":[
        {
            "category":"Shopping",
            "subcategory":"Hobbies, Toys, & Games",
            "type":"Retail Goods"
        }
    ],
    "sg:phone":"+1 813 885 5562",
    "sg:postcode":"33615",
    "sg:province":"FL",
    "wof:name":"Hobby Cleveland H Jr and",
    "wof:placetype":"venue"
},
  "geometry": {"coordinates":[-82.568028,28.000888],"type":"Point"}
}