{
  "type": "Feature",
  "properties": {
    "addr:full":"159 SW 1st Ter Deerfield Beach FL 33441",
    "addr:housenumber":"159",
    "addr:postcode":"33441",
    "addr:street":"Sw 1St Ter;Beach",
    "iso:country":"US",
    "sg:address":"159 SW 1st Ter",
    "sg:city":"Deerfield Beach",
    "sg:classifiers":[
        {
            "category":"Personal",
            "subcategory":"Beauty Salon",
            "type":"Services"
        }
    ],
    "sg:phone":"+1 954 481 8373",
    "sg:postcode":"33441",
    "sg:province":"FL",
    "sg:tags":[
        "shop"
    ],
    "wof:name":"New Image Beauty Salon",
    "wof:placetype":"venue"
},
  "geometry": {"coordinates":[-80.10389600000001,26.316544],"type":"Point"}
}