{
  "type": "Feature",
  "properties": {
    "addr:full":"18365 SE Birdie Ln Jupiter FL 33469",
    "addr:housenumber":"18365",
    "addr:postcode":"33469",
    "addr:street":"Se Birdie Ln",
    "iso:country":"US",
    "sg:address":"18365 SE Birdie Ln",
    "sg:city":"Jupiter",
    "sg:classifiers":[
        {
            "category":"Shopping",
            "subcategory":"Gifts & Souvenirs",
            "type":"Retail Goods"
        }
    ],
    "sg:phone":"+1 561 746 2109",
    "sg:postcode":"33469",
    "sg:province":"FL",
    "sg:tags":[
        "shop"
    ],
    "wof:name":"Le Toade Stoole Inc",
    "wof:placetype":"venue"
},
  "geometry": {"coordinates":[-80.12314600000001,26.982893],"type":"Point"}
}