{
  "type": "Feature",
  "properties": {
    "iso:country":"US",
    "sg:address":"2858 Tunnel Rd",
    "sg:city":"Milton",
    "sg:classifiers":[
        {
            "category":"Building & Trades",
            "subcategory":"Plumbing",
            "type":"Services"
        }
    ],
    "sg:phone":"+1 850 995 8678",
    "sg:postcode":"32571",
    "sg:province":"FL",
    "sg:tags":[
        "contractor"
    ],
    "wof:name":"Mathews Heating & Air",
    "wof:placetype":"venue"
},
  "geometry": {"coordinates":[-87.202048,30.64846],"type":"Point"}
}