{
  "type": "Feature",
  "properties": {
    "iso:country":"US",
    "sg:address":"8880 NW 20th St Ste J",
    "sg:city":"Doral",
    "sg:classifiers":[
        {
            "category":"Professional",
            "subcategory":"Business Services",
            "type":"Services"
        }
    ],
    "sg:phone":"+1 305 593 5139",
    "sg:postcode":"33172",
    "sg:province":"FL",
    "sg:tags":[
        "medical",
        "administration"
    ],
    "wof:name":"Best Care Medical Pl",
    "wof:placetype":"venue"
},
  "geometry": {"coordinates":[-80.34022299999999,25.792491],"type":"Point"}
}