{
  "type": "Feature",
  "properties": {
    "iso:country":"US",
    "sg:address":"10345 Crotty Ave",
    "sg:city":"Hastings",
    "sg:classifiers":[
        {
            "category":"Wholesale",
            "subcategory":"Vending Machines",
            "type":"Manufacturing & Wholesale Goods"
        }
    ],
    "sg:phone":"+1 386 325 5842",
    "sg:postcode":"32145",
    "sg:province":"FL",
    "sg:tags":[
        "merchandise"
    ],
    "wof:name":"Danas Vending",
    "wof:placetype":"venue"
},
  "geometry": {"coordinates":[-81.427903,29.639246],"type":"Point"}
}