{
  "type": "Feature",
  "properties": {
    "iso:country":"US",
    "sg:address":"7617 SW 93rd Ct",
    "sg:city":"Miami",
    "sg:classifiers":[
        {
            "category":"Professional",
            "subcategory":"Business Services",
            "type":"Services"
        }
    ],
    "sg:phone":"+1 305 279 9800",
    "sg:postcode":"33173",
    "sg:province":"FL",
    "wof:name":"F & F Interiors Inc",
    "wof:placetype":"venue"
},
  "geometry": {"coordinates":[-80.344735,25.697338],"type":"Point"}
}