{
  "type": "Feature",
  "properties": {
    "addr:full":"228 Pinellas St Lakeland FL 33803",
    "addr:housenumber":"228",
    "addr:postcode":"33803",
    "addr:street":"Pinellas St",
    "iso:country":"US",
    "sg:address":"228 Pinellas St",
    "sg:city":"Lakeland",
    "sg:classifiers":[
        {
            "category":"Professional",
            "subcategory":"Engineering",
            "type":"Services"
        }
    ],
    "sg:phone":"+1 863 644 2297",
    "sg:postcode":"33803",
    "sg:province":"FL",
    "wof:name":"Perusa Enviromet Inc",
    "wof:placetype":"venue"
},
  "geometry": {"coordinates":[-81.95486099999999,28.000854],"type":"Point"}
}