{
  "type": "Feature",
  "properties": {
    "iso:country":"US",
    "sg:address":"1504 Avocado Ave",
    "sg:city":"Melbourne",
    "sg:classifiers":[
        {
            "category":"Health Services",
            "subcategory":"Clinic",
            "type":"Services"
        }
    ],
    "sg:phone":"+1 321 253 4271",
    "sg:postcode":"32935",
    "sg:province":"FL",
    "wof:name":"Comprehensive Health Care",
    "wof:placetype":"venue"
},
  "geometry": {"coordinates":[-80.630225,28.131647],"type":"Point"}
}