{
  "type": "Feature",
  "properties": {
    "iso:country":"US",
    "sg:address":"125 Hypoluxo Rd",
    "sg:city":"Lake Worth",
    "sg:classifiers":[
        {
            "category":"Home & Garden",
            "subcategory":"Garden Supply",
            "type":"Retail Goods"
        }
    ],
    "sg:phone":"+1 561 588 0423",
    "sg:postcode":"33462",
    "sg:province":"FL",
    "wof:name":"Melrose Supply & Sales Corp",
    "wof:placetype":"venue"
},
  "geometry": {"coordinates":[-80.054243,26.572045],"type":"Point"}
}