{
  "type": "Feature",
  "properties": {
    "addr:full":"317 SE Osceola St Stuart FL 34994",
    "addr:housenumber":"317",
    "addr:postcode":"34994",
    "addr:street":"Se Osceola St",
    "iso:country":"US",
    "sg:address":"317 SE Osceola St",
    "sg:city":"Stuart",
    "sg:classifiers":[
        {
            "category":"Wholesale",
            "subcategory":"Non-durable Goods",
            "type":"Manufacturing & Wholesale Goods"
        }
    ],
    "sg:phone":"+1 772 220 1588",
    "sg:postcode":"34994",
    "sg:province":"FL",
    "sg:tags":[
        "importing",
        "marketing",
        "merchandise"
    ],
    "wof:name":"S & H Usa Inc",
    "wof:placetype":"venue"
},
  "geometry": {"coordinates":[-80.24850000000001,27.198504],"type":"Point"}
}