{
  "type": "Feature",
  "properties": {
    "addr:full":"1695 Metropolitan Cir Tallahassee FL 32308",
    "addr:housenumber":"1695",
    "addr:postcode":"32308",
    "addr:street":"Metropolitan Cir",
    "iso:country":"US",
    "sg:address":"1695 Metropolitan Cir",
    "sg:city":"Tallahassee",
    "sg:classifiers":[
        {
            "category":"Professional",
            "subcategory":"Lawyer & Legal Services",
            "type":"Services"
        }
    ],
    "sg:phone":"+1 850 523 9300",
    "sg:postcode":"32308",
    "sg:province":"FL",
    "sg:tags":[
        "attorney"
    ],
    "wof:name":"Terrence T Dariotis",
    "wof:placetype":"venue"
},
  "geometry": {"coordinates":[-84.251024,30.497836],"type":"Point"}
}