{
  "type": "Feature",
  "properties": {
    "addr:full":"11244 SW 156th Ct Miami FL 33196",
    "addr:housenumber":"11244",
    "addr:postcode":"33196",
    "addr:street":"Sw 156Th Ct",
    "iso:country":"US",
    "sg:address":"11244 SW 156th Ct",
    "sg:city":"Miami",
    "sg:classifiers":[
        {
            "category":"Freight",
            "type":"Transportation"
        }
    ],
    "sg:phone":"+1 305 383 6171",
    "sg:postcode":"33196",
    "sg:province":"FL",
    "sg:tags":[
        "operator",
        "local",
        "trucking"
    ],
    "wof:name":"Roadstar Delivery",
    "wof:placetype":"venue"
},
  "geometry": {"coordinates":[-80.449044,25.662673],"type":"Point"}
}