{
  "type": "Feature",
  "properties": {
    "iso:country":"US",
    "sg:address":"405 E North St",
    "sg:city":"Tampa",
    "sg:classifiers":[
        {
            "category":"Building & Trades",
            "subcategory":"Landscaping Services",
            "type":"Services"
        }
    ],
    "sg:phone":"+1 813 234 3121",
    "sg:postcode":"33604",
    "sg:province":"FL",
    "sg:tags":[
        "landscape"
    ],
    "wof:name":"Natural Landscape Solutions",
    "wof:placetype":"venue"
},
  "geometry": {"coordinates":[-82.456383,28.005718],"type":"Point"}
}