{
  "type": "Feature",
  "properties": {
    "addr:full":"10822 SW 89th Ter Miami FL 33176",
    "addr:housenumber":"10822",
    "addr:postcode":"33176",
    "addr:street":"Sw 89Th Ter",
    "iso:country":"US",
    "sg:address":"10822 SW 89th Ter",
    "sg:city":"Miami",
    "sg:classifiers":[
        {
            "category":"Wholesale",
            "subcategory":"Machinery & Supplies",
            "type":"Manufacturing & Wholesale Goods"
        },
        {
            "category":"Building & Trades",
            "subcategory":"Electrical",
            "type":"Services"
        }
    ],
    "sg:phone":"+1 305 279 2662",
    "sg:postcode":"33176",
    "sg:province":"FL",
    "sg:tags":[
        "used",
        "machinery-new",
        "power",
        "transmission",
        "equipment",
        "industrial"
    ],
    "wof:name":"Romulex Export & Import Inc",
    "wof:placetype":"venue"
},
  "geometry": {"coordinates":[-80.370926,25.685491],"type":"Point"}
}