{
  "type": "Feature",
  "properties": {
    "addr:full":"1801 French Creek Rd Tampa FL 33613",
    "addr:housenumber":"1801",
    "addr:postcode":"33613",
    "addr:street":"French Creek Rd",
    "iso:country":"US",
    "sg:address":"1801 French Creek Rd",
    "sg:city":"Tampa",
    "sg:classifiers":[
        {
            "category":"Shopping",
            "subcategory":"Computers & Home Electronics",
            "type":"Retail Goods"
        },
        {
            "category":"Professional",
            "subcategory":"Computer Services",
            "type":"Services"
        }
    ],
    "sg:phone":"+1 813 863 1519",
    "sg:postcode":"33613",
    "sg:province":"FL",
    "sg:tags":[
        "repair",
        "network",
        "supply",
        "technical",
        "assistance",
        "system",
        "hardware",
        "design",
        "equipment-service",
        "support",
        "software"
    ],
    "wof:name":"Omega Computer Systems",
    "wof:placetype":"venue"
},
  "geometry": {"coordinates":[-82.441299,28.07181],"type":"Point"}
}