{
  "type": "Feature",
  "properties": {
    "iso:country":"US",
    "sg:address":"3281 Easy St",
    "sg:city":"Port Charlotte",
    "sg:classifiers":[
        {
            "category":"Building & Trades",
            "subcategory":"Landscaping Services",
            "type":"Services"
        }
    ],
    "sg:phone":"+1 941 743 5616",
    "sg:postcode":"33952",
    "sg:province":"FL",
    "sg:tags":[
        "landscape"
    ],
    "wof:name":"Andrade & Macarini Inc",
    "wof:placetype":"venue"
},
  "geometry": {"coordinates":[-82.090433,26.982049],"type":"Point"}
}