{
  "type": "Feature",
  "properties": {
    "iso:country":"US",
    "sg:address":"1981 Winding Oaks Way",
    "sg:city":"Naples",
    "sg:classifiers":[
        {
            "category":"Wholesale",
            "subcategory":"Non-durable Goods",
            "type":"Manufacturing & Wholesale Goods"
        }
    ],
    "sg:phone":"+1 239 513 1266",
    "sg:postcode":"34109",
    "sg:province":"FL",
    "wof:name":"Competitive Edge",
    "wof:placetype":"venue"
},
  "geometry": {"coordinates":[-81.77579900000001,26.263101],"type":"Point"}
}