{
  "type": "Feature",
  "properties": {
    "addr:full":"350 Biscayne Blvd Miami FL 33132",
    "addr:housenumber":"350",
    "addr:postcode":"33132",
    "addr:street":"Biscayne Blvd",
    "iso:country":"US",
    "sg:address":"350 Biscayne Blvd",
    "sg:city":"Miami",
    "sg:classifiers":[
        {
            "category":"Arts & Performance",
            "subcategory":"Theater",
            "type":"Entertainment"
        }
    ],
    "sg:phone":"+1 305 573 6105",
    "sg:postcode":"33132",
    "sg:province":"FL",
    "sg:tags":[
        "bureau"
    ],
    "wof:name":"Fredericks Entertainment",
    "wof:placetype":"venue"
},
  "geometry": {"coordinates":[-80.188036,25.777669],"type":"Point"}
}