{
  "type": "Feature",
  "properties": {
    "addr:full":"9901 Gulf Blvd Treasure Island FL 33706",
    "addr:housenumber":"9901",
    "addr:postcode":"33706",
    "addr:street":"Gulf Blvd",
    "iso:country":"US",
    "sg:address":"9901 Gulf Blvd",
    "sg:city":"Treasure Island",
    "sg:classifiers":[
        {
            "category":"Shopping",
            "subcategory":"Gifts & Souvenirs",
            "type":"Retail Goods"
        }
    ],
    "sg:phone":"+1 727 367 9599",
    "sg:postcode":"33706",
    "sg:province":"FL",
    "sg:tags":[
        "shell"
    ],
    "wof:name":"Florida Shell Shop",
    "wof:placetype":"venue"
},
  "geometry": {"coordinates":[-82.765558,27.759085],"type":"Point"}
}