{
  "type": "Feature",
  "properties": {
    "iso:country":"US",
    "sg:address":"10831 Bal Harbor Dr",
    "sg:city":"Boca Raton",
    "sg:classifiers":[
        {
            "category":"Shopping",
            "subcategory":"Catalog Store",
            "type":"Retail Goods"
        }
    ],
    "sg:phone":"+1 561 852 5789",
    "sg:postcode":"33498",
    "sg:province":"FL",
    "sg:tags":[
        "mail",
        "house"
    ],
    "wof:name":"Sparkys Collectibles",
    "wof:placetype":"venue"
},
  "geometry": {"coordinates":[-80.21653999999999,26.378916],"type":"Point"}
}