{
  "type": "Feature",
  "properties": {
    "addr:full":"12491 SW 130th St Miami FL 33186",
    "addr:housenumber":"12491",
    "addr:postcode":"33186",
    "addr:street":"Sw 130Th St",
    "iso:country":"US",
    "sg:address":"12491 SW 130th St",
    "sg:city":"Miami",
    "sg:classifiers":[
        {
            "category":"Home & Garden",
            "subcategory":"Building Materials",
            "type":"Retail Goods"
        }
    ],
    "sg:phone":"+1 305 252 0509",
    "sg:postcode":"33186",
    "sg:province":"FL",
    "wof:name":"Everlasting Woodwork",
    "wof:placetype":"venue"
},
  "geometry": {"coordinates":[-80.39622,25.646917],"type":"Point"}
}