{
  "type": "Feature",
  "properties": {
    "iso:country":"US",
    "sg:address":"200 W Main St",
    "sg:city":"Apopka",
    "sg:classifiers":[
        {
            "category":"Manufacturing",
            "subcategory":"Rubber & Plastics",
            "type":"Manufacturing & Wholesale Goods"
        },
        {
            "category":"Autos & Motor Vehicles",
            "subcategory":"Auto Supplies",
            "type":"Retail Goods"
        },
        {
            "category":"Retail",
            "subcategory":"Auto Repair",
            "type":"Services"
        }
    ],
    "sg:phone":"+1 407 889 7074",
    "sg:postcode":"32703",
    "sg:province":"FL",
    "sg:tags":[
        "recap",
        "retread",
        "tires-wholesale",
        "tire",
        "manufacturer"
    ],
    "sg:website":"http://www.coopertire.com/html/",
    "wof:name":"A.O.K. Tire Mart",
    "wof:placetype":"venue"
},
  "geometry": {"coordinates":[-81.51583100000001,28.675529],"type":"Point"}
}