{
  "type": "Feature",
  "properties": {
    "iso:country":"US",
    "sg:address":"2634 Apopka Blvd",
    "sg:city":"Apopka",
    "sg:classifiers":[
        {
            "category":"Wholesale",
            "subcategory":"Electrical",
            "type":"Manufacturing & Wholesale Goods"
        }
    ],
    "sg:phone":"+1 407 296 8655",
    "sg:postcode":"32703",
    "sg:province":"FL",
    "sg:tags":[
        "battery"
    ],
    "wof:name":"Battery World Inc",
    "wof:placetype":"venue"
},
  "geometry": {"coordinates":[-81.458506,28.638404],"type":"Point"}
}