{
  "type": "Feature",
  "properties": {
    "iso:country":"US",
    "sg:address":"9835 NE 2nd Ave",
    "sg:city":"Miami Shores",
    "sg:classifiers":[
        {
            "category":"Building & Trades",
            "subcategory":"Locksmith",
            "type":"Services"
        }
    ],
    "sg:phone":"+1 305 755 4586",
    "sg:postcode":"33138",
    "sg:province":"FL",
    "sg:tags":[
        "key"
    ],
    "wof:name":"Always Available 24 Hour Emergency Locksmith",
    "wof:placetype":"venue"
},
  "geometry": {"coordinates":[-80.193355,25.865497],"type":"Point"}
}