{
  "type": "Feature",
  "properties": {
    "iso:country":"US",
    "sg:address":"5300 Georgia Ave",
    "sg:city":"West Palm Beach",
    "sg:classifiers":[
        {
            "category":"Wholesale",
            "subcategory":"Seafood",
            "type":"Manufacturing & Wholesale Goods"
        }
    ],
    "sg:phone":"+1 561 586 2212",
    "sg:postcode":"33405",
    "sg:province":"FL",
    "wof:name":"Independent Seafood",
    "wof:placetype":"venue"
},
  "geometry": {"coordinates":[-80.058727,26.665539],"type":"Point"}
}