{
  "type": "Feature",
  "properties": {
    "iso:country":"US",
    "sg:address":"420 Havendale Blvd",
    "sg:city":"Auburndale",
    "sg:classifiers":[
        {
            "category":"Restaurant",
            "type":"Food & Drink"
        }
    ],
    "sg:menulink":"http://www.allmenus.com/fl/winter-haven-auburndale/187000-mcdonalds/menu/",
    "sg:postcode":"33823",
    "sg:province":"FL",
    "sg:tags":[
        "burger",
        "american"
    ],
    "wof:name":"McDonald's",
    "wof:placetype":"venue"
},
  "geometry": {"coordinates":[-81.777748,28.054775],"type":"Point"}
}