{
  "type": "Feature",
  "properties": {
    "addr:full":"5365 W Nine Mile Rd Pensacola FL 32526",
    "addr:housenumber":"5365",
    "addr:postcode":"32526",
    "addr:street":"W Nine Mile Rd",
    "iso:country":"US",
    "sg:address":"5365 W Nine Mile Rd",
    "sg:city":"Pensacola",
    "sg:classifiers":[
        {
            "category":"Health Services",
            "subcategory":"Medical Lab",
            "type":"Services"
        }
    ],
    "sg:phone":"+1 850 941 8181",
    "sg:postcode":"32526",
    "sg:province":"FL",
    "sg:website":"http://www.doclicense.com",
    "wof:name":"Doctors Licensure Group",
    "wof:placetype":"venue"
},
  "geometry": {"coordinates":[-87.37394999999999,30.535481],"type":"Point"}
}