{
  "type": "Feature",
  "properties": {
    "iso:country":"US",
    "sg:address":"2243 NW 2nd Ave",
    "sg:city":"Miami",
    "sg:classifiers":[
        {
            "category":"Shopping",
            "subcategory":"Clothing, Apparel, & Fashions",
            "type":"Retail Goods"
        }
    ],
    "sg:phone":"+1 305 572 1330",
    "sg:postcode":"33127",
    "sg:province":"FL",
    "wof:name":"Duek's Fashion",
    "wof:placetype":"venue"
},
  "geometry": {"coordinates":[-80.198941,25.798774],"type":"Point"}
}