{
  "type": "Feature",
  "properties": {
    "iso:country":"US",
    "sg:address":"4011 E Columbus Dr",
    "sg:city":"Tampa",
    "sg:classifiers":[
        {
            "category":"Travel",
            "subcategory":"Hotels & Motels",
            "type":"Entertainment"
        }
    ],
    "sg:phone":"+1 813 740 1161",
    "sg:postcode":"33605",
    "sg:province":"FL",
    "wof:name":"Golden Motel",
    "wof:placetype":"venue"
},
  "geometry": {"coordinates":[-82.410134,27.96669],"type":"Point"}
}