{
  "type": "Feature",
  "properties": {
    "addr:full":"718 Lakeside Cir North Palm Beach FL 33408",
    "addr:housenumber":"718",
    "addr:postcode":"33408",
    "addr:street":"Lakeside Cir North",
    "iso:country":"US",
    "sg:address":"718 Lakeside Cir",
    "sg:city":"North Palm Beach",
    "sg:classifiers":[
        {
            "category":"Real Estate",
            "subcategory":"Real Estate Agent",
            "type":"Services"
        }
    ],
    "sg:phone":"+1 561 881 1248",
    "sg:postcode":"33408",
    "sg:province":"FL",
    "wof:name":"JGM Properties Inc",
    "wof:placetype":"venue"
},
  "geometry": {"coordinates":[-80.05467,26.818376],"type":"Point"}
}