{
  "type": "Feature",
  "properties": {
    "addr:full":"1200 Deltona Blvd Deltona FL 32725",
    "addr:housenumber":"1200",
    "addr:postcode":"32725",
    "addr:street":"Deltona Blvd",
    "iso:country":"US",
    "sg:address":"1200 Deltona Blvd",
    "sg:city":"Deltona",
    "sg:classifiers":[
        {
            "category":"Restaurant",
            "type":"Food & Drink"
        }
    ],
    "sg:phone":"+1 386 574 7477",
    "sg:postcode":"32725",
    "sg:province":"FL",
    "wof:name":"Marie's Place",
    "wof:placetype":"venue"
},
  "geometry": {"coordinates":[-81.27159899999999,28.8957],"type":"Point"}
}