{
  "type": "Feature",
  "properties": {
    "iso:country":"US",
    "sg:address":"1838 Patterson Ave",
    "sg:city":"De Land",
    "sg:classifiers":[
        {
            "category":"Manufacturing",
            "subcategory":"Food",
            "type":"Manufacturing & Wholesale Goods"
        }
    ],
    "sg:phone":"+1 386 734 3029",
    "sg:postcode":"32724",
    "sg:province":"FL",
    "sg:tags":[
        "mfg"
    ],
    "wof:name":"Florida Gourmet Foods",
    "wof:placetype":"venue"
},
  "geometry": {"coordinates":[-81.29885299999999,29.058561],"type":"Point"}
}