{
  "type": "Feature",
  "properties": {
    "addr:full":"1485 37th St Vero Beach FL 32960",
    "addr:housenumber":"1485",
    "addr:postcode":"32960",
    "addr:street":"37Th St",
    "iso:country":"US",
    "sg:address":"1485 37th St",
    "sg:city":"Vero Beach",
    "sg:classifiers":[
        {
            "category":"Social Services",
            "subcategory":"Job Training",
            "type":"Services"
        }
    ],
    "sg:phone":"+1 772 562 7917",
    "sg:postcode":"32960",
    "sg:province":"FL",
    "sg:tags":[
        "rehabilitation"
    ],
    "wof:name":"Treasure Coast Rehab Hosp",
    "wof:placetype":"venue"
},
  "geometry": {"coordinates":[-80.399451,27.660177],"type":"Point"}
}