{
  "type": "Feature",
  "properties": {
    "addr:full":"2720 S Dixie Hwy Ste F Miami FL 33133",
    "addr:housenumber":"2720",
    "addr:postcode":"33133",
    "addr:street":"S Dixie Hwy Ste F",
    "iso:country":"US",
    "sg:address":"2720 S Dixie Hwy Ste F",
    "sg:city":"Miami",
    "sg:classifiers":[
        {
            "category":"Sports & Exercise",
            "subcategory":"Gym",
            "type":"Entertainment"
        }
    ],
    "sg:phone":"+1 305 448 3508",
    "sg:postcode":"33133",
    "sg:province":"FL",
    "sg:tags":[
        "trainer"
    ],
    "wof:name":"Jenny Craig Weight Loss Centres",
    "wof:placetype":"venue"
},
  "geometry": {"coordinates":[-80.23840300000001,25.7397],"type":"Point"}
}