{
  "type": "Feature",
  "properties": {
    "iso:country":"US",
    "sg:address":"17843 Murdock Cir",
    "sg:city":"Port Charlotte",
    "sg:classifiers":[
        {
            "category":"Professional",
            "subcategory":"Lawyer & Legal Services",
            "type":"Services"
        }
    ],
    "sg:phone":"+1 941 743 2990",
    "sg:postcode":"33948",
    "sg:province":"FL",
    "sg:tags":[
        "attorney"
    ],
    "wof:name":"R Kimber Martin",
    "wof:placetype":"venue"
},
  "geometry": {"coordinates":[-82.150362,27.006702],"type":"Point"}
}