{
  "type": "Feature",
  "properties": {
    "addr:full":"2736 SW 37th Ave Coconut Grove FL 33133",
    "addr:housenumber":"2736",
    "addr:postcode":"33133",
    "addr:street":"Sw 37Th Ave",
    "iso:country":"US",
    "sg:address":"2736 SW 37th Ave",
    "sg:city":"Coconut Grove",
    "sg:classifiers":[
        {
            "category":"Food & Beverages",
            "subcategory":"Groceries & Convenience Stores",
            "type":"Retail Goods"
        }
    ],
    "sg:phone":"+1 305 445 1717",
    "sg:postcode":"33133",
    "sg:province":"FL",
    "wof:name":"El Polar Supermarket & Cafeteria",
    "wof:placetype":"venue"
},
  "geometry": {"coordinates":[-80.25430299999999,25.740499],"type":"Point"}
}