{
  "type": "Feature",
  "properties": {
    "addr:full":"5704 Lakefield Ct Orlando FL 32810",
    "addr:housenumber":"5704",
    "addr:postcode":"32810",
    "addr:street":"Lakefield Ct",
    "iso:country":"US",
    "sg:address":"5704 Lakefield Ct",
    "sg:city":"Orlando",
    "sg:classifiers":[
        {
            "category":"Freight",
            "type":"Transportation"
        }
    ],
    "sg:phone":"+1 407 445 7263",
    "sg:postcode":"32810",
    "sg:province":"FL",
    "wof:name":"Jerome Andre Transportation",
    "wof:placetype":"venue"
},
  "geometry": {"coordinates":[-81.462416,28.616315],"type":"Point"}
}