{
  "type": "Feature",
  "properties": {
    "addr:full":"13951 50th St S Wellington FL 33414",
    "addr:housenumber":"13951",
    "addr:postcode":"33414",
    "addr:street":"50Th St S",
    "iso:country":"US",
    "sg:address":"13951 50th St S",
    "sg:city":"Wellington",
    "sg:classifiers":[
        {
            "category":"Farming",
            "subcategory":"Nursery",
            "type":"Manufacturing & Wholesale Goods"
        },
        {
            "category":"Manufacturing",
            "subcategory":"Paper Products",
            "type":"Manufacturing & Wholesale Goods"
        }
    ],
    "sg:phone":"+1 561 753 9700",
    "sg:postcode":"33414",
    "sg:province":"FL",
    "sg:tags":[
        "bamboo",
        "tree",
        "nurseries-plants"
    ],
    "sg:website":"http://www.southeastgrowers.com",
    "wof:name":"Southeast Growers Inc",
    "wof:placetype":"venue"
},
  "geometry": {"coordinates":[-80.269666,26.608085],"type":"Point"}
}