{
  "type": "Feature",
  "properties": {
    "addr:full":"4645 Mirabella Ct Saint Petersburg FL 33706",
    "addr:housenumber":"4645",
    "addr:postcode":"33706",
    "addr:street":"Mirabella Ct",
    "iso:country":"US",
    "sg:address":"4645 Mirabella Ct",
    "sg:city":"Saint Petersburg",
    "sg:classifiers":[
        {
            "category":"Professional",
            "subcategory":"Management & Consulting",
            "type":"Services"
        }
    ],
    "sg:phone":"+1 727 363 0177",
    "sg:postcode":"33706",
    "sg:province":"FL",
    "wof:name":"Oak Creek Capital",
    "wof:placetype":"venue"
},
  "geometry": {"coordinates":[-82.737397,27.722171],"type":"Point"}
}