{
  "type": "Feature",
  "properties": {
    "iso:country":"US",
    "sg:address":"128 S Federal Hwy",
    "sg:city":"Dania",
    "sg:classifiers":[
        {
            "category":"Restaurant",
            "type":"Food & Drink"
        }
    ],
    "sg:menulink":"http://www.allmenus.com/fl/hollywood/15924-jaxons/menu/",
    "sg:phone":"+1 954 923 4445",
    "sg:postcode":"33004",
    "sg:province":"FL",
    "sg:tags":[
        "american"
    ],
    "wof:name":"Jaxon's",
    "wof:placetype":"venue"
},
  "geometry": {"coordinates":[-80.143536,26.0499],"type":"Point"}
}