{
  "type": "Feature",
  "properties": {
    "iso:country":"US",
    "sg:address":"6633 E Gentry St",
    "sg:city":"Inverness",
    "sg:classifiers":[
        {
            "category":"Building & Trades",
            "subcategory":"Landscaping Services",
            "type":"Services"
        }
    ],
    "sg:phone":"+1 352 341 1648",
    "sg:postcode":"34452",
    "sg:province":"FL",
    "sg:tags":[
        "lawn",
        "maintenance",
        "grounds"
    ],
    "wof:name":"Brian Reed's Lawn Care",
    "wof:placetype":"venue"
},
  "geometry": {"coordinates":[-82.32449800000001,28.809108],"type":"Point"}
}