{
  "type": "Feature",
  "properties": {
    "addr:full":"2450 Sweetland Ave Sarasota FL 34232",
    "addr:postcode":"2450;34232",
    "addr:street":"Sweetland Ave",
    "iso:country":"US",
    "sg:address":"2450 Sweetland Ave",
    "sg:city":"Sarasota",
    "sg:classifiers":[
        {
            "category":"Organizations",
            "subcategory":"Religious Organization",
            "type":"Services"
        }
    ],
    "sg:phone":"+1 941 922 7583",
    "sg:postcode":"34232",
    "sg:province":"FL",
    "wof:name":"Amb Ministries",
    "wof:placetype":"venue"
},
  "geometry": {"coordinates":[-82.49121,27.309167],"type":"Point"}
}