{
  "type": "Feature",
  "properties": {
    "addr:full":"2300 Simpson Ridge Cir Kissimmee FL 34744",
    "addr:housenumber":"2300",
    "addr:postcode":"34744",
    "addr:street":"Simpson Ridge Cir",
    "iso:country":"US",
    "sg:address":"2300 Simpson Ridge Cir",
    "sg:city":"Kissimmee",
    "sg:classifiers":[
        {
            "category":"Real Estate",
            "subcategory":"Real Estate Operator",
            "type":"Services"
        }
    ],
    "sg:phone":"+1 407 870 5220",
    "sg:postcode":"34744",
    "sg:province":"FL",
    "sg:tags":[
        "building",
        "apartment"
    ],
    "wof:name":"Simpson Ridge Apts Ltd",
    "wof:placetype":"venue"
},
  "geometry": {"coordinates":[-81.350077,28.289692],"type":"Point"}
}