{
  "type": "Feature",
  "properties": {
    "iso:country":"US",
    "sg:address":"9597 Oregon Rd",
    "sg:city":"Boca Raton",
    "sg:classifiers":[
        {
            "category":"Building & Trades",
            "subcategory":"Landscaping Services",
            "type":"Services"
        }
    ],
    "sg:phone":"+1 561 487 4789",
    "sg:postcode":"33434",
    "sg:province":"FL",
    "wof:name":"Shur-Cut Lawn & Landscape Inc",
    "wof:placetype":"venue"
},
  "geometry": {"coordinates":[-80.196659,26.392805],"type":"Point"}
}