{
  "type": "Feature",
  "properties": {
    "addr:full":"1001 8th Ave W Palmetto FL 34221",
    "addr:housenumber":"1001",
    "addr:postcode":"34221",
    "addr:street":"8Th Ave W",
    "iso:country":"US",
    "sg:address":"1001 8th Ave W",
    "sg:city":"Palmetto",
    "sg:classifiers":[
        {
            "category":"Restaurant",
            "type":"Food & Drink"
        }
    ],
    "sg:menulink":"http://www.allmenus.com/fl/palmetto/163208-rallys/menu/",
    "sg:phone":"+1 941 723 9231",
    "sg:postcode":"34221",
    "sg:province":"FL",
    "sg:tags":[
        "sandwich",
        "dog",
        "burger",
        "hot",
        "wrap",
        "american"
    ],
    "wof:name":"Rally's",
    "wof:placetype":"venue"
},
  "geometry": {"coordinates":[-82.57291600000001,27.52127],"type":"Point"}
}