{
  "type": "Feature",
  "properties": {
    "iso:country":"US",
    "sg:address":"2991 Commercial Way",
    "sg:city":"Spring Hill",
    "sg:classifiers":[
        {
            "category":"Personal",
            "subcategory":"Beauty Salon",
            "type":"Services"
        }
    ],
    "sg:phone":"+1 352 666 7057",
    "sg:postcode":"34606",
    "sg:province":"FL",
    "sg:tags":[
        "shop"
    ],
    "wof:name":"Shear Beauty Hair Salon",
    "wof:placetype":"venue"
},
  "geometry": {"coordinates":[-82.612075,28.477542],"type":"Point"}
}