{
  "type": "Feature",
  "properties": {
    "iso:country":"US",
    "sg:address":"311 S Brevard Ave",
    "sg:city":"Tampa",
    "sg:classifiers":[
        {
            "category":"Professional",
            "subcategory":"Lawyer & Legal Services",
            "type":"Services"
        }
    ],
    "sg:phone":"+1 813 250 0323",
    "sg:postcode":"33606",
    "sg:province":"FL",
    "wof:name":"Law Office Hlen Stratigakos PA",
    "wof:placetype":"venue"
},
  "geometry": {"coordinates":[-82.466809,27.940691],"type":"Point"}
}