{
  "type": "Feature",
  "properties": {
    "addr:full":"9774 NW 27th Ter Miami FL 33172",
    "addr:housenumber":"9774",
    "addr:postcode":"33172",
    "addr:street":"Nw 27Th Ter",
    "iso:country":"US",
    "sg:address":"9774 NW 27th Ter",
    "sg:city":"Miami",
    "sg:classifiers":[
        {
            "category":"Freight",
            "type":"Transportation"
        }
    ],
    "sg:phone":"+1 305 477 5405",
    "sg:postcode":"33172",
    "sg:province":"FL",
    "sg:tags":[
        "operator",
        "local",
        "trucking"
    ],
    "wof:name":"Jorge Deliveries",
    "wof:placetype":"venue"
},
  "geometry": {"coordinates":[-80.353826,25.799451],"type":"Point"}
}