{
  "type": "Feature",
  "properties": {
    "iso:country":"US",
    "sg:address":"601 S Falkenburg Rd",
    "sg:city":"Tampa",
    "sg:classifiers":[
        {
            "category":"Recreation",
            "subcategory":"Amusement Park",
            "type":"Entertainment"
        }
    ],
    "sg:phone":"+1 813 685 8792",
    "sg:postcode":"33619",
    "sg:province":"FL",
    "sg:tags":[
        "device"
    ],
    "wof:name":"Comspeq International",
    "wof:placetype":"venue"
},
  "geometry": {"coordinates":[-82.334974,27.94505],"type":"Point"}
}