{
  "type": "Feature",
  "properties": {
    "iso:country":"US",
    "sg:address":"342 Andalusia Ave",
    "sg:city":"Ormond Beach",
    "sg:classifiers":[
        {
            "category":"Building & Trades",
            "subcategory":"Plumbing",
            "type":"Services"
        }
    ],
    "sg:phone":"+1 386 673 5335",
    "sg:postcode":"32174",
    "sg:province":"FL",
    "sg:tags":[
        "heating",
        "contractor"
    ],
    "wof:name":"Noah Day & Associates",
    "wof:placetype":"venue"
},
  "geometry": {"coordinates":[-81.05749,29.272167],"type":"Point"}
}