{
  "type": "Feature",
  "properties": {
    "iso:country":"US",
    "sg:address":"1401 S Ridgewood Ave",
    "sg:city":"Edgewater",
    "sg:classifiers":[
        {
            "category":"Personal",
            "subcategory":"Beauty Salon",
            "type":"Services"
        }
    ],
    "sg:phone":"+1 386 427 4321",
    "sg:postcode":"32132",
    "sg:province":"FL",
    "wof:name":"Alpha Omega",
    "wof:placetype":"venue"
},
  "geometry": {"coordinates":[-80.899002,28.97768],"type":"Point"}
}