{
  "type": "Feature",
  "properties": {
    "iso:country":"US",
    "sg:address":"4532 W Village Dr",
    "sg:city":"Tampa",
    "sg:classifiers":[
        {
            "category":"Personal",
            "type":"Services"
        },
        {
            "category":"Sports & Exercise",
            "subcategory":"Gym",
            "type":"Entertainment"
        },
        {
            "category":"Arena",
            "subcategory":"Sports Club",
            "type":"Entertainment"
        }
    ],
    "sg:phone":"+1 813 962 1850",
    "sg:postcode":"33624",
    "sg:province":"FL",
    "sg:tags":[
        "trainer",
        "consultant",
        "program",
        "health",
        "fitness",
        "physical"
    ],
    "wof:name":"Fitness First",
    "wof:placetype":"venue"
},
  "geometry": {"coordinates":[-82.52327,28.073218],"type":"Point"}
}