{
  "type": "Feature",
  "properties": {
    "iso:country":"US",
    "sg:address":"608 SW 12th Ct",
    "sg:city":"Fort Lauderdale",
    "sg:classifiers":[
        {
            "category":"Building & Trades",
            "subcategory":"Plumbing",
            "type":"Services"
        }
    ],
    "sg:phone":"+1 954 527 4654",
    "sg:postcode":"33315",
    "sg:province":"FL",
    "sg:tags":[
        "contractor"
    ],
    "wof:name":"P S Plumbing Inc",
    "wof:placetype":"venue"
},
  "geometry": {"coordinates":[-80.15071,26.106395],"type":"Point"}
}