{
  "type": "Feature",
  "properties": {
    "iso:country":"US",
    "sg:address":"10 NW 42nd Ave",
    "sg:city":"Miami",
    "sg:classifiers":[
        {
            "category":"Professional",
            "subcategory":"Computer Services",
            "type":"Services"
        }
    ],
    "sg:phone":"+1 305 447 4900",
    "sg:postcode":"33126",
    "sg:province":"FL",
    "sg:tags":[
        "repair"
    ],
    "sg:website":"www.compits.net",
    "wof:name":"Computer It Solutions",
    "wof:placetype":"venue"
},
  "geometry": {"coordinates":[-80.263886,25.771746],"type":"Point"}
}