{
  "type": "Feature",
  "properties": {
    "addr:full":"4880 Cangro St Cocoa FL 32926",
    "addr:postcode":"4880;32926",
    "addr:street":"Cangro St",
    "iso:country":"US",
    "sg:address":"4880 Cangro St",
    "sg:city":"Cocoa",
    "sg:classifiers":[
        {
            "category":"Retail",
            "subcategory":"Auto Repair",
            "type":"Services"
        }
    ],
    "sg:phone":"+1 321 636 5758",
    "sg:postcode":"32926",
    "sg:province":"FL",
    "sg:tags":[
        "automotive"
    ],
    "wof:name":"Toms Mobile Marine",
    "wof:placetype":"venue"
},
  "geometry": {"coordinates":[-80.826672,28.430713],"type":"Point"}
}