{
  "type": "Feature",
  "properties": {
    "iso:country":"US",
    "sg:address":"128 Odin Dr",
    "sg:city":"Winter Haven",
    "sg:classifiers":[
        {
            "category":"Farming",
            "subcategory":"Orchard",
            "type":"Manufacturing & Wholesale Goods"
        }
    ],
    "sg:phone":"+1 863 324 1699",
    "sg:postcode":"33884",
    "sg:province":"FL",
    "sg:tags":[
        "citrus",
        "grove",
        "fruit"
    ],
    "wof:name":"Billie B Garrett",
    "wof:placetype":"venue"
},
  "geometry": {"coordinates":[-81.71355699999999,27.97884],"type":"Point"}
}