{
  "type": "Feature",
  "properties": {
    "iso:country":"US",
    "sg:address":"4070 N US Hwy 17",
    "sg:city":"Deland",
    "sg:classifiers":[
        {
            "category":"Retail",
            "subcategory":"Auto Repair",
            "type":"Services"
        }
    ],
    "sg:phone":"+1 386 985 0304",
    "sg:postcode":"32720",
    "sg:province":"FL",
    "sg:tags":[
        "repairing",
        "automobile"
    ],
    "wof:name":"Barrie Wholesalers",
    "wof:placetype":"venue"
},
  "geometry": {"coordinates":[-81.33645,29.099078],"type":"Point"}
}