{
  "type": "Feature",
  "properties": {
    "addr:full":"2627 Coventry Ln Ocoee FL 34761",
    "addr:housenumber":"2627",
    "addr:postcode":"34761",
    "addr:street":"Coventry Ln",
    "iso:country":"US",
    "sg:address":"2627 Coventry Ln",
    "sg:city":"Ocoee",
    "sg:classifiers":[
        {
            "category":"Professional",
            "subcategory":"Management & Consulting",
            "type":"Services"
        }
    ],
    "sg:phone":"+1 407 578 1224",
    "sg:postcode":"34761",
    "sg:province":"FL",
    "sg:tags":[
        "retail",
        "direct",
        "sales"
    ],
    "wof:name":"J P Enterprise",
    "wof:placetype":"venue"
},
  "geometry": {"coordinates":[-81.504536,28.580772],"type":"Point"}
}