{
  "type": "Feature",
  "properties": {
    "iso:country":"US",
    "sg:address":"2318 E Hwy 98",
    "sg:city":"Panama City",
    "sg:classifiers":[
        {
            "category":"Retail",
            "subcategory":"Auto Repair",
            "type":"Services"
        }
    ],
    "sg:phone":"+1 850 763 5226",
    "sg:postcode":"32401",
    "sg:province":"FL",
    "sg:tags":[
        "repairing",
        "automobile"
    ],
    "wof:name":"Noles Automotive",
    "wof:placetype":"venue"
},
  "geometry": {"coordinates":[-85.628516,30.156731],"type":"Point"}
}