{
  "type": "Feature",
  "properties": {
    "iso:country":"US",
    "sg:address":"8325 NW 68th St",
    "sg:city":"Miami",
    "sg:classifiers":[
        {
            "category":"Wholesale",
            "subcategory":"Machinery & Supplies",
            "type":"Manufacturing & Wholesale Goods"
        },
        {
            "category":"Airline",
            "type":"Transportation"
        }
    ],
    "sg:phone":"+1 305 592 6192",
    "sg:postcode":"33166",
    "sg:province":"FL",
    "sg:tags":[
        "aviation",
        "consulting",
        "dist",
        "company"
    ],
    "wof:name":"Skytrade International Entp",
    "wof:placetype":"venue"
},
  "geometry": {"coordinates":[-80.3318,25.835346],"type":"Point"}
}