{
  "type": "Feature",
  "properties": {
    "addr:full":"205 SE 29th Ave Ocala FL 34471",
    "addr:housenumber":"205",
    "addr:postcode":"34471",
    "addr:street":"Se 29Th Ave",
    "iso:country":"US",
    "sg:address":"205 SE 29th Ave",
    "sg:city":"Ocala",
    "sg:classifiers":[
        {
            "category":"Building & Trades",
            "subcategory":"Construction",
            "type":"Services"
        }
    ],
    "sg:phone":"+1 352 895 2612",
    "sg:postcode":"34471",
    "sg:province":"FL",
    "sg:tags":[
        "resurfacing",
        "laying",
        "refinishing",
        "floor"
    ],
    "wof:name":"Damon M Nelson Flooring",
    "wof:placetype":"venue"
},
  "geometry": {"coordinates":[-82.097433,29.184102],"type":"Point"}
}