{
  "type": "Feature",
  "properties": {
    "addr:full":"1741 W Beaver St Jacksonville FL 32209",
    "addr:housenumber":"1741",
    "addr:postcode":"32209",
    "addr:street":"W Beaver St",
    "iso:country":"US",
    "sg:address":"1741 W Beaver St",
    "sg:city":"Jacksonville",
    "sg:classifiers":[
        {
            "category":"Professional",
            "subcategory":"Employment Agencies",
            "type":"Services"
        }
    ],
    "sg:phone":"+1 904 633 7260",
    "sg:postcode":"32209",
    "sg:province":"FL",
    "sg:tags":[
        "help",
        "supply"
    ],
    "wof:name":"Adecco Employment Services",
    "wof:placetype":"venue"
},
  "geometry": {"coordinates":[-81.68792500000001,30.334725],"type":"Point"}
}