{
  "type": "Feature",
  "properties": {
    "addr:full":"4201 Deepwater Ln Tampa FL 33615",
    "addr:housenumber":"4201",
    "addr:postcode":"33615",
    "addr:street":"Deepwater Ln",
    "iso:country":"US",
    "sg:address":"4201 Deepwater Ln",
    "sg:city":"Tampa",
    "sg:classifiers":[
        {
            "category":"Real Estate",
            "subcategory":"Real Estate Operator",
            "type":"Services"
        }
    ],
    "sg:phone":"+1 813 887 3490",
    "sg:postcode":"33615",
    "sg:province":"FL",
    "sg:tags":[
        "building",
        "nonresidential"
    ],
    "wof:name":"Harbour Village Shopping",
    "wof:placetype":"venue"
},
  "geometry": {"coordinates":[-82.565,27.978679],"type":"Point"}
}