{
  "type": "Feature",
  "properties": {
    "addr:full":"401 SE 4th St Deerfield Beach FL 33441",
    "addr:housenumber":"401",
    "addr:postcode":"33441",
    "addr:street":"Se 4Th St",
    "iso:country":"US",
    "sg:address":"401 SE 4th St",
    "sg:city":"Deerfield Beach",
    "sg:classifiers":[
        {
            "category":"Building & Trades",
            "subcategory":"Landscaping Services",
            "type":"Services"
        }
    ],
    "sg:phone":"+1 954 427 7555",
    "sg:postcode":"33441",
    "sg:province":"FL",
    "wof:name":"Landscape People",
    "wof:placetype":"venue"
},
  "geometry": {"coordinates":[-80.096479,26.312395],"type":"Point"}
}