{
  "type": "Feature",
  "properties": {
    "iso:country":"US",
    "sg:address":"7507 Aloma Ave",
    "sg:city":"Winter Park",
    "sg:classifiers":[
        {
            "category":"Banks & Credit Unions",
            "subcategory":"Financial Services",
            "type":"Services"
        }
    ],
    "sg:phone":"+1 407 657 5050",
    "sg:postcode":"32792",
    "sg:province":"FL",
    "sg:tags":[
        "broker",
        "mortgage"
    ],
    "wof:name":"Expert Mortgage Corporation - CLOSED",
    "wof:placetype":"venue"
},
  "geometry": {"coordinates":[-81.28630099999999,28.6099],"type":"Point"}
}