{
  "type": "Feature",
  "properties": {
    "iso:country":"US",
    "sg:address":"6237 Presidential Ct Ste B",
    "sg:city":"Fort Myers",
    "sg:classifiers":[
        {
            "category":"Health Services",
            "subcategory":"Clinic",
            "type":"Services"
        }
    ],
    "sg:phone":"+1 239 481 6161",
    "sg:postcode":"33919",
    "sg:province":"FL",
    "sg:tags":[
        "counseling",
        "mental"
    ],
    "wof:name":"Bolhouse Lisa Lcsw Acsw",
    "wof:placetype":"venue"
},
  "geometry": {"coordinates":[-81.885902,26.559601],"type":"Point"}
}