{
  "type": "Feature",
  "properties": {
    "addr:full":"3903 Ondich Rd Apopka FL 32712",
    "addr:housenumber":"3903",
    "addr:postcode":"32712",
    "addr:street":"Ondich Rd",
    "iso:country":"US",
    "sg:address":"3903 Ondich Rd",
    "sg:city":"Apopka",
    "sg:classifiers":[
        {
            "category":"Farming",
            "subcategory":"Livestock Farm",
            "type":"Manufacturing & Wholesale Goods"
        }
    ],
    "sg:phone":"+1 407 814 7808",
    "sg:postcode":"32712",
    "sg:province":"FL",
    "sg:tags":[
        "equine"
    ],
    "wof:name":"Amber Lee Meridith",
    "wof:placetype":"venue"
},
  "geometry": {"coordinates":[-81.57431699999999,28.771208],"type":"Point"}
}