{
  "type": "Feature",
  "properties": {
    "addr:full":"7000 NW 32nd Ave Miami FL 33147",
    "addr:housenumber":"7000",
    "addr:postcode":"33147",
    "addr:street":"Nw 32Nd Ave",
    "iso:country":"US",
    "sg:address":"7000 NW 32nd Ave",
    "sg:city":"Miami",
    "sg:classifiers":[
        {
            "category":"Wholesale",
            "subcategory":"Groceries",
            "type":"Manufacturing & Wholesale Goods"
        }
    ],
    "sg:phone":"+1 305 696 0080",
    "sg:postcode":"33147",
    "sg:province":"FL",
    "sg:tags":[
        "general"
    ],
    "wof:name":"Marketing Management Inc",
    "wof:placetype":"venue"
},
  "geometry": {"coordinates":[-80.249607,25.837708],"type":"Point"}
}