{
  "type": "Feature",
  "properties": {
    "iso:country":"US",
    "sg:address":"14941 SW 82nd Ter",
    "sg:city":"Miami",
    "sg:classifiers":[
        {
            "category":"Wholesale",
            "subcategory":"Non-durable Goods",
            "type":"Manufacturing & Wholesale Goods"
        }
    ],
    "sg:phone":"+1 305 752 0896",
    "sg:postcode":"33193",
    "sg:province":"FL",
    "wof:name":"Daas Export Co",
    "wof:placetype":"venue"
},
  "geometry": {"coordinates":[-80.43379,25.689987],"type":"Point"}
}