{
  "type": "Feature",
  "properties": {
    "iso:country":"US",
    "sg:address":"504 NE 9th Ave",
    "sg:city":"Gainesville",
    "sg:classifiers":[
        {
            "category":"Health Services",
            "subcategory":"Health Practitioner",
            "type":"Services"
        }
    ],
    "sg:phone":"+1 352 213 0722",
    "sg:postcode":"32601",
    "sg:province":"FL",
    "sg:tags":[
        "therapist",
        "physical"
    ],
    "wof:name":"Julie Y Krim Rn Lmt",
    "wof:placetype":"venue"
},
  "geometry": {"coordinates":[-82.31994400000001,29.660064],"type":"Point"}
}