{
  "type": "Feature",
  "properties": {
    "iso:country":"US",
    "sg:address":"3850 NW 118th Ave",
    "sg:city":"Coral Springs",
    "sg:classifiers":[
        {
            "category":"Manufacturing",
            "subcategory":"Tools & Machinery",
            "type":"Manufacturing & Wholesale Goods"
        }
    ],
    "sg:phone":"+1 954 752 3090",
    "sg:postcode":"33065",
    "sg:province":"FL",
    "sg:tags":[
        "machine",
        "shop",
        "repair",
        "jobbing",
        "specializing"
    ],
    "sg:website":"www.bakerhillindustries.com",
    "wof:name":"Baker Hill Industries Inc",
    "wof:placetype":"venue"
},
  "geometry": {"coordinates":[-80.284001,26.277888],"type":"Point"}
}