{
  "type": "Feature",
  "properties": {
    "addr:full":"7205 NW 68th St Miami FL 33166",
    "addr:housenumber":"7205",
    "addr:postcode":"33166",
    "addr:street":"Nw 68Th St",
    "iso:country":"US",
    "sg:address":"7205 NW 68th St",
    "sg:city":"Miami",
    "sg:classifiers":[
        {
            "category":"Retail",
            "subcategory":"Auto Repair",
            "type":"Services"
        },
        {
            "category":"Wholesale",
            "subcategory":"Durable Goods & Equipment",
            "type":"Manufacturing & Wholesale Goods"
        }
    ],
    "sg:phone":"+1 305 888 8899",
    "sg:postcode":"33166",
    "sg:province":"FL",
    "sg:tags":[
        "exhaust",
        "exporter"
    ],
    "wof:name":"Midas Export USA Corp",
    "wof:placetype":"venue"
},
  "geometry": {"coordinates":[-80.31505900000001,25.83532],"type":"Point"}
}