{
  "type": "Feature",
  "properties": {
    "iso:country":"US",
    "sg:address":"6427 NW 18th Ave",
    "sg:city":"Miami",
    "sg:classifiers":[
        {
            "category":"Education",
            "subcategory":"School",
            "type":"Public Place"
        }
    ],
    "sg:phone":"+1 305 835 2842",
    "sg:postcode":"33147",
    "sg:province":"FL",
    "wof:name":"Choice Preparatory School",
    "wof:placetype":"venue"
},
  "geometry": {"coordinates":[-80.22684599999999,25.833676],"type":"Point"}
}