{
  "type": "Feature",
  "properties": {
    "iso:country":"US",
    "sg:address":"4206 W Osborne Ave",
    "sg:city":"Tampa",
    "sg:classifiers":[
        {
            "category":"Manufacturing",
            "subcategory":"Tools & Machinery",
            "type":"Manufacturing & Wholesale Goods"
        }
    ],
    "sg:phone":"+1 813 870 6653",
    "sg:postcode":"33614",
    "sg:province":"FL",
    "sg:tags":[
        "manufacture",
        "personal",
        "computer"
    ],
    "wof:name":"Corporate Technology",
    "wof:placetype":"venue"
},
  "geometry": {"coordinates":[-82.51564999999999,27.988996],"type":"Point"}
}