{
  "type": "Feature",
  "properties": {
    "iso:country":"US",
    "sg:address":"940 Harbor Island Dr",
    "sg:city":"Hollywood",
    "sg:classifiers":[
        {
            "category":"Real Estate",
            "subcategory":"Real Estate Agent",
            "type":"Services"
        }
    ],
    "sg:phone":"+1 954 454 5511",
    "sg:postcode":"33019",
    "sg:province":"FL",
    "wof:name":"Harbor Islands Realty Inc",
    "wof:placetype":"venue"
},
  "geometry": {"coordinates":[-80.125873,25.998581],"type":"Point"}
}