{
  "type": "Feature",
  "properties": {
    "addr:full":"1149 Milan Ave Coral Gables FL 33134",
    "addr:housenumber":"1149",
    "addr:postcode":"33134",
    "addr:street":"Milan Ave",
    "iso:country":"US",
    "sg:address":"1149 Milan Ave",
    "sg:city":"Coral Gables",
    "sg:classifiers":[
        {
            "category":"Professional",
            "subcategory":"Employment Agencies",
            "type":"Services"
        }
    ],
    "sg:phone":"+1 305 446 8232",
    "sg:postcode":"33134",
    "sg:province":"FL",
    "sg:tags":[
        "consultant",
        "search",
        "executive"
    ],
    "wof:name":"Griffin Von Fallois Inc",
    "wof:placetype":"venue"
},
  "geometry": {"coordinates":[-80.279295,25.757013],"type":"Point"}
}