{
  "type": "Feature",
  "properties": {
    "addr:full":"3924 W Bird St Tampa FL 33614",
    "addr:housenumber":"3924",
    "addr:postcode":"33614",
    "addr:street":"W Bird St",
    "iso:country":"US",
    "sg:address":"3924 W Bird St",
    "sg:city":"Tampa",
    "sg:classifiers":[
        {
            "category":"Wholesale",
            "subcategory":"Tobacco Products",
            "type":"Manufacturing & Wholesale Goods"
        }
    ],
    "sg:phone":"+1 813 806 9615",
    "sg:postcode":"33614",
    "sg:province":"FL",
    "sg:tags":[
        "distributor",
        "military",
        "food",
        "item"
    ],
    "wof:name":"Havana Tobacco Exporters",
    "wof:placetype":"venue"
},
  "geometry": {"coordinates":[-82.510368,28.022998],"type":"Point"}
}