{
  "type": "Feature",
  "properties": {
    "addr:full":"8201 Kona Ave Jacksonville FL 32211",
    "addr:housenumber":"8201",
    "addr:postcode":"32211",
    "addr:street":"Kona Ave",
    "iso:country":"US",
    "sg:address":"8201 Kona Ave",
    "sg:city":"Jacksonville",
    "sg:classifiers":[
        {
            "category":"Real Estate",
            "subcategory":"Real Estate Operator",
            "type":"Services"
        }
    ],
    "sg:phone":"+1 904 725 7566",
    "sg:postcode":"32211",
    "sg:province":"FL",
    "sg:tags":[
        "apartment",
        "complex"
    ],
    "wof:name":"Oakwood Villa APT",
    "wof:placetype":"venue"
},
  "geometry": {"coordinates":[-81.569784,30.322865],"type":"Point"}
}