{
  "type": "Feature",
  "properties": {
    "addr:full":"1013 Megan Lynn Ct Saint Cloud FL 34772",
    "addr:housenumber":"1013",
    "addr:postcode":"34772",
    "addr:street":"Megan Lynn Ct",
    "iso:country":"US",
    "sg:address":"1013 Megan Lynn Ct",
    "sg:city":"Saint Cloud",
    "sg:classifiers":[
        {
            "category":"Shopping",
            "subcategory":"Clothing, Apparel, & Fashions",
            "type":"Retail Goods"
        }
    ],
    "sg:phone":"+1 407 891 0297",
    "sg:postcode":"34772",
    "sg:province":"FL",
    "wof:name":"Plus Size Mommies To Be",
    "wof:placetype":"venue"
},
  "geometry": {"coordinates":[-81.27867999999999,28.213604],"type":"Point"}
}