{
  "type": "Feature",
  "properties": {
    "iso:country":"US",
    "sg:address":"4475 US Hwy 1 S",
    "sg:city":"St Augustine",
    "sg:classifiers":[
        {
            "category":"Shopping",
            "type":"Retail Goods"
        }
    ],
    "sg:phone":"+1 904 794 5044",
    "sg:postcode":"32086",
    "sg:province":"FL",
    "sg:tags":[
        "equipment",
        "telephone",
        "supply"
    ],
    "sg:website":"www.csib2b.com",
    "wof:name":"CSI Communications Solutions",
    "wof:placetype":"venue"
},
  "geometry": {"coordinates":[-81.321811,29.808456],"type":"Point"}
}