{
  "type": "Feature",
  "properties": {
    "addr:full":"6295 Lake Worth Rd Greenacres FL 33463",
    "addr:housenumber":"6295",
    "addr:postcode":"33463",
    "addr:street":"Lake Worth Rd",
    "iso:country":"US",
    "sg:address":"6295 Lake Worth Rd",
    "sg:city":"Greenacres",
    "sg:classifiers":[
        {
            "category":"Insurance",
            "subcategory":"Insurance Agent",
            "type":"Services"
        }
    ],
    "sg:phone":"+1 561 439 2655",
    "sg:postcode":"33463",
    "sg:province":"FL",
    "sg:tags":[
        "adjuster"
    ],
    "wof:name":"Diversified Professional",
    "wof:placetype":"venue"
},
  "geometry": {"coordinates":[-80.143233,26.619356],"type":"Point"}
}