{
  "type": "Feature",
  "properties": {
    "addr:full":"6805 33rd St E Sarasota FL 34243",
    "addr:housenumber":"6805",
    "addr:postcode":"34243",
    "addr:street":"33Rd St E",
    "iso:country":"US",
    "sg:address":"6805 33rd St E",
    "sg:city":"Sarasota",
    "sg:classifiers":[
        {
            "category":"Shopping",
            "subcategory":"Optical Goods",
            "type":"Retail Goods"
        }
    ],
    "sg:phone":"+1 941 751 1928",
    "sg:postcode":"34243",
    "sg:province":"FL",
    "sg:tags":[
        "contact",
        "lense"
    ],
    "wof:name":"Utica Laboratories",
    "wof:placetype":"venue"
},
  "geometry": {"coordinates":[-82.52187499999999,27.424871],"type":"Point"}
}