{
  "type": "Feature",
  "properties": {
    "addr:full":"4129 Laurel Oak Cir Tallahassee FL 32311",
    "addr:housenumber":"4129",
    "addr:postcode":"32311",
    "addr:street":"Laurel Oak Cir",
    "iso:country":"US",
    "sg:address":"4129 Laurel Oak Cir",
    "sg:city":"Tallahassee",
    "sg:classifiers":[
        {
            "category":"Professional",
            "subcategory":"Management & Consulting",
            "type":"Services"
        }
    ],
    "sg:phone":"+1 850 877 3664",
    "sg:postcode":"32311",
    "sg:province":"FL",
    "sg:tags":[
        "consultant"
    ],
    "wof:name":"Americana Media Consulting Inc",
    "wof:placetype":"venue"
},
  "geometry": {"coordinates":[-84.193896,30.425557],"type":"Point"}
}