{
  "type": "Feature",
  "properties": {
    "iso:country":"US",
    "sg:address":"460 E 23rd St Apt 317",
    "sg:city":"Hialeah",
    "sg:classifiers":[
        {
            "category":"Communications",
            "subcategory":"Television Station",
            "type":"Services"
        }
    ],
    "sg:phone":"+1 305 815 4130",
    "sg:postcode":"33013",
    "sg:province":"FL",
    "sg:tags":[
        "broadcast",
        "representative"
    ],
    "wof:name":"Henry Lopez",
    "wof:placetype":"venue"
},
  "geometry": {"coordinates":[-80.27288299999999,25.842914],"type":"Point"}
}