{
  "type": "Feature",
  "properties": {
    "iso:country":"US",
    "sg:address":"12125 SW 107th Ave",
    "sg:city":"Miami",
    "sg:classifiers":[
        {
            "category":"Education",
            "subcategory":"School",
            "type":"Public Place"
        }
    ],
    "sg:phone":"+1 305 255 7315",
    "sg:postcode":"33176",
    "sg:province":"FL",
    "sg:tags":[
        "high",
        "middle",
        "elementary"
    ],
    "wof:name":"St John Neumann Elementary School",
    "wof:placetype":"venue"
},
  "geometry": {"coordinates":[-80.367302,25.6565],"type":"Point"}
}