{
  "type": "Feature",
  "properties": {
    "iso:country":"US",
    "sg:address":"17902 Arbor Greene Dr",
    "sg:city":"Tampa",
    "sg:classifiers":[
        {
            "category":"Organizations",
            "subcategory":"Professional Association",
            "type":"Services"
        }
    ],
    "sg:phone":"+1 813 929 3918",
    "sg:postcode":"33647",
    "sg:province":"FL",
    "wof:name":"Esteban Celis",
    "wof:placetype":"venue"
},
  "geometry": {"coordinates":[-82.31876,28.132481],"type":"Point"}
}