{
  "type": "Feature",
  "properties": {
    "iso:country":"US",
    "sg:address":"3350 SW 148th Ave",
    "sg:city":"Hollywood",
    "sg:classifiers":[
        {
            "category":"Building & Trades",
            "subcategory":"Cleaning & Sanitation",
            "type":"Services"
        }
    ],
    "sg:phone":"+1 786 881 1868",
    "sg:postcode":"33027",
    "sg:province":"FL",
    "sg:tags":[
        "janitorial"
    ],
    "wof:name":"Exclusive Clg Svcs Staffing Co",
    "wof:placetype":"venue"
},
  "geometry": {"coordinates":[-80.34381,25.975973],"type":"Point"}
}