{
  "type": "Feature",
  "properties": {
    "addr:full":"4050 E Colonial Dr Orlando FL 32803",
    "addr:housenumber":"4050",
    "addr:postcode":"32803",
    "addr:street":"E Colonial Dr",
    "iso:country":"US",
    "sg:address":"4050 E Colonial Dr",
    "sg:city":"Orlando",
    "sg:classifiers":[
        {
            "category":"Fast Food",
            "type":"Food & Drink"
        },
        {
            "category":"Restaurant",
            "type":"Food & Drink"
        }
    ],
    "sg:phone":"+1 407 897 6040",
    "sg:postcode":"32803",
    "sg:province":"FL",
    "sg:tags":[
        "house",
        "american",
        "steak",
        "take",
        "barbecue"
    ],
    "sg:website":"http://www.longhornsteakhouse.com",
    "wof:name":"Longhorn Steakhouse",
    "wof:placetype":"venue"
},
  "geometry": {"coordinates":[-81.3349,28.553391],"type":"Point"}
}