{
  "type": "Feature",
  "properties": {
    "addr:full":"3456 Old Dixie Hwy Stuart FL 34994",
    "addr:housenumber":"3456",
    "addr:postcode":"34994",
    "addr:street":"Old Dixie Hwy",
    "iso:country":"US",
    "sg:address":"3456 Old Dixie Hwy",
    "sg:city":"Stuart",
    "sg:classifiers":[
        {
            "category":"Professional",
            "subcategory":"Art Services",
            "type":"Services"
        }
    ],
    "sg:phone":"+1 772 287 3972",
    "sg:postcode":"34994",
    "sg:province":"FL",
    "sg:tags":[
        "photographer"
    ],
    "wof:name":"Peter Gorman Photographer",
    "wof:placetype":"venue"
},
  "geometry": {"coordinates":[-80.21606199999999,27.162126],"type":"Point"}
}