{
  "type": "Feature",
  "properties": {
    "iso:country":"US",
    "sg:address":"5049 Encinitas Dr",
    "sg:city":"Delray Beach",
    "sg:classifiers":[
        {
            "category":"Manufacturing",
            "subcategory":"Furniture",
            "type":"Manufacturing & Wholesale Goods"
        }
    ],
    "sg:phone":"+1 561 638 8538",
    "sg:postcode":"33484",
    "sg:province":"FL",
    "sg:tags":[
        "household",
        "mfg"
    ],
    "wof:name":"Henry J Nite",
    "wof:placetype":"venue"
},
  "geometry": {"coordinates":[-80.123463,26.429855],"type":"Point"}
}