{
  "type": "Feature",
  "properties": {
    "iso:country":"US",
    "sg:address":"10200 Dylan St",
    "sg:city":"Orlando",
    "sg:classifiers":[
        {
            "category":"Home & Garden",
            "subcategory":"Furniture",
            "type":"Retail Goods"
        }
    ],
    "sg:phone":"+1 407 737 8383",
    "sg:postcode":"32825",
    "sg:province":"FL",
    "sg:tags":[
        "store"
    ],
    "wof:name":"Furnishings For Less",
    "wof:placetype":"venue"
},
  "geometry": {"coordinates":[-81.241051,28.54389],"type":"Point"}
}