{
  "type": "Feature",
  "properties": {
    "addr:full":"705 Boardwalk Dr Ponte Vedra Bch FL 32082",
    "addr:housenumber":"705",
    "addr:postcode":"32082",
    "addr:street":"Boardwalk Dr",
    "iso:country":"US",
    "sg:address":"705 Boardwalk Dr",
    "sg:city":"Ponte Vedra Bch",
    "sg:classifiers":[
        {
            "category":"Shopping",
            "subcategory":"Gifts & Souvenirs",
            "type":"Retail Goods"
        }
    ],
    "sg:phone":"+1 904 280 4468",
    "sg:postcode":"32082",
    "sg:province":"FL",
    "sg:tags":[
        "shop"
    ],
    "wof:name":"GIFTSPRONTO.COM",
    "wof:placetype":"venue"
},
  "geometry": {"coordinates":[-81.398222,30.250143],"type":"Point"}
}