{
  "type": "Feature",
  "properties": {
    "addr:full":"1821 S State Rd 7 Davie FL 33317",
    "addr:housenumber":"1821;7",
    "addr:postcode":"33317",
    "addr:street":"S State Rd",
    "iso:country":"US",
    "sg:address":"1821 S State Rd 7",
    "sg:city":"Davie",
    "sg:classifiers":[
        {
            "category":"Retail",
            "subcategory":"Auto Repair",
            "type":"Services"
        }
    ],
    "sg:phone":"+1 954 584 5440",
    "sg:postcode":"33317",
    "sg:province":"FL",
    "sg:tags":[
        "transmission"
    ],
    "wof:name":"AAMCO Transmissions",
    "wof:placetype":"venue"
},
  "geometry": {"coordinates":[-80.20139500000001,26.097975],"type":"Point"}
}