{
  "type": "Feature",
  "properties": {
    "addr:full":"2428 SW 18th Ct Okeechobee FL 34974",
    "addr:housenumber":"2428",
    "addr:postcode":"34974",
    "addr:street":"Sw 18Th Ct",
    "iso:country":"US",
    "sg:address":"2428 SW 18th Ct",
    "sg:city":"Okeechobee",
    "sg:classifiers":[
        {
            "category":"Manufacturing",
            "subcategory":"Metals",
            "type":"Manufacturing & Wholesale Goods"
        }
    ],
    "sg:phone":"+1 863 467 7003",
    "sg:postcode":"34974",
    "sg:province":"FL",
    "sg:tags":[
        "aluminum",
        "primary",
        "producer"
    ],
    "wof:name":"Hoss & Son Best Buy Aluminum",
    "wof:placetype":"venue"
},
  "geometry": {"coordinates":[-80.854556,27.226734],"type":"Point"}
}