{
  "type": "Feature",
  "properties": {
    "iso:country":"US",
    "sg:address":"615 Turner St",
    "sg:city":"Clearwater",
    "sg:classifiers":[
        {
            "category":"Professional",
            "subcategory":"Lawyer & Legal Services",
            "type":"Services"
        }
    ],
    "sg:phone":"+1 727 446 7505",
    "sg:postcode":"33756",
    "sg:province":"FL",
    "sg:tags":[
        "attorney"
    ],
    "wof:name":"Bjorn E Brunvand PA",
    "wof:placetype":"venue"
},
  "geometry": {"coordinates":[-82.797132,27.959471],"type":"Point"}
}