{
  "type": "Feature",
  "properties": {
    "iso:country":"US",
    "sg:address":"829 Floral St",
    "sg:city":"Tallahassee",
    "sg:classifiers":[
        {
            "category":"Building & Trades",
            "subcategory":"Electrical",
            "type":"Services"
        }
    ],
    "sg:phone":"+1 850 224 9626",
    "sg:postcode":"32310",
    "sg:province":"FL",
    "sg:tags":[
        "electrician",
        "contractor"
    ],
    "wof:name":"Competitive Electric",
    "wof:placetype":"venue"
},
  "geometry": {"coordinates":[-84.296631,30.42765],"type":"Point"}
}