{
  "type": "Feature",
  "properties": {
    "iso:country":"US",
    "sg:address":"2100 W 76th St",
    "sg:city":"Hialeah",
    "sg:classifiers":[
        {
            "category":"Building & Trades",
            "subcategory":"Construction",
            "type":"Services"
        }
    ],
    "sg:phone":"+1 305 823 7859",
    "sg:postcode":"33016",
    "sg:province":"FL",
    "sg:tags":[
        "contractor"
    ],
    "wof:name":"E L A Construction",
    "wof:placetype":"venue"
},
  "geometry": {"coordinates":[-80.326302,25.8915],"type":"Point"}
}