{
  "type": "Feature",
  "properties": {
    "iso:country":"US",
    "sg:address":"3541 SE Kubin Ave",
    "sg:city":"Stuart",
    "sg:classifiers":[
        {
            "category":"Building & Trades",
            "subcategory":"Landscaping Services",
            "type":"Services"
        }
    ],
    "sg:phone":"+1 772 286 9571",
    "sg:postcode":"34997",
    "sg:province":"FL",
    "sg:tags":[
        "landscape"
    ],
    "wof:name":"Robert Winters Landscaping",
    "wof:placetype":"venue"
},
  "geometry": {"coordinates":[-80.18785099999999,27.162246],"type":"Point"}
}