{
  "type": "Feature",
  "properties": {
    "iso:country":"US",
    "sg:address":"11870 Pines Blvd",
    "sg:city":"Hollywood",
    "sg:classifiers":[
        {
            "category":"Wholesale",
            "subcategory":"Plants",
            "type":"Manufacturing & Wholesale Goods"
        }
    ],
    "sg:phone":"+1 954 436 1667",
    "sg:postcode":"33026",
    "sg:province":"FL",
    "sg:tags":[
        "wholesaler",
        "floral",
        "retailer",
        "supply"
    ],
    "wof:name":"Floral Supply Mart Inc",
    "wof:placetype":"venue"
},
  "geometry": {"coordinates":[-80.306819,26.007766],"type":"Point"}
}