{
  "type": "Feature",
  "properties": {
    "iso:country":"US",
    "sg:address":"1946 NE 163rd St",
    "sg:city":"Miami",
    "sg:classifiers":[
        {
            "category":"Manufacturing",
            "subcategory":"Furniture",
            "type":"Manufacturing & Wholesale Goods"
        }
    ],
    "sg:phone":"+1 305 919 9430",
    "sg:postcode":"33162",
    "sg:province":"FL",
    "sg:tags":[
        "drapery",
        "mfg"
    ],
    "wof:name":"Kilaris US LLC",
    "wof:placetype":"venue"
},
  "geometry": {"coordinates":[-80.16072699999999,25.925937],"type":"Point"}
}