{
  "type": "Feature",
  "properties": {
    "addr:full":"4219 SW Co Rd 307 Bell FL 32619",
    "addr:housenumber":"4219",
    "addr:postcode":"32619",
    "addr:street":"Sw Co Rd 307",
    "iso:country":"US",
    "sg:address":"4219 SW Co Rd 307",
    "sg:city":"Bell",
    "sg:phone":"+1 352 463 2057",
    "sg:postcode":"32619",
    "sg:province":"FL",
    "sg:tags":[
        "farm",
        "field",
        "dairy",
        "crop"
    ],
    "wof:name":"Jones Farm",
    "wof:placetype":"venue"
},
  "geometry": {"coordinates":[-82.857264,29.675317],"type":"Point"}
}