{
  "type": "Feature",
  "properties": {
    "iso:country":"US",
    "sg:address":"1538 N Orange St",
    "sg:city":"Mount Dora",
    "sg:classifiers":[
        {
            "category":"Building & Trades",
            "subcategory":"Construction",
            "type":"Services"
        }
    ],
    "sg:phone":"+1 352 383 7289",
    "sg:postcode":"32757",
    "sg:province":"FL",
    "sg:tags":[
        "hanging",
        "contractor"
    ],
    "wof:name":"Enrique Zepeda Painting",
    "wof:placetype":"venue"
},
  "geometry": {"coordinates":[-81.635391,28.810248],"type":"Point"}
}