{
  "type": "Feature",
  "properties": {
    "iso:country":"US",
    "sg:address":"3128 Maltby Dr",
    "sg:city":"Deltona",
    "sg:classifiers":[
        {
            "category":"Freight",
            "type":"Transportation"
        }
    ],
    "sg:phone":"+1 407 328 4838",
    "sg:postcode":"32738",
    "sg:province":"FL",
    "wof:name":"Merca Transport Inc",
    "wof:placetype":"venue"
},
  "geometry": {"coordinates":[-81.177961,28.883819],"type":"Point"}
}