{
  "type": "Feature",
  "properties": {
    "addr:full":"6927 Nova Scotia Dr Port Richey FL 34668",
    "addr:housenumber":"6927",
    "addr:postcode":"34668",
    "addr:street":"Nova Scotia Dr",
    "iso:country":"US",
    "sg:address":"6927 Nova Scotia Dr",
    "sg:city":"Port Richey",
    "sg:classifiers":[
        {
            "category":"Travel",
            "subcategory":"Travel Agent",
            "type":"Entertainment"
        }
    ],
    "sg:phone":"+1 727 848 2299",
    "sg:postcode":"34668",
    "sg:province":"FL",
    "sg:tags":[
        "agency"
    ],
    "wof:name":"Savon Travel",
    "wof:placetype":"venue"
},
  "geometry": {"coordinates":[-82.69704299999999,28.284877],"type":"Point"}
}