{
  "type": "Feature",
  "properties": {
    "iso:country":"US",
    "sg:address":"736 Jenks Ave",
    "sg:city":"Panama City",
    "sg:classifiers":[
        {
            "category":"Recreation",
            "subcategory":"Arcade",
            "type":"Entertainment"
        }
    ],
    "sg:phone":"+1 850 763 5555",
    "sg:postcode":"32401",
    "sg:province":"FL",
    "wof:name":"Sherman Arcade LLC",
    "wof:placetype":"venue"
},
  "geometry": {"coordinates":[-85.66254000000001,30.161792],"type":"Point"}
}