{
  "type": "Feature",
  "properties": {
    "addr:full":"342 W Sugarland Hwy Clewiston FL 33440",
    "addr:housenumber":"342",
    "addr:postcode":"33440",
    "addr:street":"W Sugarland Hwy",
    "iso:country":"US",
    "sg:address":"342 W Sugarland Hwy",
    "sg:city":"Clewiston",
    "sg:classifiers":[
        {
            "category":"Food & Beverages",
            "subcategory":"Groceries & Convenience Stores",
            "type":"Retail Goods"
        }
    ],
    "sg:phone":"+1 863 983 8864",
    "sg:postcode":"33440",
    "sg:province":"FL",
    "wof:name":"Star Food Store",
    "wof:placetype":"venue"
},
  "geometry": {"coordinates":[-80.936145,26.754205],"type":"Point"}
}