{
  "type": "Feature",
  "properties": {
    "iso:country":"US",
    "sg:address":"6640 Collins Ave",
    "sg:city":"Miami Beach",
    "sg:classifiers":[
        {
            "category":"Fast Food",
            "type":"Food & Drink"
        },
        {
            "category":"Restaurant",
            "type":"Food & Drink"
        }
    ],
    "sg:phone":"+1 305 868 8282",
    "sg:postcode":"33141",
    "sg:province":"FL",
    "sg:tags":[
        "traditional",
        "burger",
        "american"
    ],
    "sg:website":"www.eatatmuncheez.com",
    "wof:name":"Muncheez",
    "wof:placetype":"venue"
},
  "geometry": {"coordinates":[-80.120491,25.85024],"type":"Point"}
}