{
  "type": "Feature",
  "properties": {
    "iso:country":"US",
    "sg:address":"6215 Schwab Dr",
    "sg:city":"Pensacola",
    "sg:classifiers":[
        {
            "category":"Shopping",
            "subcategory":"Florist",
            "type":"Retail Goods"
        }
    ],
    "sg:phone":"+1 850 478 1656",
    "sg:postcode":"32504",
    "sg:province":"FL",
    "wof:name":"Plant & Flower Boutique Inc",
    "wof:placetype":"venue"
},
  "geometry": {"coordinates":[-87.20066199999999,30.487141],"type":"Point"}
}