{
  "type": "Feature",
  "properties": {
    "iso:country":"US",
    "sg:address":"748 Bernice Ct",
    "sg:city":"Orlando",
    "sg:classifiers":[
        {
            "category":"Building & Trades",
            "subcategory":"Construction",
            "type":"Services"
        }
    ],
    "sg:phone":"+1 407 482 1008",
    "sg:postcode":"32825",
    "sg:province":"FL",
    "sg:tags":[
        "contractor",
        "finishing",
        "wood",
        "carpentry"
    ],
    "wof:name":"Door & Trim Works Inc",
    "wof:placetype":"venue"
},
  "geometry": {"coordinates":[-81.23555,28.553274],"type":"Point"}
}