{
  "type": "Feature",
  "properties": {
    "addr:full":"330 Glenn Pkwy Hollywood FL 33021",
    "addr:housenumber":"330",
    "addr:postcode":"33021",
    "addr:street":"Glenn Pkwy",
    "iso:country":"US",
    "sg:address":"330 Glenn Pkwy",
    "sg:city":"Hollywood",
    "sg:classifiers":[
        {
            "category":"Professional",
            "type":"Services"
        }
    ],
    "sg:phone":"+1 617 641 9777",
    "sg:postcode":"33021",
    "sg:province":"FL",
    "wof:name":"Nicholas and Alex Costopoulos",
    "wof:placetype":"venue"
},
  "geometry": {"coordinates":[-80.20237899999999,26.012741],"type":"Point"}
}