{
  "type": "Feature",
  "properties": {
    "iso:country":"US",
    "sg:address":"6625 Buddy Ln",
    "sg:city":"Port Richey",
    "sg:classifiers":[
        {
            "category":"Building & Trades",
            "subcategory":"Construction",
            "type":"Services"
        }
    ],
    "sg:phone":"+1 727 849 1044",
    "sg:postcode":"34668",
    "sg:province":"FL",
    "sg:tags":[
        "fire",
        "restoration",
        "damage"
    ],
    "wof:name":"Duraclean By Kirsch",
    "wof:placetype":"venue"
},
  "geometry": {"coordinates":[-82.70423,28.299129],"type":"Point"}
}