{
  "type": "Feature",
  "properties": {
    "addr:full":"415 Parque Dr Ormond Beach FL 32174",
    "addr:housenumber":"415",
    "addr:postcode":"32174",
    "addr:street":"Parque Dr",
    "iso:country":"US",
    "sg:address":"415 Parque Dr",
    "sg:city":"Ormond Beach",
    "sg:classifiers":[
        {
            "category":"Manufacturing",
            "subcategory":"Metals",
            "type":"Manufacturing & Wholesale Goods"
        },
        {
            "category":"Wholesale",
            "subcategory":"Non-durable Goods",
            "type":"Manufacturing & Wholesale Goods"
        }
    ],
    "sg:phone":"+1 386 677 6693",
    "sg:postcode":"32174",
    "sg:province":"FL",
    "sg:tags":[
        "art",
        "work",
        "sculpture",
        "ornamental"
    ],
    "sg:website":"www.devall.com",
    "wof:name":"Metal Sculpture By Devall",
    "wof:placetype":"venue"
},
  "geometry": {"coordinates":[-81.05898000000001,29.273738],"type":"Point"}
}