{
  "type": "Feature",
  "properties": {
    "iso:country":"US",
    "sg:address":"2631 McCormick Dr",
    "sg:city":"Clearwater",
    "sg:classifiers":[
        {
            "category":"Health Services",
            "subcategory":"Doctor",
            "type":"Services"
        }
    ],
    "sg:phone":"+1 727 723 0779",
    "sg:postcode":"33759",
    "sg:province":"FL",
    "sg:tags":[
        "physician",
        "surgeon"
    ],
    "wof:name":"Advanced Psychiatry",
    "wof:placetype":"venue"
},
  "geometry": {"coordinates":[-82.72825400000001,27.999178],"type":"Point"}
}