{
  "type": "Feature",
  "properties": {
    "addr:full":"2703 Middle St Orlando FL 32807",
    "addr:housenumber":"2703",
    "addr:postcode":"32807",
    "addr:street":"Middle St",
    "iso:country":"US",
    "sg:address":"2703 Middle St",
    "sg:city":"Orlando",
    "sg:classifiers":[
        {
            "category":"Building & Trades",
            "subcategory":"Cleaning & Sanitation",
            "type":"Services"
        }
    ],
    "sg:phone":"+1 407 673 2978",
    "sg:postcode":"32807",
    "sg:province":"FL",
    "sg:tags":[
        "janitor"
    ],
    "wof:name":"Your Choice Cleaning By Wilson",
    "wof:placetype":"venue"
},
  "geometry": {"coordinates":[-81.29157600000001,28.582293],"type":"Point"}
}