{
  "type": "Feature",
  "properties": {
    "iso:country":"US",
    "sg:address":"5200 Hoffner Ave",
    "sg:city":"Orlando",
    "sg:classifiers":[
        {
            "category":"Health Services",
            "subcategory":"Doctor",
            "type":"Services"
        }
    ],
    "sg:phone":"+1 407 856 1900",
    "sg:postcode":"32812",
    "sg:province":"FL",
    "sg:tags":[
        "physician",
        "surgeon"
    ],
    "wof:name":"Family Physicians Hoffner",
    "wof:placetype":"venue"
},
  "geometry": {"coordinates":[-81.31756,28.480591],"type":"Point"}
}