{
  "type": "Feature",
  "properties": {
    "addr:full":"129 Miracle Mile Miami FL 33134",
    "addr:housenumber":"129",
    "addr:postcode":"33134",
    "addr:street":"Miracle Mile",
    "iso:country":"US",
    "sg:address":"129 Miracle Mile",
    "sg:city":"Miami",
    "sg:classifiers":[
        {
            "category":"Professional",
            "type":"Services"
        },
        {
            "category":"Professional",
            "subcategory":"Detective & Security Services",
            "type":"Services"
        },
        {
            "category":"Shopping",
            "subcategory":"Computers & Home Electronics",
            "type":"Retail Goods"
        }
    ],
    "sg:phone":"+1 305 442 9999",
    "sg:postcode":"33134",
    "sg:province":"FL",
    "sg:tags":[
        "control",
        "monitoring",
        "system"
    ],
    "sg:website":"www.spystoresite.com/store/home....",
    "wof:name":"Spy Store",
    "wof:placetype":"venue"
},
  "geometry": {"coordinates":[-80.257896,25.749599],"type":"Point"}
}