{
  "type": "Feature",
  "properties": {
    "addr:full":"5244 Waterwood Run Bartow FL 33830",
    "addr:housenumber":"5244",
    "addr:postcode":"33830",
    "addr:street":"Waterwood Run",
    "iso:country":"US",
    "sg:address":"5244 Waterwood Run",
    "sg:city":"Bartow",
    "sg:classifiers":[
        {
            "category":"Wholesale",
            "subcategory":"Groceries",
            "type":"Manufacturing & Wholesale Goods"
        }
    ],
    "sg:phone":"+1 863 644 6932",
    "sg:postcode":"33830",
    "sg:province":"FL",
    "sg:tags":[
        "general"
    ],
    "wof:name":"Benton Food Brokers LLC",
    "wof:placetype":"venue"
},
  "geometry": {"coordinates":[-81.85900100000001,27.954321],"type":"Point"}
}