{
  "type": "Feature",
  "properties": {
    "iso:country":"US",
    "sg:address":"880 Manchester Ave",
    "sg:city":"Oviedo",
    "sg:classifiers":[
        {
            "category":"Professional",
            "subcategory":"Business Services",
            "type":"Services"
        }
    ],
    "sg:phone":"+1 407 359 8539",
    "sg:postcode":"32765",
    "sg:province":"FL",
    "wof:name":"Pjp Solutions Inc",
    "wof:placetype":"venue"
},
  "geometry": {"coordinates":[-81.21529,28.682948],"type":"Point"}
}