{
  "type": "Feature",
  "properties": {
    "iso:country":"US",
    "sg:address":"2600 Technology Dr",
    "sg:city":"Orlando",
    "sg:classifiers":[
        {
            "category":"Education",
            "subcategory":"College",
            "type":"Public Place"
        }
    ],
    "sg:phone":"+1 407 293 9911",
    "sg:postcode":"32804",
    "sg:province":"FL",
    "sg:tags":[
        "academic",
        "university",
        "school"
    ],
    "sg:website":"http://www.ccis.edu",
    "wof:name":"Columbia College",
    "wof:placetype":"venue"
},
  "geometry": {"coordinates":[-81.41201,28.555719],"type":"Point"}
}