{
  "type": "Feature",
  "properties": {
    "iso:country":"US",
    "sg:address":"10001 NW 50th St",
    "sg:city":"Fort Lauderdale",
    "sg:classifiers":[
        {
            "category":"Professional",
            "subcategory":"Computer Services",
            "type":"Services"
        }
    ],
    "sg:phone":"+1 954 572 0970",
    "sg:postcode":"33351",
    "sg:province":"FL",
    "sg:tags":[
        "consultant",
        "designer",
        "datum",
        "system"
    ],
    "wof:name":"Able Data Corp",
    "wof:placetype":"venue"
},
  "geometry": {"coordinates":[-80.28421899999999,26.186515],"type":"Point"}
}