{
  "type": "Feature",
  "properties": {
    "addr:full":"75 Fairway Dr Apt 1W Miami Springs FL 33166",
    "addr:housenumber":"75",
    "addr:postcode":"33166",
    "addr:street":"Fairway Dr Apt 1W",
    "iso:country":"US",
    "sg:address":"75 Fairway Dr Apt 1W",
    "sg:city":"Miami Springs",
    "sg:classifiers":[
        {
            "category":"Real Estate",
            "subcategory":"Real Estate Operator",
            "type":"Services"
        }
    ],
    "sg:phone":"+1 305 871 3746",
    "sg:postcode":"33166",
    "sg:province":"FL",
    "sg:tags":[
        "apartment"
    ],
    "wof:name":"Fairway Apartments",
    "wof:placetype":"venue"
},
  "geometry": {"coordinates":[-80.2817,25.808399],"type":"Point"}
}