{
  "type": "Feature",
  "properties": {
    "addr:full":"10001 NW 133rd St Hialeah FL 33018",
    "addr:housenumber":"10001",
    "addr:postcode":"33018",
    "addr:street":"Nw 133Rd St",
    "iso:country":"US",
    "sg:address":"10001 NW 133rd St",
    "sg:city":"Hialeah",
    "sg:classifiers":[
        {
            "category":"Organizations",
            "subcategory":"Religious Organization",
            "type":"Services"
        }
    ],
    "sg:phone":"+1 305 826 2524",
    "sg:postcode":"33018",
    "sg:province":"FL",
    "wof:name":"Jesus Sosa Segundo Sosa S",
    "wof:placetype":"venue"
},
  "geometry": {"coordinates":[-80.36159499999999,25.894298],"type":"Point"}
}