{
  "type": "Feature",
  "properties": {
    "iso:country":"US",
    "sg:address":"235 N Collier Blvd",
    "sg:city":"Marco Island",
    "sg:classifiers":[
        {
            "category":"Real Estate",
            "subcategory":"Real Estate Agent",
            "type":"Services"
        }
    ],
    "sg:phone":"+1 239 393 2586",
    "sg:postcode":"34145",
    "sg:province":"FL",
    "wof:name":"Downing Frye Realty",
    "wof:placetype":"venue"
},
  "geometry": {"coordinates":[-81.732542,25.942713],"type":"Point"}
}