{
  "type": "Feature",
  "properties": {
    "iso:country":"US",
    "sg:address":"2642 39th Ave N",
    "sg:city":"St Petersburg",
    "sg:classifiers":[
        {
            "category":"Building & Trades",
            "subcategory":"Cleaning & Sanitation",
            "type":"Services"
        }
    ],
    "sg:phone":"+1 727 522 4688",
    "sg:postcode":"33714",
    "sg:province":"FL",
    "sg:tags":[
        "janitor"
    ],
    "wof:name":"L & L Cleaning Svc",
    "wof:placetype":"venue"
},
  "geometry": {"coordinates":[-82.67097,27.807346],"type":"Point"}
}