{
  "type": "Feature",
  "properties": {
    "iso:country":"US",
    "sg:address":"2885 SW 69th Ct",
    "sg:city":"Miami",
    "sg:classifiers":[
        {
            "category":"Wholesale",
            "subcategory":"Machinery & Supplies",
            "type":"Manufacturing & Wholesale Goods"
        }
    ],
    "sg:phone":"+1 305 263 9595",
    "sg:postcode":"33155",
    "sg:province":"FL",
    "sg:tags":[
        "equipment",
        "mining"
    ],
    "wof:name":"Kanere Mining Inc",
    "wof:placetype":"venue"
},
  "geometry": {"coordinates":[-80.308319,25.743643],"type":"Point"}
}