{
  "type": "Feature",
  "properties": {
    "iso:country":"US",
    "sg:address":"340 Alhambra Cir",
    "sg:city":"Coral Gables",
    "sg:classifiers":[
        {
            "category":"Health Services",
            "subcategory":"Doctor",
            "type":"Services"
        }
    ],
    "sg:phone":"+1 305 445 7785",
    "sg:postcode":"33134",
    "sg:province":"FL",
    "sg:tags":[
        "dentist"
    ],
    "wof:name":"Lawrence R Imber DDS PA",
    "wof:placetype":"venue"
},
  "geometry": {"coordinates":[-80.262046,25.751818],"type":"Point"}
}