{
  "type": "Feature",
  "properties": {
    "iso:country":"US",
    "sg:address":"4400 Bayou Blvd Ste 36",
    "sg:city":"Pensacola",
    "sg:classifiers":[
        {
            "category":"Health Services",
            "subcategory":"Doctor",
            "type":"Services"
        },
        {
            "category":"Health Services",
            "subcategory":"Clinic",
            "type":"Services"
        }
    ],
    "sg:phone":"+1 954 840 8457",
    "sg:postcode":"32503",
    "sg:province":"FL",
    "sg:tags":[
        "physician",
        "gynecology",
        "endocrinology",
        "medical",
        "surgeons",
        "obstetrics",
        "surgeon",
        "metabolism",
        "diabetes"
    ],
    "sg:website":"http://national.citysearch.com/profile/external/44424207/pensacola_fl/new_leaders_in_fertility_and_endocrinology.html?publisher=yellowpages&reference_id=15&placement=ypwebsitemip",
    "wof:name":"New Leaders in Fertility and Endocrinology",
    "wof:placetype":"venue"
},
  "geometry": {"coordinates":[-87.20504800000001,30.46706],"type":"Point"}
}