{
  "type": "Feature",
  "properties": {
    "addr:full":"2545 S Adams St Tallahassee FL 32301",
    "addr:housenumber":"2545",
    "addr:postcode":"32301",
    "addr:street":"S Adams St",
    "iso:country":"US",
    "sg:address":"2545 S Adams St",
    "sg:city":"Tallahassee",
    "sg:classifiers":[
        {
            "category":"Building & Trades",
            "subcategory":"Equipment Rental",
            "type":"Services"
        }
    ],
    "sg:phone":"+1 850 878 2137",
    "sg:postcode":"32301",
    "sg:province":"FL",
    "sg:tags":[
        "own",
        "offer",
        "to",
        "rent",
        "which",
        "home",
        "electronics",
        "store"
    ],
    "wof:name":"Rent-A-Center",
    "wof:placetype":"venue"
},
  "geometry": {"coordinates":[-84.282319,30.417248],"type":"Point"}
}