{
  "type": "Feature",
  "properties": {
    "addr:full":"6542 N State Rd 7 Pompano Beach FL 33073",
    "addr:housenumber":"6542;7",
    "addr:postcode":"33073",
    "addr:street":"N State Rd",
    "iso:country":"US",
    "sg:address":"6542 N State Rd 7",
    "sg:city":"Pompano Beach",
    "sg:classifiers":[
        {
            "category":"Shopping",
            "type":"Retail Goods"
        },
        {
            "category":"Building & Trades",
            "subcategory":"Construction",
            "type":"Services"
        }
    ],
    "sg:phone":"+1 954 429 8866",
    "sg:postcode":"33073",
    "sg:province":"FL",
    "sg:tags":[
        "equipment",
        "industrial",
        "merchandise",
        "contractor"
    ],
    "wof:name":"Family Pool & Patio",
    "wof:placetype":"venue"
},
  "geometry": {"coordinates":[-80.20220500000001,26.308377],"type":"Point"}
}