{
  "type": "Feature",
  "properties": {
    "iso:country":"US",
    "sg:address":"2351 Drew St",
    "sg:city":"Clearwater",
    "sg:classifiers":[
        {
            "category":"Personal",
            "type":"Services"
        }
    ],
    "sg:phone":"+1 727 799 4933",
    "sg:postcode":"33765",
    "sg:province":"FL",
    "sg:tags":[
        "electrologist"
    ],
    "wof:name":"Absolute Answers",
    "wof:placetype":"venue"
},
  "geometry": {"coordinates":[-82.740876,27.967909],"type":"Point"}
}