{
  "type": "Feature",
  "properties": {
    "iso:country":"US",
    "sg:address":"2821 N Miami Ave",
    "sg:city":"North Miami Bch",
    "sg:classifiers":[
        {
            "category":"Professional",
            "subcategory":"Computer Services",
            "type":"Services"
        }
    ],
    "sg:phone":"+1 305 944 3542",
    "sg:postcode":"33127",
    "sg:province":"FL",
    "wof:name":"Network Edge Corp",
    "wof:placetype":"venue"
},
  "geometry": {"coordinates":[-80.19505700000001,25.803823],"type":"Point"}
}