{
  "type": "Feature",
  "properties": {
    "addr:full":"528 Wynnwood Dr Brandon FL 33511",
    "addr:housenumber":"528",
    "addr:postcode":"33511",
    "addr:street":"Wynnwood Dr",
    "iso:country":"US",
    "sg:address":"528 Wynnwood Dr",
    "sg:city":"Brandon",
    "sg:classifiers":[
        {
            "category":"Wholesale",
            "subcategory":"Stationery",
            "type":"Manufacturing & Wholesale Goods"
        }
    ],
    "sg:phone":"+1 813 651 0200",
    "sg:postcode":"33511",
    "sg:province":"FL",
    "sg:tags":[
        "supply"
    ],
    "wof:name":"J & S Copy Core Inc",
    "wof:placetype":"venue"
},
  "geometry": {"coordinates":[-82.27417,27.877323],"type":"Point"}
}