{
  "type": "Feature",
  "properties": {
    "iso:country":"US",
    "sg:address":"7 Enterprise Dr",
    "sg:city":"Bunnell",
    "sg:classifiers":[
        {
            "category":"Building & Trades",
            "subcategory":"Equipment Rental",
            "type":"Services"
        }
    ],
    "sg:phone":"+1 386 445 1001",
    "sg:postcode":"32110",
    "sg:province":"FL",
    "sg:tags":[
        "party",
        "supply"
    ],
    "wof:name":"Rentaland",
    "wof:placetype":"venue"
},
  "geometry": {"coordinates":[-81.26408000000001,29.52651],"type":"Point"}
}