{
  "type": "Feature",
  "properties": {
    "addr:full":"35200 S Dixie Hwy Homestead FL 33034",
    "addr:housenumber":"35200",
    "addr:postcode":"33034",
    "addr:street":"S Dixie Hwy",
    "iso:country":"US",
    "sg:address":"35200 S Dixie Hwy",
    "sg:city":"Homestead",
    "sg:classifiers":[
        {
            "category":"Travel",
            "subcategory":"Hotels & Motels",
            "type":"Entertainment"
        },
        {
            "category":"Retail",
            "subcategory":"Event Space",
            "type":"Services"
        }
    ],
    "sg:phone":"+1 800 345 8082",
    "sg:postcode":"33034",
    "sg:province":"FL",
    "sg:tags":[
        "facility",
        "banquet",
        "reception",
        "lodging",
        "corporate",
        "hall"
    ],
    "sg:website":"http://ad.doubleclick.net/clk;222816988;46581822;v?http://www.hiexpress.com/redirect?path=hd&brandCode=ex&hotelCode=fcffl&_PMID=99601036&cm_mmc=mdpr-_-yellowpages-_-ex-_-fcffl",
    "wof:name":"Holiday Inn Express Hotel & Suites Florida City-Gateway To Keys",
    "wof:placetype":"venue"
},
  "geometry": {"coordinates":[-80.475098,25.43914],"type":"Point"}
}