{
  "type": "Feature",
  "properties": {
    "iso:country":"US",
    "sg:address":"7037 Commonwealth Ave",
    "sg:city":"Jacksonville",
    "sg:classifiers":[
        {
            "category":"Wholesale",
            "subcategory":"Auto Parts",
            "type":"Manufacturing & Wholesale Goods"
        }
    ],
    "sg:phone":"+1 904 378 2741",
    "sg:postcode":"32220",
    "sg:province":"FL",
    "wof:name":"Elgitread USA LLC",
    "wof:placetype":"venue"
},
  "geometry": {"coordinates":[-81.764459,30.335776],"type":"Point"}
}