{
  "type": "Feature",
  "properties": {
    "iso:country":"US",
    "sg:address":"7500 SW 59th Pl",
    "sg:city":"South Miami",
    "sg:classifiers":[
        {
            "category":"Professional",
            "type":"Services"
        }
    ],
    "sg:phone":"+1 305 667 9631",
    "sg:postcode":"33143",
    "sg:province":"FL",
    "sg:tags":[
        "establishment"
    ],
    "wof:name":"Sunet Manor",
    "wof:placetype":"venue"
},
  "geometry": {"coordinates":[-80.290858,25.701451],"type":"Point"}
}