{
  "type": "Feature",
  "properties": {
    "iso:country":"US",
    "sg:address":"401 N Charleston Ave",
    "sg:city":"Fort Meade",
    "sg:classifiers":[
        {
            "category":"Restaurant",
            "type":"Food & Drink"
        }
    ],
    "sg:phone":"+1 863 494 3355",
    "sg:postcode":"33841",
    "sg:province":"FL",
    "sg:tags":[
        "parlor",
        "ice",
        "cream"
    ],
    "wof:name":"Paleteria-Flor-De-Michoacan",
    "wof:placetype":"venue"
},
  "geometry": {"coordinates":[-81.80146499999999,27.756504],"type":"Point"}
}