{
  "type": "Feature",
  "properties": {
    "iso:country":"US",
    "sg:address":"5449 San Marino Pl",
    "sg:city":"Orlando",
    "sg:classifiers":[
        {
            "category":"Building & Trades",
            "subcategory":"Construction",
            "type":"Services"
        }
    ],
    "sg:phone":"+1 407 243 6777",
    "sg:postcode":"32807",
    "sg:province":"FL",
    "sg:tags":[
        "drywall",
        "metal"
    ],
    "wof:name":"EJ Intr Extrior Wall Systems",
    "wof:placetype":"venue"
},
  "geometry": {"coordinates":[-81.316278,28.531261],"type":"Point"}
}