{
  "type": "Feature",
  "properties": {
    "iso:country":"US",
    "sg:address":"3345 W Gulf Dr",
    "sg:city":"Sanibel",
    "sg:classifiers":[
        {
            "category":"Travel",
            "subcategory":"Hotels & Motels",
            "type":"Entertainment"
        }
    ],
    "sg:phone":"+1 239 472 1541",
    "sg:postcode":"33957",
    "sg:province":"FL",
    "sg:tags":[
        "resort"
    ],
    "sg:website":"www.westwindinn.com",
    "wof:name":"West Wind Inn The",
    "wof:placetype":"venue"
},
  "geometry": {"coordinates":[-82.107071,26.429923],"type":"Point"}
}