{
  "type": "Feature",
  "properties": {
    "addr:full":"11670 Island Lakes Ln Boca Raton FL 33498",
    "addr:housenumber":"11670",
    "addr:postcode":"33498",
    "addr:street":"Island Lakes Ln",
    "iso:country":"US",
    "sg:address":"11670 Island Lakes Ln",
    "sg:city":"Boca Raton",
    "sg:classifiers":[
        {
            "category":"Professional",
            "subcategory":"Accounting & Tax Preparation",
            "type":"Services"
        }
    ],
    "sg:phone":"+1 561 488 5655",
    "sg:postcode":"33498",
    "sg:province":"FL",
    "sg:tags":[
        "billing"
    ],
    "wof:name":"Medical Billing Plus",
    "wof:placetype":"venue"
},
  "geometry": {"coordinates":[-80.231584,26.367956],"type":"Point"}
}