{
  "type": "Feature",
  "properties": {
    "addr:full":"2574 Muir Cir West Palm Beach FL 33414",
    "addr:housenumber":"2574",
    "addr:postcode":"33414",
    "addr:street":"Muir Cir",
    "iso:country":"US",
    "sg:address":"2574 Muir Cir",
    "sg:city":"West Palm Beach",
    "sg:classifiers":[
        {
            "category":"Real Estate",
            "subcategory":"Real Estate Agent",
            "type":"Services"
        }
    ],
    "sg:phone":"+1 561 793 4830",
    "sg:postcode":"33414",
    "sg:province":"FL",
    "sg:tags":[
        "broker"
    ],
    "wof:name":"Daisy Hill Realty",
    "wof:placetype":"venue"
},
  "geometry": {"coordinates":[-80.237449,26.643312],"type":"Point"}
}