{
  "type": "Feature",
  "properties": {
    "iso:country":"US",
    "sg:address":"776 E Fairbairn Dr",
    "sg:city":"Deltona",
    "sg:classifiers":[
        {
            "category":"Wholesale",
            "subcategory":"Electrical",
            "type":"Manufacturing & Wholesale Goods"
        }
    ],
    "sg:phone":"+1 386 860 6238",
    "sg:postcode":"32725",
    "sg:province":"FL",
    "sg:tags":[
        "generator"
    ],
    "wof:name":"Alturdyne Generators",
    "wof:placetype":"venue"
},
  "geometry": {"coordinates":[-81.271051,28.884594],"type":"Point"}
}