{
  "type": "Feature",
  "properties": {
    "addr:full":"91645 Overseas Hwy Tavernier FL 33070",
    "addr:housenumber":"91645",
    "addr:postcode":"33070",
    "addr:street":"Overseas Hwy",
    "iso:country":"US",
    "sg:address":"91645 Overseas Hwy",
    "sg:city":"Tavernier",
    "sg:classifiers":[
        {
            "category":"Professional",
            "subcategory":"Lawyer & Legal Services",
            "type":"Services"
        }
    ],
    "sg:phone":"+1 305 852 9292",
    "sg:postcode":"33070",
    "sg:province":"FL",
    "sg:tags":[
        "attorney"
    ],
    "wof:name":"Nicholas W Mulick Pa",
    "wof:placetype":"venue"
},
  "geometry": {"coordinates":[-80.51962399999999,25.006722],"type":"Point"}
}