{
  "type": "Feature",
  "properties": {
    "iso:country":"US",
    "sg:address":"38850 Old Sparkman St",
    "sg:city":"Dade City",
    "sg:classifiers":[
        {
            "category":"Real Estate",
            "subcategory":"Real Estate Operator",
            "type":"Services"
        }
    ],
    "sg:phone":"+1 352 521 5695",
    "sg:postcode":"33525",
    "sg:province":"FL",
    "sg:tags":[
        "building",
        "nonresidential"
    ],
    "wof:name":"Bluefield Properties LLC",
    "wof:placetype":"venue"
},
  "geometry": {"coordinates":[-82.173784,28.350448],"type":"Point"}
}