{
  "type": "Feature",
  "properties": {
    "addr:full":"7620 Lake Marsha Dr Orlando FL 32819",
    "addr:housenumber":"7620",
    "addr:postcode":"32819",
    "addr:street":"Lake Marsha Dr",
    "iso:country":"US",
    "sg:address":"7620 Lake Marsha Dr",
    "sg:city":"Orlando",
    "sg:classifiers":[
        {
            "category":"Professional",
            "subcategory":"Management & Consulting",
            "type":"Services"
        }
    ],
    "sg:phone":"+1 407 351 1834",
    "sg:postcode":"32819",
    "sg:province":"FL",
    "sg:tags":[
        "public",
        "relations"
    ],
    "wof:name":"Exclusive Design Promotions",
    "wof:placetype":"venue"
},
  "geometry": {"coordinates":[-81.486429,28.476498],"type":"Point"}
}