{
  "type": "Feature",
  "properties": {
    "iso:country":"US",
    "sg:address":"4536 Golfview Blvd",
    "sg:city":"Lehigh Acres",
    "sg:classifiers":[
        {
            "category":"Professional",
            "subcategory":"Art Services",
            "type":"Services"
        }
    ],
    "sg:phone":"+1 239 369 7024",
    "sg:postcode":"33973",
    "sg:province":"FL",
    "sg:tags":[
        "photographer"
    ],
    "wof:name":"St Jean Photography",
    "wof:placetype":"venue"
},
  "geometry": {"coordinates":[-81.722947,26.603284],"type":"Point"}
}