{
  "type": "Feature",
  "properties": {
    "iso:country":"US",
    "sg:address":"15900 SW 56th St",
    "sg:city":"Miami",
    "sg:classifiers":[
        {
            "category":"Education",
            "subcategory":"School",
            "type":"Public Place"
        }
    ],
    "sg:phone":"+1 305 408 2700",
    "sg:postcode":"33185",
    "sg:province":"FL",
    "wof:name":"Miami-Dade County Public Schools-158",
    "wof:placetype":"venue"
},
  "geometry": {"coordinates":[-80.44940200000001,25.7134],"type":"Point"}
}