{
  "type": "Feature",
  "properties": {
    "addr:full":"18001 Old Cutler Rd Ste 429 Palmetto Bay FL 33157",
    "addr:housenumber":"18001",
    "addr:postcode":"33157",
    "addr:street":"Old Cutler Rd Ste 429",
    "iso:country":"US",
    "sg:address":"18001 Old Cutler Rd Ste 429",
    "sg:city":"Palmetto Bay",
    "sg:classifiers":[
        {
            "category":"Professional",
            "subcategory":"Lawyer & Legal Services",
            "type":"Services"
        }
    ],
    "sg:phone":"+1 305 251 0997",
    "sg:postcode":"33157",
    "sg:province":"FL",
    "wof:name":"Usich James S Law Offices",
    "wof:placetype":"venue"
},
  "geometry": {"coordinates":[-80.31371900000001,25.603251],"type":"Point"}
}