{
  "type": "Feature",
  "properties": {
    "addr:full":"1616 18th Ave N Lake Worth FL 33460",
    "addr:housenumber":"1616",
    "addr:postcode":"33460",
    "addr:street":"18Th Ave N",
    "iso:country":"US",
    "sg:address":"1616 18th Ave N",
    "sg:city":"Lake Worth",
    "sg:classifiers":[
        {
            "category":"Shopping",
            "subcategory":"Catalog Store",
            "type":"Retail Goods"
        }
    ],
    "sg:phone":"+1 561 547 2464",
    "sg:postcode":"33460",
    "sg:province":"FL",
    "sg:tags":[
        "e"
    ],
    "wof:name":"E-Comm Enterprises Inc",
    "wof:placetype":"venue"
},
  "geometry": {"coordinates":[-80.0626,26.637225],"type":"Point"}
}