{
  "type": "Feature",
  "properties": {
    "iso:country":"US",
    "sg:address":"2809 Grand Ave",
    "sg:city":"Fort Myers",
    "sg:classifiers":[
        {
            "category":"Organizations",
            "subcategory":"Religious Organization",
            "type":"Services"
        }
    ],
    "sg:phone":"+1 239 334 1387",
    "sg:postcode":"33901",
    "sg:province":"FL",
    "wof:name":"Korean Community Church",
    "wof:placetype":"venue"
},
  "geometry": {"coordinates":[-81.870034,26.625992],"type":"Point"}
}