{
  "type": "Feature",
  "properties": {
    "iso:country":"US",
    "sg:address":"783 Shotgun Rd",
    "sg:city":"Sunrise",
    "sg:classifiers":[
        {
            "category":"Building & Trades",
            "subcategory":"Construction",
            "type":"Services"
        }
    ],
    "sg:phone":"+1 954 385 0244",
    "sg:postcode":"33326",
    "sg:province":"FL",
    "sg:tags":[
        "contractor"
    ],
    "wof:name":"Sunrise Commerce Ctr",
    "wof:placetype":"venue"
},
  "geometry": {"coordinates":[-80.34973100000001,26.110595],"type":"Point"}
}