{
  "type": "Feature",
  "properties": {
    "addr:full":"630 Monastery Rd Orange City FL 32763",
    "addr:housenumber":"630",
    "addr:postcode":"32763",
    "addr:street":"Monastery Rd",
    "iso:country":"US",
    "sg:address":"630 Monastery Rd",
    "sg:city":"Orange City",
    "sg:classifiers":[
        {
            "category":"Building & Trades",
            "subcategory":"Construction",
            "type":"Services"
        }
    ],
    "sg:phone":"+1 386 774 9634",
    "sg:postcode":"32763",
    "sg:province":"FL",
    "sg:tags":[
        "contractor"
    ],
    "wof:name":"Affordable Pressure Washing",
    "wof:placetype":"venue"
},
  "geometry": {"coordinates":[-81.27810700000001,28.943925],"type":"Point"}
}