{
  "type": "Feature",
  "properties": {
    "addr:full":"750 N Ocean Blvd Pompano Beach FL 33062",
    "addr:housenumber":"750",
    "addr:postcode":"33062",
    "addr:street":"N Ocean Blvd",
    "iso:country":"US",
    "sg:address":"750 N Ocean Blvd",
    "sg:city":"Pompano Beach",
    "sg:classifiers":[
        {
            "category":"Real Estate",
            "subcategory":"Real Estate Operator",
            "type":"Services"
        },
        {
            "category":"Organizations",
            "subcategory":"Community Association",
            "type":"Services"
        }
    ],
    "sg:phone":"+1 954 946 2549",
    "sg:postcode":"33062",
    "sg:province":"FL",
    "sg:tags":[
        "condominium"
    ],
    "wof:name":"Admiralty Towers",
    "wof:placetype":"venue"
},
  "geometry": {"coordinates":[-80.087532,26.244665],"type":"Point"}
}