{
  "type": "Feature",
  "properties": {
    "addr:full":"2219 King Alpines Ct Winter Park FL 32792",
    "addr:housenumber":"2219",
    "addr:postcode":"32792",
    "addr:street":"King Alpines Ct",
    "iso:country":"US",
    "sg:address":"2219 King Alpines Ct",
    "sg:city":"Winter Park",
    "sg:classifiers":[
        {
            "category":"Building & Trades",
            "subcategory":"Pest Control",
            "type":"Services"
        }
    ],
    "sg:phone":"+1 407 339 8854",
    "sg:postcode":"32792",
    "sg:province":"FL",
    "wof:name":"Darryl's Pest Control",
    "wof:placetype":"venue"
},
  "geometry": {"coordinates":[-81.316399,28.613199],"type":"Point"}
}