{
  "type": "Feature",
  "properties": {
    "addr:full":"4331 E Country Club Cir Fort Lauderdale FL 33317",
    "addr:housenumber":"4331",
    "addr:postcode":"33317",
    "addr:street":"E Country Club Cir",
    "iso:country":"US",
    "sg:address":"4331 E Country Club Cir",
    "sg:city":"Fort Lauderdale",
    "sg:classifiers":[
        {
            "category":"Retail",
            "subcategory":"Portrait Studio",
            "type":"Services"
        },
        {
            "category":"Professional",
            "subcategory":"Art Services",
            "type":"Services"
        }
    ],
    "sg:phone":"+1 954 325 2951",
    "sg:postcode":"33317",
    "sg:province":"FL",
    "sg:tags":[
        "photographer",
        "photography"
    ],
    "wof:name":"Charles Ferrara Visuals Inc",
    "wof:placetype":"venue"
},
  "geometry": {"coordinates":[-80.20739,26.117813],"type":"Point"}
}