{
  "type": "Feature",
  "properties": {
    "addr:full":"129 S Belcher Rd Clearwater FL 33765",
    "addr:housenumber":"129",
    "addr:postcode":"33765",
    "addr:street":"S Belcher Rd",
    "iso:country":"US",
    "sg:address":"129 S Belcher Rd",
    "sg:city":"Clearwater",
    "sg:classifiers":[
        {
            "category":"Education",
            "subcategory":"School",
            "type":"Public Place"
        }
    ],
    "sg:phone":"+1 727 797 1186",
    "sg:postcode":"33765",
    "sg:province":"FL",
    "sg:website":"www.skycrest.org",
    "wof:name":"Skycrest Christian School",
    "wof:placetype":"venue"
},
  "geometry": {"coordinates":[-82.74615,27.9654],"type":"Point"}
}