{
  "type": "Feature",
  "properties": {
    "iso:country":"US",
    "sg:address":"3165 W 16th Ave",
    "sg:city":"Hialeah",
    "sg:classifiers":[
        {
            "category":"Retail",
            "subcategory":"Laundry & Dry Cleaning",
            "type":"Services"
        },
        {
            "category":"Retail",
            "subcategory":"Repair Shop",
            "type":"Services"
        }
    ],
    "sg:phone":"+1 305 446 6361",
    "sg:postcode":"33012",
    "sg:province":"FL",
    "sg:tags":[
        "cleaner",
        "rug",
        "carpet"
    ],
    "wof:name":"Hilliard Rug Cleaners",
    "wof:placetype":"venue"
},
  "geometry": {"coordinates":[-80.314397,25.850055],"type":"Point"}
}