{
  "type": "Feature",
  "properties": {
    "addr:full":"210 Bonaventure Blvd Weston FL 33326",
    "addr:housenumber":"210",
    "addr:postcode":"33326",
    "addr:street":"Bonaventure Blvd",
    "iso:country":"US",
    "sg:address":"210 Bonaventure Blvd",
    "sg:city":"Weston",
    "sg:classifiers":[
        {
            "category":"Travel",
            "subcategory":"Hotels & Motels",
            "type":"Entertainment"
        }
    ],
    "sg:phone":"+1 954 385 5570",
    "sg:postcode":"33326",
    "sg:province":"FL",
    "sg:tags":[
        "resort"
    ],
    "wof:name":"Vacation Village-Bonaventure",
    "wof:placetype":"venue"
},
  "geometry": {"coordinates":[-80.37115,26.119497],"type":"Point"}
}