{
  "type": "Feature",
  "properties": {
    "iso:country":"US",
    "sg:address":"3532 Grand Blvd",
    "sg:city":"New Port Richey",
    "sg:classifiers":[
        {
            "category":"Retail",
            "subcategory":"Auto Repair",
            "type":"Services"
        }
    ],
    "sg:phone":"+1 727 934 1124",
    "sg:postcode":"34652",
    "sg:province":"FL",
    "sg:tags":[
        "repairing",
        "automobile"
    ],
    "wof:name":"S & S Svc Ctr",
    "wof:placetype":"venue"
},
  "geometry": {"coordinates":[-82.723416,28.214325],"type":"Point"}
}