{
  "type": "Feature",
  "properties": {
    "addr:full":"1342 US Hwy 92 Haines City FL 33844",
    "addr:housenumber":"1342",
    "addr:postcode":"33844",
    "addr:street":"Us Hwy 92",
    "iso:country":"US",
    "sg:address":"1342 US Hwy 92",
    "sg:city":"Haines City",
    "sg:classifiers":[
        {
            "category":"Freight",
            "type":"Transportation"
        }
    ],
    "sg:phone":"+1 863 419 9576",
    "sg:postcode":"33844",
    "sg:province":"FL",
    "sg:tags":[
        "commercial",
        "storage"
    ],
    "wof:name":"Store For Less",
    "wof:placetype":"venue"
},
  "geometry": {"coordinates":[-81.64751800000001,28.106677],"type":"Point"}
}