{
  "type": "Feature",
  "properties": {
    "addr:full":"3540 Victory Dr Milton FL 32571",
    "addr:housenumber":"3540",
    "addr:postcode":"32571",
    "addr:street":"Victory Dr",
    "iso:country":"US",
    "sg:address":"3540 Victory Dr",
    "sg:city":"Milton",
    "sg:classifiers":[
        {
            "category":"Wholesale",
            "subcategory":"Vending Machines",
            "type":"Manufacturing & Wholesale Goods"
        }
    ],
    "sg:phone":"+1 850 995 4329",
    "sg:postcode":"32571",
    "sg:province":"FL",
    "wof:name":"Variety Vending",
    "wof:placetype":"venue"
},
  "geometry": {"coordinates":[-87.174266,30.643147],"type":"Point"}
}