{
  "type": "Feature",
  "properties": {
    "iso:country":"US",
    "sg:address":"2374 Rusty Ln",
    "sg:city":"Gulf Breeze",
    "sg:classifiers":[
        {
            "category":"Building & Trades",
            "subcategory":"Construction",
            "type":"Services"
        }
    ],
    "sg:phone":"+1 850 916 4243",
    "sg:postcode":"32563",
    "sg:province":"FL",
    "sg:tags":[
        "repairing",
        "remodeling",
        "contractor"
    ],
    "wof:name":"Anu Labor Force Inc",
    "wof:placetype":"venue"
},
  "geometry": {"coordinates":[-86.97347000000001,30.421879],"type":"Point"}
}