{
  "type": "Feature",
  "properties": {
    "iso:country":"US",
    "sg:address":"6010 Yucatan Dr",
    "sg:city":"Orlando",
    "sg:classifiers":[
        {
            "category":"Building & Trades",
            "subcategory":"Construction",
            "type":"Services"
        }
    ],
    "sg:phone":"+1 407 277 3198",
    "sg:postcode":"32807",
    "sg:province":"FL",
    "sg:tags":[
        "house"
    ],
    "wof:name":"Don Muzzey Remodeling",
    "wof:placetype":"venue"
},
  "geometry": {"coordinates":[-81.30336699999999,28.542842],"type":"Point"}
}