{
  "type": "Feature",
  "properties": {
    "iso:country":"US",
    "sg:address":"6419 SW 40th St",
    "sg:city":"Miami",
    "sg:classifiers":[
        {
            "category":"Insurance",
            "subcategory":"Hazard Insurance",
            "type":"Services"
        }
    ],
    "sg:phone":"+1 305 663 3312",
    "sg:postcode":"33155",
    "sg:province":"FL",
    "sg:tags":[
        "bond"
    ],
    "wof:name":"Harold Valdes Bail Bonds",
    "wof:placetype":"venue"
},
  "geometry": {"coordinates":[-80.29946099999999,25.733614],"type":"Point"}
}