{
  "type": "Feature",
  "properties": {
    "addr:full":"10264 Gulf Blvd Treasure Island FL 33706",
    "addr:housenumber":"10264",
    "addr:postcode":"33706",
    "addr:street":"Gulf Blvd",
    "iso:country":"US",
    "sg:address":"10264 Gulf Blvd",
    "sg:city":"Treasure Island",
    "sg:classifiers":[
        {
            "category":"Travel",
            "subcategory":"Hotels & Motels",
            "type":"Entertainment"
        }
    ],
    "sg:phone":"+1 727 360 9256",
    "sg:postcode":"33706",
    "sg:province":"FL",
    "wof:name":"Suncoast Motel",
    "wof:placetype":"venue"
},
  "geometry": {"coordinates":[-82.767066,27.763522],"type":"Point"}
}