{
  "type": "Feature",
  "properties": {
    "iso:country":"US",
    "sg:address":"16909 Gulf Blvd",
    "sg:city":"Saint Petersburg",
    "sg:classifiers":[
        {
            "category":"Restaurant",
            "type":"Food & Drink"
        }
    ],
    "sg:phone":"+1 727 392 4117",
    "sg:postcode":"33708",
    "sg:province":"FL",
    "sg:tags":[
        "eating"
    ],
    "wof:name":"Frog Pond Restaurant",
    "wof:placetype":"venue"
},
  "geometry": {"coordinates":[-82.82327100000001,27.818296],"type":"Point"}
}