{
  "type": "Feature",
  "properties": {
    "iso:country":"US",
    "sg:address":"100 SW 52nd Ave",
    "sg:city":"Ocala",
    "sg:classifiers":[
        {
            "category":"Wholesale",
            "subcategory":"Durable Goods & Equipment",
            "type":"Manufacturing & Wholesale Goods"
        }
    ],
    "sg:phone":"+1 352 690 7328",
    "sg:postcode":"34474",
    "sg:province":"FL",
    "sg:tags":[
        "representative",
        "manufacturer"
    ],
    "wof:name":"New Lenox Industries Inc",
    "wof:placetype":"venue"
},
  "geometry": {"coordinates":[-82.206253,29.186163],"type":"Point"}
}