{
  "type": "Feature",
  "properties": {
    "addr:full":"3913 Lakeside Reserve Ln Orlando FL 32810",
    "addr:housenumber":"3913",
    "addr:postcode":"32810",
    "addr:street":"Lakeside Reserve Ln",
    "iso:country":"US",
    "sg:address":"3913 Lakeside Reserve Ln",
    "sg:city":"Orlando",
    "sg:classifiers":[
        {
            "category":"Building & Trades",
            "subcategory":"Construction",
            "type":"Services"
        }
    ],
    "sg:phone":"+1 407 291 7487",
    "sg:postcode":"32810",
    "sg:province":"FL",
    "sg:tags":[
        "house"
    ],
    "wof:name":"Mercedes Hmes At Lkside Rserve",
    "wof:placetype":"venue"
},
  "geometry": {"coordinates":[-81.42957800000001,28.62801],"type":"Point"}
}