{
  "type": "Feature",
  "properties": {
    "addr:full":"104 E Lakeview Ave Eustis FL 32726",
    "addr:housenumber":"104",
    "addr:postcode":"32726",
    "addr:street":"E Lakeview Ave",
    "iso:country":"US",
    "sg:address":"104 E Lakeview Ave",
    "sg:city":"Eustis",
    "sg:classifiers":[
        {
            "category":"Personal",
            "subcategory":"Beauty Salon",
            "type":"Services"
        }
    ],
    "sg:phone":"+1 352 357 1139",
    "sg:postcode":"32726",
    "sg:province":"FL",
    "wof:name":"Carmen's Beauty Salon",
    "wof:placetype":"venue"
},
  "geometry": {"coordinates":[-81.68449,28.84187],"type":"Point"}
}