{
  "type": "Feature",
  "properties": {
    "iso:country":"US",
    "sg:address":"3907 W South Ave",
    "sg:city":"Tampa",
    "sg:classifiers":[
        {
            "category":"Manufacturing",
            "subcategory":"Metals",
            "type":"Manufacturing & Wholesale Goods"
        }
    ],
    "sg:phone":"+1 813 876 6102",
    "sg:postcode":"33614",
    "sg:province":"FL",
    "sg:tags":[
        "metalwork",
        "sheet",
        "mfg"
    ],
    "wof:name":"Sunshine Aluminum Products",
    "wof:placetype":"venue"
},
  "geometry": {"coordinates":[-82.506466,27.991362],"type":"Point"}
}