{
  "type": "Feature",
  "properties": {
    "iso:country":"US",
    "sg:address":"1453 20th St",
    "sg:city":"Vero Beach",
    "sg:classifiers":[
        {
            "category":"Bars & Pubs",
            "type":"Food & Drink"
        }
    ],
    "sg:phone":"+1 772 567 2311",
    "sg:postcode":"32960",
    "sg:province":"FL",
    "wof:name":"Palm Tree Inn",
    "wof:placetype":"venue"
},
  "geometry": {"coordinates":[-80.400249,27.638559],"type":"Point"}
}