{
  "type": "Feature",
  "properties": {
    "addr:full":"1100 S Patrick Dr Satellite Beach FL 32937",
    "addr:housenumber":"1100",
    "addr:postcode":"32937",
    "addr:street":"S Patrick Dr",
    "iso:country":"US",
    "sg:address":"1100 S Patrick Dr",
    "sg:city":"Satellite Beach",
    "sg:classifiers":[
        {
            "category":"Shopping",
            "subcategory":"Bicycles & Sporting Goods",
            "type":"Retail Goods"
        }
    ],
    "sg:phone":"+1 321 773 6611",
    "sg:postcode":"32937",
    "sg:province":"FL",
    "sg:tags":[
        "station",
        "gasoline"
    ],
    "wof:name":"South Patrick Shamrock",
    "wof:placetype":"venue"
},
  "geometry": {"coordinates":[-80.60611,28.182501],"type":"Point"}
}