{
  "type": "Feature",
  "properties": {
    "iso:country":"US",
    "sg:address":"11913 NW 99th Ave",
    "sg:city":"Hialeah",
    "sg:classifiers":[
        {
            "category":"Building & Trades",
            "subcategory":"Construction",
            "type":"Services"
        }
    ],
    "sg:phone":"+1 305 362 6632",
    "sg:postcode":"33018",
    "sg:province":"FL",
    "wof:name":"Bobcat of Metro Dade Inc",
    "wof:placetype":"venue"
},
  "geometry": {"coordinates":[-80.35941800000001,25.881846],"type":"Point"}
}