{
  "type": "Feature",
  "properties": {
    "iso:country":"US",
    "sg:address":"310 Oak St",
    "sg:city":"Jacksonville",
    "sg:classifiers":[
        {
            "category":"Retail",
            "subcategory":"Auto Repair",
            "type":"Services"
        }
    ],
    "sg:phone":"+1 904 353 5090",
    "sg:postcode":"32204",
    "sg:province":"FL",
    "sg:tags":[
        "general"
    ],
    "wof:name":"Eight Ball Garage",
    "wof:placetype":"venue"
},
  "geometry": {"coordinates":[-81.675641,30.322816],"type":"Point"}
}