{
  "type": "Feature",
  "properties": {
    "addr:full":"8090 Cleary Blvd Plantation FL 33324",
    "addr:housenumber":"8090",
    "addr:postcode":"33324",
    "addr:street":"Cleary Blvd",
    "iso:country":"US",
    "sg:address":"8090 Cleary Blvd",
    "sg:city":"Plantation",
    "sg:classifiers":[
        {
            "category":"Building & Trades",
            "subcategory":"Cleaning & Sanitation",
            "type":"Services"
        }
    ],
    "sg:phone":"+1 954 474 8880",
    "sg:postcode":"33324",
    "sg:province":"FL",
    "sg:tags":[
        "janitor"
    ],
    "wof:name":"Clean Sweep Cleaning Svc LLC",
    "wof:placetype":"venue"
},
  "geometry": {"coordinates":[-80.258163,26.133892],"type":"Point"}
}