{
  "type": "Feature",
  "properties": {
    "addr:full":"17805 Hanna Rd Lutz FL 33549",
    "addr:housenumber":"17805",
    "addr:postcode":"33549",
    "addr:street":"Hanna Rd",
    "iso:country":"US",
    "sg:address":"17805 Hanna Rd",
    "sg:city":"Lutz",
    "sg:classifiers":[
        {
            "category":"Building & Trades",
            "subcategory":"Construction",
            "type":"Services"
        }
    ],
    "sg:phone":"+1 813 949 1260",
    "sg:postcode":"33549",
    "sg:province":"FL",
    "sg:tags":[
        "painting",
        "contractor"
    ],
    "wof:name":"Whiteside Chrles L Pntg Svc In",
    "wof:placetype":"venue"
},
  "geometry": {"coordinates":[-82.442745,28.130852],"type":"Point"}
}