{
  "type": "Feature",
  "properties": {
    "iso:country":"US",
    "sg:address":"11961 US Hwy 441",
    "sg:city":"Okeechobee",
    "sg:classifiers":[
        {
            "category":"Professional",
            "subcategory":"Management & Consulting",
            "type":"Services"
        }
    ],
    "sg:phone":"+1 863 763 2739",
    "sg:postcode":"34974",
    "sg:province":"FL",
    "wof:name":"Burke & Associates Inc",
    "wof:placetype":"venue"
},
  "geometry": {"coordinates":[-80.705716,27.156423],"type":"Point"}
}