{
  "type": "Feature",
  "properties": {
    "addr:full":"2527 W Tennessee St Tallahassee FL 32304",
    "addr:housenumber":"2527",
    "addr:postcode":"32304",
    "addr:street":"W Tennessee St",
    "iso:country":"US",
    "sg:address":"2527 W Tennessee St",
    "sg:city":"Tallahassee",
    "sg:classifiers":[
        {
            "category":"Autos & Motor Vehicles",
            "subcategory":"Automobile Sales",
            "type":"Retail Goods"
        }
    ],
    "sg:phone":"+1 850 575 2444",
    "sg:postcode":"32304",
    "sg:province":"FL",
    "sg:tags":[
        "car",
        "dealer"
    ],
    "wof:name":"Drive It Away Auto Sales West",
    "wof:placetype":"venue"
},
  "geometry": {"coordinates":[-84.332127,30.450062],"type":"Point"}
}