{
  "type": "Feature",
  "properties": {
    "addr:full":"525 State Hwy 16 St Augustine FL 32084",
    "addr:housenumber":"525",
    "addr:postcode":"32084",
    "addr:street":"State Hwy 16 St",
    "iso:country":"US",
    "sg:address":"525 State Hwy 16",
    "sg:city":"St Augustine",
    "sg:classifiers":[
        {
            "category":"Personal",
            "subcategory":"Beauty Salon",
            "type":"Services"
        }
    ],
    "sg:phone":"+1 904 829 5454",
    "sg:postcode":"32084",
    "sg:province":"FL",
    "sg:tags":[
        "manicuring"
    ],
    "wof:name":"L A Nail",
    "wof:placetype":"venue"
},
  "geometry": {"coordinates":[-81.348697,29.916425],"type":"Point"}
}