{
  "type": "Feature",
  "properties": {
    "addr:full":"935 S Howard Ave Tampa FL 33606",
    "addr:housenumber":"935",
    "addr:postcode":"33606",
    "addr:street":"S Howard Ave",
    "iso:country":"US",
    "sg:address":"935 S Howard Ave",
    "sg:city":"Tampa",
    "sg:classifiers":[
        {
            "category":"Shopping",
            "subcategory":"Clothing, Apparel, & Fashions",
            "type":"Retail Goods"
        }
    ],
    "sg:phone":"+1 813 254 8080",
    "sg:postcode":"33606",
    "sg:province":"FL",
    "sg:tags":[
        "item",
        "boutique"
    ],
    "wof:name":"Eccentricities",
    "wof:placetype":"venue"
},
  "geometry": {"coordinates":[-82.483131,27.933976],"type":"Point"}
}