{
  "type": "Feature",
  "properties": {
    "iso:country":"US",
    "sg:address":"5126 Tarragona Dr",
    "sg:city":"Orlando",
    "sg:classifiers":[
        {
            "category":"Banks & Credit Unions",
            "subcategory":"Bank",
            "type":"Services"
        }
    ],
    "sg:phone":"+1 407 251 1259",
    "sg:postcode":"32837",
    "sg:province":"FL",
    "sg:tags":[
        "loan",
        "real estate"
    ],
    "wof:name":"B C Mortgage",
    "wof:placetype":"venue"
},
  "geometry": {"coordinates":[-81.46273100000001,28.366145],"type":"Point"}
}