{
  "type": "Feature",
  "properties": {
    "iso:country":"US",
    "sg:address":"669 SW 16th St",
    "sg:city":"Belle Glade",
    "sg:classifiers":[
        {
            "category":"Organizations",
            "subcategory":"Religious Organization",
            "type":"Services"
        }
    ],
    "sg:phone":"+1 561 996 0921",
    "sg:postcode":"33430",
    "sg:province":"FL",
    "sg:tags":[
        "church"
    ],
    "wof:name":"Jehovah's Witnesses",
    "wof:placetype":"venue"
},
  "geometry": {"coordinates":[-80.686194,26.678611],"type":"Point"}
}