{
  "type": "Feature",
  "properties": {
    "addr:full":"1258 NE 13th Ave Okeechobee FL 34972",
    "addr:housenumber":"1258",
    "addr:postcode":"34972",
    "addr:street":"Ne 13Th Ave",
    "iso:country":"US",
    "sg:address":"1258 NE 13th Ave",
    "sg:city":"Okeechobee",
    "sg:classifiers":[
        {
            "category":"Organizations",
            "subcategory":"Religious Organization",
            "type":"Services"
        }
    ],
    "sg:phone":"+1 863 763 6512",
    "sg:postcode":"34972",
    "sg:province":"FL",
    "sg:tags":[
        "churches-baptist",
        "church"
    ],
    "wof:name":"Bethel Baptist Church",
    "wof:placetype":"venue"
},
  "geometry": {"coordinates":[-80.815552,27.254225],"type":"Point"}
}