{
  "type": "Feature",
  "properties": {
    "iso:country":"US",
    "sg:address":"7307 Sandscove Ct Ste 3",
    "sg:city":"Winter Park",
    "sg:classifiers":[
        {
            "category":"Arts & Performance",
            "subcategory":"Arts Center",
            "type":"Entertainment"
        },
        {
            "category":"Sports & Exercise",
            "subcategory":"Gym",
            "type":"Entertainment"
        }
    ],
    "sg:phone":"+1 407 679 6620",
    "sg:postcode":"32792",
    "sg:province":"FL",
    "sg:tags":[
        "performing"
    ],
    "wof:name":"University Cats",
    "wof:placetype":"venue"
},
  "geometry": {"coordinates":[-81.289299,28.605801],"type":"Point"}
}