{
  "type": "Feature",
  "properties": {
    "iso:country":"US",
    "sg:address":"5514 Flaxman St",
    "sg:city":"Pensacola",
    "sg:classifiers":[
        {
            "category":"Building & Trades",
            "subcategory":"Landscaping Services",
            "type":"Services"
        }
    ],
    "sg:phone":"+1 850 453 5087",
    "sg:postcode":"32506",
    "sg:province":"FL",
    "sg:tags":[
        "landscape",
        "contractor"
    ],
    "wof:name":"Randall Smith Landscaping Svc",
    "wof:placetype":"venue"
},
  "geometry": {"coordinates":[-87.287841,30.427913],"type":"Point"}
}