{
  "type": "Feature",
  "properties": {
    "addr:full":"3760 NW 83rd St Ste 1 Gainesville FL 32606",
    "addr:housenumber":"3760",
    "addr:postcode":"32606",
    "addr:street":"Nw 83Rd St Ste 1",
    "iso:country":"US",
    "sg:address":"3760 NW 83rd St Ste 1",
    "sg:city":"Gainesville",
    "sg:classifiers":[
        {
            "category":"Real Estate",
            "subcategory":"Developer",
            "type":"Services"
        }
    ],
    "sg:phone":"+1 352 336 3996",
    "sg:postcode":"32606",
    "sg:province":"FL",
    "wof:name":"Hodor, Howard Real Estate",
    "wof:placetype":"venue"
},
  "geometry": {"coordinates":[-82.43025900000001,29.687417],"type":"Point"}
}