{
  "type": "Feature",
  "properties": {
    "addr:full":"5250 Sunbeam Rd Jacksonville FL 32257",
    "addr:postcode":"5250;32257",
    "addr:street":"Sunbeam Rd",
    "iso:country":"US",
    "sg:address":"5250 Sunbeam Rd",
    "sg:city":"Jacksonville",
    "sg:classifiers":[
        {
            "category":"Wholesale",
            "subcategory":"Home Furnishings",
            "type":"Manufacturing & Wholesale Goods"
        }
    ],
    "sg:phone":"+1 904 288 5688",
    "sg:postcode":"32257",
    "sg:province":"FL",
    "sg:tags":[
        "rug",
        "carpet"
    ],
    "wof:name":"Prosource Of Jacksonville",
    "wof:placetype":"venue"
},
  "geometry": {"coordinates":[-81.577556,30.206102],"type":"Point"}
}