{
  "type": "Feature",
  "properties": {
    "iso:country":"US",
    "sg:address":"1716 Wellington Ave",
    "sg:city":"Lehigh Acres",
    "sg:classifiers":[
        {
            "category":"Building & Trades",
            "subcategory":"Construction",
            "type":"Services"
        }
    ],
    "sg:phone":"+1 239 369 6678",
    "sg:postcode":"33972",
    "sg:province":"FL",
    "sg:tags":[
        "house"
    ],
    "wof:name":"Alex Gran Site Preparation",
    "wof:placetype":"venue"
},
  "geometry": {"coordinates":[-81.58201,26.664928],"type":"Point"}
}