{
  "type": "Feature",
  "properties": {
    "iso:country":"US",
    "sg:address":"3111 Fortune Way",
    "sg:city":"Wellington",
    "sg:classifiers":[
        {
            "category":"Autos & Motor Vehicles",
            "subcategory":"Automobile Sales",
            "type":"Retail Goods"
        }
    ],
    "sg:phone":"+1 561 333 8033",
    "sg:postcode":"33414",
    "sg:province":"FL",
    "sg:tags":[
        "car",
        "dealer"
    ],
    "wof:name":"Americarr",
    "wof:placetype":"venue"
},
  "geometry": {"coordinates":[-80.22706700000001,26.635562],"type":"Point"}
}