{
  "type": "Feature",
  "properties": {
    "addr:full":"275 Plaza Oval Casselberry FL 32707",
    "addr:housenumber":"275",
    "addr:postcode":"32707",
    "addr:street":"Plaza Oval",
    "iso:country":"US",
    "sg:address":"275 Plaza Oval",
    "sg:city":"Casselberry",
    "sg:classifiers":[
        {
            "category":"Building & Trades",
            "subcategory":"Construction",
            "type":"Services"
        }
    ],
    "sg:phone":"+1 407 331 6357",
    "sg:postcode":"32707",
    "sg:province":"FL",
    "sg:tags":[
        "contractor"
    ],
    "wof:name":"Clyde D Achord Dry Wall",
    "wof:placetype":"venue"
},
  "geometry": {"coordinates":[-81.404265,28.651639],"type":"Point"}
}