{
  "type": "Feature",
  "properties": {
    "iso:country":"US",
    "sg:address":"2231 N 50th Ave",
    "sg:city":"Hollywood",
    "sg:classifiers":[
        {
            "category":"Shopping",
            "subcategory":"Computers & Home Electronics",
            "type":"Retail Goods"
        }
    ],
    "sg:phone":"+1 954 981 9272",
    "sg:postcode":"33021",
    "sg:province":"FL",
    "wof:name":"Mfs Computer Inc",
    "wof:placetype":"venue"
},
  "geometry": {"coordinates":[-80.19405999999999,26.029416],"type":"Point"}
}