{
  "type": "Feature",
  "properties": {
    "iso:country":"US",
    "sg:address":"1120 Curlew Rd",
    "sg:city":"Dunedin",
    "sg:classifiers":[
        {
            "category":"Organizations",
            "subcategory":"Non-profit Organization",
            "type":"Services"
        }
    ],
    "sg:phone":"+1 727 738 1652",
    "sg:postcode":"34698",
    "sg:province":"FL",
    "sg:tags":[
        "human"
    ],
    "wof:name":"Habitat For Humanity",
    "wof:placetype":"venue"
},
  "geometry": {"coordinates":[-82.77678299999999,28.048866],"type":"Point"}
}