{
  "type": "Feature",
  "properties": {
    "iso:country":"US",
    "sg:address":"1723 Tallevast Rd",
    "sg:city":"Sarasota",
    "sg:classifiers":[
        {
            "category":"Professional",
            "type":"Services"
        }
    ],
    "sg:phone":"+1 941 358 6336",
    "sg:postcode":"34270",
    "sg:province":"FL",
    "sg:tags":[
        "establishment"
    ],
    "wof:name":"KAPCO",
    "wof:placetype":"venue"
},
  "geometry": {"coordinates":[-82.543791,27.403582],"type":"Point"}
}