{
  "type": "Feature",
  "properties": {
    "addr:full":"1320 Dixie Hwy Miami FL 33146",
    "addr:housenumber":"1320",
    "addr:postcode":"33146",
    "addr:street":"Dixie Hwy",
    "iso:country":"US",
    "sg:address":"1320 Dixie Hwy",
    "sg:city":"Miami",
    "sg:classifiers":[
        {
            "category":"Professional",
            "subcategory":"Management & Consulting",
            "type":"Services"
        }
    ],
    "sg:phone":"+1 305 668 3777",
    "sg:postcode":"33146",
    "sg:province":"FL",
    "sg:tags":[
        "marketing"
    ],
    "wof:name":"Vereli Products Inc",
    "wof:placetype":"venue"
},
  "geometry": {"coordinates":[-80.27675600000001,25.714751],"type":"Point"}
}