{
  "type": "Feature",
  "properties": {
    "iso:country":"US",
    "sg:address":"12785 SW 248th St",
    "sg:city":"Homestead",
    "sg:classifiers":[
        {
            "category":"Professional",
            "type":"Services"
        }
    ],
    "sg:phone":"+1 305 258 7678",
    "sg:postcode":"33032",
    "sg:province":"FL",
    "wof:name":"El Puerto Devallarta Inc",
    "wof:placetype":"venue"
},
  "geometry": {"coordinates":[-80.396816,25.536727],"type":"Point"}
}