{
  "type": "Feature",
  "properties": {
    "iso:country":"US",
    "sg:address":"7173 SE Federal Hwy",
    "sg:city":"Port Saint Lucie",
    "sg:classifiers":[
        {
            "category":"Shopping",
            "subcategory":"Gifts & Souvenirs",
            "type":"Retail Goods"
        }
    ],
    "sg:phone":"+1 772 340 0906",
    "sg:postcode":"34997",
    "sg:province":"FL",
    "wof:name":"Discount Cards",
    "wof:placetype":"venue"
},
  "geometry": {"coordinates":[-80.18413099999999,27.120127],"type":"Point"}
}