{
  "type": "Feature",
  "properties": {
    "iso:country":"US",
    "sg:address":"1925 S Osprey Ave",
    "sg:city":"Sarasota",
    "sg:classifiers":[
        {
            "category":"Food & Beverages",
            "subcategory":"Liquor & Beverages",
            "type":"Retail Goods"
        }
    ],
    "sg:phone":"+1 941 362 9463",
    "sg:postcode":"34239",
    "sg:province":"FL",
    "sg:tags":[
        "wine"
    ],
    "sg:website":"www.epicureanlife.com",
    "wof:name":"J D Ford Purveyor Of Fine Wine",
    "wof:placetype":"venue"
},
  "geometry": {"coordinates":[-82.533669,27.315716],"type":"Point"}
}