{
  "type": "Feature",
  "properties": {
    "addr:full":"95 N Highland Ave Clearwater FL 33755",
    "addr:housenumber":"95",
    "addr:postcode":"33755",
    "addr:street":"N Highland Ave",
    "iso:country":"US",
    "sg:address":"95 N Highland Ave",
    "sg:city":"Clearwater",
    "sg:classifiers":[
        {
            "category":"Shopping",
            "subcategory":"Bicycles & Sporting Goods",
            "type":"Retail Goods"
        }
    ],
    "sg:phone":"+1 727 586 2929",
    "sg:postcode":"33755",
    "sg:province":"FL",
    "sg:tags":[
        "gun",
        "gunsmith"
    ],
    "wof:name":"Fort Harrison Firearms",
    "wof:placetype":"venue"
},
  "geometry": {"coordinates":[-82.775218,27.965552],"type":"Point"}
}