{
  "type": "Feature",
  "properties": {
    "iso:country":"US",
    "sg:address":"835 E Park Ave",
    "sg:city":"Tallahassee",
    "sg:classifiers":[
        {
            "category":"Personal",
            "type":"Services"
        }
    ],
    "sg:phone":"+1 850 656 4000",
    "sg:postcode":"32301",
    "sg:province":"FL",
    "sg:tags":[
        "therapist",
        "massage"
    ],
    "wof:name":"Vicki Lyle",
    "wof:placetype":"venue"
},
  "geometry": {"coordinates":[-84.267967,30.441671],"type":"Point"}
}