{
  "type": "Feature",
  "properties": {
    "addr:full":"2912 W Arch St Tampa FL 33607",
    "addr:housenumber":"2912",
    "addr:postcode":"33607",
    "addr:street":"W Arch St",
    "iso:country":"US",
    "sg:address":"2912 W Arch St",
    "sg:city":"Tampa",
    "sg:classifiers":[
        {
            "category":"Building & Trades",
            "subcategory":"Construction",
            "type":"Services"
        }
    ],
    "sg:phone":"+1 813 870 1775",
    "sg:postcode":"33607",
    "sg:province":"FL",
    "sg:tags":[
        "house"
    ],
    "wof:name":"Omars Construction",
    "wof:placetype":"venue"
},
  "geometry": {"coordinates":[-82.489823,27.954145],"type":"Point"}
}