{
  "type": "Feature",
  "properties": {
    "iso:country":"US",
    "sg:address":"416 State Rd 434 E",
    "sg:city":"Winter Springs",
    "sg:classifiers":[
        {
            "category":"Utilities",
            "subcategory":"Telephone",
            "type":"Services"
        }
    ],
    "sg:phone":"+1 407 327 8180",
    "sg:postcode":"32708",
    "sg:province":"FL",
    "sg:tags":[
        "company"
    ],
    "wof:name":"Telephone Marketing Promotions",
    "wof:placetype":"venue"
},
  "geometry": {"coordinates":[-81.300676,28.69949],"type":"Point"}
}