{
  "type": "Feature",
  "properties": {
    "iso:country":"US",
    "sg:address":"2000 N Alafaya Trl",
    "sg:city":"Orlando",
    "sg:classifiers":[
        {
            "category":"Shopping",
            "subcategory":"Computers & Home Electronics",
            "type":"Retail Goods"
        }
    ],
    "sg:phone":"+1 407 207 9200",
    "sg:postcode":"32826",
    "sg:province":"FL",
    "sg:tags":[
        "equipment",
        "dealer"
    ],
    "wof:name":"Hewlett-Packard Co",
    "wof:placetype":"venue"
},
  "geometry": {"coordinates":[-81.207821,28.569612],"type":"Point"}
}