{
  "type": "Feature",
  "properties": {
    "iso:country":"US",
    "sg:address":"62110 Frontier Cir",
    "sg:city":"Labelle",
    "sg:classifiers":[
        {
            "category":"Building & Trades",
            "subcategory":"Construction",
            "type":"Services"
        }
    ],
    "sg:phone":"+1 863 675 4547",
    "sg:postcode":"33935",
    "sg:province":"FL",
    "sg:tags":[
        "general",
        "contractor"
    ],
    "wof:name":"Charles Banky General Contr",
    "wof:placetype":"venue"
},
  "geometry": {"coordinates":[-81.38414899999999,26.773067],"type":"Point"}
}