{
  "type": "Feature",
  "properties": {
    "iso:country":"US",
    "sg:address":"205 Sunward Run",
    "sg:city":"Davenport",
    "sg:classifiers":[
        {
            "category":"Building & Trades",
            "subcategory":"Plumbing",
            "type":"Services"
        }
    ],
    "sg:phone":"+1 863 424 3381",
    "sg:postcode":"33896",
    "sg:province":"FL",
    "sg:tags":[
        "contractor"
    ],
    "wof:name":"Baers Repairs Plumbing Inc",
    "wof:placetype":"venue"
},
  "geometry": {"coordinates":[-81.654157,28.257638],"type":"Point"}
}