{
  "type": "Feature",
  "properties": {
    "iso:country":"US",
    "sg:address":"2912 Fairfield Ct",
    "sg:city":"Dunedin",
    "sg:classifiers":[
        {
            "category":"Professional",
            "subcategory":"Business Services",
            "type":"Services"
        }
    ],
    "sg:phone":"+1 727 712 1629",
    "sg:postcode":"34698",
    "sg:province":"FL",
    "wof:name":"Mojo Heat",
    "wof:placetype":"venue"
},
  "geometry": {"coordinates":[-82.742233,28.027367],"type":"Point"}
}