{
  "type": "Feature",
  "properties": {
    "iso:country":"US",
    "sg:address":"20590 W Dixie Hwy",
    "sg:city":"Miami",
    "sg:classifiers":[
        {
            "category":"Professional",
            "subcategory":"Accounting & Tax Preparation",
            "type":"Services"
        }
    ],
    "sg:phone":"+1 305 937 2272",
    "sg:postcode":"33180",
    "sg:province":"FL",
    "wof:name":"Levi Cahlin & Company",
    "wof:placetype":"venue"
},
  "geometry": {"coordinates":[-80.147812,25.965522],"type":"Point"}
}