{
  "type": "Feature",
  "properties": {
    "iso:country":"US",
    "sg:address":"17894 SE 92nd Amory Ave",
    "sg:city":"Lady Lake",
    "sg:classifiers":[
        {
            "category":"Banks & Credit Unions",
            "subcategory":"Financial Services",
            "type":"Services"
        }
    ],
    "sg:phone":"+1 352 259 8086",
    "sg:postcode":"32162",
    "sg:province":"FL",
    "sg:tags":[
        "trust",
        "management"
    ],
    "wof:name":"A McCook",
    "wof:placetype":"venue"
},
  "geometry": {"coordinates":[-81.999482,28.961206],"type":"Point"}
}