{
  "type": "Feature",
  "properties": {
    "iso:country":"US",
    "sg:address":"12101 NW 98th Ave",
    "sg:city":"Hialeah",
    "sg:classifiers":[
        {
            "category":"Manufacturing",
            "subcategory":"Jewelry",
            "type":"Manufacturing & Wholesale Goods"
        }
    ],
    "sg:phone":"+1 305 821 8685",
    "sg:postcode":"33018",
    "sg:province":"FL",
    "sg:tags":[
        "manufacture",
        "metal",
        "precious",
        "rings"
    ],
    "wof:name":"Wedding Rings By Mario Inc",
    "wof:placetype":"venue"
},
  "geometry": {"coordinates":[-80.35758300000001,25.882289],"type":"Point"}
}