{
  "type": "Feature",
  "properties": {
    "iso:country":"US",
    "sg:address":"4308 Alton Rd",
    "sg:city":"Miami Beach",
    "sg:classifiers":[
        {
            "category":"Health Services",
            "subcategory":"Doctor",
            "type":"Services"
        }
    ],
    "sg:phone":"+1 305 604 2888",
    "sg:postcode":"33140",
    "sg:province":"FL",
    "sg:tags":[
        "medicine",
        "internal"
    ],
    "wof:name":"Dr Gary Merlino",
    "wof:placetype":"venue"
},
  "geometry": {"coordinates":[-80.139771,25.814978],"type":"Point"}
}