{
  "type": "Feature",
  "properties": {
    "addr:full":"1408 E Blount St Pensacola FL 32503",
    "addr:housenumber":"1408",
    "addr:postcode":"32503",
    "addr:street":"E Blount St",
    "iso:country":"US",
    "sg:address":"1408 E Blount St",
    "sg:city":"Pensacola",
    "sg:classifiers":[
        {
            "category":"Education",
            "subcategory":"School",
            "type":"Public Place"
        }
    ],
    "sg:phone":"+1 850 595 6990",
    "sg:postcode":"32503",
    "sg:province":"FL",
    "wof:name":"Patts Center The",
    "wof:placetype":"venue"
},
  "geometry": {"coordinates":[-87.19983000000001,30.431262],"type":"Point"}
}