{
  "type": "Feature",
  "properties": {
    "iso:country":"US",
    "sg:address":"7725 Travelers Tree Dr",
    "sg:city":"Boca Raton",
    "sg:classifiers":[
        {
            "category":"Manufacturing",
            "subcategory":"Furniture",
            "type":"Manufacturing & Wholesale Goods"
        }
    ],
    "sg:phone":"+1 561 392 4182",
    "sg:postcode":"33433",
    "sg:province":"FL",
    "sg:tags":[
        "drapery",
        "mfg"
    ],
    "wof:name":"Lipke Steven B",
    "wof:placetype":"venue"
},
  "geometry": {"coordinates":[-80.167109,26.328643],"type":"Point"}
}