{
  "type": "Feature",
  "properties": {
    "iso:country":"US",
    "sg:address":"11919 SW 130th St",
    "sg:city":"Miami",
    "sg:classifiers":[
        {
            "category":"Real Estate",
            "subcategory":"Real Estate Services",
            "type":"Services"
        },
        {
            "category":"Real Estate",
            "subcategory":"Real Estate Agent",
            "type":"Services"
        }
    ],
    "sg:phone":"+1 305 253 0650",
    "sg:postcode":"33186",
    "sg:province":"FL",
    "sg:tags":[
        "buyer",
        "broker"
    ],
    "wof:name":"S F Enterprises Of Miami Ltd",
    "wof:placetype":"venue"
},
  "geometry": {"coordinates":[-80.388638,25.647192],"type":"Point"}
}