{
  "type": "Feature",
  "properties": {
    "addr:full":"611 N Pine Hills Rd Orlando FL 32808",
    "addr:housenumber":"611",
    "addr:postcode":"32808",
    "addr:street":"N Pine Hills Rd",
    "iso:country":"US",
    "sg:address":"611 N Pine Hills Rd",
    "sg:city":"Orlando",
    "sg:classifiers":[
        {
            "category":"Professional",
            "subcategory":"Accounting & Tax Preparation",
            "type":"Services"
        }
    ],
    "sg:phone":"+1 407 445 9335",
    "sg:postcode":"32808",
    "sg:province":"FL",
    "sg:tags":[
        "return",
        "filing"
    ],
    "wof:name":"Singh Deoraj Income Tax Svc",
    "wof:placetype":"venue"
},
  "geometry": {"coordinates":[-81.447586,28.552083],"type":"Point"}
}