{
  "type": "Feature",
  "properties": {
    "addr:full":"107 W Lambright St Tampa FL 33604",
    "addr:housenumber":"107",
    "addr:postcode":"33604",
    "addr:street":"W Lambright St",
    "iso:country":"US",
    "sg:address":"107 W Lambright St",
    "sg:city":"Tampa",
    "sg:classifiers":[
        {
            "category":"Building & Trades",
            "subcategory":"Construction",
            "type":"Services"
        }
    ],
    "sg:phone":"+1 813 935 1131",
    "sg:postcode":"33604",
    "sg:province":"FL",
    "sg:tags":[
        "masonry",
        "contractor"
    ],
    "wof:name":"Rick's Masonry Cleaning Inc",
    "wof:placetype":"venue"
},
  "geometry": {"coordinates":[-82.462096,28.00669],"type":"Point"}
}