{
  "type": "Feature",
  "properties": {
    "iso:country":"US",
    "sg:address":"8507 Surf Dr",
    "sg:city":"Panama City Bch",
    "sg:classifiers":[
        {
            "category":"Travel",
            "subcategory":"Hotels & Motels",
            "type":"Entertainment"
        }
    ],
    "sg:phone":"+1 850 233 1899",
    "sg:postcode":"32408",
    "sg:province":"FL",
    "wof:name":"Lollye On The Beach",
    "wof:placetype":"venue"
},
  "geometry": {"coordinates":[-85.787578,30.165123],"type":"Point"}
}