{
  "type": "Feature",
  "properties": {
    "iso:country":"US",
    "sg:address":"1010 SE 9th St",
    "sg:city":"Cape Coral",
    "sg:classifiers":[
        {
            "category":"Wholesale",
            "subcategory":"Construction Materials",
            "type":"Manufacturing & Wholesale Goods"
        }
    ],
    "sg:phone":"+1 239 574 3122",
    "sg:postcode":"33990",
    "sg:province":"FL",
    "sg:tags":[
        "fence"
    ],
    "wof:name":"Century Fence Co",
    "wof:placetype":"venue"
},
  "geometry": {"coordinates":[-81.952099,26.636097],"type":"Point"}
}