{
  "type": "Feature",
  "properties": {
    "addr:full":"8015 W 14th Ave Hialeah FL 33014",
    "addr:housenumber":"8015",
    "addr:postcode":"33014",
    "addr:street":"W 14Th Ave",
    "iso:country":"US",
    "sg:address":"8015 W 14th Ave",
    "sg:city":"Hialeah",
    "sg:classifiers":[
        {
            "category":"Building & Trades",
            "subcategory":"Construction",
            "type":"Services"
        }
    ],
    "sg:phone":"+1 305 825 7466",
    "sg:postcode":"33014",
    "sg:province":"FL",
    "sg:tags":[
        "house",
        "consulting",
        "management"
    ],
    "wof:name":"Adriola Corporation",
    "wof:placetype":"venue"
},
  "geometry": {"coordinates":[-80.312049,25.896042],"type":"Point"}
}