{
  "type": "Feature",
  "properties": {
    "iso:country":"US",
    "sg:address":"2550 W Colonial Dr",
    "sg:city":"Orlando",
    "sg:classifiers":[
        {
            "category":"Personal",
            "subcategory":"Psychics & Astrologers",
            "type":"Services"
        }
    ],
    "sg:phone":"+1 407 245 7575",
    "sg:postcode":"32804",
    "sg:province":"FL",
    "sg:tags":[
        "therapist",
        "respiratory"
    ],
    "wof:name":"Central Florida Pulmonary Rehab",
    "wof:placetype":"venue"
},
  "geometry": {"coordinates":[-81.412184,28.55272],"type":"Point"}
}