{
  "type": "Feature",
  "properties": {
    "iso:country":"US",
    "sg:address":"1115 45th St",
    "sg:city":"West Palm Beach",
    "sg:classifiers":[
        {
            "category":"Organizations",
            "subcategory":"Non-profit Organization",
            "type":"Services"
        }
    ],
    "sg:phone":"+1 561 863 4600",
    "sg:postcode":"33407",
    "sg:province":"FL",
    "sg:tags":[
        "information",
        "alcoholism",
        "treatment"
    ],
    "wof:name":"Palm Beach Psych Iatric & Adct",
    "wof:placetype":"venue"
},
  "geometry": {"coordinates":[-80.06908300000001,26.753206],"type":"Point"}
}