{
  "type": "Feature",
  "properties": {
    "iso:country":"US",
    "sg:address":"5313 Summerset St",
    "sg:city":"Orlando",
    "sg:classifiers":[
        {
            "category":"Building & Trades",
            "subcategory":"Construction",
            "type":"Services"
        }
    ],
    "sg:phone":"+1 407 629 9643",
    "sg:postcode":"32810",
    "sg:province":"FL",
    "sg:tags":[
        "contractor"
    ],
    "wof:name":"Nathan Rose Stucco",
    "wof:placetype":"venue"
},
  "geometry": {"coordinates":[-81.395662,28.609013],"type":"Point"}
}