{
  "type": "Feature",
  "properties": {
    "iso:country":"US",
    "sg:address":"3512 Maclay Blvd S",
    "sg:city":"Tallahassee",
    "sg:classifiers":[
        {
            "category":"Personal",
            "type":"Services"
        }
    ],
    "sg:phone":"+1 850 205 2111",
    "sg:postcode":"32312",
    "sg:province":"FL",
    "sg:tags":[
        "assistant"
    ],
    "sg:website":"http://www.csifl.com",
    "wof:name":"Consulting Solutions International, Inc.",
    "wof:placetype":"venue"
},
  "geometry": {"coordinates":[-84.252379,30.507928],"type":"Point"}
}