{
  "type": "Feature",
  "properties": {
    "addr:full":"2504 W 67th Pl Hialeah FL 33016",
    "addr:housenumber":"2504",
    "addr:postcode":"33016",
    "addr:street":"W 67Th Pl",
    "iso:country":"US",
    "sg:address":"2504 W 67th Pl",
    "sg:city":"Hialeah",
    "sg:classifiers":[
        {
            "category":"Insurance",
            "subcategory":"Insurance Agent",
            "type":"Services"
        }
    ],
    "sg:phone":"+1 305 669 8876",
    "sg:postcode":"33016",
    "sg:province":"FL",
    "wof:name":"Ludlam Insurance",
    "wof:placetype":"venue"
},
  "geometry": {"coordinates":[-80.33459000000001,25.883693],"type":"Point"}
}