{
  "type": "Feature",
  "properties": {
    "addr:full":"801 Brickell Ave Fl 9 Miami FL 33131",
    "addr:housenumber":"801;9",
    "addr:postcode":"33131",
    "addr:street":"Brickell Ave Fl",
    "iso:country":"US",
    "sg:address":"801 Brickell Ave Fl 9",
    "sg:city":"Miami",
    "sg:classifiers":[
        {
            "category":"Professional",
            "subcategory":"Business Services",
            "type":"Services"
        }
    ],
    "sg:phone":"+1 305 789 6696",
    "sg:postcode":"33131",
    "sg:province":"FL",
    "sg:tags":[
        "environmental",
        "product",
        "ecological"
    ],
    "wof:name":"Ssi",
    "wof:placetype":"venue"
},
  "geometry": {"coordinates":[-80.19059799999999,25.76614],"type":"Point"}
}