{
  "type": "Feature",
  "properties": {
    "iso:country":"US",
    "sg:address":"12829 Darby Ridge Dr",
    "sg:city":"Tampa",
    "sg:classifiers":[
        {
            "category":"Autos & Motor Vehicles",
            "subcategory":"Auto Supplies",
            "type":"Retail Goods"
        }
    ],
    "sg:phone":"+1 813 963 5654",
    "sg:postcode":"33624",
    "sg:province":"FL",
    "sg:tags":[
        "tire"
    ],
    "wof:name":"Just Tires Of Tampa",
    "wof:placetype":"venue"
},
  "geometry": {"coordinates":[-82.522126,28.060771],"type":"Point"}
}