{
  "type": "Feature",
  "properties": {
    "iso:country":"US",
    "sg:address":"1575 Donna Rd",
    "sg:city":"West Palm Beach",
    "sg:classifiers":[
        {
            "category":"Retail",
            "subcategory":"Auto Repair",
            "type":"Services"
        }
    ],
    "sg:phone":"+1 561 242 1145",
    "sg:postcode":"33409",
    "sg:province":"FL",
    "sg:tags":[
        "automobile",
        "co",
        "drive",
        "transporter"
    ],
    "wof:name":"Bullet Auto Transport",
    "wof:placetype":"venue"
},
  "geometry": {"coordinates":[-80.081119,26.700418],"type":"Point"}
}