{
  "type": "Feature",
  "properties": {
    "iso:country":"US",
    "sg:address":"463 S Buckmoore Rd",
    "sg:city":"Lake Wales",
    "sg:classifiers":[
        {
            "category":"Organizations",
            "subcategory":"Religious Organization",
            "type":"Services"
        }
    ],
    "sg:phone":"+1 863 676 4114",
    "sg:postcode":"33853",
    "sg:province":"FL",
    "sg:tags":[
        "church"
    ],
    "wof:name":"Church Of Christ",
    "wof:placetype":"venue"
},
  "geometry": {"coordinates":[-81.556003,27.894848],"type":"Point"}
}