{
  "type": "Feature",
  "properties": {
    "iso:country":"US",
    "sg:address":"7393 Woodmont Ct",
    "sg:city":"Boca Raton",
    "sg:classifiers":[
        {
            "category":"Professional",
            "subcategory":"Management & Consulting",
            "type":"Services"
        }
    ],
    "sg:phone":"+1 561 488 7566",
    "sg:postcode":"33434",
    "sg:province":"FL",
    "wof:name":"Nathan Management Inc",
    "wof:placetype":"venue"
},
  "geometry": {"coordinates":[-80.16158299999999,26.381988],"type":"Point"}
}