{
  "type": "Feature",
  "properties": {
    "addr:full":"1231 Cleveland St Clearwater FL 33755",
    "addr:housenumber":"1231",
    "addr:postcode":"33755",
    "addr:street":"Cleveland St",
    "iso:country":"US",
    "sg:address":"1231 Cleveland St",
    "sg:city":"Clearwater",
    "sg:classifiers":[
        {
            "category":"Autos & Motor Vehicles",
            "subcategory":"Boat Sales",
            "type":"Retail Goods"
        }
    ],
    "sg:phone":"+1 727 443 2280",
    "sg:postcode":"33755",
    "sg:province":"FL",
    "sg:tags":[
        "dealer",
        "equipment",
        "marine",
        "mari",
        "supply"
    ],
    "wof:name":"West Marine Inc",
    "wof:placetype":"venue"
},
  "geometry": {"coordinates":[-82.78671300000001,27.965557],"type":"Point"}
}