{
  "type": "Feature",
  "properties": {
    "addr:full":"4335 NE 21st St Ocala FL 34470",
    "addr:housenumber":"4335",
    "addr:postcode":"34470",
    "addr:street":"Ne 21St St",
    "iso:country":"US",
    "sg:address":"4335 NE 21st St",
    "sg:city":"Ocala",
    "sg:classifiers":[
        {
            "category":"Shopping",
            "subcategory":"Florist",
            "type":"Retail Goods"
        }
    ],
    "sg:phone":"+1 352 236 5912",
    "sg:postcode":"34470",
    "sg:province":"FL",
    "wof:name":"Booker's Roses",
    "wof:placetype":"venue"
},
  "geometry": {"coordinates":[-82.072918,29.208283],"type":"Point"}
}