{
  "type": "Feature",
  "properties": {
    "addr:full":"314 E Geneva St Ocoee FL 34761",
    "addr:housenumber":"314",
    "addr:postcode":"34761",
    "addr:street":"E Geneva St",
    "iso:country":"US",
    "sg:address":"314 E Geneva St",
    "sg:city":"Ocoee",
    "sg:classifiers":[
        {
            "category":"Banks & Credit Unions",
            "subcategory":"Financial Services",
            "type":"Services"
        }
    ],
    "sg:phone":"+1 407 656 9841",
    "sg:postcode":"34761",
    "sg:province":"FL",
    "sg:tags":[
        "trust",
        "investment",
        "real estate"
    ],
    "wof:name":"Sports Investments Inc",
    "wof:placetype":"venue"
},
  "geometry": {"coordinates":[-81.54356900000001,28.559099],"type":"Point"}
}