{
  "type": "Feature",
  "properties": {
    "iso:country":"US",
    "sg:address":"839 SW 13th St",
    "sg:city":"Cape Coral",
    "sg:classifiers":[
        {
            "category":"Social Services",
            "type":"Services"
        }
    ],
    "sg:phone":"+1 239 574 4590",
    "sg:postcode":"33991",
    "sg:province":"FL",
    "sg:tags":[
        "organization",
        "welfare"
    ],
    "wof:name":"Island Cast Intl Adoption Agcy",
    "wof:placetype":"venue"
},
  "geometry": {"coordinates":[-81.99735800000001,26.628184],"type":"Point"}
}