{
  "type": "Feature",
  "properties": {
    "addr:full":"2251 Sarno Rd Melbourne FL 32935",
    "addr:housenumber":"2251",
    "addr:postcode":"32935",
    "addr:street":"Sarno Rd",
    "iso:country":"US",
    "sg:address":"2251 Sarno Rd",
    "sg:city":"Melbourne",
    "sg:classifiers":[
        {
            "category":"Personal",
            "type":"Services"
        }
    ],
    "sg:phone":"+1 321 253 2922",
    "sg:postcode":"32935",
    "sg:province":"FL",
    "wof:name":"Brandon Wedding Services",
    "wof:placetype":"venue"
},
  "geometry": {"coordinates":[-80.65860499999999,28.121598],"type":"Point"}
}