{
  "type": "Feature",
  "properties": {
    "addr:full":"28515 State Hwy 46 Sorrento FL 32776",
    "addr:housenumber":"28515",
    "addr:postcode":"32776",
    "addr:street":"State Hwy 46",
    "iso:country":"US",
    "sg:address":"28515 State Hwy 46",
    "sg:city":"Sorrento",
    "sg:classifiers":[
        {
            "category":"Manufacturing",
            "subcategory":"Lumber",
            "type":"Manufacturing & Wholesale Goods"
        }
    ],
    "sg:phone":"+1 352 735 2259",
    "sg:postcode":"32776",
    "sg:province":"FL",
    "sg:tags":[
        "logging"
    ],
    "wof:name":"John Bagwell Logging",
    "wof:placetype":"venue"
},
  "geometry": {"coordinates":[-81.486029,28.818538],"type":"Point"}
}