{
  "type": "Feature",
  "properties": {
    "iso:country":"US",
    "sg:address":"27156 W Dixie Hwy",
    "sg:city":"Homestead",
    "sg:classifiers":[
        {
            "category":"Restaurant",
            "type":"Food & Drink"
        }
    ],
    "sg:phone":"+1 305 248 7909",
    "sg:postcode":"33032",
    "sg:province":"FL",
    "wof:name":"Gio Dan Restaurant",
    "wof:placetype":"venue"
},
  "geometry": {"coordinates":[-80.431695,25.516353],"type":"Point"}
}