{
  "type": "Feature",
  "properties": {
    "iso:country":"US",
    "sg:address":"1880 Collins Landing Rd",
    "sg:city":"Tallahassee",
    "sg:classifiers":[
        {
            "category":"Home & Garden",
            "subcategory":"Home Furnishings",
            "type":"Retail Goods"
        }
    ],
    "sg:phone":"+1 850 574 9648",
    "sg:postcode":"32310",
    "sg:province":"FL",
    "wof:name":"Custom Window Coverings",
    "wof:placetype":"venue"
},
  "geometry": {"coordinates":[-84.56823900000001,30.423878],"type":"Point"}
}