{
  "type": "Feature",
  "properties": {
    "addr:full":"3380 S Park Ave Titusville FL 32780",
    "addr:housenumber":"3380",
    "addr:postcode":"32780",
    "addr:street":"S Park Ave",
    "iso:country":"US",
    "sg:address":"3380 S Park Ave",
    "sg:city":"Titusville",
    "sg:classifiers":[
        {
            "category":"Building & Trades",
            "subcategory":"Landscaping Services",
            "type":"Services"
        }
    ],
    "sg:phone":"+1 321 385 2615",
    "sg:postcode":"32780",
    "sg:province":"FL",
    "sg:tags":[
        "designer",
        "landscape"
    ],
    "wof:name":"Parterre LA",
    "wof:placetype":"venue"
},
  "geometry": {"coordinates":[-80.838459,28.574585],"type":"Point"}
}