{
  "type": "Feature",
  "properties": {
    "iso:country":"US",
    "sg:address":"9917 NW 17th St",
    "sg:city":"Pompano Beach",
    "sg:classifiers":[
        {
            "category":"Building & Trades",
            "subcategory":"Construction",
            "type":"Services"
        }
    ],
    "sg:phone":"+1 954 752 1869",
    "sg:postcode":"33071",
    "sg:province":"FL",
    "sg:tags":[
        "house"
    ],
    "wof:name":"Urbish Urbish Construction",
    "wof:placetype":"venue"
},
  "geometry": {"coordinates":[-80.26088,26.25143],"type":"Point"}
}