{
  "type": "Feature",
  "properties": {
    "addr:full":"2600 Windsor Ln N Fort Walton Bch FL 32547",
    "addr:housenumber":"2600",
    "addr:postcode":"32547",
    "addr:street":"Windsor Ln N Fort",
    "iso:country":"US",
    "sg:address":"2600 Windsor Ln N",
    "sg:city":"Fort Walton Bch",
    "sg:classifiers":[
        {
            "category":"Personal",
            "type":"Services"
        }
    ],
    "sg:phone":"+1 850 865 1207",
    "sg:postcode":"32547",
    "sg:province":"FL",
    "sg:tags":[
        "control",
        "weight"
    ],
    "wof:name":"Herbalife Distributor",
    "wof:placetype":"venue"
},
  "geometry": {"coordinates":[-86.655113,30.465787],"type":"Point"}
}