{
  "type": "Feature",
  "properties": {
    "iso:country":"US",
    "sg:address":"3919 Woodville Hwy",
    "sg:city":"Tallahassee",
    "sg:classifiers":[
        {
            "category":"Freight",
            "type":"Transportation"
        }
    ],
    "sg:phone":"+1 850 656 1566",
    "sg:postcode":"32305",
    "sg:province":"FL",
    "sg:tags":[
        "trucking"
    ],
    "wof:name":"CCP Trucking & Trans Inc",
    "wof:placetype":"venue"
},
  "geometry": {"coordinates":[-84.276286,30.390284],"type":"Point"}
}