{
  "type": "Feature",
  "properties": {
    "addr:full":"7333 SW 27th Ct Fort Lauderdale FL 33314",
    "addr:housenumber":"7333",
    "addr:postcode":"33314",
    "addr:street":"Sw 27Th Ct",
    "iso:country":"US",
    "sg:address":"7333 SW 27th Ct",
    "sg:city":"Fort Lauderdale",
    "sg:classifiers":[
        {
            "category":"Insurance",
            "subcategory":"Insurance Agent",
            "type":"Services"
        }
    ],
    "sg:phone":"+1 954 370 9409",
    "sg:postcode":"33314",
    "sg:province":"FL",
    "wof:name":"Richard Rentner Insurance",
    "wof:placetype":"venue"
},
  "geometry": {"coordinates":[-80.246465,26.088147],"type":"Point"}
}