{
  "type": "Feature",
  "properties": {
    "iso:country":"US",
    "sg:address":"9124 Sikes Cow Pen Rd",
    "sg:city":"Brooksville",
    "sg:classifiers":[
        {
            "category":"Shopping",
            "subcategory":"Computers & Home Electronics",
            "type":"Retail Goods"
        }
    ],
    "sg:phone":"+1 352 796 6860",
    "sg:postcode":"34601",
    "sg:province":"FL",
    "wof:name":"Casewarez",
    "wof:placetype":"venue"
},
  "geometry": {"coordinates":[-82.296828,28.559679],"type":"Point"}
}