{
  "type": "Feature",
  "properties": {
    "iso:country":"US",
    "sg:address":"1660 Sarno Rd",
    "sg:city":"Melbourne",
    "sg:classifiers":[
        {
            "category":"Social Services",
            "subcategory":"Adult Care",
            "type":"Services"
        }
    ],
    "sg:phone":"+1 321 253 3355",
    "sg:postcode":"32935",
    "sg:province":"FL",
    "sg:tags":[
        "home",
        "residential"
    ],
    "wof:name":"Pleasent Harbor",
    "wof:placetype":"venue"
},
  "geometry": {"coordinates":[-80.648217,28.121709],"type":"Point"}
}