{
  "type": "Feature",
  "properties": {
    "iso:country":"US",
    "sg:address":"3000 W Martin Luther King Jr Blvd",
    "sg:city":"Tampa",
    "sg:classifiers":[
        {
            "category":"Shopping",
            "subcategory":"Optical Goods",
            "type":"Retail Goods"
        }
    ],
    "sg:phone":"+1 813 875 5395",
    "sg:postcode":"33607",
    "sg:province":"FL",
    "sg:tags":[
        "contact",
        "lense"
    ],
    "wof:name":"Tampa Eye Clinic",
    "wof:placetype":"venue"
},
  "geometry": {"coordinates":[-82.49299999999999,27.981354],"type":"Point"}
}