{
  "type": "Feature",
  "properties": {
    "addr:full":"8365 SW 91st St Miami FL 33156",
    "addr:housenumber":"8365",
    "addr:postcode":"33156",
    "addr:street":"Sw 91St St",
    "iso:country":"US",
    "sg:address":"8365 SW 91st St",
    "sg:city":"Miami",
    "sg:classifiers":[
        {
            "category":"Professional",
            "subcategory":"Lawyer & Legal Services",
            "type":"Services"
        }
    ],
    "sg:phone":"+1 305 271 4836",
    "sg:postcode":"33156",
    "sg:province":"FL",
    "wof:name":"Palley Sheldon B Atty",
    "wof:placetype":"venue"
},
  "geometry": {"coordinates":[-80.33049800000001,25.6856],"type":"Point"}
}