{
  "type": "Feature",
  "properties": {
    "iso:country":"US",
    "sg:address":"601 W State St",
    "sg:city":"Jacksonville",
    "sg:classifiers":[
        {
            "category":"Education",
            "subcategory":"College",
            "type":"Public Place"
        }
    ],
    "sg:phone":"+1 904 633 8114",
    "sg:postcode":"32202",
    "sg:province":"FL",
    "sg:tags":[
        "academic",
        "school"
    ],
    "wof:name":"FCCJ",
    "wof:placetype":"venue"
},
  "geometry": {"coordinates":[-81.66451000000001,30.334823],"type":"Point"}
}