{
  "type": "Feature",
  "properties": {
    "addr:full":"1775 Aurora Rd Melbourne FL 32935",
    "addr:housenumber":"1775",
    "addr:postcode":"32935",
    "addr:street":"Aurora Rd",
    "iso:country":"US",
    "sg:address":"1775 Aurora Rd",
    "sg:city":"Melbourne",
    "sg:classifiers":[
        {
            "category":"Autos & Motor Vehicles",
            "subcategory":"Automobile Sales",
            "type":"Retail Goods"
        }
    ],
    "sg:phone":"+1 321 254 0300",
    "sg:postcode":"32935",
    "sg:province":"FL",
    "sg:tags":[
        "used"
    ],
    "wof:name":"Minton Motors",
    "wof:placetype":"venue"
},
  "geometry": {"coordinates":[-80.649418,28.135848],"type":"Point"}
}