{
  "type": "Feature",
  "properties": {
    "iso:country":"US",
    "sg:address":"3001 N Rocky Point Dr E",
    "sg:city":"Tampa",
    "sg:classifiers":[
        {
            "category":"Professional",
            "subcategory":"Computer Services",
            "type":"Services"
        }
    ],
    "sg:phone":"+1 813 287 1780",
    "sg:postcode":"33607",
    "sg:province":"FL",
    "sg:tags":[
        "consultant"
    ],
    "wof:name":"Coleman Technologies Inc",
    "wof:placetype":"venue"
},
  "geometry": {"coordinates":[-82.56410099999999,27.970502],"type":"Point"}
}