{
  "type": "Feature",
  "properties": {
    "iso:country":"US",
    "sg:address":"7431 W Atlantic Ave",
    "sg:city":"Delray Beach",
    "sg:classifiers":[
        {
            "category":"Health Services",
            "subcategory":"Health Practitioner",
            "type":"Services"
        }
    ],
    "sg:phone":"+1 561 638 7455",
    "sg:postcode":"33446",
    "sg:province":"FL",
    "sg:tags":[
        "therapist",
        "physical"
    ],
    "wof:name":"Back In Action",
    "wof:placetype":"venue"
},
  "geometry": {"coordinates":[-80.162251,26.45379],"type":"Point"}
}