{
  "type": "Feature",
  "properties": {
    "addr:full":"2173 SW Oak Ridge Rd Palm City FL 34990",
    "addr:housenumber":"2173",
    "addr:postcode":"34990",
    "addr:street":"Sw Oak Ridge Rd",
    "iso:country":"US",
    "sg:address":"2173 SW Oak Ridge Rd",
    "sg:city":"Palm City",
    "sg:classifiers":[
        {
            "category":"Building & Trades",
            "subcategory":"Construction",
            "type":"Services"
        }
    ],
    "sg:phone":"+1 772 220 0775",
    "sg:postcode":"34990",
    "sg:province":"FL",
    "sg:tags":[
        "residential"
    ],
    "wof:name":"Michael Walsh Contracting",
    "wof:placetype":"venue"
},
  "geometry": {"coordinates":[-80.283311,27.191341],"type":"Point"}
}