{
  "type": "Feature",
  "properties": {
    "iso:country":"US",
    "sg:address":"12661 Metro Pkwy",
    "sg:city":"Fort Myers",
    "sg:classifiers":[
        {
            "category":"Professional",
            "subcategory":"Engineering",
            "type":"Services"
        }
    ],
    "sg:phone":"+1 239 768 0077",
    "sg:postcode":"33966",
    "sg:province":"FL",
    "sg:tags":[
        "engineer"
    ],
    "wof:name":"Neese & Assoc",
    "wof:placetype":"venue"
},
  "geometry": {"coordinates":[-81.852616,26.548873],"type":"Point"}
}