{
  "type": "Feature",
  "properties": {
    "addr:full":"57500 Morton St Marathon FL 33050",
    "addr:postcode":"57500;33050",
    "addr:street":"Morton St",
    "iso:country":"US",
    "sg:address":"57500 Morton St",
    "sg:city":"Marathon",
    "sg:classifiers":[
        {
            "category":"Recreation",
            "type":"Entertainment"
        }
    ],
    "sg:phone":"+1 305 743 0929",
    "sg:postcode":"33050",
    "sg:province":"FL",
    "sg:tags":[
        "guide"
    ],
    "wof:name":"Fishing Pursuits",
    "wof:placetype":"venue"
},
  "geometry": {"coordinates":[-80.966808,24.758084],"type":"Point"}
}