{
  "type": "Feature",
  "properties": {
    "addr:full":"111 SW 3 St Gainesville FL 32601",
    "addr:housenumber":"111",
    "addr:postcode":"32601",
    "addr:street":"Sw 3 St",
    "iso:country":"US",
    "sg:address":"111 SW 3 St",
    "sg:city":"Gainesville",
    "sg:classifiers":[
        {
            "category":"Professional",
            "subcategory":"Lawyer & Legal Services",
            "type":"Services"
        }
    ],
    "sg:phone":"+1 352 372 6503",
    "sg:postcode":"32601",
    "sg:province":"FL",
    "wof:name":"Raymond M Ivey Inc",
    "wof:placetype":"venue"
},
  "geometry": {"coordinates":[-82.327859,29.650336],"type":"Point"}
}