{
  "type": "Feature",
  "properties": {
    "iso:country":"US",
    "sg:address":"4661 SW 72nd Ave",
    "sg:city":"Miami",
    "sg:classifiers":[
        {
            "category":"Home & Garden",
            "subcategory":"Building Materials",
            "type":"Retail Goods"
        },
        {
            "category":"Manufacturing",
            "subcategory":"Building Materials",
            "type":"Manufacturing & Wholesale Goods"
        }
    ],
    "sg:phone":"+1 305 668 8805",
    "sg:postcode":"33155",
    "sg:province":"FL",
    "sg:tags":[
        "doors-wholesale",
        "accessory",
        "window",
        "doors",
        "frames",
        "manufacturer"
    ],
    "wof:name":"South Florida Impact Windows And Doors",
    "wof:placetype":"venue"
},
  "geometry": {"coordinates":[-80.31076400000001,25.726747],"type":"Point"}
}