{
  "type": "Feature",
  "properties": {
    "iso:country":"US",
    "sg:address":"730 E 7th Ave",
    "sg:city":"Hialeah",
    "sg:classifiers":[
        {
            "category":"Manufacturing",
            "subcategory":"Furniture",
            "type":"Manufacturing & Wholesale Goods"
        }
    ],
    "sg:phone":"+1 305 324 6669",
    "sg:postcode":"33010",
    "sg:province":"FL",
    "sg:tags":[
        "furniture-unfinished"
    ],
    "wof:name":"Margarita Toledo",
    "wof:placetype":"venue"
},
  "geometry": {"coordinates":[-80.267458,25.829042],"type":"Point"}
}