{
  "type": "Feature",
  "properties": {
    "iso:country":"US",
    "sg:address":"1986 NE 8th St",
    "sg:city":"Homestead",
    "sg:classifiers":[
        {
            "category":"Utilities",
            "subcategory":"Mobile Phone",
            "type":"Services"
        }
    ],
    "sg:phone":"+1 305 245 4455",
    "sg:postcode":"33033",
    "sg:province":"FL",
    "sg:tags":[
        "communication",
        "radiotelephone"
    ],
    "wof:name":"South Dade Beeper Inc",
    "wof:placetype":"venue"
},
  "geometry": {"coordinates":[-80.452746,25.477298],"type":"Point"}
}