{
  "type": "Feature",
  "properties": {
    "addr:full":"11600 Mackay Blvd Orlando FL 32826",
    "addr:housenumber":"11600",
    "addr:postcode":"32826",
    "addr:street":"Mackay Blvd",
    "iso:country":"US",
    "sg:address":"11600 Mackay Blvd",
    "sg:city":"Orlando",
    "sg:classifiers":[
        {
            "category":"Real Estate",
            "subcategory":"Real Estate Services",
            "type":"Services"
        },
        {
            "category":"Real Estate",
            "subcategory":"Real Estate Operator",
            "type":"Services"
        }
    ],
    "sg:phone":"+1 407 282 7333",
    "sg:postcode":"32826",
    "sg:province":"FL",
    "sg:tags":[
        "vacancy",
        "apartment",
        "rental",
        "finder",
        "listing"
    ],
    "wof:name":"Jefferson Arbour Apartments",
    "wof:placetype":"venue"
},
  "geometry": {"coordinates":[-81.21118199999999,28.588551],"type":"Point"}
}