{
  "type": "Feature",
  "properties": {
    "iso:country":"US",
    "sg:address":"189 Eglin Pkwy S",
    "sg:city":"Fort Walton Bch",
    "sg:classifiers":[
        {
            "category":"Manufacturing",
            "subcategory":"Tools & Machinery",
            "type":"Manufacturing & Wholesale Goods"
        }
    ],
    "sg:phone":"+1 850 243 5768",
    "sg:postcode":"32548",
    "sg:province":"FL",
    "sg:tags":[
        "industry",
        "aerospace"
    ],
    "wof:name":"Lockheed Martin Owego",
    "wof:placetype":"venue"
},
  "geometry": {"coordinates":[-86.606308,30.405307],"type":"Point"}
}