{
  "type": "Feature",
  "properties": {
    "addr:full":"15227 SW Palm Oak Ave Indiantown FL 34956",
    "addr:housenumber":"15227",
    "addr:postcode":"34956",
    "addr:street":"Sw Palm Oak Ave",
    "iso:country":"US",
    "sg:address":"15227 SW Palm Oak Ave",
    "sg:city":"Indiantown",
    "sg:classifiers":[
        {
            "category":"Restaurant",
            "type":"Food & Drink"
        }
    ],
    "sg:phone":"+1 772 597 5971",
    "sg:postcode":"34956",
    "sg:province":"FL",
    "wof:name":"Uncle Bill's Smoke Shack",
    "wof:placetype":"venue"
},
  "geometry": {"coordinates":[-80.460684,27.01204],"type":"Point"}
}