{
  "type": "Feature",
  "properties": {
    "iso:country":"US",
    "sg:address":"988 Sweetbrier Dr",
    "sg:city":"Deltona",
    "sg:classifiers":[
        {
            "category":"Building & Trades",
            "subcategory":"Landscaping Services",
            "type":"Services"
        }
    ],
    "sg:phone":"+1 386 575 3370",
    "sg:postcode":"32725",
    "sg:province":"FL",
    "sg:tags":[
        "lawn",
        "maintenance",
        "grounds"
    ],
    "wof:name":"Pryor's Landscaping",
    "wof:placetype":"venue"
},
  "geometry": {"coordinates":[-81.253562,28.88996],"type":"Point"}
}