{
  "type": "Feature",
  "properties": {
    "addr:full":"6971 W Broward Blvd Plantation FL 33317",
    "addr:housenumber":"6971",
    "addr:postcode":"33317",
    "addr:street":"W Broward Blvd",
    "iso:country":"US",
    "sg:address":"6971 W Broward Blvd",
    "sg:city":"Plantation",
    "sg:classifiers":[
        {
            "category":"Restaurant",
            "type":"Food & Drink"
        }
    ],
    "sg:phone":"+1 954 792 8898",
    "sg:postcode":"33317",
    "sg:province":"FL",
    "wof:name":"Empire Sushi",
    "wof:placetype":"venue"
},
  "geometry": {"coordinates":[-80.239142,26.120887],"type":"Point"}
}