{
  "type": "Feature",
  "properties": {
    "iso:country":"US",
    "sg:address":"475 Hamlin Ave",
    "sg:city":"Satellite Beach",
    "sg:classifiers":[
        {
            "category":"Building & Trades",
            "subcategory":"Construction",
            "type":"Services"
        }
    ],
    "sg:phone":"+1 321 773 0028",
    "sg:postcode":"32937",
    "sg:province":"FL",
    "sg:tags":[
        "house",
        "contractor"
    ],
    "wof:name":"Dumont Smith Construction",
    "wof:placetype":"venue"
},
  "geometry": {"coordinates":[-80.599448,28.176309],"type":"Point"}
}