{
  "type": "Feature",
  "properties": {
    "addr:full":"2903 29th Ave E Bradenton FL 34208",
    "addr:housenumber":"2903",
    "addr:postcode":"34208",
    "addr:street":"29Th Ave E",
    "iso:country":"US",
    "sg:address":"2903 29th Ave E",
    "sg:city":"Bradenton",
    "sg:classifiers":[
        {
            "category":"Professional",
            "type":"Services"
        }
    ],
    "sg:phone":"+1 941 750 6776",
    "sg:postcode":"34208",
    "sg:province":"FL",
    "sg:tags":[
        "establishment"
    ],
    "wof:name":"Rimer & Rimer",
    "wof:placetype":"venue"
},
  "geometry": {"coordinates":[-82.525919,27.473544],"type":"Point"}
}