{
  "type": "Feature",
  "properties": {
    "addr:full":"906 36th St West Palm Beach FL 33407",
    "addr:housenumber":"906",
    "addr:postcode":"33407",
    "addr:street":"36Th St",
    "iso:country":"US",
    "sg:address":"906 36th St",
    "sg:city":"West Palm Beach",
    "sg:classifiers":[
        {
            "category":"Social Services",
            "subcategory":"Adult Care",
            "type":"Services"
        },
        {
            "category":"Autos & Motor Vehicles",
            "subcategory":"Fuel & Gas Station",
            "type":"Retail Goods"
        }
    ],
    "sg:phone":"+1 561 844 6127",
    "sg:postcode":"33407",
    "sg:province":"FL",
    "sg:tags":[
        "home",
        "station",
        "gasoline",
        "residential"
    ],
    "wof:name":"B P Assisted Living Inc",
    "wof:placetype":"venue"
},
  "geometry": {"coordinates":[-80.06447300000001,26.745972],"type":"Point"}
}