{
  "type": "Feature",
  "properties": {
    "iso:country":"US",
    "sg:address":"7356 W 29th Ln",
    "sg:city":"Hialeah",
    "sg:classifiers":[
        {
            "category":"Home & Garden",
            "subcategory":"Carpets & Floor Coverings",
            "type":"Retail Goods"
        }
    ],
    "sg:phone":"+1 305 827 4656",
    "sg:postcode":"33018",
    "sg:province":"FL",
    "wof:name":"Souto Tiles & Carpet",
    "wof:placetype":"venue"
},
  "geometry": {"coordinates":[-80.343307,25.888312],"type":"Point"}
}