{
  "type": "Feature",
  "properties": {
    "iso:country":"US",
    "sg:address":"5201 Brooks Rd",
    "sg:city":"Fort Myers",
    "sg:classifiers":[
        {
            "category":"Building & Trades",
            "subcategory":"Construction",
            "type":"Services"
        }
    ],
    "sg:phone":"+1 239 694 0557",
    "sg:postcode":"33905",
    "sg:province":"FL",
    "sg:tags":[
        "contractor"
    ],
    "wof:name":"Valiant Construction Corp",
    "wof:placetype":"venue"
},
  "geometry": {"coordinates":[-81.727084,26.670923],"type":"Point"}
}