{
  "type": "Feature",
  "properties": {
    "addr:full":"8513 Crosswinds Dr Saint Augustine FL 32092",
    "addr:housenumber":"8513",
    "addr:postcode":"32092",
    "addr:street":"Crosswinds Dr",
    "iso:country":"US",
    "sg:address":"8513 Crosswinds Dr",
    "sg:city":"Saint Augustine",
    "sg:classifiers":[
        {
            "category":"Building & Trades",
            "subcategory":"Construction",
            "type":"Services"
        }
    ],
    "sg:phone":"+1 904 284 1151",
    "sg:postcode":"32092",
    "sg:province":"FL",
    "sg:tags":[
        "carpentry",
        "contractor"
    ],
    "wof:name":"Michael F McCann Carpentry",
    "wof:placetype":"venue"
},
  "geometry": {"coordinates":[-81.595505,29.992532],"type":"Point"}
}