{
  "type": "Feature",
  "properties": {
    "iso:country":"US",
    "sg:address":"1840 Donald St",
    "sg:city":"Jacksonville",
    "sg:classifiers":[
        {
            "category":"Shopping",
            "subcategory":"Used Merchandise",
            "type":"Retail Goods"
        }
    ],
    "sg:phone":"+1 904 384 5355",
    "sg:postcode":"32205",
    "sg:province":"FL",
    "wof:name":"Susan Berg Antiques & Art Inc",
    "wof:placetype":"venue"
},
  "geometry": {"coordinates":[-81.696988,30.300795],"type":"Point"}
}