{
  "type": "Feature",
  "properties": {
    "addr:full":"31145 Ave A Big Pine Key FL 33043",
    "addr:housenumber":"31145",
    "addr:postcode":"33043",
    "addr:street":"Ave A",
    "iso:country":"US",
    "sg:address":"31145 Ave A",
    "sg:city":"Big Pine Key",
    "sg:classifiers":[
        {
            "category":"Retail",
            "subcategory":"Repair Shop",
            "type":"Services"
        }
    ],
    "sg:phone":"+1 305 872 3384",
    "sg:postcode":"33043",
    "sg:province":"FL",
    "sg:tags":[
        "scooter",
        "motorcycle",
        "motor"
    ],
    "wof:name":"Skip's Cycles",
    "wof:placetype":"venue"
},
  "geometry": {"coordinates":[-81.346118,24.669705],"type":"Point"}
}