{
  "type": "Feature",
  "properties": {
    "addr:full":"819 Colonial Rd West Palm Beach FL 33405",
    "addr:housenumber":"819",
    "addr:postcode":"33405",
    "addr:street":"Colonial Rd",
    "iso:country":"US",
    "sg:address":"819 Colonial Rd",
    "sg:city":"West Palm Beach",
    "sg:classifiers":[
        {
            "category":"Building & Trades",
            "subcategory":"Construction",
            "type":"Services"
        }
    ],
    "sg:phone":"+1 561 547 3787",
    "sg:postcode":"33405",
    "sg:province":"FL",
    "sg:tags":[
        "maintenance",
        "contractor"
    ],
    "wof:name":"G Nel Maintenance Svc",
    "wof:placetype":"venue"
},
  "geometry": {"coordinates":[-80.06365,26.659823],"type":"Point"}
}