{
  "type": "Feature",
  "properties": {
    "iso:country":"US",
    "sg:address":"320 Racetrack Rd NW",
    "sg:city":"Fort Walton Beach",
    "sg:classifiers":[
        {
            "category":"Professional",
            "subcategory":"Advertising",
            "type":"Services"
        }
    ],
    "sg:phone":"+1 850 863 5322",
    "sg:postcode":"32547",
    "sg:province":"FL",
    "sg:tags":[
        "representative"
    ],
    "wof:name":"Cablerep Advertising",
    "wof:placetype":"venue"
},
  "geometry": {"coordinates":[-86.628505,30.449434],"type":"Point"}
}