{
  "type": "Feature",
  "properties": {
    "iso:country":"US",
    "sg:address":"831 NW 151st St",
    "sg:city":"Miami",
    "sg:classifiers":[
        {
            "category":"Education",
            "subcategory":"School",
            "type":"Public Place"
        }
    ],
    "sg:phone":"+1 305 685 5399",
    "sg:postcode":"33169",
    "sg:province":"FL",
    "sg:tags":[
        "k-",
        "private"
    ],
    "wof:name":"Atlantic Southeastern Academy Inc",
    "wof:placetype":"venue"
},
  "geometry": {"coordinates":[-80.213874,25.912924],"type":"Point"}
}