{
  "type": "Feature",
  "properties": {
    "iso:country":"US",
    "sg:address":"420 Lanark St",
    "sg:city":"Sanford",
    "sg:classifiers":[
        {
            "category":"Building & Trades",
            "subcategory":"Landscaping Services",
            "type":"Services"
        }
    ],
    "sg:phone":"+1 407 321 5076",
    "sg:postcode":"32773",
    "sg:province":"FL",
    "sg:tags":[
        "lawn",
        "maintenance",
        "grounds"
    ],
    "wof:name":"Alvin W Kilgore Lawn Svc",
    "wof:placetype":"venue"
},
  "geometry": {"coordinates":[-81.27778600000001,28.731153],"type":"Point"}
}