{
  "type": "Feature",
  "properties": {
    "iso:country":"US",
    "sg:address":"31980 US Hwy 19 N",
    "sg:city":"Palm Harbor",
    "sg:classifiers":[
        {
            "category":"Health Services",
            "subcategory":"Doctor",
            "type":"Services"
        }
    ],
    "sg:phone":"+1 727 772 1120",
    "sg:postcode":"34684",
    "sg:province":"FL",
    "sg:tags":[
        "dentist"
    ],
    "wof:name":"Family Dental Care",
    "wof:placetype":"venue"
},
  "geometry": {"coordinates":[-82.738967,28.064807],"type":"Point"}
}