{
  "type": "Feature",
  "properties": {
    "iso:country":"US",
    "sg:address":"5285 NW 70th Ave",
    "sg:city":"Fort Lauderdale",
    "sg:classifiers":[
        {
            "category":"Organizations",
            "subcategory":"Religious Organization",
            "type":"Services"
        }
    ],
    "sg:phone":"+1 954 533 5661",
    "sg:postcode":"33319",
    "sg:province":"FL",
    "sg:tags":[
        "profit",
        "education",
        "church"
    ],
    "wof:name":"Frankie Walls Ministries",
    "wof:placetype":"venue"
},
  "geometry": {"coordinates":[-80.24436300000001,26.191504],"type":"Point"}
}