{
  "type": "Feature",
  "properties": {
    "iso:country":"US",
    "sg:address":"300 Lock Rd",
    "sg:city":"Deerfield Beach",
    "sg:classifiers":[
        {
            "category":"Government",
            "subcategory":"Office",
            "type":"Public Place"
        }
    ],
    "sg:phone":"+1 954 421 9183",
    "sg:postcode":"33442",
    "sg:province":"FL",
    "sg:tags":[
        "federal",
        "taxation"
    ],
    "wof:name":"US Internal Revenue Svc",
    "wof:placetype":"venue"
},
  "geometry": {"coordinates":[-80.126344,26.324061],"type":"Point"}
}