{
  "type": "Feature",
  "properties": {
    "addr:full":"6741 Panther Ln Fort Myers FL 33919",
    "addr:housenumber":"6741",
    "addr:postcode":"33919",
    "addr:street":"Panther Ln",
    "iso:country":"US",
    "sg:address":"6741 Panther Ln",
    "sg:city":"Fort Myers",
    "sg:classifiers":[
        {
            "category":"Professional",
            "subcategory":"Business Services",
            "type":"Services"
        }
    ],
    "sg:phone":"+1 239 482 1206",
    "sg:postcode":"33919",
    "sg:province":"FL",
    "sg:tags":[
        "interior",
        "consultant",
        "design",
        "decorator"
    ],
    "wof:name":"Bonnie Murrie Interiors",
    "wof:placetype":"venue"
},
  "geometry": {"coordinates":[-81.900537,26.540679],"type":"Point"}
}