{
  "type": "Feature",
  "properties": {
    "iso:country":"US",
    "sg:address":"1785 Windsor Gate E",
    "sg:city":"Clearwater",
    "sg:classifiers":[
        {
            "category":"Building & Trades",
            "subcategory":"Landscaping Services",
            "type":"Services"
        },
        {
            "category":"Utilities",
            "subcategory":"Water",
            "type":"Services"
        },
        {
            "category":"Retail",
            "subcategory":"Repair Shop",
            "type":"Services"
        },
        {
            "category":"Wholesale",
            "subcategory":"Machinery & Supplies",
            "type":"Manufacturing & Wholesale Goods"
        },
        {
            "category":"Home & Garden",
            "subcategory":"Garden Supply",
            "type":"Retail Goods"
        }
    ],
    "sg:phone":"+1 727 443 7268",
    "sg:postcode":"33755",
    "sg:province":"FL",
    "sg:tags":[
        "lawn",
        "installation",
        "sprinklers-garden",
        "well",
        "irrigation",
        "system",
        "equipment",
        "pump",
        "drilling",
        "pumps-service",
        "contractor"
    ],
    "sg:website":"http://www.a1irrigation.com",
    "wof:name":"A -1 Irrigation Inc",
    "wof:placetype":"venue"
},
  "geometry": {"coordinates":[-82.76325900000001,27.995316],"type":"Point"}
}