{
  "type": "Feature",
  "properties": {
    "iso:country":"US",
    "sg:address":"2540 SW 12th Pl",
    "sg:city":"Cape Coral",
    "sg:classifiers":[
        {
            "category":"Building & Trades",
            "subcategory":"Landscaping Services",
            "type":"Services"
        }
    ],
    "sg:phone":"+1 239 574 0974",
    "sg:postcode":"33914",
    "sg:province":"FL",
    "sg:tags":[
        "landscape"
    ],
    "wof:name":"Martin Craig Wall Covering",
    "wof:placetype":"venue"
},
  "geometry": {"coordinates":[-82.000874,26.604758],"type":"Point"}
}