{
  "type": "Feature",
  "properties": {
    "addr:full":"3318 S West Shore Blvd Tampa FL 33629",
    "addr:housenumber":"3318",
    "addr:postcode":"33629",
    "addr:street":"S West Shore Blvd",
    "iso:country":"US",
    "sg:address":"3318 S West Shore Blvd",
    "sg:city":"Tampa",
    "sg:classifiers":[
        {
            "category":"Building & Trades",
            "subcategory":"Equipment Rental",
            "type":"Services"
        }
    ],
    "sg:phone":"+1 813 831 4731",
    "sg:postcode":"33629",
    "sg:province":"FL",
    "sg:tags":[
        "yard"
    ],
    "wof:name":"Rug Doctor",
    "wof:placetype":"venue"
},
  "geometry": {"coordinates":[-82.52669899999999,27.913971],"type":"Point"}
}