{
  "type": "Feature",
  "properties": {
    "iso:country":"US",
    "sg:address":"944 Collins Ave",
    "sg:city":"Miami Beach",
    "sg:classifiers":[
        {
            "category":"Travel",
            "subcategory":"Hotels & Motels",
            "type":"Entertainment"
        }
    ],
    "sg:phone":"+1 305 673 2262",
    "sg:postcode":"33139",
    "sg:province":"FL",
    "sg:website":"www.bluemoonhotel.com",
    "wof:name":"Blue Moon Hotel & Bar",
    "wof:placetype":"venue"
},
  "geometry": {"coordinates":[-80.131699,25.7799],"type":"Point"}
}