{
  "type": "Feature",
  "properties": {
    "addr:full":"36002 Emeralda Ave Leesburg FL 34788",
    "addr:postcode":"36002;34788",
    "addr:street":"Emeralda Ave",
    "iso:country":"US",
    "sg:address":"36002 Emeralda Ave",
    "sg:city":"Leesburg",
    "sg:classifiers":[
        {
            "category":"Autos & Motor Vehicles",
            "subcategory":"Fuel & Gas Station",
            "type":"Retail Goods"
        }
    ],
    "sg:phone":"+1 352 365 2877",
    "sg:postcode":"34788",
    "sg:province":"FL",
    "sg:tags":[
        "grocery",
        "gasoline"
    ],
    "wof:name":"Island Foods",
    "wof:placetype":"venue"
},
  "geometry": {"coordinates":[-81.782444,28.873704],"type":"Point"}
}