{
  "type": "Feature",
  "properties": {
    "iso:country":"US",
    "sg:address":"10416 Captain Hook Cir",
    "sg:city":"Thonotosassa",
    "sg:classifiers":[
        {
            "category":"Building & Trades",
            "subcategory":"Construction",
            "type":"Services"
        }
    ],
    "sg:phone":"+1 813 986 6322",
    "sg:postcode":"33592",
    "sg:province":"FL",
    "sg:tags":[
        "painter"
    ],
    "wof:name":"William W Docherty",
    "wof:placetype":"venue"
},
  "geometry": {"coordinates":[-82.305198,28.064597],"type":"Point"}
}