{
  "type": "Feature",
  "properties": {
    "addr:full":"1425 Tomoka Farms Rd Daytona Beach FL 32124",
    "addr:postcode":"1425;32124",
    "addr:street":"Tomoka Farms Rd",
    "iso:country":"US",
    "sg:address":"1425 Tomoka Farms Rd",
    "sg:city":"Daytona Beach",
    "sg:classifiers":[
        {
            "category":"Shopping",
            "subcategory":"Clothing, Apparel, & Fashions",
            "type":"Retail Goods"
        }
    ],
    "sg:phone":"+1 386 252 0919",
    "sg:postcode":"32124",
    "sg:province":"FL",
    "wof:name":"Fashion Fair",
    "wof:placetype":"venue"
},
  "geometry": {"coordinates":[-81.083433,29.15407],"type":"Point"}
}