{
  "type": "Feature",
  "properties": {
    "iso:country":"US",
    "sg:address":"3402 Lithia Pinecrest Rd",
    "sg:city":"Valrico",
    "sg:classifiers":[
        {
            "category":"Banks & Credit Unions",
            "subcategory":"Bank",
            "type":"Services"
        }
    ],
    "sg:phone":"+1 813 654 4464",
    "sg:postcode":"33596",
    "sg:province":"FL",
    "sg:tags":[
        "saving",
        "commercial"
    ],
    "sg:website":"http://www.fifththird.com",
    "wof:name":"First National Bank",
    "wof:placetype":"venue"
},
  "geometry": {"coordinates":[-82.243652,27.893486],"type":"Point"}
}