{
  "type": "Feature",
  "properties": {
    "iso:country":"US",
    "sg:address":"2707 Westhigh Ave",
    "sg:city":"Tampa",
    "sg:classifiers":[
        {
            "category":"Building & Trades",
            "subcategory":"Landscaping Services",
            "type":"Services"
        }
    ],
    "sg:phone":"+1 813 933 6012",
    "sg:postcode":"33614",
    "sg:province":"FL",
    "wof:name":"Charles M Reid",
    "wof:placetype":"venue"
},
  "geometry": {"coordinates":[-82.48741800000001,28.02144],"type":"Point"}
}