{
  "type": "Feature",
  "properties": {
    "iso:country":"US",
    "sg:address":"5501 NW 7th St Apt E114",
    "sg:city":"Miami",
    "sg:classifiers":[
        {
            "category":"Structure",
            "subcategory":"Warehouse",
            "type":"Public Place"
        }
    ],
    "sg:phone":"+1 786 216 3587",
    "sg:postcode":"33126",
    "sg:province":"FL",
    "sg:tags":[
        "warehouses-merchandise",
        "warehouses-public-commercial"
    ],
    "wof:name":"Malcuni Custom Contract Inc",
    "wof:placetype":"venue"
},
  "geometry": {"coordinates":[-80.284971,25.778147],"type":"Point"}
}