{
  "type": "Feature",
  "properties": {
    "addr:full":"6200 Porter Rd Sarasota FL 34240",
    "addr:housenumber":"6200",
    "addr:postcode":"34240",
    "addr:street":"Porter Rd",
    "iso:country":"US",
    "sg:address":"6200 Porter Rd",
    "sg:city":"Sarasota",
    "sg:classifiers":[
        {
            "category":"Manufacturing",
            "subcategory":"Metals",
            "type":"Manufacturing & Wholesale Goods"
        }
    ],
    "sg:phone":"+1 941 371 8110",
    "sg:postcode":"34240",
    "sg:province":"FL",
    "sg:tags":[
        "glass",
        "product",
        "mfg"
    ],
    "wof:name":"Styleline Doors",
    "wof:placetype":"venue"
},
  "geometry": {"coordinates":[-82.446066,27.318517],"type":"Point"}
}