{
  "type": "Feature",
  "properties": {
    "addr:full":"5800 Firestone Rd Jacksonville FL 32244",
    "addr:housenumber":"5800",
    "addr:postcode":"32244",
    "addr:street":"Firestone Rd",
    "iso:country":"US",
    "sg:address":"5800 Firestone Rd",
    "sg:city":"Jacksonville",
    "sg:classifiers":[
        {
            "category":"Building & Trades",
            "subcategory":"Construction",
            "type":"Services"
        }
    ],
    "sg:phone":"+1 904 778 8352",
    "sg:postcode":"32244",
    "sg:province":"FL",
    "sg:tags":[
        "general",
        "contractor"
    ],
    "wof:name":"R G White Construction",
    "wof:placetype":"venue"
},
  "geometry": {"coordinates":[-81.764619,30.24347],"type":"Point"}
}