{
  "type": "Feature",
  "properties": {
    "addr:full":"4111 NW 27th St Miami FL 33142",
    "addr:housenumber":"4111",
    "addr:postcode":"33142",
    "addr:street":"Nw 27Th St",
    "iso:country":"US",
    "sg:address":"4111 NW 27th St",
    "sg:city":"Miami",
    "sg:classifiers":[
        {
            "category":"Professional",
            "subcategory":"Business Services",
            "type":"Services"
        }
    ],
    "sg:phone":"+1 305 871 6944",
    "sg:postcode":"33142",
    "sg:province":"FL",
    "sg:tags":[
        "delivery",
        "courier"
    ],
    "sg:website":"www.shipgreyhound.com",
    "wof:name":"Greyhound Package Express",
    "wof:placetype":"venue"
},
  "geometry": {"coordinates":[-80.263603,25.8001],"type":"Point"}
}