{
  "type": "Feature",
  "properties": {
    "iso:country":"US",
    "sg:address":"3199 Commodore Plaza",
    "sg:city":"Miami",
    "sg:classifiers":[
        {
            "category":"Personal",
            "subcategory":"Day Spa",
            "type":"Services"
        }
    ],
    "sg:phone":"+1 786 360 3309",
    "sg:postcode":"33133",
    "sg:province":"FL",
    "sg:website":"www.coiffureandnature.com",
    "wof:name":"Coiffure & Nature",
    "wof:placetype":"venue"
},
  "geometry": {"coordinates":[-80.245074,25.727983],"type":"Point"}
}