{
  "type": "Feature",
  "properties": {
    "addr:full":"637 Southern Lily Dr Jacksonville FL 32259",
    "addr:housenumber":"637",
    "addr:postcode":"32259",
    "addr:street":"Southern Lily Dr",
    "iso:country":"US",
    "sg:address":"637 Southern Lily Dr",
    "sg:city":"Jacksonville",
    "sg:classifiers":[
        {
            "category":"Organizations",
            "subcategory":"Religious Organization",
            "type":"Services"
        }
    ],
    "sg:phone":"+1 904 287 0415",
    "sg:postcode":"32259",
    "sg:province":"FL",
    "sg:tags":[
        "church"
    ],
    "wof:name":"Church The Village Baptist",
    "wof:placetype":"venue"
},
  "geometry": {"coordinates":[-81.52940599999999,30.062459],"type":"Point"}
}