{
  "type": "Feature",
  "properties": {
    "addr:full":"4500 SW 34th Dr Fort Lauderdale FL 33312",
    "addr:housenumber":"4500",
    "addr:postcode":"33312",
    "addr:street":"Sw 34Th Dr",
    "iso:country":"US",
    "sg:address":"4500 SW 34th Dr",
    "sg:city":"Fort Lauderdale",
    "sg:classifiers":[
        {
            "category":"Freight",
            "type":"Transportation"
        }
    ],
    "sg:phone":"+1 954 964 3906",
    "sg:postcode":"33312",
    "sg:province":"FL",
    "sg:tags":[
        "consultant",
        "ship",
        "marine",
        "broker"
    ],
    "wof:name":"Navigar Inc",
    "wof:placetype":"venue"
},
  "geometry": {"coordinates":[-80.18984,26.06341],"type":"Point"}
}