{
  "type": "Feature",
  "properties": {
    "addr:full":"328 W Brandon Blvd Brandon FL 33511",
    "addr:housenumber":"328",
    "addr:postcode":"33511",
    "addr:street":"W Brandon Blvd",
    "iso:country":"US",
    "sg:address":"328 W Brandon Blvd",
    "sg:city":"Brandon",
    "sg:classifiers":[
        {
            "category":"Retail",
            "subcategory":"Car Wash",
            "type":"Services"
        }
    ],
    "sg:phone":"+1 813 662 2404",
    "sg:postcode":"33511",
    "sg:province":"FL",
    "sg:tags":[
        "carwash",
        "station",
        "gasoline"
    ],
    "wof:name":"Brandon Grand Prix",
    "wof:placetype":"venue"
},
  "geometry": {"coordinates":[-82.28949,27.937815],"type":"Point"}
}