{
  "type": "Feature",
  "properties": {
    "addr:full":"3658 Lone Pine Rd Delray Beach FL 33445",
    "addr:housenumber":"3658",
    "addr:postcode":"33445",
    "addr:street":"Lone Pine Rd",
    "iso:country":"US",
    "sg:address":"3658 Lone Pine Rd",
    "sg:city":"Delray Beach",
    "sg:classifiers":[
        {
            "category":"Professional",
            "subcategory":"Business Services",
            "type":"Services"
        }
    ],
    "sg:phone":"+1 561 265 2431",
    "sg:postcode":"33445",
    "sg:province":"FL",
    "wof:name":"J D F Enterprises",
    "wof:placetype":"venue"
},
  "geometry": {"coordinates":[-80.10033799999999,26.482664],"type":"Point"}
}