{
  "type": "Feature",
  "properties": {
    "iso:country":"US",
    "sg:address":"156 Crescent Dr",
    "sg:city":"Defuniak Springs",
    "sg:classifiers":[
        {
            "category":"Social Services",
            "subcategory":"Child Care",
            "type":"Services"
        }
    ],
    "sg:phone":"+1 850 892 0533",
    "sg:postcode":"32435",
    "sg:province":"FL",
    "wof:name":"First Baptist Church Preschool",
    "wof:placetype":"venue"
},
  "geometry": {"coordinates":[-86.116713,30.718484],"type":"Point"}
}