{
  "type": "Feature",
  "properties": {
    "iso:country":"US",
    "sg:address":"1962 Crystal Downs Ct",
    "sg:city":"Oviedo",
    "sg:classifiers":[
        {
            "category":"Real Estate",
            "subcategory":"Real Estate Agent",
            "type":"Services"
        }
    ],
    "sg:phone":"+1 407 365 7959",
    "sg:postcode":"32765",
    "sg:province":"FL",
    "wof:name":"Real Hero Foundation",
    "wof:placetype":"venue"
},
  "geometry": {"coordinates":[-81.170406,28.641485],"type":"Point"}
}