{
  "type": "Feature",
  "properties": {
    "addr:full":"1380 S Federal Hwy Pompano Beach FL 33062",
    "addr:housenumber":"1380",
    "addr:postcode":"33062",
    "addr:street":"S Federal Hwy",
    "iso:country":"US",
    "sg:address":"1380 S Federal Hwy",
    "sg:city":"Pompano Beach",
    "sg:classifiers":[
        {
            "category":"Autos & Motor Vehicles",
            "subcategory":"Automobile Sales",
            "type":"Retail Goods"
        }
    ],
    "sg:phone":"+1 954 946 2010",
    "sg:postcode":"33062",
    "sg:province":"FL",
    "sg:tags":[
        "used"
    ],
    "wof:name":"Corvette Store",
    "wof:placetype":"venue"
},
  "geometry": {"coordinates":[-80.106487,26.213067],"type":"Point"}
}