{
  "type": "Feature",
  "properties": {
    "addr:full":"1951 NE 163rd St North Miami Beach FL 33162",
    "addr:housenumber":"1951",
    "addr:postcode":"33162",
    "addr:street":"Ne 163Rd St",
    "iso:country":"US",
    "sg:address":"1951 NE 163rd St",
    "sg:city":"North Miami Beach",
    "sg:classifiers":[
        {
            "category":"Shopping",
            "subcategory":"Bicycles & Sporting Goods",
            "type":"Retail Goods"
        }
    ],
    "sg:phone":"+1 305 940 1050",
    "sg:postcode":"33162",
    "sg:province":"FL",
    "sg:tags":[
        "bike"
    ],
    "wof:name":"Bell's Bicycles & Repair",
    "wof:placetype":"venue"
},
  "geometry": {"coordinates":[-80.16091299999999,25.926076],"type":"Point"}
}