{
  "type": "Feature",
  "properties": {
    "iso:country":"US",
    "sg:address":"1432 Cleveland St",
    "sg:city":"Jacksonville",
    "sg:phone":"+1 904 356 0731",
    "sg:postcode":"32209",
    "sg:province":"FL",
    "sg:tags":[
        "oil"
    ],
    "wof:name":"H R Lewis Petroleum Co",
    "wof:placetype":"venue"
},
  "geometry": {"coordinates":[-81.670875,30.342509],"type":"Point"}
}