{
  "type": "Feature",
  "properties": {
    "iso:country":"US",
    "sg:address":"1200 Victoria Dr",
    "sg:city":"West Palm Beach",
    "sg:classifiers":[
        {
            "category":"Utilities",
            "subcategory":"Refuse",
            "type":"Services"
        }
    ],
    "sg:phone":"+1 561 965 6678",
    "sg:postcode":"33406",
    "sg:province":"FL",
    "sg:tags":[
        "garbage",
        "collection"
    ],
    "wof:name":"Bobcat Service/We Haul It All",
    "wof:placetype":"venue"
},
  "geometry": {"coordinates":[-80.092664,26.658413],"type":"Point"}
}