{
  "type": "Feature",
  "properties": {
    "iso:country":"US",
    "sg:address":"10991 San Jose Blvd",
    "sg:city":"Jacksonville",
    "sg:classifiers":[
        {
            "category":"Shopping",
            "subcategory":"Shoes",
            "type":"Retail Goods"
        }
    ],
    "sg:phone":"+1 904 268 7105",
    "sg:postcode":"32223",
    "sg:province":"FL",
    "wof:name":"Payless Shoe Source",
    "wof:placetype":"venue"
},
  "geometry": {"coordinates":[-81.627765,30.175836],"type":"Point"}
}