{
  "type": "Feature",
  "properties": {
    "iso:country":"US",
    "sg:address":"741 SE 17th St",
    "sg:city":"Fort Lauderdale",
    "sg:classifiers":[
        {
            "category":"Restaurant",
            "type":"Food & Drink"
        }
    ],
    "sg:menulink":"http://www.allmenus.com/fl/fort-lauderdale/15904-bistro-mezzaluna/menu/",
    "sg:phone":"+1 954 522 9191",
    "sg:postcode":"33316",
    "sg:province":"FL",
    "sg:tags":[
        "american"
    ],
    "wof:name":"Bistro Mezzaluna",
    "wof:placetype":"venue"
},
  "geometry": {"coordinates":[-80.135513,26.100289],"type":"Point"}
}