{
  "type": "Feature",
  "properties": {
    "iso:country":"US",
    "sg:address":"1701 SW 6th St",
    "sg:city":"Miami",
    "sg:classifiers":[
        {
            "category":"Building & Trades",
            "subcategory":"Locksmith",
            "type":"Services"
        }
    ],
    "sg:phone":"+1 305 423 3649",
    "sg:postcode":"33135",
    "sg:province":"FL",
    "sg:tags":[
        "key"
    ],
    "wof:name":"AAA Locksmith 24 Hour",
    "wof:placetype":"venue"
},
  "geometry": {"coordinates":[-80.22258100000001,25.767577],"type":"Point"}
}