{
  "type": "Feature",
  "properties": {
    "iso:country":"US",
    "sg:address":"700 S Harbour Island Blvd",
    "sg:city":"Tampa",
    "sg:phone":"+1 813 229 2500",
    "sg:postcode":"33602",
    "sg:province":"FL",
    "wof:name":"Parkcrest Harbor Island",
    "wof:placetype":"venue"
},
  "geometry": {"coordinates":[-82.453424,27.937375],"type":"Point"}
}