{
  "type": "Feature",
  "properties": {
    "addr:full":"3641 S Miami Ave Miami FL 33133",
    "addr:housenumber":"3641",
    "addr:postcode":"33133",
    "addr:street":"S Miami Ave",
    "iso:country":"US",
    "sg:address":"3641 S Miami Ave",
    "sg:city":"Miami",
    "sg:classifiers":[
        {
            "category":"Health Services",
            "subcategory":"Clinic",
            "type":"Services"
        },
        {
            "category":"Health Services",
            "subcategory":"Hospital",
            "type":"Services"
        }
    ],
    "sg:phone":"+1 305 285 2922",
    "sg:postcode":"33133",
    "sg:province":"FL",
    "sg:tags":[
        "laboratory",
        "medical",
        "specialty",
        "outpatient"
    ],
    "sg:website":"www.mercymiami.com",
    "wof:name":"Mercy Outpatient Center",
    "wof:placetype":"venue"
},
  "geometry": {"coordinates":[-80.21623599999999,25.743182],"type":"Point"}
}