{
  "type": "Feature",
  "properties": {
    "iso:country":"US",
    "sg:address":"6939 SW 109th Pl",
    "sg:city":"Miami",
    "sg:classifiers":[
        {
            "category":"Home & Garden",
            "subcategory":"Carpets & Floor Coverings",
            "type":"Retail Goods"
        }
    ],
    "sg:phone":"+1 786 357 8662",
    "sg:postcode":"33173",
    "sg:province":"FL",
    "sg:tags":[
        "flooring",
        "contractor"
    ],
    "wof:name":"JC Floors",
    "wof:placetype":"venue"
},
  "geometry": {"coordinates":[-80.37120400000001,25.703207],"type":"Point"}
}