{
  "type": "Feature",
  "properties": {
    "iso:country":"US",
    "sg:address":"12953 Palms West Dr",
    "sg:city":"Loxahatchee",
    "sg:phone":"+1 561 795 2400",
    "sg:postcode":"33470",
    "sg:province":"FL",
    "wof:name":"Palms West OBGYN Assc",
    "wof:placetype":"venue"
},
  "geometry": {"coordinates":[-80.250606,26.68303],"type":"Point"}
}