{
  "type": "Feature",
  "properties": {
    "addr:full":"201 NW 1st Ave Hallandale FL 33009",
    "addr:housenumber":"201",
    "addr:postcode":"33009",
    "addr:street":"Nw 1St Ave",
    "iso:country":"US",
    "sg:address":"201 NW 1st Ave",
    "sg:city":"Hallandale",
    "sg:classifiers":[
        {
            "category":"Building & Trades",
            "subcategory":"Construction",
            "type":"Services"
        }
    ],
    "sg:phone":"+1 954 923 0880",
    "sg:postcode":"33009",
    "sg:province":"FL",
    "sg:tags":[
        "contracting"
    ],
    "wof:name":"April One Inc",
    "wof:placetype":"venue"
},
  "geometry": {"coordinates":[-80.14946500000001,25.989131],"type":"Point"}
}