{
  "type": "Feature",
  "properties": {
    "iso:country":"US",
    "sg:address":"2122 Park Pl",
    "sg:city":"Boca Raton",
    "sg:classifiers":[
        {
            "category":"Farming",
            "subcategory":"Farm",
            "type":"Manufacturing & Wholesale Goods"
        }
    ],
    "sg:phone":"+1 561 394 2636",
    "sg:postcode":"33486",
    "sg:province":"FL",
    "sg:tags":[
        "crop",
        "general"
    ],
    "wof:name":"Idea Farm Inc",
    "wof:placetype":"venue"
},
  "geometry": {"coordinates":[-80.12858300000001,26.3565],"type":"Point"}
}