{
  "type": "Feature",
  "properties": {
    "addr:full":"203 Pelham Rd Fort Walton Bch FL 32547",
    "addr:housenumber":"203",
    "addr:postcode":"32547",
    "addr:street":"Pelham Rd",
    "iso:country":"US",
    "sg:address":"203 Pelham Rd",
    "sg:city":"Fort Walton Bch",
    "sg:classifiers":[
        {
            "category":"Building & Trades",
            "subcategory":"Construction",
            "type":"Services"
        }
    ],
    "sg:phone":"+1 850 862 5376",
    "sg:postcode":"32547",
    "sg:province":"FL",
    "sg:tags":[
        "general",
        "contractor"
    ],
    "wof:name":"NWF Contractors Inc",
    "wof:placetype":"venue"
},
  "geometry": {"coordinates":[-86.637811,30.434945],"type":"Point"}
}