{
  "type": "Feature",
  "properties": {
    "iso:country":"US",
    "sg:address":"107 Hampton Rd",
    "sg:city":"Clearwater",
    "sg:classifiers":[
        {
            "category":"Real Estate",
            "subcategory":"Real Estate Agent",
            "type":"Services"
        }
    ],
    "sg:phone":"+1 727 726 4770",
    "sg:postcode":"33759",
    "sg:province":"FL",
    "sg:tags":[
        "management"
    ],
    "wof:name":"Provident Management Corp",
    "wof:placetype":"venue"
},
  "geometry": {"coordinates":[-82.721424,27.963329],"type":"Point"}
}