{
  "type": "Feature",
  "properties": {
    "iso:country":"US",
    "sg:address":"2950 SW 3rd Ave",
    "sg:city":"Miami",
    "sg:classifiers":[
        {
            "category":"Organizations",
            "subcategory":"Community Association",
            "type":"Services"
        }
    ],
    "sg:phone":"+1 305 854 7829",
    "sg:postcode":"33129",
    "sg:province":"FL",
    "sg:tags":[
        "condominium"
    ],
    "wof:name":"Coral Way Tower Condominiums",
    "wof:placetype":"venue"
},
  "geometry": {"coordinates":[-80.21127799999999,25.753361],"type":"Point"}
}