{
  "type": "Feature",
  "properties": {
    "iso:country":"US",
    "sg:address":"17210 Panama City Beach Pkwy",
    "sg:city":"Panama City",
    "sg:classifiers":[
        {
            "category":"Banks & Credit Unions",
            "subcategory":"Investment Brokerage",
            "type":"Services"
        }
    ],
    "sg:phone":"+1 850 233 2089",
    "sg:postcode":"32413",
    "sg:province":"FL",
    "sg:tags":[
        "security"
    ],
    "wof:name":"Edward Jones Investments",
    "wof:placetype":"venue"
},
  "geometry": {"coordinates":[-85.900029,30.234256],"type":"Point"}
}