{
  "type": "Feature",
  "properties": {
    "iso:country":"US",
    "sg:address":"6024 26th St W",
    "sg:city":"Bradenton",
    "sg:classifiers":[
        {
            "category":"Education",
            "subcategory":"School",
            "type":"Public Place"
        }
    ],
    "sg:phone":"+1 941 753 4987",
    "sg:postcode":"34207",
    "sg:province":"FL",
    "wof:name":"Center For Education",
    "wof:placetype":"venue"
},
  "geometry": {"coordinates":[-82.587701,27.435848],"type":"Point"}
}