{
  "type": "Feature",
  "properties": {
    "iso:country":"US",
    "sg:address":"2207 E Hillsborough Ave",
    "sg:city":"Tampa",
    "sg:classifiers":[
        {
            "category":"Shopping",
            "subcategory":"Gifts & Souvenirs",
            "type":"Retail Goods"
        }
    ],
    "sg:phone":"+1 813 236 3301",
    "sg:postcode":"33610",
    "sg:province":"FL",
    "sg:tags":[
        "collectible"
    ],
    "wof:name":"African & American Hut",
    "wof:placetype":"venue"
},
  "geometry": {"coordinates":[-82.431442,27.995989],"type":"Point"}
}