{
  "type": "Feature",
  "properties": {
    "addr:full":"627 Hoffner Ave Orlando FL 32809",
    "addr:housenumber":"627",
    "addr:postcode":"32809",
    "addr:street":"Hoffner Ave",
    "iso:country":"US",
    "sg:address":"627 Hoffner Ave",
    "sg:city":"Orlando",
    "sg:classifiers":[
        {
            "category":"Restaurant",
            "type":"Food & Drink"
        }
    ],
    "sg:phone":"+1 407 852 5890",
    "sg:postcode":"32809",
    "sg:province":"FL",
    "wof:name":"New Chinese House",
    "wof:placetype":"venue"
},
  "geometry": {"coordinates":[-81.368005,28.475301],"type":"Point"}
}