{
  "type": "Feature",
  "properties": {
    "addr:full":"8395 NW 53rd St Miami FL 33166",
    "addr:housenumber":"8395",
    "addr:postcode":"33166",
    "addr:street":"Nw 53Rd St",
    "iso:country":"US",
    "sg:address":"8395 NW 53rd St",
    "sg:city":"Miami",
    "sg:classifiers":[
        {
            "category":"Wholesale",
            "subcategory":"Seafood",
            "type":"Manufacturing & Wholesale Goods"
        }
    ],
    "sg:phone":"+1 305 477 9942",
    "sg:postcode":"33166",
    "sg:province":"FL",
    "wof:name":"Stolt Sea Farm Inc",
    "wof:placetype":"venue"
},
  "geometry": {"coordinates":[-80.33404400000001,25.82007],"type":"Point"}
}