{
  "type": "Feature",
  "properties": {
    "iso:country":"US",
    "sg:address":"2025 Indian Rocks Rd",
    "sg:city":"Largo",
    "sg:classifiers":[
        {
            "category":"Health Services",
            "subcategory":"Doctor",
            "type":"Services"
        }
    ],
    "sg:phone":"+1 727 586 7124",
    "sg:postcode":"33774",
    "sg:province":"FL",
    "sg:tags":[
        "physician",
        "surgeon"
    ],
    "wof:name":"Pepin Heart & Vascular Inst",
    "wof:placetype":"venue"
},
  "geometry": {"coordinates":[-82.82623100000001,27.898181],"type":"Point"}
}