{
  "type": "Feature",
  "properties": {
    "iso:country":"US",
    "sg:address":"6175 NW 167th St",
    "sg:city":"Hialeah",
    "sg:classifiers":[
        {
            "category":"Wholesale",
            "subcategory":"Medical Equipment & Supplies",
            "type":"Manufacturing & Wholesale Goods"
        },
        {
            "category":"Retail",
            "subcategory":"Repair Shop",
            "type":"Services"
        }
    ],
    "sg:phone":"+1 305 826 7118",
    "sg:postcode":"33015",
    "sg:province":"FL",
    "sg:tags":[
        "x-ray",
        "apparatus"
    ],
    "wof:name":"Sunrise X-Ray Inc",
    "wof:placetype":"venue"
},
  "geometry": {"coordinates":[-80.298198,25.925131],"type":"Point"}
}