{
  "type": "Feature",
  "properties": {
    "iso:country":"US",
    "sg:address":"141 Fishermans Way",
    "sg:city":"Jupiter",
    "sg:classifiers":[
        {
            "category":"Wholesale",
            "subcategory":"Sporting Goods",
            "type":"Manufacturing & Wholesale Goods"
        }
    ],
    "sg:phone":"+1 561 748 2551",
    "sg:postcode":"33477",
    "sg:province":"FL",
    "sg:tags":[
        "boat"
    ],
    "sg:website":"www.internationalnautic.com",
    "wof:name":"International Nautic Corp",
    "wof:placetype":"venue"
},
  "geometry": {"coordinates":[-80.08645,26.936125],"type":"Point"}
}