{
  "type": "Feature",
  "properties": {
    "iso:country":"US",
    "sg:address":"26428 Co Rd 44A",
    "sg:city":"Eustis",
    "sg:classifiers":[
        {
            "category":"Building & Trades",
            "subcategory":"Construction",
            "type":"Services"
        }
    ],
    "sg:phone":"+1 352 357 2245",
    "sg:postcode":"32736",
    "sg:province":"FL",
    "sg:tags":[
        "concrete",
        "contractor"
    ],
    "wof:name":"W & S Concrete",
    "wof:placetype":"venue"
},
  "geometry": {"coordinates":[-81.51916,28.876835],"type":"Point"}
}