{
  "type": "Feature",
  "properties": {
    "iso:country":"US",
    "sg:address":"133 Marine St",
    "sg:city":"Saint Augustine",
    "sg:classifiers":[
        {
            "category":"Real Estate",
            "subcategory":"Architect",
            "type":"Services"
        }
    ],
    "sg:phone":"+1 904 825 1266",
    "sg:postcode":"32084",
    "sg:province":"FL",
    "sg:tags":[
        "architectural"
    ],
    "wof:name":"Crg Archtects Plnrs St Augstne",
    "wof:placetype":"venue"
},
  "geometry": {"coordinates":[-81.30894000000001,29.884471],"type":"Point"}
}