{
  "type": "Feature",
  "properties": {
    "iso:country":"US",
    "sg:address":"1840 NE 39th Blvd",
    "sg:city":"Okeechobee",
    "sg:classifiers":[
        {
            "category":"Organizations",
            "subcategory":"Religious Organization",
            "type":"Services"
        }
    ],
    "sg:phone":"+1 863 763 4962",
    "sg:postcode":"34972",
    "sg:province":"FL",
    "sg:tags":[
        "church"
    ],
    "wof:name":"Trinity Freewill Baptist Ch",
    "wof:placetype":"venue"
},
  "geometry": {"coordinates":[-80.813016,27.291224],"type":"Point"}
}