{
  "type": "Feature",
  "properties": {
    "iso:country":"US",
    "sg:address":"1202 Pine Ave",
    "sg:city":"Orlando",
    "sg:classifiers":[
        {
            "category":"Freight",
            "type":"Transportation"
        }
    ],
    "sg:phone":"+1 407 855 9537",
    "sg:postcode":"32824",
    "sg:province":"FL",
    "sg:tags":[
        "operator",
        "trucking"
    ],
    "wof:name":"Hansen & Adkins Auto Transport",
    "wof:placetype":"venue"
},
  "geometry": {"coordinates":[-81.363079,28.441747],"type":"Point"}
}