{
  "type": "Feature",
  "properties": {
    "iso:country":"US",
    "sg:address":"7820 Callan Ct",
    "sg:city":"New Port Richey",
    "sg:classifiers":[
        {
            "category":"Building & Trades",
            "subcategory":"Cleaning & Sanitation",
            "type":"Services"
        }
    ],
    "sg:phone":"+1 727 845 3132",
    "sg:postcode":"34654",
    "sg:province":"FL",
    "sg:tags":[
        "fireplace",
        "chimney"
    ],
    "wof:name":"Village Sweep",
    "wof:placetype":"venue"
},
  "geometry": {"coordinates":[-82.664941,28.27195],"type":"Point"}
}