{
  "type": "Feature",
  "properties": {
    "iso:country":"US",
    "sg:address":"2012 Walnut St",
    "sg:city":"Jacksonville",
    "sg:classifiers":[
        {
            "category":"Banks & Credit Unions",
            "subcategory":"Financial Services",
            "type":"Services"
        }
    ],
    "sg:phone":"+1 904 355 3715",
    "sg:postcode":"32206",
    "sg:province":"FL",
    "sg:tags":[
        "investment",
        "closed"
    ],
    "wof:name":"R&R Investment Properties",
    "wof:placetype":"venue"
},
  "geometry": {"coordinates":[-81.647527,30.348818],"type":"Point"}
}