{
  "type": "Feature",
  "properties": {
    "iso:country":"US",
    "sg:address":"138 Valencia Dr",
    "sg:city":"Islamorada",
    "sg:classifiers":[
        {
            "category":"Shopping",
            "subcategory":"Computers & Home Electronics",
            "type":"Retail Goods"
        }
    ],
    "sg:phone":"+1 305 664 9225",
    "sg:postcode":"33036",
    "sg:province":"FL",
    "sg:tags":[
        "equipment",
        "dealer"
    ],
    "wof:name":"Usalco Computers",
    "wof:placetype":"venue"
},
  "geometry": {"coordinates":[-80.586308,24.957333],"type":"Point"}
}