{
  "type": "Feature",
  "properties": {
    "iso:country":"US",
    "sg:address":"455 Harrison Ave",
    "sg:city":"Panama City",
    "sg:classifiers":[
        {
            "category":"Banks & Credit Unions",
            "subcategory":"Investment Brokerage",
            "type":"Services"
        }
    ],
    "sg:phone":"+1 850 914 2277",
    "sg:postcode":"32401",
    "sg:province":"FL",
    "sg:tags":[
        "consultant",
        "planning",
        "financial"
    ],
    "wof:name":"W D Boss & Co",
    "wof:placetype":"venue"
},
  "geometry": {"coordinates":[-85.66046299999999,30.156046],"type":"Point"}
}