{
  "type": "Feature",
  "properties": {
    "addr:full":"4712 Lark Ridge Cir Sarasota FL 34233",
    "addr:housenumber":"4712",
    "addr:postcode":"34233",
    "addr:street":"Lark Ridge Cir",
    "iso:country":"US",
    "sg:address":"4712 Lark Ridge Cir",
    "sg:city":"Sarasota",
    "sg:classifiers":[
        {
            "category":"Travel",
            "subcategory":"Hotels & Motels",
            "type":"Entertainment"
        }
    ],
    "sg:phone":"+1 941 926 2586",
    "sg:postcode":"34233",
    "sg:province":"FL",
    "sg:tags":[
        "management"
    ],
    "wof:name":"Crestmont Hospitality",
    "wof:placetype":"venue"
},
  "geometry": {"coordinates":[-82.495318,27.285278],"type":"Point"}
}