{
  "type": "Feature",
  "properties": {
    "iso:country":"US",
    "sg:address":"5610 Adair Way",
    "sg:city":"Lake Worth",
    "sg:classifiers":[
        {
            "category":"Building & Trades",
            "subcategory":"Landscaping Services",
            "type":"Services"
        }
    ],
    "sg:phone":"+1 561 966 2898",
    "sg:postcode":"33467",
    "sg:province":"FL",
    "sg:tags":[
        "landscape"
    ],
    "wof:name":"Lynn Bender Landscape",
    "wof:placetype":"venue"
},
  "geometry": {"coordinates":[-80.175494,26.593224],"type":"Point"}
}