{
  "type": "Feature",
  "properties": {
    "addr:full":"3048 State Hwy 674 Ruskin FL 33570",
    "addr:housenumber":"3048",
    "addr:postcode":"33570",
    "addr:street":"State Hwy 674",
    "iso:country":"US",
    "sg:address":"3048 State Hwy 674",
    "sg:city":"Ruskin",
    "sg:classifiers":[
        {
            "category":"Food & Beverages",
            "subcategory":"Groceries & Convenience Stores",
            "type":"Retail Goods"
        }
    ],
    "sg:phone":"+1 813 645 4671",
    "sg:postcode":"33570",
    "sg:province":"FL",
    "sg:tags":[
        "supermarket"
    ],
    "wof:name":"Publix",
    "wof:placetype":"venue"
},
  "geometry": {"coordinates":[-82.393747,27.713134],"type":"Point"}
}