{
  "type": "Feature",
  "properties": {
    "iso:country":"US",
    "sg:address":"3244 39th St",
    "sg:city":"Orlando",
    "sg:classifiers":[
        {
            "category":"Building & Trades",
            "subcategory":"Construction",
            "type":"Services"
        }
    ],
    "sg:phone":"+1 407 843 1584",
    "sg:postcode":"32839",
    "sg:province":"FL",
    "sg:tags":[
        "painting",
        "contractor"
    ],
    "wof:name":"Boyd Hart Co Inc",
    "wof:placetype":"venue"
},
  "geometry": {"coordinates":[-81.41986799999999,28.50328],"type":"Point"}
}