{
  "type": "Feature",
  "properties": {
    "addr:full":"5035 W Irlo Bronson Memorial Hwy Kissimmee FL 34746",
    "addr:housenumber":"5035",
    "addr:postcode":"34746",
    "addr:street":"W Irlo Bronson Memorial Hwy",
    "iso:country":"US",
    "sg:address":"5035 W Irlo Bronson Memorial Hwy",
    "sg:city":"Kissimmee",
    "sg:phone":"+1 407 397 2848",
    "sg:postcode":"34746",
    "sg:province":"FL",
    "sg:website":"http://www.tgifridays.com",
    "wof:name":"T.G.I. Friday's",
    "wof:placetype":"venue"
},
  "geometry": {"coordinates":[-81.48511999999999,28.33284],"type":"Point"}
}