{
  "type": "Feature",
  "properties": {
    "iso:country":"US",
    "sg:address":"890 NE Ocean Blvd",
    "sg:city":"Stuart",
    "sg:classifiers":[
        {
            "category":"Professional",
            "subcategory":"Research",
            "type":"Services"
        }
    ],
    "sg:phone":"+1 772 225 0505",
    "sg:postcode":"34996",
    "sg:province":"FL",
    "sg:tags":[
        "profit",
        "organization",
        "education"
    ],
    "wof:name":"Coastal Center",
    "wof:placetype":"venue"
},
  "geometry": {"coordinates":[-80.177559,27.217858],"type":"Point"}
}