{
  "type": "Feature",
  "properties": {
    "addr:full":"601 N Fort Harrison Ave Clearwater FL 33755",
    "addr:housenumber":"601",
    "addr:postcode":"33755",
    "addr:street":"N Fort Harrison Ave",
    "iso:country":"US",
    "sg:address":"601 N Fort Harrison Ave",
    "sg:city":"Clearwater",
    "sg:classifiers":[
        {
            "category":"Restaurant",
            "type":"Food & Drink"
        }
    ],
    "sg:phone":"+1 727 443 7172",
    "sg:postcode":"33755",
    "sg:province":"FL",
    "wof:name":"Quiznos Sub",
    "wof:placetype":"venue"
},
  "geometry": {"coordinates":[-82.799902,27.971642],"type":"Point"}
}