{
  "type": "Feature",
  "properties": {
    "addr:full":"9660 Pines Blvd Pembroke Pines FL 33024",
    "addr:housenumber":"9660",
    "addr:postcode":"33024",
    "addr:street":"Pines Blvd",
    "iso:country":"US",
    "sg:address":"9660 Pines Blvd",
    "sg:city":"Pembroke Pines",
    "sg:classifiers":[
        {
            "category":"Personal",
            "subcategory":"Beauty Salon",
            "type":"Services"
        }
    ],
    "sg:phone":"+1 954 450 0100",
    "sg:postcode":"33024",
    "sg:province":"FL",
    "wof:name":"Timarke Salon",
    "wof:placetype":"venue"
},
  "geometry": {"coordinates":[-80.27394700000001,26.008409],"type":"Point"}
}