{
  "type": "Feature",
  "properties": {
    "addr:full":"5627 Commerce Dr Orlando FL 32839",
    "addr:housenumber":"5627",
    "addr:postcode":"32839",
    "addr:street":"Commerce Dr",
    "iso:country":"US",
    "sg:address":"5627 Commerce Dr",
    "sg:city":"Orlando",
    "sg:classifiers":[
        {
            "category":"Wholesale",
            "subcategory":"Machinery & Supplies",
            "type":"Manufacturing & Wholesale Goods"
        }
    ],
    "sg:phone":"+1 407 851 3536",
    "sg:postcode":"32839",
    "sg:province":"FL",
    "sg:tags":[
        "hose"
    ],
    "sg:website":"www.orlandohose.com",
    "wof:name":"Orlando Hose & Fluid Power Inc",
    "wof:placetype":"venue"
},
  "geometry": {"coordinates":[-81.374207,28.478666],"type":"Point"}
}