{
  "type": "Feature",
  "properties": {
    "iso:country":"US",
    "sg:address":"2515 Oak St",
    "sg:city":"Jacksonville",
    "sg:classifiers":[
        {
            "category":"Building & Trades",
            "subcategory":"Construction",
            "type":"Services"
        }
    ],
    "sg:phone":"+1 904 387 1750",
    "sg:postcode":"32204",
    "sg:province":"FL",
    "sg:tags":[
        "painter"
    ],
    "wof:name":"Boucher's Paint & Pressure",
    "wof:placetype":"venue"
},
  "geometry": {"coordinates":[-81.68934,30.310291],"type":"Point"}
}