{
  "type": "Feature",
  "properties": {
    "iso:country":"US",
    "sg:address":"1529 S Dale Mabry Hwy",
    "sg:city":"Tampa",
    "sg:classifiers":[
        {
            "category":"Banks & Credit Unions",
            "subcategory":"Bank",
            "type":"Services"
        }
    ],
    "sg:phone":"+1 813 769 0631",
    "sg:postcode":"33629",
    "sg:province":"FL",
    "sg:tags":[
        "loan",
        "real estate"
    ],
    "sg:website":"http://www.capstonemortgage.com",
    "wof:name":"Capstone Mortgage",
    "wof:placetype":"venue"
},
  "geometry": {"coordinates":[-82.505877,27.929515],"type":"Point"}
}