{
  "type": "Feature",
  "properties": {
    "iso:country":"US",
    "sg:address":"1801 Clint Moore Rd",
    "sg:city":"Boca Raton",
    "sg:classifiers":[
        {
            "category":"Banks & Credit Unions",
            "subcategory":"Investment Brokerage",
            "type":"Services"
        }
    ],
    "sg:phone":"+1 561 997 0300",
    "sg:postcode":"33487",
    "sg:province":"FL",
    "sg:tags":[
        "advisory",
        "financial"
    ],
    "wof:name":"ARS Financial Svc Inc",
    "wof:placetype":"venue"
},
  "geometry": {"coordinates":[-80.120199,26.408212],"type":"Point"}
}