{
  "type": "Feature",
  "properties": {
    "addr:full":"5495 S Orange Blossom Trl Orlando FL 32839",
    "addr:housenumber":"5495",
    "addr:postcode":"32839",
    "addr:street":"S Orange Blossom Trl",
    "iso:country":"US",
    "sg:address":"5495 S Orange Blossom Trl",
    "sg:city":"Orlando",
    "sg:classifiers":[
        {
            "category":"Autos & Motor Vehicles",
            "subcategory":"Automobile Sales",
            "type":"Retail Goods"
        }
    ],
    "sg:phone":"+1 407 855 9202",
    "sg:postcode":"32839",
    "sg:province":"FL",
    "sg:tags":[
        "new",
        "used",
        "dealer",
        "car"
    ],
    "wof:name":"Autoquest",
    "wof:placetype":"venue"
},
  "geometry": {"coordinates":[-81.39664500000001,28.4818],"type":"Point"}
}