{
  "type": "Feature",
  "properties": {
    "iso:country":"US",
    "sg:address":"1301 Moseley Ave",
    "sg:city":"Palatka",
    "sg:classifiers":[
        {
            "category":"Professional",
            "subcategory":"Employment Agencies",
            "type":"Services"
        }
    ],
    "sg:phone":"+1 386 329 3701",
    "sg:postcode":"32177",
    "sg:province":"FL",
    "sg:tags":[
        "consultant",
        "search",
        "executive"
    ],
    "wof:name":"Army National Guard Recruiting",
    "wof:placetype":"venue"
},
  "geometry": {"coordinates":[-81.64957099999999,29.638035],"type":"Point"}
}