{
  "type": "Feature",
  "properties": {
    "iso:country":"US",
    "sg:address":"131 Royal Palm Dr",
    "sg:city":"Leesburg",
    "sg:classifiers":[
        {
            "category":"Personal",
            "type":"Services"
        },
        {
            "category":"Professional",
            "subcategory":"Art Services",
            "type":"Services"
        }
    ],
    "sg:phone":"+1 352 365 0446",
    "sg:postcode":"34748",
    "sg:province":"FL",
    "sg:tags":[
        "photography",
        "videography",
        "wedding"
    ],
    "wof:name":"Susan Gleason Photography",
    "wof:placetype":"venue"
},
  "geometry": {"coordinates":[-81.873779,28.753071],"type":"Point"}
}