{
  "type": "Feature",
  "properties": {
    "addr:full":"1921 W Jefferson St Quincy FL 32351",
    "addr:housenumber":"1921",
    "addr:postcode":"32351",
    "addr:street":"W Jefferson St",
    "iso:country":"US",
    "sg:address":"1921 W Jefferson St",
    "sg:city":"Quincy",
    "sg:classifiers":[
        {
            "category":"Food & Beverages",
            "subcategory":"Groceries & Convenience Stores",
            "type":"Retail Goods"
        }
    ],
    "sg:phone":"+1 850 627 1661",
    "sg:postcode":"32351",
    "sg:province":"FL",
    "sg:tags":[
        "grocer"
    ],
    "wof:name":"Mi Favorita Tony Saenz",
    "wof:placetype":"venue"
},
  "geometry": {"coordinates":[-84.602902,30.585486],"type":"Point"}
}