{
  "type": "Feature",
  "properties": {
    "iso:country":"US",
    "sg:address":"3790 161st Ter N",
    "sg:city":"Loxahatchee",
    "sg:classifiers":[
        {
            "category":"Building & Trades",
            "subcategory":"Construction",
            "type":"Services"
        }
    ],
    "sg:phone":"+1 561 793 0781",
    "sg:postcode":"33470",
    "sg:province":"FL",
    "sg:tags":[
        "excavating",
        "contractor"
    ],
    "wof:name":"William Gifford Jr Excavation",
    "wof:placetype":"venue"
},
  "geometry": {"coordinates":[-80.29825700000001,26.738998],"type":"Point"}
}