{
  "type": "Feature",
  "properties": {
    "addr:full":"19496 Island Court Dr Boca Raton FL 33434",
    "addr:housenumber":"19496",
    "addr:postcode":"33434",
    "addr:street":"Island Court Dr",
    "iso:country":"US",
    "sg:address":"19496 Island Court Dr",
    "sg:city":"Boca Raton",
    "sg:classifiers":[
        {
            "category":"Professional",
            "subcategory":"Management & Consulting",
            "type":"Services"
        }
    ],
    "sg:phone":"+1 561 477 6626",
    "sg:postcode":"33434",
    "sg:province":"FL",
    "sg:tags":[
        "consultant",
        "business"
    ],
    "wof:name":"Network Associates",
    "wof:placetype":"venue"
},
  "geometry": {"coordinates":[-80.16157,26.386107],"type":"Point"}
}