{
  "type": "Feature",
  "properties": {
    "addr:full":"1475 Atlantic Blvd Jacksonville FL 32207",
    "addr:housenumber":"1475",
    "addr:postcode":"32207",
    "addr:street":"Atlantic Blvd",
    "iso:country":"US",
    "sg:address":"1475 Atlantic Blvd",
    "sg:city":"Jacksonville",
    "sg:classifiers":[
        {
            "category":"Shopping",
            "subcategory":"Hobbies, Toys, & Games",
            "type":"Retail Goods"
        }
    ],
    "sg:phone":"+1 904 246 0601",
    "sg:postcode":"32207",
    "sg:province":"FL",
    "sg:tags":[
        "model",
        "supply"
    ],
    "wof:name":"Art's Hobby Shop",
    "wof:placetype":"venue"
},
  "geometry": {"coordinates":[-81.653586,30.304962],"type":"Point"}
}