{
  "type": "Feature",
  "properties": {
    "iso:country":"US",
    "sg:address":"411 Cleveland St",
    "sg:city":"Clearwater",
    "sg:classifiers":[
        {
            "category":"Shopping",
            "subcategory":"Discount & Variety Stores",
            "type":"Retail Goods"
        }
    ],
    "sg:phone":"+1 727 449 1674",
    "sg:postcode":"33755",
    "sg:province":"FL",
    "sg:tags":[
        "retailer"
    ],
    "wof:name":"One Stoppe Shoppe",
    "wof:placetype":"venue"
},
  "geometry": {"coordinates":[-82.800687,27.965526],"type":"Point"}
}