{
  "type": "Feature",
  "properties": {
    "iso:country":"US",
    "sg:address":"2828 Cedaridge Dr",
    "sg:city":"Tampa",
    "sg:classifiers":[
        {
            "category":"Shopping",
            "type":"Retail Goods"
        }
    ],
    "sg:phone":"+1 813 601 0067",
    "sg:postcode":"33618",
    "sg:province":"FL",
    "sg:tags":[
        "equipment",
        "telephone",
        "supply"
    ],
    "wof:name":"Clear Link Communications",
    "wof:placetype":"venue"
},
  "geometry": {"coordinates":[-82.49220099999999,28.099619],"type":"Point"}
}