{
  "type": "Feature",
  "properties": {
    "iso:country":"US",
    "sg:address":"19501 Biscayne Blvd Aventura Mall, Ste 503",
    "sg:city":"Aventura",
    "sg:classifiers":[
        {
            "category":"Shopping",
            "type":"Retail Goods"
        }
    ],
    "sg:phone":"+1 305 933 0923",
    "sg:postcode":"33180",
    "sg:province":"FL",
    "wof:name":"Barneys NY Coop",
    "wof:placetype":"venue"
},
  "geometry": {"coordinates":[-80.146787,25.956979],"type":"Point"}
}