{
  "type": "Feature",
  "properties": {
    "iso:country":"US",
    "sg:address":"1737 Citron Ct",
    "sg:city":"New Port Richey",
    "sg:classifiers":[
        {
            "category":"Utilities",
            "subcategory":"Telephone",
            "type":"Services"
        }
    ],
    "sg:phone":"+1 727 834 8768",
    "sg:postcode":"34655",
    "sg:province":"FL",
    "sg:tags":[
        "distance",
        "long"
    ],
    "wof:name":"Time Machine Inc",
    "wof:placetype":"venue"
},
  "geometry": {"coordinates":[-82.65482900000001,28.182562],"type":"Point"}
}