{
  "type": "Feature",
  "properties": {
    "iso:country":"US",
    "sg:address":"12134 NW 23rd Manor",
    "sg:city":"Pompano Beach",
    "sg:classifiers":[
        {
            "category":"Building & Trades",
            "subcategory":"Construction",
            "type":"Services"
        }
    ],
    "sg:phone":"+1 954 340 3044",
    "sg:postcode":"33065",
    "sg:province":"FL",
    "sg:tags":[
        "contractor"
    ],
    "wof:name":"Houle Giles Drywall",
    "wof:placetype":"venue"
},
  "geometry": {"coordinates":[-80.28744,26.260478],"type":"Point"}
}