{
  "type": "Feature",
  "properties": {
    "iso:country":"US",
    "sg:address":"4050 NE 12th Ave",
    "sg:city":"Pompano Beach",
    "sg:classifiers":[
        {
            "category":"Shopping",
            "type":"Retail Goods"
        }
    ],
    "sg:phone":"+1 954 650 5114",
    "sg:postcode":"33064",
    "sg:province":"FL",
    "sg:tags":[
        "merchandise"
    ],
    "wof:name":"Glenns Tropicals Inc",
    "wof:placetype":"venue"
},
  "geometry": {"coordinates":[-80.106786,26.281064],"type":"Point"}
}