{
  "type": "Feature",
  "properties": {
    "addr:full":"2816 W Dunnellon Rd Dunnellon FL 34433",
    "addr:housenumber":"2816",
    "addr:postcode":"34433",
    "addr:street":"W Dunnellon Rd",
    "iso:country":"US",
    "sg:address":"2816 W Dunnellon Rd",
    "sg:city":"Dunnellon",
    "sg:classifiers":[
        {
            "category":"Shopping",
            "subcategory":"Crafts & Fabrics",
            "type":"Retail Goods"
        }
    ],
    "sg:phone":"+1 352 465 1300",
    "sg:postcode":"34433",
    "sg:province":"FL",
    "sg:tags":[
        "florist",
        "supplies-wholesale",
        "manufacturer",
        "florists'",
        "supply"
    ],
    "wof:name":"Nova Usa Inc",
    "wof:placetype":"venue"
},
  "geometry": {"coordinates":[-82.484244,29.040473],"type":"Point"}
}