{
  "type": "Feature",
  "properties": {
    "addr:full":"3696 Heron Ridge Ln Fort Lauderdale FL 33331",
    "addr:housenumber":"3696",
    "addr:postcode":"33331",
    "addr:street":"Heron Ridge Ln",
    "iso:country":"US",
    "sg:address":"3696 Heron Ridge Ln",
    "sg:city":"Fort Lauderdale",
    "sg:classifiers":[
        {
            "category":"Professional",
            "subcategory":"Business Services",
            "type":"Services"
        }
    ],
    "sg:phone":"+1 954 609 0948",
    "sg:postcode":"33331",
    "sg:province":"FL",
    "wof:name":"La Group LLC",
    "wof:placetype":"venue"
},
  "geometry": {"coordinates":[-80.386746,26.072345],"type":"Point"}
}