{
  "type": "Feature",
  "properties": {
    "iso:country":"US",
    "sg:address":"2930 Apalachee Pkwy",
    "sg:city":"Tallahassee",
    "sg:classifiers":[
        {
            "category":"Banks & Credit Unions",
            "subcategory":"Bank",
            "type":"Services"
        }
    ],
    "sg:phone":"+1 850 942 6390",
    "sg:postcode":"32301",
    "sg:province":"FL",
    "wof:name":"Bank Of America",
    "wof:placetype":"venue"
},
  "geometry": {"coordinates":[-84.231307,30.427161],"type":"Point"}
}