{
  "type": "Feature",
  "properties": {
    "addr:full":"1003 del Prado Blvd S Cape Coral FL 33990",
    "addr:housenumber":"1003",
    "addr:postcode":"33990",
    "addr:street":"Del Prado Blvd S",
    "iso:country":"US",
    "sg:address":"1003 del Prado Blvd S",
    "sg:city":"Cape Coral",
    "sg:classifiers":[
        {
            "category":"Health Services",
            "subcategory":"Doctor",
            "type":"Services"
        }
    ],
    "sg:phone":"+1 239 573 1505",
    "sg:postcode":"33990",
    "sg:province":"FL",
    "sg:tags":[
        "medical"
    ],
    "wof:name":"Narmo L Ortiz Jr DPM PA",
    "wof:placetype":"venue"
},
  "geometry": {"coordinates":[-81.940743,26.632908],"type":"Point"}
}