{
  "type": "Feature",
  "properties": {
    "iso:country":"US",
    "sg:address":"1414 S Orange Ave",
    "sg:city":"Orlando",
    "sg:classifiers":[
        {
            "category":"Health Services",
            "subcategory":"Doctor",
            "type":"Services"
        }
    ],
    "sg:phone":"+1 407 843 3360",
    "sg:postcode":"32806",
    "sg:province":"FL",
    "sg:tags":[
        "physician",
        "surgeon"
    ],
    "wof:name":"Emergency Physicians-Cntrl Fl",
    "wof:placetype":"venue"
},
  "geometry": {"coordinates":[-81.37654499999999,28.525878],"type":"Point"}
}