{
  "type": "Feature",
  "properties": {
    "addr:full":"10454 Roosevelt Blvd N St Petersburg FL 33716",
    "addr:housenumber":"10454",
    "addr:postcode":"33716",
    "addr:street":"Roosevelt Blvd N",
    "iso:country":"US",
    "sg:address":"10454 Roosevelt Blvd N",
    "sg:city":"St Petersburg",
    "sg:classifiers":[
        {
            "category":"Personal",
            "subcategory":"Beauty Salon",
            "type":"Services"
        }
    ],
    "sg:phone":"+1 727 578 4800",
    "sg:postcode":"33716",
    "sg:province":"FL",
    "sg:tags":[
        "manicuring"
    ],
    "wof:name":"Your Nails",
    "wof:placetype":"venue"
},
  "geometry": {"coordinates":[-82.644333,27.867726],"type":"Point"}
}