{
  "type": "Feature",
  "properties": {
    "addr:full":"2285 Fritzke Rd Dover FL 33527",
    "addr:housenumber":"2285",
    "addr:postcode":"33527",
    "addr:street":"Fritzke Rd",
    "iso:country":"US",
    "sg:address":"2285 Fritzke Rd",
    "sg:city":"Dover",
    "sg:classifiers":[
        {
            "category":"Retail",
            "subcategory":"Auto Repair",
            "type":"Services"
        }
    ],
    "sg:phone":"+1 813 986 9773",
    "sg:postcode":"33527",
    "sg:province":"FL",
    "sg:tags":[
        "repairing",
        "automobile"
    ],
    "wof:name":"Frank's Pump Repair",
    "wof:placetype":"venue"
},
  "geometry": {"coordinates":[-82.21605599999999,28.032189],"type":"Point"}
}