{
  "type": "Feature",
  "properties": {
    "addr:full":"9050 Pines Blvd Hollywood FL 33024",
    "addr:postcode":"9050;33024",
    "addr:street":"Pines Blvd",
    "iso:country":"US",
    "sg:address":"9050 Pines Blvd",
    "sg:city":"Hollywood",
    "sg:classifiers":[
        {
            "category":"Retail",
            "subcategory":"Auto Rental",
            "type":"Services"
        }
    ],
    "sg:phone":"+1 954 437 9198",
    "sg:postcode":"33024",
    "sg:province":"FL",
    "sg:tags":[
        "passenger",
        "car"
    ],
    "wof:name":"Thrifty Rent-A-Car System",
    "wof:placetype":"venue"
},
  "geometry": {"coordinates":[-80.26396099999999,26.008722],"type":"Point"}
}