{
  "type": "Feature",
  "properties": {
    "iso:country":"US",
    "sg:address":"11615 Columbia Park Dr E",
    "sg:city":"Jacksonville",
    "sg:classifiers":[
        {
            "category":"Professional",
            "subcategory":"Research",
            "type":"Services"
        }
    ],
    "sg:phone":"+1 904 292 2734",
    "sg:postcode":"32258",
    "sg:province":"FL",
    "sg:tags":[
        "environmental",
        "ecological"
    ],
    "wof:name":"Transamerican Drilling & Test",
    "wof:placetype":"venue"
},
  "geometry": {"coordinates":[-81.53678499999999,30.157901],"type":"Point"}
}