{
  "type": "Feature",
  "properties": {
    "iso:country":"US",
    "sg:address":"2310 Ariana Blvd",
    "sg:city":"Auburndale",
    "sg:classifiers":[
        {
            "category":"Building & Trades",
            "subcategory":"Construction",
            "type":"Services"
        }
    ],
    "sg:phone":"+1 863 965 7002",
    "sg:postcode":"33823",
    "sg:province":"FL",
    "sg:tags":[
        "house"
    ],
    "wof:name":"Lord Built Construction",
    "wof:placetype":"venue"
},
  "geometry": {"coordinates":[-81.802908,28.069669],"type":"Point"}
}