{
  "type": "Feature",
  "properties": {
    "iso:country":"US",
    "sg:address":"300 W Broward Blvd",
    "sg:city":"Fort Lauderdale",
    "sg:classifiers":[
        {
            "category":"Banks & Credit Unions",
            "subcategory":"Bank",
            "type":"Services"
        }
    ],
    "sg:phone":"+1 954 766 6007",
    "sg:postcode":"33312",
    "sg:province":"FL",
    "sg:tags":[
        "state",
        "commercial"
    ],
    "wof:name":"Rbc Centura Bank",
    "wof:placetype":"venue"
},
  "geometry": {"coordinates":[-80.147509,26.122182],"type":"Point"}
}