{
  "type": "Feature",
  "properties": {
    "iso:country":"US",
    "sg:address":"2241 Fairview Rd",
    "sg:city":"Marianna",
    "sg:classifiers":[
        {
            "category":"Retail",
            "subcategory":"Auto Repair",
            "type":"Services"
        }
    ],
    "sg:phone":"+1 850 482 5399",
    "sg:postcode":"32448",
    "sg:province":"FL",
    "sg:tags":[
        "general"
    ],
    "wof:name":"Billys Automotive & Trctr Repr",
    "wof:placetype":"venue"
},
  "geometry": {"coordinates":[-85.292461,30.729107],"type":"Point"}
}