{
  "type": "Feature",
  "properties": {
    "addr:full":"3307 Kings Rd Panama City FL 32405",
    "addr:housenumber":"3307",
    "addr:postcode":"32405",
    "addr:street":"Kings Rd",
    "iso:country":"US",
    "sg:address":"3307 Kings Rd",
    "sg:city":"Panama City",
    "sg:classifiers":[
        {
            "category":"Building & Trades",
            "subcategory":"Construction",
            "type":"Services"
        }
    ],
    "sg:phone":"+1 850 872 1522",
    "sg:postcode":"32405",
    "sg:province":"FL",
    "sg:tags":[
        "contractor"
    ],
    "wof:name":"Gulf Coast Hydroseed",
    "wof:placetype":"venue"
},
  "geometry": {"coordinates":[-85.699881,30.204747],"type":"Point"}
}