{
  "type": "Feature",
  "properties": {
    "addr:full":"4017 Ballard Rd Tallahassee FL 32305",
    "addr:housenumber":"4017",
    "addr:postcode":"32305",
    "addr:street":"Ballard Rd",
    "iso:country":"US",
    "sg:address":"4017 Ballard Rd",
    "sg:city":"Tallahassee",
    "sg:classifiers":[
        {
            "category":"Home & Garden",
            "subcategory":"Carpets & Floor Coverings",
            "type":"Retail Goods"
        }
    ],
    "sg:phone":"+1 850 656 5723",
    "sg:postcode":"32305",
    "sg:province":"FL",
    "wof:name":"Professional Maintenance Svcs",
    "wof:placetype":"venue"
},
  "geometry": {"coordinates":[-84.298675,30.388979],"type":"Point"}
}