{
  "type": "Feature",
  "properties": {
    "iso:country":"US",
    "sg:address":"4315 Brentwood Ave",
    "sg:city":"Jacksonville",
    "sg:classifiers":[
        {
            "category":"Restaurant",
            "type":"Food & Drink"
        }
    ],
    "sg:menulink":"http://www.allmenus.com/fl/jacksonville/157728-aunt-tillies-soul-food-restaurant/menu/",
    "sg:phone":"+1 904 475 0707",
    "sg:postcode":"32206",
    "sg:province":"FL",
    "sg:tags":[
        "food",
        "american",
        "soul"
    ],
    "wof:name":"Aunt Tillies Soul Food Restaurant",
    "wof:placetype":"venue"
},
  "geometry": {"coordinates":[-81.66365500000001,30.364703],"type":"Point"}
}