{
  "type": "Feature",
  "properties": {
    "iso:country":"US",
    "sg:address":"1919 US Hwy 1 S",
    "sg:city":"St Augustine",
    "sg:classifiers":[
        {
            "category":"Banks & Credit Unions",
            "subcategory":"Bank",
            "type":"Services"
        }
    ],
    "sg:phone":"+1 904 824 7550",
    "sg:postcode":"32086",
    "sg:province":"FL",
    "wof:name":"Wachovia Bank",
    "wof:placetype":"venue"
},
  "geometry": {"coordinates":[-81.32307299999999,29.866335],"type":"Point"}
}