{
  "type": "Feature",
  "properties": {
    "addr:full":"16438 SW 97th St Miami FL 33196",
    "addr:housenumber":"16438",
    "addr:postcode":"33196",
    "addr:street":"Sw 97Th St",
    "iso:country":"US",
    "sg:address":"16438 SW 97th St",
    "sg:city":"Miami",
    "sg:classifiers":[
        {
            "category":"Professional",
            "type":"Services"
        }
    ],
    "sg:phone":"+1 305 408 2452",
    "sg:postcode":"33196",
    "sg:province":"FL",
    "wof:name":"Up Today Net Corp",
    "wof:placetype":"venue"
},
  "geometry": {"coordinates":[-80.463604,25.675539],"type":"Point"}
}