{
  "type": "Feature",
  "properties": {
    "iso:country":"US",
    "sg:address":"500 Crofton Ct",
    "sg:city":"Orange Park",
    "sg:classifiers":[
        {
            "category":"Building & Trades",
            "subcategory":"Construction",
            "type":"Services"
        }
    ],
    "sg:phone":"+1 904 264 4100",
    "sg:postcode":"32311",
    "sg:province":"FL",
    "sg:tags":[
        "installation",
        "cabinet"
    ],
    "wof:name":"Kauffman Woodworking",
    "wof:placetype":"venue"
},
  "geometry": {"coordinates":[-84.185199,30.456727],"type":"Point"}
}