{
  "type": "Feature",
  "properties": {
    "iso:country":"US",
    "sg:address":"1595 Co Rd 13A",
    "sg:city":"Elkton",
    "sg:classifiers":[
        {
            "category":"Health Services",
            "subcategory":"Health Practitioner",
            "type":"Services"
        }
    ],
    "sg:phone":"+1 904 669 0456",
    "sg:postcode":"32033",
    "sg:province":"FL",
    "wof:name":"Weiss Patricia Rn Lmt",
    "wof:placetype":"venue"
},
  "geometry": {"coordinates":[-81.48465,29.81431],"type":"Point"}
}