{
  "type": "Feature",
  "properties": {
    "iso:country":"US",
    "sg:address":"200 W Main St",
    "sg:city":"Avon Park",
    "sg:classifiers":[
        {
            "category":"Autos & Motor Vehicles",
            "subcategory":"Fuel & Gas Station",
            "type":"Retail Goods"
        }
    ],
    "sg:phone":"+1 863 453 5727",
    "sg:postcode":"33825",
    "sg:province":"FL",
    "sg:tags":[
        "oil"
    ],
    "wof:name":"Main Street Car Care",
    "wof:placetype":"venue"
},
  "geometry": {"coordinates":[-81.504092,27.595693],"type":"Point"}
}