{
  "type": "Feature",
  "properties": {
    "addr:full":"4281 Weymouth St Lake Worth FL 33461",
    "addr:housenumber":"4281",
    "addr:postcode":"33461",
    "addr:street":"Weymouth St",
    "iso:country":"US",
    "sg:address":"4281 Weymouth St",
    "sg:city":"Lake Worth",
    "sg:classifiers":[
        {
            "category":"Building & Trades",
            "subcategory":"Landscaping Services",
            "type":"Services"
        }
    ],
    "sg:phone":"+1 561 432 5456",
    "sg:postcode":"33461",
    "sg:province":"FL",
    "wof:name":"Angels Lawn Maintenance Inc",
    "wof:placetype":"venue"
},
  "geometry": {"coordinates":[-80.11169700000001,26.628771],"type":"Point"}
}