{
  "type": "Feature",
  "properties": {
    "iso:country":"US",
    "sg:address":"211 Agua Vista St",
    "sg:city":"Debary",
    "sg:classifiers":[
        {
            "category":"Professional",
            "type":"Services"
        }
    ],
    "sg:phone":"+1 386 668 8499",
    "sg:postcode":"32713",
    "sg:province":"FL",
    "sg:tags":[
        "establishment"
    ],
    "wof:name":"R & J",
    "wof:placetype":"venue"
},
  "geometry": {"coordinates":[-81.306391,28.874302],"type":"Point"}
}