{
  "type": "Feature",
  "properties": {
    "iso:country":"US",
    "sg:address":"781 N Alafaya Trl",
    "sg:city":"Orlando",
    "sg:classifiers":[
        {
            "category":"Education",
            "subcategory":"Dance Studio",
            "type":"Public Place"
        }
    ],
    "sg:phone":"+1 407 380 6620",
    "sg:postcode":"32828",
    "sg:province":"FL",
    "sg:tags":[
        "instruction",
        "dancing"
    ],
    "wof:name":"Gotta Dance At Waterford Lakes",
    "wof:placetype":"venue"
},
  "geometry": {"coordinates":[-81.20627500000001,28.554413],"type":"Point"}
}