{
  "type": "Feature",
  "properties": {
    "iso:country":"US",
    "sg:address":"825 S US Hwy 1",
    "sg:city":"Jupiter",
    "sg:classifiers":[
        {
            "category":"Shopping",
            "subcategory":"Computers & Home Electronics",
            "type":"Retail Goods"
        }
    ],
    "sg:phone":"+1 561 575 1334",
    "sg:postcode":"33477",
    "sg:province":"FL",
    "sg:tags":[
        "software"
    ],
    "wof:name":"Tevixmd",
    "wof:placetype":"venue"
},
  "geometry": {"coordinates":[-80.076519,26.925841],"type":"Point"}
}