{
  "type": "Feature",
  "properties": {
    "addr:full":"10775 Biscayne Blvd Miami FL 33138",
    "addr:housenumber":"10775",
    "addr:postcode":"33138",
    "addr:street":"Biscayne Blvd",
    "iso:country":"US",
    "sg:address":"10775 Biscayne Blvd",
    "sg:city":"Miami",
    "sg:classifiers":[
        {
            "category":"Shopping",
            "subcategory":"Discount & Variety Stores",
            "type":"Retail Goods"
        }
    ],
    "sg:phone":"+1 305 899 1007",
    "sg:postcode":"33138",
    "sg:province":"FL",
    "wof:name":"Lou's 99 Cents Plus Inc",
    "wof:placetype":"venue"
},
  "geometry": {"coordinates":[-80.170815,25.873976],"type":"Point"}
}