{
  "type": "Feature",
  "properties": {
    "iso:country":"US",
    "sg:address":"3230 SW 149th Ave",
    "sg:city":"Miami",
    "sg:classifiers":[
        {
            "category":"Professional",
            "subcategory":"Business Services",
            "type":"Services"
        }
    ],
    "sg:phone":"+1 305 222 1203",
    "sg:postcode":"33185",
    "sg:province":"FL",
    "wof:name":"Orion Logistic Group",
    "wof:placetype":"venue"
},
  "geometry": {"coordinates":[-80.436025,25.737394],"type":"Point"}
}