{
  "type": "Feature",
  "properties": {
    "iso:country":"US",
    "sg:address":"4300 Fortune Pl",
    "sg:city":"Melbourne",
    "sg:classifiers":[
        {
            "category":"Manufacturing",
            "subcategory":"Electronics",
            "type":"Manufacturing & Wholesale Goods"
        },
        {
            "category":"Manufacturing",
            "subcategory":"Tools & Machinery",
            "type":"Manufacturing & Wholesale Goods"
        }
    ],
    "sg:phone":"+1 321 725 8000",
    "sg:postcode":"32904",
    "sg:province":"FL",
    "sg:tags":[
        "mfg",
        "devices",
        "surge",
        "semiconductor",
        "equipment",
        "protection",
        "related"
    ],
    "wof:name":"Atlantic Scientific Corp",
    "wof:placetype":"venue"
},
  "geometry": {"coordinates":[-80.69738,28.094936],"type":"Point"}
}