{
  "type": "Feature",
  "properties": {
    "iso:country":"US",
    "sg:address":"1115 N Federal Hwy",
    "sg:city":"Boynton Beach",
    "sg:classifiers":[
        {
            "category":"Arts & Performance",
            "subcategory":"Theater",
            "type":"Entertainment"
        }
    ],
    "sg:phone":"+1 561 734 8866",
    "sg:postcode":"33435",
    "sg:province":"FL",
    "sg:tags":[
        "entertainer"
    ],
    "wof:name":"Platinum Showgirls",
    "wof:placetype":"venue"
},
  "geometry": {"coordinates":[-80.057785,26.536735],"type":"Point"}
}