{
  "type": "Feature",
  "properties": {
    "iso:country":"US",
    "sg:address":"1314 Belgrade Ave",
    "sg:city":"Orlando",
    "sg:classifiers":[
        {
            "category":"Professional",
            "subcategory":"Business Services",
            "type":"Services"
        }
    ],
    "sg:phone":"+1 407 228 4848",
    "sg:postcode":"32803",
    "sg:province":"FL",
    "sg:tags":[
        "convention",
        "meeting",
        "facility"
    ],
    "sg:website":"www.theawesomegroup.com",
    "wof:name":"Awesome Group",
    "wof:placetype":"venue"
},
  "geometry": {"coordinates":[-81.362571,28.56382],"type":"Point"}
}