{
  "type": "Feature",
  "properties": {
    "iso:country":"US",
    "sg:address":"2326 Arthur St",
    "sg:city":"Hollywood",
    "sg:classifiers":[
        {
            "category":"Food & Beverages",
            "subcategory":"Groceries & Convenience Stores",
            "type":"Retail Goods"
        }
    ],
    "sg:phone":"+1 954 922 8095",
    "sg:postcode":"33020",
    "sg:province":"FL",
    "wof:name":"Champ General Service Inc",
    "wof:placetype":"venue"
},
  "geometry": {"coordinates":[-80.154414,26.022294],"type":"Point"}
}