{
  "type": "Feature",
  "properties": {
    "addr:full":"2540 Lisenby Ave Panama City FL 32405",
    "addr:housenumber":"2540",
    "addr:postcode":"32405",
    "addr:street":"Lisenby Ave",
    "iso:country":"US",
    "sg:address":"2540 Lisenby Ave",
    "sg:city":"Panama City",
    "sg:classifiers":[
        {
            "category":"Shopping",
            "type":"Retail Goods"
        }
    ],
    "sg:phone":"+1 850 785 3277",
    "sg:postcode":"32405",
    "sg:province":"FL",
    "sg:tags":[
        "pet",
        "shop"
    ],
    "wof:name":"Mid-Florida Pet Supply",
    "wof:placetype":"venue"
},
  "geometry": {"coordinates":[-85.683342,30.193718],"type":"Point"}
}