{
  "type": "Feature",
  "properties": {
    "addr:full":"3961 Florida Blvd Palm Beach Gdns FL 33410",
    "addr:housenumber":"3961",
    "addr:postcode":"33410",
    "addr:street":"Florida Blvd Palm Beach Gdns",
    "iso:country":"US",
    "sg:address":"3961 Florida Blvd",
    "sg:city":"Palm Beach Gdns",
    "sg:classifiers":[
        {
            "category":"Food & Beverages",
            "subcategory":"Groceries & Convenience Stores",
            "type":"Retail Goods"
        }
    ],
    "sg:phone":"+1 561 625 0464",
    "sg:postcode":"33410",
    "sg:province":"FL",
    "wof:name":"Loren Food Mart",
    "wof:placetype":"venue"
},
  "geometry": {"coordinates":[-80.09625800000001,26.857053],"type":"Point"}
}