{
  "type": "Feature",
  "properties": {
    "iso:country":"US",
    "sg:address":"4803 Lincoln Ave",
    "sg:city":"Orlando",
    "sg:classifiers":[
        {
            "category":"Building & Trades",
            "subcategory":"Construction",
            "type":"Services"
        }
    ],
    "sg:phone":"+1 407 253 0933",
    "sg:postcode":"32819",
    "sg:province":"FL",
    "sg:tags":[
        "home",
        "builder"
    ],
    "wof:name":"Farmer Trading & Construction",
    "wof:placetype":"venue"
},
  "geometry": {"coordinates":[-81.500015,28.490111],"type":"Point"}
}