{
  "type": "Feature",
  "properties": {
    "addr:full":"300 N Dixie Hwy West Palm Beach FL 33401",
    "addr:housenumber":"300",
    "addr:postcode":"33401",
    "addr:street":"N Dixie Hwy",
    "iso:country":"US",
    "sg:address":"300 N Dixie Hwy",
    "sg:city":"West Palm Beach",
    "sg:classifiers":[
        {
            "category":"Government",
            "subcategory":"Office",
            "type":"Public Place"
        }
    ],
    "sg:phone":"+1 561 355 2500",
    "sg:postcode":"33401",
    "sg:province":"FL",
    "wof:name":"Palm Beach County Courts Civil",
    "wof:placetype":"venue"
},
  "geometry": {"coordinates":[-80.05346299999999,26.71611],"type":"Point"}
}