{
  "type": "Feature",
  "properties": {
    "iso:country":"US",
    "sg:address":"579 Hobart Rd",
    "sg:city":"Terra Ceia",
    "sg:classifiers":[
        {
            "category":"Professional",
            "subcategory":"Business Services",
            "type":"Services"
        }
    ],
    "sg:phone":"+1 941 723 5091",
    "sg:postcode":"34293",
    "sg:province":"FL",
    "sg:tags":[
        "broker",
        "merchandise"
    ],
    "wof:name":"Native Plant Brokers Inc",
    "wof:placetype":"venue"
},
  "geometry": {"coordinates":[-82.408106,27.033669],"type":"Point"}
}