{
  "type": "Feature",
  "properties": {
    "iso:country":"US",
    "sg:address":"76 NE 49th St",
    "sg:city":"Miami",
    "sg:classifiers":[
        {
            "category":"Arts & Performance",
            "subcategory":"Theater",
            "type":"Entertainment"
        }
    ],
    "sg:phone":"+1 305 754 6446",
    "sg:postcode":"33137",
    "sg:province":"FL",
    "sg:tags":[
        "bureau"
    ],
    "wof:name":"On Point Entrtn Marketing Inc",
    "wof:placetype":"venue"
},
  "geometry": {"coordinates":[-80.19522600000001,25.820543],"type":"Point"}
}