{
  "type": "Feature",
  "properties": {
    "addr:full":"14855 NW 7th Ave Miami FL 33168",
    "addr:housenumber":"14855",
    "addr:postcode":"33168",
    "addr:street":"Nw 7Th Ave",
    "iso:country":"US",
    "sg:address":"14855 NW 7th Ave",
    "sg:city":"Miami",
    "sg:classifiers":[
        {
            "category":"Professional",
            "subcategory":"Business Services",
            "type":"Services"
        }
    ],
    "sg:phone":"+1 305 685 0343",
    "sg:postcode":"33168",
    "sg:province":"FL",
    "sg:tags":[
        "pool",
        "swimming"
    ],
    "wof:name":"Spec Pool Svc & Equipment Copr",
    "wof:placetype":"venue"
},
  "geometry": {"coordinates":[-80.21164,25.911567],"type":"Point"}
}