{
  "type": "Feature",
  "properties": {
    "iso:country":"US",
    "sg:address":"1616 Mc Caskill Ave",
    "sg:city":"Tallahassee",
    "sg:classifiers":[
        {
            "category":"Shopping",
            "subcategory":"Used Merchandise",
            "type":"Retail Goods"
        }
    ],
    "sg:phone":"+1 850 580 5200",
    "sg:postcode":"32310",
    "sg:province":"FL",
    "sg:tags":[
        "shop",
        "thrift"
    ],
    "wof:name":"Goodson's & More",
    "wof:placetype":"venue"
},
  "geometry": {"coordinates":[-84.30840499999999,30.425573],"type":"Point"}
}