{
  "type": "Feature",
  "properties": {
    "iso:country":"US",
    "sg:address":"2321 SW 57th Ter",
    "sg:city":"Hollywood",
    "sg:classifiers":[
        {
            "category":"Wholesale",
            "subcategory":"Machinery & Supplies",
            "type":"Manufacturing & Wholesale Goods"
        }
    ],
    "sg:phone":"+1 954 962 8445",
    "sg:postcode":"33023",
    "sg:province":"FL",
    "sg:tags":[
        "equipment",
        "transportation"
    ],
    "wof:name":"Abet Propeller Technologies",
    "wof:placetype":"venue"
},
  "geometry": {"coordinates":[-80.20096700000001,25.988023],"type":"Point"}
}