{
  "type": "Feature",
  "properties": {
    "iso:country":"US",
    "sg:address":"1999 Main St",
    "sg:city":"Sarasota",
    "sg:classifiers":[
        {
            "category":"Banks & Credit Unions",
            "subcategory":"Investment Brokerage",
            "type":"Services"
        }
    ],
    "sg:phone":"+1 941 365 8500",
    "sg:postcode":"34236",
    "sg:province":"FL",
    "sg:tags":[
        "stock",
        "bond"
    ],
    "sg:website":"www.leggmason.com",
    "wof:name":"Legg Mason Wood Walker Inc",
    "wof:placetype":"venue"
},
  "geometry": {"coordinates":[-82.532721,27.336467],"type":"Point"}
}