{
  "type": "Feature",
  "properties": {
    "iso:country":"US",
    "sg:address":"3322 SE Federal Hwy",
    "sg:city":"Stuart",
    "sg:classifiers":[
        {
            "category":"Personal",
            "subcategory":"Beauty Salon",
            "type":"Services"
        }
    ],
    "sg:phone":"+1 772 286 7022",
    "sg:postcode":"34997",
    "sg:province":"FL",
    "sg:tags":[
        "shop"
    ],
    "wof:name":"Champs Haircuts",
    "wof:placetype":"venue"
},
  "geometry": {"coordinates":[-80.226158,27.164264],"type":"Point"}
}