{
  "type": "Feature",
  "properties": {
    "iso:country":"US",
    "sg:address":"10601 NW 41st St",
    "sg:city":"Doral",
    "sg:classifiers":[
        {
            "category":"Banks & Credit Unions",
            "subcategory":"Bank",
            "type":"Services"
        },
        {
            "category":"Banks & Credit Unions",
            "subcategory":"Financial Services",
            "type":"Services"
        }
    ],
    "sg:phone":"+1 305 597 5818",
    "sg:postcode":"33178",
    "sg:province":"FL",
    "sg:tags":[
        "commercial",
        "loan",
        "saving",
        "mortgage"
    ],
    "sg:website":"https://www.wachovia.com/?DCMP=KNL-CPS-DS-Directory-0703&HBX_PK=Banks&HBX_OU=71",
    "wof:name":"Wachovia Bank",
    "wof:placetype":"venue"
},
  "geometry": {"coordinates":[-80.368329,25.811729],"type":"Point"}
}