{
  "type": "Feature",
  "properties": {
    "iso:country":"US",
    "sg:address":"528 S North Lake Blvd",
    "sg:city":"Altamonte Spgs",
    "sg:classifiers":[
        {
            "category":"Professional",
            "subcategory":"Printing & Photocopies",
            "type":"Services"
        }
    ],
    "sg:phone":"+1 407 834 3886",
    "sg:postcode":"32701",
    "sg:province":"FL",
    "sg:tags":[
        "duplicating",
        "copying"
    ],
    "wof:name":"Copy Control Ctr",
    "wof:placetype":"venue"
},
  "geometry": {"coordinates":[-81.38647899999999,28.653305],"type":"Point"}
}