{
  "type": "Feature",
  "properties": {
    "iso:country":"US",
    "sg:address":"1091 E 26th St",
    "sg:city":"Hialeah",
    "sg:classifiers":[
        {
            "category":"Retail",
            "subcategory":"Laundry & Dry Cleaning",
            "type":"Services"
        }
    ],
    "sg:phone":"+1 786 507 0050",
    "sg:postcode":"33013",
    "sg:province":"FL",
    "wof:name":"Monte De Oca Filters Service Inc",
    "wof:placetype":"venue"
},
  "geometry": {"coordinates":[-80.26088900000001,25.846481],"type":"Point"}
}