{
  "type": "Feature",
  "properties": {
    "iso:country":"US",
    "sg:address":"101 E Kennedy Blvd",
    "sg:city":"Tampa",
    "sg:classifiers":[
        {
            "category":"Banks & Credit Unions",
            "subcategory":"Bank",
            "type":"Services"
        }
    ],
    "sg:phone":"+1 813 225 8153",
    "sg:postcode":"33602",
    "sg:province":"FL",
    "sg:tags":[
        "national"
    ],
    "wof:name":"Bank of America",
    "wof:placetype":"venue"
},
  "geometry": {"coordinates":[-82.458772,27.947405],"type":"Point"}
}