{
  "type": "Feature",
  "properties": {
    "addr:full":"1209 Lake Loop Winter Haven FL 33880",
    "addr:housenumber":"1209",
    "addr:postcode":"33880",
    "addr:street":"Lake Loop",
    "iso:country":"US",
    "sg:address":"1209 Lake Loop",
    "sg:city":"Winter Haven",
    "sg:classifiers":[
        {
            "category":"Building & Trades",
            "subcategory":"Cleaning & Sanitation",
            "type":"Services"
        }
    ],
    "sg:phone":"+1 863 294 2319",
    "sg:postcode":"33880",
    "sg:province":"FL",
    "sg:tags":[
        "maintenance"
    ],
    "wof:name":"Fire Protection Services",
    "wof:placetype":"venue"
},
  "geometry": {"coordinates":[-81.78700000000001,28.013686],"type":"Point"}
}