{
  "type": "Feature",
  "properties": {
    "iso:country":"US",
    "sg:address":"1911 Seward Ave",
    "sg:city":"Naples",
    "sg:classifiers":[
        {
            "category":"Professional",
            "subcategory":"Art Services",
            "type":"Services"
        },
        {
            "category":"Home & Garden",
            "subcategory":"Building Materials",
            "type":"Retail Goods"
        },
        {
            "category":"Building & Trades",
            "subcategory":"Construction",
            "type":"Services"
        },
        {
            "category":"Train Station",
            "subcategory":"Rail",
            "type":"Transportation"
        }
    ],
    "sg:phone":"+1 239 597 5374",
    "sg:postcode":"34109",
    "sg:province":"FL",
    "sg:tags":[
        "stairway",
        "ornamental",
        "welder",
        "work",
        "metal",
        "rails",
        "accessory",
        "railing",
        "contractor",
        "fence-sales"
    ],
    "sg:website":"http://www.customornamentals.com",
    "wof:name":"Custom Ornamental Iron Works Inc",
    "wof:placetype":"venue"
},
  "geometry": {"coordinates":[-81.77989599999999,26.215452],"type":"Point"}
}