{
  "type": "Feature",
  "properties": {
    "iso:country":"US",
    "sg:address":"10275 Gregory Ave",
    "sg:city":"Hastings",
    "sg:classifiers":[
        {
            "category":"Building & Trades",
            "subcategory":"Construction",
            "type":"Services"
        }
    ],
    "sg:phone":"+1 386 325 5299",
    "sg:postcode":"32145",
    "sg:province":"FL",
    "sg:tags":[
        "clearing",
        "land",
        "leveling"
    ],
    "wof:name":"First Coast Tractor Svc",
    "wof:placetype":"venue"
},
  "geometry": {"coordinates":[-81.49068800000001,29.640563],"type":"Point"}
}