{
  "type": "Feature",
  "properties": {
    "iso:country":"US",
    "sg:address":"844 SE 8th St",
    "sg:city":"Hialeah",
    "sg:classifiers":[
        {
            "category":"Shopping",
            "subcategory":"Clothing, Apparel, & Fashions",
            "type":"Retail Goods"
        }
    ],
    "sg:phone":"+1 305 885 5808",
    "sg:postcode":"33010",
    "sg:province":"FL",
    "sg:tags":[
        "designer"
    ],
    "wof:name":"Disenos Exclusivos Of Miami",
    "wof:placetype":"venue"
},
  "geometry": {"coordinates":[-80.264735,25.815702],"type":"Point"}
}