{
  "type": "Feature",
  "properties": {
    "iso:country":"US",
    "sg:address":"174 W Comstock Ave",
    "sg:city":"Winter Park",
    "sg:classifiers":[
        {
            "category":"Professional",
            "subcategory":"Lawyer & Legal Services",
            "type":"Services"
        }
    ],
    "sg:phone":"+1 407 644 5151",
    "sg:postcode":"32789",
    "sg:province":"FL",
    "wof:name":"Bounds Gonzalez Pl",
    "wof:placetype":"venue"
},
  "geometry": {"coordinates":[-81.351681,28.593948],"type":"Point"}
}