{
  "type": "Feature",
  "properties": {
    "iso:country":"US",
    "sg:address":"1190 NW 95th St Ste 201",
    "sg:city":"Miami",
    "sg:classifiers":[
        {
            "category":"Health Services",
            "subcategory":"Doctor",
            "type":"Services"
        },
        {
            "category":"Health Services",
            "subcategory":"Health Practitioner",
            "type":"Services"
        }
    ],
    "sg:phone":"+1 305 758 6271",
    "sg:postcode":"33150",
    "sg:province":"FL",
    "sg:tags":[
        "physician",
        "ophthalmology",
        "surgeons",
        "surgeon"
    ],
    "wof:name":"Miami Eye Specialists",
    "wof:placetype":"venue"
},
  "geometry": {"coordinates":[-80.214647,25.861671],"type":"Point"}
}