{
  "type": "Feature",
  "properties": {
    "addr:full":"1627 Leeway Ave Orlando FL 32810",
    "addr:housenumber":"1627",
    "addr:postcode":"32810",
    "addr:street":"Leeway Ave",
    "iso:country":"US",
    "sg:address":"1627 Leeway Ave",
    "sg:city":"Orlando",
    "sg:classifiers":[
        {
            "category":"Building & Trades",
            "subcategory":"Pest Control",
            "type":"Services"
        }
    ],
    "sg:phone":"+1 407 647 3260",
    "sg:postcode":"32810",
    "sg:province":"FL",
    "sg:tags":[
        "industrial",
        "services-commercial"
    ],
    "wof:name":"Era Exterminating Inc",
    "wof:placetype":"venue"
},
  "geometry": {"coordinates":[-81.40512,28.614471],"type":"Point"}
}