{
  "type": "Feature",
  "properties": {
    "iso:country":"US",
    "sg:address":"1744 Co Rd 416N",
    "sg:city":"Lake Panasoffkee",
    "sg:classifiers":[
        {
            "category":"Building & Trades",
            "subcategory":"Landscaping Services",
            "type":"Services"
        }
    ],
    "sg:phone":"+1 352 568 8290",
    "sg:postcode":"33538",
    "sg:province":"FL",
    "sg:tags":[
        "lawn",
        "maintenance",
        "grounds"
    ],
    "wof:name":"B & T Lawn Svc",
    "wof:placetype":"venue"
},
  "geometry": {"coordinates":[-82.138897,28.779336],"type":"Point"}
}