{
  "type": "Feature",
  "properties": {
    "iso:country":"US",
    "sg:address":"6490 Homestead Ave",
    "sg:city":"Cocoa",
    "sg:classifiers":[
        {
            "category":"Professional",
            "subcategory":"Business Services",
            "type":"Services"
        }
    ],
    "sg:phone":"+1 407 896 7828",
    "sg:postcode":"32927",
    "sg:province":"FL",
    "sg:tags":[
        "interior",
        "plant",
        "care"
    ],
    "wof:name":"Fancy Plants",
    "wof:placetype":"venue"
},
  "geometry": {"coordinates":[-80.824089,28.473018],"type":"Point"}
}