{
  "type": "Feature",
  "properties": {
    "addr:full":"6330 46th St N Pinellas Park FL 33781",
    "addr:housenumber":"6330",
    "addr:postcode":"33781",
    "addr:street":"46Th St N",
    "iso:country":"US",
    "sg:address":"6330 46th St N",
    "sg:city":"Pinellas Park",
    "sg:classifiers":[
        {
            "category":"Freight",
            "type":"Transportation"
        }
    ],
    "sg:phone":"+1 727 323 8729",
    "sg:postcode":"33781",
    "sg:province":"FL",
    "sg:tags":[
        "warehouse"
    ],
    "wof:name":"S & S Landscape Not A Corp",
    "wof:placetype":"venue"
},
  "geometry": {"coordinates":[-82.695964,27.829233],"type":"Point"}
}