{
  "type": "Feature",
  "properties": {
    "addr:full":"31646 Saint Joe Rd Dade City FL 33525",
    "addr:housenumber":"31646",
    "addr:postcode":"33525",
    "addr:street":"Saint Joe Rd",
    "iso:country":"US",
    "sg:address":"31646 Saint Joe Rd",
    "sg:city":"Dade City",
    "sg:classifiers":[
        {
            "category":"Farming",
            "subcategory":"Orchard",
            "type":"Manufacturing & Wholesale Goods"
        }
    ],
    "sg:phone":"+1 352 588 2428",
    "sg:postcode":"33525",
    "sg:province":"FL",
    "sg:tags":[
        "citrus",
        "grove",
        "fruit"
    ],
    "wof:name":"Frassrand Estates Inc",
    "wof:placetype":"venue"
},
  "geometry": {"coordinates":[-82.28690899999999,28.375943],"type":"Point"}
}