{
  "type": "Feature",
  "properties": {
    "addr:full":"13110 N Dale Mabry Hwy Tampa FL 33618",
    "addr:housenumber":"13110",
    "addr:postcode":"33618",
    "addr:street":"N Dale Mabry Hwy",
    "iso:country":"US",
    "sg:address":"13110 N Dale Mabry Hwy",
    "sg:city":"Tampa",
    "sg:classifiers":[
        {
            "category":"Personal",
            "subcategory":"Massage",
            "type":"Services"
        },
        {
            "category":"Personal",
            "subcategory":"Beauty Salon",
            "type":"Services"
        },
        {
            "category":"Personal",
            "subcategory":"Skin Care",
            "type":"Services"
        }
    ],
    "sg:phone":"+1 813 968 4836",
    "sg:postcode":"33618",
    "sg:province":"FL",
    "sg:tags":[
        "hair",
        "braiding",
        "therapist",
        "stylist"
    ],
    "sg:website":"http://www.shearart.com",
    "wof:name":"Shear Art Salon & Spa",
    "wof:placetype":"venue"
},
  "geometry": {"coordinates":[-82.50528,28.066674],"type":"Point"}
}