{
  "type": "Feature",
  "properties": {
    "addr:full":"8525 Pocasset Pl Orlando FL 32827",
    "addr:housenumber":"8525",
    "addr:postcode":"32827",
    "addr:street":"Pocasset Pl",
    "iso:country":"US",
    "sg:address":"8525 Pocasset Pl",
    "sg:city":"Orlando",
    "sg:classifiers":[
        {
            "category":"Banks & Credit Unions",
            "subcategory":"Investment Brokerage",
            "type":"Services"
        }
    ],
    "sg:phone":"+1 407 356 3549",
    "sg:postcode":"32827",
    "sg:province":"FL",
    "sg:tags":[
        "trust"
    ],
    "wof:name":"Nea Trust",
    "wof:placetype":"venue"
},
  "geometry": {"coordinates":[-81.344872,28.440002],"type":"Point"}
}