{
  "type": "Feature",
  "properties": {
    "iso:country":"US",
    "sg:address":"13311 Pinto Ln",
    "sg:city":"Fort Myers",
    "sg:classifiers":[
        {
            "category":"Personal",
            "type":"Services"
        }
    ],
    "sg:phone":"+1 239 768 3186",
    "sg:postcode":"33912",
    "sg:province":"FL",
    "wof:name":"Serenity Spa For Total Health",
    "wof:placetype":"venue"
},
  "geometry": {"coordinates":[-81.812473,26.549487],"type":"Point"}
}