{
  "type": "Feature",
  "properties": {
    "iso:country":"US",
    "sg:address":"5601 Butler National Dr",
    "sg:city":"Orlando",
    "sg:classifiers":[
        {
            "category":"Restaurant",
            "type":"Food & Drink"
        }
    ],
    "sg:phone":"+1 407 854 3434",
    "sg:postcode":"32812",
    "sg:province":"FL",
    "wof:name":"Cafe Sabraso",
    "wof:placetype":"venue"
},
  "geometry": {"coordinates":[-81.31379099999999,28.466036],"type":"Point"}
}