{
  "type": "Feature",
  "properties": {
    "iso:country":"US",
    "sg:address":"2849 Apalachee Pkwy",
    "sg:city":"Tallahassee",
    "sg:classifiers":[
        {
            "category":"Home & Garden",
            "subcategory":"Building Materials",
            "type":"Retail Goods"
        }
    ],
    "sg:phone":"+1 850 309 7533",
    "sg:postcode":"32301",
    "sg:province":"FL",
    "wof:name":"Eppes Decorating-Eastside",
    "wof:placetype":"venue"
},
  "geometry": {"coordinates":[-84.23195200000001,30.427049],"type":"Point"}
}