{
  "type": "Feature",
  "properties": {
    "iso:country":"US",
    "sg:address":"7113 N Nebraska Ave",
    "sg:city":"Tampa",
    "sg:classifiers":[
        {
            "category":"Shopping",
            "subcategory":"Pawn Shop",
            "type":"Retail Goods"
        }
    ],
    "sg:phone":"+1 813 238 3286",
    "sg:postcode":"33604",
    "sg:province":"FL",
    "sg:tags":[
        "pawnbroker"
    ],
    "sg:website":"http://www.ezpawninc.com",
    "wof:name":"Ez Pawn B0205",
    "wof:placetype":"venue"
},
  "geometry": {"coordinates":[-82.451302,28.012582],"type":"Point"}
}