{
  "type": "Feature",
  "properties": {
    "iso:country":"US",
    "sg:address":"420 Lincoln Rd",
    "sg:city":"Miami Beach",
    "sg:classifiers":[
        {
            "category":"Banks & Credit Unions",
            "subcategory":"Financial Services",
            "type":"Services"
        }
    ],
    "sg:phone":"+1 305 531 6469",
    "sg:postcode":"33139",
    "sg:province":"FL",
    "sg:tags":[
        "broker",
        "mortgage"
    ],
    "wof:name":"Midtown Mortgage Corp",
    "wof:placetype":"venue"
},
  "geometry": {"coordinates":[-80.132115,25.790543],"type":"Point"}
}