{
  "type": "Feature",
  "properties": {
    "addr:full":"20321 Summerlin Rd Fort Myers FL 33908",
    "addr:housenumber":"20321",
    "addr:postcode":"33908",
    "addr:street":"Summerlin Rd",
    "iso:country":"US",
    "sg:address":"20321 Summerlin Rd",
    "sg:city":"Fort Myers",
    "sg:classifiers":[
        {
            "category":"Food & Beverages",
            "subcategory":"Groceries & Convenience Stores",
            "type":"Retail Goods"
        }
    ],
    "sg:phone":"+1 239 454 0145",
    "sg:postcode":"33908",
    "sg:province":"FL",
    "sg:tags":[
        "grocer"
    ],
    "wof:name":"Publix Super Market",
    "wof:placetype":"venue"
},
  "geometry": {"coordinates":[-81.94135,26.493995],"type":"Point"}
}