{
  "type": "Feature",
  "properties": {
    "addr:full":"12995 S Cleveland Ave Ste 156 Fort Myers FL 33907",
    "addr:housenumber":"12995",
    "addr:postcode":"myers;33907",
    "addr:street":"S Cleveland Ave Ste 156",
    "iso:country":"US",
    "sg:address":"12995 S Cleveland Ave Ste 156",
    "sg:city":"Fort Myers",
    "sg:classifiers":[
        {
            "category":"Shopping",
            "subcategory":"Clothing, Apparel, & Fashions",
            "type":"Retail Goods"
        }
    ],
    "sg:phone":"+1 239 936 1001",
    "sg:postcode":"33907",
    "sg:province":"FL",
    "sg:tags":[
        "accessory",
        "clothing",
        "women's"
    ],
    "wof:name":"Elite Repeat Designer Labels",
    "wof:placetype":"venue"
},
  "geometry": {"coordinates":[-81.87159699999999,26.552],"type":"Point"}
}