{
  "type": "Feature",
  "properties": {
    "iso:country":"US",
    "sg:address":"6420 Ridge Rd",
    "sg:city":"Port Richey",
    "sg:classifiers":[
        {
            "category":"Social Services",
            "type":"Services"
        }
    ],
    "sg:phone":"+1 727 844 0442",
    "sg:postcode":"34668",
    "sg:province":"FL",
    "sg:tags":[
        "information",
        "abuse",
        "domestic",
        "treatment"
    ],
    "wof:name":"Western Judicial Svc Inc",
    "wof:placetype":"venue"
},
  "geometry": {"coordinates":[-82.70728800000001,28.280538],"type":"Point"}
}