{
  "type": "Feature",
  "properties": {
    "addr:full":"3111 Willow St Cottondale FL 32431",
    "addr:housenumber":"3111",
    "addr:postcode":"32431",
    "addr:street":"Willow St",
    "iso:country":"US",
    "sg:address":"3111 Willow St",
    "sg:city":"Cottondale",
    "sg:classifiers":[
        {
            "category":"Real Estate",
            "subcategory":"Real Estate Operator",
            "type":"Services"
        }
    ],
    "sg:phone":"+1 850 352 2281",
    "sg:postcode":"32431",
    "sg:province":"FL",
    "sg:tags":[
        "apartment"
    ],
    "wof:name":"Villas Apartments",
    "wof:placetype":"venue"
},
  "geometry": {"coordinates":[-85.36842900000001,30.792726],"type":"Point"}
}