{
  "type": "Feature",
  "properties": {
    "iso:country":"US",
    "sg:address":"840 Tanager Rd",
    "sg:city":"Fort Walton Beach",
    "sg:classifiers":[
        {
            "category":"Retail",
            "subcategory":"Laundry & Dry Cleaning",
            "type":"Services"
        }
    ],
    "sg:phone":"+1 850 862 7713",
    "sg:postcode":"32547",
    "sg:province":"FL",
    "wof:name":"Troys Precision Carpet Care",
    "wof:placetype":"venue"
},
  "geometry": {"coordinates":[-86.62587499999999,30.464609],"type":"Point"}
}