{
  "type": "Feature",
  "properties": {
    "iso:country":"US",
    "sg:address":"1900 Sunset Harbour Dr",
    "sg:city":"Miami Beach",
    "sg:classifiers":[
        {
            "category":"Health Services",
            "subcategory":"Doctor",
            "type":"Services"
        }
    ],
    "sg:phone":"+1 305 674 0055",
    "sg:postcode":"33139",
    "sg:province":"FL",
    "sg:tags":[
        "physician",
        "surgeon"
    ],
    "wof:name":"Pedro Armenteros MD",
    "wof:placetype":"venue"
},
  "geometry": {"coordinates":[-80.14432600000001,25.791757],"type":"Point"}
}