{
  "type": "Feature",
  "properties": {
    "addr:full":"3434 SW 171st Ter Hollywood FL 33027",
    "addr:housenumber":"3434",
    "addr:postcode":"33027",
    "addr:street":"Sw 171St Ter",
    "iso:country":"US",
    "sg:address":"3434 SW 171st Ter",
    "sg:city":"Hollywood",
    "sg:classifiers":[
        {
            "category":"Professional",
            "type":"Services"
        }
    ],
    "sg:phone":"+1 954 438 5924",
    "sg:postcode":"33027",
    "sg:province":"FL",
    "wof:name":"Benepom Inc",
    "wof:placetype":"venue"
},
  "geometry": {"coordinates":[-80.375187,25.977322],"type":"Point"}
}