{
  "type": "Feature",
  "properties": {
    "iso:country":"US",
    "sg:address":"104 Crandon Blvd",
    "sg:city":"Key Biscayne",
    "sg:classifiers":[
        {
            "category":"Wholesale",
            "subcategory":"Durable Goods & Equipment",
            "type":"Manufacturing & Wholesale Goods"
        },
        {
            "category":"Banks & Credit Unions",
            "subcategory":"Bank",
            "type":"Services"
        }
    ],
    "sg:phone":"+1 305 361 7573",
    "sg:postcode":"33149",
    "sg:province":"FL",
    "sg:tags":[
        "federal",
        "importer",
        "agency"
    ],
    "wof:name":"Jaspergreen Corp",
    "wof:placetype":"venue"
},
  "geometry": {"coordinates":[-80.163042,25.697321],"type":"Point"}
}