{
  "type": "Feature",
  "properties": {
    "iso:country":"US",
    "sg:address":"344 S Beach St",
    "sg:city":"Daytona Beach",
    "sg:classifiers":[
        {
            "category":"Organizations",
            "subcategory":"Non-profit Organization",
            "type":"Services"
        }
    ],
    "sg:phone":"+1 386 258 0250",
    "sg:postcode":"32114",
    "sg:province":"FL",
    "sg:tags":[
        "abused",
        "support",
        "woman",
        "for",
        "child"
    ],
    "wof:name":"I Care",
    "wof:placetype":"venue"
},
  "geometry": {"coordinates":[-81.016952,29.206542],"type":"Point"}
}