{
  "type": "Feature",
  "properties": {
    "addr:full":"435 Pool Branch Rd Fort Meade FL 33841",
    "addr:housenumber":"435",
    "addr:postcode":"33841",
    "addr:street":"Pool Branch Rd",
    "iso:country":"US",
    "sg:address":"435 Pool Branch Rd",
    "sg:city":"Fort Meade",
    "sg:classifiers":[
        {
            "category":"Building & Trades",
            "subcategory":"Construction",
            "type":"Services"
        }
    ],
    "sg:phone":"+1 863 285 9630",
    "sg:postcode":"33841",
    "sg:province":"FL",
    "sg:tags":[
        "contractor"
    ],
    "wof:name":"Edmund Contracting Inc",
    "wof:placetype":"venue"
},
  "geometry": {"coordinates":[-81.768912,27.75578],"type":"Point"}
}