{
  "type": "Feature",
  "properties": {
    "iso:country":"US",
    "sg:address":"222 S Forest Ave",
    "sg:city":"Avon Park",
    "sg:classifiers":[
        {
            "category":"Retail",
            "subcategory":"Repair Shop",
            "type":"Services"
        }
    ],
    "sg:phone":"+1 863 453 9353",
    "sg:postcode":"33825",
    "sg:province":"FL",
    "sg:tags":[
        "welding"
    ],
    "wof:name":"Pro Weld Inc",
    "wof:placetype":"venue"
},
  "geometry": {"coordinates":[-81.50306500000001,27.593293],"type":"Point"}
}