{
  "type": "Feature",
  "properties": {
    "addr:full":"455 Plumhollow Ln Maitland FL 32751",
    "addr:housenumber":"455",
    "addr:postcode":"32751",
    "addr:street":"Plumhollow Ln",
    "iso:country":"US",
    "sg:address":"455 Plumhollow Ln",
    "sg:city":"Maitland",
    "sg:classifiers":[
        {
            "category":"Communications",
            "subcategory":"Film & Video Production",
            "type":"Services"
        },
        {
            "category":"Communications",
            "subcategory":"Television Station",
            "type":"Services"
        }
    ],
    "sg:phone":"+1 407 332 0720",
    "sg:postcode":"32751",
    "sg:province":"FL",
    "sg:tags":[
        "companies-film",
        "producer",
        "tv",
        "program",
        "radio",
        "distributor"
    ],
    "wof:name":"Firestorm Inc",
    "wof:placetype":"venue"
},
  "geometry": {"coordinates":[-81.37335400000001,28.641563],"type":"Point"}
}