{
  "type": "Feature",
  "properties": {
    "addr:full":"1128 E Semoran Blvd Apopka FL 32703",
    "addr:housenumber":"1128 e",
    "addr:postcode":"32703",
    "addr:street":"Semoran Blvd",
    "iso:country":"US",
    "sg:address":"1128 E Semoran Blvd",
    "sg:city":"Apopka",
    "sg:classifiers":[
        {
            "category":"Banks & Credit Unions",
            "subcategory":"Bank",
            "type":"Services"
        }
    ],
    "sg:phone":"+1 407 389 1234",
    "sg:postcode":"32703",
    "sg:province":"FL",
    "sg:tags":[
        "loan",
        "real estate"
    ],
    "wof:name":"Yes Mortgage",
    "wof:placetype":"venue"
},
  "geometry": {"coordinates":[-81.48939300000001,28.672935],"type":"Point"}
}