{
  "type": "Feature",
  "properties": {
    "iso:country":"US",
    "sg:address":"4533 Highway Ave",
    "sg:city":"Jacksonville",
    "sg:classifiers":[
        {
            "category":"Building & Trades",
            "subcategory":"Construction",
            "type":"Services"
        }
    ],
    "sg:phone":"+1 904 387 2481",
    "sg:postcode":"32254",
    "sg:province":"FL",
    "sg:tags":[
        "dry wall",
        "contractor"
    ],
    "wof:name":"Smith Brothers Plastering Co",
    "wof:placetype":"venue"
},
  "geometry": {"coordinates":[-81.722514,30.32184],"type":"Point"}
}