{
  "type": "Feature",
  "properties": {
    "addr:full":"7100 SW 8th Ct Fort Lauderdale FL 33317",
    "addr:housenumber":"7100",
    "addr:postcode":"33317",
    "addr:street":"Sw 8Th Ct",
    "iso:country":"US",
    "sg:address":"7100 SW 8th Ct",
    "sg:city":"Fort Lauderdale",
    "sg:classifiers":[
        {
            "category":"Building & Trades",
            "subcategory":"Landscaping Services",
            "type":"Services"
        }
    ],
    "sg:phone":"+1 954 689 8124",
    "sg:postcode":"33317",
    "sg:province":"FL",
    "sg:tags":[
        "contracting",
        "lawn"
    ],
    "wof:name":"French Cut Landscaping Inc",
    "wof:placetype":"venue"
},
  "geometry": {"coordinates":[-80.24240899999999,26.109955],"type":"Point"}
}