{
  "type": "Feature",
  "properties": {
    "iso:country":"US",
    "sg:address":"13234 Cherry Bark Cir",
    "sg:city":"Riverview",
    "sg:classifiers":[
        {
            "category":"Professional",
            "subcategory":"Detective & Security Services",
            "type":"Services"
        }
    ],
    "sg:phone":"+1 813 389 3147",
    "sg:postcode":"33579",
    "sg:province":"FL",
    "sg:tags":[
        "information",
        "bureau"
    ],
    "wof:name":"People's Choice Realty Services",
    "wof:placetype":"venue"
},
  "geometry": {"coordinates":[-82.311094,27.791612],"type":"Point"}
}