{
  "type": "Feature",
  "properties": {
    "iso:country":"US",
    "sg:address":"101 Dunbar Ave",
    "sg:city":"Oldsmar",
    "sg:classifiers":[
        {
            "category":"Building & Trades",
            "subcategory":"Landscaping Services",
            "type":"Services"
        },
        {
            "category":"Farming",
            "subcategory":"Nursery",
            "type":"Manufacturing & Wholesale Goods"
        }
    ],
    "sg:phone":"+1 727 786 7666",
    "sg:postcode":"34677",
    "sg:province":"FL",
    "sg:tags":[
        "lawn",
        "nurseries-plants",
        "tree",
        "contractor",
        "arborist",
        "landscape"
    ],
    "sg:website":"http://www.kirabannerworks.com",
    "wof:name":"Raymow Tree Service",
    "wof:placetype":"venue"
},
  "geometry": {"coordinates":[-82.658287,28.039789],"type":"Point"}
}