{
  "type": "Feature",
  "properties": {
    "iso:country":"US",
    "sg:address":"10 Faulkner St",
    "sg:city":"New Smyrna Beach",
    "sg:classifiers":[
        {
            "category":"Insurance",
            "subcategory":"Insurance Agent",
            "type":"Services"
        }
    ],
    "sg:phone":"+1 386 409 2111",
    "sg:postcode":"32168",
    "sg:province":"FL",
    "wof:name":"Reed Wade Insurance",
    "wof:placetype":"venue"
},
  "geometry": {"coordinates":[-80.923511,29.025972],"type":"Point"}
}