{
  "type": "Feature",
  "properties": {
    "addr:full":"9731 W Mcnab Rd Tamarac FL 33321",
    "addr:housenumber":"9731",
    "addr:postcode":"33321",
    "addr:street":"W Mcnab Rd",
    "iso:country":"US",
    "sg:address":"9731 W Mcnab Rd",
    "sg:city":"Tamarac",
    "sg:classifiers":[
        {
            "category":"Building & Trades",
            "subcategory":"Construction",
            "type":"Services"
        }
    ],
    "sg:phone":"+1 863 414 1038",
    "sg:postcode":"33321",
    "sg:province":"FL",
    "sg:tags":[
        "system",
        "contractor",
        "air conditioning"
    ],
    "wof:name":"Just Cool It Air Conditioning Co",
    "wof:placetype":"venue"
},
  "geometry": {"coordinates":[-80.281369,26.208333],"type":"Point"}
}