{
  "type": "Feature",
  "properties": {
    "iso:country":"US",
    "sg:address":"2946 Howland Blvd Ste C",
    "sg:city":"Deltona",
    "sg:classifiers":[
        {
            "category":"Personal",
            "subcategory":"Beauty Salon",
            "type":"Services"
        }
    ],
    "sg:phone":"+1 386 789 2322",
    "sg:postcode":"32725",
    "sg:province":"FL",
    "wof:name":"Abracadabra Hair Styling",
    "wof:placetype":"venue"
},
  "geometry": {"coordinates":[-81.22776,28.94562],"type":"Point"}
}