{
  "type": "Feature",
  "properties": {
    "iso:country":"US",
    "sg:address":"12011 State Hwy 89",
    "sg:city":"Jay",
    "sg:phone":"+1 850 675 3070",
    "sg:postcode":"32565",
    "sg:province":"FL",
    "sg:tags":[
        "farm",
        "field",
        "crop",
        "cotton"
    ],
    "wof:name":"Jones L Jerry Farm",
    "wof:placetype":"venue"
},
  "geometry": {"coordinates":[-87.15126600000001,30.855218],"type":"Point"}
}