{
  "type": "Feature",
  "properties": {
    "addr:full":"3885 Oakwater Cir Orlando FL 32806",
    "addr:housenumber":"3885",
    "addr:postcode":"32806",
    "addr:street":"Oakwater Cir",
    "iso:country":"US",
    "sg:address":"3885 Oakwater Cir",
    "sg:city":"Orlando",
    "sg:classifiers":[
        {
            "category":"Health Services",
            "subcategory":"Doctor",
            "type":"Services"
        }
    ],
    "sg:phone":"+1 407 826 0101",
    "sg:postcode":"32806",
    "sg:province":"FL",
    "sg:tags":[
        "clinic"
    ],
    "wof:name":"Gambro Healthcare",
    "wof:placetype":"venue"
},
  "geometry": {"coordinates":[-81.37578499999999,28.501607],"type":"Point"}
}