{
  "type": "Feature",
  "properties": {
    "addr:full":"21706 Tolliver Rd Fountain FL 32438",
    "addr:postcode":"21706;32438",
    "addr:street":"Tolliver Rd",
    "iso:country":"US",
    "sg:address":"21706 Tolliver Rd",
    "sg:city":"Fountain",
    "sg:classifiers":[
        {
            "category":"Professional",
            "subcategory":"Detective & Security Services",
            "type":"Services"
        }
    ],
    "sg:phone":"+1 850 303 1681",
    "sg:postcode":"32438",
    "sg:province":"FL",
    "sg:tags":[
        "information",
        "bureau"
    ],
    "wof:name":"Advanced Mobile Er Services",
    "wof:placetype":"venue"
},
  "geometry": {"coordinates":[-85.403341,30.543895],"type":"Point"}
}