{
  "type": "Feature",
  "properties": {
    "iso:country":"US",
    "sg:address":"1132 W 29th St",
    "sg:city":"Hialeah",
    "sg:classifiers":[
        {
            "category":"Freight",
            "type":"Transportation"
        }
    ],
    "sg:phone":"+1 305 823 8188",
    "sg:postcode":"33012",
    "sg:province":"FL",
    "wof:name":"Leos Trucks & Moving Corporat",
    "wof:placetype":"venue"
},
  "geometry": {"coordinates":[-80.30570899999999,25.847915],"type":"Point"}
}