{
  "type": "Feature",
  "properties": {
    "addr:full":"1943 Empress Ct Naples FL 34110",
    "addr:housenumber":"1943",
    "addr:postcode":"34110",
    "addr:street":"Empress Ct",
    "iso:country":"US",
    "sg:address":"1943 Empress Ct",
    "sg:city":"Naples",
    "sg:classifiers":[
        {
            "category":"Shopping",
            "subcategory":"Gifts & Souvenirs",
            "type":"Retail Goods"
        }
    ],
    "sg:phone":"+1 239 591 8049",
    "sg:postcode":"34110",
    "sg:province":"FL",
    "sg:tags":[
        "basket"
    ],
    "wof:name":"Empress Gift Designs",
    "wof:placetype":"venue"
},
  "geometry": {"coordinates":[-81.771118,26.30048],"type":"Point"}
}