{
  "type": "Feature",
  "properties": {
    "addr:full":"1990 S University Dr Davie FL 33324",
    "addr:housenumber":"1990",
    "addr:postcode":"33324",
    "addr:street":"S University Dr",
    "iso:country":"US",
    "sg:address":"1990 S University Dr",
    "sg:city":"Davie",
    "sg:classifiers":[
        {
            "category":"Shopping",
            "subcategory":"Department Store",
            "type":"Retail Goods"
        }
    ],
    "sg:phone":"+1 954 475 8779",
    "sg:postcode":"33324",
    "sg:province":"FL",
    "sg:website":"www.rossstores.com",
    "wof:name":"Ross Dress For Less",
    "wof:placetype":"venue"
},
  "geometry": {"coordinates":[-80.25116,26.09662],"type":"Point"}
}