{
  "type": "Feature",
  "properties": {
    "iso:country":"US",
    "sg:address":"3180 Mandeville St",
    "sg:city":"Deltona",
    "sg:classifiers":[
        {
            "category":"Building & Trades",
            "subcategory":"Construction",
            "type":"Services"
        }
    ],
    "sg:phone":"+1 386 789 5590",
    "sg:postcode":"32738",
    "sg:province":"FL",
    "sg:tags":[
        "air",
        "heating",
        "conditioning/hvac"
    ],
    "sg:website":"www.laraair.com",
    "wof:name":"Lara Air Inc",
    "wof:placetype":"venue"
},
  "geometry": {"coordinates":[-81.17617,28.94719],"type":"Point"}
}