{
  "type": "Feature",
  "properties": {
    "iso:country":"US",
    "sg:address":"6222 99th St E",
    "sg:city":"Bradenton",
    "sg:classifiers":[
        {
            "category":"Professional",
            "subcategory":"Business Services",
            "type":"Services"
        }
    ],
    "sg:phone":"+1 941 753 9977",
    "sg:postcode":"34202",
    "sg:province":"FL",
    "sg:tags":[
        "pool",
        "swimming"
    ],
    "wof:name":"Chris Hegedus Pool Care",
    "wof:placetype":"venue"
},
  "geometry": {"coordinates":[-82.44274799999999,27.434073],"type":"Point"}
}