{
  "type": "Feature",
  "properties": {
    "addr:full":"1000 NW 57th Ct Miami FL 33126",
    "addr:housenumber":"1000",
    "addr:postcode":"33126",
    "addr:street":"Nw 57Th Ct",
    "iso:country":"US",
    "sg:address":"1000 NW 57th Ct",
    "sg:city":"Miami",
    "sg:classifiers":[
        {
            "category":"Professional",
            "subcategory":"Detective & Security Services",
            "type":"Services"
        }
    ],
    "sg:phone":"+1 305 267 8870",
    "sg:postcode":"33126",
    "sg:province":"FL",
    "sg:tags":[
        "information",
        "bureau"
    ],
    "wof:name":"First American Services Corp",
    "wof:placetype":"venue"
},
  "geometry": {"coordinates":[-80.28849,25.78019],"type":"Point"}
}