{
  "type": "Feature",
  "properties": {
    "iso:country":"US",
    "sg:address":"7200 NW 36th St",
    "sg:city":"Miami",
    "sg:classifiers":[
        {
            "category":"Retail",
            "subcategory":"Auto Repair",
            "type":"Services"
        }
    ],
    "sg:phone":"+1 305 592 5588",
    "sg:postcode":"33166",
    "sg:province":"FL",
    "wof:name":"Bugallo Texaco Service Center",
    "wof:placetype":"venue"
},
  "geometry": {"coordinates":[-80.31379699999999,25.809401],"type":"Point"}
}