{
  "type": "Feature",
  "properties": {
    "iso:country":"US",
    "sg:address":"4100 Goodlette Rd N",
    "sg:city":"Naples",
    "sg:classifiers":[
        {
            "category":"Professional",
            "type":"Services"
        }
    ],
    "sg:phone":"+1 239 434 5333",
    "sg:postcode":"34103",
    "sg:province":"FL",
    "sg:tags":[
        "establishment"
    ],
    "wof:name":"American Venture",
    "wof:placetype":"venue"
},
  "geometry": {"coordinates":[-81.79198700000001,26.198051],"type":"Point"}
}