{
  "type": "Feature",
  "properties": {
    "iso:country":"US",
    "sg:address":"13015 SW 89th Pl",
    "sg:city":"Miami",
    "sg:classifiers":[
        {
            "category":"Communications",
            "subcategory":"Film & Video Production",
            "type":"Services"
        }
    ],
    "sg:phone":"+1 305 710 9541",
    "sg:postcode":"33176",
    "sg:province":"FL",
    "sg:tags":[
        "taping"
    ],
    "wof:name":"Advantage Dvd Productions",
    "wof:placetype":"venue"
},
  "geometry": {"coordinates":[-80.33990799999999,25.647906],"type":"Point"}
}