{
  "type": "Feature",
  "properties": {
    "addr:full":"4021 SW 96th Ave Miami FL 33165",
    "addr:housenumber":"4021",
    "addr:postcode":"33165",
    "addr:street":"Sw 96Th Ave",
    "iso:country":"US",
    "sg:address":"4021 SW 96th Ave",
    "sg:city":"Miami",
    "sg:classifiers":[
        {
            "category":"Wholesale",
            "subcategory":"Medical Equipment & Supplies",
            "type":"Manufacturing & Wholesale Goods"
        }
    ],
    "sg:phone":"+1 305 553 2825",
    "sg:postcode":"33165",
    "sg:province":"FL",
    "sg:tags":[
        "physician",
        "surgeon"
    ],
    "wof:name":"B & B Respiratory Eqpt Inc",
    "wof:placetype":"venue"
},
  "geometry": {"coordinates":[-80.350476,25.730203],"type":"Point"}
}