{
  "type": "Feature",
  "properties": {
    "iso:country":"US",
    "sg:address":"4 SE Broadway St",
    "sg:city":"Ocala",
    "sg:classifiers":[
        {
            "category":"Professional",
            "subcategory":"Lawyer & Legal Services",
            "type":"Services"
        }
    ],
    "sg:phone":"+1 352 732 7218",
    "sg:postcode":"34471",
    "sg:province":"FL",
    "sg:tags":[
        "attorney",
        "death",
        "personal",
        "wrongful",
        "injury",
        "law"
    ],
    "sg:website":"http://www.bmaklaw.com",
    "wof:name":"Blanchard Merriam Adel & Kirkland P a",
    "wof:placetype":"venue"
},
  "geometry": {"coordinates":[-82.13689100000001,29.186301],"type":"Point"}
}