{
  "type": "Feature",
  "properties": {
    "addr:full":"8748 Forest Lake Dr Port Richey FL 34668",
    "addr:housenumber":"8748",
    "addr:postcode":"34668",
    "addr:street":"Forest Lake Dr",
    "iso:country":"US",
    "sg:address":"8748 Forest Lake Dr",
    "sg:city":"Port Richey",
    "sg:classifiers":[
        {
            "category":"Travel",
            "subcategory":"Travel Agent",
            "type":"Entertainment"
        }
    ],
    "sg:phone":"+1 727 847 5507",
    "sg:postcode":"34668",
    "sg:province":"FL",
    "sg:tags":[
        "agency"
    ],
    "wof:name":"Diamond Destinations Travel",
    "wof:placetype":"venue"
},
  "geometry": {"coordinates":[-82.68785200000001,28.284309],"type":"Point"}
}