{
  "type": "Feature",
  "properties": {
    "iso:country":"US",
    "sg:address":"8031 Muirhead Cir",
    "sg:city":"Boynton Beach",
    "sg:classifiers":[
        {
            "category":"Real Estate",
            "subcategory":"Real Estate Agent",
            "type":"Services"
        }
    ],
    "sg:phone":"+1 561 375 9483",
    "sg:postcode":"33472",
    "sg:province":"FL",
    "wof:name":"Schechter Realty",
    "wof:placetype":"venue"
},
  "geometry": {"coordinates":[-80.167762,26.556212],"type":"Point"}
}