{
  "type": "Feature",
  "properties": {
    "iso:country":"US",
    "sg:address":"11717 Trumbull Dr",
    "sg:city":"Spring Hill",
    "sg:classifiers":[
        {
            "category":"Building & Trades",
            "subcategory":"Cleaning & Sanitation",
            "type":"Services"
        }
    ],
    "sg:phone":"+1 352 650 6658",
    "sg:postcode":"34609",
    "sg:province":"FL",
    "sg:tags":[
        "janitor"
    ],
    "wof:name":"Madonna Dornan Cleaning",
    "wof:placetype":"venue"
},
  "geometry": {"coordinates":[-82.526797,28.44984],"type":"Point"}
}