{
  "type": "Feature",
  "properties": {
    "addr:full":"1904 SE 36th Ter Cape Coral FL 33904",
    "addr:housenumber":"1904",
    "addr:postcode":"33904",
    "addr:street":"Se 36Th Ter",
    "iso:country":"US",
    "sg:address":"1904 SE 36th Ter",
    "sg:city":"Cape Coral",
    "sg:classifiers":[
        {
            "category":"Shopping",
            "type":"Retail Goods"
        }
    ],
    "sg:phone":"+1 239 549 1533",
    "sg:postcode":"33904",
    "sg:province":"FL",
    "sg:tags":[
        "merchandise"
    ],
    "wof:name":"A Personal Shopper",
    "wof:placetype":"venue"
},
  "geometry": {"coordinates":[-81.933385,26.58452],"type":"Point"}
}