{
  "type": "Feature",
  "properties": {
    "iso:country":"US",
    "sg:address":"1593 Canterbury Cir",
    "sg:city":"Casselberry",
    "sg:classifiers":[
        {
            "category":"Shopping",
            "subcategory":"Computers & Home Electronics",
            "type":"Retail Goods"
        }
    ],
    "sg:phone":"+1 407 696 7665",
    "sg:postcode":"32707",
    "sg:province":"FL",
    "wof:name":"Media Innovations Inc",
    "wof:placetype":"venue"
},
  "geometry": {"coordinates":[-81.306161,28.662562],"type":"Point"}
}