{
  "type": "Feature",
  "properties": {
    "iso:country":"US",
    "sg:address":"21301 Powerline Rd",
    "sg:city":"Boca Raton",
    "sg:classifiers":[
        {
            "category":"Health Services",
            "subcategory":"Nursing And Care Facility",
            "type":"Services"
        },
        {
            "category":"Professional",
            "subcategory":"Management & Consulting",
            "type":"Services"
        }
    ],
    "sg:phone":"+1 561 477 3700",
    "sg:postcode":"33433",
    "sg:province":"FL",
    "sg:tags":[
        "home",
        "retirement",
        "community",
        "consultant"
    ],
    "sg:website":"www.flahealth.com",
    "wof:name":"Florida Health Consultants Inc",
    "wof:placetype":"venue"
},
  "geometry": {"coordinates":[-80.15313399999999,26.359873],"type":"Point"}
}