{
  "type": "Feature",
  "properties": {
    "iso:country":"US",
    "sg:address":"4021 S Pine Ave",
    "sg:city":"Ocala",
    "sg:classifiers":[
        {
            "category":"Autos & Motor Vehicles",
            "subcategory":"Automobile Sales",
            "type":"Retail Goods"
        }
    ],
    "sg:phone":"+1 352 690 7377",
    "sg:postcode":"34480",
    "sg:province":"FL",
    "sg:tags":[
        "dealers-used",
        "car",
        "used",
        "cars-wholesale"
    ],
    "wof:name":"Wise Auto Sales",
    "wof:placetype":"venue"
},
  "geometry": {"coordinates":[-82.113691,29.145705],"type":"Point"}
}