{
  "type": "Feature",
  "properties": {
    "iso:country":"US",
    "sg:address":"3615 Dupont Ave",
    "sg:city":"Jacksonville",
    "sg:classifiers":[
        {
            "category":"Shopping",
            "subcategory":"Clothing, Apparel, & Fashions",
            "type":"Retail Goods"
        }
    ],
    "sg:phone":"+1 904 737 0611",
    "sg:postcode":"32217",
    "sg:province":"FL",
    "wof:name":"Offbeat Records & Sea Star",
    "wof:placetype":"venue"
},
  "geometry": {"coordinates":[-81.623278,30.255453],"type":"Point"}
}