{
  "type": "Feature",
  "properties": {
    "addr:full":"11234 NW 43rd Ct Pompano Beach FL 33065",
    "addr:housenumber":"11234",
    "addr:postcode":"33065",
    "addr:street":"Nw 43Rd Ct",
    "iso:country":"US",
    "sg:address":"11234 NW 43rd Ct",
    "sg:city":"Pompano Beach",
    "sg:classifiers":[
        {
            "category":"Restaurant",
            "type":"Food & Drink"
        }
    ],
    "sg:phone":"+1 954 698 0078",
    "sg:postcode":"33065",
    "sg:province":"FL",
    "sg:tags":[
        "ice",
        "cream"
    ],
    "wof:name":"Dairy Queen",
    "wof:placetype":"venue"
},
  "geometry": {"coordinates":[-80.275437,26.28394],"type":"Point"}
}