{
  "type": "Feature",
  "properties": {
    "iso:country":"US",
    "sg:address":"4028 NW 22 Dr",
    "sg:city":"Gainesville",
    "sg:classifiers":[
        {
            "category":"Shopping",
            "type":"Retail Goods"
        }
    ],
    "sg:phone":"+1 352 692 3338",
    "sg:postcode":"32605",
    "sg:province":"FL",
    "sg:tags":[
        "cosmetic",
        "perfume"
    ],
    "wof:name":"Beauty Alliance",
    "wof:placetype":"venue"
},
  "geometry": {"coordinates":[-82.354578,29.691418],"type":"Point"}
}