{
  "type": "Feature",
  "properties": {
    "addr:full":"446 Burns Ct Sarasota FL 34236",
    "addr:housenumber":"446",
    "addr:postcode":"34236",
    "addr:street":"Burns Ct",
    "iso:country":"US",
    "sg:address":"446 Burns Ct",
    "sg:city":"Sarasota",
    "sg:classifiers":[
        {
            "category":"Professional",
            "subcategory":"Business Services",
            "type":"Services"
        }
    ],
    "sg:phone":"+1 941 954 1800",
    "sg:postcode":"34236",
    "sg:province":"FL",
    "sg:tags":[
        "interior",
        "consultant",
        "design",
        "decorator"
    ],
    "wof:name":"Goldfine Interiors Inc",
    "wof:placetype":"venue"
},
  "geometry": {"coordinates":[-82.540092,27.332841],"type":"Point"}
}