{
  "type": "Feature",
  "properties": {
    "addr:full":"2441 NW 43 St Gainesville FL 32606",
    "addr:housenumber":"2441",
    "addr:postcode":"32606",
    "addr:street":"Nw 43 St",
    "iso:country":"US",
    "sg:address":"2441 NW 43 St",
    "sg:city":"Gainesville",
    "sg:classifiers":[
        {
            "category":"Restaurant",
            "type":"Food & Drink"
        }
    ],
    "sg:phone":"+1 352 378 3756",
    "sg:postcode":"32606",
    "sg:province":"FL",
    "sg:tags":[
        "personal",
        "eating",
        "caterer"
    ],
    "wof:name":"Elegant Events/Gourmet-To-go",
    "wof:placetype":"venue"
},
  "geometry": {"coordinates":[-82.38890000000001,29.674415],"type":"Point"}
}