{
  "type": "Feature",
  "properties": {
    "iso:country":"US",
    "sg:address":"590 Hialeah Dr Ste A",
    "sg:city":"Hialeah",
    "sg:classifiers":[
        {
            "category":"Retail",
            "subcategory":"Auto Repair",
            "type":"Services"
        }
    ],
    "sg:phone":"+1 305 888 3562",
    "sg:postcode":"33010",
    "sg:province":"FL",
    "wof:name":"J & F Automotive",
    "wof:placetype":"venue"
},
  "geometry": {"coordinates":[-80.26942099999999,25.822904],"type":"Point"}
}