{
  "type": "Feature",
  "properties": {
    "addr:full":"420 S Orange Ave Orlando FL 32801",
    "addr:housenumber":"420",
    "addr:postcode":"32801",
    "addr:street":"S Orange Ave",
    "iso:country":"US",
    "sg:address":"420 S Orange Ave",
    "sg:city":"Orlando",
    "sg:phone":"+1 407 423 4000",
    "sg:postcode":"32801",
    "sg:province":"FL",
    "wof:name":"Ross, Thomas T",
    "wof:placetype":"venue"
},
  "geometry": {"coordinates":[-81.378711,28.537815],"type":"Point"}
}