{
  "type": "Feature",
  "properties": {
    "iso:country":"US",
    "sg:address":"562 E Eau Gallie Blvd",
    "sg:city":"Indian Hrbr Bch",
    "sg:classifiers":[
        {
            "category":"Shopping",
            "subcategory":"Bicycles & Sporting Goods",
            "type":"Retail Goods"
        }
    ],
    "sg:phone":"+1 321 779 0160",
    "sg:postcode":"32937",
    "sg:province":"FL",
    "sg:tags":[
        "tackle",
        "fishing"
    ],
    "wof:name":"D & R Saltwater Tackle",
    "wof:placetype":"venue"
},
  "geometry": {"coordinates":[-80.591228,28.138645],"type":"Point"}
}