{
  "type": "Feature",
  "properties": {
    "addr:full":"1908 N Barnes St Plant City FL 33563",
    "addr:housenumber":"1908",
    "addr:postcode":"33563",
    "addr:street":"N Barnes St",
    "iso:country":"US",
    "sg:address":"1908 N Barnes St",
    "sg:city":"Plant City",
    "sg:classifiers":[
        {
            "category":"Building & Trades",
            "subcategory":"Construction",
            "type":"Services"
        }
    ],
    "sg:phone":"+1 813 752 1147",
    "sg:postcode":"33563",
    "sg:province":"FL",
    "sg:tags":[
        "painter"
    ],
    "wof:name":"Moore's Painting",
    "wof:placetype":"venue"
},
  "geometry": {"coordinates":[-82.128837,28.031993],"type":"Point"}
}