{
  "type": "Feature",
  "properties": {
    "iso:country":"US",
    "sg:address":"5653 NW 122nd Ave",
    "sg:city":"Pompano Beach",
    "sg:classifiers":[
        {
            "category":"Utilities",
            "subcategory":"Mobile Phone",
            "type":"Services"
        }
    ],
    "sg:phone":"+1 954 757 2440",
    "sg:postcode":"33076",
    "sg:province":"FL",
    "sg:tags":[
        "communication",
        "radiotelephone"
    ],
    "wof:name":"Wireless Fiestacom Inc",
    "wof:placetype":"venue"
},
  "geometry": {"coordinates":[-80.288821,26.299937],"type":"Point"}
}