{
  "type": "Feature",
  "properties": {
    "iso:country":"US",
    "sg:address":"611 Baffie Ave",
    "sg:city":"Winter Park",
    "sg:classifiers":[
        {
            "category":"Real Estate",
            "subcategory":"Real Estate Agent",
            "type":"Services"
        }
    ],
    "sg:phone":"+1 407 740 4043",
    "sg:postcode":"32789",
    "sg:province":"FL",
    "wof:name":"Keller Williams Realtors",
    "wof:placetype":"venue"
},
  "geometry": {"coordinates":[-81.382687,28.592732],"type":"Point"}
}