{
  "type": "Feature",
  "properties": {
    "iso:country":"US",
    "sg:address":"2514 N Beaumont Ave",
    "sg:city":"Kissimmee",
    "sg:classifiers":[
        {
            "category":"Professional",
            "subcategory":"Computer Services",
            "type":"Services"
        }
    ],
    "sg:phone":"+1 407 460 3804",
    "sg:postcode":"34741",
    "sg:province":"FL",
    "sg:tags":[
        "datum"
    ],
    "wof:name":"Port 80 Designs",
    "wof:placetype":"venue"
},
  "geometry": {"coordinates":[-81.410028,28.32198],"type":"Point"}
}