{
  "type": "Feature",
  "properties": {
    "iso:country":"US",
    "sg:address":"6017 Pine Ridge Rd",
    "sg:city":"Naples",
    "sg:classifiers":[
        {
            "category":"Real Estate",
            "subcategory":"Real Estate Agent",
            "type":"Services"
        }
    ],
    "sg:phone":"+1 239 353 0229",
    "sg:postcode":"34119",
    "sg:province":"FL",
    "wof:name":"Real Estate Appraisels",
    "wof:placetype":"venue"
},
  "geometry": {"coordinates":[-81.71680600000001,26.211911],"type":"Point"}
}