{
  "type": "Feature",
  "properties": {
    "iso:country":"US",
    "sg:address":"6097 S US Hwy 1",
    "sg:city":"Grant",
    "sg:classifiers":[
        {
            "category":"Restaurant",
            "type":"Food & Drink"
        }
    ],
    "sg:phone":"+1 321 729 9757",
    "sg:postcode":"32949",
    "sg:province":"FL",
    "wof:name":"R J's Pub",
    "wof:placetype":"venue"
},
  "geometry": {"coordinates":[-80.519198,27.917674],"type":"Point"}
}