{
  "type": "Feature",
  "properties": {
    "iso:country":"US",
    "sg:address":"6150 N Atlantic Ave",
    "sg:city":"Cape Canaveral",
    "sg:classifiers":[
        {
            "category":"Retail",
            "subcategory":"Auto Repair",
            "type":"Services"
        }
    ],
    "sg:phone":"+1 321 799 3907",
    "sg:postcode":"32920",
    "sg:province":"FL",
    "sg:tags":[
        "automotive"
    ],
    "wof:name":"Canaveral Auto Clinic",
    "wof:placetype":"venue"
},
  "geometry": {"coordinates":[-80.60549899999999,28.3734],"type":"Point"}
}