{
  "type": "Feature",
  "properties": {
    "iso:country":"US",
    "sg:address":"13592 McGregor Blvd",
    "sg:city":"Fort Myers",
    "sg:classifiers":[
        {
            "category":"Banks & Credit Unions",
            "subcategory":"Bank",
            "type":"Services"
        }
    ],
    "sg:phone":"+1 239 267 1318",
    "sg:postcode":"33919",
    "sg:province":"FL",
    "sg:tags":[
        "loan",
        "real estate"
    ],
    "wof:name":"Nu Vision Mortgages",
    "wof:placetype":"venue"
},
  "geometry": {"coordinates":[-81.915104,26.543798],"type":"Point"}
}