{
  "type": "Feature",
  "properties": {
    "iso:country":"US",
    "sg:address":"17587 Dixie Hwy",
    "sg:city":"Miami",
    "sg:classifiers":[
        {
            "category":"Retail",
            "subcategory":"Laundry & Dry Cleaning",
            "type":"Services"
        }
    ],
    "sg:phone":"+1 305 253 5557",
    "sg:postcode":"33157",
    "sg:province":"FL",
    "sg:tags":[
        "drycleaning",
        "plant"
    ],
    "wof:name":"G & J Cleaners Inc",
    "wof:placetype":"venue"
},
  "geometry": {"coordinates":[-80.35041200000001,25.606777],"type":"Point"}
}