{
  "type": "Feature",
  "properties": {
    "iso:country":"US",
    "sg:address":"7424 W Irlo Bronson Memorial Hwy",
    "sg:city":"Kissimmee",
    "sg:classifiers":[
        {
            "category":"Autos & Motor Vehicles",
            "subcategory":"Fuel & Gas Station",
            "type":"Retail Goods"
        }
    ],
    "sg:phone":"+1 407 396 2721",
    "sg:postcode":"34747",
    "sg:province":"FL",
    "sg:tags":[
        "repair",
        "grocer",
        "station",
        "gasoline",
        "general"
    ],
    "wof:name":"Exxon",
    "wof:placetype":"venue"
},
  "geometry": {"coordinates":[-81.58458299999999,28.332431],"type":"Point"}
}