{
  "type": "Feature",
  "properties": {
    "iso:country":"US",
    "sg:address":"2130 E Edgewood Dr Ste 1",
    "sg:city":"Lakeland",
    "sg:classifiers":[
        {
            "category":"Real Estate",
            "subcategory":"Real Estate Services",
            "type":"Services"
        },
        {
            "category":"Real Estate",
            "subcategory":"Surveying",
            "type":"Services"
        }
    ],
    "sg:phone":"+1 863 665 9195",
    "sg:postcode":"33803",
    "sg:province":"FL",
    "sg:tags":[
        "industrial",
        "appraisers-commercial",
        "appraiser"
    ],
    "wof:name":"Klusza & Goding Inc",
    "wof:placetype":"venue"
},
  "geometry": {"coordinates":[-81.92271,28.012958],"type":"Point"}
}