{
  "type": "Feature",
  "properties": {
    "addr:full":"1705 Belvedere Rd West Palm Beach FL 33406",
    "addr:housenumber":"1705",
    "addr:postcode":"33406",
    "addr:street":"Belvedere Rd",
    "iso:country":"US",
    "sg:address":"1705 Belvedere Rd",
    "sg:city":"West Palm Beach",
    "sg:classifiers":[
        {
            "category":"Food & Beverages",
            "subcategory":"Groceries & Convenience Stores",
            "type":"Retail Goods"
        }
    ],
    "sg:phone":"+1 561 686 6631",
    "sg:postcode":"33406",
    "sg:province":"FL",
    "sg:tags":[
        "station",
        "gasoline"
    ],
    "wof:name":"Daisy Fresh Budget Stores Inc",
    "wof:placetype":"venue"
},
  "geometry": {"coordinates":[-80.074995,26.690875],"type":"Point"}
}