{
  "type": "Feature",
  "properties": {
    "iso:country":"US",
    "sg:address":"3611 1st St",
    "sg:city":"Bradenton",
    "sg:classifiers":[
        {
            "category":"Restaurant",
            "type":"Food & Drink"
        }
    ],
    "sg:phone":"+1 941 747 3595",
    "sg:postcode":"34208",
    "sg:province":"FL",
    "wof:name":"All Star Steakhouse & Sports",
    "wof:placetype":"venue"
},
  "geometry": {"coordinates":[-82.56285699999999,27.469701],"type":"Point"}
}