{
  "type": "Feature",
  "properties": {
    "iso:country":"US",
    "sg:address":"231 Ruby Ave",
    "sg:city":"Kissimmee",
    "sg:classifiers":[
        {
            "category":"Professional",
            "subcategory":"Management & Consulting",
            "type":"Services"
        }
    ],
    "sg:phone":"+1 407 847 2280",
    "sg:postcode":"34741",
    "sg:province":"FL",
    "sg:tags":[
        "association"
    ],
    "wof:name":"Association Solutions-Florida",
    "wof:placetype":"venue"
},
  "geometry": {"coordinates":[-81.405608,28.290096],"type":"Point"}
}