{
  "type": "Feature",
  "properties": {
    "addr:full":"15321 State Hwy 121 Gainesville FL 32653",
    "addr:housenumber":"15321",
    "addr:postcode":"32653",
    "addr:street":"State Hwy 121",
    "iso:country":"US",
    "sg:address":"15321 State Hwy 121",
    "sg:city":"Gainesville",
    "sg:classifiers":[
        {
            "category":"Farming",
            "subcategory":"Nursery",
            "type":"Manufacturing & Wholesale Goods"
        }
    ],
    "sg:phone":"+1 386 418 0484",
    "sg:postcode":"32653",
    "sg:province":"FL",
    "sg:tags":[
        "product"
    ],
    "wof:name":"Gainesville Tree Farm",
    "wof:placetype":"venue"
},
  "geometry": {"coordinates":[-82.3837,29.797203],"type":"Point"}
}