{
  "type": "Feature",
  "properties": {
    "addr:full":"2028 Coral Creek Dr Pensacola FL 32506",
    "addr:housenumber":"2028",
    "addr:postcode":"32506",
    "addr:street":"Coral Creek Dr",
    "iso:country":"US",
    "sg:address":"2028 Coral Creek Dr",
    "sg:city":"Pensacola",
    "sg:classifiers":[
        {
            "category":"Manufacturing",
            "subcategory":"Furniture",
            "type":"Manufacturing & Wholesale Goods"
        }
    ],
    "sg:phone":"+1 850 456 1141",
    "sg:postcode":"32506",
    "sg:province":"FL",
    "sg:tags":[
        "household",
        "mfg"
    ],
    "wof:name":"Sunrise Interiors Inc",
    "wof:placetype":"venue"
},
  "geometry": {"coordinates":[-87.34961300000001,30.365834],"type":"Point"}
}