{
  "type": "Feature",
  "properties": {
    "iso:country":"US",
    "sg:address":"1270 N Wickham Rd",
    "sg:city":"Melbourne",
    "sg:classifiers":[
        {
            "category":"Building & Trades",
            "subcategory":"Landscaping Services",
            "type":"Services"
        }
    ],
    "sg:phone":"+1 321 302 0565",
    "sg:postcode":"32935",
    "sg:province":"FL",
    "wof:name":"A L S Lawnscaping",
    "wof:placetype":"venue"
},
  "geometry": {"coordinates":[-80.67167600000001,28.128405],"type":"Point"}
}