{
  "type": "Feature",
  "properties": {
    "iso:country":"US",
    "sg:address":"6808 59th St",
    "sg:city":"Pinellas Park",
    "sg:classifiers":[
        {
            "category":"Manufacturing",
            "subcategory":"Building Materials",
            "type":"Manufacturing & Wholesale Goods"
        }
    ],
    "sg:phone":"+1 727 545 2112",
    "sg:postcode":"33781",
    "sg:province":"FL",
    "sg:tags":[
        "mfg",
        "wood",
        "kitchen",
        "cabinet"
    ],
    "wof:name":"Knots Cabinetry",
    "wof:placetype":"venue"
},
  "geometry": {"coordinates":[-82.714039,27.834475],"type":"Point"}
}