{
  "type": "Feature",
  "properties": {
    "iso:country":"US",
    "sg:address":"19810 SW 117th Ave",
    "sg:city":"Miami",
    "sg:classifiers":[
        {
            "category":"Real Estate",
            "subcategory":"Real Estate Services",
            "type":"Services"
        }
    ],
    "sg:phone":"+1 305 969 6299",
    "sg:postcode":"33177",
    "sg:province":"FL",
    "sg:tags":[
        "inspection"
    ],
    "wof:name":"Mecca Home Inspection Inc",
    "wof:placetype":"venue"
},
  "geometry": {"coordinates":[-80.38050800000001,25.582739],"type":"Point"}
}