{
  "type": "Feature",
  "properties": {
    "iso:country":"US",
    "sg:address":"1301 Persimmon Ct",
    "sg:city":"Sebring",
    "sg:classifiers":[
        {
            "category":"Real Estate",
            "subcategory":"Real Estate Operator",
            "type":"Services"
        }
    ],
    "sg:phone":"+1 863 385 7740",
    "sg:postcode":"33870",
    "sg:province":"FL",
    "sg:tags":[
        "apartment"
    ],
    "wof:name":"Villa's Of Sebring",
    "wof:placetype":"venue"
},
  "geometry": {"coordinates":[-81.43438399999999,27.481363],"type":"Point"}
}