{
  "type": "Feature",
  "properties": {
    "iso:country":"US",
    "sg:address":"2117 N State Road 7",
    "sg:city":"Hollywood",
    "sg:classifiers":[
        {
            "category":"Professional",
            "subcategory":"Lawyer & Legal Services",
            "type":"Services"
        }
    ],
    "sg:phone":"+1 954 964 6888",
    "sg:postcode":"33021",
    "sg:province":"FL",
    "sg:tags":[
        "consultant",
        "attorney",
        "law",
        "immigration",
        "naturalization"
    ],
    "wof:name":"Aains Immigration Svc",
    "wof:placetype":"venue"
},
  "geometry": {"coordinates":[-80.208305,26.028705],"type":"Point"}
}