{
  "type": "Feature",
  "properties": {
    "iso:country":"US",
    "sg:address":"2646 Bayshore Blvd",
    "sg:city":"Dunedin",
    "sg:classifiers":[
        {
            "category":"Health Services",
            "subcategory":"Chiropractor",
            "type":"Services"
        }
    ],
    "sg:phone":"+1 727 733 3371",
    "sg:postcode":"34698",
    "sg:province":"FL",
    "wof:name":"Total Health & Wellness III",
    "wof:placetype":"venue"
},
  "geometry": {"coordinates":[-82.77906,28.052647],"type":"Point"}
}