{
  "type": "Feature",
  "properties": {
    "iso:country":"US",
    "sg:address":"12609 Lysterfield Ct",
    "sg:city":"Orlando",
    "sg:classifiers":[
        {
            "category":"Autos & Motor Vehicles",
            "subcategory":"Auto Supplies",
            "type":"Retail Goods"
        },
        {
            "category":"Manufacturing",
            "subcategory":"Apparel",
            "type":"Manufacturing & Wholesale Goods"
        },
        {
            "category":"Manufacturing",
            "subcategory":"Glass & Minerals",
            "type":"Manufacturing & Wholesale Goods"
        },
        {
            "category":"Manufacturing",
            "subcategory":"Building Materials",
            "type":"Manufacturing & Wholesale Goods"
        },
        {
            "category":"Building & Trades",
            "subcategory":"Construction",
            "type":"Services"
        }
    ],
    "sg:phone":"+1 321 948 5656",
    "sg:postcode":"32837",
    "sg:province":"FL",
    "sg:tags":[
        "plate",
        "installation",
        "repair",
        "windows-repair",
        "doors-glass",
        "coating",
        "glass-auto",
        "tinting",
        "accessory",
        "window",
        "doors",
        "frames",
        "glass-broken",
        "replacement"
    ],
    "sg:website":"http://www.appleglassworks.com/",
    "wof:name":"Apple Glass Works",
    "wof:placetype":"venue"
},
  "geometry": {"coordinates":[-81.422096,28.382682],"type":"Point"}
}