{
  "type": "Feature",
  "properties": {
    "addr:full":"1749 NE Miami Ct Stdio 408 Studio Miami FL 33132",
    "addr:housenumber":"1749;408",
    "addr:postcode":"33132",
    "addr:street":"Ne Miami Ct Stdio",
    "iso:country":"US",
    "sg:address":"1749 NE Miami Ct Stdio 408 Studio",
    "sg:city":"Miami",
    "sg:classifiers":[
        {
            "category":"Manufacturing",
            "subcategory":"Printing",
            "type":"Manufacturing & Wholesale Goods"
        }
    ],
    "sg:phone":"+1 786 863 8133",
    "sg:postcode":"33132",
    "sg:province":"FL",
    "sg:tags":[
        "magazines-distributors"
    ],
    "wof:name":"Level Magazine",
    "wof:placetype":"venue"
},
  "geometry": {"coordinates":[-80.193939,25.792067],"type":"Point"}
}