{
  "type": "Feature",
  "properties": {
    "iso:country":"US",
    "sg:address":"5425 NW 82nd Ave",
    "sg:city":"Miami",
    "sg:classifiers":[
        {
            "category":"Wholesale",
            "subcategory":"Non-durable Goods",
            "type":"Manufacturing & Wholesale Goods"
        }
    ],
    "sg:phone":"+1 305 639 2912",
    "sg:postcode":"33166",
    "sg:province":"FL",
    "wof:name":"Decor Trading Inc",
    "wof:placetype":"venue"
},
  "geometry": {"coordinates":[-80.329646,25.824178],"type":"Point"}
}