{
  "type": "Feature",
  "properties": {
    "addr:full":"3222 9th St N St Petersburg FL 33704",
    "addr:housenumber":"3222",
    "addr:postcode":"33704",
    "addr:street":"9Th St N",
    "iso:country":"US",
    "sg:address":"3222 9th St N",
    "sg:city":"St Petersburg",
    "sg:classifiers":[
        {
            "category":"Shopping",
            "subcategory":"Used Merchandise",
            "type":"Retail Goods"
        }
    ],
    "sg:phone":"+1 727 894 2048",
    "sg:postcode":"33704",
    "sg:province":"FL",
    "sg:tags":[
        "shop",
        "consignment"
    ],
    "wof:name":"Auction Connection",
    "wof:placetype":"venue"
},
  "geometry": {"coordinates":[-82.646829,27.80134],"type":"Point"}
}