{
  "type": "Feature",
  "properties": {
    "addr:full":"706 NW 177th Ave Hollywood FL 33029",
    "addr:housenumber":"706",
    "addr:postcode":"33029",
    "addr:street":"Nw 177Th Ave",
    "iso:country":"US",
    "sg:address":"706 NW 177th Ave",
    "sg:city":"Hollywood",
    "sg:classifiers":[
        {
            "category":"Banks & Credit Unions",
            "subcategory":"Bank",
            "type":"Services"
        }
    ],
    "sg:phone":"+1 954 437 7499",
    "sg:postcode":"33029",
    "sg:province":"FL",
    "sg:tags":[
        "loan",
        "broker"
    ],
    "wof:name":"Premier Investment Properties",
    "wof:placetype":"venue"
},
  "geometry": {"coordinates":[-80.38279199999999,26.011706],"type":"Point"}
}