{
  "type": "Feature",
  "properties": {
    "addr:full":"6536 Bowline Dr Sarasota FL 34231",
    "addr:housenumber":"6536",
    "addr:postcode":"34231",
    "addr:street":"Bowline Dr",
    "iso:country":"US",
    "sg:address":"6536 Bowline Dr",
    "sg:city":"Sarasota",
    "sg:classifiers":[
        {
            "category":"Real Estate",
            "subcategory":"Surveying",
            "type":"Services"
        }
    ],
    "sg:phone":"+1 941 487 7086",
    "sg:postcode":"34231",
    "sg:province":"FL",
    "sg:tags":[
        "engineer"
    ],
    "wof:name":"Slate Associates",
    "wof:placetype":"venue"
},
  "geometry": {"coordinates":[-82.50188199999999,27.261461],"type":"Point"}
}