{
  "type": "Feature",
  "properties": {
    "iso:country":"US",
    "sg:address":"2937 Bee Ridge Rd",
    "sg:city":"Sarasota",
    "sg:classifiers":[
        {
            "category":"Building & Trades",
            "subcategory":"Construction",
            "type":"Services"
        }
    ],
    "sg:phone":"+1 941 924 4988",
    "sg:postcode":"34239",
    "sg:province":"FL",
    "sg:tags":[
        "contractor"
    ],
    "wof:name":"Howard J Brown Tile & Trowel",
    "wof:placetype":"venue"
},
  "geometry": {"coordinates":[-82.51085999999999,27.298897],"type":"Point"}
}