{
  "type": "Feature",
  "properties": {
    "addr:full":"418 30th St West Palm Beach FL 33407",
    "addr:housenumber":"418",
    "addr:postcode":"33407",
    "addr:street":"30Th St",
    "iso:country":"US",
    "sg:address":"418 30th St",
    "sg:city":"West Palm Beach",
    "sg:classifiers":[
        {
            "category":"Professional",
            "subcategory":"Business Services",
            "type":"Services"
        }
    ],
    "sg:phone":"+1 561 543 7152",
    "sg:postcode":"33407",
    "sg:province":"FL",
    "sg:tags":[
        "interior",
        "consultant",
        "design",
        "decorator"
    ],
    "wof:name":"Rakas Design Inc",
    "wof:placetype":"venue"
},
  "geometry": {"coordinates":[-80.054367,26.740707],"type":"Point"}
}