{
  "type": "Feature",
  "properties": {
    "addr:full":"5493 Atlantic View Ave St Augustine FL 32080",
    "addr:housenumber":"5493",
    "addr:postcode":"32080",
    "addr:street":"Atlantic View Ave St",
    "iso:country":"US",
    "sg:address":"5493 Atlantic View Ave",
    "sg:city":"St Augustine",
    "sg:classifiers":[
        {
            "category":"Building & Trades",
            "subcategory":"Construction",
            "type":"Services"
        }
    ],
    "sg:phone":"+1 904 471 5890",
    "sg:postcode":"32080",
    "sg:province":"FL",
    "sg:tags":[
        "house",
        "nonresidential",
        "general",
        "contractor"
    ],
    "wof:name":"Tully Builders Inc",
    "wof:placetype":"venue"
},
  "geometry": {"coordinates":[-81.260141,29.792736],"type":"Point"}
}