{
  "type": "Feature",
  "properties": {
    "addr:full":"5745 S Pine Ave Ocala FL 34480",
    "addr:housenumber":"5745",
    "addr:postcode":"34480",
    "addr:street":"S Pine Ave",
    "iso:country":"US",
    "sg:address":"5745 S Pine Ave",
    "sg:city":"Ocala",
    "sg:classifiers":[
        {
            "category":"Autos & Motor Vehicles",
            "subcategory":"Automobile Sales",
            "type":"Retail Goods"
        }
    ],
    "sg:phone":"+1 352 620 0909",
    "sg:postcode":"34480",
    "sg:province":"FL",
    "sg:tags":[
        "car",
        "dealer"
    ],
    "wof:name":"Ocala Car Sales Inc",
    "wof:placetype":"venue"
},
  "geometry": {"coordinates":[-82.10458300000001,29.129946],"type":"Point"}
}