{
  "type": "Feature",
  "properties": {
    "iso:country":"US",
    "sg:address":"950 Gulf Shore Dr",
    "sg:city":"Destin",
    "sg:classifiers":[
        {
            "category":"Food & Beverages",
            "subcategory":"Groceries & Convenience Stores",
            "type":"Retail Goods"
        }
    ],
    "sg:phone":"+1 850 837 6328",
    "sg:postcode":"32541",
    "sg:province":"FL",
    "wof:name":"Callahans Island Rest & Deli",
    "wof:placetype":"venue"
},
  "geometry": {"coordinates":[-86.481098,30.386513],"type":"Point"}
}