{
  "type": "Feature",
  "properties": {
    "iso:country":"US",
    "sg:address":"12515 Orange Dr",
    "sg:city":"Davie",
    "sg:classifiers":[
        {
            "category":"Social Services",
            "type":"Services"
        }
    ],
    "sg:phone":"+1 954 475 4575",
    "sg:postcode":"33328",
    "sg:province":"FL",
    "sg:tags":[
        "counseling"
    ],
    "wof:name":"About You Counseling & Rffrl",
    "wof:placetype":"venue"
},
  "geometry": {"coordinates":[-80.31454100000001,26.064345],"type":"Point"}
}