{
  "type": "Feature",
  "properties": {
    "iso:country":"US",
    "sg:address":"4200 SW 102nd Ave",
    "sg:city":"Davie",
    "sg:classifiers":[
        {
            "category":"Building & Trades",
            "subcategory":"Equipment Rental",
            "type":"Services"
        }
    ],
    "sg:phone":"+1 954 452 1899",
    "sg:postcode":"33328",
    "sg:province":"FL",
    "sg:tags":[
        "yard",
        "leasing",
        "store"
    ],
    "wof:name":"Sakura Rentals",
    "wof:placetype":"venue"
},
  "geometry": {"coordinates":[-80.283537,26.068187],"type":"Point"}
}