{
  "type": "Feature",
  "properties": {
    "iso:country":"US",
    "sg:address":"2330 W Brandon Blvd",
    "sg:city":"Brandon",
    "sg:classifiers":[
        {
            "category":"Personal",
            "subcategory":"Beauty Salon",
            "type":"Services"
        }
    ],
    "sg:phone":"+1 813 315 0120",
    "sg:postcode":"33511",
    "sg:province":"FL",
    "wof:name":"Haircolor Xpress",
    "wof:placetype":"venue"
},
  "geometry": {"coordinates":[-82.321037,27.938303],"type":"Point"}
}