{
  "type": "Feature",
  "properties": {
    "addr:full":"8220 Hanley Rd Tampa FL 33634",
    "addr:postcode":"8220;33634",
    "addr:street":"Hanley Rd",
    "iso:country":"US",
    "sg:address":"8220 Hanley Rd",
    "sg:city":"Tampa",
    "sg:classifiers":[
        {
            "category":"Real Estate",
            "subcategory":"Real Estate Services",
            "type":"Services"
        },
        {
            "category":"Insurance",
            "subcategory":"Insurance Agent",
            "type":"Services"
        }
    ],
    "sg:phone":"+1 813 885 4195",
    "sg:postcode":"33634",
    "sg:province":"FL",
    "sg:tags":[
        "company",
        "title"
    ],
    "wof:name":"Pan American Title Company",
    "wof:placetype":"venue"
},
  "geometry": {"coordinates":[-82.562454,28.024261],"type":"Point"}
}