{
  "type": "Feature",
  "properties": {
    "addr:full":"871 Island Club Sq Vero Beach FL 32963",
    "addr:housenumber":"871",
    "addr:postcode":"32963",
    "addr:street":"Island Club Sq",
    "iso:country":"US",
    "sg:address":"871 Island Club Sq",
    "sg:city":"Vero Beach",
    "sg:classifiers":[
        {
            "category":"Building & Trades",
            "subcategory":"Construction",
            "type":"Services"
        }
    ],
    "sg:phone":"+1 772 234 0174",
    "sg:postcode":"32963",
    "sg:province":"FL",
    "sg:tags":[
        "builder",
        "operative"
    ],
    "wof:name":"Beazer",
    "wof:placetype":"venue"
},
  "geometry": {"coordinates":[-80.394271,27.745286],"type":"Point"}
}