{
  "type": "Feature",
  "properties": {
    "addr:full":"4387 36th St Orlando FL 32811",
    "addr:housenumber":"4387",
    "addr:postcode":"32811",
    "addr:street":"36Th St",
    "iso:country":"US",
    "sg:address":"4387 36th St",
    "sg:city":"Orlando",
    "sg:classifiers":[
        {
            "category":"Building & Trades",
            "subcategory":"Equipment Rental",
            "type":"Services"
        }
    ],
    "sg:phone":"+1 407 975 0484",
    "sg:postcode":"32811",
    "sg:province":"FL",
    "wof:name":"Lum - N-8lighting and Grip",
    "wof:placetype":"venue"
},
  "geometry": {"coordinates":[-81.439961,28.502597],"type":"Point"}
}