{
  "type": "Feature",
  "properties": {
    "iso:country":"US",
    "sg:address":"1410 Astor Commons Pl",
    "sg:city":"Brandon",
    "sg:classifiers":[
        {
            "category":"Bars & Pubs",
            "type":"Food & Drink"
        }
    ],
    "sg:phone":"+1 813 661 4283",
    "sg:postcode":"33511",
    "sg:province":"FL",
    "sg:tags":[
        "drinking"
    ],
    "wof:name":"Brandon Breath",
    "wof:placetype":"venue"
},
  "geometry": {"coordinates":[-82.324755,27.913606],"type":"Point"}
}