{
  "type": "Feature",
  "properties": {
    "iso:country":"US",
    "sg:address":"17000 Terraverde Cir",
    "sg:city":"Fort Myers",
    "sg:classifiers":[
        {
            "category":"Sports & Exercise",
            "subcategory":"Golf",
            "type":"Entertainment"
        }
    ],
    "sg:phone":"+1 239 437 2427",
    "sg:postcode":"33908",
    "sg:province":"FL",
    "wof:name":"Terraverde Master Association",
    "wof:placetype":"venue"
},
  "geometry": {"coordinates":[-81.858299,26.491199],"type":"Point"}
}