{
  "type": "Feature",
  "properties": {
    "iso:country":"US",
    "sg:address":"3464 Trade St",
    "sg:city":"Deltona",
    "sg:classifiers":[
        {
            "category":"Shopping",
            "subcategory":"Beauty & Cosmetics",
            "type":"Retail Goods"
        }
    ],
    "sg:phone":"+1 407 320 8073",
    "sg:postcode":"32738",
    "sg:province":"FL",
    "sg:tags":[
        "consulting",
        "management",
        "merchandise"
    ],
    "wof:name":"Anne Denoyer",
    "wof:placetype":"venue"
},
  "geometry": {"coordinates":[-81.167377,28.88293],"type":"Point"}
}