{
  "type": "Feature",
  "properties": {
    "addr:full":"6234 Candler Ter Sebring FL 33876",
    "addr:postcode":"6234;33876",
    "addr:street":"Candler Ter",
    "iso:country":"US",
    "sg:address":"6234 Candler Ter",
    "sg:city":"Sebring",
    "sg:classifiers":[
        {
            "category":"Arts & Performance",
            "subcategory":"Theater",
            "type":"Entertainment"
        }
    ],
    "sg:phone":"+1 863 655 3450",
    "sg:postcode":"33876",
    "sg:province":"FL",
    "sg:tags":[
        "entertainer"
    ],
    "wof:name":"Heartland Karaoke & DJ",
    "wof:placetype":"venue"
},
  "geometry": {"coordinates":[-81.31263800000001,27.434305],"type":"Point"}
}