{
  "type": "Feature",
  "properties": {
    "iso:country":"US",
    "sg:address":"3724 Gatlin Woods Dr",
    "sg:city":"Orlando",
    "sg:classifiers":[
        {
            "category":"Professional",
            "subcategory":"Business Services",
            "type":"Services"
        }
    ],
    "sg:phone":"+1 407 823 9624",
    "sg:postcode":"32812",
    "sg:province":"FL",
    "sg:tags":[
        "auctioneer"
    ],
    "wof:name":"Richard Chuilli",
    "wof:placetype":"venue"
},
  "geometry": {"coordinates":[-81.32541000000001,28.497038],"type":"Point"}
}