{
  "type": "Feature",
  "properties": {
    "addr:full":"6057 Palm Ct West Palm Beach FL 33415",
    "addr:housenumber":"6057",
    "addr:postcode":"33415",
    "addr:street":"Palm Ct",
    "iso:country":"US",
    "sg:address":"6057 Palm Ct",
    "sg:city":"West Palm Beach",
    "sg:classifiers":[
        {
            "category":"Professional",
            "subcategory":"Accounting & Tax Preparation",
            "type":"Services"
        }
    ],
    "sg:phone":"+1 561 687 2322",
    "sg:postcode":"33415",
    "sg:province":"FL",
    "wof:name":"Dazzle ME Twice Dance",
    "wof:placetype":"venue"
},
  "geometry": {"coordinates":[-80.13624799999999,26.672624],"type":"Point"}
}