{
  "type": "Feature",
  "properties": {
    "iso:country":"US",
    "sg:address":"1107 SW Spruce St",
    "sg:city":"Palm City",
    "sg:classifiers":[
        {
            "category":"Building & Trades",
            "subcategory":"Construction",
            "type":"Services"
        }
    ],
    "sg:phone":"+1 772 286 4871",
    "sg:postcode":"34990",
    "sg:province":"FL",
    "sg:tags":[
        "contractor"
    ],
    "wof:name":"Artistique Plastering Inc",
    "wof:placetype":"venue"
},
  "geometry": {"coordinates":[-80.26786300000001,27.173394],"type":"Point"}
}