{
  "type": "Feature",
  "properties": {
    "iso:country":"US",
    "sg:address":"7111 Harney Rd",
    "sg:city":"Tampa",
    "sg:classifiers":[
        {
            "category":"Home & Garden",
            "subcategory":"Garden Supply",
            "type":"Retail Goods"
        }
    ],
    "sg:phone":"+1 813 980 3809",
    "sg:postcode":"33617",
    "sg:province":"FL",
    "sg:tags":[
        "farm",
        "equine"
    ],
    "wof:name":"Lucky S Farm",
    "wof:placetype":"venue"
},
  "geometry": {"coordinates":[-82.375764,28.011427],"type":"Point"}
}