{
  "type": "Feature",
  "properties": {
    "addr:full":"224 E River Park Dr Jupiter FL 33477",
    "addr:housenumber":"224",
    "addr:postcode":"33477",
    "addr:street":"E River Park Dr",
    "iso:country":"US",
    "sg:address":"224 E River Park Dr",
    "sg:city":"Jupiter",
    "sg:classifiers":[
        {
            "category":"Manufacturing",
            "subcategory":"Retail Goods",
            "type":"Manufacturing & Wholesale Goods"
        }
    ],
    "sg:phone":"+1 561 744 0024",
    "sg:postcode":"33477",
    "sg:province":"FL",
    "sg:tags":[
        "identification"
    ],
    "wof:name":"Id Alert NETWORK",
    "wof:placetype":"venue"
},
  "geometry": {"coordinates":[-80.070763,26.901859],"type":"Point"}
}