{
  "type": "Feature",
  "properties": {
    "addr:full":"38006 Palm Grove Dr Zephyrhills FL 33542",
    "addr:housenumber":"38006",
    "addr:postcode":"33542",
    "addr:street":"Palm Grove Dr",
    "iso:country":"US",
    "sg:address":"38006 Palm Grove Dr",
    "sg:city":"Zephyrhills",
    "sg:classifiers":[
        {
            "category":"Building & Trades",
            "subcategory":"Construction",
            "type":"Services"
        }
    ],
    "sg:phone":"+1 813 783 1963",
    "sg:postcode":"33542",
    "sg:province":"FL",
    "sg:tags":[
        "drywall",
        "contractor"
    ],
    "wof:name":"Charles Pierce Textures Inc",
    "wof:placetype":"venue"
},
  "geometry": {"coordinates":[-82.186414,28.217678],"type":"Point"}
}