{
  "type": "Feature",
  "properties": {
    "iso:country":"US",
    "sg:address":"7045 Harbor Point Blvd",
    "sg:city":"Orlando",
    "sg:classifiers":[
        {
            "category":"Personal",
            "type":"Services"
        }
    ],
    "sg:phone":"+1 407 376 5290",
    "sg:postcode":"32835",
    "sg:province":"FL",
    "sg:tags":[
        "therapist",
        "massage"
    ],
    "wof:name":"Milton Chin Massage Therapy",
    "wof:placetype":"venue"
},
  "geometry": {"coordinates":[-81.477395,28.536051],"type":"Point"}
}