{
  "type": "Feature",
  "properties": {
    "iso:country":"US",
    "sg:address":"Highway 77 S",
    "sg:city":"Chipley",
    "sg:classifiers":[
        {
            "category":"Building & Trades",
            "subcategory":"Plumbing",
            "type":"Services"
        },
        {
            "category":"Wholesale",
            "subcategory":"Construction Materials",
            "type":"Manufacturing & Wholesale Goods"
        }
    ],
    "sg:phone":"+1 850 638 1921",
    "sg:postcode":"32428",
    "sg:province":"FL",
    "sg:tags":[
        "plumber",
        "part",
        "fixtures",
        "supply"
    ],
    "wof:name":"High Plumbing Inc Of Washington County",
    "wof:placetype":"venue"
},
  "geometry": {"coordinates":[-85.55534299999999,30.733722],"type":"Point"}
}