{
  "type": "Feature",
  "properties": {
    "iso:country":"US",
    "sg:address":"9811 Marlinton Ln",
    "sg:city":"Port Richey",
    "sg:classifiers":[
        {
            "category":"Health Services",
            "subcategory":"Clinic",
            "type":"Services"
        }
    ],
    "sg:phone":"+1 727 942 9935",
    "sg:postcode":"34668",
    "sg:province":"FL",
    "sg:tags":[
        "home"
    ],
    "wof:name":"Bay Area Care",
    "wof:placetype":"venue"
},
  "geometry": {"coordinates":[-82.681701,28.299618],"type":"Point"}
}