{
  "type": "Feature",
  "properties": {
    "iso:country":"US",
    "sg:address":"10900 NW 21st St Ste 240",
    "sg:city":"Miami",
    "sg:classifiers":[
        {
            "category":"Wholesale",
            "subcategory":"Computers",
            "type":"Manufacturing & Wholesale Goods"
        },
        {
            "category":"Professional",
            "subcategory":"Computer Services",
            "type":"Services"
        }
    ],
    "sg:phone":"+1 954 614 4932",
    "sg:postcode":"33172",
    "sg:province":"FL",
    "sg:tags":[
        "designer",
        "consultant",
        "system",
        "equipment",
        "software"
    ],
    "wof:name":"T D L A",
    "wof:placetype":"venue"
},
  "geometry": {"coordinates":[-80.371977,25.79343],"type":"Point"}
}