{
  "type": "Feature",
  "properties": {
    "iso:country":"US",
    "sg:address":"2680 Settlers Colony Blvd",
    "sg:city":"Gulf Breeze",
    "sg:classifiers":[
        {
            "category":"Building & Trades",
            "subcategory":"Construction",
            "type":"Services"
        }
    ],
    "sg:phone":"+1 850 857 4439",
    "sg:postcode":"32563",
    "sg:province":"FL",
    "sg:tags":[
        "house"
    ],
    "wof:name":"Analytic Construction",
    "wof:placetype":"venue"
},
  "geometry": {"coordinates":[-87.11208999999999,30.376649],"type":"Point"}
}