{
  "type": "Feature",
  "properties": {
    "addr:full":"600 Regal Cruise Way Palmetto FL 34221",
    "addr:housenumber":"600",
    "addr:postcode":"34221",
    "addr:street":"Regal Cruise Way",
    "iso:country":"US",
    "sg:address":"600 Regal Cruise Way",
    "sg:city":"Palmetto",
    "sg:classifiers":[
        {
            "category":"Wholesale",
            "subcategory":"Durable Goods & Equipment",
            "type":"Manufacturing & Wholesale Goods"
        }
    ],
    "sg:phone":"+1 941 721 3037",
    "sg:postcode":"34221",
    "sg:province":"FL",
    "wof:name":"Meridian Exotic Wood Products",
    "wof:placetype":"venue"
},
  "geometry": {"coordinates":[-82.558739,27.632136],"type":"Point"}
}