{
  "type": "Feature",
  "properties": {
    "iso:country":"US",
    "sg:address":"15850 SW 184th St",
    "sg:city":"Miami",
    "sg:classifiers":[
        {
            "category":"Wholesale",
            "subcategory":"Plants",
            "type":"Manufacturing & Wholesale Goods"
        }
    ],
    "sg:phone":"+1 305 232 4720",
    "sg:postcode":"33187",
    "sg:province":"FL",
    "sg:tags":[
        "nursery",
        "tree"
    ],
    "wof:name":"Geisa's Tropical Gardens",
    "wof:placetype":"venue"
},
  "geometry": {"coordinates":[-80.44601900000001,25.595371],"type":"Point"}
}