{
  "type": "Feature",
  "properties": {
    "iso:country":"US",
    "sg:address":"11500 Summit West Blvd",
    "sg:city":"Tampa",
    "sg:classifiers":[
        {
            "category":"Real Estate",
            "subcategory":"Real Estate Operator",
            "type":"Services"
        }
    ],
    "sg:phone":"+1 813 988 9253",
    "sg:postcode":"33617",
    "sg:province":"FL",
    "sg:tags":[
        "apartment"
    ],
    "wof:name":"Summit West Apartments",
    "wof:placetype":"venue"
},
  "geometry": {"coordinates":[-82.38635499999999,28.054415],"type":"Point"}
}