{
  "type": "Feature",
  "properties": {
    "iso:country":"US",
    "sg:address":"400 US Hwy 29",
    "sg:city":"Cantonment",
    "sg:classifiers":[
        {
            "category":"Food & Beverages",
            "subcategory":"Groceries & Convenience Stores",
            "type":"Retail Goods"
        }
    ],
    "sg:phone":"+1 850 968 6220",
    "sg:postcode":"32533",
    "sg:province":"FL",
    "wof:name":"CMP Food Mart",
    "wof:placetype":"venue"
},
  "geometry": {"coordinates":[-87.323277,30.615814],"type":"Point"}
}