{
  "type": "Feature",
  "properties": {
    "iso:country":"US",
    "sg:address":"3100 W Commercial Blvd",
    "sg:city":"Fort Lauderdale",
    "sg:classifiers":[
        {
            "category":"Shopping",
            "subcategory":"Clothing, Apparel, & Fashions",
            "type":"Retail Goods"
        }
    ],
    "sg:phone":"+1 954 730 8002",
    "sg:postcode":"33309",
    "sg:province":"FL",
    "sg:tags":[
        "furnishing"
    ],
    "wof:name":"Stepping Out",
    "wof:placetype":"venue"
},
  "geometry": {"coordinates":[-80.18929799999999,26.186266],"type":"Point"}
}