{
  "type": "Feature",
  "properties": {
    "addr:full":"331 Dover Pl Naples FL 34104",
    "addr:housenumber":"331",
    "addr:postcode":"34104",
    "addr:street":"Dover Pl",
    "iso:country":"US",
    "sg:address":"331 Dover Pl",
    "sg:city":"Naples",
    "sg:classifiers":[
        {
            "category":"Real Estate",
            "subcategory":"Real Estate Operator",
            "type":"Services"
        }
    ],
    "sg:phone":"+1 239 649 3268",
    "sg:postcode":"34104",
    "sg:province":"FL",
    "sg:tags":[
        "condominium"
    ],
    "wof:name":"Dover Place Condiminium",
    "wof:placetype":"venue"
},
  "geometry": {"coordinates":[-81.746751,26.154771],"type":"Point"}
}