{
  "type": "Feature",
  "properties": {
    "addr:full":"14550 Crazy Horse Ln Palm Beach Gardens FL 33418",
    "addr:housenumber":"14550",
    "addr:postcode":"33418",
    "addr:street":"Crazy Horse Ln",
    "iso:country":"US",
    "sg:address":"14550 Crazy Horse Ln",
    "sg:city":"Palm Beach Gardens",
    "sg:classifiers":[
        {
            "category":"Retail",
            "subcategory":"Animal Services",
            "type":"Services"
        }
    ],
    "sg:phone":"+1 561 626 4218",
    "sg:postcode":"33418",
    "sg:province":"FL",
    "wof:name":"Gatos Run Inc",
    "wof:placetype":"venue"
},
  "geometry": {"coordinates":[-80.271559,26.895152],"type":"Point"}
}