{
  "type": "Feature",
  "properties": {
    "iso:country":"US",
    "sg:address":"5735 S Florida Ave",
    "sg:city":"Lakeland",
    "sg:classifiers":[
        {
            "category":"Shopping",
            "type":"Retail Goods"
        }
    ],
    "sg:phone":"+1 863 607 4808",
    "sg:postcode":"33813",
    "sg:province":"FL",
    "sg:tags":[
        "art",
        "gallery",
        "dealer"
    ],
    "wof:name":"Art Werks",
    "wof:placetype":"venue"
},
  "geometry": {"coordinates":[-81.968414,27.95545],"type":"Point"}
}