{
  "type": "Feature",
  "properties": {
    "addr:full":"559 S Chickasaw Trl Orlando FL 32825",
    "addr:housenumber":"559",
    "addr:postcode":"32825",
    "addr:street":"S Chickasaw Trl",
    "iso:country":"US",
    "sg:address":"559 S Chickasaw Trl",
    "sg:city":"Orlando",
    "sg:classifiers":[
        {
            "category":"Personal",
            "subcategory":"Beauty Salon",
            "type":"Services"
        }
    ],
    "sg:phone":"+1 407 658 0661",
    "sg:postcode":"32825",
    "sg:province":"FL",
    "sg:tags":[
        "shop"
    ],
    "wof:name":"Great Clips",
    "wof:placetype":"venue"
},
  "geometry": {"coordinates":[-81.27580399999999,28.538696],"type":"Point"}
}