{
  "type": "Feature",
  "properties": {
    "addr:full":"706 Fortuna Dr Brandon FL 33511",
    "addr:housenumber":"706",
    "addr:postcode":"33511",
    "addr:street":"Fortuna Dr",
    "iso:country":"US",
    "sg:address":"706 Fortuna Dr",
    "sg:city":"Brandon",
    "sg:classifiers":[
        {
            "category":"Shopping",
            "type":"Retail Goods"
        }
    ],
    "sg:phone":"+1 813 684 0833",
    "sg:postcode":"33511",
    "sg:province":"FL",
    "sg:tags":[
        "merchandise"
    ],
    "wof:name":"Amway Home Products",
    "wof:placetype":"venue"
},
  "geometry": {"coordinates":[-82.272599,27.879936],"type":"Point"}
}