{
  "type": "Feature",
  "properties": {
    "iso:country":"US",
    "sg:address":"8135 Royal Hart Dr",
    "sg:city":"New Port Richey",
    "sg:classifiers":[
        {
            "category":"Shopping",
            "subcategory":"Clothing, Apparel, & Fashions",
            "type":"Retail Goods"
        }
    ],
    "sg:phone":"+1 727 846 9227",
    "sg:postcode":"34653",
    "sg:province":"FL",
    "sg:tags":[
        "hair",
        "supply"
    ],
    "wof:name":"Doris' Hair Design",
    "wof:placetype":"venue"
},
  "geometry": {"coordinates":[-82.677329,28.232044],"type":"Point"}
}