{
  "type": "Feature",
  "properties": {
    "addr:full":"114 Canal St New Smyrna Beach FL 32168",
    "addr:housenumber":"114",
    "addr:postcode":"32168",
    "addr:street":"Canal St",
    "iso:country":"US",
    "sg:address":"114 Canal St",
    "sg:city":"New Smyrna Beach",
    "sg:classifiers":[
        {
            "category":"Organizations",
            "subcategory":"Community Association",
            "type":"Services"
        }
    ],
    "sg:phone":"+1 386 423 2223",
    "sg:postcode":"32168",
    "sg:province":"FL",
    "sg:tags":[
        "support",
        "business"
    ],
    "wof:name":"Quantum Furniture LLC",
    "wof:placetype":"venue"
},
  "geometry": {"coordinates":[-80.920965,29.025545],"type":"Point"}
}