{
  "type": "Feature",
  "properties": {
    "addr:full":"295 Park Ave Satellite Beach FL 32937",
    "addr:housenumber":"295",
    "addr:postcode":"32937",
    "addr:street":"Park Ave",
    "iso:country":"US",
    "sg:address":"295 Park Ave",
    "sg:city":"Satellite Beach",
    "sg:classifiers":[
        {
            "category":"Building & Trades",
            "subcategory":"Landscaping Services",
            "type":"Services"
        }
    ],
    "sg:phone":"+1 321 536 2980",
    "sg:postcode":"32937",
    "sg:province":"FL",
    "sg:tags":[
        "lawn",
        "maintenance",
        "grounds"
    ],
    "wof:name":"Tracy Winton's Lawn Care",
    "wof:placetype":"venue"
},
  "geometry": {"coordinates":[-80.59652199999999,28.177884],"type":"Point"}
}