{
  "type": "Feature",
  "properties": {
    "addr:full":"8259 NW 7th St Miami FL 33126",
    "addr:housenumber":"8259",
    "addr:postcode":"33126",
    "addr:street":"Nw 7Th St",
    "iso:country":"US",
    "sg:address":"8259 NW 7th St",
    "sg:city":"Miami",
    "sg:classifiers":[
        {
            "category":"Professional",
            "subcategory":"Accounting & Tax Preparation",
            "type":"Services"
        }
    ],
    "sg:phone":"+1 305 772 7568",
    "sg:postcode":"33126",
    "sg:province":"FL",
    "sg:tags":[
        "return"
    ],
    "wof:name":"Day Care Center",
    "wof:placetype":"venue"
},
  "geometry": {"coordinates":[-80.32961400000001,25.776828],"type":"Point"}
}