{
  "type": "Feature",
  "properties": {
    "addr:full":"5371 NW 79th Ave Doral FL 33166",
    "addr:housenumber":"5371",
    "addr:postcode":"33166",
    "addr:street":"Nw 79Th Ave",
    "iso:country":"US",
    "sg:address":"5371 NW 79th Ave",
    "sg:city":"Doral",
    "sg:classifiers":[
        {
            "category":"Manufacturing",
            "subcategory":"Printing",
            "type":"Manufacturing & Wholesale Goods"
        }
    ],
    "sg:phone":"+1 305 592 4646",
    "sg:postcode":"33166",
    "sg:province":"FL",
    "sg:tags":[
        "equipment",
        "scanning",
        "printer",
        "plotting",
        "supply"
    ],
    "wof:name":"Action Printing Inc",
    "wof:placetype":"venue"
},
  "geometry": {"coordinates":[-80.32565700000001,25.822312],"type":"Point"}
}