{
  "type": "Feature",
  "properties": {
    "addr:full":"10557 SE Maricamp Rd Ocala FL 34472",
    "addr:postcode":"10557;34472",
    "addr:street":"Se Maricamp Rd",
    "iso:country":"US",
    "sg:address":"10557 SE Maricamp Rd",
    "sg:city":"Ocala",
    "sg:classifiers":[
        {
            "category":"Professional",
            "subcategory":"Detective & Security Services",
            "type":"Services"
        }
    ],
    "sg:phone":"+1 352 687 0806",
    "sg:postcode":"34472",
    "sg:province":"FL",
    "sg:tags":[
        "information",
        "bureau"
    ],
    "wof:name":"All County Plumbing Inc",
    "wof:placetype":"venue"
},
  "geometry": {"coordinates":[-81.97577,29.074168],"type":"Point"}
}