{
  "type": "Feature",
  "properties": {
    "iso:country":"US",
    "sg:address":"10506 Riverside Rd",
    "sg:city":"Port Charlotte",
    "sg:classifiers":[
        {
            "category":"Professional",
            "subcategory":"Business Services",
            "type":"Services"
        }
    ],
    "sg:phone":"+1 941 457 0488",
    "sg:postcode":"33981",
    "sg:province":"FL",
    "wof:name":"Mark A Bracefield Business Svc",
    "wof:placetype":"venue"
},
  "geometry": {"coordinates":[-82.206874,26.873887],"type":"Point"}
}