{
  "type": "Feature",
  "properties": {
    "addr:full":"3280 Coral Way Coral Gables FL 33145",
    "addr:housenumber":"3280",
    "addr:postcode":"33145",
    "addr:street":"Coral Way",
    "iso:country":"US",
    "sg:address":"3280 Coral Way",
    "sg:city":"Coral Gables",
    "sg:classifiers":[
        {
            "category":"Fast Food",
            "type":"Food & Drink"
        }
    ],
    "sg:phone":"+1 305 444 5466",
    "sg:postcode":"33145",
    "sg:province":"FL",
    "sg:website":"www.mcdonalds.com",
    "wof:name":"McDonald's",
    "wof:placetype":"venue"
},
  "geometry": {"coordinates":[-80.248245,25.749983],"type":"Point"}
}