{
  "type": "Feature",
  "properties": {
    "addr:full":"2905 NW 27th Ave Miami FL 33142",
    "addr:housenumber":"2905",
    "addr:postcode":"33142",
    "addr:street":"Nw 27Th Ave",
    "iso:country":"US",
    "sg:address":"2905 NW 27th Ave",
    "sg:city":"Miami",
    "sg:classifiers":[
        {
            "category":"Banks & Credit Unions",
            "subcategory":"Financial Services",
            "type":"Services"
        }
    ],
    "sg:phone":"+1 786 235 6605",
    "sg:postcode":"33142",
    "sg:province":"FL",
    "sg:tags":[
        "cashing",
        "check"
    ],
    "wof:name":"Check Cashing USA #8",
    "wof:placetype":"venue"
},
  "geometry": {"coordinates":[-80.23993,25.802648],"type":"Point"}
}