{
  "type": "Feature",
  "properties": {
    "iso:country":"US",
    "sg:address":"1217 NE Osceola Ave",
    "sg:city":"Ocala",
    "sg:classifiers":[
        {
            "category":"Place Of Worship",
            "type":"Public Place"
        }
    ],
    "sg:phone":"+1 352 867 5567",
    "sg:postcode":"34470",
    "sg:province":"FL",
    "sg:tags":[
        "church"
    ],
    "wof:name":"Tabernacle Economic Development Inc",
    "wof:placetype":"venue"
},
  "geometry": {"coordinates":[-82.135071,29.198806],"type":"Point"}
}