{
  "type": "Feature",
  "properties": {
    "iso:country":"US",
    "sg:address":"1638 N Plaza Dr",
    "sg:city":"Tallahassee",
    "sg:classifiers":[
        {
            "category":"Health Services",
            "subcategory":"Doctor",
            "type":"Services"
        }
    ],
    "sg:phone":"+1 850 878 5147",
    "sg:postcode":"32308",
    "sg:province":"FL",
    "sg:tags":[
        "physician",
        "surgeon"
    ],
    "wof:name":"Lionel Henry MD",
    "wof:placetype":"venue"
},
  "geometry": {"coordinates":[-84.238899,30.458907],"type":"Point"}
}