{
  "type": "Feature",
  "properties": {
    "iso:country":"US",
    "sg:address":"10682 SW 186th St",
    "sg:city":"Cutler Bay",
    "sg:classifiers":[
        {
            "category":"Building & Trades",
            "subcategory":"Construction",
            "type":"Services"
        }
    ],
    "sg:phone":"+1 305 259 5661",
    "sg:postcode":"33157",
    "sg:province":"FL",
    "sg:tags":[
        "air",
        "heating",
        "conditioning/hvac"
    ],
    "wof:name":"Air On Demand",
    "wof:placetype":"venue"
},
  "geometry": {"coordinates":[-80.36517000000001,25.595767],"type":"Point"}
}