{
  "type": "Feature",
  "properties": {
    "iso:country":"US",
    "sg:address":"6231 Lake Osprey Dr",
    "sg:city":"Sarasota",
    "sg:classifiers":[
        {
            "category":"Travel",
            "subcategory":"Hotels & Motels",
            "type":"Entertainment"
        },
        {
            "category":"Retail",
            "subcategory":"Event Space",
            "type":"Services"
        },
        {
            "category":"Travel",
            "subcategory":"Resort",
            "type":"Entertainment"
        }
    ],
    "sg:phone":"+1 800 345 8082",
    "sg:postcode":"34240",
    "sg:province":"FL",
    "sg:tags":[
        "facility",
        "banquet",
        "reception",
        "lodging",
        "corporate",
        "hall"
    ],
    "sg:website":"http://ad.doubleclick.net/clk;223371278;47096201;d?http://www.holidayinn.com/redirect?path=hd&brandCode=hi&hotelCode=srqlo&_PMID=99601036&cm_mmc=mdpr-_-yellowpages-_-hi-_-srqlo",
    "wof:name":"Holiday Inn Sarasota-Lakewood Ranch",
    "wof:placetype":"venue"
},
  "geometry": {"coordinates":[-82.445933,27.38592],"type":"Point"}
}