{
  "type": "Feature",
  "properties": {
    "iso:country":"US",
    "sg:address":"165 Pine St",
    "sg:city":"Port Saint Joe",
    "sg:classifiers":[
        {
            "category":"Banks & Credit Unions",
            "subcategory":"Financial Services",
            "type":"Services"
        }
    ],
    "sg:phone":"+1 850 229 2697",
    "sg:postcode":"32456",
    "sg:province":"FL",
    "sg:tags":[
        "investment",
        "closed"
    ],
    "wof:name":"Gibbs Investments Ltd",
    "wof:placetype":"venue"
},
  "geometry": {"coordinates":[-85.35835,29.894067],"type":"Point"}
}