{
  "type": "Feature",
  "properties": {
    "iso:country":"US",
    "sg:address":"320 W Fletcher Ave Ste 107",
    "sg:city":"Tampa",
    "sg:classifiers":[
        {
            "category":"Farming",
            "subcategory":"Fish & Marine Products",
            "type":"Manufacturing & Wholesale Goods"
        },
        {
            "category":"Banks & Credit Unions",
            "subcategory":"Financial Services",
            "type":"Services"
        }
    ],
    "sg:phone":"+1 813 932 1211",
    "sg:postcode":"33612",
    "sg:province":"FL",
    "sg:tags":[
        "planning",
        "sharing",
        "profit",
        "annuity",
        "actuary",
        "retirement",
        "plan",
        "insurance",
        "pension"
    ],
    "wof:name":"Suncoast Pension Group",
    "wof:placetype":"venue"
},
  "geometry": {"coordinates":[-82.462929,28.069309],"type":"Point"}
}