{
  "type": "Feature",
  "properties": {
    "addr:full":"864 NW 23rd St Miami FL 33127",
    "addr:housenumber":"864",
    "addr:postcode":"33127",
    "addr:street":"Nw 23Rd St",
    "iso:country":"US",
    "sg:address":"864 NW 23rd St",
    "sg:city":"Miami",
    "sg:classifiers":[
        {
            "category":"Government",
            "subcategory":"Office",
            "type":"Public Place"
        }
    ],
    "sg:phone":"+1 305 638 5739",
    "sg:postcode":"33127",
    "sg:province":"FL",
    "sg:tags":[
        "county",
        "resource"
    ],
    "wof:name":"Liheap Community Action Agency",
    "wof:placetype":"venue"
},
  "geometry": {"coordinates":[-80.210628,25.798743],"type":"Point"}
}