{
  "type": "Feature",
  "properties": {
    "iso:country":"US",
    "sg:address":"6407 13th Street Ct E",
    "sg:city":"Bradenton",
    "sg:classifiers":[
        {
            "category":"Organizations",
            "subcategory":"Non-profit Organization",
            "type":"Services"
        }
    ],
    "sg:phone":"+1 941 755 6689",
    "sg:postcode":"34203",
    "sg:province":"FL",
    "sg:tags":[
        "charity",
        "foundations-educational",
        "philanthropic",
        "research"
    ],
    "wof:name":"Christian Fellowship Radio Inc",
    "wof:placetype":"venue"
},
  "geometry": {"coordinates":[-82.54879,27.428046],"type":"Point"}
}