{
  "type": "Feature",
  "properties": {
    "iso:country":"US",
    "sg:address":"4181 114th Ter N",
    "sg:city":"Clearwater",
    "sg:classifiers":[
        {
            "category":"Manufacturing",
            "subcategory":"Printing",
            "type":"Manufacturing & Wholesale Goods"
        }
    ],
    "sg:phone":"+1 727 573 3339",
    "sg:postcode":"33762",
    "sg:province":"FL",
    "sg:tags":[
        "commercial"
    ],
    "wof:name":"Printing Impressions",
    "wof:placetype":"venue"
},
  "geometry": {"coordinates":[-82.69184199999999,27.875748],"type":"Point"}
}