{
  "type": "Feature",
  "properties": {
    "iso:country":"US",
    "sg:address":"950 SE 21 Ave",
    "sg:city":"Gainesville",
    "sg:classifiers":[
        {
            "category":"Building & Trades",
            "subcategory":"Landscaping Services",
            "type":"Services"
        }
    ],
    "sg:phone":"+1 352 376 4888",
    "sg:postcode":"32641",
    "sg:province":"FL",
    "wof:name":"E/F X Ground",
    "wof:placetype":"venue"
},
  "geometry": {"coordinates":[-82.314233,29.632396],"type":"Point"}
}