{
  "type": "Feature",
  "properties": {
    "addr:full":"1411 Moylan Rd Panama City Bch FL 32407",
    "addr:housenumber":"1411",
    "addr:postcode":"32407",
    "addr:street":"Moylan Rd",
    "iso:country":"US",
    "sg:address":"1411 Moylan Rd",
    "sg:city":"Panama City Bch",
    "sg:classifiers":[
        {
            "category":"Wholesale",
            "subcategory":"Drugs",
            "type":"Manufacturing & Wholesale Goods"
        }
    ],
    "sg:phone":"+1 850 235 0661",
    "sg:postcode":"32407",
    "sg:province":"FL",
    "sg:tags":[
        "cosmetic"
    ],
    "sg:website":"www.panamajack.com",
    "wof:name":"Panama Jack",
    "wof:placetype":"venue"
},
  "geometry": {"coordinates":[-85.79263400000001,30.186721],"type":"Point"}
}