{
  "type": "Feature",
  "properties": {
    "iso:country":"US",
    "sg:address":"3109 Lynwood Ct",
    "sg:city":"Land O Lakes",
    "sg:classifiers":[
        {
            "category":"Building & Trades",
            "subcategory":"Construction",
            "type":"Services"
        }
    ],
    "sg:phone":"+1 813 948 0753",
    "sg:postcode":"34638",
    "sg:province":"FL",
    "sg:tags":[
        "contractor"
    ],
    "wof:name":"Oakstead Model",
    "wof:placetype":"venue"
},
  "geometry": {"coordinates":[-82.485789,28.200488],"type":"Point"}
}