{
  "type": "Feature",
  "properties": {
    "addr:full":"1217 Island Rd West Palm Beach FL 33404",
    "addr:housenumber":"1217",
    "addr:postcode":"33404",
    "addr:street":"Island Rd",
    "iso:country":"US",
    "sg:address":"1217 Island Rd",
    "sg:city":"West Palm Beach",
    "sg:classifiers":[
        {
            "category":"Wholesale",
            "subcategory":"Non-durable Goods",
            "type":"Manufacturing & Wholesale Goods"
        }
    ],
    "sg:phone":"+1 561 841 5889",
    "sg:postcode":"33404",
    "sg:province":"FL",
    "wof:name":"Mako Lady Unlimited Inc",
    "wof:placetype":"venue"
},
  "geometry": {"coordinates":[-80.035944,26.782814],"type":"Point"}
}