{
  "type": "Feature",
  "properties": {
    "addr:full":"975 W Wisconsin Ave Deland FL 32720",
    "addr:housenumber":"975",
    "addr:postcode":"32720",
    "addr:street":"W Wisconsin Ave",
    "iso:country":"US",
    "sg:address":"975 W Wisconsin Ave",
    "sg:city":"Deland",
    "sg:classifiers":[
        {
            "category":"Insurance",
            "subcategory":"Hazard Insurance",
            "type":"Services"
        }
    ],
    "sg:phone":"+1 386 738 4805",
    "sg:postcode":"32720",
    "sg:province":"FL",
    "sg:website":"http://statefarm.mqgroup.com/url.asp?usr=592342",
    "wof:name":"State Farm Insurance Agent-Sonia Mori",
    "wof:placetype":"venue"
},
  "geometry": {"coordinates":[-81.32341099999999,29.031576],"type":"Point"}
}