{
  "type": "Feature",
  "properties": {
    "iso:country":"US",
    "sg:address":"9901 N 16th St",
    "sg:city":"Tampa",
    "sg:classifiers":[
        {
            "category":"Food & Beverages",
            "subcategory":"Groceries & Convenience Stores",
            "type":"Retail Goods"
        }
    ],
    "sg:phone":"+1 813 935 6486",
    "sg:postcode":"33612",
    "sg:province":"FL",
    "wof:name":"Mi Bohio",
    "wof:placetype":"venue"
},
  "geometry": {"coordinates":[-82.441582,28.039907],"type":"Point"}
}