{
  "type": "Feature",
  "properties": {
    "iso:country":"US",
    "sg:address":"2545 S French Ave",
    "sg:city":"Sanford",
    "sg:classifiers":[
        {
            "category":"Restaurant",
            "type":"Food & Drink"
        }
    ],
    "sg:menulink":"http://www.allmenus.com/fl/sanford/63578-bbq-rib-ranch/menu/",
    "sg:phone":"+1 407 321 0090",
    "sg:postcode":"32773",
    "sg:province":"FL",
    "sg:tags":[
        "barbecue",
        "american"
    ],
    "wof:name":"Bbq Rib Ranch",
    "wof:placetype":"venue"
},
  "geometry": {"coordinates":[-81.27278099999999,28.784634],"type":"Point"}
}