{
  "type": "Feature",
  "properties": {
    "iso:country":"US",
    "sg:address":"1661 SW 37th Ave",
    "sg:city":"Miami",
    "sg:phone":"+1 800 967 8840",
    "sg:postcode":"33145",
    "sg:province":"FL",
    "sg:website":"http://doctorflood.com",
    "wof:name":"Dr Flood Miami Beach-Water Removal Flood Mud Sewage Clean Up Fire Damage Restoration",
    "wof:placetype":"venue"
},
  "geometry": {"coordinates":[-80.254797,25.756254],"type":"Point"}
}