{
  "type": "Feature",
  "properties": {
    "addr:full":"2565 N Hiatus Rd Hollywood FL 33026",
    "addr:housenumber":"2565",
    "addr:postcode":"33026",
    "addr:street":"N Hiatus Rd",
    "iso:country":"US",
    "sg:address":"2565 N Hiatus Rd",
    "sg:city":"Hollywood",
    "sg:classifiers":[
        {
            "category":"Health Services",
            "subcategory":"Chiropractor",
            "type":"Services"
        }
    ],
    "sg:phone":"+1 954 252 7744",
    "sg:postcode":"33026",
    "sg:province":"FL",
    "wof:name":"Center-Family Health & Wellnes",
    "wof:placetype":"venue"
},
  "geometry": {"coordinates":[-80.29687,26.033006],"type":"Point"}
}