{
  "type": "Feature",
  "properties": {
    "addr:full":"1650 SE 111 Ct Morriston FL 32668",
    "addr:housenumber":"1650",
    "addr:postcode":"32668",
    "addr:street":"Se 111 Ct",
    "iso:country":"US",
    "sg:address":"1650 SE 111 Ct",
    "sg:city":"Morriston",
    "sg:classifiers":[
        {
            "category":"Professional",
            "subcategory":"Computer Services",
            "type":"Services"
        }
    ],
    "sg:phone":"+1 352 486 6711",
    "sg:postcode":"32668",
    "sg:province":"FL",
    "sg:tags":[
        "consultant",
        "designer"
    ],
    "wof:name":"Mark 1 Systems Corp",
    "wof:placetype":"venue"
},
  "geometry": {"coordinates":[-82.58797,29.31075],"type":"Point"}
}