{
  "type": "Feature",
  "properties": {
    "addr:full":"571 Diplomat Ct Marco Island FL 34145",
    "addr:housenumber":"571",
    "addr:postcode":"34145",
    "addr:street":"Diplomat Ct",
    "iso:country":"US",
    "sg:address":"571 Diplomat Ct",
    "sg:city":"Marco Island",
    "sg:classifiers":[
        {
            "category":"Restaurant",
            "type":"Food & Drink"
        }
    ],
    "sg:phone":"+1 239 389 9997",
    "sg:postcode":"34145",
    "sg:province":"FL",
    "sg:tags":[
        "caterer"
    ],
    "wof:name":"Cordon Bleu",
    "wof:placetype":"venue"
},
  "geometry": {"coordinates":[-81.737624,25.951385],"type":"Point"}
}