{
  "type": "Feature",
  "properties": {
    "addr:full":"2360 Glades Cir Weston FL 33327",
    "addr:housenumber":"2360",
    "addr:postcode":"33327",
    "addr:street":"Glades Cir",
    "iso:country":"US",
    "sg:address":"2360 Glades Cir",
    "sg:city":"Weston",
    "sg:classifiers":[
        {
            "category":"Place Of Worship",
            "subcategory":"Synagogue",
            "type":"Public Place"
        },
        {
            "category":"Place Of Worship",
            "type":"Public Place"
        },
        {
            "category":"Organizations",
            "subcategory":"Religious Organization",
            "type":"Services"
        }
    ],
    "sg:phone":"+1 954 389 1232",
    "sg:postcode":"33327",
    "sg:province":"FL",
    "sg:tags":[
        "synagogues-reform",
        "church"
    ],
    "wof:name":"Temple Dor Dorim",
    "wof:placetype":"venue"
},
  "geometry": {"coordinates":[-80.421846,26.138319],"type":"Point"}
}