{
  "type": "Feature",
  "properties": {
    "addr:full":"2660 SW College Rd Ocala FL 34471",
    "addr:housenumber":"2660",
    "addr:postcode":"34471",
    "addr:street":"Sw College Rd",
    "iso:country":"US",
    "sg:address":"2660 SW College Rd",
    "sg:city":"Ocala",
    "sg:classifiers":[
        {
            "category":"Professional",
            "subcategory":"Employment Agencies",
            "type":"Services"
        }
    ],
    "sg:phone":"+1 352 237 9660",
    "sg:postcode":"34471",
    "sg:province":"FL",
    "sg:tags":[
        "information",
        "technology"
    ],
    "wof:name":"Allegis Group Inc",
    "wof:placetype":"venue"
},
  "geometry": {"coordinates":[-82.17573899999999,29.159515],"type":"Point"}
}