{
  "type": "Feature",
  "properties": {
    "iso:country":"US",
    "sg:address":"8230 W 30th Ct",
    "sg:city":"Hialeah",
    "sg:classifiers":[
        {
            "category":"Wholesale",
            "subcategory":"Machinery & Supplies",
            "type":"Manufacturing & Wholesale Goods"
        }
    ],
    "sg:phone":"+1 305 827 4120",
    "sg:postcode":"33018",
    "sg:province":"FL",
    "sg:tags":[
        "equipment",
        "industrial",
        "representative",
        "mfg"
    ],
    "wof:name":"Enviro-Mechanical Inc",
    "wof:placetype":"venue"
},
  "geometry": {"coordinates":[-80.345356,25.896109],"type":"Point"}
}