{
  "type": "Feature",
  "properties": {
    "iso:country":"US",
    "sg:address":"3111 N University Dr",
    "sg:city":"Pompano Beach",
    "sg:classifiers":[
        {
            "category":"Banks & Credit Unions",
            "subcategory":"Investment Brokerage",
            "type":"Services"
        }
    ],
    "sg:phone":"+1 954 255 3411",
    "sg:postcode":"33065",
    "sg:province":"FL",
    "sg:tags":[
        "security",
        "management",
        "consulting"
    ],
    "wof:name":"RSM Equico Inc",
    "wof:placetype":"venue"
},
  "geometry": {"coordinates":[-80.249932,26.265425],"type":"Point"}
}