{
  "type": "Feature",
  "properties": {
    "iso:country":"US",
    "sg:address":"2132 Montana Ave NE",
    "sg:city":"Saint Petersburg",
    "sg:classifiers":[
        {
            "category":"Building & Trades",
            "subcategory":"Construction",
            "type":"Services"
        }
    ],
    "sg:phone":"+1 727 525 2405",
    "sg:postcode":"33703",
    "sg:province":"FL",
    "sg:tags":[
        "house"
    ],
    "wof:name":"Sun Bay Builders Inc",
    "wof:placetype":"venue"
},
  "geometry": {"coordinates":[-82.59863,27.820904],"type":"Point"}
}