{
  "type": "Feature",
  "properties": {
    "iso:country":"US",
    "sg:address":"205 Joel Blvd",
    "sg:city":"Lehigh Acres",
    "sg:classifiers":[
        {
            "category":"Shopping",
            "subcategory":"Discount & Variety Stores",
            "type":"Retail Goods"
        }
    ],
    "sg:phone":"+1 239 303 1311",
    "sg:postcode":"33972",
    "sg:province":"FL",
    "sg:tags":[
        "merchandise",
        "general"
    ],
    "wof:name":"Diabetic Supply Foundation",
    "wof:placetype":"venue"
},
  "geometry": {"coordinates":[-81.606183,26.607678],"type":"Point"}
}