{
  "type": "Feature",
  "properties": {
    "iso:country":"US",
    "sg:address":"445 Douglas Ave",
    "sg:city":"Altamonte Springs",
    "sg:classifiers":[
        {
            "category":"Wholesale",
            "subcategory":"Books, Periodicals, & Newspapers",
            "type":"Manufacturing & Wholesale Goods"
        }
    ],
    "sg:phone":"+1 407 331 5000",
    "sg:postcode":"32714",
    "sg:province":"FL",
    "sg:tags":[
        "distributor",
        "magazine",
        "broker"
    ],
    "wof:name":"Publishers Certified Service",
    "wof:placetype":"venue"
},
  "geometry": {"coordinates":[-81.390292,28.667837],"type":"Point"}
}