{
  "type": "Feature",
  "properties": {
    "addr:full":"1427 Baytowne Cir E Destin FL 32550",
    "addr:housenumber":"1427",
    "addr:postcode":"32550",
    "addr:street":"Baytowne Cir E",
    "iso:country":"US",
    "sg:address":"1427 Baytowne Cir E",
    "sg:city":"Destin",
    "sg:classifiers":[
        {
            "category":"Food & Beverages",
            "subcategory":"Specialty",
            "type":"Retail Goods"
        }
    ],
    "sg:phone":"+1 850 267 3302",
    "sg:postcode":"32550",
    "sg:province":"FL",
    "sg:tags":[
        "health",
        "diet"
    ],
    "wof:name":"Shaklee Distributor",
    "wof:placetype":"venue"
},
  "geometry": {"coordinates":[-86.310164,30.386163],"type":"Point"}
}