{
  "type": "Feature",
  "properties": {
    "iso:country":"US",
    "sg:address":"6201 W Sample Rd",
    "sg:city":"Coral Springs",
    "sg:classifiers":[
        {
            "category":"Banks & Credit Unions",
            "subcategory":"Bank",
            "type":"Services"
        }
    ],
    "sg:phone":"+1 954 752 3014",
    "sg:postcode":"33064",
    "sg:province":"FL",
    "wof:name":"Washington Mutual",
    "wof:placetype":"venue"
},
  "geometry": {"coordinates":[-80.211473,26.274049],"type":"Point"}
}