{
  "type": "Feature",
  "properties": {
    "addr:full":"1703 N Main St Kissimmee FL 34744",
    "addr:housenumber":"1703",
    "addr:postcode":"34744",
    "addr:street":"N Main St",
    "iso:country":"US",
    "sg:address":"1703 N Main St",
    "sg:city":"Kissimmee",
    "sg:classifiers":[
        {
            "category":"Organizations",
            "subcategory":"Non-profit Organization",
            "type":"Services"
        }
    ],
    "sg:phone":"+1 407 933 2064",
    "sg:postcode":"34744",
    "sg:province":"FL",
    "wof:name":"American Association For Nude",
    "wof:placetype":"venue"
},
  "geometry": {"coordinates":[-81.403662,28.308074],"type":"Point"}
}