{
  "type": "Feature",
  "properties": {
    "iso:country":"US",
    "sg:address":"1207 Tamarac Dr",
    "sg:city":"Holiday",
    "sg:classifiers":[
        {
            "category":"Personal",
            "subcategory":"Beauty Salon",
            "type":"Services"
        }
    ],
    "sg:phone":"+1 727 943 9772",
    "sg:postcode":"34690",
    "sg:province":"FL",
    "sg:tags":[
        "shop"
    ],
    "wof:name":"HI Salon Inc",
    "wof:placetype":"venue"
},
  "geometry": {"coordinates":[-82.72020500000001,28.174738],"type":"Point"}
}