{
  "type": "Feature",
  "properties": {
    "iso:country":"US",
    "sg:address":"890 Northern Way Ste F2",
    "sg:city":"Winter Springs",
    "sg:classifiers":[
        {
            "category":"Personal",
            "subcategory":"Massage",
            "type":"Services"
        },
        {
            "category":"Health Services",
            "subcategory":"Health Practitioner",
            "type":"Services"
        }
    ],
    "sg:phone":"+1 407 719 8883",
    "sg:postcode":"32708",
    "sg:province":"FL",
    "sg:tags":[
        "acupuncture"
    ],
    "sg:website":"www.serenitycenter.com",
    "wof:name":"Serenity Center",
    "wof:placetype":"venue"
},
  "geometry": {"coordinates":[-81.26213,28.675352],"type":"Point"}
}