{
  "type": "Feature",
  "properties": {
    "addr:full":"2225 SE Seamist St Port Saint Lucie FL 34952",
    "addr:housenumber":"2225",
    "addr:postcode":"34952",
    "addr:street":"Se Seamist St",
    "iso:country":"US",
    "sg:address":"2225 SE Seamist St",
    "sg:city":"Port Saint Lucie",
    "sg:classifiers":[
        {
            "category":"Personal",
            "subcategory":"Barber",
            "type":"Services"
        }
    ],
    "sg:phone":"+1 772 337 1913",
    "sg:postcode":"34952",
    "sg:province":"FL",
    "sg:tags":[
        "shop"
    ],
    "wof:name":"His Provision Inc",
    "wof:placetype":"venue"
},
  "geometry": {"coordinates":[-80.273269,27.274979],"type":"Point"}
}