{
  "type": "Feature",
  "properties": {
    "iso:country":"US",
    "sg:address":"1845 Oak Trl W",
    "sg:city":"Clearwater",
    "sg:classifiers":[
        {
            "category":"Building & Trades",
            "subcategory":"Construction",
            "type":"Services"
        }
    ],
    "sg:phone":"+1 727 512 1052",
    "sg:postcode":"33764",
    "sg:province":"FL",
    "sg:tags":[
        "house"
    ],
    "wof:name":"Mike Wehrli Trim",
    "wof:placetype":"venue"
},
  "geometry": {"coordinates":[-82.733188,27.930215],"type":"Point"}
}