{
  "type": "Feature",
  "properties": {
    "iso:country":"US",
    "sg:address":"9139 Ruger Dr",
    "sg:city":"New Port Richey",
    "sg:classifiers":[
        {
            "category":"Professional",
            "subcategory":"Advertising",
            "type":"Services"
        }
    ],
    "sg:phone":"+1 727 376 0151",
    "sg:postcode":"34655",
    "sg:province":"FL",
    "sg:tags":[
        "mail",
        "direct"
    ],
    "wof:name":"Endeavor Marketing Inc",
    "wof:placetype":"venue"
},
  "geometry": {"coordinates":[-82.663899,28.238842],"type":"Point"}
}