{
  "type": "Feature",
  "properties": {
    "addr:full":"209 Waterway Cir NE Port Charlotte FL 33952",
    "addr:housenumber":"209",
    "addr:postcode":"33952",
    "addr:street":"Waterway Cir Ne",
    "iso:country":"US",
    "sg:address":"209 Waterway Cir NE",
    "sg:city":"Port Charlotte",
    "sg:classifiers":[
        {
            "category":"Shopping",
            "subcategory":"Gifts & Souvenirs",
            "type":"Retail Goods"
        }
    ],
    "sg:phone":"+1 941 624 6116",
    "sg:postcode":"33952",
    "sg:province":"FL",
    "wof:name":"Cavanaghs Nest",
    "wof:placetype":"venue"
},
  "geometry": {"coordinates":[-82.09335299999999,26.973905],"type":"Point"}
}