{
  "type": "Feature",
  "properties": {
    "addr:full":"10765 NW 58th St Doral FL 33178",
    "addr:housenumber":"10765",
    "addr:postcode":"33178",
    "addr:street":"Nw 58Th St",
    "iso:country":"US",
    "sg:address":"10765 NW 58th St",
    "sg:city":"Doral",
    "sg:classifiers":[
        {
            "category":"Personal",
            "subcategory":"Nail Salon",
            "type":"Services"
        }
    ],
    "sg:phone":"+1 305 468 1755",
    "sg:postcode":"33178",
    "sg:province":"FL",
    "wof:name":"Unique Nails",
    "wof:placetype":"venue"
},
  "geometry": {"coordinates":[-80.371498,25.826099],"type":"Point"}
}