{
  "type": "Feature",
  "properties": {
    "iso:country":"US",
    "sg:address":"3883 Pembroke Rd",
    "sg:city":"Hollywood",
    "sg:classifiers":[
        {
            "category":"Utilities",
            "subcategory":"Cable",
            "type":"Services"
        }
    ],
    "sg:phone":"+1 954 966 1877",
    "sg:postcode":"33021",
    "sg:province":"FL",
    "sg:tags":[
        "television"
    ],
    "wof:name":"Access International",
    "wof:placetype":"venue"
},
  "geometry": {"coordinates":[-80.178135,25.995852],"type":"Point"}
}