{
  "type": "Feature",
  "properties": {
    "iso:country":"US",
    "sg:address":"1803 Wayne Dr",
    "sg:city":"Melbourne",
    "sg:classifiers":[
        {
            "category":"Building & Trades",
            "subcategory":"Landscaping Services",
            "type":"Services"
        }
    ],
    "sg:phone":"+1 321 728 4056",
    "sg:postcode":"32901",
    "sg:province":"FL",
    "wof:name":"Zachary S Bareford Lawn Svc",
    "wof:placetype":"venue"
},
  "geometry": {"coordinates":[-80.629915,28.082039],"type":"Point"}
}