{
  "type": "Feature",
  "properties": {
    "iso:country":"US",
    "sg:address":"3801 Bee Ridge Rd",
    "sg:city":"Sarasota",
    "sg:classifiers":[
        {
            "category":"Health Services",
            "subcategory":"Doctor",
            "type":"Services"
        }
    ],
    "sg:phone":"+1 941 924 1729",
    "sg:postcode":"34233",
    "sg:province":"FL",
    "sg:tags":[
        "osteopathic"
    ],
    "wof:name":"Van Buskirk Richard L Do",
    "wof:placetype":"venue"
},
  "geometry": {"coordinates":[-82.493414,27.298839],"type":"Point"}
}