{
  "type": "Feature",
  "properties": {
    "addr:full":"1535 Cypress Dr Jupiter FL 33469",
    "addr:housenumber":"1535",
    "addr:postcode":"33469",
    "addr:street":"Cypress Dr",
    "iso:country":"US",
    "sg:address":"1535 Cypress Dr",
    "sg:city":"Jupiter",
    "sg:classifiers":[
        {
            "category":"Food & Beverages",
            "subcategory":"Liquor & Beverages",
            "type":"Retail Goods"
        }
    ],
    "sg:phone":"+1 561 748 6747",
    "sg:postcode":"33469",
    "sg:province":"FL",
    "sg:tags":[
        "wine"
    ],
    "wof:name":"Vinum International",
    "wof:placetype":"venue"
},
  "geometry": {"coordinates":[-80.092839,26.966069],"type":"Point"}
}