{
  "type": "Feature",
  "properties": {
    "addr:full":"10601 Sheldon Rd Tampa FL 33626",
    "addr:housenumber":"10601",
    "addr:postcode":"33626",
    "addr:street":"Sheldon Rd",
    "iso:country":"US",
    "sg:address":"10601 Sheldon Rd",
    "sg:city":"Tampa",
    "sg:classifiers":[
        {
            "category":"Food & Beverages",
            "subcategory":"Groceries & Convenience Stores",
            "type":"Retail Goods"
        }
    ],
    "sg:phone":"+1 813 792 1354",
    "sg:postcode":"33626",
    "sg:province":"FL",
    "wof:name":"7-Eleven",
    "wof:placetype":"venue"
},
  "geometry": {"coordinates":[-82.582589,28.045942],"type":"Point"}
}