{
  "type": "Feature",
  "properties": {
    "addr:full":"160 S University Dr Plantation FL 33324",
    "addr:housenumber":"160",
    "addr:postcode":"33324",
    "addr:street":"S University Dr",
    "iso:country":"US",
    "sg:address":"160 S University Dr",
    "sg:city":"Plantation",
    "sg:classifiers":[
        {
            "category":"Recreation",
            "type":"Entertainment"
        }
    ],
    "sg:phone":"+1 954 423 9065",
    "sg:postcode":"33324",
    "sg:province":"FL",
    "sg:tags":[
        "spa",
        "hot",
        "tub"
    ],
    "wof:name":"AAA Anytime Svc",
    "wof:placetype":"venue"
},
  "geometry": {"coordinates":[-80.248071,26.008741],"type":"Point"}
}