{
  "type": "Feature",
  "properties": {
    "iso:country":"US",
    "sg:address":"7623 Tamarind Ave",
    "sg:city":"Tampa",
    "sg:classifiers":[
        {
            "category":"Recreation",
            "type":"Entertainment"
        }
    ],
    "sg:phone":"+1 813 926 1978",
    "sg:postcode":"33625",
    "sg:province":"FL",
    "wof:name":"Siemer Valerie Training",
    "wof:placetype":"venue"
},
  "geometry": {"coordinates":[-82.57333199999999,28.074834],"type":"Point"}
}