{
  "type": "Feature",
  "properties": {
    "iso:country":"US",
    "sg:address":"8250 Bryan Dairy Rd",
    "sg:city":"Seminole",
    "sg:classifiers":[
        {
            "category":"Professional",
            "subcategory":"Advertising",
            "type":"Services"
        }
    ],
    "sg:phone":"+1 727 366 1312",
    "sg:postcode":"33777",
    "sg:province":"FL",
    "sg:tags":[
        "advertising-telephone",
        "fax",
        "telemarketing"
    ],
    "sg:website":"http://www.mutualmarketing.net",
    "wof:name":"Mutual Marketing",
    "wof:placetype":"venue"
},
  "geometry": {"coordinates":[-82.753212,27.87219],"type":"Point"}
}