{
  "type": "Feature",
  "properties": {
    "iso:country":"US",
    "sg:address":"9471 Baymeadows Rd",
    "sg:city":"Jacksonville",
    "sg:classifiers":[
        {
            "category":"Utilities",
            "subcategory":"Refuse",
            "type":"Services"
        }
    ],
    "sg:phone":"+1 904 732 7358",
    "sg:postcode":"32256",
    "sg:province":"FL",
    "sg:tags":[
        "disposal",
        "waste"
    ],
    "wof:name":"Peerless Waste Industries Inc",
    "wof:placetype":"venue"
},
  "geometry": {"coordinates":[-81.561655,30.220993],"type":"Point"}
}