{
  "type": "Feature",
  "properties": {
    "addr:full":"404 Viscaya Ave Coral Gables FL 33134",
    "addr:housenumber":"404",
    "addr:postcode":"33134",
    "addr:street":"Viscaya Ave",
    "iso:country":"US",
    "sg:address":"404 Viscaya Ave",
    "sg:city":"Coral Gables",
    "sg:classifiers":[
        {
            "category":"Professional",
            "subcategory":"Lawyer & Legal Services",
            "type":"Services"
        }
    ],
    "sg:phone":"+1 305 476 0600",
    "sg:postcode":"33134",
    "sg:province":"FL",
    "wof:name":"Barns Paul D Jr Atty",
    "wof:placetype":"venue"
},
  "geometry": {"coordinates":[-80.262703,25.7379],"type":"Point"}
}