{
  "type": "Feature",
  "properties": {
    "addr:full":"3093 Cleveland Ave Fort Myers FL 33901",
    "addr:housenumber":"3093",
    "addr:postcode":"33901",
    "addr:street":"Cleveland Ave",
    "iso:country":"US",
    "sg:address":"3093 Cleveland Ave",
    "sg:city":"Fort Myers",
    "sg:classifiers":[
        {
            "category":"Personal",
            "subcategory":"Tattoo Parlor",
            "type":"Services"
        }
    ],
    "sg:phone":"+1 239 332 0200",
    "sg:postcode":"33901",
    "sg:province":"FL",
    "sg:tags":[
        "tattooing"
    ],
    "wof:name":"Skin Games",
    "wof:placetype":"venue"
},
  "geometry": {"coordinates":[-81.87214899999999,26.620223],"type":"Point"}
}