{
  "type": "Feature",
  "properties": {
    "addr:full":"180 Wilshire Blvd Casselberry FL 32707",
    "addr:housenumber":"180",
    "addr:postcode":"32707",
    "addr:street":"Wilshire Blvd",
    "iso:country":"US",
    "sg:address":"180 Wilshire Blvd",
    "sg:city":"Casselberry",
    "sg:classifiers":[
        {
            "category":"Organizations",
            "subcategory":"Religious Organization",
            "type":"Services"
        }
    ],
    "sg:phone":"+1 407 472 2100",
    "sg:postcode":"32707",
    "sg:province":"FL",
    "sg:tags":[
        "mirror"
    ],
    "sg:website":"http://www.answers4men.com",
    "wof:name":"Man In The Mirror Inc",
    "wof:placetype":"venue"
},
  "geometry": {"coordinates":[-81.32961299999999,28.650339],"type":"Point"}
}