{
  "type": "Feature",
  "properties": {
    "iso:country":"US",
    "sg:address":"2940 NW Commerce Park Dr",
    "sg:city":"Boynton Beach",
    "sg:classifiers":[
        {
            "category":"Wholesale",
            "subcategory":"Farm Supplies",
            "type":"Manufacturing & Wholesale Goods"
        }
    ],
    "sg:phone":"+1 561 588 0394",
    "sg:postcode":"33426",
    "sg:province":"FL",
    "sg:tags":[
        "landscaping",
        "product"
    ],
    "wof:name":"Lesco Service Center 435",
    "wof:placetype":"venue"
},
  "geometry": {"coordinates":[-80.07258299999999,26.554598],"type":"Point"}
}