{
  "type": "Feature",
  "properties": {
    "addr:full":"14843 SW 168th Ave Indiantown FL 34956",
    "addr:housenumber":"14843",
    "addr:postcode":"34956",
    "addr:street":"Sw 168Th Ave",
    "iso:country":"US",
    "sg:address":"14843 SW 168th Ave",
    "sg:city":"Indiantown",
    "sg:classifiers":[
        {
            "category":"Utilities",
            "subcategory":"Sewage",
            "type":"Services"
        }
    ],
    "sg:phone":"+1 772 597 3496",
    "sg:postcode":"34956",
    "sg:province":"FL",
    "sg:tags":[
        "disposal",
        "system"
    ],
    "wof:name":"Indiantown Co Inc",
    "wof:placetype":"venue"
},
  "geometry": {"coordinates":[-80.482433,27.025697],"type":"Point"}
}