{
  "type": "Feature",
  "properties": {
    "iso:country":"US",
    "sg:address":"810 N Tuxedo Ave",
    "sg:city":"Deland",
    "sg:classifiers":[
        {
            "category":"Shopping",
            "subcategory":"Catalog Store",
            "type":"Retail Goods"
        }
    ],
    "sg:phone":"+1 386 775 2785",
    "sg:postcode":"32724",
    "sg:province":"FL",
    "sg:tags":[
        "e"
    ],
    "wof:name":"Peter A Bromberg & Assoc",
    "wof:placetype":"venue"
},
  "geometry": {"coordinates":[-81.298005,29.042244],"type":"Point"}
}