{
  "type": "Feature",
  "properties": {
    "iso:country":"US",
    "sg:address":"640 E Ocean Ave",
    "sg:city":"Boynton Beach",
    "sg:classifiers":[
        {
            "category":"Professional",
            "subcategory":"Business Services",
            "type":"Services"
        }
    ],
    "sg:phone":"+1 561 738 0707",
    "sg:postcode":"33435",
    "sg:province":"FL",
    "sg:tags":[
        "event"
    ],
    "wof:name":"Special Requests",
    "wof:placetype":"venue"
},
  "geometry": {"coordinates":[-80.05783099999999,26.527034],"type":"Point"}
}