{
  "type": "Feature",
  "properties": {
    "addr:full":"380 Zinnia Dr Casselberry FL 32707",
    "addr:housenumber":"380",
    "addr:postcode":"32707",
    "addr:street":"Zinnia Dr",
    "iso:country":"US",
    "sg:address":"380 Zinnia Dr",
    "sg:city":"Casselberry",
    "sg:classifiers":[
        {
            "category":"Building & Trades",
            "subcategory":"Construction",
            "type":"Services"
        }
    ],
    "sg:phone":"+1 407 260 8279",
    "sg:postcode":"32707",
    "sg:province":"FL",
    "sg:tags":[
        "contractor"
    ],
    "wof:name":"Tile Marble & Brick",
    "wof:placetype":"venue"
},
  "geometry": {"coordinates":[-81.320053,28.652868],"type":"Point"}
}