{
  "type": "Feature",
  "properties": {
    "addr:full":"625 E New Haven Ave Melbourne FL 32901",
    "addr:housenumber":"625",
    "addr:postcode":"32901",
    "addr:street":"E New Haven Ave",
    "iso:country":"US",
    "sg:address":"625 E New Haven Ave",
    "sg:city":"Melbourne",
    "sg:classifiers":[
        {
            "category":"Organizations",
            "subcategory":"Non-profit Organization",
            "type":"Services"
        },
        {
            "category":"Professional",
            "type":"Services"
        }
    ],
    "sg:phone":"+1 321 783 3809",
    "sg:postcode":"32901",
    "sg:province":"FL",
    "wof:name":"Strawbridge Art League",
    "wof:placetype":"venue"
},
  "geometry": {"coordinates":[-80.609983,28.078406],"type":"Point"}
}