{
  "type": "Feature",
  "properties": {
    "iso:country":"US",
    "sg:address":"7600 38th Ave N",
    "sg:city":"St Petersburg",
    "sg:classifiers":[
        {
            "category":"Insurance",
            "subcategory":"Insurance Agent",
            "type":"Services"
        }
    ],
    "sg:phone":"+1 727 347 3515",
    "sg:postcode":"33710",
    "sg:province":"FL",
    "wof:name":"Joe Ems Insurance Agency Inc",
    "wof:placetype":"venue"
},
  "geometry": {"coordinates":[-82.74442500000001,27.806381],"type":"Point"}
}