{
  "type": "Feature",
  "properties": {
    "iso:country":"US",
    "sg:address":"86 Zenith St",
    "sg:city":"Port Charlotte",
    "sg:classifiers":[
        {
            "category":"Shopping",
            "subcategory":"Catalog Store",
            "type":"Retail Goods"
        }
    ],
    "sg:phone":"+1 941 815 0514",
    "sg:postcode":"33954",
    "sg:province":"FL",
    "sg:tags":[
        "house",
        "mail"
    ],
    "wof:name":"Lima John",
    "wof:placetype":"venue"
},
  "geometry": {"coordinates":[-82.06977500000001,27.030551],"type":"Point"}
}