{
  "type": "Feature",
  "properties": {
    "iso:country":"US",
    "sg:address":"1511 S Nova Rd",
    "sg:city":"Daytona Beach",
    "sg:classifiers":[
        {
            "category":"Shopping",
            "subcategory":"Music",
            "type":"Retail Goods"
        }
    ],
    "sg:phone":"+1 386 238 8822",
    "sg:postcode":"32114",
    "sg:province":"FL",
    "sg:tags":[
        "video",
        "disc",
        "tape",
        "cassette"
    ],
    "wof:name":"16000 Movies",
    "wof:placetype":"venue"
},
  "geometry": {"coordinates":[-81.028554,29.175563],"type":"Point"}
}