{
  "type": "Feature",
  "properties": {
    "iso:country":"US",
    "sg:address":"1019 Railroad Ave",
    "sg:city":"Tallahassee",
    "sg:classifiers":[
        {
            "category":"Shopping",
            "subcategory":"Used Merchandise",
            "type":"Retail Goods"
        }
    ],
    "sg:phone":"+1 850 224 6666",
    "sg:postcode":"32310",
    "sg:province":"FL",
    "wof:name":"Other Side",
    "wof:placetype":"venue"
},
  "geometry": {"coordinates":[-84.289749,30.433218],"type":"Point"}
}