{
  "type": "Feature",
  "properties": {
    "addr:full":"5213 8th Ave S Gulfport FL 33707",
    "addr:housenumber":"5213",
    "addr:postcode":"33707",
    "addr:street":"8Th Ave S",
    "iso:country":"US",
    "sg:address":"5213 8th Ave S",
    "sg:city":"Gulfport",
    "sg:classifiers":[
        {
            "category":"Wholesale",
            "subcategory":"Jewelry",
            "type":"Manufacturing & Wholesale Goods"
        }
    ],
    "sg:phone":"+1 727 327 8928",
    "sg:postcode":"33707",
    "sg:province":"FL",
    "sg:tags":[
        "beads"
    ],
    "wof:name":"Bead Land",
    "wof:placetype":"venue"
},
  "geometry": {"coordinates":[-82.705065,27.762419],"type":"Point"}
}