{
  "type": "Feature",
  "properties": {
    "addr:full":"1851 N University Dr Fort Lauderdale FL 33322",
    "addr:housenumber":"1851",
    "addr:postcode":"33322",
    "addr:street":"N University Dr",
    "iso:country":"US",
    "sg:address":"1851 N University Dr",
    "sg:city":"Fort Lauderdale",
    "sg:classifiers":[
        {
            "category":"Restaurant",
            "type":"Food & Drink"
        }
    ],
    "sg:menulink":"http://www.allmenus.com/fl/plantation/158602-arbys/menu/",
    "sg:phone":"+1 954 474 4452",
    "sg:postcode":"33322",
    "sg:province":"FL",
    "sg:tags":[
        "burger",
        "american"
    ],
    "wof:name":"Arby's",
    "wof:placetype":"venue"
},
  "geometry": {"coordinates":[-80.25716799999999,26.149252],"type":"Point"}
}