{
  "type": "Feature",
  "properties": {
    "addr:full":"1670 NW 94th Ave Miami FL 33172",
    "addr:housenumber":"1670",
    "addr:postcode":"33172",
    "addr:street":"Nw 94Th Ave",
    "iso:country":"US",
    "sg:address":"1670 NW 94th Ave",
    "sg:city":"Miami",
    "sg:classifiers":[
        {
            "category":"Wholesale",
            "subcategory":"Machinery & Supplies",
            "type":"Manufacturing & Wholesale Goods"
        }
    ],
    "sg:phone":"+1 305 599 1922",
    "sg:postcode":"33172",
    "sg:province":"FL",
    "sg:tags":[
        "equipment",
        "industrial"
    ],
    "wof:name":"Sahco Inc",
    "wof:placetype":"venue"
},
  "geometry": {"coordinates":[-80.347801,25.789945],"type":"Point"}
}