{
  "type": "Feature",
  "properties": {
    "addr:full":"150 Woodbridge Rd Palm Beach FL 33480",
    "addr:housenumber":"150",
    "addr:postcode":"33480",
    "addr:street":"Woodbridge Rd",
    "iso:country":"US",
    "sg:address":"150 Woodbridge Rd",
    "sg:city":"Palm Beach",
    "sg:classifiers":[
        {
            "category":"Building & Trades",
            "subcategory":"Construction",
            "type":"Services"
        }
    ],
    "sg:phone":"+1 561 802 3155",
    "sg:postcode":"33480",
    "sg:province":"FL",
    "sg:tags":[
        "general",
        "contractor"
    ],
    "wof:name":"Jalis Construction",
    "wof:placetype":"venue"
},
  "geometry": {"coordinates":[-80.03748899999999,26.677974],"type":"Point"}
}