{
  "type": "Feature",
  "properties": {
    "iso:country":"US",
    "sg:address":"8632 SE 133rd Ln",
    "sg:city":"Summerfield",
    "sg:classifiers":[
        {
            "category":"Retail",
            "subcategory":"Laundry & Dry Cleaning",
            "type":"Services"
        }
    ],
    "sg:phone":"+1 352 307 5625",
    "sg:postcode":"34491",
    "sg:province":"FL",
    "sg:tags":[
        "cleaner",
        "commercial"
    ],
    "wof:name":"Anns Cleaners",
    "wof:placetype":"venue"
},
  "geometry": {"coordinates":[-82.009242,29.027614],"type":"Point"}
}