{
  "type": "Feature",
  "properties": {
    "iso:country":"US",
    "sg:address":"4601 Sheridan St",
    "sg:city":"Hollywood",
    "sg:classifiers":[
        {
            "category":"Wholesale",
            "subcategory":"Machinery & Supplies",
            "type":"Manufacturing & Wholesale Goods"
        },
        {
            "category":"Wholesale",
            "subcategory":"Electrical",
            "type":"Manufacturing & Wholesale Goods"
        }
    ],
    "sg:phone":"+1 954 986 9688",
    "sg:postcode":"33021",
    "sg:province":"FL",
    "sg:tags":[
        "sales",
        "generator"
    ],
    "wof:name":"Demag Delaval",
    "wof:placetype":"venue"
},
  "geometry": {"coordinates":[-80.19246699999999,26.032722],"type":"Point"}
}