{
  "type": "Feature",
  "properties": {
    "iso:country":"US",
    "sg:address":"10055 NW 23rd Ave",
    "sg:city":"Miami",
    "sg:classifiers":[
        {
            "category":"Place Of Worship",
            "subcategory":"Church",
            "type":"Public Place"
        },
        {
            "category":"Place Of Worship",
            "type":"Public Place"
        }
    ],
    "sg:phone":"+1 305 835 8700",
    "sg:postcode":"33147",
    "sg:province":"FL",
    "sg:tags":[
        "churches-holiness"
    ],
    "wof:name":"Holy Hills Of Zion",
    "wof:placetype":"venue"
},
  "geometry": {"coordinates":[-80.23631,25.866419],"type":"Point"}
}