{
  "type": "Feature",
  "properties": {
    "addr:full":"5853 Calumet Ct Crestview FL 32536",
    "addr:housenumber":"5853",
    "addr:postcode":"32536",
    "addr:street":"Calumet Ct",
    "iso:country":"US",
    "sg:address":"5853 Calumet Ct",
    "sg:city":"Crestview",
    "sg:classifiers":[
        {
            "category":"Building & Trades",
            "subcategory":"Construction",
            "type":"Services"
        },
        {
            "category":"Retail",
            "subcategory":"Auto Repair",
            "type":"Services"
        }
    ],
    "sg:phone":"+1 850 758 0052",
    "sg:postcode":"32536",
    "sg:province":"FL",
    "sg:tags":[
        "glass",
        "coating",
        "tinting",
        "contractor"
    ],
    "wof:name":"Mike's Window Tint",
    "wof:placetype":"venue"
},
  "geometry": {"coordinates":[-86.574085,30.798802],"type":"Point"}
}