{
  "type": "Feature",
  "properties": {
    "iso:country":"US",
    "sg:address":"3062 Grand Ave",
    "sg:city":"Miami",
    "sg:classifiers":[
        {
            "category":"Shopping",
            "subcategory":"Shoes",
            "type":"Retail Goods"
        }
    ],
    "sg:phone":"+1 305 476 7773",
    "sg:postcode":"33133",
    "sg:province":"FL",
    "sg:tags":[
        "management",
        "store",
        "business"
    ],
    "wof:name":"Novo-Miami Import Corp",
    "wof:placetype":"venue"
},
  "geometry": {"coordinates":[-80.242814,25.727924],"type":"Point"}
}