{
  "type": "Feature",
  "properties": {
    "addr:full":"13510 46th St Live Oak FL 32060",
    "addr:housenumber":"13510",
    "addr:postcode":"32060",
    "addr:street":"46Th St",
    "iso:country":"US",
    "sg:address":"13510 46th St",
    "sg:city":"Live Oak",
    "sg:classifiers":[
        {
            "category":"Building & Trades",
            "subcategory":"Landscaping Services",
            "type":"Services"
        }
    ],
    "sg:phone":"+1 386 362 6885",
    "sg:postcode":"32060",
    "sg:province":"FL",
    "wof:name":"Cutting Edge Lawn Service",
    "wof:placetype":"venue"
},
  "geometry": {"coordinates":[-83.005692,30.367028],"type":"Point"}
}