{
  "type": "Feature",
  "properties": {
    "addr:full":"407 NW 9th Ave Fort Lauderdale FL 33311",
    "addr:housenumber":"407",
    "addr:postcode":"33311",
    "addr:street":"Nw 9Th Ave",
    "iso:country":"US",
    "sg:address":"407 NW 9th Ave",
    "sg:city":"Fort Lauderdale",
    "sg:classifiers":[
        {
            "category":"Real Estate",
            "subcategory":"Real Estate Agent",
            "type":"Services"
        }
    ],
    "sg:phone":"+1 954 767 9919",
    "sg:postcode":"33311",
    "sg:province":"FL",
    "sg:tags":[
        "property",
        "management"
    ],
    "wof:name":"Mount Olive Development",
    "wof:placetype":"venue"
},
  "geometry": {"coordinates":[-80.15362,26.127459],"type":"Point"}
}