{
  "type": "Feature",
  "properties": {
    "addr:full":"13651 Sophomore Ln Fort Myers FL 33912",
    "addr:housenumber":"13651",
    "addr:postcode":"33912",
    "addr:street":"Sophomore Ln",
    "iso:country":"US",
    "sg:address":"13651 Sophomore Ln",
    "sg:city":"Fort Myers",
    "sg:classifiers":[
        {
            "category":"Shopping",
            "subcategory":"Bicycles & Sporting Goods",
            "type":"Retail Goods"
        }
    ],
    "sg:phone":"+1 239 768 0989",
    "sg:postcode":"33912",
    "sg:province":"FL",
    "sg:tags":[
        "small",
        "gunsmith",
        "arms",
        "gun",
        "mfg"
    ],
    "wof:name":"Haverfield Firearms & Ammun",
    "wof:placetype":"venue"
},
  "geometry": {"coordinates":[-81.816475,26.542053],"type":"Point"}
}