{
  "type": "Feature",
  "properties": {
    "iso:country":"US",
    "sg:address":"15102 Sunset Dr",
    "sg:city":"Miami",
    "sg:classifiers":[
        {
            "category":"Shopping",
            "subcategory":"Music",
            "type":"Retail Goods"
        }
    ],
    "sg:phone":"+1 305 386 4084",
    "sg:postcode":"33193",
    "sg:province":"FL",
    "sg:tags":[
        "compact",
        "record",
        "disc",
        "tape"
    ],
    "wof:name":"Fabian's Records Musica Ncnl",
    "wof:placetype":"venue"
},
  "geometry": {"coordinates":[-80.436604,25.699163],"type":"Point"}
}