{
  "type": "Feature",
  "properties": {
    "iso:country":"US",
    "sg:address":"140 Circle Dr",
    "sg:city":"Maitland",
    "sg:classifiers":[
        {
            "category":"Social Services",
            "type":"Services"
        }
    ],
    "sg:phone":"+1 407 629 6866",
    "sg:postcode":"32751",
    "sg:province":"FL",
    "sg:tags":[
        "counseling"
    ],
    "wof:name":"Linda K Bronson",
    "wof:placetype":"venue"
},
  "geometry": {"coordinates":[-81.36647600000001,28.615692],"type":"Point"}
}