{
  "type": "Feature",
  "properties": {
    "iso:country":"US",
    "sg:address":"7801 NW 37th St",
    "sg:city":"Miami",
    "sg:classifiers":[
        {
            "category":"Wholesale",
            "subcategory":"Plants",
            "type":"Manufacturing & Wholesale Goods"
        }
    ],
    "sg:phone":"+1 305 644 8459",
    "sg:postcode":"33166",
    "sg:province":"FL",
    "sg:tags":[
        "rose"
    ],
    "wof:name":"Rosaprima",
    "wof:placetype":"venue"
},
  "geometry": {"coordinates":[-80.325282,25.80794],"type":"Point"}
}