{
  "type": "Feature",
  "properties": {
    "addr:full":"10702 Crosswicks Rd Jacksonville FL 32256",
    "addr:housenumber":"10702",
    "addr:postcode":"32256",
    "addr:street":"Crosswicks Rd",
    "iso:country":"US",
    "sg:address":"10702 Crosswicks Rd",
    "sg:city":"Jacksonville",
    "sg:classifiers":[
        {
            "category":"Professional",
            "type":"Services"
        }
    ],
    "sg:phone":"+1 904 641 3404",
    "sg:postcode":"32256",
    "sg:province":"FL",
    "wof:name":"Crosswicks Corporation",
    "wof:placetype":"venue"
},
  "geometry": {"coordinates":[-81.53817600000001,30.223882],"type":"Point"}
}