{
  "type": "Feature",
  "properties": {
    "iso:country":"US",
    "sg:address":"5055 NE 13th Ave",
    "sg:city":"Fort Lauderdale",
    "sg:classifiers":[
        {
            "category":"Manufacturing",
            "subcategory":"Signs",
            "type":"Manufacturing & Wholesale Goods"
        }
    ],
    "sg:phone":"+1 954 491 0141",
    "sg:postcode":"33334",
    "sg:province":"FL",
    "sg:tags":[
        "trim",
        "specialty",
        "mfg"
    ],
    "wof:name":"C H S",
    "wof:placetype":"venue"
},
  "geometry": {"coordinates":[-80.13034500000001,26.190397],"type":"Point"}
}