{
  "type": "Feature",
  "properties": {
    "iso:country":"US",
    "sg:address":"149 E Tilden St",
    "sg:city":"Winter Garden",
    "sg:classifiers":[
        {
            "category":"Food & Beverages",
            "subcategory":"Specialty",
            "type":"Retail Goods"
        }
    ],
    "sg:phone":"+1 407 654 2152",
    "sg:postcode":"34787",
    "sg:province":"FL",
    "wof:name":"Nutrition For Life",
    "wof:placetype":"venue"
},
  "geometry": {"coordinates":[-81.583235,28.569438],"type":"Point"}
}