{
  "type": "Feature",
  "properties": {
    "addr:full":"60 N Barrett Sq Rosemary Beach FL 32413",
    "addr:housenumber":"60",
    "addr:postcode":"32413",
    "addr:street":"N Barrett Sq",
    "iso:country":"US",
    "sg:address":"60 N Barrett Sq",
    "sg:city":"Rosemary Beach",
    "sg:classifiers":[
        {
            "category":"Cafe",
            "type":"Food & Drink"
        }
    ],
    "sg:menulink":"http://www.allmenus.com/fl/freeport/290596-summer-kitchen-cafe/menu/",
    "sg:phone":"+1 850 231 6264",
    "sg:postcode":"32413",
    "sg:province":"FL",
    "sg:tags":[
        "american",
        "sandwich"
    ],
    "wof:name":"Summer Kitchen Cafe",
    "wof:placetype":"venue"
},
  "geometry": {"coordinates":[-86.015691,30.280768],"type":"Point"}
}