{
  "type": "Feature",
  "properties": {
    "iso:country":"US",
    "sg:address":"11712 Veal Rd",
    "sg:city":"Panama City",
    "sg:classifiers":[
        {
            "category":"Farming",
            "subcategory":"Berry Farm",
            "type":"Manufacturing & Wholesale Goods"
        }
    ],
    "sg:phone":"+1 850 722 4819",
    "sg:postcode":"32404",
    "sg:province":"FL",
    "sg:tags":[
        "crop"
    ],
    "wof:name":"Sweatmore Ranch",
    "wof:placetype":"venue"
},
  "geometry": {"coordinates":[-85.418846,30.333947],"type":"Point"}
}