{
  "type": "Feature",
  "properties": {
    "iso:country":"US",
    "sg:address":"108 San Rafael Rd",
    "sg:city":"St Augustine",
    "sg:classifiers":[
        {
            "category":"Restaurant",
            "type":"Food & Drink"
        }
    ],
    "sg:phone":"+1 904 471 9060",
    "sg:postcode":"32080",
    "sg:province":"FL",
    "wof:name":"Fratellis Restaurant",
    "wof:placetype":"venue"
},
  "geometry": {"coordinates":[-81.281988,29.872291],"type":"Point"}
}