{
  "type": "Feature",
  "properties": {
    "iso:country":"US",
    "sg:address":"899 Silvarado Ct",
    "sg:city":"Lake Mary",
    "sg:classifiers":[
        {
            "category":"Real Estate",
            "subcategory":"Real Estate Agent",
            "type":"Services"
        }
    ],
    "sg:phone":"+1 407 302 0365",
    "sg:postcode":"32746",
    "sg:province":"FL",
    "wof:name":"Inter Pro Services",
    "wof:placetype":"venue"
},
  "geometry": {"coordinates":[-81.35528499999999,28.729673],"type":"Point"}
}