{
  "type": "Feature",
  "properties": {
    "iso:country":"US",
    "sg:address":"2010 N Flamingo Rd",
    "sg:city":"Hollywood",
    "sg:classifiers":[
        {
            "category":"Restaurant",
            "type":"Food & Drink"
        }
    ],
    "sg:menulink":"http://www.allmenus.com/fl/miramar-pembroke-pines/161191-cheeburger-cheeburger/menu/",
    "sg:phone":"+1 954 441 9799",
    "sg:postcode":"33028",
    "sg:province":"FL",
    "sg:tags":[
        "burger",
        "american",
        "diner"
    ],
    "wof:name":"Cheeburger Cheeburger",
    "wof:placetype":"venue"
},
  "geometry": {"coordinates":[-80.3125,26.026526],"type":"Point"}
}