{
  "type": "Feature",
  "properties": {
    "addr:full":"19701 NW 5th Ct Miami FL 33169",
    "addr:housenumber":"19701",
    "addr:postcode":"33169",
    "addr:street":"Nw 5Th Ct",
    "iso:country":"US",
    "sg:address":"19701 NW 5th Ct",
    "sg:city":"Miami",
    "sg:classifiers":[
        {
            "category":"Health Services",
            "subcategory":"Clinic",
            "type":"Services"
        }
    ],
    "sg:phone":"+1 305 336 5331",
    "sg:postcode":"33169",
    "sg:province":"FL",
    "wof:name":"Scott Rubylette Hlth Care Svcs",
    "wof:placetype":"venue"
},
  "geometry": {"coordinates":[-80.210554,25.956134],"type":"Point"}
}