{
  "type": "Feature",
  "properties": {
    "iso:country":"US",
    "sg:address":"2030 NW 68th St",
    "sg:city":"Miami",
    "sg:classifiers":[
        {
            "category":"Home & Garden",
            "subcategory":"Building Materials",
            "type":"Retail Goods"
        }
    ],
    "sg:phone":"+1 305 693 1637",
    "sg:postcode":"33147",
    "sg:province":"FL",
    "sg:tags":[
        "plumbing",
        "fixture",
        "supply"
    ],
    "wof:name":"Gwens Kitchen",
    "wof:placetype":"venue"
},
  "geometry": {"coordinates":[-80.230824,25.835626],"type":"Point"}
}