{
  "type": "Feature",
  "properties": {
    "iso:country":"US",
    "sg:address":"17390 SW 200th St",
    "sg:city":"Miami",
    "sg:classifiers":[
        {
            "category":"Building & Trades",
            "subcategory":"Landscaping Services",
            "type":"Services"
        }
    ],
    "sg:phone":"+1 305 232 1656",
    "sg:postcode":"33187",
    "sg:province":"FL",
    "sg:tags":[
        "consultant",
        "designer",
        "landscape",
        "contractor"
    ],
    "wof:name":"Florida Evergreen Foliage",
    "wof:placetype":"venue"
},
  "geometry": {"coordinates":[-80.47211299999999,25.579865],"type":"Point"}
}