{
  "type": "Feature",
  "properties": {
    "addr:full":"1785 W Fairbanks Ave Winter Park FL 32789",
    "addr:housenumber":"1785",
    "addr:postcode":"32789",
    "addr:street":"W Fairbanks Ave",
    "iso:country":"US",
    "sg:address":"1785 W Fairbanks Ave",
    "sg:city":"Winter Park",
    "sg:classifiers":[
        {
            "category":"Retail",
            "subcategory":"Repair Shop",
            "type":"Services"
        }
    ],
    "sg:phone":"+1 407 647 1544",
    "sg:postcode":"32789",
    "sg:province":"FL",
    "sg:tags":[
        "machine",
        "sewing"
    ],
    "wof:name":"Hallmark Sewing Machine",
    "wof:placetype":"venue"
},
  "geometry": {"coordinates":[-81.372809,28.592963],"type":"Point"}
}