{
  "type": "Feature",
  "properties": {
    "iso:country":"US",
    "sg:address":"233 State Hwy 16",
    "sg:city":"St Augustine",
    "sg:classifiers":[
        {
            "category":"Home & Garden",
            "subcategory":"Furniture",
            "type":"Retail Goods"
        }
    ],
    "sg:phone":"+1 904 829 0979",
    "sg:postcode":"32084",
    "sg:province":"FL",
    "sg:tags":[
        "mattress"
    ],
    "wof:name":"Beds Beds Beds",
    "wof:placetype":"venue"
},
  "geometry": {"coordinates":[-81.338307,29.915543],"type":"Point"}
}