{
  "type": "Feature",
  "properties": {
    "iso:country":"US",
    "sg:address":"5061 Placida Rd",
    "sg:city":"Englewood",
    "sg:classifiers":[
        {
            "category":"Building & Trades",
            "subcategory":"Landscaping Services",
            "type":"Services"
        }
    ],
    "sg:phone":"+1 941 625 6274",
    "sg:postcode":"34224",
    "sg:province":"FL",
    "sg:tags":[
        "landscape"
    ],
    "wof:name":"All American Trees & Ldscpg",
    "wof:placetype":"venue"
},
  "geometry": {"coordinates":[-82.31055499999999,26.898459],"type":"Point"}
}