{
  "type": "Feature",
  "properties": {
    "addr:full":"126 Anastasia Lodge Dr St Augustine FL 32080",
    "addr:housenumber":"126",
    "addr:postcode":"32080",
    "addr:street":"Anastasia Lodge Dr St",
    "iso:country":"US",
    "sg:address":"126 Anastasia Lodge Dr",
    "sg:city":"St Augustine",
    "sg:classifiers":[
        {
            "category":"Home & Garden",
            "subcategory":"Building Materials",
            "type":"Retail Goods"
        }
    ],
    "sg:phone":"+1 904 540 4300",
    "sg:postcode":"32080",
    "sg:province":"FL",
    "sg:tags":[
        "glass",
        "window",
        "plate"
    ],
    "wof:name":"Auto Glass Guy",
    "wof:placetype":"venue"
},
  "geometry": {"coordinates":[-81.267156,29.858991],"type":"Point"}
}