{
  "type": "Feature",
  "properties": {
    "iso:country":"US",
    "sg:address":"326 Eastern Ave",
    "sg:city":"St Cloud",
    "sg:classifiers":[
        {
            "category":"Shopping",
            "type":"Retail Goods"
        },
        {
            "category":"Wholesale",
            "subcategory":"Electrical",
            "type":"Manufacturing & Wholesale Goods"
        }
    ],
    "sg:phone":"+1 407 892 2887",
    "sg:postcode":"34769",
    "sg:province":"FL",
    "sg:tags":[
        "communication",
        "radio",
        "system",
        "merchandise",
        "mfg"
    ],
    "wof:name":"Airport Communications",
    "wof:placetype":"venue"
},
  "geometry": {"coordinates":[-81.26836900000001,28.2565],"type":"Point"}
}