{
  "type": "Feature",
  "properties": {
    "iso:country":"US",
    "sg:address":"10150 Highland Manor Dr",
    "sg:city":"Tampa",
    "sg:classifiers":[
        {
            "category":"Professional",
            "subcategory":"Lawyer & Legal Services",
            "type":"Services"
        }
    ],
    "sg:phone":"+1 813 684 7881",
    "sg:postcode":"33610",
    "sg:province":"FL",
    "sg:tags":[
        "attorney"
    ],
    "wof:name":"Limberopoulos Steingold",
    "wof:placetype":"venue"
},
  "geometry": {"coordinates":[-82.334097,27.983506],"type":"Point"}
}