{
  "type": "Feature",
  "properties": {
    "iso:country":"US",
    "sg:address":"16800 NW 2nd Ave Ste 202",
    "sg:city":"North Miami Beach",
    "sg:classifiers":[
        {
            "category":"Health Services",
            "subcategory":"Doctor",
            "type":"Services"
        }
    ],
    "sg:phone":"+1 305 653 6365",
    "sg:postcode":"33169",
    "sg:province":"FL",
    "wof:name":"Iskandarani Marwan MD",
    "wof:placetype":"venue"
},
  "geometry": {"coordinates":[-80.20447900000001,25.928822],"type":"Point"}
}