{
  "type": "Feature",
  "properties": {
    "addr:full":"135 N Woodland Blvd Deland FL 32720",
    "addr:housenumber":"135",
    "addr:postcode":"32720",
    "addr:street":"N Woodland Blvd",
    "iso:country":"US",
    "sg:address":"135 N Woodland Blvd",
    "sg:city":"Deland",
    "sg:classifiers":[
        {
            "category":"Real Estate",
            "subcategory":"Real Estate Services",
            "type":"Services"
        },
        {
            "category":"Real Estate",
            "subcategory":"Real Estate Agent",
            "type":"Services"
        }
    ],
    "sg:phone":"+1 386 734 8455",
    "sg:postcode":"32720",
    "sg:province":"FL",
    "sg:tags":[
        "buyer",
        "broker"
    ],
    "wof:name":"Mar Les Inc",
    "wof:placetype":"venue"
},
  "geometry": {"coordinates":[-81.303423,29.029104],"type":"Point"}
}