{
  "type": "Feature",
  "properties": {
    "iso:country":"US",
    "sg:address":"3536 Estates Rd",
    "sg:city":"Tallahassee",
    "sg:classifiers":[
        {
            "category":"Social Services",
            "type":"Services"
        }
    ],
    "sg:phone":"+1 850 575 2719",
    "sg:postcode":"32305",
    "sg:province":"FL",
    "wof:name":"Imani Dnce Prgrm Fr Yth Delvp",
    "wof:placetype":"venue"
},
  "geometry": {"coordinates":[-84.303915,30.395371],"type":"Point"}
}