{
  "type": "Feature",
  "properties": {
    "iso:country":"US",
    "sg:address":"820 NE 46th Ct",
    "sg:city":"Oakland Park",
    "sg:classifiers":[
        {
            "category":"Home & Garden",
            "subcategory":"Carpets & Floor Coverings",
            "type":"Retail Goods"
        }
    ],
    "sg:phone":"+1 954 267 8674",
    "sg:postcode":"33334",
    "sg:province":"FL",
    "sg:tags":[
        "dealer",
        "rug"
    ],
    "wof:name":"Carpet Man",
    "wof:placetype":"venue"
},
  "geometry": {"coordinates":[-80.137559,26.184265],"type":"Point"}
}