{
  "type": "Feature",
  "properties": {
    "iso:country":"US",
    "sg:address":"10018 W McNab Rd",
    "sg:city":"Tamarac",
    "sg:classifiers":[
        {
            "category":"Retail",
            "subcategory":"Laundry & Dry Cleaning",
            "type":"Services"
        }
    ],
    "sg:phone":"+1 954 741 6633",
    "sg:postcode":"33321",
    "sg:province":"FL",
    "sg:tags":[
        "cleaners",
        "rug",
        "carpet"
    ],
    "wof:name":"Chem-Dry Hal",
    "wof:placetype":"venue"
},
  "geometry": {"coordinates":[-80.29113599999999,26.208318],"type":"Point"}
}