{
  "type": "Feature",
  "properties": {
    "addr:full":"5081 Sheridan St Hollywood FL 33021",
    "addr:housenumber":"5081",
    "addr:postcode":"33021",
    "addr:street":"Sheridan St",
    "iso:country":"US",
    "sg:address":"5081 Sheridan St",
    "sg:city":"Hollywood",
    "sg:classifiers":[
        {
            "category":"Shopping",
            "subcategory":"Clothing, Apparel, & Fashions",
            "type":"Retail Goods"
        }
    ],
    "sg:phone":"+1 954 894 2343",
    "sg:postcode":"33021",
    "sg:province":"FL",
    "wof:name":"Body & Swim",
    "wof:placetype":"venue"
},
  "geometry": {"coordinates":[-80.19058200000001,26.032831],"type":"Point"}
}