{
  "type": "Feature",
  "properties": {
    "addr:full":"195 W Pine Ave Longwood FL 32750",
    "addr:housenumber":"195",
    "addr:postcode":"32750",
    "addr:street":"W Pine Ave",
    "iso:country":"US",
    "sg:address":"195 W Pine Ave",
    "sg:city":"Longwood",
    "sg:classifiers":[
        {
            "category":"Wholesale",
            "subcategory":"Electrical",
            "type":"Manufacturing & Wholesale Goods"
        }
    ],
    "sg:phone":"+1 407 831 8233",
    "sg:postcode":"32750",
    "sg:province":"FL",
    "sg:tags":[
        "electronic",
        "component",
        "representative"
    ],
    "wof:name":"Semtronic Associates Inc",
    "wof:placetype":"venue"
},
  "geometry": {"coordinates":[-81.347289,28.698787],"type":"Point"}
}