{
  "type": "Feature",
  "properties": {
    "iso:country":"US",
    "sg:address":"1014 Ringo Ln",
    "sg:city":"Immokalee",
    "sg:classifiers":[
        {
            "category":"Organizations",
            "subcategory":"Religious Organization",
            "type":"Services"
        }
    ],
    "sg:phone":"+1 239 657 6650",
    "sg:postcode":"34142",
    "sg:province":"FL",
    "sg:tags":[
        "church"
    ],
    "wof:name":"Immokalee Church Of Nazarene",
    "wof:placetype":"venue"
},
  "geometry": {"coordinates":[-81.442339,26.432453],"type":"Point"}
}