{
  "type": "Feature",
  "properties": {
    "iso:country":"US",
    "sg:address":"811 Eyrie Dr Ste C",
    "sg:city":"Oviedo",
    "sg:classifiers":[
        {
            "category":"Personal",
            "subcategory":"Nail Salon",
            "type":"Services"
        }
    ],
    "sg:phone":"+1 407 366 0014",
    "sg:postcode":"32765",
    "sg:province":"FL",
    "wof:name":"Diamond Nails To Tails Inc",
    "wof:placetype":"venue"
},
  "geometry": {"coordinates":[-81.223448,28.658381],"type":"Point"}
}