{
  "type": "Feature",
  "properties": {
    "addr:full":"4665 N US Hwy 1 Rockledge FL 32955",
    "addr:housenumber":"4665",
    "addr:postcode":"32955",
    "addr:street":"N Us Hwy 1",
    "iso:country":"US",
    "sg:address":"4665 N US Hwy 1",
    "sg:city":"Rockledge",
    "sg:classifiers":[
        {
            "category":"Shopping",
            "subcategory":"Used Merchandise",
            "type":"Retail Goods"
        }
    ],
    "sg:phone":"+1 321 632 3434",
    "sg:postcode":"32955",
    "sg:province":"FL",
    "wof:name":"Victorias Antiques and Gifts",
    "wof:placetype":"venue"
},
  "geometry": {"coordinates":[-80.69021499999999,28.267249],"type":"Point"}
}