{
  "type": "Feature",
  "properties": {
    "iso:country":"US",
    "sg:address":"170 Dairy Rd",
    "sg:city":"Auburndale",
    "sg:classifiers":[
        {
            "category":"Building & Trades",
            "subcategory":"Landscaping Services",
            "type":"Services"
        }
    ],
    "sg:phone":"+1 863 965 1389",
    "sg:postcode":"33823",
    "sg:province":"FL",
    "wof:name":"Reliable Lawn Ser",
    "wof:placetype":"venue"
},
  "geometry": {"coordinates":[-81.77637900000001,28.06906],"type":"Point"}
}