{
  "type": "Feature",
  "properties": {
    "iso:country":"US",
    "sg:address":"2742 SW 8th St Ste 217",
    "sg:city":"Miami",
    "sg:classifiers":[
        {
            "category":"Organizations",
            "subcategory":"Community Association",
            "type":"Services"
        }
    ],
    "sg:phone":"+1 305 553 8423",
    "sg:postcode":"33135",
    "sg:province":"FL",
    "wof:name":"Municipio De Regla En El Exilio Inc",
    "wof:placetype":"venue"
},
  "geometry": {"coordinates":[-80.23965,25.765156],"type":"Point"}
}