{
  "type": "Feature",
  "properties": {
    "iso:country":"US",
    "sg:address":"1521 Palm Beach Trace Dr",
    "sg:city":"West Palm Beach",
    "sg:classifiers":[
        {
            "category":"Professional",
            "subcategory":"Business Services",
            "type":"Services"
        }
    ],
    "sg:phone":"+1 561 317 6031",
    "sg:postcode":"33411",
    "sg:province":"FL",
    "sg:tags":[
        "pool",
        "swimming"
    ],
    "wof:name":"Clean Splash",
    "wof:placetype":"venue"
},
  "geometry": {"coordinates":[-80.22552899999999,26.712199],"type":"Point"}
}