{
  "type": "Feature",
  "properties": {
    "iso:country":"US",
    "sg:address":"405 Alexandria Blvd",
    "sg:city":"Oviedo",
    "sg:classifiers":[
        {
            "category":"Insurance",
            "subcategory":"Insurance Agent",
            "type":"Services"
        }
    ],
    "sg:phone":"+1 407 366 5710",
    "sg:postcode":"32765",
    "sg:province":"FL",
    "sg:tags":[
        "agency",
        "title"
    ],
    "wof:name":"New Century Title of Orlando",
    "wof:placetype":"venue"
},
  "geometry": {"coordinates":[-81.206101,28.652538],"type":"Point"}
}