{
  "type": "Feature",
  "properties": {
    "iso:country":"US",
    "sg:address":"510 Briarcliff Ct",
    "sg:city":"Melbourne",
    "sg:classifiers":[
        {
            "category":"Insurance",
            "subcategory":"Insurance Agent",
            "type":"Services"
        }
    ],
    "sg:phone":"+1 321 751 0221",
    "sg:postcode":"32940",
    "sg:province":"FL",
    "wof:name":"Adjusters International",
    "wof:placetype":"venue"
},
  "geometry": {"coordinates":[-80.694683,28.237113],"type":"Point"}
}