{
  "type": "Feature",
  "properties": {
    "iso:country":"US",
    "sg:address":"209 Esplanade Way",
    "sg:city":"Casselberry",
    "sg:classifiers":[
        {
            "category":"Professional",
            "type":"Services"
        }
    ],
    "sg:phone":"+1 407 339 2191",
    "sg:postcode":"32707",
    "sg:province":"FL",
    "wof:name":"Kaye Leta Jimersons Kreatio",
    "wof:placetype":"venue"
},
  "geometry": {"coordinates":[-81.32569100000001,28.644892],"type":"Point"}
}