{
  "type": "Feature",
  "properties": {
    "addr:full":"3270 Suntree Blvd Melbourne FL 32940",
    "addr:housenumber":"3270",
    "addr:postcode":"32940",
    "addr:street":"Suntree Blvd",
    "iso:country":"US",
    "sg:address":"3270 Suntree Blvd",
    "sg:city":"Melbourne",
    "sg:classifiers":[
        {
            "category":"Recreation",
            "type":"Entertainment"
        }
    ],
    "sg:phone":"+1 321 757 5505",
    "sg:postcode":"32940",
    "sg:province":"FL",
    "sg:tags":[
        "club",
        "baseball"
    ],
    "wof:name":"Top Prospects Baseball",
    "wof:placetype":"venue"
},
  "geometry": {"coordinates":[-80.678399,28.227919],"type":"Point"}
}