{
  "type": "Feature",
  "properties": {
    "addr:full":"3930 NE 2nd Ave Miami FL 33137",
    "addr:housenumber":"3930",
    "addr:postcode":"33137",
    "addr:street":"Ne 2Nd Ave",
    "iso:country":"US",
    "sg:address":"3930 NE 2nd Ave",
    "sg:city":"Miami",
    "sg:classifiers":[
        {
            "category":"Restaurant",
            "type":"Food & Drink"
        }
    ],
    "sg:phone":"+1 305 573 0444",
    "sg:postcode":"33137",
    "sg:province":"FL",
    "sg:website":"www.elementsrestaurant.net",
    "wof:name":"Elements",
    "wof:placetype":"venue"
},
  "geometry": {"coordinates":[-80.191367,25.813021],"type":"Point"}
}