{
  "type": "Feature",
  "properties": {
    "addr:full":"1111 Homestead Rd N Lehigh Acres FL 33936",
    "addr:housenumber":"1111",
    "addr:postcode":"33936",
    "addr:street":"Homestead Rd N",
    "iso:country":"US",
    "sg:address":"1111 Homestead Rd N",
    "sg:city":"Lehigh Acres",
    "sg:classifiers":[
        {
            "category":"Restaurant",
            "type":"Food & Drink"
        }
    ],
    "sg:phone":"+1 239 369 1110",
    "sg:postcode":"33936",
    "sg:province":"FL",
    "wof:name":"China Star Chinese American",
    "wof:placetype":"venue"
},
  "geometry": {"coordinates":[-81.64899200000001,26.605879],"type":"Point"}
}