{
  "type": "Feature",
  "properties": {
    "iso:country":"US",
    "sg:address":"8601 N Davis Hwy",
    "sg:city":"Pensacola",
    "sg:phone":"+1 850 477 5951",
    "sg:postcode":"32514",
    "sg:province":"FL",
    "sg:tags":[
        "oil"
    ],
    "wof:name":"Texaco Mini Mart",
    "wof:placetype":"venue"
},
  "geometry": {"coordinates":[-87.21368699999999,30.519638],"type":"Point"}
}