{
  "type": "Feature",
  "properties": {
    "addr:full":"217 N Lake Ave Tavares FL 32778",
    "addr:housenumber":"217",
    "addr:postcode":"32778",
    "addr:street":"N Lake Ave",
    "iso:country":"US",
    "sg:address":"217 N Lake Ave",
    "sg:city":"Tavares",
    "sg:classifiers":[
        {
            "category":"Retail",
            "subcategory":"Auto Repair",
            "type":"Services"
        }
    ],
    "sg:phone":"+1 352 742 1002",
    "sg:postcode":"32778",
    "sg:province":"FL",
    "sg:tags":[
        "body",
        "automobile",
        "painting"
    ],
    "wof:name":"AFP Bodyworks",
    "wof:placetype":"venue"
},
  "geometry": {"coordinates":[-81.73673599999999,28.804118],"type":"Point"}
}