{
  "type": "Feature",
  "properties": {
    "iso:country":"US",
    "sg:address":"126 E Olympia Ave",
    "sg:city":"Punta Gorda",
    "sg:classifiers":[
        {
            "category":"Real Estate",
            "subcategory":"Real Estate Agent",
            "type":"Services"
        }
    ],
    "sg:phone":"+1 941 639 1120",
    "sg:postcode":"33950",
    "sg:province":"FL",
    "wof:name":"United Realty Of Sw Florida",
    "wof:placetype":"venue"
},
  "geometry": {"coordinates":[-82.04758099999999,26.935934],"type":"Point"}
}