{
  "type": "Feature",
  "properties": {
    "iso:country":"US",
    "sg:address":"265 E Marion Ave",
    "sg:city":"Punta Gorda",
    "sg:classifiers":[
        {
            "category":"Personal",
            "type":"Services"
        }
    ],
    "sg:phone":"+1 941 575 6178",
    "sg:postcode":"33950",
    "sg:province":"FL",
    "sg:tags":[
        "cosmetic"
    ],
    "wof:name":"Permanent Cosmetics",
    "wof:placetype":"venue"
},
  "geometry": {"coordinates":[-82.04723300000001,26.93761],"type":"Point"}
}