{
  "type": "Feature",
  "properties": {
    "iso:country":"US",
    "sg:address":"677 N Washington Blvd",
    "sg:city":"Sarasota",
    "sg:classifiers":[
        {
            "category":"Banks & Credit Unions",
            "subcategory":"Bank",
            "type":"Services"
        }
    ],
    "sg:phone":"+1 941 952 5824",
    "sg:postcode":"34236",
    "sg:province":"FL",
    "sg:tags":[
        "loan",
        "real estate"
    ],
    "wof:name":"Coast To Coast Mortgage",
    "wof:placetype":"venue"
},
  "geometry": {"coordinates":[-82.53106099999999,27.341384],"type":"Point"}
}