{
  "type": "Feature",
  "properties": {
    "addr:full":"1925 Dewey St Hollywood FL 33020",
    "addr:housenumber":"1925",
    "addr:postcode":"33020",
    "addr:street":"Dewey St",
    "iso:country":"US",
    "sg:address":"1925 Dewey St",
    "sg:city":"Hollywood",
    "sg:classifiers":[
        {
            "category":"Arts & Performance",
            "subcategory":"Music",
            "type":"Entertainment"
        }
    ],
    "sg:phone":"+1 954 929 7733",
    "sg:postcode":"33020",
    "sg:province":"FL",
    "sg:tags":[
        "wedding"
    ],
    "wof:name":"Randy Singer Music Inc",
    "wof:placetype":"venue"
},
  "geometry": {"coordinates":[-80.14531599999999,26.003134],"type":"Point"}
}