{
  "type": "Feature",
  "properties": {
    "iso:country":"US",
    "sg:address":"3435 Enterprise Ave",
    "sg:city":"Naples",
    "sg:classifiers":[
        {
            "category":"Retail",
            "subcategory":"Repair Shop",
            "type":"Services"
        }
    ],
    "sg:phone":"+1 239 261 1350",
    "sg:postcode":"34104",
    "sg:province":"FL",
    "sg:tags":[
        "welding"
    ],
    "wof:name":"WBA Fabrication Inc",
    "wof:placetype":"venue"
},
  "geometry": {"coordinates":[-81.759823,26.160757],"type":"Point"}
}