{
  "type": "Feature",
  "properties": {
    "addr:full":"16031 SW 300th St Homestead FL 33033",
    "addr:housenumber":"16031",
    "addr:postcode":"33033",
    "addr:street":"Sw 300Th St",
    "iso:country":"US",
    "sg:address":"16031 SW 300th St",
    "sg:city":"Homestead",
    "sg:classifiers":[
        {
            "category":"Building & Trades",
            "subcategory":"Construction",
            "type":"Services"
        }
    ],
    "sg:phone":"+1 305 246 3047",
    "sg:postcode":"33033",
    "sg:province":"FL",
    "wof:name":"S Rodea Corp",
    "wof:placetype":"venue"
},
  "geometry": {"coordinates":[-80.452541,25.488422],"type":"Point"}
}