{
  "type": "Feature",
  "properties": {
    "addr:full":"1300 Thicket Ln Sarasota FL 34240",
    "addr:housenumber":"1300",
    "addr:postcode":"34240",
    "addr:street":"Thicket Ln",
    "iso:country":"US",
    "sg:address":"1300 Thicket Ln",
    "sg:city":"Sarasota",
    "sg:classifiers":[
        {
            "category":"Building & Trades",
            "subcategory":"Construction",
            "type":"Services"
        }
    ],
    "sg:phone":"+1 941 915 7862",
    "sg:postcode":"34240",
    "sg:province":"FL",
    "sg:tags":[
        "roofing",
        "industrial",
        "contractors-commercial",
        "contractor"
    ],
    "wof:name":"Galvans Inc",
    "wof:placetype":"venue"
},
  "geometry": {"coordinates":[-82.423782,27.344007],"type":"Point"}
}