{
  "type": "Feature",
  "properties": {
    "iso:country":"US",
    "sg:address":"629 Tuscanny St",
    "sg:city":"Brandon",
    "sg:classifiers":[
        {
            "category":"Personal",
            "type":"Services"
        }
    ],
    "sg:phone":"+1 813 689 5652",
    "sg:postcode":"33511",
    "sg:province":"FL",
    "sg:tags":[
        "miscellaneous"
    ],
    "wof:name":"Clone Yourself Concierge Svc",
    "wof:placetype":"venue"
},
  "geometry": {"coordinates":[-82.263105,27.931402],"type":"Point"}
}