{
  "type": "Feature",
  "properties": {
    "addr:full":"7751 Industrial Rd Melbourne FL 32904",
    "addr:housenumber":"7751",
    "addr:postcode":"32904",
    "addr:street":"Industrial Rd",
    "iso:country":"US",
    "sg:address":"7751 Industrial Rd",
    "sg:city":"Melbourne",
    "sg:classifiers":[
        {
            "category":"Home & Garden",
            "subcategory":"Building Materials",
            "type":"Retail Goods"
        }
    ],
    "sg:phone":"+1 321 724 1593",
    "sg:postcode":"32904",
    "sg:province":"FL",
    "sg:tags":[
        "door"
    ],
    "wof:name":"Omega Garage Door Co",
    "wof:placetype":"venue"
},
  "geometry": {"coordinates":[-80.677398,28.098172],"type":"Point"}
}