{
  "type": "Feature",
  "properties": {
    "iso:country":"US",
    "sg:address":"9657 Ilex Cir S",
    "sg:city":"Palm Beach Gardens",
    "sg:classifiers":[
        {
            "category":"Professional",
            "type":"Services"
        }
    ],
    "sg:phone":"+1 561 625 5616",
    "sg:postcode":"33410",
    "sg:province":"FL",
    "wof:name":"Tshield Inc",
    "wof:placetype":"venue"
},
  "geometry": {"coordinates":[-80.098894,26.818413],"type":"Point"}
}