{
  "type": "Feature",
  "properties": {
    "iso:country":"US",
    "sg:address":"1250 N University Dr",
    "sg:city":"Coral Springs",
    "sg:classifiers":[
        {
            "category":"Shopping",
            "type":"Retail Goods"
        }
    ],
    "sg:phone":"+1 954 346 9040",
    "sg:postcode":"33071",
    "sg:province":"FL",
    "sg:tags":[
        "cosmetic",
        "perfume"
    ],
    "wof:name":"SFC Of Coral Springs",
    "wof:placetype":"venue"
},
  "geometry": {"coordinates":[-80.253044,26.247017],"type":"Point"}
}