{
  "type": "Feature",
  "properties": {
    "addr:full":"11150 N 30th St Tampa FL 33612",
    "addr:housenumber":"11150",
    "addr:postcode":"33612",
    "addr:street":"N 30Th St",
    "iso:country":"US",
    "sg:address":"11150 N 30th St",
    "sg:city":"Tampa",
    "sg:classifiers":[
        {
            "category":"Restaurant",
            "type":"Food & Drink"
        }
    ],
    "sg:phone":"+1 813 979 0013",
    "sg:postcode":"33612",
    "sg:province":"FL",
    "sg:tags":[
        "barbecue"
    ],
    "wof:name":"Bar B Que King",
    "wof:placetype":"venue"
},
  "geometry": {"coordinates":[-82.426255,28.048115],"type":"Point"}
}