{
  "type": "Feature",
  "properties": {
    "addr:full":"3213 Apalachee Pkwy Tallahassee FL 32311",
    "addr:housenumber":"3213",
    "addr:postcode":"32311",
    "addr:street":"Apalachee Pkwy",
    "iso:country":"US",
    "sg:address":"3213 Apalachee Pkwy",
    "sg:city":"Tallahassee",
    "sg:classifiers":[
        {
            "category":"Home & Garden",
            "subcategory":"Furniture",
            "type":"Retail Goods"
        }
    ],
    "sg:phone":"+1 850 385 2065",
    "sg:postcode":"32311",
    "sg:province":"FL",
    "wof:name":"Scan Haus Import Office",
    "wof:placetype":"venue"
},
  "geometry": {"coordinates":[-84.224142,30.42756],"type":"Point"}
}