{
  "type": "Feature",
  "properties": {
    "iso:country":"US",
    "sg:address":"3208 E Gonzalez St",
    "sg:city":"Pensacola",
    "sg:classifiers":[
        {
            "category":"Government",
            "subcategory":"Office",
            "type":"Public Place"
        }
    ],
    "sg:phone":"+1 850 435 1794",
    "sg:postcode":"32503",
    "sg:province":"FL",
    "sg:tags":[
        "village"
    ],
    "wof:name":"East Pensacola Heights Ctr",
    "wof:placetype":"venue"
},
  "geometry": {"coordinates":[-87.177511,30.427954],"type":"Point"}
}