{
  "type": "Feature",
  "properties": {
    "addr:full":"440 45th Ave Vero Beach FL 32968",
    "addr:housenumber":"440",
    "addr:postcode":"32968",
    "addr:street":"45Th Ave",
    "iso:country":"US",
    "sg:address":"440 45th Ave",
    "sg:city":"Vero Beach",
    "sg:classifiers":[
        {
            "category":"Shopping",
            "subcategory":"Discount & Variety Stores",
            "type":"Retail Goods"
        }
    ],
    "sg:phone":"+1 772 562 9216",
    "sg:postcode":"32968",
    "sg:province":"FL",
    "sg:tags":[
        "merchandise",
        "general"
    ],
    "wof:name":"Richard Perkins Sales",
    "wof:placetype":"venue"
},
  "geometry": {"coordinates":[-80.432958,27.612075],"type":"Point"}
}