{
  "type": "Feature",
  "properties": {
    "iso:country":"US",
    "sg:address":"5300 NW 12th Ave",
    "sg:city":"Fort Lauderdale",
    "sg:classifiers":[
        {
            "category":"Real Estate",
            "subcategory":"Architect",
            "type":"Services"
        }
    ],
    "sg:phone":"+1 954 776 1698",
    "sg:postcode":"33309",
    "sg:province":"FL",
    "wof:name":"Sehres Danon Architecture",
    "wof:placetype":"venue"
},
  "geometry": {"coordinates":[-80.159525,26.193462],"type":"Point"}
}