{
  "type": "Feature",
  "properties": {
    "iso:country":"US",
    "sg:address":"2144 SW 6th St",
    "sg:city":"Miami",
    "sg:classifiers":[
        {
            "category":"Real Estate",
            "subcategory":"Real Estate Operator",
            "type":"Services"
        }
    ],
    "sg:phone":"+1 305 893 2633",
    "sg:postcode":"33135",
    "sg:province":"FL",
    "sg:tags":[
        "building",
        "apartment"
    ],
    "wof:name":"Wynchwood Apts",
    "wof:placetype":"venue"
},
  "geometry": {"coordinates":[-80.230074,25.767146],"type":"Point"}
}