{
  "type": "Feature",
  "properties": {
    "iso:country":"US",
    "sg:address":"45 NW 5th St",
    "sg:city":"Miami",
    "sg:classifiers":[
        {
            "category":"Professional",
            "subcategory":"Lawyer & Legal Services",
            "type":"Services"
        }
    ],
    "sg:phone":"+1 305 755 9280",
    "sg:postcode":"33128",
    "sg:province":"FL",
    "wof:name":"Public John Q Jr Atty",
    "wof:placetype":"venue"
},
  "geometry": {"coordinates":[-80.19380200000001,25.7789],"type":"Point"}
}