{
  "type": "Feature",
  "properties": {
    "addr:full":"9050 University Pkwy Pensacola FL 32514",
    "addr:housenumber":"9050",
    "addr:postcode":"32514",
    "addr:street":"University Pkwy",
    "iso:country":"US",
    "sg:address":"9050 University Pkwy",
    "sg:city":"Pensacola",
    "sg:classifiers":[
        {
            "category":"Insurance",
            "subcategory":"Insurance Agent",
            "type":"Services"
        }
    ],
    "sg:phone":"+1 850 474 3533",
    "sg:postcode":"32514",
    "sg:province":"FL",
    "sg:website":"www.westernsouthernlife.com",
    "wof:name":"Western-Southern Life Ins Co",
    "wof:placetype":"venue"
},
  "geometry": {"coordinates":[-87.221254,30.532473],"type":"Point"}
}