{
  "type": "Feature",
  "properties": {
    "addr:full":"2100 Barcelona Way S Saint Petersburg FL 33712",
    "addr:housenumber":"2100",
    "addr:postcode":"33712",
    "addr:street":"Barcelona Way S",
    "iso:country":"US",
    "sg:address":"2100 Barcelona Way S",
    "sg:city":"Saint Petersburg",
    "sg:classifiers":[
        {
            "category":"Building & Trades",
            "subcategory":"Construction",
            "type":"Services"
        }
    ],
    "sg:phone":"+1 727 867 2702",
    "sg:postcode":"33712",
    "sg:province":"FL",
    "sg:tags":[
        "contractor"
    ],
    "wof:name":"Monroe  Leighton Drywall Inc",
    "wof:placetype":"venue"
},
  "geometry": {"coordinates":[-82.66341799999999,27.72309],"type":"Point"}
}