{
  "type": "Feature",
  "properties": {
    "addr:full":"6200 Metro Plex Dr Fort Myers FL 33912",
    "addr:postcode":"6200;33912",
    "addr:street":"Metro Plex Dr",
    "iso:country":"US",
    "sg:address":"6200 Metro Plex Dr",
    "sg:city":"Fort Myers",
    "sg:classifiers":[
        {
            "category":"Home & Garden",
            "subcategory":"Building Materials",
            "type":"Retail Goods"
        }
    ],
    "sg:phone":"+1 239 931 3647",
    "sg:postcode":"33912",
    "sg:province":"FL",
    "sg:tags":[
        "shutter"
    ],
    "wof:name":"Shutter Products Intl",
    "wof:placetype":"venue"
},
  "geometry": {"coordinates":[-81.848099,26.575914],"type":"Point"}
}