{
  "type": "Feature",
  "properties": {
    "iso:country":"US",
    "sg:address":"2651 N Point Ct",
    "sg:city":"Tallahassee",
    "sg:classifiers":[
        {
            "category":"Real Estate",
            "subcategory":"Real Estate Operator",
            "type":"Services"
        }
    ],
    "sg:phone":"+1 850 422 3700",
    "sg:postcode":"32308",
    "sg:province":"FL",
    "sg:tags":[
        "apartment"
    ],
    "wof:name":"North Point Apartments",
    "wof:placetype":"venue"
},
  "geometry": {"coordinates":[-84.24276500000001,30.489384],"type":"Point"}
}