{
  "type": "Feature",
  "properties": {
    "iso:country":"US",
    "sg:address":"6365 Evaro Ave",
    "sg:city":"Spring Hill",
    "sg:classifiers":[
        {
            "category":"Shopping",
            "subcategory":"Bicycles & Sporting Goods",
            "type":"Retail Goods"
        }
    ],
    "sg:phone":"+1 352 686 1875",
    "sg:postcode":"34608",
    "sg:province":"FL",
    "sg:tags":[
        "equipment",
        "golf",
        "supply"
    ],
    "wof:name":"Jean's Golf Shop",
    "wof:placetype":"venue"
},
  "geometry": {"coordinates":[-82.55611399999999,28.523387],"type":"Point"}
}