{
  "type": "Feature",
  "properties": {
    "iso:country":"US",
    "sg:address":"2702 Wilson Cir",
    "sg:city":"Lutz",
    "sg:classifiers":[
        {
            "category":"Real Estate",
            "subcategory":"Real Estate Services",
            "type":"Services"
        },
        {
            "category":"Real Estate",
            "subcategory":"Real Estate Agent",
            "type":"Services"
        }
    ],
    "sg:phone":"+1 813 948 4111",
    "sg:postcode":"33548",
    "sg:province":"FL",
    "sg:tags":[
        "management"
    ],
    "wof:name":"L G Land Cattle & Timber Co Inc",
    "wof:placetype":"venue"
},
  "geometry": {"coordinates":[-82.492734,28.144382],"type":"Point"}
}