{
  "type": "Feature",
  "properties": {
    "addr:full":"10823 Tamiami Trl N Naples FL 34108",
    "addr:housenumber":"10823",
    "addr:postcode":"34108",
    "addr:street":"Tamiami Trl N",
    "iso:country":"US",
    "sg:address":"10823 Tamiami Trl N",
    "sg:city":"Naples",
    "sg:classifiers":[
        {
            "category":"Personal",
            "subcategory":"Beauty Salon",
            "type":"Services"
        }
    ],
    "sg:phone":"+1 239 596 0042",
    "sg:postcode":"34108",
    "sg:province":"FL",
    "sg:tags":[
        "shop",
        "manicuring"
    ],
    "wof:name":"Natural Nails",
    "wof:placetype":"venue"
},
  "geometry": {"coordinates":[-81.801669,26.270387],"type":"Point"}
}