{
  "type": "Feature",
  "properties": {
    "addr:full":"6901 Bee Ridge Rd Sarasota FL 34241",
    "addr:housenumber":"6901",
    "addr:postcode":"34241",
    "addr:street":"Bee Ridge Rd",
    "iso:country":"US",
    "sg:address":"6901 Bee Ridge Rd",
    "sg:city":"Sarasota",
    "sg:classifiers":[
        {
            "category":"Organizations",
            "subcategory":"Religious Organization",
            "type":"Services"
        }
    ],
    "sg:phone":"+1 941 371 3071",
    "sg:postcode":"34241",
    "sg:province":"FL",
    "sg:tags":[
        "church"
    ],
    "sg:website":"www.faithbaptistsarasota.com",
    "wof:name":"Faith Baptist Church",
    "wof:placetype":"venue"
},
  "geometry": {"coordinates":[-82.43473,27.298713],"type":"Point"}
}