{
  "type": "Feature",
  "properties": {
    "iso:country":"US",
    "sg:address":"221 SW 2nd Ave",
    "sg:city":"Fort Lauderdale",
    "sg:classifiers":[
        {
            "category":"Real Estate",
            "subcategory":"Architect",
            "type":"Services"
        }
    ],
    "sg:phone":"+1 954 728 9690",
    "sg:postcode":"33301",
    "sg:province":"FL",
    "wof:name":"American Institute-Architects",
    "wof:placetype":"venue"
},
  "geometry": {"coordinates":[-80.14570000000001,26.119601],"type":"Point"}
}