{
  "type": "Feature",
  "properties": {
    "addr:full":"4604 8th Ave E Bradenton FL 34208",
    "addr:housenumber":"4604",
    "addr:postcode":"34208",
    "addr:street":"8Th Ave E",
    "iso:country":"US",
    "sg:address":"4604 8th Ave E",
    "sg:city":"Bradenton",
    "sg:classifiers":[
        {
            "category":"Personal",
            "subcategory":"Beauty Salon",
            "type":"Services"
        }
    ],
    "sg:phone":"+1 941 758 1444",
    "sg:postcode":"34208",
    "sg:province":"FL",
    "wof:name":"Mane Tamers-A Hair Emporium",
    "wof:placetype":"venue"
},
  "geometry": {"coordinates":[-82.502392,27.491431],"type":"Point"}
}