{
  "type": "Feature",
  "properties": {
    "addr:full":"710 Corbin Park Rd New Smyrna Beach FL 32168",
    "addr:housenumber":"710",
    "addr:postcode":"32168",
    "addr:street":"Corbin Park Rd",
    "iso:country":"US",
    "sg:address":"710 Corbin Park Rd",
    "sg:city":"New Smyrna Beach",
    "sg:classifiers":[
        {
            "category":"Freight",
            "type":"Transportation"
        }
    ],
    "sg:phone":"+1 386 423 5438",
    "sg:postcode":"32168",
    "sg:province":"FL",
    "sg:tags":[
        "mover"
    ],
    "wof:name":"Diggs Moving Svc",
    "wof:placetype":"venue"
},
  "geometry": {"coordinates":[-80.951916,29.007116],"type":"Point"}
}