{
  "type": "Feature",
  "properties": {
    "iso:country":"US",
    "sg:address":"6372 Goodway Dr",
    "sg:city":"Brooksville",
    "sg:classifiers":[
        {
            "category":"Animal Shelter",
            "type":"Public Place"
        },
        {
            "category":"Retail",
            "subcategory":"Pet Boarding",
            "type":"Services"
        },
        {
            "category":"Retail",
            "subcategory":"Animal Services",
            "type":"Services"
        }
    ],
    "sg:phone":"+1 352 345 8025",
    "sg:postcode":"34602",
    "sg:province":"FL",
    "sg:tags":[
        "grooming",
        "kennel"
    ],
    "sg:website":"http://panaceapetresort.com",
    "wof:name":"Panacea Pet Resort",
    "wof:placetype":"venue"
},
  "geometry": {"coordinates":[-82.27173500000001,28.526543],"type":"Point"}
}