{
  "type": "Feature",
  "properties": {
    "iso:country":"US",
    "sg:address":"5610 Blanding Blvd",
    "sg:city":"Jacksonville",
    "sg:classifiers":[
        {
            "category":"Retail",
            "subcategory":"Veterinary Services",
            "type":"Services"
        }
    ],
    "sg:phone":"+1 904 771 6024",
    "sg:postcode":"32244",
    "sg:province":"FL",
    "sg:tags":[
        "veterinarian",
        "specialty"
    ],
    "wof:name":"Martin Dan D.V.M.",
    "wof:placetype":"venue"
},
  "geometry": {"coordinates":[-81.743111,30.246571],"type":"Point"}
}