{
  "type": "Feature",
  "properties": {
    "iso:country":"US",
    "sg:address":"121 Center St",
    "sg:city":"Jupiter",
    "sg:classifiers":[
        {
            "category":"Restaurant",
            "type":"Food & Drink"
        }
    ],
    "sg:phone":"+1 561 746 2344",
    "sg:postcode":"33458",
    "sg:province":"FL",
    "sg:tags":[
        "eating"
    ],
    "wof:name":"Connection For Subs Sandwiches",
    "wof:placetype":"venue"
},
  "geometry": {"coordinates":[-80.094325,26.94154],"type":"Point"}
}