{
  "type": "Feature",
  "properties": {
    "iso:country":"US",
    "sg:address":"600 E Zack St",
    "sg:city":"Tampa",
    "sg:classifiers":[
        {
            "category":"Building & Trades",
            "subcategory":"Construction",
            "type":"Services"
        }
    ],
    "sg:phone":"+1 813 229 7000",
    "sg:postcode":"33602",
    "sg:province":"FL",
    "sg:tags":[
        "system",
        "specialty",
        "heating",
        "contractor",
        "air conditioning"
    ],
    "wof:name":"Mcmullen Ac Refrigeration Serv",
    "wof:placetype":"venue"
},
  "geometry": {"coordinates":[-82.456367,27.950809],"type":"Point"}
}