{
  "type": "Feature",
  "properties": {
    "addr:full":"1855 Dundee Rd Winter Haven FL 33884",
    "addr:housenumber":"1855",
    "addr:postcode":"33884",
    "addr:street":"Dundee Rd",
    "iso:country":"US",
    "sg:address":"1855 Dundee Rd",
    "sg:city":"Winter Haven",
    "sg:classifiers":[
        {
            "category":"Building & Trades",
            "subcategory":"Pest Control",
            "type":"Services"
        }
    ],
    "sg:phone":"+1 863 678 0224",
    "sg:postcode":"33884",
    "sg:province":"FL",
    "wof:name":"Middleton Lawn & Pest Control",
    "wof:placetype":"venue"
},
  "geometry": {"coordinates":[-81.695899,28.02256],"type":"Point"}
}