{
  "type": "Feature",
  "properties": {
    "addr:full":"1010 SW Lighthouse Dr Palm City FL 34990",
    "addr:housenumber":"1010",
    "addr:postcode":"34990",
    "addr:street":"Sw Lighthouse Dr",
    "iso:country":"US",
    "sg:address":"1010 SW Lighthouse Dr",
    "sg:city":"Palm City",
    "sg:classifiers":[
        {
            "category":"Manufacturing",
            "subcategory":"Printing",
            "type":"Manufacturing & Wholesale Goods"
        }
    ],
    "sg:phone":"+1 772 288 0387",
    "sg:postcode":"34990",
    "sg:province":"FL",
    "sg:tags":[
        "publisher"
    ],
    "wof:name":"T L Enterprises Inc",
    "wof:placetype":"venue"
},
  "geometry": {"coordinates":[-80.276101,27.190775],"type":"Point"}
}