{
  "type": "Feature",
  "properties": {
    "addr:full":"10801 Corkscrew Rd Estero FL 33928",
    "addr:housenumber":"10801",
    "addr:postcode":"33928",
    "addr:street":"Corkscrew Rd",
    "iso:country":"US",
    "sg:address":"10801 Corkscrew Rd",
    "sg:city":"Estero",
    "sg:classifiers":[
        {
            "category":"Shopping",
            "subcategory":"Jewelry",
            "type":"Retail Goods"
        }
    ],
    "sg:phone":"+1 239 947 1982",
    "sg:postcode":"33928",
    "sg:province":"FL",
    "sg:tags":[
        "watch"
    ],
    "wof:name":"Time Factory Watch Outlet",
    "wof:placetype":"venue"
},
  "geometry": {"coordinates":[-81.80503299999999,26.431274],"type":"Point"}
}