{
  "type": "Feature",
  "properties": {
    "addr:full":"4833 Okeechobee Rd West Palm Beach FL 33417",
    "addr:housenumber":"4833",
    "addr:postcode":"33417",
    "addr:street":"Okeechobee Rd",
    "iso:country":"US",
    "sg:address":"4833 Okeechobee Rd",
    "sg:city":"West Palm Beach",
    "sg:classifiers":[
        {
            "category":"Shopping",
            "subcategory":"Gifts & Souvenirs",
            "type":"Retail Goods"
        }
    ],
    "sg:phone":"+1 561 683 3004",
    "sg:postcode":"33417",
    "sg:province":"FL",
    "sg:tags":[
        "party",
        "supply"
    ],
    "wof:name":"Party Outlet North Inc",
    "wof:placetype":"venue"
},
  "geometry": {"coordinates":[-80.115268,26.706995],"type":"Point"}
}