{
  "type": "Feature",
  "properties": {
    "addr:full":"1685 State Rd 62 Bowling Green FL 33834",
    "addr:housenumber":"1685;62",
    "addr:postcode":"33834",
    "addr:street":"State Rd;Green",
    "iso:country":"US",
    "sg:address":"1685 State Rd 62",
    "sg:city":"Bowling Green",
    "sg:classifiers":[
        {
            "category":"Farming",
            "subcategory":"Orchard",
            "type":"Manufacturing & Wholesale Goods"
        }
    ],
    "sg:phone":"+1 863 773 9131",
    "sg:postcode":"33834",
    "sg:province":"FL",
    "sg:tags":[
        "citrus",
        "grove",
        "fruit"
    ],
    "wof:name":"Bryant Minor",
    "wof:placetype":"venue"
},
  "geometry": {"coordinates":[-81.85884799999999,27.594728],"type":"Point"}
}