{
  "type": "Feature",
  "properties": {
    "iso:country":"US",
    "sg:address":"392 Flagler Ave",
    "sg:city":"New Smyrna Beach",
    "sg:classifiers":[
        {
            "category":"Bars & Pubs",
            "type":"Food & Drink"
        }
    ],
    "sg:phone":"+1 386 423 9111",
    "sg:postcode":"32169",
    "sg:province":"FL",
    "wof:name":"Echochamber",
    "wof:placetype":"venue"
},
  "geometry": {"coordinates":[-80.900604,29.038624],"type":"Point"}
}