{
  "type": "Feature",
  "properties": {
    "addr:full":"25715 State Hwy 46 Sorrento FL 32776",
    "addr:housenumber":"25715",
    "addr:postcode":"32776",
    "addr:street":"State Hwy 46",
    "iso:country":"US",
    "sg:address":"25715 State Hwy 46",
    "sg:city":"Sorrento",
    "sg:classifiers":[
        {
            "category":"Real Estate",
            "subcategory":"Real Estate Agent",
            "type":"Services"
        }
    ],
    "sg:phone":"+1 352 383 3772",
    "sg:postcode":"32776",
    "sg:province":"FL",
    "sg:website":"www.catherinehanson.com",
    "wof:name":"Catherine Hanson Real Estate",
    "wof:placetype":"venue"
},
  "geometry": {"coordinates":[-81.530828,28.809926],"type":"Point"}
}