{
  "type": "Feature",
  "properties": {
    "addr:full":"900 Park Ave Orange Park FL 32073",
    "addr:housenumber":"900",
    "addr:postcode":"32073",
    "addr:street":"Park Ave",
    "iso:country":"US",
    "sg:address":"900 Park Ave",
    "sg:city":"Orange Park",
    "sg:classifiers":[
        {
            "category":"Social Services",
            "subcategory":"Child Care",
            "type":"Services"
        }
    ],
    "sg:phone":"+1 904 264 1118",
    "sg:postcode":"32073",
    "sg:province":"FL",
    "sg:tags":[
        "kindergarten",
        "academic",
        "school"
    ],
    "sg:website":"www.ivbc.org",
    "wof:name":"Island View Baptist Child Care",
    "wof:placetype":"venue"
},
  "geometry": {"coordinates":[-81.701725,30.177834],"type":"Point"}
}