{
  "type": "Feature",
  "properties": {
    "addr:full":"6418 NW 113th Pl Miami FL 33178",
    "addr:housenumber":"6418",
    "addr:postcode":"33178",
    "addr:street":"Nw 113Th Pl",
    "iso:country":"US",
    "sg:address":"6418 NW 113th Pl",
    "sg:city":"Miami",
    "sg:classifiers":[
        {
            "category":"Shopping",
            "subcategory":"Bicycles & Sporting Goods",
            "type":"Retail Goods"
        }
    ],
    "sg:phone":"+1 305 591 7693",
    "sg:postcode":"33178",
    "sg:province":"FL",
    "wof:name":"Ferez Industries Maker Cham",
    "wof:placetype":"venue"
},
  "geometry": {"coordinates":[-80.38185799999999,25.829573],"type":"Point"}
}