{
  "type": "Feature",
  "properties": {
    "addr:full":"6821 Southpoint Dr N Jacksonville FL 32216",
    "addr:housenumber":"6821",
    "addr:postcode":"32216",
    "addr:street":"Southpoint Dr N",
    "iso:country":"US",
    "sg:address":"6821 Southpoint Dr N",
    "sg:city":"Jacksonville",
    "sg:classifiers":[
        {
            "category":"Banks & Credit Unions",
            "subcategory":"Bank",
            "type":"Services"
        }
    ],
    "sg:phone":"+1 904 332 0601",
    "sg:postcode":"32216",
    "sg:province":"FL",
    "sg:tags":[
        "loan",
        "mortgage",
        "real estate"
    ],
    "wof:name":"Professional Mortgage Assoc",
    "wof:placetype":"venue"
},
  "geometry": {"coordinates":[-81.58667,30.256639],"type":"Point"}
}