{
  "type": "Feature",
  "properties": {
    "addr:full":"3010 SW 103rd Ct Miami FL 33165",
    "addr:housenumber":"3010",
    "addr:postcode":"33165",
    "addr:street":"Sw 103Rd Ct",
    "iso:country":"US",
    "sg:address":"3010 SW 103rd Ct",
    "sg:city":"Miami",
    "sg:classifiers":[
        {
            "category":"Professional",
            "subcategory":"Accounting & Tax Preparation",
            "type":"Services"
        }
    ],
    "sg:phone":"+1 305 559 8163",
    "sg:postcode":"33165",
    "sg:province":"FL",
    "sg:tags":[
        "billing"
    ],
    "wof:name":"Luna Billing",
    "wof:placetype":"venue"
},
  "geometry": {"coordinates":[-80.36241099999999,25.739847],"type":"Point"}
}