{
  "type": "Feature",
  "properties": {
    "iso:country":"US",
    "sg:address":"8010 N Atlantic Ave Ste 2",
    "sg:city":"Cpe Canaveral",
    "sg:classifiers":[
        {
            "category":"Personal",
            "subcategory":"Beauty Salon",
            "type":"Services"
        }
    ],
    "sg:phone":"+1 321 866 0000",
    "sg:postcode":"32920",
    "sg:province":"FL",
    "sg:tags":[
        "hair"
    ],
    "wof:name":"Applause Hair Studio",
    "wof:placetype":"venue"
},
  "geometry": {"coordinates":[-80.60553299999999,28.388934],"type":"Point"}
}