{
  "type": "Feature",
  "properties": {
    "addr:full":"14190 SW 24th St Fort Lauderdale FL 33325",
    "addr:housenumber":"14190",
    "addr:postcode":"33325",
    "addr:street":"Sw 24Th St",
    "iso:country":"US",
    "sg:address":"14190 SW 24th St",
    "sg:city":"Fort Lauderdale",
    "sg:classifiers":[
        {
            "category":"Building & Trades",
            "subcategory":"Construction",
            "type":"Services"
        }
    ],
    "sg:phone":"+1 954 585 4802",
    "sg:postcode":"33325",
    "sg:province":"FL",
    "sg:tags":[
        "house"
    ],
    "wof:name":"Infinity Construction Corp",
    "wof:placetype":"venue"
},
  "geometry": {"coordinates":[-80.334384,26.089402],"type":"Point"}
}