{
  "type": "Feature",
  "properties": {
    "iso:country":"US",
    "sg:address":"13066 SW 132nd Ct",
    "sg:city":"Miami",
    "sg:classifiers":[
        {
            "category":"Professional",
            "subcategory":"Testing Lab",
            "type":"Services"
        }
    ],
    "sg:phone":"+1 305 255 8700",
    "sg:postcode":"33186",
    "sg:province":"FL",
    "sg:tags":[
        "radon",
        "mitigation",
        "g",
        "measurement"
    ],
    "wof:name":"Radon Environmental Testing",
    "wof:placetype":"venue"
},
  "geometry": {"coordinates":[-80.408331,25.648267],"type":"Point"}
}