{
  "type": "Feature",
  "properties": {
    "addr:full":"1615 S Federal Hwy Boca Raton FL 33432",
    "addr:housenumber":"1615",
    "addr:postcode":"33432",
    "addr:street":"S Federal Hwy",
    "iso:country":"US",
    "sg:address":"1615 S Federal Hwy",
    "sg:city":"Boca Raton",
    "sg:classifiers":[
        {
            "category":"Real Estate",
            "subcategory":"Real Estate Agent",
            "type":"Services"
        },
        {
            "category":"Professional",
            "subcategory":"Management & Consulting",
            "type":"Services"
        }
    ],
    "sg:phone":"+1 561 392 7678",
    "sg:postcode":"33432",
    "sg:province":"FL",
    "sg:tags":[
        "investment"
    ],
    "wof:name":"Atlantic Development & Mgmt",
    "wof:placetype":"venue"
},
  "geometry": {"coordinates":[-80.08866999999999,26.334867],"type":"Point"}
}