{
  "type": "Feature",
  "properties": {
    "iso:country":"US",
    "sg:address":"3118 Gulf To Bay Blvd",
    "sg:city":"Clearwater",
    "sg:classifiers":[
        {
            "category":"Restaurant",
            "type":"Food & Drink"
        }
    ],
    "sg:phone":"+1 727 724 8292",
    "sg:postcode":"33759",
    "sg:province":"FL",
    "sg:tags":[
        "eating"
    ],
    "wof:name":"Subway",
    "wof:placetype":"venue"
},
  "geometry": {"coordinates":[-82.710826,27.960683],"type":"Point"}
}