{
  "type": "Feature",
  "properties": {
    "addr:full":"1245 NE 144th St Miami FL 33161",
    "addr:housenumber":"1245",
    "addr:postcode":"33161",
    "addr:street":"Ne 144Th St",
    "iso:country":"US",
    "sg:address":"1245 NE 144th St",
    "sg:city":"Miami",
    "sg:classifiers":[
        {
            "category":"Health Services",
            "subcategory":"Clinic",
            "type":"Services"
        }
    ],
    "sg:phone":"+1 305 956 3800",
    "sg:postcode":"33161",
    "sg:province":"FL",
    "wof:name":"Health Administrative Svc",
    "wof:placetype":"venue"
},
  "geometry": {"coordinates":[-80.171992,25.908248],"type":"Point"}
}