{
  "type": "Feature",
  "properties": {
    "iso:country":"US",
    "sg:address":"17734 Pine Needle Ter",
    "sg:city":"Boca Raton",
    "sg:classifiers":[
        {
            "category":"Manufacturing",
            "subcategory":"Toys & Sporting Goods",
            "type":"Manufacturing & Wholesale Goods"
        }
    ],
    "sg:phone":"+1 561 994 4750",
    "sg:postcode":"33487",
    "sg:province":"FL",
    "sg:tags":[
        "mfg"
    ],
    "wof:name":"Silvermarc Marketing Corp",
    "wof:placetype":"venue"
},
  "geometry": {"coordinates":[-80.115595,26.413646],"type":"Point"}
}