{
  "type": "Feature",
  "properties": {
    "addr:full":"52 W Broadway St Oviedo FL 32765",
    "addr:housenumber":"52",
    "addr:postcode":"32765",
    "addr:street":"W Broadway St",
    "iso:country":"US",
    "sg:address":"52 W Broadway St",
    "sg:city":"Oviedo",
    "sg:classifiers":[
        {
            "category":"Shopping",
            "type":"Retail Goods"
        }
    ],
    "sg:phone":"+1 407 359 5010",
    "sg:postcode":"32765",
    "sg:province":"FL",
    "sg:tags":[
        "candle"
    ],
    "wof:name":"Flickering Lights",
    "wof:placetype":"venue"
},
  "geometry": {"coordinates":[-81.21049600000001,28.670278],"type":"Point"}
}