{
  "type": "Feature",
  "properties": {
    "iso:country":"US",
    "sg:address":"24445 Rampart Blvd",
    "sg:city":"Punta Gorda",
    "sg:classifiers":[
        {
            "category":"Organizations",
            "subcategory":"Religious Organization",
            "type":"Services"
        }
    ],
    "sg:phone":"+1 941 624 3799",
    "sg:postcode":"33980",
    "sg:province":"FL",
    "sg:tags":[
        "church"
    ],
    "sg:website":"www.sanantoniocatholicchurch.com",
    "wof:name":"San Antonio Catholic Church",
    "wof:placetype":"venue"
},
  "geometry": {"coordinates":[-82.04057899999999,27.00258],"type":"Point"}
}