{
  "type": "Feature",
  "properties": {
    "iso:country":"US",
    "sg:address":"5100 Doug Taylor Cir",
    "sg:city":"St James City",
    "sg:classifiers":[
        {
            "category":"Retail",
            "subcategory":"Veterinary Services",
            "type":"Services"
        }
    ],
    "sg:phone":"+1 239 283 1244",
    "sg:postcode":"33956",
    "sg:province":"FL",
    "sg:tags":[
        "hospital",
        "animal"
    ],
    "wof:name":"Pine Island Animal Clinic Inc",
    "wof:placetype":"venue"
},
  "geometry": {"coordinates":[-82.114349,26.607715],"type":"Point"}
}