{
  "type": "Feature",
  "properties": {
    "addr:full":"3531 W Waters Ave Tampa FL 33614",
    "addr:housenumber":"3531",
    "addr:postcode":"33614",
    "addr:street":"W Waters Ave",
    "iso:country":"US",
    "sg:address":"3531 W Waters Ave",
    "sg:city":"Tampa",
    "sg:classifiers":[
        {
            "category":"Banks & Credit Unions",
            "subcategory":"Bank",
            "type":"Services"
        }
    ],
    "sg:phone":"+1 813 935 4645",
    "sg:postcode":"33614",
    "sg:province":"FL",
    "sg:tags":[
        "cashing",
        "check"
    ],
    "wof:name":"Checkpoint",
    "wof:placetype":"venue"
},
  "geometry": {"coordinates":[-82.499137,28.025537],"type":"Point"}
}