{
  "type": "Feature",
  "properties": {
    "iso:country":"US",
    "sg:address":"715 N Washington Blvd",
    "sg:city":"Sarasota",
    "sg:classifiers":[
        {
            "category":"Insurance",
            "subcategory":"Insurance Agent",
            "type":"Services"
        }
    ],
    "sg:phone":"+1 941 366 4500",
    "sg:postcode":"34236",
    "sg:province":"FL",
    "wof:name":"All American Insurance",
    "wof:placetype":"venue"
},
  "geometry": {"coordinates":[-82.531057,27.342877],"type":"Point"}
}