{
  "type": "Feature",
  "properties": {
    "addr:full":"1900 Clifford St Fort Myers FL 33901",
    "addr:housenumber":"1900",
    "addr:postcode":"33901",
    "addr:street":"Clifford St",
    "iso:country":"US",
    "sg:address":"1900 Clifford St",
    "sg:city":"Fort Myers",
    "sg:classifiers":[
        {
            "category":"Real Estate",
            "subcategory":"Real Estate Operator",
            "type":"Services"
        }
    ],
    "sg:phone":"+1 239 334 2848",
    "sg:postcode":"33901",
    "sg:province":"FL",
    "sg:tags":[
        "apartment"
    ],
    "wof:name":"Riverside Club",
    "wof:placetype":"venue"
},
  "geometry": {"coordinates":[-81.877269,26.639091],"type":"Point"}
}