{
  "type": "Feature",
  "properties": {
    "addr:full":"5527 23rd St E Bradenton FL 34203",
    "addr:housenumber":"5527",
    "addr:postcode":"34203",
    "addr:street":"23Rd St",
    "iso:country":"US",
    "sg:address":"5527 23rd St E",
    "sg:city":"Bradenton",
    "sg:classifiers":[
        {
            "category":"Wholesale",
            "subcategory":"Machinery & Supplies",
            "type":"Manufacturing & Wholesale Goods"
        }
    ],
    "sg:phone":"+1 941 751 4369",
    "sg:postcode":"34203",
    "sg:province":"FL",
    "sg:tags":[
        "crane",
        "derrick"
    ],
    "wof:name":"D C Crane Co",
    "wof:placetype":"venue"
},
  "geometry": {"coordinates":[-82.535087,27.442159],"type":"Point"}
}