{
  "type": "Feature",
  "properties": {
    "addr:full":"18440 Paulson Dr Port Charlotte FL 33954",
    "addr:housenumber":"18440",
    "addr:postcode":"33954",
    "addr:street":"Paulson Dr",
    "iso:country":"US",
    "sg:address":"18440 Paulson Dr",
    "sg:city":"Port Charlotte",
    "sg:classifiers":[
        {
            "category":"Wholesale",
            "subcategory":"Construction Materials",
            "type":"Manufacturing & Wholesale Goods"
        }
    ],
    "sg:phone":"+1 941 624 5958",
    "sg:postcode":"33954",
    "sg:province":"FL",
    "sg:tags":[
        "marble"
    ],
    "wof:name":"American Marble",
    "wof:placetype":"venue"
},
  "geometry": {"coordinates":[-82.14597999999999,27.016709],"type":"Point"}
}