{
  "type": "Feature",
  "properties": {
    "addr:full":"1551 Lambert Ave Flagler Beach FL 32136",
    "addr:housenumber":"1551",
    "addr:postcode":"32136",
    "addr:street":"Lambert Ave",
    "iso:country":"US",
    "sg:address":"1551 Lambert Ave",
    "sg:city":"Flagler Beach",
    "sg:classifiers":[
        {
            "category":"Shopping",
            "type":"Retail Goods"
        }
    ],
    "sg:phone":"+1 386 439 6307",
    "sg:postcode":"32136",
    "sg:province":"FL",
    "sg:tags":[
        "art",
        "gallery",
        "dealer"
    ],
    "wof:name":"Ingenhag Gallery",
    "wof:placetype":"venue"
},
  "geometry": {"coordinates":[-81.14443199999999,29.495628],"type":"Point"}
}