{
  "type": "Feature",
  "properties": {
    "addr:full":"12 Stone St Cocoa FL 32922",
    "addr:housenumber":"12",
    "addr:postcode":"32922",
    "addr:street":"Stone St",
    "iso:country":"US",
    "sg:address":"12 Stone St",
    "sg:city":"Cocoa",
    "sg:classifiers":[
        {
            "category":"Professional",
            "subcategory":"Lawyer & Legal Services",
            "type":"Services"
        }
    ],
    "sg:phone":"+1 321 636 2858",
    "sg:postcode":"32922",
    "sg:province":"FL",
    "sg:tags":[
        "attorney",
        "law",
        "disability",
        "security",
        "social"
    ],
    "wof:name":"Smith, Kathleen A",
    "wof:placetype":"venue"
},
  "geometry": {"coordinates":[-80.72675599999999,28.3547],"type":"Point"}
}