{
  "type": "Feature",
  "properties": {
    "addr:full":"3155 NW 82nd Ave Miami FL 33122",
    "addr:housenumber":"3155",
    "addr:postcode":"33122",
    "addr:street":"Nw 82Nd Ave",
    "iso:country":"US",
    "sg:address":"3155 NW 82nd Ave",
    "sg:city":"Miami",
    "sg:classifiers":[
        {
            "category":"Shopping",
            "subcategory":"Catalog Store",
            "type":"Retail Goods"
        }
    ],
    "sg:phone":"+1 305 222 1677",
    "sg:postcode":"33122",
    "sg:province":"FL",
    "sg:tags":[
        "discount",
        "medical",
        "card",
        "for"
    ],
    "wof:name":"Medmore",
    "wof:placetype":"venue"
},
  "geometry": {"coordinates":[-80.329059,25.802188],"type":"Point"}
}