{
  "type": "Feature",
  "properties": {
    "iso:country":"US",
    "sg:address":"712 Edgewood Ave N",
    "sg:city":"Jacksonville",
    "sg:classifiers":[
        {
            "category":"Personal",
            "subcategory":"Beauty Salon",
            "type":"Services"
        }
    ],
    "sg:phone":"+1 904 384 7746",
    "sg:postcode":"32254",
    "sg:province":"FL",
    "sg:tags":[
        "manicuring"
    ],
    "wof:name":"Nail Palace",
    "wof:placetype":"venue"
},
  "geometry": {"coordinates":[-81.731072,30.332389],"type":"Point"}
}