{
  "type": "Feature",
  "properties": {
    "iso:country":"US",
    "sg:address":"10320 Riverburn Dr",
    "sg:city":"Tampa",
    "sg:phone":"+1 813 651 5400",
    "sg:postcode":"33647",
    "sg:province":"FL",
    "sg:tags":[
        "product",
        "material",
        "petroleum"
    ],
    "wof:name":"Lanigan Performance Products",
    "wof:placetype":"venue"
},
  "geometry": {"coordinates":[-82.321027,28.146575],"type":"Point"}
}