{
  "type": "Feature",
  "properties": {
    "iso:country":"US",
    "sg:address":"5441 Jenkins Loop Dr",
    "sg:city":"Keystone Heights",
    "sg:classifiers":[
        {
            "category":"Building & Trades",
            "subcategory":"Construction",
            "type":"Services"
        }
    ],
    "sg:phone":"+1 352 473 9557",
    "sg:postcode":"32656",
    "sg:province":"FL",
    "sg:tags":[
        "layer",
        "carpet"
    ],
    "wof:name":"Daniel Shepherd",
    "wof:placetype":"venue"
},
  "geometry": {"coordinates":[-81.898203,29.820078],"type":"Point"}
}