{
  "type": "Feature",
  "properties": {
    "addr:full":"8100 SW 117th Ave Miami FL 33183",
    "addr:housenumber":"8100",
    "addr:postcode":"33183",
    "addr:street":"Sw 117Th Ave",
    "iso:country":"US",
    "sg:address":"8100 SW 117th Ave",
    "sg:city":"Miami",
    "sg:classifiers":[
        {
            "category":"Organizations",
            "subcategory":"Religious Organization",
            "type":"Services"
        }
    ],
    "sg:phone":"+1 305 275 0097",
    "sg:postcode":"33183",
    "sg:province":"FL",
    "wof:name":"General Conference of S D A",
    "wof:placetype":"venue"
},
  "geometry": {"coordinates":[-80.382738,25.692364],"type":"Point"}
}