{
  "type": "Feature",
  "properties": {
    "addr:full":"795 US Hwy 98 Destin FL 32541",
    "addr:housenumber":"795",
    "addr:postcode":"32541",
    "addr:street":"Us Hwy 98",
    "iso:country":"US",
    "sg:address":"795 US Hwy 98",
    "sg:city":"Destin",
    "sg:classifiers":[
        {
            "category":"Food & Beverages",
            "subcategory":"Bakery",
            "type":"Retail Goods"
        }
    ],
    "sg:phone":"+1 850 650 3552",
    "sg:postcode":"32541",
    "sg:province":"FL",
    "wof:name":"Krispy Kreme",
    "wof:placetype":"venue"
},
  "geometry": {"coordinates":[-86.49029899999999,30.390981],"type":"Point"}
}