{
  "type": "Feature",
  "properties": {
    "iso:country":"US",
    "sg:address":"3315 E Venice Ave",
    "sg:city":"Venice",
    "sg:classifiers":[
        {
            "category":"Building & Trades",
            "subcategory":"Electrical",
            "type":"Services"
        }
    ],
    "sg:phone":"+1 941 488 1654",
    "sg:postcode":"34292",
    "sg:province":"FL",
    "sg:tags":[
        "on",
        "contractor",
        "site",
        "electric"
    ],
    "wof:name":"Bob's Electric",
    "wof:placetype":"venue"
},
  "geometry": {"coordinates":[-82.358554,27.099148],"type":"Point"}
}