{
  "type": "Feature",
  "properties": {
    "addr:full":"1677 SW 107 Ave Miami FL 33165",
    "addr:housenumber":"1677",
    "addr:postcode":"33165",
    "addr:street":"Sw 107 Ave",
    "iso:country":"US",
    "sg:address":"1677 SW 107 Ave",
    "sg:city":"Miami",
    "sg:classifiers":[
        {
            "category":"Food & Beverages",
            "subcategory":"Specialty",
            "type":"Retail Goods"
        }
    ],
    "sg:phone":"+1 305 223 7260",
    "sg:postcode":"33165",
    "sg:province":"FL",
    "wof:name":"El Rey De Las Fritas",
    "wof:placetype":"venue"
},
  "geometry": {"coordinates":[-80.36793299999999,25.752638],"type":"Point"}
}