{
  "type": "Feature",
  "properties": {
    "iso:country":"US",
    "sg:address":"730 Westwood Beach Cir",
    "sg:city":"Panama City Bch",
    "sg:classifiers":[
        {
            "category":"Retail",
            "subcategory":"Repair Shop",
            "type":"Services"
        }
    ],
    "sg:phone":"+1 850 234 6044",
    "sg:postcode":"32413",
    "sg:province":"FL",
    "sg:tags":[
        "bathtub",
        "sink",
        "refinishing"
    ],
    "wof:name":"Perfect Touch Resurfacing",
    "wof:placetype":"venue"
},
  "geometry": {"coordinates":[-85.958364,30.264462],"type":"Point"}
}