{
  "type": "Feature",
  "properties": {
    "iso:country":"US",
    "sg:address":"1210 Lafayette St",
    "sg:city":"Cape Coral",
    "sg:classifiers":[
        {
            "category":"Shopping",
            "subcategory":"Hobbies, Toys, & Games",
            "type":"Retail Goods"
        }
    ],
    "sg:phone":"+1 239 542 3363",
    "sg:postcode":"33904",
    "sg:province":"FL",
    "sg:tags":[
        "model",
        "supply"
    ],
    "wof:name":"A & J Models",
    "wof:placetype":"venue"
},
  "geometry": {"coordinates":[-81.94574900000001,26.561572],"type":"Point"}
}