{
  "type": "Feature",
  "properties": {
    "iso:country":"US",
    "sg:address":"14821 US Hwy 19",
    "sg:city":"Hudson",
    "sg:classifiers":[
        {
            "category":"Autos & Motor Vehicles",
            "subcategory":"Auto Supplies",
            "type":"Retail Goods"
        }
    ],
    "sg:phone":"+1 727 863 0424",
    "sg:postcode":"34667",
    "sg:province":"FL",
    "sg:tags":[
        "equipment",
        "repair",
        "electric",
        "automotive",
        "automobile"
    ],
    "wof:name":"West Side Auto Electrical Rbld",
    "wof:placetype":"venue"
},
  "geometry": {"coordinates":[-82.685182,28.372738],"type":"Point"}
}