{
  "type": "Feature",
  "properties": {
    "iso:country":"US",
    "sg:address":"3101 W Broward Blvd",
    "sg:city":"Fort Lauderdale",
    "sg:classifiers":[
        {
            "category":"Food & Beverages",
            "subcategory":"Liquor & Beverages",
            "type":"Retail Goods"
        }
    ],
    "sg:phone":"+1 954 581 6864",
    "sg:postcode":"33312",
    "sg:province":"FL",
    "sg:tags":[
        "depository",
        "banking",
        "alcoholic"
    ],
    "wof:name":"Flamingo Liqours",
    "wof:placetype":"venue"
},
  "geometry": {"coordinates":[-80.187607,26.121221],"type":"Point"}
}