{
  "type": "Feature",
  "properties": {
    "iso:country":"US",
    "sg:address":"1285 SW 101st Way",
    "sg:city":"Pembroke Pines",
    "sg:classifiers":[
        {
            "category":"Professional",
            "subcategory":"Management & Consulting",
            "type":"Services"
        }
    ],
    "sg:phone":"+1 954 295 9333",
    "sg:postcode":"33025",
    "sg:province":"FL",
    "sg:tags":[
        "consultant",
        "safety"
    ],
    "wof:name":"Dr Safety",
    "wof:placetype":"venue"
},
  "geometry": {"coordinates":[-80.281476,25.996992],"type":"Point"}
}