{
  "type": "Feature",
  "properties": {
    "iso:country":"US",
    "sg:address":"412 E Kennedy Blvd",
    "sg:city":"Maitland",
    "sg:classifiers":[
        {
            "category":"Social Services",
            "subcategory":"Child Care",
            "type":"Services"
        }
    ],
    "sg:phone":"+1 407 644 1270",
    "sg:postcode":"32751",
    "sg:province":"FL",
    "sg:tags":[
        "start",
        "head",
        "center"
    ],
    "wof:name":"Eatonville Head Start Center",
    "wof:placetype":"venue"
},
  "geometry": {"coordinates":[-81.377925,28.618433],"type":"Point"}
}