{
  "type": "Feature",
  "properties": {
    "iso:country":"US",
    "sg:address":"5312 E Bay Dr",
    "sg:city":"Clearwater",
    "sg:classifiers":[
        {
            "category":"Professional",
            "subcategory":"Accounting & Tax Preparation",
            "type":"Services"
        }
    ],
    "sg:phone":"+1 727 535 3150",
    "sg:postcode":"33764",
    "sg:province":"FL",
    "sg:tags":[
        "return",
        "filing"
    ],
    "wof:name":"H & R Block Tax Svc",
    "wof:placetype":"venue"
},
  "geometry": {"coordinates":[-82.730192,27.916222],"type":"Point"}
}