{
  "type": "Feature",
  "properties": {
    "addr:full":"12352 Arlington Park Ln Orlando FL 32824",
    "addr:housenumber":"12352",
    "addr:postcode":"32824",
    "addr:street":"Arlington Park Ln",
    "iso:country":"US",
    "sg:address":"12352 Arlington Park Ln",
    "sg:city":"Orlando",
    "sg:classifiers":[
        {
            "category":"Restaurant",
            "type":"Food & Drink"
        }
    ],
    "sg:phone":"+1 407 826 9300",
    "sg:postcode":"32824",
    "sg:province":"FL",
    "wof:name":"Burger King",
    "wof:placetype":"venue"
},
  "geometry": {"coordinates":[-81.37929699999999,28.390242],"type":"Point"}
}