{
  "type": "Feature",
  "properties": {
    "addr:full":"2581 SW Grotto Cir Port Saint Lucie FL 34953",
    "addr:housenumber":"2581",
    "addr:postcode":"34953",
    "addr:street":"Sw Grotto Cir",
    "iso:country":"US",
    "sg:address":"2581 SW Grotto Cir",
    "sg:city":"Port Saint Lucie",
    "sg:classifiers":[
        {
            "category":"Building & Trades",
            "subcategory":"Construction",
            "type":"Services"
        }
    ],
    "sg:phone":"+1 772 879 1577",
    "sg:postcode":"34953",
    "sg:province":"FL",
    "sg:tags":[
        "floor",
        "laying",
        "contractor"
    ],
    "wof:name":"All Coast Construction",
    "wof:placetype":"venue"
},
  "geometry": {"coordinates":[-80.356557,27.264768],"type":"Point"}
}