{
  "type": "Feature",
  "properties": {
    "iso:country":"US",
    "sg:address":"13550 SW 120th St",
    "sg:city":"Miami",
    "sg:classifiers":[
        {
            "category":"Shopping",
            "subcategory":"Clothing, Apparel, & Fashions",
            "type":"Retail Goods"
        },
        {
            "category":"Wholesale",
            "subcategory":"Apparel",
            "type":"Manufacturing & Wholesale Goods"
        },
        {
            "category":"Shopping",
            "subcategory":"Shoes",
            "type":"Retail Goods"
        }
    ],
    "sg:phone":"+1 305 969 9060",
    "sg:postcode":"33186",
    "sg:province":"FL",
    "sg:tags":[
        "shoes-wholesale",
        "clothing",
        "store",
        "manufacturer"
    ],
    "wof:name":"Areasevenshoes And Handbags",
    "wof:placetype":"venue"
},
  "geometry": {"coordinates":[-80.41394,25.65628],"type":"Point"}
}