{
  "type": "Feature",
  "properties": {
    "iso:country":"US",
    "sg:address":"19145 Biscayne Blvd",
    "sg:city":"Aventura",
    "sg:classifiers":[
        {
            "category":"Shopping",
            "subcategory":"Mobile Phones",
            "type":"Retail Goods"
        }
    ],
    "sg:phone":"+1 305 792 5733",
    "sg:postcode":"33180",
    "sg:province":"FL",
    "wof:name":"Access Wireless",
    "wof:placetype":"venue"
},
  "geometry": {"coordinates":[-80.14679700000001,25.952999],"type":"Point"}
}