{
  "type": "Feature",
  "properties": {
    "addr:full":"641 Marphill Loop Brandon FL 33511",
    "addr:housenumber":"641",
    "addr:postcode":"33511",
    "addr:street":"Marphill Loop",
    "iso:country":"US",
    "sg:address":"641 Marphill Loop",
    "sg:city":"Brandon",
    "sg:classifiers":[
        {
            "category":"Professional",
            "subcategory":"Business Services",
            "type":"Services"
        }
    ],
    "sg:phone":"+1 813 685 6859",
    "sg:postcode":"33511",
    "sg:province":"FL",
    "sg:tags":[
        "auctioneer"
    ],
    "wof:name":"Li Ji Enterprises",
    "wof:placetype":"venue"
},
  "geometry": {"coordinates":[-82.29157499999999,27.90692],"type":"Point"}
}