{
  "type": "Feature",
  "properties": {
    "iso:country":"US",
    "sg:address":"2202 E Silver Springs Blvd",
    "sg:city":"Ocala",
    "sg:classifiers":[
        {
            "category":"Food & Beverages",
            "subcategory":"Specialty",
            "type":"Retail Goods"
        }
    ],
    "sg:phone":"+1 352 867 8727",
    "sg:postcode":"34470",
    "sg:province":"FL",
    "sg:tags":[
        "health",
        "diet"
    ],
    "wof:name":"B-Healthy",
    "wof:placetype":"venue"
},
  "geometry": {"coordinates":[-82.103163,29.186992],"type":"Point"}
}