{
  "type": "Feature",
  "properties": {
    "iso:country":"US",
    "sg:address":"2810 SE 5th Cir",
    "sg:city":"Boynton Beach",
    "sg:classifiers":[
        {
            "category":"Shopping",
            "subcategory":"Beauty & Cosmetics",
            "type":"Retail Goods"
        }
    ],
    "sg:phone":"+1 561 737 7100",
    "sg:postcode":"33435",
    "sg:province":"FL",
    "sg:tags":[
        "direct",
        "merchandise",
        "sales"
    ],
    "wof:name":"Martha Williams",
    "wof:placetype":"venue"
},
  "geometry": {"coordinates":[-80.063497,26.503327],"type":"Point"}
}