{
  "type": "Feature",
  "properties": {
    "addr:full":"834 W Lantana Rd Lantana FL 33462",
    "addr:housenumber":"834",
    "addr:postcode":"33462",
    "addr:street":"W Lantana Rd",
    "iso:country":"US",
    "sg:address":"834 W Lantana Rd",
    "sg:city":"Lantana",
    "sg:classifiers":[
        {
            "category":"Banks & Credit Unions",
            "subcategory":"Bank",
            "type":"Services"
        }
    ],
    "sg:phone":"+1 561 582 1411",
    "sg:postcode":"33462",
    "sg:province":"FL",
    "sg:tags":[
        "loan",
        "real estate"
    ],
    "wof:name":"GVS Financial Corp",
    "wof:placetype":"venue"
},
  "geometry": {"coordinates":[-80.064109,26.587038],"type":"Point"}
}