{
  "type": "Feature",
  "properties": {
    "iso:country":"US",
    "sg:address":"801 S Ocean Dr",
    "sg:city":"Fort Pierce",
    "sg:classifiers":[
        {
            "category":"Professional",
            "subcategory":"Business Services",
            "type":"Services"
        }
    ],
    "sg:phone":"+1 772 466 4587",
    "sg:postcode":"34949",
    "sg:province":"FL",
    "wof:name":"Lee Advisory Group Inc",
    "wof:placetype":"venue"
},
  "geometry": {"coordinates":[-80.28862700000001,27.460187],"type":"Point"}
}