{
  "type": "Feature",
  "properties": {
    "iso:country":"US",
    "sg:address":"2635 Skyview Dr",
    "sg:city":"Lakeland",
    "sg:classifiers":[
        {
            "category":"Professional",
            "subcategory":"Business Services",
            "type":"Services"
        }
    ],
    "sg:phone":"+1 863 669 1444",
    "sg:postcode":"33801",
    "sg:province":"FL",
    "sg:tags":[
        "event"
    ],
    "wof:name":"Palette Productions Inc",
    "wof:placetype":"venue"
},
  "geometry": {"coordinates":[-81.904937,28.025951],"type":"Point"}
}