{
  "type": "Feature",
  "properties": {
    "iso:country":"US",
    "sg:address":"690 Regatta Bay Blvd",
    "sg:city":"Destin",
    "sg:classifiers":[
        {
            "category":"Autos & Motor Vehicles",
            "subcategory":"Boat Sales",
            "type":"Retail Goods"
        }
    ],
    "sg:phone":"+1 850 337 8300",
    "sg:postcode":"32541",
    "sg:province":"FL",
    "sg:tags":[
        "dealer",
        "sales"
    ],
    "sg:website":"www.legendarymarine.com",
    "wof:name":"Legendary Marine",
    "wof:placetype":"venue"
},
  "geometry": {"coordinates":[-86.424043,30.397324],"type":"Point"}
}