{
  "type": "Feature",
  "properties": {
    "iso:country":"US",
    "sg:address":"19512 Preserve Dr",
    "sg:city":"Boca Raton",
    "sg:classifiers":[
        {
            "category":"Banks & Credit Unions",
            "subcategory":"Financial Services",
            "type":"Services"
        }
    ],
    "sg:phone":"+1 561 482 1063",
    "sg:postcode":"33498",
    "sg:province":"FL",
    "sg:tags":[
        "patent"
    ],
    "wof:name":"Best Idea Inc",
    "wof:placetype":"venue"
},
  "geometry": {"coordinates":[-80.21619200000001,26.385202],"type":"Point"}
}