{
  "type": "Feature",
  "properties": {
    "addr:full":"20737 Eustis Rd Land O Lakes FL 34637",
    "addr:postcode":"20737;34637",
    "addr:street":"Eustis Rd",
    "iso:country":"US",
    "sg:address":"20737 Eustis Rd",
    "sg:city":"Land O Lakes",
    "sg:classifiers":[
        {
            "category":"Wholesale",
            "subcategory":"Machinery & Supplies",
            "type":"Manufacturing & Wholesale Goods"
        }
    ],
    "sg:phone":"+1 813 996 9581",
    "sg:postcode":"34637",
    "sg:province":"FL",
    "sg:tags":[
        "representative",
        "manufacturer"
    ],
    "wof:name":"Hunting Packaging Machinery",
    "wof:placetype":"venue"
},
  "geometry": {"coordinates":[-82.469821,28.265454],"type":"Point"}
}