{
  "type": "Feature",
  "properties": {
    "addr:full":"1705 Alabama Ave Lynn Haven FL 32444",
    "addr:housenumber":"1705",
    "addr:postcode":"32444",
    "addr:street":"Alabama Ave",
    "iso:country":"US",
    "sg:address":"1705 Alabama Ave",
    "sg:city":"Lynn Haven",
    "sg:classifiers":[
        {
            "category":"Retail",
            "subcategory":"Auto Repair",
            "type":"Services"
        }
    ],
    "sg:phone":"+1 850 271 0102",
    "sg:postcode":"32444",
    "sg:province":"FL",
    "sg:tags":[
        "automotive"
    ],
    "wof:name":"A Cheap Tow",
    "wof:placetype":"venue"
},
  "geometry": {"coordinates":[-85.65340500000001,30.232024],"type":"Point"}
}