{
  "type": "Feature",
  "properties": {
    "iso:country":"US",
    "sg:address":"1508 State Ave",
    "sg:city":"Daytona Beach",
    "sg:classifiers":[
        {
            "category":"Communications",
            "subcategory":"Radio Station",
            "type":"Services"
        }
    ],
    "sg:phone":"+1 386 677 4272",
    "sg:postcode":"32117",
    "sg:province":"FL",
    "sg:tags":[
        "company",
        "broadcasting"
    ],
    "wof:name":"Public Radio Inc",
    "wof:placetype":"venue"
},
  "geometry": {"coordinates":[-81.048675,29.25442],"type":"Point"}
}