{
  "type": "Feature",
  "properties": {
    "addr:full":"1005 Colorado Ave Lynn Haven FL 32444",
    "addr:housenumber":"1005",
    "addr:postcode":"32444",
    "addr:street":"Colorado Ave",
    "iso:country":"US",
    "sg:address":"1005 Colorado Ave",
    "sg:city":"Lynn Haven",
    "sg:classifiers":[
        {
            "category":"Building & Trades",
            "subcategory":"Construction",
            "type":"Services"
        }
    ],
    "sg:phone":"+1 850 248 2486",
    "sg:postcode":"32444",
    "sg:province":"FL",
    "sg:tags":[
        "contractor"
    ],
    "wof:name":"Southern Boarders Custom Fence",
    "wof:placetype":"venue"
},
  "geometry": {"coordinates":[-85.63608499999999,30.24209],"type":"Point"}
}