{
  "type": "Feature",
  "properties": {
    "addr:full":"5417 Tangerine Dr New Port Richey FL 34652",
    "addr:housenumber":"5417",
    "addr:postcode":"34652",
    "addr:street":"Tangerine Dr",
    "iso:country":"US",
    "sg:address":"5417 Tangerine Dr",
    "sg:city":"New Port Richey",
    "sg:classifiers":[
        {
            "category":"Banks & Credit Unions",
            "subcategory":"Bank",
            "type":"Services"
        }
    ],
    "sg:phone":"+1 727 834 9766",
    "sg:postcode":"34652",
    "sg:province":"FL",
    "sg:tags":[
        "broker",
        "mortgage"
    ],
    "wof:name":"Elan Enterprises Inc",
    "wof:placetype":"venue"
},
  "geometry": {"coordinates":[-82.72436999999999,28.232155],"type":"Point"}
}