{
  "type": "Feature",
  "properties": {
    "addr:full":"1500 N Powerline Rd Pompano Beach FL 33069",
    "addr:housenumber":"1500",
    "addr:postcode":"33069",
    "addr:street":"N Powerline Rd",
    "iso:country":"US",
    "sg:address":"1500 N Powerline Rd",
    "sg:city":"Pompano Beach",
    "sg:classifiers":[
        {
            "category":"Building & Trades",
            "subcategory":"Construction",
            "type":"Services"
        }
    ],
    "sg:phone":"+1 954 973 1805",
    "sg:postcode":"33069",
    "sg:province":"FL",
    "sg:tags":[
        "television",
        "telephone",
        "cable",
        "contractor"
    ],
    "sg:website":"www.ccgcatv.com",
    "wof:name":"Communications Construction",
    "wof:placetype":"venue"
},
  "geometry": {"coordinates":[-80.151546,26.248613],"type":"Point"}
}