{
  "type": "Feature",
  "properties": {
    "iso:country":"US",
    "sg:address":"721 US Hwy 1",
    "sg:city":"North Palm Beach",
    "sg:classifiers":[
        {
            "category":"Banks & Credit Unions",
            "subcategory":"Investment Brokerage",
            "type":"Services"
        }
    ],
    "sg:phone":"+1 561 848 9973",
    "sg:postcode":"33408",
    "sg:province":"FL",
    "sg:tags":[
        "advisory",
        "financial"
    ],
    "wof:name":"PDI Financial Resources",
    "wof:placetype":"venue"
},
  "geometry": {"coordinates":[-80.059049,26.820399],"type":"Point"}
}