{
  "type": "Feature",
  "properties": {
    "addr:full":"3701 N Wilder Rd Plant City FL 33565",
    "addr:housenumber":"3701",
    "addr:postcode":"33565",
    "addr:street":"N Wilder Rd",
    "iso:country":"US",
    "sg:address":"3701 N Wilder Rd",
    "sg:city":"Plant City",
    "sg:classifiers":[
        {
            "category":"Personal",
            "subcategory":"Beauty Salon",
            "type":"Services"
        }
    ],
    "sg:phone":"+1 813 752 3917",
    "sg:postcode":"33565",
    "sg:province":"FL",
    "sg:tags":[
        "shop"
    ],
    "wof:name":"Wanda's Beauty Shop",
    "wof:placetype":"venue"
},
  "geometry": {"coordinates":[-82.09704600000001,28.055608],"type":"Point"}
}