{
  "type": "Feature",
  "properties": {
    "addr:full":"1305 S Orange Blossom Trl Orlando FL 32805",
    "addr:housenumber":"1305",
    "addr:postcode":"32805",
    "addr:street":"S Orange Blossom Trl",
    "iso:country":"US",
    "sg:address":"1305 S Orange Blossom Trl",
    "sg:city":"Orlando",
    "sg:classifiers":[
        {
            "category":"Restaurant",
            "type":"Food & Drink"
        }
    ],
    "sg:phone":"+1 407 854 5056",
    "sg:postcode":"32805",
    "sg:province":"FL",
    "sg:tags":[
        "pizza"
    ],
    "wof:name":"Godfather's Pizza",
    "wof:placetype":"venue"
},
  "geometry": {"coordinates":[-81.397002,28.525564],"type":"Point"}
}