{
  "type": "Feature",
  "properties": {
    "iso:country":"US",
    "sg:address":"973 State Hwy 436",
    "sg:city":"Casselberry",
    "sg:classifiers":[
        {
            "category":"Home & Garden",
            "subcategory":"Furniture",
            "type":"Retail Goods"
        }
    ],
    "sg:phone":"+1 407 657 6972",
    "sg:postcode":"32707",
    "sg:province":"FL",
    "wof:name":"Mattress One",
    "wof:placetype":"venue"
},
  "geometry": {"coordinates":[-81.324045,28.648063],"type":"Point"}
}