{
  "type": "Feature",
  "properties": {
    "addr:full":"5801 SW 94th St Miami FL 33156",
    "addr:housenumber":"5801",
    "addr:postcode":"33156",
    "addr:street":"Sw 94Th St",
    "iso:country":"US",
    "sg:address":"5801 SW 94th St",
    "sg:city":"Miami",
    "sg:classifiers":[
        {
            "category":"Building & Trades",
            "subcategory":"Construction",
            "type":"Services"
        }
    ],
    "sg:phone":"+1 305 669 4243",
    "sg:postcode":"33156",
    "sg:province":"FL",
    "sg:tags":[
        "house"
    ],
    "wof:name":"Ce Construction Deve",
    "wof:placetype":"venue"
},
  "geometry": {"coordinates":[-80.287119,25.683457],"type":"Point"}
}