{
  "type": "Feature",
  "properties": {
    "iso:country":"US",
    "sg:address":"407 Georgia St",
    "sg:city":"Starke",
    "sg:classifiers":[
        {
            "category":"Wholesale",
            "subcategory":"Construction Materials",
            "type":"Manufacturing & Wholesale Goods"
        }
    ],
    "sg:phone":"+1 904 964 9649",
    "sg:postcode":"32091",
    "sg:province":"FL",
    "sg:tags":[
        "tank",
        "system",
        "septic"
    ],
    "wof:name":"East Star Industries",
    "wof:placetype":"venue"
},
  "geometry": {"coordinates":[-82.108705,29.955166],"type":"Point"}
}