{
  "type": "Feature",
  "properties": {
    "iso:country":"US",
    "sg:address":"10935 SE 177th Pl",
    "sg:city":"Summerfield",
    "sg:classifiers":[
        {
            "category":"Real Estate",
            "subcategory":"Real Estate Services",
            "type":"Services"
        }
    ],
    "sg:phone":"+1 352 307 9111",
    "sg:postcode":"34491",
    "sg:province":"FL",
    "sg:tags":[
        "company",
        "title"
    ],
    "wof:name":"American Heritage Title",
    "wof:placetype":"venue"
},
  "geometry": {"coordinates":[-81.980193,28.963784],"type":"Point"}
}