{
  "type": "Feature",
  "properties": {
    "addr:full":"13 NE 8 Ave Gainesville FL 32601",
    "addr:housenumber":"13",
    "addr:postcode":"32601",
    "addr:street":"Ne 8 Ave",
    "iso:country":"US",
    "sg:address":"13 NE 8 Ave",
    "sg:city":"Gainesville",
    "sg:classifiers":[
        {
            "category":"Home & Garden",
            "subcategory":"Furniture",
            "type":"Retail Goods"
        }
    ],
    "sg:phone":"+1 352 338 2724",
    "sg:postcode":"32601",
    "sg:province":"FL",
    "wof:name":"Thomasville Home Furnishings",
    "wof:placetype":"venue"
},
  "geometry": {"coordinates":[-82.324045,29.659185],"type":"Point"}
}