{
  "type": "Feature",
  "properties": {
    "iso:country":"US",
    "sg:address":"7305 Old Kings Rd S",
    "sg:city":"Jacksonville",
    "sg:classifiers":[
        {
            "category":"Building & Trades",
            "subcategory":"Construction",
            "type":"Services"
        }
    ],
    "sg:phone":"+1 904 786 1855",
    "sg:postcode":"32217",
    "sg:province":"FL",
    "sg:tags":[
        "railroad",
        "contractor"
    ],
    "wof:name":"H A Bass",
    "wof:placetype":"venue"
},
  "geometry": {"coordinates":[-81.617339,30.246503],"type":"Point"}
}