{
  "type": "Feature",
  "properties": {
    "iso:country":"US",
    "sg:address":"1802 Sir Henrys Trl",
    "sg:city":"Lakeland",
    "sg:classifiers":[
        {
            "category":"Professional",
            "subcategory":"Engineering",
            "type":"Services"
        }
    ],
    "sg:phone":"+1 863 853 5456",
    "sg:postcode":"33809",
    "sg:province":"FL",
    "sg:tags":[
        "civil",
        "consulting",
        "structural",
        "engineer"
    ],
    "wof:name":"Frey Engineering",
    "wof:placetype":"venue"
},
  "geometry": {"coordinates":[-81.92244599999999,28.139442],"type":"Point"}
}