{
  "type": "Feature",
  "properties": {
    "iso:country":"US",
    "sg:address":"508 Wellington Ave",
    "sg:city":"Lehigh Acres",
    "sg:classifiers":[
        {
            "category":"Shopping",
            "type":"Retail Goods"
        }
    ],
    "sg:phone":"+1 239 369 9888",
    "sg:postcode":"33972",
    "sg:province":"FL",
    "sg:tags":[
        "merchandise"
    ],
    "wof:name":"Little Rascals Pet Store",
    "wof:placetype":"venue"
},
  "geometry": {"coordinates":[-81.581444,26.621457],"type":"Point"}
}