{
  "type": "Feature",
  "properties": {
    "iso:country":"US",
    "sg:address":"6996 Piazza Grande Ave Suite 304",
    "sg:city":"Orlando",
    "sg:classifiers":[
        {
            "category":"Building & Trades",
            "subcategory":"Construction",
            "type":"Services"
        }
    ],
    "sg:phone":"+1 407 221 4444",
    "sg:postcode":"32835",
    "sg:province":"FL",
    "sg:tags":[
        "estimate"
    ],
    "sg:website":"http://www.hibiscushomesfl.com",
    "wof:name":"Verde Ridge & Patterson Groves Community Builder - Hibiscus Homes",
    "wof:placetype":"venue"
},
  "geometry": {"coordinates":[-81.48274000000001,28.516326],"type":"Point"}
}