{
  "type": "Feature",
  "properties": {
    "iso:country":"US",
    "sg:address":"1155 Cathy Tripp Ln",
    "sg:city":"Jacksonville",
    "sg:classifiers":[
        {
            "category":"Real Estate",
            "subcategory":"Developer",
            "type":"Services"
        }
    ],
    "sg:phone":"+1 904 781 4740",
    "sg:postcode":"32220",
    "sg:province":"FL",
    "wof:name":"Capps Land Management Inc",
    "wof:placetype":"venue"
},
  "geometry": {"coordinates":[-81.81705599999999,30.333834],"type":"Point"}
}