{
  "type": "Feature",
  "properties": {
    "iso:country":"US",
    "sg:address":"1010 Palm Coast Pkwy NW",
    "sg:city":"Palm Coast",
    "sg:classifiers":[
        {
            "category":"Autos & Motor Vehicles",
            "subcategory":"Auto Supplies",
            "type":"Retail Goods"
        }
    ],
    "sg:phone":"+1 386 446 4530",
    "sg:postcode":"32137",
    "sg:province":"FL",
    "sg:tags":[
        "equipment",
        "electrical"
    ],
    "wof:name":"Discount Auto Parts Inc",
    "wof:placetype":"venue"
},
  "geometry": {"coordinates":[-81.25608,29.55312],"type":"Point"}
}