{
  "type": "Feature",
  "properties": {
    "iso:country":"US",
    "sg:address":"248 Tampa Ave W",
    "sg:city":"Venice",
    "sg:classifiers":[
        {
            "category":"Shopping",
            "subcategory":"Gifts & Souvenirs",
            "type":"Retail Goods"
        }
    ],
    "sg:phone":"+1 941 484 5950",
    "sg:postcode":"34285",
    "sg:province":"FL",
    "wof:name":"Rose Cabbage",
    "wof:placetype":"venue"
},
  "geometry": {"coordinates":[-82.44696500000001,27.100884],"type":"Point"}
}