{
  "type": "Feature",
  "properties": {
    "iso:country":"US",
    "sg:address":"3554 Haldeman Creek Dr",
    "sg:city":"Naples",
    "sg:classifiers":[
        {
            "category":"Professional",
            "type":"Services"
        }
    ],
    "sg:phone":"+1 239 732 1573",
    "sg:postcode":"34112",
    "sg:province":"FL",
    "sg:tags":[
        "establishment"
    ],
    "wof:name":"Compass Point South",
    "wof:placetype":"venue"
},
  "geometry": {"coordinates":[-81.778841,26.119264],"type":"Point"}
}