{
  "type": "Feature",
  "properties": {
    "iso:country":"US",
    "sg:address":"2856 Sunset Blvd",
    "sg:city":"Largo",
    "sg:classifiers":[
        {
            "category":"Professional",
            "subcategory":"Business Services",
            "type":"Services"
        }
    ],
    "sg:phone":"+1 727 585 2497",
    "sg:postcode":"33770",
    "sg:province":"FL",
    "wof:name":"Whitehall Enterprises Inc",
    "wof:placetype":"venue"
},
  "geometry": {"coordinates":[-82.818771,27.918381],"type":"Point"}
}