{
  "type": "Feature",
  "properties": {
    "addr:full":"1420 Lemon St De Land FL 32720",
    "addr:housenumber":"1420",
    "addr:postcode":"32720",
    "addr:street":"Lemon St;Land",
    "iso:country":"US",
    "sg:address":"1420 Lemon St",
    "sg:city":"De Land",
    "sg:classifiers":[
        {
            "category":"Manufacturing",
            "subcategory":"Chemicals & Compounds",
            "type":"Manufacturing & Wholesale Goods"
        }
    ],
    "sg:phone":"+1 386 736 0838",
    "sg:postcode":"32720",
    "sg:province":"FL",
    "sg:tags":[
        "agricultural",
        "mfg"
    ],
    "wof:name":"Foliar Nutrients Inc",
    "wof:placetype":"venue"
},
  "geometry": {"coordinates":[-81.35166700000001,29.089572],"type":"Point"}
}