{
  "type": "Feature",
  "properties": {
    "iso:country":"US",
    "sg:address":"12057 Cedar Bluff",
    "sg:city":"Tallahassee",
    "sg:classifiers":[
        {
            "category":"Professional",
            "subcategory":"Secretarial Services",
            "type":"Services"
        }
    ],
    "sg:phone":"+1 850 894 0828",
    "sg:postcode":"32312",
    "sg:province":"FL",
    "sg:tags":[
        "reporting",
        "court"
    ],
    "wof:name":"Preimere Reporting",
    "wof:placetype":"venue"
},
  "geometry": {"coordinates":[-84.243452,30.612221],"type":"Point"}
}