{
  "type": "Feature",
  "properties": {
    "iso:country":"US",
    "sg:address":"5002 E Sligh Ave",
    "sg:city":"Tampa",
    "sg:classifiers":[
        {
            "category":"Food & Beverages",
            "subcategory":"Groceries & Convenience Stores",
            "type":"Retail Goods"
        }
    ],
    "sg:phone":"+1 813 988 1146",
    "sg:postcode":"33617",
    "sg:province":"FL",
    "wof:name":"Snax Food Store Inc",
    "wof:placetype":"venue"
},
  "geometry": {"coordinates":[-82.39779,28.010774],"type":"Point"}
}