{
  "type": "Feature",
  "properties": {
    "addr:full":"157 NE 2nd Ave Delray Beach FL 33444",
    "addr:housenumber":"157",
    "addr:postcode":"33444",
    "addr:street":"Ne 2Nd Ave",
    "iso:country":"US",
    "sg:address":"157 NE 2nd Ave",
    "sg:city":"Delray Beach",
    "sg:classifiers":[
        {
            "category":"Home & Garden",
            "subcategory":"Furniture",
            "type":"Retail Goods"
        }
    ],
    "sg:phone":"+1 561 274 9700",
    "sg:postcode":"33444",
    "sg:province":"FL",
    "sg:tags":[
        "equipment",
        "furnishing",
        "store"
    ],
    "wof:name":"Museo",
    "wof:placetype":"venue"
},
  "geometry": {"coordinates":[-80.071067,26.464254],"type":"Point"}
}