{
  "type": "Feature",
  "properties": {
    "iso:country":"US",
    "sg:address":"2620 NW 112th Ave",
    "sg:city":"Pompano Beach",
    "sg:classifiers":[
        {
            "category":"Wholesale",
            "subcategory":"Machinery & Supplies",
            "type":"Manufacturing & Wholesale Goods"
        }
    ],
    "sg:phone":"+1 954 340 8882",
    "sg:postcode":"33065",
    "sg:province":"FL",
    "sg:tags":[
        "shell",
        "construction"
    ],
    "wof:name":"Dimensional Construction",
    "wof:placetype":"venue"
},
  "geometry": {"coordinates":[-80.298238,26.157438],"type":"Point"}
}