{
  "type": "Feature",
  "properties": {
    "iso:country":"US",
    "sg:address":"11240 St Johns Industrial Pkwy N",
    "sg:city":"Jacksonville",
    "sg:classifiers":[
        {
            "category":"Building & Trades",
            "subcategory":"Construction",
            "type":"Services"
        }
    ],
    "sg:phone":"+1 904 398 7936",
    "sg:postcode":"32246",
    "sg:province":"FL",
    "sg:tags":[
        "contractor"
    ],
    "wof:name":"Tom Collier Building Cntrctr",
    "wof:placetype":"venue"
},
  "geometry": {"coordinates":[-81.528173,30.281205],"type":"Point"}
}