{
  "type": "Feature",
  "properties": {
    "iso:country":"US",
    "sg:address":"5843 Brannen Rd S",
    "sg:city":"Lakeland",
    "sg:classifiers":[
        {
            "category":"Organizations",
            "subcategory":"Community Association",
            "type":"Services"
        }
    ],
    "sg:phone":"+1 863 647 5217",
    "sg:postcode":"33813",
    "sg:province":"FL",
    "sg:tags":[
        "fraternal"
    ],
    "wof:name":"Fraternal Order Of Eagles",
    "wof:placetype":"venue"
},
  "geometry": {"coordinates":[-81.96000100000001,27.959843],"type":"Point"}
}