{
  "type": "Feature",
  "properties": {
    "iso:country":"US",
    "sg:address":"2939 Wynn St",
    "sg:city":"Marianna",
    "sg:classifiers":[
        {
            "category":"Professional",
            "subcategory":"Management & Consulting",
            "type":"Services"
        }
    ],
    "sg:phone":"+1 850 482 6486",
    "sg:postcode":"32446",
    "sg:province":"FL",
    "wof:name":"Wheelus Management Services",
    "wof:placetype":"venue"
},
  "geometry": {"coordinates":[-85.23122600000001,30.779187],"type":"Point"}
}