{
  "type": "Feature",
  "properties": {
    "iso:country":"US",
    "sg:address":"670 SE 5th Ct",
    "sg:city":"Pompano Beach",
    "sg:classifiers":[
        {
            "category":"Retail",
            "subcategory":"Animal Services",
            "type":"Services"
        }
    ],
    "sg:phone":"+1 954 943 2802",
    "sg:postcode":"33060",
    "sg:province":"FL",
    "wof:name":"Bella Poochie Pet Salon",
    "wof:placetype":"venue"
},
  "geometry": {"coordinates":[-80.111531,26.222903],"type":"Point"}
}