{
  "type": "Feature",
  "properties": {
    "iso:country":"US",
    "sg:address":"15045 Aubrey Ave",
    "sg:city":"Spring Hill",
    "sg:classifiers":[
        {
            "category":"Organizations",
            "subcategory":"Religious Organization",
            "type":"Services"
        }
    ],
    "sg:phone":"+1 727 856 7562",
    "sg:postcode":"34610",
    "sg:province":"FL",
    "wof:name":"American Catholic Church",
    "wof:placetype":"venue"
},
  "geometry": {"coordinates":[-82.55944700000001,28.427281],"type":"Point"}
}