{
  "type": "Feature",
  "properties": {
    "addr:full":"651 Rugby St Orlando FL 32804",
    "addr:housenumber":"651",
    "addr:postcode":"32804",
    "addr:street":"Rugby St",
    "iso:country":"US",
    "sg:address":"651 Rugby St",
    "sg:city":"Orlando",
    "sg:classifiers":[
        {
            "category":"Health Services",
            "subcategory":"Chiropractor",
            "type":"Services"
        }
    ],
    "sg:phone":"+1 407 244 5554",
    "sg:postcode":"32804",
    "sg:province":"FL",
    "wof:name":"A To Z Medical Center Inc",
    "wof:placetype":"venue"
},
  "geometry": {"coordinates":[-81.388238,28.573649],"type":"Point"}
}