{
  "type": "Feature",
  "properties": {
    "iso:country":"US",
    "sg:address":"2133 W US Hwy 90",
    "sg:city":"Lake City",
    "sg:classifiers":[
        {
            "category":"Building & Trades",
            "subcategory":"Equipment Rental",
            "type":"Services"
        }
    ],
    "sg:phone":"+1 386 755 3777",
    "sg:postcode":"32055",
    "sg:province":"FL",
    "sg:tags":[
        "yard"
    ],
    "wof:name":"Buddy's Home Furnishings",
    "wof:placetype":"venue"
},
  "geometry": {"coordinates":[-82.654039,30.18528],"type":"Point"}
}