{
  "type": "Feature",
  "properties": {
    "iso:country":"US",
    "sg:address":"101 Ave C SE",
    "sg:city":"Winter Haven",
    "sg:classifiers":[
        {
            "category":"Professional",
            "subcategory":"Lawyer & Legal Services",
            "type":"Services"
        }
    ],
    "sg:phone":"+1 863 294 0051",
    "sg:postcode":"33880",
    "sg:province":"FL",
    "wof:name":"Rodney Durrance Jr",
    "wof:placetype":"venue"
},
  "geometry": {"coordinates":[-81.72475300000001,28.018594],"type":"Point"}
}