{
  "type": "Feature",
  "properties": {
    "iso:country":"US",
    "sg:address":"128 Shorthorn Dr",
    "sg:city":"Apopka",
    "sg:classifiers":[
        {
            "category":"Building & Trades",
            "subcategory":"Construction",
            "type":"Services"
        }
    ],
    "sg:phone":"+1 407 886 4004",
    "sg:postcode":"32712",
    "sg:province":"FL",
    "sg:tags":[
        "hanging",
        "contractor"
    ],
    "wof:name":"Burdens Buzz Painting",
    "wof:placetype":"venue"
},
  "geometry": {"coordinates":[-81.513487,28.761989],"type":"Point"}
}