{
  "type": "Feature",
  "properties": {
    "addr:full":"2516 NE 21st Ter Pompano Beach FL 33064",
    "addr:housenumber":"2516",
    "addr:postcode":"33064",
    "addr:street":"Ne 21St Ter",
    "iso:country":"US",
    "sg:address":"2516 NE 21st Ter",
    "sg:city":"Pompano Beach",
    "sg:classifiers":[
        {
            "category":"Professional",
            "subcategory":"Art Services",
            "type":"Services"
        }
    ],
    "sg:phone":"+1 954 786 1022",
    "sg:postcode":"33064",
    "sg:province":"FL",
    "sg:tags":[
        "commercial",
        "design"
    ],
    "wof:name":"Latitude 26 Designs Inc",
    "wof:placetype":"venue"
},
  "geometry": {"coordinates":[-80.094129,26.263375],"type":"Point"}
}