{
  "type": "Feature",
  "properties": {
    "addr:full":"15124 Tealrise Way Lithia FL 33547",
    "addr:postcode":"15124;33547",
    "addr:street":"Tealrise Way",
    "iso:country":"US",
    "sg:address":"15124 Tealrise Way",
    "sg:city":"Lithia",
    "sg:classifiers":[
        {
            "category":"Building & Trades",
            "subcategory":"Construction",
            "type":"Services"
        }
    ],
    "sg:phone":"+1 813 685 4599",
    "sg:postcode":"33547",
    "sg:province":"FL",
    "sg:tags":[
        "home",
        "builder"
    ],
    "wof:name":"Cardel Master Builder Inc",
    "wof:placetype":"venue"
},
  "geometry": {"coordinates":[-82.236018,27.843069],"type":"Point"}
}