{
  "type": "Feature",
  "properties": {
    "iso:country":"US",
    "sg:address":"8430 Egret Ln",
    "sg:city":"Seminole",
    "sg:classifiers":[
        {
            "category":"Professional",
            "subcategory":"Management & Consulting",
            "type":"Services"
        },
        {
            "category":"Professional",
            "subcategory":"Computer Services",
            "type":"Services"
        }
    ],
    "sg:phone":"+1 727 393 6048",
    "sg:postcode":"33776",
    "sg:province":"FL",
    "sg:tags":[
        "consultant",
        "designer"
    ],
    "wof:name":"Quality Plus Technologies Inc",
    "wof:placetype":"venue"
},
  "geometry": {"coordinates":[-82.83877200000001,27.849896],"type":"Point"}
}