{
  "type": "Feature",
  "properties": {
    "iso:country":"US",
    "sg:address":"3275 Hillmont Cir",
    "sg:city":"Orlando",
    "sg:classifiers":[
        {
            "category":"Professional",
            "type":"Services"
        }
    ],
    "sg:phone":"+1 407 681 0400",
    "sg:postcode":"32817",
    "sg:province":"FL",
    "wof:name":"Subfinders Com Inc",
    "wof:placetype":"venue"
},
  "geometry": {"coordinates":[-81.22999299999999,28.595431],"type":"Point"}
}