{
  "type": "Feature",
  "properties": {
    "addr:full":"20 S Monroe St Quincy FL 32351",
    "addr:housenumber":"20",
    "addr:postcode":"32351",
    "addr:street":"S Monroe St",
    "iso:country":"US",
    "sg:address":"20 S Monroe St",
    "sg:city":"Quincy",
    "sg:classifiers":[
        {
            "category":"Shopping",
            "subcategory":"Musical Instruments",
            "type":"Retail Goods"
        }
    ],
    "sg:phone":"+1 850 627 9309",
    "sg:postcode":"32351",
    "sg:province":"FL",
    "sg:tags":[
        "pro"
    ],
    "wof:name":"House Of Music",
    "wof:placetype":"venue"
},
  "geometry": {"coordinates":[-84.578197,30.587315],"type":"Point"}
}