{
  "type": "Feature",
  "properties": {
    "iso:country":"US",
    "sg:address":"6280 SW 72nd St",
    "sg:city":"Miami",
    "sg:classifiers":[
        {
            "category":"Health Services",
            "subcategory":"Doctor",
            "type":"Services"
        }
    ],
    "sg:phone":"+1 305 669 9828",
    "sg:postcode":"33143",
    "sg:province":"FL",
    "sg:tags":[
        "medical"
    ],
    "wof:name":"Felser Frederick S MD",
    "wof:placetype":"venue"
},
  "geometry": {"coordinates":[-80.295479,25.703958],"type":"Point"}
}