{
  "type": "Feature",
  "properties": {
    "addr:full":"1604 Southbrook Ln Tallahassee FL 32312",
    "addr:housenumber":"1604",
    "addr:postcode":"32312",
    "addr:street":"Southbrook Ln",
    "iso:country":"US",
    "sg:address":"1604 Southbrook Ln",
    "sg:city":"Tallahassee",
    "sg:classifiers":[
        {
            "category":"Professional",
            "subcategory":"Advertising",
            "type":"Services"
        }
    ],
    "sg:phone":"+1 850 668 4889",
    "sg:postcode":"32312",
    "sg:province":"FL",
    "sg:tags":[
        "counselor"
    ],
    "wof:name":"Canopy Road Marketing",
    "wof:placetype":"venue"
},
  "geometry": {"coordinates":[-84.247069,30.612671],"type":"Point"}
}