{
  "type": "Feature",
  "properties": {
    "iso:country":"US",
    "sg:address":"8680 Schirra Ct",
    "sg:city":"Titusville",
    "sg:classifiers":[
        {
            "category":"Building & Trades",
            "subcategory":"Construction",
            "type":"Services"
        }
    ],
    "sg:phone":"+1 321 385 9155",
    "sg:postcode":"32780",
    "sg:province":"FL",
    "sg:tags":[
        "industrial",
        "painting",
        "contractors-commercial",
        "contractor"
    ],
    "wof:name":"Heyne Industrial Services Pntg",
    "wof:placetype":"venue"
},
  "geometry": {"coordinates":[-80.816299,28.519966],"type":"Point"}
}