{
  "type": "Feature",
  "properties": {
    "iso:country":"US",
    "sg:address":"3445 Cypress Ter",
    "sg:city":"Pinellas Park",
    "sg:classifiers":[
        {
            "category":"Retail",
            "subcategory":"Auto Repair",
            "type":"Services"
        }
    ],
    "sg:phone":"+1 727 526 3947",
    "sg:postcode":"33781",
    "sg:province":"FL",
    "sg:tags":[
        "speedometer"
    ],
    "wof:name":"Speedometer Repair",
    "wof:placetype":"venue"
},
  "geometry": {"coordinates":[-82.680679,27.836262],"type":"Point"}
}