{
  "type": "Feature",
  "properties": {
    "addr:full":"4300 Curry Ford Rd Orlando FL 32806",
    "addr:housenumber":"4300",
    "addr:postcode":"32806",
    "addr:street":"Curry Ford Rd",
    "iso:country":"US",
    "sg:address":"4300 Curry Ford Rd",
    "sg:city":"Orlando",
    "sg:classifiers":[
        {
            "category":"Building & Trades",
            "subcategory":"Construction",
            "type":"Services"
        }
    ],
    "sg:phone":"+1 407 898 7488",
    "sg:postcode":"32806",
    "sg:province":"FL",
    "sg:tags":[
        "house",
        "general",
        "contractor"
    ],
    "wof:name":"Christopher Wren Inc",
    "wof:placetype":"venue"
},
  "geometry": {"coordinates":[-81.331675,28.524178],"type":"Point"}
}