{
  "type": "Feature",
  "properties": {
    "addr:full":"45 Shore Dr N Miami FL 33133",
    "addr:housenumber":"45",
    "addr:postcode":"33133",
    "addr:street":"Shore Dr N",
    "iso:country":"US",
    "sg:address":"45 Shore Dr N",
    "sg:city":"Miami",
    "sg:classifiers":[
        {
            "category":"Health Services",
            "subcategory":"Clinic",
            "type":"Services"
        }
    ],
    "sg:phone":"+1 305 285 4140",
    "sg:postcode":"33133",
    "sg:province":"FL",
    "wof:name":"Rural Afghan Healthcare Assoc",
    "wof:placetype":"venue"
},
  "geometry": {"coordinates":[-80.213106,25.747925],"type":"Point"}
}