{
  "type": "Feature",
  "properties": {
    "addr:full":"1587 S Highland Ave Clearwater FL 33756",
    "addr:housenumber":"1587",
    "addr:postcode":"33756",
    "addr:street":"S Highland Ave",
    "iso:country":"US",
    "sg:address":"1587 S Highland Ave",
    "sg:city":"Clearwater",
    "sg:classifiers":[
        {
            "category":"Retail",
            "subcategory":"Laundry & Dry Cleaning",
            "type":"Services"
        }
    ],
    "sg:phone":"+1 727 446 5872",
    "sg:postcode":"33756",
    "sg:province":"FL",
    "sg:tags":[
        "cleaners"
    ],
    "wof:name":"Scott's Custom Cleaners",
    "wof:placetype":"venue"
},
  "geometry": {"coordinates":[-82.774961,27.941026],"type":"Point"}
}