{
  "type": "Feature",
  "properties": {
    "addr:full":"1707 E Edgewood Dr Lakeland FL 33803",
    "addr:housenumber":"1707",
    "addr:postcode":"33803",
    "addr:street":"E Edgewood Dr",
    "iso:country":"US",
    "sg:address":"1707 E Edgewood Dr",
    "sg:city":"Lakeland",
    "sg:classifiers":[
        {
            "category":"Health Services",
            "subcategory":"Doctor",
            "type":"Services"
        }
    ],
    "sg:phone":"+1 863 688 9219",
    "sg:postcode":"33803",
    "sg:province":"FL",
    "sg:tags":[
        "clinic"
    ],
    "wof:name":"SOUTHSIDE Medical Ctr",
    "wof:placetype":"venue"
},
  "geometry": {"coordinates":[-81.9286,28.011248],"type":"Point"}
}