{
  "type": "Feature",
  "properties": {
    "iso:country":"US",
    "sg:address":"2153 Copley Dr",
    "sg:city":"Pensacola",
    "sg:classifiers":[
        {
            "category":"Real Estate",
            "subcategory":"Real Estate Operator",
            "type":"Services"
        }
    ],
    "sg:phone":"+1 850 438 5367",
    "sg:postcode":"32503",
    "sg:province":"FL",
    "sg:tags":[
        "dwelling"
    ],
    "wof:name":"Clover Properties Pensacola",
    "wof:placetype":"venue"
},
  "geometry": {"coordinates":[-87.19586200000001,30.463804],"type":"Point"}
}