{
  "type": "Feature",
  "properties": {
    "iso:country":"US",
    "sg:address":"1003 Atlantic Blvd",
    "sg:city":"Atlantic Beach",
    "sg:classifiers":[
        {
            "category":"Shopping",
            "subcategory":"Gifts & Souvenirs",
            "type":"Retail Goods"
        }
    ],
    "sg:phone":"+1 904 246 0998",
    "sg:postcode":"32233",
    "sg:province":"FL",
    "sg:tags":[
        "collectible",
        "sport"
    ],
    "wof:name":"Sportsfans Collectibles",
    "wof:placetype":"venue"
},
  "geometry": {"coordinates":[-81.412509,30.324448],"type":"Point"}
}