{
  "type": "Feature",
  "properties": {
    "iso:country":"US",
    "sg:address":"4200 Tamiami Trl",
    "sg:city":"Port Charlotte",
    "sg:classifiers":[
        {
            "category":"Cafe",
            "type":"Food & Drink"
        }
    ],
    "sg:menulink":"http://www.allmenus.com/fl/port-charlotte/88589-the-soup-jungle-cafe/menu/",
    "sg:phone":"+1 941 258 3500",
    "sg:postcode":"33952",
    "sg:province":"FL",
    "sg:tags":[
        "american"
    ],
    "wof:name":"The Soup Jungle Cafe",
    "wof:placetype":"venue"
},
  "geometry": {"coordinates":[-82.078924,26.967611],"type":"Point"}
}