{
  "type": "Feature",
  "properties": {
    "iso:country":"US",
    "sg:address":"3066 Drew Way",
    "sg:city":"Palm Springs",
    "sg:classifiers":[
        {
            "category":"Organizations",
            "subcategory":"Religious Organization",
            "type":"Services"
        }
    ],
    "sg:phone":"+1 561 641 0082",
    "sg:postcode":"33406",
    "sg:province":"FL",
    "sg:tags":[
        "church"
    ],
    "wof:name":"Holy Spirit Anglican Church",
    "wof:placetype":"venue"
},
  "geometry": {"coordinates":[-80.08913699999999,26.6408],"type":"Point"}
}