{
  "type": "Feature",
  "properties": {
    "addr:full":"1357 Rockledge Dr Rockledge FL 32955",
    "addr:housenumber":"1357",
    "addr:postcode":"32955",
    "addr:street":"Rockledge Dr",
    "iso:country":"US",
    "sg:address":"1357 Rockledge Dr",
    "sg:city":"Rockledge",
    "sg:classifiers":[
        {
            "category":"Building & Trades",
            "subcategory":"Construction",
            "type":"Services"
        }
    ],
    "sg:phone":"+1 321 636 1126",
    "sg:postcode":"32955",
    "sg:province":"FL",
    "sg:tags":[
        "screen",
        "enclosure"
    ],
    "wof:name":"Action Aluminum",
    "wof:placetype":"venue"
},
  "geometry": {"coordinates":[-80.71083400000001,28.322705],"type":"Point"}
}