{
  "type": "Feature",
  "properties": {
    "iso:country":"US",
    "sg:address":"2424 US Hwy 301",
    "sg:city":"Ellenton",
    "sg:classifiers":[
        {
            "category":"Manufacturing",
            "subcategory":"Furniture",
            "type":"Manufacturing & Wholesale Goods"
        }
    ],
    "sg:phone":"+1 941 729 7604",
    "sg:postcode":"34222",
    "sg:province":"FL",
    "sg:tags":[
        "box",
        "spring",
        "mfg",
        "mattress"
    ],
    "wof:name":"Pittsburgh Mattress Factory",
    "wof:placetype":"venue"
},
  "geometry": {"coordinates":[-82.539272,27.521757],"type":"Point"}
}