{
  "type": "Feature",
  "properties": {
    "iso:country":"US",
    "sg:address":"1672 NE 70th St",
    "sg:city":"Ocala",
    "sg:classifiers":[
        {
            "category":"Farming",
            "subcategory":"Farm",
            "type":"Manufacturing & Wholesale Goods"
        }
    ],
    "sg:phone":"+1 352 351 1481",
    "sg:postcode":"34479",
    "sg:province":"FL",
    "wof:name":"Magnolia Bloodstock",
    "wof:placetype":"venue"
},
  "geometry": {"coordinates":[-82.125586,29.25921],"type":"Point"}
}