{
  "type": "Feature",
  "properties": {
    "addr:full":"1117 Primrose Ln Wellington FL 33414",
    "addr:housenumber":"1117",
    "addr:postcode":"33414",
    "addr:street":"Primrose Ln",
    "iso:country":"US",
    "sg:address":"1117 Primrose Ln",
    "sg:city":"Wellington",
    "sg:classifiers":[
        {
            "category":"Communications",
            "subcategory":"Film & Video Production",
            "type":"Services"
        }
    ],
    "sg:phone":"+1 561 792 7290",
    "sg:postcode":"33414",
    "sg:province":"FL",
    "sg:tags":[
        "taping"
    ],
    "wof:name":"Silver Beach Productions",
    "wof:placetype":"venue"
},
  "geometry": {"coordinates":[-80.270737,26.665239],"type":"Point"}
}