{
  "type": "Feature",
  "properties": {
    "iso:country":"US",
    "sg:address":"3320 W 23rd St",
    "sg:city":"Panama City",
    "sg:classifiers":[
        {
            "category":"Food & Beverages",
            "subcategory":"Specialty",
            "type":"Retail Goods"
        }
    ],
    "sg:phone":"+1 850 215 3388",
    "sg:postcode":"32405",
    "sg:province":"FL",
    "sg:tags":[
        "health",
        "diet"
    ],
    "wof:name":"Sonshine Natural Products Inc",
    "wof:placetype":"venue"
},
  "geometry": {"coordinates":[-85.705804,30.189846],"type":"Point"}
}