{
  "type": "Feature",
  "properties": {
    "addr:full":"1880 19th St SW Naples FL 34117",
    "addr:housenumber":"1880",
    "addr:postcode":"34117",
    "addr:street":"19Th St Sw",
    "iso:country":"US",
    "sg:address":"1880 19th St SW",
    "sg:city":"Naples",
    "sg:classifiers":[
        {
            "category":"Building & Trades",
            "subcategory":"Construction",
            "type":"Services"
        }
    ],
    "sg:phone":"+1 239 353 2321",
    "sg:postcode":"34117",
    "sg:province":"FL",
    "sg:tags":[
        "contractor"
    ],
    "wof:name":"Stone Edge Installations",
    "wof:placetype":"venue"
},
  "geometry": {"coordinates":[-81.644509,26.199657],"type":"Point"}
}