{
  "type": "Feature",
  "properties": {
    "addr:full":"2708 Airport Rd Plant City FL 33563",
    "addr:housenumber":"2708",
    "addr:postcode":"33563",
    "addr:street":"Airport Rd",
    "iso:country":"US",
    "sg:address":"2708 Airport Rd",
    "sg:city":"Plant City",
    "sg:classifiers":[
        {
            "category":"Building & Trades",
            "subcategory":"Construction",
            "type":"Services"
        }
    ],
    "sg:phone":"+1 813 754 8797",
    "sg:postcode":"33563",
    "sg:province":"FL",
    "sg:tags":[
        "maker",
        "cabinet"
    ],
    "wof:name":"Double S/S Cabinets",
    "wof:placetype":"venue"
},
  "geometry": {"coordinates":[-82.152101,28.003494],"type":"Point"}
}