{
  "type": "Feature",
  "properties": {
    "iso:country":"US",
    "sg:address":"3293 Newmark Dr",
    "sg:city":"Deltona",
    "sg:classifiers":[
        {
            "category":"Home & Garden",
            "subcategory":"Furniture",
            "type":"Retail Goods"
        }
    ],
    "sg:phone":"+1 386 216 6302",
    "sg:postcode":"32738",
    "sg:province":"FL",
    "sg:tags":[
        "mattress"
    ],
    "wof:name":"Diana R Pena",
    "wof:placetype":"venue"
},
  "geometry": {"coordinates":[-81.17101700000001,28.914272],"type":"Point"}
}