{
  "type": "Feature",
  "properties": {
    "addr:full":"800 N Federal Hwy Hollywood FL 33020",
    "addr:housenumber":"800",
    "addr:postcode":"33020",
    "addr:street":"N Federal Hwy",
    "iso:country":"US",
    "sg:address":"800 N Federal Hwy",
    "sg:city":"Hollywood",
    "sg:classifiers":[
        {
            "category":"Travel",
            "subcategory":"Hotels & Motels",
            "type":"Entertainment"
        }
    ],
    "sg:phone":"+1 954 922 3380",
    "sg:postcode":"33020",
    "sg:province":"FL",
    "sg:tags":[
        "operation"
    ],
    "wof:name":"Super Budget Motel",
    "wof:placetype":"venue"
},
  "geometry": {"coordinates":[-80.14330200000001,26.018922],"type":"Point"}
}