{
  "type": "Feature",
  "properties": {
    "iso:country":"US",
    "sg:address":"5017 Hiatus Rd",
    "sg:city":"Sunrise",
    "sg:classifiers":[
        {
            "category":"Building & Trades",
            "subcategory":"Equipment Rental",
            "type":"Services"
        }
    ],
    "sg:phone":"+1 954 318 1566",
    "sg:postcode":"33351",
    "sg:province":"FL",
    "sg:tags":[
        "leasing"
    ],
    "wof:name":"Baytree Leasing Co LLC",
    "wof:placetype":"venue"
},
  "geometry": {"coordinates":[-80.289472,26.189981],"type":"Point"}
}