{
  "type": "Feature",
  "properties": {
    "addr:full":"7331 Gum Tree Rd Jacksonville FL 32244",
    "addr:housenumber":"7331",
    "addr:postcode":"32244",
    "addr:street":"Gum Tree Rd",
    "iso:country":"US",
    "sg:address":"7331 Gum Tree Rd",
    "sg:city":"Jacksonville",
    "sg:classifiers":[
        {
            "category":"Building & Trades",
            "subcategory":"Landscaping Services",
            "type":"Services"
        },
        {
            "category":"Health Services",
            "subcategory":"Nursing And Care Facility",
            "type":"Services"
        }
    ],
    "sg:phone":"+1 904 573 2013",
    "sg:postcode":"32244",
    "sg:province":"FL",
    "sg:tags":[
        "personal",
        "home",
        "aged",
        "homes-institutional"
    ],
    "wof:name":"Resources For Human Development",
    "wof:placetype":"venue"
},
  "geometry": {"coordinates":[-81.766143,30.21834],"type":"Point"}
}