{
  "type": "Feature",
  "properties": {
    "iso:country":"US",
    "sg:address":"618 Sunrise Ave",
    "sg:city":"Winter Springs",
    "sg:classifiers":[
        {
            "category":"Professional",
            "subcategory":"Business Services",
            "type":"Services"
        },
        {
            "category":"Building & Trades",
            "subcategory":"Construction",
            "type":"Services"
        }
    ],
    "sg:phone":"+1 407 699 6803",
    "sg:postcode":"32708",
    "sg:province":"FL",
    "sg:tags":[
        "acoustical",
        "flooring",
        "contractor"
    ],
    "wof:name":"About Time Acoustics",
    "wof:placetype":"venue"
},
  "geometry": {"coordinates":[-81.292,28.677],"type":"Point"}
}