{
  "type": "Feature",
  "properties": {
    "addr:full":"4320 Cape San Blas Rd Port St Joe FL 32456",
    "addr:housenumber":"4320",
    "addr:postcode":"32456",
    "addr:street":"Cape San Blas Rd",
    "iso:country":"US",
    "sg:address":"4320 Cape San Blas Rd",
    "sg:city":"Port St Joe",
    "sg:classifiers":[
        {
            "category":"Real Estate",
            "subcategory":"Real Estate Agent",
            "type":"Services"
        }
    ],
    "sg:phone":"+1 850 227 2160",
    "sg:postcode":"32456",
    "sg:province":"FL",
    "wof:name":"Cape San Blas Realty Inc",
    "wof:placetype":"venue"
},
  "geometry": {"coordinates":[-85.37721999999999,29.70166],"type":"Point"}
}