{
  "type": "Feature",
  "properties": {
    "iso:country":"US",
    "sg:address":"7519 SE State Rd 26",
    "sg:city":"Trenton",
    "sg:classifiers":[
        {
            "category":"Building & Trades",
            "subcategory":"Plumbing",
            "type":"Services"
        }
    ],
    "sg:phone":"+1 352 472 4001",
    "sg:postcode":"32693",
    "sg:province":"FL",
    "sg:tags":[
        "conditioning",
        "air",
        "system",
        "contractor"
    ],
    "wof:name":"Allstate Mechanical Inc",
    "wof:placetype":"venue"
},
  "geometry": {"coordinates":[-82.67992599999999,29.637265],"type":"Point"}
}