{
  "type": "Feature",
  "properties": {
    "addr:full":"7831 NW 175th St Hialeah FL 33015",
    "addr:housenumber":"7831",
    "addr:postcode":"33015",
    "addr:street":"Nw 175Th St",
    "iso:country":"US",
    "sg:address":"7831 NW 175th St",
    "sg:city":"Hialeah",
    "sg:classifiers":[
        {
            "category":"Building & Trades",
            "subcategory":"Construction",
            "type":"Services"
        }
    ],
    "sg:phone":"+1 305 825 8511",
    "sg:postcode":"33015",
    "sg:province":"FL",
    "sg:tags":[
        "carpentry",
        "contractor"
    ],
    "wof:name":"D&H Group Inc",
    "wof:placetype":"venue"
},
  "geometry": {"coordinates":[-80.328408,25.932785],"type":"Point"}
}