{
  "type": "Feature",
  "properties": {
    "iso:country":"US",
    "sg:address":"11491 SW 109th Rd",
    "sg:city":"Miami",
    "sg:classifiers":[
        {
            "category":"Wholesale",
            "subcategory":"Electrical",
            "type":"Manufacturing & Wholesale Goods"
        }
    ],
    "sg:phone":"+1 305 596 6922",
    "sg:postcode":"33176",
    "sg:province":"FL",
    "sg:tags":[
        "alarm",
        "burglar",
        "system"
    ],
    "wof:name":"Alarm Service",
    "wof:placetype":"venue"
},
  "geometry": {"coordinates":[-80.380743,25.668695],"type":"Point"}
}