{
  "type": "Feature",
  "properties": {
    "addr:full":"5415 Collins Ave Miami Beach FL 33140",
    "addr:housenumber":"5415",
    "addr:postcode":"33140",
    "addr:street":"Collins Ave",
    "iso:country":"US",
    "sg:address":"5415 Collins Ave",
    "sg:city":"Miami Beach",
    "sg:classifiers":[
        {
            "category":"Real Estate",
            "subcategory":"Real Estate Agent",
            "type":"Services"
        }
    ],
    "sg:phone":"+1 305 866 6163",
    "sg:postcode":"33140",
    "sg:province":"FL",
    "wof:name":"Logan Katia Licensed RE Brk",
    "wof:placetype":"venue"
},
  "geometry": {"coordinates":[-80.122901,25.818863],"type":"Point"}
}