{
  "type": "Feature",
  "properties": {
    "addr:full":"661 E Altamonte Dr Altamonte Springs FL 32701",
    "addr:housenumber":"661",
    "addr:postcode":"32701",
    "addr:street":"E Altamonte Dr",
    "iso:country":"US",
    "sg:address":"661 E Altamonte Dr",
    "sg:city":"Altamonte Springs",
    "sg:classifiers":[
        {
            "category":"Health Services",
            "subcategory":"Doctor",
            "type":"Services"
        }
    ],
    "sg:phone":"+1 407 830 8661",
    "sg:postcode":"32701",
    "sg:province":"FL",
    "sg:tags":[
        "medical"
    ],
    "wof:name":"Straker Richard J MD",
    "wof:placetype":"venue"
},
  "geometry": {"coordinates":[-81.370332,28.663959],"type":"Point"}
}