{
  "type": "Feature",
  "properties": {
    "addr:full":"460 Bus Park Way Royal Palm Beach FL 33411",
    "addr:housenumber":"460",
    "addr:postcode":"33411",
    "addr:street":"Bus Park Way",
    "iso:country":"US",
    "sg:address":"460 Bus Park Way",
    "sg:city":"Royal Palm Beach",
    "sg:classifiers":[
        {
            "category":"Building & Trades",
            "subcategory":"Construction",
            "type":"Services"
        }
    ],
    "sg:phone":"+1 561 383 7330",
    "sg:postcode":"33411",
    "sg:province":"FL",
    "sg:tags":[
        "dry wall",
        "contractor"
    ],
    "wof:name":"Vast Drywall",
    "wof:placetype":"venue"
},
  "geometry": {"coordinates":[-80.204633,26.699369],"type":"Point"}
}