{
  "type": "Feature",
  "properties": {
    "iso:country":"US",
    "sg:address":"4200 SE 120th St",
    "sg:city":"Belleview",
    "sg:classifiers":[
        {
            "category":"Professional",
            "subcategory":"Engineering",
            "type":"Services"
        },
        {
            "category":"Professional",
            "subcategory":"Business Services",
            "type":"Services"
        }
    ],
    "sg:phone":"+1 352 245 4449",
    "sg:postcode":"34420",
    "sg:province":"FL",
    "sg:tags":[
        "consultant",
        "consulting",
        "coach",
        "engineer"
    ],
    "wof:name":"Banning Frank J Jr Consulting Engineer",
    "wof:placetype":"venue"
},
  "geometry": {"coordinates":[-82.07430100000001,29.04788],"type":"Point"}
}