{
  "type": "Feature",
  "properties": {
    "iso:country":"US",
    "sg:address":"13741 SW 90th Ave",
    "sg:city":"Miami",
    "sg:classifiers":[
        {
            "category":"Wholesale",
            "subcategory":"Non-durable Goods",
            "type":"Manufacturing & Wholesale Goods"
        }
    ],
    "sg:phone":"+1 305 235 7062",
    "sg:postcode":"33176",
    "sg:province":"FL",
    "wof:name":"Relentless Imports Inc",
    "wof:placetype":"venue"
},
  "geometry": {"coordinates":[-80.338973,25.636828],"type":"Point"}
}