{
  "type": "Feature",
  "properties": {
    "iso:country":"US",
    "sg:address":"4601 34th St",
    "sg:city":"Orlando",
    "sg:classifiers":[
        {
            "category":"Wholesale",
            "subcategory":"Non-durable Goods",
            "type":"Manufacturing & Wholesale Goods"
        }
    ],
    "sg:phone":"+1 407 841 7047",
    "sg:postcode":"32811",
    "sg:province":"FL",
    "sg:tags":[
        "item",
        "novelty",
        "gift"
    ],
    "wof:name":"Drewtina Global Sourcing LLC",
    "wof:placetype":"venue"
},
  "geometry": {"coordinates":[-81.43677700000001,28.505857],"type":"Point"}
}