{
  "type": "Feature",
  "properties": {
    "iso:country":"US",
    "sg:address":"5950 Sunset Dr",
    "sg:city":"South Miami",
    "sg:classifiers":[
        {
            "category":"Health Services",
            "subcategory":"Doctor",
            "type":"Services"
        }
    ],
    "sg:phone":"+1 305 661 3732",
    "sg:postcode":"33143",
    "sg:province":"FL",
    "wof:name":"Segal A James MD",
    "wof:placetype":"venue"
},
  "geometry": {"coordinates":[-80.290604,25.704399],"type":"Point"}
}