{
  "type": "Feature",
  "properties": {
    "addr:full":"5127 Recker Hwy Winter Haven FL 33880",
    "addr:housenumber":"5127",
    "addr:postcode":"33880",
    "addr:street":"Recker Hwy",
    "iso:country":"US",
    "sg:address":"5127 Recker Hwy",
    "sg:city":"Winter Haven",
    "sg:classifiers":[
        {
            "category":"Wholesale",
            "subcategory":"Machinery & Supplies",
            "type":"Manufacturing & Wholesale Goods"
        }
    ],
    "sg:phone":"+1 863 967 8551",
    "sg:postcode":"33880",
    "sg:province":"FL",
    "sg:tags":[
        "equipment",
        "industrial",
        "repair"
    ],
    "wof:name":"Florida Lift Systems",
    "wof:placetype":"venue"
},
  "geometry": {"coordinates":[-81.77844,27.973076],"type":"Point"}
}