{
  "type": "Feature",
  "properties": {
    "iso:country":"US",
    "sg:address":"600 Biltmore Way",
    "sg:city":"Coral Gables",
    "sg:classifiers":[
        {
            "category":"Professional",
            "subcategory":"Lawyer & Legal Services",
            "type":"Services"
        }
    ],
    "sg:phone":"+1 305 461 4050",
    "sg:postcode":"33134",
    "sg:province":"FL",
    "sg:tags":[
        "attorney"
    ],
    "wof:name":"Richard H Hunt & Assoc",
    "wof:placetype":"venue"
},
  "geometry": {"coordinates":[-80.268804,25.74803],"type":"Point"}
}