{
  "type": "Feature",
  "properties": {
    "iso:country":"US",
    "sg:address":"317 Racetrack Rd NE",
    "sg:city":"Fort Walton Bch",
    "sg:classifiers":[
        {
            "category":"Real Estate",
            "subcategory":"Real Estate Operator",
            "type":"Services"
        }
    ],
    "sg:phone":"+1 850 864 1300",
    "sg:postcode":"32547",
    "sg:province":"FL",
    "sg:tags":[
        "apartment"
    ],
    "wof:name":"Cheze Elan Fine Apartments",
    "wof:placetype":"venue"
},
  "geometry": {"coordinates":[-86.60397399999999,30.444395],"type":"Point"}
}