{
  "type": "Feature",
  "properties": {
    "addr:full":"4965 SW 74th Ct Miami FL 33155",
    "addr:housenumber":"4965",
    "addr:postcode":"33155",
    "addr:street":"Sw 74Th Ct",
    "iso:country":"US",
    "sg:address":"4965 SW 74th Ct",
    "sg:city":"Miami",
    "sg:classifiers":[
        {
            "category":"Professional",
            "subcategory":"Engineering",
            "type":"Services"
        }
    ],
    "sg:phone":"+1 305 669 3211",
    "sg:postcode":"33155",
    "sg:province":"FL",
    "sg:tags":[
        "architect",
        "naval"
    ],
    "wof:name":"Arthur M Barbeito & Assoc Inc",
    "wof:placetype":"venue"
},
  "geometry": {"coordinates":[-80.315128,25.724083],"type":"Point"}
}