{
  "type": "Feature",
  "properties": {
    "iso:country":"US",
    "sg:address":"7908 W Dunnellon Rd",
    "sg:city":"Dunnellon",
    "sg:classifiers":[
        {
            "category":"Retail",
            "subcategory":"Auto Repair",
            "type":"Services"
        }
    ],
    "sg:phone":"+1 352 564 8898",
    "sg:postcode":"34433",
    "sg:province":"FL",
    "sg:tags":[
        "repairing",
        "automobile"
    ],
    "wof:name":"All Fleet Svc Of Citrus County",
    "wof:placetype":"venue"
},
  "geometry": {"coordinates":[-82.56486200000001,29.010602],"type":"Point"}
}