{
  "type": "Feature",
  "properties": {
    "addr:full":"4241 Palm Ln Miami FL 33137",
    "addr:housenumber":"4241",
    "addr:postcode":"33137",
    "addr:street":"Palm Ln",
    "iso:country":"US",
    "sg:address":"4241 Palm Ln",
    "sg:city":"Miami",
    "sg:classifiers":[
        {
            "category":"Building & Trades",
            "subcategory":"Construction",
            "type":"Services"
        }
    ],
    "sg:phone":"+1 305 576 6840",
    "sg:postcode":"33137",
    "sg:province":"FL",
    "sg:tags":[
        "commercial",
        "entertainment"
    ],
    "wof:name":"J E Gamas Construction Company",
    "wof:placetype":"venue"
},
  "geometry": {"coordinates":[-80.182506,25.817969],"type":"Point"}
}