{
  "type": "Feature",
  "properties": {
    "addr:full":"6113 Town Colony Dr Boca Raton FL 33433",
    "addr:housenumber":"6113",
    "addr:postcode":"33433",
    "addr:street":"Town Colony Dr",
    "iso:country":"US",
    "sg:address":"6113 Town Colony Dr",
    "sg:city":"Boca Raton",
    "sg:classifiers":[
        {
            "category":"Professional",
            "type":"Services"
        }
    ],
    "sg:phone":"+1 561 487 3983",
    "sg:postcode":"33433",
    "sg:province":"FL",
    "sg:tags":[
        "establishment"
    ],
    "wof:name":"Hyna Limited Inc",
    "wof:placetype":"venue"
},
  "geometry": {"coordinates":[-80.138745,26.364222],"type":"Point"}
}