{
  "type": "Feature",
  "properties": {
    "addr:full":"10131 San Jose Blvd Jacksonville FL 32257",
    "addr:housenumber":"10131",
    "addr:postcode":"32257",
    "addr:street":"San Jose Blvd",
    "iso:country":"US",
    "sg:address":"10131 San Jose Blvd",
    "sg:city":"Jacksonville",
    "sg:classifiers":[
        {
            "category":"Fast Food",
            "type":"Food & Drink"
        },
        {
            "category":"Restaurant",
            "type":"Food & Drink"
        },
        {
            "category":"Food & Beverages",
            "subcategory":"Groceries & Convenience Stores",
            "type":"Retail Goods"
        }
    ],
    "sg:phone":"+1 904 886 2179",
    "sg:postcode":"32257",
    "sg:province":"FL",
    "sg:tags":[
        "shop",
        "sandwich",
        "take"
    ],
    "sg:website":"http://www.firehousesubs.com/",
    "wof:name":"Firehouse Subs",
    "wof:placetype":"venue"
},
  "geometry": {"coordinates":[-81.62449100000001,30.193196],"type":"Point"}
}