{
  "type": "Feature",
  "properties": {
    "addr:full":"1604 Capital Cir NE Tallahassee FL 32308",
    "addr:housenumber":"1604",
    "addr:postcode":"32308",
    "addr:street":"Capital Cir Ne",
    "iso:country":"US",
    "sg:address":"1604 Capital Cir NE",
    "sg:city":"Tallahassee",
    "sg:classifiers":[
        {
            "category":"Home & Garden",
            "subcategory":"Household Appliances",
            "type":"Retail Goods"
        },
        {
            "category":"Home & Garden",
            "subcategory":"Home Furnishings",
            "type":"Retail Goods"
        },
        {
            "category":"Wholesale",
            "subcategory":"Construction Materials",
            "type":"Manufacturing & Wholesale Goods"
        },
        {
            "category":"Wholesale",
            "subcategory":"Home Furnishings",
            "type":"Manufacturing & Wholesale Goods"
        }
    ],
    "sg:phone":"+1 850 942 5222",
    "sg:postcode":"32308",
    "sg:province":"FL",
    "sg:tags":[
        "major",
        "supply",
        "fixture",
        "part",
        "lighting",
        "plumbing",
        "fixtures",
        "supplies-wholesale",
        "manufacturer"
    ],
    "sg:website":"http://www.ferguson.com/homeowner.shtml",
    "wof:name":"Ferguson Bath, Kitchen & Lighting Gallery",
    "wof:placetype":"venue"
},
  "geometry": {"coordinates":[-84.228099,30.460455],"type":"Point"}
}