{
  "type": "Feature",
  "properties": {
    "iso:country":"US",
    "sg:address":"1202 6th St NW",
    "sg:city":"Winter Haven",
    "sg:classifiers":[
        {
            "category":"Autos & Motor Vehicles",
            "subcategory":"Fuel & Gas Station",
            "type":"Retail Goods"
        }
    ],
    "sg:phone":"+1 863 294 1997",
    "sg:postcode":"33881",
    "sg:province":"FL",
    "sg:tags":[
        "grocery",
        "station",
        "gasoline"
    ],
    "wof:name":"Sunoco",
    "wof:placetype":"venue"
},
  "geometry": {"coordinates":[-81.733054,28.035742],"type":"Point"}
}