{
  "type": "Feature",
  "properties": {
    "iso:country":"US",
    "sg:address":"4811 Gulf Blvd",
    "sg:city":"St Pete Beach",
    "sg:classifiers":[
        {
            "category":"Banks & Credit Unions",
            "subcategory":"Bank",
            "type":"Services"
        }
    ],
    "sg:phone":"+1 727 000 1111",
    "sg:postcode":"33706",
    "sg:province":"FL",
    "wof:name":"AM South Bank",
    "wof:placetype":"venue"
},
  "geometry": {"coordinates":[-82.740189,27.722037],"type":"Point"}
}