{
  "type": "Feature",
  "properties": {
    "addr:full":"70 Emerald Woods Dr Naples FL 34108",
    "addr:housenumber":"70",
    "addr:postcode":"34108",
    "addr:street":"Emerald Woods Dr",
    "iso:country":"US",
    "sg:address":"70 Emerald Woods Dr",
    "sg:city":"Naples",
    "sg:classifiers":[
        {
            "category":"Shopping",
            "subcategory":"Computers & Home Electronics",
            "type":"Retail Goods"
        }
    ],
    "sg:phone":"+1 239 513 1459",
    "sg:postcode":"34108",
    "sg:province":"FL",
    "wof:name":"Tim Jones Computers",
    "wof:placetype":"venue"
},
  "geometry": {"coordinates":[-81.798524,26.246134],"type":"Point"}
}