{
  "type": "Feature",
  "properties": {
    "addr:full":"841 Hemlock Dr Apopka FL 32712",
    "addr:housenumber":"841",
    "addr:postcode":"32712",
    "addr:street":"Hemlock Dr",
    "iso:country":"US",
    "sg:address":"841 Hemlock Dr",
    "sg:city":"Apopka",
    "sg:classifiers":[
        {
            "category":"Home & Garden",
            "subcategory":"Garden Supply",
            "type":"Retail Goods"
        },
        {
            "category":"Farming",
            "subcategory":"Nursery",
            "type":"Manufacturing & Wholesale Goods"
        }
    ],
    "sg:phone":"+1 407 889 4001",
    "sg:postcode":"32712",
    "sg:province":"FL",
    "sg:tags":[
        "plant",
        "grower",
        "nursery-wholesale"
    ],
    "wof:name":"Cooks Nursery Inc",
    "wof:placetype":"venue"
},
  "geometry": {"coordinates":[-81.47305900000001,28.695438],"type":"Point"}
}