{
  "type": "Feature",
  "properties": {
    "iso:country":"US",
    "sg:address":"4600 Summerlin Rd Ste C12",
    "sg:city":"Fort Myers",
    "sg:classifiers":[
        {
            "category":"Food & Beverages",
            "subcategory":"Bakery",
            "type":"Retail Goods"
        }
    ],
    "sg:phone":"+1 239 936 6622",
    "sg:postcode":"33919",
    "sg:province":"FL",
    "sg:tags":[
        "sandwich"
    ],
    "wof:name":"Philly Junction",
    "wof:placetype":"venue"
},
  "geometry": {"coordinates":[-81.884179,26.59588],"type":"Point"}
}