{
  "type": "Feature",
  "properties": {
    "iso:country":"US",
    "sg:address":"3706 US Hwy 19",
    "sg:city":"New Port Richey",
    "sg:classifiers":[
        {
            "category":"Autos & Motor Vehicles",
            "subcategory":"Automobile Sales",
            "type":"Retail Goods"
        }
    ],
    "sg:phone":"+1 727 845 1479",
    "sg:postcode":"34652",
    "sg:province":"FL",
    "sg:tags":[
        "used"
    ],
    "wof:name":"Highland Auto Sales Inc",
    "wof:placetype":"venue"
},
  "geometry": {"coordinates":[-82.739493,28.209785],"type":"Point"}
}