{
  "type": "Feature",
  "properties": {
    "iso:country":"US",
    "sg:address":"6401 Sheridan St",
    "sg:city":"Hollywood",
    "sg:classifiers":[
        {
            "category":"Restaurant",
            "type":"Food & Drink"
        }
    ],
    "sg:phone":"+1 954 966 8800",
    "sg:postcode":"33024",
    "sg:province":"FL",
    "wof:name":"Cony Island Joe's",
    "wof:placetype":"venue"
},
  "geometry": {"coordinates":[-80.220777,26.03186],"type":"Point"}
}