{
  "type": "Feature",
  "properties": {
    "addr:full":"2860 W Michigan Ave Pensacola FL 32526",
    "addr:housenumber":"2860",
    "addr:postcode":"32526",
    "addr:street":"W Michigan Ave",
    "iso:country":"US",
    "sg:address":"2860 W Michigan Ave",
    "sg:city":"Pensacola",
    "sg:classifiers":[
        {
            "category":"Food & Beverages",
            "subcategory":"Groceries & Convenience Stores",
            "type":"Retail Goods"
        }
    ],
    "sg:phone":"+1 850 941 2561",
    "sg:postcode":"32526",
    "sg:province":"FL",
    "wof:name":"Tillion Corporation",
    "wof:placetype":"venue"
},
  "geometry": {"coordinates":[-87.291364,30.460986],"type":"Point"}
}