{
  "type": "Feature",
  "properties": {
    "iso:country":"US",
    "sg:address":"6505 85th Ave",
    "sg:city":"Pinellas Park",
    "sg:classifiers":[
        {
            "category":"Professional",
            "subcategory":"Business Services",
            "type":"Services"
        }
    ],
    "sg:phone":"+1 727 544 1051",
    "sg:postcode":"33781",
    "sg:province":"FL",
    "sg:tags":[
        "cemetery"
    ],
    "wof:name":"Pinellas Memorial Pet Cemetery",
    "wof:placetype":"venue"
},
  "geometry": {"coordinates":[-82.728617,27.84927],"type":"Point"}
}