{
  "type": "Feature",
  "properties": {
    "iso:country":"US",
    "sg:address":"2511 NE 12th Ct",
    "sg:city":"Pompano Beach",
    "sg:classifiers":[
        {
            "category":"Building & Trades",
            "subcategory":"Construction",
            "type":"Services"
        }
    ],
    "sg:phone":"+1 954 782 7276",
    "sg:postcode":"33062",
    "sg:province":"FL",
    "sg:tags":[
        "concrete",
        "contractor"
    ],
    "wof:name":"Chariot Concrete",
    "wof:placetype":"venue"
},
  "geometry": {"coordinates":[-80.097802,26.247672],"type":"Point"}
}