{
  "type": "Feature",
  "properties": {
    "addr:full":"2570 N Courtenay Pkwy Merritt Island FL 32953",
    "addr:housenumber":"2570",
    "addr:postcode":"32953",
    "addr:street":"N Courtenay Pkwy",
    "iso:country":"US",
    "sg:address":"2570 N Courtenay Pkwy",
    "sg:city":"Merritt Island",
    "sg:classifiers":[
        {
            "category":"Autos & Motor Vehicles",
            "subcategory":"Fuel & Gas Station",
            "type":"Retail Goods"
        }
    ],
    "sg:phone":"+1 321 449 9663",
    "sg:postcode":"32953",
    "sg:province":"FL",
    "sg:website":"www.racetrac.com",
    "wof:name":"Racetrac Petroleum Inc",
    "wof:placetype":"venue"
},
  "geometry": {"coordinates":[-80.705399,28.4025],"type":"Point"}
}