{
  "type": "Feature",
  "properties": {
    "addr:full":"2600 Doc Durrance Rd Bradley FL 33860",
    "addr:housenumber":"2600",
    "addr:postcode":"33860",
    "addr:street":"Doc Durrance Rd",
    "iso:country":"US",
    "sg:address":"2600 Doc Durrance Rd",
    "sg:city":"Bradley",
    "sg:classifiers":[
        {
            "category":"Manufacturing",
            "subcategory":"Chemicals & Compounds",
            "type":"Manufacturing & Wholesale Goods"
        }
    ],
    "sg:phone":"+1 863 428 1404",
    "sg:postcode":"33860",
    "sg:province":"FL",
    "sg:tags":[
        "mineral"
    ],
    "wof:name":"IMC",
    "wof:placetype":"venue"
},
  "geometry": {"coordinates":[-82.024956,27.795787],"type":"Point"}
}