{
  "type": "Feature",
  "properties": {
    "iso:country":"US",
    "sg:address":"2983 Ravenswood Rd",
    "sg:city":"Fort Lauderdale",
    "sg:classifiers":[
        {
            "category":"Restaurant",
            "type":"Food & Drink"
        }
    ],
    "sg:phone":"+1 877 667 9377",
    "sg:postcode":"33312",
    "sg:province":"FL",
    "sg:tags":[
        "eating"
    ],
    "wof:name":"Twistee Treat Corp",
    "wof:placetype":"venue"
},
  "geometry": {"coordinates":[-80.17106,26.084223],"type":"Point"}
}