{
  "type": "Feature",
  "properties": {
    "iso:country":"US",
    "sg:address":"10647 4th Ave",
    "sg:city":"Ocoee",
    "sg:classifiers":[
        {
            "category":"Building & Trades",
            "subcategory":"Construction",
            "type":"Services"
        }
    ],
    "sg:phone":"+1 407 822 3500",
    "sg:postcode":"34761",
    "sg:province":"FL",
    "sg:tags":[
        "contractor"
    ],
    "wof:name":"All Purpose Drywall Systems",
    "wof:placetype":"venue"
},
  "geometry": {"coordinates":[-81.53729800000001,28.596285],"type":"Point"}
}