{
  "type": "Feature",
  "properties": {
    "iso:country":"US",
    "sg:address":"531 N Maitland Ave",
    "sg:city":"Maitland",
    "sg:classifiers":[
        {
            "category":"Health Services",
            "subcategory":"Doctor",
            "type":"Services"
        }
    ],
    "sg:phone":"+1 321 397 1212",
    "sg:postcode":"32751",
    "sg:province":"FL",
    "sg:tags":[
        "obstetrician",
        "gynecologist"
    ],
    "sg:website":"www.liposelectiondoctor.com",
    "wof:name":"Premier Obstetrics & Gynecology of Orlando PA",
    "wof:placetype":"venue"
},
  "geometry": {"coordinates":[-81.365799,28.631701],"type":"Point"}
}