{
  "type": "Feature",
  "properties": {
    "iso:country":"US",
    "sg:address":"8403 NW 68th St",
    "sg:city":"Miami",
    "sg:classifiers":[
        {
            "category":"Professional",
            "subcategory":"Research",
            "type":"Services"
        }
    ],
    "sg:phone":"+1 786 845 9717",
    "sg:postcode":"33166",
    "sg:province":"FL",
    "sg:tags":[
        "commercial",
        "physical"
    ],
    "wof:name":"Bioquem Corp",
    "wof:placetype":"venue"
},
  "geometry": {"coordinates":[-80.338007,25.835316],"type":"Point"}
}