{
  "type": "Feature",
  "properties": {
    "addr:full":"7384 Lawn Tennis Ln Jacksonville FL 32277",
    "addr:housenumber":"7384",
    "addr:postcode":"32277",
    "addr:street":"Tennis Ln",
    "iso:country":"US",
    "sg:address":"7384 Lawn Tennis Ln",
    "sg:city":"Jacksonville",
    "sg:classifiers":[
        {
            "category":"Shopping",
            "subcategory":"Clothing, Apparel, & Fashions",
            "type":"Retail Goods"
        }
    ],
    "sg:phone":"+1 904 744 2710",
    "sg:postcode":"32277",
    "sg:province":"FL",
    "wof:name":"Jeracu Kids Dress",
    "wof:placetype":"venue"
},
  "geometry": {"coordinates":[-81.56946000000001,30.362609],"type":"Point"}
}