{
  "type": "Feature",
  "properties": {
    "addr:full":"58 Main St Panama City FL 32413",
    "addr:housenumber":"58",
    "addr:postcode":"32413",
    "addr:street":"Main St",
    "iso:country":"US",
    "sg:address":"58 Main St",
    "sg:city":"Panama City",
    "sg:classifiers":[
        {
            "category":"Home & Garden",
            "subcategory":"Furniture",
            "type":"Retail Goods"
        }
    ],
    "sg:phone":"+1 850 231 4164",
    "sg:postcode":"32413",
    "sg:province":"FL",
    "wof:name":"Shabby Slips",
    "wof:placetype":"venue"
},
  "geometry": {"coordinates":[-86.01619700000001,30.279753],"type":"Point"}
}