{
  "type": "Feature",
  "properties": {
    "iso:country":"US",
    "sg:address":"11497 Deep Creek Dr",
    "sg:city":"Spring Hill",
    "sg:classifiers":[
        {
            "category":"Retail",
            "subcategory":"Repair Shop",
            "type":"Services"
        }
    ],
    "sg:phone":"+1 352 688 9978",
    "sg:postcode":"34609",
    "sg:province":"FL",
    "wof:name":"Don & Ryan Grill Taxidermists",
    "wof:placetype":"venue"
},
  "geometry": {"coordinates":[-82.531401,28.459478],"type":"Point"}
}