{
  "type": "Feature",
  "properties": {
    "iso:country":"US",
    "sg:address":"4651 Salisbury Rd Ste 320",
    "sg:city":"Jacksonville",
    "sg:classifiers":[
        {
            "category":"Banks & Credit Unions",
            "subcategory":"Financial Services",
            "type":"Services"
        }
    ],
    "sg:phone":"+1 904 296 8635",
    "sg:postcode":"32256",
    "sg:province":"FL",
    "sg:tags":[
        "sharing",
        "profit",
        "annuity",
        "retirement",
        "planning",
        "plan",
        "insurance",
        "pension"
    ],
    "wof:name":"Manulife Financial Savings & Retirement",
    "wof:placetype":"venue"
},
  "geometry": {"coordinates":[-81.588171,30.247643],"type":"Point"}
}