{
  "type": "Feature",
  "properties": {
    "addr:full":"4141 Bay Beach Ln Fort Myers Beach FL 33931",
    "addr:housenumber":"4141",
    "addr:postcode":"33931",
    "addr:street":"Bay Beach Ln",
    "iso:country":"US",
    "sg:address":"4141 Bay Beach Ln",
    "sg:city":"Fort Myers Beach",
    "sg:classifiers":[
        {
            "category":"Building & Trades",
            "subcategory":"Construction",
            "type":"Services"
        }
    ],
    "sg:phone":"+1 239 765 0021",
    "sg:postcode":"33931",
    "sg:province":"FL",
    "sg:tags":[
        "elevator"
    ],
    "wof:name":"Waterside Iv Elevator",
    "wof:placetype":"venue"
},
  "geometry": {"coordinates":[-81.891436,26.410657],"type":"Point"}
}