{
  "type": "Feature",
  "properties": {
    "iso:country":"US",
    "sg:address":"12217 S Dixie Hwy",
    "sg:city":"Miami",
    "sg:classifiers":[
        {
            "category":"Shopping",
            "subcategory":"Jewelry",
            "type":"Retail Goods"
        }
    ],
    "sg:phone":"+1 305 278 7770",
    "sg:postcode":"33156",
    "sg:province":"FL",
    "wof:name":"Seb's Fashions Inc",
    "wof:placetype":"venue"
},
  "geometry": {"coordinates":[-80.327797,25.657],"type":"Point"}
}