{
  "type": "Feature",
  "properties": {
    "iso:country":"US",
    "sg:address":"1220 N University Dr",
    "sg:city":"Fort Lauderdale",
    "sg:classifiers":[
        {
            "category":"Health Services",
            "subcategory":"Health Practitioner",
            "type":"Services"
        }
    ],
    "sg:phone":"+1 954 370 7802",
    "sg:postcode":"33322",
    "sg:province":"FL",
    "wof:name":"Ellen Edd Gertz",
    "wof:placetype":"venue"
},
  "geometry": {"coordinates":[-80.25305,26.247548],"type":"Point"}
}