{
  "type": "Feature",
  "properties": {
    "iso:country":"US",
    "sg:address":"5017 Log Cabin Dr",
    "sg:city":"Lakeland",
    "sg:classifiers":[
        {
            "category":"Professional",
            "subcategory":"Computer Services",
            "type":"Services"
        }
    ],
    "sg:phone":"+1 863 687 9040",
    "sg:postcode":"33810",
    "sg:province":"FL",
    "sg:tags":[
        "development",
        "application",
        "software"
    ],
    "wof:name":"Black Cypress Inc",
    "wof:placetype":"venue"
},
  "geometry": {"coordinates":[-82.04003299999999,28.065213],"type":"Point"}
}