{
  "type": "Feature",
  "properties": {
    "iso:country":"US",
    "sg:address":"1670 NW 122nd St",
    "sg:city":"Miami",
    "sg:classifiers":[
        {
            "category":"Manufacturing",
            "subcategory":"Retail Goods",
            "type":"Manufacturing & Wholesale Goods"
        }
    ],
    "sg:phone":"+1 305 687 4755",
    "sg:postcode":"33167",
    "sg:province":"FL",
    "sg:tags":[
        "product",
        "mfg"
    ],
    "wof:name":"Allusize Inzuszla",
    "wof:placetype":"venue"
},
  "geometry": {"coordinates":[-80.225539,25.885817],"type":"Point"}
}