{
  "type": "Feature",
  "properties": {
    "iso:country":"US",
    "sg:address":"2855 NW 112th Ave",
    "sg:city":"Doral",
    "sg:classifiers":[
        {
            "category":"Wholesale",
            "subcategory":"Machinery & Supplies",
            "type":"Manufacturing & Wholesale Goods"
        }
    ],
    "sg:phone":"+1 305 463 8393",
    "sg:postcode":"33172",
    "sg:province":"FL",
    "sg:tags":[
        "equipment",
        "to",
        "safety",
        "wholesaler",
        "distributes",
        "clothing"
    ],
    "wof:name":"More Than Safety",
    "wof:placetype":"venue"
},
  "geometry": {"coordinates":[-80.377184,25.798769],"type":"Point"}
}