{
  "type": "Feature",
  "properties": {
    "iso:country":"US",
    "sg:address":"21201 Bassett Ave",
    "sg:city":"Port Charlotte",
    "sg:classifiers":[
        {
            "category":"Education",
            "subcategory":"Vocational School",
            "type":"Public Place"
        }
    ],
    "sg:phone":"+1 941 255 3700",
    "sg:postcode":"33952",
    "sg:province":"FL",
    "sg:tags":[
        "technical",
        "trade"
    ],
    "wof:name":"Target Training Systems",
    "wof:placetype":"venue"
},
  "geometry": {"coordinates":[-82.10072599999999,27.010885],"type":"Point"}
}