{
  "type": "Feature",
  "properties": {
    "addr:full":"4708 26th St W Bradenton FL 34207",
    "addr:housenumber":"4708",
    "addr:postcode":"34207",
    "addr:street":"26Th St W",
    "iso:country":"US",
    "sg:address":"4708 26th St W",
    "sg:city":"Bradenton",
    "sg:classifiers":[
        {
            "category":"Health Services",
            "subcategory":"Doctor",
            "type":"Services"
        }
    ],
    "sg:phone":"+1 941 758 4543",
    "sg:postcode":"34207",
    "sg:province":"FL",
    "sg:tags":[
        "dentist"
    ],
    "wof:name":"Family Dental Inc",
    "wof:placetype":"venue"
},
  "geometry": {"coordinates":[-82.587692,27.456307],"type":"Point"}
}