{
  "type": "Feature",
  "properties": {
    "iso:country":"US",
    "sg:address":"405 Anastasia Blvd",
    "sg:city":"St Augustine",
    "sg:classifiers":[
        {
            "category":"Retail",
            "subcategory":"Self-service Laundry",
            "type":"Services"
        },
        {
            "category":"Retail",
            "subcategory":"Laundry & Dry Cleaning",
            "type":"Services"
        }
    ],
    "sg:phone":"+1 904 824 4262",
    "sg:postcode":"32080",
    "sg:province":"FL",
    "sg:tags":[
        "coin"
    ],
    "wof:name":"Laundry Room",
    "wof:placetype":"venue"
},
  "geometry": {"coordinates":[-81.29749099999999,29.890959],"type":"Point"}
}