{
  "type": "Feature",
  "properties": {
    "iso:country":"US",
    "sg:address":"200 Wildwood Dr",
    "sg:city":"Port St Joe",
    "sg:classifiers":[
        {
            "category":"Building & Trades",
            "subcategory":"Construction",
            "type":"Services"
        }
    ],
    "sg:phone":"+1 850 648 5781",
    "sg:postcode":"32404",
    "sg:province":"FL",
    "sg:tags":[
        "excavating",
        "contractor"
    ],
    "wof:name":"Butler Backhoe & Tractor",
    "wof:placetype":"venue"
},
  "geometry": {"coordinates":[-85.50922199999999,30.139823],"type":"Point"}
}