{
  "type": "Feature",
  "properties": {
    "iso:country":"US",
    "sg:address":"3345 NW South River Dr",
    "sg:city":"Miami",
    "sg:classifiers":[
        {
            "category":"Marine",
            "type":"Transportation"
        }
    ],
    "sg:phone":"+1 305 635 1727",
    "sg:postcode":"33142",
    "sg:province":"FL",
    "sg:tags":[
        "water",
        "salvage",
        "transport"
    ],
    "wof:name":"Byrd Commercial Diving Inc",
    "wof:placetype":"venue"
},
  "geometry": {"coordinates":[-80.249309,25.798246],"type":"Point"}
}