{
  "type": "Feature",
  "properties": {
    "iso:country":"US",
    "sg:address":"308 Oceanside Ct",
    "sg:city":"Kissimmee",
    "sg:classifiers":[
        {
            "category":"Building & Trades",
            "subcategory":"Landscaping Services",
            "type":"Services"
        }
    ],
    "sg:phone":"+1 407 319 2680",
    "sg:postcode":"34743",
    "sg:province":"FL",
    "sg:tags":[
        "lawn",
        "maintenance",
        "grounds"
    ],
    "wof:name":"John Nazario Lawn Care",
    "wof:placetype":"venue"
},
  "geometry": {"coordinates":[-81.36943100000001,28.346931],"type":"Point"}
}