{
  "type": "Feature",
  "properties": {
    "iso:country":"US",
    "sg:address":"2840 NE 24th Ct",
    "sg:city":"Fort Lauderdale",
    "sg:classifiers":[
        {
            "category":"Professional",
            "subcategory":"Management & Consulting",
            "type":"Services"
        }
    ],
    "sg:phone":"+1 954 561 9852",
    "sg:postcode":"33305",
    "sg:province":"FL",
    "sg:tags":[
        "consultant",
        "business"
    ],
    "wof:name":"Serka International Corp",
    "wof:placetype":"venue"
},
  "geometry": {"coordinates":[-80.10698600000001,26.155953],"type":"Point"}
}