{
  "type": "Feature",
  "properties": {
    "iso:country":"US",
    "sg:address":"12019 NW 136th St",
    "sg:city":"Alachua",
    "sg:classifiers":[
        {
            "category":"Building & Trades",
            "subcategory":"Landscaping Services",
            "type":"Services"
        }
    ],
    "sg:phone":"+1 386 462 1090",
    "sg:postcode":"32615",
    "sg:province":"FL",
    "sg:tags":[
        "lawn",
        "landscape",
        "contractor"
    ],
    "wof:name":"Alca Assoc Landscape Contracto",
    "wof:placetype":"venue"
},
  "geometry": {"coordinates":[-82.489057,29.762821],"type":"Point"}
}