{
  "type": "Feature",
  "properties": {
    "addr:full":"9771 Dixie Hwy Miami FL 33156",
    "addr:housenumber":"9771",
    "addr:postcode":"33156",
    "addr:street":"Dixie Hwy",
    "iso:country":"US",
    "sg:address":"9771 Dixie Hwy",
    "sg:city":"Miami",
    "sg:classifiers":[
        {
            "category":"Real Estate",
            "subcategory":"Developer",
            "type":"Services"
        }
    ],
    "sg:phone":"+1 305 665 4275",
    "sg:postcode":"33156",
    "sg:province":"FL",
    "sg:tags":[
        "development"
    ],
    "wof:name":"Hollub Construction Group",
    "wof:placetype":"venue"
},
  "geometry": {"coordinates":[-80.31650999999999,25.680471],"type":"Point"}
}