{
  "type": "Feature",
  "properties": {
    "addr:full":"20650 SW 177th Ave Miami FL 33187",
    "addr:housenumber":"20650",
    "addr:postcode":"33187",
    "addr:street":"Sw 177Th Ave",
    "iso:country":"US",
    "sg:address":"20650 SW 177th Ave",
    "sg:city":"Miami",
    "sg:classifiers":[
        {
            "category":"Home & Garden",
            "subcategory":"Garden Supply",
            "type":"Retail Goods"
        }
    ],
    "sg:phone":"+1 305 962 4864",
    "sg:postcode":"33187",
    "sg:province":"FL",
    "sg:tags":[
        "nurseryman"
    ],
    "wof:name":"Happy Green Nursery",
    "wof:placetype":"venue"
},
  "geometry": {"coordinates":[-80.47835499999999,25.572877],"type":"Point"}
}