{
  "type": "Feature",
  "properties": {
    "iso:country":"US",
    "sg:address":"16155 SW 117th Ave Bay 24",
    "sg:city":"Miami",
    "sg:classifiers":[
        {
            "category":"Building & Trades",
            "subcategory":"Landscaping Services",
            "type":"Services"
        }
    ],
    "sg:phone":"+1 786 242 9701",
    "sg:postcode":"33177",
    "sg:province":"FL",
    "sg:tags":[
        "arborist",
        "tree"
    ],
    "wof:name":"Tropical Trees & Maintenance Corp.",
    "wof:placetype":"venue"
},
  "geometry": {"coordinates":[-80.38188599999999,25.618002],"type":"Point"}
}