{
  "type": "Feature",
  "properties": {
    "addr:full":"1070 NW 106th St Miami FL 33150",
    "addr:housenumber":"1070",
    "addr:postcode":"33150",
    "addr:street":"Nw 106Th St",
    "iso:country":"US",
    "sg:address":"1070 NW 106th St",
    "sg:city":"Miami",
    "sg:classifiers":[
        {
            "category":"Retail",
            "subcategory":"Portrait Studio",
            "type":"Services"
        },
        {
            "category":"Professional",
            "subcategory":"Art Services",
            "type":"Services"
        }
    ],
    "sg:phone":"+1 305 836 6797",
    "sg:postcode":"33150",
    "sg:province":"FL",
    "sg:tags":[
        "rental",
        "photographers-portrait",
        "photographic",
        "darkroom"
    ],
    "wof:name":"Ed Robinson Photography",
    "wof:placetype":"venue"
},
  "geometry": {"coordinates":[-80.21553400000001,25.871723],"type":"Point"}
}