{
  "type": "Feature",
  "properties": {
    "addr:full":"845 Norman Ct Longwood FL 32750",
    "addr:housenumber":"845",
    "addr:postcode":"32750",
    "addr:street":"Norman Ct",
    "iso:country":"US",
    "sg:address":"845 Norman Ct",
    "sg:city":"Longwood",
    "sg:classifiers":[
        {
            "category":"Personal",
            "subcategory":"Beauty Salon",
            "type":"Services"
        }
    ],
    "sg:phone":"+1 407 260 9842",
    "sg:postcode":"32750",
    "sg:province":"FL",
    "sg:tags":[
        "shop"
    ],
    "wof:name":"Cosmopolitan Salon & Beauty Su",
    "wof:placetype":"venue"
},
  "geometry": {"coordinates":[-81.316371,28.728588],"type":"Point"}
}