{
  "type": "Feature",
  "properties": {
    "addr:full":"1447 Thomasville Rd Tallahassee FL 32303",
    "addr:housenumber":"1447",
    "addr:postcode":"32303",
    "addr:street":"Thomasville Rd",
    "iso:country":"US",
    "sg:address":"1447 Thomasville Rd",
    "sg:city":"Tallahassee",
    "sg:classifiers":[
        {
            "category":"Personal",
            "subcategory":"Beauty Salon",
            "type":"Services"
        }
    ],
    "sg:phone":"+1 850 273 6655",
    "sg:postcode":"32303",
    "sg:province":"FL",
    "sg:website":"http://www.hauteheadzsalon.com/",
    "wof:name":"Haute Headz",
    "wof:placetype":"venue"
},
  "geometry": {"coordinates":[-84.275352,30.45952],"type":"Point"}
}