{
  "type": "Feature",
  "properties": {
    "addr:full":"3301 NW 47th Ter Fort Lauderdale FL 33319",
    "addr:housenumber":"3301",
    "addr:postcode":"33319",
    "addr:street":"Nw 47Th Ter",
    "iso:country":"US",
    "sg:address":"3301 NW 47th Ter",
    "sg:city":"Fort Lauderdale",
    "sg:classifiers":[
        {
            "category":"Shopping",
            "subcategory":"Gifts & Souvenirs",
            "type":"Retail Goods"
        }
    ],
    "sg:phone":"+1 954 677 9977",
    "sg:postcode":"33319",
    "sg:province":"FL",
    "wof:name":"Garden of Gifts",
    "wof:placetype":"venue"
},
  "geometry": {"coordinates":[-80.212423,26.166283],"type":"Point"}
}