{
  "type": "Feature",
  "properties": {
    "addr:full":"2401 N Miami Ave Miami FL 33127",
    "addr:housenumber":"2401",
    "addr:postcode":"33127",
    "addr:street":"N Miami Ave",
    "iso:country":"US",
    "sg:address":"2401 N Miami Ave",
    "sg:city":"Miami",
    "sg:classifiers":[
        {
            "category":"Professional",
            "subcategory":"Business Services",
            "type":"Services"
        }
    ],
    "sg:phone":"+1 305 573 8423",
    "sg:postcode":"33127",
    "sg:province":"FL",
    "sg:tags":[
        "recording",
        "studio"
    ],
    "wof:name":"Positive Vibe Entertainment",
    "wof:placetype":"venue"
},
  "geometry": {"coordinates":[-80.194992,25.80068],"type":"Point"}
}