{
  "type": "Feature",
  "properties": {
    "iso:country":"US",
    "sg:address":"199 Villacrest Dr",
    "sg:city":"Crestview",
    "sg:classifiers":[
        {
            "category":"Building & Trades",
            "subcategory":"Construction",
            "type":"Services"
        }
    ],
    "sg:phone":"+1 850 689 1100",
    "sg:postcode":"32536",
    "sg:province":"FL",
    "sg:tags":[
        "home",
        "builder"
    ],
    "wof:name":"Henry Co Homes",
    "wof:placetype":"venue"
},
  "geometry": {"coordinates":[-86.57916299999999,30.713538],"type":"Point"}
}