{
  "type": "Feature",
  "properties": {
    "addr:full":"126 S Osprey Ave Sarasota FL 34236",
    "addr:housenumber":"126",
    "addr:postcode":"34236",
    "addr:street":"S Osprey Ave",
    "iso:country":"US",
    "sg:address":"126 S Osprey Ave",
    "sg:city":"Sarasota",
    "sg:classifiers":[
        {
            "category":"Professional",
            "subcategory":"Management & Consulting",
            "type":"Services"
        }
    ],
    "sg:phone":"+1 941 316 0308",
    "sg:postcode":"34236",
    "sg:province":"FL",
    "sg:tags":[
        "consultant",
        "educational"
    ],
    "sg:website":"http://www.campusworksinc.com",
    "wof:name":"Campusworks Inc",
    "wof:placetype":"venue"
},
  "geometry": {"coordinates":[-82.534384,27.335563],"type":"Point"}
}