{
  "type": "Feature",
  "properties": {
    "iso:country":"US",
    "sg:address":"4818 S Florida Ave",
    "sg:city":"Lakeland",
    "sg:classifiers":[
        {
            "category":"Retail",
            "subcategory":"Laundry & Dry Cleaning",
            "type":"Services"
        }
    ],
    "sg:phone":"+1 863 644 3631",
    "sg:postcode":"33813",
    "sg:province":"FL",
    "sg:tags":[
        "operated",
        "cleaner",
        "washer",
        "coin",
        "dryer"
    ],
    "wof:name":"Executive Cleaners & Launderers",
    "wof:placetype":"venue"
},
  "geometry": {"coordinates":[-81.957714,27.978861],"type":"Point"}
}