{
  "type": "Feature",
  "properties": {
    "addr:full":"5001 Norriswood Dr Mulberry FL 33860",
    "addr:housenumber":"5001",
    "addr:postcode":"33860",
    "addr:street":"Norriswood Dr",
    "iso:country":"US",
    "sg:address":"5001 Norriswood Dr",
    "sg:city":"Mulberry",
    "sg:classifiers":[
        {
            "category":"Professional",
            "subcategory":"Art Services",
            "type":"Services"
        }
    ],
    "sg:phone":"+1 863 648 1104",
    "sg:postcode":"33860",
    "sg:province":"FL",
    "sg:tags":[
        "artist"
    ],
    "wof:name":"Peace Globe Inc",
    "wof:placetype":"venue"
},
  "geometry": {"coordinates":[-82.029957,27.932914],"type":"Point"}
}