{
  "type": "Feature",
  "properties": {
    "iso:country":"US",
    "sg:address":"3834 Coronado Rd",
    "sg:city":"Jacksonville",
    "sg:classifiers":[
        {
            "category":"Retail",
            "subcategory":"Repair Shop",
            "type":"Services"
        }
    ],
    "sg:phone":"+1 904 731 1588",
    "sg:postcode":"32217",
    "sg:province":"FL",
    "sg:tags":[
        "clocks",
        "parts"
    ],
    "wof:name":"Clocks & Collectibles",
    "wof:placetype":"venue"
},
  "geometry": {"coordinates":[-81.61807399999999,30.244031],"type":"Point"}
}