{
  "type": "Feature",
  "properties": {
    "iso:country":"US",
    "sg:address":"214 Madrid St",
    "sg:city":"St Augustine",
    "sg:classifiers":[
        {
            "category":"Autos & Motor Vehicles",
            "subcategory":"Boat Sales",
            "type":"Retail Goods"
        }
    ],
    "sg:phone":"+1 904 824 1102",
    "sg:postcode":"32080",
    "sg:province":"FL",
    "sg:tags":[
        "yacht",
        "broker"
    ],
    "sg:website":"www.bottomlineyachts.com",
    "wof:name":"Bottom Line Yacht Sales & Svc",
    "wof:placetype":"venue"
},
  "geometry": {"coordinates":[-81.272794,29.831662],"type":"Point"}
}