{
  "type": "Feature",
  "properties": {
    "iso:country":"US",
    "sg:address":"917 Venture Ave",
    "sg:city":"Leesburg",
    "sg:classifiers":[
        {
            "category":"Retail",
            "subcategory":"Repair Shop",
            "type":"Services"
        }
    ],
    "sg:phone":"+1 352 314 0144",
    "sg:postcode":"34748",
    "sg:province":"FL",
    "sg:tags":[
        "equipment",
        "testing",
        "telecommunication"
    ],
    "wof:name":"Restor Telecom Inc",
    "wof:placetype":"venue"
},
  "geometry": {"coordinates":[-81.89201300000001,28.802425],"type":"Point"}
}