{
  "type": "Feature",
  "properties": {
    "addr:full":"330 NE 42nd St Oakland Park FL 33334",
    "addr:housenumber":"330",
    "addr:postcode":"33334",
    "addr:street":"Ne 42Nd St",
    "iso:country":"US",
    "sg:address":"330 NE 42nd St",
    "sg:city":"Oakland Park",
    "sg:classifiers":[
        {
            "category":"Travel",
            "subcategory":"Travel Agent",
            "type":"Entertainment"
        }
    ],
    "sg:phone":"+1 954 568 2121",
    "sg:postcode":"33334",
    "sg:province":"FL",
    "sg:tags":[
        "agency",
        "bureau"
    ],
    "wof:name":"Travel Agents Intl",
    "wof:placetype":"venue"
},
  "geometry": {"coordinates":[-80.14102,26.178359],"type":"Point"}
}