{
  "type": "Feature",
  "properties": {
    "iso:country":"US",
    "sg:address":"505 8th Ave S",
    "sg:city":"Naples",
    "sg:classifiers":[
        {
            "category":"Real Estate",
            "subcategory":"Real Estate Agent",
            "type":"Services"
        }
    ],
    "sg:phone":"+1 239 649 2224",
    "sg:postcode":"34102",
    "sg:province":"FL",
    "wof:name":"Foresite Development",
    "wof:placetype":"venue"
},
  "geometry": {"coordinates":[-81.797123,26.138209],"type":"Point"}
}