{
  "type": "Feature",
  "properties": {
    "iso:country":"US",
    "sg:address":"5429 SW 80 St",
    "sg:city":"Gainesville",
    "sg:classifiers":[
        {
            "category":"Professional",
            "type":"Services"
        }
    ],
    "sg:phone":"+1 352 336 8377",
    "sg:postcode":"32608",
    "sg:province":"FL",
    "sg:tags":[
        "writer"
    ],
    "wof:name":"Barbara Cox Biomedical Writer",
    "wof:placetype":"venue"
},
  "geometry": {"coordinates":[-82.427781,29.604544],"type":"Point"}
}