{
  "type": "Feature",
  "properties": {
    "addr:full":"209 E Acre Dr Plantation FL 33317",
    "addr:housenumber":"209",
    "addr:postcode":"33317",
    "addr:street":"E Acre Dr",
    "iso:country":"US",
    "sg:address":"209 E Acre Dr",
    "sg:city":"Plantation",
    "sg:classifiers":[
        {
            "category":"Building & Trades",
            "subcategory":"Construction",
            "type":"Services"
        }
    ],
    "sg:phone":"+1 954 650 6876",
    "sg:postcode":"33317",
    "sg:province":"FL",
    "sg:tags":[
        "designer",
        "dealer",
        "pool",
        "swimming"
    ],
    "wof:name":"All Seasons Pool Builders Inc",
    "wof:placetype":"venue"
},
  "geometry": {"coordinates":[-80.219905,26.128063],"type":"Point"}
}