{
  "type": "Feature",
  "properties": {
    "iso:country":"US",
    "sg:address":"20820 NW 7th Ave",
    "sg:city":"Miami",
    "sg:classifiers":[
        {
            "category":"Professional",
            "subcategory":"Business Services",
            "type":"Services"
        }
    ],
    "sg:phone":"+1 305 653 8179",
    "sg:postcode":"33169",
    "sg:province":"FL",
    "sg:tags":[
        "fund",
        "promotion",
        "raising"
    ],
    "wof:name":"Phatman Promotions Big Skreemz",
    "wof:placetype":"venue"
},
  "geometry": {"coordinates":[-80.214287,25.966631],"type":"Point"}
}