{
  "type": "Feature",
  "properties": {
    "addr:full":"1955 NW 110th Ave Miami FL 33172",
    "addr:housenumber":"1955",
    "addr:postcode":"33172",
    "addr:street":"Nw 110Th Ave",
    "iso:country":"US",
    "sg:address":"1955 NW 110th Ave",
    "sg:city":"Miami",
    "sg:classifiers":[
        {
            "category":"Building & Trades",
            "subcategory":"Construction",
            "type":"Services"
        }
    ],
    "sg:phone":"+1 305 594 4152",
    "sg:postcode":"33172",
    "sg:province":"FL",
    "sg:tags":[
        "repair",
        "maintenance"
    ],
    "wof:name":"H & R Maintenance LLC",
    "wof:placetype":"venue"
},
  "geometry": {"coordinates":[-80.374216,25.794633],"type":"Point"}
}