{
  "type": "Feature",
  "properties": {
    "addr:full":"116 Poquito Rd Shalimar FL 32579",
    "addr:housenumber":"116",
    "addr:postcode":"32579",
    "addr:street":"Poquito Rd",
    "iso:country":"US",
    "sg:address":"116 Poquito Rd",
    "sg:city":"Shalimar",
    "sg:classifiers":[
        {
            "category":"Real Estate",
            "subcategory":"Real Estate Operator",
            "type":"Services"
        }
    ],
    "sg:phone":"+1 850 651 3335",
    "sg:postcode":"32579",
    "sg:province":"FL",
    "sg:tags":[
        "mobile",
        "home",
        "site"
    ],
    "wof:name":"Pinecrest Mobile Home Park",
    "wof:placetype":"venue"
},
  "geometry": {"coordinates":[-86.58642999999999,30.456384],"type":"Point"}
}