{
  "type": "Feature",
  "properties": {
    "iso:country":"US",
    "sg:address":"1716 S Riverside Dr",
    "sg:city":"Edgewater",
    "sg:classifiers":[
        {
            "category":"Shopping",
            "subcategory":"Discount & Variety Stores",
            "type":"Retail Goods"
        }
    ],
    "sg:phone":"+1 386 427 5032",
    "sg:postcode":"32132",
    "sg:province":"FL",
    "sg:tags":[
        "merchandise",
        "general"
    ],
    "wof:name":"Noor Enterprise Inc",
    "wof:placetype":"venue"
},
  "geometry": {"coordinates":[-80.894363,28.975081],"type":"Point"}
}