{
  "type": "Feature",
  "properties": {
    "iso:country":"US",
    "sg:address":"3230 NW 18th St",
    "sg:city":"Miami",
    "sg:classifiers":[
        {
            "category":"Building & Trades",
            "subcategory":"Landscaping Services",
            "type":"Services"
        }
    ],
    "sg:phone":"+1 305 633 3892",
    "sg:postcode":"33125",
    "sg:province":"FL",
    "sg:tags":[
        "lawn",
        "maintenance"
    ],
    "wof:name":"Orlando Ara",
    "wof:placetype":"venue"
},
  "geometry": {"coordinates":[-80.248535,25.791081],"type":"Point"}
}