{
  "type": "Feature",
  "properties": {
    "addr:full":"212 S Armenia Ave Tampa FL 33609",
    "addr:housenumber":"212",
    "addr:postcode":"33609",
    "addr:street":"S Armenia Ave",
    "iso:country":"US",
    "sg:address":"212 S Armenia Ave",
    "sg:city":"Tampa",
    "sg:classifiers":[
        {
            "category":"Retail",
            "subcategory":"Auto Rental",
            "type":"Services"
        }
    ],
    "sg:phone":"+1 813 250 0510",
    "sg:postcode":"33609",
    "sg:province":"FL",
    "sg:tags":[
        "renting",
        "truck",
        "leasing"
    ],
    "wof:name":"U-Haul Co",
    "wof:placetype":"venue"
},
  "geometry": {"coordinates":[-82.484987,27.942096],"type":"Point"}
}