{
  "type": "Feature",
  "properties": {
    "iso:country":"US",
    "sg:address":"5734 15th St E",
    "sg:city":"Bradenton",
    "sg:classifiers":[
        {
            "category":"Autos & Motor Vehicles",
            "subcategory":"Automobile Sales",
            "type":"Retail Goods"
        }
    ],
    "sg:phone":"+1 941 755 7232",
    "sg:postcode":"34203",
    "sg:province":"FL",
    "sg:tags":[
        "car",
        "dealer"
    ],
    "wof:name":"W W Motors",
    "wof:placetype":"venue"
},
  "geometry": {"coordinates":[-82.546753,27.436686],"type":"Point"}
}