{
  "type": "Feature",
  "properties": {
    "iso:country":"US",
    "sg:address":"9703 S Dixie Hwy Ste 204C",
    "sg:city":"Miami",
    "sg:classifiers":[
        {
            "category":"Communications",
            "type":"Services"
        }
    ],
    "sg:phone":"+1 305 359 5387",
    "sg:postcode":"33156",
    "sg:province":"FL",
    "sg:tags":[
        "translator",
        "interpreter"
    ],
    "wof:name":"Interpret-Ears Corp.",
    "wof:placetype":"venue"
},
  "geometry": {"coordinates":[-80.316856,25.67963],"type":"Point"}
}