{
  "type": "Feature",
  "properties": {
    "iso:country":"US",
    "sg:address":"11350 NW 53rd Ln",
    "sg:city":"Doral",
    "sg:classifiers":[
        {
            "category":"Shopping",
            "subcategory":"Bicycles & Sporting Goods",
            "type":"Retail Goods"
        },
        {
            "category":"Parking",
            "subcategory":"Bicycle",
            "type":"Transportation"
        }
    ],
    "sg:phone":"+1 305 463 6700",
    "sg:postcode":"33178",
    "sg:province":"FL",
    "sg:tags":[
        "shop",
        "security",
        "system",
        "rack"
    ],
    "wof:name":"Z Bike Wear",
    "wof:placetype":"venue"
},
  "geometry": {"coordinates":[-80.3813,25.82206],"type":"Point"}
}