{
  "type": "Feature",
  "properties": {
    "iso:country":"US",
    "sg:address":"8530 N Wickham Rd Ste 114",
    "sg:city":"Melbourne",
    "sg:classifiers":[
        {
            "category":"Wholesale",
            "subcategory":"Medical Equipment & Supplies",
            "type":"Manufacturing & Wholesale Goods"
        },
        {
            "category":"Utilities",
            "subcategory":"Natural Gas",
            "type":"Services"
        }
    ],
    "sg:phone":"+1 321 259 1029",
    "sg:postcode":"32940",
    "sg:province":"FL",
    "sg:tags":[
        "assistive",
        "device",
        "aids-manufacturers",
        "aid",
        "hearing"
    ],
    "wof:name":"Gulf Atlantic Hearing Aid",
    "wof:placetype":"venue"
},
  "geometry": {"coordinates":[-80.724446,28.229989],"type":"Point"}
}