{
  "type": "Feature",
  "properties": {
    "addr:full":"221 Circle Dr Maitland FL 32751",
    "addr:housenumber":"221",
    "addr:postcode":"32751",
    "addr:street":"Circle Dr",
    "iso:country":"US",
    "sg:address":"221 Circle Dr",
    "sg:city":"Maitland",
    "sg:classifiers":[
        {
            "category":"Building & Trades",
            "subcategory":"Construction",
            "type":"Services"
        }
    ],
    "sg:phone":"+1 407 644 8923",
    "sg:postcode":"32751",
    "sg:province":"FL",
    "sg:tags":[
        "commercial",
        "contractor"
    ],
    "sg:website":"www.wpc.com",
    "wof:name":"Winter Park Construction",
    "wof:placetype":"venue"
},
  "geometry": {"coordinates":[-81.366501,28.615999],"type":"Point"}
}