{
  "type": "Feature",
  "properties": {
    "addr:full":"305 N Prescott Ave Clearwater FL 33755",
    "addr:housenumber":"305",
    "addr:postcode":"33755",
    "addr:street":"N Prescott Ave",
    "iso:country":"US",
    "sg:address":"305 N Prescott Ave",
    "sg:city":"Clearwater",
    "sg:classifiers":[
        {
            "category":"Professional",
            "subcategory":"Computer Services",
            "type":"Services"
        }
    ],
    "sg:phone":"+1 727 631 0249",
    "sg:postcode":"33755",
    "sg:province":"FL",
    "sg:tags":[
        "website",
        "design"
    ],
    "wof:name":"Industrial Strenghts Webbsites",
    "wof:placetype":"venue"
},
  "geometry": {"coordinates":[-82.784757,27.969121],"type":"Point"}
}