{
  "type": "Feature",
  "properties": {
    "addr:full":"1582 Biscayne Blvd Miami FL 33132",
    "addr:housenumber":"1582",
    "addr:postcode":"33132",
    "addr:street":"Biscayne Blvd",
    "iso:country":"US",
    "sg:address":"1582 Biscayne Blvd",
    "sg:city":"Miami",
    "sg:classifiers":[
        {
            "category":"Professional",
            "subcategory":"Computer Services",
            "type":"Services"
        }
    ],
    "sg:phone":"+1 305 851 7676",
    "sg:postcode":"33132",
    "sg:province":"FL",
    "sg:tags":[
        "repair"
    ],
    "sg:website":"www.harmonysolutions.us",
    "wof:name":"Harmony Business Solutions",
    "wof:placetype":"venue"
},
  "geometry": {"coordinates":[-80.18907799999999,25.790368],"type":"Point"}
}