{
  "type": "Feature",
  "properties": {
    "addr:full":"48143 Ephesus Rd Hilliard FL 32046",
    "addr:postcode":"48143;32046",
    "addr:street":"Ephesus Rd",
    "iso:country":"US",
    "sg:address":"48143 Ephesus Rd",
    "sg:city":"Hilliard",
    "sg:classifiers":[
        {
            "category":"Place Of Worship",
            "subcategory":"Church",
            "type":"Public Place"
        },
        {
            "category":"Place Of Worship",
            "type":"Public Place"
        }
    ],
    "sg:phone":"+1 904 845 3426",
    "sg:postcode":"32046",
    "sg:province":"FL",
    "sg:tags":[
        "churches-baptist-general",
        "churches-baptist"
    ],
    "wof:name":"Ephesus Baptist Church",
    "wof:placetype":"venue"
},
  "geometry": {"coordinates":[-81.817232,30.73306],"type":"Point"}
}