{
  "type": "Feature",
  "properties": {
    "addr:full":"130 E Bloomingdale Ave Brandon FL 33511",
    "addr:housenumber":"130",
    "addr:postcode":"33511",
    "addr:street":"E Bloomingdale Ave",
    "iso:country":"US",
    "sg:address":"130 E Bloomingdale Ave",
    "sg:city":"Brandon",
    "sg:classifiers":[
        {
            "category":"Real Estate",
            "subcategory":"Real Estate Services",
            "type":"Services"
        },
        {
            "category":"Real Estate",
            "subcategory":"Real Estate Agent",
            "type":"Services"
        }
    ],
    "sg:phone":"+1 813 662 2600",
    "sg:postcode":"33511",
    "sg:province":"FL",
    "sg:tags":[
        "buyer",
        "management",
        "broker"
    ],
    "wof:name":"Michael Davis Realty",
    "wof:placetype":"venue"
},
  "geometry": {"coordinates":[-82.284964,27.89362],"type":"Point"}
}