{
  "type": "Feature",
  "properties": {
    "iso:country":"US",
    "sg:address":"15615 Blountstown Hwy",
    "sg:city":"Tallahassee",
    "sg:classifiers":[
        {
            "category":"Building & Trades",
            "subcategory":"Landscaping Services",
            "type":"Services"
        }
    ],
    "sg:phone":"+1 850 574 1954",
    "sg:postcode":"32310",
    "sg:province":"FL",
    "sg:tags":[
        "lawn"
    ],
    "wof:name":"Fort Braden Tractor Service",
    "wof:placetype":"venue"
},
  "geometry": {"coordinates":[-84.522491,30.435533],"type":"Point"}
}