{
  "type": "Feature",
  "properties": {
    "iso:country":"US",
    "sg:address":"4471 NW 36th St Ste 206",
    "sg:city":"Miami Springs",
    "sg:classifiers":[
        {
            "category":"Real Estate",
            "subcategory":"Architect",
            "type":"Services"
        }
    ],
    "sg:phone":"+1 305 863 9427",
    "sg:postcode":"33166",
    "sg:province":"FL",
    "wof:name":"Design 2004",
    "wof:placetype":"venue"
},
  "geometry": {"coordinates":[-80.270203,25.8083],"type":"Point"}
}