{
  "type": "Feature",
  "properties": {
    "iso:country":"US",
    "sg:address":"15420 SW 96th Ter",
    "sg:city":"Miami",
    "sg:classifiers":[
        {
            "category":"Building & Trades",
            "subcategory":"Construction",
            "type":"Services"
        }
    ],
    "sg:phone":"+1 305 595 1228",
    "sg:postcode":"33196",
    "sg:province":"FL",
    "sg:tags":[
        "painter"
    ],
    "wof:name":"FPD Painting Corp",
    "wof:placetype":"venue"
},
  "geometry": {"coordinates":[-80.44539899999999,25.676627],"type":"Point"}
}