{
  "type": "Feature",
  "properties": {
    "addr:full":"11845 Tanya Ter E Jacksonville FL 32223",
    "addr:housenumber":"11845",
    "addr:postcode":"32223",
    "addr:street":"Tanya Ter E",
    "iso:country":"US",
    "sg:address":"11845 Tanya Ter E",
    "sg:city":"Jacksonville",
    "sg:classifiers":[
        {
            "category":"Professional",
            "subcategory":"Management & Consulting",
            "type":"Services"
        }
    ],
    "sg:phone":"+1 904 268 4485",
    "sg:postcode":"32223",
    "sg:province":"FL",
    "wof:name":"Gys Management",
    "wof:placetype":"venue"
},
  "geometry": {"coordinates":[-81.63872499999999,30.155565],"type":"Point"}
}