{
  "type": "Feature",
  "properties": {
    "addr:full":"4414 Oak Ln Milton FL 32583",
    "addr:housenumber":"4414",
    "addr:postcode":"32583",
    "addr:street":"Oak Ln",
    "iso:country":"US",
    "sg:address":"4414 Oak Ln",
    "sg:city":"Milton",
    "sg:classifiers":[
        {
            "category":"Building & Trades",
            "subcategory":"Landscaping Services",
            "type":"Services"
        }
    ],
    "sg:phone":"+1 850 981 1301",
    "sg:postcode":"32583",
    "sg:province":"FL",
    "sg:tags":[
        "landscape"
    ],
    "wof:name":"Jimmy Phillips Landscapin",
    "wof:placetype":"venue"
},
  "geometry": {"coordinates":[-87.083805,30.59498],"type":"Point"}
}