{
  "type": "Feature",
  "properties": {
    "iso:country":"US",
    "sg:address":"7285 NW 87th Ave",
    "sg:city":"Miami",
    "sg:classifiers":[
        {
            "category":"Freight",
            "type":"Transportation"
        }
    ],
    "sg:phone":"+1 305 594 7124",
    "sg:postcode":"33178",
    "sg:province":"FL",
    "sg:website":"www.republicshipping.com",
    "wof:name":"Republic Shipping",
    "wof:placetype":"venue"
},
  "geometry": {"coordinates":[-80.33808000000001,25.839849],"type":"Point"}
}