{
  "type": "Feature",
  "properties": {
    "addr:full":"1435 Immokalee Rd Naples FL 34119",
    "addr:housenumber":"1435",
    "addr:postcode":"34119",
    "addr:street":"Immokalee Rd",
    "iso:country":"US",
    "sg:address":"1435 Immokalee Rd",
    "sg:city":"Naples",
    "sg:classifiers":[
        {
            "category":"Health Services",
            "subcategory":"Doctor",
            "type":"Services"
        }
    ],
    "sg:phone":"+1 239 592 5511",
    "sg:postcode":"34119",
    "sg:province":"FL",
    "sg:tags":[
        "physician",
        "surgeon"
    ],
    "sg:website":"www.allsaintseyecenter.com",
    "wof:name":"All Saints Eye Ctr",
    "wof:placetype":"venue"
},
  "geometry": {"coordinates":[-81.789585,26.272347],"type":"Point"}
}