{
  "type": "Feature",
  "properties": {
    "iso:country":"US",
    "sg:address":"4755 SW 51st St",
    "sg:city":"Davie",
    "sg:classifiers":[
        {
            "category":"Freight",
            "type":"Transportation"
        }
    ],
    "sg:phone":"+1 954 689 8252",
    "sg:postcode":"33314",
    "sg:province":"FL",
    "sg:tags":[
        "delivery"
    ],
    "wof:name":"Straight Shot Express",
    "wof:placetype":"venue"
},
  "geometry": {"coordinates":[-80.21289400000001,26.05911],"type":"Point"}
}