{
  "type": "Feature",
  "properties": {
    "addr:full":"3001 S Ocean Dr Hollywood FL 33019",
    "addr:housenumber":"3001",
    "addr:postcode":"33019",
    "addr:street":"S Ocean Dr",
    "iso:country":"US",
    "sg:address":"3001 S Ocean Dr",
    "sg:city":"Hollywood",
    "sg:classifiers":[
        {
            "category":"Retail",
            "subcategory":"Laundry & Dry Cleaning",
            "type":"Services"
        }
    ],
    "sg:phone":"+1 954 929 3383",
    "sg:postcode":"33019",
    "sg:province":"FL",
    "sg:tags":[
        "drycleaning",
        "plant"
    ],
    "wof:name":"Decadent Cleaners Inc",
    "wof:placetype":"venue"
},
  "geometry": {"coordinates":[-80.11869900000001,25.991593],"type":"Point"}
}