{
  "type": "Feature",
  "properties": {
    "iso:country":"US",
    "sg:address":"401 W Donegan Ave",
    "sg:city":"Kissimmee",
    "sg:classifiers":[
        {
            "category":"Real Estate",
            "subcategory":"Real Estate Operator",
            "type":"Services"
        }
    ],
    "sg:phone":"+1 407 931 3000",
    "sg:postcode":"34741",
    "sg:province":"FL",
    "sg:tags":[
        "mobile",
        "home",
        "community"
    ],
    "wof:name":"C J Properties Inc",
    "wof:placetype":"venue"
},
  "geometry": {"coordinates":[-81.408796,28.318893],"type":"Point"}
}