{
  "type": "Feature",
  "properties": {
    "addr:full":"3975 Arnold Ave Naples FL 34104",
    "addr:housenumber":"3975",
    "addr:postcode":"34104",
    "addr:street":"Arnold Ave",
    "iso:country":"US",
    "sg:address":"3975 Arnold Ave",
    "sg:city":"Naples",
    "sg:classifiers":[
        {
            "category":"Building & Trades",
            "subcategory":"Construction",
            "type":"Services"
        }
    ],
    "sg:phone":"+1 239 403 9339",
    "sg:postcode":"34104",
    "sg:province":"FL",
    "sg:tags":[
        "general",
        "contractor"
    ],
    "wof:name":"R D Harris Construction Inc",
    "wof:placetype":"venue"
},
  "geometry": {"coordinates":[-81.763508,26.167235],"type":"Point"}
}