{
  "type": "Feature",
  "properties": {
    "iso:country":"US",
    "sg:address":"1401 Viscaya Pkwy Ste 1",
    "sg:city":"Cape Coral",
    "sg:classifiers":[
        {
            "category":"Professional",
            "subcategory":"Printing & Photocopies",
            "type":"Services"
        }
    ],
    "sg:phone":"+1 239 772 0600",
    "sg:postcode":"33990",
    "sg:province":"FL",
    "wof:name":"Quickprint Business Center",
    "wof:placetype":"venue"
},
  "geometry": {"coordinates":[-81.94450399999999,26.6362],"type":"Point"}
}