{
  "type": "Feature",
  "properties": {
    "addr:full":"2115 N Commerce Pkwy Weston FL 33326",
    "addr:housenumber":"2115",
    "addr:postcode":"33326",
    "addr:street":"N Commerce Pkwy",
    "iso:country":"US",
    "sg:address":"2115 N Commerce Pkwy",
    "sg:city":"Weston",
    "sg:classifiers":[
        {
            "category":"Professional",
            "subcategory":"Lawyer & Legal Services",
            "type":"Services"
        }
    ],
    "sg:phone":"+1 954 384 9200",
    "sg:postcode":"33326",
    "sg:province":"FL",
    "sg:tags":[
        "attorney"
    ],
    "wof:name":"Rosenthal, Alex P",
    "wof:placetype":"venue"
},
  "geometry": {"coordinates":[-80.36798899999999,26.091579],"type":"Point"}
}