{
  "type": "Feature",
  "properties": {
    "iso:country":"US",
    "sg:address":"193 Stahlman Ave",
    "sg:city":"Destin",
    "sg:classifiers":[
        {
            "category":"Freight",
            "type":"Transportation"
        }
    ],
    "sg:phone":"+1 850 837 2425",
    "sg:postcode":"32541",
    "sg:province":"FL",
    "sg:tags":[
        "commercial",
        "storage"
    ],
    "wof:name":"Destin Mini-Storage Inc",
    "wof:placetype":"venue"
},
  "geometry": {"coordinates":[-86.50895800000001,30.396475],"type":"Point"}
}