{
  "type": "Feature",
  "properties": {
    "iso:country":"US",
    "sg:address":"4820 Okeechobee Rd",
    "sg:city":"West Palm Beach",
    "sg:classifiers":[
        {
            "category":"Health Services",
            "subcategory":"Doctor",
            "type":"Services"
        }
    ],
    "sg:phone":"+1 561 689 5500",
    "sg:postcode":"33417",
    "sg:province":"FL",
    "sg:tags":[
        "physician",
        "surgeon"
    ],
    "sg:website":"www.bentzeye.com",
    "wof:name":"Bentz Eye Ctr",
    "wof:placetype":"venue"
},
  "geometry": {"coordinates":[-80.115442,26.706849],"type":"Point"}
}