{
  "type": "Feature",
  "properties": {
    "addr:full":"2333 Brickell Ave Apt E Miami FL 33129",
    "addr:housenumber":"2333",
    "addr:postcode":"33129",
    "addr:street":"Brickell Ave Apt E",
    "iso:country":"US",
    "sg:address":"2333 Brickell Ave Apt E",
    "sg:city":"Miami",
    "sg:classifiers":[
        {
            "category":"Health Services",
            "subcategory":"Doctor",
            "type":"Services"
        }
    ],
    "sg:phone":"+1 305 785 7899",
    "sg:postcode":"33129",
    "sg:province":"FL",
    "sg:tags":[
        "physician",
        "pediatrics-emergency",
        "pediatrics",
        "surgeons",
        "medicine",
        "surgeon"
    ],
    "wof:name":"Pediatric Dental Centers",
    "wof:placetype":"venue"
},
  "geometry": {"coordinates":[-80.201566,25.751871],"type":"Point"}
}