{
  "type": "Feature",
  "properties": {
    "iso:country":"US",
    "sg:address":"1400 NE Miami Gardens Dr 206C",
    "sg:city":"Miami",
    "sg:classifiers":[
        {
            "category":"Professional",
            "subcategory":"Lawyer & Legal Services",
            "type":"Services"
        }
    ],
    "sg:phone":"+1 305 940 8065",
    "sg:postcode":"33179",
    "sg:province":"FL",
    "sg:tags":[
        "information",
        "attorney",
        "referral",
        "practice",
        "disability",
        "social",
        "security",
        "law"
    ],
    "wof:name":"Harold R Cohen Atty At Law",
    "wof:placetype":"venue"
},
  "geometry": {"coordinates":[-80.173264,25.944706],"type":"Point"}
}