{
  "type": "Feature",
  "properties": {
    "iso:country":"US",
    "sg:address":"251 Palm Cir W",
    "sg:city":"Hollywood",
    "sg:classifiers":[
        {
            "category":"Building & Trades",
            "subcategory":"Construction",
            "type":"Services"
        }
    ],
    "sg:phone":"+1 954 442 0418",
    "sg:postcode":"33025",
    "sg:province":"FL",
    "sg:tags":[
        "hanging",
        "contractor"
    ],
    "wof:name":"Paintpros",
    "wof:placetype":"venue"
},
  "geometry": {"coordinates":[-80.270684,26.006792],"type":"Point"}
}