{
  "type": "Feature",
  "properties": {
    "addr:full":"1616 Old Daytona Rd Deland FL 32724",
    "addr:housenumber":"1616",
    "addr:postcode":"32724",
    "addr:street":"Old Daytona Rd",
    "iso:country":"US",
    "sg:address":"1616 Old Daytona Rd",
    "sg:city":"Deland",
    "sg:classifiers":[
        {
            "category":"Building & Trades",
            "subcategory":"Pest Control",
            "type":"Services"
        }
    ],
    "sg:phone":"+1 386 738 2265",
    "sg:postcode":"32724",
    "sg:province":"FL",
    "wof:name":"Professional Pest Products",
    "wof:placetype":"venue"
},
  "geometry": {"coordinates":[-81.26738899999999,29.06754],"type":"Point"}
}