{
  "type": "Feature",
  "properties": {
    "addr:full":"1967 East Rd Jacksonville FL 32216",
    "addr:housenumber":"1967",
    "addr:postcode":"32216",
    "addr:street":"East Rd",
    "iso:country":"US",
    "sg:address":"1967 East Rd",
    "sg:city":"Jacksonville",
    "sg:classifiers":[
        {
            "category":"Retail",
            "subcategory":"Repair Shop",
            "type":"Services"
        }
    ],
    "sg:phone":"+1 904 805 9562",
    "sg:postcode":"32216",
    "sg:province":"FL",
    "sg:tags":[
        "upholsterer"
    ],
    "wof:name":"Greer's Upholstery & Foam",
    "wof:placetype":"venue"
},
  "geometry": {"coordinates":[-81.58475300000001,30.286336],"type":"Point"}
}