{
  "type": "Feature",
  "properties": {
    "addr:full":"690 NW 183rd St Miami FL 33169",
    "addr:housenumber":"690",
    "addr:postcode":"33169",
    "addr:street":"Nw 183Rd St",
    "iso:country":"US",
    "sg:address":"690 NW 183rd St",
    "sg:city":"Miami",
    "sg:classifiers":[
        {
            "category":"Retail",
            "subcategory":"Portrait Studio",
            "type":"Services"
        },
        {
            "category":"Shopping",
            "subcategory":"Pharmacy",
            "type":"Retail Goods"
        }
    ],
    "sg:phone":"+1 305 249 6792",
    "sg:postcode":"33169",
    "sg:province":"FL",
    "sg:tags":[
        "photography",
        "drugstore",
        "store"
    ],
    "sg:website":"www.walgreens.com/",
    "wof:name":"Walgreens",
    "wof:placetype":"venue"
},
  "geometry": {"coordinates":[-80.212564,25.941804],"type":"Point"}
}