{
  "type": "Feature",
  "properties": {
    "addr:full":"514 Palo Verde Dr Leesburg FL 34748",
    "addr:housenumber":"514",
    "addr:postcode":"34748",
    "addr:street":"Palo Verde Dr",
    "iso:country":"US",
    "sg:address":"514 Palo Verde Dr",
    "sg:city":"Leesburg",
    "sg:classifiers":[
        {
            "category":"Transit Center",
            "subcategory":"Freight",
            "type":"Transportation"
        },
        {
            "category":"Freight",
            "type":"Transportation"
        }
    ],
    "sg:phone":"+1 352 326 8356",
    "sg:postcode":"34748",
    "sg:province":"FL",
    "sg:tags":[
        "local",
        "trucking-motor",
        "trucking"
    ],
    "wof:name":"Micheal Peters Trucking",
    "wof:placetype":"venue"
},
  "geometry": {"coordinates":[-81.86635,28.759511],"type":"Point"}
}