{
  "type": "Feature",
  "properties": {
    "iso:country":"US",
    "sg:address":"9105 S Dadeland Blvd",
    "sg:city":"Miami",
    "sg:classifiers":[
        {
            "category":"Shopping",
            "subcategory":"Pharmacy",
            "type":"Retail Goods"
        },
        {
            "category":"Food & Beverages",
            "subcategory":"Groceries & Convenience Stores",
            "type":"Retail Goods"
        }
    ],
    "sg:phone":"+1 305 670 8929",
    "sg:postcode":"33156",
    "sg:province":"FL",
    "sg:tags":[
        "drugstore"
    ],
    "sg:website":"www.publix.com",
    "wof:name":"Publix",
    "wof:placetype":"venue"
},
  "geometry": {"coordinates":[-80.314796,25.685301],"type":"Point"}
}