{
  "type": "Feature",
  "properties": {
    "iso:country":"US",
    "sg:address":"5401 L B Mcleod Rd",
    "sg:city":"Orlando",
    "sg:classifiers":[
        {
            "category":"Personal",
            "type":"Services"
        },
        {
            "category":"Retail",
            "subcategory":"Storage",
            "type":"Services"
        }
    ],
    "sg:phone":"+1 877 258 8230",
    "sg:postcode":"32811",
    "sg:province":"FL",
    "sg:tags":[
        "self",
        "full",
        "commercial",
        "mover",
        "household"
    ],
    "sg:website":"http://www.publicstorage.com/?pid=ypcomCPCingenio",
    "wof:name":"Public Storage",
    "wof:placetype":"venue"
},
  "geometry": {"coordinates":[-81.45245799999999,28.50473],"type":"Point"}
}