{
  "type": "Feature",
  "properties": {
    "iso:country":"US",
    "sg:address":"866 S Goldenrod Rd",
    "sg:city":"Orlando",
    "sg:classifiers":[
        {
            "category":"Recreation",
            "type":"Entertainment"
        }
    ],
    "sg:phone":"+1 407 282 3141",
    "sg:postcode":"32822",
    "sg:province":"FL",
    "wof:name":"Sk8 Zone By Curtis Schult",
    "wof:placetype":"venue"
},
  "geometry": {"coordinates":[-81.28577900000001,28.533572],"type":"Point"}
}