{
  "type": "Feature",
  "properties": {
    "iso:country":"US",
    "sg:address":"24940 W Newberry Rd",
    "sg:city":"Newberry",
    "sg:classifiers":[
        {
            "category":"Personal",
            "subcategory":"Beauty Salon",
            "type":"Services"
        }
    ],
    "sg:phone":"+1 352 472 3737",
    "sg:postcode":"32669",
    "sg:province":"FL",
    "sg:tags":[
        "hair",
        "stylist"
    ],
    "wof:name":"Rebecca's Hair Studio",
    "wof:placetype":"venue"
},
  "geometry": {"coordinates":[-82.60601800000001,29.646606],"type":"Point"}
}