{
  "type": "Feature",
  "properties": {
    "iso:country":"US",
    "sg:address":"335 Mockingbird Ln",
    "sg:city":"Lantana",
    "sg:classifiers":[
        {
            "category":"Professional",
            "subcategory":"Computer Services",
            "type":"Services"
        }
    ],
    "sg:phone":"+1 561 296 5225",
    "sg:postcode":"33462",
    "sg:province":"FL",
    "sg:tags":[
        "internet"
    ],
    "wof:name":"Reference Pt",
    "wof:placetype":"venue"
},
  "geometry": {"coordinates":[-80.053342,26.589473],"type":"Point"}
}