{
  "type": "Feature",
  "properties": {
    "addr:full":"701 Brickell Ave Ste 3000 Miami FL 33131",
    "addr:housenumber":"701",
    "addr:postcode":"33131",
    "addr:street":"Brickell Ave Ste 3000",
    "iso:country":"US",
    "sg:address":"701 Brickell Ave Ste 3000",
    "sg:city":"Miami",
    "sg:classifiers":[
        {
            "category":"Food & Beverages",
            "subcategory":"Groceries & Convenience Stores",
            "type":"Retail Goods"
        }
    ],
    "sg:phone":"+1 305 358 0083",
    "sg:postcode":"33131",
    "sg:province":"FL",
    "wof:name":"Lg Deep Blue Llc",
    "wof:placetype":"venue"
},
  "geometry": {"coordinates":[-80.190372,25.767049],"type":"Point"}
}