{
  "type": "Feature",
  "properties": {
    "addr:full":"2211 S Florida Ave Lakeland FL 33803",
    "addr:housenumber":"2211",
    "addr:postcode":"33803",
    "addr:street":"S Florida Ave",
    "iso:country":"US",
    "sg:address":"2211 S Florida Ave",
    "sg:city":"Lakeland",
    "sg:classifiers":[
        {
            "category":"Shopping",
            "subcategory":"Bicycles & Sporting Goods",
            "type":"Retail Goods"
        }
    ],
    "sg:phone":"+1 863 688 7757",
    "sg:postcode":"33803",
    "sg:province":"FL",
    "wof:name":"Play It Again Sports",
    "wof:placetype":"venue"
},
  "geometry": {"coordinates":[-81.95713600000001,28.016847],"type":"Point"}
}