{
  "type": "Feature",
  "properties": {
    "iso:country":"US",
    "sg:address":"12636 NW 13th Ct",
    "sg:city":"Fort Lauderdale",
    "sg:classifiers":[
        {
            "category":"Airline",
            "type":"Transportation"
        }
    ],
    "sg:phone":"+1 954 835 2247",
    "sg:postcode":"33323",
    "sg:province":"FL",
    "sg:tags":[
        "scheduled",
        "air"
    ],
    "wof:name":"Coulton Charters Inc",
    "wof:placetype":"venue"
},
  "geometry": {"coordinates":[-80.317615,26.13859],"type":"Point"}
}