{
  "type": "Feature",
  "properties": {
    "addr:full":"3213 W Cass St Tampa FL 33609",
    "addr:housenumber":"3213",
    "addr:postcode":"33609",
    "addr:street":"W Cass St",
    "iso:country":"US",
    "sg:address":"3213 W Cass St",
    "sg:city":"Tampa",
    "sg:classifiers":[
        {
            "category":"Social Services",
            "subcategory":"Adult Care",
            "type":"Services"
        }
    ],
    "sg:phone":"+1 813 877 1404",
    "sg:postcode":"33609",
    "sg:province":"FL",
    "sg:tags":[
        "home",
        "residential"
    ],
    "wof:name":"Gloria's ACLFI",
    "wof:placetype":"venue"
},
  "geometry": {"coordinates":[-82.49737500000001,27.94981],"type":"Point"}
}