{
  "type": "Feature",
  "properties": {
    "iso:country":"US",
    "sg:address":"1250 US Hwy 92",
    "sg:city":"Longwood",
    "sg:classifiers":[
        {
            "category":"Insurance",
            "subcategory":"Insurance Agent",
            "type":"Services"
        }
    ],
    "sg:phone":"+1 407 629 8858",
    "sg:postcode":"32750",
    "sg:province":"FL",
    "wof:name":"Professional Liability Service",
    "wof:placetype":"venue"
},
  "geometry": {"coordinates":[-81.328694,28.689513],"type":"Point"}
}