{
  "type": "Feature",
  "properties": {
    "iso:country":"US",
    "sg:address":"1602 SW College Rd",
    "sg:city":"Ocala",
    "sg:classifiers":[
        {
            "category":"Autos & Motor Vehicles",
            "subcategory":"Automobile Sales",
            "type":"Retail Goods"
        }
    ],
    "sg:phone":"+1 352 620 2264",
    "sg:postcode":"34471",
    "sg:province":"FL",
    "sg:tags":[
        "car",
        "dealer"
    ],
    "wof:name":"Buchanan Jenkins Hyundai",
    "wof:placetype":"venue"
},
  "geometry": {"coordinates":[-82.162166,29.171463],"type":"Point"}
}