{
  "type": "Feature",
  "properties": {
    "addr:full":"2527 Glen Dr New Smyrna Beach FL 32168",
    "addr:housenumber":"2527",
    "addr:postcode":"32168",
    "addr:street":"Glen Dr",
    "iso:country":"US",
    "sg:address":"2527 Glen Dr",
    "sg:city":"New Smyrna Beach",
    "sg:classifiers":[
        {
            "category":"Professional",
            "type":"Services"
        }
    ],
    "sg:phone":"+1 386 409 3229",
    "sg:postcode":"32168",
    "sg:province":"FL",
    "wof:name":"Sabaku Aeromedical Inc",
    "wof:placetype":"venue"
},
  "geometry": {"coordinates":[-80.971469,29.002996],"type":"Point"}
}