{
  "type": "Feature",
  "properties": {
    "addr:full":"5073 N Dixie Hwy Fort Lauderdale FL 33334",
    "addr:housenumber":"5073",
    "addr:postcode":"33334",
    "addr:street":"N Dixie Hwy",
    "iso:country":"US",
    "sg:address":"5073 N Dixie Hwy",
    "sg:city":"Fort Lauderdale",
    "sg:classifiers":[
        {
            "category":"Restaurant",
            "type":"Food & Drink"
        }
    ],
    "sg:menulink":"http://www.allmenus.com/fl/fort-lauderdale/52357-ginos-pizza--italian-restaurant/menu/",
    "sg:phone":"+1 954 493 7457",
    "sg:postcode":"33334",
    "sg:province":"FL",
    "sg:tags":[
        "italian"
    ],
    "wof:name":"Gino's Pizza & Italian Restaurant",
    "wof:placetype":"venue"
},
  "geometry": {"coordinates":[-80.133174,26.190187],"type":"Point"}
}