{
  "type": "Feature",
  "properties": {
    "addr:full":"3030 Palm Rd West Palm Beach FL 33409",
    "addr:housenumber":"3030",
    "addr:postcode":"33409",
    "addr:street":"Palm Rd",
    "iso:country":"US",
    "sg:address":"3030 Palm Rd",
    "sg:city":"West Palm Beach",
    "sg:classifiers":[
        {
            "category":"Autos & Motor Vehicles",
            "subcategory":"Fuel & Gas Station",
            "type":"Retail Goods"
        }
    ],
    "sg:phone":"+1 561 683 2927",
    "sg:postcode":"33409",
    "sg:province":"FL",
    "sg:tags":[
        "grocery",
        "station",
        "gasoline"
    ],
    "wof:name":"Amoco",
    "wof:placetype":"venue"
},
  "geometry": {"coordinates":[-80.102457,26.722942],"type":"Point"}
}