{
  "type": "Feature",
  "properties": {
    "iso:country":"US",
    "sg:address":"777 NW 72nd Ave",
    "sg:city":"Miami",
    "sg:classifiers":[
        {
            "category":"Shopping",
            "subcategory":"Clothing, Apparel, & Fashions",
            "type":"Retail Goods"
        }
    ],
    "sg:phone":"+1 305 269 8601",
    "sg:postcode":"33126",
    "sg:province":"FL",
    "wof:name":"Tiff & Dav Inc",
    "wof:placetype":"venue"
},
  "geometry": {"coordinates":[-80.31238,25.777343],"type":"Point"}
}