{
  "type": "Feature",
  "properties": {
    "addr:full":"8189 SW 24th St Fort Lauderdale FL 33324",
    "addr:housenumber":"8189",
    "addr:postcode":"33324",
    "addr:street":"Sw 24Th St",
    "iso:country":"US",
    "sg:address":"8189 SW 24th St",
    "sg:city":"Fort Lauderdale",
    "sg:classifiers":[
        {
            "category":"Banks & Credit Unions",
            "subcategory":"Bank",
            "type":"Services"
        }
    ],
    "sg:phone":"+1 954 723 1549",
    "sg:postcode":"33324",
    "sg:province":"FL",
    "sg:tags":[
        "broker",
        "mortgage"
    ],
    "wof:name":"First Realty Mortgage Corp",
    "wof:placetype":"venue"
},
  "geometry": {"coordinates":[-80.23874600000001,26.199223],"type":"Point"}
}