{
  "type": "Feature",
  "properties": {
    "iso:country":"US",
    "sg:address":"132 E Flagler St",
    "sg:city":"Miami",
    "sg:classifiers":[
        {
            "category":"Shopping",
            "subcategory":"Jewelry",
            "type":"Retail Goods"
        }
    ],
    "sg:phone":"+1 305 371 1321",
    "sg:postcode":"33131",
    "sg:province":"FL",
    "sg:tags":[
        "jeweler"
    ],
    "sg:website":"www.kirkjewelers.com",
    "wof:name":"KIRK Jewelers",
    "wof:placetype":"venue"
},
  "geometry": {"coordinates":[-80.19075599999999,25.77415],"type":"Point"}
}