{
  "type": "Feature",
  "properties": {
    "iso:country":"US",
    "sg:address":"3216 Beaver Ave",
    "sg:city":"Spring Hill",
    "sg:classifiers":[
        {
            "category":"Building & Trades",
            "subcategory":"Construction",
            "type":"Services"
        }
    ],
    "sg:phone":"+1 352 684 6296",
    "sg:postcode":"34609",
    "sg:province":"FL",
    "sg:tags":[
        "house"
    ],
    "wof:name":"Madyson Custom Home Builders",
    "wof:placetype":"venue"
},
  "geometry": {"coordinates":[-82.525088,28.478767],"type":"Point"}
}