{
  "type": "Feature",
  "properties": {
    "addr:full":"475 NE Spanish River Blvd Boca Raton FL 33431",
    "addr:housenumber":"475",
    "addr:postcode":"33431",
    "addr:street":"Ne Spanish River Blvd",
    "iso:country":"US",
    "sg:address":"475 NE Spanish River Blvd",
    "sg:city":"Boca Raton",
    "sg:classifiers":[
        {
            "category":"Restaurant",
            "type":"Food & Drink"
        }
    ],
    "sg:phone":"+1 561 395 4929",
    "sg:postcode":"33431",
    "sg:province":"FL",
    "sg:tags":[
        "eating"
    ],
    "wof:name":"Griddle",
    "wof:placetype":"venue"
},
  "geometry": {"coordinates":[-80.080882,26.386088],"type":"Point"}
}