{
  "type": "Feature",
  "properties": {
    "addr:full":"5084 NW 74th Ave Miami FL 33166",
    "addr:housenumber":"5084",
    "addr:postcode":"33166",
    "addr:street":"Nw 74Th Ave",
    "iso:country":"US",
    "sg:address":"5084 NW 74th Ave",
    "sg:city":"Miami",
    "sg:classifiers":[
        {
            "category":"Wholesale",
            "subcategory":"Machinery & Supplies",
            "type":"Manufacturing & Wholesale Goods"
        }
    ],
    "sg:phone":"+1 305 436 5585",
    "sg:postcode":"33166",
    "sg:province":"FL",
    "sg:tags":[
        "cargo",
        "container",
        "freight"
    ],
    "wof:name":"Elite Transportation Of Miami",
    "wof:placetype":"venue"
},
  "geometry": {"coordinates":[-80.317624,25.819143],"type":"Point"}
}