{
  "type": "Feature",
  "properties": {
    "iso:country":"US",
    "sg:address":"121 Cardinal Rd",
    "sg:city":"Saint Augustine",
    "sg:classifiers":[
        {
            "category":"Marine",
            "type":"Transportation"
        }
    ],
    "sg:phone":"+1 904 797 3676",
    "sg:postcode":"32086",
    "sg:province":"FL",
    "sg:tags":[
        "water",
        "transport"
    ],
    "wof:name":"Great White Charters",
    "wof:placetype":"venue"
},
  "geometry": {"coordinates":[-81.31552499999999,29.849596],"type":"Point"}
}