{
  "type": "Feature",
  "properties": {
    "addr:full":"8595 College Pkwy Fort Myers FL 33919",
    "addr:housenumber":"8595",
    "addr:postcode":"33919",
    "addr:street":"College Pkwy",
    "iso:country":"US",
    "sg:address":"8595 College Pkwy",
    "sg:city":"Fort Myers",
    "sg:classifiers":[
        {
            "category":"Education",
            "subcategory":"Vocational School",
            "type":"Public Place"
        }
    ],
    "sg:phone":"+1 239 481 0017",
    "sg:postcode":"33919",
    "sg:province":"FL",
    "sg:tags":[
        "real estate"
    ],
    "wof:name":"Ed Klopfer Schools Of Rl Est",
    "wof:placetype":"venue"
},
  "geometry": {"coordinates":[-81.897128,26.556519],"type":"Point"}
}