{
  "type": "Feature",
  "properties": {
    "addr:full":"10050 Burnt Store Rd Punta Gorda FL 33950",
    "addr:housenumber":"10050",
    "addr:postcode":"33950",
    "addr:street":"Burnt Store Rd",
    "iso:country":"US",
    "sg:address":"10050 Burnt Store Rd",
    "sg:city":"Punta Gorda",
    "sg:classifiers":[
        {
            "category":"Travel",
            "subcategory":"Travel Agent",
            "type":"Entertainment"
        }
    ],
    "sg:phone":"+1 941 639 2313",
    "sg:postcode":"33950",
    "sg:province":"FL",
    "sg:tags":[
        "agency"
    ],
    "wof:name":"Burnt Store Travel",
    "wof:placetype":"venue"
},
  "geometry": {"coordinates":[-82.02328199999999,26.888956],"type":"Point"}
}