{
  "type": "Feature",
  "properties": {
    "addr:full":"13500 Tamiami Trl N Naples FL 34110",
    "addr:housenumber":"13500",
    "addr:postcode":"34110",
    "addr:street":"Tamiami Trl N",
    "iso:country":"US",
    "sg:address":"13500 Tamiami Trl N",
    "sg:city":"Naples",
    "sg:classifiers":[
        {
            "category":"Banks & Credit Unions",
            "subcategory":"Bank",
            "type":"Services"
        }
    ],
    "sg:phone":"+1 239 513 1040",
    "sg:postcode":"34110",
    "sg:province":"FL",
    "sg:tags":[
        "financing"
    ],
    "wof:name":"Fee Group",
    "wof:placetype":"venue"
},
  "geometry": {"coordinates":[-81.801959,26.293187],"type":"Point"}
}