{
  "type": "Feature",
  "properties": {
    "iso:country":"US",
    "sg:address":"12825 SW 42nd St",
    "sg:city":"Miami",
    "sg:classifiers":[
        {
            "category":"Restaurant",
            "type":"Food & Drink"
        }
    ],
    "sg:phone":"+1 305 228 2636",
    "sg:postcode":"33175",
    "sg:province":"FL",
    "sg:tags":[
        "eating"
    ],
    "wof:name":"Rinconicito Paisa",
    "wof:placetype":"venue"
},
  "geometry": {"coordinates":[-80.403173,25.729669],"type":"Point"}
}