{
  "type": "Feature",
  "properties": {
    "addr:full":"712 Date Palm Rd Vero Beach FL 32963",
    "addr:housenumber":"712",
    "addr:postcode":"32963",
    "addr:street":"Date Palm Rd",
    "iso:country":"US",
    "sg:address":"712 Date Palm Rd",
    "sg:city":"Vero Beach",
    "sg:classifiers":[
        {
            "category":"Professional",
            "type":"Services"
        }
    ],
    "sg:phone":"+1 772 567 6087",
    "sg:postcode":"32963",
    "sg:province":"FL",
    "sg:tags":[
        "establishment"
    ],
    "wof:name":"Fox Raphael P",
    "wof:placetype":"venue"
},
  "geometry": {"coordinates":[-80.35887200000001,27.657105],"type":"Point"}
}