{
  "type": "Feature",
  "properties": {
    "iso:country":"US",
    "sg:address":"41 Oak Village Blvd",
    "sg:city":"Homosassa",
    "sg:classifiers":[
        {
            "category":"Professional",
            "type":"Services"
        }
    ],
    "sg:phone":"+1 352 382 3873",
    "sg:postcode":"34446",
    "sg:province":"FL",
    "wof:name":"JDB Code Svc Inc",
    "wof:placetype":"venue"
},
  "geometry": {"coordinates":[-82.526723,28.71272],"type":"Point"}
}