{
  "type": "Feature",
  "properties": {
    "iso:country":"US",
    "sg:address":"23046 State Road 54",
    "sg:city":"Lutz",
    "sg:classifiers":[
        {
            "category":"Home & Garden",
            "subcategory":"Furniture",
            "type":"Retail Goods"
        }
    ],
    "sg:phone":"+1 813 909 2411",
    "sg:postcode":"33549",
    "sg:province":"FL",
    "sg:tags":[
        "store"
    ],
    "sg:website":"http://www.roomexchangeonline.com",
    "wof:name":"The Room Exchange",
    "wof:placetype":"venue"
},
  "geometry": {"coordinates":[-82.433379,28.185706],"type":"Point"}
}