{
  "type": "Feature",
  "properties": {
    "iso:country":"US",
    "sg:address":"11212 SW 184th St",
    "sg:city":"Miami",
    "sg:classifiers":[
        {
            "category":"Government",
            "subcategory":"Office",
            "type":"Public Place"
        }
    ],
    "sg:phone":"+1 305 234 2120",
    "sg:postcode":"33157",
    "sg:province":"FL",
    "sg:tags":[
        "township",
        "government-city",
        "village"
    ],
    "wof:name":"Pinecrest Village Of",
    "wof:placetype":"venue"
},
  "geometry": {"coordinates":[-80.372643,25.597869],"type":"Point"}
}