{
  "type": "Feature",
  "properties": {
    "addr:full":"4001 N 30th Ave Hollywood FL 33020",
    "addr:housenumber":"4001",
    "addr:postcode":"33020",
    "addr:street":"N 30Th Ave",
    "iso:country":"US",
    "sg:address":"4001 N 30th Ave",
    "sg:city":"Hollywood",
    "sg:classifiers":[
        {
            "category":"Building & Trades",
            "subcategory":"Equipment Rental",
            "type":"Services"
        }
    ],
    "sg:phone":"+1 954 965 0277",
    "sg:postcode":"33020",
    "sg:province":"FL",
    "sg:tags":[
        "wire",
        "fabricated",
        "mfg"
    ],
    "wof:name":"National Rent-A-Fence",
    "wof:placetype":"venue"
},
  "geometry": {"coordinates":[-80.169172,26.047898],"type":"Point"}
}