{
  "type": "Feature",
  "properties": {
    "iso:country":"US",
    "sg:address":"6475 Shoreline Dr",
    "sg:city":"Saint Petersburg",
    "sg:classifiers":[
        {
            "category":"Insurance",
            "subcategory":"Insurance Agent",
            "type":"Services"
        }
    ],
    "sg:phone":"+1 727 392 8656",
    "sg:postcode":"33708",
    "sg:province":"FL",
    "wof:name":"Curt Thomas CLU",
    "wof:placetype":"venue"
},
  "geometry": {"coordinates":[-82.772392,27.829441],"type":"Point"}
}