{
  "type": "Feature",
  "properties": {
    "addr:full":"1460 Beltrees St Dunedin FL 34698",
    "addr:housenumber":"1460",
    "addr:postcode":"34698",
    "addr:street":"Beltrees St",
    "iso:country":"US",
    "sg:address":"1460 Beltrees St",
    "sg:city":"Dunedin",
    "sg:classifiers":[
        {
            "category":"Health Services",
            "subcategory":"Doctor",
            "type":"Services"
        }
    ],
    "sg:phone":"+1 727 736 5120",
    "sg:postcode":"34698",
    "sg:province":"FL",
    "sg:tags":[
        "clinic"
    ],
    "wof:name":"JSA Healthcare",
    "wof:placetype":"venue"
},
  "geometry": {"coordinates":[-82.76459,28.005554],"type":"Point"}
}