{
  "type": "Feature",
  "properties": {
    "iso:country":"US",
    "sg:address":"3740 Beach Blvd",
    "sg:city":"Jacksonville",
    "sg:classifiers":[
        {
            "category":"Professional",
            "subcategory":"Lawyer & Legal Services",
            "type":"Services"
        }
    ],
    "sg:phone":"+1 904 396 6614",
    "sg:postcode":"32207",
    "sg:province":"FL",
    "sg:tags":[
        "attorney"
    ],
    "wof:name":"Ronald S Cohen",
    "wof:placetype":"venue"
},
  "geometry": {"coordinates":[-81.627274,30.302098],"type":"Point"}
}