{
  "type": "Feature",
  "properties": {
    "iso:country":"US",
    "sg:address":"8225 Sedgefield Dr",
    "sg:city":"Pensacola",
    "sg:classifiers":[
        {
            "category":"Retail",
            "subcategory":"Repair Shop",
            "type":"Services"
        }
    ],
    "sg:phone":"+1 850 455 0153",
    "sg:postcode":"32507",
    "sg:province":"FL",
    "sg:tags":[
        "small",
        "major",
        "appliance",
        "refinishing"
    ],
    "wof:name":"Reliance Service Company",
    "wof:placetype":"venue"
},
  "geometry": {"coordinates":[-87.32116000000001,30.378472],"type":"Point"}
}