{
  "type": "Feature",
  "properties": {
    "iso:country":"US",
    "sg:address":"4436 Inverrary Blvd",
    "sg:city":"Lauderhill",
    "sg:classifiers":[
        {
            "category":"Place Of Worship",
            "subcategory":"Church",
            "type":"Public Place"
        },
        {
            "category":"Place Of Worship",
            "type":"Public Place"
        }
    ],
    "sg:phone":"+1 954 749 3663",
    "sg:postcode":"33319",
    "sg:province":"FL",
    "sg:tags":[
        "churches-interdenominational",
        "churches-various",
        "denomination"
    ],
    "wof:name":"Sunrise Haitian Baptist Church",
    "wof:placetype":"venue"
},
  "geometry": {"coordinates":[-80.239861,26.179548],"type":"Point"}
}