{
  "type": "Feature",
  "properties": {
    "addr:full":"2212 Gulf Gate Dr Sarasota FL 34231",
    "addr:housenumber":"2212",
    "addr:postcode":"34231",
    "addr:street":"Gulf Gate Dr",
    "iso:country":"US",
    "sg:address":"2212 Gulf Gate Dr",
    "sg:city":"Sarasota",
    "sg:classifiers":[
        {
            "category":"Restaurant",
            "type":"Food & Drink"
        }
    ],
    "sg:phone":"+1 941 921 9084",
    "sg:postcode":"34231",
    "sg:province":"FL",
    "sg:tags":[
        "delicatessen"
    ],
    "wof:name":"A Taste Of Europe Intl Deli",
    "wof:placetype":"venue"
},
  "geometry": {"coordinates":[-82.52002,27.259017],"type":"Point"}
}