{
  "type": "Feature",
  "properties": {
    "iso:country":"US",
    "sg:address":"1219 Branda Vista Dr",
    "sg:city":"Brandon",
    "sg:classifiers":[
        {
            "category":"Place Of Worship",
            "subcategory":"Church",
            "type":"Public Place"
        },
        {
            "category":"Place Of Worship",
            "type":"Public Place"
        }
    ],
    "sg:phone":"+1 813 657 0462",
    "sg:postcode":"33510",
    "sg:province":"FL",
    "sg:tags":[
        "churches-baptist-general",
        "churches-baptist"
    ],
    "wof:name":"Florida Future Business Ame",
    "wof:placetype":"venue"
},
  "geometry": {"coordinates":[-82.2808,27.95821],"type":"Point"}
}