{
  "type": "Feature",
  "properties": {
    "addr:full":"4725 Lakeland Commerce Pkwy Lakeland FL 33805",
    "addr:housenumber":"4725",
    "addr:postcode":"33805",
    "addr:street":"Lakeland Commerce Pkwy",
    "iso:country":"US",
    "sg:address":"4725 Lakeland Commerce Pkwy",
    "sg:city":"Lakeland",
    "sg:classifiers":[
        {
            "category":"Shopping",
            "subcategory":"Gifts & Souvenirs",
            "type":"Retail Goods"
        }
    ],
    "sg:phone":"+1 863 667 3776",
    "sg:postcode":"33805",
    "sg:province":"FL",
    "sg:tags":[
        "cards",
        "greeting"
    ],
    "wof:name":"Mannco Enterprises Inc",
    "wof:placetype":"venue"
},
  "geometry": {"coordinates":[-81.907729,28.104356],"type":"Point"}
}