{
  "type": "Feature",
  "properties": {
    "addr:full":"604 S Pinellas Ave Tarpon Springs FL 34689",
    "addr:housenumber":"604",
    "addr:postcode":"34689",
    "addr:street":"S Pinellas Ave",
    "iso:country":"US",
    "sg:address":"604 S Pinellas Ave",
    "sg:city":"Tarpon Springs",
    "sg:classifiers":[
        {
            "category":"Food & Beverages",
            "subcategory":"Liquor & Beverages",
            "type":"Retail Goods"
        }
    ],
    "sg:phone":"+1 727 938 4000",
    "sg:postcode":"34689",
    "sg:province":"FL",
    "sg:tags":[
        "alcoholic"
    ],
    "wof:name":"A To Z Discount Beverage",
    "wof:placetype":"venue"
},
  "geometry": {"coordinates":[-82.75662199999999,28.140411],"type":"Point"}
}