{
  "type": "Feature",
  "properties": {
    "iso:country":"US",
    "sg:address":"100 Biscayne Blvd",
    "sg:city":"Miami",
    "sg:classifiers":[
        {
            "category":"Professional",
            "subcategory":"Research",
            "type":"Services"
        }
    ],
    "sg:phone":"+1 305 416 0200",
    "sg:postcode":"33132",
    "sg:province":"FL",
    "sg:tags":[
        "market",
        "analysis"
    ],
    "wof:name":"Ebony Marketing Research",
    "wof:placetype":"venue"
},
  "geometry": {"coordinates":[-80.187522,25.776241],"type":"Point"}
}