{
  "type": "Feature",
  "properties": {
    "iso:country":"US",
    "sg:address":"3825 NW 32nd Ave",
    "sg:city":"Miami",
    "sg:classifiers":[
        {
            "category":"Building & Trades",
            "subcategory":"Construction",
            "type":"Services"
        }
    ],
    "sg:phone":"+1 305 633 7500",
    "sg:postcode":"33142",
    "sg:province":"FL",
    "sg:tags":[
        "woodworker"
    ],
    "wof:name":"Concepts In Wood Corp",
    "wof:placetype":"venue"
},
  "geometry": {"coordinates":[-80.24835,25.810948],"type":"Point"}
}