{
  "type": "Feature",
  "properties": {
    "iso:country":"US",
    "sg:address":"1470 Tamiami Trl",
    "sg:city":"Port Charlotte",
    "sg:classifiers":[
        {
            "category":"Autos & Motor Vehicles",
            "subcategory":"Fuel & Gas Station",
            "type":"Retail Goods"
        }
    ],
    "sg:phone":"+1 941 255 5562",
    "sg:postcode":"33948",
    "sg:province":"FL",
    "sg:tags":[
        "convenient",
        "station",
        "store"
    ],
    "wof:name":"Amerada Hess Corporation",
    "wof:placetype":"venue"
},
  "geometry": {"coordinates":[-82.152067,27.015686],"type":"Point"}
}