{
  "type": "Feature",
  "properties": {
    "iso:country":"US",
    "sg:address":"7240 S Florida Ave",
    "sg:city":"Floral City",
    "sg:classifiers":[
        {
            "category":"Restaurant",
            "type":"Food & Drink"
        }
    ],
    "sg:phone":"+1 352 344 3773",
    "sg:postcode":"34436",
    "sg:province":"FL",
    "wof:name":"Pudgees' Hot Dog Stand",
    "wof:placetype":"venue"
},
  "geometry": {"coordinates":[-82.29444700000001,28.758169],"type":"Point"}
}