{
  "type": "Feature",
  "properties": {
    "addr:full":"3016 Airport Rd Panama City FL 32405",
    "addr:housenumber":"3016",
    "addr:postcode":"32405",
    "addr:street":"Airport Rd",
    "iso:country":"US",
    "sg:address":"3016 Airport Rd",
    "sg:city":"Panama City",
    "sg:classifiers":[
        {
            "category":"Building & Trades",
            "subcategory":"Construction",
            "type":"Services"
        }
    ],
    "sg:phone":"+1 850 215 5371",
    "sg:postcode":"32405",
    "sg:province":"FL",
    "sg:tags":[
        "house"
    ],
    "wof:name":"Davis Renovations",
    "wof:placetype":"venue"
},
  "geometry": {"coordinates":[-85.687302,30.204917],"type":"Point"}
}