{
  "type": "Feature",
  "properties": {
    "iso:country":"US",
    "sg:address":"6425 Sheryl Ann Dr",
    "sg:city":"Orlando",
    "sg:classifiers":[
        {
            "category":"Banks & Credit Unions",
            "subcategory":"Investment Brokerage",
            "type":"Services"
        }
    ],
    "sg:phone":"+1 407 859 6395",
    "sg:postcode":"32809",
    "sg:province":"FL",
    "sg:tags":[
        "trust"
    ],
    "wof:name":"Staley's Lawn And Home Services Inc",
    "wof:placetype":"venue"
},
  "geometry": {"coordinates":[-81.379622,28.465134],"type":"Point"}
}