{
  "type": "Feature",
  "properties": {
    "iso:country":"US",
    "sg:address":"801 Eyrie Dr",
    "sg:city":"Oviedo",
    "sg:classifiers":[
        {
            "category":"Building & Trades",
            "subcategory":"Plumbing",
            "type":"Services"
        }
    ],
    "sg:phone":"+1 407 359 6368",
    "sg:postcode":"32765",
    "sg:province":"FL",
    "sg:tags":[
        "contractor",
        "mechanical"
    ],
    "wof:name":"Florida Central Mechanical Inc",
    "wof:placetype":"venue"
},
  "geometry": {"coordinates":[-81.2242,28.656969],"type":"Point"}
}