{
  "type": "Feature",
  "properties": {
    "iso:country":"US",
    "sg:address":"11862 SW 169th St",
    "sg:city":"Miami",
    "sg:classifiers":[
        {
            "category":"Retail",
            "subcategory":"Auto Repair",
            "type":"Services"
        }
    ],
    "sg:phone":"+1 305 254 4662",
    "sg:postcode":"33177",
    "sg:province":"FL",
    "sg:tags":[
        "wrecker"
    ],
    "wof:name":"Emergency Towing & Recovery",
    "wof:placetype":"venue"
},
  "geometry": {"coordinates":[-80.384518,25.611101],"type":"Point"}
}