{
  "type": "Feature",
  "properties": {
    "iso:country":"US",
    "sg:address":"7221 Forest Oaks Blvd",
    "sg:city":"Spring Hill",
    "sg:classifiers":[
        {
            "category":"Travel",
            "subcategory":"Travel Agent",
            "type":"Entertainment"
        }
    ],
    "sg:phone":"+1 352 686 0681",
    "sg:postcode":"34606",
    "sg:province":"FL",
    "sg:tags":[
        "agency",
        "bureau"
    ],
    "wof:name":"Enterprise Travel Service Inc",
    "wof:placetype":"venue"
},
  "geometry": {"coordinates":[-82.590368,28.490996],"type":"Point"}
}