{
  "type": "Feature",
  "properties": {
    "iso:country":"US",
    "sg:address":"245 High Point Blvd",
    "sg:city":"Delray Beach",
    "sg:classifiers":[
        {
            "category":"Real Estate",
            "subcategory":"Real Estate Operator",
            "type":"Services"
        }
    ],
    "sg:phone":"+1 561 243 9186",
    "sg:postcode":"33445",
    "sg:province":"FL",
    "sg:tags":[
        "condominium"
    ],
    "wof:name":"High Point Of Delray Beach Cnd",
    "wof:placetype":"venue"
},
  "geometry": {"coordinates":[-80.101724,26.460666],"type":"Point"}
}