{
  "type": "Feature",
  "properties": {
    "addr:full":"8785 SW 194th Ct Dunnellon FL 34432",
    "addr:housenumber":"8785",
    "addr:postcode":"34432",
    "addr:street":"Sw 194Th Ct",
    "iso:country":"US",
    "sg:address":"8785 SW 194th Ct",
    "sg:city":"Dunnellon",
    "sg:classifiers":[
        {
            "category":"Professional",
            "subcategory":"Business Services",
            "type":"Services"
        }
    ],
    "sg:phone":"+1 352 465 4160",
    "sg:postcode":"34432",
    "sg:province":"FL",
    "sg:tags":[
        "consultant",
        "coach"
    ],
    "wof:name":"Bgh Medical Legal Consulting",
    "wof:placetype":"venue"
},
  "geometry": {"coordinates":[-82.44278199999999,29.095103],"type":"Point"}
}