{
  "type": "Feature",
  "properties": {
    "iso:country":"US",
    "sg:address":"3233 S Andrews Ave",
    "sg:city":"Fort Lauderdale",
    "sg:classifiers":[
        {
            "category":"Wholesale",
            "subcategory":"Construction Materials",
            "type":"Manufacturing & Wholesale Goods"
        }
    ],
    "sg:phone":"+1 954 523 2664",
    "sg:postcode":"33316",
    "sg:province":"FL",
    "sg:tags":[
        "building"
    ],
    "wof:name":"Florida Intercontinental Inc",
    "wof:placetype":"venue"
},
  "geometry": {"coordinates":[-80.13851200000001,26.083573],"type":"Point"}
}