{
  "type": "Feature",
  "properties": {
    "iso:country":"US",
    "sg:address":"250 N Lee St",
    "sg:city":"Labelle",
    "sg:classifiers":[
        {
            "category":"Government",
            "subcategory":"Office",
            "type":"Public Place"
        }
    ],
    "sg:phone":"+1 863 675 6007",
    "sg:postcode":"33935",
    "sg:province":"FL",
    "sg:tags":[
        "county",
        "program",
        "adm"
    ],
    "wof:name":"Hendry County Economic Dev",
    "wof:placetype":"venue"
},
  "geometry": {"coordinates":[-81.43614599999999,26.764348],"type":"Point"}
}