{
  "type": "Feature",
  "properties": {
    "addr:full":"2241 S Woodland Blvd Deland FL 32720",
    "addr:housenumber":"2241",
    "addr:postcode":"32720",
    "addr:street":"S Woodland Blvd",
    "iso:country":"US",
    "sg:address":"2241 S Woodland Blvd",
    "sg:city":"Deland",
    "sg:classifiers":[
        {
            "category":"Restaurant",
            "type":"Food & Drink"
        }
    ],
    "sg:phone":"+1 386 738 7000",
    "sg:postcode":"32720",
    "sg:province":"FL",
    "wof:name":"Key West Cafe",
    "wof:placetype":"venue"
},
  "geometry": {"coordinates":[-81.30099800000001,28.989613],"type":"Point"}
}