{
  "type": "Feature",
  "properties": {
    "iso:country":"US",
    "sg:address":"7220 NW 36th St Ste 100",
    "sg:city":"Miami",
    "sg:classifiers":[
        {
            "category":"Real Estate",
            "subcategory":"Real Estate Services",
            "type":"Services"
        }
    ],
    "sg:phone":"+1 305 592 5150",
    "sg:postcode":"33166",
    "sg:province":"FL",
    "sg:tags":[
        "management"
    ],
    "wof:name":"Palmetto Services Inc.",
    "wof:placetype":"venue"
},
  "geometry": {"coordinates":[-80.31470899999999,25.80928],"type":"Point"}
}