{
  "type": "Feature",
  "properties": {
    "addr:full":"2600 SW 3rd Ave Ste 650 Miami FL 33129",
    "addr:housenumber":"2600",
    "addr:postcode":"33129",
    "addr:street":"Sw 3Rd Ave Ste 650",
    "iso:country":"US",
    "sg:address":"2600 SW 3rd Ave Ste 650",
    "sg:city":"Miami",
    "sg:classifiers":[
        {
            "category":"Real Estate",
            "subcategory":"Real Estate Services",
            "type":"Services"
        }
    ],
    "sg:phone":"+1 305 596 2900",
    "sg:postcode":"33129",
    "sg:province":"FL",
    "sg:tags":[
        "management",
        "condominium"
    ],
    "wof:name":"Palmcrest Villas",
    "wof:placetype":"venue"
},
  "geometry": {"coordinates":[-80.20826,25.75543],"type":"Point"}
}