{
  "type": "Feature",
  "properties": {
    "iso:country":"US",
    "sg:address":"9496 50th Way",
    "sg:city":"Pinellas Park",
    "sg:classifiers":[
        {
            "category":"Retail",
            "subcategory":"Auto Repair",
            "type":"Services"
        }
    ],
    "sg:phone":"+1 727 545 1714",
    "sg:postcode":"33782",
    "sg:province":"FL",
    "sg:tags":[
        "automobile",
        "installation",
        "glass"
    ],
    "wof:name":"Auto Glass Etc",
    "wof:placetype":"venue"
},
  "geometry": {"coordinates":[-82.702697,27.857484],"type":"Point"}
}