{
  "type": "Feature",
  "properties": {
    "addr:full":"9440 Richmond Cir Boca Raton FL 33434",
    "addr:housenumber":"9440",
    "addr:postcode":"33434",
    "addr:street":"Richmond Cir",
    "iso:country":"US",
    "sg:address":"9440 Richmond Cir",
    "sg:city":"Boca Raton",
    "sg:classifiers":[
        {
            "category":"Professional",
            "subcategory":"Management & Consulting",
            "type":"Services"
        }
    ],
    "sg:phone":"+1 561 852 1710",
    "sg:postcode":"33434",
    "sg:province":"FL",
    "sg:tags":[
        "export"
    ],
    "wof:name":"Pioneer Sales & Marketing",
    "wof:placetype":"venue"
},
  "geometry": {"coordinates":[-80.19354800000001,26.390704],"type":"Point"}
}