{
  "type": "Feature",
  "properties": {
    "addr:full":"1135 NE Krome Ter Homestead FL 33030",
    "addr:housenumber":"1135",
    "addr:postcode":"33030",
    "addr:street":"Ne Krome Ter",
    "iso:country":"US",
    "sg:address":"1135 NE Krome Ter",
    "sg:city":"Homestead",
    "sg:classifiers":[
        {
            "category":"Real Estate",
            "subcategory":"Surveying",
            "type":"Services"
        }
    ],
    "sg:phone":"+1 305 247 1356",
    "sg:postcode":"33030",
    "sg:province":"FL",
    "wof:name":"Frank Makowski Pe",
    "wof:placetype":"venue"
},
  "geometry": {"coordinates":[-80.475785,25.481421],"type":"Point"}
}