{
  "type": "Feature",
  "properties": {
    "iso:country":"US",
    "sg:address":"12830 Metro Pkwy Ste 1",
    "sg:city":"Fort Myers",
    "sg:classifiers":[
        {
            "category":"Home & Garden",
            "subcategory":"Hardware",
            "type":"Retail Goods"
        }
    ],
    "sg:phone":"+1 239 561 3560",
    "sg:postcode":"33966",
    "sg:province":"FL",
    "sg:tags":[
        "store"
    ],
    "sg:website":"www.acehardware.com",
    "wof:name":"Vision Ace Hardware",
    "wof:placetype":"venue"
},
  "geometry": {"coordinates":[-81.853093,26.555397],"type":"Point"}
}