{
  "type": "Feature",
  "properties": {
    "iso:country":"US",
    "sg:address":"1566 Dixie Hwy",
    "sg:city":"Coral Gables",
    "sg:classifiers":[
        {
            "category":"Personal",
            "subcategory":"Beauty Salon",
            "type":"Services"
        }
    ],
    "sg:phone":"+1 305 661 9050",
    "sg:postcode":"33146",
    "sg:province":"FL",
    "wof:name":"Magpie Salon",
    "wof:placetype":"venue"
},
  "geometry": {"coordinates":[-80.28465300000001,25.708189],"type":"Point"}
}