{
  "type": "Feature",
  "properties": {
    "iso:country":"US",
    "sg:address":"1601 Atlantic Blvd",
    "sg:city":"Jacksonville",
    "sg:classifiers":[
        {
            "category":"Organizations",
            "subcategory":"Labor Organization",
            "type":"Services"
        }
    ],
    "sg:phone":"+1 904 396 4063",
    "sg:postcode":"32207",
    "sg:province":"FL",
    "sg:tags":[
        "union"
    ],
    "wof:name":"Duval Teachers United",
    "wof:placetype":"venue"
},
  "geometry": {"coordinates":[-81.651691,30.305716],"type":"Point"}
}