{
  "type": "Feature",
  "properties": {
    "addr:full":"16150 Aviation Loop Dr Brooksville FL 34604",
    "addr:housenumber":"16150",
    "addr:postcode":"34604",
    "addr:street":"Aviation Loop Dr",
    "iso:country":"US",
    "sg:address":"16150 Aviation Loop Dr",
    "sg:city":"Brooksville",
    "sg:classifiers":[
        {
            "category":"Government",
            "subcategory":"Post Office",
            "type":"Public Place"
        }
    ],
    "sg:phone":"+1 352 000 1111",
    "sg:postcode":"34604",
    "sg:province":"FL",
    "wof:name":"US Post Office",
    "wof:placetype":"venue"
},
  "geometry": {"coordinates":[-82.46548799999999,28.48042],"type":"Point"}
}