{
  "type": "Feature",
  "properties": {
    "addr:full":"3975 NW 103rd Dr Coral Springs FL 33065",
    "addr:housenumber":"3975",
    "addr:postcode":"33065",
    "addr:street":"Nw 103Rd Dr",
    "iso:country":"US",
    "sg:address":"3975 NW 103rd Dr",
    "sg:city":"Coral Springs",
    "sg:classifiers":[
        {
            "category":"Shopping",
            "subcategory":"Jewelry",
            "type":"Retail Goods"
        }
    ],
    "sg:phone":"+1 954 796 4178",
    "sg:postcode":"33065",
    "sg:province":"FL",
    "sg:tags":[
        "jeweler"
    ],
    "wof:name":"Sterling Moments",
    "wof:placetype":"venue"
},
  "geometry": {"coordinates":[-80.263853,26.280301],"type":"Point"}
}