{
  "type": "Feature",
  "properties": {
    "addr:full":"17820 NW 22nd Ave Opa Locka FL 33056",
    "addr:housenumber":"17820",
    "addr:postcode":"33056",
    "addr:street":"Nw 22Nd Ave;Locka",
    "iso:country":"US",
    "sg:address":"17820 NW 22nd Ave",
    "sg:city":"Opa Locka",
    "sg:classifiers":[
        {
            "category":"Health Services",
            "subcategory":"Nursing And Care Facility",
            "type":"Services"
        }
    ],
    "sg:phone":"+1 305 623 0710",
    "sg:postcode":"33056",
    "sg:province":"FL",
    "sg:tags":[
        "intermediate",
        "retirement",
        "community",
        "home"
    ],
    "wof:name":"Lucille's Loving Care",
    "wof:placetype":"venue"
},
  "geometry": {"coordinates":[-80.23719,25.937479],"type":"Point"}
}