{
  "type": "Feature",
  "properties": {
    "iso:country":"US",
    "sg:address":"27286 Hiawatha Blvd",
    "sg:city":"Brooksville",
    "sg:classifiers":[
        {
            "category":"Building & Trades",
            "subcategory":"Construction",
            "type":"Services"
        }
    ],
    "sg:phone":"+1 352 238 0849",
    "sg:postcode":"34601",
    "sg:province":"FL",
    "sg:tags":[
        "handyman"
    ],
    "wof:name":"Heritage Handyman",
    "wof:placetype":"venue"
},
  "geometry": {"coordinates":[-82.288935,28.664954],"type":"Point"}
}