{
  "type": "Feature",
  "properties": {
    "iso:country":"US",
    "sg:address":"3106 Holly St",
    "sg:city":"Lake Wales",
    "sg:classifiers":[
        {
            "category":"Building & Trades",
            "subcategory":"Construction",
            "type":"Services"
        }
    ],
    "sg:phone":"+1 205 368 5623",
    "sg:postcode":"33898",
    "sg:province":"FL",
    "sg:tags":[
        "carpentry",
        "contractor"
    ],
    "wof:name":"Kenneth Edwards",
    "wof:placetype":"venue"
},
  "geometry": {"coordinates":[-81.53750100000001,27.887919],"type":"Point"}
}