{
  "type": "Feature",
  "properties": {
    "addr:full":"545 Patrick Ave Merritt Island FL 32953",
    "addr:housenumber":"545",
    "addr:postcode":"32953",
    "addr:street":"Patrick Ave",
    "iso:country":"US",
    "sg:address":"545 Patrick Ave",
    "sg:city":"Merritt Island",
    "sg:classifiers":[
        {
            "category":"Professional",
            "subcategory":"Advertising",
            "type":"Services"
        }
    ],
    "sg:phone":"+1 321 452 4894",
    "sg:postcode":"32953",
    "sg:province":"FL",
    "sg:tags":[
        "counselor"
    ],
    "sg:website":"www.grammargirl.com",
    "wof:name":"Glad Tidings",
    "wof:placetype":"venue"
},
  "geometry": {"coordinates":[-80.68878100000001,28.366814],"type":"Point"}
}