{
  "type": "Feature",
  "properties": {
    "iso:country":"US",
    "sg:address":"1120 Mahogany Way",
    "sg:city":"Delray Beach",
    "sg:classifiers":[
        {
            "category":"Retail",
            "subcategory":"Repair Shop",
            "type":"Services"
        }
    ],
    "sg:phone":"+1 561 279 9449",
    "sg:postcode":"33445",
    "sg:province":"FL",
    "sg:tags":[
        "related"
    ],
    "wof:name":"Healthcare Equipment Inc",
    "wof:placetype":"venue"
},
  "geometry": {"coordinates":[-80.09786099999999,26.442257],"type":"Point"}
}