{
  "type": "Feature",
  "properties": {
    "iso:country":"US",
    "sg:address":"9342 Cumberland Station Dr",
    "sg:city":"Jacksonville",
    "sg:classifiers":[
        {
            "category":"Professional",
            "subcategory":"Computer Services",
            "type":"Services"
        }
    ],
    "sg:phone":"+1 904 733 4948",
    "sg:postcode":"32257",
    "sg:province":"FL",
    "sg:tags":[
        "prepackaged",
        "software"
    ],
    "wof:name":"Silence Software",
    "wof:placetype":"venue"
},
  "geometry": {"coordinates":[-81.593711,30.209902],"type":"Point"}
}