{
  "type": "Feature",
  "properties": {
    "addr:full":"2720 N Harbor City Blvd Melbourne FL 32935",
    "addr:housenumber":"2720",
    "addr:postcode":"32935",
    "addr:street":"N Harbor City Blvd",
    "iso:country":"US",
    "sg:address":"2720 N Harbor City Blvd",
    "sg:city":"Melbourne",
    "sg:classifiers":[
        {
            "category":"Real Estate",
            "subcategory":"Real Estate Agent",
            "type":"Services"
        }
    ],
    "sg:phone":"+1 321 255 5036",
    "sg:postcode":"32935",
    "sg:province":"FL",
    "wof:name":"Realty Executives Space Coast",
    "wof:placetype":"venue"
},
  "geometry": {"coordinates":[-80.638603,28.148392],"type":"Point"}
}