{
  "type": "Feature",
  "properties": {
    "addr:full":"4080 2nd Ave Laurel Hill FL 32567",
    "addr:housenumber":"4080",
    "addr:postcode":"32567",
    "addr:street":"2Nd Ave",
    "iso:country":"US",
    "sg:address":"4080 2nd Ave",
    "sg:city":"Laurel Hill",
    "sg:classifiers":[
        {
            "category":"Retail",
            "subcategory":"Repair Shop",
            "type":"Services"
        }
    ],
    "sg:phone":"+1 850 652 3652",
    "sg:postcode":"32567",
    "sg:province":"FL",
    "sg:tags":[
        "heavy",
        "equipment"
    ],
    "wof:name":"Track & Machine Inc",
    "wof:placetype":"venue"
},
  "geometry": {"coordinates":[-86.446387,30.963444],"type":"Point"}
}