{
  "type": "Feature",
  "properties": {
    "iso:country":"US",
    "sg:address":"8405 SW 44th Pl",
    "sg:city":"Bushnell",
    "sg:classifiers":[
        {
            "category":"Banks & Credit Unions",
            "subcategory":"Financial Services",
            "type":"Services"
        }
    ],
    "sg:phone":"+1 352 793 3513",
    "sg:postcode":"33513",
    "sg:province":"FL",
    "sg:tags":[
        "investor"
    ],
    "wof:name":"Sumter Investments Inc",
    "wof:placetype":"venue"
},
  "geometry": {"coordinates":[-82.23787799999999,28.692393],"type":"Point"}
}