{
  "type": "Feature",
  "properties": {
    "addr:full":"2820 Tennis Club Dr West Palm Beach FL 33417",
    "addr:housenumber":"2820",
    "addr:postcode":"33417",
    "addr:street":"Tennis Club Dr",
    "iso:country":"US",
    "sg:address":"2820 Tennis Club Dr",
    "sg:city":"West Palm Beach",
    "sg:classifiers":[
        {
            "category":"Retail",
            "subcategory":"Auto Repair",
            "type":"Services"
        }
    ],
    "sg:phone":"+1 561 601 8630",
    "sg:postcode":"33417",
    "sg:province":"FL",
    "sg:tags":[
        "repairing",
        "automobile"
    ],
    "wof:name":"One Perfect Touch",
    "wof:placetype":"venue"
},
  "geometry": {"coordinates":[-80.118543,26.719386],"type":"Point"}
}