{
  "type": "Feature",
  "properties": {
    "addr:full":"2112 SW 34 St Gainesville FL 32608",
    "addr:housenumber":"2112",
    "addr:postcode":"32608",
    "addr:street":"Sw 34 St",
    "iso:country":"US",
    "sg:address":"2112 SW 34 St",
    "sg:city":"Gainesville",
    "sg:classifiers":[
        {
            "category":"Retail",
            "subcategory":"Laundry & Dry Cleaning",
            "type":"Services"
        }
    ],
    "sg:phone":"+1 352 372 6139",
    "sg:postcode":"32608",
    "sg:province":"FL",
    "sg:tags":[
        "r"
    ],
    "wof:name":"A 1 Alterations",
    "wof:placetype":"venue"
},
  "geometry": {"coordinates":[-82.367842,29.600135],"type":"Point"}
}