{
  "type": "Feature",
  "properties": {
    "addr:full":"1200 NE Miami Gardens Dr # 405 Miami FL 33179",
    "addr:housenumber":"1200;405",
    "addr:postcode":"33179",
    "addr:street":"Ne Miami Gardens Dr #",
    "iso:country":"US",
    "sg:address":"1200 NE Miami Gardens Dr # 405",
    "sg:city":"Miami",
    "sg:classifiers":[
        {
            "category":"Professional",
            "subcategory":"Printing & Photocopies",
            "type":"Services"
        }
    ],
    "sg:phone":"+1 305 861 6636",
    "sg:postcode":"33179",
    "sg:province":"FL",
    "sg:tags":[
        "services-commercial",
        "form",
        "printers-business"
    ],
    "wof:name":"Label Depot",
    "wof:placetype":"venue"
},
  "geometry": {"coordinates":[-80.17688800000001,25.945499],"type":"Point"}
}