{
  "type": "Feature",
  "properties": {
    "addr:full":"2432 Manatee Ave E Bradenton FL 34208",
    "addr:housenumber":"2432",
    "addr:postcode":"34208",
    "addr:street":"Manatee Ave E",
    "iso:country":"US",
    "sg:address":"2432 Manatee Ave E",
    "sg:city":"Bradenton",
    "sg:classifiers":[
        {
            "category":"Organizations",
            "subcategory":"Religious Organization",
            "type":"Services"
        }
    ],
    "sg:phone":"+1 941 747 1122",
    "sg:postcode":"34208",
    "sg:province":"FL",
    "sg:tags":[
        "church"
    ],
    "wof:name":"Eagle's Landing Church",
    "wof:placetype":"venue"
},
  "geometry": {"coordinates":[-82.53335199999999,27.496137],"type":"Point"}
}