{
  "type": "Feature",
  "properties": {
    "iso:country":"US",
    "sg:address":"4485 NW 93rd Doral Ct",
    "sg:city":"Doral",
    "sg:classifiers":[
        {
            "category":"Education",
            "subcategory":"Dance Studio",
            "type":"Public Place"
        }
    ],
    "sg:phone":"+1 305 594 0047",
    "sg:postcode":"33178",
    "sg:province":"FL",
    "sg:tags":[
        "instruction",
        "dancing"
    ],
    "wof:name":"Generations Dance Studio Inc",
    "wof:placetype":"venue"
},
  "geometry": {"coordinates":[-80.346653,25.812808],"type":"Point"}
}