{
  "type": "Feature",
  "properties": {
    "addr:full":"1197 Willis Ave Daytona Beach FL 32114",
    "addr:housenumber":"1197",
    "addr:postcode":"32114",
    "addr:street":"Willis Ave",
    "iso:country":"US",
    "sg:address":"1197 Willis Ave",
    "sg:city":"Daytona Beach",
    "sg:classifiers":[
        {
            "category":"Social Services",
            "subcategory":"Child Care",
            "type":"Services"
        }
    ],
    "sg:phone":"+1 386 238 1402",
    "sg:postcode":"32114",
    "sg:province":"FL",
    "sg:website":"www.kindercare.com",
    "wof:name":"Kinder Care Learning Ctr",
    "wof:placetype":"venue"
},
  "geometry": {"coordinates":[-81.051202,29.206484],"type":"Point"}
}