{
  "type": "Feature",
  "properties": {
    "iso:country":"US",
    "sg:address":"7711 N Military Trl",
    "sg:city":"Palm Beach Gardens",
    "sg:classifiers":[
        {
            "category":"Professional",
            "subcategory":"Advertising",
            "type":"Services"
        }
    ],
    "sg:phone":"+1 561 799 1188",
    "sg:postcode":"33410",
    "sg:province":"FL",
    "sg:tags":[
        "agency"
    ],
    "wof:name":"J & S Marketing & Advertising",
    "wof:placetype":"venue"
},
  "geometry": {"coordinates":[-80.107033,26.790386],"type":"Point"}
}