{
  "type": "Feature",
  "properties": {
    "addr:full":"1106 W Dixie St Plant City FL 33563",
    "addr:housenumber":"1106",
    "addr:postcode":"33563",
    "addr:street":"W Dixie St",
    "iso:country":"US",
    "sg:address":"1106 W Dixie St",
    "sg:city":"Plant City",
    "sg:classifiers":[
        {
            "category":"Shopping",
            "type":"Retail Goods"
        }
    ],
    "sg:phone":"+1 813 707 9322",
    "sg:postcode":"33563",
    "sg:province":"FL",
    "sg:tags":[
        "pet",
        "food",
        "supply"
    ],
    "wof:name":"L A's Pet Supplies",
    "wof:placetype":"venue"
},
  "geometry": {"coordinates":[-82.132981,28.028662],"type":"Point"}
}