{
  "type": "Feature",
  "properties": {
    "addr:full":"3580 N Federal Hwy Lighthouse Point FL 33064",
    "addr:housenumber":"3580",
    "addr:postcode":"33064",
    "addr:street":"N Federal Hwy",
    "iso:country":"US",
    "sg:address":"3580 N Federal Hwy",
    "sg:city":"Lighthouse Point",
    "sg:classifiers":[
        {
            "category":"Shopping",
            "subcategory":"Pharmacy",
            "type":"Retail Goods"
        }
    ],
    "sg:phone":"+1 954 943 3012",
    "sg:postcode":"33064",
    "sg:province":"FL",
    "wof:name":"CBS",
    "wof:placetype":"venue"
},
  "geometry": {"coordinates":[-80.097598,26.27439],"type":"Point"}
}