{
  "type": "Feature",
  "properties": {
    "iso:country":"US",
    "sg:address":"664 Azalea Ln",
    "sg:city":"Vero Beach",
    "sg:classifiers":[
        {
            "category":"Real Estate",
            "subcategory":"Real Estate Agent",
            "type":"Services"
        }
    ],
    "sg:phone":"+1 772 231 4400",
    "sg:postcode":"32963",
    "sg:province":"FL",
    "wof:name":"Re/Max Connection",
    "wof:placetype":"venue"
},
  "geometry": {"coordinates":[-80.361688,27.652302],"type":"Point"}
}