{
  "type": "Feature",
  "properties": {
    "addr:full":"11839 San Jose Blvd Jacksonville FL 32223",
    "addr:housenumber":"11839",
    "addr:postcode":"32223",
    "addr:street":"San Jose Blvd",
    "iso:country":"US",
    "sg:address":"11839 San Jose Blvd",
    "sg:city":"Jacksonville",
    "sg:classifiers":[
        {
            "category":"Professional",
            "subcategory":"Employment Agencies",
            "type":"Services"
        }
    ],
    "sg:phone":"+1 904 880 2336",
    "sg:postcode":"32223",
    "sg:province":"FL",
    "sg:tags":[
        "leasing"
    ],
    "wof:name":"PEO Professionals",
    "wof:placetype":"venue"
},
  "geometry": {"coordinates":[-81.63262899999999,30.157322],"type":"Point"}
}