{
  "type": "Feature",
  "properties": {
    "addr:full":"1940 Cleveland St Hollywood FL 33020",
    "addr:housenumber":"1940",
    "addr:postcode":"33020",
    "addr:street":"Cleveland St",
    "iso:country":"US",
    "sg:address":"1940 Cleveland St",
    "sg:city":"Hollywood",
    "sg:classifiers":[
        {
            "category":"Wholesale",
            "subcategory":"Apparel",
            "type":"Manufacturing & Wholesale Goods"
        }
    ],
    "sg:phone":"+1 954 920 5301",
    "sg:postcode":"33020",
    "sg:province":"FL",
    "sg:tags":[
        "clothing"
    ],
    "wof:name":"Tee Tee Co",
    "wof:placetype":"venue"
},
  "geometry": {"coordinates":[-80.14649300000001,26.023379],"type":"Point"}
}