{
  "type": "Feature",
  "properties": {
    "iso:country":"US",
    "sg:address":"4148 E 8th Ave",
    "sg:city":"Hialeah",
    "sg:classifiers":[
        {
            "category":"Retail",
            "subcategory":"Veterinary Services",
            "type":"Services"
        }
    ],
    "sg:phone":"+1 305 688 0561",
    "sg:postcode":"33013",
    "sg:province":"FL",
    "sg:tags":[
        "pet",
        "hospital",
        "clinic",
        "veterinarian",
        "animal",
        "special"
    ],
    "sg:website":"http://www.muelleranimalhospital.net",
    "wof:name":"Mueller Animal Hospital",
    "wof:placetype":"venue"
},
  "geometry": {"coordinates":[-80.26660200000001,25.8606],"type":"Point"}
}