{
  "type": "Feature",
  "properties": {
    "iso:country":"US",
    "sg:address":"2738 Gall Blvd",
    "sg:city":"Zephyrhills",
    "sg:classifiers":[
        {
            "category":"Recreation",
            "type":"Entertainment"
        }
    ],
    "sg:phone":"+1 813 783 2827",
    "sg:postcode":"33540",
    "sg:province":"FL",
    "sg:tags":[
        "carnival"
    ],
    "wof:name":"Zephyrhills Festival & Auction",
    "wof:placetype":"venue"
},
  "geometry": {"coordinates":[-82.211725,28.17219],"type":"Point"}
}