{
  "type": "Feature",
  "properties": {
    "iso:country":"US",
    "sg:address":"1153 Co Rd 466",
    "sg:city":"Oxford",
    "sg:classifiers":[
        {
            "category":"Building & Trades",
            "subcategory":"Construction",
            "type":"Services"
        }
    ],
    "sg:phone":"+1 352 330 0536",
    "sg:postcode":"34484",
    "sg:province":"FL",
    "sg:tags":[
        "contractor"
    ],
    "wof:name":"Chris Sharp Fence",
    "wof:placetype":"venue"
},
  "geometry": {"coordinates":[-82.077259,28.927268],"type":"Point"}
}