{
  "type": "Feature",
  "properties": {
    "addr:full":"9621 Sidney Hayes Rd Orlando FL 32824",
    "addr:housenumber":"9621",
    "addr:postcode":"32824",
    "addr:street":"Sidney Hayes Rd",
    "iso:country":"US",
    "sg:address":"9621 Sidney Hayes Rd",
    "sg:city":"Orlando",
    "sg:classifiers":[
        {
            "category":"Retail",
            "subcategory":"Repair Shop",
            "type":"Services"
        }
    ],
    "sg:phone":"+1 407 857 4171",
    "sg:postcode":"32824",
    "sg:province":"FL",
    "sg:tags":[
        "welding"
    ],
    "wof:name":"G & K Heavy Equipment Trans",
    "wof:placetype":"venue"
},
  "geometry": {"coordinates":[-81.375906,28.427118],"type":"Point"}
}