{
  "type": "Feature",
  "properties": {
    "iso:country":"US",
    "sg:address":"1719 Ave del Sol",
    "sg:city":"Boca Raton",
    "sg:classifiers":[
        {
            "category":"Professional",
            "subcategory":"Business Services",
            "type":"Services"
        }
    ],
    "sg:phone":"+1 561 391 7077",
    "sg:postcode":"33432",
    "sg:province":"FL",
    "sg:tags":[
        "interior",
        "consultant",
        "design",
        "decorator"
    ],
    "wof:name":"Integrative Designs",
    "wof:placetype":"venue"
},
  "geometry": {"coordinates":[-80.088781,26.36685],"type":"Point"}
}