{
  "type": "Feature",
  "properties": {
    "addr:full":"3450 Townsend Blvd Jacksonville FL 32277",
    "addr:housenumber":"3450",
    "addr:postcode":"32277",
    "addr:street":"Townsend Blvd",
    "iso:country":"US",
    "sg:address":"3450 Townsend Blvd",
    "sg:city":"Jacksonville",
    "sg:classifiers":[
        {
            "category":"Real Estate",
            "subcategory":"Real Estate Operator",
            "type":"Services"
        }
    ],
    "sg:phone":"+1 904 744 0122",
    "sg:postcode":"32277",
    "sg:province":"FL",
    "sg:tags":[
        "building",
        "apartment"
    ],
    "wof:name":"Abbington Square Apartments",
    "wof:placetype":"venue"
},
  "geometry": {"coordinates":[-81.57726700000001,30.36187],"type":"Point"}
}