{
  "type": "Feature",
  "properties": {
    "iso:country":"US",
    "sg:address":"10385 Royal Palm Blvd",
    "sg:city":"Coral Springs",
    "sg:classifiers":[
        {
            "category":"Banks & Credit Unions",
            "subcategory":"Bank",
            "type":"Services"
        }
    ],
    "sg:phone":"+1 954 227 4229",
    "sg:postcode":"33065",
    "sg:province":"FL",
    "sg:tags":[
        "state"
    ],
    "wof:name":"South Trust Bank",
    "wof:placetype":"venue"
},
  "geometry": {"coordinates":[-80.265147,26.259162],"type":"Point"}
}