{
  "type": "Feature",
  "properties": {
    "addr:full":"6992 NW 29th Ter Fort Lauderdale FL 33309",
    "addr:housenumber":"6992",
    "addr:postcode":"33309",
    "addr:street":"Nw 29Th Ter",
    "iso:country":"US",
    "sg:address":"6992 NW 29th Ter",
    "sg:city":"Fort Lauderdale",
    "sg:classifiers":[
        {
            "category":"Building & Trades",
            "subcategory":"Construction",
            "type":"Services"
        }
    ],
    "sg:phone":"+1 954 975 7285",
    "sg:postcode":"33309",
    "sg:province":"FL",
    "sg:tags":[
        "floor",
        "laying",
        "contractor"
    ],
    "wof:name":"Seni Carpet Installation Corp",
    "wof:placetype":"venue"
},
  "geometry": {"coordinates":[-80.184573,26.208629],"type":"Point"}
}