{
  "type": "Feature",
  "properties": {
    "iso:country":"US",
    "sg:address":"1475 E Airport Blvd",
    "sg:city":"Sanford",
    "sg:classifiers":[
        {
            "category":"Government",
            "subcategory":"Post Office",
            "type":"Public Place"
        }
    ],
    "sg:phone":"+1 407 324 9559",
    "sg:postcode":"32773",
    "sg:province":"FL",
    "sg:tags":[
        "postal",
        "us"
    ],
    "wof:name":"US Post Office",
    "wof:placetype":"venue"
},
  "geometry": {"coordinates":[-81.256175,28.771174],"type":"Point"}
}