{
  "type": "Feature",
  "properties": {
    "addr:full":"1859 Constitution Dr Gulf Breeze FL 32566",
    "addr:housenumber":"1859",
    "addr:postcode":"32566",
    "addr:street":"Constitution Dr",
    "iso:country":"US",
    "sg:address":"1859 Constitution Dr",
    "sg:city":"Gulf Breeze",
    "sg:classifiers":[
        {
            "category":"Professional",
            "subcategory":"Computer Services",
            "type":"Services"
        }
    ],
    "sg:phone":"+1 850 936 0008",
    "sg:postcode":"32566",
    "sg:province":"FL",
    "sg:tags":[
        "related"
    ],
    "wof:name":"After Hours Computing",
    "wof:placetype":"venue"
},
  "geometry": {"coordinates":[-86.934382,30.402432],"type":"Point"}
}