{
  "type": "Feature",
  "properties": {
    "iso:country":"US",
    "sg:address":"1098 NW Fork Rd",
    "sg:city":"Stuart",
    "sg:classifiers":[
        {
            "category":"Shopping",
            "subcategory":"Clothing, Apparel, & Fashions",
            "type":"Retail Goods"
        }
    ],
    "sg:phone":"+1 772 692 7434",
    "sg:postcode":"34994",
    "sg:province":"FL",
    "wof:name":"Pier 61",
    "wof:placetype":"venue"
},
  "geometry": {"coordinates":[-80.267341,27.215376],"type":"Point"}
}