{
  "type": "Feature",
  "properties": {
    "iso:country":"US",
    "sg:address":"1070 NE 48th Ct",
    "sg:city":"Fort Lauderdale",
    "sg:classifiers":[
        {
            "category":"Retail",
            "subcategory":"Repair Shop",
            "type":"Services"
        }
    ],
    "sg:phone":"+1 954 491 6852",
    "sg:postcode":"33334",
    "sg:province":"FL",
    "wof:name":"Guzowski & Steppe Organ Bldrs",
    "wof:placetype":"venue"
},
  "geometry": {"coordinates":[-80.132904,26.186991],"type":"Point"}
}