{
  "type": "Feature",
  "properties": {
    "iso:country":"US",
    "sg:address":"15 Fir Dr",
    "sg:city":"Ocala",
    "sg:classifiers":[
        {
            "category":"Professional",
            "type":"Services"
        }
    ],
    "sg:phone":"+1 352 687 2130",
    "sg:postcode":"34472",
    "sg:province":"FL",
    "wof:name":"Perfect Air Systems",
    "wof:placetype":"venue"
},
  "geometry": {"coordinates":[-82.025294,29.146622],"type":"Point"}
}