{
  "type": "Feature",
  "properties": {
    "addr:full":"1102 W Flagler St Miami FL 33130",
    "addr:housenumber":"1102",
    "addr:postcode":"33130",
    "addr:street":"W Flagler St",
    "iso:country":"US",
    "sg:address":"1102 W Flagler St",
    "sg:city":"Miami",
    "sg:classifiers":[
        {
            "category":"Home & Garden",
            "subcategory":"Furniture",
            "type":"Retail Goods"
        }
    ],
    "sg:phone":"+1 305 960 7058",
    "sg:postcode":"33130",
    "sg:province":"FL",
    "sg:tags":[
        "store"
    ],
    "wof:name":"Coral Designs Furniture",
    "wof:placetype":"venue"
},
  "geometry": {"coordinates":[-80.213002,25.773568],"type":"Point"}
}