{
  "type": "Feature",
  "properties": {
    "iso:country":"US",
    "sg:address":"1930 Harrison St Suite 209",
    "sg:city":"Hollywood",
    "sg:classifiers":[
        {
            "category":"Professional",
            "subcategory":"Lawyer & Legal Services",
            "type":"Services"
        }
    ],
    "sg:phone":"+1 954 404 6648",
    "sg:postcode":"33020",
    "sg:province":"FL",
    "sg:tags":[
        "attorney",
        "right",
        "family",
        "estate",
        "civil",
        "divorce",
        "labor",
        "personal",
        "planning",
        "plan",
        "discrimination",
        "injury",
        "criminal",
        "employment",
        "law"
    ],
    "wof:name":"Fischer & Feldman PA",
    "wof:placetype":"venue"
},
  "geometry": {"coordinates":[-80.14559199999999,26.010502],"type":"Point"}
}