{
  "type": "Feature",
  "properties": {
    "addr:full":"2915 Estero Blvd Fort Myers Beach FL 33931",
    "addr:housenumber":"2915",
    "addr:postcode":"33931",
    "addr:street":"Estero Blvd",
    "iso:country":"US",
    "sg:address":"2915 Estero Blvd",
    "sg:city":"Fort Myers Beach",
    "sg:classifiers":[
        {
            "category":"Personal",
            "subcategory":"Beauty Salon",
            "type":"Services"
        }
    ],
    "sg:phone":"+1 239 463 3773",
    "sg:postcode":"33931",
    "sg:province":"FL",
    "sg:tags":[
        "manicuring"
    ],
    "wof:name":"Mystique's Nail Boutique",
    "wof:placetype":"venue"
},
  "geometry": {"coordinates":[-81.93898299999999,26.447404],"type":"Point"}
}