{
  "type": "Feature",
  "properties": {
    "addr:full":"8841 Atlantic Blvd Jacksonville FL 32211",
    "addr:housenumber":"8841",
    "addr:postcode":"32211",
    "addr:street":"Atlantic Blvd",
    "iso:country":"US",
    "sg:address":"8841 Atlantic Blvd",
    "sg:city":"Jacksonville",
    "sg:classifiers":[
        {
            "category":"Building & Trades",
            "subcategory":"Construction",
            "type":"Services"
        }
    ],
    "sg:phone":"+1 904 721 2227",
    "sg:postcode":"32211",
    "sg:province":"FL",
    "sg:tags":[
        "house",
        "construct",
        "contractor"
    ],
    "wof:name":"Permalar Industries Of Florida",
    "wof:placetype":"venue"
},
  "geometry": {"coordinates":[-81.56352699999999,30.314399],"type":"Point"}
}