{
  "type": "Feature",
  "properties": {
    "addr:full":"12771 SW 267th St Homestead FL 33032",
    "addr:housenumber":"12771",
    "addr:postcode":"33032",
    "addr:street":"Sw 267Th St",
    "iso:country":"US",
    "sg:address":"12771 SW 267th St",
    "sg:city":"Homestead",
    "sg:classifiers":[
        {
            "category":"Social Services",
            "subcategory":"Child Care",
            "type":"Services"
        }
    ],
    "sg:phone":"+1 305 258 0050",
    "sg:postcode":"33032",
    "sg:province":"FL",
    "sg:tags":[
        "day"
    ],
    "wof:name":"Happy Face Homes Corp",
    "wof:placetype":"venue"
},
  "geometry": {"coordinates":[-80.398832,25.519211],"type":"Point"}
}