{
  "type": "Feature",
  "properties": {
    "iso:country":"US",
    "sg:address":"11240 SW 95th St",
    "sg:city":"Miami",
    "sg:classifiers":[
        {
            "category":"Arts & Performance",
            "subcategory":"Theater",
            "type":"Entertainment"
        }
    ],
    "sg:phone":"+1 305 595 8123",
    "sg:postcode":"33176",
    "sg:province":"FL",
    "sg:tags":[
        "theatrical",
        "manager",
        "producer"
    ],
    "wof:name":"Miami Repertory Theater",
    "wof:placetype":"venue"
},
  "geometry": {"coordinates":[-80.38044499999999,25.680169],"type":"Point"}
}