{
  "type": "Feature",
  "properties": {
    "iso:country":"US",
    "sg:address":"336 Wilshire Blvd",
    "sg:city":"Casselberry",
    "sg:classifiers":[
        {
            "category":"Real Estate",
            "subcategory":"Real Estate Agent",
            "type":"Services"
        }
    ],
    "sg:phone":"+1 407 339 4090",
    "sg:postcode":"32707",
    "sg:province":"FL",
    "wof:name":"Crystal Bay Club LTD",
    "wof:placetype":"venue"
},
  "geometry": {"coordinates":[-81.328762,28.650931],"type":"Point"}
}