{
  "type": "Feature",
  "properties": {
    "addr:full":"1175 NE 125th St North Miami FL 33161",
    "addr:housenumber":"1175",
    "addr:postcode":"33161",
    "addr:street":"Ne 125Th St",
    "iso:country":"US",
    "sg:address":"1175 NE 125th St",
    "sg:city":"North Miami",
    "sg:classifiers":[
        {
            "category":"Manufacturing",
            "subcategory":"Tools & Machinery",
            "type":"Manufacturing & Wholesale Goods"
        }
    ],
    "sg:phone":"+1 305 895 4376",
    "sg:postcode":"33161",
    "sg:province":"FL",
    "sg:tags":[
        "control"
    ],
    "wof:name":"Engineered Controls",
    "wof:placetype":"venue"
},
  "geometry": {"coordinates":[-80.174696,25.890824],"type":"Point"}
}