{
  "type": "Feature",
  "properties": {
    "iso:country":"US",
    "sg:address":"1901 NW 62nd St",
    "sg:city":"Fort Lauderdale",
    "sg:classifiers":[
        {
            "category":"Professional",
            "subcategory":"Computer Services",
            "type":"Services"
        }
    ],
    "sg:phone":"+1 954 491 1414",
    "sg:postcode":"33309",
    "sg:province":"FL",
    "sg:tags":[
        "related"
    ],
    "wof:name":"Deak Group",
    "wof:placetype":"venue"
},
  "geometry": {"coordinates":[-80.16472,26.203103],"type":"Point"}
}