{
  "type": "Feature",
  "properties": {
    "iso:country":"US",
    "sg:address":"1018 Pennsylvania Ave NE",
    "sg:city":"Palm Bay",
    "sg:classifiers":[
        {
            "category":"Organizations",
            "subcategory":"Religious Organization",
            "type":"Services"
        }
    ],
    "sg:phone":"+1 321 729 0000",
    "sg:postcode":"32907",
    "sg:province":"FL",
    "wof:name":"Christian Life Family Church",
    "wof:placetype":"venue"
},
  "geometry": {"coordinates":[-80.652376,28.024927],"type":"Point"}
}