{
  "type": "Feature",
  "properties": {
    "addr:full":"200 W Forsyth St Jacksonville FL 32202",
    "addr:housenumber":"200",
    "addr:postcode":"32202",
    "addr:street":"W Forsyth St",
    "iso:country":"US",
    "sg:address":"200 W Forsyth St",
    "sg:city":"Jacksonville",
    "sg:classifiers":[
        {
            "category":"Professional",
            "subcategory":"Lawyer & Legal Services",
            "type":"Services"
        }
    ],
    "sg:phone":"+1 904 355 1155",
    "sg:postcode":"32202",
    "sg:province":"FL",
    "sg:tags":[
        "attorney",
        "trust",
        "corporation",
        "wills",
        "partnership",
        "planning",
        "real estate",
        "law"
    ],
    "wof:name":"Candeto, Michael A",
    "wof:placetype":"venue"
},
  "geometry": {"coordinates":[-81.660393,30.327591],"type":"Point"}
}