{
  "type": "Feature",
  "properties": {
    "iso:country":"US",
    "sg:address":"8952 Pensacola Blvd",
    "sg:city":"Pensacola",
    "sg:classifiers":[
        {
            "category":"Restaurant",
            "type":"Food & Drink"
        }
    ],
    "sg:phone":"+1 850 477 9191",
    "sg:postcode":"32534",
    "sg:province":"FL",
    "wof:name":"Uncle Jiang",
    "wof:placetype":"venue"
},
  "geometry": {"coordinates":[-87.274826,30.526961],"type":"Point"}
}