{
  "type": "Feature",
  "properties": {
    "addr:full":"101 N Monroe St Tallahassee FL 32301",
    "addr:housenumber":"101",
    "addr:postcode":"32301",
    "addr:street":"N Monroe St",
    "iso:country":"US",
    "sg:address":"101 N Monroe St",
    "sg:city":"Tallahassee",
    "sg:classifiers":[
        {
            "category":"Professional",
            "type":"Services"
        }
    ],
    "sg:phone":"+1 850 681 9111",
    "sg:postcode":"32301",
    "sg:province":"FL",
    "sg:tags":[
        "establishment"
    ],
    "wof:name":"Rubin Group",
    "wof:placetype":"venue"
},
  "geometry": {"coordinates":[-84.28067799999999,30.443592],"type":"Point"}
}