{
  "type": "Feature",
  "properties": {
    "iso:country":"US",
    "sg:address":"504 Via de Palmas",
    "sg:city":"Boca Raton",
    "sg:classifiers":[
        {
            "category":"Bars & Pubs",
            "type":"Food & Drink"
        }
    ],
    "sg:phone":"+1 561 361 8445",
    "sg:postcode":"33432",
    "sg:province":"FL",
    "wof:name":"Holloway's Pub",
    "wof:placetype":"venue"
},
  "geometry": {"coordinates":[-80.084909,26.346573],"type":"Point"}
}