{
  "type": "Feature",
  "properties": {
    "iso:country":"US",
    "sg:address":"8726 Old Co Rd 54",
    "sg:city":"New Port Richey",
    "sg:classifiers":[
        {
            "category":"Travel",
            "subcategory":"Travel Agent",
            "type":"Entertainment"
        }
    ],
    "sg:phone":"+1 727 376 8687",
    "sg:postcode":"34653",
    "sg:province":"FL",
    "sg:tags":[
        "agency",
        "bureau"
    ],
    "wof:name":"Seven Springs Travel",
    "wof:placetype":"venue"
},
  "geometry": {"coordinates":[-82.672371,28.216994],"type":"Point"}
}