{
  "type": "Feature",
  "properties": {
    "addr:full":"921 Nutmeg Ave Niceville FL 32578",
    "addr:housenumber":"921",
    "addr:postcode":"32578",
    "addr:street":"Nutmeg Ave",
    "iso:country":"US",
    "sg:address":"921 Nutmeg Ave",
    "sg:city":"Niceville",
    "sg:classifiers":[
        {
            "category":"Wholesale",
            "subcategory":"Computers",
            "type":"Manufacturing & Wholesale Goods"
        }
    ],
    "sg:phone":"+1 850 678 5778",
    "sg:postcode":"32578",
    "sg:province":"FL",
    "wof:name":"Gator Byte Computers",
    "wof:placetype":"venue"
},
  "geometry": {"coordinates":[-86.464046,30.500818],"type":"Point"}
}