{
  "type": "Feature",
  "properties": {
    "addr:full":"19368 Ocean Grande Ct Boca Raton FL 33498",
    "addr:housenumber":"19368",
    "addr:postcode":"33498",
    "addr:street":"Ocean Grande Ct",
    "iso:country":"US",
    "sg:address":"19368 Ocean Grande Ct",
    "sg:city":"Boca Raton",
    "sg:classifiers":[
        {
            "category":"Banks & Credit Unions",
            "subcategory":"Investment Brokerage",
            "type":"Services"
        }
    ],
    "sg:phone":"+1 561 488 2699",
    "sg:postcode":"33498",
    "sg:province":"FL",
    "sg:tags":[
        "newsletter",
        "stock"
    ],
    "wof:name":"Market Gems",
    "wof:placetype":"venue"
},
  "geometry": {"coordinates":[-80.21793099999999,26.385626],"type":"Point"}
}