{
  "type": "Feature",
  "properties": {
    "addr:full":"815 N Federal Hwy Fort Lauderdale FL 33304",
    "addr:housenumber":"815",
    "addr:postcode":"33304",
    "addr:street":"N Federal Hwy",
    "iso:country":"US",
    "sg:address":"815 N Federal Hwy",
    "sg:city":"Fort Lauderdale",
    "sg:classifiers":[
        {
            "category":"Restaurant",
            "type":"Food & Drink"
        }
    ],
    "sg:phone":"+1 954 454 5618",
    "sg:postcode":"33304",
    "sg:province":"FL",
    "sg:tags":[
        "eating"
    ],
    "wof:name":"Yum Brands Inc",
    "wof:placetype":"venue"
},
  "geometry": {"coordinates":[-80.137697,26.134791],"type":"Point"}
}