{
  "type": "Feature",
  "properties": {
    "addr:full":"760 Sextant Dr Sanibel FL 33957",
    "addr:housenumber":"760",
    "addr:postcode":"33957",
    "addr:street":"Sextant Dr",
    "iso:country":"US",
    "sg:address":"760 Sextant Dr",
    "sg:city":"Sanibel",
    "sg:classifiers":[
        {
            "category":"Local Transit",
            "type":"Transportation"
        }
    ],
    "sg:phone":"+1 239 472 5005",
    "sg:postcode":"33957",
    "sg:province":"FL",
    "sg:tags":[
        "bus",
        "line"
    ],
    "wof:name":"Northfield Lines Inc",
    "wof:placetype":"venue"
},
  "geometry": {"coordinates":[-82.035466,26.452035],"type":"Point"}
}