{
  "type": "Feature",
  "properties": {
    "addr:full":"3849 S Delard Way Homosassa FL 34448",
    "addr:housenumber":"3849",
    "addr:postcode":"34448",
    "addr:street":"S Delard Way",
    "iso:country":"US",
    "sg:address":"3849 S Delard Way",
    "sg:city":"Homosassa",
    "sg:classifiers":[
        {
            "category":"Building & Trades",
            "subcategory":"Construction",
            "type":"Services"
        }
    ],
    "sg:phone":"+1 352 628 9257",
    "sg:postcode":"34448",
    "sg:province":"FL",
    "sg:tags":[
        "wallcoverings-installation",
        "wallpaper",
        "painting",
        "contractor"
    ],
    "wof:name":"Norman Barfus Painting",
    "wof:placetype":"venue"
},
  "geometry": {"coordinates":[-82.532169,28.804737],"type":"Point"}
}