{
  "type": "Feature",
  "properties": {
    "iso:country":"US",
    "sg:address":"10234 NW 47th St",
    "sg:city":"Fort Lauderdale",
    "sg:classifiers":[
        {
            "category":"Wholesale",
            "subcategory":"Machinery & Supplies",
            "type":"Manufacturing & Wholesale Goods"
        },
        {
            "category":"Wholesale",
            "subcategory":"Electrical",
            "type":"Manufacturing & Wholesale Goods"
        }
    ],
    "sg:phone":"+1 954 746 6848",
    "sg:postcode":"33351",
    "sg:province":"FL",
    "sg:tags":[
        "equipment",
        "transportation",
        "electronic"
    ],
    "wof:name":"Electro Enterprises Inc",
    "wof:placetype":"venue"
},
  "geometry": {"coordinates":[-80.285619,26.183363],"type":"Point"}
}