{
  "type": "Feature",
  "properties": {
    "iso:country":"US",
    "sg:address":"141 NE 3rd Ave Ste 601",
    "sg:city":"Miami",
    "sg:classifiers":[
        {
            "category":"Professional",
            "subcategory":"Lawyer & Legal Services",
            "type":"Services"
        }
    ],
    "sg:phone":"+1 305 373 9737",
    "sg:postcode":"33132",
    "sg:province":"FL",
    "wof:name":"Schwartz Terrence S Atty",
    "wof:placetype":"venue"
},
  "geometry": {"coordinates":[-80.188599,25.7757],"type":"Point"}
}