{
  "type": "Feature",
  "properties": {
    "addr:full":"2618 Spruce Creek Blvd Daytona Beach FL 32128",
    "addr:housenumber":"2618",
    "addr:postcode":"32128",
    "addr:street":"Spruce Creek Blvd",
    "iso:country":"US",
    "sg:address":"2618 Spruce Creek Blvd",
    "sg:city":"Daytona Beach",
    "sg:classifiers":[
        {
            "category":"Professional",
            "type":"Services"
        }
    ],
    "sg:phone":"+1 386 767 9977",
    "sg:postcode":"32128",
    "sg:province":"FL",
    "wof:name":"Great Beginnings Learning Ctr",
    "wof:placetype":"venue"
},
  "geometry": {"coordinates":[-81.037403,29.084215],"type":"Point"}
}