{
  "type": "Feature",
  "properties": {
    "addr:full":"1615 N Woodland Blvd Deland FL 32720",
    "addr:housenumber":"1615",
    "addr:postcode":"32720",
    "addr:street":"N Woodland Blvd",
    "iso:country":"US",
    "sg:address":"1615 N Woodland Blvd",
    "sg:city":"Deland",
    "sg:classifiers":[
        {
            "category":"Autos & Motor Vehicles",
            "subcategory":"Auto Supplies",
            "type":"Retail Goods"
        },
        {
            "category":"Retail",
            "subcategory":"Auto Repair",
            "type":"Services"
        }
    ],
    "sg:phone":"+1 386 736 2123",
    "sg:postcode":"32720",
    "sg:province":"FL",
    "sg:tags":[
        "wheel",
        "tire",
        "retread",
        "balancing",
        "wheels-aligning",
        "recap",
        "brake"
    ],
    "sg:website":"http://www.tirekingdom.com",
    "wof:name":"Tire Kingdom",
    "wof:placetype":"venue"
},
  "geometry": {"coordinates":[-81.30432399999999,29.057854],"type":"Point"}
}