{
  "type": "Feature",
  "properties": {
    "addr:full":"642 W Broad St Groveland FL 34736",
    "addr:housenumber":"642",
    "addr:postcode":"34736",
    "addr:street":"W Broad St",
    "iso:country":"US",
    "sg:address":"642 W Broad St",
    "sg:city":"Groveland",
    "sg:classifiers":[
        {
            "category":"Retail",
            "subcategory":"Auto Repair",
            "type":"Services"
        }
    ],
    "sg:phone":"+1 352 429 0289",
    "sg:postcode":"34736",
    "sg:province":"FL",
    "sg:tags":[
        "glass",
        "replacement"
    ],
    "wof:name":"Guardian Auto Glass",
    "wof:placetype":"venue"
},
  "geometry": {"coordinates":[-81.863375,28.563363],"type":"Point"}
}