{
  "type": "Feature",
  "properties": {
    "addr:full":"250 S Lake Starr Blvd Lake Wales FL 33898",
    "addr:housenumber":"250",
    "addr:postcode":"33898",
    "addr:street":"S Lake Starr Blvd",
    "iso:country":"US",
    "sg:address":"250 S Lake Starr Blvd",
    "sg:city":"Lake Wales",
    "sg:classifiers":[
        {
            "category":"Building & Trades",
            "subcategory":"Construction",
            "type":"Services"
        }
    ],
    "sg:phone":"+1 863 676 2066",
    "sg:postcode":"33898",
    "sg:province":"FL",
    "sg:tags":[
        "hanging",
        "contractor"
    ],
    "wof:name":"A1 Painting",
    "wof:placetype":"venue"
},
  "geometry": {"coordinates":[-81.59132,27.950997],"type":"Point"}
}