{
  "type": "Feature",
  "properties": {
    "iso:country":"US",
    "sg:address":"11333 Silverwood Ct",
    "sg:city":"Spring Hill",
    "sg:classifiers":[
        {
            "category":"Building & Trades",
            "subcategory":"Landscaping Services",
            "type":"Services"
        }
    ],
    "sg:phone":"+1 352 686 9994",
    "sg:postcode":"34609",
    "sg:province":"FL",
    "wof:name":"G&J Lawn Service",
    "wof:placetype":"venue"
},
  "geometry": {"coordinates":[-82.534059,28.478129],"type":"Point"}
}