{
  "type": "Feature",
  "properties": {
    "iso:country":"US",
    "sg:address":"250 Fellsmere Rd",
    "sg:city":"Sebastian",
    "sg:classifiers":[
        {
            "category":"Shopping",
            "subcategory":"Hobbies, Toys, & Games",
            "type":"Retail Goods"
        }
    ],
    "sg:phone":"+1 772 581 4778",
    "sg:postcode":"32958",
    "sg:province":"FL",
    "wof:name":"Riverside Hobbies",
    "wof:placetype":"venue"
},
  "geometry": {"coordinates":[-80.47105999999999,27.80652],"type":"Point"}
}