{
  "type": "Feature",
  "properties": {
    "addr:full":"3839 W Kennedy Blvd Tampa FL 33609",
    "addr:housenumber":"3839",
    "addr:postcode":"33609",
    "addr:street":"W Kennedy Blvd",
    "iso:country":"US",
    "sg:address":"3839 W Kennedy Blvd",
    "sg:city":"Tampa",
    "sg:classifiers":[
        {
            "category":"Professional",
            "subcategory":"Lawyer & Legal Services",
            "type":"Services"
        }
    ],
    "sg:phone":"+1 813 870 3839",
    "sg:postcode":"33609",
    "sg:province":"FL",
    "sg:tags":[
        "attorney"
    ],
    "wof:name":"Joryn Jenkins",
    "wof:placetype":"venue"
},
  "geometry": {"coordinates":[-82.507104,27.944896],"type":"Point"}
}