{
  "type": "Feature",
  "properties": {
    "addr:full":"2694 Starwood Ct West Palm Beach FL 33406",
    "addr:housenumber":"2694",
    "addr:postcode":"33406",
    "addr:street":"Starwood Ct",
    "iso:country":"US",
    "sg:address":"2694 Starwood Ct",
    "sg:city":"West Palm Beach",
    "sg:classifiers":[
        {
            "category":"Professional",
            "subcategory":"Management & Consulting",
            "type":"Services"
        }
    ],
    "sg:phone":"+1 561 969 3838",
    "sg:postcode":"33406",
    "sg:province":"FL",
    "sg:tags":[
        "consultant",
        "hospital"
    ],
    "wof:name":"Avega Health Systems",
    "wof:placetype":"venue"
},
  "geometry": {"coordinates":[-80.08179,26.657559],"type":"Point"}
}