{
  "type": "Feature",
  "properties": {
    "iso:country":"US",
    "sg:address":"1490 W 49th St",
    "sg:city":"Hialeah",
    "sg:classifiers":[
        {
            "category":"Health Services",
            "subcategory":"Medical Lab",
            "type":"Services"
        },
        {
            "category":"Health Services",
            "subcategory":"Doctor",
            "type":"Services"
        }
    ],
    "sg:phone":"+1 305 827 2514",
    "sg:postcode":"33012",
    "sg:province":"FL",
    "sg:tags":[
        "laboratory",
        "dentist",
        "dental"
    ],
    "wof:name":"Prime Dental Studio Inc",
    "wof:placetype":"venue"
},
  "geometry": {"coordinates":[-80.314409,25.866515],"type":"Point"}
}