{
  "type": "Feature",
  "properties": {
    "addr:full":"1350 E Lake Rd N Tarpon Springs FL 34688",
    "addr:housenumber":"1350",
    "addr:postcode":"34688",
    "addr:street":"E Lake Rd N",
    "iso:country":"US",
    "sg:address":"1350 E Lake Rd N",
    "sg:city":"Tarpon Springs",
    "sg:classifiers":[
        {
            "category":"Organizations",
            "subcategory":"Religious Organization",
            "type":"Services"
        }
    ],
    "sg:phone":"+1 727 934 0058",
    "sg:postcode":"34688",
    "sg:province":"FL",
    "sg:tags":[
        "commercial",
        "legal"
    ],
    "sg:website":"www.highestpraisefamilychurch.org",
    "wof:name":"Highest Praise Family Church",
    "wof:placetype":"venue"
},
  "geometry": {"coordinates":[-82.69898999999999,28.170758],"type":"Point"}
}