{
  "type": "Feature",
  "properties": {
    "addr:full":"355 E Crisafulli Rd Merritt Island FL 32953",
    "addr:housenumber":"355",
    "addr:postcode":"32953",
    "addr:street":"E Crisafulli Rd",
    "iso:country":"US",
    "sg:address":"355 E Crisafulli Rd",
    "sg:city":"Merritt Island",
    "sg:classifiers":[
        {
            "category":"Building & Trades",
            "subcategory":"Construction",
            "type":"Services"
        }
    ],
    "sg:phone":"+1 321 455 6635",
    "sg:postcode":"32953",
    "sg:province":"FL",
    "sg:tags":[
        "contractor"
    ],
    "wof:name":"Wrp Renovations Inc",
    "wof:placetype":"venue"
},
  "geometry": {"coordinates":[-80.700658,28.464813],"type":"Point"}
}