{
  "type": "Feature",
  "properties": {
    "addr:full":"8092 Tiger Lily Dr Naples FL 34113",
    "addr:housenumber":"8092",
    "addr:postcode":"34113",
    "addr:street":"Tiger Lily Dr",
    "iso:country":"US",
    "sg:address":"8092 Tiger Lily Dr",
    "sg:city":"Naples",
    "sg:classifiers":[
        {
            "category":"Banks & Credit Unions",
            "subcategory":"Financial Services",
            "type":"Services"
        }
    ],
    "sg:phone":"+1 239 732 2067",
    "sg:postcode":"34113",
    "sg:province":"FL",
    "sg:tags":[
        "investor"
    ],
    "wof:name":"Lumar Investments LLC",
    "wof:placetype":"venue"
},
  "geometry": {"coordinates":[-81.694244,26.081059],"type":"Point"}
}