{
  "type": "Feature",
  "properties": {
    "iso:country":"US",
    "sg:address":"775 Conestee Dr",
    "sg:city":"West Melbourne",
    "sg:classifiers":[
        {
            "category":"Professional",
            "type":"Services"
        }
    ],
    "sg:phone":"+1 321 722 2077",
    "sg:postcode":"32904",
    "sg:province":"FL",
    "sg:tags":[
        "establishment"
    ],
    "wof:name":"Bantry Group",
    "wof:placetype":"venue"
},
  "geometry": {"coordinates":[-80.692939,28.095297],"type":"Point"}
}