{
  "type": "Feature",
  "properties": {
    "iso:country":"US",
    "sg:address":"970 N Cocoa Blvd Ste 4",
    "sg:city":"Cocoa",
    "sg:classifiers":[
        {
            "category":"Professional",
            "subcategory":"Lawyer & Legal Services",
            "type":"Services"
        }
    ],
    "sg:phone":"+1 321 633 7444",
    "sg:postcode":"32922",
    "sg:province":"FL",
    "sg:tags":[
        "attorney",
        "practice"
    ],
    "wof:name":"Musil Law P",
    "wof:placetype":"venue"
},
  "geometry": {"coordinates":[-80.73653400000001,28.373929],"type":"Point"}
}