{
  "type": "Feature",
  "properties": {
    "iso:country":"US",
    "sg:address":"274 Wilshire Blvd",
    "sg:city":"Casselberry",
    "sg:classifiers":[
        {
            "category":"Banks & Credit Unions",
            "subcategory":"Investment Brokerage",
            "type":"Services"
        }
    ],
    "sg:phone":"+1 407 478 3156",
    "sg:postcode":"32707",
    "sg:province":"FL",
    "sg:tags":[
        "trade",
        "barter",
        "exchange"
    ],
    "wof:name":"Barterfirst International",
    "wof:placetype":"venue"
},
  "geometry": {"coordinates":[-81.329339,28.65055],"type":"Point"}
}