{
  "type": "Feature",
  "properties": {
    "addr:full":"3807 N 12th Ave Pensacola FL 32503",
    "addr:housenumber":"3807",
    "addr:postcode":"32503",
    "addr:street":"N 12Th Ave",
    "iso:country":"US",
    "sg:address":"3807 N 12th Ave",
    "sg:city":"Pensacola",
    "sg:classifiers":[
        {
            "category":"Real Estate",
            "subcategory":"Real Estate Services",
            "type":"Services"
        },
        {
            "category":"Real Estate",
            "subcategory":"Surveying",
            "type":"Services"
        },
        {
            "category":"Professional",
            "subcategory":"Business Services",
            "type":"Services"
        }
    ],
    "sg:phone":"+1 850 470 0224",
    "sg:postcode":"32503",
    "sg:province":"FL",
    "sg:tags":[
        "auction",
        "industrial",
        "appraisers-commercial",
        "appraiser"
    ],
    "wof:name":"Michael C Thorsen",
    "wof:placetype":"venue"
},
  "geometry": {"coordinates":[-87.20966900000001,30.45467],"type":"Point"}
}