{
  "type": "Feature",
  "properties": {
    "addr:full":"889 S Lake Howard Dr Winter Haven FL 33880",
    "addr:housenumber":"889",
    "addr:postcode":"33880",
    "addr:street":"S Lake Howard Dr",
    "iso:country":"US",
    "sg:address":"889 S Lake Howard Dr",
    "sg:city":"Winter Haven",
    "sg:classifiers":[
        {
            "category":"Autos & Motor Vehicles",
            "subcategory":"Motorcycle Sales",
            "type":"Retail Goods"
        }
    ],
    "sg:phone":"+1 863 293 1279",
    "sg:postcode":"33880",
    "sg:province":"FL",
    "sg:tags":[
        "scooter"
    ],
    "wof:name":"Honda Of Winter Haven",
    "wof:placetype":"venue"
},
  "geometry": {"coordinates":[-81.737557,28.017432],"type":"Point"}
}