{
  "type": "Feature",
  "properties": {
    "iso:country":"US",
    "sg:address":"4970 SW 72nd Ave Ste 109",
    "sg:city":"Miami",
    "sg:classifiers":[
        {
            "category":"Retail",
            "subcategory":"Veterinary Services",
            "type":"Services"
        }
    ],
    "sg:phone":"+1 305 385 8000",
    "sg:postcode":"33155",
    "sg:province":"FL",
    "sg:tags":[
        "veterinarian"
    ],
    "wof:name":"Kendale Lakes Pet Health Care Center",
    "wof:placetype":"venue"
},
  "geometry": {"coordinates":[-80.310699,25.7237],"type":"Point"}
}