{
  "type": "Feature",
  "properties": {
    "addr:full":"316 Farmington Dr Fort Lauderdale FL 33317",
    "addr:housenumber":"316",
    "addr:postcode":"33317",
    "addr:street":"Farmington Dr",
    "iso:country":"US",
    "sg:address":"316 Farmington Dr",
    "sg:city":"Fort Lauderdale",
    "sg:classifiers":[
        {
            "category":"Wholesale",
            "subcategory":"Groceries",
            "type":"Manufacturing & Wholesale Goods"
        }
    ],
    "sg:phone":"+1 954 584 8632",
    "sg:postcode":"33317",
    "sg:province":"FL",
    "sg:tags":[
        "condiment"
    ],
    "wof:name":"Greek Island Spice Inc",
    "wof:placetype":"venue"
},
  "geometry": {"coordinates":[-80.225065,26.126327],"type":"Point"}
}