{
  "type": "Feature",
  "properties": {
    "addr:full":"8918 Lantana Rd Lake Worth FL 33467",
    "addr:housenumber":"8918",
    "addr:postcode":"33467",
    "addr:street":"Lantana Rd",
    "iso:country":"US",
    "sg:address":"8918 Lantana Rd",
    "sg:city":"Lake Worth",
    "sg:classifiers":[
        {
            "category":"Restaurant",
            "type":"Food & Drink"
        }
    ],
    "sg:phone":"+1 561 965 3424",
    "sg:postcode":"33467",
    "sg:province":"FL",
    "wof:name":"Nuccio's Pizza",
    "wof:placetype":"venue"
},
  "geometry": {"coordinates":[-80.18854899999999,26.590783],"type":"Point"}
}