{
  "type": "Feature",
  "properties": {
    "iso:country":"US",
    "sg:address":"43 SE 5th Ct",
    "sg:city":"Pompano Beach",
    "sg:classifiers":[
        {
            "category":"Shopping",
            "type":"Retail Goods"
        }
    ],
    "sg:phone":"+1 954 491 1367",
    "sg:postcode":"33060",
    "sg:province":"FL",
    "sg:tags":[
        "repair",
        "register",
        "cash"
    ],
    "wof:name":"Berts Cash Registers Inc",
    "wof:placetype":"venue"
},
  "geometry": {"coordinates":[-80.122592,26.223073],"type":"Point"}
}