{
  "type": "Feature",
  "properties": {
    "iso:country":"US",
    "sg:address":"6869 Valhalla Way",
    "sg:city":"Windermere",
    "sg:classifiers":[
        {
            "category":"Professional",
            "subcategory":"Business Services",
            "type":"Services"
        }
    ],
    "sg:phone":"+1 321 217 4130",
    "sg:postcode":"34786",
    "sg:province":"FL",
    "sg:tags":[
        "consultant",
        "coach"
    ],
    "wof:name":"Chorley Consulting",
    "wof:placetype":"venue"
},
  "geometry": {"coordinates":[-81.535237,28.463986],"type":"Point"}
}