{
  "type": "Feature",
  "properties": {
    "iso:country":"US",
    "sg:address":"1280 SW 1st St",
    "sg:city":"Miami",
    "sg:classifiers":[
        {
            "category":"Health Services",
            "subcategory":"Clinic",
            "type":"Services"
        },
        {
            "category":"Community Center",
            "type":"Public Place"
        }
    ],
    "sg:phone":"+1 305 631 7007",
    "sg:postcode":"33135",
    "sg:province":"FL",
    "sg:tags":[
        "medical"
    ],
    "wof:name":"Little Havana Medical Services",
    "wof:placetype":"venue"
},
  "geometry": {"coordinates":[-80.216027,25.772479],"type":"Point"}
}