{
  "type": "Feature",
  "properties": {
    "addr:full":"26314 Asuncion Dr Punta Gorda FL 33983",
    "addr:postcode":"26314;33983",
    "addr:street":"Asuncion Dr",
    "iso:country":"US",
    "sg:address":"26314 Asuncion Dr",
    "sg:city":"Punta Gorda",
    "sg:classifiers":[
        {
            "category":"Freight",
            "type":"Transportation"
        }
    ],
    "sg:phone":"+1 941 235 3144",
    "sg:postcode":"33983",
    "sg:province":"FL",
    "sg:tags":[
        "operator",
        "local",
        "trucking"
    ],
    "wof:name":"Steven Marotta Trucking",
    "wof:placetype":"venue"
},
  "geometry": {"coordinates":[-82.01407399999999,27.028602],"type":"Point"}
}