{
  "type": "Feature",
  "properties": {
    "iso:country":"US",
    "sg:address":"2851 NE 183rd St",
    "sg:city":"Miami",
    "sg:classifiers":[
        {
            "category":"Banks & Credit Unions",
            "subcategory":"Financial Services",
            "type":"Services"
        }
    ],
    "sg:phone":"+1 305 931 3699",
    "sg:postcode":"33160",
    "sg:province":"FL",
    "sg:tags":[
        "trust",
        "management"
    ],
    "wof:name":"Gerald Reizes Trust",
    "wof:placetype":"venue"
},
  "geometry": {"coordinates":[-80.140721,25.944883],"type":"Point"}
}