{
  "type": "Feature",
  "properties": {
    "addr:full":"330 NE 2nd Ave Delray Beach FL 33444",
    "addr:housenumber":"330",
    "addr:postcode":"33444",
    "addr:street":"Ne 2Nd Ave",
    "iso:country":"US",
    "sg:address":"330 NE 2nd Ave",
    "sg:city":"Delray Beach",
    "sg:classifiers":[
        {
            "category":"Social Services",
            "type":"Services"
        }
    ],
    "sg:phone":"+1 561 276 5579",
    "sg:postcode":"33444",
    "sg:province":"FL",
    "wof:name":"Women In Visual Arts Inc",
    "wof:placetype":"venue"
},
  "geometry": {"coordinates":[-80.07131,26.46856],"type":"Point"}
}