{
  "type": "Feature",
  "properties": {
    "iso:country":"US",
    "sg:address":"1038 SW 66th Ave",
    "sg:city":"Miami",
    "sg:classifiers":[
        {
            "category":"Shopping",
            "type":"Retail Goods"
        }
    ],
    "sg:phone":"+1 305 261 9159",
    "sg:postcode":"33144",
    "sg:province":"FL",
    "sg:tags":[
        "merchandise"
    ],
    "wof:name":"Eugart Company Inc",
    "wof:placetype":"venue"
},
  "geometry": {"coordinates":[-80.30278300000001,25.759855],"type":"Point"}
}