{
  "type": "Feature",
  "properties": {
    "iso:country":"US",
    "sg:address":"2104 W 68th St",
    "sg:city":"Hialeah",
    "sg:classifiers":[
        {
            "category":"Health Services",
            "subcategory":"Doctor",
            "type":"Services"
        }
    ],
    "sg:phone":"+1 305 823 8722",
    "sg:postcode":"33016",
    "sg:province":"FL",
    "sg:tags":[
        "clinic",
        "therapy",
        "physical"
    ],
    "wof:name":"Palmetto Physical Therapy",
    "wof:placetype":"venue"
},
  "geometry": {"coordinates":[-80.326441,25.883662],"type":"Point"}
}