{
  "type": "Feature",
  "properties": {
    "addr:full":"3101 Pioneer Ct Kissimmee FL 34744",
    "addr:housenumber":"3101",
    "addr:postcode":"34744",
    "addr:street":"Pioneer Ct",
    "iso:country":"US",
    "sg:address":"3101 Pioneer Ct",
    "sg:city":"Kissimmee",
    "sg:classifiers":[
        {
            "category":"Restaurant",
            "type":"Food & Drink"
        }
    ],
    "sg:phone":"+1 407 344 8990",
    "sg:postcode":"34744",
    "sg:province":"FL",
    "sg:tags":[
        "eating"
    ],
    "wof:name":"Showtime Catering",
    "wof:placetype":"venue"
},
  "geometry": {"coordinates":[-81.316008,28.342097],"type":"Point"}
}