{
  "type": "Feature",
  "properties": {
    "addr:full":"18973 SE 106th St Ocklawaha FL 32179",
    "addr:housenumber":"18973",
    "addr:postcode":"32179",
    "addr:street":"Se 106Th St",
    "iso:country":"US",
    "sg:address":"18973 SE 106th St",
    "sg:city":"Ocklawaha",
    "sg:classifiers":[
        {
            "category":"Organizations",
            "subcategory":"Labor Organization",
            "type":"Services"
        }
    ],
    "sg:phone":"+1 352 288 3176",
    "sg:postcode":"32179",
    "sg:province":"FL",
    "wof:name":"Communications Workers-America",
    "wof:placetype":"venue"
},
  "geometry": {"coordinates":[-81.84031899999999,29.068047],"type":"Point"}
}