{
  "type": "Feature",
  "properties": {
    "addr:full":"169 E Flagler St Miami FL 33131",
    "addr:housenumber":"169",
    "addr:postcode":"33131",
    "addr:street":"E Flagler St",
    "iso:country":"US",
    "sg:address":"169 E Flagler St",
    "sg:city":"Miami",
    "sg:classifiers":[
        {
            "category":"Manufacturing",
            "subcategory":"Metals",
            "type":"Manufacturing & Wholesale Goods"
        }
    ],
    "sg:phone":"+1 305 577 0284",
    "sg:postcode":"33131",
    "sg:province":"FL",
    "sg:tags":[
        "diamond",
        "setter"
    ],
    "wof:name":"Urrego, German",
    "wof:placetype":"venue"
},
  "geometry": {"coordinates":[-80.190663,25.774207],"type":"Point"}
}