{
  "type": "Feature",
  "properties": {
    "iso:country":"US",
    "sg:address":"782 E 57th St",
    "sg:city":"Hialeah",
    "sg:classifiers":[
        {
            "category":"Restaurant",
            "type":"Food & Drink"
        }
    ],
    "sg:phone":"+1 305 687 2897",
    "sg:postcode":"33013",
    "sg:province":"FL",
    "wof:name":"Mercy's Cafe Corp",
    "wof:placetype":"venue"
},
  "geometry": {"coordinates":[-80.268452,25.874456],"type":"Point"}
}