{
  "type": "Feature",
  "properties": {
    "addr:full":"1304 Ocoee Apopka Rd Ocoee FL 34761",
    "addr:housenumber":"1304",
    "addr:postcode":"34761",
    "addr:street":"Ocoee Apopka Rd",
    "iso:country":"US",
    "sg:address":"1304 Ocoee Apopka Rd",
    "sg:city":"Ocoee",
    "sg:classifiers":[
        {
            "category":"Building & Trades",
            "subcategory":"Construction",
            "type":"Services"
        }
    ],
    "sg:phone":"+1 407 877 6420",
    "sg:postcode":"34761",
    "sg:province":"FL",
    "sg:tags":[
        "painter"
    ],
    "wof:name":"Israel Gonzalez Painting",
    "wof:placetype":"venue"
},
  "geometry": {"coordinates":[-81.551129,28.588613],"type":"Point"}
}