{
  "type": "Feature",
  "properties": {
    "addr:full":"1147 Agate Ave Spring Hill FL 34609",
    "addr:housenumber":"1147",
    "addr:postcode":"34609",
    "addr:street":"Agate Ave",
    "iso:country":"US",
    "sg:address":"1147 Agate Ave",
    "sg:city":"Spring Hill",
    "sg:classifiers":[
        {
            "category":"Building & Trades",
            "subcategory":"Construction",
            "type":"Services"
        }
    ],
    "sg:phone":"+1 352 686 5575",
    "sg:postcode":"34609",
    "sg:province":"FL",
    "sg:tags":[
        "residential"
    ],
    "wof:name":"Anderson Contracting",
    "wof:placetype":"venue"
},
  "geometry": {"coordinates":[-82.507728,28.450482],"type":"Point"}
}