{
  "type": "Feature",
  "properties": {
    "addr:full":"956 SW 12th Ave Pompano Beach FL 33069",
    "addr:housenumber":"956",
    "addr:postcode":"33069",
    "addr:street":"Sw 12Th Ave",
    "iso:country":"US",
    "sg:address":"956 SW 12th Ave",
    "sg:city":"Pompano Beach",
    "sg:classifiers":[
        {
            "category":"Manufacturing",
            "subcategory":"Rubber & Plastics",
            "type":"Manufacturing & Wholesale Goods"
        }
    ],
    "sg:phone":"+1 954 943 8421",
    "sg:postcode":"33069",
    "sg:province":"FL",
    "sg:tags":[
        "product",
        "mechanical",
        "mfg"
    ],
    "sg:website":"www.pompadourproducts.com",
    "wof:name":"Pompadour Products Inc",
    "wof:placetype":"venue"
},
  "geometry": {"coordinates":[-80.138543,26.21814],"type":"Point"}
}