{
  "type": "Feature",
  "properties": {
    "iso:country":"US",
    "sg:address":"4370 S Tamiami Trl",
    "sg:city":"Sarasota",
    "sg:classifiers":[
        {
            "category":"Travel",
            "subcategory":"Travel Agent",
            "type":"Entertainment"
        }
    ],
    "sg:phone":"+1 941 927 9484",
    "sg:postcode":"34231",
    "sg:province":"FL",
    "sg:tags":[
        "agency"
    ],
    "wof:name":"Cruise One",
    "wof:placetype":"venue"
},
  "geometry": {"coordinates":[-82.530737,27.290618],"type":"Point"}
}