{
  "type": "Feature",
  "properties": {
    "iso:country":"US",
    "sg:address":"1105 6th Ave S",
    "sg:city":"Lake Worth",
    "sg:classifiers":[
        {
            "category":"Building & Trades",
            "subcategory":"Construction",
            "type":"Services"
        }
    ],
    "sg:phone":"+1 561 582 4106",
    "sg:postcode":"33460",
    "sg:province":"FL",
    "sg:tags":[
        "roofing",
        "contractor"
    ],
    "wof:name":"Michael Brodbeck Roof Svc",
    "wof:placetype":"venue"
},
  "geometry": {"coordinates":[-80.060541,26.608559],"type":"Point"}
}