{
  "type": "Feature",
  "properties": {
    "iso:country":"US",
    "sg:address":"4100 Lake Underhill Rd",
    "sg:city":"Orlando",
    "sg:classifiers":[
        {
            "category":"Professional",
            "subcategory":"Computer Services",
            "type":"Services"
        }
    ],
    "sg:phone":"+1 407 898 4455",
    "sg:postcode":"32803",
    "sg:province":"FL",
    "sg:tags":[
        "design",
        "system"
    ],
    "wof:name":"Revolution Design Inc",
    "wof:placetype":"venue"
},
  "geometry": {"coordinates":[-81.333939,28.536141],"type":"Point"}
}