{
  "type": "Feature",
  "properties": {
    "addr:full":"4253 Bay Beach Ln Fort Myers Beach FL 33931",
    "addr:housenumber":"4253",
    "addr:postcode":"33931",
    "addr:street":"Bay Beach Ln",
    "iso:country":"US",
    "sg:address":"4253 Bay Beach Ln",
    "sg:city":"Fort Myers Beach",
    "sg:classifiers":[
        {
            "category":"Wholesale",
            "subcategory":"Non-durable Goods",
            "type":"Manufacturing & Wholesale Goods"
        }
    ],
    "sg:phone":"+1 239 765 1841",
    "sg:postcode":"33931",
    "sg:province":"FL",
    "wof:name":"L K Sales",
    "wof:placetype":"venue"
},
  "geometry": {"coordinates":[-81.893486,26.411711],"type":"Point"}
}