{
  "type": "Feature",
  "properties": {
    "addr:full":"3015 Hartley Rd Jacksonville FL 32257",
    "addr:housenumber":"3015",
    "addr:postcode":"32257",
    "addr:street":"Hartley Rd",
    "iso:country":"US",
    "sg:address":"3015 Hartley Rd",
    "sg:city":"Jacksonville",
    "sg:phone":"+1 904 268 8879",
    "sg:postcode":"32257",
    "sg:province":"FL",
    "sg:tags":[
        "plastic",
        "equipment",
        "good",
        "supply"
    ],
    "wof:name":"Cambro Manufacturing Company",
    "wof:placetype":"venue"
},
  "geometry": {"coordinates":[-81.630937,30.185364],"type":"Point"}
}