{
  "type": "Feature",
  "properties": {
    "addr:full":"3080 Vineland Rd Kissimmee FL 34746",
    "addr:housenumber":"3080",
    "addr:postcode":"34746",
    "addr:street":"Vineland Rd",
    "iso:country":"US",
    "sg:address":"3080 Vineland Rd",
    "sg:city":"Kissimmee",
    "sg:classifiers":[
        {
            "category":"Building & Trades",
            "subcategory":"Construction",
            "type":"Services"
        }
    ],
    "sg:phone":"+1 407 396 1210",
    "sg:postcode":"34746",
    "sg:province":"FL",
    "sg:tags":[
        "home",
        "builder"
    ],
    "wof:name":"Beazer Homes",
    "wof:placetype":"venue"
},
  "geometry": {"coordinates":[-81.480846,28.338667],"type":"Point"}
}