{
  "type": "Feature",
  "properties": {
    "iso:country":"US",
    "sg:address":"3063 Enterprise Rd",
    "sg:city":"Debary",
    "sg:classifiers":[
        {
            "category":"Home & Garden",
            "subcategory":"Garden Supply",
            "type":"Retail Goods"
        },
        {
            "category":"Building & Trades",
            "subcategory":"Equipment Rental",
            "type":"Services"
        }
    ],
    "sg:phone":"+1 386 668 7368",
    "sg:postcode":"32713",
    "sg:province":"FL",
    "sg:tags":[
        "lawn",
        "contractors'",
        "leasing",
        "mower"
    ],
    "sg:website":"http://www.volusiarental.com",
    "wof:name":"Volusia Rental & Equipment",
    "wof:placetype":"venue"
},
  "geometry": {"coordinates":[-81.280598,28.889438],"type":"Point"}
}