{
  "type": "Feature",
  "properties": {
    "iso:country":"US",
    "sg:address":"4575 US Hwy 1",
    "sg:city":"Vero Beach",
    "sg:classifiers":[
        {
            "category":"Wholesale",
            "subcategory":"Auto Parts",
            "type":"Manufacturing & Wholesale Goods"
        }
    ],
    "sg:phone":"+1 772 770 9949",
    "sg:postcode":"32967",
    "sg:province":"FL",
    "sg:tags":[
        "shaft",
        "drive"
    ],
    "wof:name":"Vero Beach Powertrain",
    "wof:placetype":"venue"
},
  "geometry": {"coordinates":[-80.408063,27.676695],"type":"Point"}
}