{
  "type": "Feature",
  "properties": {
    "iso:country":"US",
    "sg:address":"300 Cherry St",
    "sg:city":"Melbourne",
    "sg:classifiers":[
        {
            "category":"Organizations",
            "subcategory":"Religious Organization",
            "type":"Services"
        }
    ],
    "sg:phone":"+1 321 727 1701",
    "sg:postcode":"32901",
    "sg:province":"FL",
    "sg:tags":[
        "church"
    ],
    "wof:name":"Church At Melbourne",
    "wof:placetype":"venue"
},
  "geometry": {"coordinates":[-80.61610400000001,28.099897],"type":"Point"}
}