{
  "type": "Feature",
  "properties": {
    "addr:full":"12971 SW 112th St Miami FL 33186",
    "addr:housenumber":"12971",
    "addr:postcode":"33186",
    "addr:street":"Sw 112Th St",
    "iso:country":"US",
    "sg:address":"12971 SW 112th St",
    "sg:city":"Miami",
    "sg:classifiers":[
        {
            "category":"Personal",
            "subcategory":"Beauty Salon",
            "type":"Services"
        }
    ],
    "sg:phone":"+1 305 385 2069",
    "sg:postcode":"33186",
    "sg:province":"FL",
    "wof:name":"Iris Hair Design",
    "wof:placetype":"venue"
},
  "geometry": {"coordinates":[-80.40625300000001,25.663294],"type":"Point"}
}