{
  "type": "Feature",
  "properties": {
    "iso:country":"US",
    "sg:address":"95 Doubloon Dr",
    "sg:city":"Placida",
    "sg:classifiers":[
        {
            "category":"Wholesale",
            "subcategory":"Groceries",
            "type":"Manufacturing & Wholesale Goods"
        }
    ],
    "sg:phone":"+1 941 698 0090",
    "sg:postcode":"33946",
    "sg:province":"FL",
    "wof:name":"Pokorny",
    "wof:placetype":"venue"
},
  "geometry": {"coordinates":[-82.29506499999999,26.853981],"type":"Point"}
}