{
  "type": "Feature",
  "properties": {
    "iso:country":"US",
    "sg:address":"3004 Folsom Rd",
    "sg:city":"Mims",
    "sg:classifiers":[
        {
            "category":"Building & Trades",
            "subcategory":"Construction",
            "type":"Services"
        }
    ],
    "sg:phone":"+1 321 269 6061",
    "sg:postcode":"32754",
    "sg:province":"FL",
    "sg:tags":[
        "painting",
        "contractor"
    ],
    "wof:name":"Shawn L Rice & Wayne Brady",
    "wof:placetype":"venue"
},
  "geometry": {"coordinates":[-80.855656,28.679158],"type":"Point"}
}