{
  "type": "Feature",
  "properties": {
    "iso:country":"US",
    "sg:address":"2408 SW 1st St",
    "sg:city":"Boynton Beach",
    "sg:classifiers":[
        {
            "category":"Professional",
            "type":"Services"
        }
    ],
    "sg:phone":"+1 561 732 1341",
    "sg:postcode":"33435",
    "sg:province":"FL",
    "wof:name":"Leanne J Whaley Inc",
    "wof:placetype":"venue"
},
  "geometry": {"coordinates":[-80.067638,26.506959],"type":"Point"}
}