{
  "type": "Feature",
  "properties": {
    "addr:full":"4450 Woodbine Rd Pace FL 32571",
    "addr:housenumber":"4450",
    "addr:postcode":"32571",
    "addr:street":"Woodbine Rd",
    "iso:country":"US",
    "sg:address":"4450 Woodbine Rd",
    "sg:city":"Pace",
    "sg:classifiers":[
        {
            "category":"Shopping",
            "subcategory":"Jewelry",
            "type":"Retail Goods"
        }
    ],
    "sg:phone":"+1 850 994 5515",
    "sg:postcode":"32571",
    "sg:province":"FL",
    "sg:tags":[
        "jeweler"
    ],
    "wof:name":"Gunner's Gulf Coast Jewelers",
    "wof:placetype":"venue"
},
  "geometry": {"coordinates":[-87.181741,30.623143],"type":"Point"}
}