{
  "type": "Feature",
  "properties": {
    "iso:country":"US",
    "sg:address":"416 SE Balboa Ave",
    "sg:city":"Stuart",
    "sg:classifiers":[
        {
            "category":"Professional",
            "type":"Services"
        }
    ],
    "sg:phone":"+1 772 463 5870",
    "sg:postcode":"34994",
    "sg:province":"FL",
    "sg:tags":[
        "establishment"
    ],
    "wof:name":"Outdoor Capital",
    "wof:placetype":"venue"
},
  "geometry": {"coordinates":[-80.24067100000001,27.197347],"type":"Point"}
}