{
  "type": "Feature",
  "properties": {
    "iso:country":"US",
    "sg:address":"1173 North Ln",
    "sg:city":"Englewood",
    "sg:classifiers":[
        {
            "category":"Building & Trades",
            "subcategory":"Construction",
            "type":"Services"
        }
    ],
    "sg:phone":"+1 941 474 8247",
    "sg:postcode":"34224",
    "sg:province":"FL",
    "sg:tags":[
        "house"
    ],
    "wof:name":"Curry Fenwick Construction",
    "wof:placetype":"venue"
},
  "geometry": {"coordinates":[-82.32730599999999,26.939297],"type":"Point"}
}