{
  "type": "Feature",
  "properties": {
    "addr:full":"10801 International Dr Orlando FL 32821",
    "addr:housenumber":"10801",
    "addr:postcode":"32821",
    "addr:street":"International Dr",
    "iso:country":"US",
    "sg:address":"10801 International Dr",
    "sg:city":"Orlando",
    "sg:classifiers":[
        {
            "category":"Travel",
            "subcategory":"Hotels & Motels",
            "type":"Entertainment"
        }
    ],
    "sg:phone":"+1 407 354 1176",
    "sg:postcode":"32821",
    "sg:province":"FL",
    "sg:tags":[
        "lodging"
    ],
    "sg:website":"http://www.marriott.com",
    "wof:name":"Marriott",
    "wof:placetype":"venue"
},
  "geometry": {"coordinates":[-81.45616699999999,28.410797],"type":"Point"}
}