{
  "type": "Feature",
  "properties": {
    "iso:country":"US",
    "sg:address":"4131 Central Ave",
    "sg:city":"St Petersburg",
    "sg:classifiers":[
        {
            "category":"Health Services",
            "subcategory":"Doctor",
            "type":"Services"
        }
    ],
    "sg:phone":"+1 727 327 3300",
    "sg:postcode":"33713",
    "sg:province":"FL",
    "sg:tags":[
        "clinic"
    ],
    "wof:name":"All Women's Family Planning",
    "wof:placetype":"venue"
},
  "geometry": {"coordinates":[-82.689916,27.771019],"type":"Point"}
}