{
  "type": "Feature",
  "properties": {
    "addr:full":"961 Alabama Ave Fort Lauderdale FL 33312",
    "addr:housenumber":"961",
    "addr:postcode":"33312",
    "addr:street":"Alabama Ave",
    "iso:country":"US",
    "sg:address":"961 Alabama Ave",
    "sg:city":"Fort Lauderdale",
    "sg:classifiers":[
        {
            "category":"Professional",
            "type":"Services"
        }
    ],
    "sg:phone":"+1 954 797 0617",
    "sg:postcode":"33312",
    "sg:province":"FL",
    "wof:name":"Seek & Destroy Inc",
    "wof:placetype":"venue"
},
  "geometry": {"coordinates":[-80.19016499999999,26.108151],"type":"Point"}
}