{
  "type": "Feature",
  "properties": {
    "iso:country":"US",
    "sg:address":"6201 78th Ave",
    "sg:city":"Pinellas Park",
    "sg:classifiers":[
        {
            "category":"Retail",
            "subcategory":"Auto Repair",
            "type":"Services"
        }
    ],
    "sg:phone":"+1 727 541 7410",
    "sg:postcode":"33781",
    "sg:province":"FL",
    "sg:tags":[
        "repairing",
        "automobile"
    ],
    "wof:name":"Euro Car Repair",
    "wof:placetype":"venue"
},
  "geometry": {"coordinates":[-82.720196,27.842809],"type":"Point"}
}