{
  "type": "Feature",
  "properties": {
    "addr:full":"4080 W New Haven Ave Melbourne FL 32904",
    "addr:housenumber":"4080",
    "addr:postcode":"32904",
    "addr:street":"W New Haven Ave",
    "iso:country":"US",
    "sg:address":"4080 W New Haven Ave",
    "sg:city":"Melbourne",
    "sg:classifiers":[
        {
            "category":"Communications",
            "type":"Services"
        },
        {
            "category":"Shopping",
            "subcategory":"Computers & Home Electronics",
            "type":"Retail Goods"
        }
    ],
    "sg:phone":"+1 321 951 0883",
    "sg:postcode":"32904",
    "sg:province":"FL",
    "sg:tags":[
        "sound",
        "television",
        "system",
        "equipment",
        "radio",
        "store"
    ],
    "wof:name":"Stereo Town, Inc.",
    "wof:placetype":"venue"
},
  "geometry": {"coordinates":[-80.692673,28.079],"type":"Point"}
}