{
  "type": "Feature",
  "properties": {
    "addr:full":"2018 Ranchland Dr Lakeland FL 33809",
    "addr:housenumber":"2018",
    "addr:postcode":"33809",
    "addr:street":"Ranchland Dr",
    "iso:country":"US",
    "sg:address":"2018 Ranchland Dr",
    "sg:city":"Lakeland",
    "sg:classifiers":[
        {
            "category":"Shopping",
            "subcategory":"Gifts & Souvenirs",
            "type":"Retail Goods"
        }
    ],
    "sg:phone":"+1 863 859 6433",
    "sg:postcode":"33809",
    "sg:province":"FL",
    "wof:name":"Robert Gaskins Gifts",
    "wof:placetype":"venue"
},
  "geometry": {"coordinates":[-81.984188,28.217355],"type":"Point"}
}