{
  "type": "Feature",
  "properties": {
    "iso:country":"US",
    "sg:address":"10870 Wiles Rd",
    "sg:city":"Coral Springs",
    "sg:classifiers":[
        {
            "category":"Retail",
            "subcategory":"Laundry & Dry Cleaning",
            "type":"Services"
        }
    ],
    "sg:phone":"+1 954 341 8890",
    "sg:postcode":"33076",
    "sg:province":"FL",
    "sg:tags":[
        "cleaners"
    ],
    "wof:name":"ANF Dry Cleaners",
    "wof:placetype":"venue"
},
  "geometry": {"coordinates":[-80.26749,26.287213],"type":"Point"}
}