{
  "type": "Feature",
  "properties": {
    "addr:full":"1400 Locust St NE Saint Petersburg FL 33704",
    "addr:housenumber":"1400",
    "addr:postcode":"33704",
    "addr:street":"Locust St Ne",
    "iso:country":"US",
    "sg:address":"1400 Locust St NE",
    "sg:city":"Saint Petersburg",
    "sg:classifiers":[
        {
            "category":"Building & Trades",
            "subcategory":"Construction",
            "type":"Services"
        }
    ],
    "sg:phone":"+1 727 741 0213",
    "sg:postcode":"33704",
    "sg:province":"FL",
    "sg:tags":[
        "carpentry",
        "contractor"
    ],
    "wof:name":"Fox Robertson",
    "wof:placetype":"venue"
},
  "geometry": {"coordinates":[-82.630269,27.786535],"type":"Point"}
}