{
  "type": "Feature",
  "properties": {
    "iso:country":"US",
    "sg:address":"818 N Main St",
    "sg:city":"Kissimmee",
    "sg:classifiers":[
        {
            "category":"Banks & Credit Unions",
            "subcategory":"Bank",
            "type":"Services"
        }
    ],
    "sg:phone":"+1 407 466 3280",
    "sg:postcode":"34744",
    "sg:province":"FL",
    "sg:tags":[
        "broker",
        "mortgage"
    ],
    "wof:name":"Capital Funding Corporation",
    "wof:placetype":"venue"
},
  "geometry": {"coordinates":[-81.40382,28.299668],"type":"Point"}
}