{
  "type": "Feature",
  "properties": {
    "iso:country":"US",
    "sg:address":"816 Broad St",
    "sg:city":"Jacksonville",
    "sg:classifiers":[
        {
            "category":"Banks & Credit Unions",
            "subcategory":"Bank",
            "type":"Services"
        }
    ],
    "sg:phone":"+1 904 359 0540",
    "sg:postcode":"32202",
    "sg:province":"FL",
    "sg:tags":[
        "mortgage",
        "loan",
        "broker",
        "real estate"
    ],
    "wof:name":"First Capstone Mortgage Inc",
    "wof:placetype":"venue"
},
  "geometry": {"coordinates":[-81.66345200000001,30.334465],"type":"Point"}
}