{
  "type": "Feature",
  "properties": {
    "addr:full":"21150 Gertrude Ave Port Charlotte FL 33952",
    "addr:postcode":"21150;33952",
    "addr:street":"Gertrude Ave",
    "iso:country":"US",
    "sg:address":"21150 Gertrude Ave",
    "sg:city":"Port Charlotte",
    "sg:classifiers":[
        {
            "category":"Shopping",
            "subcategory":"Jewelry",
            "type":"Retail Goods"
        }
    ],
    "sg:phone":"+1 941 255 5547",
    "sg:postcode":"33952",
    "sg:province":"FL",
    "wof:name":"Lady Remington Jewelry",
    "wof:placetype":"venue"
},
  "geometry": {"coordinates":[-82.10222899999999,26.992281],"type":"Point"}
}