{
  "type": "Feature",
  "properties": {
    "iso:country":"US",
    "sg:address":"14508 Perdido Key Dr",
    "sg:city":"Pensacola",
    "sg:classifiers":[
        {
            "category":"Professional",
            "subcategory":"Management & Consulting",
            "type":"Services"
        }
    ],
    "sg:phone":"+1 850 492 1941",
    "sg:postcode":"32507",
    "sg:province":"FL",
    "sg:tags":[
        "consultant",
        "business"
    ],
    "wof:name":"SDS Intl",
    "wof:placetype":"venue"
},
  "geometry": {"coordinates":[-87.446619,30.294797],"type":"Point"}
}