{
  "type": "Feature",
  "properties": {
    "iso:country":"US",
    "sg:address":"2050 N University Dr",
    "sg:city":"Fort Lauderdale",
    "sg:classifiers":[
        {
            "category":"Shopping",
            "subcategory":"Optical Goods",
            "type":"Retail Goods"
        }
    ],
    "sg:phone":"+1 954 572 8953",
    "sg:postcode":"33322",
    "sg:province":"FL",
    "wof:name":"Lasik Vision Institute",
    "wof:placetype":"venue"
},
  "geometry": {"coordinates":[-80.25697,26.151847],"type":"Point"}
}