{
  "type": "Feature",
  "properties": {
    "addr:full":"4545 Chumuckla Hwy Milton FL 32571",
    "addr:housenumber":"4545",
    "addr:postcode":"32571",
    "addr:street":"Chumuckla Hwy",
    "iso:country":"US",
    "sg:address":"4545 Chumuckla Hwy",
    "sg:city":"Milton",
    "sg:classifiers":[
        {
            "category":"Real Estate",
            "subcategory":"Real Estate Agent",
            "type":"Services"
        }
    ],
    "sg:phone":"+1 850 994 8080",
    "sg:postcode":"32571",
    "sg:province":"FL",
    "wof:name":"Cotton Real Estate Inc",
    "wof:placetype":"venue"
},
  "geometry": {"coordinates":[-87.16160600000001,30.60222],"type":"Point"}
}