{
  "type": "Feature",
  "properties": {
    "addr:full":"1109 Harrison Ave Panama City FL 32401",
    "addr:housenumber":"1109",
    "addr:postcode":"32401",
    "addr:street":"Harrison Ave",
    "iso:country":"US",
    "sg:address":"1109 Harrison Ave",
    "sg:city":"Panama City",
    "sg:classifiers":[
        {
            "category":"Health Services",
            "subcategory":"Doctor",
            "type":"Services"
        }
    ],
    "sg:phone":"+1 850 784 1767",
    "sg:postcode":"32401",
    "sg:province":"FL",
    "sg:tags":[
        "physician",
        "surgeon"
    ],
    "wof:name":"Ordonez Medical Group",
    "wof:placetype":"venue"
},
  "geometry": {"coordinates":[-85.660301,30.169558],"type":"Point"}
}