{
  "type": "Feature",
  "properties": {
    "iso:country":"US",
    "sg:address":"2224 NW 7th St",
    "sg:city":"Miami",
    "sg:classifiers":[
        {
            "category":"Shopping",
            "subcategory":"Department Store",
            "type":"Retail Goods"
        }
    ],
    "sg:phone":"+1 305 643 7878",
    "sg:postcode":"33125",
    "sg:province":"FL",
    "sg:tags":[
        "shop",
        "discount"
    ],
    "wof:name":"Santa Fe Discount",
    "wof:placetype":"venue"
},
  "geometry": {"coordinates":[-80.23178900000001,25.779712],"type":"Point"}
}