{
  "type": "Feature",
  "properties": {
    "iso:country":"US",
    "sg:address":"295 S Wickham Rd",
    "sg:city":"Melbourne",
    "sg:classifiers":[
        {
            "category":"Retail",
            "subcategory":"Auto Repair",
            "type":"Services"
        }
    ],
    "sg:phone":"+1 321 726 9700",
    "sg:postcode":"32904",
    "sg:province":"FL",
    "sg:tags":[
        "transmission"
    ],
    "wof:name":"T & G Transmission",
    "wof:placetype":"venue"
},
  "geometry": {"coordinates":[-80.67265399999999,28.102475],"type":"Point"}
}