{
  "type": "Feature",
  "properties": {
    "addr:full":"1209 S Ridgewood Ave Edgewater FL 32132",
    "addr:housenumber":"1209",
    "addr:postcode":"32132",
    "addr:street":"S Ridgewood Ave",
    "iso:country":"US",
    "sg:address":"1209 S Ridgewood Ave",
    "sg:city":"Edgewater",
    "sg:phone":"+1 386 427 3800",
    "sg:postcode":"32132",
    "sg:province":"FL",
    "wof:name":"Big Planet Pizza Pub",
    "wof:placetype":"venue"
},
  "geometry": {"coordinates":[-80.901027,28.980933],"type":"Point"}
}