{
  "type": "Feature",
  "properties": {
    "iso:country":"US",
    "sg:address":"3970 NW 27th St",
    "sg:city":"Miami",
    "sg:classifiers":[
        {
            "category":"Professional",
            "type":"Services"
        }
    ],
    "sg:phone":"+1 786 265 0888",
    "sg:postcode":"33142",
    "sg:province":"FL",
    "sg:tags":[
        "establishment"
    ],
    "wof:name":"Royalty",
    "wof:placetype":"venue"
},
  "geometry": {"coordinates":[-80.263518,25.800177],"type":"Point"}
}