{
  "type": "Feature",
  "properties": {
    "iso:country":"US",
    "sg:address":"2107 S French Ave",
    "sg:city":"Sanford",
    "sg:classifiers":[
        {
            "category":"Utilities",
            "subcategory":"Mobile Phone",
            "type":"Services"
        }
    ],
    "sg:phone":"+1 407 688 7716",
    "sg:postcode":"32771",
    "sg:province":"FL",
    "sg:tags":[
        "telephone",
        "cellular"
    ],
    "wof:name":"Buy Beehive Wireless",
    "wof:placetype":"venue"
},
  "geometry": {"coordinates":[-81.27301,28.793113],"type":"Point"}
}