{
  "type": "Feature",
  "properties": {
    "addr:full":"1177 Plainfield Ave Orange Park FL 32073",
    "addr:housenumber":"1177",
    "addr:postcode":"32073",
    "addr:street":"Plainfield Ave",
    "iso:country":"US",
    "sg:address":"1177 Plainfield Ave",
    "sg:city":"Orange Park",
    "sg:classifiers":[
        {
            "category":"Real Estate",
            "subcategory":"Real Estate Agent",
            "type":"Services"
        }
    ],
    "sg:phone":"+1 904 269 4663",
    "sg:postcode":"32073",
    "sg:province":"FL",
    "wof:name":"T C Cummings",
    "wof:placetype":"venue"
},
  "geometry": {"coordinates":[-81.704584,30.175671],"type":"Point"}
}