{
  "type": "Feature",
  "properties": {
    "iso:country":"US",
    "sg:address":"2454 N McMullen Booth Rd",
    "sg:city":"Clearwater",
    "sg:classifiers":[
        {
            "category":"Personal",
            "type":"Services"
        }
    ],
    "sg:phone":"+1 727 799 2030",
    "sg:postcode":"33759",
    "sg:province":"FL",
    "sg:tags":[
        "miscellaneous"
    ],
    "wof:name":"Unemployment Specialist Inc",
    "wof:placetype":"venue"
},
  "geometry": {"coordinates":[-82.70893100000001,28.01024],"type":"Point"}
}