{
  "type": "Feature",
  "properties": {
    "iso:country":"US",
    "sg:address":"1026 S Florida Ave",
    "sg:city":"Lakeland",
    "sg:classifiers":[
        {
            "category":"Wholesale",
            "subcategory":"Home Furnishings",
            "type":"Manufacturing & Wholesale Goods"
        }
    ],
    "sg:phone":"+1 863 680 3239",
    "sg:postcode":"33803",
    "sg:province":"FL",
    "sg:tags":[
        "rug",
        "carpet"
    ],
    "wof:name":"Paul Morgan Assoc LLC",
    "wof:placetype":"venue"
},
  "geometry": {"coordinates":[-81.95705,28.032045],"type":"Point"}
}