{
  "type": "Feature",
  "properties": {
    "iso:country":"US",
    "sg:address":"3230 Palm Ave",
    "sg:city":"Hialeah",
    "sg:classifiers":[
        {
            "category":"Autos & Motor Vehicles",
            "subcategory":"Auto Supplies",
            "type":"Retail Goods"
        }
    ],
    "sg:phone":"+1 305 883 6245",
    "sg:postcode":"33012",
    "sg:province":"FL",
    "sg:tags":[
        "tire"
    ],
    "wof:name":"Palm Avenue Tire Corp",
    "wof:placetype":"venue"
},
  "geometry": {"coordinates":[-80.282402,25.851601],"type":"Point"}
}