{
  "type": "Feature",
  "properties": {
    "addr:full":"6049 NW 3rd St Pompano Beach FL 33063",
    "addr:housenumber":"6049",
    "addr:postcode":"33063",
    "addr:street":"Nw 3Rd St",
    "iso:country":"US",
    "sg:address":"6049 NW 3rd St",
    "sg:city":"Pompano Beach",
    "sg:classifiers":[
        {
            "category":"Social Services",
            "subcategory":"Adult Care",
            "type":"Services"
        }
    ],
    "sg:phone":"+1 954 971 1387",
    "sg:postcode":"33063",
    "sg:province":"FL",
    "sg:tags":[
        "residential"
    ],
    "wof:name":"Trinity Village Retirement Ctr",
    "wof:placetype":"venue"
},
  "geometry": {"coordinates":[-80.20881900000001,26.233298],"type":"Point"}
}