{
  "type": "Feature",
  "properties": {
    "iso:country":"US",
    "sg:address":"5550 W Idlewild Ave",
    "sg:city":"Tampa",
    "sg:classifiers":[
        {
            "category":"Communications",
            "subcategory":"Television Station",
            "type":"Services"
        }
    ],
    "sg:phone":"+1 813 880 5000",
    "sg:postcode":"33634",
    "sg:province":"FL",
    "sg:tags":[
        "broadcast",
        "representative"
    ],
    "wof:name":"Viasat",
    "wof:placetype":"venue"
},
  "geometry": {"coordinates":[-82.53543999999999,28.001522],"type":"Point"}
}