{
  "type": "Feature",
  "properties": {
    "iso:country":"US",
    "sg:address":"1409 Sadler Rd",
    "sg:city":"Fernandina Beach",
    "sg:classifiers":[
        {
            "category":"Banks & Credit Unions",
            "subcategory":"Bank",
            "type":"Services"
        }
    ],
    "sg:phone":"+1 904 277 3677",
    "sg:postcode":"32034",
    "sg:province":"FL",
    "wof:name":"AM South Bank",
    "wof:placetype":"venue"
},
  "geometry": {"coordinates":[-81.452951,30.639745],"type":"Point"}
}