{
  "type": "Feature",
  "properties": {
    "addr:full":"500 1st St Indian Rocks Beach FL 33785",
    "addr:housenumber":"500",
    "addr:postcode":"33785",
    "addr:street":"1St St",
    "iso:country":"US",
    "sg:address":"500 1st St",
    "sg:city":"Indian Rocks Beach",
    "sg:classifiers":[
        {
            "category":"Bars & Pubs",
            "type":"Food & Drink"
        }
    ],
    "sg:menulink":"http://www.allmenus.com/fl/clearwater/36146-p-js-oyster-bar/menu/",
    "sg:phone":"+1 727 596 5898",
    "sg:postcode":"33785",
    "sg:province":"FL",
    "sg:tags":[
        "seafood",
        "american"
    ],
    "wof:name":"P J's Oyster Bar",
    "wof:placetype":"venue"
},
  "geometry": {"coordinates":[-82.84934,27.884247],"type":"Point"}
}