{
  "type": "Feature",
  "properties": {
    "iso:country":"US",
    "sg:address":"410 S Pegasus Ave",
    "sg:city":"Clearwater",
    "sg:classifiers":[
        {
            "category":"Retail",
            "subcategory":"Veterinary Services",
            "type":"Services"
        }
    ],
    "sg:phone":"+1 727 461 4393",
    "sg:postcode":"33765",
    "sg:province":"FL",
    "sg:tags":[
        "veterinarian"
    ],
    "wof:name":"A Pet's Place",
    "wof:placetype":"venue"
},
  "geometry": {"coordinates":[-82.76089899999999,27.961625],"type":"Point"}
}