{
  "type": "Feature",
  "properties": {
    "addr:full":"2717 15th St Vero Beach FL 32960",
    "addr:housenumber":"2717",
    "addr:postcode":"32960",
    "addr:street":"15Th St",
    "iso:country":"US",
    "sg:address":"2717 15th St",
    "sg:city":"Vero Beach",
    "sg:classifiers":[
        {
            "category":"Shopping",
            "subcategory":"Bicycles & Sporting Goods",
            "type":"Retail Goods"
        }
    ],
    "sg:phone":"+1 772 569 2709",
    "sg:postcode":"32960",
    "sg:province":"FL",
    "wof:name":"Grace Arms Co",
    "wof:placetype":"venue"
},
  "geometry": {"coordinates":[-80.414658,27.629088],"type":"Point"}
}