{
  "type": "Feature",
  "properties": {
    "iso:country":"US",
    "sg:address":"12825 NW 10th Ln",
    "sg:city":"Miami",
    "sg:classifiers":[
        {
            "category":"Professional",
            "type":"Services"
        }
    ],
    "sg:phone":"+1 305 226 4061",
    "sg:postcode":"33182",
    "sg:province":"FL",
    "wof:name":"Christian Art Cmmncations Corp",
    "wof:placetype":"venue"
},
  "geometry": {"coordinates":[-80.403503,25.780558],"type":"Point"}
}