{
  "type": "Feature",
  "properties": {
    "iso:country":"US",
    "sg:address":"974 Sabal Grove Dr",
    "sg:city":"Rockledge",
    "sg:classifiers":[
        {
            "category":"Building & Trades",
            "subcategory":"Landscaping Services",
            "type":"Services"
        }
    ],
    "sg:phone":"+1 321 750 3983",
    "sg:postcode":"32955",
    "sg:province":"FL",
    "wof:name":"Bryan Goodson Lawn Maintenance",
    "wof:placetype":"venue"
},
  "geometry": {"coordinates":[-80.72632,28.310457],"type":"Point"}
}