{
  "type": "Feature",
  "properties": {
    "addr:full":"4674 N Powerline Rd Pompano Beach FL 33073",
    "addr:housenumber":"4674",
    "addr:postcode":"33073",
    "addr:street":"N Powerline Rd",
    "iso:country":"US",
    "sg:address":"4674 N Powerline Rd",
    "sg:city":"Pompano Beach",
    "sg:classifiers":[
        {
            "category":"Building & Trades",
            "subcategory":"Construction",
            "type":"Services"
        }
    ],
    "sg:phone":"+1 954 984 9080",
    "sg:postcode":"33073",
    "sg:province":"FL",
    "sg:tags":[
        "general",
        "commercial",
        "contractor"
    ],
    "wof:name":"Sharp General Contractors Inc",
    "wof:placetype":"venue"
},
  "geometry": {"coordinates":[-80.15225,26.287205],"type":"Point"}
}