{
  "type": "Feature",
  "properties": {
    "addr:full":"5755 Yahl St Naples FL 34109",
    "addr:housenumber":"5755",
    "addr:postcode":"34109",
    "addr:street":"Yahl St",
    "iso:country":"US",
    "sg:address":"5755 Yahl St",
    "sg:city":"Naples",
    "sg:classifiers":[
        {
            "category":"Retail",
            "subcategory":"Auto Repair",
            "type":"Services"
        }
    ],
    "sg:phone":"+1 239 593 6262",
    "sg:postcode":"34109",
    "sg:province":"FL",
    "sg:tags":[
        "wrecker"
    ],
    "wof:name":"Cruz Auto Truck Storage",
    "wof:placetype":"venue"
},
  "geometry": {"coordinates":[-81.77757699999999,26.21692],"type":"Point"}
}