{
  "type": "Feature",
  "properties": {
    "iso:country":"US",
    "sg:address":"916 Wicketrun Dr",
    "sg:city":"Brandon",
    "sg:classifiers":[
        {
            "category":"Professional",
            "subcategory":"Art Services",
            "type":"Services"
        }
    ],
    "sg:phone":"+1 813 681 9520",
    "sg:postcode":"33510",
    "sg:province":"FL",
    "sg:tags":[
        "commercial",
        "design"
    ],
    "wof:name":"Ellis Eugene A Graphics",
    "wof:placetype":"venue"
},
  "geometry": {"coordinates":[-82.276094,27.952777],"type":"Point"}
}