{
  "type": "Feature",
  "properties": {
    "iso:country":"US",
    "sg:address":"716 N 14th St",
    "sg:city":"Leesburg",
    "sg:classifiers":[
        {
            "category":"Personal",
            "subcategory":"Beauty Salon",
            "type":"Services"
        }
    ],
    "sg:phone":"+1 352 315 1748",
    "sg:postcode":"34748",
    "sg:province":"FL",
    "sg:tags":[
        "shop"
    ],
    "wof:name":"Precise Images Hair Salon",
    "wof:placetype":"venue"
},
  "geometry": {"coordinates":[-81.88735200000001,28.818633],"type":"Point"}
}