{
  "type": "Feature",
  "properties": {
    "iso:country":"US",
    "sg:address":"33701 State Hwy 52",
    "sg:city":"St Leo",
    "sg:classifiers":[
        {
            "category":"Shopping",
            "subcategory":"Gifts & Souvenirs",
            "type":"Retail Goods"
        }
    ],
    "sg:phone":"+1 352 588 2606",
    "sg:postcode":"33574",
    "sg:province":"FL",
    "sg:tags":[
        "shop"
    ],
    "wof:name":"St Leo Abbey Gift Shop",
    "wof:placetype":"venue"
},
  "geometry": {"coordinates":[-82.20402199999999,28.36055],"type":"Point"}
}