{
  "type": "Feature",
  "properties": {
    "addr:full":"23492 US Hwy 19 Clearwater FL 33765",
    "addr:housenumber":"23492",
    "addr:postcode":"33765",
    "addr:street":"Us Hwy 19",
    "iso:country":"US",
    "sg:address":"23492 US Hwy 19",
    "sg:city":"Clearwater",
    "sg:classifiers":[
        {
            "category":"Shopping",
            "subcategory":"Computers & Home Electronics",
            "type":"Retail Goods"
        }
    ],
    "sg:phone":"+1 727 726 7575",
    "sg:postcode":"33765",
    "sg:province":"FL",
    "sg:tags":[
        "high",
        "fidelity",
        "stereophonic"
    ],
    "wof:name":"St Cecilia Sound Gallery",
    "wof:placetype":"venue"
},
  "geometry": {"coordinates":[-82.72969500000001,27.988389],"type":"Point"}
}