{
  "type": "Feature",
  "properties": {
    "iso:country":"US",
    "sg:address":"3511 12th St W",
    "sg:city":"Lehigh Acres",
    "sg:classifiers":[
        {
            "category":"Freight",
            "type":"Transportation"
        }
    ],
    "sg:phone":"+1 239 693 7211",
    "sg:postcode":"33971",
    "sg:province":"FL",
    "sg:tags":[
        "operator",
        "local",
        "trucking"
    ],
    "wof:name":"Alderman Trucking",
    "wof:placetype":"venue"
},
  "geometry": {"coordinates":[-81.690562,26.624147],"type":"Point"}
}