{
  "type": "Feature",
  "properties": {
    "iso:country":"US",
    "sg:address":"2935 SE 58th Ave",
    "sg:city":"Ocala",
    "sg:classifiers":[
        {
            "category":"Insurance",
            "subcategory":"Hazard Insurance",
            "type":"Services"
        }
    ],
    "sg:phone":"+1 352 624 2100",
    "sg:postcode":"34480",
    "sg:province":"FL",
    "wof:name":"Central States Health & Life Co Of Omaha",
    "wof:placetype":"venue"
},
  "geometry": {"coordinates":[-82.053658,29.15858],"type":"Point"}
}