{
  "type": "Feature",
  "properties": {
    "addr:full":"6782 Stirling Rd Hollywood FL 33024",
    "addr:housenumber":"6782",
    "addr:postcode":"33024",
    "addr:street":"Stirling Rd",
    "iso:country":"US",
    "sg:address":"6782 Stirling Rd",
    "sg:city":"Hollywood",
    "sg:classifiers":[
        {
            "category":"Personal",
            "subcategory":"Barber",
            "type":"Services"
        }
    ],
    "sg:phone":"+1 954 987 1309",
    "sg:postcode":"33024",
    "sg:province":"FL",
    "sg:tags":[
        "shop"
    ],
    "wof:name":"Sterling Plaza Barber Shop",
    "wof:placetype":"venue"
},
  "geometry": {"coordinates":[-80.22393,26.046217],"type":"Point"}
}