{
  "type": "Feature",
  "properties": {
    "addr:full":"3603 Crescent Park Blvd Orlando FL 32812",
    "addr:housenumber":"3603",
    "addr:postcode":"32812",
    "addr:street":"Crescent Park Blvd",
    "iso:country":"US",
    "sg:address":"3603 Crescent Park Blvd",
    "sg:city":"Orlando",
    "sg:classifiers":[
        {
            "category":"Education",
            "subcategory":"Vocational School",
            "type":"Public Place"
        }
    ],
    "sg:phone":"+1 407 812 1904",
    "sg:postcode":"32812",
    "sg:province":"FL",
    "sg:tags":[
        "computer",
        "technology",
        "child"
    ],
    "wof:name":"Compuchild Of Central Florida",
    "wof:placetype":"venue"
},
  "geometry": {"coordinates":[-81.337907,28.464325],"type":"Point"}
}