{
  "type": "Feature",
  "properties": {
    "iso:country":"US",
    "sg:address":"1400 N Federal Hwy",
    "sg:city":"Hollywood",
    "sg:classifiers":[
        {
            "category":"Wholesale",
            "subcategory":"Construction Materials",
            "type":"Manufacturing & Wholesale Goods"
        }
    ],
    "sg:phone":"+1 954 922 2900",
    "sg:postcode":"33020",
    "sg:province":"FL",
    "sg:tags":[
        "tile",
        "installation",
        "marble"
    ],
    "wof:name":"Plad Tile and Foam",
    "wof:placetype":"venue"
},
  "geometry": {"coordinates":[-80.14324499999999,26.024459],"type":"Point"}
}