{
  "type": "Feature",
  "properties": {
    "addr:full":"5750 Coach House Cir Boca Raton FL 33486",
    "addr:housenumber":"5750",
    "addr:postcode":"33486",
    "addr:street":"Coach House Cir",
    "iso:country":"US",
    "sg:address":"5750 Coach House Cir",
    "sg:city":"Boca Raton",
    "sg:classifiers":[
        {
            "category":"Professional",
            "subcategory":"Management & Consulting",
            "type":"Services"
        }
    ],
    "sg:phone":"+1 561 750 9720",
    "sg:postcode":"33486",
    "sg:province":"FL",
    "sg:tags":[
        "marketing",
        "consultant"
    ],
    "wof:name":"Imagemaker Communications Inc",
    "wof:placetype":"venue"
},
  "geometry": {"coordinates":[-80.13055,26.352095],"type":"Point"}
}