{
  "type": "Feature",
  "properties": {
    "addr:full":"12000 Biscayne Blvd Miami FL 33181",
    "addr:housenumber":"12000",
    "addr:postcode":"33181",
    "addr:street":"Biscayne Blvd",
    "iso:country":"US",
    "sg:address":"12000 Biscayne Blvd",
    "sg:city":"Miami",
    "sg:classifiers":[
        {
            "category":"Professional",
            "subcategory":"Computer Services",
            "type":"Services"
        }
    ],
    "sg:phone":"+1 305 892 2611",
    "sg:postcode":"33181",
    "sg:province":"FL",
    "sg:tags":[
        "communication",
        "cable",
        "cellular"
    ],
    "wof:name":"Comcast",
    "wof:placetype":"venue"
},
  "geometry": {"coordinates":[-80.164309,25.887532],"type":"Point"}
}