{
  "type": "Feature",
  "properties": {
    "addr:full":"102 E 49th St Hialeah FL 33013",
    "addr:housenumber":"102",
    "addr:postcode":"33013",
    "addr:street":"E 49Th St",
    "iso:country":"US",
    "sg:address":"102 E 49th St",
    "sg:city":"Hialeah",
    "sg:classifiers":[
        {
            "category":"Professional",
            "subcategory":"Lawyer & Legal Services",
            "type":"Services"
        }
    ],
    "sg:phone":"+1 305 826 9994",
    "sg:postcode":"33013",
    "sg:province":"FL",
    "wof:name":"Izquierdo Alexis",
    "wof:placetype":"venue"
},
  "geometry": {"coordinates":[-80.2808,25.8668],"type":"Point"}
}