{
  "type": "Feature",
  "properties": {
    "iso:country":"US",
    "sg:address":"5262 S Dale Mabry Hwy",
    "sg:city":"Tampa",
    "sg:classifiers":[
        {
            "category":"Autos & Motor Vehicles",
            "subcategory":"Fuel & Gas Station",
            "type":"Retail Goods"
        }
    ],
    "sg:phone":"+1 813 839 1337",
    "sg:postcode":"33611",
    "sg:province":"FL",
    "sg:tags":[
        "oil"
    ],
    "wof:name":"Nanu's Enterprises Inc",
    "wof:placetype":"venue"
},
  "geometry": {"coordinates":[-82.506338,27.887807],"type":"Point"}
}