{
  "type": "Feature",
  "properties": {
    "iso:country":"US",
    "sg:address":"5500 Military Trl",
    "sg:city":"Jupiter",
    "sg:classifiers":[
        {
            "category":"Communications",
            "subcategory":"Film & Video Production",
            "type":"Services"
        }
    ],
    "sg:phone":"+1 561 799 3363",
    "sg:postcode":"33458",
    "sg:province":"FL",
    "sg:tags":[
        "taping"
    ],
    "wof:name":"Lighthouse Atlantic Production",
    "wof:placetype":"venue"
},
  "geometry": {"coordinates":[-80.10261199999999,26.907697],"type":"Point"}
}