{
  "type": "Feature",
  "properties": {
    "addr:full":"1 Industrial Park Rd Destin FL 32541",
    "addr:housenumber":"1",
    "addr:postcode":"32541",
    "addr:street":"Industrial Park Rd",
    "iso:country":"US",
    "sg:address":"1 Industrial Park Rd",
    "sg:city":"Destin",
    "sg:classifiers":[
        {
            "category":"Wholesale",
            "subcategory":"Construction Materials",
            "type":"Manufacturing & Wholesale Goods"
        },
        {
            "category":"Building & Trades",
            "subcategory":"Construction",
            "type":"Services"
        }
    ],
    "sg:phone":"+1 850 654 1981",
    "sg:postcode":"32541",
    "sg:province":"FL",
    "sg:tags":[
        "concrete",
        "product",
        "contractor"
    ],
    "wof:name":"Creative Columns",
    "wof:placetype":"venue"
},
  "geometry": {"coordinates":[-86.478239,30.395336],"type":"Point"}
}