{
  "type": "Feature",
  "properties": {
    "addr:full":"8219 Solano Bay Loop Tampa FL 33635",
    "addr:housenumber":"8219",
    "addr:postcode":"33635",
    "addr:street":"Solano Bay Loop",
    "iso:country":"US",
    "sg:address":"8219 Solano Bay Loop",
    "sg:city":"Tampa",
    "sg:classifiers":[
        {
            "category":"Shopping",
            "subcategory":"Catalog Store",
            "type":"Retail Goods"
        }
    ],
    "sg:phone":"+1 813 925 1520",
    "sg:postcode":"33635",
    "sg:province":"FL",
    "sg:tags":[
        "house",
        "mail"
    ],
    "wof:name":"Xpress Your View",
    "wof:placetype":"venue"
},
  "geometry": {"coordinates":[-82.64017699999999,28.028511],"type":"Point"}
}