{
  "type": "Feature",
  "properties": {
    "addr:full":"7003 Ridge Rd New Port Richey FL 34668",
    "addr:housenumber":"7003",
    "addr:postcode":"34668",
    "addr:street":"Ridge Rd",
    "iso:country":"US",
    "sg:address":"7003 Ridge Rd",
    "sg:city":"New Port Richey",
    "sg:classifiers":[
        {
            "category":"Building & Trades",
            "subcategory":"Equipment Rental",
            "type":"Services"
        }
    ],
    "sg:phone":"+1 727 845 4979",
    "sg:postcode":"34668",
    "sg:province":"FL",
    "wof:name":"Video King",
    "wof:placetype":"venue"
},
  "geometry": {"coordinates":[-82.698644,28.280697],"type":"Point"}
}