{
  "type": "Feature",
  "properties": {
    "iso:country":"US",
    "sg:address":"7301 NW 70th St",
    "sg:city":"Miami",
    "sg:classifiers":[
        {
            "category":"Utilities",
            "subcategory":"Water",
            "type":"Services"
        }
    ],
    "sg:phone":"+1 305 883 8640",
    "sg:postcode":"33166",
    "sg:province":"FL",
    "sg:tags":[
        "management",
        "supply"
    ],
    "wof:name":"Public Works Dept",
    "wof:placetype":"venue"
},
  "geometry": {"coordinates":[-80.31572199999999,25.837183],"type":"Point"}
}