{
  "type": "Feature",
  "properties": {
    "addr:full":"5315 NW 27 Ave Gainesville FL 32606",
    "addr:housenumber":"5315",
    "addr:postcode":"32606",
    "addr:street":"Nw 27 Ave",
    "iso:country":"US",
    "sg:address":"5315 NW 27 Ave",
    "sg:city":"Gainesville",
    "sg:classifiers":[
        {
            "category":"Wholesale",
            "subcategory":"Apparel",
            "type":"Manufacturing & Wholesale Goods"
        }
    ],
    "sg:phone":"+1 352 374 7010",
    "sg:postcode":"32606",
    "sg:province":"FL",
    "sg:tags":[
        "piece"
    ],
    "wof:name":"Delgran International",
    "wof:placetype":"venue"
},
  "geometry": {"coordinates":[-82.40137799999999,29.677677],"type":"Point"}
}