{
  "type": "Feature",
  "properties": {
    "iso:country":"US",
    "sg:address":"7090 SW 117th Ave",
    "sg:city":"Miami",
    "sg:classifiers":[
        {
            "category":"Professional",
            "subcategory":"Management & Consulting",
            "type":"Services"
        }
    ],
    "sg:phone":"+1 305 270 0334",
    "sg:postcode":"33183",
    "sg:province":"FL",
    "sg:tags":[
        "business"
    ],
    "wof:name":"Equestrian Authority Inc",
    "wof:placetype":"venue"
},
  "geometry": {"coordinates":[-80.382306,25.702038],"type":"Point"}
}