{
  "type": "Feature",
  "properties": {
    "addr:full":"10731 Lannom Ln Sarasota FL 34240",
    "addr:housenumber":"10731",
    "addr:postcode":"34240",
    "addr:street":"Lannom Ln",
    "iso:country":"US",
    "sg:address":"10731 Lannom Ln",
    "sg:city":"Sarasota",
    "sg:classifiers":[
        {
            "category":"Manufacturing",
            "subcategory":"Metals",
            "type":"Manufacturing & Wholesale Goods"
        }
    ],
    "sg:phone":"+1 941 379 9990",
    "sg:postcode":"34240",
    "sg:province":"FL",
    "sg:tags":[
        "metalwork",
        "sheet",
        "mfg"
    ],
    "wof:name":"KMC Fabricators",
    "wof:placetype":"venue"
},
  "geometry": {"coordinates":[-82.361656,27.347882],"type":"Point"}
}