{
  "type": "Feature",
  "properties": {
    "iso:country":"US",
    "sg:address":"20480 Huffmaster Rd",
    "sg:city":"Fort Myers",
    "sg:classifiers":[
        {
            "category":"Arts & Performance",
            "subcategory":"Theater",
            "type":"Entertainment"
        }
    ],
    "sg:phone":"+1 239 543 2461",
    "sg:postcode":"33917",
    "sg:province":"FL",
    "sg:tags":[
        "group"
    ],
    "wof:name":"Southland Messengers Inc",
    "wof:placetype":"venue"
},
  "geometry": {"coordinates":[-81.84217700000001,26.760536],"type":"Point"}
}