{
  "type": "Feature",
  "properties": {
    "addr:full":"12400 NW 15th St Sunrise FL 33323",
    "addr:housenumber":"12400",
    "addr:postcode":"33323",
    "addr:street":"Nw 15Th St",
    "iso:country":"US",
    "sg:address":"12400 NW 15th St",
    "sg:city":"Sunrise",
    "sg:classifiers":[
        {
            "category":"Banks & Credit Unions",
            "subcategory":"Investment Brokerage",
            "type":"Services"
        }
    ],
    "sg:phone":"+1 954 838 8503",
    "sg:postcode":"33323",
    "sg:province":"FL",
    "sg:tags":[
        "consultant",
        "planning",
        "financial"
    ],
    "wof:name":"American Express Financial Adv",
    "wof:placetype":"venue"
},
  "geometry": {"coordinates":[-80.317314,26.141968],"type":"Point"}
}