{
  "type": "Feature",
  "properties": {
    "addr:full":"2851 W 68th St Hialeah FL 33018",
    "addr:housenumber":"2851",
    "addr:postcode":"33018",
    "addr:street":"W 68Th St",
    "iso:country":"US",
    "sg:address":"2851 W 68th St",
    "sg:city":"Hialeah",
    "sg:classifiers":[
        {
            "category":"Restaurant",
            "type":"Food & Drink"
        }
    ],
    "sg:menulink":"http://www.allmenus.com/fl/hialeah/93657-wing-zone/menu/",
    "sg:phone":"+1 999 999 9999",
    "sg:postcode":"33018",
    "sg:province":"FL",
    "sg:tags":[
        "american",
        "wing"
    ],
    "wof:name":"Wing Zone",
    "wof:placetype":"venue"
},
  "geometry": {"coordinates":[-80.339718,25.884148],"type":"Point"}
}