{
  "type": "Feature",
  "properties": {
    "iso:country":"US",
    "sg:address":"16804 Spring St",
    "sg:city":"White Springs",
    "sg:classifiers":[
        {
            "category":"Freight",
            "type":"Transportation"
        }
    ],
    "sg:phone":"+1 386 397 2723",
    "sg:postcode":"32096",
    "sg:province":"FL",
    "sg:tags":[
        "hauling",
        "trucking"
    ],
    "wof:name":"B & E Hauling Inc",
    "wof:placetype":"venue"
},
  "geometry": {"coordinates":[-82.746889,30.330006],"type":"Point"}
}