{
  "type": "Feature",
  "properties": {
    "addr:full":"1840 W 49th St Hialeah FL 33012",
    "addr:housenumber":"1840",
    "addr:postcode":"33012",
    "addr:street":"W 49Th St",
    "iso:country":"US",
    "sg:address":"1840 W 49th St",
    "sg:city":"Hialeah",
    "sg:classifiers":[
        {
            "category":"Organizations",
            "subcategory":"Labor Organization",
            "type":"Services"
        }
    ],
    "sg:phone":"+1 305 821 3121",
    "sg:postcode":"33012",
    "sg:province":"FL",
    "wof:name":"Communications Workers-America",
    "wof:placetype":"venue"
},
  "geometry": {"coordinates":[-80.319397,25.866497],"type":"Point"}
}