{
  "type": "Feature",
  "properties": {
    "iso:country":"US",
    "sg:address":"590 N Broadway Ave",
    "sg:city":"Bartow",
    "sg:classifiers":[
        {
            "category":"Fast Food",
            "type":"Food & Drink"
        },
        {
            "category":"Restaurant",
            "type":"Food & Drink"
        }
    ],
    "sg:phone":"+1 863 533 3600",
    "sg:postcode":"33830",
    "sg:province":"FL",
    "sg:tags":[
        "chicken",
        "style",
        "american",
        "family",
        "take"
    ],
    "sg:website":"http://www.zaxbys.com",
    "wof:name":"Zaxby's",
    "wof:placetype":"venue"
},
  "geometry": {"coordinates":[-81.84333700000001,27.900234],"type":"Point"}
}