{
  "type": "Feature",
  "properties": {
    "iso:country":"US",
    "sg:address":"444 24th St",
    "sg:city":"West Palm Beach",
    "sg:classifiers":[
        {
            "category":"Restaurant",
            "type":"Food & Drink"
        }
    ],
    "sg:phone":"+1 561 837 2200",
    "sg:postcode":"33407",
    "sg:province":"FL",
    "sg:tags":[
        "eating"
    ],
    "wof:name":"Ralph's Place",
    "wof:placetype":"venue"
},
  "geometry": {"coordinates":[-80.054046,26.735542],"type":"Point"}
}