{
  "type": "Feature",
  "properties": {
    "addr:full":"17110 Panama City Beach Pkwy Panama City Bch FL 32413",
    "addr:housenumber":"17110",
    "addr:postcode":"32413",
    "addr:street":"Panama;Beach Pkwy",
    "iso:country":"US",
    "sg:address":"17110 Panama City Beach Pkwy",
    "sg:city":"Panama City Bch",
    "sg:classifiers":[
        {
            "category":"Restaurant",
            "type":"Food & Drink"
        }
    ],
    "sg:phone":"+1 850 233 0046",
    "sg:postcode":"32413",
    "sg:province":"FL",
    "wof:name":"Waffle House",
    "wof:placetype":"venue"
},
  "geometry": {"coordinates":[-85.90022399999999,30.234338],"type":"Point"}
}