{
  "type": "Feature",
  "properties": {
    "iso:country":"US",
    "sg:address":"9901 SW 47th St",
    "sg:city":"Miami",
    "sg:classifiers":[
        {
            "category":"Shopping",
            "subcategory":"Catalog Store",
            "type":"Retail Goods"
        }
    ],
    "sg:phone":"+1 305 223 1976",
    "sg:postcode":"33165",
    "sg:province":"FL",
    "sg:tags":[
        "mail",
        "order",
        "online"
    ],
    "wof:name":"The Wee Wardrobe",
    "wof:placetype":"venue"
},
  "geometry": {"coordinates":[-80.35571299999999,25.72407],"type":"Point"}
}