{
  "type": "Feature",
  "properties": {
    "addr:full":"3949 Evans Ave Fort Myers FL 33901",
    "addr:housenumber":"3949",
    "addr:postcode":"33901",
    "addr:street":"Evans Ave",
    "iso:country":"US",
    "sg:address":"3949 Evans Ave",
    "sg:city":"Fort Myers",
    "sg:classifiers":[
        {
            "category":"Health Services",
            "subcategory":"Doctor",
            "type":"Services"
        }
    ],
    "sg:phone":"+1 239 939 2428",
    "sg:postcode":"33901",
    "sg:province":"FL",
    "sg:tags":[
        "clinic",
        "medical"
    ],
    "wof:name":"Than Tin Myo MD",
    "wof:placetype":"venue"
},
  "geometry": {"coordinates":[-81.859663,26.602888],"type":"Point"}
}