{
  "type": "Feature",
  "properties": {
    "iso:country":"US",
    "sg:address":"2669 N Tamiami Trl",
    "sg:city":"Fort Myers",
    "sg:classifiers":[
        {
            "category":"Real Estate",
            "subcategory":"Real Estate Operator",
            "type":"Services"
        }
    ],
    "sg:phone":"+1 239 995 6977",
    "sg:postcode":"33903",
    "sg:province":"FL",
    "sg:tags":[
        "apartment"
    ],
    "wof:name":"Blue Lantern Apartments",
    "wof:placetype":"venue"
},
  "geometry": {"coordinates":[-81.892684,26.701081],"type":"Point"}
}