{
  "type": "Feature",
  "properties": {
    "iso:country":"US",
    "sg:address":"1825 Sunset Point Rd",
    "sg:city":"Clearwater",
    "sg:classifiers":[
        {
            "category":"Building & Trades",
            "subcategory":"Construction",
            "type":"Services"
        }
    ],
    "sg:phone":"+1 727 461 3039",
    "sg:postcode":"33765",
    "sg:province":"FL",
    "sg:tags":[
        "general",
        "contractor"
    ],
    "wof:name":"Metron Construction Co",
    "wof:placetype":"venue"
},
  "geometry": {"coordinates":[-82.761945,27.989914],"type":"Point"}
}