{
  "type": "Feature",
  "properties": {
    "iso:country":"US",
    "sg:address":"105 E Main St",
    "sg:city":"Bartow",
    "sg:classifiers":[
        {
            "category":"Shopping",
            "subcategory":"Used Merchandise",
            "type":"Retail Goods"
        }
    ],
    "sg:phone":"+1 863 533 0290",
    "sg:postcode":"33830",
    "sg:province":"FL",
    "sg:tags":[
        "antique"
    ],
    "wof:name":"Yesterday & Today",
    "wof:placetype":"venue"
},
  "geometry": {"coordinates":[-81.842448,27.896371],"type":"Point"}
}