{
  "type": "Feature",
  "properties": {
    "addr:full":"3014 Senna Ct Orlando FL 32826",
    "addr:postcode":"3014;32826",
    "addr:street":"Senna Ct",
    "iso:country":"US",
    "sg:address":"3014 Senna Ct",
    "sg:city":"Orlando",
    "sg:classifiers":[
        {
            "category":"Building & Trades",
            "subcategory":"Construction",
            "type":"Services"
        }
    ],
    "sg:phone":"+1 407 658 0801",
    "sg:postcode":"32826",
    "sg:province":"FL",
    "sg:tags":[
        "contractor"
    ],
    "wof:name":"Kenneth W Nelson Contractor",
    "wof:placetype":"venue"
},
  "geometry": {"coordinates":[-81.17936,28.588149],"type":"Point"}
}