{
  "type": "Feature",
  "properties": {
    "iso:country":"US",
    "sg:address":"271 7th St SW",
    "sg:city":"Naples",
    "sg:classifiers":[
        {
            "category":"Building & Trades",
            "subcategory":"Construction",
            "type":"Services"
        }
    ],
    "sg:phone":"+1 239 352 6427",
    "sg:postcode":"34117",
    "sg:province":"FL",
    "sg:tags":[
        "heavy"
    ],
    "wof:name":"Todd Beckman Grading Inc",
    "wof:placetype":"venue"
},
  "geometry": {"coordinates":[-81.620908,26.226717],"type":"Point"}
}