{
  "type": "Feature",
  "properties": {
    "iso:country":"US",
    "sg:address":"1804 Thunder Hill Way",
    "sg:city":"Tallahassee",
    "sg:classifiers":[
        {
            "category":"Shopping",
            "subcategory":"Jewelry",
            "type":"Retail Goods"
        }
    ],
    "sg:phone":"+1 850 894 2892",
    "sg:postcode":"32312",
    "sg:province":"FL",
    "sg:tags":[
        "precious",
        "semi-precious",
        "stone"
    ],
    "wof:name":"Earthly Treasures Jewelry",
    "wof:placetype":"venue"
},
  "geometry": {"coordinates":[-84.24530900000001,30.60816],"type":"Point"}
}