{
  "type": "Feature",
  "properties": {
    "iso:country":"US",
    "sg:address":"10500 Stirling Rd",
    "sg:city":"Hollywood",
    "sg:classifiers":[
        {
            "category":"Social Services",
            "type":"Services"
        },
        {
            "category":"Professional",
            "subcategory":"Employment Agencies",
            "type":"Services"
        },
        {
            "category":"Sports & Exercise",
            "subcategory":"Sports Center",
            "type":"Entertainment"
        }
    ],
    "sg:phone":"+1 954 434 2541",
    "sg:postcode":"33026",
    "sg:province":"FL",
    "sg:tags":[
        "workers'",
        "placement",
        "volunteer"
    ],
    "wof:name":"The Optimist Club Of Cooper City Inc",
    "wof:placetype":"venue"
},
  "geometry": {"coordinates":[-80.286531,26.044311],"type":"Point"}
}