{
  "type": "Feature",
  "properties": {
    "addr:full":"11 Hibiscus St Tarpon Springs FL 34689",
    "addr:housenumber":"11",
    "addr:postcode":"34689",
    "addr:street":"Hibiscus St",
    "iso:country":"US",
    "sg:address":"11 Hibiscus St",
    "sg:city":"Tarpon Springs",
    "sg:classifiers":[
        {
            "category":"Personal",
            "type":"Services"
        }
    ],
    "sg:phone":"+1 727 934 0085",
    "sg:postcode":"34689",
    "sg:province":"FL",
    "sg:tags":[
        "therapist",
        "massage"
    ],
    "wof:name":"Back Care Ctr",
    "wof:placetype":"venue"
},
  "geometry": {"coordinates":[-82.756074,28.147127],"type":"Point"}
}