{
  "type": "Feature",
  "properties": {
    "iso:country":"US",
    "sg:address":"1544 E Commercial Blvd",
    "sg:city":"Oakland Park",
    "sg:classifiers":[
        {
            "category":"Restaurant",
            "type":"Food & Drink"
        }
    ],
    "sg:phone":"+1 954 491 4115",
    "sg:postcode":"33334",
    "sg:province":"FL",
    "wof:name":"Subway Sandwiches & Salads",
    "wof:placetype":"venue"
},
  "geometry": {"coordinates":[-80.128407,26.188869],"type":"Point"}
}