{
  "type": "Feature",
  "properties": {
    "iso:country":"US",
    "sg:address":"1221 Minnesota Ave",
    "sg:city":"Winter Park",
    "sg:classifiers":[
        {
            "category":"Retail",
            "subcategory":"Auto Rental",
            "type":"Services"
        }
    ],
    "sg:phone":"+1 407 539 3046",
    "sg:postcode":"32789",
    "sg:province":"FL",
    "sg:tags":[
        "renting",
        "truck",
        "leasing"
    ],
    "wof:name":"Hertz Corp",
    "wof:placetype":"venue"
},
  "geometry": {"coordinates":[-81.366647,28.589533],"type":"Point"}
}