{
  "type": "Feature",
  "properties": {
    "addr:full":"2228 Winter Woods Blvd Winter Park FL 32792",
    "addr:housenumber":"2228",
    "addr:postcode":"32792",
    "addr:street":"Winter Woods Blvd",
    "iso:country":"US",
    "sg:address":"2228 Winter Woods Blvd",
    "sg:city":"Winter Park",
    "sg:classifiers":[
        {
            "category":"Professional",
            "subcategory":"Research",
            "type":"Services"
        }
    ],
    "sg:phone":"+1 407 671 9000",
    "sg:postcode":"32792",
    "sg:province":"FL",
    "sg:tags":[
        "archaeologist"
    ],
    "wof:name":"Florida Archeological Conslntg",
    "wof:placetype":"venue"
},
  "geometry": {"coordinates":[-81.315962,28.618394],"type":"Point"}
}