{
  "type": "Feature",
  "properties": {
    "iso:country":"US",
    "sg:address":"7100 W 20th Ave",
    "sg:city":"Hialeah",
    "sg:classifiers":[
        {
            "category":"Health Services",
            "subcategory":"Doctor",
            "type":"Services"
        }
    ],
    "sg:phone":"+1 305 822 3221",
    "sg:postcode":"33016",
    "sg:province":"FL",
    "sg:tags":[
        "medical"
    ],
    "wof:name":"Garcia Onelio Jr MD Facs",
    "wof:placetype":"venue"
},
  "geometry": {"coordinates":[-80.324423,25.886858],"type":"Point"}
}