{
  "type": "Feature",
  "properties": {
    "addr:full":"2820 21st Ave N St Petersburg FL 33713",
    "addr:housenumber":"2820",
    "addr:postcode":"33713",
    "addr:street":"21St Ave N",
    "iso:country":"US",
    "sg:address":"2820 21st Ave N",
    "sg:city":"St Petersburg",
    "sg:classifiers":[
        {
            "category":"Retail",
            "subcategory":"Repair Shop",
            "type":"Services"
        }
    ],
    "sg:phone":"+1 727 323 0921",
    "sg:postcode":"33713",
    "sg:province":"FL",
    "sg:tags":[
        "sharpening"
    ],
    "wof:name":"A Sharpening & Repair",
    "wof:placetype":"venue"
},
  "geometry": {"coordinates":[-82.672991,27.79092],"type":"Point"}
}