{
  "type": "Feature",
  "properties": {
    "addr:full":"1270 W 78th St Hialeah FL 33014",
    "addr:housenumber":"1270",
    "addr:postcode":"33014",
    "addr:street":"W 78Th St",
    "iso:country":"US",
    "sg:address":"1270 W 78th St",
    "sg:city":"Hialeah",
    "sg:classifiers":[
        {
            "category":"Home & Garden",
            "subcategory":"Furniture",
            "type":"Retail Goods"
        }
    ],
    "sg:phone":"+1 305 456 3414",
    "sg:postcode":"33014",
    "sg:province":"FL",
    "wof:name":"Custom Stone Furniture",
    "wof:placetype":"venue"
},
  "geometry": {"coordinates":[-80.30944599999999,25.892948],"type":"Point"}
}