{
  "type": "Feature",
  "properties": {
    "iso:country":"US",
    "sg:address":"1640 NE 32nd Ave",
    "sg:city":"Ocala",
    "sg:classifiers":[
        {
            "category":"Retail",
            "subcategory":"Auto Repair",
            "type":"Services"
        }
    ],
    "sg:phone":"+1 352 369 3555",
    "sg:postcode":"34470",
    "sg:province":"FL",
    "sg:tags":[
        "body",
        "painting",
        "repairing",
        "automobile"
    ],
    "wof:name":"Ryan's Cars & Trucks Of Ocala",
    "wof:placetype":"venue"
},
  "geometry": {"coordinates":[-82.092506,29.203255],"type":"Point"}
}