{
  "type": "Feature",
  "properties": {
    "iso:country":"US",
    "sg:address":"411 N Donnelly St",
    "sg:city":"Mt Dora",
    "sg:classifiers":[
        {
            "category":"Shopping",
            "subcategory":"Gifts & Souvenirs",
            "type":"Retail Goods"
        }
    ],
    "sg:phone":"+1 352 385 7207",
    "sg:postcode":"32757",
    "sg:province":"FL",
    "sg:tags":[
        "shop"
    ],
    "wof:name":"Barbara B's",
    "wof:placetype":"venue"
},
  "geometry": {"coordinates":[-81.644786,28.800437],"type":"Point"}
}