{
  "type": "Feature",
  "properties": {
    "addr:full":"9203 Hosford Hwy Quincy FL 32351",
    "addr:housenumber":"9203",
    "addr:postcode":"32351",
    "addr:street":"Hosford Hwy",
    "iso:country":"US",
    "sg:address":"9203 Hosford Hwy",
    "sg:city":"Quincy",
    "sg:classifiers":[
        {
            "category":"Utilities",
            "subcategory":"Refuse",
            "type":"Services"
        }
    ],
    "sg:phone":"+1 850 627 3359",
    "sg:postcode":"32351",
    "sg:province":"FL",
    "sg:tags":[
        "truck",
        "dump"
    ],
    "wof:name":"Breeden Trucking",
    "wof:placetype":"venue"
},
  "geometry": {"coordinates":[-84.673169,30.572441],"type":"Point"}
}