{
  "type": "Feature",
  "properties": {
    "iso:country":"US",
    "sg:address":"2835 Lake Tohopekaliga Blvd",
    "sg:city":"Kissimmee",
    "sg:classifiers":[
        {
            "category":"Building & Trades",
            "subcategory":"Landscaping Services",
            "type":"Services"
        }
    ],
    "sg:phone":"+1 407 709 6721",
    "sg:postcode":"34746",
    "sg:province":"FL",
    "sg:tags":[
        "lawn",
        "maintenance",
        "grounds"
    ],
    "wof:name":"Jake Miller Lawncare",
    "wof:placetype":"venue"
},
  "geometry": {"coordinates":[-81.42077399999999,28.213564],"type":"Point"}
}