{
  "type": "Feature",
  "properties": {
    "iso:country":"US",
    "sg:address":"661 Maplewood Dr",
    "sg:city":"Jupiter",
    "sg:classifiers":[
        {
            "category":"Banks & Credit Unions",
            "subcategory":"Investment Brokerage",
            "type":"Services"
        },
        {
            "category":"Shopping",
            "subcategory":"Crafts & Fabrics",
            "type":"Retail Goods"
        }
    ],
    "sg:phone":"+1 561 747 0525",
    "sg:postcode":"33458",
    "sg:province":"FL",
    "sg:tags":[
        "shop",
        "material",
        "machines-household",
        "quilting",
        "quilt",
        "supply",
        "instruction",
        "sewing",
        "embroidery"
    ],
    "wof:name":"Quilters' Choice",
    "wof:placetype":"venue"
},
  "geometry": {"coordinates":[-80.123437,26.929438],"type":"Point"}
}