{
  "type": "Feature",
  "properties": {
    "iso:country":"US",
    "sg:address":"601 N Garland Ave",
    "sg:city":"Orlando",
    "sg:classifiers":[
        {
            "category":"Home & Garden",
            "subcategory":"Furniture",
            "type":"Retail Goods"
        }
    ],
    "sg:phone":"+1 407 872 0500",
    "sg:postcode":"32801",
    "sg:province":"FL",
    "wof:name":"Abba Office Furniture",
    "wof:placetype":"venue"
},
  "geometry": {"coordinates":[-81.38191999999999,28.553082],"type":"Point"}
}