{
  "type": "Feature",
  "properties": {
    "addr:full":"2825 Winkler Ave Fort Myers FL 33916",
    "addr:housenumber":"2825",
    "addr:postcode":"33916",
    "addr:street":"Winkler Ave",
    "iso:country":"US",
    "sg:address":"2825 Winkler Ave",
    "sg:city":"Fort Myers",
    "sg:classifiers":[
        {
            "category":"Real Estate",
            "subcategory":"Real Estate Agent",
            "type":"Services"
        }
    ],
    "sg:phone":"+1 239 275 8868",
    "sg:postcode":"33916",
    "sg:province":"FL",
    "sg:tags":[
        "manager"
    ],
    "wof:name":"Riverbend Apartments",
    "wof:placetype":"venue"
},
  "geometry": {"coordinates":[-81.853363,26.604471],"type":"Point"}
}