{
  "type": "Feature",
  "properties": {
    "iso:country":"US",
    "sg:address":"110 Penman Rd",
    "sg:city":"Neptune Beach",
    "sg:classifiers":[
        {
            "category":"Personal",
            "subcategory":"Barber",
            "type":"Services"
        }
    ],
    "sg:phone":"+1 904 249 8660",
    "sg:postcode":"32266",
    "sg:province":"FL",
    "sg:tags":[
        "shop"
    ],
    "wof:name":"Embassy Barber Shop",
    "wof:placetype":"venue"
},
  "geometry": {"coordinates":[-81.40905600000001,30.323712],"type":"Point"}
}