{
  "type": "Feature",
  "properties": {
    "addr:full":"2011 NE 153rd St Miami FL 33162",
    "addr:housenumber":"2011",
    "addr:postcode":"33162",
    "addr:street":"Ne 153Rd St",
    "iso:country":"US",
    "sg:address":"2011 NE 153rd St",
    "sg:city":"Miami",
    "sg:classifiers":[
        {
            "category":"Retail",
            "subcategory":"Animal Services",
            "type":"Services"
        }
    ],
    "sg:phone":"+1 305 945 0609",
    "sg:postcode":"33162",
    "sg:province":"FL",
    "sg:tags":[
        "training",
        "dog"
    ],
    "wof:name":"At Your Command Dog Training",
    "wof:placetype":"venue"
},
  "geometry": {"coordinates":[-80.16066499999999,25.916363],"type":"Point"}
}