{
  "type": "Feature",
  "properties": {
    "iso:country":"US",
    "sg:address":"4400 Hillcrest Dr Apt 903",
    "sg:city":"Hollywood",
    "sg:classifiers":[
        {
            "category":"Banks & Credit Unions",
            "subcategory":"Investment Brokerage",
            "type":"Services"
        },
        {
            "category":"Real Estate",
            "subcategory":"Developer",
            "type":"Services"
        }
    ],
    "sg:phone":"+1 954 985 9852",
    "sg:postcode":"33021",
    "sg:province":"FL",
    "sg:tags":[
        "investing"
    ],
    "wof:name":"Arv Holdings",
    "wof:placetype":"venue"
},
  "geometry": {"coordinates":[-80.1865,25.999798],"type":"Point"}
}