{
  "type": "Feature",
  "properties": {
    "addr:full":"2000 Hollywood Blvd Hollywood FL 33020",
    "addr:housenumber":"2000",
    "addr:postcode":"33020",
    "addr:street":"Hollywood Blvd",
    "iso:country":"US",
    "sg:address":"2000 Hollywood Blvd",
    "sg:city":"Hollywood",
    "sg:classifiers":[
        {
            "category":"Shopping",
            "subcategory":"Jewelry",
            "type":"Retail Goods"
        }
    ],
    "sg:phone":"+1 305 940 0600",
    "sg:postcode":"33020",
    "sg:province":"FL",
    "sg:tags":[
        "used",
        "merchandise"
    ],
    "wof:name":"Morningstar Jewelers",
    "wof:placetype":"venue"
},
  "geometry": {"coordinates":[-80.14882299999999,26.01144],"type":"Point"}
}