{
  "type": "Feature",
  "properties": {
    "iso:country":"US",
    "sg:address":"3849 Klondike Pl",
    "sg:city":"Sanford",
    "sg:phone":"+1 407 420 5828",
    "sg:postcode":"32771",
    "sg:province":"FL",
    "wof:name":"America Waste Management",
    "wof:placetype":"venue"
},
  "geometry": {"coordinates":[-81.21050700000001,28.789373],"type":"Point"}
}