{
  "type": "Feature",
  "properties": {
    "addr:full":"13045 Cooper Rd Spring Hill FL 34609",
    "addr:housenumber":"13045",
    "addr:postcode":"34609",
    "addr:street":"Cooper Rd",
    "iso:country":"US",
    "sg:address":"13045 Cooper Rd",
    "sg:city":"Spring Hill",
    "sg:classifiers":[
        {
            "category":"Professional",
            "subcategory":"Business Services",
            "type":"Services"
        }
    ],
    "sg:phone":"+1 352 683 0727",
    "sg:postcode":"34609",
    "sg:province":"FL",
    "sg:website":"www.northbayhomeinspections.com",
    "wof:name":"North Bay Home Inspections",
    "wof:placetype":"venue"
},
  "geometry": {"coordinates":[-82.50877199999999,28.456353],"type":"Point"}
}