{
  "type": "Feature",
  "properties": {
    "iso:country":"US",
    "sg:address":"714 Saint Johns Ave",
    "sg:city":"Palatka",
    "sg:classifiers":[
        {
            "category":"Manufacturing",
            "subcategory":"Food",
            "type":"Manufacturing & Wholesale Goods"
        }
    ],
    "sg:phone":"+1 386 325 5454",
    "sg:postcode":"32177",
    "sg:province":"FL",
    "sg:tags":[
        "confectionery-wholesale",
        "candy",
        "manufacturer"
    ],
    "wof:name":"Mr Goodbarz",
    "wof:placetype":"venue"
},
  "geometry": {"coordinates":[-81.635757,29.647347],"type":"Point"}
}