{
  "type": "Feature",
  "properties": {
    "iso:country":"US",
    "sg:address":"7461 74th Ct S",
    "sg:city":"Lake Worth",
    "sg:classifiers":[
        {
            "category":"Building & Trades",
            "subcategory":"Landscaping Services",
            "type":"Services"
        }
    ],
    "sg:phone":"+1 561 964 6727",
    "sg:postcode":"33463",
    "sg:province":"FL",
    "wof:name":"Instant Shade Nurs & Ldscp Co",
    "wof:placetype":"venue"
},
  "geometry": {"coordinates":[-80.126097,26.565446],"type":"Point"}
}