{
  "type": "Feature",
  "properties": {
    "iso:country":"US",
    "sg:address":"1600 Lakeland Hills Blvd",
    "sg:city":"Lakeland",
    "sg:classifiers":[
        {
            "category":"Health Services",
            "subcategory":"Doctor",
            "type":"Services"
        }
    ],
    "sg:phone":"+1 863 680 7931",
    "sg:postcode":"33805",
    "sg:province":"FL",
    "sg:tags":[
        "medical"
    ],
    "wof:name":"Helena Narvarte MD",
    "wof:placetype":"venue"
},
  "geometry": {"coordinates":[-81.95329099999999,28.067043],"type":"Point"}
}