{
  "type": "Feature",
  "properties": {
    "iso:country":"US",
    "sg:address":"933 Alfred Dr",
    "sg:city":"Orlando",
    "sg:classifiers":[
        {
            "category":"Building & Trades",
            "subcategory":"Construction",
            "type":"Services"
        }
    ],
    "sg:phone":"+1 407 740 8634",
    "sg:postcode":"32810",
    "sg:province":"FL",
    "sg:tags":[
        "layer",
        "carpet"
    ],
    "wof:name":"Mickey G Cameron Carpet Instll",
    "wof:placetype":"venue"
},
  "geometry": {"coordinates":[-81.395222,28.611151],"type":"Point"}
}