{
  "type": "Feature",
  "properties": {
    "iso:country":"US",
    "sg:address":"8000 W Broward Blvd",
    "sg:city":"Plantation",
    "sg:classifiers":[
        {
            "category":"Shopping",
            "subcategory":"Jewelry",
            "type":"Retail Goods"
        }
    ],
    "sg:phone":"+1 954 916 2345",
    "sg:postcode":"33317",
    "sg:province":"FL",
    "sg:tags":[
        "jeweler"
    ],
    "wof:name":"Bonita's Silver & Crafts",
    "wof:placetype":"venue"
},
  "geometry": {"coordinates":[-80.254075,26.120739],"type":"Point"}
}