{
  "type": "Feature",
  "properties": {
    "iso:country":"US",
    "sg:address":"3201 SE 6th Ave",
    "sg:city":"Fort Lauderdale",
    "sg:classifiers":[
        {
            "category":"Freight",
            "type":"Transportation"
        },
        {
            "category":"Wholesale",
            "subcategory":"Durable Goods & Equipment",
            "type":"Manufacturing & Wholesale Goods"
        }
    ],
    "sg:phone":"+1 954 767 9067",
    "sg:postcode":"33316",
    "sg:province":"FL",
    "sg:tags":[
        "export",
        "exporter",
        "marine"
    ],
    "sg:website":"www.cjexport.com",
    "wof:name":"C J Worldwide Export Inc",
    "wof:placetype":"venue"
},
  "geometry": {"coordinates":[-80.13786,26.084463],"type":"Point"}
}