{
  "type": "Feature",
  "properties": {
    "iso:country":"US",
    "sg:address":"757 Farm Rd",
    "sg:city":"Sebring",
    "sg:classifiers":[
        {
            "category":"Building & Trades",
            "subcategory":"Construction",
            "type":"Services"
        }
    ],
    "sg:phone":"+1 863 655 2025",
    "sg:postcode":"33876",
    "sg:province":"FL",
    "sg:tags":[
        "floor",
        "laying",
        "contractor"
    ],
    "wof:name":"Carls Custom Carpets LLC",
    "wof:placetype":"venue"
},
  "geometry": {"coordinates":[-81.372805,27.42711],"type":"Point"}
}