{
  "type": "Feature",
  "properties": {
    "iso:country":"US",
    "sg:address":"1445 E Venice Ave Ste 204",
    "sg:city":"Venice",
    "sg:phone":"+1 941 488 1988",
    "sg:postcode":"34292",
    "sg:province":"FL",
    "wof:name":"China Wok",
    "wof:placetype":"venue"
},
  "geometry": {"coordinates":[-82.415038,27.099679],"type":"Point"}
}