{
  "type": "Feature",
  "properties": {
    "addr:full":"200 W Welbourne Ave Winter Park FL 32789",
    "addr:housenumber":"200",
    "addr:postcode":"32789",
    "addr:street":"W Welbourne Ave",
    "iso:country":"US",
    "sg:address":"200 W Welbourne Ave",
    "sg:city":"Winter Park",
    "sg:classifiers":[
        {
            "category":"Insurance",
            "subcategory":"Insurance Agent",
            "type":"Services"
        }
    ],
    "sg:phone":"+1 407 740 5337",
    "sg:postcode":"32789",
    "sg:province":"FL",
    "wof:name":"Insurance Cons Centl Fla",
    "wof:placetype":"venue"
},
  "geometry": {"coordinates":[-81.35259499999999,28.59669],"type":"Point"}
}