{
  "type": "Feature",
  "properties": {
    "addr:full":"81954 Overseas Hwy Islamorada FL 33036",
    "addr:housenumber":"81954",
    "addr:postcode":"33036",
    "addr:street":"Overseas Hwy",
    "iso:country":"US",
    "sg:address":"81954 Overseas Hwy",
    "sg:city":"Islamorada",
    "sg:classifiers":[
        {
            "category":"Autos & Motor Vehicles",
            "subcategory":"Boat Sales",
            "type":"Retail Goods"
        }
    ],
    "sg:phone":"+1 305 664 2777",
    "sg:postcode":"33036",
    "sg:province":"FL",
    "sg:tags":[
        "dealer",
        "sales"
    ],
    "wof:name":"Islamorada Boat Center",
    "wof:placetype":"venue"
},
  "geometry": {"coordinates":[-80.630346,24.922387],"type":"Point"}
}