{
  "type": "Feature",
  "properties": {
    "iso:country":"US",
    "sg:address":"707 Main St",
    "sg:city":"Titusville",
    "sg:classifiers":[
        {
            "category":"Building & Trades",
            "subcategory":"Plumbing",
            "type":"Services"
        }
    ],
    "sg:phone":"+1 321 267 6200",
    "sg:postcode":"32796",
    "sg:province":"FL",
    "sg:tags":[
        "conditioning",
        "contractor",
        "refrigeration",
        "system",
        "air"
    ],
    "wof:name":"Allens Cooling & Heating Inc",
    "wof:placetype":"venue"
},
  "geometry": {"coordinates":[-80.814031,28.612507],"type":"Point"}
}