{
  "type": "Feature",
  "properties": {
    "iso:country":"US",
    "sg:address":"504 SE Williston Rd",
    "sg:city":"Gainesville",
    "sg:phone":"+1 352 376 5131",
    "sg:postcode":"32641",
    "sg:province":"FL",
    "sg:tags":[
        "oil",
        "gasoline"
    ],
    "wof:name":"Almond Oil Co",
    "wof:placetype":"venue"
},
  "geometry": {"coordinates":[-82.316104,29.636204],"type":"Point"}
}