{
  "type": "Feature",
  "properties": {
    "iso:country":"US",
    "sg:address":"679 Beville Rd",
    "sg:city":"South Daytona",
    "sg:classifiers":[
        {
            "category":"Professional",
            "subcategory":"Lawyer & Legal Services",
            "type":"Services"
        }
    ],
    "sg:phone":"+1 386 788 8334",
    "sg:postcode":"32119",
    "sg:province":"FL",
    "sg:tags":[
        "attorney"
    ],
    "wof:name":"Hoffman & Hoffmann",
    "wof:placetype":"venue"
},
  "geometry": {"coordinates":[-81.016997,29.179961],"type":"Point"}
}