{
  "type": "Feature",
  "properties": {
    "iso:country":"US",
    "sg:address":"1987 Americana Blvd",
    "sg:city":"Orlando",
    "sg:classifiers":[
        {
            "category":"Home & Garden",
            "subcategory":"Building Materials",
            "type":"Retail Goods"
        }
    ],
    "sg:phone":"+1 321 947 5166",
    "sg:postcode":"32839",
    "sg:province":"FL",
    "sg:tags":[
        "door"
    ],
    "wof:name":"Affordable Garage Door",
    "wof:placetype":"venue"
},
  "geometry": {"coordinates":[-81.405163,28.485226],"type":"Point"}
}