{
  "type": "Feature",
  "properties": {
    "iso:country":"US",
    "sg:address":"1331 SW 8th St",
    "sg:city":"Miami",
    "sg:classifiers":[
        {
            "category":"Arts & Performance",
            "subcategory":"Art Gallery",
            "type":"Entertainment"
        }
    ],
    "sg:phone":"+1 305 856 6789",
    "sg:postcode":"33135",
    "sg:province":"FL",
    "sg:website":"www.reneegallery.info",
    "wof:name":"Renee Gallery",
    "wof:placetype":"venue"
},
  "geometry": {"coordinates":[-80.21676600000001,25.765798],"type":"Point"}
}