{
  "type": "Feature",
  "properties": {
    "addr:full":"12307 NW 9 Ln Newberry FL 32669",
    "addr:housenumber":"12307",
    "addr:postcode":"32669",
    "addr:street":"Nw 9 Ln",
    "iso:country":"US",
    "sg:address":"12307 NW 9 Ln",
    "sg:city":"Newberry",
    "sg:classifiers":[
        {
            "category":"Banks & Credit Unions",
            "subcategory":"Investment Brokerage",
            "type":"Services"
        }
    ],
    "sg:phone":"+1 352 332 7166",
    "sg:postcode":"32669",
    "sg:province":"FL",
    "sg:tags":[
        "advisory"
    ],
    "wof:name":"P & G Financial Services",
    "wof:placetype":"venue"
},
  "geometry": {"coordinates":[-82.47461199999999,29.661505],"type":"Point"}
}