{
  "type": "Feature",
  "properties": {
    "iso:country":"US",
    "sg:address":"818 10th Ave W",
    "sg:city":"Palmetto",
    "sg:classifiers":[
        {
            "category":"Manufacturing",
            "subcategory":"Metals",
            "type":"Manufacturing & Wholesale Goods"
        }
    ],
    "sg:phone":"+1 941 722 4043",
    "sg:postcode":"34221",
    "sg:province":"FL",
    "sg:tags":[
        "product",
        "aluminum",
        "mfg"
    ],
    "wof:name":"B & W Aluminum Products",
    "wof:placetype":"venue"
},
  "geometry": {"coordinates":[-82.575558,27.519678],"type":"Point"}
}