{
  "type": "Feature",
  "properties": {
    "iso:country":"US",
    "sg:address":"1699 SW Dyer Point Rd",
    "sg:city":"Palm City",
    "sg:classifiers":[
        {
            "category":"Restaurant",
            "type":"Food & Drink"
        }
    ],
    "sg:phone":"+1 772 283 8034",
    "sg:postcode":"34990",
    "sg:province":"FL",
    "sg:tags":[
        "eating"
    ],
    "wof:name":"Hungry Bear Adventures Inc",
    "wof:placetype":"venue"
},
  "geometry": {"coordinates":[-80.27684000000001,27.197591],"type":"Point"}
}