{
  "type": "Feature",
  "properties": {
    "addr:full":"12240 Doris Rd Parrish FL 34219",
    "addr:housenumber":"12240",
    "addr:postcode":"34219",
    "addr:street":"Doris Rd",
    "iso:country":"US",
    "sg:address":"12240 Doris Rd",
    "sg:city":"Parrish",
    "sg:classifiers":[
        {
            "category":"Shopping",
            "subcategory":"Hobbies, Toys, & Games",
            "type":"Retail Goods"
        }
    ],
    "sg:phone":"+1 941 776 2769",
    "sg:postcode":"34219",
    "sg:province":"FL",
    "wof:name":"Lady Jane",
    "wof:placetype":"venue"
},
  "geometry": {"coordinates":[-82.421961,27.568917],"type":"Point"}
}