{
  "type": "Feature",
  "properties": {
    "iso:country":"US",
    "sg:address":"1562 SE Floresta Dr",
    "sg:city":"Port Saint Lucie",
    "sg:classifiers":[
        {
            "category":"Restaurant",
            "type":"Food & Drink"
        }
    ],
    "sg:phone":"+1 772 879 7888",
    "sg:postcode":"34983",
    "sg:province":"FL",
    "sg:tags":[
        "eating"
    ],
    "wof:name":"China Express Enterprises",
    "wof:placetype":"venue"
},
  "geometry": {"coordinates":[-80.326902,27.293762],"type":"Point"}
}