{
  "type": "Feature",
  "properties": {
    "addr:full":"1644 Providence Blvd Deltona FL 32725",
    "addr:housenumber":"1644",
    "addr:postcode":"32725",
    "addr:street":"Providence Blvd",
    "iso:country":"US",
    "sg:address":"1644 Providence Blvd",
    "sg:city":"Deltona",
    "sg:classifiers":[
        {
            "category":"Professional",
            "subcategory":"Computer Services",
            "type":"Services"
        }
    ],
    "sg:phone":"+1 386 860 2639",
    "sg:postcode":"32725",
    "sg:province":"FL",
    "sg:tags":[
        "publisher",
        "developer",
        "software"
    ],
    "wof:name":"Netwolves Inc",
    "wof:placetype":"venue"
},
  "geometry": {"coordinates":[-81.227997,28.90313],"type":"Point"}
}