{
  "type": "Feature",
  "properties": {
    "addr:full":"90 NW 23rd Ave Miami FL 33125",
    "addr:housenumber":"90",
    "addr:postcode":"33125",
    "addr:street":"Nw 23Rd Ave",
    "iso:country":"US",
    "sg:address":"90 NW 23rd Ave",
    "sg:city":"Miami",
    "sg:classifiers":[
        {
            "category":"Shopping",
            "subcategory":"Thrift Store",
            "type":"Retail Goods"
        },
        {
            "category":"Banks & Credit Unions",
            "subcategory":"Bank",
            "type":"Services"
        }
    ],
    "sg:phone":"+1 305 573 4200",
    "sg:postcode":"33125",
    "sg:province":"FL",
    "sg:tags":[
        "shop",
        "second",
        "hand"
    ],
    "wof:name":"Salvation Army Thrift Store",
    "wof:placetype":"venue"
},
  "geometry": {"coordinates":[-80.233026,25.773985],"type":"Point"}
}