{
  "type": "Feature",
  "properties": {
    "addr:full":"2845 Pga Blvd Palm Beach Gdns FL 33410",
    "addr:housenumber":"2845",
    "addr:postcode":"33410",
    "addr:street":"Pga Blvd Palm Beach Gdns",
    "iso:country":"US",
    "sg:address":"2845 Pga Blvd",
    "sg:city":"Palm Beach Gdns",
    "sg:classifiers":[
        {
            "category":"Home & Garden",
            "subcategory":"Furniture",
            "type":"Retail Goods"
        }
    ],
    "sg:phone":"+1 561 630 0196",
    "sg:postcode":"33410",
    "sg:province":"FL",
    "wof:name":"LA-Z-Boy Furntiure Galleries",
    "wof:placetype":"venue"
},
  "geometry": {"coordinates":[-80.07572,26.844811],"type":"Point"}
}