{
  "type": "Feature",
  "properties": {
    "iso:country":"US",
    "sg:address":"6460 Topaz Ct",
    "sg:city":"Fort Myers",
    "sg:classifiers":[
        {
            "category":"Building & Trades",
            "subcategory":"Plumbing",
            "type":"Services"
        }
    ],
    "sg:phone":"+1 239 482 1542",
    "sg:postcode":"33966",
    "sg:province":"FL",
    "sg:tags":[
        "conditioning",
        "air",
        "system",
        "contractor"
    ],
    "sg:website":"www.kobiekool.com",
    "wof:name":"Kobie Kooling Inc",
    "wof:placetype":"venue"
},
  "geometry": {"coordinates":[-81.852223,26.569138],"type":"Point"}
}