{
  "type": "Feature",
  "properties": {
    "iso:country":"US",
    "sg:address":"5911 S Dixie Hwy",
    "sg:city":"West Palm Beach",
    "sg:classifiers":[
        {
            "category":"Shopping",
            "subcategory":"Hobbies, Toys, & Games",
            "type":"Retail Goods"
        },
        {
            "category":"Building & Trades",
            "subcategory":"Construction",
            "type":"Services"
        }
    ],
    "sg:phone":"+1 561 585 7744",
    "sg:postcode":"33405",
    "sg:province":"FL",
    "sg:tags":[
        "hanging",
        "contractor",
        "craft",
        "supply"
    ],
    "wof:name":"Craft Gallery The",
    "wof:placetype":"venue"
},
  "geometry": {"coordinates":[-80.055882,26.661082],"type":"Point"}
}