{
  "type": "Feature",
  "properties": {
    "iso:country":"US",
    "sg:address":"3941 W State Rd 46",
    "sg:city":"Sanford",
    "sg:classifiers":[
        {
            "category":"Autos & Motor Vehicles",
            "subcategory":"Automobile Sales",
            "type":"Retail Goods"
        }
    ],
    "sg:phone":"+1 407 936 2277",
    "sg:postcode":"32771",
    "sg:province":"FL",
    "sg:tags":[
        "car",
        "dealer"
    ],
    "wof:name":"Sharp Car Store",
    "wof:placetype":"venue"
},
  "geometry": {"coordinates":[-81.319698,28.811342],"type":"Point"}
}