{
  "type": "Feature",
  "properties": {
    "iso:country":"US",
    "sg:address":"400 Nut Tree Dr",
    "sg:city":"Deland",
    "sg:classifiers":[
        {
            "category":"Building & Trades",
            "subcategory":"Construction",
            "type":"Services"
        }
    ],
    "sg:phone":"+1 386 738 4272",
    "sg:postcode":"32724",
    "sg:province":"FL",
    "sg:tags":[
        "contractor"
    ],
    "wof:name":"The Oaks",
    "wof:placetype":"venue"
},
  "geometry": {"coordinates":[-81.270599,29.024],"type":"Point"}
}