{
  "type": "Feature",
  "properties": {
    "addr:full":"211 5th St S Flagler Beach FL 32136",
    "addr:housenumber":"211",
    "addr:postcode":"32136",
    "addr:street":"5Th St S",
    "iso:country":"US",
    "sg:address":"211 5th St S",
    "sg:city":"Flagler Beach",
    "sg:classifiers":[
        {
            "category":"Building & Trades",
            "subcategory":"Construction",
            "type":"Services"
        }
    ],
    "sg:phone":"+1 386 439 1648",
    "sg:postcode":"32136",
    "sg:province":"FL",
    "sg:tags":[
        "house"
    ],
    "wof:name":"Hensons Painting & Remodeling",
    "wof:placetype":"venue"
},
  "geometry": {"coordinates":[-81.12712000000001,29.478019],"type":"Point"}
}