{
  "type": "Feature",
  "properties": {
    "iso:country":"US",
    "sg:address":"1401 Brickell Ave",
    "sg:city":"Miami",
    "sg:classifiers":[
        {
            "category":"Real Estate",
            "subcategory":"Real Estate Agent",
            "type":"Services"
        }
    ],
    "sg:phone":"+1 305 379 7670",
    "sg:postcode":"33129",
    "sg:province":"FL",
    "wof:name":"Fortune House Intl Realty",
    "wof:placetype":"venue"
},
  "geometry": {"coordinates":[-80.192443,25.759441],"type":"Point"}
}