{
  "type": "Feature",
  "properties": {
    "iso:country":"US",
    "sg:address":"3600 Mystic Pointe Dr",
    "sg:city":"Aventura",
    "sg:classifiers":[
        {
            "category":"Health Services",
            "subcategory":"Optometrist",
            "type":"Services"
        }
    ],
    "sg:phone":"+1 305 466 9165",
    "sg:postcode":"33180",
    "sg:province":"FL",
    "wof:name":"Aventura Eyecare & Assoc",
    "wof:placetype":"venue"
},
  "geometry": {"coordinates":[-80.12935299999999,25.953482],"type":"Point"}
}