{
  "type": "Feature",
  "properties": {
    "addr:full":"1814 14th St W Bradenton FL 34205",
    "addr:housenumber":"1814",
    "addr:postcode":"34205",
    "addr:street":"14Th St W",
    "iso:country":"US",
    "sg:address":"1814 14th St W",
    "sg:city":"Bradenton",
    "sg:classifiers":[
        {
            "category":"Bars & Pubs",
            "type":"Food & Drink"
        }
    ],
    "sg:phone":"+1 941 746 1577",
    "sg:postcode":"34205",
    "sg:province":"FL",
    "sg:tags":[
        "drinking"
    ],
    "wof:name":"Gator Lounge & Package",
    "wof:placetype":"venue"
},
  "geometry": {"coordinates":[-82.575405,27.482601],"type":"Point"}
}