{
  "type": "Feature",
  "properties": {
    "addr:full":"2415 10th Ave N Lake Worth FL 33461",
    "addr:housenumber":"2415",
    "addr:postcode":"33461",
    "addr:street":"10Th Ave N",
    "iso:country":"US",
    "sg:address":"2415 10th Ave N",
    "sg:city":"Lake Worth",
    "sg:classifiers":[
        {
            "category":"Real Estate",
            "subcategory":"Real Estate Agent",
            "type":"Services"
        }
    ],
    "sg:phone":"+1 561 964 2129",
    "sg:postcode":"33461",
    "sg:province":"FL",
    "wof:name":"Mary M Mayhut",
    "wof:placetype":"venue"
},
  "geometry": {"coordinates":[-80.076674,26.628191],"type":"Point"}
}