{
  "type": "Feature",
  "properties": {
    "iso:country":"US",
    "sg:address":"12273 Emerald Coast Pkwy W",
    "sg:city":"Destin",
    "sg:classifiers":[
        {
            "category":"Insurance",
            "subcategory":"Title Insurance",
            "type":"Services"
        }
    ],
    "sg:phone":"+1 850 259 3330",
    "sg:postcode":"32550",
    "sg:province":"FL",
    "wof:name":"Title Works",
    "wof:placetype":"venue"
},
  "geometry": {"coordinates":[-86.376938,30.384951],"type":"Point"}
}