{
  "type": "Feature",
  "properties": {
    "iso:country":"US",
    "sg:address":"1927 S 14th St",
    "sg:city":"Fernandina Beach",
    "sg:classifiers":[
        {
            "category":"Professional",
            "subcategory":"Business Services",
            "type":"Services"
        },
        {
            "category":"Recreation",
            "type":"Entertainment"
        }
    ],
    "sg:phone":"+1 904 277 4787",
    "sg:postcode":"32034",
    "sg:province":"FL",
    "sg:tags":[
        "guide"
    ],
    "wof:name":"Miss Kayla Fishing Charters",
    "wof:placetype":"venue"
},
  "geometry": {"coordinates":[-81.45601499999999,30.639255],"type":"Point"}
}