{
  "type": "Feature",
  "properties": {
    "addr:full":"5915 4th St N St Petersburg FL 33703",
    "addr:housenumber":"5915",
    "addr:postcode":"33703",
    "addr:street":"4Th St N",
    "iso:country":"US",
    "sg:address":"5915 4th St N",
    "sg:city":"St Petersburg",
    "sg:classifiers":[
        {
            "category":"Building & Trades",
            "subcategory":"Construction",
            "type":"Services"
        }
    ],
    "sg:phone":"+1 727 525 7131",
    "sg:postcode":"33703",
    "sg:province":"FL",
    "sg:tags":[
        "pumping",
        "contractor"
    ],
    "wof:name":"Pumping Station",
    "wof:placetype":"venue"
},
  "geometry": {"coordinates":[-82.638595,27.825904],"type":"Point"}
}