{
  "type": "Feature",
  "properties": {
    "iso:country":"US",
    "sg:address":"12703 N Florida Ave",
    "sg:city":"Tampa",
    "sg:classifiers":[
        {
            "category":"Organizations",
            "subcategory":"Religious Organization",
            "type":"Services"
        }
    ],
    "sg:phone":"+1 813 932 8192",
    "sg:postcode":"33612",
    "sg:province":"FL",
    "sg:website":"www.faithluthtampaelca.com",
    "wof:name":"Faith Lutheran Church ELCA",
    "wof:placetype":"venue"
},
  "geometry": {"coordinates":[-82.45926799999999,28.062066],"type":"Point"}
}