{
  "type": "Feature",
  "properties": {
    "addr:full":"701 NW 65th Way Hollywood FL 33024",
    "addr:housenumber":"701",
    "addr:postcode":"33024",
    "addr:street":"Nw 65Th Way",
    "iso:country":"US",
    "sg:address":"701 NW 65th Way",
    "sg:city":"Hollywood",
    "sg:classifiers":[
        {
            "category":"Building & Trades",
            "subcategory":"Construction",
            "type":"Services"
        }
    ],
    "sg:phone":"+1 954 983 6282",
    "sg:postcode":"33024",
    "sg:province":"FL",
    "sg:tags":[
        "system",
        "contractor",
        "air conditioning"
    ],
    "wof:name":"Michael Allgair Airconditioning Inc",
    "wof:placetype":"venue"
},
  "geometry": {"coordinates":[-80.220513,26.015645],"type":"Point"}
}