{
  "type": "Feature",
  "properties": {
    "addr:full":"1961 River Reach Dr Naples FL 34104",
    "addr:housenumber":"1961",
    "addr:postcode":"34104",
    "addr:street":"River Reach Dr",
    "iso:country":"US",
    "sg:address":"1961 River Reach Dr",
    "sg:city":"Naples",
    "sg:classifiers":[
        {
            "category":"Banks & Credit Unions",
            "subcategory":"Investment Brokerage",
            "type":"Services"
        }
    ],
    "sg:phone":"+1 239 434 6262",
    "sg:postcode":"34104",
    "sg:province":"FL",
    "sg:tags":[
        "contracting",
        "trading",
        "general"
    ],
    "wof:name":"Interntonal Un Gen Trade Contg",
    "wof:placetype":"venue"
},
  "geometry": {"coordinates":[-81.780058,26.16262],"type":"Point"}
}