{
  "type": "Feature",
  "properties": {
    "iso:country":"US",
    "sg:address":"37550 Clay Gully Rd",
    "sg:city":"Myakka City",
    "sg:classifiers":[
        {
            "category":"Building & Trades",
            "subcategory":"Construction",
            "type":"Services"
        }
    ],
    "sg:phone":"+1 941 322 1786",
    "sg:postcode":"34251",
    "sg:province":"FL",
    "sg:tags":[
        "carpentry",
        "contractor"
    ],
    "wof:name":"Jason Durrance Framing",
    "wof:placetype":"venue"
},
  "geometry": {"coordinates":[-82.13840999999999,27.273582],"type":"Point"}
}