{
  "type": "Feature",
  "properties": {
    "addr:full":"943 Ridgewood Way Niceville FL 32578",
    "addr:housenumber":"943",
    "addr:postcode":"32578",
    "addr:street":"Ridgewood Way",
    "iso:country":"US",
    "sg:address":"943 Ridgewood Way",
    "sg:city":"Niceville",
    "sg:classifiers":[
        {
            "category":"Building & Trades",
            "subcategory":"Landscaping Services",
            "type":"Services"
        }
    ],
    "sg:phone":"+1 850 897 2778",
    "sg:postcode":"32578",
    "sg:province":"FL",
    "wof:name":"Bayside Lawn Care",
    "wof:placetype":"venue"
},
  "geometry": {"coordinates":[-86.413146,30.47071],"type":"Point"}
}