{
  "type": "Feature",
  "properties": {
    "iso:country":"US",
    "sg:address":"26030 Sitting Bull St",
    "sg:city":"Brooksville",
    "sg:classifiers":[
        {
            "category":"Building & Trades",
            "subcategory":"Landscaping Services",
            "type":"Services"
        }
    ],
    "sg:phone":"+1 352 799 4454",
    "sg:postcode":"34601",
    "sg:province":"FL",
    "wof:name":"Donald L Morris",
    "wof:placetype":"venue"
},
  "geometry": {"coordinates":[-82.310406,28.653855],"type":"Point"}
}