{
  "type": "Feature",
  "properties": {
    "addr:full":"9118 Old Dixie Hwy West Palm Beach FL 33403",
    "addr:housenumber":"9118",
    "addr:postcode":"33403",
    "addr:street":"Old Dixie Hwy",
    "iso:country":"US",
    "sg:address":"9118 Old Dixie Hwy",
    "sg:city":"West Palm Beach",
    "sg:classifiers":[
        {
            "category":"Education",
            "subcategory":"School",
            "type":"Public Place"
        }
    ],
    "sg:phone":"+1 561 848 2841",
    "sg:postcode":"33403",
    "sg:province":"FL",
    "sg:tags":[
        "child",
        "day",
        "care"
    ],
    "wof:name":"Snow White Private School",
    "wof:placetype":"venue"
},
  "geometry": {"coordinates":[-80.079092,26.810308],"type":"Point"}
}