{
  "type": "Feature",
  "properties": {
    "addr:full":"4425 del Prado Blvd S Cape Coral FL 33904",
    "addr:housenumber":"4425",
    "addr:postcode":"33904",
    "addr:street":"Del Prado Blvd S",
    "iso:country":"US",
    "sg:address":"4425 del Prado Blvd S",
    "sg:city":"Cape Coral",
    "sg:classifiers":[
        {
            "category":"Manufacturing",
            "subcategory":"Printing",
            "type":"Manufacturing & Wholesale Goods"
        }
    ],
    "sg:phone":"+1 239 542 1020",
    "sg:postcode":"33904",
    "sg:province":"FL",
    "sg:tags":[
        "lithographic",
        "commercial",
        "photocopying"
    ],
    "wof:name":"University Quickprint",
    "wof:placetype":"venue"
},
  "geometry": {"coordinates":[-81.94372799999999,26.567268],"type":"Point"}
}