{
  "type": "Feature",
  "properties": {
    "iso:country":"US",
    "sg:address":"1830 Les Chateaux Blvd",
    "sg:city":"Naples",
    "sg:classifiers":[
        {
            "category":"Real Estate",
            "subcategory":"Real Estate Agent",
            "type":"Services"
        }
    ],
    "sg:phone":"+1 239 596 5096",
    "sg:postcode":"34109",
    "sg:province":"FL",
    "wof:name":"Lois M Chapman",
    "wof:placetype":"venue"
},
  "geometry": {"coordinates":[-81.781997,26.253647],"type":"Point"}
}