{
  "type": "Feature",
  "properties": {
    "iso:country":"US",
    "sg:address":"20356 NW 2nd Ave",
    "sg:city":"Miami",
    "sg:classifiers":[
        {
            "category":"Restaurant",
            "type":"Food & Drink"
        }
    ],
    "sg:phone":"+1 305 651 4761",
    "sg:postcode":"33169",
    "sg:province":"FL",
    "wof:name":"Chef Creole",
    "wof:placetype":"venue"
},
  "geometry": {"coordinates":[-80.205918,25.962921],"type":"Point"}
}