{
  "type": "Feature",
  "properties": {
    "addr:full":"13783 6th Pl E Bradenton FL 34212",
    "addr:housenumber":"13783",
    "addr:postcode":"34212",
    "addr:street":"6Th Pl E",
    "iso:country":"US",
    "sg:address":"13783 6th Pl E",
    "sg:city":"Bradenton",
    "sg:classifiers":[
        {
            "category":"Transit Center",
            "subcategory":"Freight",
            "type":"Transportation"
        },
        {
            "category":"Freight",
            "type":"Transportation"
        }
    ],
    "sg:phone":"+1 941 741 4039",
    "sg:postcode":"34212",
    "sg:province":"FL",
    "sg:tags":[
        "local",
        "trucking-motor",
        "trucking"
    ],
    "wof:name":"Larry Berg Trucking",
    "wof:placetype":"venue"
},
  "geometry": {"coordinates":[-82.3976,27.489124],"type":"Point"}
}