{
  "type": "Feature",
  "properties": {
    "iso:country":"US",
    "sg:address":"510 NE Park St",
    "sg:city":"Okeechobee",
    "sg:classifiers":[
        {
            "category":"Autos & Motor Vehicles",
            "subcategory":"Fuel & Gas Station",
            "type":"Retail Goods"
        }
    ],
    "sg:phone":"+1 863 763 3993",
    "sg:postcode":"34972",
    "sg:province":"FL",
    "sg:tags":[
        "oil"
    ],
    "wof:name":"Park Street Shell",
    "wof:placetype":"venue"
},
  "geometry": {"coordinates":[-80.82517199999999,27.243659],"type":"Point"}
}