{
  "type": "Feature",
  "properties": {
    "iso:country":"US",
    "sg:address":"6031 Clark Center Ave",
    "sg:city":"Sarasota",
    "sg:classifiers":[
        {
            "category":"Manufacturing",
            "subcategory":"Metals",
            "type":"Manufacturing & Wholesale Goods"
        }
    ],
    "sg:phone":"+1 941 922 1844",
    "sg:postcode":"34238",
    "sg:province":"FL",
    "sg:tags":[
        "metalwork",
        "sheet",
        "mfg"
    ],
    "sg:website":"www.windowcraftsmen.com",
    "wof:name":"Window Craftsmen Inc",
    "wof:placetype":"venue"
},
  "geometry": {"coordinates":[-82.475964,27.265503],"type":"Point"}
}