{
  "type": "Feature",
  "properties": {
    "iso:country":"US",
    "sg:address":"21311 SW 147th Ave",
    "sg:city":"Miami",
    "sg:classifiers":[
        {
            "category":"Home & Garden",
            "subcategory":"Garden Supply",
            "type":"Retail Goods"
        }
    ],
    "sg:phone":"+1 305 256 1685",
    "sg:postcode":"33187",
    "sg:province":"FL",
    "sg:tags":[
        "nurseryman"
    ],
    "wof:name":"Mix'd Greens Wholesale Nursery",
    "wof:placetype":"venue"
},
  "geometry": {"coordinates":[-80.429301,25.56684],"type":"Point"}
}