{
  "type": "Feature",
  "properties": {
    "addr:full":"2311 E Hillsborough Ave Tampa FL 33610",
    "addr:housenumber":"2311",
    "addr:postcode":"33610",
    "addr:street":"E Hillsborough Ave",
    "iso:country":"US",
    "sg:address":"2311 E Hillsborough Ave",
    "sg:city":"Tampa",
    "sg:classifiers":[
        {
            "category":"Professional",
            "type":"Services"
        }
    ],
    "sg:phone":"+1 813 238 6829",
    "sg:postcode":"33610",
    "sg:province":"FL",
    "sg:tags":[
        "establishment"
    ],
    "wof:name":"Hi Style",
    "wof:placetype":"venue"
},
  "geometry": {"coordinates":[-82.43228000000001,27.995991],"type":"Point"}
}