{
  "type": "Feature",
  "properties": {
    "iso:country":"US",
    "sg:address":"7200 NW 19th St Ste 409",
    "sg:city":"Miami",
    "sg:classifiers":[
        {
            "category":"Food & Beverages",
            "subcategory":"Liquor & Beverages",
            "type":"Retail Goods"
        },
        {
            "category":"Wholesale",
            "subcategory":"Wine & Distilled Alcoholic Beverages",
            "type":"Manufacturing & Wholesale Goods"
        }
    ],
    "sg:phone":"+1 941 721 1927",
    "sg:postcode":"33126",
    "sg:province":"FL",
    "sg:tags":[
        "broker"
    ],
    "wof:name":"Cremaschi Wine Imports",
    "wof:placetype":"venue"
},
  "geometry": {"coordinates":[-80.312881,25.79225],"type":"Point"}
}