{
  "type": "Feature",
  "properties": {
    "addr:full":"12302 SW 128th Ct Miami FL 33186",
    "addr:housenumber":"12302",
    "addr:postcode":"33186",
    "addr:street":"Sw 128Th Ct",
    "iso:country":"US",
    "sg:address":"12302 SW 128th Ct",
    "sg:city":"Miami",
    "sg:classifiers":[
        {
            "category":"Building & Trades",
            "subcategory":"Cleaning & Sanitation",
            "type":"Services"
        },
        {
            "category":"Retail",
            "subcategory":"Laundry & Dry Cleaning",
            "type":"Services"
        },
        {
            "category":"Home & Garden",
            "subcategory":"Carpets & Floor Coverings",
            "type":"Retail Goods"
        }
    ],
    "sg:phone":"+1 305 971 2788",
    "sg:postcode":"33186",
    "sg:province":"FL",
    "sg:tags":[
        "cleaner",
        "site-clean-up",
        "fire",
        "cleaners-water",
        "rug",
        "damage",
        "water",
        "extraction",
        "construction",
        "remediation",
        "mold",
        "restoration"
    ],
    "sg:website":"http://www.servicemastercg.com",
    "wof:name":"Servicemaster Of Coral Gables II",
    "wof:placetype":"venue"
},
  "geometry": {"coordinates":[-80.40240799999999,25.653726],"type":"Point"}
}