{
  "type": "Feature",
  "properties": {
    "addr:full":"2020 SW 31st Ave Hallandale FL 33009",
    "addr:housenumber":"2020",
    "addr:postcode":"33009",
    "addr:street":"Sw 31St Ave",
    "iso:country":"US",
    "sg:address":"2020 SW 31st Ave",
    "sg:city":"Hallandale",
    "sg:classifiers":[
        {
            "category":"Wholesale",
            "subcategory":"Groceries",
            "type":"Manufacturing & Wholesale Goods"
        }
    ],
    "sg:phone":"+1 954 966 7502",
    "sg:postcode":"33009",
    "sg:province":"FL",
    "sg:tags":[
        "frozen",
        "mixture",
        "drink"
    ],
    "wof:name":"ICEE Company",
    "wof:placetype":"venue"
},
  "geometry": {"coordinates":[-80.16874900000001,25.993496],"type":"Point"}
}