{
  "type": "Feature",
  "properties": {
    "iso:country":"US",
    "sg:address":"26 E 7th St",
    "sg:city":"Hialeah",
    "sg:classifiers":[
        {
            "category":"Social Services",
            "subcategory":"Child Care",
            "type":"Services"
        }
    ],
    "sg:phone":"+1 305 888 0024",
    "sg:postcode":"33010",
    "sg:province":"FL",
    "wof:name":"Del Travieso Learning Day Care",
    "wof:placetype":"venue"
},
  "geometry": {"coordinates":[-80.279972,25.828066],"type":"Point"}
}