{
  "type": "Feature",
  "properties": {
    "iso:country":"US",
    "sg:address":"6501 Hollywood Blvd",
    "sg:city":"Hollywood",
    "sg:classifiers":[
        {
            "category":"Education",
            "subcategory":"School",
            "type":"Public Place"
        }
    ],
    "sg:phone":"+1 754 323 1200",
    "sg:postcode":"33024",
    "sg:province":"FL",
    "sg:tags":[
        "high"
    ],
    "wof:name":"McArthur High School",
    "wof:placetype":"venue"
},
  "geometry": {"coordinates":[-80.21811,26.009952],"type":"Point"}
}