{
  "type": "Feature",
  "properties": {
    "iso:country":"US",
    "sg:address":"3250 N 29th Ave",
    "sg:city":"Hollywood",
    "sg:classifiers":[
        {
            "category":"Professional",
            "subcategory":"Employment Agencies",
            "type":"Services"
        }
    ],
    "sg:phone":"+1 954 889 0286",
    "sg:postcode":"33020",
    "sg:province":"FL",
    "sg:tags":[
        "supply",
        "leasing",
        "insurance",
        "help"
    ],
    "wof:name":"Concept 2000 Prof Employers",
    "wof:placetype":"venue"
},
  "geometry": {"coordinates":[-80.16581600000001,26.039161],"type":"Point"}
}