{
  "type": "Feature",
  "properties": {
    "addr:full":"1249 Semoran Blvd Casselberry FL 32707",
    "addr:housenumber":"1249",
    "addr:postcode":"32707",
    "addr:street":"Semoran Blvd",
    "iso:country":"US",
    "sg:address":"1249 Semoran Blvd",
    "sg:city":"Casselberry",
    "sg:classifiers":[
        {
            "category":"Banks & Credit Unions",
            "subcategory":"Bank",
            "type":"Services"
        }
    ],
    "sg:phone":"+1 407 677 0916",
    "sg:postcode":"32707",
    "sg:province":"FL",
    "sg:tags":[
        "mortgage"
    ],
    "wof:name":"Upland Mortgage",
    "wof:placetype":"venue"
},
  "geometry": {"coordinates":[-81.32254500000001,28.639536],"type":"Point"}
}