{
  "type": "Feature",
  "properties": {
    "iso:country":"US",
    "sg:address":"1923 Laurel Ln",
    "sg:city":"West Palm Beach",
    "sg:classifiers":[
        {
            "category":"Building & Trades",
            "subcategory":"Cleaning & Sanitation",
            "type":"Services"
        }
    ],
    "sg:phone":"+1 561 642 6900",
    "sg:postcode":"33406",
    "sg:province":"FL",
    "sg:tags":[
        "maintenance"
    ],
    "wof:name":"Roper's Building Maintenance",
    "wof:placetype":"venue"
},
  "geometry": {"coordinates":[-80.076621,26.647928],"type":"Point"}
}