{
  "type": "Feature",
  "properties": {
    "iso:country":"US",
    "sg:address":"210 California Dr NE",
    "sg:city":"Fort Walton Beach",
    "sg:classifiers":[
        {
            "category":"Building & Trades",
            "subcategory":"Landscaping Services",
            "type":"Services"
        }
    ],
    "sg:phone":"+1 850 243 8642",
    "sg:postcode":"32548",
    "sg:province":"FL",
    "wof:name":"Lawn Zone",
    "wof:placetype":"venue"
},
  "geometry": {"coordinates":[-86.601944,30.416294],"type":"Point"}
}