{
  "type": "Feature",
  "properties": {
    "addr:full":"3236 NE 11th Ave Fort Lauderdale FL 33334",
    "addr:housenumber":"3236",
    "addr:postcode":"33334",
    "addr:street":"Ne 11Th Ave",
    "iso:country":"US",
    "sg:address":"3236 NE 11th Ave",
    "sg:city":"Fort Lauderdale",
    "sg:classifiers":[
        {
            "category":"Bars & Pubs",
            "type":"Food & Drink"
        }
    ],
    "sg:phone":"+1 954 568 1502",
    "sg:postcode":"33334",
    "sg:province":"FL",
    "sg:tags":[
        "drinking"
    ],
    "wof:name":"Grannys",
    "wof:placetype":"venue"
},
  "geometry": {"coordinates":[-80.132288,26.168322],"type":"Point"}
}