{
  "type": "Feature",
  "properties": {
    "iso:country":"US",
    "sg:address":"5777 Myerlake Cir",
    "sg:city":"Clearwater",
    "sg:classifiers":[
        {
            "category":"Wholesale",
            "subcategory":"Computers",
            "type":"Manufacturing & Wholesale Goods"
        }
    ],
    "sg:phone":"+1 727 539 7429",
    "sg:postcode":"33760",
    "sg:province":"FL",
    "sg:tags":[
        "warehouse"
    ],
    "wof:name":"Tech Data Corporation",
    "wof:placetype":"venue"
},
  "geometry": {"coordinates":[-82.712346,27.903348],"type":"Point"}
}