{
  "type": "Feature",
  "properties": {
    "iso:country":"US",
    "sg:address":"14275 S Dixie Hwy",
    "sg:city":"Miami",
    "sg:classifiers":[
        {
            "category":"Autos & Motor Vehicles",
            "subcategory":"Motorcycle Sales",
            "type":"Retail Goods"
        },
        {
            "category":"Retail",
            "subcategory":"Auto Repair",
            "type":"Services"
        }
    ],
    "sg:phone":"+1 305 238 0005",
    "sg:postcode":"33176",
    "sg:province":"FL",
    "sg:tags":[
        "scooters-repairing",
        "scooters-parts",
        "motorcycles-customizing",
        "supply"
    ],
    "sg:website":"www.everythingmotorcycle.com",
    "wof:name":"Everything Motorcycles.Com",
    "wof:placetype":"venue"
},
  "geometry": {"coordinates":[-80.336811,25.637452],"type":"Point"}
}