{
  "type": "Feature",
  "properties": {
    "iso:country":"US",
    "sg:address":"6461 Daniels Rd",
    "sg:city":"Naples",
    "sg:classifiers":[
        {
            "category":"Retail",
            "subcategory":"Animal Services",
            "type":"Services"
        }
    ],
    "sg:phone":"+1 239 596 8302",
    "sg:postcode":"34109",
    "sg:province":"FL",
    "wof:name":"Equestrian Ctr At Hrse Creek",
    "wof:placetype":"venue"
},
  "geometry": {"coordinates":[-81.739028,26.232222],"type":"Point"}
}