{
  "type": "Feature",
  "properties": {
    "iso:country":"US",
    "sg:address":"408 Mariner Dr",
    "sg:city":"Jupiter",
    "sg:classifiers":[
        {
            "category":"Personal",
            "type":"Services"
        }
    ],
    "sg:phone":"+1 561 575 4886",
    "sg:postcode":"33477",
    "sg:province":"FL",
    "wof:name":"State Street Houses Inc",
    "wof:placetype":"venue"
},
  "geometry": {"coordinates":[-80.08296199999999,26.897413],"type":"Point"}
}