{
  "type": "Feature",
  "properties": {
    "iso:country":"US",
    "sg:address":"6587 Trammel Dr",
    "sg:city":"Milton",
    "sg:classifiers":[
        {
            "category":"Freight",
            "type":"Transportation"
        }
    ],
    "sg:phone":"+1 850 623 3517",
    "sg:postcode":"32570",
    "sg:province":"FL",
    "sg:tags":[
        "trucking"
    ],
    "wof:name":"Mar Gen Trucking",
    "wof:placetype":"venue"
},
  "geometry": {"coordinates":[-87.048412,30.660363],"type":"Point"}
}