{
  "type": "Feature",
  "properties": {
    "addr:full":"1340 Clayton Dr Deltona FL 32725",
    "addr:housenumber":"1340",
    "addr:postcode":"32725",
    "addr:street":"Clayton Dr",
    "iso:country":"US",
    "sg:address":"1340 Clayton Dr",
    "sg:city":"Deltona",
    "sg:classifiers":[
        {
            "category":"Professional",
            "subcategory":"Business Services",
            "type":"Services"
        }
    ],
    "sg:phone":"+1 407 443 3726",
    "sg:postcode":"32725",
    "sg:province":"FL",
    "wof:name":"Light Stuff",
    "wof:placetype":"venue"
},
  "geometry": {"coordinates":[-81.23709700000001,28.889701],"type":"Point"}
}