{
  "type": "Feature",
  "properties": {
    "iso:country":"US",
    "sg:address":"206 W Dundee St",
    "sg:city":"Perry",
    "sg:classifiers":[
        {
            "category":"Organizations",
            "subcategory":"Religious Organization",
            "type":"Services"
        }
    ],
    "sg:phone":"+1 850 584 2508",
    "sg:postcode":"32348",
    "sg:province":"FL",
    "sg:tags":[
        "church"
    ],
    "wof:name":"Living Word Ministry",
    "wof:placetype":"venue"
},
  "geometry": {"coordinates":[-83.58308599999999,30.110364],"type":"Point"}
}