{
  "type": "Feature",
  "properties": {
    "iso:country":"US",
    "sg:address":"421 SE 1st Ave",
    "sg:city":"Homestead",
    "sg:classifiers":[
        {
            "category":"Restaurant",
            "type":"Food & Drink"
        }
    ],
    "sg:phone":"+1 305 248 8898",
    "sg:postcode":"33034",
    "sg:province":"FL",
    "sg:tags":[
        "submarine",
        "sandwich"
    ],
    "wof:name":"Subway",
    "wof:placetype":"venue"
},
  "geometry": {"coordinates":[-80.47700399999999,25.467404],"type":"Point"}
}