{
  "type": "Feature",
  "properties": {
    "iso:country":"US",
    "sg:address":"711 NW 23rd Ave",
    "sg:city":"Miami",
    "sg:classifiers":[
        {
            "category":"Health Services",
            "subcategory":"Doctor",
            "type":"Services"
        }
    ],
    "sg:phone":"+1 305 541 2888",
    "sg:postcode":"33125",
    "sg:province":"FL",
    "sg:tags":[
        "medical",
        "imaging"
    ],
    "wof:name":"Department-Xray & Ultrasound",
    "wof:placetype":"venue"
},
  "geometry": {"coordinates":[-80.23331,25.781285],"type":"Point"}
}