{
  "type": "Feature",
  "properties": {
    "iso:country":"US",
    "sg:address":"909 W Brandon Blvd",
    "sg:city":"Brandon",
    "sg:classifiers":[
        {
            "category":"Restaurant",
            "type":"Food & Drink"
        }
    ],
    "sg:menulink":"http://www.allmenus.com/fl/brandon/28445-china-palace/menu/",
    "sg:phone":"+1 813 651 5888",
    "sg:postcode":"33511",
    "sg:province":"FL",
    "sg:tags":[
        "asian",
        "chinese"
    ],
    "wof:name":"China Palace",
    "wof:placetype":"venue"
},
  "geometry": {"coordinates":[-82.297346,27.937595],"type":"Point"}
}