{
  "type": "Feature",
  "properties": {
    "addr:full":"11725 Collier Blvd Naples FL 34116",
    "addr:housenumber":"11725",
    "addr:postcode":"34116",
    "addr:street":"Collier Blvd",
    "iso:country":"US",
    "sg:address":"11725 Collier Blvd",
    "sg:city":"Naples",
    "sg:classifiers":[
        {
            "category":"Building & Trades",
            "subcategory":"Construction",
            "type":"Services"
        }
    ],
    "sg:phone":"+1 239 304 1526",
    "sg:postcode":"34116",
    "sg:province":"FL",
    "sg:tags":[
        "general",
        "contractor"
    ],
    "wof:name":"Gustafson Construction Corp",
    "wof:placetype":"venue"
},
  "geometry": {"coordinates":[-81.68706899999999,26.184471],"type":"Point"}
}