{
  "type": "Feature",
  "properties": {
    "iso:country":"US",
    "sg:address":"4830 N Federal Hwy",
    "sg:city":"Fort Lauderdale",
    "sg:classifiers":[
        {
            "category":"Shopping",
            "subcategory":"Optical Goods",
            "type":"Retail Goods"
        }
    ],
    "sg:phone":"+1 954 491 0530",
    "sg:postcode":"33308",
    "sg:province":"FL",
    "wof:name":"Med Optical",
    "wof:placetype":"venue"
},
  "geometry": {"coordinates":[-80.115892,26.187893],"type":"Point"}
}