{
  "type": "Feature",
  "properties": {
    "addr:full":"3071 US Hwy 98 Lakeland FL 33805",
    "addr:housenumber":"3071",
    "addr:postcode":"33805",
    "addr:street":"Us Hwy 98",
    "iso:country":"US",
    "sg:address":"3071 US Hwy 98",
    "sg:city":"Lakeland",
    "sg:classifiers":[
        {
            "category":"Mining & Drilling",
            "type":"Manufacturing & Wholesale Goods"
        }
    ],
    "sg:phone":"+1 863 557 2922",
    "sg:postcode":"33805",
    "sg:province":"FL",
    "sg:tags":[
        "natural",
        "production",
        "gas",
        "liquid"
    ],
    "wof:name":"Rams Patco Inc",
    "wof:placetype":"venue"
},
  "geometry": {"coordinates":[-81.967265,28.082223],"type":"Point"}
}