{
  "type": "Feature",
  "properties": {
    "iso:country":"US",
    "sg:address":"443 E College Ave",
    "sg:city":"Tallahassee",
    "sg:classifiers":[
        {
            "category":"Professional",
            "subcategory":"Accounting & Tax Preparation",
            "type":"Services"
        }
    ],
    "sg:phone":"+1 850 224 7144",
    "sg:postcode":"32301",
    "sg:province":"FL",
    "sg:tags":[
        "accountant"
    ],
    "wof:name":"Purvis Gray & Co",
    "wof:placetype":"venue"
},
  "geometry": {"coordinates":[-84.278102,30.440663],"type":"Point"}
}