{
  "type": "Feature",
  "properties": {
    "iso:country":"US",
    "sg:address":"4830 NW 43 St",
    "sg:city":"Gainesville",
    "sg:classifiers":[
        {
            "category":"Real Estate",
            "subcategory":"Real Estate Operator",
            "type":"Services"
        }
    ],
    "sg:phone":"+1 352 378 4800",
    "sg:postcode":"32606",
    "sg:province":"FL",
    "sg:tags":[
        "building",
        "apartment"
    ],
    "sg:website":"www.hunterscrossing.com",
    "wof:name":"Hunters Crossing",
    "wof:placetype":"venue"
},
  "geometry": {"coordinates":[-82.388982,29.697411],"type":"Point"}
}