{
  "type": "Feature",
  "properties": {
    "addr:full":"7935 Pine Forest Rd Pensacola FL 32526",
    "addr:housenumber":"7935",
    "addr:postcode":"32526",
    "addr:street":"Pine Forest Rd",
    "iso:country":"US",
    "sg:address":"7935 Pine Forest Rd",
    "sg:city":"Pensacola",
    "sg:classifiers":[
        {
            "category":"Food & Beverages",
            "subcategory":"Groceries & Convenience Stores",
            "type":"Retail Goods"
        }
    ],
    "sg:phone":"+1 850 944 0345",
    "sg:postcode":"32526",
    "sg:province":"FL",
    "wof:name":"Tom Thumb 19",
    "wof:placetype":"venue"
},
  "geometry": {"coordinates":[-87.31300400000001,30.518324],"type":"Point"}
}