{
  "type": "Feature",
  "properties": {
    "addr:full":"700 W Oak St Kissimmee FL 34741",
    "addr:housenumber":"700",
    "addr:postcode":"34741",
    "addr:street":"W Oak St",
    "iso:country":"US",
    "sg:address":"700 W Oak St",
    "sg:city":"Kissimmee",
    "sg:classifiers":[
        {
            "category":"Banks & Credit Unions",
            "subcategory":"Bank",
            "type":"Services"
        },
        {
            "category":"Banks & Credit Unions",
            "subcategory":"Financial Services",
            "type":"Services"
        }
    ],
    "sg:phone":"+1 407 943 7296",
    "sg:postcode":"34741",
    "sg:province":"FL",
    "sg:tags":[
        "commercial",
        "loan",
        "saving",
        "mortgage"
    ],
    "sg:website":"https://www.wachovia.com/?DCMP=KNL-CPS-DS-Directory-0703&HBX_PK=Banks&HBX_OU=71",
    "wof:name":"Wachovia Bank",
    "wof:placetype":"venue"
},
  "geometry": {"coordinates":[-81.410906,28.300885],"type":"Point"}
}