{
  "type": "Feature",
  "properties": {
    "iso:country":"US",
    "sg:address":"1801 NW 5 Ave",
    "sg:city":"Gainesville",
    "sg:classifiers":[
        {
            "category":"Organizations",
            "subcategory":"Religious Organization",
            "type":"Services"
        }
    ],
    "sg:phone":"+1 352 376 2062",
    "sg:postcode":"32603",
    "sg:province":"FL",
    "sg:website":"www.flcgainesville.org",
    "wof:name":"First Lutheran Church",
    "wof:placetype":"venue"
},
  "geometry": {"coordinates":[-82.34551500000001,29.655758],"type":"Point"}
}