{
  "type": "Feature",
  "properties": {
    "addr:full":"4201 Belfort Rd Jacksonville FL 32216",
    "addr:housenumber":"4201",
    "addr:postcode":"32216",
    "addr:street":"Belfort Rd",
    "iso:country":"US",
    "sg:address":"4201 Belfort Rd",
    "sg:city":"Jacksonville",
    "sg:classifiers":[
        {
            "category":"Professional",
            "subcategory":"Detective & Security Services",
            "type":"Services"
        }
    ],
    "sg:phone":"+1 904 296 3773",
    "sg:postcode":"32216",
    "sg:province":"FL",
    "sg:tags":[
        "car"
    ],
    "wof:name":"Stlukes Security",
    "wof:placetype":"venue"
},
  "geometry": {"coordinates":[-81.584181,30.252596],"type":"Point"}
}