{
  "type": "Feature",
  "properties": {
    "addr:full":"25020 Harborside Blvd Punta Gorda FL 33955",
    "addr:postcode":"25020;33955",
    "addr:street":"Harborside Blvd",
    "iso:country":"US",
    "sg:address":"25020 Harborside Blvd",
    "sg:city":"Punta Gorda",
    "sg:classifiers":[
        {
            "category":"Real Estate",
            "subcategory":"Real Estate Agent",
            "type":"Services"
        }
    ],
    "sg:phone":"+1 941 505 9779",
    "sg:postcode":"33955",
    "sg:province":"FL",
    "wof:name":"Century 21 Sunbelt Realty Inc",
    "wof:placetype":"venue"
},
  "geometry": {"coordinates":[-82.036157,26.786728],"type":"Point"}
}