{
  "type": "Feature",
  "properties": {
    "addr:full":"7710 Lady Frances Way Orlando FL 32807",
    "addr:housenumber":"7710",
    "addr:postcode":"32807",
    "addr:street":"Lady Frances Way",
    "iso:country":"US",
    "sg:address":"7710 Lady Frances Way",
    "sg:city":"Orlando",
    "sg:classifiers":[
        {
            "category":"Building & Trades",
            "subcategory":"Construction",
            "type":"Services"
        }
    ],
    "sg:phone":"+1 407 719 8459",
    "sg:postcode":"32807",
    "sg:province":"FL",
    "sg:tags":[
        "finishing",
        "wood"
    ],
    "wof:name":"Wise, Jeramie",
    "wof:placetype":"venue"
},
  "geometry": {"coordinates":[-81.283719,28.574994],"type":"Point"}
}