{
  "type": "Feature",
  "properties": {
    "iso:country":"US",
    "sg:address":"2217 NE 36th Pl",
    "sg:city":"Ocala",
    "sg:classifiers":[
        {
            "category":"Real Estate",
            "subcategory":"Real Estate Services",
            "type":"Services"
        },
        {
            "category":"Building & Trades",
            "subcategory":"Cleaning & Sanitation",
            "type":"Services"
        }
    ],
    "sg:phone":"+1 352 620 0887",
    "sg:postcode":"34479",
    "sg:province":"FL",
    "sg:tags":[
        "maintenance",
        "cleaners-interior"
    ],
    "wof:name":"I Do Windows By Bridgette",
    "wof:placetype":"venue"
},
  "geometry": {"coordinates":[-82.107052,29.22464],"type":"Point"}
}