{
  "type": "Feature",
  "properties": {
    "iso:country":"US",
    "sg:address":"3762 S Hopkins Ave",
    "sg:city":"Titusville",
    "sg:classifiers":[
        {
            "category":"Retail",
            "subcategory":"Auto Repair",
            "type":"Services"
        }
    ],
    "sg:phone":"+1 321 267 5102",
    "sg:postcode":"32780",
    "sg:province":"FL",
    "sg:tags":[
        "repairing",
        "automobile"
    ],
    "wof:name":"KBK Automotive",
    "wof:placetype":"venue"
},
  "geometry": {"coordinates":[-80.803279,28.569701],"type":"Point"}
}