{
  "type": "Feature",
  "properties": {
    "addr:full":"2631 S Sanford Ave Sanford FL 32773",
    "addr:housenumber":"2631",
    "addr:postcode":"32773",
    "addr:street":"S Sanford Ave",
    "iso:country":"US",
    "sg:address":"2631 S Sanford Ave",
    "sg:city":"Sanford",
    "sg:classifiers":[
        {
            "category":"Food & Beverages",
            "subcategory":"Groceries & Convenience Stores",
            "type":"Retail Goods"
        }
    ],
    "sg:phone":"+1 407 323 7810",
    "sg:postcode":"32773",
    "sg:province":"FL",
    "sg:tags":[
        "gasoline"
    ],
    "wof:name":"Circle K Store",
    "wof:placetype":"venue"
},
  "geometry": {"coordinates":[-81.264678,28.779812],"type":"Point"}
}