{
  "type": "Feature",
  "properties": {
    "iso:country":"US",
    "sg:address":"1249 Pilgram Pl",
    "sg:city":"Daytona Beach",
    "sg:classifiers":[
        {
            "category":"Building & Trades",
            "subcategory":"Construction",
            "type":"Services"
        }
    ],
    "sg:phone":"+1 386 767 9308",
    "sg:postcode":"32119",
    "sg:province":"FL",
    "sg:tags":[
        "house",
        "nonresidential"
    ],
    "wof:name":"Gohr & Company Inc",
    "wof:placetype":"venue"
},
  "geometry": {"coordinates":[-81.03209099999999,29.163861],"type":"Point"}
}