{
  "type": "Feature",
  "properties": {
    "addr:full":"2616 6th St W Lehigh Acres FL 33971",
    "addr:housenumber":"2616",
    "addr:postcode":"33971",
    "addr:street":"6Th St W",
    "iso:country":"US",
    "sg:address":"2616 6th St W",
    "sg:city":"Lehigh Acres",
    "sg:classifiers":[
        {
            "category":"Professional",
            "subcategory":"Accounting & Tax Preparation",
            "type":"Services"
        }
    ],
    "sg:phone":"+1 239 498 1525",
    "sg:postcode":"33971",
    "sg:province":"FL",
    "sg:tags":[
        "bookkeeping",
        "general"
    ],
    "wof:name":"Terry Lissack",
    "wof:placetype":"venue"
},
  "geometry": {"coordinates":[-81.665381,26.619202],"type":"Point"}
}