{
  "type": "Feature",
  "properties": {
    "addr:full":"11150 SE Federal Hwy Hobe Sound FL 33455",
    "addr:postcode":"11150;33455",
    "addr:street":"Se Federal Hwy",
    "iso:country":"US",
    "sg:address":"11150 SE Federal Hwy",
    "sg:city":"Hobe Sound",
    "sg:classifiers":[
        {
            "category":"Restaurant",
            "type":"Food & Drink"
        }
    ],
    "sg:phone":"+1 772 546 6860",
    "sg:postcode":"33455",
    "sg:province":"FL",
    "wof:name":"C W's BBQ",
    "wof:placetype":"venue"
},
  "geometry": {"coordinates":[-80.141441,27.070309],"type":"Point"}
}