{
  "type": "Feature",
  "properties": {
    "iso:country":"US",
    "sg:address":"11591 NW 2nd St",
    "sg:city":"Miami",
    "sg:classifiers":[
        {
            "category":"Real Estate",
            "subcategory":"Real Estate Operator",
            "type":"Services"
        }
    ],
    "sg:phone":"+1 305 551 2637",
    "sg:postcode":"33172",
    "sg:province":"FL",
    "sg:tags":[
        "apartment"
    ],
    "wof:name":"Orsa Gardens Apartments",
    "wof:placetype":"venue"
},
  "geometry": {"coordinates":[-80.383043,25.770283],"type":"Point"}
}