{
  "type": "Feature",
  "properties": {
    "iso:country":"US",
    "sg:address":"3634 Curry Ford Rd",
    "sg:city":"Orlando",
    "sg:classifiers":[
        {
            "category":"Restaurant",
            "type":"Food & Drink"
        }
    ],
    "sg:menulink":"http://www.allmenus.com/fl/orlando/156376-krystal-burgers/menu/",
    "sg:phone":"+1 407 898 8141",
    "sg:postcode":"32806",
    "sg:province":"FL",
    "sg:tags":[
        "burger",
        "chicken",
        "american"
    ],
    "wof:name":"Krystal Burgers",
    "wof:placetype":"venue"
},
  "geometry": {"coordinates":[-81.3385,28.52386],"type":"Point"}
}