{
  "type": "Feature",
  "properties": {
    "iso:country":"US",
    "sg:address":"3762 Maddie Ln",
    "sg:city":"Jacksonville",
    "sg:classifiers":[
        {
            "category":"Organizations",
            "subcategory":"Religious Organization",
            "type":"Services"
        }
    ],
    "sg:phone":"+1 904 781 3464",
    "sg:postcode":"32210",
    "sg:province":"FL",
    "wof:name":"Life Enrichment Christian",
    "wof:placetype":"venue"
},
  "geometry": {"coordinates":[-81.79616,30.266252],"type":"Point"}
}