{
  "type": "Feature",
  "properties": {
    "addr:full":"9180 9th Ave Jacksonville FL 32208",
    "addr:housenumber":"9180",
    "addr:postcode":"32208",
    "addr:street":"9Th Ave",
    "iso:country":"US",
    "sg:address":"9180 9th Ave",
    "sg:city":"Jacksonville",
    "sg:classifiers":[
        {
            "category":"Building & Trades",
            "subcategory":"Construction",
            "type":"Services"
        }
    ],
    "sg:phone":"+1 904 379 6587",
    "sg:postcode":"32208",
    "sg:province":"FL",
    "sg:tags":[
        "contractor"
    ],
    "wof:name":"Larry Michael Mc Nair Contr",
    "wof:placetype":"venue"
},
  "geometry": {"coordinates":[-81.69319400000001,30.40387],"type":"Point"}
}