{
  "type": "Feature",
  "properties": {
    "iso:country":"US",
    "sg:address":"1725 Memorial Park Dr",
    "sg:city":"Jacksonville",
    "sg:classifiers":[
        {
            "category":"Banks & Credit Unions",
            "subcategory":"Financial Services",
            "type":"Services"
        }
    ],
    "sg:phone":"+1 904 358 7932",
    "sg:postcode":"32204",
    "sg:province":"FL",
    "sg:tags":[
        "investment",
        "closed"
    ],
    "wof:name":"Dmh Enterprises",
    "wof:placetype":"venue"
},
  "geometry": {"coordinates":[-81.67884100000001,30.311528],"type":"Point"}
}