{
  "type": "Feature",
  "properties": {
    "iso:country":"US",
    "sg:address":"516 S Dixie Hwy",
    "sg:city":"West Palm Beach",
    "sg:classifiers":[
        {
            "category":"Health Services",
            "subcategory":"Chiropractor",
            "type":"Services"
        }
    ],
    "sg:phone":"+1 561 659 6636",
    "sg:postcode":"33401",
    "sg:province":"FL",
    "sg:tags":[
        "clinic"
    ],
    "wof:name":"Power Chiropractic Inc",
    "wof:placetype":"venue"
},
  "geometry": {"coordinates":[-80.05358099999999,26.708671],"type":"Point"}
}