{
  "type": "Feature",
  "properties": {
    "iso:country":"US",
    "sg:address":"2529 Kingsland Ave",
    "sg:city":"Orlando",
    "sg:classifiers":[
        {
            "category":"Professional",
            "subcategory":"Accounting & Tax Preparation",
            "type":"Services"
        }
    ],
    "sg:phone":"+1 407 299 9445",
    "sg:postcode":"32808",
    "sg:province":"FL",
    "sg:tags":[
        "bookkeeping"
    ],
    "wof:name":"Al Eayrs and Associates Inc",
    "wof:placetype":"venue"
},
  "geometry": {"coordinates":[-81.447743,28.57749],"type":"Point"}
}