{
  "type": "Feature",
  "properties": {
    "addr:full":"12909 NW 43rd Ln Ocala FL 34482",
    "addr:housenumber":"12909",
    "addr:postcode":"34482",
    "addr:street":"Nw 43Rd Ln",
    "iso:country":"US",
    "sg:address":"12909 NW 43rd Ln",
    "sg:city":"Ocala",
    "sg:classifiers":[
        {
            "category":"Insurance",
            "subcategory":"Insurance Agent",
            "type":"Services"
        }
    ],
    "sg:phone":"+1 352 867 5093",
    "sg:postcode":"34482",
    "sg:province":"FL",
    "wof:name":"R T S Services Inc",
    "wof:placetype":"venue"
},
  "geometry": {"coordinates":[-82.334497,29.233148],"type":"Point"}
}