{
  "type": "Feature",
  "properties": {
    "addr:full":"4013 Gallagher Rd Dover FL 33527",
    "addr:housenumber":"4013",
    "addr:postcode":"33527",
    "addr:street":"Gallagher Rd",
    "iso:country":"US",
    "sg:address":"4013 Gallagher Rd",
    "sg:city":"Dover",
    "sg:classifiers":[
        {
            "category":"Farming",
            "subcategory":"Berry Farm",
            "type":"Manufacturing & Wholesale Goods"
        }
    ],
    "sg:phone":"+1 813 659 0870",
    "sg:postcode":"33527",
    "sg:province":"FL",
    "sg:tags":[
        "crop"
    ],
    "wof:name":"McClelland Reese Farms",
    "wof:placetype":"venue"
},
  "geometry": {"coordinates":[-82.236323,28.009293],"type":"Point"}
}