{
  "type": "Feature",
  "properties": {
    "addr:full":"410 Leonard Blvd N Lehigh Acres FL 33971",
    "addr:housenumber":"410",
    "addr:postcode":"33971",
    "addr:street":"Leonard Blvd N",
    "iso:country":"US",
    "sg:address":"410 Leonard Blvd N",
    "sg:city":"Lehigh Acres",
    "sg:classifiers":[
        {
            "category":"Building & Trades",
            "subcategory":"Construction",
            "type":"Services"
        }
    ],
    "sg:phone":"+1 239 303 9055",
    "sg:postcode":"33971",
    "sg:province":"FL",
    "sg:tags":[
        "repairing",
        "remodeling",
        "contractor"
    ],
    "wof:name":"Pyramid Remodeling & Constr",
    "wof:placetype":"venue"
},
  "geometry": {"coordinates":[-81.74911,26.615682],"type":"Point"}
}