{
  "type": "Feature",
  "properties": {
    "iso:country":"US",
    "sg:address":"1360 Poppy Ave",
    "sg:city":"Pensacola",
    "sg:classifiers":[
        {
            "category":"Shopping",
            "subcategory":"Computers & Home Electronics",
            "type":"Retail Goods"
        }
    ],
    "sg:phone":"+1 850 516 5336",
    "sg:postcode":"32507",
    "sg:province":"FL",
    "sg:tags":[
        "theater",
        "consumer",
        "system"
    ],
    "wof:name":"Brothers In Christ, Ent.",
    "wof:placetype":"venue"
},
  "geometry": {"coordinates":[-87.26896499999999,30.392173],"type":"Point"}
}