{
  "type": "Feature",
  "properties": {
    "addr:full":"4567 S Congress Ave Lake Worth FL 33461",
    "addr:housenumber":"4567",
    "addr:postcode":"33461",
    "addr:street":"S Congress Ave",
    "iso:country":"US",
    "sg:address":"4567 S Congress Ave",
    "sg:city":"Lake Worth",
    "sg:classifiers":[
        {
            "category":"Autos & Motor Vehicles",
            "subcategory":"Fuel & Gas Station",
            "type":"Retail Goods"
        }
    ],
    "sg:phone":"+1 561 968 1720",
    "sg:postcode":"33461",
    "sg:province":"FL",
    "sg:tags":[
        "grocery",
        "station",
        "gasoline"
    ],
    "wof:name":"Amoco",
    "wof:placetype":"venue"
},
  "geometry": {"coordinates":[-80.089431,26.610038],"type":"Point"}
}