{
  "type": "Feature",
  "properties": {
    "iso:country":"US",
    "sg:address":"4017 Amberjack Dr",
    "sg:city":"Spring Hill",
    "sg:classifiers":[
        {
            "category":"Manufacturing",
            "subcategory":"Printing",
            "type":"Manufacturing & Wholesale Goods"
        }
    ],
    "sg:phone":"+1 352 684 9904",
    "sg:postcode":"34607",
    "sg:province":"FL",
    "sg:tags":[
        "commercial"
    ],
    "wof:name":"Dis Unique Designs",
    "wof:placetype":"venue"
},
  "geometry": {"coordinates":[-82.655112,28.476901],"type":"Point"}
}