{
  "type": "Feature",
  "properties": {
    "iso:country":"US",
    "sg:address":"7378 W Atlantic Blvd",
    "sg:city":"Margate",
    "sg:classifiers":[
        {
            "category":"Shopping",
            "subcategory":"Books",
            "type":"Retail Goods"
        },
        {
            "category":"Wholesale",
            "subcategory":"Books, Periodicals, & Newspapers",
            "type":"Manufacturing & Wholesale Goods"
        }
    ],
    "sg:phone":"+1 954 968 1192",
    "sg:postcode":"33063",
    "sg:province":"FL",
    "sg:tags":[
        "books-wholesale",
        "store",
        "manufacturer"
    ],
    "wof:name":"Finding Forresters Books",
    "wof:placetype":"venue"
},
  "geometry": {"coordinates":[-80.224948,26.235339],"type":"Point"}
}