{
  "type": "Feature",
  "properties": {
    "iso:country":"US",
    "sg:address":"16038 US Hwy 441",
    "sg:city":"Eustis",
    "sg:classifiers":[
        {
            "category":"Restaurant",
            "type":"Food & Drink"
        }
    ],
    "sg:phone":"+1 352 357 5464",
    "sg:postcode":"32726",
    "sg:province":"FL",
    "wof:name":"Burger King",
    "wof:placetype":"venue"
},
  "geometry": {"coordinates":[-81.69081300000001,28.823066],"type":"Point"}
}