{
  "type": "Feature",
  "properties": {
    "addr:full":"404 Mountain Dr Destin FL 32541",
    "addr:housenumber":"404",
    "addr:postcode":"32541",
    "addr:street":"Mountain Dr",
    "iso:country":"US",
    "sg:address":"404 Mountain Dr",
    "sg:city":"Destin",
    "sg:classifiers":[
        {
            "category":"Manufacturing",
            "subcategory":"Printing",
            "type":"Manufacturing & Wholesale Goods"
        }
    ],
    "sg:phone":"+1 850 837 3190",
    "sg:postcode":"32541",
    "sg:province":"FL",
    "sg:tags":[
        "printer"
    ],
    "sg:website":"www.sos-products.com",
    "wof:name":"SOS Printing & Graphics",
    "wof:placetype":"venue"
},
  "geometry": {"coordinates":[-86.50018,30.394548],"type":"Point"}
}