{
  "type": "Feature",
  "properties": {
    "addr:full":"4870 NW 183rd St Opa Locka FL 33055",
    "addr:housenumber":"4870",
    "addr:postcode":"33055",
    "addr:street":"Nw 183Rd St;Locka",
    "iso:country":"US",
    "sg:address":"4870 NW 183rd St",
    "sg:city":"Opa Locka",
    "sg:classifiers":[
        {
            "category":"Restaurant",
            "type":"Food & Drink"
        }
    ],
    "sg:menulink":"http://www.allmenus.com/fl/northwest-dade/200807-long-john-silvers/menu/",
    "sg:phone":"+1 305 430 7125",
    "sg:postcode":"33055",
    "sg:province":"FL",
    "sg:tags":[
        "seafood",
        "american"
    ],
    "wof:name":"Long John Silver's",
    "wof:placetype":"venue"
},
  "geometry": {"coordinates":[-80.280951,25.93953],"type":"Point"}
}