{
  "type": "Feature",
  "properties": {
    "addr:full":"648 Barnes Blvd Rockledge FL 32955",
    "addr:housenumber":"648",
    "addr:postcode":"32955",
    "addr:street":"Barnes Blvd",
    "iso:country":"US",
    "sg:address":"648 Barnes Blvd",
    "sg:city":"Rockledge",
    "sg:classifiers":[
        {
            "category":"Restaurant",
            "type":"Food & Drink"
        }
    ],
    "sg:menulink":"http://www.allmenus.com/fl/cocoa-rockledge/169176-wendys/menu/",
    "sg:phone":"+1 321 633 5667",
    "sg:postcode":"32955",
    "sg:province":"FL",
    "sg:tags":[
        "burger",
        "american",
        "soup"
    ],
    "wof:name":"Wendy's",
    "wof:placetype":"venue"
},
  "geometry": {"coordinates":[-80.726865,28.295304],"type":"Point"}
}