{
  "type": "Feature",
  "properties": {
    "addr:full":"8690 Scenic Hills Dr Pensacola FL 32514",
    "addr:housenumber":"8690",
    "addr:postcode":"32514",
    "addr:street":"Scenic Hills Dr",
    "iso:country":"US",
    "sg:address":"8690 Scenic Hills Dr",
    "sg:city":"Pensacola",
    "sg:classifiers":[
        {
            "category":"Shopping",
            "subcategory":"Gifts & Souvenirs",
            "type":"Retail Goods"
        }
    ],
    "sg:phone":"+1 850 474 1877",
    "sg:postcode":"32514",
    "sg:province":"FL",
    "wof:name":"Heart To Heart Matters",
    "wof:placetype":"venue"
},
  "geometry": {"coordinates":[-87.232676,30.539678],"type":"Point"}
}