{
  "type": "Feature",
  "properties": {
    "addr:full":"3100 N University Dr Sunrise FL 33351",
    "addr:housenumber":"3100",
    "addr:postcode":"33351",
    "addr:street":"N University Dr",
    "iso:country":"US",
    "sg:address":"3100 N University Dr",
    "sg:city":"Sunrise",
    "sg:classifiers":[
        {
            "category":"Autos & Motor Vehicles",
            "subcategory":"Automobile Sales",
            "type":"Retail Goods"
        }
    ],
    "sg:phone":"+1 954 572 4600",
    "sg:postcode":"33351",
    "sg:province":"FL",
    "sg:tags":[
        "used",
        "leasing",
        "car",
        "dealers-used",
        "truck",
        "new",
        "cars-wholesale"
    ],
    "sg:website":"http://www.saturnofwestbroward.com",
    "wof:name":"Saturn Of West Broward",
    "wof:placetype":"venue"
},
  "geometry": {"coordinates":[-80.256699,26.164351],"type":"Point"}
}