{
  "type": "Feature",
  "properties": {
    "addr:full":"8201 NW 47th St Fort Lauderdale FL 33351",
    "addr:housenumber":"8201",
    "addr:postcode":"33351",
    "addr:street":"Nw 47Th St",
    "iso:country":"US",
    "sg:address":"8201 NW 47th St",
    "sg:city":"Fort Lauderdale",
    "sg:classifiers":[
        {
            "category":"Restaurant",
            "type":"Food & Drink"
        }
    ],
    "sg:phone":"+1 954 748 7707",
    "sg:postcode":"33351",
    "sg:province":"FL",
    "sg:tags":[
        "eating"
    ],
    "wof:name":"Dominos Pizza",
    "wof:placetype":"venue"
},
  "geometry": {"coordinates":[-80.26306099999999,26.183107],"type":"Point"}
}