{
  "type": "Feature",
  "properties": {
    "addr:full":"1432 Leeway Ave Orlando FL 32810",
    "addr:housenumber":"1432",
    "addr:postcode":"32810",
    "addr:street":"Leeway Ave",
    "iso:country":"US",
    "sg:address":"1432 Leeway Ave",
    "sg:city":"Orlando",
    "sg:classifiers":[
        {
            "category":"Transit Center",
            "subcategory":"Freight",
            "type":"Transportation"
        },
        {
            "category":"Professional",
            "subcategory":"Advertising",
            "type":"Services"
        }
    ],
    "sg:phone":"+1 407 647 3113",
    "sg:postcode":"32810",
    "sg:province":"FL",
    "sg:tags":[
        "outdoor"
    ],
    "wof:name":"Dusty Branton",
    "wof:placetype":"venue"
},
  "geometry": {"coordinates":[-81.40266200000001,28.614503],"type":"Point"}
}