{
  "type": "Feature",
  "properties": {
    "addr:full":"420 W 20th St Hialeah FL 33010",
    "addr:housenumber":"420",
    "addr:postcode":"33010",
    "addr:street":"W 20Th St",
    "iso:country":"US",
    "sg:address":"420 W 20th St",
    "sg:city":"Hialeah",
    "sg:classifiers":[
        {
            "category":"Home & Garden",
            "subcategory":"Building Materials",
            "type":"Retail Goods"
        }
    ],
    "sg:phone":"+1 305 887 5100",
    "sg:postcode":"33010",
    "sg:province":"FL",
    "sg:tags":[
        "plumbing",
        "fixture",
        "supply"
    ],
    "wof:name":"Bathroom Unique Inc",
    "wof:placetype":"venue"
},
  "geometry": {"coordinates":[-80.29057899999999,25.839738],"type":"Point"}
}