{
  "type": "Feature",
  "properties": {
    "addr:full":"201 NE 32nd Ct Fort Lauderdale FL 33334",
    "addr:housenumber":"201",
    "addr:postcode":"33334",
    "addr:street":"Ne 32Nd Ct",
    "iso:country":"US",
    "sg:address":"201 NE 32nd Ct",
    "sg:city":"Fort Lauderdale",
    "sg:classifiers":[
        {
            "category":"Retail",
            "subcategory":"Auto Repair",
            "type":"Services"
        }
    ],
    "sg:phone":"+1 954 561 0155",
    "sg:postcode":"33334",
    "sg:province":"FL",
    "sg:tags":[
        "repairing",
        "automobile",
        "automotive"
    ],
    "wof:name":"S & V Auto Repair Inc",
    "wof:placetype":"venue"
},
  "geometry": {"coordinates":[-80.14245099999999,26.168122],"type":"Point"}
}