{
  "type": "Feature",
  "properties": {
    "addr:full":"1771 W Flagler St Miami FL 33135",
    "addr:housenumber":"1771",
    "addr:postcode":"33135",
    "addr:street":"W Flagler St",
    "iso:country":"US",
    "sg:address":"1771 W Flagler St",
    "sg:city":"Miami",
    "sg:classifiers":[
        {
            "category":"Manufacturing",
            "subcategory":"Printing",
            "type":"Manufacturing & Wholesale Goods"
        }
    ],
    "sg:phone":"+1 305 541 6289",
    "sg:postcode":"33135",
    "sg:province":"FL",
    "sg:tags":[
        "services-commercial",
        "commercial",
        "lithographic"
    ],
    "wof:name":"Hps",
    "wof:placetype":"venue"
},
  "geometry": {"coordinates":[-80.22426,25.772762],"type":"Point"}
}