{
  "type": "Feature",
  "properties": {
    "addr:full":"11555 Lake Underhill Rd Orlando FL 32825",
    "addr:housenumber":"11555",
    "addr:postcode":"32825",
    "addr:street":"Lake Underhill Rd",
    "iso:country":"US",
    "sg:address":"11555 Lake Underhill Rd",
    "sg:city":"Orlando",
    "sg:classifiers":[
        {
            "category":"Real Estate",
            "subcategory":"Real Estate Agent",
            "type":"Services"
        },
        {
            "category":"Professional",
            "subcategory":"Management & Consulting",
            "type":"Services"
        }
    ],
    "sg:phone":"+1 407 382 0003",
    "sg:postcode":"32825",
    "sg:province":"FL",
    "sg:tags":[
        "company"
    ],
    "sg:website":"www.exitrealestateprofessionals.com",
    "wof:name":"Exit Real Estate Professionals",
    "wof:placetype":"venue"
},
  "geometry": {"coordinates":[-81.216159,28.546735],"type":"Point"}
}