{
  "type": "Feature",
  "properties": {
    "addr:full":"6801 Roosevelt Blvd Jacksonville Nas FL 32212",
    "addr:housenumber":"6801",
    "addr:postcode":"32212",
    "addr:street":"Roosevelt Blvd",
    "iso:country":"US",
    "sg:address":"6801 Roosevelt Blvd",
    "sg:city":"Jacksonville Nas",
    "sg:classifiers":[
        {
            "category":"Restaurant",
            "type":"Food & Drink"
        }
    ],
    "sg:phone":"+1 904 772 8229",
    "sg:postcode":"32212",
    "sg:province":"FL",
    "wof:name":"Subway Sandwiches & Salads",
    "wof:placetype":"venue"
},
  "geometry": {"coordinates":[-81.70209800000001,30.220591],"type":"Point"}
}