{
  "type": "Feature",
  "properties": {
    "addr:full":"6984 Collins Avenue Miami Beach FL 33141",
    "addr:housenumber":"6984",
    "addr:postcode":"33141",
    "addr:street":"Collins Avenue",
    "iso:country":"US",
    "sg:address":"6984 Collins Avenue",
    "sg:city":"Miami Beach",
    "sg:classifiers":[
        {
            "category":"Restaurant",
            "type":"Food & Drink"
        }
    ],
    "sg:phone":"+1 305 397 8215",
    "sg:postcode":"33141",
    "sg:province":"FL",
    "sg:tags":[
        "brazilian"
    ],
    "sg:website":"www.littlebrazilrestaurant.com",
    "wof:name":"Little Brazil",
    "wof:placetype":"venue"
},
  "geometry": {"coordinates":[-80.12121,25.867649],"type":"Point"}
}