{
  "type": "Feature",
  "properties": {
    "iso:country":"US",
    "sg:address":"2673 Montague Ct W",
    "sg:city":"Clearwater",
    "sg:classifiers":[
        {
            "category":"Shopping",
            "subcategory":"Pets & Pet Supplies",
            "type":"Retail Goods"
        }
    ],
    "sg:phone":"+1 727 785 0160",
    "sg:postcode":"33761",
    "sg:province":"FL",
    "sg:tags":[
        "furnishing",
        "dog",
        "store",
        "cat"
    ],
    "wof:name":"Pet & Home Services Co",
    "wof:placetype":"venue"
},
  "geometry": {"coordinates":[-82.726254,28.045663],"type":"Point"}
}