{
  "type": "Feature",
  "properties": {
    "addr:full":"1411 Chloe Ter Sebring FL 33870",
    "addr:housenumber":"1411",
    "addr:postcode":"33870",
    "addr:street":"Chloe Ter",
    "iso:country":"US",
    "sg:address":"1411 Chloe Ter",
    "sg:city":"Sebring",
    "sg:classifiers":[
        {
            "category":"Building & Trades",
            "subcategory":"Construction",
            "type":"Services"
        }
    ],
    "sg:phone":"+1 863 385 6861",
    "sg:postcode":"33870",
    "sg:province":"FL",
    "sg:tags":[
        "general",
        "contractor"
    ],
    "wof:name":"Bateman & Sons Construction",
    "wof:placetype":"venue"
},
  "geometry": {"coordinates":[-81.48050000000001,27.493072],"type":"Point"}
}