{
  "type": "Feature",
  "properties": {
    "addr:full":"2023 NW 102nd Way Gainesville FL 32606",
    "addr:housenumber":"2023",
    "addr:postcode":"32606",
    "addr:street":"Nw 102Nd Way",
    "iso:country":"US",
    "sg:address":"2023 NW 102nd Way",
    "sg:city":"Gainesville",
    "sg:classifiers":[
        {
            "category":"Shopping",
            "subcategory":"Computers & Home Electronics",
            "type":"Retail Goods"
        }
    ],
    "sg:phone":"+1 352 331 6769",
    "sg:postcode":"32606",
    "sg:province":"FL",
    "sg:tags":[
        "furniture"
    ],
    "wof:name":"Wright Line",
    "wof:placetype":"venue"
},
  "geometry": {"coordinates":[-82.45042599999999,29.67232],"type":"Point"}
}