{
  "type": "Feature",
  "properties": {
    "iso:country":"US",
    "sg:address":"4191 W Commercial Blvd",
    "sg:city":"Fort Lauderdale",
    "sg:classifiers":[
        {
            "category":"Shopping",
            "subcategory":"Discount & Variety Stores",
            "type":"Retail Goods"
        },
        {
            "category":"Shopping",
            "subcategory":"Department Store",
            "type":"Retail Goods"
        }
    ],
    "sg:phone":"+1 954 731 9056",
    "sg:postcode":"33319",
    "sg:province":"FL",
    "sg:tags":[
        "shop"
    ],
    "wof:name":"Dollar Tree",
    "wof:placetype":"venue"
},
  "geometry": {"coordinates":[-80.20728099999999,26.187438],"type":"Point"}
}