{
  "type": "Feature",
  "properties": {
    "iso:country":"US",
    "sg:address":"800 Main St",
    "sg:city":"Daytona Beach",
    "sg:classifiers":[
        {
            "category":"Bars & Pubs",
            "type":"Food & Drink"
        }
    ],
    "sg:phone":"+1 386 253 0330",
    "sg:postcode":"32118",
    "sg:province":"FL",
    "sg:tags":[
        "bar"
    ],
    "wof:name":"Froggy's Saloon",
    "wof:placetype":"venue"
},
  "geometry": {"coordinates":[-81.009029,29.226391],"type":"Point"}
}