{
  "type": "Feature",
  "properties": {
    "iso:country":"US",
    "sg:address":"324 E Church St",
    "sg:city":"Deland",
    "sg:classifiers":[
        {
            "category":"Social Services",
            "type":"Services"
        },
        {
            "category":"Health Services",
            "subcategory":"Health Practitioner",
            "type":"Services"
        }
    ],
    "sg:phone":"+1 386 736 4722",
    "sg:postcode":"32724",
    "sg:province":"FL",
    "sg:tags":[
        "counseling"
    ],
    "wof:name":"Diane Zeidwig",
    "wof:placetype":"venue"
},
  "geometry": {"coordinates":[-81.298588,29.030857],"type":"Point"}
}