{
  "type": "Feature",
  "properties": {
    "iso:country":"US",
    "sg:address":"2020 Thomas Dr",
    "sg:city":"Panama City Bch",
    "sg:classifiers":[
        {
            "category":"Home & Garden",
            "subcategory":"Furniture",
            "type":"Retail Goods"
        }
    ],
    "sg:phone":"+1 850 233 0070",
    "sg:postcode":"32408",
    "sg:province":"FL",
    "sg:website":"www.abigaylesinteriors.com",
    "wof:name":"Abigayle's Interiors & Resort",
    "wof:placetype":"venue"
},
  "geometry": {"coordinates":[-85.756124,30.164673],"type":"Point"}
}