{
  "type": "Feature",
  "properties": {
    "addr:full":"52 W Gore St Orlando FL 32806",
    "addr:housenumber":"52",
    "addr:postcode":"32806",
    "addr:street":"W Gore St",
    "iso:country":"US",
    "sg:address":"52 W Gore St",
    "sg:city":"Orlando",
    "sg:classifiers":[
        {
            "category":"Health Services",
            "subcategory":"Doctor",
            "type":"Services"
        }
    ],
    "sg:phone":"+1 407 426 8484",
    "sg:postcode":"32806",
    "sg:province":"FL",
    "sg:tags":[
        "medical"
    ],
    "wof:name":"Holasek Maureen C MD",
    "wof:placetype":"venue"
},
  "geometry": {"coordinates":[-81.37756,28.531065],"type":"Point"}
}