{
  "type": "Feature",
  "properties": {
    "iso:country":"US",
    "sg:address":"18604 Demko Rd",
    "sg:city":"Altoona",
    "sg:classifiers":[
        {
            "category":"Health Services",
            "subcategory":"Doctor",
            "type":"Services"
        }
    ],
    "sg:phone":"+1 352 669 9235",
    "sg:postcode":"32702",
    "sg:province":"FL",
    "sg:tags":[
        "medical"
    ],
    "wof:name":"Umbach Karl Heinz Dr",
    "wof:placetype":"venue"
},
  "geometry": {"coordinates":[-81.65379799999999,28.974462],"type":"Point"}
}