{
  "type": "Feature",
  "properties": {
    "addr:full":"6869 Stapoint Ct Winter Park FL 32792",
    "addr:housenumber":"6869",
    "addr:postcode":"32792",
    "addr:street":"Stapoint Ct",
    "iso:country":"US",
    "sg:address":"6869 Stapoint Ct",
    "sg:city":"Winter Park",
    "sg:classifiers":[
        {
            "category":"Home & Garden",
            "subcategory":"Carpets & Floor Coverings",
            "type":"Retail Goods"
        }
    ],
    "sg:phone":"+1 407 677 9777",
    "sg:postcode":"32792",
    "sg:province":"FL",
    "sg:tags":[
        "flooring"
    ],
    "sg:website":"www.deloretointeriors.com",
    "wof:name":"Deloreto Interiors Inc",
    "wof:placetype":"venue"
},
  "geometry": {"coordinates":[-81.297723,28.589449],"type":"Point"}
}