{
  "type": "Feature",
  "properties": {
    "iso:country":"US",
    "sg:address":"3577 NE 163rd St",
    "sg:city":"North Miami Beach",
    "sg:classifiers":[
        {
            "category":"Real Estate",
            "subcategory":"Real Estate Services",
            "type":"Services"
        }
    ],
    "sg:phone":"+1 305 940 4660",
    "sg:postcode":"33160",
    "sg:province":"FL",
    "wof:name":"Gold Coast School of Real Estate",
    "wof:placetype":"venue"
},
  "geometry": {"coordinates":[-80.132797,25.929899],"type":"Point"}
}