{
  "type": "Feature",
  "properties": {
    "iso:country":"US",
    "sg:address":"12050 NW 28th Ave",
    "sg:city":"Miami",
    "sg:classifiers":[
        {
            "category":"Structure",
            "subcategory":"Warehouse",
            "type":"Public Place"
        },
        {
            "category":"Retail",
            "subcategory":"Storage",
            "type":"Services"
        }
    ],
    "sg:phone":"+1 305 685 6281",
    "sg:postcode":"33167",
    "sg:province":"FL",
    "sg:tags":[
        "self",
        "warehouses-merchandise"
    ],
    "wof:name":"Countywide Warehouse",
    "wof:placetype":"venue"
},
  "geometry": {"coordinates":[-80.24566299999999,25.884463],"type":"Point"}
}