{
  "type": "Feature",
  "properties": {
    "addr:full":"2603 Middlehurst Rd Titusville FL 32796",
    "addr:housenumber":"2603",
    "addr:postcode":"32796",
    "addr:street":"Middlehurst Rd",
    "iso:country":"US",
    "sg:address":"2603 Middlehurst Rd",
    "sg:city":"Titusville",
    "sg:classifiers":[
        {
            "category":"Building & Trades",
            "subcategory":"Construction",
            "type":"Services"
        }
    ],
    "sg:phone":"+1 321 268 6952",
    "sg:postcode":"32796",
    "sg:province":"FL",
    "sg:tags":[
        "floor",
        "laying",
        "contractor"
    ],
    "wof:name":"Cipollas Family Flooring Inc",
    "wof:placetype":"venue"
},
  "geometry": {"coordinates":[-80.835162,28.609812],"type":"Point"}
}