{
  "type": "Feature",
  "properties": {
    "addr:full":"3745 Suffolk Dr Tallahassee FL 32309",
    "addr:housenumber":"3745",
    "addr:postcode":"32309",
    "addr:street":"Suffolk Dr",
    "iso:country":"US",
    "sg:address":"3745 Suffolk Dr",
    "sg:city":"Tallahassee",
    "sg:classifiers":[
        {
            "category":"Professional",
            "subcategory":"Management & Consulting",
            "type":"Services"
        }
    ],
    "sg:phone":"+1 850 668 4148",
    "sg:postcode":"32309",
    "sg:province":"FL",
    "sg:tags":[
        "consultant",
        "educational"
    ],
    "wof:name":"A M Educational Publishing",
    "wof:placetype":"venue"
},
  "geometry": {"coordinates":[-84.23000999999999,30.51825],"type":"Point"}
}