{
  "type": "Feature",
  "properties": {
    "iso:country":"US",
    "sg:address":"4410 S Florida Ct",
    "sg:city":"Lakeland",
    "sg:classifiers":[
        {
            "category":"Retail",
            "subcategory":"Laundry & Dry Cleaning",
            "type":"Services"
        }
    ],
    "sg:phone":"+1 863 646 2439",
    "sg:postcode":"33813",
    "sg:province":"FL",
    "wof:name":"Taylors Alteration",
    "wof:placetype":"venue"
},
  "geometry": {"coordinates":[-81.95578399999999,27.985214],"type":"Point"}
}