{
  "type": "Feature",
  "properties": {
    "iso:country":"US",
    "sg:address":"2005 Van Buren St",
    "sg:city":"Hollywood",
    "sg:classifiers":[
        {
            "category":"Real Estate",
            "subcategory":"Real Estate Agent",
            "type":"Services"
        }
    ],
    "sg:phone":"+1 954 924 4107",
    "sg:postcode":"33020",
    "sg:province":"FL",
    "wof:name":"Kirschner Realty International",
    "wof:placetype":"venue"
},
  "geometry": {"coordinates":[-80.148718,26.009592],"type":"Point"}
}