{
  "type": "Feature",
  "properties": {
    "iso:country":"US",
    "sg:address":"1006 N 14th St",
    "sg:city":"Leesburg",
    "sg:classifiers":[
        {
            "category":"Banks & Credit Unions",
            "subcategory":"Bank",
            "type":"Services"
        }
    ],
    "sg:phone":"+1 352 360 0339",
    "sg:postcode":"34748",
    "sg:province":"FL",
    "sg:tags":[
        "saving",
        "commercial"
    ],
    "wof:name":"Orange Bank Of Florida",
    "wof:placetype":"venue"
},
  "geometry": {"coordinates":[-81.887489,28.822411],"type":"Point"}
}