{
  "type": "Feature",
  "properties": {
    "iso:country":"US",
    "sg:address":"824 Main St",
    "sg:city":"Chipley",
    "sg:classifiers":[
        {
            "category":"Food & Beverages",
            "subcategory":"Candy",
            "type":"Retail Goods"
        },
        {
            "category":"Manufacturing",
            "subcategory":"Food",
            "type":"Manufacturing & Wholesale Goods"
        }
    ],
    "sg:phone":"+1 850 638 9393",
    "sg:postcode":"32428",
    "sg:province":"FL",
    "sg:tags":[
        "confectionery",
        "mfg"
    ],
    "wof:name":"Chocolate Gallery Inc",
    "wof:placetype":"venue"
},
  "geometry": {"coordinates":[-85.539028,30.79225],"type":"Point"}
}