{
  "type": "Feature",
  "properties": {
    "iso:country":"US",
    "sg:address":"2751 S Ocean Dr",
    "sg:city":"Hollywood",
    "sg:classifiers":[
        {
            "category":"Restaurant",
            "type":"Food & Drink"
        }
    ],
    "sg:phone":"+1 954 925 1094",
    "sg:postcode":"33019",
    "sg:province":"FL",
    "wof:name":"Aquarius Cafe",
    "wof:placetype":"venue"
},
  "geometry": {"coordinates":[-80.118888,25.989941],"type":"Point"}
}