{
  "type": "Feature",
  "properties": {
    "addr:full":"2012 Norfield Ct Orlando FL 32837",
    "addr:housenumber":"2012",
    "addr:postcode":"32837",
    "addr:street":"Norfield Ct",
    "iso:country":"US",
    "sg:address":"2012 Norfield Ct",
    "sg:city":"Orlando",
    "sg:classifiers":[
        {
            "category":"Freight",
            "type":"Transportation"
        }
    ],
    "sg:phone":"+1 407 438 4675",
    "sg:postcode":"32837",
    "sg:province":"FL",
    "wof:name":"Ecua Transportation Inc",
    "wof:placetype":"venue"
},
  "geometry": {"coordinates":[-81.410281,28.398738],"type":"Point"}
}