{
  "type": "Feature",
  "properties": {
    "iso:country":"US",
    "sg:address":"3099 SE Monroe St",
    "sg:city":"Stuart",
    "sg:classifiers":[
        {
            "category":"Manufacturing",
            "subcategory":"Tools & Machinery",
            "type":"Manufacturing & Wholesale Goods"
        }
    ],
    "sg:phone":"+1 772 287 8400",
    "sg:postcode":"34997",
    "sg:province":"FL",
    "sg:tags":[
        "machine",
        "shop"
    ],
    "wof:name":"Krieger Machine Co",
    "wof:placetype":"venue"
},
  "geometry": {"coordinates":[-80.214979,27.153143],"type":"Point"}
}