{
  "type": "Feature",
  "properties": {
    "addr:full":"1728 Morelos Rd Lady Lake FL 32159",
    "addr:housenumber":"1728",
    "addr:postcode":"32159",
    "addr:street":"Morelos Rd",
    "iso:country":"US",
    "sg:address":"1728 Morelos Rd",
    "sg:city":"Lady Lake",
    "sg:classifiers":[
        {
            "category":"Wholesale",
            "subcategory":"Machinery & Supplies",
            "type":"Manufacturing & Wholesale Goods"
        }
    ],
    "sg:phone":"+1 352 750 6306",
    "sg:postcode":"32159",
    "sg:province":"FL",
    "sg:tags":[
        "equipment",
        "establishment"
    ],
    "wof:name":"Sloan Funeral Supply",
    "wof:placetype":"venue"
},
  "geometry": {"coordinates":[-81.96449,28.926331],"type":"Point"}
}