{
  "type": "Feature",
  "properties": {
    "iso:country":"US",
    "sg:address":"4150 Hancock Bridge Pkwy",
    "sg:city":"N Ft Myers",
    "sg:classifiers":[
        {
            "category":"Restaurant",
            "type":"Food & Drink"
        }
    ],
    "sg:phone":"+1 239 997 0009",
    "sg:postcode":"33903",
    "sg:province":"FL",
    "wof:name":"Las Delicias Cafeteria & Bakery",
    "wof:placetype":"venue"
},
  "geometry": {"coordinates":[-81.918688,26.651979],"type":"Point"}
}