{
  "type": "Feature",
  "properties": {
    "iso:country":"US",
    "sg:address":"12951 Biscayne Blvd",
    "sg:city":"North Miami",
    "sg:classifiers":[
        {
            "category":"Building & Trades",
            "subcategory":"Locksmith",
            "type":"Services"
        }
    ],
    "sg:phone":"+1 786 228 5633",
    "sg:postcode":"33181",
    "sg:province":"FL",
    "sg:tags":[
        "key"
    ],
    "wof:name":"Emergency Locksmith On Biscayne Blvd",
    "wof:placetype":"venue"
},
  "geometry": {"coordinates":[-80.161996,25.895349],"type":"Point"}
}