{
  "type": "Feature",
  "properties": {
    "addr:full":"2370 NW 17th Ave Miami FL 33142",
    "addr:housenumber":"2370",
    "addr:postcode":"33142",
    "addr:street":"Nw 17Th Ave",
    "iso:country":"US",
    "sg:address":"2370 NW 17th Ave",
    "sg:city":"Miami",
    "sg:classifiers":[
        {
            "category":"Recreation",
            "type":"Entertainment"
        }
    ],
    "sg:phone":"+1 305 635 1813",
    "sg:postcode":"33142",
    "sg:province":"FL",
    "wof:name":"YMCA",
    "wof:placetype":"venue"
},
  "geometry": {"coordinates":[-80.223529,25.799278],"type":"Point"}
}