{
  "type": "Feature",
  "properties": {
    "addr:full":"14114 Alabama St Jay FL 32565",
    "addr:housenumber":"14114",
    "addr:postcode":"32565",
    "addr:street":"Alabama St",
    "iso:country":"US",
    "sg:address":"14114 Alabama St",
    "sg:city":"Jay",
    "sg:classifiers":[
        {
            "category":"Health Services",
            "subcategory":"Doctor",
            "type":"Services"
        },
        {
            "category":"Personal",
            "type":"Services"
        }
    ],
    "sg:phone":"+1 850 675 4787",
    "sg:postcode":"32565",
    "sg:province":"FL",
    "sg:tags":[
        "fitness",
        "physician",
        "surgeon",
        "program",
        "consultant"
    ],
    "wof:name":"North West Florida Rural Health Network",
    "wof:placetype":"venue"
},
  "geometry": {"coordinates":[-87.15173299999999,30.94989],"type":"Point"}
}