{
  "type": "Feature",
  "properties": {
    "iso:country":"US",
    "sg:address":"2190 Corporation Blvd",
    "sg:city":"Naples",
    "sg:classifiers":[
        {
            "category":"Retail",
            "subcategory":"Auto Repair",
            "type":"Services"
        }
    ],
    "sg:phone":"+1 239 592 0500",
    "sg:postcode":"34109",
    "sg:province":"FL",
    "sg:tags":[
        "body"
    ],
    "wof:name":"Michael Hatfield Auto Body",
    "wof:placetype":"venue"
},
  "geometry": {"coordinates":[-81.775048,26.222804],"type":"Point"}
}