{
  "type": "Feature",
  "properties": {
    "iso:country":"US",
    "sg:address":"13435 S McCall Rd",
    "sg:city":"Port Charlotte",
    "sg:classifiers":[
        {
            "category":"Professional",
            "subcategory":"Computer Services",
            "type":"Services"
        }
    ],
    "sg:phone":"+1 941 698 4900",
    "sg:postcode":"33981",
    "sg:province":"FL",
    "sg:tags":[
        "internet"
    ],
    "wof:name":"Interdezign",
    "wof:placetype":"venue"
},
  "geometry": {"coordinates":[-82.226411,26.933287],"type":"Point"}
}