{
  "type": "Feature",
  "properties": {
    "addr:full":"7622 Southern Brook Bend Tampa FL 33635",
    "addr:housenumber":"7622",
    "addr:postcode":"33635",
    "addr:street":"Southern Brook Bend",
    "iso:country":"US",
    "sg:address":"7622 Southern Brook Bend",
    "sg:city":"Tampa",
    "sg:classifiers":[
        {
            "category":"Professional",
            "subcategory":"Computer Services",
            "type":"Services"
        }
    ],
    "sg:phone":"+1 813 855 7120",
    "sg:postcode":"33635",
    "sg:province":"FL",
    "sg:tags":[
        "consulting",
        "related"
    ],
    "wof:name":"Computer Nerds of Tampa Bay",
    "wof:placetype":"venue"
},
  "geometry": {"coordinates":[-82.62197399999999,28.022608],"type":"Point"}
}