{
  "type": "Feature",
  "properties": {
    "iso:country":"US",
    "sg:address":"106 Crestwood Dr",
    "sg:city":"Safety Harbor",
    "sg:classifiers":[
        {
            "category":"Manufacturing",
            "subcategory":"Printing",
            "type":"Manufacturing & Wholesale Goods"
        }
    ],
    "sg:phone":"+1 727 726 5594",
    "sg:postcode":"34695",
    "sg:province":"FL",
    "sg:tags":[
        "commercial"
    ],
    "wof:name":"Computype Inc",
    "wof:placetype":"venue"
},
  "geometry": {"coordinates":[-82.703259,27.990678],"type":"Point"}
}