{
  "type": "Feature",
  "properties": {
    "iso:country":"US",
    "sg:address":"2857 SW 27th Ave",
    "sg:city":"Miami",
    "sg:classifiers":[
        {
            "category":"Travel",
            "subcategory":"Travel Agent",
            "type":"Entertainment"
        }
    ],
    "sg:phone":"+1 305 444 6561",
    "sg:postcode":"33133",
    "sg:province":"FL",
    "sg:tags":[
        "agency",
        "bureau"
    ],
    "sg:website":"http://www.kirstentravel.com",
    "wof:name":"Kirsten Travel Agency",
    "wof:placetype":"venue"
},
  "geometry": {"coordinates":[-80.23778,25.738265],"type":"Point"}
}