{
  "type": "Feature",
  "properties": {
    "addr:full":"630 N Canal Dr Port Saint Joe FL 32456",
    "addr:housenumber":"630",
    "addr:postcode":"32456",
    "addr:street":"N Canal Dr",
    "iso:country":"US",
    "sg:address":"630 N Canal Dr",
    "sg:city":"Port Saint Joe",
    "sg:classifiers":[
        {
            "category":"Shopping",
            "subcategory":"Gifts & Souvenirs",
            "type":"Retail Goods"
        }
    ],
    "sg:phone":"+1 850 229 9277",
    "sg:postcode":"32456",
    "sg:province":"FL",
    "wof:name":"Melitas Boutique",
    "wof:placetype":"venue"
},
  "geometry": {"coordinates":[-85.37355100000001,29.99886],"type":"Point"}
}