{
  "type": "Feature",
  "properties": {
    "iso:country":"US",
    "sg:address":"946 Berkley Ct",
    "sg:city":"Palm Harbor",
    "sg:classifiers":[
        {
            "category":"Freight",
            "type":"Transportation"
        }
    ],
    "sg:phone":"+1 727 458 4192",
    "sg:postcode":"34684",
    "sg:province":"FL",
    "sg:tags":[
        "trucking"
    ],
    "wof:name":"Atlas Motorlines Inc",
    "wof:placetype":"venue"
},
  "geometry": {"coordinates":[-82.714709,28.076294],"type":"Point"}
}