{
  "type": "Feature",
  "properties": {
    "iso:country":"US",
    "sg:address":"1705 Jess Parrish Ct",
    "sg:city":"Titusville",
    "sg:classifiers":[
        {
            "category":"Health Services",
            "subcategory":"Nursing And Care Facility",
            "type":"Services"
        }
    ],
    "sg:phone":"+1 321 269 5720",
    "sg:postcode":"32796",
    "sg:province":"FL",
    "sg:tags":[
        "home",
        "convalescent"
    ],
    "wof:name":"Titusville Rehab & Nursing",
    "wof:placetype":"venue"
},
  "geometry": {"coordinates":[-80.821958,28.627472],"type":"Point"}
}