{
  "type": "Feature",
  "properties": {
    "iso:country":"US",
    "sg:address":"1531 NW 16th Ave",
    "sg:city":"Miami",
    "sg:classifiers":[
        {
            "category":"Real Estate",
            "subcategory":"Real Estate Agent",
            "type":"Services"
        }
    ],
    "sg:phone":"+1 305 609 9894",
    "sg:postcode":"33125",
    "sg:province":"FL",
    "sg:tags":[
        "property",
        "investment"
    ],
    "wof:name":"4th Union Realty Inc",
    "wof:placetype":"venue"
},
  "geometry": {"coordinates":[-80.22159000000001,25.789738],"type":"Point"}
}