{
  "type": "Feature",
  "properties": {
    "iso:country":"US",
    "sg:address":"19667 Turnberry Way",
    "sg:city":"Miami",
    "sg:classifiers":[
        {
            "category":"Real Estate",
            "subcategory":"Real Estate Agent",
            "type":"Services"
        }
    ],
    "sg:phone":"+1 305 935 4438",
    "sg:postcode":"33180",
    "sg:province":"FL",
    "wof:name":"Denise Katzaronoff PA",
    "wof:placetype":"venue"
},
  "geometry": {"coordinates":[-80.127154,25.957157],"type":"Point"}
}