{
  "type": "Feature",
  "properties": {
    "addr:full":"2761 NW 82nd Ave Doral FL 33122",
    "addr:housenumber":"2761",
    "addr:postcode":"33122",
    "addr:street":"Nw 82Nd Ave",
    "iso:country":"US",
    "sg:address":"2761 NW 82nd Ave",
    "sg:city":"Doral",
    "sg:classifiers":[
        {
            "category":"Home & Garden",
            "subcategory":"Home Furnishings",
            "type":"Retail Goods"
        }
    ],
    "sg:phone":"+1 305 392 5300",
    "sg:postcode":"33122",
    "sg:province":"FL",
    "sg:tags":[
        "utensil",
        "cooking"
    ],
    "wof:name":"Mega Trading",
    "wof:placetype":"venue"
},
  "geometry": {"coordinates":[-80.32897699999999,25.799661],"type":"Point"}
}