{
  "type": "Feature",
  "properties": {
    "iso:country":"US",
    "sg:address":"316 River Chase Cir",
    "sg:city":"Wauchula",
    "sg:classifiers":[
        {
            "category":"Real Estate",
            "subcategory":"Real Estate Operator",
            "type":"Services"
        }
    ],
    "sg:phone":"+1 863 767 0683",
    "sg:postcode":"33873",
    "sg:province":"FL",
    "sg:tags":[
        "apartment"
    ],
    "sg:website":"http://www.davisproperties.com",
    "wof:name":"River Chase Apts",
    "wof:placetype":"venue"
},
  "geometry": {"coordinates":[-81.803996,27.552265],"type":"Point"}
}