{
  "type": "Feature",
  "properties": {
    "iso:country":"US",
    "sg:address":"4506 86th St W",
    "sg:city":"Bradenton",
    "sg:classifiers":[
        {
            "category":"Personal",
            "type":"Services"
        }
    ],
    "sg:phone":"+1 941 795 5711",
    "sg:postcode":"34210",
    "sg:province":"FL",
    "sg:tags":[
        "house",
        "sitter"
    ],
    "wof:name":"As Good As It Gets",
    "wof:placetype":"venue"
},
  "geometry": {"coordinates":[-82.648522,27.457582],"type":"Point"}
}