{
  "type": "Feature",
  "properties": {
    "iso:country":"US",
    "sg:address":"7672 15th St E",
    "sg:city":"Sarasota",
    "sg:classifiers":[
        {
            "category":"Professional",
            "subcategory":"Detective & Security Services",
            "type":"Services"
        }
    ],
    "sg:phone":"+1 941 351 6049",
    "sg:postcode":"34243",
    "sg:province":"FL",
    "sg:tags":[
        "investigator"
    ],
    "wof:name":"Skyway Investigation",
    "wof:placetype":"venue"
},
  "geometry": {"coordinates":[-82.546869,27.404006],"type":"Point"}
}