{
  "type": "Feature",
  "properties": {
    "iso:country":"US",
    "sg:address":"8 Pecan Course Trl",
    "sg:city":"Ocala",
    "sg:classifiers":[
        {
            "category":"Home & Garden",
            "subcategory":"Building Materials",
            "type":"Retail Goods"
        }
    ],
    "sg:phone":"+1 352 687 2036",
    "sg:postcode":"34472",
    "sg:province":"FL",
    "sg:tags":[
        "center"
    ],
    "wof:name":"Fashion House Designer Outlet",
    "wof:placetype":"venue"
},
  "geometry": {"coordinates":[-82.03968500000001,29.141168],"type":"Point"}
}