{
  "type": "Feature",
  "properties": {
    "iso:country":"US",
    "sg:address":"1121 Lemon Tree Ter",
    "sg:city":"Delray Beach",
    "sg:classifiers":[
        {
            "category":"Professional",
            "subcategory":"Accounting & Tax Preparation",
            "type":"Services"
        }
    ],
    "sg:phone":"+1 561 278 3834",
    "sg:postcode":"33445",
    "sg:province":"FL",
    "wof:name":"Lenora Goldberg",
    "wof:placetype":"venue"
},
  "geometry": {"coordinates":[-80.098775,26.442496],"type":"Point"}
}