{
  "type": "Feature",
  "properties": {
    "addr:full":"15104 Cloverdale Dr Fort Myers FL 33919",
    "addr:housenumber":"15104",
    "addr:postcode":"33919",
    "addr:street":"Cloverdale Dr",
    "iso:country":"US",
    "sg:address":"15104 Cloverdale Dr",
    "sg:city":"Fort Myers",
    "sg:classifiers":[
        {
            "category":"Building & Trades",
            "subcategory":"Landscaping Services",
            "type":"Services"
        }
    ],
    "sg:phone":"+1 239 410 8472",
    "sg:postcode":"33919",
    "sg:province":"FL",
    "sg:tags":[
        "lawn",
        "maintenance",
        "grounds"
    ],
    "wof:name":"Environmental Horticultural",
    "wof:placetype":"venue"
},
  "geometry": {"coordinates":[-81.904488,26.523857],"type":"Point"}
}