{
  "type": "Feature",
  "properties": {
    "addr:full":"8031 N Ola Ave Tampa FL 33604",
    "addr:housenumber":"8031",
    "addr:postcode":"33604",
    "addr:street":"N Ola Ave",
    "iso:country":"US",
    "sg:address":"8031 N Ola Ave",
    "sg:city":"Tampa",
    "sg:classifiers":[
        {
            "category":"Health Services",
            "subcategory":"Clinic",
            "type":"Services"
        }
    ],
    "sg:phone":"+1 813 931 4015",
    "sg:postcode":"33604",
    "sg:province":"FL",
    "sg:tags":[
        "home"
    ],
    "wof:name":"Peoples Quality Cares",
    "wof:placetype":"venue"
},
  "geometry": {"coordinates":[-82.465172,28.020573],"type":"Point"}
}