{
  "type": "Feature",
  "properties": {
    "addr:full":"1005 Pippin Dr Mary Esther FL 32569",
    "addr:housenumber":"1005",
    "addr:postcode":"32569",
    "addr:street":"Pippin Dr",
    "iso:country":"US",
    "sg:address":"1005 Pippin Dr",
    "sg:city":"Mary Esther",
    "sg:classifiers":[
        {
            "category":"Building & Trades",
            "subcategory":"Construction",
            "type":"Services"
        }
    ],
    "sg:phone":"+1 850 243 4018",
    "sg:postcode":"32569",
    "sg:province":"FL",
    "sg:tags":[
        "hanging",
        "contractor"
    ],
    "wof:name":"Don Fields Painting",
    "wof:placetype":"venue"
},
  "geometry": {"coordinates":[-86.763313,30.409854],"type":"Point"}
}