{
  "type": "Feature",
  "properties": {
    "addr:full":"4835 E 4th Ave Hialeah FL 33013",
    "addr:housenumber":"4835",
    "addr:postcode":"33013",
    "addr:street":"E 4Th Ave",
    "iso:country":"US",
    "sg:address":"4835 E 4th Ave",
    "sg:city":"Hialeah",
    "sg:classifiers":[
        {
            "category":"Health Services",
            "subcategory":"Doctor",
            "type":"Services"
        }
    ],
    "sg:phone":"+1 305 685 6009",
    "sg:postcode":"33013",
    "sg:province":"FL",
    "sg:tags":[
        "clinic"
    ],
    "wof:name":"J C Medical Ctr",
    "wof:placetype":"venue"
},
  "geometry": {"coordinates":[-80.274556,25.866834],"type":"Point"}
}