{
  "type": "Feature",
  "properties": {
    "iso:country":"US",
    "sg:address":"696 S Gulfview Blvd",
    "sg:city":"Clearwater",
    "sg:classifiers":[
        {
            "category":"Restaurant",
            "type":"Food & Drink"
        }
    ],
    "sg:phone":"+1 727 447 9325",
    "sg:postcode":"33767",
    "sg:province":"FL",
    "wof:name":"Subway Sandwiches & Salads",
    "wof:placetype":"venue"
},
  "geometry": {"coordinates":[-82.827354,27.968],"type":"Point"}
}