{
  "type": "Feature",
  "properties": {
    "addr:full":"1131 Starling Ave Miami FL 33166",
    "addr:housenumber":"1131",
    "addr:postcode":"33166",
    "addr:street":"Starling Ave",
    "iso:country":"US",
    "sg:address":"1131 Starling Ave",
    "sg:city":"Miami",
    "sg:classifiers":[
        {
            "category":"Home & Garden",
            "subcategory":"Furniture",
            "type":"Retail Goods"
        }
    ],
    "sg:phone":"+1 305 887 4262",
    "sg:postcode":"33166",
    "sg:province":"FL",
    "wof:name":"Madera Espanola Furniture Inc",
    "wof:placetype":"venue"
},
  "geometry": {"coordinates":[-80.30344700000001,25.837176],"type":"Point"}
}