{
  "type": "Feature",
  "properties": {
    "iso:country":"US",
    "sg:address":"2303 Hollywood Blvd Ste 2",
    "sg:city":"Hollywood",
    "sg:classifiers":[
        {
            "category":"Real Estate",
            "subcategory":"Real Estate Services",
            "type":"Services"
        },
        {
            "category":"Real Estate",
            "subcategory":"Developer",
            "type":"Services"
        },
        {
            "category":"Real Estate",
            "subcategory":"Real Estate Agent",
            "type":"Services"
        }
    ],
    "sg:phone":"+1 954 374 3473",
    "sg:postcode":"33020",
    "sg:province":"FL",
    "sg:tags":[
        "investing",
        "buyer",
        "broker"
    ],
    "wof:name":"Dnj Development Inc",
    "wof:placetype":"venue"
},
  "geometry": {"coordinates":[-80.15278600000001,26.011259],"type":"Point"}
}