{
  "type": "Feature",
  "properties": {
    "addr:full":"5149 NW 74th Ave Miami FL 33166",
    "addr:housenumber":"5149",
    "addr:postcode":"33166",
    "addr:street":"Nw 74Th Ave",
    "iso:country":"US",
    "sg:address":"5149 NW 74th Ave",
    "sg:city":"Miami",
    "sg:classifiers":[
        {
            "category":"Professional",
            "subcategory":"Management & Consulting",
            "type":"Services"
        }
    ],
    "sg:phone":"+1 305 436 9907",
    "sg:postcode":"33166",
    "sg:province":"FL",
    "sg:tags":[
        "consultant"
    ],
    "wof:name":"Artistic World Inc",
    "wof:placetype":"venue"
},
  "geometry": {"coordinates":[-80.31756799999999,25.820264],"type":"Point"}
}