{
  "type": "Feature",
  "properties": {
    "iso:country":"US",
    "sg:address":"521 E 26th St",
    "sg:city":"Hialeah",
    "sg:classifiers":[
        {
            "category":"Shopping",
            "subcategory":"Pets & Pet Supplies",
            "type":"Retail Goods"
        }
    ],
    "sg:phone":"+1 305 688 2623",
    "sg:postcode":"33013",
    "sg:province":"FL",
    "sg:tags":[
        "store"
    ],
    "wof:name":"Sunshine Pet Shop",
    "wof:placetype":"venue"
},
  "geometry": {"coordinates":[-80.27185799999999,25.84578],"type":"Point"}
}