{
  "type": "Feature",
  "properties": {
    "addr:full":"21392 Crestfalls Ct Boca Raton FL 33428",
    "addr:housenumber":"21392",
    "addr:postcode":"33428",
    "addr:street":"Crestfalls Ct",
    "iso:country":"US",
    "sg:address":"21392 Crestfalls Ct",
    "sg:city":"Boca Raton",
    "sg:classifiers":[
        {
            "category":"Insurance",
            "subcategory":"Insurance Agent",
            "type":"Services"
        }
    ],
    "sg:phone":"+1 561 487 8860",
    "sg:postcode":"33428",
    "sg:province":"FL",
    "sg:tags":[
        "consultant"
    ],
    "wof:name":"PCBA",
    "wof:placetype":"venue"
},
  "geometry": {"coordinates":[-80.24204,26.35769],"type":"Point"}
}