{
  "type": "Feature",
  "properties": {
    "addr:full":"761 Anclote Rd Tarpon Springs FL 34689",
    "addr:housenumber":"761",
    "addr:postcode":"34689",
    "addr:street":"Anclote Rd",
    "iso:country":"US",
    "sg:address":"761 Anclote Rd",
    "sg:city":"Tarpon Springs",
    "sg:classifiers":[
        {
            "category":"Recreation",
            "subcategory":"Marina",
            "type":"Entertainment"
        }
    ],
    "sg:phone":"+1 727 939 1589",
    "sg:postcode":"34689",
    "sg:province":"FL",
    "wof:name":"Mar Marina",
    "wof:placetype":"venue"
},
  "geometry": {"coordinates":[-82.774745,28.169991],"type":"Point"}
}