{
  "type": "Feature",
  "properties": {
    "addr:full":"3966 Hamilton Club Cir Sarasota FL 34242",
    "addr:housenumber":"3966",
    "addr:postcode":"34242",
    "addr:street":"Hamilton Club Cir",
    "iso:country":"US",
    "sg:address":"3966 Hamilton Club Cir",
    "sg:city":"Sarasota",
    "sg:classifiers":[
        {
            "category":"Professional",
            "subcategory":"Management & Consulting",
            "type":"Services"
        }
    ],
    "sg:phone":"+1 941 349 8492",
    "sg:postcode":"34242",
    "sg:province":"FL",
    "wof:name":"Siegel Associates Inc",
    "wof:placetype":"venue"
},
  "geometry": {"coordinates":[-82.55789300000001,27.296398],"type":"Point"}
}