{
  "type": "Feature",
  "properties": {
    "addr:full":"208 3rd St Perry FL 32348",
    "addr:housenumber":"208",
    "addr:postcode":"32348",
    "addr:street":"3Rd St",
    "iso:country":"US",
    "sg:address":"208 3rd St",
    "sg:city":"Perry",
    "sg:classifiers":[
        {
            "category":"Shopping",
            "subcategory":"Shoes",
            "type":"Retail Goods"
        }
    ],
    "sg:phone":"+1 850 584 7286",
    "sg:postcode":"32348",
    "sg:province":"FL",
    "wof:name":"AR Greene Inc",
    "wof:placetype":"venue"
},
  "geometry": {"coordinates":[-83.596985,30.106662],"type":"Point"}
}