{
  "type": "Feature",
  "properties": {
    "iso:country":"US",
    "sg:address":"2665 Cleveland Ave Ste 205",
    "sg:city":"Fort Myers",
    "sg:classifiers":[
        {
            "category":"Health Services",
            "subcategory":"Chiropractor",
            "type":"Services"
        }
    ],
    "sg:phone":"+1 239 332 0099",
    "sg:postcode":"33901",
    "sg:province":"FL",
    "wof:name":"Injury and Wellness Centers of Fort Myers Inc the",
    "wof:placetype":"venue"
},
  "geometry": {"coordinates":[-81.872398,26.628401],"type":"Point"}
}