{
  "type": "Feature",
  "properties": {
    "addr:full":"3352 Whipporwill Dr Tallahassee FL 32310",
    "addr:housenumber":"3352",
    "addr:postcode":"32310",
    "addr:street":"Whipporwill Dr",
    "iso:country":"US",
    "sg:address":"3352 Whipporwill Dr",
    "sg:city":"Tallahassee",
    "sg:classifiers":[
        {
            "category":"Building & Trades",
            "subcategory":"Cleaning & Sanitation",
            "type":"Services"
        }
    ],
    "sg:phone":"+1 850 528 1588",
    "sg:postcode":"32310",
    "sg:province":"FL",
    "sg:tags":[
        "butler",
        "maid"
    ],
    "wof:name":"Maid Runners Inc",
    "wof:placetype":"venue"
},
  "geometry": {"coordinates":[-84.572452,30.409619],"type":"Point"}
}