{
  "type": "Feature",
  "properties": {
    "iso:country":"US",
    "sg:address":"2536 Griffin Sq",
    "sg:city":"West Palm Beach",
    "sg:classifiers":[
        {
            "category":"Social Services",
            "subcategory":"Child Care",
            "type":"Services"
        }
    ],
    "sg:phone":"+1 561 818 0121",
    "sg:postcode":"33406",
    "sg:province":"FL",
    "sg:tags":[
        "day"
    ],
    "wof:name":"Charlottes Child Care",
    "wof:placetype":"venue"
},
  "geometry": {"coordinates":[-80.110795,26.647579],"type":"Point"}
}