{
  "type": "Feature",
  "properties": {
    "iso:country":"US",
    "sg:address":"2715 N W St",
    "sg:city":"Pensacola",
    "sg:classifiers":[
        {
            "category":"Retail",
            "subcategory":"Repair Shop",
            "type":"Services"
        }
    ],
    "sg:phone":"+1 850 438 9011",
    "sg:postcode":"32505",
    "sg:province":"FL",
    "sg:tags":[
        "welding"
    ],
    "wof:name":"D & D Welding Inc",
    "wof:placetype":"venue"
},
  "geometry": {"coordinates":[-87.24889899999999,30.441145],"type":"Point"}
}