{
  "type": "Feature",
  "properties": {
    "addr:full":"7044 Stapoint Ct Winter Park FL 32792",
    "addr:housenumber":"7044",
    "addr:postcode":"32792",
    "addr:street":"Stapoint Ct",
    "iso:country":"US",
    "sg:address":"7044 Stapoint Ct",
    "sg:city":"Winter Park",
    "sg:classifiers":[
        {
            "category":"Professional",
            "type":"Services"
        }
    ],
    "sg:phone":"+1 407 657 5704",
    "sg:postcode":"32792",
    "sg:province":"FL",
    "sg:tags":[
        "establishment"
    ],
    "wof:name":"World Stage Productions",
    "wof:placetype":"venue"
},
  "geometry": {"coordinates":[-81.29539800000001,28.589019],"type":"Point"}
}