{
  "type": "Feature",
  "properties": {
    "addr:full":"1874 Martin Luther King Ter Sebring FL 33870",
    "addr:housenumber":"1874",
    "addr:postcode":"33870",
    "addr:street":"Martin Luther King Ter",
    "iso:country":"US",
    "sg:address":"1874 Martin Luther King Ter",
    "sg:city":"Sebring",
    "sg:classifiers":[
        {
            "category":"Professional",
            "type":"Services"
        }
    ],
    "sg:phone":"+1 863 314 9707",
    "sg:postcode":"33870",
    "sg:province":"FL",
    "sg:tags":[
        "establishment"
    ],
    "wof:name":"Terra's",
    "wof:placetype":"venue"
},
  "geometry": {"coordinates":[-81.42147300000001,27.50126],"type":"Point"}
}