{
  "type": "Feature",
  "properties": {
    "iso:country":"US",
    "sg:address":"777 E Atlantic Ave",
    "sg:city":"Delray Beach",
    "sg:classifiers":[
        {
            "category":"Personal",
            "subcategory":"Beauty Salon",
            "type":"Services"
        },
        {
            "category":"Sports & Exercise",
            "subcategory":"Gym",
            "type":"Entertainment"
        }
    ],
    "sg:phone":"+1 561 921 0422",
    "sg:postcode":"33483",
    "sg:province":"FL",
    "sg:tags":[
        "spa"
    ],
    "wof:name":"Vincenzo Nardi Salon & Spa",
    "wof:placetype":"venue"
},
  "geometry": {"coordinates":[-80.065799,26.46174],"type":"Point"}
}