{
  "type": "Feature",
  "properties": {
    "iso:country":"US",
    "sg:address":"6887 Bird Rd",
    "sg:city":"Miami",
    "sg:classifiers":[
        {
            "category":"Insurance",
            "subcategory":"Hazard Insurance",
            "type":"Services"
        },
        {
            "category":"Insurance",
            "subcategory":"Health Insurance",
            "type":"Services"
        }
    ],
    "sg:phone":"+1 305 740 0515",
    "sg:postcode":"33155",
    "sg:province":"FL",
    "sg:tags":[
        "business",
        "commercial",
        "worker",
        "disability",
        "compensation"
    ],
    "sg:website":"http://www.aicins.com/",
    "wof:name":"Acceptance Insurance Services Inc",
    "wof:placetype":"venue"
},
  "geometry": {"coordinates":[-80.306336,25.733362],"type":"Point"}
}