{
  "type": "Feature",
  "properties": {
    "addr:full":"9919 Scepter Ave Brooksville FL 34613",
    "addr:housenumber":"9919",
    "addr:postcode":"34613",
    "addr:street":"Scepter Ave",
    "iso:country":"US",
    "sg:address":"9919 Scepter Ave",
    "sg:city":"Brooksville",
    "sg:classifiers":[
        {
            "category":"Building & Trades",
            "subcategory":"Construction",
            "type":"Services"
        }
    ],
    "sg:phone":"+1 352 597 0696",
    "sg:postcode":"34613",
    "sg:province":"FL",
    "sg:tags":[
        "hanging",
        "contractor"
    ],
    "wof:name":"Albert J Paulette",
    "wof:placetype":"venue"
},
  "geometry": {"coordinates":[-82.484162,28.555748],"type":"Point"}
}