{
  "type": "Feature",
  "properties": {
    "iso:country":"US",
    "sg:address":"13590 SW 134th Ave",
    "sg:city":"Miami",
    "sg:classifiers":[
        {
            "category":"Professional",
            "subcategory":"Computer Services",
            "type":"Services"
        }
    ],
    "sg:phone":"+1 305 378 4978",
    "sg:postcode":"33186",
    "sg:province":"FL",
    "sg:tags":[
        "publisher",
        "web",
        "site",
        "design",
        "software",
        "developer"
    ],
    "wof:name":"Scala Design",
    "wof:placetype":"venue"
},
  "geometry": {"coordinates":[-80.41255200000001,25.663215],"type":"Point"}
}