{
  "type": "Feature",
  "properties": {
    "iso:country":"US",
    "sg:address":"100 Ocean Lane Dr",
    "sg:city":"Key Biscayne",
    "sg:classifiers":[
        {
            "category":"Organizations",
            "subcategory":"Professional Association",
            "type":"Services"
        }
    ],
    "sg:phone":"+1 305 361 2011",
    "sg:postcode":"33149",
    "sg:province":"FL",
    "sg:tags":[
        "management",
        "property"
    ],
    "wof:name":"Key Biscayne 100 Condominium Association",
    "wof:placetype":"venue"
},
  "geometry": {"coordinates":[-80.160797,25.6989],"type":"Point"}
}