{
  "type": "Feature",
  "properties": {
    "iso:country":"US",
    "sg:address":"2082 Trade Center Way",
    "sg:city":"Naples",
    "sg:classifiers":[
        {
            "category":"Building & Trades",
            "subcategory":"Construction",
            "type":"Services"
        }
    ],
    "sg:phone":"+1 239 597 5343",
    "sg:postcode":"34109",
    "sg:province":"FL",
    "sg:tags":[
        "planning",
        "remodeling",
        "kitchen"
    ],
    "wof:name":"Kitchens Direct Of Naples",
    "wof:placetype":"venue"
},
  "geometry": {"coordinates":[-81.776944,26.225118],"type":"Point"}
}