{
  "type": "Feature",
  "properties": {
    "iso:country":"US",
    "sg:address":"2109 SE Floresta Dr",
    "sg:city":"Port Saint Lucie",
    "sg:classifiers":[
        {
            "category":"Personal",
            "type":"Services"
        }
    ],
    "sg:phone":"+1 772 873 4215",
    "sg:postcode":"34984",
    "sg:province":"FL",
    "wof:name":"Body Mind & Spirit",
    "wof:placetype":"venue"
},
  "geometry": {"coordinates":[-80.331838,27.277878],"type":"Point"}
}