{
  "type": "Feature",
  "properties": {
    "addr:full":"1015 SE Floresta Dr Port St Lucie FL 34983",
    "addr:housenumber":"1015",
    "addr:postcode":"34983",
    "addr:street":"Se Floresta Dr",
    "iso:country":"US",
    "sg:address":"1015 SE Floresta Dr",
    "sg:city":"Port St Lucie",
    "sg:classifiers":[
        {
            "category":"Professional",
            "subcategory":"Art Services",
            "type":"Services"
        }
    ],
    "sg:phone":"+1 772 336 6931",
    "sg:postcode":"34983",
    "sg:province":"FL",
    "sg:tags":[
        "logos"
    ],
    "wof:name":"Michelle Burns Monograms/Embrd",
    "wof:placetype":"venue"
},
  "geometry": {"coordinates":[-80.332179,27.308723],"type":"Point"}
}