{
  "type": "Feature",
  "properties": {
    "iso:country":"US",
    "sg:address":"905 11th St",
    "sg:city":"Palm Harbor",
    "sg:classifiers":[
        {
            "category":"Travel",
            "subcategory":"Travel Agent",
            "type":"Entertainment"
        }
    ],
    "sg:phone":"+1 727 573 2883",
    "sg:postcode":"34683",
    "sg:province":"FL",
    "sg:tags":[
        "agency",
        "bureau"
    ],
    "wof:name":"Clear Water Cruises",
    "wof:placetype":"venue"
},
  "geometry": {"coordinates":[-82.76608299999999,28.077129],"type":"Point"}
}