{
  "type": "Feature",
  "properties": {
    "iso:country":"US",
    "sg:address":"7007 Sea Harbor Dr",
    "sg:city":"Orlando",
    "sg:classifiers":[
        {
            "category":"Recreation",
            "subcategory":"Picnic Area",
            "type":"Entertainment"
        },
        {
            "category":"Community Center",
            "type":"Public Place"
        },
        {
            "category":"Landmark",
            "subcategory":"Tourist Information",
            "type":"Public Place"
        }
    ],
    "sg:phone":"+1 407 363 2617",
    "sg:postcode":"32821",
    "sg:province":"FL",
    "sg:tags":[
        "attraction",
        "amusement",
        "arcade"
    ],
    "wof:name":"Seaworld Orlando Tdd Guest",
    "wof:placetype":"venue"
},
  "geometry": {"coordinates":[-81.470603,28.406524],"type":"Point"}
}