{
  "type": "Feature",
  "properties": {
    "iso:country":"US",
    "sg:address":"1200 NW 6th Ave",
    "sg:city":"Miami",
    "sg:classifiers":[
        {
            "category":"Education",
            "subcategory":"Special Training",
            "type":"Public Place"
        }
    ],
    "sg:phone":"+1 786 337 0195",
    "sg:postcode":"33136",
    "sg:province":"FL",
    "sg:tags":[
        "educational"
    ],
    "wof:name":"Technology Student Association",
    "wof:placetype":"venue"
},
  "geometry": {"coordinates":[-80.204826,25.786659],"type":"Point"}
}