{
  "type": "Feature",
  "properties": {
    "addr:full":"1412 SW 9th Ave Cape Coral FL 33991",
    "addr:housenumber":"1412",
    "addr:postcode":"33991",
    "addr:street":"Sw 9Th Ave",
    "iso:country":"US",
    "sg:address":"1412 SW 9th Ave",
    "sg:city":"Cape Coral",
    "sg:classifiers":[
        {
            "category":"Building & Trades",
            "subcategory":"Plumbing",
            "type":"Services"
        }
    ],
    "sg:phone":"+1 239 574 7215",
    "sg:postcode":"33991",
    "sg:province":"FL",
    "sg:tags":[
        "contractor"
    ],
    "wof:name":"Deno & Sons Inc",
    "wof:placetype":"venue"
},
  "geometry": {"coordinates":[-81.99460999999999,26.62628],"type":"Point"}
}