{
  "type": "Feature",
  "properties": {
    "iso:country":"US",
    "sg:address":"3120 W 84th St",
    "sg:city":"Hialeah",
    "sg:classifiers":[
        {
            "category":"Freight",
            "type":"Transportation"
        }
    ],
    "sg:phone":"+1 305 819 3245",
    "sg:postcode":"33018",
    "sg:province":"FL",
    "sg:tags":[
        "motion",
        "picture",
        "film"
    ],
    "wof:name":"Media Library House",
    "wof:placetype":"venue"
},
  "geometry": {"coordinates":[-80.34710200000001,25.897599],"type":"Point"}
}