{
  "type": "Feature",
  "properties": {
    "iso:country":"US",
    "sg:address":"2522 SW 113th Ct",
    "sg:city":"Miami",
    "sg:classifiers":[
        {
            "category":"Wholesale",
            "subcategory":"Electrical",
            "type":"Manufacturing & Wholesale Goods"
        }
    ],
    "sg:phone":"+1 305 207 9974",
    "sg:postcode":"33165",
    "sg:province":"FL",
    "sg:tags":[
        "control",
        "security",
        "system"
    ],
    "wof:name":"Alarm Digital Telecommuncation",
    "wof:placetype":"venue"
},
  "geometry": {"coordinates":[-80.378422,25.746099],"type":"Point"}
}