{
  "type": "Feature",
  "properties": {
    "iso:country":"US",
    "sg:address":"742 US Hwy 1",
    "sg:city":"North Palm Beach",
    "sg:classifiers":[
        {
            "category":"Manufacturing",
            "subcategory":"Printing",
            "type":"Manufacturing & Wholesale Goods"
        }
    ],
    "sg:phone":"+1 561 844 7077",
    "sg:postcode":"33408",
    "sg:province":"FL",
    "sg:tags":[
        "printer"
    ],
    "wof:name":"PIP Printing",
    "wof:placetype":"venue"
},
  "geometry": {"coordinates":[-80.05472,26.798748],"type":"Point"}
}