{
  "type": "Feature",
  "properties": {
    "addr:full":"619 N Grandview Ave Daytona Beach FL 32118",
    "addr:housenumber":"619",
    "addr:postcode":"32118",
    "addr:street":"N Grandview Ave",
    "iso:country":"US",
    "sg:address":"619 N Grandview Ave",
    "sg:city":"Daytona Beach",
    "sg:classifiers":[
        {
            "category":"Building & Trades",
            "subcategory":"Construction",
            "type":"Services"
        }
    ],
    "sg:phone":"+1 386 547 4470",
    "sg:postcode":"32118",
    "sg:province":"FL",
    "sg:tags":[
        "house"
    ],
    "wof:name":"Real Estate Maintenance",
    "wof:placetype":"venue"
},
  "geometry": {"coordinates":[-81.01421000000001,29.236519],"type":"Point"}
}