{
  "type": "Feature",
  "properties": {
    "iso:country":"US",
    "sg:address":"4528 Villa Capri Ln",
    "sg:city":"Bonita Springs",
    "sg:classifiers":[
        {
            "category":"Building & Trades",
            "subcategory":"Cleaning & Sanitation",
            "type":"Services"
        }
    ],
    "sg:phone":"+1 239 947 1848",
    "sg:postcode":"34134",
    "sg:province":"FL",
    "sg:tags":[
        "janitor"
    ],
    "wof:name":"Simco Cleaning Svc",
    "wof:placetype":"venue"
},
  "geometry": {"coordinates":[-81.827731,26.399756],"type":"Point"}
}