{
  "type": "Feature",
  "properties": {
    "addr:full":"175 E Welch Rd Apopka FL 32712",
    "addr:housenumber":"175",
    "addr:postcode":"32712",
    "addr:street":"E Welch Rd",
    "iso:country":"US",
    "sg:address":"175 E Welch Rd",
    "sg:city":"Apopka",
    "sg:classifiers":[
        {
            "category":"Banks & Credit Unions",
            "subcategory":"Bank",
            "type":"Services"
        },
        {
            "category":"Banks & Credit Unions",
            "subcategory":"Financial Services",
            "type":"Services"
        }
    ],
    "sg:phone":"+1 800 734 4667",
    "sg:postcode":"32712",
    "sg:province":"FL",
    "sg:tags":[
        "saving",
        "loan",
        "commercial"
    ],
    "sg:website":"http://www.regionsbank.com",
    "wof:name":"Regions Bank",
    "wof:placetype":"venue"
},
  "geometry": {"coordinates":[-81.506912,28.70589],"type":"Point"}
}