{
  "type": "Feature",
  "properties": {
    "iso:country":"US",
    "sg:address":"481 John Ringling Blvd",
    "sg:city":"Sarasota",
    "sg:classifiers":[
        {
            "category":"Shopping",
            "subcategory":"Clothing, Apparel, & Fashions",
            "type":"Retail Goods"
        }
    ],
    "sg:phone":"+1 941 388 5239",
    "sg:postcode":"34236",
    "sg:province":"FL",
    "sg:tags":[
        "ready"
    ],
    "wof:name":"Foxy Lady West Inc",
    "wof:placetype":"venue"
},
  "geometry": {"coordinates":[-82.576055,27.319254],"type":"Point"}
}