{
  "type": "Feature",
  "properties": {
    "iso:country":"US",
    "sg:address":"11919 59th St N",
    "sg:city":"Royal Palm Beach",
    "sg:classifiers":[
        {
            "category":"Building & Trades",
            "subcategory":"Construction",
            "type":"Services"
        }
    ],
    "sg:phone":"+1 561 615 1635",
    "sg:postcode":"33411",
    "sg:province":"FL",
    "sg:tags":[
        "home",
        "builder"
    ],
    "wof:name":"R C Construction Of South Fl",
    "wof:placetype":"venue"
},
  "geometry": {"coordinates":[-80.22919899999999,26.763936],"type":"Point"}
}