{
  "type": "Feature",
  "properties": {
    "iso:country":"US",
    "sg:address":"2422 W 60th St",
    "sg:city":"Hialeah",
    "sg:classifiers":[
        {
            "category":"Shopping",
            "subcategory":"Clothing, Apparel, & Fashions",
            "type":"Retail Goods"
        }
    ],
    "sg:phone":"+1 305 821 9893",
    "sg:postcode":"33016",
    "sg:province":"FL",
    "wof:name":"Super Fashions Viii Inc",
    "wof:placetype":"venue"
},
  "geometry": {"coordinates":[-80.33248399999999,25.876937],"type":"Point"}
}