{
  "type": "Feature",
  "properties": {
    "iso:country":"US",
    "sg:address":"305 Bay Arbor Blvd",
    "sg:city":"Oldsmar",
    "sg:classifiers":[
        {
            "category":"Social Services",
            "subcategory":"Job Training",
            "type":"Services"
        }
    ],
    "sg:phone":"+1 813 880 0280",
    "sg:postcode":"34677",
    "sg:province":"FL",
    "wof:name":"Atec Training Corp",
    "wof:placetype":"venue"
},
  "geometry": {"coordinates":[-82.68325,28.052293],"type":"Point"}
}