{
  "type": "Feature",
  "properties": {
    "iso:country":"US",
    "sg:address":"6709 NE 3rd Ave",
    "sg:city":"Miami",
    "sg:classifiers":[
        {
            "category":"Home & Garden",
            "subcategory":"Home Furnishings",
            "type":"Retail Goods"
        },
        {
            "category":"Shopping",
            "subcategory":"Crafts & Fabrics",
            "type":"Retail Goods"
        }
    ],
    "sg:phone":"+1 305 751 8200",
    "sg:postcode":"33138",
    "sg:province":"FL",
    "sg:tags":[
        "bedding",
        "quilting",
        "quilt"
    ],
    "wof:name":"Miami Quilting Center Inc",
    "wof:placetype":"venue"
},
  "geometry": {"coordinates":[-80.190234,25.836518],"type":"Point"}
}