{
  "type": "Feature",
  "properties": {
    "addr:full":"820 NW Park St Okeechobee FL 34972",
    "addr:housenumber":"820",
    "addr:postcode":"34972",
    "addr:street":"Nw Park St",
    "iso:country":"US",
    "sg:address":"820 NW Park St",
    "sg:city":"Okeechobee",
    "sg:classifiers":[
        {
            "category":"Real Estate",
            "subcategory":"Real Estate Agent",
            "type":"Services"
        }
    ],
    "sg:phone":"+1 863 357 7277",
    "sg:postcode":"34972",
    "sg:province":"FL",
    "wof:name":"Tina's Best Buy",
    "wof:placetype":"venue"
},
  "geometry": {"coordinates":[-80.838875,27.243816],"type":"Point"}
}