{
  "type": "Feature",
  "properties": {
    "addr:full":"6225 15th St E Bradenton FL 34203",
    "addr:housenumber":"6225",
    "addr:postcode":"34203",
    "addr:street":"15Th St",
    "iso:country":"US",
    "sg:address":"6225 15th St E",
    "sg:city":"Bradenton",
    "sg:classifiers":[
        {
            "category":"Manufacturing",
            "subcategory":"Tools & Machinery",
            "type":"Manufacturing & Wholesale Goods"
        }
    ],
    "sg:phone":"+1 941 758 7771",
    "sg:postcode":"34203",
    "sg:province":"FL",
    "sg:tags":[
        "industry",
        "electrical",
        "special",
        "mfg"
    ],
    "wof:name":"Battery Equipment Service Co",
    "wof:placetype":"venue"
},
  "geometry": {"coordinates":[-82.546609,27.429711],"type":"Point"}
}