{
  "type": "Feature",
  "properties": {
    "iso:country":"US",
    "sg:address":"2004 State Hwy 77",
    "sg:city":"Lynn Haven",
    "sg:classifiers":[
        {
            "category":"Restaurant",
            "type":"Food & Drink"
        }
    ],
    "sg:phone":"+1 850 265 0120",
    "sg:postcode":"32444",
    "sg:province":"FL",
    "sg:tags":[
        "eating"
    ],
    "wof:name":"Flap Jacks",
    "wof:placetype":"venue"
},
  "geometry": {"coordinates":[-85.649281,30.23001],"type":"Point"}
}