{
  "type": "Feature",
  "properties": {
    "iso:country":"US",
    "sg:address":"813 E Lemon Ave",
    "sg:city":"Eustis",
    "sg:classifiers":[
        {
            "category":"Professional",
            "subcategory":"Detective & Security Services",
            "type":"Services"
        }
    ],
    "sg:phone":"+1 352 483 1698",
    "sg:postcode":"32726",
    "sg:province":"FL",
    "sg:tags":[
        "information",
        "bureau"
    ],
    "wof:name":"Robert A. Cruz Construction Services Inc.",
    "wof:placetype":"venue"
},
  "geometry": {"coordinates":[-81.67717399999999,28.850162],"type":"Point"}
}