{
  "type": "Feature",
  "properties": {
    "addr:full":"403 E International Speedway Blvd Daytona Beach FL 32118",
    "addr:housenumber":"403",
    "addr:postcode":"32118",
    "addr:street":"E International Speedway Blvd",
    "iso:country":"US",
    "sg:address":"403 E International Speedway Blvd",
    "sg:city":"Daytona Beach",
    "sg:classifiers":[
        {
            "category":"Autos & Motor Vehicles",
            "subcategory":"Auto Supplies",
            "type":"Retail Goods"
        }
    ],
    "sg:phone":"+1 386 253 3768",
    "sg:postcode":"32118",
    "sg:province":"FL",
    "sg:tags":[
        "equipment",
        "racing",
        "car",
        "automobile"
    ],
    "wof:name":"Racing Fuels Of Daytona",
    "wof:placetype":"venue"
},
  "geometry": {"coordinates":[-81.008754,29.221218],"type":"Point"}
}