{
  "type": "Feature",
  "properties": {
    "addr:full":"325 Shore Dr Fort Myers FL 33905",
    "addr:housenumber":"325",
    "addr:postcode":"33905",
    "addr:street":"Shore Dr",
    "iso:country":"US",
    "sg:address":"325 Shore Dr",
    "sg:city":"Fort Myers",
    "sg:classifiers":[
        {
            "category":"Retail",
            "subcategory":"Repair Shop",
            "type":"Services"
        }
    ],
    "sg:phone":"+1 239 694 4520",
    "sg:postcode":"33905",
    "sg:province":"FL",
    "wof:name":"Neptune Marine Inc",
    "wof:placetype":"venue"
},
  "geometry": {"coordinates":[-81.805966,26.689188],"type":"Point"}
}