{
  "type": "Feature",
  "properties": {
    "iso:country":"US",
    "sg:address":"220 Bahama St",
    "sg:city":"Venice",
    "sg:classifiers":[
        {
            "category":"Education",
            "subcategory":"School",
            "type":"Public Place"
        }
    ],
    "sg:phone":"+1 941 486 2559",
    "sg:postcode":"34285",
    "sg:province":"FL",
    "sg:tags":[
        "district"
    ],
    "sg:website":"http://www.sarasotamiddleschool.com",
    "wof:name":"Gulf Coast Marine Inst South",
    "wof:placetype":"venue"
},
  "geometry": {"coordinates":[-82.44309199999999,27.097068],"type":"Point"}
}