{
  "type": "Feature",
  "properties": {
    "addr:full":"423 S Scott Ave Sanford FL 32771",
    "addr:housenumber":"423",
    "addr:postcode":"32771",
    "addr:street":"S Scott Ave",
    "iso:country":"US",
    "sg:address":"423 S Scott Ave",
    "sg:city":"Sanford",
    "sg:classifiers":[
        {
            "category":"Real Estate",
            "subcategory":"Real Estate Agent",
            "type":"Services"
        }
    ],
    "sg:phone":"+1 407 323 1515",
    "sg:postcode":"32771",
    "sg:province":"FL",
    "wof:name":"Wisteria Realty Inc",
    "wof:placetype":"venue"
},
  "geometry": {"coordinates":[-81.251419,28.805631],"type":"Point"}
}