{
  "type": "Feature",
  "properties": {
    "addr:full":"1701 Ponce De Leon Blvd Coral Gables FL 33134",
    "addr:housenumber":"1701",
    "addr:postcode":"33134",
    "addr:street":"Ponce De Leon Blvd",
    "iso:country":"US",
    "sg:address":"1701 Ponce De Leon Blvd",
    "sg:city":"Coral Gables",
    "sg:classifiers":[
        {
            "category":"Travel",
            "subcategory":"Travel Agent",
            "type":"Entertainment"
        }
    ],
    "sg:phone":"+1 305 444 4484",
    "sg:postcode":"33134",
    "sg:province":"FL",
    "wof:name":"Traveleaders",
    "wof:placetype":"venue"
},
  "geometry": {"coordinates":[-80.258698,25.756599],"type":"Point"}
}