{
  "type": "Feature",
  "properties": {
    "iso:country":"US",
    "sg:address":"3540 Banks Rd",
    "sg:city":"Pompano Beach",
    "sg:classifiers":[
        {
            "category":"Professional",
            "type":"Services"
        }
    ],
    "sg:phone":"+1 954 969 5124",
    "sg:postcode":"33063",
    "sg:province":"FL",
    "wof:name":"Gilberto Juarez",
    "wof:placetype":"venue"
},
  "geometry": {"coordinates":[-80.194585,26.273536],"type":"Point"}
}