{
  "type": "Feature",
  "properties": {
    "addr:full":"10540 NW 26th St Mia Doral FL 33172",
    "addr:housenumber":"10540",
    "addr:postcode":"33172",
    "addr:street":"Nw 26Th St",
    "iso:country":"US",
    "sg:address":"10540 NW 26th St Mia",
    "sg:city":"Doral",
    "sg:classifiers":[
        {
            "category":"Autos & Motor Vehicles",
            "subcategory":"Automobile Sales",
            "type":"Retail Goods"
        }
    ],
    "sg:phone":"+1 305 599 5237",
    "sg:postcode":"33172",
    "sg:province":"FL",
    "sg:tags":[
        "leasing"
    ],
    "wof:name":"Luxury Leasing",
    "wof:placetype":"venue"
},
  "geometry": {"coordinates":[-80.366985,25.798019],"type":"Point"}
}