{
  "type": "Feature",
  "properties": {
    "iso:country":"US",
    "sg:address":"204 S Dillard St",
    "sg:city":"Winter Garden",
    "sg:classifiers":[
        {
            "category":"Real Estate",
            "subcategory":"Real Estate Agent",
            "type":"Services"
        }
    ],
    "sg:phone":"+1 407 877 9694",
    "sg:postcode":"34787",
    "sg:province":"FL",
    "wof:name":"Property Investment Spec Inc",
    "wof:placetype":"venue"
},
  "geometry": {"coordinates":[-81.58361499999999,28.562097],"type":"Point"}
}