{
  "type": "Feature",
  "properties": {
    "iso:country":"US",
    "sg:address":"8009 S Orange Ave",
    "sg:city":"Orlando",
    "sg:classifiers":[
        {
            "category":"Real Estate",
            "subcategory":"Real Estate Agent",
            "type":"Services"
        }
    ],
    "sg:phone":"+1 407 846 0346",
    "sg:postcode":"32809",
    "sg:province":"FL",
    "sg:tags":[
        "management"
    ],
    "wof:name":"Leland Management Inc",
    "wof:placetype":"venue"
},
  "geometry": {"coordinates":[-81.36431399999999,28.454086],"type":"Point"}
}