{
  "type": "Feature",
  "properties": {
    "iso:country":"US",
    "sg:address":"3498 NE 18th Ave",
    "sg:city":"Fort Lauderdale",
    "sg:classifiers":[
        {
            "category":"Food & Beverages",
            "subcategory":"Specialty",
            "type":"Retail Goods"
        }
    ],
    "sg:phone":"+1 954 561 0295",
    "sg:postcode":"33306",
    "sg:province":"FL",
    "wof:name":"ME Et Moi Inc",
    "wof:placetype":"venue"
},
  "geometry": {"coordinates":[-80.122005,26.170759],"type":"Point"}
}