{
  "type": "Feature",
  "properties": {
    "iso:country":"US",
    "sg:address":"1321 Covey Cir S",
    "sg:city":"Lakeland",
    "sg:classifiers":[
        {
            "category":"Insurance",
            "subcategory":"Insurance Agent",
            "type":"Services"
        }
    ],
    "sg:phone":"+1 863 858 8071",
    "sg:postcode":"33809",
    "sg:province":"FL",
    "wof:name":"William Penn Association",
    "wof:placetype":"venue"
},
  "geometry": {"coordinates":[-81.926484,28.141499],"type":"Point"}
}