{
  "type": "Feature",
  "properties": {
    "addr:full":"4440 Domestic Ave Naples FL 34104",
    "addr:postcode":"4440;34104",
    "addr:street":"Domestic Ave",
    "iso:country":"US",
    "sg:address":"4440 Domestic Ave",
    "sg:city":"Naples",
    "sg:classifiers":[
        {
            "category":"Restaurant",
            "type":"Food & Drink"
        }
    ],
    "sg:phone":"+1 239 649 7499",
    "sg:postcode":"34104",
    "sg:province":"FL",
    "wof:name":"Paloma Blanca Cafe",
    "wof:placetype":"venue"
},
  "geometry": {"coordinates":[-81.757846,26.16245],"type":"Point"}
}