{
  "type": "Feature",
  "properties": {
    "iso:country":"US",
    "sg:address":"6770 102nd Ave",
    "sg:city":"Pinellas Park",
    "sg:classifiers":[
        {
            "category":"Health Services",
            "subcategory":"Nursing And Care Facility",
            "type":"Services"
        }
    ],
    "sg:phone":"+1 727 541 4199",
    "sg:postcode":"33782",
    "sg:province":"FL",
    "sg:tags":[
        "skilled"
    ],
    "wof:name":"Hospice of Florida Suncoast",
    "wof:placetype":"venue"
},
  "geometry": {"coordinates":[-82.731995,27.864639],"type":"Point"}
}