{
  "type": "Feature",
  "properties": {
    "addr:full":"7900 NW 27th Ave. Miami FL 33147",
    "addr:housenumber":"7900",
    "addr:postcode":"33147",
    "addr:street":"Nw 27Th Ave.",
    "iso:country":"US",
    "sg:address":"7900 NW 27th Ave.",
    "sg:city":"Miami",
    "sg:classifiers":[
        {
            "category":"Restaurant",
            "type":"Food & Drink"
        }
    ],
    "sg:postcode":"33147",
    "sg:province":"FL",
    "sg:website":"entenmanns.gwbakeries.com",
    "wof:name":"Entenmann's Outlet Store",
    "wof:placetype":"venue"
},
  "geometry": {"coordinates":[-80.243741,25.848624],"type":"Point"}
}