{
  "type": "Feature",
  "properties": {
    "iso:country":"US",
    "sg:address":"1609 N Dixie Hwy",
    "sg:city":"West Palm Beach",
    "sg:classifiers":[
        {
            "category":"Shopping",
            "subcategory":"Gifts & Souvenirs",
            "type":"Retail Goods"
        }
    ],
    "sg:phone":"+1 561 512 6627",
    "sg:postcode":"33407",
    "sg:province":"FL",
    "sg:tags":[
        "shop"
    ],
    "wof:name":"Kimberly Denney Inc",
    "wof:placetype":"venue"
},
  "geometry": {"coordinates":[-80.053191,26.727252],"type":"Point"}
}