{
  "type": "Feature",
  "properties": {
    "iso:country":"US",
    "sg:address":"900 N Orange Ave",
    "sg:city":"Winter Park",
    "sg:classifiers":[
        {
            "category":"Real Estate",
            "subcategory":"Real Estate Agent",
            "type":"Services"
        }
    ],
    "sg:phone":"+1 407 622 5100",
    "sg:postcode":"32789",
    "sg:province":"FL",
    "sg:website":"www.stirlingrealty.com",
    "wof:name":"Stirling International Realty",
    "wof:placetype":"venue"
},
  "geometry": {"coordinates":[-81.358721,28.591131],"type":"Point"}
}