{
  "type": "Feature",
  "properties": {
    "addr:full":"240 SW 32nd Ct Fort Lauderdale FL 33315",
    "addr:housenumber":"240",
    "addr:postcode":"33315",
    "addr:street":"Sw 32Nd Ct",
    "iso:country":"US",
    "sg:address":"240 SW 32nd Ct",
    "sg:city":"Fort Lauderdale",
    "sg:classifiers":[
        {
            "category":"Wholesale",
            "subcategory":"Hardware",
            "type":"Manufacturing & Wholesale Goods"
        }
    ],
    "sg:phone":"+1 954 463 2288",
    "sg:postcode":"33315",
    "sg:province":"FL",
    "sg:tags":[
        "marine"
    ],
    "sg:website":"www.beardmarine.com",
    "wof:name":"Beard Marine",
    "wof:placetype":"venue"
},
  "geometry": {"coordinates":[-80.142523,26.084309],"type":"Point"}
}