{
  "type": "Feature",
  "properties": {
    "addr:full":"1927 Victoria Ave Fort Myers FL 33901",
    "addr:housenumber":"1927",
    "addr:postcode":"33901",
    "addr:street":"Victoria Ave",
    "iso:country":"US",
    "sg:address":"1927 Victoria Ave",
    "sg:city":"Fort Myers",
    "sg:classifiers":[
        {
            "category":"Organizations",
            "subcategory":"Community Association",
            "type":"Services"
        }
    ],
    "sg:phone":"+1 239 334 0552",
    "sg:postcode":"33901",
    "sg:province":"FL",
    "sg:tags":[
        "club"
    ],
    "wof:name":"Fort Myers Lion Club",
    "wof:placetype":"venue"
},
  "geometry": {"coordinates":[-81.874408,26.637116],"type":"Point"}
}