{
  "type": "Feature",
  "properties": {
    "iso:country":"US",
    "sg:address":"10533 Kitten Trl",
    "sg:city":"Hudson",
    "sg:classifiers":[
        {
            "category":"Building & Trades",
            "subcategory":"Plumbing",
            "type":"Services"
        }
    ],
    "sg:phone":"+1 727 869 6446",
    "sg:postcode":"34669",
    "sg:province":"FL",
    "sg:tags":[
        "plumbing",
        "contractor"
    ],
    "wof:name":"Dolphin Plumbing Contractors",
    "wof:placetype":"venue"
},
  "geometry": {"coordinates":[-82.643382,28.373527],"type":"Point"}
}