{
  "type": "Feature",
  "properties": {
    "iso:country":"US",
    "sg:address":"15401 SW 60th St",
    "sg:city":"Miami",
    "sg:classifiers":[
        {
            "category":"Home & Garden",
            "subcategory":"Home Furnishings",
            "type":"Retail Goods"
        }
    ],
    "sg:phone":"+1 305 382 2120",
    "sg:postcode":"33193",
    "sg:province":"FL",
    "sg:tags":[
        "beveled",
        "glass",
        "ornamental"
    ],
    "wof:name":"Starq 2000",
    "wof:placetype":"venue"
},
  "geometry": {"coordinates":[-80.443986,25.709923],"type":"Point"}
}