{
  "type": "Feature",
  "properties": {
    "iso:country":"US",
    "sg:address":"1352 Aegean Ct",
    "sg:city":"Punta Gorda",
    "sg:classifiers":[
        {
            "category":"Manufacturing",
            "subcategory":"Building Materials",
            "type":"Manufacturing & Wholesale Goods"
        }
    ],
    "sg:phone":"+1 941 625 2316",
    "sg:postcode":"33983",
    "sg:province":"FL",
    "sg:tags":[
        "mfg",
        "wood",
        "kitchen",
        "cabinet"
    ],
    "wof:name":"Cabinet Installation Spc",
    "wof:placetype":"venue"
},
  "geometry": {"coordinates":[-82.027277,27.008152],"type":"Point"}
}