{
  "type": "Feature",
  "properties": {
    "addr:full":"5060 Evinrude Rd Melbourne FL 32934",
    "addr:housenumber":"5060",
    "addr:postcode":"32934",
    "addr:street":"Evinrude Rd",
    "iso:country":"US",
    "sg:address":"5060 Evinrude Rd",
    "sg:city":"Melbourne",
    "sg:classifiers":[
        {
            "category":"Building & Trades",
            "subcategory":"Pest Control",
            "type":"Services"
        }
    ],
    "sg:phone":"+1 321 255 5099",
    "sg:postcode":"32934",
    "sg:province":"FL",
    "wof:name":"Universal Pest Svc",
    "wof:placetype":"venue"
},
  "geometry": {"coordinates":[-80.715993,28.129238],"type":"Point"}
}