{
  "type": "Feature",
  "properties": {
    "iso:country":"US",
    "sg:address":"8890 W Irlo Bronson Memorial Hwy",
    "sg:city":"Kissimmee",
    "sg:classifiers":[
        {
            "category":"Autos & Motor Vehicles",
            "subcategory":"Fuel & Gas Station",
            "type":"Retail Goods"
        },
        {
            "category":"Food & Beverages",
            "subcategory":"Groceries & Convenience Stores",
            "type":"Retail Goods"
        }
    ],
    "sg:phone":"+1 407 390 6124",
    "sg:postcode":"34747",
    "sg:province":"FL",
    "sg:website":"http://www.racetrac.com",
    "wof:name":"RaceTrac",
    "wof:placetype":"venue"
},
  "geometry": {"coordinates":[-81.644614,28.346761],"type":"Point"}
}