{
  "type": "Feature",
  "properties": {
    "addr:full":"14908 N Ola Ave Tampa FL 33613",
    "addr:housenumber":"14908",
    "addr:postcode":"33613",
    "addr:street":"N Ola Ave",
    "iso:country":"US",
    "sg:address":"14908 N Ola Ave",
    "sg:city":"Tampa",
    "sg:classifiers":[
        {
            "category":"Food & Beverages",
            "subcategory":"Groceries & Convenience Stores",
            "type":"Retail Goods"
        }
    ],
    "sg:phone":"+1 813 968 6148",
    "sg:postcode":"33613",
    "sg:province":"FL",
    "wof:name":"Quest Systems LLC",
    "wof:placetype":"venue"
},
  "geometry": {"coordinates":[-82.46374299999999,28.085714],"type":"Point"}
}