{
  "type": "Feature",
  "properties": {
    "iso:country":"US",
    "sg:address":"4740 S Lake Dr",
    "sg:city":"Palm Beach Gardens",
    "sg:classifiers":[
        {
            "category":"Building & Trades",
            "subcategory":"Landscaping Services",
            "type":"Services"
        }
    ],
    "sg:phone":"+1 561 718 1502",
    "sg:postcode":"33435",
    "sg:province":"FL",
    "sg:tags":[
        "landscape"
    ],
    "wof:name":"Brett Armstrong Landscape",
    "wof:placetype":"venue"
},
  "geometry": {"coordinates":[-80.07886499999999,26.486525],"type":"Point"}
}