{
  "type": "Feature",
  "properties": {
    "addr:full":"1035 SE 4 St Gainesville FL 32601",
    "addr:housenumber":"1035;4",
    "addr:postcode":"32601",
    "addr:street":"Se",
    "iso:country":"US",
    "sg:address":"1035 SE 4 St",
    "sg:city":"Gainesville",
    "sg:classifiers":[
        {
            "category":"Manufacturing",
            "subcategory":"Food",
            "type":"Manufacturing & Wholesale Goods"
        }
    ],
    "sg:phone":"+1 352 376 6653",
    "sg:postcode":"32601",
    "sg:province":"FL",
    "sg:tags":[
        "ice"
    ],
    "wof:name":"University Service Ctr",
    "wof:placetype":"venue"
},
  "geometry": {"coordinates":[-82.319256,29.640549],"type":"Point"}
}