{
  "type": "Feature",
  "properties": {
    "iso:country":"US",
    "sg:address":"2333 Seven Springs Blvd",
    "sg:city":"New Port Richey",
    "sg:classifiers":[
        {
            "category":"Personal",
            "subcategory":"Beauty Salon",
            "type":"Services"
        }
    ],
    "sg:phone":"+1 727 375 5025",
    "sg:postcode":"34655",
    "sg:province":"FL",
    "sg:tags":[
        "manicuring"
    ],
    "wof:name":"Zip Nails",
    "wof:placetype":"venue"
},
  "geometry": {"coordinates":[-82.69902399999999,28.192966],"type":"Point"}
}