{
  "type": "Feature",
  "properties": {
    "iso:country":"US",
    "sg:address":"6621 NW 7th Ave",
    "sg:city":"Miami",
    "sg:classifiers":[
        {
            "category":"Food & Beverages",
            "subcategory":"Groceries & Convenience Stores",
            "type":"Retail Goods"
        }
    ],
    "sg:phone":"+1 305 751 1313",
    "sg:postcode":"33150",
    "sg:province":"FL",
    "wof:name":"Family Food & Beverage",
    "wof:placetype":"venue"
},
  "geometry": {"coordinates":[-80.20880099999999,25.8358],"type":"Point"}
}