{
  "type": "Feature",
  "properties": {
    "iso:country":"US",
    "sg:address":"400 Semoran Blvd",
    "sg:city":"Casselberry",
    "sg:classifiers":[
        {
            "category":"Insurance",
            "subcategory":"Insurance Agent",
            "type":"Services"
        }
    ],
    "sg:phone":"+1 407 834 0058",
    "sg:postcode":"32707",
    "sg:province":"FL",
    "wof:name":"Benefit Solutions Inc",
    "wof:placetype":"venue"
},
  "geometry": {"coordinates":[-81.33263599999999,28.65502],"type":"Point"}
}