{
  "type": "Feature",
  "properties": {
    "iso:country":"US",
    "sg:address":"8270 College Pkwy",
    "sg:city":"Fort Myers",
    "sg:classifiers":[
        {
            "category":"Real Estate",
            "subcategory":"Real Estate Agent",
            "type":"Services"
        },
        {
            "category":"Professional",
            "subcategory":"Management & Consulting",
            "type":"Services"
        }
    ],
    "sg:phone":"+1 239 415 7400",
    "sg:postcode":"33919",
    "sg:province":"FL",
    "sg:tags":[
        "buyer",
        "broker"
    ],
    "wof:name":"Management Connection Inc",
    "wof:placetype":"venue"
},
  "geometry": {"coordinates":[-81.895776,26.556712],"type":"Point"}
}