{
  "type": "Feature",
  "properties": {
    "iso:country":"US",
    "sg:address":"1022 Land O Lakes Blvd",
    "sg:city":"Lutz",
    "sg:classifiers":[
        {
            "category":"Insurance",
            "subcategory":"Title Insurance",
            "type":"Services"
        }
    ],
    "sg:phone":"+1 813 948 0361",
    "sg:postcode":"33549",
    "sg:province":"FL",
    "sg:tags":[
        "carrier"
    ],
    "wof:name":"Security Frst Ttle Affltes Inc",
    "wof:placetype":"venue"
},
  "geometry": {"coordinates":[-82.46266300000001,28.174605],"type":"Point"}
}