{
  "type": "Feature",
  "properties": {
    "addr:full":"2910 SE 3rd Ct Ocala FL 34471",
    "addr:housenumber":"2910",
    "addr:postcode":"34471",
    "addr:street":"Se 3Rd Ct",
    "iso:country":"US",
    "sg:address":"2910 SE 3rd Ct",
    "sg:city":"Ocala",
    "sg:classifiers":[
        {
            "category":"Health Services",
            "subcategory":"Medical Lab",
            "type":"Services"
        }
    ],
    "sg:phone":"+1 352 351 9244",
    "sg:postcode":"34471",
    "sg:province":"FL",
    "sg:tags":[
        "laboratory"
    ],
    "sg:website":"www.questdiagnostics.com",
    "wof:name":"Quest Diagnostics Inc",
    "wof:placetype":"venue"
},
  "geometry": {"coordinates":[-82.132622,29.159417],"type":"Point"}
}