{
  "type": "Feature",
  "properties": {
    "addr:full":"100 W Dania Beach Blvd Dania FL 33004",
    "addr:housenumber":"100",
    "addr:postcode":"33004",
    "addr:street":"W Dania Beach Blvd",
    "iso:country":"US",
    "sg:address":"100 W Dania Beach Blvd",
    "sg:city":"Dania",
    "sg:classifiers":[
        {
            "category":"Government",
            "subcategory":"Police Station",
            "type":"Public Place"
        },
        {
            "category":"Government",
            "subcategory":"Office",
            "type":"Public Place"
        }
    ],
    "sg:phone":"+1 954 926 2400",
    "sg:postcode":"33004",
    "sg:province":"FL",
    "sg:tags":[
        "department",
        "parish",
        "government-county"
    ],
    "sg:website":"http://www.sheriff.org",
    "wof:name":"Broward Sheriff's Office - Dania Beach",
    "wof:placetype":"venue"
},
  "geometry": {"coordinates":[-80.14447800000001,26.052271],"type":"Point"}
}