{
  "type": "Feature",
  "properties": {
    "iso:country":"US",
    "sg:address":"318 E Hathaway Ave",
    "sg:city":"Bronson",
    "sg:classifiers":[
        {
            "category":"Personal",
            "subcategory":"Barber",
            "type":"Services"
        }
    ],
    "sg:phone":"+1 352 486 0062",
    "sg:postcode":"32621",
    "sg:province":"FL",
    "wof:name":"County Seat Barber Shop",
    "wof:placetype":"venue"
},
  "geometry": {"coordinates":[-82.6379,29.445607],"type":"Point"}
}