{
  "type": "Feature",
  "properties": {
    "addr:full":"2915 Hillsboro Rd West Palm Beach FL 33405",
    "addr:housenumber":"2915",
    "addr:postcode":"33405",
    "addr:street":"Hillsboro Rd",
    "iso:country":"US",
    "sg:address":"2915 Hillsboro Rd",
    "sg:city":"West Palm Beach",
    "sg:classifiers":[
        {
            "category":"Wholesale",
            "subcategory":"Machinery & Supplies",
            "type":"Manufacturing & Wholesale Goods"
        }
    ],
    "sg:phone":"+1 561 832 3260",
    "sg:postcode":"33405",
    "sg:province":"FL",
    "sg:tags":[
        "food",
        "equipment",
        "c",
        "retail",
        "industry"
    ],
    "wof:name":"M & S Restaurant Equipment Co",
    "wof:placetype":"venue"
},
  "geometry": {"coordinates":[-80.070148,26.688033],"type":"Point"}
}