{
  "type": "Feature",
  "properties": {
    "iso:country":"US",
    "sg:address":"9704 SW 24th St",
    "sg:city":"Miami",
    "sg:classifiers":[
        {
            "category":"Autos & Motor Vehicles",
            "subcategory":"Motorcycle Sales",
            "type":"Retail Goods"
        }
    ],
    "sg:phone":"+1 305 228 7640",
    "sg:postcode":"33165",
    "sg:province":"FL",
    "sg:tags":[
        "scooter"
    ],
    "wof:name":"Right On Track",
    "wof:placetype":"venue"
},
  "geometry": {"coordinates":[-80.352949,25.747119],"type":"Point"}
}