{
  "type": "Feature",
  "properties": {
    "addr:full":"7222 Auburn Ln New Port Richey FL 34654",
    "addr:housenumber":"7222",
    "addr:postcode":"34654",
    "addr:street":"Auburn Ln",
    "iso:country":"US",
    "sg:address":"7222 Auburn Ln",
    "sg:city":"New Port Richey",
    "sg:classifiers":[
        {
            "category":"Professional",
            "subcategory":"Management & Consulting",
            "type":"Services"
        }
    ],
    "sg:phone":"+1 727 849 0977",
    "sg:postcode":"34654",
    "sg:province":"FL",
    "sg:tags":[
        "business"
    ],
    "wof:name":"Data Security Holding Inc",
    "wof:placetype":"venue"
},
  "geometry": {"coordinates":[-82.64904799999999,28.260529],"type":"Point"}
}