{
  "type": "Feature",
  "properties": {
    "iso:country":"US",
    "sg:address":"19721 NE 21st Ct",
    "sg:city":"Miami",
    "sg:classifiers":[
        {
            "category":"Real Estate",
            "subcategory":"Architect",
            "type":"Services"
        }
    ],
    "sg:phone":"+1 305 937 1456",
    "sg:postcode":"33179",
    "sg:province":"FL",
    "wof:name":"Sg 2 Architects",
    "wof:placetype":"venue"
},
  "geometry": {"coordinates":[-80.15830200000001,25.957701],"type":"Point"}
}