{
  "type": "Feature",
  "properties": {
    "addr:full":"2912 Oak Harbor Dr Gulf Breeze FL 32566",
    "addr:housenumber":"2912",
    "addr:postcode":"32566",
    "addr:street":"Oak Harbor Dr",
    "iso:country":"US",
    "sg:address":"2912 Oak Harbor Dr",
    "sg:city":"Gulf Breeze",
    "sg:classifiers":[
        {
            "category":"Real Estate",
            "subcategory":"Real Estate Agent",
            "type":"Services"
        }
    ],
    "sg:phone":"+1 850 939 0387",
    "sg:postcode":"32566",
    "sg:province":"FL",
    "wof:name":"ERA",
    "wof:placetype":"venue"
},
  "geometry": {"coordinates":[-86.94373899999999,30.446991],"type":"Point"}
}