{
  "type": "Feature",
  "properties": {
    "addr:full":"224 Commercial Blvd Fort Lauderdale FL 33308",
    "addr:housenumber":"224",
    "addr:postcode":"33308",
    "addr:street":"Commercial Blvd",
    "iso:country":"US",
    "sg:address":"224 Commercial Blvd",
    "sg:city":"Fort Lauderdale",
    "sg:classifiers":[
        {
            "category":"Professional",
            "subcategory":"Accounting & Tax Preparation",
            "type":"Services"
        }
    ],
    "sg:phone":"+1 954 351 7992",
    "sg:postcode":"33308",
    "sg:province":"FL",
    "wof:name":"Health Care Blling Specialists",
    "wof:placetype":"venue"
},
  "geometry": {"coordinates":[-80.10136799999999,26.189788],"type":"Point"}
}