{
  "type": "Feature",
  "properties": {
    "iso:country":"US",
    "sg:address":"2246 Palm Vista Dr",
    "sg:city":"Apopka",
    "sg:classifiers":[
        {
            "category":"Building & Trades",
            "subcategory":"Construction",
            "type":"Services"
        }
    ],
    "sg:phone":"+1 407 886 8910",
    "sg:postcode":"32712",
    "sg:province":"FL",
    "sg:tags":[
        "home",
        "general",
        "family",
        "contractor"
    ],
    "wof:name":"Alpine-Sun Development Corp",
    "wof:placetype":"venue"
},
  "geometry": {"coordinates":[-81.468485,28.702218],"type":"Point"}
}