{
  "type": "Feature",
  "properties": {
    "addr:full":"408 Casler Ave Clearwater FL 33755",
    "addr:housenumber":"408",
    "addr:postcode":"33755",
    "addr:street":"Casler Ave",
    "iso:country":"US",
    "sg:address":"408 Casler Ave",
    "sg:city":"Clearwater",
    "sg:classifiers":[
        {
            "category":"Retail",
            "subcategory":"Auto Repair",
            "type":"Services"
        }
    ],
    "sg:phone":"+1 727 443 0296",
    "sg:postcode":"33755",
    "sg:province":"FL",
    "sg:tags":[
        "body",
        "painting",
        "repairing",
        "automobile"
    ],
    "wof:name":"Florida Autobody Collision Alliance - Ta",
    "wof:placetype":"venue"
},
  "geometry": {"coordinates":[-82.767539,27.970168],"type":"Point"}
}