{
  "type": "Feature",
  "properties": {
    "iso:country":"US",
    "sg:address":"9407 Eldridge Rd",
    "sg:city":"Spring Hill",
    "sg:classifiers":[
        {
            "category":"Building & Trades",
            "subcategory":"Cleaning & Sanitation",
            "type":"Services"
        }
    ],
    "sg:phone":"+1 352 688 4346",
    "sg:postcode":"34608",
    "sg:province":"FL",
    "sg:tags":[
        "house"
    ],
    "wof:name":"Diamond Home Cleaning",
    "wof:placetype":"venue"
},
  "geometry": {"coordinates":[-82.56545199999999,28.453333],"type":"Point"}
}