{
  "type": "Feature",
  "properties": {
    "iso:country":"US",
    "sg:address":"4604 Andrus Ave",
    "sg:city":"Orlando",
    "sg:classifiers":[
        {
            "category":"Banks & Credit Unions",
            "subcategory":"Bank",
            "type":"Services"
        }
    ],
    "sg:phone":"+1 407 532 3393",
    "sg:postcode":"32804",
    "sg:province":"FL",
    "sg:tags":[
        "loan",
        "real estate"
    ],
    "wof:name":"Priority Mortgage",
    "wof:placetype":"venue"
},
  "geometry": {"coordinates":[-81.40307799999999,28.602256],"type":"Point"}
}