{
  "type": "Feature",
  "properties": {
    "addr:full":"3900 NE 1st Ave Miami FL 33137",
    "addr:housenumber":"3900",
    "addr:postcode":"33137",
    "addr:street":"Ne 1St Ave",
    "iso:country":"US",
    "sg:address":"3900 NE 1st Ave",
    "sg:city":"Miami",
    "sg:classifiers":[
        {
            "category":"Shopping",
            "type":"Retail Goods"
        }
    ],
    "sg:phone":"+1 305 573 7343",
    "sg:postcode":"33137",
    "sg:province":"FL",
    "sg:tags":[
        "art",
        "gallery",
        "dealer"
    ],
    "wof:name":"Lurie Fine Art Galleries",
    "wof:placetype":"venue"
},
  "geometry": {"coordinates":[-80.19342,25.813413],"type":"Point"}
}