{
  "type": "Feature",
  "properties": {
    "addr:full":"821 Chipley Ct Winter Park FL 32792",
    "addr:housenumber":"821",
    "addr:postcode":"32792",
    "addr:street":"Chipley Ct",
    "iso:country":"US",
    "sg:address":"821 Chipley Ct",
    "sg:city":"Winter Park",
    "sg:classifiers":[
        {
            "category":"Real Estate",
            "subcategory":"Real Estate Agent",
            "type":"Services"
        }
    ],
    "sg:phone":"+1 407 679 4662",
    "sg:postcode":"32792",
    "sg:province":"FL",
    "wof:name":"John Mellusi Jr Co",
    "wof:placetype":"venue"
},
  "geometry": {"coordinates":[-81.30340700000001,28.60885],"type":"Point"}
}