{
  "type": "Feature",
  "properties": {
    "addr:full":"3319 N Monroe St Tallahassee FL 32303",
    "addr:housenumber":"3319",
    "addr:postcode":"32303",
    "addr:street":"N Monroe St",
    "iso:country":"US",
    "sg:address":"3319 N Monroe St",
    "sg:city":"Tallahassee",
    "sg:classifiers":[
        {
            "category":"Retail",
            "subcategory":"Animal Services",
            "type":"Services"
        }
    ],
    "sg:phone":"+1 850 562 0184",
    "sg:postcode":"32303",
    "sg:province":"FL",
    "sg:tags":[
        "pet",
        "grooming",
        "washing"
    ],
    "wof:name":"Pampered Poodles & Terriers",
    "wof:placetype":"venue"
},
  "geometry": {"coordinates":[-84.320595,30.488756],"type":"Point"}
}