{
  "type": "Feature",
  "properties": {
    "iso:country":"US",
    "sg:address":"1150 SW Hogan St",
    "sg:city":"Port St Lucie",
    "sg:classifiers":[
        {
            "category":"Wholesale",
            "subcategory":"Construction Materials",
            "type":"Manufacturing & Wholesale Goods"
        }
    ],
    "sg:phone":"+1 772 785 6939",
    "sg:postcode":"34983",
    "sg:province":"FL",
    "sg:tags":[
        "marble"
    ],
    "wof:name":"Cafa Custom Marble Inc",
    "wof:placetype":"venue"
},
  "geometry": {"coordinates":[-80.362137,27.305186],"type":"Point"}
}