{
  "type": "Feature",
  "properties": {
    "addr:full":"6 Canter Ct Ormond Beach FL 32174",
    "addr:housenumber":"6",
    "addr:postcode":"32174",
    "addr:street":"Canter Ct",
    "iso:country":"US",
    "sg:address":"6 Canter Ct",
    "sg:city":"Ormond Beach",
    "sg:classifiers":[
        {
            "category":"Building & Trades",
            "subcategory":"Construction",
            "type":"Services"
        }
    ],
    "sg:phone":"+1 386 299 8230",
    "sg:postcode":"32174",
    "sg:province":"FL",
    "sg:tags":[
        "hanging",
        "contractor"
    ],
    "wof:name":"Fiffe Josue Painting",
    "wof:placetype":"venue"
},
  "geometry": {"coordinates":[-81.13185199999999,29.266154],"type":"Point"}
}