{
  "type": "Feature",
  "properties": {
    "iso:country":"US",
    "sg:address":"2381 Kirkwood Ave",
    "sg:city":"Naples",
    "sg:classifiers":[
        {
            "category":"Retail",
            "subcategory":"Auto Repair",
            "type":"Services"
        }
    ],
    "sg:phone":"+1 239 732 9355",
    "sg:postcode":"34112",
    "sg:province":"FL",
    "sg:tags":[
        "automobile",
        "top",
        "upholstery"
    ],
    "wof:name":"Collier's Finest Custom",
    "wof:placetype":"venue"
},
  "geometry": {"coordinates":[-81.777849,26.137487],"type":"Point"}
}