{
  "type": "Feature",
  "properties": {
    "addr:full":"5490 Pinnacle Ln West Palm Beach FL 33415",
    "addr:housenumber":"5490",
    "addr:postcode":"33415",
    "addr:street":"Pinnacle Ln",
    "iso:country":"US",
    "sg:address":"5490 Pinnacle Ln",
    "sg:city":"West Palm Beach",
    "sg:classifiers":[
        {
            "category":"Building & Trades",
            "subcategory":"Landscaping Services",
            "type":"Services"
        }
    ],
    "sg:phone":"+1 561 616 3275",
    "sg:postcode":"33415",
    "sg:province":"FL",
    "wof:name":"Proud Lawn Care By Prada",
    "wof:placetype":"venue"
},
  "geometry": {"coordinates":[-80.127354,26.676978],"type":"Point"}
}