{
  "type": "Feature",
  "properties": {
    "iso:country":"US",
    "sg:address":"3305 Shoal Line Blvd",
    "sg:city":"Spring Hill",
    "sg:classifiers":[
        {
            "category":"Bars & Pubs",
            "type":"Food & Drink"
        }
    ],
    "sg:phone":"+1 352 596 3558",
    "sg:postcode":"34607",
    "sg:province":"FL",
    "sg:tags":[
        "drinking"
    ],
    "wof:name":"Hernando Hideaway",
    "wof:placetype":"venue"
},
  "geometry": {"coordinates":[-82.650392,28.488221],"type":"Point"}
}