{
  "type": "Feature",
  "properties": {
    "iso:country":"US",
    "sg:address":"10790 Park Blvd",
    "sg:city":"Seminole",
    "sg:classifiers":[
        {
            "category":"Restaurant",
            "type":"Food & Drink"
        }
    ],
    "sg:menulink":"http://www.allmenus.com/fl/boca-ciega/179769-chick-fil-a/menu/",
    "sg:phone":"+1 727 398 0777",
    "sg:postcode":"33772",
    "sg:province":"FL",
    "sg:tags":[
        "wrap",
        "soup",
        "american",
        "sandwich",
        "salad"
    ],
    "wof:name":"Chick-fil-A",
    "wof:placetype":"venue"
},
  "geometry": {"coordinates":[-82.78852999999999,27.839528],"type":"Point"}
}