{
  "type": "Feature",
  "properties": {
    "iso:country":"US",
    "sg:address":"2924 South St",
    "sg:city":"Fort Myers",
    "sg:classifiers":[
        {
            "category":"Building & Trades",
            "subcategory":"Landscaping Services",
            "type":"Services"
        }
    ],
    "sg:phone":"+1 239 337 1648",
    "sg:postcode":"33916",
    "sg:province":"FL",
    "wof:name":"Angelina and Lexo Andres Lawn",
    "wof:placetype":"venue"
},
  "geometry": {"coordinates":[-81.851951,26.629979],"type":"Point"}
}