{
  "type": "Feature",
  "properties": {
    "addr:full":"7012 Rose Ave Orlando FL 32810",
    "addr:housenumber":"7012",
    "addr:postcode":"32810",
    "addr:street":"Rose Ave",
    "iso:country":"US",
    "sg:address":"7012 Rose Ave",
    "sg:city":"Orlando",
    "sg:classifiers":[
        {
            "category":"Building & Trades",
            "subcategory":"Construction",
            "type":"Services"
        }
    ],
    "sg:phone":"+1 407 532 3358",
    "sg:postcode":"32810",
    "sg:province":"FL",
    "sg:tags":[
        "floor",
        "laying",
        "contractor"
    ],
    "wof:name":"Brian Lampro Inc",
    "wof:placetype":"venue"
},
  "geometry": {"coordinates":[-81.442779,28.619082],"type":"Point"}
}