{
  "type": "Feature",
  "properties": {
    "iso:country":"US",
    "sg:address":"721 US Hwy 1",
    "sg:city":"North Palm Beach",
    "sg:classifiers":[
        {
            "category":"Professional",
            "subcategory":"Engineering",
            "type":"Services"
        }
    ],
    "sg:phone":"+1 561 840 7422",
    "sg:postcode":"33408",
    "sg:province":"FL",
    "sg:tags":[
        "engineer"
    ],
    "wof:name":"Aral Consulting Engineers",
    "wof:placetype":"venue"
},
  "geometry": {"coordinates":[-80.059049,26.820399],"type":"Point"}
}