{
  "type": "Feature",
  "properties": {
    "iso:country":"US",
    "sg:address":"4242 Rabbit Pond Rd",
    "sg:city":"Tallahassee",
    "sg:classifiers":[
        {
            "category":"Real Estate",
            "subcategory":"Real Estate Agent",
            "type":"Services"
        }
    ],
    "sg:phone":"+1 850 668 6866",
    "sg:postcode":"32309",
    "sg:province":"FL",
    "wof:name":"Trend Properties Inc",
    "wof:placetype":"venue"
},
  "geometry": {"coordinates":[-84.206211,30.554182],"type":"Point"}
}