{
  "type": "Feature",
  "properties": {
    "iso:country":"US",
    "sg:address":"5301 Conroy Rd",
    "sg:city":"Orlando",
    "sg:classifiers":[
        {
            "category":"Wholesale",
            "subcategory":"Medical Equipment & Supplies",
            "type":"Manufacturing & Wholesale Goods"
        }
    ],
    "sg:phone":"+1 407 420 4745",
    "sg:postcode":"32811",
    "sg:province":"FL",
    "sg:tags":[
        "hospital"
    ],
    "wof:name":"Binson's Hospital Supplies Inc",
    "wof:placetype":"venue"
},
  "geometry": {"coordinates":[-81.452478,28.494416],"type":"Point"}
}