{
  "type": "Feature",
  "properties": {
    "iso:country":"US",
    "sg:address":"1720 Angle Dr",
    "sg:city":"Longwood",
    "sg:classifiers":[
        {
            "category":"Building & Trades",
            "subcategory":"Construction",
            "type":"Services"
        }
    ],
    "sg:phone":"+1 407 688 0844",
    "sg:postcode":"32750",
    "sg:province":"FL",
    "sg:tags":[
        "house"
    ],
    "wof:name":"JKS Screen Builder Factory",
    "wof:placetype":"venue"
},
  "geometry": {"coordinates":[-81.311556,28.730459],"type":"Point"}
}