{
  "type": "Feature",
  "properties": {
    "iso:country":"US",
    "sg:address":"420 7th Ave NE",
    "sg:city":"Ruskin",
    "sg:classifiers":[
        {
            "category":"Farming",
            "subcategory":"Nursery",
            "type":"Manufacturing & Wholesale Goods"
        }
    ],
    "sg:phone":"+1 813 645 2525",
    "sg:postcode":"33570",
    "sg:province":"FL",
    "sg:tags":[
        "commercial"
    ],
    "wof:name":"Hamlin Azalea Specialists",
    "wof:placetype":"venue"
},
  "geometry": {"coordinates":[-82.429614,27.724361],"type":"Point"}
}