{
  "type": "Feature",
  "properties": {
    "iso:country":"US",
    "sg:address":"974 Burntleaf Ln",
    "sg:city":"Tallahassee",
    "sg:classifiers":[
        {
            "category":"Professional",
            "subcategory":"Detective & Security Services",
            "type":"Services"
        }
    ],
    "sg:phone":"+1 850 545 4964",
    "sg:postcode":"32310",
    "sg:province":"FL",
    "sg:tags":[
        "information",
        "bureau"
    ],
    "wof:name":"Diane's Catering Services",
    "wof:placetype":"venue"
},
  "geometry": {"coordinates":[-84.43481300000001,30.434156],"type":"Point"}
}