{
  "type": "Feature",
  "properties": {
    "iso:country":"US",
    "sg:address":"2616 Tamiami Trl",
    "sg:city":"Port Charlotte",
    "sg:classifiers":[
        {
            "category":"Health Services",
            "subcategory":"Medical Lab",
            "type":"Services"
        }
    ],
    "sg:phone":"+1 941 255 3886",
    "sg:postcode":"33952",
    "sg:province":"FL",
    "sg:tags":[
        "laboratory",
        "dental"
    ],
    "wof:name":"Aesthetic Dental Arts Lab",
    "wof:placetype":"venue"
},
  "geometry": {"coordinates":[-82.11360000000001,26.992871],"type":"Point"}
}