{
  "type": "Feature",
  "properties": {
    "addr:full":"4636 SW 75th Ave Miami FL 33155",
    "addr:housenumber":"4636",
    "addr:postcode":"33155",
    "addr:street":"Sw 75Th Ave",
    "iso:country":"US",
    "sg:address":"4636 SW 75th Ave",
    "sg:city":"Miami",
    "sg:classifiers":[
        {
            "category":"Retail",
            "subcategory":"Repair Shop",
            "type":"Services"
        }
    ],
    "sg:phone":"+1 305 261 5060",
    "sg:postcode":"33155",
    "sg:province":"FL",
    "sg:tags":[
        "welding"
    ],
    "wof:name":"Pena General Welding Inc",
    "wof:placetype":"venue"
},
  "geometry": {"coordinates":[-80.316971,25.728649],"type":"Point"}
}