{
  "type": "Feature",
  "properties": {
    "addr:full":"9332 SW 56th St Miami FL 33165",
    "addr:housenumber":"9332",
    "addr:postcode":"33165",
    "addr:street":"Sw 56Th St",
    "iso:country":"US",
    "sg:address":"9332 SW 56th St",
    "sg:city":"Miami",
    "sg:classifiers":[
        {
            "category":"Retail",
            "subcategory":"Laundry & Dry Cleaning",
            "type":"Services"
        }
    ],
    "sg:phone":"+1 305 598 0412",
    "sg:postcode":"33165",
    "sg:province":"FL",
    "sg:tags":[
        "cleaner"
    ],
    "sg:website":"www.dryclean-usa.com",
    "wof:name":"Dryclean USA",
    "wof:placetype":"venue"
},
  "geometry": {"coordinates":[-80.345619,25.716082],"type":"Point"}
}