{
  "type": "Feature",
  "properties": {
    "addr:full":"3745 1st Ave N St Petersburg FL 33713",
    "addr:housenumber":"3745",
    "addr:postcode":"33713",
    "addr:street":"1St Ave N",
    "iso:country":"US",
    "sg:address":"3745 1st Ave N",
    "sg:city":"St Petersburg",
    "sg:classifiers":[
        {
            "category":"Banks & Credit Unions",
            "subcategory":"Investment Brokerage",
            "type":"Services"
        }
    ],
    "sg:phone":"+1 727 321 4400",
    "sg:postcode":"33713",
    "sg:province":"FL",
    "sg:tags":[
        "advisory",
        "financial"
    ],
    "wof:name":"Covenant Financial Solutions",
    "wof:placetype":"venue"
},
  "geometry": {"coordinates":[-82.684298,27.77193],"type":"Point"}
}