{
  "type": "Feature",
  "properties": {
    "iso:country":"US",
    "sg:address":"201 S Ridgewood Ave",
    "sg:city":"Edgewater",
    "sg:classifiers":[
        {
            "category":"Food & Beverages",
            "subcategory":"Bakery",
            "type":"Retail Goods"
        }
    ],
    "sg:phone":"+1 386 409 9800",
    "sg:postcode":"32132",
    "sg:province":"FL",
    "sg:tags":[
        "baker"
    ],
    "wof:name":"Country Nook Bakery",
    "wof:placetype":"venue"
},
  "geometry": {"coordinates":[-80.906913,28.990064],"type":"Point"}
}