{
  "type": "Feature",
  "properties": {
    "iso:country":"US",
    "sg:address":"374 Dragonfly Ln S",
    "sg:city":"Jacksonville",
    "sg:classifiers":[
        {
            "category":"Manufacturing",
            "subcategory":"Toys & Sporting Goods",
            "type":"Manufacturing & Wholesale Goods"
        }
    ],
    "sg:phone":"+1 904 220 6176",
    "sg:postcode":"32225",
    "sg:province":"FL",
    "sg:tags":[
        "mfg"
    ],
    "wof:name":"Dragonfly Custom Fishing Rods",
    "wof:placetype":"venue"
},
  "geometry": {"coordinates":[-81.478582,30.330995],"type":"Point"}
}