{
  "type": "Feature",
  "properties": {
    "iso:country":"US",
    "sg:address":"806 S Douglas Rd",
    "sg:city":"Coral Gables",
    "sg:classifiers":[
        {
            "category":"Real Estate",
            "subcategory":"Real Estate Agent",
            "type":"Services"
        }
    ],
    "sg:phone":"+1 305 774 5889",
    "sg:postcode":"33134",
    "sg:province":"FL",
    "sg:website":"www.prudentialfloridawci.com",
    "wof:name":"Prudential Florida WCI Realty",
    "wof:placetype":"venue"
},
  "geometry": {"coordinates":[-80.255155,25.763102],"type":"Point"}
}