{
  "type": "Feature",
  "properties": {
    "iso:country":"US",
    "sg:address":"601 NW 33rd Ave",
    "sg:city":"Fort Lauderdale",
    "sg:classifiers":[
        {
            "category":"Social Services",
            "subcategory":"Child Care",
            "type":"Services"
        }
    ],
    "sg:phone":"+1 954 581 8251",
    "sg:postcode":"33311",
    "sg:province":"FL",
    "sg:tags":[
        "day"
    ],
    "wof:name":"Baynard Family Inc",
    "wof:placetype":"venue"
},
  "geometry": {"coordinates":[-80.188912,26.129001],"type":"Point"}
}