{
  "type": "Feature",
  "properties": {
    "iso:country":"US",
    "sg:address":"1133 Bal Harbor Blvd",
    "sg:city":"Punta Gorda",
    "sg:classifiers":[
        {
            "category":"Wholesale",
            "subcategory":"Computers",
            "type":"Manufacturing & Wholesale Goods"
        }
    ],
    "sg:phone":"+1 941 766 7444",
    "sg:postcode":"33950",
    "sg:province":"FL",
    "sg:tags":[
        "peripheral",
        "software"
    ],
    "wof:name":"Sb Technologies",
    "wof:placetype":"venue"
},
  "geometry": {"coordinates":[-82.070866,26.910592],"type":"Point"}
}