{
  "type": "Feature",
  "properties": {
    "addr:full":"810 W Mowry Dr Homestead FL 33030",
    "addr:housenumber":"810",
    "addr:postcode":"33030",
    "addr:street":"W Mowry Dr",
    "iso:country":"US",
    "sg:address":"810 W Mowry Dr",
    "sg:city":"Homestead",
    "sg:classifiers":[
        {
            "category":"Social Services",
            "type":"Services"
        }
    ],
    "sg:phone":"+1 305 242 2020",
    "sg:postcode":"33030",
    "sg:province":"FL",
    "wof:name":"Wic Program",
    "wof:placetype":"venue"
},
  "geometry": {"coordinates":[-80.487393,25.469691],"type":"Point"}
}