{
  "type": "Feature",
  "properties": {
    "iso:country":"US",
    "sg:address":"1301 6th Ave W",
    "sg:city":"Bradenton",
    "sg:classifiers":[
        {
            "category":"Professional",
            "type":"Services"
        },
        {
            "category":"Social Services",
            "type":"Services"
        }
    ],
    "sg:phone":"+1 941 747 0889",
    "sg:postcode":"34205",
    "sg:province":"FL",
    "sg:tags":[
        "establishment"
    ],
    "wof:name":"Healthy Families Manatee",
    "wof:placetype":"venue"
},
  "geometry": {"coordinates":[-82.57520100000001,27.494197],"type":"Point"}
}