{
  "type": "Feature",
  "properties": {
    "iso:country":"US",
    "sg:address":"1400 SW 19th St",
    "sg:city":"Boca Raton",
    "sg:classifiers":[
        {
            "category":"Real Estate",
            "subcategory":"Real Estate Agent",
            "type":"Services"
        }
    ],
    "sg:phone":"+1 561 998 1876",
    "sg:postcode":"33486",
    "sg:province":"FL",
    "sg:tags":[
        "property",
        "management"
    ],
    "wof:name":"Ebc 1200 Corporate Place",
    "wof:placetype":"venue"
},
  "geometry": {"coordinates":[-80.11547899999999,26.33111],"type":"Point"}
}