{
  "type": "Feature",
  "properties": {
    "iso:country":"US",
    "sg:address":"614 Pecan Park Rd",
    "sg:city":"Jacksonville",
    "sg:classifiers":[
        {
            "category":"Shopping",
            "subcategory":"Beauty & Cosmetics",
            "type":"Retail Goods"
        }
    ],
    "sg:phone":"+1 904 751 5165",
    "sg:postcode":"32218",
    "sg:province":"FL",
    "sg:tags":[
        "merchandise"
    ],
    "wof:name":"Sweet Success",
    "wof:placetype":"venue"
},
  "geometry": {"coordinates":[-81.636291,30.517515],"type":"Point"}
}