{
  "type": "Feature",
  "properties": {
    "iso:country":"US",
    "sg:address":"11 W 23rd St",
    "sg:city":"Panama City",
    "sg:classifiers":[
        {
            "category":"Health Services",
            "subcategory":"Doctor",
            "type":"Services"
        }
    ],
    "sg:phone":"+1 850 914 0700",
    "sg:postcode":"32405",
    "sg:province":"FL",
    "sg:tags":[
        "physician",
        "surgeon"
    ],
    "wof:name":"Northwest Florida Hematology",
    "wof:placetype":"venue"
},
  "geometry": {"coordinates":[-85.658798,30.189528],"type":"Point"}
}