{
  "type": "Feature",
  "properties": {
    "addr:full":"6001 Lexington Park Orlando FL 32819",
    "addr:housenumber":"6001",
    "addr:postcode":"32819",
    "iso:country":"US",
    "sg:address":"6001 Lexington Park",
    "sg:city":"Orlando",
    "sg:classifiers":[
        {
            "category":"Real Estate",
            "subcategory":"Real Estate Agent",
            "type":"Services"
        }
    ],
    "sg:phone":"+1 407 876 6856",
    "sg:postcode":"32819",
    "sg:province":"FL",
    "wof:name":"Leisure Capital Mgmt Inc",
    "wof:placetype":"venue"
},
  "geometry": {"coordinates":[-81.502511,28.462436],"type":"Point"}
}