{
  "type": "Feature",
  "properties": {
    "iso:country":"US",
    "sg:address":"4360 NW 193rd St",
    "sg:city":"Opa Locka",
    "sg:classifiers":[
        {
            "category":"Professional",
            "type":"Services"
        }
    ],
    "sg:phone":"+1 305 624 9299",
    "sg:postcode":"33055",
    "sg:province":"FL",
    "wof:name":"Rd Brothers Inc",
    "wof:placetype":"venue"
},
  "geometry": {"coordinates":[-80.273375,25.949245],"type":"Point"}
}