{
  "type": "Feature",
  "properties": {
    "addr:full":"3281 Lake Worth Rd Lake Worth FL 33461",
    "addr:housenumber":"3281",
    "addr:postcode":"33461",
    "addr:street":"Lake Worth Rd",
    "iso:country":"US",
    "sg:address":"3281 Lake Worth Rd",
    "sg:city":"Lake Worth",
    "sg:classifiers":[
        {
            "category":"Building & Trades",
            "subcategory":"Construction",
            "type":"Services"
        }
    ],
    "sg:phone":"+1 561 439 3698",
    "sg:postcode":"33461",
    "sg:province":"FL",
    "sg:tags":[
        "roofing",
        "contractor"
    ],
    "wof:name":"South Florida Contractors Inc",
    "wof:placetype":"venue"
},
  "geometry": {"coordinates":[-80.09324599999999,26.617563],"type":"Point"}
}