{
  "type": "Feature",
  "properties": {
    "addr:full":"1701 66th St N St Petersburg FL 33710",
    "addr:housenumber":"1701",
    "addr:postcode":"33710",
    "addr:street":"66Th St N",
    "iso:country":"US",
    "sg:address":"1701 66th St N",
    "sg:city":"St Petersburg",
    "sg:classifiers":[
        {
            "category":"Health Services",
            "subcategory":"Doctor",
            "type":"Services"
        }
    ],
    "sg:phone":"+1 727 381 3535",
    "sg:postcode":"33710",
    "sg:province":"FL",
    "sg:tags":[
        "dentist"
    ],
    "wof:name":"Tague Dental Care",
    "wof:placetype":"venue"
},
  "geometry": {"coordinates":[-82.728369,27.785017],"type":"Point"}
}