{
  "type": "Feature",
  "properties": {
    "addr:full":"1022 Virginia Ave St Cloud FL 34769",
    "addr:housenumber":"1022",
    "addr:postcode":"34769",
    "addr:street":"Virginia Ave",
    "iso:country":"US",
    "sg:address":"1022 Virginia Ave",
    "sg:city":"St Cloud",
    "sg:classifiers":[
        {
            "category":"Education",
            "subcategory":"School",
            "type":"Public Place"
        }
    ],
    "sg:phone":"+1 407 892 8218",
    "sg:postcode":"34769",
    "sg:province":"FL",
    "wof:name":"COPE Ctr",
    "wof:placetype":"venue"
},
  "geometry": {"coordinates":[-81.27569099999999,28.248206],"type":"Point"}
}