{
  "type": "Feature",
  "properties": {
    "iso:country":"US",
    "sg:address":"300 S Canal St",
    "sg:city":"Leesburg",
    "sg:classifiers":[
        {
            "category":"Social Services",
            "type":"Services"
        }
    ],
    "sg:phone":"+1 352 323 8303",
    "sg:postcode":"34748",
    "sg:province":"FL",
    "sg:tags":[
        "organization",
        "welfare"
    ],
    "wof:name":"Children's Advocacy Ctr",
    "wof:placetype":"venue"
},
  "geometry": {"coordinates":[-81.87372499999999,28.807336],"type":"Point"}
}