{
  "type": "Feature",
  "properties": {
    "addr:full":"5010 Central Sarasota Pkwy Sarasota FL 34238",
    "addr:housenumber":"5010",
    "addr:postcode":"34238",
    "addr:street":"Central Sarasota Pkwy",
    "iso:country":"US",
    "sg:address":"5010 Central Sarasota Pkwy",
    "sg:city":"Sarasota",
    "sg:classifiers":[
        {
            "category":"Real Estate",
            "subcategory":"Real Estate Agent",
            "type":"Services"
        },
        {
            "category":"Real Estate",
            "subcategory":"Real Estate Operator",
            "type":"Services"
        }
    ],
    "sg:phone":"+1 941 921 9868",
    "sg:postcode":"34238",
    "sg:province":"FL",
    "sg:tags":[
        "apartment"
    ],
    "wof:name":"Mayfair",
    "wof:placetype":"venue"
},
  "geometry": {"coordinates":[-82.46398600000001,27.221968],"type":"Point"}
}