{
  "type": "Feature",
  "properties": {
    "addr:full":"1351 S Military Trl Deerfield Beach FL 33442",
    "addr:housenumber":"1351",
    "addr:postcode":"33442",
    "addr:street":"S Military Trl",
    "iso:country":"US",
    "sg:address":"1351 S Military Trl",
    "sg:city":"Deerfield Beach",
    "sg:classifiers":[
        {
            "category":"Utilities",
            "subcategory":"Mobile Phone",
            "type":"Services"
        }
    ],
    "sg:phone":"+1 954 481 9990",
    "sg:postcode":"33442",
    "sg:province":"FL",
    "sg:tags":[
        "telephone",
        "cellular"
    ],
    "wof:name":"Cellular Touch",
    "wof:placetype":"venue"
},
  "geometry": {"coordinates":[-80.13457099999999,26.300666],"type":"Point"}
}