{
  "type": "Feature",
  "properties": {
    "addr:full":"1250 N Maitland Ave Maitland FL 32751",
    "addr:housenumber":"1250",
    "addr:postcode":"32751",
    "addr:street":"N Maitland Ave",
    "iso:country":"US",
    "sg:address":"1250 N Maitland Ave",
    "sg:city":"Maitland",
    "sg:classifiers":[
        {
            "category":"Education",
            "subcategory":"School",
            "type":"Public Place"
        }
    ],
    "sg:phone":"+1 407 599 4001",
    "sg:postcode":"32751",
    "sg:province":"FL",
    "sg:website":"www.summitcharter.com",
    "wof:name":"Summit Charter School",
    "wof:placetype":"venue"
},
  "geometry": {"coordinates":[-81.36579399999999,28.644489],"type":"Point"}
}