{
  "type": "Feature",
  "properties": {
    "addr:full":"3650 Spectrum Blvd Tampa FL 33612",
    "addr:housenumber":"3650",
    "addr:postcode":"33612",
    "addr:street":"Spectrum Blvd",
    "iso:country":"US",
    "sg:address":"3650 Spectrum Blvd",
    "sg:city":"Tampa",
    "sg:classifiers":[
        {
            "category":"Manufacturing",
            "subcategory":"Tools & Machinery",
            "type":"Manufacturing & Wholesale Goods"
        }
    ],
    "sg:phone":"+1 813 972 2241",
    "sg:postcode":"33612",
    "sg:province":"FL",
    "sg:tags":[
        "terminal",
        "peripheral",
        "computer",
        "co",
        "mfg"
    ],
    "wof:name":"Microslate USA Inc",
    "wof:placetype":"venue"
},
  "geometry": {"coordinates":[-82.41869699999999,28.056404],"type":"Point"}
}