{
  "type": "Feature",
  "properties": {
    "iso:country":"US",
    "sg:address":"11 Fawn Ln",
    "sg:city":"Shalimar",
    "sg:classifiers":[
        {
            "category":"Education",
            "subcategory":"Special Training",
            "type":"Public Place"
        }
    ],
    "sg:phone":"+1 850 651 0911",
    "sg:postcode":"32579",
    "sg:province":"FL",
    "sg:tags":[
        "tutoring"
    ],
    "wof:name":"Tina Moore Home Tutoring Svc",
    "wof:placetype":"venue"
},
  "geometry": {"coordinates":[-86.570751,30.437387],"type":"Point"}
}