{
  "type": "Feature",
  "properties": {
    "iso:country":"US",
    "sg:address":"912 N 21st St",
    "sg:city":"Fort Pierce",
    "sg:classifiers":[
        {
            "category":"Professional",
            "subcategory":"Management & Consulting",
            "type":"Services"
        }
    ],
    "sg:phone":"+1 772 467 2470",
    "sg:postcode":"34950",
    "sg:province":"FL",
    "sg:tags":[
        "business"
    ],
    "wof:name":"Redon Ent Inc",
    "wof:placetype":"venue"
},
  "geometry": {"coordinates":[-80.345777,27.45738],"type":"Point"}
}