{
  "type": "Feature",
  "properties": {
    "addr:full":"4500 W Shannon Lakes Dr Tallahassee FL 32309",
    "addr:housenumber":"4500",
    "addr:postcode":"32309",
    "addr:street":"W Shannon Lakes Dr",
    "iso:country":"US",
    "sg:address":"4500 W Shannon Lakes Dr",
    "sg:city":"Tallahassee",
    "sg:classifiers":[
        {
            "category":"Recreation",
            "type":"Entertainment"
        }
    ],
    "sg:phone":"+1 850 893 5425",
    "sg:postcode":"32309",
    "sg:province":"FL",
    "sg:tags":[
        "martial",
        "arts",
        "instruction"
    ],
    "sg:website":"www.akskenpo.com",
    "wof:name":"American Karate Studios",
    "wof:placetype":"venue"
},
  "geometry": {"coordinates":[-84.21252699999999,30.536531],"type":"Point"}
}