{
  "type": "Feature",
  "properties": {
    "iso:country":"US",
    "sg:address":"8695 College Pkwy Ste 347",
    "sg:city":"Fort Myers",
    "sg:classifiers":[
        {
            "category":"Professional",
            "subcategory":"Employment Agencies",
            "type":"Services"
        }
    ],
    "sg:phone":"+1 239 277 9675",
    "sg:postcode":"33919",
    "sg:province":"FL",
    "wof:name":"Express Personnel Services",
    "wof:placetype":"venue"
},
  "geometry": {"coordinates":[-81.898903,26.556801],"type":"Point"}
}