{
  "type": "Feature",
  "properties": {
    "iso:country":"US",
    "sg:address":"2450 N West Shore Blvd",
    "sg:city":"Tampa",
    "sg:classifiers":[
        {
            "category":"Airport",
            "type":"Transportation"
        }
    ],
    "sg:phone":"+1 813 876 8874",
    "sg:postcode":"33607",
    "sg:province":"FL",
    "sg:tags":[
        "aircraft",
        "maintenance"
    ],
    "wof:name":"United Beachcraft-Tampa",
    "wof:placetype":"venue"
},
  "geometry": {"coordinates":[-82.523977,27.966877],"type":"Point"}
}