{
  "type": "Feature",
  "properties": {
    "iso:country":"US",
    "sg:address":"606 W Atlantic Ave",
    "sg:city":"Delray Beach",
    "sg:classifiers":[
        {
            "category":"Retail",
            "subcategory":"Funeral Services",
            "type":"Services"
        }
    ],
    "sg:phone":"+1 561 265 0622",
    "sg:postcode":"33444",
    "sg:province":"FL",
    "sg:tags":[
        "director"
    ],
    "wof:name":"Shuler's Memorial Chapel Inc",
    "wof:placetype":"venue"
},
  "geometry": {"coordinates":[-80.07963700000001,26.461539],"type":"Point"}
}