{
  "type": "Feature",
  "properties": {
    "addr:full":"291 35th Ave NE Naples FL 34120",
    "addr:housenumber":"291",
    "addr:postcode":"34120",
    "addr:street":"35Th Ave Ne",
    "iso:country":"US",
    "sg:address":"291 35th Ave NE",
    "sg:city":"Naples",
    "sg:classifiers":[
        {
            "category":"Building & Trades",
            "subcategory":"Cleaning & Sanitation",
            "type":"Services"
        }
    ],
    "sg:phone":"+1 239 354 3688",
    "sg:postcode":"34120",
    "sg:province":"FL",
    "sg:tags":[
        "house"
    ],
    "wof:name":"A-Action Cleaning Svc Inc",
    "wof:placetype":"venue"
},
  "geometry": {"coordinates":[-81.600515,26.297512],"type":"Point"}
}