{
  "type": "Feature",
  "properties": {
    "iso:country":"US",
    "sg:address":"7448 Aloma Ave",
    "sg:city":"Winter Park",
    "sg:classifiers":[
        {
            "category":"Wholesale",
            "subcategory":"Apparel",
            "type":"Manufacturing & Wholesale Goods"
        }
    ],
    "sg:phone":"+1 407 678 0445",
    "sg:postcode":"32792",
    "sg:province":"FL",
    "sg:tags":[
        "clothing"
    ],
    "wof:name":"Scarlet Ribbons",
    "wof:placetype":"venue"
},
  "geometry": {"coordinates":[-81.28668,28.609569],"type":"Point"}
}