{
  "type": "Feature",
  "properties": {
    "iso:country":"US",
    "sg:address":"310 Polk Dr",
    "sg:city":"Tallahassee",
    "sg:classifiers":[
        {
            "category":"Home & Garden",
            "subcategory":"Furniture",
            "type":"Retail Goods"
        }
    ],
    "sg:phone":"+1 850 656 1869",
    "sg:postcode":"32301",
    "sg:province":"FL",
    "wof:name":"Beautiful Discount Bedding Ctr",
    "wof:placetype":"venue"
},
  "geometry": {"coordinates":[-84.28001500000001,30.413304],"type":"Point"}
}