{
  "type": "Feature",
  "properties": {
    "iso:country":"US",
    "sg:address":"4090 E Jessie Ln",
    "sg:city":"Inverness",
    "sg:classifiers":[
        {
            "category":"Building & Trades",
            "subcategory":"Construction",
            "type":"Services"
        }
    ],
    "sg:phone":"+1 352 344 9501",
    "sg:postcode":"34453",
    "sg:province":"FL",
    "sg:tags":[
        "contractor"
    ],
    "wof:name":"Techniques Plst & Wall Systems",
    "wof:placetype":"venue"
},
  "geometry": {"coordinates":[-82.367997,28.87325],"type":"Point"}
}