{
  "type": "Feature",
  "properties": {
    "iso:country":"US",
    "sg:address":"551 Health Blvd",
    "sg:city":"Daytona Beach",
    "sg:classifiers":[
        {
            "category":"Health Services",
            "subcategory":"Doctor",
            "type":"Services"
        }
    ],
    "sg:phone":"+1 386 323 7558",
    "sg:postcode":"32114",
    "sg:province":"FL",
    "sg:tags":[
        "physician",
        "surgeon"
    ],
    "wof:name":"Va Outpatient Clinic",
    "wof:placetype":"venue"
},
  "geometry": {"coordinates":[-81.061303,29.20815],"type":"Point"}
}