{
  "type": "Feature",
  "properties": {
    "iso:country":"US",
    "sg:address":"9100 NW 97th Ter",
    "sg:city":"Medley",
    "sg:classifiers":[
        {
            "category":"Building & Trades",
            "subcategory":"Equipment Rental",
            "type":"Services"
        }
    ],
    "sg:phone":"+1 877 349 2742",
    "sg:postcode":"33178",
    "sg:province":"FL",
    "sg:tags":[
        "conditioning-emergency",
        "air"
    ],
    "wof:name":"Aggreko",
    "wof:placetype":"venue"
},
  "geometry": {"coordinates":[-80.345742,25.86229],"type":"Point"}
}