{
  "type": "Feature",
  "properties": {
    "addr:full":"1200 S International Pkwy Lake Mary FL 32746",
    "addr:housenumber":"1200",
    "addr:postcode":"32746",
    "addr:street":"S International Pkwy",
    "iso:country":"US",
    "sg:address":"1200 S International Pkwy",
    "sg:city":"Lake Mary",
    "sg:classifiers":[
        {
            "category":"Banks & Credit Unions",
            "subcategory":"Bank",
            "type":"Services"
        }
    ],
    "sg:phone":"+1 407 771 0097",
    "sg:postcode":"32746",
    "sg:province":"FL",
    "wof:name":"Cnlbank",
    "wof:placetype":"venue"
},
  "geometry": {"coordinates":[-81.344398,28.7675],"type":"Point"}
}