{
  "type": "Feature",
  "properties": {
    "addr:full":"11008 Riverside Rd Leesburg FL 34788",
    "addr:housenumber":"11008",
    "addr:postcode":"34788",
    "addr:street":"Riverside Rd",
    "iso:country":"US",
    "sg:address":"11008 Riverside Rd",
    "sg:city":"Leesburg",
    "sg:classifiers":[
        {
            "category":"Wholesale",
            "subcategory":"Non-durable Goods",
            "type":"Manufacturing & Wholesale Goods"
        }
    ],
    "sg:phone":"+1 352 365 9019",
    "sg:postcode":"34788",
    "sg:province":"FL",
    "wof:name":"Nicole White",
    "wof:placetype":"venue"
},
  "geometry": {"coordinates":[-81.771992,28.859532],"type":"Point"}
}