{
  "type": "Feature",
  "properties": {
    "iso:country":"US",
    "sg:address":"5949 Approach Rd",
    "sg:city":"Sarasota",
    "sg:classifiers":[
        {
            "category":"Building & Trades",
            "subcategory":"Construction",
            "type":"Services"
        }
    ],
    "sg:phone":"+1 941 926 7825",
    "sg:postcode":"34238",
    "sg:province":"FL",
    "sg:tags":[
        "residential"
    ],
    "wof:name":"Kate M Development",
    "wof:placetype":"venue"
},
  "geometry": {"coordinates":[-82.455969,27.26592],"type":"Point"}
}