{
  "type": "Feature",
  "properties": {
    "iso:country":"US",
    "sg:address":"4029 Radnor Pl",
    "sg:city":"Sarasota",
    "sg:classifiers":[
        {
            "category":"Professional",
            "type":"Services"
        }
    ],
    "sg:phone":"+1 941 371 8033",
    "sg:postcode":"34233",
    "sg:province":"FL",
    "wof:name":"Scott T Snow",
    "wof:placetype":"venue"
},
  "geometry": {"coordinates":[-82.485998,27.296136],"type":"Point"}
}