{
  "type": "Feature",
  "properties": {
    "addr:full":"1762 N Clara Ave De Land FL 32720",
    "addr:housenumber":"1762",
    "addr:postcode":"32720",
    "addr:street":"N Clara Ave",
    "iso:country":"US",
    "sg:address":"1762 N Clara Ave",
    "sg:city":"De Land",
    "sg:classifiers":[
        {
            "category":"Building & Trades",
            "subcategory":"Landscaping Services",
            "type":"Services"
        }
    ],
    "sg:phone":"+1 386 748 3581",
    "sg:postcode":"32720",
    "sg:province":"FL",
    "wof:name":"Felix Berriozabal",
    "wof:placetype":"venue"
},
  "geometry": {"coordinates":[-81.308819,29.068412],"type":"Point"}
}