{
  "type": "Feature",
  "properties": {
    "addr:full":"540 N Dixie Fwy New Smyrna Beach FL 32168",
    "addr:housenumber":"540",
    "addr:postcode":"32168",
    "addr:street":"N Dixie Fwy",
    "iso:country":"US",
    "sg:address":"540 N Dixie Fwy",
    "sg:city":"New Smyrna Beach",
    "sg:classifiers":[
        {
            "category":"Organizations",
            "subcategory":"Religious Organization",
            "type":"Services"
        }
    ],
    "sg:phone":"+1 386 426 8240",
    "sg:postcode":"32168",
    "sg:province":"FL",
    "sg:tags":[
        "church"
    ],
    "sg:website":"www.locec.com",
    "wof:name":"Light Of Calvary Church",
    "wof:placetype":"venue"
},
  "geometry": {"coordinates":[-80.928675,29.030286],"type":"Point"}
}