{
  "type": "Feature",
  "properties": {
    "addr:full":"4251 Smith Ryals Rd Plant City FL 33567",
    "addr:housenumber":"4251",
    "addr:postcode":"33567",
    "addr:street":"Smith Ryals Rd",
    "iso:country":"US",
    "sg:address":"4251 Smith Ryals Rd",
    "sg:city":"Plant City",
    "sg:classifiers":[
        {
            "category":"Wholesale",
            "subcategory":"Non-durable Goods",
            "type":"Manufacturing & Wholesale Goods"
        }
    ],
    "sg:phone":"+1 813 478 9191",
    "sg:postcode":"33567",
    "sg:province":"FL",
    "sg:tags":[
        "advertising"
    ],
    "wof:name":"Barbara Powers Promotional",
    "wof:placetype":"venue"
},
  "geometry": {"coordinates":[-82.08859699999999,27.954734],"type":"Point"}
}