{
  "type": "Feature",
  "properties": {
    "iso:country":"US",
    "sg:address":"5301 NE 40 Ter",
    "sg:city":"Gainesville",
    "sg:classifiers":[
        {
            "category":"Education",
            "subcategory":"Vocational School",
            "type":"Public Place"
        }
    ],
    "sg:phone":"+1 352 377 2555",
    "sg:postcode":"32609",
    "sg:province":"FL",
    "wof:name":"Gainesville Job Corps Ctr",
    "wof:placetype":"venue"
},
  "geometry": {"coordinates":[-82.27427299999999,29.704131],"type":"Point"}
}