{
  "type": "Feature",
  "properties": {
    "addr:full":"1405 NE 129th St North Miami FL 33161",
    "addr:housenumber":"1405",
    "addr:postcode":"33161",
    "addr:street":"Ne 129Th St",
    "iso:country":"US",
    "sg:address":"1405 NE 129th St",
    "sg:city":"North Miami",
    "sg:classifiers":[
        {
            "category":"Retail",
            "subcategory":"Auto Repair",
            "type":"Services"
        }
    ],
    "sg:phone":"+1 305 892 1771",
    "sg:postcode":"33161",
    "sg:province":"FL",
    "sg:tags":[
        "body",
        "shop"
    ],
    "wof:name":"13 Stars Inc Paint & Body Shop",
    "wof:placetype":"venue"
},
  "geometry": {"coordinates":[-80.170303,25.894699],"type":"Point"}
}