{
  "type": "Feature",
  "properties": {
    "iso:country":"US",
    "sg:address":"421 East Ln",
    "sg:city":"Sanford",
    "sg:classifiers":[
        {
            "category":"Building & Trades",
            "subcategory":"Construction",
            "type":"Services"
        }
    ],
    "sg:phone":"+1 407 323 7817",
    "sg:postcode":"32771",
    "sg:province":"FL",
    "sg:tags":[
        "house",
        "builder",
        "home"
    ],
    "wof:name":"Regency Construction Corp",
    "wof:placetype":"venue"
},
  "geometry": {"coordinates":[-81.352041,28.80612],"type":"Point"}
}