{
  "type": "Feature",
  "properties": {
    "iso:country":"US",
    "sg:address":"2060 51st St",
    "sg:city":"Sarasota",
    "sg:classifiers":[
        {
            "category":"Building & Trades",
            "subcategory":"Construction",
            "type":"Services"
        }
    ],
    "sg:phone":"+1 941 925 3096",
    "sg:postcode":"34234",
    "sg:province":"FL",
    "sg:tags":[
        "coping",
        "plastering",
        "tiling",
        "pool",
        "swimming"
    ],
    "wof:name":"Britewater Swimming Pool",
    "wof:placetype":"venue"
},
  "geometry": {"coordinates":[-82.529195,27.377914],"type":"Point"}
}