{
  "type": "Feature",
  "properties": {
    "iso:country":"US",
    "sg:address":"8032 NW 66th St",
    "sg:city":"Miami",
    "sg:classifiers":[
        {
            "category":"Home & Garden",
            "subcategory":"Home Furnishings",
            "type":"Retail Goods"
        }
    ],
    "sg:phone":"+1 305 436 1174",
    "sg:postcode":"33166",
    "sg:province":"FL",
    "wof:name":"ABS Towels Inc",
    "wof:placetype":"venue"
},
  "geometry": {"coordinates":[-80.326942,25.83341],"type":"Point"}
}