{
  "type": "Feature",
  "properties": {
    "iso:country":"US",
    "sg:address":"12 W University Ave",
    "sg:city":"Gainesville",
    "sg:classifiers":[
        {
            "category":"Organizations",
            "subcategory":"Community Association",
            "type":"Services"
        }
    ],
    "sg:phone":"+1 352 373 1078",
    "sg:postcode":"32601",
    "sg:province":"FL",
    "sg:tags":[
        "environmental",
        "org"
    ],
    "wof:name":"Alachua Conservation Trust",
    "wof:placetype":"venue"
},
  "geometry": {"coordinates":[-82.325761,29.652046],"type":"Point"}
}