{
  "type": "Feature",
  "properties": {
    "addr:full":"7701 SW 78th St Miami FL 33143",
    "addr:housenumber":"7701",
    "addr:postcode":"33143",
    "addr:street":"Sw 78Th St",
    "iso:country":"US",
    "sg:address":"7701 SW 78th St",
    "sg:city":"Miami",
    "sg:classifiers":[
        {
            "category":"Banks & Credit Unions",
            "subcategory":"Bank",
            "type":"Services"
        }
    ],
    "sg:phone":"+1 305 271 8483",
    "sg:postcode":"33143",
    "sg:province":"FL",
    "sg:tags":[
        "federal",
        "agency"
    ],
    "wof:name":"Spicer Export Co Inc",
    "wof:placetype":"venue"
},
  "geometry": {"coordinates":[-80.320365,25.69743],"type":"Point"}
}