{
  "type": "Feature",
  "properties": {
    "iso:country":"US",
    "sg:address":"301 NE 38th St",
    "sg:city":"Fort Lauderdale",
    "sg:classifiers":[
        {
            "category":"Government",
            "subcategory":"Police Station",
            "type":"Public Place"
        }
    ],
    "sg:phone":"+1 954 461 6114",
    "sg:postcode":"33334",
    "sg:province":"FL",
    "sg:tags":[
        "fire",
        "city",
        "department",
        "rescue"
    ],
    "wof:name":"City Fire Rescue Dept",
    "wof:placetype":"venue"
},
  "geometry": {"coordinates":[-80.141542,26.174038],"type":"Point"}
}