{
  "type": "Feature",
  "properties": {
    "iso:country":"US",
    "sg:address":"18667 SW 107th Ave",
    "sg:city":"Cutler Bay",
    "sg:classifiers":[
        {
            "category":"Building & Trades",
            "subcategory":"Locksmith",
            "type":"Services"
        }
    ],
    "sg:phone":"+1 786 581 2375",
    "sg:postcode":"33157",
    "sg:province":"FL",
    "sg:tags":[
        "key"
    ],
    "wof:name":"Always Available 24 Hour Emergency Locksmith",
    "wof:placetype":"venue"
},
  "geometry": {"coordinates":[-80.364195,25.594753],"type":"Point"}
}