{
  "type": "Feature",
  "properties": {
    "iso:country":"US",
    "sg:address":"4301 Honeysuckle Ave",
    "sg:city":"Palm Beach Gardens",
    "sg:classifiers":[
        {
            "category":"Building & Trades",
            "subcategory":"Landscaping Services",
            "type":"Services"
        }
    ],
    "sg:phone":"+1 561 624 3215",
    "sg:postcode":"33410",
    "sg:province":"FL",
    "wof:name":"Absolute Lawn Landscape",
    "wof:placetype":"venue"
},
  "geometry": {"coordinates":[-80.103082,26.819353],"type":"Point"}
}