{
  "type": "Feature",
  "properties": {
    "iso:country":"US",
    "sg:address":"3039 11th Ave N",
    "sg:city":"Saint Petersburg",
    "sg:classifiers":[
        {
            "category":"Building & Trades",
            "subcategory":"Pest Control",
            "type":"Services"
        }
    ],
    "sg:phone":"+1 727 321 7482",
    "sg:postcode":"33713",
    "sg:province":"FL",
    "wof:name":"Billings Pest Svcs",
    "wof:placetype":"venue"
},
  "geometry": {"coordinates":[-82.67419,27.782891],"type":"Point"}
}