{
  "type": "Feature",
  "properties": {
    "addr:full":"4884 NW 97th Pl Miami FL 33178",
    "addr:housenumber":"4884",
    "addr:postcode":"33178",
    "addr:street":"Nw 97Th Pl",
    "iso:country":"US",
    "sg:address":"4884 NW 97th Pl",
    "sg:city":"Miami",
    "sg:classifiers":[
        {
            "category":"Freight",
            "type":"Transportation"
        }
    ],
    "sg:phone":"+1 305 477 8924",
    "sg:postcode":"33178",
    "sg:province":"FL",
    "wof:name":"Ruiz Logistics International I",
    "wof:placetype":"venue"
},
  "geometry": {"coordinates":[-80.35538,25.818141],"type":"Point"}
}