{
  "type": "Feature",
  "properties": {
    "addr:full":"2035 NE 151st St Miami FL 33162",
    "addr:housenumber":"2035",
    "addr:postcode":"33162",
    "addr:street":"Ne 151St St",
    "iso:country":"US",
    "sg:address":"2035 NE 151st St",
    "sg:city":"Miami",
    "sg:classifiers":[
        {
            "category":"Manufacturing",
            "subcategory":"Apparel",
            "type":"Manufacturing & Wholesale Goods"
        }
    ],
    "sg:phone":"+1 305 354 7034",
    "sg:postcode":"33162",
    "sg:province":"FL",
    "sg:tags":[
        "manufacture",
        "draperies",
        "product",
        "quilted",
        "bed",
        "spread",
        "w",
        "shades-wholesale",
        "curtain",
        "drapery",
        "manufacturer"
    ],
    "wof:name":"Uffner Textile Corp",
    "wof:placetype":"venue"
},
  "geometry": {"coordinates":[-80.159409,25.914961],"type":"Point"}
}