{
  "type": "Feature",
  "properties": {
    "addr:full":"6800 SW 40th St, # 642 Miami FL 33155",
    "addr:housenumber":"6800",
    "addr:postcode":"33155",
    "addr:street":"Sw 40Th St # 642",
    "iso:country":"US",
    "sg:address":"6800 SW 40th St, # 642",
    "sg:city":"Miami",
    "sg:classifiers":[
        {
            "category":"Personal",
            "type":"Services"
        }
    ],
    "sg:phone":"+1 866 920 8009",
    "sg:postcode":"33155",
    "sg:province":"FL",
    "sg:tags":[
        "shopping"
    ],
    "sg:website":"www.shopperselect.com",
    "wof:name":"Shopper Select",
    "wof:placetype":"venue"
},
  "geometry": {"coordinates":[-80.30502199999999,25.733249],"type":"Point"}
}