{
  "type": "Feature",
  "properties": {
    "iso:country":"US",
    "sg:address":"4712 W Concord Ave",
    "sg:city":"Orlando",
    "sg:classifiers":[
        {
            "category":"Retail",
            "subcategory":"Auto Repair",
            "type":"Services"
        }
    ],
    "sg:phone":"+1 321 689 0545",
    "sg:postcode":"32808",
    "sg:province":"FL",
    "sg:tags":[
        "general"
    ],
    "wof:name":"Deltech Auto",
    "wof:placetype":"venue"
},
  "geometry": {"coordinates":[-81.441163,28.550656],"type":"Point"}
}