{
  "type": "Feature",
  "properties": {
    "iso:country":"US",
    "sg:address":"2426 Sweetwater Country Club Dr",
    "sg:city":"Apopka",
    "sg:classifiers":[
        {
            "category":"Professional",
            "subcategory":"Computer Services",
            "type":"Services"
        }
    ],
    "sg:phone":"+1 407 880 2310",
    "sg:postcode":"32712",
    "sg:province":"FL",
    "sg:tags":[
        "consulting"
    ],
    "wof:name":"Ronald H Rovig & Co Inc",
    "wof:placetype":"venue"
},
  "geometry": {"coordinates":[-81.464522,28.704422],"type":"Point"}
}