{
  "type": "Feature",
  "properties": {
    "iso:country":"US",
    "sg:address":"825 Clearwater Largo Rd N",
    "sg:city":"Largo",
    "sg:classifiers":[
        {
            "category":"Shopping",
            "type":"Retail Goods"
        }
    ],
    "sg:phone":"+1 727 461 5278",
    "sg:postcode":"33770",
    "sg:province":"FL",
    "sg:tags":[
        "merchandise"
    ],
    "wof:name":"KAST Orthotics & Prosthetics",
    "wof:placetype":"venue"
},
  "geometry": {"coordinates":[-82.796339,27.924846],"type":"Point"}
}