{
  "type": "Feature",
  "properties": {
    "iso:country":"US",
    "sg:address":"15249 Brookridge Blvd",
    "sg:city":"Brooksville",
    "sg:classifiers":[
        {
            "category":"Building & Trades",
            "subcategory":"Cleaning & Sanitation",
            "type":"Services"
        }
    ],
    "sg:phone":"+1 352 592 4786",
    "sg:postcode":"34613",
    "sg:province":"FL",
    "sg:tags":[
        "janitor"
    ],
    "wof:name":"Hernando Beach Cleaning",
    "wof:placetype":"venue"
},
  "geometry": {"coordinates":[-82.488688,28.548464],"type":"Point"}
}