{
  "type": "Feature",
  "properties": {
    "iso:country":"US",
    "sg:address":"19161 Mystic Pointe Dr",
    "sg:city":"Aventura",
    "sg:classifiers":[
        {
            "category":"Organizations",
            "subcategory":"Membership Organization",
            "type":"Services"
        }
    ],
    "sg:phone":"+1 305 932 5895",
    "sg:postcode":"33180",
    "sg:province":"FL",
    "sg:tags":[
        "athletic"
    ],
    "wof:name":"Mystic Pointe Tennis Club",
    "wof:placetype":"venue"
},
  "geometry": {"coordinates":[-80.128122,25.953915],"type":"Point"}
}