{
  "type": "Feature",
  "properties": {
    "iso:country":"US",
    "sg:address":"25 Old Kings Rd N",
    "sg:city":"Palm Coast",
    "sg:classifiers":[
        {
            "category":"Real Estate",
            "subcategory":"Real Estate Agent",
            "type":"Services"
        }
    ],
    "sg:phone":"+1 386 447 0200",
    "sg:postcode":"32137",
    "sg:province":"FL",
    "wof:name":"Accord Realty Inc",
    "wof:placetype":"venue"
},
  "geometry": {"coordinates":[-81.232871,29.582909],"type":"Point"}
}