{
  "type": "Feature",
  "properties": {
    "iso:country":"US",
    "sg:address":"2192 W C 48",
    "sg:city":"Bushnell",
    "sg:classifiers":[
        {
            "category":"Autos & Motor Vehicles",
            "subcategory":"Fuel & Gas Station",
            "type":"Retail Goods"
        },
        {
            "category":"Food & Beverages",
            "subcategory":"Groceries & Convenience Stores",
            "type":"Retail Goods"
        }
    ],
    "sg:phone":"+1 352 793 1295",
    "sg:postcode":"33513",
    "sg:province":"FL",
    "wof:name":"Saint George Citgo Incorporated",
    "wof:placetype":"venue"
},
  "geometry": {"coordinates":[-82.137913,28.668639],"type":"Point"}
}