{
  "type": "Feature",
  "properties": {
    "addr:full":"3990 NW 88th Ave Fort Lauderdale FL 33351",
    "addr:housenumber":"3990",
    "addr:postcode":"33351",
    "addr:street":"Nw 88Th Ave",
    "iso:country":"US",
    "sg:address":"3990 NW 88th Ave",
    "sg:city":"Fort Lauderdale",
    "sg:classifiers":[
        {
            "category":"Home & Garden",
            "subcategory":"Building Materials",
            "type":"Retail Goods"
        }
    ],
    "sg:phone":"+1 954 741 3296",
    "sg:postcode":"33351",
    "sg:province":"FL",
    "wof:name":"Artesanias Sand & Glass Inc",
    "wof:placetype":"venue"
},
  "geometry": {"coordinates":[-80.267617,26.174134],"type":"Point"}
}