{
  "type": "Feature",
  "properties": {
    "iso:country":"US",
    "sg:address":"6006 N 42nd St",
    "sg:city":"Tampa",
    "sg:classifiers":[
        {
            "category":"Organizations",
            "subcategory":"Religious Organization",
            "type":"Services"
        }
    ],
    "sg:phone":"+1 813 626 5710",
    "sg:postcode":"33610",
    "sg:province":"FL",
    "sg:tags":[
        "clergy"
    ],
    "wof:name":"Jordan Jacob Rev",
    "wof:placetype":"venue"
},
  "geometry": {"coordinates":[-82.412132,28.001244],"type":"Point"}
}