{
  "type": "Feature",
  "properties": {
    "iso:country":"US",
    "sg:address":"6108 Suntan Cir",
    "sg:city":"Pensacola",
    "sg:classifiers":[
        {
            "category":"Personal",
            "subcategory":"Beauty Salon",
            "type":"Services"
        }
    ],
    "sg:phone":"+1 850 458 7944",
    "sg:postcode":"32526",
    "sg:province":"FL",
    "wof:name":"Salon Royale",
    "wof:placetype":"venue"
},
  "geometry": {"coordinates":[-87.327682,30.462181],"type":"Point"}
}