{
  "type": "Feature",
  "properties": {
    "addr:full":"160 NW 73rd St Miami FL 33150",
    "addr:housenumber":"160",
    "addr:postcode":"33150",
    "addr:street":"Nw 73Rd St",
    "iso:country":"US",
    "sg:address":"160 NW 73rd St",
    "sg:city":"Miami",
    "sg:classifiers":[
        {
            "category":"Utilities",
            "subcategory":"Electric",
            "type":"Services"
        }
    ],
    "sg:phone":"+1 305 758 5041",
    "sg:postcode":"33150",
    "sg:province":"FL",
    "sg:tags":[
        "equipment",
        "supplies-repair",
        "electronic",
        "equipment-repair"
    ],
    "sg:website":"http://www.marinebatteries.com",
    "wof:name":"D C Battery Specialists",
    "wof:placetype":"venue"
},
  "geometry": {"coordinates":[-80.20038599999999,25.842337],"type":"Point"}
}