{
  "type": "Feature",
  "properties": {
    "iso:country":"US",
    "sg:address":"7703 Dumaine Ct",
    "sg:city":"Tampa",
    "sg:classifiers":[
        {
            "category":"Social Services",
            "subcategory":"Child Care",
            "type":"Services"
        }
    ],
    "sg:phone":"+1 813 987 9757",
    "sg:postcode":"33637",
    "sg:province":"FL",
    "wof:name":"Jennings Family Day",
    "wof:placetype":"venue"
},
  "geometry": {"coordinates":[-82.36446100000001,28.018094],"type":"Point"}
}