{
  "type": "Feature",
  "properties": {
    "iso:country":"US",
    "sg:address":"734 S Dale Mabry Hwy",
    "sg:city":"Tampa",
    "sg:classifiers":[
        {
            "category":"Travel",
            "subcategory":"Hotels & Motels",
            "type":"Entertainment"
        }
    ],
    "sg:phone":"+1 877 574 2464",
    "sg:postcode":"33609",
    "sg:province":"FL",
    "sg:tags":[
        "operation"
    ],
    "sg:website":"http://book.bestwestern.com/bestwestern/priceAvail.do?propertyCode=10306&cm_mmc=IYP-_-YP-_-property-_-10306",
    "wof:name":"Best Western Tampa",
    "wof:placetype":"venue"
},
  "geometry": {"coordinates":[-82.505748,27.93646],"type":"Point"}
}