{
  "type": "Feature",
  "properties": {
    "iso:country":"US",
    "sg:address":"5315 E Big Buck Ct",
    "sg:city":"Inverness",
    "sg:classifiers":[
        {
            "category":"Professional",
            "subcategory":"Secretarial Services",
            "type":"Services"
        },
        {
            "category":"Professional",
            "subcategory":"Employment Agencies",
            "type":"Services"
        }
    ],
    "sg:phone":"+1 352 344 4535",
    "sg:postcode":"34452",
    "sg:province":"FL",
    "sg:tags":[
        "typing"
    ],
    "wof:name":"Kimberly Henick Secretarial",
    "wof:placetype":"venue"
},
  "geometry": {"coordinates":[-82.345985,28.791666],"type":"Point"}
}