{
  "type": "Feature",
  "properties": {
    "iso:country":"US",
    "sg:address":"5767 Manatee Ave W",
    "sg:city":"Bradenton",
    "sg:classifiers":[
        {
            "category":"Personal",
            "type":"Services"
        }
    ],
    "sg:phone":"+1 941 795 8845",
    "sg:postcode":"34209",
    "sg:province":"FL",
    "sg:tags":[
        "control",
        "weight"
    ],
    "wof:name":"L A Weight Loss Ctr",
    "wof:placetype":"venue"
},
  "geometry": {"coordinates":[-82.61819300000001,27.49604],"type":"Point"}
}