{
  "type": "Feature",
  "properties": {
    "addr:full":"8100 SW Archer Rd Gainesville FL 32608",
    "addr:housenumber":"8100",
    "addr:postcode":"32608",
    "addr:street":"Sw Archer Rd",
    "iso:country":"US",
    "sg:address":"8100 SW Archer Rd",
    "sg:city":"Gainesville",
    "sg:classifiers":[
        {
            "category":"Organizations",
            "subcategory":"Community Association",
            "type":"Services"
        }
    ],
    "sg:phone":"+1 352 376 7334",
    "sg:postcode":"32608",
    "sg:province":"FL",
    "sg:tags":[
        "fraternal"
    ],
    "wof:name":"Gainesville Shrine Club",
    "wof:placetype":"venue"
},
  "geometry": {"coordinates":[-82.429585,29.594656],"type":"Point"}
}