{
  "type": "Feature",
  "properties": {
    "addr:full":"1020 N Orlando Ave Maitland FL 32751",
    "addr:housenumber":"1020",
    "addr:postcode":"32751",
    "addr:street":"N Orlando Ave",
    "iso:country":"US",
    "sg:address":"1020 N Orlando Ave",
    "sg:city":"Maitland",
    "sg:classifiers":[
        {
            "category":"Insurance",
            "subcategory":"Insurance Agent",
            "type":"Services"
        }
    ],
    "sg:phone":"+1 407 647 1616",
    "sg:postcode":"32751",
    "sg:province":"FL",
    "sg:tags":[
        "agency"
    ],
    "wof:name":"Merrimac Marine Insurance",
    "wof:placetype":"venue"
},
  "geometry": {"coordinates":[-81.359369,28.636382],"type":"Point"}
}