{
  "type": "Feature",
  "properties": {
    "addr:full":"2751 NW 18th Ter Fort Lauderdale FL 33311",
    "addr:housenumber":"2751",
    "addr:postcode":"33311",
    "addr:street":"Nw 18Th Ter",
    "iso:country":"US",
    "sg:address":"2751 NW 18th Ter",
    "sg:city":"Fort Lauderdale",
    "sg:classifiers":[
        {
            "category":"Freight",
            "type":"Transportation"
        }
    ],
    "sg:phone":"+1 954 484 0680",
    "sg:postcode":"33311",
    "sg:province":"FL",
    "sg:tags":[
        "operator",
        "local",
        "trucking"
    ],
    "wof:name":"Leo Paving & Trucking",
    "wof:placetype":"venue"
},
  "geometry": {"coordinates":[-80.167312,26.161059],"type":"Point"}
}