{
  "type": "Feature",
  "properties": {
    "iso:country":"US",
    "sg:address":"966 Helmsley Ct",
    "sg:city":"Lake Mary",
    "sg:classifiers":[
        {
            "category":"Wholesale",
            "subcategory":"Fruits & Vegetables",
            "type":"Manufacturing & Wholesale Goods"
        }
    ],
    "sg:phone":"+1 407 330 2364",
    "sg:postcode":"32746",
    "sg:province":"FL",
    "wof:name":"Gulf Atlantic Produce Sales In",
    "wof:placetype":"venue"
},
  "geometry": {"coordinates":[-81.357996,28.749906],"type":"Point"}
}