{
  "type": "Feature",
  "properties": {
    "addr:full":"9500 Corkscrew Rd Estero FL 33928",
    "addr:housenumber":"9500",
    "addr:postcode":"33928",
    "addr:street":"Corkscrew Rd",
    "iso:country":"US",
    "sg:address":"9500 Corkscrew Rd",
    "sg:city":"Estero",
    "sg:classifiers":[
        {
            "category":"Health Services",
            "subcategory":"Doctor",
            "type":"Services"
        }
    ],
    "sg:phone":"+1 239 948 7555",
    "sg:postcode":"33928",
    "sg:province":"FL",
    "sg:tags":[
        "physician",
        "surgeon"
    ],
    "wof:name":"Konowal Vision",
    "wof:placetype":"venue"
},
  "geometry": {"coordinates":[-81.795901,26.431147],"type":"Point"}
}