{
  "type": "Feature",
  "properties": {
    "iso:country":"US",
    "sg:address":"530 Challenger Rd",
    "sg:city":"Cape Canaveral",
    "sg:classifiers":[
        {
            "category":"Taxi",
            "type":"Transportation"
        },
        {
            "category":"Airline",
            "type":"Transportation"
        }
    ],
    "sg:phone":"+1 321 799 1388",
    "sg:postcode":"32920",
    "sg:province":"FL",
    "sg:tags":[
        "shuttle",
        "airport"
    ],
    "wof:name":"Beachline Transportation Group Inc",
    "wof:placetype":"venue"
},
  "geometry": {"coordinates":[-80.614425,28.404537],"type":"Point"}
}