{
  "type": "Feature",
  "properties": {
    "addr:full":"1312 Illinois Ave Saint Cloud FL 34769",
    "addr:housenumber":"1312",
    "addr:postcode":"34769",
    "addr:street":"Illinois Ave",
    "iso:country":"US",
    "sg:address":"1312 Illinois Ave",
    "sg:city":"Saint Cloud",
    "sg:classifiers":[
        {
            "category":"Professional",
            "subcategory":"Accounting & Tax Preparation",
            "type":"Services"
        }
    ],
    "sg:phone":"+1 407 892 5033",
    "sg:postcode":"34769",
    "sg:province":"FL",
    "wof:name":"Alm & Associates",
    "wof:placetype":"venue"
},
  "geometry": {"coordinates":[-81.27798,28.245202],"type":"Point"}
}