{
  "type": "Feature",
  "properties": {
    "iso:country":"US",
    "sg:address":"1106 W 4th St",
    "sg:city":"Lynn Haven",
    "sg:classifiers":[
        {
            "category":"Organizations",
            "subcategory":"Community Association",
            "type":"Services"
        }
    ],
    "sg:phone":"+1 850 265 5021",
    "sg:postcode":"32444",
    "sg:province":"FL",
    "wof:name":"Dolphin Run Owners Association",
    "wof:placetype":"venue"
},
  "geometry": {"coordinates":[-85.66089100000001,30.251819],"type":"Point"}
}