{
  "type": "Feature",
  "properties": {
    "iso:country":"US",
    "sg:address":"10114 Bluff Ct",
    "sg:city":"Orlando",
    "sg:classifiers":[
        {
            "category":"Food & Beverages",
            "subcategory":"Liquor & Beverages",
            "type":"Retail Goods"
        }
    ],
    "sg:phone":"+1 407 239 8979",
    "sg:postcode":"32821",
    "sg:province":"FL",
    "sg:tags":[
        "alcoholic"
    ],
    "wof:name":"Lees Liquors",
    "wof:placetype":"venue"
},
  "geometry": {"coordinates":[-81.44759000000001,28.418578],"type":"Point"}
}