{
  "type": "Feature",
  "properties": {
    "iso:country":"US",
    "sg:address":"1463 Mount Laurel Dr",
    "sg:city":"Winter Springs",
    "sg:classifiers":[
        {
            "category":"Building & Trades",
            "subcategory":"Construction",
            "type":"Services"
        }
    ],
    "sg:phone":"+1 407 366 6704",
    "sg:postcode":"32708",
    "sg:province":"FL",
    "sg:tags":[
        "painter"
    ],
    "wof:name":"East Coast Painting",
    "wof:placetype":"venue"
},
  "geometry": {"coordinates":[-81.250342,28.682893],"type":"Point"}
}