{
  "type": "Feature",
  "properties": {
    "addr:full":"3595 NW 72nd Ave Miami FL 33122",
    "addr:housenumber":"3595",
    "addr:postcode":"33122",
    "addr:street":"Nw 72Nd Ave",
    "iso:country":"US",
    "sg:address":"3595 NW 72nd Ave",
    "sg:city":"Miami",
    "sg:classifiers":[
        {
            "category":"Government",
            "subcategory":"Jail",
            "type":"Public Place"
        }
    ],
    "sg:phone":"+1 305 477 9153",
    "sg:postcode":"33122",
    "sg:province":"FL",
    "sg:tags":[
        "county",
        "govt",
        "institution"
    ],
    "wof:name":"Dade County Corrections Dept",
    "wof:placetype":"venue"
},
  "geometry": {"coordinates":[-80.313101,25.806155],"type":"Point"}
}