{
  "type": "Feature",
  "properties": {
    "addr:full":"6950 NW 46th St Miami FL 33166",
    "addr:housenumber":"6950",
    "addr:postcode":"33166",
    "addr:street":"Nw 46Th St",
    "iso:country":"US",
    "sg:address":"6950 NW 46th St",
    "sg:city":"Miami",
    "sg:classifiers":[
        {
            "category":"Banks & Credit Unions",
            "subcategory":"Bank",
            "type":"Services"
        }
    ],
    "sg:phone":"+1 305 477 5293",
    "sg:postcode":"33166",
    "sg:province":"FL",
    "sg:tags":[
        "financing"
    ],
    "wof:name":"North Finance Group",
    "wof:placetype":"venue"
},
  "geometry": {"coordinates":[-80.31286,25.815193],"type":"Point"}
}