{
  "type": "Feature",
  "properties": {
    "iso:country":"US",
    "sg:address":"319 S Lee Ave",
    "sg:city":"Arcadia",
    "sg:classifiers":[
        {
            "category":"Place Of Worship",
            "subcategory":"Church",
            "type":"Public Place"
        },
        {
            "category":"Place Of Worship",
            "type":"Public Place"
        }
    ],
    "sg:phone":"+1 863 494 0320",
    "sg:postcode":"34266",
    "sg:province":"FL",
    "sg:tags":[
        "churches-interdenominational",
        "denomination",
        "churches-various",
        "churches-methodist"
    ],
    "wof:name":"Pleasant Hill Methodist Church",
    "wof:placetype":"venue"
},
  "geometry": {"coordinates":[-81.868858,27.21274],"type":"Point"}
}