{
  "type": "Feature",
  "properties": {
    "iso:country":"US",
    "sg:address":"1105 S 6th Ave",
    "sg:city":"Wauchula",
    "sg:classifiers":[
        {
            "category":"Shopping",
            "subcategory":"Clothing, Apparel, & Fashions",
            "type":"Retail Goods"
        },
        {
            "category":"Shopping",
            "subcategory":"Department Store",
            "type":"Retail Goods"
        }
    ],
    "sg:phone":"+1 863 773 6205",
    "sg:postcode":"33873",
    "sg:province":"FL",
    "sg:tags":[
        "clothing"
    ],
    "sg:website":"http://www.beallsoutlet.com",
    "wof:name":"Beall's Outlet 386",
    "wof:placetype":"venue"
},
  "geometry": {"coordinates":[-81.80933400000001,27.531965],"type":"Point"}
}