{
  "type": "Feature",
  "properties": {
    "addr:full":"4414 Bee Ridge Rd Sarasota FL 34233",
    "addr:housenumber":"4414",
    "addr:postcode":"34233",
    "addr:street":"Bee Ridge Rd",
    "iso:country":"US",
    "sg:address":"4414 Bee Ridge Rd",
    "sg:city":"Sarasota",
    "sg:classifiers":[
        {
            "category":"Recreation",
            "type":"Entertainment"
        }
    ],
    "sg:phone":"+1 941 378 1160",
    "sg:postcode":"34233",
    "sg:province":"FL",
    "sg:tags":[
        "bingo",
        "game"
    ],
    "wof:name":"Palm Plaza Bingo Hall",
    "wof:placetype":"venue"
},
  "geometry": {"coordinates":[-82.47687500000001,27.298674],"type":"Point"}
}