{
  "type": "Feature",
  "properties": {
    "iso:country":"US",
    "sg:address":"16887 SW 1st Pl",
    "sg:city":"Pembroke Pines",
    "sg:classifiers":[
        {
            "category":"Professional",
            "subcategory":"Management & Consulting",
            "type":"Services"
        }
    ],
    "sg:phone":"+1 954 383 7839",
    "sg:postcode":"33027",
    "sg:province":"FL",
    "sg:tags":[
        "aviation",
        "consultant"
    ],
    "wof:name":"Vialair Inc",
    "wof:placetype":"venue"
},
  "geometry": {"coordinates":[-80.37235699999999,26.006175],"type":"Point"}
}