{
  "type": "Feature",
  "properties": {
    "iso:country":"US",
    "sg:address":"1471 Sungate Dr",
    "sg:city":"Kissimmee",
    "sg:classifiers":[
        {
            "category":"Education",
            "subcategory":"School",
            "type":"Public Place"
        }
    ],
    "sg:phone":"+1 407 846 1012",
    "sg:postcode":"34746",
    "sg:province":"FL",
    "wof:name":"Jerstad Laura",
    "wof:placetype":"venue"
},
  "geometry": {"coordinates":[-81.43781300000001,28.264289],"type":"Point"}
}