{
  "type": "Feature",
  "properties": {
    "iso:country":"US",
    "sg:address":"222 W 6th Ave",
    "sg:city":"Mount Dora",
    "sg:classifiers":[
        {
            "category":"Organizations",
            "subcategory":"Religious Organization",
            "type":"Services"
        }
    ],
    "sg:phone":"+1 352 383 2666",
    "sg:postcode":"32757",
    "sg:province":"FL",
    "sg:tags":[
        "church"
    ],
    "wof:name":"First Presbt Church Mt Dora",
    "wof:placetype":"venue"
},
  "geometry": {"coordinates":[-81.64657699999999,28.801357],"type":"Point"}
}