{
  "type": "Feature",
  "properties": {
    "iso:country":"US",
    "sg:address":"100 Oyster Pl",
    "sg:city":"Rockledge",
    "sg:classifiers":[
        {
            "category":"Insurance",
            "subcategory":"Hazard Insurance",
            "type":"Services"
        }
    ],
    "sg:phone":"+1 321 863 2591",
    "sg:postcode":"32955",
    "sg:province":"FL",
    "wof:name":"Dean And Associates Inc",
    "wof:placetype":"venue"
},
  "geometry": {"coordinates":[-80.685806,28.26487],"type":"Point"}
}