{
  "type": "Feature",
  "properties": {
    "iso:country":"US",
    "sg:address":"832 S Southlake Dr",
    "sg:city":"Hollywood",
    "sg:classifiers":[
        {
            "category":"Professional",
            "subcategory":"Research",
            "type":"Services"
        }
    ],
    "sg:phone":"+1 954 920 2522",
    "sg:postcode":"33019",
    "sg:province":"FL",
    "sg:tags":[
        "information",
        "medical"
    ],
    "sg:website":"http://www.effectiveresearch.com",
    "wof:name":"Effective Research Inc",
    "wof:placetype":"venue"
},
  "geometry": {"coordinates":[-80.124239,26.006979],"type":"Point"}
}