{
  "type": "Feature",
  "properties": {
    "addr:full":"200 S Federal Hwy Boynton Beach FL 33435",
    "addr:housenumber":"200",
    "addr:postcode":"33435",
    "addr:street":"S Federal Hwy",
    "iso:country":"US",
    "sg:address":"200 S Federal Hwy",
    "sg:city":"Boynton Beach",
    "sg:classifiers":[
        {
            "category":"Food & Beverages",
            "subcategory":"Groceries & Convenience Stores",
            "type":"Retail Goods"
        }
    ],
    "sg:phone":"+1 561 272 6413",
    "sg:postcode":"33435",
    "sg:province":"FL",
    "wof:name":"Sunoco",
    "wof:placetype":"venue"
},
  "geometry": {"coordinates":[-80.058081,26.526142],"type":"Point"}
}