{
  "type": "Feature",
  "properties": {
    "iso:country":"US",
    "sg:address":"1101 South Clarke Road",
    "sg:city":"Ocoee",
    "sg:classifiers":[
        {
            "category":"Professional",
            "subcategory":"Employment Agencies",
            "type":"Services"
        }
    ],
    "sg:phone":"+1 407 271 8945",
    "sg:postcode":"34761",
    "sg:province":"FL",
    "sg:tags":[
        "consultant",
        "opportunity",
        "screening",
        "resume"
    ],
    "sg:website":"http://orlandoflwest.expresspros.com/?utm_source=yellowpages&utm_content=2571&utm_campaign=localmaps",
    "wof:name":"Express Employment Professionals - Staffing",
    "wof:placetype":"venue"
},
  "geometry": {"coordinates":[-81.520422,28.55354],"type":"Point"}
}