{
  "type": "Feature",
  "properties": {
    "iso:country":"US",
    "sg:address":"600 N Homestead Blvd",
    "sg:city":"Homestead",
    "sg:classifiers":[
        {
            "category":"Banks & Credit Unions",
            "subcategory":"Bank",
            "type":"Services"
        }
    ],
    "sg:phone":"+1 305 247 5001",
    "sg:postcode":"33030",
    "sg:province":"FL",
    "wof:name":"T I B Bank Of The Keys",
    "wof:placetype":"venue"
},
  "geometry": {"coordinates":[-80.46463799999999,25.478055],"type":"Point"}
}