{
  "type": "Feature",
  "properties": {
    "iso:country":"US",
    "sg:address":"40 S Main St",
    "sg:city":"Winter Garden",
    "sg:classifiers":[
        {
            "category":"Manufacturing",
            "subcategory":"Textiles",
            "type":"Manufacturing & Wholesale Goods"
        },
        {
            "category":"Manufacturing",
            "subcategory":"Toys & Sporting Goods",
            "type":"Manufacturing & Wholesale Goods"
        }
    ],
    "sg:phone":"+1 407 656 1133",
    "sg:postcode":"34787",
    "sg:province":"FL",
    "sg:tags":[
        "manufacture",
        "athletic",
        "rope",
        "accessory"
    ],
    "wof:name":"Masterline USA Inc",
    "wof:placetype":"venue"
},
  "geometry": {"coordinates":[-81.585725,28.56528],"type":"Point"}
}