{
  "type": "Feature",
  "properties": {
    "iso:country":"US",
    "sg:address":"5108 W Hanna Ave",
    "sg:city":"Tampa",
    "sg:classifiers":[
        {
            "category":"Wholesale",
            "subcategory":"Construction Materials",
            "type":"Manufacturing & Wholesale Goods"
        }
    ],
    "sg:phone":"+1 813 249 7808",
    "sg:postcode":"33634",
    "sg:province":"FL",
    "sg:tags":[
        "equipment",
        "maker",
        "cabinet"
    ],
    "wof:name":"Laminates & Things Co",
    "wof:placetype":"venue"
},
  "geometry": {"coordinates":[-82.53245200000001,28.003543],"type":"Point"}
}