{
  "type": "Feature",
  "properties": {
    "iso:country":"US",
    "sg:address":"4000 S Red Rd",
    "sg:city":"Miami",
    "sg:classifiers":[
        {
            "category":"Shopping",
            "subcategory":"Pharmacy",
            "type":"Retail Goods"
        }
    ],
    "sg:phone":"+1 305 666 8581",
    "sg:postcode":"33155",
    "sg:province":"FL",
    "sg:tags":[
        "drugstore"
    ],
    "wof:name":"Allen's My Pharmacy",
    "wof:placetype":"venue"
},
  "geometry": {"coordinates":[-80.28646500000001,25.73327],"type":"Point"}
}