{
  "type": "Feature",
  "properties": {
    "iso:country":"US",
    "sg:address":"324 S Hyde Park Ave",
    "sg:city":"Tampa",
    "sg:classifiers":[
        {
            "category":"Banks & Credit Unions",
            "subcategory":"Investment Brokerage",
            "type":"Services"
        }
    ],
    "sg:phone":"+1 813 254 0123",
    "sg:postcode":"33606",
    "sg:province":"FL",
    "sg:tags":[
        "stock",
        "bond"
    ],
    "wof:name":"Security Econometrics Corp",
    "wof:placetype":"venue"
},
  "geometry": {"coordinates":[-82.46386800000001,27.940813],"type":"Point"}
}