{
  "type": "Feature",
  "properties": {
    "iso:country":"US",
    "sg:address":"1475 Taylor Rd E Ste D",
    "sg:city":"Deland",
    "sg:classifiers":[
        {
            "category":"Building & Trades",
            "subcategory":"Construction",
            "type":"Services"
        }
    ],
    "sg:phone":"+1 386 740 8188",
    "sg:postcode":"32724",
    "sg:province":"FL",
    "sg:tags":[
        "contractor"
    ],
    "wof:name":"United Contractors Building Corp",
    "wof:placetype":"venue"
},
  "geometry": {"coordinates":[-81.26631500000001,29.000751],"type":"Point"}
}