{
  "type": "Feature",
  "properties": {
    "iso:country":"US",
    "sg:address":"830 W 84th St",
    "sg:city":"Hialeah",
    "sg:classifiers":[
        {
            "category":"Autos & Motor Vehicles",
            "subcategory":"Auto Supplies",
            "type":"Retail Goods"
        },
        {
            "category":"Wholesale",
            "subcategory":"Auto Parts",
            "type":"Manufacturing & Wholesale Goods"
        }
    ],
    "sg:phone":"+1 305 822 6415",
    "sg:postcode":"33014",
    "sg:province":"FL",
    "sg:tags":[
        "automobile",
        "accessory",
        "rebuilt-wholesale",
        "supplies-used",
        "rebuilt",
        "manufacturer"
    ],
    "wof:name":"Body Parts Of America-Miami",
    "wof:placetype":"venue"
},
  "geometry": {"coordinates":[-80.302262,25.898661],"type":"Point"}
}