{
  "type": "Feature",
  "properties": {
    "iso:country":"US",
    "sg:address":"1678 Ridgewood Ave",
    "sg:city":"Daytona Beach",
    "sg:classifiers":[
        {
            "category":"Home & Garden",
            "subcategory":"Carpets & Floor Coverings",
            "type":"Retail Goods"
        }
    ],
    "sg:phone":"+1 386 615 1145",
    "sg:postcode":"32117",
    "sg:province":"FL",
    "sg:tags":[
        "dealer",
        "rug"
    ],
    "wof:name":"Athens Carpet & Rug Services",
    "wof:placetype":"venue"
},
  "geometry": {"coordinates":[-81.047263,29.256066],"type":"Point"}
}