{
  "type": "Feature",
  "properties": {
    "addr:full":"306 NW 7th Ave Ocala FL 34475",
    "addr:housenumber":"306",
    "addr:postcode":"34475",
    "addr:street":"Nw 7Th Ave",
    "iso:country":"US",
    "sg:address":"306 NW 7th Ave",
    "sg:city":"Ocala",
    "sg:classifiers":[
        {
            "category":"Social Services",
            "subcategory":"Child Care",
            "type":"Services"
        }
    ],
    "sg:phone":"+1 352 620 8706",
    "sg:postcode":"34475",
    "sg:province":"FL",
    "sg:tags":[
        "kindergarten",
        "academic",
        "school"
    ],
    "wof:name":"Childhood Development Svc",
    "wof:placetype":"venue"
},
  "geometry": {"coordinates":[-82.144931,29.189215],"type":"Point"}
}