{
  "type": "Feature",
  "properties": {
    "addr:full":"2169 SE Ocean Blvd Stuart FL 34996",
    "addr:housenumber":"2169",
    "addr:postcode":"34996",
    "addr:street":"Se Ocean Blvd",
    "iso:country":"US",
    "sg:address":"2169 SE Ocean Blvd",
    "sg:city":"Stuart",
    "sg:classifiers":[
        {
            "category":"Wholesale",
            "subcategory":"Medical Equipment & Supplies",
            "type":"Manufacturing & Wholesale Goods"
        }
    ],
    "sg:phone":"+1 772 286 0085",
    "sg:postcode":"34996",
    "sg:province":"FL",
    "sg:tags":[
        "hospital"
    ],
    "sg:website":"www.lincare.com",
    "wof:name":"Lincare",
    "wof:placetype":"venue"
},
  "geometry": {"coordinates":[-80.222751,27.197177],"type":"Point"}
}