{
  "type": "Feature",
  "properties": {
    "iso:country":"US",
    "sg:address":"325 NE 25th Ave",
    "sg:city":"Ocala",
    "sg:classifiers":[
        {
            "category":"Insurance",
            "subcategory":"Insurance Agent",
            "type":"Services"
        }
    ],
    "sg:phone":"+1 352 694 4200",
    "sg:postcode":"34470",
    "sg:province":"FL",
    "wof:name":"Waller Insurance",
    "wof:placetype":"venue"
},
  "geometry": {"coordinates":[-82.103193,29.191529],"type":"Point"}
}