{
  "type": "Feature",
  "properties": {
    "addr:full":"5435 Shirley St Naples FL 34109",
    "addr:housenumber":"5435",
    "addr:postcode":"34109",
    "addr:street":"Shirley St",
    "iso:country":"US",
    "sg:address":"5435 Shirley St",
    "sg:city":"Naples",
    "sg:classifiers":[
        {
            "category":"Building & Trades",
            "subcategory":"Equipment Rental",
            "type":"Services"
        },
        {
            "category":"Professional",
            "subcategory":"Management & Consulting",
            "type":"Services"
        }
    ],
    "sg:phone":"+1 239 597 5311",
    "sg:postcode":"34109",
    "sg:province":"FL",
    "sg:tags":[
        "function",
        "set",
        "for",
        "specialty",
        "planning",
        "party"
    ],
    "wof:name":"Sky's The Limit Productions",
    "wof:placetype":"venue"
},
  "geometry": {"coordinates":[-81.78153399999999,26.213233],"type":"Point"}
}