{
  "type": "Feature",
  "properties": {
    "iso:country":"US",
    "sg:address":"6500 NW 37th Ave",
    "sg:city":"Miami",
    "sg:classifiers":[
        {
            "category":"Wholesale",
            "subcategory":"Durable Goods & Equipment",
            "type":"Manufacturing & Wholesale Goods"
        }
    ],
    "sg:phone":"+1 305 691 5000",
    "sg:postcode":"33147",
    "sg:province":"FL",
    "sg:tags":[
        "valve",
        "exporter"
    ],
    "wof:name":"A & B Pipe & Supply Inc",
    "wof:placetype":"venue"
},
  "geometry": {"coordinates":[-80.257491,25.832991],"type":"Point"}
}