{
  "type": "Feature",
  "properties": {
    "iso:country":"US",
    "sg:address":"3715 Cleveland Ave",
    "sg:city":"Fort Myers",
    "sg:classifiers":[
        {
            "category":"Travel",
            "subcategory":"Hotels & Motels",
            "type":"Entertainment"
        }
    ],
    "sg:phone":"+1 239 936 2181",
    "sg:postcode":"33901",
    "sg:province":"FL",
    "sg:website":"www.budgetinn.com",
    "wof:name":"Budget Inn",
    "wof:placetype":"venue"
},
  "geometry": {"coordinates":[-81.871803,26.610201],"type":"Point"}
}