{
  "type": "Feature",
  "properties": {
    "iso:country":"US",
    "sg:address":"5913 Georgia Ave",
    "sg:city":"West Palm Beach",
    "sg:classifiers":[
        {
            "category":"Retail",
            "subcategory":"Auto Repair",
            "type":"Services"
        }
    ],
    "sg:phone":"+1 561 588 6811",
    "sg:postcode":"33405",
    "sg:province":"FL",
    "sg:tags":[
        "repairing",
        "automobile",
        "general"
    ],
    "sg:website":"www.avenueimports.com",
    "wof:name":"Avenue Imports Inc",
    "wof:placetype":"venue"
},
  "geometry": {"coordinates":[-80.058972,26.661189],"type":"Point"}
}