{
  "type": "Feature",
  "properties": {
    "iso:country":"US",
    "sg:address":"1338 W Pipkin Rd",
    "sg:city":"Lakeland",
    "sg:classifiers":[
        {
            "category":"Building & Trades",
            "subcategory":"Construction",
            "type":"Services"
        }
    ],
    "sg:phone":"+1 863 709 1100",
    "sg:postcode":"33811",
    "sg:province":"FL",
    "sg:tags":[
        "general",
        "contractor"
    ],
    "wof:name":"Midway Maintenance",
    "wof:placetype":"venue"
},
  "geometry": {"coordinates":[-81.979713,27.974765],"type":"Point"}
}