{
  "type": "Feature",
  "properties": {
    "addr:full":"794 NW 134th Ave Miami FL 33182",
    "addr:housenumber":"794",
    "addr:postcode":"33182",
    "addr:street":"Nw 134Th Ave",
    "iso:country":"US",
    "sg:address":"794 NW 134th Ave",
    "sg:city":"Miami",
    "sg:classifiers":[
        {
            "category":"Wholesale",
            "subcategory":"Vending Machines",
            "type":"Manufacturing & Wholesale Goods"
        }
    ],
    "sg:phone":"+1 305 227 3858",
    "sg:postcode":"33182",
    "sg:province":"FL",
    "sg:tags":[
        "operator",
        "merchandise"
    ],
    "wof:name":"Top Quality Vending Machines",
    "wof:placetype":"venue"
},
  "geometry": {"coordinates":[-80.412566,25.775818],"type":"Point"}
}