{
  "type": "Feature",
  "properties": {
    "addr:full":"2675 Winkler Ave Ste 300 Fort Myers FL 33901",
    "addr:housenumber":"2675",
    "addr:postcode":"myers;33901",
    "addr:street":"Winkler Ave Ste 300",
    "iso:country":"US",
    "sg:address":"2675 Winkler Ave Ste 300",
    "sg:city":"Fort Myers",
    "sg:classifiers":[
        {
            "category":"Health Services",
            "subcategory":"Doctor",
            "type":"Services"
        }
    ],
    "sg:phone":"+1 239 936 1343",
    "sg:postcode":"33901",
    "sg:province":"FL",
    "wof:name":"Kotula Rudolf MD",
    "wof:placetype":"venue"
},
  "geometry": {"coordinates":[-81.8582,26.6045],"type":"Point"}
}