{
  "type": "Feature",
  "properties": {
    "addr:full":"3266 NW Federal Hwy Jensen Beach FL 34957",
    "addr:housenumber":"3266",
    "addr:postcode":"34957",
    "addr:street":"Nw Federal Hwy",
    "iso:country":"US",
    "sg:address":"3266 NW Federal Hwy",
    "sg:city":"Jensen Beach",
    "sg:classifiers":[
        {
            "category":"Restaurant",
            "type":"Food & Drink"
        }
    ],
    "sg:phone":"+1 772 692 9833",
    "sg:postcode":"34957",
    "sg:province":"FL",
    "wof:name":"Barvarian Colony",
    "wof:placetype":"venue"
},
  "geometry": {"coordinates":[-80.270231,27.239909],"type":"Point"}
}