{
  "type": "Feature",
  "properties": {
    "iso:country":"US",
    "sg:address":"7281 Miller Dr",
    "sg:city":"Miami",
    "sg:classifiers":[
        {
            "category":"Wholesale",
            "subcategory":"Computers",
            "type":"Manufacturing & Wholesale Goods"
        },
        {
            "category":"Professional",
            "subcategory":"Computer Services",
            "type":"Services"
        }
    ],
    "sg:phone":"+1 305 667 7343",
    "sg:postcode":"33155",
    "sg:province":"FL",
    "sg:tags":[
        "publisher",
        "software",
        "developer",
        "equipment"
    ],
    "wof:name":"Computer Spectrum International Corporation",
    "wof:placetype":"venue"
},
  "geometry": {"coordinates":[-80.312364,25.718029],"type":"Point"}
}