{
  "type": "Feature",
  "properties": {
    "iso:country":"US",
    "sg:address":"10625 Hilltop Dr",
    "sg:city":"New Port Richey",
    "sg:classifiers":[
        {
            "category":"Social Services",
            "subcategory":"Adult Care",
            "type":"Services"
        }
    ],
    "sg:phone":"+1 813 862 0805",
    "sg:postcode":"34654",
    "sg:province":"FL",
    "sg:tags":[
        "home",
        "residential"
    ],
    "wof:name":"Hilltop House",
    "wof:placetype":"venue"
},
  "geometry": {"coordinates":[-82.659751,28.313838],"type":"Point"}
}