{
  "type": "Feature",
  "properties": {
    "addr:full":"7164 SW 13th Ter Miami FL 33144",
    "addr:housenumber":"7164",
    "addr:postcode":"33144",
    "addr:street":"Sw 13Th Ter",
    "iso:country":"US",
    "sg:address":"7164 SW 13th Ter",
    "sg:city":"Miami",
    "sg:classifiers":[
        {
            "category":"Building & Trades",
            "subcategory":"Construction",
            "type":"Services"
        }
    ],
    "sg:phone":"+1 305 261 5555",
    "sg:postcode":"33144",
    "sg:province":"FL",
    "sg:tags":[
        "hanging",
        "contractor"
    ],
    "wof:name":"Labauts Painting Inc",
    "wof:placetype":"venue"
},
  "geometry": {"coordinates":[-80.310548,25.757716],"type":"Point"}
}