{
  "type": "Feature",
  "properties": {
    "iso:country":"US",
    "sg:address":"16234 Key Lime Blvd",
    "sg:city":"Loxahatchee",
    "sg:classifiers":[
        {
            "category":"Building & Trades",
            "subcategory":"Equipment Rental",
            "type":"Services"
        }
    ],
    "sg:phone":"+1 561 795 8505",
    "sg:postcode":"33470",
    "sg:province":"FL",
    "wof:name":"A Bounce Around Rentals Inc",
    "wof:placetype":"venue"
},
  "geometry": {"coordinates":[-80.29806499999999,26.785831],"type":"Point"}
}