{
  "type": "Feature",
  "properties": {
    "iso:country":"US",
    "sg:address":"3881 Newport Ave",
    "sg:city":"Boynton Beach",
    "sg:classifiers":[
        {
            "category":"Real Estate",
            "subcategory":"Real Estate Agent",
            "type":"Services"
        }
    ],
    "sg:phone":"+1 561 868 5125",
    "sg:postcode":"33436",
    "sg:province":"FL",
    "sg:tags":[
        "inspection"
    ],
    "wof:name":"Suburban Home Inspection Inc",
    "wof:placetype":"venue"
},
  "geometry": {"coordinates":[-80.10279,26.565179],"type":"Point"}
}