{
  "type": "Feature",
  "properties": {
    "iso:country":"US",
    "sg:address":"2737 NW 17th St",
    "sg:city":"Miami",
    "sg:classifiers":[
        {
            "category":"Wholesale",
            "subcategory":"Sporting Goods",
            "type":"Manufacturing & Wholesale Goods"
        }
    ],
    "sg:phone":"+1 305 635 1064",
    "sg:postcode":"33125",
    "sg:province":"FL",
    "wof:name":"National Marine Express",
    "wof:placetype":"venue"
},
  "geometry": {"coordinates":[-80.24059,25.790693],"type":"Point"}
}