{
  "type": "Feature",
  "properties": {
    "iso:country":"US",
    "sg:address":"429 SW 44th St",
    "sg:city":"Cape Coral",
    "sg:classifiers":[
        {
            "category":"Building & Trades",
            "subcategory":"Plumbing",
            "type":"Services"
        }
    ],
    "sg:phone":"+1 239 939 6940",
    "sg:postcode":"33914",
    "sg:province":"FL",
    "wof:name":"Leak Surgeons Inc",
    "wof:placetype":"venue"
},
  "geometry": {"coordinates":[-81.98395499999999,26.570131],"type":"Point"}
}