{
  "type": "Feature",
  "properties": {
    "iso:country":"US",
    "sg:address":"1100 S 24th Ter",
    "sg:city":"Hollywood",
    "sg:phone":"+1 954 524 0205",
    "sg:postcode":"33020",
    "sg:province":"FL",
    "sg:tags":[
        "fuel",
        "diesel"
    ],
    "wof:name":"Streicher Mobile Fueling Inc",
    "wof:placetype":"venue"
},
  "geometry": {"coordinates":[-80.155979,26.000973],"type":"Point"}
}