{
  "type": "Feature",
  "properties": {
    "addr:full":"1515 Old Bainbridge Rd Tallahassee FL 32303",
    "addr:housenumber":"1515",
    "addr:postcode":"32303",
    "addr:street":"Old Bainbridge Rd",
    "iso:country":"US",
    "sg:address":"1515 Old Bainbridge Rd",
    "sg:city":"Tallahassee",
    "sg:classifiers":[
        {
            "category":"Health Services",
            "subcategory":"Doctor",
            "type":"Services"
        }
    ],
    "sg:phone":"+1 850 487 3185",
    "sg:postcode":"32303",
    "sg:province":"FL",
    "sg:tags":[
        "clinic"
    ],
    "wof:name":"Leon County Public Health Unit",
    "wof:placetype":"venue"
},
  "geometry": {"coordinates":[-84.296817,30.460463],"type":"Point"}
}