{
  "type": "Feature",
  "properties": {
    "iso:country":"US",
    "sg:address":"656 NE 44th St",
    "sg:city":"Oakland Park",
    "sg:classifiers":[
        {
            "category":"Home & Garden",
            "subcategory":"Furniture",
            "type":"Retail Goods"
        }
    ],
    "sg:phone":"+1 954 563 9911",
    "sg:postcode":"33334",
    "sg:province":"FL",
    "sg:tags":[
        "builder",
        "custom"
    ],
    "sg:website":"www.ajoriginals.com",
    "wof:name":"A J Originals",
    "wof:placetype":"venue"
},
  "geometry": {"coordinates":[-80.13706500000001,26.181492],"type":"Point"}
}