{
  "type": "Feature",
  "properties": {
    "addr:full":"1160 W 33rd St Hialeah FL 33012",
    "addr:housenumber":"1160",
    "addr:postcode":"33012",
    "addr:street":"W 33Rd St",
    "iso:country":"US",
    "sg:address":"1160 W 33rd St",
    "sg:city":"Hialeah",
    "sg:classifiers":[
        {
            "category":"Banks & Credit Unions",
            "subcategory":"Financial Services",
            "type":"Services"
        }
    ],
    "sg:phone":"+1 786 228 9399",
    "sg:postcode":"33012",
    "sg:province":"FL",
    "sg:tags":[
        "card",
        "card-merchant"
    ],
    "wof:name":"Nec Credit Services Inc.",
    "wof:placetype":"venue"
},
  "geometry": {"coordinates":[-80.305635,25.85162],"type":"Point"}
}