{
  "type": "Feature",
  "properties": {
    "iso:country":"US",
    "sg:address":"9032 Glenarm Way",
    "sg:city":"Brooksville",
    "sg:classifiers":[
        {
            "category":"Building & Trades",
            "subcategory":"Plumbing",
            "type":"Services"
        }
    ],
    "sg:phone":"+1 352 596 3672",
    "sg:postcode":"34613",
    "sg:province":"FL",
    "sg:tags":[
        "plumbing",
        "contractor"
    ],
    "wof:name":"Grigg Jerry Early Bird Plumber",
    "wof:placetype":"venue"
},
  "geometry": {"coordinates":[-82.57602900000001,28.546212],"type":"Point"}
}