{
  "type": "Feature",
  "properties": {
    "iso:country":"US",
    "sg:address":"20 Wright Pkwy NW",
    "sg:city":"Fort Walton Bch",
    "sg:classifiers":[
        {
            "category":"Building & Trades",
            "subcategory":"Cleaning & Sanitation",
            "type":"Services"
        }
    ],
    "sg:phone":"+1 850 240 1785",
    "sg:postcode":"32548",
    "sg:province":"FL",
    "sg:tags":[
        "janitor"
    ],
    "wof:name":"WDM Cleaning",
    "wof:placetype":"venue"
},
  "geometry": {"coordinates":[-86.63927099999999,30.416003],"type":"Point"}
}