{
  "type": "Feature",
  "properties": {
    "addr:full":"694 N Dean Rd Orlando FL 32825",
    "addr:housenumber":"694",
    "addr:postcode":"32825",
    "addr:street":"N Dean Rd",
    "iso:country":"US",
    "sg:address":"694 N Dean Rd",
    "sg:city":"Orlando",
    "sg:classifiers":[
        {
            "category":"Organizations",
            "subcategory":"Religious Organization",
            "type":"Services"
        }
    ],
    "sg:phone":"+1 407 380 2414",
    "sg:postcode":"32825",
    "sg:province":"FL",
    "sg:tags":[
        "church"
    ],
    "sg:website":"www.watchtower.org",
    "wof:name":"Jehovah's Witnesses",
    "wof:placetype":"venue"
},
  "geometry": {"coordinates":[-81.244704,28.551718],"type":"Point"}
}