{
  "type": "Feature",
  "properties": {
    "iso:country":"US",
    "sg:address":"1313 SW South Macedo Blvd",
    "sg:city":"Port St Lucie",
    "sg:classifiers":[
        {
            "category":"Government",
            "subcategory":"Office",
            "type":"Public Place"
        }
    ],
    "sg:phone":"+1 772 871 5042",
    "sg:postcode":"34983",
    "sg:province":"FL",
    "sg:tags":[
        "village"
    ],
    "sg:website":"www.cityofpsl.com",
    "wof:name":"Port St Lucie Animal Control",
    "wof:placetype":"venue"
},
  "geometry": {"coordinates":[-80.37034199999999,27.29877],"type":"Point"}
}