{
  "type": "Feature",
  "properties": {
    "addr:full":"49 W Granada Blvd Ormond Beach FL 32174",
    "addr:housenumber":"49",
    "addr:postcode":"32174",
    "addr:street":"W Granada Blvd",
    "iso:country":"US",
    "sg:address":"49 W Granada Blvd",
    "sg:city":"Ormond Beach",
    "sg:classifiers":[
        {
            "category":"Restaurant",
            "type":"Food & Drink"
        }
    ],
    "sg:phone":"+1 386 672 7673",
    "sg:postcode":"32174",
    "sg:province":"FL",
    "sg:website":"www.englishrosetearoom.com",
    "wof:name":"English Rose Tea Room",
    "wof:placetype":"venue"
},
  "geometry": {"coordinates":[-81.056214,29.285655],"type":"Point"}
}