{
  "type": "Feature",
  "properties": {
    "addr:full":"2436 Croton Rd Melbourne FL 32935",
    "addr:housenumber":"2436",
    "addr:postcode":"32935",
    "addr:street":"Croton Rd",
    "iso:country":"US",
    "sg:address":"2436 Croton Rd",
    "sg:city":"Melbourne",
    "sg:classifiers":[
        {
            "category":"Organizations",
            "subcategory":"Religious Organization",
            "type":"Services"
        }
    ],
    "sg:phone":"+1 321 259 3356",
    "sg:postcode":"32935",
    "sg:province":"FL",
    "sg:website":"www.crossroadscommunityonline.org",
    "wof:name":"Crossroads Community Church",
    "wof:placetype":"venue"
},
  "geometry": {"coordinates":[-80.655136,28.145771],"type":"Point"}
}