{
  "type": "Feature",
  "properties": {
    "iso:country":"US",
    "sg:address":"5660 Fishhawk Crossing Blvd",
    "sg:city":"Lithia",
    "sg:classifiers":[
        {
            "category":"Personal",
            "subcategory":"Nail Salon",
            "type":"Services"
        }
    ],
    "sg:phone":"+1 813 661 1845",
    "sg:postcode":"33547",
    "sg:province":"FL",
    "wof:name":"Signal Nails",
    "wof:placetype":"venue"
},
  "geometry": {"coordinates":[-82.207047,27.85269],"type":"Point"}
}