{
  "type": "Feature",
  "properties": {
    "iso:country":"US",
    "sg:address":"250 W Sunrise Blvd",
    "sg:city":"Fort Lauderdale",
    "sg:classifiers":[
        {
            "category":"Autos & Motor Vehicles",
            "subcategory":"Auto Supplies",
            "type":"Retail Goods"
        }
    ],
    "sg:phone":"+1 954 764 1582",
    "sg:postcode":"33311",
    "sg:province":"FL",
    "sg:tags":[
        "tire"
    ],
    "wof:name":"Dale's Tires",
    "wof:placetype":"venue"
},
  "geometry": {"coordinates":[-80.14660000000001,26.13662],"type":"Point"}
}