{
  "type": "Feature",
  "properties": {
    "addr:full":"3391 E Silver Springs Blvd Ocala FL 34470",
    "addr:housenumber":"3391",
    "addr:postcode":"34470",
    "addr:street":"E Silver Springs Blvd",
    "iso:country":"US",
    "sg:address":"3391 E Silver Springs Blvd",
    "sg:city":"Ocala",
    "sg:classifiers":[
        {
            "category":"Organizations",
            "subcategory":"Non-profit Organization",
            "type":"Services"
        }
    ],
    "sg:phone":"+1 352 690 6030",
    "sg:postcode":"34470",
    "sg:province":"FL",
    "sg:tags":[
        "info",
        "addiction",
        "abuse",
        "treatment",
        "drug"
    ],
    "wof:name":"Options Of Marion County",
    "wof:placetype":"venue"
},
  "geometry": {"coordinates":[-82.0909,29.195142],"type":"Point"}
}