{
  "type": "Feature",
  "properties": {
    "iso:country":"US",
    "sg:address":"4340 NW 10th Ave",
    "sg:city":"Fort Lauderdale",
    "sg:classifiers":[
        {
            "category":"Building & Trades",
            "subcategory":"Construction",
            "type":"Services"
        }
    ],
    "sg:phone":"+1 954 771 8556",
    "sg:postcode":"33309",
    "sg:province":"FL",
    "sg:tags":[
        "maker",
        "cabinet"
    ],
    "wof:name":"E G Cabinets & Custom Frntr",
    "wof:placetype":"venue"
},
  "geometry": {"coordinates":[-80.15873499999999,26.176447],"type":"Point"}
}