{
  "type": "Feature",
  "properties": {
    "iso:country":"US",
    "sg:address":"2834 N Miami Ave",
    "sg:city":"Miami",
    "sg:classifiers":[
        {
            "category":"Food & Beverages",
            "subcategory":"Groceries & Convenience Stores",
            "type":"Retail Goods"
        }
    ],
    "sg:phone":"+1 305 573 5773",
    "sg:postcode":"33127",
    "sg:province":"FL",
    "wof:name":"Cerro Market",
    "wof:placetype":"venue"
},
  "geometry": {"coordinates":[-80.19520300000001,25.803732],"type":"Point"}
}