{
  "type": "Feature",
  "properties": {
    "addr:full":"1601 Biscayne Blvd Miami FL 33132",
    "addr:housenumber":"1601",
    "addr:postcode":"33132",
    "addr:street":"Biscayne Blvd",
    "iso:country":"US",
    "sg:address":"1601 Biscayne Blvd",
    "sg:city":"Miami",
    "sg:classifiers":[
        {
            "category":"Travel",
            "subcategory":"Hotels & Motels",
            "type":"Entertainment"
        }
    ],
    "sg:phone":"+1 305 374 0000",
    "sg:postcode":"33132",
    "sg:province":"FL",
    "sg:website":"hiltonmiamidowntown.com/",
    "wof:name":"Hilton Miami Downtown",
    "wof:placetype":"venue"
},
  "geometry": {"coordinates":[-80.188874,25.790755],"type":"Point"}
}