{
  "type": "Feature",
  "properties": {
    "addr:full":"1206 Columbia Way Cocoa FL 32922",
    "addr:housenumber":"1206",
    "addr:postcode":"32922",
    "addr:street":"Columbia Way",
    "iso:country":"US",
    "sg:address":"1206 Columbia Way",
    "sg:city":"Cocoa",
    "sg:classifiers":[
        {
            "category":"Professional",
            "subcategory":"Business Services",
            "type":"Services"
        }
    ],
    "sg:phone":"+1 321 632 2519",
    "sg:postcode":"32922",
    "sg:province":"FL",
    "wof:name":"Worldwide Debit Corp",
    "wof:placetype":"venue"
},
  "geometry": {"coordinates":[-80.74950200000001,28.378793],"type":"Point"}
}