{
  "type": "Feature",
  "properties": {
    "iso:country":"US",
    "sg:address":"1445 N Congress Ave",
    "sg:city":"Delray Beach",
    "sg:classifiers":[
        {
            "category":"Retail",
            "subcategory":"Repair Shop",
            "type":"Services"
        }
    ],
    "sg:phone":"+1 561 274 8111",
    "sg:postcode":"33445",
    "sg:province":"FL",
    "sg:tags":[
        "equipment",
        "good",
        "golf",
        "refinishing",
        "mfg"
    ],
    "wof:name":"Custom Clubs By Pinehurst Golf",
    "wof:placetype":"venue"
},
  "geometry": {"coordinates":[-80.08982899999999,26.482585],"type":"Point"}
}