{
  "type": "Feature",
  "properties": {
    "addr:full":"444 NW 79th Ave Miami FL 33126",
    "addr:housenumber":"444",
    "addr:postcode":"33126",
    "addr:street":"Nw 79Th Ave",
    "iso:country":"US",
    "sg:address":"444 NW 79th Ave",
    "sg:city":"Miami",
    "sg:classifiers":[
        {
            "category":"Wholesale",
            "subcategory":"Computers",
            "type":"Manufacturing & Wholesale Goods"
        }
    ],
    "sg:phone":"+1 305 265 7815",
    "sg:postcode":"33126",
    "sg:province":"FL",
    "sg:website":"www.alienware.com/",
    "wof:name":"Alienware Corp",
    "wof:placetype":"venue"
},
  "geometry": {"coordinates":[-80.324203,25.7743],"type":"Point"}
}