{
  "type": "Feature",
  "properties": {
    "addr:full":"12957 SW 134th Ct Miami FL 33186",
    "addr:housenumber":"12957",
    "addr:postcode":"33186",
    "addr:street":"Sw 134Th Ct",
    "iso:country":"US",
    "sg:address":"12957 SW 134th Ct",
    "sg:city":"Miami",
    "sg:classifiers":[
        {
            "category":"Autos & Motor Vehicles",
            "subcategory":"Auto Supplies",
            "type":"Retail Goods"
        },
        {
            "category":"Retail",
            "subcategory":"Auto Repair",
            "type":"Services"
        }
    ],
    "sg:phone":"+1 305 253 8902",
    "sg:postcode":"33186",
    "sg:province":"FL",
    "sg:tags":[
        "transmission",
        "transmissions-other"
    ],
    "wof:name":"Kendall Automatic Transmission Inc",
    "wof:placetype":"venue"
},
  "geometry": {"coordinates":[-80.412194,25.647244],"type":"Point"}
}