{
  "type": "Feature",
  "properties": {
    "addr:full":"3672 Bramble Rd Jacksonville FL 32210",
    "addr:housenumber":"3672",
    "addr:postcode":"32210",
    "addr:street":"Bramble Rd",
    "iso:country":"US",
    "sg:address":"3672 Bramble Rd",
    "sg:city":"Jacksonville",
    "sg:classifiers":[
        {
            "category":"Professional",
            "subcategory":"Management & Consulting",
            "type":"Services"
        }
    ],
    "sg:phone":"+1 904 374 9230",
    "sg:postcode":"32210",
    "sg:province":"FL",
    "sg:tags":[
        "business"
    ],
    "wof:name":"Ada Consultants of Ne Florida",
    "wof:placetype":"venue"
},
  "geometry": {"coordinates":[-81.78594200000001,30.268999],"type":"Point"}
}