{
  "type": "Feature",
  "properties": {
    "iso:country":"US",
    "sg:address":"100 West Bay Street",
    "sg:city":"Jacksonville",
    "sg:classifiers":[
        {
            "category":"Professional",
            "subcategory":"Computer Services",
            "type":"Services"
        }
    ],
    "sg:phone":"+1 866 961 9529",
    "sg:postcode":"32202",
    "sg:province":"FL",
    "sg:website":"http://www.fortegrafinancial.com/",
    "wof:name":"Fortegra Financial",
    "wof:placetype":"venue"
},
  "geometry": {"coordinates":[-81.660635,30.326836],"type":"Point"}
}