{
  "type": "Feature",
  "properties": {
    "addr:full":"6731 15th St E Sarasota FL 34243",
    "addr:housenumber":"6731",
    "addr:postcode":"34243",
    "addr:street":"15Th St E",
    "iso:country":"US",
    "sg:address":"6731 15th St E",
    "sg:city":"Sarasota",
    "sg:classifiers":[
        {
            "category":"Retail",
            "subcategory":"Auto Repair",
            "type":"Services"
        }
    ],
    "sg:phone":"+1 941 752 0666",
    "sg:postcode":"34243",
    "sg:province":"FL",
    "sg:tags":[
        "automobile",
        "imported"
    ],
    "wof:name":"Hellier Group Import Auto",
    "wof:placetype":"venue"
},
  "geometry": {"coordinates":[-82.54664699999999,27.420628],"type":"Point"}
}