{
  "type": "Feature",
  "properties": {
    "iso:country":"US",
    "sg:address":"4929 S West Shore Blvd",
    "sg:city":"Tampa",
    "sg:classifiers":[
        {
            "category":"Professional",
            "subcategory":"Management & Consulting",
            "type":"Services"
        }
    ],
    "sg:phone":"+1 813 831 7400",
    "sg:postcode":"33611",
    "sg:province":"FL",
    "sg:tags":[
        "employee",
        "consultant",
        "benefit"
    ],
    "wof:name":"SIG Benefits",
    "wof:placetype":"venue"
},
  "geometry": {"coordinates":[-82.5269,27.892685],"type":"Point"}
}