{
  "type": "Feature",
  "properties": {
    "iso:country":"US",
    "sg:address":"8599 Uranus Ter",
    "sg:city":"West Palm Beach",
    "sg:classifiers":[
        {
            "category":"Shopping",
            "subcategory":"Shoes",
            "type":"Retail Goods"
        }
    ],
    "sg:phone":"+1 561 691 0746",
    "sg:postcode":"33403",
    "sg:province":"FL",
    "wof:name":"Calzado Edgar Piedad Z",
    "wof:placetype":"venue"
},
  "geometry": {"coordinates":[-80.09175999999999,26.803289],"type":"Point"}
}