{
  "type": "Feature",
  "properties": {
    "iso:country":"US",
    "sg:address":"2279 S University Dr",
    "sg:city":"Fort Lauderdale",
    "sg:classifiers":[
        {
            "category":"Shopping",
            "subcategory":"Optical Goods",
            "type":"Retail Goods"
        }
    ],
    "sg:phone":"+1 954 474 9823",
    "sg:postcode":"33324",
    "sg:province":"FL",
    "sg:tags":[
        "store"
    ],
    "wof:name":"Jazzy Eyes Inc",
    "wof:placetype":"venue"
},
  "geometry": {"coordinates":[-80.251177,26.093277],"type":"Point"}
}