{
  "type": "Feature",
  "properties": {
    "iso:country":"US",
    "sg:address":"2220 Mcrae Ave",
    "sg:city":"Orlando",
    "sg:classifiers":[
        {
            "category":"Shopping",
            "subcategory":"Gifts & Souvenirs",
            "type":"Retail Goods"
        }
    ],
    "sg:phone":"+1 407 303 2706",
    "sg:postcode":"32803",
    "sg:province":"FL",
    "sg:tags":[
        "shop"
    ],
    "sg:website":"http://www.ahss.org",
    "wof:name":"Florida Hospital Gift Sp Whse",
    "wof:placetype":"venue"
},
  "geometry": {"coordinates":[-81.372286,28.571541],"type":"Point"}
}