{
  "type": "Feature",
  "properties": {
    "iso:country":"US",
    "sg:address":"3522 Buffam Pl",
    "sg:city":"Casselberry",
    "sg:classifiers":[
        {
            "category":"Building & Trades",
            "subcategory":"Electrical",
            "type":"Services"
        }
    ],
    "sg:phone":"+1 407 644 2332",
    "sg:postcode":"32707",
    "sg:province":"FL",
    "sg:tags":[
        "electrical",
        "contractor"
    ],
    "wof:name":"Hines Electric Co",
    "wof:placetype":"venue"
},
  "geometry": {"coordinates":[-81.285675,28.653352],"type":"Point"}
}