{
  "type": "Feature",
  "properties": {
    "addr:full":"2014 Cortez Rd W Bradenton FL 34207",
    "addr:housenumber":"2014",
    "addr:postcode":"34207",
    "addr:street":"Cortez Rd W",
    "iso:country":"US",
    "sg:address":"2014 Cortez Rd W",
    "sg:city":"Bradenton",
    "sg:classifiers":[
        {
            "category":"Personal",
            "subcategory":"Beauty Salon",
            "type":"Services"
        }
    ],
    "sg:phone":"+1 941 758 1332",
    "sg:postcode":"34207",
    "sg:province":"FL",
    "wof:name":"Sorrento Beauty Salon",
    "wof:placetype":"venue"
},
  "geometry": {"coordinates":[-82.58542199999999,27.462569],"type":"Point"}
}