{
  "type": "Feature",
  "properties": {
    "addr:full":"2660 Fawn Lake Blvd Mims FL 32754",
    "addr:housenumber":"2660",
    "addr:postcode":"32754",
    "addr:street":"Fawn Lake Blvd",
    "iso:country":"US",
    "sg:address":"2660 Fawn Lake Blvd",
    "sg:city":"Mims",
    "sg:classifiers":[
        {
            "category":"Manufacturing",
            "subcategory":"Tools & Machinery",
            "type":"Manufacturing & Wholesale Goods"
        }
    ],
    "sg:phone":"+1 321 264 1645",
    "sg:postcode":"32754",
    "sg:province":"FL",
    "sg:tags":[
        "mfg"
    ],
    "wof:name":"Moore Controls Inc",
    "wof:placetype":"venue"
},
  "geometry": {"coordinates":[-80.893242,28.674307],"type":"Point"}
}