{
  "type": "Feature",
  "properties": {
    "iso:country":"US",
    "sg:address":"549 Spinnaker Dr",
    "sg:city":"Marco Island",
    "sg:classifiers":[
        {
            "category":"Building & Trades",
            "subcategory":"Construction",
            "type":"Services"
        }
    ],
    "sg:phone":"+1 239 394 3861",
    "sg:postcode":"34145",
    "sg:province":"FL",
    "sg:tags":[
        "painter"
    ],
    "wof:name":"Chuck Corrado Decorating",
    "wof:placetype":"venue"
},
  "geometry": {"coordinates":[-81.746137,25.951729],"type":"Point"}
}