{
  "type": "Feature",
  "properties": {
    "addr:full":"4671 S Congress Ave Lake Worth FL 33461",
    "addr:housenumber":"4671",
    "addr:postcode":"33461",
    "addr:street":"S Congress Ave",
    "iso:country":"US",
    "sg:address":"4671 S Congress Ave",
    "sg:city":"Lake Worth",
    "sg:classifiers":[
        {
            "category":"Real Estate",
            "subcategory":"Real Estate Agent",
            "type":"Services"
        }
    ],
    "sg:phone":"+1 561 641 7503",
    "sg:postcode":"33461",
    "sg:province":"FL",
    "wof:name":"Green Field Properties",
    "wof:placetype":"venue"
},
  "geometry": {"coordinates":[-80.089517,26.607943],"type":"Point"}
}