{
  "type": "Feature",
  "properties": {
    "addr:full":"1497 SE 17th St Fort Lauderdale FL 33316",
    "addr:housenumber":"1497",
    "addr:postcode":"33316",
    "addr:street":"Se 17Th St",
    "iso:country":"US",
    "sg:address":"1497 SE 17th St",
    "sg:city":"Fort Lauderdale",
    "sg:classifiers":[
        {
            "category":"Utilities",
            "subcategory":"Telephone",
            "type":"Services"
        }
    ],
    "sg:phone":"+1 954 332 3101",
    "sg:postcode":"33316",
    "sg:province":"FL",
    "sg:tags":[
        "telecommunication"
    ],
    "wof:name":"Enet Cafe",
    "wof:placetype":"venue"
},
  "geometry": {"coordinates":[-80.13063,26.100509],"type":"Point"}
}