{
  "type": "Feature",
  "properties": {
    "addr:full":"2632 Hollywood Blvd Hollywood FL 33020",
    "addr:housenumber":"2632",
    "addr:postcode":"33020",
    "addr:street":"Hollywood Blvd",
    "iso:country":"US",
    "sg:address":"2632 Hollywood Blvd",
    "sg:city":"Hollywood",
    "sg:classifiers":[
        {
            "category":"Insurance",
            "subcategory":"Insurance Agent",
            "type":"Services"
        }
    ],
    "sg:phone":"+1 954 920 6814",
    "sg:postcode":"33020",
    "sg:province":"FL",
    "wof:name":"Liberty National Life Insur Co",
    "wof:placetype":"venue"
},
  "geometry": {"coordinates":[-80.160415,26.011156],"type":"Point"}
}