{
  "type": "Feature",
  "properties": {
    "iso:country":"US",
    "sg:address":"660 Celebration Ave",
    "sg:city":"Kissimmee",
    "sg:classifiers":[
        {
            "category":"Manufacturing",
            "subcategory":"Printing",
            "type":"Manufacturing & Wholesale Goods"
        }
    ],
    "sg:phone":"+1 407 566 1033",
    "sg:postcode":"34747",
    "sg:province":"FL",
    "sg:tags":[
        "newsletter"
    ],
    "wof:name":"Mc Donald Financial Svc",
    "wof:placetype":"venue"
},
  "geometry": {"coordinates":[-81.53587899999999,28.320314],"type":"Point"}
}