{
  "type": "Feature",
  "properties": {
    "iso:country":"US",
    "sg:address":"105 Center St",
    "sg:city":"Jupiter",
    "sg:classifiers":[
        {
            "category":"Home & Garden",
            "subcategory":"Furniture",
            "type":"Retail Goods"
        }
    ],
    "sg:phone":"+1 561 575 5414",
    "sg:postcode":"33458",
    "sg:province":"FL",
    "wof:name":"Fifth Ave Furniture",
    "wof:placetype":"venue"
},
  "geometry": {"coordinates":[-80.094589,26.941541],"type":"Point"}
}