{
  "type": "Feature",
  "properties": {
    "iso:country":"US",
    "sg:address":"8260 Spicewood Rd",
    "sg:city":"Pensacola",
    "sg:classifiers":[
        {
            "category":"Building & Trades",
            "subcategory":"Construction",
            "type":"Services"
        }
    ],
    "sg:phone":"+1 850 944 8947",
    "sg:postcode":"32526",
    "sg:province":"FL",
    "sg:tags":[
        "hanging",
        "contractor"
    ],
    "wof:name":"John Wheat Painting Inc",
    "wof:placetype":"venue"
},
  "geometry": {"coordinates":[-87.417248,30.549273],"type":"Point"}
}