{
  "type": "Feature",
  "properties": {
    "iso:country":"US",
    "sg:address":"3008 Kenilworth Blvd",
    "sg:city":"Sebring",
    "sg:classifiers":[
        {
            "category":"Freight",
            "type":"Transportation"
        }
    ],
    "sg:phone":"+1 863 382 0040",
    "sg:postcode":"33870",
    "sg:province":"FL",
    "sg:tags":[
        "delivery",
        "grocery"
    ],
    "wof:name":"J & S Foods",
    "wof:placetype":"venue"
},
  "geometry": {"coordinates":[-81.436455,27.485831],"type":"Point"}
}