{
  "type": "Feature",
  "properties": {
    "addr:full":"2905 NW 87th Ave Mia Doral FL 33172",
    "addr:housenumber":"2905",
    "addr:postcode":"33172",
    "addr:street":"Nw 87Th Ave",
    "iso:country":"US",
    "sg:address":"2905 NW 87th Ave Mia",
    "sg:city":"Doral",
    "sg:classifiers":[
        {
            "category":"Wholesale",
            "subcategory":"Books, Periodicals, & Newspapers",
            "type":"Manufacturing & Wholesale Goods"
        }
    ],
    "sg:phone":"+1 305 599 0037",
    "sg:postcode":"33172",
    "sg:province":"FL",
    "sg:tags":[
        "publisher",
        "book"
    ],
    "sg:website":"http://www.baschool.org",
    "wof:name":"Inter-American Division Publishing Association,",
    "wof:placetype":"venue"
},
  "geometry": {"coordinates":[-80.337075,25.80142],"type":"Point"}
}