{
  "type": "Feature",
  "properties": {
    "iso:country":"US",
    "sg:address":"10870 NW 5th St",
    "sg:city":"Fort Lauderdale",
    "sg:classifiers":[
        {
            "category":"Real Estate",
            "subcategory":"Real Estate Operator",
            "type":"Services"
        }
    ],
    "sg:phone":"+1 954 382 0372",
    "sg:postcode":"33324",
    "sg:province":"FL",
    "sg:tags":[
        "building",
        "apartment"
    ],
    "wof:name":"Fairview Apts",
    "wof:placetype":"venue"
},
  "geometry": {"coordinates":[-80.29410300000001,26.125089],"type":"Point"}
}