{
  "type": "Feature",
  "properties": {
    "iso:country":"US",
    "sg:address":"201 Ponce de Leon Blvd",
    "sg:city":"Brooksville",
    "sg:classifiers":[
        {
            "category":"Autos & Motor Vehicles",
            "subcategory":"Automobile Sales",
            "type":"Retail Goods"
        }
    ],
    "sg:phone":"+1 352 799 0017",
    "sg:postcode":"34601",
    "sg:province":"FL",
    "sg:tags":[
        "dealers-used",
        "car",
        "used",
        "cars-wholesale",
        "new"
    ],
    "wof:name":"Town Motors",
    "wof:placetype":"venue"
},
  "geometry": {"coordinates":[-82.397614,28.55628],"type":"Point"}
}