{
  "type": "Feature",
  "properties": {
    "iso:country":"US",
    "sg:address":"14010 Old Dixie Hwy",
    "sg:city":"Hudson",
    "sg:classifiers":[
        {
            "category":"Professional",
            "type":"Services"
        }
    ],
    "sg:phone":"+1 727 863 2211",
    "sg:postcode":"34667",
    "sg:province":"FL",
    "sg:tags":[
        "establishment"
    ],
    "wof:name":"Ambassador Enterprises",
    "wof:placetype":"venue"
},
  "geometry": {"coordinates":[-82.698869,28.360771],"type":"Point"}
}