{
  "type": "Feature",
  "properties": {
    "addr:full":"10892 State Hwy 50 Ocoee FL 34761",
    "addr:housenumber":"10892",
    "addr:postcode":"34761",
    "addr:street":"State Hwy 50",
    "iso:country":"US",
    "sg:address":"10892 State Hwy 50",
    "sg:city":"Ocoee",
    "sg:classifiers":[
        {
            "category":"Shopping",
            "subcategory":"Used Merchandise",
            "type":"Retail Goods"
        }
    ],
    "sg:phone":"+1 407 656 8338",
    "sg:postcode":"34761",
    "sg:province":"FL",
    "wof:name":"New Hope Gift & Thrift Inc",
    "wof:placetype":"venue"
},
  "geometry": {"coordinates":[-81.54019099999999,28.551557],"type":"Point"}
}