{
  "type": "Feature",
  "properties": {
    "iso:country":"US",
    "sg:address":"1201 S Ocean Blvd",
    "sg:city":"Pompano Beach",
    "sg:classifiers":[
        {
            "category":"Retail",
            "subcategory":"Laundry & Dry Cleaning",
            "type":"Services"
        }
    ],
    "sg:phone":"+1 954 782 8811",
    "sg:postcode":"33062",
    "sg:province":"FL",
    "sg:tags":[
        "garment",
        "agent"
    ],
    "wof:name":"A1a Cleaners & Alterations",
    "wof:placetype":"venue"
},
  "geometry": {"coordinates":[-80.09126500000001,26.222879],"type":"Point"}
}