{
  "type": "Feature",
  "properties": {
    "addr:full":"1314 Stetson St Orlando FL 32804",
    "addr:housenumber":"1314",
    "addr:postcode":"32804",
    "addr:street":"Stetson St",
    "iso:country":"US",
    "sg:address":"1314 Stetson St",
    "sg:city":"Orlando",
    "sg:classifiers":[
        {
            "category":"Professional",
            "subcategory":"Management & Consulting",
            "type":"Services"
        }
    ],
    "sg:phone":"+1 407 857 0060",
    "sg:postcode":"32804",
    "sg:province":"FL",
    "sg:tags":[
        "marketing",
        "program"
    ],
    "wof:name":"Orlando 4 Free",
    "wof:placetype":"venue"
},
  "geometry": {"coordinates":[-81.399407,28.568213],"type":"Point"}
}