{
  "type": "Feature",
  "properties": {
    "iso:country":"US",
    "sg:address":"542 Dundee Rd",
    "sg:city":"Dundee",
    "sg:classifiers":[
        {
            "category":"Food & Beverages",
            "subcategory":"Groceries & Convenience Stores",
            "type":"Retail Goods"
        }
    ],
    "sg:phone":"+1 863 439 2540",
    "sg:postcode":"33838",
    "sg:province":"FL",
    "sg:tags":[
        "grocer"
    ],
    "wof:name":"A & N Food Inc",
    "wof:placetype":"venue"
},
  "geometry": {"coordinates":[-81.629453,28.018767],"type":"Point"}
}