{
  "type": "Feature",
  "properties": {
    "addr:full":"2650 Airport Pulling Rd S Naples FL 34112",
    "addr:housenumber":"2650",
    "addr:postcode":"34112",
    "addr:street":"Airport Pulling Rd S",
    "iso:country":"US",
    "sg:address":"2650 Airport Pulling Rd S",
    "sg:city":"Naples",
    "sg:classifiers":[
        {
            "category":"Insurance",
            "subcategory":"Hazard Insurance",
            "type":"Services"
        }
    ],
    "sg:phone":"+1 239 417 2168",
    "sg:postcode":"34112",
    "sg:province":"FL",
    "sg:tags":[
        "bond"
    ],
    "wof:name":"Florida Agency-Investigations",
    "wof:placetype":"venue"
},
  "geometry": {"coordinates":[-81.766426,26.127171],"type":"Point"}
}