{
  "type": "Feature",
  "properties": {
    "addr:full":"670 Central Ave St Petersburg FL 33701",
    "addr:housenumber":"670",
    "addr:postcode":"33701",
    "addr:street":"Central Ave",
    "iso:country":"US",
    "sg:address":"670 Central Ave",
    "sg:city":"St Petersburg",
    "sg:classifiers":[
        {
            "category":"Shopping",
            "subcategory":"Used Merchandise",
            "type":"Retail Goods"
        }
    ],
    "sg:phone":"+1 727 894 0325",
    "sg:postcode":"33701",
    "sg:province":"FL",
    "sg:tags":[
        "shop",
        "consignment"
    ],
    "wof:name":"Sequins & Denim Inc",
    "wof:placetype":"venue"
},
  "geometry": {"coordinates":[-82.641729,27.7712],"type":"Point"}
}