{
  "type": "Feature",
  "properties": {
    "iso:country":"US",
    "sg:address":"16850 S Glades Dr",
    "sg:city":"Miami",
    "sg:classifiers":[
        {
            "category":"Organizations",
            "subcategory":"Community Association",
            "type":"Services"
        }
    ],
    "sg:phone":"+1 305 947 6242",
    "sg:postcode":"33162",
    "sg:province":"FL",
    "sg:tags":[
        "condominium"
    ],
    "wof:name":"Andor Plaza Apts",
    "wof:placetype":"venue"
},
  "geometry": {"coordinates":[-80.169415,25.930871],"type":"Point"}
}