{
  "type": "Feature",
  "properties": {
    "addr:full":"1818 Tennessee Ave Lynn Haven FL 32444",
    "addr:housenumber":"1818",
    "addr:postcode":"32444",
    "addr:street":"Tennessee Ave",
    "iso:country":"US",
    "sg:address":"1818 Tennessee Ave",
    "sg:city":"Lynn Haven",
    "sg:classifiers":[
        {
            "category":"Retail",
            "subcategory":"Auto Repair",
            "type":"Services"
        }
    ],
    "sg:phone":"+1 850 271 3456",
    "sg:postcode":"32444",
    "sg:province":"FL",
    "sg:tags":[
        "repairing",
        "automobile"
    ],
    "wof:name":"C & J Automotive",
    "wof:placetype":"venue"
},
  "geometry": {"coordinates":[-85.655832,30.231429],"type":"Point"}
}