{
  "type": "Feature",
  "properties": {
    "iso:country":"US",
    "sg:address":"18770 SE River Ridge Ct",
    "sg:city":"Jupiter",
    "sg:classifiers":[
        {
            "category":"Manufacturing",
            "subcategory":"Rubber & Plastics",
            "type":"Manufacturing & Wholesale Goods"
        }
    ],
    "sg:phone":"+1 561 744 3007",
    "sg:postcode":"33469",
    "sg:province":"FL",
    "wof:name":"Palm Beach Plastics LLC",
    "wof:placetype":"venue"
},
  "geometry": {"coordinates":[-80.112123,26.975883],"type":"Point"}
}