{
  "type": "Feature",
  "properties": {
    "iso:country":"US",
    "sg:address":"1750 W Broadway St # 106",
    "sg:city":"Oviedo",
    "sg:classifiers":[
        {
            "category":"Real Estate",
            "subcategory":"Real Estate Services",
            "type":"Services"
        },
        {
            "category":"Real Estate",
            "subcategory":"Real Estate Agent",
            "type":"Services"
        }
    ],
    "sg:phone":"+1 407 463 1120",
    "sg:postcode":"32765",
    "sg:province":"FL",
    "sg:tags":[
        "buyer",
        "broker"
    ],
    "wof:name":"Donna Ashley Realtors",
    "wof:placetype":"venue"
},
  "geometry": {"coordinates":[-81.224478,28.658061],"type":"Point"}
}