{
  "type": "Feature",
  "properties": {
    "iso:country":"US",
    "sg:address":"12890 SW 116th St",
    "sg:city":"Miami",
    "sg:classifiers":[
        {
            "category":"Shopping",
            "subcategory":"Clothing, Apparel, & Fashions",
            "type":"Retail Goods"
        }
    ],
    "sg:phone":"+1 305 386 7357",
    "sg:postcode":"33186",
    "sg:province":"FL",
    "wof:name":"Nicks Phat",
    "wof:placetype":"venue"
},
  "geometry": {"coordinates":[-80.403952,25.660817],"type":"Point"}
}