{
  "type": "Feature",
  "properties": {
    "iso:country":"US",
    "sg:address":"1431 Lake Erie Dr",
    "sg:city":"Lake Worth",
    "sg:classifiers":[
        {
            "category":"Building & Trades",
            "subcategory":"Construction",
            "type":"Services"
        }
    ],
    "sg:phone":"+1 561 586 8384",
    "sg:postcode":"33461",
    "sg:province":"FL",
    "sg:tags":[
        "contractor"
    ],
    "wof:name":"W E Lyle Enterprises Inc",
    "wof:placetype":"venue"
},
  "geometry": {"coordinates":[-80.075278,26.591595],"type":"Point"}
}