{
  "type": "Feature",
  "properties": {
    "addr:full":"5517 Baker Rd New Port Richey FL 34653",
    "addr:housenumber":"5517",
    "addr:postcode":"34653",
    "addr:street":"Baker Rd",
    "iso:country":"US",
    "sg:address":"5517 Baker Rd",
    "sg:city":"New Port Richey",
    "sg:classifiers":[
        {
            "category":"Building & Trades",
            "subcategory":"Cleaning & Sanitation",
            "type":"Services"
        }
    ],
    "sg:phone":"+1 727 848 6696",
    "sg:postcode":"34653",
    "sg:province":"FL",
    "sg:tags":[
        "carwash",
        "maintenance"
    ],
    "wof:name":"Lynton J Fairhurst",
    "wof:placetype":"venue"
},
  "geometry": {"coordinates":[-82.700813,28.240842],"type":"Point"}
}