{
  "type": "Feature",
  "properties": {
    "addr:full":"813 Nightingale Rd Jacksonville FL 32216",
    "addr:housenumber":"813",
    "addr:postcode":"32216",
    "addr:street":"Nightingale Rd",
    "iso:country":"US",
    "sg:address":"813 Nightingale Rd",
    "sg:city":"Jacksonville",
    "sg:classifiers":[
        {
            "category":"Building & Trades",
            "subcategory":"Construction",
            "type":"Services"
        }
    ],
    "sg:phone":"+1 904 725 7047",
    "sg:postcode":"32216",
    "sg:province":"FL",
    "sg:tags":[
        "hanging",
        "contractor"
    ],
    "wof:name":"Brian Cason Painting",
    "wof:placetype":"venue"
},
  "geometry": {"coordinates":[-81.588204,30.300673],"type":"Point"}
}