{
  "type": "Feature",
  "properties": {
    "iso:country":"US",
    "sg:address":"2601 Reed Ave",
    "sg:city":"Melbourne",
    "sg:classifiers":[
        {
            "category":"Professional",
            "subcategory":"Business Services",
            "type":"Services"
        }
    ],
    "sg:phone":"+1 321 837 0316",
    "sg:postcode":"32901",
    "sg:province":"FL",
    "sg:tags":[
        "organizing",
        "services-household"
    ],
    "sg:website":"http://www.dennishanda.com",
    "wof:name":"D H Management Inc",
    "wof:placetype":"venue"
},
  "geometry": {"coordinates":[-80.63117200000001,28.06954],"type":"Point"}
}