{
  "type": "Feature",
  "properties": {
    "iso:country":"US",
    "sg:address":"13621 NW 9th Ter",
    "sg:city":"Miami",
    "sg:classifiers":[
        {
            "category":"Professional",
            "subcategory":"Computer Services",
            "type":"Services"
        }
    ],
    "sg:phone":"+1 305 551 8934",
    "sg:postcode":"33182",
    "sg:province":"FL",
    "sg:tags":[
        "consultant",
        "designer",
        "system"
    ],
    "wof:name":"Alberto J Lorenzo",
    "wof:placetype":"venue"
},
  "geometry": {"coordinates":[-80.41536000000001,25.778193],"type":"Point"}
}