{
  "type": "Feature",
  "properties": {
    "addr:full":"6023 Bania Wood Cir Lake Worth FL 33462",
    "addr:postcode":"6023;33462",
    "addr:street":"Wood Cir",
    "iso:country":"US",
    "sg:address":"6023 Bania Wood Cir",
    "sg:city":"Lake Worth",
    "sg:classifiers":[
        {
            "category":"Professional",
            "type":"Services"
        }
    ],
    "sg:phone":"+1 561 964 9171",
    "sg:postcode":"33462",
    "sg:province":"FL",
    "wof:name":"Cindy Adair PA",
    "wof:placetype":"venue"
},
  "geometry": {"coordinates":[-80.111028,26.587718],"type":"Point"}
}