{
  "type": "Feature",
  "properties": {
    "addr:full":"10301 Marsh Harbor Way Riverview FL 33578",
    "addr:housenumber":"10301",
    "addr:postcode":"33578",
    "addr:street":"Marsh Harbor Way",
    "iso:country":"US",
    "sg:address":"10301 Marsh Harbor Way",
    "sg:city":"Riverview",
    "sg:classifiers":[
        {
            "category":"Real Estate",
            "subcategory":"Real Estate Operator",
            "type":"Services"
        }
    ],
    "sg:phone":"+1 813 622 7229",
    "sg:postcode":"33578",
    "sg:province":"FL",
    "sg:tags":[
        "building",
        "apartment",
        "complex"
    ],
    "wof:name":"Polos At Brandon The",
    "wof:placetype":"venue"
},
  "geometry": {"coordinates":[-82.342511,27.920458],"type":"Point"}
}