{
  "type": "Feature",
  "properties": {
    "addr:full":"308 N Salisbury Ave Deland FL 32720",
    "addr:housenumber":"308",
    "addr:postcode":"32720",
    "addr:street":"N Salisbury Ave",
    "iso:country":"US",
    "sg:address":"308 N Salisbury Ave",
    "sg:city":"Deland",
    "sg:classifiers":[
        {
            "category":"Building & Trades",
            "subcategory":"Pest Control",
            "type":"Services"
        }
    ],
    "sg:phone":"+1 386 736 0393",
    "sg:postcode":"32720",
    "sg:province":"FL",
    "wof:name":"Ladybug Pest Services",
    "wof:placetype":"venue"
},
  "geometry": {"coordinates":[-81.314796,29.0322],"type":"Point"}
}