{
  "type": "Feature",
  "properties": {
    "addr:full":"5926 W Hallandale Beach Blvd Hollywood FL 33023",
    "addr:housenumber":"5926",
    "addr:postcode":"33023",
    "addr:street":"W Hallandale Beach Blvd",
    "iso:country":"US",
    "sg:address":"5926 W Hallandale Beach Blvd",
    "sg:city":"Hollywood",
    "sg:classifiers":[
        {
            "category":"Shopping",
            "subcategory":"Used Merchandise",
            "type":"Retail Goods"
        }
    ],
    "sg:phone":"+1 954 981 0551",
    "sg:postcode":"33023",
    "sg:province":"FL",
    "sg:tags":[
        "pawnbroker"
    ],
    "wof:name":"Advantage Pawn & Loan",
    "wof:placetype":"venue"
},
  "geometry": {"coordinates":[-80.20616699999999,25.984575],"type":"Point"}
}