{
  "type": "Feature",
  "properties": {
    "iso:country":"US",
    "sg:address":"5355 2nd Ave S",
    "sg:city":"St Petersburg",
    "sg:classifiers":[
        {
            "category":"Health Services",
            "subcategory":"Clinic",
            "type":"Services"
        }
    ],
    "sg:phone":"+1 727 244 1653",
    "sg:postcode":"33707",
    "sg:province":"FL",
    "sg:tags":[
        "home"
    ],
    "wof:name":"Bear Hugs",
    "wof:placetype":"venue"
},
  "geometry": {"coordinates":[-82.70602100000001,27.769218],"type":"Point"}
}