{
  "type": "Feature",
  "properties": {
    "addr:full":"8410 SW 24th St Miami FL 33155",
    "addr:housenumber":"8410",
    "addr:postcode":"33155",
    "addr:street":"Sw 24Th St",
    "iso:country":"US",
    "sg:address":"8410 SW 24th St",
    "sg:city":"Miami",
    "sg:classifiers":[
        {
            "category":"Personal",
            "subcategory":"Barber",
            "type":"Services"
        }
    ],
    "sg:phone":"+1 305 552 9378",
    "sg:postcode":"33155",
    "sg:province":"FL",
    "sg:tags":[
        "shop"
    ],
    "wof:name":"Westchester Mall Barber Shop",
    "wof:placetype":"venue"
},
  "geometry": {"coordinates":[-80.335528,25.747563],"type":"Point"}
}