{
  "type": "Feature",
  "properties": {
    "addr:full":"9110 Anita Ave Englewood FL 34224",
    "addr:housenumber":"9110",
    "addr:postcode":"34224",
    "addr:street":"Anita Ave",
    "iso:country":"US",
    "sg:address":"9110 Anita Ave",
    "sg:city":"Englewood",
    "sg:classifiers":[
        {
            "category":"Building & Trades",
            "subcategory":"Landscaping Services",
            "type":"Services"
        }
    ],
    "sg:phone":"+1 941 320 3052",
    "sg:postcode":"34224",
    "sg:province":"FL",
    "sg:tags":[
        "landscape"
    ],
    "wof:name":"Doyle Nokomis Landscape Svc",
    "wof:placetype":"venue"
},
  "geometry": {"coordinates":[-82.302845,26.931519],"type":"Point"}
}