{
  "type": "Feature",
  "properties": {
    "addr:full":"720 Sesame St Englewood FL 34223",
    "addr:housenumber":"720",
    "addr:postcode":"34223",
    "addr:street":"Sesame St",
    "iso:country":"US",
    "sg:address":"720 Sesame St",
    "sg:city":"Englewood",
    "sg:classifiers":[
        {
            "category":"Home & Garden",
            "subcategory":"Home Furnishings",
            "type":"Retail Goods"
        }
    ],
    "sg:phone":"+1 941 474 0987",
    "sg:postcode":"34223",
    "sg:province":"FL",
    "sg:tags":[
        "curtain",
        "made",
        "drapery"
    ],
    "wof:name":"Custom Draperies & Blinds",
    "wof:placetype":"venue"
},
  "geometry": {"coordinates":[-82.367965,26.971828],"type":"Point"}
}