{
  "type": "Feature",
  "properties": {
    "iso:country":"US",
    "sg:address":"10690 SW 72nd St",
    "sg:city":"Miami",
    "sg:classifiers":[
        {
            "category":"Building & Trades",
            "subcategory":"Locksmith",
            "type":"Services"
        }
    ],
    "sg:phone":"+1 305 423 2056",
    "sg:postcode":"33173",
    "sg:province":"FL",
    "sg:tags":[
        "key"
    ],
    "wof:name":"Zero Waiting Accurate Locksmith",
    "wof:placetype":"venue"
},
  "geometry": {"coordinates":[-80.36583,25.700903],"type":"Point"}
}