{
  "type": "Feature",
  "properties": {
    "iso:country":"US",
    "sg:address":"625 Herndon Ave",
    "sg:city":"Orlando",
    "sg:classifiers":[
        {
            "category":"Shopping",
            "type":"Retail Goods"
        },
        {
            "category":"Wholesale",
            "subcategory":"Groceries",
            "type":"Manufacturing & Wholesale Goods"
        }
    ],
    "sg:phone":"+1 407 894 4458",
    "sg:postcode":"32803",
    "sg:province":"FL",
    "sg:tags":[
        "supply",
        "mi",
        "general",
        "equipment",
        "cake",
        "decorating"
    ],
    "wof:name":"D & G Occasions",
    "wof:placetype":"venue"
},
  "geometry": {"coordinates":[-81.337385,28.552976],"type":"Point"}
}