{
  "type": "Feature",
  "properties": {
    "addr:full":"1901 W Colonial Dr Orlando FL 32804",
    "addr:housenumber":"1901",
    "addr:postcode":"32804",
    "addr:street":"W Colonial Dr",
    "iso:country":"US",
    "sg:address":"1901 W Colonial Dr",
    "sg:city":"Orlando",
    "sg:classifiers":[
        {
            "category":"Professional",
            "subcategory":"Management & Consulting",
            "type":"Services"
        }
    ],
    "sg:phone":"+1 407 872 8466",
    "sg:postcode":"32804",
    "sg:province":"FL",
    "wof:name":"Norteam Inc",
    "wof:placetype":"venue"
},
  "geometry": {"coordinates":[-81.40569499999999,28.552868],"type":"Point"}
}