{
  "type": "Feature",
  "properties": {
    "iso:country":"US",
    "sg:address":"1082 Tupelo Way",
    "sg:city":"Fort Lauderdale",
    "sg:classifiers":[
        {
            "category":"Professional",
            "subcategory":"Computer Services",
            "type":"Services"
        }
    ],
    "sg:phone":"+1 954 217 1107",
    "sg:postcode":"33327",
    "sg:province":"FL",
    "sg:tags":[
        "design",
        "system"
    ],
    "wof:name":"My Family Web Doctor Inc",
    "wof:placetype":"venue"
},
  "geometry": {"coordinates":[-80.410847,26.120562],"type":"Point"}
}