{
  "type": "Feature",
  "properties": {
    "iso:country":"US",
    "sg:address":"777 S State Hwy 7",
    "sg:city":"Pompano Beach",
    "sg:classifiers":[
        {
            "category":"Shopping",
            "type":"Retail Goods"
        }
    ],
    "sg:phone":"+1 954 785 2970",
    "sg:postcode":"33068",
    "sg:province":"FL",
    "sg:tags":[
        "merchandise"
    ],
    "wof:name":"Ahhp",
    "wof:placetype":"venue"
},
  "geometry": {"coordinates":[-80.204539,26.222014],"type":"Point"}
}