{
  "type": "Feature",
  "properties": {
    "iso:country":"US",
    "sg:address":"2661 University Blvd N",
    "sg:city":"Jacksonville",
    "sg:classifiers":[
        {
            "category":"Freight",
            "type":"Transportation"
        }
    ],
    "sg:phone":"+1 904 551 5473",
    "sg:postcode":"32211",
    "sg:province":"FL",
    "sg:tags":[
        "operator",
        "local",
        "trucking"
    ],
    "wof:name":"O&H Trucking",
    "wof:placetype":"venue"
},
  "geometry": {"coordinates":[-81.60262299999999,30.3488],"type":"Point"}
}