{
  "type": "Feature",
  "properties": {
    "addr:full":"1221 NW 7th St Boynton Beach FL 33426",
    "addr:housenumber":"1221",
    "addr:postcode":"33426",
    "addr:street":"Nw 7Th St",
    "iso:country":"US",
    "sg:address":"1221 NW 7th St",
    "sg:city":"Boynton Beach",
    "sg:classifiers":[
        {
            "category":"Professional",
            "type":"Services"
        }
    ],
    "sg:phone":"+1 561 734 1720",
    "sg:postcode":"33426",
    "sg:province":"FL",
    "wof:name":"Jr Window & Door Inc",
    "wof:placetype":"venue"
},
  "geometry": {"coordinates":[-80.077189,26.537402],"type":"Point"}
}