{
  "type": "Feature",
  "properties": {
    "addr:full":"612 S Washington Ave Titusville FL 32796",
    "addr:housenumber":"612",
    "addr:postcode":"32796",
    "addr:street":"S Washington Ave",
    "iso:country":"US",
    "sg:address":"612 S Washington Ave",
    "sg:city":"Titusville",
    "sg:classifiers":[
        {
            "category":"Travel",
            "subcategory":"Hotels & Motels",
            "type":"Entertainment"
        }
    ],
    "sg:phone":"+1 321 267 4211",
    "sg:postcode":"32796",
    "sg:province":"FL",
    "sg:tags":[
        "operation"
    ],
    "wof:name":"Budget Motel",
    "wof:placetype":"venue"
},
  "geometry": {"coordinates":[-80.807669,28.608152],"type":"Point"}
}