{
  "type": "Feature",
  "properties": {
    "iso:country":"US",
    "sg:address":"2500 W Azeele St",
    "sg:city":"Tampa",
    "sg:phone":"+1 813 879 5228",
    "sg:postcode":"33609",
    "sg:province":"FL",
    "wof:name":"Circles",
    "wof:placetype":"venue"
},
  "geometry": {"coordinates":[-82.4851,27.941111],"type":"Point"}
}