{
  "type": "Feature",
  "properties": {
    "iso:country":"US",
    "sg:address":"3412 W San Luis St",
    "sg:city":"Tampa",
    "sg:classifiers":[
        {
            "category":"Personal",
            "subcategory":"Beauty Salon",
            "type":"Services"
        }
    ],
    "sg:phone":"+1 813 831 2747",
    "sg:postcode":"33629",
    "sg:province":"FL",
    "sg:tags":[
        "shop"
    ],
    "wof:name":"Salon National Laboutique",
    "wof:placetype":"venue"
},
  "geometry": {"coordinates":[-82.500319,27.915524],"type":"Point"}
}