{
  "type": "Feature",
  "properties": {
    "addr:full":"4917 Jupiter Rd Fort Myers FL 33905",
    "addr:housenumber":"4917",
    "addr:postcode":"33905",
    "addr:street":"Jupiter Rd",
    "iso:country":"US",
    "sg:address":"4917 Jupiter Rd",
    "sg:city":"Fort Myers",
    "sg:classifiers":[
        {
            "category":"Building & Trades",
            "subcategory":"Cleaning & Sanitation",
            "type":"Services"
        }
    ],
    "sg:phone":"+1 239 470 1722",
    "sg:postcode":"33905",
    "sg:province":"FL",
    "sg:tags":[
        "janitor"
    ],
    "wof:name":"William Love Janitorial Svc",
    "wof:placetype":"venue"
},
  "geometry": {"coordinates":[-81.808638,26.655394],"type":"Point"}
}