{
  "type": "Feature",
  "properties": {
    "iso:country":"US",
    "sg:address":"2768 NW 167th St",
    "sg:city":"Miami Gardens",
    "sg:classifiers":[
        {
            "category":"Personal",
            "subcategory":"Nail Salon",
            "type":"Services"
        }
    ],
    "sg:phone":"+1 305 623 3916",
    "sg:postcode":"33054",
    "sg:province":"FL",
    "wof:name":"Spring Nail",
    "wof:placetype":"venue"
},
  "geometry": {"coordinates":[-80.24601699999999,25.925826],"type":"Point"}
}