{
  "type": "Feature",
  "properties": {
    "addr:full":"1825 Rosseberry Ln Sanford FL 32771",
    "addr:housenumber":"1825",
    "addr:postcode":"32771",
    "addr:street":"Rosseberry Ln",
    "iso:country":"US",
    "sg:address":"1825 Rosseberry Ln",
    "sg:city":"Sanford",
    "sg:classifiers":[
        {
            "category":"Building & Trades",
            "subcategory":"Construction",
            "type":"Services"
        }
    ],
    "sg:phone":"+1 407 323 9463",
    "sg:postcode":"32771",
    "sg:province":"FL",
    "sg:tags":[
        "house",
        "contractor",
        "concrete"
    ],
    "wof:name":"Heard James Construction",
    "wof:placetype":"venue"
},
  "geometry": {"coordinates":[-81.246,28.797208],"type":"Point"}
}