{
  "type": "Feature",
  "properties": {
    "addr:full":"60 Memorial Medical Pkwy Palm Coast FL 32164",
    "addr:housenumber":"60",
    "addr:postcode":"32164",
    "addr:street":"Medical Pkwy",
    "iso:country":"US",
    "sg:address":"60 Memorial Medical Pkwy",
    "sg:city":"Palm Coast",
    "sg:classifiers":[
        {
            "category":"Health Services",
            "subcategory":"Optometrist",
            "type":"Services"
        }
    ],
    "sg:phone":"+1 386 734 7285",
    "sg:postcode":"32164",
    "sg:province":"FL",
    "wof:name":"Flagler Eye Ctr Pa",
    "wof:placetype":"venue"
},
  "geometry": {"coordinates":[-81.19044100000001,29.477791],"type":"Point"}
}