{
  "type": "Feature",
  "properties": {
    "addr:full":"9819 SW 190th Avenue Rd Dunnellon FL 34432",
    "addr:housenumber":"9819",
    "addr:postcode":"34432",
    "addr:street":"Sw 190Th Avenue Rd",
    "iso:country":"US",
    "sg:address":"9819 SW 190th Avenue Rd",
    "sg:city":"Dunnellon",
    "sg:classifiers":[
        {
            "category":"Manufacturing",
            "subcategory":"Motor Vehicles & Parts",
            "type":"Manufacturing & Wholesale Goods"
        }
    ],
    "sg:phone":"+1 352 465 3263",
    "sg:postcode":"34432",
    "sg:province":"FL",
    "sg:tags":[
        "component",
        "mfg"
    ],
    "wof:name":"Gw Sears Inc",
    "wof:placetype":"venue"
},
  "geometry": {"coordinates":[-82.43227,29.08091],"type":"Point"}
}