{
  "type": "Feature",
  "properties": {
    "iso:country":"US",
    "sg:address":"2150 W 68th St",
    "sg:city":"Hialeah",
    "sg:classifiers":[
        {
            "category":"Banks & Credit Unions",
            "subcategory":"Bank",
            "type":"Services"
        }
    ],
    "sg:phone":"+1 305 863 9665",
    "sg:postcode":"33016",
    "sg:province":"FL",
    "wof:name":"Eastern Financial Federal CU",
    "wof:placetype":"venue"
},
  "geometry": {"coordinates":[-80.32553900000001,25.884004],"type":"Point"}
}