{
  "type": "Feature",
  "properties": {
    "iso:country":"US",
    "sg:address":"1801 Tyndall Dr",
    "sg:city":"Panama City",
    "sg:classifiers":[
        {
            "category":"Marine",
            "type":"Transportation"
        }
    ],
    "sg:phone":"+1 850 763 5253",
    "sg:postcode":"32401",
    "sg:province":"FL",
    "sg:tags":[
        "water",
        "transport"
    ],
    "wof:name":"Downeaster Boat Inc",
    "wof:placetype":"venue"
},
  "geometry": {"coordinates":[-85.63705299999999,30.147363],"type":"Point"}
}