{
  "type": "Feature",
  "properties": {
    "iso:country":"US",
    "sg:address":"7753 N Davis Hwy",
    "sg:city":"Pensacola",
    "sg:classifiers":[
        {
            "category":"Restaurant",
            "type":"Food & Drink"
        }
    ],
    "sg:phone":"+1 850 474 0180",
    "sg:postcode":"32514",
    "sg:province":"FL",
    "sg:tags":[
        "eating"
    ],
    "wof:name":"Peking Garden Restaurant",
    "wof:placetype":"venue"
},
  "geometry": {"coordinates":[-87.22150000000001,30.505962],"type":"Point"}
}