{
  "type": "Feature",
  "properties": {
    "iso:country":"US",
    "sg:address":"2942 Nina Ct",
    "sg:city":"Merritt Island",
    "sg:classifiers":[
        {
            "category":"Manufacturing",
            "subcategory":"Apparel",
            "type":"Manufacturing & Wholesale Goods"
        }
    ],
    "sg:phone":"+1 321 452 0513",
    "sg:postcode":"32953",
    "sg:province":"FL",
    "wof:name":"Sunshine Embroidery",
    "wof:placetype":"venue"
},
  "geometry": {"coordinates":[-80.710302,28.410583],"type":"Point"}
}