{
  "type": "Feature",
  "properties": {
    "addr:full":"324 Ocean Ave Melbourne Beach FL 32951",
    "addr:housenumber":"324",
    "addr:postcode":"32951",
    "addr:street":"Ocean Ave",
    "iso:country":"US",
    "sg:address":"324 Ocean Ave",
    "sg:city":"Melbourne Beach",
    "sg:classifiers":[
        {
            "category":"Government",
            "subcategory":"Office",
            "type":"Public Place"
        }
    ],
    "sg:phone":"+1 321 956 5642",
    "sg:postcode":"32951",
    "sg:province":"FL",
    "sg:tags":[
        "educational",
        "program",
        "administrative"
    ],
    "wof:name":"Brevard County Library Systems",
    "wof:placetype":"venue"
},
  "geometry": {"coordinates":[-80.560228,28.068446],"type":"Point"}
}