{
  "type": "Feature",
  "properties": {
    "iso:country":"US",
    "sg:address":"6702 N 12th St",
    "sg:city":"Tampa",
    "sg:classifiers":[
        {
            "category":"Building & Trades",
            "subcategory":"Construction",
            "type":"Services"
        }
    ],
    "sg:phone":"+1 813 237 5128",
    "sg:postcode":"33604",
    "sg:province":"FL",
    "sg:tags":[
        "house"
    ],
    "wof:name":"Ko Framing & Construction Inc",
    "wof:placetype":"venue"
},
  "geometry": {"coordinates":[-82.447214,28.008619],"type":"Point"}
}