{
  "type": "Feature",
  "properties": {
    "iso:country":"US",
    "sg:address":"835 NW 37th Ave",
    "sg:city":"Miami",
    "sg:classifiers":[
        {
            "category":"Restaurant",
            "type":"Food & Drink"
        }
    ],
    "sg:phone":"+1 305 541 9100",
    "sg:postcode":"33125",
    "sg:province":"FL",
    "wof:name":"LA Tropical Cafeteria",
    "wof:placetype":"venue"
},
  "geometry": {"coordinates":[-80.255657,25.779541],"type":"Point"}
}