{
  "type": "Feature",
  "properties": {
    "iso:country":"US",
    "sg:address":"621 Robin Rd",
    "sg:city":"Lakeland",
    "sg:classifiers":[
        {
            "category":"Personal",
            "subcategory":"Beauty Salon",
            "type":"Services"
        }
    ],
    "sg:phone":"+1 863 647 5677",
    "sg:postcode":"33803",
    "sg:province":"FL",
    "sg:tags":[
        "hair",
        "shop",
        "stylist"
    ],
    "wof:name":"Classic Nails",
    "wof:placetype":"venue"
},
  "geometry": {"coordinates":[-81.94945199999999,28.00082],"type":"Point"}
}