{
  "type": "Feature",
  "properties": {
    "iso:country":"US",
    "sg:address":"6676 Hatteras Dr",
    "sg:city":"Lake Worth",
    "sg:classifiers":[
        {
            "category":"Professional",
            "subcategory":"Management & Consulting",
            "type":"Services"
        }
    ],
    "sg:phone":"+1 561 868 0297",
    "sg:postcode":"33467",
    "sg:province":"FL",
    "sg:tags":[
        "consultant",
        "business"
    ],
    "wof:name":"Occupancy Plus",
    "wof:placetype":"venue"
},
  "geometry": {"coordinates":[-80.150702,26.563699],"type":"Point"}
}