{
  "type": "Feature",
  "properties": {
    "iso:country":"US",
    "sg:address":"3829 Hollywood Blvd",
    "sg:city":"Hollywood",
    "sg:classifiers":[
        {
            "category":"Insurance",
            "subcategory":"Insurance Agent",
            "type":"Services"
        },
        {
            "category":"Insurance",
            "subcategory":"Hazard Insurance",
            "type":"Services"
        },
        {
            "category":"Insurance",
            "subcategory":"Title Insurance",
            "type":"Services"
        },
        {
            "category":"Insurance",
            "subcategory":"Life Insurance",
            "type":"Services"
        }
    ],
    "sg:phone":"+1 954 961 9300",
    "sg:postcode":"33021",
    "sg:province":"FL",
    "sg:tags":[
        "business",
        "auto",
        "commercial",
        "homeowner",
        "motorcycle",
        "renter"
    ],
    "wof:name":"Allstate Insurance Company - Ronald Barnes",
    "wof:placetype":"venue"
},
  "geometry": {"coordinates":[-80.182413,26.010944],"type":"Point"}
}