{
  "type": "Feature",
  "properties": {
    "addr:full":"13156 North Rd Loxahatchee FL 33470",
    "addr:housenumber":"13156",
    "addr:postcode":"33470",
    "addr:street":"North Rd",
    "iso:country":"US",
    "sg:address":"13156 North Rd",
    "sg:city":"Loxahatchee",
    "sg:classifiers":[
        {
            "category":"Building & Trades",
            "subcategory":"Construction",
            "type":"Services"
        }
    ],
    "sg:phone":"+1 561 784 4740",
    "sg:postcode":"33470",
    "sg:province":"FL",
    "sg:tags":[
        "ceiling"
    ],
    "wof:name":"Ceilpro",
    "wof:placetype":"venue"
},
  "geometry": {"coordinates":[-80.254791,26.720482],"type":"Point"}
}