{
  "type": "Feature",
  "properties": {
    "iso:country":"US",
    "sg:address":"9464 NW 13th St",
    "sg:city":"Miami",
    "sg:classifiers":[
        {
            "category":"Professional",
            "subcategory":"Business Services",
            "type":"Services"
        }
    ],
    "sg:phone":"+1 305 477 3466",
    "sg:postcode":"33172",
    "sg:province":"FL",
    "wof:name":"SDC Group Corp",
    "wof:placetype":"venue"
},
  "geometry": {"coordinates":[-80.34957300000001,25.784671],"type":"Point"}
}