{
  "type": "Feature",
  "properties": {
    "iso:country":"US",
    "sg:address":"2202 E 13th St",
    "sg:city":"Panama City",
    "sg:classifiers":[
        {
            "category":"Freight",
            "type":"Transportation"
        }
    ],
    "sg:phone":"+1 850 785 2070",
    "sg:postcode":"32401",
    "sg:province":"FL",
    "sg:tags":[
        "mover"
    ],
    "wof:name":"Office Movers Express",
    "wof:placetype":"venue"
},
  "geometry": {"coordinates":[-85.63126699999999,30.171212],"type":"Point"}
}