{
  "type": "Feature",
  "properties": {
    "addr:full":"7335 Lake Ellenor Dr Orlando FL 32809",
    "addr:housenumber":"7335",
    "addr:postcode":"32809",
    "addr:street":"Lake Ellenor Dr",
    "iso:country":"US",
    "sg:address":"7335 Lake Ellenor Dr",
    "sg:city":"Orlando",
    "sg:classifiers":[
        {
            "category":"Professional",
            "subcategory":"Management & Consulting",
            "type":"Services"
        }
    ],
    "sg:phone":"+1 407 854 0866",
    "sg:postcode":"32809",
    "sg:province":"FL",
    "sg:tags":[
        "fuel"
    ],
    "wof:name":"Contract Management Solutions",
    "wof:placetype":"venue"
},
  "geometry": {"coordinates":[-81.405084,28.461522],"type":"Point"}
}