{
  "type": "Feature",
  "properties": {
    "addr:full":"6404 21st Ave W Bradenton FL 34209",
    "addr:housenumber":"6404",
    "addr:postcode":"34209",
    "addr:street":"21St Ave W",
    "iso:country":"US",
    "sg:address":"6404 21st Ave W",
    "sg:city":"Bradenton",
    "sg:classifiers":[
        {
            "category":"Travel",
            "subcategory":"Hotels & Motels",
            "type":"Entertainment"
        }
    ],
    "sg:phone":"+1 941 798 8802",
    "sg:postcode":"34209",
    "sg:province":"FL",
    "wof:name":"Homewood William",
    "wof:placetype":"venue"
},
  "geometry": {"coordinates":[-82.624618,27.483238],"type":"Point"}
}