{
  "type": "Feature",
  "properties": {
    "iso:country":"US",
    "sg:address":"103 W Palmetto Park Rd",
    "sg:city":"Boca Raton",
    "sg:classifiers":[
        {
            "category":"Food & Beverages",
            "subcategory":"Groceries & Convenience Stores",
            "type":"Retail Goods"
        }
    ],
    "sg:phone":"+1 561 392 6858",
    "sg:postcode":"33486",
    "sg:province":"FL",
    "wof:name":"7-Eleven",
    "wof:placetype":"venue"
},
  "geometry": {"coordinates":[-80.089752,26.350544],"type":"Point"}
}