{
  "type": "Feature",
  "properties": {
    "iso:country":"US",
    "sg:address":"3191 Croton Ave",
    "sg:city":"Deltona",
    "sg:classifiers":[
        {
            "category":"Building & Trades",
            "subcategory":"Landscaping Services",
            "type":"Services"
        }
    ],
    "sg:phone":"+1 407 687 3399",
    "sg:postcode":"32738",
    "sg:province":"FL",
    "sg:tags":[
        "lawn",
        "maintenance",
        "grounds"
    ],
    "wof:name":"Justin's Lawn Care",
    "wof:placetype":"venue"
},
  "geometry": {"coordinates":[-81.182604,28.951589],"type":"Point"}
}