{
  "type": "Feature",
  "properties": {
    "addr:full":"4694 W Irlo Bronson Memorial Hwy Kissimmee FL 34746",
    "addr:housenumber":"4694",
    "addr:postcode":"34746",
    "addr:street":"W Irlo Bronson Memorial Hwy",
    "iso:country":"US",
    "sg:address":"4694 W Irlo Bronson Memorial Hwy",
    "sg:city":"Kissimmee",
    "sg:classifiers":[
        {
            "category":"Travel",
            "subcategory":"Hotels & Motels",
            "type":"Entertainment"
        }
    ],
    "sg:phone":"+1 407 396 1780",
    "sg:postcode":"34746",
    "sg:province":"FL",
    "sg:tags":[
        "lodging"
    ],
    "sg:website":"http://www.travelodge.com",
    "wof:name":"Travelodge",
    "wof:placetype":"venue"
},
  "geometry": {"coordinates":[-81.47023799999999,28.3186],"type":"Point"}
}