{
  "type": "Feature",
  "properties": {
    "iso:country":"US",
    "sg:address":"10440 SW Village Center Dr",
    "sg:city":"Port Saint Lucie",
    "sg:classifiers":[
        {
            "category":"Restaurant",
            "type":"Food & Drink"
        }
    ],
    "sg:menulink":"http://www.allmenus.com/fl/port-st-lucie/151432-hurricane-grill--wings/menu/",
    "sg:phone":"+1 772 345 9464",
    "sg:postcode":"34987",
    "sg:province":"FL",
    "sg:tags":[
        "american",
        "wing"
    ],
    "wof:name":"Hurricane Grill & Wings",
    "wof:placetype":"venue"
},
  "geometry": {"coordinates":[-80.431314,27.267934],"type":"Point"}
}