{
  "type": "Feature",
  "properties": {
    "addr:full":"502 E Sunrise Blvd Fort Lauderdale FL 33304",
    "addr:housenumber":"502",
    "addr:postcode":"33304",
    "addr:street":"E Sunrise Blvd",
    "iso:country":"US",
    "sg:address":"502 E Sunrise Blvd",
    "sg:city":"Fort Lauderdale",
    "sg:classifiers":[
        {
            "category":"Bars & Pubs",
            "type":"Food & Drink"
        }
    ],
    "sg:phone":"+1 954 525 6662",
    "sg:postcode":"33304",
    "sg:province":"FL",
    "sg:tags":[
        "club",
        "night"
    ],
    "wof:name":"Monas",
    "wof:placetype":"venue"
},
  "geometry": {"coordinates":[-80.13889899999999,26.136834],"type":"Point"}
}