{
  "type": "Feature",
  "properties": {
    "addr:full":"7657 London Ln Boca Raton FL 33433",
    "addr:housenumber":"7657",
    "addr:postcode":"33433",
    "addr:street":"London Ln",
    "iso:country":"US",
    "sg:address":"7657 London Ln",
    "sg:city":"Boca Raton",
    "sg:classifiers":[
        {
            "category":"Professional",
            "subcategory":"Management & Consulting",
            "type":"Services"
        }
    ],
    "sg:phone":"+1 561 750 1778",
    "sg:postcode":"33433",
    "sg:province":"FL",
    "wof:name":"Siedler Consulting",
    "wof:placetype":"venue"
},
  "geometry": {"coordinates":[-80.16498199999999,26.343527],"type":"Point"}
}