{
  "type": "Feature",
  "properties": {
    "iso:country":"US",
    "sg:address":"5999 Biscayne Blvd",
    "sg:city":"Miami",
    "sg:classifiers":[
        {
            "category":"Professional",
            "subcategory":"Lawyer & Legal Services",
            "type":"Services"
        }
    ],
    "sg:phone":"+1 305 758 7774",
    "sg:postcode":"33137",
    "sg:province":"FL",
    "wof:name":"Law Offices of Gonzalez & Associates",
    "wof:placetype":"venue"
},
  "geometry": {"coordinates":[-80.183881,25.831913],"type":"Point"}
}