{
  "type": "Feature",
  "properties": {
    "iso:country":"US",
    "sg:address":"24532 Deer Trace Dr",
    "sg:city":"Ponte Vedra Beach",
    "sg:classifiers":[
        {
            "category":"Professional",
            "subcategory":"Management & Consulting",
            "type":"Services"
        }
    ],
    "sg:phone":"+1 904 280 0896",
    "sg:postcode":"32082",
    "sg:province":"FL",
    "sg:tags":[
        "business"
    ],
    "wof:name":"Heron Lake Consultants Inc",
    "wof:placetype":"venue"
},
  "geometry": {"coordinates":[-81.400122,30.228141],"type":"Point"}
}