{
  "type": "Feature",
  "properties": {
    "addr:full":"532 Riverside Ave Jacksonville FL 32202",
    "addr:housenumber":"532",
    "addr:postcode":"32202",
    "addr:street":"Riverside Ave",
    "iso:country":"US",
    "sg:address":"532 Riverside Ave",
    "sg:city":"Jacksonville",
    "sg:classifiers":[
        {
            "category":"Professional",
            "type":"Services"
        }
    ],
    "sg:phone":"+1 904 791 8728",
    "sg:postcode":"32202",
    "sg:province":"FL",
    "sg:tags":[
        "establishment"
    ],
    "wof:name":"Tricenturion LLC Program",
    "wof:placetype":"venue"
},
  "geometry": {"coordinates":[-81.675224,30.319267],"type":"Point"}
}