{
  "type": "Feature",
  "properties": {
    "iso:country":"US",
    "sg:address":"341 N Maitland Ave",
    "sg:city":"Maitland",
    "sg:classifiers":[
        {
            "category":"Professional",
            "subcategory":"Lawyer & Legal Services",
            "type":"Services"
        }
    ],
    "sg:phone":"+1 407 539 1811",
    "sg:postcode":"32751",
    "sg:province":"FL",
    "wof:name":"Katz L H Atty Law PA",
    "wof:placetype":"venue"
},
  "geometry": {"coordinates":[-81.365683,28.630831],"type":"Point"}
}