{
  "type": "Feature",
  "properties": {
    "iso:country":"US",
    "sg:address":"9480 E Colonial Dr",
    "sg:city":"Orlando",
    "sg:classifiers":[
        {
            "category":"Manufacturing",
            "subcategory":"Aerospace",
            "type":"Manufacturing & Wholesale Goods"
        },
        {
            "category":"Wholesale",
            "subcategory":"Electrical",
            "type":"Manufacturing & Wholesale Goods"
        }
    ],
    "sg:phone":"+1 407 277 2131",
    "sg:postcode":"32817",
    "sg:province":"FL",
    "sg:tags":[
        "wire",
        "mfg",
        "devices",
        "missile",
        "aircraft",
        "harness",
        "including",
        "interconnection"
    ],
    "wof:name":"Tri Tech Electronics Inc",
    "wof:placetype":"venue"
},
  "geometry": {"coordinates":[-81.25341400000001,28.568313],"type":"Point"}
}