{
  "type": "Feature",
  "properties": {
    "iso:country":"US",
    "sg:address":"3850 Washington St",
    "sg:city":"Hollywood",
    "sg:classifiers":[
        {
            "category":"Home & Garden",
            "subcategory":"Carpets & Floor Coverings",
            "type":"Retail Goods"
        }
    ],
    "sg:phone":"+1 954 588 4414",
    "sg:postcode":"33021",
    "sg:province":"FL",
    "wof:name":"Florida Carpet Master",
    "wof:placetype":"venue"
},
  "geometry": {"coordinates":[-80.18282600000001,26.002914],"type":"Point"}
}