{
  "type": "Feature",
  "properties": {
    "addr:full":"3460 Fairlane Farms Rd Wellington FL 33414",
    "addr:housenumber":"3460",
    "addr:postcode":"33414",
    "addr:street":"Fairlane Farms Rd",
    "iso:country":"US",
    "sg:address":"3460 Fairlane Farms Rd",
    "sg:city":"Wellington",
    "sg:classifiers":[
        {
            "category":"Health Services",
            "subcategory":"Medical Lab",
            "type":"Services"
        },
        {
            "category":"Science Facility",
            "type":"Public Place"
        }
    ],
    "sg:phone":"+1 561 791 8787",
    "sg:postcode":"33414",
    "sg:province":"FL",
    "sg:tags":[
        "laboratories-pathological",
        "development",
        "laboratories-research",
        "laboratory"
    ],
    "wof:name":"Chempep Inc",
    "wof:placetype":"venue"
},
  "geometry": {"coordinates":[-80.223733,26.630197],"type":"Point"}
}