{
  "type": "Feature",
  "properties": {
    "iso:country":"US",
    "sg:address":"1000 NE 48th Avenue Rd",
    "sg:city":"Ocala",
    "sg:classifiers":[
        {
            "category":"Building & Trades",
            "subcategory":"Construction",
            "type":"Services"
        }
    ],
    "sg:phone":"+1 352 236 3306",
    "sg:postcode":"34470",
    "sg:province":"FL",
    "sg:tags":[
        "floor",
        "laying",
        "contractor"
    ],
    "wof:name":"Mike Boyles Flooring Installat",
    "wof:placetype":"venue"
},
  "geometry": {"coordinates":[-82.06757899999999,29.197904],"type":"Point"}
}