{
  "type": "Feature",
  "properties": {
    "addr:full":"7539 W Waters Ave Tampa FL 33615",
    "addr:housenumber":"7539",
    "addr:postcode":"33615",
    "addr:street":"W Waters Ave",
    "iso:country":"US",
    "sg:address":"7539 W Waters Ave",
    "sg:city":"Tampa",
    "sg:classifiers":[
        {
            "category":"Shopping",
            "subcategory":"Department Store",
            "type":"Retail Goods"
        }
    ],
    "sg:phone":"+1 813 886 8109",
    "sg:postcode":"33615",
    "sg:province":"FL",
    "sg:tags":[
        "shop"
    ],
    "wof:name":"Beall's Outlet",
    "wof:placetype":"venue"
},
  "geometry": {"coordinates":[-82.56430400000001,28.025962],"type":"Point"}
}