{
  "type": "Feature",
  "properties": {
    "iso:country":"US",
    "sg:address":"200 E 13th St",
    "sg:city":"West Palm Beach",
    "sg:classifiers":[
        {
            "category":"Restaurant",
            "type":"Food & Drink"
        }
    ],
    "sg:phone":"+1 561 845 5532",
    "sg:postcode":"33404",
    "sg:province":"FL",
    "sg:tags":[
        "eating"
    ],
    "wof:name":"Tiki Waterfront Sea Grill",
    "wof:placetype":"venue"
},
  "geometry": {"coordinates":[-80.05286,26.773488],"type":"Point"}
}