{
  "type": "Feature",
  "properties": {
    "iso:country":"US",
    "sg:address":"13727 SW 152nd St Ste 223",
    "sg:city":"Miami",
    "sg:classifiers":[
        {
            "category":"Health Services",
            "subcategory":"Clinic",
            "type":"Services"
        }
    ],
    "sg:phone":"+1 305 300 5407",
    "sg:postcode":"33177",
    "sg:province":"FL",
    "sg:tags":[
        "welfare"
    ],
    "wof:name":"South Miami Medical Billing, Inc.",
    "wof:placetype":"venue"
},
  "geometry": {"coordinates":[-80.415538,25.626312],"type":"Point"}
}