{
  "type": "Feature",
  "properties": {
    "iso:country":"US",
    "sg:address":"4327 W Bay To Bay Blvd",
    "sg:city":"Tampa",
    "sg:classifiers":[
        {
            "category":"Real Estate",
            "subcategory":"Real Estate Agent",
            "type":"Services"
        }
    ],
    "sg:phone":"+1 813 935 1951",
    "sg:postcode":"33629",
    "sg:province":"FL",
    "wof:name":"Mauro Serafino",
    "wof:placetype":"venue"
},
  "geometry": {"coordinates":[-82.51746300000001,27.919942],"type":"Point"}
}