{
  "type": "Feature",
  "properties": {
    "addr:full":"11911 US Hwy 1 Palm Beach Gdns FL 33408",
    "addr:housenumber":"11911",
    "addr:postcode":"33408",
    "addr:street":"Us Hwy 1 Palm Beach Gdns",
    "iso:country":"US",
    "sg:address":"11911 US Hwy 1",
    "sg:city":"Palm Beach Gdns",
    "sg:classifiers":[
        {
            "category":"Professional",
            "subcategory":"Computer Services",
            "type":"Services"
        }
    ],
    "sg:phone":"+1 561 622 5602",
    "sg:postcode":"33408",
    "sg:province":"FL",
    "wof:name":"New Dawn Computer Consultants",
    "wof:placetype":"venue"
},
  "geometry": {"coordinates":[-80.05933,26.850049],"type":"Point"}
}