{
  "type": "Feature",
  "properties": {
    "iso:country":"US",
    "sg:address":"45 Woodbourne Ln",
    "sg:city":"Ormond Beach",
    "sg:classifiers":[
        {
            "category":"Building & Trades",
            "subcategory":"Construction",
            "type":"Services"
        }
    ],
    "sg:phone":"+1 386 676 1567",
    "sg:postcode":"32174",
    "sg:province":"FL",
    "sg:tags":[
        "house"
    ],
    "wof:name":"Toms Repair & Maintenance",
    "wof:placetype":"venue"
},
  "geometry": {"coordinates":[-81.067789,29.306468],"type":"Point"}
}