{
  "type": "Feature",
  "properties": {
    "addr:full":"201 83rd St Miami Beach FL 33141",
    "addr:housenumber":"201",
    "addr:postcode":"33141",
    "addr:street":"83Rd St",
    "iso:country":"US",
    "sg:address":"201 83rd St",
    "sg:city":"Miami Beach",
    "sg:classifiers":[
        {
            "category":"Building & Trades",
            "subcategory":"Locksmith",
            "type":"Services"
        }
    ],
    "sg:phone":"+1 305 908 8679",
    "sg:postcode":"33141",
    "sg:province":"FL",
    "sg:tags":[
        "key"
    ],
    "wof:name":"0 0 24 Hour Locksmith",
    "wof:placetype":"venue"
},
  "geometry": {"coordinates":[-80.121195,25.868217],"type":"Point"}
}