{
  "type": "Feature",
  "properties": {
    "iso:country":"US",
    "sg:address":"171 Tequesta Dr",
    "sg:city":"Jupiter",
    "sg:classifiers":[
        {
            "category":"Banks & Credit Unions",
            "subcategory":"Bank",
            "type":"Services"
        }
    ],
    "sg:phone":"+1 561 747 5100",
    "sg:postcode":"33469",
    "sg:province":"FL",
    "sg:tags":[
        "federal",
        "savings",
        "institution"
    ],
    "wof:name":"Fidelity Federal Sav Bnk Fla",
    "wof:placetype":"venue"
},
  "geometry": {"coordinates":[-80.08743699999999,26.959084],"type":"Point"}
}