{
  "type": "Feature",
  "properties": {
    "addr:full":"4438 Bittern Ct Naples FL 34119",
    "addr:housenumber":"4438",
    "addr:postcode":"34119",
    "addr:street":"Bittern Ct",
    "iso:country":"US",
    "sg:address":"4438 Bittern Ct",
    "sg:city":"Naples",
    "sg:classifiers":[
        {
            "category":"Real Estate",
            "subcategory":"Real Estate Agent",
            "type":"Services"
        }
    ],
    "sg:phone":"+1 239 591 3337",
    "sg:postcode":"34119",
    "sg:province":"FL",
    "sg:tags":[
        "appraiser"
    ],
    "wof:name":"Southwest Fl Appraisal Svc",
    "wof:placetype":"venue"
},
  "geometry": {"coordinates":[-81.7239,26.277562],"type":"Point"}
}