{
  "type": "Feature",
  "properties": {
    "addr:full":"2931 Coral Way Coral Gables FL 33145",
    "addr:housenumber":"2931",
    "addr:postcode":"33145",
    "addr:street":"Coral Way",
    "iso:country":"US",
    "sg:address":"2931 Coral Way",
    "sg:city":"Coral Gables",
    "sg:classifiers":[
        {
            "category":"Health Services",
            "subcategory":"Doctor",
            "type":"Services"
        }
    ],
    "sg:phone":"+1 305 448 4431",
    "sg:postcode":"33145",
    "sg:province":"FL",
    "wof:name":"Padron Manuel MD",
    "wof:placetype":"venue"
},
  "geometry": {"coordinates":[-80.241501,25.7502],"type":"Point"}
}