{
  "type": "Feature",
  "properties": {
    "addr:full":"11100 Chumuckla Hwy Jay FL 32565",
    "addr:housenumber":"11100",
    "addr:postcode":"32565",
    "addr:street":"Chumuckla Hwy",
    "iso:country":"US",
    "sg:address":"11100 Chumuckla Hwy",
    "sg:city":"Jay",
    "sg:classifiers":[
        {
            "category":"Building & Trades",
            "subcategory":"Construction",
            "type":"Services"
        }
    ],
    "sg:phone":"+1 850 675 5744",
    "sg:postcode":"32565",
    "sg:province":"FL",
    "sg:tags":[
        "house"
    ],
    "wof:name":"Harrington Construction Co",
    "wof:placetype":"venue"
},
  "geometry": {"coordinates":[-87.20208599999999,30.842475],"type":"Point"}
}