{
  "type": "Feature",
  "properties": {
    "iso:country":"US",
    "sg:address":"10 Berry Dr",
    "sg:city":"Mascotte",
    "sg:classifiers":[
        {
            "category":"Personal",
            "type":"Services"
        }
    ],
    "sg:phone":"+1 352 429 9825",
    "sg:postcode":"34753",
    "sg:province":"FL",
    "sg:tags":[
        "consultant",
        "planning",
        "wedding"
    ],
    "wof:name":"Me Occasions",
    "wof:placetype":"venue"
},
  "geometry": {"coordinates":[-81.889572,28.58259],"type":"Point"}
}