{
  "type": "Feature",
  "properties": {
    "addr:full":"5937 SW 133rd Ct Miami FL 33183",
    "addr:housenumber":"5937",
    "addr:postcode":"33183",
    "addr:street":"Sw 133Rd Ct",
    "iso:country":"US",
    "sg:address":"5937 SW 133rd Ct",
    "sg:city":"Miami",
    "sg:classifiers":[
        {
            "category":"Health Services",
            "subcategory":"Medical Lab",
            "type":"Services"
        }
    ],
    "sg:phone":"+1 305 388 7597",
    "sg:postcode":"33183",
    "sg:province":"FL",
    "sg:tags":[
        "transcription"
    ],
    "wof:name":"Ccs Transcription",
    "wof:placetype":"venue"
},
  "geometry": {"coordinates":[-80.40929199999999,25.712793],"type":"Point"}
}