{
  "type": "Feature",
  "properties": {
    "addr:full":"7742 33rd Ln E Sarasota FL 34243",
    "addr:housenumber":"7742",
    "addr:postcode":"34243",
    "addr:street":"33Rd Ln E",
    "iso:country":"US",
    "sg:address":"7742 33rd Ln E",
    "sg:city":"Sarasota",
    "sg:classifiers":[
        {
            "category":"Organizations",
            "subcategory":"Community Association",
            "type":"Services"
        }
    ],
    "sg:phone":"+1 941 359 0597",
    "sg:postcode":"34243",
    "sg:province":"FL",
    "wof:name":"Maple Lakes Homeowners Assn",
    "wof:placetype":"venue"
},
  "geometry": {"coordinates":[-82.521193,27.402315],"type":"Point"}
}