{
  "type": "Feature",
  "properties": {
    "iso:country":"US",
    "sg:address":"1635 Washington Ave",
    "sg:city":"Miami Beach",
    "sg:classifiers":[
        {
            "category":"Shopping",
            "subcategory":"Discount & Variety Stores",
            "type":"Retail Goods"
        },
        {
            "category":"Food & Beverages",
            "subcategory":"Groceries & Convenience Stores",
            "type":"Retail Goods"
        }
    ],
    "sg:phone":"+1 305 674 3500",
    "sg:postcode":"33139",
    "sg:province":"FL",
    "sg:tags":[
        "grocer"
    ],
    "wof:name":"Marlins Market Inc",
    "wof:placetype":"venue"
},
  "geometry": {"coordinates":[-80.131897,25.7899],"type":"Point"}
}