{
  "type": "Feature",
  "properties": {
    "iso:country":"US",
    "sg:address":"23442 E Colonial Dr",
    "sg:city":"Christmas",
    "sg:classifiers":[
        {
            "category":"Organizations",
            "subcategory":"Religious Organization",
            "type":"Services"
        }
    ],
    "sg:phone":"+1 407 381 2999",
    "sg:postcode":"32709",
    "sg:province":"FL",
    "wof:name":"Christmas Ministries Inc",
    "wof:placetype":"venue"
},
  "geometry": {"coordinates":[-81.020505,28.536386],"type":"Point"}
}