{
  "type": "Feature",
  "properties": {
    "addr:full":"5501 W Sample Rd Coconut Creek FL 33073",
    "addr:housenumber":"5501",
    "addr:postcode":"33073",
    "addr:street":"W Sample Rd",
    "iso:country":"US",
    "sg:address":"5501 W Sample Rd",
    "sg:city":"Coconut Creek",
    "sg:classifiers":[
        {
            "category":"Retail",
            "subcategory":"Auto Rental",
            "type":"Services"
        }
    ],
    "sg:phone":"+1 954 861 6100",
    "sg:postcode":"33073",
    "sg:province":"FL",
    "sg:tags":[
        "automobile",
        "leasing"
    ],
    "wof:name":"Broward Infiniti Coconut Creek",
    "wof:placetype":"venue"
},
  "geometry": {"coordinates":[-80.19837,26.274285],"type":"Point"}
}