{
  "type": "Feature",
  "properties": {
    "addr:full":"134 Carswell Ave Daytona Beach FL 32117",
    "addr:housenumber":"134",
    "addr:postcode":"32117",
    "addr:street":"Carswell Ave",
    "iso:country":"US",
    "sg:address":"134 Carswell Ave",
    "sg:city":"Daytona Beach",
    "sg:classifiers":[
        {
            "category":"Building & Trades",
            "subcategory":"Construction",
            "type":"Services"
        }
    ],
    "sg:phone":"+1 386 248 0033",
    "sg:postcode":"32117",
    "sg:province":"FL",
    "sg:tags":[
        "general",
        "contractor"
    ],
    "wof:name":"Wise Builders",
    "wof:placetype":"venue"
},
  "geometry": {"coordinates":[-81.033477,29.226606],"type":"Point"}
}