{
  "type": "Feature",
  "properties": {
    "addr:full":"766 E Main St Bartow FL 33830",
    "addr:housenumber":"766",
    "addr:postcode":"33830",
    "addr:street":"E Main St",
    "iso:country":"US",
    "sg:address":"766 E Main St",
    "sg:city":"Bartow",
    "sg:classifiers":[
        {
            "category":"Professional",
            "subcategory":"Lawyer & Legal Services",
            "type":"Services"
        }
    ],
    "sg:phone":"+1 863 804 0999",
    "sg:postcode":"33830",
    "sg:province":"FL",
    "wof:name":"Buerger Law Firm Pa",
    "wof:placetype":"venue"
},
  "geometry": {"coordinates":[-81.83644099999999,27.896543],"type":"Point"}
}