{
  "type": "Feature",
  "properties": {
    "iso:country":"US",
    "sg:address":"912 Indiana Ave",
    "sg:city":"St Cloud",
    "sg:classifiers":[
        {
            "category":"Building & Trades",
            "subcategory":"Construction",
            "type":"Services"
        }
    ],
    "sg:phone":"+1 407 460 0672",
    "sg:postcode":"34769",
    "sg:province":"FL",
    "sg:tags":[
        "handyman"
    ],
    "wof:name":"John D Paul Handyman",
    "wof:placetype":"venue"
},
  "geometry": {"coordinates":[-81.27903000000001,28.249034],"type":"Point"}
}