{
  "type": "Feature",
  "properties": {
    "iso:country":"US",
    "sg:address":"9235 Telfer Run",
    "sg:city":"Orlando",
    "sg:classifiers":[
        {
            "category":"Education",
            "subcategory":"Special Training",
            "type":"Public Place"
        }
    ],
    "sg:phone":"+1 407 671 9299",
    "sg:postcode":"32817",
    "sg:province":"FL",
    "sg:tags":[
        "school",
        "language"
    ],
    "wof:name":"Italian Language Svc",
    "wof:placetype":"venue"
},
  "geometry": {"coordinates":[-81.25894,28.588038],"type":"Point"}
}