{
  "type": "Feature",
  "properties": {
    "addr:full":"1000 Lee St Wildwood FL 34785",
    "addr:housenumber":"1000",
    "addr:postcode":"34785",
    "addr:street":"Lee St",
    "iso:country":"US",
    "sg:address":"1000 Lee St",
    "sg:city":"Wildwood",
    "sg:classifiers":[
        {
            "category":"Real Estate",
            "subcategory":"Real Estate Operator",
            "type":"Services"
        }
    ],
    "sg:phone":"+1 352 748 0047",
    "sg:postcode":"34785",
    "sg:province":"FL",
    "sg:tags":[
        "apartment"
    ],
    "wof:name":"Wildwood Commons Apartments",
    "wof:placetype":"venue"
},
  "geometry": {"coordinates":[-82.03611600000001,28.87341],"type":"Point"}
}