{
  "type": "Feature",
  "properties": {
    "addr:full":"206 6th St W Carrabelle FL 32322",
    "addr:housenumber":"206",
    "addr:postcode":"32322",
    "addr:street":"6Th St W",
    "iso:country":"US",
    "sg:address":"206 6th St W",
    "sg:city":"Carrabelle",
    "sg:classifiers":[
        {
            "category":"Professional",
            "subcategory":"Lawyer & Legal Services",
            "type":"Services"
        }
    ],
    "sg:phone":"+1 850 697 5555",
    "sg:postcode":"32322",
    "sg:province":"FL",
    "sg:tags":[
        "attorney"
    ],
    "wof:name":"Daniel H Cox",
    "wof:placetype":"venue"
},
  "geometry": {"coordinates":[-84.67014500000001,29.853869],"type":"Point"}
}