{
  "type": "Feature",
  "properties": {
    "addr:full":"7031 Benjamin Rd Tampa FL 33634",
    "addr:housenumber":"7031",
    "addr:postcode":"33634",
    "addr:street":"Benjamin Rd",
    "iso:country":"US",
    "sg:address":"7031 Benjamin Rd",
    "sg:city":"Tampa",
    "sg:classifiers":[
        {
            "category":"Manufacturing",
            "subcategory":"Printing",
            "type":"Manufacturing & Wholesale Goods"
        }
    ],
    "sg:phone":"+1 813 886 3346",
    "sg:postcode":"33634",
    "sg:province":"FL",
    "sg:tags":[
        "commercial"
    ],
    "wof:name":"Printers Aid",
    "wof:placetype":"venue"
},
  "geometry": {"coordinates":[-82.54183399999999,28.014052],"type":"Point"}
}