{
  "type": "Feature",
  "properties": {
    "iso:country":"US",
    "sg:address":"313 S H St",
    "sg:city":"Lake Worth",
    "sg:classifiers":[
        {
            "category":"Shopping",
            "type":"Retail Goods"
        }
    ],
    "sg:phone":"+1 561 586 0464",
    "sg:postcode":"33460",
    "sg:province":"FL",
    "sg:tags":[
        "awning",
        "installation"
    ],
    "sg:website":"www.southernawning.com",
    "wof:name":"Southern Awning",
    "wof:placetype":"venue"
},
  "geometry": {"coordinates":[-80.058598,26.61122],"type":"Point"}
}