{
  "type": "Feature",
  "properties": {
    "addr:full":"931 N State Rd 434 Altamonte Springs FL 32714",
    "addr:housenumber":"931",
    "addr:postcode":"32714",
    "addr:street":"N State Rd 434",
    "iso:country":"US",
    "sg:address":"931 N State Rd 434",
    "sg:city":"Altamonte Springs",
    "sg:classifiers":[
        {
            "category":"Building & Trades",
            "subcategory":"Construction",
            "type":"Services"
        }
    ],
    "sg:phone":"+1 321 626 8272",
    "sg:postcode":"32714",
    "sg:province":"FL",
    "wof:name":"Woodtech Industries",
    "wof:placetype":"venue"
},
  "geometry": {"coordinates":[-81.418943,28.680896],"type":"Point"}
}