{
  "type": "Feature",
  "properties": {
    "addr:full":"404 W Cervantes St Pensacola FL 32501",
    "addr:housenumber":"404",
    "addr:postcode":"32501",
    "addr:street":"W Cervantes St",
    "iso:country":"US",
    "sg:address":"404 W Cervantes St",
    "sg:city":"Pensacola",
    "sg:classifiers":[
        {
            "category":"Professional",
            "subcategory":"Employment Agencies",
            "type":"Services"
        }
    ],
    "sg:phone":"+1 850 433 9955",
    "sg:postcode":"32501",
    "sg:province":"FL",
    "sg:tags":[
        "help",
        "supply"
    ],
    "wof:name":"Able Body Labor",
    "wof:placetype":"venue"
},
  "geometry": {"coordinates":[-87.222559,30.420514],"type":"Point"}
}