{
  "type": "Feature",
  "properties": {
    "iso:country":"US",
    "sg:address":"601 S Fremont Ave",
    "sg:city":"Tampa",
    "sg:classifiers":[
        {
            "category":"Professional",
            "subcategory":"Lawyer & Legal Services",
            "type":"Services"
        }
    ],
    "sg:phone":"+1 813 251 3380",
    "sg:postcode":"33606",
    "sg:province":"FL",
    "wof:name":"Douglas L Grose Pa",
    "wof:placetype":"venue"
},
  "geometry": {"coordinates":[-82.478898,27.93735],"type":"Point"}
}