{
  "type": "Feature",
  "properties": {
    "iso:country":"US",
    "sg:address":"2607 S Woodland Blvd",
    "sg:city":"Deland",
    "sg:classifiers":[
        {
            "category":"Building & Trades",
            "subcategory":"Plumbing",
            "type":"Services"
        }
    ],
    "sg:phone":"+1 386 574 1818",
    "sg:postcode":"32720",
    "sg:province":"FL",
    "sg:tags":[
        "septic"
    ],
    "wof:name":"Woody's Septic Tank Svc",
    "wof:placetype":"venue"
},
  "geometry": {"coordinates":[-81.299381,28.9808],"type":"Point"}
}