{
  "type": "Feature",
  "properties": {
    "iso:country":"US",
    "sg:address":"981 University Blvd N",
    "sg:city":"Jacksonville",
    "sg:classifiers":[
        {
            "category":"Organizations",
            "subcategory":"Non-profit Organization",
            "type":"Services"
        },
        {
            "category":"Organizations",
            "subcategory":"Labor Organization",
            "type":"Services"
        }
    ],
    "sg:phone":"+1 904 743 9940",
    "sg:postcode":"32211",
    "sg:province":"FL",
    "sg:tags":[
        "social"
    ],
    "wof:name":"Florida Police Benevolent Assn",
    "wof:placetype":"venue"
},
  "geometry": {"coordinates":[-81.603815,30.328792],"type":"Point"}
}