{
  "type": "Feature",
  "properties": {
    "iso:country":"US",
    "sg:address":"230 NE 51st St",
    "sg:city":"Miami",
    "sg:classifiers":[
        {
            "category":"Building & Trades",
            "subcategory":"Construction",
            "type":"Services"
        }
    ],
    "sg:phone":"+1 305 724 3834",
    "sg:postcode":"33137",
    "sg:province":"FL",
    "sg:tags":[
        "tile",
        "dealer"
    ],
    "wof:name":"Grirez Tiles & Marbles Inc",
    "wof:placetype":"venue"
},
  "geometry": {"coordinates":[-80.191057,25.822907],"type":"Point"}
}