{
  "type": "Feature",
  "properties": {
    "addr:full":"4224 NE Jacksonville Rd Ocala FL 34479",
    "addr:housenumber":"4224",
    "addr:postcode":"34479",
    "addr:street":"Ne Jacksonville Rd",
    "iso:country":"US",
    "sg:address":"4224 NE Jacksonville Rd",
    "sg:city":"Ocala",
    "sg:classifiers":[
        {
            "category":"Travel",
            "subcategory":"Hotels & Motels",
            "type":"Entertainment"
        }
    ],
    "sg:phone":"+1 352 629 5889",
    "sg:postcode":"34479",
    "sg:province":"FL",
    "wof:name":"Countryside Motel",
    "wof:placetype":"venue"
},
  "geometry": {"coordinates":[-82.12167599999999,29.231057],"type":"Point"}
}