{
  "type": "Feature",
  "properties": {
    "addr:full":"5615 Midnight Pass Rd Sarasota FL 34242",
    "addr:housenumber":"5615",
    "addr:postcode":"34242",
    "addr:street":"Midnight Pass Rd",
    "iso:country":"US",
    "sg:address":"5615 Midnight Pass Rd",
    "sg:city":"Sarasota",
    "sg:classifiers":[
        {
            "category":"Social Services",
            "subcategory":"Child Care",
            "type":"Services"
        },
        {
            "category":"Organizations",
            "subcategory":"Religious Organization",
            "type":"Services"
        }
    ],
    "sg:phone":"+1 941 346 0636",
    "sg:postcode":"34242",
    "sg:province":"FL",
    "sg:tags":[
        "day",
        "church"
    ],
    "wof:name":"St Boniface Pre School",
    "wof:placetype":"venue"
},
  "geometry": {"coordinates":[-82.54617500000001,27.269904],"type":"Point"}
}