{
  "type": "Feature",
  "properties": {
    "iso:country":"US",
    "sg:address":"9773 Lancaster Pl",
    "sg:city":"Boca Raton",
    "sg:classifiers":[
        {
            "category":"Government",
            "subcategory":"Office",
            "type":"Public Place"
        }
    ],
    "sg:phone":"+1 561 479 1571",
    "sg:postcode":"33434",
    "sg:province":"FL",
    "sg:tags":[
        "international",
        "affairs"
    ],
    "wof:name":"Bramson Intl",
    "wof:placetype":"venue"
},
  "geometry": {"coordinates":[-80.198302,26.388487],"type":"Point"}
}