{
  "type": "Feature",
  "properties": {
    "addr:full":"11805 Pines Blvd Hollywood FL 33026",
    "addr:housenumber":"11805",
    "addr:postcode":"33026",
    "addr:street":"Pines Blvd",
    "iso:country":"US",
    "sg:address":"11805 Pines Blvd",
    "sg:city":"Hollywood",
    "sg:classifiers":[
        {
            "category":"Shopping",
            "subcategory":"Music",
            "type":"Retail Goods"
        }
    ],
    "sg:phone":"+1 954 433 5658",
    "sg:postcode":"33026",
    "sg:province":"FL",
    "wof:name":"Camelot Music 338",
    "wof:placetype":"venue"
},
  "geometry": {"coordinates":[-80.306151,26.007907],"type":"Point"}
}