{
  "type": "Feature",
  "properties": {
    "iso:country":"US",
    "sg:address":"2201 SW 39th St",
    "sg:city":"Fort Lauderdale",
    "sg:classifiers":[
        {
            "category":"Parking",
            "type":"Transportation"
        }
    ],
    "sg:phone":"+1 954 583 8338",
    "sg:postcode":"33312",
    "sg:province":"FL",
    "sg:tags":[
        "attendant"
    ],
    "wof:name":"USA Parking",
    "wof:placetype":"venue"
},
  "geometry": {"coordinates":[-80.170744,26.073618],"type":"Point"}
}