{
  "type": "Feature",
  "properties": {
    "addr:full":"1601 Belvedere Rd West Palm Beach FL 33406",
    "addr:housenumber":"1601",
    "addr:postcode":"33406",
    "addr:street":"Belvedere Rd",
    "iso:country":"US",
    "sg:address":"1601 Belvedere Rd",
    "sg:city":"West Palm Beach",
    "sg:classifiers":[
        {
            "category":"Travel",
            "subcategory":"Hotels & Motels",
            "type":"Entertainment"
        }
    ],
    "sg:phone":"+1 561 689 6400",
    "sg:postcode":"33406",
    "sg:province":"FL",
    "wof:name":"Crowne Plaza West Palm Beach",
    "wof:placetype":"venue"
},
  "geometry": {"coordinates":[-80.076825,26.690932],"type":"Point"}
}