{
  "type": "Feature",
  "properties": {
    "addr:full":"5906 Sonora Dr W Jacksonville FL 32244",
    "addr:housenumber":"5906",
    "addr:postcode":"32244",
    "addr:street":"Sonora Dr W",
    "iso:country":"US",
    "sg:address":"5906 Sonora Dr W",
    "sg:city":"Jacksonville",
    "sg:classifiers":[
        {
            "category":"Personal",
            "subcategory":"Beauty Salon",
            "type":"Services"
        }
    ],
    "sg:phone":"+1 904 908 5040",
    "sg:postcode":"32244",
    "sg:province":"FL",
    "wof:name":"Inez Hair Salon",
    "wof:placetype":"venue"
},
  "geometry": {"coordinates":[-81.762002,30.241491],"type":"Point"}
}