{
  "type": "Feature",
  "properties": {
    "addr:full":"7925 Merrill Rd Jacksonville FL 32277",
    "addr:housenumber":"7925",
    "addr:postcode":"32277",
    "addr:street":"Merrill Rd",
    "iso:country":"US",
    "sg:address":"7925 Merrill Rd",
    "sg:city":"Jacksonville",
    "sg:classifiers":[
        {
            "category":"Real Estate",
            "subcategory":"Real Estate Operator",
            "type":"Services"
        }
    ],
    "sg:phone":"+1 904 745 0333",
    "sg:postcode":"32277",
    "sg:province":"FL",
    "sg:tags":[
        "apartment"
    ],
    "wof:name":"Paddock Club Apartments",
    "wof:placetype":"venue"
},
  "geometry": {"coordinates":[-81.56583999999999,30.35231],"type":"Point"}
}