{
  "type": "Feature",
  "properties": {
    "iso:country":"US",
    "sg:address":"537 Burlington St",
    "sg:city":"Opa Locka",
    "sg:classifiers":[
        {
            "category":"Health Services",
            "subcategory":"Clinic",
            "type":"Services"
        }
    ],
    "sg:phone":"+1 305 687 1367",
    "sg:postcode":"33054",
    "sg:province":"FL",
    "sg:tags":[
        "organization",
        "medical",
        "surgical"
    ],
    "wof:name":"Bouck Management Assoc Inc",
    "wof:placetype":"venue"
},
  "geometry": {"coordinates":[-80.255044,25.898316],"type":"Point"}
}