{
  "type": "Feature",
  "properties": {
    "iso:country":"US",
    "sg:address":"1906 Clint Moore Rd",
    "sg:city":"Boca Raton",
    "sg:classifiers":[
        {
            "category":"Personal",
            "subcategory":"Beauty Salon",
            "type":"Services"
        }
    ],
    "sg:phone":"+1 561 998 3101",
    "sg:postcode":"33496",
    "sg:province":"FL",
    "sg:tags":[
        "shop"
    ],
    "wof:name":"Izzy & Co Hairdressing Inc",
    "wof:placetype":"venue"
},
  "geometry": {"coordinates":[-80.125119,26.407648],"type":"Point"}
}