{
  "type": "Feature",
  "properties": {
    "iso:country":"US",
    "sg:address":"3664 Derbyshire Rd",
    "sg:city":"Casselberry",
    "sg:classifiers":[
        {
            "category":"Shopping",
            "subcategory":"Catalog Store",
            "type":"Retail Goods"
        }
    ],
    "sg:phone":"+1 407 260 6079",
    "sg:postcode":"32707",
    "sg:province":"FL",
    "sg:tags":[
        "mail",
        "order"
    ],
    "wof:name":"Southern Police Academy",
    "wof:placetype":"venue"
},
  "geometry": {"coordinates":[-81.32711,28.640337],"type":"Point"}
}