{
  "type": "Feature",
  "properties": {
    "iso:country":"US",
    "sg:address":"23442 SW 57th Ave",
    "sg:city":"Boca Raton",
    "sg:classifiers":[
        {
            "category":"Professional",
            "subcategory":"Management & Consulting",
            "type":"Services"
        }
    ],
    "sg:phone":"+1 561 477 6301",
    "sg:postcode":"33428",
    "sg:province":"FL",
    "sg:tags":[
        "party",
        "planning"
    ],
    "wof:name":"Celebration Cake Design",
    "wof:placetype":"venue"
},
  "geometry": {"coordinates":[-80.1871,26.330478],"type":"Point"}
}