{
  "type": "Feature",
  "properties": {
    "iso:country":"US",
    "sg:address":"1602 N 15th St",
    "sg:city":"Tampa",
    "sg:classifiers":[
        {
            "category":"Parking",
            "type":"Transportation"
        }
    ],
    "sg:phone":"+1 813 247 4198",
    "sg:postcode":"33605",
    "sg:province":"FL",
    "sg:tags":[
        "garage"
    ],
    "wof:name":"Parking Management",
    "wof:placetype":"venue"
},
  "geometry": {"coordinates":[-82.443049,27.959479],"type":"Point"}
}