{
  "type": "Feature",
  "properties": {
    "addr:full":"13828 Palm Beach Blvd Fort Myers FL 33905",
    "addr:housenumber":"13828",
    "addr:postcode":"33905",
    "addr:street":"Palm Beach Blvd",
    "iso:country":"US",
    "sg:address":"13828 Palm Beach Blvd",
    "sg:city":"Fort Myers",
    "sg:classifiers":[
        {
            "category":"Autos & Motor Vehicles",
            "subcategory":"Automobile Sales",
            "type":"Retail Goods"
        }
    ],
    "sg:phone":"+1 239 690 3333",
    "sg:postcode":"33905",
    "sg:province":"FL",
    "sg:tags":[
        "car",
        "dealer"
    ],
    "wof:name":"Car & Trucks For Less Inc",
    "wof:placetype":"venue"
},
  "geometry": {"coordinates":[-81.732005,26.70765],"type":"Point"}
}