{
  "type": "Feature",
  "properties": {
    "iso:country":"US",
    "sg:address":"5008 Pimlico Ct",
    "sg:city":"West Palm Beach",
    "sg:classifiers":[
        {
            "category":"Building & Trades",
            "subcategory":"Construction",
            "type":"Services"
        }
    ],
    "sg:phone":"+1 561 719 9894",
    "sg:postcode":"33415",
    "sg:province":"FL",
    "sg:tags":[
        "restoration",
        "cleaning",
        "patio",
        "deck"
    ],
    "wof:name":"Atlantic Coast Cleaning Syst",
    "wof:placetype":"venue"
},
  "geometry": {"coordinates":[-80.11949199999999,26.651442],"type":"Point"}
}