{
  "type": "Feature",
  "properties": {
    "iso:country":"US",
    "sg:address":"7990 93rd Ave",
    "sg:city":"Vero Beach",
    "sg:classifiers":[
        {
            "category":"Building & Trades",
            "subcategory":"Landscaping Services",
            "type":"Services"
        }
    ],
    "sg:phone":"+1 772 589 5546",
    "sg:postcode":"32967",
    "sg:province":"FL",
    "sg:tags":[
        "landscape"
    ],
    "wof:name":"Blairs Home Services",
    "wof:placetype":"venue"
},
  "geometry": {"coordinates":[-80.51743500000001,27.738947],"type":"Point"}
}