{
  "type": "Feature",
  "properties": {
    "addr:full":"2618 Success Dr Ste B Odessa FL 33556",
    "addr:housenumber":"2618",
    "addr:postcode":"33556",
    "addr:street":"Success Dr Ste B",
    "iso:country":"US",
    "sg:address":"2618 Success Dr Ste B",
    "sg:city":"Odessa",
    "sg:classifiers":[
        {
            "category":"Wholesale",
            "subcategory":"Groceries",
            "type":"Manufacturing & Wholesale Goods"
        }
    ],
    "sg:phone":"+1 727 232 8193",
    "sg:postcode":"33556",
    "sg:province":"FL",
    "sg:tags":[
        "food",
        "products-wholesale"
    ],
    "wof:name":"Island Way Sorbet, Inc.",
    "wof:placetype":"venue"
},
  "geometry": {"coordinates":[-82.62601100000001,28.196639],"type":"Point"}
}