{
  "type": "Feature",
  "properties": {
    "iso:country":"US",
    "sg:address":"1420 Columbus Ave",
    "sg:city":"Lehigh Acres",
    "sg:classifiers":[
        {
            "category":"Building & Trades",
            "subcategory":"Landscaping Services",
            "type":"Services"
        }
    ],
    "sg:phone":"+1 239 368 1618",
    "sg:postcode":"33972",
    "sg:province":"FL",
    "wof:name":"Lester Lewis Lawn Care",
    "wof:placetype":"venue"
},
  "geometry": {"coordinates":[-81.587631,26.654379],"type":"Point"}
}