{
  "type": "Feature",
  "properties": {
    "addr:full":"39 Patio de Leon Fort Myers FL 33901",
    "addr:housenumber":"39",
    "addr:postcode":"33901",
    "addr:street":"Patio De Leon",
    "iso:country":"US",
    "sg:address":"39 Patio de Leon",
    "sg:city":"Fort Myers",
    "sg:classifiers":[
        {
            "category":"Shopping",
            "subcategory":"Jewelry",
            "type":"Retail Goods"
        }
    ],
    "sg:phone":"+1 239 275 3999",
    "sg:postcode":"33901",
    "sg:province":"FL",
    "wof:name":"Silver & Stones",
    "wof:placetype":"venue"
},
  "geometry": {"coordinates":[-81.869801,26.643616],"type":"Point"}
}