{
  "type": "Feature",
  "properties": {
    "addr:full":"15408 Rosaire Ln Delray Beach FL 33484",
    "addr:housenumber":"15408",
    "addr:postcode":"33484",
    "addr:street":"Rosaire Ln",
    "iso:country":"US",
    "sg:address":"15408 Rosaire Ln",
    "sg:city":"Delray Beach",
    "sg:classifiers":[
        {
            "category":"Professional",
            "subcategory":"Secretarial Services",
            "type":"Services"
        }
    ],
    "sg:phone":"+1 954 722 2956",
    "sg:postcode":"33484",
    "sg:province":"FL",
    "sg:tags":[
        "convention",
        "court",
        "reporter"
    ],
    "wof:name":"AAMM Inc",
    "wof:placetype":"venue"
},
  "geometry": {"coordinates":[-80.139252,26.447962],"type":"Point"}
}