{
  "type": "Feature",
  "properties": {
    "addr:full":"201 Bunker Ranch Rd West Palm Beach FL 33405",
    "addr:housenumber":"201",
    "addr:postcode":"33405",
    "addr:street":"Bunker Ranch Rd",
    "iso:country":"US",
    "sg:address":"201 Bunker Ranch Rd",
    "sg:city":"West Palm Beach",
    "sg:classifiers":[
        {
            "category":"Professional",
            "type":"Services"
        }
    ],
    "sg:phone":"+1 561 547 3196",
    "sg:postcode":"33405",
    "sg:province":"FL",
    "sg:tags":[
        "establishment"
    ],
    "wof:name":"Notre Mot Inc",
    "wof:placetype":"venue"
},
  "geometry": {"coordinates":[-80.050484,26.664764],"type":"Point"}
}