{
  "type": "Feature",
  "properties": {
    "addr:full":"7139 Prestwick Ct Bradenton FL 34201",
    "addr:housenumber":"7139",
    "addr:postcode":"34201",
    "addr:street":"Prestwick Ct",
    "iso:country":"US",
    "sg:address":"7139 Prestwick Ct",
    "sg:city":"Bradenton",
    "sg:classifiers":[
        {
            "category":"Travel",
            "subcategory":"Hotels & Motels",
            "type":"Entertainment"
        }
    ],
    "sg:phone":"+1 941 359 9913",
    "sg:postcode":"34201",
    "sg:province":"FL",
    "sg:tags":[
        "membership",
        "lodging"
    ],
    "wof:name":"Saevn Inc",
    "wof:placetype":"venue"
},
  "geometry": {"coordinates":[-82.475813,27.412991],"type":"Point"}
}