{
  "type": "Feature",
  "properties": {
    "iso:country":"US",
    "sg:address":"3416 Balaton Ave",
    "sg:city":"Milton",
    "sg:classifiers":[
        {
            "category":"Building & Trades",
            "subcategory":"Pest Control",
            "type":"Services"
        }
    ],
    "sg:phone":"+1 850 994 6184",
    "sg:postcode":"32583",
    "sg:province":"FL",
    "wof:name":"A To Z Termite & Pest Svc",
    "wof:placetype":"venue"
},
  "geometry": {"coordinates":[-87.118527,30.559556],"type":"Point"}
}