{
  "type": "Feature",
  "properties": {
    "iso:country":"US",
    "sg:address":"7347 Spring Hill Dr",
    "sg:city":"Spring Hill",
    "sg:classifiers":[
        {
            "category":"Personal",
            "type":"Services"
        },
        {
            "category":"Health Services",
            "subcategory":"Clinic",
            "type":"Services"
        }
    ],
    "sg:phone":"+1 352 684 9907",
    "sg:postcode":"34606",
    "sg:province":"FL",
    "sg:tags":[
        "control",
        "specialty",
        "weight",
        "outpatient"
    ],
    "wof:name":"L A Weightloss",
    "wof:placetype":"venue"
},
  "geometry": {"coordinates":[-82.595631,28.451027],"type":"Point"}
}