{
  "type": "Feature",
  "properties": {
    "iso:country":"US",
    "sg:address":"102 W Crystal Lake St",
    "sg:city":"Orlando",
    "sg:classifiers":[
        {
            "category":"Building & Trades",
            "subcategory":"Construction",
            "type":"Services"
        }
    ],
    "sg:phone":"+1 407 425 0761",
    "sg:postcode":"32806",
    "sg:province":"FL",
    "sg:tags":[
        "planning",
        "remodeling",
        "kitchen"
    ],
    "wof:name":"Miller Custom Kitchen",
    "wof:placetype":"venue"
},
  "geometry": {"coordinates":[-81.379682,28.514711],"type":"Point"}
}