{
  "type": "Feature",
  "properties": {
    "addr:full":"1854 NE Jensen Beach Blvd Jensen Beach FL 34957",
    "addr:housenumber":"1854",
    "addr:postcode":"34957",
    "addr:street":"Ne Jensen Beach Blvd",
    "iso:country":"US",
    "sg:address":"1854 NE Jensen Beach Blvd",
    "sg:city":"Jensen Beach",
    "sg:classifiers":[
        {
            "category":"Retail",
            "subcategory":"Self-service Laundry",
            "type":"Services"
        }
    ],
    "sg:phone":"+1 772 334 8467",
    "sg:postcode":"34957",
    "sg:province":"FL",
    "sg:tags":[
        "coin"
    ],
    "wof:name":"Wash Club",
    "wof:placetype":"venue"
},
  "geometry": {"coordinates":[-80.22761800000001,27.24369],"type":"Point"}
}