{
  "type": "Feature",
  "properties": {
    "iso:country":"US",
    "sg:address":"14710 7th Ave E",
    "sg:city":"Bradenton",
    "sg:classifiers":[
        {
            "category":"Retail",
            "subcategory":"Repair Shop",
            "type":"Services"
        }
    ],
    "sg:phone":"+1 941 750 0767",
    "sg:postcode":"34212",
    "sg:province":"FL",
    "wof:name":"Cleaners of Fuel Tank",
    "wof:placetype":"venue"
},
  "geometry": {"coordinates":[-82.39141499999999,27.495678],"type":"Point"}
}