{
  "type": "Feature",
  "properties": {
    "addr:full":"409 Arietta Blvd Auburndale FL 33823",
    "addr:housenumber":"409",
    "addr:postcode":"33823",
    "addr:street":"Arietta Blvd",
    "iso:country":"US",
    "sg:address":"409 Arietta Blvd",
    "sg:city":"Auburndale",
    "sg:classifiers":[
        {
            "category":"Retail",
            "subcategory":"Animal Services",
            "type":"Services"
        }
    ],
    "sg:phone":"+1 863 968 0862",
    "sg:postcode":"33823",
    "sg:province":"FL",
    "wof:name":"Swamp Man Kennels",
    "wof:placetype":"venue"
},
  "geometry": {"coordinates":[-81.817503,28.108632],"type":"Point"}
}