{
  "type": "Feature",
  "properties": {
    "iso:country":"US",
    "sg:address":"118 NW Madison Cir N",
    "sg:city":"St Petersburg",
    "sg:classifiers":[
        {
            "category":"Building & Trades",
            "subcategory":"Landscaping Services",
            "type":"Services"
        }
    ],
    "sg:phone":"+1 727 521 9646",
    "sg:postcode":"33702",
    "sg:province":"FL",
    "sg:tags":[
        "lawn",
        "maintenance",
        "grounds"
    ],
    "wof:name":"Hayden Lawn Care",
    "wof:placetype":"venue"
},
  "geometry": {"coordinates":[-82.63898,27.830803],"type":"Point"}
}