{
  "type": "Feature",
  "properties": {
    "addr:full":"11245 4th St E Saint Petersburg FL 33706",
    "addr:housenumber":"11245",
    "addr:postcode":"33706",
    "addr:street":"4Th St E",
    "iso:country":"US",
    "sg:address":"11245 4th St E",
    "sg:city":"Saint Petersburg",
    "sg:classifiers":[
        {
            "category":"Building & Trades",
            "subcategory":"Construction",
            "type":"Services"
        }
    ],
    "sg:phone":"+1 727 363 4314",
    "sg:postcode":"33706",
    "sg:province":"FL",
    "sg:tags":[
        "general",
        "contractor"
    ],
    "wof:name":"Ed Seifried General Contractor",
    "wof:placetype":"venue"
},
  "geometry": {"coordinates":[-82.768111,27.775247],"type":"Point"}
}