{
  "type": "Feature",
  "properties": {
    "iso:country":"US",
    "sg:address":"5276 W State St",
    "sg:city":"Homosassa",
    "sg:classifiers":[
        {
            "category":"Shopping",
            "subcategory":"Hobbies, Toys, & Games",
            "type":"Retail Goods"
        }
    ],
    "sg:phone":"+1 352 628 2363",
    "sg:postcode":"34446",
    "sg:province":"FL",
    "sg:tags":[
        "craft"
    ],
    "wof:name":"Designs By Margaret Revels",
    "wof:placetype":"venue"
},
  "geometry": {"coordinates":[-82.528043,28.793831],"type":"Point"}
}