{
  "type": "Feature",
  "properties": {
    "addr:full":"534 Collins Dr Tallahassee FL 32303",
    "addr:housenumber":"534",
    "addr:postcode":"32303",
    "addr:street":"Collins Dr",
    "iso:country":"US",
    "sg:address":"534 Collins Dr",
    "sg:city":"Tallahassee",
    "sg:classifiers":[
        {
            "category":"Building & Trades",
            "subcategory":"Construction",
            "type":"Services"
        }
    ],
    "sg:phone":"+1 850 422 0082",
    "sg:postcode":"32303",
    "sg:province":"FL",
    "sg:tags":[
        "contractor"
    ],
    "wof:name":"Chops Acoustical",
    "wof:placetype":"venue"
},
  "geometry": {"coordinates":[-84.270937,30.466194],"type":"Point"}
}