{
  "type": "Feature",
  "properties": {
    "iso:country":"US",
    "sg:address":"8490 E Hwy 25",
    "sg:city":"Belleview",
    "sg:classifiers":[
        {
            "category":"Restaurant",
            "type":"Food & Drink"
        }
    ],
    "sg:phone":"+1 352 347 1961",
    "sg:postcode":"34420",
    "sg:province":"FL",
    "wof:name":"Stacy's Wings & Things",
    "wof:placetype":"venue"
},
  "geometry": {"coordinates":[-82.0123,29.054479],"type":"Point"}
}