{
  "type": "Feature",
  "properties": {
    "iso:country":"US",
    "sg:address":"16160 Forest Oaks Dr",
    "sg:city":"Fort Myers",
    "sg:classifiers":[
        {
            "category":"Manufacturing",
            "subcategory":"Building Materials",
            "type":"Manufacturing & Wholesale Goods"
        }
    ],
    "sg:phone":"+1 941 698 0011",
    "sg:postcode":"33908",
    "sg:province":"FL",
    "sg:tags":[
        "truss"
    ],
    "sg:website":"www.customtrusses.com",
    "wof:name":"Custom Made Home Components",
    "wof:placetype":"venue"
},
  "geometry": {"coordinates":[-81.87377600000001,26.507793],"type":"Point"}
}