{
  "type": "Feature",
  "properties": {
    "addr:full":"4585 WESTON RD WESTON FL 33331",
    "addr:housenumber":"4585",
    "addr:postcode":"33331",
    "addr:street":"Weston Rd",
    "iso:country":"US",
    "sg:address":"4585 WESTON RD",
    "sg:city":"WESTON",
    "sg:classifiers":[
        {
            "category":"Retail",
            "subcategory":"Veterinary Services",
            "type":"Services"
        }
    ],
    "sg:phone":"+1 954 389 5656",
    "sg:postcode":"33331",
    "sg:province":"FL",
    "sg:tags":[
        "hospital",
        "veterinarian",
        "clinic",
        "emergency"
    ],
    "sg:website":"http://www.westonroadanimalhospital.com",
    "wof:name":"Weston Road Animal Hospital",
    "wof:placetype":"venue"
},
  "geometry": {"coordinates":[-80.362362,26.063493],"type":"Point"}
}