{
  "type": "Feature",
  "properties": {
    "iso:country":"US",
    "sg:address":"9000 Fruitville Rd",
    "sg:city":"Sarasota",
    "sg:classifiers":[
        {
            "category":"Building & Trades",
            "subcategory":"Construction",
            "type":"Services"
        }
    ],
    "sg:phone":"+1 941 377 7003",
    "sg:postcode":"34240",
    "sg:province":"FL",
    "sg:tags":[
        "course",
        "golf"
    ],
    "wof:name":"Quality Grassing & Svc",
    "wof:placetype":"venue"
},
  "geometry": {"coordinates":[-82.40186,27.338379],"type":"Point"}
}