{
  "type": "Feature",
  "properties": {
    "iso:country":"US",
    "sg:address":"3948 S Peninsula Dr",
    "sg:city":"Daytona Beach",
    "sg:classifiers":[
        {
            "category":"Recreation",
            "subcategory":"Marina",
            "type":"Entertainment"
        }
    ],
    "sg:phone":"+1 386 756 2180",
    "sg:postcode":"32127",
    "sg:province":"FL",
    "wof:name":"Adventure Yacht Harbor Inc",
    "wof:placetype":"venue"
},
  "geometry": {"coordinates":[-80.96143499999999,29.133257],"type":"Point"}
}