{
  "type": "Feature",
  "properties": {
    "iso:country":"US",
    "sg:address":"5650 NW 36th St",
    "sg:city":"Miami",
    "sg:classifiers":[
        {
            "category":"Taxi",
            "type":"Transportation"
        }
    ],
    "sg:phone":"+1 305 639 6422",
    "sg:postcode":"33166",
    "sg:province":"FL",
    "sg:tags":[
        "delivery"
    ],
    "wof:name":"I BC Airways Inc",
    "wof:placetype":"venue"
},
  "geometry": {"coordinates":[-80.289086,25.807481],"type":"Point"}
}