{
  "type": "Feature",
  "properties": {
    "addr:full":"1590 Northwood Dr Saint Augustine FL 32084",
    "addr:housenumber":"1590",
    "addr:postcode":"32084",
    "addr:street":"Northwood Dr",
    "iso:country":"US",
    "sg:address":"1590 Northwood Dr",
    "sg:city":"Saint Augustine",
    "sg:classifiers":[
        {
            "category":"Home & Garden",
            "subcategory":"Building Materials",
            "type":"Retail Goods"
        }
    ],
    "sg:phone":"+1 904 827 1115",
    "sg:postcode":"32084",
    "sg:province":"FL",
    "wof:name":"F E C P Inc",
    "wof:placetype":"venue"
},
  "geometry": {"coordinates":[-81.359627,29.877468],"type":"Point"}
}