{
  "type": "Feature",
  "properties": {
    "addr:full":"497 E James Lee Blvd Crestview FL 32539",
    "addr:housenumber":"497",
    "addr:postcode":"32539",
    "addr:street":"E James Lee Blvd",
    "iso:country":"US",
    "sg:address":"497 E James Lee Blvd",
    "sg:city":"Crestview",
    "sg:classifiers":[
        {
            "category":"Autos & Motor Vehicles",
            "subcategory":"Auto Supplies",
            "type":"Retail Goods"
        }
    ],
    "sg:phone":"+1 850 682 3711",
    "sg:postcode":"32539",
    "sg:province":"FL",
    "sg:tags":[
        "transmission",
        "transmissions-other"
    ],
    "wof:name":"Perry's Transmission & Auto Repairs",
    "wof:placetype":"venue"
},
  "geometry": {"coordinates":[-86.566552,30.762821],"type":"Point"}
}