{
  "type": "Feature",
  "properties": {
    "iso:country":"US",
    "sg:address":"4 Whitt Pl",
    "sg:city":"Palm Coast",
    "sg:classifiers":[
        {
            "category":"Organizations",
            "subcategory":"Professional Association",
            "type":"Services"
        }
    ],
    "sg:phone":"+1 386 445 6934",
    "sg:postcode":"32164",
    "sg:province":"FL",
    "wof:name":"J Sportini Nicholas PA",
    "wof:placetype":"venue"
},
  "geometry": {"coordinates":[-81.230316,29.526023],"type":"Point"}
}