{
  "type": "Feature",
  "properties": {
    "addr:full":"38147 16th Ave Zephyrhills FL 33542",
    "addr:housenumber":"38147",
    "addr:postcode":"33542",
    "addr:street":"16Th Ave",
    "iso:country":"US",
    "sg:address":"38147 16th Ave",
    "sg:city":"Zephyrhills",
    "sg:classifiers":[
        {
            "category":"Personal",
            "subcategory":"Beauty Salon",
            "type":"Services"
        }
    ],
    "sg:phone":"+1 813 715 4504",
    "sg:postcode":"33542",
    "sg:province":"FL",
    "wof:name":"All About Faces Hair Salon",
    "wof:placetype":"venue"
},
  "geometry": {"coordinates":[-82.185576,28.244111],"type":"Point"}
}