{
  "type": "Feature",
  "properties": {
    "iso:country":"US",
    "sg:address":"10175 Dixie Hwy",
    "sg:city":"Miami",
    "sg:classifiers":[
        {
            "category":"Home & Garden",
            "subcategory":"Home Furnishings",
            "type":"Retail Goods"
        }
    ],
    "sg:phone":"+1 305 666 0177",
    "sg:postcode":"33156",
    "sg:province":"FL",
    "sg:tags":[
        "sewing"
    ],
    "wof:name":"Fabric Depot",
    "wof:placetype":"venue"
},
  "geometry": {"coordinates":[-80.31890300000001,25.676583],"type":"Point"}
}