{
  "type": "Feature",
  "properties": {
    "addr:full":"1407 83rd St NW Bradenton FL 34209",
    "addr:housenumber":"1407",
    "addr:postcode":"34209",
    "addr:street":"83Rd St Nw",
    "iso:country":"US",
    "sg:address":"1407 83rd St NW",
    "sg:city":"Bradenton",
    "sg:classifiers":[
        {
            "category":"Banks & Credit Unions",
            "subcategory":"Bank",
            "type":"Services"
        }
    ],
    "sg:phone":"+1 941 795 3915",
    "sg:postcode":"34209",
    "sg:province":"FL",
    "sg:tags":[
        "loan"
    ],
    "wof:name":"Landmark Lenders Inc",
    "wof:placetype":"venue"
},
  "geometry": {"coordinates":[-82.644583,27.513039],"type":"Point"}
}