{
  "type": "Feature",
  "properties": {
    "iso:country":"US",
    "sg:address":"9840 SW 131st St",
    "sg:city":"Miami",
    "sg:classifiers":[
        {
            "category":"Professional",
            "subcategory":"Business Services",
            "type":"Services"
        }
    ],
    "sg:phone":"+1 305 278 1575",
    "sg:postcode":"33176",
    "sg:province":"FL",
    "wof:name":"Records Management Options",
    "wof:placetype":"venue"
},
  "geometry": {"coordinates":[-80.35338,25.647812],"type":"Point"}
}