{
  "type": "Feature",
  "properties": {
    "iso:country":"US",
    "sg:address":"1055 SE 9th Ter",
    "sg:city":"Hialeah",
    "sg:classifiers":[
        {
            "category":"Building & Trades",
            "subcategory":"Landscaping Services",
            "type":"Services"
        },
        {
            "category":"Farming",
            "subcategory":"Nursery",
            "type":"Manufacturing & Wholesale Goods"
        }
    ],
    "sg:phone":"+1 305 247 6367",
    "sg:postcode":"33010",
    "sg:province":"FL",
    "sg:tags":[
        "contractor",
        "tree",
        "landscape",
        "nurseries-plants"
    ],
    "wof:name":"Exotics Design Center",
    "wof:placetype":"venue"
},
  "geometry": {"coordinates":[-80.26097799999999,25.813629],"type":"Point"}
}