{
  "type": "Feature",
  "properties": {
    "iso:country":"US",
    "sg:address":"30 W Belmont St",
    "sg:city":"Pensacola",
    "sg:classifiers":[
        {
            "category":"Professional",
            "subcategory":"Lawyer & Legal Services",
            "type":"Services"
        }
    ],
    "sg:phone":"+1 850 433 2210",
    "sg:postcode":"32501",
    "sg:province":"FL",
    "wof:name":"Morris Bart PLC",
    "wof:placetype":"venue"
},
  "geometry": {"coordinates":[-87.217572,30.417448],"type":"Point"}
}