{
  "type": "Feature",
  "properties": {
    "addr:full":"1920 Pinehurst Rd Dunedin FL 34698",
    "addr:housenumber":"1920",
    "addr:postcode":"34698",
    "addr:street":"Pinehurst Rd",
    "iso:country":"US",
    "sg:address":"1920 Pinehurst Rd",
    "sg:city":"Dunedin",
    "sg:classifiers":[
        {
            "category":"Personal",
            "type":"Services"
        },
        {
            "category":"Sports & Exercise",
            "subcategory":"Gym",
            "type":"Entertainment"
        }
    ],
    "sg:phone":"+1 727 470 6478",
    "sg:postcode":"34698",
    "sg:province":"FL",
    "sg:tags":[
        "trainer",
        "consultant",
        "program",
        "physical",
        "fitness"
    ],
    "sg:website":"http://tampabay.citysearch.com/profile/external/2842876/dunedin_fl/jazzercise_dunedin_community_center.html?publisher=yellowpages&reference_id=1&placement=ypwebsitemip",
    "wof:name":"Jazzercise Dunedin Community Center",
    "wof:placetype":"venue"
},
  "geometry": {"coordinates":[-82.77175200000001,28.036124],"type":"Point"}
}