{
  "type": "Feature",
  "properties": {
    "iso:country":"US",
    "sg:address":"18221 Palm Creek Dr",
    "sg:city":"Fort Myers",
    "sg:classifiers":[
        {
            "category":"Retail",
            "subcategory":"Animal Services",
            "type":"Services"
        }
    ],
    "sg:phone":"+1 239 543 6378",
    "sg:postcode":"33917",
    "sg:province":"FL",
    "sg:tags":[
        "breeder",
        "german",
        "shepherd"
    ],
    "wof:name":"Vom Katzenblut Shepherds",
    "wof:placetype":"venue"
},
  "geometry": {"coordinates":[-81.777393,26.728447],"type":"Point"}
}