{
  "type": "Feature",
  "properties": {
    "addr:full":"5911 Breckenridge Pkwy Tampa FL 33610",
    "addr:housenumber":"5911",
    "addr:postcode":"33610",
    "addr:street":"Breckenridge Pkwy",
    "iso:country":"US",
    "sg:address":"5911 Breckenridge Pkwy",
    "sg:city":"Tampa",
    "sg:classifiers":[
        {
            "category":"Government",
            "subcategory":"Office",
            "type":"Public Place"
        }
    ],
    "sg:phone":"+1 813 272 2260",
    "sg:postcode":"33610",
    "sg:province":"FL",
    "wof:name":"Tampa Petroleum Testing Lab",
    "wof:placetype":"venue"
},
  "geometry": {"coordinates":[-82.357876,28.007422],"type":"Point"}
}