{
  "type": "Feature",
  "properties": {
    "iso:country":"US",
    "sg:address":"9070 Cove Ave",
    "sg:city":"Pensacola",
    "sg:classifiers":[
        {
            "category":"Personal",
            "type":"Services"
        }
    ],
    "sg:phone":"+1 850 476 8494",
    "sg:postcode":"32534",
    "sg:province":"FL",
    "sg:tags":[
        "towing"
    ],
    "wof:name":"Interstate Road Service",
    "wof:placetype":"venue"
},
  "geometry": {"coordinates":[-87.28815,30.52606],"type":"Point"}
}