{
  "type": "Feature",
  "properties": {
    "iso:country":"US",
    "sg:address":"21 King St",
    "sg:city":"St Augustine",
    "sg:classifiers":[
        {
            "category":"Shopping",
            "subcategory":"Gifts & Souvenirs",
            "type":"Retail Goods"
        }
    ],
    "sg:phone":"+1 904 829 1694",
    "sg:postcode":"32084",
    "sg:province":"FL",
    "sg:tags":[
        "shop"
    ],
    "sg:website":"www.potterswax.com",
    "wof:name":"Potter's Museum Store",
    "wof:placetype":"venue"
},
  "geometry": {"coordinates":[-81.312623,29.892145],"type":"Point"}
}