{
  "type": "Feature",
  "properties": {
    "addr:full":"7045 Garside Dr Zephyrhills FL 33540",
    "addr:housenumber":"7045",
    "addr:postcode":"33540",
    "addr:street":"Garside Dr",
    "iso:country":"US",
    "sg:address":"7045 Garside Dr",
    "sg:city":"Zephyrhills",
    "sg:classifiers":[
        {
            "category":"Freight",
            "type":"Transportation"
        }
    ],
    "sg:phone":"+1 813 783 7181",
    "sg:postcode":"33540",
    "sg:province":"FL",
    "wof:name":"Kaeberlein Transport",
    "wof:placetype":"venue"
},
  "geometry": {"coordinates":[-82.178653,28.259923],"type":"Point"}
}