{
  "type": "Feature",
  "properties": {
    "iso:country":"US",
    "sg:address":"511 Lucky World Dr",
    "sg:city":"Davenport",
    "sg:classifiers":[
        {
            "category":"Real Estate",
            "subcategory":"Real Estate Operator",
            "type":"Services"
        }
    ],
    "sg:phone":"+1 863 420 3999",
    "sg:postcode":"33897",
    "sg:province":"FL",
    "sg:tags":[
        "apartment"
    ],
    "wof:name":"Kingdom States Villas",
    "wof:placetype":"venue"
},
  "geometry": {"coordinates":[-81.681898,28.261103],"type":"Point"}
}