{
  "type": "Feature",
  "properties": {
    "addr:full":"36 W Oak Ave Panama City FL 32401",
    "addr:housenumber":"36",
    "addr:postcode":"32401",
    "addr:street":"W Oak Ave",
    "iso:country":"US",
    "sg:address":"36 W Oak Ave",
    "sg:city":"Panama City",
    "sg:classifiers":[
        {
            "category":"Professional",
            "subcategory":"Lawyer & Legal Services",
            "type":"Services"
        }
    ],
    "sg:phone":"+1 850 769 5235",
    "sg:postcode":"32401",
    "sg:province":"FL",
    "sg:tags":[
        "attorney"
    ],
    "wof:name":"M & P",
    "wof:placetype":"venue"
},
  "geometry": {"coordinates":[-85.662032,30.154954],"type":"Point"}
}