{
  "type": "Feature",
  "properties": {
    "iso:country":"US",
    "sg:address":"2516 Jmt Industrial Dr",
    "sg:city":"Apopka",
    "sg:classifiers":[
        {
            "category":"Retail",
            "subcategory":"Auto Repair",
            "type":"Services"
        }
    ],
    "sg:phone":"+1 407 295 2480",
    "sg:postcode":"32703",
    "sg:province":"FL",
    "sg:tags":[
        "repairing",
        "automobile"
    ],
    "wof:name":"TLM Motorsports",
    "wof:placetype":"venue"
},
  "geometry": {"coordinates":[-81.460086,28.630669],"type":"Point"}
}