{
  "type": "Feature",
  "properties": {
    "iso:country":"US",
    "sg:address":"110 Heritage Cir",
    "sg:city":"Panama City Bch",
    "sg:classifiers":[
        {
            "category":"Professional",
            "subcategory":"Accounting & Tax Preparation",
            "type":"Services"
        }
    ],
    "sg:phone":"+1 850 230 0136",
    "sg:postcode":"32407",
    "sg:province":"FL",
    "sg:tags":[
        "billing"
    ],
    "wof:name":"Medical Insurance Admnstrtrs",
    "wof:placetype":"venue"
},
  "geometry": {"coordinates":[-85.771013,30.189727],"type":"Point"}
}