{
  "type": "Feature",
  "properties": {
    "addr:full":"15750 SW 72nd St Miami FL 33193",
    "addr:housenumber":"15750",
    "addr:postcode":"33193",
    "addr:street":"Sw 72Nd St",
    "iso:country":"US",
    "sg:address":"15750 SW 72nd St",
    "sg:city":"Miami",
    "sg:classifiers":[
        {
            "category":"Food & Beverages",
            "subcategory":"Groceries & Convenience Stores",
            "type":"Retail Goods"
        }
    ],
    "sg:phone":"+1 305 383 6990",
    "sg:postcode":"33193",
    "sg:province":"FL",
    "sg:tags":[
        "product",
        "grocer",
        "mfg"
    ],
    "wof:name":"Publix Super Market 529",
    "wof:placetype":"venue"
},
  "geometry": {"coordinates":[-80.447085,25.698779],"type":"Point"}
}