{
  "type": "Feature",
  "properties": {
    "addr:full":"4630 McIntosh Rd Dover FL 33527",
    "addr:housenumber":"4630",
    "addr:postcode":"33527",
    "addr:street":"Mcintosh Rd",
    "iso:country":"US",
    "sg:address":"4630 McIntosh Rd",
    "sg:city":"Dover",
    "sg:classifiers":[
        {
            "category":"Travel",
            "subcategory":"Campground",
            "type":"Entertainment"
        }
    ],
    "sg:phone":"+1 813 659 0002",
    "sg:postcode":"33527",
    "sg:province":"FL",
    "wof:name":"Sunburst-Encore Tampa East",
    "wof:placetype":"venue"
},
  "geometry": {"coordinates":[-82.24460000000001,28.003619],"type":"Point"}
}