{
  "type": "Feature",
  "properties": {
    "iso:country":"US",
    "sg:address":"210 Brightview Dr",
    "sg:city":"Lake Mary",
    "sg:classifiers":[
        {
            "category":"Building & Trades",
            "subcategory":"Construction",
            "type":"Services"
        }
    ],
    "sg:phone":"+1 407 463 3294",
    "sg:postcode":"32746",
    "sg:province":"FL",
    "sg:tags":[
        "handyman"
    ],
    "wof:name":"Henry Archibold Handyman",
    "wof:placetype":"venue"
},
  "geometry": {"coordinates":[-81.30667,28.780125],"type":"Point"}
}