{
  "type": "Feature",
  "properties": {
    "iso:country":"US",
    "sg:address":"1327 21st St",
    "sg:city":"Vero Beach",
    "sg:classifiers":[
        {
            "category":"Restaurant",
            "type":"Food & Drink"
        }
    ],
    "sg:phone":"+1 772 770 4771",
    "sg:postcode":"32960",
    "sg:province":"FL",
    "sg:tags":[
        "eating"
    ],
    "wof:name":"Citrus Blossom Cafe",
    "wof:placetype":"venue"
},
  "geometry": {"coordinates":[-80.399174,27.639671],"type":"Point"}
}