{
  "type": "Feature",
  "properties": {
    "iso:country":"US",
    "sg:address":"1849 S Ocean Dr",
    "sg:city":"Hallandale",
    "sg:classifiers":[
        {
            "category":"Professional",
            "subcategory":"Computer Services",
            "type":"Services"
        }
    ],
    "sg:phone":"+1 954 458 9439",
    "sg:postcode":"33009",
    "sg:province":"FL",
    "sg:tags":[
        "consulting",
        "software"
    ],
    "wof:name":"Computing For Industries Inc",
    "wof:placetype":"venue"
},
  "geometry": {"coordinates":[-80.11957200000001,25.975517],"type":"Point"}
}