{
  "type": "Feature",
  "properties": {
    "addr:full":"5405 Jet View Cir Tampa FL 33634",
    "addr:housenumber":"5405",
    "addr:postcode":"33634",
    "addr:street":"Jet View Cir",
    "iso:country":"US",
    "sg:address":"5405 Jet View Cir",
    "sg:city":"Tampa",
    "sg:classifiers":[
        {
            "category":"Professional",
            "subcategory":"Business Services",
            "type":"Services"
        },
        {
            "category":"Wholesale",
            "subcategory":"Chemicals & Plastics",
            "type":"Manufacturing & Wholesale Goods"
        }
    ],
    "sg:phone":"+1 813 882 4636",
    "sg:postcode":"33634",
    "sg:province":"FL",
    "sg:tags":[
        "packaging",
        "shape",
        "based"
    ],
    "wof:name":"Technical Packaging A P I",
    "wof:placetype":"venue"
},
  "geometry": {"coordinates":[-82.543294,27.997213],"type":"Point"}
}