{
  "type": "Feature",
  "properties": {
    "addr:full":"3317 Bartlett Blvd Orlando FL 32811",
    "addr:housenumber":"3317",
    "addr:postcode":"32811",
    "addr:street":"Bartlett Blvd",
    "iso:country":"US",
    "sg:address":"3317 Bartlett Blvd",
    "sg:city":"Orlando",
    "sg:classifiers":[
        {
            "category":"Freight",
            "type":"Transportation"
        }
    ],
    "sg:phone":"+1 407 540 1022",
    "sg:postcode":"32811",
    "sg:province":"FL",
    "sg:tags":[
        "warehouse",
        "self",
        "storage"
    ],
    "wof:name":"Endangered Species Store Whse",
    "wof:placetype":"venue"
},
  "geometry": {"coordinates":[-81.43410799999999,28.506129],"type":"Point"}
}