{
  "type": "Feature",
  "properties": {
    "addr:full":"705 Grove Park Blvd Jacksonville FL 32216",
    "addr:housenumber":"705",
    "addr:postcode":"32216",
    "addr:street":"Grove Park Blvd",
    "iso:country":"US",
    "sg:address":"705 Grove Park Blvd",
    "sg:city":"Jacksonville",
    "sg:classifiers":[
        {
            "category":"Home & Garden",
            "subcategory":"Furniture",
            "type":"Retail Goods"
        }
    ],
    "sg:phone":"+1 904 724 2800",
    "sg:postcode":"32216",
    "sg:province":"FL",
    "wof:name":"Freddies Furniture Moving Ser",
    "wof:placetype":"venue"
},
  "geometry": {"coordinates":[-81.572807,30.304766],"type":"Point"}
}