{
  "type": "Feature",
  "properties": {
    "addr:full":"1688 Meridian Ave Miami Beach FL 33139",
    "addr:housenumber":"1688",
    "addr:postcode":"33139",
    "addr:street":"Meridian Ave",
    "iso:country":"US",
    "sg:address":"1688 Meridian Ave",
    "sg:city":"Miami Beach",
    "sg:classifiers":[
        {
            "category":"Professional",
            "subcategory":"Accounting & Tax Preparation",
            "type":"Services"
        }
    ],
    "sg:phone":"+1 305 534 7973",
    "sg:postcode":"33139",
    "sg:province":"FL",
    "sg:tags":[
        "payroll"
    ],
    "wof:name":"Cast & Crew Payroll Inc",
    "wof:placetype":"venue"
},
  "geometry": {"coordinates":[-80.136668,25.79158],"type":"Point"}
}