{
  "type": "Feature",
  "properties": {
    "addr:full":"4150 Hollis Dr Marianna FL 32448",
    "addr:housenumber":"4150",
    "addr:postcode":"32448",
    "addr:street":"Hollis Dr",
    "iso:country":"US",
    "sg:address":"4150 Hollis Dr",
    "sg:city":"Marianna",
    "sg:classifiers":[
        {
            "category":"Health Services",
            "subcategory":"Clinic",
            "type":"Services"
        }
    ],
    "sg:phone":"+1 850 526 3133",
    "sg:postcode":"32448",
    "sg:province":"FL",
    "sg:tags":[
        "outpatient",
        "alcohol"
    ],
    "wof:name":"Chemical Addctns Recvry",
    "wof:placetype":"venue"
},
  "geometry": {"coordinates":[-85.250516,30.780587],"type":"Point"}
}