{
  "type": "Feature",
  "properties": {
    "iso:country":"US",
    "sg:address":"9600 NW 77th Ave",
    "sg:city":"Hialeah",
    "sg:classifiers":[
        {
            "category":"Freight",
            "type":"Transportation"
        }
    ],
    "sg:phone":"+1 305 231 0203",
    "sg:postcode":"33016",
    "sg:province":"FL",
    "sg:tags":[
        "commercial",
        "storage"
    ],
    "wof:name":"Ted's Shed",
    "wof:placetype":"venue"
},
  "geometry": {"coordinates":[-80.32323700000001,25.862465],"type":"Point"}
}