{
  "type": "Feature",
  "properties": {
    "addr:full":"14100 Palmetto Frontage Rd Hialeah FL 33016",
    "addr:housenumber":"14100",
    "addr:postcode":"33016",
    "addr:street":"Palmetto Frontage Rd",
    "iso:country":"US",
    "sg:address":"14100 Palmetto Frontage Rd",
    "sg:city":"Hialeah",
    "sg:classifiers":[
        {
            "category":"Banks & Credit Unions",
            "subcategory":"Bank",
            "type":"Services"
        }
    ],
    "sg:phone":"+1 305 819 2700",
    "sg:postcode":"33016",
    "sg:province":"FL",
    "sg:tags":[
        "loan",
        "real estate"
    ],
    "wof:name":"Nobis Mortgage Group",
    "wof:placetype":"venue"
},
  "geometry": {"coordinates":[-80.325284,25.905017],"type":"Point"}
}