{
  "type": "Feature",
  "properties": {
    "iso:country":"US",
    "sg:address":"4404 US Hwy 1",
    "sg:city":"Vero Beach",
    "sg:classifiers":[
        {
            "category":"Building & Trades",
            "subcategory":"Electrical",
            "type":"Services"
        }
    ],
    "sg:phone":"+1 772 564 0065",
    "sg:postcode":"32967",
    "sg:province":"FL",
    "sg:tags":[
        "communication",
        "installation"
    ],
    "wof:name":"Telcom Services LLC",
    "wof:placetype":"venue"
},
  "geometry": {"coordinates":[-80.406781,27.671945],"type":"Point"}
}