{
  "type": "Feature",
  "properties": {
    "addr:full":"5574 Kimmons Rd Milton FL 32583",
    "addr:housenumber":"5574",
    "addr:postcode":"32583",
    "addr:street":"Kimmons Rd",
    "iso:country":"US",
    "sg:address":"5574 Kimmons Rd",
    "sg:city":"Milton",
    "sg:classifiers":[
        {
            "category":"Building & Trades",
            "subcategory":"Construction",
            "type":"Services"
        }
    ],
    "sg:phone":"+1 850 626 1678",
    "sg:postcode":"32583",
    "sg:province":"FL",
    "sg:tags":[
        "contractor"
    ],
    "wof:name":"Kimmons Drywall",
    "wof:placetype":"venue"
},
  "geometry": {"coordinates":[-86.99998100000001,30.634753],"type":"Point"}
}