{
  "type": "Feature",
  "properties": {
    "iso:country":"US",
    "sg:address":"109 SE 3rd Ct",
    "sg:city":"Deerfield Beach",
    "sg:classifiers":[
        {
            "category":"Home & Garden",
            "subcategory":"Furniture",
            "type":"Retail Goods"
        }
    ],
    "sg:phone":"+1 954 421 9553",
    "sg:postcode":"33441",
    "sg:province":"FL",
    "sg:tags":[
        "cabinet"
    ],
    "wof:name":"Eagle Design Furniture",
    "wof:placetype":"venue"
},
  "geometry": {"coordinates":[-80.10203300000001,26.313421],"type":"Point"}
}