{
  "type": "Feature",
  "properties": {
    "iso:country":"US",
    "sg:address":"4655 NW 36th Ave",
    "sg:city":"Miami",
    "sg:classifiers":[
        {
            "category":"Wholesale",
            "subcategory":"Auto Parts",
            "type":"Manufacturing & Wholesale Goods"
        }
    ],
    "sg:phone":"+1 305 633 2278",
    "sg:postcode":"33142",
    "sg:province":"FL",
    "sg:tags":[
        "automobile",
        "rebuilt",
        "supply"
    ],
    "wof:name":"F & J Used Auto Parts",
    "wof:placetype":"venue"
},
  "geometry": {"coordinates":[-80.254739,25.816489],"type":"Point"}
}