{
  "type": "Feature",
  "properties": {
    "iso:country":"US",
    "sg:address":"300 Cedar Ln",
    "sg:city":"Largo",
    "sg:classifiers":[
        {
            "category":"Building & Trades",
            "subcategory":"Construction",
            "type":"Services"
        }
    ],
    "sg:phone":"+1 727 585 2856",
    "sg:postcode":"33770",
    "sg:province":"FL",
    "sg:tags":[
        "concrete",
        "contractor"
    ],
    "wof:name":"Bl Concrete Inc",
    "wof:placetype":"venue"
},
  "geometry": {"coordinates":[-82.82701900000001,27.906378],"type":"Point"}
}