{
  "type": "Feature",
  "properties": {
    "addr:full":"4944 W Irlo Bronson Memorial Hwy Kissimmee FL 34746",
    "addr:housenumber":"4944",
    "addr:postcode":"34746",
    "addr:street":"W Irlo Bronson Memorial Hwy",
    "iso:country":"US",
    "sg:address":"4944 W Irlo Bronson Memorial Hwy",
    "sg:city":"Kissimmee",
    "sg:classifiers":[
        {
            "category":"Bars & Pubs",
            "type":"Food & Drink"
        }
    ],
    "sg:menulink":"http://www.allmenus.com/fl/kissimmee/45989-coconut-willys-british-pub/menu/",
    "sg:phone":"+1 407 397 7455",
    "sg:postcode":"34746",
    "sg:province":"FL",
    "sg:tags":[
        "british"
    ],
    "wof:name":"Coconut Willy's British Pub",
    "wof:placetype":"venue"
},
  "geometry": {"coordinates":[-81.48110200000001,28.332828],"type":"Point"}
}