{
  "type": "Feature",
  "properties": {
    "addr:full":"3501 Fowler St Fort Myers FL 33901",
    "addr:housenumber":"3501",
    "addr:postcode":"33901",
    "addr:street":"Fowler St",
    "iso:country":"US",
    "sg:address":"3501 Fowler St",
    "sg:city":"Fort Myers",
    "sg:classifiers":[
        {
            "category":"Restaurant",
            "type":"Food & Drink"
        }
    ],
    "sg:phone":"+1 239 939 1141",
    "sg:postcode":"33901",
    "sg:province":"FL",
    "wof:name":"Subway Sandwiches & Salads",
    "wof:placetype":"venue"
},
  "geometry": {"coordinates":[-81.86186499999999,26.611856],"type":"Point"}
}