{
  "type": "Feature",
  "properties": {
    "iso:country":"US",
    "sg:address":"7961 SW 89th Ter",
    "sg:city":"Miami",
    "sg:classifiers":[
        {
            "category":"Building & Trades",
            "subcategory":"Construction",
            "type":"Services"
        },
        {
            "category":"Sports & Exercise",
            "subcategory":"Swimming Pool",
            "type":"Entertainment"
        }
    ],
    "sg:phone":"+1 305 596 5035",
    "sg:postcode":"33156",
    "sg:province":"FL",
    "wof:name":"Coronado Pools Inc",
    "wof:placetype":"venue"
},
  "geometry": {"coordinates":[-80.324331,25.686868],"type":"Point"}
}