{
  "type": "Feature",
  "properties": {
    "iso:country":"US",
    "sg:address":"3663 8th St SW",
    "sg:city":"Miami",
    "sg:classifiers":[
        {
            "category":"Building & Trades",
            "subcategory":"Construction",
            "type":"Services"
        }
    ],
    "sg:phone":"+1 305 805 5202",
    "sg:postcode":"33135",
    "sg:province":"FL",
    "sg:tags":[
        "general",
        "contractor"
    ],
    "wof:name":"H F Contractors Inc",
    "wof:placetype":"venue"
},
  "geometry": {"coordinates":[-80.254909,25.764771],"type":"Point"}
}