{
  "type": "Feature",
  "properties": {
    "addr:full":"16452 NE 27th Ave Miami FL 33160",
    "addr:housenumber":"16452",
    "addr:postcode":"33160",
    "addr:street":"Ne 27Th Ave",
    "iso:country":"US",
    "sg:address":"16452 NE 27th Ave",
    "sg:city":"Miami",
    "sg:classifiers":[
        {
            "category":"Building & Trades",
            "subcategory":"Construction",
            "type":"Services"
        }
    ],
    "sg:phone":"+1 305 949 0052",
    "sg:postcode":"33160",
    "sg:province":"FL",
    "sg:tags":[
        "house"
    ],
    "wof:name":"Harvey Cohan Builders",
    "wof:placetype":"venue"
},
  "geometry": {"coordinates":[-80.145948,25.927869],"type":"Point"}
}