{
  "type": "Feature",
  "properties": {
    "iso:country":"US",
    "sg:address":"3241 SW Island Way",
    "sg:city":"Palm City",
    "sg:classifiers":[
        {
            "category":"Professional",
            "subcategory":"Lawyer & Legal Services",
            "type":"Services"
        }
    ],
    "sg:phone":"+1 772 287 1001",
    "sg:postcode":"34990",
    "sg:province":"FL",
    "sg:tags":[
        "attorney"
    ],
    "wof:name":"Vello Veski",
    "wof:placetype":"venue"
},
  "geometry": {"coordinates":[-80.296801,27.198776],"type":"Point"}
}