{
  "type": "Feature",
  "properties": {
    "iso:country":"US",
    "sg:address":"13720 SW 32nd St",
    "sg:city":"Miami",
    "sg:classifiers":[
        {
            "category":"Travel",
            "subcategory":"Travel Agent",
            "type":"Entertainment"
        }
    ],
    "sg:phone":"+1 305 552 6647",
    "sg:postcode":"33175",
    "sg:province":"FL",
    "sg:tags":[
        "agency"
    ],
    "wof:name":"Meagans Bay Travel Consultant",
    "wof:placetype":"venue"
},
  "geometry": {"coordinates":[-80.41725099999999,25.73803],"type":"Point"}
}