{
  "type": "Feature",
  "properties": {
    "addr:full":"4046 Marlow Loop Land O Lakes FL 34639",
    "addr:housenumber":"4046",
    "addr:postcode":"34639",
    "addr:street":"Marlow Loop Land",
    "iso:country":"US",
    "sg:address":"4046 Marlow Loop",
    "sg:city":"Land O Lakes",
    "sg:classifiers":[
        {
            "category":"Professional",
            "subcategory":"Business Services",
            "type":"Services"
        }
    ],
    "sg:phone":"+1 813 929 8588",
    "sg:postcode":"34639",
    "sg:province":"FL",
    "wof:name":"Busekrus Group LLC",
    "wof:placetype":"venue"
},
  "geometry": {"coordinates":[-82.43902799999999,28.215705],"type":"Point"}
}