{
  "type": "Feature",
  "properties": {
    "iso:country":"US",
    "sg:address":"108 Willowtree Ln",
    "sg:city":"Longwood",
    "sg:classifiers":[
        {
            "category":"Building & Trades",
            "subcategory":"Construction",
            "type":"Services"
        }
    ],
    "sg:phone":"+1 407 782 5865",
    "sg:postcode":"32750",
    "sg:province":"FL",
    "sg:tags":[
        "handyman"
    ],
    "wof:name":"Richard Merritt Handyman Svc",
    "wof:placetype":"venue"
},
  "geometry": {"coordinates":[-81.37549199999999,28.712477],"type":"Point"}
}