{
  "type": "Feature",
  "properties": {
    "iso:country":"US",
    "sg:address":"103 Kenilwood Ln",
    "sg:city":"Lakeland",
    "sg:classifiers":[
        {
            "category":"Building & Trades",
            "subcategory":"Landscaping Services",
            "type":"Services"
        }
    ],
    "sg:phone":"+1 863 859 6805",
    "sg:postcode":"33809",
    "sg:province":"FL",
    "wof:name":"Greenfields Landscape Mgt Co",
    "wof:placetype":"venue"
},
  "geometry": {"coordinates":[-81.953689,28.099536],"type":"Point"}
}