{
  "type": "Feature",
  "properties": {
    "iso:country":"US",
    "sg:address":"3758 N Andrews Ave",
    "sg:city":"Fort Lauderdale",
    "sg:classifiers":[
        {
            "category":"Food & Beverages",
            "subcategory":"Groceries & Convenience Stores",
            "type":"Retail Goods"
        },
        {
            "category":"Shopping",
            "subcategory":"Gifts & Souvenirs",
            "type":"Retail Goods"
        }
    ],
    "sg:phone":"+1 954 568 6620",
    "sg:postcode":"33309",
    "sg:province":"FL",
    "sg:tags":[
        "shop"
    ],
    "wof:name":"Conexco Brazil",
    "wof:placetype":"venue"
},
  "geometry": {"coordinates":[-80.14658,26.173439],"type":"Point"}
}