{
  "type": "Feature",
  "properties": {
    "iso:country":"US",
    "sg:address":"3891 Edwards Rd",
    "sg:city":"Fort Pierce",
    "sg:classifiers":[
        {
            "category":"Organizations",
            "subcategory":"Religious Organization",
            "type":"Services"
        }
    ],
    "sg:phone":"+1 772 466 8100",
    "sg:postcode":"34981",
    "sg:province":"FL",
    "sg:tags":[
        "church"
    ],
    "sg:website":"www.cfamins.org",
    "wof:name":"Christian Flshp Live Ministry",
    "wof:placetype":"venue"
},
  "geometry": {"coordinates":[-80.360604,27.407553],"type":"Point"}
}