{
  "type": "Feature",
  "properties": {
    "iso:country":"US",
    "sg:address":"103 Elderwood St",
    "sg:city":"Winter Springs",
    "sg:classifiers":[
        {
            "category":"Building & Trades",
            "subcategory":"Construction",
            "type":"Services"
        }
    ],
    "sg:phone":"+1 407 695 7352",
    "sg:postcode":"32708",
    "sg:province":"FL",
    "sg:tags":[
        "hanging",
        "contractor"
    ],
    "wof:name":"Maintence Hooper Group",
    "wof:placetype":"venue"
},
  "geometry": {"coordinates":[-81.303731,28.688003],"type":"Point"}
}