{
  "type": "Feature",
  "properties": {
    "addr:full":"4526 Garrison Rd Panama City FL 32404",
    "addr:housenumber":"4526",
    "addr:postcode":"32404",
    "addr:street":"Garrison Rd",
    "iso:country":"US",
    "sg:address":"4526 Garrison Rd",
    "sg:city":"Panama City",
    "sg:classifiers":[
        {
            "category":"Building & Trades",
            "subcategory":"Construction",
            "type":"Services"
        }
    ],
    "sg:phone":"+1 850 914 9116",
    "sg:postcode":"32404",
    "sg:province":"FL",
    "sg:tags":[
        "concrete",
        "contractor"
    ],
    "wof:name":"Wallis Stucco & Plastering",
    "wof:placetype":"venue"
},
  "geometry": {"coordinates":[-85.60506700000001,30.226253],"type":"Point"}
}