{
  "type": "Feature",
  "properties": {
    "iso:country":"US",
    "sg:address":"3030 E Semoran Blvd Ste. 192 And 194",
    "sg:city":"Apopka",
    "sg:classifiers":[
        {
            "category":"Professional",
            "subcategory":"Computer Services",
            "type":"Services"
        },
        {
            "category":"Utilities",
            "subcategory":"Telephone",
            "type":"Services"
        },
        {
            "category":"Communications",
            "type":"Services"
        },
        {
            "category":"Communications",
            "subcategory":"Television Station",
            "type":"Services"
        }
    ],
    "sg:phone":"+1 407 788 1388",
    "sg:postcode":"32703",
    "sg:province":"FL",
    "sg:tags":[
        "satellite",
        "cable",
        "tv",
        "isp",
        "system",
        "equipment",
        "internet",
        "data",
        "provider"
    ],
    "sg:website":"http://CenturyLink.com",
    "wof:name":"Apopka CenturyLink Store",
    "wof:placetype":"venue"
},
  "geometry": {"coordinates":[-81.453371,28.670375],"type":"Point"}
}