{
  "type": "Feature",
  "properties": {
    "iso:country":"US",
    "sg:address":"4481 Rainbird Rise Rd",
    "sg:city":"Crestview",
    "sg:classifiers":[
        {
            "category":"Home & Garden",
            "subcategory":"Carpets & Floor Coverings",
            "type":"Retail Goods"
        }
    ],
    "sg:phone":"+1 850 683 0617",
    "sg:postcode":"32539",
    "sg:province":"FL",
    "sg:tags":[
        "material"
    ],
    "wof:name":"Angel Rodriguez Custom Woodwor",
    "wof:placetype":"venue"
},
  "geometry": {"coordinates":[-86.416849,30.823929],"type":"Point"}
}