{
  "type": "Feature",
  "properties": {
    "addr:full":"2267 1st St Fort Myers FL 33901",
    "addr:housenumber":"2267",
    "addr:postcode":"33901",
    "addr:street":"1St St",
    "iso:country":"US",
    "sg:address":"2267 1st St",
    "sg:city":"Fort Myers",
    "sg:classifiers":[
        {
            "category":"Arts & Performance",
            "subcategory":"Theater",
            "type":"Entertainment"
        }
    ],
    "sg:phone":"+1 239 332 4488",
    "sg:postcode":"33901",
    "sg:province":"FL",
    "sg:tags":[
        "performing"
    ],
    "sg:website":"www.floridarep.org",
    "wof:name":"Florida Repertory Theatre",
    "wof:placetype":"venue"
},
  "geometry": {"coordinates":[-81.8694,26.6446],"type":"Point"}
}