{
  "type": "Feature",
  "properties": {
    "iso:country":"US",
    "sg:address":"7454 SW 48th St",
    "sg:city":"Miami",
    "sg:classifiers":[
        {
            "category":"Building & Trades",
            "subcategory":"Electrical",
            "type":"Services"
        }
    ],
    "sg:phone":"+1 305 661 8223",
    "sg:postcode":"33155",
    "sg:province":"FL",
    "sg:tags":[
        "industrial",
        "electrician",
        "contractors-commercial",
        "electric"
    ],
    "wof:name":"Electrical Contractor",
    "wof:placetype":"venue"
},
  "geometry": {"coordinates":[-80.313129,25.725517],"type":"Point"}
}