{
  "type": "Feature",
  "properties": {
    "addr:full":"349 S Main St Belle Glade FL 33430",
    "addr:housenumber":"349",
    "addr:postcode":"33430",
    "addr:street":"S Main St",
    "iso:country":"US",
    "sg:address":"349 S Main St",
    "sg:city":"Belle Glade",
    "sg:classifiers":[
        {
            "category":"Retail",
            "subcategory":"Laundry & Dry Cleaning",
            "type":"Services"
        }
    ],
    "sg:phone":"+1 561 996 4333",
    "sg:postcode":"33430",
    "sg:province":"FL",
    "sg:tags":[
        "garment",
        "agent",
        "cleaners"
    ],
    "wof:name":"Affordable Dry Cleaning Inc",
    "wof:placetype":"venue"
},
  "geometry": {"coordinates":[-80.667744,26.683597],"type":"Point"}
}