{
  "type": "Feature",
  "properties": {
    "addr:full":"121 Appleby St NE Palm Bay FL 32907",
    "addr:housenumber":"121",
    "addr:postcode":"32907",
    "addr:street":"Appleby St Ne",
    "iso:country":"US",
    "sg:address":"121 Appleby St NE",
    "sg:city":"Palm Bay",
    "sg:classifiers":[
        {
            "category":"Retail",
            "subcategory":"Auto Repair",
            "type":"Services"
        }
    ],
    "sg:phone":"+1 321 960 0317",
    "sg:postcode":"32907",
    "sg:province":"FL",
    "sg:tags":[
        "repairing",
        "automobile"
    ],
    "wof:name":"Marcelo A Chaves Auto Repair",
    "wof:placetype":"venue"
},
  "geometry": {"coordinates":[-80.67028500000001,28.00419],"type":"Point"}
}