{
  "type": "Feature",
  "properties": {
    "addr:full":"9341 SW 56th St Miami FL 33165",
    "addr:housenumber":"9341",
    "addr:postcode":"33165",
    "addr:street":"Sw 56Th St",
    "iso:country":"US",
    "sg:address":"9341 SW 56th St",
    "sg:city":"Miami",
    "sg:classifiers":[
        {
            "category":"Fast Food",
            "type":"Food & Drink"
        },
        {
            "category":"Restaurant",
            "type":"Food & Drink"
        }
    ],
    "sg:phone":"+1 305 270 1943",
    "sg:postcode":"33165",
    "sg:province":"FL",
    "sg:tags":[
        "hamburger",
        "hot",
        "dog",
        "american",
        "take",
        "chicken"
    ],
    "sg:website":"http://www.mcdonalds.com",
    "wof:name":"McDonald's",
    "wof:placetype":"venue"
},
  "geometry": {"coordinates":[-80.345721,25.716742],"type":"Point"}
}