{
  "type": "Feature",
  "properties": {
    "iso:country":"US",
    "sg:address":"5600 Old Cheney Hwy",
    "sg:city":"Orlando",
    "sg:classifiers":[
        {
            "category":"Social Services",
            "subcategory":"Child Care",
            "type":"Services"
        }
    ],
    "sg:phone":"+1 407 658 1728",
    "sg:postcode":"32807",
    "sg:province":"FL",
    "sg:tags":[
        "day"
    ],
    "wof:name":"Kiddie Kottage",
    "wof:placetype":"venue"
},
  "geometry": {"coordinates":[-81.310847,28.561577],"type":"Point"}
}