{
  "type": "Feature",
  "properties": {
    "addr:full":"2101 NW 62nd St Fort Lauderdale FL 33309",
    "addr:housenumber":"2101",
    "addr:postcode":"33309",
    "addr:street":"Nw 62Nd St",
    "iso:country":"US",
    "sg:address":"2101 NW 62nd St",
    "sg:city":"Fort Lauderdale",
    "sg:classifiers":[
        {
            "category":"Professional",
            "subcategory":"Computer Services",
            "type":"Services"
        }
    ],
    "sg:phone":"+1 954 975 8011",
    "sg:postcode":"33309",
    "sg:province":"FL",
    "sg:tags":[
        "internet"
    ],
    "wof:name":"Christian Interactive Network",
    "wof:placetype":"venue"
},
  "geometry": {"coordinates":[-80.17935199999999,26.202662],"type":"Point"}
}