{
  "type": "Feature",
  "properties": {
    "iso:country":"US",
    "sg:address":"2740 9th St N",
    "sg:city":"St Petersburg",
    "sg:classifiers":[
        {
            "category":"Retail",
            "subcategory":"Auto Repair",
            "type":"Services"
        }
    ],
    "sg:phone":"+1 727 822 5820",
    "sg:postcode":"33704",
    "sg:province":"FL",
    "sg:tags":[
        "repairing",
        "automobile",
        "general"
    ],
    "wof:name":"Middleton's Auto Care",
    "wof:placetype":"venue"
},
  "geometry": {"coordinates":[-82.646822,27.797156],"type":"Point"}
}