{
  "type": "Feature",
  "properties": {
    "iso:country":"US",
    "sg:address":"27348 Aloha Dr",
    "sg:city":"Punta Gorda",
    "sg:classifiers":[
        {
            "category":"Autos & Motor Vehicles",
            "subcategory":"Boat Sales",
            "type":"Retail Goods"
        }
    ],
    "sg:phone":"+1 941 637 6274",
    "sg:postcode":"33955",
    "sg:province":"FL",
    "wof:name":"Mikeys Jet Ski & Boat Salvage",
    "wof:placetype":"venue"
},
  "geometry": {"coordinates":[-81.996737,26.841441],"type":"Point"}
}