{
  "type": "Feature",
  "properties": {
    "addr:full":"504 Royal Palm Beach Blvd West Palm Beach FL 33411",
    "addr:housenumber":"504",
    "addr:postcode":"33411",
    "addr:street":"Royal Palm Beach Blvd",
    "iso:country":"US",
    "sg:address":"504 Royal Palm Beach Blvd",
    "sg:city":"West Palm Beach",
    "sg:classifiers":[
        {
            "category":"Professional",
            "subcategory":"Accounting & Tax Preparation",
            "type":"Services"
        }
    ],
    "sg:phone":"+1 561 791 0645",
    "sg:postcode":"33411",
    "sg:province":"FL",
    "wof:name":"Carolyn A Gold CPA P A",
    "wof:placetype":"venue"
},
  "geometry": {"coordinates":[-80.230017,26.684143],"type":"Point"}
}