{
  "type": "Feature",
  "properties": {
    "iso:country":"US",
    "sg:address":"403 N 15th St",
    "sg:city":"Immokalee",
    "sg:classifiers":[
        {
            "category":"Utilities",
            "subcategory":"Electric",
            "type":"Services"
        },
        {
            "category":"Manufacturing",
            "subcategory":"Electronics",
            "type":"Manufacturing & Wholesale Goods"
        }
    ],
    "sg:phone":"+1 239 657 6516",
    "sg:postcode":"34142",
    "sg:province":"FL",
    "sg:tags":[
        "equipment-testing"
    ],
    "sg:website":"http://www.lcec.net",
    "wof:name":"Lee County Electric Cooperative, Inc.",
    "wof:placetype":"venue"
},
  "geometry": {"coordinates":[-81.433651,26.422926],"type":"Point"}
}