{
  "type": "Feature",
  "properties": {
    "iso:country":"US",
    "sg:address":"390 N Indiana Ave",
    "sg:city":"Englewood",
    "sg:classifiers":[
        {
            "category":"Home & Garden",
            "subcategory":"Furniture",
            "type":"Retail Goods"
        }
    ],
    "sg:phone":"+1 941 473 1026",
    "sg:postcode":"34223",
    "sg:province":"FL",
    "sg:tags":[
        "new",
        "used"
    ],
    "wof:name":"San Casa Furniture",
    "wof:placetype":"venue"
},
  "geometry": {"coordinates":[-82.35304499999999,26.967649],"type":"Point"}
}