{
  "type": "Feature",
  "properties": {
    "iso:country":"US",
    "sg:address":"201 Monument Rd",
    "sg:city":"Jacksonville",
    "sg:classifiers":[
        {
            "category":"Manufacturing",
            "subcategory":"Wood Products",
            "type":"Manufacturing & Wholesale Goods"
        }
    ],
    "sg:phone":"+1 904 805 0370",
    "sg:postcode":"32225",
    "sg:province":"FL",
    "sg:tags":[
        "mfg"
    ],
    "wof:name":"B A Framer",
    "wof:placetype":"venue"
},
  "geometry": {"coordinates":[-81.54685000000001,30.325725],"type":"Point"}
}