{
  "type": "Feature",
  "properties": {
    "iso:country":"US",
    "sg:address":"660 NE 119th St",
    "sg:city":"Miami",
    "sg:classifiers":[
        {
            "category":"Marine",
            "type":"Transportation"
        }
    ],
    "sg:phone":"+1 305 891 0445",
    "sg:postcode":"33161",
    "sg:province":"FL",
    "sg:tags":[
        "water",
        "transport"
    ],
    "wof:name":"Brett Carlson Marine Surveyers",
    "wof:placetype":"venue"
},
  "geometry": {"coordinates":[-80.185321,25.884751],"type":"Point"}
}