{
  "type": "Feature",
  "properties": {
    "addr:full":"8440 US Hwy 1 Sebastian FL 32976",
    "addr:housenumber":"8440",
    "addr:postcode":"32976",
    "addr:street":"Us Hwy 1",
    "iso:country":"US",
    "sg:address":"8440 US Hwy 1",
    "sg:city":"Sebastian",
    "sg:classifiers":[
        {
            "category":"Real Estate",
            "subcategory":"Real Estate Operator",
            "type":"Services"
        }
    ],
    "sg:phone":"+1 772 664 4560",
    "sg:postcode":"32976",
    "sg:province":"FL",
    "sg:tags":[
        "mobile",
        "home",
        "park",
        "operates"
    ],
    "wof:name":"River Grove Mobile Home Vlg",
    "wof:placetype":"venue"
},
  "geometry": {"coordinates":[-80.498195,27.874421],"type":"Point"}
}