{
  "type": "Feature",
  "properties": {
    "iso:country":"US",
    "sg:address":"1401 Brickell Ave",
    "sg:city":"Miami",
    "sg:classifiers":[
        {
            "category":"Professional",
            "subcategory":"Lawyer & Legal Services",
            "type":"Services"
        }
    ],
    "sg:phone":"+1 305 371 8797",
    "sg:postcode":"33131",
    "sg:province":"FL",
    "sg:tags":[
        "litigation"
    ],
    "wof:name":"Levine Paul A Atty",
    "wof:placetype":"venue"
},
  "geometry": {"coordinates":[-80.19210099999999,25.7603],"type":"Point"}
}