{
  "type": "Feature",
  "properties": {
    "iso:country":"US",
    "sg:address":"10140 SE 139th Pl",
    "sg:city":"Summerfield",
    "sg:classifiers":[
        {
            "category":"Professional",
            "type":"Services"
        }
    ],
    "sg:phone":"+1 352 288 4133",
    "sg:postcode":"34491",
    "sg:province":"FL",
    "sg:tags":[
        "writer"
    ],
    "wof:name":"Connie E Neumann Writer",
    "wof:placetype":"venue"
},
  "geometry": {"coordinates":[-81.98483,29.019412],"type":"Point"}
}