{
  "type": "Feature",
  "properties": {
    "addr:full":"7451 Wilson Blvd Jacksonville FL 32210",
    "addr:housenumber":"7451",
    "addr:postcode":"32210",
    "addr:street":"Wilson Blvd",
    "iso:country":"US",
    "sg:address":"7451 Wilson Blvd",
    "sg:city":"Jacksonville",
    "sg:classifiers":[
        {
            "category":"Bus Charters",
            "type":"Transportation"
        }
    ],
    "sg:phone":"+1 904 268 8082",
    "sg:postcode":"32210",
    "sg:province":"FL",
    "sg:website":"www.annettbuslines.com",
    "wof:name":"Annett Bus Lines",
    "wof:placetype":"venue"
},
  "geometry": {"coordinates":[-81.771884,30.269848],"type":"Point"}
}