{
  "type": "Feature",
  "properties": {
    "addr:full":"694 Unity Dr Melbourne FL 32937",
    "addr:housenumber":"694",
    "addr:postcode":"32937",
    "addr:street":"Unity Dr",
    "iso:country":"US",
    "sg:address":"694 Unity Dr",
    "sg:city":"Melbourne",
    "sg:classifiers":[
        {
            "category":"Building & Trades",
            "subcategory":"Construction",
            "type":"Services"
        }
    ],
    "sg:phone":"+1 321 984 7717",
    "sg:postcode":"32937",
    "sg:province":"FL",
    "sg:tags":[
        "residential"
    ],
    "wof:name":"Emerald Bays",
    "wof:placetype":"venue"
},
  "geometry": {"coordinates":[-80.592445,28.137888],"type":"Point"}
}