{
  "type": "Feature",
  "properties": {
    "addr:full":"1257 Sophie Blvd Orlando FL 32828",
    "addr:housenumber":"1257",
    "addr:postcode":"32828",
    "addr:street":"Sophie Blvd",
    "iso:country":"US",
    "sg:address":"1257 Sophie Blvd",
    "sg:city":"Orlando",
    "sg:classifiers":[
        {
            "category":"Building & Trades",
            "subcategory":"Cleaning & Sanitation",
            "type":"Services"
        }
    ],
    "sg:phone":"+1 407 234 9001",
    "sg:postcode":"32828",
    "sg:province":"FL",
    "sg:tags":[
        "janitor"
    ],
    "wof:name":"A-Plus Office Cleaning Svc",
    "wof:placetype":"venue"
},
  "geometry": {"coordinates":[-81.20371400000001,28.561718],"type":"Point"}
}