{
  "type": "Feature",
  "properties": {
    "addr:full":"3060 Perdue Rd NE Wauchula FL 33873",
    "addr:housenumber":"3060",
    "addr:postcode":"33873",
    "addr:street":"Perdue Rd Ne",
    "iso:country":"US",
    "sg:address":"3060 Perdue Rd NE",
    "sg:city":"Wauchula",
    "sg:classifiers":[
        {
            "category":"Farming",
            "subcategory":"Dairy Farm",
            "type":"Manufacturing & Wholesale Goods"
        }
    ],
    "sg:phone":"+1 863 773 6771",
    "sg:postcode":"33873",
    "sg:province":"FL",
    "wof:name":"Lake Branch Dairy Inc",
    "wof:placetype":"venue"
},
  "geometry": {"coordinates":[-81.760424,27.587904],"type":"Point"}
}