{
  "type": "Feature",
  "properties": {
    "addr:full":"963 Dunn Ave Jacksonville FL 32218",
    "addr:housenumber":"963",
    "addr:postcode":"32218",
    "addr:street":"Dunn Ave",
    "iso:country":"US",
    "sg:address":"963 Dunn Ave",
    "sg:city":"Jacksonville",
    "sg:classifiers":[
        {
            "category":"Food & Beverages",
            "subcategory":"Liquor & Beverages",
            "type":"Retail Goods"
        }
    ],
    "sg:phone":"+1 904 757 9210",
    "sg:postcode":"32218",
    "sg:province":"FL",
    "sg:website":"www.abcfws.com",
    "wof:name":"ABC Fine Wines & Spirits",
    "wof:placetype":"venue"
},
  "geometry": {"coordinates":[-81.665408,30.429934],"type":"Point"}
}