{
  "type": "Feature",
  "properties": {
    "iso:country":"US",
    "sg:address":"826 W Main St",
    "sg:city":"Lake City",
    "sg:classifiers":[
        {
            "category":"Banks & Credit Unions",
            "subcategory":"Bank",
            "type":"Services"
        }
    ],
    "sg:phone":"+1 386 754 1386",
    "sg:postcode":"32054",
    "sg:province":"FL",
    "sg:tags":[
        "loan",
        "real estate"
    ],
    "wof:name":"Farm Credit Of North Florida",
    "wof:placetype":"venue"
},
  "geometry": {"coordinates":[-82.348221,30.024395],"type":"Point"}
}