{
  "type": "Feature",
  "properties": {
    "iso:country":"US",
    "sg:address":"1229 US Hwy 41",
    "sg:city":"Venice",
    "sg:classifiers":[
        {
            "category":"Personal",
            "type":"Services"
        }
    ],
    "sg:phone":"+1 941 468 2037",
    "sg:postcode":"34285",
    "sg:province":"FL",
    "sg:tags":[
        "therapist",
        "massage"
    ],
    "wof:name":"Valre Hart Massage Therapist",
    "wof:placetype":"venue"
},
  "geometry": {"coordinates":[-82.43097,27.07895],"type":"Point"}
}