{
  "type": "Feature",
  "properties": {
    "iso:country":"US",
    "sg:address":"13003 Hidden Ridge Ln",
    "sg:city":"Clermont",
    "sg:classifiers":[
        {
            "category":"Building & Trades",
            "subcategory":"Cleaning & Sanitation",
            "type":"Services"
        }
    ],
    "sg:phone":"+1 407 970 2313",
    "sg:postcode":"34715",
    "sg:province":"FL",
    "sg:tags":[
        "concrete",
        "sealing",
        "restoration"
    ],
    "wof:name":"Protective Coatings Unlimited",
    "wof:placetype":"venue"
},
  "geometry": {"coordinates":[-81.739057,28.661373],"type":"Point"}
}