{
  "type": "Feature",
  "properties": {
    "iso:country":"US",
    "sg:address":"1119 Sunset Dr",
    "sg:city":"Lake Wales",
    "sg:classifiers":[
        {
            "category":"Home & Garden",
            "subcategory":"Household Appliances",
            "type":"Retail Goods"
        }
    ],
    "sg:phone":"+1 863 676 6610",
    "sg:postcode":"33853",
    "sg:province":"FL",
    "wof:name":"L & L Appliance Sales & Svc",
    "wof:placetype":"venue"
},
  "geometry": {"coordinates":[-81.56247999999999,27.901276],"type":"Point"}
}