{
  "type": "Feature",
  "properties": {
    "addr:full":"4014 Gunn Hwy Tampa FL 33618",
    "addr:housenumber":"4014",
    "addr:postcode":"33618",
    "addr:street":"Gunn Hwy",
    "iso:country":"US",
    "sg:address":"4014 Gunn Hwy",
    "sg:city":"Tampa",
    "sg:classifiers":[
        {
            "category":"Insurance",
            "subcategory":"Hazard Insurance",
            "type":"Services"
        },
        {
            "category":"Insurance",
            "subcategory":"Health Insurance",
            "type":"Services"
        }
    ],
    "sg:phone":"+1 813 962 7080",
    "sg:postcode":"33618",
    "sg:province":"FL",
    "sg:tags":[
        "employee",
        "benefit",
        "commercial",
        "business"
    ],
    "sg:website":"http://www.bcbsfl.com",
    "wof:name":"Florida Insurance Inc",
    "wof:placetype":"venue"
},
  "geometry": {"coordinates":[-82.50819799999999,28.038492],"type":"Point"}
}