{
  "type": "Feature",
  "properties": {
    "addr:full":"14897 85th Rd N Loxahatchee FL 33470",
    "addr:housenumber":"14897",
    "addr:postcode":"33470",
    "addr:street":"85Th Rd N",
    "iso:country":"US",
    "sg:address":"14897 85th Rd N",
    "sg:city":"Loxahatchee",
    "sg:classifiers":[
        {
            "category":"Building & Trades",
            "subcategory":"Construction",
            "type":"Services"
        }
    ],
    "sg:phone":"+1 561 844 4664",
    "sg:postcode":"33470",
    "sg:province":"FL",
    "sg:tags":[
        "residential",
        "remodeling",
        "new"
    ],
    "wof:name":"C L R International Inc",
    "wof:placetype":"venue"
},
  "geometry": {"coordinates":[-80.275522,26.803747],"type":"Point"}
}