{
  "type": "Feature",
  "properties": {
    "iso:country":"US",
    "sg:address":"2413 Linwood Ave",
    "sg:city":"Naples",
    "sg:classifiers":[
        {
            "category":"Wholesale",
            "subcategory":"Electrical",
            "type":"Manufacturing & Wholesale Goods"
        }
    ],
    "sg:phone":"+1 239 793 9899",
    "sg:postcode":"34112",
    "sg:province":"FL",
    "sg:tags":[
        "alarm",
        "burglar",
        "system"
    ],
    "wof:name":"A Guardian Protection System",
    "wof:placetype":"venue"
},
  "geometry": {"coordinates":[-81.777827,26.136151],"type":"Point"}
}