{
  "type": "Feature",
  "properties": {
    "iso:country":"US",
    "sg:address":"4108 Laguna St",
    "sg:city":"Miami",
    "sg:classifiers":[
        {
            "category":"Building & Trades",
            "subcategory":"Construction",
            "type":"Services"
        }
    ],
    "sg:phone":"+1 305 774 9000",
    "sg:postcode":"33146",
    "sg:province":"FL",
    "sg:tags":[
        "residential",
        "industrial",
        "general",
        "contractor"
    ],
    "wof:name":"Nunez Construction Inc",
    "wof:placetype":"venue"
},
  "geometry": {"coordinates":[-80.261257,25.734038],"type":"Point"}
}