{
  "type": "Feature",
  "properties": {
    "iso:country":"US",
    "sg:address":"1300 S Federal Hwy",
    "sg:city":"Dania",
    "sg:classifiers":[
        {
            "category":"Restaurant",
            "type":"Food & Drink"
        }
    ],
    "sg:phone":"+1 954 920 2377",
    "sg:postcode":"33004",
    "sg:province":"FL",
    "sg:tags":[
        "eating"
    ],
    "wof:name":"Pizza Hut",
    "wof:placetype":"venue"
},
  "geometry": {"coordinates":[-80.143315,26.03576],"type":"Point"}
}