{
  "type": "Feature",
  "properties": {
    "iso:country":"US",
    "sg:address":"5305 NW 35th Ter",
    "sg:city":"Fort Lauderdale",
    "sg:classifiers":[
        {
            "category":"Health Services",
            "subcategory":"Medical Lab",
            "type":"Services"
        }
    ],
    "sg:phone":"+1 954 733 7499",
    "sg:postcode":"33309",
    "sg:province":"FL",
    "sg:tags":[
        "laboratory"
    ],
    "wof:name":"Kem Medical",
    "wof:placetype":"venue"
},
  "geometry": {"coordinates":[-80.19826500000001,26.191329],"type":"Point"}
}