{
  "type": "Feature",
  "properties": {
    "iso:country":"US",
    "sg:address":"12735 Starkey Rd",
    "sg:city":"Largo",
    "sg:classifiers":[
        {
            "category":"Restaurant",
            "type":"Food & Drink"
        }
    ],
    "sg:menulink":"http://www.allmenus.com/fl/clearwater/82058-dominos-pizza/menu/",
    "sg:phone":"+1 727 530 3335",
    "sg:postcode":"33773",
    "sg:province":"FL",
    "sg:tags":[
        "american",
        "wing",
        "pizza"
    ],
    "wof:name":"Domino's Pizza",
    "wof:placetype":"venue"
},
  "geometry": {"coordinates":[-82.761753,27.888318],"type":"Point"}
}