{
  "type": "Feature",
  "properties": {
    "iso:country":"US",
    "sg:address":"8900 NW 33rd St",
    "sg:city":"Doral",
    "sg:classifiers":[
        {
            "category":"Personal",
            "subcategory":"Shoe Repair & Shine",
            "type":"Services"
        }
    ],
    "sg:phone":"+1 877 380 7675",
    "sg:postcode":"33172",
    "sg:province":"FL",
    "sg:tags":[
        "sunglass"
    ],
    "sg:website":"http://local.ingenio.com/Listings/Details.aspx?NUM=a%3a10316258%3a13%3a4859924%3a14%3a0%3a7",
    "wof:name":"Sunico",
    "wof:placetype":"venue"
},
  "geometry": {"coordinates":[-80.341553,25.80526],"type":"Point"}
}