{
  "type": "Feature",
  "properties": {
    "iso:country":"US",
    "sg:address":"100 Biscayne Blvd",
    "sg:city":"Miami",
    "sg:classifiers":[
        {
            "category":"Health Services",
            "subcategory":"Clinic",
            "type":"Services"
        }
    ],
    "sg:phone":"+1 305 350 6978",
    "sg:postcode":"33131",
    "sg:province":"FL",
    "sg:tags":[
        "home",
        "care"
    ],
    "wof:name":"Vitas Hospice Chariable Fund",
    "wof:placetype":"venue"
},
  "geometry": {"coordinates":[-80.187119,25.772926],"type":"Point"}
}