{
  "type": "Feature",
  "properties": {
    "iso:country":"US",
    "sg:address":"201 Town Center Blvd",
    "sg:city":"Davenport",
    "sg:phone":"+1 863 420 8323",
    "sg:postcode":"33896",
    "sg:province":"FL",
    "sg:website":"http://www.wix.com/AVCFlorida/avc",
    "wof:name":"Atlantic Veterinary Clinic",
    "wof:placetype":"venue"
},
  "geometry": {"coordinates":[-81.590492,28.25045],"type":"Point"}
}