{
  "type": "Feature",
  "properties": {
    "iso:country":"US",
    "sg:address":"3407 NW 72nd Ave",
    "sg:city":"Miami",
    "sg:classifiers":[
        {
            "category":"Restaurant",
            "type":"Food & Drink"
        }
    ],
    "sg:phone":"+1 305 406 2662",
    "sg:postcode":"33125",
    "sg:province":"FL",
    "sg:tags":[
        "seafood"
    ],
    "wof:name":"Port Royale Trading",
    "wof:placetype":"venue"
},
  "geometry": {"coordinates":[-80.233498,25.7815],"type":"Point"}
}