{
  "type": "Feature",
  "properties": {
    "addr:full":"6910 N Kendall Dr Miami FL 33156",
    "addr:housenumber":"6910",
    "addr:postcode":"33156",
    "addr:street":"N Kendall Dr",
    "iso:country":"US",
    "sg:address":"6910 N Kendall Dr",
    "sg:city":"Miami",
    "sg:classifiers":[
        {
            "category":"Health Services",
            "subcategory":"Clinic",
            "type":"Services"
        }
    ],
    "sg:phone":"+1 305 668 5400",
    "sg:postcode":"33156",
    "sg:province":"FL",
    "wof:name":"Florida Total Healthcare",
    "wof:placetype":"venue"
},
  "geometry": {"coordinates":[-80.30548899999999,25.688938],"type":"Point"}
}