{
  "type": "Feature",
  "properties": {
    "iso:country":"US",
    "sg:address":"1056 E 33rd St",
    "sg:city":"Hialeah",
    "sg:classifiers":[
        {
            "category":"Building & Trades",
            "subcategory":"Construction",
            "type":"Services"
        }
    ],
    "sg:phone":"+1 305 261 4399",
    "sg:postcode":"33013",
    "sg:province":"FL",
    "sg:tags":[
        "roofing",
        "contractor"
    ],
    "wof:name":"Sunshine Roofing & Sheet Metal",
    "wof:placetype":"venue"
},
  "geometry": {"coordinates":[-80.261269,25.852713],"type":"Point"}
}