{
  "type": "Feature",
  "properties": {
    "iso:country":"US",
    "sg:address":"5003 Old Cheney Hwy",
    "sg:city":"Orlando",
    "sg:classifiers":[
        {
            "category":"Insurance",
            "subcategory":"Insurance Agent",
            "type":"Services"
        }
    ],
    "sg:phone":"+1 407 273 0230",
    "sg:postcode":"32807",
    "sg:province":"FL",
    "sg:website":"www.jmeyers.com",
    "wof:name":"J Meyers Insurance Group",
    "wof:placetype":"venue"
},
  "geometry": {"coordinates":[-81.320391,28.554447],"type":"Point"}
}