{
  "type": "Feature",
  "properties": {
    "iso:country":"US",
    "sg:address":"8616 Blackberry Ln E",
    "sg:city":"Jacksonville",
    "sg:classifiers":[
        {
            "category":"Professional",
            "type":"Services"
        }
    ],
    "sg:phone":"+1 904 777 6096",
    "sg:postcode":"32244",
    "sg:province":"FL",
    "wof:name":"Paylittle Co",
    "wof:placetype":"venue"
},
  "geometry": {"coordinates":[-81.76284699999999,30.192627],"type":"Point"}
}