{
  "type": "Feature",
  "properties": {
    "addr:full":"914 NE 24th Ln Cape Coral FL 33909",
    "addr:housenumber":"914",
    "addr:postcode":"33909",
    "addr:street":"Ne 24Th Ln",
    "iso:country":"US",
    "sg:address":"914 NE 24th Ln",
    "sg:city":"Cape Coral",
    "sg:classifiers":[
        {
            "category":"Retail",
            "subcategory":"Laundry & Dry Cleaning",
            "type":"Services"
        }
    ],
    "sg:phone":"+1 239 997 0770",
    "sg:postcode":"33909",
    "sg:province":"FL",
    "sg:tags":[
        "cleaners",
        "rug",
        "carpet"
    ],
    "wof:name":"Lee Carpet Cleaning Inc",
    "wof:placetype":"venue"
},
  "geometry": {"coordinates":[-81.953732,26.698175],"type":"Point"}
}