{
  "type": "Feature",
  "properties": {
    "iso:country":"US",
    "sg:address":"3670 NW 79th Way",
    "sg:city":"Hollywood",
    "sg:classifiers":[
        {
            "category":"Professional",
            "subcategory":"Detective & Security Services",
            "type":"Services"
        }
    ],
    "sg:phone":"+1 954 760 7911",
    "sg:postcode":"33024",
    "sg:province":"FL",
    "sg:tags":[
        "control",
        "consultant",
        "access",
        "system",
        "equipment"
    ],
    "wof:name":"A F W Access Systems",
    "wof:placetype":"venue"
},
  "geometry": {"coordinates":[-80.246937,26.041388],"type":"Point"}
}