{
  "type": "Feature",
  "properties": {
    "addr:full":"5165 Canal St Milton FL 32570",
    "addr:housenumber":"5165",
    "addr:postcode":"32570",
    "addr:street":"Canal St",
    "iso:country":"US",
    "sg:address":"5165 Canal St",
    "sg:city":"Milton",
    "sg:classifiers":[
        {
            "category":"Health Services",
            "subcategory":"Health Practitioner",
            "type":"Services"
        }
    ],
    "sg:phone":"+1 850 516 3717",
    "sg:postcode":"32570",
    "sg:province":"FL",
    "sg:tags":[
        "pathologist",
        "speech"
    ],
    "wof:name":"Julie Butler Speech Pthlgst",
    "wof:placetype":"venue"
},
  "geometry": {"coordinates":[-87.038991,30.620104],"type":"Point"}
}