{
  "type": "Feature",
  "properties": {
    "addr:full":"3720 76th St N St Petersburg FL 33710",
    "addr:housenumber":"3720",
    "addr:postcode":"33710",
    "addr:street":"76Th St N",
    "iso:country":"US",
    "sg:address":"3720 76th St N",
    "sg:city":"St Petersburg",
    "sg:classifiers":[
        {
            "category":"Retail",
            "subcategory":"Laundry & Dry Cleaning",
            "type":"Services"
        }
    ],
    "sg:phone":"+1 727 580 3502",
    "sg:postcode":"33710",
    "sg:province":"FL",
    "sg:tags":[
        "cleaners",
        "rug",
        "carpet"
    ],
    "wof:name":"Bastow Carpet & Upholstery Cln",
    "wof:placetype":"venue"
},
  "geometry": {"coordinates":[-82.743431,27.80619],"type":"Point"}
}