{
  "type": "Feature",
  "properties": {
    "iso:country":"US",
    "sg:address":"7141 SW 97th Pl",
    "sg:city":"Ocala",
    "sg:classifiers":[
        {
            "category":"Building & Trades",
            "subcategory":"Construction",
            "type":"Services"
        }
    ],
    "sg:phone":"+1 352 861 2320",
    "sg:postcode":"34476",
    "sg:province":"FL",
    "sg:tags":[
        "roofing",
        "industrial",
        "contractors-commercial",
        "contractor"
    ],
    "wof:name":"Seeber Construction",
    "wof:placetype":"venue"
},
  "geometry": {"coordinates":[-82.238765,29.081343],"type":"Point"}
}