{
  "type": "Feature",
  "properties": {
    "iso:country":"US",
    "sg:address":"315 E Magnolia St",
    "sg:city":"Lakeland",
    "sg:classifiers":[
        {
            "category":"Building & Trades",
            "subcategory":"Electrical",
            "type":"Services"
        }
    ],
    "sg:phone":"+1 863 665 8481",
    "sg:postcode":"33801",
    "sg:province":"FL",
    "sg:tags":[
        "electric",
        "contractor"
    ],
    "wof:name":"Southern Power & Electric",
    "wof:placetype":"venue"
},
  "geometry": {"coordinates":[-81.954334,28.049368],"type":"Point"}
}