{
  "type": "Feature",
  "properties": {
    "addr:full":"1011 Woodfield Cir Palm Beach Gardens FL 33418",
    "addr:housenumber":"1011",
    "addr:postcode":"33418",
    "addr:street":"Woodfield Cir",
    "iso:country":"US",
    "sg:address":"1011 Woodfield Cir",
    "sg:city":"Palm Beach Gardens",
    "sg:classifiers":[
        {
            "category":"Communications",
            "type":"Services"
        }
    ],
    "sg:phone":"+1 561 625 6299",
    "sg:postcode":"33418",
    "sg:province":"FL",
    "sg:tags":[
        "communication"
    ],
    "wof:name":"Wjm Communications",
    "wof:placetype":"venue"
},
  "geometry": {"coordinates":[-80.12179399999999,26.81424],"type":"Point"}
}