{
  "type": "Feature",
  "properties": {
    "iso:country":"US",
    "sg:address":"1375 Jan Lan Blvd",
    "sg:city":"St Cloud",
    "sg:classifiers":[
        {
            "category":"Restaurant",
            "type":"Food & Drink"
        }
    ],
    "sg:phone":"+1 407 957 6250",
    "sg:postcode":"34772",
    "sg:province":"FL",
    "wof:name":"Main Street Grill",
    "wof:placetype":"venue"
},
  "geometry": {"coordinates":[-81.255464,28.236603],"type":"Point"}
}