{
  "type": "Feature",
  "properties": {
    "iso:country":"US",
    "sg:address":"627 S Range St",
    "sg:city":"Madison",
    "sg:classifiers":[
        {
            "category":"Professional",
            "subcategory":"Accounting & Tax Preparation",
            "type":"Services"
        }
    ],
    "sg:phone":"+1 850 973 4353",
    "sg:postcode":"32340",
    "sg:province":"FL",
    "sg:tags":[
        "return",
        "filing"
    ],
    "wof:name":"Schoelles & Assoc Inc",
    "wof:placetype":"venue"
},
  "geometry": {"coordinates":[-83.412977,30.465131],"type":"Point"}
}