{
  "type": "Feature",
  "properties": {
    "iso:country":"US",
    "sg:address":"5470 SE Smith Ave",
    "sg:city":"Stuart",
    "sg:classifiers":[
        {
            "category":"Building & Trades",
            "subcategory":"Electrical",
            "type":"Services"
        }
    ],
    "sg:phone":"+1 561 758 6508",
    "sg:postcode":"34997",
    "sg:province":"FL",
    "sg:tags":[
        "electrical",
        "contractor"
    ],
    "wof:name":"Donovan Wojcieszaks Cabling",
    "wof:placetype":"venue"
},
  "geometry": {"coordinates":[-80.2311,27.135724],"type":"Point"}
}