{
  "type": "Feature",
  "properties": {
    "iso:country":"US",
    "sg:address":"10503 Sago Rd",
    "sg:city":"Tampa",
    "sg:classifiers":[
        {
            "category":"Real Estate",
            "subcategory":"Real Estate Services",
            "type":"Services"
        },
        {
            "category":"Real Estate",
            "subcategory":"Developer",
            "type":"Services"
        },
        {
            "category":"Real Estate",
            "subcategory":"Real Estate Agent",
            "type":"Services"
        }
    ],
    "sg:phone":"+1 813 930 9060",
    "sg:postcode":"33618",
    "sg:province":"FL",
    "sg:tags":[
        "buyer",
        "broker"
    ],
    "wof:name":"Concorde Realty Advisors",
    "wof:placetype":"venue"
},
  "geometry": {"coordinates":[-82.490639,28.043733],"type":"Point"}
}