{
  "type": "Feature",
  "properties": {
    "addr:full":"8290 SW Hwy 200 Ocala FL 34481",
    "addr:housenumber":"8290",
    "addr:postcode":"34481",
    "addr:street":"Sw Hwy 200",
    "iso:country":"US",
    "sg:address":"8290 SW Hwy 200",
    "sg:city":"Ocala",
    "sg:classifiers":[
        {
            "category":"Banks & Credit Unions",
            "subcategory":"Investment Brokerage",
            "type":"Services"
        }
    ],
    "sg:phone":"+1 352 732 0160",
    "sg:postcode":"34481",
    "sg:province":"FL",
    "sg:tags":[
        "security"
    ],
    "wof:name":"Southtrust Securities Inc",
    "wof:placetype":"venue"
},
  "geometry": {"coordinates":[-82.252674,29.083609],"type":"Point"}
}