{
  "type": "Feature",
  "properties": {
    "iso:country":"US",
    "sg:address":"5955 Pine Ridge Rd",
    "sg:city":"Naples",
    "sg:classifiers":[
        {
            "category":"Restaurant",
            "type":"Food & Drink"
        }
    ],
    "sg:phone":"+1 239 455 7987",
    "sg:postcode":"34119",
    "sg:province":"FL",
    "wof:name":"Subway Sandwiches & Salads",
    "wof:placetype":"venue"
},
  "geometry": {"coordinates":[-81.71619800000001,26.211919],"type":"Point"}
}