{
  "type": "Feature",
  "properties": {
    "addr:full":"1786 SW 1st St Miami FL 33135",
    "addr:housenumber":"1786",
    "addr:postcode":"33135",
    "addr:street":"Sw 1St St",
    "iso:country":"US",
    "sg:address":"1786 SW 1st St",
    "sg:city":"Miami",
    "sg:classifiers":[
        {
            "category":"Personal",
            "subcategory":"Beauty Salon",
            "type":"Services"
        }
    ],
    "sg:phone":"+1 305 642 3754",
    "sg:postcode":"33135",
    "sg:province":"FL",
    "wof:name":"Sache Unisex",
    "wof:placetype":"venue"
},
  "geometry": {"coordinates":[-80.223795,25.771966],"type":"Point"}
}