{
  "type": "Feature",
  "properties": {
    "addr:full":"1645 W 49th St Hialeah FL 33012",
    "addr:housenumber":"1645",
    "addr:postcode":"33012",
    "addr:street":"W 49Th St",
    "iso:country":"US",
    "sg:address":"1645 W 49th St",
    "sg:city":"Hialeah",
    "sg:classifiers":[
        {
            "category":"Shopping",
            "subcategory":"Discount & Variety Stores",
            "type":"Retail Goods"
        }
    ],
    "sg:phone":"+1 305 364 4083",
    "sg:postcode":"33012",
    "sg:province":"FL",
    "wof:name":"Hollywood Dollar Store Inc",
    "wof:placetype":"venue"
},
  "geometry": {"coordinates":[-80.316923,25.866664],"type":"Point"}
}