{
  "type": "Feature",
  "properties": {
    "iso:country":"US",
    "sg:address":"13144 Park Blvd",
    "sg:city":"Largo",
    "sg:classifiers":[
        {
            "category":"Personal",
            "type":"Services"
        }
    ],
    "sg:phone":"+1 727 399 8856",
    "sg:postcode":"33776",
    "sg:province":"FL",
    "sg:tags":[
        "hair",
        "replacement"
    ],
    "wof:name":"Murray Hair Transplant Clinic",
    "wof:placetype":"venue"
},
  "geometry": {"coordinates":[-82.822079,27.843617],"type":"Point"}
}