{
  "type": "Feature",
  "properties": {
    "iso:country":"US",
    "sg:address":"3013 Wedge Ct",
    "sg:city":"Orlando",
    "sg:classifiers":[
        {
            "category":"Retail",
            "subcategory":"Auto Repair",
            "type":"Services"
        }
    ],
    "sg:phone":"+1 407 273 0828",
    "sg:postcode":"32817",
    "sg:province":"FL",
    "sg:tags":[
        "repairing",
        "automobile"
    ],
    "wof:name":"Jimenez Import Repair",
    "wof:placetype":"venue"
},
  "geometry": {"coordinates":[-81.27622599999999,28.581661],"type":"Point"}
}