{
  "type": "Feature",
  "properties": {
    "iso:country":"US",
    "sg:address":"551 Laurel Ct",
    "sg:city":"Winter Springs",
    "sg:classifiers":[
        {
            "category":"Building & Trades",
            "subcategory":"Locksmith",
            "type":"Services"
        }
    ],
    "sg:phone":"+1 407 702 1563",
    "sg:postcode":"32708",
    "sg:province":"FL",
    "sg:tags":[
        "key"
    ],
    "wof:name":"1 Action 7 Day Lock Service",
    "wof:placetype":"venue"
},
  "geometry": {"coordinates":[-81.31146699999999,28.684784],"type":"Point"}
}