{
  "type": "Feature",
  "properties": {
    "addr:full":"6774 Taylor St Milton FL 32570",
    "addr:housenumber":"6774",
    "addr:postcode":"32570",
    "addr:street":"Taylor St",
    "iso:country":"US",
    "sg:address":"6774 Taylor St",
    "sg:city":"Milton",
    "sg:classifiers":[
        {
            "category":"Building & Trades",
            "subcategory":"Construction",
            "type":"Services"
        }
    ],
    "sg:phone":"+1 850 623 2857",
    "sg:postcode":"32570",
    "sg:province":"FL",
    "sg:tags":[
        "handyman"
    ],
    "wof:name":"Timothy Nelson Handyman",
    "wof:placetype":"venue"
},
  "geometry": {"coordinates":[-87.036625,30.612249],"type":"Point"}
}