{
  "type": "Feature",
  "properties": {
    "addr:full":"513 W Helm Way Casselberry FL 32707",
    "addr:housenumber":"513",
    "addr:postcode":"32707",
    "addr:street":"W Helm Way",
    "iso:country":"US",
    "sg:address":"513 W Helm Way",
    "sg:city":"Casselberry",
    "sg:classifiers":[
        {
            "category":"Building & Trades",
            "subcategory":"Construction",
            "type":"Services"
        }
    ],
    "sg:phone":"+1 407 834 1409",
    "sg:postcode":"32707",
    "sg:province":"FL",
    "sg:tags":[
        "contractor"
    ],
    "wof:name":"S Adams Drywall",
    "wof:placetype":"venue"
},
  "geometry": {"coordinates":[-81.317696,28.657064],"type":"Point"}
}