{
  "type": "Feature",
  "properties": {
    "iso:country":"US",
    "sg:address":"3624 Harborview Ct",
    "sg:city":"New Port Richey",
    "sg:classifiers":[
        {
            "category":"Shopping",
            "subcategory":"Clothing, Apparel, & Fashions",
            "type":"Retail Goods"
        }
    ],
    "sg:phone":"+1 727 847 3323",
    "sg:postcode":"34652",
    "sg:province":"FL",
    "wof:name":"Leather Wear Intl Inc",
    "wof:placetype":"venue"
},
  "geometry": {"coordinates":[-82.75445000000001,28.236297],"type":"Point"}
}