{
  "type": "Feature",
  "properties": {
    "addr:full":"4102 W Linebaugh Ave Tampa FL 33624",
    "addr:housenumber":"4102",
    "addr:postcode":"33624",
    "addr:street":"W Linebaugh Ave",
    "iso:country":"US",
    "sg:address":"4102 W Linebaugh Ave",
    "sg:city":"Tampa",
    "sg:classifiers":[
        {
            "category":"Social Services",
            "type":"Services"
        }
    ],
    "sg:phone":"+1 813 960 2229",
    "sg:postcode":"33624",
    "sg:province":"FL",
    "sg:tags":[
        "agency",
        "adoption"
    ],
    "wof:name":"ABC Adoptions By Choice",
    "wof:placetype":"venue"
},
  "geometry": {"coordinates":[-82.50891,28.04016],"type":"Point"}
}