{
  "type": "Feature",
  "properties": {
    "iso:country":"US",
    "sg:address":"9009 NW 152nd Ln",
    "sg:city":"Hialeah",
    "sg:classifiers":[
        {
            "category":"Retail",
            "subcategory":"Auto Repair",
            "type":"Services"
        }
    ],
    "sg:phone":"+1 305 821 3018",
    "sg:postcode":"33018",
    "sg:province":"FL",
    "sg:tags":[
        "automotive"
    ],
    "wof:name":"Ralph A Rojas Towing",
    "wof:placetype":"venue"
},
  "geometry": {"coordinates":[-80.347854,25.912116],"type":"Point"}
}