{
  "type": "Feature",
  "properties": {
    "iso:country":"US",
    "sg:address":"7782 Tennyson Ct",
    "sg:city":"Boca Raton",
    "sg:classifiers":[
        {
            "category":"Professional",
            "subcategory":"Engineering",
            "type":"Services"
        }
    ],
    "sg:phone":"+1 561 394 2120",
    "sg:postcode":"33433",
    "sg:province":"FL",
    "wof:name":"Norman Tandy & Associates",
    "wof:placetype":"venue"
},
  "geometry": {"coordinates":[-80.167023,26.342981],"type":"Point"}
}