{
  "type": "Feature",
  "properties": {
    "iso:country":"US",
    "sg:address":"1500 Biscayne Blvd",
    "sg:city":"Miami",
    "sg:classifiers":[
        {
            "category":"Education",
            "subcategory":"Library",
            "type":"Public Place"
        }
    ],
    "sg:phone":"+1 305 995 2249",
    "sg:postcode":"33132",
    "sg:province":"FL",
    "wof:name":"Library Media Services",
    "wof:placetype":"venue"
},
  "geometry": {"coordinates":[-80.189086,25.789996],"type":"Point"}
}