{
  "type": "Feature",
  "properties": {
    "iso:country":"US",
    "sg:address":"1101 Oak Ln",
    "sg:city":"Winter Springs",
    "sg:classifiers":[
        {
            "category":"Wholesale",
            "subcategory":"Metals & Minerals",
            "type":"Manufacturing & Wholesale Goods"
        }
    ],
    "sg:phone":"+1 407 339 2576",
    "sg:postcode":"32708",
    "sg:province":"FL",
    "sg:tags":[
        "steel",
        "warehouse"
    ],
    "wof:name":"Alro Metals Inc",
    "wof:placetype":"venue"
},
  "geometry": {"coordinates":[-81.32543699999999,28.701473],"type":"Point"}
}