{
  "type": "Feature",
  "properties": {
    "addr:full":"150 S Park Ave Winter Park FL 32789",
    "addr:housenumber":"150",
    "addr:postcode":"32789",
    "addr:street":"S Park Ave",
    "iso:country":"US",
    "sg:address":"150 S Park Ave",
    "sg:city":"Winter Park",
    "sg:classifiers":[
        {
            "category":"Home & Garden",
            "subcategory":"Home Furnishings",
            "type":"Retail Goods"
        }
    ],
    "sg:phone":"+1 407 628 5900",
    "sg:postcode":"32789",
    "sg:province":"FL",
    "sg:tags":[
        "bath",
        "kitchen",
        "accessory"
    ],
    "sg:website":"www.williams-sonoma.com",
    "wof:name":"Williams Sonoma",
    "wof:placetype":"venue"
},
  "geometry": {"coordinates":[-81.351196,28.597099],"type":"Point"}
}