{
  "type": "Feature",
  "properties": {
    "iso:country":"US",
    "sg:address":"2940 Justina Rd",
    "sg:city":"Jacksonville",
    "sg:classifiers":[
        {
            "category":"Organizations",
            "subcategory":"Religious Organization",
            "type":"Services"
        }
    ],
    "sg:phone":"+1 904 744 9744",
    "sg:postcode":"32277",
    "sg:province":"FL",
    "sg:tags":[
        "church"
    ],
    "wof:name":"New Revelation Ministries",
    "wof:placetype":"venue"
},
  "geometry": {"coordinates":[-81.599568,30.354091],"type":"Point"}
}