{
  "type": "Feature",
  "properties": {
    "iso:country":"US",
    "sg:address":"7400 Canada Ave",
    "sg:city":"Orlando",
    "sg:classifiers":[
        {
            "category":"Travel",
            "subcategory":"Hotels & Motels",
            "type":"Entertainment"
        }
    ],
    "sg:phone":"+1 407 363 0332",
    "sg:postcode":"32819",
    "sg:province":"FL",
    "sg:tags":[
        "operation"
    ],
    "wof:name":"Quality Inn",
    "wof:placetype":"venue"
},
  "geometry": {"coordinates":[-81.468407,28.452566],"type":"Point"}
}