{
  "type": "Feature",
  "properties": {
    "addr:full":"17408 Heather Oaks Pl Tampa FL 33647",
    "addr:housenumber":"17408",
    "addr:postcode":"33647",
    "addr:street":"Heather Oaks Pl",
    "iso:country":"US",
    "sg:address":"17408 Heather Oaks Pl",
    "sg:city":"Tampa",
    "sg:classifiers":[
        {
            "category":"Wholesale",
            "subcategory":"Medical Equipment & Supplies",
            "type":"Manufacturing & Wholesale Goods"
        }
    ],
    "sg:phone":"+1 813 973 2325",
    "sg:postcode":"33647",
    "sg:province":"FL",
    "sg:tags":[
        "orthopedic",
        "sales"
    ],
    "wof:name":"Fox Orthopedics Inc",
    "wof:placetype":"venue"
},
  "geometry": {"coordinates":[-82.35553899999999,28.122122],"type":"Point"}
}