{
  "type": "Feature",
  "properties": {
    "iso:country":"US",
    "sg:address":"4232 Fort Courage Cir",
    "sg:city":"Kissimmee",
    "sg:classifiers":[
        {
            "category":"Building & Trades",
            "subcategory":"Construction",
            "type":"Services"
        }
    ],
    "sg:phone":"+1 407 870 5653",
    "sg:postcode":"34746",
    "sg:province":"FL",
    "sg:tags":[
        "floor",
        "laying",
        "contractor"
    ],
    "wof:name":"Nick Huckabee",
    "wof:placetype":"venue"
},
  "geometry": {"coordinates":[-81.43939899999999,28.165401],"type":"Point"}
}