{
  "type": "Feature",
  "properties": {
    "addr:full":"1106 Illinois Ave Palm Harbor FL 34683",
    "addr:housenumber":"1106",
    "addr:postcode":"34683",
    "addr:street":"Illinois Ave",
    "iso:country":"US",
    "sg:address":"1106 Illinois Ave",
    "sg:city":"Palm Harbor",
    "sg:classifiers":[
        {
            "category":"Freight",
            "type":"Transportation"
        }
    ],
    "sg:phone":"+1 727 781 3382",
    "sg:postcode":"34683",
    "sg:province":"FL",
    "sg:tags":[
        "trucking"
    ],
    "wof:name":"Armellini Express Lines Inc",
    "wof:placetype":"venue"
},
  "geometry": {"coordinates":[-82.764984,28.074373],"type":"Point"}
}