{
  "type": "Feature",
  "properties": {
    "addr:full":"9776 S Military Trl Boynton Beach FL 33436",
    "addr:housenumber":"9776",
    "addr:postcode":"33436",
    "addr:street":"S Military Trl",
    "iso:country":"US",
    "sg:address":"9776 S Military Trl",
    "sg:city":"Boynton Beach",
    "sg:classifiers":[
        {
            "category":"Social Services",
            "subcategory":"Job Training",
            "type":"Services"
        }
    ],
    "sg:phone":"+1 561 369 7655",
    "sg:postcode":"33436",
    "sg:province":"FL",
    "sg:tags":[
        "rehabilitation"
    ],
    "wof:name":"Total Rehab & Medical Ctr",
    "wof:placetype":"venue"
},
  "geometry": {"coordinates":[-80.12277,26.530944],"type":"Point"}
}