{
  "type": "Feature",
  "properties": {
    "iso:country":"US",
    "sg:address":"2917 Optimist Dr",
    "sg:city":"Marianna",
    "sg:classifiers":[
        {
            "category":"Insurance",
            "subcategory":"Insurance Agent",
            "type":"Services"
        }
    ],
    "sg:phone":"+1 850 526 5690",
    "sg:postcode":"32448",
    "sg:province":"FL",
    "wof:name":"Hagan Agency",
    "wof:placetype":"venue"
},
  "geometry": {"coordinates":[-85.253151,30.77747],"type":"Point"}
}