{
  "type": "Feature",
  "properties": {
    "iso:country":"US",
    "sg:address":"213 N Parsons Ave",
    "sg:city":"Brandon",
    "sg:classifiers":[
        {
            "category":"Professional",
            "subcategory":"Accounting & Tax Preparation",
            "type":"Services"
        }
    ],
    "sg:phone":"+1 813 651 0406",
    "sg:postcode":"33510",
    "sg:province":"FL",
    "sg:tags":[
        "accountant",
        "public",
        "certified"
    ],
    "wof:name":"Stephen G Connett CPA PA",
    "wof:placetype":"venue"
},
  "geometry": {"coordinates":[-82.285736,27.940885],"type":"Point"}
}