{
  "type": "Feature",
  "properties": {
    "iso:country":"US",
    "sg:address":"300 W 41st St",
    "sg:city":"Miami Beach",
    "sg:classifiers":[
        {
            "category":"Health Services",
            "subcategory":"Clinic",
            "type":"Services"
        }
    ],
    "sg:phone":"+1 305 674 1300",
    "sg:postcode":"33140",
    "sg:province":"FL",
    "sg:tags":[
        "specialty",
        "outpatient"
    ],
    "wof:name":"Miami Beach Rehabilitation",
    "wof:placetype":"venue"
},
  "geometry": {"coordinates":[-80.126886,25.813741],"type":"Point"}
}