{
  "type": "Feature",
  "properties": {
    "iso:country":"US",
    "sg:address":"1601 Hicks Ditch Rd",
    "sg:city":"Eustis",
    "sg:classifiers":[
        {
            "category":"Farming",
            "subcategory":"Livestock Farm",
            "type":"Manufacturing & Wholesale Goods"
        }
    ],
    "sg:phone":"+1 352 357 2839",
    "sg:postcode":"32726",
    "sg:province":"FL",
    "sg:tags":[
        "ranch"
    ],
    "wof:name":"J Getford",
    "wof:placetype":"venue"
},
  "geometry": {"coordinates":[-81.671097,28.87336],"type":"Point"}
}