{
  "type": "Feature",
  "properties": {
    "addr:full":"12327 Howey Cross Rd Clermont FL 34715",
    "addr:housenumber":"12327",
    "addr:postcode":"34715",
    "addr:street":"Howey Cross Rd",
    "iso:country":"US",
    "sg:address":"12327 Howey Cross Rd",
    "sg:city":"Clermont",
    "sg:classifiers":[
        {
            "category":"Health Services",
            "subcategory":"Clinic",
            "type":"Services"
        },
        {
            "category":"Health Services",
            "subcategory":"Health Practitioner",
            "type":"Services"
        }
    ],
    "sg:phone":"+1 352 394 3190",
    "sg:postcode":"34715",
    "sg:province":"FL",
    "sg:tags":[
        "therapist",
        "therapy",
        "physical"
    ],
    "wof:name":"Donna Shepperd Lmt",
    "wof:placetype":"venue"
},
  "geometry": {"coordinates":[-81.75064399999999,28.644987],"type":"Point"}
}