{
  "type": "Feature",
  "properties": {
    "addr:full":"1919 Robie Ave Mount Dora FL 32757",
    "addr:housenumber":"1919",
    "addr:postcode":"32757",
    "addr:street":"Robie Ave",
    "iso:country":"US",
    "sg:address":"1919 Robie Ave",
    "sg:city":"Mount Dora",
    "sg:classifiers":[
        {
            "category":"Manufacturing",
            "subcategory":"Watercraft",
            "type":"Manufacturing & Wholesale Goods"
        }
    ],
    "sg:phone":"+1 352 735 2909",
    "sg:postcode":"32757",
    "sg:province":"FL",
    "sg:tags":[
        "repairing"
    ],
    "wof:name":"Wekiva Canoe Co",
    "wof:placetype":"venue"
},
  "geometry": {"coordinates":[-81.625055,28.789664],"type":"Point"}
}