{
  "type": "Feature",
  "properties": {
    "iso:country":"US",
    "sg:address":"10217 Gulfshore Dr",
    "sg:city":"Naples",
    "sg:classifiers":[
        {
            "category":"Banks & Credit Unions",
            "subcategory":"Financial Services",
            "type":"Services"
        }
    ],
    "sg:phone":"+1 239 598 4550",
    "sg:postcode":"34108",
    "sg:province":"FL",
    "sg:tags":[
        "company",
        "holding"
    ],
    "wof:name":"Clearly Holdings LLC",
    "wof:placetype":"venue"
},
  "geometry": {"coordinates":[-81.824697,26.264321],"type":"Point"}
}