{
  "type": "Feature",
  "properties": {
    "iso:country":"US",
    "sg:address":"8800 Adamo Dr",
    "sg:city":"Tampa",
    "sg:classifiers":[
        {
            "category":"Retail",
            "subcategory":"Auto Rental",
            "type":"Services"
        }
    ],
    "sg:phone":"+1 813 908 0808",
    "sg:postcode":"33619",
    "sg:province":"FL",
    "sg:tags":[
        "truck"
    ],
    "wof:name":"Ryder",
    "wof:placetype":"venue"
},
  "geometry": {"coordinates":[-82.36027199999999,27.950017],"type":"Point"}
}