{
  "type": "Feature",
  "properties": {
    "iso:country":"US",
    "sg:address":"3641 Manor Oaks Dr",
    "sg:city":"Jacksonville",
    "sg:classifiers":[
        {
            "category":"Building & Trades",
            "subcategory":"Pest Control",
            "type":"Services"
        }
    ],
    "sg:phone":"+1 904 743 7611",
    "sg:postcode":"32277",
    "sg:province":"FL",
    "sg:tags":[
        "termite"
    ],
    "wof:name":"Clifton Termite And Pest Control Inc",
    "wof:placetype":"venue"
},
  "geometry": {"coordinates":[-81.567581,30.367189],"type":"Point"}
}