{
  "type": "Feature",
  "properties": {
    "iso:country":"US",
    "sg:address":"3481 Cedarwood Trl",
    "sg:city":"Tallahassee",
    "sg:classifiers":[
        {
            "category":"Professional",
            "subcategory":"Management & Consulting",
            "type":"Services"
        }
    ],
    "sg:phone":"+1 850 294 4808",
    "sg:postcode":"32312",
    "sg:province":"FL",
    "sg:tags":[
        "party",
        "planning"
    ],
    "wof:name":"Music & Motorsports Mgmt",
    "wof:placetype":"venue"
},
  "geometry": {"coordinates":[-84.23083,30.578332],"type":"Point"}
}