{
  "type": "Feature",
  "properties": {
    "iso:country":"US",
    "sg:address":"6900 N Church Ave",
    "sg:city":"Mulberry",
    "sg:classifiers":[
        {
            "category":"Personal",
            "subcategory":"Beauty Salon",
            "type":"Services"
        }
    ],
    "sg:phone":"+1 863 607 9927",
    "sg:postcode":"33860",
    "sg:province":"FL",
    "sg:tags":[
        "hair",
        "stylist"
    ],
    "sg:website":"http://www.smartstyle.com",
    "wof:name":"Smartstyle Salon",
    "wof:placetype":"venue"
},
  "geometry": {"coordinates":[-81.974182,27.93478],"type":"Point"}
}