{
  "type": "Feature",
  "properties": {
    "iso:country":"US",
    "sg:address":"6099 Patricia Pl",
    "sg:city":"Spring Hill",
    "sg:classifiers":[
        {
            "category":"Real Estate",
            "subcategory":"Real Estate Agent",
            "type":"Services"
        }
    ],
    "sg:phone":"+1 352 597 1740",
    "sg:postcode":"34607",
    "sg:province":"FL",
    "wof:name":"Melvin Spinoza",
    "wof:placetype":"venue"
},
  "geometry": {"coordinates":[-82.595164,28.516676],"type":"Point"}
}