{
  "type": "Feature",
  "properties": {
    "iso:country":"US",
    "sg:address":"1696 SE Hillmoor Dr",
    "sg:city":"Port Saint Lucie",
    "sg:classifiers":[
        {
            "category":"Health Services",
            "subcategory":"Podiatrist",
            "type":"Services"
        }
    ],
    "sg:phone":"+1 772 335 0057",
    "sg:postcode":"34952",
    "sg:province":"FL",
    "wof:name":"Saint Lucie Foot & Ankle Ctr",
    "wof:placetype":"venue"
},
  "geometry": {"coordinates":[-80.296796,27.288404],"type":"Point"}
}