{
  "type": "Feature",
  "properties": {
    "iso:country":"US",
    "sg:address":"2625 S Highway 29",
    "sg:city":"Cantonment",
    "sg:classifiers":[
        {
            "category":"Autos & Motor Vehicles",
            "subcategory":"Auto Supplies",
            "type":"Retail Goods"
        }
    ],
    "sg:phone":"+1 850 438 7596",
    "sg:postcode":"32533",
    "sg:province":"FL",
    "sg:tags":[
        "body",
        "truck"
    ],
    "wof:name":"Truck Equipment Sales",
    "wof:placetype":"venue"
},
  "geometry": {"coordinates":[-87.29291600000001,30.575919],"type":"Point"}
}