{
  "type": "Feature",
  "properties": {
    "iso:country":"US",
    "sg:address":"2967 SE San Jeronimo Rd",
    "sg:city":"Port Saint Lucie",
    "sg:classifiers":[
        {
            "category":"Building & Trades",
            "subcategory":"Construction",
            "type":"Services"
        }
    ],
    "sg:phone":"+1 772 398 4440",
    "sg:postcode":"34952",
    "sg:province":"FL",
    "sg:tags":[
        "carpentry",
        "contractor"
    ],
    "wof:name":"Danforth Carpentry",
    "wof:placetype":"venue"
},
  "geometry": {"coordinates":[-80.30929399999999,27.255234],"type":"Point"}
}