{
  "type": "Feature",
  "properties": {
    "iso:country":"US",
    "sg:address":"19701 NW 84th Ct",
    "sg:city":"Hialeah",
    "sg:classifiers":[
        {
            "category":"Personal",
            "type":"Services"
        }
    ],
    "sg:phone":"+1 305 829 2915",
    "sg:postcode":"33015",
    "sg:province":"FL",
    "wof:name":"Stress Free Massage Service",
    "wof:placetype":"venue"
},
  "geometry": {"coordinates":[-80.339033,25.952234],"type":"Point"}
}