{
  "type": "Feature",
  "properties": {
    "addr:full":"5017 Bennington Pl Rockledge FL 32955",
    "addr:housenumber":"5017",
    "addr:postcode":"32955",
    "addr:street":"Bennington Pl",
    "iso:country":"US",
    "sg:address":"5017 Bennington Pl",
    "sg:city":"Rockledge",
    "sg:classifiers":[
        {
            "category":"Shopping",
            "subcategory":"Clothing, Apparel, & Fashions",
            "type":"Retail Goods"
        }
    ],
    "sg:phone":"+1 321 961 0173",
    "sg:postcode":"32955",
    "sg:province":"FL",
    "sg:tags":[
        "dressmaker"
    ],
    "wof:name":"Nels' Dressmaking & Alteration",
    "wof:placetype":"venue"
},
  "geometry": {"coordinates":[-80.71640499999999,28.277172],"type":"Point"}
}