{
  "type": "Feature",
  "properties": {
    "iso:country":"US",
    "sg:address":"16215 SW 117th Ave",
    "sg:city":"Miami",
    "sg:classifiers":[
        {
            "category":"Manufacturing",
            "subcategory":"Tools & Machinery",
            "type":"Manufacturing & Wholesale Goods"
        }
    ],
    "sg:phone":"+1 305 253 8222",
    "sg:postcode":"33177",
    "sg:province":"FL",
    "sg:tags":[
        "millwright"
    ],
    "wof:name":"Miami Millwrights",
    "wof:placetype":"venue"
},
  "geometry": {"coordinates":[-80.381834,25.616584],"type":"Point"}
}