{
  "type": "Feature",
  "properties": {
    "addr:full":"101 Bush Blvd Sanford FL 32773",
    "addr:housenumber":"101",
    "addr:postcode":"32773",
    "addr:street":"Bush Blvd",
    "iso:country":"US",
    "sg:address":"101 Bush Blvd",
    "sg:city":"Sanford",
    "sg:classifiers":[
        {
            "category":"Government",
            "subcategory":"Office",
            "type":"Public Place"
        }
    ],
    "sg:phone":"+1 407 665 4356",
    "sg:postcode":"32773",
    "sg:province":"FL",
    "sg:website":"www.seminoleclerk.org",
    "wof:name":"Seminole County Circuit Crmnl",
    "wof:placetype":"venue"
},
  "geometry": {"coordinates":[-81.300494,28.747653],"type":"Point"}
}