{
  "type": "Feature",
  "properties": {
    "iso:country":"US",
    "sg:address":"6797 Capri Ln",
    "sg:city":"Bokeelia",
    "sg:classifiers":[
        {
            "category":"Building & Trades",
            "subcategory":"Construction",
            "type":"Services"
        }
    ],
    "sg:phone":"+1 239 282 9195",
    "sg:postcode":"33922",
    "sg:province":"FL",
    "sg:tags":[
        "residential",
        "carpentry",
        "contractor"
    ],
    "wof:name":"X Cell Contracting Inc",
    "wof:placetype":"venue"
},
  "geometry": {"coordinates":[-82.136948,26.65918],"type":"Point"}
}