{
  "type": "Feature",
  "properties": {
    "addr:full":"347 Eland Dr Fort Myers FL 33917",
    "addr:housenumber":"347",
    "addr:postcode":"33917",
    "addr:street":"Eland Dr",
    "iso:country":"US",
    "sg:address":"347 Eland Dr",
    "sg:city":"Fort Myers",
    "sg:classifiers":[
        {
            "category":"Building & Trades",
            "subcategory":"Landscaping Services",
            "type":"Services"
        }
    ],
    "sg:phone":"+1 239 994 1535",
    "sg:postcode":"33917",
    "sg:province":"FL",
    "wof:name":"Michael W Spradlin Lawn Svcs",
    "wof:placetype":"venue"
},
  "geometry": {"coordinates":[-81.896641,26.71508],"type":"Point"}
}