{
  "type": "Feature",
  "properties": {
    "iso:country":"US",
    "sg:address":"4301 Palm Ave",
    "sg:city":"Hialeah",
    "sg:classifiers":[
        {
            "category":"Personal",
            "subcategory":"Beauty Salon",
            "type":"Services"
        }
    ],
    "sg:phone":"+1 305 827 2224",
    "sg:postcode":"33012",
    "sg:province":"FL",
    "sg:tags":[
        "shop"
    ],
    "wof:name":"Marisela Beauty Salon",
    "wof:placetype":"venue"
},
  "geometry": {"coordinates":[-80.28286199999999,25.86227],"type":"Point"}
}