{
  "type": "Feature",
  "properties": {
    "addr:full":"3047 Waters View Cir Orange Park FL 32073",
    "addr:housenumber":"3047",
    "addr:postcode":"32073",
    "addr:street":"Waters View Cir",
    "iso:country":"US",
    "sg:address":"3047 Waters View Cir",
    "sg:city":"Orange Park",
    "sg:classifiers":[
        {
            "category":"Building & Trades",
            "subcategory":"Construction",
            "type":"Services"
        }
    ],
    "sg:phone":"+1 904 838 0802",
    "sg:postcode":"32073",
    "sg:province":"FL",
    "sg:tags":[
        "house"
    ],
    "wof:name":"Jims Affordable Home Repairs",
    "wof:placetype":"venue"
},
  "geometry": {"coordinates":[-81.796223,30.187583],"type":"Point"}
}