{
  "type": "Feature",
  "properties": {
    "addr:full":"2911 Grand Ave Miami FL 33133",
    "addr:housenumber":"2911",
    "addr:postcode":"33133",
    "addr:street":"Grand Ave",
    "iso:country":"US",
    "sg:address":"2911 Grand Ave",
    "sg:city":"Miami",
    "sg:classifiers":[
        {
            "category":"Bars & Pubs",
            "type":"Food & Drink"
        }
    ],
    "sg:phone":"+1 305 443 5060",
    "sg:postcode":"33133",
    "sg:province":"FL",
    "sg:website":"www.wetwillies.com",
    "wof:name":"Wet Willies",
    "wof:placetype":"venue"
},
  "geometry": {"coordinates":[-80.24050099999999,25.728201],"type":"Point"}
}