{
  "type": "Feature",
  "properties": {
    "iso:country":"US",
    "sg:address":"3450 Morris St N",
    "sg:city":"St Petersburg",
    "sg:classifiers":[
        {
            "category":"Building & Trades",
            "subcategory":"Equipment Rental",
            "type":"Services"
        }
    ],
    "sg:phone":"+1 727 528 2877",
    "sg:postcode":"33713",
    "sg:province":"FL",
    "sg:tags":[
        "audio",
        "leasing"
    ],
    "wof:name":"Industrial Strength Inc",
    "wof:placetype":"venue"
},
  "geometry": {"coordinates":[-82.672388,27.803432],"type":"Point"}
}