{
  "type": "Feature",
  "properties": {
    "iso:country":"US",
    "sg:address":"7030 Pine Forest Rd",
    "sg:city":"Pensacola",
    "sg:classifiers":[
        {
            "category":"Health Services",
            "subcategory":"Health Practitioner",
            "type":"Services"
        }
    ],
    "sg:phone":"+1 850 944 5360",
    "sg:postcode":"32526",
    "sg:province":"FL",
    "wof:name":"Pine Forest Physical Therapy",
    "wof:placetype":"venue"
},
  "geometry": {"coordinates":[-87.305992,30.492605],"type":"Point"}
}