{
  "type": "Feature",
  "properties": {
    "addr:full":"2119 Greenbriar Blvd Clearwater FL 33763",
    "addr:housenumber":"2119",
    "addr:postcode":"33763",
    "addr:street":"Greenbriar Blvd",
    "iso:country":"US",
    "sg:address":"2119 Greenbriar Blvd",
    "sg:city":"Clearwater",
    "sg:classifiers":[
        {
            "category":"Transit Center",
            "subcategory":"Freight",
            "type":"Transportation"
        },
        {
            "category":"Freight",
            "type":"Transportation"
        }
    ],
    "sg:phone":"+1 727 483 0662",
    "sg:postcode":"33763",
    "sg:province":"FL",
    "sg:tags":[
        "local",
        "trucking-motor",
        "trucking"
    ],
    "wof:name":"J And D Moving Company",
    "wof:placetype":"venue"
},
  "geometry": {"coordinates":[-82.75000900000001,28.008368],"type":"Point"}
}