{
  "type": "Feature",
  "properties": {
    "addr:full":"7418 SW 48th St Miami FL 33155",
    "addr:housenumber":"7418",
    "addr:postcode":"33155",
    "addr:street":"Sw 48Th St",
    "iso:country":"US",
    "sg:address":"7418 SW 48th St",
    "sg:city":"Miami",
    "sg:classifiers":[
        {
            "category":"Real Estate",
            "subcategory":"Architect",
            "type":"Services"
        }
    ],
    "sg:phone":"+1 305 667 6333",
    "sg:postcode":"33155",
    "sg:province":"FL",
    "wof:name":"Axioma 3 Inc",
    "wof:placetype":"venue"
},
  "geometry": {"coordinates":[-80.312991,25.725531],"type":"Point"}
}