{
  "type": "Feature",
  "properties": {
    "addr:full":"1031 Ives Dairy Rd Miami FL 33179",
    "addr:housenumber":"1031",
    "addr:postcode":"33179",
    "addr:street":"Ives Dairy Rd",
    "iso:country":"US",
    "sg:address":"1031 Ives Dairy Rd",
    "sg:city":"Miami",
    "sg:classifiers":[
        {
            "category":"Professional",
            "subcategory":"Business Services",
            "type":"Services"
        },
        {
            "category":"Wholesale",
            "subcategory":"Books, Periodicals, & Newspapers",
            "type":"Manufacturing & Wholesale Goods"
        }
    ],
    "sg:phone":"+1 305 914 3783",
    "sg:postcode":"33179",
    "sg:province":"FL",
    "sg:tags":[
        "consultant",
        "publishing",
        "representative",
        "publisher"
    ],
    "wof:name":"Casaclup International",
    "wof:placetype":"venue"
},
  "geometry": {"coordinates":[-80.182689,25.964585],"type":"Point"}
}