{
  "type": "Feature",
  "properties": {
    "iso:country":"US",
    "sg:address":"5090 Coconut Creek Pkwy",
    "sg:city":"Margate",
    "sg:classifiers":[
        {
            "category":"Organizations",
            "subcategory":"Community Association",
            "type":"Services"
        }
    ],
    "sg:phone":"+1 954 971 1163",
    "sg:postcode":"33063",
    "sg:province":"FL",
    "wof:name":"Youth Co-Op Inc",
    "wof:placetype":"venue"
},
  "geometry": {"coordinates":[-80.1956,26.24453],"type":"Point"}
}