{
  "type": "Feature",
  "properties": {
    "iso:country":"US",
    "sg:address":"108 N Magnolia Ave",
    "sg:city":"Ocala",
    "sg:classifiers":[
        {
            "category":"Professional",
            "subcategory":"Accounting & Tax Preparation",
            "type":"Services"
        }
    ],
    "sg:phone":"+1 352 840 0688",
    "sg:postcode":"34475",
    "sg:province":"FL",
    "sg:tags":[
        "return",
        "filing"
    ],
    "wof:name":"Reiuceo Tax Svc",
    "wof:placetype":"venue"
},
  "geometry": {"coordinates":[-82.13701,29.188553],"type":"Point"}
}