{
  "type": "Feature",
  "properties": {
    "iso:country":"US",
    "sg:address":"13305 Panama City Beach Pkwy",
    "sg:city":"Panama City Bch",
    "sg:classifiers":[
        {
            "category":"Professional",
            "subcategory":"Engineering",
            "type":"Services"
        }
    ],
    "sg:phone":"+1 850 230 8812",
    "sg:postcode":"32407",
    "sg:province":"FL",
    "sg:tags":[
        "engineer"
    ],
    "sg:website":"www.carrengineering.com",
    "wof:name":"Carr Engineering & Constr Inc",
    "wof:placetype":"venue"
},
  "geometry": {"coordinates":[-85.842145,30.206355],"type":"Point"}
}