{
  "type": "Feature",
  "properties": {
    "addr:full":"8353 W Flagler St Miami FL 33144",
    "addr:housenumber":"8353",
    "addr:postcode":"33144",
    "addr:street":"W Flagler St",
    "iso:country":"US",
    "sg:address":"8353 W Flagler St",
    "sg:city":"Miami",
    "sg:classifiers":[
        {
            "category":"Bakery",
            "type":"Food & Drink"
        }
    ],
    "sg:phone":"+1 305 262 7626",
    "sg:postcode":"33144",
    "sg:province":"FL",
    "wof:name":"Marilyn Bakery II",
    "wof:placetype":"venue"
},
  "geometry": {"coordinates":[-80.33110000000001,25.7696],"type":"Point"}
}