{
  "type": "Feature",
  "properties": {
    "iso:country":"US",
    "sg:address":"4340 SW 20 Ave",
    "sg:city":"Gainesville",
    "sg:classifiers":[
        {
            "category":"Food & Beverages",
            "subcategory":"Liquor & Beverages",
            "type":"Retail Goods"
        }
    ],
    "sg:phone":"+1 352 335 7055",
    "sg:postcode":"32607",
    "sg:province":"FL",
    "sg:tags":[
        "beer",
        "ale",
        "alcoholic"
    ],
    "wof:name":"Tailgate Beverages",
    "wof:placetype":"venue"
},
  "geometry": {"coordinates":[-82.389309,29.636364],"type":"Point"}
}