{
  "type": "Feature",
  "properties": {
    "iso:country":"US",
    "sg:address":"3043 W Cleveland St",
    "sg:city":"Tampa",
    "sg:classifiers":[
        {
            "category":"Health Services",
            "subcategory":"Doctor",
            "type":"Services"
        }
    ],
    "sg:phone":"+1 813 876 9961",
    "sg:postcode":"33609",
    "sg:province":"FL",
    "sg:tags":[
        "physician",
        "surgeon"
    ],
    "wof:name":"Bayside Physicians",
    "wof:placetype":"venue"
},
  "geometry": {"coordinates":[-82.49257,27.94352],"type":"Point"}
}