{
  "type": "Feature",
  "properties": {
    "addr:full":"2320 SW 56th Ter Hollywood FL 33023",
    "addr:housenumber":"2320",
    "addr:postcode":"33023",
    "addr:street":"Sw 56Th Ter",
    "iso:country":"US",
    "sg:address":"2320 SW 56th Ter",
    "sg:city":"Hollywood",
    "sg:classifiers":[
        {
            "category":"Manufacturing",
            "subcategory":"Metals",
            "type":"Manufacturing & Wholesale Goods"
        }
    ],
    "sg:phone":"+1 954 981 1991",
    "sg:postcode":"33023",
    "sg:province":"FL",
    "sg:tags":[
        "finisher"
    ],
    "wof:name":"Stuart Metal Finishing Inc",
    "wof:placetype":"venue"
},
  "geometry": {"coordinates":[-80.199502,25.987978],"type":"Point"}
}