{
  "type": "Feature",
  "properties": {
    "iso:country":"US",
    "sg:address":"204 Kelly Rd",
    "sg:city":"Niceville",
    "sg:classifiers":[
        {
            "category":"Freight",
            "type":"Transportation"
        }
    ],
    "sg:phone":"+1 850 729 1005",
    "sg:postcode":"32578",
    "sg:province":"FL",
    "sg:tags":[
        "commercial",
        "storage"
    ],
    "wof:name":"Jone's Mini Storage",
    "wof:placetype":"venue"
},
  "geometry": {"coordinates":[-86.504013,30.521343],"type":"Point"}
}