{
  "type": "Feature",
  "properties": {
    "addr:full":"8201 Coral Way Miami FL 33155",
    "addr:housenumber":"8201",
    "addr:postcode":"33155",
    "addr:street":"Coral Way",
    "iso:country":"US",
    "sg:address":"8201 Coral Way",
    "sg:city":"Miami",
    "sg:classifiers":[
        {
            "category":"Professional",
            "subcategory":"Engineering",
            "type":"Services"
        }
    ],
    "sg:phone":"+1 305 262 5151",
    "sg:postcode":"33155",
    "sg:province":"FL",
    "sg:tags":[
        "civil",
        "environmental",
        "planning",
        "engineer"
    ],
    "wof:name":"Cas Engineering Inc",
    "wof:placetype":"venue"
},
  "geometry": {"coordinates":[-80.32924199999999,25.747595],"type":"Point"}
}