{
  "type": "Feature",
  "properties": {
    "iso:country":"US",
    "sg:address":"14230 W Dixie Hwy",
    "sg:city":"North Miami",
    "sg:classifiers":[
        {
            "category":"Building & Trades",
            "subcategory":"Locksmith",
            "type":"Services"
        }
    ],
    "sg:phone":"+1 786 228 5653",
    "sg:postcode":"33161",
    "sg:province":"FL",
    "sg:tags":[
        "key"
    ],
    "wof:name":"Anywhere Locksmith Service On W Dixie Hwy",
    "wof:placetype":"venue"
},
  "geometry": {"coordinates":[-80.17196,25.90643],"type":"Point"}
}