{
  "type": "Feature",
  "properties": {
    "iso:country":"US",
    "sg:address":"5308 Long Rd",
    "sg:city":"Orlando",
    "sg:classifiers":[
        {
            "category":"Building & Trades",
            "subcategory":"Cleaning & Sanitation",
            "type":"Services"
        },
        {
            "category":"Personal",
            "type":"Services"
        }
    ],
    "sg:phone":"+1 407 232 0546",
    "sg:postcode":"32808",
    "sg:province":"FL",
    "sg:tags":[
        "maids'",
        "house",
        "contractor",
        "cleaning-industrial",
        "butlers'",
        "janitorial"
    ],
    "sg:website":"http://www.haywoodsmaids.com",
    "wof:name":"Haywood's Maids & Cleaning Services",
    "wof:placetype":"venue"
},
  "geometry": {"coordinates":[-81.434748,28.608827],"type":"Point"}
}