{
  "type": "Feature",
  "properties": {
    "iso:country":"US",
    "sg:address":"698 Anchor Dr",
    "sg:city":"Sanibel",
    "sg:classifiers":[
        {
            "category":"Banks & Credit Unions",
            "subcategory":"Investment Brokerage",
            "type":"Services"
        }
    ],
    "sg:phone":"+1 239 395 2419",
    "sg:postcode":"33957",
    "sg:province":"FL",
    "sg:tags":[
        "advisory"
    ],
    "wof:name":"Impala Investment Partners",
    "wof:placetype":"venue"
},
  "geometry": {"coordinates":[-82.031319,26.44614],"type":"Point"}
}