{
  "type": "Feature",
  "properties": {
    "addr:full":"9150 S Apopka Vineland Rd Orlando FL 32836",
    "addr:housenumber":"9150",
    "addr:postcode":"32836",
    "addr:street":"S Apopka Vineland Rd",
    "iso:country":"US",
    "sg:address":"9150 S Apopka Vineland Rd",
    "sg:city":"Orlando",
    "sg:classifiers":[
        {
            "category":"Education",
            "subcategory":"School",
            "type":"Public Place"
        }
    ],
    "sg:phone":"+1 407 876 4266",
    "sg:postcode":"32836",
    "sg:province":"FL",
    "sg:tags":[
        "elementary"
    ],
    "wof:name":"Bay Meadows",
    "wof:placetype":"venue"
},
  "geometry": {"coordinates":[-81.503939,28.433294],"type":"Point"}
}