{
  "type": "Feature",
  "properties": {
    "iso:country":"US",
    "sg:address":"1092 Wilson St",
    "sg:city":"Melbourne",
    "sg:classifiers":[
        {
            "category":"Wholesale",
            "subcategory":"Groceries",
            "type":"Manufacturing & Wholesale Goods"
        }
    ],
    "sg:phone":"+1 321 259 3485",
    "sg:postcode":"32935",
    "sg:province":"FL",
    "wof:name":"Deanna Maloney",
    "wof:placetype":"venue"
},
  "geometry": {"coordinates":[-80.654201,28.126745],"type":"Point"}
}