{
  "type": "Feature",
  "properties": {
    "addr:full":"9393 Chumuckla Hwy Milton FL 32571",
    "addr:housenumber":"9393",
    "addr:postcode":"32571",
    "addr:street":"Chumuckla Hwy",
    "iso:country":"US",
    "sg:address":"9393 Chumuckla Hwy",
    "sg:city":"Milton",
    "sg:classifiers":[
        {
            "category":"Banks & Credit Unions",
            "subcategory":"Investment Brokerage",
            "type":"Services"
        }
    ],
    "sg:phone":"+1 850 995 9677",
    "sg:postcode":"32571",
    "sg:province":"FL",
    "sg:tags":[
        "advisory",
        "financial"
    ],
    "wof:name":"Tatum Financial",
    "wof:placetype":"venue"
},
  "geometry": {"coordinates":[-87.207638,30.784038],"type":"Point"}
}