{
  "type": "Feature",
  "properties": {
    "addr:full":"3611 NW 46th St Miami FL 33142",
    "addr:housenumber":"3611",
    "addr:postcode":"33142",
    "addr:street":"Nw 46Th St",
    "iso:country":"US",
    "sg:address":"3611 NW 46th St",
    "sg:city":"Miami",
    "sg:classifiers":[
        {
            "category":"Retail",
            "subcategory":"Auto Repair",
            "type":"Services"
        }
    ],
    "sg:phone":"+1 305 637 0788",
    "sg:postcode":"33142",
    "sg:province":"FL",
    "sg:tags":[
        "repairing",
        "automobile"
    ],
    "wof:name":"L & J Auto Svc",
    "wof:placetype":"venue"
},
  "geometry": {"coordinates":[-80.256061,25.816106],"type":"Point"}
}