{
  "type": "Feature",
  "properties": {
    "iso:country":"US",
    "sg:address":"2884 Waverly Falls Ct",
    "sg:city":"Jacksonville",
    "sg:classifiers":[
        {
            "category":"Restaurant",
            "type":"Food & Drink"
        }
    ],
    "sg:phone":"+1 904 292 0462",
    "sg:postcode":"32224",
    "sg:province":"FL",
    "sg:tags":[
        "house",
        "steak",
        "barbecue"
    ],
    "wof:name":"Beach Blvd Bbq Dba Woody S",
    "wof:placetype":"venue"
},
  "geometry": {"coordinates":[-81.44547900000001,30.295372],"type":"Point"}
}