{
  "type": "Feature",
  "properties": {
    "addr:full":"4480 Exchange Ave Naples FL 34104",
    "addr:housenumber":"4480",
    "addr:postcode":"34104",
    "addr:street":"Exchange Ave",
    "iso:country":"US",
    "sg:address":"4480 Exchange Ave",
    "sg:city":"Naples",
    "sg:classifiers":[
        {
            "category":"Recreation",
            "subcategory":"Marina",
            "type":"Entertainment"
        }
    ],
    "sg:phone":"+1 239 435 9189",
    "sg:postcode":"34104",
    "sg:province":"FL",
    "sg:tags":[
        "repair",
        "operation"
    ],
    "wof:name":"All Marine",
    "wof:placetype":"venue"
},
  "geometry": {"coordinates":[-81.757024,26.158757],"type":"Point"}
}