{
  "type": "Feature",
  "properties": {
    "iso:country":"US",
    "sg:address":"12277 SW 130th St",
    "sg:city":"Miami",
    "sg:classifiers":[
        {
            "category":"Professional",
            "subcategory":"Research",
            "type":"Services"
        }
    ],
    "sg:phone":"+1 786 573 2247",
    "sg:postcode":"33186",
    "sg:province":"FL",
    "sg:tags":[
        "development",
        "electronics"
    ],
    "wof:name":"Niles Audio Corp",
    "wof:placetype":"venue"
},
  "geometry": {"coordinates":[-80.392833,25.647046],"type":"Point"}
}