{
  "type": "Feature",
  "properties": {
    "iso:country":"US",
    "sg:address":"8911 Daniels Pkwy",
    "sg:city":"Fort Myers",
    "sg:classifiers":[
        {
            "category":"Sports & Exercise",
            "subcategory":"Gym",
            "type":"Entertainment"
        }
    ],
    "sg:phone":"+1 239 561 7474",
    "sg:postcode":"33912",
    "sg:province":"FL",
    "sg:tags":[
        "facility",
        "club",
        "gymnasium",
        "health",
        "fitness",
        "studio",
        "physical"
    ],
    "wof:name":"Elite Body Physique",
    "wof:placetype":"venue"
},
  "geometry": {"coordinates":[-81.808307,26.547116],"type":"Point"}
}