{
  "type": "Feature",
  "properties": {
    "addr:full":"2530 Green Spring Dr Jacksonville FL 32246",
    "addr:housenumber":"2530",
    "addr:postcode":"32246",
    "addr:street":"Green Spring Dr",
    "iso:country":"US",
    "sg:address":"2530 Green Spring Dr",
    "sg:city":"Jacksonville",
    "sg:classifiers":[
        {
            "category":"Retail",
            "subcategory":"Auto Repair",
            "type":"Services"
        }
    ],
    "sg:phone":"+1 904 642 0358",
    "sg:postcode":"32246",
    "sg:province":"FL",
    "sg:tags":[
        "general"
    ],
    "wof:name":"Smooth Edge MBL Auto Detailing",
    "wof:placetype":"venue"
},
  "geometry": {"coordinates":[-81.519019,30.301796],"type":"Point"}
}