{
  "type": "Feature",
  "properties": {
    "addr:full":"7601 Seminole Blvd Seminole FL 33772",
    "addr:housenumber":"7601",
    "addr:postcode":"33772",
    "addr:street":"Seminole Blvd",
    "iso:country":"US",
    "sg:address":"7601 Seminole Blvd",
    "sg:city":"Seminole",
    "sg:classifiers":[
        {
            "category":"Health Services",
            "subcategory":"Doctor",
            "type":"Services"
        },
        {
            "category":"Health Services",
            "subcategory":"Clinic",
            "type":"Services"
        }
    ],
    "sg:phone":"+1 727 399 9922",
    "sg:postcode":"33772",
    "sg:province":"FL",
    "sg:tags":[
        "physician",
        "gynecology",
        "surgeons",
        "osteopathic",
        "obstetrics",
        "surgeon"
    ],
    "wof:name":"Ritter Brooke DO",
    "wof:placetype":"venue"
},
  "geometry": {"coordinates":[-82.786987,27.841675],"type":"Point"}
}