{
  "type": "Feature",
  "properties": {
    "iso:country":"US",
    "sg:address":"12966 N Dale Mabry Hwy",
    "sg:city":"Tampa",
    "sg:classifiers":[
        {
            "category":"Real Estate",
            "subcategory":"Real Estate Agent",
            "type":"Services"
        }
    ],
    "sg:phone":"+1 813 962 1777",
    "sg:postcode":"33618",
    "sg:province":"FL",
    "sg:website":"www.erapologroup.com",
    "wof:name":"Polo Group Inc",
    "wof:placetype":"venue"
},
  "geometry": {"coordinates":[-82.50403,28.06324],"type":"Point"}
}