{
  "type": "Feature",
  "properties": {
    "iso:country":"US",
    "sg:address":"4924 Lake Worth Rd",
    "sg:city":"Greenacres",
    "sg:classifiers":[
        {
            "category":"Home & Garden",
            "subcategory":"Garden Supply",
            "type":"Retail Goods"
        },
        {
            "category":"Personal",
            "type":"Services"
        },
        {
            "category":"Shopping",
            "subcategory":"Florist",
            "type":"Retail Goods"
        },
        {
            "category":"Farming",
            "subcategory":"Nursery",
            "type":"Manufacturing & Wholesale Goods"
        }
    ],
    "sg:phone":"+1 561 968 1109",
    "sg:postcode":"33463",
    "sg:province":"FL",
    "sg:tags":[
        "plant",
        "nurseries-plants",
        "consultant",
        "tree",
        "planning",
        "wedding",
        "party",
        "event"
    ],
    "sg:website":"http://www.flowerjungleoflakeworth.com",
    "wof:name":"Flower Jungle",
    "wof:placetype":"venue"
},
  "geometry": {"coordinates":[-80.12048299999999,26.618674],"type":"Point"}
}