{
  "type": "Feature",
  "properties": {
    "addr:full":"2118 N Mac Dill Ave Tampa FL 33607",
    "addr:housenumber":"2118",
    "addr:postcode":"33607",
    "addr:street":"N Mac Dill Ave",
    "iso:country":"US",
    "sg:address":"2118 N Mac Dill Ave",
    "sg:city":"Tampa",
    "sg:classifiers":[
        {
            "category":"Social Services",
            "subcategory":"Child Care",
            "type":"Services"
        }
    ],
    "sg:phone":"+1 813 873 2244",
    "sg:postcode":"33607",
    "sg:province":"FL",
    "sg:tags":[
        "day"
    ],
    "wof:name":"Tweety Twins Day Care Center",
    "wof:placetype":"venue"
},
  "geometry": {"coordinates":[-82.49327599999999,27.961079],"type":"Point"}
}