{
  "type": "Feature",
  "properties": {
    "iso:country":"US",
    "sg:address":"6834 Gall Blvd",
    "sg:city":"Zephyrhills",
    "sg:phone":"+1 813 782 7117",
    "sg:postcode":"33542",
    "sg:province":"FL",
    "sg:tags":[
        "gas"
    ],
    "wof:name":"Suburban Propane",
    "wof:placetype":"venue"
},
  "geometry": {"coordinates":[-82.18811599999999,28.25598],"type":"Point"}
}