{
  "type": "Feature",
  "properties": {
    "addr:full":"214 Domaris Ave Lake Wales FL 33853",
    "addr:housenumber":"214",
    "addr:postcode":"33853",
    "addr:street":"Domaris Ave",
    "iso:country":"US",
    "sg:address":"214 Domaris Ave",
    "sg:city":"Lake Wales",
    "sg:classifiers":[
        {
            "category":"Building & Trades",
            "subcategory":"Pest Control",
            "type":"Services"
        }
    ],
    "sg:phone":"+1 863 676 0107",
    "sg:postcode":"33853",
    "sg:province":"FL",
    "wof:name":"Truman's Pest Control",
    "wof:placetype":"venue"
},
  "geometry": {"coordinates":[-81.585731,27.893031],"type":"Point"}
}