{
  "type": "Feature",
  "properties": {
    "iso:country":"US",
    "sg:address":"12929 Williams Rd",
    "sg:city":"Dade City",
    "sg:classifiers":[
        {
            "category":"Shopping",
            "subcategory":"Clothing, Apparel, & Fashions",
            "type":"Retail Goods"
        }
    ],
    "sg:phone":"+1 352 567 7670",
    "sg:postcode":"33525",
    "sg:province":"FL",
    "sg:tags":[
        "wear"
    ],
    "wof:name":"New Kid Fashions",
    "wof:placetype":"venue"
},
  "geometry": {"coordinates":[-82.21963599999999,28.345708],"type":"Point"}
}