{
  "type": "Feature",
  "properties": {
    "addr:full":"278 Fairway Cir Naples FL 34110",
    "addr:housenumber":"278",
    "addr:postcode":"34110",
    "addr:street":"Fairway Cir",
    "iso:country":"US",
    "sg:address":"278 Fairway Cir",
    "sg:city":"Naples",
    "sg:classifiers":[
        {
            "category":"Building & Trades",
            "subcategory":"Construction",
            "type":"Services"
        }
    ],
    "sg:phone":"+1 239 514 3586",
    "sg:postcode":"34110",
    "sg:province":"FL",
    "sg:tags":[
        "painting",
        "contractor"
    ],
    "wof:name":"JP Home Finishes Inc",
    "wof:placetype":"venue"
},
  "geometry": {"coordinates":[-81.78267700000001,26.282183],"type":"Point"}
}