{
  "type": "Feature",
  "properties": {
    "iso:country":"US",
    "sg:address":"210 N University Dr",
    "sg:city":"Pompano Beach",
    "sg:classifiers":[
        {
            "category":"Utilities",
            "subcategory":"Mobile Phone",
            "type":"Services"
        }
    ],
    "sg:phone":"+1 954 755 3271",
    "sg:postcode":"33071",
    "sg:province":"FL",
    "sg:tags":[
        "radio",
        "pager",
        "communication"
    ],
    "wof:name":"Metrocall Holdings Inc",
    "wof:placetype":"venue"
},
  "geometry": {"coordinates":[-80.254367,26.235783],"type":"Point"}
}