{
  "type": "Feature",
  "properties": {
    "addr:full":"206 E Brandon Blvd Brandon FL 33511",
    "addr:housenumber":"206",
    "addr:postcode":"33511",
    "addr:street":"E Brandon Blvd",
    "iso:country":"US",
    "sg:address":"206 E Brandon Blvd",
    "sg:city":"Brandon",
    "sg:classifiers":[
        {
            "category":"Health Services",
            "subcategory":"Doctor",
            "type":"Services"
        }
    ],
    "sg:phone":"+1 813 681 5571",
    "sg:postcode":"33511",
    "sg:province":"FL",
    "sg:tags":[
        "clinic"
    ],
    "wof:name":"Doctor's Walk-In Clinic",
    "wof:placetype":"venue"
},
  "geometry": {"coordinates":[-82.28415800000001,27.937812],"type":"Point"}
}