{
  "type": "Feature",
  "properties": {
    "iso:country":"US",
    "sg:address":"125 SW 34th St",
    "sg:city":"Gainesville",
    "sg:classifiers":[
        {
            "category":"Food & Beverages",
            "subcategory":"Groceries & Convenience Stores",
            "type":"Retail Goods"
        }
    ],
    "sg:phone":"+1 352 376 1217",
    "sg:postcode":"32608",
    "sg:province":"FL",
    "sg:tags":[
        "grocer",
        "supermarket"
    ],
    "wof:name":"Publix Super Market 125",
    "wof:placetype":"venue"
},
  "geometry": {"coordinates":[-82.367492,29.599832],"type":"Point"}
}