{
  "type": "Feature",
  "properties": {
    "addr:full":"442 Grace Ave Panama City FL 32401",
    "addr:housenumber":"442",
    "addr:postcode":"32401",
    "addr:street":"Grace Ave",
    "iso:country":"US",
    "sg:address":"442 Grace Ave",
    "sg:city":"Panama City",
    "sg:classifiers":[
        {
            "category":"Professional",
            "subcategory":"Lawyer & Legal Services",
            "type":"Services"
        }
    ],
    "sg:phone":"+1 850 747 8131",
    "sg:postcode":"32401",
    "sg:province":"FL",
    "wof:name":"Mallorey & Warner PA",
    "wof:placetype":"venue"
},
  "geometry": {"coordinates":[-85.66147599999999,30.15627],"type":"Point"}
}