{
  "type": "Feature",
  "properties": {
    "iso:country":"US",
    "sg:address":"3621 Central Ave",
    "sg:city":"St Petersburg",
    "sg:classifiers":[
        {
            "category":"Professional",
            "subcategory":"Lawyer & Legal Services",
            "type":"Services"
        }
    ],
    "sg:phone":"+1 727 327 7526",
    "sg:postcode":"33713",
    "sg:province":"FL",
    "sg:tags":[
        "attorney"
    ],
    "wof:name":"Edward T Culbertson PA",
    "wof:placetype":"venue"
},
  "geometry": {"coordinates":[-82.683224,27.771073],"type":"Point"}
}