{
  "type": "Feature",
  "properties": {
    "addr:full":"2007 Gandy Blvd N Saint Petersburg FL 33702",
    "addr:housenumber":"2007",
    "addr:postcode":"33702",
    "addr:street":"Gandy Blvd N",
    "iso:country":"US",
    "sg:address":"2007 Gandy Blvd N",
    "sg:city":"Saint Petersburg",
    "sg:classifiers":[
        {
            "category":"Retail",
            "subcategory":"Repair Shop",
            "type":"Services"
        }
    ],
    "sg:phone":"+1 727 576 1140",
    "sg:postcode":"33702",
    "sg:province":"FL",
    "sg:tags":[
        "machine",
        "vending"
    ],
    "wof:name":"Canteen Vending",
    "wof:placetype":"venue"
},
  "geometry": {"coordinates":[-82.653547,27.857695],"type":"Point"}
}