{
  "type": "Feature",
  "properties": {
    "addr:full":"1059 N Range Rd Cocoa FL 32926",
    "addr:housenumber":"1059",
    "addr:postcode":"32926",
    "addr:street":"N Range Rd",
    "iso:country":"US",
    "sg:address":"1059 N Range Rd",
    "sg:city":"Cocoa",
    "sg:classifiers":[
        {
            "category":"Real Estate",
            "subcategory":"Real Estate Agent",
            "type":"Services"
        }
    ],
    "sg:phone":"+1 321 639 7786",
    "sg:postcode":"32926",
    "sg:province":"FL",
    "sg:website":"http://www.adamusrealtygroup.com",
    "wof:name":"Adamus Realty Group Inc",
    "wof:placetype":"venue"
},
  "geometry": {"coordinates":[-80.771463,28.373016],"type":"Point"}
}