{
  "type": "Feature",
  "properties": {
    "addr:full":"20271 Tappan Zee Dr Port Charlotte FL 33952",
    "addr:postcode":"20271;33952",
    "addr:street":"Zee Dr",
    "iso:country":"US",
    "sg:address":"20271 Tappan Zee Dr",
    "sg:city":"Port Charlotte",
    "sg:classifiers":[
        {
            "category":"Organizations",
            "subcategory":"Community Association",
            "type":"Services"
        }
    ],
    "sg:phone":"+1 941 766 8855",
    "sg:postcode":"33952",
    "sg:province":"FL",
    "sg:tags":[
        "club"
    ],
    "wof:name":"Women's Club Of Port Charlotte",
    "wof:placetype":"venue"
},
  "geometry": {"coordinates":[-82.119923,27.01599],"type":"Point"}
}