{
  "type": "Feature",
  "properties": {
    "addr:full":"4008 Midland Rd Sarasota FL 34231",
    "addr:housenumber":"4008",
    "addr:postcode":"34231",
    "addr:street":"Midland Rd",
    "iso:country":"US",
    "sg:address":"4008 Midland Rd",
    "sg:city":"Sarasota",
    "sg:classifiers":[
        {
            "category":"Building & Trades",
            "subcategory":"Construction",
            "type":"Services"
        }
    ],
    "sg:phone":"+1 941 923 7139",
    "sg:postcode":"34231",
    "sg:province":"FL",
    "sg:tags":[
        "roofing",
        "industrial",
        "contractors-commercial",
        "contractor"
    ],
    "wof:name":"Douglas Roofing",
    "wof:placetype":"venue"
},
  "geometry": {"coordinates":[-82.512108,27.29698],"type":"Point"}
}