{
  "type": "Feature",
  "properties": {
    "addr:full":"2301 S Division Ave Orlando FL 32805",
    "addr:housenumber":"2301",
    "addr:postcode":"32805",
    "addr:street":"S Division Ave",
    "iso:country":"US",
    "sg:address":"2301 S Division Ave",
    "sg:city":"Orlando",
    "sg:classifiers":[
        {
            "category":"Local Transit",
            "type":"Transportation"
        }
    ],
    "sg:phone":"+1 407 649 6599",
    "sg:postcode":"32805",
    "sg:province":"FL",
    "sg:tags":[
        "passenger"
    ],
    "wof:name":"Jet Set Line Inc",
    "wof:placetype":"venue"
},
  "geometry": {"coordinates":[-81.384647,28.515033],"type":"Point"}
}