{
  "type": "Feature",
  "properties": {
    "addr:full":"2683 E Silver Springs Blvd Ocala FL 34470",
    "addr:housenumber":"2683",
    "addr:postcode":"34470",
    "addr:street":"E Silver Springs Blvd",
    "iso:country":"US",
    "sg:address":"2683 E Silver Springs Blvd",
    "sg:city":"Ocala",
    "sg:classifiers":[
        {
            "category":"Restaurant",
            "type":"Food & Drink"
        }
    ],
    "sg:phone":"+1 352 622 3507",
    "sg:postcode":"34470",
    "sg:province":"FL",
    "sg:tags":[
        "sandwich",
        "eating"
    ],
    "wof:name":"T J's Sandwich Shop",
    "wof:placetype":"venue"
},
  "geometry": {"coordinates":[-82.101572,29.188057],"type":"Point"}
}