{
  "type": "Feature",
  "properties": {
    "addr:full":"101 Grand Palms Dr Hollywood FL 33027",
    "addr:housenumber":"101",
    "addr:postcode":"33027",
    "addr:street":"Grand Palms Dr",
    "iso:country":"US",
    "sg:address":"101 Grand Palms Dr",
    "sg:city":"Hollywood",
    "sg:classifiers":[
        {
            "category":"Professional",
            "subcategory":"Management & Consulting",
            "type":"Services"
        }
    ],
    "sg:phone":"+1 954 431 2835",
    "sg:postcode":"33027",
    "sg:province":"FL",
    "wof:name":"Miami Management",
    "wof:placetype":"venue"
},
  "geometry": {"coordinates":[-80.34578399999999,26.004816],"type":"Point"}
}