{
  "type": "Feature",
  "properties": {
    "iso:country":"US",
    "sg:address":"2632 Fountainview Cir",
    "sg:city":"Naples",
    "sg:classifiers":[
        {
            "category":"Professional",
            "subcategory":"Management & Consulting",
            "type":"Services"
        }
    ],
    "sg:phone":"+1 239 598 1011",
    "sg:postcode":"34109",
    "sg:province":"FL",
    "sg:tags":[
        "consultant",
        "educational"
    ],
    "wof:name":"Dynalogic Concepts",
    "wof:placetype":"venue"
},
  "geometry": {"coordinates":[-81.76552,26.224225],"type":"Point"}
}