{
  "type": "Feature",
  "properties": {
    "iso:country":"US",
    "sg:address":"4119 N Taliaferro Ave",
    "sg:city":"Tampa",
    "sg:classifiers":[
        {
            "category":"Health Services",
            "subcategory":"Doctor",
            "type":"Services"
        }
    ],
    "sg:phone":"+1 813 238 3384",
    "sg:postcode":"33603",
    "sg:province":"FL",
    "sg:tags":[
        "dentist"
    ],
    "wof:name":"Marsh Orthodontics",
    "wof:placetype":"venue"
},
  "geometry": {"coordinates":[-82.453131,27.98316],"type":"Point"}
}