{
  "type": "Feature",
  "properties": {
    "addr:full":"233 W Ave A Belle Glade FL 33430",
    "addr:housenumber":"233",
    "addr:postcode":"33430",
    "addr:street":"W Ave A Belle Glade",
    "iso:country":"US",
    "sg:address":"233 W Ave A",
    "sg:city":"Belle Glade",
    "sg:classifiers":[
        {
            "category":"Social Services",
            "type":"Services"
        }
    ],
    "sg:phone":"+1 561 996 6888",
    "sg:postcode":"33430",
    "sg:province":"FL",
    "sg:tags":[
        "pregnancy",
        "counseling",
        "information"
    ],
    "wof:name":"First Care Pregnancy Centers",
    "wof:placetype":"venue"
},
  "geometry": {"coordinates":[-80.670141,26.68568],"type":"Point"}
}