{
  "type": "Feature",
  "properties": {
    "addr:full":"4405 Summer Oak Dr Tampa FL 33618",
    "addr:housenumber":"4405",
    "addr:postcode":"33618",
    "addr:street":"Summer Oak Dr",
    "iso:country":"US",
    "sg:address":"4405 Summer Oak Dr",
    "sg:city":"Tampa",
    "sg:classifiers":[
        {
            "category":"Professional",
            "subcategory":"Advertising",
            "type":"Services"
        }
    ],
    "sg:phone":"+1 813 960 7452",
    "sg:postcode":"33618",
    "sg:province":"FL",
    "sg:tags":[
        "counselor"
    ],
    "wof:name":"Nan Nadler",
    "wof:placetype":"venue"
},
  "geometry": {"coordinates":[-82.51545900000001,28.047843],"type":"Point"}
}