{
  "type": "Feature",
  "properties": {
    "iso:country":"US",
    "sg:address":"13290 92nd St",
    "sg:city":"Largo",
    "sg:classifiers":[
        {
            "category":"Building & Trades",
            "subcategory":"Plumbing",
            "type":"Services"
        }
    ],
    "sg:phone":"+1 727 585 5626",
    "sg:postcode":"33773",
    "sg:province":"FL",
    "sg:tags":[
        "mechanical",
        "contractor"
    ],
    "wof:name":"Bay West Mechanical Inc",
    "wof:placetype":"venue"
},
  "geometry": {"coordinates":[-82.767504,27.892648],"type":"Point"}
}