{
  "type": "Feature",
  "properties": {
    "addr:full":"17826 Pine Needle Ter Boca Raton FL 33487",
    "addr:housenumber":"17826",
    "addr:postcode":"33487",
    "addr:street":"Pine Needle Ter",
    "iso:country":"US",
    "sg:address":"17826 Pine Needle Ter",
    "sg:city":"Boca Raton",
    "sg:classifiers":[
        {
            "category":"Building & Trades",
            "subcategory":"Landscaping Services",
            "type":"Services"
        }
    ],
    "sg:phone":"+1 561 733 4620",
    "sg:postcode":"33487",
    "sg:province":"FL",
    "sg:tags":[
        "landscape",
        "contractor"
    ],
    "wof:name":"Treasure Coast Landscape Svc",
    "wof:placetype":"venue"
},
  "geometry": {"coordinates":[-80.11644200000001,26.412396],"type":"Point"}
}