{
  "type": "Feature",
  "properties": {
    "iso:country":"US",
    "sg:address":"3000 SW 107th Ave",
    "sg:city":"Miami",
    "sg:classifiers":[
        {
            "category":"Organizations",
            "subcategory":"Religious Organization",
            "type":"Services"
        }
    ],
    "sg:phone":"+1 305 552 6109",
    "sg:postcode":"33165",
    "sg:province":"FL",
    "sg:website":"www.ag.org",
    "wof:name":"University Assembly of God",
    "wof:placetype":"venue"
},
  "geometry": {"coordinates":[-80.367897,25.7411],"type":"Point"}
}