{
  "type": "Feature",
  "properties": {
    "addr:full":"1160 S McCall Rd Englewood FL 34223",
    "addr:housenumber":"1160",
    "addr:postcode":"34223",
    "addr:street":"S Mccall Rd",
    "iso:country":"US",
    "sg:address":"1160 S McCall Rd",
    "sg:city":"Englewood",
    "sg:classifiers":[
        {
            "category":"Travel",
            "subcategory":"Travel Agent",
            "type":"Entertainment"
        }
    ],
    "sg:phone":"+1 941 474 0397",
    "sg:postcode":"34223",
    "sg:province":"FL",
    "sg:tags":[
        "agency",
        "bureau"
    ],
    "wof:name":"Ship 'N' Shore Cruise & Tours",
    "wof:placetype":"venue"
},
  "geometry": {"coordinates":[-82.350245,26.943293],"type":"Point"}
}