{
  "type": "Feature",
  "properties": {
    "addr:full":"10859 Emerald Coast Pkwy W Destin FL 32550",
    "addr:housenumber":"10859",
    "addr:postcode":"32550",
    "addr:street":"Emerald Coast Pkwy W",
    "iso:country":"US",
    "sg:address":"10859 Emerald Coast Pkwy W",
    "sg:city":"Destin",
    "sg:classifiers":[
        {
            "category":"Shopping",
            "subcategory":"Bicycles & Sporting Goods",
            "type":"Retail Goods"
        }
    ],
    "sg:phone":"+1 850 650 9696",
    "sg:postcode":"32550",
    "sg:province":"FL",
    "sg:tags":[
        "equipment",
        "tennis",
        "golf"
    ],
    "wof:name":"Destin Golf & Tennis Inc",
    "wof:placetype":"venue"
},
  "geometry": {"coordinates":[-86.353067,30.378675],"type":"Point"}
}