{
  "type": "Feature",
  "properties": {
    "iso:country":"US",
    "sg:address":"2845 NE 9th St",
    "sg:city":"Fort Lauderdale",
    "sg:classifiers":[
        {
            "category":"Real Estate",
            "subcategory":"Developer",
            "type":"Services"
        }
    ],
    "sg:phone":"+1 954 567 4575",
    "sg:postcode":"33304",
    "sg:province":"FL",
    "sg:tags":[
        "condominium"
    ],
    "wof:name":"Le Club International LLC",
    "wof:placetype":"venue"
},
  "geometry": {"coordinates":[-80.10675999999999,26.136515],"type":"Point"}
}