{
  "type": "Feature",
  "properties": {
    "iso:country":"US",
    "sg:address":"1949 NW 62nd St",
    "sg:city":"Miami",
    "sg:classifiers":[
        {
            "category":"Food & Beverages",
            "subcategory":"Groceries & Convenience Stores",
            "type":"Retail Goods"
        }
    ],
    "sg:phone":"+1 305 691 5833",
    "sg:postcode":"33147",
    "sg:province":"FL",
    "sg:tags":[
        "grocer"
    ],
    "wof:name":"Jugglers Market",
    "wof:placetype":"venue"
},
  "geometry": {"coordinates":[-80.22959899999999,25.831499],"type":"Point"}
}