{
  "type": "Feature",
  "properties": {
    "iso:country":"US",
    "sg:address":"17514 Boy Scout Rd",
    "sg:city":"Odessa",
    "sg:classifiers":[
        {
            "category":"Banks & Credit Unions",
            "subcategory":"Financial Services",
            "type":"Services"
        }
    ],
    "sg:phone":"+1 813 920 7221",
    "sg:postcode":"33556",
    "sg:province":"FL",
    "sg:tags":[
        "investor"
    ],
    "wof:name":"Krillz Industries & Investment",
    "wof:placetype":"venue"
},
  "geometry": {"coordinates":[-82.622783,28.131716],"type":"Point"}
}