{
  "type": "Feature",
  "properties": {
    "addr:full":"4187 34th St Orlando FL 32811",
    "addr:housenumber":"4187",
    "addr:postcode":"32811",
    "addr:street":"34Th St",
    "iso:country":"US",
    "sg:address":"4187 34th St",
    "sg:city":"Orlando",
    "sg:classifiers":[
        {
            "category":"Home & Garden",
            "subcategory":"Carpets & Floor Coverings",
            "type":"Retail Goods"
        }
    ],
    "sg:phone":"+1 407 948 5372",
    "sg:postcode":"32811",
    "sg:province":"FL",
    "wof:name":"C-Side Carpets & Interiors",
    "wof:placetype":"venue"
},
  "geometry": {"coordinates":[-81.428246,28.504974],"type":"Point"}
}