{
  "type": "Feature",
  "properties": {
    "iso:country":"US",
    "sg:address":"8729 SW 24th St",
    "sg:city":"Miami",
    "sg:classifiers":[
        {
            "category":"Personal",
            "subcategory":"Beauty Salon",
            "type":"Services"
        }
    ],
    "sg:phone":"+1 305 480 1008",
    "sg:postcode":"33165",
    "sg:province":"FL",
    "sg:tags":[
        "hair"
    ],
    "wof:name":"Studio 2000 Hair Designers",
    "wof:placetype":"venue"
},
  "geometry": {"coordinates":[-80.336304,25.747601],"type":"Point"}
}