{
  "type": "Feature",
  "properties": {
    "addr:full":"11018 US Hwy 92 Seffner FL 33584",
    "addr:housenumber":"11018",
    "addr:postcode":"33584",
    "addr:street":"Us Hwy 92",
    "iso:country":"US",
    "sg:address":"11018 US Hwy 92",
    "sg:city":"Seffner",
    "sg:classifiers":[
        {
            "category":"Professional",
            "type":"Services"
        }
    ],
    "sg:phone":"+1 813 630 5073",
    "sg:postcode":"33584",
    "sg:province":"FL",
    "wof:name":"2x Tail Inc",
    "wof:placetype":"venue"
},
  "geometry": {"coordinates":[-82.31501900000001,27.999407],"type":"Point"}
}