{
  "type": "Feature",
  "properties": {
    "addr:full":"2130 Pine Forest Dr Clearwater FL 33764",
    "addr:housenumber":"2130",
    "addr:postcode":"33764",
    "addr:street":"Pine Forest Dr",
    "iso:country":"US",
    "sg:address":"2130 Pine Forest Dr",
    "sg:city":"Clearwater",
    "sg:classifiers":[
        {
            "category":"Retail",
            "subcategory":"Auto Repair",
            "type":"Services"
        }
    ],
    "sg:phone":"+1 727 530 1638",
    "sg:postcode":"33764",
    "sg:province":"FL",
    "sg:tags":[
        "body",
        "automobile",
        "painting"
    ],
    "sg:website":"www.jamesab.com",
    "wof:name":"James Auto Body",
    "wof:placetype":"venue"
},
  "geometry": {"coordinates":[-82.736085,27.918997],"type":"Point"}
}