{
  "type": "Feature",
  "properties": {
    "addr:full":"18650 US Hwy 441 Mount Dora FL 32757",
    "addr:housenumber":"18650",
    "addr:postcode":"32757",
    "addr:street":"Us Hwy 441",
    "iso:country":"US",
    "sg:address":"18650 US Hwy 441",
    "sg:city":"Mount Dora",
    "sg:classifiers":[
        {
            "category":"Building & Trades",
            "subcategory":"Construction",
            "type":"Services"
        }
    ],
    "sg:phone":"+1 352 735 7770",
    "sg:postcode":"32757",
    "sg:province":"FL",
    "sg:tags":[
        "house"
    ],
    "wof:name":"New Homes Neighborhoods Inc",
    "wof:placetype":"venue"
},
  "geometry": {"coordinates":[-81.647811,28.823866],"type":"Point"}
}