{
  "type": "Feature",
  "properties": {
    "iso:country":"US",
    "sg:address":"711 7th Ter",
    "sg:city":"Palm Beach Gdns",
    "sg:classifiers":[
        {
            "category":"Travel",
            "subcategory":"Travel Agent",
            "type":"Entertainment"
        }
    ],
    "sg:phone":"+1 561 253 8008",
    "sg:postcode":"33418",
    "sg:province":"FL",
    "sg:tags":[
        "agency",
        "bureau"
    ],
    "wof:name":"Global Travel Inc",
    "wof:placetype":"venue"
},
  "geometry": {"coordinates":[-80.131486,26.833278],"type":"Point"}
}