{
  "type": "Feature",
  "properties": {
    "iso:country":"US",
    "sg:address":"31716 Merry Rd",
    "sg:city":"Tavares",
    "sg:classifiers":[
        {
            "category":"Building & Trades",
            "subcategory":"Landscaping Services",
            "type":"Services"
        }
    ],
    "sg:phone":"+1 352 343 6717",
    "sg:postcode":"32778",
    "sg:province":"FL",
    "sg:tags":[
        "tree"
    ],
    "wof:name":"Curry's Tree Svc",
    "wof:placetype":"venue"
},
  "geometry": {"coordinates":[-81.704975,28.810899],"type":"Point"}
}