{
  "type": "Feature",
  "properties": {
    "addr:full":"3729 Hileman Dr N Lakeland FL 33810",
    "addr:housenumber":"3729",
    "addr:postcode":"33810",
    "addr:street":"Hileman Dr N",
    "iso:country":"US",
    "sg:address":"3729 Hileman Dr N",
    "sg:city":"Lakeland",
    "sg:classifiers":[
        {
            "category":"Building & Trades",
            "subcategory":"Landscaping Services",
            "type":"Services"
        }
    ],
    "sg:phone":"+1 863 859 7272",
    "sg:postcode":"33810",
    "sg:province":"FL",
    "wof:name":"Nats Lawn Service",
    "wof:placetype":"venue"
},
  "geometry": {"coordinates":[-82.021113,28.1343],"type":"Point"}
}