{
  "type": "Feature",
  "properties": {
    "iso:country":"US",
    "sg:address":"4 N Navy Blvd",
    "sg:city":"Pensacola",
    "sg:classifiers":[
        {
            "category":"Professional",
            "subcategory":"Business Services",
            "type":"Services"
        }
    ],
    "sg:phone":"+1 850 457 1270",
    "sg:postcode":"32507",
    "sg:province":"FL",
    "sg:tags":[
        "inventory"
    ],
    "wof:name":"Inventory Liquidators",
    "wof:placetype":"venue"
},
  "geometry": {"coordinates":[-87.278176,30.388678],"type":"Point"}
}