{
  "type": "Feature",
  "properties": {
    "addr:full":"8975 130th Ave Largo FL 33773",
    "addr:housenumber":"8975",
    "addr:postcode":"33773",
    "addr:street":"130Th Ave",
    "iso:country":"US",
    "sg:address":"8975 130th Ave",
    "sg:city":"Largo",
    "sg:classifiers":[
        {
            "category":"Building & Trades",
            "subcategory":"Construction",
            "type":"Services"
        }
    ],
    "sg:phone":"+1 727 584 3179",
    "sg:postcode":"33773",
    "sg:province":"FL",
    "sg:tags":[
        "tile",
        "contractor"
    ],
    "wof:name":"J & A Tile",
    "wof:placetype":"venue"
},
  "geometry": {"coordinates":[-82.763925,27.890891],"type":"Point"}
}