{
  "type": "Feature",
  "properties": {
    "iso:country":"US",
    "sg:address":"1474 Poteete Rd",
    "sg:city":"Middleburg",
    "sg:classifiers":[
        {
            "category":"Building & Trades",
            "subcategory":"Equipment Rental",
            "type":"Services"
        }
    ],
    "sg:phone":"+1 904 282 1271",
    "sg:postcode":"32068",
    "sg:province":"FL",
    "wof:name":"Lucky Star Promotions & Lsg",
    "wof:placetype":"venue"
},
  "geometry": {"coordinates":[-81.95329099999999,30.117298],"type":"Point"}
}