{
  "type": "Feature",
  "properties": {
    "addr:full":"7130 Granada Blvd Hollywood FL 33023",
    "addr:housenumber":"7130",
    "addr:postcode":"33023",
    "addr:street":"Granada Blvd",
    "iso:country":"US",
    "sg:address":"7130 Granada Blvd",
    "sg:city":"Hollywood",
    "sg:classifiers":[
        {
            "category":"Organizations",
            "subcategory":"Religious Organization",
            "type":"Services"
        }
    ],
    "sg:phone":"+1 954 962 2503",
    "sg:postcode":"33023",
    "sg:province":"FL",
    "wof:name":"Christ From Cradle Ministry",
    "wof:placetype":"venue"
},
  "geometry": {"coordinates":[-80.23144000000001,25.981018],"type":"Point"}
}