{
  "type": "Feature",
  "properties": {
    "iso:country":"US",
    "sg:address":"700 NW 57th St",
    "sg:city":"Fort Lauderdale",
    "sg:classifiers":[
        {
            "category":"Building & Trades",
            "subcategory":"Construction",
            "type":"Services"
        }
    ],
    "sg:phone":"+1 954 771 0100",
    "sg:postcode":"33309",
    "sg:province":"FL",
    "sg:tags":[
        "glass",
        "glazing",
        "contractor"
    ],
    "wof:name":"Esser Glass Mirror & Plastics",
    "wof:placetype":"venue"
},
  "geometry": {"coordinates":[-80.154194,26.197262],"type":"Point"}
}