{
  "type": "Feature",
  "properties": {
    "addr:full":"324 NE 2nd Ave Hallandale FL 33009",
    "addr:housenumber":"324",
    "addr:postcode":"33009",
    "addr:street":"Ne 2Nd Ave",
    "iso:country":"US",
    "sg:address":"324 NE 2nd Ave",
    "sg:city":"Hallandale",
    "sg:classifiers":[
        {
            "category":"Real Estate",
            "subcategory":"Real Estate Agent",
            "type":"Services"
        }
    ],
    "sg:phone":"+1 954 455 0058",
    "sg:postcode":"33009",
    "sg:province":"FL",
    "wof:name":"Real Estate Appraisal Services",
    "wof:placetype":"venue"
},
  "geometry": {"coordinates":[-80.14710100000001,25.989433],"type":"Point"}
}