{
  "type": "Feature",
  "properties": {
    "addr:full":"1089 Creekford Dr Fort Lauderdale FL 33326",
    "addr:housenumber":"1089",
    "addr:postcode":"33326",
    "addr:street":"Creekford Dr",
    "iso:country":"US",
    "sg:address":"1089 Creekford Dr",
    "sg:city":"Fort Lauderdale",
    "sg:classifiers":[
        {
            "category":"Restaurant",
            "type":"Food & Drink"
        }
    ],
    "sg:phone":"+1 954 389 8722",
    "sg:postcode":"33326",
    "sg:province":"FL",
    "sg:tags":[
        "eating"
    ],
    "wof:name":"Old Boston Seafood/Lobster",
    "wof:placetype":"venue"
},
  "geometry": {"coordinates":[-80.365065,26.108794],"type":"Point"}
}