{
  "type": "Feature",
  "properties": {
    "addr:full":"3863 Prospect Ave Naples FL 34104",
    "addr:housenumber":"3863",
    "addr:postcode":"34104",
    "addr:street":"Prospect Ave",
    "iso:country":"US",
    "sg:address":"3863 Prospect Ave",
    "sg:city":"Naples",
    "sg:classifiers":[
        {
            "category":"Retail",
            "subcategory":"Auto Repair",
            "type":"Services"
        }
    ],
    "sg:phone":"+1 239 643 5735",
    "sg:postcode":"34104",
    "sg:province":"FL",
    "sg:tags":[
        "body",
        "welding"
    ],
    "wof:name":"Dorias Interprice",
    "wof:placetype":"venue"
},
  "geometry": {"coordinates":[-81.764866,26.156958],"type":"Point"}
}