{
  "type": "Feature",
  "properties": {
    "addr:full":"13446 Neville Dr Brooksville FL 34609",
    "addr:housenumber":"13446",
    "addr:postcode":"34609",
    "addr:street":"Neville Dr",
    "iso:country":"US",
    "sg:address":"13446 Neville Dr",
    "sg:city":"Brooksville",
    "sg:classifiers":[
        {
            "category":"Building & Trades",
            "subcategory":"Pest Control",
            "type":"Services"
        }
    ],
    "sg:phone":"+1 352 596 1860",
    "sg:postcode":"34609",
    "sg:province":"FL",
    "wof:name":"Garrison Pest Control",
    "wof:placetype":"venue"
},
  "geometry": {"coordinates":[-82.496419,28.531764],"type":"Point"}
}