{
  "type": "Feature",
  "properties": {
    "iso:country":"US",
    "sg:address":"725 SW 16th Ave",
    "sg:city":"Delray Beach",
    "sg:classifiers":[
        {
            "category":"Building & Trades",
            "subcategory":"Construction",
            "type":"Services"
        }
    ],
    "sg:phone":"+1 561 279 2484",
    "sg:postcode":"33444",
    "sg:province":"FL",
    "sg:tags":[
        "roofing",
        "contractor"
    ],
    "wof:name":"Tectonic Systems Inc",
    "wof:placetype":"venue"
},
  "geometry": {"coordinates":[-80.088718,26.447189],"type":"Point"}
}