{
  "type": "Feature",
  "properties": {
    "addr:full":"3427 Hiatus Rd Sunrise FL 33351",
    "addr:housenumber":"3427",
    "addr:postcode":"33351",
    "addr:street":"Hiatus Rd",
    "iso:country":"US",
    "sg:address":"3427 Hiatus Rd",
    "sg:city":"Sunrise",
    "sg:classifiers":[
        {
            "category":"Retail",
            "subcategory":"Laundry & Dry Cleaning",
            "type":"Services"
        }
    ],
    "sg:phone":"+1 954 578 1923",
    "sg:postcode":"33351",
    "sg:province":"FL",
    "sg:tags":[
        "cleaners"
    ],
    "wof:name":"Asia Dry Cleaners",
    "wof:placetype":"venue"
},
  "geometry": {"coordinates":[-80.29632599999999,26.168513],"type":"Point"}
}