{
  "type": "Feature",
  "properties": {
    "addr:full":"113 Overoaks Pl Sanford FL 32771",
    "addr:housenumber":"113",
    "addr:postcode":"32771",
    "addr:street":"Overoaks Pl",
    "iso:country":"US",
    "sg:address":"113 Overoaks Pl",
    "sg:city":"Sanford",
    "sg:classifiers":[
        {
            "category":"Building & Trades",
            "subcategory":"Construction",
            "type":"Services"
        }
    ],
    "sg:phone":"+1 407 328 4171",
    "sg:postcode":"32771",
    "sg:province":"FL",
    "sg:tags":[
        "home",
        "builder"
    ],
    "wof:name":"Waterford Quality Homes",
    "wof:placetype":"venue"
},
  "geometry": {"coordinates":[-81.36093200000001,28.813961],"type":"Point"}
}