{
  "type": "Feature",
  "properties": {
    "iso:country":"US",
    "sg:address":"2430 N Dixie Hwy",
    "sg:city":"Fort Lauderdale",
    "sg:classifiers":[
        {
            "category":"Autos & Motor Vehicles",
            "subcategory":"Automobile Sales",
            "type":"Retail Goods"
        }
    ],
    "sg:phone":"+1 954 568 3717",
    "sg:postcode":"33305",
    "sg:province":"FL",
    "sg:tags":[
        "used"
    ],
    "wof:name":"Consumer Autos Inc",
    "wof:placetype":"venue"
},
  "geometry": {"coordinates":[-80.13195899999999,26.15801],"type":"Point"}
}