{
  "type": "Feature",
  "properties": {
    "iso:country":"US",
    "sg:address":"2670 W 84th St",
    "sg:city":"Hialeah",
    "sg:classifiers":[
        {
            "category":"Shopping",
            "subcategory":"Optical Goods",
            "type":"Retail Goods"
        }
    ],
    "sg:phone":"+1 305 825 2565",
    "sg:postcode":"33016",
    "sg:province":"FL",
    "sg:tags":[
        "sun",
        "goggles",
        "sunglasses"
    ],
    "wof:name":"Miami Zol Corp",
    "wof:placetype":"venue"
},
  "geometry": {"coordinates":[-80.33730199999999,25.897459],"type":"Point"}
}