{
  "type": "Feature",
  "properties": {
    "iso:country":"US",
    "sg:address":"2007 Wood Ct",
    "sg:city":"Plant City",
    "sg:classifiers":[
        {
            "category":"Building & Trades",
            "subcategory":"Cleaning & Sanitation",
            "type":"Services"
        }
    ],
    "sg:phone":"+1 813 659 9076",
    "sg:postcode":"33563",
    "sg:province":"FL",
    "sg:tags":[
        "maintenance"
    ],
    "wof:name":"Kone Crane Maintenance Svcs",
    "wof:placetype":"venue"
},
  "geometry": {"coordinates":[-82.14247400000001,28.006231],"type":"Point"}
}