{
  "type": "Feature",
  "properties": {
    "iso:country":"US",
    "sg:address":"6105 Raleigh St",
    "sg:city":"Orlando",
    "sg:classifiers":[
        {
            "category":"Communications",
            "subcategory":"Film & Video Production",
            "type":"Services"
        }
    ],
    "sg:phone":"+1 407 294 5242",
    "sg:postcode":"32835",
    "sg:province":"FL",
    "sg:tags":[
        "motion"
    ],
    "wof:name":"Papacy Productions Inc",
    "wof:placetype":"venue"
},
  "geometry": {"coordinates":[-81.465008,28.528002],"type":"Point"}
}