{
  "type": "Feature",
  "properties": {
    "addr:full":"9901 SW 40th St Miami FL 33165",
    "addr:housenumber":"9901",
    "addr:postcode":"33165",
    "addr:street":"Sw 40Th St",
    "iso:country":"US",
    "sg:address":"9901 SW 40th St",
    "sg:city":"Miami",
    "sg:classifiers":[
        {
            "category":"Autos & Motor Vehicles",
            "subcategory":"Fuel & Gas Station",
            "type":"Retail Goods"
        }
    ],
    "sg:phone":"+1 305 223 9561",
    "sg:postcode":"33165",
    "sg:province":"FL",
    "sg:tags":[
        "oil"
    ],
    "wof:name":"Pascual Amoco",
    "wof:placetype":"venue"
},
  "geometry": {"coordinates":[-80.35674299999999,25.732588],"type":"Point"}
}