{
  "type": "Feature",
  "properties": {
    "addr:full":"2260 W Co Hwy 30A Santa Rosa Beach FL 32459",
    "addr:housenumber":"2260",
    "addr:postcode":"32459",
    "addr:street":"W Co Hwy 30A;Rosa",
    "iso:country":"US",
    "sg:address":"2260 W Co Hwy 30A",
    "sg:city":"Santa Rosa Beach",
    "sg:classifiers":[
        {
            "category":"Restaurant",
            "type":"Food & Drink"
        }
    ],
    "sg:phone":"+1 850 622 1909",
    "sg:postcode":"32459",
    "sg:province":"FL",
    "wof:name":"Beach Bistro",
    "wof:placetype":"venue"
},
  "geometry": {"coordinates":[-86.20467600000001,30.340707],"type":"Point"}
}