{
  "type": "Feature",
  "properties": {
    "iso:country":"US",
    "sg:address":"6838 NW 77th Ct",
    "sg:city":"Miami",
    "sg:classifiers":[
        {
            "category":"Wholesale",
            "subcategory":"Office Equipment",
            "type":"Manufacturing & Wholesale Goods"
        }
    ],
    "sg:phone":"+1 305 471 9725",
    "sg:postcode":"33166",
    "sg:province":"FL",
    "sg:tags":[
        "machine",
        "duplicating",
        "copying"
    ],
    "wof:name":"Kendall Copiers Inc",
    "wof:placetype":"venue"
},
  "geometry": {"coordinates":[-80.322391,25.835704],"type":"Point"}
}