{
  "type": "Feature",
  "properties": {
    "iso:country":"US",
    "sg:address":"2401 The Oaks Blvd",
    "sg:city":"Kissimmee",
    "sg:classifiers":[
        {
            "category":"Professional",
            "subcategory":"Management & Consulting",
            "type":"Services"
        }
    ],
    "sg:phone":"+1 407 931 3443",
    "sg:postcode":"34746",
    "sg:province":"FL",
    "sg:tags":[
        "marketing",
        "consultant"
    ],
    "sg:website":"www.infrasignal.com",
    "wof:name":"INFRASIGNAL.COM",
    "wof:placetype":"venue"
},
  "geometry": {"coordinates":[-81.422872,28.25864],"type":"Point"}
}