{
  "type": "Feature",
  "properties": {
    "iso:country":"US",
    "sg:address":"12474 Sawgrass Ct",
    "sg:city":"Wellington",
    "sg:classifiers":[
        {
            "category":"Professional",
            "subcategory":"Computer Services",
            "type":"Services"
        }
    ],
    "sg:phone":"+1 561 333 3091",
    "sg:postcode":"33414",
    "sg:province":"FL",
    "sg:tags":[
        "consultant",
        "designer",
        "datum",
        "system"
    ],
    "wof:name":"Tsl Solutions",
    "wof:placetype":"venue"
},
  "geometry": {"coordinates":[-80.24038,26.672389],"type":"Point"}
}