{
  "type": "Feature",
  "properties": {
    "iso:country":"US",
    "sg:address":"2870 NW 72nd Ave",
    "sg:city":"Miami",
    "sg:classifiers":[
        {
            "category":"Wholesale",
            "subcategory":"Durable Goods & Equipment",
            "type":"Manufacturing & Wholesale Goods"
        }
    ],
    "sg:phone":"+1 305 468 9667",
    "sg:postcode":"33122",
    "sg:province":"FL",
    "sg:tags":[
        "exporter"
    ],
    "wof:name":"International Ribbon Ctr Inc",
    "wof:placetype":"venue"
},
  "geometry": {"coordinates":[-80.31311700000001,25.801184],"type":"Point"}
}