{
  "type": "Feature",
  "properties": {
    "addr:full":"5773 Starcher Ave Fort Pierce FL 34947",
    "addr:housenumber":"5773",
    "addr:postcode":"34947",
    "addr:street":"Starcher Ave",
    "iso:country":"US",
    "sg:address":"5773 Starcher Ave",
    "sg:city":"Fort Pierce",
    "sg:classifiers":[
        {
            "category":"Building & Trades",
            "subcategory":"Cleaning & Sanitation",
            "type":"Services"
        }
    ],
    "sg:phone":"+1 772 489 0762",
    "sg:postcode":"34947",
    "sg:province":"FL",
    "sg:tags":[
        "maintenance"
    ],
    "wof:name":"All American Maid Cleaning Svc",
    "wof:placetype":"venue"
},
  "geometry": {"coordinates":[-80.383377,27.443245],"type":"Point"}
}