{
  "type": "Feature",
  "properties": {
    "iso:country":"US",
    "sg:address":"1380 24th Ave NE",
    "sg:city":"Naples",
    "sg:classifiers":[
        {
            "category":"Food & Beverages",
            "subcategory":"Groceries & Convenience Stores",
            "type":"Retail Goods"
        }
    ],
    "sg:phone":"+1 239 254 7887",
    "sg:postcode":"34120",
    "sg:province":"FL",
    "wof:name":"Toku Food Group Inc",
    "wof:placetype":"venue"
},
  "geometry": {"coordinates":[-81.590582,26.273687],"type":"Point"}
}