{
  "type": "Feature",
  "properties": {
    "addr:full":"2960 Orange Grove Trl Naples FL 34120",
    "addr:housenumber":"2960",
    "addr:postcode":"34120",
    "addr:street":"Orange Grove Trl",
    "iso:country":"US",
    "sg:address":"2960 Orange Grove Trl",
    "sg:city":"Naples",
    "sg:classifiers":[
        {
            "category":"Building & Trades",
            "subcategory":"Electrical",
            "type":"Services"
        }
    ],
    "sg:phone":"+1 239 353 7016",
    "sg:postcode":"34120",
    "sg:province":"FL",
    "sg:tags":[
        "electrical",
        "contractor"
    ],
    "wof:name":"Jwl Electric Inc",
    "wof:placetype":"venue"
},
  "geometry": {"coordinates":[-81.592738,26.284641],"type":"Point"}
}