{
  "type": "Feature",
  "properties": {
    "iso:country":"US",
    "sg:address":"7535 Foxbloom Dr",
    "sg:city":"Port Richey",
    "sg:classifiers":[
        {
            "category":"Building & Trades",
            "subcategory":"Landscaping Services",
            "type":"Services"
        }
    ],
    "sg:phone":"+1 727 869 1904",
    "sg:postcode":"34668",
    "sg:province":"FL",
    "sg:tags":[
        "landscape"
    ],
    "wof:name":"Jonathan Allen Lawn Boyz Svc",
    "wof:placetype":"venue"
},
  "geometry": {"coordinates":[-82.68954600000001,28.321387],"type":"Point"}
}