{
  "type": "Feature",
  "properties": {
    "iso:country":"US",
    "sg:address":"1130 83rd Ave N",
    "sg:city":"St Petersburg",
    "sg:classifiers":[
        {
            "category":"Real Estate",
            "subcategory":"Real Estate Operator",
            "type":"Services"
        }
    ],
    "sg:phone":"+1 727 577 2235",
    "sg:postcode":"33702",
    "sg:province":"FL",
    "sg:tags":[
        "condominium"
    ],
    "wof:name":"Williamsburg Condominiums",
    "wof:placetype":"venue"
},
  "geometry": {"coordinates":[-82.649596,27.847436],"type":"Point"}
}