{
  "type": "Feature",
  "properties": {
    "iso:country":"US",
    "sg:address":"1820 N Corporate Lakes Blvd",
    "sg:city":"Weston",
    "sg:classifiers":[
        {
            "category":"Professional",
            "subcategory":"Lawyer & Legal Services",
            "type":"Services"
        }
    ],
    "sg:phone":"+1 954 217 9398",
    "sg:postcode":"33326",
    "sg:province":"FL",
    "sg:tags":[
        "attorney"
    ],
    "wof:name":"Don Gonzales Esq Attorney",
    "wof:placetype":"venue"
},
  "geometry": {"coordinates":[-80.365763,26.095183],"type":"Point"}
}