{
  "type": "Feature",
  "properties": {
    "addr:full":"210 Hummingbird Ln Longwood FL 32779",
    "addr:housenumber":"210",
    "addr:postcode":"32779",
    "addr:street":"Hummingbird Ln",
    "iso:country":"US",
    "sg:address":"210 Hummingbird Ln",
    "sg:city":"Longwood",
    "sg:classifiers":[
        {
            "category":"Banks & Credit Unions",
            "subcategory":"Bank",
            "type":"Services"
        }
    ],
    "sg:phone":"+1 407 774 8569",
    "sg:postcode":"32779",
    "sg:province":"FL",
    "sg:tags":[
        "loan",
        "broker"
    ],
    "wof:name":"Silver & Associates Inc",
    "wof:placetype":"venue"
},
  "geometry": {"coordinates":[-81.39860299999999,28.692695],"type":"Point"}
}