{
  "type": "Feature",
  "properties": {
    "addr:full":"845 W Swoope Ave Winter Park FL 32789",
    "addr:housenumber":"845",
    "addr:postcode":"32789",
    "addr:street":"W Swoope Ave",
    "iso:country":"US",
    "sg:address":"845 W Swoope Ave",
    "sg:city":"Winter Park",
    "sg:classifiers":[
        {
            "category":"Real Estate",
            "subcategory":"Real Estate Operator",
            "type":"Services"
        }
    ],
    "sg:phone":"+1 407 645 2529",
    "sg:postcode":"32789",
    "sg:province":"FL",
    "sg:tags":[
        "apartment"
    ],
    "wof:name":"Tranquil Terrace Apartments",
    "wof:placetype":"venue"
},
  "geometry": {"coordinates":[-81.35916400000001,28.601984],"type":"Point"}
}