{
  "type": "Feature",
  "properties": {
    "addr:full":"4300 Royal Wood Blvd Naples FL 34112",
    "addr:housenumber":"4300",
    "addr:postcode":"34112",
    "addr:street":"Royal Wood Blvd",
    "iso:country":"US",
    "sg:address":"4300 Royal Wood Blvd",
    "sg:city":"Naples",
    "sg:classifiers":[
        {
            "category":"Recreation",
            "type":"Entertainment"
        }
    ],
    "sg:phone":"+1 239 774 2213",
    "sg:postcode":"34112",
    "sg:province":"FL",
    "sg:tags":[
        "club",
        "course",
        "membership",
        "golf"
    ],
    "wof:name":"Royal Wood Master Association",
    "wof:placetype":"venue"
},
  "geometry": {"coordinates":[-81.719579,26.111738],"type":"Point"}
}