{
  "type": "Feature",
  "properties": {
    "iso:country":"US",
    "sg:address":"4480 Melany Ln",
    "sg:city":"Lake Worth",
    "sg:classifiers":[
        {
            "category":"Building & Trades",
            "subcategory":"Construction",
            "type":"Services"
        }
    ],
    "sg:phone":"+1 561 433 1173",
    "sg:postcode":"33461",
    "sg:province":"FL",
    "sg:tags":[
        "contractor"
    ],
    "wof:name":"Alfaro Plastering Inc",
    "wof:placetype":"venue"
},
  "geometry": {"coordinates":[-80.109786,26.611944],"type":"Point"}
}