{
  "type": "Feature",
  "properties": {
    "iso:country":"US",
    "sg:address":"206 Moody Blvd",
    "sg:city":"Flagler Beach",
    "sg:classifiers":[
        {
            "category":"Real Estate",
            "subcategory":"Architect",
            "type":"Services"
        }
    ],
    "sg:phone":"+1 386 439 5650",
    "sg:postcode":"32136",
    "sg:province":"FL",
    "wof:name":"Joseph Pozzuoli Architects",
    "wof:placetype":"venue"
},
  "geometry": {"coordinates":[-81.127572,29.480954],"type":"Point"}
}