{
  "type": "Feature",
  "properties": {
    "iso:country":"US",
    "sg:address":"727 7th Ln",
    "sg:city":"Palm Beach Gdns",
    "sg:classifiers":[
        {
            "category":"Building & Trades",
            "subcategory":"Plumbing",
            "type":"Services"
        }
    ],
    "sg:phone":"+1 561 746 6798",
    "sg:postcode":"33418",
    "sg:province":"FL",
    "sg:tags":[
        "leak",
        "detecting"
    ],
    "wof:name":"Leak Control",
    "wof:placetype":"venue"
},
  "geometry": {"coordinates":[-80.10798800000001,26.844177],"type":"Point"}
}