{
  "type": "Feature",
  "properties": {
    "iso:country":"US",
    "sg:address":"2080 NE 2nd St",
    "sg:city":"Deerfield Beach",
    "sg:classifiers":[
        {
            "category":"Shopping",
            "subcategory":"Discount & Variety Stores",
            "type":"Retail Goods"
        }
    ],
    "sg:phone":"+1 954 421 7870",
    "sg:postcode":"33441",
    "sg:province":"FL",
    "sg:tags":[
        "specializing",
        "beach",
        "supply"
    ],
    "wof:name":"Beachcomber",
    "wof:placetype":"venue"
},
  "geometry": {"coordinates":[-80.076943,26.316346],"type":"Point"}
}