{
  "type": "Feature",
  "properties": {
    "iso:country":"US",
    "sg:address":"701 S Howard Ave",
    "sg:city":"Tampa",
    "sg:classifiers":[
        {
            "category":"Shopping",
            "subcategory":"Bicycles & Sporting Goods",
            "type":"Retail Goods"
        }
    ],
    "sg:phone":"+1 813 254 8444",
    "sg:postcode":"33606",
    "sg:province":"FL",
    "sg:tags":[
        "tackle",
        "fishing"
    ],
    "wof:name":"Tampa Bay Outfitters LLC",
    "wof:placetype":"venue"
},
  "geometry": {"coordinates":[-82.483037,27.936031],"type":"Point"}
}