{
  "type": "Feature",
  "properties": {
    "iso:country":"US",
    "sg:address":"9100 W State Road 84",
    "sg:city":"Fort Lauderdale",
    "sg:classifiers":[
        {
            "category":"Cafe",
            "type":"Food & Drink"
        },
        {
            "category":"Bars & Pubs",
            "subcategory":"Wine Bar",
            "type":"Food & Drink"
        }
    ],
    "sg:menulink":"http://www.allmenus.com/fl/davie/16085-vienna-cafe--wine-bar/menu/",
    "sg:phone":"+1 954 423 1961",
    "sg:postcode":"33324",
    "sg:province":"FL",
    "sg:tags":[
        "wrap",
        "american",
        "sandwich"
    ],
    "wof:name":"Vienna Cafe & Wine Bar",
    "wof:placetype":"venue"
},
  "geometry": {"coordinates":[-80.27369,26.1044],"type":"Point"}
}