{
  "type": "Feature",
  "properties": {
    "iso:country":"US",
    "sg:address":"1204 N Woodland Blvd",
    "sg:city":"De Land",
    "sg:classifiers":[
        {
            "category":"Building & Trades",
            "subcategory":"Equipment Rental",
            "type":"Services"
        }
    ],
    "sg:phone":"+1 386 736 2222",
    "sg:postcode":"32720",
    "sg:province":"FL",
    "sg:tags":[
        "personal"
    ],
    "wof:name":"Dan Rents Tents",
    "wof:placetype":"venue"
},
  "geometry": {"coordinates":[-81.30418299999999,29.048377],"type":"Point"}
}