{
  "type": "Feature",
  "properties": {
    "addr:full":"11222 Quail Roost Dr Miami FL 33157",
    "addr:housenumber":"11222",
    "addr:postcode":"33157",
    "addr:street":"Quail Roost Dr",
    "iso:country":"US",
    "sg:address":"11222 Quail Roost Dr",
    "sg:city":"Miami",
    "sg:classifiers":[
        {
            "category":"Insurance",
            "subcategory":"Hazard Insurance",
            "type":"Services"
        },
        {
            "category":"Insurance",
            "subcategory":"Life Insurance",
            "type":"Services"
        },
        {
            "category":"Insurance",
            "subcategory":"Title Insurance",
            "type":"Services"
        },
        {
            "category":"Insurance",
            "subcategory":"Health Insurance",
            "type":"Services"
        }
    ],
    "sg:phone":"+1 305 253 2244",
    "sg:postcode":"33157",
    "sg:province":"FL",
    "sg:tags":[
        "group",
        "homeowner"
    ],
    "wof:name":"American Bankers Insurance Group, Inc.",
    "wof:placetype":"venue"
},
  "geometry": {"coordinates":[-80.37600999999999,25.594604],"type":"Point"}
}