{
  "type": "Feature",
  "properties": {
    "iso:country":"US",
    "sg:address":"6401 SW 87th Ave",
    "sg:city":"Miami",
    "sg:classifiers":[
        {
            "category":"Professional",
            "subcategory":"Accounting & Tax Preparation",
            "type":"Services"
        }
    ],
    "sg:phone":"+1 305 598 8456",
    "sg:postcode":"33173",
    "sg:province":"FL",
    "sg:tags":[
        "accountant"
    ],
    "wof:name":"Howard K Bott CPA",
    "wof:placetype":"venue"
},
  "geometry": {"coordinates":[-80.334384,25.7068],"type":"Point"}
}