{
  "type": "Feature",
  "properties": {
    "iso:country":"US",
    "sg:address":"119 W Sturtevant St",
    "sg:city":"Orlando",
    "sg:classifiers":[
        {
            "category":"Sports & Exercise",
            "subcategory":"Gym",
            "type":"Entertainment"
        }
    ],
    "sg:phone":"+1 407 237 6351",
    "sg:postcode":"32806",
    "sg:province":"FL",
    "sg:tags":[
        "center",
        "fitness"
    ],
    "sg:website":"www.orhs.org",
    "wof:name":"Orlando Regional Wellness Ctr",
    "wof:placetype":"venue"
},
  "geometry": {"coordinates":[-81.381083,28.525018],"type":"Point"}
}