{
  "type": "Feature",
  "properties": {
    "iso:country":"US",
    "sg:address":"2803 E Cervantes St",
    "sg:city":"Pensacola",
    "sg:classifiers":[
        {
            "category":"Social Services",
            "type":"Services"
        }
    ],
    "sg:phone":"+1 850 433 2042",
    "sg:postcode":"32503",
    "sg:province":"FL",
    "sg:tags":[
        "counseling"
    ],
    "wof:name":"Lorraine M Graves",
    "wof:placetype":"venue"
},
  "geometry": {"coordinates":[-87.183621,30.425265],"type":"Point"}
}