{
  "type": "Feature",
  "properties": {
    "iso:country":"US",
    "sg:address":"15281 NE 85th Pl",
    "sg:city":"Silver Springs",
    "sg:classifiers":[
        {
            "category":"Building & Trades",
            "subcategory":"Construction",
            "type":"Services"
        }
    ],
    "sg:phone":"+1 352 625 2250",
    "sg:postcode":"34488",
    "sg:province":"FL",
    "sg:tags":[
        "floor",
        "laying",
        "contractor"
    ],
    "wof:name":"Reardon & Sons Installation",
    "wof:placetype":"venue"
},
  "geometry": {"coordinates":[-81.902171,29.276205],"type":"Point"}
}