{
  "type": "Feature",
  "properties": {
    "addr:full":"336 Lake Dr NW Fort Walton Beach FL 32548",
    "addr:housenumber":"336",
    "addr:postcode":"32548",
    "addr:street":"Lake Dr Nw",
    "iso:country":"US",
    "sg:address":"336 Lake Dr NW",
    "sg:city":"Fort Walton Beach",
    "sg:classifiers":[
        {
            "category":"Building & Trades",
            "subcategory":"Construction",
            "type":"Services"
        }
    ],
    "sg:phone":"+1 850 314 0277",
    "sg:postcode":"32548",
    "sg:province":"FL",
    "sg:tags":[
        "floor",
        "laying",
        "contractor"
    ],
    "wof:name":"Salvador Najera Flooring Co",
    "wof:placetype":"venue"
},
  "geometry": {"coordinates":[-86.63654099999999,30.422579],"type":"Point"}
}