{
  "type": "Feature",
  "properties": {
    "iso:country":"US",
    "sg:address":"1535 Owens Rd",
    "sg:city":"Jacksonville",
    "sg:classifiers":[
        {
            "category":"Autos & Motor Vehicles",
            "subcategory":"Auto Supplies",
            "type":"Retail Goods"
        }
    ],
    "sg:phone":"+1 904 741 4850",
    "sg:postcode":"32218",
    "sg:province":"FL",
    "sg:tags":[
        "equipment",
        "racing",
        "car",
        "automobile"
    ],
    "sg:website":"www.turboaction.com",
    "wof:name":"Turbo Action High Performance",
    "wof:placetype":"venue"
},
  "geometry": {"coordinates":[-81.65415400000001,30.490297],"type":"Point"}
}