{
  "type": "Feature",
  "properties": {
    "iso:country":"US",
    "sg:address":"155 NW 14th St",
    "sg:city":"Homestead",
    "sg:classifiers":[
        {
            "category":"Real Estate",
            "subcategory":"Real Estate Operator",
            "type":"Services"
        }
    ],
    "sg:phone":"+1 305 248 3500",
    "sg:postcode":"33030",
    "sg:province":"FL",
    "sg:tags":[
        "apartment"
    ],
    "wof:name":"Gateway Apartments",
    "wof:placetype":"venue"
},
  "geometry": {"coordinates":[-80.480541,25.483588],"type":"Point"}
}