{
  "type": "Feature",
  "properties": {
    "iso:country":"US",
    "sg:address":"2000 NE 13th Ave",
    "sg:city":"Cape Coral",
    "sg:classifiers":[
        {
            "category":"Shopping",
            "subcategory":"Books",
            "type":"Retail Goods"
        }
    ],
    "sg:phone":"+1 239 573 7273",
    "sg:postcode":"33909",
    "sg:province":"FL",
    "wof:name":"Books By Fontz",
    "wof:placetype":"venue"
},
  "geometry": {"coordinates":[-81.947413,26.692165],"type":"Point"}
}