{
  "type": "Feature",
  "properties": {
    "iso:country":"US",
    "sg:address":"519 Mountain Dr",
    "sg:city":"Destin",
    "sg:classifiers":[
        {
            "category":"Autos & Motor Vehicles",
            "subcategory":"Auto Supplies",
            "type":"Retail Goods"
        }
    ],
    "sg:phone":"+1 850 837 6176",
    "sg:postcode":"32541",
    "sg:province":"FL",
    "sg:tags":[
        "automobile",
        "parts"
    ],
    "wof:name":"NAPA Auto Parts",
    "wof:placetype":"venue"
},
  "geometry": {"coordinates":[-86.498122,30.394254],"type":"Point"}
}