{
  "type": "Feature",
  "properties": {
    "iso:country":"US",
    "sg:address":"271 NE 166th St",
    "sg:city":"Miami",
    "sg:classifiers":[
        {
            "category":"Food & Beverages",
            "subcategory":"Groceries & Convenience Stores",
            "type":"Retail Goods"
        }
    ],
    "sg:phone":"+1 305 944 3737",
    "sg:postcode":"33162",
    "sg:province":"FL",
    "wof:name":"International Food Store Inc",
    "wof:placetype":"venue"
},
  "geometry": {"coordinates":[-80.19555800000001,25.92759],"type":"Point"}
}