{
  "type": "Feature",
  "properties": {
    "iso:country":"US",
    "sg:address":"4977 S Cleveland Ave",
    "sg:city":"Fort Myers",
    "sg:classifiers":[
        {
            "category":"Shopping Center",
            "type":"Public Place"
        }
    ],
    "sg:phone":"+1 866 262 7700",
    "sg:postcode":"33907",
    "sg:province":"FL",
    "wof:name":"Page Field Commons",
    "wof:placetype":"venue"
},
  "geometry": {"coordinates":[-81.87162499999999,26.58817],"type":"Point"}
}