{
  "type": "Feature",
  "properties": {
    "iso:country":"US",
    "sg:address":"10 Towne Center Cir",
    "sg:city":"Sanford",
    "sg:classifiers":[
        {
            "category":"Restaurant",
            "type":"Food & Drink"
        }
    ],
    "sg:menulink":"http://www.allmenus.com/fl/sanford/13878-olive-garden-italian-restaurant/menu/",
    "sg:phone":"+1 407 322 5655",
    "sg:postcode":"32771",
    "sg:province":"FL",
    "sg:tags":[
        "italian"
    ],
    "wof:name":"Olive Garden Italian Restaurant",
    "wof:placetype":"venue"
},
  "geometry": {"coordinates":[-81.335673,28.806368],"type":"Point"}
}