{
  "type": "Feature",
  "properties": {
    "addr:full":"5302 Marina Dr Bradenton Beach FL 34217",
    "addr:housenumber":"5302",
    "addr:postcode":"34217",
    "addr:street":"Marina Dr",
    "iso:country":"US",
    "sg:address":"5302 Marina Dr",
    "sg:city":"Bradenton Beach",
    "sg:classifiers":[
        {
            "category":"Shopping",
            "subcategory":"Gifts & Souvenirs",
            "type":"Retail Goods"
        }
    ],
    "sg:phone":"+1 941 778 2024",
    "sg:postcode":"34217",
    "sg:province":"FL",
    "wof:name":"Sandrea Inc",
    "wof:placetype":"venue"
},
  "geometry": {"coordinates":[-82.714403,27.507778],"type":"Point"}
}