{
  "type": "Feature",
  "properties": {
    "addr:full":"6741 W 24th Ct Hialeah FL 33016",
    "addr:housenumber":"6741",
    "addr:postcode":"33016",
    "addr:street":"W 24Th Ct",
    "iso:country":"US",
    "sg:address":"6741 W 24th Ct",
    "sg:city":"Hialeah",
    "sg:classifiers":[
        {
            "category":"Health Services",
            "subcategory":"Dentist",
            "type":"Services"
        }
    ],
    "sg:phone":"+1 305 266 3630",
    "sg:postcode":"33016",
    "sg:province":"FL",
    "sg:tags":[
        "equipment",
        "dental",
        "supply"
    ],
    "wof:name":"Pan American Dental Discount Supply",
    "wof:placetype":"venue"
},
  "geometry": {"coordinates":[-80.332078,25.883442],"type":"Point"}
}