{
  "type": "Feature",
  "properties": {
    "iso:country":"US",
    "sg:address":"4006 W Kennedy Blvd",
    "sg:city":"Tampa",
    "sg:classifiers":[
        {
            "category":"Personal",
            "type":"Services"
        }
    ],
    "sg:phone":"+1 813 282 4608",
    "sg:postcode":"33609",
    "sg:province":"FL",
    "sg:tags":[
        "therapist",
        "massage"
    ],
    "wof:name":"KKDL Corp",
    "wof:placetype":"venue"
},
  "geometry": {"coordinates":[-82.51078800000001,27.944755],"type":"Point"}
}