{
  "type": "Feature",
  "properties": {
    "iso:country":"US",
    "sg:address":"35 Clayton Ln",
    "sg:city":"Santa Rosa Beach",
    "sg:classifiers":[
        {
            "category":"Real Estate",
            "subcategory":"Real Estate Agent",
            "type":"Services"
        }
    ],
    "sg:phone":"+1 850 267 0271",
    "sg:postcode":"32459",
    "sg:province":"FL",
    "wof:name":"Spooky Lane LLC",
    "wof:placetype":"venue"
},
  "geometry": {"coordinates":[-86.16612600000001,30.339098],"type":"Point"}
}