{
  "type": "Feature",
  "properties": {
    "addr:full":"3108 N Boundary Blvd Tampa FL 33621",
    "addr:housenumber":"3108",
    "addr:postcode":"33621",
    "addr:street":"N Boundary Blvd",
    "iso:country":"US",
    "sg:address":"3108 N Boundary Blvd",
    "sg:city":"Tampa",
    "sg:classifiers":[
        {
            "category":"Health Services",
            "subcategory":"Optometrist",
            "type":"Services"
        }
    ],
    "sg:phone":"+1 813 840 2292",
    "sg:postcode":"33621",
    "sg:province":"FL",
    "sg:tags":[
        "good",
        "optical"
    ],
    "wof:name":"Sunland Optical",
    "wof:placetype":"venue"
},
  "geometry": {"coordinates":[-82.49571400000001,27.863061],"type":"Point"}
}