{
  "type": "Feature",
  "properties": {
    "addr:full":"2035 Bearing Ln Kissimmee FL 34744",
    "addr:housenumber":"2035",
    "addr:postcode":"34744",
    "addr:street":"Bearing Ln",
    "iso:country":"US",
    "sg:address":"2035 Bearing Ln",
    "sg:city":"Kissimmee",
    "sg:classifiers":[
        {
            "category":"Building & Trades",
            "subcategory":"Construction",
            "type":"Services"
        }
    ],
    "sg:phone":"+1 407 847 9340",
    "sg:postcode":"34744",
    "sg:province":"FL",
    "sg:tags":[
        "home",
        "builder"
    ],
    "wof:name":"Kb Home Orlando LLC",
    "wof:placetype":"venue"
},
  "geometry": {"coordinates":[-81.358839,28.27913],"type":"Point"}
}