{
  "type": "Feature",
  "properties": {
    "iso:country":"US",
    "sg:address":"1371 S Walnut St",
    "sg:city":"Starke",
    "sg:classifiers":[
        {
            "category":"Shopping",
            "subcategory":"Clothing, Apparel, & Fashions",
            "type":"Retail Goods"
        }
    ],
    "sg:phone":"+1 904 964 8389",
    "sg:postcode":"32091",
    "sg:province":"FL",
    "wof:name":"Cato",
    "wof:placetype":"venue"
},
  "geometry": {"coordinates":[-82.11636300000001,29.932776],"type":"Point"}
}