{
  "type": "Feature",
  "properties": {
    "addr:full":"7414 State Rd 52 Hudson FL 34667",
    "addr:housenumber":"7414;52",
    "addr:postcode":"34667",
    "addr:street":"State Rd",
    "iso:country":"US",
    "sg:address":"7414 State Rd 52",
    "sg:city":"Hudson",
    "sg:classifiers":[
        {
            "category":"Home & Garden",
            "subcategory":"Building Materials",
            "type":"Retail Goods"
        },
        {
            "category":"Wholesale",
            "subcategory":"Metals & Minerals",
            "type":"Manufacturing & Wholesale Goods"
        }
    ],
    "sg:phone":"+1 727 862 3783",
    "sg:postcode":"34667",
    "sg:province":"FL",
    "sg:tags":[
        "center",
        "aluminum"
    ],
    "wof:name":"Solar Ray Windows Inc",
    "wof:placetype":"venue"
},
  "geometry": {"coordinates":[-82.69151599999999,28.331171],"type":"Point"}
}