{
  "type": "Feature",
  "properties": {
    "iso:country":"US",
    "sg:address":"1320 Blanding Blvd",
    "sg:city":"Orange Park",
    "sg:classifiers":[
        {
            "category":"Shopping",
            "subcategory":"Pharmacy",
            "type":"Retail Goods"
        }
    ],
    "sg:phone":"+1 904 276 7113",
    "sg:postcode":"32065",
    "sg:province":"FL",
    "sg:tags":[
        "drug",
        "store"
    ],
    "wof:name":"Walgreens",
    "wof:placetype":"venue"
},
  "geometry": {"coordinates":[-81.79811100000001,30.123458],"type":"Point"}
}