{
  "type": "Feature",
  "properties": {
    "iso:country":"US",
    "sg:address":"451 Interstate Ct",
    "sg:city":"Sarasota",
    "sg:classifiers":[
        {
            "category":"Manufacturing",
            "subcategory":"Printing",
            "type":"Manufacturing & Wholesale Goods"
        }
    ],
    "sg:phone":"+1 941 922 0844",
    "sg:postcode":"34240",
    "sg:province":"FL",
    "sg:tags":[
        "magazine",
        "publishing"
    ],
    "wof:name":"Small Publisher Coop",
    "wof:placetype":"venue"
},
  "geometry": {"coordinates":[-82.444819,27.333129],"type":"Point"}
}