{
  "type": "Feature",
  "properties": {
    "iso:country":"US",
    "sg:address":"6325 Edgewater Dr",
    "sg:city":"Orlando",
    "sg:classifiers":[
        {
            "category":"Shopping",
            "subcategory":"Mobile Phones",
            "type":"Retail Goods"
        }
    ],
    "sg:phone":"+1 407 298 0788",
    "sg:postcode":"32810",
    "sg:province":"FL",
    "wof:name":"Wireless Essentialz",
    "wof:placetype":"venue"
},
  "geometry": {"coordinates":[-81.422297,28.614393],"type":"Point"}
}