{
  "type": "Feature",
  "properties": {
    "iso:country":"US",
    "sg:address":"1450 S Davis Ave",
    "sg:city":"Bartow",
    "sg:classifiers":[
        {
            "category":"Retail",
            "subcategory":"Repair Shop",
            "type":"Services"
        }
    ],
    "sg:phone":"+1 863 519 5342",
    "sg:postcode":"33830",
    "sg:province":"FL",
    "wof:name":"Shirley Cleaning",
    "wof:placetype":"venue"
},
  "geometry": {"coordinates":[-81.83067,27.88144],"type":"Point"}
}