{
  "type": "Feature",
  "properties": {
    "iso:country":"US",
    "sg:address":"9155 NW 52nd Ct",
    "sg:city":"Pompano Beach",
    "sg:classifiers":[
        {
            "category":"Restaurant",
            "type":"Food & Drink"
        }
    ],
    "sg:phone":"+1 954 755 2391",
    "sg:postcode":"33067",
    "sg:province":"FL",
    "sg:tags":[
        "eating"
    ],
    "wof:name":"Caresmac Corp",
    "wof:placetype":"venue"
},
  "geometry": {"coordinates":[-80.247001,26.294611],"type":"Point"}
}