{
  "type": "Feature",
  "properties": {
    "addr:full":"620 Murray Ave Osteen FL 32764",
    "addr:housenumber":"620",
    "addr:postcode":"32764",
    "addr:street":"Murray Ave",
    "iso:country":"US",
    "sg:address":"620 Murray Ave",
    "sg:city":"Osteen",
    "sg:classifiers":[
        {
            "category":"Building & Trades",
            "subcategory":"Construction",
            "type":"Services"
        }
    ],
    "sg:phone":"+1 407 323 4188",
    "sg:postcode":"32764",
    "sg:province":"FL",
    "sg:tags":[
        "house"
    ],
    "wof:name":"Burk Construction Service",
    "wof:placetype":"venue"
},
  "geometry": {"coordinates":[-81.150997,28.840135],"type":"Point"}
}