{
  "type": "Feature",
  "properties": {
    "addr:full":"13741 NW 22nd St Sunrise FL 33323",
    "addr:housenumber":"13741",
    "addr:postcode":"33323",
    "addr:street":"Nw 22Nd St",
    "iso:country":"US",
    "sg:address":"13741 NW 22nd St",
    "sg:city":"Sunrise",
    "sg:classifiers":[
        {
            "category":"Building & Trades",
            "subcategory":"Construction",
            "type":"Services"
        }
    ],
    "sg:phone":"+1 954 647 8014",
    "sg:postcode":"33323",
    "sg:province":"FL",
    "sg:tags":[
        "restoration",
        "cleaning",
        "patio",
        "deck"
    ],
    "wof:name":"Robert Halliday Pressure Clean",
    "wof:placetype":"venue"
},
  "geometry": {"coordinates":[-80.331744,26.151609],"type":"Point"}
}