{
  "type": "Feature",
  "properties": {
    "addr:full":"19510 SW 114th Pl Miami FL 33157",
    "addr:housenumber":"19510",
    "addr:postcode":"33157",
    "addr:street":"Sw 114Th Pl",
    "iso:country":"US",
    "sg:address":"19510 SW 114th Pl",
    "sg:city":"Miami",
    "sg:classifiers":[
        {
            "category":"Restaurant",
            "type":"Food & Drink"
        }
    ],
    "sg:phone":"+1 305 233 0665",
    "sg:postcode":"33157",
    "sg:province":"FL",
    "sg:tags":[
        "parlor",
        "ice",
        "cream"
    ],
    "wof:name":"Magali Mena Ice Cream",
    "wof:placetype":"venue"
},
  "geometry": {"coordinates":[-80.378336,25.586396],"type":"Point"}
}