{
  "type": "Feature",
  "properties": {
    "addr:full":"925 S Broad St Brooksville FL 34601",
    "addr:housenumber":"925",
    "addr:postcode":"34601",
    "addr:street":"S Broad St",
    "iso:country":"US",
    "sg:address":"925 S Broad St",
    "sg:city":"Brooksville",
    "sg:classifiers":[
        {
            "category":"Autos & Motor Vehicles",
            "subcategory":"Auto Supplies",
            "type":"Retail Goods"
        }
    ],
    "sg:phone":"+1 352 799 2991",
    "sg:postcode":"34601",
    "sg:province":"FL",
    "sg:tags":[
        "home"
    ],
    "wof:name":"Olson Don Tire & Auto Centers",
    "wof:placetype":"venue"
},
  "geometry": {"coordinates":[-82.400859,28.545195],"type":"Point"}
}