{
  "type": "Feature",
  "properties": {
    "iso:country":"US",
    "sg:address":"2830 Forsyth Rd",
    "sg:city":"Winter Park",
    "sg:classifiers":[
        {
            "category":"Manufacturing",
            "subcategory":"Metals",
            "type":"Manufacturing & Wholesale Goods"
        }
    ],
    "sg:phone":"+1 407 671 1003",
    "sg:postcode":"32792",
    "sg:province":"FL",
    "sg:tags":[
        "gates",
        "metalwork",
        "mfg",
        "trade",
        "architectural",
        "contractor"
    ],
    "wof:name":"M & R Iron Works",
    "wof:placetype":"venue"
},
  "geometry": {"coordinates":[-81.294715,28.586362],"type":"Point"}
}