{
  "type": "Feature",
  "properties": {
    "iso:country":"US",
    "sg:address":"3530 NW 115th Ave",
    "sg:city":"Doral",
    "sg:classifiers":[
        {
            "category":"Wholesale",
            "subcategory":"Medical Equipment & Supplies",
            "type":"Manufacturing & Wholesale Goods"
        }
    ],
    "sg:phone":"+1 305 597 5277",
    "sg:postcode":"33178",
    "sg:province":"FL",
    "sg:tags":[
        "physician",
        "surgeon"
    ],
    "wof:name":"Demetech Corp",
    "wof:placetype":"venue"
},
  "geometry": {"coordinates":[-80.383937,25.809139],"type":"Point"}
}