{
  "type": "Feature",
  "properties": {
    "iso:country":"US",
    "sg:address":"10665 Wiles Rd",
    "sg:city":"Pompano Beach",
    "sg:classifiers":[
        {
            "category":"Restaurant",
            "type":"Food & Drink"
        },
        {
            "category":"Ice Cream",
            "type":"Food & Drink"
        }
    ],
    "sg:menulink":"http://www.allmenus.com/fl/deerfield-beach/172317-dairy-queen/menu/",
    "sg:phone":"+1 954 255 0888",
    "sg:postcode":"33076",
    "sg:province":"FL",
    "sg:tags":[
        "burger",
        "american",
        "ice",
        "cream"
    ],
    "wof:name":"Dairy Queen",
    "wof:placetype":"venue"
},
  "geometry": {"coordinates":[-80.26939299999999,26.287316],"type":"Point"}
}