{
  "type": "Feature",
  "properties": {
    "addr:full":"19 Bulow Woods Cir Flagler Beach FL 32136",
    "addr:housenumber":"19",
    "addr:postcode":"32136",
    "addr:street":"Bulow Woods Cir",
    "iso:country":"US",
    "sg:address":"19 Bulow Woods Cir",
    "sg:city":"Flagler Beach",
    "sg:classifiers":[
        {
            "category":"Building & Trades",
            "subcategory":"Equipment Rental",
            "type":"Services"
        }
    ],
    "sg:phone":"+1 386 439 9260",
    "sg:postcode":"32136",
    "sg:province":"FL",
    "wof:name":"L C Ledyard",
    "wof:placetype":"venue"
},
  "geometry": {"coordinates":[-81.12263900000001,29.432039],"type":"Point"}
}