{
  "type": "Feature",
  "properties": {
    "addr:full":"11121 NE 110th St Fort Mc Coy FL 32134",
    "addr:housenumber":"11121",
    "addr:postcode":"32134",
    "addr:street":"Ne 110Th St",
    "iso:country":"US",
    "sg:address":"11121 NE 110th St",
    "sg:city":"Fort Mc Coy",
    "sg:classifiers":[
        {
            "category":"Shopping",
            "subcategory":"Discount & Variety Stores",
            "type":"Retail Goods"
        }
    ],
    "sg:phone":"+1 352 438 0306",
    "sg:postcode":"32134",
    "sg:province":"FL",
    "sg:tags":[
        "merchandise",
        "general"
    ],
    "wof:name":"Plante Sales",
    "wof:placetype":"venue"
},
  "geometry": {"coordinates":[-81.960223,29.311434],"type":"Point"}
}