{
  "type": "Feature",
  "properties": {
    "addr:full":"825 Brickell Bay Dr Miami FL 33131",
    "addr:housenumber":"825",
    "addr:postcode":"33131",
    "addr:street":"Bay",
    "iso:country":"US",
    "sg:address":"825 Brickell Bay Dr",
    "sg:city":"Miami",
    "sg:classifiers":[
        {
            "category":"Professional",
            "subcategory":"Lawyer & Legal Services",
            "type":"Services"
        }
    ],
    "sg:phone":"+1 305 358 1181",
    "sg:postcode":"33131",
    "sg:province":"FL",
    "wof:name":"Ginsberg Marc R Atty",
    "wof:placetype":"venue"
},
  "geometry": {"coordinates":[-80.189499,25.7656],"type":"Point"}
}