{
  "type": "Feature",
  "properties": {
    "addr:full":"5127 US Hwy 19 New Port Richey FL 34652",
    "addr:housenumber":"5127",
    "addr:postcode":"34652",
    "addr:street":"Us Hwy 19",
    "iso:country":"US",
    "sg:address":"5127 US Hwy 19",
    "sg:city":"New Port Richey",
    "sg:classifiers":[
        {
            "category":"Food & Beverages",
            "subcategory":"Groceries & Convenience Stores",
            "type":"Retail Goods"
        }
    ],
    "sg:phone":"+1 727 849 2283",
    "sg:postcode":"34652",
    "sg:province":"FL",
    "sg:tags":[
        "supermarket"
    ],
    "wof:name":"Publix Super Market 115",
    "wof:placetype":"venue"
},
  "geometry": {"coordinates":[-82.728808,28.234451],"type":"Point"}
}