{
  "type": "Feature",
  "properties": {
    "addr:full":"17409 Summer Oak Ln Clermont FL 34711",
    "addr:housenumber":"17409",
    "addr:postcode":"34711",
    "addr:street":"Summer Oak Ln",
    "iso:country":"US",
    "sg:address":"17409 Summer Oak Ln",
    "sg:city":"Clermont",
    "sg:classifiers":[
        {
            "category":"Building & Trades",
            "subcategory":"Construction",
            "type":"Services"
        }
    ],
    "sg:phone":"+1 407 877 1095",
    "sg:postcode":"34711",
    "sg:province":"FL",
    "sg:tags":[
        "automotive",
        "contractor"
    ],
    "wof:name":"Freeman Marcus Window Trtmnt",
    "wof:placetype":"venue"
},
  "geometry": {"coordinates":[-81.66828,28.539395],"type":"Point"}
}