{
  "type": "Feature",
  "properties": {
    "iso:country":"US",
    "sg:address":"9341 Wellington Park Cir",
    "sg:city":"Tampa",
    "sg:classifiers":[
        {
            "category":"Health Services",
            "subcategory":"Doctor",
            "type":"Services"
        }
    ],
    "sg:phone":"+1 813 903 0060",
    "sg:postcode":"33647",
    "sg:province":"FL",
    "sg:tags":[
        "medical"
    ],
    "wof:name":"Teena Hughes MD PA",
    "wof:placetype":"venue"
},
  "geometry": {"coordinates":[-82.33668299999999,28.132993],"type":"Point"}
}