{
  "type": "Feature",
  "properties": {
    "addr:full":"58 W Burdick Ave Defuniak Springs FL 32433",
    "addr:housenumber":"58",
    "addr:postcode":"32433",
    "addr:street":"W Burdick Ave",
    "iso:country":"US",
    "sg:address":"58 W Burdick Ave",
    "sg:city":"Defuniak Springs",
    "sg:classifiers":[
        {
            "category":"Government",
            "subcategory":"Fire Station",
            "type":"Public Place"
        }
    ],
    "sg:phone":"+1 850 892 8515",
    "sg:postcode":"32433",
    "sg:province":"FL",
    "sg:tags":[
        "department"
    ],
    "wof:name":"De Funiak Springs Fire Dept",
    "wof:placetype":"venue"
},
  "geometry": {"coordinates":[-86.11533799999999,30.725532],"type":"Point"}
}