{
  "type": "Feature",
  "properties": {
    "iso:country":"US",
    "sg:address":"8408 Monarch Dr",
    "sg:city":"Port Richey",
    "sg:classifiers":[
        {
            "category":"Education",
            "subcategory":"School",
            "type":"Public Place"
        }
    ],
    "sg:phone":"+1 727 862 6981",
    "sg:postcode":"34668",
    "sg:province":"FL",
    "wof:name":"Bishop Larkin School",
    "wof:placetype":"venue"
},
  "geometry": {"coordinates":[-82.67577799999999,28.297059],"type":"Point"}
}