{
  "type": "Feature",
  "properties": {
    "iso:country":"US",
    "sg:address":"7442 N Tamiami Trl",
    "sg:city":"Sarasota",
    "sg:classifiers":[
        {
            "category":"Health Services",
            "subcategory":"Doctor",
            "type":"Services"
        }
    ],
    "sg:phone":"+1 941 351 8338",
    "sg:postcode":"34243",
    "sg:province":"FL",
    "sg:tags":[
        "dentist"
    ],
    "sg:website":"www.florida-dentist.com",
    "wof:name":"Kenneth Liszewski & Assoc",
    "wof:placetype":"venue"
},
  "geometry": {"coordinates":[-82.56682000000001,27.403119],"type":"Point"}
}