{
  "type": "Feature",
  "properties": {
    "addr:full":"321 Jay Ave Lake Wales FL 33872",
    "addr:housenumber":"321",
    "addr:postcode":"33872",
    "addr:street":"Jay Ave",
    "iso:country":"US",
    "sg:address":"321 Jay Ave",
    "sg:city":"Lake Wales",
    "sg:classifiers":[
        {
            "category":"Education",
            "subcategory":"School",
            "type":"Public Place"
        }
    ],
    "sg:phone":"+1 863 678 4262",
    "sg:postcode":"33872",
    "sg:province":"FL",
    "wof:name":"Spook Hill Elementary School",
    "wof:placetype":"venue"
},
  "geometry": {"coordinates":[-81.49716100000001,27.489186],"type":"Point"}
}