{
  "type": "Feature",
  "properties": {
    "addr:full":"1507 Seffner Valrico Rd Seffner FL 33584",
    "addr:housenumber":"1507",
    "addr:postcode":"33584",
    "addr:street":"Seffner Valrico Rd",
    "iso:country":"US",
    "sg:address":"1507 Seffner Valrico Rd",
    "sg:city":"Seffner",
    "sg:classifiers":[
        {
            "category":"Farming",
            "subcategory":"Orchard",
            "type":"Manufacturing & Wholesale Goods"
        }
    ],
    "sg:phone":"+1 813 654 2447",
    "sg:postcode":"33584",
    "sg:province":"FL",
    "sg:tags":[
        "farm",
        "crop",
        "citrus",
        "fruit",
        "grove",
        "berry"
    ],
    "wof:name":"Eugene Cowert",
    "wof:placetype":"venue"
},
  "geometry": {"coordinates":[-82.269386,27.963751],"type":"Point"}
}