{
  "type": "Feature",
  "properties": {
    "addr:full":"516 Ocean Mist Ct Ruskin FL 33570",
    "addr:housenumber":"516",
    "addr:postcode":"33570",
    "addr:street":"Ocean Mist Ct",
    "iso:country":"US",
    "sg:address":"516 Ocean Mist Ct",
    "sg:city":"Ruskin",
    "sg:classifiers":[
        {
            "category":"Professional",
            "subcategory":"Detective & Security Services",
            "type":"Services"
        }
    ],
    "sg:phone":"+1 813 850 1755",
    "sg:postcode":"33570",
    "sg:province":"FL",
    "sg:tags":[
        "information",
        "bureau"
    ],
    "wof:name":"Pena Block Services Inc",
    "wof:placetype":"venue"
},
  "geometry": {"coordinates":[-82.440467,27.697822],"type":"Point"}
}