{
  "type": "Feature",
  "properties": {
    "addr:full":"16215 Panama City Beach Pkwy Panama City Bch FL 32413",
    "addr:housenumber":"16215",
    "addr:postcode":"32413",
    "addr:street":"Panama;Beach Pkwy",
    "iso:country":"US",
    "sg:address":"16215 Panama City Beach Pkwy",
    "sg:city":"Panama City Bch",
    "sg:classifiers":[
        {
            "category":"Banks & Credit Unions",
            "subcategory":"Investment Brokerage",
            "type":"Services"
        }
    ],
    "sg:phone":"+1 850 230 0045",
    "sg:postcode":"32413",
    "sg:province":"FL",
    "sg:tags":[
        "security",
        "stock",
        "bond"
    ],
    "sg:website":"www.agedwards.com",
    "wof:name":"A G Edwards & Sons Inc",
    "wof:placetype":"venue"
},
  "geometry": {"coordinates":[-85.88166,30.227888],"type":"Point"}
}