{
  "type": "Feature",
  "properties": {
    "iso:country":"US",
    "sg:address":"7770 Lund Rd",
    "sg:city":"Milton",
    "sg:classifiers":[
        {
            "category":"Government",
            "subcategory":"Fire Station",
            "type":"Public Place"
        }
    ],
    "sg:phone":"+1 850 983 0045",
    "sg:postcode":"32570",
    "sg:province":"FL",
    "sg:tags":[
        "department"
    ],
    "wof:name":"Skyline Fire & Rescue Dist 2",
    "wof:placetype":"venue"
},
  "geometry": {"coordinates":[-86.995949,30.675922],"type":"Point"}
}