{
  "type": "Feature",
  "properties": {
    "iso:country":"US",
    "sg:address":"895 Pondella Rd",
    "sg:city":"Fort Myers",
    "sg:classifiers":[
        {
            "category":"Retail",
            "subcategory":"Repair Shop",
            "type":"Services"
        }
    ],
    "sg:phone":"+1 239 995 5600",
    "sg:postcode":"33903",
    "sg:province":"FL",
    "sg:tags":[
        "machine",
        "washing"
    ],
    "wof:name":"Apec Appliances",
    "wof:placetype":"venue"
},
  "geometry": {"coordinates":[-81.914136,26.667311],"type":"Point"}
}