{
  "type": "Feature",
  "properties": {
    "iso:country":"US",
    "sg:address":"4543 Ligustrum Way",
    "sg:city":"Orlando",
    "sg:classifiers":[
        {
            "category":"Building & Trades",
            "subcategory":"Construction",
            "type":"Services"
        }
    ],
    "sg:phone":"+1 407 352 1992",
    "sg:postcode":"32839",
    "sg:province":"FL",
    "sg:tags":[
        "house"
    ],
    "wof:name":"Priester Construction",
    "wof:placetype":"venue"
},
  "geometry": {"coordinates":[-81.436587,28.476699],"type":"Point"}
}