{
  "type": "Feature",
  "properties": {
    "addr:full":"222 S John Young Pkwy Kissimmee FL 34741",
    "addr:housenumber":"222",
    "addr:postcode":"34741",
    "addr:street":"S John Young Pkwy",
    "iso:country":"US",
    "sg:address":"222 S John Young Pkwy",
    "sg:city":"Kissimmee",
    "sg:classifiers":[
        {
            "category":"Autos & Motor Vehicles",
            "subcategory":"Auto Supplies",
            "type":"Retail Goods"
        }
    ],
    "sg:phone":"+1 407 944 0068",
    "sg:postcode":"34741",
    "sg:province":"FL",
    "sg:tags":[
        "automobile",
        "parts"
    ],
    "wof:name":"Autozone",
    "wof:placetype":"venue"
},
  "geometry": {"coordinates":[-81.415909,28.289201],"type":"Point"}
}