{
  "type": "Feature",
  "properties": {
    "addr:full":"2335 Soutel Dr Jacksonville FL 32208",
    "addr:housenumber":"2335",
    "addr:postcode":"32208",
    "addr:street":"Soutel Dr",
    "iso:country":"US",
    "sg:address":"2335 Soutel Dr",
    "sg:city":"Jacksonville",
    "sg:classifiers":[
        {
            "category":"Health Services",
            "subcategory":"Nursing And Care Facility",
            "type":"Services"
        }
    ],
    "sg:phone":"+1 904 765 1144",
    "sg:postcode":"32208",
    "sg:province":"FL",
    "sg:tags":[
        "home",
        "homes-intermediate",
        "rest"
    ],
    "wof:name":"Bradford's Rest Home",
    "wof:placetype":"venue"
},
  "geometry": {"coordinates":[-81.69328299999999,30.40744],"type":"Point"}
}