{
  "type": "Feature",
  "properties": {
    "addr:full":"2250 State Hwy 44 Inverness FL 34453",
    "addr:housenumber":"2250",
    "addr:postcode":"34453",
    "addr:street":"State Hwy 44",
    "iso:country":"US",
    "sg:address":"2250 State Hwy 44",
    "sg:city":"Inverness",
    "sg:classifiers":[
        {
            "category":"Health Services",
            "subcategory":"Nursing And Care Facility",
            "type":"Services"
        },
        {
            "category":"Social Services",
            "subcategory":"Adult Care",
            "type":"Services"
        }
    ],
    "sg:phone":"+1 352 726 5588",
    "sg:postcode":"34453",
    "sg:province":"FL",
    "sg:tags":[
        "home",
        "skilled",
        "residential"
    ],
    "wof:name":"Diversicare Management Svcs Co",
    "wof:placetype":"venue"
},
  "geometry": {"coordinates":[-82.36153899999999,28.841188],"type":"Point"}
}