{
  "type": "Feature",
  "properties": {
    "addr:full":"11613 N Nebraska Ave Tampa FL 33612",
    "addr:housenumber":"11613",
    "addr:postcode":"33612",
    "addr:street":"N Nebraska Ave",
    "iso:country":"US",
    "sg:address":"11613 N Nebraska Ave",
    "sg:city":"Tampa",
    "sg:classifiers":[
        {
            "category":"Shopping",
            "subcategory":"Pharmacy",
            "type":"Retail Goods"
        }
    ],
    "sg:phone":"+1 813 978 0775",
    "sg:postcode":"33612",
    "sg:province":"FL",
    "sg:tags":[
        "drug",
        "store"
    ],
    "wof:name":"CVS",
    "wof:placetype":"venue"
},
  "geometry": {"coordinates":[-82.45111799999999,28.054407],"type":"Point"}
}