{
  "type": "Feature",
  "properties": {
    "iso:country":"US",
    "sg:address":"5628 SW 102nd Ave",
    "sg:city":"Miami",
    "sg:classifiers":[
        {
            "category":"Restaurant",
            "type":"Food & Drink"
        }
    ],
    "sg:phone":"+1 305 598 4011",
    "sg:postcode":"33173",
    "sg:province":"FL",
    "sg:tags":[
        "eating"
    ],
    "wof:name":"Ortega Restaurant",
    "wof:placetype":"venue"
},
  "geometry": {"coordinates":[-80.35900100000001,25.714701],"type":"Point"}
}