{
  "type": "Feature",
  "properties": {
    "addr:full":"3404 NW 32nd Ave Miami FL 33142",
    "addr:housenumber":"3404",
    "addr:postcode":"33142",
    "addr:street":"Nw 32Nd Ave",
    "iso:country":"US",
    "sg:address":"3404 NW 32nd Ave",
    "sg:city":"Miami",
    "sg:classifiers":[
        {
            "category":"Personal",
            "subcategory":"Beauty Salon",
            "type":"Services"
        }
    ],
    "sg:phone":"+1 305 633 9611",
    "sg:postcode":"33142",
    "sg:province":"FL",
    "sg:tags":[
        "shop"
    ],
    "wof:name":"LA Nueva Era Beauty Salon",
    "wof:placetype":"venue"
},
  "geometry": {"coordinates":[-80.24839900000001,25.807873],"type":"Point"}
}