{
  "type": "Feature",
  "properties": {
    "addr:full":"10149 Sunshine Dr Bonita Springs FL 34135",
    "addr:housenumber":"10149",
    "addr:postcode":"34135",
    "addr:street":"Sunshine Dr",
    "iso:country":"US",
    "sg:address":"10149 Sunshine Dr",
    "sg:city":"Bonita Springs",
    "sg:classifiers":[
        {
            "category":"Building & Trades",
            "subcategory":"Construction",
            "type":"Services"
        }
    ],
    "sg:phone":"+1 239 450 6391",
    "sg:postcode":"34135",
    "sg:province":"FL",
    "sg:tags":[
        "equipment",
        "installation"
    ],
    "wof:name":"Underground Specialists SW FL",
    "wof:placetype":"venue"
},
  "geometry": {"coordinates":[-81.785966,26.351347],"type":"Point"}
}