{
  "type": "Feature",
  "properties": {
    "addr:full":"1247 W 68th St Hialeah FL 33014",
    "addr:housenumber":"1247",
    "addr:postcode":"33014",
    "addr:street":"W 68Th St",
    "iso:country":"US",
    "sg:address":"1247 W 68th St",
    "sg:city":"Hialeah",
    "sg:classifiers":[
        {
            "category":"Shopping",
            "subcategory":"Pharmacy",
            "type":"Retail Goods"
        }
    ],
    "sg:phone":"+1 305 825 6546",
    "sg:postcode":"33014",
    "sg:province":"FL",
    "sg:tags":[
        "drugstore"
    ],
    "sg:website":"www.cvs.com",
    "wof:name":"Cvs",
    "wof:placetype":"venue"
},
  "geometry": {"coordinates":[-80.30857,25.884319],"type":"Point"}
}