{
  "type": "Feature",
  "properties": {
    "iso:country":"US",
    "sg:address":"401 George W Engram Blvd",
    "sg:city":"Daytona Beach",
    "sg:classifiers":[
        {
            "category":"Home & Garden",
            "subcategory":"Building Materials",
            "type":"Retail Goods"
        }
    ],
    "sg:phone":"+1 386 248 0607",
    "sg:postcode":"32114",
    "sg:province":"FL",
    "sg:tags":[
        "shutter"
    ],
    "wof:name":"Scott's Manufacturing",
    "wof:placetype":"venue"
},
  "geometry": {"coordinates":[-81.030698,29.217622],"type":"Point"}
}