{
  "type": "Feature",
  "properties": {
    "addr:full":"1051 W 45th Pl Hialeah FL 33012",
    "addr:housenumber":"1051",
    "addr:postcode":"33012",
    "addr:street":"W 45Th Pl",
    "iso:country":"US",
    "sg:address":"1051 W 45th Pl",
    "sg:city":"Hialeah",
    "sg:classifiers":[
        {
            "category":"Professional",
            "subcategory":"Engineering",
            "type":"Services"
        }
    ],
    "sg:phone":"+1 305 823 8008",
    "sg:postcode":"33012",
    "sg:province":"FL",
    "sg:tags":[
        "equipment",
        "supply"
    ],
    "wof:name":"Releigh",
    "wof:placetype":"venue"
},
  "geometry": {"coordinates":[-80.302165,25.86331],"type":"Point"}
}