{
  "type": "Feature",
  "properties": {
    "addr:full":"7897 Blanding Blvd Jacksonville FL 32244",
    "addr:housenumber":"7897",
    "addr:postcode":"32244",
    "addr:street":"Blanding Blvd",
    "iso:country":"US",
    "sg:address":"7897 Blanding Blvd",
    "sg:city":"Jacksonville",
    "sg:classifiers":[
        {
            "category":"Wholesale",
            "subcategory":"Electrical",
            "type":"Manufacturing & Wholesale Goods"
        }
    ],
    "sg:phone":"+1 904 779 6611",
    "sg:postcode":"32244",
    "sg:province":"FL",
    "sg:tags":[
        "communication",
        "radio",
        "system"
    ],
    "wof:name":"American Radio Corp",
    "wof:placetype":"venue"
},
  "geometry": {"coordinates":[-81.738623,30.208896],"type":"Point"}
}