{
  "type": "Feature",
  "properties": {
    "iso:country":"US",
    "sg:address":"6250 SW 132nd St",
    "sg:city":"Miami",
    "sg:classifiers":[
        {
            "category":"Shopping",
            "subcategory":"Clothing, Apparel, & Fashions",
            "type":"Retail Goods"
        }
    ],
    "sg:phone":"+1 305 234 6189",
    "sg:postcode":"33156",
    "sg:province":"FL",
    "wof:name":"Amb Designs",
    "wof:placetype":"venue"
},
  "geometry": {"coordinates":[-80.29470000000001,25.648644],"type":"Point"}
}