{
  "type": "Feature",
  "properties": {
    "iso:country":"US",
    "sg:address":"115 Country Club Ln",
    "sg:city":"Mulberry",
    "sg:classifiers":[
        {
            "category":"Health Services",
            "subcategory":"Doctor",
            "type":"Services"
        }
    ],
    "sg:phone":"+1 863 647 9987",
    "sg:postcode":"33860",
    "sg:province":"FL",
    "sg:tags":[
        "help",
        "supply"
    ],
    "wof:name":"Dental Temps of Lakeland",
    "wof:placetype":"venue"
},
  "geometry": {"coordinates":[-81.98581299999999,27.928128],"type":"Point"}
}