{
  "type": "Feature",
  "properties": {
    "iso:country":"US",
    "sg:address":"1341 Lyndale Blvd",
    "sg:city":"Winter Park",
    "sg:classifiers":[
        {
            "category":"Manufacturing",
            "subcategory":"Printing",
            "type":"Manufacturing & Wholesale Goods"
        }
    ],
    "sg:phone":"+1 407 629 6300",
    "sg:postcode":"32789",
    "sg:province":"FL",
    "sg:tags":[
        "multimedia"
    ],
    "wof:name":"Martin Phelps Media Inc",
    "wof:placetype":"venue"
},
  "geometry": {"coordinates":[-81.362337,28.610667],"type":"Point"}
}