{
  "type": "Feature",
  "properties": {
    "iso:country":"US",
    "sg:address":"302 3rd St",
    "sg:city":"Port St Joe",
    "sg:classifiers":[
        {
            "category":"Utilities",
            "subcategory":"Mobile Phone",
            "type":"Services"
        }
    ],
    "sg:phone":"+1 850 227 7997",
    "sg:postcode":"32410",
    "sg:province":"FL",
    "sg:tags":[
        "telephone",
        "cellular"
    ],
    "wof:name":"Emerald Coast Wireless",
    "wof:placetype":"venue"
},
  "geometry": {"coordinates":[-85.39403,29.932685],"type":"Point"}
}