{
  "type": "Feature",
  "properties": {
    "iso:country":"US",
    "sg:address":"1810 N 25th St",
    "sg:city":"Tampa",
    "sg:classifiers":[
        {
            "category":"Wholesale",
            "subcategory":"Stationery",
            "type":"Manufacturing & Wholesale Goods"
        }
    ],
    "sg:phone":"+1 813 247 5008",
    "sg:postcode":"33605",
    "sg:province":"FL",
    "sg:tags":[
        "equipment",
        "packing",
        "shipping",
        "supply"
    ],
    "wof:name":"Alpha Industrial Supplies Inc",
    "wof:placetype":"venue"
},
  "geometry": {"coordinates":[-82.43109800000001,27.960879],"type":"Point"}
}