{
  "type": "Feature",
  "properties": {
    "addr:full":"3365 SW Potts St Port St Lucie FL 34953",
    "addr:housenumber":"3365",
    "addr:postcode":"34953",
    "addr:street":"Sw Potts St;St",
    "iso:country":"US",
    "sg:address":"3365 SW Potts St",
    "sg:city":"Port St Lucie",
    "sg:classifiers":[
        {
            "category":"Building & Trades",
            "subcategory":"Construction",
            "type":"Services"
        }
    ],
    "sg:phone":"+1 772 342 3275",
    "sg:postcode":"34953",
    "sg:province":"FL",
    "sg:tags":[
        "handyman"
    ],
    "wof:name":"James Allen Aubrey Handy Svc",
    "wof:placetype":"venue"
},
  "geometry": {"coordinates":[-80.378985,27.243071],"type":"Point"}
}