{
  "type": "Feature",
  "properties": {
    "iso:country":"US",
    "sg:address":"38442 Tuskeegee Ave",
    "sg:city":"Dade City",
    "sg:classifiers":[
        {
            "category":"Organizations",
            "subcategory":"Religious Organization",
            "type":"Services"
        }
    ],
    "sg:phone":"+1 352 567 1427",
    "sg:postcode":"33525",
    "sg:province":"FL",
    "sg:tags":[
        "church"
    ],
    "wof:name":"New Jerusalem Church Of God",
    "wof:placetype":"venue"
},
  "geometry": {"coordinates":[-82.182191,28.363026],"type":"Point"}
}