{
  "type": "Feature",
  "properties": {
    "iso:country":"US",
    "sg:address":"5827 Bird Rd",
    "sg:city":"Miami",
    "sg:classifiers":[
        {
            "category":"Banks & Credit Unions",
            "subcategory":"Bank",
            "type":"Services"
        }
    ],
    "sg:phone":"+1 305 662 2887",
    "sg:postcode":"33155",
    "sg:province":"FL",
    "wof:name":"Union Planters Bank",
    "wof:placetype":"venue"
},
  "geometry": {"coordinates":[-80.28919999999999,25.7339],"type":"Point"}
}