{
  "type": "Feature",
  "properties": {
    "iso:country":"US",
    "sg:address":"106 NE Beach Ave E",
    "sg:city":"Port Saint Lucie",
    "sg:classifiers":[
        {
            "category":"Building & Trades",
            "subcategory":"Construction",
            "type":"Services"
        }
    ],
    "sg:phone":"+1 772 878 2551",
    "sg:postcode":"34952",
    "sg:province":"FL",
    "sg:tags":[
        "floor",
        "laying",
        "contractor"
    ],
    "wof:name":"Hughes Douglas Flooring LLC",
    "wof:placetype":"venue"
},
  "geometry": {"coordinates":[-80.323891,27.327805],"type":"Point"}
}