{
  "type": "Feature",
  "properties": {
    "iso:country":"US",
    "sg:address":"2102 Bridgeview Cir",
    "sg:city":"Orlando",
    "sg:classifiers":[
        {
            "category":"Manufacturing",
            "subcategory":"Printing",
            "type":"Manufacturing & Wholesale Goods"
        }
    ],
    "sg:phone":"+1 407 850 0121",
    "sg:postcode":"32824",
    "sg:province":"FL",
    "sg:tags":[
        "newspaper"
    ],
    "wof:name":"Conway News",
    "wof:placetype":"venue"
},
  "geometry": {"coordinates":[-81.354624,28.363838],"type":"Point"}
}