{
  "type": "Feature",
  "properties": {
    "addr:full":"13992 W Hillsborough Ave Tampa FL 33635",
    "addr:housenumber":"13992",
    "addr:postcode":"33635",
    "addr:street":"W Hillsborough Ave",
    "iso:country":"US",
    "sg:address":"13992 W Hillsborough Ave",
    "sg:city":"Tampa",
    "sg:classifiers":[
        {
            "category":"Personal",
            "subcategory":"Hair Removal",
            "type":"Services"
        }
    ],
    "sg:phone":"+1 813 855 8482",
    "sg:postcode":"33635",
    "sg:province":"FL",
    "wof:name":"Life Time Financial Inc",
    "wof:placetype":"venue"
},
  "geometry": {"coordinates":[-82.648506,28.033577],"type":"Point"}
}