{
  "type": "Feature",
  "properties": {
    "iso:country":"US",
    "sg:address":"251 Brescia St NE",
    "sg:city":"Palm Bay",
    "sg:classifiers":[
        {
            "category":"Real Estate",
            "subcategory":"Real Estate Agent",
            "type":"Services"
        }
    ],
    "sg:phone":"+1 321 951 4181",
    "sg:postcode":"32907",
    "sg:province":"FL",
    "sg:tags":[
        "inspection"
    ],
    "wof:name":"J F Meyers General Contractor",
    "wof:placetype":"venue"
},
  "geometry": {"coordinates":[-80.667708,28.011878],"type":"Point"}
}