{
  "type": "Feature",
  "properties": {
    "addr:full":"601 5th Ave S Naples FL 34102",
    "addr:housenumber":"601",
    "addr:postcode":"34102",
    "addr:street":"5Th Ave S",
    "iso:country":"US",
    "sg:address":"601 5th Ave S",
    "sg:city":"Naples",
    "sg:classifiers":[
        {
            "category":"Shopping",
            "subcategory":"Jewelry",
            "type":"Retail Goods"
        }
    ],
    "sg:phone":"+1 239 213 0004",
    "sg:postcode":"34102",
    "sg:province":"FL",
    "wof:name":"Congress Jewelers LTD",
    "wof:placetype":"venue"
},
  "geometry": {"coordinates":[-81.798159,26.141484],"type":"Point"}
}