{
  "type": "Feature",
  "properties": {
    "iso:country":"US",
    "sg:address":"15466 Whispering Willow Dr",
    "sg:city":"Wellington",
    "sg:classifiers":[
        {
            "category":"Retail",
            "subcategory":"Car Wash",
            "type":"Services"
        }
    ],
    "sg:phone":"+1 561 745 1138",
    "sg:postcode":"33414",
    "sg:province":"FL",
    "sg:tags":[
        "automobile",
        "detail",
        "clean"
    ],
    "wof:name":"Unique Auto Detailing",
    "wof:placetype":"venue"
},
  "geometry": {"coordinates":[-80.28947700000001,26.680424],"type":"Point"}
}