{
  "type": "Feature",
  "properties": {
    "iso:country":"US",
    "sg:address":"5 Cedardale Ct",
    "sg:city":"Palm Coast",
    "sg:classifiers":[
        {
            "category":"Recreation",
            "type":"Entertainment"
        },
        {
            "category":"Utilities",
            "type":"Services"
        }
    ],
    "sg:phone":"+1 386 447 0024",
    "sg:postcode":"32137",
    "sg:province":"FL",
    "sg:tags":[
        "sanitary",
        "psychic",
        "medium"
    ],
    "wof:name":"Midnight Sweepers",
    "wof:placetype":"venue"
},
  "geometry": {"coordinates":[-81.209155,29.593321],"type":"Point"}
}