{
  "type": "Feature",
  "properties": {
    "iso:country":"US",
    "sg:address":"7302 Logan Heights Cir",
    "sg:city":"Sanford",
    "sg:classifiers":[
        {
            "category":"Place Of Worship",
            "type":"Public Place"
        }
    ],
    "sg:phone":"+1 407 328 0888",
    "sg:postcode":"32773",
    "sg:province":"FL",
    "sg:tags":[
        "church"
    ],
    "wof:name":"Anointed Ministries",
    "wof:placetype":"venue"
},
  "geometry": {"coordinates":[-81.27964299999999,28.762965],"type":"Point"}
}