{
  "type": "Feature",
  "properties": {
    "iso:country":"US",
    "sg:address":"13245 Atlantic Blvd",
    "sg:city":"Jacksonville",
    "sg:classifiers":[
        {
            "category":"Utilities",
            "subcategory":"Mobile Phone",
            "type":"Services"
        }
    ],
    "sg:phone":"+1 904 221 1234",
    "sg:postcode":"32225",
    "sg:province":"FL",
    "sg:tags":[
        "telephone",
        "cellular"
    ],
    "wof:name":"Cingular Wireless",
    "wof:placetype":"venue"
},
  "geometry": {"coordinates":[-81.46158200000001,30.320102],"type":"Point"}
}