{
  "type": "Feature",
  "properties": {
    "addr:full":"4780 NW 128th St Opa Locka FL 33054",
    "addr:housenumber":"4780",
    "addr:postcode":"33054",
    "addr:street":"Nw 128Th St;Locka",
    "iso:country":"US",
    "sg:address":"4780 NW 128th St",
    "sg:city":"Opa Locka",
    "sg:classifiers":[
        {
            "category":"Wholesale",
            "subcategory":"Hardware",
            "type":"Manufacturing & Wholesale Goods"
        },
        {
            "category":"Manufacturing",
            "subcategory":"Rubber & Plastics",
            "type":"Manufacturing & Wholesale Goods"
        }
    ],
    "sg:phone":"+1 305 685 1101",
    "sg:postcode":"33054",
    "sg:province":"FL",
    "sg:tags":[
        "product",
        "mfg"
    ],
    "sg:website":"www.hardwareconcepts.com",
    "wof:name":"Hardware Concepts Inc",
    "wof:placetype":"venue"
},
  "geometry": {"coordinates":[-80.276698,25.892752],"type":"Point"}
}