{
  "type": "Feature",
  "properties": {
    "iso:country":"US",
    "sg:address":"8163 NW 60th St",
    "sg:city":"Miami",
    "sg:classifiers":[
        {
            "category":"Shopping",
            "subcategory":"Catalog Store",
            "type":"Retail Goods"
        },
        {
            "category":"Health Services",
            "subcategory":"Medical Lab",
            "type":"Services"
        }
    ],
    "sg:phone":"+1 305 629 8050",
    "sg:postcode":"33166",
    "sg:province":"FL",
    "sg:tags":[
        "laboratory",
        "house",
        "mail"
    ],
    "wof:name":"Blood Diagnostics Inc",
    "wof:placetype":"venue"
},
  "geometry": {"coordinates":[-80.3267,25.828142],"type":"Point"}
}