{
  "type": "Feature",
  "properties": {
    "iso:country":"US",
    "sg:address":"18849 NW Hwy 335",
    "sg:city":"Williston",
    "sg:classifiers":[
        {
            "category":"Building & Trades",
            "subcategory":"Construction",
            "type":"Services"
        }
    ],
    "sg:phone":"+1 352 528 5393",
    "sg:postcode":"32696",
    "sg:province":"FL",
    "sg:tags":[
        "floor",
        "laying",
        "contractor"
    ],
    "wof:name":"Advanced Surfacing Inc",
    "wof:placetype":"venue"
},
  "geometry": {"coordinates":[-82.405365,29.407731],"type":"Point"}
}