{
  "type": "Feature",
  "properties": {
    "iso:country":"US",
    "sg:address":"3690 NW 16th St",
    "sg:city":"Miami",
    "sg:classifiers":[
        {
            "category":"Building & Trades",
            "subcategory":"Landscaping Services",
            "type":"Services"
        }
    ],
    "sg:phone":"+1 305 634 7980",
    "sg:postcode":"33125",
    "sg:province":"FL",
    "sg:tags":[
        "landscape",
        "contractor"
    ],
    "wof:name":"Imperial Landscaping Irrgtn",
    "wof:placetype":"venue"
},
  "geometry": {"coordinates":[-80.25410100000001,25.78862],"type":"Point"}
}