{
  "type": "Feature",
  "properties": {
    "addr:full":"5306 Foxhunt Dr Wesley Chapel FL 33543",
    "addr:housenumber":"5306",
    "addr:postcode":"33543",
    "addr:street":"Foxhunt Dr",
    "iso:country":"US",
    "sg:address":"5306 Foxhunt Dr",
    "sg:city":"Wesley Chapel",
    "sg:classifiers":[
        {
            "category":"Real Estate",
            "subcategory":"Real Estate Agent",
            "type":"Services"
        }
    ],
    "sg:phone":"+1 813 973 0214",
    "sg:postcode":"33543",
    "sg:province":"FL",
    "wof:name":"Century 21",
    "wof:placetype":"venue"
},
  "geometry": {"coordinates":[-82.33301,28.233703],"type":"Point"}
}