{
  "type": "Feature",
  "properties": {
    "addr:full":"1400 NE Miami Gardens Dr Miami FL 33179",
    "addr:housenumber":"1400",
    "addr:postcode":"33179",
    "addr:street":"Ne Miami Gardens Dr",
    "iso:country":"US",
    "sg:address":"1400 NE Miami Gardens Dr",
    "sg:city":"Miami",
    "sg:classifiers":[
        {
            "category":"Health Services",
            "subcategory":"Doctor",
            "type":"Services"
        },
        {
            "category":"Health Services",
            "subcategory":"Dentist",
            "type":"Services"
        }
    ],
    "sg:phone":"+1 305 940 4911",
    "sg:postcode":"33179",
    "sg:province":"FL",
    "sg:tags":[
        "physician",
        "maxillofacial",
        "surgeons",
        "dentists-oral",
        "surgery",
        "oral",
        "dentists-orthodontists",
        "orthodontist"
    ],
    "sg:website":"www.casthelyortho.com",
    "wof:name":"Casthely Lucie F DMD Ms",
    "wof:placetype":"venue"
},
  "geometry": {"coordinates":[-80.173267,25.944574],"type":"Point"}
}