{
  "type": "Feature",
  "properties": {
    "iso:country":"US",
    "sg:address":"535 Massachusetts Ave",
    "sg:city":"Pensacola",
    "sg:classifiers":[
        {
            "category":"Wholesale",
            "subcategory":"Construction Materials",
            "type":"Manufacturing & Wholesale Goods"
        }
    ],
    "sg:phone":"+1 850 438 1129",
    "sg:postcode":"32505",
    "sg:province":"FL",
    "sg:tags":[
        "industrial"
    ],
    "wof:name":"Jeh Eagle",
    "wof:placetype":"venue"
},
  "geometry": {"coordinates":[-87.25133700000001,30.45521],"type":"Point"}
}