{
  "type": "Feature",
  "properties": {
    "addr:full":"9753 S Orange Blossom Trl Orlando FL 32837",
    "addr:housenumber":"9753",
    "addr:postcode":"32837",
    "addr:street":"S Orange Blossom Trl",
    "iso:country":"US",
    "sg:address":"9753 S Orange Blossom Trl",
    "sg:city":"Orlando",
    "sg:classifiers":[
        {
            "category":"Professional",
            "subcategory":"Lawyer & Legal Services",
            "type":"Services"
        }
    ],
    "sg:phone":"+1 407 852 1148",
    "sg:postcode":"32837",
    "sg:province":"FL",
    "wof:name":"Jimenez & Associates PA",
    "wof:placetype":"venue"
},
  "geometry": {"coordinates":[-81.404636,28.424361],"type":"Point"}
}