{
  "type": "Feature",
  "properties": {
    "iso:country":"US",
    "sg:address":"2604 W Azeele St",
    "sg:city":"Tampa",
    "sg:classifiers":[
        {
            "category":"Social Services",
            "type":"Services"
        }
    ],
    "sg:phone":"+1 813 872 7186",
    "sg:postcode":"33609",
    "sg:province":"FL",
    "sg:tags":[
        "counseling"
    ],
    "wof:name":"Samaritan Counseling Ctr",
    "wof:placetype":"venue"
},
  "geometry": {"coordinates":[-82.487067,27.941035],"type":"Point"}
}