{
  "type": "Feature",
  "properties": {
    "addr:full":"27429 Sugar Loaf Dr Zephyrhills FL 33544",
    "addr:housenumber":"27429",
    "addr:postcode":"33544",
    "addr:street":"Sugar Loaf Dr",
    "iso:country":"US",
    "sg:address":"27429 Sugar Loaf Dr",
    "sg:city":"Zephyrhills",
    "sg:classifiers":[
        {
            "category":"Banks & Credit Unions",
            "subcategory":"Bank",
            "type":"Services"
        }
    ],
    "sg:phone":"+1 813 929 1748",
    "sg:postcode":"33544",
    "sg:province":"FL",
    "sg:tags":[
        "loan",
        "broker"
    ],
    "wof:name":"Extreme Realty & Mortgage",
    "wof:placetype":"venue"
},
  "geometry": {"coordinates":[-82.363955,28.183457],"type":"Point"}
}