{
  "type": "Feature",
  "properties": {
    "iso:country":"US",
    "sg:address":"5805 Atlantic Blvd",
    "sg:city":"Jacksonville",
    "sg:classifiers":[
        {
            "category":"Retail",
            "subcategory":"Repair Shop",
            "type":"Services"
        }
    ],
    "sg:phone":"+1 904 725 4163",
    "sg:postcode":"32207",
    "sg:province":"FL",
    "sg:tags":[
        "upholsterer"
    ],
    "wof:name":"Lee's Upholstery",
    "wof:placetype":"venue"
},
  "geometry": {"coordinates":[-81.604007,30.312589],"type":"Point"}
}