{
  "type": "Feature",
  "properties": {
    "iso:country":"US",
    "sg:address":"200 24th Ave N",
    "sg:city":"Indian Rocks Beach",
    "sg:classifiers":[
        {
            "category":"Organizations",
            "subcategory":"Religious Organization",
            "type":"Services"
        }
    ],
    "sg:phone":"+1 727 595 1038",
    "sg:postcode":"33785",
    "sg:province":"FL",
    "wof:name":"Church of The Isles Inc",
    "wof:placetype":"venue"
},
  "geometry": {"coordinates":[-82.84460199999999,27.905597],"type":"Point"}
}