{
  "type": "Feature",
  "properties": {
    "iso:country":"US",
    "sg:address":"6820 W Hillsborough Ave",
    "sg:city":"Tampa",
    "sg:classifiers":[
        {
            "category":"Real Estate",
            "subcategory":"Real Estate Operator",
            "type":"Services"
        }
    ],
    "sg:phone":"+1 813 290 0796",
    "sg:postcode":"33634",
    "sg:province":"FL",
    "sg:tags":[
        "apartment",
        "community"
    ],
    "wof:name":"Archstone Rocky Creek",
    "wof:placetype":"venue"
},
  "geometry": {"coordinates":[-82.555216,27.996459],"type":"Point"}
}