{
  "type": "Feature",
  "properties": {
    "addr:full":"2494 Lake Debra Dr Orlando FL 32835",
    "addr:housenumber":"2494",
    "addr:postcode":"32835",
    "addr:street":"Lake Debra Dr",
    "iso:country":"US",
    "sg:address":"2494 Lake Debra Dr",
    "sg:city":"Orlando",
    "sg:classifiers":[
        {
            "category":"Education",
            "subcategory":"Dance Studio",
            "type":"Public Place"
        }
    ],
    "sg:phone":"+1 407 298 5906",
    "sg:postcode":"32835",
    "sg:province":"FL",
    "wof:name":"Streetstylz",
    "wof:placetype":"venue"
},
  "geometry": {"coordinates":[-81.478021,28.515298],"type":"Point"}
}