{
  "type": "Feature",
  "properties": {
    "addr:full":"321 E Boca Raton Rd Boca Raton FL 33432",
    "addr:housenumber":"321",
    "addr:postcode":"33432",
    "addr:street":"E Boca Raton Rd",
    "iso:country":"US",
    "sg:address":"321 E Boca Raton Rd",
    "sg:city":"Boca Raton",
    "sg:classifiers":[
        {
            "category":"Building & Trades",
            "subcategory":"Plumbing",
            "type":"Services"
        }
    ],
    "sg:phone":"+1 561 833 5066",
    "sg:postcode":"33432",
    "sg:province":"FL",
    "sg:tags":[
        "contractor"
    ],
    "wof:name":"A Beyers Plumbing",
    "wof:placetype":"venue"
},
  "geometry": {"coordinates":[-80.080012,26.351563],"type":"Point"}
}