{
  "type": "Feature",
  "properties": {
    "iso:country":"US",
    "sg:address":"3000 S Red Rd",
    "sg:city":"Miami",
    "sg:classifiers":[
        {
            "category":"Restaurant",
            "type":"Food & Drink"
        }
    ],
    "sg:menulink":"http://www.allmenus.com/fl/miami/51212-red-bird-diner/menu/",
    "sg:phone":"+1 305 740 3277",
    "sg:postcode":"33155",
    "sg:province":"FL",
    "sg:tags":[
        "american"
    ],
    "wof:name":"Red Bird Diner",
    "wof:placetype":"venue"
},
  "geometry": {"coordinates":[-80.287244,25.742879],"type":"Point"}
}