{
  "type": "Feature",
  "properties": {
    "iso:country":"US",
    "sg:address":"5903 Anderson Rd",
    "sg:city":"Tampa",
    "sg:classifiers":[
        {
            "category":"Autos & Motor Vehicles",
            "subcategory":"Auto Supplies",
            "type":"Retail Goods"
        }
    ],
    "sg:phone":"+1 813 890 8473",
    "sg:postcode":"33634",
    "sg:province":"FL",
    "sg:tags":[
        "tire"
    ],
    "wof:name":"Mc Gee Tire Stores",
    "wof:placetype":"venue"
},
  "geometry": {"coordinates":[-82.52744800000001,28.002066],"type":"Point"}
}