{
  "type": "Feature",
  "properties": {
    "iso:country":"US",
    "sg:address":"7360 Coral Way Ste 7",
    "sg:city":"Miami",
    "sg:classifiers":[
        {
            "category":"Health Services",
            "subcategory":"Health Practitioner",
            "type":"Services"
        }
    ],
    "sg:phone":"+1 305 267 4560",
    "sg:postcode":"33155",
    "sg:province":"FL",
    "sg:tags":[
        "acupuncture"
    ],
    "wof:name":"T C M Physicians Inc",
    "wof:placetype":"venue"
},
  "geometry": {"coordinates":[-80.314903,25.747999],"type":"Point"}
}