{
  "type": "Feature",
  "properties": {
    "iso:country":"US",
    "sg:address":"4811 W Atlantic Ave",
    "sg:city":"Delray Beach",
    "sg:classifiers":[
        {
            "category":"Health Services",
            "subcategory":"Chiropractor",
            "type":"Services"
        }
    ],
    "sg:phone":"+1 561 496 7106",
    "sg:postcode":"33445",
    "sg:province":"FL",
    "wof:name":"Jarecki Chiropractic Center",
    "wof:placetype":"venue"
},
  "geometry": {"coordinates":[-80.11922199999999,26.457923],"type":"Point"}
}