{
  "type": "Feature",
  "properties": {
    "iso:country":"US",
    "sg:address":"1032 Marlin Lakes Cir",
    "sg:city":"Sarasota",
    "sg:classifiers":[
        {
            "category":"Building & Trades",
            "subcategory":"Equipment Rental",
            "type":"Services"
        }
    ],
    "sg:phone":"+1 941 343 0370",
    "sg:postcode":"34232",
    "sg:province":"FL",
    "sg:tags":[
        "party",
        "supply"
    ],
    "wof:name":"Party Jumpers Moon Walks",
    "wof:placetype":"venue"
},
  "geometry": {"coordinates":[-82.44761200000001,27.345473],"type":"Point"}
}