{
  "type": "Feature",
  "properties": {
    "iso:country":"US",
    "sg:address":"1801 S US Hwy 1",
    "sg:city":"Jupiter",
    "sg:classifiers":[
        {
            "category":"Wholesale",
            "subcategory":"Apparel",
            "type":"Manufacturing & Wholesale Goods"
        }
    ],
    "sg:phone":"+1 561 575 4345",
    "sg:postcode":"33477",
    "sg:province":"FL",
    "sg:tags":[
        "clothing",
        "eating"
    ],
    "wof:name":"Cha Cha Bags",
    "wof:placetype":"venue"
},
  "geometry": {"coordinates":[-80.07189700000001,26.916064],"type":"Point"}
}