{
  "type": "Feature",
  "properties": {
    "iso:country":"US",
    "sg:address":"150 Marion Way",
    "sg:city":"Maitland",
    "sg:classifiers":[
        {
            "category":"Shopping",
            "subcategory":"Computers & Home Electronics",
            "type":"Retail Goods"
        }
    ],
    "sg:phone":"+1 407 647 1906",
    "sg:postcode":"32751",
    "sg:province":"FL",
    "sg:tags":[
        "equipment",
        "video",
        "supply"
    ],
    "wof:name":"Zotz Enterprises",
    "wof:placetype":"venue"
},
  "geometry": {"coordinates":[-81.364481,28.634863],"type":"Point"}
}