{
  "type": "Feature",
  "properties": {
    "iso:country":"US",
    "sg:address":"1801 W Hibiscus Blvd",
    "sg:city":"Melbourne",
    "sg:classifiers":[
        {
            "category":"Banks & Credit Unions",
            "subcategory":"Bank",
            "type":"Services"
        }
    ],
    "sg:phone":"+1 321 984 4115",
    "sg:postcode":"32901",
    "sg:province":"FL",
    "sg:tags":[
        "state",
        "commercial"
    ],
    "wof:name":"Colonial Bank",
    "wof:placetype":"venue"
},
  "geometry": {"coordinates":[-80.654566,28.0855],"type":"Point"}
}