{
  "type": "Feature",
  "properties": {
    "addr:full":"12500 SW 130th St Ste 8 Miami FL 33186",
    "addr:housenumber":"12500",
    "addr:postcode":"33186",
    "addr:street":"Sw 130Th St Ste 8",
    "iso:country":"US",
    "sg:address":"12500 SW 130th St Ste 8",
    "sg:city":"Miami",
    "sg:classifiers":[
        {
            "category":"Retail",
            "subcategory":"Auto Repair",
            "type":"Services"
        }
    ],
    "sg:phone":"+1 305 233 1603",
    "sg:postcode":"33186",
    "sg:province":"FL",
    "sg:tags":[
        "body",
        "shop"
    ],
    "wof:name":"Lex Collision Inc",
    "wof:placetype":"venue"
},
  "geometry": {"coordinates":[-80.396725,25.646845],"type":"Point"}
}