{
  "type": "Feature",
  "properties": {
    "iso:country":"US",
    "sg:address":"107 Shadeville Rd",
    "sg:city":"Crawfordville",
    "sg:classifiers":[
        {
            "category":"Place Of Worship",
            "subcategory":"Church",
            "type":"Public Place"
        },
        {
            "category":"Place Of Worship",
            "type":"Public Place"
        }
    ],
    "sg:phone":"+1 850 926 3638",
    "sg:postcode":"32327",
    "sg:province":"FL",
    "sg:tags":[
        "churches-seventh-day",
        "adventist",
        "christian",
        "churches-advent"
    ],
    "sg:website":"http://www.adventist.org",
    "wof:name":"Seventh Day Adventist Church",
    "wof:placetype":"venue"
},
  "geometry": {"coordinates":[-84.371544,30.180237],"type":"Point"}
}