{
  "type": "Feature",
  "properties": {
    "iso:country":"US",
    "sg:address":"1842 Travelers Palm Dr",
    "sg:city":"Edgewater",
    "sg:classifiers":[
        {
            "category":"Building & Trades",
            "subcategory":"Construction",
            "type":"Services"
        }
    ],
    "sg:phone":"+1 386 427 0411",
    "sg:postcode":"32141",
    "sg:province":"FL",
    "sg:tags":[
        "home",
        "builder"
    ],
    "wof:name":"Maronda Homes Fl Shores",
    "wof:placetype":"venue"
},
  "geometry": {"coordinates":[-80.912604,28.964347],"type":"Point"}
}