{
  "type": "Feature",
  "properties": {
    "iso:country":"US",
    "sg:address":"10105 Amberwood Rd",
    "sg:city":"Fort Myers",
    "sg:classifiers":[
        {
            "category":"Building & Trades",
            "subcategory":"Pest Control",
            "type":"Services"
        }
    ],
    "sg:phone":"+1 239 332 1332",
    "sg:postcode":"33913",
    "sg:province":"FL",
    "wof:name":"Preven Tech Commercial Pest",
    "wof:placetype":"venue"
},
  "geometry": {"coordinates":[-81.7878,26.564786],"type":"Point"}
}