{
  "type": "Feature",
  "properties": {
    "iso:country":"US",
    "sg:address":"11850 NW 20th Ct",
    "sg:city":"Fort Lauderdale",
    "sg:classifiers":[
        {
            "category":"Shopping",
            "subcategory":"Music",
            "type":"Retail Goods"
        }
    ],
    "sg:phone":"+1 954 452 0668",
    "sg:postcode":"33323",
    "sg:province":"FL",
    "wof:name":"Chico Records",
    "wof:placetype":"venue"
},
  "geometry": {"coordinates":[-80.313176,26.151813],"type":"Point"}
}