{
  "type": "Feature",
  "properties": {
    "addr:full":"2655 NW 42nd Ave Miami FL 33142",
    "addr:housenumber":"2655",
    "addr:postcode":"33142",
    "addr:street":"Nw 42Nd Ave",
    "iso:country":"US",
    "sg:address":"2655 NW 42nd Ave",
    "sg:city":"Miami",
    "sg:classifiers":[
        {
            "category":"Building & Trades",
            "subcategory":"Construction",
            "type":"Services"
        }
    ],
    "sg:phone":"+1 305 779 4950",
    "sg:postcode":"33142",
    "sg:province":"FL",
    "sg:tags":[
        "elevator"
    ],
    "wof:name":"Servas USA Elevator",
    "wof:placetype":"venue"
},
  "geometry": {"coordinates":[-80.264376,25.799833],"type":"Point"}
}