{
  "type": "Feature",
  "properties": {
    "iso:country":"US",
    "sg:address":"144 E Center Ave",
    "sg:city":"Sebring",
    "sg:classifiers":[
        {
            "category":"Professional",
            "subcategory":"Lawyer & Legal Services",
            "type":"Services"
        }
    ],
    "sg:phone":"+1 863 471 9662",
    "sg:postcode":"33870",
    "sg:province":"FL",
    "sg:tags":[
        "attorney"
    ],
    "wof:name":"W James Kelly Trial Attorneys",
    "wof:placetype":"venue"
},
  "geometry": {"coordinates":[-81.439395,27.496312],"type":"Point"}
}