{
  "type": "Feature",
  "properties": {
    "addr:full":"26 NE 15th St Homestead FL 33030",
    "addr:housenumber":"26",
    "addr:postcode":"33030",
    "addr:street":"Ne 15Th St",
    "iso:country":"US",
    "sg:address":"26 NE 15th St",
    "sg:city":"Homestead",
    "sg:classifiers":[
        {
            "category":"Shopping",
            "subcategory":"Gifts & Souvenirs",
            "type":"Retail Goods"
        }
    ],
    "sg:phone":"+1 305 248 0481",
    "sg:postcode":"33030",
    "sg:province":"FL",
    "sg:tags":[
        "shop",
        "interior",
        "decorating"
    ],
    "wof:name":"Enchantables",
    "wof:placetype":"venue"
},
  "geometry": {"coordinates":[-80.476646,25.484393],"type":"Point"}
}