{
  "type": "Feature",
  "properties": {
    "addr:full":"11326 Distribution Ave W Jacksonville FL 32256",
    "addr:housenumber":"11326",
    "addr:postcode":"32256",
    "addr:street":"Distribution Ave W",
    "iso:country":"US",
    "sg:address":"11326 Distribution Ave W",
    "sg:city":"Jacksonville",
    "sg:classifiers":[
        {
            "category":"Wholesale",
            "subcategory":"Machinery & Supplies",
            "type":"Manufacturing & Wholesale Goods"
        }
    ],
    "sg:phone":"+1 904 268 3030",
    "sg:postcode":"32256",
    "sg:province":"FL",
    "sg:tags":[
        "sprinkler"
    ],
    "wof:name":"Wayne Automatic Fire Sprnklrs",
    "wof:placetype":"venue"
},
  "geometry": {"coordinates":[-81.534279,30.164049],"type":"Point"}
}