{
  "type": "Feature",
  "properties": {
    "addr:full":"4039 W Kennedy Blvd Tampa FL 33609",
    "addr:housenumber":"4039",
    "addr:postcode":"33609",
    "addr:street":"W Kennedy Blvd",
    "iso:country":"US",
    "sg:address":"4039 W Kennedy Blvd",
    "sg:city":"Tampa",
    "sg:classifiers":[
        {
            "category":"Banks & Credit Unions",
            "subcategory":"Bank",
            "type":"Services"
        }
    ],
    "sg:phone":"+1 813 289 9741",
    "sg:postcode":"33609",
    "sg:province":"FL",
    "sg:tags":[
        "personal",
        "institution"
    ],
    "wof:name":"Associates Financial",
    "wof:placetype":"venue"
},
  "geometry": {"coordinates":[-82.511841,27.944905],"type":"Point"}
}