{
  "type": "Feature",
  "properties": {
    "addr:full":"1028 Hinton St Port Charlotte FL 33952",
    "addr:housenumber":"1028",
    "addr:postcode":"33952",
    "addr:street":"Hinton St",
    "iso:country":"US",
    "sg:address":"1028 Hinton St",
    "sg:city":"Port Charlotte",
    "sg:classifiers":[
        {
            "category":"Shopping",
            "type":"Retail Goods"
        }
    ],
    "sg:phone":"+1 941 235 7300",
    "sg:postcode":"33952",
    "sg:province":"FL",
    "sg:tags":[
        "equipment",
        "telephone",
        "supply"
    ],
    "wof:name":"Darryle Greene Enterprises",
    "wof:placetype":"venue"
},
  "geometry": {"coordinates":[-82.10906799999999,27.017234],"type":"Point"}
}