{
  "type": "Feature",
  "properties": {
    "iso:country":"US",
    "sg:address":"8710 Garden Way Rd",
    "sg:city":"Groveland",
    "sg:classifiers":[
        {
            "category":"Building & Trades",
            "subcategory":"Landscaping Services",
            "type":"Services"
        }
    ],
    "sg:phone":"+1 352 429 8008",
    "sg:postcode":"34736",
    "sg:province":"FL",
    "wof:name":"Luis F Avalos Lawn Care",
    "wof:placetype":"venue"
},
  "geometry": {"coordinates":[-81.810278,28.630342],"type":"Point"}
}