{
  "type": "Feature",
  "properties": {
    "iso:country":"US",
    "sg:address":"753 SE 21st Ave",
    "sg:city":"Deerfield Beach",
    "sg:classifiers":[
        {
            "category":"Building & Trades",
            "subcategory":"Construction",
            "type":"Services"
        }
    ],
    "sg:phone":"+1 954 427 8608",
    "sg:postcode":"33441",
    "sg:province":"FL",
    "sg:tags":[
        "carpentry",
        "contractor"
    ],
    "wof:name":"Steve Boyce",
    "wof:placetype":"venue"
},
  "geometry": {"coordinates":[-80.07657399999999,26.307079],"type":"Point"}
}