{
  "type": "Feature",
  "properties": {
    "iso:country":"US",
    "sg:address":"700 S Federal Hwy",
    "sg:city":"Deerfield Beach",
    "sg:classifiers":[
        {
            "category":"Sports & Exercise",
            "subcategory":"Gym",
            "type":"Entertainment"
        }
    ],
    "sg:phone":"+1 954 798 0111",
    "sg:postcode":"33441",
    "sg:province":"FL",
    "sg:tags":[
        "club",
        "health",
        "studio",
        "gymnasium"
    ],
    "wof:name":"Simply Fit",
    "wof:placetype":"venue"
},
  "geometry": {"coordinates":[-80.09224,26.308905],"type":"Point"}
}