{
  "type": "Feature",
  "properties": {
    "iso:country":"US",
    "sg:address":"4922 Tall Pine Dr",
    "sg:city":"Marianna",
    "sg:classifiers":[
        {
            "category":"Arts & Performance",
            "subcategory":"Theater",
            "type":"Entertainment"
        }
    ],
    "sg:phone":"+1 850 272 1384",
    "sg:postcode":"32446",
    "sg:province":"FL",
    "sg:tags":[
        "theatrical"
    ],
    "wof:name":"C & R Productions",
    "wof:placetype":"venue"
},
  "geometry": {"coordinates":[-85.184349,30.79987],"type":"Point"}
}