{
  "type": "Feature",
  "properties": {
    "iso:country":"US",
    "sg:address":"2639 SW 32nd Ct",
    "sg:city":"Miami",
    "sg:classifiers":[
        {
            "category":"Manufacturing",
            "subcategory":"Tobacco Products",
            "type":"Manufacturing & Wholesale Goods"
        }
    ],
    "sg:phone":"+1 786 942 1382",
    "sg:postcode":"33133",
    "sg:province":"FL",
    "sg:tags":[
        "cigarette",
        "cigar",
        "manufacturer",
        "tobacco-wholesale"
    ],
    "wof:name":"Acope Dominican Cigar Inc",
    "wof:placetype":"venue"
},
  "geometry": {"coordinates":[-80.24706,25.742605],"type":"Point"}
}