{
  "type": "Feature",
  "properties": {
    "addr:full":"23781 US Hwy 27  Suite 332 Lake Wales FL 33859",
    "addr:housenumber":"23781",
    "addr:postcode":"33859",
    "addr:street":"Us Hwy 27 Suite 332",
    "iso:country":"US",
    "sg:address":"23781 US Hwy 27  Suite 332",
    "sg:city":"Lake Wales",
    "sg:classifiers":[
        {
            "category":"Professional",
            "subcategory":"Computer Services",
            "type":"Services"
        }
    ],
    "sg:phone":"+1 863 837 1032",
    "sg:postcode":"33859",
    "sg:province":"FL",
    "sg:tags":[
        "web-design",
        "flash-web-design",
        "ecommerce",
        "custom-web-site-development",
        "web-hosting",
        "php-web-development"
    ],
    "sg:website":"http://www.emmausdesigns.com",
    "wof:name":"Emmaus Designs",
    "wof:placetype":"venue"
},
  "geometry": {"coordinates":[-81.62187400000001,27.956545],"type":"Point"}
}