{
  "type": "Feature",
  "properties": {
    "iso:country":"US",
    "sg:address":"235 City Point Rd",
    "sg:city":"Cocoa",
    "sg:classifiers":[
        {
            "category":"Health Services",
            "subcategory":"Dentist",
            "type":"Services"
        }
    ],
    "sg:phone":"+1 321 504 7575",
    "sg:postcode":"32926",
    "sg:province":"FL",
    "wof:name":"Dennis Gollehon Pa",
    "wof:placetype":"venue"
},
  "geometry": {"coordinates":[-80.750157,28.40585],"type":"Point"}
}