{
  "type": "Feature",
  "properties": {
    "iso:country":"US",
    "sg:address":"309 SE Osceola St",
    "sg:city":"Stuart",
    "sg:classifiers":[
        {
            "category":"Organizations",
            "subcategory":"Professional Association",
            "type":"Services"
        }
    ],
    "sg:phone":"+1 772 287 1750",
    "sg:postcode":"34994",
    "sg:province":"FL",
    "wof:name":"Physicians Conference Assoc",
    "wof:placetype":"venue"
},
  "geometry": {"coordinates":[-80.248811,27.198515],"type":"Point"}
}