{
  "type": "Feature",
  "properties": {
    "iso:country":"US",
    "sg:address":"4388 Pendola Point Rd",
    "sg:city":"Tampa",
    "sg:classifiers":[
        {
            "category":"Mining & Drilling",
            "type":"Manufacturing & Wholesale Goods"
        }
    ],
    "sg:phone":"+1 813 248 2074",
    "sg:postcode":"33619",
    "sg:province":"FL",
    "wof:name":"Gulf Sulphur Svc",
    "wof:placetype":"venue"
},
  "geometry": {"coordinates":[-82.405659,27.901165],"type":"Point"}
}