{
  "type": "Feature",
  "properties": {
    "iso:country":"US",
    "sg:address":"2810 Concord Rd",
    "sg:city":"De Land",
    "sg:classifiers":[
        {
            "category":"Real Estate",
            "subcategory":"Developer",
            "type":"Services"
        }
    ],
    "sg:phone":"+1 386 738 2844",
    "sg:postcode":"32720",
    "sg:province":"FL",
    "wof:name":"Norris & Ewen Development",
    "wof:placetype":"venue"
},
  "geometry": {"coordinates":[-81.322953,29.077945],"type":"Point"}
}