{
  "type": "Feature",
  "properties": {
    "iso:country":"US",
    "sg:address":"2193 SE Opal Way",
    "sg:city":"Stuart",
    "sg:classifiers":[
        {
            "category":"Shopping",
            "subcategory":"Pets & Pet Supplies",
            "type":"Retail Goods"
        }
    ],
    "sg:phone":"+1 772 286 3232",
    "sg:postcode":"34997",
    "sg:province":"FL",
    "sg:tags":[
        "food",
        "store"
    ],
    "wof:name":"City Dog",
    "wof:placetype":"venue"
},
  "geometry": {"coordinates":[-80.224149,27.1446],"type":"Point"}
}