{
  "type": "Feature",
  "properties": {
    "addr:full":"5731 Commonwealth Ave Jacksonville FL 32254",
    "addr:housenumber":"5731",
    "addr:postcode":"32254",
    "addr:street":"Commonwealth Ave",
    "iso:country":"US",
    "sg:address":"5731 Commonwealth Ave",
    "sg:city":"Jacksonville",
    "sg:classifiers":[
        {
            "category":"Autos & Motor Vehicles",
            "subcategory":"Auto Supplies",
            "type":"Retail Goods"
        }
    ],
    "sg:phone":"+1 904 378 1220",
    "sg:postcode":"32254",
    "sg:province":"FL",
    "sg:tags":[
        "equipment",
        "air",
        "conditioning",
        "automobile"
    ],
    "wof:name":"Truck Gen & Air Svc Inc",
    "wof:placetype":"venue"
},
  "geometry": {"coordinates":[-81.744012,30.336018],"type":"Point"}
}