{
  "type": "Feature",
  "properties": {
    "iso:country":"US",
    "sg:address":"203 SE 1st Ave",
    "sg:city":"Boca Raton",
    "sg:classifiers":[
        {
            "category":"Personal",
            "subcategory":"Beauty Salon",
            "type":"Services"
        }
    ],
    "sg:phone":"+1 561 395 4450",
    "sg:postcode":"33432",
    "sg:province":"FL",
    "wof:name":"Gents Barber Shop",
    "wof:placetype":"venue"
},
  "geometry": {"coordinates":[-80.085752,26.34746],"type":"Point"}
}