{
  "type": "Feature",
  "properties": {
    "iso:country":"US",
    "sg:address":"6843 State Rd 54",
    "sg:city":"New Port Richey",
    "sg:classifiers":[
        {
            "category":"Wholesale",
            "subcategory":"Books, Periodicals, & Newspapers",
            "type":"Manufacturing & Wholesale Goods"
        },
        {
            "category":"Shopping",
            "subcategory":"Books",
            "type":"Retail Goods"
        }
    ],
    "sg:phone":"+1 727 844 0888",
    "sg:postcode":"34653",
    "sg:province":"FL",
    "sg:tags":[
        "comic"
    ],
    "wof:name":"Yancy Street Comics Inc",
    "wof:placetype":"venue"
},
  "geometry": {"coordinates":[-82.701532,28.217045],"type":"Point"}
}