{
  "type": "Feature",
  "properties": {
    "iso:country":"US",
    "sg:address":"7314 Ox Bow Cir",
    "sg:city":"Tallahassee",
    "sg:classifiers":[
        {
            "category":"Home & Garden",
            "subcategory":"Home Furnishings",
            "type":"Retail Goods"
        },
        {
            "category":"Real Estate",
            "subcategory":"Architect",
            "type":"Services"
        }
    ],
    "sg:phone":"+1 850 668 3652",
    "sg:postcode":"32312",
    "sg:province":"FL",
    "sg:tags":[
        "planning",
        "residential",
        "designer",
        "design"
    ],
    "wof:name":"Francis Lee Residential Design",
    "wof:placetype":"venue"
},
  "geometry": {"coordinates":[-84.253118,30.558041],"type":"Point"}
}