{
  "type": "Feature",
  "properties": {
    "iso:country":"US",
    "sg:address":"3435 S Orange Ave",
    "sg:city":"Orlando",
    "sg:classifiers":[
        {
            "category":"Social Services",
            "subcategory":"Child Care",
            "type":"Services"
        }
    ],
    "sg:phone":"+1 407 852 6375",
    "sg:postcode":"32806",
    "sg:province":"FL",
    "wof:name":"Mommy's Little Angels Daycare",
    "wof:placetype":"venue"
},
  "geometry": {"coordinates":[-81.376186,28.504745],"type":"Point"}
}