{
  "type": "Feature",
  "properties": {
    "addr:full":"3800 Hickory Ln Saint Augustine FL 32086",
    "addr:housenumber":"3800",
    "addr:postcode":"32086",
    "addr:street":"Hickory Ln",
    "iso:country":"US",
    "sg:address":"3800 Hickory Ln",
    "sg:city":"Saint Augustine",
    "sg:classifiers":[
        {
            "category":"Professional",
            "subcategory":"Business Services",
            "type":"Services"
        }
    ],
    "sg:phone":"+1 904 794 0731",
    "sg:postcode":"32086",
    "sg:province":"FL",
    "wof:name":"Don Capo & Son Marine Service",
    "wof:placetype":"venue"
},
  "geometry": {"coordinates":[-81.31527699999999,29.825415],"type":"Point"}
}