{
  "type": "Feature",
  "properties": {
    "addr:full":"1795 SW 8th St Miami FL 33135",
    "addr:housenumber":"1795",
    "addr:postcode":"33135",
    "addr:street":"Sw 8Th St",
    "iso:country":"US",
    "sg:address":"1795 SW 8th St",
    "sg:city":"Miami",
    "sg:classifiers":[
        {
            "category":"Shopping",
            "subcategory":"Department Store",
            "type":"Retail Goods"
        }
    ],
    "sg:phone":"+1 305 541 4081",
    "sg:postcode":"33135",
    "sg:province":"FL",
    "sg:tags":[
        "variety"
    ],
    "sg:website":"http://www.familydollar.com",
    "wof:name":"Family Dollar Stores",
    "wof:placetype":"venue"
},
  "geometry": {"coordinates":[-80.224501,25.765581],"type":"Point"}
}