{
  "type": "Feature",
  "properties": {
    "addr:full":"141 Giralda Blvd NE Saint Petersburg FL 33704",
    "addr:housenumber":"141",
    "addr:postcode":"33704",
    "addr:street":"Giralda Blvd Ne",
    "iso:country":"US",
    "sg:address":"141 Giralda Blvd NE",
    "sg:city":"Saint Petersburg",
    "sg:classifiers":[
        {
            "category":"Manufacturing",
            "subcategory":"Rubber & Plastics",
            "type":"Manufacturing & Wholesale Goods"
        }
    ],
    "sg:phone":"+1 727 744 6664",
    "sg:postcode":"33704",
    "sg:province":"FL",
    "sg:tags":[
        "product",
        "mfg"
    ],
    "wof:name":"J K Industries",
    "wof:placetype":"venue"
},
  "geometry": {"coordinates":[-82.61306399999999,27.792743],"type":"Point"}
}