{
  "type": "Feature",
  "properties": {
    "addr:full":"340 10th St Lake Park FL 33403",
    "addr:housenumber":"340",
    "addr:postcode":"33403",
    "addr:street":"10Th St",
    "iso:country":"US",
    "sg:address":"340 10th St",
    "sg:city":"Lake Park",
    "sg:classifiers":[
        {
            "category":"Real Estate",
            "subcategory":"Real Estate Agent",
            "type":"Services"
        }
    ],
    "sg:phone":"+1 561 863 1592",
    "sg:postcode":"33403",
    "sg:province":"FL",
    "wof:name":"Residential Rehab Inc",
    "wof:placetype":"venue"
},
  "geometry": {"coordinates":[-80.071889,26.796409],"type":"Point"}
}