{
  "type": "Feature",
  "properties": {
    "iso:country":"US",
    "sg:address":"8454 Springhill Rd",
    "sg:city":"Tallahassee",
    "sg:classifiers":[
        {
            "category":"Manufacturing",
            "subcategory":"Building Materials",
            "type":"Manufacturing & Wholesale Goods"
        }
    ],
    "sg:phone":"+1 850 575 2642",
    "sg:postcode":"32305",
    "sg:province":"FL",
    "sg:tags":[
        "mfg",
        "wood",
        "kitchen",
        "cabinet"
    ],
    "wof:name":"Rs Cabinets & Custom Woodwork",
    "wof:placetype":"venue"
},
  "geometry": {"coordinates":[-84.388119,30.33984],"type":"Point"}
}