{
  "type": "Feature",
  "properties": {
    "addr:full":"2925 Pga Blvd Palm Beach Gardens FL 33410",
    "addr:housenumber":"2925",
    "addr:postcode":"33410",
    "addr:street":"Pga Blvd",
    "iso:country":"US",
    "sg:address":"2925 Pga Blvd",
    "sg:city":"Palm Beach Gardens",
    "sg:classifiers":[
        {
            "category":"Banks & Credit Unions",
            "subcategory":"Investment Brokerage",
            "type":"Services"
        }
    ],
    "sg:phone":"+1 561 697 2424",
    "sg:postcode":"33410",
    "sg:province":"FL",
    "sg:tags":[
        "personal",
        "trust",
        "estate"
    ],
    "wof:name":"National City Bank Private",
    "wof:placetype":"venue"
},
  "geometry": {"coordinates":[-80.081791,26.844969],"type":"Point"}
}