{
  "type": "Feature",
  "properties": {
    "addr:full":"205 State Rd 434 W Winter Springs FL 32708",
    "addr:housenumber":"205",
    "addr:postcode":"32708",
    "addr:street":"State Rd 434 W",
    "iso:country":"US",
    "sg:address":"205 State Rd 434 W",
    "sg:city":"Winter Springs",
    "sg:classifiers":[
        {
            "category":"Organizations",
            "subcategory":"Religious Organization",
            "type":"Services"
        }
    ],
    "sg:phone":"+1 407 327 4467",
    "sg:postcode":"32708",
    "sg:province":"FL",
    "wof:name":"Greater Works Endtind Mnstrs",
    "wof:placetype":"venue"
},
  "geometry": {"coordinates":[-81.307912,28.69863],"type":"Point"}
}