{
  "type": "Feature",
  "properties": {
    "iso:country":"US",
    "sg:address":"2315 Johnson St",
    "sg:city":"Hollywood",
    "sg:classifiers":[
        {
            "category":"Building & Trades",
            "subcategory":"Plumbing",
            "type":"Services"
        }
    ],
    "sg:phone":"+1 954 923 2718",
    "sg:postcode":"33020",
    "sg:province":"FL",
    "sg:tags":[
        "contractor"
    ],
    "wof:name":"Hollywood Plumbing",
    "wof:placetype":"venue"
},
  "geometry": {"coordinates":[-80.154464,26.018748],"type":"Point"}
}