{
  "type": "Feature",
  "properties": {
    "addr:full":"1018 Oakus Dr Gulf Breeze FL 32583",
    "addr:housenumber":"1018",
    "addr:postcode":"32583",
    "addr:street":"Oakus Dr",
    "iso:country":"US",
    "sg:address":"1018 Oakus Dr",
    "sg:city":"Gulf Breeze",
    "sg:classifiers":[
        {
            "category":"Restaurant",
            "type":"Food & Drink"
        }
    ],
    "sg:phone":"+1 850 932 3978",
    "sg:postcode":"32583",
    "sg:province":"FL",
    "sg:tags":[
        "eating"
    ],
    "wof:name":"NY Knicks",
    "wof:placetype":"venue"
},
  "geometry": {"coordinates":[-87.088521,30.577636],"type":"Point"}
}