{
  "type": "Feature",
  "properties": {
    "iso:country":"US",
    "sg:address":"500 SE 17th St",
    "sg:city":"Fort Lauderdale",
    "sg:classifiers":[
        {
            "category":"Health Services",
            "subcategory":"Doctor",
            "type":"Services"
        }
    ],
    "sg:phone":"+1 954 764 2833",
    "sg:postcode":"33316",
    "sg:province":"FL",
    "sg:tags":[
        "medical"
    ],
    "wof:name":"P H Mulhern MD",
    "wof:placetype":"venue"
},
  "geometry": {"coordinates":[-80.137682,26.100239],"type":"Point"}
}