{
  "type": "Feature",
  "properties": {
    "iso:country":"US",
    "sg:address":"2376 Fruitville Rd",
    "sg:city":"Sarasota",
    "sg:classifiers":[
        {
            "category":"Real Estate",
            "subcategory":"Real Estate Agent",
            "type":"Services"
        }
    ],
    "sg:phone":"+1 941 953 2977",
    "sg:postcode":"34237",
    "sg:province":"FL",
    "wof:name":"New Homes Now Corp",
    "wof:placetype":"venue"
},
  "geometry": {"coordinates":[-82.52265800000001,27.337442],"type":"Point"}
}