{
  "type": "Feature",
  "properties": {
    "iso:country":"US",
    "sg:address":"20404 SW 160th St",
    "sg:city":"Miami",
    "sg:classifiers":[
        {
            "category":"Insurance",
            "subcategory":"Insurance Agent",
            "type":"Services"
        }
    ],
    "sg:phone":"+1 305 971 9293",
    "sg:postcode":"33187",
    "sg:province":"FL",
    "wof:name":"Green State Farm Landscaping",
    "wof:placetype":"venue"
},
  "geometry": {"coordinates":[-80.522684,25.615788],"type":"Point"}
}