{
  "type": "Feature",
  "properties": {
    "iso:country":"US",
    "sg:address":"8801 Tamiami Trl N",
    "sg:city":"Naples",
    "sg:classifiers":[
        {
            "category":"Health Services",
            "subcategory":"Doctor",
            "type":"Services"
        }
    ],
    "sg:phone":"+1 239 594 8108",
    "sg:postcode":"34108",
    "sg:province":"FL",
    "sg:tags":[
        "dentist"
    ],
    "wof:name":"Roger H Koslen DDS PA",
    "wof:placetype":"venue"
},
  "geometry": {"coordinates":[-81.801269,26.249605],"type":"Point"}
}