{
  "type": "Feature",
  "properties": {
    "iso:country":"US",
    "sg:address":"1360 W State Rd 40",
    "sg:city":"Pierson",
    "sg:classifiers":[
        {
            "category":"Restaurant",
            "type":"Food & Drink"
        }
    ],
    "sg:phone":"+1 386 749 1557",
    "sg:postcode":"32180",
    "sg:province":"FL",
    "sg:tags":[
        "eating"
    ],
    "wof:name":"Essex Seafood Two",
    "wof:placetype":"venue"
},
  "geometry": {"coordinates":[-81.505444,29.170511],"type":"Point"}
}