{
  "type": "Feature",
  "properties": {
    "addr:full":"5146 SW 3rd Ave Cape Coral FL 33914",
    "addr:housenumber":"5146",
    "addr:postcode":"33914",
    "addr:street":"Sw 3Rd Ave",
    "iso:country":"US",
    "sg:address":"5146 SW 3rd Ave",
    "sg:city":"Cape Coral",
    "sg:classifiers":[
        {
            "category":"Insurance",
            "subcategory":"Insurance Agent",
            "type":"Services"
        }
    ],
    "sg:phone":"+1 239 542 2455",
    "sg:postcode":"33914",
    "sg:province":"FL",
    "wof:name":"Philip J Shevlin",
    "wof:placetype":"venue"
},
  "geometry": {"coordinates":[-81.98121399999999,26.555339],"type":"Point"}
}