{
  "type": "Feature",
  "properties": {
    "iso:country":"US",
    "sg:address":"700 SW 98th Ln",
    "sg:city":"Ocala",
    "sg:classifiers":[
        {
            "category":"Professional",
            "subcategory":"Business Services",
            "type":"Services"
        }
    ],
    "sg:phone":"+1 352 694 1443",
    "sg:postcode":"34476",
    "sg:province":"FL",
    "sg:tags":[
        "process",
        "server"
    ],
    "wof:name":"Apex Process Svc",
    "wof:placetype":"venue"
},
  "geometry": {"coordinates":[-82.139306,29.07893],"type":"Point"}
}