{
  "type": "Feature",
  "properties": {
    "addr:full":"12671 Sandy Run Rd Jupiter FL 33478",
    "addr:housenumber":"12671",
    "addr:postcode":"33478",
    "addr:street":"Sandy Run Rd",
    "iso:country":"US",
    "sg:address":"12671 Sandy Run Rd",
    "sg:city":"Jupiter",
    "sg:classifiers":[
        {
            "category":"Manufacturing",
            "subcategory":"Watercraft",
            "type":"Manufacturing & Wholesale Goods"
        }
    ],
    "sg:phone":"+1 561 575 2806",
    "sg:postcode":"33478",
    "sg:province":"FL",
    "wof:name":"A & D Yacht Detailing",
    "wof:placetype":"venue"
},
  "geometry": {"coordinates":[-80.237078,26.9066],"type":"Point"}
}