{
  "type": "Feature",
  "properties": {
    "iso:country":"US",
    "sg:address":"6135 Everett St",
    "sg:city":"Naples",
    "sg:classifiers":[
        {
            "category":"Building & Trades",
            "subcategory":"Landscaping Services",
            "type":"Services"
        }
    ],
    "sg:phone":"+1 239 774 5324",
    "sg:postcode":"34112",
    "sg:province":"FL",
    "wof:name":"Fidalgo Lawn Service",
    "wof:placetype":"venue"
},
  "geometry": {"coordinates":[-81.712979,26.114724],"type":"Point"}
}