{
  "type": "Feature",
  "properties": {
    "iso:country":"US",
    "sg:address":"265 Durian Rd",
    "sg:city":"Venice",
    "sg:classifiers":[
        {
            "category":"Building & Trades",
            "subcategory":"Construction",
            "type":"Services"
        }
    ],
    "sg:phone":"+1 941 496 4896",
    "sg:postcode":"34293",
    "sg:province":"FL",
    "sg:tags":[
        "hanging",
        "contractor"
    ],
    "wof:name":"Gerald L Gordys Painting",
    "wof:placetype":"venue"
},
  "geometry": {"coordinates":[-82.41542,27.066752],"type":"Point"}
}