{
  "type": "Feature",
  "properties": {
    "iso:country":"US",
    "sg:address":"7544 Jacque Rd",
    "sg:city":"Hudson",
    "sg:classifiers":[
        {
            "category":"Health Services",
            "subcategory":"Doctor",
            "type":"Services"
        }
    ],
    "sg:phone":"+1 727 868 3048",
    "sg:postcode":"34667",
    "sg:province":"FL",
    "sg:tags":[
        "medical",
        "clinic"
    ],
    "wof:name":"The Center For Bone & Joint Disease",
    "wof:placetype":"venue"
},
  "geometry": {"coordinates":[-82.68922499999999,28.357847],"type":"Point"}
}