{
  "type": "Feature",
  "properties": {
    "addr:full":"15820 SW 98th Ct Miami FL 33157",
    "addr:housenumber":"15820",
    "addr:postcode":"33157",
    "addr:street":"Sw 98Th Ct",
    "iso:country":"US",
    "sg:address":"15820 SW 98th Ct",
    "sg:city":"Miami",
    "sg:classifiers":[
        {
            "category":"Building & Trades",
            "subcategory":"Locksmith",
            "type":"Services"
        }
    ],
    "sg:phone":"+1 786 718 1400",
    "sg:postcode":"33157",
    "sg:province":"FL",
    "sg:tags":[
        "key"
    ],
    "wof:name":"Am Pm Locksmith",
    "wof:placetype":"venue"
},
  "geometry": {"coordinates":[-80.352906,25.622528],"type":"Point"}
}