{
  "type": "Feature",
  "properties": {
    "iso:country":"US",
    "sg:address":"6425 SW 93rd Ave",
    "sg:city":"Miami",
    "sg:classifiers":[
        {
            "category":"Real Estate",
            "subcategory":"Real Estate Operator",
            "type":"Services"
        }
    ],
    "sg:phone":"+1 305 271 3446",
    "sg:postcode":"33173",
    "sg:province":"FL",
    "sg:tags":[
        "property",
        "lessor"
    ],
    "wof:name":"K Holding Corp",
    "wof:placetype":"venue"
},
  "geometry": {"coordinates":[-80.344358,25.707498],"type":"Point"}
}