{
  "type": "Feature",
  "properties": {
    "iso:country":"US",
    "sg:address":"971 E 13th St",
    "sg:city":"Hialeah",
    "sg:classifiers":[
        {
            "category":"Building & Trades",
            "subcategory":"Construction",
            "type":"Services"
        }
    ],
    "sg:phone":"+1 305 884 8155",
    "sg:postcode":"33010",
    "sg:province":"FL",
    "sg:tags":[
        "roofing",
        "industrial",
        "contractors-commercial",
        "contractor"
    ],
    "wof:name":"Sol Del Roofing Inc",
    "wof:placetype":"venue"
},
  "geometry": {"coordinates":[-80.261685,25.834321],"type":"Point"}
}