{
  "type": "Feature",
  "properties": {
    "iso:country":"US",
    "sg:address":"1305 SE 17th St",
    "sg:city":"Fort Lauderdale",
    "sg:classifiers":[
        {
            "category":"Restaurant",
            "type":"Food & Drink"
        }
    ],
    "sg:menulink":"http://www.allmenus.com/fl/fort-lauderdale/37885-kellys-landing/menu/",
    "sg:phone":"+1 954 760 7009",
    "sg:postcode":"33316",
    "sg:province":"FL",
    "sg:tags":[
        "seafood",
        "american"
    ],
    "wof:name":"Kelly's Landing",
    "wof:placetype":"venue"
},
  "geometry": {"coordinates":[-80.12960200000001,26.100459],"type":"Point"}
}