{
  "type": "Feature",
  "properties": {
    "addr:full":"3043 S Atlantic Ave Daytona Beach FL 32118",
    "addr:housenumber":"3043",
    "addr:postcode":"32118",
    "addr:street":"S Atlantic Ave",
    "iso:country":"US",
    "sg:address":"3043 S Atlantic Ave",
    "sg:city":"Daytona Beach",
    "sg:classifiers":[
        {
            "category":"Organizations",
            "subcategory":"Membership Organization",
            "type":"Services"
        }
    ],
    "sg:phone":"+1 386 760 6187",
    "sg:postcode":"32118",
    "sg:province":"FL",
    "wof:name":"Valentine J Sheedy",
    "wof:placetype":"venue"
},
  "geometry": {"coordinates":[-80.976422,29.164856],"type":"Point"}
}