{
  "type": "Feature",
  "properties": {
    "iso:country":"US",
    "sg:address":"7595 85th St",
    "sg:city":"Vero Beach",
    "sg:classifiers":[
        {
            "category":"Building & Trades",
            "subcategory":"Electrical",
            "type":"Services"
        }
    ],
    "sg:phone":"+1 772 564 2999",
    "sg:postcode":"32967",
    "sg:province":"FL",
    "sg:tags":[
        "electrical",
        "contractor"
    ],
    "wof:name":"Powerline Electric",
    "wof:placetype":"venue"
},
  "geometry": {"coordinates":[-80.47019,27.74859],"type":"Point"}
}