{
  "type": "Feature",
  "properties": {
    "addr:full":"6470 US Hwy 1 N St Augustine FL 32095",
    "addr:housenumber":"6470",
    "addr:postcode":"32095",
    "addr:street":"Us Hwy 1 N St",
    "iso:country":"US",
    "sg:address":"6470 US Hwy 1 N",
    "sg:city":"St Augustine",
    "sg:classifiers":[
        {
            "category":"Travel",
            "subcategory":"Hotels & Motels",
            "type":"Entertainment"
        }
    ],
    "sg:phone":"+1 904 823 1466",
    "sg:postcode":"32095",
    "sg:province":"FL",
    "wof:name":"English Village Motel",
    "wof:placetype":"venue"
},
  "geometry": {"coordinates":[-81.37252599999999,29.99085],"type":"Point"}
}