{
  "type": "Feature",
  "properties": {
    "addr:full":"900 New Warrington Rd Pensacola FL 32506",
    "addr:housenumber":"900",
    "addr:postcode":"32506",
    "addr:street":"New Warrington Rd",
    "iso:country":"US",
    "sg:address":"900 New Warrington Rd",
    "sg:city":"Pensacola",
    "sg:classifiers":[
        {
            "category":"Professional",
            "type":"Services"
        },
        {
            "category":"Retail",
            "subcategory":"Auto Rental",
            "type":"Services"
        },
        {
            "category":"Building & Trades",
            "subcategory":"Equipment Rental",
            "type":"Services"
        },
        {
            "category":"Retail",
            "subcategory":"Storage",
            "type":"Services"
        }
    ],
    "sg:phone":"+1 866 205 7339",
    "sg:postcode":"32506",
    "sg:province":"FL",
    "sg:tags":[
        "renting",
        "moving-self",
        "leasing",
        "material",
        "moving",
        "services-labor",
        "truck",
        "trailer"
    ],
    "sg:website":"http://www.pensketruckrental.com/personal_rental/?cid=Yptmlist",
    "wof:name":"Penske Truck Rental",
    "wof:placetype":"venue"
},
  "geometry": {"coordinates":[-87.273842,30.42351],"type":"Point"}
}