{
  "type": "Feature",
  "properties": {
    "iso:country":"US",
    "sg:address":"4692 NW 74th Ave",
    "sg:city":"Miami",
    "sg:classifiers":[
        {
            "category":"Professional",
            "subcategory":"Business Services",
            "type":"Services"
        },
        {
            "category":"Government",
            "subcategory":"Post Office",
            "type":"Public Place"
        }
    ],
    "sg:phone":"+1 305 477 6130",
    "sg:postcode":"33166",
    "sg:province":"FL",
    "sg:tags":[
        "delivery",
        "messenger",
        "courier"
    ],
    "wof:name":"International Courier Times",
    "wof:placetype":"venue"
},
  "geometry": {"coordinates":[-80.317419,25.816123],"type":"Point"}
}