{
  "type": "Feature",
  "properties": {
    "iso:country":"US",
    "sg:address":"7147 US Hwy 1",
    "sg:city":"Port St Lucie",
    "sg:classifiers":[
        {
            "category":"Building & Trades",
            "subcategory":"Construction",
            "type":"Services"
        }
    ],
    "sg:phone":"+1 772 344 0651",
    "sg:postcode":"34982",
    "sg:province":"FL",
    "sg:tags":[
        "resurfacing",
        "laying",
        "refinishing",
        "floor"
    ],
    "wof:name":"Affordable Flooring",
    "wof:placetype":"venue"
},
  "geometry": {"coordinates":[-80.324513,27.333048],"type":"Point"}
}