{
  "type": "Feature",
  "properties": {
    "iso:country":"US",
    "sg:address":"7801 85th St",
    "sg:city":"Vero Beach",
    "sg:classifiers":[
        {
            "category":"Social Services",
            "subcategory":"Child Care",
            "type":"Services"
        }
    ],
    "sg:phone":"+1 772 388 3085",
    "sg:postcode":"32967",
    "sg:province":"FL",
    "wof:name":"RCMA Children Home",
    "wof:placetype":"venue"
},
  "geometry": {"coordinates":[-80.486574,27.748642],"type":"Point"}
}