{
  "type": "Feature",
  "properties": {
    "addr:full":"1321 SW 107th Ave Miami FL 33174",
    "addr:housenumber":"1321",
    "addr:postcode":"33174",
    "addr:street":"Sw 107Th Ave",
    "iso:country":"US",
    "sg:address":"1321 SW 107th Ave",
    "sg:city":"Miami",
    "sg:classifiers":[
        {
            "category":"Health Services",
            "subcategory":"Hospital",
            "type":"Services"
        }
    ],
    "sg:phone":"+1 305 264 5147",
    "sg:postcode":"33174",
    "sg:province":"FL",
    "sg:tags":[
        "psychiatric"
    ],
    "wof:name":"Tgs Rehabilitation Service",
    "wof:placetype":"venue"
},
  "geometry": {"coordinates":[-80.368004,25.754569],"type":"Point"}
}