{
  "type": "Feature",
  "properties": {
    "addr:full":"2353 Periwinkle Way Sanibel FL 33957",
    "addr:housenumber":"2353",
    "addr:postcode":"33957",
    "addr:street":"Periwinkle Way",
    "iso:country":"US",
    "sg:address":"2353 Periwinkle Way",
    "sg:city":"Sanibel",
    "sg:classifiers":[
        {
            "category":"Recreation",
            "type":"Entertainment"
        }
    ],
    "sg:phone":"+1 239 472 5577",
    "sg:postcode":"33957",
    "sg:province":"FL",
    "sg:tags":[
        "bicycle"
    ],
    "wof:name":"Finnimore's Cycle Shop",
    "wof:placetype":"venue"
},
  "geometry": {"coordinates":[-82.072751,26.437514],"type":"Point"}
}