{
  "type": "Feature",
  "properties": {
    "iso:country":"US",
    "sg:address":"10190 Cll Comercio",
    "sg:city":"Boca Raton",
    "sg:classifiers":[
        {
            "category":"Social Services",
            "subcategory":"Child Care",
            "type":"Services"
        }
    ],
    "sg:phone":"+1 561 487 6021",
    "sg:postcode":"33428",
    "sg:province":"FL",
    "sg:website":"www.lapetite.com",
    "wof:name":"LA Petite Academy",
    "wof:placetype":"venue"
},
  "geometry": {"coordinates":[-80.206114,26.366278],"type":"Point"}
}