{
  "type": "Feature",
  "properties": {
    "addr:full":"906 Tomlinson Dr Lutz FL 33549",
    "addr:housenumber":"906",
    "addr:postcode":"33549",
    "addr:street":"Tomlinson Dr",
    "iso:country":"US",
    "sg:address":"906 Tomlinson Dr",
    "sg:city":"Lutz",
    "sg:classifiers":[
        {
            "category":"Transit Center",
            "subcategory":"Freight",
            "type":"Transportation"
        }
    ],
    "sg:phone":"+1 813 949 8401",
    "sg:postcode":"33549",
    "sg:province":"FL",
    "sg:tags":[
        "trucking-heavy",
        "hauling"
    ],
    "sg:website":"http://www.larryshauling.com",
    "wof:name":"Aaa Larry's Hauling Svc",
    "wof:placetype":"venue"
},
  "geometry": {"coordinates":[-82.451289,28.139571],"type":"Point"}
}