{
  "type": "Feature",
  "properties": {
    "addr:full":"4286 S University Dr Davie FL 33328",
    "addr:housenumber":"4286",
    "addr:postcode":"33328",
    "addr:street":"S University Dr",
    "iso:country":"US",
    "sg:address":"4286 S University Dr",
    "sg:city":"Davie",
    "sg:classifiers":[
        {
            "category":"Insurance",
            "subcategory":"Hazard Insurance",
            "type":"Services"
        }
    ],
    "sg:phone":"+1 954 475 9773",
    "sg:postcode":"33328",
    "sg:province":"FL",
    "sg:website":"http://statefarm.mqgroup.com/url.asp?usr=596980",
    "wof:name":"State Farm Insurance Agent-Karl E Wright Insurance Agency Inc",
    "wof:placetype":"venue"
},
  "geometry": {"coordinates":[-80.25214699999999,26.066386],"type":"Point"}
}