{
  "type": "Feature",
  "properties": {
    "addr:full":"8756 Banyan Way Cape Canaveral FL 32920",
    "addr:housenumber":"8756",
    "addr:postcode":"32920",
    "addr:street":"Banyan Way",
    "iso:country":"US",
    "sg:address":"8756 Banyan Way",
    "sg:city":"Cape Canaveral",
    "sg:classifiers":[
        {
            "category":"Retail",
            "subcategory":"Animal Services",
            "type":"Services"
        }
    ],
    "sg:phone":"+1 321 868 1081",
    "sg:postcode":"32920",
    "sg:province":"FL",
    "wof:name":"Myers Menagerie Inc",
    "wof:placetype":"venue"
},
  "geometry": {"coordinates":[-80.60422699999999,28.398627],"type":"Point"}
}