{
  "type": "Feature",
  "properties": {
    "iso:country":"US",
    "sg:address":"9515 Holsberry Rd",
    "sg:city":"Pensacola",
    "sg:classifiers":[
        {
            "category":"Banks & Credit Unions",
            "subcategory":"Bank",
            "type":"Services"
        }
    ],
    "sg:phone":"+1 850 477 9444",
    "sg:postcode":"32534",
    "sg:province":"FL",
    "wof:name":"GPCE Credit Union",
    "wof:placetype":"venue"
},
  "geometry": {"coordinates":[-87.266518,30.542336],"type":"Point"}
}