{
  "type": "Feature",
  "properties": {
    "addr:full":"222 NW Zanzibar Pl Port Saint Lucie FL 34986",
    "addr:housenumber":"222",
    "addr:postcode":"34986",
    "addr:street":"Nw Zanzibar Pl",
    "iso:country":"US",
    "sg:address":"222 NW Zanzibar Pl",
    "sg:city":"Port Saint Lucie",
    "sg:classifiers":[
        {
            "category":"Professional",
            "subcategory":"Business Services",
            "type":"Services"
        }
    ],
    "sg:phone":"+1 772 873 1256",
    "sg:postcode":"34986",
    "sg:province":"FL",
    "wof:name":"E & J Wellness Group",
    "wof:placetype":"venue"
},
  "geometry": {"coordinates":[-80.38449799999999,27.318824],"type":"Point"}
}