{
  "type": "Feature",
  "properties": {
    "addr:full":"102 W Main St Tavares FL 32778",
    "addr:housenumber":"102",
    "addr:postcode":"32778",
    "addr:street":"W Main St",
    "iso:country":"US",
    "sg:address":"102 W Main St",
    "sg:city":"Tavares",
    "sg:classifiers":[
        {
            "category":"Home & Garden",
            "subcategory":"Hardware",
            "type":"Retail Goods"
        }
    ],
    "sg:phone":"+1 352 343 3361",
    "sg:postcode":"32778",
    "sg:province":"FL",
    "sg:tags":[
        "fabric"
    ],
    "wof:name":"Ace Hardware",
    "wof:placetype":"venue"
},
  "geometry": {"coordinates":[-81.72908700000001,28.802306],"type":"Point"}
}