{
  "type": "Feature",
  "properties": {
    "iso:country":"US",
    "sg:address":"5445 Collins Ave",
    "sg:city":"Miami Beach",
    "sg:classifiers":[
        {
            "category":"Shopping",
            "subcategory":"Gifts & Souvenirs",
            "type":"Retail Goods"
        }
    ],
    "sg:phone":"+1 305 993 5555",
    "sg:postcode":"33140",
    "sg:province":"FL",
    "sg:tags":[
        "shop"
    ],
    "wof:name":"Castle Gift Shop",
    "wof:placetype":"venue"
},
  "geometry": {"coordinates":[-80.12290299999999,25.818851],"type":"Point"}
}