{
  "type": "Feature",
  "properties": {
    "addr:full":"406 NE 14th Pl Cape Coral FL 33909",
    "addr:housenumber":"406",
    "addr:postcode":"33909",
    "addr:street":"Ne 14Th Pl",
    "iso:country":"US",
    "sg:address":"406 NE 14th Pl",
    "sg:city":"Cape Coral",
    "sg:classifiers":[
        {
            "category":"Building & Trades",
            "subcategory":"Landscaping Services",
            "type":"Services"
        }
    ],
    "sg:phone":"+1 239 699 9013",
    "sg:postcode":"33909",
    "sg:province":"FL",
    "wof:name":"Tom Osorio",
    "wof:placetype":"venue"
},
  "geometry": {"coordinates":[-81.944991,26.661651],"type":"Point"}
}