{
  "type": "Feature",
  "properties": {
    "addr:full":"1065 95th Street Miami Beach FL 33154",
    "addr:housenumber":"1065",
    "addr:postcode":"33154",
    "addr:street":"95Th Street",
    "iso:country":"US",
    "sg:address":"1065 95th Street",
    "sg:city":"Miami Beach",
    "sg:classifiers":[
        {
            "category":"Freight",
            "type":"Transportation"
        },
        {
            "category":"Professional",
            "subcategory":"Lawyer & Legal Services",
            "type":"Services"
        },
        {
            "category":"Shopping",
            "subcategory":"Jewelry",
            "type":"Retail Goods"
        }
    ],
    "sg:phone":"+1 305 868 7723",
    "sg:postcode":"33154",
    "sg:province":"FL",
    "sg:tags":[
        "notary",
        "shipping"
    ],
    "wof:name":"Premier Postal Center",
    "wof:placetype":"venue"
},
  "geometry": {"coordinates":[-80.130531,25.885775],"type":"Point"}
}