{
  "type": "Feature",
  "properties": {
    "iso:country":"US",
    "sg:address":"4800 W Copans Rd",
    "sg:city":"Coconut Creek",
    "sg:classifiers":[
        {
            "category":"Government",
            "subcategory":"Court House",
            "type":"Public Place"
        }
    ],
    "sg:phone":"+1 954 973 6797",
    "sg:postcode":"33063",
    "sg:province":"FL",
    "sg:tags":[
        "city",
        "counsel"
    ],
    "wof:name":"Coconut Creek City Attorney",
    "wof:placetype":"venue"
},
  "geometry": {"coordinates":[-80.18984,26.259538],"type":"Point"}
}