{
  "type": "Feature",
  "properties": {
    "iso:country":"US",
    "sg:address":"4719 NW 183rd St",
    "sg:city":"Opa Locka",
    "sg:classifiers":[
        {
            "category":"Shopping",
            "subcategory":"Beauty & Cosmetics",
            "type":"Retail Goods"
        }
    ],
    "sg:phone":"+1 305 620 1772",
    "sg:postcode":"33055",
    "sg:province":"FL",
    "sg:tags":[
        "supply"
    ],
    "wof:name":"Rabbey Beauty Supplies",
    "wof:placetype":"venue"
},
  "geometry": {"coordinates":[-80.277901,25.9396],"type":"Point"}
}