{
  "type": "Feature",
  "properties": {
    "addr:full":"606 SE 22nd Ter Cape Coral FL 33990",
    "addr:housenumber":"606",
    "addr:postcode":"33990",
    "addr:street":"Se 22Nd Ter",
    "iso:country":"US",
    "sg:address":"606 SE 22nd Ter",
    "sg:city":"Cape Coral",
    "sg:classifiers":[
        {
            "category":"Building & Trades",
            "subcategory":"Construction",
            "type":"Services"
        }
    ],
    "sg:phone":"+1 239 574 2031",
    "sg:postcode":"33990",
    "sg:province":"FL",
    "sg:tags":[
        "contractor"
    ],
    "wof:name":"Nicholas Enterprises Inc",
    "wof:placetype":"venue"
},
  "geometry": {"coordinates":[-81.95956700000001,26.610278],"type":"Point"}
}