{
  "type": "Feature",
  "properties": {
    "iso:country":"US",
    "sg:address":"709 John Adams Ln",
    "sg:city":"Melbourne",
    "sg:classifiers":[
        {
            "category":"Building & Trades",
            "subcategory":"Plumbing",
            "type":"Services"
        }
    ],
    "sg:phone":"+1 321 723 9992",
    "sg:postcode":"32904",
    "sg:province":"FL",
    "sg:tags":[
        "plumbing",
        "contractor"
    ],
    "wof:name":"Joe's Plumbing & Rooter",
    "wof:placetype":"venue"
},
  "geometry": {"coordinates":[-80.644702,28.06376],"type":"Point"}
}