{
  "type": "Feature",
  "properties": {
    "addr:full":"8535 Danbury Blvd Naples FL 34120",
    "addr:housenumber":"8535",
    "addr:postcode":"34120",
    "addr:street":"Danbury Blvd",
    "iso:country":"US",
    "sg:address":"8535 Danbury Blvd",
    "sg:city":"Naples",
    "sg:classifiers":[
        {
            "category":"Wholesale",
            "subcategory":"Non-durable Goods",
            "type":"Manufacturing & Wholesale Goods"
        }
    ],
    "sg:phone":"+1 239 354 9861",
    "sg:postcode":"34120",
    "sg:province":"FL",
    "sg:tags":[
        "product",
        "mfg"
    ],
    "wof:name":"McCormack Associates",
    "wof:placetype":"venue"
},
  "geometry": {"coordinates":[-81.684144,26.252526],"type":"Point"}
}