{
  "type": "Feature",
  "properties": {
    "addr:full":"9119 Taft St Pembroke Pines FL 33024",
    "addr:housenumber":"9119",
    "addr:postcode":"33024",
    "addr:street":"Taft St",
    "iso:country":"US",
    "sg:address":"9119 Taft St",
    "sg:city":"Pembroke Pines",
    "sg:classifiers":[
        {
            "category":"Restaurant",
            "type":"Food & Drink"
        }
    ],
    "sg:phone":"+1 954 885 1225",
    "sg:postcode":"33024",
    "sg:province":"FL",
    "wof:name":"Punta Cana Restaurant",
    "wof:placetype":"venue"
},
  "geometry": {"coordinates":[-80.26822300000001,26.02315],"type":"Point"}
}