{
  "type": "Feature",
  "properties": {
    "addr:full":"11747 Phillips Hwy Jacksonville FL 32256",
    "addr:housenumber":"11747",
    "addr:postcode":"32256",
    "addr:street":"Phillips Hwy",
    "iso:country":"US",
    "sg:address":"11747 Phillips Hwy",
    "sg:city":"Jacksonville",
    "sg:classifiers":[
        {
            "category":"Autos & Motor Vehicles",
            "subcategory":"Automobile Sales",
            "type":"Retail Goods"
        }
    ],
    "sg:phone":"+1 904 288 5500",
    "sg:postcode":"32256",
    "sg:province":"FL",
    "wof:name":"Advanced Boat Trailers",
    "wof:placetype":"venue"
},
  "geometry": {"coordinates":[-81.535214,30.162015],"type":"Point"}
}