{
  "type": "Feature",
  "properties": {
    "addr:full":"960 Long Meadow Ln Melbourne FL 32940",
    "addr:housenumber":"960",
    "addr:postcode":"32940",
    "addr:street":"Long Meadow Ln",
    "iso:country":"US",
    "sg:address":"960 Long Meadow Ln",
    "sg:city":"Melbourne",
    "sg:classifiers":[
        {
            "category":"Shopping",
            "subcategory":"Computers & Home Electronics",
            "type":"Retail Goods"
        }
    ],
    "sg:phone":"+1 321 259 9640",
    "sg:postcode":"32940",
    "sg:province":"FL",
    "sg:tags":[
        "software"
    ],
    "wof:name":"MRO Software Inc",
    "wof:placetype":"venue"
},
  "geometry": {"coordinates":[-80.691318,28.223402],"type":"Point"}
}