{
  "type": "Feature",
  "properties": {
    "addr:full":"4451 Sunbeam Rd Jacksonville FL 32257",
    "addr:housenumber":"4451",
    "addr:postcode":"32257",
    "addr:street":"Sunbeam Rd",
    "iso:country":"US",
    "sg:address":"4451 Sunbeam Rd",
    "sg:city":"Jacksonville",
    "sg:classifiers":[
        {
            "category":"Retail",
            "subcategory":"Car Wash",
            "type":"Services"
        }
    ],
    "sg:phone":"+1 904 731 5813",
    "sg:postcode":"32257",
    "sg:province":"FL",
    "sg:tags":[
        "automobile",
        "detail",
        "clean"
    ],
    "wof:name":"Baxter Brothers Professional",
    "wof:placetype":"venue"
},
  "geometry": {"coordinates":[-81.596251,30.20599],"type":"Point"}
}