{
  "type": "Feature",
  "properties": {
    "iso:country":"US",
    "sg:address":"5045 SW 102nd Pl",
    "sg:city":"Miami",
    "sg:classifiers":[
        {
            "category":"Wholesale",
            "subcategory":"Construction Materials",
            "type":"Manufacturing & Wholesale Goods"
        },
        {
            "category":"Home & Garden",
            "subcategory":"Building Materials",
            "type":"Retail Goods"
        }
    ],
    "sg:phone":"+1 786 412 0455",
    "sg:postcode":"33165",
    "sg:province":"FL",
    "sg:tags":[
        "windows-wholesale",
        "window",
        "manufacturer"
    ],
    "wof:name":"Rosell Glass And Windows Inc",
    "wof:placetype":"venue"
},
  "geometry": {"coordinates":[-80.360719,25.720699],"type":"Point"}
}