{
  "type": "Feature",
  "properties": {
    "iso:country":"US",
    "sg:address":"121 W Plymouth Ave",
    "sg:city":"Deland",
    "sg:classifiers":[
        {
            "category":"Health Services",
            "subcategory":"Medical Lab",
            "type":"Services"
        }
    ],
    "sg:phone":"+1 386 734 7167",
    "sg:postcode":"32720",
    "sg:province":"FL",
    "sg:tags":[
        "laboratory"
    ],
    "wof:name":"Quest Diagnostics Inc",
    "wof:placetype":"venue"
},
  "geometry": {"coordinates":[-81.30427899999999,29.042806],"type":"Point"}
}