{
  "type": "Feature",
  "properties": {
    "addr:full":"8340 Biscayne Blvd Miami FL 33138",
    "addr:housenumber":"8340",
    "addr:postcode":"33138",
    "addr:street":"Biscayne Blvd",
    "iso:country":"US",
    "sg:address":"8340 Biscayne Blvd",
    "sg:city":"Miami",
    "sg:classifiers":[
        {
            "category":"Wholesale",
            "subcategory":"Apparel",
            "type":"Manufacturing & Wholesale Goods"
        },
        {
            "category":"Shopping",
            "subcategory":"Clothing, Apparel, & Fashions",
            "type":"Retail Goods"
        }
    ],
    "sg:phone":"+1 305 754 6200",
    "sg:postcode":"33138",
    "sg:province":"FL",
    "sg:tags":[
        "uniform"
    ],
    "wof:name":"Jules Brothers Uniforms Inc",
    "wof:placetype":"venue"
},
  "geometry": {"coordinates":[-80.184866,25.852093],"type":"Point"}
}