{
  "type": "Feature",
  "properties": {
    "addr:full":"10047 N Dale Mabry Hwy Tampa FL 33618",
    "addr:housenumber":"10047",
    "addr:postcode":"33618",
    "addr:street":"N Dale Mabry Hwy",
    "iso:country":"US",
    "sg:address":"10047 N Dale Mabry Hwy",
    "sg:city":"Tampa",
    "sg:classifiers":[
        {
            "category":"Restaurant",
            "type":"Food & Drink"
        }
    ],
    "sg:phone":"+1 813 960 2867",
    "sg:postcode":"33618",
    "sg:province":"FL",
    "sg:tags":[
        "eating"
    ],
    "wof:name":"Schlotzsky's Deli",
    "wof:placetype":"venue"
},
  "geometry": {"coordinates":[-82.50461199999999,28.042831],"type":"Point"}
}