{
  "type": "Feature",
  "properties": {
    "iso:country":"US",
    "sg:address":"11193 Seminole Blvd",
    "sg:city":"Largo",
    "sg:classifiers":[
        {
            "category":"Shopping",
            "type":"Retail Goods"
        }
    ],
    "sg:phone":"+1 727 319 0671",
    "sg:postcode":"33778",
    "sg:province":"FL",
    "sg:tags":[
        "equipment",
        "communications",
        "telephone",
        "merchandise",
        "supply"
    ],
    "sg:website":"www.centratel.net",
    "wof:name":"Centratel Services Intl",
    "wof:placetype":"venue"
},
  "geometry": {"coordinates":[-82.786986,27.874944],"type":"Point"}
}