{
  "type": "Feature",
  "properties": {
    "iso:country":"US",
    "sg:address":"5045 Carpenter Creek Dr",
    "sg:city":"Pensacola",
    "sg:classifiers":[
        {
            "category":"Health Services",
            "subcategory":"Doctor",
            "type":"Services"
        }
    ],
    "sg:phone":"+1 850 416 2418",
    "sg:postcode":"32503",
    "sg:province":"FL",
    "sg:tags":[
        "gynecology",
        "physician",
        "surgeon",
        "surgeons",
        "obstetrics"
    ],
    "wof:name":"Univ Of Florida Colg Of Medcn Dept Of Obstetrics & G",
    "wof:placetype":"venue"
},
  "geometry": {"coordinates":[-87.21080600000001,30.471209],"type":"Point"}
}