{
  "type": "Feature",
  "properties": {
    "iso:country":"US",
    "sg:address":"3479 SE Federal Hwy",
    "sg:city":"Fort Pierce",
    "sg:classifiers":[
        {
            "category":"Government",
            "subcategory":"Office",
            "type":"Public Place"
        }
    ],
    "sg:phone":"+1 772 468 3917",
    "sg:postcode":"34997",
    "sg:province":"FL",
    "wof:name":"Marketing Div",
    "wof:placetype":"venue"
},
  "geometry": {"coordinates":[-80.224766,27.162344],"type":"Point"}
}