{
  "type": "Feature",
  "properties": {
    "iso:country":"US",
    "sg:address":"251 Maitland Ave Ste 208",
    "sg:city":"Altamonte Springs",
    "sg:classifiers":[
        {
            "category":"Insurance",
            "subcategory":"Health Insurance",
            "type":"Services"
        }
    ],
    "sg:phone":"+1 407 830 5677",
    "sg:postcode":"32701",
    "sg:province":"FL",
    "sg:tags":[
        "market"
    ],
    "wof:name":"Meyers Weight Loss",
    "wof:placetype":"venue"
},
  "geometry": {"coordinates":[-81.365644,28.65912],"type":"Point"}
}