{
  "type": "Feature",
  "properties": {
    "iso:country":"US",
    "sg:address":"3641 Misty Woods Cir",
    "sg:city":"Milton",
    "sg:classifiers":[
        {
            "category":"Banks & Credit Unions",
            "subcategory":"Financial Services",
            "type":"Services"
        }
    ],
    "sg:phone":"+1 850 994 1329",
    "sg:postcode":"32571",
    "sg:province":"FL",
    "sg:tags":[
        "trust",
        "management"
    ],
    "wof:name":"Robert Kobos Trvst",
    "wof:placetype":"venue"
},
  "geometry": {"coordinates":[-87.16966499999999,30.656659],"type":"Point"}
}