{
  "type": "Feature",
  "properties": {
    "iso:country":"US",
    "sg:address":"905 Summer Breeze Dr",
    "sg:city":"Brandon",
    "sg:classifiers":[
        {
            "category":"Shopping",
            "subcategory":"Catalog Store",
            "type":"Retail Goods"
        }
    ],
    "sg:phone":"+1 866 344 7133",
    "sg:postcode":"33511",
    "sg:province":"FL",
    "sg:tags":[
        "educational"
    ],
    "wof:name":"1st Quality Online Merchant",
    "wof:placetype":"venue"
},
  "geometry": {"coordinates":[-82.298095,27.90537],"type":"Point"}
}