{
  "type": "Feature",
  "properties": {
    "iso:country":"US",
    "sg:address":"18575 Evergreen Rd",
    "sg:city":"Fort Myers",
    "sg:classifiers":[
        {
            "category":"Real Estate",
            "subcategory":"Real Estate Agent",
            "type":"Services"
        }
    ],
    "sg:phone":"+1 239 482 3663",
    "sg:postcode":"33967",
    "sg:province":"FL",
    "sg:tags":[
        "management"
    ],
    "wof:name":"M Yolanda Beckworth Property",
    "wof:placetype":"venue"
},
  "geometry": {"coordinates":[-81.82647,26.465583],"type":"Point"}
}