{
  "type": "Feature",
  "properties": {
    "iso:country":"US",
    "sg:address":"2293 SW 17th Ave",
    "sg:city":"Miami",
    "sg:classifiers":[
        {
            "category":"Food & Beverages",
            "subcategory":"Groceries & Convenience Stores",
            "type":"Retail Goods"
        }
    ],
    "sg:phone":"+1 305 858 9801",
    "sg:postcode":"33145",
    "sg:province":"FL",
    "sg:tags":[
        "grocer"
    ],
    "wof:name":"El Milagro Supermarket",
    "wof:placetype":"venue"
},
  "geometry": {"coordinates":[-80.221802,25.749001],"type":"Point"}
}