{
  "type": "Feature",
  "properties": {
    "addr:full":"9510 SW 160th Street Miami FL 33157",
    "addr:housenumber":"9510",
    "addr:postcode":"33157",
    "addr:street":"Sw 160Th Street",
    "iso:country":"US",
    "sg:address":"9510 SW 160th Street",
    "sg:city":"Miami",
    "sg:classifiers":[
        {
            "category":"Food & Beverages",
            "subcategory":"Groceries & Convenience Stores",
            "type":"Retail Goods"
        }
    ],
    "sg:phone":"+1 305 971 9790",
    "sg:postcode":"33157",
    "sg:province":"FL",
    "wof:name":"Publix",
    "wof:placetype":"venue"
},
  "geometry": {"coordinates":[-80.347553,25.619128],"type":"Point"}
}