{
  "type": "Feature",
  "properties": {
    "iso:country":"US",
    "sg:address":"4981 Golden Gate Pkwy",
    "sg:city":"Naples",
    "sg:classifiers":[
        {
            "category":"Health Services",
            "subcategory":"Chiropractor",
            "type":"Services"
        }
    ],
    "sg:phone":"+1 239 455 4181",
    "sg:postcode":"34116",
    "sg:province":"FL",
    "sg:tags":[
        "therapist",
        "physical"
    ],
    "wof:name":"Golden Gate Chiropractic Center",
    "wof:placetype":"venue"
},
  "geometry": {"coordinates":[-81.70730500000001,26.179863],"type":"Point"}
}