{
  "type": "Feature",
  "properties": {
    "addr:full":"1690 NW 87th Ave Doral FL 33172",
    "addr:housenumber":"1690",
    "addr:postcode":"33172",
    "addr:street":"Nw 87Th Ave",
    "iso:country":"US",
    "sg:address":"1690 NW 87th Ave",
    "sg:city":"Doral",
    "sg:classifiers":[
        {
            "category":"Building & Trades",
            "subcategory":"Locksmith",
            "type":"Services"
        }
    ],
    "sg:phone":"+1 305 908 7003",
    "sg:postcode":"33172",
    "sg:province":"FL",
    "sg:tags":[
        "key"
    ],
    "wof:name":"1 Chance 2 Fix It Locksmith",
    "wof:placetype":"venue"
},
  "geometry": {"coordinates":[-80.337062,25.789885],"type":"Point"}
}