{
  "type": "Feature",
  "properties": {
    "addr:full":"2450 Sunset Point Rd Ste A Clearwater FL 33765",
    "addr:housenumber":"2450",
    "addr:postcode":"33765",
    "addr:street":"Sunset Point Rd Ste A",
    "iso:country":"US",
    "sg:address":"2450 Sunset Point Rd Ste A",
    "sg:city":"Clearwater",
    "sg:classifiers":[
        {
            "category":"Arts & Performance",
            "subcategory":"Art Gallery",
            "type":"Entertainment"
        }
    ],
    "sg:phone":"+1 727 726 5100",
    "sg:postcode":"33765",
    "sg:province":"FL",
    "sg:tags":[
        "consultant",
        "galleries"
    ],
    "sg:website":"http://www.plainsmen.com",
    "wof:name":"Plainsmen Gallery",
    "wof:placetype":"venue"
},
  "geometry": {"coordinates":[-82.735691,27.989994],"type":"Point"}
}