{
  "type": "Feature",
  "properties": {
    "iso:country":"US",
    "sg:address":"209 Pleasant Valley Dr",
    "sg:city":"Daytona Beach",
    "sg:classifiers":[
        {
            "category":"Banks & Credit Unions",
            "subcategory":"Financial Services",
            "type":"Services"
        }
    ],
    "sg:phone":"+1 386 255 1445",
    "sg:postcode":"32114",
    "sg:province":"FL",
    "sg:tags":[
        "trust",
        "management"
    ],
    "wof:name":"James C Wood Rev Trust",
    "wof:placetype":"venue"
},
  "geometry": {"coordinates":[-81.087603,29.193161],"type":"Point"}
}