{
  "type": "Feature",
  "properties": {
    "addr:full":"5529 NE 52nd Pl High Springs FL 32643",
    "addr:housenumber":"5529",
    "addr:postcode":"32643",
    "addr:street":"Ne 52Nd Pl",
    "iso:country":"US",
    "sg:address":"5529 NE 52nd Pl",
    "sg:city":"High Springs",
    "sg:classifiers":[
        {
            "category":"Organizations",
            "subcategory":"Religious Organization",
            "type":"Services"
        }
    ],
    "sg:phone":"+1 386 454 3600",
    "sg:postcode":"32643",
    "sg:province":"FL",
    "sg:tags":[
        "church"
    ],
    "wof:name":"Spring Ridge First Church God",
    "wof:placetype":"venue"
},
  "geometry": {"coordinates":[-82.715462,29.816106],"type":"Point"}
}