{
  "type": "Feature",
  "properties": {
    "iso:country":"US",
    "sg:address":"1760 N East Ave",
    "sg:city":"Sarasota",
    "sg:classifiers":[
        {
            "category":"Banks & Credit Unions",
            "subcategory":"Financial Services",
            "type":"Services"
        }
    ],
    "sg:phone":"+1 941 329 6999",
    "sg:postcode":"34234",
    "sg:province":"FL",
    "sg:tags":[
        "investor"
    ],
    "wof:name":"Lakewood Ranch Arts Centre",
    "wof:placetype":"venue"
},
  "geometry": {"coordinates":[-82.528301,27.352573],"type":"Point"}
}