{
  "type": "Feature",
  "properties": {
    "iso:country":"US",
    "sg:address":"3655 Hospitality Ln",
    "sg:city":"Clearwater",
    "sg:classifiers":[
        {
            "category":"Travel",
            "subcategory":"Hotels & Motels",
            "type":"Entertainment"
        }
    ],
    "sg:phone":"+1 727 577 9200",
    "sg:postcode":"33762",
    "sg:province":"FL",
    "sg:tags":[
        "operation"
    ],
    "wof:name":"Hampton Inn",
    "wof:placetype":"venue"
},
  "geometry": {"coordinates":[-82.681442,27.894233],"type":"Point"}
}