{
  "type": "Feature",
  "properties": {
    "iso:country":"US",
    "sg:address":"2451 NW Lakeview Dr",
    "sg:city":"Sebring",
    "sg:classifiers":[
        {
            "category":"Farming",
            "subcategory":"Dairy Farm",
            "type":"Manufacturing & Wholesale Goods"
        }
    ],
    "sg:phone":"+1 863 385 8581",
    "sg:postcode":"33870",
    "sg:province":"FL",
    "wof:name":"Sandy Gully Dairy Inc",
    "wof:placetype":"venue"
},
  "geometry": {"coordinates":[-81.470077,27.509094],"type":"Point"}
}