{
  "type": "Feature",
  "properties": {
    "addr:full":"1175 Spring Centre South Blvd Altamonte Springs FL 32714",
    "addr:housenumber":"1175",
    "addr:postcode":"32714",
    "addr:street":"Spring Centre South Blvd",
    "iso:country":"US",
    "sg:address":"1175 Spring Centre South Blvd",
    "sg:city":"Altamonte Springs",
    "sg:classifiers":[
        {
            "category":"Real Estate",
            "subcategory":"Architect",
            "type":"Services"
        }
    ],
    "sg:phone":"+1 407 788 7575",
    "sg:postcode":"32714",
    "sg:province":"FL",
    "sg:tags":[
        "architectural",
        "business"
    ],
    "wof:name":"Leibin Roger Allen & Assoc",
    "wof:placetype":"venue"
},
  "geometry": {"coordinates":[-81.392697,28.687658],"type":"Point"}
}