{
  "type": "Feature",
  "properties": {
    "iso:country":"US",
    "sg:address":"1649 SE 4th St",
    "sg:city":"Deerfield Beach",
    "sg:classifiers":[
        {
            "category":"Real Estate",
            "subcategory":"Real Estate Operator",
            "type":"Services"
        }
    ],
    "sg:phone":"+1 954 422 1996",
    "sg:postcode":"33441",
    "sg:province":"FL",
    "sg:tags":[
        "building",
        "apartment"
    ],
    "wof:name":"Emerald Cove Apts Inc",
    "wof:placetype":"venue"
},
  "geometry": {"coordinates":[-80.084548,26.312894],"type":"Point"}
}