{
  "type": "Feature",
  "properties": {
    "iso:country":"US",
    "sg:address":"11650 Capri Cir S",
    "sg:city":"Saint Petersburg",
    "sg:classifiers":[
        {
            "category":"Wholesale",
            "subcategory":"Metals & Minerals",
            "type":"Manufacturing & Wholesale Goods"
        }
    ],
    "sg:phone":"+1 727 360 3537",
    "sg:postcode":"33706",
    "sg:province":"FL",
    "sg:tags":[
        "center"
    ],
    "wof:name":"Craig Steel Corporation",
    "wof:placetype":"venue"
},
  "geometry": {"coordinates":[-82.775299,27.779487],"type":"Point"}
}