{
  "type": "Feature",
  "properties": {
    "iso:country":"US",
    "sg:address":"76071 Sidney Pl",
    "sg:city":"Yulee",
    "sg:phone":"+1 904 849 0200",
    "sg:postcode":"32097",
    "sg:province":"FL",
    "sg:website":"http://www.hiexpress.com",
    "wof:name":"Holiday Inn Express",
    "wof:placetype":"venue"
},
  "geometry": {"coordinates":[-81.646242,30.619576],"type":"Point"}
}