{
  "type": "Feature",
  "properties": {
    "addr:full":"1080 NE 176th St Miami FL 33162",
    "addr:housenumber":"1080",
    "addr:postcode":"33162",
    "addr:street":"Ne 176Th St",
    "iso:country":"US",
    "sg:address":"1080 NE 176th St",
    "sg:city":"Miami",
    "sg:classifiers":[
        {
            "category":"Shopping",
            "type":"Retail Goods"
        }
    ],
    "sg:phone":"+1 305 788 6919",
    "sg:postcode":"33162",
    "sg:province":"FL",
    "sg:tags":[
        "interior",
        "design",
        "art",
        "gallery"
    ],
    "sg:website":"www.algavi.net",
    "wof:name":"Algavi Art & Design, Inc.",
    "wof:placetype":"venue"
},
  "geometry": {"coordinates":[-80.178608,25.936939],"type":"Point"}
}