{
  "type": "Feature",
  "properties": {
    "addr:full":"538 W 28th St Hialeah FL 33010",
    "addr:housenumber":"538",
    "addr:postcode":"33010",
    "addr:street":"W 28Th St",
    "iso:country":"US",
    "sg:address":"538 W 28th St",
    "sg:city":"Hialeah",
    "sg:classifiers":[
        {
            "category":"Building & Trades",
            "subcategory":"Construction",
            "type":"Services"
        }
    ],
    "sg:phone":"+1 305 889 1344",
    "sg:postcode":"33010",
    "sg:province":"FL",
    "sg:tags":[
        "carpentry",
        "contractor"
    ],
    "wof:name":"Montes De Oca Cabinets",
    "wof:placetype":"venue"
},
  "geometry": {"coordinates":[-80.293531,25.847022],"type":"Point"}
}