{
  "type": "Feature",
  "properties": {
    "addr:full":"9125 Little Rd New Port Richey FL 34654",
    "addr:housenumber":"9125",
    "addr:postcode":"34654",
    "addr:street":"Little Rd",
    "iso:country":"US",
    "sg:address":"9125 Little Rd",
    "sg:city":"New Port Richey",
    "sg:classifiers":[
        {
            "category":"Real Estate",
            "subcategory":"Real Estate Agent",
            "type":"Services"
        }
    ],
    "sg:phone":"+1 727 869 5100",
    "sg:postcode":"34654",
    "sg:province":"FL",
    "wof:name":"Real Estate Tampa Bay Inc",
    "wof:placetype":"venue"
},
  "geometry": {"coordinates":[-82.67580100000001,28.291242],"type":"Point"}
}