{
  "type": "Feature",
  "properties": {
    "iso:country":"US",
    "sg:address":"10862 Royal Devon Way",
    "sg:city":"Lake Worth",
    "sg:classifiers":[
        {
            "category":"Professional",
            "subcategory":"Business Services",
            "type":"Services"
        }
    ],
    "sg:phone":"+1 561 963 2155",
    "sg:postcode":"33449",
    "sg:province":"FL",
    "sg:tags":[
        "fund",
        "promotion",
        "raising"
    ],
    "wof:name":"Promo Concepts Inc",
    "wof:placetype":"venue"
},
  "geometry": {"coordinates":[-80.20904,26.608418],"type":"Point"}
}