{
  "type": "Feature",
  "properties": {
    "addr:full":"601 N Congress Ave Delray Beach FL 33445",
    "addr:housenumber":"601",
    "addr:postcode":"33445",
    "addr:street":"N Congress Ave",
    "iso:country":"US",
    "sg:address":"601 N Congress Ave",
    "sg:city":"Delray Beach",
    "sg:classifiers":[
        {
            "category":"Manufacturing",
            "subcategory":"Furniture",
            "type":"Manufacturing & Wholesale Goods"
        }
    ],
    "sg:phone":"+1 561 819 6392",
    "sg:postcode":"33445",
    "sg:province":"FL",
    "wof:name":"Stone Furniture Gallery Plus",
    "wof:placetype":"venue"
},
  "geometry": {"coordinates":[-80.089816,26.478862],"type":"Point"}
}