{
  "type": "Feature",
  "properties": {
    "addr:full":"1904 Barton Park Rd Auburndale FL 33823",
    "addr:housenumber":"1904",
    "addr:postcode":"33823",
    "addr:street":"Barton Park Rd",
    "iso:country":"US",
    "sg:address":"1904 Barton Park Rd",
    "sg:city":"Auburndale",
    "sg:classifiers":[
        {
            "category":"Utilities",
            "subcategory":"Sewage",
            "type":"Services"
        },
        {
            "category":"Retail",
            "subcategory":"Auto Repair",
            "type":"Services"
        }
    ],
    "sg:phone":"+1 863 965 2599",
    "sg:postcode":"33823",
    "sg:province":"FL",
    "sg:tags":[
        "repairing",
        "plant",
        "automobile",
        "water",
        "construction",
        "treatment",
        "waste"
    ],
    "wof:name":"Consta Flow Inc",
    "wof:placetype":"venue"
},
  "geometry": {"coordinates":[-81.81078599999999,28.051252],"type":"Point"}
}