{
  "type": "Feature",
  "properties": {
    "addr:full":"5160 Rock Dove Loop Lakeland FL 33810",
    "addr:housenumber":"5160",
    "addr:postcode":"33810",
    "addr:street":"Rock Dove Loop",
    "iso:country":"US",
    "sg:address":"5160 Rock Dove Loop",
    "sg:city":"Lakeland",
    "sg:classifiers":[
        {
            "category":"Building & Trades",
            "subcategory":"Construction",
            "type":"Services"
        }
    ],
    "sg:phone":"+1 863 815 8112",
    "sg:postcode":"33810",
    "sg:province":"FL",
    "sg:tags":[
        "contractor"
    ],
    "wof:name":"John Reed Contracting",
    "wof:placetype":"venue"
},
  "geometry": {"coordinates":[-82.05468999999999,28.137996],"type":"Point"}
}