{
  "type": "Feature",
  "properties": {
    "iso:country":"US",
    "sg:address":"809 SW 8th Ave",
    "sg:city":"Miami",
    "sg:classifiers":[
        {
            "category":"Recreation",
            "type":"Entertainment"
        }
    ],
    "sg:phone":"+1 305 262 7946",
    "sg:postcode":"33130",
    "sg:province":"FL",
    "sg:tags":[
        "instruction",
        "swimming"
    ],
    "wof:name":"Swim Kids",
    "wof:placetype":"venue"
},
  "geometry": {"coordinates":[-80.207325,25.765112],"type":"Point"}
}