{
  "type": "Feature",
  "properties": {
    "addr:full":"1769 NW 79th Ave Miami FL 33126",
    "addr:housenumber":"1769",
    "addr:postcode":"33126",
    "addr:street":"Nw 79Th Ave",
    "iso:country":"US",
    "sg:address":"1769 NW 79th Ave",
    "sg:city":"Miami",
    "sg:classifiers":[
        {
            "category":"Wholesale",
            "subcategory":"Electrical",
            "type":"Manufacturing & Wholesale Goods"
        }
    ],
    "sg:phone":"+1 305 477 5204",
    "sg:postcode":"33126",
    "sg:province":"FL",
    "sg:tags":[
        "equipment"
    ],
    "wof:name":"Ademco-Miami Export",
    "wof:placetype":"venue"
},
  "geometry": {"coordinates":[-80.323988,25.7901],"type":"Point"}
}