{
  "type": "Feature",
  "properties": {
    "iso:country":"US",
    "sg:address":"490 SW 63rd Ave",
    "sg:city":"Plantation",
    "sg:classifiers":[
        {
            "category":"Building & Trades",
            "subcategory":"Pest Control",
            "type":"Services"
        }
    ],
    "sg:phone":"+1 954 316 6400",
    "sg:postcode":"33317",
    "sg:province":"FL",
    "wof:name":"Ed's Pest Control Inc",
    "wof:placetype":"venue"
},
  "geometry": {"coordinates":[-80.23330799999999,26.109463],"type":"Point"}
}