{
  "type": "Feature",
  "properties": {
    "addr:full":"3101 Indian Creek Dr Miami Beach FL 33140",
    "addr:housenumber":"3101",
    "addr:postcode":"33140",
    "addr:street":"Indian Creek Dr",
    "iso:country":"US",
    "sg:address":"3101 Indian Creek Dr",
    "sg:city":"Miami Beach",
    "sg:classifiers":[
        {
            "category":"Real Estate",
            "subcategory":"Real Estate Services",
            "type":"Services"
        }
    ],
    "sg:phone":"+1 786 276 7845",
    "sg:postcode":"33140",
    "sg:province":"FL",
    "sg:tags":[
        "management",
        "property"
    ],
    "wof:name":"South Beach Bayside Condominium I Inc",
    "wof:placetype":"venue"
},
  "geometry": {"coordinates":[-80.12550400000001,25.8069],"type":"Point"}
}