{
  "type": "Feature",
  "properties": {
    "iso:country":"US",
    "sg:address":"10355 SE 159th St",
    "sg:city":"Summerfield",
    "sg:classifiers":[
        {
            "category":"Retail",
            "subcategory":"Auto Repair",
            "type":"Services"
        }
    ],
    "sg:phone":"+1 352 288 8718",
    "sg:postcode":"34491",
    "sg:province":"FL",
    "sg:tags":[
        "repairing",
        "automobile"
    ],
    "wof:name":"Jimmy's Auto Maintenance",
    "wof:placetype":"venue"
},
  "geometry": {"coordinates":[-81.98029,28.990708],"type":"Point"}
}