{
  "type": "Feature",
  "properties": {
    "addr:full":"126 Lands End Way Jupiter FL 33458",
    "addr:housenumber":"126",
    "addr:postcode":"33458",
    "addr:street":"Lands End Way",
    "iso:country":"US",
    "sg:address":"126 Lands End Way",
    "sg:city":"Jupiter",
    "sg:classifiers":[
        {
            "category":"Organizations",
            "subcategory":"Community Association",
            "type":"Services"
        }
    ],
    "sg:phone":"+1 561 662 3458",
    "sg:postcode":"33458",
    "sg:province":"FL",
    "wof:name":"Lands Ends Home Owners As",
    "wof:placetype":"venue"
},
  "geometry": {"coordinates":[-80.09225600000001,26.945679],"type":"Point"}
}