{
  "type": "Feature",
  "properties": {
    "addr:full":"7751 E Hwy 316 Citra FL 32113",
    "addr:housenumber":"7751",
    "addr:postcode":"32113",
    "addr:street":"E Hwy 316",
    "iso:country":"US",
    "sg:address":"7751 E Hwy 316",
    "sg:city":"Citra",
    "sg:classifiers":[
        {
            "category":"Restaurant",
            "type":"Food & Drink"
        }
    ],
    "sg:phone":"+1 352 595 3737",
    "sg:postcode":"32113",
    "sg:province":"FL",
    "sg:tags":[
        "catering"
    ],
    "wof:name":"Peebles Brbque Outdoor Cooking",
    "wof:placetype":"venue"
},
  "geometry": {"coordinates":[-82.040154,29.368741],"type":"Point"}
}