{
  "type": "Feature",
  "properties": {
    "iso:country":"US",
    "sg:address":"1526 University Blvd W",
    "sg:city":"Jacksonville",
    "sg:classifiers":[
        {
            "category":"Building & Trades",
            "subcategory":"Construction",
            "type":"Services"
        }
    ],
    "sg:phone":"+1 904 379 1446",
    "sg:postcode":"32217",
    "sg:province":"FL",
    "sg:tags":[
        "excavation",
        "as",
        "an",
        "operates",
        "contractor"
    ],
    "wof:name":"Kadin Corporation",
    "wof:placetype":"venue"
},
  "geometry": {"coordinates":[-81.644144,30.260832],"type":"Point"}
}