{
  "type": "Feature",
  "properties": {
    "iso:country":"US",
    "sg:address":"310 Palm Island NE",
    "sg:city":"Clearwater",
    "sg:classifiers":[
        {
            "category":"Food & Beverages",
            "subcategory":"Specialty",
            "type":"Retail Goods"
        },
        {
            "category":"Wholesale",
            "subcategory":"Drugs",
            "type":"Manufacturing & Wholesale Goods"
        }
    ],
    "sg:phone":"+1 727 442 7379",
    "sg:postcode":"33767",
    "sg:province":"FL",
    "sg:tags":[
        "whole",
        "health",
        "vitamin",
        "diet"
    ],
    "wof:name":"Key Fitness Formulas Inc",
    "wof:placetype":"venue"
},
  "geometry": {"coordinates":[-82.814549,27.986062],"type":"Point"}
}