{
  "type": "Feature",
  "properties": {
    "iso:country":"US",
    "sg:address":"3006 W Azeele St",
    "sg:city":"Tampa",
    "sg:classifiers":[
        {
            "category":"Health Services",
            "subcategory":"Doctor",
            "type":"Services"
        }
    ],
    "sg:phone":"+1 813 874 3006",
    "sg:postcode":"33609",
    "sg:province":"FL",
    "sg:tags":[
        "physician",
        "surgeon"
    ],
    "wof:name":"Sports Medicine Clinic-Tampa",
    "wof:placetype":"venue"
},
  "geometry": {"coordinates":[-82.491584,27.941065],"type":"Point"}
}