{
  "type": "Feature",
  "properties": {
    "addr:full":"4551 Summit Blvd West Palm Beach FL 33415",
    "addr:housenumber":"4551",
    "addr:postcode":"33415",
    "addr:street":"Summit Blvd",
    "iso:country":"US",
    "sg:address":"4551 Summit Blvd",
    "sg:city":"West Palm Beach",
    "sg:classifiers":[
        {
            "category":"Personal",
            "subcategory":"Tattoo Parlor",
            "type":"Services"
        }
    ],
    "sg:phone":"+1 561 683 4134",
    "sg:postcode":"33415",
    "sg:province":"FL",
    "sg:tags":[
        "tattooing"
    ],
    "wof:name":"Outrageous Tattoos",
    "wof:placetype":"venue"
},
  "geometry": {"coordinates":[-80.114484,26.662765],"type":"Point"}
}