{
  "type": "Feature",
  "properties": {
    "iso:country":"US",
    "sg:address":"1319 NW 36th St",
    "sg:city":"Okeechobee",
    "sg:classifiers":[
        {
            "category":"Farming",
            "subcategory":"Farm",
            "type":"Manufacturing & Wholesale Goods"
        }
    ],
    "sg:phone":"+1 863 357 0786",
    "sg:postcode":"34972",
    "sg:province":"FL",
    "sg:tags":[
        "crop",
        "general"
    ],
    "wof:name":"Romero Harvesting Inc",
    "wof:placetype":"venue"
},
  "geometry": {"coordinates":[-80.84295,27.278366],"type":"Point"}
}