{
  "type": "Feature",
  "properties": {
    "addr:full":"11120 State Hwy 70 Bradenton FL 34202",
    "addr:housenumber":"11120",
    "addr:postcode":"34202",
    "addr:street":"State Hwy 70",
    "iso:country":"US",
    "sg:address":"11120 State Hwy 70",
    "sg:city":"Bradenton",
    "sg:classifiers":[
        {
            "category":"Organizations",
            "subcategory":"Religious Organization",
            "type":"Services"
        }
    ],
    "sg:phone":"+1 941 753 9365",
    "sg:postcode":"34202",
    "sg:province":"FL",
    "sg:tags":[
        "child",
        "day",
        "care"
    ],
    "wof:name":"Congregation of Elca",
    "wof:placetype":"venue"
},
  "geometry": {"coordinates":[-82.43458,27.433655],"type":"Point"}
}