{
  "type": "Feature",
  "properties": {
    "addr:full":"113 N Partin Dr Niceville FL 32578",
    "addr:housenumber":"113",
    "addr:postcode":"32578",
    "addr:street":"N Partin Dr",
    "iso:country":"US",
    "sg:address":"113 N Partin Dr",
    "sg:city":"Niceville",
    "sg:classifiers":[
        {
            "category":"Restaurant",
            "type":"Food & Drink"
        }
    ],
    "sg:phone":"+1 850 729 8646",
    "sg:postcode":"32578",
    "sg:province":"FL",
    "sg:tags":[
        "eating"
    ],
    "wof:name":"Taco Town To Go Inc",
    "wof:placetype":"venue"
},
  "geometry": {"coordinates":[-86.480268,30.519909],"type":"Point"}
}