{
  "type": "Feature",
  "properties": {
    "iso:country":"US",
    "sg:address":"204 S Central Ave",
    "sg:city":"Apopka",
    "sg:classifiers":[
        {
            "category":"Social Services",
            "subcategory":"Child Care",
            "type":"Services"
        }
    ],
    "sg:phone":"+1 407 814 0444",
    "sg:postcode":"32703",
    "sg:province":"FL",
    "sg:tags":[
        "kindergarten",
        "academic",
        "school"
    ],
    "wof:name":"Daydreams Child Development",
    "wof:placetype":"venue"
},
  "geometry": {"coordinates":[-81.511605,28.674365],"type":"Point"}
}