{
  "type": "Feature",
  "properties": {
    "addr:full":"12015 SW 14th St Miami FL 33184",
    "addr:housenumber":"12015",
    "addr:postcode":"33184",
    "addr:street":"Sw 14Th St",
    "iso:country":"US",
    "sg:address":"12015 SW 14th St",
    "sg:city":"Miami",
    "sg:classifiers":[
        {
            "category":"Freight",
            "type":"Transportation"
        }
    ],
    "sg:phone":"+1 305 229 1267",
    "sg:postcode":"33184",
    "sg:province":"FL",
    "sg:tags":[
        "operator",
        "local",
        "trucking"
    ],
    "wof:name":"Salvys Delivery/Messenger Ser",
    "wof:placetype":"venue"
},
  "geometry": {"coordinates":[-80.389126,25.75531],"type":"Point"}
}