{
  "type": "Feature",
  "properties": {
    "addr:full":"3801 Oakwood Blvd Hollywood FL 33020",
    "addr:housenumber":"3801",
    "addr:postcode":"33020",
    "addr:street":"Oakwood Blvd",
    "iso:country":"US",
    "sg:address":"3801 Oakwood Blvd",
    "sg:city":"Hollywood",
    "sg:classifiers":[
        {
            "category":"Shopping",
            "subcategory":"Clothing, Apparel, & Fashions",
            "type":"Retail Goods"
        },
        {
            "category":"Shopping",
            "subcategory":"Baby Store",
            "type":"Retail Goods"
        }
    ],
    "sg:phone":"+1 954 927 4256",
    "sg:postcode":"33020",
    "sg:province":"FL",
    "sg:tags":[
        "infant",
        "men's",
        "women's",
        "children's",
        "maternity",
        "wear",
        "apparel",
        "girls'",
        "clothing",
        "boys'",
        "clothes"
    ],
    "sg:website":"http://www.oldnavy.com",
    "wof:name":"Old Navy",
    "wof:placetype":"venue"
},
  "geometry": {"coordinates":[-80.162424,26.042426],"type":"Point"}
}