{
  "type": "Feature",
  "properties": {
    "iso:country":"US",
    "sg:address":"1818 9th Ave E",
    "sg:city":"Bradenton",
    "sg:classifiers":[
        {
            "category":"Real Estate",
            "subcategory":"Real Estate Operator",
            "type":"Services"
        }
    ],
    "sg:phone":"+1 941 748 7564",
    "sg:postcode":"34208",
    "sg:province":"FL",
    "sg:tags":[
        "building",
        "apartment"
    ],
    "wof:name":"Avondale Estate Apartments",
    "wof:placetype":"venue"
},
  "geometry": {"coordinates":[-82.54371,27.491374],"type":"Point"}
}