{
  "type": "Feature",
  "properties": {
    "iso:country":"US",
    "sg:address":"2693 Beal St",
    "sg:city":"Deltona",
    "sg:classifiers":[
        {
            "category":"Building & Trades",
            "subcategory":"Construction",
            "type":"Services"
        }
    ],
    "sg:phone":"+1 386 532 5881",
    "sg:postcode":"32738",
    "sg:province":"FL",
    "sg:tags":[
        "contractor"
    ],
    "wof:name":"Sms Services",
    "wof:placetype":"venue"
},
  "geometry": {"coordinates":[-81.192955,28.936176],"type":"Point"}
}