{
  "type": "Feature",
  "properties": {
    "addr:full":"108 1st Ter Palm Beach Gardens FL 33418",
    "addr:housenumber":"108",
    "addr:postcode":"33418",
    "addr:street":"1St Ter;Gardens",
    "iso:country":"US",
    "sg:address":"108 1st Ter",
    "sg:city":"Palm Beach Gardens",
    "sg:classifiers":[
        {
            "category":"Manufacturing",
            "subcategory":"Chemicals & Compounds",
            "type":"Manufacturing & Wholesale Goods"
        }
    ],
    "sg:phone":"+1 561 310 6452",
    "sg:postcode":"33418",
    "sg:province":"FL",
    "sg:tags":[
        "automobile",
        "primer",
        "coating",
        "for",
        "mfg"
    ],
    "wof:name":"CP Paints Inc",
    "wof:placetype":"venue"
},
  "geometry": {"coordinates":[-80.135756,26.834693],"type":"Point"}
}