{
  "type": "Feature",
  "properties": {
    "iso:country":"US",
    "sg:address":"17505 Okeechobee Rd",
    "sg:city":"Fort Pierce",
    "sg:classifiers":[
        {
            "category":"Building & Trades",
            "subcategory":"Landscaping Services",
            "type":"Services"
        }
    ],
    "sg:phone":"+1 772 465 7755",
    "sg:postcode":"34945",
    "sg:province":"FL",
    "sg:tags":[
        "landscape"
    ],
    "wof:name":"Big Lake Ldscp & Irrigation",
    "wof:placetype":"venue"
},
  "geometry": {"coordinates":[-80.502144,27.371598],"type":"Point"}
}