{
  "type": "Feature",
  "properties": {
    "addr:full":"6924 Miramar Pkwy Hollywood FL 33023",
    "addr:housenumber":"6924",
    "addr:postcode":"33023",
    "addr:street":"Miramar Pkwy",
    "iso:country":"US",
    "sg:address":"6924 Miramar Pkwy",
    "sg:city":"Hollywood",
    "sg:classifiers":[
        {
            "category":"Autos & Motor Vehicles",
            "subcategory":"Fuel & Gas Station",
            "type":"Retail Goods"
        }
    ],
    "sg:phone":"+1 954 989 3771",
    "sg:postcode":"33023",
    "sg:province":"FL",
    "sg:tags":[
        "station",
        "gasoline",
        "oil"
    ],
    "wof:name":"Sunshine Gasoline",
    "wof:placetype":"venue"
},
  "geometry": {"coordinates":[-80.225245,25.981972],"type":"Point"}
}