{
  "type": "Feature",
  "properties": {
    "iso:country":"US",
    "sg:address":"3199 NW 2nd Ave",
    "sg:city":"Boca Raton",
    "sg:classifiers":[
        {
            "category":"Building & Trades",
            "subcategory":"Plumbing",
            "type":"Services"
        }
    ],
    "sg:phone":"+1 561 368 4033",
    "sg:postcode":"33431",
    "sg:province":"FL",
    "sg:tags":[
        "contractor"
    ],
    "wof:name":"AC Offshore Inc",
    "wof:placetype":"venue"
},
  "geometry": {"coordinates":[-80.08579899999999,26.37874],"type":"Point"}
}