{
  "type": "Feature",
  "properties": {
    "addr:full":"2824 S Grove St Eustis FL 32726",
    "addr:housenumber":"2824",
    "addr:postcode":"32726",
    "addr:street":"S Grove St",
    "iso:country":"US",
    "sg:address":"2824 S Grove St",
    "sg:city":"Eustis",
    "sg:classifiers":[
        {
            "category":"Manufacturing",
            "subcategory":"Motor Vehicles & Parts",
            "type":"Manufacturing & Wholesale Goods"
        }
    ],
    "sg:phone":"+1 352 357 9559",
    "sg:postcode":"32726",
    "sg:province":"FL",
    "sg:tags":[
        "on",
        "screen",
        "cap",
        "jacket",
        "printing",
        "t",
        "embroidery"
    ],
    "wof:name":"Tip Tops",
    "wof:placetype":"venue"
},
  "geometry": {"coordinates":[-81.68364,28.826383],"type":"Point"}
}