{
  "type": "Feature",
  "properties": {
    "addr:full":"2615 US Hwy 92 Plant City FL 33566",
    "addr:housenumber":"2615",
    "addr:postcode":"33566",
    "addr:street":"Us Hwy 92",
    "iso:country":"US",
    "sg:address":"2615 US Hwy 92",
    "sg:city":"Plant City",
    "sg:classifiers":[
        {
            "category":"Manufacturing",
            "subcategory":"Food",
            "type":"Manufacturing & Wholesale Goods"
        }
    ],
    "sg:phone":"+1 813 754 5565",
    "sg:postcode":"33566",
    "sg:province":"FL",
    "sg:tags":[
        "grocery",
        "mfg"
    ],
    "wof:name":"Mrs Alisons Cookies",
    "wof:placetype":"venue"
},
  "geometry": {"coordinates":[-82.095035,28.020314],"type":"Point"}
}