{
  "type": "Feature",
  "properties": {
    "addr:full":"1455 Edgewood Cir Jacksonville FL 32205",
    "addr:housenumber":"1455",
    "addr:postcode":"32205",
    "addr:street":"Edgewood Cir",
    "iso:country":"US",
    "sg:address":"1455 Edgewood Cir",
    "sg:city":"Jacksonville",
    "sg:classifiers":[
        {
            "category":"Retail",
            "subcategory":"Repair Shop",
            "type":"Services"
        }
    ],
    "sg:phone":"+1 904 388 2628",
    "sg:postcode":"32205",
    "sg:province":"FL",
    "sg:tags":[
        "sharpening"
    ],
    "wof:name":"Advantage Mobile Sharpening",
    "wof:placetype":"venue"
},
  "geometry": {"coordinates":[-81.706829,30.303205],"type":"Point"}
}