{
  "type": "Feature",
  "properties": {
    "addr:full":"218 E Tarpon Ave Tarpon Springs FL 34689",
    "addr:housenumber":"218",
    "addr:postcode":"34689",
    "addr:street":"E Tarpon Ave",
    "iso:country":"US",
    "sg:address":"218 E Tarpon Ave",
    "sg:city":"Tarpon Springs",
    "sg:classifiers":[
        {
            "category":"Shopping",
            "subcategory":"Used Merchandise",
            "type":"Retail Goods"
        }
    ],
    "sg:phone":"+1 727 943 0440",
    "sg:postcode":"34689",
    "sg:province":"FL",
    "sg:tags":[
        "antique"
    ],
    "wof:name":"Unique Designs",
    "wof:placetype":"venue"
},
  "geometry": {"coordinates":[-82.75374600000001,28.146168],"type":"Point"}
}