{
  "type": "Feature",
  "properties": {
    "addr:full":"750 NW 119th St Miami FL 33168",
    "addr:housenumber":"750",
    "addr:postcode":"33168",
    "addr:street":"Nw 119Th St",
    "iso:country":"US",
    "sg:address":"750 NW 119th St",
    "sg:city":"Miami",
    "sg:classifiers":[
        {
            "category":"Retail",
            "subcategory":"Portrait Studio",
            "type":"Services"
        },
        {
            "category":"Shopping",
            "subcategory":"Pharmacy",
            "type":"Retail Goods"
        }
    ],
    "sg:phone":"+1 305 685 9970",
    "sg:postcode":"33168",
    "sg:province":"FL",
    "sg:tags":[
        "photography",
        "drugstore",
        "store"
    ],
    "sg:website":"www.walgreens.com/",
    "wof:name":"Walgreens",
    "wof:placetype":"venue"
},
  "geometry": {"coordinates":[-80.211337,25.883307],"type":"Point"}
}