{
  "type": "Feature",
  "properties": {
    "addr:full":"9 Airport Rd Frostproof FL 33843",
    "addr:housenumber":"9",
    "addr:postcode":"33843",
    "addr:street":"Airport Rd",
    "iso:country":"US",
    "sg:address":"9 Airport Rd",
    "sg:city":"Frostproof",
    "sg:classifiers":[
        {
            "category":"Farming",
            "subcategory":"Orchard",
            "type":"Manufacturing & Wholesale Goods"
        }
    ],
    "sg:phone":"+1 863 635 4493",
    "sg:postcode":"33843",
    "sg:province":"FL",
    "sg:tags":[
        "citrus",
        "grove",
        "fruit"
    ],
    "wof:name":"C & L Yates Inc",
    "wof:placetype":"venue"
},
  "geometry": {"coordinates":[-81.558925,27.752798],"type":"Point"}
}