{
  "type": "Feature",
  "properties": {
    "iso:country":"US",
    "sg:address":"3242 NW 121st Ave",
    "sg:city":"Sunrise",
    "sg:classifiers":[
        {
            "category":"Retail",
            "subcategory":"Laundry & Dry Cleaning",
            "type":"Services"
        }
    ],
    "sg:phone":"+1 954 749 7654",
    "sg:postcode":"33323",
    "sg:province":"FL",
    "sg:tags":[
        "cleaner",
        "rug",
        "carpet"
    ],
    "wof:name":"Eric Taft Carpet Cleaning Inc",
    "wof:placetype":"venue"
},
  "geometry": {"coordinates":[-80.309682,26.166771],"type":"Point"}
}