{
  "type": "Feature",
  "properties": {
    "iso:country":"US",
    "sg:address":"430 Crofton Dr",
    "sg:city":"Ocoee",
    "sg:classifiers":[
        {
            "category":"Building & Trades",
            "subcategory":"Construction",
            "type":"Services"
        }
    ],
    "sg:phone":"+1 407 654 6097",
    "sg:postcode":"34761",
    "sg:province":"FL",
    "sg:tags":[
        "carpentry",
        "contractor"
    ],
    "wof:name":"SAT Inc",
    "wof:placetype":"venue"
},
  "geometry": {"coordinates":[-81.549538,28.537902],"type":"Point"}
}