{
  "type": "Feature",
  "properties": {
    "iso:country":"US",
    "sg:address":"704 Oakwood Ave",
    "sg:city":"New Smyrna Beach",
    "sg:classifiers":[
        {
            "category":"Building & Trades",
            "subcategory":"Construction",
            "type":"Services"
        }
    ],
    "sg:phone":"+1 386 428 8097",
    "sg:postcode":"32169",
    "sg:province":"FL",
    "sg:tags":[
        "carpentry",
        "contractor"
    ],
    "wof:name":"Bill Bottino Carpentry",
    "wof:placetype":"venue"
},
  "geometry": {"coordinates":[-80.896826,29.036152],"type":"Point"}
}