{
  "type": "Feature",
  "properties": {
    "iso:country":"US",
    "sg:address":"1602 US Hwy 41",
    "sg:city":"Ruskin",
    "sg:classifiers":[
        {
            "category":"Shopping",
            "subcategory":"Pharmacy",
            "type":"Retail Goods"
        }
    ],
    "sg:phone":"+1 813 645 4605",
    "sg:postcode":"33570",
    "sg:province":"FL",
    "sg:tags":[
        "drug",
        "store"
    ],
    "wof:name":"CVS",
    "wof:placetype":"venue"
},
  "geometry": {"coordinates":[-82.43786799999999,27.705109],"type":"Point"}
}