{
  "type": "Feature",
  "properties": {
    "addr:full":"2875 NW 77th Ave Doral FL 33122",
    "addr:housenumber":"2875",
    "addr:postcode":"33122",
    "addr:street":"Nw 77Th Ave",
    "iso:country":"US",
    "sg:address":"2875 NW 77th Ave",
    "sg:city":"Doral",
    "sg:classifiers":[
        {
            "category":"Wholesale",
            "subcategory":"Auto Parts",
            "type":"Manufacturing & Wholesale Goods"
        }
    ],
    "sg:phone":"+1 305 718 6664",
    "sg:postcode":"33122",
    "sg:province":"FL",
    "sg:tags":[
        "tire"
    ],
    "wof:name":"South Dade Automotive Inc",
    "wof:placetype":"venue"
},
  "geometry": {"coordinates":[-80.320801,25.8015],"type":"Point"}
}