{
  "type": "Feature",
  "properties": {
    "iso:country":"US",
    "sg:address":"1001 Capri St",
    "sg:city":"Miami",
    "sg:classifiers":[
        {
            "category":"Banks & Credit Unions",
            "subcategory":"Financial Services",
            "type":"Services"
        }
    ],
    "sg:phone":"+1 305 443 2943",
    "sg:postcode":"33134",
    "sg:province":"FL",
    "sg:tags":[
        "investor"
    ],
    "wof:name":"Volman Real Estate Investments",
    "wof:placetype":"venue"
},
  "geometry": {"coordinates":[-80.274692,25.76312],"type":"Point"}
}