{
  "type": "Feature",
  "properties": {
    "iso:country":"US",
    "sg:address":"7350 NW 7th St",
    "sg:city":"Miami",
    "sg:classifiers":[
        {
            "category":"Personal",
            "type":"Services"
        }
    ],
    "sg:phone":"+1 305 265 8280",
    "sg:postcode":"33126",
    "sg:province":"FL",
    "sg:tags":[
        "credit",
        "debt",
        "counseling"
    ],
    "wof:name":"Florida Financial Consultants",
    "wof:placetype":"venue"
},
  "geometry": {"coordinates":[-80.314454,25.777037],"type":"Point"}
}