{
  "type": "Feature",
  "properties": {
    "iso:country":"US",
    "sg:address":"12 S Ocean Ave",
    "sg:city":"Daytona Beach",
    "sg:classifiers":[
        {
            "category":"Building & Trades",
            "subcategory":"Construction",
            "type":"Services"
        }
    ],
    "sg:phone":"+1 386 257 4997",
    "sg:postcode":"32118",
    "sg:province":"FL",
    "wof:name":"Coastal Cable Inc",
    "wof:placetype":"venue"
},
  "geometry": {"coordinates":[-81.006924,29.225458],"type":"Point"}
}