{
  "type": "Feature",
  "properties": {
    "iso:country":"US",
    "sg:address":"6447 Miami Lakes Dr E Ste 222A",
    "sg:city":"Hialeah",
    "sg:classifiers":[
        {
            "category":"Personal",
            "subcategory":"Massage",
            "type":"Services"
        }
    ],
    "sg:phone":"+1 305 826 0708",
    "sg:postcode":"33014",
    "sg:province":"FL",
    "sg:website":"www.balancebeautyandharmony.com",
    "wof:name":"Balance Beauty & Harmony",
    "wof:placetype":"venue"
},
  "geometry": {"coordinates":[-80.30522000000001,25.911314],"type":"Point"}
}