{
  "type": "Feature",
  "properties": {
    "addr:full":"8913 Bowles Rd Tampa FL 33637",
    "addr:housenumber":"8913",
    "addr:postcode":"33637",
    "addr:street":"Bowles Rd",
    "iso:country":"US",
    "sg:address":"8913 Bowles Rd",
    "sg:city":"Tampa",
    "sg:classifiers":[
        {
            "category":"Building & Trades",
            "subcategory":"Electrical",
            "type":"Services"
        }
    ],
    "sg:phone":"+1 813 983 1881",
    "sg:postcode":"33637",
    "sg:province":"FL",
    "sg:tags":[
        "electrical",
        "contractor"
    ],
    "wof:name":"Mr Electric",
    "wof:placetype":"venue"
},
  "geometry": {"coordinates":[-82.347526,28.029623],"type":"Point"}
}