{
  "type": "Feature",
  "properties": {
    "addr:full":"8995 Biscayne Blvd Miami Shores FL 33138",
    "addr:housenumber":"8995",
    "addr:postcode":"33138",
    "addr:street":"Biscayne Blvd",
    "iso:country":"US",
    "sg:address":"8995 Biscayne Blvd",
    "sg:city":"Miami Shores",
    "sg:classifiers":[
        {
            "category":"Shopping",
            "subcategory":"Mobile Phones",
            "type":"Retail Goods"
        }
    ],
    "sg:phone":"+1 305 757 5177",
    "sg:postcode":"33138",
    "sg:province":"FL",
    "sg:website":"www.gowireless.net",
    "wof:name":"Go Wireless",
    "wof:placetype":"venue"
},
  "geometry": {"coordinates":[-80.18409200000001,25.857639],"type":"Point"}
}