{
  "type": "Feature",
  "properties": {
    "iso:country":"US",
    "sg:address":"3401 Lake Breeze Dr",
    "sg:city":"Orlando",
    "sg:classifiers":[
        {
            "category":"Social Services",
            "type":"Services"
        }
    ],
    "sg:phone":"+1 407 290 1609",
    "sg:postcode":"32808",
    "sg:province":"FL",
    "sg:tags":[
        "counselor",
        "health",
        "mental"
    ],
    "wof:name":"Counseling Center",
    "wof:placetype":"venue"
},
  "geometry": {"coordinates":[-81.42019999999999,28.596297],"type":"Point"}
}