{
  "type": "Feature",
  "properties": {
    "iso:country":"US",
    "sg:address":"1035 N Collier Blvd",
    "sg:city":"Marco Island",
    "sg:classifiers":[
        {
            "category":"Restaurant",
            "type":"Food & Drink"
        }
    ],
    "sg:phone":"+1 239 642 6900",
    "sg:postcode":"34145",
    "sg:province":"FL",
    "sg:tags":[
        "eating"
    ],
    "wof:name":"Breakfast Plus Restaurant",
    "wof:placetype":"venue"
},
  "geometry": {"coordinates":[-81.723322,25.954702],"type":"Point"}
}