{
  "type": "Feature",
  "properties": {
    "addr:full":"6359 Barbara St Jupiter FL 33418",
    "addr:housenumber":"6359",
    "addr:postcode":"33418",
    "addr:street":"Barbara St",
    "iso:country":"US",
    "sg:address":"6359 Barbara St",
    "sg:city":"Jupiter",
    "sg:classifiers":[
        {
            "category":"Professional",
            "subcategory":"Secretarial Services",
            "type":"Services"
        }
    ],
    "sg:phone":"+1 561 748 9610",
    "sg:postcode":"33418",
    "sg:province":"FL",
    "sg:tags":[
        "reporting"
    ],
    "wof:name":"Bokelmann Assoc Inc",
    "wof:placetype":"venue"
},
  "geometry": {"coordinates":[-80.134761,26.901341],"type":"Point"}
}