{
  "type": "Feature",
  "properties": {
    "iso:country":"US",
    "sg:address":"10667 Oak Bend Way",
    "sg:city":"West Palm Beach",
    "sg:classifiers":[
        {
            "category":"Retail",
            "subcategory":"Auto Repair",
            "type":"Services"
        }
    ],
    "sg:phone":"+1 561 795 5077",
    "sg:postcode":"33414",
    "sg:province":"FL",
    "sg:tags":[
        "body"
    ],
    "wof:name":"George M Santi Jr",
    "wof:placetype":"venue"
},
  "geometry": {"coordinates":[-80.21614099999999,26.660215],"type":"Point"}
}