{
  "type": "Feature",
  "properties": {
    "addr:full":"1650 8th St SE Miami FL 33135",
    "addr:housenumber":"1650",
    "addr:postcode":"33135",
    "addr:street":"8Th St Se",
    "iso:country":"US",
    "sg:address":"1650 8th St SE",
    "sg:city":"Miami",
    "sg:classifiers":[
        {
            "category":"Manufacturing",
            "subcategory":"Jewelry",
            "type":"Manufacturing & Wholesale Goods"
        }
    ],
    "sg:phone":"+1 305 642 2046",
    "sg:postcode":"33135",
    "sg:province":"FL",
    "sg:tags":[
        "manufacture"
    ],
    "wof:name":"Surprise Jewelry Manufacture",
    "wof:placetype":"venue"
},
  "geometry": {"coordinates":[-80.221985,25.765552],"type":"Point"}
}