{
  "type": "Feature",
  "properties": {
    "iso:country":"US",
    "sg:address":"5133 NW 51st Ter",
    "sg:city":"Pompano Beach",
    "sg:classifiers":[
        {
            "category":"Building & Trades",
            "subcategory":"Equipment Rental",
            "type":"Services"
        }
    ],
    "sg:phone":"+1 954 354 0800",
    "sg:postcode":"33073",
    "sg:province":"FL",
    "sg:tags":[
        "therapy",
        "rent",
        "physical"
    ],
    "wof:name":"Florida Sunshine Medical Inc",
    "wof:placetype":"venue"
},
  "geometry": {"coordinates":[-80.193184,26.293292],"type":"Point"}
}