{
  "type": "Feature",
  "properties": {
    "addr:full":"3801 S Ocean Dr Apt 15S Hollywood FL 33019",
    "addr:housenumber":"3801",
    "addr:postcode":"33019",
    "addr:street":"S Ocean Dr Apt 15S",
    "iso:country":"US",
    "sg:address":"3801 S Ocean Dr Apt 15S",
    "sg:city":"Hollywood",
    "sg:classifiers":[
        {
            "category":"Health Services",
            "subcategory":"Doctor",
            "type":"Services"
        }
    ],
    "sg:phone":"+1 954 457 5539",
    "sg:postcode":"33019",
    "sg:province":"FL",
    "sg:tags":[
        "physician",
        "surgeon"
    ],
    "wof:name":"Paul E Gregoline",
    "wof:placetype":"venue"
},
  "geometry": {"coordinates":[-80.119056,25.988604],"type":"Point"}
}