{
  "type": "Feature",
  "properties": {
    "addr:full":"646 W Colonial Dr Orlando FL 32804",
    "addr:housenumber":"646",
    "addr:postcode":"32804",
    "addr:street":"W Colonial Dr",
    "iso:country":"US",
    "sg:address":"646 W Colonial Dr",
    "sg:city":"Orlando",
    "sg:classifiers":[
        {
            "category":"Home & Garden",
            "subcategory":"Household Appliances",
            "type":"Retail Goods"
        },
        {
            "category":"Building & Trades",
            "subcategory":"Construction",
            "type":"Services"
        }
    ],
    "sg:phone":"+1 407 244 5986",
    "sg:postcode":"32804",
    "sg:province":"FL",
    "sg:tags":[
        "repair",
        "dishwashing",
        "system",
        "machine",
        "contractor",
        "air conditioning"
    ],
    "wof:name":"Ahern Service",
    "wof:placetype":"venue"
},
  "geometry": {"coordinates":[-81.38883199999999,28.553011],"type":"Point"}
}