{
  "type": "Feature",
  "properties": {
    "iso:country":"US",
    "sg:address":"5455 Spring Hill Dr",
    "sg:city":"Spring Hill",
    "sg:classifiers":[
        {
            "category":"Real Estate",
            "subcategory":"Real Estate Agent",
            "type":"Services"
        }
    ],
    "sg:phone":"+1 352 683 6275",
    "sg:postcode":"34606",
    "sg:province":"FL",
    "wof:name":"Alliance Realty",
    "wof:placetype":"venue"
},
  "geometry": {"coordinates":[-82.624768,28.458671],"type":"Point"}
}