{
  "type": "Feature",
  "properties": {
    "addr:full":"101 N Riverside Dr Pompano Beach FL 33062",
    "addr:housenumber":"101",
    "addr:postcode":"33062",
    "addr:street":"N Riverside Dr",
    "iso:country":"US",
    "sg:address":"101 N Riverside Dr",
    "sg:city":"Pompano Beach",
    "sg:classifiers":[
        {
            "category":"Marine",
            "type":"Transportation"
        }
    ],
    "sg:phone":"+1 954 942 0069",
    "sg:postcode":"33062",
    "sg:province":"FL",
    "sg:tags":[
        "cleaning",
        "boat"
    ],
    "wof:name":"Elite Detailing",
    "wof:placetype":"venue"
},
  "geometry": {"coordinates":[-80.09240800000001,26.234341],"type":"Point"}
}