{
  "type": "Feature",
  "properties": {
    "addr:full":"102 Bass Dr Interlachen FL 32148",
    "addr:housenumber":"102",
    "addr:postcode":"32148",
    "addr:street":"Bass Dr",
    "iso:country":"US",
    "sg:address":"102 Bass Dr",
    "sg:city":"Interlachen",
    "sg:classifiers":[
        {
            "category":"Building & Trades",
            "subcategory":"Cleaning & Sanitation",
            "type":"Services"
        }
    ],
    "sg:phone":"+1 386 684 4246",
    "sg:postcode":"32148",
    "sg:province":"FL",
    "sg:tags":[
        "janitor"
    ],
    "wof:name":"Cindy Lee Cleaning",
    "wof:placetype":"venue"
},
  "geometry": {"coordinates":[-81.896964,29.686252],"type":"Point"}
}