{
  "type": "Feature",
  "properties": {
    "iso:country":"US",
    "sg:address":"3188 Ponce de Leon Blvd",
    "sg:city":"Coral Gables",
    "sg:classifiers":[
        {
            "category":"Shopping",
            "subcategory":"Crafts & Fabrics",
            "type":"Retail Goods"
        }
    ],
    "sg:phone":"+1 305 443 9070",
    "sg:postcode":"33134",
    "sg:province":"FL",
    "sg:tags":[
        "sewing",
        "yarn"
    ],
    "wof:name":"Lady Bug Crafts",
    "wof:placetype":"venue"
},
  "geometry": {"coordinates":[-80.258563,25.739956],"type":"Point"}
}