{
  "type": "Feature",
  "properties": {
    "iso:country":"US",
    "sg:address":"5275 Hondo Way",
    "sg:city":"Orlando",
    "sg:classifiers":[
        {
            "category":"Building & Trades",
            "subcategory":"Plumbing",
            "type":"Services"
        }
    ],
    "sg:phone":"+1 407 299 3588",
    "sg:postcode":"32810",
    "sg:province":"FL",
    "sg:tags":[
        "air",
        "heating",
        "contractor",
        "system",
        "conditioning"
    ],
    "wof:name":"Libby Twins Heating & Air Cond",
    "wof:placetype":"venue"
},
  "geometry": {"coordinates":[-81.44818600000001,28.615516],"type":"Point"}
}