{
  "type": "Feature",
  "properties": {
    "addr:full":"3064 SE Ranch Acres Cir Jupiter FL 33478",
    "addr:housenumber":"3064",
    "addr:postcode":"33478",
    "addr:street":"Se Ranch Acres Cir",
    "iso:country":"US",
    "sg:address":"3064 SE Ranch Acres Cir",
    "sg:city":"Jupiter",
    "sg:classifiers":[
        {
            "category":"Building & Trades",
            "subcategory":"Construction",
            "type":"Services"
        }
    ],
    "sg:phone":"+1 561 745 1221",
    "sg:postcode":"33478",
    "sg:province":"FL",
    "sg:tags":[
        "carpenter"
    ],
    "wof:name":"Charles Tompkins Carpentry",
    "wof:placetype":"venue"
},
  "geometry": {"coordinates":[-80.191883,26.961301],"type":"Point"}
}