{
  "type": "Feature",
  "properties": {
    "addr:full":"248 S Ocean Blvd Lantana FL 33462",
    "addr:housenumber":"248",
    "addr:postcode":"33462",
    "addr:street":"S Ocean Blvd",
    "iso:country":"US",
    "sg:address":"248 S Ocean Blvd",
    "sg:city":"Lantana",
    "sg:classifiers":[
        {
            "category":"Shopping",
            "subcategory":"Clothing, Apparel, & Fashions",
            "type":"Retail Goods"
        }
    ],
    "sg:phone":"+1 561 586 7771",
    "sg:postcode":"33462",
    "sg:province":"FL",
    "wof:name":"Native Sun",
    "wof:placetype":"venue"
},
  "geometry": {"coordinates":[-80.03903099999999,26.583044],"type":"Point"}
}