{
  "type": "Feature",
  "properties": {
    "iso:country":"US",
    "sg:address":"7376 NW 34th St",
    "sg:city":"Fort Lauderdale",
    "sg:classifiers":[
        {
            "category":"Manufacturing",
            "subcategory":"Rubber & Plastics",
            "type":"Manufacturing & Wholesale Goods"
        }
    ],
    "sg:phone":"+1 954 741 6031",
    "sg:postcode":"33319",
    "sg:province":"FL",
    "sg:tags":[
        "product",
        "mfg"
    ],
    "wof:name":"Its Marine Electronics",
    "wof:placetype":"venue"
},
  "geometry": {"coordinates":[-80.24624799999999,26.169057],"type":"Point"}
}