{
  "type": "Feature",
  "properties": {
    "iso:country":"US",
    "sg:address":"1011 Snead Ave",
    "sg:city":"Sarasota",
    "sg:classifiers":[
        {
            "category":"Building & Trades",
            "subcategory":"Cleaning & Sanitation",
            "type":"Services"
        }
    ],
    "sg:phone":"+1 941 955 4036",
    "sg:postcode":"34237",
    "sg:province":"FL",
    "sg:tags":[
        "janitor"
    ],
    "wof:name":"Teresa Aguilar's Cleaning",
    "wof:placetype":"venue"
},
  "geometry": {"coordinates":[-82.518995,27.346555],"type":"Point"}
}