{
  "type": "Feature",
  "properties": {
    "iso:country":"US",
    "sg:address":"517 Crystal Dr",
    "sg:city":"Saint Petersburg",
    "sg:classifiers":[
        {
            "category":"Professional",
            "subcategory":"Computer Services",
            "type":"Services"
        }
    ],
    "sg:phone":"+1 727 391 8895",
    "sg:postcode":"33708",
    "sg:province":"FL",
    "sg:tags":[
        "related"
    ],
    "wof:name":"Lt Consulting",
    "wof:placetype":"venue"
},
  "geometry": {"coordinates":[-82.783278,27.797986],"type":"Point"}
}