{
  "type": "Feature",
  "properties": {
    "addr:full":"6622 Acacia Ct Miami FL 33143",
    "addr:housenumber":"6622",
    "addr:postcode":"33143",
    "addr:street":"Acacia Ct",
    "iso:country":"US",
    "sg:address":"6622 Acacia Ct",
    "sg:city":"Miami",
    "sg:classifiers":[
        {
            "category":"Retail",
            "subcategory":"Photofinishing",
            "type":"Services"
        }
    ],
    "sg:phone":"+1 305 674 9808",
    "sg:postcode":"33143",
    "sg:province":"FL",
    "sg:tags":[
        "photo",
        "finishing"
    ],
    "wof:name":"Beach Film Concept Inc",
    "wof:placetype":"venue"
},
  "geometry": {"coordinates":[-80.301288,25.708841],"type":"Point"}
}