{
  "type": "Feature",
  "properties": {
    "addr:full":"4005 Aurantia Rd Mims FL 32754",
    "addr:housenumber":"4005",
    "addr:postcode":"32754",
    "addr:street":"Aurantia Rd",
    "iso:country":"US",
    "sg:address":"4005 Aurantia Rd",
    "sg:city":"Mims",
    "sg:classifiers":[
        {
            "category":"Building & Trades",
            "subcategory":"Construction",
            "type":"Services"
        }
    ],
    "sg:phone":"+1 321 385 9474",
    "sg:postcode":"32754",
    "sg:province":"FL",
    "sg:tags":[
        "contractor"
    ],
    "wof:name":"Steve Lawrence Masonary",
    "wof:placetype":"venue"
},
  "geometry": {"coordinates":[-80.870904,28.731549],"type":"Point"}
}