{
  "type": "Feature",
  "properties": {
    "iso:country":"US",
    "sg:address":"1600 Pinecrest Cir",
    "sg:city":"Jupiter",
    "sg:classifiers":[
        {
            "category":"Real Estate",
            "subcategory":"Real Estate Agent",
            "type":"Services"
        }
    ],
    "sg:phone":"+1 561 746 8523",
    "sg:postcode":"33458",
    "sg:province":"FL",
    "wof:name":"Pinecrest Condo Assoc",
    "wof:placetype":"venue"
},
  "geometry": {"coordinates":[-80.137597,26.914],"type":"Point"}
}