{
  "type": "Feature",
  "properties": {
    "iso:country":"US",
    "sg:address":"2214 State Hwy 44",
    "sg:city":"Inverness",
    "sg:classifiers":[
        {
            "category":"Real Estate",
            "subcategory":"Real Estate Agent",
            "type":"Services"
        }
    ],
    "sg:phone":"+1 352 341 0900",
    "sg:postcode":"34453",
    "sg:province":"FL",
    "wof:name":"Diana Marcum",
    "wof:placetype":"venue"
},
  "geometry": {"coordinates":[-82.35671600000001,28.83837],"type":"Point"}
}