{
  "type": "Feature",
  "properties": {
    "addr:full":"3504 NW 2nd St Miami FL 33125",
    "addr:housenumber":"3504",
    "addr:postcode":"33125",
    "addr:street":"Nw 2Nd St",
    "iso:country":"US",
    "sg:address":"3504 NW 2nd St",
    "sg:city":"Miami",
    "sg:classifiers":[
        {
            "category":"Wholesale",
            "subcategory":"Music Publishers",
            "type":"Manufacturing & Wholesale Goods"
        }
    ],
    "sg:phone":"+1 305 305 1442",
    "sg:postcode":"33125",
    "sg:province":"FL",
    "sg:tags":[
        "distribution"
    ],
    "wof:name":"Lion Muzic International Inc",
    "wof:placetype":"venue"
},
  "geometry": {"coordinates":[-80.253354,25.773939],"type":"Point"}
}