{
  "type": "Feature",
  "properties": {
    "iso:country":"US",
    "sg:address":"3298 Summit Blvd Ste 27",
    "sg:city":"Pensacola",
    "sg:classifiers":[
        {
            "category":"Banks & Credit Unions",
            "subcategory":"Investment Brokerage",
            "type":"Services"
        },
        {
            "category":"Insurance",
            "subcategory":"Hazard Insurance",
            "type":"Services"
        },
        {
            "category":"Banks & Credit Unions",
            "subcategory":"Financial Services",
            "type":"Services"
        }
    ],
    "sg:phone":"+1 850 436 6615",
    "sg:postcode":"32503",
    "sg:province":"FL",
    "sg:tags":[
        "management",
        "business",
        "annuity",
        "commercial",
        "retirement",
        "plan"
    ],
    "wof:name":"Currin Insurance & Investment Services",
    "wof:placetype":"venue"
},
  "geometry": {"coordinates":[-87.179451,30.45944],"type":"Point"}
}