{
  "type": "Feature",
  "properties": {
    "addr:full":"87 Veterans Ave Brooksville FL 34601",
    "addr:housenumber":"87",
    "addr:postcode":"34601",
    "addr:street":"Veterans Ave",
    "iso:country":"US",
    "sg:address":"87 Veterans Ave",
    "sg:city":"Brooksville",
    "sg:classifiers":[
        {
            "category":"Government",
            "subcategory":"Police Station",
            "type":"Public Place"
        }
    ],
    "sg:phone":"+1 352 754 6800",
    "sg:postcode":"34601",
    "sg:province":"FL",
    "sg:tags":[
        "department",
        "protection"
    ],
    "sg:website":"www.ci.brooksville.fl.us",
    "wof:name":"Brooksville Police Department",
    "wof:placetype":"venue"
},
  "geometry": {"coordinates":[-82.40006700000001,28.552677],"type":"Point"}
}