{
  "type": "Feature",
  "properties": {
    "addr:full":"5200 Beach Blvd Jacksonville FL 32207",
    "addr:housenumber":"5200",
    "addr:postcode":"32207",
    "addr:street":"Beach Blvd",
    "iso:country":"US",
    "sg:address":"5200 Beach Blvd",
    "sg:city":"Jacksonville",
    "sg:classifiers":[
        {
            "category":"Wholesale",
            "subcategory":"Durable Goods & Equipment",
            "type":"Manufacturing & Wholesale Goods"
        }
    ],
    "sg:phone":"+1 904 398 2030",
    "sg:postcode":"32207",
    "sg:province":"FL",
    "sg:tags":[
        "fire",
        "extinguisher"
    ],
    "wof:name":"Apartment Fire Extinguisher",
    "wof:placetype":"venue"
},
  "geometry": {"coordinates":[-81.61184900000001,30.295469],"type":"Point"}
}