{
  "type": "Feature",
  "properties": {
    "addr:full":"13215 Harbour Vista Cir St Augustine FL 32080",
    "addr:housenumber":"13215",
    "addr:postcode":"32080",
    "addr:street":"Harbour Vista Cir St",
    "iso:country":"US",
    "sg:address":"13215 Harbour Vista Cir",
    "sg:city":"St Augustine",
    "sg:classifiers":[
        {
            "category":"Building & Trades",
            "subcategory":"Cleaning & Sanitation",
            "type":"Services"
        }
    ],
    "sg:phone":"+1 904 377 2077",
    "sg:postcode":"32080",
    "sg:province":"FL",
    "sg:tags":[
        "house"
    ],
    "wof:name":"Dazzle Cleaning & Janitorial",
    "wof:placetype":"venue"
},
  "geometry": {"coordinates":[-81.296136,29.861142],"type":"Point"}
}