{
  "type": "Feature",
  "properties": {
    "addr:full":"10850 SE 129th St Belleview FL 34420",
    "addr:housenumber":"10850",
    "addr:postcode":"34420",
    "addr:street":"Se 129Th St",
    "iso:country":"US",
    "sg:address":"10850 SE 129th St",
    "sg:city":"Belleview",
    "sg:classifiers":[
        {
            "category":"Building & Trades",
            "subcategory":"Construction",
            "type":"Services"
        }
    ],
    "sg:phone":"+1 352 288 3833",
    "sg:postcode":"34420",
    "sg:province":"FL",
    "sg:tags":[
        "system",
        "specialty",
        "heating",
        "contractor",
        "air conditioning"
    ],
    "wof:name":"Cook & Sons Eagle Hvac R Inc",
    "wof:placetype":"venue"
},
  "geometry": {"coordinates":[-81.97345799999999,29.034246],"type":"Point"}
}