{
  "type": "Feature",
  "properties": {
    "iso:country":"US",
    "sg:address":"371 Seminole Dr",
    "sg:city":"Lake Worth",
    "sg:classifiers":[
        {
            "category":"Farming",
            "subcategory":"Farm & Veterinary Services",
            "type":"Manufacturing & Wholesale Goods"
        }
    ],
    "sg:phone":"+1 561 965 9936",
    "sg:postcode":"33462",
    "sg:province":"FL",
    "sg:tags":[
        "crop",
        "harvesting"
    ],
    "wof:name":"S Garcia Harvesting Inc",
    "wof:placetype":"venue"
},
  "geometry": {"coordinates":[-80.101201,26.581294],"type":"Point"}
}