{
  "type": "Feature",
  "properties": {
    "iso:country":"US",
    "sg:address":"1290 34th St NW",
    "sg:city":"Winter Haven",
    "sg:classifiers":[
        {
            "category":"Food & Beverages",
            "subcategory":"Groceries & Convenience Stores",
            "type":"Retail Goods"
        }
    ],
    "sg:phone":"+1 863 967 6486",
    "sg:postcode":"33881",
    "sg:province":"FL",
    "wof:name":"Vj",
    "wof:placetype":"venue"
},
  "geometry": {"coordinates":[-81.767984,28.041926],"type":"Point"}
}