{
  "type": "Feature",
  "properties": {
    "addr:full":"8980 Antigua Dr Largo FL 33777",
    "addr:housenumber":"8980",
    "addr:postcode":"33777",
    "addr:street":"Antigua Dr",
    "iso:country":"US",
    "sg:address":"8980 Antigua Dr",
    "sg:city":"Largo",
    "sg:classifiers":[
        {
            "category":"Building & Trades",
            "subcategory":"Construction",
            "type":"Services"
        }
    ],
    "sg:phone":"+1 727 391 4172",
    "sg:postcode":"33777",
    "sg:province":"FL",
    "sg:tags":[
        "hanging",
        "painter",
        "contractor"
    ],
    "wof:name":"Richard Lashley Painting",
    "wof:placetype":"venue"
},
  "geometry": {"coordinates":[-82.76403999999999,27.859942],"type":"Point"}
}