{
  "type": "Feature",
  "properties": {
    "iso:country":"US",
    "sg:address":"3855 S Florida Ave",
    "sg:city":"Lakeland",
    "sg:classifiers":[
        {
            "category":"Organizations",
            "subcategory":"Religious Organization",
            "type":"Services"
        }
    ],
    "sg:phone":"+1 863 646 3556",
    "sg:postcode":"33813",
    "sg:province":"FL",
    "sg:tags":[
        "church"
    ],
    "sg:website":"www.churchoftheres.net",
    "wof:name":"Resurrection Catholic Church",
    "wof:placetype":"venue"
},
  "geometry": {"coordinates":[-81.957166,27.99652],"type":"Point"}
}