{
  "type": "Feature",
  "properties": {
    "iso:country":"US",
    "sg:address":"1203 Governors Square Blvd",
    "sg:city":"Tallahassee",
    "sg:classifiers":[
        {
            "category":"Government",
            "subcategory":"Office",
            "type":"Public Place"
        }
    ],
    "sg:phone":"+1 850 877 4292",
    "sg:postcode":"32301",
    "sg:province":"FL",
    "wof:name":"US Svc Ind",
    "wof:placetype":"venue"
},
  "geometry": {"coordinates":[-84.261715,30.439638],"type":"Point"}
}