{
  "type": "Feature",
  "properties": {
    "iso:country":"US",
    "sg:address":"610 Wilder Rd",
    "sg:city":"Big Pine Key",
    "sg:classifiers":[
        {
            "category":"Government",
            "subcategory":"Office",
            "type":"Public Place"
        }
    ],
    "sg:phone":"+1 305 872 9676",
    "sg:postcode":"33043",
    "sg:province":"FL",
    "sg:tags":[
        "federal"
    ],
    "wof:name":"Us Fish & Wildlife Svc",
    "wof:placetype":"venue"
},
  "geometry": {"coordinates":[-81.356218,24.679306],"type":"Point"}
}