{
  "type": "Feature",
  "properties": {
    "addr:full":"9109 Bachman Rd Orlando FL 32824",
    "addr:housenumber":"9109",
    "addr:postcode":"32824",
    "addr:street":"Bachman Rd",
    "iso:country":"US",
    "sg:address":"9109 Bachman Rd",
    "sg:city":"Orlando",
    "sg:classifiers":[
        {
            "category":"Wholesale",
            "subcategory":"Machinery & Supplies",
            "type":"Manufacturing & Wholesale Goods"
        },
        {
            "category":"Manufacturing",
            "subcategory":"Metals",
            "type":"Manufacturing & Wholesale Goods"
        }
    ],
    "sg:phone":"+1 407 850 0000",
    "sg:postcode":"32824",
    "sg:province":"FL",
    "sg:tags":[
        "equipment",
        "welding"
    ],
    "wof:name":"Euro Metal Us A",
    "wof:placetype":"venue"
},
  "geometry": {"coordinates":[-81.392269,28.428968],"type":"Point"}
}