{
  "type": "Feature",
  "properties": {
    "addr:full":"1604 Regatta Dr Fernandina Beach FL 32034",
    "addr:housenumber":"1604",
    "addr:postcode":"32034",
    "addr:street":"Regatta Dr",
    "iso:country":"US",
    "sg:address":"1604 Regatta Dr",
    "sg:city":"Fernandina Beach",
    "sg:classifiers":[
        {
            "category":"Real Estate",
            "subcategory":"Developer",
            "type":"Services"
        }
    ],
    "sg:phone":"+1 904 491 3269",
    "sg:postcode":"32034",
    "sg:province":"FL",
    "wof:name":"Personal Development Systems",
    "wof:placetype":"venue"
},
  "geometry": {"coordinates":[-81.44692999999999,30.593909],"type":"Point"}
}