{
  "type": "Feature",
  "properties": {
    "iso:country":"US",
    "sg:address":"14234 Van Ct",
    "sg:city":"Spring Hill",
    "sg:classifiers":[
        {
            "category":"Building & Trades",
            "subcategory":"Landscaping Services",
            "type":"Services"
        }
    ],
    "sg:phone":"+1 727 856 1627",
    "sg:postcode":"34610",
    "sg:province":"FL",
    "wof:name":"C & H Lawns",
    "wof:placetype":"venue"
},
  "geometry": {"coordinates":[-82.577187,28.412319],"type":"Point"}
}