{
  "type": "Feature",
  "properties": {
    "addr:full":"217 Page Bacon Rd Mary Esther FL 32569",
    "addr:housenumber":"217",
    "addr:postcode":"32569",
    "addr:street":"Page Bacon Rd",
    "iso:country":"US",
    "sg:address":"217 Page Bacon Rd",
    "sg:city":"Mary Esther",
    "sg:classifiers":[
        {
            "category":"Personal",
            "subcategory":"Beauty Salon",
            "type":"Services"
        }
    ],
    "sg:phone":"+1 850 664 7007",
    "sg:postcode":"32569",
    "sg:province":"FL",
    "wof:name":"Jackies",
    "wof:placetype":"venue"
},
  "geometry": {"coordinates":[-86.659925,30.419198],"type":"Point"}
}