{
  "type": "Feature",
  "properties": {
    "iso:country":"US",
    "sg:address":"1095 Club House Blvd",
    "sg:city":"New Smyrna Beach",
    "sg:classifiers":[
        {
            "category":"Real Estate",
            "subcategory":"Real Estate Agent",
            "type":"Services"
        }
    ],
    "sg:phone":"+1 386 424 0900",
    "sg:postcode":"32168",
    "sg:province":"FL",
    "wof:name":"Raymaley Realty",
    "wof:placetype":"venue"
},
  "geometry": {"coordinates":[-80.994511,29.04605],"type":"Point"}
}