{
  "type": "Feature",
  "properties": {
    "addr:full":"2701 SW 79th Ct Miami FL 33155",
    "addr:housenumber":"2701",
    "addr:postcode":"33155",
    "addr:street":"Sw 79Th Ct",
    "iso:country":"US",
    "sg:address":"2701 SW 79th Ct",
    "sg:city":"Miami",
    "sg:classifiers":[
        {
            "category":"Wholesale",
            "subcategory":"Machinery & Supplies",
            "type":"Manufacturing & Wholesale Goods"
        }
    ],
    "sg:phone":"+1 305 261 8195",
    "sg:postcode":"33155",
    "sg:province":"FL",
    "sg:tags":[
        "truck"
    ],
    "wof:name":"Rodriguez Lift Trucks Inc",
    "wof:placetype":"venue"
},
  "geometry": {"coordinates":[-80.324521,25.745211],"type":"Point"}
}