{
  "type": "Feature",
  "properties": {
    "addr:full":"3130 39th Ave N Saint Petersburg FL 33714",
    "addr:housenumber":"3130",
    "addr:postcode":"33714",
    "addr:street":"39Th Ave N",
    "iso:country":"US",
    "sg:address":"3130 39th Ave N",
    "sg:city":"Saint Petersburg",
    "sg:classifiers":[
        {
            "category":"Retail",
            "subcategory":"Auto Repair",
            "type":"Services"
        }
    ],
    "sg:phone":"+1 727 526 4148",
    "sg:postcode":"33714",
    "sg:province":"FL",
    "sg:tags":[
        "general"
    ],
    "wof:name":"Just Miata",
    "wof:placetype":"venue"
},
  "geometry": {"coordinates":[-82.676941,27.807449],"type":"Point"}
}