{
  "type": "Feature",
  "properties": {
    "iso:country":"US",
    "sg:address":"7525 W Waters Ave",
    "sg:city":"Tampa",
    "sg:classifiers":[
        {
            "category":"Wholesale",
            "subcategory":"Machinery & Supplies",
            "type":"Manufacturing & Wholesale Goods"
        }
    ],
    "sg:phone":"+1 813 341 1670",
    "sg:postcode":"33615",
    "sg:province":"FL",
    "sg:tags":[
        "salon",
        "beauty"
    ],
    "wof:name":"Beauty Alliance",
    "wof:placetype":"venue"
},
  "geometry": {"coordinates":[-82.564683,28.025966],"type":"Point"}
}