{
  "type": "Feature",
  "properties": {
    "addr:full":"15675 NW 15th Ave Miami FL 33169",
    "addr:housenumber":"15675",
    "addr:postcode":"33169",
    "addr:street":"Nw 15Th Ave",
    "iso:country":"US",
    "sg:address":"15675 NW 15th Ave",
    "sg:city":"Miami",
    "sg:classifiers":[
        {
            "category":"Professional",
            "type":"Services"
        },
        {
            "category":"Wholesale",
            "subcategory":"Furniture",
            "type":"Manufacturing & Wholesale Goods"
        }
    ],
    "sg:phone":"+1 305 627 9922",
    "sg:postcode":"33169",
    "sg:province":"FL",
    "sg:tags":[
        "establishment",
        "whole"
    ],
    "wof:name":"Series USA",
    "wof:placetype":"venue"
},
  "geometry": {"coordinates":[-80.224859,25.918603],"type":"Point"}
}