{
  "type": "Feature",
  "properties": {
    "addr:full":"12071 McGregor Blvd Fort Myers FL 33919",
    "addr:housenumber":"12071",
    "addr:postcode":"33919",
    "addr:street":"Mcgregor Blvd",
    "iso:country":"US",
    "sg:address":"12071 McGregor Blvd",
    "sg:city":"Fort Myers",
    "sg:classifiers":[
        {
            "category":"Autos & Motor Vehicles",
            "subcategory":"Automobile Sales",
            "type":"Retail Goods"
        }
    ],
    "sg:phone":"+1 239 481 3344",
    "sg:postcode":"33919",
    "sg:province":"FL",
    "sg:tags":[
        "used"
    ],
    "wof:name":"Lantern Motors Inc",
    "wof:placetype":"venue"
},
  "geometry": {"coordinates":[-81.904118,26.567841],"type":"Point"}
}