{
  "type": "Feature",
  "properties": {
    "iso:country":"US",
    "sg:address":"10306 Big Bend Rd",
    "sg:city":"Riverview",
    "sg:classifiers":[
        {
            "category":"Freight",
            "type":"Transportation"
        }
    ],
    "sg:phone":"+1 813 677 4886",
    "sg:postcode":"33578",
    "sg:province":"FL",
    "sg:tags":[
        "operator",
        "local",
        "trucking"
    ],
    "wof:name":"Donald A Buddemeier",
    "wof:placetype":"venue"
},
  "geometry": {"coordinates":[-82.332054,27.791992],"type":"Point"}
}