{
  "type": "Feature",
  "properties": {
    "iso:country":"US",
    "sg:address":"6439 Miller Dr",
    "sg:city":"Miami",
    "sg:classifiers":[
        {
            "category":"Health Services",
            "subcategory":"Doctor",
            "type":"Services"
        }
    ],
    "sg:phone":"+1 305 663 1042",
    "sg:postcode":"33155",
    "sg:province":"FL",
    "sg:tags":[
        "physician",
        "surgeon"
    ],
    "wof:name":"Gables Rehab & Family Practice",
    "wof:placetype":"venue"
},
  "geometry": {"coordinates":[-80.299075,25.718534],"type":"Point"}
}