{
  "type": "Feature",
  "properties": {
    "iso:country":"US",
    "sg:address":"2455 Martha Dr",
    "sg:city":"Lake Wales",
    "sg:classifiers":[
        {
            "category":"Professional",
            "subcategory":"Business Services",
            "type":"Services"
        }
    ],
    "sg:phone":"+1 863 678 9145",
    "sg:postcode":"33898",
    "sg:province":"FL",
    "sg:tags":[
        "jewelry"
    ],
    "wof:name":"J Korkos Enterprises",
    "wof:placetype":"venue"
},
  "geometry": {"coordinates":[-81.54934,27.895466],"type":"Point"}
}