{
  "type": "Feature",
  "properties": {
    "addr:full":"116 Baywest Dr Orlando FL 32835",
    "addr:housenumber":"116",
    "addr:postcode":"32835",
    "addr:street":"Baywest Dr",
    "iso:country":"US",
    "sg:address":"116 Baywest Dr",
    "sg:city":"Orlando",
    "sg:classifiers":[
        {
            "category":"Building & Trades",
            "subcategory":"Construction",
            "type":"Services"
        }
    ],
    "sg:phone":"+1 407 523 1022",
    "sg:postcode":"32835",
    "sg:province":"FL",
    "sg:tags":[
        "painter"
    ],
    "wof:name":"Reginald Denmark Painting Inc",
    "wof:placetype":"venue"
},
  "geometry": {"coordinates":[-81.49619800000001,28.541886],"type":"Point"}
}