{
  "type": "Feature",
  "properties": {
    "iso:country":"US",
    "sg:address":"211 S Mary St",
    "sg:city":"Eustis",
    "sg:classifiers":[
        {
            "category":"Shopping",
            "subcategory":"Used Merchandise",
            "type":"Retail Goods"
        }
    ],
    "sg:phone":"+1 352 589 0641",
    "sg:postcode":"32726",
    "sg:province":"FL",
    "sg:tags":[
        "shop",
        "thrift"
    ],
    "wof:name":"Saint Thomas Thrift Shop",
    "wof:placetype":"venue"
},
  "geometry": {"coordinates":[-81.67929599999999,28.850241],"type":"Point"}
}