{
  "type": "Feature",
  "properties": {
    "iso:country":"US",
    "sg:address":"868 Jupiter Blvd NW",
    "sg:city":"Palm Bay",
    "sg:classifiers":[
        {
            "category":"Personal",
            "subcategory":"Barber",
            "type":"Services"
        }
    ],
    "sg:phone":"+1 321 725 2555",
    "sg:postcode":"32907",
    "sg:province":"FL",
    "wof:name":"Palm Bay Beauty & Barber",
    "wof:placetype":"venue"
},
  "geometry": {"coordinates":[-80.696831,28.021526],"type":"Point"}
}