{
  "type": "Feature",
  "properties": {
    "iso:country":"US",
    "sg:address":"718 S Goldenrod Rd",
    "sg:city":"Orlando",
    "sg:classifiers":[
        {
            "category":"Personal",
            "subcategory":"Nail Salon",
            "type":"Services"
        }
    ],
    "sg:phone":"+1 407 382 8660",
    "sg:postcode":"32822",
    "sg:province":"FL",
    "wof:name":"Md Nails & Spa",
    "wof:placetype":"venue"
},
  "geometry": {"coordinates":[-81.285798,28.535592],"type":"Point"}
}