{
  "type": "Feature",
  "properties": {
    "addr:full":"1271 Coral Way Miami FL 33145",
    "addr:housenumber":"1271",
    "addr:postcode":"33145",
    "addr:street":"Coral Way",
    "iso:country":"US",
    "sg:address":"1271 Coral Way",
    "sg:city":"Miami",
    "sg:classifiers":[
        {
            "category":"Autos & Motor Vehicles",
            "subcategory":"Auto Supplies",
            "type":"Retail Goods"
        }
    ],
    "sg:phone":"+1 305 854 5585",
    "sg:postcode":"33145",
    "sg:province":"FL",
    "sg:tags":[
        "tire"
    ],
    "wof:name":"Tire Safe",
    "wof:placetype":"venue"
},
  "geometry": {"coordinates":[-80.215301,25.751102],"type":"Point"}
}