{
  "type": "Feature",
  "properties": {
    "iso:country":"US",
    "sg:address":"1024 Edgewood Ave W",
    "sg:city":"Jacksonville",
    "sg:classifiers":[
        {
            "category":"Personal",
            "subcategory":"Beauty Salon",
            "type":"Services"
        }
    ],
    "sg:phone":"+1 904 764 4377",
    "sg:postcode":"32208",
    "sg:province":"FL",
    "sg:tags":[
        "treatment",
        "skin"
    ],
    "wof:name":"Ethelyn's Skin & Body Clinic",
    "wof:placetype":"venue"
},
  "geometry": {"coordinates":[-81.674683,30.392246],"type":"Point"}
}