{
  "type": "Feature",
  "properties": {
    "addr:full":"120 SW 13th St Miami FL 33130",
    "addr:housenumber":"120",
    "addr:postcode":"33130",
    "addr:street":"Sw 13Th St",
    "iso:country":"US",
    "sg:address":"120 SW 13th St",
    "sg:city":"Miami",
    "sg:classifiers":[
        {
            "category":"Retail",
            "subcategory":"Laundry & Dry Cleaning",
            "type":"Services"
        }
    ],
    "sg:phone":"+1 305 854 3035",
    "sg:postcode":"33130",
    "sg:province":"FL",
    "sg:tags":[
        "cleaners"
    ],
    "wof:name":"B K Cleaners LLC",
    "wof:placetype":"venue"
},
  "geometry": {"coordinates":[-80.196945,25.761407],"type":"Point"}
}