{
  "type": "Feature",
  "properties": {
    "addr:full":"14527 Bonaire Blvd Delray Beach FL 33446",
    "addr:housenumber":"14527",
    "addr:postcode":"33446",
    "addr:street":"Bonaire Blvd",
    "iso:country":"US",
    "sg:address":"14527 Bonaire Blvd",
    "sg:city":"Delray Beach",
    "sg:classifiers":[
        {
            "category":"Shopping",
            "subcategory":"Gifts & Souvenirs",
            "type":"Retail Goods"
        }
    ],
    "sg:phone":"+1 561 496 0058",
    "sg:postcode":"33446",
    "sg:province":"FL",
    "wof:name":"Aaron Cohen",
    "wof:placetype":"venue"
},
  "geometry": {"coordinates":[-80.1491,26.458831],"type":"Point"}
}