{
  "type": "Feature",
  "properties": {
    "addr:full":"3151 E 4th Ave Hialeah FL 33013",
    "addr:housenumber":"3151",
    "addr:postcode":"33013",
    "addr:street":"E 4Th Ave",
    "iso:country":"US",
    "sg:address":"3151 E 4th Ave",
    "sg:city":"Hialeah",
    "sg:classifiers":[
        {
            "category":"Shopping",
            "subcategory":"Pharmacy",
            "type":"Retail Goods"
        }
    ],
    "sg:phone":"+1 305 691 6610",
    "sg:postcode":"33013",
    "sg:province":"FL",
    "wof:name":"Dinorah Pharmacy Corp",
    "wof:placetype":"venue"
},
  "geometry": {"coordinates":[-80.27452599999999,25.850973],"type":"Point"}
}