{
  "type": "Feature",
  "properties": {
    "addr:full":"3700 NE 28th Ave Pompano Beach FL 33064",
    "addr:housenumber":"3700",
    "addr:postcode":"33064",
    "addr:street":"Ne 28Th Ave",
    "iso:country":"US",
    "sg:address":"3700 NE 28th Ave",
    "sg:city":"Pompano Beach",
    "sg:classifiers":[
        {
            "category":"Building & Trades",
            "subcategory":"Construction",
            "type":"Services"
        }
    ],
    "sg:phone":"+1 954 234 0888",
    "sg:postcode":"33064",
    "sg:province":"FL",
    "sg:tags":[
        "contractor"
    ],
    "wof:name":"Fred T Garrett Construction",
    "wof:placetype":"venue"
},
  "geometry": {"coordinates":[-80.084881,26.278897],"type":"Point"}
}