{
  "type": "Feature",
  "properties": {
    "iso:country":"US",
    "sg:address":"3590 W Broward Blvd",
    "sg:city":"Fort Lauderdale",
    "sg:classifiers":[
        {
            "category":"Insurance",
            "subcategory":"Insurance Agent",
            "type":"Services"
        }
    ],
    "sg:phone":"+1 954 587 6120",
    "sg:postcode":"33312",
    "sg:province":"FL",
    "wof:name":"Valentino Insurance Agency",
    "wof:placetype":"venue"
},
  "geometry": {"coordinates":[-80.195886,26.120952],"type":"Point"}
}