{
  "type": "Feature",
  "properties": {
    "iso:country":"US",
    "sg:address":"13895 Co Rd 109F",
    "sg:city":"Lady Lake",
    "sg:classifiers":[
        {
            "category":"Building & Trades",
            "subcategory":"Cleaning & Sanitation",
            "type":"Services"
        }
    ],
    "sg:phone":"+1 352 874 6421",
    "sg:postcode":"32159",
    "sg:province":"FL",
    "sg:tags":[
        "janitor"
    ],
    "wof:name":"Becky A Fields Cleaning Svc",
    "wof:placetype":"venue"
},
  "geometry": {"coordinates":[-81.97170800000001,28.956607],"type":"Point"}
}