{
  "type": "Feature",
  "properties": {
    "iso:country":"US",
    "sg:address":"2524 Toups Trl",
    "sg:city":"Titusville",
    "sg:classifiers":[
        {
            "category":"Food & Beverages",
            "subcategory":"Bakery",
            "type":"Retail Goods"
        }
    ],
    "sg:phone":"+1 321 269 2699",
    "sg:postcode":"32780",
    "sg:province":"FL",
    "wof:name":"Patti Cakes Cheescake Co",
    "wof:placetype":"venue"
},
  "geometry": {"coordinates":[-80.83139300000001,28.548509],"type":"Point"}
}