{
  "type": "Feature",
  "properties": {
    "addr:full":"10 SW 8th St Miami FL 33130",
    "addr:housenumber":"10",
    "addr:postcode":"33130",
    "addr:street":"Sw 8Th St",
    "iso:country":"US",
    "sg:address":"10 SW 8th St",
    "sg:city":"Miami",
    "sg:classifiers":[
        {
            "category":"Fast Food",
            "type":"Food & Drink"
        },
        {
            "category":"Restaurant",
            "type":"Food & Drink"
        }
    ],
    "sg:phone":"+1 305 373 8444",
    "sg:postcode":"33130",
    "sg:province":"FL",
    "sg:tags":[
        "hot",
        "hamburger",
        "dog",
        "take"
    ],
    "sg:website":"www.burgerking.com",
    "wof:name":"Burger King Restaurants",
    "wof:placetype":"venue"
},
  "geometry": {"coordinates":[-80.19360399999999,25.7665],"type":"Point"}
}