{
  "type": "Feature",
  "properties": {
    "addr:full":"3250 SW 3rd Ave Miami FL 33129",
    "addr:housenumber":"3250",
    "addr:postcode":"33129",
    "addr:street":"Sw 3Rd Ave",
    "iso:country":"US",
    "sg:address":"3250 SW 3rd Ave",
    "sg:city":"Miami",
    "sg:classifiers":[
        {
            "category":"Organizations",
            "subcategory":"Non-profit Organization",
            "type":"Services"
        }
    ],
    "sg:phone":"+1 305 646 7200",
    "sg:postcode":"33129",
    "sg:province":"FL",
    "sg:tags":[
        "service/non-profit",
        "community"
    ],
    "sg:website":"www.handsonmiami.org/",
    "wof:name":"Hands On Miami",
    "wof:placetype":"venue"
},
  "geometry": {"coordinates":[-80.21379899999999,25.751801],"type":"Point"}
}