{
  "type": "Feature",
  "properties": {
    "iso:country":"US",
    "sg:address":"5825 State Hwy 16",
    "sg:city":"St Augustine",
    "sg:classifiers":[
        {
            "category":"Building & Trades",
            "subcategory":"Construction",
            "type":"Services"
        }
    ],
    "sg:phone":"+1 904 646 9565",
    "sg:postcode":"32092",
    "sg:province":"FL",
    "sg:tags":[
        "designer",
        "dealer",
        "pool",
        "swimming"
    ],
    "wof:name":"H & H Pools",
    "wof:placetype":"venue"
},
  "geometry": {"coordinates":[-81.50610500000001,29.972303],"type":"Point"}
}