{
  "type": "Feature",
  "properties": {
    "iso:country":"US",
    "sg:address":"6164 Waterfield Way",
    "sg:city":"St Cloud",
    "sg:classifiers":[
        {
            "category":"Building & Trades",
            "subcategory":"Construction",
            "type":"Services"
        }
    ],
    "sg:phone":"+1 407 957 8007",
    "sg:postcode":"34771",
    "sg:province":"FL",
    "sg:tags":[
        "carpenter"
    ],
    "wof:name":"Handyman Home Repair",
    "wof:placetype":"venue"
},
  "geometry": {"coordinates":[-81.192567,28.254396],"type":"Point"}
}