{
  "type": "Feature",
  "properties": {
    "addr:full":"1101 Marine St Clearwater FL 33755",
    "addr:housenumber":"1101",
    "addr:postcode":"33755",
    "addr:street":"Marine St",
    "iso:country":"US",
    "sg:address":"1101 Marine St",
    "sg:city":"Clearwater",
    "sg:classifiers":[
        {
            "category":"Retail",
            "subcategory":"Repair Shop",
            "type":"Services"
        }
    ],
    "sg:phone":"+1 727 447 2371",
    "sg:postcode":"33755",
    "sg:province":"FL",
    "sg:tags":[
        "repairing",
        "piano",
        "refinishing"
    ],
    "wof:name":"Levi Rice Piano Tuning",
    "wof:placetype":"venue"
},
  "geometry": {"coordinates":[-82.78954299999999,27.996471],"type":"Point"}
}