{
  "type": "Feature",
  "properties": {
    "iso:country":"US",
    "sg:address":"5519 23rd St E",
    "sg:city":"Bradenton",
    "sg:classifiers":[
        {
            "category":"Wholesale",
            "subcategory":"Sporting Goods",
            "type":"Manufacturing & Wholesale Goods"
        }
    ],
    "sg:phone":"+1 941 756 5867",
    "sg:postcode":"34203",
    "sg:province":"FL",
    "sg:tags":[
        "equipment",
        "surfing"
    ],
    "wof:name":"Chozita Del Surf SA",
    "wof:placetype":"venue"
},
  "geometry": {"coordinates":[-82.535088,27.44208],"type":"Point"}
}