{
  "type": "Feature",
  "properties": {
    "addr:full":"13002 E Wheeler Rd Dover FL 33527",
    "addr:housenumber":"13002",
    "addr:postcode":"33527",
    "addr:street":"E Wheeler Rd",
    "iso:country":"US",
    "sg:address":"13002 E Wheeler Rd",
    "sg:city":"Dover",
    "sg:classifiers":[
        {
            "category":"Building & Trades",
            "subcategory":"Landscaping Services",
            "type":"Services"
        }
    ],
    "sg:phone":"+1 813 368 5546",
    "sg:postcode":"33527",
    "sg:province":"FL",
    "wof:name":"C J Design Inc",
    "wof:placetype":"venue"
},
  "geometry": {"coordinates":[-82.244691,27.974408],"type":"Point"}
}