{
  "type": "Feature",
  "properties": {
    "iso:country":"US",
    "sg:address":"8900 High Cotton Ln",
    "sg:city":"Fort Myers",
    "sg:classifiers":[
        {
            "category":"Building & Trades",
            "subcategory":"Construction",
            "type":"Services"
        }
    ],
    "sg:phone":"+1 239 226 1030",
    "sg:postcode":"33905",
    "sg:province":"FL",
    "sg:tags":[
        "concrete",
        "pumping"
    ],
    "wof:name":"Big Johnson's Concrete Pumping",
    "wof:placetype":"venue"
},
  "geometry": {"coordinates":[-81.807233,26.642877],"type":"Point"}
}