{
  "type": "Feature",
  "properties": {
    "iso:country":"US",
    "sg:address":"2656 NE 135th St",
    "sg:city":"North Miami",
    "sg:classifiers":[
        {
            "category":"Banks & Credit Unions",
            "subcategory":"Investment Brokerage",
            "type":"Services"
        }
    ],
    "sg:phone":"+1 305 947 4456",
    "sg:postcode":"33181",
    "sg:province":"FL",
    "sg:tags":[
        "advisory",
        "financial"
    ],
    "wof:name":"S B Financial Consulting Inc",
    "wof:placetype":"venue"
},
  "geometry": {"coordinates":[-80.14392599999999,25.900855],"type":"Point"}
}