{
  "type": "Feature",
  "properties": {
    "iso:country":"US",
    "sg:address":"1507 Sun City Center Plz",
    "sg:city":"Sun City Center",
    "sg:classifiers":[
        {
            "category":"Restaurant",
            "type":"Food & Drink"
        }
    ],
    "sg:phone":"+1 813 633 2720",
    "sg:postcode":"33573",
    "sg:province":"FL",
    "wof:name":"C J's Deli & Cafe",
    "wof:placetype":"venue"
},
  "geometry": {"coordinates":[-82.35377,27.714192],"type":"Point"}
}