{
  "type": "Feature",
  "properties": {
    "addr:full":"4030 Kidron Rd Lakeland FL 33811",
    "addr:postcode":"4030;33811",
    "addr:street":"Kidron Rd",
    "iso:country":"US",
    "sg:address":"4030 Kidron Rd",
    "sg:city":"Lakeland",
    "sg:classifiers":[
        {
            "category":"Professional",
            "subcategory":"Advertising",
            "type":"Services"
        }
    ],
    "sg:phone":"+1 863 709 8088",
    "sg:postcode":"33811",
    "sg:province":"FL",
    "sg:tags":[
        "distribution"
    ],
    "wof:name":"Atec Models",
    "wof:placetype":"venue"
},
  "geometry": {"coordinates":[-82.03094400000001,27.992385],"type":"Point"}
}