{
  "type": "Feature",
  "properties": {
    "addr:full":"1707 Huron St Jacksonville FL 32254",
    "addr:housenumber":"1707",
    "addr:postcode":"32254",
    "addr:street":"Huron St",
    "iso:country":"US",
    "sg:address":"1707 Huron St",
    "sg:city":"Jacksonville",
    "sg:classifiers":[
        {
            "category":"Freight",
            "type":"Transportation"
        }
    ],
    "sg:phone":"+1 904 378 3581",
    "sg:postcode":"32254",
    "sg:province":"FL",
    "sg:tags":[
        "warehouse",
        "merchandise"
    ],
    "wof:name":"Commercial Warehousing Inc",
    "wof:placetype":"venue"
},
  "geometry": {"coordinates":[-81.714,30.346525],"type":"Point"}
}