{
  "type": "Feature",
  "properties": {
    "iso:country":"US",
    "sg:address":"5183 US Hwy 98",
    "sg:city":"Lakeland",
    "sg:classifiers":[
        {
            "category":"Shopping",
            "subcategory":"Bicycles & Sporting Goods",
            "type":"Retail Goods"
        }
    ],
    "sg:phone":"+1 863 858 2000",
    "sg:postcode":"33809",
    "sg:province":"FL",
    "wof:name":"Trek Bicycle Store",
    "wof:placetype":"venue"
},
  "geometry": {"coordinates":[-81.97371800000001,28.109806],"type":"Point"}
}