{
  "type": "Feature",
  "properties": {
    "iso:country":"US",
    "sg:address":"6519 W Newberry Rd # 1016",
    "sg:city":"Gainesville",
    "sg:classifiers":[
        {
            "category":"Professional",
            "subcategory":"Computer Services",
            "type":"Services"
        }
    ],
    "sg:phone":"+1 352 283 8194",
    "sg:postcode":"32605",
    "sg:province":"FL",
    "sg:tags":[
        "consultant",
        "designer",
        "system"
    ],
    "wof:name":"Woodard Bt Enterprises",
    "wof:placetype":"venue"
},
  "geometry": {"coordinates":[-82.421425,29.65961],"type":"Point"}
}