{
  "type": "Feature",
  "properties": {
    "addr:full":"4904 Eisenhower Blvd N Tampa FL 33634",
    "addr:housenumber":"4904",
    "addr:postcode":"33634",
    "addr:street":"Eisenhower Blvd N",
    "iso:country":"US",
    "sg:address":"4904 Eisenhower Blvd N",
    "sg:city":"Tampa",
    "sg:classifiers":[
        {
            "category":"Insurance",
            "subcategory":"Hazard Insurance",
            "type":"Services"
        }
    ],
    "sg:phone":"+1 813 885 4685",
    "sg:postcode":"33634",
    "sg:province":"FL",
    "sg:tags":[
        "mortgage"
    ],
    "wof:name":"Rmic",
    "wof:placetype":"venue"
},
  "geometry": {"coordinates":[-82.545483,27.994513],"type":"Point"}
}