{
  "type": "Feature",
  "properties": {
    "iso:country":"US",
    "sg:address":"The Blue Hotel 5300 N.W. 87th Ave.",
    "sg:city":"Miami",
    "sg:classifiers":[
        {
            "category":"Restaurant",
            "type":"Food & Drink"
        }
    ],
    "sg:phone":"+1 305 597 8600",
    "sg:postcode":"33178",
    "sg:province":"FL",
    "sg:tags":[
        "steakhouse"
    ],
    "sg:website":"www.5300chophouse.com",
    "wof:name":"5300 Chophouse",
    "wof:placetype":"venue"
},
  "geometry": {"coordinates":[-80.33774099999999,25.820873],"type":"Point"}
}