{
  "type": "Feature",
  "properties": {
    "addr:full":"10111 Old Saint Augustine Rd Jacksonville FL 32257",
    "addr:housenumber":"10111",
    "addr:postcode":"32257",
    "addr:street":"Old Saint Augustine Rd",
    "iso:country":"US",
    "sg:address":"10111 Old Saint Augustine Rd",
    "sg:city":"Jacksonville",
    "sg:classifiers":[
        {
            "category":"Personal",
            "subcategory":"Beauty Salon",
            "type":"Services"
        }
    ],
    "sg:phone":"+1 904 880 8855",
    "sg:postcode":"32257",
    "sg:province":"FL",
    "sg:tags":[
        "manicuring"
    ],
    "wof:name":"Kim's Nails",
    "wof:placetype":"venue"
},
  "geometry": {"coordinates":[-81.610764,30.194147],"type":"Point"}
}