{
  "type": "Feature",
  "properties": {
    "addr:full":"1720 Dunlawton Ave Daytona Beach FL 32127",
    "addr:housenumber":"1720",
    "addr:postcode":"32127",
    "addr:street":"Dunlawton Ave",
    "iso:country":"US",
    "sg:address":"1720 Dunlawton Ave",
    "sg:city":"Daytona Beach",
    "sg:classifiers":[
        {
            "category":"Health Services",
            "subcategory":"Doctor",
            "type":"Services"
        }
    ],
    "sg:phone":"+1 386 760 6601",
    "sg:postcode":"32127",
    "sg:province":"FL",
    "sg:tags":[
        "physician",
        "medical",
        "surgeon"
    ],
    "wof:name":"Coastal Ear Nose & Throat PA",
    "wof:placetype":"venue"
},
  "geometry": {"coordinates":[-81.02586599999999,29.110394],"type":"Point"}
}