{
  "type": "Feature",
  "properties": {
    "iso:country":"US",
    "sg:address":"11705 SW 107th Ave",
    "sg:city":"Miami",
    "sg:classifiers":[
        {
            "category":"Professional",
            "subcategory":"Computer Services",
            "type":"Services"
        }
    ],
    "sg:phone":"+1 305 259 2067",
    "sg:postcode":"33176",
    "sg:province":"FL",
    "sg:tags":[
        "consultant",
        "designer",
        "system"
    ],
    "wof:name":"Choicetech",
    "wof:placetype":"venue"
},
  "geometry": {"coordinates":[-80.36751099999999,25.660068],"type":"Point"}
}