{
  "type": "Feature",
  "properties": {
    "addr:full":"528 Sportsman Park Dr Seffner FL 33584",
    "addr:housenumber":"528",
    "addr:postcode":"33584",
    "addr:street":"Sportsman Park Dr Seffner",
    "iso:country":"US",
    "sg:address":"528 Sportsman Park Dr",
    "sg:city":"Seffner",
    "sg:classifiers":[
        {
            "category":"Home & Garden",
            "subcategory":"Home Furnishings",
            "type":"Retail Goods"
        },
        {
            "category":"Building & Trades",
            "subcategory":"Construction",
            "type":"Services"
        }
    ],
    "sg:phone":"+1 813 817 2824",
    "sg:postcode":"33584",
    "sg:province":"FL",
    "sg:tags":[
        "tile-cleaning",
        "refinish",
        "sinks-repair",
        "sealing",
        "bathtub",
        "refinishing"
    ],
    "sg:website":"http://www.suncoasttubntile.com",
    "wof:name":"SunCoast Tub & Tile Restoration",
    "wof:placetype":"venue"
},
  "geometry": {"coordinates":[-82.270652,28.00295],"type":"Point"}
}