{
  "type": "Feature",
  "properties": {
    "addr:full":"1415 16th St Vero Beach FL 32960",
    "addr:housenumber":"1415",
    "addr:postcode":"32960",
    "addr:street":"16Th St",
    "iso:country":"US",
    "sg:address":"1415 16th St",
    "sg:city":"Vero Beach",
    "sg:classifiers":[
        {
            "category":"Manufacturing",
            "subcategory":"Printing",
            "type":"Manufacturing & Wholesale Goods"
        }
    ],
    "sg:phone":"+1 772 770 2199",
    "sg:postcode":"32960",
    "sg:province":"FL",
    "sg:tags":[
        "printer"
    ],
    "sg:website":"www.bigprintsinc.com",
    "wof:name":"Big Prints Inc",
    "wof:placetype":"venue"
},
  "geometry": {"coordinates":[-80.399057,27.631039],"type":"Point"}
}