{
  "type": "Feature",
  "properties": {
    "iso:country":"US",
    "sg:address":"2543 Crawfordville Hwy",
    "sg:city":"Crawfordville",
    "sg:classifiers":[
        {
            "category":"Shopping",
            "subcategory":"Jewelry",
            "type":"Retail Goods"
        }
    ],
    "sg:phone":"+1 850 926 8331",
    "sg:postcode":"32327",
    "sg:province":"FL",
    "wof:name":"Wakulla Jewelers & Repair",
    "wof:placetype":"venue"
},
  "geometry": {"coordinates":[-84.370009,30.196918],"type":"Point"}
}