{
  "type": "Feature",
  "properties": {
    "iso:country":"US",
    "sg:address":"3740 W Lambright St",
    "sg:city":"Tampa",
    "sg:classifiers":[
        {
            "category":"Home & Garden",
            "subcategory":"Building Materials",
            "type":"Retail Goods"
        }
    ],
    "sg:phone":"+1 813 873 2403",
    "sg:postcode":"33614",
    "sg:province":"FL",
    "sg:tags":[
        "marble"
    ],
    "wof:name":"Dal-Tile",
    "wof:placetype":"venue"
},
  "geometry": {"coordinates":[-82.503927,28.00701],"type":"Point"}
}