{
  "type": "Feature",
  "properties": {
    "iso:country":"US",
    "sg:address":"5808 18th St W",
    "sg:city":"Bradenton",
    "sg:classifiers":[
        {
            "category":"Retail",
            "subcategory":"Repair Shop",
            "type":"Services"
        }
    ],
    "sg:phone":"+1 941 752 1606",
    "sg:postcode":"34207",
    "sg:province":"FL",
    "sg:tags":[
        "tile",
        "grout",
        "restoration",
        "cleaning"
    ],
    "wof:name":"Grout Masters",
    "wof:placetype":"venue"
},
  "geometry": {"coordinates":[-82.58014799999999,27.438961],"type":"Point"}
}