{
  "type": "Feature",
  "properties": {
    "addr:full":"2700 Bus Center Blvd Melbourne FL 32940",
    "addr:housenumber":"2700",
    "addr:postcode":"32940",
    "addr:street":"Bus Center Blvd",
    "iso:country":"US",
    "sg:address":"2700 Bus Center Blvd",
    "sg:city":"Melbourne",
    "sg:classifiers":[
        {
            "category":"Building & Trades",
            "subcategory":"Pest Control",
            "type":"Services"
        }
    ],
    "sg:phone":"+1 321 259 2529",
    "sg:postcode":"32940",
    "sg:province":"FL",
    "sg:tags":[
        "disinfecting"
    ],
    "wof:name":"Orkin",
    "wof:placetype":"venue"
},
  "geometry": {"coordinates":[-80.66381,28.19373],"type":"Point"}
}