{
  "type": "Feature",
  "properties": {
    "iso:country":"US",
    "sg:address":"266 W Broad St",
    "sg:city":"Groveland",
    "sg:classifiers":[
        {
            "category":"Fast Food",
            "type":"Food & Drink"
        },
        {
            "category":"Restaurant",
            "type":"Food & Drink"
        }
    ],
    "sg:phone":"+1 352 429 9377",
    "sg:postcode":"34736",
    "sg:province":"FL",
    "sg:tags":[
        "hamburger",
        "hot",
        "dog",
        "american",
        "take"
    ],
    "sg:website":"http://www.hardees.com",
    "wof:name":"Hardee's",
    "wof:placetype":"venue"
},
  "geometry": {"coordinates":[-81.856922,28.561179],"type":"Point"}
}