{
  "type": "Feature",
  "properties": {
    "addr:full":"924 N Federal Hwy Hollywood FL 33020",
    "addr:housenumber":"924",
    "addr:postcode":"33020",
    "addr:street":"N Federal Hwy",
    "iso:country":"US",
    "sg:address":"924 N Federal Hwy",
    "sg:city":"Hollywood",
    "sg:classifiers":[
        {
            "category":"Shopping",
            "subcategory":"Computers & Home Electronics",
            "type":"Retail Goods"
        }
    ],
    "sg:phone":"+1 954 921 6662",
    "sg:postcode":"33020",
    "sg:province":"FL",
    "sg:tags":[
        "repair",
        "television"
    ],
    "wof:name":"Ernies TV Sales & Service",
    "wof:placetype":"venue"
},
  "geometry": {"coordinates":[-80.143304,26.020572],"type":"Point"}
}