{
  "type": "Feature",
  "properties": {
    "addr:full":"4210 Ernest Dr Wesley Chapel FL 33543",
    "addr:housenumber":"4210",
    "addr:postcode":"33543",
    "addr:street":"Ernest Dr",
    "iso:country":"US",
    "sg:address":"4210 Ernest Dr",
    "sg:city":"Wesley Chapel",
    "sg:classifiers":[
        {
            "category":"Organizations",
            "subcategory":"Religious Organization",
            "type":"Services"
        }
    ],
    "sg:phone":"+1 813 783 2225",
    "sg:postcode":"33543",
    "sg:province":"FL",
    "sg:tags":[
        "church"
    ],
    "sg:website":"www.newriverchurch.com",
    "wof:name":"New River Methodist Church",
    "wof:placetype":"venue"
},
  "geometry": {"coordinates":[-82.26199800000001,28.217196],"type":"Point"}
}