{
  "type": "Feature",
  "properties": {
    "iso:country":"US",
    "sg:address":"13001 Alico Rd",
    "sg:city":"Fort Myers",
    "sg:classifiers":[
        {
            "category":"Utilities",
            "subcategory":"Water",
            "type":"Services"
        }
    ],
    "sg:phone":"+1 239 267 1151",
    "sg:postcode":"33913",
    "sg:province":"FL",
    "sg:tags":[
        "company",
        "sewage"
    ],
    "wof:name":"Florida Cities Water Co",
    "wof:placetype":"venue"
},
  "geometry": {"coordinates":[-81.73214,26.493288],"type":"Point"}
}