{
  "type": "Feature",
  "properties": {
    "addr:full":"4738 Live Oak Ln Milton FL 32571",
    "addr:housenumber":"4738",
    "addr:postcode":"32571",
    "addr:street":"Live Oak Ln",
    "iso:country":"US",
    "sg:address":"4738 Live Oak Ln",
    "sg:city":"Milton",
    "sg:classifiers":[
        {
            "category":"Building & Trades",
            "subcategory":"Construction",
            "type":"Services"
        }
    ],
    "sg:phone":"+1 850 995 8922",
    "sg:postcode":"32571",
    "sg:province":"FL",
    "sg:tags":[
        "contractor"
    ],
    "wof:name":"David M Nordby Stucco",
    "wof:placetype":"venue"
},
  "geometry": {"coordinates":[-87.13942,30.604919],"type":"Point"}
}