{
  "type": "Feature",
  "properties": {
    "iso:country":"US",
    "sg:address":"19599 NE 10th Ave Ste E",
    "sg:city":"Miami",
    "sg:classifiers":[
        {
            "category":"Professional",
            "subcategory":"Detective & Security Services",
            "type":"Services"
        }
    ],
    "sg:phone":"+1 305 655 0049",
    "sg:postcode":"33179",
    "sg:province":"FL",
    "sg:tags":[
        "equipment",
        "system",
        "consultant"
    ],
    "sg:website":"http://www.usaidsystems.com",
    "wof:name":"National Comm Inc",
    "wof:placetype":"venue"
},
  "geometry": {"coordinates":[-80.182068,25.955509],"type":"Point"}
}