{
  "type": "Feature",
  "properties": {
    "addr:full":"1574 Main St Dunedin FL 34698",
    "addr:housenumber":"1574",
    "addr:postcode":"34698",
    "addr:street":"Main St",
    "iso:country":"US",
    "sg:address":"1574 Main St",
    "sg:city":"Dunedin",
    "sg:classifiers":[
        {
            "category":"Restaurant",
            "type":"Food & Drink"
        }
    ],
    "sg:menulink":"http://www.allmenus.com/fl/clearwater/111318-mikeys-ny-pizza--subs/menu/",
    "sg:phone":"+1 727 738 8411",
    "sg:postcode":"34698",
    "sg:province":"FL",
    "sg:tags":[
        "american",
        "pizza"
    ],
    "wof:name":"Mikey's N.y. Pizza & Subs",
    "wof:placetype":"venue"
},
  "geometry": {"coordinates":[-82.761442,28.019547],"type":"Point"}
}