{
  "type": "Feature",
  "properties": {
    "iso:country":"US",
    "sg:address":"10436 Crystal Springs Rd",
    "sg:city":"Jacksonville",
    "sg:classifiers":[
        {
            "category":"Building & Trades",
            "subcategory":"Construction",
            "type":"Services"
        }
    ],
    "sg:phone":"+1 904 781 2288",
    "sg:postcode":"32221",
    "sg:province":"FL",
    "sg:tags":[
        "roofing",
        "contractor"
    ],
    "wof:name":"Gator Roofing Of North",
    "wof:placetype":"venue"
},
  "geometry": {"coordinates":[-81.833581,30.301861],"type":"Point"}
}