{
  "type": "Feature",
  "properties": {
    "addr:full":"12800 US Hwy 1 Juno Beach FL 33408",
    "addr:housenumber":"12800",
    "addr:postcode":"33408",
    "addr:street":"Us Hwy 1 Juno Beach",
    "iso:country":"US",
    "sg:address":"12800 US Hwy 1",
    "sg:city":"Juno Beach",
    "sg:classifiers":[
        {
            "category":"Professional",
            "subcategory":"Lawyer & Legal Services",
            "type":"Services"
        }
    ],
    "sg:phone":"+1 561 776 7001",
    "sg:postcode":"33408",
    "sg:province":"FL",
    "sg:tags":[
        "planning",
        "estate"
    ],
    "wof:name":"Cia Services",
    "wof:placetype":"venue"
},
  "geometry": {"coordinates":[-80.056099,26.859802],"type":"Point"}
}