{
  "type": "Feature",
  "properties": {
    "addr:full":"1126 S Patrick Dr Indian Hrbr Bch FL 32937",
    "addr:housenumber":"1126",
    "addr:postcode":"32937",
    "addr:street":"S Patrick Dr Indian Hrbr",
    "iso:country":"US",
    "sg:address":"1126 S Patrick Dr",
    "sg:city":"Indian Hrbr Bch",
    "sg:classifiers":[
        {
            "category":"Building & Trades",
            "subcategory":"Construction",
            "type":"Services"
        }
    ],
    "sg:phone":"+1 321 777 4442",
    "sg:postcode":"32937",
    "sg:province":"FL",
    "sg:tags":[
        "designer",
        "dealer",
        "pool",
        "swimming"
    ],
    "wof:name":"Aqua Blue Aquatech",
    "wof:placetype":"venue"
},
  "geometry": {"coordinates":[-80.606165,28.183164],"type":"Point"}
}