{
  "type": "Feature",
  "properties": {
    "iso:country":"US",
    "sg:address":"9601 SW 142nd Ave",
    "sg:city":"Miami",
    "sg:classifiers":[
        {
            "category":"Food & Beverages",
            "subcategory":"Specialty",
            "type":"Retail Goods"
        }
    ],
    "sg:phone":"+1 305 386 9640",
    "sg:postcode":"33186",
    "sg:province":"FL",
    "sg:tags":[
        "health",
        "diet"
    ],
    "wof:name":"J C Natural Life",
    "wof:placetype":"venue"
},
  "geometry": {"coordinates":[-80.42433699999999,25.672133],"type":"Point"}
}