{
  "type": "Feature",
  "properties": {
    "iso:country":"US",
    "sg:address":"2021 Sunnydale Blvd",
    "sg:city":"Clearwater",
    "sg:classifiers":[
        {
            "category":"Autos & Motor Vehicles",
            "subcategory":"Auto Supplies",
            "type":"Retail Goods"
        }
    ],
    "sg:phone":"+1 727 441 3727",
    "sg:postcode":"33765",
    "sg:province":"FL",
    "sg:tags":[
        "tire"
    ],
    "sg:website":"www.tiresplus.com",
    "wof:name":"Morgan Tire & Auto Inc",
    "wof:placetype":"venue"
},
  "geometry": {"coordinates":[-82.752194,27.986993],"type":"Point"}
}