{
  "type": "Feature",
  "properties": {
    "addr:full":"3164 Redbud Ln Marianna FL 32446",
    "addr:housenumber":"3164",
    "addr:postcode":"32446",
    "addr:street":"Redbud Ln",
    "iso:country":"US",
    "sg:address":"3164 Redbud Ln",
    "sg:city":"Marianna",
    "sg:classifiers":[
        {
            "category":"Real Estate",
            "subcategory":"Real Estate Agent",
            "type":"Services"
        }
    ],
    "sg:phone":"+1 850 482 8676",
    "sg:postcode":"32446",
    "sg:province":"FL",
    "wof:name":"P&F Inc",
    "wof:placetype":"venue"
},
  "geometry": {"coordinates":[-85.146181,30.795143],"type":"Point"}
}