{
  "type": "Feature",
  "properties": {
    "addr:full":"12970 NW 113th Ct Medley FL 33178",
    "addr:housenumber":"12970",
    "addr:postcode":"33178",
    "addr:street":"Nw 113Th Ct",
    "iso:country":"US",
    "sg:address":"12970 NW 113th Ct",
    "sg:city":"Medley",
    "sg:classifiers":[
        {
            "category":"Building & Trades",
            "subcategory":"Construction",
            "type":"Services"
        }
    ],
    "sg:phone":"+1 305 885 4116",
    "sg:postcode":"33178",
    "sg:province":"FL",
    "sg:tags":[
        "boring",
        "drilling",
        "contractor"
    ],
    "sg:website":"www.rwharrisinc.com",
    "wof:name":"R W Harris Inc",
    "wof:placetype":"venue"
},
  "geometry": {"coordinates":[-80.38234300000001,25.895148],"type":"Point"}
}