{
  "type": "Feature",
  "properties": {
    "addr:full":"1713 US Hwy 441 Okeechobee FL 34972",
    "addr:housenumber":"1713",
    "addr:postcode":"34972",
    "addr:street":"Us Hwy 441",
    "iso:country":"US",
    "sg:address":"1713 US Hwy 441",
    "sg:city":"Okeechobee",
    "sg:classifiers":[
        {
            "category":"Health Services",
            "subcategory":"Doctor",
            "type":"Services"
        }
    ],
    "sg:phone":"+1 863 357 2249",
    "sg:postcode":"34972",
    "sg:province":"FL",
    "sg:tags":[
        "physician",
        "surgeon"
    ],
    "wof:name":"Women's Health Specialists",
    "wof:placetype":"venue"
},
  "geometry": {"coordinates":[-80.83001299999999,27.261169],"type":"Point"}
}