{
  "type": "Feature",
  "properties": {
    "iso:country":"US",
    "sg:address":"285 National Pl Unit 137",
    "sg:city":"Longwood",
    "sg:classifiers":[
        {
            "category":"Shopping",
            "subcategory":"Discount & Variety Stores",
            "type":"Retail Goods"
        }
    ],
    "sg:phone":"+1 407 599 5400",
    "sg:postcode":"32750",
    "sg:province":"FL",
    "sg:tags":[
        "outlet"
    ],
    "wof:name":"Cabinet Factory Outlet of Florida",
    "wof:placetype":"venue"
},
  "geometry": {"coordinates":[-81.34945,28.688287],"type":"Point"}
}