{
  "type": "Feature",
  "properties": {
    "addr:full":"10491 SW 97th Ave Miami FL 33176",
    "addr:housenumber":"10491",
    "addr:postcode":"33176",
    "addr:street":"Sw 97Th Ave",
    "iso:country":"US",
    "sg:address":"10491 SW 97th Ave",
    "sg:city":"Miami",
    "sg:classifiers":[
        {
            "category":"Banks & Credit Unions",
            "subcategory":"Investment Brokerage",
            "type":"Services"
        },
        {
            "category":"Banks & Credit Unions",
            "subcategory":"Financial Services",
            "type":"Services"
        }
    ],
    "sg:phone":"+1 305 271 1900",
    "sg:postcode":"33176",
    "sg:province":"FL",
    "sg:tags":[
        "advisory",
        "planner"
    ],
    "wof:name":"Cuba Herzfeld",
    "wof:placetype":"venue"
},
  "geometry": {"coordinates":[-80.35126,25.67162],"type":"Point"}
}