{
  "type": "Feature",
  "properties": {
    "iso:country":"US",
    "sg:address":"6430 Alleghany Ave",
    "sg:city":"Cocoa",
    "sg:classifiers":[
        {
            "category":"Building & Trades",
            "subcategory":"Construction",
            "type":"Services"
        }
    ],
    "sg:phone":"+1 321 508 5064",
    "sg:postcode":"32927",
    "sg:province":"FL",
    "sg:tags":[
        "handyman"
    ],
    "wof:name":"Brian Seli Handyman",
    "wof:placetype":"venue"
},
  "geometry": {"coordinates":[-80.82011799999999,28.469652],"type":"Point"}
}