{
  "type": "Feature",
  "properties": {
    "iso:country":"US",
    "sg:address":"625 Zamora Ave",
    "sg:city":"Coral Gables",
    "sg:classifiers":[
        {
            "category":"Building & Trades",
            "subcategory":"Locksmith",
            "type":"Services"
        }
    ],
    "sg:phone":"+1 305 448 1111",
    "sg:postcode":"33134",
    "sg:province":"FL",
    "sg:tags":[
        "key"
    ],
    "wof:name":"Allied Lock & Key",
    "wof:placetype":"venue"
},
  "geometry": {"coordinates":[-80.267589,25.75638],"type":"Point"}
}