{
  "type": "Feature",
  "properties": {
    "iso:country":"US",
    "sg:address":"355 13th Ave S",
    "sg:city":"Naples",
    "sg:classifiers":[
        {
            "category":"Shopping",
            "subcategory":"Clothing, Apparel, & Fashions",
            "type":"Retail Goods"
        }
    ],
    "sg:phone":"+1 239 262 0906",
    "sg:postcode":"34102",
    "sg:province":"FL",
    "wof:name":"Zita Inc Womens Apparel",
    "wof:placetype":"venue"
},
  "geometry": {"coordinates":[-81.80108199999999,26.131093],"type":"Point"}
}