{
  "type": "Feature",
  "properties": {
    "iso:country":"US",
    "sg:address":"1502 Industrial St",
    "sg:city":"Edgewater",
    "sg:classifiers":[
        {
            "category":"Retail",
            "subcategory":"Auto Repair",
            "type":"Services"
        }
    ],
    "sg:phone":"+1 386 426 0280",
    "sg:postcode":"32132",
    "sg:province":"FL",
    "sg:tags":[
        "repairing",
        "automobile"
    ],
    "wof:name":"Kar Kare",
    "wof:placetype":"venue"
},
  "geometry": {"coordinates":[-80.903301,28.974229],"type":"Point"}
}