{
  "type": "Feature",
  "properties": {
    "iso:country":"US",
    "sg:address":"2330 Woodside Way",
    "sg:city":"Kissimmee",
    "sg:classifiers":[
        {
            "category":"Professional",
            "type":"Services"
        }
    ],
    "sg:phone":"+1 407 931 1480",
    "sg:postcode":"34744",
    "sg:province":"FL",
    "wof:name":"Cottage Kids",
    "wof:placetype":"venue"
},
  "geometry": {"coordinates":[-81.381629,28.312919],"type":"Point"}
}