{
  "type": "Feature",
  "properties": {
    "addr:full":"2190 Airport Blvd Pensacola FL 32503",
    "addr:housenumber":"2190",
    "addr:postcode":"32503",
    "addr:street":"Airport Blvd",
    "iso:country":"US",
    "sg:address":"2190 Airport Blvd",
    "sg:city":"Pensacola",
    "sg:classifiers":[
        {
            "category":"Professional",
            "subcategory":"Employment Agencies",
            "type":"Services"
        }
    ],
    "sg:phone":"+1 850 476 3712",
    "sg:postcode":"32503",
    "sg:province":"FL",
    "sg:tags":[
        "help",
        "supply"
    ],
    "wof:name":"Adecco Staffing",
    "wof:placetype":"venue"
},
  "geometry": {"coordinates":[-87.20173800000001,30.476153],"type":"Point"}
}