{
  "type": "Feature",
  "properties": {
    "iso:country":"US",
    "sg:address":"2569 Gulf Breeze Pkwy",
    "sg:city":"Gulf Breeze",
    "sg:classifiers":[
        {
            "category":"Health Services",
            "subcategory":"Doctor",
            "type":"Services"
        }
    ],
    "sg:phone":"+1 850 932 0440",
    "sg:postcode":"32563",
    "sg:province":"FL",
    "sg:tags":[
        "physician",
        "surgeon"
    ],
    "wof:name":"First Physicians",
    "wof:placetype":"venue"
},
  "geometry": {"coordinates":[-87.116083,30.376072],"type":"Point"}
}