{
  "type": "Feature",
  "properties": {
    "iso:country":"US",
    "sg:address":"3258 Parkside Center Cir",
    "sg:city":"Tampa",
    "sg:classifiers":[
        {
            "category":"Health Services",
            "subcategory":"Clinic",
            "type":"Services"
        }
    ],
    "sg:phone":"+1 813 635 0595",
    "sg:postcode":"33619",
    "sg:province":"FL",
    "wof:name":"Ace Endeavors LLC",
    "wof:placetype":"venue"
},
  "geometry": {"coordinates":[-82.336191,27.973341],"type":"Point"}
}