{
  "type": "Feature",
  "properties": {
    "iso:country":"US",
    "sg:address":"2350 N Volusia Ave",
    "sg:city":"Orange City",
    "sg:classifiers":[
        {
            "category":"Shopping",
            "subcategory":"Pets & Pet Supplies",
            "type":"Retail Goods"
        },
        {
            "category":"Retail",
            "subcategory":"Pet Boarding",
            "type":"Services"
        }
    ],
    "sg:phone":"+1 386 774 2008",
    "sg:postcode":"32763",
    "sg:province":"FL",
    "sg:tags":[
        "training",
        "boarding/pet",
        "sitting"
    ],
    "wof:name":"Party Animals",
    "wof:placetype":"venue"
},
  "geometry": {"coordinates":[-81.298483,28.96846],"type":"Point"}
}