{
  "type": "Feature",
  "properties": {
    "addr:full":"3188 Pga Blvd West Palm Beach FL 33410",
    "addr:housenumber":"3188",
    "addr:postcode":"33410",
    "addr:street":"Pga Blvd",
    "iso:country":"US",
    "sg:address":"3188 Pga Blvd",
    "sg:city":"West Palm Beach",
    "sg:classifiers":[
        {
            "category":"Government",
            "subcategory":"Office",
            "type":"Public Place"
        }
    ],
    "sg:phone":"+1 561 624 6521",
    "sg:postcode":"33410",
    "sg:province":"FL",
    "wof:name":"Palm Beach Cnty Property Aprrs",
    "wof:placetype":"venue"
},
  "geometry": {"coordinates":[-80.083697,26.844864],"type":"Point"}
}