{
  "type": "Feature",
  "properties": {
    "iso:country":"US",
    "sg:address":"2560 Benjamin Rd",
    "sg:city":"Jacksonville",
    "sg:classifiers":[
        {
            "category":"Health Services",
            "subcategory":"Clinic",
            "type":"Services"
        }
    ],
    "sg:phone":"+1 904 288 7008",
    "sg:postcode":"32223",
    "sg:province":"FL",
    "sg:tags":[
        "information",
        "medical"
    ],
    "wof:name":"Medical Outcome Systems Inc",
    "wof:placetype":"venue"
},
  "geometry": {"coordinates":[-81.643241,30.160016],"type":"Point"}
}