{
  "type": "Feature",
  "properties": {
    "addr:full":"900 Jamestown Ave Indian Hrbr Bch FL 32937",
    "addr:housenumber":"900",
    "addr:postcode":"32937",
    "addr:street":"Jamestown Ave",
    "iso:country":"US",
    "sg:address":"900 Jamestown Ave",
    "sg:city":"Indian Hrbr Bch",
    "sg:classifiers":[
        {
            "category":"Real Estate",
            "subcategory":"Real Estate Operator",
            "type":"Services"
        }
    ],
    "sg:phone":"+1 321 777 1425",
    "sg:postcode":"32937",
    "sg:province":"FL",
    "sg:tags":[
        "condominium"
    ],
    "wof:name":"Jamestown Condominium",
    "wof:placetype":"venue"
},
  "geometry": {"coordinates":[-80.585864,28.148082],"type":"Point"}
}