{
  "type": "Feature",
  "properties": {
    "iso:country":"US",
    "sg:address":"7430 NE 2nd Ave",
    "sg:city":"Miami",
    "sg:classifiers":[
        {
            "category":"Professional",
            "subcategory":"Detective & Security Services",
            "type":"Services"
        }
    ],
    "sg:phone":"+1 305 895 3556",
    "sg:postcode":"33138",
    "sg:province":"FL",
    "sg:tags":[
        "guard",
        "patrol"
    ],
    "wof:name":"Famous Security Services Inc",
    "wof:placetype":"venue"
},
  "geometry": {"coordinates":[-80.192644,25.843243],"type":"Point"}
}