{
  "type": "Feature",
  "properties": {
    "iso:country":"US",
    "sg:address":"8679 SW 24th St",
    "sg:city":"Miami",
    "sg:classifiers":[
        {
            "category":"Restaurant",
            "type":"Food & Drink"
        }
    ],
    "sg:phone":"+1 305 261 8665",
    "sg:postcode":"33155",
    "sg:province":"FL",
    "sg:tags":[
        "american",
        "latin"
    ],
    "wof:name":"Que Arepa Restaurant",
    "wof:placetype":"venue"
},
  "geometry": {"coordinates":[-80.335262,25.747702],"type":"Point"}
}