{
  "type": "Feature",
  "properties": {
    "addr:full":"11912 Miramar Pkwy Miramar FL 33025",
    "addr:housenumber":"11912",
    "addr:postcode":"33025",
    "addr:street":"Miramar Pkwy",
    "iso:country":"US",
    "sg:address":"11912 Miramar Pkwy",
    "sg:city":"Miramar",
    "sg:classifiers":[
        {
            "category":"Retail",
            "subcategory":"Auto Rental",
            "type":"Services"
        },
        {
            "category":"Retail",
            "subcategory":"Storage",
            "type":"Services"
        }
    ],
    "sg:phone":"+1 954 433 0875",
    "sg:postcode":"33025",
    "sg:province":"FL",
    "sg:tags":[
        "car",
        "moving-self",
        "truck"
    ],
    "wof:name":"Broward County Truck Rental & Equipment",
    "wof:placetype":"venue"
},
  "geometry": {"coordinates":[-80.304754,25.978629],"type":"Point"}
}