{
  "type": "Feature",
  "properties": {
    "iso:country":"US",
    "sg:address":"505 del Prado Blvd N",
    "sg:city":"Cape Coral",
    "sg:classifiers":[
        {
            "category":"Shopping",
            "type":"Retail Goods"
        }
    ],
    "sg:phone":"+1 239 772 5155",
    "sg:postcode":"33909",
    "sg:province":"FL",
    "sg:tags":[
        "medical",
        "apparatus"
    ],
    "wof:name":"Mobility Unlimited",
    "wof:placetype":"venue"
},
  "geometry": {"coordinates":[-81.940916,26.662987],"type":"Point"}
}