{
  "type": "Feature",
  "properties": {
    "addr:full":"428 SW Akron Ave Stuart FL 34994",
    "addr:housenumber":"428",
    "addr:postcode":"34994",
    "addr:street":"Sw Akron Ave",
    "iso:country":"US",
    "sg:address":"428 SW Akron Ave",
    "sg:city":"Stuart",
    "sg:classifiers":[
        {
            "category":"Professional",
            "subcategory":"Computer Services",
            "type":"Services"
        }
    ],
    "sg:phone":"+1 772 287 6564",
    "sg:postcode":"34994",
    "sg:province":"FL",
    "sg:tags":[
        "school",
        "processing",
        "datum",
        "related"
    ],
    "wof:name":"Littlemacs School House",
    "wof:placetype":"venue"
},
  "geometry": {"coordinates":[-80.255557,27.197225],"type":"Point"}
}