{
  "type": "Feature",
  "properties": {
    "iso:country":"US",
    "sg:address":"4700 Hiatus Rd",
    "sg:city":"Fort Lauderdale",
    "sg:classifiers":[
        {
            "category":"Banks & Credit Unions",
            "subcategory":"Bank",
            "type":"Services"
        }
    ],
    "sg:phone":"+1 954 578 3788",
    "sg:postcode":"33351",
    "sg:province":"FL",
    "sg:tags":[
        "broker",
        "mortgage"
    ],
    "wof:name":"Korn Capital Funding LLC",
    "wof:placetype":"venue"
},
  "geometry": {"coordinates":[-80.29092199999999,26.181161],"type":"Point"}
}