{
  "type": "Feature",
  "properties": {
    "addr:full":"1425 Walnut St Jacksonville FL 32206",
    "addr:housenumber":"1425",
    "addr:postcode":"32206",
    "addr:street":"Walnut St",
    "iso:country":"US",
    "sg:address":"1425 Walnut St",
    "sg:city":"Jacksonville",
    "sg:classifiers":[
        {
            "category":"Organizations",
            "subcategory":"Religious Organization",
            "type":"Services"
        }
    ],
    "sg:phone":"+1 904 356 5755",
    "sg:postcode":"32206",
    "sg:province":"FL",
    "sg:tags":[
        "church"
    ],
    "wof:name":"Good Samaritan Temple",
    "wof:placetype":"venue"
},
  "geometry": {"coordinates":[-81.64837799999999,30.33994],"type":"Point"}
}