{
  "type": "Feature",
  "properties": {
    "iso:country":"US",
    "sg:address":"19400 NW 2nd Ave",
    "sg:city":"Miami",
    "sg:classifiers":[
        {
            "category":"Manufacturing",
            "subcategory":"Leather Goods",
            "type":"Manufacturing & Wholesale Goods"
        },
        {
            "category":"Autos & Motor Vehicles",
            "subcategory":"Motorcycle Sales",
            "type":"Retail Goods"
        }
    ],
    "sg:phone":"+1 305 651 4811",
    "sg:postcode":"33169",
    "sg:province":"FL",
    "wof:name":"Phil Petersons Harley Davidson",
    "wof:placetype":"venue"
},
  "geometry": {"coordinates":[-80.205704,25.952499],"type":"Point"}
}