{
  "type": "Feature",
  "properties": {
    "addr:full":"7109 NW 11th Ave Gainesville FL 32605",
    "addr:housenumber":"7109",
    "addr:postcode":"32605",
    "addr:street":"Nw 11Th Ave",
    "iso:country":"US",
    "sg:address":"7109 NW 11th Ave",
    "sg:city":"Gainesville",
    "sg:classifiers":[
        {
            "category":"Health Services",
            "subcategory":"Doctor",
            "type":"Services"
        }
    ],
    "sg:phone":"+1 352 331 1773",
    "sg:postcode":"32605",
    "sg:province":"FL",
    "sg:tags":[
        "medical"
    ],
    "wof:name":"John A Dryfuss MD PA",
    "wof:placetype":"venue"
},
  "geometry": {"coordinates":[-82.375816,29.662608],"type":"Point"}
}