{
  "type": "Feature",
  "properties": {
    "iso:country":"US",
    "sg:address":"8405 NW 53rd St",
    "sg:city":"Miami",
    "sg:classifiers":[
        {
            "category":"Health Services",
            "subcategory":"Health Practitioner",
            "type":"Services"
        }
    ],
    "sg:phone":"+1 305 599 2111",
    "sg:postcode":"33166",
    "sg:province":"FL",
    "sg:tags":[
        "psychotherapist"
    ],
    "wof:name":"Center For Diagnostic Svc",
    "wof:placetype":"venue"
},
  "geometry": {"coordinates":[-80.334598,25.819921],"type":"Point"}
}