{
  "type": "Feature",
  "properties": {
    "iso:country":"US",
    "sg:address":"180 Royal Palm Way",
    "sg:city":"Palm Beach",
    "sg:classifiers":[
        {
            "category":"Banks & Credit Unions",
            "subcategory":"Financial Services",
            "type":"Services"
        }
    ],
    "sg:phone":"+1 561 659 4900",
    "sg:postcode":"33480",
    "sg:province":"FL",
    "sg:tags":[
        "company",
        "holding"
    ],
    "sg:website":"www.lydian.com",
    "wof:name":"Lydian Private Bank",
    "wof:placetype":"venue"
},
  "geometry": {"coordinates":[-80.034267,26.70549],"type":"Point"}
}