{
  "type": "Feature",
  "properties": {
    "iso:country":"US",
    "sg:address":"14286 Beach Blvd",
    "sg:city":"Jacksonville Bch",
    "sg:classifiers":[
        {
            "category":"Restaurant",
            "type":"Food & Drink"
        }
    ],
    "sg:phone":"+1 904 223 0115",
    "sg:postcode":"32250",
    "sg:province":"FL",
    "sg:website":"www.dickswings.com",
    "wof:name":"Dick's Wings",
    "wof:placetype":"venue"
},
  "geometry": {"coordinates":[-81.441652,30.287774],"type":"Point"}
}