{
  "type": "Feature",
  "properties": {
    "addr:full":"16932 78th Rd N Loxahatchee FL 33470",
    "addr:housenumber":"16932",
    "addr:postcode":"33470",
    "addr:street":"78Th Rd N",
    "iso:country":"US",
    "sg:address":"16932 78th Rd N",
    "sg:city":"Loxahatchee",
    "sg:classifiers":[
        {
            "category":"Building & Trades",
            "subcategory":"Plumbing",
            "type":"Services"
        }
    ],
    "sg:phone":"+1 561 795 9380",
    "sg:postcode":"33470",
    "sg:province":"FL",
    "sg:tags":[
        "plumbing",
        "contractor"
    ],
    "wof:name":"Royal Rooter Sewer & Drain",
    "wof:placetype":"venue"
},
  "geometry": {"coordinates":[-80.309755,26.792097],"type":"Point"}
}