{
  "type": "Feature",
  "properties": {
    "addr:full":"151 E Lakeview Ave Eustis FL 32726",
    "addr:housenumber":"151",
    "addr:postcode":"32726",
    "addr:street":"E Lakeview Ave",
    "iso:country":"US",
    "sg:address":"151 E Lakeview Ave",
    "sg:city":"Eustis",
    "sg:classifiers":[
        {
            "category":"Health Services",
            "subcategory":"Doctor",
            "type":"Services"
        }
    ],
    "sg:phone":"+1 352 483 1410",
    "sg:postcode":"32726",
    "sg:province":"FL",
    "sg:tags":[
        "medical"
    ],
    "wof:name":"Florida Neurology PA",
    "wof:placetype":"venue"
},
  "geometry": {"coordinates":[-81.68407999999999,28.841951],"type":"Point"}
}