{
  "type": "Feature",
  "properties": {
    "addr:full":"7444 SW 117th Ave Miami FL 33183",
    "addr:housenumber":"7444",
    "addr:postcode":"33183",
    "addr:street":"Sw 117Th Ave",
    "iso:country":"US",
    "sg:address":"7444 SW 117th Ave",
    "sg:city":"Miami",
    "sg:classifiers":[
        {
            "category":"Shopping",
            "subcategory":"Clothing, Apparel, & Fashions",
            "type":"Retail Goods"
        }
    ],
    "sg:phone":"+1 305 412 2466",
    "sg:postcode":"33183",
    "sg:province":"FL",
    "wof:name":"Secret Lady",
    "wof:placetype":"venue"
},
  "geometry": {"coordinates":[-80.38218999999999,25.700515],"type":"Point"}
}