{
  "type": "Feature",
  "properties": {
    "addr:full":"127 N Miami Ave Miami FL 33128",
    "addr:housenumber":"127",
    "addr:postcode":"33128",
    "addr:street":"N Miami Ave",
    "iso:country":"US",
    "sg:address":"127 N Miami Ave",
    "sg:city":"Miami",
    "sg:classifiers":[
        {
            "category":"Restaurant",
            "type":"Food & Drink"
        }
    ],
    "sg:phone":"+1 786 425 2969",
    "sg:postcode":"33128",
    "sg:province":"FL",
    "wof:name":"Ronceli's",
    "wof:placetype":"venue"
},
  "geometry": {"coordinates":[-80.19380200000001,25.775499],"type":"Point"}
}