{
  "type": "Feature",
  "properties": {
    "iso:country":"US",
    "sg:address":"6820 Ramoth Dr",
    "sg:city":"Jacksonville",
    "sg:classifiers":[
        {
            "category":"Building & Trades",
            "subcategory":"Construction",
            "type":"Services"
        }
    ],
    "sg:phone":"+1 904 251 9814",
    "sg:postcode":"32226",
    "sg:province":"FL",
    "sg:tags":[
        "floor",
        "laying",
        "contractor"
    ],
    "wof:name":"Dr Carpet",
    "wof:placetype":"venue"
},
  "geometry": {"coordinates":[-81.498268,30.393571],"type":"Point"}
}