{
  "type": "Feature",
  "properties": {
    "iso:country":"US",
    "sg:address":"500 W Airport Blvd",
    "sg:city":"Sanford",
    "sg:classifiers":[
        {
            "category":"Local Transit",
            "type":"Transportation"
        }
    ],
    "sg:phone":"+1 407 330 5832",
    "sg:postcode":"32773",
    "sg:province":"FL",
    "sg:tags":[
        "passenger"
    ],
    "wof:name":"Jose B Escalera",
    "wof:placetype":"venue"
},
  "geometry": {"coordinates":[-81.286266,28.772943],"type":"Point"}
}