{
  "type": "Feature",
  "properties": {
    "iso:country":"US",
    "sg:address":"867 Sebastian Blvd",
    "sg:city":"Sebastian",
    "sg:classifiers":[
        {
            "category":"Building & Trades",
            "subcategory":"Construction",
            "type":"Services"
        },
        {
            "category":"Manufacturing",
            "subcategory":"Building Materials",
            "type":"Manufacturing & Wholesale Goods"
        }
    ],
    "sg:phone":"+1 772 388 1997",
    "sg:postcode":"32958",
    "sg:province":"FL",
    "sg:tags":[
        "siding",
        "door",
        "window",
        "storm",
        "contractor"
    ],
    "wof:name":"Treasure Coast Aluminum",
    "wof:placetype":"venue"
},
  "geometry": {"coordinates":[-80.49593400000001,27.78091],"type":"Point"}
}