{
  "type": "Feature",
  "properties": {
    "iso:country":"US",
    "sg:address":"1240 SW 12th Ave",
    "sg:city":"Pompano Beach",
    "sg:classifiers":[
        {
            "category":"Manufacturing",
            "subcategory":"Glass & Minerals",
            "type":"Manufacturing & Wholesale Goods"
        }
    ],
    "sg:phone":"+1 954 933 0718",
    "sg:postcode":"33069",
    "sg:province":"FL",
    "sg:tags":[
        "fabricator",
        "marble",
        "granite"
    ],
    "wof:name":"Prima Marble & Granite",
    "wof:placetype":"venue"
},
  "geometry": {"coordinates":[-80.138715,26.214304],"type":"Point"}
}