{
  "type": "Feature",
  "properties": {
    "iso:country":"US",
    "sg:address":"906 Santa Barbara Dr",
    "sg:city":"Sanford",
    "sg:classifiers":[
        {
            "category":"Building & Trades",
            "subcategory":"Construction",
            "type":"Services"
        }
    ],
    "sg:phone":"+1 407 320 0711",
    "sg:postcode":"32773",
    "sg:province":"FL",
    "sg:tags":[
        "contractor"
    ],
    "wof:name":"Rescreen Specialist",
    "wof:placetype":"venue"
},
  "geometry": {"coordinates":[-81.276968,28.781035],"type":"Point"}
}