{
  "type": "Feature",
  "properties": {
    "iso:country":"US",
    "sg:address":"2290 S Palmetto Ave",
    "sg:city":"Daytona Beach",
    "sg:classifiers":[
        {
            "category":"Real Estate",
            "subcategory":"Real Estate Operator",
            "type":"Services"
        }
    ],
    "sg:phone":"+1 407 330 9281",
    "sg:postcode":"32119",
    "sg:province":"FL",
    "sg:tags":[
        "property"
    ],
    "wof:name":"River South Apartments",
    "wof:placetype":"venue"
},
  "geometry": {"coordinates":[-81.00058199999999,29.172708],"type":"Point"}
}