{
  "type": "Feature",
  "properties": {
    "iso:country":"US",
    "sg:address":"2502 Willamette Rd",
    "sg:city":"Tallahassee",
    "sg:classifiers":[
        {
            "category":"Professional",
            "subcategory":"Art Services",
            "type":"Services"
        }
    ],
    "sg:phone":"+1 850 656 4429",
    "sg:postcode":"32303",
    "sg:province":"FL",
    "sg:tags":[
        "designer",
        "display",
        "producer"
    ],
    "wof:name":"Crowson Design Productions",
    "wof:placetype":"venue"
},
  "geometry": {"coordinates":[-84.313202,30.475835],"type":"Point"}
}