{
  "type": "Feature",
  "properties": {
    "addr:full":"4300 US Hwy 98 Lakeland FL 33809",
    "addr:housenumber":"4300",
    "addr:postcode":"33809",
    "addr:street":"Us Hwy 98",
    "iso:country":"US",
    "sg:address":"4300 US Hwy 98",
    "sg:city":"Lakeland",
    "sg:classifiers":[
        {
            "category":"Banks & Credit Unions",
            "subcategory":"Bank",
            "type":"Services"
        }
    ],
    "sg:phone":"+1 863 816 8886",
    "sg:postcode":"33809",
    "sg:province":"FL",
    "sg:tags":[
        "state",
        "commercial"
    ],
    "wof:name":"AmSouth",
    "wof:placetype":"venue"
},
  "geometry": {"coordinates":[-81.971875,28.086565],"type":"Point"}
}