{
  "type": "Feature",
  "properties": {
    "addr:full":"7911 NW 72nd Ave Medley FL 33166",
    "addr:housenumber":"7911",
    "addr:postcode":"33166",
    "addr:street":"Nw 72Nd Ave",
    "iso:country":"US",
    "sg:address":"7911 NW 72nd Ave",
    "sg:city":"Medley",
    "sg:classifiers":[
        {
            "category":"Health Services",
            "subcategory":"Health Practitioner",
            "type":"Services"
        }
    ],
    "sg:phone":"+1 305 883 6180",
    "sg:postcode":"33166",
    "sg:province":"FL",
    "sg:tags":[
        "therapist",
        "physical"
    ],
    "wof:name":"Active Therapy Assoc",
    "wof:placetype":"venue"
},
  "geometry": {"coordinates":[-80.314283,25.846408],"type":"Point"}
}