{
  "type": "Feature",
  "properties": {
    "iso:country":"US",
    "sg:address":"13621 Walsingham Rd",
    "sg:city":"Largo",
    "sg:classifiers":[
        {
            "category":"Building & Trades",
            "subcategory":"Construction",
            "type":"Services"
        }
    ],
    "sg:phone":"+1 727 595 0914",
    "sg:postcode":"33774",
    "sg:province":"FL",
    "sg:tags":[
        "general",
        "contractor"
    ],
    "wof:name":"Cobblestone Construction",
    "wof:placetype":"venue"
},
  "geometry": {"coordinates":[-82.82548199999999,27.880438],"type":"Point"}
}