{
  "type": "Feature",
  "properties": {
    "addr:full":"540 Fontaine St Pensacola FL 32503",
    "addr:housenumber":"540",
    "addr:postcode":"32503",
    "addr:street":"Fontaine St",
    "iso:country":"US",
    "sg:address":"540 Fontaine St",
    "sg:city":"Pensacola",
    "sg:classifiers":[
        {
            "category":"Professional",
            "type":"Services"
        }
    ],
    "sg:phone":"+1 850 484 4774",
    "sg:postcode":"32503",
    "sg:province":"FL",
    "sg:tags":[
        "establishment"
    ],
    "wof:name":"Skinpath",
    "wof:placetype":"venue"
},
  "geometry": {"coordinates":[-87.223072,30.475543],"type":"Point"}
}