{
  "type": "Feature",
  "properties": {
    "addr:full":"112 W Main St Immokalee FL 34142",
    "addr:housenumber":"112",
    "addr:postcode":"34142",
    "addr:street":"W Main St",
    "iso:country":"US",
    "sg:address":"112 W Main St",
    "sg:city":"Immokalee",
    "sg:classifiers":[
        {
            "category":"Professional",
            "subcategory":"Lawyer & Legal Services",
            "type":"Services"
        }
    ],
    "sg:phone":"+1 239 657 2500",
    "sg:postcode":"34142",
    "sg:province":"FL",
    "sg:tags":[
        "attorney"
    ],
    "wof:name":"Myers Mooney & Stadnley",
    "wof:placetype":"venue"
},
  "geometry": {"coordinates":[-81.41836499999999,26.418528],"type":"Point"}
}