{
  "type": "Feature",
  "properties": {
    "addr:full":"1530 NE 34th St Pompano Beach FL 33064",
    "addr:housenumber":"1530",
    "addr:postcode":"33064",
    "addr:street":"Ne 34Th St",
    "iso:country":"US",
    "sg:address":"1530 NE 34th St",
    "sg:city":"Pompano Beach",
    "sg:classifiers":[
        {
            "category":"Manufacturing",
            "subcategory":"Signs",
            "type":"Manufacturing & Wholesale Goods"
        }
    ],
    "sg:phone":"+1 954 545 0526",
    "sg:postcode":"33064",
    "sg:province":"FL",
    "wof:name":"Action Sign & Lighting Co",
    "wof:placetype":"venue"
},
  "geometry": {"coordinates":[-80.101164,26.2733],"type":"Point"}
}