{
  "type": "Feature",
  "properties": {
    "addr:full":"3063 NE 147th Ter Silver Springs FL 34488",
    "addr:housenumber":"3063",
    "addr:postcode":"34488",
    "addr:street":"Ne 147Th Ter",
    "iso:country":"US",
    "sg:address":"3063 NE 147th Ter",
    "sg:city":"Silver Springs",
    "sg:classifiers":[
        {
            "category":"Professional",
            "subcategory":"Art Services",
            "type":"Services"
        }
    ],
    "sg:phone":"+1 352 625 5424",
    "sg:postcode":"34488",
    "sg:province":"FL",
    "sg:tags":[
        "photographer"
    ],
    "wof:name":"Images By Marie Photography",
    "wof:placetype":"venue"
},
  "geometry": {"coordinates":[-81.909302,29.216901],"type":"Point"}
}