{
  "type": "Feature",
  "properties": {
    "iso:country":"US",
    "sg:address":"1202 S Church Ave Ste B",
    "sg:city":"Tampa",
    "sg:classifiers":[
        {
            "category":"Shopping",
            "subcategory":"Department Store",
            "type":"Retail Goods"
        },
        {
            "category":"Shopping",
            "subcategory":"Discount & Variety Stores",
            "type":"Retail Goods"
        }
    ],
    "sg:phone":"+1 813 254 4494",
    "sg:postcode":"33629",
    "sg:province":"FL",
    "wof:name":"Store 2",
    "wof:placetype":"venue"
},
  "geometry": {"coordinates":[-82.507885,27.931463],"type":"Point"}
}