{
  "type": "Feature",
  "properties": {
    "addr:full":"1005 21st St Vero Beach FL 32960",
    "addr:housenumber":"1005",
    "addr:postcode":"32960",
    "addr:street":"21St St",
    "iso:country":"US",
    "sg:address":"1005 21st St",
    "sg:city":"Vero Beach",
    "sg:classifiers":[
        {
            "category":"Autos & Motor Vehicles",
            "subcategory":"Fuel & Gas Station",
            "type":"Retail Goods"
        }
    ],
    "sg:phone":"+1 772 299 1933",
    "sg:postcode":"32960",
    "sg:province":"FL",
    "sg:tags":[
        "station",
        "gasoline"
    ],
    "wof:name":"J J Marathon",
    "wof:placetype":"venue"
},
  "geometry": {"coordinates":[-80.39495599999999,27.639703],"type":"Point"}
}