{
  "type": "Feature",
  "properties": {
    "addr:full":"1007 Seminole St Clearwater FL 33755",
    "addr:housenumber":"1007",
    "addr:postcode":"33755",
    "addr:street":"Seminole St",
    "iso:country":"US",
    "sg:address":"1007 Seminole St",
    "sg:city":"Clearwater",
    "sg:classifiers":[
        {
            "category":"Building & Trades",
            "subcategory":"Landscaping Services",
            "type":"Services"
        }
    ],
    "sg:phone":"+1 727 461 0356",
    "sg:postcode":"33755",
    "sg:province":"FL",
    "sg:tags":[
        "lawn",
        "maintenance",
        "grounds"
    ],
    "wof:name":"Ozell's Ground Maintenance Inc",
    "wof:placetype":"venue"
},
  "geometry": {"coordinates":[-82.791871,27.973482],"type":"Point"}
}