{
  "type": "Feature",
  "properties": {
    "addr:full":"7680 Universal Blvd Orlando FL 32819",
    "addr:housenumber":"7680",
    "addr:postcode":"32819",
    "addr:street":"Universal Blvd",
    "iso:country":"US",
    "sg:address":"7680 Universal Blvd",
    "sg:city":"Orlando",
    "sg:classifiers":[
        {
            "category":"Professional",
            "subcategory":"Management & Consulting",
            "type":"Services"
        }
    ],
    "sg:phone":"+1 407 894 6405",
    "sg:postcode":"32819",
    "sg:province":"FL",
    "sg:tags":[
        "food",
        "facility"
    ],
    "sg:website":"www.proftesting.com",
    "wof:name":"Professional Testing Inc",
    "wof:placetype":"venue"
},
  "geometry": {"coordinates":[-81.466104,28.447929],"type":"Point"}
}