{
  "type": "Feature",
  "properties": {
    "addr:full":"11621 Nellie Oaks Bend Clermont FL 34711",
    "addr:housenumber":"11621",
    "addr:postcode":"34711",
    "addr:street":"Nellie Oaks Bend",
    "iso:country":"US",
    "sg:address":"11621 Nellie Oaks Bend",
    "sg:city":"Clermont",
    "sg:classifiers":[
        {
            "category":"Building & Trades",
            "subcategory":"Construction",
            "type":"Services"
        }
    ],
    "sg:phone":"+1 352 242 6184",
    "sg:postcode":"34711",
    "sg:province":"FL",
    "sg:tags":[
        "masonry",
        "contractor"
    ],
    "wof:name":"East West Masonry",
    "wof:placetype":"venue"
},
  "geometry": {"coordinates":[-81.76400700000001,28.477117],"type":"Point"}
}