{
  "type": "Feature",
  "properties": {
    "iso:country":"US",
    "sg:address":"5601 SW 64th Ave",
    "sg:city":"Miami",
    "sg:classifiers":[
        {
            "category":"Shopping",
            "subcategory":"Books",
            "type":"Retail Goods"
        }
    ],
    "sg:phone":"+1 305 668 9611",
    "sg:postcode":"33143",
    "sg:province":"FL",
    "wof:name":"Sun-Ride Books",
    "wof:placetype":"venue"
},
  "geometry": {"coordinates":[-80.298704,25.716144],"type":"Point"}
}