{
  "type": "Feature",
  "properties": {
    "addr:full":"1680 Long Bow Ln Clearwater FL 33764",
    "addr:housenumber":"1680",
    "addr:postcode":"33764",
    "addr:street":"Long Bow Ln",
    "iso:country":"US",
    "sg:address":"1680 Long Bow Ln",
    "sg:city":"Clearwater",
    "sg:classifiers":[
        {
            "category":"Retail",
            "subcategory":"Auto Repair",
            "type":"Services"
        }
    ],
    "sg:phone":"+1 727 539 0464",
    "sg:postcode":"33764",
    "sg:province":"FL",
    "sg:tags":[
        "body",
        "automobile",
        "painting",
        "repairing"
    ],
    "wof:name":"Cherry Sisu St",
    "wof:placetype":"venue"
},
  "geometry": {"coordinates":[-82.75087000000001,27.93401],"type":"Point"}
}