{
  "type": "Feature",
  "properties": {
    "addr:full":"15850 SW 42nd Ter Miami FL 33185",
    "addr:housenumber":"15850",
    "addr:postcode":"33185",
    "addr:street":"Sw 42Nd Ter",
    "iso:country":"US",
    "sg:address":"15850 SW 42nd Ter",
    "sg:city":"Miami",
    "sg:classifiers":[
        {
            "category":"Wholesale",
            "subcategory":"Medical Equipment & Supplies",
            "type":"Manufacturing & Wholesale Goods"
        }
    ],
    "sg:phone":"+1 305 220 8008",
    "sg:postcode":"33185",
    "sg:province":"FL",
    "wof:name":"ABO",
    "wof:placetype":"venue"
},
  "geometry": {"coordinates":[-80.449551,25.727444],"type":"Point"}
}