{
  "type": "Feature",
  "properties": {
    "iso:country":"US",
    "sg:address":"4702 Park Blvd",
    "sg:city":"Pinellas Park",
    "sg:classifiers":[
        {
            "category":"Insurance",
            "subcategory":"Insurance Agent",
            "type":"Services"
        }
    ],
    "sg:phone":"+1 727 549 2277",
    "sg:postcode":"33781",
    "sg:province":"FL",
    "wof:name":"Cash Register Auto Insurance",
    "wof:placetype":"venue"
},
  "geometry": {"coordinates":[-82.699943,27.839168],"type":"Point"}
}