{
  "type": "Feature",
  "properties": {
    "addr:full":"8102 Blanding Blvd Jacksonville FL 32244",
    "addr:housenumber":"8102",
    "addr:postcode":"32244",
    "addr:street":"Blanding Blvd",
    "iso:country":"US",
    "sg:address":"8102 Blanding Blvd",
    "sg:city":"Jacksonville",
    "sg:classifiers":[
        {
            "category":"Insurance",
            "subcategory":"Insurance Agent",
            "type":"Services"
        }
    ],
    "sg:phone":"+1 904 777 8776",
    "sg:postcode":"32244",
    "sg:province":"FL",
    "wof:name":"Allstate Insurance",
    "wof:placetype":"venue"
},
  "geometry": {"coordinates":[-81.73951599999999,30.198859],"type":"Point"}
}