{
  "type": "Feature",
  "properties": {
    "iso:country":"US",
    "sg:address":"1176 SW 4th Ct",
    "sg:city":"Boca Raton",
    "sg:classifiers":[
        {
            "category":"Professional",
            "subcategory":"Engineering",
            "type":"Services"
        }
    ],
    "sg:phone":"+1 561 417 3891",
    "sg:postcode":"33432",
    "sg:province":"FL",
    "sg:tags":[
        "engineer"
    ],
    "wof:name":"James Bushouse Inc",
    "wof:placetype":"venue"
},
  "geometry": {"coordinates":[-80.093807,26.337059],"type":"Point"}
}