{
  "type": "Feature",
  "properties": {
    "addr:full":"3150 W Commercial Blvd Fort Lauderdale FL 33309",
    "addr:housenumber":"3150",
    "addr:postcode":"33309",
    "addr:street":"W Commercial Blvd",
    "iso:country":"US",
    "sg:address":"3150 W Commercial Blvd",
    "sg:city":"Fort Lauderdale",
    "sg:classifiers":[
        {
            "category":"Shopping",
            "subcategory":"Discount & Variety Stores",
            "type":"Retail Goods"
        }
    ],
    "sg:phone":"+1 954 677 0312",
    "sg:postcode":"33309",
    "sg:province":"FL",
    "wof:name":"Family Dollar Stores",
    "wof:placetype":"venue"
},
  "geometry": {"coordinates":[-80.18843200000001,26.186193],"type":"Point"}
}