{
  "type": "Feature",
  "properties": {
    "iso:country":"US",
    "sg:address":"19045 Lake Swatara Dr",
    "sg:city":"Eustis",
    "sg:classifiers":[
        {
            "category":"Retail",
            "subcategory":"Portrait Studio",
            "type":"Services"
        }
    ],
    "sg:phone":"+1 352 357 5654",
    "sg:postcode":"32736",
    "sg:province":"FL",
    "sg:tags":[
        "photo"
    ],
    "wof:name":"Wild Expressions",
    "wof:placetype":"venue"
},
  "geometry": {"coordinates":[-81.64173,28.86277],"type":"Point"}
}