{
  "type": "Feature",
  "properties": {
    "iso:country":"US",
    "sg:address":"3136 N Woodland Blvd",
    "sg:city":"De Land",
    "sg:classifiers":[
        {
            "category":"Personal",
            "subcategory":"Beauty Salon",
            "type":"Services"
        }
    ],
    "sg:phone":"+1 386 943 4247",
    "sg:postcode":"32720",
    "sg:province":"FL",
    "sg:tags":[
        "shop"
    ],
    "wof:name":"Belli Capelli Hair Studios",
    "wof:placetype":"venue"
},
  "geometry": {"coordinates":[-81.323459,29.086904],"type":"Point"}
}