{
  "type": "Feature",
  "properties": {
    "addr:full":"12184 W Colonial Dr Winter Garden FL 34787",
    "addr:housenumber":"12184",
    "addr:postcode":"34787",
    "addr:street":"W Colonial Dr",
    "iso:country":"US",
    "sg:address":"12184 W Colonial Dr",
    "sg:city":"Winter Garden",
    "sg:classifiers":[
        {
            "category":"Banks & Credit Unions",
            "subcategory":"Investment Brokerage",
            "type":"Services"
        }
    ],
    "sg:phone":"+1 407 905 0269",
    "sg:postcode":"34787",
    "sg:province":"FL",
    "sg:tags":[
        "stock",
        "bond"
    ],
    "wof:name":"Raymond James Financial Svc",
    "wof:placetype":"venue"
},
  "geometry": {"coordinates":[-81.562139,28.551237],"type":"Point"}
}