{
  "type": "Feature",
  "properties": {
    "iso:country":"US",
    "sg:address":"2710 NW 32nd Ave",
    "sg:city":"Miami",
    "sg:classifiers":[
        {
            "category":"Utilities",
            "subcategory":"Recycling",
            "type":"Services"
        },
        {
            "category":"Wholesale",
            "subcategory":"Scrap",
            "type":"Manufacturing & Wholesale Goods"
        },
        {
            "category":"Professional",
            "subcategory":"Business Services",
            "type":"Services"
        },
        {
            "category":"Retail",
            "subcategory":"Storage",
            "type":"Services"
        },
        {
            "category":"Train Station",
            "subcategory":"Light Rail",
            "type":"Transportation"
        }
    ],
    "sg:phone":"+1 305 633 2241",
    "sg:postcode":"33142",
    "sg:province":"FL",
    "sg:tags":[
        "exporter",
        "container",
        "metal",
        "equipment",
        "waste",
        "metals-wholesale"
    ],
    "sg:website":"http://www.allfloridascrapmetal.com",
    "wof:name":"All Florida Scrap Metal",
    "wof:placetype":"venue"
},
  "geometry": {"coordinates":[-80.248135,25.800605],"type":"Point"}
}