{
  "type": "Feature",
  "properties": {
    "iso:country":"US",
    "sg:address":"260 Crandon Blvd",
    "sg:city":"Key Biscayne",
    "sg:classifiers":[
        {
            "category":"Manufacturing",
            "subcategory":"Metals",
            "type":"Manufacturing & Wholesale Goods"
        }
    ],
    "sg:phone":"+1 305 361 2252",
    "sg:postcode":"33149",
    "sg:province":"FL",
    "sg:tags":[
        "box",
        "mail"
    ],
    "wof:name":"American Postal & Business Svc",
    "wof:placetype":"venue"
},
  "geometry": {"coordinates":[-80.16283300000001,25.693841],"type":"Point"}
}