{
  "type": "Feature",
  "properties": {
    "iso:country":"US",
    "sg:address":"4930 NW 74th Pl",
    "sg:city":"Pompano Beach",
    "sg:classifiers":[
        {
            "category":"Shopping",
            "subcategory":"Florist",
            "type":"Retail Goods"
        }
    ],
    "sg:phone":"+1 954 421 2300",
    "sg:postcode":"33073",
    "sg:province":"FL",
    "wof:name":"Hideaway Orchids & Garden Ctr",
    "wof:placetype":"venue"
},
  "geometry": {"coordinates":[-80.19976,26.323082],"type":"Point"}
}