{
  "type": "Feature",
  "properties": {
    "iso:country":"US",
    "sg:address":"1600 Minutemen Cswy",
    "sg:city":"Cocoa Beach",
    "sg:classifiers":[
        {
            "category":"Building & Trades",
            "subcategory":"Construction",
            "type":"Services"
        }
    ],
    "sg:phone":"+1 321 868 3219",
    "sg:postcode":"32931",
    "sg:province":"FL",
    "sg:tags":[
        "marking",
        "maintenance",
        "parking"
    ],
    "wof:name":"Public Works Dept Adm",
    "wof:placetype":"venue"
},
  "geometry": {"coordinates":[-80.628586,28.318289],"type":"Point"}
}