{
  "type": "Feature",
  "properties": {
    "iso:country":"US",
    "sg:address":"11358 SW 68th Ter",
    "sg:city":"Miami",
    "sg:classifiers":[
        {
            "category":"Communications",
            "subcategory":"Radio Station",
            "type":"Services"
        }
    ],
    "sg:phone":"+1 305 275 8120",
    "sg:postcode":"33173",
    "sg:province":"FL",
    "sg:tags":[
        "host"
    ],
    "wof:name":"Omar Lopez",
    "wof:placetype":"venue"
},
  "geometry": {"coordinates":[-80.37716500000001,25.703883],"type":"Point"}
}