{
  "type": "Feature",
  "properties": {
    "addr:full":"4680 Lake Underhill Rd Orlando FL 32807",
    "addr:housenumber":"4680",
    "addr:postcode":"32807",
    "addr:street":"Lake Underhill Rd",
    "iso:country":"US",
    "sg:address":"4680 Lake Underhill Rd",
    "sg:city":"Orlando",
    "sg:classifiers":[
        {
            "category":"Social Services",
            "type":"Services"
        }
    ],
    "sg:phone":"+1 407 277 1942",
    "sg:postcode":"32807",
    "sg:province":"FL",
    "sg:tags":[
        "organization",
        "welfare"
    ],
    "sg:website":"www.betacenter.org",
    "wof:name":"Beta Center",
    "wof:placetype":"venue"
},
  "geometry": {"coordinates":[-81.32502599999999,28.538773],"type":"Point"}
}