{
  "type": "Feature",
  "properties": {
    "addr:full":"4120 Rockingham Rd Tallahassee FL 32303",
    "addr:housenumber":"4120",
    "addr:postcode":"32303",
    "addr:street":"Rockingham Rd",
    "iso:country":"US",
    "sg:address":"4120 Rockingham Rd",
    "sg:city":"Tallahassee",
    "sg:classifiers":[
        {
            "category":"Professional",
            "subcategory":"Computer Services",
            "type":"Services"
        }
    ],
    "sg:phone":"+1 850 562 0801",
    "sg:postcode":"32303",
    "sg:province":"FL",
    "sg:tags":[
        "consultant",
        "designer"
    ],
    "wof:name":"Rapidata Inc",
    "wof:placetype":"venue"
},
  "geometry": {"coordinates":[-84.348983,30.508921],"type":"Point"}
}