{
  "type": "Feature",
  "properties": {
    "addr:full":"110 Indian Mound Rd Satsuma FL 32189",
    "addr:housenumber":"110",
    "addr:postcode":"32189",
    "addr:street":"Indian Mound Rd",
    "iso:country":"US",
    "sg:address":"110 Indian Mound Rd",
    "sg:city":"Satsuma",
    "sg:classifiers":[
        {
            "category":"Transit Center",
            "subcategory":"Freight",
            "type":"Transportation"
        },
        {
            "category":"Freight",
            "type":"Transportation"
        }
    ],
    "sg:phone":"+1 386 326 6075",
    "sg:postcode":"32189",
    "sg:province":"FL",
    "sg:tags":[
        "local",
        "trucking-motor",
        "trucking"
    ],
    "wof:name":"Terrys Transfer Inc",
    "wof:placetype":"venue"
},
  "geometry": {"coordinates":[-81.612736,29.58731],"type":"Point"}
}