{
  "type": "Feature",
  "properties": {
    "iso:country":"US",
    "sg:address":"16201 NW 82nd Ct",
    "sg:city":"Hialeah",
    "sg:classifiers":[
        {
            "category":"Building & Trades",
            "subcategory":"Construction",
            "type":"Services"
        }
    ],
    "sg:phone":"+1 305 819 4599",
    "sg:postcode":"33016",
    "sg:province":"FL",
    "sg:tags":[
        "new",
        "remodeling",
        "commercial"
    ],
    "wof:name":"Allied Contractors Inc",
    "wof:placetype":"venue"
},
  "geometry": {"coordinates":[-80.33412199999999,25.920544],"type":"Point"}
}