{
  "type": "Feature",
  "properties": {
    "addr:full":"3640 NW 40th Ct Fort Lauderdale FL 33309",
    "addr:housenumber":"3640",
    "addr:postcode":"33309",
    "addr:street":"Nw 40Th Ct",
    "iso:country":"US",
    "sg:address":"3640 NW 40th Ct",
    "sg:city":"Fort Lauderdale",
    "sg:classifiers":[
        {
            "category":"Professional",
            "subcategory":"Business Services",
            "type":"Services"
        }
    ],
    "sg:phone":"+1 954 735 2804",
    "sg:postcode":"33309",
    "sg:province":"FL",
    "wof:name":"One Love Enterprise",
    "wof:placetype":"venue"
},
  "geometry": {"coordinates":[-80.196922,26.176118],"type":"Point"}
}