{
  "type": "Feature",
  "properties": {
    "iso:country":"US",
    "sg:address":"601 SE 31st St",
    "sg:city":"Cape Coral",
    "sg:classifiers":[
        {
            "category":"Manufacturing",
            "subcategory":"Jewelry",
            "type":"Manufacturing & Wholesale Goods"
        }
    ],
    "sg:phone":"+1 239 458 1993",
    "sg:postcode":"33904",
    "sg:province":"FL",
    "sg:tags":[
        "costume",
        "mfg"
    ],
    "wof:name":"Unique Treasures",
    "wof:placetype":"venue"
},
  "geometry": {"coordinates":[-81.95946000000001,26.595138],"type":"Point"}
}