{
  "type": "Feature",
  "properties": {
    "iso:country":"US",
    "sg:address":"2118 17th Ter SW",
    "sg:city":"Largo",
    "sg:classifiers":[
        {
            "category":"Shopping",
            "subcategory":"Discount & Variety Stores",
            "type":"Retail Goods"
        }
    ],
    "sg:phone":"+1 727 581 2965",
    "sg:postcode":"33774",
    "sg:province":"FL",
    "sg:tags":[
        "merchandise",
        "general"
    ],
    "wof:name":"Air Force Sergeants Assocation",
    "wof:placetype":"venue"
},
  "geometry": {"coordinates":[-82.809684,27.900661],"type":"Point"}
}