{
  "type": "Feature",
  "properties": {
    "iso:country":"US",
    "sg:address":"1175 Moody Rd",
    "sg:city":"Fort Myers",
    "sg:classifiers":[
        {
            "category":"Building & Trades",
            "subcategory":"Construction",
            "type":"Services"
        }
    ],
    "sg:phone":"+1 239 995 2503",
    "sg:postcode":"33903",
    "sg:province":"FL",
    "sg:tags":[
        "resurfacing",
        "laying",
        "refinishing",
        "floor"
    ],
    "wof:name":"Don Smith Hardwood Floors",
    "wof:placetype":"venue"
},
  "geometry": {"coordinates":[-81.899376,26.666614],"type":"Point"}
}