{
  "type": "Feature",
  "properties": {
    "addr:full":"155 S Miami Ave Miami FL 33130",
    "addr:housenumber":"155",
    "addr:postcode":"33130",
    "addr:street":"S Miami Ave",
    "iso:country":"US",
    "sg:address":"155 S Miami Ave",
    "sg:city":"Miami",
    "sg:classifiers":[
        {
            "category":"Professional",
            "subcategory":"Lawyer & Legal Services",
            "type":"Services"
        }
    ],
    "sg:phone":"+1 305 371 3333",
    "sg:postcode":"33130",
    "sg:province":"FL",
    "sg:tags":[
        "attorney"
    ],
    "wof:name":"Baca Jaime J",
    "wof:placetype":"venue"
},
  "geometry": {"coordinates":[-80.19354,25.773136],"type":"Point"}
}