{
  "type": "Feature",
  "properties": {
    "iso:country":"US",
    "sg:address":"9011 N Century Blvd",
    "sg:city":"Century",
    "sg:classifiers":[
        {
            "category":"Wholesale",
            "subcategory":"Tobacco Products",
            "type":"Manufacturing & Wholesale Goods"
        }
    ],
    "sg:phone":"+1 850 256 4855",
    "sg:postcode":"32535",
    "sg:province":"FL",
    "sg:tags":[
        "cigarette",
        "cigar",
        "dealer"
    ],
    "wof:name":"Century Tobacco Shop",
    "wof:placetype":"venue"
},
  "geometry": {"coordinates":[-87.257362,30.990919],"type":"Point"}
}