{
  "type": "Feature",
  "properties": {
    "addr:full":"7362 NW 34th St Miami FL 33122",
    "addr:housenumber":"7362",
    "addr:postcode":"33122",
    "addr:street":"Nw 34Th St",
    "iso:country":"US",
    "sg:address":"7362 NW 34th St",
    "sg:city":"Miami",
    "sg:classifiers":[
        {
            "category":"Wholesale",
            "subcategory":"Home Furnishings",
            "type":"Manufacturing & Wholesale Goods"
        }
    ],
    "sg:phone":"+1 305 468 1733",
    "sg:postcode":"33122",
    "sg:province":"FL",
    "wof:name":"Gem Floor Coverings",
    "wof:placetype":"venue"
},
  "geometry": {"coordinates":[-80.316489,25.805254],"type":"Point"}
}