{
  "type": "Feature",
  "properties": {
    "iso:country":"US",
    "sg:address":"14 W Plant St",
    "sg:city":"Winter Garden",
    "sg:classifiers":[
        {
            "category":"Banks & Credit Unions",
            "subcategory":"Bank",
            "type":"Services"
        }
    ],
    "sg:phone":"+1 407 656 3919",
    "sg:postcode":"34787",
    "sg:province":"FL",
    "sg:tags":[
        "loan"
    ],
    "wof:name":"Winter Garden Loan Co",
    "wof:placetype":"venue"
},
  "geometry": {"coordinates":[-81.586595,28.565395],"type":"Point"}
}