{
  "type": "Feature",
  "properties": {
    "iso:country":"US",
    "sg:address":"13000 NW 42nd Ave",
    "sg:city":"Opa Locka",
    "sg:classifiers":[
        {
            "category":"Shopping",
            "subcategory":"Discount & Variety Stores",
            "type":"Retail Goods"
        }
    ],
    "sg:phone":"+1 305 688 4940",
    "sg:postcode":"33054",
    "sg:province":"FL",
    "sg:tags":[
        "outlet"
    ],
    "wof:name":"Ocm Factory Outlet",
    "wof:placetype":"venue"
},
  "geometry": {"coordinates":[-80.26750199999999,25.8923],"type":"Point"}
}