{
  "type": "Feature",
  "properties": {
    "iso:country":"US",
    "sg:address":"8001 W 26th Ave",
    "sg:city":"Hialeah",
    "sg:classifiers":[
        {
            "category":"Real Estate",
            "subcategory":"Real Estate Services",
            "type":"Services"
        }
    ],
    "sg:phone":"+1 305 557 0165",
    "sg:postcode":"33016",
    "sg:province":"FL",
    "sg:tags":[
        "management",
        "property"
    ],
    "sg:website":"www.aldirealestate.com",
    "wof:name":"Aldi Real Estate",
    "wof:placetype":"venue"
},
  "geometry": {"coordinates":[-80.33609800000001,25.8948],"type":"Point"}
}