{
  "type": "Feature",
  "properties": {
    "iso:country":"US",
    "sg:address":"274 Veleros Ct",
    "sg:city":"Miami",
    "sg:classifiers":[
        {
            "category":"Professional",
            "type":"Services"
        }
    ],
    "sg:phone":"+1 305 666 6957",
    "sg:postcode":"33143",
    "sg:province":"FL",
    "wof:name":"Si Hablo Espanol Inc",
    "wof:placetype":"venue"
},
  "geometry": {"coordinates":[-80.256546,25.703883],"type":"Point"}
}