{
  "type": "Feature",
  "properties": {
    "iso:country":"US",
    "sg:address":"4965 Central Ave",
    "sg:city":"St Petersburg",
    "sg:classifiers":[
        {
            "category":"Shopping",
            "subcategory":"Florist",
            "type":"Retail Goods"
        }
    ],
    "sg:phone":"+1 727 327 6739",
    "sg:postcode":"33710",
    "sg:province":"FL",
    "wof:name":"A Secret Garden Flowers & Gift",
    "wof:placetype":"venue"
},
  "geometry": {"coordinates":[-82.700406,27.770988],"type":"Point"}
}