{
  "type": "Feature",
  "properties": {
    "addr:full":"1426 Massa St Kissimmee FL 34744",
    "addr:housenumber":"1426",
    "addr:postcode":"34744",
    "addr:street":"Massa St",
    "iso:country":"US",
    "sg:address":"1426 Massa St",
    "sg:city":"Kissimmee",
    "sg:classifiers":[
        {
            "category":"Building & Trades",
            "subcategory":"Landscaping Services",
            "type":"Services"
        }
    ],
    "sg:phone":"+1 407 933 0779",
    "sg:postcode":"34744",
    "sg:province":"FL",
    "wof:name":"Pat Alderman S Lawn Services",
    "wof:placetype":"venue"
},
  "geometry": {"coordinates":[-81.38458900000001,28.319948],"type":"Point"}
}