{
  "type": "Feature",
  "properties": {
    "iso:country":"US",
    "sg:address":"2155 S Melanie Dr",
    "sg:city":"Homosassa",
    "sg:classifiers":[
        {
            "category":"Building & Trades",
            "subcategory":"Landscaping Services",
            "type":"Services"
        }
    ],
    "sg:phone":"+1 352 628 9884",
    "sg:postcode":"34448",
    "sg:province":"FL",
    "sg:tags":[
        "stump",
        "tree",
        "grinding",
        "contractor",
        "removal",
        "landscape"
    ],
    "wof:name":"Countywide Tree Landscaping",
    "wof:placetype":"venue"
},
  "geometry": {"coordinates":[-82.56576,28.830443],"type":"Point"}
}