{
  "type": "Feature",
  "properties": {
    "iso:country":"US",
    "sg:address":"215 N Federal Hwy",
    "sg:city":"Hollywood",
    "sg:classifiers":[
        {
            "category":"Arts & Performance",
            "subcategory":"Theater",
            "type":"Entertainment"
        }
    ],
    "sg:phone":"+1 954 929 6010",
    "sg:postcode":"33020",
    "sg:province":"FL",
    "sg:tags":[
        "theatrical"
    ],
    "wof:name":"Kadurie Arie Enterprises Inc",
    "wof:placetype":"venue"
},
  "geometry": {"coordinates":[-80.14298599999999,26.013278],"type":"Point"}
}