{
  "type": "Feature",
  "properties": {
    "iso:country":"US",
    "sg:address":"10001 Tamiami Trl",
    "sg:city":"Naples",
    "sg:classifiers":[
        {
            "category":"Home & Garden",
            "subcategory":"Furniture",
            "type":"Retail Goods"
        }
    ],
    "sg:phone":"+1 239 417 1413",
    "sg:postcode":"34113",
    "sg:province":"FL",
    "wof:name":"Lenny's Furniture",
    "wof:placetype":"venue"
},
  "geometry": {"coordinates":[-81.736358,26.094546],"type":"Point"}
}