{
  "type": "Feature",
  "properties": {
    "addr:full":"11802 N 56th St Tampa FL 33617",
    "addr:housenumber":"11802",
    "addr:postcode":"33617",
    "addr:street":"N 56Th St",
    "iso:country":"US",
    "sg:address":"11802 N 56th St",
    "sg:city":"Tampa",
    "sg:classifiers":[
        {
            "category":"Health Services",
            "subcategory":"Chiropractor",
            "type":"Services"
        }
    ],
    "sg:phone":"+1 813 985 1322",
    "sg:postcode":"33617",
    "sg:province":"FL",
    "wof:name":"Debra L Hoffman Chiropractic",
    "wof:placetype":"venue"
},
  "geometry": {"coordinates":[-82.39379700000001,28.057389],"type":"Point"}
}