{
  "type": "Feature",
  "properties": {
    "iso:country":"US",
    "sg:address":"3455 Countryside Blvd",
    "sg:city":"Clearwater",
    "sg:classifiers":[
        {
            "category":"Building & Trades",
            "subcategory":"Landscaping Services",
            "type":"Services"
        }
    ],
    "sg:phone":"+1 727 771 9010",
    "sg:postcode":"33761",
    "sg:province":"FL",
    "sg:tags":[
        "tree"
    ],
    "wof:name":"Roberts Tree Service",
    "wof:placetype":"venue"
},
  "geometry": {"coordinates":[-82.71834,28.048979],"type":"Point"}
}