{
  "type": "Feature",
  "properties": {
    "iso:country":"US",
    "sg:address":"1026 S Dixie Hwy",
    "sg:city":"Delray Beach",
    "sg:classifiers":[
        {
            "category":"Restaurant",
            "type":"Food & Drink"
        }
    ],
    "sg:phone":"+1 561 276 6551",
    "sg:postcode":"33483",
    "sg:province":"FL",
    "sg:tags":[
        "eating"
    ],
    "wof:name":"Backdraft Barbeque Inc",
    "wof:placetype":"venue"
},
  "geometry": {"coordinates":[-80.072622,26.446208],"type":"Point"}
}