{
  "type": "Feature",
  "properties": {
    "iso:country":"US",
    "sg:address":"938 Salerno Ct",
    "sg:city":"Kissimmee",
    "sg:classifiers":[
        {
            "category":"Shopping",
            "subcategory":"Clothing, Apparel, & Fashions",
            "type":"Retail Goods"
        }
    ],
    "sg:phone":"+1 407 846 0472",
    "sg:postcode":"34758",
    "sg:province":"FL",
    "wof:name":"Brass Sassy Shop",
    "wof:placetype":"venue"
},
  "geometry": {"coordinates":[-81.48673100000001,28.174465],"type":"Point"}
}