{
  "type": "Feature",
  "properties": {
    "iso:country":"US",
    "sg:address":"2038 W 1st St",
    "sg:city":"Fort Myers",
    "sg:classifiers":[
        {
            "category":"Travel",
            "subcategory":"Hotels & Motels",
            "type":"Entertainment"
        }
    ],
    "sg:phone":"+1 239 479 5255",
    "sg:postcode":"33901",
    "sg:province":"FL",
    "wof:name":"Sullivan Florida Group",
    "wof:placetype":"venue"
},
  "geometry": {"coordinates":[-81.87550400000001,26.6408],"type":"Point"}
}