{
  "type": "Feature",
  "properties": {
    "iso:country":"US",
    "sg:address":"2675 Winkler Ave Ste 300",
    "sg:city":"Fort Myers",
    "sg:classifiers":[
        {
            "category":"Health Services",
            "subcategory":"Doctor",
            "type":"Services"
        }
    ],
    "sg:phone":"+1 239 936 1343",
    "sg:postcode":"33901",
    "sg:province":"FL",
    "wof:name":"Ima Internal Medicine Associats of Le Cnty M D P A",
    "wof:placetype":"venue"
},
  "geometry": {"coordinates":[-81.8582,26.6045],"type":"Point"}
}