{
  "type": "Feature",
  "properties": {
    "addr:full":"1040 Biscayne Blvd Miami FL 33132",
    "addr:housenumber":"1040",
    "addr:postcode":"33132",
    "addr:street":"Biscayne Blvd",
    "iso:country":"US",
    "sg:address":"1040 Biscayne Blvd",
    "sg:city":"Miami",
    "sg:classifiers":[
        {
            "category":"Real Estate",
            "subcategory":"Real Estate Services",
            "type":"Services"
        }
    ],
    "sg:phone":"+1 305 503 6183",
    "sg:postcode":"33132",
    "sg:province":"FL",
    "sg:website":"www.tenmuseumparkcondos.com",
    "wof:name":"Ten Museum Park",
    "wof:placetype":"venue"
},
  "geometry": {"coordinates":[-80.18970400000001,25.784308],"type":"Point"}
}