{
  "type": "Feature",
  "properties": {
    "addr:full":"445 N Grandview Ave Daytona Beach FL 32118",
    "addr:housenumber":"445",
    "addr:postcode":"32118",
    "addr:street":"N Grandview Ave",
    "iso:country":"US",
    "sg:address":"445 N Grandview Ave",
    "sg:city":"Daytona Beach",
    "sg:classifiers":[
        {
            "category":"Professional",
            "subcategory":"Lawyer & Legal Services",
            "type":"Services"
        }
    ],
    "sg:phone":"+1 386 258 7230",
    "sg:postcode":"32118",
    "sg:province":"FL",
    "wof:name":"Manjasek & Moore",
    "wof:placetype":"venue"
},
  "geometry": {"coordinates":[-81.012456,29.232739],"type":"Point"}
}