{
  "type": "Feature",
  "properties": {
    "iso:country":"US",
    "sg:address":"401 Palmetto St",
    "sg:city":"New Smyrna Beach",
    "sg:classifiers":[
        {
            "category":"Health Services",
            "subcategory":"Doctor",
            "type":"Services"
        }
    ],
    "sg:phone":"+1 386 424 5167",
    "sg:postcode":"32168",
    "sg:province":"FL",
    "sg:tags":[
        "physician",
        "surgeon"
    ],
    "wof:name":"Arthur J Botting MD",
    "wof:placetype":"venue"
},
  "geometry": {"coordinates":[-80.922715,29.020732],"type":"Point"}
}