{
  "type": "Feature",
  "properties": {
    "iso:country":"US",
    "sg:address":"911 Lady Bug Ln",
    "sg:city":"Vero Beach",
    "sg:classifiers":[
        {
            "category":"Wholesale",
            "subcategory":"Apparel",
            "type":"Manufacturing & Wholesale Goods"
        }
    ],
    "sg:phone":"+1 772 234 3547",
    "sg:postcode":"32963",
    "sg:province":"FL",
    "sg:tags":[
        "clothing"
    ],
    "wof:name":"Cow Designs",
    "wof:placetype":"venue"
},
  "geometry": {"coordinates":[-80.354934,27.635634],"type":"Point"}
}