{
  "type": "Feature",
  "properties": {
    "addr:full":"1467 Rose Hill Dr W Jacksonville FL 32221",
    "addr:housenumber":"1467",
    "addr:postcode":"32221",
    "addr:street":"Rose Hill Dr W",
    "iso:country":"US",
    "sg:address":"1467 Rose Hill Dr W",
    "sg:city":"Jacksonville",
    "sg:classifiers":[
        {
            "category":"Professional",
            "type":"Services"
        }
    ],
    "sg:phone":"+1 904 786 1404",
    "sg:postcode":"32221",
    "sg:province":"FL",
    "sg:tags":[
        "establishment"
    ],
    "wof:name":"Echo Location",
    "wof:placetype":"venue"
},
  "geometry": {"coordinates":[-81.801686,30.296321],"type":"Point"}
}