{
  "type": "Feature",
  "properties": {
    "iso:country":"US",
    "sg:address":"144 SW Virginia Cir",
    "sg:city":"Mayo",
    "sg:classifiers":[
        {
            "category":"Health Services",
            "subcategory":"Doctor",
            "type":"Services"
        }
    ],
    "sg:phone":"+1 386 294 1226",
    "sg:postcode":"32066",
    "sg:province":"FL",
    "sg:tags":[
        "medicine",
        "physician",
        "practice",
        "surgeons",
        "family"
    ],
    "sg:website":"http://www.northflorida.va.gov",
    "wof:name":"Mayo Health Services",
    "wof:placetype":"venue"
},
  "geometry": {"coordinates":[-83.184929,30.056681],"type":"Point"}
}