{
  "type": "Feature",
  "properties": {
    "iso:country":"US",
    "sg:address":"6617 State Rd 54",
    "sg:city":"New Port Richey",
    "sg:classifiers":[
        {
            "category":"Professional",
            "subcategory":"Accounting & Tax Preparation",
            "type":"Services"
        }
    ],
    "sg:phone":"+1 727 846 1911",
    "sg:postcode":"34653",
    "sg:province":"FL",
    "sg:tags":[
        "return"
    ],
    "wof:name":"Kenneth M Rumberger LLC",
    "wof:placetype":"venue"
},
  "geometry": {"coordinates":[-82.70552600000001,28.217044],"type":"Point"}
}