{
  "type": "Feature",
  "properties": {
    "addr:full":"790 del Prado Blvd N Cape Coral FL 33909",
    "addr:housenumber":"790",
    "addr:postcode":"33909",
    "addr:street":"Del Prado Blvd N",
    "iso:country":"US",
    "sg:address":"790 del Prado Blvd N",
    "sg:city":"Cape Coral",
    "sg:classifiers":[
        {
            "category":"Home & Garden",
            "subcategory":"Furniture",
            "type":"Retail Goods"
        }
    ],
    "sg:phone":"+1 239 574 3545",
    "sg:postcode":"33909",
    "sg:province":"FL",
    "sg:website":"www.fosfurniture.com",
    "wof:name":"FOS Furniture",
    "wof:placetype":"venue"
},
  "geometry": {"coordinates":[-81.94105999999999,26.665089],"type":"Point"}
}