{
  "type": "Feature",
  "properties": {
    "iso:country":"US",
    "sg:address":"657 Maitland Ave",
    "sg:city":"Altamonte Spgs",
    "sg:classifiers":[
        {
            "category":"Wholesale",
            "subcategory":"Non-durable Goods",
            "type":"Manufacturing & Wholesale Goods"
        }
    ],
    "sg:phone":"+1 407 331 5111",
    "sg:postcode":"32701",
    "sg:province":"FL",
    "sg:tags":[
        "advertising"
    ],
    "wof:name":"Gillman Advertising Spec",
    "wof:placetype":"venue"
},
  "geometry": {"coordinates":[-81.365785,28.651941],"type":"Point"}
}