{
  "type": "Feature",
  "properties": {
    "addr:full":"7320 Sanibel Blvd Fort Myers FL 33967",
    "addr:housenumber":"7320",
    "addr:postcode":"33967",
    "addr:street":"Sanibel Blvd",
    "iso:country":"US",
    "sg:address":"7320 Sanibel Blvd",
    "sg:city":"Fort Myers",
    "sg:classifiers":[
        {
            "category":"Insurance",
            "subcategory":"Insurance Agent",
            "type":"Services"
        }
    ],
    "sg:phone":"+1 239 267 3974",
    "sg:postcode":"33967",
    "sg:province":"FL",
    "wof:name":"State Farm Insurance",
    "wof:placetype":"venue"
},
  "geometry": {"coordinates":[-81.82870800000001,26.464173],"type":"Point"}
}