{
  "type": "Feature",
  "properties": {
    "iso:country":"US",
    "sg:address":"915 E. Bloomingdale Ave",
    "sg:city":"Brandon",
    "sg:classifiers":[
        {
            "category":"Health Services",
            "subcategory":"Optometrist",
            "type":"Services"
        }
    ],
    "sg:phone":"+1 813 661 1930",
    "sg:postcode":"33511",
    "sg:province":"FL",
    "sg:tags":[
        "good",
        "optical"
    ],
    "sg:website":"http://www.opticaloutlets.com",
    "wof:name":"Optical Outlets",
    "wof:placetype":"venue"
},
  "geometry": {"coordinates":[-82.271286,27.89366],"type":"Point"}
}