{
  "type": "Feature",
  "properties": {
    "iso:country":"US",
    "sg:address":"5765 SW 113th St",
    "sg:city":"Miami",
    "sg:classifiers":[
        {
            "category":"Real Estate",
            "subcategory":"Real Estate Operator",
            "type":"Services"
        }
    ],
    "sg:phone":"+1 305 669 1142",
    "sg:postcode":"33156",
    "sg:province":"FL",
    "sg:tags":[
        "property",
        "lessor"
    ],
    "wof:name":"Caeral Holdings",
    "wof:placetype":"venue"
},
  "geometry": {"coordinates":[-80.286699,25.666391],"type":"Point"}
}