{
  "type": "Feature",
  "properties": {
    "iso:country":"US",
    "sg:address":"209 Brittany Ave",
    "sg:city":"Daytona Beach",
    "sg:classifiers":[
        {
            "category":"Professional",
            "type":"Services"
        }
    ],
    "sg:phone":"+1 386 788 5780",
    "sg:postcode":"32127",
    "sg:province":"FL",
    "wof:name":"Fiberlight Apparel Inc",
    "wof:placetype":"venue"
},
  "geometry": {"coordinates":[-80.995667,29.104317],"type":"Point"}
}