{
  "type": "Feature",
  "properties": {
    "iso:country":"US",
    "sg:address":"7540 SW 117th Ave",
    "sg:city":"Miami",
    "sg:classifiers":[
        {
            "category":"Personal",
            "type":"Services"
        }
    ],
    "sg:phone":"+1 305 275 8870",
    "sg:postcode":"33183",
    "sg:province":"FL",
    "wof:name":"La Weight Loss Centers Inc",
    "wof:placetype":"venue"
},
  "geometry": {"coordinates":[-80.382143,25.697957],"type":"Point"}
}