{
  "type": "Feature",
  "properties": {
    "addr:full":"1720 Tamiami Trl Venice FL 34293",
    "addr:housenumber":"1720",
    "addr:postcode":"34293",
    "addr:street":"Tamiami Trl",
    "iso:country":"US",
    "sg:address":"1720 Tamiami Trl",
    "sg:city":"Venice",
    "sg:classifiers":[
        {
            "category":"Restaurant",
            "type":"Food & Drink"
        }
    ],
    "sg:phone":"+1 941 493 4555",
    "sg:postcode":"34293",
    "sg:province":"FL",
    "wof:name":"Mc Donald's",
    "wof:placetype":"venue"
},
  "geometry": {"coordinates":[-82.423349,27.07156],"type":"Point"}
}