{
  "type": "Feature",
  "properties": {
    "iso:country":"US",
    "sg:address":"7566 SE 135th St",
    "sg:city":"Summerfield",
    "sg:classifiers":[
        {
            "category":"Building & Trades",
            "subcategory":"Construction",
            "type":"Services"
        }
    ],
    "sg:phone":"+1 352 347 6883",
    "sg:postcode":"34491",
    "sg:province":"FL",
    "sg:tags":[
        "wallcoverings-installation",
        "wallpaper",
        "painting",
        "contractor"
    ],
    "wof:name":"Terry Turman Painting",
    "wof:placetype":"venue"
},
  "geometry": {"coordinates":[-82.027304,29.021417],"type":"Point"}
}