{
  "type": "Feature",
  "properties": {
    "iso:country":"US",
    "sg:address":"3417 S Manhattan Ave",
    "sg:city":"Tampa",
    "sg:classifiers":[
        {
            "category":"Shopping",
            "subcategory":"Clothing, Apparel, & Fashions",
            "type":"Retail Goods"
        }
    ],
    "sg:phone":"+1 813 902 8428",
    "sg:postcode":"33629",
    "sg:province":"FL",
    "wof:name":"Imagine That",
    "wof:placetype":"venue"
},
  "geometry": {"coordinates":[-82.518028,27.911659],"type":"Point"}
}