{
  "type": "Feature",
  "properties": {
    "addr:full":"636 Fallsmead Cir Longwood FL 32750",
    "addr:housenumber":"636",
    "addr:postcode":"32750",
    "addr:street":"Fallsmead Cir",
    "iso:country":"US",
    "sg:address":"636 Fallsmead Cir",
    "sg:city":"Longwood",
    "sg:classifiers":[
        {
            "category":"Farming",
            "subcategory":"Livestock Farm",
            "type":"Manufacturing & Wholesale Goods"
        }
    ],
    "sg:phone":"+1 407 767 8970",
    "sg:postcode":"32750",
    "sg:province":"FL",
    "sg:tags":[
        "beef",
        "feedlot",
        "cattle"
    ],
    "wof:name":"H&H Timber & Cattle Co",
    "wof:placetype":"venue"
},
  "geometry": {"coordinates":[-81.35521799999999,28.710973],"type":"Point"}
}