{
  "type": "Feature",
  "properties": {
    "addr:full":"4077 Woodcock Dr Jacksonville FL 32207",
    "addr:housenumber":"4077",
    "addr:postcode":"32207",
    "addr:street":"Woodcock Dr",
    "iso:country":"US",
    "sg:address":"4077 Woodcock Dr",
    "sg:city":"Jacksonville",
    "sg:classifiers":[
        {
            "category":"Government",
            "subcategory":"Office",
            "type":"Public Place"
        }
    ],
    "sg:phone":"+1 904 348 2660",
    "sg:postcode":"32207",
    "sg:province":"FL",
    "sg:tags":[
        "state"
    ],
    "wof:name":"State Dept",
    "wof:placetype":"venue"
},
  "geometry": {"coordinates":[-81.619564,30.30265],"type":"Point"}
}