{
  "type": "Feature",
  "properties": {
    "addr:full":"3606 Warmspring Way Valrico FL 33596",
    "addr:housenumber":"3606",
    "addr:postcode":"33596",
    "addr:street":"Warmspring Way",
    "iso:country":"US",
    "sg:address":"3606 Warmspring Way",
    "sg:city":"Valrico",
    "sg:classifiers":[
        {
            "category":"Banks & Credit Unions",
            "subcategory":"Financial Services",
            "type":"Services"
        }
    ],
    "sg:phone":"+1 813 571 7071",
    "sg:postcode":"33596",
    "sg:province":"FL",
    "sg:tags":[
        "investment",
        "closed"
    ],
    "wof:name":"Farrell J&M Enterprises LLC",
    "wof:placetype":"venue"
},
  "geometry": {"coordinates":[-82.240073,27.888018],"type":"Point"}
}