{
  "type": "Feature",
  "properties": {
    "addr:full":"11937 Whistling Way Bradenton FL 34202",
    "addr:housenumber":"11937",
    "addr:postcode":"34202",
    "addr:street":"Whistling Way",
    "iso:country":"US",
    "sg:address":"11937 Whistling Way",
    "sg:city":"Bradenton",
    "sg:classifiers":[
        {
            "category":"Professional",
            "subcategory":"Employment Agencies",
            "type":"Services"
        }
    ],
    "sg:phone":"+1 941 794 9075",
    "sg:postcode":"34202",
    "sg:province":"FL",
    "sg:tags":[
        "consultant"
    ],
    "sg:website":"www.employeeselect.com",
    "wof:name":"Employee Selection & Developme",
    "wof:placetype":"venue"
},
  "geometry": {"coordinates":[-82.42231700000001,27.426268],"type":"Point"}
}