{
  "type": "Feature",
  "properties": {
    "addr:full":"4323 NW 6th St Gainesville FL 32609",
    "addr:housenumber":"4323",
    "addr:postcode":"32609",
    "addr:street":"Nw 6Th St",
    "iso:country":"US",
    "sg:address":"4323 NW 6th St",
    "sg:city":"Gainesville",
    "sg:classifiers":[
        {
            "category":"Retail",
            "subcategory":"Repair Shop",
            "type":"Services"
        }
    ],
    "sg:phone":"+1 352 372 8656",
    "sg:postcode":"32609",
    "sg:province":"FL",
    "wof:name":"Sanderson Cycle Repair",
    "wof:placetype":"venue"
},
  "geometry": {"coordinates":[-82.333656,29.693171],"type":"Point"}
}