{
  "type": "Feature",
  "properties": {
    "addr:full":"12351 SW 128th Ct Miami FL 33186",
    "addr:housenumber":"12351",
    "addr:postcode":"33186",
    "addr:street":"Sw 128Th Ct",
    "iso:country":"US",
    "sg:address":"12351 SW 128th Ct",
    "sg:city":"Miami",
    "sg:classifiers":[
        {
            "category":"Arts & Performance",
            "subcategory":"Music",
            "type":"Entertainment"
        }
    ],
    "sg:phone":"+1 305 232 8333",
    "sg:postcode":"33186",
    "sg:province":"FL",
    "sg:tags":[
        "jockey",
        "disc"
    ],
    "wof:name":"Live Life Music And Entertainment",
    "wof:placetype":"venue"
},
  "geometry": {"coordinates":[-80.402376,25.653258],"type":"Point"}
}