{
  "type": "Feature",
  "properties": {
    "addr:full":"1325 SW 87th Ave Miami FL 33174",
    "addr:housenumber":"1325",
    "addr:postcode":"33174",
    "addr:street":"Sw 87Th Ave",
    "iso:country":"US",
    "sg:address":"1325 SW 87th Ave",
    "sg:city":"Miami",
    "sg:classifiers":[
        {
            "category":"Professional",
            "subcategory":"Accounting & Tax Preparation",
            "type":"Services"
        }
    ],
    "sg:phone":"+1 305 267 2767",
    "sg:postcode":"33174",
    "sg:province":"FL",
    "sg:tags":[
        "return"
    ],
    "wof:name":"W S Business Center Corp",
    "wof:placetype":"venue"
},
  "geometry": {"coordinates":[-80.335945,25.757907],"type":"Point"}
}