{
  "type": "Feature",
  "properties": {
    "iso:country":"US",
    "sg:address":"111 E Madison St",
    "sg:city":"Tallahassee",
    "sg:classifiers":[
        {
            "category":"Professional",
            "subcategory":"Management & Consulting",
            "type":"Services"
        }
    ],
    "sg:phone":"+1 850 922 4990",
    "sg:postcode":"32399",
    "sg:province":"FL",
    "sg:tags":[
        "lobbyist",
        "registration"
    ],
    "wof:name":"Lobbyist Registration Office",
    "wof:placetype":"venue"
},
  "geometry": {"coordinates":[-84.280782,30.436533],"type":"Point"}
}