{
  "type": "Feature",
  "properties": {
    "addr:full":"203 Ave A NE Winter Haven FL 33881",
    "addr:housenumber":"203",
    "addr:postcode":"33881",
    "addr:street":"Ave A Ne",
    "iso:country":"US",
    "sg:address":"203 Ave A NE",
    "sg:city":"Winter Haven",
    "sg:classifiers":[
        {
            "category":"Banks & Credit Unions",
            "subcategory":"Bank",
            "type":"Services"
        }
    ],
    "sg:phone":"+1 863 291 6630",
    "sg:postcode":"33881",
    "sg:province":"FL",
    "sg:tags":[
        "national",
        "commercial"
    ],
    "wof:name":"Wachovia Bank National Assn",
    "wof:placetype":"venue"
},
  "geometry": {"coordinates":[-81.72400399999999,28.023066],"type":"Point"}
}