{
  "type": "Feature",
  "properties": {
    "addr:full":"803 George Bush Blvd Delray Beach FL 33483",
    "addr:housenumber":"803",
    "addr:postcode":"33483",
    "addr:street":"George Bush Blvd",
    "iso:country":"US",
    "sg:address":"803 George Bush Blvd",
    "sg:city":"Delray Beach",
    "sg:classifiers":[
        {
            "category":"Restaurant",
            "type":"Food & Drink"
        }
    ],
    "sg:phone":"+1 561 278 3349",
    "sg:postcode":"33483",
    "sg:province":"FL",
    "sg:tags":[
        "eating"
    ],
    "wof:name":"Marianne Gourmet Shop",
    "wof:placetype":"venue"
},
  "geometry": {"coordinates":[-80.06436100000001,26.47414],"type":"Point"}
}