{
  "type": "Feature",
  "properties": {
    "iso:country":"US",
    "sg:address":"9021 Delft Rd",
    "sg:city":"Sarasota",
    "sg:classifiers":[
        {
            "category":"Farming",
            "subcategory":"Nursery",
            "type":"Manufacturing & Wholesale Goods"
        }
    ],
    "sg:phone":"+1 941 371 7455",
    "sg:postcode":"34240",
    "sg:province":"FL",
    "sg:tags":[
        "ornamental"
    ],
    "wof:name":"Fordham Farms",
    "wof:placetype":"venue"
},
  "geometry": {"coordinates":[-82.40195,27.304637],"type":"Point"}
}