{
  "type": "Feature",
  "properties": {
    "iso:country":"US",
    "sg:address":"1 N Fort Lauderdale Beach Blvd",
    "sg:city":"Fort Lauderdale",
    "sg:classifiers":[
        {
            "category":"Building & Trades",
            "subcategory":"Electrical",
            "type":"Services"
        }
    ],
    "sg:phone":"+1 954 527 5788",
    "sg:postcode":"33304",
    "sg:province":"FL",
    "sg:tags":[
        "electric",
        "contractor"
    ],
    "wof:name":"Aneco Electrical",
    "wof:placetype":"venue"
},
  "geometry": {"coordinates":[-80.103951,26.123414],"type":"Point"}
}