{
  "type": "Feature",
  "properties": {
    "addr:full":"224 S Tyndall Pkwy Panama City FL 32404",
    "addr:housenumber":"224",
    "addr:postcode":"32404",
    "addr:street":"S Tyndall Pkwy",
    "iso:country":"US",
    "sg:address":"224 S Tyndall Pkwy",
    "sg:city":"Panama City",
    "sg:classifiers":[
        {
            "category":"Personal",
            "subcategory":"Tanning Parlor",
            "type":"Services"
        }
    ],
    "sg:phone":"+1 850 747 8261",
    "sg:postcode":"32404",
    "sg:province":"FL",
    "sg:tags":[
        "salon"
    ],
    "wof:name":"Club Sun Tanning Salon",
    "wof:placetype":"venue"
},
  "geometry": {"coordinates":[-85.591339,30.144272],"type":"Point"}
}