{
  "type": "Feature",
  "properties": {
    "iso:country":"US",
    "sg:address":"2100 Lake Ida Rd",
    "sg:city":"Delray Beach",
    "sg:classifiers":[
        {
            "category":"Health Services",
            "subcategory":"Doctor",
            "type":"Services"
        }
    ],
    "sg:phone":"+1 561 279 9250",
    "sg:postcode":"33445",
    "sg:province":"FL",
    "sg:tags":[
        "medical"
    ],
    "wof:name":"4 R Pain Rhblttion Hlth Clinic",
    "wof:placetype":"venue"
},
  "geometry": {"coordinates":[-80.09854199999999,26.473052],"type":"Point"}
}