{
  "type": "Feature",
  "properties": {
    "addr:full":"800 Corporate Dr Fort Lauderdale FL 33334",
    "addr:housenumber":"800",
    "addr:postcode":"33334",
    "addr:street":"Corporate Dr",
    "iso:country":"US",
    "sg:address":"800 Corporate Dr",
    "sg:city":"Fort Lauderdale",
    "sg:classifiers":[
        {
            "category":"Real Estate",
            "subcategory":"Real Estate Services",
            "type":"Services"
        }
    ],
    "sg:phone":"+1 954 351 8000",
    "sg:postcode":"33334",
    "sg:province":"FL",
    "sg:tags":[
        "abstract",
        "title"
    ],
    "wof:name":"Southland Title Services Inc",
    "wof:placetype":"venue"
},
  "geometry": {"coordinates":[-80.137857,26.205158],"type":"Point"}
}