{
  "type": "Feature",
  "properties": {
    "addr:full":"10570 Maple Chase Dr Boca Raton FL 33498",
    "addr:housenumber":"10570",
    "addr:postcode":"33498",
    "addr:street":"Maple Chase Dr",
    "iso:country":"US",
    "sg:address":"10570 Maple Chase Dr",
    "sg:city":"Boca Raton",
    "sg:classifiers":[
        {
            "category":"Retail",
            "subcategory":"Repair Shop",
            "type":"Services"
        }
    ],
    "sg:phone":"+1 561 218 1118",
    "sg:postcode":"33498",
    "sg:province":"FL",
    "sg:tags":[
        "equipment",
        "electronic",
        "supply"
    ],
    "wof:name":"Electronics Explosion Inc",
    "wof:placetype":"venue"
},
  "geometry": {"coordinates":[-80.213154,26.391479],"type":"Point"}
}