{
  "type": "Feature",
  "properties": {
    "iso:country":"US",
    "sg:address":"4960 Soundside Dr",
    "sg:city":"Gulf Breeze",
    "sg:classifiers":[
        {
            "category":"Retail",
            "subcategory":"Laundry & Dry Cleaning",
            "type":"Services"
        }
    ],
    "sg:phone":"+1 850 934 5574",
    "sg:postcode":"32563",
    "sg:province":"FL",
    "sg:tags":[
        "cleaners",
        "rug",
        "carpet"
    ],
    "wof:name":"Absolute Carpet Cleaners",
    "wof:placetype":"venue"
},
  "geometry": {"coordinates":[-87.018998,30.385462],"type":"Point"}
}