{
  "type": "Feature",
  "properties": {
    "iso:country":"US",
    "sg:address":"2311 Henderson Dr",
    "sg:city":"Orlando",
    "sg:classifiers":[
        {
            "category":"Building & Trades",
            "subcategory":"Plumbing",
            "type":"Services"
        }
    ],
    "sg:phone":"+1 407 898 3538",
    "sg:postcode":"32806",
    "sg:province":"FL",
    "sg:tags":[
        "plumbing",
        "contractor"
    ],
    "wof:name":"Emerald Plumbing",
    "wof:placetype":"venue"
},
  "geometry": {"coordinates":[-81.35471800000001,28.52294],"type":"Point"}
}