{
  "type": "Feature",
  "properties": {
    "addr:full":"2220 Trade Center Way Naples FL 34109",
    "addr:housenumber":"2220",
    "addr:postcode":"34109",
    "addr:street":"Trade Center Way",
    "iso:country":"US",
    "sg:address":"2220 Trade Center Way",
    "sg:city":"Naples",
    "sg:classifiers":[
        {
            "category":"Recreation",
            "subcategory":"Boat Charter",
            "type":"Entertainment"
        }
    ],
    "sg:phone":"+1 239 207 2564",
    "sg:postcode":"34109",
    "sg:province":"FL",
    "sg:tags":[
        "boat-rental"
    ],
    "wof:name":"Fly Ride Charter",
    "wof:placetype":"venue"
},
  "geometry": {"coordinates":[-81.77928300000001,26.225145],"type":"Point"}
}