{
  "type": "Feature",
  "properties": {
    "iso:country":"US",
    "sg:address":"561 Stevens St",
    "sg:city":"Jacksonville",
    "sg:classifiers":[
        {
            "category":"Freight",
            "type":"Transportation"
        }
    ],
    "sg:phone":"+1 904 824 8996",
    "sg:postcode":"32254",
    "sg:province":"FL",
    "sg:tags":[
        "special"
    ],
    "wof:name":"Van Hills Srvc-Mayflower Agcy",
    "wof:placetype":"venue"
},
  "geometry": {"coordinates":[-81.739391,30.316944],"type":"Point"}
}