{
  "type": "Feature",
  "properties": {
    "iso:country":"US",
    "sg:address":"11924 W Forest Hill Blvd",
    "sg:city":"Wellington",
    "sg:phone":"+1 561 790 3780",
    "sg:postcode":"33414",
    "sg:province":"FL",
    "wof:name":"Sal's Italian Ristorante",
    "wof:placetype":"venue"
},
  "geometry": {"coordinates":[-80.233305,26.652378],"type":"Point"}
}