{
  "type": "Feature",
  "properties": {
    "iso:country":"US",
    "sg:address":"1900 W 68th St Apt D204",
    "sg:city":"Hialeah",
    "sg:classifiers":[
        {
            "category":"Professional",
            "subcategory":"Art Services",
            "type":"Services"
        }
    ],
    "sg:phone":"+1 305 826 6607",
    "sg:postcode":"33014",
    "sg:province":"FL",
    "sg:tags":[
        "commercial",
        "artist"
    ],
    "wof:name":"Art Design Gloria Corp",
    "wof:placetype":"venue"
},
  "geometry": {"coordinates":[-80.321899,25.884529],"type":"Point"}
}