{
  "type": "Feature",
  "properties": {
    "addr:full":"30328 Cortez Blvd Brooksville FL 34602",
    "addr:housenumber":"30328",
    "addr:postcode":"34602",
    "addr:street":"Cortez Blvd",
    "iso:country":"US",
    "sg:address":"30328 Cortez Blvd",
    "sg:city":"Brooksville",
    "sg:classifiers":[
        {
            "category":"Autos & Motor Vehicles",
            "subcategory":"Fuel & Gas Station",
            "type":"Retail Goods"
        }
    ],
    "sg:phone":"+1 352 799 0288",
    "sg:postcode":"34602",
    "sg:province":"FL",
    "sg:tags":[
        "station",
        "gasoline",
        "oil"
    ],
    "wof:name":"Sunrise Food Mart 12",
    "wof:placetype":"venue"
},
  "geometry": {"coordinates":[-82.238285,28.523063],"type":"Point"}
}