{
  "type": "Feature",
  "properties": {
    "iso:country":"US",
    "sg:address":"17101 NE 19th Ave Ste 101",
    "sg:city":"North Miami Beach",
    "sg:classifiers":[
        {
            "category":"Health Services",
            "subcategory":"Doctor",
            "type":"Services"
        },
        {
            "category":"Personal",
            "subcategory":"Hair Removal",
            "type":"Services"
        }
    ],
    "sg:phone":"+1 305 940 7766",
    "sg:postcode":"33162",
    "sg:province":"FL",
    "sg:tags":[
        "dermatologist"
    ],
    "wof:name":"Rockley Paul F MD PA",
    "wof:placetype":"venue"
},
  "geometry": {"coordinates":[-80.162201,25.933399],"type":"Point"}
}