{
  "type": "Feature",
  "properties": {
    "addr:full":"3745 W 6th Ave Hialeah FL 33012",
    "addr:housenumber":"3745",
    "addr:postcode":"33012",
    "addr:street":"W 6Th Ave",
    "iso:country":"US",
    "sg:address":"3745 W 6th Ave",
    "sg:city":"Hialeah",
    "sg:classifiers":[
        {
            "category":"Retail",
            "subcategory":"Auto Repair",
            "type":"Services"
        }
    ],
    "sg:phone":"+1 305 557 8252",
    "sg:postcode":"33012",
    "sg:province":"FL",
    "sg:tags":[
        "glass",
        "windshield",
        "replacement"
    ],
    "wof:name":"Speedy Auto Glass",
    "wof:placetype":"venue"
},
  "geometry": {"coordinates":[-80.29447399999999,25.855698],"type":"Point"}
}