{
  "type": "Feature",
  "properties": {
    "addr:full":"2777 Capital Cir NE Tallahassee FL 32308",
    "addr:housenumber":"2777",
    "addr:postcode":"32308",
    "addr:street":"Capital Cir Ne",
    "iso:country":"US",
    "sg:address":"2777 Capital Cir NE",
    "sg:city":"Tallahassee",
    "sg:classifiers":[
        {
            "category":"Wholesale",
            "subcategory":"Office Equipment",
            "type":"Manufacturing & Wholesale Goods"
        }
    ],
    "sg:phone":"+1 850 402 0646",
    "sg:postcode":"32308",
    "sg:province":"FL",
    "sg:tags":[
        "machine",
        "duplicating",
        "copying"
    ],
    "wof:name":"Service Plus & Office Machine",
    "wof:placetype":"venue"
},
  "geometry": {"coordinates":[-84.24168400000001,30.490816],"type":"Point"}
}