{
  "type": "Feature",
  "properties": {
    "iso:country":"US",
    "sg:address":"1155 Tampa Rd",
    "sg:city":"Palm Harbor",
    "sg:classifiers":[
        {
            "category":"Professional",
            "subcategory":"Advertising",
            "type":"Services"
        }
    ],
    "sg:phone":"+1 727 772 1827",
    "sg:postcode":"34683",
    "sg:province":"FL",
    "sg:tags":[
        "distribution"
    ],
    "wof:name":"Janick Group Inc",
    "wof:placetype":"venue"
},
  "geometry": {"coordinates":[-82.765916,28.067991],"type":"Point"}
}