{
  "type": "Feature",
  "properties": {
    "addr:full":"25013 Derby Dr Sorrento FL 32776",
    "addr:housenumber":"25013",
    "addr:postcode":"32776",
    "addr:street":"Derby Dr",
    "iso:country":"US",
    "sg:address":"25013 Derby Dr",
    "sg:city":"Sorrento",
    "sg:classifiers":[
        {
            "category":"Building & Trades",
            "subcategory":"Construction",
            "type":"Services"
        }
    ],
    "sg:phone":"+1 352 589 2997",
    "sg:postcode":"32776",
    "sg:province":"FL",
    "sg:tags":[
        "general",
        "contractor"
    ],
    "wof:name":"Baybrook Homes",
    "wof:placetype":"venue"
},
  "geometry": {"coordinates":[-81.541342,28.853746],"type":"Point"}
}