{
  "type": "Feature",
  "properties": {
    "addr:full":"3016 SW 132nd Ter Archer FL 32618",
    "addr:housenumber":"3016",
    "addr:postcode":"32618",
    "addr:street":"Sw 132Nd Ter Archer",
    "iso:country":"US",
    "sg:address":"3016 SW 132nd Ter",
    "sg:city":"Archer",
    "sg:classifiers":[
        {
            "category":"Manufacturing",
            "subcategory":"Glass & Minerals",
            "type":"Manufacturing & Wholesale Goods"
        }
    ],
    "sg:phone":"+1 352 332 2605",
    "sg:postcode":"32618",
    "sg:province":"FL",
    "sg:tags":[
        "glass-wholesale",
        "shape",
        "circle",
        "special",
        "manufacturer"
    ],
    "wof:name":"Creative Stained Glass",
    "wof:placetype":"venue"
},
  "geometry": {"coordinates":[-82.484151,29.626044],"type":"Point"}
}