{
  "type": "Feature",
  "properties": {
    "iso:country":"US",
    "sg:address":"8999 Park Blvd N",
    "sg:city":"Largo",
    "sg:classifiers":[
        {
            "category":"Restaurant",
            "type":"Food & Drink"
        }
    ],
    "sg:phone":"+1 727 391 2761",
    "sg:postcode":"33777",
    "sg:province":"FL",
    "sg:tags":[
        "eating"
    ],
    "wof:name":"Ya Yas Flame Broiled Chicken",
    "wof:placetype":"venue"
},
  "geometry": {"coordinates":[-82.76215500000001,27.839368],"type":"Point"}
}