{
  "type": "Feature",
  "properties": {
    "addr:full":"5350 Chatsworth Ct Orlando FL 32812",
    "addr:housenumber":"5350",
    "addr:postcode":"32812",
    "addr:street":"Chatsworth Ct",
    "iso:country":"US",
    "sg:address":"5350 Chatsworth Ct",
    "sg:city":"Orlando",
    "sg:classifiers":[
        {
            "category":"Building & Trades",
            "subcategory":"Landscaping Services",
            "type":"Services"
        }
    ],
    "sg:phone":"+1 407 482 0059",
    "sg:postcode":"32812",
    "sg:province":"FL",
    "wof:name":"Barrow Landscaping",
    "wof:placetype":"venue"
},
  "geometry": {"coordinates":[-81.31689,28.506587],"type":"Point"}
}