{
  "type": "Feature",
  "properties": {
    "iso:country":"US",
    "sg:address":"2224 1st St",
    "sg:city":"Fort Myers",
    "sg:classifiers":[
        {
            "category":"Coffee & Tea",
            "type":"Food & Drink"
        }
    ],
    "sg:phone":"+1 239 790 2665",
    "sg:postcode":"33901",
    "sg:province":"FL",
    "wof:name":"Cool Beans & Bottles",
    "wof:placetype":"venue"
},
  "geometry": {"coordinates":[-81.870459,26.643975],"type":"Point"}
}