{
  "type": "Feature",
  "properties": {
    "iso:country":"US",
    "sg:address":"1550 Brescia Ave",
    "sg:city":"Coral Gables",
    "sg:classifiers":[
        {
            "category":"Organizations",
            "subcategory":"Community Association",
            "type":"Services"
        }
    ],
    "sg:phone":"+1 305 284 2444",
    "sg:postcode":"33146",
    "sg:province":"FL",
    "sg:tags":[
        "club"
    ],
    "wof:name":"Affairs At The Club",
    "wof:placetype":"venue"
},
  "geometry": {"coordinates":[-80.284524,25.711717],"type":"Point"}
}