{
  "type": "Feature",
  "properties": {
    "iso:country":"US",
    "sg:address":"404 Vonderburg Dr",
    "sg:city":"Brandon",
    "sg:classifiers":[
        {
            "category":"Health Services",
            "subcategory":"Doctor",
            "type":"Services"
        }
    ],
    "sg:phone":"+1 813 684 6000",
    "sg:postcode":"33511",
    "sg:province":"FL",
    "sg:tags":[
        "physician",
        "surgeon"
    ],
    "wof:name":"Bay Area Cardiology Assoc",
    "wof:placetype":"venue"
},
  "geometry": {"coordinates":[-82.28941,27.933039],"type":"Point"}
}