{
  "type": "Feature",
  "properties": {
    "addr:full":"312 Minorca Ave Coral Gables FL 33134",
    "addr:housenumber":"312",
    "addr:postcode":"33134",
    "addr:street":"Minorca Ave",
    "iso:country":"US",
    "sg:address":"312 Minorca Ave",
    "sg:city":"Coral Gables",
    "sg:classifiers":[
        {
            "category":"Banks & Credit Unions",
            "subcategory":"Bank",
            "type":"Services"
        }
    ],
    "sg:phone":"+1 305 476 0939",
    "sg:postcode":"33134",
    "sg:province":"FL",
    "sg:tags":[
        "loan",
        "real estate"
    ],
    "wof:name":"Mortgage One Group",
    "wof:placetype":"venue"
},
  "geometry": {"coordinates":[-80.26264,25.753421],"type":"Point"}
}