{
  "type": "Feature",
  "properties": {
    "addr:full":"2350 W 60th St Hialeah FL 33016",
    "addr:housenumber":"2350",
    "addr:postcode":"33016",
    "addr:street":"W 60Th St",
    "iso:country":"US",
    "sg:address":"2350 W 60th St",
    "sg:city":"Hialeah",
    "sg:classifiers":[
        {
            "category":"Shopping",
            "subcategory":"Mobile Phones",
            "type":"Retail Goods"
        }
    ],
    "sg:phone":"+1 305 512 7901",
    "sg:postcode":"33016",
    "sg:province":"FL",
    "wof:name":"A Tc Wireless Inc",
    "wof:placetype":"venue"
},
  "geometry": {"coordinates":[-80.330299,25.877001],"type":"Point"}
}