{
  "type": "Feature",
  "properties": {
    "addr:full":"2440 W Beaver St Jacksonville FL 32209",
    "addr:housenumber":"2440",
    "addr:postcode":"32209",
    "addr:street":"W Beaver St",
    "iso:country":"US",
    "sg:address":"2440 W Beaver St",
    "sg:city":"Jacksonville",
    "sg:classifiers":[
        {
            "category":"Restaurant",
            "type":"Food & Drink"
        }
    ],
    "sg:phone":"+1 904 388 0031",
    "sg:postcode":"32209",
    "sg:province":"FL",
    "sg:tags":[
        "take"
    ],
    "wof:name":"Mary Anns Golden Fried Chicken",
    "wof:placetype":"venue"
},
  "geometry": {"coordinates":[-81.70502399999999,30.331716],"type":"Point"}
}