{
  "type": "Feature",
  "properties": {
    "addr:full":"15427 US Hwy 19 Hudson FL 34667",
    "addr:postcode":"15427;34667",
    "addr:street":"Us Hwy 19",
    "iso:country":"US",
    "sg:address":"15427 US Hwy 19",
    "sg:city":"Hudson",
    "sg:classifiers":[
        {
            "category":"Travel",
            "subcategory":"Hotels & Motels",
            "type":"Entertainment"
        }
    ],
    "sg:phone":"+1 727 869 9291",
    "sg:postcode":"34667",
    "sg:province":"FL",
    "sg:tags":[
        "resort"
    ],
    "wof:name":"Resort Locators Intl",
    "wof:placetype":"venue"
},
  "geometry": {"coordinates":[-82.675618,28.383012],"type":"Point"}
}