{
  "type": "Feature",
  "properties": {
    "addr:full":"9817 White Barn Way Riverview FL 33569",
    "addr:housenumber":"9817",
    "addr:postcode":"33569",
    "addr:street":"White Barn Way",
    "iso:country":"US",
    "sg:address":"9817 White Barn Way",
    "sg:city":"Riverview",
    "sg:classifiers":[
        {
            "category":"Organizations",
            "subcategory":"Non-profit Organization",
            "type":"Services"
        }
    ],
    "sg:phone":"+1 813 671 3053",
    "sg:postcode":"33569",
    "sg:province":"FL",
    "sg:tags":[
        "charity",
        "foundations-educational",
        "philanthropic",
        "research"
    ],
    "wof:name":"Victory World Impact Inc",
    "wof:placetype":"venue"
},
  "geometry": {"coordinates":[-82.30362100000001,27.855407],"type":"Point"}
}