{
  "type": "Feature",
  "properties": {
    "addr:full":"4218 Cleveland Ave Fort Myers FL 33901",
    "addr:housenumber":"4218",
    "addr:postcode":"33901",
    "addr:street":"Cleveland Ave",
    "iso:country":"US",
    "sg:address":"4218 Cleveland Ave",
    "sg:city":"Fort Myers",
    "sg:classifiers":[
        {
            "category":"Building & Trades",
            "subcategory":"Construction",
            "type":"Services"
        }
    ],
    "sg:phone":"+1 239 656 4111",
    "sg:postcode":"33901",
    "sg:province":"FL",
    "sg:tags":[
        "residential",
        "speculative",
        "new"
    ],
    "wof:name":"Investment Builders LLC",
    "wof:placetype":"venue"
},
  "geometry": {"coordinates":[-81.871888,26.601502],"type":"Point"}
}