{
  "type": "Feature",
  "properties": {
    "iso:country":"US",
    "sg:address":"4010 Sawyer Rd",
    "sg:city":"Sarasota",
    "sg:classifiers":[
        {
            "category":"Health Services",
            "subcategory":"Chiropractor",
            "type":"Services"
        }
    ],
    "sg:phone":"+1 941 924 9892",
    "sg:postcode":"34233",
    "sg:province":"FL",
    "wof:name":"Chiropractic & Acupuncture Ctr",
    "wof:placetype":"venue"
},
  "geometry": {"coordinates":[-82.489375,27.29499],"type":"Point"}
}