{
  "type": "Feature",
  "properties": {
    "addr:full":"17980 San Carlos Blvd Fort Myers Beach FL 33931",
    "addr:housenumber":"17980",
    "addr:postcode":"33931",
    "addr:street":"San Carlos Blvd",
    "iso:country":"US",
    "sg:address":"17980 San Carlos Blvd",
    "sg:city":"Fort Myers Beach",
    "sg:classifiers":[
        {
            "category":"Professional",
            "subcategory":"Computer Services",
            "type":"Services"
        }
    ],
    "sg:phone":"+1 239 437 3957",
    "sg:postcode":"33931",
    "sg:province":"FL",
    "sg:tags":[
        "programming"
    ],
    "wof:name":"Craig's Software Solutions",
    "wof:placetype":"venue"
},
  "geometry": {"coordinates":[-81.94979499999999,26.481071],"type":"Point"}
}