{
  "type": "Feature",
  "properties": {
    "iso:country":"US",
    "sg:address":"305 S H St",
    "sg:city":"Lake Worth",
    "sg:classifiers":[
        {
            "category":"Wholesale",
            "subcategory":"Auto Parts",
            "type":"Manufacturing & Wholesale Goods"
        }
    ],
    "sg:phone":"+1 561 588 8352",
    "sg:postcode":"33460",
    "sg:province":"FL",
    "wof:name":"Guaranteed Auto Inc",
    "wof:placetype":"venue"
},
  "geometry": {"coordinates":[-80.058601,26.611121],"type":"Point"}
}