{
  "type": "Feature",
  "properties": {
    "iso:country":"US",
    "sg:address":"3468 Marcus Pointe Blvd",
    "sg:city":"Pensacola",
    "sg:classifiers":[
        {
            "category":"Real Estate",
            "subcategory":"Real Estate Services",
            "type":"Services"
        },
        {
            "category":"Real Estate",
            "subcategory":"Real Estate Agent",
            "type":"Services"
        }
    ],
    "sg:phone":"+1 850 475 9294",
    "sg:postcode":"32505",
    "sg:province":"FL",
    "sg:tags":[
        "buyer",
        "broker"
    ],
    "wof:name":"Gordon Realestate",
    "wof:placetype":"venue"
},
  "geometry": {"coordinates":[-87.281526,30.47016],"type":"Point"}
}