{
  "type": "Feature",
  "properties": {
    "iso:country":"US",
    "sg:address":"6990 Pine Forest Rd",
    "sg:city":"Pensacola",
    "sg:classifiers":[
        {
            "category":"Real Estate",
            "subcategory":"Real Estate Agent",
            "type":"Services"
        }
    ],
    "sg:phone":"+1 850 944 3233",
    "sg:postcode":"32526",
    "sg:province":"FL",
    "wof:name":"Gulf Winds Real Estate Group",
    "wof:placetype":"venue"
},
  "geometry": {"coordinates":[-87.306252,30.488939],"type":"Point"}
}