{
  "type": "Feature",
  "properties": {
    "iso:country":"US",
    "sg:address":"31801 State Hwy 44",
    "sg:city":"Eustis",
    "sg:classifiers":[
        {
            "category":"Building & Trades",
            "subcategory":"Construction",
            "type":"Services"
        }
    ],
    "sg:phone":"+1 352 589 7445",
    "sg:postcode":"32736",
    "sg:province":"FL",
    "sg:tags":[
        "concrete",
        "contractor"
    ],
    "wof:name":"Shapiro Stucco Inc",
    "wof:placetype":"venue"
},
  "geometry": {"coordinates":[-81.431697,28.939459],"type":"Point"}
}