{
  "type": "Feature",
  "properties": {
    "addr:full":"4811 George Rd Tampa FL 33634",
    "addr:housenumber":"4811",
    "addr:postcode":"33634",
    "addr:street":"George Rd",
    "iso:country":"US",
    "sg:address":"4811 George Rd",
    "sg:city":"Tampa",
    "sg:classifiers":[
        {
            "category":"Organizations",
            "subcategory":"Religious Organization",
            "type":"Services"
        }
    ],
    "sg:phone":"+1 813 884 4328",
    "sg:postcode":"33634",
    "sg:province":"FL",
    "sg:tags":[
        "church"
    ],
    "sg:website":"www.biblelineministries.org",
    "wof:name":"Calvary Community Church",
    "wof:placetype":"venue"
},
  "geometry": {"coordinates":[-82.55032,27.988993],"type":"Point"}
}