{
  "type": "Feature",
  "properties": {
    "addr:full":"2665 S Bayshore Dr Miami FL 33133",
    "addr:housenumber":"2665",
    "addr:postcode":"33133",
    "addr:street":"S Bayshore Dr",
    "iso:country":"US",
    "sg:address":"2665 S Bayshore Dr",
    "sg:city":"Miami",
    "sg:classifiers":[
        {
            "category":"Professional",
            "subcategory":"Lawyer & Legal Services",
            "type":"Services"
        }
    ],
    "sg:phone":"+1 305 859 9200",
    "sg:postcode":"33133",
    "sg:province":"FL",
    "sg:tags":[
        "firm",
        "divorce",
        "law",
        "family"
    ],
    "wof:name":"Wayne Barry Atty",
    "wof:placetype":"venue"
},
  "geometry": {"coordinates":[-80.235901,25.7306],"type":"Point"}
}