{
  "type": "Feature",
  "properties": {
    "iso:country":"US",
    "sg:address":"1627 US Hwy 1",
    "sg:city":"Sebastian",
    "sg:classifiers":[
        {
            "category":"Organizations",
            "subcategory":"Religious Organization",
            "type":"Services"
        }
    ],
    "sg:phone":"+1 772 589 7373",
    "sg:postcode":"32958",
    "sg:province":"FL",
    "sg:tags":[
        "church"
    ],
    "wof:name":"First Baptist Church",
    "wof:placetype":"venue"
},
  "geometry": {"coordinates":[-80.47633999999999,27.82634],"type":"Point"}
}