{
  "type": "Feature",
  "properties": {
    "iso:country":"US",
    "sg:address":"640 NE 7th Ave",
    "sg:city":"Fort Lauderdale",
    "sg:classifiers":[
        {
            "category":"Real Estate",
            "subcategory":"Real Estate Operator",
            "type":"Services"
        }
    ],
    "sg:phone":"+1 954 763 4334",
    "sg:postcode":"33304",
    "sg:province":"FL",
    "sg:tags":[
        "building",
        "apartment"
    ],
    "wof:name":"Manor Park II",
    "wof:placetype":"venue"
},
  "geometry": {"coordinates":[-80.135986,26.131008],"type":"Point"}
}