{
  "type": "Feature",
  "properties": {
    "iso:country":"US",
    "sg:address":"4511 Crichton Ln",
    "sg:city":"Orlando",
    "sg:classifiers":[
        {
            "category":"Building & Trades",
            "subcategory":"Landscaping Services",
            "type":"Services"
        }
    ],
    "sg:phone":"+1 407 851 9382",
    "sg:postcode":"32806",
    "sg:province":"FL",
    "wof:name":"A Cut Above The Rest",
    "wof:placetype":"venue"
},
  "geometry": {"coordinates":[-81.355975,28.495481],"type":"Point"}
}