{
  "type": "Feature",
  "properties": {
    "iso:country":"US",
    "sg:address":"2659 SW 73rd Way",
    "sg:city":"Fort Lauderdale",
    "sg:classifiers":[
        {
            "category":"Building & Trades",
            "subcategory":"Landscaping Services",
            "type":"Services"
        }
    ],
    "sg:phone":"+1 954 452 5216",
    "sg:postcode":"33314",
    "sg:province":"FL",
    "wof:name":"Horticultural Creations Inc",
    "wof:placetype":"venue"
},
  "geometry": {"coordinates":[-80.245555,26.088388],"type":"Point"}
}