{
  "type": "Feature",
  "properties": {
    "addr:full":"3646 Hartsfield Rd Tallahassee FL 32303",
    "addr:housenumber":"3646",
    "addr:postcode":"32303",
    "addr:street":"Hartsfield Rd",
    "iso:country":"US",
    "sg:address":"3646 Hartsfield Rd",
    "sg:city":"Tallahassee",
    "sg:classifiers":[
        {
            "category":"Manufacturing",
            "subcategory":"Glass & Minerals",
            "type":"Manufacturing & Wholesale Goods"
        }
    ],
    "sg:phone":"+1 850 575 5415",
    "sg:postcode":"32303",
    "sg:province":"FL",
    "sg:tags":[
        "auto",
        "product",
        "mfg"
    ],
    "wof:name":"Owns Libby Ford",
    "wof:placetype":"venue"
},
  "geometry": {"coordinates":[-84.35404800000001,30.469422],"type":"Point"}
}