{
  "type": "Feature",
  "properties": {
    "iso:country":"US",
    "sg:address":"922 Lake Baldwin Ln Ste A",
    "sg:city":"Orlando",
    "sg:classifiers":[
        {
            "category":"Insurance",
            "subcategory":"Hazard Insurance",
            "type":"Services"
        }
    ],
    "sg:phone":"+1 407 277 2994",
    "sg:postcode":"32814",
    "sg:province":"FL",
    "sg:website":"http://statefarm.mqgroup.com/url.asp?usr=596462",
    "wof:name":"State Farm Insurance Agent-Jim Ackerman",
    "wof:placetype":"venue"
},
  "geometry": {"coordinates":[-81.327411,28.557415],"type":"Point"}
}