{
  "type": "Feature",
  "properties": {
    "addr:full":"1321 SW 107th Ave Miami FL 33174",
    "addr:housenumber":"1321",
    "addr:postcode":"33174",
    "addr:street":"Sw 107Th Ave",
    "iso:country":"US",
    "sg:address":"1321 SW 107th Ave",
    "sg:city":"Miami",
    "sg:classifiers":[
        {
            "category":"Education",
            "subcategory":"Special Training",
            "type":"Public Place"
        }
    ],
    "sg:phone":"+1 305 226 9004",
    "sg:postcode":"33174",
    "sg:province":"FL",
    "sg:tags":[
        "instruction",
        "driving"
    ],
    "wof:name":"AAAA Traffic School Prgrms",
    "wof:placetype":"venue"
},
  "geometry": {"coordinates":[-80.368004,25.754569],"type":"Point"}
}