{
  "type": "Feature",
  "properties": {
    "iso:country":"US",
    "sg:address":"1635 N Magnolia Ave",
    "sg:city":"Ocala",
    "sg:classifiers":[
        {
            "category":"Wholesale",
            "subcategory":"Machinery & Supplies",
            "type":"Manufacturing & Wholesale Goods"
        }
    ],
    "sg:phone":"+1 352 732 4141",
    "sg:postcode":"34475",
    "sg:province":"FL",
    "sg:tags":[
        "industrial"
    ],
    "sg:website":"www.millerbearings.com",
    "wof:name":"Miller Bearings Inc",
    "wof:placetype":"venue"
},
  "geometry": {"coordinates":[-82.136437,29.20389],"type":"Point"}
}