{
  "type": "Feature",
  "properties": {
    "iso:country":"US",
    "sg:address":"2015 NW 38th Ave",
    "sg:city":"Okeechobee",
    "sg:classifiers":[
        {
            "category":"Freight",
            "type":"Transportation"
        }
    ],
    "sg:phone":"+1 863 467 2721",
    "sg:postcode":"34972",
    "sg:province":"FL",
    "sg:tags":[
        "operator",
        "trucking"
    ],
    "wof:name":"Cook Silas L and Patricia",
    "wof:placetype":"venue"
},
  "geometry": {"coordinates":[-80.868622,27.263893],"type":"Point"}
}