{
  "type": "Feature",
  "properties": {
    "iso:country":"US",
    "sg:address":"1931 W 60th St",
    "sg:city":"Hialeah",
    "sg:classifiers":[
        {
            "category":"Health Services",
            "subcategory":"Doctor",
            "type":"Services"
        }
    ],
    "sg:phone":"+1 305 557 1006",
    "sg:postcode":"33012",
    "sg:province":"FL",
    "sg:tags":[
        "medical"
    ],
    "wof:name":"Nancy Ortiz MD",
    "wof:placetype":"venue"
},
  "geometry": {"coordinates":[-80.32290500000001,25.877069],"type":"Point"}
}