{
  "type": "Feature",
  "properties": {
    "iso:country":"US",
    "sg:address":"2316 Woodside Way",
    "sg:city":"Kissimmee",
    "sg:classifiers":[
        {
            "category":"Manufacturing",
            "subcategory":"Paper Products",
            "type":"Manufacturing & Wholesale Goods"
        }
    ],
    "sg:phone":"+1 407 847 8919",
    "sg:postcode":"34744",
    "sg:province":"FL",
    "sg:tags":[
        "converted",
        "mfg"
    ],
    "wof:name":"Tags With Class",
    "wof:placetype":"venue"
},
  "geometry": {"coordinates":[-81.38163,28.313125],"type":"Point"}
}