{
  "type": "Feature",
  "properties": {
    "iso:country":"US",
    "sg:address":"6914 Jones Rd",
    "sg:city":"Odessa",
    "sg:classifiers":[
        {
            "category":"Building & Trades",
            "subcategory":"Plumbing",
            "type":"Services"
        }
    ],
    "sg:phone":"+1 813 792 2264",
    "sg:postcode":"33556",
    "sg:province":"FL",
    "sg:tags":[
        "sewer",
        "cleaning",
        "drain"
    ],
    "wof:name":"Anytime Plumbing & Drain",
    "wof:placetype":"venue"
},
  "geometry": {"coordinates":[-82.56336899999999,28.169193],"type":"Point"}
}