{
  "type": "Feature",
  "properties": {
    "addr:full":"5026 Silver Star Rd Orlando FL 32808",
    "addr:housenumber":"5026",
    "addr:postcode":"32808",
    "addr:street":"Silver Star Rd",
    "iso:country":"US",
    "sg:address":"5026 Silver Star Rd",
    "sg:city":"Orlando",
    "sg:classifiers":[
        {
            "category":"Real Estate",
            "subcategory":"Real Estate Agent",
            "type":"Services"
        }
    ],
    "sg:phone":"+1 407 297 1030",
    "sg:postcode":"32808",
    "sg:province":"FL",
    "sg:tags":[
        "investment"
    ],
    "wof:name":"Goodwill Real Estate LLC",
    "wof:placetype":"venue"
},
  "geometry": {"coordinates":[-81.450008,28.577883],"type":"Point"}
}