{
  "type": "Feature",
  "properties": {
    "addr:full":"4085 L B McLeod Rd Orlando FL 32811",
    "addr:housenumber":"4085;b",
    "addr:postcode":"32811",
    "addr:street":"L;Mcleod Rd",
    "iso:country":"US",
    "sg:address":"4085 L B McLeod Rd",
    "sg:city":"Orlando",
    "sg:classifiers":[
        {
            "category":"Shopping",
            "subcategory":"Clothing, Apparel, & Fashions",
            "type":"Retail Goods"
        }
    ],
    "sg:phone":"+1 407 872 1774",
    "sg:postcode":"32811",
    "sg:province":"FL",
    "wof:name":"Peak Performance",
    "wof:placetype":"venue"
},
  "geometry": {"coordinates":[-81.430121,28.508794],"type":"Point"}
}