{
  "type": "Feature",
  "properties": {
    "iso:country":"US",
    "sg:address":"9745 SW 72nd St",
    "sg:city":"Miami",
    "sg:classifiers":[
        {
            "category":"Real Estate",
            "subcategory":"Real Estate Agent",
            "type":"Services"
        }
    ],
    "sg:phone":"+1 305 630 9470",
    "sg:postcode":"33173",
    "sg:province":"FL",
    "wof:name":"Goldview Realty Inc",
    "wof:placetype":"venue"
},
  "geometry": {"coordinates":[-80.35129999999999,25.701674],"type":"Point"}
}