{
  "type": "Feature",
  "properties": {
    "iso:country":"US",
    "sg:address":"6883 NE 3rd Ave",
    "sg:city":"Miami",
    "sg:classifiers":[
        {
            "category":"Taxi",
            "type":"Transportation"
        },
        {
            "category":"Professional",
            "subcategory":"Business Services",
            "type":"Services"
        },
        {
            "category":"Government",
            "subcategory":"Post Office",
            "type":"Public Place"
        }
    ],
    "sg:phone":"+1 305 759 5002",
    "sg:postcode":"33138",
    "sg:province":"FL",
    "sg:tags":[
        "courier",
        "shipping",
        "delivery",
        "messenger",
        "mail"
    ],
    "sg:website":"http://www.90minutecourier.com",
    "wof:name":"90 Minute Courier",
    "wof:placetype":"venue"
},
  "geometry": {"coordinates":[-80.190321,25.838031],"type":"Point"}
}