{
  "type": "Feature",
  "properties": {
    "addr:full":"5751 Youngquist Rd Fort Myers FL 33912",
    "addr:housenumber":"5751",
    "addr:postcode":"33912",
    "addr:street":"Youngquist Rd",
    "iso:country":"US",
    "sg:address":"5751 Youngquist Rd",
    "sg:city":"Fort Myers",
    "sg:classifiers":[
        {
            "category":"Home & Garden",
            "subcategory":"Furniture",
            "type":"Retail Goods"
        }
    ],
    "sg:phone":"+1 239 433 1188",
    "sg:postcode":"33912",
    "sg:province":"FL",
    "sg:tags":[
        "top",
        "counter"
    ],
    "wof:name":"Harp Industries",
    "wof:placetype":"venue"
},
  "geometry": {"coordinates":[-81.86056499999999,26.510993],"type":"Point"}
}