{
  "type": "Feature",
  "properties": {
    "addr:full":"168 Kildare Dr Sebastian FL 32958",
    "addr:housenumber":"168",
    "addr:postcode":"32958",
    "addr:street":"Kildare Dr",
    "iso:country":"US",
    "sg:address":"168 Kildare Dr",
    "sg:city":"Sebastian",
    "sg:classifiers":[
        {
            "category":"Farming",
            "subcategory":"Fish & Marine Products",
            "type":"Manufacturing & Wholesale Goods"
        }
    ],
    "sg:phone":"+1 772 581 4569",
    "sg:postcode":"32958",
    "sg:province":"FL",
    "sg:tags":[
        "fishing"
    ],
    "wof:name":"Patrick W Hynes",
    "wof:placetype":"venue"
},
  "geometry": {"coordinates":[-80.47002999999999,27.78483],"type":"Point"}
}