{
  "type": "Feature",
  "properties": {
    "iso:country":"US",
    "sg:address":"250 NE 6th Blvd",
    "sg:city":"Williston",
    "sg:classifiers":[
        {
            "category":"Organizations",
            "subcategory":"Community Association",
            "type":"Services"
        }
    ],
    "sg:phone":"+1 352 528 2904",
    "sg:postcode":"32696",
    "sg:province":"FL",
    "sg:tags":[
        "fraternal"
    ],
    "wof:name":"Masonic Lodge",
    "wof:placetype":"venue"
},
  "geometry": {"coordinates":[-82.445054,29.396684],"type":"Point"}
}