{
  "type": "Feature",
  "properties": {
    "iso:country":"US",
    "sg:address":"26 N Beach St",
    "sg:city":"Ormond Beach",
    "sg:classifiers":[
        {
            "category":"Health Services",
            "subcategory":"Chiropractor",
            "type":"Services"
        }
    ],
    "sg:phone":"+1 386 673 0201",
    "sg:postcode":"32174",
    "sg:province":"FL",
    "wof:name":"Pain Medicine Rehabilitation &",
    "wof:placetype":"venue"
},
  "geometry": {"coordinates":[-81.05634000000001,29.287508],"type":"Point"}
}