{
  "type": "Feature",
  "properties": {
    "addr:full":"6140 E Hwy 98 Panama City FL 32404",
    "addr:housenumber":"6140",
    "addr:postcode":"32404",
    "addr:street":"E Hwy 98",
    "iso:country":"US",
    "sg:address":"6140 E Hwy 98",
    "sg:city":"Panama City",
    "sg:classifiers":[
        {
            "category":"Real Estate",
            "subcategory":"Real Estate Agent",
            "type":"Services"
        }
    ],
    "sg:phone":"+1 850 896 0910",
    "sg:postcode":"32404",
    "sg:province":"FL",
    "wof:name":"Rainier Properties Inc",
    "wof:placetype":"venue"
},
  "geometry": {"coordinates":[-85.600058,30.113934],"type":"Point"}
}