{
  "type": "Feature",
  "properties": {
    "addr:full":"5760 N Orange Blossom Trl Orlando FL 32810",
    "addr:housenumber":"5760",
    "addr:postcode":"32810",
    "addr:street":"N Orange Blossom Trl",
    "iso:country":"US",
    "sg:address":"5760 N Orange Blossom Trl",
    "sg:city":"Orlando",
    "sg:classifiers":[
        {
            "category":"Shopping",
            "subcategory":"Pharmacy",
            "type":"Retail Goods"
        }
    ],
    "sg:phone":"+1 407 297 8017",
    "sg:postcode":"32810",
    "sg:province":"FL",
    "sg:tags":[
        "photofinishing",
        "laboratory"
    ],
    "wof:name":"CVS",
    "wof:placetype":"venue"
},
  "geometry": {"coordinates":[-81.42818699999999,28.610155],"type":"Point"}
}