{
  "type": "Feature",
  "properties": {
    "iso:country":"US",
    "sg:address":"4360 Gulf Shore Blvd N",
    "sg:city":"Naples",
    "sg:classifiers":[
        {
            "category":"Shopping",
            "subcategory":"Clothing, Apparel, & Fashions",
            "type":"Retail Goods"
        }
    ],
    "sg:phone":"+1 239 643 2728",
    "sg:postcode":"34103",
    "sg:province":"FL",
    "wof:name":"Curvaceous",
    "wof:placetype":"venue"
},
  "geometry": {"coordinates":[-81.81262700000001,26.198348],"type":"Point"}
}