{
  "type": "Feature",
  "properties": {
    "iso:country":"US",
    "sg:address":"15207 SW 46th Ln",
    "sg:city":"Miami",
    "sg:classifiers":[
        {
            "category":"Shopping",
            "subcategory":"Clothing, Apparel, & Fashions",
            "type":"Retail Goods"
        }
    ],
    "sg:phone":"+1 786 226 3117",
    "sg:postcode":"33185",
    "sg:province":"FL",
    "sg:tags":[
        "clothing",
        "glove",
        "store"
    ],
    "wof:name":"Reggae Blend, Inc.",
    "wof:placetype":"venue"
},
  "geometry": {"coordinates":[-80.43951,25.721719],"type":"Point"}
}