{
  "type": "Feature",
  "properties": {
    "iso:country":"US",
    "sg:address":"236 Edgemere Way E",
    "sg:city":"Naples",
    "sg:classifiers":[
        {
            "category":"Building & Trades",
            "subcategory":"Construction",
            "type":"Services"
        }
    ],
    "sg:phone":"+1 239 261 6242",
    "sg:postcode":"34105",
    "sg:province":"FL",
    "sg:tags":[
        "general",
        "contractor"
    ],
    "wof:name":"J F Smith Bldg Contractors Inc",
    "wof:placetype":"venue"
},
  "geometry": {"coordinates":[-81.736599,26.186629],"type":"Point"}
}