{
  "type": "Feature",
  "properties": {
    "addr:full":"2143 NW 20th St Miami FL 33142",
    "addr:housenumber":"2143",
    "addr:postcode":"33142",
    "addr:street":"Nw 20Th St",
    "iso:country":"US",
    "sg:address":"2143 NW 20th St",
    "sg:city":"Miami",
    "sg:classifiers":[
        {
            "category":"Shopping",
            "subcategory":"Clothing, Apparel, & Fashions",
            "type":"Retail Goods"
        },
        {
            "category":"Manufacturing",
            "subcategory":"Apparel",
            "type":"Manufacturing & Wholesale Goods"
        }
    ],
    "sg:phone":"+1 305 325 0074",
    "sg:postcode":"33142",
    "sg:province":"FL",
    "sg:tags":[
        "apparel-wholesale",
        "accessory",
        "clothing",
        "manufacturer",
        "women's"
    ],
    "wof:name":"Indian Tropical Fashions Inc",
    "wof:placetype":"venue"
},
  "geometry": {"coordinates":[-80.230282,25.794696],"type":"Point"}
}