{
  "type": "Feature",
  "properties": {
    "addr:full":"2635 Temple Dr Winter Park FL 32789",
    "addr:housenumber":"2635",
    "addr:postcode":"32789",
    "addr:street":"Temple Dr",
    "iso:country":"US",
    "sg:address":"2635 Temple Dr",
    "sg:city":"Winter Park",
    "sg:classifiers":[
        {
            "category":"Sports & Exercise",
            "subcategory":"Gym",
            "type":"Entertainment"
        }
    ],
    "sg:phone":"+1 407 644 1967",
    "sg:postcode":"32789",
    "sg:province":"FL",
    "sg:tags":[
        "facility",
        "club",
        "sp",
        "gymnasium",
        "personal",
        "studio",
        "fitness",
        "health",
        "physical"
    ],
    "wof:name":"Wellness Zone",
    "wof:placetype":"venue"
},
  "geometry": {"coordinates":[-81.33595,28.624145],"type":"Point"}
}