{
  "type": "Feature",
  "properties": {
    "iso:country":"US",
    "sg:address":"2500 Lee Rd",
    "sg:city":"Orlando",
    "sg:classifiers":[
        {
            "category":"Government",
            "subcategory":"Office",
            "type":"Public Place"
        }
    ],
    "sg:phone":"+1 407 628 4144",
    "sg:postcode":"32810",
    "sg:province":"FL",
    "wof:name":"Us Defense Security Svc",
    "wof:placetype":"venue"
},
  "geometry": {"coordinates":[-81.414523,28.599087],"type":"Point"}
}