{
  "type": "Feature",
  "properties": {
    "addr:full":"2725 Judge Fran Jamieson Way Melbourne FL 32940",
    "addr:housenumber":"2725",
    "addr:postcode":"32940",
    "addr:street":"Judge Fran Jamieson Way",
    "iso:country":"US",
    "sg:address":"2725 Judge Fran Jamieson Way",
    "sg:city":"Melbourne",
    "sg:classifiers":[
        {
            "category":"Government",
            "subcategory":"Office",
            "type":"Public Place"
        }
    ],
    "sg:phone":"+1 321 617 7510",
    "sg:postcode":"32940",
    "sg:province":"FL",
    "sg:tags":[
        "government-state"
    ],
    "sg:website":"http://www.duvalclerk.com",
    "wof:name":"Florida State Of",
    "wof:placetype":"venue"
},
  "geometry": {"coordinates":[-80.736906,28.24763],"type":"Point"}
}