{
  "type": "Feature",
  "properties": {
    "iso:country":"US",
    "sg:address":"645 Herndon Ave",
    "sg:city":"Orlando",
    "sg:classifiers":[
        {
            "category":"Professional",
            "subcategory":"Advertising",
            "type":"Services"
        }
    ],
    "sg:phone":"+1 407 896 7000",
    "sg:postcode":"32803",
    "sg:province":"FL",
    "sg:tags":[
        "counselor"
    ],
    "wof:name":"Antique Custom & Sport Car",
    "wof:placetype":"venue"
},
  "geometry": {"coordinates":[-81.337384,28.552599],"type":"Point"}
}