{
  "type": "Feature",
  "properties": {
    "iso:country":"US",
    "sg:address":"7281 Eleanor Cir",
    "sg:city":"Sarasota",
    "sg:classifiers":[
        {
            "category":"Building & Trades",
            "subcategory":"Construction",
            "type":"Services"
        }
    ],
    "sg:phone":"+1 941 228 6560",
    "sg:postcode":"34243",
    "sg:province":"FL",
    "sg:tags":[
        "carpenter"
    ],
    "wof:name":"Sergey Popesky Carpentry",
    "wof:placetype":"venue"
},
  "geometry": {"coordinates":[-82.500069,27.410458],"type":"Point"}
}