{
  "type": "Feature",
  "properties": {
    "addr:full":"8217 Fort Dade Ave Brooksville FL 34601",
    "addr:housenumber":"8217",
    "addr:postcode":"34601",
    "addr:street":"Fort Dade Ave",
    "iso:country":"US",
    "sg:address":"8217 Fort Dade Ave",
    "sg:city":"Brooksville",
    "sg:classifiers":[
        {
            "category":"Home & Garden",
            "subcategory":"Mobile Homes",
            "type":"Retail Goods"
        }
    ],
    "sg:phone":"+1 352 796 7002",
    "sg:postcode":"34601",
    "sg:province":"FL",
    "wof:name":"Wilkins Mobile Home Setup Inc",
    "wof:placetype":"venue"
},
  "geometry": {"coordinates":[-82.45509699999999,28.555531],"type":"Point"}
}