{
  "type": "Feature",
  "properties": {
    "addr:full":"3956 Dunwoody Dr Pensacola FL 32503",
    "addr:housenumber":"3956",
    "addr:postcode":"32503",
    "addr:street":"Dunwoody Dr",
    "iso:country":"US",
    "sg:address":"3956 Dunwoody Dr",
    "sg:city":"Pensacola",
    "sg:classifiers":[
        {
            "category":"Real Estate",
            "subcategory":"Real Estate Agent",
            "type":"Services"
        }
    ],
    "sg:phone":"+1 850 433 1460",
    "sg:postcode":"32503",
    "sg:province":"FL",
    "wof:name":"Hornsby Co",
    "wof:placetype":"venue"
},
  "geometry": {"coordinates":[-87.202747,30.459342],"type":"Point"}
}