{
  "type": "Feature",
  "properties": {
    "addr:full":"5816 Regent Rd Venice FL 34293",
    "addr:housenumber":"5816",
    "addr:postcode":"34293",
    "addr:street":"Regent Rd",
    "iso:country":"US",
    "sg:address":"5816 Regent Rd",
    "sg:city":"Venice",
    "sg:classifiers":[
        {
            "category":"Building & Trades",
            "subcategory":"Construction",
            "type":"Services"
        }
    ],
    "sg:phone":"+1 941 493 1978",
    "sg:postcode":"34293",
    "sg:province":"FL",
    "sg:tags":[
        "contractor"
    ],
    "wof:name":"A & M Cstm Crmic Tile Setting",
    "wof:placetype":"venue"
},
  "geometry": {"coordinates":[-82.41115000000001,27.025916],"type":"Point"}
}