{
  "type": "Feature",
  "properties": {
    "iso:country":"US",
    "sg:address":"8228 NW 30th Ter",
    "sg:city":"Doral",
    "sg:classifiers":[
        {
            "category":"Wholesale",
            "subcategory":"Durable Goods & Equipment",
            "type":"Manufacturing & Wholesale Goods"
        }
    ],
    "sg:phone":"+1 305 994 7994",
    "sg:postcode":"33122",
    "sg:province":"FL",
    "sg:tags":[
        "exporter"
    ],
    "wof:name":"MIC Import & Export",
    "wof:placetype":"venue"
},
  "geometry": {"coordinates":[-80.33248399999999,25.801636],"type":"Point"}
}