{
  "type": "Feature",
  "properties": {
    "iso:country":"US",
    "sg:address":"707 N Goldenrod Rd",
    "sg:city":"Orlando",
    "sg:classifiers":[
        {
            "category":"Personal",
            "subcategory":"Beauty Salon",
            "type":"Services"
        }
    ],
    "sg:phone":"+1 407 381 3699",
    "sg:postcode":"32807",
    "sg:province":"FL",
    "wof:name":"Universal Beauty Salon",
    "wof:placetype":"venue"
},
  "geometry": {"coordinates":[-81.285875,28.5547],"type":"Point"}
}