{
  "type": "Feature",
  "properties": {
    "iso:country":"US",
    "sg:address":"936 Crystal Cresst Ter",
    "sg:city":"Crystal River",
    "sg:classifiers":[
        {
            "category":"Health Services",
            "subcategory":"Doctor",
            "type":"Services"
        }
    ],
    "sg:phone":"+1 352 564 8802",
    "sg:postcode":"34429",
    "sg:province":"FL",
    "sg:tags":[
        "physician",
        "surgeon"
    ],
    "wof:name":"Quehuong Pham MD",
    "wof:placetype":"venue"
},
  "geometry": {"coordinates":[-82.57364200000001,28.875107],"type":"Point"}
}