{
  "type": "Feature",
  "properties": {
    "addr:full":"250 E Palm Dr Homestead FL 33034",
    "addr:housenumber":"250",
    "addr:postcode":"33034",
    "addr:street":"E Palm Dr",
    "iso:country":"US",
    "sg:address":"250 E Palm Dr",
    "sg:city":"Homestead",
    "sg:classifiers":[
        {
            "category":"Restaurant",
            "type":"Food & Drink"
        }
    ],
    "sg:menulink":"http://www.allmenus.com/fl/homestead/82969-villa-pizza/menu/",
    "sg:phone":"+1 305 247 2515",
    "sg:postcode":"33034",
    "sg:province":"FL",
    "sg:tags":[
        "american",
        "italian",
        "pizza"
    ],
    "wof:name":"Villa Pizza",
    "wof:placetype":"venue"
},
  "geometry": {"coordinates":[-80.473189,25.452091],"type":"Point"}
}