{
  "type": "Feature",
  "properties": {
    "addr:full":"9503 NW 52nd Ct Fort Lauderdale FL 33351",
    "addr:housenumber":"9503",
    "addr:postcode":"33351",
    "addr:street":"Nw 52Nd Ct",
    "iso:country":"US",
    "sg:address":"9503 NW 52nd Ct",
    "sg:city":"Fort Lauderdale",
    "sg:classifiers":[
        {
            "category":"Professional",
            "subcategory":"Computer Services",
            "type":"Services"
        }
    ],
    "sg:phone":"+1 954 747 7773",
    "sg:postcode":"33351",
    "sg:province":"FL",
    "sg:tags":[
        "datum"
    ],
    "wof:name":"Swarm Interactive",
    "wof:placetype":"venue"
},
  "geometry": {"coordinates":[-80.279571,26.188069],"type":"Point"}
}