{
  "type": "Feature",
  "properties": {
    "addr:full":"201 E Government St Pensacola FL 32502",
    "addr:housenumber":"201",
    "addr:postcode":"32502",
    "addr:street":"E Government St",
    "iso:country":"US",
    "sg:address":"201 E Government St",
    "sg:city":"Pensacola",
    "sg:classifiers":[
        {
            "category":"Professional",
            "subcategory":"Lawyer & Legal Services",
            "type":"Services"
        }
    ],
    "sg:phone":"+1 850 432 7705",
    "sg:postcode":"32502",
    "sg:province":"FL",
    "sg:tags":[
        "attorney",
        "law",
        "family",
        "duo",
        "divorce",
        "child",
        "criminal",
        "dwi",
        "custody"
    ],
    "wof:name":"Peeler Law Firm, P.C.",
    "wof:placetype":"venue"
},
  "geometry": {"coordinates":[-87.21196,30.40971],"type":"Point"}
}