{
  "type": "Feature",
  "properties": {
    "addr:full":"815 Orienta Ave Altamonte Springs FL 32701",
    "addr:housenumber":"815",
    "addr:postcode":"32701",
    "addr:street":"Orienta Ave",
    "iso:country":"US",
    "sg:address":"815 Orienta Ave",
    "sg:city":"Altamonte Springs",
    "sg:classifiers":[
        {
            "category":"Professional",
            "subcategory":"Lawyer & Legal Services",
            "type":"Services"
        }
    ],
    "sg:phone":"+1 407 332 9111",
    "sg:postcode":"32701",
    "sg:province":"FL",
    "wof:name":"Fountain Dennis F Atty At Law",
    "wof:placetype":"venue"
},
  "geometry": {"coordinates":[-81.362701,28.6611],"type":"Point"}
}