{
  "type": "Feature",
  "properties": {
    "iso:country":"US",
    "sg:address":"5635 Bayview Dr",
    "sg:city":"Seminole",
    "sg:classifiers":[
        {
            "category":"Building & Trades",
            "subcategory":"Electrical",
            "type":"Services"
        }
    ],
    "sg:phone":"+1 727 393 2016",
    "sg:postcode":"33772",
    "sg:province":"FL",
    "sg:tags":[
        "electrical",
        "contractor"
    ],
    "wof:name":"Troup Electric",
    "wof:placetype":"venue"
},
  "geometry": {"coordinates":[-82.803556,27.822604],"type":"Point"}
}