{
  "type": "Feature",
  "properties": {
    "addr:full":"20784 Boca Ridge Dr N Boca Raton FL 33428",
    "addr:housenumber":"20784",
    "addr:postcode":"33428",
    "addr:street":"Boca Ridge Dr N",
    "iso:country":"US",
    "sg:address":"20784 Boca Ridge Dr N",
    "sg:city":"Boca Raton",
    "sg:classifiers":[
        {
            "category":"Real Estate",
            "subcategory":"Real Estate Agent",
            "type":"Services"
        }
    ],
    "sg:phone":"+1 561 483 8961",
    "sg:postcode":"33428",
    "sg:province":"FL",
    "wof:name":"Alliance Realty",
    "wof:placetype":"venue"
},
  "geometry": {"coordinates":[-80.19401999999999,26.367291],"type":"Point"}
}