{
  "type": "Feature",
  "properties": {
    "iso:country":"US",
    "sg:address":"3915 S Nova Rd",
    "sg:city":"Daytona Beach",
    "sg:classifiers":[
        {
            "category":"Retail",
            "subcategory":"Veterinary Services",
            "type":"Services"
        }
    ],
    "sg:phone":"+1 386 761 8844",
    "sg:postcode":"32127",
    "sg:province":"FL",
    "wof:name":"James G Trantham Dvm",
    "wof:placetype":"venue"
},
  "geometry": {"coordinates":[-81.002408,29.122644],"type":"Point"}
}