{
  "type": "Feature",
  "properties": {
    "addr:full":"7 Sanctuary Ave Debary FL 32713",
    "addr:housenumber":"7",
    "addr:postcode":"32713",
    "addr:street":"Sanctuary Ave",
    "iso:country":"US",
    "sg:address":"7 Sanctuary Ave",
    "sg:city":"Debary",
    "sg:classifiers":[
        {
            "category":"Freight",
            "type":"Transportation"
        }
    ],
    "sg:phone":"+1 386 668 1937",
    "sg:postcode":"32713",
    "sg:province":"FL",
    "sg:tags":[
        "commercial",
        "storage"
    ],
    "wof:name":"Highbanks Mini Storage",
    "wof:placetype":"venue"
},
  "geometry": {"coordinates":[-81.340411,28.886384],"type":"Point"}
}