{
  "type": "Feature",
  "properties": {
    "addr:full":"5301 SW 7th St Plantation FL 33317",
    "addr:housenumber":"5301",
    "addr:postcode":"33317",
    "addr:street":"Sw 7Th St",
    "iso:country":"US",
    "sg:address":"5301 SW 7th St",
    "sg:city":"Plantation",
    "sg:classifiers":[
        {
            "category":"Retail",
            "subcategory":"Repair Shop",
            "type":"Services"
        }
    ],
    "sg:phone":"+1 954 791 6799",
    "sg:postcode":"33317",
    "sg:province":"FL",
    "sg:tags":[
        "equipment",
        "conditioning",
        "air"
    ],
    "wof:name":"Cool Comfort Air Cond & Refrig",
    "wof:placetype":"venue"
},
  "geometry": {"coordinates":[-80.220703,26.11216],"type":"Point"}
}