{
  "type": "Feature",
  "properties": {
    "iso:country":"US",
    "sg:address":"335 S Plumosa St",
    "sg:city":"Merritt Island",
    "sg:classifiers":[
        {
            "category":"Personal",
            "subcategory":"Beauty Salon",
            "type":"Services"
        }
    ],
    "sg:phone":"+1 321 452 8323",
    "sg:postcode":"32952",
    "sg:province":"FL",
    "sg:tags":[
        "shop"
    ],
    "wof:name":"Bangs of Brevard County Inc",
    "wof:placetype":"venue"
},
  "geometry": {"coordinates":[-80.692151,28.352969],"type":"Point"}
}