{
  "type": "Feature",
  "properties": {
    "addr:full":"8644 US Hwy 441 Leesburg FL 34788",
    "addr:housenumber":"8644",
    "addr:postcode":"34788",
    "addr:street":"Us Hwy 441",
    "iso:country":"US",
    "sg:address":"8644 US Hwy 441",
    "sg:city":"Leesburg",
    "sg:classifiers":[
        {
            "category":"Autos & Motor Vehicles",
            "subcategory":"Automobile Sales",
            "type":"Retail Goods"
        }
    ],
    "sg:phone":"+1 352 365 1228",
    "sg:postcode":"34788",
    "sg:province":"FL",
    "wof:name":"Johnsons Kia",
    "wof:placetype":"venue"
},
  "geometry": {"coordinates":[-81.815074,28.831812],"type":"Point"}
}