{
  "type": "Feature",
  "properties": {
    "iso:country":"US",
    "sg:address":"2417 18th Ave W",
    "sg:city":"Bradenton",
    "sg:classifiers":[
        {
            "category":"Building & Trades",
            "subcategory":"Construction",
            "type":"Services"
        }
    ],
    "sg:phone":"+1 941 750 8247",
    "sg:postcode":"34205",
    "sg:province":"FL",
    "sg:tags":[
        "carpenter"
    ],
    "wof:name":"Absolute Framing LLC",
    "wof:placetype":"venue"
},
  "geometry": {"coordinates":[-82.585356,27.483626],"type":"Point"}
}