{
  "type": "Feature",
  "properties": {
    "iso:country":"US",
    "sg:address":"6164 SW 2nd St",
    "sg:city":"Pompano Beach",
    "sg:classifiers":[
        {
            "category":"Building & Trades",
            "subcategory":"Construction",
            "type":"Services"
        }
    ],
    "sg:phone":"+1 954 984 4312",
    "sg:postcode":"33068",
    "sg:province":"FL",
    "sg:tags":[
        "hanging",
        "contractor"
    ],
    "wof:name":"Gh Painting Inc",
    "wof:placetype":"venue"
},
  "geometry": {"coordinates":[-80.20893599999999,26.228814],"type":"Point"}
}