{
  "type": "Feature",
  "properties": {
    "iso:country":"US",
    "sg:address":"11318 Taft St",
    "sg:city":"Hollywood",
    "sg:classifiers":[
        {
            "category":"Food & Beverages",
            "subcategory":"Specialty",
            "type":"Retail Goods"
        }
    ],
    "sg:phone":"+1 954 443 1948",
    "sg:postcode":"33026",
    "sg:province":"FL",
    "wof:name":"Sport Nutrition Warehouse Inc",
    "wof:placetype":"venue"
},
  "geometry": {"coordinates":[-80.30195999999999,26.024082],"type":"Point"}
}