{
  "type": "Feature",
  "properties": {
    "addr:full":"880 NW 210th St Miami FL 33169",
    "addr:housenumber":"880",
    "addr:postcode":"33169",
    "addr:street":"Nw 210Th St",
    "iso:country":"US",
    "sg:address":"880 NW 210th St",
    "sg:city":"Miami",
    "sg:classifiers":[
        {
            "category":"Retail",
            "subcategory":"Auto Repair",
            "type":"Services"
        }
    ],
    "sg:phone":"+1 305 917 0410",
    "sg:postcode":"33169",
    "sg:province":"FL",
    "sg:tags":[
        "body",
        "automobile",
        "painting",
        "repairing"
    ],
    "wof:name":"G S B Body Shop Corporation",
    "wof:placetype":"venue"
},
  "geometry": {"coordinates":[-80.217912,25.968785],"type":"Point"}
}