{
  "type": "Feature",
  "properties": {
    "addr:full":"1110 N G St Lake Worth FL 33460",
    "addr:housenumber":"1110",
    "addr:postcode":"33460",
    "addr:street":"N G St",
    "iso:country":"US",
    "sg:address":"1110 N G St",
    "sg:city":"Lake Worth",
    "sg:classifiers":[
        {
            "category":"Education",
            "subcategory":"Special Training",
            "type":"Public Place"
        }
    ],
    "sg:phone":"+1 561 533 0077",
    "sg:postcode":"33460",
    "sg:province":"FL",
    "sg:tags":[
        "educational"
    ],
    "wof:name":"Rosemary Educational Inc",
    "wof:placetype":"venue"
},
  "geometry": {"coordinates":[-80.058781,26.629894],"type":"Point"}
}