{
  "type": "Feature",
  "properties": {
    "addr:full":"1006 Capri St Coral Gables FL 33134",
    "addr:housenumber":"1006",
    "addr:postcode":"33134",
    "addr:street":"Capri St",
    "iso:country":"US",
    "sg:address":"1006 Capri St",
    "sg:city":"Coral Gables",
    "sg:classifiers":[
        {
            "category":"Professional",
            "subcategory":"Business Services",
            "type":"Services"
        }
    ],
    "sg:phone":"+1 305 461 2503",
    "sg:postcode":"33134",
    "sg:province":"FL",
    "sg:tags":[
        "event"
    ],
    "wof:name":"Exilio Productions",
    "wof:placetype":"venue"
},
  "geometry": {"coordinates":[-80.274844,25.763171],"type":"Point"}
}