{
  "type": "Feature",
  "properties": {
    "iso:country":"US",
    "sg:address":"1970 Boyce St",
    "sg:city":"Sarasota",
    "sg:classifiers":[
        {
            "category":"Manufacturing",
            "subcategory":"Chemicals & Compounds",
            "type":"Manufacturing & Wholesale Goods"
        }
    ],
    "sg:phone":"+1 941 955 4247",
    "sg:postcode":"34239",
    "sg:province":"FL",
    "sg:tags":[
        "preparation",
        "toilet",
        "beauty",
        "shop",
        "mfg"
    ],
    "wof:name":"Advanced Hair Restoration",
    "wof:placetype":"venue"
},
  "geometry": {"coordinates":[-82.53336899999999,27.31138],"type":"Point"}
}