{
  "type": "Feature",
  "properties": {
    "addr:full":"2500 NW 107th Ave Doral FL 33172",
    "addr:housenumber":"2500",
    "addr:postcode":"33172",
    "addr:street":"Nw 107Th Ave",
    "iso:country":"US",
    "sg:address":"2500 NW 107th Ave",
    "sg:city":"Doral",
    "sg:classifiers":[
        {
            "category":"Professional",
            "subcategory":"Management & Consulting",
            "type":"Services"
        }
    ],
    "sg:phone":"+1 305 436 8664",
    "sg:postcode":"33172",
    "sg:province":"FL",
    "sg:tags":[
        "fuel"
    ],
    "wof:name":"All Around Management",
    "wof:placetype":"venue"
},
  "geometry": {"coordinates":[-80.36915399999999,25.798827],"type":"Point"}
}