{
  "type": "Feature",
  "properties": {
    "addr:full":"6067 Hollywood Blvd Hollywood FL 33024",
    "addr:housenumber":"6067",
    "addr:postcode":"33024",
    "addr:street":"Hollywood Blvd",
    "iso:country":"US",
    "sg:address":"6067 Hollywood Blvd",
    "sg:city":"Hollywood",
    "sg:classifiers":[
        {
            "category":"Building & Trades",
            "subcategory":"Construction",
            "type":"Services"
        }
    ],
    "sg:phone":"+1 954 438 4011",
    "sg:postcode":"33024",
    "sg:province":"FL",
    "sg:tags":[
        "painter"
    ],
    "wof:name":"Alotta Pressure",
    "wof:placetype":"venue"
},
  "geometry": {"coordinates":[-80.208544,26.010231],"type":"Point"}
}