{
  "type": "Feature",
  "properties": {
    "addr:full":"451 E Altamonte Dr Altamonte Springs FL 32701",
    "addr:housenumber":"451",
    "addr:postcode":"32701",
    "addr:street":"E Altamonte Dr",
    "iso:country":"US",
    "sg:address":"451 E Altamonte Dr",
    "sg:city":"Altamonte Springs",
    "sg:classifiers":[
        {
            "category":"Retail",
            "subcategory":"Auto Rental",
            "type":"Services"
        }
    ],
    "sg:phone":"+1 407 767 0380",
    "sg:postcode":"32701",
    "sg:province":"FL",
    "sg:tags":[
        "car"
    ],
    "sg:website":"www.avis.com",
    "wof:name":"Avis Rent A Car Nationwide Reservations",
    "wof:placetype":"venue"
},
  "geometry": {"coordinates":[-81.377315,28.664045],"type":"Point"}
}