{
  "type": "Feature",
  "properties": {
    "iso:country":"US",
    "sg:address":"6170 Moonbeam Dr",
    "sg:city":"Lake Worth",
    "sg:classifiers":[
        {
            "category":"Building & Trades",
            "subcategory":"Construction",
            "type":"Services"
        }
    ],
    "sg:phone":"+1 561 439 4028",
    "sg:postcode":"33463",
    "sg:province":"FL",
    "sg:tags":[
        "hanging",
        "contractor"
    ],
    "wof:name":"Martinez Cipriano",
    "wof:placetype":"venue"
},
  "geometry": {"coordinates":[-80.14293000000001,26.590738],"type":"Point"}
}