{
  "type": "Feature",
  "properties": {
    "addr:full":"30 Oaks Dr Jacksonville Bch FL 32250",
    "addr:postcode":"32250",
    "addr:street":"30 Oaks Dr",
    "iso:country":"US",
    "sg:address":"30 Oaks Dr",
    "sg:city":"Jacksonville Bch",
    "sg:classifiers":[
        {
            "category":"Building & Trades",
            "subcategory":"Construction",
            "type":"Services"
        }
    ],
    "sg:phone":"+1 904 247 7060",
    "sg:postcode":"32250",
    "sg:province":"FL",
    "sg:tags":[
        "hanging",
        "paper",
        "painting",
        "painter",
        "contractor"
    ],
    "wof:name":"R W Wood & Associates Inc",
    "wof:placetype":"venue"
},
  "geometry": {"coordinates":[-81.404242,30.272566],"type":"Point"}
}