{
  "type": "Feature",
  "properties": {
    "iso:country":"US",
    "sg:address":"2245 Leaside Ct",
    "sg:city":"Merritt Island",
    "sg:classifiers":[
        {
            "category":"Building & Trades",
            "subcategory":"Construction",
            "type":"Services"
        }
    ],
    "sg:phone":"+1 321 452 1537",
    "sg:postcode":"32952",
    "sg:province":"FL",
    "sg:tags":[
        "hanging",
        "contractor"
    ],
    "wof:name":"Able Industrial Maintenance",
    "wof:placetype":"venue"
},
  "geometry": {"coordinates":[-80.67006499999999,28.397468],"type":"Point"}
}