{
  "type": "Feature",
  "properties": {
    "iso:country":"US",
    "sg:address":"10126 Woodberry Rd",
    "sg:city":"Tampa",
    "sg:classifiers":[
        {
            "category":"Real Estate",
            "subcategory":"Surveying",
            "type":"Services"
        }
    ],
    "sg:phone":"+1 813 662 3434",
    "sg:postcode":"33619",
    "sg:province":"FL",
    "wof:name":"Robertson & Associates",
    "wof:placetype":"venue"
},
  "geometry": {"coordinates":[-82.32937200000001,27.952313],"type":"Point"}
}