{
  "type": "Feature",
  "properties": {
    "addr:full":"4286 Windmill Point Ln Loxahatchee FL 33470",
    "addr:housenumber":"4286",
    "addr:postcode":"33470",
    "addr:street":"Windmill Point Ln",
    "iso:country":"US",
    "sg:address":"4286 Windmill Point Ln",
    "sg:city":"Loxahatchee",
    "sg:classifiers":[
        {
            "category":"Wholesale",
            "subcategory":"Plants",
            "type":"Manufacturing & Wholesale Goods"
        }
    ],
    "sg:phone":"+1 561 793 4834",
    "sg:postcode":"33470",
    "sg:province":"FL",
    "sg:tags":[
        "nursery",
        "tree"
    ],
    "wof:name":"Meadowlands Nursery",
    "wof:placetype":"venue"
},
  "geometry": {"coordinates":[-80.358343,26.747017],"type":"Point"}
}