{
  "type": "Feature",
  "properties": {
    "addr:full":"460 Lpga Blvd Daytona Beach FL 32117",
    "addr:housenumber":"460",
    "addr:postcode":"32117",
    "addr:street":"Lpga Blvd",
    "iso:country":"US",
    "sg:address":"460 Lpga Blvd",
    "sg:city":"Daytona Beach",
    "sg:classifiers":[
        {
            "category":"Retail",
            "subcategory":"Auto Repair",
            "type":"Services"
        }
    ],
    "sg:phone":"+1 386 253 2050",
    "sg:postcode":"32117",
    "sg:province":"FL",
    "sg:tags":[
        "automotive",
        "general"
    ],
    "wof:name":"Eds Auto Service",
    "wof:placetype":"venue"
},
  "geometry": {"coordinates":[-81.046131,29.244055],"type":"Point"}
}