{
  "type": "Feature",
  "properties": {
    "iso:country":"US",
    "sg:address":"14861 SW 152nd Ct",
    "sg:city":"Miami",
    "sg:classifiers":[
        {
            "category":"Building & Trades",
            "subcategory":"Construction",
            "type":"Services"
        }
    ],
    "sg:phone":"+1 305 776 6159",
    "sg:postcode":"33196",
    "sg:province":"FL",
    "sg:tags":[
        "tile-contractors"
    ],
    "wof:name":"W.P. Trading Corp Of Miami",
    "wof:placetype":"venue"
},
  "geometry": {"coordinates":[-80.439612,25.628724],"type":"Point"}
}