{
  "type": "Feature",
  "properties": {
    "addr:full":"16 Westgate Ln Boynton Beach FL 33436",
    "addr:housenumber":"16",
    "addr:postcode":"33436",
    "addr:street":"Westgate Ln",
    "iso:country":"US",
    "sg:address":"16 Westgate Ln",
    "sg:city":"Boynton Beach",
    "sg:classifiers":[
        {
            "category":"Real Estate",
            "subcategory":"Real Estate Agent",
            "type":"Services"
        }
    ],
    "sg:phone":"+1 561 734 8815",
    "sg:postcode":"33436",
    "sg:province":"FL",
    "wof:name":"Stage Street Inc",
    "wof:placetype":"venue"
},
  "geometry": {"coordinates":[-80.11280600000001,26.486884],"type":"Point"}
}