{
  "type": "Feature",
  "properties": {
    "addr:full":"2375 Bass Blvd Geneva FL 32732",
    "addr:housenumber":"2375",
    "addr:postcode":"32732",
    "addr:street":"Bass Blvd",
    "iso:country":"US",
    "sg:address":"2375 Bass Blvd",
    "sg:city":"Geneva",
    "sg:classifiers":[
        {
            "category":"Wholesale",
            "subcategory":"Machinery & Supplies",
            "type":"Manufacturing & Wholesale Goods"
        }
    ],
    "sg:phone":"+1 407 628 3225",
    "sg:postcode":"32732",
    "sg:province":"FL",
    "sg:tags":[
        "equipment",
        "system",
        "vacuum"
    ],
    "wof:name":"Silent Maid Central Vacuum",
    "wof:placetype":"venue"
},
  "geometry": {"coordinates":[-81.153345,28.787069],"type":"Point"}
}