{
  "type": "Feature",
  "properties": {
    "iso:country":"US",
    "sg:address":"6200 SW 17th St",
    "sg:city":"Pompano Beach",
    "sg:classifiers":[
        {
            "category":"Health Services",
            "subcategory":"Nursing And Care Facility",
            "type":"Services"
        }
    ],
    "sg:phone":"+1 954 979 5864",
    "sg:postcode":"33068",
    "sg:province":"FL",
    "sg:tags":[
        "home",
        "retirement",
        "community"
    ],
    "wof:name":"Broadview Boarding Home",
    "wof:placetype":"venue"
},
  "geometry": {"coordinates":[-80.20838500000001,26.205612],"type":"Point"}
}