{
  "type": "Feature",
  "properties": {
    "iso:country":"US",
    "sg:address":"115 E Davis Blvd",
    "sg:city":"Tampa",
    "sg:classifiers":[
        {
            "category":"Health Services",
            "subcategory":"Nursing And Care Facility",
            "type":"Services"
        }
    ],
    "sg:phone":"+1 813 254 8399",
    "sg:postcode":"33606",
    "sg:province":"FL",
    "wof:name":"Hudson Manor",
    "wof:placetype":"venue"
},
  "geometry": {"coordinates":[-82.456434,27.930758],"type":"Point"}
}