{
  "type": "Feature",
  "properties": {
    "iso:country":"US",
    "sg:address":"1637 Metropolitan Blvd",
    "sg:city":"Tallahassee",
    "sg:classifiers":[
        {
            "category":"Restaurant",
            "type":"Food & Drink"
        }
    ],
    "sg:phone":"+1 850 219 1408",
    "sg:postcode":"32308",
    "sg:province":"FL",
    "sg:tags":[
        "loan",
        "real estate"
    ],
    "wof:name":"Applejam Inc",
    "wof:placetype":"venue"
},
  "geometry": {"coordinates":[-84.250525,30.49764],"type":"Point"}
}