{
  "type": "Feature",
  "properties": {
    "addr:full":"1409 Bridlebrook Dr Casselberry FL 32707",
    "addr:housenumber":"1409",
    "addr:postcode":"32707",
    "addr:street":"Bridlebrook Dr",
    "iso:country":"US",
    "sg:address":"1409 Bridlebrook Dr",
    "sg:city":"Casselberry",
    "sg:classifiers":[
        {
            "category":"Recreation",
            "type":"Entertainment"
        }
    ],
    "sg:phone":"+1 407 695 6432",
    "sg:postcode":"32707",
    "sg:province":"FL",
    "sg:tags":[
        "instruction",
        "golf"
    ],
    "wof:name":"Brad Denton Golf Instruction",
    "wof:placetype":"venue"
},
  "geometry": {"coordinates":[-81.30345199999999,28.652765],"type":"Point"}
}