{
  "type": "Feature",
  "properties": {
    "addr:full":"13168 Cortez Blvd Brooksville FL 34613",
    "addr:housenumber":"13168",
    "addr:postcode":"34613",
    "addr:street":"Cortez Blvd",
    "iso:country":"US",
    "sg:address":"13168 Cortez Blvd",
    "sg:city":"Brooksville",
    "sg:classifiers":[
        {
            "category":"Building & Trades",
            "subcategory":"Equipment Rental",
            "type":"Services"
        }
    ],
    "sg:phone":"+1 352 596 9655",
    "sg:postcode":"34613",
    "sg:province":"FL",
    "sg:tags":[
        "appliance"
    ],
    "wof:name":"Rent Max",
    "wof:placetype":"venue"
},
  "geometry": {"coordinates":[-82.508912,28.533606],"type":"Point"}
}