{
  "type": "Feature",
  "properties": {
    "iso:country":"US",
    "sg:address":"3423 40th Way N",
    "sg:city":"St Petersburg",
    "sg:classifiers":[
        {
            "category":"Building & Trades",
            "subcategory":"Construction",
            "type":"Services"
        }
    ],
    "sg:phone":"+1 727 528 7500",
    "sg:postcode":"33713",
    "sg:province":"FL",
    "sg:tags":[
        "painter"
    ],
    "wof:name":"Peter Alexander Painter Life",
    "wof:placetype":"venue"
},
  "geometry": {"coordinates":[-82.688355,27.803495],"type":"Point"}
}