{
  "type": "Feature",
  "properties": {
    "iso:country":"US",
    "sg:address":"177 S Banana River Dr",
    "sg:city":"Merritt Island",
    "sg:classifiers":[
        {
            "category":"Building & Trades",
            "subcategory":"Electrical",
            "type":"Services"
        }
    ],
    "sg:phone":"+1 321 863 5239",
    "sg:postcode":"32952",
    "sg:province":"FL",
    "sg:tags":[
        "electrical",
        "contractor"
    ],
    "wof:name":"Innovative Netting Systems",
    "wof:placetype":"venue"
},
  "geometry": {"coordinates":[-80.662381,28.35597],"type":"Point"}
}