{
  "type": "Feature",
  "properties": {
    "addr:full":"80 SW 8th St Ste 2150 Miami FL 33130",
    "addr:housenumber":"80",
    "addr:postcode":"33130",
    "addr:street":"Sw 8Th St Ste 2150",
    "iso:country":"US",
    "sg:address":"80 SW 8th St Ste 2150",
    "sg:city":"Miami",
    "sg:classifiers":[
        {
            "category":"Professional",
            "subcategory":"Lawyer & Legal Services",
            "type":"Services"
        }
    ],
    "sg:phone":"+1 305 358 2727",
    "sg:postcode":"33130",
    "sg:province":"FL",
    "wof:name":"Adams & Quinton PA",
    "wof:placetype":"venue"
},
  "geometry": {"coordinates":[-80.195198,25.7663],"type":"Point"}
}