{
  "type": "Feature",
  "properties": {
    "iso:country":"US",
    "sg:address":"20537 Porthole Ct",
    "sg:city":"Estero",
    "sg:classifiers":[
        {
            "category":"Shopping",
            "subcategory":"Pets & Pet Supplies",
            "type":"Retail Goods"
        }
    ],
    "sg:phone":"+1 239 948 8550",
    "sg:postcode":"33928",
    "sg:province":"FL",
    "sg:tags":[
        "furnishing",
        "dog",
        "store",
        "cat"
    ],
    "wof:name":"Pet Kingdoms Bowwow Room",
    "wof:placetype":"venue"
},
  "geometry": {"coordinates":[-81.836095,26.440302],"type":"Point"}
}