{
  "type": "Feature",
  "properties": {
    "addr:full":"11801 Pembroke Rd Hollywood FL 33025",
    "addr:housenumber":"11801",
    "addr:postcode":"33025",
    "addr:street":"Pembroke Rd",
    "iso:country":"US",
    "sg:address":"11801 Pembroke Rd",
    "sg:city":"Hollywood",
    "sg:classifiers":[
        {
            "category":"Real Estate",
            "subcategory":"Developer",
            "type":"Services"
        },
        {
            "category":"Real Estate",
            "subcategory":"Real Estate Operator",
            "type":"Services"
        }
    ],
    "sg:phone":"+1 954 435 9997",
    "sg:postcode":"33025",
    "sg:province":"FL",
    "sg:tags":[
        "building",
        "apartment",
        "complex"
    ],
    "wof:name":"Pasadena Place Apartments",
    "wof:placetype":"venue"
},
  "geometry": {"coordinates":[-80.304976,25.993281],"type":"Point"}
}