{
  "type": "Feature",
  "properties": {
    "iso:country":"US",
    "sg:address":"699 S Highway 27",
    "sg:city":"Clermont",
    "sg:classifiers":[
        {
            "category":"Wholesale",
            "subcategory":"Farm Supplies",
            "type":"Manufacturing & Wholesale Goods"
        },
        {
            "category":"Utilities",
            "subcategory":"Water",
            "type":"Services"
        },
        {
            "category":"Wholesale",
            "subcategory":"Machinery & Supplies",
            "type":"Manufacturing & Wholesale Goods"
        },
        {
            "category":"Shopping",
            "subcategory":"Pets & Pet Supplies",
            "type":"Retail Goods"
        },
        {
            "category":"Sports & Exercise",
            "subcategory":"Race Track",
            "type":"Entertainment"
        }
    ],
    "sg:phone":"+1 352 242 1257",
    "sg:postcode":"34711",
    "sg:province":"FL",
    "sg:tags":[
        "feed",
        "horse",
        "supplement",
        "equipment",
        "concentrate",
        "baling",
        "barn"
    ],
    "wof:name":"Clermont Equestrian Saddlery & Feed Store",
    "wof:placetype":"venue"
},
  "geometry": {"coordinates":[-81.744558,28.568543],"type":"Point"}
}