{
  "type": "Feature",
  "properties": {
    "iso:country":"US",
    "sg:address":"601 S Martin Luther King Blvd",
    "sg:city":"Daytona Beach",
    "sg:classifiers":[
        {
            "category":"Food & Beverages",
            "subcategory":"Groceries & Convenience Stores",
            "type":"Retail Goods"
        }
    ],
    "sg:phone":"+1 386 253 7608",
    "sg:postcode":"32114",
    "sg:province":"FL",
    "sg:tags":[
        "grocer"
    ],
    "wof:name":"Ebony Cold Spot",
    "wof:placetype":"venue"
},
  "geometry": {"coordinates":[-81.022924,29.198072],"type":"Point"}
}