{
  "type": "Feature",
  "properties": {
    "iso:country":"US",
    "sg:address":"30101 W Dixie Hwy",
    "sg:city":"Homestead",
    "sg:classifiers":[
        {
            "category":"Autos & Motor Vehicles",
            "subcategory":"Automobile Sales",
            "type":"Retail Goods"
        }
    ],
    "sg:phone":"+1 305 248 5880",
    "sg:postcode":"33033",
    "sg:province":"FL",
    "sg:tags":[
        "car",
        "dealer"
    ],
    "wof:name":"Spitzer Dodge Of Homestead Inc",
    "wof:placetype":"venue"
},
  "geometry": {"coordinates":[-80.457532,25.490028],"type":"Point"}
}