{
  "type": "Feature",
  "properties": {
    "addr:full":"8320 14th Way N St Petersburg FL 33702",
    "addr:housenumber":"8320",
    "addr:postcode":"33702",
    "addr:street":"14Th Way N",
    "iso:country":"US",
    "sg:address":"8320 14th Way N",
    "sg:city":"St Petersburg",
    "sg:classifiers":[
        {
            "category":"Social Services",
            "subcategory":"Adult Care",
            "type":"Services"
        }
    ],
    "sg:phone":"+1 727 576 6069",
    "sg:postcode":"33702",
    "sg:province":"FL",
    "sg:tags":[
        "home",
        "residential"
    ],
    "wof:name":"Gateway Manor Assisted Living",
    "wof:placetype":"venue"
},
  "geometry": {"coordinates":[-82.652269,27.848061],"type":"Point"}
}