{
  "type": "Feature",
  "properties": {
    "addr:full":"1133 Clearwater Rd Daytona Beach FL 32114",
    "addr:housenumber":"1133",
    "addr:postcode":"32114",
    "addr:street":"Clearwater Rd",
    "iso:country":"US",
    "sg:address":"1133 Clearwater Rd",
    "sg:city":"Daytona Beach",
    "sg:classifiers":[
        {
            "category":"Building & Trades",
            "subcategory":"Construction",
            "type":"Services"
        }
    ],
    "sg:phone":"+1 386 258 9213",
    "sg:postcode":"32114",
    "sg:province":"FL",
    "sg:tags":[
        "nonresidential"
    ],
    "wof:name":"John Luxton",
    "wof:placetype":"venue"
},
  "geometry": {"coordinates":[-81.034204,29.179661],"type":"Point"}
}