{
  "type": "Feature",
  "properties": {
    "iso:country":"US",
    "sg:address":"1389 36th St NW",
    "sg:city":"Winter Haven",
    "sg:classifiers":[
        {
            "category":"Utilities",
            "subcategory":"Mobile Phone",
            "type":"Services"
        }
    ],
    "sg:phone":"+1 863 651 9355",
    "sg:postcode":"33881",
    "sg:province":"FL",
    "sg:tags":[
        "communication",
        "radiotelephone"
    ],
    "wof:name":"Sprint",
    "wof:placetype":"venue"
},
  "geometry": {"coordinates":[-81.77010199999999,28.037912],"type":"Point"}
}