{
  "type": "Feature",
  "properties": {
    "iso:country":"US",
    "sg:address":"1320 US Hwy 92",
    "sg:city":"Winter Haven",
    "sg:classifiers":[
        {
            "category":"Retail",
            "subcategory":"Auto Repair",
            "type":"Services"
        }
    ],
    "sg:phone":"+1 863 956 1977",
    "sg:postcode":"33881",
    "sg:province":"FL",
    "sg:tags":[
        "repairing",
        "automobile"
    ],
    "wof:name":"E E & K Inc Auto Sales",
    "wof:placetype":"venue"
},
  "geometry": {"coordinates":[-81.744259,28.070704],"type":"Point"}
}