{
  "type": "Feature",
  "properties": {
    "iso:country":"US",
    "sg:address":"14202 Flora Ln",
    "sg:city":"West Palm Beach",
    "sg:classifiers":[
        {
            "category":"Farming",
            "subcategory":"Livestock Farm",
            "type":"Manufacturing & Wholesale Goods"
        }
    ],
    "sg:phone":"+1 561 792 4368",
    "sg:postcode":"33414",
    "sg:province":"FL",
    "sg:tags":[
        "equine"
    ],
    "wof:name":"Sapphire Gates Farm Inc",
    "wof:placetype":"venue"
},
  "geometry": {"coordinates":[-80.27128,26.662388],"type":"Point"}
}