{
  "type": "Feature",
  "properties": {
    "addr:full":"4675 Elon Cres Lakeland FL 33810",
    "addr:housenumber":"4675",
    "addr:postcode":"33810",
    "addr:street":"Elon Cres",
    "iso:country":"US",
    "sg:address":"4675 Elon Cres",
    "sg:city":"Lakeland",
    "sg:classifiers":[
        {
            "category":"Personal",
            "subcategory":"Beauty Salon",
            "type":"Services"
        }
    ],
    "sg:phone":"+1 863 859 2918",
    "sg:postcode":"33810",
    "sg:province":"FL",
    "sg:tags":[
        "manicuring"
    ],
    "wof:name":"Hot Nails",
    "wof:placetype":"venue"
},
  "geometry": {"coordinates":[-81.983328,28.105436],"type":"Point"}
}