{
  "type": "Feature",
  "properties": {
    "addr:full":"21205 Keaton Beach Rd Perry FL 32348",
    "addr:postcode":"21205;32348",
    "addr:street":"Keaton Beach Rd",
    "iso:country":"US",
    "sg:address":"21205 Keaton Beach Rd",
    "sg:city":"Perry",
    "sg:classifiers":[
        {
            "category":"Shopping",
            "subcategory":"Gifts & Souvenirs",
            "type":"Retail Goods"
        }
    ],
    "sg:phone":"+1 850 578 2119",
    "sg:postcode":"32348",
    "sg:province":"FL",
    "sg:tags":[
        "shop"
    ],
    "wof:name":"Beach Treasures",
    "wof:placetype":"venue"
},
  "geometry": {"coordinates":[-83.59417999999999,29.819239],"type":"Point"}
}