{
  "type": "Feature",
  "properties": {
    "addr:full":"2288 N Flamingo Rd Hollywood FL 33028",
    "addr:housenumber":"2288",
    "addr:postcode":"33028",
    "addr:street":"N Flamingo Rd",
    "iso:country":"US",
    "sg:address":"2288 N Flamingo Rd",
    "sg:city":"Hollywood",
    "sg:classifiers":[
        {
            "category":"Autos & Motor Vehicles",
            "subcategory":"Auto Supplies",
            "type":"Retail Goods"
        }
    ],
    "sg:phone":"+1 954 880 0288",
    "sg:postcode":"33028",
    "sg:province":"FL",
    "wof:name":"Martino Tire Co Flamingo FA",
    "wof:placetype":"venue"
},
  "geometry": {"coordinates":[-80.312628,26.027926],"type":"Point"}
}