{
  "type": "Feature",
  "properties": {
    "iso:country":"US",
    "sg:address":"229 Tamiami Trl",
    "sg:city":"Venice",
    "sg:classifiers":[
        {
            "category":"Banks & Credit Unions",
            "subcategory":"Bank",
            "type":"Services"
        }
    ],
    "sg:phone":"+1 941 484 7181",
    "sg:postcode":"34285",
    "sg:province":"FL",
    "sg:tags":[
        "mortgage",
        "loan",
        "broker",
        "real estate"
    ],
    "wof:name":"Rock Mortgage Group Inc",
    "wof:placetype":"venue"
},
  "geometry": {"coordinates":[-82.444236,27.096396],"type":"Point"}
}