{
  "type": "Feature",
  "properties": {
    "addr:full":"4730 Co Rd 656 Webster FL 33597",
    "addr:housenumber":"4730;656",
    "addr:postcode":"33597",
    "addr:street":"Co Rd",
    "iso:country":"US",
    "sg:address":"4730 Co Rd 656",
    "sg:city":"Webster",
    "sg:classifiers":[
        {
            "category":"Retail",
            "subcategory":"Animal Services",
            "type":"Services"
        }
    ],
    "sg:phone":"+1 352 568 7719",
    "sg:postcode":"33597",
    "sg:province":"FL",
    "sg:tags":[
        "pet",
        "grooming",
        "washing"
    ],
    "wof:name":"4X4 Mobile Pet Grooming",
    "wof:placetype":"venue"
},
  "geometry": {"coordinates":[-82.18625900000001,28.58168],"type":"Point"}
}