{
  "type": "Feature",
  "properties": {
    "iso:country":"US",
    "sg:address":"17063 W Dixie Hwy",
    "sg:city":"North Miami Bch",
    "sg:classifiers":[
        {
            "category":"Wholesale",
            "subcategory":"Durable Goods & Equipment",
            "type":"Manufacturing & Wholesale Goods"
        }
    ],
    "sg:phone":"+1 305 948 4822",
    "sg:postcode":"33160",
    "sg:province":"FL",
    "sg:tags":[
        "exporter"
    ],
    "wof:name":"Executive ETCA Corp",
    "wof:placetype":"venue"
},
  "geometry": {"coordinates":[-80.153589,25.932118],"type":"Point"}
}