{
  "type": "Feature",
  "properties": {
    "iso:country":"US",
    "sg:address":"4936 Tuska Bay Ct",
    "sg:city":"Winter Springs",
    "sg:classifiers":[
        {
            "category":"Manufacturing",
            "subcategory":"Printing",
            "type":"Manufacturing & Wholesale Goods"
        }
    ],
    "sg:phone":"+1 407 699 7470",
    "sg:postcode":"32708",
    "sg:province":"FL",
    "sg:tags":[
        "book"
    ],
    "wof:name":"Publishing By Nancy Russell",
    "wof:placetype":"venue"
},
  "geometry": {"coordinates":[-81.27846099999999,28.668068],"type":"Point"}
}