{
  "type": "Feature",
  "properties": {
    "iso:country":"US",
    "sg:address":"130 Skyland Dr",
    "sg:city":"Lakeland",
    "sg:classifiers":[
        {
            "category":"Professional",
            "subcategory":"Computer Services",
            "type":"Services"
        }
    ],
    "sg:phone":"+1 863 647 5046",
    "sg:postcode":"33813",
    "sg:province":"FL",
    "sg:tags":[
        "consultant",
        "designer"
    ],
    "wof:name":"Doty Enterprises",
    "wof:placetype":"venue"
},
  "geometry": {"coordinates":[-81.95578999999999,27.994513],"type":"Point"}
}