{
  "type": "Feature",
  "properties": {
    "iso:country":"US",
    "sg:address":"5525 4th Ave",
    "sg:city":"Fort Myers",
    "sg:classifiers":[
        {
            "category":"Health Services",
            "subcategory":"Doctor",
            "type":"Services"
        }
    ],
    "sg:phone":"+1 239 277 9993",
    "sg:postcode":"33907",
    "sg:province":"FL",
    "sg:tags":[
        "medical"
    ],
    "wof:name":"Patricia K Qasem Home & Office",
    "wof:placetype":"venue"
},
  "geometry": {"coordinates":[-81.876232,26.57114],"type":"Point"}
}