{
  "type": "Feature",
  "properties": {
    "addr:full":"1229 Romney St Jacksonville FL 32211",
    "addr:housenumber":"1229",
    "addr:postcode":"32211",
    "addr:street":"Romney St",
    "iso:country":"US",
    "sg:address":"1229 Romney St",
    "sg:city":"Jacksonville",
    "sg:classifiers":[
        {
            "category":"Banks & Credit Unions",
            "subcategory":"Investment Brokerage",
            "type":"Services"
        }
    ],
    "sg:phone":"+1 904 744 2229",
    "sg:postcode":"32211",
    "sg:province":"FL",
    "wof:name":"CAL Invstmnt-North Florida",
    "wof:placetype":"venue"
},
  "geometry": {"coordinates":[-81.600098,30.332319],"type":"Point"}
}