{
  "type": "Feature",
  "properties": {
    "addr:full":"16201 SW 95th Ave Ste 214 Miami FL 33157",
    "addr:housenumber":"16201",
    "addr:postcode":"33157",
    "addr:street":"Sw 95Th Ave Ste 214",
    "iso:country":"US",
    "sg:address":"16201 SW 95th Ave Ste 214",
    "sg:city":"Miami",
    "sg:classifiers":[
        {
            "category":"Government",
            "subcategory":"Court House",
            "type":"Public Place"
        }
    ],
    "sg:phone":"+1 305 234 2208",
    "sg:postcode":"33157",
    "sg:province":"FL",
    "sg:tags":[
        "legislator"
    ],
    "wof:name":"Rep. Eb Bullard",
    "wof:placetype":"venue"
},
  "geometry": {"coordinates":[-80.34690399999999,25.618456],"type":"Point"}
}