{
  "type": "Feature",
  "properties": {
    "addr:full":"2901 Palm Beach Blvd Fort Myers FL 33916",
    "addr:housenumber":"2901",
    "addr:postcode":"33916",
    "addr:street":"Palm Beach Blvd",
    "iso:country":"US",
    "sg:address":"2901 Palm Beach Blvd",
    "sg:city":"Fort Myers",
    "sg:classifiers":[
        {
            "category":"Autos & Motor Vehicles",
            "subcategory":"Boat Sales",
            "type":"Retail Goods"
        }
    ],
    "sg:phone":"+1 239 332 0909",
    "sg:postcode":"33916",
    "sg:province":"FL",
    "sg:tags":[
        "equipment",
        "supply"
    ],
    "wof:name":"Marine Surplus",
    "wof:placetype":"venue"
},
  "geometry": {"coordinates":[-81.852639,26.653958],"type":"Point"}
}