{
  "type": "Feature",
  "properties": {
    "iso:country":"US",
    "sg:address":"1520 University Blvd W",
    "sg:city":"Jacksonville",
    "sg:classifiers":[
        {
            "category":"Food & Beverages",
            "subcategory":"Groceries & Convenience Stores",
            "type":"Retail Goods"
        }
    ],
    "sg:phone":"+1 904 448 5400",
    "sg:postcode":"32217",
    "sg:province":"FL",
    "sg:tags":[
        "grocer"
    ],
    "wof:name":"Winn-Dixie",
    "wof:placetype":"venue"
},
  "geometry": {"coordinates":[-81.64405499999999,30.260833],"type":"Point"}
}