{
  "type": "Feature",
  "properties": {
    "iso:country":"US",
    "sg:address":"4401 SW Bimini Cir N",
    "sg:city":"Palm City",
    "sg:classifiers":[
        {
            "category":"Real Estate",
            "subcategory":"Real Estate Operator",
            "type":"Services"
        }
    ],
    "sg:phone":"+1 772 215 2017",
    "sg:postcode":"34990",
    "sg:province":"FL",
    "sg:tags":[
        "property",
        "lessor"
    ],
    "wof:name":"Akambi Inc",
    "wof:placetype":"venue"
},
  "geometry": {"coordinates":[-80.310439,27.202482],"type":"Point"}
}