{
  "type": "Feature",
  "properties": {
    "addr:full":"5991 Ravenswood Rd Fort Lauderdale FL 33312",
    "addr:housenumber":"5991",
    "addr:postcode":"33312",
    "addr:street":"Ravenswood Rd",
    "iso:country":"US",
    "sg:address":"5991 Ravenswood Rd",
    "sg:city":"Fort Lauderdale",
    "sg:classifiers":[
        {
            "category":"Freight",
            "type":"Transportation"
        }
    ],
    "sg:phone":"+1 954 961 0113",
    "sg:postcode":"33312",
    "sg:province":"FL",
    "sg:tags":[
        "warehouse",
        "self",
        "storage"
    ],
    "wof:name":"Ravenswood Warehouse",
    "wof:placetype":"venue"
},
  "geometry": {"coordinates":[-80.168223,26.049492],"type":"Point"}
}