{
  "type": "Feature",
  "properties": {
    "iso:country":"US",
    "sg:address":"227 Hall St",
    "sg:city":"Wildwood",
    "sg:classifiers":[
        {
            "category":"Government",
            "subcategory":"Fire Station",
            "type":"Public Place"
        }
    ],
    "sg:phone":"+1 352 330 1342",
    "sg:postcode":"34785",
    "sg:province":"FL",
    "sg:tags":[
        "department"
    ],
    "wof:name":"Wildwood Fire Dept",
    "wof:placetype":"venue"
},
  "geometry": {"coordinates":[-82.040488,28.860884],"type":"Point"}
}