{
  "type": "Feature",
  "properties": {
    "iso:country":"US",
    "sg:address":"132 Bridle Path",
    "sg:city":"Arcadia",
    "sg:classifiers":[
        {
            "category":"Personal",
            "subcategory":"Beauty Salon",
            "type":"Services"
        }
    ],
    "sg:phone":"+1 863 491 8800",
    "sg:postcode":"34266",
    "sg:province":"FL",
    "wof:name":"Nalana Hairs & More",
    "wof:placetype":"venue"
},
  "geometry": {"coordinates":[-81.87226,27.225569],"type":"Point"}
}