{
  "type": "Feature",
  "properties": {
    "iso:country":"US",
    "sg:address":"1390 SW Bellevue Ave",
    "sg:city":"Port Saint Lucie",
    "sg:classifiers":[
        {
            "category":"Building & Trades",
            "subcategory":"Landscaping Services",
            "type":"Services"
        }
    ],
    "sg:phone":"+1 772 344 6550",
    "sg:postcode":"34953",
    "sg:province":"FL",
    "sg:tags":[
        "landscape"
    ],
    "wof:name":"Quck Kerd By Jazz",
    "wof:placetype":"venue"
},
  "geometry": {"coordinates":[-80.389742,27.292127],"type":"Point"}
}