{
  "type": "Feature",
  "properties": {
    "addr:full":"2260 Eagle Bluff Dr Valrico FL 33596",
    "addr:housenumber":"2260",
    "addr:postcode":"33596",
    "addr:street":"Eagle Bluff Dr",
    "iso:country":"US",
    "sg:address":"2260 Eagle Bluff Dr",
    "sg:city":"Valrico",
    "sg:classifiers":[
        {
            "category":"Personal",
            "type":"Services"
        }
    ],
    "sg:phone":"+1 813 571 1624",
    "sg:postcode":"33596",
    "sg:province":"FL",
    "sg:tags":[
        "assistant"
    ],
    "wof:name":"General Electric Company",
    "wof:placetype":"venue"
},
  "geometry": {"coordinates":[-82.250305,27.880609],"type":"Point"}
}