{
  "type": "Feature",
  "properties": {
    "addr:full":"7511 W Irlo Bronson Memorial Hwy Kissimmee FL 34747",
    "addr:housenumber":"7511",
    "addr:postcode":"34747",
    "addr:street":"W Irlo Bronson Memorial Hwy",
    "iso:country":"US",
    "sg:address":"7511 W Irlo Bronson Memorial Hwy",
    "sg:city":"Kissimmee",
    "sg:classifiers":[
        {
            "category":"Professional",
            "subcategory":"Advertising",
            "type":"Services"
        }
    ],
    "sg:phone":"+1 407 396 2067",
    "sg:postcode":"34747",
    "sg:province":"FL",
    "sg:tags":[
        "marketing",
        "program"
    ],
    "wof:name":"Tempus Marketing",
    "wof:placetype":"venue"
},
  "geometry": {"coordinates":[-81.588722,28.33359],"type":"Point"}
}