{
  "type": "Feature",
  "properties": {
    "iso:country":"US",
    "sg:address":"397 E Altamonte Dr",
    "sg:city":"Altamonte Spgs",
    "sg:classifiers":[
        {
            "category":"Home & Garden",
            "subcategory":"Furniture",
            "type":"Retail Goods"
        }
    ],
    "sg:phone":"+1 407 265 1414",
    "sg:postcode":"32701",
    "sg:province":"FL",
    "sg:website":"www.theleathergalleries.com",
    "wof:name":"Classic Leather Galleries Inc",
    "wof:placetype":"venue"
},
  "geometry": {"coordinates":[-81.378236,28.66381],"type":"Point"}
}