{
  "type": "Feature",
  "properties": {
    "addr:full":"1501 22nd St S St Petersburg FL 33712",
    "addr:housenumber":"1501",
    "addr:postcode":"33712",
    "addr:street":"22Nd St S",
    "iso:country":"US",
    "sg:address":"1501 22nd St S",
    "sg:city":"St Petersburg",
    "sg:classifiers":[
        {
            "category":"Personal",
            "subcategory":"Beauty Salon",
            "type":"Services"
        }
    ],
    "sg:phone":"+1 727 321 0111",
    "sg:postcode":"33712",
    "sg:province":"FL",
    "wof:name":"Golden Shears Beauty Salon",
    "wof:placetype":"venue"
},
  "geometry": {"coordinates":[-82.662961,27.755343],"type":"Point"}
}