{
  "type": "Feature",
  "properties": {
    "addr:full":"20260 NE 25th Ave Miami FL 33180",
    "addr:housenumber":"20260",
    "addr:postcode":"33180",
    "addr:street":"Ne 25Th Ave",
    "iso:country":"US",
    "sg:address":"20260 NE 25th Ave",
    "sg:city":"Miami",
    "sg:classifiers":[
        {
            "category":"Wholesale",
            "subcategory":"Durable Goods & Equipment",
            "type":"Manufacturing & Wholesale Goods"
        }
    ],
    "sg:phone":"+1 305 682 8118",
    "sg:postcode":"33180",
    "sg:province":"FL",
    "wof:name":"Buncher Wholesale Company",
    "wof:placetype":"venue"
},
  "geometry": {"coordinates":[-80.15196899999999,25.962968],"type":"Point"}
}