{
  "type": "Feature",
  "properties": {
    "iso:country":"US",
    "sg:address":"1522 3rd St SW",
    "sg:city":"Winter Haven",
    "sg:classifiers":[
        {
            "category":"Shopping",
            "subcategory":"Crafts & Fabrics",
            "type":"Retail Goods"
        }
    ],
    "sg:phone":"+1 863 299 1552",
    "sg:postcode":"33880",
    "sg:province":"FL",
    "sg:tags":[
        "sewing"
    ],
    "wof:name":"Jo-Ann Fabrics & Crafts",
    "wof:placetype":"venue"
},
  "geometry": {"coordinates":[-81.73075799999999,28.007849],"type":"Point"}
}