{
  "type": "Feature",
  "properties": {
    "iso:country":"US",
    "sg:address":"8955 SW 107th Ave",
    "sg:city":"Miami",
    "sg:classifiers":[
        {
            "category":"Personal",
            "subcategory":"Beauty Salon",
            "type":"Services"
        }
    ],
    "sg:phone":"+1 305 279 2224",
    "sg:postcode":"33176",
    "sg:province":"FL",
    "sg:tags":[
        "hair"
    ],
    "sg:website":"www.grandehairsalon.com",
    "wof:name":"Grande Hair Salon",
    "wof:placetype":"venue"
},
  "geometry": {"coordinates":[-80.367104,25.683901],"type":"Point"}
}