{
  "type": "Feature",
  "properties": {
    "iso:country":"US",
    "sg:address":"4566 Heritage Oak Dr",
    "sg:city":"Orlando",
    "sg:classifiers":[
        {
            "category":"Shopping",
            "subcategory":"Hobbies, Toys, & Games",
            "type":"Retail Goods"
        }
    ],
    "sg:phone":"+1 407 292 3770",
    "sg:postcode":"32808",
    "sg:province":"FL",
    "sg:tags":[
        "basket"
    ],
    "wof:name":"Fruits Of The Spirit",
    "wof:placetype":"venue"
},
  "geometry": {"coordinates":[-81.437622,28.606408],"type":"Point"}
}