{
  "type": "Feature",
  "properties": {
    "addr:full":"1885 S Lehigh Dr Deltona FL 32738",
    "addr:housenumber":"1885",
    "addr:postcode":"32738",
    "addr:street":"S Lehigh Dr",
    "iso:country":"US",
    "sg:address":"1885 S Lehigh Dr",
    "sg:city":"Deltona",
    "sg:classifiers":[
        {
            "category":"Manufacturing",
            "subcategory":"Petroleum Products",
            "type":"Manufacturing & Wholesale Goods"
        }
    ],
    "sg:phone":"+1 386 574 0811",
    "sg:postcode":"32738",
    "sg:province":"FL",
    "sg:tags":[
        "contract"
    ],
    "wof:name":"M J Boturla Industries Inc",
    "wof:placetype":"venue"
},
  "geometry": {"coordinates":[-81.218718,28.875253],"type":"Point"}
}