{
  "type": "Feature",
  "properties": {
    "iso:country":"US",
    "sg:address":"3025 S Adams St",
    "sg:city":"Tallahassee",
    "sg:classifiers":[
        {
            "category":"Real Estate",
            "subcategory":"Real Estate Operator",
            "type":"Services"
        }
    ],
    "sg:phone":"+1 850 878 0300",
    "sg:postcode":"32301",
    "sg:province":"FL",
    "sg:tags":[
        "apartment"
    ],
    "wof:name":"University Courtyard Apartment",
    "wof:placetype":"venue"
},
  "geometry": {"coordinates":[-84.283709,30.4055],"type":"Point"}
}