{
  "type": "Feature",
  "properties": {
    "iso:country":"US",
    "sg:address":"545 Oaks Ln",
    "sg:city":"Pompano Beach",
    "sg:classifiers":[
        {
            "category":"Home & Garden",
            "subcategory":"Carpets & Floor Coverings",
            "type":"Retail Goods"
        }
    ],
    "sg:phone":"+1 954 975 4629",
    "sg:postcode":"33069",
    "sg:province":"FL",
    "sg:tags":[
        "dealer",
        "rug"
    ],
    "sg:website":"www.tenaska.com",
    "wof:name":"Resat Komec",
    "wof:placetype":"venue"
},
  "geometry": {"coordinates":[-80.172713,26.223539],"type":"Point"}
}