{
  "type": "Feature",
  "properties": {
    "iso:country":"US",
    "sg:address":"229 E 18th St",
    "sg:city":"Hialeah",
    "sg:classifiers":[
        {
            "category":"Sports & Exercise",
            "subcategory":"Swimming Pool",
            "type":"Entertainment"
        }
    ],
    "sg:phone":"+1 305 884 3624",
    "sg:postcode":"33010",
    "sg:province":"FL",
    "sg:tags":[
        "repair"
    ],
    "wof:name":"Gonzales & Son Pool Plast",
    "wof:placetype":"venue"
},
  "geometry": {"coordinates":[-80.27735,25.838237],"type":"Point"}
}