{
  "type": "Feature",
  "properties": {
    "iso:country":"US",
    "sg:address":"1200 S John Young Pkwy",
    "sg:city":"Kissimmee",
    "sg:classifiers":[
        {
            "category":"Autos & Motor Vehicles",
            "subcategory":"Auto Supplies",
            "type":"Retail Goods"
        }
    ],
    "sg:phone":"+1 407 846 1962",
    "sg:postcode":"34741",
    "sg:province":"FL",
    "sg:tags":[
        "automotive",
        "general",
        "tire",
        "provides",
        "repair"
    ],
    "wof:name":"Clay Jeff & Sons Tires",
    "wof:placetype":"venue"
},
  "geometry": {"coordinates":[-81.416831,28.278679],"type":"Point"}
}