{
  "type": "Feature",
  "properties": {
    "iso:country":"US",
    "sg:address":"12461 SW 130th St",
    "sg:city":"Miami",
    "sg:classifiers":[
        {
            "category":"Manufacturing",
            "subcategory":"Signs",
            "type":"Manufacturing & Wholesale Goods"
        }
    ],
    "sg:phone":"+1 305 752 5265",
    "sg:postcode":"33186",
    "sg:province":"FL",
    "sg:tags":[
        "advertising",
        "specialty"
    ],
    "wof:name":"Signs Up Now Inc",
    "wof:placetype":"venue"
},
  "geometry": {"coordinates":[-80.395905,25.646932],"type":"Point"}
}