{
  "type": "Feature",
  "properties": {
    "addr:full":"1851 Talpeco Rd Tallahassee FL 32303",
    "addr:housenumber":"1851",
    "addr:postcode":"32303",
    "addr:street":"Talpeco Rd",
    "iso:country":"US",
    "sg:address":"1851 Talpeco Rd",
    "sg:city":"Tallahassee",
    "sg:classifiers":[
        {
            "category":"Health Services",
            "subcategory":"Health Practitioner",
            "type":"Services"
        }
    ],
    "sg:phone":"+1 850 562 1001",
    "sg:postcode":"32303",
    "sg:province":"FL",
    "sg:tags":[
        "nutritionist"
    ],
    "wof:name":"Nutrition & Health Assocs",
    "wof:placetype":"venue"
},
  "geometry": {"coordinates":[-84.32422699999999,30.492778],"type":"Point"}
}