{
  "type": "Feature",
  "properties": {
    "addr:full":"25452 Shore Dr Punta Gorda FL 33950",
    "addr:housenumber":"25452",
    "addr:postcode":"33950",
    "addr:street":"Shore Dr",
    "iso:country":"US",
    "sg:address":"25452 Shore Dr",
    "sg:city":"Punta Gorda",
    "sg:classifiers":[
        {
            "category":"Real Estate",
            "subcategory":"Real Estate Operator",
            "type":"Services"
        }
    ],
    "sg:phone":"+1 941 637 8716",
    "sg:postcode":"33950",
    "sg:province":"FL",
    "sg:tags":[
        "apartment"
    ],
    "wof:name":"Dickson's Duplexes",
    "wof:placetype":"venue"
},
  "geometry": {"coordinates":[-82.028858,26.948458],"type":"Point"}
}