{
  "type": "Feature",
  "properties": {
    "iso:country":"US",
    "sg:address":"570 Sandy Hook Rd",
    "sg:city":"Palm Harbor",
    "sg:classifiers":[
        {
            "category":"Utilities",
            "subcategory":"Refuse",
            "type":"Services"
        }
    ],
    "sg:phone":"+1 727 785 3689",
    "sg:postcode":"34683",
    "sg:province":"FL",
    "sg:tags":[
        "system"
    ],
    "wof:name":"Roberto Stephanie Fowler Jean",
    "wof:placetype":"venue"
},
  "geometry": {"coordinates":[-82.755298,28.083543],"type":"Point"}
}