{
  "type": "Feature",
  "properties": {
    "iso:country":"US",
    "sg:address":"2698 N University Dr",
    "sg:city":"Sunrise",
    "sg:classifiers":[
        {
            "category":"Shopping",
            "subcategory":"Bicycles & Sporting Goods",
            "type":"Retail Goods"
        }
    ],
    "sg:phone":"+1 954 742 3015",
    "sg:postcode":"33322",
    "sg:province":"FL",
    "sg:tags":[
        "repair",
        "security",
        "system",
        "rack"
    ],
    "wof:name":"Johnny's Schwinn Cycle",
    "wof:placetype":"venue"
},
  "geometry": {"coordinates":[-80.25715599999999,26.15753],"type":"Point"}
}