{
  "type": "Feature",
  "properties": {
    "addr:full":"32 Emerson Dr Palm Coast FL 32164",
    "addr:housenumber":"32",
    "addr:postcode":"32164",
    "addr:street":"Emerson Dr",
    "iso:country":"US",
    "sg:address":"32 Emerson Dr",
    "sg:city":"Palm Coast",
    "sg:classifiers":[
        {
            "category":"Banks & Credit Unions",
            "subcategory":"Bank",
            "type":"Services"
        }
    ],
    "sg:phone":"+1 386 586 1423",
    "sg:postcode":"32164",
    "sg:province":"FL",
    "sg:tags":[
        "loan",
        "real estate"
    ],
    "wof:name":"MFC Mortgage",
    "wof:placetype":"venue"
},
  "geometry": {"coordinates":[-81.22148900000001,29.491003],"type":"Point"}
}