{
  "type": "Feature",
  "properties": {
    "addr:full":"1160 Nassau St Delray Beach FL 33483",
    "addr:housenumber":"1160",
    "addr:postcode":"33483",
    "addr:street":"Nassau St",
    "iso:country":"US",
    "sg:address":"1160 Nassau St",
    "sg:city":"Delray Beach",
    "sg:classifiers":[
        {
            "category":"Professional",
            "type":"Services"
        }
    ],
    "sg:phone":"+1 561 272 1602",
    "sg:postcode":"33483",
    "sg:province":"FL",
    "wof:name":"Aegis Netware Inc",
    "wof:placetype":"venue"
},
  "geometry": {"coordinates":[-80.05990300000001,26.456736],"type":"Point"}
}