{
  "type": "Feature",
  "properties": {
    "addr:full":"1251 E Sample Rd Pompano Beach FL 33064",
    "addr:housenumber":"1251",
    "addr:postcode":"33064",
    "addr:street":"E Sample Rd",
    "iso:country":"US",
    "sg:address":"1251 E Sample Rd",
    "sg:city":"Pompano Beach",
    "sg:classifiers":[
        {
            "category":"Real Estate",
            "subcategory":"Real Estate Agent",
            "type":"Services"
        }
    ],
    "sg:phone":"+1 954 748 5918",
    "sg:postcode":"33064",
    "sg:province":"FL",
    "wof:name":"Canaan International Rlty Inc",
    "wof:placetype":"venue"
},
  "geometry": {"coordinates":[-80.107101,26.275509],"type":"Point"}
}