{
  "type": "Feature",
  "properties": {
    "iso:country":"US",
    "sg:address":"3820 Ron Rd",
    "sg:city":"Green Cove Springs",
    "sg:classifiers":[
        {
            "category":"Home & Garden",
            "subcategory":"Building Materials",
            "type":"Retail Goods"
        }
    ],
    "sg:phone":"+1 904 529 8109",
    "sg:postcode":"32043",
    "sg:province":"FL",
    "wof:name":"J M Davis LLC",
    "wof:placetype":"venue"
},
  "geometry": {"coordinates":[-81.751198,29.987315],"type":"Point"}
}