{
  "type": "Feature",
  "properties": {
    "addr:full":"1369 Pilgrim Rd Spring Hill FL 34606",
    "addr:housenumber":"1369",
    "addr:postcode":"34606",
    "addr:street":"Pilgrim Rd",
    "iso:country":"US",
    "sg:address":"1369 Pilgrim Rd",
    "sg:city":"Spring Hill",
    "sg:classifiers":[
        {
            "category":"Manufacturing",
            "subcategory":"Furniture",
            "type":"Manufacturing & Wholesale Goods"
        },
        {
            "category":"Wholesale",
            "subcategory":"Furniture",
            "type":"Manufacturing & Wholesale Goods"
        }
    ],
    "sg:phone":"+1 352 688 4651",
    "sg:postcode":"34606",
    "sg:province":"FL",
    "sg:tags":[
        "household"
    ],
    "wof:name":"Park Avenue Lucite",
    "wof:placetype":"venue"
},
  "geometry": {"coordinates":[-82.60187500000001,28.454621],"type":"Point"}
}