{
  "type": "Feature",
  "properties": {
    "addr:full":"8768 N River Rd Tampa FL 33635",
    "addr:housenumber":"8768",
    "addr:postcode":"33635",
    "addr:street":"N River Rd",
    "iso:country":"US",
    "sg:address":"8768 N River Rd",
    "sg:city":"Tampa",
    "sg:classifiers":[
        {
            "category":"Building & Trades",
            "subcategory":"Landscaping Services",
            "type":"Services"
        }
    ],
    "sg:phone":"+1 813 818 8600",
    "sg:postcode":"33635",
    "sg:province":"FL",
    "sg:tags":[
        "sod",
        "sodding"
    ],
    "wof:name":"Felix's Sod Delivery",
    "wof:placetype":"venue"
},
  "geometry": {"coordinates":[-82.63062600000001,28.033364],"type":"Point"}
}