{
  "type": "Feature",
  "properties": {
    "addr:full":"2655 Northbrooke Dr Naples FL 34119",
    "addr:housenumber":"2655",
    "addr:postcode":"34119",
    "addr:street":"Northbrooke Dr",
    "iso:country":"US",
    "sg:address":"2655 Northbrooke Dr",
    "sg:city":"Naples",
    "sg:classifiers":[
        {
            "category":"Professional",
            "subcategory":"Management & Consulting",
            "type":"Services"
        }
    ],
    "sg:phone":"+1 239 254 9440",
    "sg:postcode":"34119",
    "sg:province":"FL",
    "sg:tags":[
        "consultant",
        "business"
    ],
    "wof:name":"US Service Corps-Retired Execs",
    "wof:placetype":"venue"
},
  "geometry": {"coordinates":[-81.73899,26.284272],"type":"Point"}
}