{
  "type": "Feature",
  "properties": {
    "addr:full":"4175 NE 301st Blvd Okeechobee FL 34972",
    "addr:housenumber":"4175",
    "addr:postcode":"34972",
    "addr:street":"Ne 301St Blvd",
    "iso:country":"US",
    "sg:address":"4175 NE 301st Blvd",
    "sg:city":"Okeechobee",
    "sg:classifiers":[
        {
            "category":"Professional",
            "subcategory":"Art Services",
            "type":"Services"
        }
    ],
    "sg:phone":"+1 941 763 7277",
    "sg:postcode":"34972",
    "sg:province":"FL",
    "sg:tags":[
        "taxidermist"
    ],
    "wof:name":"George's Taxidermist",
    "wof:placetype":"venue"
},
  "geometry": {"coordinates":[-80.78105100000001,27.527353],"type":"Point"}
}