{
  "type": "Feature",
  "properties": {
    "addr:full":"10750 Gulf Blvd Treasure Island FL 33706",
    "addr:housenumber":"10750",
    "addr:postcode":"33706",
    "addr:street":"Gulf Blvd",
    "iso:country":"US",
    "sg:address":"10750 Gulf Blvd",
    "sg:city":"Treasure Island",
    "sg:classifiers":[
        {
            "category":"Travel",
            "subcategory":"Hotels & Motels",
            "type":"Entertainment"
        }
    ],
    "sg:phone":"+1 727 367 2704",
    "sg:postcode":"33706",
    "sg:province":"FL",
    "sg:website":"www.seacastlesuites.com",
    "wof:name":"Best Western Inn",
    "wof:placetype":"venue"
},
  "geometry": {"coordinates":[-82.769655,27.769446],"type":"Point"}
}