{
  "type": "Feature",
  "properties": {
    "addr:full":"1000 S Federal Hwy Fort Lauderdale FL 33316",
    "addr:housenumber":"1000",
    "addr:postcode":"33316",
    "addr:street":"S Federal Hwy",
    "iso:country":"US",
    "sg:address":"1000 S Federal Hwy",
    "sg:city":"Fort Lauderdale",
    "sg:classifiers":[
        {
            "category":"Professional",
            "subcategory":"Lawyer & Legal Services",
            "type":"Services"
        }
    ],
    "sg:phone":"+1 954 764 8225",
    "sg:postcode":"33316",
    "sg:province":"FL",
    "wof:name":"Itzler Peter PA",
    "wof:placetype":"venue"
},
  "geometry": {"coordinates":[-80.136889,26.11086],"type":"Point"}
}