{
  "type": "Feature",
  "properties": {
    "iso:country":"US",
    "sg:address":"4075 13th St",
    "sg:city":"St Cloud",
    "sg:classifiers":[
        {
            "category":"Real Estate",
            "subcategory":"Real Estate Agent",
            "type":"Services"
        }
    ],
    "sg:phone":"+1 407 892 0146",
    "sg:postcode":"34769",
    "sg:province":"FL",
    "wof:name":"Cavendish Property Management",
    "wof:placetype":"venue"
},
  "geometry": {"coordinates":[-81.31335799999999,28.251148],"type":"Point"}
}