{
  "type": "Feature",
  "properties": {
    "addr:full":"270 H L Sudduth Cir Panama City FL 32404",
    "addr:housenumber":"270",
    "addr:postcode":"32404",
    "addr:street":"H L Sudduth Cir",
    "iso:country":"US",
    "sg:address":"270 H L Sudduth Cir",
    "sg:city":"Panama City",
    "sg:classifiers":[
        {
            "category":"Autos & Motor Vehicles",
            "subcategory":"Automobile Sales",
            "type":"Retail Goods"
        },
        {
            "category":"Airport",
            "type":"Transportation"
        }
    ],
    "sg:phone":"+1 850 871 3621",
    "sg:postcode":"32404",
    "sg:province":"FL",
    "sg:tags":[
        "equipment",
        "aircraft",
        "parts",
        "supply"
    ],
    "wof:name":"Experimental Products Inc",
    "wof:placetype":"venue"
},
  "geometry": {"coordinates":[-85.58317700000001,30.137315],"type":"Point"}
}