{
  "type": "Feature",
  "properties": {
    "addr:full":"5354 US Hwy 98 Lakeland FL 33809",
    "addr:housenumber":"5354",
    "addr:postcode":"33809",
    "addr:street":"Us Hwy 98",
    "iso:country":"US",
    "sg:address":"5354 US Hwy 98",
    "sg:city":"Lakeland",
    "sg:classifiers":[
        {
            "category":"Real Estate",
            "subcategory":"Real Estate Agent",
            "type":"Services"
        }
    ],
    "sg:phone":"+1 863 858 1434",
    "sg:postcode":"33809",
    "sg:province":"FL",
    "wof:name":"Better Homes and Gardens",
    "wof:placetype":"venue"
},
  "geometry": {"coordinates":[-81.979517,28.169415],"type":"Point"}
}