{
  "type": "Feature",
  "properties": {
    "iso:country":"US",
    "sg:address":"15321 S Dixie Hwy Ste 302",
    "sg:city":"Miami",
    "sg:classifiers":[
        {
            "category":"Professional",
            "subcategory":"Lawyer & Legal Services",
            "type":"Services"
        }
    ],
    "sg:phone":"+1 305 255 3654",
    "sg:postcode":"33157",
    "sg:province":"FL",
    "sg:tags":[
        "divorce",
        "law",
        "family"
    ],
    "wof:name":"Law Offices of C Y Howard - CLOSED",
    "wof:placetype":"venue"
},
  "geometry": {"coordinates":[-80.34139999999999,25.627899],"type":"Point"}
}