{
  "type": "Feature",
  "properties": {
    "iso:country":"US",
    "sg:address":"10616 Cedar Forest Cir",
    "sg:city":"Clermont",
    "sg:classifiers":[
        {
            "category":"Building & Trades",
            "subcategory":"Construction",
            "type":"Services"
        }
    ],
    "sg:phone":"+1 352 988 7707",
    "sg:postcode":"34711",
    "sg:province":"FL",
    "sg:tags":[
        "roofing",
        "consultant"
    ],
    "wof:name":"Michael Arnold And Associates",
    "wof:placetype":"venue"
},
  "geometry": {"coordinates":[-81.784813,28.502308],"type":"Point"}
}