{
  "type": "Feature",
  "properties": {
    "addr:full":"3630 N 56th Ave Apt 314 Hollywood FL 33021",
    "addr:housenumber":"3630;314",
    "addr:postcode":"33021",
    "addr:street":"N 56Th Ave Apt",
    "iso:country":"US",
    "sg:address":"3630 N 56th Ave Apt 314",
    "sg:city":"Hollywood",
    "sg:classifiers":[
        {
            "category":"Professional",
            "subcategory":"Business Services",
            "type":"Services"
        }
    ],
    "sg:phone":"+1 954 983 4559",
    "sg:postcode":"33021",
    "sg:province":"FL",
    "sg:tags":[
        "consultant",
        "coach"
    ],
    "wof:name":"Latin American Consultants Inc",
    "wof:placetype":"venue"
},
  "geometry": {"coordinates":[-80.200693,26.042941],"type":"Point"}
}