{
  "type": "Feature",
  "properties": {
    "addr:full":"7331 NW 47th Pl Lauderhill FL 33319",
    "addr:housenumber":"7331",
    "addr:postcode":"33319",
    "addr:street":"Nw 47Th Pl",
    "iso:country":"US",
    "sg:address":"7331 NW 47th Pl",
    "sg:city":"Lauderhill",
    "sg:classifiers":[
        {
            "category":"Wholesale",
            "subcategory":"Dairy",
            "type":"Manufacturing & Wholesale Goods"
        }
    ],
    "sg:phone":"+1 954 572 7438",
    "sg:postcode":"33319",
    "sg:province":"FL",
    "sg:tags":[
        "frozen",
        "dessert",
        "ice",
        "cream"
    ],
    "wof:name":"Beverly Brinson Ice Cream",
    "wof:placetype":"venue"
},
  "geometry": {"coordinates":[-80.247359,26.183514],"type":"Point"}
}