{
  "type": "Feature",
  "properties": {
    "addr:full":"4891 NW 9th Ave Oakland Park FL 33309",
    "addr:housenumber":"4891",
    "addr:postcode":"33309",
    "addr:street":"Nw 9Th Ave",
    "iso:country":"US",
    "sg:address":"4891 NW 9th Ave",
    "sg:city":"Oakland Park",
    "sg:classifiers":[
        {
            "category":"Food & Beverages",
            "subcategory":"Groceries & Convenience Stores",
            "type":"Retail Goods"
        }
    ],
    "sg:phone":"+1 954 491 5410",
    "sg:postcode":"33309",
    "sg:province":"FL",
    "wof:name":"Advice Business Practice",
    "wof:placetype":"venue"
},
  "geometry": {"coordinates":[-80.155162,26.186023],"type":"Point"}
}