{
  "type": "Feature",
  "properties": {
    "iso:country":"US",
    "sg:address":"1634 NE 26th St",
    "sg:city":"Ocala",
    "sg:classifiers":[
        {
            "category":"Retail",
            "subcategory":"Auto Repair",
            "type":"Services"
        }
    ],
    "sg:phone":"+1 352 622 3321",
    "sg:postcode":"34470",
    "sg:province":"FL",
    "sg:tags":[
        "repairing",
        "automobile"
    ],
    "wof:name":"Nix Brothers Well & Pump Svc",
    "wof:placetype":"venue"
},
  "geometry": {"coordinates":[-82.11647600000001,29.2133],"type":"Point"}
}