{
  "type": "Feature",
  "properties": {
    "iso:country":"US",
    "sg:address":"6800 SE Twin Oaks Cir",
    "sg:city":"Stuart",
    "sg:classifiers":[
        {
            "category":"Professional",
            "subcategory":"Computer Services",
            "type":"Services"
        }
    ],
    "sg:phone":"+1 772 781 4446",
    "sg:postcode":"34997",
    "sg:province":"FL",
    "sg:tags":[
        "repair"
    ],
    "wof:name":"Tek Medics",
    "wof:placetype":"venue"
},
  "geometry": {"coordinates":[-80.217406,27.122401],"type":"Point"}
}