{
  "type": "Feature",
  "properties": {
    "iso:country":"US",
    "sg:address":"3622 NE 2nd Ave",
    "sg:city":"Miami",
    "sg:classifiers":[
        {
            "category":"Restaurant",
            "type":"Food & Drink"
        }
    ],
    "sg:phone":"+1 305 576 5755",
    "sg:postcode":"33137",
    "sg:province":"FL",
    "wof:name":"French Box Cafe",
    "wof:placetype":"venue"
},
  "geometry": {"coordinates":[-80.191362,25.811329],"type":"Point"}
}