{
  "type": "Feature",
  "properties": {
    "addr:full":"3328 NE Sugarhill Ave Jensen Beach FL 34957",
    "addr:housenumber":"3328",
    "addr:postcode":"34957",
    "addr:street":"Ne Sugarhill Ave",
    "iso:country":"US",
    "sg:address":"3328 NE Sugarhill Ave",
    "sg:city":"Jensen Beach",
    "sg:classifiers":[
        {
            "category":"Professional",
            "subcategory":"Computer Services",
            "type":"Services"
        }
    ],
    "sg:phone":"+1 772 225 1733",
    "sg:postcode":"34957",
    "sg:province":"FL",
    "sg:tags":[
        "consultant",
        "designer"
    ],
    "wof:name":"Total Tec Systems Inc",
    "wof:placetype":"venue"
},
  "geometry": {"coordinates":[-80.23894,27.248335],"type":"Point"}
}