{
  "type": "Feature",
  "properties": {
    "addr:full":"1585 Lake Ave Clermont FL 34711",
    "addr:housenumber":"1585",
    "addr:postcode":"34711",
    "addr:street":"Lake Ave",
    "iso:country":"US",
    "sg:address":"1585 Lake Ave",
    "sg:city":"Clermont",
    "sg:classifiers":[
        {
            "category":"Shopping",
            "subcategory":"Gifts & Souvenirs",
            "type":"Retail Goods"
        }
    ],
    "sg:phone":"+1 352 394 4583",
    "sg:postcode":"34711",
    "sg:province":"FL",
    "wof:name":"Gifts 2 Love Co Inc",
    "wof:placetype":"venue"
},
  "geometry": {"coordinates":[-81.76427700000001,28.547359],"type":"Point"}
}