{
  "type": "Feature",
  "properties": {
    "iso:country":"US",
    "sg:address":"2090 J and C Blvd",
    "sg:city":"Naples",
    "sg:classifiers":[
        {
            "category":"Building & Trades",
            "subcategory":"Electrical",
            "type":"Services"
        }
    ],
    "sg:phone":"+1 239 594 2455",
    "sg:postcode":"34109",
    "sg:province":"FL",
    "sg:tags":[
        "electric",
        "contractor"
    ],
    "wof:name":"Ideal Electric",
    "wof:placetype":"venue"
},
  "geometry": {"coordinates":[-81.78152300000001,26.223653],"type":"Point"}
}