{
  "type": "Feature",
  "properties": {
    "iso:country":"US",
    "sg:address":"2916 Louise St",
    "sg:city":"Miami",
    "sg:classifiers":[
        {
            "category":"Shopping",
            "subcategory":"Used Merchandise",
            "type":"Retail Goods"
        }
    ],
    "sg:phone":"+1 305 444 0065",
    "sg:postcode":"33133",
    "sg:province":"FL",
    "wof:name":"Longobardis Antiques",
    "wof:placetype":"venue"
},
  "geometry": {"coordinates":[-80.239452,25.736458],"type":"Point"}
}