{
  "type": "Feature",
  "properties": {
    "addr:full":"1264 Waterview Ln Fort Lauderdale FL 33326",
    "addr:housenumber":"1264",
    "addr:postcode":"33326",
    "addr:street":"Waterview Ln",
    "iso:country":"US",
    "sg:address":"1264 Waterview Ln",
    "sg:city":"Fort Lauderdale",
    "sg:classifiers":[
        {
            "category":"Professional",
            "subcategory":"Accounting & Tax Preparation",
            "type":"Services"
        }
    ],
    "sg:phone":"+1 954 385 1535",
    "sg:postcode":"33326",
    "sg:province":"FL",
    "wof:name":"Marlene B Barbe CPA P A",
    "wof:placetype":"venue"
},
  "geometry": {"coordinates":[-80.387872,26.107724],"type":"Point"}
}