{
  "type": "Feature",
  "properties": {
    "iso:country":"US",
    "sg:address":"4601 Dardanelle Dr",
    "sg:city":"Orlando",
    "sg:classifiers":[
        {
            "category":"Wholesale",
            "subcategory":"Auto Parts",
            "type":"Manufacturing & Wholesale Goods"
        }
    ],
    "sg:phone":"+1 407 647 5510",
    "sg:postcode":"32808",
    "sg:province":"FL",
    "sg:tags":[
        "mfg",
        "motor",
        "vehicle"
    ],
    "wof:name":"Lake Shore Radiator & Spec",
    "wof:placetype":"venue"
},
  "geometry": {"coordinates":[-81.44194299999999,28.58001],"type":"Point"}
}