{
  "type": "Feature",
  "properties": {
    "addr:full":"582 Riviera Dr Tampa FL 33606",
    "addr:housenumber":"582",
    "addr:postcode":"33606",
    "addr:street":"Riviera Dr",
    "iso:country":"US",
    "sg:address":"582 Riviera Dr",
    "sg:city":"Tampa",
    "sg:classifiers":[
        {
            "category":"Health Services",
            "subcategory":"Doctor",
            "type":"Services"
        }
    ],
    "sg:phone":"+1 813 258 0907",
    "sg:postcode":"33606",
    "sg:province":"FL",
    "sg:tags":[
        "physician",
        "surgeon"
    ],
    "wof:name":"Lutz H Schlicke MD",
    "wof:placetype":"venue"
},
  "geometry": {"coordinates":[-82.461022,27.91219],"type":"Point"}
}