{
  "type": "Feature",
  "properties": {
    "addr:full":"16400 NW 15th Ave Miami FL 33169",
    "addr:housenumber":"16400",
    "addr:postcode":"33169",
    "addr:street":"Nw 15Th Ave",
    "iso:country":"US",
    "sg:address":"16400 NW 15th Ave",
    "sg:city":"Miami",
    "sg:classifiers":[
        {
            "category":"Wholesale",
            "subcategory":"Chemicals & Plastics",
            "type":"Manufacturing & Wholesale Goods"
        }
    ],
    "sg:phone":"+1 305 622 9446",
    "sg:postcode":"33169",
    "sg:province":"FL",
    "sg:tags":[
        "product",
        "export"
    ],
    "wof:name":"Global Pac",
    "wof:placetype":"venue"
},
  "geometry": {"coordinates":[-80.22516299999999,25.923284],"type":"Point"}
}