{
  "type": "Feature",
  "properties": {
    "iso:country":"US",
    "sg:address":"1948 Harrison St",
    "sg:city":"Hollywood",
    "sg:classifiers":[
        {
            "category":"Real Estate",
            "subcategory":"Real Estate Services",
            "type":"Services"
        },
        {
            "category":"Real Estate",
            "subcategory":"Real Estate Agent",
            "type":"Services"
        },
        {
            "category":"Professional",
            "type":"Services"
        }
    ],
    "sg:phone":"+1 954 668 9056",
    "sg:postcode":"33020",
    "sg:province":"FL",
    "sg:tags":[
        "information",
        "relocation",
        "broker",
        "buyer",
        "referral",
        "rental"
    ],
    "sg:website":"http://www.Fort-Lauderdale-Beach-Real-Estate.com/",
    "wof:name":"Susan Weaver Realtor",
    "wof:placetype":"venue"
},
  "geometry": {"coordinates":[-80.14595300000001,26.010491],"type":"Point"}
}