{
  "type": "Feature",
  "properties": {
    "addr:full":"408 2nd St Indian Rocks Beach FL 33785",
    "addr:housenumber":"408",
    "addr:postcode":"33785",
    "addr:street":"2Nd St",
    "iso:country":"US",
    "sg:address":"408 2nd St",
    "sg:city":"Indian Rocks Beach",
    "sg:classifiers":[
        {
            "category":"Coffee & Tea",
            "type":"Food & Drink"
        },
        {
            "category":"Cafe",
            "type":"Food & Drink"
        }
    ],
    "sg:menulink":"http://www.allmenus.com/fl/clearwater/38002-konorama-cafe/menu/",
    "sg:phone":"+1 727 596 6080",
    "sg:postcode":"33785",
    "sg:province":"FL",
    "sg:tags":[
        "american"
    ],
    "wof:name":"Konorama Cafe",
    "wof:placetype":"venue"
},
  "geometry": {"coordinates":[-82.848989,27.882747],"type":"Point"}
}