{
  "type": "Feature",
  "properties": {
    "iso:country":"US",
    "sg:address":"16495 69th St N",
    "sg:city":"Loxahatchee",
    "sg:classifiers":[
        {
            "category":"Shopping",
            "subcategory":"Jewelry",
            "type":"Retail Goods"
        }
    ],
    "sg:phone":"+1 561 791 2010",
    "sg:postcode":"33470",
    "sg:province":"FL",
    "wof:name":"Rt S Gems & Jewelry",
    "wof:placetype":"venue"
},
  "geometry": {"coordinates":[-80.30312000000001,26.777956],"type":"Point"}
}