{
  "type": "Feature",
  "properties": {
    "iso:country":"US",
    "sg:address":"11401 NW 12th St Suite 384",
    "sg:city":"Miami",
    "sg:classifiers":[
        {
            "category":"Wholesale",
            "subcategory":"Electrical",
            "type":"Manufacturing & Wholesale Goods"
        },
        {
            "category":"Shopping",
            "subcategory":"Computers & Home Electronics",
            "type":"Retail Goods"
        },
        {
            "category":"Communications",
            "type":"Services"
        }
    ],
    "sg:phone":"+1 786 623 4136",
    "sg:postcode":"33172",
    "sg:province":"FL",
    "sg:tags":[
        "sound",
        "television",
        "theater",
        "equipment-wholesale",
        "stereo",
        "system",
        "high",
        "equipment",
        "stereophonic",
        "video",
        "equipment-dealers",
        "radio",
        "fidelity",
        "audio",
        "consumer",
        "store",
        "manufacturer"
    ],
    "sg:website":"http://miami.citysearch.com/profile/external/46282566/miami_fl/bose.html?publisher=yellowpages&reference_id=1&placement=ypwebsitemip",
    "wof:name":"Bose",
    "wof:placetype":"venue"
},
  "geometry": {"coordinates":[-80.37683199999999,25.782765],"type":"Point"}
}