{
  "type": "Feature",
  "properties": {
    "addr:full":"14023 N Dale Mabry Hwy Tampa FL 33614",
    "addr:housenumber":"14023",
    "addr:postcode":"33614",
    "addr:street":"N Dale Mabry Hwy",
    "iso:country":"US",
    "sg:address":"14023 N Dale Mabry Hwy",
    "sg:city":"Tampa",
    "sg:classifiers":[
        {
            "category":"Insurance",
            "subcategory":"Insurance Agent",
            "type":"Services"
        }
    ],
    "sg:phone":"+1 813 269 7787",
    "sg:postcode":"33614",
    "sg:province":"FL",
    "sg:tags":[
        "adjuster"
    ],
    "wof:name":"Abercrombie Simmons & Gillette",
    "wof:placetype":"venue"
},
  "geometry": {"coordinates":[-82.50665499999999,28.075653],"type":"Point"}
}