{
  "type": "Feature",
  "properties": {
    "addr:full":"2503 W Azeele St Tampa FL 33609",
    "addr:housenumber":"2503",
    "addr:postcode":"33609",
    "addr:street":"W Azeele St",
    "iso:country":"US",
    "sg:address":"2503 W Azeele St",
    "sg:city":"Tampa",
    "sg:classifiers":[
        {
            "category":"Travel",
            "subcategory":"Travel Agent",
            "type":"Entertainment"
        }
    ],
    "sg:phone":"+1 813 235 5295",
    "sg:postcode":"33609",
    "sg:province":"FL",
    "sg:tags":[
        "agency",
        "services-commercial"
    ],
    "wof:name":"Mcmar Travel",
    "wof:placetype":"venue"
},
  "geometry": {"coordinates":[-82.485116,27.941111],"type":"Point"}
}