{
  "type": "Feature",
  "properties": {
    "addr:full":"510 Shotgun Rd Ste 110 Sunrise FL 33326",
    "addr:housenumber":"510",
    "addr:postcode":"33326",
    "addr:street":"Shotgun Rd Ste 110",
    "iso:country":"US",
    "sg:address":"510 Shotgun Rd Ste 110",
    "sg:city":"Sunrise",
    "sg:classifiers":[
        {
            "category":"Professional",
            "subcategory":"Engineering",
            "type":"Services"
        },
        {
            "category":"Retail",
            "subcategory":"Repair Shop",
            "type":"Services"
        }
    ],
    "sg:phone":"+1 954 423 5345",
    "sg:postcode":"33326",
    "sg:province":"FL",
    "sg:tags":[
        "rebuilding",
        "aircraft",
        "maintenance"
    ],
    "wof:name":"Aviation Fuel International",
    "wof:placetype":"venue"
},
  "geometry": {"coordinates":[-80.347686,26.113102],"type":"Point"}
}