{
  "type": "Feature",
  "properties": {
    "iso:country":"US",
    "sg:address":"2591 SW Estella Ter",
    "sg:city":"Palm City",
    "sg:classifiers":[
        {
            "category":"Building & Trades",
            "subcategory":"Construction",
            "type":"Services"
        }
    ],
    "sg:phone":"+1 772 286 5119",
    "sg:postcode":"34990",
    "sg:province":"FL",
    "sg:tags":[
        "heavy"
    ],
    "wof:name":"Essenwine John",
    "wof:placetype":"venue"
},
  "geometry": {"coordinates":[-80.2885,27.166363],"type":"Point"}
}