{
  "type": "Feature",
  "properties": {
    "iso:country":"US",
    "sg:address":"6845 Narcoossee Rd",
    "sg:city":"Orlando",
    "sg:classifiers":[
        {
            "category":"Professional",
            "subcategory":"Management & Consulting",
            "type":"Services"
        },
        {
            "category":"Building & Trades",
            "subcategory":"Cleaning & Sanitation",
            "type":"Services"
        },
        {
            "category":"Professional",
            "subcategory":"Business Services",
            "type":"Services"
        },
        {
            "category":"Professional",
            "subcategory":"Engineering",
            "type":"Services"
        }
    ],
    "sg:phone":"+1 407 382 2132",
    "sg:postcode":"32822",
    "sg:province":"FL",
    "sg:tags":[
        "control",
        "product",
        "consultant",
        "hazardous",
        "material",
        "removal",
        "environmental",
        "ecological",
        "engineer"
    ],
    "wof:name":"Dial Environmental Services",
    "wof:placetype":"venue"
},
  "geometry": {"coordinates":[-81.277086,28.467732],"type":"Point"}
}