{
  "type": "Feature",
  "properties": {
    "addr:full":"2602 Amsden Rd Winter Park FL 32792",
    "addr:housenumber":"2602",
    "addr:postcode":"32792",
    "addr:street":"Amsden Rd",
    "iso:country":"US",
    "sg:address":"2602 Amsden Rd",
    "sg:city":"Winter Park",
    "sg:classifiers":[
        {
            "category":"Professional",
            "subcategory":"Computer Services",
            "type":"Services"
        }
    ],
    "sg:phone":"+1 407 673 7655",
    "sg:postcode":"32792",
    "sg:province":"FL",
    "wof:name":"Slovak Technical Svc",
    "wof:placetype":"venue"
},
  "geometry": {"coordinates":[-81.316335,28.60119],"type":"Point"}
}