{
  "type": "Feature",
  "properties": {
    "iso:country":"US",
    "sg:address":"6491 SW 25th St",
    "sg:city":"Miami",
    "sg:classifiers":[
        {
            "category":"Professional",
            "subcategory":"Employment Agencies",
            "type":"Services"
        },
        {
            "category":"Professional",
            "subcategory":"Lawyer & Legal Services",
            "type":"Services"
        }
    ],
    "sg:phone":"+1 786 368 9731",
    "sg:postcode":"33155",
    "sg:province":"FL",
    "sg:tags":[
        "convention",
        "secretarial",
        "reporters-court"
    ],
    "wof:name":"Isabel Solomon",
    "wof:placetype":"venue"
},
  "geometry": {"coordinates":[-80.301243,25.747338],"type":"Point"}
}