{
  "type": "Feature",
  "properties": {
    "addr:full":"1870 US Hwy 1 Rockledge FL 32955",
    "addr:housenumber":"1870",
    "addr:postcode":"32955",
    "addr:street":"Us Hwy 1",
    "iso:country":"US",
    "sg:address":"1870 US Hwy 1",
    "sg:city":"Rockledge",
    "sg:classifiers":[
        {
            "category":"Shopping",
            "subcategory":"Gifts & Souvenirs",
            "type":"Retail Goods"
        }
    ],
    "sg:phone":"+1 321 636 8471",
    "sg:postcode":"32955",
    "sg:province":"FL",
    "sg:tags":[
        "shop"
    ],
    "wof:name":"Hallmark Card & Gift Shop",
    "wof:placetype":"venue"
},
  "geometry": {"coordinates":[-80.71910200000001,28.326779],"type":"Point"}
}