{
  "type": "Feature",
  "properties": {
    "iso:country":"US",
    "sg:address":"1525 Palm Beach Trace Dr",
    "sg:city":"West Palm Beach",
    "sg:classifiers":[
        {
            "category":"Shopping",
            "subcategory":"Hobbies, Toys, & Games",
            "type":"Retail Goods"
        }
    ],
    "sg:phone":"+1 561 689 5439",
    "sg:postcode":"33411",
    "sg:province":"FL",
    "sg:tags":[
        "craft"
    ],
    "wof:name":"Things Jamaican By Robert",
    "wof:placetype":"venue"
},
  "geometry": {"coordinates":[-80.22553499999999,26.712207],"type":"Point"}
}