{
  "type": "Feature",
  "properties": {
    "iso:country":"US",
    "sg:address":"5500 Grant St",
    "sg:city":"Hollywood",
    "sg:classifiers":[
        {
            "category":"Professional",
            "subcategory":"Research",
            "type":"Services"
        }
    ],
    "sg:phone":"+1 954 983 4589",
    "sg:postcode":"33021",
    "sg:province":"FL",
    "sg:tags":[
        "environmental",
        "ecological"
    ],
    "wof:name":"Brown & Assoc Environ Inc",
    "wof:placetype":"venue"
},
  "geometry": {"coordinates":[-80.197152,26.018699],"type":"Point"}
}