{
  "type": "Feature",
  "properties": {
    "iso:country":"US",
    "sg:address":"5507 Forest Hills Dr",
    "sg:city":"Holiday",
    "sg:classifiers":[
        {
            "category":"Banks & Credit Unions",
            "subcategory":"Financial Services",
            "type":"Services"
        },
        {
            "category":"Building & Trades",
            "subcategory":"Construction",
            "type":"Services"
        }
    ],
    "sg:phone":"+1 727 808 6286",
    "sg:postcode":"34690",
    "sg:province":"FL",
    "sg:tags":[
        "investor",
        "demolition",
        "contractor"
    ],
    "wof:name":"J M Faulk Inc",
    "wof:placetype":"venue"
},
  "geometry": {"coordinates":[-82.721356,28.183176],"type":"Point"}
}