{
  "type": "Feature",
  "properties": {
    "iso:country":"US",
    "sg:address":"780 Deltona Blvd",
    "sg:city":"Deltona",
    "sg:classifiers":[
        {
            "category":"Professional",
            "subcategory":"Management & Consulting",
            "type":"Services"
        }
    ],
    "sg:phone":"+1 386 575 2355",
    "sg:postcode":"32725",
    "sg:province":"FL",
    "sg:tags":[
        "consultant",
        "business"
    ],
    "wof:name":"Business Development Lab",
    "wof:placetype":"venue"
},
  "geometry": {"coordinates":[-81.276946,28.885232],"type":"Point"}
}