{
  "type": "Feature",
  "properties": {
    "iso:country":"US",
    "sg:address":"404 16th St",
    "sg:city":"Miami Beach",
    "sg:classifiers":[
        {
            "category":"Personal",
            "subcategory":"Beauty Salon",
            "type":"Services"
        }
    ],
    "sg:phone":"+1 305 672 7527",
    "sg:postcode":"33139",
    "sg:province":"FL",
    "wof:name":"Larue Beauty Salon",
    "wof:placetype":"venue"
},
  "geometry": {"coordinates":[-80.132481,25.789041],"type":"Point"}
}