{
  "type": "Feature",
  "properties": {
    "iso:country":"US",
    "sg:address":"2727 Junior Ave",
    "sg:city":"Apopka",
    "sg:classifiers":[
        {
            "category":"Home & Garden",
            "subcategory":"Garden Supply",
            "type":"Retail Goods"
        }
    ],
    "sg:phone":"+1 407 886 0620",
    "sg:postcode":"32712",
    "sg:province":"FL",
    "sg:tags":[
        "nurseryman"
    ],
    "wof:name":"N & P Begonias",
    "wof:placetype":"venue"
},
  "geometry": {"coordinates":[-81.498649,28.724031],"type":"Point"}
}