{
  "type": "Feature",
  "properties": {
    "addr:full":"23 Castle Hill Way Stuart FL 34996",
    "addr:housenumber":"23",
    "addr:postcode":"34996",
    "addr:street":"Castle Hill Way",
    "iso:country":"US",
    "sg:address":"23 Castle Hill Way",
    "sg:city":"Stuart",
    "sg:classifiers":[
        {
            "category":"Professional",
            "type":"Services"
        }
    ],
    "sg:phone":"+1 772 219 2118",
    "sg:postcode":"34996",
    "sg:province":"FL",
    "wof:name":"M & A Southeast Inc",
    "wof:placetype":"venue"
},
  "geometry": {"coordinates":[-80.211905,27.21953],"type":"Point"}
}