{
  "type": "Feature",
  "properties": {
    "addr:full":"3532 Broadway Riviera Beach FL 33404",
    "addr:housenumber":"3532",
    "addr:postcode":"33404",
    "addr:street":"Broadway",
    "iso:country":"US",
    "sg:address":"3532 Broadway",
    "sg:city":"Riviera Beach",
    "sg:classifiers":[
        {
            "category":"Manufacturing",
            "subcategory":"Printing",
            "type":"Manufacturing & Wholesale Goods"
        }
    ],
    "sg:phone":"+1 561 848 1402",
    "sg:postcode":"33404",
    "sg:province":"FL",
    "sg:tags":[
        "commercial"
    ],
    "sg:website":"www.portprinting.com",
    "wof:name":"Port Printing",
    "wof:placetype":"venue"
},
  "geometry": {"coordinates":[-80.05418899999999,26.791594],"type":"Point"}
}