{
  "type": "Feature",
  "properties": {
    "addr:full":"2330 Manatee Ave E Bradenton FL 34208",
    "addr:housenumber":"2330",
    "addr:postcode":"34208",
    "addr:street":"Manatee Ave E",
    "iso:country":"US",
    "sg:address":"2330 Manatee Ave E",
    "sg:city":"Bradenton",
    "sg:classifiers":[
        {
            "category":"Freight",
            "type":"Transportation"
        }
    ],
    "sg:phone":"+1 941 747 8989",
    "sg:postcode":"34208",
    "sg:province":"FL",
    "sg:tags":[
        "commercial",
        "storage"
    ],
    "wof:name":"Pinnacle Storage Svc",
    "wof:placetype":"venue"
},
  "geometry": {"coordinates":[-82.53479299999999,27.49614],"type":"Point"}
}