{
  "type": "Feature",
  "properties": {
    "iso:country":"US",
    "sg:address":"2221 Hollywood Blvd",
    "sg:city":"Hollywood",
    "sg:classifiers":[
        {
            "category":"Manufacturing",
            "subcategory":"Printing",
            "type":"Manufacturing & Wholesale Goods"
        }
    ],
    "sg:phone":"+1 954 921 2594",
    "sg:postcode":"33020",
    "sg:province":"FL",
    "sg:tags":[
        "print",
        "lithographic",
        "typesetting"
    ],
    "wof:name":"Sir Speedy",
    "wof:placetype":"venue"
},
  "geometry": {"coordinates":[-80.154151,26.01138],"type":"Point"}
}