{
  "type": "Feature",
  "properties": {
    "addr:full":"4408 NW 74th Ave Miami FL 33166",
    "addr:housenumber":"4408",
    "addr:postcode":"33166",
    "addr:street":"Nw 74Th Ave",
    "iso:country":"US",
    "sg:address":"4408 NW 74th Ave",
    "sg:city":"Miami",
    "sg:classifiers":[
        {
            "category":"Wholesale",
            "subcategory":"Computers",
            "type":"Manufacturing & Wholesale Goods"
        }
    ],
    "sg:phone":"+1 305 471 5164",
    "sg:postcode":"33166",
    "sg:province":"FL",
    "sg:tags":[
        "parts",
        "system",
        "reseller"
    ],
    "wof:name":"Wintel Group Corp",
    "wof:placetype":"venue"
},
  "geometry": {"coordinates":[-80.317393,25.814537],"type":"Point"}
}