{
  "type": "Feature",
  "properties": {
    "addr:full":"838 NW 183rd St Miami FL 33169",
    "addr:housenumber":"838",
    "addr:postcode":"33169",
    "addr:street":"Nw 183Rd St",
    "iso:country":"US",
    "sg:address":"838 NW 183rd St",
    "sg:city":"Miami",
    "sg:classifiers":[
        {
            "category":"Social Services",
            "type":"Services"
        }
    ],
    "sg:phone":"+1 305 454 0358",
    "sg:postcode":"33169",
    "sg:province":"FL",
    "sg:tags":[
        "product",
        "developmentally",
        "disabled",
        "need",
        "special"
    ],
    "wof:name":"D S Support Service Inc",
    "wof:placetype":"venue"
},
  "geometry": {"coordinates":[-80.216219,25.942009],"type":"Point"}
}