{
  "type": "Feature",
  "properties": {
    "iso:country":"US",
    "sg:address":"2055 Wood St",
    "sg:city":"Sarasota",
    "sg:classifiers":[
        {
            "category":"Professional",
            "subcategory":"Art Services",
            "type":"Services"
        }
    ],
    "sg:phone":"+1 941 366 1212",
    "sg:postcode":"34237",
    "sg:province":"FL",
    "sg:tags":[
        "photographer"
    ],
    "sg:website":"www.gregwilsonphoto.com",
    "wof:name":"Greg Wilson Group",
    "wof:placetype":"venue"
},
  "geometry": {"coordinates":[-82.529357,27.328487],"type":"Point"}
}