{
  "type": "Feature",
  "properties": {
    "addr:full":"433 Tanya Pass Panama City FL 32404",
    "addr:housenumber":"433",
    "addr:postcode":"32404",
    "addr:street":"Tanya Pass",
    "iso:country":"US",
    "sg:address":"433 Tanya Pass",
    "sg:city":"Panama City",
    "sg:classifiers":[
        {
            "category":"Professional",
            "subcategory":"Management & Consulting",
            "type":"Services"
        }
    ],
    "sg:phone":"+1 850 871 0712",
    "sg:postcode":"32404",
    "sg:province":"FL",
    "sg:tags":[
        "retail",
        "direct",
        "sales"
    ],
    "wof:name":"Break Time Foods",
    "wof:placetype":"venue"
},
  "geometry": {"coordinates":[-85.55932900000001,30.142202],"type":"Point"}
}