{
  "type": "Feature",
  "properties": {
    "addr:full":"4556 S Semoran Blvd Orlando FL 32822",
    "addr:housenumber":"4556",
    "addr:postcode":"32822",
    "addr:street":"S Semoran Blvd",
    "iso:country":"US",
    "sg:address":"4556 S Semoran Blvd",
    "sg:city":"Orlando",
    "sg:classifiers":[
        {
            "category":"Personal",
            "subcategory":"Beauty Salon",
            "type":"Services"
        }
    ],
    "sg:phone":"+1 407 273 1313",
    "sg:postcode":"32822",
    "sg:province":"FL",
    "wof:name":"Elegance Hair Salon",
    "wof:placetype":"venue"
},
  "geometry": {"coordinates":[-81.31028999999999,28.495343],"type":"Point"}
}