{
  "type": "Feature",
  "properties": {
    "addr:full":"7375 NW 36th St Miami FL 33166",
    "addr:housenumber":"7375",
    "addr:postcode":"33166",
    "addr:street":"Nw 36Th St",
    "iso:country":"US",
    "sg:address":"7375 NW 36th St",
    "sg:city":"Miami",
    "sg:classifiers":[
        {
            "category":"Shopping",
            "type":"Retail Goods"
        }
    ],
    "sg:phone":"+1 305 594 2159",
    "sg:postcode":"33166",
    "sg:province":"FL",
    "sg:tags":[
        "picture",
        "frame"
    ],
    "wof:name":"Frame Art",
    "wof:placetype":"venue"
},
  "geometry": {"coordinates":[-80.314103,25.809374],"type":"Point"}
}