{
  "type": "Feature",
  "properties": {
    "iso:country":"US",
    "sg:address":"2802 NW 15th St",
    "sg:city":"Miami",
    "sg:classifiers":[
        {
            "category":"Real Estate",
            "subcategory":"Real Estate Operator",
            "type":"Services"
        }
    ],
    "sg:phone":"+1 305 633 1395",
    "sg:postcode":"33125",
    "sg:province":"FL",
    "sg:tags":[
        "apartment"
    ],
    "wof:name":"Mujica Investments Inc",
    "wof:placetype":"venue"
},
  "geometry": {"coordinates":[-80.241078,25.787969],"type":"Point"}
}