{
  "type": "Feature",
  "properties": {
    "iso:country":"US",
    "sg:address":"10199 SE US Hwy 441",
    "sg:city":"Belleview",
    "sg:classifiers":[
        {
            "category":"Restaurant",
            "type":"Food & Drink"
        }
    ],
    "sg:phone":"+1 352 347 1113",
    "sg:postcode":"34420",
    "sg:province":"FL",
    "sg:tags":[
        "eating"
    ],
    "wof:name":"Taco Bell",
    "wof:placetype":"venue"
},
  "geometry": {"coordinates":[-82.072778,29.073418],"type":"Point"}
}