{
  "type": "Feature",
  "properties": {
    "addr:full":"7160 SW 62nd St South Miami FL 33143",
    "addr:housenumber":"7160",
    "addr:postcode":"33143",
    "addr:street":"Sw 62Nd St",
    "iso:country":"US",
    "sg:address":"7160 SW 62nd St",
    "sg:city":"South Miami",
    "sg:classifiers":[
        {
            "category":"Government",
            "subcategory":"Court House",
            "type":"Public Place"
        }
    ],
    "sg:phone":"+1 305 663 6318",
    "sg:postcode":"33143",
    "sg:province":"FL",
    "sg:tags":[
        "city",
        "counsel"
    ],
    "wof:name":"South Miami City Attorney",
    "wof:placetype":"venue"
},
  "geometry": {"coordinates":[-80.309343,25.712484],"type":"Point"}
}