{
  "type": "Feature",
  "properties": {
    "iso:country":"US",
    "sg:address":"106 Benning Dr Ste 2",
    "sg:city":"Destin",
    "sg:classifiers":[
        {
            "category":"Organizations",
            "subcategory":"Membership Organization",
            "type":"Services"
        }
    ],
    "sg:phone":"+1 850 837 1794",
    "sg:postcode":"32541",
    "sg:province":"FL",
    "sg:tags":[
        "military",
        "veteran"
    ],
    "wof:name":"Am Vets Post 29",
    "wof:placetype":"venue"
},
  "geometry": {"coordinates":[-86.49588,30.392584],"type":"Point"}
}