{
  "type": "Feature",
  "properties": {
    "iso:country":"US",
    "sg:address":"24319 Twin Lakes Dr",
    "sg:city":"Land O Lakes",
    "sg:classifiers":[
        {
            "category":"Building & Trades",
            "subcategory":"Construction",
            "type":"Services"
        }
    ],
    "sg:phone":"+1 813 909 9029",
    "sg:postcode":"34639",
    "sg:province":"FL",
    "sg:tags":[
        "residential"
    ],
    "wof:name":"Mha Construction",
    "wof:placetype":"venue"
},
  "geometry": {"coordinates":[-82.412729,28.190985],"type":"Point"}
}