{
  "type": "Feature",
  "properties": {
    "iso:country":"US",
    "sg:address":"399 W Palmetto Park Rd",
    "sg:city":"Boca Raton",
    "sg:classifiers":[
        {
            "category":"Real Estate",
            "subcategory":"Real Estate Agent",
            "type":"Services"
        }
    ],
    "sg:phone":"+1 561 367 9933",
    "sg:postcode":"33486",
    "sg:province":"FL",
    "wof:name":"Lancore Realty Inc",
    "wof:placetype":"venue"
},
  "geometry": {"coordinates":[-80.09278399999999,26.350438],"type":"Point"}
}