{
  "type": "Feature",
  "properties": {
    "addr:full":"2941 22nd Ave S St Petersburg FL 33712",
    "addr:housenumber":"2941",
    "addr:postcode":"33712",
    "addr:street":"22Nd Ave S",
    "iso:country":"US",
    "sg:address":"2941 22nd Ave S",
    "sg:city":"St Petersburg",
    "sg:classifiers":[
        {
            "category":"Building & Trades",
            "subcategory":"Construction",
            "type":"Services"
        }
    ],
    "sg:phone":"+1 727 327 2488",
    "sg:postcode":"33712",
    "sg:province":"FL",
    "sg:tags":[
        "general",
        "contractor"
    ],
    "wof:name":"Reed Roofing & Tile Co",
    "wof:placetype":"venue"
},
  "geometry": {"coordinates":[-82.672803,27.748444],"type":"Point"}
}