{
  "type": "Feature",
  "properties": {
    "iso:country":"US",
    "sg:address":"155 Isle of Venice Dr",
    "sg:city":"Fort Lauderdale",
    "sg:classifiers":[
        {
            "category":"Organizations",
            "subcategory":"Professional Association",
            "type":"Services"
        }
    ],
    "sg:phone":"+1 954 522 3448",
    "sg:postcode":"33301",
    "sg:province":"FL",
    "wof:name":"Venice Isle Tower Assn Inc",
    "wof:placetype":"venue"
},
  "geometry": {"coordinates":[-80.120662,26.125556],"type":"Point"}
}