{
  "type": "Feature",
  "properties": {
    "addr:full":"9580 SW 40th St Miami FL 33165",
    "addr:housenumber":"9580",
    "addr:postcode":"33165",
    "addr:street":"Sw 40Th St",
    "iso:country":"US",
    "sg:address":"9580 SW 40th St",
    "sg:city":"Miami",
    "sg:classifiers":[
        {
            "category":"Shopping",
            "subcategory":"Gifts & Souvenirs",
            "type":"Retail Goods"
        }
    ],
    "sg:phone":"+1 305 559 0777",
    "sg:postcode":"33165",
    "sg:province":"FL",
    "sg:tags":[
        "equipment"
    ],
    "wof:name":"Bu Party Rentals and Supply",
    "wof:placetype":"venue"
},
  "geometry": {"coordinates":[-80.350155,25.732675],"type":"Point"}
}