{
  "type": "Feature",
  "properties": {
    "addr:full":"1187 8th St S Naples FL 34102",
    "addr:housenumber":"1187",
    "addr:postcode":"34102",
    "addr:street":"8Th St S",
    "iso:country":"US",
    "sg:address":"1187 8th St S",
    "sg:city":"Naples",
    "sg:classifiers":[
        {
            "category":"Professional",
            "subcategory":"Business Services",
            "type":"Services"
        }
    ],
    "sg:phone":"+1 239 430 1415",
    "sg:postcode":"34102",
    "sg:province":"FL",
    "sg:tags":[
        "broker"
    ],
    "wof:name":"Business Development Corp",
    "wof:placetype":"venue"
},
  "geometry": {"coordinates":[-81.794923,26.133441],"type":"Point"}
}