{
  "type": "Feature",
  "properties": {
    "iso:country":"US",
    "sg:address":"114 McDowell St",
    "sg:city":"Santa Rosa Beach",
    "sg:classifiers":[
        {
            "category":"Retail",
            "subcategory":"Laundry & Dry Cleaning",
            "type":"Services"
        }
    ],
    "sg:phone":"+1 850 837 4372",
    "sg:postcode":"32459",
    "sg:province":"FL",
    "sg:tags":[
        "floor",
        "covering"
    ],
    "wof:name":"Sandollar Carpet Cleaning",
    "wof:placetype":"venue"
},
  "geometry": {"coordinates":[-86.291583,30.395825],"type":"Point"}
}