{
  "type": "Feature",
  "properties": {
    "iso:country":"US",
    "sg:address":"632 Atlantus Ter",
    "sg:city":"Sebastian",
    "sg:classifiers":[
        {
            "category":"Shopping",
            "subcategory":"Shoes",
            "type":"Retail Goods"
        }
    ],
    "sg:phone":"+1 772 589 0417",
    "sg:postcode":"32958",
    "sg:province":"FL",
    "wof:name":"William B McKinney Monkey N AR",
    "wof:placetype":"venue"
},
  "geometry": {"coordinates":[-80.489422,27.773792],"type":"Point"}
}