{
  "type": "Feature",
  "properties": {
    "addr:full":"3435 10th St N Naples FL 34103",
    "addr:housenumber":"3435",
    "addr:postcode":"34103",
    "addr:street":"10Th St N",
    "iso:country":"US",
    "sg:address":"3435 10th St N",
    "sg:city":"Naples",
    "sg:classifiers":[
        {
            "category":"Banks & Credit Unions",
            "subcategory":"Investment Brokerage",
            "type":"Services"
        }
    ],
    "sg:phone":"+1 239 659 4467",
    "sg:postcode":"34103",
    "sg:province":"FL",
    "sg:tags":[
        "consultant",
        "planning",
        "financial"
    ],
    "wof:name":"Arco Financial",
    "wof:placetype":"venue"
},
  "geometry": {"coordinates":[-81.798497,26.187397],"type":"Point"}
}