{
  "type": "Feature",
  "properties": {
    "addr:full":"2261 Kettle Dr Orlando FL 32835",
    "addr:housenumber":"2261",
    "addr:postcode":"32835",
    "addr:street":"Kettle Dr",
    "iso:country":"US",
    "sg:address":"2261 Kettle Dr",
    "sg:city":"Orlando",
    "sg:classifiers":[
        {
            "category":"Insurance",
            "subcategory":"Insurance Agent",
            "type":"Services"
        }
    ],
    "sg:phone":"+1 407 294 2996",
    "sg:postcode":"32835",
    "sg:province":"FL",
    "sg:tags":[
        "consulting",
        "management"
    ],
    "wof:name":"Metro Planning  Inc",
    "wof:placetype":"venue"
},
  "geometry": {"coordinates":[-81.496673,28.516957],"type":"Point"}
}