{
  "type": "Feature",
  "properties": {
    "addr:full":"10130 NW 47th St Sunrise FL 33351",
    "addr:housenumber":"10130",
    "addr:postcode":"33351",
    "addr:street":"Nw 47Th St",
    "iso:country":"US",
    "sg:address":"10130 NW 47th St",
    "sg:city":"Sunrise",
    "sg:phone":"+1 954 742 8248",
    "sg:postcode":"33351",
    "sg:province":"FL",
    "wof:name":"Zevuloni & Associates",
    "wof:placetype":"venue"
},
  "geometry": {"coordinates":[-80.285546,26.183331],"type":"Point"}
}