{
  "type": "Feature",
  "properties": {
    "addr:full":"5858 US Hwy 98 Lakeland FL 33809",
    "addr:housenumber":"5858",
    "addr:postcode":"33809",
    "addr:street":"Us Hwy 98",
    "iso:country":"US",
    "sg:address":"5858 US Hwy 98",
    "sg:city":"Lakeland",
    "sg:classifiers":[
        {
            "category":"Building & Trades",
            "subcategory":"Plumbing",
            "type":"Services"
        }
    ],
    "sg:phone":"+1 863 859 0062",
    "sg:postcode":"33809",
    "sg:province":"FL",
    "sg:tags":[
        "conditioning",
        "air",
        "system",
        "contractor"
    ],
    "wof:name":"Ierna's Heating & Cooling",
    "wof:placetype":"venue"
},
  "geometry": {"coordinates":[-81.973677,28.120818],"type":"Point"}
}