{
  "type": "Feature",
  "properties": {
    "iso:country":"US",
    "sg:address":"2999 NE 191st St Ste 403",
    "sg:city":"Miami",
    "sg:classifiers":[
        {
            "category":"Health Services",
            "subcategory":"Doctor",
            "type":"Services"
        }
    ],
    "sg:phone":"+1 305 931 6661",
    "sg:postcode":"33180",
    "sg:province":"FL",
    "sg:tags":[
        "dermatologist"
    ],
    "wof:name":"Advanced Dermatology and Cosmetic Surgery",
    "wof:placetype":"venue"
},
  "geometry": {"coordinates":[-80.142799,25.952299],"type":"Point"}
}