{
  "type": "Feature",
  "properties": {
    "iso:country":"US",
    "sg:address":"152 Mat Trl",
    "sg:city":"Palatka",
    "sg:classifiers":[
        {
            "category":"Building & Trades",
            "subcategory":"Equipment Rental",
            "type":"Services"
        }
    ],
    "sg:phone":"+1 386 325 6188",
    "sg:postcode":"32177",
    "sg:province":"FL",
    "sg:tags":[
        "toilet"
    ],
    "wof:name":"A Dire Need Inc",
    "wof:placetype":"venue"
},
  "geometry": {"coordinates":[-81.72071,29.637332],"type":"Point"}
}