{
  "type": "Feature",
  "properties": {
    "iso:country":"US",
    "sg:address":"2835 NW 14th Ter",
    "sg:city":"Cape Coral",
    "sg:classifiers":[
        {
            "category":"Shopping",
            "subcategory":"Florist",
            "type":"Retail Goods"
        }
    ],
    "sg:phone":"+1 239 574 9188",
    "sg:postcode":"33993",
    "sg:province":"FL",
    "wof:name":"Silk Arrngmnts By Crlyn Ovrsby",
    "wof:placetype":"venue"
},
  "geometry": {"coordinates":[-82.03219199999999,26.679298],"type":"Point"}
}