{
  "type": "Feature",
  "properties": {
    "iso:country":"US",
    "sg:address":"218 E Ocean Ave",
    "sg:city":"Lantana",
    "sg:classifiers":[
        {
            "category":"Personal",
            "subcategory":"Beauty Salon",
            "type":"Services"
        }
    ],
    "sg:phone":"+1 561 547 3200",
    "sg:postcode":"33462",
    "sg:province":"FL",
    "sg:tags":[
        "hair",
        "stylist"
    ],
    "wof:name":"Hair By Ada & Company",
    "wof:placetype":"venue"
},
  "geometry": {"coordinates":[-80.050696,26.584372],"type":"Point"}
}