{
  "type": "Feature",
  "properties": {
    "iso:country":"US",
    "sg:address":"1612 Capital Cir NE",
    "sg:city":"Tallahassee",
    "sg:classifiers":[
        {
            "category":"Transit Center",
            "subcategory":"Freight",
            "type":"Transportation"
        }
    ],
    "sg:phone":"+1 850 562 3554",
    "sg:postcode":"32308",
    "sg:province":"FL",
    "sg:tags":[
        "container",
        "broker"
    ],
    "wof:name":"United Shipping Solutions",
    "wof:placetype":"venue"
},
  "geometry": {"coordinates":[-84.22807899999999,30.461715],"type":"Point"}
}