{
  "type": "Feature",
  "properties": {
    "addr:full":"320 E Dania Beach Blvd Dania FL 33004",
    "addr:housenumber":"320",
    "addr:postcode":"33004",
    "addr:street":"E Dania Beach Blvd",
    "iso:country":"US",
    "sg:address":"320 E Dania Beach Blvd",
    "sg:city":"Dania",
    "sg:classifiers":[
        {
            "category":"Shopping",
            "subcategory":"Gifts & Souvenirs",
            "type":"Retail Goods"
        }
    ],
    "sg:phone":"+1 954 923 4048",
    "sg:postcode":"33004",
    "sg:province":"FL",
    "wof:name":"Oak Moon Rising Inc",
    "wof:placetype":"venue"
},
  "geometry": {"coordinates":[-80.138893,26.052474],"type":"Point"}
}