{
  "type": "Feature",
  "properties": {
    "addr:full":"3841 NW 21st St Fort Lauderdale FL 33311",
    "addr:housenumber":"3841",
    "addr:postcode":"33311",
    "addr:street":"Nw 21St St",
    "iso:country":"US",
    "sg:address":"3841 NW 21st St",
    "sg:city":"Fort Lauderdale",
    "sg:classifiers":[
        {
            "category":"Real Estate",
            "subcategory":"Real Estate Operator",
            "type":"Services"
        },
        {
            "category":"Travel",
            "subcategory":"Bed & Breakfast",
            "type":"Entertainment"
        }
    ],
    "sg:phone":"+1 954 735 5200",
    "sg:postcode":"33311",
    "sg:province":"FL",
    "sg:tags":[
        "building",
        "housing",
        "apartment",
        "student"
    ],
    "wof:name":"Cambridge Square Apartments",
    "wof:placetype":"venue"
},
  "geometry": {"coordinates":[-80.199935,26.152935],"type":"Point"}
}