{
  "type": "Feature",
  "properties": {
    "addr:full":"2100 Summerfield Rd Winter Park FL 32792",
    "addr:housenumber":"2100",
    "addr:postcode":"32792",
    "addr:street":"Summerfield Rd",
    "iso:country":"US",
    "sg:address":"2100 Summerfield Rd",
    "sg:city":"Winter Park",
    "sg:classifiers":[
        {
            "category":"Education",
            "subcategory":"School",
            "type":"Public Place"
        }
    ],
    "sg:phone":"+1 407 645 4405",
    "sg:postcode":"32792",
    "sg:province":"FL",
    "wof:name":"Winter Park Community School",
    "wof:placetype":"venue"
},
  "geometry": {"coordinates":[-81.324327,28.585758],"type":"Point"}
}