{
  "type": "Feature",
  "properties": {
    "iso:country":"US",
    "sg:address":"251 NW 29th St",
    "sg:city":"Miami",
    "sg:classifiers":[
        {
            "category":"Professional",
            "subcategory":"Management & Consulting",
            "type":"Services"
        },
        {
            "category":"Professional",
            "subcategory":"Advertising",
            "type":"Services"
        },
        {
            "category":"Professional",
            "subcategory":"Computer Services",
            "type":"Services"
        }
    ],
    "sg:phone":"+1 305 576 9491",
    "sg:postcode":"33127",
    "sg:province":"FL",
    "sg:tags":[
        "web",
        "marketing",
        "site",
        "program",
        "design",
        "internet",
        "consultant"
    ],
    "sg:website":"http://www.expertwebsitedesign.net",
    "wof:name":"Expert Website Design",
    "wof:placetype":"venue"
},
  "geometry": {"coordinates":[-80.20021,25.803815],"type":"Point"}
}