{
  "type": "Feature",
  "properties": {
    "iso:country":"US",
    "sg:address":"901 NE 125th St Ste 107",
    "sg:city":"North Miami",
    "sg:classifiers":[
        {
            "category":"Professional",
            "subcategory":"Accounting & Tax Preparation",
            "type":"Services"
        }
    ],
    "sg:phone":"+1 305 895 0202",
    "sg:postcode":"33161",
    "sg:province":"FL",
    "sg:tags":[
        "accountant"
    ],
    "wof:name":"Ribotsky Levine Canner Brody Starman and Abtnte PA",
    "wof:placetype":"venue"
},
  "geometry": {"coordinates":[-80.182503,25.892],"type":"Point"}
}