{
  "type": "Feature",
  "properties": {
    "iso:country":"US",
    "sg:address":"1216 Tangelo Isle",
    "sg:city":"Fort Lauderdale",
    "sg:classifiers":[
        {
            "category":"Building & Trades",
            "subcategory":"Construction",
            "type":"Services"
        }
    ],
    "sg:phone":"+1 954 524 2600",
    "sg:postcode":"33315",
    "sg:province":"FL",
    "sg:tags":[
        "general",
        "contractor"
    ],
    "wof:name":"R & T Construction Assoc Inc",
    "wof:placetype":"venue"
},
  "geometry": {"coordinates":[-80.15743399999999,26.101381],"type":"Point"}
}