{
  "type": "Feature",
  "properties": {
    "iso:country":"US",
    "sg:address":"2525 N Main St",
    "sg:city":"Gainesville",
    "sg:classifiers":[
        {
            "category":"Autos & Motor Vehicles",
            "subcategory":"Automobile Sales",
            "type":"Retail Goods"
        }
    ],
    "sg:phone":"+1 352 378 3997",
    "sg:postcode":"32609",
    "sg:province":"FL",
    "sg:tags":[
        "car",
        "dealer"
    ],
    "wof:name":"Bush Daewoo Gainesville",
    "wof:placetype":"venue"
},
  "geometry": {"coordinates":[-82.320823,29.674983],"type":"Point"}
}