{
  "type": "Feature",
  "properties": {
    "addr:full":"2712 S 14th St Fernandina Beach FL 32034",
    "addr:housenumber":"2712",
    "addr:postcode":"32034",
    "addr:street":"S 14Th St",
    "iso:country":"US",
    "sg:address":"2712 S 14th St",
    "sg:city":"Fernandina Beach",
    "sg:classifiers":[
        {
            "category":"Organizations",
            "subcategory":"Religious Organization",
            "type":"Services"
        }
    ],
    "sg:phone":"+1 904 277 4577",
    "sg:postcode":"32034",
    "sg:province":"FL",
    "sg:tags":[
        "church"
    ],
    "wof:name":"Church Of God Of Prophecy",
    "wof:placetype":"venue"
},
  "geometry": {"coordinates":[-81.455005,30.629904],"type":"Point"}
}