{
  "type": "Feature",
  "properties": {
    "addr:full":"7490 49th St N Pinellas Park FL 33781",
    "addr:housenumber":"7490",
    "addr:postcode":"33781",
    "addr:street":"49Th St N",
    "iso:country":"US",
    "sg:address":"7490 49th St N",
    "sg:city":"Pinellas Park",
    "sg:classifiers":[
        {
            "category":"Organizations",
            "subcategory":"Non-profit Organization",
            "type":"Services"
        }
    ],
    "sg:phone":"+1 727 548 4710",
    "sg:postcode":"33781",
    "sg:province":"FL",
    "sg:tags":[
        "charitable",
        "institution"
    ],
    "wof:name":"Childrens Charity Fund",
    "wof:placetype":"venue"
},
  "geometry": {"coordinates":[-82.700046,27.839512],"type":"Point"}
}