{
  "type": "Feature",
  "properties": {
    "iso:country":"US",
    "sg:address":"404 Riberia St",
    "sg:city":"Saint Augustine",
    "sg:classifiers":[
        {
            "category":"Wholesale",
            "subcategory":"Scrap",
            "type":"Manufacturing & Wholesale Goods"
        }
    ],
    "sg:phone":"+1 904 824 9969",
    "sg:postcode":"32084",
    "sg:province":"FL",
    "sg:tags":[
        "material"
    ],
    "wof:name":"Sea Tow",
    "wof:placetype":"venue"
},
  "geometry": {"coordinates":[-81.314318,29.880348],"type":"Point"}
}