{
  "type": "Feature",
  "properties": {
    "addr:full":"2522 Capital Cir NE Tallahassee FL 32308",
    "addr:housenumber":"2522",
    "addr:postcode":"32308",
    "addr:street":"Capital Cir Ne",
    "iso:country":"US",
    "sg:address":"2522 Capital Cir NE",
    "sg:city":"Tallahassee",
    "sg:classifiers":[
        {
            "category":"Insurance",
            "subcategory":"Insurance Agent",
            "type":"Services"
        }
    ],
    "sg:phone":"+1 850 523 0605",
    "sg:postcode":"32308",
    "sg:province":"FL",
    "wof:name":"Great Florida Insurance",
    "wof:placetype":"venue"
},
  "geometry": {"coordinates":[-84.238586,30.487266],"type":"Point"}
}