{
  "type": "Feature",
  "properties": {
    "iso:country":"US",
    "sg:address":"18671 Collins Ave",
    "sg:city":"Miami",
    "sg:classifiers":[
        {
            "category":"Shopping",
            "subcategory":"Clothing, Apparel, & Fashions",
            "type":"Retail Goods"
        }
    ],
    "sg:phone":"+1 305 545 7878",
    "sg:postcode":"33160",
    "sg:province":"FL",
    "wof:name":"Atlantic Lngrie Pantyhose Outl",
    "wof:placetype":"venue"
},
  "geometry": {"coordinates":[-80.12070900000001,25.948994],"type":"Point"}
}