{
  "type": "Feature",
  "properties": {
    "iso:country":"US",
    "sg:address":"11497 Columbia Park Dr W",
    "sg:city":"Jacksonville",
    "sg:classifiers":[
        {
            "category":"Home & Garden",
            "subcategory":"Building Materials",
            "type":"Retail Goods"
        }
    ],
    "sg:phone":"+1 904 268 8046",
    "sg:postcode":"32258",
    "sg:province":"FL",
    "sg:website":"www.americansolarenergy.com",
    "wof:name":"American Solar Energy",
    "wof:placetype":"venue"
},
  "geometry": {"coordinates":[-81.539118,30.160516],"type":"Point"}
}