{
  "type": "Feature",
  "properties": {
    "addr:full":"1834 Grove Ave Fort Myers FL 33901",
    "addr:housenumber":"1834",
    "addr:postcode":"33901",
    "addr:street":"Grove Ave",
    "iso:country":"US",
    "sg:address":"1834 Grove Ave",
    "sg:city":"Fort Myers",
    "sg:classifiers":[
        {
            "category":"Building & Trades",
            "subcategory":"Construction",
            "type":"Services"
        }
    ],
    "sg:phone":"+1 239 939 0383",
    "sg:postcode":"33901",
    "sg:province":"FL",
    "sg:tags":[
        "general",
        "contractor"
    ],
    "wof:name":"EHC Inc",
    "wof:placetype":"venue"
},
  "geometry": {"coordinates":[-81.875659,26.608457],"type":"Point"}
}