{
  "type": "Feature",
  "properties": {
    "addr:full":"3510 Fruitville Rd Sarasota FL 34237",
    "addr:housenumber":"3510",
    "addr:postcode":"34237",
    "addr:street":"Fruitville Rd",
    "iso:country":"US",
    "sg:address":"3510 Fruitville Rd",
    "sg:city":"Sarasota",
    "sg:classifiers":[
        {
            "category":"Banks & Credit Unions",
            "subcategory":"Bank",
            "type":"Services"
        }
    ],
    "sg:phone":"+1 888 871 2690",
    "sg:postcode":"34237",
    "sg:province":"FL",
    "sg:website":"http://www.gtefcu.org",
    "wof:name":"GTE Federal Credit Union",
    "wof:placetype":"venue"
},
  "geometry": {"coordinates":[-82.497794,27.337474],"type":"Point"}
}