{
  "type": "Feature",
  "properties": {
    "iso:country":"US",
    "sg:address":"777 Country Club Dr",
    "sg:city":"Titusville",
    "sg:classifiers":[
        {
            "category":"Professional",
            "subcategory":"Management & Consulting",
            "type":"Services"
        }
    ],
    "sg:phone":"+1 321 383 2582",
    "sg:postcode":"32780",
    "sg:province":"FL",
    "sg:tags":[
        "club",
        "membership",
        "ea"
    ],
    "wof:name":"La Cita Golf & Country Club",
    "wof:placetype":"venue"
},
  "geometry": {"coordinates":[-80.807427,28.577509],"type":"Point"}
}