{
  "type": "Feature",
  "properties": {
    "iso:country":"US",
    "sg:address":"1781 River Rd",
    "sg:city":"Jacksonville",
    "sg:classifiers":[
        {
            "category":"Professional",
            "subcategory":"Advertising",
            "type":"Services"
        }
    ],
    "sg:phone":"+1 904 398 3095",
    "sg:postcode":"32207",
    "sg:province":"FL",
    "sg:tags":[
        "agency"
    ],
    "wof:name":"Emilie M Pennington Advg",
    "wof:placetype":"venue"
},
  "geometry": {"coordinates":[-81.660128,30.306187],"type":"Point"}
}