{
  "type": "Feature",
  "properties": {
    "iso:country":"US",
    "sg:address":"1877 W New Haven Ave",
    "sg:city":"West Melbourne",
    "sg:classifiers":[
        {
            "category":"Shopping",
            "subcategory":"Musical Instruments",
            "type":"Retail Goods"
        }
    ],
    "sg:phone":"+1 321 984 8135",
    "sg:postcode":"32904",
    "sg:province":"FL",
    "sg:tags":[
        "organs"
    ],
    "wof:name":"Music Makers",
    "wof:placetype":"venue"
},
  "geometry": {"coordinates":[-80.65146,28.078781],"type":"Point"}
}