{
  "type": "Feature",
  "properties": {
    "iso:country":"US",
    "sg:address":"2098 NW 20th St Unit 9",
    "sg:city":"Miami",
    "sg:classifiers":[
        {
            "category":"Shopping",
            "subcategory":"Clothing, Apparel, & Fashions",
            "type":"Retail Goods"
        },
        {
            "category":"Shopping",
            "subcategory":"Baby Store",
            "type":"Retail Goods"
        }
    ],
    "sg:phone":"+1 305 545 6321",
    "sg:postcode":"33142",
    "sg:province":"FL",
    "sg:tags":[
        "infant",
        "women's",
        "children's",
        "wear",
        "apparel",
        "clothing"
    ],
    "wof:name":"Kids House",
    "wof:placetype":"venue"
},
  "geometry": {"coordinates":[-80.2295,25.7946],"type":"Point"}
}