{
  "type": "Feature",
  "properties": {
    "addr:full":"12 Marker Rd N Rotonda West FL 33947",
    "addr:housenumber":"12",
    "addr:postcode":"33947",
    "addr:street":"Marker Rd N",
    "iso:country":"US",
    "sg:address":"12 Marker Rd N",
    "sg:city":"Rotonda West",
    "sg:classifiers":[
        {
            "category":"Building & Trades",
            "subcategory":"Construction",
            "type":"Services"
        }
    ],
    "sg:phone":"+1 941 698 1889",
    "sg:postcode":"33947",
    "sg:province":"FL",
    "sg:tags":[
        "contractor"
    ],
    "wof:name":"Carmen P Pacinelli Drywall",
    "wof:placetype":"venue"
},
  "geometry": {"coordinates":[-82.29123,26.880038],"type":"Point"}
}