{
  "type": "Feature",
  "properties": {
    "addr:full":"9900 SW 168th St Miami FL 33157",
    "addr:housenumber":"9900",
    "addr:postcode":"33157",
    "addr:street":"Sw 168Th St",
    "iso:country":"US",
    "sg:address":"9900 SW 168th St",
    "sg:city":"Miami",
    "sg:phone":"+1 305 259 9989",
    "sg:postcode":"33157",
    "sg:province":"FL",
    "wof:name":"Sealy Trinbago Inc",
    "wof:placetype":"venue"
},
  "geometry": {"coordinates":[-80.352728,25.613725],"type":"Point"}
}