{
  "type": "Feature",
  "properties": {
    "iso:country":"US",
    "sg:address":"9624 Black Bear Ln",
    "sg:city":"Winter Garden",
    "sg:classifiers":[
        {
            "category":"Freight",
            "type":"Transportation"
        }
    ],
    "sg:phone":"+1 407 415 3777",
    "sg:postcode":"34787",
    "sg:province":"FL",
    "sg:tags":[
        "house",
        "production",
        "rental",
        "space"
    ],
    "wof:name":"Shadow West Inc",
    "wof:placetype":"venue"
},
  "geometry": {"coordinates":[-81.659468,28.487146],"type":"Point"}
}