{
  "type": "Feature",
  "properties": {
    "iso:country":"US",
    "sg:address":"22476 Sacramento Ave",
    "sg:city":"Port Charlotte",
    "sg:classifiers":[
        {
            "category":"Home & Garden",
            "subcategory":"Building Materials",
            "type":"Retail Goods"
        }
    ],
    "sg:phone":"+1 941 627 5819",
    "sg:postcode":"33954",
    "sg:province":"FL",
    "wof:name":"Glass Pro Inc",
    "wof:placetype":"venue"
},
  "geometry": {"coordinates":[-82.07642300000001,27.020076],"type":"Point"}
}