{
  "type": "Feature",
  "properties": {
    "iso:country":"US",
    "sg:address":"2257 Coral Way",
    "sg:city":"Miami",
    "sg:classifiers":[
        {
            "category":"Restaurant",
            "type":"Food & Drink"
        }
    ],
    "sg:phone":"+1 305 859 2228",
    "sg:postcode":"33145",
    "sg:province":"FL",
    "sg:tags":[
        "italian"
    ],
    "sg:website":"www.romeoscafe.com/",
    "wof:name":"Romeo's Cafe",
    "wof:placetype":"venue"
},
  "geometry": {"coordinates":[-80.2313,25.750626],"type":"Point"}
}