{
  "type": "Feature",
  "properties": {
    "iso:country":"US",
    "sg:address":"13031 Palm Beach Blvd",
    "sg:city":"Fort Myers",
    "sg:classifiers":[
        {
            "category":"Organizations",
            "subcategory":"Religious Organization",
            "type":"Services"
        }
    ],
    "sg:phone":"+1 239 693 0818",
    "sg:postcode":"33905",
    "sg:province":"FL",
    "sg:tags":[
        "church"
    ],
    "wof:name":"St Vincent De Paul Church",
    "wof:placetype":"venue"
},
  "geometry": {"coordinates":[-81.750055,26.703874],"type":"Point"}
}