{
  "type": "Feature",
  "properties": {
    "addr:full":"9104 Cypress Green Dr Jacksonville FL 32256",
    "addr:housenumber":"9104",
    "addr:postcode":"32256",
    "addr:street":"Cypress Green Dr",
    "iso:country":"US",
    "sg:address":"9104 Cypress Green Dr",
    "sg:city":"Jacksonville",
    "sg:classifiers":[
        {
            "category":"Professional",
            "subcategory":"Lawyer & Legal Services",
            "type":"Services"
        }
    ],
    "sg:phone":"+1 904 448 6000",
    "sg:postcode":"32256",
    "sg:province":"FL",
    "wof:name":"Gary B Tullis PA",
    "wof:placetype":"venue"
},
  "geometry": {"coordinates":[-81.569264,30.223333],"type":"Point"}
}