{
  "type": "Feature",
  "properties": {
    "addr:full":"154 Calhoun Ave Destin FL 32541",
    "addr:housenumber":"154",
    "addr:postcode":"32541",
    "addr:street":"Calhoun Ave",
    "iso:country":"US",
    "sg:address":"154 Calhoun Ave",
    "sg:city":"Destin",
    "sg:phone":"+1 850 837 0573",
    "sg:postcode":"32541",
    "sg:province":"FL",
    "sg:website":"http://www.fpcdestin.org",
    "wof:name":"First Presbyterian Church Inc",
    "wof:placetype":"venue"
},
  "geometry": {"coordinates":[-86.510217,30.400266],"type":"Point"}
}