{
  "type": "Feature",
  "properties": {
    "addr:full":"7225 NW 25th St Miami FL 33122",
    "addr:housenumber":"7225",
    "addr:postcode":"33122",
    "addr:street":"Nw 25Th St",
    "iso:country":"US",
    "sg:address":"7225 NW 25th St",
    "sg:city":"Miami",
    "sg:classifiers":[
        {
            "category":"Transit Center",
            "subcategory":"Freight",
            "type":"Transportation"
        }
    ],
    "sg:phone":"+1 305 715 7057",
    "sg:postcode":"33122",
    "sg:province":"FL",
    "sg:tags":[
        "forwarding"
    ],
    "sg:website":"http://www.arishipping.com",
    "wof:name":"Ari Shipping Corporation",
    "wof:placetype":"venue"
},
  "geometry": {"coordinates":[-80.313445,25.797056],"type":"Point"}
}