{
  "type": "Feature",
  "properties": {
    "addr:full":"105 W Plant St Winter Garden FL 34787",
    "addr:housenumber":"105",
    "addr:postcode":"34787",
    "addr:street":"W Plant St",
    "iso:country":"US",
    "sg:address":"105 W Plant St",
    "sg:city":"Winter Garden",
    "sg:classifiers":[
        {
            "category":"Real Estate",
            "subcategory":"Real Estate Agent",
            "type":"Services"
        }
    ],
    "sg:phone":"+1 407 877 8920",
    "sg:postcode":"34787",
    "sg:province":"FL",
    "sg:tags":[
        "appraiser"
    ],
    "wof:name":"Ray N Lait",
    "wof:placetype":"venue"
},
  "geometry": {"coordinates":[-81.58772,28.56536],"type":"Point"}
}