{
  "type": "Feature",
  "properties": {
    "iso:country":"US",
    "sg:address":"18600 SE Country Club Dr",
    "sg:city":"Jupiter",
    "sg:classifiers":[
        {
            "category":"Restaurant",
            "type":"Food & Drink"
        }
    ],
    "sg:phone":"+1 561 744 5733",
    "sg:postcode":"33469",
    "sg:province":"FL",
    "sg:tags":[
        "mexican"
    ],
    "wof:name":"Lafogata Mexican Deli Lacarrub",
    "wof:placetype":"venue"
},
  "geometry": {"coordinates":[-80.129242,26.97806],"type":"Point"}
}