{
  "type": "Feature",
  "properties": {
    "iso:country":"US",
    "sg:address":"11301 S Dixie Hwy",
    "sg:city":"Pinecrest",
    "sg:classifiers":[
        {
            "category":"Building & Trades",
            "subcategory":"Cleaning & Sanitation",
            "type":"Services"
        },
        {
            "category":"Building & Trades",
            "subcategory":"Construction",
            "type":"Services"
        }
    ],
    "sg:phone":"+1 305 767 9010",
    "sg:postcode":"33256",
    "sg:province":"FL",
    "sg:tags":[
        "cleaner",
        "pool",
        "contractor"
    ],
    "sg:website":"www.luxuryoutdoordesign.com",
    "wof:name":"Outdoor Luxury Design",
    "wof:placetype":"venue"
},
  "geometry": {"coordinates":[-80.324063,25.665753],"type":"Point"}
}