{
  "type": "Feature",
  "properties": {
    "addr:full":"892 Gillen Ave NW Palm Bay FL 32907",
    "addr:housenumber":"892",
    "addr:postcode":"32907",
    "addr:street":"Gillen Ave Nw",
    "iso:country":"US",
    "sg:address":"892 Gillen Ave NW",
    "sg:city":"Palm Bay",
    "sg:classifiers":[
        {
            "category":"Building & Trades",
            "subcategory":"Construction",
            "type":"Services"
        }
    ],
    "sg:phone":"+1 321 984 8537",
    "sg:postcode":"32907",
    "sg:province":"FL",
    "sg:tags":[
        "hanging",
        "contractor"
    ],
    "wof:name":"2001 Painting",
    "wof:placetype":"venue"
},
  "geometry": {"coordinates":[-80.711861,28.019802],"type":"Point"}
}