{
  "type": "Feature",
  "properties": {
    "iso:country":"US",
    "sg:address":"2400 N Commerce Pkwy",
    "sg:city":"Fort Lauderdale",
    "sg:classifiers":[
        {
            "category":"Professional",
            "subcategory":"Lawyer & Legal Services",
            "type":"Services"
        }
    ],
    "sg:phone":"+1 954 525 0255",
    "sg:postcode":"33326",
    "sg:province":"FL",
    "wof:name":"Mitrani Rynor Adamsky Macauley",
    "wof:placetype":"venue"
},
  "geometry": {"coordinates":[-80.366681,26.091406],"type":"Point"}
}