{
  "type": "Feature",
  "properties": {
    "iso:country":"US",
    "sg:address":"1357 Defender St NW",
    "sg:city":"Palm Bay",
    "sg:classifiers":[
        {
            "category":"Shopping",
            "subcategory":"Gifts & Souvenirs",
            "type":"Retail Goods"
        }
    ],
    "sg:phone":"+1 321 952 3633",
    "sg:postcode":"32907",
    "sg:province":"FL",
    "wof:name":"Catchers Mint Comic/Card/Colec",
    "wof:placetype":"venue"
},
  "geometry": {"coordinates":[-80.71015199999999,28.003315],"type":"Point"}
}