{
  "type": "Feature",
  "properties": {
    "addr:full":"5901 SW 74th St Miami FL 33143",
    "addr:housenumber":"5901",
    "addr:postcode":"33143",
    "addr:street":"Sw 74Th St",
    "iso:country":"US",
    "sg:address":"5901 SW 74th St",
    "sg:city":"Miami",
    "sg:classifiers":[
        {
            "category":"Professional",
            "subcategory":"Lawyer & Legal Services",
            "type":"Services"
        }
    ],
    "sg:phone":"+1 305 661 1750",
    "sg:postcode":"33143",
    "sg:province":"FL",
    "wof:name":"Wakeman Charles H Atty",
    "wof:placetype":"venue"
},
  "geometry": {"coordinates":[-80.289902,25.7024],"type":"Point"}
}