{
  "type": "Feature",
  "properties": {
    "iso:country":"US",
    "sg:address":"80 W Oakland Park Blvd",
    "sg:city":"Fort Lauderdale",
    "sg:classifiers":[
        {
            "category":"Shopping",
            "subcategory":"Shoes",
            "type":"Retail Goods"
        }
    ],
    "sg:phone":"+1 954 485 1416",
    "sg:postcode":"33311",
    "sg:province":"FL",
    "wof:name":"Sonny Shoes",
    "wof:placetype":"venue"
},
  "geometry": {"coordinates":[-80.148707,26.166433],"type":"Point"}
}