{
  "type": "Feature",
  "properties": {
    "iso:country":"US",
    "sg:address":"12526 Magbury Ln",
    "sg:city":"Jacksonville",
    "sg:classifiers":[
        {
            "category":"Shopping",
            "subcategory":"Catalog Store",
            "type":"Retail Goods"
        }
    ],
    "sg:phone":"+1 904 880 4052",
    "sg:postcode":"32258",
    "sg:province":"FL",
    "sg:tags":[
        "mail",
        "house"
    ],
    "wof:name":"Shoppers Treasure",
    "wof:placetype":"venue"
},
  "geometry": {"coordinates":[-81.526811,30.14289],"type":"Point"}
}