{
  "type": "Feature",
  "properties": {
    "addr:full":"13575 58th St N Clearwater FL 33760",
    "addr:housenumber":"13575",
    "addr:postcode":"33760",
    "addr:street":"58Th St N",
    "iso:country":"US",
    "sg:address":"13575 58th St N",
    "sg:city":"Clearwater",
    "sg:classifiers":[
        {
            "category":"Wholesale",
            "subcategory":"Medical Equipment & Supplies",
            "type":"Manufacturing & Wholesale Goods"
        }
    ],
    "sg:phone":"+1 727 524 1954",
    "sg:postcode":"33760",
    "sg:province":"FL",
    "sg:tags":[
        "physician",
        "surgeon"
    ],
    "wof:name":"Oxford Instruments",
    "wof:placetype":"venue"
},
  "geometry": {"coordinates":[-82.712357,27.895248],"type":"Point"}
}