{
  "type": "Feature",
  "properties": {
    "addr:full":"13713 SW 9th St Miami FL 33184",
    "addr:housenumber":"13713",
    "addr:postcode":"33184",
    "addr:street":"Sw 9Th St",
    "iso:country":"US",
    "sg:address":"13713 SW 9th St",
    "sg:city":"Miami",
    "sg:classifiers":[
        {
            "category":"Health Services",
            "subcategory":"Doctor",
            "type":"Services"
        }
    ],
    "sg:phone":"+1 305 448 4860",
    "sg:postcode":"33184",
    "sg:province":"FL",
    "sg:tags":[
        "physician",
        "surgeon"
    ],
    "wof:name":"General Medicine Group",
    "wof:placetype":"venue"
},
  "geometry": {"coordinates":[-80.418747,25.759053],"type":"Point"}
}