{
  "type": "Feature",
  "properties": {
    "addr:full":"2303 US Hwy 27 Sebring FL 33870",
    "addr:housenumber":"2303",
    "addr:postcode":"33870",
    "addr:street":"Us Hwy 27",
    "iso:country":"US",
    "sg:address":"2303 US Hwy 27",
    "sg:city":"Sebring",
    "sg:classifiers":[
        {
            "category":"Home & Garden",
            "subcategory":"Building Materials",
            "type":"Retail Goods"
        }
    ],
    "sg:phone":"+1 863 471 6119",
    "sg:postcode":"33870",
    "sg:province":"FL",
    "wof:name":"Home Depot",
    "wof:placetype":"venue"
},
  "geometry": {"coordinates":[-81.491255,27.504064],"type":"Point"}
}