{
  "type": "Feature",
  "properties": {
    "iso:country":"US",
    "sg:address":"904 S Highland Ave",
    "sg:city":"Clearwater",
    "sg:classifiers":[
        {
            "category":"Shopping",
            "subcategory":"Crafts & Fabrics",
            "type":"Retail Goods"
        }
    ],
    "sg:phone":"+1 727 447 7832",
    "sg:postcode":"33756",
    "sg:province":"FL",
    "sg:tags":[
        "material",
        "needlework"
    ],
    "wof:name":"Clearwater Cushion Shop",
    "wof:placetype":"venue"
},
  "geometry": {"coordinates":[-82.775244,27.953447],"type":"Point"}
}