{
  "type": "Feature",
  "properties": {
    "iso:country":"US",
    "sg:address":"2037 N Atlantic Ave",
    "sg:city":"Cocoa Beach",
    "sg:classifiers":[
        {
            "category":"Personal",
            "type":"Services"
        }
    ],
    "sg:phone":"+1 321 784 2208",
    "sg:postcode":"32931",
    "sg:province":"FL",
    "sg:tags":[
        "therapist",
        "massage"
    ],
    "wof:name":"Massage By Morakot",
    "wof:placetype":"venue"
},
  "geometry": {"coordinates":[-80.609781,28.345026],"type":"Point"}
}