{
  "type": "Feature",
  "properties": {
    "iso:country":"US",
    "sg:address":"835 13th St",
    "sg:city":"Lake Park",
    "sg:classifiers":[
        {
            "category":"Manufacturing",
            "subcategory":"Food",
            "type":"Manufacturing & Wholesale Goods"
        }
    ],
    "sg:phone":"+1 561 842 4593",
    "sg:postcode":"33403",
    "sg:province":"FL",
    "sg:tags":[
        "preparation"
    ],
    "wof:name":"CRNS Inc",
    "wof:placetype":"venue"
},
  "geometry": {"coordinates":[-80.079459,26.800278],"type":"Point"}
}