{
  "type": "Feature",
  "properties": {
    "iso:country":"US",
    "sg:address":"3659 W Hillsborough Ave",
    "sg:city":"Tampa",
    "sg:classifiers":[
        {
            "category":"Professional",
            "subcategory":"Computer Services",
            "type":"Services"
        }
    ],
    "sg:phone":"+1 813 806 0484",
    "sg:postcode":"33614",
    "sg:province":"FL",
    "sg:tags":[
        "consultant"
    ],
    "wof:name":"Computer Needs",
    "wof:placetype":"venue"
},
  "geometry": {"coordinates":[-82.502274,27.996026],"type":"Point"}
}