{
  "type": "Feature",
  "properties": {
    "addr:full":"216 3rd Ave S Jacksonville Beach FL 32250",
    "addr:housenumber":"216",
    "addr:postcode":"32250",
    "addr:street":"3Rd Ave S Jacksonville",
    "iso:country":"US",
    "sg:address":"216 3rd Ave S",
    "sg:city":"Jacksonville Beach",
    "sg:classifiers":[
        {
            "category":"Manufacturing",
            "subcategory":"Tools & Machinery",
            "type":"Manufacturing & Wholesale Goods"
        }
    ],
    "sg:phone":"+1 904 242 0282",
    "sg:postcode":"32250",
    "sg:province":"FL",
    "sg:tags":[
        "mfg"
    ],
    "wof:name":"Washington Equipment Co-FL LLC",
    "wof:placetype":"venue"
},
  "geometry": {"coordinates":[-81.391006,30.285286],"type":"Point"}
}