{
  "type": "Feature",
  "properties": {
    "addr:full":"13125 72nd Ave Seminole FL 33776",
    "addr:housenumber":"13125",
    "addr:postcode":"33776",
    "addr:street":"72Nd Ave",
    "iso:country":"US",
    "sg:address":"13125 72nd Ave",
    "sg:city":"Seminole",
    "sg:classifiers":[
        {
            "category":"Building & Trades",
            "subcategory":"Construction",
            "type":"Services"
        }
    ],
    "sg:phone":"+1 727 393 1516",
    "sg:postcode":"33776",
    "sg:province":"FL",
    "sg:tags":[
        "house"
    ],
    "wof:name":"Kapper Construction Inc",
    "wof:placetype":"venue"
},
  "geometry": {"coordinates":[-82.82101900000001,27.838019],"type":"Point"}
}