{
  "type": "Feature",
  "properties": {
    "iso:country":"US",
    "sg:address":"9400 SW 40th St",
    "sg:city":"Miami",
    "sg:classifiers":[
        {
            "category":"Building & Trades",
            "subcategory":"Construction",
            "type":"Services"
        }
    ],
    "sg:phone":"+1 305 552 0350",
    "sg:postcode":"33165",
    "sg:province":"FL",
    "sg:tags":[
        "fence",
        "contractor"
    ],
    "wof:name":"Miami Fence Design",
    "wof:placetype":"venue"
},
  "geometry": {"coordinates":[-80.348767,25.732802],"type":"Point"}
}