{
  "type": "Feature",
  "properties": {
    "addr:full":"345 Goodlette Rd N Naples FL 34103",
    "addr:housenumber":"345",
    "addr:postcode":"34103",
    "addr:street":"Goodlette Rd N",
    "iso:country":"US",
    "sg:address":"345 Goodlette Rd N",
    "sg:city":"Naples",
    "sg:classifiers":[
        {
            "category":"Real Estate",
            "subcategory":"Real Estate Agent",
            "type":"Services"
        }
    ],
    "sg:phone":"+1 239 649 1208",
    "sg:postcode":"34103",
    "sg:province":"FL",
    "wof:name":"South Bay Realty",
    "wof:placetype":"venue"
},
  "geometry": {"coordinates":[-81.791017,26.153271],"type":"Point"}
}