{
  "type": "Feature",
  "properties": {
    "iso:country":"US",
    "sg:address":"411 N Donnelly St",
    "sg:city":"Mt Dora",
    "sg:classifiers":[
        {
            "category":"Personal",
            "type":"Services"
        }
    ],
    "sg:phone":"+1 352 383 8007",
    "sg:postcode":"32757",
    "sg:province":"FL",
    "sg:tags":[
        "therapist",
        "massage"
    ],
    "wof:name":"Beneficial Massage",
    "wof:placetype":"venue"
},
  "geometry": {"coordinates":[-81.644786,28.800437],"type":"Point"}
}