{
  "type": "Feature",
  "properties": {
    "iso:country":"US",
    "sg:address":"217 SE Ocean Blvd",
    "sg:city":"Stuart",
    "sg:classifiers":[
        {
            "category":"Professional",
            "subcategory":"Lawyer & Legal Services",
            "type":"Services"
        }
    ],
    "sg:phone":"+1 772 286 0200",
    "sg:postcode":"34996",
    "sg:province":"FL",
    "wof:name":"Maxine A Noel",
    "wof:placetype":"venue"
},
  "geometry": {"coordinates":[-80.250106,27.197604],"type":"Point"}
}