{
  "type": "Feature",
  "properties": {
    "addr:full":"1520 Grand Rd Winter Park FL 32792",
    "addr:housenumber":"1520",
    "addr:postcode":"32792",
    "addr:street":"Grand Rd",
    "iso:country":"US",
    "sg:address":"1520 Grand Rd",
    "sg:city":"Winter Park",
    "sg:classifiers":[
        {
            "category":"Health Services",
            "subcategory":"Clinic",
            "type":"Services"
        }
    ],
    "sg:phone":"+1 407 339 1816",
    "sg:postcode":"32792",
    "sg:province":"FL",
    "sg:tags":[
        "medical"
    ],
    "wof:name":"Longwood Health Care Center",
    "wof:placetype":"venue"
},
  "geometry": {"coordinates":[-81.287003,28.6248],"type":"Point"}
}