{
  "type": "Feature",
  "properties": {
    "iso:country":"US",
    "sg:address":"9896 Majestic Way",
    "sg:city":"Boynton Beach",
    "sg:classifiers":[
        {
            "category":"Professional",
            "subcategory":"Management & Consulting",
            "type":"Services"
        }
    ],
    "sg:phone":"+1 561 252 8200",
    "sg:postcode":"33437",
    "sg:province":"FL",
    "sg:tags":[
        "consultant",
        "business"
    ],
    "wof:name":"Hositality Firm",
    "wof:placetype":"venue"
},
  "geometry": {"coordinates":[-80.13760000000001,26.530383],"type":"Point"}
}