{
  "type": "Feature",
  "properties": {
    "iso:country":"US",
    "sg:address":"2033 S Ridgewood Ave",
    "sg:city":"Edgewater",
    "sg:classifiers":[
        {
            "category":"Retail",
            "subcategory":"Auto Repair",
            "type":"Services"
        }
    ],
    "sg:phone":"+1 386 427 1703",
    "sg:postcode":"32141",
    "sg:province":"FL",
    "sg:tags":[
        "body",
        "general"
    ],
    "wof:name":"Edgewater Garage Inc",
    "wof:placetype":"venue"
},
  "geometry": {"coordinates":[-80.89379099999999,28.969498],"type":"Point"}
}