{
  "type": "Feature",
  "properties": {
    "iso:country":"US",
    "sg:address":"2050 51st St",
    "sg:city":"Sarasota",
    "sg:classifiers":[
        {
            "category":"Utilities",
            "subcategory":"Refuse",
            "type":"Services"
        }
    ],
    "sg:phone":"+1 941 809 1182",
    "sg:postcode":"34234",
    "sg:province":"FL",
    "sg:tags":[
        "system"
    ],
    "wof:name":"Suncoast Metal Recycling LLC",
    "wof:placetype":"venue"
},
  "geometry": {"coordinates":[-82.529014,27.377914],"type":"Point"}
}