{
  "type": "Feature",
  "properties": {
    "iso:country":"US",
    "sg:address":"398 Recker Hwy",
    "sg:city":"Auburndale",
    "sg:classifiers":[
        {
            "category":"Place Of Worship",
            "subcategory":"Church",
            "type":"Public Place"
        }
    ],
    "sg:phone":"+1 863 551 1700",
    "sg:postcode":"33823",
    "sg:province":"FL",
    "sg:tags":[
        "churches-baptist-independent"
    ],
    "wof:name":"Mount Calvary Haitian",
    "wof:placetype":"venue"
},
  "geometry": {"coordinates":[-81.80188800000001,28.051371],"type":"Point"}
}