{
  "type": "Feature",
  "properties": {
    "addr:full":"301 Barefoot Blvd Sebastian FL 32976",
    "addr:housenumber":"301",
    "addr:postcode":"32976",
    "addr:street":"Barefoot Blvd",
    "iso:country":"US",
    "sg:address":"301 Barefoot Blvd",
    "sg:city":"Sebastian",
    "sg:classifiers":[
        {
            "category":"Government",
            "subcategory":"Fire Station",
            "type":"Public Place"
        }
    ],
    "sg:phone":"+1 772 664 5533",
    "sg:postcode":"32976",
    "sg:province":"FL",
    "sg:tags":[
        "department"
    ],
    "wof:name":"Micco Fire Dept",
    "wof:placetype":"venue"
},
  "geometry": {"coordinates":[-80.505734,27.883506],"type":"Point"}
}