{
  "type": "Feature",
  "properties": {
    "iso:country":"US",
    "sg:address":"6385 Baker Rd",
    "sg:city":"Keystone Heights",
    "sg:classifiers":[
        {
            "category":"Professional",
            "type":"Services"
        }
    ],
    "sg:phone":"+1 352 473 3954",
    "sg:postcode":"32656",
    "sg:province":"FL",
    "wof:name":"Carl Sievers",
    "wof:placetype":"venue"
},
  "geometry": {"coordinates":[-82.023162,29.750191],"type":"Point"}
}