{
  "type": "Feature",
  "properties": {
    "addr:full":"2104 SW 34 St Gainesville FL 32608",
    "addr:housenumber":"2104",
    "addr:postcode":"32608",
    "addr:street":"Sw 34 St",
    "iso:country":"US",
    "sg:address":"2104 SW 34 St",
    "sg:city":"Gainesville",
    "sg:classifiers":[
        {
            "category":"Restaurant",
            "type":"Food & Drink"
        }
    ],
    "sg:phone":"+1 352 374 2111",
    "sg:postcode":"32608",
    "sg:province":"FL",
    "sg:tags":[
        "pizza"
    ],
    "wof:name":"Pizza Man Express",
    "wof:placetype":"venue"
},
  "geometry": {"coordinates":[-82.367836,29.600128],"type":"Point"}
}