{
  "type": "Feature",
  "properties": {
    "iso:country":"US",
    "sg:address":"2801 NW 74th Ave Ste 217",
    "sg:city":"Miami",
    "sg:classifiers":[
        {
            "category":"Professional",
            "subcategory":"Lawyer & Legal Services",
            "type":"Services"
        }
    ],
    "sg:phone":"+1 305 463 5225",
    "sg:postcode":"33122",
    "sg:province":"FL",
    "wof:name":"Letelier Gazitua PA",
    "wof:placetype":"venue"
},
  "geometry": {"coordinates":[-80.317117,25.800218],"type":"Point"}
}