{
  "type": "Feature",
  "properties": {
    "iso:country":"US",
    "sg:address":"1715 Periwinkle Way",
    "sg:city":"Sanibel",
    "sg:classifiers":[
        {
            "category":"Professional",
            "subcategory":"Business Services",
            "type":"Services"
        }
    ],
    "sg:phone":"+1 239 395 0607",
    "sg:postcode":"33957",
    "sg:province":"FL",
    "wof:name":"1 800 Sanibel",
    "wof:placetype":"venue"
},
  "geometry": {"coordinates":[-82.062493,26.440324],"type":"Point"}
}