{
  "type": "Feature",
  "properties": {
    "iso:country":"US",
    "sg:address":"2153 NW 3rd St",
    "sg:city":"Miami",
    "sg:classifiers":[
        {
            "category":"Education",
            "subcategory":"School",
            "type":"Public Place"
        }
    ],
    "sg:phone":"+1 305 642 5055",
    "sg:postcode":"33125",
    "sg:province":"FL",
    "sg:tags":[
        "high",
        "middle",
        "elementary"
    ],
    "sg:website":"citrus.dadeschools.net",
    "wof:name":"Miami-Dade County Public Schools",
    "wof:placetype":"venue"
},
  "geometry": {"coordinates":[-80.23013400000001,25.776311],"type":"Point"}
}