{
  "type": "Feature",
  "properties": {
    "addr:full":"1633 E Vine St Kissimmee FL 34744",
    "addr:housenumber":"1633",
    "addr:postcode":"34744",
    "addr:street":"E Vine St",
    "iso:country":"US",
    "sg:address":"1633 E Vine St",
    "sg:city":"Kissimmee",
    "sg:classifiers":[
        {
            "category":"Real Estate",
            "subcategory":"Real Estate Agent",
            "type":"Services"
        }
    ],
    "sg:phone":"+1 407 870 7344",
    "sg:postcode":"34744",
    "sg:province":"FL",
    "wof:name":"Rivera Realty Inc",
    "wof:placetype":"venue"
},
  "geometry": {"coordinates":[-81.37521599999999,28.300773],"type":"Point"}
}