{
  "type": "Feature",
  "properties": {
    "addr:full":"1140 S Semoran Blvd Ste E Orlando FL 32807",
    "addr:housenumber":"1140",
    "addr:postcode":"32807",
    "addr:street":"S Semoran Blvd Ste E",
    "iso:country":"US",
    "sg:address":"1140 S Semoran Blvd Ste E",
    "sg:city":"Orlando",
    "sg:classifiers":[
        {
            "category":"Health Services",
            "subcategory":"Doctor",
            "type":"Services"
        },
        {
            "category":"Health Services",
            "subcategory":"Clinic",
            "type":"Services"
        },
        {
            "category":"Community Center",
            "type":"Public Place"
        }
    ],
    "sg:phone":"+1 407 281 9105",
    "sg:postcode":"32807",
    "sg:province":"FL",
    "sg:tags":[
        "physician",
        "family",
        "medical",
        "practice",
        "surgeons",
        "medicine"
    ],
    "wof:name":"We Care Family Medical Group",
    "wof:placetype":"venue"
},
  "geometry": {"coordinates":[-81.31052200000001,28.528622],"type":"Point"}
}