{
  "type": "Feature",
  "properties": {
    "iso:country":"US",
    "sg:address":"3202 N Palafox St",
    "sg:city":"Pensacola",
    "sg:classifiers":[
        {
            "category":"Autos & Motor Vehicles",
            "subcategory":"Auto Supplies",
            "type":"Retail Goods"
        },
        {
            "category":"Retail",
            "subcategory":"Auto Repair",
            "type":"Services"
        }
    ],
    "sg:phone":"+1 850 434 9940",
    "sg:postcode":"32501",
    "sg:province":"FL",
    "sg:tags":[
        "recap",
        "retread",
        "tire"
    ],
    "wof:name":"Hamm's Tire Center",
    "wof:placetype":"venue"
},
  "geometry": {"coordinates":[-87.22784799999999,30.445743],"type":"Point"}
}