{
  "type": "Feature",
  "properties": {
    "addr:full":"1707 1st St Bradenton FL 34208",
    "addr:housenumber":"1707",
    "addr:postcode":"34208",
    "addr:street":"1St St",
    "iso:country":"US",
    "sg:address":"1707 1st St",
    "sg:city":"Bradenton",
    "sg:classifiers":[
        {
            "category":"Shopping",
            "subcategory":"Bicycles & Sporting Goods",
            "type":"Retail Goods"
        }
    ],
    "sg:phone":"+1 941 750 8633",
    "sg:postcode":"34208",
    "sg:province":"FL",
    "sg:tags":[
        "tackle",
        "fishing"
    ],
    "wof:name":"$20 Fish & Tackle Store",
    "wof:placetype":"venue"
},
  "geometry": {"coordinates":[-82.563131,27.482072],"type":"Point"}
}