{
  "type": "Feature",
  "properties": {
    "iso:country":"US",
    "sg:address":"4219 N Armenia Ave",
    "sg:city":"Tampa",
    "sg:classifiers":[
        {
            "category":"Shopping",
            "subcategory":"Jewelry",
            "type":"Retail Goods"
        }
    ],
    "sg:phone":"+1 813 870 6319",
    "sg:postcode":"33607",
    "sg:province":"FL",
    "sg:tags":[
        "jeweler"
    ],
    "wof:name":"Jewels Of The World",
    "wof:placetype":"venue"
},
  "geometry": {"coordinates":[-82.484638,27.979894],"type":"Point"}
}