{
  "type": "Feature",
  "properties": {
    "addr:full":"1236 Hammondville Rd Pompano Beach FL 33069",
    "addr:housenumber":"1236",
    "addr:postcode":"33069",
    "addr:street":"Hammondville Rd",
    "iso:country":"US",
    "sg:address":"1236 Hammondville Rd",
    "sg:city":"Pompano Beach",
    "sg:classifiers":[
        {
            "category":"Wholesale",
            "subcategory":"Fruits & Vegetables",
            "type":"Manufacturing & Wholesale Goods"
        }
    ],
    "sg:phone":"+1 954 788 6800",
    "sg:postcode":"33069",
    "sg:province":"FL",
    "sg:tags":[
        "produce"
    ],
    "wof:name":"Ayco Farms Inc",
    "wof:placetype":"venue"
},
  "geometry": {"coordinates":[-80.13914,26.235577],"type":"Point"}
}