{
  "type": "Feature",
  "properties": {
    "iso:country":"US",
    "sg:address":"4680 Oakcreek St Apt 108",
    "sg:city":"Orlando",
    "sg:classifiers":[
        {
            "category":"Wholesale",
            "subcategory":"Vending Machines",
            "type":"Manufacturing & Wholesale Goods"
        }
    ],
    "sg:phone":"+1 407 578 8411",
    "sg:postcode":"32835",
    "sg:province":"FL",
    "sg:tags":[
        "merchandise"
    ],
    "wof:name":"Cyndie Sweets",
    "wof:placetype":"venue"
},
  "geometry": {"coordinates":[-81.46194199999999,28.494212],"type":"Point"}
}