{
  "type": "Feature",
  "properties": {
    "iso:country":"US",
    "sg:address":"3008 Lions Ct",
    "sg:city":"Kissimmee",
    "sg:classifiers":[
        {
            "category":"Building & Trades",
            "subcategory":"Electrical",
            "type":"Services"
        }
    ],
    "sg:phone":"+1 407 344 7776",
    "sg:postcode":"34744",
    "sg:province":"FL",
    "sg:tags":[
        "electric",
        "contractor"
    ],
    "wof:name":"J & J Electric",
    "wof:placetype":"venue"
},
  "geometry": {"coordinates":[-81.38686,28.33855],"type":"Point"}
}