{
  "type": "Feature",
  "properties": {
    "iso:country":"US",
    "sg:address":"6200 Metrowest Blvd",
    "sg:city":"Orlando",
    "sg:classifiers":[
        {
            "category":"Professional",
            "subcategory":"Lawyer & Legal Services",
            "type":"Services"
        }
    ],
    "sg:phone":"+1 407 363 9939",
    "sg:postcode":"32835",
    "sg:province":"FL",
    "sg:tags":[
        "attorney",
        "criminal",
        "family",
        "personal",
        "practice",
        "worker",
        "compensation",
        "benefit",
        "employee",
        "injury",
        "law"
    ],
    "sg:website":"http://www.francislawfirm.net",
    "wof:name":"Francis Law Group The",
    "wof:placetype":"venue"
},
  "geometry": {"coordinates":[-81.46745799999999,28.515271],"type":"Point"}
}