{
  "type": "Feature",
  "properties": {
    "iso:country":"US",
    "sg:address":"9510 US Hwy 19",
    "sg:city":"Port Richey",
    "sg:classifiers":[
        {
            "category":"Cinema",
            "subcategory":"Movie Theater",
            "type":"Entertainment"
        }
    ],
    "sg:phone":"+1 727 848 4424",
    "sg:postcode":"34668",
    "sg:province":"FL",
    "wof:name":"Cinema Grill Embassy 6",
    "wof:placetype":"venue"
},
  "geometry": {"coordinates":[-82.708671,28.294771],"type":"Point"}
}