{
  "type": "Feature",
  "properties": {
    "addr:full":"7235 W 19th Ct Hialeah FL 33014",
    "addr:housenumber":"7235",
    "addr:postcode":"33014",
    "addr:street":"W 19Th Ct",
    "iso:country":"US",
    "sg:address":"7235 W 19th Ct",
    "sg:city":"Hialeah",
    "sg:classifiers":[
        {
            "category":"Utilities",
            "subcategory":"Mobile Phone",
            "type":"Services"
        }
    ],
    "sg:phone":"+1 786 331 7669",
    "sg:postcode":"33014",
    "sg:province":"FL",
    "sg:tags":[
        "telephone",
        "cellular"
    ],
    "wof:name":"Direct Wireless",
    "wof:placetype":"venue"
},
  "geometry": {"coordinates":[-80.32247700000001,25.890557],"type":"Point"}
}