{
  "type": "Feature",
  "properties": {
    "addr:full":"15380 SW 42nd Ln Miami FL 33185",
    "addr:housenumber":"15380",
    "addr:postcode":"33185",
    "addr:street":"Sw 42Nd Ln",
    "iso:country":"US",
    "sg:address":"15380 SW 42nd Ln",
    "sg:city":"Miami",
    "sg:classifiers":[
        {
            "category":"Freight",
            "type":"Transportation"
        }
    ],
    "sg:phone":"+1 305 559 4401",
    "sg:postcode":"33185",
    "sg:province":"FL",
    "sg:tags":[
        "courier"
    ],
    "wof:name":"Carrera Courier Inc",
    "wof:placetype":"venue"
},
  "geometry": {"coordinates":[-80.44307999999999,25.725796],"type":"Point"}
}