{
  "type": "Feature",
  "properties": {
    "addr:full":"11547 SW 64th St Apt G Miami FL 33173",
    "addr:housenumber":"11547",
    "addr:postcode":"33173",
    "addr:street":"Sw 64Th St Apt G",
    "iso:country":"US",
    "sg:address":"11547 SW 64th St Apt G",
    "sg:city":"Miami",
    "sg:classifiers":[
        {
            "category":"Communications",
            "subcategory":"Film & Video Production",
            "type":"Services"
        }
    ],
    "sg:phone":"+1 305 595 1104",
    "sg:postcode":"33173",
    "sg:province":"FL",
    "sg:tags":[
        "tv",
        "radio",
        "services-commercial",
        "companies-film"
    ],
    "wof:name":"Alex Teixeira Productions Inc",
    "wof:placetype":"venue"
},
  "geometry": {"coordinates":[-80.37972000000001,25.707477],"type":"Point"}
}