{
  "type": "Feature",
  "properties": {
    "addr:full":"1299 E Commercial Blvd Oakland Park FL 33334",
    "addr:housenumber":"1299",
    "addr:postcode":"33334",
    "addr:street":"E Commercial Blvd",
    "iso:country":"US",
    "sg:address":"1299 E Commercial Blvd",
    "sg:city":"Oakland Park",
    "sg:classifiers":[
        {
            "category":"Retail",
            "subcategory":"Repair Shop",
            "type":"Services"
        }
    ],
    "sg:phone":"+1 954 630 1832",
    "sg:postcode":"33334",
    "sg:province":"FL",
    "sg:tags":[
        "scooter",
        "motorcycle",
        "motor"
    ],
    "sg:website":"www.eastcoastchoppers.net",
    "wof:name":"East Coast Choppers",
    "wof:placetype":"venue"
},
  "geometry": {"coordinates":[-80.130757,26.188895],"type":"Point"}
}