{
  "type": "Feature",
  "properties": {
    "iso:country":"US",
    "sg:address":"10734 NW 70th St",
    "sg:city":"Miami",
    "sg:classifiers":[
        {
            "category":"Shopping",
            "type":"Retail Goods"
        }
    ],
    "sg:phone":"+1 305 406 9570",
    "sg:postcode":"33178",
    "sg:province":"FL",
    "sg:tags":[
        "merchandise"
    ],
    "wof:name":"Gipssy & Loxan Corp",
    "wof:placetype":"venue"
},
  "geometry": {"coordinates":[-80.37488399999999,25.83642],"type":"Point"}
}