{
  "type": "Feature",
  "properties": {
    "addr:full":"5622 Julie Dr Panama City FL 32404",
    "addr:housenumber":"5622",
    "addr:postcode":"32404",
    "addr:street":"Julie Dr",
    "iso:country":"US",
    "sg:address":"5622 Julie Dr",
    "sg:city":"Panama City",
    "sg:classifiers":[
        {
            "category":"Organizations",
            "subcategory":"Religious Organization",
            "type":"Services"
        }
    ],
    "sg:phone":"+1 850 769 5067",
    "sg:postcode":"32404",
    "sg:province":"FL",
    "sg:tags":[
        "church"
    ],
    "wof:name":"Our Lady Of The Rosary",
    "wof:placetype":"venue"
},
  "geometry": {"coordinates":[-85.566789,30.24642],"type":"Point"}
}