{
  "type": "Feature",
  "properties": {
    "iso:country":"US",
    "sg:address":"4001 NW Blitchton Rd",
    "sg:city":"Ocala",
    "sg:classifiers":[
        {
            "category":"Wholesale",
            "subcategory":"Fruits & Vegetables",
            "type":"Manufacturing & Wholesale Goods"
        }
    ],
    "sg:phone":"+1 352 369 6464",
    "sg:postcode":"34482",
    "sg:province":"FL",
    "wof:name":"Select Produce",
    "wof:placetype":"venue"
},
  "geometry": {"coordinates":[-82.188844,29.208477],"type":"Point"}
}