{
  "type": "Feature",
  "properties": {
    "iso:country":"US",
    "sg:address":"810 W Wisconsin Ave",
    "sg:city":"Deland",
    "sg:classifiers":[
        {
            "category":"Building & Trades",
            "subcategory":"Landscaping Services",
            "type":"Services"
        }
    ],
    "sg:phone":"+1 386 736 9587",
    "sg:postcode":"32720",
    "sg:province":"FL",
    "sg:tags":[
        "sod",
        "sodding"
    ],
    "wof:name":"Osteeen Sod Farms Inc",
    "wof:placetype":"venue"
},
  "geometry": {"coordinates":[-81.318901,29.031534],"type":"Point"}
}