{
  "type": "Feature",
  "properties": {
    "iso:country":"US",
    "sg:address":"10263 Shadow Run Ct",
    "sg:city":"Punta Gorda",
    "sg:classifiers":[
        {
            "category":"Wholesale",
            "subcategory":"Machinery & Supplies",
            "type":"Manufacturing & Wholesale Goods"
        }
    ],
    "sg:phone":"+1 941 505 7722",
    "sg:postcode":"33955",
    "sg:province":"FL",
    "sg:tags":[
        "equipment",
        "industrial"
    ],
    "wof:name":"Tractel Inc",
    "wof:placetype":"venue"
},
  "geometry": {"coordinates":[-82.021321,26.881447],"type":"Point"}
}