{
  "type": "Feature",
  "properties": {
    "addr:full":"20771 Central Ave E Blountstown FL 32424",
    "addr:postcode":"20771;32424",
    "addr:street":"Central Ave E",
    "iso:country":"US",
    "sg:address":"20771 Central Ave E",
    "sg:city":"Blountstown",
    "sg:classifiers":[
        {
            "category":"Building & Trades",
            "subcategory":"Pest Control",
            "type":"Services"
        }
    ],
    "sg:phone":"+1 850 674 5928",
    "sg:postcode":"32424",
    "sg:province":"FL",
    "wof:name":"Howell Exterminating & Chemical Co",
    "wof:placetype":"venue"
},
  "geometry": {"coordinates":[-85.043493,30.44319],"type":"Point"}
}