{
  "type": "Feature",
  "properties": {
    "iso:country":"US",
    "sg:address":"613 Cedarside Way",
    "sg:city":"Melbourne",
    "sg:classifiers":[
        {
            "category":"Real Estate",
            "subcategory":"Real Estate Agent",
            "type":"Services"
        }
    ],
    "sg:phone":"+1 321 255 8326",
    "sg:postcode":"32940",
    "sg:province":"FL",
    "wof:name":"Nierenberg Team",
    "wof:placetype":"venue"
},
  "geometry": {"coordinates":[-80.68401799999999,28.22178],"type":"Point"}
}