{
  "type": "Feature",
  "properties": {
    "iso:country":"US",
    "sg:address":"14181 SW 143rd Ct",
    "sg:city":"Miami",
    "sg:classifiers":[
        {
            "category":"Arena",
            "subcategory":"Stadium",
            "type":"Entertainment"
        }
    ],
    "sg:phone":"+1 305 256 2001",
    "sg:postcode":"33186",
    "sg:province":"FL",
    "sg:tags":[
        "athletic",
        "stadiums",
        "field"
    ],
    "wof:name":"Titan Field Works",
    "wof:placetype":"venue"
},
  "geometry": {"coordinates":[-80.426013,25.635543],"type":"Point"}
}