{
  "type": "Feature",
  "properties": {
    "iso:country":"US",
    "sg:address":"11531 US Hwy 41",
    "sg:city":"Gibsonton",
    "sg:classifiers":[
        {
            "category":"Building & Trades",
            "subcategory":"Plumbing",
            "type":"Services"
        }
    ],
    "sg:phone":"+1 813 671 2107",
    "sg:postcode":"33534",
    "sg:province":"FL",
    "sg:tags":[
        "air",
        "heating",
        "conditioning",
        "contractor"
    ],
    "wof:name":"Ken Hope Air Conditioning",
    "wof:placetype":"venue"
},
  "geometry": {"coordinates":[-82.381872,27.83456],"type":"Point"}
}