{
  "type": "Feature",
  "properties": {
    "addr:full":"4493 Windjammer Ln Fort Myers FL 33919",
    "addr:housenumber":"4493",
    "addr:postcode":"33919",
    "addr:street":"Windjammer Ln",
    "iso:country":"US",
    "sg:address":"4493 Windjammer Ln",
    "sg:city":"Fort Myers",
    "sg:classifiers":[
        {
            "category":"Professional",
            "type":"Services"
        }
    ],
    "sg:phone":"+1 239 481 0748",
    "sg:postcode":"33919",
    "sg:province":"FL",
    "wof:name":"Guy Dorval",
    "wof:placetype":"venue"
},
  "geometry": {"coordinates":[-81.91674399999999,26.551972],"type":"Point"}
}