{
  "type": "Feature",
  "properties": {
    "iso:country":"US",
    "sg:address":"603 27th St SE",
    "sg:city":"Ruskin",
    "sg:classifiers":[
        {
            "category":"Building & Trades",
            "subcategory":"Landscaping Services",
            "type":"Services"
        }
    ],
    "sg:phone":"+1 813 641 3672",
    "sg:postcode":"33570",
    "sg:province":"FL",
    "sg:tags":[
        "landscape"
    ],
    "wof:name":"Valleycrest Landscape Maint",
    "wof:placetype":"venue"
},
  "geometry": {"coordinates":[-82.39821600000001,27.714001],"type":"Point"}
}