{
  "type": "Feature",
  "properties": {
    "iso:country":"US",
    "sg:address":"6606 Old Main St",
    "sg:city":"New Port Richey",
    "sg:classifiers":[
        {
            "category":"Building & Trades",
            "subcategory":"Landscaping Services",
            "type":"Services"
        }
    ],
    "sg:phone":"+1 727 845 5253",
    "sg:postcode":"34653",
    "sg:province":"FL",
    "sg:tags":[
        "lawn",
        "maintenance",
        "grounds"
    ],
    "wof:name":"Britton Lawn Care Svc",
    "wof:placetype":"venue"
},
  "geometry": {"coordinates":[-82.706644,28.250555],"type":"Point"}
}