{
  "type": "Feature",
  "properties": {
    "iso:country":"US",
    "sg:address":"4000 Hollywood Blvd 485S",
    "sg:city":"Hollywood",
    "sg:classifiers":[
        {
            "category":"Real Estate",
            "subcategory":"Real Estate Services",
            "type":"Services"
        },
        {
            "category":"Real Estate",
            "subcategory":"Real Estate Agent",
            "type":"Services"
        }
    ],
    "sg:phone":"+1 954 549 2400",
    "sg:postcode":"33021",
    "sg:province":"FL",
    "sg:tags":[
        "buyer",
        "management",
        "broker"
    ],
    "wof:name":"Bucci Jhm Realty",
    "wof:placetype":"venue"
},
  "geometry": {"coordinates":[-80.183807,26.011709],"type":"Point"}
}