{
  "type": "Feature",
  "properties": {
    "iso:country":"US",
    "sg:address":"5100 W Cypress St",
    "sg:city":"Tampa",
    "sg:classifiers":[
        {
            "category":"Shopping",
            "subcategory":"Clothing, Apparel, & Fashions",
            "type":"Retail Goods"
        }
    ],
    "sg:phone":"+1 813 282 8338",
    "sg:postcode":"33607",
    "sg:province":"FL",
    "sg:tags":[
        "work",
        "uniform",
        "uniforms-accessories",
        "clothes"
    ],
    "wof:name":"Risse Brothers School Uniforms",
    "wof:placetype":"venue"
},
  "geometry": {"coordinates":[-82.530312,27.952339],"type":"Point"}
}