{
  "type": "Feature",
  "properties": {
    "iso:country":"US",
    "sg:address":"5201 NW 30th Pl",
    "sg:city":"Miami",
    "sg:classifiers":[
        {
            "category":"Building & Trades",
            "subcategory":"Locksmith",
            "type":"Services"
        }
    ],
    "sg:phone":"+1 305 908 5591",
    "sg:postcode":"33142",
    "sg:province":"FL",
    "sg:tags":[
        "key"
    ],
    "wof:name":"0 0 0 0 0 0 0 1 A Locksmith",
    "wof:placetype":"venue"
},
  "geometry": {"coordinates":[-80.245828,25.821915],"type":"Point"}
}