{
  "type": "Feature",
  "properties": {
    "iso:country":"US",
    "sg:address":"12633 White Coral Dr",
    "sg:city":"Wellington",
    "sg:classifiers":[
        {
            "category":"Real Estate",
            "subcategory":"Real Estate Agent",
            "type":"Services"
        }
    ],
    "sg:phone":"+1 561 632 1187",
    "sg:postcode":"33414",
    "sg:province":"FL",
    "wof:name":"Ewan Leslie's Properties",
    "wof:placetype":"venue"
},
  "geometry": {"coordinates":[-80.24271299999999,26.652547],"type":"Point"}
}