{
  "type": "Feature",
  "properties": {
    "iso:country":"US",
    "sg:address":"1500 S Martin Luther King Jr Blvd",
    "sg:city":"Tallahassee",
    "sg:classifiers":[
        {
            "category":"Education",
            "subcategory":"Library",
            "type":"Public Place"
        }
    ],
    "sg:phone":"+1 850 599 3370",
    "sg:postcode":"32307",
    "sg:province":"FL",
    "sg:website":"www.famu.edu/library",
    "wof:name":"S H Coleman Memorial Library",
    "wof:placetype":"venue"
},
  "geometry": {"coordinates":[-84.28560899999999,30.427139],"type":"Point"}
}