{
  "type": "Feature",
  "properties": {
    "iso:country":"US",
    "sg:address":"3541 N Ponce de Leon Blvd",
    "sg:city":"Saint Augustine",
    "sg:classifiers":[
        {
            "category":"Retail",
            "subcategory":"Auto Repair",
            "type":"Services"
        }
    ],
    "sg:phone":"+1 904 824 8090",
    "sg:postcode":"32084",
    "sg:province":"FL",
    "sg:tags":[
        "automotive"
    ],
    "wof:name":"Texaco",
    "wof:placetype":"venue"
},
  "geometry": {"coordinates":[-81.325484,29.924035],"type":"Point"}
}