{
  "type": "Feature",
  "properties": {
    "iso:country":"US",
    "sg:address":"13711 SW 37th Ter",
    "sg:city":"Miami",
    "sg:classifiers":[
        {
            "category":"Professional",
            "type":"Services"
        }
    ],
    "sg:phone":"+1 305 223 8365",
    "sg:postcode":"33175",
    "sg:province":"FL",
    "wof:name":"Ignite Statewide Inc",
    "wof:placetype":"venue"
},
  "geometry": {"coordinates":[-80.416398,25.73352],"type":"Point"}
}