{
  "type": "Feature",
  "properties": {
    "addr:full":"6506 Salerno Rd Fort Pierce FL 34951",
    "addr:housenumber":"6506",
    "addr:postcode":"34951",
    "addr:street":"Salerno Rd",
    "iso:country":"US",
    "sg:address":"6506 Salerno Rd",
    "sg:city":"Fort Pierce",
    "sg:classifiers":[
        {
            "category":"Building & Trades",
            "subcategory":"Construction",
            "type":"Services"
        }
    ],
    "sg:phone":"+1 772 464 3745",
    "sg:postcode":"34951",
    "sg:province":"FL",
    "sg:tags":[
        "nonresidential"
    ],
    "wof:name":"Urban J Matthews Jr",
    "wof:placetype":"venue"
},
  "geometry": {"coordinates":[-80.39401700000001,27.549403],"type":"Point"}
}