{
  "type": "Feature",
  "properties": {
    "addr:full":"4120 NW 26th St Fort Lauderdale FL 33313",
    "addr:housenumber":"4120",
    "addr:postcode":"33313",
    "addr:street":"Nw 26Th St",
    "iso:country":"US",
    "sg:address":"4120 NW 26th St",
    "sg:city":"Fort Lauderdale",
    "sg:classifiers":[
        {
            "category":"Food & Beverages",
            "subcategory":"Groceries & Convenience Stores",
            "type":"Retail Goods"
        }
    ],
    "sg:phone":"+1 954 731 6962",
    "sg:postcode":"33313",
    "sg:province":"FL",
    "wof:name":"Star Food Stores Lauderhill",
    "wof:placetype":"venue"
},
  "geometry": {"coordinates":[-80.204955,26.15876],"type":"Point"}
}