{
  "type": "Feature",
  "properties": {
    "iso:country":"US",
    "sg:address":"711 NW 3rd Ave",
    "sg:city":"Delray Beach",
    "sg:classifiers":[
        {
            "category":"Local Transit",
            "type":"Transportation"
        }
    ],
    "sg:phone":"+1 561 272 5618",
    "sg:postcode":"33444",
    "sg:province":"FL",
    "wof:name":"Kevin Rickard Inc",
    "wof:placetype":"venue"
},
  "geometry": {"coordinates":[-80.07640499999999,26.47379],"type":"Point"}
}