{
  "type": "Feature",
  "properties": {
    "iso:country":"US",
    "sg:address":"201 3rd St SW",
    "sg:city":"Winter Haven",
    "sg:classifiers":[
        {
            "category":"Retail",
            "subcategory":"Auto Repair",
            "type":"Services"
        }
    ],
    "sg:phone":"+1 863 293 2195",
    "sg:postcode":"33880",
    "sg:province":"FL",
    "sg:tags":[
        "repairing",
        "automobile"
    ],
    "wof:name":"Goodyear Auto Svc Ctr",
    "wof:placetype":"venue"
},
  "geometry": {"coordinates":[-81.73060099999999,28.020854],"type":"Point"}
}