{
  "type": "Feature",
  "properties": {
    "addr:full":"1790 Indian Creek Pkwy Jupiter FL 33458",
    "addr:housenumber":"1790",
    "addr:postcode":"33458",
    "addr:street":"Indian Creek Pkwy",
    "iso:country":"US",
    "sg:address":"1790 Indian Creek Pkwy",
    "sg:city":"Jupiter",
    "sg:classifiers":[
        {
            "category":"Health Services",
            "subcategory":"Clinic",
            "type":"Services"
        }
    ],
    "sg:phone":"+1 561 744 7714",
    "sg:postcode":"33458",
    "sg:province":"FL",
    "sg:tags":[
        "home"
    ],
    "wof:name":"Comprehensive Wellness Svc Inc",
    "wof:placetype":"venue"
},
  "geometry": {"coordinates":[-80.124762,26.911729],"type":"Point"}
}