{
  "type": "Feature",
  "properties": {
    "iso:country":"US",
    "sg:address":"126 Tomahawk Dr",
    "sg:city":"Indian Hrbr Bch",
    "sg:classifiers":[
        {
            "category":"Retail",
            "subcategory":"Repair Shop",
            "type":"Services"
        },
        {
            "category":"Building & Trades",
            "subcategory":"Construction",
            "type":"Services"
        }
    ],
    "sg:phone":"+1 321 773 5882",
    "sg:postcode":"32937",
    "sg:province":"FL",
    "sg:tags":[
        "welding",
        "contractor"
    ],
    "wof:name":"Sticks Beachside Welding Inc",
    "wof:placetype":"venue"
},
  "geometry": {"coordinates":[-80.600926,28.160489],"type":"Point"}
}