{
  "type": "Feature",
  "properties": {
    "iso:country":"US",
    "sg:address":"7098 73rd St",
    "sg:city":"Pinellas Park",
    "sg:classifiers":[
        {
            "category":"Building & Trades",
            "subcategory":"Construction",
            "type":"Services"
        }
    ],
    "sg:phone":"+1 727 548 4655",
    "sg:postcode":"33781",
    "sg:province":"FL",
    "sg:tags":[
        "contractor"
    ],
    "wof:name":"A A A Affordable Roofing",
    "wof:placetype":"venue"
},
  "geometry": {"coordinates":[-82.73802000000001,27.835649],"type":"Point"}
}