{
  "type": "Feature",
  "properties": {
    "addr:full":"711 Royal Palm Pl Vero Beach FL 32960",
    "addr:housenumber":"711",
    "addr:postcode":"32960",
    "addr:street":"Royal Palm Pl",
    "iso:country":"US",
    "sg:address":"711 Royal Palm Pl",
    "sg:city":"Vero Beach",
    "sg:classifiers":[
        {
            "category":"Freight",
            "type":"Transportation"
        }
    ],
    "sg:phone":"+1 772 567 2679",
    "sg:postcode":"32960",
    "sg:province":"FL",
    "sg:tags":[
        "operator",
        "trucking"
    ],
    "wof:name":"Gould Trucking Inc",
    "wof:placetype":"venue"
},
  "geometry": {"coordinates":[-80.388222,27.64468],"type":"Point"}
}