{
  "type": "Feature",
  "properties": {
    "iso:country":"US",
    "sg:address":"1600 S Bayshore Ln",
    "sg:city":"Miami",
    "sg:classifiers":[
        {
            "category":"Home & Garden",
            "subcategory":"Carpets & Floor Coverings",
            "type":"Retail Goods"
        }
    ],
    "sg:phone":"+1 786 261 7771",
    "sg:postcode":"33133",
    "sg:province":"FL",
    "wof:name":"Miller Floorings Inc",
    "wof:placetype":"venue"
},
  "geometry": {"coordinates":[-80.222038,25.737195],"type":"Point"}
}