{
  "type": "Feature",
  "properties": {
    "iso:country":"US",
    "sg:address":"3655 N Atlantic Ave",
    "sg:city":"Cocoa Beach",
    "sg:classifiers":[
        {
            "category":"Travel",
            "subcategory":"Hotels & Motels",
            "type":"Entertainment"
        }
    ],
    "sg:phone":"+1 321 783 6868",
    "sg:postcode":"32931",
    "sg:province":"FL",
    "sg:website":"www.qualitysuitescocoabeach.com",
    "wof:name":"Quality Suites Cocoa Beach",
    "wof:placetype":"venue"
},
  "geometry": {"coordinates":[-80.608902,28.351801],"type":"Point"}
}