{
  "type": "Feature",
  "properties": {
    "addr:full":"3199 Suntree Blvd Rockledge FL 32955",
    "addr:housenumber":"3199",
    "addr:postcode":"32955",
    "addr:street":"Suntree Blvd",
    "iso:country":"US",
    "sg:address":"3199 Suntree Blvd",
    "sg:city":"Rockledge",
    "sg:classifiers":[
        {
            "category":"Personal",
            "subcategory":"Beauty Salon",
            "type":"Services"
        }
    ],
    "sg:phone":"+1 321 254 4600",
    "sg:postcode":"32955",
    "sg:province":"FL",
    "wof:name":"Lather Lounge Hair Studio",
    "wof:placetype":"venue"
},
  "geometry": {"coordinates":[-80.675629,28.228689],"type":"Point"}
}