{
  "type": "Feature",
  "properties": {
    "iso:country":"US",
    "sg:address":"717 Opa Locka Blvd",
    "sg:city":"Opa Locka",
    "sg:classifiers":[
        {
            "category":"Health Services",
            "subcategory":"Doctor",
            "type":"Services"
        }
    ],
    "sg:phone":"+1 305 687 7685",
    "sg:postcode":"33054",
    "sg:province":"FL",
    "sg:tags":[
        "medical"
    ],
    "wof:name":"Soul of A Woman Maternity Ctr",
    "wof:placetype":"venue"
},
  "geometry": {"coordinates":[-80.249562,25.89999],"type":"Point"}
}