{
  "type": "Feature",
  "properties": {
    "addr:full":"326 la Salona Ave Arcadia FL 34266",
    "addr:housenumber":"326",
    "addr:postcode":"34266",
    "addr:street":"La Salona Ave",
    "iso:country":"US",
    "sg:address":"326 la Salona Ave",
    "sg:city":"Arcadia",
    "sg:classifiers":[
        {
            "category":"Building & Trades",
            "subcategory":"Construction",
            "type":"Services"
        }
    ],
    "sg:phone":"+1 863 993 0585",
    "sg:postcode":"34266",
    "sg:province":"FL",
    "sg:tags":[
        "general",
        "contractor"
    ],
    "wof:name":"M & M Construction",
    "wof:placetype":"venue"
},
  "geometry": {"coordinates":[-82.491767,27.285881],"type":"Point"}
}