{
  "type": "Feature",
  "properties": {
    "addr:full":"77 Berwick Cir Shalimar FL 32579",
    "addr:housenumber":"77",
    "addr:postcode":"32579",
    "addr:street":"Berwick Cir",
    "iso:country":"US",
    "sg:address":"77 Berwick Cir",
    "sg:city":"Shalimar",
    "sg:classifiers":[
        {
            "category":"Professional",
            "subcategory":"Lawyer & Legal Services",
            "type":"Services"
        }
    ],
    "sg:phone":"+1 850 651 0642",
    "sg:postcode":"32579",
    "sg:province":"FL",
    "sg:tags":[
        "attorney",
        "criminal",
        "law"
    ],
    "wof:name":"John E Freeman Enterprises",
    "wof:placetype":"venue"
},
  "geometry": {"coordinates":[-86.565618,30.446154],"type":"Point"}
}