{
  "type": "Feature",
  "properties": {
    "iso:country":"US",
    "sg:address":"4405 Kelly Rd",
    "sg:city":"Tampa",
    "sg:classifiers":[
        {
            "category":"Social Services",
            "subcategory":"Child Care",
            "type":"Services"
        }
    ],
    "sg:phone":"+1 813 884 5326",
    "sg:postcode":"33615",
    "sg:province":"FL",
    "wof:name":"Sunshine Children's Learning",
    "wof:placetype":"venue"
},
  "geometry": {"coordinates":[-82.564876,27.982079],"type":"Point"}
}