{
  "type": "Feature",
  "properties": {
    "iso:country":"US",
    "sg:address":"1012 Angle Rd",
    "sg:city":"Fort Pierce",
    "sg:classifiers":[
        {
            "category":"Manufacturing",
            "subcategory":"Retail Goods",
            "type":"Manufacturing & Wholesale Goods"
        }
    ],
    "sg:phone":"+1 772 519 1780",
    "sg:postcode":"34947",
    "sg:province":"FL",
    "sg:tags":[
        "manufacturer"
    ],
    "wof:name":"Mike Daniels Citrus Ladders",
    "wof:placetype":"venue"
},
  "geometry": {"coordinates":[-80.36831100000001,27.459642],"type":"Point"}
}