{
  "type": "Feature",
  "properties": {
    "iso:country":"US",
    "sg:address":"1850 SW 8th St Ste 308",
    "sg:city":"Miami",
    "sg:classifiers":[
        {
            "category":"Health Services",
            "subcategory":"Doctor",
            "type":"Services"
        }
    ],
    "sg:phone":"+1 305 649 3362",
    "sg:postcode":"33135",
    "sg:province":"FL",
    "sg:tags":[
        "surgeon",
        "oral"
    ],
    "wof:name":"Mencio George DDS",
    "wof:placetype":"venue"
},
  "geometry": {"coordinates":[-80.225601,25.765499],"type":"Point"}
}