{
  "type": "Feature",
  "properties": {
    "iso:country":"US",
    "sg:address":"5425 Golden Gate Pkwy",
    "sg:city":"Naples",
    "sg:classifiers":[
        {
            "category":"Building & Trades",
            "subcategory":"Construction",
            "type":"Services"
        }
    ],
    "sg:phone":"+1 239 354 4027",
    "sg:postcode":"34116",
    "sg:province":"FL",
    "sg:tags":[
        "contractor"
    ],
    "wof:name":"Tandem Building Co",
    "wof:placetype":"venue"
},
  "geometry": {"coordinates":[-81.715051,26.174619],"type":"Point"}
}