{
  "type": "Feature",
  "properties": {
    "iso:country":"US",
    "sg:address":"6433 Rockingtree Ln",
    "sg:city":"Orlando",
    "sg:classifiers":[
        {
            "category":"Local Transit",
            "type":"Transportation"
        }
    ],
    "sg:phone":"+1 407 355 3196",
    "sg:postcode":"32819",
    "sg:province":"FL",
    "sg:tags":[
        "passenger"
    ],
    "wof:name":"50 USA Group Corp",
    "wof:placetype":"venue"
},
  "geometry": {"coordinates":[-81.49232499999999,28.474113],"type":"Point"}
}