{
  "type": "Feature",
  "properties": {
    "addr:full":"2604 64th Pl N St Petersburg FL 33702",
    "addr:housenumber":"2604",
    "addr:postcode":"33702",
    "addr:street":"64Th Pl N",
    "iso:country":"US",
    "sg:address":"2604 64th Pl N",
    "sg:city":"St Petersburg",
    "sg:classifiers":[
        {
            "category":"Home & Garden",
            "subcategory":"Building Materials",
            "type":"Retail Goods"
        }
    ],
    "sg:phone":"+1 727 521 4721",
    "sg:postcode":"33702",
    "sg:province":"FL",
    "sg:tags":[
        "door"
    ],
    "sg:website":"www.donkiger.com",
    "wof:name":"Don Kiger Door & Trim",
    "wof:placetype":"venue"
},
  "geometry": {"coordinates":[-82.670908,27.830537],"type":"Point"}
}