{
  "type": "Feature",
  "properties": {
    "addr:full":"6869 N 9th Ave Pensacola FL 32504",
    "addr:housenumber":"6869",
    "addr:postcode":"32504",
    "addr:street":"N 9Th Ave",
    "iso:country":"US",
    "sg:address":"6869 N 9th Ave",
    "sg:city":"Pensacola",
    "sg:classifiers":[
        {
            "category":"Restaurant",
            "type":"Food & Drink"
        }
    ],
    "sg:menulink":"http://www.allmenus.com/fl/pensacola/92062-firehouse-subs/menu/",
    "sg:phone":"+1 850 476 6626",
    "sg:postcode":"32504",
    "sg:province":"FL",
    "sg:tags":[
        "wrap",
        "american",
        "sandwich"
    ],
    "wof:name":"Firehouse Subs",
    "wof:placetype":"venue"
},
  "geometry": {"coordinates":[-87.19037899999999,30.494421],"type":"Point"}
}