{
  "type": "Feature",
  "properties": {
    "addr:full":"5365 Stirling Rd Davie FL 33314",
    "addr:housenumber":"5365",
    "addr:postcode":"33314",
    "addr:street":"Stirling Rd",
    "iso:country":"US",
    "sg:address":"5365 Stirling Rd",
    "sg:city":"Davie",
    "sg:classifiers":[
        {
            "category":"Building & Trades",
            "subcategory":"Construction",
            "type":"Services"
        }
    ],
    "sg:phone":"+1 954 587 0520",
    "sg:postcode":"33314",
    "sg:province":"FL",
    "sg:tags":[
        "general",
        "contractor"
    ],
    "wof:name":"Widell Inc",
    "wof:placetype":"venue"
},
  "geometry": {"coordinates":[-80.214777,26.046553],"type":"Point"}
}