{
  "type": "Feature",
  "properties": {
    "iso:country":"US",
    "sg:address":"6840 Pinewood Ln",
    "sg:city":"Punta Gorda",
    "sg:classifiers":[
        {
            "category":"Recreation",
            "type":"Entertainment"
        }
    ],
    "sg:phone":"+1 941 505 4124",
    "sg:postcode":"33982",
    "sg:province":"FL",
    "sg:tags":[
        "riding",
        "academy"
    ],
    "wof:name":"Bridle Brook Stables",
    "wof:placetype":"venue"
},
  "geometry": {"coordinates":[-81.97402599999999,26.958011],"type":"Point"}
}