{
  "type": "Feature",
  "properties": {
    "iso:country":"US",
    "sg:address":"18107 Coyote Creek Ct",
    "sg:city":"Parrish",
    "sg:classifiers":[
        {
            "category":"Home & Garden",
            "subcategory":"Furniture",
            "type":"Retail Goods"
        }
    ],
    "sg:phone":"+1 941 776 5998",
    "sg:postcode":"34219",
    "sg:province":"FL",
    "sg:tags":[
        "store"
    ],
    "wof:name":"Andi Furniture Company Inc",
    "wof:placetype":"venue"
},
  "geometry": {"coordinates":[-82.35602,27.557743],"type":"Point"}
}