{
  "type": "Feature",
  "properties": {
    "iso:country":"US",
    "sg:address":"12061 66th St N",
    "sg:city":"Largo",
    "sg:classifiers":[
        {
            "category":"Shopping",
            "subcategory":"Gifts & Souvenirs",
            "type":"Retail Goods"
        }
    ],
    "sg:phone":"+1 727 539 6134",
    "sg:postcode":"33773",
    "sg:province":"FL",
    "sg:tags":[
        "collectible"
    ],
    "wof:name":"Prestige",
    "wof:placetype":"venue"
},
  "geometry": {"coordinates":[-82.72910899999999,27.880902],"type":"Point"}
}