{
  "type": "Feature",
  "properties": {
    "addr:full":"1040 E 15th St Hialeah FL 33010",
    "addr:housenumber":"1040",
    "addr:postcode":"33010",
    "addr:street":"E 15Th St",
    "iso:country":"US",
    "sg:address":"1040 E 15th St",
    "sg:city":"Hialeah",
    "sg:classifiers":[
        {
            "category":"Shopping",
            "subcategory":"Clothing, Apparel, & Fashions",
            "type":"Retail Goods"
        }
    ],
    "sg:phone":"+1 305 887 1560",
    "sg:postcode":"33010",
    "sg:province":"FL",
    "sg:website":"www.connection.com",
    "wof:name":"D Andre & Assoc Inc",
    "wof:placetype":"venue"
},
  "geometry": {"coordinates":[-80.26063499999999,25.836379],"type":"Point"}
}