{
  "type": "Feature",
  "properties": {
    "iso:country":"US",
    "sg:address":"248 S University Dr",
    "sg:city":"Fort Lauderdale",
    "sg:classifiers":[
        {
            "category":"Restaurant",
            "type":"Food & Drink"
        }
    ],
    "sg:phone":"+1 954 475 1034",
    "sg:postcode":"33324",
    "sg:province":"FL",
    "sg:tags":[
        "eating"
    ],
    "wof:name":"Bagel Host",
    "wof:placetype":"venue"
},
  "geometry": {"coordinates":[-80.24808,26.009048],"type":"Point"}
}