{
  "type": "Feature",
  "properties": {
    "iso:country":"US",
    "sg:address":"630 Talwood Cir",
    "sg:city":"Brandon",
    "sg:classifiers":[
        {
            "category":"Building & Trades",
            "subcategory":"Construction",
            "type":"Services"
        }
    ],
    "sg:phone":"+1 813 621 7281",
    "sg:postcode":"33510",
    "sg:province":"FL",
    "sg:tags":[
        "contractor"
    ],
    "wof:name":"BEC Masonry Inc",
    "wof:placetype":"venue"
},
  "geometry": {"coordinates":[-82.284407,27.94706],"type":"Point"}
}