{
  "type": "Feature",
  "properties": {
    "iso:country":"US",
    "sg:address":"736 NW Buck Hendry Way",
    "sg:city":"Stuart",
    "sg:classifiers":[
        {
            "category":"Home & Garden",
            "subcategory":"Furniture",
            "type":"Retail Goods"
        }
    ],
    "sg:phone":"+1 772 692 5543",
    "sg:postcode":"34994",
    "sg:province":"FL",
    "sg:tags":[
        "store"
    ],
    "wof:name":"Amberwaves Trading Co",
    "wof:placetype":"venue"
},
  "geometry": {"coordinates":[-80.263282,27.224504],"type":"Point"}
}