{
  "type": "Feature",
  "properties": {
    "iso:country":"US",
    "sg:address":"11124 Libby Rd",
    "sg:city":"Spring Hill",
    "sg:classifiers":[
        {
            "category":"Wholesale",
            "subcategory":"Medical Equipment & Supplies",
            "type":"Manufacturing & Wholesale Goods"
        }
    ],
    "sg:phone":"+1 352 684 7040",
    "sg:postcode":"34609",
    "sg:province":"FL",
    "sg:tags":[
        "physician",
        "surgeon"
    ],
    "wof:name":"Hernando Medical Supply",
    "wof:placetype":"venue"
},
  "geometry": {"coordinates":[-82.53891400000001,28.49355],"type":"Point"}
}