{
  "type": "Feature",
  "properties": {
    "addr:full":"2600 Cardena St Miami FL 33134",
    "addr:housenumber":"2600",
    "addr:postcode":"33134",
    "addr:street":"Cardena St",
    "iso:country":"US",
    "sg:address":"2600 Cardena St",
    "sg:city":"Miami",
    "sg:classifiers":[
        {
            "category":"Banks & Credit Unions",
            "subcategory":"Financial Services",
            "type":"Services"
        }
    ],
    "sg:phone":"+1 305 456 6273",
    "sg:postcode":"33134",
    "sg:province":"FL",
    "sg:tags":[
        "investor"
    ],
    "wof:name":"Pyxis Investment Inc",
    "wof:placetype":"venue"
},
  "geometry": {"coordinates":[-80.268711,25.746306],"type":"Point"}
}