{
  "type": "Feature",
  "properties": {
    "iso:country":"US",
    "sg:address":"2451 S Hiawassee Rd",
    "sg:city":"Orlando",
    "sg:classifiers":[
        {
            "category":"Restaurant",
            "type":"Food & Drink"
        }
    ],
    "sg:menulink":"http://www.allmenus.com/fl/winter-garden-ocoee/113811-planet-smoothie/menu/",
    "sg:phone":"+1 407 296 0500",
    "sg:postcode":"32835",
    "sg:province":"FL",
    "sg:tags":[
        "smoothy",
        "juice",
        "american"
    ],
    "wof:name":"Planet Smoothie",
    "wof:placetype":"venue"
},
  "geometry": {"coordinates":[-81.48556600000001,28.514975],"type":"Point"}
}