{
  "type": "Feature",
  "properties": {
    "addr:full":"1077 Cassat Ave Jacksonville FL 32205",
    "addr:housenumber":"1077",
    "addr:postcode":"32205",
    "addr:street":"Cassat Ave",
    "iso:country":"US",
    "sg:address":"1077 Cassat Ave",
    "sg:city":"Jacksonville",
    "sg:classifiers":[
        {
            "category":"Retail",
            "subcategory":"Auto Repair",
            "type":"Services"
        }
    ],
    "sg:phone":"+1 904 384 2696",
    "sg:postcode":"32205",
    "sg:province":"FL",
    "sg:tags":[
        "repairing",
        "automobile",
        "transmission"
    ],
    "wof:name":"Guaranteed Transmissions",
    "wof:placetype":"venue"
},
  "geometry": {"coordinates":[-81.730531,30.307333],"type":"Point"}
}