{
  "type": "Feature",
  "properties": {
    "iso:country":"US",
    "sg:address":"4720 Country Oaks Blvd",
    "sg:city":"Sarasota",
    "sg:classifiers":[
        {
            "category":"Building & Trades",
            "subcategory":"Construction",
            "type":"Services"
        }
    ],
    "sg:phone":"+1 941 358 1458",
    "sg:postcode":"34243",
    "sg:province":"FL",
    "sg:tags":[
        "house"
    ],
    "wof:name":"Gene Flag Construction Inc",
    "wof:placetype":"venue"
},
  "geometry": {"coordinates":[-82.50215799999999,27.393728],"type":"Point"}
}