{
  "type": "Feature",
  "properties": {
    "iso:country":"US",
    "sg:address":"6300 NW 74th Ave",
    "sg:city":"Miami",
    "sg:classifiers":[
        {
            "category":"Professional",
            "subcategory":"Computer Services",
            "type":"Services"
        }
    ],
    "sg:phone":"+1 305 418 4889",
    "sg:postcode":"33166",
    "sg:province":"FL",
    "sg:tags":[
        "repair"
    ],
    "sg:website":"www.dataconcepts.net",
    "wof:name":"Data Concepts",
    "wof:placetype":"venue"
},
  "geometry": {"coordinates":[-80.318197,25.831208],"type":"Point"}
}