{
  "type": "Feature",
  "properties": {
    "addr:full":"928 Limpet Dr Sanibel FL 33957",
    "addr:housenumber":"928",
    "addr:postcode":"33957",
    "addr:street":"Limpet Dr",
    "iso:country":"US",
    "sg:address":"928 Limpet Dr",
    "sg:city":"Sanibel",
    "sg:classifiers":[
        {
            "category":"Farming",
            "subcategory":"Farm & Veterinary Services",
            "type":"Manufacturing & Wholesale Goods"
        }
    ],
    "sg:phone":"+1 239 472 9170",
    "sg:postcode":"33957",
    "sg:province":"FL",
    "sg:tags":[
        "labor",
        "contractor"
    ],
    "wof:name":"J&J Lo Inc",
    "wof:placetype":"venue"
},
  "geometry": {"coordinates":[-82.03376400000001,26.451016],"type":"Point"}
}