{
  "type": "Feature",
  "properties": {
    "iso:country":"US",
    "sg:address":"105 Dunbar Ave",
    "sg:city":"Oldsmar",
    "sg:classifiers":[
        {
            "category":"Building & Trades",
            "subcategory":"Construction",
            "type":"Services"
        }
    ],
    "sg:phone":"+1 813 818 4422",
    "sg:postcode":"34677",
    "sg:province":"FL",
    "sg:tags":[
        "roofing",
        "contractor"
    ],
    "wof:name":"TNT Roofing Inc",
    "wof:placetype":"venue"
},
  "geometry": {"coordinates":[-82.658193,28.041591],"type":"Point"}
}