{
  "type": "Feature",
  "properties": {
    "iso:country":"US",
    "sg:address":"17131 NE 6th Ave",
    "sg:city":"Miami",
    "sg:classifiers":[
        {
            "category":"Professional",
            "subcategory":"Secretarial Services",
            "type":"Services"
        }
    ],
    "sg:phone":"+1 305 770 2201",
    "sg:postcode":"33162",
    "sg:province":"FL",
    "wof:name":"Unique Office Services Inc",
    "wof:placetype":"venue"
},
  "geometry": {"coordinates":[-80.18841500000001,25.933458],"type":"Point"}
}