{
  "type": "Feature",
  "properties": {
    "iso:country":"US",
    "sg:address":"309 Aulin Ave Ste 100",
    "sg:city":"Oviedo",
    "sg:classifiers":[
        {
            "category":"Real Estate",
            "subcategory":"Real Estate Agent",
            "type":"Services"
        }
    ],
    "sg:phone":"+1 407 366 4000",
    "sg:postcode":"32765",
    "sg:province":"FL",
    "wof:name":"Soup Line Properties",
    "wof:placetype":"venue"
},
  "geometry": {"coordinates":[-81.21883,28.665722],"type":"Point"}
}