{
  "type": "Feature",
  "properties": {
    "addr:full":"2091 N Stewart St Kissimmee FL 34746",
    "addr:housenumber":"2091",
    "addr:postcode":"34746",
    "addr:street":"N Stewart St",
    "iso:country":"US",
    "sg:address":"2091 N Stewart St",
    "sg:city":"Kissimmee",
    "sg:classifiers":[
        {
            "category":"Organizations",
            "subcategory":"Religious Organization",
            "type":"Services"
        }
    ],
    "sg:phone":"+1 407 870 2772",
    "sg:postcode":"34746",
    "sg:province":"FL",
    "wof:name":"Word & Wordship International",
    "wof:placetype":"venue"
},
  "geometry": {"coordinates":[-81.430088,28.212357],"type":"Point"}
}