{
  "type": "Feature",
  "properties": {
    "iso:country":"US",
    "sg:address":"6200 S Dixie Hwy",
    "sg:city":"West Palm Beach",
    "sg:classifiers":[
        {
            "category":"Home & Garden",
            "subcategory":"Furniture",
            "type":"Retail Goods"
        }
    ],
    "sg:phone":"+1 561 586 0303",
    "sg:postcode":"33405",
    "sg:province":"FL",
    "wof:name":"Park Furniture & Interiors",
    "wof:placetype":"venue"
},
  "geometry": {"coordinates":[-80.05588400000001,26.658759],"type":"Point"}
}