{
  "type": "Feature",
  "properties": {
    "addr:full":"734 NW 75th St Miami FL 33150",
    "addr:housenumber":"734",
    "addr:postcode":"33150",
    "addr:street":"Nw 75Th St",
    "iso:country":"US",
    "sg:address":"734 NW 75th St",
    "sg:city":"Miami",
    "sg:classifiers":[
        {
            "category":"Wholesale",
            "subcategory":"Scrap",
            "type":"Manufacturing & Wholesale Goods"
        }
    ],
    "sg:phone":"+1 305 836 8853",
    "sg:postcode":"33150",
    "sg:province":"FL",
    "sg:tags":[
        "aircraft",
        "salvage"
    ],
    "wof:name":"Eddie Ramsey Metal & Alloy",
    "wof:placetype":"venue"
},
  "geometry": {"coordinates":[-80.210859,25.843243],"type":"Point"}
}