{
  "type": "Feature",
  "properties": {
    "iso:country":"US",
    "sg:address":"417 NE 6th Ave",
    "sg:city":"Boynton Beach",
    "sg:classifiers":[
        {
            "category":"Retail",
            "subcategory":"Auto Repair",
            "type":"Services"
        }
    ],
    "sg:phone":"+1 561 369 4356",
    "sg:postcode":"33435",
    "sg:province":"FL",
    "sg:tags":[
        "body",
        "automobile",
        "painting"
    ],
    "wof:name":"Eastern Auto Body & Glass",
    "wof:placetype":"venue"
},
  "geometry": {"coordinates":[-80.059231,26.532699],"type":"Point"}
}