{
  "type": "Feature",
  "properties": {
    "addr:full":"1111 Lincoln Rd Miami Beach FL 33139",
    "addr:housenumber":"1111",
    "addr:postcode":"33139",
    "addr:street":"Lincoln Rd",
    "iso:country":"US",
    "sg:address":"1111 Lincoln Rd",
    "sg:city":"Miami Beach",
    "sg:classifiers":[
        {
            "category":"Banks & Credit Unions",
            "subcategory":"Bank",
            "type":"Services"
        }
    ],
    "sg:phone":"+1 305 674 5200",
    "sg:postcode":"33139",
    "sg:province":"FL",
    "sg:website":"www.suntrust.com",
    "wof:name":"Suntrust",
    "wof:placetype":"venue"
},
  "geometry": {"coordinates":[-80.14009900000001,25.790501],"type":"Point"}
}