{
  "type": "Feature",
  "properties": {
    "iso:country":"US",
    "sg:address":"12864 Biscayne Blvd.",
    "sg:city":"North Miami",
    "sg:classifiers":[
        {
            "category":"Building & Trades",
            "subcategory":"Cleaning & Sanitation",
            "type":"Services"
        }
    ],
    "sg:phone":"+1 866 463 0825",
    "sg:postcode":"33181",
    "sg:province":"FL",
    "sg:tags":[
        "carpet"
    ],
    "sg:website":"www.usafloorcare.com",
    "wof:name":"USA Floor Care",
    "wof:placetype":"venue"
},
  "geometry": {"coordinates":[-80.162235,25.894703],"type":"Point"}
}