{
  "type": "Feature",
  "properties": {
    "iso:country":"US",
    "sg:address":"6210 NW 173rd St",
    "sg:city":"Hialeah",
    "sg:classifiers":[
        {
            "category":"Building & Trades",
            "subcategory":"Construction",
            "type":"Services"
        }
    ],
    "sg:phone":"+1 305 823 7675",
    "sg:postcode":"33015",
    "sg:province":"FL",
    "sg:tags":[
        "floor",
        "laying",
        "contractor"
    ],
    "wof:name":"Lias Flooring Co",
    "wof:placetype":"venue"
},
  "geometry": {"coordinates":[-80.300315,25.931172],"type":"Point"}
}