{
  "type": "Feature",
  "properties": {
    "iso:country":"US",
    "sg:address":"433 Harrison Ave",
    "sg:city":"Panama City",
    "sg:classifiers":[
        {
            "category":"Professional",
            "subcategory":"Employment Agencies",
            "type":"Services"
        }
    ],
    "sg:phone":"+1 850 784 1680",
    "sg:postcode":"32401",
    "sg:province":"FL",
    "sg:tags":[
        "consultant",
        "search",
        "executive"
    ],
    "wof:name":"Cantrell & Associates",
    "wof:placetype":"venue"
},
  "geometry": {"coordinates":[-85.660464,30.156452],"type":"Point"}
}