{
  "type": "Feature",
  "properties": {
    "iso:country":"US",
    "sg:address":"220 E Central Pkwy",
    "sg:city":"Altamonte Springs",
    "sg:classifiers":[
        {
            "category":"Professional",
            "subcategory":"Research",
            "type":"Services"
        }
    ],
    "sg:phone":"+1 407 741 5300",
    "sg:postcode":"32701",
    "sg:province":"FL",
    "sg:tags":[
        "trader",
        "company"
    ],
    "wof:name":"I N T L Trader Company Inc",
    "wof:placetype":"venue"
},
  "geometry": {"coordinates":[-81.383471,28.669111],"type":"Point"}
}