{
  "type": "Feature",
  "properties": {
    "iso:country":"US",
    "sg:address":"1467 Classic Dr",
    "sg:city":"Holiday",
    "sg:classifiers":[
        {
            "category":"Building & Trades",
            "subcategory":"Construction",
            "type":"Services"
        }
    ],
    "sg:phone":"+1 727 364 6022",
    "sg:postcode":"34691",
    "sg:province":"FL",
    "sg:tags":[
        "restoration",
        "cleaning",
        "patio",
        "deck"
    ],
    "wof:name":"Raymond Leighs Pressure Clean",
    "wof:placetype":"venue"
},
  "geometry": {"coordinates":[-82.755427,28.179075],"type":"Point"}
}