{
  "type": "Feature",
  "properties": {
    "addr:full":"1006 N Woodland Blvd Ste A Deland FL 32720",
    "addr:housenumber":"1006",
    "addr:postcode":"32720",
    "addr:street":"N Woodland Blvd Ste A",
    "iso:country":"US",
    "sg:address":"1006 N Woodland Blvd Ste A",
    "sg:city":"Deland",
    "sg:classifiers":[
        {
            "category":"Professional",
            "subcategory":"Accounting & Tax Preparation",
            "type":"Services"
        }
    ],
    "sg:phone":"+1 386 734 9441",
    "sg:postcode":"32720",
    "sg:province":"FL",
    "sg:tags":[
        "accountant"
    ],
    "wof:name":"Teal Parke S CPA",
    "wof:placetype":"venue"
},
  "geometry": {"coordinates":[-81.30410000000001,29.044901],"type":"Point"}
}