{
  "type": "Feature",
  "properties": {
    "iso:country":"US",
    "sg:address":"401 Winston Ave",
    "sg:city":"Lake Wales",
    "sg:classifiers":[
        {
            "category":"Real Estate",
            "subcategory":"Real Estate Operator",
            "type":"Services"
        }
    ],
    "sg:phone":"+1 863 676 9213",
    "sg:postcode":"33853",
    "sg:province":"FL",
    "sg:tags":[
        "apartment"
    ],
    "wof:name":"Orangemont Village",
    "wof:placetype":"venue"
},
  "geometry": {"coordinates":[-81.58342399999999,27.886709],"type":"Point"}
}