{
  "type": "Feature",
  "properties": {
    "iso:country":"US",
    "sg:address":"1690 US Hwy 1 S",
    "sg:city":"St Augustine",
    "sg:classifiers":[
        {
            "category":"Real Estate",
            "subcategory":"Real Estate Services",
            "type":"Services"
        }
    ],
    "sg:phone":"+1 904 797 5077",
    "sg:postcode":"32084",
    "sg:province":"FL",
    "sg:tags":[
        "company",
        "title"
    ],
    "wof:name":"First American Title Co",
    "wof:placetype":"venue"
},
  "geometry": {"coordinates":[-81.32311199999999,29.870847],"type":"Point"}
}