{
  "type": "Feature",
  "properties": {
    "addr:full":"3300 el Jardin Dr Hollywood FL 33024",
    "addr:housenumber":"3300",
    "addr:postcode":"33024",
    "addr:street":"El Jardin Dr",
    "iso:country":"US",
    "sg:address":"3300 el Jardin Dr",
    "sg:city":"Hollywood",
    "sg:classifiers":[
        {
            "category":"Real Estate",
            "subcategory":"Real Estate Operator",
            "type":"Services"
        }
    ],
    "sg:phone":"+1 954 437 6110",
    "sg:postcode":"33024",
    "sg:province":"FL",
    "sg:tags":[
        "apartment"
    ],
    "wof:name":"El Jardin Apartments",
    "wof:placetype":"venue"
},
  "geometry": {"coordinates":[-80.23931,26.041649],"type":"Point"}
}