{
  "type": "Feature",
  "properties": {
    "iso:country":"US",
    "sg:address":"5342 W Crenshaw St",
    "sg:city":"Tampa",
    "sg:classifiers":[
        {
            "category":"Retail",
            "subcategory":"Auto Repair",
            "type":"Services"
        }
    ],
    "sg:phone":"+1 813 870 2430",
    "sg:postcode":"33634",
    "sg:province":"FL",
    "sg:tags":[
        "repairing",
        "automobile"
    ],
    "wof:name":"Hillsboro Tire & Wheel Inc",
    "wof:placetype":"venue"
},
  "geometry": {"coordinates":[-82.54107399999999,28.015002],"type":"Point"}
}