{
  "type": "Feature",
  "properties": {
    "addr:full":"322 Oregon St Hollywood FL 33019",
    "addr:housenumber":"322",
    "addr:postcode":"33019",
    "addr:street":"Oregon St",
    "iso:country":"US",
    "sg:address":"322 Oregon St",
    "sg:city":"Hollywood",
    "sg:classifiers":[
        {
            "category":"Travel",
            "subcategory":"Hotels & Motels",
            "type":"Entertainment"
        }
    ],
    "sg:phone":"+1 954 920 0490",
    "sg:postcode":"33019",
    "sg:province":"FL",
    "wof:name":"Southwinds Motel",
    "wof:placetype":"venue"
},
  "geometry": {"coordinates":[-80.11766299999999,26.008744],"type":"Point"}
}