{
  "type": "Feature",
  "properties": {
    "iso:country":"US",
    "sg:address":"4690 Woodstock Rd",
    "sg:city":"St James City",
    "sg:classifiers":[
        {
            "category":"Organizations",
            "subcategory":"Religious Organization",
            "type":"Services"
        }
    ],
    "sg:phone":"+1 239 283 2553",
    "sg:postcode":"33956",
    "sg:province":"FL",
    "sg:tags":[
        "church"
    ],
    "sg:website":"www.jdkministries.com",
    "wof:name":"John David Kirby Ministries",
    "wof:placetype":"venue"
},
  "geometry": {"coordinates":[-82.105587,26.582406],"type":"Point"}
}