{
  "type": "Feature",
  "properties": {
    "iso:country":"US",
    "sg:address":"9601 Greenpointe Dr",
    "sg:city":"Tampa",
    "sg:classifiers":[
        {
            "category":"Marine",
            "type":"Transportation"
        }
    ],
    "sg:phone":"+1 813 920 8754",
    "sg:postcode":"33626",
    "sg:province":"FL",
    "sg:tags":[
        "operations",
        "charter",
        "boat"
    ],
    "wof:name":"Delamer Marine Properties LLC",
    "wof:placetype":"venue"
},
  "geometry": {"coordinates":[-82.616861,28.042184],"type":"Point"}
}