{
  "type": "Feature",
  "properties": {
    "iso:country":"US",
    "sg:address":"7209 SW 59th Ave",
    "sg:city":"South Miami",
    "sg:classifiers":[
        {
            "category":"Ice Cream",
            "type":"Food & Drink"
        }
    ],
    "sg:phone":"+1 305 740 0488",
    "sg:postcode":"33143",
    "sg:province":"FL",
    "sg:tags":[
        "frozen",
        "yogurt"
    ],
    "sg:website":"www.yogenfruz.com",
    "wof:name":"Yogen Fruz",
    "wof:placetype":"venue"
},
  "geometry": {"coordinates":[-80.28928500000001,25.704234],"type":"Point"}
}