{
  "type": "Feature",
  "properties": {
    "iso:country":"US",
    "sg:address":"3001 Seminole Rd",
    "sg:city":"St Cloud",
    "sg:classifiers":[
        {
            "category":"Wholesale",
            "subcategory":"Plants",
            "type":"Manufacturing & Wholesale Goods"
        }
    ],
    "sg:phone":"+1 407 892 1306",
    "sg:postcode":"34772",
    "sg:province":"FL",
    "sg:tags":[
        "nursery",
        "tree"
    ],
    "wof:name":"Pennington Nursery & Sod Svc",
    "wof:placetype":"venue"
},
  "geometry": {"coordinates":[-81.366871,28.211858],"type":"Point"}
}