{
  "type": "Feature",
  "properties": {
    "iso:country":"US",
    "sg:address":"2120 S Ridgewood Ave",
    "sg:city":"Edgewater",
    "sg:classifiers":[
        {
            "category":"Shopping",
            "subcategory":"Hobbies, Toys, & Games",
            "type":"Retail Goods"
        },
        {
            "category":"Building & Trades",
            "subcategory":"Construction",
            "type":"Services"
        }
    ],
    "sg:phone":"+1 386 428 0203",
    "sg:postcode":"32141",
    "sg:province":"FL",
    "sg:tags":[
        "glass",
        "product",
        "ceramic",
        "contractor",
        "mfg"
    ],
    "wof:name":"Blue Lantern Ceramic Studio",
    "wof:placetype":"venue"
},
  "geometry": {"coordinates":[-80.89252500000001,28.966949],"type":"Point"}
}