{
  "type": "Feature",
  "properties": {
    "iso:country":"US",
    "sg:address":"1100 Sunset Strip",
    "sg:city":"Sunrise",
    "sg:classifiers":[
        {
            "category":"Retail",
            "subcategory":"Driving School",
            "type":"Services"
        }
    ],
    "sg:phone":"+1 954 306 8252",
    "sg:postcode":"33313",
    "sg:province":"FL",
    "sg:tags":[
        "instruction",
        "traffic"
    ],
    "wof:name":"Protect Your Priviledge",
    "wof:placetype":"venue"
},
  "geometry": {"coordinates":[-80.23144000000001,26.13749],"type":"Point"}
}