{
  "type": "Feature",
  "properties": {
    "addr:full":"270 Tamiami Trl N Naples FL 34102",
    "addr:housenumber":"270",
    "addr:postcode":"34102",
    "addr:street":"Tamiami Trl N",
    "iso:country":"US",
    "sg:address":"270 Tamiami Trl N",
    "sg:city":"Naples",
    "sg:classifiers":[
        {
            "category":"Health Services",
            "subcategory":"Doctor",
            "type":"Services"
        }
    ],
    "sg:phone":"+1 239 261 0926",
    "sg:postcode":"34102",
    "sg:province":"FL",
    "sg:tags":[
        "physician",
        "surgeon"
    ],
    "wof:name":"Gustavo Medina MD",
    "wof:placetype":"venue"
},
  "geometry": {"coordinates":[-81.795922,26.150455],"type":"Point"}
}