{
  "type": "Feature",
  "properties": {
    "addr:full":"15826 Country Lake Dr Tampa FL 33624",
    "addr:housenumber":"15826",
    "addr:postcode":"33624",
    "addr:street":"Country Lake Dr",
    "iso:country":"US",
    "sg:address":"15826 Country Lake Dr",
    "sg:city":"Tampa",
    "sg:classifiers":[
        {
            "category":"Professional",
            "subcategory":"Management & Consulting",
            "type":"Services"
        }
    ],
    "sg:phone":"+1 813 269 8897",
    "sg:postcode":"33624",
    "sg:province":"FL",
    "sg:tags":[
        "consultant",
        "business"
    ],
    "wof:name":"Echo Management Group",
    "wof:placetype":"venue"
},
  "geometry": {"coordinates":[-82.53158000000001,28.0964],"type":"Point"}
}