{
  "type": "Feature",
  "properties": {
    "iso:country":"US",
    "sg:address":"4446 Wilkinson Dr",
    "sg:city":"Lake Worth",
    "sg:classifiers":[
        {
            "category":"Shopping",
            "subcategory":"Computers & Home Electronics",
            "type":"Retail Goods"
        }
    ],
    "sg:phone":"+1 561 649 6616",
    "sg:postcode":"33461",
    "sg:province":"FL",
    "wof:name":"Lethal PC",
    "wof:placetype":"venue"
},
  "geometry": {"coordinates":[-80.10074299999999,26.613164],"type":"Point"}
}