{
  "type": "Feature",
  "properties": {
    "addr:full":"10707 Roundview Ln Tampa FL 33624",
    "addr:postcode":"10707;33624",
    "addr:street":"Roundview Ln",
    "iso:country":"US",
    "sg:address":"10707 Roundview Ln",
    "sg:city":"Tampa",
    "sg:classifiers":[
        {
            "category":"Building & Trades",
            "subcategory":"Landscaping Services",
            "type":"Services"
        }
    ],
    "sg:phone":"+1 813 968 3633",
    "sg:postcode":"33624",
    "sg:province":"FL",
    "wof:name":"Larry S Whaley",
    "wof:placetype":"venue"
},
  "geometry": {"coordinates":[-82.51747899999999,28.046626],"type":"Point"}
}