{
  "type": "Feature",
  "properties": {
    "iso:country":"US",
    "sg:address":"9965 San Jose Blvd",
    "sg:city":"Jacksonville",
    "sg:classifiers":[
        {
            "category":"Personal",
            "subcategory":"Beauty Salon",
            "type":"Services"
        }
    ],
    "sg:phone":"+1 904 262 9771",
    "sg:postcode":"32257",
    "sg:province":"FL",
    "wof:name":"Astor Place Of Mandarin",
    "wof:placetype":"venue"
},
  "geometry": {"coordinates":[-81.620377,30.198815],"type":"Point"}
}