{
  "type": "Feature",
  "properties": {
    "iso:country":"US",
    "sg:address":"1550 Eastbrook Dr",
    "sg:city":"Sarasota",
    "sg:classifiers":[
        {
            "category":"Manufacturing",
            "subcategory":"Printing",
            "type":"Manufacturing & Wholesale Goods"
        }
    ],
    "sg:phone":"+1 941 922 6861",
    "sg:postcode":"34231",
    "sg:province":"FL",
    "sg:tags":[
        "publishing"
    ],
    "wof:name":"Dodson Publishing",
    "wof:placetype":"venue"
},
  "geometry": {"coordinates":[-82.53401700000001,27.294961],"type":"Point"}
}