{
  "type": "Feature",
  "properties": {
    "addr:full":"2601 Pickettville Rd Jacksonville FL 32220",
    "addr:housenumber":"2601",
    "addr:postcode":"32220",
    "addr:street":"Pickettville Rd",
    "iso:country":"US",
    "sg:address":"2601 Pickettville Rd",
    "sg:city":"Jacksonville",
    "sg:classifiers":[
        {
            "category":"Building & Trades",
            "subcategory":"Electrical",
            "type":"Services"
        }
    ],
    "sg:phone":"+1 904 786 3420",
    "sg:postcode":"32220",
    "sg:province":"FL",
    "sg:tags":[
        "electrician"
    ],
    "wof:name":"D & W Electric Co Inc",
    "wof:placetype":"venue"
},
  "geometry": {"coordinates":[-81.764647,30.354667],"type":"Point"}
}