{
  "type": "Feature",
  "properties": {
    "addr:full":"25706 US Hwy 19 Clearwater FL 33763",
    "addr:postcode":"25706;33763",
    "addr:street":"Us Hwy 19",
    "iso:country":"US",
    "sg:address":"25706 US Hwy 19",
    "sg:city":"Clearwater",
    "sg:classifiers":[
        {
            "category":"Retail",
            "subcategory":"Auto Rental",
            "type":"Services"
        }
    ],
    "sg:phone":"+1 727 723 8661",
    "sg:postcode":"33763",
    "sg:province":"FL",
    "sg:tags":[
        "renting",
        "automobile"
    ],
    "wof:name":"Hertz Rent A Car",
    "wof:placetype":"venue"
},
  "geometry": {"coordinates":[-82.73045500000001,28.007885],"type":"Point"}
}