{
  "type": "Feature",
  "properties": {
    "iso:country":"US",
    "sg:address":"850 Land Ave",
    "sg:city":"Longwood",
    "sg:classifiers":[
        {
            "category":"Building & Trades",
            "subcategory":"Construction",
            "type":"Services"
        }
    ],
    "sg:phone":"+1 407 265 1893",
    "sg:postcode":"32750",
    "sg:province":"FL",
    "sg:tags":[
        "carpentry",
        "contractor"
    ],
    "wof:name":"Luis Avila Frame Met & Drywall",
    "wof:placetype":"venue"
},
  "geometry": {"coordinates":[-81.330966,28.707441],"type":"Point"}
}