{
  "type": "Feature",
  "properties": {
    "addr:full":"320 Tulip Ln Melbourne FL 32901",
    "addr:housenumber":"320",
    "addr:postcode":"32901",
    "addr:street":"Tulip Ln",
    "iso:country":"US",
    "sg:address":"320 Tulip Ln",
    "sg:city":"Melbourne",
    "sg:classifiers":[
        {
            "category":"Shopping",
            "subcategory":"Bicycles & Sporting Goods",
            "type":"Retail Goods"
        }
    ],
    "sg:phone":"+1 321 726 8360",
    "sg:postcode":"32901",
    "sg:province":"FL",
    "wof:name":"Sport Net Inc",
    "wof:placetype":"venue"
},
  "geometry": {"coordinates":[-80.616049,28.095711],"type":"Point"}
}