{
  "type": "Feature",
  "properties": {
    "addr:full":"7570 NW 14th St Miami FL 33126",
    "addr:housenumber":"7570",
    "addr:postcode":"33126",
    "addr:street":"Nw 14Th St",
    "iso:country":"US",
    "sg:address":"7570 NW 14th St",
    "sg:city":"Miami",
    "sg:classifiers":[
        {
            "category":"Professional",
            "subcategory":"Management & Consulting",
            "type":"Services"
        }
    ],
    "sg:phone":"+1 786 845 7166",
    "sg:postcode":"33126",
    "sg:province":"FL",
    "sg:tags":[
        "roofing",
        "consultant"
    ],
    "wof:name":"Service CBD",
    "wof:placetype":"venue"
},
  "geometry": {"coordinates":[-80.32005700000001,25.786196],"type":"Point"}
}