{
  "type": "Feature",
  "properties": {
    "iso:country":"US",
    "sg:address":"5075 Tamiami Trl",
    "sg:city":"Naples",
    "sg:classifiers":[
        {
            "category":"Building & Trades",
            "subcategory":"Construction",
            "type":"Services"
        }
    ],
    "sg:phone":"+1 239 417 1888",
    "sg:postcode":"34113",
    "sg:province":"FL",
    "sg:tags":[
        "painting",
        "contractor"
    ],
    "wof:name":"Custom Quality Painting Inc",
    "wof:placetype":"venue"
},
  "geometry": {"coordinates":[-81.7484,26.107807],"type":"Point"}
}