{
  "type": "Feature",
  "properties": {
    "addr:full":"12518 River Birch Dr Riverview FL 33569",
    "addr:housenumber":"12518",
    "addr:postcode":"33569",
    "addr:street":"River Birch Dr",
    "iso:country":"US",
    "sg:address":"12518 River Birch Dr",
    "sg:city":"Riverview",
    "sg:classifiers":[
        {
            "category":"Health Services",
            "subcategory":"Clinic",
            "type":"Services"
        },
        {
            "category":"Health Services",
            "subcategory":"Medical Lab",
            "type":"Services"
        }
    ],
    "sg:phone":"+1 813 671 3155",
    "sg:postcode":"33569",
    "sg:province":"FL",
    "sg:tags":[
        "placement",
        "for",
        "tissue",
        "human",
        "banks",
        "eye"
    ],
    "wof:name":"Interntional Sight Restoration",
    "wof:placetype":"venue"
},
  "geometry": {"coordinates":[-82.286676,27.864643],"type":"Point"}
}