{
  "type": "Feature",
  "properties": {
    "iso:country":"US",
    "sg:address":"1103 Ferdinand St",
    "sg:city":"Miami",
    "sg:classifiers":[
        {
            "category":"Banks & Credit Unions",
            "subcategory":"Bank",
            "type":"Services"
        }
    ],
    "sg:phone":"+1 305 444 5546",
    "sg:postcode":"33134",
    "sg:province":"FL",
    "sg:tags":[
        "broker",
        "mortgage"
    ],
    "wof:name":"Mortgage Providers Group Inc",
    "wof:placetype":"venue"
},
  "geometry": {"coordinates":[-80.285393,25.760304],"type":"Point"}
}