{
  "type": "Feature",
  "properties": {
    "addr:full":"10302 Southside Blvd Jacksonville FL 32256",
    "addr:housenumber":"10302",
    "addr:postcode":"32256",
    "addr:street":"Southside Blvd",
    "iso:country":"US",
    "sg:address":"10302 Southside Blvd",
    "sg:city":"Jacksonville",
    "sg:classifiers":[
        {
            "category":"Retail",
            "subcategory":"Portrait Studio",
            "type":"Services"
        },
        {
            "category":"Professional",
            "subcategory":"Art Services",
            "type":"Services"
        }
    ],
    "sg:phone":"+1 904 363 9283",
    "sg:postcode":"32256",
    "sg:province":"FL",
    "sg:tags":[
        "rental",
        "photographers-portrait",
        "photographic",
        "darkroom"
    ],
    "wof:name":"Sears Portrait Studio",
    "wof:placetype":"venue"
},
  "geometry": {"coordinates":[-81.55175800000001,30.180251],"type":"Point"}
}