{
  "type": "Feature",
  "properties": {
    "iso:country":"US",
    "sg:address":"1000 Co Rd 722",
    "sg:city":"Webster",
    "sg:classifiers":[
        {
            "category":"Utilities",
            "subcategory":"Cable",
            "type":"Services"
        }
    ],
    "sg:phone":"+1 352 793 3946",
    "sg:postcode":"33597",
    "sg:province":"FL",
    "sg:tags":[
        "television"
    ],
    "wof:name":"Harley Cable By Renay Harley",
    "wof:placetype":"venue"
},
  "geometry": {"coordinates":[-82.08666100000001,28.631984],"type":"Point"}
}