{
  "type": "Feature",
  "properties": {
    "iso:country":"US",
    "sg:address":"2405 Seattle Slew Dr",
    "sg:city":"Sarasota",
    "sg:classifiers":[
        {
            "category":"Building & Trades",
            "subcategory":"Electrical",
            "type":"Services"
        }
    ],
    "sg:phone":"+1 941 330 1299",
    "sg:postcode":"34240",
    "sg:province":"FL",
    "sg:tags":[
        "electric",
        "contractor"
    ],
    "wof:name":"Shark Electric",
    "wof:placetype":"venue"
},
  "geometry": {"coordinates":[-82.441695,27.310884],"type":"Point"}
}