{
  "type": "Feature",
  "properties": {
    "addr:full":"3995 E Dano St Inverness FL 34453",
    "addr:housenumber":"3995",
    "addr:postcode":"34453",
    "addr:street":"E Dano St",
    "iso:country":"US",
    "sg:address":"3995 E Dano St",
    "sg:city":"Inverness",
    "sg:classifiers":[
        {
            "category":"Communications",
            "subcategory":"Film & Video Production",
            "type":"Services"
        }
    ],
    "sg:phone":"+1 352 344 2947",
    "sg:postcode":"34453",
    "sg:province":"FL",
    "sg:tags":[
        "motion"
    ],
    "wof:name":"Diversified Video Productions",
    "wof:placetype":"venue"
},
  "geometry": {"coordinates":[-82.368398,28.86498],"type":"Point"}
}