{
  "type": "Feature",
  "properties": {
    "iso:country":"US",
    "sg:address":"13905 W Dixie Hwy",
    "sg:city":"North Miami",
    "sg:classifiers":[
        {
            "category":"Restaurant",
            "type":"Food & Drink"
        }
    ],
    "sg:phone":"+1 305 892 0606",
    "sg:postcode":"33161",
    "sg:province":"FL",
    "sg:tags":[
        "pizza"
    ],
    "wof:name":"Festive Pizza Ltd Inc",
    "wof:placetype":"venue"
},
  "geometry": {"coordinates":[-80.17449999999999,25.9042],"type":"Point"}
}