{
  "type": "Feature",
  "properties": {
    "iso:country":"US",
    "sg:address":"119 NW 26th Ave",
    "sg:city":"Cape Coral",
    "sg:classifiers":[
        {
            "category":"Building & Trades",
            "subcategory":"Construction",
            "type":"Services"
        }
    ],
    "sg:phone":"+1 239 691 1309",
    "sg:postcode":"33993",
    "sg:province":"FL",
    "sg:tags":[
        "floor",
        "laying",
        "contractor"
    ],
    "wof:name":"Quality Custom Harwood Floors",
    "wof:placetype":"venue"
},
  "geometry": {"coordinates":[-82.027396,26.658813],"type":"Point"}
}