{
  "type": "Feature",
  "properties": {
    "addr:full":"2322 Lake Ave SE Largo FL 33771",
    "addr:housenumber":"2322",
    "addr:postcode":"33771",
    "addr:street":"Lake Ave Se",
    "iso:country":"US",
    "sg:address":"2322 Lake Ave SE",
    "sg:city":"Largo",
    "sg:classifiers":[
        {
            "category":"Real Estate",
            "subcategory":"Architect",
            "type":"Services"
        }
    ],
    "sg:phone":"+1 727 772 9796",
    "sg:postcode":"33771",
    "sg:province":"FL",
    "sg:tags":[
        "architectural"
    ],
    "wof:name":"By Marbella Inc",
    "wof:placetype":"venue"
},
  "geometry": {"coordinates":[-82.770855,27.897546],"type":"Point"}
}