{
  "type": "Feature",
  "properties": {
    "iso:country":"US",
    "sg:address":"303 N River Rd",
    "sg:city":"Labelle",
    "sg:classifiers":[
        {
            "category":"Shopping",
            "subcategory":"Bicycles & Sporting Goods",
            "type":"Retail Goods"
        }
    ],
    "sg:phone":"+1 863 675 8828",
    "sg:postcode":"33935",
    "sg:province":"FL",
    "sg:tags":[
        "bait",
        "fishing"
    ],
    "wof:name":"Riverside Marine",
    "wof:placetype":"venue"
},
  "geometry": {"coordinates":[-81.43841500000001,26.770893],"type":"Point"}
}