{
  "type": "Feature",
  "properties": {
    "addr:full":"91 Cobia St Destin FL 32541",
    "addr:housenumber":"91",
    "addr:postcode":"32541",
    "addr:street":"Cobia St",
    "iso:country":"US",
    "sg:address":"91 Cobia St",
    "sg:city":"Destin",
    "sg:classifiers":[
        {
            "category":"Retail",
            "subcategory":"Auto Repair",
            "type":"Services"
        }
    ],
    "sg:phone":"+1 850 837 1598",
    "sg:postcode":"32541",
    "sg:province":"FL",
    "sg:tags":[
        "general"
    ],
    "wof:name":"Hectors Auto Repair",
    "wof:placetype":"venue"
},
  "geometry": {"coordinates":[-86.418904,30.385138],"type":"Point"}
}