{
  "type": "Feature",
  "properties": {
    "addr:full":"5491 NW 15th St #23 Margate FL 33063",
    "addr:housenumber":"5491",
    "addr:postcode":"33063",
    "addr:street":"Nw 15Th St # 23 Margate",
    "iso:country":"US",
    "sg:address":"5491 NW 15th St #23",
    "sg:city":"Margate",
    "sg:phone":"+1 305 351 1677",
    "sg:postcode":"33063",
    "sg:province":"FL",
    "wof:name":"Mick Botting, Inc.",
    "wof:placetype":"venue"
},
  "geometry": {"coordinates":[-80.199254,26.248594],"type":"Point"}
}