{
  "type": "Feature",
  "properties": {
    "iso:country":"US",
    "sg:address":"405 Buenaventura Blvd",
    "sg:city":"Kissimmee",
    "sg:classifiers":[
        {
            "category":"Education",
            "subcategory":"Library",
            "type":"Public Place"
        }
    ],
    "sg:phone":"+1 407 348 8767",
    "sg:postcode":"34743",
    "sg:province":"FL",
    "sg:tags":[
        "executive"
    ],
    "wof:name":"Buenaventura Lakes Library",
    "wof:placetype":"venue"
},
  "geometry": {"coordinates":[-81.352277,28.331163],"type":"Point"}
}