{
  "type": "Feature",
  "properties": {
    "addr:full":"1951 Summit Tower Blvd Orlando FL 32810",
    "addr:housenumber":"1951",
    "addr:postcode":"32810",
    "addr:street":"Summit Tower Blvd",
    "iso:country":"US",
    "sg:address":"1951 Summit Tower Blvd",
    "sg:city":"Orlando",
    "sg:classifiers":[
        {
            "category":"Personal",
            "type":"Services"
        }
    ],
    "sg:phone":"+1 407 896 4770",
    "sg:postcode":"32810",
    "sg:province":"FL",
    "sg:tags":[
        "welcoming",
        "newcomer",
        "for"
    ],
    "wof:name":"Prime Hospitality Corp",
    "wof:placetype":"venue"
},
  "geometry": {"coordinates":[-81.40297200000001,28.634049],"type":"Point"}
}