{
  "type": "Feature",
  "properties": {
    "addr:full":"1823 N University Dr Coral Springs FL 33071",
    "addr:housenumber":"1823",
    "addr:postcode":"33071",
    "addr:street":"N University Dr",
    "iso:country":"US",
    "sg:address":"1823 N University Dr",
    "sg:city":"Coral Springs",
    "sg:classifiers":[
        {
            "category":"Travel",
            "subcategory":"Campground",
            "type":"Entertainment"
        }
    ],
    "sg:phone":"+1 954 227 7700",
    "sg:postcode":"33071",
    "sg:province":"FL",
    "sg:tags":[
        "camp"
    ],
    "wof:name":"Camp Chipinaw",
    "wof:placetype":"venue"
},
  "geometry": {"coordinates":[-80.253236,26.251961],"type":"Point"}
}