{
  "type": "Feature",
  "properties": {
    "iso:country":"US",
    "sg:address":"12305 4th St E",
    "sg:city":"Treasure Island",
    "sg:classifiers":[
        {
            "category":"Building & Trades",
            "subcategory":"Plumbing",
            "type":"Services"
        }
    ],
    "sg:phone":"+1 727 363 1350",
    "sg:postcode":"33706",
    "sg:province":"FL",
    "sg:tags":[
        "plumbing",
        "contractor"
    ],
    "wof:name":"Gulf Beach Plumbing",
    "wof:placetype":"venue"
},
  "geometry": {"coordinates":[-82.772863,27.782722],"type":"Point"}
}