{
  "type": "Feature",
  "properties": {
    "iso:country":"US",
    "sg:address":"2901 S University Dr",
    "sg:city":"Davie",
    "sg:classifiers":[
        {
            "category":"Retail",
            "subcategory":"Repair Shop",
            "type":"Services"
        }
    ],
    "sg:phone":"+1 954 446 7263",
    "sg:postcode":"33328",
    "sg:province":"FL",
    "sg:tags":[
        "lock",
        "locksmith"
    ],
    "wof:name":"7 Day Emergency 24 Hr Lcksmth",
    "wof:placetype":"venue"
},
  "geometry": {"coordinates":[-80.251143,26.089498],"type":"Point"}
}