{
  "type": "Feature",
  "properties": {
    "iso:country":"US",
    "sg:address":"8805 Nature View Ln W",
    "sg:city":"Jacksonville",
    "sg:classifiers":[
        {
            "category":"Professional",
            "subcategory":"Business Services",
            "type":"Services"
        }
    ],
    "sg:phone":"+1 904 739 2686",
    "sg:postcode":"32217",
    "sg:province":"FL",
    "sg:tags":[
        "development",
        "product",
        "designers-industrial",
        "marketing",
        "commercial",
        "design"
    ],
    "wof:name":"Design Edge Inc",
    "wof:placetype":"venue"
},
  "geometry": {"coordinates":[-81.605006,30.221468],"type":"Point"}
}