{
  "type": "Feature",
  "properties": {
    "iso:country":"US",
    "sg:address":"8350 S Florida Ave",
    "sg:city":"Floral City",
    "sg:classifiers":[
        {
            "category":"Autos & Motor Vehicles",
            "subcategory":"Fuel & Gas Station",
            "type":"Retail Goods"
        }
    ],
    "sg:phone":"+1 352 726 0138",
    "sg:postcode":"34436",
    "sg:province":"FL",
    "sg:tags":[
        "station",
        "gasoline",
        "oil"
    ],
    "wof:name":"Rick's Gas",
    "wof:placetype":"venue"
},
  "geometry": {"coordinates":[-82.30039499999999,28.740926],"type":"Point"}
}