{
  "type": "Feature",
  "properties": {
    "addr:full":"8101 Mainline Pkwy Fort Myers FL 33912",
    "addr:housenumber":"8101",
    "addr:postcode":"33912",
    "addr:street":"Mainline Pkwy",
    "iso:country":"US",
    "sg:address":"8101 Mainline Pkwy",
    "sg:city":"Fort Myers",
    "sg:classifiers":[
        {
            "category":"Building & Trades",
            "subcategory":"Equipment Rental",
            "type":"Services"
        }
    ],
    "sg:phone":"+1 239 437 9400",
    "sg:postcode":"33912",
    "sg:province":"FL",
    "sg:tags":[
        "toilet"
    ],
    "wof:name":"United Site Svc",
    "wof:placetype":"venue"
},
  "geometry": {"coordinates":[-81.82319699999999,26.498315],"type":"Point"}
}