{
  "type": "Feature",
  "properties": {
    "addr:full":"744 35th Ave N St Petersburg FL 33704",
    "addr:housenumber":"744",
    "addr:postcode":"33704",
    "addr:street":"35Th Ave N",
    "iso:country":"US",
    "sg:address":"744 35th Ave N",
    "sg:city":"St Petersburg",
    "sg:classifiers":[
        {
            "category":"Home & Garden",
            "subcategory":"Garden Supply",
            "type":"Retail Goods"
        }
    ],
    "sg:phone":"+1 727 522 9874",
    "sg:postcode":"33704",
    "sg:province":"FL",
    "sg:tags":[
        "sprinkler"
    ],
    "wof:name":"John Williams Sprinklers Inc",
    "wof:placetype":"venue"
},
  "geometry": {"coordinates":[-82.64587299999999,27.803711],"type":"Point"}
}