{
  "type": "Feature",
  "properties": {
    "iso:country":"US",
    "sg:address":"140 SW 96th Ave",
    "sg:city":"Plantation",
    "sg:classifiers":[
        {
            "category":"Professional",
            "subcategory":"Employment Agencies",
            "type":"Services"
        }
    ],
    "sg:phone":"+1 954 370 5035",
    "sg:postcode":"33324",
    "sg:province":"FL",
    "sg:tags":[
        "consultant",
        "search",
        "executive"
    ],
    "wof:name":"Temporary Crew 4 Yachts",
    "wof:placetype":"venue"
},
  "geometry": {"coordinates":[-80.273467,26.006975],"type":"Point"}
}