{
  "type": "Feature",
  "properties": {
    "iso:country":"US",
    "sg:address":"11394 Habersham Ct",
    "sg:city":"Fort Myers",
    "sg:classifiers":[
        {
            "category":"Building & Trades",
            "subcategory":"Construction",
            "type":"Services"
        }
    ],
    "sg:phone":"+1 239 707 6789",
    "sg:postcode":"33917",
    "sg:province":"FL",
    "sg:tags":[
        "contractor"
    ],
    "wof:name":"Southwest Florida Masonry Inc",
    "wof:placetype":"venue"
},
  "geometry": {"coordinates":[-81.770821,26.716193],"type":"Point"}
}