{
  "type": "Feature",
  "properties": {
    "iso:country":"US",
    "sg:address":"2721 S McCall Rd",
    "sg:city":"Englewood",
    "sg:classifiers":[
        {
            "category":"Retail",
            "subcategory":"Auto Repair",
            "type":"Services"
        }
    ],
    "sg:phone":"+1 941 474 3257",
    "sg:postcode":"34224",
    "sg:province":"FL",
    "sg:tags":[
        "body",
        "automobile",
        "painting"
    ],
    "wof:name":"Auto Pride Collision Ctr",
    "wof:placetype":"venue"
},
  "geometry": {"coordinates":[-82.31581,26.934486],"type":"Point"}
}