{
  "type": "Feature",
  "properties": {
    "iso:country":"US",
    "sg:address":"1186 La Mesa Ave",
    "sg:city":"Winter Springs",
    "sg:classifiers":[
        {
            "category":"Building & Trades",
            "subcategory":"Locksmith",
            "type":"Services"
        }
    ],
    "sg:phone":"+1 407 268 6248",
    "sg:postcode":"32708",
    "sg:province":"FL",
    "sg:tags":[
        "key"
    ],
    "wof:name":"Aalways Available Locksmith",
    "wof:placetype":"venue"
},
  "geometry": {"coordinates":[-81.263093,28.654538],"type":"Point"}
}