{
  "type": "Feature",
  "properties": {
    "iso:country":"US",
    "sg:address":"225 Cooper Ln",
    "sg:city":"Lake Helen",
    "sg:classifiers":[
        {
            "category":"Freight",
            "type":"Transportation"
        }
    ],
    "sg:phone":"+1 386 228 2434",
    "sg:postcode":"32744",
    "sg:province":"FL",
    "sg:tags":[
        "operator",
        "local",
        "trucking"
    ],
    "wof:name":"Cooper Db Trucking",
    "wof:placetype":"venue"
},
  "geometry": {"coordinates":[-81.233023,28.994681],"type":"Point"}
}