{
  "type": "Feature",
  "properties": {
    "iso:country":"US",
    "sg:address":"3111 N University Dr",
    "sg:city":"Coral Springs",
    "sg:classifiers":[
        {
            "category":"Professional",
            "subcategory":"Lawyer & Legal Services",
            "type":"Services"
        }
    ],
    "sg:phone":"+1 954 340 7277",
    "sg:postcode":"33065",
    "sg:province":"FL",
    "sg:tags":[
        "attorney"
    ],
    "wof:name":"Ameen & Drucker P A",
    "wof:placetype":"venue"
},
  "geometry": {"coordinates":[-80.249932,26.265425],"type":"Point"}
}