{
  "type": "Feature",
  "properties": {
    "iso:country":"US",
    "sg:address":"1341 Howell Branch Rd",
    "sg:city":"Winter Park",
    "sg:classifiers":[
        {
            "category":"Restaurant",
            "type":"Food & Drink"
        }
    ],
    "sg:phone":"+1 407 645 0065",
    "sg:postcode":"32789",
    "sg:province":"FL",
    "sg:tags":[
        "traditional",
        "american",
        "diner"
    ],
    "wof:name":"Uncle Henry's Country Grill",
    "wof:placetype":"venue"
},
  "geometry": {"coordinates":[-81.336444,28.624946],"type":"Point"}
}