{
  "type": "Feature",
  "properties": {
    "iso:country":"US",
    "sg:address":"171 Tanager Rd",
    "sg:city":"Venice",
    "sg:classifiers":[
        {
            "category":"Professional",
            "subcategory":"Business Services",
            "type":"Services"
        }
    ],
    "sg:phone":"+1 941 493 2035",
    "sg:postcode":"34293",
    "sg:province":"FL",
    "sg:tags":[
        "pool",
        "swimming"
    ],
    "wof:name":"H 2 Oh Pool Svc",
    "wof:placetype":"venue"
},
  "geometry": {"coordinates":[-82.41387,27.064348],"type":"Point"}
}