{
  "type": "Feature",
  "properties": {
    "iso:country":"US",
    "sg:address":"4676 SW 72nd Ave",
    "sg:city":"Miami",
    "sg:classifiers":[
        {
            "category":"Shopping",
            "subcategory":"Jewelry",
            "type":"Retail Goods"
        }
    ],
    "sg:phone":"+1 305 663 0075",
    "sg:postcode":"33155",
    "sg:province":"FL",
    "wof:name":"Singer Jewelers",
    "wof:placetype":"venue"
},
  "geometry": {"coordinates":[-80.310868,25.725859],"type":"Point"}
}