{
  "type": "Feature",
  "properties": {
    "addr:full":"2215 River Blvd Jacksonville FL 32204",
    "addr:housenumber":"2215",
    "addr:postcode":"32204",
    "addr:street":"River Blvd",
    "iso:country":"US",
    "sg:address":"2215 River Blvd",
    "sg:city":"Jacksonville",
    "sg:classifiers":[
        {
            "category":"Real Estate",
            "subcategory":"Real Estate Operator",
            "type":"Services"
        }
    ],
    "sg:phone":"+1 904 389 5430",
    "sg:postcode":"32204",
    "sg:province":"FL",
    "sg:tags":[
        "apartment"
    ],
    "wof:name":"Apartment Company The",
    "wof:placetype":"venue"
},
  "geometry": {"coordinates":[-81.68387800000001,30.308975],"type":"Point"}
}