{
  "type": "Feature",
  "properties": {
    "iso:country":"US",
    "sg:address":"4901 Gulfport Blvd S",
    "sg:city":"Gulfport",
    "sg:classifiers":[
        {
            "category":"Autos & Motor Vehicles",
            "subcategory":"Auto Supplies",
            "type":"Retail Goods"
        },
        {
            "category":"Wholesale",
            "subcategory":"Electrical",
            "type":"Manufacturing & Wholesale Goods"
        },
        {
            "category":"Wholesale",
            "subcategory":"Auto Parts",
            "type":"Manufacturing & Wholesale Goods"
        },
        {
            "category":"Retail",
            "subcategory":"Auto Repair",
            "type":"Services"
        }
    ],
    "sg:phone":"+1 727 323 2971",
    "sg:postcode":"33707",
    "sg:province":"FL",
    "sg:tags":[
        "engines-rebuild",
        "exchange",
        "battery",
        "automobile",
        "accessory",
        "equipment",
        "truck",
        "supplies-used",
        "rebuilt",
        "batteries-storage"
    ],
    "sg:website":"http://www.advanceautoparts.com",
    "wof:name":"Advance Auto Parts",
    "wof:placetype":"venue"
},
  "geometry": {"coordinates":[-82.73263900000001,27.75807],"type":"Point"}
}