{
  "type": "Feature",
  "properties": {
    "addr:full":"6216 31st St E Bradenton FL 34203",
    "addr:housenumber":"6216",
    "addr:postcode":"34203",
    "addr:street":"31St St",
    "iso:country":"US",
    "sg:address":"6216 31st St E",
    "sg:city":"Bradenton",
    "sg:classifiers":[
        {
            "category":"Freight",
            "type":"Transportation"
        }
    ],
    "sg:phone":"+1 941 751 9301",
    "sg:postcode":"34203",
    "sg:province":"FL",
    "sg:tags":[
        "trucking"
    ],
    "sg:website":"www.odfl.com",
    "wof:name":"Old Dominion Freight Line",
    "wof:placetype":"venue"
},
  "geometry": {"coordinates":[-82.525025,27.429479],"type":"Point"}
}