{
  "type": "Feature",
  "properties": {
    "iso:country":"US",
    "sg:address":"4572 Commercial Way",
    "sg:city":"Spring Hill",
    "sg:classifiers":[
        {
            "category":"Education",
            "subcategory":"Dance Studio",
            "type":"Public Place"
        }
    ],
    "sg:phone":"+1 352 597 5979",
    "sg:postcode":"34606",
    "sg:province":"FL",
    "sg:tags":[
        "instruction",
        "dancing"
    ],
    "wof:name":"Diana Dance Express",
    "wof:placetype":"venue"
},
  "geometry": {"coordinates":[-82.59598099999999,28.494835],"type":"Point"}
}