{
  "type": "Feature",
  "properties": {
    "iso:country":"US",
    "sg:address":"72 Foxtail Ave",
    "sg:city":"Middleburg",
    "sg:classifiers":[
        {
            "category":"Retail",
            "subcategory":"Repair Shop",
            "type":"Services"
        },
        {
            "category":"Home & Garden",
            "subcategory":"Building Materials",
            "type":"Retail Goods"
        },
        {
            "category":"Building & Trades",
            "subcategory":"Construction",
            "type":"Services"
        },
        {
            "category":"Building & Trades",
            "subcategory":"Electrical",
            "type":"Services"
        }
    ],
    "sg:phone":"+1 904 378 3882",
    "sg:postcode":"32068",
    "sg:province":"FL",
    "sg:tags":[
        "industrial",
        "electrician",
        "electric",
        "improvement",
        "generators-electric-service",
        "contractors-commercial",
        "maintenance"
    ],
    "sg:website":"http://www.mrelectric.com",
    "wof:name":"Mr. Electric Of Jacksonville",
    "wof:placetype":"venue"
},
  "geometry": {"coordinates":[-81.905889,30.076289],"type":"Point"}
}