{
  "type": "Feature",
  "properties": {
    "addr:full":"1900 SW 13th St Gainesville FL 32608",
    "addr:housenumber":"1900",
    "addr:postcode":"32608",
    "addr:street":"Sw 13Th St",
    "iso:country":"US",
    "sg:address":"1900 SW 13th St",
    "sg:city":"Gainesville",
    "sg:classifiers":[
        {
            "category":"Restaurant",
            "type":"Food & Drink"
        }
    ],
    "sg:menulink":"http://www.allmenus.com/fl/gainesville/62998-china-super-buffet/menu/",
    "sg:phone":"+1 352 375 8828",
    "sg:postcode":"32608",
    "sg:province":"FL",
    "sg:tags":[
        "asian",
        "chinese"
    ],
    "wof:name":"China Super Buffet",
    "wof:placetype":"venue"
},
  "geometry": {"coordinates":[-82.339493,29.634602],"type":"Point"}
}