{
  "type": "Feature",
  "properties": {
    "addr:full":"224 SE Prima Vista Blvd Port Saint Lucie FL 34983",
    "addr:housenumber":"224",
    "addr:postcode":"34983",
    "addr:street":"Se Prima Vista Blvd",
    "iso:country":"US",
    "sg:address":"224 SE Prima Vista Blvd",
    "sg:city":"Port Saint Lucie",
    "sg:classifiers":[
        {
            "category":"Building & Trades",
            "subcategory":"Landscaping Services",
            "type":"Services"
        }
    ],
    "sg:phone":"+1 772 878 6152",
    "sg:postcode":"34983",
    "sg:province":"FL",
    "wof:name":"Kellys Lawnscapes",
    "wof:placetype":"venue"
},
  "geometry": {"coordinates":[-80.340992,27.31875],"type":"Point"}
}