{
  "type": "Feature",
  "properties": {
    "iso:country":"US",
    "sg:address":"535 Dorado Way",
    "sg:city":"Indian Hrbr Bch",
    "sg:classifiers":[
        {
            "category":"Building & Trades",
            "subcategory":"Construction",
            "type":"Services"
        }
    ],
    "sg:phone":"+1 321 777 8178",
    "sg:postcode":"32937",
    "sg:province":"FL",
    "sg:tags":[
        "painter"
    ],
    "wof:name":"Bill's Custom Ceilings & Paint",
    "wof:placetype":"venue"
},
  "geometry": {"coordinates":[-80.59015100000001,28.148199],"type":"Point"}
}