{
  "type": "Feature",
  "properties": {
    "iso:country":"US",
    "sg:address":"125 N Swinton Ave",
    "sg:city":"Delray Beach",
    "sg:classifiers":[
        {
            "category":"Professional",
            "subcategory":"Lawyer & Legal Services",
            "type":"Services"
        }
    ],
    "sg:phone":"+1 561 266 5801",
    "sg:postcode":"33444",
    "sg:province":"FL",
    "sg:tags":[
        "attorney"
    ],
    "wof:name":"Clear Title",
    "wof:placetype":"venue"
},
  "geometry": {"coordinates":[-80.073099,26.464835],"type":"Point"}
}