{
  "type": "Feature",
  "properties": {
    "addr:full":"1848 Evergreen Dr West Palm Beach FL 33406",
    "addr:housenumber":"1848",
    "addr:postcode":"33406",
    "addr:street":"Evergreen Dr",
    "iso:country":"US",
    "sg:address":"1848 Evergreen Dr",
    "sg:city":"West Palm Beach",
    "sg:classifiers":[
        {
            "category":"Health Services",
            "subcategory":"Doctor",
            "type":"Services"
        }
    ],
    "sg:phone":"+1 561 833 2046",
    "sg:postcode":"33406",
    "sg:province":"FL",
    "sg:tags":[
        "physician",
        "surgeon"
    ],
    "wof:name":"Yrma M Signo MD",
    "wof:placetype":"venue"
},
  "geometry": {"coordinates":[-80.079623,26.654777],"type":"Point"}
}