{
  "type": "Feature",
  "properties": {
    "iso:country":"US",
    "sg:address":"499 E Central Pkwy",
    "sg:city":"Altamonte Springs",
    "sg:classifiers":[
        {
            "category":"Health Services",
            "subcategory":"Doctor",
            "type":"Services"
        }
    ],
    "sg:phone":"+1 407 332 0003",
    "sg:postcode":"32701",
    "sg:province":"FL",
    "sg:tags":[
        "medicine",
        "internal"
    ],
    "wof:name":"Orlando Family Physicians Inc",
    "wof:placetype":"venue"
},
  "geometry": {"coordinates":[-81.374432,28.669857],"type":"Point"}
}