{
  "type": "Feature",
  "properties": {
    "iso:country":"US",
    "sg:address":"10300 SW 216th St",
    "sg:city":"Miami",
    "sg:classifiers":[
        {
            "category":"Health Services",
            "subcategory":"Hospital",
            "type":"Services"
        }
    ],
    "sg:phone":"+1 305 252 4840",
    "sg:postcode":"33190",
    "sg:province":"FL",
    "sg:tags":[
        "mental"
    ],
    "wof:name":"Behavioral Health Dept",
    "wof:placetype":"venue"
},
  "geometry": {"coordinates":[-80.358575,25.566734],"type":"Point"}
}