{
  "type": "Feature",
  "properties": {
    "iso:country":"US",
    "sg:address":"1300 SW 54th Ave",
    "sg:city":"Plantation",
    "sg:classifiers":[
        {
            "category":"Education",
            "subcategory":"School",
            "type":"Public Place"
        }
    ],
    "sg:phone":"+1 954 797 4600",
    "sg:postcode":"33317",
    "sg:province":"FL",
    "wof:name":"South Plantation High School",
    "wof:placetype":"venue"
},
  "geometry": {"coordinates":[-80.22125699999999,26.104232],"type":"Point"}
}