{
  "type": "Feature",
  "properties": {
    "iso:country":"US",
    "sg:address":"305 S Pinellas Ave",
    "sg:city":"Tarpon Springs",
    "sg:classifiers":[
        {
            "category":"Donuts",
            "type":"Food & Drink"
        }
    ],
    "sg:menulink":"http://www.allmenus.com/fl/tarpon-springs/33678-mr-bills-donut--deli/menu/",
    "sg:phone":"+1 727 934 0331",
    "sg:postcode":"34689",
    "sg:province":"FL",
    "sg:tags":[
        "american",
        "diner"
    ],
    "wof:name":"Mr. Bill's Donut & Deli",
    "wof:placetype":"venue"
},
  "geometry": {"coordinates":[-82.756615,28.143989],"type":"Point"}
}