{
  "type": "Feature",
  "properties": {
    "iso:country":"US",
    "sg:address":"6114 NW 7th Ave",
    "sg:city":"Miami",
    "sg:classifiers":[
        {
            "category":"Insurance",
            "subcategory":"Hazard Insurance",
            "type":"Services"
        }
    ],
    "sg:phone":"+1 305 759 3344",
    "sg:postcode":"33127",
    "sg:province":"FL",
    "sg:tags":[
        "bond"
    ],
    "wof:name":"Security Solutions Bail Bond",
    "wof:placetype":"venue"
},
  "geometry": {"coordinates":[-80.20857100000001,25.83212],"type":"Point"}
}