{
  "type": "Feature",
  "properties": {
    "iso:country":"US",
    "sg:address":"130 S Semoran Blvd",
    "sg:city":"Orlando",
    "sg:classifiers":[
        {
            "category":"Personal",
            "subcategory":"Tanning Parlor",
            "type":"Services"
        }
    ],
    "sg:phone":"+1 407 381 3884",
    "sg:postcode":"32807",
    "sg:province":"FL",
    "sg:tags":[
        "salon"
    ],
    "wof:name":"Sunbody Tanning",
    "wof:placetype":"venue"
},
  "geometry": {"coordinates":[-81.310722,28.545314],"type":"Point"}
}