{
  "type": "Feature",
  "properties": {
    "iso:country":"US",
    "sg:address":"675 NW 56th St Bldg C",
    "sg:city":"Miami",
    "sg:classifiers":[
        {
            "category":"Professional",
            "subcategory":"Management & Consulting",
            "type":"Services"
        }
    ],
    "sg:phone":"+1 305 757 3737",
    "sg:postcode":"33127",
    "sg:province":"FL",
    "wof:name":"T E D C",
    "wof:placetype":"venue"
},
  "geometry": {"coordinates":[-80.207741,25.826796],"type":"Point"}
}