{
  "type": "Feature",
  "properties": {
    "iso:country":"US",
    "sg:address":"12720 S Orange Blossom Trl",
    "sg:city":"Orlando",
    "sg:classifiers":[
        {
            "category":"Professional",
            "subcategory":"Computer Services",
            "type":"Services"
        }
    ],
    "sg:phone":"+1 407 857 2224",
    "sg:postcode":"32837",
    "sg:province":"FL",
    "sg:tags":[
        "graphics"
    ],
    "wof:name":"Graphics Place",
    "wof:placetype":"venue"
},
  "geometry": {"coordinates":[-81.40458599999999,28.377824],"type":"Point"}
}