{
  "type": "Feature",
  "properties": {
    "addr:full":"603 Pearl Rd Winter Springs FL 32708",
    "addr:housenumber":"603",
    "addr:postcode":"32708",
    "addr:street":"Pearl Rd",
    "iso:country":"US",
    "sg:address":"603 Pearl Rd",
    "sg:city":"Winter Springs",
    "sg:classifiers":[
        {
            "category":"Recreation",
            "type":"Entertainment"
        }
    ],
    "sg:phone":"+1 407 327 1501",
    "sg:postcode":"32708",
    "sg:province":"FL",
    "wof:name":"Deshazo Enterprises",
    "wof:placetype":"venue"
},
  "geometry": {"coordinates":[-81.289304,28.699511],"type":"Point"}
}