{
  "type": "Feature",
  "properties": {
    "addr:full":"903 N Central Ave Kissimmee FL 34741",
    "addr:housenumber":"903",
    "addr:postcode":"34741",
    "addr:street":"N Central Ave",
    "iso:country":"US",
    "sg:address":"903 N Central Ave",
    "sg:city":"Kissimmee",
    "sg:classifiers":[
        {
            "category":"Health Services",
            "subcategory":"Doctor",
            "type":"Services"
        }
    ],
    "sg:phone":"+1 407 933 6506",
    "sg:postcode":"34741",
    "sg:province":"FL",
    "sg:tags":[
        "physician",
        "surgeon"
    ],
    "wof:name":"Pain Medicine Assoc Of Fl",
    "wof:placetype":"venue"
},
  "geometry": {"coordinates":[-81.407793,28.300896],"type":"Point"}
}