{
  "type": "Feature",
  "properties": {
    "iso:country":"US",
    "sg:address":"265 E Marion Ave",
    "sg:city":"Punta Gorda",
    "sg:classifiers":[
        {
            "category":"Professional",
            "subcategory":"Lawyer & Legal Services",
            "type":"Services"
        }
    ],
    "sg:phone":"+1 941 575 5100",
    "sg:postcode":"33950",
    "sg:province":"FL",
    "sg:tags":[
        "attorney"
    ],
    "wof:name":"John Balliro Sebastian Law Ofc",
    "wof:placetype":"venue"
},
  "geometry": {"coordinates":[-82.04723300000001,26.93761],"type":"Point"}
}