{
  "type": "Feature",
  "properties": {
    "iso:country":"US",
    "sg:address":"30 Pinehurst Pl",
    "sg:city":"Palm Coast",
    "sg:classifiers":[
        {
            "category":"Wholesale",
            "subcategory":"Durable Goods & Equipment",
            "type":"Manufacturing & Wholesale Goods"
        }
    ],
    "sg:phone":"+1 904 347 1011",
    "sg:postcode":"32137",
    "sg:province":"FL",
    "sg:tags":[
        "distributor",
        "microscope",
        "balance",
        "bo"
    ],
    "wof:name":"MSA",
    "wof:placetype":"venue"
},
  "geometry": {"coordinates":[-81.195447,29.56249],"type":"Point"}
}