{
  "type": "Feature",
  "properties": {
    "iso:country":"US",
    "sg:address":"434 SW 12th Ave",
    "sg:city":"Miami",
    "sg:classifiers":[
        {
            "category":"Health Services",
            "subcategory":"Dentist",
            "type":"Services"
        }
    ],
    "sg:phone":"+1 305 642 0504",
    "sg:postcode":"33130",
    "sg:province":"FL",
    "sg:tags":[
        "dental",
        "clinic"
    ],
    "wof:name":"Sonria Dental Group",
    "wof:placetype":"venue"
},
  "geometry": {"coordinates":[-80.214523,25.76928],"type":"Point"}
}