{
  "type": "Feature",
  "properties": {
    "addr:full":"12193 N Miami Ave North Miami FL 33168",
    "addr:housenumber":"12193",
    "addr:postcode":"33168",
    "addr:street":"N Miami Ave",
    "iso:country":"US",
    "sg:address":"12193 N Miami Ave",
    "sg:city":"North Miami",
    "sg:classifiers":[
        {
            "category":"Shopping",
            "subcategory":"Discount & Variety Stores",
            "type":"Retail Goods"
        }
    ],
    "sg:phone":"+1 305 877 0737",
    "sg:postcode":"33168",
    "sg:province":"FL",
    "sg:tags":[
        "merchandise",
        "general"
    ],
    "wof:name":"LA Gran Via Dollar Stores",
    "wof:placetype":"venue"
},
  "geometry": {"coordinates":[-80.198488,25.887482],"type":"Point"}
}