{
  "type": "Feature",
  "properties": {
    "iso:country":"US",
    "sg:address":"3680 Ellis Rd",
    "sg:city":"Fort Myers",
    "sg:classifiers":[
        {
            "category":"Professional",
            "subcategory":"Computer Services",
            "type":"Services"
        }
    ],
    "sg:phone":"+1 239 489 0400",
    "sg:postcode":"33905",
    "sg:province":"FL",
    "sg:tags":[
        "internet"
    ],
    "wof:name":"Real Solutions Inc",
    "wof:placetype":"venue"
},
  "geometry": {"coordinates":[-81.77807300000001,26.688936],"type":"Point"}
}