{
  "type": "Feature",
  "properties": {
    "addr:full":"15741 SW 152nd St Miami FL 33187",
    "addr:housenumber":"15741",
    "addr:postcode":"33187",
    "addr:street":"Sw 152Nd St",
    "iso:country":"US",
    "sg:address":"15741 SW 152nd St",
    "sg:city":"Miami",
    "sg:classifiers":[
        {
            "category":"Restaurant",
            "type":"Food & Drink"
        },
        {
            "category":"Shopping",
            "subcategory":"Computers & Home Electronics",
            "type":"Retail Goods"
        }
    ],
    "sg:phone":"+1 305 251 3009",
    "sg:postcode":"33187",
    "sg:province":"FL",
    "sg:tags":[
        "grocery",
        "pan",
        "chinese",
        "store",
        "asian"
    ],
    "wof:name":"Hong Kong Chinese Restaurant",
    "wof:placetype":"venue"
},
  "geometry": {"coordinates":[-80.448041,25.625355],"type":"Point"}
}