{
  "type": "Feature",
  "properties": {
    "addr:full":"1558 Kelly Ave Kissimmee FL 34744",
    "addr:housenumber":"1558",
    "addr:postcode":"34744",
    "addr:street":"Kelly Ave",
    "iso:country":"US",
    "sg:address":"1558 Kelly Ave",
    "sg:city":"Kissimmee",
    "sg:classifiers":[
        {
            "category":"Building & Trades",
            "subcategory":"Construction",
            "type":"Services"
        }
    ],
    "sg:phone":"+1 407 846 8274",
    "sg:postcode":"34744",
    "sg:province":"FL",
    "sg:tags":[
        "contractor"
    ],
    "sg:website":"www.salvadorconstruction.com",
    "wof:name":"Salvador Construction Inc",
    "wof:placetype":"venue"
},
  "geometry": {"coordinates":[-81.397443,28.306724],"type":"Point"}
}