{
  "type": "Feature",
  "properties": {
    "iso:country":"US",
    "sg:address":"4815 Alcea St",
    "sg:city":"New Port Richey",
    "sg:classifiers":[
        {
            "category":"Building & Trades",
            "subcategory":"Pest Control",
            "type":"Services"
        }
    ],
    "sg:phone":"+1 727 847 0722",
    "sg:postcode":"34652",
    "sg:province":"FL",
    "wof:name":"Earth's Best Pest Management",
    "wof:placetype":"venue"
},
  "geometry": {"coordinates":[-82.719126,28.229131],"type":"Point"}
}