{
  "type": "Feature",
  "properties": {
    "addr:full":"5157 Floria Way Boynton Beach FL 33437",
    "addr:housenumber":"5157",
    "addr:postcode":"33437",
    "addr:street":"Floria Way",
    "iso:country":"US",
    "sg:address":"5157 Floria Way",
    "sg:city":"Boynton Beach",
    "sg:classifiers":[
        {
            "category":"Education",
            "subcategory":"Special Training",
            "type":"Public Place"
        }
    ],
    "sg:phone":"+1 561 736 5884",
    "sg:postcode":"33437",
    "sg:province":"FL",
    "sg:tags":[
        "tutoring"
    ],
    "wof:name":"Tutor One To One",
    "wof:placetype":"venue"
},
  "geometry": {"coordinates":[-80.126231,26.53089],"type":"Point"}
}