{
  "type": "Feature",
  "properties": {
    "addr:full":"1100 Collins Ave Miami Beach FL 33139",
    "addr:housenumber":"1100",
    "addr:postcode":"33139",
    "addr:street":"Collins Ave",
    "iso:country":"US",
    "sg:address":"1100 Collins Ave",
    "sg:city":"Miami Beach",
    "sg:classifiers":[
        {
            "category":"Banks & Credit Unions",
            "subcategory":"Financial Services",
            "type":"Services"
        }
    ],
    "sg:phone":"+1 305 604 3541",
    "sg:postcode":"33139",
    "sg:province":"FL",
    "sg:tags":[
        "investor"
    ],
    "wof:name":"Immobiliare Investors Inc",
    "wof:placetype":"venue"
},
  "geometry": {"coordinates":[-80.13121,25.78284],"type":"Point"}
}