{
  "type": "Feature",
  "properties": {
    "iso:country":"US",
    "sg:address":"6941 Sunset Strip",
    "sg:city":"Sunrise",
    "sg:classifiers":[
        {
            "category":"Restaurant",
            "type":"Food & Drink"
        }
    ],
    "sg:phone":"+1 954 749 7472",
    "sg:postcode":"33313",
    "sg:province":"FL",
    "sg:tags":[
        "eating"
    ],
    "wof:name":"Chef Carlin",
    "wof:placetype":"venue"
},
  "geometry": {"coordinates":[-80.240668,26.154925],"type":"Point"}
}