{
  "type": "Feature",
  "properties": {
    "iso:country":"US",
    "sg:address":"230a Sunrise Ave",
    "sg:city":"Palm Beach",
    "sg:classifiers":[
        {
            "category":"Restaurant",
            "type":"Food & Drink"
        }
    ],
    "sg:menulink":"http://www.allmenus.com/fl/west-palm-beach/16347-echo/menu/",
    "sg:phone":"+1 561 802 4222",
    "sg:postcode":"33480",
    "sg:province":"FL",
    "sg:tags":[
        "sushi",
        "asian"
    ],
    "wof:name":"Echo",
    "wof:placetype":"venue"
},
  "geometry": {"coordinates":[-80.038803,26.720059],"type":"Point"}
}