{
  "type": "Feature",
  "properties": {
    "iso:country":"US",
    "sg:address":"1900 SW 34 St",
    "sg:city":"Gainesville",
    "sg:classifiers":[
        {
            "category":"Government",
            "subcategory":"Office",
            "type":"Public Place"
        }
    ],
    "sg:phone":"+1 352 955 2272",
    "sg:postcode":"32608",
    "sg:province":"FL",
    "sg:tags":[
        "state",
        "resource"
    ],
    "wof:name":"Workers Compensation Hearings",
    "wof:placetype":"venue"
},
  "geometry": {"coordinates":[-82.36769099999999,29.599954],"type":"Point"}
}