{
  "type": "Feature",
  "properties": {
    "iso:country":"US",
    "sg:address":"280 Wilson Ave",
    "sg:city":"Satellite Beach",
    "sg:classifiers":[
        {
            "category":"Professional",
            "subcategory":"Management & Consulting",
            "type":"Services"
        }
    ],
    "sg:phone":"+1 321 779 8315",
    "sg:postcode":"32937",
    "sg:province":"FL",
    "sg:tags":[
        "fuel"
    ],
    "wof:name":"Management & Marketing Svc",
    "wof:placetype":"venue"
},
  "geometry": {"coordinates":[-80.594499,28.181237],"type":"Point"}
}