{
  "type": "Feature",
  "properties": {
    "iso:country":"US",
    "sg:address":"7805 Immokolee Rd",
    "sg:city":"Fort Pierce",
    "sg:classifiers":[
        {
            "category":"Farming",
            "subcategory":"Orchard",
            "type":"Manufacturing & Wholesale Goods"
        }
    ],
    "sg:phone":"+1 772 461 5805",
    "sg:postcode":"34951",
    "sg:province":"FL",
    "sg:tags":[
        "citrus",
        "groves",
        "operates"
    ],
    "wof:name":"Helseth Grove Services Inc",
    "wof:placetype":"venue"
},
  "geometry": {"coordinates":[-80.404814,27.484285],"type":"Point"}
}