{
  "type": "Feature",
  "properties": {
    "addr:full":"1885 N John Young Pkwy Kissimmee FL 34741",
    "addr:housenumber":"1885",
    "addr:postcode":"34741",
    "addr:street":"N John Young Pkwy",
    "iso:country":"US",
    "sg:address":"1885 N John Young Pkwy",
    "sg:city":"Kissimmee",
    "sg:classifiers":[
        {
            "category":"Restaurant",
            "type":"Food & Drink"
        }
    ],
    "sg:menulink":"http://www.allmenus.com/fl/kissimmee/153891-zaxbys/menu/",
    "sg:phone":"+1 407 932 1843",
    "sg:postcode":"34741",
    "sg:province":"FL",
    "sg:tags":[
        "american",
        "wing"
    ],
    "wof:name":"Zaxby's",
    "wof:placetype":"venue"
},
  "geometry": {"coordinates":[-81.41582699999999,28.309667],"type":"Point"}
}