{
  "type": "Feature",
  "properties": {
    "iso:country":"US",
    "sg:address":"48 Oceanway Ave",
    "sg:city":"Jacksonville",
    "sg:classifiers":[
        {
            "category":"Manufacturing",
            "subcategory":"Signs",
            "type":"Manufacturing & Wholesale Goods"
        }
    ],
    "sg:phone":"+1 904 714 6460",
    "sg:postcode":"32218",
    "sg:province":"FL",
    "wof:name":"Patterson Graphix Inc",
    "wof:placetype":"venue"
},
  "geometry": {"coordinates":[-81.63278699999999,30.467001],"type":"Point"}
}