{
  "type": "Feature",
  "properties": {
    "iso:country":"US",
    "sg:address":"22800 SW 112th Ave",
    "sg:city":"Miami",
    "sg:classifiers":[
        {
            "category":"Place Of Worship",
            "subcategory":"Church",
            "type":"Public Place"
        },
        {
            "category":"Place Of Worship",
            "type":"Public Place"
        }
    ],
    "sg:phone":"+1 305 253 6122",
    "sg:postcode":"33170",
    "sg:province":"FL",
    "sg:tags":[
        "testament",
        "christ-new",
        "christ",
        "churches-church"
    ],
    "wof:name":"Goulds Church Of Christ Inc",
    "wof:placetype":"venue"
},
  "geometry": {"coordinates":[-80.372103,25.555157],"type":"Point"}
}