{
  "type": "Feature",
  "properties": {
    "iso:country":"US",
    "sg:address":"18375 NW 27th Ave",
    "sg:city":"Opa Locka",
    "sg:classifiers":[
        {
            "category":"Retail",
            "subcategory":"Laundry & Dry Cleaning",
            "type":"Services"
        }
    ],
    "sg:phone":"+1 305 624 2123",
    "sg:postcode":"33054",
    "sg:province":"FL",
    "sg:tags":[
        "diaper"
    ],
    "wof:name":"Baby City",
    "wof:placetype":"venue"
},
  "geometry": {"coordinates":[-80.245311,25.942679],"type":"Point"}
}