{
  "type": "Feature",
  "properties": {
    "iso:country":"US",
    "sg:address":"261 Miracle Mile",
    "sg:city":"Miami",
    "sg:classifiers":[
        {
            "category":"Restaurant",
            "type":"Food & Drink"
        }
    ],
    "sg:phone":"+1 305 403 7000",
    "sg:postcode":"33134",
    "sg:province":"FL",
    "sg:website":"www.coldstonecreamery.com",
    "wof:name":"Cold Stone Creamery",
    "wof:placetype":"venue"
},
  "geometry": {"coordinates":[-80.260019,25.749598],"type":"Point"}
}