{
  "type": "Feature",
  "properties": {
    "iso:country":"US",
    "sg:address":"1101 Southside Dr",
    "sg:city":"Brandon",
    "sg:classifiers":[
        {
            "category":"Building & Trades",
            "subcategory":"Construction",
            "type":"Services"
        }
    ],
    "sg:phone":"+1 813 643 8004",
    "sg:postcode":"33511",
    "sg:province":"FL",
    "sg:tags":[
        "wallcoverings-installation",
        "wallpaper",
        "painting",
        "contractor"
    ],
    "wof:name":"Duncans Painting And Remodeling",
    "wof:placetype":"venue"
},
  "geometry": {"coordinates":[-82.26718099999999,27.931179],"type":"Point"}
}