{
  "type": "Feature",
  "properties": {
    "addr:full":"8067 Woodduck Dr Orlando FL 32825",
    "addr:housenumber":"8067",
    "addr:postcode":"32825",
    "addr:street":"Woodduck Dr",
    "iso:country":"US",
    "sg:address":"8067 Woodduck Dr",
    "sg:city":"Orlando",
    "sg:classifiers":[
        {
            "category":"Manufacturing",
            "subcategory":"Wood Products",
            "type":"Manufacturing & Wholesale Goods"
        }
    ],
    "sg:phone":"+1 407 737 1879",
    "sg:postcode":"32825",
    "sg:province":"FL",
    "sg:tags":[
        "reconstituted",
        "mfg"
    ],
    "wof:name":"Guillermo D Iriarte",
    "wof:placetype":"venue"
},
  "geometry": {"coordinates":[-81.277359,28.534526],"type":"Point"}
}