{
  "type": "Feature",
  "properties": {
    "iso:country":"US",
    "sg:address":"1611 W Swann Ave",
    "sg:city":"Tampa",
    "sg:classifiers":[
        {
            "category":"Restaurant",
            "type":"Food & Drink"
        }
    ],
    "sg:menulink":"http://www.allmenus.com/fl/tampa/158292-wine-exchange/menu/",
    "sg:phone":"+1 813 254 9463",
    "sg:postcode":"33606",
    "sg:province":"FL",
    "sg:tags":[
        "new",
        "american"
    ],
    "wof:name":"Wine Exchange",
    "wof:placetype":"venue"
},
  "geometry": {"coordinates":[-82.476546,27.937352],"type":"Point"}
}