{
  "type": "Feature",
  "properties": {
    "addr:full":"4800 Palm Beach Blvd Fort Myers FL 33905",
    "addr:housenumber":"4800",
    "addr:postcode":"33905",
    "addr:street":"Palm Beach Blvd",
    "iso:country":"US",
    "sg:address":"4800 Palm Beach Blvd",
    "sg:city":"Fort Myers",
    "sg:classifiers":[
        {
            "category":"Organizations",
            "subcategory":"Community Association",
            "type":"Services"
        }
    ],
    "sg:phone":"+1 239 693 0351",
    "sg:postcode":"33905",
    "sg:province":"FL",
    "sg:tags":[
        "military"
    ],
    "wof:name":"American Legion",
    "wof:placetype":"venue"
},
  "geometry": {"coordinates":[-81.81083,26.67728],"type":"Point"}
}