{
  "type": "Feature",
  "properties": {
    "addr:full":"6 Pfeiffer St Gulf Breeze FL 32561",
    "addr:housenumber":"6",
    "addr:postcode":"32561",
    "addr:street":"Pfeiffer St",
    "iso:country":"US",
    "sg:address":"6 Pfeiffer St",
    "sg:city":"Gulf Breeze",
    "sg:classifiers":[
        {
            "category":"Manufacturing",
            "subcategory":"Printing",
            "type":"Manufacturing & Wholesale Goods"
        }
    ],
    "sg:phone":"+1 850 932 0998",
    "sg:postcode":"32561",
    "sg:province":"FL",
    "sg:tags":[
        "printer"
    ],
    "wof:name":"Dolphin Design & Printing Inc",
    "wof:placetype":"venue"
},
  "geometry": {"coordinates":[-87.171104,30.366899],"type":"Point"}
}