{
  "type": "Feature",
  "properties": {
    "addr:full":"2124 Velvet Way Lakeland FL 33811",
    "addr:housenumber":"2124",
    "addr:postcode":"33811",
    "addr:street":"Velvet Way",
    "iso:country":"US",
    "sg:address":"2124 Velvet Way",
    "sg:city":"Lakeland",
    "sg:classifiers":[
        {
            "category":"Building & Trades",
            "subcategory":"Construction",
            "type":"Services"
        }
    ],
    "sg:phone":"+1 863 648 0371",
    "sg:postcode":"33811",
    "sg:province":"FL",
    "sg:tags":[
        "home"
    ],
    "wof:name":"A Shayne Homes Inc",
    "wof:placetype":"venue"
},
  "geometry": {"coordinates":[-81.99282700000001,27.956831],"type":"Point"}
}