{
  "type": "Feature",
  "properties": {
    "addr:full":"7629 Herricks Loop Orlando FL 32835",
    "addr:housenumber":"7629",
    "addr:postcode":"32835",
    "addr:street":"Herricks Loop",
    "iso:country":"US",
    "sg:address":"7629 Herricks Loop",
    "sg:city":"Orlando",
    "sg:classifiers":[
        {
            "category":"Manufacturing",
            "subcategory":"Food",
            "type":"Manufacturing & Wholesale Goods"
        }
    ],
    "sg:phone":"+1 407 297 1038",
    "sg:postcode":"32835",
    "sg:province":"FL",
    "sg:tags":[
        "mfg"
    ],
    "wof:name":"Sunland Marketing",
    "wof:placetype":"venue"
},
  "geometry": {"coordinates":[-81.48761399999999,28.541575],"type":"Point"}
}