{
  "type": "Feature",
  "properties": {
    "iso:country":"US",
    "sg:address":"10661 SW 113th Pl",
    "sg:city":"Miami",
    "sg:classifiers":[
        {
            "category":"Freight",
            "type":"Transportation"
        }
    ],
    "sg:phone":"+1 305 596 3905",
    "sg:postcode":"33176",
    "sg:province":"FL",
    "sg:tags":[
        "cartage",
        "trucking"
    ],
    "wof:name":"Downtown Hub Inc",
    "wof:placetype":"venue"
},
  "geometry": {"coordinates":[-80.378163,25.669417],"type":"Point"}
}