{
  "type": "Feature",
  "properties": {
    "iso:country":"US",
    "sg:address":"2384 Commercial Way",
    "sg:city":"Spring Hill",
    "sg:classifiers":[
        {
            "category":"Food & Beverages",
            "subcategory":"Groceries & Convenience Stores",
            "type":"Retail Goods"
        }
    ],
    "sg:phone":"+1 352 683 3424",
    "sg:postcode":"34606",
    "sg:province":"FL",
    "sg:tags":[
        "supermarket"
    ],
    "wof:name":"Kash N Karry Store 1788",
    "wof:placetype":"venue"
},
  "geometry": {"coordinates":[-82.62250299999999,28.46587],"type":"Point"}
}