{
  "type": "Feature",
  "properties": {
    "addr:full":"2363 SW 15th St Miami FL 33145",
    "addr:housenumber":"2363",
    "addr:postcode":"33145",
    "addr:street":"Sw 15Th St",
    "iso:country":"US",
    "sg:address":"2363 SW 15th St",
    "sg:city":"Miami",
    "sg:classifiers":[
        {
            "category":"Travel",
            "subcategory":"Travel Agent",
            "type":"Entertainment"
        }
    ],
    "sg:phone":"+1 305 740 9898",
    "sg:postcode":"33145",
    "sg:province":"FL",
    "sg:tags":[
        "agency",
        "services-commercial"
    ],
    "sg:website":"http://www.destinationcruises.com",
    "wof:name":"Destination Travel Center",
    "wof:placetype":"venue"
},
  "geometry": {"coordinates":[-80.233761,25.758883],"type":"Point"}
}