{
  "type": "Feature",
  "properties": {
    "iso:country":"US",
    "sg:address":"4600 Summerlin Rd Ste C3",
    "sg:city":"Fort Myers",
    "sg:classifiers":[
        {
            "category":"Restaurant",
            "type":"Food & Drink"
        }
    ],
    "sg:phone":"+1 239 939 3779",
    "sg:postcode":"33919",
    "sg:province":"FL",
    "wof:name":"Something Special Cafe",
    "wof:placetype":"venue"
},
  "geometry": {"coordinates":[-81.88400300000001,26.5959],"type":"Point"}
}