{
  "type": "Feature",
  "properties": {
    "addr:full":"600 E Strawbridge Ave Melbourne FL 32901",
    "addr:housenumber":"600",
    "addr:postcode":"32901",
    "addr:street":"E Strawbridge Ave",
    "iso:country":"US",
    "sg:address":"600 E Strawbridge Ave",
    "sg:city":"Melbourne",
    "sg:classifiers":[
        {
            "category":"Banks & Credit Unions",
            "subcategory":"Investment Brokerage",
            "type":"Services"
        }
    ],
    "sg:phone":"+1 321 984 2152",
    "sg:postcode":"32901",
    "sg:province":"FL",
    "sg:tags":[
        "advisory",
        "financial"
    ],
    "wof:name":"Sound Financial Solutions",
    "wof:placetype":"venue"
},
  "geometry": {"coordinates":[-80.609606,28.079461],"type":"Point"}
}