{
  "type": "Feature",
  "properties": {
    "iso:country":"US",
    "sg:address":"6041 Bartholf Ave",
    "sg:city":"Jacksonville",
    "sg:classifiers":[
        {
            "category":"Wholesale",
            "subcategory":"Machinery & Supplies",
            "type":"Manufacturing & Wholesale Goods"
        }
    ],
    "sg:phone":"+1 904 779 0602",
    "sg:postcode":"32210",
    "sg:province":"FL",
    "sg:tags":[
        "equipment",
        "irrigation",
        "system"
    ],
    "wof:name":"Lawn Sculptors",
    "wof:placetype":"venue"
},
  "geometry": {"coordinates":[-81.740484,30.263256],"type":"Point"}
}