{
  "type": "Feature",
  "properties": {
    "addr:full":"115 Spring Lake Cir Ocoee FL 34761",
    "addr:housenumber":"115",
    "addr:postcode":"34761",
    "addr:street":"Spring Lake Cir",
    "iso:country":"US",
    "sg:address":"115 Spring Lake Cir",
    "sg:city":"Ocoee",
    "sg:classifiers":[
        {
            "category":"Education",
            "subcategory":"School",
            "type":"Public Place"
        }
    ],
    "sg:phone":"+1 407 877 5047",
    "sg:postcode":"34761",
    "sg:province":"FL",
    "sg:tags":[
        "elementary"
    ],
    "sg:website":"http://www.tchsbands.com",
    "wof:name":"Spring Lake Elementary School",
    "wof:placetype":"venue"
},
  "geometry": {"coordinates":[-81.525527,28.585539],"type":"Point"}
}