{
  "type": "Feature",
  "properties": {
    "addr:full":"145 Jet Dr NW Fort Walton Beach FL 32548",
    "addr:housenumber":"145",
    "addr:postcode":"32548",
    "addr:street":"Jet Dr Nw",
    "iso:country":"US",
    "sg:address":"145 Jet Dr NW",
    "sg:city":"Fort Walton Beach",
    "sg:classifiers":[
        {
            "category":"Autos & Motor Vehicles",
            "subcategory":"Motorcycle Sales",
            "type":"Retail Goods"
        }
    ],
    "sg:phone":"+1 850 864 5931",
    "sg:postcode":"32548",
    "sg:province":"FL",
    "wof:name":"Xtrskn",
    "wof:placetype":"venue"
},
  "geometry": {"coordinates":[-86.6271,30.418436],"type":"Point"}
}