{
  "type": "Feature",
  "properties": {
    "addr:full":"9958 NW 18th St Pembroke Pines FL 33024",
    "addr:housenumber":"9958",
    "addr:postcode":"33024",
    "addr:street":"Nw 18Th St",
    "iso:country":"US",
    "sg:address":"9958 NW 18th St",
    "sg:city":"Pembroke Pines",
    "sg:classifiers":[
        {
            "category":"Real Estate",
            "subcategory":"Real Estate Agent",
            "type":"Services"
        }
    ],
    "sg:phone":"+1 954 499 0795",
    "sg:postcode":"33024",
    "sg:province":"FL",
    "sg:tags":[
        "investment"
    ],
    "wof:name":"Royal Returns Inc",
    "wof:placetype":"venue"
},
  "geometry": {"coordinates":[-80.278116,26.023231],"type":"Point"}
}