{
  "type": "Feature",
  "properties": {
    "iso:country":"US",
    "sg:address":"2778 S Westmoreland Dr",
    "sg:city":"Orlando",
    "sg:classifiers":[
        {
            "category":"Social Services",
            "subcategory":"Child Care",
            "type":"Services"
        }
    ],
    "sg:phone":"+1 407 843 9265",
    "sg:postcode":"32805",
    "sg:province":"FL",
    "sg:tags":[
        "day"
    ],
    "wof:name":"ABC Learning Tree",
    "wof:placetype":"venue"
},
  "geometry": {"coordinates":[-81.39293000000001,28.514453],"type":"Point"}
}