{
  "type": "Feature",
  "properties": {
    "addr:full":"15696 71st Dr N Palm Beach Gardens FL 33418",
    "addr:housenumber":"15696",
    "addr:postcode":"33418",
    "addr:street":"71St Dr N",
    "iso:country":"US",
    "sg:address":"15696 71st Dr N",
    "sg:city":"Palm Beach Gardens",
    "sg:classifiers":[
        {
            "category":"Shopping",
            "subcategory":"Stationery & Office Supplies",
            "type":"Retail Goods"
        },
        {
            "category":"Wholesale",
            "subcategory":"Durable Goods & Equipment",
            "type":"Manufacturing & Wholesale Goods"
        }
    ],
    "sg:phone":"+1 561 745 4934",
    "sg:postcode":"33418",
    "sg:province":"FL",
    "sg:tags":[
        "rubber",
        "stamp",
        "brass",
        "plastic"
    ],
    "wof:name":"Adamz Originals Inc",
    "wof:placetype":"venue"
},
  "geometry": {"coordinates":[-80.145565,26.908051],"type":"Point"}
}