{
  "type": "Feature",
  "properties": {
    "addr:full":"180 NE 4th Ave Delray Beach FL 33483",
    "addr:housenumber":"180",
    "addr:postcode":"33483",
    "addr:street":"Ne 4Th Ave",
    "iso:country":"US",
    "sg:address":"180 NE 4th Ave",
    "sg:city":"Delray Beach",
    "sg:classifiers":[
        {
            "category":"Real Estate",
            "subcategory":"Real Estate Operator",
            "type":"Services"
        }
    ],
    "sg:phone":"+1 561 330 3217",
    "sg:postcode":"33483",
    "sg:province":"FL",
    "sg:tags":[
        "building",
        "parks"
    ],
    "wof:name":"Ocean City Lofts",
    "wof:placetype":"venue"
},
  "geometry": {"coordinates":[-80.06918899999999,26.463809],"type":"Point"}
}