{
  "type": "Feature",
  "properties": {
    "iso:country":"US",
    "sg:address":"16085 NW 52nd Ave",
    "sg:city":"Hialeah",
    "sg:classifiers":[
        {
            "category":"Sports & Exercise",
            "subcategory":"Bicycle Rental",
            "type":"Entertainment"
        }
    ],
    "sg:phone":"+1 305 624 4228",
    "sg:postcode":"33014",
    "sg:province":"FL",
    "sg:tags":[
        "wear"
    ],
    "wof:name":"Richland Apparel",
    "wof:placetype":"venue"
},
  "geometry": {"coordinates":[-80.28476999999999,25.919548],"type":"Point"}
}