{
  "type": "Feature",
  "properties": {
    "iso:country":"US",
    "sg:address":"726 12th St E",
    "sg:city":"Bradenton",
    "sg:classifiers":[
        {
            "category":"Organizations",
            "subcategory":"Religious Organization",
            "type":"Services"
        }
    ],
    "sg:phone":"+1 941 747 9127",
    "sg:postcode":"34208",
    "sg:province":"FL",
    "sg:tags":[
        "church"
    ],
    "wof:name":"Truth Bible Church Of God",
    "wof:placetype":"venue"
},
  "geometry": {"coordinates":[-82.55054800000001,27.493182],"type":"Point"}
}