{
  "type": "Feature",
  "properties": {
    "iso:country":"US",
    "sg:address":"4000 N 40th St",
    "sg:city":"Hollywood",
    "sg:classifiers":[
        {
            "category":"Health Services",
            "subcategory":"Dentist",
            "type":"Services"
        }
    ],
    "sg:phone":"+1 954 983 4979",
    "sg:postcode":"33021",
    "sg:province":"FL",
    "wof:name":"Harvey Pereta Dds",
    "wof:placetype":"venue"
},
  "geometry": {"coordinates":[-80.18395200000001,26.045469],"type":"Point"}
}