{
  "type": "Feature",
  "properties": {
    "iso:country":"US",
    "sg:address":"110 SE 6th St",
    "sg:city":"Fort Lauderdale",
    "sg:classifiers":[
        {
            "category":"Professional",
            "subcategory":"Lawyer & Legal Services",
            "type":"Services"
        }
    ],
    "sg:phone":"+1 954 761 7116",
    "sg:postcode":"33301",
    "sg:province":"FL",
    "sg:tags":[
        "attorney"
    ],
    "wof:name":"Stephen H Butter",
    "wof:placetype":"venue"
},
  "geometry": {"coordinates":[-80.140326,26.114758],"type":"Point"}
}