{
  "type": "Feature",
  "properties": {
    "iso:country":"US",
    "sg:address":"1290 Mimosa Ct",
    "sg:city":"Marco Island",
    "sg:classifiers":[
        {
            "category":"Building & Trades",
            "subcategory":"Landscaping Services",
            "type":"Services"
        }
    ],
    "sg:phone":"+1 239 642 8060",
    "sg:postcode":"34145",
    "sg:province":"FL",
    "sg:tags":[
        "landscape"
    ],
    "wof:name":"Welsby Inc",
    "wof:placetype":"venue"
},
  "geometry": {"coordinates":[-81.716798,25.917434],"type":"Point"}
}