{
  "type": "Feature",
  "properties": {
    "addr:full":"800 Carlton Ct Winter Haven FL 33884",
    "addr:housenumber":"800",
    "addr:postcode":"33884",
    "addr:street":"Carlton Ct",
    "iso:country":"US",
    "sg:address":"800 Carlton Ct",
    "sg:city":"Winter Haven",
    "sg:classifiers":[
        {
            "category":"Building & Trades",
            "subcategory":"Construction",
            "type":"Services"
        }
    ],
    "sg:phone":"+1 863 324 5588",
    "sg:postcode":"33884",
    "sg:province":"FL",
    "sg:tags":[
        "pipeline",
        "installation"
    ],
    "wof:name":"Pipeline Maintenance & Svcs",
    "wof:placetype":"venue"
},
  "geometry": {"coordinates":[-81.708758,27.964395],"type":"Point"}
}