{
  "type": "Feature",
  "properties": {
    "addr:full":"2683 Saint Johns Bluff Rd S Jacksonville FL 32246",
    "addr:housenumber":"2683",
    "addr:postcode":"32246",
    "addr:street":"Saint Johns Bluff Rd",
    "iso:country":"US",
    "sg:address":"2683 Saint Johns Bluff Rd S",
    "sg:city":"Jacksonville",
    "sg:classifiers":[
        {
            "category":"Shopping",
            "type":"Retail Goods"
        }
    ],
    "sg:phone":"+1 904 996 9305",
    "sg:postcode":"32246",
    "sg:province":"FL",
    "sg:tags":[
        "spa",
        "hot",
        "tub"
    ],
    "wof:name":"Steam Room USA Of Florida",
    "wof:placetype":"venue"
},
  "geometry": {"coordinates":[-81.52579299999999,30.298348],"type":"Point"}
}