{
  "type": "Feature",
  "properties": {
    "addr:full":"581 NW 183rd St Miami FL 33169",
    "addr:housenumber":"581",
    "addr:postcode":"33169",
    "addr:street":"Nw 183Rd St",
    "iso:country":"US",
    "sg:address":"581 NW 183rd St",
    "sg:city":"Miami",
    "sg:classifiers":[
        {
            "category":"Health Services",
            "subcategory":"Doctor",
            "type":"Services"
        }
    ],
    "sg:phone":"+1 305 651 2334",
    "sg:postcode":"33169",
    "sg:province":"FL",
    "sg:tags":[
        "physician",
        "surgeon",
        "pediatrics",
        "surgeons"
    ],
    "wof:name":"Jaraki Pediatrics Inc",
    "wof:placetype":"venue"
},
  "geometry": {"coordinates":[-80.21066,25.942384],"type":"Point"}
}