{
  "type": "Feature",
  "properties": {
    "iso:country":"US",
    "sg:address":"112 N County Rd",
    "sg:city":"Palm Beach",
    "sg:classifiers":[
        {
            "category":"Shopping",
            "subcategory":"Used Merchandise",
            "type":"Retail Goods"
        }
    ],
    "sg:phone":"+1 561 655 5188",
    "sg:postcode":"33480",
    "sg:province":"FL",
    "wof:name":"French Heritage Antiques",
    "wof:placetype":"venue"
},
  "geometry": {"coordinates":[-80.03791699999999,26.71858],"type":"Point"}
}