{
  "type": "Feature",
  "properties": {
    "iso:country":"US",
    "sg:address":"11524 Perkle Rd",
    "sg:city":"Lakeland",
    "sg:classifiers":[
        {
            "category":"Building & Trades",
            "subcategory":"Construction",
            "type":"Services"
        }
    ],
    "sg:phone":"+1 863 858 6142",
    "sg:postcode":"33809",
    "sg:province":"FL",
    "sg:tags":[
        "hanging",
        "contractor"
    ],
    "wof:name":"Nicks M L Roofing Sheet Metal",
    "wof:placetype":"venue"
},
  "geometry": {"coordinates":[-82.003848,28.213753],"type":"Point"}
}