{
  "type": "Feature",
  "properties": {
    "addr:full":"16 Ferry Rd SE Fort Walton Beach FL 32548",
    "addr:housenumber":"16",
    "addr:postcode":"32548",
    "addr:street":"Ferry Rd Se",
    "iso:country":"US",
    "sg:address":"16 Ferry Rd SE",
    "sg:city":"Fort Walton Beach",
    "sg:classifiers":[
        {
            "category":"Banks & Credit Unions",
            "subcategory":"Financial Services",
            "type":"Services"
        }
    ],
    "sg:phone":"+1 850 244 5713",
    "sg:postcode":"32548",
    "sg:province":"FL",
    "sg:tags":[
        "trust",
        "investment",
        "real estate"
    ],
    "wof:name":"Carl A Deramus Repairs",
    "wof:placetype":"venue"
},
  "geometry": {"coordinates":[-86.600419,30.411797],"type":"Point"}
}