{
  "type": "Feature",
  "properties": {
    "iso:country":"US",
    "sg:address":"3715 Crystal Springs Rd",
    "sg:city":"Zephyrhills",
    "sg:classifiers":[
        {
            "category":"Recreation",
            "subcategory":"Campground",
            "type":"Entertainment"
        }
    ],
    "sg:phone":"+1 813 788 6675",
    "sg:postcode":"33541",
    "sg:province":"FL",
    "sg:tags":[
        "recreational",
        "park",
        "vehicle"
    ],
    "wof:name":"Sandollar R.V. Park",
    "wof:placetype":"venue"
},
  "geometry": {"coordinates":[-82.18283099999999,28.210434],"type":"Point"}
}