{
  "type": "Feature",
  "properties": {
    "iso:country":"US",
    "sg:address":"2620 SE Willoughby Blvd",
    "sg:city":"Stuart",
    "sg:classifiers":[
        {
            "category":"Recreation",
            "type":"Entertainment"
        }
    ],
    "sg:phone":"+1 772 288 2468",
    "sg:postcode":"34994",
    "sg:province":"FL",
    "sg:tags":[
        "martial",
        "arts",
        "instruction"
    ],
    "wof:name":"Us Tae KWON Do College",
    "wof:placetype":"venue"
},
  "geometry": {"coordinates":[-80.24703,27.174452],"type":"Point"}
}