{
  "type": "Feature",
  "properties": {
    "iso:country":"US",
    "sg:address":"3203 Lime Tree Dr",
    "sg:city":"Edgewater",
    "sg:classifiers":[
        {
            "category":"Building & Trades",
            "subcategory":"Construction",
            "type":"Services"
        }
    ],
    "sg:phone":"+1 386 427 6662",
    "sg:postcode":"32141",
    "sg:province":"FL",
    "sg:tags":[
        "contractor"
    ],
    "wof:name":"Mastercraft",
    "wof:placetype":"venue"
},
  "geometry": {"coordinates":[-80.89375099999999,28.940103],"type":"Point"}
}