{
  "type": "Feature",
  "properties": {
    "iso:country":"US",
    "sg:address":"5414 Swaying Palm Dr",
    "sg:city":"Punta Gorda",
    "sg:classifiers":[
        {
            "category":"Building & Trades",
            "subcategory":"Equipment Rental",
            "type":"Services"
        }
    ],
    "sg:phone":"+1 941 575 6636",
    "sg:postcode":"33982",
    "sg:province":"FL",
    "wof:name":"Fun Equipment Rental",
    "wof:placetype":"venue"
},
  "geometry": {"coordinates":[-81.95001499999999,26.956975],"type":"Point"}
}