{
  "type": "Feature",
  "properties": {
    "iso:country":"US",
    "sg:address":"9880 Gulfshore Dr",
    "sg:city":"Naples",
    "sg:classifiers":[
        {
            "category":"Professional",
            "type":"Services"
        }
    ],
    "sg:phone":"+1 239 596 7332",
    "sg:postcode":"34108",
    "sg:province":"FL",
    "sg:tags":[
        "establishment"
    ],
    "wof:name":"Prestress Systems Of Florida",
    "wof:placetype":"venue"
},
  "geometry": {"coordinates":[-81.822756,26.254666],"type":"Point"}
}