{
  "type": "Feature",
  "properties": {
    "iso:country":"US",
    "sg:address":"3141 US Hwy 19",
    "sg:city":"Holiday",
    "sg:classifiers":[
        {
            "category":"Autos & Motor Vehicles",
            "subcategory":"Recreational Vehicle Sales",
            "type":"Retail Goods"
        }
    ],
    "sg:phone":"+1 727 939 0800",
    "sg:postcode":"34691",
    "sg:province":"FL",
    "sg:website":"www.sunrv.com",
    "wof:name":"Sun RV Superstore",
    "wof:placetype":"venue"
},
  "geometry": {"coordinates":[-82.73986600000001,28.20326],"type":"Point"}
}