{
  "type": "Feature",
  "properties": {
    "addr:full":"822 W Central Blvd Orlando FL 32805",
    "addr:housenumber":"822",
    "addr:postcode":"32805",
    "addr:street":"W Central Blvd",
    "iso:country":"US",
    "sg:address":"822 W Central Blvd",
    "sg:city":"Orlando",
    "sg:classifiers":[
        {
            "category":"Building & Trades",
            "subcategory":"Construction",
            "type":"Services"
        }
    ],
    "sg:phone":"+1 407 849 0436",
    "sg:postcode":"32805",
    "sg:province":"FL",
    "sg:tags":[
        "contractor",
        "commercial",
        "general"
    ],
    "sg:website":"www.akholcomb.com",
    "wof:name":"A K Holcomb Construction Inc",
    "wof:placetype":"venue"
},
  "geometry": {"coordinates":[-81.390923,28.541919],"type":"Point"}
}