{
  "type": "Feature",
  "properties": {
    "addr:full":"8820 Gall Blvd Zephyrhills FL 33541",
    "addr:postcode":"8820;33541",
    "addr:street":"Gall Blvd",
    "iso:country":"US",
    "sg:address":"8820 Gall Blvd",
    "sg:city":"Zephyrhills",
    "sg:classifiers":[
        {
            "category":"Autos & Motor Vehicles",
            "subcategory":"Motorcycle Sales",
            "type":"Retail Goods"
        }
    ],
    "sg:phone":"+1 813 788 1779",
    "sg:postcode":"33541",
    "sg:province":"FL",
    "sg:tags":[
        "scooter"
    ],
    "wof:name":"Cahill's Motor Sports LLC",
    "wof:placetype":"venue"
},
  "geometry": {"coordinates":[-82.187803,28.286636],"type":"Point"}
}