{
  "type": "Feature",
  "properties": {
    "iso:country":"US",
    "sg:address":"1253 Washington Ave Ste 222",
    "sg:city":"Miami Beach",
    "sg:classifiers":[
        {
            "category":"Real Estate",
            "subcategory":"Architect",
            "type":"Services"
        }
    ],
    "sg:phone":"+1 786 276 6000",
    "sg:postcode":"33139",
    "sg:province":"FL",
    "wof:name":"Mouzon Properties",
    "wof:placetype":"venue"
},
  "geometry": {"coordinates":[-80.131989,25.783599],"type":"Point"}
}