{
  "type": "Feature",
  "properties": {
    "addr:full":"815 Beachland Blvd Vero Beach FL 32963",
    "addr:housenumber":"815",
    "addr:postcode":"32963",
    "addr:street":"Beachland Blvd",
    "iso:country":"US",
    "sg:address":"815 Beachland Blvd",
    "sg:city":"Vero Beach",
    "sg:classifiers":[
        {
            "category":"Building & Trades",
            "subcategory":"Construction",
            "type":"Services"
        }
    ],
    "sg:phone":"+1 772 234 3950",
    "sg:postcode":"32963",
    "sg:province":"FL",
    "sg:tags":[
        "heavy",
        "maintenance"
    ],
    "wof:name":"Sandpipers Inc",
    "wof:placetype":"venue"
},
  "geometry": {"coordinates":[-80.35784200000001,27.653467],"type":"Point"}
}