{
  "type": "Feature",
  "properties": {
    "addr:full":"8520 Pocassett Pl Orlando FL 32827",
    "addr:housenumber":"8520",
    "addr:postcode":"32827",
    "addr:street":"Pocassett Pl",
    "iso:country":"US",
    "sg:address":"8520 Pocassett Pl",
    "sg:city":"Orlando",
    "sg:classifiers":[
        {
            "category":"Professional",
            "type":"Services"
        }
    ],
    "sg:phone":"+1 407 852 0788",
    "sg:postcode":"32827",
    "sg:province":"FL",
    "wof:name":"Mark Legrand",
    "wof:placetype":"venue"
},
  "geometry": {"coordinates":[-81.34475399999999,28.442978],"type":"Point"}
}