{
  "type": "Feature",
  "properties": {
    "addr:full":"214 Palmetto St New Smyrna Beach FL 32168",
    "addr:housenumber":"214",
    "addr:postcode":"32168",
    "addr:street":"Palmetto St",
    "iso:country":"US",
    "sg:address":"214 Palmetto St",
    "sg:city":"New Smyrna Beach",
    "sg:classifiers":[
        {
            "category":"Wholesale",
            "subcategory":"Machinery & Supplies",
            "type":"Manufacturing & Wholesale Goods"
        }
    ],
    "sg:phone":"+1 386 428 4054",
    "sg:postcode":"32168",
    "sg:province":"FL",
    "sg:tags":[
        "contractor"
    ],
    "wof:name":"Find Equipment Co",
    "wof:placetype":"venue"
},
  "geometry": {"coordinates":[-80.923653,29.022675],"type":"Point"}
}