{
  "type": "Feature",
  "properties": {
    "addr:full":"5203 7th St W Lehigh Acres FL 33971",
    "addr:housenumber":"5203",
    "addr:postcode":"33971",
    "addr:street":"7Th St W",
    "iso:country":"US",
    "sg:address":"5203 7th St W",
    "sg:city":"Lehigh Acres",
    "sg:classifiers":[
        {
            "category":"Restaurant",
            "type":"Food & Drink"
        }
    ],
    "sg:phone":"+1 239 368 4661",
    "sg:postcode":"33971",
    "sg:province":"FL",
    "sg:tags":[
        "caterer"
    ],
    "wof:name":"Jim Bob's Bar-B-Que",
    "wof:placetype":"venue"
},
  "geometry": {"coordinates":[-81.735737,26.619346],"type":"Point"}
}