{
  "type": "Feature",
  "properties": {
    "iso:country":"US",
    "sg:address":"9816 S Military Trl",
    "sg:city":"Boynton Beach",
    "sg:classifiers":[
        {
            "category":"Wholesale",
            "subcategory":"Machinery & Supplies",
            "type":"Manufacturing & Wholesale Goods"
        }
    ],
    "sg:phone":"+1 561 742 2823",
    "sg:postcode":"33436",
    "sg:province":"FL",
    "sg:tags":[
        "manufacturer",
        "retailer",
        "sign"
    ],
    "wof:name":"Sign-A-Rama",
    "wof:placetype":"venue"
},
  "geometry": {"coordinates":[-80.122773,26.530428],"type":"Point"}
}