{
  "type": "Feature",
  "properties": {
    "addr:full":"100 S Hogan St Jacksonville FL 32202",
    "addr:housenumber":"100",
    "addr:postcode":"32202",
    "addr:street":"S Hogan St",
    "iso:country":"US",
    "sg:address":"100 S Hogan St",
    "sg:city":"Jacksonville",
    "sg:classifiers":[
        {
            "category":"Professional",
            "subcategory":"Detective & Security Services",
            "type":"Services"
        }
    ],
    "sg:phone":"+1 904 355 0979",
    "sg:postcode":"32202",
    "sg:province":"FL",
    "sg:tags":[
        "system"
    ],
    "wof:name":"Florida Door Ctrl of Orlando",
    "wof:placetype":"venue"
},
  "geometry": {"coordinates":[-81.66108699999999,30.325312],"type":"Point"}
}