{
  "type": "Feature",
  "properties": {
    "iso:country":"US",
    "sg:address":"2101 S Combee Rd",
    "sg:city":"Lakeland",
    "sg:classifiers":[
        {
            "category":"Restaurant",
            "type":"Food & Drink"
        }
    ],
    "sg:phone":"+1 863 667 2300",
    "sg:postcode":"33801",
    "sg:province":"FL",
    "wof:name":"Mike's Deli",
    "wof:placetype":"venue"
},
  "geometry": {"coordinates":[-81.907878,28.021844],"type":"Point"}
}