{
  "type": "Feature",
  "properties": {
    "addr:full":"6238 SW 59th St South Miami FL 33143",
    "addr:housenumber":"6238",
    "addr:postcode":"33143",
    "addr:street":"Sw 59Th St",
    "iso:country":"US",
    "sg:address":"6238 SW 59th St",
    "sg:city":"South Miami",
    "sg:classifiers":[
        {
            "category":"Personal",
            "subcategory":"Beauty Salon",
            "type":"Services"
        }
    ],
    "sg:phone":"+1 305 667 0840",
    "sg:postcode":"33143",
    "sg:province":"FL",
    "wof:name":"Garbutts Hair & Nails",
    "wof:placetype":"venue"
},
  "geometry": {"coordinates":[-80.29495799999999,25.715726],"type":"Point"}
}