{
  "type": "Feature",
  "properties": {
    "iso:country":"US",
    "sg:address":"2718 Oak Bend Ct",
    "sg:city":"New Port Richey",
    "sg:classifiers":[
        {
            "category":"Professional",
            "subcategory":"Art Services",
            "type":"Services"
        }
    ],
    "sg:phone":"+1 727 376 6451",
    "sg:postcode":"34655",
    "sg:province":"FL",
    "sg:tags":[
        "artist"
    ],
    "wof:name":"Heaven Sent Artistic Designs",
    "wof:placetype":"venue"
},
  "geometry": {"coordinates":[-82.69822600000001,28.199448],"type":"Point"}
}