{
  "type": "Feature",
  "properties": {
    "iso:country":"US",
    "sg:address":"18141 Matt Rd",
    "sg:city":"Fort Myers",
    "sg:classifiers":[
        {
            "category":"Home & Garden",
            "subcategory":"Garden Supply",
            "type":"Retail Goods"
        }
    ],
    "sg:phone":"+1 239 567 0700",
    "sg:postcode":"33917",
    "sg:province":"FL",
    "sg:tags":[
        "sprinkler"
    ],
    "wof:name":"Spirit Filled Sprinkler System",
    "wof:placetype":"venue"
},
  "geometry": {"coordinates":[-81.854214,26.729454],"type":"Point"}
}