{
  "type": "Feature",
  "properties": {
    "addr:full":"860 US Hwy 98 Destin FL 32541",
    "addr:housenumber":"860",
    "addr:postcode":"32541",
    "addr:street":"Us Hwy 98",
    "iso:country":"US",
    "sg:address":"860 US Hwy 98",
    "sg:city":"Destin",
    "sg:classifiers":[
        {
            "category":"Shopping",
            "type":"Retail Goods"
        }
    ],
    "sg:phone":"+1 850 650 7791",
    "sg:postcode":"32541",
    "sg:province":"FL",
    "sg:tags":[
        "art",
        "gallery",
        "dealer"
    ],
    "wof:name":"Art-Itude",
    "wof:placetype":"venue"
},
  "geometry": {"coordinates":[-86.48241899999999,30.389227],"type":"Point"}
}