{
  "type": "Feature",
  "properties": {
    "iso:country":"US",
    "sg:address":"2702 W Azeele St",
    "sg:city":"Tampa",
    "sg:classifiers":[
        {
            "category":"Personal",
            "type":"Services"
        }
    ],
    "sg:phone":"+1 813 354 8800",
    "sg:postcode":"33609",
    "sg:province":"FL",
    "wof:name":"Body & Mind Massage Inc",
    "wof:placetype":"venue"
},
  "geometry": {"coordinates":[-82.487844,27.941036],"type":"Point"}
}