{
  "type": "Feature",
  "properties": {
    "addr:full":"850 County Line Rd Lakeland FL 33815",
    "addr:housenumber":"850",
    "addr:postcode":"33815",
    "addr:street":"County Line Rd",
    "iso:country":"US",
    "sg:address":"850 County Line Rd",
    "sg:city":"Lakeland",
    "sg:classifiers":[
        {
            "category":"Fast Food",
            "type":"Food & Drink"
        },
        {
            "category":"Restaurant",
            "type":"Food & Drink"
        },
        {
            "category":"Food & Beverages",
            "subcategory":"Groceries & Convenience Stores",
            "type":"Retail Goods"
        }
    ],
    "sg:phone":"+1 863 802 1780",
    "sg:postcode":"33815",
    "sg:province":"FL",
    "sg:tags":[
        "shop",
        "american",
        "sandwich",
        "take"
    ],
    "sg:website":"http://www.subway.com",
    "wof:name":"Subway",
    "wof:placetype":"venue"
},
  "geometry": {"coordinates":[-82.05587,28.032971],"type":"Point"}
}