{
  "type": "Feature",
  "properties": {
    "addr:full":"207 S Walnut St Starke FL 32091",
    "addr:housenumber":"207",
    "addr:postcode":"32091",
    "addr:street":"S Walnut St",
    "iso:country":"US",
    "sg:address":"207 S Walnut St",
    "sg:city":"Starke",
    "sg:classifiers":[
        {
            "category":"Health Services",
            "subcategory":"Optometrist",
            "type":"Services"
        }
    ],
    "sg:phone":"+1 904 964 6311",
    "sg:postcode":"32091",
    "sg:province":"FL",
    "wof:name":"D W Whiffen OD",
    "wof:placetype":"venue"
},
  "geometry": {"coordinates":[-82.110125,29.943376],"type":"Point"}
}