{
  "type": "Feature",
  "properties": {
    "iso:country":"US",
    "sg:address":"1648 Pine Bay Dr",
    "sg:city":"Lake Mary",
    "sg:classifiers":[
        {
            "category":"Building & Trades",
            "subcategory":"Electrical",
            "type":"Services"
        }
    ],
    "sg:phone":"+1 407 333 1417",
    "sg:postcode":"32746",
    "sg:province":"FL",
    "sg:tags":[
        "installation"
    ],
    "wof:name":"Tim Phillips Creative",
    "wof:placetype":"venue"
},
  "geometry": {"coordinates":[-81.368172,28.73095],"type":"Point"}
}