{
  "type": "Feature",
  "properties": {
    "iso:country":"US",
    "sg:address":"4436 Stacey Cir",
    "sg:city":"Milton",
    "sg:classifiers":[
        {
            "category":"Shopping",
            "type":"Retail Goods"
        }
    ],
    "sg:phone":"+1 850 626 6456",
    "sg:postcode":"32583",
    "sg:province":"FL",
    "sg:tags":[
        "merchandise"
    ],
    "wof:name":"Kevin L Lech Picture Frames",
    "wof:placetype":"venue"
},
  "geometry": {"coordinates":[-87.088342,30.596515],"type":"Point"}
}