{
  "type": "Feature",
  "properties": {
    "addr:full":"5901 S Farragut Dr Hollywood FL 33021",
    "addr:housenumber":"5901",
    "addr:postcode":"33021",
    "addr:street":"S Farragut Dr",
    "iso:country":"US",
    "sg:address":"5901 S Farragut Dr",
    "sg:city":"Hollywood",
    "sg:phone":"+1 954 981 1221",
    "sg:postcode":"33021",
    "sg:province":"FL",
    "sg:tags":[
        "scale"
    ],
    "wof:name":"Vikeen Systems Inc",
    "wof:placetype":"venue"
},
  "geometry": {"coordinates":[-80.20734299999999,26.03398],"type":"Point"}
}