{
  "type": "Feature",
  "properties": {
    "addr:full":"4932 Woodbine Rd Milton FL 32571",
    "addr:housenumber":"4932",
    "addr:postcode":"32571",
    "addr:street":"Woodbine Rd",
    "iso:country":"US",
    "sg:address":"4932 Woodbine Rd",
    "sg:city":"Milton",
    "sg:classifiers":[
        {
            "category":"Wholesale",
            "subcategory":"Books, Periodicals, & Newspapers",
            "type":"Manufacturing & Wholesale Goods"
        }
    ],
    "sg:phone":"+1 850 994 7340",
    "sg:postcode":"32571",
    "sg:province":"FL",
    "sg:tags":[
        "publisher",
        "book"
    ],
    "sg:website":"http://www.tomterrific.com",
    "wof:name":"Tom Terrific Publications",
    "wof:placetype":"venue"
},
  "geometry": {"coordinates":[-87.181747,30.625992],"type":"Point"}
}