{
  "type": "Feature",
  "properties": {
    "iso:country":"US",
    "sg:address":"1980 Ave L",
    "sg:city":"Riviera Beach",
    "sg:classifiers":[
        {
            "category":"Autos & Motor Vehicles",
            "subcategory":"Automobile Sales",
            "type":"Retail Goods"
        }
    ],
    "sg:phone":"+1 561 842 5843",
    "sg:postcode":"33404",
    "sg:province":"FL",
    "sg:tags":[
        "car",
        "dealer"
    ],
    "wof:name":"Mosler Automotive",
    "wof:placetype":"venue"
},
  "geometry": {"coordinates":[-80.06828299999999,26.780166],"type":"Point"}
}