{
  "type": "Feature",
  "properties": {
    "iso:country":"US",
    "sg:address":"1901 SE 37th Court Cir",
    "sg:city":"Ocala",
    "sg:classifiers":[
        {
            "category":"Shopping",
            "subcategory":"Used Merchandise",
            "type":"Retail Goods"
        }
    ],
    "sg:phone":"+1 352 624 3093",
    "sg:postcode":"34471",
    "sg:province":"FL",
    "sg:tags":[
        "resale",
        "shop"
    ],
    "wof:name":"Consignment Gallery",
    "wof:placetype":"venue"
},
  "geometry": {"coordinates":[-82.086288,29.168489],"type":"Point"}
}