{
  "type": "Feature",
  "properties": {
    "addr:full":"8220 W 30th Ct Hialeah FL 33018",
    "addr:housenumber":"8220",
    "addr:postcode":"33018",
    "addr:street":"W 30Th Ct",
    "iso:country":"US",
    "sg:address":"8220 W 30th Ct",
    "sg:city":"Hialeah",
    "sg:classifiers":[
        {
            "category":"Banks & Credit Unions",
            "subcategory":"Bank",
            "type":"Services"
        }
    ],
    "sg:phone":"+1 305 558 2525",
    "sg:postcode":"33018",
    "sg:province":"FL",
    "sg:tags":[
        "depository",
        "banking",
        "check",
        "cashing"
    ],
    "wof:name":"Montero's Check Cashing",
    "wof:placetype":"venue"
},
  "geometry": {"coordinates":[-80.345358,25.896169],"type":"Point"}
}