{
  "type": "Feature",
  "properties": {
    "addr:full":"3309 14th St Elkton FL 32033",
    "addr:housenumber":"3309",
    "addr:postcode":"32033",
    "addr:street":"14Th St",
    "iso:country":"US",
    "sg:address":"3309 14th St",
    "sg:city":"Elkton",
    "sg:classifiers":[
        {
            "category":"Home & Garden",
            "subcategory":"Building Materials",
            "type":"Retail Goods"
        }
    ],
    "sg:phone":"+1 904 272 2070",
    "sg:postcode":"32033",
    "sg:province":"FL",
    "sg:tags":[
        "door"
    ],
    "wof:name":"Associated Doors",
    "wof:placetype":"venue"
},
  "geometry": {"coordinates":[-81.394391,29.807046],"type":"Point"}
}