{
  "type": "Feature",
  "properties": {
    "iso:country":"US",
    "sg:address":"3801 W Lake Mary Blvd Unit 163",
    "sg:city":"Lake Mary",
    "sg:classifiers":[
        {
            "category":"Education",
            "subcategory":"Special Training",
            "type":"Public Place"
        }
    ],
    "sg:phone":"+1 407 322 2219",
    "sg:postcode":"32746",
    "sg:province":"FL",
    "sg:tags":[
        "tutoring"
    ],
    "sg:website":"lake_mary.huntingtonlearning.com",
    "wof:name":"Huntington Learning Center",
    "wof:placetype":"venue"
},
  "geometry": {"coordinates":[-81.344398,28.7675],"type":"Point"}
}