{
  "type": "Feature",
  "properties": {
    "addr:full":"117 New Market Rd W Immokalee FL 34142",
    "addr:housenumber":"117",
    "addr:postcode":"34142",
    "addr:street":"New Market Rd W",
    "iso:country":"US",
    "sg:address":"117 New Market Rd W",
    "sg:city":"Immokalee",
    "sg:classifiers":[
        {
            "category":"Food & Beverages",
            "subcategory":"Fruits & Vegetables",
            "type":"Retail Goods"
        }
    ],
    "sg:phone":"+1 239 657 4700",
    "sg:postcode":"34142",
    "sg:province":"FL",
    "sg:tags":[
        "produce"
    ],
    "wof:name":"Rodriquez Produce",
    "wof:placetype":"venue"
},
  "geometry": {"coordinates":[-81.41699699999999,26.427068],"type":"Point"}
}