{
  "type": "Feature",
  "properties": {
    "iso:country":"US",
    "sg:address":"26201 SW 139th Ct",
    "sg:city":"Homestead",
    "sg:classifiers":[
        {
            "category":"Real Estate",
            "subcategory":"Real Estate Agent",
            "type":"Services"
        }
    ],
    "sg:phone":"+1 305 258 6889",
    "sg:postcode":"33032",
    "sg:province":"FL",
    "wof:name":"Pinnacle Realty Management Co",
    "wof:placetype":"venue"
},
  "geometry": {"coordinates":[-80.417627,25.523606],"type":"Point"}
}