{
  "type": "Feature",
  "properties": {
    "iso:country":"US",
    "sg:address":"1614 Bellair Blvd",
    "sg:city":"Orange Park",
    "sg:classifiers":[
        {
            "category":"Real Estate",
            "subcategory":"Real Estate Agent",
            "type":"Services"
        }
    ],
    "sg:phone":"+1 904 264 2356",
    "sg:postcode":"32073",
    "sg:province":"FL",
    "wof:name":"Htl Motel Brokers Network LLC",
    "wof:placetype":"venue"
},
  "geometry": {"coordinates":[-81.730175,30.168391],"type":"Point"}
}