{
  "type": "Feature",
  "properties": {
    "iso:country":"US",
    "sg:address":"2115 Citrus Blvd",
    "sg:city":"Leesburg",
    "sg:classifiers":[
        {
            "category":"Organizations",
            "subcategory":"Non-profit Organization",
            "type":"Services"
        }
    ],
    "sg:phone":"+1 352 360 0960",
    "sg:postcode":"34748",
    "sg:province":"FL",
    "sg:tags":[
        "information",
        "alcoholism",
        "treatment"
    ],
    "wof:name":"Alcoholics Anonymous",
    "wof:placetype":"venue"
},
  "geometry": {"coordinates":[-81.89445000000001,28.840841],"type":"Point"}
}