{
  "type": "Feature",
  "properties": {
    "addr:full":"111 Busch Dr Jacksonville FL 32218",
    "addr:housenumber":"111",
    "addr:postcode":"32218",
    "addr:street":"Busch Dr",
    "iso:country":"US",
    "sg:address":"111 Busch Dr",
    "sg:city":"Jacksonville",
    "sg:classifiers":[
        {
            "category":"Professional",
            "subcategory":"Management & Consulting",
            "type":"Services"
        }
    ],
    "sg:phone":"+1 904 751 9333",
    "sg:postcode":"32218",
    "sg:province":"FL",
    "sg:tags":[
        "retail",
        "direct",
        "sales"
    ],
    "wof:name":"Aramark",
    "wof:placetype":"venue"
},
  "geometry": {"coordinates":[-81.63597900000001,30.427271],"type":"Point"}
}