{
  "type": "Feature",
  "properties": {
    "addr:full":"8995 Biscayne Blvd Miami Shores FL 33138",
    "addr:housenumber":"8995",
    "addr:postcode":"33138",
    "addr:street":"Biscayne Blvd",
    "iso:country":"US",
    "sg:address":"8995 Biscayne Blvd",
    "sg:city":"Miami Shores",
    "sg:classifiers":[
        {
            "category":"Shopping",
            "subcategory":"Used Merchandise",
            "type":"Retail Goods"
        }
    ],
    "sg:phone":"+1 305 751 6344",
    "sg:postcode":"33138",
    "sg:province":"FL",
    "sg:tags":[
        "shop",
        "consignment"
    ],
    "wof:name":"Online Consignment Store",
    "wof:placetype":"venue"
},
  "geometry": {"coordinates":[-80.184595,25.857061],"type":"Point"}
}