{
  "type": "Feature",
  "properties": {
    "iso:country":"US",
    "sg:address":"260 Palm Ave",
    "sg:city":"Jacksonville",
    "sg:classifiers":[
        {
            "category":"Building & Trades",
            "subcategory":"Cleaning & Sanitation",
            "type":"Services"
        }
    ],
    "sg:phone":"+1 904 266 4764",
    "sg:postcode":"32234",
    "sg:province":"FL",
    "sg:tags":[
        "maintenance"
    ],
    "wof:name":"PM Cleaning Service",
    "wof:placetype":"venue"
},
  "geometry": {"coordinates":[-81.97948100000001,30.306782],"type":"Point"}
}