{
  "type": "Feature",
  "properties": {
    "iso:country":"US",
    "sg:address":"529 Blanding Blvd",
    "sg:city":"Orange Park",
    "sg:classifiers":[
        {
            "category":"Retail",
            "subcategory":"Veterinary Services",
            "type":"Services"
        }
    ],
    "sg:phone":"+1 904 272 0653",
    "sg:postcode":"32073",
    "sg:province":"FL",
    "wof:name":"Park West Animal Hospital",
    "wof:placetype":"venue"
},
  "geometry": {"coordinates":[-81.74785300000001,30.15495],"type":"Point"}
}