{
  "type": "Feature",
  "properties": {
    "iso:country":"US",
    "sg:address":"1701 Washington Ave",
    "sg:city":"Miami Beach",
    "sg:classifiers":[
        {
            "category":"Education",
            "subcategory":"University",
            "type":"Public Place"
        }
    ],
    "sg:phone":"+1 305 535 1066",
    "sg:postcode":"33139",
    "sg:province":"FL",
    "sg:tags":[
        "college"
    ],
    "wof:name":"Touro College",
    "wof:placetype":"venue"
},
  "geometry": {"coordinates":[-80.131758,25.792275],"type":"Point"}
}