{
  "type": "Feature",
  "properties": {
    "addr:full":"9714 Poplarwood Ct Orlando FL 32825",
    "addr:housenumber":"9714",
    "addr:postcode":"32825",
    "addr:street":"Poplarwood Ct",
    "iso:country":"US",
    "sg:address":"9714 Poplarwood Ct",
    "sg:city":"Orlando",
    "sg:classifiers":[
        {
            "category":"Manufacturing",
            "subcategory":"Aerospace",
            "type":"Manufacturing & Wholesale Goods"
        }
    ],
    "sg:phone":"+1 407 207 8183",
    "sg:postcode":"32825",
    "sg:province":"FL",
    "sg:tags":[
        "aircraft",
        "mfg"
    ],
    "wof:name":"Florida Atlantic Turbo",
    "wof:placetype":"venue"
},
  "geometry": {"coordinates":[-81.24896699999999,28.53665],"type":"Point"}
}