{
  "type": "Feature",
  "properties": {
    "addr:full":"5201 Blue Lagoon Dr Miami FL 33126",
    "addr:housenumber":"5201",
    "addr:postcode":"33126",
    "addr:street":"Blue Lagoon Dr",
    "iso:country":"US",
    "sg:address":"5201 Blue Lagoon Dr",
    "sg:city":"Miami",
    "sg:classifiers":[
        {
            "category":"Manufacturing",
            "subcategory":"Tools & Machinery",
            "type":"Manufacturing & Wholesale Goods"
        }
    ],
    "sg:phone":"+1 305 262 5727",
    "sg:postcode":"33126",
    "sg:province":"FL",
    "sg:tags":[
        "optical"
    ],
    "wof:name":"Safilo Latin America",
    "wof:placetype":"venue"
},
  "geometry": {"coordinates":[-80.28171399999999,25.78207],"type":"Point"}
}