{
  "type": "Feature",
  "properties": {
    "addr:full":"4635 Gulf Blvd St Pete Beach FL 33706",
    "addr:housenumber":"4635",
    "addr:postcode":"33706",
    "addr:street":"Gulf Blvd St Pete Beach",
    "iso:country":"US",
    "sg:address":"4635 Gulf Blvd",
    "sg:city":"St Pete Beach",
    "sg:classifiers":[
        {
            "category":"Shopping",
            "subcategory":"Department Store",
            "type":"Retail Goods"
        }
    ],
    "sg:phone":"+1 727 360 2718",
    "sg:postcode":"33706",
    "sg:province":"FL",
    "sg:tags":[
        "shop"
    ],
    "wof:name":"Dollar Tree",
    "wof:placetype":"venue"
},
  "geometry": {"coordinates":[-82.740731,27.723638],"type":"Point"}
}