{
  "type": "Feature",
  "properties": {
    "addr:full":"8386 Holly Hill Cv Jacksonville FL 32221",
    "addr:housenumber":"8386",
    "addr:postcode":"32221",
    "addr:street":"Holly Hill Cv",
    "iso:country":"US",
    "sg:address":"8386 Holly Hill Cv",
    "sg:city":"Jacksonville",
    "sg:classifiers":[
        {
            "category":"Building & Trades",
            "subcategory":"Electrical",
            "type":"Services"
        }
    ],
    "sg:phone":"+1 904 378 9599",
    "sg:postcode":"32221",
    "sg:province":"FL",
    "sg:tags":[
        "electrician"
    ],
    "wof:name":"Kerr Wj Electrical Electrical",
    "wof:placetype":"venue"
},
  "geometry": {"coordinates":[-81.789107,30.310734],"type":"Point"}
}