{
  "type": "Feature",
  "properties": {
    "addr:full":"12230 SW 68th Ave Miami FL 33156",
    "addr:housenumber":"12230",
    "addr:postcode":"33156",
    "addr:street":"Sw 68Th Ave",
    "iso:country":"US",
    "sg:address":"12230 SW 68th Ave",
    "sg:city":"Miami",
    "sg:classifiers":[
        {
            "category":"Professional",
            "subcategory":"Engineering",
            "type":"Services"
        }
    ],
    "sg:phone":"+1 305 661 5503",
    "sg:postcode":"33156",
    "sg:province":"FL",
    "sg:tags":[
        "consulting",
        "engineer"
    ],
    "wof:name":"Highlander Engineering Services Inc",
    "wof:placetype":"venue"
},
  "geometry": {"coordinates":[-80.30403200000001,25.656831],"type":"Point"}
}