{
  "type": "Feature",
  "properties": {
    "addr:full":"632 Longmeadow Cir Longwood FL 32779",
    "addr:housenumber":"632",
    "addr:postcode":"32779",
    "addr:street":"Longmeadow Cir",
    "iso:country":"US",
    "sg:address":"632 Longmeadow Cir",
    "sg:city":"Longwood",
    "sg:classifiers":[
        {
            "category":"Professional",
            "subcategory":"Management & Consulting",
            "type":"Services"
        }
    ],
    "sg:phone":"+1 407 788 7937",
    "sg:postcode":"32779",
    "sg:province":"FL",
    "sg:tags":[
        "business"
    ],
    "wof:name":"HJM Consulting",
    "wof:placetype":"venue"
},
  "geometry": {"coordinates":[-81.402793,28.705723],"type":"Point"}
}