{
  "type": "Feature",
  "properties": {
    "addr:full":"4765 Hodges Blvd Jacksonville FL 32224",
    "addr:housenumber":"4765",
    "addr:postcode":"32224",
    "addr:street":"Hodges Blvd",
    "iso:country":"US",
    "sg:address":"4765 Hodges Blvd",
    "sg:city":"Jacksonville",
    "sg:classifiers":[
        {
            "category":"Cinema",
            "subcategory":"Movie Rental",
            "type":"Entertainment"
        }
    ],
    "sg:phone":"+1 904 821 4530",
    "sg:postcode":"32224",
    "sg:province":"FL",
    "sg:tags":[
        "video",
        "tape"
    ],
    "wof:name":"Blockbuster",
    "wof:placetype":"venue"
},
  "geometry": {"coordinates":[-81.466437,30.254059],"type":"Point"}
}