{
  "type": "Feature",
  "properties": {
    "iso:country":"US",
    "sg:address":"4116 Rolling Oak Dr",
    "sg:city":"Lakeland",
    "sg:classifiers":[
        {
            "category":"Building & Trades",
            "subcategory":"Electrical",
            "type":"Services"
        },
        {
            "category":"Utilities",
            "type":"Services"
        }
    ],
    "sg:phone":"+1 863 859 1873",
    "sg:postcode":"33810",
    "sg:province":"FL",
    "sg:tags":[
        "contractors-commercial",
        "industrial",
        "electric",
        "contractor"
    ],
    "wof:name":"Lawrence Cable Construction",
    "wof:placetype":"venue"
},
  "geometry": {"coordinates":[-82.030542,28.136209],"type":"Point"}
}