{
  "type": "Feature",
  "properties": {
    "iso:country":"US",
    "sg:address":"5101 Deer Run Dr",
    "sg:city":"Fort Pierce",
    "sg:classifiers":[
        {
            "category":"Real Estate",
            "subcategory":"Real Estate Agent",
            "type":"Services"
        }
    ],
    "sg:phone":"+1 772 466 9040",
    "sg:postcode":"34951",
    "sg:province":"FL",
    "sg:tags":[
        "inspection"
    ],
    "wof:name":"Robert Sak Home Inspection",
    "wof:placetype":"venue"
},
  "geometry": {"coordinates":[-80.379037,27.525976],"type":"Point"}
}