{
  "type": "Feature",
  "properties": {
    "iso:country":"US",
    "sg:address":"1367 Tadsworth Ter",
    "sg:city":"Lake Mary",
    "sg:classifiers":[
        {
            "category":"Professional",
            "type":"Services"
        }
    ],
    "sg:phone":"+1 407 333 3393",
    "sg:postcode":"32746",
    "sg:province":"FL",
    "sg:tags":[
        "establishment"
    ],
    "wof:name":"Al Dia Travel Agent Update",
    "wof:placetype":"venue"
},
  "geometry": {"coordinates":[-81.371433,28.779228],"type":"Point"}
}