{
  "type": "Feature",
  "properties": {
    "addr:full":"4400 Hillcrest Dr Apt 301 Hollywood FL 33021",
    "addr:housenumber":"4400;301",
    "addr:postcode":"33021",
    "addr:street":"Hillcrest Dr Apt",
    "iso:country":"US",
    "sg:address":"4400 Hillcrest Dr Apt 301",
    "sg:city":"Hollywood",
    "sg:classifiers":[
        {
            "category":"Wholesale",
            "subcategory":"Computers",
            "type":"Manufacturing & Wholesale Goods"
        }
    ],
    "sg:phone":"+1 954 966 5575",
    "sg:postcode":"33021",
    "sg:province":"FL",
    "sg:tags":[
        "computer-wholesale",
        "manufacturer"
    ],
    "wof:name":"A Digital Store",
    "wof:placetype":"venue"
},
  "geometry": {"coordinates":[-80.1865,25.999798],"type":"Point"}
}