{
  "type": "Feature",
  "properties": {
    "iso:country":"US",
    "sg:address":"2401 Conway Blvd",
    "sg:city":"Port Charlotte",
    "sg:classifiers":[
        {
            "category":"Retail",
            "subcategory":"Repair Shop",
            "type":"Services"
        }
    ],
    "sg:phone":"+1 941 625 2434",
    "sg:postcode":"33952",
    "sg:province":"FL",
    "wof:name":"Premier Performance Inc",
    "wof:placetype":"venue"
},
  "geometry": {"coordinates":[-82.082559,26.992079],"type":"Point"}
}