{
  "type": "Feature",
  "properties": {
    "addr:full":"870 Industrial Ct Pensacola FL 32505",
    "addr:housenumber":"870",
    "addr:postcode":"32505",
    "addr:street":"Industrial Ct",
    "iso:country":"US",
    "sg:address":"870 Industrial Ct",
    "sg:city":"Pensacola",
    "sg:classifiers":[
        {
            "category":"Building & Trades",
            "subcategory":"Construction",
            "type":"Services"
        }
    ],
    "sg:phone":"+1 850 484 9998",
    "sg:postcode":"32505",
    "sg:province":"FL",
    "sg:tags":[
        "sing",
        "carpentry",
        "material",
        "contractor"
    ],
    "wof:name":"Window World Inc",
    "wof:placetype":"venue"
},
  "geometry": {"coordinates":[-87.258374,30.474533],"type":"Point"}
}