{
  "type": "Feature",
  "properties": {
    "addr:full":"461 7th Ave S Saint Petersburg FL 33701",
    "addr:housenumber":"461",
    "addr:postcode":"33701",
    "addr:street":"7Th Ave S",
    "iso:country":"US",
    "sg:address":"461 7th Ave S",
    "sg:city":"Saint Petersburg",
    "sg:classifiers":[
        {
            "category":"Health Services",
            "subcategory":"Doctor",
            "type":"Services"
        }
    ],
    "sg:phone":"+1 727 502 9440",
    "sg:postcode":"33701",
    "sg:province":"FL",
    "sg:tags":[
        "medical"
    ],
    "wof:name":"Brian Slaby MD",
    "wof:placetype":"venue"
},
  "geometry": {"coordinates":[-82.63981800000001,27.763189],"type":"Point"}
}