{
  "type": "Feature",
  "properties": {
    "addr:full":"633 Washburn Rd Melbourne FL 32934",
    "addr:housenumber":"633",
    "addr:postcode":"32934",
    "addr:street":"Washburn Rd",
    "iso:country":"US",
    "sg:address":"633 Washburn Rd",
    "sg:city":"Melbourne",
    "sg:classifiers":[
        {
            "category":"Home & Garden",
            "subcategory":"Furniture",
            "type":"Retail Goods"
        }
    ],
    "sg:phone":"+1 321 259 1301",
    "sg:postcode":"32934",
    "sg:province":"FL",
    "sg:tags":[
        "cabinet"
    ],
    "wof:name":"Angie's Custom Cabinets Inc",
    "wof:placetype":"venue"
},
  "geometry": {"coordinates":[-80.686466,28.117554],"type":"Point"}
}