{
  "type": "Feature",
  "properties": {
    "iso:country":"US",
    "sg:address":"424 N Federal Hwy",
    "sg:city":"Boynton Beach",
    "sg:classifiers":[
        {
            "category":"Food & Beverages",
            "subcategory":"Groceries & Convenience Stores",
            "type":"Retail Goods"
        }
    ],
    "sg:phone":"+1 561 732 0007",
    "sg:postcode":"33435",
    "sg:province":"FL",
    "wof:name":"Sunshine Caribbean Amercn Mart",
    "wof:placetype":"venue"
},
  "geometry": {"coordinates":[-80.05807,26.530567],"type":"Point"}
}