{
  "type": "Feature",
  "properties": {
    "iso:country":"US",
    "sg:address":"5561 Woodbine Rd",
    "sg:city":"Milton",
    "sg:classifiers":[
        {
            "category":"Real Estate",
            "subcategory":"Real Estate Agent",
            "type":"Services"
        }
    ],
    "sg:phone":"+1 850 995 7277",
    "sg:postcode":"32571",
    "sg:province":"FL",
    "wof:name":"Diana Casey",
    "wof:placetype":"venue"
},
  "geometry": {"coordinates":[-87.18183399999999,30.638633],"type":"Point"}
}