{
  "type": "Feature",
  "properties": {
    "iso:country":"US",
    "sg:address":"2043 NW 57th Ct",
    "sg:city":"Ocala",
    "sg:classifiers":[
        {
            "category":"Professional",
            "subcategory":"Printing & Photocopies",
            "type":"Services"
        }
    ],
    "sg:phone":"+1 352 690 3091",
    "sg:postcode":"34482",
    "sg:province":"FL",
    "sg:tags":[
        "photographers-commercial"
    ],
    "wof:name":"Image Perceptions By Linda",
    "wof:placetype":"venue"
},
  "geometry": {"coordinates":[-82.214039,29.207272],"type":"Point"}
}