{
  "type": "Feature",
  "properties": {
    "addr:full":"4747 W Waters Ave Tampa FL 33614",
    "addr:housenumber":"4747",
    "addr:postcode":"33614",
    "addr:street":"W Waters Ave",
    "iso:country":"US",
    "sg:address":"4747 W Waters Ave",
    "sg:city":"Tampa",
    "sg:classifiers":[
        {
            "category":"Shopping",
            "subcategory":"Discount & Variety Stores",
            "type":"Retail Goods"
        }
    ],
    "sg:phone":"+1 813 243 9525",
    "sg:postcode":"33614",
    "sg:province":"FL",
    "sg:tags":[
        "merchandising",
        "wedding"
    ],
    "wof:name":"Millennium Treasures",
    "wof:placetype":"venue"
},
  "geometry": {"coordinates":[-82.52553,28.025552],"type":"Point"}
}