{
  "type": "Feature",
  "properties": {
    "addr:full":"1952 W Martin Luther King Jr Blvd Tampa FL 33607",
    "addr:housenumber":"1952",
    "addr:postcode":"33607",
    "addr:street":"W Martin Luther King Jr Blvd",
    "iso:country":"US",
    "sg:address":"1952 W Martin Luther King Jr Blvd",
    "sg:city":"Tampa",
    "sg:classifiers":[
        {
            "category":"Organizations",
            "subcategory":"Non-profit Organization",
            "type":"Services"
        }
    ],
    "sg:phone":"+1 813 873 7541",
    "sg:postcode":"33607",
    "sg:province":"FL",
    "sg:tags":[
        "action",
        "agency",
        "community"
    ],
    "wof:name":"Minority Community Svc",
    "wof:placetype":"venue"
},
  "geometry": {"coordinates":[-82.47962800000001,27.981192],"type":"Point"}
}