{
  "type": "Feature",
  "properties": {
    "addr:full":"11440 Kenley Cir Orlando FL 32824",
    "addr:housenumber":"11440",
    "addr:postcode":"32824",
    "addr:street":"Kenley Cir",
    "iso:country":"US",
    "sg:address":"11440 Kenley Cir",
    "sg:city":"Orlando",
    "sg:classifiers":[
        {
            "category":"Freight",
            "type":"Transportation"
        }
    ],
    "sg:phone":"+1 407 851 5990",
    "sg:postcode":"32824",
    "sg:province":"FL",
    "sg:tags":[
        "operator",
        "local",
        "trucking"
    ],
    "wof:name":"Best Way Transportation U",
    "wof:placetype":"venue"
},
  "geometry": {"coordinates":[-81.387394,28.398962],"type":"Point"}
}