{
  "type": "Feature",
  "properties": {
    "iso:country":"US",
    "sg:address":"6283 W Waters Ave",
    "sg:city":"Tampa",
    "sg:classifiers":[
        {
            "category":"Government",
            "subcategory":"Office",
            "type":"Public Place"
        }
    ],
    "sg:phone":"+1 813 307 6500",
    "sg:postcode":"33634",
    "sg:province":"FL",
    "sg:tags":[
        "county",
        "taxation"
    ],
    "wof:name":"Hillsborough Cnty Tax Collect",
    "wof:placetype":"venue"
},
  "geometry": {"coordinates":[-82.54750300000001,28.025636],"type":"Point"}
}