{
  "type": "Feature",
  "properties": {
    "addr:full":"853 N State Road 434 Altamonte Springs FL 32714",
    "addr:housenumber":"853",
    "addr:postcode":"32714",
    "addr:street":"N State Road 434",
    "iso:country":"US",
    "sg:address":"853 N State Road 434",
    "sg:city":"Altamonte Springs",
    "sg:classifiers":[
        {
            "category":"Professional",
            "subcategory":"Accounting & Tax Preparation",
            "type":"Services"
        }
    ],
    "sg:phone":"+1 407 774 7001",
    "sg:postcode":"32714",
    "sg:province":"FL",
    "sg:tags":[
        "accountant"
    ],
    "wof:name":"Watkins Pagano & Associates",
    "wof:placetype":"venue"
},
  "geometry": {"coordinates":[-81.41909800000001,28.678699],"type":"Point"}
}