{
  "type": "Feature",
  "properties": {
    "iso:country":"US",
    "sg:address":"510 W Michigan Ave",
    "sg:city":"Pensacola",
    "sg:classifiers":[
        {
            "category":"Autos & Motor Vehicles",
            "subcategory":"Automobile Sales",
            "type":"Retail Goods"
        }
    ],
    "sg:phone":"+1 850 432 6862",
    "sg:postcode":"32505",
    "sg:province":"FL",
    "sg:tags":[
        "used"
    ],
    "wof:name":"A J Sawatka Auto Sales",
    "wof:placetype":"venue"
},
  "geometry": {"coordinates":[-87.25523200000001,30.465376],"type":"Point"}
}