{
  "type": "Feature",
  "properties": {
    "iso:country":"US",
    "sg:address":"8024 Old Town Dr",
    "sg:city":"Orlando",
    "sg:classifiers":[
        {
            "category":"Professional",
            "subcategory":"Management & Consulting",
            "type":"Services"
        }
    ],
    "sg:phone":"+1 407 248 7895",
    "sg:postcode":"32819",
    "sg:province":"FL",
    "wof:name":"J & Z Management LLC",
    "wof:placetype":"venue"
},
  "geometry": {"coordinates":[-81.49521300000001,28.480621],"type":"Point"}
}