{
  "type": "Feature",
  "properties": {
    "addr:full":"160 E Hillsboro Blvd Deerfield Beach FL 33441",
    "addr:housenumber":"160",
    "addr:postcode":"33441",
    "addr:street":"E Hillsboro Blvd",
    "iso:country":"US",
    "sg:address":"160 E Hillsboro Blvd",
    "sg:city":"Deerfield Beach",
    "sg:classifiers":[
        {
            "category":"Retail",
            "subcategory":"Auto Repair",
            "type":"Services"
        }
    ],
    "sg:phone":"+1 954 986 4900",
    "sg:postcode":"33441",
    "sg:province":"FL",
    "wof:name":"Executive Mobil South Inc",
    "wof:placetype":"venue"
},
  "geometry": {"coordinates":[-80.100112,26.318407],"type":"Point"}
}