{
  "type": "Feature",
  "properties": {
    "addr:full":"1000 W McNab Rd Pompano Beach FL 33069",
    "addr:housenumber":"1000",
    "addr:postcode":"33069",
    "addr:street":"W Mcnab Rd",
    "iso:country":"US",
    "sg:address":"1000 W McNab Rd",
    "sg:city":"Pompano Beach",
    "sg:classifiers":[
        {
            "category":"Insurance",
            "subcategory":"Insurance Agent",
            "type":"Services"
        }
    ],
    "sg:phone":"+1 954 545 3831",
    "sg:postcode":"33069",
    "sg:province":"FL",
    "sg:tags":[
        "processing"
    ],
    "wof:name":"At Global",
    "wof:placetype":"venue"
},
  "geometry": {"coordinates":[-80.137394,26.210721],"type":"Point"}
}