{
  "type": "Feature",
  "properties": {
    "addr:full":"2340 SW 6th St Miami FL 33135",
    "addr:housenumber":"2340",
    "addr:postcode":"33135",
    "addr:street":"Sw 6Th St",
    "iso:country":"US",
    "sg:address":"2340 SW 6th St",
    "sg:city":"Miami",
    "sg:classifiers":[
        {
            "category":"Building & Trades",
            "subcategory":"Construction",
            "type":"Services"
        }
    ],
    "sg:phone":"+1 305 642 3402",
    "sg:postcode":"33135",
    "sg:province":"FL",
    "sg:tags":[
        "wallcoverings-installation",
        "wallpaper",
        "painting",
        "contractor"
    ],
    "wof:name":"Ac Gonzalez Painting Contractors Inc",
    "wof:placetype":"venue"
},
  "geometry": {"coordinates":[-80.23361800000001,25.767115],"type":"Point"}
}