{
  "type": "Feature",
  "properties": {
    "iso:country":"US",
    "sg:address":"4000 N US Hwy 17",
    "sg:city":"Deland",
    "sg:classifiers":[
        {
            "category":"Autos & Motor Vehicles",
            "subcategory":"Auto Supplies",
            "type":"Retail Goods"
        }
    ],
    "sg:phone":"+1 386 985 1002",
    "sg:postcode":"32720",
    "sg:province":"FL",
    "sg:tags":[
        "equipment",
        "racing",
        "car",
        "automobile"
    ],
    "wof:name":"Bemco Fabrication",
    "wof:placetype":"venue"
},
  "geometry": {"coordinates":[-81.33123399999999,29.093518],"type":"Point"}
}