{
  "type": "Feature",
  "properties": {
    "addr:full":"3953 Belmoor Dr Palm Harbor FL 34685",
    "addr:housenumber":"3953",
    "addr:postcode":"34685",
    "addr:street":"Belmoor Dr",
    "iso:country":"US",
    "sg:address":"3953 Belmoor Dr",
    "sg:city":"Palm Harbor",
    "sg:classifiers":[
        {
            "category":"Autos & Motor Vehicles",
            "subcategory":"Automobile Sales",
            "type":"Retail Goods"
        }
    ],
    "sg:phone":"+1 727 786 6501",
    "sg:postcode":"34685",
    "sg:province":"FL",
    "sg:tags":[
        "used"
    ],
    "wof:name":"Advance Import Inc",
    "wof:placetype":"venue"
},
  "geometry": {"coordinates":[-82.67882299999999,28.097896],"type":"Point"}
}