{
  "type": "Feature",
  "properties": {
    "addr:full":"758 NW 2nd St Miami FL 33128",
    "addr:housenumber":"758",
    "addr:postcode":"33128",
    "addr:street":"Nw 2Nd St",
    "iso:country":"US",
    "sg:address":"758 NW 2nd St",
    "sg:city":"Miami",
    "sg:classifiers":[
        {
            "category":"Real Estate",
            "subcategory":"Real Estate Operator",
            "type":"Services"
        }
    ],
    "sg:phone":"+1 305 326 9178",
    "sg:postcode":"33128",
    "sg:province":"FL",
    "sg:tags":[
        "boarding",
        "house"
    ],
    "wof:name":"South Florida Home Svc",
    "wof:placetype":"venue"
},
  "geometry": {"coordinates":[-80.20690999999999,25.775628],"type":"Point"}
}