{
  "type": "Feature",
  "properties": {
    "addr:full":"4700 SW 42nd Ter Fort Lauderdale FL 33314",
    "addr:housenumber":"4700",
    "addr:postcode":"33314",
    "addr:street":"Sw 42Nd Ter",
    "iso:country":"US",
    "sg:address":"4700 SW 42nd Ter",
    "sg:city":"Fort Lauderdale",
    "sg:classifiers":[
        {
            "category":"Building & Trades",
            "subcategory":"Plumbing",
            "type":"Services"
        }
    ],
    "sg:phone":"+1 954 584 4830",
    "sg:postcode":"33314",
    "sg:province":"FL",
    "sg:tags":[
        "air",
        "conditioning",
        "contractor"
    ],
    "wof:name":"Air Giant Inc",
    "wof:placetype":"venue"
},
  "geometry": {"coordinates":[-80.20292499999999,26.066323],"type":"Point"}
}