{
  "type": "Feature",
  "properties": {
    "addr:full":"4400 Lister St Port Charlotte FL 33952",
    "addr:housenumber":"4400",
    "addr:postcode":"33952",
    "addr:street":"Lister St",
    "iso:country":"US",
    "sg:address":"4400 Lister St",
    "sg:city":"Port Charlotte",
    "sg:classifiers":[
        {
            "category":"Recreation",
            "type":"Entertainment"
        }
    ],
    "sg:phone":"+1 941 629 5131",
    "sg:postcode":"33952",
    "sg:province":"FL",
    "sg:tags":[
        "club",
        "yacht",
        "private"
    ],
    "sg:website":"www.thechyc.com",
    "wof:name":"Charlotte Harbor Yacht Club",
    "wof:placetype":"venue"
},
  "geometry": {"coordinates":[-82.081186,26.960814],"type":"Point"}
}