{
  "type": "Feature",
  "properties": {
    "iso:country":"US",
    "sg:address":"7950 Shoals Dr",
    "sg:city":"Orlando",
    "sg:classifiers":[
        {
            "category":"Real Estate",
            "subcategory":"Real Estate Agent",
            "type":"Services"
        }
    ],
    "sg:phone":"+1 407 678 2223",
    "sg:postcode":"32817",
    "sg:province":"FL",
    "sg:tags":[
        "apartment",
        "complex"
    ],
    "wof:name":"Waterside Apartments",
    "wof:placetype":"venue"
},
  "geometry": {"coordinates":[-81.279999,28.610001],"type":"Point"}
}