{
  "type": "Feature",
  "properties": {
    "iso:country":"US",
    "sg:address":"6701 Church St",
    "sg:city":"Jupiter",
    "sg:classifiers":[
        {
            "category":"Education",
            "subcategory":"School",
            "type":"Public Place"
        }
    ],
    "sg:phone":"+1 561 744 7985",
    "sg:postcode":"33458",
    "sg:province":"FL",
    "sg:website":"www.palmbeach.k12.fl.us",
    "wof:name":"Limestone Creek Elmentary Schl",
    "wof:placetype":"venue"
},
  "geometry": {"coordinates":[-80.137635,26.941776],"type":"Point"}
}