{
  "type": "Feature",
  "properties": {
    "iso:country":"US",
    "sg:address":"421 S Atlantic Ave",
    "sg:city":"New Smyrna Beach",
    "sg:classifiers":[
        {
            "category":"Travel",
            "subcategory":"Hotels & Motels",
            "type":"Entertainment"
        }
    ],
    "sg:phone":"+1 386 423 8400",
    "sg:postcode":"32169",
    "sg:province":"FL",
    "sg:tags":[
        "operation"
    ],
    "wof:name":"Oceania Beach Club",
    "wof:placetype":"venue"
},
  "geometry": {"coordinates":[-80.895613,29.036583],"type":"Point"}
}