{
  "type": "Feature",
  "properties": {
    "addr:full":"1537 Cownie Ln Sebastian FL 32958",
    "addr:housenumber":"1537",
    "addr:postcode":"32958",
    "addr:street":"Cownie Ln",
    "iso:country":"US",
    "sg:address":"1537 Cownie Ln",
    "sg:city":"Sebastian",
    "sg:classifiers":[
        {
            "category":"Building & Trades",
            "subcategory":"Construction",
            "type":"Services"
        }
    ],
    "sg:phone":"+1 772 388 2830",
    "sg:postcode":"32958",
    "sg:province":"FL",
    "sg:tags":[
        "roofing",
        "contractor"
    ],
    "wof:name":"Roof Clinic",
    "wof:placetype":"venue"
},
  "geometry": {"coordinates":[-80.486583,27.761753],"type":"Point"}
}