{
  "type": "Feature",
  "properties": {
    "iso:country":"US",
    "sg:address":"1722 Fairhaven Ct",
    "sg:city":"Apopka",
    "sg:classifiers":[
        {
            "category":"Building & Trades",
            "subcategory":"Construction",
            "type":"Services"
        }
    ],
    "sg:phone":"+1 407 880 7006",
    "sg:postcode":"32712",
    "sg:province":"FL",
    "sg:tags":[
        "contractor"
    ],
    "wof:name":"R & D Plastering",
    "wof:placetype":"venue"
},
  "geometry": {"coordinates":[-81.50339200000001,28.709218],"type":"Point"}
}