{
  "type": "Feature",
  "properties": {
    "addr:full":"448 Gerona Rd Saint Augustine FL 32086",
    "addr:housenumber":"448",
    "addr:postcode":"32086",
    "addr:street":"Gerona Rd",
    "iso:country":"US",
    "sg:address":"448 Gerona Rd",
    "sg:city":"Saint Augustine",
    "sg:classifiers":[
        {
            "category":"Professional",
            "type":"Services"
        }
    ],
    "sg:phone":"+1 904 794 2382",
    "sg:postcode":"32086",
    "sg:province":"FL",
    "wof:name":"Lords Precious Gems",
    "wof:placetype":"venue"
},
  "geometry": {"coordinates":[-81.31677000000001,29.846217],"type":"Point"}
}