{
  "type": "Feature",
  "properties": {
    "addr:full":"1117 N Gadsden St Tallahassee FL 32303",
    "addr:housenumber":"1117",
    "addr:postcode":"32303",
    "addr:street":"N Gadsden St",
    "iso:country":"US",
    "sg:address":"1117 N Gadsden St",
    "sg:city":"Tallahassee",
    "sg:classifiers":[
        {
            "category":"Insurance",
            "subcategory":"Insurance Agent",
            "type":"Services"
        }
    ],
    "sg:phone":"+1 850 224 2204",
    "sg:postcode":"32303",
    "sg:province":"FL",
    "wof:name":"AFLAC",
    "wof:placetype":"venue"
},
  "geometry": {"coordinates":[-84.276442,30.454958],"type":"Point"}
}