{
  "type": "Feature",
  "properties": {
    "addr:full":"915 S Sr 15A Deland FL 32720",
    "addr:housenumber":"915;15a",
    "addr:postcode":"32720",
    "addr:street":"S Sr",
    "iso:country":"US",
    "sg:address":"915 S Sr 15A",
    "sg:city":"Deland",
    "sg:classifiers":[
        {
            "category":"Shopping",
            "subcategory":"Department Store",
            "type":"Retail Goods"
        },
        {
            "category":"Shopping",
            "subcategory":"Discount & Variety Stores",
            "type":"Retail Goods"
        }
    ],
    "sg:phone":"+1 386 736 9522",
    "sg:postcode":"32720",
    "sg:province":"FL",
    "sg:website":"http://www.familydollar.com",
    "wof:name":"Family Dollar",
    "wof:placetype":"venue"
},
  "geometry": {"coordinates":[-81.324433,29.043213],"type":"Point"}
}