{
  "type": "Feature",
  "properties": {
    "addr:full":"100 Moseley Ave Palatka FL 32177",
    "addr:housenumber":"100",
    "addr:postcode":"32177",
    "addr:street":"Moseley Ave",
    "iso:country":"US",
    "sg:address":"100 Moseley Ave",
    "sg:city":"Palatka",
    "sg:classifiers":[
        {
            "category":"Travel",
            "subcategory":"Hotels & Motels",
            "type":"Entertainment"
        }
    ],
    "sg:phone":"+1 386 328 1533",
    "sg:postcode":"32177",
    "sg:province":"FL",
    "sg:tags":[
        "corporate",
        "lodging"
    ],
    "sg:website":"http://www.budgetinn.com",
    "wof:name":"Budget Inn",
    "wof:placetype":"venue"
},
  "geometry": {"coordinates":[-81.649834,29.649139],"type":"Point"}
}