{
  "type": "Feature",
  "properties": {
    "addr:full":"1614 S Dixie Hwy Lake Worth FL 33460",
    "addr:housenumber":"1614",
    "addr:postcode":"33460",
    "addr:street":"S Dixie Hwy",
    "iso:country":"US",
    "sg:address":"1614 S Dixie Hwy",
    "sg:city":"Lake Worth",
    "sg:classifiers":[
        {
            "category":"Shopping",
            "subcategory":"Florist",
            "type":"Retail Goods"
        }
    ],
    "sg:phone":"+1 561 586 5768",
    "sg:postcode":"33460",
    "sg:province":"FL",
    "wof:name":"Lake Worth Villager Florist",
    "wof:placetype":"venue"
},
  "geometry": {"coordinates":[-80.053862,26.595284],"type":"Point"}
}