{
  "type": "Feature",
  "properties": {
    "addr:full":"5912 New Kings Rd Jacksonville FL 32209",
    "addr:housenumber":"5912",
    "addr:postcode":"32209",
    "addr:street":"New Kings Rd",
    "iso:country":"US",
    "sg:address":"5912 New Kings Rd",
    "sg:city":"Jacksonville",
    "sg:classifiers":[
        {
            "category":"Travel",
            "subcategory":"Hotels & Motels",
            "type":"Entertainment"
        }
    ],
    "sg:phone":"+1 904 768 4826",
    "sg:postcode":"32209",
    "sg:province":"FL",
    "wof:name":"Jax-American Motel",
    "wof:placetype":"venue"
},
  "geometry": {"coordinates":[-81.72416,30.370389],"type":"Point"}
}