{
  "type": "Feature",
  "properties": {
    "iso:country":"US",
    "sg:address":"3489 Oleander Ave",
    "sg:city":"Fort Pierce",
    "sg:classifiers":[
        {
            "category":"Utilities",
            "subcategory":"Natural Gas",
            "type":"Services"
        }
    ],
    "sg:phone":"+1 772 464 5414",
    "sg:postcode":"34982",
    "sg:province":"FL",
    "sg:tags":[
        "company"
    ],
    "wof:name":"Coast Gas",
    "wof:placetype":"venue"
},
  "geometry": {"coordinates":[-80.333955,27.398211],"type":"Point"}
}