{
  "type": "Feature",
  "properties": {
    "iso:country":"US",
    "sg:address":"1330 Oak St",
    "sg:city":"Melbourne",
    "sg:classifiers":[
        {
            "category":"Health Services",
            "subcategory":"Doctor",
            "type":"Services"
        }
    ],
    "sg:phone":"+1 321 768 9778",
    "sg:postcode":"32901",
    "sg:province":"FL",
    "sg:tags":[
        "physician",
        "family",
        "practice",
        "surgeons",
        "medicine",
        "surgeon"
    ],
    "wof:name":"Omni Healthcare Inc",
    "wof:placetype":"venue"
},
  "geometry": {"coordinates":[-80.61522100000001,28.088253],"type":"Point"}
}