{
  "type": "Feature",
  "properties": {
    "iso:country":"US",
    "sg:address":"6221 SW 109th Ave",
    "sg:city":"Miami",
    "sg:classifiers":[
        {
            "category":"Wholesale",
            "subcategory":"Hardware",
            "type":"Manufacturing & Wholesale Goods"
        }
    ],
    "sg:phone":"+1 305 279 9544",
    "sg:postcode":"33173",
    "sg:province":"FL",
    "sg:tags":[
        "refrigeration"
    ],
    "wof:name":"Florido & Assoc Inc",
    "wof:placetype":"venue"
},
  "geometry": {"coordinates":[-80.37063999999999,25.709312],"type":"Point"}
}