{
  "type": "Feature",
  "properties": {
    "addr:full":"451 E Altamonte Dr Altamonte Springs FL 32701",
    "addr:housenumber":"451",
    "addr:postcode":"32701",
    "addr:street":"E Altamonte Dr",
    "iso:country":"US",
    "sg:address":"451 E Altamonte Dr",
    "sg:city":"Altamonte Springs",
    "sg:classifiers":[
        {
            "category":"Shopping",
            "subcategory":"Clothing, Apparel, & Fashions",
            "type":"Retail Goods"
        }
    ],
    "sg:phone":"+1 407 260 1185",
    "sg:postcode":"32701",
    "sg:province":"FL",
    "sg:tags":[
        "accessory",
        "clothing",
        "women's"
    ],
    "sg:website":"www.guess.com",
    "wof:name":"G by Guess",
    "wof:placetype":"venue"
},
  "geometry": {"coordinates":[-81.377315,28.664045],"type":"Point"}
}