{
  "type": "Feature",
  "properties": {
    "iso:country":"US",
    "sg:address":"8814 Darlington Dr",
    "sg:city":"Jacksonville",
    "sg:classifiers":[
        {
            "category":"Restaurant",
            "type":"Food & Drink"
        }
    ],
    "sg:phone":"+1 904 683 1278",
    "sg:postcode":"32208",
    "sg:province":"FL",
    "sg:tags":[
        "caterer"
    ],
    "wof:name":"Catering By Mother Dunn",
    "wof:placetype":"venue"
},
  "geometry": {"coordinates":[-81.718988,30.401583],"type":"Point"}
}