{
  "type": "Feature",
  "properties": {
    "addr:full":"14394 Demery Dr S Jacksonville Beach FL 32250",
    "addr:housenumber":"14394",
    "addr:postcode":"32250",
    "addr:street":"Demery Dr S;Beach",
    "iso:country":"US",
    "sg:address":"14394 Demery Dr S",
    "sg:city":"Jacksonville Beach",
    "sg:classifiers":[
        {
            "category":"Building & Trades",
            "subcategory":"Construction",
            "type":"Services"
        }
    ],
    "sg:phone":"+1 904 223 5189",
    "sg:postcode":"32250",
    "sg:province":"FL",
    "sg:tags":[
        "house"
    ],
    "wof:name":"Edward J Vaesa",
    "wof:placetype":"venue"
},
  "geometry": {"coordinates":[-81.43567400000001,30.271751],"type":"Point"}
}