{
  "type": "Feature",
  "properties": {
    "iso:country":"US",
    "sg:address":"11869 34th St N",
    "sg:city":"St Petersburg",
    "sg:classifiers":[
        {
            "category":"Wholesale",
            "subcategory":"Chemicals & Plastics",
            "type":"Manufacturing & Wholesale Goods"
        }
    ],
    "sg:phone":"+1 727 572 0222",
    "sg:postcode":"33716",
    "sg:province":"FL",
    "sg:tags":[
        "oxygen"
    ],
    "wof:name":"Air Sep Corp",
    "wof:placetype":"venue"
},
  "geometry": {"coordinates":[-82.679688,27.880117],"type":"Point"}
}