{
  "type": "Feature",
  "properties": {
    "iso:country":"US",
    "sg:address":"341 W Davidson St",
    "sg:city":"Bartow",
    "sg:classifiers":[
        {
            "category":"Professional",
            "subcategory":"Lawyer & Legal Services",
            "type":"Services"
        }
    ],
    "sg:phone":"+1 863 533 1300",
    "sg:postcode":"33830",
    "sg:province":"FL",
    "sg:tags":[
        "attorney"
    ],
    "wof:name":"Kelly B Hardwick III",
    "wof:placetype":"venue"
},
  "geometry": {"coordinates":[-81.845827,27.897103],"type":"Point"}
}