{
  "type": "Feature",
  "properties": {
    "iso:country":"US",
    "sg:address":"10012 Fountain Ct",
    "sg:city":"New Port Richey",
    "sg:classifiers":[
        {
            "category":"Real Estate",
            "subcategory":"Developer",
            "type":"Services"
        }
    ],
    "sg:phone":"+1 727 841 6000",
    "sg:postcode":"34654",
    "sg:province":"FL",
    "sg:website":"www.teamkar.com",
    "wof:name":"Teamkar Development Corp",
    "wof:placetype":"venue"
},
  "geometry": {"coordinates":[-82.64882299999999,28.263873],"type":"Point"}
}