{
  "type": "Feature",
  "properties": {
    "iso:country":"US",
    "sg:address":"7401 NW Gainesville Rd",
    "sg:city":"Ocala",
    "sg:classifiers":[
        {
            "category":"Building & Trades",
            "subcategory":"Construction",
            "type":"Services"
        }
    ],
    "sg:phone":"+1 352 369 0490",
    "sg:postcode":"34475",
    "sg:province":"FL",
    "sg:tags":[
        "paving",
        "contractor"
    ],
    "wof:name":"Steven Counts Inc Asphalt Plnt",
    "wof:placetype":"venue"
},
  "geometry": {"coordinates":[-82.179709,29.262781],"type":"Point"}
}