{
  "type": "Feature",
  "properties": {
    "iso:country":"US",
    "sg:address":"8129 Sabal Oak Ln",
    "sg:city":"Jacksonville",
    "sg:classifiers":[
        {
            "category":"Professional",
            "type":"Services"
        }
    ],
    "sg:phone":"+1 904 232 4000",
    "sg:postcode":"32256",
    "sg:province":"FL",
    "sg:tags":[
        "establishment"
    ],
    "wof:name":"Long & Short",
    "wof:placetype":"venue"
},
  "geometry": {"coordinates":[-81.523287,30.220781],"type":"Point"}
}