{
  "type": "Feature",
  "properties": {
    "iso:country":"US",
    "sg:address":"780 Deltona Blvd",
    "sg:city":"Deltona",
    "sg:classifiers":[
        {
            "category":"Building & Trades",
            "subcategory":"Construction",
            "type":"Services"
        }
    ],
    "sg:phone":"+1 386 574 4776",
    "sg:postcode":"32725",
    "sg:province":"FL",
    "sg:tags":[
        "contractor"
    ],
    "wof:name":"Independence Homes",
    "wof:placetype":"venue"
},
  "geometry": {"coordinates":[-81.278603,28.883499],"type":"Point"}
}