{
  "type": "Feature",
  "properties": {
    "iso:country":"US",
    "sg:address":"3470 SW 8th St",
    "sg:city":"Miami",
    "sg:classifiers":[
        {
            "category":"Personal",
            "type":"Services"
        }
    ],
    "sg:phone":"+1 305 443 3680",
    "sg:postcode":"33135",
    "sg:province":"FL",
    "sg:tags":[
        "assistant"
    ],
    "wof:name":"The Courts At Versailles Liec",
    "wof:placetype":"venue"
},
  "geometry": {"coordinates":[-80.25179300000001,25.764776],"type":"Point"}
}