{
  "type": "Feature",
  "properties": {
    "addr:full":"5821 Ridgewood Ave Cocoa Beach FL 32931",
    "addr:housenumber":"5821",
    "addr:postcode":"32931",
    "addr:street":"Ridgewood Ave",
    "iso:country":"US",
    "sg:address":"5821 Ridgewood Ave",
    "sg:city":"Cocoa Beach",
    "sg:classifiers":[
        {
            "category":"Shopping",
            "type":"Retail Goods"
        }
    ],
    "sg:phone":"+1 386 761 5331",
    "sg:postcode":"32931",
    "sg:province":"FL",
    "sg:tags":[
        "aquarium"
    ],
    "wof:name":"Living Waters Aquarium",
    "wof:placetype":"venue"
},
  "geometry": {"coordinates":[-80.60389000000001,28.371031],"type":"Point"}
}