{
  "type": "Feature",
  "properties": {
    "iso:country":"US",
    "sg:address":"2602 Rogero Rd",
    "sg:city":"Jacksonville",
    "sg:classifiers":[
        {
            "category":"Building & Trades",
            "subcategory":"Plumbing",
            "type":"Services"
        }
    ],
    "sg:phone":"+1 904 745 3330",
    "sg:postcode":"32211",
    "sg:province":"FL",
    "sg:tags":[
        "plumbing",
        "contractor"
    ],
    "wof:name":"Plumbing By Josh",
    "wof:placetype":"venue"
},
  "geometry": {"coordinates":[-81.58956000000001,30.34971],"type":"Point"}
}