{
  "type": "Feature",
  "properties": {
    "addr:full":"1525 E Amelia St Orlando FL 32803",
    "addr:housenumber":"1525",
    "addr:postcode":"32803",
    "addr:street":"E Amelia St",
    "iso:country":"US",
    "sg:address":"1525 E Amelia St",
    "sg:city":"Orlando",
    "sg:classifiers":[
        {
            "category":"Building & Trades",
            "subcategory":"Construction",
            "type":"Services"
        }
    ],
    "sg:phone":"+1 407 894 7661",
    "sg:postcode":"32803",
    "sg:province":"FL",
    "sg:tags":[
        "commercial"
    ],
    "wof:name":"Scherer Cnstr & Engrg LLC",
    "wof:placetype":"venue"
},
  "geometry": {"coordinates":[-81.361428,28.549543],"type":"Point"}
}