{
  "type": "Feature",
  "properties": {
    "iso:country":"US",
    "sg:address":"12375 91st St",
    "sg:city":"Fellsmere",
    "sg:classifiers":[
        {
            "category":"Home & Garden",
            "subcategory":"Garden Supply",
            "type":"Retail Goods"
        },
        {
            "category":"Professional",
            "subcategory":"Art Services",
            "type":"Services"
        }
    ],
    "sg:phone":"+1 772 571 9833",
    "sg:postcode":"32948",
    "sg:province":"FL",
    "sg:tags":[
        "plant",
        "designer",
        "plants-interior",
        "design",
        "maintenance",
        "interior",
        "decorator"
    ],
    "wof:name":"Evergreen Plant Leasing & Maintenance",
    "wof:placetype":"venue"
},
  "geometry": {"coordinates":[-80.58975,27.761071],"type":"Point"}
}