{
  "type": "Feature",
  "properties": {
    "addr:full":"79 E Oakland Park Blvd Oakland Park FL 33334",
    "addr:housenumber":"79",
    "addr:postcode":"33334",
    "addr:street":"E Oakland Park Blvd",
    "iso:country":"US",
    "sg:address":"79 E Oakland Park Blvd",
    "sg:city":"Oakland Park",
    "sg:classifiers":[
        {
            "category":"Health Services",
            "subcategory":"Optometrist",
            "type":"Services"
        }
    ],
    "sg:phone":"+1 954 566 2020",
    "sg:postcode":"33334",
    "sg:province":"FL",
    "wof:name":"DOC Optics Ctr",
    "wof:placetype":"venue"
},
  "geometry": {"coordinates":[-80.14637399999999,26.166662],"type":"Point"}
}