{
  "type": "Feature",
  "properties": {
    "iso:country":"US",
    "sg:address":"995 Marble Ridge Dr",
    "sg:city":"Orange Park",
    "sg:classifiers":[
        {
            "category":"Shopping",
            "subcategory":"Gifts & Souvenirs",
            "type":"Retail Goods"
        }
    ],
    "sg:phone":"+1 904 282 7195",
    "sg:postcode":"32065",
    "sg:province":"FL",
    "wof:name":"ABC Fun Jumps & Balloon Bouque",
    "wof:placetype":"venue"
},
  "geometry": {"coordinates":[-81.782324,30.150833],"type":"Point"}
}