{
  "type": "Feature",
  "properties": {
    "iso:country":"US",
    "sg:address":"235 NW 44th St",
    "sg:city":"Fort Lauderdale",
    "sg:classifiers":[
        {
            "category":"Wholesale",
            "subcategory":"Electrical",
            "type":"Manufacturing & Wholesale Goods"
        }
    ],
    "sg:phone":"+1 954 772 3968",
    "sg:postcode":"33309",
    "sg:province":"FL",
    "sg:tags":[
        "lighting",
        "lamp",
        "retail",
        "shades",
        "f"
    ],
    "wof:name":"Flowers Lighting Inc",
    "wof:placetype":"venue"
},
  "geometry": {"coordinates":[-80.147442,26.181352],"type":"Point"}
}