{
  "type": "Feature",
  "properties": {
    "iso:country":"US",
    "sg:address":"12755 Turtle Lake Ln",
    "sg:city":"Jacksonville",
    "sg:classifiers":[
        {
            "category":"Professional",
            "subcategory":"Detective & Security Services",
            "type":"Services"
        }
    ],
    "sg:phone":"+1 904 221 4712",
    "sg:postcode":"32246",
    "sg:province":"FL",
    "sg:tags":[
        "information",
        "bureau"
    ],
    "wof:name":"Daniel J Kelly Svc",
    "wof:placetype":"venue"
},
  "geometry": {"coordinates":[-81.46975,30.309675],"type":"Point"}
}