{
  "type": "Feature",
  "properties": {
    "iso:country":"US",
    "sg:address":"1919 Delaney Ave",
    "sg:city":"Orlando",
    "sg:classifiers":[
        {
            "category":"Organizations",
            "subcategory":"Religious Organization",
            "type":"Services"
        }
    ],
    "sg:phone":"+1 407 422 0758",
    "sg:postcode":"32806",
    "sg:province":"FL",
    "sg:tags":[
        "church"
    ],
    "sg:website":"www.delaneychurch.com",
    "wof:name":"Delaney Street Baptist Church",
    "wof:placetype":"venue"
},
  "geometry": {"coordinates":[-81.372185,28.519537],"type":"Point"}
}