{
  "type": "Feature",
  "properties": {
    "addr:full":"7035 Lake Dr Orlando FL 32809",
    "addr:housenumber":"7035",
    "addr:postcode":"32809",
    "addr:street":"Lake Dr",
    "iso:country":"US",
    "sg:address":"7035 Lake Dr",
    "sg:city":"Orlando",
    "sg:classifiers":[
        {
            "category":"Real Estate",
            "subcategory":"Real Estate Agent",
            "type":"Services"
        }
    ],
    "sg:phone":"+1 407 854 9801",
    "sg:postcode":"32809",
    "sg:province":"FL",
    "wof:name":"Exit Real Estate Results",
    "wof:placetype":"venue"
},
  "geometry": {"coordinates":[-81.35590999999999,28.460791],"type":"Point"}
}