{
  "type": "Feature",
  "properties": {
    "iso:country":"US",
    "sg:address":"2795 Co Rd 220",
    "sg:city":"Middleburg",
    "sg:classifiers":[
        {
            "category":"Social Services",
            "type":"Services"
        }
    ],
    "sg:phone":"+1 904 276 6677",
    "sg:postcode":"32068",
    "sg:province":"FL",
    "sg:tags":[
        "organization",
        "welfare"
    ],
    "wof:name":"Salvation Army",
    "wof:placetype":"venue"
},
  "geometry": {"coordinates":[-81.78551,30.10204],"type":"Point"}
}