{
  "type": "Feature",
  "properties": {
    "addr:full":"1063 SW 8th Ct Miami FL 33130",
    "addr:housenumber":"1063",
    "addr:postcode":"33130",
    "addr:street":"Sw 8Th Ct",
    "iso:country":"US",
    "sg:address":"1063 SW 8th Ct",
    "sg:city":"Miami",
    "sg:classifiers":[
        {
            "category":"Personal",
            "subcategory":"Beauty Salon",
            "type":"Services"
        }
    ],
    "sg:phone":"+1 305 285 0779",
    "sg:postcode":"33130",
    "sg:province":"FL",
    "wof:name":"Carmen Design Hair Stylist",
    "wof:placetype":"venue"
},
  "geometry": {"coordinates":[-80.20801899999999,25.764801],"type":"Point"}
}