{
  "type": "Feature",
  "properties": {
    "iso:country":"US",
    "sg:address":"521 Mary Esther Cutoff NW",
    "sg:city":"Fort Walton Bch",
    "sg:classifiers":[
        {
            "category":"Food & Beverages",
            "subcategory":"Groceries & Convenience Stores",
            "type":"Retail Goods"
        }
    ],
    "sg:phone":"+1 850 664 7714",
    "sg:postcode":"32548",
    "sg:province":"FL",
    "sg:tags":[
        "grocer"
    ],
    "wof:name":"Ritz Food Store",
    "wof:placetype":"venue"
},
  "geometry": {"coordinates":[-86.65149,30.422366],"type":"Point"}
}