{
  "type": "Feature",
  "properties": {
    "iso:country":"US",
    "sg:address":"1010 N State Rd 7",
    "sg:city":"Hollywood",
    "sg:classifiers":[
        {
            "category":"Shopping",
            "subcategory":"Computers & Home Electronics",
            "type":"Retail Goods"
        }
    ],
    "sg:phone":"+1 954 966 9614",
    "sg:postcode":"33021",
    "sg:province":"FL",
    "sg:tags":[
        "automobile",
        "used"
    ],
    "wof:name":"Mr Car Stereo",
    "wof:placetype":"venue"
},
  "geometry": {"coordinates":[-80.208052,26.019388],"type":"Point"}
}