{
  "type": "Feature",
  "properties": {
    "iso:country":"US",
    "sg:address":"9815 Rocky Bank Dr",
    "sg:city":"Naples",
    "sg:classifiers":[
        {
            "category":"Wholesale",
            "subcategory":"Non-durable Goods",
            "type":"Manufacturing & Wholesale Goods"
        }
    ],
    "sg:phone":"+1 239 598 3730",
    "sg:postcode":"34109",
    "sg:province":"FL",
    "wof:name":"McGill Worldwide Inc",
    "wof:placetype":"venue"
},
  "geometry": {"coordinates":[-81.742113,26.252679],"type":"Point"}
}