{
  "type": "Feature",
  "properties": {
    "iso:country":"US",
    "sg:address":"1401 N Myrtle Ave",
    "sg:city":"Clearwater",
    "sg:classifiers":[
        {
            "category":"Manufacturing",
            "subcategory":"Watercraft",
            "type":"Manufacturing & Wholesale Goods"
        }
    ],
    "sg:phone":"+1 727 443 0373",
    "sg:postcode":"33755",
    "sg:province":"FL",
    "sg:tags":[
        "engine"
    ],
    "wof:name":"SBT",
    "wof:placetype":"venue"
},
  "geometry": {"coordinates":[-82.79586999999999,27.980353],"type":"Point"}
}