{
  "type": "Feature",
  "properties": {
    "iso:country":"US",
    "sg:address":"10400 Atlantic Blvd",
    "sg:city":"Jacksonville",
    "sg:classifiers":[
        {
            "category":"Restaurant",
            "type":"Food & Drink"
        }
    ],
    "sg:phone":"+1 904 642 0967",
    "sg:postcode":"32225",
    "sg:province":"FL",
    "sg:tags":[
        "fast"
    ],
    "wof:name":"KFC",
    "wof:placetype":"venue"
},
  "geometry": {"coordinates":[-81.52879299999999,30.323885],"type":"Point"}
}