{
  "type": "Feature",
  "properties": {
    "iso:country":"US",
    "sg:address":"3001 NW 24th St",
    "sg:city":"Fort Lauderdale",
    "sg:classifiers":[
        {
            "category":"Organizations",
            "subcategory":"Religious Organization",
            "type":"Services"
        }
    ],
    "sg:phone":"+1 954 733 6649",
    "sg:postcode":"33311",
    "sg:province":"FL",
    "sg:tags":[
        "church"
    ],
    "wof:name":"United Christian Fellowship",
    "wof:placetype":"venue"
},
  "geometry": {"coordinates":[-80.18530699999999,26.155901],"type":"Point"}
}