{
  "type": "Feature",
  "properties": {
    "iso:country":"US",
    "sg:address":"1101 W Hibiscus Blvd",
    "sg:city":"Melbourne",
    "sg:classifiers":[
        {
            "category":"Professional",
            "subcategory":"Lawyer & Legal Services",
            "type":"Services"
        }
    ],
    "sg:phone":"+1 321 956 6005",
    "sg:postcode":"32901",
    "sg:province":"FL",
    "sg:tags":[
        "attorney"
    ],
    "wof:name":"Tina M Robbins Pa",
    "wof:placetype":"venue"
},
  "geometry": {"coordinates":[-80.642742,28.085233],"type":"Point"}
}