{
  "type": "Feature",
  "properties": {
    "iso:country":"US",
    "sg:address":"9770 S Military Trl",
    "sg:city":"Boynton Beach",
    "sg:classifiers":[
        {
            "category":"Building & Trades",
            "subcategory":"Construction",
            "type":"Services"
        }
    ],
    "sg:phone":"+1 561 740 4446",
    "sg:postcode":"33436",
    "sg:province":"FL",
    "sg:tags":[
        "general",
        "contractor"
    ],
    "wof:name":"Jones Inspection Svc",
    "wof:placetype":"venue"
},
  "geometry": {"coordinates":[-80.12277,26.531022],"type":"Point"}
}