{
  "type": "Feature",
  "properties": {
    "iso:country":"US",
    "sg:address":"620 S D St",
    "sg:city":"Pensacola",
    "sg:classifiers":[
        {
            "category":"Organizations",
            "subcategory":"Community Association",
            "type":"Services"
        }
    ],
    "sg:phone":"+1 850 433 8863",
    "sg:postcode":"32501",
    "sg:province":"FL",
    "wof:name":"Krewe Of Lafitte",
    "wof:placetype":"venue"
},
  "geometry": {"coordinates":[-87.22995899999999,30.403302],"type":"Point"}
}