{
  "type": "Feature",
  "properties": {
    "iso:country":"US",
    "sg:address":"1205 W Oak St",
    "sg:city":"Kissimmee",
    "sg:classifiers":[
        {
            "category":"Restaurant",
            "type":"Food & Drink"
        }
    ],
    "sg:phone":"+1 407 847 3441",
    "sg:postcode":"34741",
    "sg:province":"FL",
    "sg:tags":[
        "eating"
    ],
    "wof:name":"P G's Wings & More",
    "wof:placetype":"venue"
},
  "geometry": {"coordinates":[-81.416082,28.300967],"type":"Point"}
}