{
  "type": "Feature",
  "properties": {
    "addr:full":"4911 W Sam Allen Rd Plant City FL 33565",
    "addr:housenumber":"4911",
    "addr:postcode":"33565",
    "addr:street":"W Sam Allen Rd",
    "iso:country":"US",
    "sg:address":"4911 W Sam Allen Rd",
    "sg:city":"Plant City",
    "sg:classifiers":[
        {
            "category":"Building & Trades",
            "subcategory":"Construction",
            "type":"Services"
        }
    ],
    "sg:phone":"+1 813 621 2567",
    "sg:postcode":"33565",
    "sg:province":"FL",
    "sg:tags":[
        "sheet",
        "metal",
        "contractor"
    ],
    "wof:name":"United Machine Works",
    "wof:placetype":"venue"
},
  "geometry": {"coordinates":[-82.180922,28.046923],"type":"Point"}
}