{
  "type": "Feature",
  "properties": {
    "iso:country":"US",
    "sg:address":"1318 Lafayette St",
    "sg:city":"Cape Coral",
    "sg:classifiers":[
        {
            "category":"Professional",
            "subcategory":"Accounting & Tax Preparation",
            "type":"Services"
        }
    ],
    "sg:phone":"+1 239 549 2444",
    "sg:postcode":"33904",
    "sg:province":"FL",
    "sg:tags":[
        "accountant"
    ],
    "wof:name":"Hill & Co CPA PA",
    "wof:placetype":"venue"
},
  "geometry": {"coordinates":[-81.94789900000001,26.5616],"type":"Point"}
}