{
  "type": "Feature",
  "properties": {
    "addr:full":"71 N Federal Hwy Dania FL 33004",
    "addr:housenumber":"71",
    "addr:postcode":"33004",
    "addr:street":"N Federal Hwy",
    "iso:country":"US",
    "sg:address":"71 N Federal Hwy",
    "sg:city":"Dania",
    "sg:classifiers":[
        {
            "category":"Shopping",
            "subcategory":"Used Merchandise",
            "type":"Retail Goods"
        }
    ],
    "sg:phone":"+1 954 927 0210",
    "sg:postcode":"33004",
    "sg:province":"FL",
    "sg:tags":[
        "antique"
    ],
    "wof:name":"Gordons of London Inc",
    "wof:placetype":"venue"
},
  "geometry": {"coordinates":[-80.143615,26.052817],"type":"Point"}
}