{
  "type": "Feature",
  "properties": {
    "iso:country":"US",
    "sg:address":"5213 Wesconnett Blvd",
    "sg:city":"Jacksonville",
    "sg:classifiers":[
        {
            "category":"Building & Trades",
            "subcategory":"Pest Control",
            "type":"Services"
        }
    ],
    "sg:phone":"+1 904 777 4460",
    "sg:postcode":"32210",
    "sg:province":"FL",
    "wof:name":"Florida Pest Control Co",
    "wof:placetype":"venue"
},
  "geometry": {"coordinates":[-81.739272,30.250025],"type":"Point"}
}