{
  "type": "Feature",
  "properties": {
    "addr:full":"1835 US Hwy 1 S Saint Augustine FL 32084",
    "addr:housenumber":"1835",
    "addr:postcode":"32084",
    "addr:street":"Us Hwy 1 S",
    "iso:country":"US",
    "sg:address":"1835 US Hwy 1 S",
    "sg:city":"Saint Augustine",
    "sg:classifiers":[
        {
            "category":"Building & Trades",
            "subcategory":"Construction",
            "type":"Services"
        }
    ],
    "sg:phone":"+1 904 794 5974",
    "sg:postcode":"32084",
    "sg:province":"FL",
    "sg:tags":[
        "carpentry",
        "contractor"
    ],
    "wof:name":"Lee Henry Carpentry",
    "wof:placetype":"venue"
},
  "geometry": {"coordinates":[-81.32322600000001,29.868251],"type":"Point"}
}