{
  "type": "Feature",
  "properties": {
    "iso:country":"US",
    "sg:address":"523 W King St",
    "sg:city":"Quincy",
    "sg:classifiers":[
        {
            "category":"Education",
            "subcategory":"School",
            "type":"Public Place"
        }
    ],
    "sg:phone":"+1 850 627 3861",
    "sg:postcode":"32351",
    "sg:province":"FL",
    "wof:name":"Quincy Pre-Kindergarten-Hdstrt",
    "wof:placetype":"venue"
},
  "geometry": {"coordinates":[-84.58348700000001,30.591045],"type":"Point"}
}