{
  "type": "Feature",
  "properties": {
    "iso:country":"US",
    "sg:address":"625 N Flagler Dr",
    "sg:city":"West Palm Beach",
    "sg:classifiers":[
        {
            "category":"Professional",
            "type":"Services"
        }
    ],
    "sg:phone":"+1 561 835 8377",
    "sg:postcode":"33401",
    "sg:province":"FL",
    "sg:tags":[
        "establishment"
    ],
    "wof:name":"Iris & B Gerald Cantor Fndtn",
    "wof:placetype":"venue"
},
  "geometry": {"coordinates":[-80.050271,26.71837],"type":"Point"}
}