{
  "type": "Feature",
  "properties": {
    "addr:full":"4500 Pine Cone Pl Cocoa FL 32926",
    "addr:housenumber":"4500",
    "addr:postcode":"32926",
    "addr:street":"Pine Cone Pl",
    "iso:country":"US",
    "sg:address":"4500 Pine Cone Pl",
    "sg:city":"Cocoa",
    "sg:classifiers":[
        {
            "category":"Manufacturing",
            "subcategory":"Building Materials",
            "type":"Manufacturing & Wholesale Goods"
        },
        {
            "category":"Building & Trades",
            "subcategory":"Construction",
            "type":"Services"
        }
    ],
    "sg:phone":"+1 321 633 6462",
    "sg:postcode":"32926",
    "sg:province":"FL",
    "sg:tags":[
        "cabinet",
        "wood",
        "maker",
        "kitchen",
        "mfg"
    ],
    "wof:name":"Case Custom Cabinets",
    "wof:placetype":"venue"
},
  "geometry": {"coordinates":[-80.789418,28.376534],"type":"Point"}
}