{
  "type": "Feature",
  "properties": {
    "iso:country":"US",
    "sg:address":"1650 Latham Rd",
    "sg:city":"West Palm Beach",
    "sg:classifiers":[
        {
            "category":"Taxi",
            "type":"Transportation"
        }
    ],
    "sg:phone":"+1 561 640 0999",
    "sg:postcode":"33409",
    "sg:province":"FL",
    "sg:tags":[
        "taxicab"
    ],
    "wof:name":"City Cab",
    "wof:placetype":"venue"
},
  "geometry": {"coordinates":[-80.082289,26.701613],"type":"Point"}
}