{
  "type": "Feature",
  "properties": {
    "iso:country":"US",
    "sg:address":"6420 Park Ave",
    "sg:city":"Milton",
    "sg:classifiers":[
        {
            "category":"Personal",
            "subcategory":"Beauty Salon",
            "type":"Services"
        }
    ],
    "sg:phone":"+1 850 623 4181",
    "sg:postcode":"32570",
    "sg:province":"FL",
    "sg:tags":[
        "shop"
    ],
    "wof:name":"Park Avenue Hair Design",
    "wof:placetype":"venue"
},
  "geometry": {"coordinates":[-87.05485,30.631049],"type":"Point"}
}