{
  "type": "Feature",
  "properties": {
    "iso:country":"US",
    "sg:address":"6488 State Hwy 121",
    "sg:city":"Lake Butler",
    "sg:classifiers":[
        {
            "category":"Organizations",
            "subcategory":"Religious Organization",
            "type":"Services"
        }
    ],
    "sg:phone":"+1 386 496 3880",
    "sg:postcode":"32054",
    "sg:province":"FL",
    "sg:tags":[
        "church"
    ],
    "wof:name":"Danville Church Of Christ",
    "wof:placetype":"venue"
},
  "geometry": {"coordinates":[-82.350157,30.017768],"type":"Point"}
}