{
  "type": "Feature",
  "properties": {
    "iso:country":"US",
    "sg:address":"510 Dunlawton Ave",
    "sg:city":"Daytona Beach",
    "sg:classifiers":[
        {
            "category":"Social Services",
            "subcategory":"Child Care",
            "type":"Services"
        }
    ],
    "sg:phone":"+1 386 756 0660",
    "sg:postcode":"32127",
    "sg:province":"FL",
    "sg:tags":[
        "day"
    ],
    "wof:name":"Imagination Station",
    "wof:placetype":"venue"
},
  "geometry": {"coordinates":[-80.993748,29.141779],"type":"Point"}
}