{
  "type": "Feature",
  "properties": {
    "iso:country":"US",
    "sg:address":"1033 Fernvale Ave",
    "sg:city":"Sebring",
    "sg:classifiers":[
        {
            "category":"Professional",
            "subcategory":"Advertising",
            "type":"Services"
        }
    ],
    "sg:phone":"+1 863 385 3382",
    "sg:postcode":"33870",
    "sg:province":"FL",
    "wof:name":"Hi-Way Displays",
    "wof:placetype":"venue"
},
  "geometry": {"coordinates":[-81.44415499999999,27.504361],"type":"Point"}
}