{
  "type": "Feature",
  "properties": {
    "addr:full":"855 NE 78th St Boca Raton FL 33487",
    "addr:housenumber":"855",
    "addr:postcode":"33487",
    "addr:street":"Ne 78Th St",
    "iso:country":"US",
    "sg:address":"855 NE 78th St",
    "sg:city":"Boca Raton",
    "sg:classifiers":[
        {
            "category":"Real Estate",
            "subcategory":"Developer",
            "type":"Services"
        }
    ],
    "sg:phone":"+1 561 488 7189",
    "sg:postcode":"33487",
    "sg:province":"FL",
    "wof:name":"Jet Age Homes Inc",
    "wof:placetype":"venue"
},
  "geometry": {"coordinates":[-80.06725,26.419333],"type":"Point"}
}