{
  "type": "Feature",
  "properties": {
    "iso:country":"US",
    "sg:address":"4200 Langley Ave",
    "sg:city":"Pensacola",
    "sg:classifiers":[
        {
            "category":"Recreation",
            "type":"Entertainment"
        }
    ],
    "sg:phone":"+1 850 221 8366",
    "sg:postcode":"32504",
    "sg:province":"FL",
    "sg:tags":[
        "concessionaire"
    ],
    "wof:name":"Lara Mc Knight Barefoot Cncrg",
    "wof:placetype":"venue"
},
  "geometry": {"coordinates":[-87.17150599999999,30.483994],"type":"Point"}
}