{
  "type": "Feature",
  "properties": {
    "addr:full":"11791 S Cleveland Ave Ste 2 Fort Myers FL 33907",
    "addr:housenumber":"11791",
    "addr:postcode":"myers fl 33907",
    "addr:street":"S Cleveland Ave Ste 2",
    "iso:country":"US",
    "sg:address":"11791 S Cleveland Ave Ste 2",
    "sg:city":"Fort Myers",
    "sg:classifiers":[
        {
            "category":"Restaurant",
            "type":"Food & Drink"
        }
    ],
    "sg:phone":"+1 239 936 2003",
    "sg:postcode":"33907",
    "sg:province":"FL",
    "wof:name":"Subway Sandwich & Salads",
    "wof:placetype":"venue"
},
  "geometry": {"coordinates":[-81.87190200000001,26.57],"type":"Point"}
}