{
  "type": "Feature",
  "properties": {
    "iso:country":"US",
    "sg:address":"1110 E 13th St",
    "sg:city":"Hialeah",
    "sg:classifiers":[
        {
            "category":"Shopping",
            "subcategory":"Clothing, Apparel, & Fashions",
            "type":"Retail Goods"
        }
    ],
    "sg:phone":"+1 305 884 7300",
    "sg:postcode":"33010",
    "sg:province":"FL",
    "sg:tags":[
        "handbag"
    ],
    "wof:name":"David's Wholesale Ctr",
    "wof:placetype":"venue"
},
  "geometry": {"coordinates":[-80.26137799999999,25.83428],"type":"Point"}
}