{
  "type": "Feature",
  "properties": {
    "addr:full":"1529 W North A St Tampa FL 33606",
    "addr:housenumber":"1529",
    "addr:postcode":"33606",
    "addr:street":"W North A St",
    "iso:country":"US",
    "sg:address":"1529 W North A St",
    "sg:city":"Tampa",
    "sg:classifiers":[
        {
            "category":"Building & Trades",
            "subcategory":"Construction",
            "type":"Services"
        }
    ],
    "sg:phone":"+1 813 254 7278",
    "sg:postcode":"33606",
    "sg:province":"FL",
    "sg:tags":[
        "specializing",
        "contractor",
        "work",
        "installation",
        "carpet"
    ],
    "sg:website":"www.shawonline.com",
    "wof:name":"Spectra Contract Flooring",
    "wof:placetype":"venue"
},
  "geometry": {"coordinates":[-82.47629000000001,27.946154],"type":"Point"}
}