{
  "type": "Feature",
  "properties": {
    "addr:full":"718 128th St NE Bradenton FL 34212",
    "addr:housenumber":"718",
    "addr:postcode":"34212",
    "addr:street":"128Th St Ne",
    "iso:country":"US",
    "sg:address":"718 128th St NE",
    "sg:city":"Bradenton",
    "sg:classifiers":[
        {
            "category":"Professional",
            "subcategory":"Employment Agencies",
            "type":"Services"
        }
    ],
    "sg:phone":"+1 941 708 9070",
    "sg:postcode":"34212",
    "sg:province":"FL",
    "sg:tags":[
        "help",
        "supply"
    ],
    "wof:name":"Mark Ozment",
    "wof:placetype":"venue"
},
  "geometry": {"coordinates":[-82.41404300000001,27.511961],"type":"Point"}
}