{
  "type": "Feature",
  "properties": {
    "iso:country":"US",
    "sg:address":"4807 W Flamingo Rd",
    "sg:city":"Tampa",
    "sg:classifiers":[
        {
            "category":"Real Estate",
            "subcategory":"Real Estate Operator",
            "type":"Services"
        }
    ],
    "sg:phone":"+1 813 251 6265",
    "sg:postcode":"33611",
    "sg:province":"FL",
    "sg:tags":[
        "building",
        "apartment"
    ],
    "wof:name":"Flamingo Apts",
    "wof:placetype":"venue"
},
  "geometry": {"coordinates":[-82.53008699999999,27.904491],"type":"Point"}
}