{
  "type": "Feature",
  "properties": {
    "iso:country":"US",
    "sg:address":"6445 20th St N",
    "sg:city":"Saint Petersburg",
    "sg:classifiers":[
        {
            "category":"Wholesale",
            "subcategory":"Machinery & Supplies",
            "type":"Manufacturing & Wholesale Goods"
        }
    ],
    "sg:phone":"+1 727 577 6900",
    "sg:postcode":"33702",
    "sg:province":"FL",
    "sg:tags":[
        "equipment",
        "broker",
        "reseller"
    ],
    "wof:name":"Fastex",
    "wof:placetype":"venue"
},
  "geometry": {"coordinates":[-82.66139200000001,27.831522],"type":"Point"}
}