{
  "type": "Feature",
  "properties": {
    "addr:full":"3020 Marcos Dr Miami FL 33160",
    "addr:housenumber":"3020",
    "addr:postcode":"33160",
    "addr:street":"Marcos Dr",
    "iso:country":"US",
    "sg:address":"3020 Marcos Dr",
    "sg:city":"Miami",
    "sg:classifiers":[
        {
            "category":"Professional",
            "subcategory":"Management & Consulting",
            "type":"Services"
        }
    ],
    "sg:phone":"+1 305 692 4489",
    "sg:postcode":"33160",
    "sg:province":"FL",
    "wof:name":"Loria Management Cco",
    "wof:placetype":"venue"
},
  "geometry": {"coordinates":[-80.141668,25.939332],"type":"Point"}
}