{
  "type": "Feature",
  "properties": {
    "iso:country":"US",
    "sg:address":"1500 Colonial Blvd",
    "sg:city":"Fort Myers",
    "sg:classifiers":[
        {
            "category":"Building & Trades",
            "subcategory":"Construction",
            "type":"Services"
        }
    ],
    "sg:phone":"+1 239 278 5766",
    "sg:postcode":"33907",
    "sg:province":"FL",
    "sg:tags":[
        "house"
    ],
    "wof:name":"Adams Homes of NW Florida Inc",
    "wof:placetype":"venue"
},
  "geometry": {"coordinates":[-81.883071,26.596667],"type":"Point"}
}