{
  "type": "Feature",
  "properties": {
    "iso:country":"US",
    "sg:address":"7855 NW 12th St",
    "sg:city":"Doral",
    "sg:classifiers":[
        {
            "category":"Professional",
            "subcategory":"Business Services",
            "type":"Services"
        }
    ],
    "sg:phone":"+1 305 594 8610",
    "sg:postcode":"33126",
    "sg:province":"FL",
    "wof:name":"American Business Acctg",
    "wof:placetype":"venue"
},
  "geometry": {"coordinates":[-80.323002,25.782696],"type":"Point"}
}