{
  "type": "Feature",
  "properties": {
    "iso:country":"US",
    "sg:address":"4007 S Dixie Hwy",
    "sg:city":"West Palm Beach",
    "sg:classifiers":[
        {
            "category":"Personal",
            "type":"Services"
        },
        {
            "category":"Personal",
            "subcategory":"Tattoo Parlor",
            "type":"Services"
        }
    ],
    "sg:phone":"+1 561 659 2900",
    "sg:postcode":"33405",
    "sg:province":"FL",
    "sg:tags":[
        "tattooing"
    ],
    "sg:website":"www.hellcattattoo.com",
    "wof:name":"Hellcat Tattoo Inc",
    "wof:placetype":"venue"
},
  "geometry": {"coordinates":[-80.054855,26.675029],"type":"Point"}
}