{
  "type": "Feature",
  "properties": {
    "addr:full":"1601 US Hwy 1 Boynton Beach FL 33435",
    "addr:housenumber":"1601",
    "addr:postcode":"33435",
    "addr:street":"Us Hwy 1",
    "iso:country":"US",
    "sg:address":"1601 US Hwy 1",
    "sg:city":"Boynton Beach",
    "sg:classifiers":[
        {
            "category":"Professional",
            "subcategory":"Business Services",
            "type":"Services"
        }
    ],
    "sg:phone":"+1 561 734 1659",
    "sg:postcode":"33435",
    "sg:province":"FL",
    "sg:tags":[
        "fire",
        "protection"
    ],
    "wof:name":"Atlantic Coast Fire Equipment",
    "wof:placetype":"venue"
},
  "geometry": {"coordinates":[-80.057194,26.541784],"type":"Point"}
}