{
  "type": "Feature",
  "properties": {
    "addr:full":"11012 Rosehill Dr Clermont FL 34711",
    "addr:housenumber":"11012",
    "addr:postcode":"34711",
    "addr:street":"Rosehill Dr",
    "iso:country":"US",
    "sg:address":"11012 Rosehill Dr",
    "sg:city":"Clermont",
    "sg:classifiers":[
        {
            "category":"Building & Trades",
            "subcategory":"Construction",
            "type":"Services"
        }
    ],
    "sg:phone":"+1 407 719 4463",
    "sg:postcode":"34711",
    "sg:province":"FL",
    "sg:tags":[
        "hanging",
        "contractor"
    ],
    "wof:name":"Cut Line Painting Inc",
    "wof:placetype":"venue"
},
  "geometry": {"coordinates":[-81.768221,28.497415],"type":"Point"}
}