{
  "type": "Feature",
  "properties": {
    "addr:full":"227 S Summit Crescent City FL 32112",
    "addr:housenumber":"227",
    "addr:postcode":"32112",
    "addr:street":"S Summit Crescent",
    "iso:country":"US",
    "sg:address":"227 S Summit",
    "sg:city":"Crescent City",
    "sg:classifiers":[
        {
            "category":"Restaurant",
            "type":"Food & Drink"
        }
    ],
    "sg:phone":"+1 386 698 4189",
    "sg:postcode":"32112",
    "sg:province":"FL",
    "wof:name":"Jim & Lynn Smith's Smokehouse",
    "wof:placetype":"venue"
},
  "geometry": {"coordinates":[-81.510569,29.433706],"type":"Point"}
}