{
  "type": "Feature",
  "properties": {
    "iso:country":"US",
    "sg:address":"2307 W Comanche Ave",
    "sg:city":"Tampa",
    "sg:classifiers":[
        {
            "category":"Professional",
            "subcategory":"Lawyer & Legal Services",
            "type":"Services"
        }
    ],
    "sg:phone":"+1 813 875 7016",
    "sg:postcode":"33603",
    "sg:province":"FL",
    "sg:tags":[
        "information",
        "attorney",
        "referral"
    ],
    "wof:name":"Kevin J Mcdonald Pa",
    "wof:placetype":"venue"
},
  "geometry": {"coordinates":[-82.48259299999999,27.997585],"type":"Point"}
}