{
  "type": "Feature",
  "properties": {
    "addr:full":"347 Mcarthur Ave Sarasota FL 34243",
    "addr:housenumber":"347",
    "addr:postcode":"34243",
    "addr:street":"Mcarthur Ave",
    "iso:country":"US",
    "sg:address":"347 Mcarthur Ave",
    "sg:city":"Sarasota",
    "sg:classifiers":[
        {
            "category":"Real Estate",
            "subcategory":"Real Estate Services",
            "type":"Services"
        }
    ],
    "sg:phone":"+1 941 302 3293",
    "sg:postcode":"34243",
    "sg:province":"FL",
    "sg:tags":[
        "inspection"
    ],
    "wof:name":"Complete Home Inspection",
    "wof:placetype":"venue"
},
  "geometry": {"coordinates":[-82.567818,27.410219],"type":"Point"}
}