{
  "type": "Feature",
  "properties": {
    "addr:full":"1125 Kings Estate Rd Saint Augustine FL 32086",
    "addr:housenumber":"1125",
    "addr:postcode":"32086",
    "addr:street":"Kings Estate Rd",
    "iso:country":"US",
    "sg:address":"1125 Kings Estate Rd",
    "sg:city":"Saint Augustine",
    "sg:classifiers":[
        {
            "category":"Retail",
            "subcategory":"Auto Repair",
            "type":"Services"
        }
    ],
    "sg:phone":"+1 904 794 5330",
    "sg:postcode":"32086",
    "sg:province":"FL",
    "sg:tags":[
        "general"
    ],
    "wof:name":"Extreme Auto Accessories",
    "wof:placetype":"venue"
},
  "geometry": {"coordinates":[-81.34711,29.845403],"type":"Point"}
}