{
  "type": "Feature",
  "properties": {
    "addr:full":"411 E Harding St Orlando FL 32806",
    "addr:housenumber":"411",
    "addr:postcode":"32806",
    "addr:street":"E Harding St",
    "iso:country":"US",
    "sg:address":"411 E Harding St",
    "sg:city":"Orlando",
    "sg:classifiers":[
        {
            "category":"Shopping",
            "subcategory":"Gifts & Souvenirs",
            "type":"Retail Goods"
        }
    ],
    "sg:phone":"+1 407 316 0034",
    "sg:postcode":"32806",
    "sg:province":"FL",
    "wof:name":"Backstage Magic & Novelties",
    "wof:placetype":"venue"
},
  "geometry": {"coordinates":[-81.370644,28.518542],"type":"Point"}
}