{
  "type": "Feature",
  "properties": {
    "iso:country":"US",
    "sg:address":"2000 Parks Oaks Ave",
    "sg:city":"Orlando",
    "sg:classifiers":[
        {
            "category":"Wholesale",
            "subcategory":"Hardware",
            "type":"Manufacturing & Wholesale Goods"
        }
    ],
    "sg:phone":"+1 407 532 7000",
    "sg:postcode":"32808",
    "sg:province":"FL",
    "sg:tags":[
        "heater",
        "make",
        "refrigeration",
        "air"
    ],
    "sg:website":"www.carrier.com",
    "wof:name":"Carrier Central Florida",
    "wof:placetype":"venue"
},
  "geometry": {"coordinates":[-81.42235599999999,28.568911],"type":"Point"}
}