{
  "type": "Feature",
  "properties": {
    "addr:full":"4303 Vineland Rd Orlando FL 32811",
    "addr:housenumber":"4303",
    "addr:postcode":"32811",
    "addr:street":"Vineland Rd",
    "iso:country":"US",
    "sg:address":"4303 Vineland Rd",
    "sg:city":"Orlando",
    "sg:classifiers":[
        {
            "category":"Building & Trades",
            "subcategory":"Construction",
            "type":"Services"
        }
    ],
    "sg:phone":"+1 407 841 5411",
    "sg:postcode":"32811",
    "sg:province":"FL",
    "sg:tags":[
        "home",
        "builder"
    ],
    "wof:name":"Sunshine Magic Vacation Homes",
    "wof:placetype":"venue"
},
  "geometry": {"coordinates":[-81.432247,28.499293],"type":"Point"}
}