{
  "type": "Feature",
  "properties": {
    "addr:full":"320 N Atlantic Ave Cocoa Beach FL 32931",
    "addr:housenumber":"320",
    "addr:postcode":"32931",
    "addr:street":"N Atlantic Ave",
    "iso:country":"US",
    "sg:address":"320 N Atlantic Ave",
    "sg:city":"Cocoa Beach",
    "sg:classifiers":[
        {
            "category":"Professional",
            "subcategory":"Management & Consulting",
            "type":"Services"
        }
    ],
    "sg:phone":"+1 321 799 4022",
    "sg:postcode":"32931",
    "sg:province":"FL",
    "sg:tags":[
        "consultant",
        "business"
    ],
    "sg:website":"www.cmtfl.com",
    "wof:name":"Creative Management Technology",
    "wof:placetype":"venue"
},
  "geometry": {"coordinates":[-80.609185,28.325236],"type":"Point"}
}