{
  "type": "Feature",
  "properties": {
    "addr:full":"5307 Forest Breeze Ct Saint Cloud FL 34771",
    "addr:housenumber":"5307",
    "addr:postcode":"34771",
    "addr:street":"Forest Breeze Ct",
    "iso:country":"US",
    "sg:address":"5307 Forest Breeze Ct",
    "sg:city":"Saint Cloud",
    "sg:classifiers":[
        {
            "category":"Banks & Credit Unions",
            "subcategory":"Investment Brokerage",
            "type":"Services"
        }
    ],
    "sg:phone":"+1 407 892 0079",
    "sg:postcode":"34771",
    "sg:province":"FL",
    "sg:tags":[
        "advisory"
    ],
    "wof:name":"Gbi Inc",
    "wof:placetype":"venue"
},
  "geometry": {"coordinates":[-81.2289,28.346926],"type":"Point"}
}