{
  "type": "Feature",
  "properties": {
    "addr:full":"4220 Aledo St Cocoa FL 32927",
    "addr:housenumber":"4220",
    "addr:postcode":"32927",
    "addr:street":"Aledo St",
    "iso:country":"US",
    "sg:address":"4220 Aledo St",
    "sg:city":"Cocoa",
    "sg:classifiers":[
        {
            "category":"Real Estate",
            "subcategory":"Real Estate Agent",
            "type":"Services"
        }
    ],
    "sg:phone":"+1 321 632 1366",
    "sg:postcode":"32927",
    "sg:province":"FL",
    "wof:name":"For Buyers Only",
    "wof:placetype":"venue"
},
  "geometry": {"coordinates":[-80.787811,28.484762],"type":"Point"}
}