{
  "type": "Feature",
  "properties": {
    "iso:country":"US",
    "sg:address":"1674 NW 82nd Ave",
    "sg:city":"Miami",
    "sg:classifiers":[
        {
            "category":"Wholesale",
            "subcategory":"Durable Goods & Equipment",
            "type":"Manufacturing & Wholesale Goods"
        }
    ],
    "sg:phone":"+1 305 470 6250",
    "sg:postcode":"33126",
    "sg:province":"FL",
    "wof:name":"Integrated Supports Services",
    "wof:placetype":"venue"
},
  "geometry": {"coordinates":[-80.328817,25.789637],"type":"Point"}
}