{
  "type": "Feature",
  "properties": {
    "addr:full":"1515 June Ave Panama City FL 32405",
    "addr:housenumber":"1515",
    "addr:postcode":"32405",
    "addr:street":"June Ave",
    "iso:country":"US",
    "sg:address":"1515 June Ave",
    "sg:city":"Panama City",
    "sg:classifiers":[
        {
            "category":"Education",
            "subcategory":"School",
            "type":"Public Place"
        }
    ],
    "sg:phone":"+1 850 873 4111",
    "sg:postcode":"32405",
    "sg:province":"FL",
    "wof:name":"Emerald Bay Academy",
    "wof:placetype":"venue"
},
  "geometry": {"coordinates":[-85.678605,30.176751],"type":"Point"}
}