{
  "type": "Feature",
  "properties": {
    "iso:country":"US",
    "sg:address":"15062 SW 9th Way",
    "sg:city":"Miami",
    "sg:classifiers":[
        {
            "category":"Manufacturing",
            "subcategory":"Metals",
            "type":"Manufacturing & Wholesale Goods"
        }
    ],
    "sg:phone":"+1 305 970 4145",
    "sg:postcode":"33194",
    "sg:province":"FL",
    "sg:tags":[
        "steel",
        "fabricator",
        "specialty"
    ],
    "wof:name":"Hernandez Metal Fabricators",
    "wof:placetype":"venue"
},
  "geometry": {"coordinates":[-80.43982099999999,25.757687],"type":"Point"}
}