{
  "type": "Feature",
  "properties": {
    "iso:country":"US",
    "sg:address":"2239 SE 27th St",
    "sg:city":"Cape Coral",
    "sg:classifiers":[
        {
            "category":"Retail",
            "subcategory":"Auto Repair",
            "type":"Services"
        }
    ],
    "sg:phone":"+1 239 574 7475",
    "sg:postcode":"33904",
    "sg:province":"FL",
    "sg:tags":[
        "general"
    ],
    "wof:name":"Auto Service of Schiller",
    "wof:placetype":"venue"
},
  "geometry": {"coordinates":[-81.924229,26.60365],"type":"Point"}
}