{
  "type": "Feature",
  "properties": {
    "addr:full":"1724 Mc Quade St Jacksonville FL 32209",
    "addr:housenumber":"1724",
    "addr:postcode":"32209",
    "addr:street":"Mc Quade St",
    "iso:country":"US",
    "sg:address":"1724 Mc Quade St",
    "sg:city":"Jacksonville",
    "sg:classifiers":[
        {
            "category":"Personal",
            "subcategory":"Beauty Salon",
            "type":"Services"
        }
    ],
    "sg:phone":"+1 904 356 4577",
    "sg:postcode":"32209",
    "sg:province":"FL",
    "wof:name":"Daddy's Cutters",
    "wof:placetype":"venue"
},
  "geometry": {"coordinates":[-81.68710299999999,30.339058],"type":"Point"}
}