{
  "type": "Feature",
  "properties": {
    "addr:full":"839 E 24th St Hialeah FL 33013",
    "addr:housenumber":"839",
    "addr:postcode":"33013",
    "addr:street":"E 24Th St",
    "iso:country":"US",
    "sg:address":"839 E 24th St",
    "sg:city":"Hialeah",
    "sg:classifiers":[
        {
            "category":"Real Estate",
            "subcategory":"Real Estate Operator",
            "type":"Services"
        }
    ],
    "sg:phone":"+1 305 836 8130",
    "sg:postcode":"33013",
    "sg:province":"FL",
    "sg:tags":[
        "building",
        "apartment"
    ],
    "wof:name":"Chaple Apts",
    "wof:placetype":"venue"
},
  "geometry": {"coordinates":[-80.264826,25.844451],"type":"Point"}
}