{
  "type": "Feature",
  "properties": {
    "addr:full":"346 Valparaiso Pkwy Valparaiso FL 32580",
    "addr:housenumber":"346",
    "addr:postcode":"32580",
    "addr:street":"Valparaiso Pkwy",
    "iso:country":"US",
    "sg:address":"346 Valparaiso Pkwy",
    "sg:city":"Valparaiso",
    "sg:classifiers":[
        {
            "category":"Personal",
            "type":"Services"
        },
        {
            "category":"Building & Trades",
            "subcategory":"Cleaning & Sanitation",
            "type":"Services"
        }
    ],
    "sg:phone":"+1 850 678 4118",
    "sg:postcode":"32580",
    "sg:province":"FL",
    "sg:tags":[
        "house",
        "butlers'",
        "maids'"
    ],
    "wof:name":"Aim High Cleaning Service",
    "wof:placetype":"venue"
},
  "geometry": {"coordinates":[-86.494789,30.510465],"type":"Point"}
}