{
  "type": "Feature",
  "properties": {
    "iso:country":"US",
    "sg:address":"7401 SW 84th Pl",
    "sg:city":"Miami",
    "sg:classifiers":[
        {
            "category":"Retail",
            "subcategory":"Veterinary Services",
            "type":"Services"
        }
    ],
    "sg:phone":"+1 305 270 0484",
    "sg:postcode":"33143",
    "sg:province":"FL",
    "sg:tags":[
        "veterinarian"
    ],
    "sg:website":"stanleyglassdvmhousecalls.com/",
    "wof:name":"Dr Stanley Glass Housecalls",
    "wof:placetype":"venue"
},
  "geometry": {"coordinates":[-80.331177,25.700675],"type":"Point"}
}