{
  "type": "Feature",
  "properties": {
    "addr:full":"6812 S Cortez Ave Tampa FL 33616",
    "addr:housenumber":"6812",
    "addr:postcode":"33616",
    "addr:street":"S Cortez Ave",
    "iso:country":"US",
    "sg:address":"6812 S Cortez Ave",
    "sg:city":"Tampa",
    "sg:classifiers":[
        {
            "category":"Wholesale",
            "subcategory":"Non-durable Goods",
            "type":"Manufacturing & Wholesale Goods"
        }
    ],
    "sg:phone":"+1 813 837 0999",
    "sg:postcode":"33616",
    "sg:province":"FL",
    "wof:name":"Victoria C Jewett",
    "wof:placetype":"venue"
},
  "geometry": {"coordinates":[-82.520025,27.867334],"type":"Point"}
}