{
  "type": "Feature",
  "properties": {
    "addr:full":"5901 Haines Rd N St Petersburg FL 33714",
    "addr:housenumber":"5901",
    "addr:postcode":"33714",
    "addr:street":"Haines Rd N",
    "iso:country":"US",
    "sg:address":"5901 Haines Rd N",
    "sg:city":"St Petersburg",
    "sg:classifiers":[
        {
            "category":"Restaurant",
            "type":"Food & Drink"
        }
    ],
    "sg:phone":"+1 727 528 2508",
    "sg:postcode":"33714",
    "sg:province":"FL",
    "wof:name":"Mikes Breakfast & Lunch",
    "wof:placetype":"venue"
},
  "geometry": {"coordinates":[-82.674116,27.82661],"type":"Point"}
}