{
  "type": "Feature",
  "properties": {
    "addr:full":"25 Granada St St Augustine FL 32084",
    "addr:housenumber":"25",
    "addr:postcode":"32084",
    "addr:street":"Granada St",
    "iso:country":"US",
    "sg:address":"25 Granada St",
    "sg:city":"St Augustine",
    "sg:classifiers":[
        {
            "category":"Restaurant",
            "type":"Food & Drink"
        }
    ],
    "sg:phone":"+1 904 824 7813",
    "sg:postcode":"32084",
    "sg:province":"FL",
    "sg:tags":[
        "eating"
    ],
    "wof:name":"Cafe Alcazar",
    "wof:placetype":"venue"
},
  "geometry": {"coordinates":[-81.31431499999999,29.891392],"type":"Point"}
}