{
  "type": "Feature",
  "properties": {
    "iso:country":"US",
    "sg:address":"5502 Pioneer Park Blvd",
    "sg:city":"Tampa",
    "sg:classifiers":[
        {
            "category":"Manufacturing",
            "subcategory":"Building Materials",
            "type":"Manufacturing & Wholesale Goods"
        }
    ],
    "sg:phone":"+1 813 889 3861",
    "sg:postcode":"33634",
    "sg:province":"FL",
    "sg:tags":[
        "door",
        "mfg"
    ],
    "wof:name":"Premdor",
    "wof:placetype":"venue"
},
  "geometry": {"coordinates":[-82.535967,28.013596],"type":"Point"}
}