{
  "type": "Feature",
  "properties": {
    "iso:country":"US",
    "sg:address":"1420 State Hwy 20",
    "sg:city":"Interlachen",
    "sg:classifiers":[
        {
            "category":"Shopping",
            "subcategory":"Used Merchandise",
            "type":"Retail Goods"
        }
    ],
    "sg:phone":"+1 386 684 6982",
    "sg:postcode":"32148",
    "sg:province":"FL",
    "sg:tags":[
        "pawnbroker"
    ],
    "wof:name":"Bucks Gold & Pawn",
    "wof:placetype":"venue"
},
  "geometry": {"coordinates":[-81.93069,29.623859],"type":"Point"}
}