{
  "type": "Feature",
  "properties": {
    "iso:country":"US",
    "sg:address":"1125 Kenneth Ave",
    "sg:city":"Crestview",
    "sg:classifiers":[
        {
            "category":"Real Estate",
            "subcategory":"Surveying",
            "type":"Services"
        }
    ],
    "sg:phone":"+1 850 682 4385",
    "sg:postcode":"32536",
    "sg:province":"FL",
    "sg:tags":[
        "surveyor"
    ],
    "wof:name":"Robert F Johnson",
    "wof:placetype":"venue"
},
  "geometry": {"coordinates":[-86.5748,30.77515],"type":"Point"}
}