{
  "type": "Feature",
  "properties": {
    "addr:full":"4800 NW 157th St Hialeah FL 33014",
    "addr:housenumber":"4800",
    "addr:postcode":"33014",
    "addr:street":"Nw 157Th St",
    "iso:country":"US",
    "sg:address":"4800 NW 157th St",
    "sg:city":"Hialeah",
    "sg:classifiers":[
        {
            "category":"Manufacturing",
            "subcategory":"Tools & Machinery",
            "type":"Manufacturing & Wholesale Goods"
        }
    ],
    "sg:phone":"+1 305 623 8700",
    "sg:postcode":"33014",
    "sg:province":"FL",
    "sg:tags":[
        "manufacture",
        "industry",
        "paper"
    ],
    "wof:name":"Quipp Inc",
    "wof:placetype":"venue"
},
  "geometry": {"coordinates":[-80.28033499999999,25.916929],"type":"Point"}
}