{
  "type": "Feature",
  "properties": {
    "iso:country":"US",
    "sg:address":"4006 Water Park Ct",
    "sg:city":"Riverview",
    "sg:classifiers":[
        {
            "category":"Home & Garden",
            "subcategory":"Furniture",
            "type":"Retail Goods"
        }
    ],
    "sg:phone":"+1 813 684 7528",
    "sg:postcode":"33578",
    "sg:province":"FL",
    "wof:name":"Landmark Industries Inc",
    "wof:placetype":"venue"
},
  "geometry": {"coordinates":[-82.354263,27.914593],"type":"Point"}
}