{
  "type": "Feature",
  "properties": {
    "addr:full":"1275 Starkey Rd Largo FL 33771",
    "addr:housenumber":"1275",
    "addr:postcode":"33771",
    "addr:street":"Starkey Rd",
    "iso:country":"US",
    "sg:address":"1275 Starkey Rd",
    "sg:city":"Largo",
    "sg:classifiers":[
        {
            "category":"Autos & Motor Vehicles",
            "subcategory":"Auto Supplies",
            "type":"Retail Goods"
        },
        {
            "category":"Retail",
            "subcategory":"Auto Repair",
            "type":"Services"
        }
    ],
    "sg:phone":"+1 727 531 7372",
    "sg:postcode":"33771",
    "sg:province":"FL",
    "sg:tags":[
        "tire"
    ],
    "sg:website":"http://hstrial-BrownAutomoti.intuitwebsites.com",
    "wof:name":"Brown Automotive Inc",
    "wof:placetype":"venue"
},
  "geometry": {"coordinates":[-82.762383,27.905619],"type":"Point"}
}