{
  "type": "Feature",
  "properties": {
    "addr:full":"2845 Tech Dr Orlando FL 32817",
    "addr:housenumber":"2845",
    "addr:postcode":"32817",
    "addr:street":"Tech Dr",
    "iso:country":"US",
    "sg:address":"2845 Tech Dr",
    "sg:city":"Orlando",
    "sg:classifiers":[
        {
            "category":"Professional",
            "type":"Services"
        }
    ],
    "sg:phone":"+1 407 679 0695",
    "sg:postcode":"32817",
    "sg:province":"FL",
    "sg:tags":[
        "establishment"
    ],
    "wof:name":"Underworld Productions",
    "wof:placetype":"venue"
},
  "geometry": {"coordinates":[-81.27029400000001,28.582116],"type":"Point"}
}