{
  "type": "Feature",
  "properties": {
    "addr:full":"815 Success Ave Lakeland FL 33801",
    "addr:housenumber":"815",
    "addr:postcode":"33801",
    "addr:street":"Success Ave",
    "iso:country":"US",
    "sg:address":"815 Success Ave",
    "sg:city":"Lakeland",
    "sg:classifiers":[
        {
            "category":"Building & Trades",
            "subcategory":"Cleaning & Sanitation",
            "type":"Services"
        }
    ],
    "sg:phone":"+1 863 687 3075",
    "sg:postcode":"33801",
    "sg:province":"FL",
    "sg:tags":[
        "property",
        "maintenance"
    ],
    "wof:name":"Action Property Maintainance",
    "wof:placetype":"venue"
},
  "geometry": {"coordinates":[-81.95317,28.034634],"type":"Point"}
}