{
  "type": "Feature",
  "properties": {
    "iso:country":"US",
    "sg:address":"7613 E 26th Ave",
    "sg:city":"Tampa",
    "sg:classifiers":[
        {
            "category":"Wholesale",
            "subcategory":"Durable Goods & Equipment",
            "type":"Manufacturing & Wholesale Goods"
        }
    ],
    "sg:phone":"+1 813 626 0069",
    "sg:postcode":"33619",
    "sg:province":"FL",
    "wof:name":"Bay Area Trading Co",
    "wof:placetype":"venue"
},
  "geometry": {"coordinates":[-82.36999900000001,27.974013],"type":"Point"}
}