{
  "type": "Feature",
  "properties": {
    "addr:full":"260 Alameda Ave Fort Myers FL 33905",
    "addr:housenumber":"260",
    "addr:postcode":"33905",
    "addr:street":"Alameda Ave",
    "iso:country":"US",
    "sg:address":"260 Alameda Ave",
    "sg:city":"Fort Myers",
    "sg:classifiers":[
        {
            "category":"Retail",
            "subcategory":"Repair Shop",
            "type":"Services"
        }
    ],
    "sg:phone":"+1 239 693 6835",
    "sg:postcode":"33905",
    "sg:province":"FL",
    "sg:tags":[
        "electrical"
    ],
    "wof:name":"Clarence D Bowman",
    "wof:placetype":"venue"
},
  "geometry": {"coordinates":[-81.807889,26.687394],"type":"Point"}
}