{
  "type": "Feature",
  "properties": {
    "iso:country":"US",
    "sg:address":"308 Talwood Dr",
    "sg:city":"Tallahassee",
    "sg:classifiers":[
        {
            "category":"Building & Trades",
            "subcategory":"Construction",
            "type":"Services"
        }
    ],
    "sg:phone":"+1 850 385 6993",
    "sg:postcode":"32312",
    "sg:province":"FL",
    "sg:tags":[
        "contractor"
    ],
    "wof:name":"Seminole Pressure Cleaning",
    "wof:placetype":"venue"
},
  "geometry": {"coordinates":[-84.28801300000001,30.479785],"type":"Point"}
}