{
  "type": "Feature",
  "properties": {
    "addr:full":"5409 Evora Ave Sarasota FL 34235",
    "addr:housenumber":"5409",
    "addr:postcode":"34235",
    "addr:street":"Evora Ave",
    "iso:country":"US",
    "sg:address":"5409 Evora Ave",
    "sg:city":"Sarasota",
    "sg:classifiers":[
        {
            "category":"Building & Trades",
            "subcategory":"Construction",
            "type":"Services"
        }
    ],
    "sg:phone":"+1 941 355 6811",
    "sg:postcode":"34235",
    "sg:province":"FL",
    "sg:tags":[
        "roofing",
        "contractor"
    ],
    "wof:name":"Quali-Tile Roofing Inc",
    "wof:placetype":"venue"
},
  "geometry": {"coordinates":[-82.489051,27.380765],"type":"Point"}
}