{
  "type": "Feature",
  "properties": {
    "iso:country":"US",
    "sg:address":"6855 Plum Lake Dr N",
    "sg:city":"Jacksonville",
    "sg:classifiers":[
        {
            "category":"Restaurant",
            "type":"Food & Drink"
        }
    ],
    "sg:phone":"+1 904 573 5829",
    "sg:postcode":"32222",
    "sg:province":"FL",
    "sg:tags":[
        "eating"
    ],
    "wof:name":"Daves Donut Shoppe Inc",
    "wof:placetype":"venue"
},
  "geometry": {"coordinates":[-81.818065,30.221919],"type":"Point"}
}