{
  "type": "Feature",
  "properties": {
    "iso:country":"US",
    "sg:address":"3858 Schoenwald Ln",
    "sg:city":"Jacksonville",
    "sg:classifiers":[
        {
            "category":"Building & Trades",
            "subcategory":"Construction",
            "type":"Services"
        }
    ],
    "sg:phone":"+1 904 292 4269",
    "sg:postcode":"32223",
    "sg:province":"FL",
    "sg:tags":[
        "contractor"
    ],
    "wof:name":"EIS Construction Co",
    "wof:placetype":"venue"
},
  "geometry": {"coordinates":[-81.60995800000001,30.160643],"type":"Point"}
}