{
  "type": "Feature",
  "properties": {
    "iso:country":"US",
    "sg:address":"9821 50th Ave N",
    "sg:city":"Saint Petersburg",
    "sg:classifiers":[
        {
            "category":"Real Estate",
            "subcategory":"Real Estate Agent",
            "type":"Services"
        }
    ],
    "sg:phone":"+1 727 392 3672",
    "sg:postcode":"33708",
    "sg:province":"FL",
    "sg:tags":[
        "appraiser"
    ],
    "wof:name":"Djn Enterprise",
    "wof:placetype":"venue"
},
  "geometry": {"coordinates":[-82.77496600000001,27.817764],"type":"Point"}
}