{
  "type": "Feature",
  "properties": {
    "addr:full":"6621 Southpoint Dr N Jacksonville FL 32216",
    "addr:housenumber":"6621",
    "addr:postcode":"32216",
    "addr:street":"Southpoint Dr N",
    "iso:country":"US",
    "sg:address":"6621 Southpoint Dr N",
    "sg:city":"Jacksonville",
    "sg:classifiers":[
        {
            "category":"Utilities",
            "subcategory":"Telephone",
            "type":"Services"
        }
    ],
    "sg:phone":"+1 904 279 9880",
    "sg:postcode":"32216",
    "sg:province":"FL",
    "sg:tags":[
        "telecommunication"
    ],
    "wof:name":"Qwest Communications",
    "wof:placetype":"venue"
},
  "geometry": {"coordinates":[-81.589974,30.254581],"type":"Point"}
}