{
  "type": "Feature",
  "properties": {
    "addr:full":"914 S Pinellas Ave Tarpon Springs FL 34689",
    "addr:housenumber":"914",
    "addr:postcode":"34689",
    "addr:street":"S Pinellas Ave",
    "iso:country":"US",
    "sg:address":"914 S Pinellas Ave",
    "sg:city":"Tarpon Springs",
    "sg:classifiers":[
        {
            "category":"Food & Beverages",
            "subcategory":"Groceries & Convenience Stores",
            "type":"Retail Goods"
        }
    ],
    "sg:phone":"+1 727 942 0379",
    "sg:postcode":"34689",
    "sg:province":"FL",
    "sg:tags":[
        "grocer"
    ],
    "wof:name":"European Foods Inc",
    "wof:placetype":"venue"
},
  "geometry": {"coordinates":[-82.75662199999999,28.140411],"type":"Point"}
}