{
  "type": "Feature",
  "properties": {
    "addr:full":"1584 Riverside Dr Daytona Beach FL 32117",
    "addr:housenumber":"1584",
    "addr:postcode":"32117",
    "addr:street":"Riverside Dr",
    "iso:country":"US",
    "sg:address":"1584 Riverside Dr",
    "sg:city":"Daytona Beach",
    "sg:classifiers":[
        {
            "category":"Wholesale",
            "subcategory":"Vending Machines",
            "type":"Manufacturing & Wholesale Goods"
        }
    ],
    "sg:phone":"+1 386 253 7994",
    "sg:postcode":"32117",
    "sg:province":"FL",
    "sg:tags":[
        "operator"
    ],
    "wof:name":"H&B Vending Inc",
    "wof:placetype":"venue"
},
  "geometry": {"coordinates":[-81.04079900000001,29.256861],"type":"Point"}
}