{
  "type": "Feature",
  "properties": {
    "iso:country":"US",
    "sg:address":"458 Grant St",
    "sg:city":"Dunedin",
    "sg:classifiers":[
        {
            "category":"Professional",
            "subcategory":"Employment Agencies",
            "type":"Services"
        }
    ],
    "sg:phone":"+1 727 735 0838",
    "sg:postcode":"34698",
    "sg:province":"FL",
    "sg:tags":[
        "opportunity"
    ],
    "wof:name":"Bristol Associates",
    "wof:placetype":"venue"
},
  "geometry": {"coordinates":[-82.786502,28.01314],"type":"Point"}
}