{
  "type": "Feature",
  "properties": {
    "iso:country":"US",
    "sg:address":"2719 W Bobe St",
    "sg:city":"Pensacola",
    "sg:classifiers":[
        {
            "category":"Building & Trades",
            "subcategory":"Construction",
            "type":"Services"
        }
    ],
    "sg:phone":"+1 850 432 0678",
    "sg:postcode":"32505",
    "sg:province":"FL",
    "sg:tags":[
        "masonry"
    ],
    "wof:name":"Wesleys Masonry Construction",
    "wof:placetype":"venue"
},
  "geometry": {"coordinates":[-87.24800500000001,30.436272],"type":"Point"}
}