{
  "type": "Feature",
  "properties": {
    "iso:country":"US",
    "sg:address":"2054 Warwick Hills Dr",
    "sg:city":"Orlando",
    "sg:classifiers":[
        {
            "category":"Personal",
            "type":"Services"
        }
    ],
    "sg:phone":"+1 407 384 3312",
    "sg:postcode":"32826",
    "sg:province":"FL",
    "sg:tags":[
        "house",
        "construction"
    ],
    "wof:name":"RG Service",
    "wof:placetype":"venue"
},
  "geometry": {"coordinates":[-81.17497299999999,28.575685],"type":"Point"}
}