{
  "type": "Feature",
  "properties": {
    "addr:full":"3588 Gardenview St Milton FL 32571",
    "addr:housenumber":"3588",
    "addr:postcode":"32571",
    "addr:street":"Gardenview St",
    "iso:country":"US",
    "sg:address":"3588 Gardenview St",
    "sg:city":"Milton",
    "sg:classifiers":[
        {
            "category":"Building & Trades",
            "subcategory":"Landscaping Services",
            "type":"Services"
        }
    ],
    "sg:phone":"+1 850 994 5817",
    "sg:postcode":"32571",
    "sg:province":"FL",
    "sg:tags":[
        "tree"
    ],
    "wof:name":"Box Shrubs",
    "wof:placetype":"venue"
},
  "geometry": {"coordinates":[-87.17322,30.64763],"type":"Point"}
}