{
  "type": "Feature",
  "properties": {
    "iso:country":"US",
    "sg:address":"1770 Windover Oaks Cir",
    "sg:city":"Titusville",
    "sg:classifiers":[
        {
            "category":"Real Estate",
            "subcategory":"Real Estate Operator",
            "type":"Services"
        }
    ],
    "sg:phone":"+1 321 268 3432",
    "sg:postcode":"32780",
    "sg:province":"FL",
    "sg:tags":[
        "building",
        "apartment"
    ],
    "wof:name":"Windover Oaks Apartments",
    "wof:placetype":"venue"
},
  "geometry": {"coordinates":[-80.832624,28.591441],"type":"Point"}
}