{
  "type": "Feature",
  "properties": {
    "iso:country":"US",
    "sg:address":"7859 N Frontage Rd",
    "sg:city":"Orlando",
    "sg:classifiers":[
        {
            "category":"Parking",
            "subcategory":"Lot",
            "type":"Transportation"
        }
    ],
    "sg:phone":"+1 407 251 7555",
    "sg:postcode":"32812",
    "sg:province":"FL",
    "sg:tags":[
        "airport"
    ],
    "wof:name":"Parking Company of America",
    "wof:placetype":"venue"
},
  "geometry": {"coordinates":[-81.31588000000001,28.45213],"type":"Point"}
}