{
  "type": "Feature",
  "properties": {
    "addr:full":"2401 SW 16th Ct Miami FL 33145",
    "addr:housenumber":"2401",
    "addr:postcode":"33145",
    "addr:street":"Sw 16Th Ct",
    "iso:country":"US",
    "sg:address":"2401 SW 16th Ct",
    "sg:city":"Miami",
    "sg:classifiers":[
        {
            "category":"Professional",
            "subcategory":"Lawyer & Legal Services",
            "type":"Services"
        }
    ],
    "sg:phone":"+1 305 595 0645",
    "sg:postcode":"33145",
    "sg:province":"FL",
    "sg:tags":[
        "naturalization",
        "immigration"
    ],
    "wof:name":"Immigration Service Group",
    "wof:placetype":"venue"
},
  "geometry": {"coordinates":[-80.220761,25.747749],"type":"Point"}
}