{
  "type": "Feature",
  "properties": {
    "addr:full":"14180 NE 6th Ave North Miami FL 33161",
    "addr:housenumber":"14180",
    "addr:postcode":"33161",
    "addr:street":"Ne 6Th Ave",
    "iso:country":"US",
    "sg:address":"14180 NE 6th Ave",
    "sg:city":"North Miami",
    "sg:classifiers":[
        {
            "category":"Education",
            "subcategory":"Preschool",
            "type":"Public Place"
        },
        {
            "category":"Education",
            "subcategory":"School",
            "type":"Public Place"
        }
    ],
    "sg:phone":"+1 305 893 0603",
    "sg:postcode":"33161",
    "sg:province":"FL",
    "sg:tags":[
        "elementary"
    ],
    "wof:name":"Star Bright Montessori Pre School",
    "wof:placetype":"venue"
},
  "geometry": {"coordinates":[-80.18699599999999,25.9055],"type":"Point"}
}