{
  "type": "Feature",
  "properties": {
    "addr:full":"3524 US Hwy 1 S Saint Augustine FL 32086",
    "addr:housenumber":"3524",
    "addr:postcode":"32086",
    "addr:street":"Us Hwy 1 S",
    "iso:country":"US",
    "sg:address":"3524 US Hwy 1 S",
    "sg:city":"Saint Augustine",
    "sg:classifiers":[
        {
            "category":"Retail",
            "subcategory":"Auto Rental",
            "type":"Services"
        }
    ],
    "sg:phone":"+1 904 794 0775",
    "sg:postcode":"32086",
    "sg:province":"FL",
    "sg:tags":[
        "truck"
    ],
    "wof:name":"U-Haul",
    "wof:placetype":"venue"
},
  "geometry": {"coordinates":[-81.322104,29.828931],"type":"Point"}
}