{
  "type": "Feature",
  "properties": {
    "addr:full":"1243 Pine St Valrico FL 33594",
    "addr:housenumber":"1243",
    "addr:postcode":"33594",
    "addr:street":"Pine St",
    "iso:country":"US",
    "sg:address":"1243 Pine St",
    "sg:city":"Valrico",
    "sg:classifiers":[
        {
            "category":"Real Estate",
            "subcategory":"Real Estate Agent",
            "type":"Services"
        }
    ],
    "sg:phone":"+1 813 661 8073",
    "sg:postcode":"33594",
    "sg:province":"FL",
    "sg:tags":[
        "appraiser"
    ],
    "wof:name":"Tornillo Appraisals Inc",
    "wof:placetype":"venue"
},
  "geometry": {"coordinates":[-82.225939,27.875016],"type":"Point"}
}