{
  "type": "Feature",
  "properties": {
    "addr:full":"1498 Good Homes Rd Orlando FL 32818",
    "addr:housenumber":"1498",
    "addr:postcode":"32818",
    "addr:street":"Good Homes Rd",
    "iso:country":"US",
    "sg:address":"1498 Good Homes Rd",
    "sg:city":"Orlando",
    "sg:classifiers":[
        {
            "category":"Food & Beverages",
            "subcategory":"Groceries & Convenience Stores",
            "type":"Retail Goods"
        }
    ],
    "sg:phone":"+1 407 290 6766",
    "sg:postcode":"32818",
    "sg:province":"FL",
    "wof:name":"Circle K",
    "wof:placetype":"venue"
},
  "geometry": {"coordinates":[-81.504927,28.559227],"type":"Point"}
}