{
  "type": "Feature",
  "properties": {
    "addr:full":"101 1st St SE Fort Walton Bch FL 32548",
    "addr:housenumber":"101",
    "addr:postcode":"32548",
    "addr:street":"1St St Se Fort",
    "iso:country":"US",
    "sg:address":"101 1st St SE",
    "sg:city":"Fort Walton Bch",
    "sg:classifiers":[
        {
            "category":"Organizations",
            "subcategory":"Religious Organization",
            "type":"Services"
        }
    ],
    "sg:phone":"+1 850 664 7744",
    "sg:postcode":"32548",
    "sg:province":"FL",
    "wof:name":"Evangelistic Centre",
    "wof:placetype":"venue"
},
  "geometry": {"coordinates":[-86.609649,30.405384],"type":"Point"}
}