{
  "type": "Feature",
  "properties": {
    "iso:country":"US",
    "sg:address":"4719 N Thatcher Ave",
    "sg:city":"Tampa",
    "sg:classifiers":[
        {
            "category":"Wholesale",
            "subcategory":"Furniture",
            "type":"Manufacturing & Wholesale Goods"
        }
    ],
    "sg:phone":"+1 813 673 8555",
    "sg:postcode":"33614",
    "sg:province":"FL",
    "wof:name":"Cubicle Design Inc",
    "wof:placetype":"venue"
},
  "geometry": {"coordinates":[-82.51437300000001,27.988508],"type":"Point"}
}