{
  "type": "Feature",
  "properties": {
    "addr:full":"13256 NW 12th Ct Sunrise FL 33323",
    "addr:housenumber":"13256",
    "addr:postcode":"33323",
    "addr:street":"Nw 12Th Ct",
    "iso:country":"US",
    "sg:address":"13256 NW 12th Ct",
    "sg:city":"Sunrise",
    "sg:phone":"+1 954 309 5673",
    "sg:postcode":"33323",
    "sg:province":"FL",
    "wof:name":"Karl A Robertson",
    "wof:placetype":"venue"
},
  "geometry": {"coordinates":[-80.327281,26.1374],"type":"Point"}
}