{
  "type": "Feature",
  "properties": {
    "iso:country":"US",
    "sg:address":"4501 N 42nd St",
    "sg:city":"Tampa",
    "sg:classifiers":[
        {
            "category":"Organizations",
            "subcategory":"Religious Organization",
            "type":"Services"
        }
    ],
    "sg:phone":"+1 813 663 0848",
    "sg:postcode":"33610",
    "sg:province":"FL",
    "sg:tags":[
        "church"
    ],
    "wof:name":"There Is Hope In Jesus",
    "wof:placetype":"venue"
},
  "geometry": {"coordinates":[-82.41225900000001,27.986725],"type":"Point"}
}