{
  "type": "Feature",
  "properties": {
    "iso:country":"US",
    "sg:address":"201 N Riverside Dr Ste C",
    "sg:city":"Indialantic",
    "sg:classifiers":[
        {
            "category":"Professional",
            "type":"Services"
        },
        {
            "category":"Professional",
            "subcategory":"Advertising",
            "type":"Services"
        },
        {
            "category":"Retail",
            "subcategory":"Event Space",
            "type":"Services"
        },
        {
            "category":"Recreation",
            "type":"Entertainment"
        }
    ],
    "sg:phone":"+1 321 722 9391",
    "sg:postcode":"32903",
    "sg:province":"FL",
    "sg:tags":[
        "product",
        "fair",
        "business",
        "trade",
        "planning",
        "exposition",
        "entertainers-family",
        "advertising-promotional",
        "meeting",
        "shows"
    ],
    "wof:name":"Asa Entertainment",
    "wof:placetype":"venue"
},
  "geometry": {"coordinates":[-80.57540899999999,28.089872],"type":"Point"}
}