{
  "type": "Feature",
  "properties": {
    "iso:country":"US",
    "sg:address":"500 S Highland Ave",
    "sg:city":"Apopka",
    "sg:classifiers":[
        {
            "category":"Organizations",
            "subcategory":"Religious Organization",
            "type":"Services"
        }
    ],
    "sg:phone":"+1 407 886 5943",
    "sg:postcode":"32703",
    "sg:province":"FL",
    "sg:tags":[
        "church"
    ],
    "wof:name":"First Presbyterian Church Inc",
    "wof:placetype":"venue"
},
  "geometry": {"coordinates":[-81.505394,28.670575],"type":"Point"}
}