{
  "type": "Feature",
  "properties": {
    "iso:country":"US",
    "sg:address":"8250 W Flagler St Ste 112",
    "sg:city":"Miami",
    "sg:classifiers":[
        {
            "category":"Retail",
            "subcategory":"Event Space",
            "type":"Services"
        }
    ],
    "sg:phone":"+1 305 551 0808",
    "sg:postcode":"33144",
    "sg:province":"FL",
    "sg:tags":[
        "venue"
    ],
    "sg:website":"www.dclassbanquethall.com",
    "wof:name":"D' Class Banquet Hall",
    "wof:placetype":"venue"
},
  "geometry": {"coordinates":[-80.329353,25.769651],"type":"Point"}
}