{
  "type": "Feature",
  "properties": {
    "addr:full":"4731 9th Pl Vero Beach FL 32966",
    "addr:housenumber":"4731",
    "addr:postcode":"32966",
    "addr:street":"9Th Pl",
    "iso:country":"US",
    "sg:address":"4731 9th Pl",
    "sg:city":"Vero Beach",
    "sg:classifiers":[
        {
            "category":"Wholesale",
            "subcategory":"Durable Goods & Equipment",
            "type":"Manufacturing & Wholesale Goods"
        }
    ],
    "sg:phone":"+1 772 778 3900",
    "sg:postcode":"32966",
    "sg:province":"FL",
    "sg:tags":[
        "representative",
        "manufacturer"
    ],
    "wof:name":"Skor",
    "wof:placetype":"venue"
},
  "geometry": {"coordinates":[-80.434804,27.618689],"type":"Point"}
}