{
  "type": "Feature",
  "properties": {
    "addr:full":"1314 Shelby Pkwy Cape Coral FL 33904",
    "addr:housenumber":"1314",
    "addr:postcode":"33904",
    "addr:street":"Shelby Pkwy",
    "iso:country":"US",
    "sg:address":"1314 Shelby Pkwy",
    "sg:city":"Cape Coral",
    "sg:classifiers":[
        {
            "category":"Organizations",
            "subcategory":"Community Association",
            "type":"Services"
        }
    ],
    "sg:phone":"+1 239 574 6632",
    "sg:postcode":"33904",
    "sg:province":"FL",
    "wof:name":"Order of White Shrine",
    "wof:placetype":"venue"
},
  "geometry": {"coordinates":[-81.94278,26.600674],"type":"Point"}
}