{
  "type": "Feature",
  "properties": {
    "iso:country":"US",
    "sg:address":"8141 Gandy Way",
    "sg:city":"Orlando",
    "sg:classifiers":[
        {
            "category":"Autos & Motor Vehicles",
            "subcategory":"Automobile Sales",
            "type":"Retail Goods"
        }
    ],
    "sg:phone":"+1 407 293 0423",
    "sg:postcode":"32810",
    "sg:province":"FL",
    "sg:tags":[
        "used"
    ],
    "wof:name":"Leader Motors",
    "wof:placetype":"venue"
},
  "geometry": {"coordinates":[-81.430204,28.630203],"type":"Point"}
}