{
  "type": "Feature",
  "properties": {
    "iso:country":"US",
    "sg:address":"115 Michigan Ave",
    "sg:city":"Daytona Beach",
    "sg:classifiers":[
        {
            "category":"Retail",
            "subcategory":"Auto Repair",
            "type":"Services"
        }
    ],
    "sg:phone":"+1 386 255 1886",
    "sg:postcode":"32114",
    "sg:province":"FL",
    "sg:tags":[
        "repairing",
        "automobile"
    ],
    "wof:name":"Dan's Auto Svc",
    "wof:placetype":"venue"
},
  "geometry": {"coordinates":[-81.02382900000001,29.22033],"type":"Point"}
}