{
  "type": "Feature",
  "properties": {
    "iso:country":"US",
    "sg:address":"100 Dresdan Ct",
    "sg:city":"Sanford",
    "sg:classifiers":[
        {
            "category":"Building & Trades",
            "subcategory":"Construction",
            "type":"Services"
        }
    ],
    "sg:phone":"+1 407 324 2173",
    "sg:postcode":"32771",
    "sg:province":"FL",
    "sg:tags":[
        "contractor"
    ],
    "wof:name":"Design Tile Co",
    "wof:placetype":"venue"
},
  "geometry": {"coordinates":[-81.32387300000001,28.790395],"type":"Point"}
}