{
  "type": "Feature",
  "properties": {
    "addr:full":"9922 Nicoma Ln Orlando FL 32817",
    "addr:housenumber":"9922",
    "addr:postcode":"32817",
    "addr:street":"Nicoma Ln",
    "iso:country":"US",
    "sg:address":"9922 Nicoma Ln",
    "sg:city":"Orlando",
    "sg:classifiers":[
        {
            "category":"Building & Trades",
            "subcategory":"Construction",
            "type":"Services"
        }
    ],
    "sg:phone":"+1 407 678 4126",
    "sg:postcode":"32817",
    "sg:province":"FL",
    "sg:tags":[
        "hanging",
        "contractor"
    ],
    "wof:name":"Bob Hester Painting",
    "wof:placetype":"venue"
},
  "geometry": {"coordinates":[-81.246002,28.584761],"type":"Point"}
}