{
  "type": "Feature",
  "properties": {
    "iso:country":"US",
    "sg:address":"1302 Timberlane Rd",
    "sg:city":"Tallahassee",
    "sg:classifiers":[
        {
            "category":"Real Estate",
            "subcategory":"Real Estate Agent",
            "type":"Services"
        }
    ],
    "sg:phone":"+1 850 894 1212",
    "sg:postcode":"32312",
    "sg:province":"FL",
    "sg:tags":[
        "appraiser"
    ],
    "wof:name":"Schrader & Assoc",
    "wof:placetype":"venue"
},
  "geometry": {"coordinates":[-84.258561,30.503704],"type":"Point"}
}