{
  "type": "Feature",
  "properties": {
    "iso:country":"US",
    "sg:address":"2655 E 8th Ave",
    "sg:city":"Hialeah",
    "sg:classifiers":[
        {
            "category":"Professional",
            "subcategory":"Management & Consulting",
            "type":"Services"
        }
    ],
    "sg:phone":"+1 305 648 4300",
    "sg:postcode":"33013",
    "sg:province":"FL",
    "sg:tags":[
        "agricultural",
        "consultant"
    ],
    "wof:name":"Bunge",
    "wof:placetype":"venue"
},
  "geometry": {"coordinates":[-80.266192,25.846673],"type":"Point"}
}