{
  "type": "Feature",
  "properties": {
    "iso:country":"US",
    "sg:address":"1601 Sunset Dr",
    "sg:city":"Sebring",
    "sg:classifiers":[
        {
            "category":"Shopping",
            "type":"Retail Goods"
        }
    ],
    "sg:phone":"+1 863 385 7803",
    "sg:postcode":"33870",
    "sg:province":"FL",
    "sg:tags":[
        "merchandise",
        "animal"
    ],
    "wof:name":"Affordable Pet Supplies",
    "wof:placetype":"venue"
},
  "geometry": {"coordinates":[-81.48207600000001,27.51639],"type":"Point"}
}