{
  "type": "Feature",
  "properties": {
    "iso:country":"US",
    "sg:address":"7300 Ocean Terrace",
    "sg:city":"Miami Beach",
    "sg:classifiers":[
        {
            "category":"Restaurant",
            "type":"Food & Drink"
        }
    ],
    "sg:phone":"+1 305 397 8261",
    "sg:postcode":"33141",
    "sg:province":"FL",
    "sg:tags":[
        "thai"
    ],
    "wof:name":"Le Banyan",
    "wof:placetype":"venue"
},
  "geometry": {"coordinates":[-80.120116,25.858647],"type":"Point"}
}