{
  "type": "Feature",
  "properties": {
    "addr:full":"1806 N Howard Ave Tampa FL 33607",
    "addr:housenumber":"1806",
    "addr:postcode":"33607",
    "addr:street":"N Howard Ave",
    "iso:country":"US",
    "sg:address":"1806 N Howard Ave",
    "sg:city":"Tampa",
    "sg:classifiers":[
        {
            "category":"Organizations",
            "subcategory":"Religious Organization",
            "type":"Services"
        }
    ],
    "sg:phone":"+1 813 254 7857",
    "sg:postcode":"33607",
    "sg:province":"FL",
    "sg:tags":[
        "church"
    ],
    "wof:name":"Bible Day Church Of America",
    "wof:placetype":"venue"
},
  "geometry": {"coordinates":[-82.48296999999999,27.958577],"type":"Point"}
}