{
  "type": "Feature",
  "properties": {
    "iso:country":"US",
    "sg:address":"410 County Line Rd W",
    "sg:city":"Lutz",
    "sg:classifiers":[
        {
            "category":"Place Of Worship",
            "subcategory":"Church",
            "type":"Public Place"
        },
        {
            "category":"Place Of Worship",
            "type":"Public Place"
        },
        {
            "category":"Organizations",
            "subcategory":"Religious Organization",
            "type":"Services"
        }
    ],
    "sg:phone":"+1 813 949 1912",
    "sg:postcode":"33548",
    "sg:province":"FL",
    "sg:tags":[
        "god",
        "god-independent",
        "churches-assemblies"
    ],
    "wof:name":"Assembly Of God",
    "wof:placetype":"venue"
},
  "geometry": {"coordinates":[-82.46358499999999,28.171841],"type":"Point"}
}