{
  "type": "Feature",
  "properties": {
    "addr:full":"2705 Shawnee Way Jacksonville FL 32259",
    "addr:housenumber":"2705",
    "addr:postcode":"32259",
    "addr:street":"Shawnee Way",
    "iso:country":"US",
    "sg:address":"2705 Shawnee Way",
    "sg:city":"Jacksonville",
    "sg:classifiers":[
        {
            "category":"Utilities",
            "subcategory":"Telephone",
            "type":"Services"
        }
    ],
    "sg:phone":"+1 904 287 0069",
    "sg:postcode":"32259",
    "sg:province":"FL",
    "sg:tags":[
        "communication"
    ],
    "wof:name":"Sprint",
    "wof:placetype":"venue"
},
  "geometry": {"coordinates":[-81.547128,30.057051],"type":"Point"}
}