{
  "type": "Feature",
  "properties": {
    "iso:country":"US",
    "sg:address":"7162 SW 47th St",
    "sg:city":"Miami",
    "sg:classifiers":[
        {
            "category":"Communications",
            "subcategory":"Film & Video Production",
            "type":"Services"
        }
    ],
    "sg:phone":"+1 305 662 3919",
    "sg:postcode":"33155",
    "sg:province":"FL",
    "sg:tags":[
        "motion",
        "business",
        "audio-visual"
    ],
    "sg:website":"http://www.sonic3.com",
    "wof:name":"Sonic III Inc",
    "wof:placetype":"venue"
},
  "geometry": {"coordinates":[-80.30916499999999,25.726416],"type":"Point"}
}