{
  "type": "Feature",
  "properties": {
    "addr:full":"659 Florida Central Pkwy Longwood FL 32750",
    "addr:housenumber":"659",
    "addr:postcode":"32750",
    "addr:street":"Florida Central Pkwy",
    "iso:country":"US",
    "sg:address":"659 Florida Central Pkwy",
    "sg:city":"Longwood",
    "sg:classifiers":[
        {
            "category":"Professional",
            "subcategory":"Detective & Security Services",
            "type":"Services"
        },
        {
            "category":"Government",
            "subcategory":"Fire Station",
            "type":"Public Place"
        },
        {
            "category":"Wholesale",
            "subcategory":"Machinery & Supplies",
            "type":"Manufacturing & Wholesale Goods"
        },
        {
            "category":"Building & Trades",
            "subcategory":"Electrical",
            "type":"Services"
        }
    ],
    "sg:phone":"+1 407 260 6444",
    "sg:postcode":"32750",
    "sg:province":"FL",
    "sg:tags":[
        "control",
        "monitoring",
        "alarm",
        "system",
        "equipment",
        "protection",
        "servicing",
        "smoke",
        "department",
        "detector",
        "equipment-repairing"
    ],
    "wof:name":"Siemens Fire Safety",
    "wof:placetype":"venue"
},
  "geometry": {"coordinates":[-81.352755,28.693286],"type":"Point"}
}