{
  "type": "Feature",
  "properties": {
    "iso:country":"US",
    "sg:address":"3801 NW 92nd Ave",
    "sg:city":"Hollywood",
    "sg:classifiers":[
        {
            "category":"Autos & Motor Vehicles",
            "subcategory":"Automobile Sales",
            "type":"Retail Goods"
        }
    ],
    "sg:phone":"+1 954 499 8755",
    "sg:postcode":"33024",
    "sg:province":"FL",
    "sg:tags":[
        "equipment",
        "aircraft",
        "parts",
        "supply"
    ],
    "wof:name":"Aircraft Surplus Inc",
    "wof:placetype":"venue"
},
  "geometry": {"coordinates":[-80.27098100000001,26.043994],"type":"Point"}
}