{
  "type": "Feature",
  "properties": {
    "addr:full":"3121 Mobile Hwy Pensacola FL 32505",
    "addr:housenumber":"3121",
    "addr:postcode":"32505",
    "addr:street":"Mobile Hwy",
    "iso:country":"US",
    "sg:address":"3121 Mobile Hwy",
    "sg:city":"Pensacola",
    "sg:classifiers":[
        {
            "category":"Personal",
            "subcategory":"Beauty Salon",
            "type":"Services"
        }
    ],
    "sg:phone":"+1 850 470 9977",
    "sg:postcode":"32505",
    "sg:province":"FL",
    "sg:tags":[
        "shop"
    ],
    "wof:name":"Rose Alteration & Rosies Nail",
    "wof:placetype":"venue"
},
  "geometry": {"coordinates":[-87.253345,30.421949],"type":"Point"}
}