{
  "type": "Feature",
  "properties": {
    "iso:country":"US",
    "sg:address":"815 S Volusia Ave",
    "sg:city":"Orange City",
    "sg:classifiers":[
        {
            "category":"Banks & Credit Unions",
            "subcategory":"Bank",
            "type":"Services"
        }
    ],
    "sg:phone":"+1 386 775 2002",
    "sg:postcode":"32763",
    "sg:province":"FL",
    "sg:tags":[
        "loan"
    ],
    "wof:name":"Vanessa Little USA",
    "wof:placetype":"venue"
},
  "geometry": {"coordinates":[-81.29895399999999,28.94093],"type":"Point"}
}