{
  "type": "Feature",
  "properties": {
    "addr:full":"7370 College Pkwy Fort Myers FL 33907",
    "addr:housenumber":"7370",
    "addr:postcode":"33907",
    "addr:street":"College Pkwy",
    "iso:country":"US",
    "sg:address":"7370 College Pkwy",
    "sg:city":"Fort Myers",
    "sg:classifiers":[
        {
            "category":"Professional",
            "subcategory":"Engineering",
            "type":"Services"
        }
    ],
    "sg:phone":"+1 239 275 1899",
    "sg:postcode":"33907",
    "sg:province":"FL",
    "sg:tags":[
        "engineer"
    ],
    "wof:name":"Speath Engineering",
    "wof:placetype":"venue"
},
  "geometry": {"coordinates":[-81.87503100000001,26.556435],"type":"Point"}
}