{
  "type": "Feature",
  "properties": {
    "addr:full":"1975 S Ferdon Blvd Crestview FL 32536",
    "addr:housenumber":"1975",
    "addr:postcode":"32536",
    "addr:street":"S Ferdon Blvd",
    "iso:country":"US",
    "sg:address":"1975 S Ferdon Blvd",
    "sg:city":"Crestview",
    "sg:classifiers":[
        {
            "category":"Shopping",
            "subcategory":"Used Merchandise",
            "type":"Retail Goods"
        }
    ],
    "sg:phone":"+1 850 689 2700",
    "sg:postcode":"32536",
    "sg:province":"FL",
    "sg:tags":[
        "shop",
        "thrift"
    ],
    "sg:website":"www.waterfrontmission.org",
    "wof:name":"Waterfront Mission Bargain Str",
    "wof:placetype":"venue"
},
  "geometry": {"coordinates":[-86.564487,30.739148],"type":"Point"}
}