{
  "type": "Feature",
  "properties": {
    "addr:full":"4614 SW 22nd Ave Cape Coral FL 33914",
    "addr:housenumber":"4614",
    "addr:postcode":"33914",
    "addr:street":"Sw 22Nd Ave",
    "iso:country":"US",
    "sg:address":"4614 SW 22nd Ave",
    "sg:city":"Cape Coral",
    "sg:classifiers":[
        {
            "category":"Building & Trades",
            "subcategory":"Construction",
            "type":"Services"
        }
    ],
    "sg:phone":"+1 239 540 8171",
    "sg:postcode":"33914",
    "sg:province":"FL",
    "sg:tags":[
        "concrete",
        "contractor"
    ],
    "wof:name":"McKibben Concrete Solutions",
    "wof:placetype":"venue"
},
  "geometry": {"coordinates":[-82.019744,26.566215],"type":"Point"}
}