{
  "type": "Feature",
  "properties": {
    "iso:country":"US",
    "sg:address":"5106 State Rd 54",
    "sg:city":"New Port Richey",
    "sg:classifiers":[
        {
            "category":"Autos & Motor Vehicles",
            "subcategory":"Automobile Sales",
            "type":"Retail Goods"
        }
    ],
    "sg:phone":"+1 727 849 4486",
    "sg:postcode":"34652",
    "sg:province":"FL",
    "sg:tags":[
        "car",
        "dealer"
    ],
    "wof:name":"Auto Arcade Inc",
    "wof:placetype":"venue"
},
  "geometry": {"coordinates":[-82.729921,28.216894],"type":"Point"}
}