{
  "type": "Feature",
  "properties": {
    "iso:country":"US",
    "sg:address":"324 SW 12th Ave Ste A",
    "sg:city":"Miami",
    "sg:classifiers":[
        {
            "category":"Retail",
            "subcategory":"Repair Shop",
            "type":"Services"
        },
        {
            "category":"Professional",
            "subcategory":"Detective & Security Services",
            "type":"Services"
        }
    ],
    "sg:phone":"+1 305 643 3220",
    "sg:postcode":"33130",
    "sg:province":"FL",
    "sg:tags":[
        "skip",
        "tracing",
        "bail",
        "bond"
    ],
    "wof:name":"24 7 Bail Bonds Inc",
    "wof:placetype":"venue"
},
  "geometry": {"coordinates":[-80.21455400000001,25.770343],"type":"Point"}
}