{
  "type": "Feature",
  "properties": {
    "addr:full":"7423 US Hwy 301 Riverview FL 33569",
    "addr:housenumber":"7423",
    "addr:postcode":"33569",
    "addr:street":"Us Hwy 301",
    "iso:country":"US",
    "sg:address":"7423 US Hwy 301",
    "sg:city":"Riverview",
    "sg:classifiers":[
        {
            "category":"Professional",
            "subcategory":"Management & Consulting",
            "type":"Services"
        }
    ],
    "sg:phone":"+1 813 677 6004",
    "sg:postcode":"33569",
    "sg:province":"FL",
    "sg:tags":[
        "consultant",
        "business"
    ],
    "wof:name":"Freight Management Svc",
    "wof:placetype":"venue"
},
  "geometry": {"coordinates":[-82.326787,27.876939],"type":"Point"}
}