{
  "type": "Feature",
  "properties": {
    "addr:full":"736 US Hwy 29 Cantonment FL 32533",
    "addr:housenumber":"736",
    "addr:postcode":"32533",
    "addr:street":"Us Hwy 29",
    "iso:country":"US",
    "sg:address":"736 US Hwy 29",
    "sg:city":"Cantonment",
    "sg:classifiers":[
        {
            "category":"Food & Beverages",
            "subcategory":"Groceries & Convenience Stores",
            "type":"Retail Goods"
        }
    ],
    "sg:phone":"+1 850 968 0822",
    "sg:postcode":"32533",
    "sg:province":"FL",
    "wof:name":"Greers 20",
    "wof:placetype":"venue"
},
  "geometry": {"coordinates":[-87.326353,30.620733],"type":"Point"}
}