{
  "type": "Feature",
  "properties": {
    "iso:country":"US",
    "sg:address":"1850 Greenwich Ave",
    "sg:city":"Winter Park",
    "sg:classifiers":[
        {
            "category":"Health Services",
            "subcategory":"Optometrist",
            "type":"Services"
        },
        {
            "category":"Shopping",
            "subcategory":"Optician",
            "type":"Retail Goods"
        }
    ],
    "sg:phone":"+1 407 647 7227",
    "sg:postcode":"32789",
    "sg:province":"FL",
    "sg:tags":[
        "ophthalmologist",
        "eyewear"
    ],
    "wof:name":"Contact Lens Replacement Center",
    "wof:placetype":"venue"
},
  "geometry": {"coordinates":[-81.3283,28.597799],"type":"Point"}
}