{
  "type": "Feature",
  "properties": {
    "iso:country":"US",
    "sg:address":"3220 Whitfield Ave",
    "sg:city":"Sarasota",
    "sg:classifiers":[
        {
            "category":"Building & Trades",
            "subcategory":"Landscaping Services",
            "type":"Services"
        }
    ],
    "sg:phone":"+1 941 351 2864",
    "sg:postcode":"34243",
    "sg:province":"FL",
    "sg:tags":[
        "plant",
        "indoor",
        "leasing",
        "maintenance"
    ],
    "wof:name":"Tropex",
    "wof:placetype":"venue"
},
  "geometry": {"coordinates":[-82.521072,27.418001],"type":"Point"}
}