{
  "type": "Feature",
  "properties": {
    "addr:full":"745 Greensward Ct Delray Beach FL 33445",
    "addr:housenumber":"745",
    "addr:postcode":"33445",
    "addr:street":"Greensward Ct",
    "iso:country":"US",
    "sg:address":"745 Greensward Ct",
    "sg:city":"Delray Beach",
    "sg:classifiers":[
        {
            "category":"Organizations",
            "subcategory":"Community Association",
            "type":"Services"
        }
    ],
    "sg:phone":"+1 561 498 8538",
    "sg:postcode":"33445",
    "sg:province":"FL",
    "sg:tags":[
        "real estate"
    ],
    "wof:name":"Greensward Vlg One Condo Assn",
    "wof:placetype":"venue"
},
  "geometry": {"coordinates":[-80.110173,26.448126],"type":"Point"}
}