{
  "type": "Feature",
  "properties": {
    "iso:country":"US",
    "sg:address":"2029 NW 87th Ave",
    "sg:city":"Doral",
    "sg:classifiers":[
        {
            "category":"Professional",
            "subcategory":"Management & Consulting",
            "type":"Services"
        },
        {
            "category":"Health Services",
            "subcategory":"Doctor",
            "type":"Services"
        }
    ],
    "sg:phone":"+1 305 269 1515",
    "sg:postcode":"33172",
    "sg:province":"FL",
    "sg:tags":[
        "marketing",
        "clinic"
    ],
    "wof:name":"Medicard Inc",
    "wof:placetype":"venue"
},
  "geometry": {"coordinates":[-80.33676199999999,25.792274],"type":"Point"}
}