{
  "type": "Feature",
  "properties": {
    "iso:country":"US",
    "sg:address":"224 S Dixie Hwy",
    "sg:city":"Hallandale Beach",
    "sg:classifiers":[
        {
            "category":"Building & Trades",
            "subcategory":"Construction",
            "type":"Services"
        }
    ],
    "sg:phone":"+1 954 454 6430",
    "sg:postcode":"33009",
    "sg:province":"FL",
    "sg:tags":[
        "general",
        "contractor"
    ],
    "wof:name":"Shanco Construction",
    "wof:placetype":"venue"
},
  "geometry": {"coordinates":[-80.14837,25.982176],"type":"Point"}
}