{
  "type": "Feature",
  "properties": {
    "addr:full":"8500 SW 8th St Ste 228 Miami FL 33144",
    "addr:housenumber":"8500",
    "addr:postcode":"33144",
    "addr:street":"Sw 8Th St Ste 228",
    "iso:country":"US",
    "sg:address":"8500 SW 8th St Ste 228",
    "sg:city":"Miami",
    "sg:classifiers":[
        {
            "category":"Real Estate",
            "subcategory":"Real Estate Services",
            "type":"Services"
        },
        {
            "category":"Real Estate",
            "subcategory":"Real Estate Operator",
            "type":"Services"
        }
    ],
    "sg:phone":"+1 305 262 6533",
    "sg:postcode":"33144",
    "sg:province":"FL",
    "sg:tags":[
        "apartment"
    ],
    "wof:name":"General Real Estate",
    "wof:placetype":"venue"
},
  "geometry": {"coordinates":[-80.332802,25.7619],"type":"Point"}
}