{
  "type": "Feature",
  "properties": {
    "iso:country":"US",
    "sg:address":"8901 Warrior Way",
    "sg:city":"Hudson",
    "sg:classifiers":[
        {
            "category":"Health Services",
            "subcategory":"Clinic",
            "type":"Services"
        }
    ],
    "sg:phone":"+1 727 862 7055",
    "sg:postcode":"34667",
    "sg:province":"FL",
    "sg:tags":[
        "home"
    ],
    "wof:name":"Senior Home Care Options",
    "wof:placetype":"venue"
},
  "geometry": {"coordinates":[-82.666871,28.352144],"type":"Point"}
}