{
  "type": "Feature",
  "properties": {
    "iso:country":"US",
    "sg:address":"1285 16th St",
    "sg:city":"Vero Beach",
    "sg:classifiers":[
        {
            "category":"Shopping",
            "subcategory":"Florist",
            "type":"Retail Goods"
        }
    ],
    "sg:phone":"+1 772 567 8271",
    "sg:postcode":"32960",
    "sg:province":"FL",
    "wof:name":"Flower World Florist",
    "wof:placetype":"venue"
},
  "geometry": {"coordinates":[-80.396607,27.631552],"type":"Point"}
}