{
  "type": "Feature",
  "properties": {
    "iso:country":"US",
    "sg:address":"9288 Barney Broxson Rd",
    "sg:city":"Milton",
    "sg:classifiers":[
        {
            "category":"Building & Trades",
            "subcategory":"Construction",
            "type":"Services"
        }
    ],
    "sg:phone":"+1 850 623 8961",
    "sg:postcode":"32583",
    "sg:province":"FL",
    "sg:tags":[
        "carpenter"
    ],
    "sg:website":"http://www.shelbycountybuilders.com",
    "wof:name":"Shelby Custom Cabinets",
    "wof:placetype":"venue"
},
  "geometry": {"coordinates":[-86.935413,30.587914],"type":"Point"}
}