{
  "type": "Feature",
  "properties": {
    "addr:full":"201 S Orange Ave Orlando FL 32801",
    "addr:housenumber":"201",
    "addr:postcode":"32801",
    "addr:street":"S Orange Ave",
    "iso:country":"US",
    "sg:address":"201 S Orange Ave",
    "sg:city":"Orlando",
    "sg:classifiers":[
        {
            "category":"Banks & Credit Unions",
            "subcategory":"Bank",
            "type":"Services"
        }
    ],
    "sg:phone":"+1 407 567 2200",
    "sg:postcode":"32801",
    "sg:province":"FL",
    "sg:tags":[
        "saving",
        "commercial"
    ],
    "wof:name":"Seaside National Bank & Trust",
    "wof:placetype":"venue"
},
  "geometry": {"coordinates":[-81.37902099999999,28.54034],"type":"Point"}
}