{
  "type": "Feature",
  "properties": {
    "iso:country":"US",
    "sg:address":"1365 S Railroad Ave",
    "sg:city":"Chipley",
    "sg:classifiers":[
        {
            "category":"Shopping",
            "subcategory":"Used Merchandise",
            "type":"Retail Goods"
        }
    ],
    "sg:phone":"+1 850 638 9443",
    "sg:postcode":"32428",
    "sg:province":"FL",
    "wof:name":"Antique Market Place",
    "wof:placetype":"venue"
},
  "geometry": {"coordinates":[-85.543099,30.780025],"type":"Point"}
}