{
  "type": "Feature",
  "properties": {
    "iso:country":"US",
    "sg:address":"915 SE 14th St",
    "sg:city":"Cape Coral",
    "sg:classifiers":[
        {
            "category":"Manufacturing",
            "subcategory":"Building Materials",
            "type":"Manufacturing & Wholesale Goods"
        }
    ],
    "sg:phone":"+1 239 573 4700",
    "sg:postcode":"33990",
    "sg:province":"FL",
    "sg:tags":[
        "mfg",
        "wood",
        "kitchen",
        "cabinet"
    ],
    "wof:name":"Lifestyle Cabinetry",
    "wof:placetype":"venue"
},
  "geometry": {"coordinates":[-81.954553,26.626719],"type":"Point"}
}