{
  "type": "Feature",
  "properties": {
    "iso:country":"US",
    "sg:address":"13117 SE 38th Ct",
    "sg:city":"Belleview",
    "sg:classifiers":[
        {
            "category":"Personal",
            "subcategory":"Adult",
            "type":"Services"
        }
    ],
    "sg:phone":"+1 352 245 5129",
    "sg:postcode":"34420",
    "sg:province":"FL",
    "sg:tags":[
        "escort"
    ],
    "wof:name":"Linda D Poulston Escort",
    "wof:placetype":"venue"
},
  "geometry": {"coordinates":[-82.083214,29.031584],"type":"Point"}
}