{
  "type": "Feature",
  "properties": {
    "addr:full":"2100 Hollywood Blvd Hollywood FL 33020",
    "addr:housenumber":"2100",
    "addr:postcode":"33020",
    "addr:street":"Hollywood Blvd",
    "iso:country":"US",
    "sg:address":"2100 Hollywood Blvd",
    "sg:city":"Hollywood",
    "sg:classifiers":[
        {
            "category":"Bars & Pubs",
            "type":"Food & Drink"
        }
    ],
    "sg:phone":"+1 954 923 9255",
    "sg:postcode":"33020",
    "sg:province":"FL",
    "sg:tags":[
        "drinking"
    ],
    "wof:name":"Club 2100",
    "wof:placetype":"venue"
},
  "geometry": {"coordinates":[-80.15096200000001,26.011367],"type":"Point"}
}