{
  "type": "Feature",
  "properties": {
    "iso:country":"US",
    "sg:address":"1618 Periwinkle Way",
    "sg:city":"Sanibel",
    "sg:classifiers":[
        {
            "category":"Home & Garden",
            "subcategory":"Furniture",
            "type":"Retail Goods"
        }
    ],
    "sg:phone":"+1 239 472 5552",
    "sg:postcode":"33957",
    "sg:province":"FL",
    "sg:tags":[
        "store"
    ],
    "sg:website":"http://www.sanibelhomefurnishings.com",
    "wof:name":"Sanibel Home Furnishings",
    "wof:placetype":"venue"
},
  "geometry": {"coordinates":[-82.056478,26.442107],"type":"Point"}
}