{
  "type": "Feature",
  "properties": {
    "iso:country":"US",
    "sg:address":"10441 Orange Dr",
    "sg:city":"Davie",
    "sg:classifiers":[
        {
            "category":"Retail",
            "subcategory":"Veterinary Services",
            "type":"Services"
        }
    ],
    "sg:phone":"+1 954 473 0842",
    "sg:postcode":"33328",
    "sg:province":"FL",
    "sg:tags":[
        "veterinarian"
    ],
    "wof:name":"Pet Emergency Center",
    "wof:placetype":"venue"
},
  "geometry": {"coordinates":[-80.26032600000001,26.065189],"type":"Point"}
}