{
  "type": "Feature",
  "properties": {
    "iso:country":"US",
    "sg:address":"2701 E Colonial Dr",
    "sg:city":"Orlando",
    "sg:classifiers":[
        {
            "category":"Restaurant",
            "type":"Food & Drink"
        }
    ],
    "sg:menulink":"http://www.allmenus.com/fl/orlando/187528-mcdonalds/menu/",
    "sg:phone":"+1 407 898 6879",
    "sg:postcode":"32803",
    "sg:province":"FL",
    "sg:tags":[
        "burger",
        "american"
    ],
    "wof:name":"McDonald's",
    "wof:placetype":"venue"
},
  "geometry": {"coordinates":[-81.34875,28.553794],"type":"Point"}
}