{
  "type": "Feature",
  "properties": {
    "addr:full":"301 Palm Ct Indialantic FL 32903",
    "addr:housenumber":"301",
    "addr:postcode":"32903",
    "addr:street":"Palm Ct",
    "iso:country":"US",
    "sg:address":"301 Palm Ct",
    "sg:city":"Indialantic",
    "sg:classifiers":[
        {
            "category":"Personal",
            "type":"Services"
        }
    ],
    "sg:phone":"+1 321 727 8866",
    "sg:postcode":"32903",
    "sg:province":"FL",
    "sg:tags":[
        "therapist",
        "massage"
    ],
    "wof:name":"Hollis Larosa Massage & Skin",
    "wof:placetype":"venue"
},
  "geometry": {"coordinates":[-80.57046699999999,28.085616],"type":"Point"}
}