{
  "type": "Feature",
  "properties": {
    "addr:full":"10651 NW 44th St Pompano Beach FL 33065",
    "addr:housenumber":"10651",
    "addr:postcode":"33065",
    "addr:street":"Nw 44Th St",
    "iso:country":"US",
    "sg:address":"10651 NW 44th St",
    "sg:city":"Pompano Beach",
    "sg:classifiers":[
        {
            "category":"Building & Trades",
            "subcategory":"Construction",
            "type":"Services"
        }
    ],
    "sg:phone":"+1 954 255 1326",
    "sg:postcode":"33065",
    "sg:province":"FL",
    "sg:tags":[
        "dealer",
        "contractor"
    ],
    "wof:name":"Primetime Satelite Technology",
    "wof:placetype":"venue"
},
  "geometry": {"coordinates":[-80.269285,26.285116],"type":"Point"}
}