{
  "type": "Feature",
  "properties": {
    "addr:full":"5725 Rowan Rd New Port Richey FL 34653",
    "addr:housenumber":"5725",
    "addr:postcode":"34653",
    "addr:street":"Rowan Rd",
    "iso:country":"US",
    "sg:address":"5725 Rowan Rd",
    "sg:city":"New Port Richey",
    "sg:classifiers":[
        {
            "category":"Organizations",
            "subcategory":"Religious Organization",
            "type":"Services"
        }
    ],
    "sg:phone":"+1 727 842 2336",
    "sg:postcode":"34653",
    "sg:province":"FL",
    "sg:tags":[
        "church"
    ],
    "wof:name":"Trinity Baptist Church",
    "wof:placetype":"venue"
},
  "geometry": {"coordinates":[-82.696223,28.24461],"type":"Point"}
}