{
  "type": "Feature",
  "properties": {
    "iso:country":"US",
    "sg:address":"3909 Sunbeam Rd",
    "sg:city":"Jacksonville",
    "sg:classifiers":[
        {
            "category":"Home & Garden",
            "subcategory":"Building Materials",
            "type":"Retail Goods"
        },
        {
            "category":"Retail",
            "subcategory":"Auto Repair",
            "type":"Services"
        }
    ],
    "sg:phone":"+1 904 745 0249",
    "sg:postcode":"32257",
    "sg:province":"FL",
    "sg:tags":[
        "door",
        "general"
    ],
    "wof:name":"B & S Garage Door Svc",
    "wof:placetype":"venue"
},
  "geometry": {"coordinates":[-81.61282,30.205821],"type":"Point"}
}