{
  "type": "Feature",
  "properties": {
    "iso:country":"US",
    "sg:address":"26 Dickman Dr SE",
    "sg:city":"Ruskin",
    "sg:classifiers":[
        {
            "category":"Education",
            "subcategory":"Library",
            "type":"Public Place"
        }
    ],
    "sg:phone":"+1 813 273 3652",
    "sg:postcode":"33570",
    "sg:province":"FL",
    "sg:website":"http://www.sao13th.com",
    "wof:name":"Public Library Cooperative",
    "wof:placetype":"venue"
},
  "geometry": {"coordinates":[-82.43318600000001,27.718528],"type":"Point"}
}