{
  "type": "Feature",
  "properties": {
    "addr:full":"8163 Bruce St Sneads FL 32460",
    "addr:housenumber":"8163",
    "addr:postcode":"32460",
    "addr:street":"Bruce St",
    "iso:country":"US",
    "sg:address":"8163 Bruce St",
    "sg:city":"Sneads",
    "sg:classifiers":[
        {
            "category":"Building & Trades",
            "subcategory":"Pest Control",
            "type":"Services"
        }
    ],
    "sg:phone":"+1 850 593 5656",
    "sg:postcode":"32460",
    "sg:province":"FL",
    "wof:name":"H & H Pest Control",
    "wof:placetype":"venue"
},
  "geometry": {"coordinates":[-84.91330600000001,30.714845],"type":"Point"}
}