{
  "type": "Feature",
  "properties": {
    "iso:country":"US",
    "sg:address":"1420 SE 16th St",
    "sg:city":"Cape Coral",
    "sg:classifiers":[
        {
            "category":"Building & Trades",
            "subcategory":"Construction",
            "type":"Services"
        }
    ],
    "sg:phone":"+1 239 574 6564",
    "sg:postcode":"33990",
    "sg:province":"FL",
    "sg:tags":[
        "roofing",
        "contractor"
    ],
    "wof:name":"Day Brothers Roofing",
    "wof:placetype":"venue"
},
  "geometry": {"coordinates":[-81.94549000000001,26.622934],"type":"Point"}
}