{
  "type": "Feature",
  "properties": {
    "addr:full":"11602 NW 7th Ave Miami FL 33168",
    "addr:housenumber":"11602",
    "addr:postcode":"33168",
    "addr:street":"Nw 7Th Ave",
    "iso:country":"US",
    "sg:address":"11602 NW 7th Ave",
    "sg:city":"Miami",
    "sg:classifiers":[
        {
            "category":"Personal",
            "subcategory":"Barber",
            "type":"Services"
        }
    ],
    "sg:phone":"+1 305 687 4555",
    "sg:postcode":"33168",
    "sg:province":"FL",
    "sg:tags":[
        "shop"
    ],
    "wof:name":"G Q Barber Shop",
    "wof:placetype":"venue"
},
  "geometry": {"coordinates":[-80.210553,25.88151],"type":"Point"}
}