{
  "type": "Feature",
  "properties": {
    "addr:full":"20585 SW 1st St Hollywood FL 33029",
    "addr:housenumber":"20585",
    "addr:postcode":"33029",
    "addr:street":"Sw 1St St",
    "iso:country":"US",
    "sg:address":"20585 SW 1st St",
    "sg:city":"Hollywood",
    "sg:classifiers":[
        {
            "category":"Shopping",
            "subcategory":"Shoes",
            "type":"Retail Goods"
        }
    ],
    "sg:phone":"+1 954 437 3832",
    "sg:postcode":"33029",
    "sg:province":"FL",
    "wof:name":"Hdc International",
    "wof:placetype":"venue"
},
  "geometry": {"coordinates":[-80.42108899999999,26.006877],"type":"Point"}
}