{
  "type": "Feature",
  "properties": {
    "iso:country":"US",
    "sg:address":"930 S Harbor City Blvd",
    "sg:city":"Melbourne",
    "sg:classifiers":[
        {
            "category":"Banks & Credit Unions",
            "subcategory":"Bank",
            "type":"Services"
        }
    ],
    "sg:phone":"+1 321 952 1115",
    "sg:postcode":"32901",
    "sg:province":"FL",
    "sg:tags":[
        "loan",
        "real estate"
    ],
    "wof:name":"Countrywide Home Loans",
    "wof:placetype":"venue"
},
  "geometry": {"coordinates":[-80.61211400000001,28.09811],"type":"Point"}
}