{
  "type": "Feature",
  "properties": {
    "addr:full":"2320 1st St Fort Myers FL 33901",
    "addr:housenumber":"2320",
    "addr:postcode":"33901",
    "addr:street":"1St St",
    "iso:country":"US",
    "sg:address":"2320 1st St",
    "sg:city":"Fort Myers",
    "sg:classifiers":[
        {
            "category":"Professional",
            "type":"Services"
        }
    ],
    "sg:phone":"+1 239 226 1009",
    "sg:postcode":"33901",
    "sg:province":"FL",
    "sg:tags":[
        "establishment"
    ],
    "wof:name":"Economou James & Assoc",
    "wof:placetype":"venue"
},
  "geometry": {"coordinates":[-81.868892,26.644798],"type":"Point"}
}