{
  "type": "Feature",
  "properties": {
    "addr:full":"4451 Co Rd 846 Immokalee FL 34142",
    "addr:housenumber":"4451",
    "addr:postcode":"34142",
    "addr:street":"Co Rd 846",
    "iso:country":"US",
    "sg:address":"4451 Co Rd 846",
    "sg:city":"Immokalee",
    "sg:classifiers":[
        {
            "category":"Farming",
            "subcategory":"Livestock Farm",
            "type":"Manufacturing & Wholesale Goods"
        }
    ],
    "sg:phone":"+1 239 657 2000",
    "sg:postcode":"34142",
    "sg:province":"FL",
    "sg:tags":[
        "ranch",
        "cattle"
    ],
    "wof:name":"Immokalee Ranch",
    "wof:placetype":"venue"
},
  "geometry": {"coordinates":[-81.386892,26.419055],"type":"Point"}
}