{
  "type": "Feature",
  "properties": {
    "addr:full":"8425 NW 68th St Miami FL 33166",
    "addr:housenumber":"8425",
    "addr:postcode":"33166",
    "addr:street":"Nw 68Th St",
    "iso:country":"US",
    "sg:address":"8425 NW 68th St",
    "sg:city":"Miami",
    "sg:classifiers":[
        {
            "category":"Shopping",
            "subcategory":"Computers & Home Electronics",
            "type":"Retail Goods"
        }
    ],
    "sg:phone":"+1 786 265 0445",
    "sg:postcode":"33166",
    "sg:province":"FL",
    "sg:tags":[
        "equipment",
        "dealer"
    ],
    "wof:name":"Compu Mall",
    "wof:placetype":"venue"
},
  "geometry": {"coordinates":[-80.337743,25.835318],"type":"Point"}
}