{
  "type": "Feature",
  "properties": {
    "addr:full":"3021 W Waters Ave Tampa FL 33614",
    "addr:housenumber":"3021",
    "addr:postcode":"33614",
    "addr:street":"W Waters Ave",
    "iso:country":"US",
    "sg:address":"3021 W Waters Ave",
    "sg:city":"Tampa",
    "sg:classifiers":[
        {
            "category":"Education",
            "subcategory":"Dance Studio",
            "type":"Public Place"
        }
    ],
    "sg:phone":"+1 813 933 9321",
    "sg:postcode":"33614",
    "sg:province":"FL",
    "sg:tags":[
        "school"
    ],
    "sg:website":"www.frankreydancestudio.com",
    "wof:name":"Frank Rey Dance Studio",
    "wof:placetype":"venue"
},
  "geometry": {"coordinates":[-82.4922,28.02549],"type":"Point"}
}