{
  "type": "Feature",
  "properties": {
    "iso:country":"US",
    "sg:address":"306 S State Road 19",
    "sg:city":"Palatka",
    "sg:classifiers":[
        {
            "category":"Insurance",
            "subcategory":"Hazard Insurance",
            "type":"Services"
        },
        {
            "category":"Banks & Credit Unions",
            "subcategory":"Financial Services",
            "type":"Services"
        },
        {
            "category":"Banks & Credit Unions",
            "subcategory":"Bank",
            "type":"Services"
        }
    ],
    "sg:phone":"+1 386 328 7761",
    "sg:postcode":"32177",
    "sg:province":"FL",
    "sg:tags":[
        "saving",
        "commercial"
    ],
    "wof:name":"Neal Chancey Insurance Agency Incorporated",
    "wof:placetype":"venue"
},
  "geometry": {"coordinates":[-81.67558200000001,29.642943],"type":"Point"}
}