{
  "type": "Feature",
  "properties": {
    "iso:country":"US",
    "sg:address":"2901 South St",
    "sg:city":"Leesburg",
    "sg:classifiers":[
        {
            "category":"Real Estate",
            "subcategory":"Developer",
            "type":"Services"
        }
    ],
    "sg:phone":"+1 352 728 6888",
    "sg:postcode":"34748",
    "sg:province":"FL",
    "wof:name":"Royal Oak Estates of Lake Cnty",
    "wof:placetype":"venue"
},
  "geometry": {"coordinates":[-81.915031,28.803697],"type":"Point"}
}