{
  "type": "Feature",
  "properties": {
    "iso:country":"US",
    "sg:address":"240 Southridge Industrial Dr",
    "sg:city":"Tavares",
    "sg:classifiers":[
        {
            "category":"Home & Garden",
            "subcategory":"Home Furnishings",
            "type":"Retail Goods"
        },
        {
            "category":"Building & Trades",
            "subcategory":"Construction",
            "type":"Services"
        },
        {
            "category":"Manufacturing",
            "subcategory":"Building Materials",
            "type":"Manufacturing & Wholesale Goods"
        }
    ],
    "sg:phone":"+1 352 343 7999",
    "sg:postcode":"32778",
    "sg:province":"FL",
    "sg:tags":[
        "specialty",
        "frames",
        "contractor",
        "housewares",
        "doors",
        "mirror",
        "insulation",
        "accessory"
    ],
    "sg:website":"http://www.suncoastinsulators.com",
    "wof:name":"Suncoast Insulators & Specialties",
    "wof:placetype":"venue"
},
  "geometry": {"coordinates":[-81.73007200000001,28.7633],"type":"Point"}
}