{
  "type": "Feature",
  "properties": {
    "iso:country":"US",
    "sg:address":"105 State Rd 434 E",
    "sg:city":"Winter Springs",
    "sg:classifiers":[
        {
            "category":"Insurance",
            "subcategory":"Insurance Agent",
            "type":"Services"
        }
    ],
    "sg:phone":"+1 407 327 8600",
    "sg:postcode":"32708",
    "sg:province":"FL",
    "sg:tags":[
        "agency"
    ],
    "wof:name":"State Farm Insurance",
    "wof:placetype":"venue"
},
  "geometry": {"coordinates":[-81.30421200000001,28.69889],"type":"Point"}
}