{
  "type": "Feature",
  "properties": {
    "addr:full":"277 NE 2nd Ave Delray Beach FL 33444",
    "addr:housenumber":"277",
    "addr:postcode":"33444",
    "addr:street":"Ne 2Nd Ave",
    "iso:country":"US",
    "sg:address":"277 NE 2nd Ave",
    "sg:city":"Delray Beach",
    "sg:classifiers":[
        {
            "category":"Building & Trades",
            "subcategory":"Construction",
            "type":"Services"
        }
    ],
    "sg:phone":"+1 561 819 2800",
    "sg:postcode":"33444",
    "sg:province":"FL",
    "sg:tags":[
        "contractor"
    ],
    "wof:name":"Citywalk",
    "wof:placetype":"venue"
},
  "geometry": {"coordinates":[-80.071099,26.465683],"type":"Point"}
}