{
  "type": "Feature",
  "properties": {
    "addr:full":"2300 Hollywood Blvd Hollywood FL 33020",
    "addr:housenumber":"2300",
    "addr:postcode":"33020",
    "addr:street":"Hollywood Blvd",
    "iso:country":"US",
    "sg:address":"2300 Hollywood Blvd",
    "sg:city":"Hollywood",
    "sg:classifiers":[
        {
            "category":"Organizations",
            "subcategory":"Religious Organization",
            "type":"Services"
        }
    ],
    "sg:phone":"+1 954 923 8640",
    "sg:postcode":"33020",
    "sg:province":"FL",
    "wof:name":"Hollywood Bible Chapel Inc",
    "wof:placetype":"venue"
},
  "geometry": {"coordinates":[-80.152804,26.011259],"type":"Point"}
}