{
  "type": "Feature",
  "properties": {
    "addr:full":"3319 Lucas Lake Rd Chipley FL 32428",
    "addr:housenumber":"3319",
    "addr:postcode":"32428",
    "addr:street":"Lucas Lake Rd",
    "iso:country":"US",
    "sg:address":"3319 Lucas Lake Rd",
    "sg:city":"Chipley",
    "sg:classifiers":[
        {
            "category":"Building & Trades",
            "subcategory":"Landscaping Services",
            "type":"Services"
        }
    ],
    "sg:phone":"+1 850 773 9591",
    "sg:postcode":"32428",
    "sg:province":"FL",
    "wof:name":"Adams Landscape Management",
    "wof:placetype":"venue"
},
  "geometry": {"coordinates":[-85.685318,30.539206],"type":"Point"}
}