{
  "type": "Feature",
  "properties": {
    "addr:full":"11800 NW 100th Rd Medley FL 33178",
    "addr:housenumber":"11800",
    "addr:postcode":"33178",
    "addr:street":"Nw 100Th Rd",
    "iso:country":"US",
    "sg:address":"11800 NW 100th Rd",
    "sg:city":"Medley",
    "sg:classifiers":[
        {
            "category":"Wholesale",
            "subcategory":"Fruits & Vegetables",
            "type":"Manufacturing & Wholesale Goods"
        }
    ],
    "sg:phone":"+1 305 882 1500",
    "sg:postcode":"33178",
    "sg:province":"FL",
    "wof:name":"Inaexpo USA",
    "wof:placetype":"venue"
},
  "geometry": {"coordinates":[-80.363545,25.876493],"type":"Point"}
}