{
  "type": "Feature",
  "properties": {
    "iso:country":"US",
    "sg:address":"3236 NW South River Dr",
    "sg:city":"Miami",
    "sg:classifiers":[
        {
            "category":"Wholesale",
            "subcategory":"Durable Goods & Equipment",
            "type":"Manufacturing & Wholesale Goods"
        }
    ],
    "sg:phone":"+1 305 633 5114",
    "sg:postcode":"33142",
    "sg:province":"FL",
    "sg:tags":[
        "antique",
        "dealers-wholesale",
        "secondhand",
        "item"
    ],
    "sg:website":"http://www.stoneage-antiques.com",
    "wof:name":"Stone Age Antiques",
    "wof:placetype":"venue"
},
  "geometry": {"coordinates":[-80.24730099999999,25.796713],"type":"Point"}
}