{
  "type": "Feature",
  "properties": {
    "addr:full":"3504 Mount Tabor Rd Lakeland FL 33810",
    "addr:housenumber":"3504",
    "addr:postcode":"33810",
    "addr:street":"Mount Tabor Rd",
    "iso:country":"US",
    "sg:address":"3504 Mount Tabor Rd",
    "sg:city":"Lakeland",
    "sg:classifiers":[
        {
            "category":"Organizations",
            "subcategory":"Religious Organization",
            "type":"Services"
        }
    ],
    "sg:phone":"+1 863 858 3608",
    "sg:postcode":"33810",
    "sg:province":"FL",
    "sg:tags":[
        "baptist",
        "church"
    ],
    "wof:name":"Mount Tabor Baptist Church",
    "wof:placetype":"venue"
},
  "geometry": {"coordinates":[-82.01483,28.097345],"type":"Point"}
}