{
  "type": "Feature",
  "properties": {
    "addr:full":"580 Ballough Rd Daytona Beach FL 32114",
    "addr:housenumber":"580",
    "addr:postcode":"32114",
    "addr:street":"Ballough Rd",
    "iso:country":"US",
    "sg:address":"580 Ballough Rd",
    "sg:city":"Daytona Beach",
    "sg:classifiers":[
        {
            "category":"Professional",
            "subcategory":"Accounting & Tax Preparation",
            "type":"Services"
        }
    ],
    "sg:phone":"+1 386 304 6279",
    "sg:postcode":"32114",
    "sg:province":"FL",
    "sg:tags":[
        "return",
        "filing"
    ],
    "wof:name":"M & A Assoc",
    "wof:placetype":"venue"
},
  "geometry": {"coordinates":[-81.022808,29.223922],"type":"Point"}
}