{
  "type": "Feature",
  "properties": {
    "iso:country":"US",
    "sg:address":"6 NW 2nd St",
    "sg:city":"Gainesville",
    "sg:classifiers":[
        {
            "category":"Personal",
            "subcategory":"Beauty Salon",
            "type":"Services"
        }
    ],
    "sg:phone":"+1 352 335 1488",
    "sg:postcode":"32601",
    "sg:province":"FL",
    "sg:tags":[
        "shop",
        "barber"
    ],
    "wof:name":"Rays Hair Salon",
    "wof:placetype":"venue"
},
  "geometry": {"coordinates":[-82.326689,29.65109],"type":"Point"}
}