{
  "type": "Feature",
  "properties": {
    "iso:country":"US",
    "sg:address":"1026 7th St S",
    "sg:city":"Jacksonville Beach",
    "sg:classifiers":[
        {
            "category":"Building & Trades",
            "subcategory":"Construction",
            "type":"Services"
        }
    ],
    "sg:phone":"+1 904 246 3011",
    "sg:postcode":"32250",
    "sg:province":"FL",
    "sg:tags":[
        "hanging",
        "contractor"
    ],
    "wof:name":"Charles W Parks Incorporated",
    "wof:placetype":"venue"
},
  "geometry": {"coordinates":[-81.394244,30.277471],"type":"Point"}
}