{
  "type": "Feature",
  "properties": {
    "addr:full":"17632 Willis V McCall Rd Umatilla FL 32784",
    "addr:housenumber":"17632",
    "addr:postcode":"32784",
    "addr:street":"Willis V Mccall Rd",
    "iso:country":"US",
    "sg:address":"17632 Willis V McCall Rd",
    "sg:city":"Umatilla",
    "sg:classifiers":[
        {
            "category":"Travel",
            "subcategory":"Travel Agent",
            "type":"Entertainment"
        }
    ],
    "sg:phone":"+1 352 669 5897",
    "sg:postcode":"32784",
    "sg:province":"FL",
    "sg:tags":[
        "passenger",
        "transportation",
        "agency",
        "rail",
        "arrangement",
        "bureau"
    ],
    "wof:name":"A Round Travel Inc",
    "wof:placetype":"venue"
},
  "geometry": {"coordinates":[-81.665791,28.909394],"type":"Point"}
}