{
  "type": "Feature",
  "properties": {
    "addr:full":"333 N Falkenburg Rd Tampa FL 33619",
    "addr:housenumber":"333",
    "addr:postcode":"33619",
    "addr:street":"N Falkenburg Rd",
    "iso:country":"US",
    "sg:address":"333 N Falkenburg Rd",
    "sg:city":"Tampa",
    "sg:classifiers":[
        {
            "category":"Building & Trades",
            "subcategory":"Construction",
            "type":"Services"
        }
    ],
    "sg:phone":"+1 813 653 4599",
    "sg:postcode":"33619",
    "sg:province":"FL",
    "sg:tags":[
        "house",
        "general",
        "contractor"
    ],
    "wof:name":"Peter Borg Construction",
    "wof:placetype":"venue"
},
  "geometry": {"coordinates":[-82.335054,27.952161],"type":"Point"}
}