{
  "type": "Feature",
  "properties": {
    "iso:country":"US",
    "sg:address":"10912 Wiles Rd",
    "sg:city":"Coral Springs",
    "sg:classifiers":[
        {
            "category":"Retail",
            "subcategory":"Auto Repair",
            "type":"Services"
        }
    ],
    "sg:phone":"+1 954 755 3340",
    "sg:postcode":"33076",
    "sg:province":"FL",
    "sg:tags":[
        "repairing",
        "automobile",
        "general",
        "automotive",
        "sup"
    ],
    "wof:name":"Terrace Garage",
    "wof:placetype":"venue"
},
  "geometry": {"coordinates":[-80.26705699999999,26.287205],"type":"Point"}
}