{
  "type": "Feature",
  "properties": {
    "iso:country":"US",
    "sg:address":"2015 N Main St",
    "sg:city":"Kissimmee",
    "sg:classifiers":[
        {
            "category":"Retail",
            "subcategory":"Auto Repair",
            "type":"Services"
        }
    ],
    "sg:phone":"+1 407 847 9899",
    "sg:postcode":"34744",
    "sg:province":"FL",
    "sg:tags":[
        "body",
        "automobile",
        "painting"
    ],
    "wof:name":"Econo-Auto Painting Of Florida",
    "wof:placetype":"venue"
},
  "geometry": {"coordinates":[-81.403644,28.308932],"type":"Point"}
}