{
  "type": "Feature",
  "properties": {
    "iso:country":"US",
    "sg:address":"2380 SE 8th Ct",
    "sg:city":"Pompano Beach",
    "sg:classifiers":[
        {
            "category":"Restaurant",
            "type":"Food & Drink"
        }
    ],
    "sg:phone":"+1 954 782 0028",
    "sg:postcode":"33062",
    "sg:province":"FL",
    "sg:tags":[
        "eating"
    ],
    "wof:name":"Caffe Americano Inc",
    "wof:placetype":"venue"
},
  "geometry": {"coordinates":[-80.10099700000001,26.219968],"type":"Point"}
}