{
  "type": "Feature",
  "properties": {
    "addr:full":"18440 NW 44th Pl Opa Locka FL 33055",
    "addr:housenumber":"18440",
    "addr:postcode":"33055",
    "addr:street":"Nw 44Th Pl",
    "iso:country":"US",
    "sg:address":"18440 NW 44th Pl",
    "sg:city":"Opa Locka",
    "sg:classifiers":[
        {
            "category":"Shopping",
            "subcategory":"Florist",
            "type":"Retail Goods"
        }
    ],
    "sg:phone":"+1 305 620 2329",
    "sg:postcode":"33055",
    "sg:province":"FL",
    "wof:name":"Flowers By Sandra",
    "wof:placetype":"venue"
},
  "geometry": {"coordinates":[-80.274567,25.941182],"type":"Point"}
}