{
  "type": "Feature",
  "properties": {
    "addr:full":"121 E Hibiscus Blvd Melbourne FL 32901",
    "addr:housenumber":"121",
    "addr:postcode":"32901",
    "addr:street":"E Hibiscus Blvd",
    "iso:country":"US",
    "sg:address":"121 E Hibiscus Blvd",
    "sg:city":"Melbourne",
    "sg:classifiers":[
        {
            "category":"Professional",
            "subcategory":"Accounting & Tax Preparation",
            "type":"Services"
        }
    ],
    "sg:phone":"+1 321 733 1064",
    "sg:postcode":"32901",
    "sg:province":"FL",
    "wof:name":"Self James CPA PA",
    "wof:placetype":"venue"
},
  "geometry": {"coordinates":[-80.619844,28.085119],"type":"Point"}
}