{
  "type": "Feature",
  "properties": {
    "addr:full":"6320 SW 7th St Margate FL 33068",
    "addr:housenumber":"6320",
    "addr:postcode":"33068",
    "addr:street":"Sw 7Th St Margate",
    "iso:country":"US",
    "sg:address":"6320 SW 7th St",
    "sg:city":"Margate",
    "sg:classifiers":[
        {
            "category":"Building & Trades",
            "subcategory":"Landscaping Services",
            "type":"Services"
        }
    ],
    "sg:phone":"+1 954 501 5156",
    "sg:postcode":"33068",
    "sg:province":"FL",
    "sg:tags":[
        "lawn",
        "maintenance",
        "grounds"
    ],
    "wof:name":"Tanis Seinor Lawn Svc",
    "wof:placetype":"venue"
},
  "geometry": {"coordinates":[-80.210264,26.222452],"type":"Point"}
}