{
  "type": "Feature",
  "properties": {
    "iso:country":"US",
    "sg:address":"37 NE 15th St",
    "sg:city":"Miami",
    "sg:classifiers":[
        {
            "category":"Professional",
            "subcategory":"Business Services",
            "type":"Services"
        }
    ],
    "sg:phone":"+1 786 355 8385",
    "sg:postcode":"33132",
    "sg:province":"FL",
    "sg:tags":[
        "holding"
    ],
    "wof:name":"2898 Biscayne Holdings",
    "wof:placetype":"venue"
},
  "geometry": {"coordinates":[-80.193878,25.789419],"type":"Point"}
}