{
  "type": "Feature",
  "properties": {
    "iso:country":"US",
    "sg:address":"1413 S Howard Ave",
    "sg:city":"Tampa",
    "sg:classifiers":[
        {
            "category":"Real Estate",
            "subcategory":"Real Estate Agent",
            "type":"Services"
        }
    ],
    "sg:phone":"+1 813 253 0890",
    "sg:postcode":"33606",
    "sg:province":"FL",
    "sg:tags":[
        "management"
    ],
    "sg:website":"www.lanecompany.com",
    "wof:name":"Lane Co",
    "wof:placetype":"venue"
},
  "geometry": {"coordinates":[-82.483296,27.928444],"type":"Point"}
}