{
  "type": "Feature",
  "properties": {
    "iso:country":"US",
    "sg:address":"5932 6th St E",
    "sg:city":"Bradenton",
    "sg:classifiers":[
        {
            "category":"Manufacturing",
            "subcategory":"Retail Goods",
            "type":"Manufacturing & Wholesale Goods"
        }
    ],
    "sg:phone":"+1 941 755 5984",
    "sg:postcode":"34203",
    "sg:province":"FL",
    "sg:tags":[
        "product",
        "mfg"
    ],
    "wof:name":"Jjdm Industries Inc",
    "wof:placetype":"venue"
},
  "geometry": {"coordinates":[-82.55824699999999,27.435092],"type":"Point"}
}