{
  "type": "Feature",
  "properties": {
    "addr:full":"135 NW 14th Ave Delray Beach FL 33444",
    "addr:housenumber":"135",
    "addr:postcode":"33444",
    "addr:street":"Nw 14Th Ave",
    "iso:country":"US",
    "sg:address":"135 NW 14th Ave",
    "sg:city":"Delray Beach",
    "sg:classifiers":[
        {
            "category":"Building & Trades",
            "subcategory":"Construction",
            "type":"Services"
        }
    ],
    "sg:phone":"+1 561 929 4909",
    "sg:postcode":"33444",
    "sg:province":"FL",
    "sg:tags":[
        "restoration",
        "cleaning",
        "patio",
        "deck"
    ],
    "wof:name":"Ramon Trice Pressure Cleaning",
    "wof:placetype":"venue"
},
  "geometry": {"coordinates":[-80.087383,26.46471],"type":"Point"}
}