{
  "type": "Feature",
  "properties": {
    "addr:full":"8671 NW 56th St Doral FL 33166",
    "addr:housenumber":"8671",
    "addr:postcode":"33166",
    "addr:street":"Nw 56Th St",
    "iso:country":"US",
    "sg:address":"8671 NW 56th St",
    "sg:city":"Doral",
    "sg:classifiers":[
        {
            "category":"Professional",
            "subcategory":"Advertising",
            "type":"Services"
        }
    ],
    "sg:phone":"+1 305 994 9997",
    "sg:postcode":"33166",
    "sg:province":"FL",
    "sg:tags":[
        "mail"
    ],
    "wof:name":"Avion International Inc",
    "wof:placetype":"venue"
},
  "geometry": {"coordinates":[-80.336878,25.824472],"type":"Point"}
}