{
  "type": "Feature",
  "properties": {
    "iso:country":"US",
    "sg:address":"6177 Shoreline Cir N",
    "sg:city":"Daytona Beach",
    "sg:classifiers":[
        {
            "category":"Building & Trades",
            "subcategory":"Plumbing",
            "type":"Services"
        }
    ],
    "sg:phone":"+1 386 788 5007",
    "sg:postcode":"32127",
    "sg:province":"FL",
    "sg:tags":[
        "plumbing",
        "contractor"
    ],
    "wof:name":"Suncoast Plumbing",
    "wof:placetype":"venue"
},
  "geometry": {"coordinates":[-80.99752599999999,29.083846],"type":"Point"}
}