{
  "type": "Feature",
  "properties": {
    "addr:full":"310 W Bay Dr Largo FL 33770",
    "addr:housenumber":"310",
    "addr:postcode":"33770",
    "addr:street":"W Bay Dr",
    "iso:country":"US",
    "sg:address":"310 W Bay Dr",
    "sg:city":"Largo",
    "sg:classifiers":[
        {
            "category":"Real Estate",
            "subcategory":"Real Estate Agent",
            "type":"Services"
        }
    ],
    "sg:phone":"+1 727 587 9960",
    "sg:postcode":"33770",
    "sg:province":"FL",
    "wof:name":"Wren Real Estate",
    "wof:placetype":"venue"
},
  "geometry": {"coordinates":[-82.791974,27.916824],"type":"Point"}
}