{
  "type": "Feature",
  "properties": {
    "iso:country":"US",
    "sg:address":"3015 Calvin Blvd",
    "sg:city":"Fort Myers",
    "sg:classifiers":[
        {
            "category":"Building & Trades",
            "subcategory":"Pest Control",
            "type":"Services"
        }
    ],
    "sg:phone":"+1 239 337 3336",
    "sg:postcode":"33901",
    "sg:province":"FL",
    "wof:name":"Rapid Pest Control & Lawn Svc",
    "wof:placetype":"venue"
},
  "geometry": {"coordinates":[-81.86903700000001,26.620231],"type":"Point"}
}