{
  "type": "Feature",
  "properties": {
    "iso:country":"US",
    "sg:address":"430 S Park Rd",
    "sg:city":"Hollywood",
    "sg:classifiers":[
        {
            "category":"Professional",
            "type":"Services"
        }
    ],
    "sg:phone":"+1 954 962 8365",
    "sg:postcode":"33021",
    "sg:province":"FL",
    "wof:name":"Global Trders Distrs Represent",
    "wof:placetype":"venue"
},
  "geometry": {"coordinates":[-80.175574,26.00655],"type":"Point"}
}