{
  "type": "Feature",
  "properties": {
    "iso:country":"US",
    "sg:address":"5312 Sarapointe Dr",
    "sg:city":"Sarasota",
    "sg:classifiers":[
        {
            "category":"Retail",
            "subcategory":"Laundry & Dry Cleaning",
            "type":"Services"
        },
        {
            "category":"Retail",
            "subcategory":"Repair Shop",
            "type":"Services"
        },
        {
            "category":"Building & Trades",
            "subcategory":"Cleaning & Sanitation",
            "type":"Services"
        }
    ],
    "sg:phone":"+1 941 377 2884",
    "sg:postcode":"34232",
    "sg:province":"FL",
    "sg:tags":[
        "cleaner",
        "upholstery",
        "floor",
        "fire",
        "rug",
        "damage",
        "water",
        "waxing",
        "restoration",
        "polishing",
        "janitorial",
        "carpet"
    ],
    "wof:name":"Certified Carpet & Floor Care",
    "wof:placetype":"venue"
},
  "geometry": {"coordinates":[-82.46322499999999,27.343125],"type":"Point"}
}