{
  "type": "Feature",
  "properties": {
    "iso:country":"US",
    "sg:address":"18493 Powell Rd",
    "sg:city":"Brooksville",
    "sg:classifiers":[
        {
            "category":"Building & Trades",
            "subcategory":"Construction",
            "type":"Services"
        }
    ],
    "sg:phone":"+1 352 754 1841",
    "sg:postcode":"34604",
    "sg:province":"FL",
    "sg:tags":[
        "home",
        "improvement"
    ],
    "wof:name":"Ken's Home Improvement",
    "wof:placetype":"venue"
},
  "geometry": {"coordinates":[-82.42479899999999,28.492041],"type":"Point"}
}