{
  "type": "Feature",
  "properties": {
    "addr:full":"634 Glades Rd Boca Raton FL 33432",
    "addr:housenumber":"634",
    "addr:postcode":"33432",
    "addr:street":"Glades Rd",
    "iso:country":"US",
    "sg:address":"634 Glades Rd",
    "sg:city":"Boca Raton",
    "sg:classifiers":[
        {
            "category":"Shopping",
            "subcategory":"Florist",
            "type":"Retail Goods"
        }
    ],
    "sg:phone":"+1 561 368 1333",
    "sg:postcode":"33432",
    "sg:province":"FL",
    "wof:name":"Oaks Florist",
    "wof:placetype":"venue"
},
  "geometry": {"coordinates":[-80.101173,26.364695],"type":"Point"}
}