{
  "type": "Feature",
  "properties": {
    "iso:country":"US",
    "sg:address":"18788 SW 105th Ave",
    "sg:city":"Cutler Bay",
    "sg:classifiers":[
        {
            "category":"Retail",
            "subcategory":"Auto Repair",
            "type":"Services"
        }
    ],
    "sg:phone":"+1 305 238 3002",
    "sg:postcode":"33157",
    "sg:province":"FL",
    "wof:name":"Car Care International Corp",
    "wof:placetype":"venue"
},
  "geometry": {"coordinates":[-80.362512,25.592551],"type":"Point"}
}