{
  "type": "Feature",
  "properties": {
    "addr:full":"8465 Beulah Rd Pensacola FL 32526",
    "addr:housenumber":"8465",
    "addr:postcode":"32526",
    "addr:street":"Beulah Rd",
    "iso:country":"US",
    "sg:address":"8465 Beulah Rd",
    "sg:city":"Pensacola",
    "sg:classifiers":[
        {
            "category":"Manufacturing",
            "subcategory":"Lumber",
            "type":"Manufacturing & Wholesale Goods"
        }
    ],
    "sg:phone":"+1 850 944 0365",
    "sg:postcode":"32526",
    "sg:province":"FL",
    "sg:tags":[
        "operation",
        "tract",
        "tree",
        "timber"
    ],
    "wof:name":"Daniel Hutchins Family Lt",
    "wof:placetype":"venue"
},
  "geometry": {"coordinates":[-87.380987,30.523005],"type":"Point"}
}