{
  "type": "Feature",
  "properties": {
    "iso:country":"US",
    "sg:address":"1450 N Carpenter Ave",
    "sg:city":"Orange City",
    "sg:classifiers":[
        {
            "category":"Building & Trades",
            "subcategory":"Pest Control",
            "type":"Services"
        }
    ],
    "sg:phone":"+1 386 774 1260",
    "sg:postcode":"32763",
    "sg:province":"FL",
    "wof:name":"River City Pest Mangment",
    "wof:placetype":"venue"
},
  "geometry": {"coordinates":[-81.302902,28.962299],"type":"Point"}
}