{
  "type": "Feature",
  "properties": {
    "addr:full":"8904 SW 129th Ter Miami FL 33176",
    "addr:housenumber":"8904",
    "addr:postcode":"33176",
    "addr:street":"Sw 129Th Ter",
    "iso:country":"US",
    "sg:address":"8904 SW 129th Ter",
    "sg:city":"Miami",
    "sg:classifiers":[
        {
            "category":"Real Estate",
            "subcategory":"Real Estate Operator",
            "type":"Services"
        }
    ],
    "sg:phone":"+1 305 278 0396",
    "sg:postcode":"33176",
    "sg:province":"FL",
    "sg:tags":[
        "shopping",
        "operation",
        "property",
        "commercial",
        "center"
    ],
    "wof:name":"Coral Reef Plaza Inc",
    "wof:placetype":"venue"
},
  "geometry": {"coordinates":[-80.33949,25.649579],"type":"Point"}
}