{
  "type": "Feature",
  "properties": {
    "iso:country":"US",
    "sg:address":"3347 NW 74th Ave",
    "sg:city":"Miami",
    "sg:classifiers":[
        {
            "category":"Wholesale",
            "subcategory":"Medical Equipment & Supplies",
            "type":"Manufacturing & Wholesale Goods"
        }
    ],
    "sg:phone":"+1 305 500 9902",
    "sg:postcode":"33122",
    "sg:province":"FL",
    "wof:name":"Itc",
    "wof:placetype":"venue"
},
  "geometry": {"coordinates":[-80.317098,25.805761],"type":"Point"}
}