{
  "type": "Feature",
  "properties": {
    "addr:full":"33191 Cortez Blvd Dade City FL 33523",
    "addr:housenumber":"33191",
    "addr:postcode":"33523",
    "addr:street":"Cortez Blvd",
    "iso:country":"US",
    "sg:address":"33191 Cortez Blvd",
    "sg:city":"Dade City",
    "sg:classifiers":[
        {
            "category":"Restaurant",
            "type":"Food & Drink"
        }
    ],
    "sg:menulink":"http://www.allmenus.com/fl/ridge-manor/237190-hungry-howies-pizza/menu/",
    "sg:phone":"+1 352 583 5456",
    "sg:postcode":"33523",
    "sg:province":"FL",
    "sg:tags":[
        "wrap",
        "american",
        "sandwich",
        "pizza"
    ],
    "wof:name":"Hungry Howie's Pizza",
    "wof:placetype":"venue"
},
  "geometry": {"coordinates":[-82.19593399999999,28.508635],"type":"Point"}
}