{
  "type": "Feature",
  "properties": {
    "addr:full":"6209 Upcountry Dr Zephyrhills FL 33542",
    "addr:housenumber":"6209",
    "addr:postcode":"33542",
    "addr:street":"Upcountry Dr",
    "iso:country":"US",
    "sg:address":"6209 Upcountry Dr",
    "sg:city":"Zephyrhills",
    "sg:classifiers":[
        {
            "category":"Building & Trades",
            "subcategory":"Construction",
            "type":"Services"
        }
    ],
    "sg:phone":"+1 813 780 9940",
    "sg:postcode":"33542",
    "sg:province":"FL",
    "sg:tags":[
        "contractor"
    ],
    "wof:name":"Jenkins Masonary Inc",
    "wof:placetype":"venue"
},
  "geometry": {"coordinates":[-82.16227000000001,28.247011],"type":"Point"}
}