{
  "type": "Feature",
  "properties": {
    "iso:country":"US",
    "sg:address":"18980 W Dixie Hwy",
    "sg:city":"Miami",
    "sg:classifiers":[
        {
            "category":"Retail",
            "subcategory":"Animal Services",
            "type":"Services"
        }
    ],
    "sg:phone":"+1 305 466 1516",
    "sg:postcode":"33180",
    "sg:province":"FL",
    "sg:tags":[
        "pet",
        "grooming",
        "washing"
    ],
    "wof:name":"Doglee Grooming",
    "wof:placetype":"venue"
},
  "geometry": {"coordinates":[-80.148983,25.950885],"type":"Point"}
}