{
  "type": "Feature",
  "properties": {
    "addr:full":"11000 Metro Pkwy Fort Myers FL 33912",
    "addr:postcode":"11000;33912",
    "addr:street":"Metro Pkwy",
    "iso:country":"US",
    "sg:address":"11000 Metro Pkwy",
    "sg:city":"Fort Myers",
    "sg:classifiers":[
        {
            "category":"Wholesale",
            "subcategory":"Electrical",
            "type":"Manufacturing & Wholesale Goods"
        }
    ],
    "sg:phone":"+1 239 275 0202",
    "sg:postcode":"33912",
    "sg:province":"FL",
    "sg:tags":[
        "equipment",
        "parts",
        "electronic"
    ],
    "wof:name":"Message On Hold Network",
    "wof:placetype":"venue"
},
  "geometry": {"coordinates":[-81.85319,26.581225],"type":"Point"}
}