{
  "type": "Feature",
  "properties": {
    "iso:country":"US",
    "sg:address":"1423 SE 16th Ter",
    "sg:city":"Cape Coral",
    "sg:classifiers":[
        {
            "category":"Real Estate",
            "subcategory":"Real Estate Agent",
            "type":"Services"
        }
    ],
    "sg:phone":"+1 239 573 6464",
    "sg:postcode":"33990",
    "sg:province":"FL",
    "wof:name":"Realamerica Realty",
    "wof:placetype":"venue"
},
  "geometry": {"coordinates":[-81.945103,26.622258],"type":"Point"}
}