{
  "type": "Feature",
  "properties": {
    "iso:country":"US",
    "sg:address":"417 E Sheridan St",
    "sg:city":"Dania",
    "sg:classifiers":[
        {
            "category":"Professional",
            "subcategory":"Business Services",
            "type":"Services"
        }
    ],
    "sg:phone":"+1 954 920 1901",
    "sg:postcode":"33004",
    "sg:province":"FL",
    "sg:tags":[
        "packaging"
    ],
    "wof:name":"Super Postal Ctr",
    "wof:placetype":"venue"
},
  "geometry": {"coordinates":[-80.137288,26.033841],"type":"Point"}
}