{
  "type": "Feature",
  "properties": {
    "iso:country":"US",
    "sg:address":"625 Cortez Rd W",
    "sg:city":"Bradenton",
    "sg:classifiers":[
        {
            "category":"Personal",
            "subcategory":"Beauty Salon",
            "type":"Services"
        }
    ],
    "sg:phone":"+1 941 752 0661",
    "sg:postcode":"34207",
    "sg:province":"FL",
    "sg:tags":[
        "manicuring"
    ],
    "wof:name":"Nail World",
    "wof:placetype":"venue"
},
  "geometry": {"coordinates":[-82.56821100000001,27.462236],"type":"Point"}
}