{
  "type": "Feature",
  "properties": {
    "iso:country":"US",
    "sg:address":"1837 Lake Heron Dr",
    "sg:city":"Lutz",
    "sg:classifiers":[
        {
            "category":"Professional",
            "type":"Services"
        }
    ],
    "sg:phone":"+1 813 416 3284",
    "sg:postcode":"33549",
    "sg:province":"FL",
    "wof:name":"Space LLC",
    "wof:placetype":"venue"
},
  "geometry": {"coordinates":[-82.462547,28.182609],"type":"Point"}
}