{
  "type": "Feature",
  "properties": {
    "addr:full":"2315 Cheryl Dr Jacksonville FL 32217",
    "addr:housenumber":"2315",
    "addr:postcode":"32217",
    "addr:street":"Cheryl Dr",
    "iso:country":"US",
    "sg:address":"2315 Cheryl Dr",
    "sg:city":"Jacksonville",
    "sg:classifiers":[
        {
            "category":"Wholesale",
            "subcategory":"Jewelry",
            "type":"Manufacturing & Wholesale Goods"
        }
    ],
    "sg:phone":"+1 904 737 4909",
    "sg:postcode":"32217",
    "sg:province":"FL",
    "sg:tags":[
        "stone"
    ],
    "wof:name":"William A Shedlin Inc",
    "wof:placetype":"venue"
},
  "geometry": {"coordinates":[-81.623963,30.237625],"type":"Point"}
}