{
  "type": "Feature",
  "properties": {
    "addr:full":"1756 N Bayshore Dr Miami FL 33132",
    "addr:housenumber":"1756",
    "addr:postcode":"33132",
    "addr:street":"N Bayshore Dr",
    "iso:country":"US",
    "sg:address":"1756 N Bayshore Dr",
    "sg:city":"Miami",
    "sg:classifiers":[
        {
            "category":"Health Services",
            "subcategory":"Doctor",
            "type":"Services"
        }
    ],
    "sg:phone":"+1 305 503 5704",
    "sg:postcode":"33132",
    "sg:province":"FL",
    "sg:tags":[
        "physician",
        "surgeon"
    ],
    "wof:name":"Halem Dr Monica",
    "wof:placetype":"venue"
},
  "geometry": {"coordinates":[-80.18656300000001,25.792791],"type":"Point"}
}