{
  "type": "Feature",
  "properties": {
    "iso:country":"US",
    "sg:address":"8851 Navarre Pkwy",
    "sg:city":"Gulf Breeze",
    "sg:classifiers":[
        {
            "category":"Real Estate",
            "subcategory":"Real Estate Agent",
            "type":"Services"
        },
        {
            "category":"Organizations",
            "subcategory":"Professional Association",
            "type":"Services"
        }
    ],
    "sg:phone":"+1 850 939 3870",
    "sg:postcode":"32566",
    "sg:province":"FL",
    "sg:tags":[
        "board"
    ],
    "wof:name":"Navarre Beach Bd of Realtors",
    "wof:placetype":"venue"
},
  "geometry": {"coordinates":[-86.854399,30.403231],"type":"Point"}
}