{
  "type": "Feature",
  "properties": {
    "iso:country":"US",
    "sg:address":"528 NW 1st Ave",
    "sg:city":"Fort Lauderdale",
    "sg:classifiers":[
        {
            "category":"Building & Trades",
            "subcategory":"Construction",
            "type":"Services"
        }
    ],
    "sg:phone":"+1 954 779 1188",
    "sg:postcode":"33301",
    "sg:province":"FL",
    "sg:tags":[
        "brick",
        "interlocking",
        "contractor"
    ],
    "wof:name":"Perfect Pavers Inc",
    "wof:placetype":"venue"
},
  "geometry": {"coordinates":[-80.144662,26.129147],"type":"Point"}
}