{
  "type": "Feature",
  "properties": {
    "iso:country":"US",
    "sg:address":"39 Wiregrass Ln",
    "sg:city":"Quincy",
    "sg:classifiers":[
        {
            "category":"Home & Garden",
            "subcategory":"Building Materials",
            "type":"Retail Goods"
        },
        {
            "category":"Building & Trades",
            "subcategory":"Construction",
            "type":"Services"
        }
    ],
    "sg:phone":"+1 850 627 4967",
    "sg:postcode":"32351",
    "sg:province":"FL",
    "sg:tags":[
        "concrete",
        "staining",
        "contractor"
    ],
    "wof:name":"Conley Concrete",
    "wof:placetype":"venue"
},
  "geometry": {"coordinates":[-84.615666,30.482122],"type":"Point"}
}