{
  "type": "Feature",
  "properties": {
    "iso:country":"US",
    "sg:address":"4328 Corporate Sq",
    "sg:city":"Naples",
    "sg:classifiers":[
        {
            "category":"Shopping",
            "type":"Retail Goods"
        }
    ],
    "sg:phone":"+1 239 261 9910",
    "sg:postcode":"34104",
    "sg:province":"FL",
    "sg:tags":[
        "equipment",
        "telephone",
        "supply"
    ],
    "wof:name":"Biz Comm Technologies",
    "wof:placetype":"venue"
},
  "geometry": {"coordinates":[-81.758447,26.156189],"type":"Point"}
}