{
  "type": "Feature",
  "properties": {
    "addr:full":"9281 New Martinsville Ave Englewood FL 34224",
    "addr:housenumber":"9281",
    "addr:postcode":"34224",
    "addr:street":"New Martinsville Ave",
    "iso:country":"US",
    "sg:address":"9281 New Martinsville Ave",
    "sg:city":"Englewood",
    "sg:classifiers":[
        {
            "category":"Organizations",
            "subcategory":"Religious Organization",
            "type":"Services"
        }
    ],
    "sg:phone":"+1 941 474 3383",
    "sg:postcode":"34224",
    "sg:province":"FL",
    "sg:tags":[
        "church"
    ],
    "wof:name":"Restoration Church",
    "wof:placetype":"venue"
},
  "geometry": {"coordinates":[-82.297906,26.927296],"type":"Point"}
}