{
  "type": "Feature",
  "properties": {
    "addr:full":"3303 NW 135th St Opa Locka FL 33054",
    "addr:housenumber":"3303",
    "addr:postcode":"33054",
    "addr:street":"Nw 135Th St;Locka",
    "iso:country":"US",
    "sg:address":"3303 NW 135th St",
    "sg:city":"Opa Locka",
    "sg:classifiers":[
        {
            "category":"Autos & Motor Vehicles",
            "subcategory":"Automobile Sales",
            "type":"Retail Goods"
        }
    ],
    "sg:phone":"+1 305 681 4666",
    "sg:postcode":"33054",
    "sg:province":"FL",
    "sg:tags":[
        "car",
        "dealer"
    ],
    "wof:name":"Lima Auto Sales",
    "wof:placetype":"venue"
},
  "geometry": {"coordinates":[-80.254766,25.896921],"type":"Point"}
}