{
  "type": "Feature",
  "properties": {
    "iso:country":"US",
    "sg:address":"6605 NW 7th St",
    "sg:city":"Miami",
    "sg:classifiers":[
        {
            "category":"Travel",
            "subcategory":"Hotels & Motels",
            "type":"Entertainment"
        }
    ],
    "sg:phone":"+1 305 260 0085",
    "sg:postcode":"33126",
    "sg:province":"FL",
    "wof:name":"Homestead Village",
    "wof:placetype":"venue"
},
  "geometry": {"coordinates":[-80.30390199999999,25.777599],"type":"Point"}
}