{
  "type": "Feature",
  "properties": {
    "iso:country":"US",
    "sg:address":"125 Madison Pl",
    "sg:city":"Deltona",
    "sg:classifiers":[
        {
            "category":"Building & Trades",
            "subcategory":"Construction",
            "type":"Services"
        }
    ],
    "sg:phone":"+1 386 668 7176",
    "sg:postcode":"32725",
    "sg:province":"FL",
    "sg:tags":[
        "framing"
    ],
    "wof:name":"Kitterer Mark Business Svcs",
    "wof:placetype":"venue"
},
  "geometry": {"coordinates":[-81.264432,28.870303],"type":"Point"}
}