{
  "type": "Feature",
  "properties": {
    "iso:country":"US",
    "sg:address":"2495 N McMullen Booth Rd",
    "sg:city":"Clearwater",
    "sg:classifiers":[
        {
            "category":"Autos & Motor Vehicles",
            "subcategory":"Fuel & Gas Station",
            "type":"Retail Goods"
        }
    ],
    "sg:phone":"+1 727 791 9363",
    "sg:postcode":"33759",
    "sg:province":"FL",
    "sg:tags":[
        "convenience",
        "gasoline",
        "store"
    ],
    "wof:name":"Mobil",
    "wof:placetype":"venue"
},
  "geometry": {"coordinates":[-82.70885199999999,28.010736],"type":"Point"}
}