{
  "type": "Feature",
  "properties": {
    "iso:country":"US",
    "sg:address":"310 N Myrtle Ave",
    "sg:city":"Clearwater",
    "sg:classifiers":[
        {
            "category":"Government",
            "subcategory":"Office",
            "type":"Public Place"
        }
    ],
    "sg:phone":"+1 727 469 5800",
    "sg:postcode":"33755",
    "sg:province":"FL",
    "sg:tags":[
        "government-state",
        "government-county",
        "parish"
    ],
    "sg:website":"http://www.fortdesoto.com",
    "wof:name":"Pinellas County Health Dept",
    "wof:placetype":"venue"
},
  "geometry": {"coordinates":[-82.79593,27.969149],"type":"Point"}
}