{
  "type": "Feature",
  "properties": {
    "iso:country":"US",
    "sg:address":"2630 Hollywood Blvd",
    "sg:city":"Hollywood",
    "sg:classifiers":[
        {
            "category":"Banks & Credit Unions",
            "subcategory":"Bank",
            "type":"Services"
        }
    ],
    "sg:phone":"+1 954 924 1660",
    "sg:postcode":"33020",
    "sg:province":"FL",
    "sg:tags":[
        "mortgage",
        "loan",
        "broker",
        "real estate"
    ],
    "wof:name":"Arlington Mortgage Group LLC",
    "wof:placetype":"venue"
},
  "geometry": {"coordinates":[-80.16041300000001,26.011038],"type":"Point"}
}