{
  "type": "Feature",
  "properties": {
    "iso:country":"US",
    "sg:address":"15815 Tower View Dr",
    "sg:city":"Clermont",
    "sg:classifiers":[
        {
            "category":"Freight",
            "type":"Transportation"
        }
    ],
    "sg:phone":"+1 352 404 9694",
    "sg:postcode":"34711",
    "sg:province":"FL",
    "sg:tags":[
        "trucking"
    ],
    "wof:name":"Tasnim Trucking Co Inc",
    "wof:placetype":"venue"
},
  "geometry": {"coordinates":[-81.786293,28.578139],"type":"Point"}
}