{
  "type": "Feature",
  "properties": {
    "addr:full":"2170 Sunnydale Blvd Ste X Clearwater FL 33765",
    "addr:housenumber":"2170",
    "addr:postcode":"33765",
    "addr:street":"Sunnydale Blvd Ste X",
    "iso:country":"US",
    "sg:address":"2170 Sunnydale Blvd Ste X",
    "sg:city":"Clearwater",
    "sg:classifiers":[
        {
            "category":"Shopping",
            "subcategory":"Optical Goods",
            "type":"Retail Goods"
        }
    ],
    "sg:phone":"+1 727 441 2623",
    "sg:postcode":"33765",
    "sg:province":"FL",
    "sg:tags":[
        "repair"
    ],
    "wof:name":"Pro Med Direct Inc",
    "wof:placetype":"venue"
},
  "geometry": {"coordinates":[-82.74762,27.987055],"type":"Point"}
}