{
  "type": "Feature",
  "properties": {
    "iso:country":"US",
    "sg:address":"4336 Narvarez Way",
    "sg:city":"Saint Petersburg",
    "sg:classifiers":[
        {
            "category":"Building & Trades",
            "subcategory":"Construction",
            "type":"Services"
        }
    ],
    "sg:phone":"+1 727 867 2276",
    "sg:postcode":"33712",
    "sg:province":"FL",
    "sg:tags":[
        "house"
    ],
    "wof:name":"L&L Home Improvements Inc",
    "wof:placetype":"venue"
},
  "geometry": {"coordinates":[-82.67127600000001,27.729077],"type":"Point"}
}