{
  "type": "Feature",
  "properties": {
    "iso:country":"US",
    "sg:address":"1401 N Mills Ave",
    "sg:city":"Orlando",
    "sg:classifiers":[
        {
            "category":"Retail",
            "subcategory":"Car Wash",
            "type":"Services"
        }
    ],
    "sg:phone":"+1 407 896 1926",
    "sg:postcode":"32803",
    "sg:province":"FL",
    "sg:tags":[
        "automobile",
        "detailing"
    ],
    "sg:website":"http://www.octopuscarwashflorida.com",
    "wof:name":"Octopus Car Wash",
    "wof:placetype":"venue"
},
  "geometry": {"coordinates":[-81.36444899999999,28.564039],"type":"Point"}
}