{
  "type": "Feature",
  "properties": {
    "iso:country":"US",
    "sg:address":"2963 E Rawhide Ln",
    "sg:city":"Hernando",
    "sg:classifiers":[
        {
            "category":"Professional",
            "subcategory":"Employment Agencies",
            "type":"Services"
        }
    ],
    "sg:phone":"+1 352 860 2114",
    "sg:postcode":"34442",
    "sg:province":"FL",
    "wof:name":"America Employment Agency",
    "wof:placetype":"venue"
},
  "geometry": {"coordinates":[-82.385019,28.927932],"type":"Point"}
}