{
  "type": "Feature",
  "properties": {
    "addr:full":"2653 73rd Ct W Bradenton FL 34209",
    "addr:housenumber":"2653",
    "addr:postcode":"34209",
    "addr:street":"73Rd Ct W",
    "iso:country":"US",
    "sg:address":"2653 73rd Ct W",
    "sg:city":"Bradenton",
    "sg:classifiers":[
        {
            "category":"Home & Garden",
            "subcategory":"Building Materials",
            "type":"Retail Goods"
        }
    ],
    "sg:phone":"+1 941 739 5858",
    "sg:postcode":"34209",
    "sg:province":"FL",
    "sg:tags":[
        "trade",
        "contractor"
    ],
    "wof:name":"Closets Unlimited",
    "wof:placetype":"venue"
},
  "geometry": {"coordinates":[-82.635125,27.476001],"type":"Point"}
}