{
  "type": "Feature",
  "properties": {
    "iso:country":"US",
    "sg:address":"4301 N Wickham Rd Ste 6",
    "sg:city":"Melbourne",
    "sg:classifiers":[
        {
            "category":"Retail",
            "subcategory":"Auto Repair",
            "type":"Services"
        }
    ],
    "sg:phone":"+1 321 255 1770",
    "sg:postcode":"32935",
    "sg:province":"FL",
    "sg:tags":[
        "body",
        "automobile",
        "painting",
        "repairing"
    ],
    "wof:name":"Shirlee Fender",
    "wof:placetype":"venue"
},
  "geometry": {"coordinates":[-80.67192799999999,28.180099],"type":"Point"}
}