{
  "type": "Feature",
  "properties": {
    "addr:full":"11659 NW Gainesville Rd Ocala FL 34482",
    "addr:housenumber":"11659",
    "addr:postcode":"34482",
    "addr:street":"Nw Gainesville Rd",
    "iso:country":"US",
    "sg:address":"11659 NW Gainesville Rd",
    "sg:city":"Ocala",
    "sg:classifiers":[
        {
            "category":"Freight",
            "type":"Transportation"
        }
    ],
    "sg:phone":"+1 352 732 3377",
    "sg:postcode":"34482",
    "sg:province":"FL",
    "sg:tags":[
        "operator",
        "trucking"
    ],
    "wof:name":"Lowell Terminal",
    "wof:placetype":"venue"
},
  "geometry": {"coordinates":[-82.19635100000001,29.320051],"type":"Point"}
}