{
  "type": "Feature",
  "properties": {
    "iso:country":"US",
    "sg:address":"2530 W 6th Ln",
    "sg:city":"Hialeah",
    "sg:classifiers":[
        {
            "category":"Manufacturing",
            "subcategory":"Building Materials",
            "type":"Manufacturing & Wholesale Goods"
        }
    ],
    "sg:phone":"+1 305 885 5474",
    "sg:postcode":"33010",
    "sg:province":"FL",
    "sg:tags":[
        "mfg",
        "wood",
        "kitchen",
        "cabinet"
    ],
    "wof:name":"Creative Home By Design",
    "wof:placetype":"venue"
},
  "geometry": {"coordinates":[-80.29535199999999,25.844981],"type":"Point"}
}