{
  "type": "Feature",
  "properties": {
    "iso:country":"US",
    "sg:address":"5709 Main St",
    "sg:city":"New Port Richey",
    "sg:classifiers":[
        {
            "category":"Professional",
            "subcategory":"Lawyer & Legal Services",
            "type":"Services"
        }
    ],
    "sg:phone":"+1 727 845 3574",
    "sg:postcode":"34652",
    "sg:province":"FL",
    "sg:tags":[
        "attorney"
    ],
    "wof:name":"Beltz Ruth Magazine Newman",
    "wof:placetype":"venue"
},
  "geometry": {"coordinates":[-82.72012599999999,28.250281],"type":"Point"}
}