{
  "type": "Feature",
  "properties": {
    "addr:full":"9240 NW 44th Ct Pompano Beach FL 33065",
    "addr:housenumber":"9240",
    "addr:postcode":"33065",
    "addr:street":"Nw 44Th Ct",
    "iso:country":"US",
    "sg:address":"9240 NW 44th Ct",
    "sg:city":"Pompano Beach",
    "sg:classifiers":[
        {
            "category":"Manufacturing",
            "subcategory":"Tools & Machinery",
            "type":"Manufacturing & Wholesale Goods"
        }
    ],
    "sg:phone":"+1 954 345 2529",
    "sg:postcode":"33065",
    "sg:province":"FL",
    "sg:tags":[
        "computer",
        "storage",
        "devices",
        "mfg"
    ],
    "wof:name":"Reliant Medical",
    "wof:placetype":"venue"
},
  "geometry": {"coordinates":[-80.24852799999999,26.284499],"type":"Point"}
}