{
  "type": "Feature",
  "properties": {
    "addr:full":"1616 Washington Ave Miami Beach FL 33139",
    "addr:housenumber":"1616",
    "addr:postcode":"33139",
    "addr:street":"Washington Ave",
    "iso:country":"US",
    "sg:address":"1616 Washington Ave",
    "sg:city":"Miami Beach",
    "sg:classifiers":[
        {
            "category":"Fast Food",
            "type":"Food & Drink"
        },
        {
            "category":"Restaurant",
            "type":"Food & Drink"
        }
    ],
    "sg:phone":"+1 305 532 5277",
    "sg:postcode":"33139",
    "sg:province":"FL",
    "sg:tags":[
        "argentine"
    ],
    "sg:website":"www.halfmoonempanadas.com",
    "wof:name":"Half Moon Empanadas",
    "wof:placetype":"venue"
},
  "geometry": {"coordinates":[-80.131897,25.789824],"type":"Point"}
}