{
  "type": "Feature",
  "properties": {
    "iso:country":"US",
    "sg:address":"200 Ross Dr",
    "sg:city":"Delray Beach",
    "sg:classifiers":[
        {
            "category":"Building & Trades",
            "subcategory":"Construction",
            "type":"Services"
        }
    ],
    "sg:phone":"+1 561 265 0517",
    "sg:postcode":"33445",
    "sg:province":"FL",
    "sg:tags":[
        "contractor"
    ],
    "wof:name":"Azam Tile Inc",
    "wof:placetype":"venue"
},
  "geometry": {"coordinates":[-80.096554,26.465802],"type":"Point"}
}