{
  "type": "Feature",
  "properties": {
    "addr:full":"5928 Fortune Pl Apollo Beach FL 33572",
    "addr:housenumber":"5928",
    "addr:postcode":"33572",
    "addr:street":"Fortune Pl",
    "iso:country":"US",
    "sg:address":"5928 Fortune Pl",
    "sg:city":"Apollo Beach",
    "sg:classifiers":[
        {
            "category":"Professional",
            "subcategory":"Computer Services",
            "type":"Services"
        }
    ],
    "sg:phone":"+1 813 641 0026",
    "sg:postcode":"33572",
    "sg:province":"FL",
    "sg:tags":[
        "repair"
    ],
    "wof:name":"Robert Earl Gambrell",
    "wof:placetype":"venue"
},
  "geometry": {"coordinates":[-82.398281,27.76256],"type":"Point"}
}