{
  "type": "Feature",
  "properties": {
    "iso:country":"US",
    "sg:address":"2940 SW 3rd Ave",
    "sg:city":"Miami",
    "sg:classifiers":[
        {
            "category":"Building & Trades",
            "subcategory":"Locksmith",
            "type":"Services"
        }
    ],
    "sg:phone":"+1 786 245 4795",
    "sg:postcode":"33129",
    "sg:province":"FL",
    "sg:tags":[
        "key"
    ],
    "wof:name":"0 0 0 24 Hour Locksmith",
    "wof:placetype":"venue"
},
  "geometry": {"coordinates":[-80.211285,25.753556],"type":"Point"}
}