{
  "type": "Feature",
  "properties": {
    "addr:full":"11401 NW 12th St Miami FL 33172",
    "addr:housenumber":"11401",
    "addr:postcode":"33172",
    "addr:street":"Nw 12Th St",
    "iso:country":"US",
    "sg:address":"11401 NW 12th St",
    "sg:city":"Miami",
    "sg:classifiers":[
        {
            "category":"Shopping",
            "subcategory":"Gifts & Souvenirs",
            "type":"Retail Goods"
        },
        {
            "category":"Manufacturing",
            "subcategory":"Jewelry",
            "type":"Manufacturing & Wholesale Goods"
        },
        {
            "category":"Shopping",
            "type":"Retail Goods"
        }
    ],
    "sg:phone":"+1 305 717 3560",
    "sg:postcode":"33172",
    "sg:province":"FL",
    "sg:tags":[
        "shop",
        "novelty"
    ],
    "sg:website":"www.spencersonline.com",
    "wof:name":"Spencer Gifts",
    "wof:placetype":"venue"
},
  "geometry": {"coordinates":[-80.376503,25.782801],"type":"Point"}
}