{
  "type": "Feature",
  "properties": {
    "addr:full":"1282 3rd St S Jacksonville Bch FL 32250",
    "addr:housenumber":"1282",
    "addr:postcode":"32250",
    "addr:street":"3Rd St S",
    "iso:country":"US",
    "sg:address":"1282 3rd St S",
    "sg:city":"Jacksonville Bch",
    "sg:classifiers":[
        {
            "category":"Shopping",
            "type":"Retail Goods"
        }
    ],
    "sg:phone":"+1 904 249 1757",
    "sg:postcode":"32250",
    "sg:province":"FL",
    "sg:tags":[
        "limb",
        "artificial"
    ],
    "wof:name":"Nova Care Orthotics & Prsthtcs",
    "wof:placetype":"venue"
},
  "geometry": {"coordinates":[-81.389517,30.276846],"type":"Point"}
}