{
  "type": "Feature",
  "properties": {
    "addr:full":"5373 Ehrlich Rd Tampa FL 33625",
    "addr:housenumber":"5373",
    "addr:postcode":"33625",
    "addr:street":"Ehrlich Rd",
    "iso:country":"US",
    "sg:address":"5373 Ehrlich Rd",
    "sg:city":"Tampa",
    "sg:classifiers":[
        {
            "category":"Professional",
            "subcategory":"Engineering",
            "type":"Services"
        }
    ],
    "sg:phone":"+1 813 269 0401",
    "sg:postcode":"33625",
    "sg:province":"FL",
    "sg:tags":[
        "engineer"
    ],
    "wof:name":"Structures One",
    "wof:placetype":"venue"
},
  "geometry": {"coordinates":[-82.542171,28.083143],"type":"Point"}
}