{
  "type": "Feature",
  "properties": {
    "addr:full":"7970 Starkey Rd Seminole FL 33777",
    "addr:housenumber":"7970",
    "addr:postcode":"33777",
    "addr:street":"Starkey Rd",
    "iso:country":"US",
    "sg:address":"7970 Starkey Rd",
    "sg:city":"Seminole",
    "sg:classifiers":[
        {
            "category":"Education",
            "subcategory":"Special Training",
            "type":"Public Place"
        },
        {
            "category":"Social Services",
            "subcategory":"Child Care",
            "type":"Services"
        },
        {
            "category":"Education",
            "subcategory":"Preschool",
            "type":"Public Place"
        },
        {
            "category":"Education",
            "subcategory":"School",
            "type":"Public Place"
        }
    ],
    "sg:phone":"+1 727 397 8207",
    "sg:postcode":"33777",
    "sg:province":"FL",
    "sg:tags":[
        "educational",
        "private",
        "kindergarten",
        "nursery",
        "k-",
        "day"
    ],
    "sg:website":"http://www.gingerbreadschool.com",
    "wof:name":"Gingerbread Schools",
    "wof:placetype":"venue"
},
  "geometry": {"coordinates":[-82.76239,27.844559],"type":"Point"}
}