{
  "type": "Feature",
  "properties": {
    "addr:full":"4978 W Colonial Dr Orlando FL 32808",
    "addr:housenumber":"4978",
    "addr:postcode":"32808",
    "addr:street":"W Colonial Dr",
    "iso:country":"US",
    "sg:address":"4978 W Colonial Dr",
    "sg:city":"Orlando",
    "sg:classifiers":[
        {
            "category":"Shopping",
            "subcategory":"Computers & Home Electronics",
            "type":"Retail Goods"
        }
    ],
    "sg:phone":"+1 407 298 3040",
    "sg:postcode":"32808",
    "sg:province":"FL",
    "sg:tags":[
        "stereo",
        "automobile",
        "system",
        "high",
        "stereophonic",
        "radio",
        "fidelity"
    ],
    "sg:website":"www.ultimate-audio.com",
    "wof:name":"Ultimate Audio",
    "wof:placetype":"venue"
},
  "geometry": {"coordinates":[-81.447056,28.552409],"type":"Point"}
}