{
  "type": "Feature",
  "properties": {
    "iso:country":"US",
    "sg:address":"26814 Dayflower Blvd",
    "sg:city":"Zephyrhills",
    "sg:classifiers":[
        {
            "category":"Building & Trades",
            "subcategory":"Construction",
            "type":"Services"
        }
    ],
    "sg:phone":"+1 813 997 3380",
    "sg:postcode":"33544",
    "sg:province":"FL",
    "sg:tags":[
        "residential"
    ],
    "wof:name":"Faulkner Franklin W Bill Inc",
    "wof:placetype":"venue"
},
  "geometry": {"coordinates":[-82.373122,28.242935],"type":"Point"}
}