{
  "type": "Feature",
  "properties": {
    "iso:country":"US",
    "sg:address":"1150 SW 10th Ave",
    "sg:city":"Pompano Beach",
    "sg:classifiers":[
        {
            "category":"Manufacturing",
            "subcategory":"Printing",
            "type":"Manufacturing & Wholesale Goods"
        }
    ],
    "sg:phone":"+1 954 545 8088",
    "sg:postcode":"33069",
    "sg:province":"FL",
    "sg:tags":[
        "printer"
    ],
    "wof:name":"Alpha One Xpress Corp",
    "wof:placetype":"venue"
},
  "geometry": {"coordinates":[-80.137513,26.214949],"type":"Point"}
}