{
  "type": "Feature",
  "properties": {
    "addr:full":"5711 Johns Rd Tampa FL 33634",
    "addr:housenumber":"5711",
    "addr:postcode":"33634",
    "addr:street":"Johns Rd",
    "iso:country":"US",
    "sg:address":"5711 Johns Rd",
    "sg:city":"Tampa",
    "sg:classifiers":[
        {
            "category":"Wholesale",
            "subcategory":"Motor Vehicles",
            "type":"Manufacturing & Wholesale Goods"
        },
        {
            "category":"Wholesale",
            "subcategory":"Durable Goods & Equipment",
            "type":"Manufacturing & Wholesale Goods"
        }
    ],
    "sg:phone":"+1 813 290 9818",
    "sg:postcode":"33634",
    "sg:province":"FL",
    "sg:tags":[
        "exporter",
        "export"
    ],
    "wof:name":"Spark International L L C",
    "wof:placetype":"venue"
},
  "geometry": {"coordinates":[-82.53938100000001,28.008225],"type":"Point"}
}