{
  "type": "Feature",
  "properties": {
    "iso:country":"US",
    "sg:address":"6999 NW 50th St",
    "sg:city":"Miami",
    "sg:classifiers":[
        {
            "category":"Shopping",
            "subcategory":"Florist",
            "type":"Retail Goods"
        }
    ],
    "sg:phone":"+1 305 463 9807",
    "sg:postcode":"33166",
    "sg:province":"FL",
    "wof:name":"Floral Party Wholesale",
    "wof:placetype":"venue"
},
  "geometry": {"coordinates":[-80.31099500000001,25.819061],"type":"Point"}
}