{
  "type": "Feature",
  "properties": {
    "iso:country":"US",
    "sg:address":"4914 SW 72nd Ave",
    "sg:city":"Miami",
    "sg:classifiers":[
        {
            "category":"Professional",
            "subcategory":"Engineering",
            "type":"Services"
        }
    ],
    "sg:phone":"+1 305 666 3563",
    "sg:postcode":"33155",
    "sg:province":"FL",
    "sg:tags":[
        "engineer"
    ],
    "wof:name":"Kaderabek Co",
    "wof:placetype":"venue"
},
  "geometry": {"coordinates":[-80.31078599999999,25.725624],"type":"Point"}
}