{
  "type": "Feature",
  "properties": {
    "addr:full":"1564 Eagle Nest Cir Winter Springs FL 32708",
    "addr:housenumber":"1564",
    "addr:postcode":"32708",
    "addr:street":"Eagle Nest Cir",
    "iso:country":"US",
    "sg:address":"1564 Eagle Nest Cir",
    "sg:city":"Winter Springs",
    "sg:classifiers":[
        {
            "category":"Professional",
            "subcategory":"Business Services",
            "type":"Services"
        }
    ],
    "sg:phone":"+1 407 359 3093",
    "sg:postcode":"32708",
    "sg:province":"FL",
    "wof:name":"Keystone Commercial Properties",
    "wof:placetype":"venue"
},
  "geometry": {"coordinates":[-81.237208,28.673749],"type":"Point"}
}