{
  "type": "Feature",
  "properties": {
    "addr:full":"20444 Midway Blvd Port Charlotte FL 33952",
    "addr:housenumber":"20444",
    "addr:postcode":"33952",
    "addr:street":"Midway Blvd",
    "iso:country":"US",
    "sg:address":"20444 Midway Blvd",
    "sg:city":"Port Charlotte",
    "sg:classifiers":[
        {
            "category":"Social Services",
            "type":"Services"
        }
    ],
    "sg:phone":"+1 941 629 0440",
    "sg:postcode":"33952",
    "sg:province":"FL",
    "sg:tags":[
        "counseling"
    ],
    "wof:name":"Cove Counseling",
    "wof:placetype":"venue"
},
  "geometry": {"coordinates":[-82.113213,26.996927],"type":"Point"}
}