{
  "type": "Feature",
  "properties": {
    "addr:full":"3305 Boot Bay Rd Plant City FL 33563",
    "addr:housenumber":"3305",
    "addr:postcode":"33563",
    "addr:street":"Boot Bay Rd",
    "iso:country":"US",
    "sg:address":"3305 Boot Bay Rd",
    "sg:city":"Plant City",
    "sg:classifiers":[
        {
            "category":"Building & Trades",
            "subcategory":"Construction",
            "type":"Services"
        }
    ],
    "sg:phone":"+1 813 659 2569",
    "sg:postcode":"33563",
    "sg:province":"FL",
    "sg:tags":[
        "steel",
        "erection",
        "structural"
    ],
    "wof:name":"Capitol Steel Erectors Inc",
    "wof:placetype":"venue"
},
  "geometry": {"coordinates":[-82.156691,28.025297],"type":"Point"}
}