{
  "type": "Feature",
  "properties": {
    "iso:country":"US",
    "sg:address":"1192 Juniper Ave",
    "sg:city":"Niceville",
    "sg:classifiers":[
        {
            "category":"Communications",
            "type":"Services"
        }
    ],
    "sg:phone":"+1 850 678 5290",
    "sg:postcode":"32578",
    "sg:province":"FL",
    "wof:name":"Qantum Communications",
    "wof:placetype":"venue"
},
  "geometry": {"coordinates":[-86.468221,30.516536],"type":"Point"}
}