{
  "type": "Feature",
  "properties": {
    "iso:country":"US",
    "sg:address":"2321 Hermitage Blvd",
    "sg:city":"Venice",
    "sg:classifiers":[
        {
            "category":"Professional",
            "subcategory":"Business Services",
            "type":"Services"
        }
    ],
    "sg:phone":"+1 941 475 5115",
    "sg:postcode":"34292",
    "sg:province":"FL",
    "sg:tags":[
        "interior",
        "consultant",
        "design",
        "decorator"
    ],
    "wof:name":"Dream Home Coach Inc",
    "wof:placetype":"venue"
},
  "geometry": {"coordinates":[-82.39975,27.110092],"type":"Point"}
}