{
  "type": "Feature",
  "properties": {
    "iso:country":"US",
    "sg:address":"90 Princeton Rd",
    "sg:city":"Venice",
    "sg:classifiers":[
        {
            "category":"Personal",
            "type":"Services"
        }
    ],
    "sg:phone":"+1 941 497 5290",
    "sg:postcode":"34293",
    "sg:province":"FL",
    "sg:tags":[
        "mfg"
    ],
    "wof:name":"Frost General Home Improv",
    "wof:placetype":"venue"
},
  "geometry": {"coordinates":[-82.400003,27.038691],"type":"Point"}
}