{
  "type": "Feature",
  "properties": {
    "iso:country":"US",
    "sg:address":"4085 Hancock Bridge Pkwy Ste 114",
    "sg:city":"North Fort Myers",
    "sg:classifiers":[
        {
            "category":"Personal",
            "subcategory":"Nail Salon",
            "type":"Services"
        }
    ],
    "sg:phone":"+1 239 995 2174",
    "sg:postcode":"33903",
    "sg:province":"FL",
    "wof:name":"Nail Art",
    "wof:placetype":"venue"
},
  "geometry": {"coordinates":[-81.914553,26.652419],"type":"Point"}
}