{
  "type": "Feature",
  "properties": {
    "addr:full":"1420 Pennsylvania Ave Miami Beach FL 33139",
    "addr:housenumber":"1420",
    "addr:postcode":"33139",
    "addr:street":"Pennsylvania Ave",
    "iso:country":"US",
    "sg:address":"1420 Pennsylvania Ave",
    "sg:city":"Miami Beach",
    "sg:classifiers":[
        {
            "category":"Banks & Credit Unions",
            "subcategory":"Investment Brokerage",
            "type":"Services"
        }
    ],
    "sg:phone":"+1 305 532 4076",
    "sg:postcode":"33139",
    "sg:province":"FL",
    "sg:tags":[
        "security"
    ],
    "wof:name":"Bruce J Wolfram",
    "wof:placetype":"venue"
},
  "geometry": {"coordinates":[-80.13423299999999,25.785499],"type":"Point"}
}