{
  "type": "Feature",
  "properties": {
    "iso:country":"US",
    "sg:address":"4509 Bee Ridge Rd",
    "sg:city":"Sarasota",
    "sg:classifiers":[
        {
            "category":"Shopping",
            "subcategory":"Computers & Home Electronics",
            "type":"Retail Goods"
        }
    ],
    "sg:phone":"+1 941 379 8382",
    "sg:postcode":"34233",
    "sg:province":"FL",
    "sg:tags":[
        "equipment",
        "electronic",
        "supply"
    ],
    "wof:name":"MKS Instruments",
    "wof:placetype":"venue"
},
  "geometry": {"coordinates":[-82.478762,27.298816],"type":"Point"}
}