{
  "type": "Feature",
  "properties": {
    "iso:country":"US",
    "sg:address":"6460 W Atlantic Blvd",
    "sg:city":"Margate",
    "sg:classifiers":[
        {
            "category":"Social Services",
            "subcategory":"Child Care",
            "type":"Services"
        }
    ],
    "sg:phone":"+1 954 977 9311",
    "sg:postcode":"33063",
    "sg:province":"FL",
    "wof:name":"Wexford Day Care",
    "wof:placetype":"venue"
},
  "geometry": {"coordinates":[-80.210471,26.235451],"type":"Point"}
}