{
  "type": "Feature",
  "properties": {
    "addr:full":"4217 SW 64th Ave Davie FL 33314",
    "addr:housenumber":"4217",
    "addr:postcode":"33314",
    "addr:street":"Sw 64Th Ave",
    "iso:country":"US",
    "sg:address":"4217 SW 64th Ave",
    "sg:city":"Davie",
    "sg:classifiers":[
        {
            "category":"Professional",
            "subcategory":"Detective & Security Services",
            "type":"Services"
        }
    ],
    "sg:phone":"+1 954 797 7202",
    "sg:postcode":"33314",
    "sg:province":"FL",
    "sg:tags":[
        "investigator"
    ],
    "wof:name":"Action Investigative & Prtctv",
    "wof:placetype":"venue"
},
  "geometry": {"coordinates":[-80.23232,26.069558],"type":"Point"}
}