{
  "type": "Feature",
  "properties": {
    "addr:full":"2515 Genessee Ave West Palm Beach FL 33409",
    "addr:housenumber":"2515",
    "addr:postcode":"33409",
    "addr:street":"Genessee Ave",
    "iso:country":"US",
    "sg:address":"2515 Genessee Ave",
    "sg:city":"West Palm Beach",
    "sg:classifiers":[
        {
            "category":"Building & Trades",
            "subcategory":"Electrical",
            "type":"Services"
        }
    ],
    "sg:phone":"+1 561 697 2682",
    "sg:postcode":"33409",
    "sg:province":"FL",
    "sg:tags":[
        "electric",
        "contractor"
    ],
    "wof:name":"J M Russell Electric",
    "wof:placetype":"venue"
},
  "geometry": {"coordinates":[-80.092826,26.704539],"type":"Point"}
}