{
  "type": "Feature",
  "properties": {
    "addr:full":"9831 Delray Dr New Port Richey FL 34654",
    "addr:housenumber":"9831",
    "addr:postcode":"34654",
    "addr:street":"Delray Dr",
    "iso:country":"US",
    "sg:address":"9831 Delray Dr",
    "sg:city":"New Port Richey",
    "sg:classifiers":[
        {
            "category":"Insurance",
            "subcategory":"Insurance Agent",
            "type":"Services"
        }
    ],
    "sg:phone":"+1 727 848 1636",
    "sg:postcode":"34654",
    "sg:province":"FL",
    "wof:name":"Roberts Insurance",
    "wof:placetype":"venue"
},
  "geometry": {"coordinates":[-82.65265599999999,28.272632],"type":"Point"}
}