{
  "type": "Feature",
  "properties": {
    "iso:country":"US",
    "sg:address":"3033 NW 7th Ave",
    "sg:city":"Miami",
    "sg:classifiers":[
        {
            "category":"Social Services",
            "type":"Services"
        }
    ],
    "sg:phone":"+1 305 633 5105",
    "sg:postcode":"33127",
    "sg:province":"FL",
    "sg:tags":[
        "youth",
        "center"
    ],
    "wof:name":"Miami City Mission Youth Center",
    "wof:placetype":"venue"
},
  "geometry": {"coordinates":[-80.20734899999999,25.804767],"type":"Point"}
}