{
  "type": "Feature",
  "properties": {
    "iso:country":"US",
    "sg:address":"13196 SW 49th Ct",
    "sg:city":"Hollywood",
    "sg:classifiers":[
        {
            "category":"Shopping",
            "subcategory":"Clothing, Apparel, & Fashions",
            "type":"Retail Goods"
        }
    ],
    "sg:phone":"+1 305 829 0217",
    "sg:postcode":"33027",
    "sg:province":"FL",
    "sg:tags":[
        "woman",
        "accessory"
    ],
    "wof:name":"Spring Love Too",
    "wof:placetype":"venue"
},
  "geometry": {"coordinates":[-80.321664,25.963154],"type":"Point"}
}