{
  "type": "Feature",
  "properties": {
    "iso:country":"US",
    "sg:address":"2700 Pine Ridge Rd",
    "sg:city":"Naples",
    "sg:classifiers":[
        {
            "category":"Personal",
            "type":"Services"
        }
    ],
    "sg:phone":"+1 239 352 8200",
    "sg:postcode":"34109",
    "sg:province":"FL",
    "sg:tags":[
        "program",
        "physical",
        "exercise",
        "fitness"
    ],
    "wof:name":"Thyme & Heart Massage",
    "wof:placetype":"venue"
},
  "geometry": {"coordinates":[-81.76396699999999,26.211686],"type":"Point"}
}