{
  "type": "Feature",
  "properties": {
    "iso:country":"US",
    "sg:address":"9505 SW 40th St",
    "sg:city":"Miami",
    "sg:classifiers":[
        {
            "category":"Retail",
            "subcategory":"Repair Shop",
            "type":"Services"
        }
    ],
    "sg:phone":"+1 305 552 5156",
    "sg:postcode":"33165",
    "sg:province":"FL",
    "wof:name":"Gerrys Locksmith",
    "wof:placetype":"venue"
},
  "geometry": {"coordinates":[-80.34968000000001,25.732846],"type":"Point"}
}