{
  "type": "Feature",
  "properties": {
    "addr:full":"2225 J and C Blvd Naples FL 34109",
    "addr:housenumber":"2225;and",
    "addr:postcode":"34109",
    "addr:street":"C Blvd",
    "iso:country":"US",
    "sg:address":"2225 J and C Blvd",
    "sg:city":"Naples",
    "sg:classifiers":[
        {
            "category":"Retail",
            "subcategory":"Auto Repair",
            "type":"Services"
        }
    ],
    "sg:phone":"+1 239 592 0511",
    "sg:postcode":"34109",
    "sg:province":"FL",
    "sg:tags":[
        "repairing",
        "automobile"
    ],
    "wof:name":"Rick's Automotive Svc",
    "wof:placetype":"venue"
},
  "geometry": {"coordinates":[-81.77131,26.223993],"type":"Point"}
}