{
  "type": "Feature",
  "properties": {
    "iso:country":"US",
    "sg:address":"240 SW 33rd Ct",
    "sg:city":"Fort Lauderdale",
    "sg:classifiers":[
        {
            "category":"Manufacturing",
            "subcategory":"Toys & Sporting Goods",
            "type":"Manufacturing & Wholesale Goods"
        },
        {
            "category":"Manufacturing",
            "subcategory":"Watercraft",
            "type":"Manufacturing & Wholesale Goods"
        }
    ],
    "sg:phone":"+1 954 522 4238",
    "sg:postcode":"33315",
    "sg:province":"FL",
    "sg:tags":[
        "supply",
        "mfg",
        "equipment",
        "fishing",
        "chair",
        "boat"
    ],
    "sg:website":"www.bluewaterchairs.com",
    "wof:name":"Blue Water Chairs & Tackle Inc",
    "wof:placetype":"venue"
},
  "geometry": {"coordinates":[-80.142922,26.082492],"type":"Point"}
}