{
  "type": "Feature",
  "properties": {
    "addr:full":"5665 Coral Ridge Dr Coral Springs FL 33076",
    "addr:housenumber":"5665",
    "addr:postcode":"33076",
    "addr:street":"Coral Ridge Dr",
    "iso:country":"US",
    "sg:address":"5665 Coral Ridge Dr",
    "sg:city":"Coral Springs",
    "sg:classifiers":[
        {
            "category":"Shopping",
            "subcategory":"Bicycles & Sporting Goods",
            "type":"Retail Goods"
        }
    ],
    "sg:phone":"+1 954 255 2639",
    "sg:postcode":"33076",
    "sg:province":"FL",
    "sg:tags":[
        "equipment",
        "exercise"
    ],
    "wof:name":"All Bodies Home Fitness",
    "wof:placetype":"venue"
},
  "geometry": {"coordinates":[-80.27882,26.30001],"type":"Point"}
}