{
  "type": "Feature",
  "properties": {
    "iso:country":"US",
    "sg:address":"7359 NW 34th St",
    "sg:city":"Miami",
    "sg:classifiers":[
        {
            "category":"Wholesale",
            "subcategory":"Durable Goods & Equipment",
            "type":"Manufacturing & Wholesale Goods"
        }
    ],
    "sg:phone":"+1 305 591 8910",
    "sg:postcode":"33122",
    "sg:province":"FL",
    "sg:tags":[
        "exporter"
    ],
    "wof:name":"Kyoto Corp",
    "wof:placetype":"venue"
},
  "geometry": {"coordinates":[-80.316642,25.805397],"type":"Point"}
}