{
  "type": "Feature",
  "properties": {
    "iso:country":"US",
    "sg:address":"7325 NW 20th Ct",
    "sg:city":"Fort Lauderdale",
    "sg:classifiers":[
        {
            "category":"Freight",
            "type":"Transportation"
        }
    ],
    "sg:phone":"+1 954 748 4513",
    "sg:postcode":"33313",
    "sg:province":"FL",
    "sg:tags":[
        "operator",
        "local",
        "trucking"
    ],
    "wof:name":"Star K Trucking Inc",
    "wof:placetype":"venue"
},
  "geometry": {"coordinates":[-80.241777,26.15129],"type":"Point"}
}