{
  "type": "Feature",
  "properties": {
    "iso:country":"US",
    "sg:address":"8526 Pinto Dr",
    "sg:city":"Lake Worth",
    "sg:classifiers":[
        {
            "category":"Building & Trades",
            "subcategory":"Construction",
            "type":"Services"
        }
    ],
    "sg:phone":"+1 561 432 9742",
    "sg:postcode":"33467",
    "sg:province":"FL",
    "sg:tags":[
        "heavy"
    ],
    "wof:name":"Championship Golf Svcs & Sup",
    "wof:placetype":"venue"
},
  "geometry": {"coordinates":[-80.18188499999999,26.625968],"type":"Point"}
}