{
  "type": "Feature",
  "properties": {
    "addr:full":"13230 Polo Club Rd Wellington FL 33414",
    "addr:housenumber":"13230",
    "addr:postcode":"33414",
    "addr:street":"Polo Club Rd",
    "iso:country":"US",
    "sg:address":"13230 Polo Club Rd",
    "sg:city":"Wellington",
    "sg:classifiers":[
        {
            "category":"Professional",
            "type":"Services"
        }
    ],
    "sg:phone":"+1 561 793 5840",
    "sg:postcode":"33414",
    "sg:province":"FL",
    "sg:tags":[
        "establishment"
    ],
    "wof:name":"B J's Hunt Room",
    "wof:placetype":"venue"
},
  "geometry": {"coordinates":[-80.256067,26.64172],"type":"Point"}
}