{
  "type": "Feature",
  "properties": {
    "iso:country":"US",
    "sg:address":"3180 Coastal Hwy",
    "sg:city":"Crawfordville",
    "sg:classifiers":[
        {
            "category":"Banks & Credit Unions",
            "subcategory":"Investment Brokerage",
            "type":"Services"
        }
    ],
    "sg:phone":"+1 850 926 7797",
    "sg:postcode":"32327",
    "sg:province":"FL",
    "sg:tags":[
        "advisory",
        "financial"
    ],
    "wof:name":"Tatm Financial Systems",
    "wof:placetype":"venue"
},
  "geometry": {"coordinates":[-84.38026000000001,30.10487],"type":"Point"}
}