{
  "type": "Feature",
  "properties": {
    "iso:country":"US",
    "sg:address":"215 W Hibiscus Blvd",
    "sg:city":"Melbourne",
    "sg:classifiers":[
        {
            "category":"Restaurant",
            "type":"Food & Drink"
        }
    ],
    "sg:phone":"+1 321 724 8399",
    "sg:postcode":"32901",
    "sg:province":"FL",
    "sg:tags":[
        "eating"
    ],
    "wof:name":"Billy-Joe's Wings",
    "wof:placetype":"venue"
},
  "geometry": {"coordinates":[-80.627032,28.08517],"type":"Point"}
}