{
  "type": "Feature",
  "properties": {
    "iso:country":"US",
    "sg:address":"3780 Kori Rd",
    "sg:city":"Jacksonville",
    "sg:classifiers":[
        {
            "category":"Personal",
            "subcategory":"Beauty Salon",
            "type":"Services"
        }
    ],
    "sg:phone":"+1 904 880 5202",
    "sg:postcode":"32257",
    "sg:province":"FL",
    "wof:name":"Debi's",
    "wof:placetype":"venue"
},
  "geometry": {"coordinates":[-81.61602600000001,30.20048],"type":"Point"}
}