{
  "type": "Feature",
  "properties": {
    "addr:full":"2801 NW 74th Ave Miami FL 33122",
    "addr:housenumber":"2801",
    "addr:postcode":"33122",
    "addr:street":"Nw 74Th Ave",
    "iso:country":"US",
    "sg:address":"2801 NW 74th Ave",
    "sg:city":"Miami",
    "sg:classifiers":[
        {
            "category":"Freight",
            "type":"Transportation"
        }
    ],
    "sg:phone":"+1 305 593 0642",
    "sg:postcode":"33122",
    "sg:province":"FL",
    "wof:name":"Benson's Forwarding Svc",
    "wof:placetype":"venue"
},
  "geometry": {"coordinates":[-80.316979,25.801925],"type":"Point"}
}