{
  "type": "Feature",
  "properties": {
    "iso:country":"US",
    "sg:address":"3655 NW 78th Ave",
    "sg:city":"Doral",
    "sg:classifiers":[
        {
            "category":"Home & Garden",
            "subcategory":"Furniture",
            "type":"Retail Goods"
        }
    ],
    "sg:phone":"+1 305 436 7322",
    "sg:postcode":"33166",
    "sg:province":"FL",
    "sg:tags":[
        "store"
    ],
    "wof:name":"Solare Furniture",
    "wof:placetype":"venue"
},
  "geometry": {"coordinates":[-80.323392,25.807676],"type":"Point"}
}