{
  "type": "Feature",
  "properties": {
    "iso:country":"US",
    "sg:address":"4095 SE 38th Loop",
    "sg:city":"Ocala",
    "sg:classifiers":[
        {
            "category":"Building & Trades",
            "subcategory":"Construction",
            "type":"Services"
        }
    ],
    "sg:phone":"+1 352 624 2928",
    "sg:postcode":"34480",
    "sg:province":"FL",
    "sg:tags":[
        "equipment",
        "supply",
        "drywall",
        "contractor"
    ],
    "wof:name":"Drywall Assemblies",
    "wof:placetype":"venue"
},
  "geometry": {"coordinates":[-82.083843,29.146311],"type":"Point"}
}