{
  "type": "Feature",
  "properties": {
    "iso:country":"US",
    "sg:address":"2020 S Parrott Ave Frnt",
    "sg:city":"Okeechobee",
    "sg:classifiers":[
        {
            "category":"Real Estate",
            "subcategory":"Real Estate Services",
            "type":"Services"
        },
        {
            "category":"Real Estate",
            "subcategory":"Real Estate Agent",
            "type":"Services"
        }
    ],
    "sg:phone":"+1 863 467 1446",
    "sg:postcode":"34974",
    "sg:province":"FL",
    "sg:tags":[
        "buyer",
        "broker"
    ],
    "wof:name":"Lawrence Real Estate Co",
    "wof:placetype":"venue"
},
  "geometry": {"coordinates":[-80.829948,27.224751],"type":"Point"}
}