{
  "type": "Feature",
  "properties": {
    "iso:country":"US",
    "sg:address":"2310 S Harbor City Blvd",
    "sg:city":"Melbourne",
    "sg:classifiers":[
        {
            "category":"Personal",
            "subcategory":"Barber",
            "type":"Services"
        }
    ],
    "sg:phone":"+1 321 729 9720",
    "sg:postcode":"32901",
    "sg:province":"FL",
    "wof:name":"Constance Barber Shop",
    "wof:placetype":"venue"
},
  "geometry": {"coordinates":[-80.601534,28.073611],"type":"Point"}
}