{
  "type": "Feature",
  "properties": {
    "addr:full":"2813 Bay Tree Ln Tallahassee FL 32301",
    "addr:housenumber":"2813",
    "addr:postcode":"32301",
    "addr:street":"Bay Tree Ln",
    "iso:country":"US",
    "sg:address":"2813 Bay Tree Ln",
    "sg:city":"Tallahassee",
    "sg:classifiers":[
        {
            "category":"Building & Trades",
            "subcategory":"Construction",
            "type":"Services"
        }
    ],
    "sg:phone":"+1 850 878 1328",
    "sg:postcode":"32301",
    "sg:province":"FL",
    "sg:tags":[
        "painter"
    ],
    "wof:name":"Grady Owens Enterprises",
    "wof:placetype":"venue"
},
  "geometry": {"coordinates":[-84.237696,30.431715],"type":"Point"}
}