{
  "type": "Feature",
  "properties": {
    "addr:full":"15202 Livingston Ave Lutz FL 33559",
    "addr:housenumber":"15202",
    "addr:postcode":"33559",
    "addr:street":"Livingston Ave",
    "iso:country":"US",
    "sg:address":"15202 Livingston Ave",
    "sg:city":"Lutz",
    "sg:classifiers":[
        {
            "category":"Food & Beverages",
            "subcategory":"Groceries & Convenience Stores",
            "type":"Retail Goods"
        }
    ],
    "sg:phone":"+1 813 977 8211",
    "sg:postcode":"33559",
    "sg:province":"FL",
    "wof:name":"S N R Inc",
    "wof:placetype":"venue"
},
  "geometry": {"coordinates":[-82.430763,28.091519],"type":"Point"}
}