{
  "type": "Feature",
  "properties": {
    "addr:full":"3901 W Sunrise Blvd Fort Lauderdale FL 33311",
    "addr:housenumber":"3901",
    "addr:postcode":"33311",
    "addr:street":"W Sunrise Blvd",
    "iso:country":"US",
    "sg:address":"3901 W Sunrise Blvd",
    "sg:city":"Fort Lauderdale",
    "sg:classifiers":[
        {
            "category":"Freight",
            "type":"Transportation"
        }
    ],
    "sg:phone":"+1 954 583 0880",
    "sg:postcode":"33311",
    "sg:province":"FL",
    "sg:tags":[
        "general"
    ],
    "wof:name":"Extra Space Storage Rentals",
    "wof:placetype":"venue"
},
  "geometry": {"coordinates":[-80.204612,26.136001],"type":"Point"}
}