{
  "type": "Feature",
  "properties": {
    "addr:full":"1972 State Rd 44 New Smyrna Beach FL 32168",
    "addr:housenumber":"1972;44",
    "addr:postcode":"32168",
    "addr:street":"State Rd",
    "iso:country":"US",
    "sg:address":"1972 State Rd 44",
    "sg:city":"New Smyrna Beach",
    "sg:classifiers":[
        {
            "category":"Shopping",
            "type":"Retail Goods"
        }
    ],
    "sg:phone":"+1 386 426 5069",
    "sg:postcode":"32168",
    "sg:province":"FL",
    "sg:tags":[
        "wheel",
        "chair",
        "scooter"
    ],
    "wof:name":"Scooter Mobility Ctr Inc",
    "wof:placetype":"venue"
},
  "geometry": {"coordinates":[-80.946192,29.013523],"type":"Point"}
}