{
  "type": "Feature",
  "properties": {
    "iso:country":"US",
    "sg:address":"451 NW 87th Ln",
    "sg:city":"Plantation",
    "sg:classifiers":[
        {
            "category":"Building & Trades",
            "subcategory":"Landscaping Services",
            "type":"Services"
        }
    ],
    "sg:phone":"+1 954 452 9996",
    "sg:postcode":"33324",
    "sg:province":"FL",
    "sg:tags":[
        "tree"
    ],
    "wof:name":"Affordable Treemen",
    "wof:placetype":"venue"
},
  "geometry": {"coordinates":[-80.265108,26.124833],"type":"Point"}
}