{
  "type": "Feature",
  "properties": {
    "addr:full":"9703 S Dixie Hwy Ste 14 Miami FL 33156",
    "addr:housenumber":"9703",
    "addr:postcode":"33156",
    "addr:street":"S Dixie Hwy Ste 14",
    "iso:country":"US",
    "sg:address":"9703 S Dixie Hwy Ste 14",
    "sg:city":"Miami",
    "sg:classifiers":[
        {
            "category":"Shopping",
            "subcategory":"Gifts & Souvenirs",
            "type":"Retail Goods"
        },
        {
            "category":"Shopping",
            "subcategory":"Jewelry",
            "type":"Retail Goods"
        },
        {
            "category":"Manufacturing",
            "subcategory":"Jewelry",
            "type":"Manufacturing & Wholesale Goods"
        }
    ],
    "sg:phone":"+1 305 666 6193",
    "sg:postcode":"33156",
    "sg:province":"FL",
    "sg:tags":[
        "shop",
        "designer",
        "jewelers-wholesale",
        "jeweler",
        "manufacturer"
    ],
    "wof:name":"Enchanted Mesa Trading Company",
    "wof:placetype":"venue"
},
  "geometry": {"coordinates":[-80.316856,25.67963],"type":"Point"}
}