{
  "type": "Feature",
  "properties": {
    "iso:country":"US",
    "sg:address":"5200 Seminole Blvd",
    "sg:city":"St Petersburg",
    "sg:classifiers":[
        {
            "category":"Banks & Credit Unions",
            "subcategory":"Bank",
            "type":"Services"
        }
    ],
    "sg:phone":"+1 727 319 4800",
    "sg:postcode":"33708",
    "sg:province":"FL",
    "sg:tags":[
        "loan",
        "real estate"
    ],
    "wof:name":"Mallbanc Mortgage",
    "wof:placetype":"venue"
},
  "geometry": {"coordinates":[-82.78709499999999,27.819059],"type":"Point"}
}