{
  "type": "Feature",
  "properties": {
    "addr:full":"411 S Old County Rd Edgewater FL 32132",
    "addr:housenumber":"411",
    "addr:postcode":"32132",
    "addr:street":"S Old County Rd",
    "iso:country":"US",
    "sg:address":"411 S Old County Rd",
    "sg:city":"Edgewater",
    "sg:classifiers":[
        {
            "category":"Retail",
            "subcategory":"Repair Shop",
            "type":"Services"
        }
    ],
    "sg:phone":"+1 386 427 0912",
    "sg:postcode":"32132",
    "sg:province":"FL",
    "sg:tags":[
        "related"
    ],
    "wof:name":"A & M Repairs",
    "wof:placetype":"venue"
},
  "geometry": {"coordinates":[-80.90910100000001,28.986153],"type":"Point"}
}