{
  "type": "Feature",
  "properties": {
    "iso:country":"US",
    "sg:address":"1930 Thacker Ave",
    "sg:city":"Jacksonville",
    "sg:classifiers":[
        {
            "category":"Shopping",
            "subcategory":"Computers & Home Electronics",
            "type":"Retail Goods"
        }
    ],
    "sg:phone":"+1 904 396 9086",
    "sg:postcode":"32207",
    "sg:province":"FL",
    "sg:tags":[
        "equipment",
        "dealer"
    ],
    "wof:name":"Deskin Wood Computer Svc",
    "wof:placetype":"venue"
},
  "geometry": {"coordinates":[-81.65316799999999,30.306885],"type":"Point"}
}