{
  "type": "Feature",
  "properties": {
    "addr:full":"15701 Mifflin Ct Tampa FL 33647",
    "addr:postcode":"15701;33647",
    "addr:street":"Mifflin Ct",
    "iso:country":"US",
    "sg:address":"15701 Mifflin Ct",
    "sg:city":"Tampa",
    "sg:classifiers":[
        {
            "category":"Shopping",
            "subcategory":"Computers & Home Electronics",
            "type":"Retail Goods"
        }
    ],
    "sg:phone":"+1 813 631 8975",
    "sg:postcode":"33647",
    "sg:province":"FL",
    "sg:tags":[
        "software"
    ],
    "wof:name":"Bea Systems",
    "wof:placetype":"venue"
},
  "geometry": {"coordinates":[-82.372912,28.09295],"type":"Point"}
}