{
  "type": "Feature",
  "properties": {
    "addr:full":"10019 N Dale Mabry Hwy Tampa FL 33618",
    "addr:housenumber":"10019",
    "addr:postcode":"33618",
    "addr:street":"N Dale Mabry Hwy",
    "iso:country":"US",
    "sg:address":"10019 N Dale Mabry Hwy",
    "sg:city":"Tampa",
    "sg:classifiers":[
        {
            "category":"Personal",
            "subcategory":"Beauty Salon",
            "type":"Services"
        }
    ],
    "sg:phone":"+1 813 961 8969",
    "sg:postcode":"33618",
    "sg:province":"FL",
    "sg:tags":[
        "manicuring"
    ],
    "wof:name":"New York Nails",
    "wof:placetype":"venue"
},
  "geometry": {"coordinates":[-82.504599,28.043132],"type":"Point"}
}