{
  "type": "Feature",
  "properties": {
    "iso:country":"US",
    "sg:address":"405 Hibiscus Ave",
    "sg:city":"Pompano Beach",
    "sg:classifiers":[
        {
            "category":"Manufacturing",
            "subcategory":"Signs",
            "type":"Manufacturing & Wholesale Goods"
        }
    ],
    "sg:phone":"+1 954 781 8965",
    "sg:postcode":"33062",
    "sg:province":"FL",
    "sg:tags":[
        "mfg",
        "advertising",
        "specialty"
    ],
    "sg:website":"www.signsthatworkinc.com",
    "wof:name":"Signs That Work Inc",
    "wof:placetype":"venue"
},
  "geometry": {"coordinates":[-80.092533,26.228222],"type":"Point"}
}