{
  "type": "Feature",
  "properties": {
    "iso:country":"US",
    "sg:address":"4479 Edgewater Dr",
    "sg:city":"Orlando",
    "sg:classifiers":[
        {
            "category":"Retail",
            "subcategory":"Repair Shop",
            "type":"Services"
        }
    ],
    "sg:phone":"+1 407 822 0905",
    "sg:postcode":"32804",
    "sg:province":"FL",
    "sg:tags":[
        "reupholstery",
        "refinishing",
        "furniture"
    ],
    "sg:website":"http://www.realpages.com/sites/ajimasookupholst",
    "wof:name":"Ajimasook Upholstery",
    "wof:placetype":"venue"
},
  "geometry": {"coordinates":[-81.4021,28.599701],"type":"Point"}
}