{
  "type": "Feature",
  "properties": {
    "iso:country":"US",
    "sg:address":"18392 Lee Ave",
    "sg:city":"Brooksville",
    "sg:classifiers":[
        {
            "category":"Retail",
            "subcategory":"Repair Shop",
            "type":"Services"
        }
    ],
    "sg:phone":"+1 352 540 9474",
    "sg:postcode":"34601",
    "sg:province":"FL",
    "sg:tags":[
        "repairing",
        "piano",
        "refinishing"
    ],
    "wof:name":"Brian S Cross",
    "wof:placetype":"venue"
},
  "geometry": {"coordinates":[-82.423528,28.553782],"type":"Point"}
}