{
  "type": "Feature",
  "properties": {
    "addr:full":"8491 US Hwy 1 Port Saint Lucie FL 34982",
    "addr:housenumber":"8491",
    "addr:postcode":"34982",
    "addr:street":"Us Hwy 1",
    "iso:country":"US",
    "sg:address":"8491 US Hwy 1",
    "sg:city":"Port Saint Lucie",
    "sg:classifiers":[
        {
            "category":"Health Services",
            "subcategory":"Doctor",
            "type":"Services"
        }
    ],
    "sg:phone":"+1 772 878 3000",
    "sg:postcode":"34982",
    "sg:province":"FL",
    "sg:tags":[
        "medical"
    ],
    "wof:name":"Lazaro Completo MD",
    "wof:placetype":"venue"
},
  "geometry": {"coordinates":[-80.313501,27.314376],"type":"Point"}
}