{
  "type": "Feature",
  "properties": {
    "iso:country":"US",
    "sg:address":"1234 Orton St",
    "sg:city":"Jacksonville",
    "sg:classifiers":[
        {
            "category":"Building & Trades",
            "subcategory":"Cleaning & Sanitation",
            "type":"Services"
        }
    ],
    "sg:phone":"+1 904 389 8990",
    "sg:postcode":"32205",
    "sg:province":"FL",
    "sg:tags":[
        "ventilating",
        "system"
    ],
    "wof:name":"IAQ Specialists",
    "wof:placetype":"venue"
},
  "geometry": {"coordinates":[-81.74270199999999,30.302973],"type":"Point"}
}