{
  "type": "Feature",
  "properties": {
    "addr:full":"3460 6th Ave NE Naples FL 34120",
    "addr:housenumber":"3460",
    "addr:postcode":"34120",
    "addr:street":"6Th Ave Ne",
    "iso:country":"US",
    "sg:address":"3460 6th Ave NE",
    "sg:city":"Naples",
    "sg:classifiers":[
        {
            "category":"Building & Trades",
            "subcategory":"Landscaping Services",
            "type":"Services"
        }
    ],
    "sg:phone":"+1 239 352 8032",
    "sg:postcode":"34120",
    "sg:province":"FL",
    "wof:name":"Nadotti S Lawn Service",
    "wof:placetype":"venue"
},
  "geometry": {"coordinates":[-81.5287,26.241685],"type":"Point"}
}