{
  "type": "Feature",
  "properties": {
    "iso:country":"US",
    "sg:address":"2679 New Effort Church Rd",
    "sg:city":"Bonifay",
    "sg:classifiers":[
        {
            "category":"Place Of Worship",
            "type":"Public Place"
        }
    ],
    "sg:phone":"+1 850 547 2996",
    "sg:postcode":"32425",
    "sg:province":"FL",
    "sg:tags":[
        "church"
    ],
    "wof:name":"New Effort Church",
    "wof:placetype":"venue"
},
  "geometry": {"coordinates":[-85.754547,30.792587],"type":"Point"}
}