{
  "type": "Feature",
  "properties": {
    "addr:full":"10425 SW 112th St Miami FL 33176",
    "addr:housenumber":"10425",
    "addr:postcode":"33176",
    "addr:street":"Sw 112Th St",
    "iso:country":"US",
    "sg:address":"10425 SW 112th St",
    "sg:city":"Miami",
    "sg:classifiers":[
        {
            "category":"Manufacturing",
            "subcategory":"Tools & Machinery",
            "type":"Manufacturing & Wholesale Goods"
        }
    ],
    "sg:phone":"+1 305 971 7380",
    "sg:postcode":"33176",
    "sg:province":"FL",
    "sg:tags":[
        "computer"
    ],
    "sg:website":"www.platinum-electronics.com",
    "wof:name":"Platinum Electronics",
    "wof:placetype":"venue"
},
  "geometry": {"coordinates":[-80.363435,25.665125],"type":"Point"}
}