{
  "type": "Feature",
  "properties": {
    "iso:country":"US",
    "sg:address":"1400 Royal Palm Square Blvd Ste 101",
    "sg:city":"Fort Myers",
    "sg:classifiers":[
        {
            "category":"Health Services",
            "subcategory":"Dentist",
            "type":"Services"
        }
    ],
    "sg:phone":"+1 239 939 2433",
    "sg:postcode":"33919",
    "sg:province":"FL",
    "wof:name":"Plummer Richard W Jr DMD",
    "wof:placetype":"venue"
},
  "geometry": {"coordinates":[-81.883819,26.59418],"type":"Point"}
}