{
  "type": "Feature",
  "properties": {
    "iso:country":"US",
    "sg:address":"1399 NW 17th Ave",
    "sg:city":"Miami",
    "sg:classifiers":[
        {
            "category":"Wholesale",
            "subcategory":"Medical Equipment & Supplies",
            "type":"Manufacturing & Wholesale Goods"
        }
    ],
    "sg:phone":"+1 305 547 1600",
    "sg:postcode":"33125",
    "sg:province":"FL",
    "sg:tags":[
        "physician",
        "surgeon"
    ],
    "wof:name":"MNM Medical Equipment",
    "wof:placetype":"venue"
},
  "geometry": {"coordinates":[-80.22294599999999,25.786925],"type":"Point"}
}