{
  "type": "Feature",
  "properties": {
    "addr:full":"13879 78th Pl N West Palm Beach FL 33412",
    "addr:housenumber":"13879",
    "addr:postcode":"33412",
    "addr:street":"78Th Pl N",
    "iso:country":"US",
    "sg:address":"13879 78th Pl N",
    "sg:city":"West Palm Beach",
    "sg:classifiers":[
        {
            "category":"Building & Trades",
            "subcategory":"Construction",
            "type":"Services"
        }
    ],
    "sg:phone":"+1 561 333 3160",
    "sg:postcode":"33412",
    "sg:province":"FL",
    "sg:tags":[
        "residential"
    ],
    "wof:name":"B Catoe Enterprise Inc",
    "wof:placetype":"venue"
},
  "geometry": {"coordinates":[-80.259168,26.792622],"type":"Point"}
}