{
  "type": "Feature",
  "properties": {
    "iso:country":"US",
    "sg:address":"14752 SW 143rd Ter",
    "sg:city":"Miami",
    "sg:classifiers":[
        {
            "category":"Professional",
            "type":"Services"
        }
    ],
    "sg:phone":"+1 305 233 8543",
    "sg:postcode":"33196",
    "sg:province":"FL",
    "wof:name":"Indaya Corp",
    "wof:placetype":"venue"
},
  "geometry": {"coordinates":[-80.43199,25.633579],"type":"Point"}
}