{
  "type": "Feature",
  "properties": {
    "iso:country":"US",
    "sg:address":"1801 Arlington St",
    "sg:city":"Sarasota",
    "sg:classifiers":[
        {
            "category":"Health Services",
            "subcategory":"Doctor",
            "type":"Services"
        },
        {
            "category":"Health Services",
            "subcategory":"Medical Lab",
            "type":"Services"
        }
    ],
    "sg:phone":"+1 941 917 8365",
    "sg:postcode":"34239",
    "sg:province":"FL",
    "sg:tags":[
        "laboratory",
        "surgeon",
        "physician"
    ],
    "wof:name":"Caballero Carolos F MD",
    "wof:placetype":"venue"
},
  "geometry": {"coordinates":[-82.53173,27.317335],"type":"Point"}
}