{
  "type": "Feature",
  "properties": {
    "addr:full":"888 Biscayne Blvd Miami FL 33132",
    "addr:housenumber":"888",
    "addr:postcode":"33132",
    "addr:street":"Biscayne Blvd",
    "iso:country":"US",
    "sg:address":"888 Biscayne Blvd",
    "sg:city":"Miami",
    "sg:classifiers":[
        {
            "category":"Real Estate",
            "subcategory":"Real Estate Services",
            "type":"Services"
        },
        {
            "category":"Building & Trades",
            "subcategory":"Construction",
            "type":"Services"
        }
    ],
    "sg:phone":"+1 305 347 5340",
    "sg:postcode":"33132",
    "sg:province":"FL",
    "sg:tags":[
        "management",
        "condominium"
    ],
    "wof:name":"Marina Blue Condominium Association",
    "wof:placetype":"venue"
},
  "geometry": {"coordinates":[-80.18955200000001,25.782845],"type":"Point"}
}