{
  "type": "Feature",
  "properties": {
    "addr:full":"430 A St Saint Augustine FL 32080",
    "addr:housenumber":"430",
    "addr:postcode":"32080",
    "addr:street":"A St",
    "iso:country":"US",
    "sg:address":"430 A St",
    "sg:city":"Saint Augustine",
    "sg:classifiers":[
        {
            "category":"Travel",
            "subcategory":"Hotels & Motels",
            "type":"Entertainment"
        }
    ],
    "sg:phone":"+1 904 471 4000",
    "sg:postcode":"32080",
    "sg:province":"FL",
    "sg:tags":[
        "operation"
    ],
    "wof:name":"Hampton Inn",
    "wof:placetype":"venue"
},
  "geometry": {"coordinates":[-81.272727,29.844668],"type":"Point"}
}