{
  "type": "Feature",
  "properties": {
    "iso:country":"US",
    "sg:address":"7410 Becky Thatcher Ln",
    "sg:city":"Tampa",
    "sg:classifiers":[
        {
            "category":"Retail",
            "subcategory":"Car Wash",
            "type":"Services"
        }
    ],
    "sg:phone":"+1 813 984 7894",
    "sg:postcode":"33637",
    "sg:province":"FL",
    "sg:tags":[
        "carwash"
    ],
    "wof:name":"Strong Arm Power Wash",
    "wof:placetype":"venue"
},
  "geometry": {"coordinates":[-82.37127700000001,28.020022],"type":"Point"}
}