{
  "type": "Feature",
  "properties": {
    "addr:full":"2255 Glades Rd Boca Raton FL 33431",
    "addr:housenumber":"2255",
    "addr:postcode":"33431",
    "addr:street":"Glades Rd",
    "iso:country":"US",
    "sg:address":"2255 Glades Rd",
    "sg:city":"Boca Raton",
    "sg:classifiers":[
        {
            "category":"Banks & Credit Unions",
            "subcategory":"Bank",
            "type":"Services"
        }
    ],
    "sg:phone":"+1 561 000 1111",
    "sg:postcode":"33431",
    "sg:province":"FL",
    "wof:name":"Bank Of America",
    "wof:placetype":"venue"
},
  "geometry": {"coordinates":[-80.12821599999999,26.368249],"type":"Point"}
}