{
  "type": "Feature",
  "properties": {
    "addr:full":"903 W Midway Rd Fort Pierce FL 34982",
    "addr:housenumber":"903",
    "addr:postcode":"34982",
    "addr:street":"W Midway Rd",
    "iso:country":"US",
    "sg:address":"903 W Midway Rd",
    "sg:city":"Fort Pierce",
    "sg:classifiers":[
        {
            "category":"Organizations",
            "subcategory":"Religious Organization",
            "type":"Services"
        }
    ],
    "sg:phone":"+1 772 464 3869",
    "sg:postcode":"34982",
    "sg:province":"FL",
    "sg:tags":[
        "church"
    ],
    "wof:name":"First Baptist Church",
    "wof:placetype":"venue"
},
  "geometry": {"coordinates":[-80.33584399999999,27.374243],"type":"Point"}
}