{
  "type": "Feature",
  "properties": {
    "iso:country":"US",
    "sg:address":"17589 Jamestown Way",
    "sg:city":"Lutz",
    "sg:classifiers":[
        {
            "category":"Manufacturing",
            "subcategory":"Petroleum Products",
            "type":"Manufacturing & Wholesale Goods"
        }
    ],
    "sg:phone":"+1 813 326 2579",
    "sg:postcode":"33558",
    "sg:province":"FL",
    "sg:tags":[
        "contract"
    ],
    "wof:name":"Wooden Built Industries",
    "wof:placetype":"venue"
},
  "geometry": {"coordinates":[-82.542507,28.135855],"type":"Point"}
}