{
  "type": "Feature",
  "properties": {
    "iso:country":"US",
    "sg:address":"1410 Nieuport Ln",
    "sg:city":"Orlando",
    "sg:classifiers":[
        {
            "category":"Organizations",
            "subcategory":"Religious Organization",
            "type":"Services"
        }
    ],
    "sg:phone":"+1 407 447 5993",
    "sg:postcode":"32805",
    "sg:province":"FL",
    "sg:tags":[
        "church"
    ],
    "wof:name":"Revival Temple Inc",
    "wof:placetype":"venue"
},
  "geometry": {"coordinates":[-81.391981,28.523849],"type":"Point"}
}