{
  "type": "Feature",
  "properties": {
    "addr:full":"4004 Niles Way Saint Cloud FL 34769",
    "addr:housenumber":"4004",
    "addr:postcode":"34769",
    "addr:street":"Niles Way",
    "iso:country":"US",
    "sg:address":"4004 Niles Way",
    "sg:city":"Saint Cloud",
    "sg:classifiers":[
        {
            "category":"Building & Trades",
            "subcategory":"Landscaping Services",
            "type":"Services"
        }
    ],
    "sg:phone":"+1 407 892 2459",
    "sg:postcode":"34769",
    "sg:province":"FL",
    "wof:name":"Maintenance Mike",
    "wof:placetype":"venue"
},
  "geometry": {"coordinates":[-81.31497299999999,28.237109],"type":"Point"}
}