{
  "type": "Feature",
  "properties": {
    "addr:full":"894 US Hwy 98 Destin FL 32541",
    "addr:housenumber":"894",
    "addr:postcode":"32541",
    "addr:street":"Us Hwy 98",
    "iso:country":"US",
    "sg:address":"894 US Hwy 98",
    "sg:city":"Destin",
    "sg:classifiers":[
        {
            "category":"Real Estate",
            "subcategory":"Real Estate Agent",
            "type":"Services"
        }
    ],
    "sg:phone":"+1 850 650 6277",
    "sg:postcode":"32541",
    "sg:province":"FL",
    "wof:name":"Rick Basham",
    "wof:placetype":"venue"
},
  "geometry": {"coordinates":[-86.48334199999999,30.389454],"type":"Point"}
}