{
  "type": "Feature",
  "properties": {
    "iso:country":"US",
    "sg:address":"17509 N Palms Village Pl",
    "sg:city":"Tampa",
    "sg:classifiers":[
        {
            "category":"Ice Cream",
            "type":"Food & Drink"
        }
    ],
    "sg:menulink":"http://www.allmenus.com/fl/thonotosassa/92395-steak-n-shake/menu/",
    "sg:phone":"+1 813 978 8819",
    "sg:postcode":"33647",
    "sg:province":"FL",
    "sg:tags":[
        "american"
    ],
    "wof:name":"Steak 'n Shake",
    "wof:placetype":"venue"
},
  "geometry": {"coordinates":[-82.36646,28.126579],"type":"Point"}
}