{
  "type": "Feature",
  "properties": {
    "iso:country":"US",
    "sg:address":"360 N County Rd",
    "sg:city":"Palm Beach",
    "sg:classifiers":[
        {
            "category":"Government",
            "subcategory":"Fire Station",
            "type":"Public Place"
        }
    ],
    "sg:phone":"+1 561 838 5420",
    "sg:postcode":"33480",
    "sg:province":"FL",
    "sg:tags":[
        "department"
    ],
    "sg:website":"www.townofpalmbeach.com",
    "wof:name":"Palm Beach Fire Rescue Chief",
    "wof:placetype":"venue"
},
  "geometry": {"coordinates":[-80.037679,26.727632],"type":"Point"}
}