{
  "type": "Feature",
  "properties": {
    "addr:full":"560 Breckenridge Village Altamonte Springs FL 32714",
    "addr:housenumber":"560",
    "addr:postcode":"32714",
    "addr:street":"Breckenridge Village",
    "iso:country":"US",
    "sg:address":"560 Breckenridge Village",
    "sg:city":"Altamonte Springs",
    "sg:classifiers":[
        {
            "category":"Food & Beverages",
            "subcategory":"Specialty",
            "type":"Retail Goods"
        }
    ],
    "sg:phone":"+1 407 788 4272",
    "sg:postcode":"32714",
    "sg:province":"FL",
    "wof:name":"Precision Nutrition Consulting",
    "wof:placetype":"venue"
},
  "geometry": {"coordinates":[-81.403284,28.681039],"type":"Point"}
}