{
  "type": "Feature",
  "properties": {
    "iso:country":"US",
    "sg:address":"9280 SW 150th Ave",
    "sg:city":"Miami",
    "sg:classifiers":[
        {
            "category":"Health Services",
            "subcategory":"Doctor",
            "type":"Services"
        }
    ],
    "sg:phone":"+1 305 386 2766",
    "sg:postcode":"33196",
    "sg:province":"FL",
    "sg:tags":[
        "dentist"
    ],
    "wof:name":"Orlando Dominguez DDS",
    "wof:placetype":"venue"
},
  "geometry": {"coordinates":[-80.43883,25.680521],"type":"Point"}
}