{
  "type": "Feature",
  "properties": {
    "iso:country":"US",
    "sg:address":"10201 Hammocks Blvd",
    "sg:city":"Miami",
    "sg:classifiers":[
        {
            "category":"Insurance",
            "subcategory":"Insurance Agent",
            "type":"Services"
        }
    ],
    "sg:phone":"+1 305 382 9000",
    "sg:postcode":"33196",
    "sg:province":"FL",
    "wof:name":"Allstate",
    "wof:placetype":"venue"
},
  "geometry": {"coordinates":[-80.444068,25.673127],"type":"Point"}
}