{
  "type": "Feature",
  "properties": {
    "addr:full":"2601 SW 37th Ave Miami FL 33133",
    "addr:housenumber":"2601",
    "addr:postcode":"33133",
    "addr:street":"Sw 37Th Ave",
    "iso:country":"US",
    "sg:address":"2601 SW 37th Ave",
    "sg:city":"Miami",
    "sg:classifiers":[
        {
            "category":"Health Services",
            "subcategory":"Medical Lab",
            "type":"Services"
        }
    ],
    "sg:phone":"+1 305 529 0077",
    "sg:postcode":"33133",
    "sg:province":"FL",
    "sg:tags":[
        "laboratory"
    ],
    "wof:name":"Florida Reference Laboratory",
    "wof:placetype":"venue"
},
  "geometry": {"coordinates":[-80.254322,25.742552],"type":"Point"}
}