{
  "type": "Feature",
  "properties": {
    "addr:full":"8200 W Waters Ave Tampa FL 33615",
    "addr:housenumber":"8200",
    "addr:postcode":"33615",
    "addr:street":"W Waters Ave",
    "iso:country":"US",
    "sg:address":"8200 W Waters Ave",
    "sg:city":"Tampa",
    "sg:classifiers":[
        {
            "category":"Restaurant",
            "type":"Food & Drink"
        }
    ],
    "sg:menulink":"http://www.allmenus.com/fl/tampa/111277-ginza-japanese-steak-house/menu/",
    "sg:phone":"+1 813 806 1551",
    "sg:postcode":"33615",
    "sg:province":"FL",
    "sg:tags":[
        "japanese",
        "asian"
    ],
    "wof:name":"Ginza Japanese Steak House",
    "wof:placetype":"venue"
},
  "geometry": {"coordinates":[-82.57271299999999,28.025884],"type":"Point"}
}