{
  "type": "Feature",
  "properties": {
    "iso:country":"US",
    "sg:address":"10 E University Ave",
    "sg:city":"Gainesville",
    "sg:classifiers":[
        {
            "category":"Building & Trades",
            "subcategory":"Landscaping Services",
            "type":"Services"
        },
        {
            "category":"Home & Garden",
            "subcategory":"Garden Supply",
            "type":"Retail Goods"
        },
        {
            "category":"Wholesale",
            "subcategory":"Machinery & Supplies",
            "type":"Manufacturing & Wholesale Goods"
        },
        {
            "category":"Professional",
            "subcategory":"Business Services",
            "type":"Services"
        }
    ],
    "sg:phone":"+1 352 373 4145",
    "sg:postcode":"32601",
    "sg:province":"FL",
    "sg:tags":[
        "lawn",
        "installation",
        "sprinkler",
        "consultant",
        "sprinklers-garden",
        "irrigation",
        "system",
        "equipment",
        "supervisory"
    ],
    "sg:website":"http://www.jeffwilliamsenterprise.com",
    "wof:name":"Jeff Williams Sprinkler Repair",
    "wof:placetype":"venue"
},
  "geometry": {"coordinates":[-82.32494,29.65195],"type":"Point"}
}