{
  "type": "Feature",
  "properties": {
    "iso:country":"US",
    "sg:address":"106 Mayrose Dr",
    "sg:city":"Sanford",
    "sg:classifiers":[
        {
            "category":"Building & Trades",
            "subcategory":"Construction",
            "type":"Services"
        }
    ],
    "sg:phone":"+1 407 268 3711",
    "sg:postcode":"32771",
    "sg:province":"FL",
    "sg:tags":[
        "roofing",
        "contractor"
    ],
    "wof:name":"Florida Statewide Roofing Inc",
    "wof:placetype":"venue"
},
  "geometry": {"coordinates":[-81.28478699999999,28.789372],"type":"Point"}
}