{
  "type": "Feature",
  "properties": {
    "iso:country":"US",
    "sg:address":"4105 E 4th Ave",
    "sg:city":"Hialeah",
    "sg:classifiers":[
        {
            "category":"Retail",
            "subcategory":"Auto Repair",
            "type":"Services"
        }
    ],
    "sg:phone":"+1 305 681 5015",
    "sg:postcode":"33013",
    "sg:province":"FL",
    "sg:tags":[
        "repairing",
        "automobile"
    ],
    "wof:name":"Robert's Auto Ctr",
    "wof:placetype":"venue"
},
  "geometry": {"coordinates":[-80.27458900000001,25.860654],"type":"Point"}
}