{
  "type": "Feature",
  "properties": {
    "addr:full":"570 Crown Oak Centre Dr Longwood FL 32750",
    "addr:housenumber":"570",
    "addr:postcode":"32750",
    "addr:street":"Crown Oak Centre Dr",
    "iso:country":"US",
    "sg:address":"570 Crown Oak Centre Dr",
    "sg:city":"Longwood",
    "sg:classifiers":[
        {
            "category":"Professional",
            "subcategory":"Lawyer & Legal Services",
            "type":"Services"
        }
    ],
    "sg:phone":"+1 407 339 1118",
    "sg:postcode":"32750",
    "sg:province":"FL",
    "wof:name":"The Nation Law Firm",
    "wof:placetype":"venue"
},
  "geometry": {"coordinates":[-81.382896,28.6873],"type":"Point"}
}