{
  "type": "Feature",
  "properties": {
    "addr:full":"2021 Crystal Ln Saint Cloud FL 34769",
    "addr:housenumber":"2021",
    "addr:postcode":"34769",
    "addr:street":"Crystal Ln",
    "iso:country":"US",
    "sg:address":"2021 Crystal Ln",
    "sg:city":"Saint Cloud",
    "sg:classifiers":[
        {
            "category":"Shopping",
            "subcategory":"Gifts & Souvenirs",
            "type":"Retail Goods"
        }
    ],
    "sg:phone":"+1 407 957 1639",
    "sg:postcode":"34769",
    "sg:province":"FL",
    "wof:name":"Briar Patch Gifts",
    "wof:placetype":"venue"
},
  "geometry": {"coordinates":[-81.29168799999999,28.238441],"type":"Point"}
}