{
  "type": "Feature",
  "properties": {
    "iso:country":"US",
    "sg:address":"8242 Little Rd",
    "sg:city":"New Port Richey",
    "sg:classifiers":[
        {
            "category":"Restaurant",
            "type":"Food & Drink"
        }
    ],
    "sg:menulink":"http://www.allmenus.com/fl/new-port-richey/189544-kfc---kentucky-fried-chicken/menu/",
    "sg:phone":"+1 727 815 3815",
    "sg:postcode":"34654",
    "sg:province":"FL",
    "sg:tags":[
        "american",
        "chicken"
    ],
    "wof:name":"KFC - Kentucky Fried Chicken",
    "wof:placetype":"venue"
},
  "geometry": {"coordinates":[-82.674211,28.276533],"type":"Point"}
}