{
  "type": "Feature",
  "properties": {
    "iso:country":"US",
    "sg:address":"10540 Anders Blvd",
    "sg:city":"Jacksonville",
    "sg:classifiers":[
        {
            "category":"Government",
            "subcategory":"Office",
            "type":"Public Place"
        }
    ],
    "sg:phone":"+1 904 565 2669",
    "sg:postcode":"32246",
    "sg:province":"FL",
    "sg:tags":[
        "village"
    ],
    "wof:name":"Jacksonville Windy Hill Ctr",
    "wof:placetype":"venue"
},
  "geometry": {"coordinates":[-81.538876,30.278113],"type":"Point"}
}