{
  "type": "Feature",
  "properties": {
    "addr:full":"1100 W Hickory St Arcadia FL 34266",
    "addr:housenumber":"1100",
    "addr:postcode":"34266",
    "addr:street":"W Hickory St",
    "iso:country":"US",
    "sg:address":"1100 W Hickory St",
    "sg:city":"Arcadia",
    "sg:classifiers":[
        {
            "category":"Recreation",
            "type":"Entertainment"
        }
    ],
    "sg:phone":"+1 863 993 4854",
    "sg:postcode":"34266",
    "sg:province":"FL",
    "sg:tags":[
        "parks"
    ],
    "wof:name":"Morgan Park",
    "wof:placetype":"venue"
},
  "geometry": {"coordinates":[-81.87564999999999,27.22535],"type":"Point"}
}