{
  "type": "Feature",
  "properties": {
    "iso:country":"US",
    "sg:address":"12551 Indian Rocks Rd",
    "sg:city":"Largo",
    "sg:classifiers":[
        {
            "category":"Retail",
            "subcategory":"Repair Shop",
            "type":"Services"
        }
    ],
    "sg:phone":"+1 727 595 7068",
    "sg:postcode":"33774",
    "sg:province":"FL",
    "sg:tags":[
        "retailing",
        "tennis"
    ],
    "wof:name":"String Along With Vince",
    "wof:placetype":"venue"
},
  "geometry": {"coordinates":[-82.83237,27.887282],"type":"Point"}
}