{
  "type": "Feature",
  "properties": {
    "iso:country":"US",
    "sg:address":"4301 W Vine St",
    "sg:city":"Kissimmee",
    "sg:classifiers":[
        {
            "category":"Wholesale",
            "subcategory":"Machinery & Supplies",
            "type":"Manufacturing & Wholesale Goods"
        }
    ],
    "sg:phone":"+1 407 397 0065",
    "sg:postcode":"34746",
    "sg:province":"FL",
    "sg:tags":[
        "equipment",
        "printing"
    ],
    "wof:name":"Advantage Printer-Central Fl",
    "wof:placetype":"venue"
},
  "geometry": {"coordinates":[-81.456152,28.303713],"type":"Point"}
}