{
  "type": "Feature",
  "properties": {
    "iso:country":"US",
    "sg:address":"7053 High Ridge Rd",
    "sg:city":"Boynton Beach",
    "sg:classifiers":[
        {
            "category":"Social Services",
            "subcategory":"Child Care",
            "type":"Services"
        }
    ],
    "sg:phone":"+1 561 585 5300",
    "sg:postcode":"33426",
    "sg:province":"FL",
    "wof:name":"First Impressions Preschool",
    "wof:placetype":"venue"
},
  "geometry": {"coordinates":[-80.07461600000001,26.571701],"type":"Point"}
}