{
  "type": "Feature",
  "properties": {
    "iso:country":"US",
    "sg:address":"427 Benning Dr",
    "sg:city":"Destin",
    "sg:classifiers":[
        {
            "category":"Recreation",
            "type":"Entertainment"
        }
    ],
    "sg:phone":"+1 850 837 6620",
    "sg:postcode":"32541",
    "sg:province":"FL",
    "sg:tags":[
        "charter",
        "boat"
    ],
    "wof:name":"Melanie Dawn Charter Boats",
    "wof:placetype":"venue"
},
  "geometry": {"coordinates":[-86.495285,30.400139],"type":"Point"}
}