{
  "type": "Feature",
  "properties": {
    "iso:country":"US",
    "sg:address":"106 W Park Ave",
    "sg:city":"Edgewater",
    "sg:classifiers":[
        {
            "category":"Wholesale",
            "subcategory":"Machinery & Supplies",
            "type":"Manufacturing & Wholesale Goods"
        },
        {
            "category":"Building & Trades",
            "subcategory":"Construction",
            "type":"Services"
        }
    ],
    "sg:phone":"+1 386 427 0407",
    "sg:postcode":"32132",
    "sg:province":"FL",
    "sg:tags":[
        "heavy",
        "system",
        "contractor"
    ],
    "wof:name":"R & R Trenching Inc",
    "wof:placetype":"venue"
},
  "geometry": {"coordinates":[-80.908871,28.991157],"type":"Point"}
}