{
  "type": "Feature",
  "properties": {
    "iso:country":"US",
    "sg:address":"5828 W Park Rd",
    "sg:city":"Hollywood",
    "sg:classifiers":[
        {
            "category":"Building & Trades",
            "subcategory":"Cleaning & Sanitation",
            "type":"Services"
        }
    ],
    "sg:phone":"+1 954 394 4047",
    "sg:postcode":"33021",
    "sg:province":"FL",
    "sg:tags":[
        "janitor"
    ],
    "wof:name":"Brite Shine CS",
    "wof:placetype":"venue"
},
  "geometry": {"coordinates":[-80.205175,26.028508],"type":"Point"}
}