{
  "type": "Feature",
  "properties": {
    "addr:full":"5963 SW 66th St South Miami FL 33143",
    "addr:housenumber":"5963",
    "addr:postcode":"33143",
    "addr:street":"Sw 66Th St",
    "iso:country":"US",
    "sg:address":"5963 SW 66th St",
    "sg:city":"South Miami",
    "sg:classifiers":[
        {
            "category":"Personal",
            "subcategory":"Beauty Salon",
            "type":"Services"
        }
    ],
    "sg:phone":"+1 305 663 1114",
    "sg:postcode":"33143",
    "sg:province":"FL",
    "wof:name":"Garbutts Hair",
    "wof:placetype":"venue"
},
  "geometry": {"coordinates":[-80.29021,25.709751],"type":"Point"}
}