{
  "type": "Feature",
  "properties": {
    "iso:country":"US",
    "sg:address":"2708 W Dr Martin Luther King Jr Blvd",
    "sg:city":"Tampa",
    "sg:classifiers":[
        {
            "category":"Restaurant",
            "type":"Food & Drink"
        }
    ],
    "sg:menulink":"http://www.allmenus.com/fl/tampa/106434-boston-market/menu/",
    "sg:phone":"+1 813 872 7929",
    "sg:postcode":"33607",
    "sg:province":"FL",
    "sg:tags":[
        "barbecue",
        "american",
        "soup"
    ],
    "wof:name":"Boston Market",
    "wof:placetype":"venue"
},
  "geometry": {"coordinates":[-82.48709599999999,27.981177],"type":"Point"}
}