{
  "type": "Feature",
  "properties": {
    "iso:country":"US",
    "sg:address":"6596 NW 31st Way",
    "sg:city":"Boca Raton",
    "sg:classifiers":[
        {
            "category":"Wholesale",
            "subcategory":"Chemicals & Plastics",
            "type":"Manufacturing & Wholesale Goods"
        }
    ],
    "sg:phone":"+1 561 989 3610",
    "sg:postcode":"33496",
    "sg:province":"FL",
    "wof:name":"PM Plastic Technologies Inc",
    "wof:placetype":"venue"
},
  "geometry": {"coordinates":[-80.15033200000001,26.407414],"type":"Point"}
}