{
  "type": "Feature",
  "properties": {
    "iso:country":"US",
    "sg:address":"2025 Porter Lake Dr",
    "sg:city":"Sarasota",
    "sg:classifiers":[
        {
            "category":"Building & Trades",
            "subcategory":"Construction",
            "type":"Services"
        }
    ],
    "sg:phone":"+1 941 378 8172",
    "sg:postcode":"34240",
    "sg:province":"FL",
    "sg:tags":[
        "contractor"
    ],
    "wof:name":"Diversified Welding & Fabricat",
    "wof:placetype":"venue"
},
  "geometry": {"coordinates":[-82.44727899999999,27.312915],"type":"Point"}
}