{
  "type": "Feature",
  "properties": {
    "iso:country":"US",
    "sg:address":"10544 US Hwy 1",
    "sg:city":"Port Saint Lucie",
    "sg:classifiers":[
        {
            "category":"Health Services",
            "subcategory":"Chiropractor",
            "type":"Services"
        }
    ],
    "sg:phone":"+1 561 994 2196",
    "sg:postcode":"34952",
    "sg:province":"FL",
    "wof:name":"Winters Chiropractic Life Ctr",
    "wof:placetype":"venue"
},
  "geometry": {"coordinates":[-80.28754600000001,27.270193],"type":"Point"}
}