{
  "type": "Feature",
  "properties": {
    "iso:country":"US",
    "sg:address":"110 N 39th St",
    "sg:city":"Port St Joe",
    "sg:classifiers":[
        {
            "category":"Recreation",
            "type":"Entertainment"
        }
    ],
    "sg:phone":"+1 850 648 8211",
    "sg:postcode":"32410",
    "sg:province":"FL",
    "sg:tags":[
        "guide"
    ],
    "sg:website":"www.charismacharters.com",
    "wof:name":"Charisma Charters",
    "wof:placetype":"venue"
},
  "geometry": {"coordinates":[-85.42360499999999,29.953204],"type":"Point"}
}