{
  "type": "Feature",
  "properties": {
    "addr:full":"114 N Kings Ave Brandon FL 33510",
    "addr:housenumber":"114",
    "addr:postcode":"33510",
    "addr:street":"N Kings Ave",
    "iso:country":"US",
    "sg:address":"114 N Kings Ave",
    "sg:city":"Brandon",
    "sg:classifiers":[
        {
            "category":"Food & Beverages",
            "subcategory":"Specialty",
            "type":"Retail Goods"
        }
    ],
    "sg:phone":"+1 813 657 2555",
    "sg:postcode":"33510",
    "sg:province":"FL",
    "sg:tags":[
        "health",
        "diet"
    ],
    "wof:name":"Chucks Natural Food Market Pl",
    "wof:placetype":"venue"
},
  "geometry": {"coordinates":[-82.294017,27.93832],"type":"Point"}
}