{
  "type": "Feature",
  "properties": {
    "iso:country":"US",
    "sg:address":"1229 Forest Oaks Dr",
    "sg:city":"Neptune Beach",
    "sg:classifiers":[
        {
            "category":"Building & Trades",
            "subcategory":"Construction",
            "type":"Services"
        }
    ],
    "sg:phone":"+1 904 249 3213",
    "sg:postcode":"32266",
    "sg:province":"FL",
    "sg:tags":[
        "house"
    ],
    "wof:name":"Northeast Broward Construction",
    "wof:placetype":"venue"
},
  "geometry": {"coordinates":[-81.41178600000001,30.315773],"type":"Point"}
}