{
  "type": "Feature",
  "properties": {
    "iso:country":"US",
    "sg:address":"15 Lancaster Dr",
    "sg:city":"Lake Worth",
    "sg:classifiers":[
        {
            "category":"Banks & Credit Unions",
            "subcategory":"Bank",
            "type":"Services"
        }
    ],
    "sg:phone":"+1 561 642 9568",
    "sg:postcode":"33463",
    "sg:province":"FL",
    "sg:tags":[
        "mortgage"
    ],
    "wof:name":"Mortgage & Lending Connection",
    "wof:placetype":"venue"
},
  "geometry": {"coordinates":[-80.133194,26.629319],"type":"Point"}
}