{
  "type": "Feature",
  "properties": {
    "iso:country":"US",
    "sg:address":"7975 NW 12th St",
    "sg:city":"Miami",
    "sg:classifiers":[
        {
            "category":"Restaurant",
            "type":"Food & Drink"
        }
    ],
    "sg:menulink":"http://www.allmenus.com/fl/north-westside/155614-steak-out/menu/",
    "sg:phone":"+1 305 592 4444",
    "sg:postcode":"33126",
    "sg:province":"FL",
    "sg:tags":[
        "american",
        "steakhouse"
    ],
    "wof:name":"Steak-Out",
    "wof:placetype":"venue"
},
  "geometry": {"coordinates":[-80.325591,25.783546],"type":"Point"}
}