{
  "type": "Feature",
  "properties": {
    "iso:country":"US",
    "sg:address":"1320 SE 17th St",
    "sg:city":"Fort Lauderdale",
    "sg:classifiers":[
        {
            "category":"Banks & Credit Unions",
            "subcategory":"Bank",
            "type":"Services"
        }
    ],
    "sg:phone":"+1 954 522 7994",
    "sg:postcode":"33316",
    "sg:province":"FL",
    "sg:tags":[
        "loan",
        "real estate"
    ],
    "sg:website":"www.wecanlend.com",
    "wof:name":"WECANLEND.COM",
    "wof:placetype":"venue"
},
  "geometry": {"coordinates":[-80.12872900000001,26.100409],"type":"Point"}
}