{
  "type": "Feature",
  "properties": {
    "addr:full":"1853 N Pine Island Rd Fort Lauderdale FL 33322",
    "addr:housenumber":"1853",
    "addr:postcode":"33322",
    "addr:street":"N Pine Island Rd",
    "iso:country":"US",
    "sg:address":"1853 N Pine Island Rd",
    "sg:city":"Fort Lauderdale",
    "sg:classifiers":[
        {
            "category":"Shopping",
            "type":"Retail Goods"
        }
    ],
    "sg:phone":"+1 954 370 7500",
    "sg:postcode":"33322",
    "sg:province":"FL",
    "sg:tags":[
        "merchandise"
    ],
    "wof:name":"Paws Plus Inc",
    "wof:placetype":"venue"
},
  "geometry": {"coordinates":[-80.26924099999999,26.144845],"type":"Point"}
}