{
  "type": "Feature",
  "properties": {
    "addr:full":"616 Ohio Blvd Eustis FL 32726",
    "addr:housenumber":"616",
    "addr:postcode":"32726",
    "addr:street":"Ohio Blvd",
    "iso:country":"US",
    "sg:address":"616 Ohio Blvd",
    "sg:city":"Eustis",
    "sg:classifiers":[
        {
            "category":"Communications",
            "subcategory":"Film & Video Production",
            "type":"Services"
        }
    ],
    "sg:phone":"+1 352 589 9479",
    "sg:postcode":"32726",
    "sg:province":"FL",
    "sg:tags":[
        "motion"
    ],
    "wof:name":"Stewart Productions",
    "wof:placetype":"venue"
},
  "geometry": {"coordinates":[-81.66446500000001,28.845069],"type":"Point"}
}