{
  "type": "Feature",
  "properties": {
    "iso:country":"US",
    "sg:address":"7274 SW 48th St",
    "sg:city":"Miami",
    "sg:classifiers":[
        {
            "category":"Professional",
            "subcategory":"Management & Consulting",
            "type":"Services"
        }
    ],
    "sg:phone":"+1 305 663 2104",
    "sg:postcode":"33155",
    "sg:province":"FL",
    "sg:tags":[
        "employee",
        "consultant",
        "benefit"
    ],
    "wof:name":"Diversified Benefits Group",
    "wof:placetype":"venue"
},
  "geometry": {"coordinates":[-80.312487,25.725499],"type":"Point"}
}