{
  "type": "Feature",
  "properties": {
    "iso:country":"US",
    "sg:address":"924 S Main St",
    "sg:city":"Gainesville",
    "sg:classifiers":[
        {
            "category":"Manufacturing",
            "subcategory":"Glass & Minerals",
            "type":"Manufacturing & Wholesale Goods"
        }
    ],
    "sg:phone":"+1 352 376 6491",
    "sg:postcode":"32601",
    "sg:province":"FL",
    "sg:tags":[
        "ready"
    ],
    "wof:name":"Florida Rock Industries Inc",
    "wof:placetype":"venue"
},
  "geometry": {"coordinates":[-82.325979,29.640927],"type":"Point"}
}