{
  "type": "Feature",
  "properties": {
    "addr:full":"2900 SW 149th Ave Miami FL 33185",
    "addr:housenumber":"2900",
    "addr:postcode":"33185",
    "addr:street":"Sw 149Th Ave",
    "iso:country":"US",
    "sg:address":"2900 SW 149th Ave",
    "sg:city":"Miami",
    "sg:classifiers":[
        {
            "category":"Insurance",
            "subcategory":"Insurance Agent",
            "type":"Services"
        },
        {
            "category":"Insurance",
            "subcategory":"Hazard Insurance",
            "type":"Services"
        },
        {
            "category":"Insurance",
            "subcategory":"Title Insurance",
            "type":"Services"
        },
        {
            "category":"Insurance",
            "subcategory":"Health Insurance",
            "type":"Services"
        },
        {
            "category":"Insurance",
            "subcategory":"Life Insurance",
            "type":"Services"
        }
    ],
    "sg:phone":"+1 305 620 0200",
    "sg:postcode":"33185",
    "sg:province":"FL",
    "sg:tags":[
        "business",
        "consultant",
        "commercial",
        "homeowner",
        "auto",
        "analyst"
    ],
    "sg:website":"http://www.thflorida.com",
    "wof:name":"Tanenbaum Harber Insurance Group",
    "wof:placetype":"venue"
},
  "geometry": {"coordinates":[-80.43615200000001,25.739889],"type":"Point"}
}