{
  "type": "Feature",
  "properties": {
    "iso:country":"US",
    "sg:address":"10995 Whitehawk St",
    "sg:city":"Fort Lauderdale",
    "sg:classifiers":[
        {
            "category":"Restaurant",
            "type":"Food & Drink"
        }
    ],
    "sg:phone":"+1 954 382 1930",
    "sg:postcode":"33324",
    "sg:province":"FL",
    "sg:tags":[
        "eating"
    ],
    "wof:name":"Terry S Foods Inc",
    "wof:placetype":"venue"
},
  "geometry": {"coordinates":[-80.29558,26.115183],"type":"Point"}
}