{
  "type": "Feature",
  "properties": {
    "addr:full":"1415 Cleveland St Clearwater FL 33755",
    "addr:housenumber":"1415",
    "addr:postcode":"33755",
    "addr:street":"Cleveland St",
    "iso:country":"US",
    "sg:address":"1415 Cleveland St",
    "sg:city":"Clearwater",
    "sg:classifiers":[
        {
            "category":"Real Estate",
            "subcategory":"Real Estate Agent",
            "type":"Services"
        }
    ],
    "sg:phone":"+1 727 461 5865",
    "sg:postcode":"33755",
    "sg:province":"FL",
    "wof:name":"Buddy Verdi Realty & Mortgage",
    "wof:placetype":"venue"
},
  "geometry": {"coordinates":[-82.77978400000001,27.965551],"type":"Point"}
}