{
  "type": "Feature",
  "properties": {
    "addr:full":"100 NE 1st Ave Mulberry FL 33860",
    "addr:housenumber":"100",
    "addr:postcode":"33860",
    "addr:street":"Ne 1St Ave",
    "iso:country":"US",
    "sg:address":"100 NE 1st Ave",
    "sg:city":"Mulberry",
    "sg:classifiers":[
        {
            "category":"Professional",
            "subcategory":"Lawyer & Legal Services",
            "type":"Services"
        }
    ],
    "sg:phone":"+1 863 869 9632",
    "sg:postcode":"33860",
    "sg:province":"FL",
    "sg:tags":[
        "information",
        "attorney",
        "law",
        "negligence",
        "practice",
        "liability",
        "malpractice",
        "referral"
    ],
    "wof:name":"Knox Stephen J Attorney At Law",
    "wof:placetype":"venue"
},
  "geometry": {"coordinates":[-81.972679,27.89502],"type":"Point"}
}