{
  "type": "Feature",
  "properties": {
    "iso:country":"US",
    "sg:address":"6167 Westwood Blvd",
    "sg:city":"Orlando",
    "sg:classifiers":[
        {
            "category":"Shopping",
            "subcategory":"Bicycles & Sporting Goods",
            "type":"Retail Goods"
        }
    ],
    "sg:phone":"+1 407 238 2222",
    "sg:postcode":"32821",
    "sg:province":"FL",
    "sg:tags":[
        "equipment",
        "golf",
        "supply"
    ],
    "wof:name":"International Golf Discount",
    "wof:placetype":"venue"
},
  "geometry": {"coordinates":[-81.46977699999999,28.417377],"type":"Point"}
}