{
  "type": "Feature",
  "properties": {
    "addr:full":"235 E Washington St Monticello FL 32344",
    "addr:housenumber":"235",
    "addr:postcode":"32344",
    "addr:street":"E Washington St",
    "iso:country":"US",
    "sg:address":"235 E Washington St",
    "sg:city":"Monticello",
    "sg:classifiers":[
        {
            "category":"Insurance",
            "subcategory":"Insurance Agent",
            "type":"Services"
        }
    ],
    "sg:phone":"+1 850 997 8292",
    "sg:postcode":"32344",
    "sg:province":"FL",
    "wof:name":"Swann Insurance Agency",
    "wof:placetype":"venue"
},
  "geometry": {"coordinates":[-83.86881,30.54505],"type":"Point"}
}