{
  "type": "Feature",
  "properties": {
    "iso:country":"US",
    "sg:address":"7721 Rutillio Ct",
    "sg:city":"New Port Richey",
    "sg:classifiers":[
        {
            "category":"Building & Trades",
            "subcategory":"Electrical",
            "type":"Services"
        }
    ],
    "sg:phone":"+1 727 847 9292",
    "sg:postcode":"34653",
    "sg:province":"FL",
    "sg:tags":[
        "electric",
        "contractor"
    ],
    "wof:name":"Raco Electric Co Inc",
    "wof:placetype":"venue"
},
  "geometry": {"coordinates":[-82.70370200000001,28.270097],"type":"Point"}
}