{
  "type": "Feature",
  "properties": {
    "addr:full":"207 N Wiggins Rd Plant City FL 33566",
    "addr:housenumber":"207",
    "addr:postcode":"33566",
    "addr:street":"N Wiggins Rd",
    "iso:country":"US",
    "sg:address":"207 N Wiggins Rd",
    "sg:city":"Plant City",
    "sg:classifiers":[
        {
            "category":"Mining & Drilling",
            "type":"Manufacturing & Wholesale Goods"
        }
    ],
    "sg:phone":"+1 813 752 5411",
    "sg:postcode":"33566",
    "sg:province":"FL",
    "sg:tags":[
        "well"
    ],
    "wof:name":"Sure Shot Directional Inc",
    "wof:placetype":"venue"
},
  "geometry": {"coordinates":[-82.068179,28.03264],"type":"Point"}
}