{
  "type": "Feature",
  "properties": {
    "iso:country":"US",
    "sg:address":"10675 Atlantic Blvd",
    "sg:city":"Jacksonville",
    "sg:classifiers":[
        {
            "category":"Autos & Motor Vehicles",
            "subcategory":"Fuel & Gas Station",
            "type":"Retail Goods"
        }
    ],
    "sg:phone":"+1 904 641 7377",
    "sg:postcode":"32225",
    "sg:province":"FL",
    "sg:tags":[
        "oil"
    ],
    "wof:name":"BP",
    "wof:placetype":"venue"
},
  "geometry": {"coordinates":[-81.523994,30.324391],"type":"Point"}
}