{
  "type": "Feature",
  "properties": {
    "iso:country":"US",
    "sg:address":"321 S Palafox St",
    "sg:city":"Pensacola",
    "sg:classifiers":[
        {
            "category":"Social Services",
            "subcategory":"Child Care",
            "type":"Services"
        }
    ],
    "sg:phone":"+1 850 433 7546",
    "sg:postcode":"32502",
    "sg:province":"FL",
    "wof:name":"For Kids Only",
    "wof:placetype":"venue"
},
  "geometry": {"coordinates":[-87.214421,30.408414],"type":"Point"}
}