{
  "type": "Feature",
  "properties": {
    "addr:full":"1360 E Venice Ave Venice FL 34285",
    "addr:housenumber":"1360",
    "addr:postcode":"34285",
    "addr:street":"E Venice Ave",
    "iso:country":"US",
    "sg:address":"1360 E Venice Ave",
    "sg:city":"Venice",
    "sg:classifiers":[
        {
            "category":"Health Services",
            "subcategory":"Doctor",
            "type":"Services"
        }
    ],
    "sg:phone":"+1 941 488 2020",
    "sg:postcode":"34285",
    "sg:province":"FL",
    "sg:tags":[
        "physician",
        "surgeon"
    ],
    "wof:name":"Center For Sight",
    "wof:placetype":"venue"
},
  "geometry": {"coordinates":[-82.414535,27.099858],"type":"Point"}
}