{
  "type": "Feature",
  "properties": {
    "iso:country":"US",
    "sg:address":"961 Sand Fly Ln",
    "sg:city":"Vero Beach",
    "sg:classifiers":[
        {
            "category":"Building & Trades",
            "subcategory":"Construction",
            "type":"Services"
        }
    ],
    "sg:phone":"+1 772 231 3293",
    "sg:postcode":"32963",
    "sg:province":"FL",
    "sg:tags":[
        "industrial"
    ],
    "wof:name":"Johnson JB Custom Renovation",
    "wof:placetype":"venue"
},
  "geometry": {"coordinates":[-80.35524100000001,27.642827],"type":"Point"}
}