{
  "type": "Feature",
  "properties": {
    "iso:country":"US",
    "sg:address":"7141 Gulf Blvd",
    "sg:city":"St Pete Beach",
    "sg:classifiers":[
        {
            "category":"Restaurant",
            "type":"Food & Drink"
        }
    ],
    "sg:phone":"+1 727 367 9999",
    "sg:postcode":"33706",
    "sg:province":"FL",
    "sg:tags":[
        "italian"
    ],
    "wof:name":"Alfredinos On The Beach Inc",
    "wof:placetype":"venue"
},
  "geometry": {"coordinates":[-82.75004300000001,27.739965],"type":"Point"}
}