{
  "type": "Feature",
  "properties": {
    "iso:country":"US",
    "sg:address":"10548 SW 8th St",
    "sg:city":"Miami",
    "sg:classifiers":[
        {
            "category":"Food & Beverages",
            "subcategory":"Bakery",
            "type":"Retail Goods"
        }
    ],
    "sg:phone":"+1 305 480 5786",
    "sg:postcode":"33174",
    "sg:province":"FL",
    "sg:tags":[
        "sandwich"
    ],
    "sg:website":"www.quiznos.com/subsandwiches/La...",
    "wof:name":"Quiznos",
    "wof:placetype":"venue"
},
  "geometry": {"coordinates":[-80.367074,25.761212],"type":"Point"}
}