{
  "type": "Feature",
  "properties": {
    "addr:full":"5010 Winchester Dr Titusville FL 32780",
    "addr:housenumber":"5010",
    "addr:postcode":"32780",
    "addr:street":"Winchester Dr",
    "iso:country":"US",
    "sg:address":"5010 Winchester Dr",
    "sg:city":"Titusville",
    "sg:classifiers":[
        {
            "category":"Manufacturing",
            "subcategory":"Printing",
            "type":"Manufacturing & Wholesale Goods"
        }
    ],
    "sg:phone":"+1 321 264 2200",
    "sg:postcode":"32780",
    "sg:province":"FL",
    "sg:tags":[
        "publisher"
    ],
    "wof:name":"Citrus Press",
    "wof:placetype":"venue"
},
  "geometry": {"coordinates":[-80.836547,28.553994],"type":"Point"}
}