{
  "type": "Feature",
  "properties": {
    "iso:country":"US",
    "sg:address":"1690 Sunset Cir",
    "sg:city":"Mt Dora",
    "sg:classifiers":[
        {
            "category":"Autos & Motor Vehicles",
            "subcategory":"Automobile Sales",
            "type":"Retail Goods"
        }
    ],
    "sg:phone":"+1 352 735 4300",
    "sg:postcode":"32757",
    "sg:province":"FL",
    "sg:tags":[
        "truck"
    ],
    "wof:name":"Sterling Trucks",
    "wof:placetype":"venue"
},
  "geometry": {"coordinates":[-81.662722,28.82127],"type":"Point"}
}