{
  "type": "Feature",
  "properties": {
    "iso:country":"US",
    "sg:address":"6854 Hills Dr",
    "sg:city":"New Port Richey",
    "sg:classifiers":[
        {
            "category":"Real Estate",
            "subcategory":"Real Estate Agent",
            "type":"Services"
        }
    ],
    "sg:phone":"+1 727 849 2942",
    "sg:postcode":"34653",
    "sg:province":"FL",
    "wof:name":"Beacon Realty Caron & Assoc",
    "wof:placetype":"venue"
},
  "geometry": {"coordinates":[-82.701415,28.256328],"type":"Point"}
}