{
  "type": "Feature",
  "properties": {
    "addr:full":"919 Lake Ln Longwood FL 32750",
    "addr:housenumber":"919",
    "addr:postcode":"32750",
    "addr:street":"Lake Ln",
    "iso:country":"US",
    "sg:address":"919 Lake Ln",
    "sg:city":"Longwood",
    "sg:classifiers":[
        {
            "category":"Professional",
            "subcategory":"Business Services",
            "type":"Services"
        }
    ],
    "sg:phone":"+1 407 468 7768",
    "sg:postcode":"32750",
    "sg:province":"FL",
    "sg:tags":[
        "delivery",
        "courier"
    ],
    "sg:website":"www.anythingnow.com",
    "wof:name":"AnythingNow",
    "wof:placetype":"venue"
},
  "geometry": {"coordinates":[-81.33755600000001,28.72904],"type":"Point"}
}