{
  "type": "Feature",
  "properties": {
    "iso:country":"US",
    "sg:address":"230 NE 1st St",
    "sg:city":"Miami",
    "sg:classifiers":[
        {
            "category":"Shopping",
            "type":"Retail Goods"
        }
    ],
    "sg:phone":"+1 305 374 2336",
    "sg:postcode":"33132",
    "sg:province":"FL",
    "sg:tags":[
        "stamp",
        "currency",
        "coin",
        "foreign",
        "exchange"
    ],
    "wof:name":"Abbot Foreign Money Exchange",
    "wof:placetype":"venue"
},
  "geometry": {"coordinates":[-80.190198,25.775149],"type":"Point"}
}