{
  "type": "Feature",
  "properties": {
    "addr:full":"5400 E Busch Blvd Tampa FL 33617",
    "addr:housenumber":"5400",
    "addr:postcode":"33617",
    "addr:street":"E Busch Blvd",
    "iso:country":"US",
    "sg:address":"5400 E Busch Blvd",
    "sg:city":"Tampa",
    "sg:classifiers":[
        {
            "category":"Restaurant",
            "type":"Food & Drink"
        }
    ],
    "sg:phone":"+1 813 985 3931",
    "sg:postcode":"33617",
    "sg:province":"FL",
    "sg:tags":[
        "pizza"
    ],
    "wof:name":"Little Caesars Pizza",
    "wof:placetype":"venue"
},
  "geometry": {"coordinates":[-82.39552999999999,28.032615],"type":"Point"}
}