{
  "type": "Feature",
  "properties": {
    "iso:country":"US",
    "sg:address":"39 NW 166th St Ste 2",
    "sg:city":"Miami",
    "sg:classifiers":[
        {
            "category":"Building & Trades",
            "subcategory":"Locksmith",
            "type":"Services"
        }
    ],
    "sg:phone":"+1 305 944 2345",
    "sg:postcode":"33169",
    "sg:province":"FL",
    "sg:tags":[
        "key"
    ],
    "wof:name":"Abraham Lock & Key",
    "wof:placetype":"venue"
},
  "geometry": {"coordinates":[-80.201103,25.9272],"type":"Point"}
}