{
  "type": "Feature",
  "properties": {
    "iso:country":"US",
    "sg:address":"2428 13th St",
    "sg:city":"St Cloud",
    "sg:classifiers":[
        {
            "category":"Manufacturing",
            "subcategory":"Printing",
            "type":"Manufacturing & Wholesale Goods"
        }
    ],
    "sg:phone":"+1 407 891 2116",
    "sg:postcode":"34769",
    "sg:province":"FL",
    "sg:tags":[
        "printer"
    ],
    "wof:name":"St Cloud Printing",
    "wof:placetype":"venue"
},
  "geometry": {"coordinates":[-81.296171,28.246166],"type":"Point"}
}