{
  "type": "Feature",
  "properties": {
    "iso:country":"US",
    "sg:address":"1539 S 8th St",
    "sg:city":"Fernandina Beach",
    "sg:classifiers":[
        {
            "category":"Autos & Motor Vehicles",
            "subcategory":"Auto Supplies",
            "type":"Retail Goods"
        },
        {
            "category":"Shopping",
            "subcategory":"Computers & Home Electronics",
            "type":"Retail Goods"
        }
    ],
    "sg:phone":"+1 904 491 0153",
    "sg:postcode":"32034",
    "sg:province":"FL",
    "sg:tags":[
        "automobile",
        "stereo",
        "radio",
        "software"
    ],
    "wof:name":"Pinnacle Electronics",
    "wof:placetype":"venue"
},
  "geometry": {"coordinates":[-81.46035500000001,30.651741],"type":"Point"}
}