{
  "type": "Feature",
  "properties": {
    "addr:full":"2190 NW 22nd Ct Miami FL 33142",
    "addr:housenumber":"2190",
    "addr:postcode":"33142",
    "addr:street":"Nw 22Nd Ct",
    "iso:country":"US",
    "sg:address":"2190 NW 22nd Ct",
    "sg:city":"Miami",
    "sg:classifiers":[
        {
            "category":"Building & Trades",
            "subcategory":"Plumbing",
            "type":"Services"
        },
        {
            "category":"Building & Trades",
            "subcategory":"Cleaning & Sanitation",
            "type":"Services"
        }
    ],
    "sg:phone":"+1 305 635 4516",
    "sg:postcode":"33142",
    "sg:province":"FL",
    "sg:tags":[
        "cleaner",
        "plumber",
        "industrial",
        "repairer",
        "sewer",
        "contractors-commercial",
        "plumbing-drain"
    ],
    "sg:website":"http://www.ringemann.com",
    "wof:name":"Ringemann Plumbing Service",
    "wof:placetype":"venue"
},
  "geometry": {"coordinates":[-80.23249800000001,25.7969],"type":"Point"}
}