{
  "type": "Feature",
  "properties": {
    "iso:country":"US",
    "sg:address":"13111 SW 9th Ct",
    "sg:city":"Davie",
    "sg:classifiers":[
        {
            "category":"Home & Garden",
            "subcategory":"Household Appliances",
            "type":"Retail Goods"
        }
    ],
    "sg:phone":"+1 954 570 6778",
    "sg:postcode":"33325",
    "sg:province":"FL",
    "sg:tags":[
        "major"
    ],
    "wof:name":"Air Conditioning & Appliance Svc By Jim Inc",
    "wof:placetype":"venue"
},
  "geometry": {"coordinates":[-80.323487,26.108226],"type":"Point"}
}