{
  "type": "Feature",
  "properties": {
    "addr:full":"2301 Avalon Ave Vero Beach FL 32960",
    "addr:housenumber":"2301",
    "addr:postcode":"32960",
    "addr:street":"Avalon Ave",
    "iso:country":"US",
    "sg:address":"2301 Avalon Ave",
    "sg:city":"Vero Beach",
    "sg:classifiers":[
        {
            "category":"Real Estate",
            "subcategory":"Real Estate Operator",
            "type":"Services"
        }
    ],
    "sg:phone":"+1 772 770 6906",
    "sg:postcode":"32960",
    "sg:province":"FL",
    "sg:tags":[
        "building",
        "nonresidential"
    ],
    "wof:name":"Arden Properties LLC",
    "wof:placetype":"venue"
},
  "geometry": {"coordinates":[-80.41279,27.641759],"type":"Point"}
}