{
  "type": "Feature",
  "properties": {
    "iso:country":"US",
    "sg:address":"630 Maplewood Dr",
    "sg:city":"Jupiter",
    "sg:classifiers":[
        {
            "category":"Recreation",
            "subcategory":"Marina",
            "type":"Entertainment"
        }
    ],
    "sg:phone":"+1 561 625 4202",
    "sg:postcode":"33458",
    "sg:province":"FL",
    "sg:tags":[
        "operation"
    ],
    "wof:name":"Inlet Marina of Palm Beach",
    "wof:placetype":"venue"
},
  "geometry": {"coordinates":[-80.123541,26.927685],"type":"Point"}
}