{
  "type": "Feature",
  "properties": {
    "iso:country":"US",
    "sg:address":"10693 SE 58th Ave",
    "sg:city":"Belleview",
    "sg:classifiers":[
        {
            "category":"Home & Garden",
            "subcategory":"Garden Supply",
            "type":"Retail Goods"
        },
        {
            "category":"Shopping",
            "subcategory":"Party Supplies",
            "type":"Retail Goods"
        },
        {
            "category":"Personal",
            "type":"Services"
        },
        {
            "category":"Shopping",
            "subcategory":"Florist",
            "type":"Retail Goods"
        }
    ],
    "sg:phone":"+1 866 933 8218",
    "sg:postcode":"34420",
    "sg:province":"FL",
    "sg:tags":[
        "consultant",
        "plant",
        "planning",
        "wedding"
    ],
    "sg:website":"http://www.belleviewflorist.com/",
    "wof:name":"Belleview Florist Inc",
    "wof:placetype":"venue"
},
  "geometry": {"coordinates":[-82.052205,29.066085],"type":"Point"}
}