{
  "type": "Feature",
  "properties": {
    "addr:full":"509 S Palm Ave Titusville FL 32796",
    "addr:housenumber":"509",
    "addr:postcode":"32796",
    "addr:street":"S Palm Ave",
    "iso:country":"US",
    "sg:address":"509 S Palm Ave",
    "sg:city":"Titusville",
    "sg:classifiers":[
        {
            "category":"Professional",
            "subcategory":"Management & Consulting",
            "type":"Services"
        }
    ],
    "sg:phone":"+1 321 269 1345",
    "sg:postcode":"32796",
    "sg:province":"FL",
    "sg:tags":[
        "consultant"
    ],
    "wof:name":"Professional Contracting Service Inc",
    "wof:placetype":"venue"
},
  "geometry": {"coordinates":[-80.80911399999999,28.610201],"type":"Point"}
}