{
  "type": "Feature",
  "properties": {
    "iso:country":"US",
    "sg:address":"6383 Pensacola Blvd",
    "sg:city":"Pensacola",
    "sg:classifiers":[
        {
            "category":"Restaurant",
            "type":"Food & Drink"
        }
    ],
    "sg:phone":"+1 850 476 4350",
    "sg:postcode":"32505",
    "sg:province":"FL",
    "sg:tags":[
        "style",
        "family",
        "lunch",
        "american",
        "brunch",
        "breakfast"
    ],
    "sg:website":"http://www.wafflehouse.com",
    "wof:name":"Waffle House",
    "wof:placetype":"venue"
},
  "geometry": {"coordinates":[-87.254569,30.480891],"type":"Point"}
}