{
  "type": "Feature",
  "properties": {
    "iso:country":"US",
    "sg:address":"7653 W 14th Ct",
    "sg:city":"Hialeah",
    "sg:classifiers":[
        {
            "category":"Professional",
            "subcategory":"Business Services",
            "type":"Services"
        }
    ],
    "sg:phone":"+1 305 558 2624",
    "sg:postcode":"33014",
    "sg:province":"FL",
    "sg:tags":[
        "interior",
        "consultant",
        "design",
        "decorator"
    ],
    "wof:name":"Adcon Construction",
    "wof:placetype":"venue"
},
  "geometry": {"coordinates":[-80.312726,25.89322],"type":"Point"}
}