{
  "type": "Feature",
  "properties": {
    "addr:full":"11051 SW 69th Dr Miami FL 33173",
    "addr:housenumber":"11051",
    "addr:postcode":"33173",
    "addr:street":"Sw 69Th Dr",
    "iso:country":"US",
    "sg:address":"11051 SW 69th Dr",
    "sg:city":"Miami",
    "sg:classifiers":[
        {
            "category":"Education",
            "subcategory":"Music School",
            "type":"Public Place"
        },
        {
            "category":"Education",
            "subcategory":"School",
            "type":"Public Place"
        }
    ],
    "sg:phone":"+1 305 388 2466",
    "sg:postcode":"33173",
    "sg:province":"FL",
    "wof:name":"Theatre & Music Arts Inc",
    "wof:placetype":"venue"
},
  "geometry": {"coordinates":[-80.373625,25.706776],"type":"Point"}
}