{
  "type": "Feature",
  "properties": {
    "addr:full":"3324 W University Ave # 125 Gainesville FL 32607",
    "addr:housenumber":"3324",
    "addr:postcode":"32607",
    "addr:street":"W University Ave # 125",
    "iso:country":"US",
    "sg:address":"3324 W University Ave # 125",
    "sg:city":"Gainesville",
    "sg:classifiers":[
        {
            "category":"Education",
            "subcategory":"Special Training",
            "type":"Public Place"
        }
    ],
    "sg:phone":"+1 352 336 8724",
    "sg:postcode":"32607",
    "sg:province":"FL",
    "sg:tags":[
        "educational"
    ],
    "wof:name":"Tutoringtraincom",
    "wof:placetype":"venue"
},
  "geometry": {"coordinates":[-82.37966900000001,29.651899],"type":"Point"}
}