{
  "type": "Feature",
  "properties": {
    "iso:country":"US",
    "sg:address":"136 S Woodland Blvd",
    "sg:city":"Deland",
    "sg:classifiers":[
        {
            "category":"Banks & Credit Unions",
            "subcategory":"Bank",
            "type":"Services"
        }
    ],
    "sg:phone":"+1 386 734 1931",
    "sg:postcode":"32720",
    "sg:province":"FL",
    "wof:name":"Fairwinds Credit Union",
    "wof:placetype":"venue"
},
  "geometry": {"coordinates":[-81.303493,29.027026],"type":"Point"}
}