{
  "type": "Feature",
  "properties": {
    "addr:full":"1215 Stevens Ave Orlando FL 32806",
    "addr:housenumber":"1215",
    "addr:postcode":"32806",
    "addr:street":"Stevens Ave",
    "iso:country":"US",
    "sg:address":"1215 Stevens Ave",
    "sg:city":"Orlando",
    "sg:classifiers":[
        {
            "category":"Building & Trades",
            "subcategory":"Plumbing",
            "type":"Services"
        }
    ],
    "sg:phone":"+1 407 240 2811",
    "sg:postcode":"32806",
    "sg:province":"FL",
    "sg:tags":[
        "conditioning",
        "air",
        "system",
        "contractor"
    ],
    "wof:name":"E & S Air Conditioning & Htg",
    "wof:placetype":"venue"
},
  "geometry": {"coordinates":[-81.35988999999999,28.496303],"type":"Point"}
}