{
  "type": "Feature",
  "properties": {
    "iso:country":"US",
    "sg:address":"2603 King Richard Rd",
    "sg:city":"Melbourne",
    "sg:classifiers":[
        {
            "category":"Building & Trades",
            "subcategory":"Construction",
            "type":"Services"
        }
    ],
    "sg:phone":"+1 321 253 9074",
    "sg:postcode":"32935",
    "sg:province":"FL",
    "sg:tags":[
        "carpentry",
        "contractor"
    ],
    "wof:name":"Thomas S Gustin Carpentery",
    "wof:placetype":"venue"
},
  "geometry": {"coordinates":[-80.664872,28.175094],"type":"Point"}
}