{
  "type": "Feature",
  "properties": {
    "addr:full":"1201 NW 8th St Pompano Beach FL 33069",
    "addr:housenumber":"1201",
    "addr:postcode":"33069",
    "addr:street":"Nw 8Th St",
    "iso:country":"US",
    "sg:address":"1201 NW 8th St",
    "sg:city":"Pompano Beach",
    "sg:classifiers":[
        {
            "category":"Building & Trades",
            "subcategory":"Plumbing",
            "type":"Services"
        }
    ],
    "sg:phone":"+1 954 943 9625",
    "sg:postcode":"33069",
    "sg:province":"FL",
    "sg:tags":[
        "plumbing",
        "contractor"
    ],
    "wof:name":"Coastal Plumbing Co Of Miami",
    "wof:placetype":"venue"
},
  "geometry": {"coordinates":[-80.137393,26.238498],"type":"Point"}
}