{
  "type": "Feature",
  "properties": {
    "iso:country":"US",
    "sg:address":"7331 NW 35th St",
    "sg:city":"Miami",
    "sg:classifiers":[
        {
            "category":"Wholesale",
            "subcategory":"Durable Goods & Equipment",
            "type":"Manufacturing & Wholesale Goods"
        }
    ],
    "sg:phone":"+1 305 471 0081",
    "sg:postcode":"33122",
    "sg:province":"FL",
    "sg:tags":[
        "exporter"
    ],
    "sg:website":"www.ezeformal.com",
    "wof:name":"Ezeformal Corp",
    "wof:placetype":"venue"
},
  "geometry": {"coordinates":[-80.31699500000001,25.806178],"type":"Point"}
}