{
  "type": "Feature",
  "properties": {
    "iso:country":"US",
    "sg:address":"8380 Baymeadows Rd",
    "sg:city":"Jacksonville",
    "sg:classifiers":[
        {
            "category":"Restaurant",
            "type":"Food & Drink"
        }
    ],
    "sg:menulink":"http://www.allmenus.com/fl/jacksonville/106200-steak-out/menu/",
    "sg:phone":"+1 904 733 5343",
    "sg:postcode":"32256",
    "sg:province":"FL",
    "sg:tags":[
        "american",
        "steakhouse"
    ],
    "wof:name":"Steak-Out",
    "wof:placetype":"venue"
},
  "geometry": {"coordinates":[-81.583545,30.2207],"type":"Point"}
}