{
  "type": "Feature",
  "properties": {
    "addr:full":"7534 Golden Glenn Dr Orlando FL 32807",
    "addr:housenumber":"7534",
    "addr:postcode":"32807",
    "addr:street":"Golden Glenn Dr",
    "iso:country":"US",
    "sg:address":"7534 Golden Glenn Dr",
    "sg:city":"Orlando",
    "sg:classifiers":[
        {
            "category":"Building & Trades",
            "subcategory":"Construction",
            "type":"Services"
        }
    ],
    "sg:phone":"+1 407 380 5186",
    "sg:postcode":"32807",
    "sg:province":"FL",
    "sg:tags":[
        "painter"
    ],
    "wof:name":"Scotty's Painting & Pressure",
    "wof:placetype":"venue"
},
  "geometry": {"coordinates":[-81.288124,28.559499],"type":"Point"}
}