{
  "type": "Feature",
  "properties": {
    "addr:full":"5606 Osprey Park Pl Lithia FL 33547",
    "addr:housenumber":"5606",
    "addr:postcode":"33547",
    "addr:street":"Osprey Park Pl",
    "iso:country":"US",
    "sg:address":"5606 Osprey Park Pl",
    "sg:city":"Lithia",
    "sg:classifiers":[
        {
            "category":"Shopping",
            "type":"Retail Goods"
        }
    ],
    "sg:phone":"+1 813 571 9419",
    "sg:postcode":"33547",
    "sg:province":"FL",
    "sg:tags":[
        "plant",
        "flower",
        "tree",
        "artificial"
    ],
    "wof:name":"Christine Ross Creations",
    "wof:placetype":"venue"
},
  "geometry": {"coordinates":[-82.230553,27.851521],"type":"Point"}
}