{
  "type": "Feature",
  "properties": {
    "iso:country":"US",
    "sg:address":"233 E State St",
    "sg:city":"Jacksonville",
    "sg:classifiers":[
        {
            "category":"Real Estate",
            "subcategory":"Real Estate Operator",
            "type":"Services"
        }
    ],
    "sg:phone":"+1 904 356 8491",
    "sg:postcode":"32202",
    "sg:province":"FL",
    "sg:tags":[
        "commercial"
    ],
    "wof:name":"Kings Bay Properties Ltd",
    "wof:placetype":"venue"
},
  "geometry": {"coordinates":[-81.65271799999999,30.332352],"type":"Point"}
}