{
  "type": "Feature",
  "properties": {
    "iso:country":"US",
    "sg:address":"1777 Blount Rd",
    "sg:city":"Pompano Beach",
    "sg:classifiers":[
        {
            "category":"Wholesale",
            "subcategory":"Non-durable Goods",
            "type":"Manufacturing & Wholesale Goods"
        }
    ],
    "sg:phone":"+1 954 979 2790",
    "sg:postcode":"33069",
    "sg:province":"FL",
    "sg:tags":[
        "novelty",
        "gift"
    ],
    "wof:name":"Brockmans Rack Service Inc",
    "wof:placetype":"venue"
},
  "geometry": {"coordinates":[-80.16389700000001,26.251382],"type":"Point"}
}