{
  "type": "Feature",
  "properties": {
    "iso:country":"US",
    "sg:address":"1409 Spring Loop Way",
    "sg:city":"Winter Garden",
    "sg:classifiers":[
        {
            "category":"Organizations",
            "subcategory":"Religious Organization",
            "type":"Services"
        }
    ],
    "sg:phone":"+1 407 656 9683",
    "sg:postcode":"34787",
    "sg:province":"FL",
    "sg:tags":[
        "church"
    ],
    "sg:website":"www.cfbiblechurch.org",
    "wof:name":"Central Florida Bible Church",
    "wof:placetype":"venue"
},
  "geometry": {"coordinates":[-81.567598,28.585297],"type":"Point"}
}