{
  "type": "Feature",
  "properties": {
    "iso:country":"US",
    "sg:address":"4412 N 56th St",
    "sg:city":"Tampa",
    "sg:classifiers":[
        {
            "category":"Professional",
            "subcategory":"Business Services",
            "type":"Services"
        },
        {
            "category":"Wholesale",
            "subcategory":"Books, Periodicals, & Newspapers",
            "type":"Manufacturing & Wholesale Goods"
        }
    ],
    "sg:phone":"+1 813 626 8877",
    "sg:postcode":"33610",
    "sg:province":"FL",
    "sg:tags":[
        "dealers-wholesale",
        "publisher",
        "news",
        "publishing",
        "consultant"
    ],
    "wof:name":"Tampa Tribune",
    "wof:placetype":"venue"
},
  "geometry": {"coordinates":[-82.39644199999999,27.985822],"type":"Point"}
}