{
  "type": "Feature",
  "properties": {
    "addr:full":"1270 Estero Blvd Fort Myers Beach FL 33931",
    "addr:housenumber":"1270",
    "addr:postcode":"33931",
    "addr:street":"Estero Blvd",
    "iso:country":"US",
    "sg:address":"1270 Estero Blvd",
    "sg:city":"Fort Myers Beach",
    "sg:classifiers":[
        {
            "category":"Real Estate",
            "subcategory":"Real Estate Agent",
            "type":"Services"
        }
    ],
    "sg:phone":"+1 239 765 2288",
    "sg:postcode":"33931",
    "sg:province":"FL",
    "wof:name":"Watermark Realty At The Beach",
    "wof:placetype":"venue"
},
  "geometry": {"coordinates":[-81.952558,26.452008],"type":"Point"}
}