{
  "type": "Feature",
  "properties": {
    "iso:country":"US",
    "sg:address":"1055 Aragon Ave",
    "sg:city":"Winter Park",
    "sg:classifiers":[
        {
            "category":"Professional",
            "subcategory":"Advertising",
            "type":"Services"
        }
    ],
    "sg:phone":"+1 407 595 4793",
    "sg:postcode":"32789",
    "sg:province":"FL",
    "sg:tags":[
        "marketing"
    ],
    "sg:website":"www.MpactOrlando.com",
    "wof:name":"Mpact Orlando",
    "wof:placetype":"venue"
},
  "geometry": {"coordinates":[-81.36312700000001,28.590843],"type":"Point"}
}