{
  "type": "Feature",
  "properties": {
    "iso:country":"US",
    "sg:address":"437 Lexingdale Dr",
    "sg:city":"Orlando",
    "sg:classifiers":[
        {
            "category":"Autos & Motor Vehicles",
            "subcategory":"Fuel & Gas Station",
            "type":"Retail Goods"
        }
    ],
    "sg:phone":"+1 407 380 1101",
    "sg:postcode":"32828",
    "sg:province":"FL",
    "sg:tags":[
        "station"
    ],
    "wof:name":"Shell",
    "wof:placetype":"venue"
},
  "geometry": {"coordinates":[-81.18955200000001,28.540386],"type":"Point"}
}