{
  "type": "Feature",
  "properties": {
    "addr:full":"2850 Tigertail Ave Miami FL 33133",
    "addr:postcode":"2850;33133",
    "addr:street":"Tigertail Ave",
    "iso:country":"US",
    "sg:address":"2850 Tigertail Ave",
    "sg:city":"Miami",
    "sg:classifiers":[
        {
            "category":"Banks & Credit Unions",
            "subcategory":"Bank",
            "type":"Services"
        }
    ],
    "sg:phone":"+1 305 860 0920",
    "sg:postcode":"33133",
    "sg:province":"FL",
    "wof:name":"Grove Compco",
    "wof:placetype":"venue"
},
  "geometry": {"coordinates":[-80.238805,25.730353],"type":"Point"}
}