{
  "type": "Feature",
  "properties": {
    "iso:country":"US",
    "sg:address":"7329 Dairy Rd",
    "sg:city":"Zephyrhills",
    "sg:classifiers":[
        {
            "category":"Place Of Worship",
            "subcategory":"Church",
            "type":"Public Place"
        },
        {
            "category":"Place Of Worship",
            "type":"Public Place"
        }
    ],
    "sg:phone":"+1 813 782 2000",
    "sg:postcode":"33540",
    "sg:province":"FL",
    "sg:tags":[
        "churches-seventh-day",
        "adventist",
        "christian",
        "churches-advent"
    ],
    "wof:name":"East Pasco Seventh Day Adventist Church",
    "wof:placetype":"venue"
},
  "geometry": {"coordinates":[-82.184067,28.26375],"type":"Point"}
}