{
  "type": "Feature",
  "properties": {
    "addr:full":"517 Deltona Blvd Deltona FL 32725",
    "addr:housenumber":"517",
    "addr:postcode":"32725",
    "addr:street":"Deltona Blvd",
    "iso:country":"US",
    "sg:address":"517 Deltona Blvd",
    "sg:city":"Deltona",
    "sg:classifiers":[
        {
            "category":"Health Services",
            "subcategory":"Clinic",
            "type":"Services"
        }
    ],
    "sg:phone":"+1 386 860 9993",
    "sg:postcode":"32725",
    "sg:province":"FL",
    "sg:tags":[
        "home"
    ],
    "wof:name":"Lincare",
    "wof:placetype":"venue"
},
  "geometry": {"coordinates":[-81.282099,28.876063],"type":"Point"}
}