{
  "type": "Feature",
  "properties": {
    "addr:full":"1324 Coral Ridge Dr Coral Springs FL 33071",
    "addr:housenumber":"1324",
    "addr:postcode":"33071",
    "addr:street":"Coral Ridge Dr",
    "iso:country":"US",
    "sg:address":"1324 Coral Ridge Dr",
    "sg:city":"Coral Springs",
    "sg:classifiers":[
        {
            "category":"Restaurant",
            "type":"Food & Drink"
        }
    ],
    "sg:phone":"+1 954 796 2344",
    "sg:postcode":"33071",
    "sg:province":"FL",
    "wof:name":"Subway Sandwiches & Salads",
    "wof:placetype":"venue"
},
  "geometry": {"coordinates":[-80.280441,26.250024],"type":"Point"}
}