{
  "type": "Feature",
  "properties": {
    "iso:country":"US",
    "sg:address":"1813 Dennis St",
    "sg:city":"Jacksonville",
    "sg:classifiers":[
        {
            "category":"Building & Trades",
            "subcategory":"Construction",
            "type":"Services"
        }
    ],
    "sg:phone":"+1 904 358 3362",
    "sg:postcode":"32204",
    "sg:province":"FL",
    "sg:tags":[
        "heavy"
    ],
    "wof:name":"Florida Floats",
    "wof:placetype":"venue"
},
  "geometry": {"coordinates":[-81.68027600000001,30.329215],"type":"Point"}
}