{
  "type": "Feature",
  "properties": {
    "addr:full":"5611 Warren St Naples FL 34113",
    "addr:housenumber":"5611",
    "addr:postcode":"34113",
    "addr:street":"Warren St",
    "iso:country":"US",
    "sg:address":"5611 Warren St",
    "sg:city":"Naples",
    "sg:classifiers":[
        {
            "category":"Social Services",
            "type":"Services"
        }
    ],
    "sg:phone":"+1 239 775 9550",
    "sg:postcode":"34113",
    "sg:province":"FL",
    "sg:tags":[
        "youth",
        "organization",
        "center"
    ],
    "wof:name":"Gulf Coast Little League Inc",
    "wof:placetype":"venue"
},
  "geometry": {"coordinates":[-81.726552,26.096832],"type":"Point"}
}