{
  "type": "Feature",
  "properties": {
    "addr:full":"2149 NE 56th Ct Fort Lauderdale FL 33308",
    "addr:housenumber":"2149",
    "addr:postcode":"33308",
    "addr:street":"Ne 56Th Ct",
    "iso:country":"US",
    "sg:address":"2149 NE 56th Ct",
    "sg:city":"Fort Lauderdale",
    "sg:classifiers":[
        {
            "category":"Professional",
            "subcategory":"Art Services",
            "type":"Services"
        }
    ],
    "sg:phone":"+1 954 771 2222",
    "sg:postcode":"33308",
    "sg:province":"FL",
    "sg:tags":[
        "packaging",
        "invention",
        "commercial"
    ],
    "wof:name":"Modernage Consumer Products",
    "wof:placetype":"venue"
},
  "geometry": {"coordinates":[-80.117012,26.197397],"type":"Point"}
}