{
  "type": "Feature",
  "properties": {
    "iso:country":"US",
    "sg:address":"456 S Cypress Rd",
    "sg:city":"Pompano Beach",
    "sg:classifiers":[
        {
            "category":"Restaurant",
            "type":"Food & Drink"
        }
    ],
    "sg:phone":"+1 954 781 3769",
    "sg:postcode":"33060",
    "sg:province":"FL",
    "sg:tags":[
        "delivery",
        "eating"
    ],
    "wof:name":"Canton Chinese Food",
    "wof:placetype":"venue"
},
  "geometry": {"coordinates":[-80.123206,26.224116],"type":"Point"}
}