{
  "type": "Feature",
  "properties": {
    "addr:full":"8040 Peters Rd Fort Lauderdale FL 33324",
    "addr:housenumber":"8040",
    "addr:postcode":"33324",
    "addr:street":"Peters Rd",
    "iso:country":"US",
    "sg:address":"8040 Peters Rd",
    "sg:city":"Fort Lauderdale",
    "sg:classifiers":[
        {
            "category":"Insurance",
            "subcategory":"Insurance Agent",
            "type":"Services"
        }
    ],
    "sg:phone":"+1 954 370 2345",
    "sg:postcode":"33324",
    "sg:province":"FL",
    "wof:name":"State Farm Insurance",
    "wof:placetype":"venue"
},
  "geometry": {"coordinates":[-80.255416,26.105328],"type":"Point"}
}