{
  "type": "Feature",
  "properties": {
    "iso:country":"US",
    "sg:address":"1777 W Schwartz Blvd",
    "sg:city":"Lady Lake",
    "sg:classifiers":[
        {
            "category":"Freight",
            "type":"Transportation"
        }
    ],
    "sg:phone":"+1 352 259 5670",
    "sg:postcode":"32159",
    "sg:province":"FL",
    "sg:tags":[
        "operator",
        "local",
        "trucking"
    ],
    "wof:name":"Abramovich Trucking",
    "wof:placetype":"venue"
},
  "geometry": {"coordinates":[-81.949181,28.959638],"type":"Point"}
}