{
  "type": "Feature",
  "properties": {
    "iso:country":"US",
    "sg:address":"2601 NW 32nd Ave",
    "sg:city":"Miami",
    "sg:classifiers":[
        {
            "category":"Wholesale",
            "subcategory":"Scrap",
            "type":"Manufacturing & Wholesale Goods"
        }
    ],
    "sg:phone":"+1 305 634 8777",
    "sg:postcode":"33142",
    "sg:province":"FL",
    "sg:tags":[
        "metal"
    ],
    "wof:name":"American Metals & Scrape",
    "wof:placetype":"venue"
},
  "geometry": {"coordinates":[-80.248222,25.79966],"type":"Point"}
}