{
  "type": "Feature",
  "properties": {
    "iso:country":"US",
    "sg:address":"25010 Cypress Hollow Ct",
    "sg:city":"Bonita Springs",
    "sg:classifiers":[
        {
            "category":"Shopping",
            "subcategory":"Optical Goods",
            "type":"Retail Goods"
        }
    ],
    "sg:phone":"+1 239 947 1643",
    "sg:postcode":"34134",
    "sg:province":"FL",
    "wof:name":"Cieslinski Jodell",
    "wof:placetype":"venue"
},
  "geometry": {"coordinates":[-81.818912,26.38333],"type":"Point"}
}