{
  "type": "Feature",
  "properties": {
    "iso:country":"US",
    "sg:address":"422 Linda Ave",
    "sg:city":"Panama City",
    "sg:classifiers":[
        {
            "category":"Retail",
            "subcategory":"Portrait Studio",
            "type":"Services"
        }
    ],
    "sg:phone":"+1 850 215 8361",
    "sg:postcode":"32401",
    "sg:province":"FL",
    "sg:tags":[
        "photographer"
    ],
    "wof:name":"Jan Bus Designs",
    "wof:placetype":"venue"
},
  "geometry": {"coordinates":[-85.654155,30.152716],"type":"Point"}
}