{
  "type": "Feature",
  "properties": {
    "addr:full":"513 10th St Lake Park FL 33403",
    "addr:housenumber":"513",
    "addr:postcode":"33403",
    "addr:street":"10Th St",
    "iso:country":"US",
    "sg:address":"513 10th St",
    "sg:city":"Lake Park",
    "sg:classifiers":[
        {
            "category":"Freight",
            "type":"Transportation"
        }
    ],
    "sg:phone":"+1 561 863 8442",
    "sg:postcode":"33403",
    "sg:province":"FL",
    "sg:tags":[
        "transfer",
        "express"
    ],
    "wof:name":"Cam Feu-Vert Express",
    "wof:placetype":"venue"
},
  "geometry": {"coordinates":[-80.072107,26.79735],"type":"Point"}
}