{
  "type": "Feature",
  "properties": {
    "addr:full":"18400 NW 75th Pl Ste 123 Hialeah FL 33015",
    "addr:housenumber":"18400",
    "addr:postcode":"33015",
    "addr:street":"Nw 75Th Pl Ste 123",
    "iso:country":"US",
    "sg:address":"18400 NW 75th Pl Ste 123",
    "sg:city":"Hialeah",
    "sg:classifiers":[
        {
            "category":"Shopping",
            "subcategory":"Hobbies, Toys, & Games",
            "type":"Retail Goods"
        }
    ],
    "sg:phone":"+1 305 823 8083",
    "sg:postcode":"33015",
    "sg:province":"FL",
    "sg:tags":[
        "shop",
        "hobby"
    ],
    "wof:name":"West Arcade",
    "wof:placetype":"venue"
},
  "geometry": {"coordinates":[-80.322762,25.941153],"type":"Point"}
}