{
  "type": "Feature",
  "properties": {
    "addr:full":"8473 Cooper Creek Blvd University Park FL 34201",
    "addr:housenumber":"8473",
    "addr:postcode":"34201",
    "addr:street":"Cooper Creek Blvd",
    "iso:country":"US",
    "sg:address":"8473 Cooper Creek Blvd",
    "sg:city":"University Park",
    "sg:classifiers":[
        {
            "category":"Health Services",
            "subcategory":"Health Practitioner",
            "type":"Services"
        }
    ],
    "sg:phone":"+1 941 360 0025",
    "sg:postcode":"34201",
    "sg:province":"FL",
    "sg:tags":[
        "nutritionist"
    ],
    "wof:name":"Nutrition Care",
    "wof:placetype":"venue"
},
  "geometry": {"coordinates":[-82.45588600000001,27.389221],"type":"Point"}
}