{
  "type": "Feature",
  "properties": {
    "iso:country":"US",
    "sg:address":"1528 Carlotta Rd W",
    "sg:city":"Jacksonville",
    "sg:classifiers":[
        {
            "category":"Organizations",
            "subcategory":"Religious Organization",
            "type":"Services"
        }
    ],
    "sg:phone":"+1 904 805 8957",
    "sg:postcode":"32211",
    "sg:province":"FL",
    "wof:name":"Hearts of Fire Inc",
    "wof:placetype":"venue"
},
  "geometry": {"coordinates":[-81.57925899999999,30.336721],"type":"Point"}
}