{
  "type": "Feature",
  "properties": {
    "iso:country":"US",
    "sg:address":"4141 Tamiami Trl",
    "sg:city":"Venice",
    "sg:classifiers":[
        {
            "category":"Personal",
            "subcategory":"Beauty Salon",
            "type":"Services"
        }
    ],
    "sg:phone":"+1 941 497 4218",
    "sg:postcode":"34293",
    "sg:province":"FL",
    "wof:name":"Great Clips",
    "wof:placetype":"venue"
},
  "geometry": {"coordinates":[-82.397593,27.049906],"type":"Point"}
}