{
  "type": "Feature",
  "properties": {
    "iso:country":"US",
    "sg:address":"855 E State Road 434",
    "sg:city":"Winter Springs",
    "sg:classifiers":[
        {
            "category":"Sports & Exercise",
            "subcategory":"Gym",
            "type":"Entertainment"
        }
    ],
    "sg:phone":"+1 407 327 4336",
    "sg:postcode":"32708",
    "sg:province":"FL",
    "sg:tags":[
        "trainer"
    ],
    "wof:name":"Anytime Fitness of Wintersprings",
    "wof:placetype":"venue"
},
  "geometry": {"coordinates":[-81.28616599999999,28.704033],"type":"Point"}
}