{
  "type": "Feature",
  "properties": {
    "iso:country":"US",
    "sg:address":"101 Park Place Blvd Ste 3",
    "sg:city":"Kissimmee",
    "sg:classifiers":[
        {
            "category":"Organizations",
            "subcategory":"Professional Association",
            "type":"Services"
        }
    ],
    "sg:phone":"+1 407 847 3099",
    "sg:postcode":"34741",
    "sg:province":"FL",
    "sg:tags":[
        "business",
        "trade"
    ],
    "wof:name":"Blackberry Creek And St Cloud Commerce C",
    "wof:placetype":"venue"
},
  "geometry": {"coordinates":[-81.404022,28.314369],"type":"Point"}
}