{
  "type": "Feature",
  "properties": {
    "iso:country":"US",
    "sg:address":"7508 Universal Blvd",
    "sg:city":"Orlando",
    "sg:classifiers":[
        {
            "category":"Recreation",
            "type":"Entertainment"
        }
    ],
    "sg:phone":"+1 407 363 1985",
    "sg:postcode":"32819",
    "sg:province":"FL",
    "sg:tags":[
        "theatrical"
    ],
    "wof:name":"Sleuths Mystery Dinner Show",
    "wof:placetype":"venue"
},
  "geometry": {"coordinates":[-81.464485,28.454737],"type":"Point"}
}