{
  "type": "Feature",
  "properties": {
    "addr:full":"1014 N E St Pensacola FL 32501",
    "addr:housenumber":"1014",
    "addr:postcode":"32501",
    "addr:street":"N E St",
    "iso:country":"US",
    "sg:address":"1014 N E St",
    "sg:city":"Pensacola",
    "sg:classifiers":[
        {
            "category":"Place Of Worship",
            "type":"Public Place"
        },
        {
            "category":"Organizations",
            "subcategory":"Religious Organization",
            "type":"Services"
        }
    ],
    "sg:phone":"+1 850 435 2916",
    "sg:postcode":"32501",
    "sg:province":"FL",
    "sg:tags":[
        "clergy",
        "church"
    ],
    "wof:name":"Elder Ossie Brundidge Pastor",
    "wof:placetype":"venue"
},
  "geometry": {"coordinates":[-87.229964,30.422301],"type":"Point"}
}