{
  "type": "Feature",
  "properties": {
    "addr:full":"4081 S McCall Rd Englewood FL 34224",
    "addr:housenumber":"4081",
    "addr:postcode":"34224",
    "addr:street":"S Mccall Rd",
    "iso:country":"US",
    "sg:address":"4081 S McCall Rd",
    "sg:city":"Englewood",
    "sg:classifiers":[
        {
            "category":"Personal",
            "subcategory":"Beauty Salon",
            "type":"Services"
        }
    ],
    "sg:phone":"+1 941 460 9596",
    "sg:postcode":"34224",
    "sg:province":"FL",
    "sg:tags":[
        "treatment",
        "skin"
    ],
    "wof:name":"Linda Woerner Massage Therapy",
    "wof:placetype":"venue"
},
  "geometry": {"coordinates":[-82.27300700000001,26.932662],"type":"Point"}
}