{
  "type": "Feature",
  "properties": {
    "iso:country":"US",
    "sg:address":"6191 Orange Dr",
    "sg:city":"Davie",
    "sg:classifiers":[
        {
            "category":"Real Estate",
            "subcategory":"Real Estate Agent",
            "type":"Services"
        }
    ],
    "sg:phone":"+1 954 791 5202",
    "sg:postcode":"33314",
    "sg:province":"FL",
    "wof:name":"Tropical Dream Realty",
    "wof:placetype":"venue"
},
  "geometry": {"coordinates":[-80.228296,26.065877],"type":"Point"}
}