{
  "type": "Feature",
  "properties": {
    "iso:country":"US",
    "sg:address":"23104 Island Vw",
    "sg:city":"Boca Raton",
    "sg:classifiers":[
        {
            "category":"Shopping",
            "subcategory":"Shoes",
            "type":"Retail Goods"
        }
    ],
    "sg:phone":"+1 561 394 4100",
    "sg:postcode":"33433",
    "sg:province":"FL",
    "wof:name":"Skatts USA Inc",
    "wof:placetype":"venue"
},
  "geometry": {"coordinates":[-80.138351,26.333945],"type":"Point"}
}