{
  "type": "Feature",
  "properties": {
    "addr:full":"6585 Autumn Woods Blvd Naples FL 34109",
    "addr:housenumber":"6585",
    "addr:postcode":"34109",
    "addr:street":"Autumn Woods Blvd",
    "iso:country":"US",
    "sg:address":"6585 Autumn Woods Blvd",
    "sg:city":"Naples",
    "sg:classifiers":[
        {
            "category":"Real Estate",
            "subcategory":"Real Estate Agent",
            "type":"Services"
        }
    ],
    "sg:phone":"+1 239 593 2134",
    "sg:postcode":"34109",
    "sg:province":"FL",
    "sg:tags":[
        "appraiser"
    ],
    "wof:name":"Donald R Johnson",
    "wof:placetype":"venue"
},
  "geometry": {"coordinates":[-81.78760200000001,26.227074],"type":"Point"}
}