{
  "type": "Feature",
  "properties": {
    "addr:full":"1485 NW 70th Ln Margate FL 33063",
    "addr:housenumber":"1485",
    "addr:postcode":"33063",
    "addr:street":"Nw 70Th Ln Margate",
    "iso:country":"US",
    "sg:address":"1485 NW 70th Ln",
    "sg:city":"Margate",
    "sg:classifiers":[
        {
            "category":"Building & Trades",
            "subcategory":"Landscaping Services",
            "type":"Services"
        }
    ],
    "sg:phone":"+1 954 974 7611",
    "sg:postcode":"33063",
    "sg:province":"FL",
    "sg:tags":[
        "tree"
    ],
    "wof:name":"Palm Tree Rescue",
    "wof:placetype":"venue"
},
  "geometry": {"coordinates":[-80.220088,26.247201],"type":"Point"}
}