{
  "type": "Feature",
  "properties": {
    "addr:full":"21 Comanche Ct Palm Coast FL 32137",
    "addr:housenumber":"21",
    "addr:postcode":"32137",
    "addr:street":"Comanche Ct",
    "iso:country":"US",
    "sg:address":"21 Comanche Ct",
    "sg:city":"Palm Coast",
    "sg:classifiers":[
        {
            "category":"Wholesale",
            "subcategory":"Hardware",
            "type":"Manufacturing & Wholesale Goods"
        }
    ],
    "sg:phone":"+1 386 447 6580",
    "sg:postcode":"32137",
    "sg:province":"FL",
    "wof:name":"Quepac Associates Inc",
    "wof:placetype":"venue"
},
  "geometry": {"coordinates":[-81.205764,29.598531],"type":"Point"}
}