{
  "type": "Feature",
  "properties": {
    "iso:country":"US",
    "sg:address":"3809 Ford St",
    "sg:city":"New Port Richey",
    "sg:classifiers":[
        {
            "category":"Building & Trades",
            "subcategory":"Cleaning & Sanitation",
            "type":"Services"
        }
    ],
    "sg:phone":"+1 727 819 1835",
    "sg:postcode":"34655",
    "sg:province":"FL",
    "sg:tags":[
        "janitor"
    ],
    "wof:name":"Thomas Bell Janitorial",
    "wof:placetype":"venue"
},
  "geometry": {"coordinates":[-82.698207,28.213877],"type":"Point"}
}