{
  "type": "Feature",
  "properties": {
    "addr:full":"3515 Morgan Johnson Rd Bradenton FL 34208",
    "addr:housenumber":"3515",
    "addr:postcode":"34208",
    "addr:street":"Morgan Johnson Rd",
    "iso:country":"US",
    "sg:address":"3515 Morgan Johnson Rd",
    "sg:city":"Bradenton",
    "sg:classifiers":[
        {
            "category":"Education",
            "subcategory":"School",
            "type":"Public Place"
        }
    ],
    "sg:phone":"+1 941 741 3307",
    "sg:postcode":"34208",
    "sg:province":"FL",
    "wof:name":"William H Bashaw Elementary",
    "wof:placetype":"venue"
},
  "geometry": {"coordinates":[-82.489304,27.46916],"type":"Point"}
}