{
  "type": "Feature",
  "properties": {
    "iso:country":"US",
    "sg:address":"6411 SW 113th Pl",
    "sg:city":"Miami",
    "sg:classifiers":[
        {
            "category":"Professional",
            "type":"Services"
        }
    ],
    "sg:phone":"+1 305 969 2391",
    "sg:postcode":"33173",
    "sg:province":"FL",
    "wof:name":"Kym Limited Inc",
    "wof:placetype":"venue"
},
  "geometry": {"coordinates":[-80.377813,25.708418],"type":"Point"}
}