{
  "type": "Feature",
  "properties": {
    "iso:country":"US",
    "sg:address":"8601 4th St N",
    "sg:city":"St Petersburg",
    "sg:classifiers":[
        {
            "category":"Home & Garden",
            "subcategory":"Building Materials",
            "type":"Retail Goods"
        }
    ],
    "sg:phone":"+1 727 579 8574",
    "sg:postcode":"33702",
    "sg:province":"FL",
    "sg:tags":[
        "screen",
        "window"
    ],
    "wof:name":"Southern Aluminum Systems Inc",
    "wof:placetype":"venue"
},
  "geometry": {"coordinates":[-82.638769,27.851613],"type":"Point"}
}