{
  "type": "Feature",
  "properties": {
    "iso:country":"US",
    "sg:address":"9500 S Ocean Dr",
    "sg:city":"Jensen Beach",
    "sg:classifiers":[
        {
            "category":"Real Estate",
            "subcategory":"Real Estate Operator",
            "type":"Services"
        }
    ],
    "sg:phone":"+1 772 229 2802",
    "sg:postcode":"34957",
    "sg:province":"FL",
    "sg:tags":[
        "building",
        "apartment"
    ],
    "wof:name":"Islandia 2 Condo Association",
    "wof:placetype":"venue"
},
  "geometry": {"coordinates":[-80.216848,27.296281],"type":"Point"}
}