{
  "type": "Feature",
  "properties": {
    "iso:country":"US",
    "sg:address":"1473 Hunter Ln",
    "sg:city":"Clearwater",
    "sg:classifiers":[
        {
            "category":"Autos & Motor Vehicles",
            "subcategory":"Auto Supplies",
            "type":"Retail Goods"
        }
    ],
    "sg:phone":"+1 727 531 5198",
    "sg:postcode":"33764",
    "sg:province":"FL",
    "sg:tags":[
        "automotive",
        "tow",
        "dolly"
    ],
    "wof:name":"Beilage Enterprises",
    "wof:placetype":"venue"
},
  "geometry": {"coordinates":[-82.758702,27.943979],"type":"Point"}
}