{
  "type": "Feature",
  "properties": {
    "addr:full":"233 Sarasota Center Blvd Sarasota FL 34240",
    "addr:housenumber":"233",
    "addr:postcode":"34240",
    "addr:street":"Sarasota Center Blvd",
    "iso:country":"US",
    "sg:address":"233 Sarasota Center Blvd",
    "sg:city":"Sarasota",
    "sg:classifiers":[
        {
            "category":"Manufacturing",
            "subcategory":"Metals",
            "type":"Manufacturing & Wholesale Goods"
        }
    ],
    "sg:phone":"+1 941 377 5766",
    "sg:postcode":"34240",
    "sg:province":"FL",
    "sg:tags":[
        "spring"
    ],
    "wof:name":"Cook Spring Co",
    "wof:placetype":"venue"
},
  "geometry": {"coordinates":[-82.404791,27.346212],"type":"Point"}
}