{
  "type": "Feature",
  "properties": {
    "addr:full":"22419 Old Bellamy Rd Alachua FL 32615",
    "addr:housenumber":"22419",
    "addr:postcode":"32615",
    "addr:street":"Old Bellamy Rd",
    "iso:country":"US",
    "sg:address":"22419 Old Bellamy Rd",
    "sg:city":"Alachua",
    "sg:classifiers":[
        {
            "category":"Wholesale",
            "subcategory":"Farm Supplies",
            "type":"Manufacturing & Wholesale Goods"
        }
    ],
    "sg:phone":"+1 386 462 5428",
    "sg:postcode":"32615",
    "sg:province":"FL",
    "sg:tags":[
        "livestock"
    ],
    "wof:name":"McFadden Hill  and Means",
    "wof:placetype":"venue"
},
  "geometry": {"coordinates":[-82.514996,29.854972],"type":"Point"}
}