{
  "type": "Feature",
  "properties": {
    "addr:full":"4715 6th St Sebring FL 33870",
    "addr:housenumber":"4715",
    "addr:postcode":"33870",
    "addr:street":"6Th St",
    "iso:country":"US",
    "sg:address":"4715 6th St",
    "sg:city":"Sebring",
    "sg:classifiers":[
        {
            "category":"Professional",
            "type":"Services"
        }
    ],
    "sg:phone":"+1 863 385 2007",
    "sg:postcode":"33870",
    "sg:province":"FL",
    "sg:tags":[
        "establishment"
    ],
    "wof:name":"Toys For Kids",
    "wof:placetype":"venue"
},
  "geometry": {"coordinates":[-81.419483,27.482055],"type":"Point"}
}