{
  "type": "Feature",
  "properties": {
    "addr:full":"3012 Calumet Dr Orlando FL 32810",
    "addr:housenumber":"3012",
    "addr:postcode":"32810",
    "addr:street":"Calumet Dr",
    "iso:country":"US",
    "sg:address":"3012 Calumet Dr",
    "sg:city":"Orlando",
    "sg:classifiers":[
        {
            "category":"Manufacturing",
            "subcategory":"Tools & Machinery",
            "type":"Manufacturing & Wholesale Goods"
        }
    ],
    "sg:phone":"+1 407 625 5438",
    "sg:postcode":"32810",
    "sg:province":"FL",
    "sg:tags":[
        "stairway",
        "moving",
        "elevator"
    ],
    "wof:name":"Mobility Equipment and Service",
    "wof:placetype":"venue"
},
  "geometry": {"coordinates":[-81.41887,28.637723],"type":"Point"}
}