{
  "type": "Feature",
  "properties": {
    "addr:full":"1043 Plantation Oaks Dr E Jacksonville Beach FL 32250",
    "addr:housenumber":"1043",
    "addr:postcode":"32250",
    "addr:street":"Plantation Oaks Dr E",
    "iso:country":"US",
    "sg:address":"1043 Plantation Oaks Dr E",
    "sg:city":"Jacksonville Beach",
    "sg:classifiers":[
        {
            "category":"Professional",
            "type":"Services"
        }
    ],
    "sg:phone":"+1 904 247 5225",
    "sg:postcode":"32250",
    "sg:province":"FL",
    "wof:name":"Tradersedge Inc",
    "wof:placetype":"venue"
},
  "geometry": {"coordinates":[-81.403943,30.277394],"type":"Point"}
}