{
  "type": "Feature",
  "properties": {
    "addr:full":"2121 S US Hwy 1 Jupiter FL 33477",
    "addr:housenumber":"2121",
    "addr:postcode":"33477",
    "addr:street":"S Us Hwy 1",
    "iso:country":"US",
    "sg:address":"2121 S US Hwy 1",
    "sg:city":"Jupiter",
    "sg:classifiers":[
        {
            "category":"Shopping",
            "subcategory":"Gifts & Souvenirs",
            "type":"Retail Goods"
        }
    ],
    "sg:phone":"+1 561 743 2854",
    "sg:postcode":"33477",
    "sg:province":"FL",
    "sg:tags":[
        "shop"
    ],
    "wof:name":"Belle Maison",
    "wof:placetype":"venue"
},
  "geometry": {"coordinates":[-80.07055699999999,26.913589],"type":"Point"}
}