{
  "type": "Feature",
  "properties": {
    "iso:country":"US",
    "sg:address":"8221 Glades Rd",
    "sg:city":"Boca Raton",
    "sg:classifiers":[
        {
            "category":"Restaurant",
            "type":"Food & Drink"
        }
    ],
    "sg:menulink":"http://www.allmenus.com/fl/sunshine-parkway/246778-red-lantern/menu/",
    "sg:phone":"+1 561 470 5993",
    "sg:postcode":"33434",
    "sg:province":"FL",
    "sg:tags":[
        "asian",
        "chinese"
    ],
    "wof:name":"Red Lantern",
    "wof:placetype":"venue"
},
  "geometry": {"coordinates":[-80.173863,26.368403],"type":"Point"}
}