{
  "type": "Feature",
  "properties": {
    "iso:country":"US",
    "sg:address":"5811 30th Ct E",
    "sg:city":"Ellenton",
    "sg:classifiers":[
        {
            "category":"Shopping",
            "subcategory":"Pets & Pet Supplies",
            "type":"Retail Goods"
        }
    ],
    "sg:phone":"+1 941 729 1030",
    "sg:postcode":"34222",
    "sg:province":"FL",
    "sg:tags":[
        "specialty"
    ],
    "wof:name":"The Cat's Lore",
    "wof:placetype":"venue"
},
  "geometry": {"coordinates":[-82.504597,27.540349],"type":"Point"}
}