{
  "type": "Feature",
  "properties": {
    "iso:country":"US",
    "sg:address":"710 E Silver Springs Blvd",
    "sg:city":"Ocala",
    "sg:classifiers":[
        {
            "category":"Real Estate",
            "subcategory":"Real Estate Agent",
            "type":"Services"
        }
    ],
    "sg:phone":"+1 352 351 2121",
    "sg:postcode":"34470",
    "sg:province":"FL",
    "sg:website":"www.abcrealtyocala.com",
    "wof:name":"ABC Realty",
    "wof:placetype":"venue"
},
  "geometry": {"coordinates":[-82.13168400000001,29.187024],"type":"Point"}
}