{
  "type": "Feature",
  "properties": {
    "addr:full":"501 N Orlando Ave. #141 Winter Park FL 32789",
    "addr:housenumber":"501",
    "addr:postcode":"32789",
    "addr:street":"N Orlando Ave. # 141",
    "iso:country":"US",
    "sg:address":"501 N Orlando Ave. #141",
    "sg:city":"Winter Park",
    "sg:classifiers":[
        {
            "category":"Education",
            "subcategory":"Special Training",
            "type":"Public Place"
        },
        {
            "category":"Retail",
            "subcategory":"Event Space",
            "type":"Services"
        }
    ],
    "sg:phone":"+1 407 644 8088",
    "sg:postcode":"32789",
    "sg:province":"FL",
    "sg:tags":[
        "venue",
        "school",
        "art"
    ],
    "sg:website":"www.glazeunderfire.com/contact.html",
    "wof:name":"Glaze Under Fire",
    "wof:placetype":"venue"
},
  "geometry": {"coordinates":[-81.365122,28.601645],"type":"Point"}
}