{
  "type": "Feature",
  "properties": {
    "iso:country":"US",
    "sg:address":"1175 NE 125th St",
    "sg:city":"North Miami",
    "sg:classifiers":[
        {
            "category":"Professional",
            "type":"Services"
        }
    ],
    "sg:phone":"+1 305 892 2074",
    "sg:postcode":"33161",
    "sg:province":"FL",
    "sg:tags":[
        "establishment"
    ],
    "wof:name":"Doris Amaya & Assoc Pa",
    "wof:placetype":"venue"
},
  "geometry": {"coordinates":[-80.174696,25.890824],"type":"Point"}
}