{
  "type": "Feature",
  "properties": {
    "iso:country":"US",
    "sg:address":"2220 Trescott Dr",
    "sg:city":"Tallahassee",
    "sg:classifiers":[
        {
            "category":"Home & Garden",
            "subcategory":"Carpets & Floor Coverings",
            "type":"Retail Goods"
        }
    ],
    "sg:phone":"+1 850 385 4534",
    "sg:postcode":"32308",
    "sg:province":"FL",
    "wof:name":"Ricky Beltz Floor Covering",
    "wof:placetype":"venue"
},
  "geometry": {"coordinates":[-84.257131,30.470626],"type":"Point"}
}