{
  "type": "Feature",
  "properties": {
    "iso:country":"US",
    "sg:address":"13 NW 19th Ave",
    "sg:city":"Miami",
    "sg:classifiers":[
        {
            "category":"Professional",
            "subcategory":"Accounting & Tax Preparation",
            "type":"Services"
        }
    ],
    "sg:phone":"+1 305 643 8088",
    "sg:postcode":"33125",
    "sg:province":"FL",
    "wof:name":"R & G Community Services",
    "wof:placetype":"venue"
},
  "geometry": {"coordinates":[-80.22687000000001,25.772987],"type":"Point"}
}