{
  "type": "Feature",
  "properties": {
    "iso:country":"US",
    "sg:address":"7512 State Rd 52",
    "sg:city":"Hudson",
    "sg:classifiers":[
        {
            "category":"Shopping",
            "subcategory":"Optical Goods",
            "type":"Retail Goods"
        },
        {
            "category":"Health Services",
            "subcategory":"Optometrist",
            "type":"Services"
        }
    ],
    "sg:phone":"+1 727 862 4444",
    "sg:postcode":"34667",
    "sg:province":"FL",
    "wof:name":"Eyewear Creations",
    "wof:placetype":"venue"
},
  "geometry": {"coordinates":[-82.690726,28.331174],"type":"Point"}
}