{
  "type": "Feature",
  "properties": {
    "addr:full":"625 Tamiami Trl N Venice FL 34285",
    "addr:housenumber":"625",
    "addr:postcode":"34285",
    "addr:street":"Tamiami Trl N",
    "iso:country":"US",
    "sg:address":"625 Tamiami Trl N",
    "sg:city":"Venice",
    "sg:classifiers":[
        {
            "category":"Travel",
            "subcategory":"Hotels & Motels",
            "type":"Entertainment"
        }
    ],
    "sg:phone":"+1 941 484 9559",
    "sg:postcode":"34285",
    "sg:province":"FL",
    "wof:name":"Veranda Inn And Kingfish Cafe",
    "wof:placetype":"venue"
},
  "geometry": {"coordinates":[-82.444107,27.105937],"type":"Point"}
}