{
  "type": "Feature",
  "properties": {
    "iso:country":"US",
    "sg:address":"6610 33rd St E",
    "sg:city":"Sarasota",
    "sg:classifiers":[
        {
            "category":"Manufacturing",
            "subcategory":"Metals",
            "type":"Manufacturing & Wholesale Goods"
        }
    ],
    "sg:phone":"+1 941 753 9598",
    "sg:postcode":"34243",
    "sg:province":"FL",
    "sg:tags":[
        "stampings",
        "sheet",
        "fabrication",
        "mfg"
    ],
    "sg:website":"www.gatorstamping.com",
    "wof:name":"Gator Stamping",
    "wof:placetype":"venue"
},
  "geometry": {"coordinates":[-82.52194900000001,27.420191],"type":"Point"}
}