{
  "type": "Feature",
  "properties": {
    "iso:country":"US",
    "sg:address":"1055 Shaw Lake Rd",
    "sg:city":"Pierson",
    "sg:classifiers":[
        {
            "category":"Professional",
            "type":"Services"
        }
    ],
    "sg:phone":"+1 386 749 2354",
    "sg:postcode":"32180",
    "sg:province":"FL",
    "sg:tags":[
        "establishment"
    ],
    "wof:name":"Jones T Larry Inc",
    "wof:placetype":"venue"
},
  "geometry": {"coordinates":[-81.44737499999999,29.244197],"type":"Point"}
}