{
  "type": "Feature",
  "properties": {
    "iso:country":"US",
    "sg:address":"405 Dunlawton Ave",
    "sg:city":"Port Orange",
    "sg:classifiers":[
        {
            "category":"Banks & Credit Unions",
            "subcategory":"Bank",
            "type":"Services"
        }
    ],
    "sg:phone":"+1 386 304 6577",
    "sg:postcode":"32127",
    "sg:province":"FL",
    "wof:name":"Commercial Bank-Volusia County",
    "wof:placetype":"venue"
},
  "geometry": {"coordinates":[-80.992591,29.142639],"type":"Point"}
}