{
  "type": "Feature",
  "properties": {
    "iso:country":"US",
    "sg:address":"12200 N Main St",
    "sg:city":"Jacksonville",
    "sg:classifiers":[
        {
            "category":"Wholesale",
            "subcategory":"Groceries",
            "type":"Manufacturing & Wholesale Goods"
        }
    ],
    "sg:phone":"+1 904 714 2367",
    "sg:postcode":"32218",
    "sg:province":"FL",
    "sg:tags":[
        "beverage"
    ],
    "wof:name":"Castelton Beverages",
    "wof:placetype":"venue"
},
  "geometry": {"coordinates":[-81.63484699999999,30.460594],"type":"Point"}
}