{
  "type": "Feature",
  "properties": {
    "addr:full":"13425 NW 102nd Ave Hialeah FL 33018",
    "addr:housenumber":"13425",
    "addr:postcode":"33018",
    "addr:street":"Nw 102Nd Ave",
    "iso:country":"US",
    "sg:address":"13425 NW 102nd Ave",
    "sg:city":"Hialeah",
    "sg:classifiers":[
        {
            "category":"Retail",
            "subcategory":"Auto Repair",
            "type":"Services"
        }
    ],
    "sg:phone":"+1 305 362 7730",
    "sg:postcode":"33018",
    "sg:province":"FL",
    "sg:tags":[
        "truck",
        "van"
    ],
    "wof:name":"GP & L",
    "wof:placetype":"venue"
},
  "geometry": {"coordinates":[-80.36429800000001,25.896741],"type":"Point"}
}