{
  "type": "Feature",
  "properties": {
    "iso:country":"US",
    "sg:address":"4841 Prunty St",
    "sg:city":"Jacksonville",
    "sg:classifiers":[
        {
            "category":"Building & Trades",
            "subcategory":"Construction",
            "type":"Services"
        }
    ],
    "sg:phone":"+1 904 388 5322",
    "sg:postcode":"32205",
    "sg:province":"FL",
    "sg:tags":[
        "general",
        "contractor"
    ],
    "wof:name":"Danella Construction",
    "wof:placetype":"venue"
},
  "geometry": {"coordinates":[-81.73040399999999,30.299517],"type":"Point"}
}