{
  "type": "Feature",
  "properties": {
    "iso:country":"US",
    "sg:address":"1201 N Federal Hwy",
    "sg:city":"Fort Lauderdale",
    "sg:classifiers":[
        {
            "category":"Restaurant",
            "type":"Food & Drink"
        }
    ],
    "sg:phone":"+1 954 761 3388",
    "sg:postcode":"33304",
    "sg:province":"FL",
    "sg:tags":[
        "chinese"
    ],
    "wof:name":"China Yung Restaurant",
    "wof:placetype":"venue"
},
  "geometry": {"coordinates":[-80.12020800000001,26.139765],"type":"Point"}
}