{
  "type": "Feature",
  "properties": {
    "addr:full":"21255 Snow Hill Rd Brooksville FL 34601",
    "addr:housenumber":"21255",
    "addr:postcode":"34601",
    "addr:street":"Snow Hill Rd",
    "iso:country":"US",
    "sg:address":"21255 Snow Hill Rd",
    "sg:city":"Brooksville",
    "sg:classifiers":[
        {
            "category":"Wholesale",
            "subcategory":"Construction Materials",
            "type":"Manufacturing & Wholesale Goods"
        }
    ],
    "sg:phone":"+1 352 799 6007",
    "sg:postcode":"34601",
    "sg:province":"FL",
    "wof:name":"Soluri Window Installation",
    "wof:placetype":"venue"
},
  "geometry": {"coordinates":[-82.382316,28.647781],"type":"Point"}
}