{
  "type": "Feature",
  "properties": {
    "addr:full":"9802 Hermosillo Dr New Port Richey FL 34655",
    "addr:housenumber":"9802",
    "addr:postcode":"34655",
    "addr:street":"Hermosillo Dr",
    "iso:country":"US",
    "sg:address":"9802 Hermosillo Dr",
    "sg:city":"New Port Richey",
    "sg:classifiers":[
        {
            "category":"Professional",
            "subcategory":"Management & Consulting",
            "type":"Services"
        }
    ],
    "sg:phone":"+1 727 372 4683",
    "sg:postcode":"34655",
    "sg:province":"FL",
    "sg:tags":[
        "public",
        "relations"
    ],
    "wof:name":"American Promotions Inc",
    "wof:placetype":"venue"
},
  "geometry": {"coordinates":[-82.653076,28.232142],"type":"Point"}
}