{
  "type": "Feature",
  "properties": {
    "iso:country":"US",
    "sg:address":"8155 27th St E",
    "sg:city":"Sarasota",
    "sg:classifiers":[
        {
            "category":"Building & Trades",
            "subcategory":"Cleaning & Sanitation",
            "type":"Services"
        }
    ],
    "sg:phone":"+1 941 228 6526",
    "sg:postcode":"34243",
    "sg:province":"FL",
    "sg:tags":[
        "janitor"
    ],
    "wof:name":"Brenda Lee Sterling's Cleaning",
    "wof:placetype":"venue"
},
  "geometry": {"coordinates":[-82.529375,27.396301],"type":"Point"}
}