{
  "type": "Feature",
  "properties": {
    "iso:country":"US",
    "sg:address":"4951 Tamiami Trl N",
    "sg:city":"Naples",
    "sg:classifiers":[
        {
            "category":"Personal",
            "subcategory":"Beauty Salon",
            "type":"Services"
        }
    ],
    "sg:phone":"+1 239 262 1133",
    "sg:postcode":"34103",
    "sg:province":"FL",
    "wof:name":"Salon Z",
    "wof:placetype":"venue"
},
  "geometry": {"coordinates":[-81.800426,26.207353],"type":"Point"}
}