{
  "type": "Feature",
  "properties": {
    "addr:full":"3751 Maguire Blvd Orlando FL 32803",
    "addr:housenumber":"3751",
    "addr:postcode":"32803",
    "addr:street":"Maguire Blvd",
    "iso:country":"US",
    "sg:address":"3751 Maguire Blvd",
    "sg:city":"Orlando",
    "sg:classifiers":[
        {
            "category":"Government",
            "subcategory":"Office",
            "type":"Public Place"
        }
    ],
    "sg:phone":"+1 407 648 6441",
    "sg:postcode":"32803",
    "sg:province":"FL",
    "sg:tags":[
        "federal",
        "program"
    ],
    "sg:website":"www.hud.gov",
    "wof:name":"US Housing & Urban Dev Dept",
    "wof:placetype":"venue"
},
  "geometry": {"coordinates":[-81.335069,28.560889],"type":"Point"}
}