{
  "type": "Feature",
  "properties": {
    "iso:country":"US",
    "sg:address":"2475 Old Hickory Tree Rd",
    "sg:city":"St Cloud",
    "sg:classifiers":[
        {
            "category":"Farming",
            "subcategory":"Farm & Veterinary Services",
            "type":"Manufacturing & Wholesale Goods"
        }
    ],
    "sg:phone":"+1 407 892 2800",
    "sg:postcode":"34772",
    "sg:province":"FL",
    "sg:tags":[
        "breeder",
        "livestock"
    ],
    "wof:name":"Newman Land & Cattle Co Inc",
    "wof:placetype":"venue"
},
  "geometry": {"coordinates":[-81.25597,28.227761],"type":"Point"}
}