{
  "type": "Feature",
  "properties": {
    "iso:country":"US",
    "sg:address":"5353 SE Miles Grant Rd",
    "sg:city":"Stuart",
    "sg:classifiers":[
        {
            "category":"Organizations",
            "subcategory":"Community Association",
            "type":"Services"
        }
    ],
    "sg:phone":"+1 772 287 5277",
    "sg:postcode":"34997",
    "sg:province":"FL",
    "wof:name":"Miles Grant Condo Phase II",
    "wof:placetype":"venue"
},
  "geometry": {"coordinates":[-80.17887399999999,27.149663],"type":"Point"}
}