{
  "type": "Feature",
  "properties": {
    "iso:country":"US",
    "sg:address":"641 NW 183rd St",
    "sg:city":"Miami",
    "sg:classifiers":[
        {
            "category":"Health Services",
            "subcategory":"Doctor",
            "type":"Services"
        }
    ],
    "sg:phone":"+1 305 654 9009",
    "sg:postcode":"33169",
    "sg:province":"FL",
    "wof:name":"Liberty Health Care Center",
    "wof:placetype":"venue"
},
  "geometry": {"coordinates":[-80.212402,25.9422],"type":"Point"}
}