{
  "type": "Feature",
  "properties": {
    "addr:full":"1200 Flight Line Blvd Deland FL 32724",
    "addr:housenumber":"1200",
    "addr:postcode":"32724",
    "addr:street":"Flight Line Blvd",
    "iso:country":"US",
    "sg:address":"1200 Flight Line Blvd",
    "sg:city":"Deland",
    "sg:classifiers":[
        {
            "category":"Manufacturing",
            "subcategory":"Apparel",
            "type":"Manufacturing & Wholesale Goods"
        }
    ],
    "sg:phone":"+1 386 736 3862",
    "sg:postcode":"32724",
    "sg:province":"FL",
    "sg:tags":[
        "parachute",
        "manufacturer"
    ],
    "sg:website":"www.cpsworld.com",
    "wof:name":"CPS",
    "wof:placetype":"venue"
},
  "geometry": {"coordinates":[-81.2868,29.058414],"type":"Point"}
}