{
  "type": "Feature",
  "properties": {
    "addr:full":"2809 N Albany Ave Tampa FL 33607",
    "addr:housenumber":"2809",
    "addr:postcode":"33607",
    "addr:street":"N Albany Ave",
    "iso:country":"US",
    "sg:address":"2809 N Albany Ave",
    "sg:city":"Tampa",
    "sg:classifiers":[
        {
            "category":"Personal",
            "subcategory":"Beauty Salon",
            "type":"Services"
        }
    ],
    "sg:phone":"+1 813 258 2311",
    "sg:postcode":"33607",
    "sg:province":"FL",
    "wof:name":"Salon Finesse'",
    "wof:placetype":"venue"
},
  "geometry": {"coordinates":[-82.480656,27.965867],"type":"Point"}
}