{
  "type": "Feature",
  "properties": {
    "addr:full":"1080 Pine St Starke FL 32091",
    "addr:housenumber":"1080",
    "addr:postcode":"32091",
    "addr:street":"Pine St",
    "iso:country":"US",
    "sg:address":"1080 Pine St",
    "sg:city":"Starke",
    "sg:classifiers":[
        {
            "category":"Social Services",
            "subcategory":"Child Care",
            "type":"Services"
        }
    ],
    "sg:phone":"+1 904 964 8280",
    "sg:postcode":"32091",
    "sg:province":"FL",
    "sg:website":"www.ecs4kids.org",
    "wof:name":"Starke Head Start",
    "wof:placetype":"venue"
},
  "geometry": {"coordinates":[-82.10086699999999,29.952673],"type":"Point"}
}