{
  "type": "Feature",
  "properties": {
    "addr:full":"16301 NW 24th Ave Opa Locka FL 33054",
    "addr:housenumber":"16301",
    "addr:postcode":"33054",
    "addr:street":"Nw 24Th Ave;Locka",
    "iso:country":"US",
    "sg:address":"16301 NW 24th Ave",
    "sg:city":"Opa Locka",
    "sg:classifiers":[
        {
            "category":"Food & Beverages",
            "subcategory":"Groceries & Convenience Stores",
            "type":"Retail Goods"
        }
    ],
    "sg:phone":"+1 305 625 6344",
    "sg:postcode":"33054",
    "sg:province":"FL",
    "wof:name":"S Harrell Grocery",
    "wof:placetype":"venue"
},
  "geometry": {"coordinates":[-80.240036,25.925534],"type":"Point"}
}