{
  "type": "Feature",
  "properties": {
    "addr:full":"375 E Altamonte Dr Ste 1600 Altamonte Springs FL 32701",
    "addr:housenumber":"375",
    "addr:postcode":"32701",
    "addr:street":"E Altamonte Dr Ste 1600",
    "iso:country":"US",
    "sg:address":"375 E Altamonte Dr Ste 1600",
    "sg:city":"Altamonte Springs",
    "sg:classifiers":[
        {
            "category":"Shopping",
            "subcategory":"Mobile Phones",
            "type":"Retail Goods"
        }
    ],
    "sg:phone":"+1 407 262 4000",
    "sg:postcode":"32701",
    "sg:province":"FL",
    "sg:website":"www.bellsouth.com",
    "wof:name":"Cingular Wireless",
    "wof:placetype":"venue"
},
  "geometry": {"coordinates":[-81.379178,28.663627],"type":"Point"}
}