{
  "type": "Feature",
  "properties": {
    "addr:full":"419 SE 2nd Ave Williston FL 32696",
    "addr:housenumber":"419",
    "addr:postcode":"32696",
    "addr:street":"Se 2Nd Ave",
    "iso:country":"US",
    "sg:address":"419 SE 2nd Ave",
    "sg:city":"Williston",
    "sg:classifiers":[
        {
            "category":"Personal",
            "subcategory":"Beauty Salon",
            "type":"Services"
        }
    ],
    "sg:phone":"+1 352 528 5833",
    "sg:postcode":"32696",
    "sg:province":"FL",
    "wof:name":"Tower Above Landscapes Inc",
    "wof:placetype":"venue"
},
  "geometry": {"coordinates":[-82.443172,29.38566],"type":"Point"}
}