{
  "type": "Feature",
  "properties": {
    "iso:country":"US",
    "sg:address":"2642 SE Willoughby Blvd",
    "sg:city":"Stuart",
    "sg:classifiers":[
        {
            "category":"Building & Trades",
            "subcategory":"Construction",
            "type":"Services"
        }
    ],
    "sg:phone":"+1 772 287 9798",
    "sg:postcode":"34994",
    "sg:province":"FL",
    "sg:tags":[
        "general",
        "contractor"
    ],
    "wof:name":"American General",
    "wof:placetype":"venue"
},
  "geometry": {"coordinates":[-80.247032,27.174233],"type":"Point"}
}