{
  "type": "Feature",
  "properties": {
    "iso:country":"US",
    "sg:address":"1220 S Miami Rd",
    "sg:city":"Fort Lauderdale",
    "sg:classifiers":[
        {
            "category":"Real Estate",
            "subcategory":"Real Estate Operator",
            "type":"Services"
        }
    ],
    "sg:phone":"+1 954 463 9173",
    "sg:postcode":"33316",
    "sg:province":"FL",
    "sg:tags":[
        "building",
        "apartment"
    ],
    "wof:name":"Las Olas Villas Condominium",
    "wof:placetype":"venue"
},
  "geometry": {"coordinates":[-80.136441,26.107475],"type":"Point"}
}