{
  "type": "Feature",
  "properties": {
    "iso:country":"US",
    "sg:address":"14508 NW 27th Ave",
    "sg:city":"Opa Locka",
    "sg:classifiers":[
        {
            "category":"Personal",
            "subcategory":"Beauty Salon",
            "type":"Services"
        }
    ],
    "sg:phone":"+1 305 681 9190",
    "sg:postcode":"33054",
    "sg:province":"FL",
    "sg:tags":[
        "hair"
    ],
    "wof:name":"Sonia Natural Motions Unisex Beauty Salon",
    "wof:placetype":"venue"
},
  "geometry": {"coordinates":[-80.24389600000001,25.906601],"type":"Point"}
}