{
  "type": "Feature",
  "properties": {
    "iso:country":"US",
    "sg:address":"2270 SW 51st Pl",
    "sg:city":"Fort Lauderdale",
    "sg:classifiers":[
        {
            "category":"Building & Trades",
            "subcategory":"Construction",
            "type":"Services"
        }
    ],
    "sg:phone":"+1 954 967 0270",
    "sg:postcode":"33312",
    "sg:province":"FL",
    "sg:tags":[
        "contractor"
    ],
    "wof:name":"Grd Marble & Tile Inc",
    "wof:placetype":"venue"
},
  "geometry": {"coordinates":[-80.170072,26.058166],"type":"Point"}
}