{
  "type": "Feature",
  "properties": {
    "iso:country":"US",
    "sg:address":"1259 W Atlantic Blvd",
    "sg:city":"Pompano Beach",
    "sg:classifiers":[
        {
            "category":"Freight",
            "type":"Transportation"
        }
    ],
    "sg:phone":"+1 954 783 0494",
    "sg:postcode":"33069",
    "sg:province":"FL",
    "wof:name":"Transfreight Corp",
    "wof:placetype":"venue"
},
  "geometry": {"coordinates":[-80.141023,26.231613],"type":"Point"}
}