{
  "type": "Feature",
  "properties": {
    "iso:country":"US",
    "sg:address":"2986 Saint Stevens Dr",
    "sg:city":"Tallahassee",
    "sg:classifiers":[
        {
            "category":"Professional",
            "type":"Services"
        }
    ],
    "sg:phone":"+1 850 907 0900",
    "sg:postcode":"32312",
    "sg:province":"FL",
    "sg:tags":[
        "home",
        "planning"
    ],
    "wof:name":"W L Martin Home Designs",
    "wof:placetype":"venue"
},
  "geometry": {"coordinates":[-84.226832,30.59327],"type":"Point"}
}