{
  "type": "Feature",
  "properties": {
    "iso:country":"US",
    "sg:address":"235 N US Hwy 1",
    "sg:city":"Ormond Beach",
    "sg:classifiers":[
        {
            "category":"Building & Trades",
            "subcategory":"Construction",
            "type":"Services"
        }
    ],
    "sg:phone":"+1 386 676 1000",
    "sg:postcode":"32174",
    "sg:province":"FL",
    "sg:tags":[
        "glass",
        "contractor"
    ],
    "wof:name":"Custom Glass Express",
    "wof:placetype":"venue"
},
  "geometry": {"coordinates":[-81.065273,29.288458],"type":"Point"}
}