{
  "type": "Feature",
  "properties": {
    "iso:country":"US",
    "sg:address":"5000 Palm Coast Pkwy SE",
    "sg:city":"Palm Coast",
    "sg:classifiers":[
        {
            "category":"Freight",
            "type":"Transportation"
        }
    ],
    "sg:phone":"+1 386 445 9045",
    "sg:postcode":"32137",
    "sg:province":"FL",
    "sg:tags":[
        "utility",
        "maintains",
        "toll",
        "facility"
    ],
    "wof:name":"Dunes Community Dev Dst",
    "wof:placetype":"venue"
},
  "geometry": {"coordinates":[-81.19123999999999,29.562887],"type":"Point"}
}