{
  "type": "Feature",
  "properties": {
    "iso:country":"US",
    "sg:address":"372 Formosa Dr",
    "sg:city":"Cocoa Beach",
    "sg:classifiers":[
        {
            "category":"Shopping",
            "subcategory":"Bicycles & Sporting Goods",
            "type":"Retail Goods"
        }
    ],
    "sg:phone":"+1 321 783 2187",
    "sg:postcode":"32931",
    "sg:province":"FL",
    "sg:tags":[
        "surfboard"
    ],
    "wof:name":"Davo Surf Design",
    "wof:placetype":"venue"
},
  "geometry": {"coordinates":[-80.613573,28.32629],"type":"Point"}
}