{
  "type": "Feature",
  "properties": {
    "iso:country":"US",
    "sg:address":"3301 Desoto Blvd",
    "sg:city":"Palm Harbor",
    "sg:classifiers":[
        {
            "category":"Real Estate",
            "subcategory":"Surveying",
            "type":"Services"
        }
    ],
    "sg:phone":"+1 727 784 5496",
    "sg:postcode":"34683",
    "sg:province":"FL",
    "sg:tags":[
        "land"
    ],
    "wof:name":"George A Shimp & Associates",
    "wof:placetype":"venue"
},
  "geometry": {"coordinates":[-82.77280399999999,28.100142],"type":"Point"}
}