{
  "type": "Feature",
  "properties": {
    "iso:country":"US",
    "sg:address":"129 NW 4th Ave",
    "sg:city":"Dania",
    "sg:classifiers":[
        {
            "category":"Retail",
            "subcategory":"Auto Repair",
            "type":"Services"
        }
    ],
    "sg:phone":"+1 954 923 6416",
    "sg:postcode":"33004",
    "sg:province":"FL",
    "sg:tags":[
        "body",
        "automobile",
        "customizing",
        "painting",
        "repairing"
    ],
    "wof:name":"Custom Paint & Body",
    "wof:placetype":"venue"
},
  "geometry": {"coordinates":[-80.145852,26.054544],"type":"Point"}
}