{
  "type": "Feature",
  "properties": {
    "addr:full":"9811 NW 80th Ave Hialeah FL 33016",
    "addr:housenumber":"9811",
    "addr:postcode":"33016",
    "addr:street":"Nw 80Th Ave",
    "iso:country":"US",
    "sg:address":"9811 NW 80th Ave",
    "sg:city":"Hialeah",
    "sg:classifiers":[
        {
            "category":"Professional",
            "subcategory":"Engineering",
            "type":"Services"
        },
        {
            "category":"Wholesale",
            "subcategory":"Construction Materials",
            "type":"Manufacturing & Wholesale Goods"
        }
    ],
    "sg:phone":"+1 305 821 7660",
    "sg:postcode":"33016",
    "sg:province":"FL",
    "sg:tags":[
        "passenger-commercial",
        "industrial",
        "elevators-freight",
        "elevator"
    ],
    "wof:name":"Image Elevator Inc",
    "wof:placetype":"venue"
},
  "geometry": {"coordinates":[-80.32683,25.862536],"type":"Point"}
}