{
  "type": "Feature",
  "properties": {
    "iso:country":"US",
    "sg:address":"3660 S Pine Ave",
    "sg:city":"Ocala",
    "sg:classifiers":[
        {
            "category":"Autos & Motor Vehicles",
            "subcategory":"Automobile Sales",
            "type":"Retail Goods"
        }
    ],
    "sg:phone":"+1 352 622 1205",
    "sg:postcode":"34471",
    "sg:province":"FL",
    "sg:tags":[
        "car",
        "used",
        "dealer"
    ],
    "wof:name":"Anthony Russo Auto Sales Inc",
    "wof:placetype":"venue"
},
  "geometry": {"coordinates":[-82.121711,29.151822],"type":"Point"}
}