{
  "type": "Feature",
  "properties": {
    "iso:country":"US",
    "sg:address":"3001 NW 60th St",
    "sg:city":"Fort Lauderdale",
    "sg:classifiers":[
        {
            "category":"Manufacturing",
            "subcategory":"Tools & Machinery",
            "type":"Manufacturing & Wholesale Goods"
        }
    ],
    "sg:phone":"+1 954 917 7611",
    "sg:postcode":"33309",
    "sg:province":"FL",
    "sg:tags":[
        "specializing",
        "wiring",
        "devices",
        "mfg"
    ],
    "wof:name":"Matkim Industries Inc",
    "wof:placetype":"venue"
},
  "geometry": {"coordinates":[-80.18617399999999,26.200549],"type":"Point"}
}