{
  "type": "Feature",
  "properties": {
    "iso:country":"US",
    "sg:address":"501 S Pinellas Ave",
    "sg:city":"Tarpon Springs",
    "sg:classifiers":[
        {
            "category":"Food & Beverages",
            "subcategory":"Groceries & Convenience Stores",
            "type":"Retail Goods"
        }
    ],
    "sg:phone":"+1 727 944 3619",
    "sg:postcode":"34689",
    "sg:province":"FL",
    "wof:name":"Tarpon Produce & Deli",
    "wof:placetype":"venue"
},
  "geometry": {"coordinates":[-82.756602,28.14132],"type":"Point"}
}