{
  "type": "Feature",
  "properties": {
    "addr:full":"59 E 3rd St Hialeah FL 33010",
    "addr:housenumber":"59",
    "addr:postcode":"33010",
    "addr:street":"E 3Rd St",
    "iso:country":"US",
    "sg:address":"59 E 3rd St",
    "sg:city":"Hialeah",
    "sg:classifiers":[
        {
            "category":"Local Transit",
            "type":"Transportation"
        }
    ],
    "sg:phone":"+1 305 882 0441",
    "sg:postcode":"33010",
    "sg:province":"FL",
    "wof:name":"Conchitas Transit Express",
    "wof:placetype":"venue"
},
  "geometry": {"coordinates":[-80.28045899999999,25.824558],"type":"Point"}
}