{
  "type": "Feature",
  "properties": {
    "addr:full":"382 5th Ave S Naples FL 34102",
    "addr:housenumber":"382",
    "addr:postcode":"34102",
    "addr:street":"5Th Ave S",
    "iso:country":"US",
    "sg:address":"382 5th Ave S",
    "sg:city":"Naples",
    "sg:classifiers":[
        {
            "category":"Restaurant",
            "type":"Food & Drink"
        }
    ],
    "sg:phone":"+1 239 403 3825",
    "sg:postcode":"34102",
    "sg:province":"FL",
    "wof:name":"Subway Sandwiches & Salads",
    "wof:placetype":"venue"
},
  "geometry": {"coordinates":[-81.801315,26.14105],"type":"Point"}
}