{
  "type": "Feature",
  "properties": {
    "addr:full":"1708 N State Road 7 Lauderhill FL 33313",
    "addr:housenumber":"1708",
    "addr:postcode":"33313",
    "addr:street":"N State Road 7",
    "iso:country":"US",
    "sg:address":"1708 N State Road 7",
    "sg:city":"Lauderhill",
    "sg:classifiers":[
        {
            "category":"Place Of Worship",
            "subcategory":"Church",
            "type":"Public Place"
        }
    ],
    "sg:phone":"+1 954 322 4302",
    "sg:postcode":"33313",
    "sg:province":"FL",
    "sg:tags":[
        "churches-baptist-independent"
    ],
    "wof:name":"First Baptist Church Of West Hollywood",
    "wof:placetype":"venue"
},
  "geometry": {"coordinates":[-80.20266700000001,26.147518],"type":"Point"}
}