{
  "type": "Feature",
  "properties": {
    "addr:full":"3715 NW 12th Ave Gainesville FL 32605",
    "addr:housenumber":"3715",
    "addr:postcode":"32605",
    "addr:street":"Nw 12Th Ave",
    "iso:country":"US",
    "sg:address":"3715 NW 12th Ave",
    "sg:city":"Gainesville",
    "sg:classifiers":[
        {
            "category":"Organizations",
            "subcategory":"Community Association",
            "type":"Services"
        }
    ],
    "sg:phone":"+1 352 377 6927",
    "sg:postcode":"32605",
    "sg:province":"FL",
    "wof:name":"Three Hundred Club",
    "wof:placetype":"venue"
},
  "geometry": {"coordinates":[-82.378114,29.663522],"type":"Point"}
}