{
  "type": "Feature",
  "properties": {
    "iso:country":"US",
    "sg:address":"3701 40th Ave E",
    "sg:city":"Palmetto",
    "sg:classifiers":[
        {
            "category":"Building & Trades",
            "subcategory":"Construction",
            "type":"Services"
        },
        {
            "category":"Manufacturing",
            "subcategory":"Building Materials",
            "type":"Manufacturing & Wholesale Goods"
        }
    ],
    "sg:phone":"+1 941 729 1751",
    "sg:postcode":"34221",
    "sg:province":"FL",
    "sg:tags":[
        "roofing",
        "industrial",
        "sheet",
        "consultant",
        "work",
        "metal",
        "contractor",
        "siding",
        "contractors-commercial"
    ],
    "wof:name":"Otis Joiner Roofing Inc",
    "wof:placetype":"venue"
},
  "geometry": {"coordinates":[-82.523849,27.546909],"type":"Point"}
}