{
  "type": "Feature",
  "properties": {
    "addr:full":"4000 W Watrous Ave Tampa FL 33629",
    "addr:housenumber":"4000",
    "addr:postcode":"33629",
    "addr:street":"W Watrous Ave",
    "iso:country":"US",
    "sg:address":"4000 W Watrous Ave",
    "sg:city":"Tampa",
    "sg:classifiers":[
        {
            "category":"Government",
            "subcategory":"Office",
            "type":"Public Place"
        }
    ],
    "sg:phone":"+1 813 282 2902",
    "sg:postcode":"33629",
    "sg:province":"FL",
    "sg:tags":[
        "executive"
    ],
    "wof:name":"Cal Dickson Tennis Center",
    "wof:placetype":"venue"
},
  "geometry": {"coordinates":[-82.508242,27.932018],"type":"Point"}
}