{
  "type": "Feature",
  "properties": {
    "addr:full":"849 Tiffany Pl Rockledge FL 32955",
    "addr:housenumber":"849",
    "addr:postcode":"32955",
    "addr:street":"Tiffany Pl",
    "iso:country":"US",
    "sg:address":"849 Tiffany Pl",
    "sg:city":"Rockledge",
    "sg:classifiers":[
        {
            "category":"Home & Garden",
            "subcategory":"Furniture",
            "type":"Retail Goods"
        }
    ],
    "sg:phone":"+1 321 632 7601",
    "sg:postcode":"32955",
    "sg:province":"FL",
    "sg:tags":[
        "store"
    ],
    "wof:name":"Peanut's Furniture Gallery",
    "wof:placetype":"venue"
},
  "geometry": {"coordinates":[-80.729271,28.31497],"type":"Point"}
}