{
  "type": "Feature",
  "properties": {
    "iso:country":"US",
    "sg:address":"1150 Errol Place Cir",
    "sg:city":"Apopka",
    "sg:classifiers":[
        {
            "category":"Autos & Motor Vehicles",
            "subcategory":"Automobile Sales",
            "type":"Retail Goods"
        }
    ],
    "sg:phone":"+1 407 889 7090",
    "sg:postcode":"32712",
    "sg:province":"FL",
    "sg:tags":[
        "car"
    ],
    "wof:name":"Rapid Inspections",
    "wof:placetype":"venue"
},
  "geometry": {"coordinates":[-81.53306000000001,28.686331],"type":"Point"}
}