{
  "type": "Feature",
  "properties": {
    "addr:full":"14433 62nd St N Clearwater FL 33760",
    "addr:housenumber":"14433",
    "addr:postcode":"33760",
    "addr:street":"62Nd St N",
    "iso:country":"US",
    "sg:address":"14433 62nd St N",
    "sg:city":"Clearwater",
    "sg:classifiers":[
        {
            "category":"Freight",
            "type":"Transportation"
        }
    ],
    "sg:phone":"+1 727 535 4354",
    "sg:postcode":"33760",
    "sg:province":"FL",
    "sg:tags":[
        "vehicle",
        "recreational",
        "general"
    ],
    "wof:name":"A A Accredited Storage",
    "wof:placetype":"venue"
},
  "geometry": {"coordinates":[-82.720859,27.903371],"type":"Point"}
}