{
  "type": "Feature",
  "properties": {
    "iso:country":"US",
    "sg:address":"2710 NW 112th Ave",
    "sg:city":"Miami",
    "sg:classifiers":[
        {
            "category":"Wholesale",
            "subcategory":"Electrical",
            "type":"Manufacturing & Wholesale Goods"
        }
    ],
    "sg:phone":"+1 305 599 2989",
    "sg:postcode":"33172",
    "sg:province":"FL",
    "sg:tags":[
        "electronics",
        "consumer"
    ],
    "wof:name":"Technidyne",
    "wof:placetype":"venue"
},
  "geometry": {"coordinates":[-80.377343,25.800542],"type":"Point"}
}