{
  "type": "Feature",
  "properties": {
    "iso:country":"US",
    "sg:address":"2248 Trade Center Way",
    "sg:city":"Naples",
    "sg:classifiers":[
        {
            "category":"Home & Garden",
            "subcategory":"Building Materials",
            "type":"Retail Goods"
        }
    ],
    "sg:phone":"+1 239 593 6464",
    "sg:postcode":"34109",
    "sg:province":"FL",
    "sg:tags":[
        "house"
    ],
    "wof:name":"Legendary Kitchens & Baths",
    "wof:placetype":"venue"
},
  "geometry": {"coordinates":[-81.779517,26.225056],"type":"Point"}
}