{
  "type": "Feature",
  "properties": {
    "iso:country":"US",
    "sg:address":"205 Lake Gertie Rd",
    "sg:city":"Deland",
    "sg:classifiers":[
        {
            "category":"Shopping",
            "subcategory":"Discount & Variety Stores",
            "type":"Retail Goods"
        }
    ],
    "sg:phone":"+1 386 738 5972",
    "sg:postcode":"32720",
    "sg:province":"FL",
    "sg:tags":[
        "merchandise",
        "general"
    ],
    "wof:name":"John Anderson Fern",
    "wof:placetype":"venue"
},
  "geometry": {"coordinates":[-81.306466,29.051031],"type":"Point"}
}