{
  "type": "Feature",
  "properties": {
    "iso:country":"US",
    "sg:address":"21110 Biscayne Blvd",
    "sg:city":"Miami",
    "sg:classifiers":[
        {
            "category":"Health Services",
            "subcategory":"Doctor",
            "type":"Services"
        }
    ],
    "sg:phone":"+1 305 933 8622",
    "sg:postcode":"33180",
    "sg:province":"FL",
    "sg:tags":[
        "osteopathic"
    ],
    "wof:name":"Edward L Wiener Do",
    "wof:placetype":"venue"
},
  "geometry": {"coordinates":[-80.142731,25.973008],"type":"Point"}
}