{
  "type": "Feature",
  "properties": {
    "iso:country":"US",
    "sg:address":"309 S Dixie Hwy",
    "sg:city":"Lake Worth",
    "sg:classifiers":[
        {
            "category":"Building & Trades",
            "subcategory":"Cleaning & Sanitation",
            "type":"Services"
        }
    ],
    "sg:phone":"+1 561 582 6260",
    "sg:postcode":"33460",
    "sg:province":"FL",
    "sg:tags":[
        "maintenance"
    ],
    "wof:name":"AOH Svc",
    "wof:placetype":"venue"
},
  "geometry": {"coordinates":[-80.05759,26.611142],"type":"Point"}
}