{
  "type": "Feature",
  "properties": {
    "addr:full":"15830 Morris Bridge Rd Thonotosassa FL 33592",
    "addr:housenumber":"15830",
    "addr:postcode":"33592",
    "addr:street":"Morris Bridge Rd",
    "iso:country":"US",
    "sg:address":"15830 Morris Bridge Rd",
    "sg:city":"Thonotosassa",
    "sg:classifiers":[
        {
            "category":"Place Of Worship",
            "subcategory":"Church",
            "type":"Public Place"
        },
        {
            "category":"Place Of Worship",
            "type":"Public Place"
        }
    ],
    "sg:phone":"+1 813 982 2783",
    "sg:postcode":"33592",
    "sg:province":"FL",
    "sg:tags":[
        "churches-interdenominational",
        "churches-various",
        "denomination"
    ],
    "wof:name":"Islamic Society Of New Tampa",
    "wof:placetype":"venue"
},
  "geometry": {"coordinates":[-82.280366,28.146688],"type":"Point"}
}