{
  "type": "Feature",
  "properties": {
    "iso:country":"US",
    "sg:address":"103 NW 15th Pl",
    "sg:city":"Pompano Beach",
    "sg:classifiers":[
        {
            "category":"Wholesale",
            "subcategory":"Groceries",
            "type":"Manufacturing & Wholesale Goods"
        }
    ],
    "sg:phone":"+1 954 545 3440",
    "sg:postcode":"33060",
    "sg:province":"FL",
    "sg:tags":[
        "food",
        "product"
    ],
    "wof:name":"United Farms Intl Corp",
    "wof:placetype":"venue"
},
  "geometry": {"coordinates":[-80.123417,26.247925],"type":"Point"}
}