{
  "type": "Feature",
  "properties": {
    "addr:full":"9811 Jog Rd Boynton Beach FL 33437",
    "addr:housenumber":"9811",
    "addr:postcode":"33437",
    "addr:street":"Jog Rd",
    "iso:country":"US",
    "sg:address":"9811 Jog Rd",
    "sg:city":"Boynton Beach",
    "sg:classifiers":[
        {
            "category":"Autos & Motor Vehicles",
            "subcategory":"Auto Supplies",
            "type":"Retail Goods"
        }
    ],
    "sg:phone":"+1 561 732 6664",
    "sg:postcode":"33437",
    "sg:province":"FL",
    "sg:tags":[
        "tire"
    ],
    "wof:name":"Customer 1 Tire & Auto Care",
    "wof:placetype":"venue"
},
  "geometry": {"coordinates":[-80.14733200000001,26.531143],"type":"Point"}
}