{
  "type": "Feature",
  "properties": {
    "iso:country":"US",
    "sg:address":"1322 NE 4th Ave",
    "sg:city":"Fort Lauderdale",
    "sg:classifiers":[
        {
            "category":"Professional",
            "subcategory":"Lawyer & Legal Services",
            "type":"Services"
        }
    ],
    "sg:phone":"+1 954 768 9116",
    "sg:postcode":"33304",
    "sg:province":"FL",
    "sg:tags":[
        "attorney",
        "law",
        "at"
    ],
    "wof:name":"Hemmerle Keneth V II Attny Law",
    "wof:placetype":"venue"
},
  "geometry": {"coordinates":[-80.14055,26.143641],"type":"Point"}
}