{
  "type": "Feature",
  "properties": {
    "addr:full":"1680 Michigan Ave Ste 912 Miami Beach FL 33139",
    "addr:housenumber":"1680",
    "addr:postcode":"33139",
    "addr:street":"Michigan Ave Ste 912",
    "iso:country":"US",
    "sg:address":"1680 Michigan Ave Ste 912",
    "sg:city":"Miami Beach",
    "sg:classifiers":[
        {
            "category":"Health Services",
            "subcategory":"Doctor",
            "type":"Services"
        }
    ],
    "sg:phone":"+1 305 534 0503",
    "sg:postcode":"33139",
    "sg:province":"FL",
    "wof:name":"Canas Albert MD PA",
    "wof:placetype":"venue"
},
  "geometry": {"coordinates":[-80.138802,25.791599],"type":"Point"}
}