{
  "type": "Feature",
  "properties": {
    "iso:country":"US",
    "sg:address":"701 NW 62nd Ave Ste 390",
    "sg:city":"Miami",
    "sg:classifiers":[
        {
            "category":"Shopping",
            "subcategory":"Florist",
            "type":"Retail Goods"
        }
    ],
    "sg:phone":"+1 305 265 6200",
    "sg:postcode":"33126",
    "sg:province":"FL",
    "wof:name":"Global Crossing",
    "wof:placetype":"venue"
},
  "geometry": {"coordinates":[-80.297798,25.77779],"type":"Point"}
}