{
  "type": "Feature",
  "properties": {
    "iso:country":"US",
    "sg:address":"1400 S Marion St",
    "sg:city":"Lake City",
    "sg:classifiers":[
        {
            "category":"Health Services",
            "subcategory":"Doctor",
            "type":"Services"
        }
    ],
    "sg:phone":"+1 386 752 8531",
    "sg:postcode":"32025",
    "sg:province":"FL",
    "sg:tags":[
        "dentist"
    ],
    "wof:name":"Gerber Dental",
    "wof:placetype":"venue"
},
  "geometry": {"coordinates":[-82.63692899999999,30.17877],"type":"Point"}
}