{
  "type": "Feature",
  "properties": {
    "iso:country":"US",
    "sg:address":"111 SW 1st Ct",
    "sg:city":"Miami",
    "sg:classifiers":[
        {
            "category":"Professional",
            "subcategory":"Lawyer & Legal Services",
            "type":"Services"
        }
    ],
    "sg:phone":"+1 305 358 4058",
    "sg:postcode":"33130",
    "sg:province":"FL",
    "wof:name":"McCormick and Koretsky",
    "wof:placetype":"venue"
},
  "geometry": {"coordinates":[-80.196259,25.773045],"type":"Point"}
}