{
  "type": "Feature",
  "properties": {
    "iso:country":"US",
    "sg:address":"1405 Coolidge Ave",
    "sg:city":"Bartow",
    "sg:classifiers":[
        {
            "category":"Retail",
            "subcategory":"Auto Repair",
            "type":"Services"
        }
    ],
    "sg:phone":"+1 863 533 4389",
    "sg:postcode":"33830",
    "sg:province":"FL",
    "sg:tags":[
        "general"
    ],
    "wof:name":"Anjeli Auto Life Center Inc",
    "wof:placetype":"venue"
},
  "geometry": {"coordinates":[-81.85246600000001,27.880529],"type":"Point"}
}