{
  "type": "Feature",
  "properties": {
    "iso:country":"US",
    "sg:address":"14971 SW 299th St",
    "sg:city":"Homestead",
    "sg:classifiers":[
        {
            "category":"Building & Trades",
            "subcategory":"Construction",
            "type":"Services"
        }
    ],
    "sg:phone":"+1 305 247 7315",
    "sg:postcode":"33033",
    "sg:province":"FL",
    "sg:tags":[
        "hanging",
        "contractor"
    ],
    "wof:name":"Ocl Painting",
    "wof:placetype":"venue"
},
  "geometry": {"coordinates":[-80.433403,25.489377],"type":"Point"}
}