{
  "type": "Feature",
  "properties": {
    "iso:country":"US",
    "sg:address":"1343 Barefoot Cir",
    "sg:city":"Sebastian",
    "sg:classifiers":[
        {
            "category":"Professional",
            "type":"Services"
        }
    ],
    "sg:phone":"+1 772 664 5571",
    "sg:postcode":"32976",
    "sg:province":"FL",
    "wof:name":"4th Street Station Inc",
    "wof:placetype":"venue"
},
  "geometry": {"coordinates":[-80.532912,27.894173],"type":"Point"}
}