{
  "type": "Feature",
  "properties": {
    "iso:country":"US",
    "sg:address":"2500 NW 107th Ave",
    "sg:city":"Doral",
    "sg:classifiers":[
        {
            "category":"Building & Trades",
            "subcategory":"Locksmith",
            "type":"Services"
        }
    ],
    "sg:phone":"+1 305 908 7010",
    "sg:postcode":"33172",
    "sg:province":"FL",
    "sg:tags":[
        "key"
    ],
    "wof:name":"0 Waiting Accurate Locksmith",
    "wof:placetype":"venue"
},
  "geometry": {"coordinates":[-80.369252,25.797163],"type":"Point"}
}