{
  "type": "Feature",
  "properties": {
    "addr:full":"380 Glenn Rd West Palm Beach FL 33405",
    "addr:housenumber":"380",
    "addr:postcode":"33405",
    "addr:street":"Glenn Rd",
    "iso:country":"US",
    "sg:address":"380 Glenn Rd",
    "sg:city":"West Palm Beach",
    "sg:classifiers":[
        {
            "category":"Building & Trades",
            "subcategory":"Construction",
            "type":"Services"
        }
    ],
    "sg:phone":"+1 561 547 5292",
    "sg:postcode":"33405",
    "sg:province":"FL",
    "sg:tags":[
        "framing",
        "contractor"
    ],
    "wof:name":"Lazaro Perez Interiors",
    "wof:placetype":"venue"
},
  "geometry": {"coordinates":[-80.05350799999999,26.647428],"type":"Point"}
}