{
  "type": "Feature",
  "properties": {
    "addr:full":"1939 Mound St Orlando FL 32803",
    "addr:housenumber":"1939",
    "addr:postcode":"32803",
    "addr:street":"Mound St",
    "iso:country":"US",
    "sg:address":"1939 Mound St",
    "sg:city":"Orlando",
    "sg:classifiers":[
        {
            "category":"Building & Trades",
            "subcategory":"Locksmith",
            "type":"Services"
        }
    ],
    "sg:phone":"+1 877 662 5201",
    "sg:postcode":"32803",
    "sg:province":"FL",
    "sg:tags":[
        "key"
    ],
    "wof:name":"7 Day 24 Hour Emergency Locksmith",
    "wof:placetype":"venue"
},
  "geometry": {"coordinates":[-81.31957300000001,28.690689],"type":"Point"}
}