{
  "type": "Feature",
  "properties": {
    "addr:full":"742 Vistana Cir Naples FL 34119",
    "addr:housenumber":"742",
    "addr:postcode":"34119",
    "addr:street":"Vistana Cir",
    "iso:country":"US",
    "sg:address":"742 Vistana Cir",
    "sg:city":"Naples",
    "sg:classifiers":[
        {
            "category":"Shopping",
            "subcategory":"Used Merchandise",
            "type":"Retail Goods"
        }
    ],
    "sg:phone":"+1 239 352 0493",
    "sg:postcode":"34119",
    "sg:province":"FL",
    "sg:tags":[
        "antique"
    ],
    "wof:name":"Elvid Antiques",
    "wof:placetype":"venue"
},
  "geometry": {"coordinates":[-81.72141000000001,26.242755],"type":"Point"}
}