{
  "type": "Feature",
  "properties": {
    "addr:full":"7300 Aloma Ave Winter Park FL 32792",
    "addr:housenumber":"7300",
    "addr:postcode":"32792",
    "addr:street":"Aloma Ave",
    "iso:country":"US",
    "sg:address":"7300 Aloma Ave",
    "sg:city":"Winter Park",
    "sg:classifiers":[
        {
            "category":"Professional",
            "subcategory":"Business Services",
            "type":"Services"
        }
    ],
    "sg:phone":"+1 407 679 2100",
    "sg:postcode":"32792",
    "sg:province":"FL",
    "sg:tags":[
        "appraiser"
    ],
    "wof:name":"Appraisalcorp",
    "wof:placetype":"venue"
},
  "geometry": {"coordinates":[-81.289603,28.608711],"type":"Point"}
}