{
  "type": "Feature",
  "properties": {
    "addr:full":"6916 N 30th St Tampa FL 33610",
    "addr:housenumber":"6916",
    "addr:postcode":"33610",
    "addr:street":"N 30Th St",
    "iso:country":"US",
    "sg:address":"6916 N 30th St",
    "sg:city":"Tampa",
    "sg:classifiers":[
        {
            "category":"Real Estate",
            "subcategory":"Real Estate Agent",
            "type":"Services"
        }
    ],
    "sg:phone":"+1 813 237 3433",
    "sg:postcode":"33610",
    "sg:province":"FL",
    "wof:name":"Colemans Residential Care",
    "wof:placetype":"venue"
},
  "geometry": {"coordinates":[-82.426531,28.010777],"type":"Point"}
}