{
  "type": "Feature",
  "properties": {
    "iso:country":"US",
    "sg:address":"1039 Northern Way",
    "sg:city":"Winter Springs",
    "sg:classifiers":[
        {
            "category":"Retail",
            "subcategory":"Veterinary Services",
            "type":"Services"
        }
    ],
    "sg:phone":"+1 407 365 5701",
    "sg:postcode":"32708",
    "sg:province":"FL",
    "sg:tags":[
        "veterinarian"
    ],
    "wof:name":"Pultz Lawrence DVM",
    "wof:placetype":"venue"
},
  "geometry": {"coordinates":[-81.257599,28.665701],"type":"Point"}
}