{
  "type": "Feature",
  "properties": {
    "addr:full":"8040 NW 103rd St Hialeah FL 33016",
    "addr:housenumber":"8040",
    "addr:postcode":"33016",
    "addr:street":"Nw 103Rd St",
    "iso:country":"US",
    "sg:address":"8040 NW 103rd St",
    "sg:city":"Hialeah",
    "sg:classifiers":[
        {
            "category":"Manufacturing",
            "subcategory":"Retail Goods",
            "type":"Manufacturing & Wholesale Goods"
        }
    ],
    "sg:phone":"+1 305 443 1066",
    "sg:postcode":"33016",
    "sg:province":"FL",
    "sg:tags":[
        "manufacturer"
    ],
    "wof:name":"Arnolfo Moreno Mfg",
    "wof:placetype":"venue"
},
  "geometry": {"coordinates":[-80.327725,25.868332],"type":"Point"}
}