{
  "type": "Feature",
  "properties": {
    "iso:country":"US",
    "sg:address":"413 E 23rd St",
    "sg:city":"Panama City",
    "sg:classifiers":[
        {
            "category":"Home & Garden",
            "subcategory":"Home Furnishings",
            "type":"Retail Goods"
        }
    ],
    "sg:phone":"+1 850 522 4018",
    "sg:postcode":"32405",
    "sg:province":"FL",
    "sg:tags":[
        "housewares"
    ],
    "wof:name":"Bed Bath & Beyond",
    "wof:placetype":"venue"
},
  "geometry": {"coordinates":[-85.657743,30.189671],"type":"Point"}
}