{
  "type": "Feature",
  "properties": {
    "addr:full":"425 21st St Vero Beach FL 32960",
    "addr:housenumber":"425",
    "addr:postcode":"32960",
    "addr:street":"21St St",
    "iso:country":"US",
    "sg:address":"425 21st St",
    "sg:city":"Vero Beach",
    "sg:classifiers":[
        {
            "category":"Shopping",
            "subcategory":"Used Merchandise",
            "type":"Retail Goods"
        },
        {
            "category":"Home & Garden",
            "subcategory":"Furniture",
            "type":"Retail Goods"
        }
    ],
    "sg:phone":"+1 772 299 0006",
    "sg:postcode":"32960",
    "sg:province":"FL",
    "wof:name":"Clementines Consignment Inc",
    "wof:placetype":"venue"
},
  "geometry": {"coordinates":[-80.38244899999999,27.63972],"type":"Point"}
}