{
  "type": "Feature",
  "properties": {
    "iso:country":"US",
    "sg:address":"76 Madre de Dios St",
    "sg:city":"Punta Gorda",
    "sg:classifiers":[
        {
            "category":"Building & Trades",
            "subcategory":"Construction",
            "type":"Services"
        }
    ],
    "sg:phone":"+1 941 627 5834",
    "sg:postcode":"33983",
    "sg:province":"FL",
    "sg:tags":[
        "contractor"
    ],
    "wof:name":"Baby Lifesaver Pool Fence",
    "wof:placetype":"venue"
},
  "geometry": {"coordinates":[-82.03159599999999,27.030548],"type":"Point"}
}