{
  "type": "Feature",
  "properties": {
    "iso:country":"US",
    "sg:address":"1001 SE Ocean Blvd",
    "sg:city":"Stuart",
    "sg:classifiers":[
        {
            "category":"Health Services",
            "subcategory":"Doctor",
            "type":"Services"
        }
    ],
    "sg:phone":"+1 772 220 1919",
    "sg:postcode":"34996",
    "sg:province":"FL",
    "sg:tags":[
        "physician",
        "surgeon"
    ],
    "wof:name":"Pulmonary Medicine",
    "wof:placetype":"venue"
},
  "geometry": {"coordinates":[-80.236527,27.1975],"type":"Point"}
}