{
  "type": "Feature",
  "properties": {
    "iso:country":"US",
    "sg:address":"13551 Oval Dr N",
    "sg:city":"Largo",
    "sg:classifiers":[
        {
            "category":"Building & Trades",
            "subcategory":"Construction",
            "type":"Services"
        }
    ],
    "sg:phone":"+1 727 593 0028",
    "sg:postcode":"33774",
    "sg:province":"FL",
    "sg:tags":[
        "plastering",
        "contractor"
    ],
    "wof:name":"Southern Quality Plastering",
    "wof:placetype":"venue"
},
  "geometry": {"coordinates":[-82.825446,27.879562],"type":"Point"}
}