{
  "type": "Feature",
  "properties": {
    "iso:country":"US",
    "sg:address":"3370 NE 190th St",
    "sg:city":"Miami",
    "sg:classifiers":[
        {
            "category":"Wholesale",
            "subcategory":"Computers",
            "type":"Manufacturing & Wholesale Goods"
        }
    ],
    "sg:phone":"+1 305 468 5995",
    "sg:postcode":"33180",
    "sg:province":"FL",
    "sg:tags":[
        "value",
        "parts",
        "reseller",
        "added"
    ],
    "wof:name":"Compu-King Inc",
    "wof:placetype":"venue"
},
  "geometry": {"coordinates":[-80.138182,25.951729],"type":"Point"}
}