{
  "type": "Feature",
  "properties": {
    "iso:country":"US",
    "sg:address":"8516 Miramar Pkwy",
    "sg:city":"Hollywood",
    "sg:classifiers":[
        {
            "category":"Freight",
            "type":"Transportation"
        }
    ],
    "sg:phone":"+1 954 450 9921",
    "sg:postcode":"33025",
    "sg:province":"FL",
    "wof:name":"Levy Transportation Inc",
    "wof:placetype":"venue"
},
  "geometry": {"coordinates":[-80.256997,25.981223],"type":"Point"}
}