{
  "type": "Feature",
  "properties": {
    "addr:full":"101 Forester Ct Wellington FL 33414",
    "addr:housenumber":"101",
    "addr:postcode":"33414",
    "addr:street":"Forester Ct",
    "iso:country":"US",
    "sg:address":"101 Forester Ct",
    "sg:city":"Wellington",
    "sg:classifiers":[
        {
            "category":"Real Estate",
            "subcategory":"Real Estate Services",
            "type":"Services"
        },
        {
            "category":"Banks & Credit Unions",
            "subcategory":"Financial Services",
            "type":"Services"
        }
    ],
    "sg:phone":"+1 561 793 4243",
    "sg:postcode":"33414",
    "sg:province":"FL",
    "sg:tags":[
        "loan",
        "processing"
    ],
    "wof:name":"Leeward Enterprises Inc",
    "wof:placetype":"venue"
},
  "geometry": {"coordinates":[-80.24857299999999,26.679951],"type":"Point"}
}