{
  "type": "Feature",
  "properties": {
    "iso:country":"US",
    "sg:address":"4084 Camelia Dr",
    "sg:city":"Spring Hill",
    "sg:classifiers":[
        {
            "category":"Professional",
            "subcategory":"Accounting & Tax Preparation",
            "type":"Services"
        }
    ],
    "sg:phone":"+1 352 683 8211",
    "sg:postcode":"34607",
    "sg:province":"FL",
    "wof:name":"Patterson O Clinton Jr CPA",
    "wof:placetype":"venue"
},
  "geometry": {"coordinates":[-82.658675,28.491186],"type":"Point"}
}