{
  "type": "Feature",
  "properties": {
    "addr:full":"21478 Sheridan Run Estero FL 33928",
    "addr:housenumber":"21478",
    "addr:postcode":"33928",
    "addr:street":"Sheridan Run",
    "iso:country":"US",
    "sg:address":"21478 Sheridan Run",
    "sg:city":"Estero",
    "sg:classifiers":[
        {
            "category":"Wholesale",
            "subcategory":"Vending Machines",
            "type":"Manufacturing & Wholesale Goods"
        }
    ],
    "sg:phone":"+1 239 218 1763",
    "sg:postcode":"33928",
    "sg:province":"FL",
    "wof:name":"Ditone Enterprises",
    "wof:placetype":"venue"
},
  "geometry": {"coordinates":[-81.769113,26.430011],"type":"Point"}
}