{
  "type": "Feature",
  "properties": {
    "addr:full":"12111 N 58th St Tampa FL 33617",
    "addr:housenumber":"12111",
    "addr:postcode":"33617",
    "addr:street":"N 58Th St",
    "iso:country":"US",
    "sg:address":"12111 N 58th St",
    "sg:city":"Tampa",
    "sg:classifiers":[
        {
            "category":"Organizations",
            "subcategory":"Religious Organization",
            "type":"Services"
        }
    ],
    "sg:phone":"+1 813 988 4592",
    "sg:postcode":"33617",
    "sg:province":"FL",
    "sg:tags":[
        "church"
    ],
    "wof:name":"Primeria Iglesia Cristiana",
    "wof:placetype":"venue"
},
  "geometry": {"coordinates":[-82.391398,28.055966],"type":"Point"}
}