{
  "type": "Feature",
  "properties": {
    "iso:country":"US",
    "sg:address":"3841 Lake Emma Rd",
    "sg:city":"Lake Mary",
    "sg:classifiers":[
        {
            "category":"Shopping",
            "subcategory":"Computers & Home Electronics",
            "type":"Retail Goods"
        }
    ],
    "sg:phone":"+1 407 805 8885",
    "sg:postcode":"32746",
    "sg:province":"FL",
    "sg:tags":[
        "equipment",
        "dealer"
    ],
    "wof:name":"Badboy Computers Inc",
    "wof:placetype":"venue"
},
  "geometry": {"coordinates":[-81.357724,28.755306],"type":"Point"}
}