{
  "type": "Feature",
  "properties": {
    "addr:full":"6921 Phillips Industrial Blvd Jacksonville FL 32256",
    "addr:housenumber":"6921",
    "addr:postcode":"32256",
    "addr:street":"Phillips Industrial Blvd",
    "iso:country":"US",
    "sg:address":"6921 Phillips Industrial Blvd",
    "sg:city":"Jacksonville",
    "sg:classifiers":[
        {
            "category":"Freight",
            "type":"Transportation"
        }
    ],
    "sg:phone":"+1 904 292 4810",
    "sg:postcode":"32256",
    "sg:province":"FL",
    "sg:tags":[
        "operator",
        "mover",
        "local",
        "trucking"
    ],
    "wof:name":"Van Graebel Lines Inc",
    "wof:placetype":"venue"
},
  "geometry": {"coordinates":[-81.52672200000001,30.161593],"type":"Point"}
}