{
  "type": "Feature",
  "properties": {
    "iso:country":"US",
    "sg:address":"326 John Knox Rd",
    "sg:city":"Tallahassee",
    "sg:classifiers":[
        {
            "category":"Government",
            "subcategory":"Office",
            "type":"Public Place"
        }
    ],
    "sg:phone":"+1 850 891 3960",
    "sg:postcode":"32303",
    "sg:province":"FL",
    "sg:tags":[
        "village"
    ],
    "wof:name":"Tallahassee Gymnastic Ctr",
    "wof:placetype":"venue"
},
  "geometry": {"coordinates":[-84.27812,30.474638],"type":"Point"}
}