{
  "type": "Feature",
  "properties": {
    "iso:country":"US",
    "sg:address":"9557 Apalachee Pkwy",
    "sg:city":"Tallahassee",
    "sg:classifiers":[
        {
            "category":"Home & Garden",
            "subcategory":"Carpets & Floor Coverings",
            "type":"Retail Goods"
        }
    ],
    "sg:phone":"+1 850 656 2177",
    "sg:postcode":"32311",
    "sg:province":"FL",
    "wof:name":"Palmer Floor Covering",
    "wof:placetype":"venue"
},
  "geometry": {"coordinates":[-84.115099,30.422797],"type":"Point"}
}