{
  "type": "Feature",
  "properties": {
    "addr:full":"153 Spoonbill Ct Jupiter FL 33458",
    "addr:housenumber":"153",
    "addr:postcode":"33458",
    "addr:street":"Spoonbill Ct",
    "iso:country":"US",
    "sg:address":"153 Spoonbill Ct",
    "sg:city":"Jupiter",
    "sg:classifiers":[
        {
            "category":"Professional",
            "subcategory":"Accounting & Tax Preparation",
            "type":"Services"
        }
    ],
    "sg:phone":"+1 561 747 3371",
    "sg:postcode":"33458",
    "sg:province":"FL",
    "wof:name":"RC Bookkeeping Services Inc",
    "wof:placetype":"venue"
},
  "geometry": {"coordinates":[-80.125,26.924276],"type":"Point"}
}