{
  "type": "Feature",
  "properties": {
    "iso:country":"US",
    "sg:address":"26 Cardinal Dr",
    "sg:city":"Fort Myers",
    "sg:classifiers":[
        {
            "category":"Retail",
            "subcategory":"Auto Repair",
            "type":"Services"
        }
    ],
    "sg:phone":"+1 239 997 8333",
    "sg:postcode":"33917",
    "sg:province":"FL",
    "sg:tags":[
        "repairing",
        "automobile",
        "general"
    ],
    "wof:name":"Gulf Coast Auto Repair Inc",
    "wof:placetype":"venue"
},
  "geometry": {"coordinates":[-81.879586,26.667453],"type":"Point"}
}