{
  "type": "Feature",
  "properties": {
    "addr:full":"440 Cypress Rd Venice FL 34293",
    "addr:housenumber":"440",
    "addr:postcode":"34293",
    "addr:street":"Cypress Rd",
    "iso:country":"US",
    "sg:address":"440 Cypress Rd",
    "sg:city":"Venice",
    "sg:classifiers":[
        {
            "category":"Building & Trades",
            "subcategory":"Construction",
            "type":"Services"
        }
    ],
    "sg:phone":"+1 941 234 2368",
    "sg:postcode":"34293",
    "sg:province":"FL",
    "sg:tags":[
        "carpenter"
    ],
    "wof:name":"Mayers Services",
    "wof:placetype":"venue"
},
  "geometry": {"coordinates":[-82.4054,27.038006],"type":"Point"}
}