{
  "type": "Feature",
  "properties": {
    "addr:full":"3477 Pine Logging Rd Chipley FL 32428",
    "addr:housenumber":"3477",
    "addr:postcode":"32428",
    "addr:street":"Pine Logging Rd",
    "iso:country":"US",
    "sg:address":"3477 Pine Logging Rd",
    "sg:city":"Chipley",
    "sg:classifiers":[
        {
            "category":"Retail",
            "subcategory":"Auto Repair",
            "type":"Services"
        }
    ],
    "sg:phone":"+1 850 773 1366",
    "sg:postcode":"32428",
    "sg:province":"FL",
    "sg:tags":[
        "general"
    ],
    "wof:name":"Thompson Repair and Salvage",
    "wof:placetype":"venue"
},
  "geometry": {"coordinates":[-85.64335699999999,30.563139],"type":"Point"}
}