{
  "type": "Feature",
  "properties": {
    "addr:full":"2120 Co Rd 540A Lakeland FL 33813",
    "addr:housenumber":"2120;540a",
    "addr:postcode":"33813",
    "addr:street":"Co Rd",
    "iso:country":"US",
    "sg:address":"2120 Co Rd 540A",
    "sg:city":"Lakeland",
    "sg:classifiers":[
        {
            "category":"Health Services",
            "subcategory":"Doctor",
            "type":"Services"
        }
    ],
    "sg:phone":"+1 863 644 4094",
    "sg:postcode":"33813",
    "sg:province":"FL",
    "sg:tags":[
        "personal",
        "medical"
    ],
    "wof:name":"Harish M Chokshi MD",
    "wof:placetype":"venue"
},
  "geometry": {"coordinates":[-81.923586,27.952909],"type":"Point"}
}