{
  "type": "Feature",
  "properties": {
    "iso:country":"US",
    "sg:address":"207 E Hornbeam Dr",
    "sg:city":"Longwood",
    "sg:classifiers":[
        {
            "category":"Autos & Motor Vehicles",
            "subcategory":"Auto Supplies",
            "type":"Retail Goods"
        }
    ],
    "sg:phone":"+1 407 869 7633",
    "sg:postcode":"32779",
    "sg:province":"FL",
    "sg:tags":[
        "polishing",
        "car",
        "washing",
        "equipment"
    ],
    "wof:name":"Dealer Direct Distribution Inc",
    "wof:placetype":"venue"
},
  "geometry": {"coordinates":[-81.41727299999999,28.710832],"type":"Point"}
}