{
  "type": "Feature",
  "properties": {
    "iso:country":"US",
    "sg:address":"12105 67th St N",
    "sg:city":"West Palm Beach",
    "sg:classifiers":[
        {
            "category":"Freight",
            "type":"Transportation"
        }
    ],
    "sg:phone":"+1 561 753 0329",
    "sg:postcode":"33412",
    "sg:province":"FL",
    "sg:tags":[
        "operator",
        "local",
        "trucking"
    ],
    "wof:name":"Percys Landscaping",
    "wof:placetype":"venue"
},
  "geometry": {"coordinates":[-80.23163099999999,26.776371],"type":"Point"}
}