{
  "type": "Feature",
  "properties": {
    "iso:country":"US",
    "sg:address":"668 N Orlando Ave",
    "sg:city":"Maitland",
    "sg:classifiers":[
        {
            "category":"Building & Trades",
            "subcategory":"Construction",
            "type":"Services"
        }
    ],
    "sg:phone":"+1 407 622 7831",
    "sg:postcode":"32751",
    "sg:province":"FL",
    "sg:tags":[
        "interior",
        "design"
    ],
    "wof:name":"Debra Martin Interior Designer",
    "wof:placetype":"venue"
},
  "geometry": {"coordinates":[-81.36262600000001,28.632028],"type":"Point"}
}