{
  "type": "Feature",
  "properties": {
    "iso:country":"US",
    "sg:address":"14368 SW 142nd Ave",
    "sg:city":"Miami",
    "sg:classifiers":[
        {
            "category":"Wholesale",
            "subcategory":"Auto Parts",
            "type":"Manufacturing & Wholesale Goods"
        }
    ],
    "sg:phone":"+1 786 293 3886",
    "sg:postcode":"33186",
    "sg:province":"FL",
    "wof:name":"H K L International Inc",
    "wof:placetype":"venue"
},
  "geometry": {"coordinates":[-80.422922,25.634054],"type":"Point"}
}