{
  "type": "Feature",
  "properties": {
    "addr:full":"619 Verbenia Dr Satellite Beach FL 32937",
    "addr:housenumber":"619",
    "addr:postcode":"32937",
    "addr:street":"Verbenia Dr",
    "iso:country":"US",
    "sg:address":"619 Verbenia Dr",
    "sg:city":"Satellite Beach",
    "sg:classifiers":[
        {
            "category":"Building & Trades",
            "subcategory":"Construction",
            "type":"Services"
        }
    ],
    "sg:phone":"+1 321 777 5750",
    "sg:postcode":"32937",
    "sg:province":"FL",
    "sg:tags":[
        "remodeling"
    ],
    "wof:name":"Built-Rite Construction",
    "wof:placetype":"venue"
},
  "geometry": {"coordinates":[-80.590727,28.163726],"type":"Point"}
}