{
  "type": "Feature",
  "properties": {
    "addr:full":"10251 W Oakland Park Blvd Fort Lauderdale FL 33351",
    "addr:housenumber":"10251",
    "addr:postcode":"33351",
    "addr:street":"W Oakland Park Blvd",
    "iso:country":"US",
    "sg:address":"10251 W Oakland Park Blvd",
    "sg:city":"Fort Lauderdale",
    "sg:classifiers":[
        {
            "category":"Banks & Credit Unions",
            "subcategory":"Investment Brokerage",
            "type":"Services"
        },
        {
            "category":"Professional",
            "subcategory":"Business Services",
            "type":"Services"
        }
    ],
    "sg:phone":"+1 954 741 0993",
    "sg:postcode":"33351",
    "sg:province":"FL",
    "sg:tags":[
        "advisory",
        "remittance",
        "financial",
        "money"
    ],
    "wof:name":"Vigo Remittance Corp",
    "wof:placetype":"venue"
},
  "geometry": {"coordinates":[-80.28858700000001,26.170056],"type":"Point"}
}