{
  "type": "Feature",
  "properties": {
    "iso:country":"US",
    "sg:address":"3702 NE 167th St",
    "sg:city":"Miami",
    "sg:classifiers":[
        {
            "category":"Retail",
            "subcategory":"Repair Shop",
            "type":"Services"
        }
    ],
    "sg:phone":"+1 305 673 1518",
    "sg:postcode":"33160",
    "sg:province":"FL",
    "sg:tags":[
        "lock",
        "locksmith"
    ],
    "wof:name":"Rainbow Locksmith",
    "wof:placetype":"venue"
},
  "geometry": {"coordinates":[-80.13414,25.93385],"type":"Point"}
}