{
  "type": "Feature",
  "properties": {
    "iso:country":"US",
    "sg:address":"7704 Willow Brook Ct",
    "sg:city":"Hudson",
    "sg:classifiers":[
        {
            "category":"Building & Trades",
            "subcategory":"Construction",
            "type":"Services"
        }
    ],
    "sg:phone":"+1 727 847 2275",
    "sg:postcode":"34667",
    "sg:province":"FL",
    "sg:tags":[
        "painter"
    ],
    "wof:name":"Bill Meiers Painting",
    "wof:placetype":"venue"
},
  "geometry": {"coordinates":[-82.685057,28.350671],"type":"Point"}
}