{
  "type": "Feature",
  "properties": {
    "addr:full":"1916 Boy Scout Dr Fort Myers FL 33907",
    "addr:housenumber":"1916",
    "addr:postcode":"33907",
    "addr:street":"Boy Scout Dr",
    "iso:country":"US",
    "sg:address":"1916 Boy Scout Dr",
    "sg:city":"Fort Myers",
    "sg:classifiers":[
        {
            "category":"Food & Beverages",
            "subcategory":"Groceries & Convenience Stores",
            "type":"Retail Goods"
        }
    ],
    "sg:phone":"+1 239 939 3090",
    "sg:postcode":"33907",
    "sg:province":"FL",
    "wof:name":"Petra",
    "wof:placetype":"venue"
},
  "geometry": {"coordinates":[-81.87370300000001,26.582199],"type":"Point"}
}