{
  "type": "Feature",
  "properties": {
    "addr:full":"3715 S Orlando Dr Sanford FL 32773",
    "addr:housenumber":"3715",
    "addr:postcode":"32773",
    "addr:street":"S Orlando Dr",
    "iso:country":"US",
    "sg:address":"3715 S Orlando Dr",
    "sg:city":"Sanford",
    "sg:classifiers":[
        {
            "category":"Shopping",
            "subcategory":"Shoes",
            "type":"Retail Goods"
        }
    ],
    "sg:phone":"+1 407 302 1115",
    "sg:postcode":"32773",
    "sg:province":"FL",
    "sg:tags":[
        "store"
    ],
    "sg:website":"www.payless.com",
    "wof:name":"Payless Shoe Source",
    "wof:placetype":"venue"
},
  "geometry": {"coordinates":[-81.285599,28.759701],"type":"Point"}
}