{
  "type": "Feature",
  "properties": {
    "addr:full":"510 SE 15 St Gainesville FL 32641",
    "addr:housenumber":"510;15",
    "addr:postcode":"32641",
    "addr:street":"Se",
    "iso:country":"US",
    "sg:address":"510 SE 15 St",
    "sg:city":"Gainesville",
    "sg:classifiers":[
        {
            "category":"Organizations",
            "subcategory":"Religious Organization",
            "type":"Services"
        }
    ],
    "sg:phone":"+1 352 377 6973",
    "sg:postcode":"32641",
    "sg:province":"FL",
    "sg:tags":[
        "church"
    ],
    "wof:name":"Mt Olive Primitive Baptist Chr",
    "wof:placetype":"venue"
},
  "geometry": {"coordinates":[-82.305937,29.646703],"type":"Point"}
}