{
  "type": "Feature",
  "properties": {
    "iso:country":"US",
    "sg:address":"2623 Blairstone Rd",
    "sg:city":"Tallahassee",
    "sg:classifiers":[
        {
            "category":"Insurance",
            "subcategory":"Insurance Agent",
            "type":"Services"
        }
    ],
    "sg:phone":"+1 850 942 7743",
    "sg:postcode":"32301",
    "sg:province":"FL",
    "wof:name":"Figueroa Insurance Group",
    "wof:placetype":"venue"
},
  "geometry": {"coordinates":[-84.249432,30.426398],"type":"Point"}
}