{
  "type": "Feature",
  "properties": {
    "iso:country":"US",
    "sg:address":"366 E Graves Ave",
    "sg:city":"Orange City",
    "sg:classifiers":[
        {
            "category":"Manufacturing",
            "subcategory":"Electronics",
            "type":"Manufacturing & Wholesale Goods"
        }
    ],
    "sg:phone":"+1 386 775 9305",
    "sg:postcode":"32763",
    "sg:province":"FL",
    "sg:tags":[
        "equipment",
        "mfg",
        "communication"
    ],
    "wof:name":"JDS",
    "wof:placetype":"venue"
},
  "geometry": {"coordinates":[-81.29570200000001,28.948632],"type":"Point"}
}