{
  "type": "Feature",
  "properties": {
    "iso:country":"US",
    "sg:address":"348 N Seagrave St",
    "sg:city":"Daytona Beach",
    "sg:classifiers":[
        {
            "category":"Wholesale",
            "subcategory":"Construction Materials",
            "type":"Manufacturing & Wholesale Goods"
        }
    ],
    "sg:phone":"+1 386 257 3154",
    "sg:postcode":"32114",
    "sg:province":"FL",
    "sg:tags":[
        "building",
        "roofing",
        "for"
    ],
    "wof:name":"Aggregate Yard",
    "wof:placetype":"venue"
},
  "geometry": {"coordinates":[-81.028289,29.217117],"type":"Point"}
}