{
  "type": "Feature",
  "properties": {
    "addr:full":"1100 Shoreline Dr Gulf Breeze FL 32561",
    "addr:housenumber":"1100",
    "addr:postcode":"32561",
    "addr:street":"Shoreline Dr",
    "iso:country":"US",
    "sg:address":"1100 Shoreline Dr",
    "sg:city":"Gulf Breeze",
    "sg:classifiers":[
        {
            "category":"Real Estate",
            "subcategory":"Real Estate Agent",
            "type":"Services"
        }
    ],
    "sg:phone":"+1 850 932 7749",
    "sg:postcode":"32561",
    "sg:province":"FL",
    "wof:name":"Sailwind Condominium Assoc",
    "wof:placetype":"venue"
},
  "geometry": {"coordinates":[-87.174758,30.354914],"type":"Point"}
}