{
  "type": "Feature",
  "properties": {
    "addr:full":"4749 S Orange Ave Orlando FL 32806",
    "addr:housenumber":"4749",
    "addr:postcode":"32806",
    "addr:street":"S Orange Ave",
    "iso:country":"US",
    "sg:address":"4749 S Orange Ave",
    "sg:city":"Orlando",
    "sg:classifiers":[
        {
            "category":"Health Services",
            "subcategory":"Chiropractor",
            "type":"Services"
        }
    ],
    "sg:phone":"+1 407 851 0980",
    "sg:postcode":"32806",
    "sg:province":"FL",
    "sg:tags":[
        "clinic",
        "therapy",
        "physical"
    ],
    "wof:name":"Central Florida Chiropractic Center",
    "wof:placetype":"venue"
},
  "geometry": {"coordinates":[-81.37479,28.494243],"type":"Point"}
}