{
  "type": "Feature",
  "properties": {
    "iso:country":"US",
    "sg:address":"6161 NW 72nd Ave",
    "sg:city":"Miami",
    "sg:classifiers":[
        {
            "category":"Manufacturing",
            "subcategory":"Wood Products",
            "type":"Manufacturing & Wholesale Goods"
        },
        {
            "category":"Shopping",
            "subcategory":"Pets & Pet Supplies",
            "type":"Retail Goods"
        },
        {
            "category":"Home & Garden",
            "subcategory":"Furniture",
            "type":"Retail Goods"
        }
    ],
    "sg:phone":"+1 305 882 8930",
    "sg:postcode":"33166",
    "sg:province":"FL",
    "sg:tags":[
        "furniture-outdoor-wholesale",
        "outdoor",
        "equipment",
        "patio",
        "manufacturer"
    ],
    "sg:website":"http://www.cozydays.com",
    "wof:name":"Cozydays Inc.",
    "wof:placetype":"venue"
},
  "geometry": {"coordinates":[-80.313761,25.829806],"type":"Point"}
}