{
  "type": "Feature",
  "properties": {
    "iso:country":"US",
    "sg:address":"400 Douglas Rd E",
    "sg:city":"Oldsmar",
    "sg:classifiers":[
        {
            "category":"Professional",
            "type":"Services"
        }
    ],
    "sg:phone":"+1 813 749 8218",
    "sg:postcode":"34677",
    "sg:province":"FL",
    "sg:tags":[
        "establishment"
    ],
    "wof:name":"Adela & Son",
    "wof:placetype":"venue"
},
  "geometry": {"coordinates":[-82.656108,28.041535],"type":"Point"}
}