{
  "type": "Feature",
  "properties": {
    "iso:country":"US",
    "sg:address":"711 Aljohn St",
    "sg:city":"Nokomis",
    "sg:classifiers":[
        {
            "category":"Building & Trades",
            "subcategory":"Cleaning & Sanitation",
            "type":"Services"
        },
        {
            "category":"Building & Trades",
            "subcategory":"Construction",
            "type":"Services"
        }
    ],
    "sg:phone":"+1 941 234 6176",
    "sg:postcode":"34275",
    "sg:province":"FL",
    "sg:tags":[
        "marble",
        "sealing",
        "terrazzo",
        "tile-cleaning",
        "refinishing"
    ],
    "wof:name":"West Coast Tile Setting Inc",
    "wof:placetype":"venue"
},
  "geometry": {"coordinates":[-82.442341,27.1206],"type":"Point"}
}