{
  "type": "Feature",
  "properties": {
    "addr:full":"1032 Hendricks Ave Jacksonville FL 32207",
    "addr:housenumber":"1032",
    "addr:postcode":"32207",
    "addr:street":"Hendricks Ave",
    "iso:country":"US",
    "sg:address":"1032 Hendricks Ave",
    "sg:city":"Jacksonville",
    "sg:classifiers":[
        {
            "category":"Personal",
            "subcategory":"Beauty Salon",
            "type":"Services"
        }
    ],
    "sg:phone":"+1 904 398 9722",
    "sg:postcode":"32207",
    "sg:province":"FL",
    "wof:name":"Salon San Marco",
    "wof:placetype":"venue"
},
  "geometry": {"coordinates":[-81.65480700000001,30.31602],"type":"Point"}
}