{
  "type": "Feature",
  "properties": {
    "iso:country":"US",
    "sg:address":"6500 N Military Trl",
    "sg:city":"West Palm Beach",
    "sg:classifiers":[
        {
            "category":"Travel",
            "subcategory":"Campground",
            "type":"Entertainment"
        }
    ],
    "sg:phone":"+1 561 848 6170",
    "sg:postcode":"33407",
    "sg:province":"FL",
    "sg:website":"www.vacationinnresort.com",
    "wof:name":"Vacation Inn Resort Of Palm",
    "wof:placetype":"venue"
},
  "geometry": {"coordinates":[-80.107739,26.772482],"type":"Point"}
}