{
  "type": "Feature",
  "properties": {
    "addr:full":"4100 N Powerline Rd Pompano Beach FL 33073",
    "addr:housenumber":"4100",
    "addr:postcode":"33073",
    "addr:street":"N Powerline Rd",
    "iso:country":"US",
    "sg:address":"4100 N Powerline Rd",
    "sg:city":"Pompano Beach",
    "sg:classifiers":[
        {
            "category":"Retail",
            "subcategory":"Repair Shop",
            "type":"Services"
        },
        {
            "category":"Wholesale",
            "subcategory":"Electrical",
            "type":"Manufacturing & Wholesale Goods"
        }
    ],
    "sg:phone":"+1 954 978 0078",
    "sg:postcode":"33073",
    "sg:province":"FL",
    "sg:tags":[
        "equipment",
        "electronic",
        "amplifier",
        "supply"
    ],
    "wof:name":"Thompson Radio & Communication",
    "wof:placetype":"venue"
},
  "geometry": {"coordinates":[-80.15208800000001,26.279546],"type":"Point"}
}