{
  "type": "Feature",
  "properties": {
    "addr:full":"14567 Shadow Wood Ln Delray Beach FL 33484",
    "addr:housenumber":"14567",
    "addr:postcode":"33484",
    "addr:street":"Shadow Wood Ln",
    "iso:country":"US",
    "sg:address":"14567 Shadow Wood Ln",
    "sg:city":"Delray Beach",
    "sg:classifiers":[
        {
            "category":"Wholesale",
            "subcategory":"Plants",
            "type":"Manufacturing & Wholesale Goods"
        }
    ],
    "sg:phone":"+1 561 638 5768",
    "sg:postcode":"33484",
    "sg:province":"FL",
    "sg:tags":[
        "merchandise",
        "supply"
    ],
    "wof:name":"Orchid Explosion Inc",
    "wof:placetype":"venue"
},
  "geometry": {"coordinates":[-80.14003700000001,26.459722],"type":"Point"}
}