{
  "type": "Feature",
  "properties": {
    "addr:full":"3118 Lawton Ct Panama City FL 32405",
    "addr:housenumber":"3118",
    "addr:postcode":"32405",
    "addr:street":"Lawton Ct",
    "iso:country":"US",
    "sg:address":"3118 Lawton Ct",
    "sg:city":"Panama City",
    "sg:classifiers":[
        {
            "category":"Home & Garden",
            "subcategory":"Home Furnishings",
            "type":"Retail Goods"
        }
    ],
    "sg:phone":"+1 850 215 8826",
    "sg:postcode":"32405",
    "sg:province":"FL",
    "sg:tags":[
        "venetian",
        "blind"
    ],
    "wof:name":"Blinds R Us",
    "wof:placetype":"venue"
},
  "geometry": {"coordinates":[-85.67759599999999,30.201503],"type":"Point"}
}