{
  "type": "Feature",
  "properties": {
    "addr:full":"1250 Minnesota Ave Winter Park FL 32789",
    "addr:housenumber":"1250",
    "addr:postcode":"32789",
    "addr:street":"Minnesota Ave",
    "iso:country":"US",
    "sg:address":"1250 Minnesota Ave",
    "sg:city":"Winter Park",
    "sg:classifiers":[
        {
            "category":"Manufacturing",
            "subcategory":"Electronics",
            "type":"Manufacturing & Wholesale Goods"
        }
    ],
    "sg:phone":"+1 407 677 6616",
    "sg:postcode":"32789",
    "sg:province":"FL",
    "sg:tags":[
        "computer",
        "des",
        "system",
        "devices",
        "mfg"
    ],
    "wof:name":"Softwear Techniques Inc",
    "wof:placetype":"venue"
},
  "geometry": {"coordinates":[-81.366091,28.589382],"type":"Point"}
}