{
  "type": "Feature",
  "properties": {
    "addr:full":"7071 Pelican Bay Blvd Naples FL 34108",
    "addr:housenumber":"7071",
    "addr:postcode":"34108",
    "addr:street":"Pelican Bay Blvd",
    "iso:country":"US",
    "sg:address":"7071 Pelican Bay Blvd",
    "sg:city":"Naples",
    "sg:classifiers":[
        {
            "category":"Real Estate",
            "subcategory":"Real Estate Agent",
            "type":"Services"
        }
    ],
    "sg:phone":"+1 239 598 9900",
    "sg:postcode":"34108",
    "sg:province":"FL",
    "wof:name":"Gulf Bay Marketing Group",
    "wof:placetype":"venue"
},
  "geometry": {"coordinates":[-81.812386,26.23798],"type":"Point"}
}