{
  "type": "Feature",
  "properties": {
    "addr:full":"6101 Webb Rd Ste 311 Tampa FL 33615",
    "addr:housenumber":"6101",
    "addr:postcode":"33615",
    "addr:street":"Webb Rd Ste 311",
    "iso:country":"US",
    "sg:address":"6101 Webb Rd Ste 311",
    "sg:city":"Tampa",
    "sg:classifiers":[
        {
            "category":"Health Services",
            "subcategory":"Doctor",
            "type":"Services"
        }
    ],
    "sg:phone":"+1 813 886 7112",
    "sg:postcode":"33615",
    "sg:province":"FL",
    "sg:tags":[
        "physician",
        "family",
        "practice",
        "surgeons",
        "medicine",
        "surgeon"
    ],
    "wof:name":"Fernando A Rodriguez Md",
    "wof:placetype":"venue"
},
  "geometry": {"coordinates":[-82.57518,28.00334],"type":"Point"}
}