{
  "type": "Feature",
  "properties": {
    "addr:full":"1579 N Nova Rd Daytona Beach FL 32117",
    "addr:housenumber":"1579",
    "addr:postcode":"32117",
    "addr:street":"N Nova Rd",
    "iso:country":"US",
    "sg:address":"1579 N Nova Rd",
    "sg:city":"Daytona Beach",
    "sg:classifiers":[
        {
            "category":"Shopping",
            "subcategory":"Discount & Variety Stores",
            "type":"Retail Goods"
        }
    ],
    "sg:phone":"+1 386 252 6760",
    "sg:postcode":"32117",
    "sg:province":"FL",
    "wof:name":"Family Dollar Stores",
    "wof:placetype":"venue"
},
  "geometry": {"coordinates":[-81.057581,29.238661],"type":"Point"}
}