{
  "type": "Feature",
  "properties": {
    "iso:country":"US",
    "sg:address":"3542 Fair Oaks Ln",
    "sg:city":"Longboat Key",
    "sg:classifiers":[
        {
            "category":"Professional",
            "subcategory":"Business Services",
            "type":"Services"
        }
    ],
    "sg:phone":"+1 941 383 4398",
    "sg:postcode":"34228",
    "sg:province":"FL",
    "sg:tags":[
        "development",
        "publisher",
        "music",
        "software"
    ],
    "wof:name":"Stephens Development Co",
    "wof:placetype":"venue"
},
  "geometry": {"coordinates":[-82.626153,27.381319],"type":"Point"}
}