{
  "type": "Feature",
  "properties": {
    "iso:country":"US",
    "sg:address":"308 N Dixie Hwy",
    "sg:city":"West Palm Beach",
    "sg:classifiers":[
        {
            "category":"Shopping",
            "subcategory":"Clothing, Apparel, & Fashions",
            "type":"Retail Goods"
        }
    ],
    "sg:phone":"+1 561 533 3909",
    "sg:postcode":"33401",
    "sg:province":"FL",
    "sg:tags":[
        "dancing",
        "supply"
    ],
    "wof:name":"Center Stage Sewing",
    "wof:placetype":"venue"
},
  "geometry": {"coordinates":[-80.053397,26.715724],"type":"Point"}
}