{
  "type": "Feature",
  "properties": {
    "iso:country":"US",
    "sg:address":"142 Fairway Cir",
    "sg:city":"Naples",
    "sg:classifiers":[
        {
            "category":"Sports & Exercise",
            "subcategory":"Gym",
            "type":"Entertainment"
        }
    ],
    "sg:phone":"+1 239 597 0787",
    "sg:postcode":"34110",
    "sg:province":"FL",
    "sg:tags":[
        "club",
        "health",
        "studio",
        "gymnasium"
    ],
    "wof:name":"Health Club Of Naples",
    "wof:placetype":"venue"
},
  "geometry": {"coordinates":[-81.78205800000001,26.280922],"type":"Point"}
}