{
  "type": "Feature",
  "properties": {
    "addr:full":"1423 NW 3rd Ave Fort Lauderdale FL 33311",
    "addr:housenumber":"1423",
    "addr:postcode":"33311",
    "addr:street":"Nw 3Rd Ave",
    "iso:country":"US",
    "sg:address":"1423 NW 3rd Ave",
    "sg:city":"Fort Lauderdale",
    "sg:classifiers":[
        {
            "category":"Manufacturing",
            "subcategory":"Signs",
            "type":"Manufacturing & Wholesale Goods"
        }
    ],
    "sg:phone":"+1 954 817 0944",
    "sg:postcode":"33311",
    "sg:province":"FL",
    "wof:name":"Signs & Designs",
    "wof:placetype":"venue"
},
  "geometry": {"coordinates":[-80.14741600000001,26.145191],"type":"Point"}
}