{
  "type": "Feature",
  "properties": {
    "addr:full":"2201 NW 9th Ave Fort Lauderdale FL 33311",
    "addr:housenumber":"2201",
    "addr:postcode":"33311",
    "addr:street":"Nw 9Th Ave",
    "iso:country":"US",
    "sg:address":"2201 NW 9th Ave",
    "sg:city":"Fort Lauderdale",
    "sg:classifiers":[
        {
            "category":"Manufacturing",
            "subcategory":"Furniture",
            "type":"Manufacturing & Wholesale Goods"
        }
    ],
    "sg:phone":"+1 954 828 4565",
    "sg:postcode":"33311",
    "sg:province":"FL",
    "sg:tags":[
        "building",
        "public",
        "mfg"
    ],
    "wof:name":"Mills Pond Softball Complex",
    "wof:placetype":"venue"
},
  "geometry": {"coordinates":[-80.154442,26.153925],"type":"Point"}
}