{
  "type": "Feature",
  "properties": {
    "iso:country":"US",
    "sg:address":"616 W 1st St",
    "sg:city":"Sanford",
    "sg:classifiers":[
        {
            "category":"Shopping",
            "subcategory":"Hobbies, Toys, & Games",
            "type":"Retail Goods"
        },
        {
            "category":"Shopping",
            "subcategory":"Jewelry",
            "type":"Retail Goods"
        },
        {
            "category":"Manufacturing",
            "subcategory":"Jewelry",
            "type":"Manufacturing & Wholesale Goods"
        },
        {
            "category":"Professional",
            "subcategory":"Business Services",
            "type":"Services"
        }
    ],
    "sg:phone":"+1 407 321 2211",
    "sg:postcode":"32771",
    "sg:province":"FL",
    "sg:tags":[
        "shop",
        "designer",
        "supply",
        "auction",
        "jeweler",
        "hobby",
        "model",
        "coin"
    ],
    "sg:website":"http://www.kenscoins.net",
    "wof:name":"Dittmann Kenneth Numismatist",
    "wof:placetype":"venue"
},
  "geometry": {"coordinates":[-81.27334,28.811709],"type":"Point"}
}