{
  "type": "Feature",
  "properties": {
    "addr:full":"101 67th St Holmes Beach FL 34217",
    "addr:housenumber":"101",
    "addr:postcode":"34217",
    "addr:street":"67Th St",
    "iso:country":"US",
    "sg:address":"101 67th St",
    "sg:city":"Holmes Beach",
    "sg:classifiers":[
        {
            "category":"Travel",
            "subcategory":"Hotels & Motels",
            "type":"Entertainment"
        }
    ],
    "sg:phone":"+1 941 779 2627",
    "sg:postcode":"34217",
    "sg:province":"FL",
    "sg:tags":[
        "breakfast",
        "accommodation",
        "bed"
    ],
    "wof:name":"Harrington House B & B",
    "wof:placetype":"venue"
},
  "geometry": {"coordinates":[-82.72202,27.512739],"type":"Point"}
}