{
  "type": "Feature",
  "properties": {
    "addr:full":"338 NW 171st St Miami FL 33169",
    "addr:housenumber":"338",
    "addr:postcode":"33169",
    "addr:street":"Nw 171St St",
    "iso:country":"US",
    "sg:address":"338 NW 171st St",
    "sg:city":"Miami",
    "sg:classifiers":[
        {
            "category":"Retail",
            "subcategory":"Auto Repair",
            "type":"Services"
        }
    ],
    "sg:phone":"+1 305 651 7070",
    "sg:postcode":"33169",
    "sg:province":"FL",
    "wof:name":"Performance Auto",
    "wof:placetype":"venue"
},
  "geometry": {"coordinates":[-80.20760300000001,25.931601],"type":"Point"}
}