{
  "type": "Feature",
  "properties": {
    "iso:country":"US",
    "sg:address":"2254 NW 94th Ave",
    "sg:city":"Miami",
    "sg:classifiers":[
        {
            "category":"Professional",
            "type":"Services"
        }
    ],
    "sg:phone":"+1 305 594 7799",
    "sg:postcode":"33024",
    "sg:province":"FL",
    "sg:tags":[
        "establishment"
    ],
    "wof:name":"Altima Technologies Inc",
    "wof:placetype":"venue"
},
  "geometry": {"coordinates":[-80.271466,26.028155],"type":"Point"}
}