{
  "type": "Feature",
  "properties": {
    "iso:country":"US",
    "sg:address":"1069 NW 53rd St",
    "sg:city":"Fort Lauderdale",
    "sg:classifiers":[
        {
            "category":"Manufacturing",
            "subcategory":"Retail Goods",
            "type":"Manufacturing & Wholesale Goods"
        }
    ],
    "sg:phone":"+1 954 938 9039",
    "sg:postcode":"33309",
    "sg:province":"FL",
    "sg:tags":[
        "mfg"
    ],
    "wof:name":"D & K Street Sweeping Inc",
    "wof:placetype":"venue"
},
  "geometry": {"coordinates":[-80.158845,26.192197],"type":"Point"}
}