{
  "type": "Feature",
  "properties": {
    "iso:country":"US",
    "sg:address":"706 NW 8th Ave",
    "sg:city":"Dania",
    "sg:classifiers":[
        {
            "category":"Building & Trades",
            "subcategory":"Construction",
            "type":"Services"
        }
    ],
    "sg:phone":"+1 954 921 1063",
    "sg:postcode":"33004",
    "sg:province":"FL",
    "sg:tags":[
        "floor",
        "laying",
        "contractor"
    ],
    "wof:name":"J&J Flooring Unlimited Inc",
    "wof:placetype":"venue"
},
  "geometry": {"coordinates":[-80.149388,26.06126],"type":"Point"}
}