{
  "type": "Feature",
  "properties": {
    "addr:full":"332 Cocoanut Ave Sarasota FL 34236",
    "addr:housenumber":"332",
    "addr:postcode":"34236",
    "addr:street":"Cocoanut Ave",
    "iso:country":"US",
    "sg:address":"332 Cocoanut Ave",
    "sg:city":"Sarasota",
    "sg:classifiers":[
        {
            "category":"Professional",
            "subcategory":"Management & Consulting",
            "type":"Services"
        }
    ],
    "sg:phone":"+1 941 373 9222",
    "sg:postcode":"34236",
    "sg:province":"FL",
    "sg:tags":[
        "consultant",
        "resource",
        "human"
    ],
    "wof:name":"Vocational Perspective Inc",
    "wof:placetype":"venue"
},
  "geometry": {"coordinates":[-82.54464400000001,27.339022],"type":"Point"}
}