{
  "type": "Feature",
  "properties": {
    "iso:country":"US",
    "sg:address":"438 E Monroe St",
    "sg:city":"Jacksonville",
    "sg:classifiers":[
        {
            "category":"Professional",
            "subcategory":"Lawyer & Legal Services",
            "type":"Services"
        }
    ],
    "sg:phone":"+1 904 358 8778",
    "sg:postcode":"32202",
    "sg:province":"FL",
    "sg:tags":[
        "attorney"
    ],
    "wof:name":"Muench & Luca",
    "wof:placetype":"venue"
},
  "geometry": {"coordinates":[-81.651465,30.32713],"type":"Point"}
}