{
  "type": "Feature",
  "properties": {
    "iso:country":"US",
    "sg:address":"6900 Landings Dr Apt 202",
    "sg:city":"Lauderhill",
    "sg:classifiers":[
        {
            "category":"Professional",
            "subcategory":"Management & Consulting",
            "type":"Services"
        },
        {
            "category":"Professional",
            "subcategory":"Advertising",
            "type":"Services"
        }
    ],
    "sg:phone":"+1 954 731 2865",
    "sg:postcode":"33319",
    "sg:province":"FL",
    "sg:tags":[
        "marketing",
        "program",
        "consultant"
    ],
    "wof:name":"Khan International Marketing I",
    "wof:placetype":"venue"
},
  "geometry": {"coordinates":[-80.23974,26.166667],"type":"Point"}
}