{
  "type": "Feature",
  "properties": {
    "iso:country":"US",
    "sg:address":"1021 SW Alexandria Ave",
    "sg:city":"Port St Lucie",
    "sg:classifiers":[
        {
            "category":"Wholesale",
            "subcategory":"Non-durable Goods",
            "type":"Manufacturing & Wholesale Goods"
        },
        {
            "category":"Wholesale",
            "subcategory":"Durable Goods & Equipment",
            "type":"Manufacturing & Wholesale Goods"
        }
    ],
    "sg:phone":"+1 772 344 7902",
    "sg:postcode":"34953",
    "sg:province":"FL",
    "sg:tags":[
        "importer"
    ],
    "wof:name":"Teak Imports",
    "wof:placetype":"venue"
},
  "geometry": {"coordinates":[-80.38239299999999,27.249065],"type":"Point"}
}