{
  "type": "Feature",
  "properties": {
    "iso:country":"US",
    "sg:address":"11049 NW 6th Ter",
    "sg:city":"Miami",
    "sg:classifiers":[
        {
            "category":"Wholesale",
            "subcategory":"Machinery & Supplies",
            "type":"Manufacturing & Wholesale Goods"
        }
    ],
    "sg:phone":"+1 305 222 9314",
    "sg:postcode":"33172",
    "sg:province":"FL",
    "sg:tags":[
        "medical-cylinder",
        "bulk",
        "gas-industrial"
    ],
    "wof:name":"Techwood Industrial Gases",
    "wof:placetype":"venue"
},
  "geometry": {"coordinates":[-80.37596499999999,25.774843],"type":"Point"}
}