{
  "type": "Feature",
  "properties": {
    "addr:full":"3530 1st Ave N St Petersburg FL 33713",
    "addr:housenumber":"3530",
    "addr:postcode":"33713",
    "addr:street":"1St Ave N",
    "iso:country":"US",
    "sg:address":"3530 1st Ave N",
    "sg:city":"St Petersburg",
    "sg:classifiers":[
        {
            "category":"Insurance",
            "subcategory":"Insurance Agent",
            "type":"Services"
        }
    ],
    "sg:phone":"+1 727 323 4054",
    "sg:postcode":"33713",
    "sg:province":"FL",
    "wof:name":"Rick Applefield Insurance",
    "wof:placetype":"venue"
},
  "geometry": {"coordinates":[-82.68176,27.771786],"type":"Point"}
}