{
  "type": "Feature",
  "properties": {
    "iso:country":"US",
    "sg:address":"1730 Teal Briar",
    "sg:city":"Oviedo",
    "sg:classifiers":[
        {
            "category":"Organizations",
            "subcategory":"Religious Organization",
            "type":"Services"
        }
    ],
    "sg:phone":"+1 407 859 2236",
    "sg:postcode":"32765",
    "sg:province":"FL",
    "sg:tags":[
        "church"
    ],
    "wof:name":"Temple Yeshua-Biblcl Messianic",
    "wof:placetype":"venue"
},
  "geometry": {"coordinates":[-81.176012,28.628102],"type":"Point"}
}