{
  "type": "Feature",
  "properties": {
    "iso:country":"US",
    "sg:address":"15165 NW 77th Ave",
    "sg:city":"Hialeah",
    "sg:classifiers":[
        {
            "category":"Real Estate",
            "subcategory":"Real Estate Services",
            "type":"Services"
        }
    ],
    "sg:phone":"+1 305 820 0707",
    "sg:postcode":"33014",
    "sg:province":"FL",
    "sg:tags":[
        "company",
        "title"
    ],
    "wof:name":"Lakes Title Svc",
    "wof:placetype":"venue"
},
  "geometry": {"coordinates":[-80.324181,25.906705],"type":"Point"}
}