{
  "type": "Feature",
  "properties": {
    "iso:country":"US",
    "sg:address":"6385 Bass Hwy",
    "sg:city":"Saint Cloud",
    "sg:classifiers":[
        {
            "category":"Wholesale",
            "subcategory":"Groceries",
            "type":"Manufacturing & Wholesale Goods"
        }
    ],
    "sg:phone":"+1 407 892 7367",
    "sg:postcode":"34771",
    "sg:province":"FL",
    "sg:tags":[
        "general"
    ],
    "wof:name":"W J Produce",
    "wof:placetype":"venue"
},
  "geometry": {"coordinates":[-81.18124899999999,28.256995],"type":"Point"}
}