{
  "type": "Feature",
  "properties": {
    "addr:full":"1500 S Ocean Blvd Boca Raton FL 33432",
    "addr:housenumber":"1500",
    "addr:postcode":"33432",
    "addr:street":"S Ocean Blvd",
    "iso:country":"US",
    "sg:address":"1500 S Ocean Blvd",
    "sg:city":"Boca Raton",
    "sg:classifiers":[
        {
            "category":"Real Estate",
            "subcategory":"Real Estate Operator",
            "type":"Services"
        }
    ],
    "sg:phone":"+1 561 395 3848",
    "sg:postcode":"33432",
    "sg:province":"FL",
    "sg:tags":[
        "condominium"
    ],
    "wof:name":"Addison Condominium Resident",
    "wof:placetype":"venue"
},
  "geometry": {"coordinates":[-80.07485200000001,26.328847],"type":"Point"}
}