{
  "type": "Feature",
  "properties": {
    "iso:country":"US",
    "sg:address":"2604 Kynesville Rd",
    "sg:city":"Cottondale",
    "sg:classifiers":[
        {
            "category":"Autos & Motor Vehicles",
            "subcategory":"Automobile Sales",
            "type":"Retail Goods"
        }
    ],
    "sg:phone":"+1 850 579 1270",
    "sg:postcode":"32431",
    "sg:province":"FL",
    "sg:tags":[
        "used"
    ],
    "wof:name":"PC Buyers Inc",
    "wof:placetype":"venue"
},
  "geometry": {"coordinates":[-85.376598,30.72728],"type":"Point"}
}