{
  "type": "Feature",
  "properties": {
    "iso:country":"US",
    "sg:address":"7602 Congress St",
    "sg:city":"New Port Richey",
    "sg:classifiers":[
        {
            "category":"Real Estate",
            "subcategory":"Real Estate Operator",
            "type":"Services"
        }
    ],
    "sg:phone":"+1 727 847 2800",
    "sg:postcode":"34653",
    "sg:province":"FL",
    "sg:tags":[
        "building",
        "apartment"
    ],
    "wof:name":"Florida West Management Svcs",
    "wof:placetype":"venue"
},
  "geometry": {"coordinates":[-82.707257,28.26727],"type":"Point"}
}