{
  "type": "Feature",
  "properties": {
    "iso:country":"US",
    "sg:address":"3015 NW 79th St",
    "sg:city":"Miami",
    "sg:classifiers":[
        {
            "category":"Shopping",
            "subcategory":"Clothing, Apparel, & Fashions",
            "type":"Retail Goods"
        }
    ],
    "sg:phone":"+1 305 696 2550",
    "sg:postcode":"33147",
    "sg:province":"FL",
    "sg:tags":[
        "accessory",
        "clothing",
        "women's"
    ],
    "wof:name":"Fashion Q",
    "wof:placetype":"venue"
},
  "geometry": {"coordinates":[-80.246498,25.8458],"type":"Point"}
}