{
  "type": "Feature",
  "properties": {
    "addr:full":"2100 W French Ave Orange City FL 32763",
    "addr:housenumber":"2100",
    "addr:postcode":"32763",
    "addr:street":"W French Ave",
    "iso:country":"US",
    "sg:address":"2100 W French Ave",
    "sg:city":"Orange City",
    "sg:classifiers":[
        {
            "category":"Travel",
            "subcategory":"Travel Agent",
            "type":"Entertainment"
        }
    ],
    "sg:phone":"+1 386 917 0724",
    "sg:postcode":"32763",
    "sg:province":"FL",
    "sg:tags":[
        "cruise"
    ],
    "wof:name":"Saint Johns River Ecotours Inc",
    "wof:placetype":"venue"
},
  "geometry": {"coordinates":[-81.34065,28.952231],"type":"Point"}
}