{
  "type": "Feature",
  "properties": {
    "addr:full":"3201 E Colonial Dr Orlando FL 32803",
    "addr:housenumber":"3201",
    "addr:postcode":"32803",
    "addr:street":"E Colonial Dr",
    "iso:country":"US",
    "sg:address":"3201 E Colonial Dr",
    "sg:city":"Orlando",
    "sg:classifiers":[
        {
            "category":"Restaurant",
            "type":"Food & Drink"
        }
    ],
    "sg:phone":"+1 407 898 4007",
    "sg:postcode":"32803",
    "sg:province":"FL",
    "wof:name":"Taco Bell",
    "wof:placetype":"venue"
},
  "geometry": {"coordinates":[-81.343277,28.553407],"type":"Point"}
}