{
  "type": "Feature",
  "properties": {
    "addr:full":"3100 E Oakland Park Blvd Fort Lauderdale FL 33308",
    "addr:housenumber":"3100",
    "addr:postcode":"33308",
    "addr:street":"E Oakland Park Blvd",
    "iso:country":"US",
    "sg:address":"3100 E Oakland Park Blvd",
    "sg:city":"Fort Lauderdale",
    "sg:classifiers":[
        {
            "category":"Recreation",
            "subcategory":"Marina",
            "type":"Entertainment"
        }
    ],
    "sg:phone":"+1 954 563 7101",
    "sg:postcode":"33308",
    "sg:province":"FL",
    "sg:tags":[
        "repair",
        "incidental",
        "storage",
        "boat",
        "brokerage"
    ],
    "wof:name":"Marina Mar of Ft Lauderdale",
    "wof:placetype":"venue"
},
  "geometry": {"coordinates":[-80.104731,26.167527],"type":"Point"}
}