{
  "type": "Feature",
  "properties": {
    "iso:country":"US",
    "sg:address":"415 Main St",
    "sg:city":"Auburndale",
    "sg:classifiers":[
        {
            "category":"Restaurant",
            "type":"Food & Drink"
        }
    ],
    "sg:phone":"+1 863 967 8606",
    "sg:postcode":"33823",
    "sg:province":"FL",
    "sg:tags":[
        "eating"
    ],
    "wof:name":"Main Street Diner",
    "wof:placetype":"venue"
},
  "geometry": {"coordinates":[-81.788608,28.059094],"type":"Point"}
}