{
  "type": "Feature",
  "properties": {
    "iso:country":"US",
    "sg:address":"1320 Stirling Rd",
    "sg:city":"Dania",
    "sg:classifiers":[
        {
            "category":"Home & Garden",
            "subcategory":"Furniture",
            "type":"Retail Goods"
        }
    ],
    "sg:phone":"+1 954 924 0053",
    "sg:postcode":"33004",
    "sg:province":"FL",
    "sg:tags":[
        "mattress"
    ],
    "wof:name":"Cloud 9 Mattress",
    "wof:placetype":"venue"
},
  "geometry": {"coordinates":[-80.154439,26.048324],"type":"Point"}
}