{
  "type": "Feature",
  "properties": {
    "iso:country":"US",
    "sg:address":"385 East Dr",
    "sg:city":"Melbourne",
    "sg:classifiers":[
        {
            "category":"Shopping",
            "subcategory":"Computers & Home Electronics",
            "type":"Retail Goods"
        }
    ],
    "sg:phone":"+1 321 729 8850",
    "sg:postcode":"32904",
    "sg:province":"FL",
    "sg:tags":[
        "equipment",
        "electronic",
        "supply"
    ],
    "wof:name":"Melbourne Venture Group",
    "wof:placetype":"venue"
},
  "geometry": {"coordinates":[-80.68896700000001,28.100153],"type":"Point"}
}