{
  "type": "Feature",
  "properties": {
    "iso:country":"US",
    "sg:address":"212 Jonesbury Ct",
    "sg:city":"Longwood",
    "sg:classifiers":[
        {
            "category":"Building & Trades",
            "subcategory":"Cleaning & Sanitation",
            "type":"Services"
        }
    ],
    "sg:phone":"+1 407 869 0542",
    "sg:postcode":"32779",
    "sg:province":"FL",
    "sg:tags":[
        "janitor"
    ],
    "wof:name":"Best Service",
    "wof:placetype":"venue"
},
  "geometry": {"coordinates":[-81.453682,28.698049],"type":"Point"}
}