{
  "type": "Feature",
  "properties": {
    "addr:full":"21 N Nova Rd Ormond Beach FL 32174",
    "addr:housenumber":"21",
    "addr:postcode":"32174",
    "addr:street":"N Nova Rd",
    "iso:country":"US",
    "sg:address":"21 N Nova Rd",
    "sg:city":"Ormond Beach",
    "sg:classifiers":[
        {
            "category":"Restaurant",
            "type":"Food & Drink"
        }
    ],
    "sg:phone":"+1 386 677 1106",
    "sg:postcode":"32174",
    "sg:province":"FL",
    "sg:tags":[
        "grocery",
        "eating"
    ],
    "wof:name":"Mr Wich Deli",
    "wof:placetype":"venue"
},
  "geometry": {"coordinates":[-81.08263700000001,29.280296],"type":"Point"}
}