{
  "type": "Feature",
  "properties": {
    "addr:full":"6200 Old Middleburg Rd S Jacksonville FL 32222",
    "addr:housenumber":"6200",
    "addr:postcode":"32222",
    "addr:street":"Old Middleburg Rd",
    "iso:country":"US",
    "sg:address":"6200 Old Middleburg Rd S",
    "sg:city":"Jacksonville",
    "sg:classifiers":[
        {
            "category":"Professional",
            "type":"Services"
        }
    ],
    "sg:phone":"+1 904 771 0047",
    "sg:postcode":"32222",
    "sg:province":"FL",
    "sg:tags":[
        "establishment"
    ],
    "wof:name":"Argyle Athletic Assoc Jax Hgts",
    "wof:placetype":"venue"
},
  "geometry": {"coordinates":[-81.80600200000001,30.234422],"type":"Point"}
}