{
  "type": "Feature",
  "properties": {
    "addr:full":"6540 Kimberly Blvd Pompano Beach FL 33068",
    "addr:housenumber":"6540",
    "addr:postcode":"33068",
    "addr:street":"Kimberly Blvd",
    "iso:country":"US",
    "sg:address":"6540 Kimberly Blvd",
    "sg:city":"Pompano Beach",
    "sg:classifiers":[
        {
            "category":"Building & Trades",
            "subcategory":"Construction",
            "type":"Services"
        }
    ],
    "sg:phone":"+1 954 303 8264",
    "sg:postcode":"33068",
    "sg:province":"FL",
    "sg:tags":[
        "hanging",
        "contractor"
    ],
    "wof:name":"Beas Fabian Gustavo",
    "wof:placetype":"venue"
},
  "geometry": {"coordinates":[-80.213718,26.217681],"type":"Point"}
}