{
  "type": "Feature",
  "properties": {
    "iso:country":"US",
    "sg:address":"1710 Linwood Ave",
    "sg:city":"Fort Pierce",
    "sg:classifiers":[
        {
            "category":"Retail",
            "subcategory":"Portrait Studio",
            "type":"Services"
        },
        {
            "category":"Personal",
            "subcategory":"Beauty Salon",
            "type":"Services"
        }
    ],
    "sg:phone":"+1 772 461 3184",
    "sg:postcode":"34982",
    "sg:province":"FL",
    "sg:tags":[
        "shop",
        "photographer"
    ],
    "wof:name":"Photography By Karen Parker",
    "wof:placetype":"venue"
},
  "geometry": {"coordinates":[-80.343013,27.416614],"type":"Point"}
}