{
  "type": "Feature",
  "properties": {
    "addr:full":"5100 N 9th Ave Pensacola FL 32504",
    "addr:housenumber":"5100",
    "addr:postcode":"32504",
    "addr:street":"N 9Th Ave",
    "iso:country":"US",
    "sg:address":"5100 N 9th Ave",
    "sg:city":"Pensacola",
    "sg:classifiers":[
        {
            "category":"Shopping",
            "subcategory":"Clothing, Apparel, & Fashions",
            "type":"Retail Goods"
        }
    ],
    "sg:phone":"+1 850 476 3228",
    "sg:postcode":"32504",
    "sg:province":"FL",
    "sg:tags":[
        "uniform"
    ],
    "wof:name":"Life Uniform Co",
    "wof:placetype":"venue"
},
  "geometry": {"coordinates":[-87.210933,30.475572],"type":"Point"}
}