{
  "type": "Feature",
  "properties": {
    "addr:full":"1065 Island Ave Tarpon Springs FL 34689",
    "addr:housenumber":"1065",
    "addr:postcode":"34689",
    "addr:street":"Island Ave",
    "iso:country":"US",
    "sg:address":"1065 Island Ave",
    "sg:city":"Tarpon Springs",
    "sg:classifiers":[
        {
            "category":"Manufacturing",
            "subcategory":"Watercraft",
            "type":"Manufacturing & Wholesale Goods"
        }
    ],
    "sg:phone":"+1 727 934 6055",
    "sg:postcode":"34689",
    "sg:province":"FL",
    "sg:tags":[
        "boat"
    ],
    "wof:name":"Corinthian Catamarans",
    "wof:placetype":"venue"
},
  "geometry": {"coordinates":[-82.760046,28.159457],"type":"Point"}
}