{
  "type": "Feature",
  "properties": {
    "addr:full":"3805 Gulf Breeze Pkwy Gulf Breeze FL 32563",
    "addr:housenumber":"3805",
    "addr:postcode":"32563",
    "addr:street":"Gulf Breeze Pkwy",
    "iso:country":"US",
    "sg:address":"3805 Gulf Breeze Pkwy",
    "sg:city":"Gulf Breeze",
    "sg:classifiers":[
        {
            "category":"Restaurant",
            "type":"Food & Drink"
        }
    ],
    "sg:menulink":"http://www.allmenus.com/fl/gulf-breeze-harold/103522-ruby-tuesdays/menu/",
    "sg:phone":"+1 850 916 6565",
    "sg:postcode":"32563",
    "sg:province":"FL",
    "sg:tags":[
        "burger",
        "american"
    ],
    "wof:name":"Ruby Tuesdays",
    "wof:placetype":"venue"
},
  "geometry": {"coordinates":[-87.06349299999999,30.390241],"type":"Point"}
}