{
  "type": "Feature",
  "properties": {
    "addr:full":"9344 Spring Hill Dr Spring Hill FL 34608",
    "addr:housenumber":"9344",
    "addr:postcode":"34608",
    "addr:street":"Spring Hill Dr",
    "iso:country":"US",
    "sg:address":"9344 Spring Hill Dr",
    "sg:city":"Spring Hill",
    "sg:classifiers":[
        {
            "category":"Social Services",
            "subcategory":"Child Care",
            "type":"Services"
        }
    ],
    "sg:phone":"+1 352 683 3207",
    "sg:postcode":"34608",
    "sg:province":"FL",
    "wof:name":"Tomorrow's Hope Preschool",
    "wof:placetype":"venue"
},
  "geometry": {"coordinates":[-82.56451800000001,28.454945],"type":"Point"}
}