{
  "type": "Feature",
  "properties": {
    "addr:full":"4125 Townsend St Starke FL 32091",
    "addr:housenumber":"4125",
    "addr:postcode":"32091",
    "addr:street":"Townsend St",
    "iso:country":"US",
    "sg:address":"4125 Townsend St",
    "sg:city":"Starke",
    "sg:classifiers":[
        {
            "category":"Professional",
            "subcategory":"Detective & Security Services",
            "type":"Services"
        }
    ],
    "sg:phone":"+1 904 533 9344",
    "sg:postcode":"32091",
    "sg:province":"FL",
    "sg:tags":[
        "information",
        "bureau"
    ],
    "wof:name":"Clearlake Services",
    "wof:placetype":"venue"
},
  "geometry": {"coordinates":[-82.011984,29.97583],"type":"Point"}
}