{
  "type": "Feature",
  "properties": {
    "addr:full":"1150 Johnson St Hollywood FL 33019",
    "addr:housenumber":"1150",
    "addr:postcode":"33019",
    "addr:street":"Johnson St",
    "iso:country":"US",
    "sg:address":"1150 Johnson St",
    "sg:city":"Hollywood",
    "sg:classifiers":[
        {
            "category":"Health Services",
            "subcategory":"Doctor",
            "type":"Services"
        }
    ],
    "sg:phone":"+1 954 986 2234",
    "sg:postcode":"33019",
    "sg:province":"FL",
    "sg:tags":[
        "medical"
    ],
    "wof:name":"Lynn A Meister MD",
    "wof:placetype":"venue"
},
  "geometry": {"coordinates":[-80.130458,26.019172],"type":"Point"}
}