{
  "type": "Feature",
  "properties": {
    "iso:country":"US",
    "sg:address":"660 SW 2nd St Apt 3",
    "sg:city":"Miami",
    "sg:classifiers":[
        {
            "category":"Building & Trades",
            "subcategory":"Construction",
            "type":"Services"
        }
    ],
    "sg:phone":"+1 786 226 2392",
    "sg:postcode":"33130",
    "sg:province":"FL",
    "sg:tags":[
        "wallcoverings-installation",
        "wallpaper",
        "painting",
        "contractor"
    ],
    "wof:name":"Ariel Professional Painter",
    "wof:placetype":"venue"
},
  "geometry": {"coordinates":[-80.205326,25.771841],"type":"Point"}
}