{
  "type": "Feature",
  "properties": {
    "addr:full":"436 NW 7th St Homestead FL 33030",
    "addr:housenumber":"436",
    "addr:postcode":"33030",
    "addr:street":"Nw 7Th St",
    "iso:country":"US",
    "sg:address":"436 NW 7th St",
    "sg:city":"Homestead",
    "sg:classifiers":[
        {
            "category":"Professional",
            "subcategory":"Detective & Security Services",
            "type":"Services"
        }
    ],
    "sg:phone":"+1 305 247 6671",
    "sg:postcode":"33030",
    "sg:province":"FL",
    "sg:tags":[
        "information",
        "bureau"
    ],
    "wof:name":"W Colon Quality Property Service Inc",
    "wof:placetype":"venue"
},
  "geometry": {"coordinates":[-80.48394399999999,25.476191],"type":"Point"}
}