{
  "type": "Feature",
  "properties": {
    "iso:country":"US",
    "sg:address":"28 Silver Fox Trl",
    "sg:city":"Ormond Beach",
    "sg:classifiers":[
        {
            "category":"Professional",
            "subcategory":"Employment Agencies",
            "type":"Services"
        }
    ],
    "sg:phone":"+1 386 677 6866",
    "sg:postcode":"32174",
    "sg:province":"FL",
    "wof:name":"Ceo Affiliates Inc",
    "wof:placetype":"venue"
},
  "geometry": {"coordinates":[-81.07707000000001,29.269613],"type":"Point"}
}