{
  "type": "Feature",
  "properties": {
    "addr:full":"930 Malabar Rd SE Palm Bay FL 32907",
    "addr:housenumber":"930",
    "addr:postcode":"32907",
    "addr:street":"Malabar Rd Se",
    "iso:country":"US",
    "sg:address":"930 Malabar Rd SE",
    "sg:city":"Palm Bay",
    "sg:classifiers":[
        {
            "category":"Real Estate",
            "subcategory":"Real Estate Agent",
            "type":"Services"
        }
    ],
    "sg:phone":"+1 321 724 2515",
    "sg:postcode":"32907",
    "sg:province":"FL",
    "wof:name":"Paramount Homes & Dev Corp",
    "wof:placetype":"venue"
},
  "geometry": {"coordinates":[-80.64610399999999,27.998703],"type":"Point"}
}