{
  "type": "Feature",
  "properties": {
    "iso:country":"US",
    "sg:address":"6878 San Casa Dr",
    "sg:city":"Englewood",
    "sg:classifiers":[
        {
            "category":"Government",
            "subcategory":"Office",
            "type":"Public Place"
        }
    ],
    "sg:phone":"+1 941 474 7234",
    "sg:postcode":"34224",
    "sg:province":"FL",
    "sg:website":"www.charlottecountyfl.com",
    "wof:name":"Charlotte County Road & Bridge",
    "wof:placetype":"venue"
},
  "geometry": {"coordinates":[-82.31297000000001,26.92275],"type":"Point"}
}