{
  "type": "Feature",
  "properties": {
    "iso:country":"US",
    "sg:address":"2772 Elkcam Blvd",
    "sg:city":"Deltona",
    "sg:classifiers":[
        {
            "category":"Health Services",
            "subcategory":"Doctor",
            "type":"Services"
        }
    ],
    "sg:phone":"+1 386 532 1694",
    "sg:postcode":"32738",
    "sg:province":"FL",
    "sg:tags":[
        "dentist"
    ],
    "wof:name":"Elkcam Dental",
    "wof:placetype":"venue"
},
  "geometry": {"coordinates":[-81.190442,28.926459],"type":"Point"}
}