{
  "type": "Feature",
  "properties": {
    "addr:full":"7000 SW 97th Ave Miami FL 33173",
    "addr:housenumber":"7000",
    "addr:postcode":"33173",
    "addr:street":"Sw 97Th Ave",
    "iso:country":"US",
    "sg:address":"7000 SW 97th Ave",
    "sg:city":"Miami",
    "sg:classifiers":[
        {
            "category":"Health Services",
            "subcategory":"Chiropractor",
            "type":"Services"
        }
    ],
    "sg:phone":"+1 305 670 0055",
    "sg:postcode":"33173",
    "sg:province":"FL",
    "wof:name":"May Howard A Dr",
    "wof:placetype":"venue"
},
  "geometry": {"coordinates":[-80.350223,25.703361],"type":"Point"}
}