{
  "type": "Feature",
  "properties": {
    "iso:country":"US",
    "sg:address":"10015 NE 81 St",
    "sg:city":"Gainesville",
    "sg:classifiers":[
        {
            "category":"Building & Trades",
            "subcategory":"Construction",
            "type":"Services"
        }
    ],
    "sg:phone":"+1 352 373 0847",
    "sg:postcode":"32609",
    "sg:province":"FL",
    "sg:tags":[
        "contractor"
    ],
    "wof:name":"Cornish Tile",
    "wof:placetype":"venue"
},
  "geometry": {"coordinates":[-82.23571699999999,29.753061],"type":"Point"}
}