{
  "type": "Feature",
  "properties": {
    "addr:full":"5771 Country Lakes Dr Fort Myers FL 33905",
    "addr:housenumber":"5771",
    "addr:postcode":"33905",
    "addr:street":"Country Lakes Dr",
    "iso:country":"US",
    "sg:address":"5771 Country Lakes Dr",
    "sg:city":"Fort Myers",
    "sg:classifiers":[
        {
            "category":"Retail",
            "subcategory":"Repair Shop",
            "type":"Services"
        }
    ],
    "sg:phone":"+1 239 693 5226",
    "sg:postcode":"33905",
    "sg:province":"FL",
    "wof:name":"Ellis K Phelps & Co",
    "wof:placetype":"venue"
},
  "geometry": {"coordinates":[-81.792883,26.659389],"type":"Point"}
}