{
  "type": "Feature",
  "properties": {
    "addr:full":"1993 Jenny Ct Apopka FL 32703",
    "addr:housenumber":"1993",
    "addr:postcode":"32703",
    "addr:street":"Jenny Ct",
    "iso:country":"US",
    "sg:address":"1993 Jenny Ct",
    "sg:city":"Apopka",
    "sg:classifiers":[
        {
            "category":"Retail",
            "subcategory":"Laundry & Dry Cleaning",
            "type":"Services"
        }
    ],
    "sg:phone":"+1 407 884 8946",
    "sg:postcode":"32703",
    "sg:province":"FL",
    "wof:name":"G & B Carpet Care Service Inc",
    "wof:placetype":"venue"
},
  "geometry": {"coordinates":[-81.47322,28.651104],"type":"Point"}
}