{
  "type": "Feature",
  "properties": {
    "iso:country":"US",
    "sg:address":"215 Joshua Pl",
    "sg:city":"Merritt Island",
    "sg:classifiers":[
        {
            "category":"Professional",
            "subcategory":"Advertising",
            "type":"Services"
        }
    ],
    "sg:phone":"+1 321 454 3931",
    "sg:postcode":"32953",
    "sg:province":"FL",
    "sg:website":"www.giftassistantsusa.com",
    "wof:name":"Gift Assistants USA",
    "wof:placetype":"venue"
},
  "geometry": {"coordinates":[-80.712136,28.438983],"type":"Point"}
}