{
  "type": "Feature",
  "properties": {
    "iso:country":"US",
    "sg:address":"6646 Cortez Rd W",
    "sg:city":"Bradenton",
    "sg:classifiers":[
        {
            "category":"Personal",
            "subcategory":"Beauty Salon",
            "type":"Services"
        }
    ],
    "sg:phone":"+1 941 795 6811",
    "sg:postcode":"34210",
    "sg:province":"FL",
    "sg:tags":[
        "shop"
    ],
    "sg:website":"www.myvillagehair.com",
    "wof:name":"Village Hair Studio",
    "wof:placetype":"venue"
},
  "geometry": {"coordinates":[-82.62745700000001,27.462548],"type":"Point"}
}