{
  "type": "Feature",
  "properties": {
    "iso:country":"US",
    "sg:address":"4560 Harbour North Ct",
    "sg:city":"Jacksonville",
    "sg:classifiers":[
        {
            "category":"Professional",
            "subcategory":"Secretarial Services",
            "type":"Services"
        }
    ],
    "sg:phone":"+1 904 642 4464",
    "sg:postcode":"32225",
    "sg:province":"FL",
    "sg:tags":[
        "reporting"
    ],
    "wof:name":"Caption & Real Time Reporting",
    "wof:placetype":"venue"
},
  "geometry": {"coordinates":[-81.51975299999999,30.380853],"type":"Point"}
}