{
  "type": "Feature",
  "properties": {
    "iso:country":"US",
    "sg:address":"132 Faun Rd",
    "sg:city":"St Augustine",
    "sg:classifiers":[
        {
            "category":"Banks & Credit Unions",
            "subcategory":"Bank",
            "type":"Services"
        }
    ],
    "sg:phone":"+1 904 794 4114",
    "sg:postcode":"32086",
    "sg:province":"FL",
    "sg:tags":[
        "financing"
    ],
    "wof:name":"Anastasia Financial Svc",
    "wof:placetype":"venue"
},
  "geometry": {"coordinates":[-81.308139,29.837069],"type":"Point"}
}