{
  "type": "Feature",
  "properties": {
    "iso:country":"US",
    "sg:address":"155 NE 158th St",
    "sg:city":"Miami",
    "sg:classifiers":[
        {
            "category":"Utilities",
            "subcategory":"Refuse",
            "type":"Services"
        }
    ],
    "sg:phone":"+1 305 948 0156",
    "sg:postcode":"33162",
    "sg:province":"FL",
    "sg:tags":[
        "piling"
    ],
    "wof:name":"L B Foster Company",
    "wof:placetype":"venue"
},
  "geometry": {"coordinates":[-80.196843,25.919984],"type":"Point"}
}