{
  "type": "Feature",
  "properties": {
    "iso:country":"US",
    "sg:address":"5200 Belfort Rd",
    "sg:city":"Jacksonville",
    "sg:classifiers":[
        {
            "category":"Professional",
            "subcategory":"Management & Consulting",
            "type":"Services"
        }
    ],
    "sg:phone":"+1 904 363 2535",
    "sg:postcode":"32256",
    "sg:province":"FL",
    "sg:tags":[
        "consultant",
        "resource",
        "human"
    ],
    "wof:name":"Drake Beam Morin Inc",
    "wof:placetype":"venue"
},
  "geometry": {"coordinates":[-81.58363300000001,30.242983],"type":"Point"}
}