{
  "type": "Feature",
  "properties": {
    "addr:full":"14721 Lake Olive Dr Fort Myers FL 33919",
    "addr:housenumber":"14721",
    "addr:postcode":"33919",
    "addr:street":"Lake Olive Dr",
    "iso:country":"US",
    "sg:address":"14721 Lake Olive Dr",
    "sg:city":"Fort Myers",
    "sg:classifiers":[
        {
            "category":"Building & Trades",
            "subcategory":"Construction",
            "type":"Services"
        }
    ],
    "sg:phone":"+1 239 481 8999",
    "sg:postcode":"33919",
    "sg:province":"FL",
    "sg:tags":[
        "carpentry",
        "contractor"
    ],
    "wof:name":"Irvcon Co",
    "wof:placetype":"venue"
},
  "geometry": {"coordinates":[-81.904464,26.52992],"type":"Point"}
}