{
  "type": "Feature",
  "properties": {
    "addr:full":"7114 N University Dr Tamarac FL 33321",
    "addr:housenumber":"7114",
    "addr:postcode":"33321",
    "addr:street":"N University Dr",
    "iso:country":"US",
    "sg:address":"7114 N University Dr",
    "sg:city":"Tamarac",
    "sg:classifiers":[
        {
            "category":"Retail",
            "subcategory":"Laundry & Dry Cleaning",
            "type":"Services"
        }
    ],
    "sg:phone":"+1 954 718 8822",
    "sg:postcode":"33321",
    "sg:province":"FL",
    "sg:tags":[
        "cleaners"
    ],
    "wof:name":"A Dry Cleaning",
    "wof:placetype":"venue"
},
  "geometry": {"coordinates":[-80.25227099999999,26.21098],"type":"Point"}
}