{
  "type": "Feature",
  "properties": {
    "iso:country":"US",
    "sg:address":"11420 NW 22nd St",
    "sg:city":"Hollywood",
    "sg:classifiers":[
        {
            "category":"Manufacturing",
            "subcategory":"Metals",
            "type":"Manufacturing & Wholesale Goods"
        }
    ],
    "sg:phone":"+1 954 704 3696",
    "sg:postcode":"33026",
    "sg:province":"FL",
    "sg:tags":[
        "mfg"
    ],
    "wof:name":"Rojo Moulding Corp",
    "wof:placetype":"venue"
},
  "geometry": {"coordinates":[-80.302403,26.027258],"type":"Point"}
}