{
  "type": "Feature",
  "properties": {
    "addr:full":"895 Buffalo Rd Titusville FL 32796",
    "addr:housenumber":"895",
    "addr:postcode":"32796",
    "addr:street":"Buffalo Rd",
    "iso:country":"US",
    "sg:address":"895 Buffalo Rd",
    "sg:city":"Titusville",
    "sg:classifiers":[
        {
            "category":"Manufacturing",
            "subcategory":"Metals",
            "type":"Manufacturing & Wholesale Goods"
        },
        {
            "category":"Manufacturing",
            "subcategory":"Building Materials",
            "type":"Manufacturing & Wholesale Goods"
        }
    ],
    "sg:phone":"+1 321 383 7798",
    "sg:postcode":"32796",
    "sg:province":"FL",
    "sg:tags":[
        "fabricator",
        "work",
        "sheet"
    ],
    "wof:name":"Synergy Metal Finishing",
    "wof:placetype":"venue"
},
  "geometry": {"coordinates":[-80.82458800000001,28.62468],"type":"Point"}
}