{
  "type": "Feature",
  "properties": {
    "iso:country":"US",
    "sg:address":"111 Briny Ave",
    "sg:city":"Pompano Beach",
    "sg:classifiers":[
        {
            "category":"Manufacturing",
            "subcategory":"Aerospace",
            "type":"Manufacturing & Wholesale Goods"
        }
    ],
    "sg:phone":"+1 954 781 0130",
    "sg:postcode":"33062",
    "sg:province":"FL",
    "sg:tags":[
        "aircraft",
        "mfg"
    ],
    "wof:name":"Jet Fighters International",
    "wof:placetype":"venue"
},
  "geometry": {"coordinates":[-80.090012,26.231187],"type":"Point"}
}