{
  "type": "Feature",
  "properties": {
    "iso:country":"US",
    "sg:address":"10087 Green Fountain Rd",
    "sg:city":"Tallahassee",
    "sg:classifiers":[
        {
            "category":"Taxi",
            "type":"Transportation"
        }
    ],
    "sg:phone":"+1 850 727 4327",
    "sg:postcode":"32305",
    "sg:province":"FL",
    "sg:tags":[
        "delivery"
    ],
    "wof:name":"Thomas Delivery Service",
    "wof:placetype":"venue"
},
  "geometry": {"coordinates":[-84.232337,30.300287],"type":"Point"}
}