{
  "type": "Feature",
  "properties": {
    "addr:full":"860 S US Hwy 1 Oak Hill FL 32759",
    "addr:housenumber":"860",
    "addr:postcode":"32759",
    "addr:street":"S Us Hwy 1",
    "iso:country":"US",
    "sg:address":"860 S US Hwy 1",
    "sg:city":"Oak Hill",
    "sg:classifiers":[
        {
            "category":"Farming",
            "subcategory":"Aquatic Farm",
            "type":"Manufacturing & Wholesale Goods"
        }
    ],
    "sg:phone":"+1 386 345 3333",
    "sg:postcode":"32759",
    "sg:province":"FL",
    "sg:tags":[
        "fish"
    ],
    "wof:name":"Mariculture Technologies",
    "wof:placetype":"venue"
},
  "geometry": {"coordinates":[-80.84618,28.829943],"type":"Point"}
}