{
  "type": "Feature",
  "properties": {
    "addr:full":"4411 Sunbeam Rd Jacksonville FL 32257",
    "addr:housenumber":"4411",
    "addr:postcode":"32257",
    "addr:street":"Sunbeam Rd",
    "iso:country":"US",
    "sg:address":"4411 Sunbeam Rd",
    "sg:city":"Jacksonville",
    "sg:classifiers":[
        {
            "category":"Government",
            "subcategory":"Post Office",
            "type":"Public Place"
        }
    ],
    "sg:phone":"+1 904 737 4852",
    "sg:postcode":"32257",
    "sg:province":"FL",
    "sg:tags":[
        "postal",
        "us"
    ],
    "wof:name":"Mandarin Station",
    "wof:placetype":"venue"
},
  "geometry": {"coordinates":[-81.601018,30.205987],"type":"Point"}
}