{
  "type": "Feature",
  "properties": {
    "iso:country":"US",
    "sg:address":"1414 NW 107th Ave",
    "sg:city":"Miami",
    "sg:classifiers":[
        {
            "category":"Health Services",
            "subcategory":"Clinic",
            "type":"Services"
        }
    ],
    "sg:phone":"+1 305 463 5355",
    "sg:postcode":"33172",
    "sg:province":"FL",
    "sg:tags":[
        "home",
        "care"
    ],
    "wof:name":"A R C Professional Services",
    "wof:placetype":"venue"
},
  "geometry": {"coordinates":[-80.368842,25.786796],"type":"Point"}
}