{
  "type": "Feature",
  "properties": {
    "addr:full":"1969 Coquina Way Coral Springs FL 33071",
    "addr:housenumber":"1969",
    "addr:postcode":"33071",
    "addr:street":"Coquina Way",
    "iso:country":"US",
    "sg:address":"1969 Coquina Way",
    "sg:city":"Coral Springs",
    "sg:classifiers":[
        {
            "category":"Manufacturing",
            "subcategory":"Electronics",
            "type":"Manufacturing & Wholesale Goods"
        }
    ],
    "sg:phone":"+1 954 340 2777",
    "sg:postcode":"33071",
    "sg:province":"FL",
    "sg:tags":[
        "fire",
        "alarm",
        "system"
    ],
    "wof:name":"World Electronics Inc",
    "wof:placetype":"venue"
},
  "geometry": {"coordinates":[-80.248482,26.25402],"type":"Point"}
}