{
  "type": "Feature",
  "properties": {
    "iso:country":"US",
    "sg:address":"570 Finsbay Ct",
    "sg:city":"Ocoee",
    "sg:classifiers":[
        {
            "category":"Building & Trades",
            "subcategory":"Construction",
            "type":"Services"
        }
    ],
    "sg:phone":"+1 321 242 4335",
    "sg:postcode":"34761",
    "sg:province":"FL",
    "sg:tags":[
        "house"
    ],
    "wof:name":"Kasimira Construction Corp",
    "wof:placetype":"venue"
},
  "geometry": {"coordinates":[-81.55234,28.530317],"type":"Point"}
}