{
  "type": "Feature",
  "properties": {
    "iso:country":"US",
    "sg:address":"3517 NW 10th Ave",
    "sg:city":"Fort Lauderdale",
    "sg:classifiers":[
        {
            "category":"Autos & Motor Vehicles",
            "subcategory":"Automobile Sales",
            "type":"Retail Goods"
        },
        {
            "category":"Wholesale",
            "subcategory":"Motor Vehicles",
            "type":"Manufacturing & Wholesale Goods"
        }
    ],
    "sg:phone":"+1 954 566 9818",
    "sg:postcode":"33309",
    "sg:province":"FL",
    "sg:tags":[
        "car",
        "dealer"
    ],
    "wof:name":"Da Ley Sales Inc",
    "wof:placetype":"venue"
},
  "geometry": {"coordinates":[-80.15626399999999,26.170442],"type":"Point"}
}