{
  "type": "Feature",
  "properties": {
    "iso:country":"US",
    "sg:address":"1555 NE 121 St Ste 202",
    "sg:city":"Miami",
    "sg:classifiers":[
        {
            "category":"Shopping",
            "subcategory":"Clothing, Apparel, & Fashions",
            "type":"Retail Goods"
        }
    ],
    "sg:phone":"+1 305 392 0473",
    "sg:postcode":"33161",
    "sg:province":"FL",
    "sg:tags":[
        "men's",
        "clothing",
        "women's"
    ],
    "wof:name":"Geoff Alain",
    "wof:placetype":"venue"
},
  "geometry": {"coordinates":[-80.16757,25.887971],"type":"Point"}
}