{
  "type": "Feature",
  "properties": {
    "addr:full":"4501 Treehouse Ln Tamarac FL 33319",
    "addr:housenumber":"4501",
    "addr:postcode":"33319",
    "addr:street":"Treehouse Ln",
    "iso:country":"US",
    "sg:address":"4501 Treehouse Ln",
    "sg:city":"Tamarac",
    "sg:classifiers":[
        {
            "category":"Real Estate",
            "subcategory":"Real Estate Operator",
            "type":"Services"
        }
    ],
    "sg:phone":"+1 954 739 3585",
    "sg:postcode":"33319",
    "sg:province":"FL",
    "sg:tags":[
        "apartment"
    ],
    "wof:name":"Seven Winds",
    "wof:placetype":"venue"
},
  "geometry": {"coordinates":[-80.20756900000001,26.191042],"type":"Point"}
}