{
  "type": "Feature",
  "properties": {
    "iso:country":"US",
    "sg:address":"1618 Tropic St",
    "sg:city":"Titusville",
    "sg:classifiers":[
        {
            "category":"Home & Garden",
            "subcategory":"Building Materials",
            "type":"Retail Goods"
        }
    ],
    "sg:phone":"+1 321 223 3483",
    "sg:postcode":"32796",
    "sg:province":"FL",
    "sg:tags":[
        "door"
    ],
    "wof:name":"Christopher Kreisker Garage",
    "wof:placetype":"venue"
},
  "geometry": {"coordinates":[-80.821524,28.611736],"type":"Point"}
}