{
  "type": "Feature",
  "properties": {
    "addr:full":"1900 N Flamingo Rd Pembroke Pines FL 33028",
    "addr:housenumber":"1900",
    "addr:postcode":"33028",
    "addr:street":"N Flamingo Rd",
    "iso:country":"US",
    "sg:address":"1900 N Flamingo Rd",
    "sg:city":"Pembroke Pines",
    "sg:classifiers":[
        {
            "category":"Health Services",
            "subcategory":"Chiropractor",
            "type":"Services"
        }
    ],
    "sg:phone":"+1 954 437 6660",
    "sg:postcode":"33028",
    "sg:province":"FL",
    "wof:name":"Chiropractic Fitness & Injury",
    "wof:placetype":"venue"
},
  "geometry": {"coordinates":[-80.312541,26.02434],"type":"Point"}
}