{
  "type": "Feature",
  "properties": {
    "iso:country":"US",
    "sg:address":"1129 W Arch St",
    "sg:city":"Tampa",
    "sg:classifiers":[
        {
            "category":"Building & Trades",
            "subcategory":"Landscaping Services",
            "type":"Services"
        },
        {
            "category":"Professional",
            "subcategory":"Art Services",
            "type":"Services"
        },
        {
            "category":"Building & Trades",
            "subcategory":"Construction",
            "type":"Services"
        },
        {
            "category":"Manufacturing",
            "subcategory":"Building Materials",
            "type":"Manufacturing & Wholesale Goods"
        }
    ],
    "sg:phone":"+1 813 731 2792",
    "sg:postcode":"33607",
    "sg:province":"FL",
    "sg:tags":[
        "ponds",
        "designer",
        "garden",
        "deck",
        "consultant",
        "builder",
        "lake",
        "water",
        "lighting",
        "patio",
        "landscape"
    ],
    "sg:website":"http://www.exteriorconceptsonline.com",
    "wof:name":"Exterior Concepts",
    "wof:placetype":"venue"
},
  "geometry": {"coordinates":[-82.47076199999999,27.954148],"type":"Point"}
}