{
  "type": "Feature",
  "properties": {
    "iso:country":"US",
    "sg:address":"16301 Mckinley Rd",
    "sg:city":"Umatilla",
    "sg:classifiers":[
        {
            "category":"Retail",
            "subcategory":"Storage",
            "type":"Services"
        }
    ],
    "sg:phone":"+1 352 483 0400",
    "sg:postcode":"32784",
    "sg:province":"FL",
    "sg:tags":[
        "self",
        "commercial",
        "household"
    ],
    "wof:name":"Storage Depot, The",
    "wof:placetype":"venue"
},
  "geometry": {"coordinates":[-81.685031,28.887225],"type":"Point"}
}