{
  "type": "Feature",
  "properties": {
    "addr:full":"4114 Northlake Blvd Palm Beach Gdns FL 33410",
    "addr:housenumber":"4114",
    "addr:postcode":"33410",
    "addr:street":"Northlake Blvd Palm Beach Gdns",
    "iso:country":"US",
    "sg:address":"4114 Northlake Blvd",
    "sg:city":"Palm Beach Gdns",
    "sg:classifiers":[
        {
            "category":"Banks & Credit Unions",
            "subcategory":"Bank",
            "type":"Services"
        }
    ],
    "sg:phone":"+1 561 627 8565",
    "sg:postcode":"33410",
    "sg:province":"FL",
    "sg:tags":[
        "company",
        "trust"
    ],
    "wof:name":"Sunst Trust Number One",
    "wof:placetype":"venue"
},
  "geometry": {"coordinates":[-80.10078,26.808763],"type":"Point"}
}