{
  "type": "Feature",
  "properties": {
    "addr:full":"5455 N 59th St Tampa FL 33610",
    "addr:housenumber":"5455",
    "addr:postcode":"33610",
    "addr:street":"N 59Th St",
    "iso:country":"US",
    "sg:address":"5455 N 59th St",
    "sg:city":"Tampa",
    "sg:classifiers":[
        {
            "category":"Manufacturing",
            "subcategory":"Glass & Minerals",
            "type":"Manufacturing & Wholesale Goods"
        }
    ],
    "sg:phone":"+1 813 621 2427",
    "sg:postcode":"33610",
    "sg:province":"FL",
    "sg:tags":[
        "product",
        "mfg",
        "hydraulic",
        "chemical",
        "concrete",
        "cement"
    ],
    "wof:name":"W R Bonsal Plant 44",
    "wof:placetype":"venue"
},
  "geometry": {"coordinates":[-82.3896,27.999665],"type":"Point"}
}