{
  "type": "Feature",
  "properties": {
    "addr:full":"4396 Seventh Isle Dr Hernando Beach FL 34607",
    "addr:housenumber":"4396",
    "addr:postcode":"34607",
    "addr:street":"Seventh Isle Dr;Beach",
    "iso:country":"US",
    "sg:address":"4396 Seventh Isle Dr",
    "sg:city":"Hernando Beach",
    "sg:classifiers":[
        {
            "category":"Home & Garden",
            "subcategory":"Carpets & Floor Coverings",
            "type":"Retail Goods"
        }
    ],
    "sg:phone":"+1 727 845 9005",
    "sg:postcode":"34607",
    "sg:province":"FL",
    "sg:tags":[
        "dealer",
        "rug"
    ],
    "wof:name":"James Rich Oriental Rugs",
    "wof:placetype":"venue"
},
  "geometry": {"coordinates":[-82.660893,28.49563],"type":"Point"}
}