{
  "type": "Feature",
  "properties": {
    "addr:full":"5640 39th St Vero Beach FL 32966",
    "addr:housenumber":"5640",
    "addr:postcode":"32966",
    "addr:street":"39Th St",
    "iso:country":"US",
    "sg:address":"5640 39th St",
    "sg:city":"Vero Beach",
    "sg:classifiers":[
        {
            "category":"Personal",
            "subcategory":"Beauty Salon",
            "type":"Services"
        }
    ],
    "sg:phone":"+1 772 562 2917",
    "sg:postcode":"32966",
    "sg:province":"FL",
    "sg:tags":[
        "cosmetologist"
    ],
    "wof:name":"Mary Kay Cosmetics",
    "wof:placetype":"venue"
},
  "geometry": {"coordinates":[-80.443022,27.662888],"type":"Point"}
}