{
  "type": "Feature",
  "properties": {
    "addr:full":"11648 Pine Acres Rd Jacksonville FL 32223",
    "addr:housenumber":"11648",
    "addr:postcode":"32223",
    "addr:street":"Pine Acres Rd",
    "iso:country":"US",
    "sg:address":"11648 Pine Acres Rd",
    "sg:city":"Jacksonville",
    "sg:classifiers":[
        {
            "category":"Real Estate",
            "subcategory":"Real Estate Operator",
            "type":"Services"
        }
    ],
    "sg:phone":"+1 904 268 7251",
    "sg:postcode":"32223",
    "sg:province":"FL",
    "sg:tags":[
        "apartment",
        "complex"
    ],
    "wof:name":"Mandarin Villas Ltd",
    "wof:placetype":"venue"
},
  "geometry": {"coordinates":[-81.611496,30.159204],"type":"Point"}
}