{
  "type": "Feature",
  "properties": {
    "addr:full":"2901 66th St N St Petersburg FL 33710",
    "addr:housenumber":"2901",
    "addr:postcode":"33710",
    "addr:street":"66Th St N",
    "iso:country":"US",
    "sg:address":"2901 66th St N",
    "sg:city":"St Petersburg",
    "sg:classifiers":[
        {
            "category":"Restaurant",
            "type":"Food & Drink"
        }
    ],
    "sg:phone":"+1 727 345 0559",
    "sg:postcode":"33710",
    "sg:province":"FL",
    "wof:name":"Ming Garden",
    "wof:placetype":"venue"
},
  "geometry": {"coordinates":[-82.728414,27.796311],"type":"Point"}
}