{
  "type": "Feature",
  "properties": {
    "iso:country":"US",
    "sg:address":"27222 Dayflower Blvd",
    "sg:city":"Zephyrhills",
    "sg:classifiers":[
        {
            "category":"Building & Trades",
            "subcategory":"Landscaping Services",
            "type":"Services"
        }
    ],
    "sg:phone":"+1 813 994 6653",
    "sg:postcode":"33544",
    "sg:province":"FL",
    "wof:name":"M & H Lawn Care",
    "wof:placetype":"venue"
},
  "geometry": {"coordinates":[-82.366209,28.242911],"type":"Point"}
}