{
  "type": "Feature",
  "properties": {
    "addr:full":"1018 Grand Prix Dr Sebring FL 33872",
    "addr:housenumber":"1018",
    "addr:postcode":"33872",
    "addr:street":"Grand Prix Dr",
    "iso:country":"US",
    "sg:address":"1018 Grand Prix Dr",
    "sg:city":"Sebring",
    "sg:classifiers":[
        {
            "category":"Real Estate",
            "subcategory":"Real Estate Services",
            "type":"Services"
        },
        {
            "category":"Banks & Credit Unions",
            "subcategory":"Financial Services",
            "type":"Services"
        }
    ],
    "sg:phone":"+1 863 381 4558",
    "sg:postcode":"33872",
    "sg:province":"FL",
    "sg:tags":[
        "loan",
        "processing"
    ],
    "wof:name":"Aapex Mortgage Co.",
    "wof:placetype":"venue"
},
  "geometry": {"coordinates":[-81.504014,27.507916],"type":"Point"}
}