{
  "type": "Feature",
  "properties": {
    "addr:full":"3205 Royal Oak Dr Titusville FL 32780",
    "addr:housenumber":"3205",
    "addr:postcode":"32780",
    "addr:street":"Royal Oak Dr",
    "iso:country":"US",
    "sg:address":"3205 Royal Oak Dr",
    "sg:city":"Titusville",
    "sg:classifiers":[
        {
            "category":"Professional",
            "subcategory":"Engineering",
            "type":"Services"
        }
    ],
    "sg:phone":"+1 321 385 9991",
    "sg:postcode":"32780",
    "sg:province":"FL",
    "sg:tags":[
        "engineer"
    ],
    "wof:name":"Titusville Industries Inc",
    "wof:placetype":"venue"
},
  "geometry": {"coordinates":[-80.830224,28.5776],"type":"Point"}
}