{
  "type": "Feature",
  "properties": {
    "iso:country":"US",
    "sg:address":"5065 Soutel Dr",
    "sg:city":"Jacksonville",
    "sg:classifiers":[
        {
            "category":"Retail",
            "subcategory":"Funeral Services",
            "type":"Services"
        }
    ],
    "sg:phone":"+1 904 924 9340",
    "sg:postcode":"32208",
    "sg:province":"FL",
    "sg:tags":[
        "director",
        "plans-pre-arranged"
    ],
    "wof:name":"Brown Green Fralin Funeral Directors Inc",
    "wof:placetype":"venue"
},
  "geometry": {"coordinates":[-81.725722,30.39761],"type":"Point"}
}