{
  "type": "Feature",
  "properties": {
    "iso:country":"US",
    "sg:address":"2810 E Bearss Ave",
    "sg:city":"Tampa",
    "sg:classifiers":[
        {
            "category":"Bars & Pubs",
            "type":"Food & Drink"
        }
    ],
    "sg:phone":"+1 813 971 0660",
    "sg:postcode":"33613",
    "sg:province":"FL",
    "wof:name":"Skid's Pub",
    "wof:placetype":"venue"
},
  "geometry": {"coordinates":[-82.42754600000001,28.08048],"type":"Point"}
}