{
  "type": "Feature",
  "properties": {
    "iso:country":"US",
    "sg:address":"785 NE Dixie Hwy",
    "sg:city":"Jensen Beach",
    "sg:classifiers":[
        {
            "category":"Professional",
            "subcategory":"Research",
            "type":"Services"
        }
    ],
    "sg:phone":"+1 772 225 6932",
    "sg:postcode":"34957",
    "sg:province":"FL",
    "sg:tags":[
        "development",
        "electronic"
    ],
    "wof:name":"Kopp Development",
    "wof:placetype":"venue"
},
  "geometry": {"coordinates":[-80.242121,27.219682],"type":"Point"}
}