{
  "type": "Feature",
  "properties": {
    "iso:country":"US",
    "sg:address":"1560 N University Dr",
    "sg:city":"Pembroke Pines",
    "sg:classifiers":[
        {
            "category":"Utilities",
            "subcategory":"Mobile Phone",
            "type":"Services"
        }
    ],
    "sg:phone":"+1 954 437 5144",
    "sg:postcode":"33024",
    "sg:province":"FL",
    "sg:tags":[
        "telephone",
        "cellular"
    ],
    "wof:name":"ATC Wireless Svc",
    "wof:placetype":"venue"
},
  "geometry": {"coordinates":[-80.24862899999999,26.023011],"type":"Point"}
}