{
  "type": "Feature",
  "properties": {
    "iso:country":"US",
    "sg:address":"5224 Bank St",
    "sg:city":"Fort Myers",
    "sg:classifiers":[
        {
            "category":"Banks & Credit Unions",
            "subcategory":"Financial Services",
            "type":"Services"
        }
    ],
    "sg:phone":"+1 239 694 0000",
    "sg:postcode":"33907",
    "sg:province":"FL",
    "sg:tags":[
        "broker",
        "mortgage"
    ],
    "wof:name":"Bank Street Mortgage",
    "wof:placetype":"venue"
},
  "geometry": {"coordinates":[-81.872299,26.5839],"type":"Point"}
}