{
  "type": "Feature",
  "properties": {
    "iso:country":"US",
    "sg:address":"75 SW 1 Ave",
    "sg:city":"High Springs",
    "sg:classifiers":[
        {
            "category":"Shopping",
            "subcategory":"Used Merchandise",
            "type":"Retail Goods"
        }
    ],
    "sg:phone":"+1 386 454 3729",
    "sg:postcode":"32643",
    "sg:province":"FL",
    "wof:name":"A Step In Past",
    "wof:placetype":"venue"
},
  "geometry": {"coordinates":[-82.599276,29.825689],"type":"Point"}
}