{
  "type": "Feature",
  "properties": {
    "iso:country":"US",
    "sg:address":"2414 NE Waldo Rd",
    "sg:city":"Gainesville",
    "sg:classifiers":[
        {
            "category":"Building & Trades",
            "subcategory":"Electrical",
            "type":"Services"
        }
    ],
    "sg:phone":"+1 352 376 7861",
    "sg:postcode":"32609",
    "sg:province":"FL",
    "sg:tags":[
        "electrical",
        "contractor"
    ],
    "wof:name":"George Grimm Electric Inc",
    "wof:placetype":"venue"
},
  "geometry": {"coordinates":[-82.29647199999999,29.674394],"type":"Point"}
}