{
  "type": "Feature",
  "properties": {
    "addr:full":"6800 NW Gainesville Rd Ocala FL 34475",
    "addr:housenumber":"6800",
    "addr:postcode":"34475",
    "addr:street":"Nw Gainesville Rd",
    "iso:country":"US",
    "sg:address":"6800 NW Gainesville Rd",
    "sg:city":"Ocala",
    "sg:classifiers":[
        {
            "category":"Real Estate",
            "subcategory":"Real Estate Operator",
            "type":"Services"
        }
    ],
    "sg:phone":"+1 352 867 5610",
    "sg:postcode":"34475",
    "sg:province":"FL",
    "sg:tags":[
        "mobile",
        "home",
        "community"
    ],
    "wof:name":"Our Lucaya Mobile Home Park",
    "wof:placetype":"venue"
},
  "geometry": {"coordinates":[-82.171091,29.254041],"type":"Point"}
}