{
  "type": "Feature",
  "properties": {
    "iso:country":"US",
    "sg:address":"2300 Biscayne Blvd",
    "sg:city":"Miami",
    "sg:classifiers":[
        {
            "category":"Professional",
            "subcategory":"Lawyer & Legal Services",
            "type":"Services"
        }
    ],
    "sg:phone":"+1 305 358 6555",
    "sg:postcode":"33137",
    "sg:province":"FL",
    "sg:tags":[
        "plan"
    ],
    "sg:website":"http://www.kayerose.com",
    "wof:name":"Kaye Rose & Partners",
    "wof:placetype":"venue"
},
  "geometry": {"coordinates":[-80.18911,25.79915],"type":"Point"}
}