{
  "type": "Feature",
  "properties": {
    "addr:full":"3100 SW College Rd Ocala FL 34474",
    "addr:housenumber":"3100",
    "addr:postcode":"34474",
    "addr:street":"Sw College Rd",
    "iso:country":"US",
    "sg:address":"3100 SW College Rd",
    "sg:city":"Ocala",
    "sg:classifiers":[
        {
            "category":"Shopping",
            "subcategory":"Photographic Equipment",
            "type":"Retail Goods"
        }
    ],
    "sg:phone":"+1 352 237 4700",
    "sg:postcode":"34474",
    "sg:province":"FL",
    "sg:tags":[
        "supply"
    ],
    "wof:name":"Ritz Camera Centers Inc",
    "wof:placetype":"venue"
},
  "geometry": {"coordinates":[-82.176284,29.158949],"type":"Point"}
}