{
  "type": "Feature",
  "properties": {
    "addr:full":"517 W Colonial Dr Orlando FL 32804",
    "addr:housenumber":"517",
    "addr:postcode":"32804",
    "addr:street":"W Colonial Dr",
    "iso:country":"US",
    "sg:address":"517 W Colonial Dr",
    "sg:city":"Orlando",
    "sg:classifiers":[
        {
            "category":"Organizations",
            "subcategory":"Professional Association",
            "type":"Services"
        }
    ],
    "sg:phone":"+1 407 420 2928",
    "sg:postcode":"32804",
    "sg:province":"FL",
    "sg:tags":[
        "chambers",
        "commerce"
    ],
    "wof:name":"Colombian American Chamber",
    "wof:placetype":"venue"
},
  "geometry": {"coordinates":[-81.38607399999999,28.552968],"type":"Point"}
}