{
  "type": "Feature",
  "properties": {
    "iso:country":"US",
    "sg:address":"4195 Park Ave",
    "sg:city":"Miami",
    "sg:classifiers":[
        {
            "category":"Building & Trades",
            "subcategory":"Landscaping Services",
            "type":"Services"
        }
    ],
    "sg:phone":"+1 305 666 0930",
    "sg:postcode":"33133",
    "sg:province":"FL",
    "sg:tags":[
        "designer",
        "landscape"
    ],
    "wof:name":"Edward Bilbao Landscape Design",
    "wof:placetype":"venue"
},
  "geometry": {"coordinates":[-80.259631,25.714215],"type":"Point"}
}