{
  "type": "Feature",
  "properties": {
    "addr:full":"441 Ololu Dr Winter Park FL 32789",
    "addr:housenumber":"441",
    "addr:postcode":"32789",
    "addr:street":"Ololu Dr",
    "iso:country":"US",
    "sg:address":"441 Ololu Dr",
    "sg:city":"Winter Park",
    "sg:classifiers":[
        {
            "category":"Professional",
            "subcategory":"Business Services",
            "type":"Services"
        }
    ],
    "sg:phone":"+1 407 647 6606",
    "sg:postcode":"32789",
    "sg:province":"FL",
    "sg:tags":[
        "recording",
        "studio"
    ],
    "wof:name":"Lady Bea Productions Inc",
    "wof:placetype":"venue"
},
  "geometry": {"coordinates":[-81.383776,28.60134],"type":"Point"}
}