{
  "type": "Feature",
  "properties": {
    "iso:country":"US",
    "sg:address":"6822 SW 34th Ct",
    "sg:city":"Hollywood",
    "sg:classifiers":[
        {
            "category":"Professional",
            "subcategory":"Business Services",
            "type":"Services"
        }
    ],
    "sg:phone":"+1 954 987 5969",
    "sg:postcode":"33023",
    "sg:province":"FL",
    "wof:name":"Lizasoain Guzman & Associates",
    "wof:placetype":"venue"
},
  "geometry": {"coordinates":[-80.223375,25.978867],"type":"Point"}
}