{
  "type": "Feature",
  "properties": {
    "addr:full":"9020 Berry Ave Jacksonville FL 32211",
    "addr:housenumber":"9020",
    "addr:postcode":"32211",
    "addr:street":"Berry Ave",
    "iso:country":"US",
    "sg:address":"9020 Berry Ave",
    "sg:city":"Jacksonville",
    "sg:classifiers":[
        {
            "category":"Professional",
            "subcategory":"Business Services",
            "type":"Services"
        }
    ],
    "sg:phone":"+1 904 855 8884",
    "sg:postcode":"32211",
    "sg:province":"FL",
    "sg:tags":[
        "pool",
        "swimming"
    ],
    "wof:name":"Crystal Clean Pool Svc Inc",
    "wof:placetype":"venue"
},
  "geometry": {"coordinates":[-81.561375,30.316183],"type":"Point"}
}