{
  "type": "Feature",
  "properties": {
    "addr:full":"3233 Crystal Ct Miami FL 33133",
    "addr:housenumber":"3233",
    "addr:postcode":"33133",
    "addr:street":"Crystal Ct",
    "iso:country":"US",
    "sg:address":"3233 Crystal Ct",
    "sg:city":"Miami",
    "sg:classifiers":[
        {
            "category":"Autos & Motor Vehicles",
            "subcategory":"Automobile Sales",
            "type":"Retail Goods"
        }
    ],
    "sg:phone":"+1 305 285 0095",
    "sg:postcode":"33133",
    "sg:province":"FL",
    "sg:tags":[
        "car",
        "dealer"
    ],
    "wof:name":"Danag Inc",
    "wof:placetype":"venue"
},
  "geometry": {"coordinates":[-80.223731,25.739176],"type":"Point"}
}