{
  "type": "Feature",
  "properties": {
    "iso:country":"US",
    "sg:address":"1423 Kass Cir",
    "sg:city":"Spring Hill",
    "sg:classifiers":[
        {
            "category":"Social Services",
            "type":"Services"
        }
    ],
    "sg:phone":"+1 352 683 5533",
    "sg:postcode":"34606",
    "sg:province":"FL",
    "sg:tags":[
        "clinic",
        "specialty",
        "outpatient"
    ],
    "wof:name":"Pregnancy & Parenting",
    "wof:placetype":"venue"
},
  "geometry": {"coordinates":[-82.596805,28.452783],"type":"Point"}
}