{
  "type": "Feature",
  "properties": {
    "addr:full":"333 Southern Blvd West Palm Beach FL 33405",
    "addr:housenumber":"333",
    "addr:postcode":"33405",
    "addr:street":"Southern Blvd",
    "iso:country":"US",
    "sg:address":"333 Southern Blvd",
    "sg:city":"West Palm Beach",
    "sg:classifiers":[
        {
            "category":"Freight",
            "type":"Transportation"
        }
    ],
    "sg:phone":"+1 561 832 5665",
    "sg:postcode":"33405",
    "sg:province":"FL",
    "sg:tags":[
        "shipping",
        "agent",
        "arrangement"
    ],
    "wof:name":"Sealines International",
    "wof:placetype":"venue"
},
  "geometry": {"coordinates":[-80.05358200000001,26.67576],"type":"Point"}
}