{
  "type": "Feature",
  "properties": {
    "iso:country":"US",
    "sg:address":"2535 University Blvd W",
    "sg:city":"Jacksonville",
    "sg:classifiers":[
        {
            "category":"Insurance",
            "subcategory":"Insurance Agent",
            "type":"Services"
        }
    ],
    "sg:phone":"+1 904 739 1500",
    "sg:postcode":"32217",
    "sg:province":"FL",
    "wof:name":"State Farm Insurance",
    "wof:placetype":"venue"
},
  "geometry": {"coordinates":[-81.632175,30.260972],"type":"Point"}
}