{
  "type": "Feature",
  "properties": {
    "addr:full":"2440 Palm Ridge Rd Sanibel FL 33957",
    "addr:housenumber":"2440",
    "addr:postcode":"33957",
    "addr:street":"Palm Ridge Rd",
    "iso:country":"US",
    "sg:address":"2440 Palm Ridge Rd",
    "sg:city":"Sanibel",
    "sg:classifiers":[
        {
            "category":"Restaurant",
            "type":"Food & Drink"
        }
    ],
    "sg:phone":"+1 239 472 0212",
    "sg:postcode":"33957",
    "sg:province":"FL",
    "sg:tags":[
        "eating"
    ],
    "wof:name":"Mona Lisa Pizzeria & Deli",
    "wof:placetype":"venue"
},
  "geometry": {"coordinates":[-82.07908,26.439718],"type":"Point"}
}