{
  "type": "Feature",
  "properties": {
    "iso:country":"US",
    "sg:address":"2525 S Monroe St",
    "sg:city":"Tallahassee",
    "sg:classifiers":[
        {
            "category":"Wholesale",
            "subcategory":"Machinery & Supplies",
            "type":"Manufacturing & Wholesale Goods"
        }
    ],
    "sg:phone":"+1 850 877 9151",
    "sg:postcode":"32301",
    "sg:province":"FL",
    "sg:tags":[
        "salon",
        "beauty"
    ],
    "wof:name":"Kns BEAUTY Supply",
    "wof:placetype":"venue"
},
  "geometry": {"coordinates":[-84.280551,30.415182],"type":"Point"}
}