{
  "type": "Feature",
  "properties": {
    "iso:country":"US",
    "sg:address":"1698 NE 183rd St",
    "sg:city":"Miami",
    "sg:classifiers":[
        {
            "category":"Professional",
            "subcategory":"Business Services",
            "type":"Services"
        }
    ],
    "sg:phone":"+1 305 947 6270",
    "sg:postcode":"33179",
    "sg:province":"FL",
    "wof:name":"Convention Cd's & Tapes",
    "wof:placetype":"venue"
},
  "geometry": {"coordinates":[-80.168809,25.944042],"type":"Point"}
}