{
  "type": "Feature",
  "properties": {
    "addr:full":"246 Tamiami Trl S Venice FL 34285",
    "addr:housenumber":"246",
    "addr:postcode":"34285",
    "addr:street":"Tamiami Trl S",
    "iso:country":"US",
    "sg:address":"246 Tamiami Trl S",
    "sg:city":"Venice",
    "sg:classifiers":[
        {
            "category":"Professional",
            "subcategory":"Lawyer & Legal Services",
            "type":"Services"
        }
    ],
    "sg:phone":"+1 941 484 8142",
    "sg:postcode":"34285",
    "sg:province":"FL",
    "sg:tags":[
        "attorney",
        "criminal",
        "law"
    ],
    "wof:name":"Baranowicz & Calderon Pa",
    "wof:placetype":"venue"
},
  "geometry": {"coordinates":[-82.444316,27.09747],"type":"Point"}
}