{
  "type": "Feature",
  "properties": {
    "iso:country":"US",
    "sg:address":"5501 Norwood Ave",
    "sg:city":"Jacksonville",
    "sg:classifiers":[
        {
            "category":"Personal",
            "subcategory":"Beauty Salon",
            "type":"Services"
        },
        {
            "category":"Personal",
            "subcategory":"Nail Salon",
            "type":"Services"
        }
    ],
    "sg:phone":"+1 904 924 0559",
    "sg:postcode":"32208",
    "sg:province":"FL",
    "wof:name":"Snow Nails",
    "wof:placetype":"venue"
},
  "geometry": {"coordinates":[-81.664468,30.37225],"type":"Point"}
}