{
  "type": "Feature",
  "properties": {
    "addr:full":"817 W Wheeler Rd Brandon FL 33510",
    "addr:housenumber":"817",
    "addr:postcode":"33510",
    "addr:street":"W Wheeler Rd",
    "iso:country":"US",
    "sg:address":"817 W Wheeler Rd",
    "sg:city":"Brandon",
    "sg:classifiers":[
        {
            "category":"Education",
            "subcategory":"School",
            "type":"Public Place"
        }
    ],
    "sg:phone":"+1 813 689 4470",
    "sg:postcode":"33510",
    "sg:province":"FL",
    "wof:name":"Hillsborough Assoc Retarded Ci",
    "wof:placetype":"venue"
},
  "geometry": {"coordinates":[-82.28978600000001,27.974327],"type":"Point"}
}