{
  "type": "Feature",
  "properties": {
    "addr:full":"1461 S Michigan Ave Clearwater FL 33756",
    "addr:housenumber":"1461",
    "addr:postcode":"33756",
    "addr:street":"S Michigan Ave",
    "iso:country":"US",
    "sg:address":"1461 S Michigan Ave",
    "sg:city":"Clearwater",
    "sg:classifiers":[
        {
            "category":"Building & Trades",
            "subcategory":"Landscaping Services",
            "type":"Services"
        }
    ],
    "sg:phone":"+1 727 562 9650",
    "sg:postcode":"33756",
    "sg:province":"FL",
    "sg:tags":[
        "landscape",
        "contractor"
    ],
    "wof:name":"Meadows Landscape Group Inc",
    "wof:placetype":"venue"
},
  "geometry": {"coordinates":[-82.788194,27.943577],"type":"Point"}
}