{
  "type": "Feature",
  "properties": {
    "iso:country":"US",
    "sg:address":"4004 S Semoran Blvd",
    "sg:city":"Orlando",
    "sg:classifiers":[
        {
            "category":"Restaurant",
            "type":"Food & Drink"
        }
    ],
    "sg:menulink":"http://www.allmenus.com/fl/orlando/39434-chengs-chinese-restaurant/menu/",
    "sg:phone":"+1 407 249 4180",
    "sg:postcode":"32822",
    "sg:province":"FL",
    "sg:tags":[
        "asian",
        "chinese"
    ],
    "wof:name":"Chengs Chinese Restaurant",
    "wof:placetype":"venue"
},
  "geometry": {"coordinates":[-81.31034699999999,28.503669],"type":"Point"}
}