{
  "type": "Feature",
  "properties": {
    "iso:country":"US",
    "sg:address":"1612 Talisia Ct",
    "sg:city":"Longwood",
    "sg:classifiers":[
        {
            "category":"Manufacturing",
            "subcategory":"Printing",
            "type":"Manufacturing & Wholesale Goods"
        }
    ],
    "sg:phone":"+1 407 788 6237",
    "sg:postcode":"32779",
    "sg:province":"FL",
    "sg:tags":[
        "lithographic",
        "commercial"
    ],
    "wof:name":"Mirror Image Graphics",
    "wof:placetype":"venue"
},
  "geometry": {"coordinates":[-81.39186100000001,28.720576],"type":"Point"}
}