{
  "type": "Feature",
  "properties": {
    "addr:full":"2650 S McCall Rd Englewood FL 34224",
    "addr:housenumber":"2650",
    "addr:postcode":"34224",
    "addr:street":"S Mccall Rd",
    "iso:country":"US",
    "sg:address":"2650 S McCall Rd",
    "sg:city":"Englewood",
    "sg:classifiers":[
        {
            "category":"Professional",
            "subcategory":"Lawyer & Legal Services",
            "type":"Services"
        }
    ],
    "sg:phone":"+1 941 496 9555",
    "sg:postcode":"34224",
    "sg:province":"FL",
    "sg:tags":[
        "attorney"
    ],
    "wof:name":"Shapiro Goldman & Babboni",
    "wof:placetype":"venue"
},
  "geometry": {"coordinates":[-82.31643099999999,26.93464],"type":"Point"}
}