{
  "type": "Feature",
  "properties": {
    "addr:full":"9410 Catalina Dr Bradenton FL 34210",
    "addr:housenumber":"9410",
    "addr:postcode":"34210",
    "addr:street":"Catalina Dr",
    "iso:country":"US",
    "sg:address":"9410 Catalina Dr",
    "sg:city":"Bradenton",
    "sg:classifiers":[
        {
            "category":"Real Estate",
            "subcategory":"Real Estate Agent",
            "type":"Services"
        },
        {
            "category":"Real Estate",
            "subcategory":"Real Estate Operator",
            "type":"Services"
        }
    ],
    "sg:phone":"+1 941 792 3532",
    "sg:postcode":"34210",
    "sg:province":"FL",
    "sg:tags":[
        "condominium"
    ],
    "wof:name":"Palma Sola Harbor Condominium",
    "wof:placetype":"venue"
},
  "geometry": {"coordinates":[-82.659374,27.468815],"type":"Point"}
}