{
  "type": "Feature",
  "properties": {
    "addr:full":"4350 SW 36th St Hollywood FL 33023",
    "addr:housenumber":"4350",
    "addr:postcode":"33023",
    "addr:street":"Sw 36Th St",
    "iso:country":"US",
    "sg:address":"4350 SW 36th St",
    "sg:city":"Hollywood",
    "sg:classifiers":[
        {
            "category":"Home & Garden",
            "subcategory":"Building Materials",
            "type":"Retail Goods"
        }
    ],
    "sg:phone":"+1 954 727 2179",
    "sg:postcode":"33023",
    "sg:province":"FL",
    "sg:tags":[
        "windows"
    ],
    "wof:name":"Window Professionals",
    "wof:placetype":"venue"
},
  "geometry": {"coordinates":[-80.186548,25.977407],"type":"Point"}
}