{
  "type": "Feature",
  "properties": {
    "iso:country":"US",
    "sg:address":"800 N Dixie Hwy",
    "sg:city":"Lantana",
    "sg:classifiers":[
        {
            "category":"Real Estate",
            "subcategory":"Real Estate Agent",
            "type":"Services"
        },
        {
            "category":"Real Estate",
            "subcategory":"Real Estate Operator",
            "type":"Services"
        }
    ],
    "sg:phone":"+1 561 540 5900",
    "sg:postcode":"33462",
    "sg:province":"FL",
    "sg:tags":[
        "condominium"
    ],
    "wof:name":"Moorings At Lantana",
    "wof:placetype":"venue"
},
  "geometry": {"coordinates":[-80.05233,26.592079],"type":"Point"}
}