{
  "type": "Feature",
  "properties": {
    "iso:country":"US",
    "sg:address":"4140 SE Old Saint Lucie Blvd",
    "sg:city":"Stuart",
    "sg:classifiers":[
        {
            "category":"Professional",
            "subcategory":"Business Services",
            "type":"Services"
        }
    ],
    "sg:phone":"+1 772 223 4007",
    "sg:postcode":"34996",
    "sg:province":"FL",
    "sg:tags":[
        "holding"
    ],
    "wof:name":"Treasure Coast Holdings Inc",
    "wof:placetype":"venue"
},
  "geometry": {"coordinates":[-80.20149000000001,27.178935],"type":"Point"}
}