{
  "type": "Feature",
  "properties": {
    "addr:full":"2195 W Colonial Dr Orlando FL 32804",
    "addr:housenumber":"2195",
    "addr:postcode":"32804",
    "addr:street":"W Colonial Dr",
    "iso:country":"US",
    "sg:address":"2195 W Colonial Dr",
    "sg:city":"Orlando",
    "sg:classifiers":[
        {
            "category":"Autos & Motor Vehicles",
            "subcategory":"Automobile Sales",
            "type":"Retail Goods"
        },
        {
            "category":"Retail",
            "subcategory":"Auto Rental",
            "type":"Services"
        }
    ],
    "sg:phone":"+1 407 298 9995",
    "sg:postcode":"32804",
    "sg:province":"FL",
    "sg:tags":[
        "car",
        "leasing",
        "truck"
    ],
    "sg:website":"http://budget.com/IYP_tl",
    "wof:name":"Budget Rent A Car",
    "wof:placetype":"venue"
},
  "geometry": {"coordinates":[-81.40876799999999,28.552967],"type":"Point"}
}