{
  "type": "Feature",
  "properties": {
    "iso:country":"US",
    "sg:address":"207 Old Daytona Rd",
    "sg:city":"De Land",
    "sg:classifiers":[
        {
            "category":"Manufacturing",
            "subcategory":"Tools & Machinery",
            "type":"Manufacturing & Wholesale Goods"
        }
    ],
    "sg:phone":"+1 386 734 4556",
    "sg:postcode":"32724",
    "sg:province":"FL",
    "sg:tags":[
        "automotive",
        "au",
        "industrial",
        "general",
        "mfg"
    ],
    "wof:name":"D & H Enterprises-Machine Shop",
    "wof:placetype":"venue"
},
  "geometry": {"coordinates":[-81.301734,29.057452],"type":"Point"}
}