{
  "type": "Feature",
  "properties": {
    "addr:full":"5415 Bahia Vista St Sarasota FL 34232",
    "addr:housenumber":"5415",
    "addr:postcode":"34232",
    "addr:street":"Bahia Vista St",
    "iso:country":"US",
    "sg:address":"5415 Bahia Vista St",
    "sg:city":"Sarasota",
    "sg:classifiers":[
        {
            "category":"Education",
            "subcategory":"School",
            "type":"Public Place"
        }
    ],
    "sg:phone":"+1 941 371 6481",
    "sg:postcode":"34232",
    "sg:province":"FL",
    "sg:tags":[
        "grade",
        "kindergarten",
        "through",
        "twelfth",
        "for"
    ],
    "sg:website":"www.sarasotachristian.org",
    "wof:name":"Christian Sarasota School",
    "wof:placetype":"venue"
},
  "geometry": {"coordinates":[-82.46043299999999,27.323065],"type":"Point"}
}