{
  "type": "Feature",
  "properties": {
    "addr:full":"2222 S Combee Rd Lakeland FL 33801",
    "addr:housenumber":"2222",
    "addr:postcode":"33801",
    "addr:street":"S Combee Rd",
    "iso:country":"US",
    "sg:address":"2222 S Combee Rd",
    "sg:city":"Lakeland",
    "sg:classifiers":[
        {
            "category":"Manufacturing",
            "subcategory":"Tools & Machinery",
            "type":"Manufacturing & Wholesale Goods"
        }
    ],
    "sg:phone":"+1 863 666 8590",
    "sg:postcode":"33801",
    "sg:province":"FL",
    "sg:tags":[
        "mfg",
        "material",
        "system",
        "handling",
        "turnkey"
    ],
    "wof:name":"Mouat Company Inc",
    "wof:placetype":"venue"
},
  "geometry": {"coordinates":[-81.907724,28.018691],"type":"Point"}
}