{
  "type": "Feature",
  "properties": {
    "addr:full":"18191 Slater Rd Fort Myers FL 33917",
    "addr:housenumber":"18191",
    "addr:postcode":"33917",
    "addr:street":"Slater Rd",
    "iso:country":"US",
    "sg:address":"18191 Slater Rd",
    "sg:city":"Fort Myers",
    "sg:classifiers":[
        {
            "category":"Shopping",
            "type":"Retail Goods"
        }
    ],
    "sg:phone":"+1 239 731 0180",
    "sg:postcode":"33917",
    "sg:province":"FL",
    "sg:tags":[
        "merchandise"
    ],
    "wof:name":"A To Z Bargins",
    "wof:placetype":"venue"
},
  "geometry": {"coordinates":[-81.85181799999999,26.726826],"type":"Point"}
}