{
  "type": "Feature",
  "properties": {
    "addr:full":"1104 S Manhattan Ave Tampa FL 33629",
    "addr:housenumber":"1104",
    "addr:postcode":"33629",
    "addr:street":"S Manhattan Ave",
    "iso:country":"US",
    "sg:address":"1104 S Manhattan Ave",
    "sg:city":"Tampa",
    "sg:classifiers":[
        {
            "category":"Communications",
            "subcategory":"Film & Video Production",
            "type":"Services"
        }
    ],
    "sg:phone":"+1 813 840 4949",
    "sg:postcode":"33629",
    "sg:province":"FL",
    "sg:tags":[
        "services-commercial"
    ],
    "wof:name":"Dreamscape Multimedia",
    "wof:placetype":"venue"
},
  "geometry": {"coordinates":[-82.518204,27.933031],"type":"Point"}
}