{
  "type": "Feature",
  "properties": {
    "iso:country":"US",
    "sg:address":"2666 Palm Ave",
    "sg:city":"Hialeah",
    "sg:classifiers":[
        {
            "category":"Shopping",
            "subcategory":"Beauty & Cosmetics",
            "type":"Retail Goods"
        },
        {
            "category":"Personal",
            "subcategory":"Barber",
            "type":"Services"
        },
        {
            "category":"Personal",
            "subcategory":"Beauty Salon",
            "type":"Services"
        }
    ],
    "sg:phone":"+1 305 603 7838",
    "sg:postcode":"33010",
    "sg:province":"FL",
    "sg:tags":[
        "equipment",
        "perfume",
        "salons-equipment",
        "supply"
    ],
    "wof:name":"Marilynn Beauty",
    "wof:placetype":"venue"
},
  "geometry": {"coordinates":[-80.282268,25.846203],"type":"Point"}
}