{
  "type": "Feature",
  "properties": {
    "addr:full":"280 North Dr Melbourne FL 32934",
    "addr:housenumber":"280",
    "addr:postcode":"32934",
    "addr:street":"North Dr",
    "iso:country":"US",
    "sg:address":"280 North Dr",
    "sg:city":"Melbourne",
    "sg:classifiers":[
        {
            "category":"Personal",
            "type":"Services"
        }
    ],
    "sg:phone":"+1 321 252 0013",
    "sg:postcode":"32934",
    "sg:province":"FL",
    "sg:tags":[
        "mover"
    ],
    "wof:name":"Florida Moving Systems, Inc.",
    "wof:placetype":"venue"
},
  "geometry": {"coordinates":[-80.69000699999999,28.108894],"type":"Point"}
}