{
  "type": "Feature",
  "properties": {
    "addr:full":"12911 Eagle Rd Cape Coral FL 33909",
    "addr:housenumber":"12911",
    "addr:postcode":"33909",
    "addr:street":"Eagle Rd",
    "iso:country":"US",
    "sg:address":"12911 Eagle Rd",
    "sg:city":"Cape Coral",
    "sg:classifiers":[
        {
            "category":"Shopping",
            "subcategory":"Jewelry",
            "type":"Retail Goods"
        }
    ],
    "sg:phone":"+1 239 549 1992",
    "sg:postcode":"33909",
    "sg:province":"FL",
    "sg:tags":[
        "store"
    ],
    "wof:name":"Classic Jewelers Inc",
    "wof:placetype":"venue"
},
  "geometry": {"coordinates":[-81.97174200000001,26.717066],"type":"Point"}
}