{
  "type": "Feature",
  "properties": {
    "addr:full":"513 E 9th St Sanford FL 32771",
    "addr:housenumber":"513",
    "addr:postcode":"32771",
    "addr:street":"E 9Th St",
    "iso:country":"US",
    "sg:address":"513 E 9th St",
    "sg:city":"Sanford",
    "sg:classifiers":[
        {
            "category":"Insurance",
            "subcategory":"Hazard Insurance",
            "type":"Services"
        }
    ],
    "sg:phone":"+1 407 322 6547",
    "sg:postcode":"32771",
    "sg:province":"FL",
    "sg:tags":[
        "carrier",
        "surety"
    ],
    "wof:name":"L A Black & Associates",
    "wof:placetype":"venue"
},
  "geometry": {"coordinates":[-81.262934,28.804394],"type":"Point"}
}