{
  "type": "Feature",
  "properties": {
    "addr:full":"10386 W Halls River Rd Homosassa FL 34448",
    "addr:housenumber":"10386",
    "addr:postcode":"34448",
    "addr:street":"W Halls River Rd",
    "iso:country":"US",
    "sg:address":"10386 W Halls River Rd",
    "sg:city":"Homosassa",
    "sg:classifiers":[
        {
            "category":"Food & Beverages",
            "subcategory":"Meat & Fish",
            "type":"Retail Goods"
        }
    ],
    "sg:phone":"+1 352 628 7711",
    "sg:postcode":"34448",
    "sg:province":"FL",
    "wof:name":"Seafood Cellar",
    "wof:placetype":"venue"
},
  "geometry": {"coordinates":[-82.60605700000001,28.797586],"type":"Point"}
}