{
  "type": "Feature",
  "properties": {
    "addr:full":"14024 Arbor Knoll Cir Tampa FL 33625",
    "addr:housenumber":"14024",
    "addr:postcode":"33625",
    "addr:street":"Arbor Knoll Cir",
    "iso:country":"US",
    "sg:address":"14024 Arbor Knoll Cir",
    "sg:city":"Tampa",
    "sg:classifiers":[
        {
            "category":"Professional",
            "subcategory":"Management & Consulting",
            "type":"Services"
        }
    ],
    "sg:phone":"+1 813 968 6670",
    "sg:postcode":"33625",
    "sg:province":"FL",
    "wof:name":"Scripttech Inc",
    "wof:placetype":"venue"
},
  "geometry": {"coordinates":[-82.542664,28.073535],"type":"Point"}
}