{
  "type": "Feature",
  "properties": {
    "addr:full":"2403 View Way Lakeland FL 33810",
    "addr:housenumber":"2403",
    "addr:postcode":"33810",
    "addr:street":"View Way",
    "iso:country":"US",
    "sg:address":"2403 View Way",
    "sg:city":"Lakeland",
    "sg:classifiers":[
        {
            "category":"Building & Trades",
            "subcategory":"Construction",
            "type":"Services"
        }
    ],
    "sg:phone":"+1 863 858 8938",
    "sg:postcode":"33810",
    "sg:province":"FL",
    "sg:tags":[
        "contractor"
    ],
    "wof:name":"Jenkins Masonry",
    "wof:placetype":"venue"
},
  "geometry": {"coordinates":[-81.996436,28.136617],"type":"Point"}
}