{
  "type": "Feature",
  "properties": {
    "iso:country":"US",
    "sg:address":"107 N Old Dixie Hwy",
    "sg:city":"Lady Lake",
    "sg:classifiers":[
        {
            "category":"Retail",
            "subcategory":"Repair Shop",
            "type":"Services"
        }
    ],
    "sg:phone":"+1 352 753 4141",
    "sg:postcode":"32159",
    "sg:province":"FL",
    "wof:name":"Jackies Upholstery",
    "wof:placetype":"venue"
},
  "geometry": {"coordinates":[-81.92406699999999,28.918508],"type":"Point"}
}