{
  "type": "Feature",
  "properties": {
    "iso:country":"US",
    "sg:address":"4821 Blanding Blvd",
    "sg:city":"Jacksonville",
    "sg:classifiers":[
        {
            "category":"Retail",
            "subcategory":"Auto Repair",
            "type":"Services"
        }
    ],
    "sg:phone":"+1 904 772 1701",
    "sg:postcode":"32210",
    "sg:province":"FL",
    "sg:tags":[
        "maintenance"
    ],
    "wof:name":"Jiffy Lube",
    "wof:placetype":"venue"
},
  "geometry": {"coordinates":[-81.74114299999999,30.259621],"type":"Point"}
}