{
  "type": "Feature",
  "properties": {
    "addr:full":"6444 NW 20th Ct Pompano Beach FL 33063",
    "addr:housenumber":"6444",
    "addr:postcode":"33063",
    "addr:street":"Nw 20Th Ct",
    "iso:country":"US",
    "sg:address":"6444 NW 20th Ct",
    "sg:city":"Pompano Beach",
    "sg:classifiers":[
        {
            "category":"Restaurant",
            "type":"Food & Drink"
        }
    ],
    "sg:phone":"+1 954 977 2433",
    "sg:postcode":"33063",
    "sg:province":"FL",
    "sg:tags":[
        "eating"
    ],
    "wof:name":"Chef Edge Cuisine Inc",
    "wof:placetype":"venue"
},
  "geometry": {"coordinates":[-80.210617,26.252973],"type":"Point"}
}