{
  "type": "Feature",
  "properties": {
    "iso:country":"US",
    "sg:address":"1101 NE 24th Ave",
    "sg:city":"Pompano Beach",
    "sg:classifiers":[
        {
            "category":"Manufacturing",
            "subcategory":"Printing",
            "type":"Manufacturing & Wholesale Goods"
        }
    ],
    "sg:phone":"+1 954 946 4331",
    "sg:postcode":"33062",
    "sg:province":"FL",
    "sg:tags":[
        "periodical"
    ],
    "wof:name":"Bar & Restaurant Magazine",
    "wof:placetype":"venue"
},
  "geometry": {"coordinates":[-80.099755,26.244738],"type":"Point"}
}