{
  "type": "Feature",
  "properties": {
    "addr:full":"207 W Lutz Lake Fern Rd Lutz FL 33548",
    "addr:housenumber":"207",
    "addr:postcode":"33548",
    "addr:street":"W Lutz Lake Fern Rd",
    "iso:country":"US",
    "sg:address":"207 W Lutz Lake Fern Rd",
    "sg:city":"Lutz",
    "sg:classifiers":[
        {
            "category":"Organizations",
            "subcategory":"Religious Organization",
            "type":"Services"
        }
    ],
    "sg:phone":"+1 813 949 1751",
    "sg:postcode":"33548",
    "sg:province":"FL",
    "sg:tags":[
        "methodist",
        "church"
    ],
    "sg:website":"www.firstumclutz.org",
    "wof:name":"First United Methodist Church",
    "wof:placetype":"venue"
},
  "geometry": {"coordinates":[-82.463812,28.151035],"type":"Point"}
}