{
  "type": "Feature",
  "properties": {
    "addr:full":"1952 S Lake Pleasant Rd Apopka FL 32703",
    "addr:housenumber":"1952",
    "addr:postcode":"32703",
    "addr:street":"S Lake Pleasant Rd",
    "iso:country":"US",
    "sg:address":"1952 S Lake Pleasant Rd",
    "sg:city":"Apopka",
    "sg:classifiers":[
        {
            "category":"Freight",
            "type":"Transportation"
        }
    ],
    "sg:phone":"+1 407 889 3847",
    "sg:postcode":"32703",
    "sg:province":"FL",
    "sg:tags":[
        "operator",
        "trucking"
    ],
    "wof:name":"Dan Cooper Transport",
    "wof:placetype":"venue"
},
  "geometry": {"coordinates":[-81.476377,28.64921],"type":"Point"}
}