{
  "type": "Feature",
  "properties": {
    "iso:country":"US",
    "sg:address":"4221 Drexel Ave",
    "sg:city":"Orlando",
    "sg:classifiers":[
        {
            "category":"Professional",
            "subcategory":"Engineering",
            "type":"Services"
        },
        {
            "category":"Building & Trades",
            "subcategory":"Cleaning & Sanitation",
            "type":"Services"
        },
        {
            "category":"Building & Trades",
            "subcategory":"Construction",
            "type":"Services"
        }
    ],
    "sg:phone":"+1 407 575 7910",
    "sg:postcode":"32808",
    "sg:province":"FL",
    "sg:tags":[
        "systems-repairing",
        "duct",
        "system",
        "specialty",
        "equipment",
        "heating",
        "contractor",
        "air conditioning"
    ],
    "sg:website":"http://jjairorlandofl.yolasite.com",
    "wof:name":"Express Elegance",
    "wof:placetype":"venue"
},
  "geometry": {"coordinates":[-81.457016,28.594735],"type":"Point"}
}