{
  "type": "Feature",
  "properties": {
    "iso:country":"US",
    "sg:address":"9240 NW 7th Ave",
    "sg:city":"Miami",
    "sg:classifiers":[
        {
            "category":"Autos & Motor Vehicles",
            "subcategory":"Automobile Sales",
            "type":"Retail Goods"
        }
    ],
    "sg:phone":"+1 305 754 4544",
    "sg:postcode":"33150",
    "sg:province":"FL",
    "sg:tags":[
        "used"
    ],
    "wof:name":"Escalade Leasing Corp",
    "wof:placetype":"venue"
},
  "geometry": {"coordinates":[-80.20966300000001,25.859142],"type":"Point"}
}