{
  "type": "Feature",
  "properties": {
    "iso:country":"US",
    "sg:address":"100 S Miami Ave",
    "sg:city":"Miami",
    "sg:classifiers":[
        {
            "category":"Shopping",
            "subcategory":"Jewelry",
            "type":"Retail Goods"
        }
    ],
    "sg:phone":"+1 305 577 8822",
    "sg:postcode":"33130",
    "sg:province":"FL",
    "sg:tags":[
        "jeweler"
    ],
    "wof:name":"Rosa Jewelry",
    "wof:placetype":"venue"
},
  "geometry": {"coordinates":[-80.19356399999999,25.772834],"type":"Point"}
}