{
  "type": "Feature",
  "properties": {
    "iso:country":"US",
    "sg:address":"10100 Fox Trail Rd S",
    "sg:city":"West Palm Beach",
    "sg:classifiers":[
        {
            "category":"Bakery",
            "type":"Food & Drink"
        }
    ],
    "sg:menulink":"http://www.allmenus.com/fl/royal-palm-beach-west-jupiter/100001-golden-corral/menu/",
    "sg:phone":"+1 561 793 0201",
    "sg:postcode":"33411",
    "sg:province":"FL",
    "sg:tags":[
        "american",
        "pastry"
    ],
    "wof:name":"Golden Corral",
    "wof:placetype":"venue"
},
  "geometry": {"coordinates":[-80.202162,26.708309],"type":"Point"}
}