{
  "type": "Feature",
  "properties": {
    "addr:full":"1909 University Blvd S Jacksonville FL 32216",
    "addr:housenumber":"1909",
    "addr:postcode":"32216",
    "addr:street":"University Blvd S",
    "iso:country":"US",
    "sg:address":"1909 University Blvd S",
    "sg:city":"Jacksonville",
    "sg:classifiers":[
        {
            "category":"Retail",
            "subcategory":"Auto Repair",
            "type":"Services"
        }
    ],
    "sg:phone":"+1 904 396 1113",
    "sg:postcode":"32216",
    "sg:province":"FL",
    "sg:tags":[
        "repairing",
        "automobile"
    ],
    "wof:name":"Eden Revisited Healing Mnstrs",
    "wof:placetype":"venue"
},
  "geometry": {"coordinates":[-81.600572,30.305137],"type":"Point"}
}