{
  "type": "Feature",
  "properties": {
    "iso:country":"US",
    "sg:address":"10653 N Okeechobee Rd",
    "sg:city":"Hialeah",
    "sg:classifiers":[
        {
            "category":"Wholesale",
            "subcategory":"Machinery & Supplies",
            "type":"Manufacturing & Wholesale Goods"
        }
    ],
    "sg:phone":"+1 305 825 4200",
    "sg:postcode":"33018",
    "sg:province":"FL",
    "sg:tags":[
        "industrial",
        "miscellaneous"
    ],
    "wof:name":"Lango Equipment Svc",
    "wof:placetype":"venue"
},
  "geometry": {"coordinates":[-80.343816,25.870062],"type":"Point"}
}