{
  "type": "Feature",
  "properties": {
    "addr:full":"13416 Front Beach Rd Panama City Bch FL 32407",
    "addr:housenumber":"13416",
    "addr:postcode":"32407",
    "addr:street":"Front Beach Rd",
    "iso:country":"US",
    "sg:address":"13416 Front Beach Rd",
    "sg:city":"Panama City Bch",
    "sg:classifiers":[
        {
            "category":"Autos & Motor Vehicles",
            "subcategory":"Motorcycle Sales",
            "type":"Retail Goods"
        }
    ],
    "sg:phone":"+1 850 233 1391",
    "sg:postcode":"32407",
    "sg:province":"FL",
    "sg:tags":[
        "scooter"
    ],
    "wof:name":"California Cycles Inc",
    "wof:placetype":"venue"
},
  "geometry": {"coordinates":[-85.84421399999999,30.198213],"type":"Point"}
}