{
  "type": "Feature",
  "properties": {
    "addr:full":"211 Pebble Beach Cir Naples FL 34113",
    "addr:housenumber":"211",
    "addr:postcode":"34113",
    "addr:street":"Pebble Beach Cir",
    "iso:country":"US",
    "sg:address":"211 Pebble Beach Cir",
    "sg:city":"Naples",
    "sg:classifiers":[
        {
            "category":"Building & Trades",
            "subcategory":"Construction",
            "type":"Services"
        }
    ],
    "sg:phone":"+1 239 732 5209",
    "sg:postcode":"34113",
    "sg:province":"FL",
    "sg:tags":[
        "hanging",
        "contractor"
    ],
    "wof:name":"Menefee Painting Hank",
    "wof:placetype":"venue"
},
  "geometry": {"coordinates":[-81.734493,26.096861],"type":"Point"}
}