{
  "type": "Feature",
  "properties": {
    "addr:full":"263 SW Hatteras Ct Palm City FL 34990",
    "addr:housenumber":"263",
    "addr:postcode":"34990",
    "addr:street":"Sw Hatteras Ct",
    "iso:country":"US",
    "sg:address":"263 SW Hatteras Ct",
    "sg:city":"Palm City",
    "sg:classifiers":[
        {
            "category":"Professional",
            "subcategory":"Accounting & Tax Preparation",
            "type":"Services"
        }
    ],
    "sg:phone":"+1 772 288 2775",
    "sg:postcode":"34990",
    "sg:province":"FL",
    "sg:tags":[
        "accountant"
    ],
    "wof:name":"Alexander Co",
    "wof:placetype":"venue"
},
  "geometry": {"coordinates":[-80.28140500000001,27.203391],"type":"Point"}
}