{
  "type": "Feature",
  "properties": {
    "iso:country":"US",
    "sg:address":"500 Ave L NW",
    "sg:city":"Winter Haven",
    "sg:classifiers":[
        {
            "category":"Real Estate",
            "subcategory":"Real Estate Operator",
            "type":"Services"
        }
    ],
    "sg:phone":"+1 863 299 4481",
    "sg:postcode":"33881",
    "sg:province":"FL",
    "sg:tags":[
        "building",
        "apartment"
    ],
    "wof:name":"Episcopal-Catholic Apartments",
    "wof:placetype":"venue"
},
  "geometry": {"coordinates":[-81.732957,28.033147],"type":"Point"}
}