{
  "type": "Feature",
  "properties": {
    "iso:country":"US",
    "sg:address":"2000 S Dixie Hwy",
    "sg:city":"Miami",
    "sg:classifiers":[
        {
            "category":"Health Services",
            "subcategory":"Doctor",
            "type":"Services"
        }
    ],
    "sg:phone":"+1 305 285 1462",
    "sg:postcode":"33133",
    "sg:province":"FL",
    "sg:tags":[
        "physician",
        "addiction",
        "medicine",
        "surgeons"
    ],
    "wof:name":"Discovery Program",
    "wof:placetype":"venue"
},
  "geometry": {"coordinates":[-80.225792,25.74427],"type":"Point"}
}