{
  "type": "Feature",
  "properties": {
    "addr:full":"210 42nd St W Bradenton FL 34209",
    "addr:housenumber":"210",
    "addr:postcode":"34209",
    "addr:street":"42Nd St W",
    "iso:country":"US",
    "sg:address":"210 42nd St W",
    "sg:city":"Bradenton",
    "sg:classifiers":[
        {
            "category":"Building & Trades",
            "subcategory":"Plumbing",
            "type":"Services"
        }
    ],
    "sg:phone":"+1 941 746 0593",
    "sg:postcode":"34209",
    "sg:province":"FL",
    "sg:tags":[
        "contractor"
    ],
    "wof:name":"Plumbing By George",
    "wof:placetype":"venue"
},
  "geometry": {"coordinates":[-82.60302799999999,27.49926],"type":"Point"}
}