{
  "type": "Feature",
  "properties": {
    "addr:full":"541 East 9th Street Hialeah FL 33010",
    "addr:housenumber":"541",
    "addr:postcode":"33010",
    "addr:street":"East 9Th Street",
    "iso:country":"US",
    "sg:address":"541 East 9th Street",
    "sg:city":"Hialeah",
    "sg:classifiers":[
        {
            "category":"Professional",
            "subcategory":"Printing & Photocopies",
            "type":"Services"
        }
    ],
    "sg:phone":"+1 305 863 0319",
    "sg:postcode":"33010",
    "sg:province":"FL",
    "sg:tags":[
        "medal",
        "plaque",
        "trophies"
    ],
    "sg:website":"http://www.migawards.com",
    "wof:name":"Migdalia's Awards",
    "wof:placetype":"venue"
},
  "geometry": {"coordinates":[-80.270843,25.830272],"type":"Point"}
}