{
  "type": "Feature",
  "properties": {
    "iso:country":"US",
    "sg:address":"4253 Live Oak Blvd",
    "sg:city":"Delray Beach",
    "sg:classifiers":[
        {
            "category":"Banks & Credit Unions",
            "subcategory":"Financial Services",
            "type":"Services"
        }
    ],
    "sg:phone":"+1 561 638 8672",
    "sg:postcode":"33445",
    "sg:province":"FL",
    "sg:tags":[
        "company",
        "holding"
    ],
    "wof:name":"Ancour Holdings LLC",
    "wof:placetype":"venue"
},
  "geometry": {"coordinates":[-80.10184,26.427249],"type":"Point"}
}