{
  "type": "Feature",
  "properties": {
    "addr:full":"5307 E Fletcher Ave Tampa FL 33612",
    "addr:housenumber":"5307",
    "addr:postcode":"33612",
    "addr:street":"E Fletcher Ave",
    "iso:country":"US",
    "sg:address":"5307 E Fletcher Ave",
    "sg:city":"Tampa",
    "sg:classifiers":[
        {
            "category":"Professional",
            "subcategory":"Business Services",
            "type":"Services"
        }
    ],
    "sg:phone":"+1 813 988 2800",
    "sg:postcode":"33612",
    "sg:province":"FL",
    "sg:tags":[
        "interior",
        "consultant",
        "design",
        "decorator"
    ],
    "wof:name":"Wilkeson Design Assocs",
    "wof:placetype":"venue"
},
  "geometry": {"coordinates":[-82.395017,28.069115],"type":"Point"}
}