{
  "type": "Feature",
  "properties": {
    "iso:country":"US",
    "sg:address":"18314 NW 7th Ave",
    "sg:city":"Miami",
    "sg:classifiers":[
        {
            "category":"Insurance",
            "subcategory":"Insurance Agent",
            "type":"Services"
        }
    ],
    "sg:phone":"+1 305 655 1006",
    "sg:postcode":"33169",
    "sg:province":"FL",
    "sg:website":"www.cloverleafinsurance.com",
    "wof:name":"Cloverleaf Insurance Brokers",
    "wof:placetype":"venue"
},
  "geometry": {"coordinates":[-80.213356,25.944153],"type":"Point"}
}