{
  "type": "Feature",
  "properties": {
    "addr:full":"2665 S Bayshore Dr Ste 200 Miami FL 33133",
    "addr:housenumber":"2665",
    "addr:postcode":"33133",
    "addr:street":"S Bayshore Dr Ste 200",
    "iso:country":"US",
    "sg:address":"2665 S Bayshore Dr Ste 200",
    "sg:city":"Miami",
    "sg:classifiers":[
        {
            "category":"Real Estate",
            "subcategory":"Real Estate Services",
            "type":"Services"
        },
        {
            "category":"Professional",
            "subcategory":"Research",
            "type":"Services"
        }
    ],
    "sg:phone":"+1 305 358 4800",
    "sg:postcode":"33133",
    "sg:province":"FL",
    "sg:tags":[
        "abstracter",
        "title"
    ],
    "wof:name":"Garcia & Baloyra Title Co",
    "wof:placetype":"venue"
},
  "geometry": {"coordinates":[-80.235727,25.730715],"type":"Point"}
}