{
  "type": "Feature",
  "properties": {
    "iso:country":"US",
    "sg:address":"15932 Thoroughbred Ln",
    "sg:city":"Montverde",
    "sg:classifiers":[
        {
            "category":"Farming",
            "subcategory":"Fish & Marine Products",
            "type":"Manufacturing & Wholesale Goods"
        }
    ],
    "sg:phone":"+1 407 469 4602",
    "sg:postcode":"34756",
    "sg:province":"FL",
    "sg:tags":[
        "management"
    ],
    "wof:name":"Friends of Nature Wildlif",
    "wof:placetype":"venue"
},
  "geometry": {"coordinates":[-81.691174,28.590958],"type":"Point"}
}