{
  "type": "Feature",
  "properties": {
    "iso:country":"US",
    "sg:address":"9162 Bay Hill Blvd",
    "sg:city":"Orlando",
    "sg:phone":"+1 407 909 0637",
    "sg:postcode":"32819",
    "sg:province":"FL",
    "wof:name":"Philip Brewer Pa",
    "wof:placetype":"venue"
},
  "geometry": {"coordinates":[-81.512553,28.45188],"type":"Point"}
}