{
  "type": "Feature",
  "properties": {
    "iso:country":"US",
    "sg:address":"9380 SW 72nd St",
    "sg:city":"Miami",
    "sg:classifiers":[
        {
            "category":"Banks & Credit Unions",
            "subcategory":"Bank",
            "type":"Services"
        }
    ],
    "sg:phone":"+1 305 596 3606",
    "sg:postcode":"33173",
    "sg:province":"FL",
    "sg:tags":[
        "loan",
        "real estate"
    ],
    "wof:name":"Mortgage Formula",
    "wof:placetype":"venue"
},
  "geometry": {"coordinates":[-80.34566,25.701748],"type":"Point"}
}