{
  "type": "Feature",
  "properties": {
    "addr:full":"1570 Madruga Ave Miami FL 33146",
    "addr:housenumber":"1570",
    "addr:postcode":"33146",
    "addr:street":"Madruga Ave",
    "iso:country":"US",
    "sg:address":"1570 Madruga Ave",
    "sg:city":"Miami",
    "sg:classifiers":[
        {
            "category":"Insurance",
            "subcategory":"Hazard Insurance",
            "type":"Services"
        }
    ],
    "sg:phone":"+1 305 662 4981",
    "sg:postcode":"33146",
    "sg:province":"FL",
    "sg:tags":[
        "carrier"
    ],
    "wof:name":"Quoteconnect Inc",
    "wof:placetype":"venue"
},
  "geometry": {"coordinates":[-80.284609,25.70705],"type":"Point"}
}