{
  "type": "Feature",
  "properties": {
    "iso:country":"US",
    "sg:address":"16299 133rd Dr N",
    "sg:city":"Jupiter",
    "sg:classifiers":[
        {
            "category":"Wholesale",
            "subcategory":"Non-durable Goods",
            "type":"Manufacturing & Wholesale Goods"
        }
    ],
    "sg:phone":"+1 561 747 0973",
    "sg:postcode":"33478",
    "sg:province":"FL",
    "wof:name":"ASC",
    "wof:placetype":"venue"
},
  "geometry": {"coordinates":[-80.245169,26.916174],"type":"Point"}
}