{
  "type": "Feature",
  "properties": {
    "iso:country":"US",
    "sg:address":"3210 Stiverson Rd",
    "sg:city":"Land O Lakes",
    "sg:classifiers":[
        {
            "category":"Banks & Credit Unions",
            "subcategory":"Bank",
            "type":"Services"
        }
    ],
    "sg:phone":"+1 813 949 0455",
    "sg:postcode":"34639",
    "sg:province":"FL",
    "sg:tags":[
        "mortgage",
        "loan",
        "broker",
        "real estate"
    ],
    "wof:name":"United Lenders America LLC",
    "wof:placetype":"venue"
},
  "geometry": {"coordinates":[-82.46323,28.203763],"type":"Point"}
}