{
  "type": "Feature",
  "properties": {
    "iso:country":"US",
    "sg:address":"3801 N Washington Blvd",
    "sg:city":"Sarasota",
    "sg:classifiers":[
        {
            "category":"Shopping",
            "type":"Retail Goods"
        },
        {
            "category":"Home & Garden",
            "subcategory":"Garden Supply",
            "type":"Retail Goods"
        }
    ],
    "sg:phone":"+1 941 355 8833",
    "sg:postcode":"34234",
    "sg:province":"FL",
    "sg:tags":[
        "landscaping",
        "merchandise",
        "equipment"
    ],
    "sg:website":"www.sfs1.com",
    "wof:name":"Southern Farm Supply Inc",
    "wof:placetype":"venue"
},
  "geometry": {"coordinates":[-82.530727,27.368169],"type":"Point"}
}