{
  "type": "Feature",
  "properties": {
    "iso:country":"US",
    "sg:address":"697 Jefferis Ct",
    "sg:city":"Eustis",
    "sg:classifiers":[
        {
            "category":"Building & Trades",
            "subcategory":"Electrical",
            "type":"Services"
        }
    ],
    "sg:phone":"+1 352 483 2669",
    "sg:postcode":"32726",
    "sg:province":"FL",
    "sg:tags":[
        "electrical",
        "contractor"
    ],
    "wof:name":"Pait Electric",
    "wof:placetype":"venue"
},
  "geometry": {"coordinates":[-81.666303,28.847111],"type":"Point"}
}