{
  "type": "Feature",
  "properties": {
    "iso:country":"US",
    "sg:address":"1811 Huron Trl",
    "sg:city":"Maitland",
    "sg:classifiers":[
        {
            "category":"Organizations",
            "subcategory":"Professional Association",
            "type":"Services"
        }
    ],
    "sg:phone":"+1 407 628 4444",
    "sg:postcode":"32751",
    "sg:province":"FL",
    "wof:name":"Pulse EFT Assn",
    "wof:placetype":"venue"
},
  "geometry": {"coordinates":[-81.34682100000001,28.634267],"type":"Point"}
}