{
  "type": "Feature",
  "properties": {
    "iso:country":"US",
    "sg:address":"3024 S Oakland Forest Dr",
    "sg:city":"Fort Lauderdale",
    "sg:classifiers":[
        {
            "category":"Organizations",
            "subcategory":"Community Association",
            "type":"Services"
        }
    ],
    "sg:phone":"+1 954 730 9257",
    "sg:postcode":"33309",
    "sg:province":"FL",
    "wof:name":"Condo Assoc Consolidated",
    "wof:placetype":"venue"
},
  "geometry": {"coordinates":[-80.184003,26.168912],"type":"Point"}
}