{
  "type": "Feature",
  "properties": {
    "iso:country":"US",
    "sg:address":"147 Alhambra Cir",
    "sg:city":"Coral Gables",
    "sg:classifiers":[
        {
            "category":"Health Services",
            "subcategory":"Health Practitioner",
            "type":"Services"
        }
    ],
    "sg:phone":"+1 305 648 0604",
    "sg:postcode":"33134",
    "sg:province":"FL",
    "sg:tags":[
        "psychotherapist"
    ],
    "wof:name":"Advanced Behavioral Network",
    "wof:placetype":"venue"
},
  "geometry": {"coordinates":[-80.25872200000001,25.752235],"type":"Point"}
}