{
  "type": "Feature",
  "properties": {
    "iso:country":"US",
    "sg:address":"12390 SW 131st Ave",
    "sg:city":"Miami",
    "sg:classifiers":[
        {
            "category":"Wholesale",
            "subcategory":"Hardware",
            "type":"Manufacturing & Wholesale Goods"
        },
        {
            "category":"Retail",
            "subcategory":"Repair Shop",
            "type":"Services"
        },
        {
            "category":"Home & Garden",
            "subcategory":"Hardware",
            "type":"Retail Goods"
        },
        {
            "category":"Manufacturing",
            "subcategory":"Tools & Machinery",
            "type":"Manufacturing & Wholesale Goods"
        },
        {
            "category":"Shopping",
            "subcategory":"Stationery & Office Supplies",
            "type":"Retail Goods"
        },
        {
            "category":"Home & Garden",
            "subcategory":"Garden Supply",
            "type":"Retail Goods"
        },
        {
            "category":"Building & Trades",
            "subcategory":"Equipment Rental",
            "type":"Services"
        }
    ],
    "sg:phone":"+1 305 278 2099",
    "sg:postcode":"33186",
    "sg:province":"FL",
    "sg:tags":[
        "renting",
        "lawn",
        "outdoor",
        "yard",
        "power",
        "equipment-sales",
        "tools-repairing",
        "compressors-repair",
        "hydraulic",
        "janitor",
        "landscaping",
        "part",
        "construction",
        "saw",
        "store"
    ],
    "sg:website":"http://www.equipmenttools.com",
    "wof:name":"Best Equipment Rental & Repair",
    "wof:placetype":"venue"
},
  "geometry": {"coordinates":[-80.406413,25.652678],"type":"Point"}
}