{
  "type": "Feature",
  "properties": {
    "addr:full":"5331 University Blvd W Jacksonville FL 32216",
    "addr:housenumber":"5331",
    "addr:postcode":"32216",
    "addr:street":"University Blvd W",
    "iso:country":"US",
    "sg:address":"5331 University Blvd W",
    "sg:city":"Jacksonville",
    "sg:classifiers":[
        {
            "category":"Organizations",
            "subcategory":"Community Association",
            "type":"Services"
        }
    ],
    "sg:phone":"+1 904 730 8031",
    "sg:postcode":"32216",
    "sg:province":"FL",
    "sg:tags":[
        "club"
    ],
    "wof:name":"Belissima Mens Club",
    "wof:placetype":"venue"
},
  "geometry": {"coordinates":[-81.613405,30.268794],"type":"Point"}
}