{
  "type": "Feature",
  "properties": {
    "iso:country":"US",
    "sg:address":"2 Sandhill Crane Rd",
    "sg:city":"Fernandina Beach",
    "sg:classifiers":[
        {
            "category":"Shopping",
            "subcategory":"Used Merchandise",
            "type":"Retail Goods"
        }
    ],
    "sg:phone":"+1 904 277 2483",
    "sg:postcode":"32034",
    "sg:province":"FL",
    "wof:name":"Your Hearts Desire",
    "wof:placetype":"venue"
},
  "geometry": {"coordinates":[-81.45788899999999,30.55106],"type":"Point"}
}