{
  "type": "Feature",
  "properties": {
    "addr:full":"11455 66th St N Largo FL 33773",
    "addr:housenumber":"11455",
    "addr:postcode":"33773",
    "addr:street":"66Th St N",
    "iso:country":"US",
    "sg:address":"11455 66th St N",
    "sg:city":"Largo",
    "sg:classifiers":[
        {
            "category":"Cinema",
            "subcategory":"Movie Theater",
            "type":"Entertainment"
        }
    ],
    "sg:phone":"+1 727 544 9500",
    "sg:postcode":"33773",
    "sg:province":"FL",
    "wof:name":"Candlelight Adult Theatre",
    "wof:placetype":"venue"
},
  "geometry": {"coordinates":[-82.72914400000001,27.875604],"type":"Point"}
}