{
  "type": "Feature",
  "properties": {
    "iso:country":"US",
    "sg:address":"22121 Seashore Cir",
    "sg:city":"Estero",
    "sg:classifiers":[
        {
            "category":"Health Services",
            "subcategory":"Clinic",
            "type":"Services"
        }
    ],
    "sg:phone":"+1 239 498 0730",
    "sg:postcode":"33928",
    "sg:province":"FL",
    "sg:tags":[
        "home",
        "care"
    ],
    "wof:name":"Home Helpers Direct Link",
    "wof:placetype":"venue"
},
  "geometry": {"coordinates":[-81.815152,26.41761],"type":"Point"}
}