{
  "type": "Feature",
  "properties": {
    "addr:full":"500 E Cervantes St Pensacola FL 32501",
    "addr:housenumber":"500",
    "addr:postcode":"32501",
    "addr:street":"E Cervantes St",
    "iso:country":"US",
    "sg:address":"500 E Cervantes St",
    "sg:city":"Pensacola",
    "sg:classifiers":[
        {
            "category":"Autos & Motor Vehicles",
            "subcategory":"Auto Supplies",
            "type":"Retail Goods"
        },
        {
            "category":"Retail",
            "subcategory":"Auto Repair",
            "type":"Services"
        }
    ],
    "sg:phone":"+1 850 438 4955",
    "sg:postcode":"32501",
    "sg:province":"FL",
    "sg:tags":[
        "exhaust",
        "automobile",
        "system",
        "part",
        "brake",
        "equipment-service",
        "muffler",
        "accessory",
        "air conditioning"
    ],
    "sg:website":"http://www.discountmufflersandbrakes.com",
    "wof:name":"Discount Mufflers & Brakes",
    "wof:placetype":"venue"
},
  "geometry": {"coordinates":[-87.21086099999999,30.42239],"type":"Point"}
}