{
  "type": "Feature",
  "properties": {
    "addr:full":"8651 Portside Ct Orlando FL 32817",
    "addr:housenumber":"8651",
    "addr:postcode":"32817",
    "addr:street":"Portside Ct",
    "iso:country":"US",
    "sg:address":"8651 Portside Ct",
    "sg:city":"Orlando",
    "sg:classifiers":[
        {
            "category":"Shopping",
            "subcategory":"Musical Instruments",
            "type":"Retail Goods"
        }
    ],
    "sg:phone":"+1 407 671 0730",
    "sg:postcode":"32817",
    "sg:province":"FL",
    "wof:name":"Keyboard Exchange Intl",
    "wof:placetype":"venue"
},
  "geometry": {"coordinates":[-81.265275,28.602193],"type":"Point"}
}