{
  "type": "Feature",
  "properties": {
    "iso:country":"US",
    "sg:address":"14411 S US Hwy 441",
    "sg:city":"Summerfield",
    "sg:classifiers":[
        {
            "category":"Manufacturing",
            "subcategory":"Tools & Machinery",
            "type":"Manufacturing & Wholesale Goods"
        }
    ],
    "sg:phone":"+1 352 347 6405",
    "sg:postcode":"34491",
    "sg:province":"FL",
    "sg:tags":[
        "clocks",
        "laminating",
        "mfg"
    ],
    "wof:name":"Bobo's Cypress Clocks & Supls",
    "wof:placetype":"venue"
},
  "geometry": {"coordinates":[-82.010009,29.01255],"type":"Point"}
}