{
  "type": "Feature",
  "properties": {
    "iso:country":"US",
    "sg:address":"41 Fairpoint Dr",
    "sg:city":"Gulf Breeze",
    "sg:classifiers":[
        {
            "category":"Health Services",
            "subcategory":"Doctor",
            "type":"Services"
        }
    ],
    "sg:phone":"+1 850 932 4550",
    "sg:postcode":"32561",
    "sg:province":"FL",
    "sg:tags":[
        "dentist"
    ],
    "wof:name":"J Scott Booker DDS",
    "wof:placetype":"venue"
},
  "geometry": {"coordinates":[-87.172735,30.364389],"type":"Point"}
}