{
  "type": "Feature",
  "properties": {
    "iso:country":"US",
    "sg:address":"3500 Clubhouse Ln",
    "sg:city":"Boynton Beach",
    "sg:classifiers":[
        {
            "category":"Professional",
            "type":"Services"
        }
    ],
    "sg:phone":"+1 561 738 1569",
    "sg:postcode":"33436",
    "sg:province":"FL",
    "sg:tags":[
        "establishment"
    ],
    "wof:name":"Hunters Run Isle Guardhouse",
    "wof:placetype":"venue"
},
  "geometry": {"coordinates":[-80.09834499999999,26.494777],"type":"Point"}
}