{
  "type": "Feature",
  "properties": {
    "addr:full":"1931 Old Coachman Rd N Clearwater FL 33763",
    "addr:housenumber":"1931",
    "addr:postcode":"33763",
    "addr:street":"Old Coachman Rd N",
    "iso:country":"US",
    "sg:address":"1931 Old Coachman Rd N",
    "sg:city":"Clearwater",
    "sg:classifiers":[
        {
            "category":"Freight",
            "type":"Transportation"
        }
    ],
    "sg:phone":"+1 727 791 7820",
    "sg:postcode":"33763",
    "sg:province":"FL",
    "sg:tags":[
        "operator",
        "trucking"
    ],
    "wof:name":"Antoni R Dworakowski",
    "wof:placetype":"venue"
},
  "geometry": {"coordinates":[-82.741958,27.991394],"type":"Point"}
}