{
  "type": "Feature",
  "properties": {
    "addr:full":"1110 State Hwy 60 Lake Wales FL 33853",
    "addr:housenumber":"1110",
    "addr:postcode":"33853",
    "addr:street":"State Hwy 60",
    "iso:country":"US",
    "sg:address":"1110 State Hwy 60",
    "sg:city":"Lake Wales",
    "sg:classifiers":[
        {
            "category":"Restaurant",
            "type":"Food & Drink"
        }
    ],
    "sg:phone":"+1 863 676 7110",
    "sg:postcode":"33853",
    "sg:province":"FL",
    "wof:name":"Mc Donald's",
    "wof:placetype":"venue"
},
  "geometry": {"coordinates":[-81.562618,27.89394],"type":"Point"}
}