{
  "type": "Feature",
  "properties": {
    "iso:country":"US",
    "sg:address":"305 Cypress Landing Dr",
    "sg:city":"Longwood",
    "sg:classifiers":[
        {
            "category":"Restaurant",
            "type":"Food & Drink"
        }
    ],
    "sg:phone":"+1 407 774 6921",
    "sg:postcode":"32779",
    "sg:province":"FL",
    "sg:tags":[
        "eating"
    ],
    "wof:name":"Potopas Concessions Inc",
    "wof:placetype":"venue"
},
  "geometry": {"coordinates":[-81.414451,28.709142],"type":"Point"}
}