{
  "type": "Feature",
  "properties": {
    "addr:full":"3304 Bishop Park Dr Winter Park FL 32792",
    "addr:housenumber":"3304",
    "addr:postcode":"32792",
    "addr:street":"Bishop Park Dr",
    "iso:country":"US",
    "sg:address":"3304 Bishop Park Dr",
    "sg:city":"Winter Park",
    "sg:classifiers":[
        {
            "category":"Shopping",
            "type":"Retail Goods"
        }
    ],
    "sg:phone":"+1 407 875 3289",
    "sg:postcode":"32792",
    "sg:province":"FL",
    "sg:tags":[
        "art",
        "gallery",
        "dealer"
    ],
    "wof:name":"Deck The Walls",
    "wof:placetype":"venue"
},
  "geometry": {"coordinates":[-81.30761,28.609767],"type":"Point"}
}