{
  "type": "Feature",
  "properties": {
    "addr:full":"6390 Bonnie Ct Saint Cloud FL 34771",
    "addr:housenumber":"6390",
    "addr:postcode":"34771",
    "addr:street":"Bonnie Ct",
    "iso:country":"US",
    "sg:address":"6390 Bonnie Ct",
    "sg:city":"Saint Cloud",
    "sg:classifiers":[
        {
            "category":"Wholesale",
            "subcategory":"Metals & Minerals",
            "type":"Manufacturing & Wholesale Goods"
        }
    ],
    "sg:phone":"+1 407 891 7019",
    "sg:postcode":"34771",
    "sg:province":"FL",
    "sg:tags":[
        "center"
    ],
    "wof:name":"Jadar Inc",
    "wof:placetype":"venue"
},
  "geometry": {"coordinates":[-81.182822,28.279069],"type":"Point"}
}