{
  "type": "Feature",
  "properties": {
    "addr:full":"429 Westwind Dr North Palm Beach FL 33408",
    "addr:housenumber":"429",
    "addr:postcode":"33408",
    "addr:street":"Westwind Dr North",
    "iso:country":"US",
    "sg:address":"429 Westwind Dr",
    "sg:city":"North Palm Beach",
    "sg:classifiers":[
        {
            "category":"Building & Trades",
            "subcategory":"Construction",
            "type":"Services"
        }
    ],
    "sg:phone":"+1 561 848 5272",
    "sg:postcode":"33408",
    "sg:province":"FL",
    "sg:tags":[
        "home",
        "builder"
    ],
    "wof:name":"B C Baquero Construction Inc",
    "wof:placetype":"venue"
},
  "geometry": {"coordinates":[-80.07264499999999,26.812485],"type":"Point"}
}