{
  "type": "Feature",
  "properties": {
    "iso:country":"US",
    "sg:address":"2732 Haulover Blvd",
    "sg:city":"Deltona",
    "sg:classifiers":[
        {
            "category":"Wholesale",
            "subcategory":"Painting Supplies",
            "type":"Manufacturing & Wholesale Goods"
        },
        {
            "category":"Home & Garden",
            "subcategory":"Hardware",
            "type":"Retail Goods"
        },
        {
            "category":"Home & Garden",
            "subcategory":"Building Materials",
            "type":"Retail Goods"
        },
        {
            "category":"Manufacturing",
            "subcategory":"Tools & Machinery",
            "type":"Manufacturing & Wholesale Goods"
        }
    ],
    "sg:phone":"+1 386 532 9657",
    "sg:postcode":"32738",
    "sg:province":"FL",
    "sg:tags":[
        "paint",
        "store",
        "improvement"
    ],
    "sg:website":"http://www.lowes.com",
    "wof:name":"Lowe's",
    "wof:placetype":"venue"
},
  "geometry": {"coordinates":[-81.190879,28.94951],"type":"Point"}
}