{
  "type": "Feature",
  "properties": {
    "addr:full":"7421 114th Ave N Largo FL 33773",
    "addr:housenumber":"7421",
    "addr:postcode":"33773",
    "addr:street":"114Th Ave N",
    "iso:country":"US",
    "sg:address":"7421 114th Ave N",
    "sg:city":"Largo",
    "sg:classifiers":[
        {
            "category":"Wholesale",
            "subcategory":"Hardware",
            "type":"Manufacturing & Wholesale Goods"
        },
        {
            "category":"Home & Garden",
            "subcategory":"Hardware",
            "type":"Retail Goods"
        }
    ],
    "sg:phone":"+1 727 546 4655",
    "sg:postcode":"33773",
    "sg:province":"FL",
    "sg:tags":[
        "industrial",
        "tool",
        "cutting"
    ],
    "sg:website":"www.suncoasttools.com",
    "wof:name":"Suncoast Precision Tools Inc",
    "wof:placetype":"venue"
},
  "geometry": {"coordinates":[-82.742729,27.875946],"type":"Point"}
}