{
  "type": "Feature",
  "properties": {
    "addr:full":"941 W Fairbanks Ave Winter Park FL 32789",
    "addr:housenumber":"941",
    "addr:postcode":"32789",
    "addr:street":"W Fairbanks Ave",
    "iso:country":"US",
    "sg:address":"941 W Fairbanks Ave",
    "sg:city":"Winter Park",
    "sg:classifiers":[
        {
            "category":"Retail",
            "subcategory":"Auto Rental",
            "type":"Services"
        }
    ],
    "sg:phone":"+1 407 644 0374",
    "sg:postcode":"32789",
    "sg:province":"FL",
    "sg:tags":[
        "passenger",
        "car"
    ],
    "wof:name":"Hertz",
    "wof:placetype":"venue"
},
  "geometry": {"coordinates":[-81.362652,28.593117],"type":"Point"}
}