{
  "type": "Feature",
  "properties": {
    "addr:full":"4430 Tamiami Trl Port Charlotte FL 33980",
    "addr:housenumber":"4430",
    "addr:postcode":"33980",
    "addr:street":"Tamiami Trl",
    "iso:country":"US",
    "sg:address":"4430 Tamiami Trl",
    "sg:city":"Port Charlotte",
    "sg:classifiers":[
        {
            "category":"Home & Garden",
            "subcategory":"Furniture",
            "type":"Retail Goods"
        }
    ],
    "sg:phone":"+1 941 629 7534",
    "sg:postcode":"33980",
    "sg:province":"FL",
    "sg:website":"www.rhodesfurniture.com",
    "wof:name":"Rhodes Furniture",
    "wof:placetype":"venue"
},
  "geometry": {"coordinates":[-82.078638,26.967822],"type":"Point"}
}