{
  "type": "Feature",
  "properties": {
    "iso:country":"US",
    "sg:address":"13638 120th Ln",
    "sg:city":"Largo",
    "sg:classifiers":[
        {
            "category":"Building & Trades",
            "subcategory":"Landscaping Services",
            "type":"Services"
        }
    ],
    "sg:phone":"+1 727 585 5173",
    "sg:postcode":"33778",
    "sg:province":"FL",
    "sg:tags":[
        "landscape",
        "contractor"
    ],
    "wof:name":"Willie Hillmon Lawn Service",
    "wof:placetype":"venue"
},
  "geometry": {"coordinates":[-82.805288,27.896862],"type":"Point"}
}