{
  "type": "Feature",
  "properties": {
    "iso:country":"US",
    "sg:address":"1107 S Main St",
    "sg:city":"Gainesville",
    "sg:classifiers":[
        {
            "category":"Retail",
            "subcategory":"Auto Repair",
            "type":"Services"
        }
    ],
    "sg:phone":"+1 352 372 0494",
    "sg:postcode":"32601",
    "sg:province":"FL",
    "sg:tags":[
        "repairing",
        "automobile"
    ],
    "wof:name":"Butler's Radiator Svc",
    "wof:placetype":"venue"
},
  "geometry": {"coordinates":[-82.325861,29.640729],"type":"Point"}
}