{
  "type": "Feature",
  "properties": {
    "iso:country":"US",
    "sg:address":"880 Carillon Pkwy",
    "sg:city":"St Petersburg",
    "sg:classifiers":[
        {
            "category":"Personal",
            "subcategory":"Shoe Repair & Shine",
            "type":"Services"
        }
    ],
    "sg:phone":"+1 727 567 5534",
    "sg:postcode":"33716",
    "sg:province":"FL",
    "sg:tags":[
        "repairing",
        "boot"
    ],
    "wof:name":"Old Time Shoe Shine & Repair",
    "wof:placetype":"venue"
},
  "geometry": {"coordinates":[-82.666636,27.887555],"type":"Point"}
}