{
  "type": "Feature",
  "properties": {
    "addr:full":"1353 Atlantic Blvd Neptune Beach FL 32233",
    "addr:housenumber":"1353",
    "addr:postcode":"32233",
    "addr:street":"Atlantic Blvd",
    "iso:country":"US",
    "sg:address":"1353 Atlantic Blvd",
    "sg:city":"Neptune Beach",
    "sg:classifiers":[
        {
            "category":"Autos & Motor Vehicles",
            "subcategory":"Auto Supplies",
            "type":"Retail Goods"
        }
    ],
    "sg:phone":"+1 904 242 4003",
    "sg:postcode":"32233",
    "sg:province":"FL",
    "sg:tags":[
        "tire"
    ],
    "wof:name":"Tire Kingdom",
    "wof:placetype":"venue"
},
  "geometry": {"coordinates":[-81.423914,30.32433],"type":"Point"}
}