{
  "type": "Feature",
  "properties": {
    "addr:full":"1342 Colonial Blvd Fort Myers FL 33907",
    "addr:housenumber":"1342",
    "addr:postcode":"33907",
    "addr:street":"Colonial Blvd",
    "iso:country":"US",
    "sg:address":"1342 Colonial Blvd",
    "sg:city":"Fort Myers",
    "sg:classifiers":[
        {
            "category":"Professional",
            "subcategory":"Engineering",
            "type":"Services"
        },
        {
            "category":"Manufacturing",
            "subcategory":"Metals",
            "type":"Manufacturing & Wholesale Goods"
        }
    ],
    "sg:phone":"+1 239 277 1182",
    "sg:postcode":"33907",
    "sg:province":"FL",
    "sg:tags":[
        "blast",
        "works",
        "furnace",
        "engineer"
    ],
    "wof:name":"Spectrum Engineering Inc",
    "wof:placetype":"venue"
},
  "geometry": {"coordinates":[-81.890456,26.596435],"type":"Point"}
}