{
  "type": "Feature",
  "properties": {
    "iso:country":"US",
    "sg:address":"6262 Bird Rd Ste 2I",
    "sg:city":"Miami",
    "sg:classifiers":[
        {
            "category":"Health Services",
            "subcategory":"Doctor",
            "type":"Services"
        }
    ],
    "sg:phone":"+1 305 663 7979",
    "sg:postcode":"33155",
    "sg:province":"FL",
    "sg:tags":[
        "psychiatrist"
    ],
    "wof:name":"Perez-Noy Antonio L MD",
    "wof:placetype":"venue"
},
  "geometry": {"coordinates":[-80.295787,25.733479],"type":"Point"}
}