{
  "type": "Feature",
  "properties": {
    "iso:country":"US",
    "sg:address":"1416 Pope Pl",
    "sg:city":"Lutz",
    "sg:classifiers":[
        {
            "category":"Building & Trades",
            "subcategory":"Construction",
            "type":"Services"
        }
    ],
    "sg:phone":"+1 813 949 3933",
    "sg:postcode":"33549",
    "sg:province":"FL",
    "sg:tags":[
        "painter"
    ],
    "wof:name":"Burton's Painting Svc",
    "wof:placetype":"venue"
},
  "geometry": {"coordinates":[-82.4453,28.130485],"type":"Point"}
}