{
  "type": "Feature",
  "properties": {
    "iso:country":"US",
    "sg:address":"7379 State Hwy 95A",
    "sg:city":"Molino",
    "sg:classifiers":[
        {
            "category":"Professional",
            "subcategory":"Management & Consulting",
            "type":"Services"
        }
    ],
    "sg:phone":"+1 850 587 6065",
    "sg:postcode":"32577",
    "sg:province":"FL",
    "sg:tags":[
        "marketing",
        "program"
    ],
    "wof:name":"Variety Marketing",
    "wof:placetype":"venue"
},
  "geometry": {"coordinates":[-87.347865,30.738105],"type":"Point"}
}