{
  "type": "Feature",
  "properties": {
    "iso:country":"US",
    "sg:address":"10850 W Flagler St",
    "sg:city":"Miami",
    "sg:classifiers":[
        {
            "category":"Health Services",
            "subcategory":"Clinic",
            "type":"Services"
        }
    ],
    "sg:phone":"+1 305 456 0962",
    "sg:postcode":"33174",
    "sg:province":"FL",
    "wof:name":"First Rate Medical Corp",
    "wof:placetype":"venue"
},
  "geometry": {"coordinates":[-80.371751,25.768334],"type":"Point"}
}