{
  "type": "Feature",
  "properties": {
    "iso:country":"US",
    "sg:address":"84 Hill Ave NW",
    "sg:city":"Fort Walton Beach",
    "sg:classifiers":[
        {
            "category":"Manufacturing",
            "subcategory":"Electronics",
            "type":"Manufacturing & Wholesale Goods"
        }
    ],
    "sg:phone":"+1 850 244 0043",
    "sg:postcode":"32548",
    "sg:province":"FL",
    "sg:tags":[
        "electrical",
        "component",
        "electronic",
        "mfg"
    ],
    "wof:name":"Keltec Operations",
    "wof:placetype":"venue"
},
  "geometry": {"coordinates":[-86.667331,30.418053],"type":"Point"}
}