{
  "type": "Feature",
  "properties": {
    "addr:full":"8207 SW 124th St Miami FL 33156",
    "addr:housenumber":"8207",
    "addr:postcode":"33156",
    "addr:street":"Sw 124Th St",
    "iso:country":"US",
    "sg:address":"8207 SW 124th St",
    "sg:city":"Miami",
    "sg:classifiers":[
        {
            "category":"Insurance",
            "subcategory":"Insurance Agent",
            "type":"Services"
        }
    ],
    "sg:phone":"+1 305 254 1653",
    "sg:postcode":"33156",
    "sg:province":"FL",
    "wof:name":"Allstate",
    "wof:placetype":"venue"
},
  "geometry": {"coordinates":[-80.326672,25.655289],"type":"Point"}
}