{
  "type": "Feature",
  "properties": {
    "iso:country":"US",
    "sg:address":"10262 SW 177th St",
    "sg:city":"Miami",
    "sg:classifiers":[
        {
            "category":"Wholesale",
            "subcategory":"Groceries",
            "type":"Manufacturing & Wholesale Goods"
        }
    ],
    "sg:phone":"+1 305 252 5240",
    "sg:postcode":"33157",
    "sg:province":"FL",
    "sg:tags":[
        "gourmet",
        "food"
    ],
    "wof:name":"Gourmet Carla Southern",
    "wof:placetype":"venue"
},
  "geometry": {"coordinates":[-80.35772299999999,25.604967],"type":"Point"}
}