{
  "type": "Feature",
  "properties": {
    "addr:full":"21005 Immokalee Rd Naples FL 34120",
    "addr:postcode":"21005;34120",
    "addr:street":"Immokalee Rd",
    "iso:country":"US",
    "sg:address":"21005 Immokalee Rd",
    "sg:city":"Naples",
    "sg:classifiers":[
        {
            "category":"Farming",
            "subcategory":"Farm",
            "type":"Manufacturing & Wholesale Goods"
        }
    ],
    "sg:phone":"+1 239 348 9141",
    "sg:postcode":"34120",
    "sg:province":"FL",
    "sg:tags":[
        "crop",
        "general"
    ],
    "wof:name":"Keri Farms",
    "wof:placetype":"venue"
},
  "geometry": {"coordinates":[-81.563496,26.366313],"type":"Point"}
}