{
  "type": "Feature",
  "properties": {
    "iso:country":"US",
    "sg:address":"21589 Yellowstone Park Dr",
    "sg:city":"Boca Raton",
    "sg:classifiers":[
        {
            "category":"Building & Trades",
            "subcategory":"Construction",
            "type":"Services"
        }
    ],
    "sg:phone":"+1 561 852 4298",
    "sg:postcode":"33428",
    "sg:province":"FL",
    "sg:tags":[
        "handyman"
    ],
    "wof:name":"M & M Handyman Inc",
    "wof:placetype":"venue"
},
  "geometry": {"coordinates":[-80.19781999999999,26.356961],"type":"Point"}
}