{
  "type": "Feature",
  "properties": {
    "addr:full":"16375 San Edmundo Rd Punta Gorda FL 33955",
    "addr:housenumber":"16375",
    "addr:postcode":"33955",
    "addr:street":"San Edmundo Rd",
    "iso:country":"US",
    "sg:address":"16375 San Edmundo Rd",
    "sg:city":"Punta Gorda",
    "sg:classifiers":[
        {
            "category":"Building & Trades",
            "subcategory":"Cleaning & Sanitation",
            "type":"Services"
        }
    ],
    "sg:phone":"+1 941 505 8794",
    "sg:postcode":"33955",
    "sg:province":"FL",
    "wof:name":"Mr Window",
    "wof:placetype":"venue"
},
  "geometry": {"coordinates":[-82.04221699999999,26.798768],"type":"Point"}
}