{
  "type": "Feature",
  "properties": {
    "addr:full":"18690 NE 22nd Ave Miami FL 33180",
    "addr:housenumber":"18690",
    "addr:postcode":"33180",
    "addr:street":"Ne 22Nd Ave",
    "iso:country":"US",
    "sg:address":"18690 NE 22nd Ave",
    "sg:city":"Miami",
    "sg:classifiers":[
        {
            "category":"Banks & Credit Unions",
            "subcategory":"Investment Brokerage",
            "type":"Services"
        }
    ],
    "sg:phone":"+1 305 932 8768",
    "sg:postcode":"33180",
    "sg:province":"FL",
    "sg:tags":[
        "advisory"
    ],
    "wof:name":"Financial Systems Mgt 2 Corp",
    "wof:placetype":"venue"
},
  "geometry": {"coordinates":[-80.156852,25.948054],"type":"Point"}
}