{
  "type": "Feature",
  "properties": {
    "addr:full":"7271 Cobiac Dr Saint James City FL 33956",
    "addr:housenumber":"7271",
    "addr:postcode":"33956",
    "addr:street":"Cobiac Dr",
    "iso:country":"US",
    "sg:address":"7271 Cobiac Dr",
    "sg:city":"Saint James City",
    "sg:classifiers":[
        {
            "category":"Freight",
            "type":"Transportation"
        }
    ],
    "sg:phone":"+1 239 283 0331",
    "sg:postcode":"33956",
    "sg:province":"FL",
    "sg:tags":[
        "operator",
        "trucking"
    ],
    "wof:name":"Chamberlin Trucking Inc",
    "wof:placetype":"venue"
},
  "geometry": {"coordinates":[-82.109183,26.565449],"type":"Point"}
}