{
  "type": "Feature",
  "properties": {
    "addr:full":"34 N Garden Ave Clearwater FL 33755",
    "addr:housenumber":"34",
    "addr:postcode":"33755",
    "addr:street":"N Garden Ave",
    "iso:country":"US",
    "sg:address":"34 N Garden Ave",
    "sg:city":"Clearwater",
    "sg:classifiers":[
        {
            "category":"Professional",
            "subcategory":"Art Services",
            "type":"Services"
        }
    ],
    "sg:phone":"+1 727 461 4282",
    "sg:postcode":"33755",
    "sg:province":"FL",
    "sg:tags":[
        "photographer"
    ],
    "sg:website":"www.rileyfilms.com",
    "wof:name":"Riley Arnold Productions",
    "wof:placetype":"venue"
},
  "geometry": {"coordinates":[-82.79877500000001,27.966561],"type":"Point"}
}