{
  "type": "Feature",
  "properties": {
    "addr:full":"255 Lake Ln De Bary FL 32713",
    "addr:housenumber":"255",
    "addr:postcode":"32713",
    "addr:street":"Lake Ln De",
    "iso:country":"US",
    "sg:address":"255 Lake Ln",
    "sg:city":"De Bary",
    "sg:classifiers":[
        {
            "category":"Building & Trades",
            "subcategory":"Construction",
            "type":"Services"
        }
    ],
    "sg:phone":"+1 386 668 8978",
    "sg:postcode":"32713",
    "sg:province":"FL",
    "sg:tags":[
        "house"
    ],
    "wof:name":"Professional Quality Cnstr",
    "wof:placetype":"venue"
},
  "geometry": {"coordinates":[-81.29339299999999,28.88562],"type":"Point"}
}