{
  "type": "Feature",
  "properties": {
    "iso:country":"US",
    "sg:address":"6194 Edgewater Dr",
    "sg:city":"Orlando",
    "sg:classifiers":[
        {
            "category":"Restaurant",
            "type":"Food & Drink"
        }
    ],
    "sg:menulink":"http://www.allmenus.com/fl/orlando/48380-sobiks-subs/menu/",
    "sg:phone":"+1 407 304 3500",
    "sg:postcode":"32810",
    "sg:province":"FL",
    "sg:tags":[
        "wrap",
        "american",
        "sandwich"
    ],
    "wof:name":"Sobik's Subs",
    "wof:placetype":"venue"
},
  "geometry": {"coordinates":[-81.419141,28.613174],"type":"Point"}
}