{
  "type": "Feature",
  "properties": {
    "iso:country":"US",
    "sg:address":"9601 SW 142nd Ave",
    "sg:city":"Miami",
    "sg:classifiers":[
        {
            "category":"Wholesale",
            "subcategory":"Plants",
            "type":"Manufacturing & Wholesale Goods"
        }
    ],
    "sg:phone":"+1 305 385 3115",
    "sg:postcode":"33186",
    "sg:province":"FL",
    "sg:tags":[
        "plants-wholesale"
    ],
    "wof:name":"O D Cane Inc",
    "wof:placetype":"venue"
},
  "geometry": {"coordinates":[-80.42044799999999,25.677679],"type":"Point"}
}