{
  "type": "Feature",
  "properties": {
    "addr:full":"1107 US Hwy 301 Palmetto FL 34221",
    "addr:housenumber":"1107",
    "addr:postcode":"34221",
    "addr:street":"Us Hwy 301",
    "iso:country":"US",
    "sg:address":"1107 US Hwy 301",
    "sg:city":"Palmetto",
    "sg:classifiers":[
        {
            "category":"Food & Beverages",
            "subcategory":"Specialty",
            "type":"Retail Goods"
        }
    ],
    "sg:phone":"+1 941 729 1406",
    "sg:postcode":"34221",
    "sg:province":"FL",
    "sg:tags":[
        "health",
        "diet"
    ],
    "wof:name":"Natural Health Resource Center",
    "wof:placetype":"venue"
},
  "geometry": {"coordinates":[-82.55308599999999,27.521276],"type":"Point"}
}