{
  "type": "Feature",
  "properties": {
    "iso:country":"US",
    "sg:address":"1811 NE 142nd St",
    "sg:city":"North Miami",
    "sg:classifiers":[
        {
            "category":"Real Estate",
            "subcategory":"Real Estate Agent",
            "type":"Services"
        }
    ],
    "sg:phone":"+1 305 787 0991",
    "sg:postcode":"33181",
    "sg:province":"FL",
    "sg:website":"www.easternatlantic.net",
    "wof:name":"Eastern Atlantic Realty",
    "wof:placetype":"venue"
},
  "geometry": {"coordinates":[-80.161798,25.906812],"type":"Point"}
}