{
  "type": "Feature",
  "properties": {
    "iso:country":"US",
    "sg:address":"3801 N University Dr",
    "sg:city":"Sunrise",
    "sg:classifiers":[
        {
            "category":"Travel",
            "subcategory":"Travel Agent",
            "type":"Entertainment"
        }
    ],
    "sg:phone":"+1 954 748 7544",
    "sg:postcode":"33351",
    "sg:province":"FL",
    "sg:tags":[
        "agency",
        "bureau"
    ],
    "wof:name":"Travel Time USA",
    "wof:placetype":"venue"
},
  "geometry": {"coordinates":[-80.256023,26.171187],"type":"Point"}
}