{
  "type": "Feature",
  "properties": {
    "iso:country":"US",
    "sg:address":"2311 16th Ave W",
    "sg:city":"Bradenton",
    "sg:classifiers":[
        {
            "category":"Restaurant",
            "type":"Food & Drink"
        }
    ],
    "sg:phone":"+1 941 749 0408",
    "sg:postcode":"34205",
    "sg:province":"FL",
    "sg:tags":[
        "eating"
    ],
    "wof:name":"Wings & Things",
    "wof:placetype":"venue"
},
  "geometry": {"coordinates":[-82.586625,27.485645],"type":"Point"}
}