{
  "type": "Feature",
  "properties": {
    "iso:country":"US",
    "sg:address":"6741 Coral Way Suite 19",
    "sg:city":"Miami",
    "sg:classifiers":[
        {
            "category":"Professional",
            "subcategory":"Accounting & Tax Preparation",
            "type":"Services"
        }
    ],
    "sg:phone":"+1 305 267 4890",
    "sg:postcode":"33155",
    "sg:province":"FL",
    "sg:tags":[
        "bookkeeping"
    ],
    "sg:website":"http://www.feliutax.com",
    "wof:name":"Feliu Bookkeeping & Taxes Corp",
    "wof:placetype":"venue"
},
  "geometry": {"coordinates":[-80.304236,25.74803],"type":"Point"}
}