{
  "type": "Feature",
  "properties": {
    "addr:full":"2713 24th St N St Petersburg FL 33713",
    "addr:housenumber":"2713",
    "addr:postcode":"33713",
    "addr:street":"24Th St N",
    "iso:country":"US",
    "sg:address":"2713 24th St N",
    "sg:city":"St Petersburg",
    "sg:classifiers":[
        {
            "category":"Wholesale",
            "subcategory":"Scrap",
            "type":"Manufacturing & Wholesale Goods"
        }
    ],
    "sg:phone":"+1 727 896 1088",
    "sg:postcode":"33713",
    "sg:province":"FL",
    "sg:tags":[
        "recycling",
        "refuse",
        "material",
        "center",
        "system"
    ],
    "wof:name":"A-1 Paper Recyclers",
    "wof:placetype":"venue"
},
  "geometry": {"coordinates":[-82.665194,27.79644],"type":"Point"}
}