{
  "type": "Feature",
  "properties": {
    "addr:full":"5230 Saint Ambrose Church Rd Elkton FL 32033",
    "addr:housenumber":"5230",
    "addr:postcode":"32033",
    "addr:street":"Saint Ambrose Church Rd",
    "iso:country":"US",
    "sg:address":"5230 Saint Ambrose Church Rd",
    "sg:city":"Elkton",
    "sg:classifiers":[
        {
            "category":"Manufacturing",
            "subcategory":"Food",
            "type":"Manufacturing & Wholesale Goods"
        }
    ],
    "sg:phone":"+1 904 692 2303",
    "sg:postcode":"32033",
    "sg:province":"FL",
    "sg:tags":[
        "product"
    ],
    "wof:name":"Eugene P & Brenda J Povia",
    "wof:placetype":"venue"
},
  "geometry": {"coordinates":[-81.460401,29.784002],"type":"Point"}
}