{
  "type": "Feature",
  "properties": {
    "iso:country":"US",
    "sg:address":"300 SW 107th Ave Ste 204",
    "sg:city":"Miami",
    "sg:classifiers":[
        {
            "category":"Professional",
            "subcategory":"Lawyer & Legal Services",
            "type":"Services"
        }
    ],
    "sg:phone":"+1 305 485 9700",
    "sg:postcode":"33174",
    "sg:province":"FL",
    "wof:name":"Torres Michelle G PA",
    "wof:placetype":"venue"
},
  "geometry": {"coordinates":[-80.36895199999999,25.765769],"type":"Point"}
}