{
  "type": "Feature",
  "properties": {
    "iso:country":"US",
    "sg:address":"241 Lake Ella Dr",
    "sg:city":"Tallahassee",
    "sg:classifiers":[
        {
            "category":"Organizations",
            "subcategory":"Community Association",
            "type":"Services"
        }
    ],
    "sg:phone":"+1 850 224 8838",
    "sg:postcode":"32303",
    "sg:province":"FL",
    "sg:tags":[
        "military"
    ],
    "wof:name":"Vietnam Veterans Of America",
    "wof:placetype":"venue"
},
  "geometry": {"coordinates":[-84.28048,30.462479],"type":"Point"}
}