{
  "type": "Feature",
  "properties": {
    "addr:full":"8256 Exchange Dr Orlando FL 32809",
    "addr:housenumber":"8256",
    "addr:postcode":"32809",
    "addr:street":"Exchange Dr",
    "iso:country":"US",
    "sg:address":"8256 Exchange Dr",
    "sg:city":"Orlando",
    "sg:classifiers":[
        {
            "category":"Education",
            "subcategory":"Special Training",
            "type":"Public Place"
        }
    ],
    "sg:phone":"+1 407 851 4860",
    "sg:postcode":"32809",
    "sg:province":"FL",
    "sg:tags":[
        "protection",
        "police"
    ],
    "wof:name":"Pan AM",
    "wof:placetype":"venue"
},
  "geometry": {"coordinates":[-81.413607,28.446025],"type":"Point"}
}