{
  "type": "Feature",
  "properties": {
    "iso:country":"US",
    "sg:address":"2320 SW 127th Ave",
    "sg:city":"Miami",
    "sg:classifiers":[
        {
            "category":"Travel",
            "subcategory":"Travel Agent",
            "type":"Entertainment"
        }
    ],
    "sg:phone":"+1 305 552 5497",
    "sg:postcode":"33175",
    "sg:province":"FL",
    "sg:tags":[
        "agency",
        "services-commercial"
    ],
    "wof:name":"Baseball Journeys Inc",
    "wof:placetype":"venue"
},
  "geometry": {"coordinates":[-80.40025900000001,25.746067],"type":"Point"}
}