{
  "type": "Feature",
  "properties": {
    "iso:country":"US",
    "sg:address":"1500 N University Dr",
    "sg:city":"Pompano Beach",
    "sg:classifiers":[
        {
            "category":"Building & Trades",
            "subcategory":"Electrical",
            "type":"Services"
        }
    ],
    "sg:phone":"+1 954 755 4702",
    "sg:postcode":"33071",
    "sg:province":"FL",
    "sg:tags":[
        "development",
        "computer",
        "software"
    ],
    "wof:name":"International Data Solution",
    "wof:placetype":"venue"
},
  "geometry": {"coordinates":[-80.25307100000001,26.249447],"type":"Point"}
}