{
  "type": "Feature",
  "properties": {
    "iso:country":"US",
    "sg:address":"3698 W Oakland Park Blvd",
    "sg:city":"Lauderdale Lakes",
    "sg:classifiers":[
        {
            "category":"Building & Trades",
            "subcategory":"Equipment Rental",
            "type":"Services"
        }
    ],
    "sg:phone":"+1 954 717 1723",
    "sg:postcode":"33311",
    "sg:province":"FL",
    "sg:tags":[
        "yard"
    ],
    "wof:name":"Color Tyme",
    "wof:placetype":"venue"
},
  "geometry": {"coordinates":[-80.198695,26.165257],"type":"Point"}
}