{
  "type": "Feature",
  "properties": {
    "addr:full":"2003 Sunset Dr Miami Beach FL 33140",
    "addr:housenumber":"2003",
    "addr:postcode":"33140",
    "addr:street":"Sunset Dr",
    "iso:country":"US",
    "sg:address":"2003 Sunset Dr",
    "sg:city":"Miami Beach",
    "sg:classifiers":[
        {
            "category":"Real Estate",
            "subcategory":"Real Estate Operator",
            "type":"Services"
        }
    ],
    "sg:phone":"+1 305 538 1638",
    "sg:postcode":"33140",
    "sg:province":"FL",
    "sg:tags":[
        "property",
        "lessor"
    ],
    "wof:name":"Sunset Islnds 3/4 Prprty Ownrs",
    "wof:placetype":"venue"
},
  "geometry": {"coordinates":[-80.141368,25.795833],"type":"Point"}
}