{
  "type": "Feature",
  "properties": {
    "addr:full":"218 Pelham Rd Fort Walton Bch FL 32547",
    "addr:housenumber":"218",
    "addr:postcode":"32547",
    "addr:street":"Pelham Rd",
    "iso:country":"US",
    "sg:address":"218 Pelham Rd",
    "sg:city":"Fort Walton Bch",
    "sg:classifiers":[
        {
            "category":"Building & Trades",
            "subcategory":"Cleaning & Sanitation",
            "type":"Services"
        }
    ],
    "sg:phone":"+1 850 368 8216",
    "sg:postcode":"32547",
    "sg:province":"FL",
    "sg:tags":[
        "janitor"
    ],
    "wof:name":"Koalaty Cleaning",
    "wof:placetype":"venue"
},
  "geometry": {"coordinates":[-86.635183,30.434747],"type":"Point"}
}