{
  "type": "Feature",
  "properties": {
    "addr:full":"1870 51st Ter SW Naples FL 34116",
    "addr:housenumber":"1870",
    "addr:postcode":"34116",
    "addr:street":"51St Ter Sw",
    "iso:country":"US",
    "sg:address":"1870 51st Ter SW",
    "sg:city":"Naples",
    "sg:classifiers":[
        {
            "category":"Real Estate",
            "subcategory":"Architect",
            "type":"Services"
        }
    ],
    "sg:phone":"+1 239 455 1618",
    "sg:postcode":"34116",
    "sg:province":"FL",
    "sg:tags":[
        "building",
        "construction"
    ],
    "wof:name":"Mike Byrnes Home Svc",
    "wof:placetype":"venue"
},
  "geometry": {"coordinates":[-81.709748,26.194268],"type":"Point"}
}