{
  "type": "Feature",
  "properties": {
    "addr:full":"2201 S Carnegie Dr Inverness FL 34450",
    "addr:housenumber":"2201",
    "addr:postcode":"34450",
    "addr:street":"S Carnegie Dr",
    "iso:country":"US",
    "sg:address":"2201 S Carnegie Dr",
    "sg:city":"Inverness",
    "sg:classifiers":[
        {
            "category":"Shopping",
            "subcategory":"Bicycles & Sporting Goods",
            "type":"Retail Goods"
        }
    ],
    "sg:phone":"+1 352 637 5454",
    "sg:postcode":"34450",
    "sg:province":"FL",
    "sg:tags":[
        "tackle",
        "fishing"
    ],
    "wof:name":"Codella's Heritage Sporting",
    "wof:placetype":"venue"
},
  "geometry": {"coordinates":[-82.30962700000001,28.829029],"type":"Point"}
}