{
  "type": "Feature",
  "properties": {
    "addr:full":"29825 US Hwy 19 Clearwater FL 33761",
    "addr:postcode":"29825;33761",
    "addr:street":"Us Hwy 19",
    "iso:country":"US",
    "sg:address":"29825 US Hwy 19",
    "sg:city":"Clearwater",
    "sg:classifiers":[
        {
            "category":"Shopping",
            "subcategory":"Computers & Home Electronics",
            "type":"Retail Goods"
        }
    ],
    "sg:phone":"+1 727 787 4500",
    "sg:postcode":"33761",
    "sg:province":"FL",
    "sg:tags":[
        "equipment",
        "dealer"
    ],
    "sg:website":"www.casinomars.com",
    "wof:name":"Computer Installers Inc",
    "wof:placetype":"venue"
},
  "geometry": {"coordinates":[-82.738416,28.042872],"type":"Point"}
}