{
  "type": "Feature",
  "properties": {
    "iso:country":"US",
    "sg:address":"8637 Tourmaline Blvd",
    "sg:city":"Boynton Beach",
    "sg:classifiers":[
        {
            "category":"Wholesale",
            "subcategory":"Farm Supplies",
            "type":"Manufacturing & Wholesale Goods"
        }
    ],
    "sg:phone":"+1 561 369 7620",
    "sg:postcode":"33472",
    "sg:province":"FL",
    "sg:tags":[
        "feed"
    ],
    "wof:name":"Fairlane Farms Feed Mill Inc",
    "wof:placetype":"venue"
},
  "geometry": {"coordinates":[-80.14062699999999,26.545977],"type":"Point"}
}