{
  "type": "Feature",
  "properties": {
    "iso:country":"US",
    "sg:address":"15941 Pines Blvd",
    "sg:city":"Hollywood",
    "sg:classifiers":[
        {
            "category":"Restaurant",
            "type":"Food & Drink"
        }
    ],
    "sg:menulink":"http://www.allmenus.com/fl/miramar-pembroke-pines/15984-las-vegas-cuban-cuisine/menu/",
    "sg:phone":"+1 954 443 7440",
    "sg:postcode":"33027",
    "sg:province":"FL",
    "sg:tags":[
        "cuban"
    ],
    "wof:name":"Las Vegas Cuban Cuisine",
    "wof:placetype":"venue"
},
  "geometry": {"coordinates":[-80.360528,26.007767],"type":"Point"}
}