{
  "type": "Feature",
  "properties": {
    "iso:country":"US",
    "sg:address":"6751 Nalle Grade Rd",
    "sg:city":"Fort Myers",
    "sg:classifiers":[
        {
            "category":"Building & Trades",
            "subcategory":"Construction",
            "type":"Services"
        }
    ],
    "sg:phone":"+1 239 543 4846",
    "sg:postcode":"33917",
    "sg:province":"FL",
    "sg:tags":[
        "steel",
        "erection",
        "structural"
    ],
    "wof:name":"C & L Contracting Service Inc",
    "wof:placetype":"venue"
},
  "geometry": {"coordinates":[-81.858131,26.755294],"type":"Point"}
}