{
  "type": "Feature",
  "properties": {
    "iso:country":"US",
    "sg:address":"1219 Stetson St",
    "sg:city":"Orlando",
    "sg:classifiers":[
        {
            "category":"Professional",
            "subcategory":"Printing & Photocopies",
            "type":"Services"
        }
    ],
    "sg:phone":"+1 407 841 6420",
    "sg:postcode":"32804",
    "sg:province":"FL",
    "sg:tags":[
        "photographers-commercial"
    ],
    "wof:name":"Petrey, John",
    "wof:placetype":"venue"
},
  "geometry": {"coordinates":[-81.39667900000001,28.568309],"type":"Point"}
}