{
  "type": "Feature",
  "properties": {
    "iso:country":"US",
    "sg:address":"2322 EDWARDS AVE",
    "sg:city":"JACKSONVILLE",
    "sg:classifiers":[
        {
            "category":"Building & Trades",
            "subcategory":"Plumbing",
            "type":"Services"
        }
    ],
    "sg:phone":"+1 904 384 4101",
    "sg:postcode":"32254",
    "sg:province":"FL",
    "sg:tags":[
        "plumber"
    ],
    "wof:name":"Certified Plumbing Contractors Inc.",
    "wof:placetype":"venue"
},
  "geometry": {"coordinates":[-81.701778,30.331603],"type":"Point"}
}