{
  "type": "Feature",
  "properties": {
    "addr:full":"14760 Lake Olive Dr Fort Myers FL 33919",
    "addr:housenumber":"14760",
    "addr:postcode":"33919",
    "addr:street":"Lake Olive Dr",
    "iso:country":"US",
    "sg:address":"14760 Lake Olive Dr",
    "sg:city":"Fort Myers",
    "sg:classifiers":[
        {
            "category":"Travel",
            "subcategory":"Travel Agent",
            "type":"Entertainment"
        }
    ],
    "sg:phone":"+1 239 481 8088",
    "sg:postcode":"33919",
    "sg:province":"FL",
    "sg:tags":[
        "agency"
    ],
    "wof:name":"Sailaway Cruises",
    "wof:placetype":"venue"
},
  "geometry": {"coordinates":[-81.90470000000001,26.529267],"type":"Point"}
}