{
  "type": "Feature",
  "properties": {
    "iso:country":"US",
    "sg:address":"3601 Trout Ave",
    "sg:city":"Fruitland Park",
    "sg:classifiers":[
        {
            "category":"Professional",
            "subcategory":"Management & Consulting",
            "type":"Services"
        }
    ],
    "sg:phone":"+1 352 365 0052",
    "sg:postcode":"34731",
    "sg:province":"FL",
    "sg:tags":[
        "business"
    ],
    "wof:name":"W J R Assoc Inc",
    "wof:placetype":"venue"
},
  "geometry": {"coordinates":[-81.892624,28.848613],"type":"Point"}
}