{
  "type": "Feature",
  "properties": {
    "iso:country":"US",
    "sg:address":"12689 59th St N",
    "sg:city":"West Palm Beach",
    "sg:classifiers":[
        {
            "category":"Freight",
            "type":"Transportation"
        }
    ],
    "sg:phone":"+1 561 791 7396",
    "sg:postcode":"33411",
    "sg:province":"FL",
    "sg:tags":[
        "operator",
        "local",
        "trucking"
    ],
    "wof:name":"Nancys Trucking Company",
    "wof:placetype":"venue"
},
  "geometry": {"coordinates":[-80.242161,26.76438],"type":"Point"}
}