{
  "type": "Feature",
  "properties": {
    "iso:country":"US",
    "sg:address":"2772 Monica Ln",
    "sg:city":"Palm Harbor",
    "sg:classifiers":[
        {
            "category":"Recreation",
            "type":"Entertainment"
        }
    ],
    "sg:phone":"+1 727 772 8133",
    "sg:postcode":"34684",
    "sg:province":"FL",
    "sg:tags":[
        "instruction",
        "yoga"
    ],
    "wof:name":"Shirley 'Shire' Eastin",
    "wof:placetype":"venue"
},
  "geometry": {"coordinates":[-82.733375,28.058997],"type":"Point"}
}