{
  "type": "Feature",
  "properties": {
    "iso:country":"US",
    "sg:address":"12165 Pembroke Rd",
    "sg:city":"Hollywood",
    "sg:classifiers":[
        {
            "category":"Restaurant",
            "type":"Food & Drink"
        }
    ],
    "sg:phone":"+1 954 450 9800",
    "sg:postcode":"33023",
    "sg:province":"FL",
    "sg:tags":[
        "shop",
        "sub"
    ],
    "wof:name":"Deli Boy Subs",
    "wof:placetype":"venue"
},
  "geometry": {"coordinates":[-80.307878,25.993362],"type":"Point"}
}