{
  "type": "Feature",
  "properties": {
    "iso:country":"US",
    "sg:address":"595 S. Federal Hwy, Ste 600",
    "sg:city":"Boca Raton",
    "sg:classifiers":[
        {
            "category":"Professional",
            "subcategory":"Computer Services",
            "type":"Services"
        }
    ],
    "sg:phone":"+1 877 562 2431",
    "sg:postcode":"33432",
    "sg:province":"FL",
    "sg:tags":[
        "location-as-a-service",
        "laas",
        "mobile",
        "wireless",
        "lbs",
        "location-based-services",
        "location",
        "presence",
        "mobile-middleware",
        "aggregation",
        "location-aware-applications"
    ],
    "sg:website":"http://www.loc-aid.com",
    "wof:name":"LOC-AID Technologies",
    "wof:placetype":"venue"
},
  "geometry": {"coordinates":[-80.08638999999999,26.345281],"type":"Point"}
}