{
  "type": "Feature",
  "properties": {
    "addr:full":"2580 Blanding Blvd Middleburg FL 32068",
    "addr:housenumber":"2580",
    "addr:postcode":"32068",
    "addr:street":"Blanding Blvd",
    "iso:country":"US",
    "sg:address":"2580 Blanding Blvd",
    "sg:city":"Middleburg",
    "sg:classifiers":[
        {
            "category":"Building & Trades",
            "subcategory":"Landscaping Services",
            "type":"Services"
        }
    ],
    "sg:phone":"+1 904 291 4685",
    "sg:postcode":"32068",
    "sg:province":"FL",
    "sg:tags":[
        "tree"
    ],
    "wof:name":"J & J Tree Experts Inc",
    "wof:placetype":"venue"
},
  "geometry": {"coordinates":[-81.86612100000001,30.068968],"type":"Point"}
}