{
  "type": "Feature",
  "properties": {
    "iso:country":"US",
    "sg:address":"9301 NE 6th Ave",
    "sg:city":"Miami Shores",
    "sg:classifiers":[
        {
            "category":"Professional",
            "subcategory":"Business Services",
            "type":"Services"
        }
    ],
    "sg:phone":"+1 305 751 1036",
    "sg:postcode":"33138",
    "sg:province":"FL",
    "sg:tags":[
        "reservation",
        "motel",
        "hotel"
    ],
    "wof:name":"Hoturvensa SA",
    "wof:placetype":"venue"
},
  "geometry": {"coordinates":[-80.18521699999999,25.861767],"type":"Point"}
}