{
  "type": "Feature",
  "properties": {
    "addr:full":"122 Country Club Dr Royal Palm Beach FL 33411",
    "addr:housenumber":"122",
    "addr:postcode":"33411",
    "addr:street":"Country Club Dr",
    "iso:country":"US",
    "sg:address":"122 Country Club Dr",
    "sg:city":"Royal Palm Beach",
    "sg:classifiers":[
        {
            "category":"Sports & Exercise",
            "subcategory":"Golf",
            "type":"Entertainment"
        }
    ],
    "sg:phone":"+1 561 793 1400",
    "sg:postcode":"33411",
    "sg:province":"FL",
    "sg:tags":[
        "course"
    ],
    "sg:website":"www.thevillagegolfclub.com",
    "wof:name":"Village Golf Club",
    "wof:placetype":"venue"
},
  "geometry": {"coordinates":[-80.227307,26.717375],"type":"Point"}
}