{
  "type": "Feature",
  "properties": {
    "iso:country":"US",
    "sg:address":"1570 Winkler Ave",
    "sg:city":"Fort Myers",
    "sg:classifiers":[
        {
            "category":"Personal",
            "subcategory":"Beauty Salon",
            "type":"Services"
        }
    ],
    "sg:phone":"+1 239 482 4247",
    "sg:postcode":"33901",
    "sg:province":"FL",
    "wof:name":"Designer Hair Salon",
    "wof:placetype":"venue"
},
  "geometry": {"coordinates":[-81.88104800000001,26.604513],"type":"Point"}
}