{
  "type": "Feature",
  "properties": {
    "addr:full":"14505 Commerce Way Ste 525 Hialeah FL 33016",
    "addr:housenumber":"14505",
    "addr:postcode":"33016",
    "addr:street":"Commerce Way Ste 525",
    "iso:country":"US",
    "sg:address":"14505 Commerce Way Ste 525",
    "sg:city":"Hialeah",
    "sg:classifiers":[
        {
            "category":"Real Estate",
            "subcategory":"Real Estate Services",
            "type":"Services"
        }
    ],
    "sg:phone":"+1 305 824 4672",
    "sg:postcode":"33016",
    "sg:province":"FL",
    "sg:tags":[
        "management",
        "property"
    ],
    "wof:name":"Cosmos Management Service",
    "wof:placetype":"venue"
},
  "geometry": {"coordinates":[-80.3283,25.9051],"type":"Point"}
}