{
  "type": "Feature",
  "properties": {
    "iso:country":"US",
    "sg:address":"1898 Highway 177A",
    "sg:city":"Bonifay",
    "sg:classifiers":[
        {
            "category":"Personal",
            "subcategory":"Beauty Salon",
            "type":"Services"
        }
    ],
    "sg:phone":"+1 850 547 5885",
    "sg:postcode":"32425",
    "sg:province":"FL",
    "wof:name":"Liz's Country Hair Care",
    "wof:placetype":"venue"
},
  "geometry": {"coordinates":[-85.76884,30.862644],"type":"Point"}
}