{
  "type": "Feature",
  "properties": {
    "iso:country":"US",
    "sg:address":"3174 S Atlantic Ave",
    "sg:city":"Daytona Beach",
    "sg:classifiers":[
        {
            "category":"Personal",
            "subcategory":"Beauty Salon",
            "type":"Services"
        }
    ],
    "sg:phone":"+1 386 761 1811",
    "sg:postcode":"32118",
    "sg:province":"FL",
    "sg:tags":[
        "shop"
    ],
    "wof:name":"Fran's Hair Fashions",
    "wof:placetype":"venue"
},
  "geometry": {"coordinates":[-80.975877,29.163716],"type":"Point"}
}