{
  "type": "Feature",
  "properties": {
    "iso:country":"US",
    "sg:address":"5311 Barna Ave",
    "sg:city":"Titusville",
    "sg:classifiers":[
        {
            "category":"Place Of Worship",
            "subcategory":"Church",
            "type":"Public Place"
        },
        {
            "category":"Place Of Worship",
            "type":"Public Place"
        },
        {
            "category":"Place Of Worship",
            "subcategory":"Shrine",
            "type":"Public Place"
        }
    ],
    "sg:phone":"+1 321 269 4033",
    "sg:postcode":"32780",
    "sg:province":"FL",
    "sg:tags":[
        "churches-baptist-free",
        "churches-baptist"
    ],
    "wof:name":"First Free Will Baptist Church",
    "wof:placetype":"venue"
},
  "geometry": {"coordinates":[-80.822665,28.543534],"type":"Point"}
}