{
  "type": "Feature",
  "properties": {
    "iso:country":"US",
    "sg:address":"9100 South Dadeland Boulevard Suite 1500",
    "sg:city":"Miami",
    "sg:classifiers":[
        {
            "category":"Professional",
            "subcategory":"Employment Agencies",
            "type":"Services"
        }
    ],
    "sg:phone":"+1 305 273 5533",
    "sg:postcode":"33156",
    "sg:province":"FL",
    "sg:website":"www.pystaffing.com",
    "wof:name":"Personally Yours Stafing",
    "wof:placetype":"venue"
},
  "geometry": {"coordinates":[-80.31459700000001,25.685104],"type":"Point"}
}