{
  "type": "Feature",
  "properties": {
    "iso:country":"US",
    "sg:address":"2717 Copter Rd",
    "sg:city":"Pensacola",
    "sg:classifiers":[
        {
            "category":"Building & Trades",
            "subcategory":"Landscaping Services",
            "type":"Services"
        }
    ],
    "sg:phone":"+1 850 477 5086",
    "sg:postcode":"32514",
    "sg:province":"FL",
    "wof:name":"Courtesy Lawn Care",
    "wof:placetype":"venue"
},
  "geometry": {"coordinates":[-87.20683,30.52922],"type":"Point"}
}