{
  "type": "Feature",
  "properties": {
    "iso:country":"US",
    "sg:address":"928 Spring Lake Sq",
    "sg:city":"Winter Haven",
    "sg:classifiers":[
        {
            "category":"Shopping",
            "subcategory":"Clothing, Apparel, & Fashions",
            "type":"Retail Goods"
        }
    ],
    "sg:phone":"+1 863 294 3276",
    "sg:postcode":"33881",
    "sg:province":"FL",
    "sg:tags":[
        "wear",
        "western",
        "accessory"
    ],
    "wof:name":"Cheyenne Western Wear",
    "wof:placetype":"venue"
},
  "geometry": {"coordinates":[-81.735653,28.043067],"type":"Point"}
}