{
  "type": "Feature",
  "properties": {
    "iso:country":"US",
    "sg:address":"13800 SW 88th St",
    "sg:city":"Miami",
    "sg:classifiers":[
        {
            "category":"Retail",
            "subcategory":"Laundry & Dry Cleaning",
            "type":"Services"
        }
    ],
    "sg:phone":"+1 305 387 2352",
    "sg:postcode":"33186",
    "sg:province":"FL",
    "sg:tags":[
        "garment",
        "agent"
    ],
    "wof:name":"Pak Cleaners",
    "wof:placetype":"venue"
},
  "geometry": {"coordinates":[-80.41842200000001,25.68528],"type":"Point"}
}