{
  "type": "Feature",
  "properties": {
    "addr:full":"1555 Atlantic Blvd Neptune Beach FL 32233",
    "addr:housenumber":"1555",
    "addr:postcode":"32233",
    "addr:street":"Atlantic Blvd",
    "iso:country":"US",
    "sg:address":"1555 Atlantic Blvd",
    "sg:city":"Neptune Beach",
    "sg:classifiers":[
        {
            "category":"Retail",
            "subcategory":"Auto Rental",
            "type":"Services"
        }
    ],
    "sg:phone":"+1 904 249 3700",
    "sg:postcode":"32233",
    "sg:province":"FL",
    "sg:tags":[
        "renting",
        "automobile"
    ],
    "wof:name":"Enterprise Rent-A-Car",
    "wof:placetype":"venue"
},
  "geometry": {"coordinates":[-81.423914,30.32433],"type":"Point"}
}