{
  "type": "Feature",
  "properties": {
    "iso:country":"US",
    "sg:address":"1321 NW 14th St Suite 605",
    "sg:city":"Miami",
    "sg:classifiers":[
        {
            "category":"Health Services",
            "subcategory":"Doctor",
            "type":"Services"
        }
    ],
    "sg:phone":"+1 305 325 4873",
    "sg:postcode":"33125",
    "sg:province":"FL",
    "sg:tags":[
        "physician",
        "surgeon",
        "neurology",
        "surgeons"
    ],
    "sg:website":"http://www.neurosurgicalinstitutefl.com",
    "wof:name":"Dr. Mark R. Shaya",
    "wof:placetype":"venue"
},
  "geometry": {"coordinates":[-80.216673,25.787554],"type":"Point"}
}