{
  "type": "Feature",
  "properties": {
    "iso:country":"US",
    "sg:address":"2835 Terramar St",
    "sg:city":"Fort Lauderdale",
    "sg:classifiers":[
        {
            "category":"Travel",
            "subcategory":"Hotels & Motels",
            "type":"Entertainment"
        }
    ],
    "sg:phone":"+1 954 568 6161",
    "sg:postcode":"33304",
    "sg:province":"FL",
    "sg:website":"www.saintsebastianhotel.com",
    "wof:name":"St Sebastian Guest Suites",
    "wof:placetype":"venue"
},
  "geometry": {"coordinates":[-80.10715999999999,26.131226],"type":"Point"}
}