{
  "type": "Feature",
  "properties": {
    "iso:country":"US",
    "sg:address":"2750 State Rte 21",
    "sg:city":"Atmore",
    "sg:classifiers":[
        {
            "category":"Organizations",
            "subcategory":"Religious Organization",
            "type":"Services"
        }
    ],
    "sg:phone":"+1 251 368 1635",
    "sg:postcode":"36502",
    "sg:province":"FL",
    "wof:name":"Pleasant Hill Baptist Church",
    "wof:placetype":"venue"
},
  "geometry": {"coordinates":[-87.492627,31.056403],"type":"Point"}
}