{
  "type": "Feature",
  "properties": {
    "iso:country":"US",
    "sg:address":"8895 N Military Trl",
    "sg:city":"Palm Beach Gardens",
    "sg:classifiers":[
        {
            "category":"Professional",
            "subcategory":"Credit Reporting & Collection",
            "type":"Services"
        }
    ],
    "sg:phone":"+1 561 624 7442",
    "sg:postcode":"33410",
    "sg:province":"FL",
    "sg:tags":[
        "agency"
    ],
    "wof:name":"N F S",
    "wof:placetype":"venue"
},
  "geometry": {"coordinates":[-80.106455,26.805752],"type":"Point"}
}