{
  "type": "Feature",
  "properties": {
    "iso:country":"US",
    "sg:address":"20950 NW 2nd Ave",
    "sg:city":"Miami",
    "sg:phone":"+1 954 763 1037",
    "sg:postcode":"33169",
    "sg:province":"FL",
    "wof:name":"William Lehman Subaru",
    "wof:placetype":"venue"
},
  "geometry": {"coordinates":[-80.206059,25.967962],"type":"Point"}
}