{
  "type": "Feature",
  "properties": {
    "iso:country":"US",
    "sg:address":"1185 N Hercules Ave",
    "sg:city":"Clearwater",
    "sg:classifiers":[
        {
            "category":"Restaurant",
            "type":"Food & Drink"
        }
    ],
    "sg:phone":"+1 727 461 4140",
    "sg:postcode":"33765",
    "sg:province":"FL",
    "sg:tags":[
        "eating"
    ],
    "wof:name":"Expo Restaurant Inc",
    "wof:placetype":"venue"
},
  "geometry": {"coordinates":[-82.75460099999999,27.975281],"type":"Point"}
}