{
  "type": "Feature",
  "properties": {
    "addr:full":"2111 W Beaver St Jacksonville FL 32209",
    "addr:housenumber":"2111",
    "addr:postcode":"32209",
    "addr:street":"W Beaver St",
    "iso:country":"US",
    "sg:address":"2111 W Beaver St",
    "sg:city":"Jacksonville",
    "sg:classifiers":[
        {
            "category":"Building & Trades",
            "subcategory":"Plumbing",
            "type":"Services"
        }
    ],
    "sg:phone":"+1 904 358 1701",
    "sg:postcode":"32209",
    "sg:province":"FL",
    "sg:tags":[
        "mechanical",
        "contractor"
    ],
    "wof:name":"Southeastern Mechanical Svc",
    "wof:placetype":"venue"
},
  "geometry": {"coordinates":[-81.69528,30.333501],"type":"Point"}
}