{
  "type": "Feature",
  "properties": {
    "addr:full":"350 San Lorenzo Ave Coral Gables FL 33146",
    "addr:housenumber":"350",
    "addr:postcode":"33146",
    "addr:street":"San Lorenzo Ave",
    "iso:country":"US",
    "sg:address":"350 San Lorenzo Ave",
    "sg:city":"Coral Gables",
    "sg:classifiers":[
        {
            "category":"Shopping",
            "subcategory":"Clothing, Apparel, & Fashions",
            "type":"Retail Goods"
        }
    ],
    "sg:phone":"+1 305 446 8441",
    "sg:postcode":"33146",
    "sg:province":"FL",
    "wof:name":"Express",
    "wof:placetype":"venue"
},
  "geometry": {"coordinates":[-80.26165,25.732045],"type":"Point"}
}