{
  "type": "Feature",
  "properties": {
    "addr:full":"1111 N West Shore Blvd Tampa FL 33607",
    "addr:housenumber":"1111",
    "addr:postcode":"33607",
    "addr:street":"N West Shore Blvd",
    "iso:country":"US",
    "sg:address":"1111 N West Shore Blvd",
    "sg:city":"Tampa",
    "sg:classifiers":[
        {
            "category":"Professional",
            "subcategory":"Lawyer & Legal Services",
            "type":"Services"
        }
    ],
    "sg:phone":"+1 813 286 1557",
    "sg:postcode":"33607",
    "sg:province":"FL",
    "sg:tags":[
        "attorney"
    ],
    "wof:name":"Anthony V Cortese",
    "wof:placetype":"venue"
},
  "geometry": {"coordinates":[-82.524066,27.954345],"type":"Point"}
}