{
  "type": "Feature",
  "properties": {
    "addr:full":"2329 TAMIAMI TRL N NAPLES FL 34103",
    "addr:housenumber":"2329",
    "addr:postcode":"34103",
    "addr:street":"Tamiami Trl N",
    "iso:country":"US",
    "sg:address":"2329 TAMIAMI TRL N",
    "sg:city":"NAPLES",
    "sg:classifiers":[
        {
            "category":"Travel",
            "subcategory":"Hotels & Motels",
            "type":"Entertainment"
        }
    ],
    "sg:phone":"+1 877 574 2464",
    "sg:postcode":"34103",
    "sg:province":"FL",
    "sg:tags":[
        "lodging"
    ],
    "sg:website":"http://book.bestwestern.com/bestwestern/priceAvail.do?propertyCode=10151&cm_mmc=IYP-_-YP-_-property-_-10151",
    "wof:name":"Best Western Naples Inn & Suites",
    "wof:placetype":"venue"
},
  "geometry": {"coordinates":[-81.799858,26.175638],"type":"Point"}
}