{
  "type": "Feature",
  "properties": {
    "addr:full":"13508 N Florida Ave Tampa FL 33613",
    "addr:housenumber":"13508",
    "addr:postcode":"33613",
    "addr:street":"N Florida Ave",
    "iso:country":"US",
    "sg:address":"13508 N Florida Ave",
    "sg:city":"Tampa",
    "sg:classifiers":[
        {
            "category":"Food & Beverages",
            "subcategory":"Groceries & Convenience Stores",
            "type":"Retail Goods"
        }
    ],
    "sg:phone":"+1 813 962 0774",
    "sg:postcode":"33613",
    "sg:province":"FL",
    "sg:tags":[
        "grocer"
    ],
    "wof:name":"KASH N' Karry",
    "wof:placetype":"venue"
},
  "geometry": {"coordinates":[-82.4594,28.071636],"type":"Point"}
}