{
  "type": "Feature",
  "properties": {
    "iso:country":"US",
    "sg:address":"1450 SW 10th St",
    "sg:city":"Delray Beach",
    "sg:classifiers":[
        {
            "category":"Building & Trades",
            "subcategory":"Construction",
            "type":"Services"
        }
    ],
    "sg:phone":"+1 561 272 3700",
    "sg:postcode":"33444",
    "sg:province":"FL",
    "sg:tags":[
        "contractor",
        "an",
        "commercial",
        "renovation",
        "general"
    ],
    "wof:name":"Carousel Dev & Restoration",
    "wof:placetype":"venue"
},
  "geometry": {"coordinates":[-80.087796,26.446837],"type":"Point"}
}