{
  "type": "Feature",
  "properties": {
    "addr:full":"3135 Terrace Ave Naples FL 34104",
    "addr:housenumber":"3135",
    "addr:postcode":"34104",
    "addr:street":"Terrace Ave",
    "iso:country":"US",
    "sg:address":"3135 Terrace Ave",
    "sg:city":"Naples",
    "sg:classifiers":[
        {
            "category":"Building & Trades",
            "subcategory":"Construction",
            "type":"Services"
        }
    ],
    "sg:phone":"+1 239 793 4422",
    "sg:postcode":"34104",
    "sg:province":"FL",
    "sg:tags":[
        "installer",
        "brick",
        "interlock",
        "pattern"
    ],
    "wof:name":"Keyestone Interlocking Paving",
    "wof:placetype":"venue"
},
  "geometry": {"coordinates":[-81.768951,26.139524],"type":"Point"}
}