{
  "type": "Feature",
  "properties": {
    "iso:country":"US",
    "sg:address":"3070 Carters Mill Rd",
    "sg:city":"Marianna",
    "sg:classifiers":[
        {
            "category":"Real Estate",
            "subcategory":"Real Estate Operator",
            "type":"Services"
        }
    ],
    "sg:phone":"+1 850 482 5358",
    "sg:postcode":"32446",
    "sg:province":"FL",
    "sg:tags":[
        "housing",
        "program"
    ],
    "wof:name":"Maryanna Garden & Apartment",
    "wof:placetype":"venue"
},
  "geometry": {"coordinates":[-85.243559,30.788697],"type":"Point"}
}