{
  "type": "Feature",
  "properties": {
    "iso:country":"US",
    "sg:address":"2686 NW 97th Ave",
    "sg:city":"Doral",
    "sg:classifiers":[
        {
            "category":"Wholesale",
            "subcategory":"Seafood",
            "type":"Manufacturing & Wholesale Goods"
        }
    ],
    "sg:phone":"+1 305 591 6886",
    "sg:postcode":"33172",
    "sg:province":"FL",
    "sg:tags":[
        "market"
    ],
    "wof:name":"Shells and Fish Inc",
    "wof:placetype":"venue"
},
  "geometry": {"coordinates":[-80.353279,25.798597],"type":"Point"}
}