{
  "type": "Feature",
  "properties": {
    "iso:country":"US",
    "sg:address":"5555 Red Bug Lake Rd",
    "sg:city":"Winter Springs",
    "sg:classifiers":[
        {
            "category":"Food & Beverages",
            "subcategory":"Groceries & Convenience Stores",
            "type":"Retail Goods"
        }
    ],
    "sg:phone":"+1 407 695 0936",
    "sg:postcode":"32708",
    "sg:province":"FL",
    "sg:website":"www.circlek.com",
    "wof:name":"Circle K Stores Inc",
    "wof:placetype":"venue"
},
  "geometry": {"coordinates":[-81.270973,28.647439],"type":"Point"}
}