{
  "type": "Feature",
  "properties": {
    "iso:country":"US",
    "sg:address":"7409 N Nebraska Ave",
    "sg:city":"Tampa",
    "sg:classifiers":[
        {
            "category":"Retail",
            "subcategory":"Auto Repair",
            "type":"Services"
        }
    ],
    "sg:phone":"+1 813 237 1155",
    "sg:postcode":"33604",
    "sg:province":"FL",
    "sg:tags":[
        "air"
    ],
    "wof:name":"Fair Fix Inc",
    "wof:placetype":"venue"
},
  "geometry": {"coordinates":[-82.45121399999999,28.016046],"type":"Point"}
}