{
  "type": "Feature",
  "properties": {
    "iso:country":"US",
    "sg:address":"10 S Broad St",
    "sg:city":"Brooksville",
    "sg:classifiers":[
        {
            "category":"Home & Garden",
            "subcategory":"Building Materials",
            "type":"Retail Goods"
        }
    ],
    "sg:phone":"+1 352 799 6673",
    "sg:postcode":"34601",
    "sg:province":"FL",
    "sg:tags":[
        "shutter"
    ],
    "wof:name":"Hunter Douglas Window Fashions",
    "wof:placetype":"venue"
},
  "geometry": {"coordinates":[-82.388623,28.554951],"type":"Point"}
}