{
  "type": "Feature",
  "properties": {
    "iso:country":"US",
    "sg:address":"49 Majorca Ave",
    "sg:city":"Coral Gables",
    "sg:classifiers":[
        {
            "category":"Real Estate",
            "subcategory":"Real Estate Agent",
            "type":"Services"
        }
    ],
    "sg:phone":"+1 786 552 0838",
    "sg:postcode":"33134",
    "sg:province":"FL",
    "wof:name":"Roland I Pozo Realtor",
    "wof:placetype":"venue"
},
  "geometry": {"coordinates":[-80.256162,25.755406],"type":"Point"}
}