{
  "type": "Feature",
  "properties": {
    "iso:country":"US",
    "sg:address":"8920 Sunset Blvd",
    "sg:city":"Orlando",
    "sg:classifiers":[
        {
            "category":"Building & Trades",
            "subcategory":"Construction",
            "type":"Services"
        }
    ],
    "sg:phone":"+1 407 876 0743",
    "sg:postcode":"32836",
    "sg:province":"FL",
    "sg:tags":[
        "house"
    ],
    "wof:name":"Robert W Riley Jr",
    "wof:placetype":"venue"
},
  "geometry": {"coordinates":[-81.53475299999999,28.437247],"type":"Point"}
}