{
  "type": "Feature",
  "properties": {
    "iso:country":"US",
    "sg:address":"11200 Valencia Blvd",
    "sg:city":"Boynton Beach",
    "sg:classifiers":[
        {
            "category":"Restaurant",
            "type":"Food & Drink"
        }
    ],
    "sg:phone":"+1 561 738 7568",
    "sg:postcode":"33470",
    "sg:province":"FL",
    "sg:tags":[
        "caterer"
    ],
    "wof:name":"Paul E's Catering Inc",
    "wof:placetype":"venue"
},
  "geometry": {"coordinates":[-80.296333,26.802301],"type":"Point"}
}