{
  "type": "Feature",
  "properties": {
    "addr:full":"555 Biltmore Way Suite 103 Coral Gables FL 33134",
    "addr:housenumber":"555",
    "addr:postcode":"33134",
    "addr:street":"Biltmore Way Suite 103",
    "iso:country":"US",
    "sg:address":"555 Biltmore Way Suite 103",
    "sg:city":"Coral Gables",
    "sg:classifiers":[
        {
            "category":"Health Services",
            "subcategory":"Doctor",
            "type":"Services"
        }
    ],
    "sg:phone":"+1 786 552 0027",
    "sg:postcode":"33134",
    "sg:province":"FL",
    "sg:tags":[
        "surgeon",
        "cosmetic"
    ],
    "sg:website":"www.adlerplasticsurgery.com",
    "wof:name":"Adler and Giles Plastic and Cosmetic Surgery Specialists",
    "wof:placetype":"venue"
},
  "geometry": {"coordinates":[-80.26581299999999,25.748212],"type":"Point"}
}