{
  "type": "Feature",
  "properties": {
    "iso:country":"US",
    "sg:address":"167 Ave A NW",
    "sg:city":"Winter Haven",
    "sg:classifiers":[
        {
            "category":"Shopping",
            "subcategory":"Clothing, Apparel, & Fashions",
            "type":"Retail Goods"
        }
    ],
    "sg:phone":"+1 863 294 9114",
    "sg:postcode":"33881",
    "sg:province":"FL",
    "wof:name":"Nans Alterations",
    "wof:placetype":"venue"
},
  "geometry": {"coordinates":[-81.727639,28.023075],"type":"Point"}
}