{
  "type": "Feature",
  "properties": {
    "addr:full":"900 Osceola Dr West Palm Beach FL 33409",
    "addr:housenumber":"900",
    "addr:postcode":"33409",
    "addr:street":"Osceola Dr",
    "iso:country":"US",
    "sg:address":"900 Osceola Dr",
    "sg:city":"West Palm Beach",
    "sg:classifiers":[
        {
            "category":"Professional",
            "subcategory":"Research",
            "type":"Services"
        }
    ],
    "sg:phone":"+1 561 686 7440",
    "sg:postcode":"33409",
    "sg:province":"FL",
    "wof:name":"Hilltop Research",
    "wof:placetype":"venue"
},
  "geometry": {"coordinates":[-80.092783,26.706011],"type":"Point"}
}