{
  "type": "Feature",
  "properties": {
    "addr:full":"6050 NW 27th Ave Miami FL 33142",
    "addr:housenumber":"6050",
    "addr:postcode":"33142",
    "addr:street":"Nw 27Th Ave",
    "iso:country":"US",
    "sg:address":"6050 NW 27th Ave",
    "sg:city":"Miami",
    "sg:classifiers":[
        {
            "category":"Personal",
            "subcategory":"Beauty Salon",
            "type":"Services"
        },
        {
            "category":"Personal",
            "subcategory":"Barber",
            "type":"Services"
        }
    ],
    "sg:phone":"+1 305 633 1626",
    "sg:postcode":"33142",
    "sg:province":"FL",
    "sg:tags":[
        "shop"
    ],
    "wof:name":"Action Beauty & Barber Shop",
    "wof:placetype":"venue"
},
  "geometry": {"coordinates":[-80.241131,25.829851],"type":"Point"}
}