{
  "type": "Feature",
  "properties": {
    "iso:country":"US",
    "sg:address":"1517 Perimeter Rd",
    "sg:city":"West Palm Beach",
    "sg:classifiers":[
        {
            "category":"Professional",
            "type":"Services"
        }
    ],
    "sg:phone":"+1 561 712 0301",
    "sg:postcode":"33406",
    "sg:province":"FL",
    "sg:tags":[
        "establishment"
    ],
    "wof:name":"ASDF Flt Ops",
    "wof:placetype":"venue"
},
  "geometry": {"coordinates":[-80.083862,26.677642],"type":"Point"}
}