{
  "type": "Feature",
  "properties": {
    "addr:full":"1702 N Washington Blvd Sarasota FL 34234",
    "addr:housenumber":"1702",
    "addr:postcode":"34234",
    "addr:street":"N Washington Blvd",
    "iso:country":"US",
    "sg:address":"1702 N Washington Blvd",
    "sg:city":"Sarasota",
    "sg:classifiers":[
        {
            "category":"Food & Beverages",
            "subcategory":"Groceries & Convenience Stores",
            "type":"Retail Goods"
        }
    ],
    "sg:phone":"+1 941 955 5020",
    "sg:postcode":"34234",
    "sg:province":"FL",
    "wof:name":"7-Eleven",
    "wof:placetype":"venue"
},
  "geometry": {"coordinates":[-82.530348,27.353139],"type":"Point"}
}