{
  "type": "Feature",
  "properties": {
    "iso:country":"US",
    "sg:address":"7390 Bird Rd",
    "sg:city":"Miami",
    "sg:classifiers":[
        {
            "category":"Museum",
            "subcategory":"Aquarium",
            "type":"Entertainment"
        }
    ],
    "sg:phone":"+1 305 264 1515",
    "sg:postcode":"33155",
    "sg:province":"FL",
    "wof:name":"Reef Aquariums of South West Florida",
    "wof:placetype":"venue"
},
  "geometry": {"coordinates":[-80.314763,25.732863],"type":"Point"}
}