{
  "type": "Feature",
  "properties": {
    "iso:country":"US",
    "sg:address":"21275 Olean Blvd",
    "sg:city":"Port Charlotte",
    "sg:classifiers":[
        {
            "category":"Health Services",
            "subcategory":"Hospital",
            "type":"Services"
        }
    ],
    "sg:phone":"+1 941 625 1325",
    "sg:postcode":"33952",
    "sg:province":"FL",
    "wof:name":"St Lucy's Out Patient Surgery",
    "wof:placetype":"venue"
},
  "geometry": {"coordinates":[-82.0981,26.987768],"type":"Point"}
}