{
  "type": "Feature",
  "properties": {
    "iso:country":"US",
    "sg:address":"7550 S Red Rd Ste 203",
    "sg:city":"South Miami",
    "sg:classifiers":[
        {
            "category":"Professional",
            "subcategory":"Lawyer & Legal Services",
            "type":"Services"
        }
    ],
    "sg:phone":"+1 305 661 8551",
    "sg:postcode":"33143",
    "sg:province":"FL",
    "sg:website":"www.stevenkellough.com",
    "wof:name":"Kellough Steven",
    "wof:placetype":"venue"
},
  "geometry": {"coordinates":[-80.285301,25.701099],"type":"Point"}
}