{
  "type": "Feature",
  "properties": {
    "iso:country":"US",
    "sg:address":"60 W Robinson St",
    "sg:city":"Orlando",
    "sg:classifiers":[
        {
            "category":"Real Estate",
            "subcategory":"Developer",
            "type":"Services"
        }
    ],
    "sg:phone":"+1 407 422 6105",
    "sg:postcode":"32801",
    "sg:province":"FL",
    "wof:name":"Dr Phillips Inc",
    "wof:placetype":"venue"
},
  "geometry": {"coordinates":[-81.379158,28.545599],"type":"Point"}
}