{
  "type": "Feature",
  "properties": {
    "addr:full":"8275 SW 152nd Ave Apt 106 Miami FL 33193",
    "addr:housenumber":"8275;106",
    "addr:postcode":"33193",
    "addr:street":"Sw 152Nd Ave Apt",
    "iso:country":"US",
    "sg:address":"8275 SW 152nd Ave Apt 106",
    "sg:city":"Miami",
    "sg:classifiers":[
        {
            "category":"Professional",
            "subcategory":"Computer Services",
            "type":"Services"
        }
    ],
    "sg:phone":"+1 305 388 0100",
    "sg:postcode":"33193",
    "sg:province":"FL",
    "sg:tags":[
        "design",
        "network",
        "system"
    ],
    "sg:website":"http://www.webinnovative.com",
    "wof:name":"Webinnovative Inc",
    "wof:placetype":"venue"
},
  "geometry": {"coordinates":[-80.4391,25.689742],"type":"Point"}
}