{
  "type": "Feature",
  "properties": {
    "addr:full":"3825 N Canoe Creek Rd Saint Cloud FL 34772",
    "addr:housenumber":"3825",
    "addr:postcode":"34772",
    "addr:street":"N Canoe Creek Rd",
    "iso:country":"US",
    "sg:address":"3825 N Canoe Creek Rd",
    "sg:city":"Saint Cloud",
    "sg:classifiers":[
        {
            "category":"Farming",
            "subcategory":"Orchard",
            "type":"Manufacturing & Wholesale Goods"
        }
    ],
    "sg:phone":"+1 407 892 5069",
    "sg:postcode":"34772",
    "sg:province":"FL",
    "sg:tags":[
        "orange",
        "grove"
    ],
    "wof:name":"Circle Y Groves",
    "wof:placetype":"venue"
},
  "geometry": {"coordinates":[-81.28180500000001,28.179969],"type":"Point"}
}