{
  "type": "Feature",
  "properties": {
    "iso:country":"US",
    "sg:address":"57 SW 40th Ave",
    "sg:city":"Miami",
    "sg:classifiers":[
        {
            "category":"Insurance",
            "subcategory":"Insurance Agent",
            "type":"Services"
        }
    ],
    "sg:phone":"+1 305 669 1199",
    "sg:postcode":"33134",
    "sg:province":"FL",
    "wof:name":"South Pacific Insurance Agency",
    "wof:placetype":"venue"
},
  "geometry": {"coordinates":[-80.261499,25.770742],"type":"Point"}
}