{
  "type": "Feature",
  "properties": {
    "iso:country":"US",
    "sg:address":"1443 Tammany Way",
    "sg:city":"Daytona Beach",
    "sg:classifiers":[
        {
            "category":"Building & Trades",
            "subcategory":"Construction",
            "type":"Services"
        }
    ],
    "sg:phone":"+1 386 756 4039",
    "sg:postcode":"32129",
    "sg:province":"FL",
    "sg:tags":[
        "tile",
        "dealer",
        "contractor"
    ],
    "wof:name":"Southeast Tile Co",
    "wof:placetype":"venue"
},
  "geometry": {"coordinates":[-81.042064,29.123967],"type":"Point"}
}