{
  "type": "Feature",
  "properties": {
    "iso:country":"US",
    "sg:address":"308 E Pine St",
    "sg:city":"Lakeland",
    "sg:classifiers":[
        {
            "category":"Education",
            "subcategory":"Special Training",
            "type":"Public Place"
        }
    ],
    "sg:phone":"+1 863 683 0854",
    "sg:postcode":"33801",
    "sg:province":"FL",
    "sg:tags":[
        "instruction",
        "driving"
    ],
    "wof:name":"Driver Training Associates",
    "wof:placetype":"venue"
},
  "geometry": {"coordinates":[-81.954245,28.046004],"type":"Point"}
}