{
  "type": "Feature",
  "properties": {
    "iso:country":"US",
    "sg:address":"5866 14th St W",
    "sg:city":"Bradenton",
    "sg:classifiers":[
        {
            "category":"Food & Beverages",
            "subcategory":"Bakery",
            "type":"Retail Goods"
        }
    ],
    "sg:phone":"+1 941 753 2710",
    "sg:postcode":"34207",
    "sg:province":"FL",
    "sg:tags":[
        "eating"
    ],
    "wof:name":"R & J Bagel Factory & Deli",
    "wof:placetype":"venue"
},
  "geometry": {"coordinates":[-82.575517,27.438086],"type":"Point"}
}