{
  "type": "Feature",
  "properties": {
    "addr:full":"1535 SW 62nd Ave Miami FL 33144",
    "addr:housenumber":"1535",
    "addr:postcode":"33144",
    "addr:street":"Sw 62Nd Ave",
    "iso:country":"US",
    "sg:address":"1535 SW 62nd Ave",
    "sg:city":"Miami",
    "sg:classifiers":[
        {
            "category":"Health Services",
            "subcategory":"Nursing And Care Facility",
            "type":"Services"
        }
    ],
    "sg:phone":"+1 786 326 0362",
    "sg:postcode":"33144",
    "sg:province":"FL",
    "wof:name":"Saint Jude Adult Care",
    "wof:placetype":"venue"
},
  "geometry": {"coordinates":[-80.29560600000001,25.75635],"type":"Point"}
}