{
  "type": "Feature",
  "properties": {
    "iso:country":"US",
    "sg:address":"3485 W Vine St",
    "sg:city":"Kissimmee",
    "sg:classifiers":[
        {
            "category":"Insurance",
            "subcategory":"Insurance Agent",
            "type":"Services"
        }
    ],
    "sg:phone":"+1 407 343 9071",
    "sg:postcode":"34741",
    "sg:province":"FL",
    "wof:name":"Liberty Mutual",
    "wof:placetype":"venue"
},
  "geometry": {"coordinates":[-81.44081199999999,28.304506],"type":"Point"}
}