{
  "type": "Feature",
  "properties": {
    "iso:country":"US",
    "sg:address":"291 23rd St SW",
    "sg:city":"Naples",
    "sg:classifiers":[
        {
            "category":"Building & Trades",
            "subcategory":"Landscaping Services",
            "type":"Services"
        }
    ],
    "sg:phone":"+1 239 353 7488",
    "sg:postcode":"34117",
    "sg:province":"FL",
    "sg:tags":[
        "consulting",
        "landscape",
        "business"
    ],
    "wof:name":"Naples Aquatic and Ldscp Co",
    "wof:placetype":"venue"
},
  "geometry": {"coordinates":[-81.65310700000001,26.226201],"type":"Point"}
}