{
  "type": "Feature",
  "properties": {
    "iso:country":"US",
    "sg:address":"1479 E Michigan St",
    "sg:city":"Orlando",
    "sg:classifiers":[
        {
            "category":"Autos & Motor Vehicles",
            "subcategory":"Auto Supplies",
            "type":"Retail Goods"
        }
    ],
    "sg:phone":"+1 407 895 9527",
    "sg:postcode":"32806",
    "sg:province":"FL",
    "sg:tags":[
        "automobile",
        "part"
    ],
    "sg:website":"http://www.advanceautoparts.com",
    "wof:name":"Advance Auto Parts",
    "wof:placetype":"venue"
},
  "geometry": {"coordinates":[-81.361085,28.513186],"type":"Point"}
}