{
  "type": "Feature",
  "properties": {
    "iso:country":"US",
    "sg:address":"6124 Beechwood Ave",
    "sg:city":"Sarasota",
    "sg:classifiers":[
        {
            "category":"Home & Garden",
            "subcategory":"Building Materials",
            "type":"Retail Goods"
        }
    ],
    "sg:phone":"+1 941 924 6572",
    "sg:postcode":"34231",
    "sg:province":"FL",
    "wof:name":"John R Mary Furrow",
    "wof:placetype":"venue"
},
  "geometry": {"coordinates":[-82.529597,27.262401],"type":"Point"}
}