{
  "type": "Feature",
  "properties": {
    "addr:full":"90 NW 27th Ave Miami FL 33125",
    "addr:housenumber":"90",
    "addr:postcode":"33125",
    "addr:street":"Nw 27Th Ave",
    "iso:country":"US",
    "sg:address":"90 NW 27th Ave",
    "sg:city":"Miami",
    "sg:classifiers":[
        {
            "category":"Organizations",
            "subcategory":"Religious Organization",
            "type":"Services"
        }
    ],
    "sg:phone":"+1 305 642 8953",
    "sg:postcode":"33125",
    "sg:province":"FL",
    "wof:name":"Iglesia Evangelica Pentecostal Inc",
    "wof:placetype":"venue"
},
  "geometry": {"coordinates":[-80.239098,25.7736],"type":"Point"}
}