{
  "type": "Feature",
  "properties": {
    "addr:full":"6249 SW 27th St Miramar FL 33023",
    "addr:housenumber":"6249",
    "addr:postcode":"33023",
    "addr:street":"Sw 27Th St",
    "iso:country":"US",
    "sg:address":"6249 SW 27th St",
    "sg:city":"Miramar",
    "sg:classifiers":[
        {
            "category":"Real Estate",
            "subcategory":"Real Estate Agent",
            "type":"Services"
        }
    ],
    "sg:phone":"+1 954 962 6472",
    "sg:postcode":"33023",
    "sg:province":"FL",
    "sg:tags":[
        "inspection"
    ],
    "wof:name":"A Plus Home Inspections",
    "wof:placetype":"venue"
},
  "geometry": {"coordinates":[-80.213869,25.985793],"type":"Point"}
}