{
  "type": "Feature",
  "properties": {
    "iso:country":"US",
    "sg:address":"2011 Melbourne Ct",
    "sg:city":"Melbourne",
    "sg:classifiers":[
        {
            "category":"Personal",
            "subcategory":"Beauty Salon",
            "type":"Services"
        }
    ],
    "sg:phone":"+1 321 724 1373",
    "sg:postcode":"32901",
    "sg:province":"FL",
    "wof:name":"Fred's Heads",
    "wof:placetype":"venue"
},
  "geometry": {"coordinates":[-80.604761,28.078108],"type":"Point"}
}