{
  "type": "Feature",
  "properties": {
    "addr:full":"15591 SW 63rd Ter Miami FL 33193",
    "addr:housenumber":"15591",
    "addr:postcode":"33193",
    "addr:street":"Sw 63Rd Ter",
    "iso:country":"US",
    "sg:address":"15591 SW 63rd Ter",
    "sg:city":"Miami",
    "sg:classifiers":[
        {
            "category":"Autos & Motor Vehicles",
            "subcategory":"Auto Supplies",
            "type":"Retail Goods"
        }
    ],
    "sg:phone":"+1 305 388 7165",
    "sg:postcode":"33193",
    "sg:province":"FL",
    "wof:name":"Nippon Auto Parts & Accessorie",
    "wof:placetype":"venue"
},
  "geometry": {"coordinates":[-80.444165,25.706853],"type":"Point"}
}