{
  "type": "Feature",
  "properties": {
    "addr:full":"11311 SE 40th Ave Belleview FL 34420",
    "addr:housenumber":"11311",
    "addr:postcode":"34420",
    "addr:street":"Se 40Th Ave",
    "iso:country":"US",
    "sg:address":"11311 SE 40th Ave",
    "sg:city":"Belleview",
    "sg:classifiers":[
        {
            "category":"Shopping",
            "subcategory":"Bicycles & Sporting Goods",
            "type":"Retail Goods"
        }
    ],
    "sg:phone":"+1 352 669 0575",
    "sg:postcode":"34420",
    "sg:province":"FL",
    "sg:tags":[
        "equipment",
        "diver",
        "supply"
    ],
    "sg:website":"www.dpvrepair.com",
    "wof:name":"DPV Repair",
    "wof:placetype":"venue"
},
  "geometry": {"coordinates":[-82.080415,29.0625],"type":"Point"}
}