{
  "type": "Feature",
  "properties": {
    "addr:full":"23257 State Hwy 7 Boca Raton FL 33428",
    "addr:housenumber":"23257",
    "addr:postcode":"33428",
    "addr:street":"State Hwy 7",
    "iso:country":"US",
    "sg:address":"23257 State Hwy 7",
    "sg:city":"Boca Raton",
    "sg:classifiers":[
        {
            "category":"Building & Trades",
            "subcategory":"Electrical",
            "type":"Services"
        }
    ],
    "sg:phone":"+1 561 477 8654",
    "sg:postcode":"33428",
    "sg:province":"FL",
    "sg:tags":[
        "electrical",
        "electric",
        "contractor"
    ],
    "wof:name":"O R Electric & Design",
    "wof:placetype":"venue"
},
  "geometry": {"coordinates":[-80.203017,26.33126],"type":"Point"}
}