{
  "type": "Feature",
  "properties": {
    "iso:country":"US",
    "sg:address":"1867 S Patrick Dr",
    "sg:city":"Indian Hrbr Bch",
    "sg:classifiers":[
        {
            "category":"Education",
            "subcategory":"Dance Studio",
            "type":"Public Place"
        }
    ],
    "sg:phone":"+1 321 777 0001",
    "sg:postcode":"32937",
    "sg:province":"FL",
    "sg:tags":[
        "instruction",
        "dancing"
    ],
    "wof:name":"Beachside Ballroom Club",
    "wof:placetype":"venue"
},
  "geometry": {"coordinates":[-80.599834,28.151756],"type":"Point"}
}