{
  "type": "Feature",
  "properties": {
    "addr:full":"11001 Crawfordville Rd Tallahassee FL 32305",
    "addr:housenumber":"11001",
    "addr:postcode":"32305",
    "addr:street":"Crawfordville Rd",
    "iso:country":"US",
    "sg:address":"11001 Crawfordville Rd",
    "sg:city":"Tallahassee",
    "sg:classifiers":[
        {
            "category":"Building & Trades",
            "subcategory":"Construction",
            "type":"Services"
        }
    ],
    "sg:phone":"+1 850 421 0938",
    "sg:postcode":"32305",
    "sg:province":"FL",
    "sg:tags":[
        "heavy"
    ],
    "wof:name":"Mike Johnson Construction",
    "wof:placetype":"venue"
},
  "geometry": {"coordinates":[-84.343147,30.309922],"type":"Point"}
}