{
  "type": "Feature",
  "properties": {
    "iso:country":"US",
    "sg:address":"4005 4th St",
    "sg:city":"Kissimmee",
    "sg:classifiers":[
        {
            "category":"Airport",
            "type":"Transportation"
        }
    ],
    "sg:phone":"+1 407 935 9466",
    "sg:postcode":"34741",
    "sg:province":"FL",
    "sg:tags":[
        "aircraft",
        "maintenance"
    ],
    "wof:name":"Bilmar Avionics Inc",
    "wof:placetype":"venue"
},
  "geometry": {"coordinates":[-81.445831,28.289675],"type":"Point"}
}