{
  "type": "Feature",
  "properties": {
    "iso:country":"US",
    "sg:address":"6230 SW 20th Ter",
    "sg:city":"Miami",
    "sg:classifiers":[
        {
            "category":"Transit Center",
            "subcategory":"Freight",
            "type":"Transportation"
        },
        {
            "category":"Freight",
            "type":"Transportation"
        }
    ],
    "sg:phone":"+1 786 275 8504",
    "sg:postcode":"33155",
    "sg:province":"FL",
    "sg:tags":[
        "local",
        "trucking-motor",
        "trucking"
    ],
    "wof:name":"Ramirez Trucking Inc",
    "wof:placetype":"venue"
},
  "geometry": {"coordinates":[-80.296159,25.751542],"type":"Point"}
}