{
  "type": "Feature",
  "properties": {
    "iso:country":"US",
    "sg:address":"2174 SE Dolphin Rd",
    "sg:city":"Port Saint Lucie",
    "sg:classifiers":[
        {
            "category":"Shopping",
            "subcategory":"Computers & Home Electronics",
            "type":"Retail Goods"
        }
    ],
    "sg:phone":"+1 772 337 7668",
    "sg:postcode":"34952",
    "sg:province":"FL",
    "wof:name":"Tronic Computers",
    "wof:placetype":"venue"
},
  "geometry": {"coordinates":[-80.30633899999999,27.278092],"type":"Point"}
}