{
  "type": "Feature",
  "properties": {
    "iso:country":"US",
    "sg:address":"7575 Dr Phillips Blvd",
    "sg:city":"Orlando",
    "sg:classifiers":[
        {
            "category":"Real Estate",
            "subcategory":"Real Estate Services",
            "type":"Services"
        }
    ],
    "sg:phone":"+1 407 352 6216",
    "sg:postcode":"32819",
    "sg:province":"FL",
    "sg:tags":[
        "abstract",
        "title"
    ],
    "wof:name":"Alday-Donalson Title Agencies",
    "wof:placetype":"venue"
},
  "geometry": {"coordinates":[-81.48798600000001,28.452391],"type":"Point"}
}