{
  "type": "Feature",
  "properties": {
    "iso:country":"US",
    "sg:address":"6000 49th St N",
    "sg:city":"St Petersburg",
    "sg:classifiers":[
        {
            "category":"Health Services",
            "subcategory":"Clinic",
            "type":"Services"
        }
    ],
    "sg:phone":"+1 727 521 5485",
    "sg:postcode":"33709",
    "sg:province":"FL",
    "sg:tags":[
        "agency",
        "welfare"
    ],
    "wof:name":"Company Care Occupational Svc",
    "wof:placetype":"venue"
},
  "geometry": {"coordinates":[-82.69991400000001,27.827372],"type":"Point"}
}