{
  "type": "Feature",
  "properties": {
    "iso:country":"US",
    "sg:address":"16912 Orange Blvd",
    "sg:city":"Loxahatchee",
    "sg:classifiers":[
        {
            "category":"Building & Trades",
            "subcategory":"Electrical",
            "type":"Services"
        }
    ],
    "sg:phone":"+1 561 793 5772",
    "sg:postcode":"33470",
    "sg:province":"FL",
    "sg:tags":[
        "electrical",
        "contractor"
    ],
    "wof:name":"Lighthouse Electric Inc",
    "wof:placetype":"venue"
},
  "geometry": {"coordinates":[-80.309507,26.779663],"type":"Point"}
}