{
  "type": "Feature",
  "properties": {
    "iso:country":"US",
    "sg:address":"4787 NE 11th Ave",
    "sg:city":"Oakland Park",
    "sg:classifiers":[
        {
            "category":"Retail",
            "subcategory":"Repair Shop",
            "type":"Services"
        }
    ],
    "sg:phone":"+1 954 938 0093",
    "sg:postcode":"33334",
    "sg:province":"FL",
    "sg:tags":[
        "antique",
        "restoring"
    ],
    "wof:name":"Reliance Furniture Svc",
    "wof:placetype":"venue"
},
  "geometry": {"coordinates":[-80.13276,26.185393],"type":"Point"}
}