{
  "type": "Feature",
  "properties": {
    "addr:full":"2751 Capital Cir NE Tallahassee FL 32308",
    "addr:housenumber":"2751",
    "addr:postcode":"32308",
    "addr:street":"Capital Cir Ne",
    "iso:country":"US",
    "sg:address":"2751 Capital Cir NE",
    "sg:city":"Tallahassee",
    "sg:classifiers":[
        {
            "category":"Personal",
            "type":"Services"
        }
    ],
    "sg:phone":"+1 850 385 4475",
    "sg:postcode":"32308",
    "sg:province":"FL",
    "sg:tags":[
        "program",
        "physical",
        "exercise",
        "fitness"
    ],
    "wof:name":"Barrow Hill Pilates Studio",
    "wof:placetype":"venue"
},
  "geometry": {"coordinates":[-84.239707,30.488522],"type":"Point"}
}