{
  "type": "Feature",
  "properties": {
    "iso:country":"US",
    "sg:address":"4515 George Rd",
    "sg:city":"Tampa",
    "sg:classifiers":[
        {
            "category":"Building & Trades",
            "subcategory":"Cleaning & Sanitation",
            "type":"Services"
        }
    ],
    "sg:phone":"+1 813 884 5454",
    "sg:postcode":"33634",
    "sg:province":"FL",
    "sg:tags":[
        "maintenance"
    ],
    "wof:name":"Aci Facility Maintenance Inc",
    "wof:placetype":"venue"
},
  "geometry": {"coordinates":[-82.550449,27.985533],"type":"Point"}
}