{
  "type": "Feature",
  "properties": {
    "addr:full":"425 S Babcock St Melbourne FL 32901",
    "addr:housenumber":"425",
    "addr:postcode":"32901",
    "addr:street":"S Babcock St",
    "iso:country":"US",
    "sg:address":"425 S Babcock St",
    "sg:city":"Melbourne",
    "sg:classifiers":[
        {
            "category":"Building & Trades",
            "subcategory":"Construction",
            "type":"Services"
        }
    ],
    "sg:phone":"+1 321 984 3331",
    "sg:postcode":"32901",
    "sg:province":"FL",
    "sg:tags":[
        "windows"
    ],
    "wof:name":"J & D Window Parts & Supplies",
    "wof:placetype":"venue"
},
  "geometry": {"coordinates":[-80.62184999999999,28.1035],"type":"Point"}
}