{
  "type": "Feature",
  "properties": {
    "addr:full":"620 NE 12th Ave Hallandale FL 33009",
    "addr:housenumber":"620",
    "addr:postcode":"33009",
    "addr:street":"Ne 12Th Ave",
    "iso:country":"US",
    "sg:address":"620 NE 12th Ave",
    "sg:city":"Hallandale",
    "sg:classifiers":[
        {
            "category":"Real Estate",
            "subcategory":"Real Estate Operator",
            "type":"Services"
        }
    ],
    "sg:phone":"+1 954 456 7312",
    "sg:postcode":"33009",
    "sg:province":"FL",
    "sg:tags":[
        "dwelling"
    ],
    "wof:name":"VIP Concierge Services",
    "wof:placetype":"venue"
},
  "geometry": {"coordinates":[-80.13641,25.993208],"type":"Point"}
}