{
  "type": "Feature",
  "properties": {
    "iso:country":"US",
    "sg:address":"1039 Weaver Dr",
    "sg:city":"Oviedo",
    "sg:classifiers":[
        {
            "category":"Building & Trades",
            "subcategory":"Construction",
            "type":"Services"
        }
    ],
    "sg:phone":"+1 321 436 7847",
    "sg:postcode":"32765",
    "sg:province":"FL",
    "sg:tags":[
        "altering",
        "remodeling",
        "contractor"
    ],
    "wof:name":"J.C.'S Home Improvement Company",
    "wof:placetype":"venue"
},
  "geometry": {"coordinates":[-81.190628,28.641329],"type":"Point"}
}