{
  "type": "Feature",
  "properties": {
    "addr:full":"927 King St Jacksonville FL 32204",
    "addr:housenumber":"927",
    "addr:postcode":"32204",
    "addr:street":"King St",
    "iso:country":"US",
    "sg:address":"927 King St",
    "sg:city":"Jacksonville",
    "sg:classifiers":[
        {
            "category":"Shopping",
            "type":"Retail Goods"
        }
    ],
    "sg:phone":"+1 904 389 9898",
    "sg:postcode":"32204",
    "sg:province":"FL",
    "sg:tags":[
        "merchandise"
    ],
    "sg:website":"www.mystickeys.com",
    "wof:name":"Mystic Keys",
    "wof:placetype":"venue"
},
  "geometry": {"coordinates":[-81.695736,30.313562],"type":"Point"}
}