{
  "type": "Feature",
  "properties": {
    "iso:country":"US",
    "sg:address":"1395 Cypress Ave",
    "sg:city":"Melbourne",
    "sg:classifiers":[
        {
            "category":"Shopping",
            "subcategory":"Used Merchandise",
            "type":"Retail Goods"
        }
    ],
    "sg:phone":"+1 321 610 8051",
    "sg:postcode":"32935",
    "sg:province":"FL",
    "sg:tags":[
        "resale",
        "shop"
    ],
    "wof:name":"All Good Money",
    "wof:placetype":"venue"
},
  "geometry": {"coordinates":[-80.631344,28.12957],"type":"Point"}
}