{
  "type": "Feature",
  "properties": {
    "addr:full":"13645 NW Highway 19 Chiefland FL 32626",
    "addr:housenumber":"13645",
    "addr:postcode":"32626",
    "addr:street":"Nw Highway 19",
    "iso:country":"US",
    "sg:address":"13645 NW Highway 19",
    "sg:city":"Chiefland",
    "sg:classifiers":[
        {
            "category":"Retail",
            "subcategory":"Auto Rental",
            "type":"Services"
        }
    ],
    "sg:phone":"+1 352 490 9592",
    "sg:postcode":"32626",
    "sg:province":"FL",
    "sg:tags":[
        "renting",
        "leasing",
        "trailer"
    ],
    "sg:website":"http://www.uhaul.com",
    "wof:name":"U-Haul Co",
    "wof:placetype":"venue"
},
  "geometry": {"coordinates":[-82.828312,29.425096],"type":"Point"}
}