{
  "type": "Feature",
  "properties": {
    "iso:country":"US",
    "sg:address":"2002 W Cleveland St",
    "sg:city":"Tampa",
    "sg:classifiers":[
        {
            "category":"Building & Trades",
            "subcategory":"Construction",
            "type":"Services"
        }
    ],
    "sg:phone":"+1 813 258 9329",
    "sg:postcode":"33606",
    "sg:province":"FL",
    "sg:tags":[
        "home",
        "builder"
    ],
    "wof:name":"Grant Homes",
    "wof:placetype":"venue"
},
  "geometry": {"coordinates":[-82.48090000000001,27.943244],"type":"Point"}
}