{
  "type": "Feature",
  "properties": {
    "addr:full":"2025 High Ridge Rd Boynton Beach FL 33426",
    "addr:housenumber":"2025",
    "addr:postcode":"33426",
    "addr:street":"High Ridge Rd",
    "iso:country":"US",
    "sg:address":"2025 High Ridge Rd",
    "sg:city":"Boynton Beach",
    "sg:classifiers":[
        {
            "category":"Manufacturing",
            "subcategory":"Metals",
            "type":"Manufacturing & Wholesale Goods"
        }
    ],
    "sg:phone":"+1 561 735 0608",
    "sg:postcode":"33426",
    "sg:province":"FL",
    "sg:tags":[
        "windows"
    ],
    "sg:website":"www.lawson.com",
    "wof:name":"Lawson Industries Inc",
    "wof:placetype":"venue"
},
  "geometry": {"coordinates":[-80.073114,26.550272],"type":"Point"}
}