{
  "type": "Feature",
  "properties": {
    "iso:country":"US",
    "sg:address":"2789 Wrights Rd Ste 1033",
    "sg:city":"Oviedo",
    "sg:classifiers":[
        {
            "category":"Building & Trades",
            "subcategory":"Pest Control",
            "type":"Services"
        }
    ],
    "sg:phone":"+1 386 734 0367",
    "sg:postcode":"32765",
    "sg:province":"FL",
    "sg:website":"www.bugs.com",
    "wof:name":"Hulett Environmental Services",
    "wof:placetype":"venue"
},
  "geometry": {"coordinates":[-81.253405,28.620663],"type":"Point"}
}