{
  "type": "Feature",
  "properties": {
    "addr:full":"17064 Traverse Cir Jupiter FL 33477",
    "addr:housenumber":"17064",
    "addr:postcode":"33477",
    "addr:street":"Traverse Cir",
    "iso:country":"US",
    "sg:address":"17064 Traverse Cir",
    "sg:city":"Jupiter",
    "sg:classifiers":[
        {
            "category":"Wholesale",
            "subcategory":"Office Equipment",
            "type":"Manufacturing & Wholesale Goods"
        }
    ],
    "sg:phone":"+1 561 743 9098",
    "sg:postcode":"33477",
    "sg:province":"FL",
    "sg:tags":[
        "credit"
    ],
    "sg:website":"www.merchantaccount.com",
    "wof:name":"Merchant Account Solutions Inc",
    "wof:placetype":"venue"
},
  "geometry": {"coordinates":[-80.087068,26.927988],"type":"Point"}
}