{
  "type": "Feature",
  "properties": {
    "addr:full":"410 S Lincoln Ave Clearwater FL 33756",
    "addr:housenumber":"410",
    "addr:postcode":"33756",
    "addr:street":"S Lincoln Ave",
    "iso:country":"US",
    "sg:address":"410 S Lincoln Ave",
    "sg:city":"Clearwater",
    "sg:classifiers":[
        {
            "category":"Real Estate",
            "subcategory":"Real Estate Agent",
            "type":"Services"
        }
    ],
    "sg:phone":"+1 727 441 8992",
    "sg:postcode":"33756",
    "sg:province":"FL",
    "wof:name":"Bruce Realtor Tyndall",
    "wof:placetype":"venue"
},
  "geometry": {"coordinates":[-82.785884,27.960921],"type":"Point"}
}