{
  "type": "Feature",
  "properties": {
    "iso:country":"US",
    "sg:address":"5219 Satel Dr",
    "sg:city":"Orlando",
    "sg:classifiers":[
        {
            "category":"Home & Garden",
            "subcategory":"Household Appliances",
            "type":"Retail Goods"
        },
        {
            "category":"Retail",
            "subcategory":"Repair Shop",
            "type":"Services"
        },
        {
            "category":"Building & Trades",
            "subcategory":"Construction",
            "type":"Services"
        }
    ],
    "sg:phone":"+1 407 298 0072",
    "sg:postcode":"32810",
    "sg:province":"FL",
    "sg:tags":[
        "dishwashing",
        "system",
        "contractor",
        "machine",
        "air conditioning",
        "freezers-repair",
        "refrigerator"
    ],
    "wof:name":"Above & Beyond Air",
    "wof:placetype":"venue"
},
  "geometry": {"coordinates":[-81.410099,28.606454],"type":"Point"}
}