{
  "type": "Feature",
  "properties": {
    "iso:country":"US",
    "sg:address":"20801 Biscayne Blvd",
    "sg:city":"Aventura",
    "sg:classifiers":[
        {
            "category":"Professional",
            "subcategory":"Lawyer & Legal Services",
            "type":"Services"
        }
    ],
    "sg:phone":"+1 305 933 2000",
    "sg:postcode":"33180",
    "sg:province":"FL",
    "sg:tags":[
        "attorney"
    ],
    "wof:name":"Marcy S Resnik",
    "wof:placetype":"venue"
},
  "geometry": {"coordinates":[-80.144882,25.968049],"type":"Point"}
}