{
  "type": "Feature",
  "properties": {
    "iso:country":"US",
    "sg:address":"5199 Tartan Lakes Blvd",
    "sg:city":"Boynton Beach",
    "sg:classifiers":[
        {
            "category":"Organizations",
            "subcategory":"Professional Association",
            "type":"Services"
        }
    ],
    "sg:phone":"+1 561 736 0139",
    "sg:postcode":"33472",
    "sg:province":"FL",
    "wof:name":"Waterchase Homeowners Assn Inc",
    "wof:placetype":"venue"
},
  "geometry": {"coordinates":[-80.12558900000001,26.542499],"type":"Point"}
}