{
  "type": "Feature",
  "properties": {
    "iso:country":"US",
    "sg:address":"175 E Crystal Lake Ave",
    "sg:city":"Lake Mary",
    "sg:classifiers":[
        {
            "category":"Professional",
            "subcategory":"Research",
            "type":"Services"
        }
    ],
    "sg:phone":"+1 407 324 7789",
    "sg:postcode":"32746",
    "sg:province":"FL",
    "sg:tags":[
        "market",
        "analysis"
    ],
    "wof:name":"G J Williams & Assoc Inc",
    "wof:placetype":"venue"
},
  "geometry": {"coordinates":[-81.320735,28.758919],"type":"Point"}
}