{
  "type": "Feature",
  "properties": {
    "addr:full":"200 S Scenic Hwy Frostproof FL 33843",
    "addr:housenumber":"200",
    "addr:postcode":"33843",
    "addr:street":"S Scenic Hwy",
    "iso:country":"US",
    "sg:address":"200 S Scenic Hwy",
    "sg:city":"Frostproof",
    "sg:classifiers":[
        {
            "category":"Real Estate",
            "subcategory":"Real Estate Services",
            "type":"Services"
        },
        {
            "category":"Banks & Credit Unions",
            "subcategory":"Financial Services",
            "type":"Services"
        }
    ],
    "sg:phone":"+1 863 635 4762",
    "sg:postcode":"33843",
    "sg:province":"FL",
    "sg:tags":[
        "loan",
        "mortgage"
    ],
    "wof:name":"Tmg Mortgage",
    "wof:placetype":"venue"
},
  "geometry": {"coordinates":[-81.53051000000001,27.743601],"type":"Point"}
}