{
  "type": "Feature",
  "properties": {
    "addr:full":"3120 Kumquat Dr Edgewater FL 32141",
    "addr:housenumber":"3120",
    "addr:postcode":"32141",
    "addr:street":"Kumquat Dr",
    "iso:country":"US",
    "sg:address":"3120 Kumquat Dr",
    "sg:city":"Edgewater",
    "sg:classifiers":[
        {
            "category":"Manufacturing",
            "subcategory":"Leather Goods",
            "type":"Manufacturing & Wholesale Goods"
        }
    ],
    "sg:phone":"+1 386 424 1792",
    "sg:postcode":"32141",
    "sg:province":"FL",
    "sg:tags":[
        "mfg",
        "cut",
        "footwear",
        "stock"
    ],
    "wof:name":"Custom Surface Works Inc",
    "wof:placetype":"venue"
},
  "geometry": {"coordinates":[-80.893942,28.942453],"type":"Point"}
}