{
  "type": "Feature",
  "properties": {
    "addr:full":"1100 N Federal Hwy Hollywood FL 33020",
    "addr:housenumber":"1100",
    "addr:postcode":"33020",
    "addr:street":"N Federal Hwy",
    "iso:country":"US",
    "sg:address":"1100 N Federal Hwy",
    "sg:city":"Hollywood",
    "sg:classifiers":[
        {
            "category":"Restaurant",
            "type":"Food & Drink"
        }
    ],
    "sg:phone":"+1 954 923 2835",
    "sg:postcode":"33020",
    "sg:province":"FL",
    "sg:tags":[
        "caterer"
    ],
    "wof:name":"Spectacular Affairs",
    "wof:placetype":"venue"
},
  "geometry": {"coordinates":[-80.143237,26.021238],"type":"Point"}
}