{
  "type": "Feature",
  "properties": {
    "addr:full":"2605 Ponce De Leon Blvd Coral Gables FL 33134",
    "addr:housenumber":"2605",
    "addr:postcode":"33134",
    "addr:street":"Ponce De Leon Blvd",
    "iso:country":"US",
    "sg:address":"2605 Ponce De Leon Blvd",
    "sg:city":"Coral Gables",
    "sg:classifiers":[
        {
            "category":"Professional",
            "subcategory":"Lawyer & Legal Services",
            "type":"Services"
        }
    ],
    "sg:phone":"+1 305 441 7091",
    "sg:postcode":"33134",
    "sg:province":"FL",
    "sg:website":"www.schoenlawoffice.com",
    "wof:name":"Drucker Jonathan PA",
    "wof:placetype":"venue"
},
  "geometry": {"coordinates":[-80.25840700000001,25.747854],"type":"Point"}
}