{
  "type": "Feature",
  "properties": {
    "addr:full":"1735 NW 107th St Miami FL 33167",
    "addr:housenumber":"1735",
    "addr:postcode":"33167",
    "addr:street":"Nw 107Th St",
    "iso:country":"US",
    "sg:address":"1735 NW 107th St",
    "sg:city":"Miami",
    "sg:classifiers":[
        {
            "category":"Building & Trades",
            "subcategory":"Construction",
            "type":"Services"
        }
    ],
    "sg:phone":"+1 305 685 6133",
    "sg:postcode":"33167",
    "sg:province":"FL",
    "sg:tags":[
        "contractor"
    ],
    "wof:name":"DM Maynard Construction Inc",
    "wof:placetype":"venue"
},
  "geometry": {"coordinates":[-80.226968,25.87237],"type":"Point"}
}