{
  "type": "Feature",
  "properties": {
    "iso:country":"US",
    "sg:address":"39 Harrison Ave",
    "sg:city":"Panama City",
    "sg:classifiers":[
        {
            "category":"Wholesale",
            "subcategory":"Durable Goods & Equipment",
            "type":"Manufacturing & Wholesale Goods"
        }
    ],
    "sg:phone":"+1 850 785 1368",
    "sg:postcode":"32401",
    "sg:province":"FL",
    "sg:tags":[
        "professional",
        "photocopying"
    ],
    "wof:name":"Graphic Media Inc",
    "wof:placetype":"venue"
},
  "geometry": {"coordinates":[-85.662436,30.153592],"type":"Point"}
}