{
  "type": "Feature",
  "properties": {
    "iso:country":"US",
    "sg:address":"3500 Aloma Ave",
    "sg:city":"Winter Park",
    "sg:classifiers":[
        {
            "category":"Building & Trades",
            "subcategory":"Construction",
            "type":"Services"
        }
    ],
    "sg:phone":"+1 407 293 3582",
    "sg:postcode":"32792",
    "sg:province":"FL",
    "sg:tags":[
        "contractor"
    ],
    "wof:name":"Kirk Mechanical Services",
    "wof:placetype":"venue"
},
  "geometry": {"coordinates":[-81.30145400000001,28.605637],"type":"Point"}
}