{
  "type": "Feature",
  "properties": {
    "iso:country":"US",
    "sg:address":"13315 Antonio Way",
    "sg:city":"Dade City",
    "sg:classifiers":[
        {
            "category":"Building & Trades",
            "subcategory":"Electrical",
            "type":"Services"
        }
    ],
    "sg:phone":"+1 352 588 9792",
    "sg:postcode":"33525",
    "sg:province":"FL",
    "sg:tags":[
        "electrical",
        "contractor"
    ],
    "wof:name":"Shan G Miller Electric",
    "wof:placetype":"venue"
},
  "geometry": {"coordinates":[-82.278505,28.352047],"type":"Point"}
}