{
  "type": "Feature",
  "properties": {
    "addr:full":"2109 Polo Club Dr Kissimmee FL 34741",
    "addr:housenumber":"2109",
    "addr:postcode":"34741",
    "addr:street":"Polo Club Dr",
    "iso:country":"US",
    "sg:address":"2109 Polo Club Dr",
    "sg:city":"Kissimmee",
    "sg:classifiers":[
        {
            "category":"Real Estate",
            "subcategory":"Real Estate Services",
            "type":"Services"
        }
    ],
    "sg:phone":"+1 407 846 6008",
    "sg:postcode":"34741",
    "sg:province":"FL",
    "sg:tags":[
        "vacancy",
        "apartment",
        "rental",
        "finder",
        "listing"
    ],
    "sg:website":"http://www.jmg1.com",
    "wof:name":"Polo South Apartments",
    "wof:placetype":"venue"
},
  "geometry": {"coordinates":[-81.437592,28.309604],"type":"Point"}
}