{
  "type": "Feature",
  "properties": {
    "iso:country":"US",
    "sg:address":"4600 Bruce Herd Ln",
    "sg:city":"Fort Myers",
    "sg:classifiers":[
        {
            "category":"Sports & Exercise",
            "subcategory":"Golf",
            "type":"Entertainment"
        }
    ],
    "sg:phone":"+1 239 321 7485",
    "sg:postcode":"33901",
    "sg:province":"FL",
    "wof:name":"Eastwood Golf Course Pro Shop",
    "wof:placetype":"venue"
},
  "geometry": {"coordinates":[-81.867203,26.6189],"type":"Point"}
}