{
  "type": "Feature",
  "properties": {
    "addr:full":"3650 21st Ave SW Naples FL 34117",
    "addr:housenumber":"3650",
    "addr:postcode":"34117",
    "addr:street":"21St Ave Sw",
    "iso:country":"US",
    "sg:address":"3650 21st Ave SW",
    "sg:city":"Naples",
    "sg:classifiers":[
        {
            "category":"Building & Trades",
            "subcategory":"Landscaping Services",
            "type":"Services"
        }
    ],
    "sg:phone":"+1 239 455 4622",
    "sg:postcode":"34117",
    "sg:province":"FL",
    "wof:name":"Von Holle Robert Lawn Maint",
    "wof:placetype":"venue"
},
  "geometry": {"coordinates":[-81.67934,26.190555],"type":"Point"}
}