{
  "type": "Feature",
  "properties": {
    "addr:full":"1417 29th Ave E Bradenton FL 34208",
    "addr:housenumber":"1417",
    "addr:postcode":"34208",
    "addr:street":"29Th Ave E",
    "iso:country":"US",
    "sg:address":"1417 29th Ave E",
    "sg:city":"Bradenton",
    "sg:classifiers":[
        {
            "category":"Building & Trades",
            "subcategory":"Construction",
            "type":"Services"
        }
    ],
    "sg:phone":"+1 941 750 0829",
    "sg:postcode":"34208",
    "sg:province":"FL",
    "sg:tags":[
        "carpentry",
        "contractor"
    ],
    "wof:name":"Darling Roger A Carpentry",
    "wof:placetype":"venue"
},
  "geometry": {"coordinates":[-82.54779499999999,27.47429],"type":"Point"}
}