{
  "type": "Feature",
  "properties": {
    "addr:full":"1680 SW Bayshore Blvd Port St Lucie FL 34984",
    "addr:housenumber":"1680",
    "addr:postcode":"34984",
    "addr:street":"Sw Bayshore Blvd",
    "iso:country":"US",
    "sg:address":"1680 SW Bayshore Blvd",
    "sg:city":"Port St Lucie",
    "sg:classifiers":[
        {
            "category":"Professional",
            "subcategory":"Lawyer & Legal Services",
            "type":"Services"
        }
    ],
    "sg:phone":"+1 772 344 9044",
    "sg:postcode":"34984",
    "sg:province":"FL",
    "sg:tags":[
        "attorney"
    ],
    "wof:name":"Elkins & Freedman",
    "wof:placetype":"venue"
},
  "geometry": {"coordinates":[-80.364861,27.290319],"type":"Point"}
}