{
  "type": "Feature",
  "properties": {
    "iso:country":"US",
    "sg:address":"7292 4th St N",
    "sg:city":"St Petersburg",
    "sg:classifiers":[
        {
            "category":"Personal",
            "subcategory":"Hair Removal",
            "type":"Services"
        },
        {
            "category":"Personal",
            "subcategory":"Beauty Salon",
            "type":"Services"
        }
    ],
    "sg:phone":"+1 727 896 8149",
    "sg:postcode":"33702",
    "sg:province":"FL",
    "sg:tags":[
        "shop",
        "removing"
    ],
    "wof:name":"New Image Clinique Inc",
    "wof:placetype":"venue"
},
  "geometry": {"coordinates":[-82.638762,27.838645],"type":"Point"}
}