{
  "type": "Feature",
  "properties": {
    "addr:full":"205 W 7th St Panama City FL 32401",
    "addr:housenumber":"205",
    "addr:postcode":"32401",
    "addr:street":"W 7Th St",
    "iso:country":"US",
    "sg:address":"205 W 7th St",
    "sg:city":"Panama City",
    "sg:classifiers":[
        {
            "category":"Insurance",
            "subcategory":"Insurance Agent",
            "type":"Services"
        }
    ],
    "sg:phone":"+1 850 769 2225",
    "sg:postcode":"32401",
    "sg:province":"FL",
    "sg:website":"www.blackwellinsurance.net",
    "wof:name":"Blackwell Insurance",
    "wof:placetype":"venue"
},
  "geometry": {"coordinates":[-85.663264,30.160578],"type":"Point"}
}