{
  "type": "Feature",
  "properties": {
    "iso:country":"US",
    "sg:address":"2001 N Federal Hwy",
    "sg:city":"Pompano Beach",
    "sg:classifiers":[
        {
            "category":"Personal",
            "subcategory":"Beauty Salon",
            "type":"Services"
        }
    ],
    "sg:phone":"+1 954 782 0088",
    "sg:postcode":"33062",
    "sg:province":"FL",
    "wof:name":"Shear Excitement",
    "wof:placetype":"venue"
},
  "geometry": {"coordinates":[-80.100371,26.25569],"type":"Point"}
}