{
  "type": "Feature",
  "properties": {
    "iso:country":"US",
    "sg:address":"15715 S Dixie Hwy Ste 211",
    "sg:city":"Miami",
    "sg:classifiers":[
        {
            "category":"Professional",
            "subcategory":"Lawyer & Legal Services",
            "type":"Services"
        }
    ],
    "sg:phone":"+1 305 256 2719",
    "sg:postcode":"33157",
    "sg:province":"FL",
    "wof:name":"Zirlin & Rounsaville Property Tax Advisors Pl",
    "wof:placetype":"venue"
},
  "geometry": {"coordinates":[-80.34272199999999,25.624702],"type":"Point"}
}