{
  "type": "Feature",
  "properties": {
    "addr:full":"825 US Hwy 1 West Palm Beach FL 33403",
    "addr:housenumber":"825",
    "addr:postcode":"33403",
    "addr:street":"Us Hwy 1",
    "iso:country":"US",
    "sg:address":"825 US Hwy 1",
    "sg:city":"West Palm Beach",
    "sg:classifiers":[
        {
            "category":"Food & Beverages",
            "subcategory":"Groceries & Convenience Stores",
            "type":"Retail Goods"
        }
    ],
    "sg:phone":"+1 561 844 7549",
    "sg:postcode":"33403",
    "sg:province":"FL",
    "wof:name":"Neighborhood Grocery",
    "wof:placetype":"venue"
},
  "geometry": {"coordinates":[-80.05483700000001,26.799866],"type":"Point"}
}