{
  "type": "Feature",
  "properties": {
    "addr:full":"955 54th Ave N St Petersburg FL 33703",
    "addr:housenumber":"955",
    "addr:postcode":"33703",
    "addr:street":"54Th Ave N",
    "iso:country":"US",
    "sg:address":"955 54th Ave N",
    "sg:city":"St Petersburg",
    "sg:classifiers":[
        {
            "category":"Shopping",
            "subcategory":"Optical Goods",
            "type":"Retail Goods"
        }
    ],
    "sg:phone":"+1 727 525 1000",
    "sg:postcode":"33703",
    "sg:province":"FL",
    "wof:name":"Regenhardt Optical",
    "wof:placetype":"venue"
},
  "geometry": {"coordinates":[-82.648157,27.821258],"type":"Point"}
}