{
  "type": "Feature",
  "properties": {
    "iso:country":"US",
    "sg:address":"401 E Gulf Blvd",
    "sg:city":"Panama City",
    "sg:classifiers":[
        {
            "category":"Retail",
            "subcategory":"Auto Repair",
            "type":"Services"
        }
    ],
    "sg:phone":"+1 850 234 5175",
    "sg:postcode":"32413",
    "sg:province":"FL",
    "sg:tags":[
        "exhaust"
    ],
    "wof:name":"Auto Pump Inc",
    "wof:placetype":"venue"
},
  "geometry": {"coordinates":[-85.855735,30.210454],"type":"Point"}
}