{
  "type": "Feature",
  "properties": {
    "iso:country":"US",
    "sg:address":"7976 Miramar Pkwy",
    "sg:city":"Hollywood",
    "sg:classifiers":[
        {
            "category":"Banks & Credit Unions",
            "subcategory":"Bank",
            "type":"Services"
        }
    ],
    "sg:phone":"+1 954 987 8077",
    "sg:postcode":"33023",
    "sg:province":"FL",
    "sg:tags":[
        "mortgage",
        "loan",
        "broker",
        "real estate"
    ],
    "wof:name":"A Atlantic Coast Mortgage Corp",
    "wof:placetype":"venue"
},
  "geometry": {"coordinates":[-80.24633799999999,25.981504],"type":"Point"}
}