{
  "type": "Feature",
  "properties": {
    "addr:full":"125 N Riverside Dr Pompano Beach FL 33062",
    "addr:housenumber":"125",
    "addr:postcode":"33062",
    "addr:street":"N Riverside Dr",
    "iso:country":"US",
    "sg:address":"125 N Riverside Dr",
    "sg:city":"Pompano Beach",
    "sg:classifiers":[
        {
            "category":"Recreation",
            "type":"Entertainment"
        }
    ],
    "sg:phone":"+1 954 784 1734",
    "sg:postcode":"33062",
    "sg:province":"FL",
    "sg:tags":[
        "club",
        "travel"
    ],
    "wof:name":"Resorts Intl Marketing",
    "wof:placetype":"venue"
},
  "geometry": {"coordinates":[-80.092411,26.234045],"type":"Point"}
}