{
  "type": "Feature",
  "properties": {
    "addr:full":"19501 NE 10th Ave Ste H North Miami Beach FL 33179",
    "addr:housenumber":"19501",
    "addr:postcode":"33179",
    "addr:street":"Ne 10Th Ave Ste H",
    "iso:country":"US",
    "sg:address":"19501 NE 10th Ave Ste H",
    "sg:city":"North Miami Beach",
    "sg:classifiers":[
        {
            "category":"Communications",
            "type":"Services"
        }
    ],
    "sg:phone":"+1 305 655 0822",
    "sg:postcode":"33179",
    "sg:province":"FL",
    "sg:tags":[
        "medium",
        "mass"
    ],
    "wof:name":"Martin Outdoor Media",
    "wof:placetype":"venue"
},
  "geometry": {"coordinates":[-80.181634,25.955023],"type":"Point"}
}