{
  "type": "Feature",
  "properties": {
    "addr:full":"831 NW 7th Ter Fort Lauderdale FL 33311",
    "addr:housenumber":"831",
    "addr:postcode":"33311",
    "addr:street":"Nw 7Th Ter",
    "iso:country":"US",
    "sg:address":"831 NW 7th Ter",
    "sg:city":"Fort Lauderdale",
    "sg:classifiers":[
        {
            "category":"Retail",
            "subcategory":"Auto Repair",
            "type":"Services"
        }
    ],
    "sg:phone":"+1 954 767 4509",
    "sg:postcode":"33311",
    "sg:province":"FL",
    "sg:tags":[
        "automobile",
        "co",
        "drive",
        "transporter"
    ],
    "wof:name":"Brothers Auto Transport Inc",
    "wof:placetype":"venue"
},
  "geometry": {"coordinates":[-80.15191900000001,26.134272],"type":"Point"}
}