{
  "type": "Feature",
  "properties": {
    "iso:country":"US",
    "sg:address":"4058 Fiesta Plz",
    "sg:city":"Tampa",
    "sg:classifiers":[
        {
            "category":"Shopping",
            "type":"Retail Goods"
        }
    ],
    "sg:phone":"+1 813 875 6697",
    "sg:postcode":"33607",
    "sg:province":"FL",
    "sg:tags":[
        "hearing",
        "equipment",
        "supply",
        "merchandise",
        "impaired"
    ],
    "wof:name":"H-Ear Better Inc",
    "wof:placetype":"venue"
},
  "geometry": {"coordinates":[-82.48537399999999,27.975459],"type":"Point"}
}