{
  "type": "Feature",
  "properties": {
    "iso:country":"US",
    "sg:address":"950 Marsh Landing Pkwy",
    "sg:city":"Jacksonville Beach",
    "sg:classifiers":[
        {
            "category":"Restaurant",
            "type":"Food & Drink"
        }
    ],
    "sg:menulink":"http://www.allmenus.com/fl/jacksonville/200022-stonewoods-restaurant/menu/",
    "sg:phone":"+1 904 285 2311",
    "sg:postcode":"32250",
    "sg:province":"FL",
    "sg:tags":[
        "new",
        "american"
    ],
    "wof:name":"Stonewoods Restaurant",
    "wof:placetype":"venue"
},
  "geometry": {"coordinates":[-81.394712,30.255866],"type":"Point"}
}