{
  "type": "Feature",
  "properties": {
    "addr:full":"20700 Basin Dr Estero FL 33928",
    "addr:housenumber":"20700",
    "addr:postcode":"33928",
    "addr:street":"Basin Dr",
    "iso:country":"US",
    "sg:address":"20700 Basin Dr",
    "sg:city":"Estero",
    "sg:classifiers":[
        {
            "category":"Real Estate",
            "subcategory":"Real Estate Operator",
            "type":"Services"
        }
    ],
    "sg:phone":"+1 239 992 3533",
    "sg:postcode":"33928",
    "sg:province":"FL",
    "sg:tags":[
        "mobile",
        "home",
        "park",
        "community",
        "operates"
    ],
    "wof:name":"Mariner's Cove",
    "wof:placetype":"venue"
},
  "geometry": {"coordinates":[-81.82549,26.44052],"type":"Point"}
}