{
  "type": "Feature",
  "properties": {
    "iso:country":"US",
    "sg:address":"3910 US Hwy 301",
    "sg:city":"Tampa",
    "sg:classifiers":[
        {
            "category":"Real Estate",
            "subcategory":"Surveying",
            "type":"Services"
        }
    ],
    "sg:phone":"+1 813 621 2732",
    "sg:postcode":"33619",
    "sg:province":"FL",
    "sg:tags":[
        "surveyor",
        "mapper",
        "consultant"
    ],
    "sg:website":"www.geomapsurv.com",
    "wof:name":"Geo Map Technologies Inc",
    "wof:placetype":"venue"
},
  "geometry": {"coordinates":[-82.360147,27.981378],"type":"Point"}
}