{
  "type": "Feature",
  "properties": {
    "iso:country":"US",
    "sg:address":"52 W 3rd St",
    "sg:city":"Atlantic Beach",
    "sg:classifiers":[
        {
            "category":"Manufacturing",
            "subcategory":"Toys & Sporting Goods",
            "type":"Manufacturing & Wholesale Goods"
        }
    ],
    "sg:phone":"+1 904 247 0808",
    "sg:postcode":"32233",
    "sg:province":"FL",
    "sg:tags":[
        "water",
        "equipment",
        "sport",
        "mfg"
    ],
    "wof:name":"D Sea International",
    "wof:placetype":"venue"
},
  "geometry": {"coordinates":[-81.41983399999999,30.326806],"type":"Point"}
}