{
  "type": "Feature",
  "properties": {
    "iso:country":"US",
    "sg:address":"2049 Dellwood Ave",
    "sg:city":"Jacksonville",
    "sg:classifiers":[
        {
            "category":"Manufacturing",
            "subcategory":"Textiles",
            "type":"Manufacturing & Wholesale Goods"
        }
    ],
    "sg:phone":"+1 904 353 6028",
    "sg:postcode":"32204",
    "sg:province":"FL",
    "sg:tags":[
        "sewing",
        "contractor"
    ],
    "wof:name":"Kimi Kb Creations Inc",
    "wof:placetype":"venue"
},
  "geometry": {"coordinates":[-81.68356,30.318033],"type":"Point"}
}