{
  "type": "Feature",
  "properties": {
    "iso:country":"US",
    "sg:address":"101 E Fern St",
    "sg:city":"Tampa",
    "sg:classifiers":[
        {
            "category":"Government",
            "subcategory":"Office",
            "type":"Public Place"
        }
    ],
    "sg:phone":"+1 813 264 3800",
    "sg:postcode":"33604",
    "sg:province":"FL",
    "sg:tags":[
        "library"
    ],
    "wof:name":"Public Library Cooperative",
    "wof:placetype":"venue"
},
  "geometry": {"coordinates":[-82.457509,28.004998],"type":"Point"}
}