{
  "type": "Feature",
  "properties": {
    "iso:country":"US",
    "sg:address":"3825 NW 49th St",
    "sg:city":"Tamarac",
    "sg:classifiers":[
        {
            "category":"Autos & Motor Vehicles",
            "subcategory":"Automobile Sales",
            "type":"Retail Goods"
        }
    ],
    "sg:phone":"+1 954 735 3232",
    "sg:postcode":"33309",
    "sg:province":"FL",
    "sg:tags":[
        "car",
        "dealer"
    ],
    "wof:name":"Auto Coat Inc",
    "wof:placetype":"venue"
},
  "geometry": {"coordinates":[-80.20250900000001,26.185498],"type":"Point"}
}