{
  "type": "Feature",
  "properties": {
    "iso:country":"US",
    "sg:address":"109 Laura St",
    "sg:city":"Dundee",
    "sg:classifiers":[
        {
            "category":"Social Services",
            "subcategory":"Child Care",
            "type":"Services"
        }
    ],
    "sg:phone":"+1 863 439 2214",
    "sg:postcode":"33838",
    "sg:province":"FL",
    "wof:name":"Dana's Daycare",
    "wof:placetype":"venue"
},
  "geometry": {"coordinates":[-81.630561,28.01882],"type":"Point"}
}