{
  "type": "Feature",
  "properties": {
    "iso:country":"US",
    "sg:address":"3300 SE 6th Ave",
    "sg:city":"Fort Lauderdale",
    "sg:classifiers":[
        {
            "category":"Manufacturing",
            "subcategory":"Building Materials",
            "type":"Manufacturing & Wholesale Goods"
        }
    ],
    "sg:phone":"+1 954 522 0653",
    "sg:postcode":"33316",
    "sg:province":"FL",
    "sg:tags":[
        "woodwork",
        "mfg",
        "door",
        "architectural",
        "custom"
    ],
    "wof:name":"Home of",
    "wof:placetype":"venue"
},
  "geometry": {"coordinates":[-80.13807,26.08342],"type":"Point"}
}