{
  "type": "Feature",
  "properties": {
    "iso:country":"US",
    "sg:address":"6039 Collins Ave",
    "sg:city":"Miami Beach",
    "sg:classifiers":[
        {
            "category":"Personal",
            "subcategory":"Beauty Salon",
            "type":"Services"
        }
    ],
    "sg:phone":"+1 305 331 9682",
    "sg:postcode":"33140",
    "sg:province":"FL",
    "sg:tags":[
        "makeup",
        "artist"
    ],
    "wof:name":"Bridal Makeovers by Aradia",
    "wof:placetype":"venue"
},
  "geometry": {"coordinates":[-80.120079,25.843156],"type":"Point"}
}