{
  "type": "Feature",
  "properties": {
    "iso:country":"US",
    "sg:address":"1816 SE 14 Ave",
    "sg:city":"Gainesville",
    "sg:classifiers":[
        {
            "category":"Building & Trades",
            "subcategory":"Landscaping Services",
            "type":"Services"
        }
    ],
    "sg:phone":"+1 352 284 7604",
    "sg:postcode":"32641",
    "sg:province":"FL",
    "sg:tags":[
        "landscape",
        "contractor"
    ],
    "wof:name":"Pat Mitchell Landscaping",
    "wof:placetype":"venue"
},
  "geometry": {"coordinates":[-82.300263,29.638199],"type":"Point"}
}