{
  "type": "Feature",
  "properties": {
    "iso:country":"US",
    "sg:address":"130 Bomar Ct",
    "sg:city":"Longwood",
    "sg:classifiers":[
        {
            "category":"Building & Trades",
            "subcategory":"Plumbing",
            "type":"Services"
        }
    ],
    "sg:phone":"+1 407 786 3600",
    "sg:postcode":"32750",
    "sg:province":"FL",
    "sg:website":"www.milleniabath.com",
    "wof:name":"Millenia Bath",
    "wof:placetype":"venue"
},
  "geometry": {"coordinates":[-81.32851599999999,28.706519],"type":"Point"}
}