{
  "type": "Feature",
  "properties": {
    "addr:full":"1235 Cypress Rd Saint Augustine FL 32086",
    "addr:housenumber":"1235",
    "addr:postcode":"32086",
    "addr:street":"Cypress Rd",
    "iso:country":"US",
    "sg:address":"1235 Cypress Rd",
    "sg:city":"Saint Augustine",
    "sg:classifiers":[
        {
            "category":"Food & Beverages",
            "subcategory":"Groceries & Convenience Stores",
            "type":"Retail Goods"
        }
    ],
    "sg:phone":"+1 904 797 3912",
    "sg:postcode":"32086",
    "sg:province":"FL",
    "wof:name":"Lindas Grocery Cart",
    "wof:placetype":"venue"
},
  "geometry": {"coordinates":[-81.34948900000001,29.849009],"type":"Point"}
}