{
  "type": "Feature",
  "properties": {
    "addr:full":"5530 S Mason Creek Rd Homosassa FL 34448",
    "addr:housenumber":"5530",
    "addr:postcode":"34448",
    "addr:street":"S Mason Creek Rd",
    "iso:country":"US",
    "sg:address":"5530 S Mason Creek Rd",
    "sg:city":"Homosassa",
    "sg:classifiers":[
        {
            "category":"Education",
            "subcategory":"Library",
            "type":"Public Place"
        }
    ],
    "sg:phone":"+1 352 628 5626",
    "sg:postcode":"34448",
    "sg:province":"FL",
    "wof:name":"Homosassa Public Library",
    "wof:placetype":"venue"
},
  "geometry": {"coordinates":[-82.615448,28.781515],"type":"Point"}
}