{
  "type": "Feature",
  "properties": {
    "iso:country":"US",
    "sg:address":"2727 Muscatello St",
    "sg:city":"Orlando",
    "sg:classifiers":[
        {
            "category":"Professional",
            "subcategory":"Management & Consulting",
            "type":"Services"
        }
    ],
    "sg:phone":"+1 407 855 1150",
    "sg:postcode":"32837",
    "sg:province":"FL",
    "sg:tags":[
        "party",
        "planning"
    ],
    "wof:name":"Party Planners 2000",
    "wof:placetype":"venue"
},
  "geometry": {"coordinates":[-81.421865,28.386956],"type":"Point"}
}