{
  "type": "Feature",
  "properties": {
    "addr:full":"10610 Immokalee Rd Naples FL 34120",
    "addr:housenumber":"10610",
    "addr:postcode":"34120",
    "addr:street":"Immokalee Rd",
    "iso:country":"US",
    "sg:address":"10610 Immokalee Rd",
    "sg:city":"Naples",
    "sg:classifiers":[
        {
            "category":"Recreation",
            "type":"Entertainment"
        }
    ],
    "sg:phone":"+1 239 348 7433",
    "sg:postcode":"34120",
    "sg:province":"FL",
    "sg:tags":[
        "riding",
        "academy"
    ],
    "wof:name":"Collier Equestrian Center",
    "wof:placetype":"venue"
},
  "geometry": {"coordinates":[-81.652052,26.27352],"type":"Point"}
}