{
  "type": "Feature",
  "properties": {
    "iso:country":"US",
    "sg:address":"3695 Tamiami Trl",
    "sg:city":"Port Charlotte",
    "sg:classifiers":[
        {
            "category":"Professional",
            "subcategory":"Lawyer & Legal Services",
            "type":"Services"
        }
    ],
    "sg:phone":"+1 941 625 6801",
    "sg:postcode":"33952",
    "sg:province":"FL",
    "sg:tags":[
        "attorney"
    ],
    "wof:name":"Joel O Lederer",
    "wof:placetype":"venue"
},
  "geometry": {"coordinates":[-82.090068,26.975112],"type":"Point"}
}