{
  "type": "Feature",
  "properties": {
    "iso:country":"US",
    "sg:address":"1659 Jeffords St",
    "sg:city":"Clearwater",
    "sg:classifiers":[
        {
            "category":"Education",
            "subcategory":"Dance Studio",
            "type":"Public Place"
        }
    ],
    "sg:phone":"+1 727 442 0382",
    "sg:postcode":"33756",
    "sg:province":"FL",
    "wof:name":"Kinderdance",
    "wof:placetype":"venue"
},
  "geometry": {"coordinates":[-82.767454,27.952891],"type":"Point"}
}