{
  "type": "Feature",
  "properties": {
    "iso:country":"US",
    "sg:address":"4834 Grapevine Way",
    "sg:city":"Fort Lauderdale",
    "sg:classifiers":[
        {
            "category":"Professional",
            "subcategory":"Business Services",
            "type":"Services"
        }
    ],
    "sg:phone":"+1 954 970 0319",
    "sg:postcode":"33331",
    "sg:province":"FL",
    "sg:tags":[
        "equipment",
        "microfilm",
        "supply"
    ],
    "wof:name":"Imagetech Microfilm Services",
    "wof:placetype":"venue"
},
  "geometry": {"coordinates":[-80.356373,26.058889],"type":"Point"}
}