{
  "type": "Feature",
  "properties": {
    "iso:country":"US",
    "sg:address":"3511 W Bay To Bay Blvd",
    "sg:city":"Tampa",
    "sg:classifiers":[
        {
            "category":"Organizations",
            "subcategory":"Religious Organization",
            "type":"Services"
        }
    ],
    "sg:phone":"+1 813 831 3301",
    "sg:postcode":"33629",
    "sg:province":"FL",
    "sg:tags":[
        "baptist",
        "church"
    ],
    "wof:name":"Palma Ceia Baptist Church",
    "wof:placetype":"venue"
},
  "geometry": {"coordinates":[-82.501738,27.919829],"type":"Point"}
}