{
  "type": "Feature",
  "properties": {
    "iso:country":"US",
    "sg:address":"6246 Lake Lizzie Dr",
    "sg:city":"St Cloud",
    "sg:classifiers":[
        {
            "category":"Building & Trades",
            "subcategory":"Construction",
            "type":"Services"
        }
    ],
    "sg:phone":"+1 407 729 8822",
    "sg:postcode":"34771",
    "sg:province":"FL",
    "sg:tags":[
        "layer",
        "carpet"
    ],
    "wof:name":"David Chandler Floor Instltn",
    "wof:placetype":"venue"
},
  "geometry": {"coordinates":[-81.192806,28.239641],"type":"Point"}
}