{
  "type": "Feature",
  "properties": {
    "iso:country":"US",
    "sg:address":"11 Moultrie Creek Cir",
    "sg:city":"Saint Augustine",
    "sg:classifiers":[
        {
            "category":"Shopping",
            "type":"Retail Goods"
        }
    ],
    "sg:phone":"+1 904 669 1103",
    "sg:postcode":"32086",
    "sg:province":"FL",
    "sg:tags":[
        "merchandise"
    ],
    "wof:name":"Old City Candles",
    "wof:placetype":"venue"
},
  "geometry": {"coordinates":[-81.356567,29.83553],"type":"Point"}
}