{
  "type": "Feature",
  "properties": {
    "iso:country":"US",
    "sg:address":"10870 NW 138th St",
    "sg:city":"Hialeah",
    "sg:classifiers":[
        {
            "category":"Park",
            "type":"Public Place"
        }
    ],
    "sg:phone":"+1 305 821 9701",
    "sg:postcode":"33018",
    "sg:province":"FL",
    "wof:name":"138th St Commercial Park Inc",
    "wof:placetype":"venue"
},
  "geometry": {"coordinates":[-80.37343,25.898491],"type":"Point"}
}