{
  "type": "Feature",
  "properties": {
    "iso:country":"US",
    "sg:address":"11050 Summerlin Square Dr Unit 101",
    "sg:city":"Fort Myers Beach",
    "sg:classifiers":[
        {
            "category":"Real Estate",
            "subcategory":"Real Estate Services",
            "type":"Services"
        }
    ],
    "sg:phone":"+1 239 454 8900",
    "sg:postcode":"33931",
    "sg:province":"FL",
    "sg:tags":[
        "management",
        "property"
    ],
    "sg:website":"www.c21prestigerealty.com",
    "wof:name":"Century 21 Prestige Realty Group",
    "wof:placetype":"venue"
},
  "geometry": {"coordinates":[-81.93635500000001,26.49318],"type":"Point"}
}