{
  "type": "Feature",
  "properties": {
    "iso:country":"US",
    "sg:address":"4241 Baymeadows Rd",
    "sg:city":"Jacksonville",
    "sg:classifiers":[
        {
            "category":"Professional",
            "subcategory":"Detective & Security Services",
            "type":"Services"
        }
    ],
    "sg:phone":"+1 904 737 1011",
    "sg:postcode":"32217",
    "sg:province":"FL",
    "wof:name":"CEO Private Investigative",
    "wof:placetype":"venue"
},
  "geometry": {"coordinates":[-81.60946,30.218973],"type":"Point"}
}