{
  "type": "Feature",
  "properties": {
    "iso:country":"US",
    "sg:address":"1102 Michigan Ct",
    "sg:city":"Winter Springs",
    "sg:classifiers":[
        {
            "category":"Building & Trades",
            "subcategory":"Construction",
            "type":"Services"
        }
    ],
    "sg:phone":"+1 407 327 7377",
    "sg:postcode":"32708",
    "sg:province":"FL",
    "sg:tags":[
        "house"
    ],
    "wof:name":"WCI Construction Inc",
    "wof:placetype":"venue"
},
  "geometry": {"coordinates":[-81.23665099999999,28.667359],"type":"Point"}
}