{
  "type": "Feature",
  "properties": {
    "iso:country":"US",
    "sg:address":"6019 SE 122nd Pl",
    "sg:city":"Belleview",
    "sg:classifiers":[
        {
            "category":"Real Estate",
            "subcategory":"Real Estate Services",
            "type":"Services"
        },
        {
            "category":"Real Estate",
            "subcategory":"Real Estate Agent",
            "type":"Services"
        }
    ],
    "sg:phone":"+1 352 245 6592",
    "sg:postcode":"34420",
    "sg:province":"FL",
    "sg:tags":[
        "management"
    ],
    "wof:name":"Floyd Graddy Real Estate",
    "wof:placetype":"venue"
},
  "geometry": {"coordinates":[-82.05175800000001,29.04479],"type":"Point"}
}