{
  "type": "Feature",
  "properties": {
    "addr:full":"4852 11th Ave Cir E Bradenton FL 34208",
    "addr:housenumber":"4852",
    "addr:postcode":"34208",
    "addr:street":"11Th Ave Cir E",
    "iso:country":"US",
    "sg:address":"4852 11th Ave Cir E",
    "sg:city":"Bradenton",
    "sg:classifiers":[
        {
            "category":"Education",
            "subcategory":"Special Training",
            "type":"Public Place"
        }
    ],
    "sg:phone":"+1 941 747 8477",
    "sg:postcode":"34208",
    "sg:province":"FL",
    "sg:tags":[
        "tutoring"
    ],
    "wof:name":"David Smith",
    "wof:placetype":"venue"
},
  "geometry": {"coordinates":[-82.502657,27.487731],"type":"Point"}
}