{
  "type": "Feature",
  "properties": {
    "addr:full":"7817 N 52nd St Tampa FL 33617",
    "addr:housenumber":"7817",
    "addr:postcode":"33617",
    "addr:street":"N 52Nd St",
    "iso:country":"US",
    "sg:address":"7817 N 52nd St",
    "sg:city":"Tampa",
    "sg:classifiers":[
        {
            "category":"Shopping",
            "subcategory":"Florist",
            "type":"Retail Goods"
        }
    ],
    "sg:phone":"+1 813 984 9184",
    "sg:postcode":"33617",
    "sg:province":"FL",
    "wof:name":"Gentlemen Gestures",
    "wof:placetype":"venue"
},
  "geometry": {"coordinates":[-82.399393,28.018374],"type":"Point"}
}