{
  "type": "Feature",
  "properties": {
    "addr:full":"880 Mandalay Ave Clearwater FL 33767",
    "addr:housenumber":"880",
    "addr:postcode":"33767",
    "addr:street":"Mandalay Ave",
    "iso:country":"US",
    "sg:address":"880 Mandalay Ave",
    "sg:city":"Clearwater",
    "sg:classifiers":[
        {
            "category":"Wholesale",
            "subcategory":"Machinery & Supplies",
            "type":"Manufacturing & Wholesale Goods"
        }
    ],
    "sg:phone":"+1 727 449 2343",
    "sg:postcode":"33767",
    "sg:province":"FL",
    "sg:tags":[
        "fire",
        "extinguisher",
        "retail"
    ],
    "wof:name":"Ansul  Incorporated",
    "wof:placetype":"venue"
},
  "geometry": {"coordinates":[-82.826942,27.996157],"type":"Point"}
}