{
  "type": "Feature",
  "properties": {
    "iso:country":"US",
    "sg:address":"4991 Hickory Wood Dr",
    "sg:city":"Naples",
    "sg:classifiers":[
        {
            "category":"Personal",
            "type":"Services"
        }
    ],
    "sg:phone":"+1 239 352 7277",
    "sg:postcode":"34119",
    "sg:province":"FL",
    "sg:tags":[
        "miscellaneous"
    ],
    "wof:name":"Pelican Home Svc",
    "wof:placetype":"venue"
},
  "geometry": {"coordinates":[-81.707819,26.237795],"type":"Point"}
}