{
  "type": "Feature",
  "properties": {
    "iso:country":"US",
    "sg:address":"480 Tall Pines Rd",
    "sg:city":"West Palm Beach",
    "sg:classifiers":[
        {
            "category":"Wholesale",
            "subcategory":"Non-durable Goods",
            "type":"Manufacturing & Wholesale Goods"
        }
    ],
    "sg:phone":"+1 561 615 4008",
    "sg:postcode":"33413",
    "sg:province":"FL",
    "sg:tags":[
        "pet",
        "supply"
    ],
    "wof:name":"Barkhouse Baking Co",
    "wof:placetype":"venue"
},
  "geometry": {"coordinates":[-80.149294,26.683313],"type":"Point"}
}