{
  "type": "Feature",
  "properties": {
    "addr:full":"447 3rd Ave N St Petersburg FL 33701",
    "addr:housenumber":"447",
    "addr:postcode":"33701",
    "addr:street":"3Rd Ave N",
    "iso:country":"US",
    "sg:address":"447 3rd Ave N",
    "sg:city":"St Petersburg",
    "sg:classifiers":[
        {
            "category":"Insurance",
            "subcategory":"Insurance Agent",
            "type":"Services"
        }
    ],
    "sg:phone":"+1 727 894 8617",
    "sg:postcode":"33701",
    "sg:province":"FL",
    "wof:name":"Claims Management Adm Inc",
    "wof:placetype":"venue"
},
  "geometry": {"coordinates":[-82.63919799999999,27.775013],"type":"Point"}
}