{
  "type": "Feature",
  "properties": {
    "addr:full":"1010 Red Bug Lake Rd Casselberry FL 32707",
    "addr:housenumber":"1010",
    "addr:postcode":"32707",
    "addr:street":"Red Bug Lake Rd",
    "iso:country":"US",
    "sg:address":"1010 Red Bug Lake Rd",
    "sg:city":"Casselberry",
    "sg:classifiers":[
        {
            "category":"Professional",
            "subcategory":"Credit Reporting & Collection",
            "type":"Services"
        }
    ],
    "sg:phone":"+1 407 339 2439",
    "sg:postcode":"32707",
    "sg:province":"FL",
    "sg:tags":[
        "system"
    ],
    "wof:name":"Check Care Systems Inc",
    "wof:placetype":"venue"
},
  "geometry": {"coordinates":[-81.316343,28.647051],"type":"Point"}
}