{
  "type": "Feature",
  "properties": {
    "addr:full":"16686 75th Pl N Loxahatchee FL 33470",
    "addr:housenumber":"16686",
    "addr:postcode":"33470",
    "addr:street":"75Th Pl N",
    "iso:country":"US",
    "sg:address":"16686 75th Pl N",
    "sg:city":"Loxahatchee",
    "sg:classifiers":[
        {
            "category":"Professional",
            "subcategory":"Business Services",
            "type":"Services"
        }
    ],
    "sg:phone":"+1 561 204 4191",
    "sg:postcode":"33470",
    "sg:province":"FL",
    "sg:tags":[
        "pool",
        "swimming"
    ],
    "wof:name":"Xpert Pool Repair Inc",
    "wof:placetype":"venue"
},
  "geometry": {"coordinates":[-80.30484300000001,26.787591],"type":"Point"}
}