{
  "type": "Feature",
  "properties": {
    "iso:country":"US",
    "sg:address":"91 Enchanting Blvd",
    "sg:city":"Naples",
    "sg:classifiers":[
        {
            "category":"Freight",
            "type":"Transportation"
        }
    ],
    "sg:phone":"+1 239 732 5990",
    "sg:postcode":"34112",
    "sg:province":"FL",
    "wof:name":"Pinder Transport LLC",
    "wof:placetype":"venue"
},
  "geometry": {"coordinates":[-81.762731,26.118798],"type":"Point"}
}