{
  "type": "Feature",
  "properties": {
    "iso:country":"US",
    "sg:address":"6900 Phillips Hwy",
    "sg:city":"Jacksonville",
    "sg:classifiers":[
        {
            "category":"Building & Trades",
            "subcategory":"Construction",
            "type":"Services"
        }
    ],
    "sg:phone":"+1 904 296 2949",
    "sg:postcode":"32216",
    "sg:province":"FL",
    "sg:tags":[
        "marble",
        "terrazzo"
    ],
    "wof:name":"Marblelife Of Ne Florida",
    "wof:placetype":"venue"
},
  "geometry": {"coordinates":[-81.601545,30.245703],"type":"Point"}
}