{
  "type": "Feature",
  "properties": {
    "addr:full":"4160 N Armenia Ave Tampa FL 33607",
    "addr:housenumber":"4160",
    "addr:postcode":"33607",
    "addr:street":"N Armenia Ave",
    "iso:country":"US",
    "sg:address":"4160 N Armenia Ave",
    "sg:city":"Tampa",
    "sg:classifiers":[
        {
            "category":"Health Services",
            "subcategory":"Doctor",
            "type":"Services"
        }
    ],
    "sg:phone":"+1 813 872 9384",
    "sg:postcode":"33607",
    "sg:province":"FL",
    "sg:tags":[
        "medicine",
        "internal",
        "cardiologist"
    ],
    "wof:name":"Luis E Bencomo MD PA",
    "wof:placetype":"venue"
},
  "geometry": {"coordinates":[-82.484821,27.978114],"type":"Point"}
}