{
  "type": "Feature",
  "properties": {
    "iso:country":"US",
    "sg:address":"3949 Forsyth Rd",
    "sg:city":"Winter Park",
    "sg:classifiers":[
        {
            "category":"Professional",
            "type":"Services"
        }
    ],
    "sg:phone":"+1 407 671 5757",
    "sg:postcode":"32792",
    "sg:province":"FL",
    "sg:tags":[
        "establishment"
    ],
    "wof:name":"Davidson Specialties",
    "wof:placetype":"venue"
},
  "geometry": {"coordinates":[-81.298985,28.602514],"type":"Point"}
}