{
  "type": "Feature",
  "properties": {
    "iso:country":"US",
    "sg:address":"1615 Colonial Blvd",
    "sg:city":"Fort Myers",
    "sg:classifiers":[
        {
            "category":"Personal",
            "subcategory":"Massage",
            "type":"Services"
        }
    ],
    "sg:phone":"+1 239 274 8201",
    "sg:postcode":"33907",
    "sg:province":"FL",
    "sg:website":"www.gulfcoastmassageandskincare.com",
    "wof:name":"Gulf Coast Massage Inc",
    "wof:placetype":"venue"
},
  "geometry": {"coordinates":[-81.87960099999999,26.597],"type":"Point"}
}