{
  "type": "Feature",
  "properties": {
    "addr:full":"1695 Forum Pl West Palm Beach FL 33401",
    "addr:housenumber":"1695",
    "addr:postcode":"33401",
    "addr:street":"Forum Pl",
    "iso:country":"US",
    "sg:address":"1695 Forum Pl",
    "sg:city":"West Palm Beach",
    "sg:classifiers":[
        {
            "category":"Retail",
            "subcategory":"Laundry & Dry Cleaning",
            "type":"Services"
        }
    ],
    "sg:phone":"+1 561 684 9264",
    "sg:postcode":"33401",
    "sg:province":"FL",
    "sg:tags":[
        "cleaners"
    ],
    "wof:name":"Dryclean USA",
    "wof:placetype":"venue"
},
  "geometry": {"coordinates":[-80.08068799999999,26.72668],"type":"Point"}
}