{
  "type": "Feature",
  "properties": {
    "addr:full":"11112 San Jose Blvd Jacksonville FL 32223",
    "addr:housenumber":"11112",
    "addr:postcode":"32223",
    "addr:street":"San Jose Blvd",
    "iso:country":"US",
    "sg:address":"11112 San Jose Blvd",
    "sg:city":"Jacksonville",
    "sg:classifiers":[
        {
            "category":"Personal",
            "subcategory":"Beauty Salon",
            "type":"Services"
        }
    ],
    "sg:phone":"+1 904 262 1411",
    "sg:postcode":"32223",
    "sg:province":"FL",
    "sg:tags":[
        "hair"
    ],
    "wof:name":"Creative Hairdressers",
    "wof:placetype":"venue"
},
  "geometry": {"coordinates":[-81.628529,30.173664],"type":"Point"}
}