{
  "type": "Feature",
  "properties": {
    "addr:full":"6740 Magnolia Pointe Cir Orlando FL 32810",
    "addr:housenumber":"6740",
    "addr:postcode":"32810",
    "addr:street":"Magnolia Pointe Cir",
    "iso:country":"US",
    "sg:address":"6740 Magnolia Pointe Cir",
    "sg:city":"Orlando",
    "sg:classifiers":[
        {
            "category":"Shopping",
            "subcategory":"Computers & Home Electronics",
            "type":"Retail Goods"
        }
    ],
    "sg:phone":"+1 407 445 4136",
    "sg:postcode":"32810",
    "sg:province":"FL",
    "wof:name":"AP Computers",
    "wof:placetype":"venue"
},
  "geometry": {"coordinates":[-81.42828,28.621971],"type":"Point"}
}