{
  "type": "Feature",
  "properties": {
    "iso:country":"US",
    "sg:address":"11643 Boyette Rd",
    "sg:city":"Riverview",
    "sg:classifiers":[
        {
            "category":"Restaurant",
            "type":"Food & Drink"
        }
    ],
    "sg:menulink":"http://www.allmenus.com/fl/wimauma-lithia/280980-westshore-pizza/menu/",
    "sg:phone":"+1 813 672 2828",
    "sg:postcode":"33569",
    "sg:province":"FL",
    "sg:tags":[
        "american",
        "pizza"
    ],
    "wof:name":"Westshore Pizza",
    "wof:placetype":"venue"
},
  "geometry": {"coordinates":[-82.305565,27.853453],"type":"Point"}
}