{
  "type": "Feature",
  "properties": {
    "iso:country":"US",
    "sg:address":"1371 W Terra Mar Dr",
    "sg:city":"Pompano Beach",
    "sg:classifiers":[
        {
            "category":"Shopping",
            "type":"Retail Goods"
        }
    ],
    "sg:phone":"+1 954 783 6325",
    "sg:postcode":"33062",
    "sg:province":"FL",
    "sg:tags":[
        "merchandise"
    ],
    "wof:name":"Kathys Pets",
    "wof:placetype":"venue"
},
  "geometry": {"coordinates":[-80.09446800000001,26.220386],"type":"Point"}
}