{
  "type": "Feature",
  "properties": {
    "iso:country":"US",
    "sg:address":"8212 Ambach Way",
    "sg:city":"Lake Worth",
    "sg:classifiers":[
        {
            "category":"Bars & Pubs",
            "type":"Food & Drink"
        }
    ],
    "sg:phone":"+1 561 586 4826",
    "sg:postcode":"33462",
    "sg:province":"FL",
    "sg:tags":[
        "drinking"
    ],
    "wof:name":"Name Longhair Productions",
    "wof:placetype":"venue"
},
  "geometry": {"coordinates":[-80.05972,26.555527],"type":"Point"}
}