{
  "type": "Feature",
  "properties": {
    "addr:full":"11190 SE 131 Ter Dunnellon FL 34431",
    "addr:housenumber":"11190;131 ter",
    "addr:postcode":"34431",
    "addr:street":"Se",
    "iso:country":"US",
    "sg:address":"11190 SE 131 Ter",
    "sg:city":"Dunnellon",
    "sg:classifiers":[
        {
            "category":"Building & Trades",
            "subcategory":"Construction",
            "type":"Services"
        }
    ],
    "sg:phone":"+1 352 427 8185",
    "sg:postcode":"34431",
    "sg:province":"FL",
    "sg:tags":[
        "fence",
        "contractor"
    ],
    "wof:name":"Patrick Kelly Fence Instlltn",
    "wof:placetype":"venue"
},
  "geometry": {"coordinates":[-82.549509,29.164946],"type":"Point"}
}