{
  "type": "Feature",
  "properties": {
    "iso:country":"US",
    "sg:address":"2657 Oak Run Blvd",
    "sg:city":"Kissimmee",
    "sg:classifiers":[
        {
            "category":"Building & Trades",
            "subcategory":"Landscaping Services",
            "type":"Services"
        }
    ],
    "sg:phone":"+1 407 518 9056",
    "sg:postcode":"34744",
    "sg:province":"FL",
    "sg:tags":[
        "landscape"
    ],
    "wof:name":"Freddys Landscaping & Pool SE",
    "wof:placetype":"venue"
},
  "geometry": {"coordinates":[-81.37793000000001,28.326677],"type":"Point"}
}