{
  "type": "Feature",
  "properties": {
    "addr:full":"4428 Lafayette St Marianna FL 32446",
    "addr:housenumber":"4428",
    "addr:postcode":"32446",
    "addr:street":"Lafayette St",
    "iso:country":"US",
    "sg:address":"4428 Lafayette St",
    "sg:city":"Marianna",
    "sg:classifiers":[
        {
            "category":"Personal",
            "subcategory":"Beauty Salon",
            "type":"Services"
        }
    ],
    "sg:phone":"+1 850 482 6643",
    "sg:postcode":"32446",
    "sg:province":"FL",
    "sg:tags":[
        "shop"
    ],
    "wof:name":"Growing Tree",
    "wof:placetype":"venue"
},
  "geometry": {"coordinates":[-85.22747,30.774464],"type":"Point"}
}