{
  "type": "Feature",
  "properties": {
    "iso:country":"US",
    "sg:address":"5849 Areca Palm Ct",
    "sg:city":"Delray Beach",
    "sg:classifiers":[
        {
            "category":"Mining & Drilling",
            "type":"Manufacturing & Wholesale Goods"
        }
    ],
    "sg:phone":"+1 561 279 0448",
    "sg:postcode":"33484",
    "sg:province":"FL",
    "sg:tags":[
        "nonmetallic",
        "mineral"
    ],
    "wof:name":"Mandel Resources Corp",
    "wof:placetype":"venue"
},
  "geometry": {"coordinates":[-80.136933,26.483305],"type":"Point"}
}