{
  "type": "Feature",
  "properties": {
    "addr:full":"978 Lakeside Dr Apopka FL 32712",
    "addr:housenumber":"978",
    "addr:postcode":"32712",
    "addr:street":"Lakeside Dr",
    "iso:country":"US",
    "sg:address":"978 Lakeside Dr",
    "sg:city":"Apopka",
    "sg:classifiers":[
        {
            "category":"Professional",
            "subcategory":"Management & Consulting",
            "type":"Services"
        }
    ],
    "sg:phone":"+1 407 880 6861",
    "sg:postcode":"32712",
    "sg:province":"FL",
    "sg:tags":[
        "consultant",
        "lighting"
    ],
    "wof:name":"International Electrical Supl",
    "wof:placetype":"venue"
},
  "geometry": {"coordinates":[-81.493984,28.711794],"type":"Point"}
}