{
  "type": "Feature",
  "properties": {
    "iso:country":"US",
    "sg:address":"201 Pine Ln",
    "sg:city":"Clewiston",
    "sg:classifiers":[
        {
            "category":"Food & Beverages",
            "subcategory":"Fruits & Vegetables",
            "type":"Retail Goods"
        }
    ],
    "sg:phone":"+1 863 983 5983",
    "sg:postcode":"33440",
    "sg:province":"FL",
    "wof:name":"Potts Produce Inc",
    "wof:placetype":"venue"
},
  "geometry": {"coordinates":[-81.06392700000001,26.689781],"type":"Point"}
}