{
  "type": "Feature",
  "properties": {
    "iso:country":"US",
    "sg:address":"23262 Kim Ave",
    "sg:city":"Port Charlotte",
    "sg:classifiers":[
        {
            "category":"Home & Garden",
            "subcategory":"Carpets & Floor Coverings",
            "type":"Retail Goods"
        }
    ],
    "sg:phone":"+1 941 286 4103",
    "sg:postcode":"33954",
    "sg:province":"FL",
    "wof:name":"David Bartas Crpt Installation",
    "wof:placetype":"venue"
},
  "geometry": {"coordinates":[-82.066008,27.021974],"type":"Point"}
}