{
  "type": "Feature",
  "properties": {
    "iso:country":"US",
    "sg:address":"20650 Newby St",
    "sg:city":"Orlando",
    "sg:classifiers":[
        {
            "category":"Building & Trades",
            "subcategory":"Construction",
            "type":"Services"
        }
    ],
    "sg:phone":"+1 407 568 0303",
    "sg:postcode":"32833",
    "sg:province":"FL",
    "sg:tags":[
        "house",
        "nonresidential"
    ],
    "wof:name":"Prestige Builders Inc",
    "wof:placetype":"venue"
},
  "geometry": {"coordinates":[-81.068258,28.501731],"type":"Point"}
}