{
  "type": "Feature",
  "properties": {
    "iso:country":"US",
    "sg:address":"2404 W Cleveland St",
    "sg:city":"Tampa",
    "sg:classifiers":[
        {
            "category":"Social Services",
            "subcategory":"Job Training",
            "type":"Services"
        }
    ],
    "sg:phone":"+1 813 237 0494",
    "sg:postcode":"33609",
    "sg:province":"FL",
    "sg:tags":[
        "employment"
    ],
    "wof:name":"Career Directions",
    "wof:placetype":"venue"
},
  "geometry": {"coordinates":[-82.484081,27.94336],"type":"Point"}
}