{
  "type": "Feature",
  "properties": {
    "iso:country":"US",
    "sg:address":"8003 NW 64th St",
    "sg:city":"Miami",
    "sg:classifiers":[
        {
            "category":"Wholesale",
            "subcategory":"Machinery & Supplies",
            "type":"Manufacturing & Wholesale Goods"
        }
    ],
    "sg:phone":"+1 305 599 6255",
    "sg:postcode":"33166",
    "sg:province":"FL",
    "sg:tags":[
        "industrial",
        "paper"
    ],
    "wof:name":"Star Island",
    "wof:placetype":"venue"
},
  "geometry": {"coordinates":[-80.326476,25.83173],"type":"Point"}
}