{
  "type": "Feature",
  "properties": {
    "iso:country":"US",
    "sg:address":"2379 SE Federal Hwy",
    "sg:city":"Stuart",
    "sg:classifiers":[
        {
            "category":"Restaurant",
            "type":"Food & Drink"
        }
    ],
    "sg:menulink":"http://www.allmenus.com/fl/stuart/30490-taj-mahal/menu/",
    "sg:phone":"+1 772 781 6664",
    "sg:postcode":"34994",
    "sg:province":"FL",
    "sg:tags":[
        "indian",
        "asian"
    ],
    "wof:name":"Taj Mahal",
    "wof:placetype":"venue"
},
  "geometry": {"coordinates":[-80.23471000000001,27.175931],"type":"Point"}
}