{
  "type": "Feature",
  "properties": {
    "addr:full":"9799 S Dixie Hwy Miami FL 33156",
    "addr:housenumber":"9799",
    "addr:postcode":"33156",
    "addr:street":"S Dixie Hwy",
    "iso:country":"US",
    "sg:address":"9799 S Dixie Hwy",
    "sg:city":"Miami",
    "sg:classifiers":[
        {
            "category":"Autos & Motor Vehicles",
            "subcategory":"Auto Supplies",
            "type":"Retail Goods"
        },
        {
            "category":"Retail",
            "subcategory":"Auto Repair",
            "type":"Services"
        }
    ],
    "sg:phone":"+1 305 661 8544",
    "sg:postcode":"33156",
    "sg:province":"FL",
    "sg:tags":[
        "lube",
        "oil",
        "tire"
    ],
    "sg:website":"http://www.firestonecompleteautocare.com/?s_kwcid=IYP_NTL",
    "wof:name":"Firestone Complete Auto Care Store",
    "wof:placetype":"venue"
},
  "geometry": {"coordinates":[-80.316963,25.67948],"type":"Point"}
}