{
  "type": "Feature",
  "properties": {
    "addr:full":"225 Ponce Harbor Dr St Augustine FL 32086",
    "addr:housenumber":"225",
    "addr:postcode":"32086",
    "addr:street":"Ponce Harbor Dr St",
    "iso:country":"US",
    "sg:address":"225 Ponce Harbor Dr",
    "sg:city":"St Augustine",
    "sg:classifiers":[
        {
            "category":"Real Estate",
            "subcategory":"Real Estate Operator",
            "type":"Services"
        }
    ],
    "sg:phone":"+1 904 794 4022",
    "sg:postcode":"32086",
    "sg:province":"FL",
    "sg:tags":[
        "apartment"
    ],
    "wof:name":"Ponce Harbor",
    "wof:placetype":"venue"
},
  "geometry": {"coordinates":[-81.328419,29.858437],"type":"Point"}
}