{
  "type": "Feature",
  "properties": {
    "addr:full":"219 Park Shore Cir Vero Beach FL 32963",
    "addr:housenumber":"219",
    "addr:postcode":"32963",
    "addr:street":"Park Shore Cir",
    "iso:country":"US",
    "sg:address":"219 Park Shore Cir",
    "sg:city":"Vero Beach",
    "sg:classifiers":[
        {
            "category":"Professional",
            "type":"Services"
        }
    ],
    "sg:phone":"+1 772 234 3074",
    "sg:postcode":"32963",
    "sg:province":"FL",
    "sg:tags":[
        "establishment"
    ],
    "wof:name":"Park Shores Of Vero Beach",
    "wof:placetype":"venue"
},
  "geometry": {"coordinates":[-80.371785,27.691784],"type":"Point"}
}