{
  "type": "Feature",
  "properties": {
    "addr:full":"10191 W Sample Rd Pompano Beach FL 33065",
    "addr:housenumber":"10191",
    "addr:postcode":"33065",
    "addr:street":"W Sample Rd",
    "iso:country":"US",
    "sg:address":"10191 W Sample Rd",
    "sg:city":"Pompano Beach",
    "sg:classifiers":[
        {
            "category":"Real Estate",
            "subcategory":"Developer",
            "type":"Services"
        }
    ],
    "sg:phone":"+1 954 575 0083",
    "sg:postcode":"33065",
    "sg:province":"FL",
    "sg:tags":[
        "development",
        "land"
    ],
    "wof:name":"V & V Development Group LLC",
    "wof:placetype":"venue"
},
  "geometry": {"coordinates":[-80.263609,26.2727],"type":"Point"}
}