{
  "type": "Feature",
  "properties": {
    "iso:country":"US",
    "sg:address":"801 NW 4th Ave",
    "sg:city":"Ocala",
    "sg:classifiers":[
        {
            "category":"Real Estate",
            "subcategory":"Real Estate Agent",
            "type":"Services"
        }
    ],
    "sg:phone":"+1 352 402 9959",
    "sg:postcode":"34475",
    "sg:province":"FL",
    "sg:tags":[
        "appraiser"
    ],
    "wof:name":"Curt Waller Appraisal Svc",
    "wof:placetype":"venue"
},
  "geometry": {"coordinates":[-82.140664,29.195211],"type":"Point"}
}