{
  "type": "Feature",
  "properties": {
    "addr:full":"990 NE 92nd St Miami Shores FL 33138",
    "addr:housenumber":"990",
    "addr:postcode":"33138",
    "addr:street":"Ne 92Nd St",
    "iso:country":"US",
    "sg:address":"990 NE 92nd St",
    "sg:city":"Miami Shores",
    "sg:classifiers":[
        {
            "category":"Insurance",
            "subcategory":"Insurance Agent",
            "type":"Services"
        }
    ],
    "sg:phone":"+1 305 759 0005",
    "sg:postcode":"33138",
    "sg:province":"FL",
    "wof:name":"Comprehensive Insurance",
    "wof:placetype":"venue"
},
  "geometry": {"coordinates":[-80.17870600000001,25.860393],"type":"Point"}
}