{
  "type": "Feature",
  "properties": {
    "addr:full":"3201 Oaklea Dr De Land FL 32720",
    "addr:housenumber":"3201",
    "addr:postcode":"32720",
    "addr:street":"Oaklea Dr",
    "iso:country":"US",
    "sg:address":"3201 Oaklea Dr",
    "sg:city":"De Land",
    "sg:classifiers":[
        {
            "category":"Building & Trades",
            "subcategory":"Construction",
            "type":"Services"
        }
    ],
    "sg:phone":"+1 386 747 7777",
    "sg:postcode":"32720",
    "sg:province":"FL",
    "sg:tags":[
        "house"
    ],
    "wof:name":"Danny Kramer Inc",
    "wof:placetype":"venue"
},
  "geometry": {"coordinates":[-81.334898,29.087698],"type":"Point"}
}