{
  "type": "Feature",
  "properties": {
    "iso:country":"US",
    "sg:address":"11400 US Hwy 441",
    "sg:city":"Boynton Beach",
    "sg:classifiers":[
        {
            "category":"Wholesale",
            "subcategory":"Fruits & Vegetables",
            "type":"Manufacturing & Wholesale Goods"
        }
    ],
    "sg:phone":"+1 561 732 4576",
    "sg:postcode":"33473",
    "sg:province":"FL",
    "sg:tags":[
        "produce"
    ],
    "wof:name":"Whitworth Sales Inc",
    "wof:placetype":"venue"
},
  "geometry": {"coordinates":[-80.20458000000001,26.483756],"type":"Point"}
}