{
  "type": "Feature",
  "properties": {
    "iso:country":"US",
    "sg:address":"813 S Highlands Ave",
    "sg:city":"Inverness",
    "sg:classifiers":[
        {
            "category":"Building & Trades",
            "subcategory":"Construction",
            "type":"Services"
        }
    ],
    "sg:phone":"+1 352 726 3187",
    "sg:postcode":"34452",
    "sg:province":"FL",
    "sg:tags":[
        "carpentry",
        "contractor"
    ],
    "wof:name":"Window Dsgns Dcor Instllations",
    "wof:placetype":"venue"
},
  "geometry": {"coordinates":[-82.325731,28.822382],"type":"Point"}
}