{
  "type": "Feature",
  "properties": {
    "iso:country":"US",
    "sg:address":"650 NW 95th St",
    "sg:city":"Miami",
    "sg:classifiers":[
        {
            "category":"Building & Trades",
            "subcategory":"Landscaping Services",
            "type":"Services"
        }
    ],
    "sg:phone":"+1 305 757 5260",
    "sg:postcode":"33150",
    "sg:province":"FL",
    "sg:tags":[
        "lawn",
        "maintenance",
        "grounds"
    ],
    "wof:name":"E & S Landscaping Svc",
    "wof:placetype":"venue"
},
  "geometry": {"coordinates":[-80.20874499999999,25.861894],"type":"Point"}
}