{
  "type": "Feature",
  "properties": {
    "iso:country":"US",
    "sg:address":"1964 N John Young Pkwy",
    "sg:city":"Kissimmee",
    "sg:classifiers":[
        {
            "category":"Real Estate",
            "subcategory":"Real Estate Agent",
            "type":"Services"
        }
    ],
    "sg:phone":"+1 407 847 2623",
    "sg:postcode":"34741",
    "sg:province":"FL",
    "wof:name":"Camac LLC",
    "wof:placetype":"venue"
},
  "geometry": {"coordinates":[-81.41589999999999,28.309614],"type":"Point"}
}