{
  "type": "Feature",
  "properties": {
    "addr:full":"801 Limona Rd Brandon FL 33510",
    "addr:housenumber":"801",
    "addr:postcode":"33510",
    "addr:street":"Limona Rd",
    "iso:country":"US",
    "sg:address":"801 Limona Rd",
    "sg:city":"Brandon",
    "sg:classifiers":[
        {
            "category":"Education",
            "subcategory":"School",
            "type":"Public Place"
        }
    ],
    "sg:phone":"+1 813 689 1952",
    "sg:postcode":"33510",
    "sg:province":"FL",
    "wof:name":"Brandon Academy",
    "wof:placetype":"venue"
},
  "geometry": {"coordinates":[-82.304255,27.95236],"type":"Point"}
}