{
  "type": "Feature",
  "properties": {
    "iso:country":"US",
    "sg:address":"7925 NW 12th St",
    "sg:city":"Doral",
    "sg:classifiers":[
        {
            "category":"Banks & Credit Unions",
            "subcategory":"Investment Brokerage",
            "type":"Services"
        },
        {
            "category":"Manufacturing",
            "subcategory":"Paper Products",
            "type":"Manufacturing & Wholesale Goods"
        }
    ],
    "sg:phone":"+1 305 436 0477",
    "sg:postcode":"33126",
    "sg:province":"FL",
    "sg:tags":[
        "mill",
        "manufacturer",
        "broker",
        "representative"
    ],
    "wof:name":"Sun Paper Company",
    "wof:placetype":"venue"
},
  "geometry": {"coordinates":[-80.32525800000001,25.782683],"type":"Point"}
}