{
  "type": "Feature",
  "properties": {
    "iso:country":"US",
    "sg:address":"10000 W Colonial Dr Ste 382",
    "sg:city":"Ocoee",
    "sg:classifiers":[
        {
            "category":"Health Services",
            "subcategory":"Doctor",
            "type":"Services"
        }
    ],
    "sg:phone":"+1 407 296 8082",
    "sg:postcode":"34761",
    "sg:province":"FL",
    "sg:tags":[
        "physician",
        "surgeon",
        "urology",
        "surgeons"
    ],
    "wof:name":"Reine Alden MD",
    "wof:placetype":"venue"
},
  "geometry": {"coordinates":[-81.529709,28.55172],"type":"Point"}
}