{
  "type": "Feature",
  "properties": {
    "iso:country":"US",
    "sg:address":"2 Jungle Hut Rd",
    "sg:city":"Palm Coast",
    "sg:classifiers":[
        {
            "category":"Professional",
            "subcategory":"Lawyer & Legal Services",
            "type":"Services"
        }
    ],
    "sg:phone":"+1 386 445 9322",
    "sg:postcode":"32137",
    "sg:province":"FL",
    "wof:name":"Timothy J Conner PA",
    "wof:placetype":"venue"
},
  "geometry": {"coordinates":[-81.18558,29.584329],"type":"Point"}
}