{
  "type": "Feature",
  "properties": {
    "addr:full":"515 Melba St Jacksonville FL 32254",
    "addr:housenumber":"515",
    "addr:postcode":"32254",
    "addr:street":"Melba St",
    "iso:country":"US",
    "sg:address":"515 Melba St",
    "sg:city":"Jacksonville",
    "sg:classifiers":[
        {
            "category":"Building & Trades",
            "subcategory":"Plumbing",
            "type":"Services"
        }
    ],
    "sg:phone":"+1 904 378 0030",
    "sg:postcode":"32254",
    "sg:province":"FL",
    "sg:tags":[
        "plumbing",
        "contractor"
    ],
    "wof:name":"Mark Faulkner Plumbing",
    "wof:placetype":"venue"
},
  "geometry": {"coordinates":[-81.717889,30.321781],"type":"Point"}
}