{
  "type": "Feature",
  "properties": {
    "addr:full":"11005 Blasius Rd Jacksonville FL 32226",
    "addr:housenumber":"11005",
    "addr:postcode":"32226",
    "addr:street":"Blasius Rd",
    "iso:country":"US",
    "sg:address":"11005 Blasius Rd",
    "sg:city":"Jacksonville",
    "sg:classifiers":[
        {
            "category":"Freight",
            "type":"Transportation"
        }
    ],
    "sg:phone":"+1 904 757 7117",
    "sg:postcode":"32226",
    "sg:province":"FL",
    "sg:tags":[
        "bulk",
        "product",
        "forwarding",
        "liquid"
    ],
    "wof:name":"C & C Bulk Liquid Transfer",
    "wof:placetype":"venue"
},
  "geometry": {"coordinates":[-81.56853,30.429347],"type":"Point"}
}