{
  "type": "Feature",
  "properties": {
    "iso:country":"US",
    "sg:address":"399 Central Florida Pkwy",
    "sg:city":"Orlando",
    "sg:classifiers":[
        {
            "category":"Home & Garden",
            "subcategory":"Building Materials",
            "type":"Retail Goods"
        }
    ],
    "sg:phone":"+1 407 859 4377",
    "sg:postcode":"32824",
    "sg:province":"FL",
    "sg:tags":[
        "granite",
        "top",
        "counter"
    ],
    "sg:website":"http://www.earthrock.us",
    "wof:name":"Earthrock Granite",
    "wof:placetype":"venue"
},
  "geometry": {"coordinates":[-81.38279,28.407681],"type":"Point"}
}