{
  "type": "Feature",
  "properties": {
    "iso:country":"US",
    "sg:address":"510 Manor Rd",
    "sg:city":"Maitland",
    "sg:classifiers":[
        {
            "category":"Health Services",
            "subcategory":"Doctor",
            "type":"Services"
        }
    ],
    "sg:phone":"+1 407 539 1206",
    "sg:postcode":"32751",
    "sg:province":"FL",
    "sg:tags":[
        "medical"
    ],
    "wof:name":"George D Mitchell MD PA",
    "wof:placetype":"venue"
},
  "geometry": {"coordinates":[-81.361329,28.622089],"type":"Point"}
}