{
  "type": "Feature",
  "properties": {
    "iso:country":"US",
    "sg:address":"4913 Normandy Ct",
    "sg:city":"Cape Coral",
    "sg:classifiers":[
        {
            "category":"Building & Trades",
            "subcategory":"Construction",
            "type":"Services"
        }
    ],
    "sg:phone":"+1 239 542 0066",
    "sg:postcode":"33904",
    "sg:province":"FL",
    "sg:tags":[
        "hanging",
        "contractor"
    ],
    "wof:name":"Obrien Painting",
    "wof:placetype":"venue"
},
  "geometry": {"coordinates":[-81.943973,26.557806],"type":"Point"}
}