{
  "type": "Feature",
  "properties": {
    "iso:country":"US",
    "sg:address":"2224 E Fletcher Ave",
    "sg:city":"Tampa",
    "sg:classifiers":[
        {
            "category":"Restaurant",
            "type":"Food & Drink"
        }
    ],
    "sg:menulink":"http://www.allmenus.com/fl/tampa/280973-westshore-pizza/menu/",
    "sg:phone":"+1 813 972 3171",
    "sg:postcode":"33612",
    "sg:province":"FL",
    "sg:tags":[
        "american",
        "pizza"
    ],
    "wof:name":"Westshore Pizza",
    "wof:placetype":"venue"
},
  "geometry": {"coordinates":[-82.433898,28.069352],"type":"Point"}
}