{
  "type": "Feature",
  "properties": {
    "addr:full":"1060 Old Dixie Hwy Vero Beach FL 32960",
    "addr:housenumber":"1060",
    "addr:postcode":"32960",
    "addr:street":"Old Dixie Hwy",
    "iso:country":"US",
    "sg:address":"1060 Old Dixie Hwy",
    "sg:city":"Vero Beach",
    "sg:classifiers":[
        {
            "category":"Freight",
            "type":"Transportation"
        }
    ],
    "sg:phone":"+1 772 562 2246",
    "sg:postcode":"32960",
    "sg:province":"FL",
    "sg:tags":[
        "product",
        "warehousing",
        "farm",
        "commercial",
        "storage",
        "general"
    ],
    "wof:name":"B & B Mini Storage",
    "wof:placetype":"venue"
},
  "geometry": {"coordinates":[-80.393089,27.620281],"type":"Point"}
}