{
  "type": "Feature",
  "properties": {
    "iso:country":"US",
    "sg:address":"3301 S Orange Blossom Trl",
    "sg:city":"Kissimmee",
    "sg:classifiers":[
        {
            "category":"Autos & Motor Vehicles",
            "subcategory":"Fuel & Gas Station",
            "type":"Retail Goods"
        }
    ],
    "sg:phone":"+1 407 944 1733",
    "sg:postcode":"34746",
    "sg:province":"FL",
    "sg:tags":[
        "oil"
    ],
    "wof:name":"Chevron Pleasant Hill",
    "wof:placetype":"venue"
},
  "geometry": {"coordinates":[-81.439066,28.259386],"type":"Point"}
}