{
  "type": "Feature",
  "properties": {
    "iso:country":"US",
    "sg:address":"4939 Duncan Rd",
    "sg:city":"Punta Gorda",
    "sg:classifiers":[
        {
            "category":"Building & Trades",
            "subcategory":"Landscaping Services",
            "type":"Services"
        }
    ],
    "sg:phone":"+1 941 505 9273",
    "sg:postcode":"33982",
    "sg:province":"FL",
    "sg:tags":[
        "landscape",
        "contractor"
    ],
    "wof:name":"Yard Doctor",
    "wof:placetype":"venue"
},
  "geometry": {"coordinates":[-81.982589,26.962634],"type":"Point"}
}