{
  "type": "Feature",
  "properties": {
    "iso:country":"US",
    "sg:address":"720 Eglin Pkwy",
    "sg:city":"Fort Walton Bch",
    "sg:classifiers":[
        {
            "category":"Retail",
            "subcategory":"Auto Repair",
            "type":"Services"
        }
    ],
    "sg:phone":"+1 850 862 6028",
    "sg:postcode":"32547",
    "sg:province":"FL",
    "sg:tags":[
        "repairing",
        "automobile"
    ],
    "wof:name":"Vern's Auto Repair & Svc",
    "wof:placetype":"venue"
},
  "geometry": {"coordinates":[-86.59748500000001,30.441164],"type":"Point"}
}