{
  "type": "Feature",
  "properties": {
    "iso:country":"US",
    "sg:address":"1496 W Dixie Hwy",
    "sg:city":"Dania",
    "sg:classifiers":[
        {
            "category":"Wholesale",
            "subcategory":"Machinery & Supplies",
            "type":"Manufacturing & Wholesale Goods"
        }
    ],
    "sg:phone":"+1 954 922 9136",
    "sg:postcode":"33004",
    "sg:province":"FL",
    "sg:tags":[
        "fire",
        "equipment",
        "safety",
        "sales"
    ],
    "wof:name":"Millennium Fire & Safety Eqp",
    "wof:placetype":"venue"
},
  "geometry": {"coordinates":[-80.150171,26.035641],"type":"Point"}
}