{
  "type": "Feature",
  "properties": {
    "addr:full":"2085 N Powerline Rd Pompano Beach FL 33069",
    "addr:housenumber":"2085",
    "addr:postcode":"33069",
    "addr:street":"N Powerline Rd",
    "iso:country":"US",
    "sg:address":"2085 N Powerline Rd",
    "sg:city":"Pompano Beach",
    "sg:classifiers":[
        {
            "category":"Manufacturing",
            "subcategory":"Signs",
            "type":"Manufacturing & Wholesale Goods"
        }
    ],
    "sg:phone":"+1 954 972 7222",
    "sg:postcode":"33069",
    "sg:province":"FL",
    "sg:tags":[
        "commercial"
    ],
    "wof:name":"First Sign Corp",
    "wof:placetype":"venue"
},
  "geometry": {"coordinates":[-80.15172099999999,26.253003],"type":"Point"}
}