{
  "type": "Feature",
  "properties": {
    "addr:full":"11771 Highway 231 Youngstown FL 32466",
    "addr:housenumber":"11771",
    "addr:postcode":"32466",
    "addr:street":"Highway 231",
    "iso:country":"US",
    "sg:address":"11771 Highway 231",
    "sg:city":"Youngstown",
    "sg:classifiers":[
        {
            "category":"Government",
            "subcategory":"Fire Station",
            "type":"Public Place"
        }
    ],
    "sg:phone":"+1 850 722 9620",
    "sg:postcode":"32466",
    "sg:province":"FL",
    "sg:tags":[
        "department",
        "protection"
    ],
    "wof:name":"Bear Crk Yngstwn Vol Fire Dept",
    "wof:placetype":"venue"
},
  "geometry": {"coordinates":[-85.440575,30.346012],"type":"Point"}
}