{
  "type": "Feature",
  "properties": {
    "iso:country":"US",
    "sg:address":"2520 Knights Station Rd",
    "sg:city":"Lakeland",
    "sg:classifiers":[
        {
            "category":"Structure",
            "subcategory":"Warehouse",
            "type":"Public Place"
        }
    ],
    "sg:phone":"+1 863 815 4424",
    "sg:postcode":"33810",
    "sg:province":"FL",
    "sg:tags":[
        "warehouses-merchandise",
        "warehouses-public-commercial"
    ],
    "sg:website":"http://www.seaboard-dist.com",
    "wof:name":"Seaboard Distribution, Inc.",
    "wof:placetype":"venue"
},
  "geometry": {"coordinates":[-81.996982,28.080507],"type":"Point"}
}