{
  "type": "Feature",
  "properties": {
    "addr:full":"800 Court St Clearwater FL 33756",
    "addr:housenumber":"800",
    "addr:postcode":"33756",
    "addr:street":"Court St",
    "iso:country":"US",
    "sg:address":"800 Court St",
    "sg:city":"Clearwater",
    "sg:classifiers":[
        {
            "category":"Professional",
            "subcategory":"Lawyer & Legal Services",
            "type":"Services"
        }
    ],
    "sg:phone":"+1 727 726 0662",
    "sg:postcode":"33756",
    "sg:province":"FL",
    "sg:tags":[
        "attorney"
    ],
    "wof:name":"Dennis Hernandez & Assoc",
    "wof:placetype":"venue"
},
  "geometry": {"coordinates":[-82.79433299999999,27.961941],"type":"Point"}
}