{
  "type": "Feature",
  "properties": {
    "iso:country":"US",
    "sg:address":"1625 N Commerce Pkwy",
    "sg:city":"Weston",
    "sg:classifiers":[
        {
            "category":"Real Estate",
            "subcategory":"Real Estate Agent",
            "type":"Services"
        }
    ],
    "sg:phone":"+1 954 384 2442",
    "sg:postcode":"33326",
    "sg:province":"FL",
    "sg:website":"www.kw.com",
    "wof:name":"Weston International Rl Est",
    "wof:placetype":"venue"
},
  "geometry": {"coordinates":[-80.366265,26.098959],"type":"Point"}
}