{
  "type": "Feature",
  "properties": {
    "iso:country":"US",
    "sg:address":"3621 NW 90th Ter",
    "sg:city":"Sunrise",
    "sg:classifiers":[
        {
            "category":"Social Services",
            "subcategory":"Adult Care",
            "type":"Services"
        }
    ],
    "sg:phone":"+1 954 747 7265",
    "sg:postcode":"33351",
    "sg:province":"FL",
    "sg:tags":[
        "home",
        "residential"
    ],
    "wof:name":"Bright Horizons Of Welleby Inc",
    "wof:placetype":"venue"
},
  "geometry": {"coordinates":[-80.27131900000001,26.169189],"type":"Point"}
}