{
  "type": "Feature",
  "properties": {
    "iso:country":"US",
    "sg:address":"702 N Division St",
    "sg:city":"Micanopy",
    "sg:classifiers":[
        {
            "category":"Bakery",
            "type":"Food & Drink"
        }
    ],
    "sg:phone":"+1 352 466 0104",
    "sg:postcode":"32667",
    "sg:province":"FL",
    "wof:name":"Stanley Strobles",
    "wof:placetype":"venue"
},
  "geometry": {"coordinates":[-82.281539,29.508029],"type":"Point"}
}