{
  "type": "Feature",
  "properties": {
    "addr:full":"15320 NE 160th Avenue Rd Fort Mc Coy FL 32134",
    "addr:housenumber":"15320",
    "addr:postcode":"32134",
    "addr:street":"Ne 160Th Avenue Rd",
    "iso:country":"US",
    "sg:address":"15320 NE 160th Avenue Rd",
    "sg:city":"Fort Mc Coy",
    "sg:classifiers":[
        {
            "category":"Building & Trades",
            "subcategory":"Landscaping Services",
            "type":"Services"
        }
    ],
    "sg:phone":"+1 352 685 3083",
    "sg:postcode":"32134",
    "sg:province":"FL",
    "wof:name":"David J Chastain",
    "wof:placetype":"venue"
},
  "geometry": {"coordinates":[-81.884523,29.37334],"type":"Point"}
}