{
  "type": "Feature",
  "properties": {
    "addr:full":"6309 Snow Rd Lakeland FL 33811",
    "addr:housenumber":"6309",
    "addr:postcode":"33811",
    "addr:street":"Snow Rd",
    "iso:country":"US",
    "sg:address":"6309 Snow Rd",
    "sg:city":"Lakeland",
    "sg:classifiers":[
        {
            "category":"Building & Trades",
            "subcategory":"Landscaping Services",
            "type":"Services"
        }
    ],
    "sg:phone":"+1 863 646 5671",
    "sg:postcode":"33811",
    "sg:province":"FL",
    "sg:tags":[
        "tree"
    ],
    "wof:name":"Tree Resources Unlimited",
    "wof:placetype":"venue"
},
  "geometry": {"coordinates":[-82.03957200000001,27.950578],"type":"Point"}
}