{
  "type": "Feature",
  "properties": {
    "iso:country":"US",
    "sg:address":"8400 Palm Cir",
    "sg:city":"Pembroke Pines",
    "sg:classifiers":[
        {
            "category":"Health Services",
            "subcategory":"Clinic",
            "type":"Services"
        }
    ],
    "sg:phone":"+1 954 987 1731",
    "sg:postcode":"33025",
    "sg:province":"FL",
    "wof:name":"Citrus Health Network",
    "wof:placetype":"venue"
},
  "geometry": {"coordinates":[-80.272543,26.0072],"type":"Point"}
}