{
  "type": "Feature",
  "properties": {
    "iso:country":"US",
    "sg:address":"91284 Overseas Hwy",
    "sg:city":"Tavernier",
    "sg:classifiers":[
        {
            "category":"Shopping",
            "type":"Retail Goods"
        }
    ],
    "sg:phone":"+1 305 852 4840",
    "sg:postcode":"33070",
    "sg:province":"FL",
    "sg:tags":[
        "art",
        "gallery",
        "dealer"
    ],
    "wof:name":"Spirit Dance Art & Printing",
    "wof:placetype":"venue"
},
  "geometry": {"coordinates":[-80.526573,25.002421],"type":"Point"}
}