{
  "type": "Feature",
  "properties": {
    "iso:country":"US",
    "sg:address":"483 Collingswood Blvd",
    "sg:city":"Port Charlotte",
    "sg:classifiers":[
        {
            "category":"Building & Trades",
            "subcategory":"Electrical",
            "type":"Services"
        }
    ],
    "sg:phone":"+1 941 627 4039",
    "sg:postcode":"33954",
    "sg:province":"FL",
    "sg:tags":[
        "electric",
        "contractor"
    ],
    "wof:name":"Stec Enterprises Inc",
    "wof:placetype":"venue"
},
  "geometry": {"coordinates":[-82.156285,27.019356],"type":"Point"}
}