{
  "type": "Feature",
  "properties": {
    "iso:country":"US",
    "sg:address":"822 N Monroe St",
    "sg:city":"Tallahassee",
    "sg:classifiers":[
        {
            "category":"Professional",
            "subcategory":"Lawyer & Legal Services",
            "type":"Services"
        }
    ],
    "sg:phone":"+1 850 681 6416",
    "sg:postcode":"32303",
    "sg:province":"FL",
    "sg:tags":[
        "attorney",
        "negligence",
        "practice",
        "liability",
        "malpractice",
        "law"
    ],
    "wof:name":"Andrews Steven R Law Offices",
    "wof:placetype":"venue"
},
  "geometry": {"coordinates":[-84.280683,30.450641],"type":"Point"}
}