{
  "type": "Feature",
  "properties": {
    "iso:country":"US",
    "sg:address":"17050 NE 4th Ave",
    "sg:city":"Miami",
    "sg:classifiers":[
        {
            "category":"Social Services",
            "subcategory":"Child Care",
            "type":"Services"
        }
    ],
    "sg:phone":"+1 305 651 8928",
    "sg:postcode":"33162",
    "sg:province":"FL",
    "sg:tags":[
        "day",
        "facility"
    ],
    "wof:name":"Brave Paulene",
    "wof:placetype":"venue"
},
  "geometry": {"coordinates":[-80.19251300000001,25.931703],"type":"Point"}
}