{
  "type": "Feature",
  "properties": {
    "iso:country":"US",
    "sg:address":"2258 NW 28th St",
    "sg:city":"Miami",
    "sg:classifiers":[
        {
            "category":"Building & Trades",
            "subcategory":"Locksmith",
            "type":"Services"
        }
    ],
    "sg:phone":"+1 786 245 4353",
    "sg:postcode":"33142",
    "sg:province":"FL",
    "sg:tags":[
        "key"
    ],
    "wof:name":"AAA Locksmith",
    "wof:placetype":"venue"
},
  "geometry": {"coordinates":[-80.23285300000001,25.801749],"type":"Point"}
}