{
  "type": "Feature",
  "properties": {
    "addr:full":"11609 Branch Mooring Dr Tampa FL 33635",
    "addr:housenumber":"11609",
    "addr:postcode":"33635",
    "addr:street":"Branch Mooring Dr",
    "iso:country":"US",
    "sg:address":"11609 Branch Mooring Dr",
    "sg:city":"Tampa",
    "sg:classifiers":[
        {
            "category":"Shopping",
            "subcategory":"Gifts & Souvenirs",
            "type":"Retail Goods"
        }
    ],
    "sg:phone":"+1 813 964 5333",
    "sg:postcode":"33635",
    "sg:province":"FL",
    "sg:tags":[
        "collectible"
    ],
    "wof:name":"Cards Be Me Inc",
    "wof:placetype":"venue"
},
  "geometry": {"coordinates":[-82.614796,28.032839],"type":"Point"}
}