{
  "type": "Feature",
  "properties": {
    "addr:full":"112 W New Haven Ave Melbourne FL 32901",
    "addr:housenumber":"112",
    "addr:postcode":"32901",
    "addr:street":"W New Haven Ave",
    "iso:country":"US",
    "sg:address":"112 W New Haven Ave",
    "sg:city":"Melbourne",
    "sg:classifiers":[
        {
            "category":"Professional",
            "subcategory":"Lawyer & Legal Services",
            "type":"Services"
        }
    ],
    "sg:phone":"+1 321 725 4207",
    "sg:postcode":"32901",
    "sg:province":"FL",
    "sg:tags":[
        "attorney"
    ],
    "wof:name":"Huddleston & Palumbo PA",
    "wof:placetype":"venue"
},
  "geometry": {"coordinates":[-80.623177,28.078718],"type":"Point"}
}