{
  "type": "Feature",
  "properties": {
    "iso:country":"US",
    "sg:address":"1401 Brickell Ave",
    "sg:city":"Miami",
    "sg:classifiers":[
        {
            "category":"Manufacturing",
            "subcategory":"Leather Goods",
            "type":"Manufacturing & Wholesale Goods"
        }
    ],
    "sg:phone":"+1 305 372 1628",
    "sg:postcode":"33131",
    "sg:province":"FL",
    "wof:name":"Longchamp U S A",
    "wof:placetype":"venue"
},
  "geometry": {"coordinates":[-80.192139,25.760309],"type":"Point"}
}