{
  "type": "Feature",
  "properties": {
    "iso:country":"US",
    "sg:address":"4634 NW 45th Ct",
    "sg:city":"Fort Lauderdale",
    "sg:classifiers":[
        {
            "category":"Professional",
            "type":"Services"
        }
    ],
    "sg:phone":"+1 954 739 5990",
    "sg:postcode":"33319",
    "sg:province":"FL",
    "wof:name":"Wilton Manors Ambassador",
    "wof:placetype":"venue"
},
  "geometry": {"coordinates":[-80.214356,26.181795],"type":"Point"}
}