{
  "type": "Feature",
  "properties": {
    "iso:country":"US",
    "sg:address":"10825 Rockridge Rd",
    "sg:city":"Lakeland",
    "sg:classifiers":[
        {
            "category":"Food & Beverages",
            "subcategory":"Groceries & Convenience Stores",
            "type":"Retail Goods"
        }
    ],
    "sg:phone":"+1 863 858 8533",
    "sg:postcode":"33809",
    "sg:province":"FL",
    "wof:name":"Juanita W Ingles",
    "wof:placetype":"venue"
},
  "geometry": {"coordinates":[-81.995617,28.197114],"type":"Point"}
}