{
  "type": "Feature",
  "properties": {
    "addr:full":"5842 Alton Rd Miami Beach FL 33140",
    "addr:housenumber":"5842",
    "addr:postcode":"33140",
    "addr:street":"Alton Rd",
    "iso:country":"US",
    "sg:address":"5842 Alton Rd",
    "sg:city":"Miami Beach",
    "sg:classifiers":[
        {
            "category":"Shopping",
            "subcategory":"Bicycles & Sporting Goods",
            "type":"Retail Goods"
        }
    ],
    "sg:phone":"+1 305 865 0061",
    "sg:postcode":"33140",
    "sg:province":"FL",
    "wof:name":"Not Just Tennis",
    "wof:placetype":"venue"
},
  "geometry": {"coordinates":[-80.13125700000001,25.839318],"type":"Point"}
}