{
  "type": "Feature",
  "properties": {
    "iso:country":"US",
    "sg:address":"4910 Vernon Rd",
    "sg:city":"Tallahassee",
    "sg:classifiers":[
        {
            "category":"Wholesale",
            "subcategory":"Non-durable Goods",
            "type":"Manufacturing & Wholesale Goods"
        }
    ],
    "sg:phone":"+1 850 878 8325",
    "sg:postcode":"32317",
    "sg:province":"FL",
    "wof:name":"Jk Sales",
    "wof:placetype":"venue"
},
  "geometry": {"coordinates":[-84.201255,30.460484],"type":"Point"}
}