{
  "type": "Feature",
  "properties": {
    "iso:country":"US",
    "sg:address":"4983 South Cleveland Ave",
    "sg:city":"Fort Myers",
    "sg:classifiers":[
        {
            "category":"Shopping",
            "subcategory":"Hobbies, Toys, & Games",
            "type":"Retail Goods"
        }
    ],
    "sg:phone":"+1 239 275 7409",
    "sg:postcode":"33907",
    "sg:province":"FL",
    "sg:tags":[
        "toy",
        "store"
    ],
    "sg:website":"www.toysrus.com",
    "wof:name":"Toys R Us",
    "wof:placetype":"venue"
},
  "geometry": {"coordinates":[-81.87178400000001,26.58712],"type":"Point"}
}