{
  "type": "Feature",
  "properties": {
    "addr:full":"1138 SE Maxwell Ln Port St Lucie FL 34952",
    "addr:housenumber":"1138",
    "addr:postcode":"34952",
    "addr:street":"Se Maxwell Ln",
    "iso:country":"US",
    "sg:address":"1138 SE Maxwell Ln",
    "sg:city":"Port St Lucie",
    "sg:classifiers":[
        {
            "category":"Retail",
            "subcategory":"Repair Shop",
            "type":"Services"
        }
    ],
    "sg:phone":"+1 561 628 6134",
    "sg:postcode":"34952",
    "sg:province":"FL",
    "sg:tags":[
        "related"
    ],
    "wof:name":"Repairs By Harry",
    "wof:placetype":"venue"
},
  "geometry": {"coordinates":[-80.31627,27.277476],"type":"Point"}
}