{
  "type": "Feature",
  "properties": {
    "addr:full":"10691 Hawks Vista St Plantation FL 33324",
    "addr:housenumber":"10691",
    "addr:postcode":"33324",
    "addr:street":"Hawks Vista St",
    "iso:country":"US",
    "sg:address":"10691 Hawks Vista St",
    "sg:city":"Plantation",
    "sg:classifiers":[
        {
            "category":"Banks & Credit Unions",
            "subcategory":"Investment Brokerage",
            "type":"Services"
        }
    ],
    "sg:phone":"+1 954 916 3657",
    "sg:postcode":"33324",
    "sg:province":"FL",
    "sg:tags":[
        "advisory",
        "financial"
    ],
    "wof:name":"CSI Financial Inc",
    "wof:placetype":"venue"
},
  "geometry": {"coordinates":[-80.292672,26.114583],"type":"Point"}
}