{
  "type": "Feature",
  "properties": {
    "addr:full":"1 Cordona Dr Kissimmee FL 34758",
    "addr:housenumber":"1",
    "addr:postcode":"34758",
    "addr:street":"Cordona Dr",
    "iso:country":"US",
    "sg:address":"1 Cordona Dr",
    "sg:city":"Kissimmee",
    "sg:classifiers":[
        {
            "category":"Building & Trades",
            "subcategory":"Construction",
            "type":"Services"
        }
    ],
    "sg:phone":"+1 407 847 2240",
    "sg:postcode":"34758",
    "sg:province":"FL",
    "sg:tags":[
        "house"
    ],
    "wof:name":"Mercedes Homes Inc",
    "wof:placetype":"venue"
},
  "geometry": {"coordinates":[-81.44910900000001,28.1496],"type":"Point"}
}