{
  "type": "Feature",
  "properties": {
    "iso:country":"US",
    "sg:address":"218 Denese Ln",
    "sg:city":"Auburndale",
    "sg:classifiers":[
        {
            "category":"Building & Trades",
            "subcategory":"Pest Control",
            "type":"Services"
        }
    ],
    "sg:phone":"+1 863 968 0292",
    "sg:postcode":"33823",
    "sg:province":"FL",
    "wof:name":"Bugman",
    "wof:placetype":"venue"
},
  "geometry": {"coordinates":[-81.781622,28.085017],"type":"Point"}
}