{
  "type": "Feature",
  "properties": {
    "iso:country":"US",
    "sg:address":"2510 Michigan Ct",
    "sg:city":"Panama City",
    "sg:classifiers":[
        {
            "category":"Sports & Exercise",
            "subcategory":"Gym",
            "type":"Entertainment"
        }
    ],
    "sg:phone":"+1 850 914 2072",
    "sg:postcode":"32405",
    "sg:province":"FL",
    "sg:tags":[
        "fitness",
        "physical",
        "facility"
    ],
    "wof:name":"Lake City Fitness Center",
    "wof:placetype":"venue"
},
  "geometry": {"coordinates":[-85.707983,30.194892],"type":"Point"}
}