{
  "type": "Feature",
  "properties": {
    "iso:country":"US",
    "sg:address":"4960 NW 16th Ct",
    "sg:city":"Lauderhill",
    "sg:classifiers":[
        {
            "category":"Food & Beverages",
            "subcategory":"Farmers Market",
            "type":"Retail Goods"
        }
    ],
    "sg:phone":"+1 954 709 9425",
    "sg:postcode":"33313",
    "sg:province":"FL",
    "sg:tags":[
        "vegetable",
        "fruit"
    ],
    "wof:name":"Clayton Walcott Produce",
    "wof:placetype":"venue"
},
  "geometry": {"coordinates":[-80.215795,26.145903],"type":"Point"}
}