{
  "type": "Feature",
  "properties": {
    "iso:country":"US",
    "sg:address":"225 Smithson Dr",
    "sg:city":"Oviedo",
    "sg:classifiers":[
        {
            "category":"Building & Trades",
            "subcategory":"Electrical",
            "type":"Services"
        }
    ],
    "sg:phone":"+1 407 365 8906",
    "sg:postcode":"32765",
    "sg:province":"FL",
    "sg:tags":[
        "electrical",
        "contractor"
    ],
    "wof:name":"Smithson Electric Inc",
    "wof:placetype":"venue"
},
  "geometry": {"coordinates":[-81.20906100000001,28.631696],"type":"Point"}
}