{
  "type": "Feature",
  "properties": {
    "iso:country":"US",
    "sg:address":"648 Rustin Dr",
    "sg:city":"Chipley",
    "sg:classifiers":[
        {
            "category":"Shopping",
            "type":"Retail Goods"
        }
    ],
    "sg:phone":"+1 850 638 0909",
    "sg:postcode":"32428",
    "sg:province":"FL",
    "sg:tags":[
        "monument"
    ],
    "wof:name":"Rustin Vault Co",
    "wof:placetype":"venue"
},
  "geometry": {"coordinates":[-85.550202,30.780117],"type":"Point"}
}