{
  "type": "Feature",
  "properties": {
    "iso:country":"US",
    "sg:address":"1351 NW 78th Ave",
    "sg:city":"Doral",
    "sg:classifiers":[
        {
            "category":"Wholesale",
            "subcategory":"Plants",
            "type":"Manufacturing & Wholesale Goods"
        }
    ],
    "sg:phone":"+1 305 592 9200",
    "sg:postcode":"33126",
    "sg:province":"FL",
    "sg:tags":[
        "florist"
    ],
    "wof:name":"Flower Farm Direct Inc",
    "wof:placetype":"venue"
},
  "geometry": {"coordinates":[-80.32256099999999,25.783809],"type":"Point"}
}