{
  "type": "Feature",
  "properties": {
    "iso:country":"US",
    "sg:address":"14834 SW 24th St",
    "sg:city":"Miami",
    "sg:classifiers":[
        {
            "category":"Wholesale",
            "subcategory":"Toys & Hobbies",
            "type":"Manufacturing & Wholesale Goods"
        }
    ],
    "sg:phone":"+1 305 480 9711",
    "sg:postcode":"33175",
    "sg:province":"FL",
    "sg:tags":[
        "firework"
    ],
    "wof:name":"Party Sparks Inc",
    "wof:placetype":"venue"
},
  "geometry": {"coordinates":[-80.427587,25.744697],"type":"Point"}
}