{
  "type": "Feature",
  "properties": {
    "addr:full":"1669 Collins Ave Miami Beach FL 33139",
    "addr:housenumber":"1669",
    "addr:postcode":"33139",
    "addr:street":"Collins Ave",
    "iso:country":"US",
    "sg:address":"1669 Collins Ave",
    "sg:city":"Miami Beach",
    "sg:classifiers":[
        {
            "category":"Professional",
            "subcategory":"Management & Consulting",
            "type":"Services"
        }
    ],
    "sg:phone":"+1 305 651 0440",
    "sg:postcode":"33139",
    "sg:province":"FL",
    "sg:tags":[
        "consultant",
        "business"
    ],
    "wof:name":"Air Management Systems Inc",
    "wof:placetype":"venue"
},
  "geometry": {"coordinates":[-80.129729,25.791723],"type":"Point"}
}