{
  "type": "Feature",
  "properties": {
    "iso:country":"US",
    "sg:address":"1855 Knox Mcrae Dr",
    "sg:city":"Titusville",
    "sg:classifiers":[
        {
            "category":"Health Services",
            "subcategory":"Doctor",
            "type":"Services"
        },
        {
            "category":"Community Center",
            "type":"Public Place"
        }
    ],
    "sg:phone":"+1 321 269 2028",
    "sg:postcode":"32780",
    "sg:province":"FL",
    "sg:tags":[
        "physician",
        "family",
        "medical",
        "practice",
        "surgeons",
        "manipulative",
        "osteopathic",
        "treatment",
        "medicine"
    ],
    "wof:name":"Royal Oaks Medical Ctr",
    "wof:placetype":"venue"
},
  "geometry": {"coordinates":[-80.82278100000001,28.571932],"type":"Point"}
}