{
  "type": "Feature",
  "properties": {
    "iso:country":"US",
    "sg:address":"1124 Cobblestone Cir",
    "sg:city":"Kissimmee",
    "sg:classifiers":[
        {
            "category":"Building & Trades",
            "subcategory":"Construction",
            "type":"Services"
        }
    ],
    "sg:phone":"+1 407 973 8254",
    "sg:postcode":"34744",
    "sg:province":"FL",
    "sg:tags":[
        "painter"
    ],
    "wof:name":"B Zee Painting & Remodeling",
    "wof:placetype":"venue"
},
  "geometry": {"coordinates":[-81.34815399999999,28.27517],"type":"Point"}
}