{
  "type": "Feature",
  "properties": {
    "iso:country":"US",
    "sg:address":"926 SW Bayshore Blvd",
    "sg:city":"Port St Lucie",
    "sg:classifiers":[
        {
            "category":"Shopping",
            "type":"Retail Goods"
        },
        {
            "category":"Professional",
            "subcategory":"Advertising",
            "type":"Services"
        }
    ],
    "sg:phone":"+1 772 873 2226",
    "sg:postcode":"34983",
    "sg:province":"FL",
    "sg:tags":[
        "merchandise"
    ],
    "wof:name":"Quality Awards & Promotions In",
    "wof:placetype":"venue"
},
  "geometry": {"coordinates":[-80.37149100000001,27.311387],"type":"Point"}
}