{
  "type": "Feature",
  "properties": {
    "addr:full":"1001 S Evergreen Ave Clearwater FL 33756",
    "addr:housenumber":"1001",
    "addr:postcode":"33756",
    "addr:street":"S Evergreen Ave",
    "iso:country":"US",
    "sg:address":"1001 S Evergreen Ave",
    "sg:city":"Clearwater",
    "sg:classifiers":[
        {
            "category":"Manufacturing",
            "subcategory":"Signs",
            "type":"Manufacturing & Wholesale Goods"
        }
    ],
    "sg:phone":"+1 727 446 8646",
    "sg:postcode":"33756",
    "sg:province":"FL",
    "wof:name":"C R Signs Inc",
    "wof:placetype":"venue"
},
  "geometry": {"coordinates":[-82.781452,27.956195],"type":"Point"}
}