{
  "type": "Feature",
  "properties": {
    "iso:country":"US",
    "sg:address":"1110 Pinellas Bayway S",
    "sg:city":"Saint Petersburg",
    "sg:classifiers":[
        {
            "category":"Professional",
            "subcategory":"Computer Services",
            "type":"Services"
        }
    ],
    "sg:phone":"+1 727 867 5767",
    "sg:postcode":"33715",
    "sg:province":"FL",
    "sg:tags":[
        "programing",
        "custom"
    ],
    "wof:name":"Peter Sector",
    "wof:placetype":"venue"
},
  "geometry": {"coordinates":[-82.725887,27.67735],"type":"Point"}
}