{
  "type": "Feature",
  "properties": {
    "iso:country":"US",
    "sg:address":"931 S 14th St",
    "sg:city":"Fernandina Beach",
    "sg:classifiers":[
        {
            "category":"Professional",
            "subcategory":"Business Services",
            "type":"Services"
        }
    ],
    "sg:phone":"+1 904 277 3344",
    "sg:postcode":"32034",
    "sg:province":"FL",
    "sg:tags":[
        "auctioneer"
    ],
    "wof:name":"Contemp Apparel & Auction Drop",
    "wof:placetype":"venue"
},
  "geometry": {"coordinates":[-81.453271,30.658278],"type":"Point"}
}