{
  "type": "Feature",
  "properties": {
    "iso:country":"US",
    "sg:address":"810 63rd Ave N",
    "sg:city":"St Petersburg",
    "sg:classifiers":[
        {
            "category":"Insurance",
            "subcategory":"Insurance Agent",
            "type":"Services"
        }
    ],
    "sg:phone":"+1 727 896 2240",
    "sg:postcode":"33702",
    "sg:province":"FL",
    "wof:name":"Harbor Insurance Group",
    "wof:placetype":"venue"
},
  "geometry": {"coordinates":[-82.64678499999999,27.829265],"type":"Point"}
}