{
  "type": "Feature",
  "properties": {
    "addr:full":"1181 W Gulf To Lake Hwy Lecanto FL 34461",
    "addr:housenumber":"1181",
    "addr:postcode":"34461",
    "addr:street":"W Gulf To Lake Hwy",
    "iso:country":"US",
    "sg:address":"1181 W Gulf To Lake Hwy",
    "sg:city":"Lecanto",
    "sg:classifiers":[
        {
            "category":"Utilities",
            "subcategory":"Cable",
            "type":"Services"
        }
    ],
    "sg:phone":"+1 352 746 7376",
    "sg:postcode":"34461",
    "sg:province":"FL",
    "wof:name":"Time Warner",
    "wof:placetype":"venue"
},
  "geometry": {"coordinates":[-82.454052,28.852515],"type":"Point"}
}