{
  "type": "Feature",
  "properties": {
    "iso:country":"US",
    "sg:address":"3233 W Columbus Dr",
    "sg:city":"Tampa",
    "sg:classifiers":[
        {
            "category":"Retail",
            "subcategory":"Repair Shop",
            "type":"Services"
        },
        {
            "category":"Shopping",
            "subcategory":"Optical Goods",
            "type":"Retail Goods"
        }
    ],
    "sg:phone":"+1 813 871 5765",
    "sg:postcode":"33607",
    "sg:province":"FL",
    "wof:name":"Irma's Optical",
    "wof:placetype":"venue"
},
  "geometry": {"coordinates":[-82.497254,27.966794],"type":"Point"}
}