{
  "type": "Feature",
  "properties": {
    "iso:country":"US",
    "sg:address":"4738 Myla Ln",
    "sg:city":"West Palm Beach",
    "sg:classifiers":[
        {
            "category":"Building & Trades",
            "subcategory":"Construction",
            "type":"Services"
        }
    ],
    "sg:phone":"+1 561 252 7345",
    "sg:postcode":"33417",
    "sg:province":"FL",
    "sg:tags":[
        "carpentry",
        "contractor"
    ],
    "wof:name":"Flowers Baking Co Florida LLC",
    "wof:placetype":"venue"
},
  "geometry": {"coordinates":[-80.111209,26.702574],"type":"Point"}
}