{
  "type": "Feature",
  "properties": {
    "iso:country":"US",
    "sg:address":"16075 SW 149th Ter",
    "sg:city":"Miami",
    "sg:classifiers":[
        {
            "category":"Wholesale",
            "subcategory":"Books, Periodicals, & Newspapers",
            "type":"Manufacturing & Wholesale Goods"
        }
    ],
    "sg:phone":"+1 305 233 1605",
    "sg:postcode":"33196",
    "sg:province":"FL",
    "sg:tags":[
        "publisher",
        "book"
    ],
    "wof:name":"Editorial Concepts Inc",
    "wof:placetype":"venue"
},
  "geometry": {"coordinates":[-80.454132,25.627665],"type":"Point"}
}