{
  "type": "Feature",
  "properties": {
    "addr:full":"3050 N Federal Hwy Delray Beach FL 33483",
    "addr:housenumber":"3050",
    "addr:postcode":"33483",
    "addr:street":"N Federal Hwy",
    "iso:country":"US",
    "sg:address":"3050 N Federal Hwy",
    "sg:city":"Delray Beach",
    "sg:classifiers":[
        {
            "category":"Manufacturing",
            "subcategory":"Electronics",
            "type":"Manufacturing & Wholesale Goods"
        },
        {
            "category":"Shopping",
            "subcategory":"Computers & Home Electronics",
            "type":"Retail Goods"
        }
    ],
    "sg:phone":"+1 561 330 2223",
    "sg:postcode":"33483",
    "sg:province":"FL",
    "sg:tags":[
        "equipment",
        "satellite",
        "mfg",
        "system",
        "communication"
    ],
    "wof:name":"Ray's Satellite Inc",
    "wof:placetype":"venue"
},
  "geometry": {"coordinates":[-80.062789,26.49308],"type":"Point"}
}