{
  "type": "Feature",
  "properties": {
    "iso:country":"US",
    "sg:address":"2690 SE 49th Ave",
    "sg:city":"Ocala",
    "sg:classifiers":[
        {
            "category":"Building & Trades",
            "subcategory":"Landscaping Services",
            "type":"Services"
        }
    ],
    "sg:phone":"+1 352 427 4700",
    "sg:postcode":"34480",
    "sg:province":"FL",
    "sg:tags":[
        "tree"
    ],
    "wof:name":"Roger Childers Tree Svc",
    "wof:placetype":"venue"
},
  "geometry": {"coordinates":[-82.06640899999999,29.160817],"type":"Point"}
}