{
  "type": "Feature",
  "properties": {
    "addr:full":"14628 Wishing Wind Way Winter Garden FL 34711",
    "addr:housenumber":"14628",
    "addr:postcode":"34711",
    "addr:street":"Wishing Wind Way",
    "iso:country":"US",
    "sg:address":"14628 Wishing Wind Way",
    "sg:city":"Winter Garden",
    "sg:classifiers":[
        {
            "category":"Building & Trades",
            "subcategory":"Construction",
            "type":"Services"
        }
    ],
    "sg:phone":"+1 407 877 7123",
    "sg:postcode":"34711",
    "sg:province":"FL",
    "sg:tags":[
        "home",
        "builder"
    ],
    "wof:name":"Horizons Homes-Central Flrd",
    "wof:placetype":"venue"
},
  "geometry": {"coordinates":[-81.685744,28.55874],"type":"Point"}
}