{
  "type": "Feature",
  "properties": {
    "iso:country":"US",
    "sg:address":"986 N Temple Ave",
    "sg:city":"Starke",
    "sg:classifiers":[
        {
            "category":"Insurance",
            "subcategory":"Hazard Insurance",
            "type":"Services"
        },
        {
            "category":"Insurance",
            "subcategory":"Insurance Agent",
            "type":"Services"
        },
        {
            "category":"Insurance",
            "subcategory":"Life Insurance",
            "type":"Services"
        }
    ],
    "sg:phone":"+1 877 387 7478",
    "sg:postcode":"32091",
    "sg:province":"FL",
    "sg:tags":[
        "property",
        "casualty"
    ],
    "sg:website":"http://www.georgerobertsins.com",
    "wof:name":"Roberts George Insurance Inc",
    "wof:placetype":"venue"
},
  "geometry": {"coordinates":[-82.107651,29.955015],"type":"Point"}
}