{
  "type": "Feature",
  "properties": {
    "addr:full":"1459 Harrison St Titusville FL 32780",
    "addr:housenumber":"1459",
    "addr:postcode":"32780",
    "addr:street":"Harrison St",
    "iso:country":"US",
    "sg:address":"1459 Harrison St",
    "sg:city":"Titusville",
    "sg:classifiers":[
        {
            "category":"Food & Beverages",
            "subcategory":"Groceries & Convenience Stores",
            "type":"Retail Goods"
        }
    ],
    "sg:phone":"+1 321 268 5933",
    "sg:postcode":"32780",
    "sg:province":"FL",
    "sg:tags":[
        "grocer"
    ],
    "wof:name":"Gooding's Supermarket",
    "wof:placetype":"venue"
},
  "geometry": {"coordinates":[-80.82104099999999,28.585692],"type":"Point"}
}