{
  "type": "Feature",
  "properties": {
    "addr:full":"3521 Maclay Blvd S Tallahassee FL 32312",
    "addr:housenumber":"3521",
    "addr:postcode":"32312",
    "addr:street":"Maclay Blvd S",
    "iso:country":"US",
    "sg:address":"3521 Maclay Blvd S",
    "sg:city":"Tallahassee",
    "sg:classifiers":[
        {
            "category":"Personal",
            "type":"Services"
        },
        {
            "category":"Sports & Exercise",
            "subcategory":"Gym",
            "type":"Entertainment"
        }
    ],
    "sg:phone":"+1 850 431 2348",
    "sg:postcode":"32312",
    "sg:province":"FL",
    "sg:tags":[
        "fitness",
        "program",
        "physical",
        "facility"
    ],
    "wof:name":"Premier Health & Fitness Cente",
    "wof:placetype":"venue"
},
  "geometry": {"coordinates":[-84.25185,30.507213],"type":"Point"}
}