{
  "type": "Feature",
  "properties": {
    "addr:full":"2881 Madison St Marianna FL 32446",
    "addr:housenumber":"2881",
    "addr:postcode":"32446",
    "addr:street":"Madison St",
    "iso:country":"US",
    "sg:address":"2881 Madison St",
    "sg:city":"Marianna",
    "sg:classifiers":[
        {
            "category":"Restaurant",
            "type":"Food & Drink"
        }
    ],
    "sg:phone":"+1 850 526 4000",
    "sg:postcode":"32446",
    "sg:province":"FL",
    "wof:name":"Madisons Warehouse Restaurant",
    "wof:placetype":"venue"
},
  "geometry": {"coordinates":[-85.22564199999999,30.774039],"type":"Point"}
}