{
  "type": "Feature",
  "properties": {
    "addr:full":"9231 Coxwell Ct Jacksonville FL 32221",
    "addr:postcode":"9231;32221",
    "addr:street":"Coxwell Ct",
    "iso:country":"US",
    "sg:address":"9231 Coxwell Ct",
    "sg:city":"Jacksonville",
    "sg:classifiers":[
        {
            "category":"Home & Garden",
            "subcategory":"Building Materials",
            "type":"Retail Goods"
        }
    ],
    "sg:phone":"+1 904 695 2262",
    "sg:postcode":"32221",
    "sg:province":"FL",
    "wof:name":"Rigdon Wallcovering",
    "wof:placetype":"venue"
},
  "geometry": {"coordinates":[-81.808744,30.307783],"type":"Point"}
}