{
  "type": "Feature",
  "properties": {
    "addr:full":"10 Starfish Dr Vero Beach FL 32960",
    "addr:housenumber":"10",
    "addr:postcode":"32960",
    "addr:street":"Starfish Dr",
    "iso:country":"US",
    "sg:address":"10 Starfish Dr",
    "sg:city":"Vero Beach",
    "sg:classifiers":[
        {
            "category":"Local Transit",
            "type":"Transportation"
        }
    ],
    "sg:phone":"+1 772 778 7590",
    "sg:postcode":"32960",
    "sg:province":"FL",
    "sg:tags":[
        "passenger"
    ],
    "wof:name":"Classic VIP Transportation",
    "wof:placetype":"venue"
},
  "geometry": {"coordinates":[-80.37675,27.642804],"type":"Point"}
}