{
  "type": "Feature",
  "properties": {
    "iso:country":"US",
    "sg:address":"2222 Ponce De Leon Blvd Fl 1",
    "sg:city":"Coral Gables",
    "sg:classifiers":[
        {
            "category":"Banks & Credit Unions",
            "subcategory":"Bank",
            "type":"Services"
        }
    ],
    "sg:phone":"+1 305 441 2222",
    "sg:postcode":"33134",
    "sg:province":"FL",
    "sg:website":"www.bankmercantile.com",
    "wof:name":"Mercantile Bank",
    "wof:placetype":"venue"
},
  "geometry": {"coordinates":[-80.25885599999999,25.751781],"type":"Point"}
}