{
  "type": "Feature",
  "properties": {
    "iso:country":"US",
    "sg:address":"12201 N Armenia Ave",
    "sg:city":"Tampa",
    "sg:classifiers":[
        {
            "category":"Wholesale",
            "subcategory":"Toys & Hobbies",
            "type":"Manufacturing & Wholesale Goods"
        }
    ],
    "sg:phone":"+1 813 931 4548",
    "sg:postcode":"33612",
    "sg:province":"FL",
    "sg:tags":[
        "wholesaler"
    ],
    "wof:name":"Southeastern Co Wholesale",
    "wof:placetype":"venue"
},
  "geometry": {"coordinates":[-82.47952600000001,28.055812],"type":"Point"}
}