{
  "type": "Feature",
  "properties": {
    "addr:full":"23102 Sandalfoot Plaza Dr Boca Raton FL 33428",
    "addr:housenumber":"23102",
    "addr:postcode":"33428",
    "addr:street":"Sandalfoot Plaza Dr",
    "iso:country":"US",
    "sg:address":"23102 Sandalfoot Plaza Dr",
    "sg:city":"Boca Raton",
    "sg:classifiers":[
        {
            "category":"Education",
            "subcategory":"Dance Studio",
            "type":"Public Place"
        }
    ],
    "sg:phone":"+1 561 488 1961",
    "sg:postcode":"33428",
    "sg:province":"FL",
    "wof:name":"Mrs PS Dance Acrobatic Studios",
    "wof:placetype":"venue"
},
  "geometry": {"coordinates":[-80.20165900000001,26.332199],"type":"Point"}
}