{
  "type": "Feature",
  "properties": {
    "iso:country":"US",
    "sg:address":"1722 S Missouri Ave",
    "sg:city":"Clearwater",
    "sg:classifiers":[
        {
            "category":"Real Estate",
            "subcategory":"Real Estate Services",
            "type":"Services"
        },
        {
            "category":"Real Estate",
            "subcategory":"Real Estate Agent",
            "type":"Services"
        }
    ],
    "sg:phone":"+1 727 581 7000",
    "sg:postcode":"33756",
    "sg:province":"FL",
    "sg:tags":[
        "management"
    ],
    "sg:website":"http://www.1031taxfreesale.com",
    "wof:name":"Able Property",
    "wof:placetype":"venue"
},
  "geometry": {"coordinates":[-82.78756799999999,27.934742],"type":"Point"}
}