{
  "type": "Feature",
  "properties": {
    "iso:country":"US",
    "sg:address":"5323 Lenox Ave",
    "sg:city":"Jacksonville",
    "sg:classifiers":[
        {
            "category":"Autos & Motor Vehicles",
            "subcategory":"Boat Sales",
            "type":"Retail Goods"
        }
    ],
    "sg:phone":"+1 904 786 7402",
    "sg:postcode":"32205",
    "sg:province":"FL",
    "sg:tags":[
        "equipment",
        "marine",
        "supply"
    ],
    "sg:website":"www.ljdiesel.com",
    "wof:name":"L & J Diesel Svc Inc",
    "wof:placetype":"venue"
},
  "geometry": {"coordinates":[-81.73801,30.31061],"type":"Point"}
}