{
  "type": "Feature",
  "properties": {
    "iso:country":"US",
    "sg:address":"21404 SW 15 Ave",
    "sg:city":"Newberry",
    "sg:classifiers":[
        {
            "category":"Restaurant",
            "type":"Food & Drink"
        }
    ],
    "sg:phone":"+1 352 472 3001",
    "sg:postcode":"32669",
    "sg:province":"FL",
    "sg:tags":[
        "eating"
    ],
    "wof:name":"J Macs Concessions & Catering",
    "wof:placetype":"venue"
},
  "geometry": {"coordinates":[-82.556887,29.640081],"type":"Point"}
}