{
  "type": "Feature",
  "properties": {
    "addr:full":"10550 Belcher Rd S Largo FL 33777",
    "addr:housenumber":"10550",
    "addr:postcode":"33777",
    "addr:street":"Belcher Rd S",
    "iso:country":"US",
    "sg:address":"10550 Belcher Rd S",
    "sg:city":"Largo",
    "sg:classifiers":[
        {
            "category":"Shopping",
            "type":"Retail Goods"
        }
    ],
    "sg:phone":"+1 727 549 9772",
    "sg:postcode":"33777",
    "sg:province":"FL",
    "sg:tags":[
        "spa",
        "hot",
        "tub"
    ],
    "wof:name":"SLA Spas",
    "wof:placetype":"venue"
},
  "geometry": {"coordinates":[-82.744691,27.868751],"type":"Point"}
}