{
  "type": "Feature",
  "properties": {
    "addr:full":"1604 Olive St Lakeland FL 33815",
    "addr:housenumber":"1604",
    "addr:postcode":"33815",
    "addr:street":"Olive St",
    "iso:country":"US",
    "sg:address":"1604 Olive St",
    "sg:city":"Lakeland",
    "sg:classifiers":[
        {
            "category":"Wholesale",
            "subcategory":"Medical Equipment & Supplies",
            "type":"Manufacturing & Wholesale Goods"
        }
    ],
    "sg:phone":"+1 863 683 1869",
    "sg:postcode":"33815",
    "sg:province":"FL",
    "sg:tags":[
        "x",
        "apparatus"
    ],
    "wof:name":"Millennium Medical Systems",
    "wof:placetype":"venue"
},
  "geometry": {"coordinates":[-81.97944699999999,28.03932],"type":"Point"}
}