{
  "type": "Feature",
  "properties": {
    "addr:full":"2807 Tamiami Trl Sarasota FL 34234",
    "addr:housenumber":"2807",
    "addr:postcode":"34234",
    "addr:street":"Tamiami Trl",
    "iso:country":"US",
    "sg:address":"2807 Tamiami Trl",
    "sg:city":"Sarasota",
    "sg:classifiers":[
        {
            "category":"Professional",
            "subcategory":"Accounting & Tax Preparation",
            "type":"Services"
        }
    ],
    "sg:phone":"+1 941 351 9872",
    "sg:postcode":"34234",
    "sg:province":"FL",
    "sg:tags":[
        "return",
        "filing"
    ],
    "wof:name":"Jackson Hewitt Tax Svc",
    "wof:placetype":"venue"
},
  "geometry": {"coordinates":[-82.550241,27.362887],"type":"Point"}
}