{
  "type": "Feature",
  "properties": {
    "iso:country":"US",
    "sg:address":"726 E Main St",
    "sg:city":"Immokalee",
    "sg:classifiers":[
        {
            "category":"Autos & Motor Vehicles",
            "subcategory":"Fuel & Gas Station",
            "type":"Retail Goods"
        }
    ],
    "sg:phone":"+1 239 657 6188",
    "sg:postcode":"34142",
    "sg:province":"FL",
    "sg:tags":[
        "oil"
    ],
    "wof:name":"Davis Oil Co",
    "wof:placetype":"venue"
},
  "geometry": {"coordinates":[-81.40871,26.417959],"type":"Point"}
}