{
  "type": "Feature",
  "properties": {
    "addr:full":"505 Zachary Dr Apopka FL 32712",
    "addr:housenumber":"505",
    "addr:postcode":"32712",
    "addr:street":"Zachary Dr",
    "iso:country":"US",
    "sg:address":"505 Zachary Dr",
    "sg:city":"Apopka",
    "sg:classifiers":[
        {
            "category":"Shopping",
            "subcategory":"Music",
            "type":"Retail Goods"
        }
    ],
    "sg:phone":"+1 407 886 4021",
    "sg:postcode":"32712",
    "sg:province":"FL",
    "wof:name":"Power Records Distributor",
    "wof:placetype":"venue"
},
  "geometry": {"coordinates":[-81.51992300000001,28.704987],"type":"Point"}
}