{
  "type": "Feature",
  "properties": {
    "addr:full":"26100 SW 177th Ave Homestead FL 33031",
    "addr:housenumber":"26100",
    "addr:postcode":"33031",
    "addr:street":"Sw 177Th Ave",
    "iso:country":"US",
    "sg:address":"26100 SW 177th Ave",
    "sg:city":"Homestead",
    "sg:classifiers":[
        {
            "category":"Wholesale",
            "subcategory":"Plants",
            "type":"Manufacturing & Wholesale Goods"
        },
        {
            "category":"Home & Garden",
            "subcategory":"Garden Supply",
            "type":"Retail Goods"
        }
    ],
    "sg:phone":"+1 305 248 5220",
    "sg:postcode":"33031",
    "sg:province":"FL",
    "sg:tags":[
        "nurseryman"
    ],
    "wof:name":"Oriental Nursery Farm Inc",
    "wof:placetype":"venue"
},
  "geometry": {"coordinates":[-80.47799999999999,25.525687],"type":"Point"}
}