{
  "type": "Feature",
  "properties": {
    "iso:country":"US",
    "sg:address":"330 Scarlet Blvd",
    "sg:city":"Oldsmar",
    "sg:classifiers":[
        {
            "category":"Manufacturing",
            "subcategory":"Chemicals & Compounds",
            "type":"Manufacturing & Wholesale Goods"
        }
    ],
    "sg:phone":"+1 813 855 6664",
    "sg:postcode":"34677",
    "sg:province":"FL",
    "sg:tags":[
        "car",
        "product",
        "mfg",
        "care"
    ],
    "sg:website":"www.megapowerinc.com",
    "wof:name":"Mega Power Inc",
    "wof:placetype":"venue"
},
  "geometry": {"coordinates":[-82.677111,28.039636],"type":"Point"}
}