{
  "type": "Feature",
  "properties": {
    "iso:country":"US",
    "sg:address":"5104 Canterbury Dr",
    "sg:city":"Sarasota",
    "sg:classifiers":[
        {
            "category":"Professional",
            "type":"Services"
        }
    ],
    "sg:phone":"+1 941 351 6806",
    "sg:postcode":"34243",
    "sg:province":"FL",
    "wof:name":"Arlak Corp",
    "wof:placetype":"venue"
},
  "geometry": {"coordinates":[-82.49626000000001,27.404288],"type":"Point"}
}