{
  "type": "Feature",
  "properties": {
    "iso:country":"US",
    "sg:address":"1824 Atlantic Blvd",
    "sg:city":"Jacksonville",
    "sg:classifiers":[
        {
            "category":"Professional",
            "subcategory":"Lawyer & Legal Services",
            "type":"Services"
        }
    ],
    "sg:phone":"+1 904 634 1122",
    "sg:postcode":"32207",
    "sg:province":"FL",
    "sg:tags":[
        "attorney"
    ],
    "sg:website":"www.sackslegal.com",
    "wof:name":"David B Sacks Law Offices",
    "wof:placetype":"venue"
},
  "geometry": {"coordinates":[-81.64872200000001,30.307052],"type":"Point"}
}