{
  "type": "Feature",
  "properties": {
    "iso:country":"US",
    "sg:address":"2985 Edison Ave",
    "sg:city":"Jacksonville",
    "sg:classifiers":[
        {
            "category":"Manufacturing",
            "subcategory":"Printing",
            "type":"Manufacturing & Wholesale Goods"
        }
    ],
    "sg:phone":"+1 904 388 2641",
    "sg:postcode":"32254",
    "sg:province":"FL",
    "sg:tags":[
        "commercial"
    ],
    "wof:name":"Don Sikes Printing Co",
    "wof:placetype":"venue"
},
  "geometry": {"coordinates":[-81.700222,30.322831],"type":"Point"}
}