{
  "type": "Feature",
  "properties": {
    "iso:country":"US",
    "sg:address":"559 3rd St",
    "sg:city":"Daytona Beach",
    "sg:classifiers":[
        {
            "category":"Building & Trades",
            "subcategory":"Landscaping Services",
            "type":"Services"
        }
    ],
    "sg:phone":"+1 386 255 0783",
    "sg:postcode":"32117",
    "sg:province":"FL",
    "wof:name":"Je Lawn Service",
    "wof:placetype":"venue"
},
  "geometry": {"coordinates":[-81.041431,29.228157],"type":"Point"}
}