{
  "type": "Feature",
  "properties": {
    "iso:country":"US",
    "sg:address":"2465 N McMullen Booth Rd",
    "sg:city":"Clearwater",
    "sg:classifiers":[
        {
            "category":"Shopping",
            "subcategory":"Pharmacy",
            "type":"Retail Goods"
        }
    ],
    "sg:phone":"+1 727 724 0303",
    "sg:postcode":"33759",
    "sg:province":"FL",
    "wof:name":"Ameridrug Pharmacy",
    "wof:placetype":"venue"
},
  "geometry": {"coordinates":[-82.708929,28.01053],"type":"Point"}
}