{
  "type": "Feature",
  "properties": {
    "iso:country":"US",
    "sg:address":"785 NE Harbour Ter",
    "sg:city":"Boca Raton",
    "sg:classifiers":[
        {
            "category":"Professional",
            "subcategory":"Research",
            "type":"Services"
        }
    ],
    "sg:phone":"+1 561 447 7006",
    "sg:postcode":"33431",
    "sg:province":"FL",
    "sg:tags":[
        "assistance",
        "program",
        "technology"
    ],
    "wof:name":"Beverage Diagnostic Corp",
    "wof:placetype":"venue"
},
  "geometry": {"coordinates":[-80.075264,26.373344],"type":"Point"}
}