{
  "type": "Feature",
  "properties": {
    "addr:full":"400 Capital Cir SE 283 Tallahassee FL 32301",
    "addr:housenumber":"400;283",
    "addr:postcode":"32301",
    "addr:street":"Capital Cir Se",
    "iso:country":"US",
    "sg:address":"400 Capital Cir SE 283",
    "sg:city":"Tallahassee",
    "sg:classifiers":[
        {
            "category":"Professional",
            "subcategory":"Research",
            "type":"Services"
        }
    ],
    "sg:phone":"+1 850 402 1023",
    "sg:postcode":"32301",
    "sg:province":"FL",
    "sg:tags":[
        "analysis",
        "market"
    ],
    "wof:name":"Dax Jordan & Assoc Inc",
    "wof:placetype":"venue"
},
  "geometry": {"coordinates":[-84.226669,30.441401],"type":"Point"}
}