{
  "type": "Feature",
  "properties": {
    "iso:country":"US",
    "sg:address":"11412 Okeechobee Blvd",
    "sg:city":"Royal Palm Beach",
    "sg:classifiers":[
        {
            "category":"Health Services",
            "subcategory":"Podiatrist",
            "type":"Services"
        }
    ],
    "sg:phone":"+1 561 793 6170",
    "sg:postcode":"33411",
    "sg:province":"FL",
    "wof:name":"Western Communities Foot",
    "wof:placetype":"venue"
},
  "geometry": {"coordinates":[-80.209031,26.709325],"type":"Point"}
}