{
  "type": "Feature",
  "properties": {
    "iso:country":"US",
    "sg:address":"14374 SW 142nd Ave",
    "sg:city":"Miami",
    "sg:classifiers":[
        {
            "category":"Manufacturing",
            "subcategory":"Furniture",
            "type":"Manufacturing & Wholesale Goods"
        }
    ],
    "sg:phone":"+1 305 252 1212",
    "sg:postcode":"33186",
    "sg:province":"FL",
    "sg:tags":[
        "builder",
        "designer",
        "custom"
    ],
    "wof:name":"Larsen Plant Containers",
    "wof:placetype":"venue"
},
  "geometry": {"coordinates":[-80.42271100000001,25.633537],"type":"Point"}
}