{
  "type": "Feature",
  "properties": {
    "addr:full":"7221 US-19 N Pinellas Park FL 33781",
    "addr:housenumber":"7221",
    "addr:postcode":"33781",
    "addr:street":"Us-19 N",
    "iso:country":"US",
    "sg:address":"7221 US-19 N",
    "sg:city":"Pinellas Park",
    "sg:classifiers":[
        {
            "category":"Restaurant",
            "type":"Food & Drink"
        }
    ],
    "sg:menulink":"http://www.allmenus.com/fl/st-petersburg/152284-honeybaked-ham/menu/",
    "sg:phone":"+1 727 521 2621",
    "sg:postcode":"33781",
    "sg:province":"FL",
    "sg:tags":[
        "american"
    ],
    "wof:name":"The HoneyBaked Ham Company",
    "wof:placetype":"venue"
},
  "geometry": {"coordinates":[-82.68249400000001,27.837571],"type":"Point"}
}