{
  "type": "Feature",
  "properties": {
    "addr:full":"12575 NE 7th Ave Miami FL 33161",
    "addr:housenumber":"12575",
    "addr:postcode":"33161",
    "addr:street":"Ne 7Th Ave",
    "iso:country":"US",
    "sg:address":"12575 NE 7th Ave",
    "sg:city":"Miami",
    "sg:classifiers":[
        {
            "category":"Home & Garden",
            "subcategory":"Mobile Homes",
            "type":"Retail Goods"
        }
    ],
    "sg:phone":"+1 786 897 4500",
    "sg:postcode":"33161",
    "sg:province":"FL",
    "wof:name":"Belvair For Modern Living",
    "wof:placetype":"venue"
},
  "geometry": {"coordinates":[-80.18438999999999,25.890589],"type":"Point"}
}