{
  "type": "Feature",
  "properties": {
    "iso:country":"US",
    "sg:address":"6419 Stirling Rd",
    "sg:city":"Davie",
    "sg:classifiers":[
        {
            "category":"Restaurant",
            "type":"Food & Drink"
        }
    ],
    "sg:phone":"+1 954 792 6220",
    "sg:postcode":"33314",
    "sg:province":"FL",
    "wof:name":"A Thai Restaurant",
    "wof:placetype":"venue"
},
  "geometry": {"coordinates":[-80.217028,26.046544],"type":"Point"}
}