{
  "type": "Feature",
  "properties": {
    "addr:full":"2654 Hemlock Ct Middleburg FL 32068",
    "addr:housenumber":"2654",
    "addr:postcode":"32068",
    "addr:street":"Hemlock Ct",
    "iso:country":"US",
    "sg:address":"2654 Hemlock Ct",
    "sg:city":"Middleburg",
    "sg:classifiers":[
        {
            "category":"Organizations",
            "subcategory":"Community Association",
            "type":"Services"
        }
    ],
    "sg:phone":"+1 904 269 4743",
    "sg:postcode":"32068",
    "sg:province":"FL",
    "wof:name":"South Lake Estates Homeow",
    "wof:placetype":"venue"
},
  "geometry": {"coordinates":[-81.764532,30.101044],"type":"Point"}
}