{
  "type": "Feature",
  "properties": {
    "iso:country":"US",
    "sg:address":"3118 W 5th St",
    "sg:city":"Jacksonville",
    "sg:classifiers":[
        {
            "category":"Building & Trades",
            "subcategory":"Landscaping Services",
            "type":"Services"
        }
    ],
    "sg:phone":"+1 904 693 0301",
    "sg:postcode":"32254",
    "sg:province":"FL",
    "sg:tags":[
        "landscape"
    ],
    "wof:name":"Mario Potts Landscaping & Remo",
    "wof:placetype":"venue"
},
  "geometry": {"coordinates":[-81.720538,30.343783],"type":"Point"}
}