{
  "type": "Feature",
  "properties": {
    "iso:country":"US",
    "sg:address":"2595 Harbor Blvd",
    "sg:city":"Port Charlotte",
    "sg:classifiers":[
        {
            "category":"Education",
            "subcategory":"Special Training",
            "type":"Public Place"
        }
    ],
    "sg:phone":"+1 941 743 6007",
    "sg:postcode":"33952",
    "sg:province":"FL",
    "sg:tags":[
        "photography",
        "school"
    ],
    "wof:name":"Wiggles & Giggles",
    "wof:placetype":"venue"
},
  "geometry": {"coordinates":[-82.09686000000001,26.987961],"type":"Point"}
}