{
  "type": "Feature",
  "properties": {
    "iso:country":"US",
    "sg:address":"1519 Killearn Center Blvd",
    "sg:city":"Tallahassee",
    "sg:classifiers":[
        {
            "category":"Real Estate",
            "subcategory":"Real Estate Agent",
            "type":"Services"
        }
    ],
    "sg:phone":"+1 850 893 2525",
    "sg:postcode":"32309",
    "sg:province":"FL",
    "sg:website":"www.armorrealty.com",
    "wof:name":"Armor Realty Of Tallahassee",
    "wof:placetype":"venue"
},
  "geometry": {"coordinates":[-84.249326,30.505155],"type":"Point"}
}