{
  "type": "Feature",
  "properties": {
    "addr:full":"185 Herron Rd Fort Myers FL 33903",
    "addr:housenumber":"185",
    "addr:postcode":"33903",
    "addr:street":"Herron Rd",
    "iso:country":"US",
    "sg:address":"185 Herron Rd",
    "sg:city":"Fort Myers",
    "sg:classifiers":[
        {
            "category":"Building & Trades",
            "subcategory":"Cleaning & Sanitation",
            "type":"Services"
        }
    ],
    "sg:phone":"+1 239 995 2418",
    "sg:postcode":"33903",
    "sg:province":"FL",
    "sg:tags":[
        "janitor"
    ],
    "wof:name":"Cynthia Ritter Cleaning Svc",
    "wof:placetype":"venue"
},
  "geometry": {"coordinates":[-81.903457,26.682174],"type":"Point"}
}