{
  "type": "Feature",
  "properties": {
    "iso:country":"US",
    "sg:address":"436 N Wymore Rd",
    "sg:city":"Winter Park",
    "sg:classifiers":[
        {
            "category":"Health Services",
            "subcategory":"Medical Lab",
            "type":"Services"
        }
    ],
    "sg:phone":"+1 407 644 1478",
    "sg:postcode":"32789",
    "sg:province":"FL",
    "sg:tags":[
        "laboratory",
        "dental"
    ],
    "wof:name":"Dental Design",
    "wof:placetype":"venue"
},
  "geometry": {"coordinates":[-81.38533,28.601401],"type":"Point"}
}