{
  "type": "Feature",
  "properties": {
    "addr:full":"607 Suwannee Ave NW Branford FL 32008",
    "addr:housenumber":"607",
    "addr:postcode":"32008",
    "addr:street":"Suwannee Ave Nw",
    "iso:country":"US",
    "sg:address":"607 Suwannee Ave NW",
    "sg:city":"Branford",
    "sg:phone":"+1 386 935 1363",
    "sg:postcode":"32008",
    "sg:province":"FL",
    "wof:name":"First Baptist Church",
    "wof:placetype":"venue"
},
  "geometry": {"coordinates":[-82.930615,29.962381],"type":"Point"}
}