{
  "type": "Feature",
  "properties": {
    "iso:country":"US",
    "sg:address":"12124 US Hwy 19",
    "sg:city":"Hudson",
    "sg:classifiers":[
        {
            "category":"Home & Garden",
            "subcategory":"Home Furnishings",
            "type":"Retail Goods"
        }
    ],
    "sg:phone":"+1 727 862 5700",
    "sg:postcode":"34667",
    "sg:province":"FL",
    "sg:tags":[
        "curtain",
        "made",
        "drapery"
    ],
    "wof:name":"Vertical Blind Empire",
    "wof:placetype":"venue"
},
  "geometry": {"coordinates":[-82.699223,28.33302],"type":"Point"}
}