{
  "type": "Feature",
  "properties": {
    "iso:country":"US",
    "sg:address":"404 Fairway Blvd",
    "sg:city":"Panama City Bch",
    "sg:classifiers":[
        {
            "category":"Building & Trades",
            "subcategory":"Construction",
            "type":"Services"
        }
    ],
    "sg:phone":"+1 850 233 3740",
    "sg:postcode":"32407",
    "sg:province":"FL",
    "sg:tags":[
        "general",
        "contractor"
    ],
    "wof:name":"Just Rite Landscaping",
    "wof:placetype":"venue"
},
  "geometry": {"coordinates":[-85.843265,30.219875],"type":"Point"}
}