{
  "type": "Feature",
  "properties": {
    "iso:country":"US",
    "sg:address":"2026 W Beach Dr",
    "sg:city":"Panama City",
    "sg:classifiers":[
        {
            "category":"Real Estate",
            "subcategory":"Real Estate Operator",
            "type":"Services"
        }
    ],
    "sg:phone":"+1 850 872 8610",
    "sg:postcode":"32401",
    "sg:province":"FL",
    "sg:tags":[
        "building",
        "commercial",
        "lessor"
    ],
    "wof:name":"Neil & Jimmie Ann Graham",
    "wof:placetype":"venue"
},
  "geometry": {"coordinates":[-85.69078500000001,30.164882],"type":"Point"}
}