{
  "type": "Feature",
  "properties": {
    "addr:full":"2290 Palm Ave Hialeah FL 33010",
    "addr:housenumber":"2290",
    "addr:postcode":"33010",
    "addr:street":"Palm Ave",
    "iso:country":"US",
    "sg:address":"2290 Palm Ave",
    "sg:city":"Hialeah",
    "sg:classifiers":[
        {
            "category":"Retail",
            "subcategory":"Repair Shop",
            "type":"Services"
        },
        {
            "category":"Home & Garden",
            "subcategory":"Garden Supply",
            "type":"Retail Goods"
        }
    ],
    "sg:phone":"+1 305 885 5512",
    "sg:postcode":"33010",
    "sg:province":"FL",
    "sg:tags":[
        "repairing",
        "lawn",
        "mower"
    ],
    "wof:name":"S & S Lawnmower & Small Engine",
    "wof:placetype":"venue"
},
  "geometry": {"coordinates":[-80.282183,25.842032],"type":"Point"}
}