{
  "type": "Feature",
  "properties": {
    "iso:country":"US",
    "sg:address":"5318 SW 87th Ave",
    "sg:city":"Cooper City",
    "sg:classifiers":[
        {
            "category":"Health Services",
            "subcategory":"Medical Lab",
            "type":"Services"
        }
    ],
    "sg:phone":"+1 954 434 6446",
    "sg:postcode":"33328",
    "sg:province":"FL",
    "sg:tags":[
        "laboratory"
    ],
    "wof:name":"Royal Crown Dental Lab",
    "wof:placetype":"venue"
},
  "geometry": {"coordinates":[-80.262263,26.052248],"type":"Point"}
}