{
  "type": "Feature",
  "properties": {
    "addr:full":"1453 E Gary Rd Lakeland FL 33801",
    "addr:housenumber":"1453",
    "addr:postcode":"33801",
    "addr:street":"E Gary Rd",
    "iso:country":"US",
    "sg:address":"1453 E Gary Rd",
    "sg:city":"Lakeland",
    "sg:classifiers":[
        {
            "category":"Building & Trades",
            "subcategory":"Electrical",
            "type":"Services"
        }
    ],
    "sg:phone":"+1 863 683 5857",
    "sg:postcode":"33801",
    "sg:province":"FL",
    "sg:tags":[
        "electrician"
    ],
    "wof:name":"Strickland Power Inc",
    "wof:placetype":"venue"
},
  "geometry": {"coordinates":[-81.93517300000001,28.049557],"type":"Point"}
}