{
  "type": "Feature",
  "properties": {
    "addr:full":"1040 Weston Rd Fort Lauderdale FL 33331",
    "addr:housenumber":"1040",
    "addr:postcode":"33331",
    "addr:street":"Weston Rd",
    "iso:country":"US",
    "sg:address":"1040 Weston Rd",
    "sg:city":"Fort Lauderdale",
    "sg:classifiers":[
        {
            "category":"Banks & Credit Unions",
            "subcategory":"Bank",
            "type":"Services"
        }
    ],
    "sg:phone":"+1 954 612 2861",
    "sg:postcode":"33331",
    "sg:province":"FL",
    "sg:tags":[
        "mortgage",
        "loan",
        "broker",
        "real estate"
    ],
    "wof:name":"Home Lending Solutions Corp",
    "wof:placetype":"venue"
},
  "geometry": {"coordinates":[-80.365865,26.104258],"type":"Point"}
}