{
  "type": "Feature",
  "properties": {
    "addr:full":"604 E Vine St Kissimmee FL 34744",
    "addr:housenumber":"604",
    "addr:postcode":"34744",
    "addr:street":"E Vine St",
    "iso:country":"US",
    "sg:address":"604 E Vine St",
    "sg:city":"Kissimmee",
    "sg:classifiers":[
        {
            "category":"Shopping",
            "subcategory":"Jewelry",
            "type":"Retail Goods"
        }
    ],
    "sg:phone":"+1 407 931 2124",
    "sg:postcode":"34744",
    "sg:province":"FL",
    "wof:name":"GSK Jewelry Inc",
    "wof:placetype":"venue"
},
  "geometry": {"coordinates":[-81.39903700000001,28.304427],"type":"Point"}
}