{
  "type": "Feature",
  "properties": {
    "iso:country":"US",
    "sg:address":"3515 Emerywood Ln",
    "sg:city":"Orlando",
    "sg:classifiers":[
        {
            "category":"Real Estate",
            "subcategory":"Real Estate Agent",
            "type":"Services"
        }
    ],
    "sg:phone":"+1 407 855 0005",
    "sg:postcode":"32812",
    "sg:province":"FL",
    "wof:name":"Ravenscroft Realty Group Inc",
    "wof:placetype":"venue"
},
  "geometry": {"coordinates":[-81.336473,28.500539],"type":"Point"}
}