{
  "type": "Feature",
  "properties": {
    "addr:full":"12620 Tamiami Trl E Naples FL 34113",
    "addr:housenumber":"12620",
    "addr:postcode":"34113",
    "addr:street":"Tamiami Trl E",
    "iso:country":"US",
    "sg:address":"12620 Tamiami Trl E",
    "sg:city":"Naples",
    "sg:classifiers":[
        {
            "category":"Fast Food",
            "type":"Food & Drink"
        },
        {
            "category":"Restaurant",
            "type":"Food & Drink"
        },
        {
            "category":"Food & Beverages",
            "subcategory":"Groceries & Convenience Stores",
            "type":"Retail Goods"
        }
    ],
    "sg:phone":"+1 239 793 7990",
    "sg:postcode":"34113",
    "sg:province":"FL",
    "sg:tags":[
        "shop",
        "american",
        "sandwich",
        "take"
    ],
    "wof:name":"Subway",
    "wof:placetype":"venue"
},
  "geometry": {"coordinates":[-81.70372,26.066046],"type":"Point"}
}