{
  "type": "Feature",
  "properties": {
    "iso:country":"US",
    "sg:address":"10175 S Arabian Ave",
    "sg:city":"Floral City",
    "sg:classifiers":[
        {
            "category":"Building & Trades",
            "subcategory":"Landscaping Services",
            "type":"Services"
        }
    ],
    "sg:phone":"+1 352 212 4026",
    "sg:postcode":"34436",
    "sg:province":"FL",
    "wof:name":"Joes Lawn Care",
    "wof:placetype":"venue"
},
  "geometry": {"coordinates":[-82.29938300000001,28.715015],"type":"Point"}
}