{
  "type": "Feature",
  "properties": {
    "addr:full":"3014 W 21st Ct Panama City FL 32405",
    "addr:housenumber":"3014",
    "addr:postcode":"32405",
    "addr:street":"W 21St Ct",
    "iso:country":"US",
    "sg:address":"3014 W 21st Ct",
    "sg:city":"Panama City",
    "sg:classifiers":[
        {
            "category":"Freight",
            "type":"Transportation"
        }
    ],
    "sg:phone":"+1 850 913 9511",
    "sg:postcode":"32405",
    "sg:province":"FL",
    "sg:tags":[
        "commercial",
        "storage"
    ],
    "wof:name":"Ace Moving",
    "wof:placetype":"venue"
},
  "geometry": {"coordinates":[-85.703078,30.18654],"type":"Point"}
}