{
  "type": "Feature",
  "properties": {
    "iso:country":"US",
    "sg:address":"2970 Robins Nest Ct",
    "sg:city":"Saint Cloud",
    "sg:classifiers":[
        {
            "category":"Wholesale",
            "subcategory":"Machinery & Supplies",
            "type":"Manufacturing & Wholesale Goods"
        }
    ],
    "sg:phone":"+1 407 957 5517",
    "sg:postcode":"34772",
    "sg:province":"FL",
    "sg:tags":[
        "equipment",
        "rep",
        "printing",
        "specialized",
        "mfg"
    ],
    "wof:name":"Formtech Services Inc",
    "wof:placetype":"venue"
},
  "geometry": {"coordinates":[-81.23671400000001,28.210469],"type":"Point"}
}