{
  "type": "Feature",
  "properties": {
    "iso:country":"US",
    "sg:address":"4302 Henderson Blvd # 107",
    "sg:city":"Tampa",
    "sg:classifiers":[
        {
            "category":"Organizations",
            "subcategory":"Professional Association",
            "type":"Services"
        }
    ],
    "sg:phone":"+1 813 253 5733",
    "sg:postcode":"33629",
    "sg:province":"FL",
    "sg:tags":[
        "business",
        "trade"
    ],
    "sg:website":"http://www.tampabx.com",
    "wof:name":"Tampa Builder's Exchange Inc",
    "wof:placetype":"venue"
},
  "geometry": {"coordinates":[-82.516497,27.924527],"type":"Point"}
}