{
  "type": "Feature",
  "properties": {
    "iso:country":"US",
    "sg:address":"8265 Hangar Blvd",
    "sg:city":"Orlando",
    "sg:classifiers":[
        {
            "category":"Deli",
            "type":"Food & Drink"
        },
        {
            "category":"Restaurant",
            "type":"Food & Drink"
        }
    ],
    "sg:phone":"+1 407 812 2028",
    "sg:postcode":"32827",
    "sg:province":"FL",
    "sg:tags":[
        "delicatessen"
    ],
    "wof:name":"Boars Head Deli",
    "wof:placetype":"venue"
},
  "geometry": {"coordinates":[-81.291039,28.447386],"type":"Point"}
}