{
  "type": "Feature",
  "properties": {
    "iso:country":"US",
    "sg:address":"2195 S Combee Rd",
    "sg:city":"Lakeland",
    "sg:classifiers":[
        {
            "category":"Retail",
            "subcategory":"Laundry & Dry Cleaning",
            "type":"Services"
        }
    ],
    "sg:phone":"+1 863 669 9699",
    "sg:postcode":"33801",
    "sg:province":"FL",
    "sg:tags":[
        "laundries-self",
        "operated",
        "washer",
        "dryer",
        "coin"
    ],
    "sg:website":"http://www.billchangers.com",
    "wof:name":"Suncoast Changer Service",
    "wof:placetype":"venue"
},
  "geometry": {"coordinates":[-81.90782799999999,28.01696],"type":"Point"}
}