{
  "type": "Feature",
  "properties": {
    "addr:full":"315 E Bay St Jacksonville FL 32202",
    "addr:housenumber":"315",
    "addr:postcode":"32202",
    "addr:street":"E Bay St",
    "iso:country":"US",
    "sg:address":"315 E Bay St",
    "sg:city":"Jacksonville",
    "sg:classifiers":[
        {
            "category":"Bars & Pubs",
            "type":"Food & Drink"
        }
    ],
    "sg:phone":"+1 904 633 9001",
    "sg:postcode":"32202",
    "sg:province":"FL",
    "sg:tags":[
        "lounge",
        "cocktail"
    ],
    "wof:name":"Orchid Ultra Lounge",
    "wof:placetype":"venue"
},
  "geometry": {"coordinates":[-81.65301599999999,30.325236],"type":"Point"}
}