{
  "type": "Feature",
  "properties": {
    "iso:country":"US",
    "sg:address":"980 NW 6th Ave",
    "sg:city":"Boca Raton",
    "sg:classifiers":[
        {
            "category":"Real Estate",
            "subcategory":"Architect",
            "type":"Services"
        }
    ],
    "sg:phone":"+1 561 395 8130",
    "sg:postcode":"33432",
    "sg:province":"FL",
    "sg:tags":[
        "architectural"
    ],
    "wof:name":"J Patrick Lynch Architect",
    "wof:placetype":"venue"
},
  "geometry": {"coordinates":[-80.097267,26.359215],"type":"Point"}
}