{
  "type": "Feature",
  "properties": {
    "iso:country":"US",
    "sg:address":"749 Lake Harney Woods Blvd",
    "sg:city":"Mims",
    "sg:classifiers":[
        {
            "category":"Building & Trades",
            "subcategory":"Electrical",
            "type":"Services"
        }
    ],
    "sg:phone":"+1 407 349 0034",
    "sg:postcode":"32754",
    "sg:province":"FL",
    "sg:tags":[
        "electric",
        "contractor"
    ],
    "wof:name":"Frogger Electric",
    "wof:placetype":"venue"
},
  "geometry": {"coordinates":[-81.03088099999999,28.733905],"type":"Point"}
}