{
  "type": "Feature",
  "properties": {
    "iso:country":"US",
    "sg:address":"144 Lake Francis Rd",
    "sg:city":"Lake Placid",
    "sg:classifiers":[
        {
            "category":"Building & Trades",
            "subcategory":"Landscaping Services",
            "type":"Services"
        }
    ],
    "sg:phone":"+1 863 699 6790",
    "sg:postcode":"33852",
    "sg:province":"FL",
    "wof:name":"Kevin E Boles",
    "wof:placetype":"venue"
},
  "geometry": {"coordinates":[-81.392882,27.35474],"type":"Point"}
}