{
  "type": "Feature",
  "properties": {
    "addr:full":"1600 N Atlantic Ave Cocoa Beach FL 32931",
    "addr:housenumber":"1600",
    "addr:postcode":"32931",
    "addr:street":"N Atlantic Ave",
    "iso:country":"US",
    "sg:address":"1600 N Atlantic Ave",
    "sg:city":"Cocoa Beach",
    "sg:classifiers":[
        {
            "category":"Social Services",
            "subcategory":"Child Care",
            "type":"Services"
        }
    ],
    "sg:phone":"+1 321 784 1237",
    "sg:postcode":"32931",
    "sg:province":"FL",
    "wof:name":"Penpals Daycare",
    "wof:placetype":"venue"
},
  "geometry": {"coordinates":[-80.610083,28.340501],"type":"Point"}
}