{
  "type": "Feature",
  "properties": {
    "addr:full":"10980 Vanderbilt Dr Naples FL 34108",
    "addr:housenumber":"10980",
    "addr:postcode":"34108",
    "addr:street":"Vanderbilt Dr",
    "iso:country":"US",
    "sg:address":"10980 Vanderbilt Dr",
    "sg:city":"Naples",
    "sg:classifiers":[
        {
            "category":"Banks & Credit Unions",
            "subcategory":"Financial Services",
            "type":"Services"
        }
    ],
    "sg:phone":"+1 239 596 4774",
    "sg:postcode":"34108",
    "sg:province":"FL",
    "sg:tags":[
        "company",
        "holding"
    ],
    "wof:name":"Naples Bay Holdings Inc",
    "wof:placetype":"venue"
},
  "geometry": {"coordinates":[-81.817643,26.271411],"type":"Point"}
}