{
  "type": "Feature",
  "properties": {
    "addr:full":"1307 Keturah St Niceville FL 32578",
    "addr:housenumber":"1307",
    "addr:postcode":"32578",
    "addr:street":"Keturah St",
    "iso:country":"US",
    "sg:address":"1307 Keturah St",
    "sg:city":"Niceville",
    "sg:classifiers":[
        {
            "category":"Building & Trades",
            "subcategory":"Plumbing",
            "type":"Services"
        }
    ],
    "sg:phone":"+1 850 279 6894",
    "sg:postcode":"32578",
    "sg:province":"FL",
    "sg:tags":[
        "plumber"
    ],
    "wof:name":"Masters Plumbing Company Inc",
    "wof:placetype":"venue"
},
  "geometry": {"coordinates":[-86.467371,30.511439],"type":"Point"}
}