{
  "type": "Feature",
  "properties": {
    "addr:full":"2901 Garden St Titusville FL 32796",
    "addr:housenumber":"2901",
    "addr:postcode":"32796",
    "addr:street":"Garden St",
    "iso:country":"US",
    "sg:address":"2901 Garden St",
    "sg:city":"Titusville",
    "sg:classifiers":[
        {
            "category":"Autos & Motor Vehicles",
            "subcategory":"Auto Supplies",
            "type":"Retail Goods"
        }
    ],
    "sg:phone":"+1 321 264 1410",
    "sg:postcode":"32796",
    "sg:province":"FL",
    "sg:tags":[
        "automobile",
        "parts"
    ],
    "sg:website":"www.advancedautoparts.com",
    "wof:name":"Discount Auto Parts 148",
    "wof:placetype":"venue"
},
  "geometry": {"coordinates":[-80.840329,28.616296],"type":"Point"}
}