{
  "type": "Feature",
  "properties": {
    "addr:full":"5011 Old Howell Branch Rd Winter Park FL 32792",
    "addr:housenumber":"5011",
    "addr:postcode":"32792",
    "addr:street":"Old Howell Branch Rd",
    "iso:country":"US",
    "sg:address":"5011 Old Howell Branch Rd",
    "sg:city":"Winter Park",
    "sg:classifiers":[
        {
            "category":"Retail",
            "subcategory":"Laundry & Dry Cleaning",
            "type":"Services"
        }
    ],
    "sg:phone":"+1 407 681 4343",
    "sg:postcode":"32792",
    "sg:province":"FL",
    "wof:name":"Barry's Cleaners",
    "wof:placetype":"venue"
},
  "geometry": {"coordinates":[-81.282501,28.6113],"type":"Point"}
}