{
  "type": "Feature",
  "properties": {
    "addr:full":"1321 NE 12th Ave Fort Lauderdale FL 33304",
    "addr:housenumber":"1321",
    "addr:postcode":"33304",
    "addr:street":"Ne 12Th Ave",
    "iso:country":"US",
    "sg:address":"1321 NE 12th Ave",
    "sg:city":"Fort Lauderdale",
    "sg:classifiers":[
        {
            "category":"Manufacturing",
            "subcategory":"Metals",
            "type":"Manufacturing & Wholesale Goods"
        }
    ],
    "sg:phone":"+1 954 763 3632",
    "sg:postcode":"33304",
    "sg:province":"FL",
    "sg:tags":[
        "plumbing",
        "sanitary",
        "ware",
        "mfg"
    ],
    "wof:name":"Pipco",
    "wof:placetype":"venue"
},
  "geometry": {"coordinates":[-80.131795,26.143891],"type":"Point"}
}