{
  "type": "Feature",
  "properties": {
    "addr:full":"14150 64th Dr N West Palm Beach FL 33418",
    "addr:housenumber":"14150",
    "addr:postcode":"33418",
    "addr:street":"64Th Dr N",
    "iso:country":"US",
    "sg:address":"14150 64th Dr N",
    "sg:city":"West Palm Beach",
    "sg:classifiers":[
        {
            "category":"Retail",
            "subcategory":"Laundry & Dry Cleaning",
            "type":"Services"
        }
    ],
    "sg:phone":"+1 561 625 3533",
    "sg:postcode":"33418",
    "sg:province":"FL",
    "sg:tags":[
        "cleaners",
        "rug",
        "carpet"
    ],
    "wof:name":"A Better Cleaning Svc",
    "wof:placetype":"venue"
},
  "geometry": {"coordinates":[-80.135475,26.884628],"type":"Point"}
}