{
  "type": "Feature",
  "properties": {
    "addr:full":"2315 Lee Rd Orlando FL 32810",
    "addr:housenumber":"2315",
    "addr:postcode":"32810",
    "addr:street":"Lee Rd",
    "iso:country":"US",
    "sg:address":"2315 Lee Rd",
    "sg:city":"Orlando",
    "sg:classifiers":[
        {
            "category":"Health Services",
            "subcategory":"Nursing And Care Facility",
            "type":"Services"
        },
        {
            "category":"Health Services",
            "subcategory":"Health Practitioner",
            "type":"Services"
        },
        {
            "category":"Social Services",
            "subcategory":"Adult Care",
            "type":"Services"
        }
    ],
    "sg:phone":"+1 407 895 8188",
    "sg:postcode":"32810",
    "sg:province":"FL",
    "sg:tags":[
        "nurses-home",
        "therapist",
        "home",
        "nurse",
        "occupational",
        "physical"
    ],
    "sg:website":"http://www.realpagessites.com/harbourprivatedutynursing",
    "wof:name":"Harbour Private Duty Nursing LLC",
    "wof:placetype":"venue"
},
  "geometry": {"coordinates":[-81.40788999999999,28.602855],"type":"Point"}
}