{
  "type": "Feature",
  "properties": {
    "iso:country":"US",
    "sg:address":"5711 SW 199th Ave",
    "sg:city":"Fort Lauderdale",
    "sg:classifiers":[
        {
            "category":"Professional",
            "subcategory":"Computer Services",
            "type":"Services"
        }
    ],
    "sg:phone":"+1 954 434 3412",
    "sg:postcode":"33332",
    "sg:province":"FL",
    "sg:tags":[
        "related"
    ],
    "wof:name":"Advanced Ntwrk Consulting Svcs",
    "wof:placetype":"venue"
},
  "geometry": {"coordinates":[-80.414917,26.046808],"type":"Point"}
}