{
  "type": "Feature",
  "properties": {
    "addr:full":"9325 Abbott Ave Miami Beach FL 33154",
    "addr:housenumber":"9325",
    "addr:postcode":"33154",
    "addr:street":"Abbott Ave",
    "iso:country":"US",
    "sg:address":"9325 Abbott Ave",
    "sg:city":"Miami Beach",
    "sg:classifiers":[
        {
            "category":"Professional",
            "type":"Services"
        },
        {
            "category":"Shopping",
            "subcategory":"Gifts & Souvenirs",
            "type":"Retail Goods"
        }
    ],
    "sg:phone":"+1 305 864 5530",
    "sg:postcode":"33154",
    "sg:province":"FL",
    "sg:tags":[
        "establishment"
    ],
    "wof:name":"Extex Corp",
    "wof:placetype":"venue"
},
  "geometry": {"coordinates":[-80.124066,25.882951],"type":"Point"}
}