{
  "type": "Feature",
  "properties": {
    "iso:country":"US",
    "sg:address":"4901 Sheridan St",
    "sg:city":"Hollywood",
    "sg:classifiers":[
        {
            "category":"Wholesale",
            "subcategory":"Office Equipment",
            "type":"Manufacturing & Wholesale Goods"
        },
        {
            "category":"Shopping",
            "subcategory":"Stationery & Office Supplies",
            "type":"Retail Goods"
        },
        {
            "category":"Shopping",
            "subcategory":"Computers & Home Electronics",
            "type":"Retail Goods"
        },
        {
            "category":"Professional",
            "subcategory":"Printing & Photocopies",
            "type":"Services"
        },
        {
            "category":"Wholesale",
            "subcategory":"Computers",
            "type":"Manufacturing & Wholesale Goods"
        }
    ],
    "sg:phone":"+1 954 985 5699",
    "sg:postcode":"33021",
    "sg:province":"FL",
    "sg:tags":[
        "register",
        "autographic",
        "duplicating",
        "copying",
        "typewriter",
        "furniture"
    ],
    "sg:website":"http://www.officedepot.com",
    "wof:name":"Office Depot",
    "wof:placetype":"venue"
},
  "geometry": {"coordinates":[-80.19323199999999,26.032715],"type":"Point"}
}