{
  "type": "Feature",
  "properties": {
    "iso:country":"US",
    "sg:address":"721 E Sugarland Hwy",
    "sg:city":"Clewiston",
    "sg:classifiers":[
        {
            "category":"Food & Beverages",
            "subcategory":"Liquor & Beverages",
            "type":"Retail Goods"
        }
    ],
    "sg:phone":"+1 863 983 8989",
    "sg:postcode":"33440",
    "sg:province":"FL",
    "wof:name":"Castaway's Lounge",
    "wof:placetype":"venue"
},
  "geometry": {"coordinates":[-80.923203,26.754384],"type":"Point"}
}