{
  "type": "Feature",
  "properties": {
    "addr:full":"24058 Heritage Pl Port Charlotte FL 33980",
    "addr:housenumber":"24058",
    "addr:postcode":"33980",
    "addr:street":"Heritage Pl",
    "iso:country":"US",
    "sg:address":"24058 Heritage Pl",
    "sg:city":"Port Charlotte",
    "sg:classifiers":[
        {
            "category":"Organizations",
            "subcategory":"Religious Organization",
            "type":"Services"
        }
    ],
    "sg:phone":"+1 941 625 7412",
    "sg:postcode":"33980",
    "sg:province":"FL",
    "sg:tags":[
        "church"
    ],
    "sg:website":"www.tricitybaptistchurch.org",
    "wof:name":"Tri-City Baptist Church",
    "wof:placetype":"venue"
},
  "geometry": {"coordinates":[-82.05667200000001,26.969568],"type":"Point"}
}