{
  "type": "Feature",
  "properties": {
    "addr:full":"13318 Sunkiss Loop Windermere FL 34786",
    "addr:housenumber":"13318",
    "addr:postcode":"34786",
    "addr:street":"Sunkiss Loop",
    "iso:country":"US",
    "sg:address":"13318 Sunkiss Loop",
    "sg:city":"Windermere",
    "sg:classifiers":[
        {
            "category":"Restaurant",
            "type":"Food & Drink"
        }
    ],
    "sg:phone":"+1 407 920 3243",
    "sg:postcode":"34786",
    "sg:province":"FL",
    "wof:name":"Melt Inc",
    "wof:placetype":"venue"
},
  "geometry": {"coordinates":[-81.583803,28.489553],"type":"Point"}
}