{
  "type": "Feature",
  "properties": {
    "iso:country":"US",
    "sg:address":"90 N Congress Ave",
    "sg:city":"Delray Beach",
    "sg:classifiers":[
        {
            "category":"Retail",
            "subcategory":"Auto Repair",
            "type":"Services"
        }
    ],
    "sg:phone":"+1 561 279 4123",
    "sg:postcode":"33445",
    "sg:province":"FL",
    "sg:tags":[
        "wrecker"
    ],
    "wof:name":"Professional Towing",
    "wof:placetype":"venue"
},
  "geometry": {"coordinates":[-80.09374099999999,26.461888],"type":"Point"}
}