{
  "type": "Feature",
  "properties": {
    "iso:country":"US",
    "sg:address":"415 W Cape Coral Pkwy",
    "sg:city":"Cape Coral",
    "sg:classifiers":[
        {
            "category":"Health Services",
            "subcategory":"Doctor",
            "type":"Services"
        }
    ],
    "sg:phone":"+1 239 540 3881",
    "sg:postcode":"33914",
    "sg:province":"FL",
    "sg:tags":[
        "dentist"
    ],
    "wof:name":"Dental Associates-Cape Coral",
    "wof:placetype":"venue"
},
  "geometry": {"coordinates":[-81.985567,26.562778],"type":"Point"}
}