{
  "type": "Feature",
  "properties": {
    "iso:country":"US",
    "sg:address":"56 NE 1st St",
    "sg:city":"Miami",
    "sg:classifiers":[
        {
            "category":"Food & Beverages",
            "subcategory":"Specialty",
            "type":"Retail Goods"
        }
    ],
    "sg:phone":"+1 305 358 6743",
    "sg:postcode":"33132",
    "sg:province":"FL",
    "sg:tags":[
        "herb",
        "health",
        "diet"
    ],
    "sg:website":"http://www.gnc.com",
    "wof:name":"GNC",
    "wof:placetype":"venue"
},
  "geometry": {"coordinates":[-80.192829,25.775122],"type":"Point"}
}