{
  "type": "Feature",
  "properties": {
    "iso:country":"US",
    "sg:address":"4609 Vineland Rd",
    "sg:city":"Orlando",
    "sg:classifiers":[
        {
            "category":"Organizations",
            "subcategory":"Religious Organization",
            "type":"Services"
        }
    ],
    "sg:phone":"+1 407 581 4230",
    "sg:postcode":"32811",
    "sg:province":"FL",
    "wof:name":"Sola Scriptura",
    "wof:placetype":"venue"
},
  "geometry": {"coordinates":[-81.43508300000001,28.495413],"type":"Point"}
}