{
  "type": "Feature",
  "properties": {
    "iso:country":"US",
    "sg:address":"18931 Titus Rd",
    "sg:city":"Hudson",
    "sg:classifiers":[
        {
            "category":"Wholesale",
            "subcategory":"Medical Equipment & Supplies",
            "type":"Manufacturing & Wholesale Goods"
        }
    ],
    "sg:phone":"+1 727 868 3988",
    "sg:postcode":"34667",
    "sg:province":"FL",
    "sg:tags":[
        "optical"
    ],
    "wof:name":"Horizon Optical Corp",
    "wof:placetype":"venue"
},
  "geometry": {"coordinates":[-82.61020600000001,28.432309],"type":"Point"}
}