{
  "type": "Feature",
  "properties": {
    "iso:country":"US",
    "sg:address":"502 E Burgess Rd",
    "sg:city":"Pensacola",
    "sg:classifiers":[
        {
            "category":"Food & Beverages",
            "subcategory":"Groceries & Convenience Stores",
            "type":"Retail Goods"
        }
    ],
    "sg:phone":"+1 850 478 4680",
    "sg:postcode":"32504",
    "sg:province":"FL",
    "sg:website":"www.circlek.com",
    "wof:name":"Circle K",
    "wof:placetype":"venue"
},
  "geometry": {"coordinates":[-87.231971,30.494347],"type":"Point"}
}