{
  "type": "Feature",
  "properties": {
    "iso:country":"US",
    "sg:address":"17543 N Dale Mabry Hwy",
    "sg:city":"Tampa",
    "sg:classifiers":[
        {
            "category":"Professional",
            "subcategory":"Computer Services",
            "type":"Services"
        }
    ],
    "sg:phone":"+1 844 874 8394",
    "sg:postcode":"33548",
    "sg:province":"FL",
    "sg:tags":[
        "pay-per-click-software",
        "predictive-analytics",
        "online-revenue-attribution"
    ],
    "sg:website":"http://www.SiteWit.com",
    "wof:name":"SiteWit",
    "wof:placetype":"venue"
},
  "geometry": {"coordinates":[-82.50235600000001,28.119562],"type":"Point"}
}