{
  "type": "Feature",
  "properties": {
    "addr:full":"21251 Stoneybrook Golf Dr Estero FL 33928",
    "addr:housenumber":"21251",
    "addr:postcode":"33928",
    "addr:street":"Stoneybrook Golf Dr",
    "iso:country":"US",
    "sg:address":"21251 Stoneybrook Golf Dr",
    "sg:city":"Estero",
    "sg:classifiers":[
        {
            "category":"Sports & Exercise",
            "subcategory":"Golf",
            "type":"Entertainment"
        },
        {
            "category":"Professional",
            "subcategory":"Management & Consulting",
            "type":"Services"
        }
    ],
    "sg:phone":"+1 239 948 3933",
    "sg:postcode":"33928",
    "sg:province":"FL",
    "sg:tags":[
        "course",
        "goo",
        "sporting",
        "public"
    ],
    "wof:name":"Stoneybrook Golf Club",
    "wof:placetype":"venue"
},
  "geometry": {"coordinates":[-81.762739,26.439562],"type":"Point"}
}