{
  "type": "Feature",
  "properties": {
    "iso:country":"US",
    "sg:address":"8809 W Waters Ave",
    "sg:city":"Tampa",
    "sg:classifiers":[
        {
            "category":"Banks & Credit Unions",
            "subcategory":"Bank",
            "type":"Services"
        }
    ],
    "sg:phone":"+1 813 884 8625",
    "sg:postcode":"33615",
    "sg:province":"FL",
    "wof:name":"Fifth Third Bank",
    "wof:placetype":"venue"
},
  "geometry": {"coordinates":[-82.585463,28.026227],"type":"Point"}
}