{
  "type": "Feature",
  "properties": {
    "addr:full":"7305 Dickens Ave Miami Beach FL 33141",
    "addr:housenumber":"7305",
    "addr:postcode":"33141",
    "addr:street":"Dickens Ave",
    "iso:country":"US",
    "sg:address":"7305 Dickens Ave",
    "sg:city":"Miami Beach",
    "sg:classifiers":[
        {
            "category":"Professional",
            "type":"Services"
        }
    ],
    "sg:phone":"+1 305 868 0045",
    "sg:postcode":"33141",
    "sg:province":"FL",
    "wof:name":"Castaneda Gesusmaria",
    "wof:placetype":"venue"
},
  "geometry": {"coordinates":[-80.125241,25.859363],"type":"Point"}
}