{
  "type": "Feature",
  "properties": {
    "iso:country":"US",
    "sg:address":"5341 Otter Ln",
    "sg:city":"Middleburg",
    "sg:classifiers":[
        {
            "category":"Manufacturing",
            "subcategory":"Printing",
            "type":"Manufacturing & Wholesale Goods"
        }
    ],
    "sg:phone":"+1 904 291 7938",
    "sg:postcode":"32068",
    "sg:province":"FL",
    "sg:tags":[
        "book"
    ],
    "wof:name":"Lovers Knot Magazine The",
    "wof:placetype":"venue"
},
  "geometry": {"coordinates":[-81.952412,30.065187],"type":"Point"}
}