{
  "type": "Feature",
  "properties": {
    "addr:full":"10404 N Nebraska Ave Tampa FL 33612",
    "addr:housenumber":"10404",
    "addr:postcode":"33612",
    "addr:street":"N Nebraska Ave",
    "iso:country":"US",
    "sg:address":"10404 N Nebraska Ave",
    "sg:city":"Tampa",
    "sg:classifiers":[
        {
            "category":"Real Estate",
            "subcategory":"Developer",
            "type":"Services"
        }
    ],
    "sg:phone":"+1 813 971 3000",
    "sg:postcode":"33612",
    "sg:province":"FL",
    "wof:name":"Palm Harbor Homes",
    "wof:placetype":"venue"
},
  "geometry": {"coordinates":[-82.451266,28.044361],"type":"Point"}
}