{
  "type": "Feature",
  "properties": {
    "addr:full":"130 Hollywood Blvd SW Fort Walton Beach FL 32548",
    "addr:housenumber":"130",
    "addr:postcode":"32548",
    "addr:street":"Hollywood Blvd Sw",
    "iso:country":"US",
    "sg:address":"130 Hollywood Blvd SW",
    "sg:city":"Fort Walton Beach",
    "sg:classifiers":[
        {
            "category":"Autos & Motor Vehicles",
            "subcategory":"Automobile Sales",
            "type":"Retail Goods"
        }
    ],
    "sg:phone":"+1 850 244 0705",
    "sg:postcode":"32548",
    "sg:province":"FL",
    "sg:tags":[
        "used"
    ],
    "wof:name":"Auto Advantage",
    "wof:placetype":"venue"
},
  "geometry": {"coordinates":[-86.627195,30.412744],"type":"Point"}
}