{
  "type": "Feature",
  "properties": {
    "iso:country":"US",
    "sg:address":"4710 28th St N",
    "sg:city":"St Petersburg",
    "sg:classifiers":[
        {
            "category":"Manufacturing",
            "subcategory":"Printing",
            "type":"Manufacturing & Wholesale Goods"
        }
    ],
    "sg:phone":"+1 727 825 0223",
    "sg:postcode":"33714",
    "sg:province":"FL",
    "sg:tags":[
        "publisher"
    ],
    "wof:name":"American Book Sales Inc",
    "wof:placetype":"venue"
},
  "geometry": {"coordinates":[-82.67143,27.815667],"type":"Point"}
}