{
  "type": "Feature",
  "properties": {
    "iso:country":"US",
    "sg:address":"1540 12th St E",
    "sg:city":"Palmetto",
    "sg:classifiers":[
        {
            "category":"Manufacturing",
            "subcategory":"Food",
            "type":"Manufacturing & Wholesale Goods"
        }
    ],
    "sg:phone":"+1 941 721 1725",
    "sg:postcode":"34221",
    "sg:province":"FL",
    "sg:tags":[
        "product",
        "mfg"
    ],
    "wof:name":"Sunstar Foods",
    "wof:placetype":"venue"
},
  "geometry": {"coordinates":[-82.55011399999999,27.523877],"type":"Point"}
}