{
  "type": "Feature",
  "properties": {
    "addr:full":"150 Woodridge Cir Oldsmar FL 34677",
    "addr:housenumber":"150",
    "addr:postcode":"34677",
    "addr:street":"Woodridge Cir",
    "iso:country":"US",
    "sg:address":"150 Woodridge Cir",
    "sg:city":"Oldsmar",
    "sg:classifiers":[
        {
            "category":"Wholesale",
            "subcategory":"Office Equipment",
            "type":"Manufacturing & Wholesale Goods"
        },
        {
            "category":"Manufacturing",
            "subcategory":"Tools & Machinery",
            "type":"Manufacturing & Wholesale Goods"
        }
    ],
    "sg:phone":"+1 727 781 2626",
    "sg:postcode":"34677",
    "sg:province":"FL",
    "sg:tags":[
        "packaging",
        "machinery-wholesale",
        "manufacturer"
    ],
    "wof:name":"Omnipack",
    "wof:placetype":"venue"
},
  "geometry": {"coordinates":[-82.690933,28.05106],"type":"Point"}
}