{
  "type": "Feature",
  "properties": {
    "addr:full":"89 Beach St Ponce Inlet FL 32127",
    "addr:housenumber":"89",
    "addr:postcode":"32127",
    "addr:street":"Beach St",
    "iso:country":"US",
    "sg:address":"89 Beach St",
    "sg:city":"Ponce Inlet",
    "sg:classifiers":[
        {
            "category":"Recreation",
            "subcategory":"Marina",
            "type":"Entertainment"
        }
    ],
    "sg:phone":"+1 386 761 1614",
    "sg:postcode":"32127",
    "sg:province":"FL",
    "sg:tags":[
        "repairing",
        "boat"
    ],
    "wof:name":"Andy's Certified Marine Svc",
    "wof:placetype":"venue"
},
  "geometry": {"coordinates":[-80.930269,29.083389],"type":"Point"}
}