{
  "type": "Feature",
  "properties": {
    "addr:full":"4121 Chardonnay Pl SW Rockledge FL 32968",
    "addr:housenumber":"4121",
    "addr:postcode":"32968",
    "addr:street":"Chardonnay Pl Sw",
    "iso:country":"US",
    "sg:address":"4121 Chardonnay Pl SW",
    "sg:city":"Rockledge",
    "sg:classifiers":[
        {
            "category":"Retail",
            "subcategory":"Auto Rental",
            "type":"Services"
        }
    ],
    "sg:phone":"+1 321 638 2212",
    "sg:postcode":"32968",
    "sg:province":"FL",
    "sg:tags":[
        "renting",
        "automobile"
    ],
    "wof:name":"Associated Rent A Car",
    "wof:placetype":"venue"
},
  "geometry": {"coordinates":[-80.427678,27.600639],"type":"Point"}
}