{
  "type": "Feature",
  "properties": {
    "iso:country":"US",
    "sg:address":"491 N State Road 434",
    "sg:city":"Altamonte Springs",
    "sg:classifiers":[
        {
            "category":"Building & Trades",
            "subcategory":"Pest Control",
            "type":"Services"
        }
    ],
    "sg:phone":"+1 407 327 7233",
    "sg:postcode":"32714",
    "sg:province":"FL",
    "wof:name":"Commercial Termite Services",
    "wof:placetype":"venue"
},
  "geometry": {"coordinates":[-81.418843,28.669006],"type":"Point"}
}