{
  "type": "Feature",
  "properties": {
    "iso:country":"US",
    "sg:address":"5833 S Ridgewood Ave",
    "sg:city":"Daytona Beach",
    "sg:classifiers":[
        {
            "category":"Retail",
            "subcategory":"Veterinary Services",
            "type":"Services"
        }
    ],
    "sg:phone":"+1 386 788 9300",
    "sg:postcode":"32127",
    "sg:province":"FL",
    "sg:tags":[
        "veterinarian"
    ],
    "wof:name":"Bayshore Animal Hospital",
    "wof:placetype":"venue"
},
  "geometry": {"coordinates":[-80.973184,29.109841],"type":"Point"}
}