{
  "type": "Feature",
  "properties": {
    "addr:full":"112 Seminole Ave Jupiter FL 33458",
    "addr:housenumber":"112",
    "addr:postcode":"33458",
    "addr:street":"Seminole Ave",
    "iso:country":"US",
    "sg:address":"112 Seminole Ave",
    "sg:city":"Jupiter",
    "sg:classifiers":[
        {
            "category":"Freight",
            "type":"Transportation"
        }
    ],
    "sg:phone":"+1 561 746 9494",
    "sg:postcode":"33458",
    "sg:province":"FL",
    "sg:tags":[
        "mover"
    ],
    "wof:name":"Coast To Coast Express Inc",
    "wof:placetype":"venue"
},
  "geometry": {"coordinates":[-80.094379,26.942377],"type":"Point"}
}