{
  "type": "Feature",
  "properties": {
    "iso:country":"US",
    "sg:address":"3515 Old Dixie Hwy",
    "sg:city":"Stuart",
    "sg:classifiers":[
        {
            "category":"Shopping",
            "subcategory":"Hobbies, Toys, & Games",
            "type":"Retail Goods"
        }
    ],
    "sg:phone":"+1 772 286 3939",
    "sg:postcode":"34997",
    "sg:province":"FL",
    "wof:name":"Kathleens Crafts/",
    "wof:placetype":"venue"
},
  "geometry": {"coordinates":[-80.21562,27.161883],"type":"Point"}
}