{
  "type": "Feature",
  "properties": {
    "addr:full":"215 NW 60th Ave Miami FL 33126",
    "addr:housenumber":"215",
    "addr:postcode":"33126",
    "addr:street":"Nw 60Th Ave",
    "iso:country":"US",
    "sg:address":"215 NW 60th Ave",
    "sg:city":"Miami",
    "sg:classifiers":[
        {
            "category":"Professional",
            "subcategory":"Management & Consulting",
            "type":"Services"
        }
    ],
    "sg:phone":"+1 305 269 6779",
    "sg:postcode":"33126",
    "sg:province":"FL",
    "wof:name":"Budget Management & Home Imprv",
    "wof:placetype":"venue"
},
  "geometry": {"coordinates":[-80.293519,25.774003],"type":"Point"}
}