{
  "type": "Feature",
  "properties": {
    "addr:full":"10941 SE US Hwy 441 Belleview FL 34420",
    "addr:housenumber":"10941",
    "addr:postcode":"34420",
    "addr:street":"Se Us Hwy 441",
    "iso:country":"US",
    "sg:address":"10941 SE US Hwy 441",
    "sg:city":"Belleview",
    "sg:classifiers":[
        {
            "category":"Banks & Credit Unions",
            "subcategory":"Bank",
            "type":"Services"
        }
    ],
    "sg:phone":"+1 352 347 7806",
    "sg:postcode":"34420",
    "sg:province":"FL",
    "sg:tags":[
        "loan",
        "real estate"
    ],
    "wof:name":"Mortgage Advocates",
    "wof:placetype":"venue"
},
  "geometry": {"coordinates":[-82.066935,29.063283],"type":"Point"}
}