{
  "type": "Feature",
  "properties": {
    "addr:full":"3811 Jefferson Rd S Tallahassee FL 32317",
    "addr:housenumber":"3811",
    "addr:postcode":"32317",
    "addr:street":"Jefferson Rd",
    "iso:country":"US",
    "sg:address":"3811 Jefferson Rd S",
    "sg:city":"Tallahassee",
    "sg:classifiers":[
        {
            "category":"Building & Trades",
            "subcategory":"Construction",
            "type":"Services"
        }
    ],
    "sg:phone":"+1 850 386 3146",
    "sg:postcode":"32317",
    "sg:province":"FL",
    "sg:tags":[
        "house"
    ],
    "wof:name":"Darrell Fain Construction LLC",
    "wof:placetype":"venue"
},
  "geometry": {"coordinates":[-84.06751199999999,30.520431],"type":"Point"}
}