{
  "type": "Feature",
  "properties": {
    "addr:full":"2841 Pga Blvd Palm Beach Gdns FL 33410",
    "addr:housenumber":"2841",
    "addr:postcode":"33410",
    "addr:street":"Pga Blvd Palm Beach Gdns",
    "iso:country":"US",
    "sg:address":"2841 Pga Blvd",
    "sg:city":"Palm Beach Gdns",
    "sg:classifiers":[
        {
            "category":"Home & Garden",
            "subcategory":"Furniture",
            "type":"Retail Goods"
        }
    ],
    "sg:phone":"+1 561 630 4040",
    "sg:postcode":"33410",
    "sg:province":"FL",
    "wof:name":"Bombay Co Kids",
    "wof:placetype":"venue"
},
  "geometry": {"coordinates":[-80.075782,26.844813],"type":"Point"}
}