{
  "type": "Feature",
  "properties": {
    "iso:country":"US",
    "sg:address":"22039 Tarragona Way",
    "sg:city":"Astor",
    "sg:classifiers":[
        {
            "category":"Real Estate",
            "subcategory":"Real Estate Agent",
            "type":"Services"
        }
    ],
    "sg:phone":"+1 352 759 2717",
    "sg:postcode":"32102",
    "sg:province":"FL",
    "wof:name":"Astor Realty",
    "wof:placetype":"venue"
},
  "geometry": {"coordinates":[-81.57710400000001,29.201943],"type":"Point"}
}