{
  "type": "Feature",
  "properties": {
    "iso:country":"US",
    "sg:address":"4377 Commercial Way",
    "sg:city":"Spring Hill",
    "sg:classifiers":[
        {
            "category":"Shopping",
            "subcategory":"Catalog Store",
            "type":"Retail Goods"
        }
    ],
    "sg:phone":"+1 352 596 4590",
    "sg:postcode":"34606",
    "sg:province":"FL",
    "sg:tags":[
        "mail",
        "house"
    ],
    "wof:name":"World of Collectibles",
    "wof:placetype":"venue"
},
  "geometry": {"coordinates":[-82.598439,28.492316],"type":"Point"}
}