{
  "type": "Feature",
  "properties": {
    "iso:country":"US",
    "sg:address":"2039 Anastasia Dr",
    "sg:city":"South Daytona",
    "sg:classifiers":[
        {
            "category":"Personal",
            "subcategory":"Beauty Salon",
            "type":"Services"
        }
    ],
    "sg:phone":"+1 386 788 6194",
    "sg:postcode":"32119",
    "sg:province":"FL",
    "sg:tags":[
        "manicuring"
    ],
    "wof:name":"Charmed",
    "wof:placetype":"venue"
},
  "geometry": {"coordinates":[-81.00704899999999,29.171968],"type":"Point"}
}