{
  "type": "Feature",
  "properties": {
    "iso:country":"US",
    "sg:address":"1612 S Harbor City Blvd",
    "sg:city":"Melbourne",
    "sg:classifiers":[
        {
            "category":"Retail",
            "subcategory":"Car Wash",
            "type":"Services"
        }
    ],
    "sg:phone":"+1 321 723 5008",
    "sg:postcode":"32901",
    "sg:province":"FL",
    "sg:tags":[
        "automobile",
        "detail",
        "clean"
    ],
    "wof:name":"Super Clean Detailing Ctr Inc",
    "wof:placetype":"venue"
},
  "geometry": {"coordinates":[-80.605362,28.082571],"type":"Point"}
}