{
  "type": "Feature",
  "properties": {
    "addr:full":"8861 SW 132nd St Miami FL 33176",
    "addr:housenumber":"8861",
    "addr:postcode":"33176",
    "addr:street":"Sw 132Nd St",
    "iso:country":"US",
    "sg:address":"8861 SW 132nd St",
    "sg:city":"Miami",
    "sg:classifiers":[
        {
            "category":"Manufacturing",
            "subcategory":"Signs",
            "type":"Manufacturing & Wholesale Goods"
        }
    ],
    "sg:phone":"+1 305 256 5877",
    "sg:postcode":"33176",
    "sg:province":"FL",
    "sg:tags":[
        "advertising",
        "specialty"
    ],
    "wof:name":"Future Signs & Printing",
    "wof:placetype":"venue"
},
  "geometry": {"coordinates":[-80.336933,25.64757],"type":"Point"}
}