{
  "type": "Feature",
  "properties": {
    "iso:country":"US",
    "sg:address":"5634 S W 102 Ave",
    "sg:city":"Miami",
    "sg:classifiers":[
        {
            "category":"Shopping",
            "type":"Retail Goods"
        },
        {
            "category":"Organizations",
            "subcategory":"Religious Organization",
            "type":"Services"
        }
    ],
    "sg:phone":"+1 305 270 0053",
    "sg:postcode":"33173",
    "sg:province":"FL",
    "sg:website":"www.botanica7mares.com",
    "wof:name":"Botanica 7 Mares",
    "wof:placetype":"venue"
},
  "geometry": {"coordinates":[-80.358876,25.715005],"type":"Point"}
}