{
  "type": "Feature",
  "properties": {
    "addr:full":"2300 S Orange Ave Orlando FL 32806",
    "addr:housenumber":"2300",
    "addr:postcode":"32806",
    "addr:street":"S Orange Ave",
    "iso:country":"US",
    "sg:address":"2300 S Orange Ave",
    "sg:city":"Orlando",
    "sg:classifiers":[
        {
            "category":"Home & Garden",
            "subcategory":"Furniture",
            "type":"Retail Goods"
        }
    ],
    "sg:phone":"+1 407 316 0101",
    "sg:postcode":"32806",
    "sg:province":"FL",
    "sg:website":"www.officefurnoutlet.com",
    "wof:name":"Office Furniture Outlet",
    "wof:placetype":"venue"
},
  "geometry": {"coordinates":[-81.376362,28.515725],"type":"Point"}
}