{
  "type": "Feature",
  "properties": {
    "iso:country":"US",
    "sg:address":"9956 Hawaiian Ct",
    "sg:city":"Orlando",
    "sg:classifiers":[
        {
            "category":"Travel",
            "subcategory":"Hotels & Motels",
            "type":"Entertainment"
        }
    ],
    "sg:phone":"+1 800 424 6423",
    "sg:postcode":"32819",
    "sg:province":"FL",
    "sg:website":"http://www.clarionhotel.com/hotel-orlando-florida-FL328?promo=yplocal",
    "wof:name":"Clarion Inn & Suites At International Drive Orlando",
    "wof:placetype":"venue"
},
  "geometry": {"coordinates":[-81.461727,28.42314],"type":"Point"}
}