{
  "type": "Feature",
  "properties": {
    "addr:full":"1175 Tumbleweed Run Tallahassee FL 32311",
    "addr:housenumber":"1175",
    "addr:postcode":"32311",
    "addr:street":"Tumbleweed Run",
    "iso:country":"US",
    "sg:address":"1175 Tumbleweed Run",
    "sg:city":"Tallahassee",
    "sg:classifiers":[
        {
            "category":"Personal",
            "subcategory":"Beauty Salon",
            "type":"Services"
        }
    ],
    "sg:phone":"+1 850 671 4872",
    "sg:postcode":"32311",
    "sg:province":"FL",
    "wof:name":"Mary Parker's Studio Salon",
    "wof:placetype":"venue"
},
  "geometry": {"coordinates":[-84.20894199999999,30.431953],"type":"Point"}
}