{
  "type": "Feature",
  "properties": {
    "iso:country":"US",
    "sg:address":"2800 SE Maricamp Rd",
    "sg:city":"Ocala",
    "sg:classifiers":[
        {
            "category":"Education",
            "subcategory":"School",
            "type":"Public Place"
        }
    ],
    "sg:phone":"+1 352 387 2210",
    "sg:postcode":"34471",
    "sg:province":"FL",
    "sg:tags":[
        "retarded",
        "work",
        "adult",
        "for",
        "center"
    ],
    "wof:name":"ARC Marion Inc",
    "wof:placetype":"venue"
},
  "geometry": {"coordinates":[-82.097724,29.166891],"type":"Point"}
}