{
  "type": "Feature",
  "properties": {
    "addr:full":"188 Lawn Ave St Augustine FL 32084",
    "addr:housenumber":"188",
    "addr:postcode":"32084",
    "addr:street":"Lawn Ave St",
    "iso:country":"US",
    "sg:address":"188 Lawn Ave",
    "sg:city":"St Augustine",
    "sg:classifiers":[
        {
            "category":"Recreation",
            "type":"Entertainment"
        }
    ],
    "sg:phone":"+1 904 669 1520",
    "sg:postcode":"32084",
    "sg:province":"FL",
    "sg:tags":[
        "charter",
        "boat"
    ],
    "wof:name":"Emory King Charter Boat",
    "wof:placetype":"venue"
},
  "geometry": {"coordinates":[-81.299964,29.923979],"type":"Point"}
}