{
  "type": "Feature",
  "properties": {
    "addr:full":"2423 S Le Jeune Rd Miami FL 33134",
    "addr:housenumber":"2423",
    "addr:postcode":"33134",
    "addr:street":"S Le Jeune Rd",
    "iso:country":"US",
    "sg:address":"2423 S Le Jeune Rd",
    "sg:city":"Miami",
    "sg:classifiers":[
        {
            "category":"Real Estate",
            "subcategory":"Real Estate Services",
            "type":"Services"
        }
    ],
    "sg:phone":"+1 305 443 7423",
    "sg:postcode":"33134",
    "sg:province":"FL",
    "wof:name":"Keyes Company Realtors",
    "wof:placetype":"venue"
},
  "geometry": {"coordinates":[-80.262604,25.748501],"type":"Point"}
}