{
  "type": "Feature",
  "properties": {
    "iso:country":"US",
    "sg:address":"12720 NW 11th St",
    "sg:city":"Miami",
    "sg:classifiers":[
        {
            "category":"Building & Trades",
            "subcategory":"Plumbing",
            "type":"Services"
        }
    ],
    "sg:phone":"+1 305 444 4777",
    "sg:postcode":"33182",
    "sg:province":"FL",
    "sg:tags":[
        "sprinkler",
        "contractor"
    ],
    "wof:name":"Sapphire Sprinklers Inc",
    "wof:placetype":"venue"
},
  "geometry": {"coordinates":[-80.401596,25.780994],"type":"Point"}
}