{
  "type": "Feature",
  "properties": {
    "addr:full":"1009 Windsong Cir Apopka FL 32703",
    "addr:housenumber":"1009",
    "addr:postcode":"32703",
    "addr:street":"Windsong Cir",
    "iso:country":"US",
    "sg:address":"1009 Windsong Cir",
    "sg:city":"Apopka",
    "sg:classifiers":[
        {
            "category":"Real Estate",
            "subcategory":"Developer",
            "type":"Services"
        }
    ],
    "sg:phone":"+1 321 303 1312",
    "sg:postcode":"32703",
    "sg:province":"FL",
    "sg:tags":[
        "investing"
    ],
    "wof:name":"Joseph Torres",
    "wof:placetype":"venue"
},
  "geometry": {"coordinates":[-81.489419,28.654359],"type":"Point"}
}