{
  "type": "Feature",
  "properties": {
    "iso:country":"US",
    "sg:address":"16061 Pine Ridge Rd",
    "sg:city":"Fort Myers",
    "sg:classifiers":[
        {
            "category":"Manufacturing",
            "subcategory":"Signs",
            "type":"Manufacturing & Wholesale Goods"
        },
        {
            "category":"Manufacturing",
            "subcategory":"Printing",
            "type":"Manufacturing & Wholesale Goods"
        }
    ],
    "sg:phone":"+1 239 466 2616",
    "sg:postcode":"33908",
    "sg:province":"FL",
    "sg:tags":[
        "fleet",
        "graphics",
        "commercial",
        "specialist"
    ],
    "sg:website":"www.nitebright.com",
    "wof:name":"Nite Bright Sign Co Inc",
    "wof:placetype":"venue"
},
  "geometry": {"coordinates":[-81.935394,26.507026],"type":"Point"}
}