{
  "type": "Feature",
  "properties": {
    "addr:full":"7000 Pine Forest Rd Ste B Pensacola FL 32526",
    "addr:housenumber":"7000",
    "addr:postcode":"32526",
    "addr:street":"Pine Forest Rd Ste B",
    "iso:country":"US",
    "sg:address":"7000 Pine Forest Rd Ste B",
    "sg:city":"Pensacola",
    "sg:classifiers":[
        {
            "category":"Banks & Credit Unions",
            "subcategory":"Investment Brokerage",
            "type":"Services"
        }
    ],
    "sg:phone":"+1 850 944 7526",
    "sg:postcode":"32526",
    "sg:province":"FL",
    "sg:tags":[
        "security"
    ],
    "sg:website":"http://www.edwardjones.com",
    "wof:name":"Edward Jones 13928",
    "wof:placetype":"venue"
},
  "geometry": {"coordinates":[-87.306183,30.48992],"type":"Point"}
}