{
  "type": "Feature",
  "properties": {
    "iso:country":"US",
    "sg:address":"5222 Karlsburg Pl",
    "sg:city":"Palm Harbor",
    "sg:classifiers":[
        {
            "category":"Professional",
            "subcategory":"Business Services",
            "type":"Services"
        }
    ],
    "sg:phone":"+1 727 934 0594",
    "sg:postcode":"34685",
    "sg:province":"FL",
    "wof:name":"Richute Enterprises Inc",
    "wof:placetype":"venue"
},
  "geometry": {"coordinates":[-82.712355,28.127474],"type":"Point"}
}