{
  "type": "Feature",
  "properties": {
    "addr:full":"1585 W 33rd St West Palm Beach FL 33404",
    "addr:housenumber":"1585",
    "addr:postcode":"33404",
    "addr:street":"W 33Rd St",
    "iso:country":"US",
    "sg:address":"1585 W 33rd St",
    "sg:city":"West Palm Beach",
    "sg:classifiers":[
        {
            "category":"Building & Trades",
            "subcategory":"Construction",
            "type":"Services"
        }
    ],
    "sg:phone":"+1 561 863 4616",
    "sg:postcode":"33404",
    "sg:province":"FL",
    "sg:tags":[
        "contractor"
    ],
    "wof:name":"Clydes Tile & Marble",
    "wof:placetype":"venue"
},
  "geometry": {"coordinates":[-80.07897199999999,26.78952],"type":"Point"}
}