{
  "type": "Feature",
  "properties": {
    "addr:full":"800 Moss Ave Clearwater FL 33759",
    "addr:housenumber":"800",
    "addr:postcode":"33759",
    "addr:street":"Moss Ave",
    "iso:country":"US",
    "sg:address":"800 Moss Ave",
    "sg:city":"Clearwater",
    "sg:classifiers":[
        {
            "category":"Building & Trades",
            "subcategory":"Construction",
            "type":"Services"
        }
    ],
    "sg:phone":"+1 727 797 4226",
    "sg:postcode":"33759",
    "sg:province":"FL",
    "sg:tags":[
        "house"
    ],
    "wof:name":"Saxony Homes",
    "wof:placetype":"venue"
},
  "geometry": {"coordinates":[-82.71173899999999,27.973917],"type":"Point"}
}