{
  "type": "Feature",
  "properties": {
    "iso:country":"US",
    "sg:address":"519 Key Royale Dr",
    "sg:city":"Bradenton Beach",
    "sg:classifiers":[
        {
            "category":"Professional",
            "subcategory":"Engineering",
            "type":"Services"
        }
    ],
    "sg:phone":"+1 941 778 0033",
    "sg:postcode":"34217",
    "sg:province":"FL",
    "sg:tags":[
        "cir",
        "consulting",
        "prototype",
        "electrical",
        "mfg"
    ],
    "wof:name":"L G K Corp",
    "wof:placetype":"venue"
},
  "geometry": {"coordinates":[-82.71346699999999,27.516348],"type":"Point"}
}