{
  "type": "Feature",
  "properties": {
    "addr:full":"1328 SW 160th Ave Fort Lauderdale FL 33326",
    "addr:housenumber":"1328",
    "addr:postcode":"33326",
    "addr:street":"Sw 160Th Ave",
    "iso:country":"US",
    "sg:address":"1328 SW 160th Ave",
    "sg:city":"Fort Lauderdale",
    "sg:classifiers":[
        {
            "category":"Restaurant",
            "type":"Food & Drink"
        }
    ],
    "sg:menulink":"http://www.allmenus.com/fl/davie/71263-pizza-hut/menu/",
    "sg:phone":"+1 954 389 2222",
    "sg:postcode":"33326",
    "sg:province":"FL",
    "sg:tags":[
        "american",
        "pizza"
    ],
    "wof:name":"Pizza Hut",
    "wof:placetype":"venue"
},
  "geometry": {"coordinates":[-80.36248399999999,26.104116],"type":"Point"}
}