{
  "type": "Feature",
  "properties": {
    "iso:country":"US",
    "sg:address":"837 NE 2nd Ave",
    "sg:city":"Fort Lauderdale",
    "sg:classifiers":[
        {
            "category":"Retail",
            "subcategory":"Auto Repair",
            "type":"Services"
        },
        {
            "category":"Autos & Motor Vehicles",
            "subcategory":"Auto Supplies",
            "type":"Retail Goods"
        }
    ],
    "sg:phone":"+1 954 524 1411",
    "sg:postcode":"33304",
    "sg:province":"FL",
    "sg:tags":[
        "installs",
        "automotive",
        "air",
        "equipment",
        "radio",
        "conditioning",
        "automobile"
    ],
    "wof:name":"United Auto Radio & AC Inc",
    "wof:placetype":"venue"
},
  "geometry": {"coordinates":[-80.14231700000001,26.134496],"type":"Point"}
}