{
  "type": "Feature",
  "properties": {
    "iso:country":"US",
    "sg:address":"2400 W Belmont St",
    "sg:city":"Pensacola",
    "sg:classifiers":[
        {
            "category":"Building & Trades",
            "subcategory":"Cleaning & Sanitation",
            "type":"Services"
        }
    ],
    "sg:phone":"+1 850 438 2892",
    "sg:postcode":"32505",
    "sg:province":"FL",
    "sg:tags":[
        "janitor"
    ],
    "wof:name":"Mattie White Cleaning Svc",
    "wof:placetype":"venue"
},
  "geometry": {"coordinates":[-87.24597799999999,30.416922],"type":"Point"}
}