{
  "type": "Feature",
  "properties": {
    "addr:full":"4145 18th Ave SE Naples FL 34117",
    "addr:housenumber":"4145",
    "addr:postcode":"34117",
    "addr:street":"18Th Ave Se",
    "iso:country":"US",
    "sg:address":"4145 18th Ave SE",
    "sg:city":"Naples",
    "sg:classifiers":[
        {
            "category":"Building & Trades",
            "subcategory":"Landscaping Services",
            "type":"Services"
        }
    ],
    "sg:phone":"+1 239 304 5977",
    "sg:postcode":"34117",
    "sg:province":"FL",
    "wof:name":"Construction Team Clean Inc",
    "wof:placetype":"venue"
},
  "geometry": {"coordinates":[-81.519316,26.198162],"type":"Point"}
}