{
  "type": "Feature",
  "properties": {
    "iso:country":"US",
    "sg:address":"5920 Red Bug Lake Rd",
    "sg:city":"Winter Springs",
    "sg:classifiers":[
        {
            "category":"Sports & Exercise",
            "subcategory":"Gym",
            "type":"Entertainment"
        }
    ],
    "sg:phone":"+1 407 696 0600",
    "sg:postcode":"32708",
    "sg:province":"FL",
    "wof:name":"Lifestyles Family Fitness",
    "wof:placetype":"venue"
},
  "geometry": {"coordinates":[-81.267,28.647897],"type":"Point"}
}