{
  "type": "Feature",
  "properties": {
    "iso:country":"US",
    "sg:address":"184 Dublin Dr",
    "sg:city":"Lake Mary",
    "sg:classifiers":[
        {
            "category":"Professional",
            "type":"Services"
        }
    ],
    "sg:phone":"+1 407 321 5933",
    "sg:postcode":"32746",
    "sg:province":"FL",
    "wof:name":"Tmvs Inc",
    "wof:placetype":"venue"
},
  "geometry": {"coordinates":[-81.35614200000001,28.74456],"type":"Point"}
}