{
  "type": "Feature",
  "properties": {
    "iso:country":"US",
    "sg:address":"290 Clyde Morris Blvd",
    "sg:city":"Ormond Beach",
    "sg:classifiers":[
        {
            "category":"Personal",
            "subcategory":"Beauty Salon",
            "type":"Services"
        }
    ],
    "sg:phone":"+1 386 254 0674",
    "sg:postcode":"32174",
    "sg:province":"FL",
    "sg:tags":[
        "treatment",
        "skin"
    ],
    "wof:name":"Visible Solutions Skin Care",
    "wof:placetype":"venue"
},
  "geometry": {"coordinates":[-81.0945,29.263189],"type":"Point"}
}