{
  "type": "Feature",
  "properties": {
    "addr:full":"4632 NW 100th St Ocala FL 34482",
    "addr:housenumber":"4632",
    "addr:postcode":"34482",
    "addr:street":"Nw 100Th St",
    "iso:country":"US",
    "sg:address":"4632 NW 100th St",
    "sg:city":"Ocala",
    "sg:classifiers":[
        {
            "category":"Wholesale",
            "subcategory":"Non-durable Goods",
            "type":"Manufacturing & Wholesale Goods"
        }
    ],
    "sg:phone":"+1 352 207 3703",
    "sg:postcode":"34482",
    "sg:province":"FL",
    "sg:tags":[
        "dry",
        "goods-wholesale"
    ],
    "wof:name":"Deaco Pets And Supply",
    "wof:placetype":"venue"
},
  "geometry": {"coordinates":[-82.197163,29.29399],"type":"Point"}
}