{
  "type": "Feature",
  "properties": {
    "iso:country":"US",
    "sg:address":"11861 Lacy Ln",
    "sg:city":"Fort Myers",
    "sg:classifiers":[
        {
            "category":"Building & Trades",
            "subcategory":"Construction",
            "type":"Services"
        }
    ],
    "sg:phone":"+1 239 591 1711",
    "sg:postcode":"33912",
    "sg:province":"FL",
    "sg:tags":[
        "interior",
        "design"
    ],
    "sg:website":"www.kitchenartdesigncenter.com/",
    "wof:name":"Kitchen Art West",
    "wof:placetype":"venue"
},
  "geometry": {"coordinates":[-81.84868899999999,26.571526],"type":"Point"}
}