{
  "type": "Feature",
  "properties": {
    "addr:full":"1515 Damon Ave Kissimmee FL 34744",
    "addr:housenumber":"1515",
    "addr:postcode":"34744",
    "addr:street":"Damon Ave",
    "iso:country":"US",
    "sg:address":"1515 Damon Ave",
    "sg:city":"Kissimmee",
    "sg:classifiers":[
        {
            "category":"Retail",
            "subcategory":"Auto Repair",
            "type":"Services"
        }
    ],
    "sg:phone":"+1 407 847 7005",
    "sg:postcode":"34744",
    "sg:province":"FL",
    "sg:tags":[
        "repairing",
        "automobile"
    ],
    "wof:name":"European Autowerks",
    "wof:placetype":"venue"
},
  "geometry": {"coordinates":[-81.396219,28.306246],"type":"Point"}
}