{
  "type": "Feature",
  "properties": {
    "addr:full":"656 Capital Cir NE Tallahassee FL 32301",
    "addr:housenumber":"656",
    "addr:postcode":"32301",
    "addr:street":"Capital Cir Ne",
    "iso:country":"US",
    "sg:address":"656 Capital Cir NE",
    "sg:city":"Tallahassee",
    "sg:classifiers":[
        {
            "category":"Professional",
            "subcategory":"Engineering",
            "type":"Services"
        }
    ],
    "sg:phone":"+1 850 251 7743",
    "sg:postcode":"32301",
    "sg:province":"FL",
    "wof:name":"Repasky Construction Int",
    "wof:placetype":"venue"
},
  "geometry": {"coordinates":[-84.226733,30.44399],"type":"Point"}
}