{
  "type": "Feature",
  "properties": {
    "addr:full":"14127 US Hwy 27 Sebring FL 33876",
    "addr:housenumber":"14127",
    "addr:postcode":"33876",
    "addr:street":"Us Hwy 27",
    "iso:country":"US",
    "sg:address":"14127 US Hwy 27",
    "sg:city":"Sebring",
    "sg:classifiers":[
        {
            "category":"Shopping",
            "subcategory":"Gifts & Souvenirs",
            "type":"Retail Goods"
        }
    ],
    "sg:phone":"+1 863 699 9022",
    "sg:postcode":"33876",
    "sg:province":"FL",
    "wof:name":"J & S Products",
    "wof:placetype":"venue"
},
  "geometry": {"coordinates":[-81.40437300000001,27.376427],"type":"Point"}
}