{
  "type": "Feature",
  "properties": {
    "iso:country":"US",
    "sg:address":"2650 N University Dr",
    "sg:city":"Fort Lauderdale",
    "sg:classifiers":[
        {
            "category":"Food & Beverages",
            "subcategory":"Groceries & Convenience Stores",
            "type":"Retail Goods"
        },
        {
            "category":"Food & Beverages",
            "subcategory":"Specialty",
            "type":"Retail Goods"
        }
    ],
    "sg:phone":"+1 954 746 4469",
    "sg:postcode":"33322",
    "sg:province":"FL",
    "sg:tags":[
        "preparation",
        "oriental",
        "mfg"
    ],
    "wof:name":"Scarborough Fare Intl",
    "wof:placetype":"venue"
},
  "geometry": {"coordinates":[-80.257074,26.156736],"type":"Point"}
}