{
  "type": "Feature",
  "properties": {
    "iso:country":"US",
    "sg:address":"3598 NW 39th St",
    "sg:city":"Fort Lauderdale",
    "sg:classifiers":[
        {
            "category":"Shopping",
            "subcategory":"Beauty & Cosmetics",
            "type":"Retail Goods"
        }
    ],
    "sg:phone":"+1 954 676 5693",
    "sg:postcode":"33309",
    "sg:province":"FL",
    "sg:tags":[
        "merchandise"
    ],
    "wof:name":"Cologne & Perfume Center",
    "wof:placetype":"venue"
},
  "geometry": {"coordinates":[-80.196935,26.173794],"type":"Point"}
}