{
  "type": "Feature",
  "properties": {
    "addr:full":"8300 Jamaican Ct Orlando FL 32819",
    "addr:housenumber":"8300",
    "addr:postcode":"32819",
    "addr:street":"Jamaican Ct",
    "iso:country":"US",
    "sg:address":"8300 Jamaican Ct",
    "sg:city":"Orlando",
    "sg:classifiers":[
        {
            "category":"Travel",
            "subcategory":"Hotels & Motels",
            "type":"Entertainment"
        }
    ],
    "sg:phone":"+1 407 351 1660",
    "sg:postcode":"32819",
    "sg:province":"FL",
    "wof:name":"LA Quinta Inn",
    "wof:placetype":"venue"
},
  "geometry": {"coordinates":[-81.47254599999999,28.445989],"type":"Point"}
}