{
  "type": "Feature",
  "properties": {
    "iso:country":"US",
    "sg:address":"6140 Riviera Manor Dr",
    "sg:city":"Jacksonville",
    "sg:classifiers":[
        {
            "category":"Building & Trades",
            "subcategory":"Landscaping Services",
            "type":"Services"
        }
    ],
    "sg:phone":"+1 904 724 7245",
    "sg:postcode":"32216",
    "sg:province":"FL",
    "wof:name":"Warming Tree Service Inc",
    "wof:placetype":"venue"
},
  "geometry": {"coordinates":[-81.597391,30.299432],"type":"Point"}
}