{
  "type": "Feature",
  "properties": {
    "iso:country":"US",
    "sg:address":"1252 W 68th St",
    "sg:city":"Hialeah",
    "sg:classifiers":[
        {
            "category":"Arts & Performance",
            "subcategory":"Art Gallery",
            "type":"Entertainment"
        }
    ],
    "sg:phone":"+1 305 825 3330",
    "sg:postcode":"33014",
    "sg:province":"FL",
    "wof:name":"Silva Studio Frame Art",
    "wof:placetype":"venue"
},
  "geometry": {"coordinates":[-80.310097,25.8843],"type":"Point"}
}