{
  "type": "Feature",
  "properties": {
    "addr:full":"2311 Division St Jacksonville FL 32209",
    "addr:housenumber":"2311",
    "addr:postcode":"32209",
    "addr:street":"Division St",
    "iso:country":"US",
    "sg:address":"2311 Division St",
    "sg:city":"Jacksonville",
    "sg:classifiers":[
        {
            "category":"Personal",
            "subcategory":"Barber",
            "type":"Services"
        }
    ],
    "sg:phone":"+1 904 355 9577",
    "sg:postcode":"32209",
    "sg:province":"FL",
    "sg:tags":[
        "shop"
    ],
    "wof:name":"Lawrence Barber Shop",
    "wof:placetype":"venue"
},
  "geometry": {"coordinates":[-81.701318,30.351516],"type":"Point"}
}