{
  "type": "Feature",
  "properties": {
    "iso:country":"US",
    "sg:address":"8100 NW 17th Ave",
    "sg:city":"Miami",
    "sg:classifiers":[
        {
            "category":"Organizations",
            "subcategory":"Religious Organization",
            "type":"Services"
        }
    ],
    "sg:phone":"+1 305 693 1301",
    "sg:postcode":"33147",
    "sg:province":"FL",
    "sg:tags":[
        "church"
    ],
    "wof:name":"Christian Fellowship Baptist Church",
    "wof:placetype":"venue"
},
  "geometry": {"coordinates":[-80.225403,25.8484],"type":"Point"}
}