{
  "type": "Feature",
  "properties": {
    "iso:country":"US",
    "sg:address":"2729 Carol Ln",
    "sg:city":"Panama City",
    "sg:classifiers":[
        {
            "category":"Building & Trades",
            "subcategory":"Construction",
            "type":"Services"
        }
    ],
    "sg:phone":"+1 850 747 4018",
    "sg:postcode":"32405",
    "sg:province":"FL",
    "sg:tags":[
        "contractor"
    ],
    "wof:name":"Tile Technologies",
    "wof:placetype":"venue"
},
  "geometry": {"coordinates":[-85.632195,30.197722],"type":"Point"}
}