{
  "type": "Feature",
  "properties": {
    "iso:country":"US",
    "sg:address":"106 S Flagler Way",
    "sg:city":"West Palm Beach",
    "sg:classifiers":[
        {
            "category":"Travel",
            "subcategory":"Travel Agent",
            "type":"Entertainment"
        }
    ],
    "sg:phone":"+1 561 833 9991",
    "sg:postcode":"33405",
    "sg:province":"FL",
    "sg:tags":[
        "agency"
    ],
    "wof:name":"Bermuda Sports Marketing LTD",
    "wof:placetype":"venue"
},
  "geometry": {"coordinates":[-80.049385,26.668046],"type":"Point"}
}