{
  "type": "Feature",
  "properties": {
    "iso:country":"US",
    "sg:address":"300 Riverside Dr E",
    "sg:city":"Bradenton",
    "sg:classifiers":[
        {
            "category":"Health Services",
            "subcategory":"Doctor",
            "type":"Services"
        }
    ],
    "sg:phone":"+1 941 228 4888",
    "sg:postcode":"34208",
    "sg:province":"FL",
    "sg:tags":[
        "physician",
        "medical",
        "surgeon"
    ],
    "wof:name":"Jose F Polanco MD PA",
    "wof:placetype":"venue"
},
  "geometry": {"coordinates":[-82.56029599999999,27.49831],"type":"Point"}
}