{
  "type": "Feature",
  "properties": {
    "addr:full":"13802 Pumpkin Hill Rd Jacksonville FL 32226",
    "addr:housenumber":"13802",
    "addr:postcode":"32226",
    "addr:street":"Pumpkin Hill Rd",
    "iso:country":"US",
    "sg:address":"13802 Pumpkin Hill Rd",
    "sg:city":"Jacksonville",
    "sg:classifiers":[
        {
            "category":"Government",
            "subcategory":"Fire Station",
            "type":"Public Place"
        }
    ],
    "sg:phone":"+1 904 696 5944",
    "sg:postcode":"32226",
    "sg:province":"FL",
    "sg:tags":[
        "protection"
    ],
    "wof:name":"Pumpkin Hill Creek Preserve",
    "wof:placetype":"venue"
},
  "geometry": {"coordinates":[-81.48707,30.478041],"type":"Point"}
}