{
  "type": "Feature",
  "properties": {
    "iso:country":"US",
    "sg:address":"2816 NW 30th Ave",
    "sg:city":"Fort Lauderdale",
    "sg:classifiers":[
        {
            "category":"Building & Trades",
            "subcategory":"Landscaping Services",
            "type":"Services"
        }
    ],
    "sg:phone":"+1 954 587 9993",
    "sg:postcode":"33311",
    "sg:province":"FL",
    "sg:tags":[
        "landscape"
    ],
    "wof:name":"Willie L Elliott",
    "wof:placetype":"venue"
},
  "geometry": {"coordinates":[-80.18501500000001,26.161186],"type":"Point"}
}