{
  "type": "Feature",
  "properties": {
    "iso:country":"US",
    "sg:address":"22480 Southshore Dr",
    "sg:city":"Land O Lakes",
    "sg:classifiers":[
        {
            "category":"Wholesale",
            "subcategory":"Non-durable Goods",
            "type":"Manufacturing & Wholesale Goods"
        }
    ],
    "sg:phone":"+1 813 929 9063",
    "sg:postcode":"34639",
    "sg:province":"FL",
    "sg:tags":[
        "pet",
        "supply"
    ],
    "wof:name":"MMS House Of Blues",
    "wof:placetype":"venue"
},
  "geometry": {"coordinates":[-82.44471299999999,28.204606],"type":"Point"}
}