{
  "type": "Feature",
  "properties": {
    "iso:country":"US",
    "sg:address":"630 NE 34th St",
    "sg:city":"Pompano Beach",
    "sg:classifiers":[
        {
            "category":"Retail",
            "subcategory":"Auto Repair",
            "type":"Services"
        }
    ],
    "sg:phone":"+1 954 782 2677",
    "sg:postcode":"33064",
    "sg:province":"FL",
    "sg:tags":[
        "repairing",
        "automobile"
    ],
    "wof:name":"Allied Motor & Pump Svc",
    "wof:placetype":"venue"
},
  "geometry": {"coordinates":[-80.11300799999999,26.272441],"type":"Point"}
}