{
  "type": "Feature",
  "properties": {
    "addr:full":"7961 SW Jack James Dr Stuart FL 34997",
    "addr:housenumber":"7961",
    "addr:postcode":"34997",
    "addr:street":"Sw Jack James Dr",
    "iso:country":"US",
    "sg:address":"7961 SW Jack James Dr",
    "sg:city":"Stuart",
    "sg:classifiers":[
        {
            "category":"Food & Beverages",
            "subcategory":"Groceries & Convenience Stores",
            "type":"Retail Goods"
        }
    ],
    "sg:phone":"+1 772 221 1190",
    "sg:postcode":"34997",
    "sg:province":"FL",
    "sg:tags":[
        "product",
        "snack"
    ],
    "wof:name":"Snyders Of Hanover",
    "wof:placetype":"venue"
},
  "geometry": {"coordinates":[-80.267512,27.110436],"type":"Point"}
}