{
  "type": "Feature",
  "properties": {
    "addr:full":"2250 S Nova Rd Daytona Beach FL 32119",
    "addr:housenumber":"2250",
    "addr:postcode":"32119",
    "addr:street":"S Nova Rd",
    "iso:country":"US",
    "sg:address":"2250 S Nova Rd",
    "sg:city":"Daytona Beach",
    "sg:classifiers":[
        {
            "category":"Restaurant",
            "type":"Food & Drink"
        }
    ],
    "sg:menulink":"http://www.allmenus.com/fl/port-orange/219505-xtra-pizza/menu/",
    "sg:phone":"+1 386 756 3210",
    "sg:postcode":"32119",
    "sg:province":"FL",
    "sg:tags":[
        "american",
        "pizza"
    ],
    "wof:name":"Xtra Pizza",
    "wof:placetype":"venue"
},
  "geometry": {"coordinates":[-81.022986,29.15949],"type":"Point"}
}