{
  "type": "Feature",
  "properties": {
    "addr:full":"2059 Range Rd Clearwater FL 33765",
    "addr:housenumber":"2059",
    "addr:postcode":"33765",
    "addr:street":"Range Rd",
    "iso:country":"US",
    "sg:address":"2059 Range Rd",
    "sg:city":"Clearwater",
    "sg:classifiers":[
        {
            "category":"Manufacturing",
            "subcategory":"Printing",
            "type":"Manufacturing & Wholesale Goods"
        }
    ],
    "sg:phone":"+1 727 446 0980",
    "sg:postcode":"33765",
    "sg:province":"FL",
    "sg:tags":[
        "screen"
    ],
    "wof:name":"Roller Graphics",
    "wof:placetype":"venue"
},
  "geometry": {"coordinates":[-82.751501,27.978861],"type":"Point"}
}