{
  "type": "Feature",
  "properties": {
    "addr:full":"706 Sharar Ave Opa Locka FL 33054",
    "addr:housenumber":"706",
    "addr:postcode":"33054",
    "addr:street":"Sharar Ave;Locka",
    "iso:country":"US",
    "sg:address":"706 Sharar Ave",
    "sg:city":"Opa Locka",
    "sg:classifiers":[
        {
            "category":"Building & Trades",
            "subcategory":"Construction",
            "type":"Services"
        }
    ],
    "sg:phone":"+1 305 681 2460",
    "sg:postcode":"33054",
    "sg:province":"FL",
    "sg:tags":[
        "painting",
        "contractor"
    ],
    "wof:name":"Sinbad Painting and Carptr Co",
    "wof:placetype":"venue"
},
  "geometry": {"coordinates":[-80.25408,25.907077],"type":"Point"}
}