{
  "type": "Feature",
  "properties": {
    "addr:full":"2249 S Woodland Blvd Deland FL 32720",
    "addr:housenumber":"2249",
    "addr:postcode":"32720",
    "addr:street":"S Woodland Blvd",
    "iso:country":"US",
    "sg:address":"2249 S Woodland Blvd",
    "sg:city":"Deland",
    "sg:classifiers":[
        {
            "category":"Banks & Credit Unions",
            "subcategory":"Bank",
            "type":"Services"
        }
    ],
    "sg:phone":"+1 386 822 4050",
    "sg:postcode":"32720",
    "sg:province":"FL",
    "sg:tags":[
        "depository",
        "banking",
        "check",
        "cashing"
    ],
    "wof:name":"Florida Cash Advance Inc",
    "wof:placetype":"venue"
},
  "geometry": {"coordinates":[-81.30111599999999,28.989749],"type":"Point"}
}