{
  "type": "Feature",
  "properties": {
    "iso:country":"US",
    "sg:address":"8505 Harding Ave",
    "sg:city":"Miami Beach",
    "sg:classifiers":[
        {
            "category":"Professional",
            "subcategory":"Business Services",
            "type":"Services"
        }
    ],
    "sg:phone":"+1 305 867 1906",
    "sg:postcode":"33141",
    "sg:province":"FL",
    "sg:tags":[
        "reservation",
        "motel",
        "hotel"
    ],
    "wof:name":"Shorehaven Motel & Apartments",
    "wof:placetype":"venue"
},
  "geometry": {"coordinates":[-80.122454,25.870891],"type":"Point"}
}