{
  "type": "Feature",
  "properties": {
    "addr:full":"2500 State Hwy 44 Inverness FL 34453",
    "addr:housenumber":"2500",
    "addr:postcode":"34453",
    "addr:street":"State Hwy 44",
    "iso:country":"US",
    "sg:address":"2500 State Hwy 44",
    "sg:city":"Inverness",
    "sg:classifiers":[
        {
            "category":"Shopping",
            "subcategory":"Musical Instruments",
            "type":"Retail Goods"
        }
    ],
    "sg:phone":"+1 352 344 0656",
    "sg:postcode":"34453",
    "sg:province":"FL",
    "wof:name":"Music Madness",
    "wof:placetype":"venue"
},
  "geometry": {"coordinates":[-82.36398,28.842823],"type":"Point"}
}