{
  "type": "Feature",
  "properties": {
    "iso:country":"US",
    "sg:address":"762 Pelican Bay Dr",
    "sg:city":"Daytona Beach",
    "sg:classifiers":[
        {
            "category":"Professional",
            "subcategory":"Business Services",
            "type":"Services"
        }
    ],
    "sg:phone":"+1 386 673 7073",
    "sg:postcode":"32119",
    "sg:province":"FL",
    "sg:website":"www.built-write.com",
    "wof:name":"Built Write Inc",
    "wof:placetype":"venue"
},
  "geometry": {"coordinates":[-81.05271,29.14774],"type":"Point"}
}