{
  "type": "Feature",
  "properties": {
    "addr:full":"1310 SW 8th Ave Deerfield Beach FL 33441",
    "addr:housenumber":"1310",
    "addr:postcode":"33441",
    "addr:street":"Sw 8Th Ave",
    "iso:country":"US",
    "sg:address":"1310 SW 8th Ave",
    "sg:city":"Deerfield Beach",
    "sg:classifiers":[
        {
            "category":"Manufacturing",
            "subcategory":"Tools & Machinery",
            "type":"Manufacturing & Wholesale Goods"
        }
    ],
    "sg:phone":"+1 954 428 7776",
    "sg:postcode":"33441",
    "sg:province":"FL",
    "sg:tags":[
        "industry",
        "mfg"
    ],
    "wof:name":"Hoods Plus",
    "wof:placetype":"venue"
},
  "geometry": {"coordinates":[-80.114772,26.300651],"type":"Point"}
}