{
  "type": "Feature",
  "properties": {
    "addr:full":"5503 Broadway Ave Jacksonville FL 32254",
    "addr:housenumber":"5503",
    "addr:postcode":"32254",
    "addr:street":"Broadway Ave",
    "iso:country":"US",
    "sg:address":"5503 Broadway Ave",
    "sg:city":"Jacksonville",
    "sg:classifiers":[
        {
            "category":"Wholesale",
            "subcategory":"Machinery & Supplies",
            "type":"Manufacturing & Wholesale Goods"
        }
    ],
    "sg:phone":"+1 904 693 8855",
    "sg:postcode":"32254",
    "sg:province":"FL",
    "sg:tags":[
        "tank"
    ],
    "wof:name":"Baker Tanks Pumps & Pipes",
    "wof:placetype":"venue"
},
  "geometry": {"coordinates":[-81.74144699999999,30.332443],"type":"Point"}
}