{
  "type": "Feature",
  "properties": {
    "addr:full":"801 SE 7th Ave Pompano Beach FL 33060",
    "addr:housenumber":"801",
    "addr:postcode":"33060",
    "addr:street":"Se 7Th Ave",
    "iso:country":"US",
    "sg:address":"801 SE 7th Ave",
    "sg:city":"Pompano Beach",
    "sg:classifiers":[
        {
            "category":"Autos & Motor Vehicles",
            "subcategory":"Fuel & Gas Station",
            "type":"Retail Goods"
        }
    ],
    "sg:phone":"+1 954 784 9498",
    "sg:postcode":"33060",
    "sg:province":"FL",
    "sg:tags":[
        "station",
        "gasoline"
    ],
    "wof:name":"Chevron Info Technology Corp",
    "wof:placetype":"venue"
},
  "geometry": {"coordinates":[-80.111735,26.219111],"type":"Point"}
}