{
  "type": "Feature",
  "properties": {
    "addr:full":"2988 Starshire Cove Jacksonville FL 32257",
    "addr:housenumber":"2988",
    "addr:postcode":"32257",
    "addr:street":"Starshire Cove",
    "iso:country":"US",
    "sg:address":"2988 Starshire Cove",
    "sg:city":"Jacksonville",
    "sg:classifiers":[
        {
            "category":"Freight",
            "type":"Transportation"
        }
    ],
    "sg:phone":"+1 904 262 0803",
    "sg:postcode":"32257",
    "sg:province":"FL",
    "sg:tags":[
        "warehouse",
        "rental",
        "unit"
    ],
    "wof:name":"Camar Enterprises Inc",
    "wof:placetype":"venue"
},
  "geometry": {"coordinates":[-81.62566200000001,30.193298],"type":"Point"}
}