{
  "type": "Feature",
  "properties": {
    "iso:country":"US",
    "sg:address":"4000 Green Forest Dr",
    "sg:city":"Boynton Beach",
    "sg:classifiers":[
        {
            "category":"Building & Trades",
            "subcategory":"Construction",
            "type":"Services"
        }
    ],
    "sg:phone":"+1 561 742 0131",
    "sg:postcode":"33436",
    "sg:province":"FL",
    "sg:tags":[
        "handyman"
    ],
    "wof:name":"Anthony J Dimino Carpenter",
    "wof:placetype":"venue"
},
  "geometry": {"coordinates":[-80.10614099999999,26.537482],"type":"Point"}
}