{
  "type": "Feature",
  "properties": {
    "iso:country":"US",
    "sg:address":"1630 Palatka Rd SE",
    "sg:city":"Palm Bay",
    "sg:classifiers":[
        {
            "category":"Building & Trades",
            "subcategory":"Construction",
            "type":"Services"
        }
    ],
    "sg:phone":"+1 321 455 0000",
    "sg:postcode":"32909",
    "sg:province":"FL",
    "sg:tags":[
        "home",
        "repair"
    ],
    "wof:name":"Stephen E Loud",
    "wof:placetype":"venue"
},
  "geometry": {"coordinates":[-80.62504,27.956799],"type":"Point"}
}