{
  "type": "Feature",
  "properties": {
    "addr:full":"1615 NW 34 Pl Gainesville FL 32605",
    "addr:housenumber":"1615",
    "addr:postcode":"32605",
    "addr:street":"Nw 34 Pl",
    "iso:country":"US",
    "sg:address":"1615 NW 34 Pl",
    "sg:city":"Gainesville",
    "sg:classifiers":[
        {
            "category":"Restaurant",
            "type":"Food & Drink"
        }
    ],
    "sg:phone":"+1 352 376 9454",
    "sg:postcode":"32605",
    "sg:province":"FL",
    "sg:tags":[
        "eating"
    ],
    "wof:name":"Little Dragon Wings",
    "wof:placetype":"venue"
},
  "geometry": {"coordinates":[-82.343255,29.684623],"type":"Point"}
}