{
  "type": "Feature",
  "properties": {
    "iso:country":"US",
    "sg:address":"404 N Halifax Ave",
    "sg:city":"Daytona Beach",
    "sg:classifiers":[
        {
            "category":"Professional",
            "subcategory":"Lawyer & Legal Services",
            "type":"Services"
        }
    ],
    "sg:phone":"+1 386 253 4720",
    "sg:postcode":"32118",
    "sg:province":"FL",
    "sg:tags":[
        "attorney"
    ],
    "wof:name":"Lauren Y Koleilat Law Office",
    "wof:placetype":"venue"
},
  "geometry": {"coordinates":[-81.01679799999999,29.230886],"type":"Point"}
}