{
  "type": "Feature",
  "properties": {
    "iso:country":"US",
    "sg:address":"3240 NW 72nd Ter",
    "sg:city":"Hollywood",
    "sg:classifiers":[
        {
            "category":"Building & Trades",
            "subcategory":"Construction",
            "type":"Services"
        }
    ],
    "sg:phone":"+1 954 981 6628",
    "sg:postcode":"33024",
    "sg:province":"FL",
    "sg:tags":[
        "hanging",
        "contractor"
    ],
    "wof:name":"Miami Nice Painting",
    "wof:placetype":"venue"
},
  "geometry": {"coordinates":[-80.23362299999999,26.037405],"type":"Point"}
}