{
  "type": "Feature",
  "properties": {
    "addr:full":"73 SW 12th Ave Unit 112 Miami FL 33130",
    "addr:housenumber":"73;112",
    "addr:postcode":"33130",
    "addr:street":"Sw 12Th Ave Unit",
    "iso:country":"US",
    "sg:address":"73 SW 12th Ave Unit 112",
    "sg:city":"Miami",
    "sg:classifiers":[
        {
            "category":"Home & Garden",
            "subcategory":"Carpets & Floor Coverings",
            "type":"Retail Goods"
        }
    ],
    "sg:phone":"+1 954 583 2233",
    "sg:postcode":"33130",
    "sg:province":"FL",
    "sg:tags":[
        "rug"
    ],
    "wof:name":"Daniel Flooring",
    "wof:placetype":"venue"
},
  "geometry": {"coordinates":[-80.214626,25.772796],"type":"Point"}
}