{
  "type": "Feature",
  "properties": {
    "iso:country":"US",
    "sg:address":"8885 Davis Blvd",
    "sg:city":"Naples",
    "sg:classifiers":[
        {
            "category":"Restaurant",
            "type":"Food & Drink"
        }
    ],
    "sg:menulink":"http://www.allmenus.com/fl/naples/160461-burger-king/menu/",
    "sg:phone":"+1 941 353 4663",
    "sg:postcode":"34104",
    "sg:province":"FL",
    "sg:tags":[
        "burger",
        "american"
    ],
    "wof:name":"Burger King",
    "wof:placetype":"venue"
},
  "geometry": {"coordinates":[-81.68781199999999,26.155309],"type":"Point"}
}