{
  "type": "Feature",
  "properties": {
    "iso:country":"US",
    "sg:address":"6937 Javid Rd",
    "sg:city":"Milton",
    "sg:classifiers":[
        {
            "category":"Building & Trades",
            "subcategory":"Construction",
            "type":"Services"
        }
    ],
    "sg:phone":"+1 850 626 0654",
    "sg:postcode":"32583",
    "sg:province":"FL",
    "sg:tags":[
        "contractor"
    ],
    "wof:name":"Sean Vetter Masonry",
    "wof:placetype":"venue"
},
  "geometry": {"coordinates":[-87.035273,30.580406],"type":"Point"}
}