{
  "type": "Feature",
  "properties": {
    "addr:full":"10452 New Kings Rd Jacksonville FL 32219",
    "addr:housenumber":"10452",
    "addr:postcode":"32219",
    "addr:street":"New Kings Rd",
    "iso:country":"US",
    "sg:address":"10452 New Kings Rd",
    "sg:city":"Jacksonville",
    "sg:phone":"+1 904 768 7444",
    "sg:postcode":"32219",
    "sg:province":"FL",
    "sg:website":"http://www.dinsmoreflorist.com",
    "wof:name":"Dinsmore Florist Inc",
    "wof:placetype":"venue"
},
  "geometry": {"coordinates":[-81.756539,30.426771],"type":"Point"}
}