{
  "type": "Feature",
  "properties": {
    "iso:country":"US",
    "sg:address":"1216 Baldwin Pl",
    "sg:city":"Lehigh Acres",
    "sg:classifiers":[
        {
            "category":"Freight",
            "type":"Transportation"
        }
    ],
    "sg:phone":"+1 239 369 8081",
    "sg:postcode":"33936",
    "sg:province":"FL",
    "sg:tags":[
        "arrangement"
    ],
    "wof:name":"Butler Truck Brokers",
    "wof:placetype":"venue"
},
  "geometry": {"coordinates":[-81.611434,26.602209],"type":"Point"}
}