{
  "type": "Feature",
  "properties": {
    "iso:country":"US",
    "sg:address":"6454 126th Ave N",
    "sg:city":"Largo",
    "sg:classifiers":[
        {
            "category":"Building & Trades",
            "subcategory":"Construction",
            "type":"Services"
        }
    ],
    "sg:phone":"+1 727 538 9949",
    "sg:postcode":"33773",
    "sg:province":"FL",
    "sg:tags":[
        "roofing",
        "contractor"
    ],
    "wof:name":"Sunwest Roofing",
    "wof:placetype":"venue"
},
  "geometry": {"coordinates":[-82.725189,27.886385],"type":"Point"}
}