{
  "type": "Feature",
  "properties": {
    "iso:country":"US",
    "sg:address":"313 NE 10th St",
    "sg:city":"Cape Coral",
    "sg:classifiers":[
        {
            "category":"Building & Trades",
            "subcategory":"Electrical",
            "type":"Services"
        }
    ],
    "sg:phone":"+1 239 826 4022",
    "sg:postcode":"33909",
    "sg:province":"FL",
    "sg:tags":[
        "electrical",
        "contractor"
    ],
    "wof:name":"Farrell John",
    "wof:placetype":"venue"
},
  "geometry": {"coordinates":[-81.968024,26.670945],"type":"Point"}
}