{
  "type": "Feature",
  "properties": {
    "addr:full":"5010 Lake Pierce Dr Lake Wales FL 33898",
    "addr:housenumber":"5010",
    "addr:postcode":"33898",
    "addr:street":"Lake Pierce Dr",
    "iso:country":"US",
    "sg:address":"5010 Lake Pierce Dr",
    "sg:city":"Lake Wales",
    "sg:classifiers":[
        {
            "category":"Manufacturing",
            "subcategory":"Printing",
            "type":"Manufacturing & Wholesale Goods"
        }
    ],
    "sg:phone":"+1 863 439 2278",
    "sg:postcode":"33898",
    "sg:province":"FL",
    "sg:tags":[
        "publishing"
    ],
    "wof:name":"Edge of Wild",
    "wof:placetype":"venue"
},
  "geometry": {"coordinates":[-81.53955499999999,27.971988],"type":"Point"}
}