{
  "type": "Feature",
  "properties": {
    "addr:full":"207 Yacht Club Dr Niceville FL 32578",
    "addr:housenumber":"207",
    "addr:postcode":"32578",
    "addr:street":"Yacht Club Dr",
    "iso:country":"US",
    "sg:address":"207 Yacht Club Dr",
    "sg:city":"Niceville",
    "sg:classifiers":[
        {
            "category":"Professional",
            "subcategory":"Business Services",
            "type":"Services"
        }
    ],
    "sg:phone":"+1 850 678 9470",
    "sg:postcode":"32578",
    "sg:province":"FL",
    "sg:tags":[
        "interior",
        "consultant",
        "design",
        "decorator"
    ],
    "wof:name":"Design Concepts",
    "wof:placetype":"venue"
},
  "geometry": {"coordinates":[-86.462823,30.488851],"type":"Point"}
}