{
  "type": "Feature",
  "properties": {
    "addr:full":"1435 NE 162nd St Miami FL 33162",
    "addr:housenumber":"1435",
    "addr:postcode":"33162",
    "addr:street":"Ne 162Nd St",
    "iso:country":"US",
    "sg:address":"1435 NE 162nd St",
    "sg:city":"Miami",
    "sg:classifiers":[
        {
            "category":"Shopping",
            "subcategory":"Used Merchandise",
            "type":"Retail Goods"
        },
        {
            "category":"Social Services",
            "type":"Services"
        }
    ],
    "sg:phone":"+1 305 947 4560",
    "sg:postcode":"33162",
    "sg:province":"FL",
    "sg:tags":[
        "shop",
        "thrift"
    ],
    "wof:name":"Safespace Thrift Store",
    "wof:placetype":"venue"
},
  "geometry": {"coordinates":[-80.17149999999999,25.924733],"type":"Point"}
}