{
  "type": "Feature",
  "properties": {
    "addr:full":"11195 SW 216th St Miami FL 33170",
    "addr:housenumber":"11195",
    "addr:postcode":"33170",
    "addr:street":"Sw 216Th St",
    "iso:country":"US",
    "sg:address":"11195 SW 216th St",
    "sg:city":"Miami",
    "sg:classifiers":[
        {
            "category":"Autos & Motor Vehicles",
            "subcategory":"Fuel & Gas Station",
            "type":"Retail Goods"
        }
    ],
    "sg:phone":"+1 305 259 0358",
    "sg:postcode":"33170",
    "sg:province":"FL",
    "sg:tags":[
        "oil"
    ],
    "wof:name":"Shell",
    "wof:placetype":"venue"
},
  "geometry": {"coordinates":[-80.370425,25.566378],"type":"Point"}
}