{
  "type": "Feature",
  "properties": {
    "addr:full":"701 Ave G NE Winter Haven FL 33881",
    "addr:housenumber":"701",
    "addr:postcode":"33881",
    "addr:street":"Ave G Ne",
    "iso:country":"US",
    "sg:address":"701 Ave G NE",
    "sg:city":"Winter Haven",
    "sg:classifiers":[
        {
            "category":"Building & Trades",
            "subcategory":"Construction",
            "type":"Services"
        }
    ],
    "sg:phone":"+1 863 521 0134",
    "sg:postcode":"33881",
    "sg:province":"FL",
    "sg:tags":[
        "coping",
        "plastering",
        "tiling",
        "pool",
        "swimming"
    ],
    "wof:name":"Hoosier Pool Man",
    "wof:placetype":"venue"
},
  "geometry": {"coordinates":[-81.714511,28.029172],"type":"Point"}
}