{
  "type": "Feature",
  "properties": {
    "addr:full":"126 Rivera Ave Royal Palm Beach FL 33411",
    "addr:housenumber":"126",
    "addr:postcode":"33411",
    "addr:street":"Rivera Ave",
    "iso:country":"US",
    "sg:address":"126 Rivera Ave",
    "sg:city":"Royal Palm Beach",
    "sg:classifiers":[
        {
            "category":"Shopping",
            "type":"Retail Goods"
        }
    ],
    "sg:phone":"+1 561 656 1550",
    "sg:postcode":"33411",
    "sg:province":"FL",
    "sg:tags":[
        "cosmetic",
        "perfume"
    ],
    "wof:name":"Mary Kay Cosmetics",
    "wof:placetype":"venue"
},
  "geometry": {"coordinates":[-80.21975999999999,26.732001],"type":"Point"}
}