{
  "type": "Feature",
  "properties": {
    "iso:country":"US",
    "sg:address":"8729 Leprechaun Ct",
    "sg:city":"Jacksonville",
    "sg:classifiers":[
        {
            "category":"Freight",
            "type":"Transportation"
        }
    ],
    "sg:phone":"+1 904 723 0166",
    "sg:postcode":"32216",
    "sg:province":"FL",
    "sg:tags":[
        "delivery"
    ],
    "wof:name":"Ace Expediters",
    "wof:placetype":"venue"
},
  "geometry": {"coordinates":[-81.565274,30.284702],"type":"Point"}
}