{
  "type": "Feature",
  "properties": {
    "iso:country":"US",
    "sg:address":"2160 NW 79th St",
    "sg:city":"Miami",
    "sg:classifiers":[
        {
            "category":"Shopping",
            "subcategory":"Pets & Pet Supplies",
            "type":"Retail Goods"
        }
    ],
    "sg:phone":"+1 305 835 6660",
    "sg:postcode":"33147",
    "sg:province":"FL",
    "sg:tags":[
        "store"
    ],
    "wof:name":"Low Price Puppies",
    "wof:placetype":"venue"
},
  "geometry": {"coordinates":[-80.232832,25.846234],"type":"Point"}
}