{
  "type": "Feature",
  "properties": {
    "iso:country":"US",
    "sg:address":"3857 Hopkins St",
    "sg:city":"Pensacola",
    "sg:classifiers":[
        {
            "category":"Building & Trades",
            "subcategory":"Construction",
            "type":"Services"
        }
    ],
    "sg:phone":"+1 850 422 0270",
    "sg:postcode":"32505",
    "sg:province":"FL",
    "sg:tags":[
        "contractor"
    ],
    "wof:name":"Centimark Roofing",
    "wof:placetype":"venue"
},
  "geometry": {"coordinates":[-87.230667,30.452286],"type":"Point"}
}