{
  "type": "Feature",
  "properties": {
    "addr:full":"1353 NE 34th St Fort Lauderdale FL 33334",
    "addr:housenumber":"1353",
    "addr:postcode":"33334",
    "addr:street":"Ne 34Th St",
    "iso:country":"US",
    "sg:address":"1353 NE 34th St",
    "sg:city":"Fort Lauderdale",
    "sg:classifiers":[
        {
            "category":"Shopping",
            "type":"Retail Goods"
        }
    ],
    "sg:phone":"+1 954 554 2654",
    "sg:postcode":"33334",
    "sg:province":"FL",
    "sg:tags":[
        "merchandise"
    ],
    "wof:name":"Media Tecnoogies",
    "wof:placetype":"venue"
},
  "geometry": {"coordinates":[-80.128602,26.169709],"type":"Point"}
}