{
  "type": "Feature",
  "properties": {
    "iso:country":"US",
    "sg:address":"3024 Plummer Cove Rd",
    "sg:city":"Jacksonville",
    "sg:classifiers":[
        {
            "category":"Retail",
            "subcategory":"Storage",
            "type":"Services"
        },
        {
            "category":"Manufacturing",
            "subcategory":"Paper Products",
            "type":"Manufacturing & Wholesale Goods"
        }
    ],
    "sg:phone":"+1 904 288 9886",
    "sg:postcode":"32223",
    "sg:province":"FL",
    "sg:tags":[
        "fiber",
        "automobile",
        "household",
        "commercial",
        "boxes-corrugated",
        "self",
        "boat"
    ],
    "sg:website":"http://www.ustoreit.com/?utm_source=yellowpages&utm_medium=premium&utm_campaign=yp2010&phid=0434",
    "wof:name":"U-Store-It",
    "wof:placetype":"venue"
},
  "geometry": {"coordinates":[-81.62876799999999,30.179092],"type":"Point"}
}