{
  "type": "Feature",
  "properties": {
    "iso:country":"US",
    "sg:address":"671 Outrigger Dr",
    "sg:city":"Deltona",
    "sg:classifiers":[
        {
            "category":"Shopping",
            "subcategory":"Computers & Home Electronics",
            "type":"Retail Goods"
        }
    ],
    "sg:phone":"+1 386 789 3303",
    "sg:postcode":"32738",
    "sg:province":"FL",
    "sg:tags":[
        "equipment",
        "dealer"
    ],
    "wof:name":"Transcomp Computer Parts & Svc",
    "wof:placetype":"venue"
},
  "geometry": {"coordinates":[-81.18237499999999,28.879983],"type":"Point"}
}