{
  "type": "Feature",
  "properties": {
    "iso:country":"US",
    "sg:address":"36 NE 1st St Ste 734",
    "sg:city":"Miami",
    "sg:classifiers":[
        {
            "category":"Shopping",
            "subcategory":"Jewelry",
            "type":"Retail Goods"
        }
    ],
    "sg:phone":"+1 305 373 0788",
    "sg:postcode":"33132",
    "sg:province":"FL",
    "sg:tags":[
        "watch"
    ],
    "wof:name":"Voloj Llc",
    "wof:placetype":"venue"
},
  "geometry": {"coordinates":[-80.19303499999999,25.775003],"type":"Point"}
}