{
  "type": "Feature",
  "properties": {
    "iso:country":"US",
    "sg:address":"1401 Town Center Dr",
    "sg:city":"Lakeland",
    "sg:classifiers":[
        {
            "category":"Shopping",
            "subcategory":"Department Store",
            "type":"Retail Goods"
        }
    ],
    "sg:phone":"+1 863 682 8989",
    "sg:postcode":"33803",
    "sg:province":"FL",
    "sg:website":"http://www.kohls.com",
    "wof:name":"Kohl's",
    "wof:placetype":"venue"
},
  "geometry": {"coordinates":[-81.9769,28.00153],"type":"Point"}
}