{
  "type": "Feature",
  "properties": {
    "addr:full":"234 N Park Ave Winter Park FL 32789",
    "addr:housenumber":"234",
    "addr:postcode":"32789",
    "addr:street":"N Park Ave",
    "iso:country":"US",
    "sg:address":"234 N Park Ave",
    "sg:city":"Winter Park",
    "sg:classifiers":[
        {
            "category":"Shopping",
            "subcategory":"Gifts & Souvenirs",
            "type":"Retail Goods"
        },
        {
            "category":"Shopping",
            "subcategory":"Beauty & Cosmetics",
            "type":"Retail Goods"
        }
    ],
    "sg:phone":"+1 407 647 2455",
    "sg:postcode":"32789",
    "sg:province":"FL",
    "sg:tags":[
        "shop",
        "personal",
        "care",
        "item"
    ],
    "wof:name":"Caswell Massey",
    "wof:placetype":"venue"
},
  "geometry": {"coordinates":[-81.35099099999999,28.59921],"type":"Point"}
}