{
  "type": "Feature",
  "properties": {
    "iso:country":"US",
    "sg:address":"336 Williams Point Blvd",
    "sg:city":"Cocoa",
    "sg:classifiers":[
        {
            "category":"Building & Trades",
            "subcategory":"Construction",
            "type":"Services"
        }
    ],
    "sg:phone":"+1 321 693 1986",
    "sg:postcode":"32927",
    "sg:province":"FL",
    "sg:tags":[
        "contractor"
    ],
    "wof:name":"Darren Gould",
    "wof:placetype":"venue"
},
  "geometry": {"coordinates":[-80.763025,28.451048],"type":"Point"}
}