{
  "type": "Feature",
  "properties": {
    "iso:country":"US",
    "sg:address":"180 Poinciana Blvd",
    "sg:city":"Destin",
    "sg:classifiers":[
        {
            "category":"Insurance",
            "subcategory":"Insurance Agent",
            "type":"Services"
        }
    ],
    "sg:phone":"+1 850 650 1900",
    "sg:postcode":"32550",
    "sg:province":"FL",
    "wof:name":"Ryland Fisher Agency",
    "wof:placetype":"venue"
},
  "geometry": {"coordinates":[-86.353532,30.376278],"type":"Point"}
}