{
  "type": "Feature",
  "properties": {
    "addr:full":"345 S Congress Ave Delray Beach FL 33445",
    "addr:housenumber":"345",
    "addr:postcode":"33445",
    "addr:street":"S Congress Ave",
    "iso:country":"US",
    "sg:address":"345 S Congress Ave",
    "sg:city":"Delray Beach",
    "sg:classifiers":[
        {
            "category":"Government",
            "subcategory":"Police Station",
            "type":"Public Place"
        }
    ],
    "sg:phone":"+1 561 274 1075",
    "sg:postcode":"33445",
    "sg:province":"FL",
    "sg:tags":[
        "sheriff"
    ],
    "wof:name":"Palm Beach Sheriff's Office",
    "wof:placetype":"venue"
},
  "geometry": {"coordinates":[-80.09353,26.454296],"type":"Point"}
}