{
  "type": "Feature",
  "properties": {
    "addr:full":"7967 NW 33rd St Doral FL 33122",
    "addr:housenumber":"7967",
    "addr:postcode":"33122",
    "addr:street":"Nw 33Rd St",
    "iso:country":"US",
    "sg:address":"7967 NW 33rd St",
    "sg:city":"Doral",
    "sg:classifiers":[
        {
            "category":"Wholesale",
            "subcategory":"Construction Materials",
            "type":"Manufacturing & Wholesale Goods"
        },
        {
            "category":"Wholesale",
            "subcategory":"Durable Goods & Equipment",
            "type":"Manufacturing & Wholesale Goods"
        }
    ],
    "sg:phone":"+1 305 592 4071",
    "sg:postcode":"33122",
    "sg:province":"FL",
    "sg:tags":[
        "bathroom",
        "ceramic",
        "importer",
        "piece"
    ],
    "wof:name":"Freixas Corp",
    "wof:placetype":"venue"
},
  "geometry": {"coordinates":[-80.32597,25.804417],"type":"Point"}
}