{
  "type": "Feature",
  "properties": {
    "iso:country":"US",
    "sg:address":"508 E Sagamore Ave",
    "sg:city":"Clewiston",
    "sg:classifiers":[
        {
            "category":"Freight",
            "type":"Transportation"
        }
    ],
    "sg:phone":"+1 863 983 9205",
    "sg:postcode":"33440",
    "sg:province":"FL",
    "sg:tags":[
        "commercial",
        "storage"
    ],
    "wof:name":"Secure Self Storage",
    "wof:placetype":"venue"
},
  "geometry": {"coordinates":[-80.926281,26.753301],"type":"Point"}
}