{
  "type": "Feature",
  "properties": {
    "iso:country":"US",
    "sg:address":"425 E Van Fleet Dr",
    "sg:city":"Bartow",
    "sg:classifiers":[
        {
            "category":"Retail",
            "subcategory":"Auto Rental",
            "type":"Services"
        }
    ],
    "sg:phone":"+1 863 533 0425",
    "sg:postcode":"33830",
    "sg:province":"FL",
    "sg:tags":[
        "renting",
        "automobile"
    ],
    "wof:name":"Bartow Ford Rental Co",
    "wof:placetype":"venue"
},
  "geometry": {"coordinates":[-81.840333,27.903941],"type":"Point"}
}