{
  "type": "Feature",
  "properties": {
    "iso:country":"US",
    "sg:address":"12 Victoria Ln",
    "sg:city":"Lake Placid",
    "sg:classifiers":[
        {
            "category":"Real Estate",
            "subcategory":"Real Estate Operator",
            "type":"Services"
        }
    ],
    "sg:phone":"+1 863 699 6017",
    "sg:postcode":"33852",
    "sg:province":"FL",
    "sg:tags":[
        "apartment"
    ],
    "wof:name":"M H C Management Inc",
    "wof:placetype":"venue"
},
  "geometry": {"coordinates":[-81.32369,27.203848],"type":"Point"}
}