{
  "type": "Feature",
  "properties": {
    "iso:country":"US",
    "sg:address":"2121 NW 58 Ter",
    "sg:city":"Gainesville",
    "sg:classifiers":[
        {
            "category":"Restaurant",
            "type":"Food & Drink"
        }
    ],
    "sg:phone":"+1 352 379 5700",
    "sg:postcode":"32605",
    "sg:province":"FL",
    "sg:tags":[
        "eating"
    ],
    "wof:name":"Quiznos Subs",
    "wof:placetype":"venue"
},
  "geometry": {"coordinates":[-82.405108,29.672207],"type":"Point"}
}