{
  "type": "Feature",
  "properties": {
    "addr:full":"38 Tara Lakes Dr E Boynton Beach FL 33436",
    "addr:housenumber":"38",
    "addr:postcode":"33436",
    "addr:street":"Tara Lakes Dr E",
    "iso:country":"US",
    "sg:address":"38 Tara Lakes Dr E",
    "sg:city":"Boynton Beach",
    "sg:classifiers":[
        {
            "category":"Building & Trades",
            "subcategory":"Cleaning & Sanitation",
            "type":"Services"
        }
    ],
    "sg:phone":"+1 561 364 0108",
    "sg:postcode":"33436",
    "sg:province":"FL",
    "sg:tags":[
        "janitor"
    ],
    "wof:name":"Terry L Golembiewski Cleaning",
    "wof:placetype":"venue"
},
  "geometry": {"coordinates":[-80.09355100000001,26.514255],"type":"Point"}
}