{
  "type": "Feature",
  "properties": {
    "addr:full":"4523 Bee Ridge Rd Sarasota FL 34233",
    "addr:housenumber":"4523",
    "addr:postcode":"34233",
    "addr:street":"Bee Ridge Rd",
    "iso:country":"US",
    "sg:address":"4523 Bee Ridge Rd",
    "sg:city":"Sarasota",
    "sg:classifiers":[
        {
            "category":"Shopping",
            "subcategory":"Clothing, Apparel, & Fashions",
            "type":"Retail Goods"
        }
    ],
    "sg:phone":"+1 941 379 3999",
    "sg:postcode":"34233",
    "sg:province":"FL",
    "sg:tags":[
        "lingerie"
    ],
    "wof:name":"Mystiques Of Sarasota",
    "wof:placetype":"venue"
},
  "geometry": {"coordinates":[-82.47903599999999,27.298814],"type":"Point"}
}