{
  "type": "Feature",
  "properties": {
    "iso:country":"US",
    "sg:address":"19058 NW 77th Pl",
    "sg:city":"Hialeah",
    "sg:classifiers":[
        {
            "category":"Retail",
            "subcategory":"Laundry & Dry Cleaning",
            "type":"Services"
        }
    ],
    "sg:phone":"+1 305 829 9596",
    "sg:postcode":"33015",
    "sg:province":"FL",
    "wof:name":"J and R Master Cleaning",
    "wof:placetype":"venue"
},
  "geometry": {"coordinates":[-80.327579,25.947641],"type":"Point"}
}