{
  "type": "Feature",
  "properties": {
    "addr:full":"19376 SW 123rd Ave Miami FL 33177",
    "addr:housenumber":"19376",
    "addr:postcode":"33177",
    "addr:street":"Sw 123Rd Ave",
    "iso:country":"US",
    "sg:address":"19376 SW 123rd Ave",
    "sg:city":"Miami",
    "sg:classifiers":[
        {
            "category":"Building & Trades",
            "subcategory":"Construction",
            "type":"Services"
        }
    ],
    "sg:phone":"+1 305 235 6673",
    "sg:postcode":"33177",
    "sg:province":"FL",
    "sg:tags":[
        "hanging",
        "contractor"
    ],
    "wof:name":"Hh Painting",
    "wof:placetype":"venue"
},
  "geometry": {"coordinates":[-80.391052,25.587597],"type":"Point"}
}