{
  "type": "Feature",
  "properties": {
    "iso:country":"US",
    "sg:address":"3841 Reid St",
    "sg:city":"Palatka",
    "sg:classifiers":[
        {
            "category":"Education",
            "subcategory":"Special Training",
            "type":"Public Place"
        }
    ],
    "sg:phone":"+1 386 329 3800",
    "sg:postcode":"32177",
    "sg:province":"FL",
    "sg:tags":[
        "consulting",
        "business"
    ],
    "wof:name":"Nefec",
    "wof:placetype":"venue"
},
  "geometry": {"coordinates":[-81.670214,29.658763],"type":"Point"}
}