{
  "type": "Feature",
  "properties": {
    "iso:country":"US",
    "sg:address":"2629 W 23rd St",
    "sg:city":"Panama City",
    "sg:classifiers":[
        {
            "category":"Insurance",
            "subcategory":"Insurance Agent",
            "type":"Services"
        }
    ],
    "sg:phone":"+1 850 784 1688",
    "sg:postcode":"32405",
    "sg:province":"FL",
    "wof:name":"Great Fla Insur of Panama Cy",
    "wof:placetype":"venue"
},
  "geometry": {"coordinates":[-85.69825400000001,30.189637],"type":"Point"}
}