{
  "type": "Feature",
  "properties": {
    "iso:country":"US",
    "sg:address":"1402 Emerald Lake St",
    "sg:city":"Clermont",
    "sg:classifiers":[
        {
            "category":"Personal",
            "subcategory":"Beauty Salon",
            "type":"Services"
        },
        {
            "category":"Personal",
            "subcategory":"Barber",
            "type":"Services"
        }
    ],
    "sg:phone":"+1 352 394 8874",
    "sg:postcode":"34711",
    "sg:province":"FL",
    "sg:tags":[
        "hair",
        "stylist"
    ],
    "sg:website":"http://metamorphous.intuitwebsites.com/",
    "wof:name":"Metamorphous Hair Salon",
    "wof:placetype":"venue"
},
  "geometry": {"coordinates":[-81.77584,28.551941],"type":"Point"}
}