{
  "type": "Feature",
  "properties": {
    "iso:country":"US",
    "sg:address":"1502 53rd St",
    "sg:city":"West Palm Beach",
    "sg:classifiers":[
        {
            "category":"Wholesale",
            "subcategory":"Furniture",
            "type":"Manufacturing & Wholesale Goods"
        }
    ],
    "sg:phone":"+1 561 389 8048",
    "sg:postcode":"33407",
    "sg:province":"FL",
    "wof:name":"Rafael R Cartaya",
    "wof:placetype":"venue"
},
  "geometry": {"coordinates":[-80.08172399999999,26.762591],"type":"Point"}
}