{
  "type": "Feature",
  "properties": {
    "iso:country":"US",
    "sg:address":"150 Amidon Ln",
    "sg:city":"Orlando",
    "sg:classifiers":[
        {
            "category":"Government",
            "subcategory":"Office",
            "type":"Public Place"
        }
    ],
    "sg:phone":"+1 407 850 5109",
    "sg:postcode":"32809",
    "sg:province":"FL",
    "wof:name":"Orange County Citizens' Comm",
    "wof:placetype":"venue"
},
  "geometry": {"coordinates":[-81.377735,28.461717],"type":"Point"}
}