{
  "type": "Feature",
  "properties": {
    "iso:country":"US",
    "sg:address":"240 31st St",
    "sg:city":"West Palm Beach",
    "sg:classifiers":[
        {
            "category":"Shopping",
            "subcategory":"Catalog Store",
            "type":"Retail Goods"
        }
    ],
    "sg:phone":"+1 561 843 8604",
    "sg:postcode":"33407",
    "sg:province":"FL",
    "sg:tags":[
        "mail",
        "house"
    ],
    "wof:name":"Bountiful Treasures Inc",
    "wof:placetype":"venue"
},
  "geometry": {"coordinates":[-80.052111,26.741395],"type":"Point"}
}