{
  "type": "Feature",
  "properties": {
    "addr:full":"1800 Corporate Blvd NW Boca Raton FL 33431",
    "addr:housenumber":"1800",
    "addr:postcode":"33431",
    "addr:street":"Corporate Blvd Nw",
    "iso:country":"US",
    "sg:address":"1800 Corporate Blvd NW",
    "sg:city":"Boca Raton",
    "sg:classifiers":[
        {
            "category":"Banks & Credit Unions",
            "subcategory":"Bank",
            "type":"Services"
        }
    ],
    "sg:phone":"+1 561 994 6800",
    "sg:postcode":"33431",
    "sg:province":"FL",
    "sg:website":"www.comerica.com",
    "wof:name":"Comerica Bank",
    "wof:placetype":"venue"
},
  "geometry": {"coordinates":[-80.122444,26.370708],"type":"Point"}
}