{
  "type": "Feature",
  "properties": {
    "addr:full":"1845 34th St Sarasota FL 34234",
    "addr:housenumber":"1845",
    "addr:postcode":"34234",
    "addr:street":"34Th St",
    "iso:country":"US",
    "sg:address":"1845 34th St",
    "sg:city":"Sarasota",
    "sg:classifiers":[
        {
            "category":"Government",
            "subcategory":"Office",
            "type":"Public Place"
        },
        {
            "category":"Recreation",
            "type":"Entertainment"
        }
    ],
    "sg:phone":"+1 941 316 1331",
    "sg:postcode":"34234",
    "sg:province":"FL",
    "sg:tags":[
        "executive",
        "hall",
        "auditorium"
    ],
    "wof:name":"Newtown Community Center",
    "wof:placetype":"venue"
},
  "geometry": {"coordinates":[-82.53369000000001,27.365717],"type":"Point"}
}