{
  "type": "Feature",
  "properties": {
    "addr:full":"1510 S Tuttle Ave Sarasota FL 34239",
    "addr:housenumber":"1510",
    "addr:postcode":"34239",
    "addr:street":"S Tuttle Ave",
    "iso:country":"US",
    "sg:address":"1510 S Tuttle Ave",
    "sg:city":"Sarasota",
    "sg:classifiers":[
        {
            "category":"Real Estate",
            "subcategory":"Real Estate Agent",
            "type":"Services"
        }
    ],
    "sg:phone":"+1 941 957 1301",
    "sg:postcode":"34239",
    "sg:province":"FL",
    "wof:name":"Smith & Assoc",
    "wof:placetype":"venue"
},
  "geometry": {"coordinates":[-82.514189,27.320568],"type":"Point"}
}