{
  "type": "Feature",
  "properties": {
    "iso:country":"US",
    "sg:address":"8084 SW 186th St",
    "sg:city":"Miami",
    "sg:classifiers":[
        {
            "category":"Communications",
            "subcategory":"Film & Video Production",
            "type":"Services"
        }
    ],
    "sg:phone":"+1 305 254 4126",
    "sg:postcode":"33157",
    "sg:province":"FL",
    "sg:tags":[
        "motion"
    ],
    "wof:name":"Sea View Productions Inc",
    "wof:placetype":"venue"
},
  "geometry": {"coordinates":[-80.32257199999999,25.594997],"type":"Point"}
}