{
  "type": "Feature",
  "properties": {
    "iso:country":"US",
    "sg:address":"2081 Squirrel Run",
    "sg:city":"Geneva",
    "sg:classifiers":[
        {
            "category":"Home & Garden",
            "subcategory":"Building Materials",
            "type":"Retail Goods"
        }
    ],
    "sg:phone":"+1 407 349 4940",
    "sg:postcode":"32732",
    "sg:province":"FL",
    "sg:tags":[
        "stone",
        "product"
    ],
    "wof:name":"Mark Rothermel",
    "wof:placetype":"venue"
},
  "geometry": {"coordinates":[-81.14634100000001,28.745931],"type":"Point"}
}