{
  "type": "Feature",
  "properties": {
    "iso:country":"US",
    "sg:address":"807 10th Ave W",
    "sg:city":"Palmetto",
    "sg:classifiers":[
        {
            "category":"Insurance",
            "subcategory":"Insurance Agent",
            "type":"Services"
        }
    ],
    "sg:phone":"+1 941 722 0564",
    "sg:postcode":"34221",
    "sg:province":"FL",
    "wof:name":"Cadwell Insurance Agency",
    "wof:placetype":"venue"
},
  "geometry": {"coordinates":[-82.57570800000001,27.519814],"type":"Point"}
}