{
  "type": "Feature",
  "properties": {
    "addr:full":"1000 Ponce de Leon Blvd Coral Gables FL 33134",
    "addr:housenumber":"1000",
    "addr:postcode":"33134",
    "addr:street":"Ponce De Leon Blvd",
    "iso:country":"US",
    "sg:address":"1000 Ponce de Leon Blvd",
    "sg:city":"Coral Gables",
    "sg:classifiers":[
        {
            "category":"Shopping",
            "subcategory":"Computers & Home Electronics",
            "type":"Retail Goods"
        }
    ],
    "sg:phone":"+1 305 529 6441",
    "sg:postcode":"33134",
    "sg:province":"FL",
    "sg:tags":[
        "system"
    ],
    "wof:name":"Automated Entertainment Syst",
    "wof:placetype":"venue"
},
  "geometry": {"coordinates":[-80.259063,25.761302],"type":"Point"}
}