{
  "type": "Feature",
  "properties": {
    "iso:country":"US",
    "sg:address":"2692 Forest Pkwy N",
    "sg:city":"Largo",
    "sg:classifiers":[
        {
            "category":"Real Estate",
            "subcategory":"Real Estate Services",
            "type":"Services"
        },
        {
            "category":"Real Estate",
            "subcategory":"Real Estate Agent",
            "type":"Services"
        }
    ],
    "sg:phone":"+1 727 539 6870",
    "sg:postcode":"33771",
    "sg:province":"FL",
    "sg:tags":[
        "management"
    ],
    "wof:name":"Wren Real Estate",
    "wof:placetype":"venue"
},
  "geometry": {"coordinates":[-82.759598,27.92334],"type":"Point"}
}