{
  "type": "Feature",
  "properties": {
    "iso:country":"US",
    "sg:address":"682 Mc Donnell Dr",
    "sg:city":"Tallahassee",
    "sg:classifiers":[
        {
            "category":"Manufacturing",
            "subcategory":"Musical Instruments",
            "type":"Manufacturing & Wholesale Goods"
        }
    ],
    "sg:phone":"+1 850 228 6960",
    "sg:postcode":"32310",
    "sg:province":"FL",
    "wof:name":"Coe Percussion",
    "wof:placetype":"venue"
},
  "geometry": {"coordinates":[-84.29276299999999,30.432644],"type":"Point"}
}