{
  "type": "Feature",
  "properties": {
    "addr:full":"255 Hilltop St Davenport FL 33837",
    "addr:housenumber":"255",
    "addr:postcode":"33837",
    "addr:street":"Hilltop St",
    "iso:country":"US",
    "sg:address":"255 Hilltop St",
    "sg:city":"Davenport",
    "sg:classifiers":[
        {
            "category":"Building & Trades",
            "subcategory":"Construction",
            "type":"Services"
        }
    ],
    "sg:phone":"+1 863 420 9019",
    "sg:postcode":"33837",
    "sg:province":"FL",
    "sg:tags":[
        "residential"
    ],
    "wof:name":"Capernaum Construction",
    "wof:placetype":"venue"
},
  "geometry": {"coordinates":[-81.613901,28.247074],"type":"Point"}
}