{
  "type": "Feature",
  "properties": {
    "iso:country":"US",
    "sg:address":"1875 S County Road 419",
    "sg:city":"Oviedo",
    "sg:classifiers":[
        {
            "category":"Cafe",
            "type":"Food & Drink"
        }
    ],
    "sg:menulink":"http://www.allmenus.com/fl/oviedo/33401-cafe-laura/menu/",
    "sg:phone":"+1 407 977 0010",
    "sg:postcode":"32766",
    "sg:province":"FL",
    "sg:tags":[
        "american"
    ],
    "wof:name":"Cafe Laura",
    "wof:placetype":"venue"
},
  "geometry": {"coordinates":[-81.129638,28.627736],"type":"Point"}
}