{
  "type": "Feature",
  "properties": {
    "iso:country":"US",
    "sg:address":"16838 SE 6 Ln",
    "sg:city":"Silver Springs",
    "sg:classifiers":[
        {
            "category":"Personal",
            "subcategory":"Adult",
            "type":"Services"
        }
    ],
    "sg:phone":"+1 352 625 0690",
    "sg:postcode":"34488",
    "sg:province":"FL",
    "wof:name":"Silk Rose Escorts",
    "wof:placetype":"venue"
},
  "geometry": {"coordinates":[-81.87473199999999,29.179809],"type":"Point"}
}