{
  "type": "Feature",
  "properties": {
    "iso:country":"US",
    "sg:address":"7201 N 9th Ave",
    "sg:city":"Pensacola",
    "sg:classifiers":[
        {
            "category":"Building & Trades",
            "subcategory":"Pest Control",
            "type":"Services"
        }
    ],
    "sg:phone":"+1 850 478 6289",
    "sg:postcode":"32504",
    "sg:province":"FL",
    "sg:tags":[
        "termite",
        "bee",
        "repellent",
        "mothproofing",
        "barriers",
        "removal",
        "bird"
    ],
    "sg:website":"http://www.bugoutwf.com",
    "wof:name":"Bug Out Service Of West Florida",
    "wof:placetype":"venue"
},
  "geometry": {"coordinates":[-87.184921,30.500111],"type":"Point"}
}