{
  "type": "Feature",
  "properties": {
    "iso:country":"US",
    "sg:address":"4840 SW 116th Pl",
    "sg:city":"Ocala",
    "sg:classifiers":[
        {
            "category":"Cinema",
            "subcategory":"Movie Rental",
            "type":"Entertainment"
        }
    ],
    "sg:phone":"+1 352 369 5155",
    "sg:postcode":"34476",
    "sg:province":"FL",
    "sg:tags":[
        "motion",
        "picture",
        "distributor",
        "film",
        "exchange"
    ],
    "wof:name":"Vergara Productions",
    "wof:placetype":"venue"
},
  "geometry": {"coordinates":[-82.2015,29.053709],"type":"Point"}
}