{
  "type": "Feature",
  "properties": {
    "iso:country":"US",
    "sg:address":"773 E Bay Ave",
    "sg:city":"Longwood",
    "sg:classifiers":[
        {
            "category":"Professional",
            "type":"Services"
        }
    ],
    "sg:phone":"+1 407 929 2137",
    "sg:postcode":"32750",
    "sg:province":"FL",
    "sg:tags":[
        "establishment"
    ],
    "wof:name":"Bruce Jordan & Assoc",
    "wof:placetype":"venue"
},
  "geometry": {"coordinates":[-81.333292,28.699621],"type":"Point"}
}