{
  "type": "Feature",
  "properties": {
    "addr:full":"4820 N Clark Ave Tampa FL 33614",
    "addr:housenumber":"4820",
    "addr:postcode":"33614",
    "addr:street":"N Clark Ave",
    "iso:country":"US",
    "sg:address":"4820 N Clark Ave",
    "sg:city":"Tampa",
    "sg:classifiers":[
        {
            "category":"Building & Trades",
            "subcategory":"Electrical",
            "type":"Services"
        }
    ],
    "sg:phone":"+1 813 876 4782",
    "sg:postcode":"33614",
    "sg:province":"FL",
    "sg:tags":[
        "electric",
        "contractor"
    ],
    "wof:name":"Delgado Electric Inc",
    "wof:placetype":"venue"
},
  "geometry": {"coordinates":[-82.5124,27.990947],"type":"Point"}
}