{
  "type": "Feature",
  "properties": {
    "iso:country":"US",
    "sg:address":"1165 Nelson St",
    "sg:city":"Dunedin",
    "sg:classifiers":[
        {
            "category":"Professional",
            "subcategory":"Accounting & Tax Preparation",
            "type":"Services"
        }
    ],
    "sg:phone":"+1 727 733 2030",
    "sg:postcode":"34698",
    "sg:province":"FL",
    "sg:tags":[
        "bookkeeping",
        "general"
    ],
    "wof:name":"Linda H Haen",
    "wof:placetype":"venue"
},
  "geometry": {"coordinates":[-82.77339000000001,28.045463],"type":"Point"}
}