{
  "type": "Feature",
  "properties": {
    "addr:full":"2000 Crawfordville Hwy B Crawfordville FL 32327",
    "addr:housenumber":"2000",
    "addr:postcode":"32327",
    "addr:street":"Crawfordville Hwy B",
    "iso:country":"US",
    "sg:address":"2000 Crawfordville Hwy B",
    "sg:city":"Crawfordville",
    "sg:classifiers":[
        {
            "category":"Shopping",
            "subcategory":"Clothing, Apparel, & Fashions",
            "type":"Retail Goods"
        }
    ],
    "sg:phone":"+1 850 926 6175",
    "sg:postcode":"32327",
    "sg:province":"FL",
    "sg:tags":[
        "apparel",
        "women's"
    ],
    "sg:website":"http://www.maurices.com",
    "wof:name":"maurices",
    "wof:placetype":"venue"
},
  "geometry": {"coordinates":[-84.362381,30.218874],"type":"Point"}
}