{
  "type": "Feature",
  "properties": {
    "iso:country":"US",
    "sg:address":"420 Wildwood Way",
    "sg:city":"Belleair",
    "sg:classifiers":[
        {
            "category":"Professional",
            "subcategory":"Business Services",
            "type":"Services"
        }
    ],
    "sg:phone":"+1 727 442 2848",
    "sg:postcode":"33756",
    "sg:province":"FL",
    "sg:tags":[
        "consultant",
        "coach"
    ],
    "wof:name":"Hub Consultant",
    "wof:placetype":"venue"
},
  "geometry": {"coordinates":[-82.801147,27.94356],"type":"Point"}
}