{
  "type": "Feature",
  "properties": {
    "addr:full":"7064 SW 158th Path Miami FL 33193",
    "addr:housenumber":"7064",
    "addr:postcode":"33193",
    "addr:street":"Sw 158Th Path",
    "iso:country":"US",
    "sg:address":"7064 SW 158th Path",
    "sg:city":"Miami",
    "sg:classifiers":[
        {
            "category":"Shopping",
            "subcategory":"Music",
            "type":"Retail Goods"
        }
    ],
    "sg:phone":"+1 305 485 4822",
    "sg:postcode":"33193",
    "sg:province":"FL",
    "sg:tags":[
        "compact",
        "record",
        "disc",
        "tape"
    ],
    "wof:name":"Music World",
    "wof:placetype":"venue"
},
  "geometry": {"coordinates":[-80.44976800000001,25.70037],"type":"Point"}
}