{
  "type": "Feature",
  "properties": {
    "addr:full":"1044 Lakeside Dr Apopka FL 32712",
    "addr:housenumber":"1044",
    "addr:postcode":"32712",
    "addr:street":"Lakeside Dr",
    "iso:country":"US",
    "sg:address":"1044 Lakeside Dr",
    "sg:city":"Apopka",
    "sg:classifiers":[
        {
            "category":"Social Services",
            "subcategory":"Child Care",
            "type":"Services"
        }
    ],
    "sg:phone":"+1 407 814 1399",
    "sg:postcode":"32712",
    "sg:province":"FL",
    "sg:tags":[
        "day"
    ],
    "wof:name":"Daydreams Child Dev Ctr",
    "wof:placetype":"venue"
},
  "geometry": {"coordinates":[-81.493049,28.712684],"type":"Point"}
}