{
  "type": "Feature",
  "properties": {
    "iso:country":"US",
    "sg:address":"6417 Pinecastle Blvd",
    "sg:city":"Orlando",
    "sg:classifiers":[
        {
            "category":"Wholesale",
            "subcategory":"Plants",
            "type":"Manufacturing & Wholesale Goods"
        }
    ],
    "sg:phone":"+1 407 852 1999",
    "sg:postcode":"32809",
    "sg:province":"FL",
    "sg:tags":[
        "florist"
    ],
    "wof:name":"Flower Market Intl",
    "wof:placetype":"venue"
},
  "geometry": {"coordinates":[-81.36884000000001,28.462579],"type":"Point"}
}