{
  "type": "Feature",
  "properties": {
    "addr:full":"1754 Funston St Hollywood FL 33020",
    "addr:housenumber":"1754",
    "addr:postcode":"33020",
    "addr:street":"Funston St",
    "iso:country":"US",
    "sg:address":"1754 Funston St",
    "sg:city":"Hollywood",
    "sg:classifiers":[
        {
            "category":"Building & Trades",
            "subcategory":"Equipment Rental",
            "type":"Services"
        }
    ],
    "sg:phone":"+1 954 923 6949",
    "sg:postcode":"33020",
    "sg:province":"FL",
    "sg:tags":[
        "cleaning"
    ],
    "wof:name":"Paulo & Margys Cleaning B",
    "wof:placetype":"venue"
},
  "geometry": {"coordinates":[-80.141717,26.002269],"type":"Point"}
}