{
  "type": "Feature",
  "properties": {
    "iso:country":"US",
    "sg:address":"500 N State Rd 7",
    "sg:city":"Royal Palm Beach",
    "sg:classifiers":[
        {
            "category":"Shopping",
            "subcategory":"Optical Goods",
            "type":"Retail Goods"
        }
    ],
    "sg:phone":"+1 561 753 6401",
    "sg:postcode":"33411",
    "sg:province":"FL",
    "wof:name":"B J's Optical",
    "wof:placetype":"venue"
},
  "geometry": {"coordinates":[-80.20193399999999,26.68658],"type":"Point"}
}