{
  "type": "Feature",
  "properties": {
    "addr:full":"16515 US Hwy 331 S Freeport FL 32439",
    "addr:postcode":"16515;32439",
    "addr:street":"Us Hwy 331 S",
    "iso:country":"US",
    "sg:address":"16515 US Hwy 331 S",
    "sg:city":"Freeport",
    "sg:classifiers":[
        {
            "category":"Real Estate",
            "subcategory":"Real Estate Agent",
            "type":"Services"
        }
    ],
    "sg:phone":"+1 850 835 1331",
    "sg:postcode":"32439",
    "sg:province":"FL",
    "wof:name":"30 A Realty Inc",
    "wof:placetype":"venue"
},
  "geometry": {"coordinates":[-86.128192,30.472909],"type":"Point"}
}