{
  "type": "Feature",
  "properties": {
    "iso:country":"US",
    "sg:address":"6015 Edgewater Dr",
    "sg:city":"Orlando",
    "sg:phone":"+1 407 295 2799",
    "sg:postcode":"32810",
    "sg:province":"FL",
    "wof:name":"Community Thrift Store",
    "wof:placetype":"venue"
},
  "geometry": {"coordinates":[-81.416518,28.611276],"type":"Point"}
}