{
  "type": "Feature",
  "properties": {
    "iso:country":"US",
    "sg:address":"4880 S Kirkman Rd",
    "sg:city":"Orlando",
    "sg:classifiers":[
        {
            "category":"Banks & Credit Unions",
            "subcategory":"Bank",
            "type":"Services"
        }
    ],
    "sg:phone":"+1 407 447 5520",
    "sg:postcode":"32811",
    "sg:province":"FL",
    "sg:tags":[
        "cashing",
        "check"
    ],
    "wof:name":"Fla Cash To Go",
    "wof:placetype":"venue"
},
  "geometry": {"coordinates":[-81.458997,28.491359],"type":"Point"}
}