{
  "type": "Feature",
  "properties": {
    "iso:country":"US",
    "sg:address":"1609 NW 14th Ave",
    "sg:city":"Miami",
    "sg:classifiers":[
        {
            "category":"Health Services",
            "subcategory":"Doctor",
            "type":"Services"
        },
        {
            "category":"Health Services",
            "subcategory":"Clinic",
            "type":"Services"
        },
        {
            "category":"Health Services",
            "subcategory":"Podiatrist",
            "type":"Services"
        },
        {
            "category":"Community Center",
            "type":"Public Place"
        }
    ],
    "sg:phone":"+1 305 324 0903",
    "sg:postcode":"33125",
    "sg:province":"FL",
    "sg:tags":[
        "physician",
        "medical",
        "surgeons",
        "surgeon"
    ],
    "wof:name":"Metzger Alan",
    "wof:placetype":"venue"
},
  "geometry": {"coordinates":[-80.2192,25.790501],"type":"Point"}
}