{
  "type": "Feature",
  "properties": {
    "addr:full":"820 Ballough Rd Daytona Beach FL 32114",
    "addr:housenumber":"820",
    "addr:postcode":"32114",
    "addr:street":"Ballough Rd",
    "iso:country":"US",
    "sg:address":"820 Ballough Rd",
    "sg:city":"Daytona Beach",
    "sg:classifiers":[
        {
            "category":"Retail",
            "subcategory":"Repair Shop",
            "type":"Services"
        }
    ],
    "sg:phone":"+1 386 252 9966",
    "sg:postcode":"32114",
    "sg:province":"FL",
    "sg:tags":[
        "marine",
        "boat"
    ],
    "wof:name":"SOS Marine",
    "wof:placetype":"venue"
},
  "geometry": {"coordinates":[-81.02399,29.22678],"type":"Point"}
}