{
  "type": "Feature",
  "properties": {
    "addr:full":"789 NE 5th St Crystal River FL 34429",
    "addr:housenumber":"789",
    "addr:postcode":"34429",
    "addr:street":"Ne 5Th St",
    "iso:country":"US",
    "sg:address":"789 NE 5th St",
    "sg:city":"Crystal River",
    "sg:classifiers":[
        {
            "category":"Restaurant",
            "type":"Food & Drink"
        }
    ],
    "sg:phone":"+1 352 795 0605",
    "sg:postcode":"34429",
    "sg:province":"FL",
    "wof:name":"Village Cafe",
    "wof:placetype":"venue"
},
  "geometry": {"coordinates":[-82.582531,28.898495],"type":"Point"}
}