{
  "type": "Feature",
  "properties": {
    "iso:country":"US",
    "sg:address":"35742 Lana Dr",
    "sg:city":"Dade City",
    "sg:classifiers":[
        {
            "category":"Manufacturing",
            "subcategory":"Apparel",
            "type":"Manufacturing & Wholesale Goods"
        }
    ],
    "sg:phone":"+1 352 523 2526",
    "sg:postcode":"33523",
    "sg:province":"FL",
    "sg:tags":[
        "sewing",
        "contractor"
    ],
    "wof:name":"Laura Garland's Creations",
    "wof:placetype":"venue"
},
  "geometry": {"coordinates":[-82.223742,28.403438],"type":"Point"}
}