{
  "type": "Feature",
  "properties": {
    "addr:full":"4211 N Federal Hwy Oakland Park FL 33308",
    "addr:housenumber":"4211",
    "addr:postcode":"33308",
    "addr:street":"N Federal Hwy",
    "iso:country":"US",
    "sg:address":"4211 N Federal Hwy",
    "sg:city":"Oakland Park",
    "sg:classifiers":[
        {
            "category":"Retail",
            "subcategory":"Repair Shop",
            "type":"Services"
        }
    ],
    "sg:phone":"+1 954 446 7111",
    "sg:postcode":"33308",
    "sg:province":"FL",
    "sg:tags":[
        "lock",
        "locksmith"
    ],
    "wof:name":"1 Day All Day Emergency Lksmth",
    "wof:placetype":"venue"
},
  "geometry": {"coordinates":[-80.119671,26.177174],"type":"Point"}
}