{
  "type": "Feature",
  "properties": {
    "iso:country":"US",
    "sg:address":"16942 Dixie Hwy",
    "sg:city":"Miami",
    "sg:classifiers":[
        {
            "category":"Personal",
            "subcategory":"Beauty Salon",
            "type":"Services"
        }
    ],
    "sg:phone":"+1 305 232 2625",
    "sg:postcode":"33157",
    "sg:province":"FL",
    "sg:tags":[
        "shop"
    ],
    "wof:name":"Latonia Beauty Salon",
    "wof:placetype":"venue"
},
  "geometry": {"coordinates":[-80.347904,25.612577],"type":"Point"}
}