{
  "type": "Feature",
  "properties": {
    "addr:full":"5221 Winter Garden Pkwy Fort Pierce FL 34951",
    "addr:housenumber":"5221",
    "addr:postcode":"34951",
    "addr:street":"Winter Garden Pkwy",
    "iso:country":"US",
    "sg:address":"5221 Winter Garden Pkwy",
    "sg:city":"Fort Pierce",
    "sg:classifiers":[
        {
            "category":"Building & Trades",
            "subcategory":"Electrical",
            "type":"Services"
        }
    ],
    "sg:phone":"+1 772 468 6464",
    "sg:postcode":"34951",
    "sg:province":"FL",
    "sg:tags":[
        "electric",
        "contractor"
    ],
    "wof:name":"R & B Electrical Inc",
    "wof:placetype":"venue"
},
  "geometry": {"coordinates":[-80.392549,27.530428],"type":"Point"}
}