{
  "type": "Feature",
  "properties": {
    "addr:full":"1900 Cardamon Dr New Port Richey FL 34655",
    "addr:postcode":"1900;34655",
    "addr:street":"Cardamon Dr",
    "iso:country":"US",
    "sg:address":"1900 Cardamon Dr",
    "sg:city":"New Port Richey",
    "sg:classifiers":[
        {
            "category":"Shopping",
            "subcategory":"Computers & Home Electronics",
            "type":"Retail Goods"
        }
    ],
    "sg:phone":"+1 727 375 9495",
    "sg:postcode":"34655",
    "sg:province":"FL",
    "wof:name":"Robert Dong",
    "wof:placetype":"venue"
},
  "geometry": {"coordinates":[-82.642831,28.187244],"type":"Point"}
}