{
  "type": "Feature",
  "properties": {
    "iso:country":"US",
    "sg:address":"5010 Parade St",
    "sg:city":"Tampa",
    "sg:classifiers":[
        {
            "category":"Communications",
            "type":"Services"
        }
    ],
    "sg:phone":"+1 813 541 5898",
    "sg:postcode":"33617",
    "sg:province":"FL",
    "sg:tags":[
        "consultant",
        "telecommunication"
    ],
    "wof:name":"Easy Connection Wireless",
    "wof:placetype":"venue"
},
  "geometry": {"coordinates":[-82.40151899999999,28.046357],"type":"Point"}
}