{
  "type": "Feature",
  "properties": {
    "iso:country":"US",
    "sg:address":"2120 NW 23rd Ct",
    "sg:city":"Miami",
    "sg:classifiers":[
        {
            "category":"Retail",
            "subcategory":"Auto Repair",
            "type":"Services"
        }
    ],
    "sg:phone":"+1 305 637 7466",
    "sg:postcode":"33142",
    "sg:province":"FL",
    "wof:name":"Jerry's Auto Works",
    "wof:placetype":"venue"
},
  "geometry": {"coordinates":[-80.234801,25.795927],"type":"Point"}
}