{
  "type": "Feature",
  "properties": {
    "addr:full":"884 S Dillard St Winter Garden FL 34787",
    "addr:housenumber":"884",
    "addr:postcode":"34787",
    "addr:street":"S Dillard St",
    "iso:country":"US",
    "sg:address":"884 S Dillard St",
    "sg:city":"Winter Garden",
    "sg:classifiers":[
        {
            "category":"Health Services",
            "subcategory":"Health Practitioner",
            "type":"Services"
        }
    ],
    "sg:phone":"+1 407 656 0505",
    "sg:postcode":"34787",
    "sg:province":"FL",
    "sg:tags":[
        "psychologist"
    ],
    "wof:name":"Universal Sleep Disorder Ctr",
    "wof:placetype":"venue"
},
  "geometry": {"coordinates":[-81.583585,28.554572],"type":"Point"}
}