{
  "type": "Feature",
  "properties": {
    "addr:full":"23614 Shining Star Dr Land O Lakes FL 34639",
    "addr:housenumber":"23614",
    "addr:postcode":"34639",
    "addr:street":"Shining Star Dr",
    "iso:country":"US",
    "sg:address":"23614 Shining Star Dr",
    "sg:city":"Land O Lakes",
    "sg:classifiers":[
        {
            "category":"Professional",
            "subcategory":"Management & Consulting",
            "type":"Services"
        }
    ],
    "sg:phone":"+1 813 996 6725",
    "sg:postcode":"34639",
    "sg:province":"FL",
    "sg:tags":[
        "consultant",
        "safety"
    ],
    "wof:name":"Herbert Traffic Safety Assoc",
    "wof:placetype":"venue"
},
  "geometry": {"coordinates":[-82.423659,28.229193],"type":"Point"}
}