{
  "type": "Feature",
  "properties": {
    "iso:country":"US",
    "sg:address":"6172 Knotty Pine Ct",
    "sg:city":"Port Orange",
    "sg:classifiers":[
        {
            "category":"Professional",
            "subcategory":"Business Services",
            "type":"Services"
        }
    ],
    "sg:phone":"+1 386 322 2190",
    "sg:postcode":"32127",
    "sg:province":"FL",
    "wof:name":"Mary A Malsch Inc",
    "wof:placetype":"venue"
},
  "geometry": {"coordinates":[-80.98541,29.085667],"type":"Point"}
}