{
  "type": "Feature",
  "properties": {
    "addr:full":"1336 E Cape Coral Pkwy Cape Coral FL 33904",
    "addr:housenumber":"1336",
    "addr:postcode":"33904",
    "addr:street":"E Cape Coral Pkwy",
    "iso:country":"US",
    "sg:address":"1336 E Cape Coral Pkwy",
    "sg:city":"Cape Coral",
    "sg:classifiers":[
        {
            "category":"Home & Garden",
            "subcategory":"Carpets & Floor Coverings",
            "type":"Retail Goods"
        }
    ],
    "sg:phone":"+1 239 541 9002",
    "sg:postcode":"33904",
    "sg:province":"FL",
    "sg:tags":[
        "material"
    ],
    "wof:name":"Dream Home Inspctn & Constr",
    "wof:placetype":"venue"
},
  "geometry": {"coordinates":[-81.947619,26.562475],"type":"Point"}
}