{
  "type": "Feature",
  "properties": {
    "addr:full":"733 Harbor Blvd Destin FL 32541",
    "addr:housenumber":"733",
    "addr:postcode":"32541",
    "addr:street":"Harbor Blvd",
    "iso:country":"US",
    "sg:address":"733 Harbor Blvd",
    "sg:city":"Destin",
    "sg:classifiers":[
        {
            "category":"Retail",
            "subcategory":"Storage",
            "type":"Services"
        }
    ],
    "sg:phone":"+1 850 312 8260",
    "sg:postcode":"32541",
    "sg:province":"FL",
    "sg:tags":[
        "automobile",
        "self",
        "commercial",
        "household"
    ],
    "sg:website":"http://national.citysearch.com/profile/external/604193582/destin_fl/a_storage_solution_of_destin.html?publisher=yellowpages&reference_id=1&placement=ypwebsitemip",
    "wof:name":"A Storage Solution of Destin",
    "wof:placetype":"venue"
},
  "geometry": {"coordinates":[-86.487831,30.390535],"type":"Point"}
}