{
  "type": "Feature",
  "properties": {
    "iso:country":"US",
    "sg:address":"2712 Lorraine Dr",
    "sg:city":"Leesburg",
    "sg:classifiers":[
        {
            "category":"Building & Trades",
            "subcategory":"Construction",
            "type":"Services"
        }
    ],
    "sg:phone":"+1 352 787 0574",
    "sg:postcode":"34748",
    "sg:province":"FL",
    "sg:tags":[
        "carpentry",
        "contractor"
    ],
    "wof:name":"Adkins Chrstopher Installation",
    "wof:placetype":"venue"
},
  "geometry": {"coordinates":[-81.90822799999999,28.815904],"type":"Point"}
}