{
  "type": "Feature",
  "properties": {
    "iso:country":"US",
    "sg:address":"1757 Oviedo Marketplace Blvd",
    "sg:city":"Oviedo",
    "sg:classifiers":[
        {
            "category":"Shopping",
            "subcategory":"Photographic Equipment",
            "type":"Retail Goods"
        }
    ],
    "sg:phone":"+1 407 977 7543",
    "sg:postcode":"32765",
    "sg:province":"FL",
    "sg:tags":[
        "photo",
        "camera",
        "supply"
    ],
    "wof:name":"Ritz Camera Centers Inc",
    "wof:placetype":"venue"
},
  "geometry": {"coordinates":[-81.23629200000001,28.659147],"type":"Point"}
}