{
  "type": "Feature",
  "properties": {
    "addr:full":"1498 Transmitter Rd Panama City FL 32401",
    "addr:housenumber":"1498",
    "addr:postcode":"32401",
    "addr:street":"Transmitter Rd",
    "iso:country":"US",
    "sg:address":"1498 Transmitter Rd",
    "sg:city":"Panama City",
    "sg:classifiers":[
        {
            "category":"Autos & Motor Vehicles",
            "subcategory":"Fuel & Gas Station",
            "type":"Retail Goods"
        }
    ],
    "sg:phone":"+1 850 784 2113",
    "sg:postcode":"32401",
    "sg:province":"FL",
    "sg:tags":[
        "oil"
    ],
    "wof:name":"Citgo Food Mart",
    "wof:placetype":"venue"
},
  "geometry": {"coordinates":[-85.60781,30.174858],"type":"Point"}
}