{
  "type": "Feature",
  "properties": {
    "iso:country":"US",
    "sg:address":"12905 Brookcrest Pl",
    "sg:city":"Riverview",
    "sg:classifiers":[
        {
            "category":"Professional",
            "subcategory":"Art Services",
            "type":"Services"
        }
    ],
    "sg:phone":"+1 813 871 0280",
    "sg:postcode":"33578",
    "sg:province":"FL",
    "sg:tags":[
        "interior",
        "designer",
        "decorator"
    ],
    "wof:name":"Dones Cabinetry & Remodeling, Inc.",
    "wof:placetype":"venue"
},
  "geometry": {"coordinates":[-82.345443,27.802627],"type":"Point"}
}