{
  "type": "Feature",
  "properties": {
    "iso:country":"US",
    "sg:address":"3828 Colony Cove Trl",
    "sg:city":"Jacksonville",
    "sg:classifiers":[
        {
            "category":"Real Estate",
            "subcategory":"Real Estate Agent",
            "type":"Services"
        }
    ],
    "sg:phone":"+1 904 743 0999",
    "sg:postcode":"32277",
    "sg:province":"FL",
    "wof:name":"Aubrey P Crites PA",
    "wof:placetype":"venue"
},
  "geometry": {"coordinates":[-81.572068,30.372324],"type":"Point"}
}