{
  "type": "Feature",
  "properties": {
    "iso:country":"US",
    "sg:address":"224 Country Club Dr",
    "sg:city":"Titusville",
    "sg:classifiers":[
        {
            "category":"Professional",
            "subcategory":"Business Services",
            "type":"Services"
        }
    ],
    "sg:phone":"+1 321 268 4022",
    "sg:postcode":"32780",
    "sg:province":"FL",
    "sg:tags":[
        "paralegal"
    ],
    "wof:name":"Non-Lawyer Clinic",
    "wof:placetype":"venue"
},
  "geometry": {"coordinates":[-80.803877,28.576651],"type":"Point"}
}