{
  "type": "Feature",
  "properties": {
    "addr:full":"1460 Pinehurst Dr Spring Hill FL 34606",
    "addr:housenumber":"1460",
    "addr:postcode":"34606",
    "addr:street":"Pinehurst Dr",
    "iso:country":"US",
    "sg:address":"1460 Pinehurst Dr",
    "sg:city":"Spring Hill",
    "sg:classifiers":[
        {
            "category":"Shopping",
            "subcategory":"Department Store",
            "type":"Retail Goods"
        }
    ],
    "sg:phone":"+1 352 683 0674",
    "sg:postcode":"34606",
    "sg:province":"FL",
    "sg:tags":[
        "shop"
    ],
    "wof:name":"Beall's Outlet",
    "wof:placetype":"venue"
},
  "geometry": {"coordinates":[-82.625934,28.460048],"type":"Point"}
}