{
  "type": "Feature",
  "properties": {
    "addr:full":"11380 Prosperity Farms Rd Palm Beach Gardens FL 33410",
    "addr:housenumber":"11380",
    "addr:postcode":"33410",
    "addr:street":"Prosperity Farms Rd",
    "iso:country":"US",
    "sg:address":"11380 Prosperity Farms Rd",
    "sg:city":"Palm Beach Gardens",
    "sg:classifiers":[
        {
            "category":"Professional",
            "subcategory":"Computer Services",
            "type":"Services"
        }
    ],
    "sg:phone":"+1 561 747 6308",
    "sg:postcode":"33410",
    "sg:province":"FL",
    "sg:tags":[
        "related"
    ],
    "wof:name":"Palm Beach Internet Consulting",
    "wof:placetype":"venue"
},
  "geometry": {"coordinates":[-80.07209899999999,26.8441],"type":"Point"}
}