{
  "type": "Feature",
  "properties": {
    "iso:country":"US",
    "sg:address":"2815 Broadway",
    "sg:city":"Riviera Beach",
    "sg:classifiers":[
        {
            "category":"Shopping",
            "subcategory":"Computers & Home Electronics",
            "type":"Retail Goods"
        }
    ],
    "sg:phone":"+1 561 844 0991",
    "sg:postcode":"33404",
    "sg:province":"FL",
    "sg:tags":[
        "software"
    ],
    "wof:name":"Sungrazer Inc",
    "wof:placetype":"venue"
},
  "geometry": {"coordinates":[-80.05482000000001,26.786089],"type":"Point"}
}