{
  "type": "Feature",
  "properties": {
    "iso:country":"US",
    "sg:address":"9906 Maple St",
    "sg:city":"Gibsonton",
    "sg:classifiers":[
        {
            "category":"Home & Garden",
            "subcategory":"Garden Supply",
            "type":"Retail Goods"
        }
    ],
    "sg:phone":"+1 813 677 5327",
    "sg:postcode":"33534",
    "sg:province":"FL",
    "sg:tags":[
        "nurseryman"
    ],
    "wof:name":"Pride Aquatic Plants",
    "wof:placetype":"venue"
},
  "geometry": {"coordinates":[-82.375298,27.853302],"type":"Point"}
}