{
  "type": "Feature",
  "properties": {
    "addr:full":"145 Sea Dunes Dr Melbourne Beach FL 32951",
    "addr:housenumber":"145",
    "addr:postcode":"32951",
    "addr:street":"Sea Dunes Dr",
    "iso:country":"US",
    "sg:address":"145 Sea Dunes Dr",
    "sg:city":"Melbourne Beach",
    "sg:classifiers":[
        {
            "category":"Organizations",
            "subcategory":"Community Association",
            "type":"Services"
        }
    ],
    "sg:phone":"+1 321 676 0893",
    "sg:postcode":"32951",
    "sg:province":"FL",
    "wof:name":"Sea Dns Dr Snst Pt Prpty Ownrs",
    "wof:placetype":"venue"
},
  "geometry": {"coordinates":[-80.51629699999999,27.974957],"type":"Point"}
}