{
  "type": "Feature",
  "properties": {
    "iso:country":"US",
    "sg:address":"100 W Indiantown Rd",
    "sg:city":"Jupiter",
    "sg:classifiers":[
        {
            "category":"Health Services",
            "subcategory":"Chiropractor",
            "type":"Services"
        }
    ],
    "sg:phone":"+1 561 575 4400",
    "sg:postcode":"33458",
    "sg:province":"FL",
    "sg:tags":[
        "chiropractic"
    ],
    "sg:website":"http://www.epterchiropractic.com",
    "wof:name":"Epter, Jack L Dc Pa",
    "wof:placetype":"venue"
},
  "geometry": {"coordinates":[-80.094109,26.934071],"type":"Point"}
}