{
  "type": "Feature",
  "properties": {
    "iso:country":"US",
    "sg:address":"2049 Americana Blvd",
    "sg:city":"Orlando",
    "sg:classifiers":[
        {
            "category":"Personal",
            "subcategory":"Beauty Salon",
            "type":"Services"
        }
    ],
    "sg:phone":"+1 407 859 2933",
    "sg:postcode":"32839",
    "sg:province":"FL",
    "wof:name":"Lookin Good Hair Fashion",
    "wof:placetype":"venue"
},
  "geometry": {"coordinates":[-81.40858900000001,28.487038],"type":"Point"}
}