{
  "type": "Feature",
  "properties": {
    "addr:full":"12414 Chickasaw Trl Largo FL 33774",
    "addr:housenumber":"12414",
    "addr:postcode":"33774",
    "addr:street":"Chickasaw Trl",
    "iso:country":"US",
    "sg:address":"12414 Chickasaw Trl",
    "sg:city":"Largo",
    "sg:classifiers":[
        {
            "category":"Building & Trades",
            "subcategory":"Construction",
            "type":"Services"
        }
    ],
    "sg:phone":"+1 727 517 7933",
    "sg:postcode":"33774",
    "sg:province":"FL",
    "sg:tags":[
        "painter"
    ],
    "wof:name":"Curb Appeal Property Imprvmnts",
    "wof:placetype":"venue"
},
  "geometry": {"coordinates":[-82.83604699999999,27.88563],"type":"Point"}
}