{
  "type": "Feature",
  "properties": {
    "iso:country":"US",
    "sg:address":"1098 W 66th St",
    "sg:city":"Hialeah",
    "sg:classifiers":[
        {
            "category":"Professional",
            "subcategory":"Business Services",
            "type":"Services"
        }
    ],
    "sg:phone":"+1 305 556 0885",
    "sg:postcode":"33012",
    "sg:province":"FL",
    "sg:tags":[
        "security",
        "system"
    ],
    "wof:name":"Fox Hollow Inc",
    "wof:placetype":"venue"
},
  "geometry": {"coordinates":[-80.301807,25.882783],"type":"Point"}
}