{
  "type": "Feature",
  "properties": {
    "iso:country":"US",
    "sg:address":"1807 Main St",
    "sg:city":"Valrico",
    "sg:classifiers":[
        {
            "category":"Insurance",
            "subcategory":"Insurance Agent",
            "type":"Services"
        }
    ],
    "sg:phone":"+1 813 681 2734",
    "sg:postcode":"33594",
    "sg:province":"FL",
    "wof:name":"Charles Talley Insurance Inc",
    "wof:placetype":"venue"
},
  "geometry": {"coordinates":[-82.257949,27.946303],"type":"Point"}
}