{
  "type": "Feature",
  "properties": {
    "iso:country":"US",
    "sg:address":"2321 Laurel Ln",
    "sg:city":"Orange Park",
    "sg:classifiers":[
        {
            "category":"Building & Trades",
            "subcategory":"Construction",
            "type":"Services"
        }
    ],
    "sg:phone":"+1 904 269 2704",
    "sg:postcode":"32073",
    "sg:province":"FL",
    "sg:tags":[
        "resurfacing",
        "laying",
        "refinishing",
        "floor"
    ],
    "wof:name":"Floor Prep Inc",
    "wof:placetype":"venue"
},
  "geometry": {"coordinates":[-81.703345,30.160604],"type":"Point"}
}