{
  "type": "Feature",
  "properties": {
    "addr:full":"747 Bon Air St Lakeland FL 33805",
    "addr:housenumber":"747",
    "addr:postcode":"33805",
    "addr:street":"Bon Air St",
    "iso:country":"US",
    "sg:address":"747 Bon Air St",
    "sg:city":"Lakeland",
    "sg:classifiers":[
        {
            "category":"Health Services",
            "subcategory":"Nursing And Care Facility",
            "type":"Services"
        }
    ],
    "sg:phone":"+1 863 688 1196",
    "sg:postcode":"33805",
    "sg:province":"FL",
    "sg:tags":[
        "home",
        "retirement",
        "community"
    ],
    "wof:name":"Tender Loving Care Retirement",
    "wof:placetype":"venue"
},
  "geometry": {"coordinates":[-81.95014999999999,28.056799],"type":"Point"}
}