{
  "type": "Feature",
  "properties": {
    "iso:country":"US",
    "sg:address":"994 E Michigan St",
    "sg:city":"Orlando",
    "sg:classifiers":[
        {
            "category":"Shopping",
            "subcategory":"Bicycles & Sporting Goods",
            "type":"Retail Goods"
        }
    ],
    "sg:phone":"+1 407 481 0805",
    "sg:postcode":"32806",
    "sg:province":"FL",
    "wof:name":"Basketball Buffay Inc",
    "wof:placetype":"venue"
},
  "geometry": {"coordinates":[-81.36520899999999,28.512996],"type":"Point"}
}