{
  "type": "Feature",
  "properties": {
    "addr:full":"1817 Holbrook Rd NW Palm Bay FL 32907",
    "addr:housenumber":"1817",
    "addr:postcode":"32907",
    "addr:street":"Holbrook Rd Nw",
    "iso:country":"US",
    "sg:address":"1817 Holbrook Rd NW",
    "sg:city":"Palm Bay",
    "sg:classifiers":[
        {
            "category":"Real Estate",
            "subcategory":"Real Estate Agent",
            "type":"Services"
        }
    ],
    "sg:phone":"+1 321 676 4118",
    "sg:postcode":"32907",
    "sg:province":"FL",
    "wof:name":"Access One",
    "wof:placetype":"venue"
},
  "geometry": {"coordinates":[-80.724136,28.007017],"type":"Point"}
}