{
  "type": "Feature",
  "properties": {
    "iso:country":"US",
    "sg:address":"699 Drew St",
    "sg:city":"Clearwater",
    "sg:classifiers":[
        {
            "category":"Shopping",
            "subcategory":"Used Merchandise",
            "type":"Retail Goods"
        }
    ],
    "sg:phone":"+1 727 298 8889",
    "sg:postcode":"33755",
    "sg:province":"FL",
    "wof:name":"A M Distributors",
    "wof:placetype":"venue"
},
  "geometry": {"coordinates":[-82.798241,27.968088],"type":"Point"}
}