{
  "type": "Feature",
  "properties": {
    "iso:country":"US",
    "sg:address":"8270 SW 27th Ter",
    "sg:city":"Miami",
    "sg:classifiers":[
        {
            "category":"Professional",
            "subcategory":"Computer Services",
            "type":"Services"
        }
    ],
    "sg:phone":"+1 305 323 4173",
    "sg:postcode":"33155",
    "sg:province":"FL",
    "wof:name":"Mr Flag Solutions",
    "wof:placetype":"venue"
},
  "geometry": {"coordinates":[-80.330865,25.744536],"type":"Point"}
}