{
  "type": "Feature",
  "properties": {
    "addr:full":"721 NW Sharpe St Port Saint Lucie FL 34983",
    "addr:housenumber":"721",
    "addr:postcode":"34983",
    "addr:street":"Nw Sharpe St",
    "iso:country":"US",
    "sg:address":"721 NW Sharpe St",
    "sg:city":"Port Saint Lucie",
    "sg:classifiers":[
        {
            "category":"Professional",
            "subcategory":"Management & Consulting",
            "type":"Services"
        }
    ],
    "sg:phone":"+1 772 878 1079",
    "sg:postcode":"34983",
    "sg:province":"FL",
    "sg:tags":[
        "retail",
        "direct",
        "sales"
    ],
    "wof:name":"Sherri Wolfe",
    "wof:placetype":"venue"
},
  "geometry": {"coordinates":[-80.36766900000001,27.336813],"type":"Point"}
}