{
  "type": "Feature",
  "properties": {
    "addr:full":"2010 Lake Dr Casselberry FL 32707",
    "addr:housenumber":"2010",
    "addr:postcode":"32707",
    "addr:street":"Lake Dr",
    "iso:country":"US",
    "sg:address":"2010 Lake Dr",
    "sg:city":"Casselberry",
    "sg:classifiers":[
        {
            "category":"Home & Garden",
            "subcategory":"Garden Supply",
            "type":"Retail Goods"
        }
    ],
    "sg:phone":"+1 407 695 3247",
    "sg:postcode":"32707",
    "sg:province":"FL",
    "sg:tags":[
        "nursery",
        "gardening"
    ],
    "wof:name":"South Seminole Farm & Nursery",
    "wof:placetype":"venue"
},
  "geometry": {"coordinates":[-81.289117,28.669825],"type":"Point"}
}