{
  "type": "Feature",
  "properties": {
    "addr:full":"3620 1st St Bradenton FL 34208",
    "addr:housenumber":"3620",
    "addr:postcode":"34208",
    "addr:street":"1St St",
    "iso:country":"US",
    "sg:address":"3620 1st St",
    "sg:city":"Bradenton",
    "sg:classifiers":[
        {
            "category":"Shopping",
            "subcategory":"Clothing, Apparel, & Fashions",
            "type":"Retail Goods"
        }
    ],
    "sg:phone":"+1 941 750 0400",
    "sg:postcode":"34208",
    "sg:province":"FL",
    "sg:tags":[
        "shop",
        "consignment"
    ],
    "wof:name":"Shoppers Bazaar LLC",
    "wof:placetype":"venue"
},
  "geometry": {"coordinates":[-82.56298700000001,27.466795],"type":"Point"}
}