{
  "type": "Feature",
  "properties": {
    "iso:country":"US",
    "sg:address":"1826 Ponce de Leon Blvd",
    "sg:city":"Miami",
    "sg:classifiers":[
        {
            "category":"Insurance",
            "subcategory":"Title Insurance",
            "type":"Services"
        }
    ],
    "sg:phone":"+1 305 444 3737",
    "sg:postcode":"33134",
    "sg:province":"FL",
    "sg:tags":[
        "agency",
        "real estate"
    ],
    "wof:name":"Ewm",
    "wof:placetype":"venue"
},
  "geometry": {"coordinates":[-80.258911,25.755382],"type":"Point"}
}