{
  "type": "Feature",
  "properties": {
    "iso:country":"US",
    "sg:address":"1111 Brickell Ave",
    "sg:city":"Miami",
    "sg:classifiers":[
        {
            "category":"Utilities",
            "subcategory":"Telephone",
            "type":"Services"
        },
        {
            "category":"Professional",
            "subcategory":"Management & Consulting",
            "type":"Services"
        }
    ],
    "sg:phone":"+1 305 416 4301",
    "sg:postcode":"33131",
    "sg:province":"FL",
    "sg:tags":[
        "telecommunication"
    ],
    "wof:name":"Telecom Argentina Usa Inc",
    "wof:placetype":"venue"
},
  "geometry": {"coordinates":[-80.191732,25.762262],"type":"Point"}
}