{
  "type": "Feature",
  "properties": {
    "addr:full":"3521 S Michigan Blvd Homosassa FL 34448",
    "addr:housenumber":"3521",
    "addr:postcode":"34448",
    "addr:street":"S Michigan Blvd",
    "iso:country":"US",
    "sg:address":"3521 S Michigan Blvd",
    "sg:city":"Homosassa",
    "sg:classifiers":[
        {
            "category":"Social Services",
            "subcategory":"Child Care",
            "type":"Services"
        }
    ],
    "sg:phone":"+1 352 628 3719",
    "sg:postcode":"34448",
    "sg:province":"FL",
    "sg:tags":[
        "day"
    ],
    "wof:name":"Precious Cargo Pre-School Inc",
    "wof:placetype":"venue"
},
  "geometry": {"coordinates":[-82.568901,28.810347],"type":"Point"}
}