{
  "type": "Feature",
  "properties": {
    "addr:full":"24036 Adair Ave Sorrento FL 32776",
    "addr:postcode":"24036;32776",
    "addr:street":"Adair Ave",
    "iso:country":"US",
    "sg:address":"24036 Adair Ave",
    "sg:city":"Sorrento",
    "sg:classifiers":[
        {
            "category":"Manufacturing",
            "subcategory":"Paper Products",
            "type":"Manufacturing & Wholesale Goods"
        }
    ],
    "sg:phone":"+1 352 735 5145",
    "sg:postcode":"32776",
    "sg:province":"FL",
    "sg:tags":[
        "bamboo"
    ],
    "wof:name":"Vanessa E Perry",
    "wof:placetype":"venue"
},
  "geometry": {"coordinates":[-81.559392,28.791446],"type":"Point"}
}