{
  "type": "Feature",
  "properties": {
    "iso:country":"US",
    "sg:address":"13254 73rd St N",
    "sg:city":"West Palm Beach",
    "sg:classifiers":[
        {
            "category":"Professional",
            "subcategory":"Research",
            "type":"Services"
        }
    ],
    "sg:phone":"+1 561 514 1122",
    "sg:postcode":"33412",
    "sg:province":"FL",
    "wof:name":"Precision Mapping & Research",
    "wof:placetype":"venue"
},
  "geometry": {"coordinates":[-80.24972099999999,26.784519],"type":"Point"}
}