{
  "type": "Feature",
  "properties": {
    "iso:country":"US",
    "sg:address":"1208 N Fort Harrison Ave",
    "sg:city":"Clearwater",
    "sg:classifiers":[
        {
            "category":"Food & Beverages",
            "subcategory":"Groceries & Convenience Stores",
            "type":"Retail Goods"
        }
    ],
    "sg:phone":"+1 727 449 9609",
    "sg:postcode":"33755",
    "sg:province":"FL",
    "wof:name":"Smart Stop Minimart Inc",
    "wof:placetype":"venue"
},
  "geometry": {"coordinates":[-82.797791,27.978755],"type":"Point"}
}