{
  "type": "Feature",
  "properties": {
    "iso:country":"US",
    "sg:address":"2 S Hopkins Ave",
    "sg:city":"Titusville",
    "sg:classifiers":[
        {
            "category":"Food & Beverages",
            "subcategory":"Groceries & Convenience Stores",
            "type":"Retail Goods"
        }
    ],
    "sg:phone":"+1 321 269 2031",
    "sg:postcode":"32796",
    "sg:province":"FL",
    "wof:name":"7-Eleven",
    "wof:placetype":"venue"
},
  "geometry": {"coordinates":[-80.808269,28.614606],"type":"Point"}
}