{
  "type": "Feature",
  "properties": {
    "addr:full":"24191 Suellen Dr Brooksville FL 34601",
    "addr:postcode":"24191;34601",
    "addr:street":"Suellen Dr",
    "iso:country":"US",
    "sg:address":"24191 Suellen Dr",
    "sg:city":"Brooksville",
    "sg:classifiers":[
        {
            "category":"Retail",
            "subcategory":"Animal Services",
            "type":"Services"
        }
    ],
    "sg:phone":"+1 352 796 1809",
    "sg:postcode":"34601",
    "sg:province":"FL",
    "wof:name":"Rosebrook Inc",
    "wof:placetype":"venue"
},
  "geometry": {"coordinates":[-82.33903100000001,28.570681],"type":"Point"}
}