{
  "type": "Feature",
  "properties": {
    "iso:country":"US",
    "sg:address":"40409 Otis Allen Rd",
    "sg:city":"Zephyrhills",
    "sg:classifiers":[
        {
            "category":"Wholesale",
            "subcategory":"Non-durable Goods",
            "type":"Manufacturing & Wholesale Goods"
        }
    ],
    "sg:phone":"+1 352 567 7117",
    "sg:postcode":"33540",
    "sg:province":"FL",
    "sg:tags":[
        "blacksmith",
        "shop",
        "supply"
    ],
    "wof:name":"Bar-K Blacksmith Supply",
    "wof:placetype":"venue"
},
  "geometry": {"coordinates":[-82.14757899999999,28.273625],"type":"Point"}
}