{
  "type": "Feature",
  "properties": {
    "addr:full":"2401 Wellington Blvd Winter Park FL 32789",
    "addr:housenumber":"2401",
    "addr:postcode":"32789",
    "addr:street":"Wellington Blvd",
    "iso:country":"US",
    "sg:address":"2401 Wellington Blvd",
    "sg:city":"Winter Park",
    "sg:classifiers":[
        {
            "category":"Education",
            "subcategory":"School",
            "type":"Public Place"
        }
    ],
    "sg:phone":"+1 407 623 1438",
    "sg:postcode":"32789",
    "sg:province":"FL",
    "sg:tags":[
        "high",
        "middle",
        "elementary"
    ],
    "wof:name":"Schools-Public Orange County",
    "wof:placetype":"venue"
},
  "geometry": {"coordinates":[-81.382093,28.595087],"type":"Point"}
}