{
  "type": "Feature",
  "properties": {
    "iso:country":"US",
    "sg:address":"2017 Clinch Dr",
    "sg:city":"Fernandina Beach",
    "sg:classifiers":[
        {
            "category":"Building & Trades",
            "subcategory":"Construction",
            "type":"Services"
        }
    ],
    "sg:phone":"+1 904 261 7550",
    "sg:postcode":"32034",
    "sg:province":"FL",
    "sg:tags":[
        "cabinet",
        "carpentry",
        "maker",
        "contractor"
    ],
    "wof:name":"Mo's Cabinets Countertops & Mr",
    "wof:placetype":"venue"
},
  "geometry": {"coordinates":[-81.46280899999999,30.63706],"type":"Point"}
}