{
  "type": "Feature",
  "properties": {
    "iso:country":"US",
    "sg:address":"919 Tyrone Blvd N",
    "sg:city":"Saint Petersburg",
    "sg:classifiers":[
        {
            "category":"Travel",
            "subcategory":"Travel Agent",
            "type":"Entertainment"
        }
    ],
    "sg:phone":"+1 727 347 1600",
    "sg:postcode":"33710",
    "sg:province":"FL",
    "sg:tags":[
        "agency"
    ],
    "wof:name":"Travel Is Fun",
    "wof:placetype":"venue"
},
  "geometry": {"coordinates":[-82.71541499999999,27.782039],"type":"Point"}
}