{
  "type": "Feature",
  "properties": {
    "addr:full":"1457 Applewood Way Tallahassee FL 32312",
    "addr:housenumber":"1457",
    "addr:postcode":"32312",
    "addr:street":"Applewood Way",
    "iso:country":"US",
    "sg:address":"1457 Applewood Way",
    "sg:city":"Tallahassee",
    "sg:classifiers":[
        {
            "category":"Building & Trades",
            "subcategory":"Cleaning & Sanitation",
            "type":"Services"
        }
    ],
    "sg:phone":"+1 850 668 0631",
    "sg:postcode":"32312",
    "sg:province":"FL",
    "sg:tags":[
        "maintenance"
    ],
    "wof:name":"Harveys Cleaning & Janitorial",
    "wof:placetype":"venue"
},
  "geometry": {"coordinates":[-84.25083600000001,30.567239],"type":"Point"}
}