{
  "type": "Feature",
  "properties": {
    "iso:country":"US",
    "sg:address":"2100 NW 107th St",
    "sg:city":"Miami",
    "sg:classifiers":[
        {
            "category":"Social Services",
            "subcategory":"Adult Care",
            "type":"Services"
        }
    ],
    "sg:phone":"+1 305 406 9708",
    "sg:postcode":"33167",
    "sg:province":"FL",
    "sg:tags":[
        "centers-adult",
        "day"
    ],
    "wof:name":"Baymar Playing Learning",
    "wof:placetype":"venue"
},
  "geometry": {"coordinates":[-80.233391,25.872259],"type":"Point"}
}