{
  "type": "Feature",
  "properties": {
    "iso:country":"US",
    "sg:address":"11716 102nd Ter",
    "sg:city":"Live Oak",
    "sg:classifiers":[
        {
            "category":"Manufacturing",
            "subcategory":"Tools & Machinery",
            "type":"Manufacturing & Wholesale Goods"
        }
    ],
    "sg:phone":"+1 386 364 1030",
    "sg:postcode":"32060",
    "sg:province":"FL",
    "sg:tags":[
        "machine",
        "shop"
    ],
    "sg:website":"www.ascentgear.com",
    "wof:name":"Ascent Precision Gear Inc",
    "wof:placetype":"venue"
},
  "geometry": {"coordinates":[-82.98874499999999,30.264327],"type":"Point"}
}