{
  "type": "Feature",
  "properties": {
    "iso:country":"US",
    "sg:address":"4140 Park Ave",
    "sg:city":"Miami",
    "sg:classifiers":[
        {
            "category":"Banks & Credit Unions",
            "subcategory":"Financial Services",
            "type":"Services"
        },
        {
            "category":"Professional",
            "subcategory":"Business Services",
            "type":"Services"
        }
    ],
    "sg:phone":"+1 305 667 1513",
    "sg:postcode":"33133",
    "sg:province":"FL",
    "sg:tags":[
        "management"
    ],
    "wof:name":"York Asset Management, Inc.",
    "wof:placetype":"venue"
},
  "geometry": {"coordinates":[-80.260096,25.714132],"type":"Point"}
}