{
  "type": "Feature",
  "properties": {
    "iso:country":"US",
    "sg:address":"2813 SW 33rd Ter",
    "sg:city":"Cape Coral",
    "sg:classifiers":[
        {
            "category":"Professional",
            "type":"Services"
        }
    ],
    "sg:phone":"+1 239 542 6104",
    "sg:postcode":"33914",
    "sg:province":"FL",
    "wof:name":"Captain Gary A Fellows",
    "wof:placetype":"venue"
},
  "geometry": {"coordinates":[-82.03430400000001,26.589892],"type":"Point"}
}