{
  "type": "Feature",
  "properties": {
    "iso:country":"US",
    "sg:address":"1425 NE 163rd St",
    "sg:city":"Miami",
    "sg:classifiers":[
        {
            "category":"Restaurant",
            "type":"Food & Drink"
        }
    ],
    "sg:menulink":"http://www.allmenus.com/fl/miami/187479-mcdonalds/menu/",
    "sg:phone":"+1 305 945 5287",
    "sg:postcode":"33162",
    "sg:province":"FL",
    "sg:tags":[
        "burger",
        "american"
    ],
    "wof:name":"McDonald's",
    "wof:placetype":"venue"
},
  "geometry": {"coordinates":[-80.17152,25.925695],"type":"Point"}
}