{
  "type": "Feature",
  "properties": {
    "iso:country":"US",
    "sg:address":"567 NW 27th St",
    "sg:city":"Miami",
    "sg:classifiers":[
        {
            "category":"Wholesale",
            "subcategory":"Apparel",
            "type":"Manufacturing & Wholesale Goods"
        }
    ],
    "sg:phone":"+1 305 571 5500",
    "sg:postcode":"33127",
    "sg:province":"FL",
    "sg:tags":[
        "shoe",
        "store"
    ],
    "sg:website":"www.tropicshoe.com",
    "wof:name":"Tropic Shoe Inc",
    "wof:placetype":"venue"
},
  "geometry": {"coordinates":[-80.204498,25.801701],"type":"Point"}
}