{
  "type": "Feature",
  "properties": {
    "iso:country":"US",
    "sg:address":"2919 SW 67th Ter",
    "sg:city":"Miramar",
    "sg:classifiers":[
        {
            "category":"Insurance",
            "subcategory":"Insurance Agent",
            "type":"Services"
        }
    ],
    "sg:phone":"+1 754 246 6095",
    "sg:postcode":"33023",
    "sg:province":"FL",
    "sg:tags":[
        "adjuster"
    ],
    "wof:name":"Fred C. Bethel",
    "wof:placetype":"venue"
},
  "geometry": {"coordinates":[-80.221118,25.984186],"type":"Point"}
}