{
  "type": "Feature",
  "properties": {
    "addr:full":"220 E Cowles St Englewood FL 34223",
    "addr:housenumber":"220",
    "addr:postcode":"34223",
    "addr:street":"E Cowles St",
    "iso:country":"US",
    "sg:address":"220 E Cowles St",
    "sg:city":"Englewood",
    "sg:classifiers":[
        {
            "category":"Banks & Credit Unions",
            "subcategory":"Financial Services",
            "type":"Services"
        }
    ],
    "sg:phone":"+1 941 473 8289",
    "sg:postcode":"34223",
    "sg:province":"FL",
    "sg:tags":[
        "trust",
        "management"
    ],
    "wof:name":"Grayce P Kalstad Trustee",
    "wof:placetype":"venue"
},
  "geometry": {"coordinates":[-82.346981,26.95837],"type":"Point"}
}