{
  "type": "Feature",
  "properties": {
    "addr:full":"1113 Arbor Glen Cir Winter Springs FL 32708",
    "addr:housenumber":"1113",
    "addr:postcode":"32708",
    "addr:street":"Arbor Glen Cir",
    "iso:country":"US",
    "sg:address":"1113 Arbor Glen Cir",
    "sg:city":"Winter Springs",
    "sg:classifiers":[
        {
            "category":"Manufacturing",
            "subcategory":"Retail Goods",
            "type":"Manufacturing & Wholesale Goods"
        }
    ],
    "sg:phone":"+1 407 492 2074",
    "sg:postcode":"32708",
    "sg:province":"FL",
    "wof:name":"Schif Solutions Inc",
    "wof:placetype":"venue"
},
  "geometry": {"coordinates":[-81.26759,28.678802],"type":"Point"}
}