{
  "type": "Feature",
  "properties": {
    "addr:full":"4729 Highway Ave Jacksonville FL 32254",
    "addr:housenumber":"4729",
    "addr:postcode":"32254",
    "addr:street":"Highway Ave",
    "iso:country":"US",
    "sg:address":"4729 Highway Ave",
    "sg:city":"Jacksonville",
    "sg:classifiers":[
        {
            "category":"Retail",
            "subcategory":"Repair Shop",
            "type":"Services"
        }
    ],
    "sg:phone":"+1 904 425 4222",
    "sg:postcode":"32254",
    "sg:province":"FL",
    "sg:tags":[
        "upholsterer"
    ],
    "wof:name":"Andrew's Custom Upholstry",
    "wof:placetype":"venue"
},
  "geometry": {"coordinates":[-81.726849,30.321733],"type":"Point"}
}