{
  "type": "Feature",
  "properties": {
    "iso:country":"US",
    "sg:address":"1511 E Robinson St",
    "sg:city":"Orlando",
    "sg:classifiers":[
        {
            "category":"Health Services",
            "subcategory":"Chiropractor",
            "type":"Services"
        }
    ],
    "sg:phone":"+1 407 894 8886",
    "sg:postcode":"32801",
    "sg:province":"FL",
    "wof:name":"Geldner R Wilson Dr",
    "wof:placetype":"venue"
},
  "geometry": {"coordinates":[-81.361268,28.545895],"type":"Point"}
}