{
  "type": "Feature",
  "properties": {
    "iso:country":"US",
    "sg:address":"5975 Mobile Hwy",
    "sg:city":"Pensacola",
    "sg:classifiers":[
        {
            "category":"Banks & Credit Unions",
            "subcategory":"Bank",
            "type":"Services"
        }
    ],
    "sg:phone":"+1 850 444 1234",
    "sg:postcode":"32526",
    "sg:province":"FL",
    "wof:name":"AM South Bank",
    "wof:placetype":"venue"
},
  "geometry": {"coordinates":[-87.300129,30.459326],"type":"Point"}
}