{
  "type": "Feature",
  "properties": {
    "addr:full":"686 N Hunt Club Blvd # 100 Longwood FL 32779",
    "addr:housenumber":"686",
    "addr:postcode":"32779",
    "addr:street":"N Hunt Club Blvd # 100",
    "iso:country":"US",
    "sg:address":"686 N Hunt Club Blvd # 100",
    "sg:city":"Longwood",
    "sg:classifiers":[
        {
            "category":"Health Services",
            "subcategory":"Dentist",
            "type":"Services"
        }
    ],
    "sg:phone":"+1 407 869 7333",
    "sg:postcode":"32779",
    "sg:province":"FL",
    "wof:name":"Offenbach, Mark Dds",
    "wof:placetype":"venue"
},
  "geometry": {"coordinates":[-81.44544999999999,28.707497],"type":"Point"}
}