{
  "type": "Feature",
  "properties": {
    "addr:full":"126 16th Ave SW Ruskin FL 33570",
    "addr:housenumber":"126",
    "addr:postcode":"33570",
    "addr:street":"16Th Ave Sw",
    "iso:country":"US",
    "sg:address":"126 16th Ave SW",
    "sg:city":"Ruskin",
    "sg:classifiers":[
        {
            "category":"Freight",
            "type":"Transportation"
        }
    ],
    "sg:phone":"+1 813 641 2971",
    "sg:postcode":"33570",
    "sg:province":"FL",
    "sg:tags":[
        "operator",
        "trucking"
    ],
    "wof:name":"S & D Export",
    "wof:placetype":"venue"
},
  "geometry": {"coordinates":[-82.439306,27.702159],"type":"Point"}
}