{
  "type": "Feature",
  "properties": {
    "iso:country":"US",
    "sg:address":"3798 Old Jennings Rd",
    "sg:city":"Middleburg",
    "sg:classifiers":[
        {
            "category":"Manufacturing",
            "subcategory":"Lumber",
            "type":"Manufacturing & Wholesale Goods"
        }
    ],
    "sg:phone":"+1 904 291 1309",
    "sg:postcode":"32068",
    "sg:province":"FL",
    "sg:tags":[
        "forestry",
        "forester"
    ],
    "wof:name":"Forest Environment Specialists",
    "wof:placetype":"venue"
},
  "geometry": {"coordinates":[-81.85639999999999,30.11415],"type":"Point"}
}