{
  "type": "Feature",
  "properties": {
    "iso:country":"US",
    "sg:address":"3116 Corrine Dr",
    "sg:city":"Orlando",
    "sg:classifiers":[
        {
            "category":"Restaurant",
            "type":"Food & Drink"
        }
    ],
    "sg:phone":"+1 407 896 9105",
    "sg:postcode":"32803",
    "sg:province":"FL",
    "sg:tags":[
        "eating",
        "product",
        "dairy"
    ],
    "wof:name":"Rainbow Sno-Cones",
    "wof:placetype":"venue"
},
  "geometry": {"coordinates":[-81.345038,28.56785],"type":"Point"}
}