{
  "type": "Feature",
  "properties": {
    "addr:full":"8080 NW 58th St Doral FL 33166",
    "addr:housenumber":"8080",
    "addr:postcode":"33166",
    "addr:street":"Nw 58Th St",
    "iso:country":"US",
    "sg:address":"8080 NW 58th St",
    "sg:city":"Doral",
    "sg:classifiers":[
        {
            "category":"Food & Beverages",
            "subcategory":"Specialty",
            "type":"Retail Goods"
        }
    ],
    "sg:phone":"+1 305 639 9848",
    "sg:postcode":"33166",
    "sg:province":"FL",
    "sg:tags":[
        "coffee",
        "roasting"
    ],
    "sg:website":"http://www.javacabana.com",
    "wof:name":"Cafe Ideal",
    "wof:placetype":"venue"
},
  "geometry": {"coordinates":[-80.328228,25.826198],"type":"Point"}
}