{
  "type": "Feature",
  "properties": {
    "addr:full":"3609 Cottage Club Ln Naples FL 34105",
    "addr:housenumber":"3609",
    "addr:postcode":"34105",
    "addr:street":"Cottage Club Ln",
    "iso:country":"US",
    "sg:address":"3609 Cottage Club Ln",
    "sg:city":"Naples",
    "sg:classifiers":[
        {
            "category":"Shopping",
            "subcategory":"Hobbies, Toys, & Games",
            "type":"Retail Goods"
        }
    ],
    "sg:phone":"+1 239 455 7492",
    "sg:postcode":"34105",
    "sg:province":"FL",
    "wof:name":"Naples Toy Factory Inc",
    "wof:placetype":"venue"
},
  "geometry": {"coordinates":[-81.771981,26.190257],"type":"Point"}
}