{
  "type": "Feature",
  "properties": {
    "iso:country":"US",
    "sg:address":"170 Big Lake Dr",
    "sg:city":"Deltona",
    "sg:classifiers":[
        {
            "category":"Banks & Credit Unions",
            "subcategory":"Investment Brokerage",
            "type":"Services"
        },
        {
            "category":"Real Estate",
            "subcategory":"Developer",
            "type":"Services"
        }
    ],
    "sg:phone":"+1 407 497 9929",
    "sg:postcode":"32738",
    "sg:province":"FL",
    "sg:tags":[
        "investing"
    ],
    "wof:name":"Wempower",
    "wof:placetype":"venue"
},
  "geometry": {"coordinates":[-81.211445,28.865838],"type":"Point"}
}