{
  "type": "Feature",
  "properties": {
    "iso:country":"US",
    "sg:address":"3333 NW 39th Ave",
    "sg:city":"Gainesville",
    "sg:classifiers":[
        {
            "category":"Government",
            "subcategory":"Police Station",
            "type":"Public Place"
        }
    ],
    "sg:phone":"+1 352 491 4444",
    "sg:postcode":"32605",
    "sg:province":"FL",
    "sg:tags":[
        "sheriff"
    ],
    "wof:name":"Alachua County Sheriff",
    "wof:placetype":"venue"
},
  "geometry": {"coordinates":[-82.37465400000001,29.688564],"type":"Point"}
}