{
  "type": "Feature",
  "properties": {
    "addr:full":"8809 Paul Starr Dr Pensacola FL 32514",
    "addr:housenumber":"8809",
    "addr:postcode":"32514",
    "addr:street":"Paul Starr Dr",
    "iso:country":"US",
    "sg:address":"8809 Paul Starr Dr",
    "sg:city":"Pensacola",
    "sg:classifiers":[
        {
            "category":"Manufacturing",
            "subcategory":"Textiles",
            "type":"Manufacturing & Wholesale Goods"
        }
    ],
    "sg:phone":"+1 850 969 0616",
    "sg:postcode":"32514",
    "sg:province":"FL",
    "sg:tags":[
        "rug",
        "carpet"
    ],
    "sg:website":"www.mohawkind.com",
    "wof:name":"Mohawk Industries Inc",
    "wof:placetype":"venue"
},
  "geometry": {"coordinates":[-87.19775199999999,30.523255],"type":"Point"}
}