{
  "type": "Feature",
  "properties": {
    "iso:country":"US",
    "sg:address":"805 Delaware Ave",
    "sg:city":"Fort Pierce",
    "sg:classifiers":[
        {
            "category":"Professional",
            "subcategory":"Lawyer & Legal Services",
            "type":"Services"
        }
    ],
    "sg:phone":"+1 772 464 4054",
    "sg:postcode":"34950",
    "sg:province":"FL",
    "sg:tags":[
        "attorney"
    ],
    "wof:name":"David M Lamos",
    "wof:placetype":"venue"
},
  "geometry": {"coordinates":[-80.331952,27.443245],"type":"Point"}
}