{
  "type": "Feature",
  "properties": {
    "iso:country":"US",
    "sg:address":"3605 E Hillsborough Ave",
    "sg:city":"Tampa",
    "sg:classifiers":[
        {
            "category":"Retail",
            "subcategory":"Auto Repair",
            "type":"Services"
        }
    ],
    "sg:phone":"+1 813 238 7744",
    "sg:postcode":"33610",
    "sg:province":"FL",
    "sg:tags":[
        "repairing",
        "automobile"
    ],
    "wof:name":"Dencar Auto Repairs",
    "wof:placetype":"venue"
},
  "geometry": {"coordinates":[-82.418381,27.99602],"type":"Point"}
}