{
  "type": "Feature",
  "properties": {
    "addr:full":"11541 State Rd 52 Hudson FL 34669",
    "addr:housenumber":"11541;52",
    "addr:postcode":"34669",
    "addr:street":"State Rd",
    "iso:country":"US",
    "sg:address":"11541 State Rd 52",
    "sg:city":"Hudson",
    "sg:classifiers":[
        {
            "category":"Autos & Motor Vehicles",
            "subcategory":"Automobile Sales",
            "type":"Retail Goods"
        }
    ],
    "sg:phone":"+1 727 856 2885",
    "sg:postcode":"34669",
    "sg:province":"FL",
    "sg:tags":[
        "car",
        "dealer"
    ],
    "wof:name":"White's Auto Sales",
    "wof:placetype":"venue"
},
  "geometry": {"coordinates":[-82.62449599999999,28.336831],"type":"Point"}
}