{
  "type": "Feature",
  "properties": {
    "iso:country":"US",
    "sg:address":"1645 Lexington Ave",
    "sg:city":"Deland",
    "sg:classifiers":[
        {
            "category":"Manufacturing",
            "subcategory":"Apparel",
            "type":"Manufacturing & Wholesale Goods"
        }
    ],
    "sg:phone":"+1 386 736 7589",
    "sg:postcode":"32724",
    "sg:province":"FL",
    "sg:tags":[
        "sewing",
        "contractor"
    ],
    "sg:website":"www.relativeworkshop.com",
    "wof:name":"Relative Workshop",
    "wof:placetype":"venue"
},
  "geometry": {"coordinates":[-81.278858,29.059107],"type":"Point"}
}