{
  "type": "Feature",
  "properties": {
    "addr:full":"116 Gulfwinds Ln Marathon FL 33050",
    "addr:housenumber":"116",
    "addr:postcode":"33050",
    "addr:street":"Gulfwinds Ln",
    "iso:country":"US",
    "sg:address":"116 Gulfwinds Ln",
    "sg:city":"Marathon",
    "sg:classifiers":[
        {
            "category":"Shopping",
            "subcategory":"Books",
            "type":"Retail Goods"
        }
    ],
    "sg:phone":"+1 305 743 5256",
    "sg:postcode":"33050",
    "sg:province":"FL",
    "wof:name":"Book Key Books",
    "wof:placetype":"venue"
},
  "geometry": {"coordinates":[-81.05049099999999,24.7299],"type":"Point"}
}