{
  "type": "Feature",
  "properties": {
    "addr:full":"13820 St Augustine Rd Jacksonville FL 32258",
    "addr:housenumber":"13820",
    "addr:postcode":"32258",
    "addr:street":"St Augustine Rd",
    "iso:country":"US",
    "sg:address":"13820 St Augustine Rd",
    "sg:city":"Jacksonville",
    "sg:classifiers":[
        {
            "category":"Building & Trades",
            "subcategory":"Electrical",
            "type":"Services"
        }
    ],
    "sg:phone":"+1 904 779 9020",
    "sg:postcode":"32258",
    "sg:province":"FL",
    "sg:tags":[
        "lighting",
        "landscape"
    ],
    "wof:name":"Nitelites Of Jacksonville",
    "wof:placetype":"venue"
},
  "geometry": {"coordinates":[-81.542013,30.141483],"type":"Point"}
}