{
  "type": "Feature",
  "properties": {
    "iso:country":"US",
    "sg:address":"8131 Vineland Ave",
    "sg:city":"Orlando",
    "sg:classifiers":[
        {
            "category":"Professional",
            "subcategory":"Advertising",
            "type":"Services"
        }
    ],
    "sg:phone":"+1 407 465 1700",
    "sg:postcode":"32821",
    "sg:province":"FL",
    "sg:tags":[
        "mailing",
        "shipping"
    ],
    "wof:name":"UPS Store",
    "wof:placetype":"venue"
},
  "geometry": {"coordinates":[-81.48671400000001,28.384829],"type":"Point"}
}