{
  "type": "Feature",
  "properties": {
    "iso:country":"US",
    "sg:address":"6361 SW 38th Ct",
    "sg:city":"Davie",
    "sg:classifiers":[
        {
            "category":"Professional",
            "type":"Services"
        }
    ],
    "sg:phone":"+1 954 583 1452",
    "sg:postcode":"33314",
    "sg:province":"FL",
    "sg:tags":[
        "establishment"
    ],
    "wof:name":"Scrubb International Ofc",
    "wof:placetype":"venue"
},
  "geometry": {"coordinates":[-80.232305,26.074063],"type":"Point"}
}