{
  "type": "Feature",
  "properties": {
    "iso:country":"US",
    "sg:address":"7806 SW Ellipse Way",
    "sg:city":"Stuart",
    "sg:classifiers":[
        {
            "category":"Manufacturing",
            "subcategory":"Tools & Machinery",
            "type":"Manufacturing & Wholesale Goods"
        }
    ],
    "sg:phone":"+1 772 419 0215",
    "sg:postcode":"34997",
    "sg:province":"FL",
    "sg:tags":[
        "lighting",
        "system",
        "emergency"
    ],
    "wof:name":"Synergy Design Group Inc",
    "wof:placetype":"venue"
},
  "geometry": {"coordinates":[-80.264375,27.110378],"type":"Point"}
}