{
  "type": "Feature",
  "properties": {
    "iso:country":"US",
    "sg:address":"5003 SW 127th Pl",
    "sg:city":"Miami",
    "sg:classifiers":[
        {
            "category":"Freight",
            "type":"Transportation"
        }
    ],
    "sg:phone":"+1 305 223 2162",
    "sg:postcode":"33175",
    "sg:province":"FL",
    "sg:tags":[
        "forwarder"
    ],
    "sg:website":"www.lazcar.com",
    "wof:name":"Lazcar International Inc",
    "wof:placetype":"venue"
},
  "geometry": {"coordinates":[-80.40040999999999,25.720056],"type":"Point"}
}