{
  "type": "Feature",
  "properties": {
    "addr:full":"2604 Pasco St Tallahassee FL 32310",
    "addr:housenumber":"2604",
    "addr:postcode":"32310",
    "addr:street":"Pasco St",
    "iso:country":"US",
    "sg:address":"2604 Pasco St",
    "sg:city":"Tallahassee",
    "sg:classifiers":[
        {
            "category":"Social Services",
            "subcategory":"Child Care",
            "type":"Services"
        }
    ],
    "sg:phone":"+1 850 576 5425",
    "sg:postcode":"32310",
    "sg:province":"FL",
    "sg:tags":[
        "day"
    ],
    "wof:name":"3 R's Academy",
    "wof:placetype":"venue"
},
  "geometry": {"coordinates":[-84.294043,30.414116],"type":"Point"}
}