{
  "type": "Feature",
  "properties": {
    "iso:country":"US",
    "sg:address":"122 N 11th St",
    "sg:city":"Haines City",
    "sg:classifiers":[
        {
            "category":"Wholesale",
            "subcategory":"Groceries",
            "type":"Manufacturing & Wholesale Goods"
        }
    ],
    "sg:phone":"+1 863 422 9416",
    "sg:postcode":"33844",
    "sg:province":"FL",
    "sg:tags":[
        "grocer"
    ],
    "wof:name":"Mainstreet Wholesale Corp",
    "wof:placetype":"venue"
},
  "geometry": {"coordinates":[-81.62262800000001,28.108436],"type":"Point"}
}