{
  "type": "Feature",
  "properties": {
    "iso:country":"US",
    "sg:address":"1548 3rd St SW",
    "sg:city":"Winter Haven",
    "sg:classifiers":[
        {
            "category":"Personal",
            "subcategory":"Beauty Salon",
            "type":"Services"
        }
    ],
    "sg:phone":"+1 863 294 7074",
    "sg:postcode":"33880",
    "sg:province":"FL",
    "sg:tags":[
        "manicuring"
    ],
    "wof:name":"Pro-Nails",
    "wof:placetype":"venue"
},
  "geometry": {"coordinates":[-81.73076399999999,28.007525],"type":"Point"}
}