{
  "type": "Feature",
  "properties": {
    "addr:full":"7909 Normandy Blvd Jacksonville FL 32221",
    "addr:housenumber":"7909",
    "addr:postcode":"32221",
    "addr:street":"Normandy Blvd",
    "iso:country":"US",
    "sg:address":"7909 Normandy Blvd",
    "sg:city":"Jacksonville",
    "sg:classifiers":[
        {
            "category":"Health Services",
            "subcategory":"Dentist",
            "type":"Services"
        }
    ],
    "sg:phone":"+1 904 786 1309",
    "sg:postcode":"32221",
    "sg:province":"FL",
    "wof:name":"Smilecare Dental Associates PA",
    "wof:placetype":"venue"
},
  "geometry": {"coordinates":[-81.779895,30.29329],"type":"Point"}
}