{
  "type": "Feature",
  "properties": {
    "addr:full":"13126 S Dixie Hwy Miami FL 33156",
    "addr:housenumber":"13126",
    "addr:postcode":"33156",
    "addr:street":"S Dixie Hwy",
    "iso:country":"US",
    "sg:address":"13126 S Dixie Hwy",
    "sg:city":"Miami",
    "sg:classifiers":[
        {
            "category":"Banks & Credit Unions",
            "subcategory":"Bank",
            "type":"Services"
        }
    ],
    "sg:phone":"+1 305 969 3661",
    "sg:postcode":"33156",
    "sg:province":"FL",
    "sg:tags":[
        "second",
        "hand"
    ],
    "wof:name":"Urban Labels",
    "wof:placetype":"venue"
},
  "geometry": {"coordinates":[-80.332139,25.648371],"type":"Point"}
}