{
  "type": "Feature",
  "properties": {
    "iso:country":"US",
    "sg:address":"17407 S Dixie Hwy",
    "sg:city":"Miami",
    "sg:classifiers":[
        {
            "category":"Building & Trades",
            "subcategory":"Locksmith",
            "type":"Services"
        }
    ],
    "sg:phone":"+1 786 228 5387",
    "sg:postcode":"33157",
    "sg:province":"FL",
    "sg:tags":[
        "key"
    ],
    "wof:name":"Emergency Locksmith On S Dixie Hwy",
    "wof:placetype":"venue"
},
  "geometry": {"coordinates":[-80.34770899999999,25.607849],"type":"Point"}
}