{
  "type": "Feature",
  "properties": {
    "addr:full":"7706 Colley Rd Odessa FL 33556",
    "addr:housenumber":"7706",
    "addr:postcode":"33556",
    "addr:street":"Colley Rd",
    "iso:country":"US",
    "sg:address":"7706 Colley Rd",
    "sg:city":"Odessa",
    "sg:classifiers":[
        {
            "category":"Building & Trades",
            "subcategory":"Plumbing",
            "type":"Services"
        }
    ],
    "sg:phone":"+1 813 920 6727",
    "sg:postcode":"33556",
    "sg:province":"FL",
    "sg:tags":[
        "contractor"
    ],
    "wof:name":"Tropical Air Inc",
    "wof:placetype":"venue"
},
  "geometry": {"coordinates":[-82.567825,28.165349],"type":"Point"}
}