{
  "type": "Feature",
  "properties": {
    "addr:full":"6325 N Orange Blossom Trl Orlando FL 32810",
    "addr:housenumber":"6325",
    "addr:postcode":"32810",
    "addr:street":"N Orange Blossom Trl",
    "iso:country":"US",
    "sg:address":"6325 N Orange Blossom Trl",
    "sg:city":"Orlando",
    "sg:classifiers":[
        {
            "category":"Restaurant",
            "type":"Food & Drink"
        }
    ],
    "sg:menulink":"http://www.allmenus.com/fl/orlando/81342-papa-johns-pizza/menu/",
    "sg:phone":"+1 407 292 7272",
    "sg:postcode":"32810",
    "sg:province":"FL",
    "sg:tags":[
        "american",
        "pizza"
    ],
    "wof:name":"Papa John's Pizza",
    "wof:placetype":"venue"
},
  "geometry": {"coordinates":[-81.432799,28.614072],"type":"Point"}
}