{
  "type": "Feature",
  "properties": {
    "iso:country":"US",
    "sg:address":"180 Scarlet Blvd",
    "sg:city":"Oldsmar",
    "sg:classifiers":[
        {
            "category":"Wholesale",
            "subcategory":"Electrical",
            "type":"Manufacturing & Wholesale Goods"
        },
        {
            "category":"Building & Trades",
            "subcategory":"Electrical",
            "type":"Services"
        }
    ],
    "sg:phone":"+1 813 925 1007",
    "sg:postcode":"34677",
    "sg:province":"FL",
    "sg:tags":[
        "control",
        "security",
        "electrician",
        "system",
        "contractor"
    ],
    "sg:website":"http://www.isofinc.com",
    "wof:name":"Integrated Systems Of Florida, Inc.",
    "wof:placetype":"venue"
},
  "geometry": {"coordinates":[-82.675979,28.041866],"type":"Point"}
}