{
  "type": "Feature",
  "properties": {
    "iso:country":"US",
    "sg:address":"8912 Metheny Cir",
    "sg:city":"Tampa",
    "sg:classifiers":[
        {
            "category":"Building & Trades",
            "subcategory":"Pest Control",
            "type":"Services"
        }
    ],
    "sg:phone":"+1 813 496 0407",
    "sg:postcode":"33615",
    "sg:province":"FL",
    "wof:name":"Pest Solutions Of Tampa Bay",
    "wof:placetype":"venue"
},
  "geometry": {"coordinates":[-82.565968,28.031109],"type":"Point"}
}