{
  "type": "Feature",
  "properties": {
    "addr:full":"18707 Yocam Ave Lutz FL 33549",
    "addr:housenumber":"18707",
    "addr:postcode":"33549",
    "addr:street":"Yocam Ave",
    "iso:country":"US",
    "sg:address":"18707 Yocam Ave",
    "sg:city":"Lutz",
    "sg:classifiers":[
        {
            "category":"Professional",
            "subcategory":"Lawyer & Legal Services",
            "type":"Services"
        }
    ],
    "sg:phone":"+1 813 949 6180",
    "sg:postcode":"33549",
    "sg:province":"FL",
    "wof:name":"Frances Law",
    "wof:placetype":"venue"
},
  "geometry": {"coordinates":[-82.450973,28.147147],"type":"Point"}
}