{
  "type": "Feature",
  "properties": {
    "addr:full":"1757 SE Monroe St Stuart FL 34997",
    "addr:housenumber":"1757",
    "addr:postcode":"34997",
    "addr:street":"Se Monroe St",
    "iso:country":"US",
    "sg:address":"1757 SE Monroe St",
    "sg:city":"Stuart",
    "sg:classifiers":[
        {
            "category":"Shopping",
            "subcategory":"Music",
            "type":"Retail Goods"
        }
    ],
    "sg:phone":"+1 772 223 9747",
    "sg:postcode":"34997",
    "sg:province":"FL",
    "wof:name":"Tiki Tone Records Etc",
    "wof:placetype":"venue"
},
  "geometry": {"coordinates":[-80.230159,27.147344],"type":"Point"}
}