{
  "type": "Feature",
  "properties": {
    "addr:full":"1512 W Gore St Ste D Orlando FL 32805",
    "addr:housenumber":"1512",
    "addr:postcode":"32805",
    "addr:street":"W Gore St Ste D",
    "iso:country":"US",
    "sg:address":"1512 W Gore St Ste D",
    "sg:city":"Orlando",
    "sg:classifiers":[
        {
            "category":"Bakery",
            "type":"Food & Drink"
        }
    ],
    "sg:phone":"+1 407 692 5973",
    "sg:postcode":"32805",
    "sg:province":"FL",
    "wof:name":"Echantillon Bakery",
    "wof:placetype":"venue"
},
  "geometry": {"coordinates":[-81.40075400000001,28.531092],"type":"Point"}
}