{
  "type": "Feature",
  "properties": {
    "iso:country":"US",
    "sg:address":"9081 Sunrise Lakes Blvd # 208",
    "sg:city":"Sunrise",
    "sg:classifiers":[
        {
            "category":"Banks & Credit Unions",
            "subcategory":"Financial Services",
            "type":"Services"
        }
    ],
    "sg:phone":"+1 954 394 7392",
    "sg:postcode":"33322",
    "sg:province":"FL",
    "sg:tags":[
        "plan"
    ],
    "wof:name":"Berkway",
    "wof:placetype":"venue"
},
  "geometry": {"coordinates":[-80.271061,26.16199],"type":"Point"}
}