{
  "type": "Feature",
  "properties": {
    "iso:country":"US",
    "sg:address":"206 Seabreeze Blvd",
    "sg:city":"Daytona Beach",
    "sg:classifiers":[
        {
            "category":"Personal",
            "subcategory":"Beauty Salon",
            "type":"Services"
        }
    ],
    "sg:phone":"+1 386 253 0505",
    "sg:postcode":"32118",
    "sg:province":"FL",
    "sg:tags":[
        "manicuring"
    ],
    "wof:name":"Nail Fantasy By Zelda",
    "wof:placetype":"venue"
},
  "geometry": {"coordinates":[-81.01683199999999,29.23391],"type":"Point"}
}