{
  "type": "Feature",
  "properties": {
    "iso:country":"US",
    "sg:address":"543 Crowne Sunset Dr",
    "sg:city":"Ormond Beach",
    "sg:classifiers":[
        {
            "category":"Professional",
            "type":"Services"
        }
    ],
    "sg:phone":"+1 386 615 3160",
    "sg:postcode":"32174",
    "sg:province":"FL",
    "sg:tags":[
        "establishment"
    ],
    "wof:name":"C 3 Solutions",
    "wof:placetype":"venue"
},
  "geometry": {"coordinates":[-81.111722,29.246703],"type":"Point"}
}