{
  "type": "Feature",
  "properties": {
    "iso:country":"US",
    "sg:address":"3860 US Hwy 1",
    "sg:city":"Grant",
    "sg:classifiers":[
        {
            "category":"Travel",
            "subcategory":"Campground",
            "type":"Entertainment"
        }
    ],
    "sg:phone":"+1 321 729 8112",
    "sg:postcode":"32949",
    "sg:province":"FL",
    "sg:tags":[
        "trailer"
    ],
    "wof:name":"Orbit Camp Site",
    "wof:placetype":"venue"
},
  "geometry": {"coordinates":[-80.53912200000001,27.9575],"type":"Point"}
}