{
  "type": "Feature",
  "properties": {
    "addr:full":"1675 S Military Trl West Palm Beach FL 33415",
    "addr:housenumber":"1675",
    "addr:postcode":"33415",
    "addr:street":"S Military Trl",
    "iso:country":"US",
    "sg:address":"1675 S Military Trl",
    "sg:city":"West Palm Beach",
    "sg:classifiers":[
        {
            "category":"Bakery",
            "type":"Food & Drink"
        },
        {
            "category":"Coffee & Tea",
            "type":"Food & Drink"
        },
        {
            "category":"Bagels",
            "type":"Food & Drink"
        },
        {
            "category":"Donuts",
            "type":"Food & Drink"
        }
    ],
    "sg:menulink":"http://www.allmenus.com/fl/lake-worth/138140-dunkin-donuts/menu/",
    "sg:phone":"+1 561 965 2563",
    "sg:postcode":"33415",
    "sg:province":"FL",
    "sg:tags":[
        "american",
        "pastry"
    ],
    "wof:name":"Dunkin' Donuts",
    "wof:placetype":"venue"
},
  "geometry": {"coordinates":[-80.11284000000001,26.652768],"type":"Point"}
}