{
  "type": "Feature",
  "properties": {
    "iso:country":"US",
    "sg:address":"707 Mill Creek Rd Ste 400",
    "sg:city":"Jacksonville",
    "sg:classifiers":[
        {
            "category":"Professional",
            "subcategory":"Employment Agencies",
            "type":"Services"
        },
        {
            "category":"Organizations",
            "subcategory":"Community Association",
            "type":"Services"
        },
        {
            "category":"Organizations",
            "subcategory":"Professional Association",
            "type":"Services"
        }
    ],
    "sg:phone":"+1 904 723 3145",
    "sg:postcode":"32211",
    "sg:province":"FL",
    "sg:tags":[
        "employer",
        "business",
        "trade"
    ],
    "wof:name":"White Foundation",
    "wof:placetype":"venue"
},
  "geometry": {"coordinates":[-81.560181,30.326312],"type":"Point"}
}