{
  "type": "Feature",
  "properties": {
    "iso:country":"US",
    "sg:address":"2851 NW 107th Ave",
    "sg:city":"Doral",
    "sg:classifiers":[
        {
            "category":"Professional",
            "subcategory":"Accounting & Tax Preparation",
            "type":"Services"
        }
    ],
    "sg:phone":"+1 305 447 1426",
    "sg:postcode":"33172",
    "sg:province":"FL",
    "sg:tags":[
        "accountant"
    ],
    "wof:name":"Marcos A Guerra Pa",
    "wof:placetype":"venue"
},
  "geometry": {"coordinates":[-80.36915399999999,25.798827],"type":"Point"}
}