{
  "type": "Feature",
  "properties": {
    "iso:country":"US",
    "sg:address":"13950 184th Pl N",
    "sg:city":"Jupiter",
    "sg:classifiers":[
        {
            "category":"Retail",
            "subcategory":"Veterinary Services",
            "type":"Services"
        }
    ],
    "sg:phone":"+1 561 744 9026",
    "sg:postcode":"33478",
    "sg:province":"FL",
    "sg:tags":[
        "veterinarian"
    ],
    "wof:name":"Wolf Meadows Equine",
    "wof:placetype":"venue"
},
  "geometry": {"coordinates":[-80.253896,26.948808],"type":"Point"}
}