{
  "type": "Feature",
  "properties": {
    "iso:country":"US",
    "sg:address":"4430 SW 34 St",
    "sg:city":"Gainesville",
    "sg:classifiers":[
        {
            "category":"Freight",
            "type":"Transportation"
        }
    ],
    "sg:phone":"+1 352 335 6793",
    "sg:postcode":"32608",
    "sg:province":"FL",
    "sg:tags":[
        "special",
        "general"
    ],
    "wof:name":"Gainesville Mini Storage",
    "wof:placetype":"venue"
},
  "geometry": {"coordinates":[-82.369685,29.602111],"type":"Point"}
}