{
  "type": "Feature",
  "properties": {
    "addr:full":"549 Hibiscus Ave Sebastian FL 32958",
    "addr:housenumber":"549",
    "addr:postcode":"32958",
    "addr:street":"Hibiscus Ave",
    "iso:country":"US",
    "sg:address":"549 Hibiscus Ave",
    "sg:city":"Sebastian",
    "sg:classifiers":[
        {
            "category":"Home & Garden",
            "subcategory":"Building Materials",
            "type":"Retail Goods"
        }
    ],
    "sg:phone":"+1 772 589 3348",
    "sg:postcode":"32958",
    "sg:province":"FL",
    "sg:tags":[
        "glass",
        "window",
        "plate"
    ],
    "wof:name":"Tri County Glass & Mirror",
    "wof:placetype":"venue"
},
  "geometry": {"coordinates":[-80.485041,27.804569],"type":"Point"}
}