{
  "type": "Feature",
  "properties": {
    "iso:country":"US",
    "sg:address":"3666 Davie Blvd",
    "sg:city":"Fort Lauderdale",
    "sg:classifiers":[
        {
            "category":"Banks & Credit Unions",
            "subcategory":"Investment Brokerage",
            "type":"Services"
        }
    ],
    "sg:phone":"+1 954 709 4724",
    "sg:postcode":"33312",
    "sg:province":"FL",
    "sg:tags":[
        "advisory"
    ],
    "wof:name":"Mars Financial Inc",
    "wof:placetype":"venue"
},
  "geometry": {"coordinates":[-80.19747700000001,26.104463],"type":"Point"}
}