{
  "type": "Feature",
  "properties": {
    "iso:country":"US",
    "sg:address":"5541 Force Four Pkwy",
    "sg:city":"Orlando",
    "sg:classifiers":[
        {
            "category":"Autos & Motor Vehicles",
            "subcategory":"Auto Supplies",
            "type":"Retail Goods"
        }
    ],
    "sg:phone":"+1 407 855 7111",
    "sg:postcode":"32839",
    "sg:province":"FL",
    "sg:tags":[
        "filter",
        "gas"
    ],
    "wof:name":"Filtrair Corp",
    "wof:placetype":"venue"
},
  "geometry": {"coordinates":[-81.372609,28.479246],"type":"Point"}
}