{
  "type": "Feature",
  "properties": {
    "iso:country":"US",
    "sg:address":"6640 NW 22nd St",
    "sg:city":"Miami",
    "sg:classifiers":[
        {
            "category":"Professional",
            "type":"Services"
        }
    ],
    "sg:phone":"+1 305 871 4766",
    "sg:postcode":"33122",
    "sg:province":"FL",
    "sg:tags":[
        "support",
        "airline"
    ],
    "wof:name":"Aircraft Maintenance Support Inc",
    "wof:placetype":"venue"
},
  "geometry": {"coordinates":[-80.30473499999999,25.793731],"type":"Point"}
}