{
  "type": "Feature",
  "properties": {
    "addr:full":"1503 Sabra Dr Brooksville FL 34601",
    "addr:housenumber":"1503",
    "addr:postcode":"34601",
    "addr:street":"Sabra Dr",
    "iso:country":"US",
    "sg:address":"1503 Sabra Dr",
    "sg:city":"Brooksville",
    "sg:classifiers":[
        {
            "category":"Building & Trades",
            "subcategory":"Landscaping Services",
            "type":"Services"
        }
    ],
    "sg:phone":"+1 352 796 0828",
    "sg:postcode":"34601",
    "sg:province":"FL",
    "wof:name":"Discount Lawn",
    "wof:placetype":"venue"
},
  "geometry": {"coordinates":[-82.396474,28.539479],"type":"Point"}
}