{
  "type": "Feature",
  "properties": {
    "iso:country":"US",
    "sg:address":"826 E New Haven Ave",
    "sg:city":"Melbourne",
    "sg:classifiers":[
        {
            "category":"Shopping",
            "subcategory":"Clothing, Apparel, & Fashions",
            "type":"Retail Goods"
        }
    ],
    "sg:phone":"+1 321 723 8008",
    "sg:postcode":"32901",
    "sg:province":"FL",
    "wof:name":"Orchid Beach Clothing Co",
    "wof:placetype":"venue"
},
  "geometry": {"coordinates":[-80.606145,28.078508],"type":"Point"}
}