{
  "type": "Feature",
  "properties": {
    "addr:full":"15600 NW 67th Ave Hialeah FL 33014",
    "addr:housenumber":"15600",
    "addr:postcode":"33014",
    "addr:street":"Nw 67Th Ave",
    "iso:country":"US",
    "sg:address":"15600 NW 67th Ave",
    "sg:city":"Hialeah",
    "sg:classifiers":[
        {
            "category":"Professional",
            "subcategory":"Lawyer & Legal Services",
            "type":"Services"
        }
    ],
    "sg:phone":"+1 305 826 7260",
    "sg:postcode":"33014",
    "sg:province":"FL",
    "sg:website":"www.kelleykronenberg.com",
    "wof:name":"Kronenberg Steven P Atty",
    "wof:placetype":"venue"
},
  "geometry": {"coordinates":[-80.30909699999999,25.914801],"type":"Point"}
}