{
  "type": "Feature",
  "properties": {
    "addr:full":"419 W Hallandale Beach Blvd Hallandale Beach FL 33009",
    "addr:housenumber":"419",
    "addr:postcode":"33009",
    "addr:street":"W Hallandale Beach Blvd",
    "iso:country":"US",
    "sg:address":"419 W Hallandale Beach Blvd",
    "sg:city":"Hallandale Beach",
    "sg:classifiers":[
        {
            "category":"Personal",
            "subcategory":"Beauty Salon",
            "type":"Services"
        }
    ],
    "sg:phone":"+1 954 454 5186",
    "sg:postcode":"33009",
    "sg:province":"FL",
    "sg:website":"www.carfamilykidsbeautysalon.com",
    "wof:name":"Car Family Kids Inc",
    "wof:placetype":"venue"
},
  "geometry": {"coordinates":[-80.15310700000001,25.985405],"type":"Point"}
}