{
  "type": "Feature",
  "properties": {
    "iso:country":"US",
    "sg:address":"7171 N Davis Hwy",
    "sg:city":"Pensacola",
    "sg:classifiers":[
        {
            "category":"Shopping",
            "subcategory":"Clothing, Apparel, & Fashions",
            "type":"Retail Goods"
        }
    ],
    "sg:phone":"+1 850 474 9266",
    "sg:postcode":"32504",
    "sg:province":"FL",
    "sg:tags":[
        "lingerie"
    ],
    "sg:website":"www.victoriassecret.com",
    "wof:name":"Victoria's Secret",
    "wof:placetype":"venue"
},
  "geometry": {"coordinates":[-87.221902,30.496433],"type":"Point"}
}