{
  "type": "Feature",
  "properties": {
    "addr:full":"5441 Windridge Ln Orlando FL 32810",
    "addr:housenumber":"5441",
    "addr:postcode":"32810",
    "addr:street":"Windridge Ln",
    "iso:country":"US",
    "sg:address":"5441 Windridge Ln",
    "sg:city":"Orlando",
    "sg:classifiers":[
        {
            "category":"Food & Beverages",
            "subcategory":"Bakery",
            "type":"Retail Goods"
        }
    ],
    "sg:phone":"+1 407 293 9374",
    "sg:postcode":"32810",
    "sg:province":"FL",
    "sg:tags":[
        "baker"
    ],
    "wof:name":"Cake Paradise",
    "wof:placetype":"venue"
},
  "geometry": {"coordinates":[-81.442834,28.626372],"type":"Point"}
}