{
  "type": "Feature",
  "properties": {
    "iso:country":"US",
    "sg:address":"1551 Edgewood Ave W",
    "sg:city":"Jacksonville",
    "sg:classifiers":[
        {
            "category":"Restaurant",
            "type":"Food & Drink"
        }
    ],
    "sg:phone":"+1 904 766 8111",
    "sg:postcode":"32208",
    "sg:province":"FL",
    "sg:tags":[
        "barbecue"
    ],
    "wof:name":"Jerome Brown Barbeque & Wings",
    "wof:placetype":"venue"
},
  "geometry": {"coordinates":[-81.682276,30.389255],"type":"Point"}
}