{
  "type": "Feature",
  "properties": {
    "iso:country":"US",
    "sg:address":"1134 Ruby St",
    "sg:city":"Lakeland",
    "sg:classifiers":[
        {
            "category":"Building & Trades",
            "subcategory":"Construction",
            "type":"Services"
        }
    ],
    "sg:phone":"+1 863 802 8494",
    "sg:postcode":"33815",
    "sg:province":"FL",
    "sg:tags":[
        "painter"
    ],
    "wof:name":"Home Doctors Carpentry",
    "wof:placetype":"venue"
},
  "geometry": {"coordinates":[-81.972932,28.036298],"type":"Point"}
}