{
  "type": "Feature",
  "properties": {
    "addr:full":"2028 Excalibur Dr Orlando FL 32822",
    "addr:housenumber":"2028",
    "addr:postcode":"32822",
    "addr:street":"Excalibur Dr",
    "iso:country":"US",
    "sg:address":"2028 Excalibur Dr",
    "sg:city":"Orlando",
    "sg:classifiers":[
        {
            "category":"Professional",
            "subcategory":"Management & Consulting",
            "type":"Services"
        }
    ],
    "sg:phone":"+1 407 273 3493",
    "sg:postcode":"32822",
    "sg:province":"FL",
    "sg:tags":[
        "consultant"
    ],
    "wof:name":"Tenncom Business Solutions",
    "wof:placetype":"venue"
},
  "geometry": {"coordinates":[-81.27614699999999,28.516815],"type":"Point"}
}