{
  "type": "Feature",
  "properties": {
    "iso:country":"US",
    "sg:address":"6332 NW 9th Ave",
    "sg:city":"Fort Lauderdale",
    "sg:classifiers":[
        {
            "category":"Personal",
            "subcategory":"Beauty Salon",
            "type":"Services"
        }
    ],
    "sg:phone":"+1 954 938 9869",
    "sg:postcode":"33309",
    "sg:province":"FL",
    "sg:tags":[
        "shop"
    ],
    "wof:name":"Profile Hair",
    "wof:placetype":"venue"
},
  "geometry": {"coordinates":[-80.155749,26.206889],"type":"Point"}
}