{
  "type": "Feature",
  "properties": {
    "iso:country":"US",
    "sg:address":"1500 Virginia Ave",
    "sg:city":"Daytona Beach",
    "sg:classifiers":[
        {
            "category":"Real Estate",
            "subcategory":"Real Estate Operator",
            "type":"Services"
        }
    ],
    "sg:phone":"+1 386 238 0554",
    "sg:postcode":"32114",
    "sg:province":"FL",
    "sg:tags":[
        "condominium"
    ],
    "wof:name":"Daytona Beach Golf & Coutntry",
    "wof:placetype":"venue"
},
  "geometry": {"coordinates":[-81.01063000000001,29.18579],"type":"Point"}
}