{
  "type": "Feature",
  "properties": {
    "iso:country":"US",
    "sg:address":"213 N Dixie Hwy",
    "sg:city":"Hallandale Beach",
    "sg:classifiers":[
        {
            "category":"Retail",
            "subcategory":"Auto Repair",
            "type":"Services"
        }
    ],
    "sg:phone":"+1 954 454 1565",
    "sg:postcode":"33009",
    "sg:province":"FL",
    "sg:tags":[
        "repairing",
        "automobile"
    ],
    "wof:name":"Auto Club & Repair Inc",
    "wof:placetype":"venue"
},
  "geometry": {"coordinates":[-80.14859800000001,25.989022],"type":"Point"}
}