{
  "type": "Feature",
  "properties": {
    "iso:country":"US",
    "sg:address":"1802 Weatherstone Dr",
    "sg:city":"Safety Harbor",
    "sg:classifiers":[
        {
            "category":"Restaurant",
            "type":"Food & Drink"
        }
    ],
    "sg:phone":"+1 727 797 8989",
    "sg:postcode":"34695",
    "sg:province":"FL",
    "sg:tags":[
        "eating"
    ],
    "wof:name":"Forbidden City Restaurant The",
    "wof:placetype":"venue"
},
  "geometry": {"coordinates":[-82.706738,28.006911],"type":"Point"}
}