{
  "type": "Feature",
  "properties": {
    "addr:full":"329 NE 166th St Miami FL 33162",
    "addr:housenumber":"329",
    "addr:postcode":"33162",
    "addr:street":"Ne 166Th St",
    "iso:country":"US",
    "sg:address":"329 NE 166th St",
    "sg:city":"Miami",
    "sg:classifiers":[
        {
            "category":"Education",
            "subcategory":"School",
            "type":"Public Place"
        }
    ],
    "sg:phone":"+1 305 945 1444",
    "sg:postcode":"33162",
    "sg:province":"FL",
    "wof:name":"Western General Education",
    "wof:placetype":"venue"
},
  "geometry": {"coordinates":[-80.193693,25.927733],"type":"Point"}
}