{
  "type": "Feature",
  "properties": {
    "iso:country":"US",
    "sg:address":"1906 Collins Ave",
    "sg:city":"Miami",
    "sg:classifiers":[
        {
            "category":"Restaurant",
            "type":"Food & Drink"
        }
    ],
    "sg:menulink":"http://www.allmenus.com/fl/miami-beach/269698-vita/menu/",
    "sg:phone":"+1 305 538 7855",
    "sg:postcode":"33139",
    "sg:province":"FL",
    "sg:tags":[
        "mediterranean"
    ],
    "wof:name":"Vita",
    "wof:placetype":"venue"
},
  "geometry": {"coordinates":[-80.129248,25.795286],"type":"Point"}
}