{
  "type": "Feature",
  "properties": {
    "addr:full":"13985 Brewster Dr Largo FL 33774",
    "addr:housenumber":"13985",
    "addr:postcode":"33774",
    "addr:street":"Brewster Dr",
    "iso:country":"US",
    "sg:address":"13985 Brewster Dr",
    "sg:city":"Largo",
    "sg:classifiers":[
        {
            "category":"Building & Trades",
            "subcategory":"Landscaping Services",
            "type":"Services"
        }
    ],
    "sg:phone":"+1 727 595 5750",
    "sg:postcode":"33774",
    "sg:province":"FL",
    "wof:name":"Total Lawn Care & Landscaping",
    "wof:placetype":"venue"
},
  "geometry": {"coordinates":[-82.83017599999999,27.870511],"type":"Point"}
}