{
  "type": "Feature",
  "properties": {
    "iso:country":"US",
    "sg:address":"5307 Rollins Ave",
    "sg:city":"Jacksonville",
    "sg:classifiers":[
        {
            "category":"Professional",
            "subcategory":"Business Services",
            "type":"Services"
        },
        {
            "category":"Professional",
            "subcategory":"Printing & Photocopies",
            "type":"Services"
        }
    ],
    "sg:phone":"+1 904 636 0824",
    "sg:postcode":"32207",
    "sg:province":"FL",
    "sg:tags":[
        "system",
        "form",
        "printers-business"
    ],
    "wof:name":"Shorty's Place In Cyberspace",
    "wof:placetype":"venue"
},
  "geometry": {"coordinates":[-81.64331799999999,30.265797],"type":"Point"}
}