{
  "type": "Feature",
  "properties": {
    "iso:country":"US",
    "sg:address":"3790 S Tuttle Ave",
    "sg:city":"Sarasota",
    "sg:phone":"+1 941 925 2511",
    "sg:postcode":"34239",
    "sg:province":"FL",
    "sg:website":"http://www.bealls.com/",
    "wof:name":"Bealls Department Store",
    "wof:placetype":"venue"
},
  "geometry": {"coordinates":[-82.514196,27.299651],"type":"Point"}
}