{
  "type": "Feature",
  "properties": {
    "iso:country":"US",
    "sg:address":"19940 Adams Rd",
    "sg:city":"Fort Myers",
    "sg:classifiers":[
        {
            "category":"Building & Trades",
            "subcategory":"Construction",
            "type":"Services"
        }
    ],
    "sg:phone":"+1 239 565 6834",
    "sg:postcode":"33908",
    "sg:province":"FL",
    "sg:tags":[
        "home",
        "builder"
    ],
    "wof:name":"A Welcome Home",
    "wof:placetype":"venue"
},
  "geometry": {"coordinates":[-81.826881,26.449942],"type":"Point"}
}