{
  "type": "Feature",
  "properties": {
    "iso:country":"US",
    "sg:address":"16648 Winners Cir",
    "sg:city":"Delray Beach",
    "sg:classifiers":[
        {
            "category":"Retail",
            "subcategory":"Animal Services",
            "type":"Services"
        }
    ],
    "sg:phone":"+1 561 496 6505",
    "sg:postcode":"33446",
    "sg:province":"FL",
    "sg:tags":[
        "horse",
        "training"
    ],
    "wof:name":"Ronnie Gurfein Stable",
    "wof:placetype":"venue"
},
  "geometry": {"coordinates":[-80.214039,26.427376],"type":"Point"}
}