{
  "type": "Feature",
  "properties": {
    "iso:country":"US",
    "sg:address":"2116 Sunnydale Blvd",
    "sg:city":"Clearwater",
    "sg:classifiers":[
        {
            "category":"Home & Garden",
            "subcategory":"Home Furnishings",
            "type":"Retail Goods"
        }
    ],
    "sg:phone":"+1 727 466 9727",
    "sg:postcode":"33765",
    "sg:province":"FL",
    "sg:tags":[
        "cutlery"
    ],
    "wof:name":"Bojay Masters Of Cutlery",
    "wof:placetype":"venue"
},
  "geometry": {"coordinates":[-82.74997399999999,27.987067],"type":"Point"}
}