{
  "type": "Feature",
  "properties": {
    "addr:full":"5341 Grand Blvd New Port Richey FL 34652",
    "addr:housenumber":"5341",
    "addr:postcode":"34652",
    "addr:street":"Grand Blvd",
    "iso:country":"US",
    "sg:address":"5341 Grand Blvd",
    "sg:city":"New Port Richey",
    "sg:classifiers":[
        {
            "category":"Building & Trades",
            "subcategory":"Equipment Rental",
            "type":"Services"
        }
    ],
    "sg:phone":"+1 727 842 8965",
    "sg:postcode":"34652",
    "sg:province":"FL",
    "sg:tags":[
        "medical"
    ],
    "sg:website":"www.homecaresupply.com",
    "wof:name":"Home Care Supply",
    "wof:placetype":"venue"
},
  "geometry": {"coordinates":[-82.722049,28.236663],"type":"Point"}
}