{
  "type": "Feature",
  "properties": {
    "addr:full":"5453 SE Harbor Ter Stuart FL 34997",
    "addr:housenumber":"5453",
    "addr:postcode":"34997",
    "addr:street":"Se Harbor Ter",
    "iso:country":"US",
    "sg:address":"5453 SE Harbor Ter",
    "sg:city":"Stuart",
    "sg:classifiers":[
        {
            "category":"Bars & Pubs",
            "type":"Food & Drink"
        }
    ],
    "sg:phone":"+1 772 219 7549",
    "sg:postcode":"34997",
    "sg:province":"FL",
    "sg:tags":[
        "drinking"
    ],
    "wof:name":"Rack N Roll Sports Bay &",
    "wof:placetype":"venue"
},
  "geometry": {"coordinates":[-80.179367,27.158226],"type":"Point"}
}