{
  "type": "Feature",
  "properties": {
    "addr:full":"401 Biscayne Blvd Ste S251 Miami FL 33132",
    "addr:housenumber":"401",
    "addr:postcode":"33132",
    "addr:street":"Biscayne Blvd Ste S251",
    "iso:country":"US",
    "sg:address":"401 Biscayne Blvd Ste S251",
    "sg:city":"Miami",
    "sg:classifiers":[
        {
            "category":"Manufacturing",
            "subcategory":"Food",
            "type":"Manufacturing & Wholesale Goods"
        },
        {
            "category":"Restaurant",
            "type":"Food & Drink"
        },
        {
            "category":"Ice Cream",
            "type":"Food & Drink"
        }
    ],
    "sg:phone":"+1 305 371 3497",
    "sg:postcode":"33132",
    "sg:province":"FL",
    "sg:tags":[
        "frozen",
        "dessert",
        "desserts-manufacturers",
        "distributor"
    ],
    "wof:name":"Coco Gelato",
    "wof:placetype":"venue"
},
  "geometry": {"coordinates":[-80.188076,25.77834],"type":"Point"}
}