{
  "type": "Feature",
  "properties": {
    "addr:full":"6946 Curlew Rd Sarasota FL 34241",
    "addr:housenumber":"6946",
    "addr:postcode":"34241",
    "addr:street":"Curlew Rd",
    "iso:country":"US",
    "sg:address":"6946 Curlew Rd",
    "sg:city":"Sarasota",
    "sg:classifiers":[
        {
            "category":"Retail",
            "subcategory":"Repair Shop",
            "type":"Services"
        }
    ],
    "sg:phone":"+1 941 366 4286",
    "sg:postcode":"34241",
    "sg:province":"FL",
    "sg:tags":[
        "refinishing",
        "furniture"
    ],
    "wof:name":"Andrew The Furniture Stylist",
    "wof:placetype":"venue"
},
  "geometry": {"coordinates":[-82.42168100000001,27.265674],"type":"Point"}
}