{
  "type": "Feature",
  "properties": {
    "iso:country":"US",
    "sg:address":"200 Canal St",
    "sg:city":"Miami Springs",
    "sg:classifiers":[
        {
            "category":"Social Services",
            "subcategory":"Child Care",
            "type":"Services"
        },
        {
            "category":"Education",
            "subcategory":"Preschool",
            "type":"Public Place"
        },
        {
            "category":"Education",
            "subcategory":"School",
            "type":"Public Place"
        }
    ],
    "sg:phone":"+1 305 888 1715",
    "sg:postcode":"33166",
    "sg:province":"FL",
    "sg:tags":[
        "elementary",
        "day"
    ],
    "wof:name":"Beavers Kiddie Kollege the New",
    "wof:placetype":"venue"
},
  "geometry": {"coordinates":[-80.282898,25.823999],"type":"Point"}
}