{
  "type": "Feature",
  "properties": {
    "iso:country":"US",
    "sg:address":"2639 Cedar Bluff Ln",
    "sg:city":"Ocoee",
    "sg:classifiers":[
        {
            "category":"Wholesale",
            "subcategory":"Construction Materials",
            "type":"Manufacturing & Wholesale Goods"
        }
    ],
    "sg:phone":"+1 407 292 6872",
    "sg:postcode":"34761",
    "sg:province":"FL",
    "sg:tags":[
        "ceramic"
    ],
    "wof:name":"Design Materials Co Inc",
    "wof:placetype":"venue"
},
  "geometry": {"coordinates":[-81.50311000000001,28.582167],"type":"Point"}
}