{
  "type": "Feature",
  "properties": {
    "iso:country":"US",
    "sg:address":"1693 Glenhaven Cir",
    "sg:city":"Ocoee",
    "sg:classifiers":[
        {
            "category":"Building & Trades",
            "subcategory":"Construction",
            "type":"Services"
        }
    ],
    "sg:phone":"+1 407 963 6608",
    "sg:postcode":"34761",
    "sg:province":"FL",
    "sg:tags":[
        "residential",
        "real estate",
        "trust",
        "investment"
    ],
    "wof:name":"A & M Bryan LLC",
    "wof:placetype":"venue"
},
  "geometry": {"coordinates":[-81.518826,28.577007],"type":"Point"}
}