{
  "type": "Feature",
  "properties": {
    "iso:country":"US",
    "sg:address":"8698 Commerce St",
    "sg:city":"Cape Canaveral",
    "sg:classifiers":[
        {
            "category":"Real Estate",
            "subcategory":"Real Estate Agent",
            "type":"Services"
        }
    ],
    "sg:phone":"+1 321 784 7575",
    "sg:postcode":"32920",
    "sg:province":"FL",
    "wof:name":"ABC Realty Of Brevard Inc",
    "wof:placetype":"venue"
},
  "geometry": {"coordinates":[-80.61159499999999,28.395597],"type":"Point"}
}