{
  "type": "Feature",
  "properties": {
    "addr:full":"10250 NW 53rd St Sunrise FL 33351",
    "addr:housenumber":"10250",
    "addr:postcode":"33351",
    "addr:street":"Nw 53Rd St",
    "iso:country":"US",
    "sg:address":"10250 NW 53rd St",
    "sg:city":"Sunrise",
    "sg:classifiers":[
        {
            "category":"Organizations",
            "subcategory":"Non-profit Organization",
            "type":"Services"
        }
    ],
    "sg:phone":"+1 954 344 2670",
    "sg:postcode":"33351",
    "sg:province":"FL",
    "sg:tags":[
        "charity",
        "foundations-educational",
        "philanthropic",
        "research"
    ],
    "sg:website":"http://www.bgcdownsyndrome.org",
    "wof:name":"Broward County Gold Coast Down Syndrome Organization",
    "wof:placetype":"venue"
},
  "geometry": {"coordinates":[-80.287128,26.189292],"type":"Point"}
}