{
  "type": "Feature",
  "properties": {
    "iso:country":"US",
    "sg:address":"15225 NE 6th Ave",
    "sg:city":"Miami",
    "sg:classifiers":[
        {
            "category":"Social Services",
            "subcategory":"Adult Care",
            "type":"Services"
        }
    ],
    "sg:phone":"+1 786 955 6632",
    "sg:postcode":"33162",
    "sg:province":"FL",
    "sg:tags":[
        "counselor",
        "relation",
        "human"
    ],
    "wof:name":"Urban Resource Strategists Inc",
    "wof:placetype":"venue"
},
  "geometry": {"coordinates":[-80.187624,25.91527],"type":"Point"}
}