{
  "type": "Feature",
  "properties": {
    "iso:country":"US",
    "sg:address":"160 Hope St",
    "sg:city":"Longwood",
    "sg:classifiers":[
        {
            "category":"Building & Trades",
            "subcategory":"Construction",
            "type":"Services"
        }
    ],
    "sg:phone":"+1 407 830 5599",
    "sg:postcode":"32750",
    "sg:province":"FL",
    "sg:tags":[
        "finishing",
        "wood",
        "refinishing"
    ],
    "wof:name":"Architectural Custom Finishes",
    "wof:placetype":"venue"
},
  "geometry": {"coordinates":[-81.357893,28.695344],"type":"Point"}
}