{
  "type": "Feature",
  "properties": {
    "iso:country":"US",
    "sg:address":"962 Candlelight Blvd",
    "sg:city":"Brooksville",
    "sg:classifiers":[
        {
            "category":"Personal",
            "subcategory":"Beauty Salon",
            "type":"Services"
        }
    ],
    "sg:phone":"+1 352 799 7737",
    "sg:postcode":"34601",
    "sg:province":"FL",
    "sg:tags":[
        "shop"
    ],
    "wof:name":"Candlelight Hair Design",
    "wof:placetype":"venue"
},
  "geometry": {"coordinates":[-82.403828,28.544792],"type":"Point"}
}