{
  "type": "Feature",
  "properties": {
    "addr:full":"306 NE 7th St Okeechobee FL 34972",
    "addr:housenumber":"306",
    "addr:postcode":"34972",
    "addr:street":"Ne 7Th St",
    "iso:country":"US",
    "sg:address":"306 NE 7th St",
    "sg:city":"Okeechobee",
    "sg:classifiers":[
        {
            "category":"Wholesale",
            "subcategory":"Groceries",
            "type":"Manufacturing & Wholesale Goods"
        }
    ],
    "sg:phone":"+1 863 763 3728",
    "sg:postcode":"34972",
    "sg:province":"FL",
    "sg:tags":[
        "confectionery"
    ],
    "wof:name":"Charlies Partner",
    "wof:placetype":"venue"
},
  "geometry": {"coordinates":[-80.827522,27.249958],"type":"Point"}
}