{
  "type": "Feature",
  "properties": {
    "addr:full":"3502 SE 18th Pl Cape Coral FL 33904",
    "addr:housenumber":"3502",
    "addr:postcode":"33904",
    "addr:street":"Se 18Th Pl",
    "iso:country":"US",
    "sg:address":"3502 SE 18th Pl",
    "sg:city":"Cape Coral",
    "sg:classifiers":[
        {
            "category":"Building & Trades",
            "subcategory":"Cleaning & Sanitation",
            "type":"Services"
        }
    ],
    "sg:phone":"+1 239 945 4283",
    "sg:postcode":"33904",
    "sg:province":"FL",
    "sg:tags":[
        "janitor"
    ],
    "wof:name":"All Night Cleaning",
    "wof:placetype":"venue"
},
  "geometry": {"coordinates":[-81.935937,26.5884],"type":"Point"}
}