{
  "type": "Feature",
  "properties": {
    "addr:full":"3421 SW 107th Ave Miami FL 33165",
    "addr:housenumber":"3421",
    "addr:postcode":"33165",
    "addr:street":"Sw 107Th Ave",
    "iso:country":"US",
    "sg:address":"3421 SW 107th Ave",
    "sg:city":"Miami",
    "sg:classifiers":[
        {
            "category":"Wholesale",
            "subcategory":"Chemicals & Plastics",
            "type":"Manufacturing & Wholesale Goods"
        }
    ],
    "sg:phone":"+1 305 559 6687",
    "sg:postcode":"33165",
    "sg:province":"FL",
    "wof:name":"Search Medical",
    "wof:placetype":"venue"
},
  "geometry": {"coordinates":[-80.36765699999999,25.736121],"type":"Point"}
}