{
  "type": "Feature",
  "properties": {
    "iso:country":"US",
    "sg:address":"11290 Park Blvd",
    "sg:city":"Seminole",
    "sg:classifiers":[
        {
            "category":"Banks & Credit Unions",
            "subcategory":"Financial Services",
            "type":"Services"
        },
        {
            "category":"Professional",
            "subcategory":"Credit Reporting & Collection",
            "type":"Services"
        }
    ],
    "sg:phone":"+1 727 391 5346",
    "sg:postcode":"33772",
    "sg:province":"FL",
    "sg:tags":[
        "counseling",
        "repair",
        "debt",
        "plan",
        "investigator"
    ],
    "wof:name":"A American Debt Consolidation",
    "wof:placetype":"venue"
},
  "geometry": {"coordinates":[-82.79470499999999,27.841273],"type":"Point"}
}