{
  "type": "Feature",
  "properties": {
    "iso:country":"US",
    "sg:address":"4120 Staffordshire Dr",
    "sg:city":"Lakeland",
    "sg:classifiers":[
        {
            "category":"Restaurant",
            "type":"Food & Drink"
        }
    ],
    "sg:phone":"+1 863 858 2198",
    "sg:postcode":"33809",
    "sg:province":"FL",
    "sg:tags":[
        "asian",
        "chinese",
        "pan"
    ],
    "wof:name":"Robert & Annie Inc",
    "wof:placetype":"venue"
},
  "geometry": {"coordinates":[-81.966345,28.094955],"type":"Point"}
}