{
  "type": "Feature",
  "properties": {
    "iso:country":"US",
    "sg:address":"8474 Lockwood Ridge Rd",
    "sg:city":"Sarasota",
    "sg:classifiers":[
        {
            "category":"Personal",
            "subcategory":"Nail Salon",
            "type":"Services"
        }
    ],
    "sg:phone":"+1 941 351 9808",
    "sg:postcode":"34243",
    "sg:province":"FL",
    "wof:name":"Happy Nails 2",
    "wof:placetype":"venue"
},
  "geometry": {"coordinates":[-82.50561999999999,27.389491],"type":"Point"}
}