{
  "type": "Feature",
  "properties": {
    "addr:full":"2216 Ali Baba Ave Opa Locka FL 33054",
    "addr:housenumber":"2216",
    "addr:postcode":"33054",
    "addr:street":"Ali Baba Ave;Locka",
    "iso:country":"US",
    "sg:address":"2216 Ali Baba Ave",
    "sg:city":"Opa Locka",
    "sg:classifiers":[
        {
            "category":"Autos & Motor Vehicles",
            "subcategory":"Automobile Sales",
            "type":"Retail Goods"
        }
    ],
    "sg:phone":"+1 305 685 3333",
    "sg:postcode":"33054",
    "sg:province":"FL",
    "sg:tags":[
        "car",
        "dealer"
    ],
    "wof:name":"One Stop Shop",
    "wof:placetype":"venue"
},
  "geometry": {"coordinates":[-80.239564,25.907124],"type":"Point"}
}