{
  "type": "Feature",
  "properties": {
    "addr:full":"6934 W Comanche Ave Tampa FL 33634",
    "addr:housenumber":"6934",
    "addr:postcode":"33634",
    "addr:street":"W Comanche Ave",
    "iso:country":"US",
    "sg:address":"6934 W Comanche Ave",
    "sg:city":"Tampa",
    "sg:classifiers":[
        {
            "category":"Organizations",
            "subcategory":"Religious Organization",
            "type":"Services"
        }
    ],
    "sg:phone":"+1 813 885 2906",
    "sg:postcode":"33634",
    "sg:province":"FL",
    "sg:tags":[
        "church"
    ],
    "wof:name":"Fuente De Vida Eterna",
    "wof:placetype":"venue"
},
  "geometry": {"coordinates":[-82.559772,27.999188],"type":"Point"}
}