{
  "type": "Feature",
  "properties": {
    "iso:country":"US",
    "sg:address":"8157 State Rd 52",
    "sg:city":"Hudson",
    "sg:classifiers":[
        {
            "category":"Retail",
            "subcategory":"Animal Services",
            "type":"Services"
        }
    ],
    "sg:phone":"+1 727 861 1057",
    "sg:postcode":"34667",
    "sg:province":"FL",
    "sg:tags":[
        "pet",
        "grooming",
        "washing"
    ],
    "wof:name":"Love On A Leash",
    "wof:placetype":"venue"
},
  "geometry": {"coordinates":[-82.67326799999999,28.331079],"type":"Point"}
}