{
  "type": "Feature",
  "properties": {
    "iso:country":"US",
    "sg:address":"13150 90th St N",
    "sg:city":"Largo",
    "sg:classifiers":[
        {
            "category":"Manufacturing",
            "subcategory":"Printing",
            "type":"Manufacturing & Wholesale Goods"
        }
    ],
    "sg:phone":"+1 727 518 2830",
    "sg:postcode":"33773",
    "sg:province":"FL",
    "sg:tags":[
        "printer"
    ],
    "wof:name":"Onyx Graphics",
    "wof:placetype":"venue"
},
  "geometry": {"coordinates":[-82.76501399999999,27.891796],"type":"Point"}
}