{
  "type": "Feature",
  "properties": {
    "addr:full":"1204 S Atlantic Ave Daytona Beach FL 32118",
    "addr:housenumber":"1204",
    "addr:postcode":"32118",
    "addr:street":"S Atlantic Ave",
    "iso:country":"US",
    "sg:address":"1204 S Atlantic Ave",
    "sg:city":"Daytona Beach",
    "sg:classifiers":[
        {
            "category":"Food & Beverages",
            "subcategory":"Groceries & Convenience Stores",
            "type":"Retail Goods"
        }
    ],
    "sg:phone":"+1 386 226 4212",
    "sg:postcode":"32118",
    "sg:province":"FL",
    "wof:name":"Sunrise Food Mart",
    "wof:placetype":"venue"
},
  "geometry": {"coordinates":[-81.000373,29.210768],"type":"Point"}
}