{
  "type": "Feature",
  "properties": {
    "iso:country":"US",
    "sg:address":"9930 Old Baymeadows Rd",
    "sg:city":"Jacksonville",
    "sg:classifiers":[
        {
            "category":"Personal",
            "subcategory":"Beauty Salon",
            "type":"Services"
        }
    ],
    "sg:phone":"+1 904 641 9463",
    "sg:postcode":"32256",
    "sg:province":"FL",
    "wof:name":"American Nails",
    "wof:placetype":"venue"
},
  "geometry": {"coordinates":[-81.55295599999999,30.220714],"type":"Point"}
}