{
  "type": "Feature",
  "properties": {
    "iso:country":"US",
    "sg:address":"6550 Gunn Hwy",
    "sg:city":"Tampa",
    "sg:classifiers":[
        {
            "category":"Health Services",
            "subcategory":"Doctor",
            "type":"Services"
        }
    ],
    "sg:phone":"+1 813 968 2710",
    "sg:postcode":"33625",
    "sg:province":"FL",
    "sg:tags":[
        "physician",
        "pediatrics",
        "family",
        "practice",
        "surgeons",
        "medicine",
        "surgeon",
        "public"
    ],
    "sg:website":"http://www.pedialliance.com",
    "wof:name":"Pediatric Health Care Alliance Citrus Park Office",
    "wof:placetype":"venue"
},
  "geometry": {"coordinates":[-82.560655,28.065369],"type":"Point"}
}