{
  "type": "Feature",
  "properties": {
    "iso:country":"US",
    "sg:address":"1501 E Park Ave",
    "sg:city":"Tallahassee",
    "sg:classifiers":[
        {
            "category":"Professional",
            "subcategory":"Lawyer & Legal Services",
            "type":"Services"
        }
    ],
    "sg:phone":"+1 850 681 2303",
    "sg:postcode":"32301",
    "sg:province":"FL",
    "sg:tags":[
        "attorney"
    ],
    "wof:name":"Flowers & White",
    "wof:placetype":"venue"
},
  "geometry": {"coordinates":[-84.256443,30.441694],"type":"Point"}
}