{
  "type": "Feature",
  "properties": {
    "addr:full":"230 Cypress Gardens Blvd Winter Haven FL 33880",
    "addr:housenumber":"230",
    "addr:postcode":"33880",
    "addr:street":"Cypress Gardens Blvd",
    "iso:country":"US",
    "sg:address":"230 Cypress Gardens Blvd",
    "sg:city":"Winter Haven",
    "sg:classifiers":[
        {
            "category":"Restaurant",
            "type":"Food & Drink"
        }
    ],
    "sg:menulink":"http://www.allmenus.com/fl/winter-haven-auburndale/128259-red-lobster/menu/",
    "sg:phone":"+1 863 294 8844",
    "sg:postcode":"33880",
    "sg:province":"FL",
    "sg:tags":[
        "seafood",
        "american"
    ],
    "wof:name":"Red Lobster",
    "wof:placetype":"venue"
},
  "geometry": {"coordinates":[-81.725369,28.004034],"type":"Point"}
}