{
  "type": "Feature",
  "properties": {
    "iso:country":"US",
    "sg:address":"3690 NW 62nd St",
    "sg:city":"Miami",
    "sg:classifiers":[
        {
            "category":"Professional",
            "subcategory":"Advertising",
            "type":"Services"
        }
    ],
    "sg:phone":"+1 305 638 3189",
    "sg:postcode":"33147",
    "sg:province":"FL",
    "sg:tags":[
        "agency"
    ],
    "wof:name":"Link Enterprises",
    "wof:placetype":"venue"
},
  "geometry": {"coordinates":[-80.257176,25.830785],"type":"Point"}
}