{
  "type": "Feature",
  "properties": {
    "addr:full":"2962 S Ridgewood Ave Edgewater FL 32141",
    "addr:housenumber":"2962",
    "addr:postcode":"32141",
    "addr:street":"S Ridgewood Ave",
    "iso:country":"US",
    "sg:address":"2962 S Ridgewood Ave",
    "sg:city":"Edgewater",
    "sg:classifiers":[
        {
            "category":"Cinema",
            "subcategory":"Movie Rental",
            "type":"Entertainment"
        }
    ],
    "sg:phone":"+1 386 423 9100",
    "sg:postcode":"32141",
    "sg:province":"FL",
    "sg:tags":[
        "video",
        "tape"
    ],
    "wof:name":"Blockbuster",
    "wof:placetype":"venue"
},
  "geometry": {"coordinates":[-80.884225,28.948767],"type":"Point"}
}