{
  "type": "Feature",
  "properties": {
    "iso:country":"US",
    "sg:address":"794 Broad Ave S",
    "sg:city":"Naples",
    "sg:classifiers":[
        {
            "category":"Home & Garden",
            "subcategory":"Home Furnishings",
            "type":"Retail Goods"
        },
        {
            "category":"Shopping",
            "subcategory":"Gifts & Souvenirs",
            "type":"Retail Goods"
        }
    ],
    "sg:phone":"+1 239 261 6658",
    "sg:postcode":"34102",
    "sg:province":"FL",
    "sg:tags":[
        "pottery"
    ],
    "wof:name":"Earth & Fire Inc",
    "wof:placetype":"venue"
},
  "geometry": {"coordinates":[-81.796268,26.133852],"type":"Point"}
}