{
  "type": "Feature",
  "properties": {
    "addr:full":"6508 Moonshell Ct Orlando FL 32819",
    "addr:housenumber":"6508",
    "addr:postcode":"32819",
    "addr:street":"Moonshell Ct",
    "iso:country":"US",
    "sg:address":"6508 Moonshell Ct",
    "sg:city":"Orlando",
    "sg:classifiers":[
        {
            "category":"Real Estate",
            "subcategory":"Real Estate Operator",
            "type":"Services"
        }
    ],
    "sg:phone":"+1 407 578 5693",
    "sg:postcode":"32819",
    "sg:province":"FL",
    "sg:tags":[
        "building",
        "apartment"
    ],
    "wof:name":"Broadfield Apartments Corp",
    "wof:placetype":"venue"
},
  "geometry": {"coordinates":[-81.468475,28.488779],"type":"Point"}
}