{
  "type": "Feature",
  "properties": {
    "iso:country":"US",
    "sg:address":"8501 Palm Pkwy",
    "sg:city":"Orlando",
    "sg:classifiers":[
        {
            "category":"Travel",
            "subcategory":"Hotels & Motels",
            "type":"Entertainment"
        }
    ],
    "sg:phone":"+1 407 239 6900",
    "sg:postcode":"32836",
    "sg:province":"FL",
    "sg:website":"http://www.marriott.com",
    "wof:name":"Courtyard by Marriott Orlando Lake Buena Vista at Vista Centre",
    "wof:placetype":"venue"
},
  "geometry": {"coordinates":[-81.501116,28.385932],"type":"Point"}
}