{
  "type": "Feature",
  "properties": {
    "iso:country":"US",
    "sg:address":"213 S Parramore Ave",
    "sg:city":"Orlando",
    "sg:classifiers":[
        {
            "category":"Personal",
            "subcategory":"Beauty Salon",
            "type":"Services"
        }
    ],
    "sg:phone":"+1 407 423 7899",
    "sg:postcode":"32805",
    "sg:province":"FL",
    "wof:name":"Classic Cuts",
    "wof:placetype":"venue"
},
  "geometry": {"coordinates":[-81.38900700000001,28.540035],"type":"Point"}
}