{
  "type": "Feature",
  "properties": {
    "iso:country":"US",
    "sg:address":"10328 Kitten Trl",
    "sg:city":"Port Richey",
    "sg:classifiers":[
        {
            "category":"Building & Trades",
            "subcategory":"Construction",
            "type":"Services"
        }
    ],
    "sg:phone":"+1 727 862 1543",
    "sg:postcode":"34669",
    "sg:province":"FL",
    "sg:tags":[
        "ceiling",
        "retail",
        "installation",
        "sales",
        "dome"
    ],
    "wof:name":"Lumilite Dome Ceilings",
    "wof:placetype":"venue"
},
  "geometry": {"coordinates":[-82.646304,28.373338],"type":"Point"}
}