{
  "type": "Feature",
  "properties": {
    "iso:country":"US",
    "sg:address":"13515 Old Dock Rd",
    "sg:city":"Orlando",
    "sg:classifiers":[
        {
            "category":"Shopping",
            "subcategory":"Computers & Home Electronics",
            "type":"Retail Goods"
        }
    ],
    "sg:phone":"+1 407 381 0906",
    "sg:postcode":"32828",
    "sg:province":"FL",
    "sg:tags":[
        "software"
    ],
    "wof:name":"Care Manager Pro",
    "wof:placetype":"venue"
},
  "geometry": {"coordinates":[-81.18312400000001,28.556991],"type":"Point"}
}