{
  "type": "Feature",
  "properties": {
    "addr:full":"38 Sweetwater Creek Cir Oviedo FL 32765",
    "addr:housenumber":"38",
    "addr:postcode":"32765",
    "addr:street":"Sweetwater Creek Cir",
    "iso:country":"US",
    "sg:address":"38 Sweetwater Creek Cir",
    "sg:city":"Oviedo",
    "sg:classifiers":[
        {
            "category":"Arts & Performance",
            "subcategory":"Theater",
            "type":"Entertainment"
        }
    ],
    "sg:phone":"+1 407 359 8916",
    "sg:postcode":"32765",
    "sg:province":"FL",
    "sg:tags":[
        "live",
        "music"
    ],
    "wof:name":"Jonathan Parker DJ",
    "wof:placetype":"venue"
},
  "geometry": {"coordinates":[-81.208367,28.678105],"type":"Point"}
}