{
  "type": "Feature",
  "properties": {
    "addr:full":"7436 Goldeneye Dr New Port Richey FL 34654",
    "addr:housenumber":"7436",
    "addr:postcode":"34654",
    "addr:street":"Goldeneye Dr",
    "iso:country":"US",
    "sg:address":"7436 Goldeneye Dr",
    "sg:city":"New Port Richey",
    "sg:classifiers":[
        {
            "category":"Professional",
            "type":"Services"
        }
    ],
    "sg:phone":"+1 727 849 5105",
    "sg:postcode":"34654",
    "sg:province":"FL",
    "wof:name":"Kenneth Taylor Svc Inc",
    "wof:placetype":"venue"
},
  "geometry": {"coordinates":[-82.64627900000001,28.265206],"type":"Point"}
}