{
  "type": "Feature",
  "properties": {
    "addr:full":"10475 SW 186th Ave Miami FL 33196",
    "addr:housenumber":"10475",
    "addr:postcode":"33196",
    "addr:street":"Sw 186Th Ave",
    "iso:country":"US",
    "sg:address":"10475 SW 186th Ave",
    "sg:city":"Miami",
    "sg:classifiers":[
        {
            "category":"Retail",
            "subcategory":"Auto Repair",
            "type":"Services"
        }
    ],
    "sg:phone":"+1 305 233 5868",
    "sg:postcode":"33196",
    "sg:province":"FL",
    "sg:tags":[
        "body",
        "automobile",
        "painting",
        "repairing"
    ],
    "wof:name":"Jorman Body Shop",
    "wof:placetype":"venue"
},
  "geometry": {"coordinates":[-80.494935,25.666215],"type":"Point"}
}