{
  "type": "Feature",
  "properties": {
    "iso:country":"US",
    "sg:address":"5367 S Florida Ave",
    "sg:city":"Lakeland",
    "sg:classifiers":[
        {
            "category":"Professional",
            "subcategory":"Employment Agencies",
            "type":"Services"
        }
    ],
    "sg:phone":"+1 863 646 6118",
    "sg:postcode":"33813",
    "sg:province":"FL",
    "sg:tags":[
        "opportunity",
        "contractor"
    ],
    "wof:name":"A-1 Temps Lakeland",
    "wof:placetype":"venue"
},
  "geometry": {"coordinates":[-81.964568,27.967809],"type":"Point"}
}