{
  "type": "Feature",
  "properties": {
    "iso:country":"US",
    "sg:address":"9210 SW 72nd St",
    "sg:city":"Miami",
    "sg:classifiers":[
        {
            "category":"Government",
            "subcategory":"Office",
            "type":"Public Place"
        }
    ],
    "sg:phone":"+1 305 275 1800",
    "sg:postcode":"33173",
    "sg:province":"FL",
    "wof:name":"Congressman I Ros-Lehtinen",
    "wof:placetype":"venue"
},
  "geometry": {"coordinates":[-80.342799,25.70187],"type":"Point"}
}