{
  "type": "Feature",
  "properties": {
    "addr:full":"3483 River Gardens Cir Pensacola FL 32514",
    "addr:housenumber":"3483",
    "addr:postcode":"32514",
    "addr:street":"River Gardens Cir",
    "iso:country":"US",
    "sg:address":"3483 River Gardens Cir",
    "sg:city":"Pensacola",
    "sg:classifiers":[
        {
            "category":"Professional",
            "subcategory":"Management & Consulting",
            "type":"Services"
        }
    ],
    "sg:phone":"+1 850 479 9925",
    "sg:postcode":"32514",
    "sg:province":"FL",
    "sg:tags":[
        "consultant",
        "business"
    ],
    "wof:name":"Derm Resources",
    "wof:placetype":"venue"
},
  "geometry": {"coordinates":[-87.19554599999999,30.532645],"type":"Point"}
}