{
  "type": "Feature",
  "properties": {
    "iso:country":"US",
    "sg:address":"920 Sebring Sq",
    "sg:city":"Sebring",
    "sg:classifiers":[
        {
            "category":"Shopping",
            "subcategory":"Clothing, Apparel, & Fashions",
            "type":"Retail Goods"
        }
    ],
    "sg:phone":"+1 863 386 9493",
    "sg:postcode":"33870",
    "sg:province":"FL",
    "wof:name":"Sue's Cubby Hole",
    "wof:placetype":"venue"
},
  "geometry": {"coordinates":[-81.49299499999999,27.512805],"type":"Point"}
}