{
  "type": "Feature",
  "properties": {
    "iso:country":"US",
    "sg:address":"4960 Sycamore Dr",
    "sg:city":"Naples",
    "sg:classifiers":[
        {
            "category":"Professional",
            "subcategory":"Employment Agencies",
            "type":"Services"
        },
        {
            "category":"Professional",
            "subcategory":"Lawyer & Legal Services",
            "type":"Services"
        }
    ],
    "sg:phone":"+1 239 353 8340",
    "sg:postcode":"34119",
    "sg:province":"FL",
    "sg:tags":[
        "convention",
        "secretarial",
        "reporters-court"
    ],
    "wof:name":"Donna A Carey Secretarial Svc",
    "wof:placetype":"venue"
},
  "geometry": {"coordinates":[-81.707728,26.213874],"type":"Point"}
}