{
  "type": "Feature",
  "properties": {
    "addr:full":"13611 McGregor Blvd Fort Myers FL 33919",
    "addr:housenumber":"13611",
    "addr:postcode":"33919",
    "addr:street":"Mcgregor Blvd",
    "iso:country":"US",
    "sg:address":"13611 McGregor Blvd",
    "sg:city":"Fort Myers",
    "sg:classifiers":[
        {
            "category":"Home & Garden",
            "subcategory":"Household Appliances",
            "type":"Retail Goods"
        }
    ],
    "sg:phone":"+1 239 415 1107",
    "sg:postcode":"33919",
    "sg:province":"FL",
    "sg:tags":[
        "cleaners",
        "vacuum"
    ],
    "wof:name":"Winter Edge LLC",
    "wof:placetype":"venue"
},
  "geometry": {"coordinates":[-81.91499,26.544107],"type":"Point"}
}