{
  "type": "Feature",
  "properties": {
    "addr:full":"930 Ponder Ave Sarasota FL 34232",
    "addr:housenumber":"930",
    "addr:postcode":"34232",
    "addr:street":"Ponder Ave",
    "iso:country":"US",
    "sg:address":"930 Ponder Ave",
    "sg:city":"Sarasota",
    "sg:classifiers":[
        {
            "category":"Building & Trades",
            "subcategory":"Landscaping Services",
            "type":"Services"
        }
    ],
    "sg:phone":"+1 941 371 3600",
    "sg:postcode":"34232",
    "sg:province":"FL",
    "wof:name":"Sheer Perfection",
    "wof:placetype":"venue"
},
  "geometry": {"coordinates":[-82.45935900000001,27.325033],"type":"Point"}
}