{
  "type": "Feature",
  "properties": {
    "iso:country":"US",
    "sg:address":"6000 Winegard Rd",
    "sg:city":"Orlando",
    "sg:classifiers":[
        {
            "category":"Education",
            "subcategory":"School",
            "type":"Public Place"
        }
    ],
    "sg:phone":"+1 407 852 3200",
    "sg:postcode":"32809",
    "sg:province":"FL",
    "sg:tags":[
        "high"
    ],
    "sg:website":"http://www.tchsbands.com",
    "wof:name":"Oak Ridge High School",
    "wof:placetype":"venue"
},
  "geometry": {"coordinates":[-81.38430200000001,28.470256],"type":"Point"}
}