{
  "type": "Feature",
  "properties": {
    "iso:country":"US",
    "sg:address":"250 Fryer Ln",
    "sg:city":"Sanford",
    "sg:classifiers":[
        {
            "category":"Ferry",
            "type":"Transportation"
        }
    ],
    "sg:phone":"+1 407 321 0753",
    "sg:postcode":"32773",
    "sg:province":"FL",
    "sg:tags":[
        "boat"
    ],
    "wof:name":"Central Florida Airboat Tours",
    "wof:placetype":"venue"
},
  "geometry": {"coordinates":[-81.266147,28.741701],"type":"Point"}
}