{
  "type": "Feature",
  "properties": {
    "iso:country":"US",
    "sg:address":"1255 Florida Ave S",
    "sg:city":"Rockledge",
    "sg:classifiers":[
        {
            "category":"Autos & Motor Vehicles",
            "subcategory":"Auto Supplies",
            "type":"Retail Goods"
        }
    ],
    "sg:phone":"+1 321 433 3255",
    "sg:postcode":"32955",
    "sg:province":"FL",
    "sg:tags":[
        "automobile",
        "part"
    ],
    "wof:name":"Assisting Hands Home Care",
    "wof:placetype":"venue"
},
  "geometry": {"coordinates":[-80.726021,28.34037],"type":"Point"}
}