{
  "type": "Feature",
  "properties": {
    "iso:country":"US",
    "sg:address":"7246 NW 31st St",
    "sg:city":"Miami",
    "sg:classifiers":[
        {
            "category":"Shopping",
            "subcategory":"Computers & Home Electronics",
            "type":"Retail Goods"
        }
    ],
    "sg:phone":"+1 305 599 8677",
    "sg:postcode":"33122",
    "sg:province":"FL",
    "wof:name":"Computer Systems 2000 Corp",
    "wof:placetype":"venue"
},
  "geometry": {"coordinates":[-80.315381,25.802473],"type":"Point"}
}