{
  "type": "Feature",
  "properties": {
    "iso:country":"US",
    "sg:address":"17 Azalea Ave",
    "sg:city":"Middleburg",
    "sg:classifiers":[
        {
            "category":"Organizations",
            "subcategory":"Religious Organization",
            "type":"Services"
        }
    ],
    "sg:phone":"+1 904 282 2957",
    "sg:postcode":"32068",
    "sg:province":"FL",
    "sg:tags":[
        "church"
    ],
    "wof:name":"Middleburg Church Of God",
    "wof:placetype":"venue"
},
  "geometry": {"coordinates":[-81.892425,30.065034],"type":"Point"}
}