{
  "type": "Feature",
  "properties": {
    "iso:country":"US",
    "sg:address":"3332 NE 190th St Apt 2816",
    "sg:city":"Miami",
    "sg:classifiers":[
        {
            "category":"Banks & Credit Unions",
            "subcategory":"Investment Brokerage",
            "type":"Services"
        }
    ],
    "sg:phone":"+1 561 827 7297",
    "sg:postcode":"33180",
    "sg:province":"FL",
    "sg:tags":[
        "transfer",
        "bond",
        "agent",
        "stock"
    ],
    "wof:name":"Icap International",
    "wof:placetype":"venue"
},
  "geometry": {"coordinates":[-80.136186,25.952089],"type":"Point"}
}