{
  "type": "Feature",
  "properties": {
    "addr:full":"3643 Saint Johns Ave Jacksonville FL 32205",
    "addr:housenumber":"3643",
    "addr:postcode":"32205",
    "addr:street":"Saint Johns Ave",
    "iso:country":"US",
    "sg:address":"3643 Saint Johns Ave",
    "sg:city":"Jacksonville",
    "sg:classifiers":[
        {
            "category":"Shopping",
            "subcategory":"Clothing, Apparel, & Fashions",
            "type":"Retail Goods"
        }
    ],
    "sg:phone":"+1 904 389 6140",
    "sg:postcode":"32205",
    "sg:province":"FL",
    "wof:name":"Petal",
    "wof:placetype":"venue"
},
  "geometry": {"coordinates":[-81.69908100000001,30.3005],"type":"Point"}
}