{
  "type": "Feature",
  "properties": {
    "iso:country":"US",
    "sg:address":"530 Fleming Ave",
    "sg:city":"Greenacres",
    "sg:classifiers":[
        {
            "category":"Shopping",
            "subcategory":"Crafts & Fabrics",
            "type":"Retail Goods"
        },
        {
            "category":"Professional",
            "subcategory":"Art Services",
            "type":"Services"
        }
    ],
    "sg:phone":"+1 561 969 6529",
    "sg:postcode":"33463",
    "sg:province":"FL",
    "sg:tags":[
        "punching",
        "design",
        "embroidery"
    ],
    "wof:name":"All American Handyworks Inc",
    "wof:placetype":"venue"
},
  "geometry": {"coordinates":[-80.129034,26.629149],"type":"Point"}
}