{
  "type": "Feature",
  "properties": {
    "addr:full":"237 Interstate Blvd Sarasota FL 34240",
    "addr:housenumber":"237",
    "addr:postcode":"34240",
    "addr:street":"Interstate Blvd",
    "iso:country":"US",
    "sg:address":"237 Interstate Blvd",
    "sg:city":"Sarasota",
    "sg:classifiers":[
        {
            "category":"Autos & Motor Vehicles",
            "subcategory":"Auto Supplies",
            "type":"Retail Goods"
        }
    ],
    "sg:phone":"+1 941 371 6669",
    "sg:postcode":"34240",
    "sg:province":"FL",
    "sg:tags":[
        "radiator"
    ],
    "wof:name":"Performance Radiator Of Nc",
    "wof:placetype":"venue"
},
  "geometry": {"coordinates":[-82.445517,27.3343],"type":"Point"}
}