{
  "type": "Feature",
  "properties": {
    "iso:country":"US",
    "sg:address":"2665 N Atlantic Ave",
    "sg:city":"Daytona Beach",
    "sg:classifiers":[
        {
            "category":"Professional",
            "type":"Services"
        }
    ],
    "sg:phone":"+1 386 871 5150",
    "sg:postcode":"32118",
    "sg:province":"FL",
    "wof:name":"An Exotic Diva",
    "wof:placetype":"venue"
},
  "geometry": {"coordinates":[-81.02458300000001,29.260929],"type":"Point"}
}