{
  "type": "Feature",
  "properties": {
    "addr:full":"22670 Vistawood Way Boca Raton FL 33428",
    "addr:postcode":"22670;33428",
    "addr:street":"Vistawood Way",
    "iso:country":"US",
    "sg:address":"22670 Vistawood Way",
    "sg:city":"Boca Raton",
    "sg:classifiers":[
        {
            "category":"Retail",
            "subcategory":"Auto Repair",
            "type":"Services"
        }
    ],
    "sg:phone":"+1 561 487 9374",
    "sg:postcode":"33428",
    "sg:province":"FL",
    "sg:tags":[
        "body"
    ],
    "wof:name":"B & K Auto Trim",
    "wof:placetype":"venue"
},
  "geometry": {"coordinates":[-80.227295,26.339593],"type":"Point"}
}