{
  "type": "Feature",
  "properties": {
    "addr:full":"990 Crystal Cresst Ter Crystal River FL 34429",
    "addr:housenumber":"990",
    "addr:postcode":"34429",
    "addr:street":"Crystal Cresst Ter",
    "iso:country":"US",
    "sg:address":"990 Crystal Cresst Ter",
    "sg:city":"Crystal River",
    "sg:classifiers":[
        {
            "category":"Autos & Motor Vehicles",
            "subcategory":"Boat Sales",
            "type":"Retail Goods"
        }
    ],
    "sg:phone":"+1 352 795 2597",
    "sg:postcode":"34429",
    "sg:province":"FL",
    "sg:tags":[
        "marine",
        "accessory"
    ],
    "wof:name":"Crystal River Marine Inc",
    "wof:placetype":"venue"
},
  "geometry": {"coordinates":[-82.573677,28.875992],"type":"Point"}
}