{
  "type": "Feature",
  "properties": {
    "iso:country":"US",
    "sg:address":"2300 N State Road 7",
    "sg:city":"Hollywood",
    "sg:classifiers":[
        {
            "category":"Utilities",
            "subcategory":"Mobile Phone",
            "type":"Services"
        },
        {
            "category":"Communications",
            "type":"Services"
        }
    ],
    "sg:phone":"+1 954 985 1666",
    "sg:postcode":"33021",
    "sg:province":"FL",
    "sg:tags":[
        "telephone",
        "cellular"
    ],
    "wof:name":"Hollywood Toyota",
    "wof:placetype":"venue"
},
  "geometry": {"coordinates":[-80.20835099999999,26.030334],"type":"Point"}
}