{
  "type": "Feature",
  "properties": {
    "iso:country":"US",
    "sg:address":"530 W 29th St",
    "sg:city":"Hialeah",
    "sg:classifiers":[
        {
            "category":"Shopping",
            "subcategory":"Department Store",
            "type":"Retail Goods"
        }
    ],
    "sg:phone":"+1 305 885 1845",
    "sg:postcode":"33012",
    "sg:province":"FL",
    "wof:name":"Sabami Store",
    "wof:placetype":"venue"
},
  "geometry": {"coordinates":[-80.292851,25.847978],"type":"Point"}
}