{
  "type": "Feature",
  "properties": {
    "iso:country":"US",
    "sg:address":"9440 Philips Hwy Ste 3",
    "sg:city":"Jacksonville",
    "sg:classifiers":[
        {
            "category":"Travel",
            "subcategory":"Travel Agent",
            "type":"Entertainment"
        }
    ],
    "sg:phone":"+1 904 288 0441",
    "sg:postcode":"32256",
    "sg:province":"FL",
    "sg:tags":[
        "agency",
        "services-commercial"
    ],
    "sg:website":"http://www.mtstravel.com",
    "wof:name":"Menno Travel Service, Inc.",
    "wof:placetype":"venue"
},
  "geometry": {"coordinates":[-81.56943099999999,30.195872],"type":"Point"}
}