{
  "type": "Feature",
  "properties": {
    "addr:full":"176 Gray Rd Melbourne FL 32904",
    "addr:housenumber":"176",
    "addr:postcode":"32904",
    "addr:street":"Gray Rd",
    "iso:country":"US",
    "sg:address":"176 Gray Rd",
    "sg:city":"Melbourne",
    "sg:classifiers":[
        {
            "category":"Building & Trades",
            "subcategory":"Construction",
            "type":"Services"
        }
    ],
    "sg:phone":"+1 321 725 1453",
    "sg:postcode":"32904",
    "sg:province":"FL",
    "sg:tags":[
        "carpentry",
        "contractor"
    ],
    "wof:name":"Tempest Shutter Repair",
    "wof:placetype":"venue"
},
  "geometry": {"coordinates":[-80.67876699999999,28.081297],"type":"Point"}
}