{
  "type": "Feature",
  "properties": {
    "addr:full":"703 9th Ave SW Ruskin FL 33570",
    "addr:housenumber":"703",
    "addr:postcode":"33570",
    "addr:street":"9Th Ave Sw",
    "iso:country":"US",
    "sg:address":"703 9th Ave SW",
    "sg:city":"Ruskin",
    "sg:classifiers":[
        {
            "category":"Structure",
            "subcategory":"Office Building",
            "type":"Public Place"
        }
    ],
    "sg:phone":"+1 813 641 2823",
    "sg:postcode":"33570",
    "sg:province":"FL",
    "sg:tags":[
        "park"
    ],
    "wof:name":"D & M Properties",
    "wof:placetype":"venue"
},
  "geometry": {"coordinates":[-82.443899,27.710854],"type":"Point"}
}