{
  "type": "Feature",
  "properties": {
    "iso:country":"US",
    "sg:address":"1230 NW 131st St",
    "sg:city":"North Miami",
    "sg:classifiers":[
        {
            "category":"Shopping",
            "subcategory":"Computers & Home Electronics",
            "type":"Retail Goods"
        }
    ],
    "sg:phone":"+1 305 685 1152",
    "sg:postcode":"33167",
    "sg:province":"FL",
    "wof:name":"Satellite Theater Effects - CLOSED",
    "wof:placetype":"venue"
},
  "geometry": {"coordinates":[-80.21970399999999,25.8944],"type":"Point"}
}