{
  "type": "Feature",
  "properties": {
    "addr:full":"117 King St St Augustine FL 32084",
    "addr:housenumber":"117",
    "addr:postcode":"32084",
    "addr:street":"King St",
    "iso:country":"US",
    "sg:address":"117 King St",
    "sg:city":"St Augustine",
    "sg:classifiers":[
        {
            "category":"Retail",
            "subcategory":"Repair Shop",
            "type":"Services"
        }
    ],
    "sg:phone":"+1 904 824 4656",
    "sg:postcode":"32084",
    "sg:province":"FL",
    "sg:tags":[
        "equipment",
        "video"
    ],
    "wof:name":"Magoun TV",
    "wof:placetype":"venue"
},
  "geometry": {"coordinates":[-81.317774,29.891499],"type":"Point"}
}