{
  "type": "Feature",
  "properties": {
    "iso:country":"US",
    "sg:address":"608 8th Ave",
    "sg:city":"Graceville",
    "sg:classifiers":[
        {
            "category":"Organizations",
            "subcategory":"Religious Organization",
            "type":"Services"
        }
    ],
    "sg:phone":"+1 850 263 6330",
    "sg:postcode":"32440",
    "sg:province":"FL",
    "wof:name":"Third United Holiness Church",
    "wof:placetype":"venue"
},
  "geometry": {"coordinates":[-85.51117499999999,30.95733],"type":"Point"}
}