{
  "type": "Feature",
  "properties": {
    "iso:country":"US",
    "sg:address":"1207 Quailwood Dr",
    "sg:city":"Destin",
    "sg:classifiers":[
        {
            "category":"Retail",
            "subcategory":"Laundry & Dry Cleaning",
            "type":"Services"
        }
    ],
    "sg:phone":"+1 850 863 9232",
    "sg:postcode":"32541",
    "sg:province":"FL",
    "sg:tags":[
        "cleaners",
        "rug",
        "carpet"
    ],
    "wof:name":"Dale's Carpet Cleaning",
    "wof:placetype":"venue"
},
  "geometry": {"coordinates":[-86.46844900000001,30.391583],"type":"Point"}
}