{
  "type": "Feature",
  "properties": {
    "iso:country":"US",
    "sg:address":"4518 Lafayette St",
    "sg:city":"Marianna",
    "sg:classifiers":[
        {
            "category":"Wholesale",
            "subcategory":"Machinery & Supplies",
            "type":"Manufacturing & Wholesale Goods"
        }
    ],
    "sg:phone":"+1 850 526 4111",
    "sg:postcode":"32446",
    "sg:province":"FL",
    "sg:tags":[
        "company",
        "holding"
    ],
    "wof:name":"T Mowery Enterprises Inc",
    "wof:placetype":"venue"
},
  "geometry": {"coordinates":[-85.219594,30.77388],"type":"Point"}
}