{
  "type": "Feature",
  "properties": {
    "iso:country":"US",
    "sg:address":"2770 Summerfield St",
    "sg:city":"Deltona",
    "sg:classifiers":[
        {
            "category":"Manufacturing",
            "subcategory":"Printing",
            "type":"Manufacturing & Wholesale Goods"
        }
    ],
    "sg:phone":"+1 386 789 4873",
    "sg:postcode":"32738",
    "sg:province":"FL",
    "sg:tags":[
        "screen"
    ],
    "wof:name":"T K Kreations Inc",
    "wof:placetype":"venue"
},
  "geometry": {"coordinates":[-81.18925400000001,28.911389],"type":"Point"}
}