{
  "type": "Feature",
  "properties": {
    "addr:full":"7276 Hunt Club Ln Seminole FL 33776",
    "addr:housenumber":"7276",
    "addr:postcode":"33776",
    "addr:street":"Hunt Club Ln",
    "iso:country":"US",
    "sg:address":"7276 Hunt Club Ln",
    "sg:city":"Seminole",
    "sg:classifiers":[
        {
            "category":"Manufacturing",
            "subcategory":"Metals",
            "type":"Manufacturing & Wholesale Goods"
        }
    ],
    "sg:phone":"+1 727 320 0981",
    "sg:postcode":"33776",
    "sg:province":"FL",
    "sg:tags":[
        "picture",
        "frame",
        "mfg"
    ],
    "wof:name":"Dashboard Memories Inc",
    "wof:placetype":"venue"
},
  "geometry": {"coordinates":[-82.823609,27.839271],"type":"Point"}
}