{
  "type": "Feature",
  "properties": {
    "iso:country":"US",
    "sg:address":"4154 Dowling Rd",
    "sg:city":"Middleburg",
    "sg:classifiers":[
        {
            "category":"Building & Trades",
            "subcategory":"Construction",
            "type":"Services"
        }
    ],
    "sg:phone":"+1 904 406 4265",
    "sg:postcode":"32068",
    "sg:province":"FL",
    "sg:tags":[
        "house"
    ],
    "wof:name":"D L Doyle Inc",
    "wof:placetype":"venue"
},
  "geometry": {"coordinates":[-81.86006399999999,30.01809],"type":"Point"}
}