{
  "type": "Feature",
  "properties": {
    "addr:full":"4232 NE Ocean Blvd Jensen Beach FL 34957",
    "addr:housenumber":"4232",
    "addr:postcode":"34957",
    "addr:street":"Ne Ocean Blvd",
    "iso:country":"US",
    "sg:address":"4232 NE Ocean Blvd",
    "sg:city":"Jensen Beach",
    "sg:classifiers":[
        {
            "category":"Shopping",
            "subcategory":"Pharmacy",
            "type":"Retail Goods"
        }
    ],
    "sg:phone":"+1 772 225 3940",
    "sg:postcode":"34957",
    "sg:province":"FL",
    "wof:name":"Eckerd",
    "wof:placetype":"venue"
},
  "geometry": {"coordinates":[-80.201185,27.262915],"type":"Point"}
}