{
  "type": "Feature",
  "properties": {
    "addr:full":"5333 N Dixie Hwy Fort Lauderdale FL 33334",
    "addr:housenumber":"5333",
    "addr:postcode":"33334",
    "addr:street":"N Dixie Hwy",
    "iso:country":"US",
    "sg:address":"5333 N Dixie Hwy",
    "sg:city":"Fort Lauderdale",
    "sg:classifiers":[
        {
            "category":"Health Services",
            "subcategory":"Doctor",
            "type":"Services"
        }
    ],
    "sg:phone":"+1 954 565 6626",
    "sg:postcode":"33334",
    "sg:province":"FL",
    "sg:tags":[
        "osteopathic"
    ],
    "wof:name":"Howard H Schlitt D O",
    "wof:placetype":"venue"
},
  "geometry": {"coordinates":[-80.13245000000001,26.194347],"type":"Point"}
}