{
  "type": "Feature",
  "properties": {
    "iso:country":"US",
    "sg:address":"7822 N Atlantic Ave",
    "sg:city":"Cape Canaveral",
    "sg:classifiers":[
        {
            "category":"Bars & Pubs",
            "type":"Food & Drink"
        }
    ],
    "sg:phone":"+1 321 783 1024",
    "sg:postcode":"32920",
    "sg:province":"FL",
    "sg:tags":[
        "lounge",
        "karaoke",
        "cocktail"
    ],
    "wof:name":"Lamp Post Lounge",
    "wof:placetype":"venue"
},
  "geometry": {"coordinates":[-80.6054,28.388201],"type":"Point"}
}