{
  "type": "Feature",
  "properties": {
    "iso:country":"US",
    "sg:address":"45 N Congress Ave",
    "sg:city":"Delray Beach",
    "sg:classifiers":[
        {
            "category":"Home & Garden",
            "subcategory":"Home Furnishings",
            "type":"Retail Goods"
        }
    ],
    "sg:phone":"+1 561 272 8741",
    "sg:postcode":"33445",
    "sg:province":"FL",
    "sg:tags":[
        "mirror"
    ],
    "wof:name":"Royal Mirrors",
    "wof:placetype":"venue"
},
  "geometry": {"coordinates":[-80.093594,26.462251],"type":"Point"}
}