{
  "type": "Feature",
  "properties": {
    "addr:full":"1607 Middle Branch Rd Ruskin FL 33570",
    "addr:housenumber":"1607",
    "addr:postcode":"33570",
    "addr:street":"Middle Branch Rd",
    "iso:country":"US",
    "sg:address":"1607 Middle Branch Rd",
    "sg:city":"Ruskin",
    "sg:classifiers":[
        {
            "category":"Farming",
            "subcategory":"Farm",
            "type":"Manufacturing & Wholesale Goods"
        }
    ],
    "sg:phone":"+1 813 641 2359",
    "sg:postcode":"33570",
    "sg:province":"FL",
    "sg:tags":[
        "crop",
        "general"
    ],
    "wof:name":"Groovy Tubeys",
    "wof:placetype":"venue"
},
  "geometry": {"coordinates":[-82.454542,27.719146],"type":"Point"}
}