{
  "type": "Feature",
  "properties": {
    "iso:country":"US",
    "sg:address":"232 Capri Cove Pl",
    "sg:city":"Sanford",
    "sg:classifiers":[
        {
            "category":"Banks & Credit Unions",
            "subcategory":"Investment Brokerage",
            "type":"Services"
        }
    ],
    "sg:phone":"+1 407 324 4211",
    "sg:postcode":"32771",
    "sg:province":"FL",
    "sg:tags":[
        "advisory"
    ],
    "wof:name":"Donovan Casterline LLC",
    "wof:placetype":"venue"
},
  "geometry": {"coordinates":[-81.366469,28.806864],"type":"Point"}
}