{
  "type": "Feature",
  "properties": {
    "addr:full":"13867 SW 42 Ave Ocala FL 34473",
    "addr:housenumber":"13867",
    "addr:postcode":"34473",
    "addr:street":"Sw 42 Ave",
    "iso:country":"US",
    "sg:address":"13867 SW 42 Ave",
    "sg:city":"Ocala",
    "sg:classifiers":[
        {
            "category":"Shopping",
            "subcategory":"Discount & Variety Stores",
            "type":"Retail Goods"
        }
    ],
    "sg:phone":"+1 352 347 6050",
    "sg:postcode":"34473",
    "sg:province":"FL",
    "sg:tags":[
        "merchandise",
        "general"
    ],
    "wof:name":"Anthony V Seidita Retailer",
    "wof:placetype":"venue"
},
  "geometry": {"coordinates":[-82.192013,29.020189],"type":"Point"}
}