{
  "type": "Feature",
  "properties": {
    "iso:country":"US",
    "sg:address":"6974 Collins Ave",
    "sg:city":"Miami Beach",
    "sg:classifiers":[
        {
            "category":"Restaurant",
            "type":"Food & Drink"
        }
    ],
    "sg:phone":"+1 305 864 4901",
    "sg:postcode":"33141",
    "sg:province":"FL",
    "sg:tags":[
        "mexican"
    ],
    "sg:website":"www.facebook.com/pages/Miami-Bea...",
    "wof:name":"Mr Taco Mexican Food",
    "wof:placetype":"venue"
},
  "geometry": {"coordinates":[-80.120766,25.855668],"type":"Point"}
}