{
  "type": "Feature",
  "properties": {
    "iso:country":"US",
    "sg:address":"4062 State Hwy 60",
    "sg:city":"Bartow",
    "sg:classifiers":[
        {
            "category":"Wholesale",
            "subcategory":"Apparel",
            "type":"Manufacturing & Wholesale Goods"
        }
    ],
    "sg:phone":"+1 863 519 0261",
    "sg:postcode":"33830",
    "sg:province":"FL",
    "sg:tags":[
        "piece"
    ],
    "wof:name":"American Business Associates",
    "wof:placetype":"venue"
},
  "geometry": {"coordinates":[-81.93006699999999,27.894609],"type":"Point"}
}