{
  "type": "Feature",
  "properties": {
    "iso:country":"US",
    "sg:address":"1400 Hiawatha Dr",
    "sg:city":"Kissimmee",
    "sg:classifiers":[
        {
            "category":"Building & Trades",
            "subcategory":"Construction",
            "type":"Services"
        }
    ],
    "sg:phone":"+1 407 846 6205",
    "sg:postcode":"34741",
    "sg:province":"FL",
    "sg:tags":[
        "general",
        "home",
        "contractor",
        "remodeling",
        "residential"
    ],
    "wof:name":"H & I Builders",
    "wof:placetype":"venue"
},
  "geometry": {"coordinates":[-81.420835,28.278259],"type":"Point"}
}