{
  "type": "Feature",
  "properties": {
    "iso:country":"US",
    "sg:address":"505 Oliver Rd",
    "sg:city":"Venus",
    "sg:classifiers":[
        {
            "category":"Travel",
            "subcategory":"Travel Agent",
            "type":"Entertainment"
        }
    ],
    "sg:phone":"+1 863 531 0093",
    "sg:postcode":"33960",
    "sg:province":"FL",
    "sg:tags":[
        "operator",
        "tour"
    ],
    "wof:name":"Biokind Tours LLC",
    "wof:placetype":"venue"
},
  "geometry": {"coordinates":[-81.43718699999999,27.048756],"type":"Point"}
}