{
  "type": "Feature",
  "properties": {
    "iso:country":"US",
    "sg:address":"435 Hialeah Dr",
    "sg:city":"Hialeah",
    "sg:classifiers":[
        {
            "category":"Professional",
            "subcategory":"Detective & Security Services",
            "type":"Services"
        }
    ],
    "sg:phone":"+1 305 888 2311",
    "sg:postcode":"33010",
    "sg:province":"FL",
    "sg:tags":[
        "guard",
        "patrol"
    ],
    "wof:name":"Metro Guard Protection",
    "wof:placetype":"venue"
},
  "geometry": {"coordinates":[-80.271923,25.823019],"type":"Point"}
}