{
  "type": "Feature",
  "properties": {
    "addr:full":"6828 Hanging Moss Rd Orlando FL 32807",
    "addr:postcode":"6828;32807",
    "addr:street":"Hanging Moss Rd",
    "iso:country":"US",
    "sg:address":"6828 Hanging Moss Rd",
    "sg:city":"Orlando",
    "sg:classifiers":[
        {
            "category":"Wholesale",
            "subcategory":"Hardware",
            "type":"Manufacturing & Wholesale Goods"
        }
    ],
    "sg:phone":"+1 407 657 6360",
    "sg:postcode":"32807",
    "sg:province":"FL",
    "sg:tags":[
        "repair",
        "steam",
        "trap",
        "boiler"
    ],
    "sg:website":"www.thermal-techinc.com",
    "wof:name":"Thermal Tech Inc",
    "wof:placetype":"venue"
},
  "geometry": {"coordinates":[-81.299226,28.578928],"type":"Point"}
}