{
  "type": "Feature",
  "properties": {
    "addr:full":"1472 Noell Blvd Palm Harbor FL 34683",
    "addr:housenumber":"1472",
    "addr:postcode":"34683",
    "addr:street":"Noell Blvd",
    "iso:country":"US",
    "sg:address":"1472 Noell Blvd",
    "sg:city":"Palm Harbor",
    "sg:classifiers":[
        {
            "category":"Retail",
            "subcategory":"Laundry & Dry Cleaning",
            "type":"Services"
        }
    ],
    "sg:phone":"+1 727 785 9888",
    "sg:postcode":"34683",
    "sg:province":"FL",
    "wof:name":"Profe Carpet Sys of Pin County",
    "wof:placetype":"venue"
},
  "geometry": {"coordinates":[-82.760068,28.064525],"type":"Point"}
}