{
  "type": "Feature",
  "properties": {
    "iso:country":"US",
    "sg:address":"1800 S Iroquois Ave",
    "sg:city":"Homosassa",
    "sg:classifiers":[
        {
            "category":"Building & Trades",
            "subcategory":"Construction",
            "type":"Services"
        }
    ],
    "sg:phone":"+1 352 563 1254",
    "sg:postcode":"34448",
    "sg:province":"FL",
    "sg:tags":[
        "pipe",
        "laying"
    ],
    "wof:name":"E&R Mechanical Inc",
    "wof:placetype":"venue"
},
  "geometry": {"coordinates":[-82.563677,28.836004],"type":"Point"}
}