{
  "type": "Feature",
  "properties": {
    "iso:country":"US",
    "sg:address":"3535 NW 60th St",
    "sg:city":"Miami",
    "sg:classifiers":[
        {
            "category":"Restaurant",
            "type":"Food & Drink"
        }
    ],
    "sg:phone":"+1 305 635 1249",
    "sg:postcode":"33142",
    "sg:province":"FL",
    "wof:name":"Culinaire Specialty Foods",
    "wof:placetype":"venue"
},
  "geometry": {"coordinates":[-80.254501,25.828899],"type":"Point"}
}