{
  "type": "Feature",
  "properties": {
    "addr:full":"132 Kendale Dr Safety Harbor FL 34695",
    "addr:housenumber":"132",
    "addr:postcode":"34695",
    "addr:street":"Kendale Dr",
    "iso:country":"US",
    "sg:address":"132 Kendale Dr",
    "sg:city":"Safety Harbor",
    "sg:classifiers":[
        {
            "category":"Manufacturing",
            "subcategory":"Food",
            "type":"Manufacturing & Wholesale Goods"
        }
    ],
    "sg:phone":"+1 727 726 5438",
    "sg:postcode":"34695",
    "sg:province":"FL",
    "sg:tags":[
        "preparation",
        "mfg"
    ],
    "wof:name":"Fly Buy Night",
    "wof:placetype":"venue"
},
  "geometry": {"coordinates":[-82.69692499999999,28.029525],"type":"Point"}
}