{
  "type": "Feature",
  "properties": {
    "iso:country":"US",
    "sg:address":"175 SW 20th Way Ste N9",
    "sg:city":"Dania",
    "sg:classifiers":[
        {
            "category":"Marine",
            "type":"Transportation"
        }
    ],
    "sg:phone":"+1 954 923 0215",
    "sg:postcode":"33004",
    "sg:province":"FL",
    "sg:tags":[
        "hardware-marine"
    ],
    "wof:name":"Signature Marine Manufacturing, Inc",
    "wof:placetype":"venue"
},
  "geometry": {"coordinates":[-80.167136,26.04982],"type":"Point"}
}