{
  "type": "Feature",
  "properties": {
    "addr:full":"620 NW 35th St Boca Raton FL 33431",
    "addr:housenumber":"620",
    "addr:postcode":"33431",
    "addr:street":"Nw 35Th St",
    "iso:country":"US",
    "sg:address":"620 NW 35th St",
    "sg:city":"Boca Raton",
    "sg:classifiers":[
        {
            "category":"Airport",
            "type":"Transportation"
        }
    ],
    "sg:phone":"+1 561 998 4744",
    "sg:postcode":"33431",
    "sg:province":"FL",
    "sg:tags":[
        "aircraft",
        "maintenance"
    ],
    "wof:name":"Magellan Aircraft Svc",
    "wof:placetype":"venue"
},
  "geometry": {"coordinates":[-80.09664600000001,26.382175],"type":"Point"}
}