{
  "type": "Feature",
  "properties": {
    "iso:country":"US",
    "sg:address":"4748 SW 143rd Ave",
    "sg:city":"Miami",
    "sg:classifiers":[
        {
            "category":"Shopping",
            "subcategory":"Clothing, Apparel, & Fashions",
            "type":"Retail Goods"
        }
    ],
    "sg:phone":"+1 305 220 8440",
    "sg:postcode":"33175",
    "sg:province":"FL",
    "sg:tags":[
        "tuxedo",
        "furnishing"
    ],
    "wof:name":"All Formal Wear Inc",
    "wof:placetype":"venue"
},
  "geometry": {"coordinates":[-80.424267,25.722027],"type":"Point"}
}