{
  "type": "Feature",
  "properties": {
    "iso:country":"US",
    "sg:address":"2058 NW 14th Ave",
    "sg:city":"Gainesville",
    "sg:classifiers":[
        {
            "category":"Professional",
            "subcategory":"Business Services",
            "type":"Services"
        }
    ],
    "sg:phone":"+1 352 375 0900",
    "sg:postcode":"32605",
    "sg:province":"FL",
    "sg:tags":[
        "literary",
        "agent"
    ],
    "wof:name":"Medical & Literary Pro Conslnt",
    "wof:placetype":"venue"
},
  "geometry": {"coordinates":[-82.351871,29.664099],"type":"Point"}
}