{
  "type": "Feature",
  "properties": {
    "addr:full":"388 Blairmore Blvd E Orange Park FL 32073",
    "addr:housenumber":"388",
    "addr:postcode":"32073",
    "addr:street":"Blairmore Blvd E",
    "iso:country":"US",
    "sg:address":"388 Blairmore Blvd E",
    "sg:city":"Orange Park",
    "sg:classifiers":[
        {
            "category":"Building & Trades",
            "subcategory":"Construction",
            "type":"Services"
        }
    ],
    "sg:phone":"+1 904 264 7292",
    "sg:postcode":"32073",
    "sg:province":"FL",
    "sg:tags":[
        "house"
    ],
    "wof:name":"Vincent Granger Home Repair",
    "wof:placetype":"venue"
},
  "geometry": {"coordinates":[-81.73863299999999,30.172899],"type":"Point"}
}