{
  "type": "Feature",
  "properties": {
    "addr:full":"2964 Aviation Ave Miami FL 33133",
    "addr:housenumber":"2964",
    "addr:postcode":"33133",
    "addr:street":"Aviation Ave",
    "iso:country":"US",
    "sg:address":"2964 Aviation Ave",
    "sg:city":"Miami",
    "sg:classifiers":[
        {
            "category":"Organizations",
            "subcategory":"Community Association",
            "type":"Services"
        }
    ],
    "sg:phone":"+1 305 447 4566",
    "sg:postcode":"33133",
    "sg:province":"FL",
    "wof:name":"Biscayne Bay Foundation",
    "wof:placetype":"venue"
},
  "geometry": {"coordinates":[-80.237272,25.736335],"type":"Point"}
}