{
  "type": "Feature",
  "properties": {
    "addr:full":"1280 N Palm Ave Sarasota FL 34236",
    "addr:housenumber":"1280",
    "addr:postcode":"34236",
    "addr:street":"N Palm Ave",
    "iso:country":"US",
    "sg:address":"1280 N Palm Ave",
    "sg:city":"Sarasota",
    "sg:classifiers":[
        {
            "category":"Banks & Credit Unions",
            "subcategory":"Investment Brokerage",
            "type":"Services"
        }
    ],
    "sg:phone":"+1 941 952 1032",
    "sg:postcode":"34236",
    "sg:province":"FL",
    "sg:tags":[
        "advisory"
    ],
    "wof:name":"Sage Capital",
    "wof:placetype":"venue"
},
  "geometry": {"coordinates":[-82.54454699999999,27.336065],"type":"Point"}
}