{
  "type": "Feature",
  "properties": {
    "iso:country":"US",
    "sg:address":"680 Spencer Ave",
    "sg:city":"Pensacola",
    "sg:classifiers":[
        {
            "category":"Building & Trades",
            "subcategory":"Construction",
            "type":"Services"
        }
    ],
    "sg:phone":"+1 850 261 0534",
    "sg:postcode":"32514",
    "sg:province":"FL",
    "sg:tags":[
        "waterproofing",
        "contractor"
    ],
    "wof:name":"Fence Doctors",
    "wof:placetype":"venue"
},
  "geometry": {"coordinates":[-87.247789,30.522015],"type":"Point"}
}