{
  "type": "Feature",
  "properties": {
    "addr:full":"17 N H St Lake Worth FL 33460",
    "addr:housenumber":"17",
    "addr:postcode":"33460",
    "addr:street":"N H St",
    "iso:country":"US",
    "sg:address":"17 N H St",
    "sg:city":"Lake Worth",
    "sg:classifiers":[
        {
            "category":"Real Estate",
            "subcategory":"Real Estate Operator",
            "type":"Services"
        }
    ],
    "sg:phone":"+1 561 622 0137",
    "sg:postcode":"33460",
    "sg:province":"FL",
    "sg:tags":[
        "building",
        "apartment"
    ],
    "wof:name":"Williams Apts",
    "wof:placetype":"venue"
},
  "geometry": {"coordinates":[-80.058414,26.616539],"type":"Point"}
}