{
  "type": "Feature",
  "properties": {
    "addr:full":"8030 Fruitville Rd Sarasota FL 34240",
    "addr:housenumber":"8030",
    "addr:postcode":"34240",
    "addr:street":"Fruitville Rd",
    "iso:country":"US",
    "sg:address":"8030 Fruitville Rd",
    "sg:city":"Sarasota",
    "sg:classifiers":[
        {
            "category":"Manufacturing",
            "subcategory":"Lumber",
            "type":"Manufacturing & Wholesale Goods"
        }
    ],
    "sg:phone":"+1 941 342 7665",
    "sg:postcode":"34240",
    "sg:province":"FL",
    "sg:tags":[
        "forester"
    ],
    "wof:name":"Forestry Resources Inc",
    "wof:placetype":"venue"
},
  "geometry": {"coordinates":[-82.40486799999999,27.338338],"type":"Point"}
}