{
  "type": "Feature",
  "properties": {
    "addr:full":"108 Ave B Carrabelle FL 32320",
    "addr:housenumber":"108",
    "addr:postcode":"32320",
    "addr:street":"Ave B",
    "iso:country":"US",
    "sg:address":"108 Ave B",
    "sg:city":"Carrabelle",
    "sg:classifiers":[
        {
            "category":"Professional",
            "subcategory":"Accounting & Tax Preparation",
            "type":"Services"
        }
    ],
    "sg:phone":"+1 850 697 2542",
    "sg:postcode":"32320",
    "sg:province":"FL",
    "sg:tags":[
        "accountant"
    ],
    "wof:name":"Paul Marxsen CPA",
    "wof:placetype":"venue"
},
  "geometry": {"coordinates":[-84.987167,29.720302],"type":"Point"}
}