{
  "type": "Feature",
  "properties": {
    "iso:country":"US",
    "sg:address":"750 Ave O SW",
    "sg:city":"Winter Haven",
    "sg:classifiers":[
        {
            "category":"Building & Trades",
            "subcategory":"Cleaning & Sanitation",
            "type":"Services"
        }
    ],
    "sg:phone":"+1 863 292 2060",
    "sg:postcode":"33880",
    "sg:province":"FL",
    "sg:tags":[
        "janitor"
    ],
    "wof:name":"Harris Cleaning",
    "wof:placetype":"venue"
},
  "geometry": {"coordinates":[-81.73570599999999,28.007519],"type":"Point"}
}