{
  "type": "Feature",
  "properties": {
    "addr:full":"1317 Oak St Melbourne FL 32901",
    "addr:housenumber":"1317",
    "addr:postcode":"32901",
    "addr:street":"Oak St",
    "iso:country":"US",
    "sg:address":"1317 Oak St",
    "sg:city":"Melbourne",
    "sg:classifiers":[
        {
            "category":"Health Services",
            "subcategory":"Doctor",
            "type":"Services"
        }
    ],
    "sg:phone":"+1 321 951 1600",
    "sg:postcode":"32901",
    "sg:province":"FL",
    "sg:tags":[
        "medical"
    ],
    "wof:name":"Peake Thomas PHD Abpp",
    "wof:placetype":"venue"
},
  "geometry": {"coordinates":[-80.615178,28.087409],"type":"Point"}
}