{
  "type": "Feature",
  "properties": {
    "addr:full":"10376 Lake Vista Cir Boca Raton FL 33498",
    "addr:housenumber":"10376",
    "addr:postcode":"33498",
    "addr:street":"Lake Vista Cir",
    "iso:country":"US",
    "sg:address":"10376 Lake Vista Cir",
    "sg:city":"Boca Raton",
    "sg:classifiers":[
        {
            "category":"Education",
            "subcategory":"Special Training",
            "type":"Public Place"
        }
    ],
    "sg:phone":"+1 561 218 1923",
    "sg:postcode":"33498",
    "sg:province":"FL",
    "sg:tags":[
        "center"
    ],
    "wof:name":"Francine Resnick Phd Learning",
    "wof:placetype":"venue"
},
  "geometry": {"coordinates":[-80.210866,26.370434],"type":"Point"}
}