{
  "type": "Feature",
  "properties": {
    "addr:full":"411 W Indiantown Rd Jupiter FL 33458",
    "addr:housenumber":"411",
    "addr:postcode":"33458",
    "addr:street":"W Indiantown Rd",
    "iso:country":"US",
    "sg:address":"411 W Indiantown Rd",
    "sg:city":"Jupiter",
    "sg:classifiers":[
        {
            "category":"Health Services",
            "subcategory":"Doctor",
            "type":"Services"
        },
        {
            "category":"Health Services",
            "subcategory":"Clinic",
            "type":"Services"
        }
    ],
    "sg:phone":"+1 561 746 7826",
    "sg:postcode":"33458",
    "sg:province":"FL",
    "sg:tags":[
        "physician",
        "surgeon",
        "osteopathic"
    ],
    "wof:name":"Surowitz Ron DO",
    "wof:placetype":"venue"
},
  "geometry": {"coordinates":[-80.099915,26.934138],"type":"Point"}
}