{
  "type": "Feature",
  "properties": {
    "addr:full":"3323 E 15th St Panama City FL 32405",
    "addr:housenumber":"3323",
    "addr:postcode":"32405",
    "addr:street":"E 15Th St",
    "iso:country":"US",
    "sg:address":"3323 E 15th St",
    "sg:city":"Panama City",
    "sg:classifiers":[
        {
            "category":"Organizations",
            "subcategory":"Religious Organization",
            "type":"Services"
        }
    ],
    "sg:phone":"+1 850 763 4682",
    "sg:postcode":"32405",
    "sg:province":"FL",
    "wof:name":"Parkway Baptist Church",
    "wof:placetype":"venue"
},
  "geometry": {"coordinates":[-85.61525399999999,30.175046],"type":"Point"}
}