{
  "type": "Feature",
  "properties": {
    "addr:full":"218 State Hwy 60 Lake Wales FL 33853",
    "addr:housenumber":"218",
    "addr:postcode":"33853",
    "addr:street":"State Hwy 60",
    "iso:country":"US",
    "sg:address":"218 State Hwy 60",
    "sg:city":"Lake Wales",
    "sg:classifiers":[
        {
            "category":"Restaurant",
            "type":"Food & Drink"
        }
    ],
    "sg:phone":"+1 863 676 1688",
    "sg:postcode":"33853",
    "sg:province":"FL",
    "sg:tags":[
        "eating"
    ],
    "wof:name":"Crown Palace",
    "wof:placetype":"venue"
},
  "geometry": {"coordinates":[-81.585812,27.89401],"type":"Point"}
}