{
  "type": "Feature",
  "properties": {
    "iso:country":"US",
    "sg:address":"2000 Estero Blvd",
    "sg:city":"Fort Myers Beach",
    "sg:classifiers":[
        {
            "category":"Travel",
            "subcategory":"Hotels & Motels",
            "type":"Entertainment"
        }
    ],
    "sg:phone":"+1 239 765 7654",
    "sg:postcode":"33931",
    "sg:province":"FL",
    "sg:tags":[
        "resort"
    ],
    "wof:name":"Diamondhead Island Bch Resort",
    "wof:placetype":"venue"
},
  "geometry": {"coordinates":[-81.947526,26.450357],"type":"Point"}
}