{
  "type": "Feature",
  "properties": {
    "addr:full":"4030 NW 26th St Miami FL 33142",
    "addr:housenumber":"4030",
    "addr:postcode":"33142",
    "addr:street":"Nw 26Th St",
    "iso:country":"US",
    "sg:address":"4030 NW 26th St",
    "sg:city":"Miami",
    "sg:classifiers":[
        {
            "category":"Autos & Motor Vehicles",
            "subcategory":"Automobile Sales",
            "type":"Retail Goods"
        }
    ],
    "sg:phone":"+1 305 642 4333",
    "sg:postcode":"33142",
    "sg:province":"FL",
    "sg:tags":[
        "limo"
    ],
    "wof:name":"AAA World Wide Limousine",
    "wof:placetype":"venue"
},
  "geometry": {"coordinates":[-80.26248099999999,25.79941],"type":"Point"}
}