{
  "type": "Feature",
  "properties": {
    "addr:full":"12006 Winding Woods Way Bradenton FL 34202",
    "addr:housenumber":"12006",
    "addr:postcode":"34202",
    "addr:street":"Winding Woods Way",
    "iso:country":"US",
    "sg:address":"12006 Winding Woods Way",
    "sg:city":"Bradenton",
    "sg:classifiers":[
        {
            "category":"Building & Trades",
            "subcategory":"Construction",
            "type":"Services"
        }
    ],
    "sg:phone":"+1 941 755 3018",
    "sg:postcode":"34202",
    "sg:province":"FL",
    "sg:tags":[
        "contractor"
    ],
    "wof:name":"Rodolfo Tile Works Inc",
    "wof:placetype":"venue"
},
  "geometry": {"coordinates":[-82.418537,27.43065],"type":"Point"}
}