{
  "type": "Feature",
  "properties": {
    "addr:full":"2830 Winkler Ave Fort Myers FL 33901",
    "addr:housenumber":"2830",
    "addr:postcode":"33901",
    "addr:street":"Winkler Ave",
    "iso:country":"US",
    "sg:address":"2830 Winkler Ave",
    "sg:city":"Fort Myers",
    "sg:classifiers":[
        {
            "category":"Insurance",
            "subcategory":"Hazard Insurance",
            "type":"Services"
        }
    ],
    "sg:phone":"+1 239 275 4667",
    "sg:postcode":"33901",
    "sg:province":"FL",
    "sg:tags":[
        "carrier"
    ],
    "wof:name":"Teachers Insurance Company",
    "wof:placetype":"venue"
},
  "geometry": {"coordinates":[-81.853301,26.604397],"type":"Point"}
}