{
  "type": "Feature",
  "properties": {
    "iso:country":"US",
    "sg:address":"12217 State St",
    "sg:city":"Tampa",
    "sg:classifiers":[
        {
            "category":"Freight",
            "type":"Transportation"
        }
    ],
    "sg:phone":"+1 813 854 3623",
    "sg:postcode":"33635",
    "sg:province":"FL",
    "sg:tags":[
        "operator",
        "local",
        "trucking"
    ],
    "wof:name":"Renecitos Trucking Inc",
    "wof:placetype":"venue"
},
  "geometry": {"coordinates":[-82.635154,28.024096],"type":"Point"}
}