{
  "type": "Feature",
  "properties": {
    "addr:full":"8125 Forest Villas Cir Spring Hill FL 34606",
    "addr:housenumber":"8125",
    "addr:postcode":"34606",
    "addr:street":"Forest Villas Cir",
    "iso:country":"US",
    "sg:address":"8125 Forest Villas Cir",
    "sg:city":"Spring Hill",
    "sg:classifiers":[
        {
            "category":"Real Estate",
            "subcategory":"Real Estate Operator",
            "type":"Services"
        }
    ],
    "sg:phone":"+1 352 686 9257",
    "sg:postcode":"34606",
    "sg:province":"FL",
    "wof:name":"Forest Oaks Villas Apts",
    "wof:placetype":"venue"
},
  "geometry": {"coordinates":[-82.588728,28.48873],"type":"Point"}
}