{
  "type": "Feature",
  "properties": {
    "iso:country":"US",
    "sg:address":"3893 Slow Tide Rd",
    "sg:city":"Green Cove Spgs",
    "sg:classifiers":[
        {
            "category":"Retail",
            "subcategory":"Repair Shop",
            "type":"Services"
        }
    ],
    "sg:phone":"+1 904 284 7932",
    "sg:postcode":"32043",
    "sg:province":"FL",
    "sg:tags":[
        "welding"
    ],
    "wof:name":"St Johns Fabricators Inc",
    "wof:placetype":"venue"
},
  "geometry": {"coordinates":[-81.66350300000001,29.986046],"type":"Point"}
}