{
  "type": "Feature",
  "properties": {
    "addr:full":"1211 N Main St Gainesville FL 32601",
    "addr:housenumber":"1211",
    "addr:postcode":"32601",
    "addr:street":"N Main St",
    "iso:country":"US",
    "sg:address":"1211 N Main St",
    "sg:city":"Gainesville",
    "sg:classifiers":[
        {
            "category":"Retail",
            "subcategory":"Auto Repair",
            "type":"Services"
        }
    ],
    "sg:phone":"+1 352 372 3537",
    "sg:postcode":"32601",
    "sg:province":"FL",
    "sg:tags":[
        "automotive",
        "supply"
    ],
    "wof:name":"Goodyear",
    "wof:placetype":"venue"
},
  "geometry": {"coordinates":[-82.324428,29.664674],"type":"Point"}
}