{
  "type": "Feature",
  "properties": {
    "iso:country":"US",
    "sg:address":"5858 SW 97th Ter",
    "sg:city":"Fort Lauderdale",
    "sg:classifiers":[
        {
            "category":"Personal",
            "subcategory":"Beauty Salon",
            "type":"Services"
        }
    ],
    "sg:phone":"+1 954 252 8184",
    "sg:postcode":"33328",
    "sg:province":"FL",
    "sg:tags":[
        "shop"
    ],
    "wof:name":"Hideaway Nail Salon Inc",
    "wof:placetype":"venue"
},
  "geometry": {"coordinates":[-80.276113,26.046547],"type":"Point"}
}