{
  "type": "Feature",
  "properties": {
    "iso:country":"US",
    "sg:address":"12944 Royal George Ave",
    "sg:city":"Odessa",
    "sg:classifiers":[
        {
            "category":"Recreation",
            "type":"Entertainment"
        }
    ],
    "sg:phone":"+1 813 926 0094",
    "sg:postcode":"33556",
    "sg:province":"FL",
    "sg:tags":[
        "training",
        "fitness"
    ],
    "wof:name":"Dan Dal Colletto & Trainers",
    "wof:placetype":"venue"
},
  "geometry": {"coordinates":[-82.647295,28.09643],"type":"Point"}
}