{
  "type": "Feature",
  "properties": {
    "iso:country":"US",
    "sg:address":"6810 Front St",
    "sg:city":"Key West",
    "sg:classifiers":[
        {
            "category":"Bars & Pubs",
            "type":"Food & Drink"
        }
    ],
    "sg:menulink":"http://www.allmenus.com/fl/key-west/51123-hogfish-bar--grill/menu/",
    "sg:phone":"+1 305 293 4041",
    "sg:postcode":"33040",
    "sg:province":"FL",
    "sg:tags":[
        "seafood",
        "american"
    ],
    "wof:name":"Hogfish Bar & Grill",
    "wof:placetype":"venue"
},
  "geometry": {"coordinates":[-81.734459,24.56632],"type":"Point"}
}