{
  "type": "Feature",
  "properties": {
    "iso:country":"US",
    "sg:address":"10732 Southern Blvd",
    "sg:city":"Royal Palm Beach",
    "sg:classifiers":[
        {
            "category":"Building & Trades",
            "subcategory":"Landscaping Services",
            "type":"Services"
        }
    ],
    "sg:phone":"+1 561 793 8705",
    "sg:postcode":"33411",
    "sg:province":"FL",
    "sg:tags":[
        "landscape",
        "contractor"
    ],
    "wof:name":"Grasshopper Lawn Maintenance",
    "wof:placetype":"venue"
},
  "geometry": {"coordinates":[-80.218356,26.680769],"type":"Point"}
}