{
  "type": "Feature",
  "properties": {
    "iso:country":"US",
    "sg:address":"1361 Reserve Dr",
    "sg:city":"Venice",
    "sg:classifiers":[
        {
            "category":"Education",
            "subcategory":"Special Training",
            "type":"Public Place"
        }
    ],
    "sg:phone":"+1 941 493 1897",
    "sg:postcode":"34285",
    "sg:province":"FL",
    "wof:name":"Teaching For The 21st Century",
    "wof:placetype":"venue"
},
  "geometry": {"coordinates":[-82.403481,27.080234],"type":"Point"}
}