{
  "type": "Feature",
  "properties": {
    "addr:full":"1915 Eucalyptus Ave Fort Pierce FL 34949",
    "addr:housenumber":"1915",
    "addr:postcode":"34949",
    "addr:street":"Eucalyptus Ave",
    "iso:country":"US",
    "sg:address":"1915 Eucalyptus Ave",
    "sg:city":"Fort Pierce",
    "sg:classifiers":[
        {
            "category":"Building & Trades",
            "subcategory":"Landscaping Services",
            "type":"Services"
        }
    ],
    "sg:phone":"+1 772 466 1967",
    "sg:postcode":"34949",
    "sg:province":"FL",
    "wof:name":"Tim Rovero Lawn Service",
    "wof:placetype":"venue"
},
  "geometry": {"coordinates":[-80.285876,27.450416],"type":"Point"}
}