{
  "type": "Feature",
  "properties": {
    "addr:full":"98 NE 9th St Ocala FL 34470",
    "addr:housenumber":"98",
    "addr:postcode":"34470",
    "addr:street":"Ne 9Th St",
    "iso:country":"US",
    "sg:address":"98 NE 9th St",
    "sg:city":"Ocala",
    "sg:classifiers":[
        {
            "category":"Restaurant",
            "type":"Food & Drink"
        }
    ],
    "sg:phone":"+1 352 622 1335",
    "sg:postcode":"34470",
    "sg:province":"FL",
    "sg:tags":[
        "sandwich"
    ],
    "wof:name":"Sub & Sandwiches Co",
    "wof:placetype":"venue"
},
  "geometry": {"coordinates":[-82.13563600000001,29.195605],"type":"Point"}
}