{
  "type": "Feature",
  "properties": {
    "addr:full":"1160 SW 4th St Miami FL 33130",
    "addr:housenumber":"1160",
    "addr:postcode":"33130",
    "addr:street":"Sw 4Th St",
    "iso:country":"US",
    "sg:address":"1160 SW 4th St",
    "sg:city":"Miami",
    "sg:classifiers":[
        {
            "category":"Food & Beverages",
            "subcategory":"Groceries & Convenience Stores",
            "type":"Retail Goods"
        }
    ],
    "sg:phone":"+1 305 545 6590",
    "sg:postcode":"33130",
    "sg:province":"FL",
    "sg:tags":[
        "grocer"
    ],
    "wof:name":"Matanzas Grocers",
    "wof:placetype":"venue"
},
  "geometry": {"coordinates":[-80.214203,25.769699],"type":"Point"}
}