{
  "type": "Feature",
  "properties": {
    "iso:country":"US",
    "sg:address":"4001 38th St S",
    "sg:city":"Saint Petersburg",
    "sg:classifiers":[
        {
            "category":"Banks & Credit Unions",
            "subcategory":"Financial Services",
            "type":"Services"
        }
    ],
    "sg:phone":"+1 727 865 2735",
    "sg:postcode":"33711",
    "sg:province":"FL",
    "sg:tags":[
        "investment",
        "real estate"
    ],
    "wof:name":"Wb Investments",
    "wof:placetype":"venue"
},
  "geometry": {"coordinates":[-82.68456,27.731936],"type":"Point"}
}