{
  "type": "Feature",
  "properties": {
    "addr:full":"5069 Old Bainbridge Rd Tallahassee FL 32303",
    "addr:housenumber":"5069",
    "addr:postcode":"32303",
    "addr:street":"Old Bainbridge Rd",
    "iso:country":"US",
    "sg:address":"5069 Old Bainbridge Rd",
    "sg:city":"Tallahassee",
    "sg:classifiers":[
        {
            "category":"Organizations",
            "subcategory":"Community Association",
            "type":"Services"
        }
    ],
    "sg:phone":"+1 850 878 6893",
    "sg:postcode":"32303",
    "sg:province":"FL",
    "wof:name":"Lions Roar Music",
    "wof:placetype":"venue"
},
  "geometry": {"coordinates":[-84.362854,30.524901],"type":"Point"}
}