{
  "type": "Feature",
  "properties": {
    "addr:full":"6767 River Rd New Port Richey FL 34652",
    "addr:housenumber":"6767",
    "addr:postcode":"34652",
    "addr:street":"River Rd",
    "iso:country":"US",
    "sg:address":"6767 River Rd",
    "sg:city":"New Port Richey",
    "sg:classifiers":[
        {
            "category":"Organizations",
            "subcategory":"Religious Organization",
            "type":"Services"
        }
    ],
    "sg:phone":"+1 727 849 5951",
    "sg:postcode":"34652",
    "sg:province":"FL",
    "wof:name":"River Road Church of Christ",
    "wof:placetype":"venue"
},
  "geometry": {"coordinates":[-82.724979,28.254475],"type":"Point"}
}