{
  "type": "Feature",
  "properties": {
    "iso:country":"US",
    "sg:address":"2019 Centre Pointe Blvd",
    "sg:city":"Tallahassee",
    "sg:classifiers":[
        {
            "category":"Real Estate",
            "subcategory":"Real Estate Operator",
            "type":"Services"
        }
    ],
    "sg:phone":"+1 850 386 2117",
    "sg:postcode":"32308",
    "sg:province":"FL",
    "sg:tags":[
        "building",
        "apartment",
        "broker"
    ],
    "wof:name":"Alexander Apartments",
    "wof:placetype":"venue"
},
  "geometry": {"coordinates":[-84.238168,30.473403],"type":"Point"}
}