{
  "type": "Feature",
  "properties": {
    "iso:country":"US",
    "sg:address":"1042 NE 34th Ct",
    "sg:city":"Fort Lauderdale",
    "sg:classifiers":[
        {
            "category":"Building & Trades",
            "subcategory":"Construction",
            "type":"Services"
        }
    ],
    "sg:phone":"+1 954 561 4234",
    "sg:postcode":"33334",
    "sg:province":"FL",
    "sg:tags":[
        "house",
        "carpentry",
        "contractor"
    ],
    "wof:name":"Gjl Carpentry",
    "wof:placetype":"venue"
},
  "geometry": {"coordinates":[-80.133167,26.170358],"type":"Point"}
}