{
  "type": "Feature",
  "properties": {
    "addr:full":"10434 Indian Walk Rd Jacksonville FL 32257",
    "addr:housenumber":"10434",
    "addr:postcode":"32257",
    "addr:street":"Indian Walk Rd",
    "iso:country":"US",
    "sg:address":"10434 Indian Walk Rd",
    "sg:city":"Jacksonville",
    "sg:classifiers":[
        {
            "category":"Communications",
            "subcategory":"Film & Video Production",
            "type":"Services"
        }
    ],
    "sg:phone":"+1 904 288 9170",
    "sg:postcode":"32257",
    "sg:province":"FL",
    "sg:tags":[
        "motion"
    ],
    "wof:name":"Lighthouse Video Productions",
    "wof:placetype":"venue"
},
  "geometry": {"coordinates":[-81.617851,30.188448],"type":"Point"}
}