{
  "type": "Feature",
  "properties": {
    "addr:full":"516 Douglas Ave Altamonte Springs FL 32714",
    "addr:housenumber":"516",
    "addr:postcode":"32714",
    "addr:street":"Douglas Ave",
    "iso:country":"US",
    "sg:address":"516 Douglas Ave",
    "sg:city":"Altamonte Springs",
    "sg:classifiers":[
        {
            "category":"Wholesale",
            "subcategory":"Chemicals & Plastics",
            "type":"Manufacturing & Wholesale Goods"
        }
    ],
    "sg:phone":"+1 407 772 0002",
    "sg:postcode":"32714",
    "sg:province":"FL",
    "wof:name":"Gallard Schlesinger Inc",
    "wof:placetype":"venue"
},
  "geometry": {"coordinates":[-81.390427,28.671299],"type":"Point"}
}