{
  "type": "Feature",
  "properties": {
    "iso:country":"US",
    "sg:address":"7400 Bird Rd",
    "sg:city":"Miami",
    "sg:classifiers":[
        {
            "category":"Autos & Motor Vehicles",
            "subcategory":"Automobile Sales",
            "type":"Retail Goods"
        }
    ],
    "sg:phone":"+1 305 266 4393",
    "sg:postcode":"33155",
    "sg:province":"FL",
    "sg:tags":[
        "new",
        "car"
    ],
    "wof:name":"Daewoo Of Miami",
    "wof:placetype":"venue"
},
  "geometry": {"coordinates":[-80.315056,25.732992],"type":"Point"}
}