{
  "type": "Feature",
  "properties": {
    "addr:full":"16110 Kingsmoor Way Hialeah FL 33014",
    "addr:postcode":"16110;33014",
    "addr:street":"Kingsmoor Way",
    "iso:country":"US",
    "sg:address":"16110 Kingsmoor Way",
    "sg:city":"Hialeah",
    "sg:classifiers":[
        {
            "category":"Retail",
            "subcategory":"Animal Services",
            "type":"Services"
        }
    ],
    "sg:phone":"+1 305 821 4680",
    "sg:postcode":"33014",
    "sg:province":"FL",
    "sg:tags":[
        "pet",
        "breeder"
    ],
    "wof:name":"Steubenville Kennel",
    "wof:placetype":"venue"
},
  "geometry": {"coordinates":[-80.311007,25.91839],"type":"Point"}
}