{
  "type": "Feature",
  "properties": {
    "iso:country":"US",
    "sg:address":"2145 NE 2nd St",
    "sg:city":"Ocala",
    "sg:classifiers":[
        {
            "category":"Professional",
            "subcategory":"Lawyer & Legal Services",
            "type":"Services"
        }
    ],
    "sg:phone":"+1 352 414 5037",
    "sg:postcode":"34470",
    "sg:province":"FL",
    "sg:tags":[
        "attorney",
        "law",
        "family",
        "wills",
        "practice",
        "planning",
        "real estate",
        "trust"
    ],
    "sg:website":"http://www.jculverlaw.com",
    "wof:name":"Culver Jonathan P Law Firm",
    "wof:placetype":"venue"
},
  "geometry": {"coordinates":[-82.108349,29.188308],"type":"Point"}
}