{
  "type": "Feature",
  "properties": {
    "addr:full":"7136 Bonita Dr Apt 1 Miami Beach FL 33141",
    "addr:housenumber":"7136;1",
    "addr:postcode":"33141",
    "addr:street":"Bonita Dr Apt",
    "iso:country":"US",
    "sg:address":"7136 Bonita Dr Apt 1",
    "sg:city":"Miami Beach",
    "sg:classifiers":[
        {
            "category":"Recreation",
            "subcategory":"Boat Charter",
            "type":"Entertainment"
        }
    ],
    "sg:phone":"+1 305 538 4040",
    "sg:postcode":"33141",
    "sg:province":"FL",
    "sg:tags":[
        "boating"
    ],
    "wof:name":"Tikki Beach Charter Corp",
    "wof:placetype":"venue"
},
  "geometry": {"coordinates":[-80.126373,25.856206],"type":"Point"}
}