{
  "type": "Feature",
  "properties": {
    "addr:full":"2937 Bee Ridge Rd Sarasota FL 34239",
    "addr:housenumber":"2937",
    "addr:postcode":"34239",
    "addr:street":"Bee Ridge Rd",
    "iso:country":"US",
    "sg:address":"2937 Bee Ridge Rd",
    "sg:city":"Sarasota",
    "sg:classifiers":[
        {
            "category":"Professional",
            "subcategory":"Accounting & Tax Preparation",
            "type":"Services"
        }
    ],
    "sg:phone":"+1 941 921 9119",
    "sg:postcode":"34239",
    "sg:province":"FL",
    "sg:tags":[
        "accountant"
    ],
    "wof:name":"Dave Roberts CPA",
    "wof:placetype":"venue"
},
  "geometry": {"coordinates":[-82.51085999999999,27.298897],"type":"Point"}
}