{
  "type": "Feature",
  "properties": {
    "addr:full":"7130 SW 44th St Miami FL 33155",
    "addr:housenumber":"7130",
    "addr:postcode":"33155",
    "addr:street":"Sw 44Th St",
    "iso:country":"US",
    "sg:address":"7130 SW 44th St",
    "sg:city":"Miami",
    "sg:classifiers":[
        {
            "category":"Autos & Motor Vehicles",
            "subcategory":"Automobile Sales",
            "type":"Retail Goods"
        }
    ],
    "sg:phone":"+1 305 667 8660",
    "sg:postcode":"33155",
    "sg:province":"FL",
    "sg:tags":[
        "car",
        "dealer"
    ],
    "wof:name":"Summer Enterprises-Miami Inc",
    "wof:placetype":"venue"
},
  "geometry": {"coordinates":[-80.309676,25.729379],"type":"Point"}
}