{
  "type": "Feature",
  "properties": {
    "iso:country":"US",
    "sg:address":"1590 Weeping Willow Way",
    "sg:city":"Hollywood",
    "sg:classifiers":[
        {
            "category":"Home & Garden",
            "subcategory":"Building Materials",
            "type":"Retail Goods"
        }
    ],
    "sg:phone":"+1 954 925 5322",
    "sg:postcode":"33019",
    "sg:province":"FL",
    "sg:tags":[
        "equipment",
        "energy",
        "systems-dealers",
        "solar"
    ],
    "wof:name":"Allyson Tomchin",
    "wof:placetype":"venue"
},
  "geometry": {"coordinates":[-80.124922,26.026407],"type":"Point"}
}