{
  "type": "Feature",
  "properties": {
    "addr:full":"4170 Waterlilly Ct Middleburg FL 32068",
    "addr:postcode":"4170;32068",
    "addr:street":"Waterlilly Ct",
    "iso:country":"US",
    "sg:address":"4170 Waterlilly Ct",
    "sg:city":"Middleburg",
    "sg:classifiers":[
        {
            "category":"Professional",
            "subcategory":"Business Services",
            "type":"Services"
        }
    ],
    "sg:phone":"+1 904 509 7379",
    "sg:postcode":"32068",
    "sg:province":"FL",
    "wof:name":"K & J Quality Punch Out",
    "wof:placetype":"venue"
},
  "geometry": {"coordinates":[-81.877955,30.043279],"type":"Point"}
}