{
  "type": "Feature",
  "properties": {
    "addr:full":"12333 SW 112th St Miami FL 33186",
    "addr:housenumber":"12333",
    "addr:postcode":"33186",
    "addr:street":"Sw 112Th St",
    "iso:country":"US",
    "sg:address":"12333 SW 112th St",
    "sg:city":"Miami",
    "sg:classifiers":[
        {
            "category":"Organizations",
            "subcategory":"Religious Organization",
            "type":"Services"
        }
    ],
    "sg:phone":"+1 305 271 5645",
    "sg:postcode":"33186",
    "sg:province":"FL",
    "sg:tags":[
        "churches-non-denominational",
        "church"
    ],
    "wof:name":"River of Life",
    "wof:placetype":"venue"
},
  "geometry": {"coordinates":[-80.39450100000001,25.6619],"type":"Point"}
}