{
  "type": "Feature",
  "properties": {
    "iso:country":"US",
    "sg:address":"234 N Temple Ave",
    "sg:city":"Starke",
    "sg:classifiers":[
        {
            "category":"Home & Garden",
            "subcategory":"Household Appliances",
            "type":"Retail Goods"
        }
    ],
    "sg:phone":"+1 904 964 7596",
    "sg:postcode":"32091",
    "sg:province":"FL",
    "wof:name":"Winkler's",
    "wof:placetype":"venue"
},
  "geometry": {"coordinates":[-82.110945,29.945753],"type":"Point"}
}