{
  "type": "Feature",
  "properties": {
    "addr:full":"3030 Sleepy Hill Rd Lakeland FL 33810",
    "addr:housenumber":"3030",
    "addr:postcode":"33810",
    "addr:street":"Sleepy Hill Rd",
    "iso:country":"US",
    "sg:address":"3030 Sleepy Hill Rd",
    "sg:city":"Lakeland",
    "sg:classifiers":[
        {
            "category":"Government",
            "subcategory":"Fire Station",
            "type":"Public Place"
        }
    ],
    "sg:phone":"+1 863 853 6029",
    "sg:postcode":"33810",
    "sg:province":"FL",
    "sg:tags":[
        "department"
    ],
    "wof:name":"Polk County Fire Dept # 24",
    "wof:placetype":"venue"
},
  "geometry": {"coordinates":[-82.01014600000001,28.091399],"type":"Point"}
}