{
  "type": "Feature",
  "properties": {
    "addr:full":"2140 W Washington St Orlando FL 32805",
    "addr:housenumber":"2140",
    "addr:postcode":"32805",
    "addr:street":"W Washington St",
    "iso:country":"US",
    "sg:address":"2140 W Washington St",
    "sg:city":"Orlando",
    "sg:classifiers":[
        {
            "category":"Social Services",
            "subcategory":"Job Training",
            "type":"Services"
        }
    ],
    "sg:phone":"+1 407 245 1600",
    "sg:postcode":"32805",
    "sg:province":"FL",
    "sg:tags":[
        "rehab",
        "government"
    ],
    "wof:name":"Job Service",
    "wof:placetype":"venue"
},
  "geometry": {"coordinates":[-81.40942699999999,28.544421],"type":"Point"}
}