{
  "type": "Feature",
  "properties": {
    "iso:country":"US",
    "sg:address":"16808 Lemans Dr",
    "sg:city":"Spring Hill",
    "sg:classifiers":[
        {
            "category":"Wholesale",
            "subcategory":"Vending Machines",
            "type":"Manufacturing & Wholesale Goods"
        }
    ],
    "sg:phone":"+1 352 238 7162",
    "sg:postcode":"34610",
    "sg:province":"FL",
    "sg:tags":[
        "operator"
    ],
    "wof:name":"Todd Stump",
    "wof:placetype":"venue"
},
  "geometry": {"coordinates":[-82.540964,28.432658],"type":"Point"}
}