{
  "type": "Feature",
  "properties": {
    "iso:country":"US",
    "sg:address":"1177 NE 104th St",
    "sg:city":"Miami",
    "sg:classifiers":[
        {
            "category":"Wholesale",
            "subcategory":"Non-durable Goods",
            "type":"Manufacturing & Wholesale Goods"
        }
    ],
    "sg:phone":"+1 305 754 9349",
    "sg:postcode":"33138",
    "sg:province":"FL",
    "wof:name":"Bay Point Imports Inc",
    "wof:placetype":"venue"
},
  "geometry": {"coordinates":[-80.17238,25.870997],"type":"Point"}
}