{
  "type": "Feature",
  "properties": {
    "addr:full":"2861 Sherman Ave Naples FL 34120",
    "addr:housenumber":"2861",
    "addr:postcode":"34120",
    "addr:street":"Sherman Ave",
    "iso:country":"US",
    "sg:address":"2861 Sherman Ave",
    "sg:city":"Naples",
    "sg:classifiers":[
        {
            "category":"Wholesale",
            "subcategory":"Non-durable Goods",
            "type":"Manufacturing & Wholesale Goods"
        }
    ],
    "sg:phone":"+1 239 352 9115",
    "sg:postcode":"34120",
    "sg:province":"FL",
    "wof:name":"Wylde Thyme Hammock Inc",
    "wof:placetype":"venue"
},
  "geometry": {"coordinates":[-81.665885,26.246705],"type":"Point"}
}