{
  "type": "Feature",
  "properties": {
    "addr:full":"4640 E 10th Ln Hialeah FL 33013",
    "addr:housenumber":"4640",
    "addr:postcode":"33013",
    "addr:street":"E 10Th Ln",
    "iso:country":"US",
    "sg:address":"4640 E 10th Ln",
    "sg:city":"Hialeah",
    "sg:classifiers":[
        {
            "category":"Real Estate",
            "subcategory":"Real Estate Operator",
            "type":"Services"
        }
    ],
    "sg:phone":"+1 305 685 3722",
    "sg:postcode":"33013",
    "sg:province":"FL",
    "sg:tags":[
        "small",
        "warehouse",
        "owns",
        "lease"
    ],
    "wof:name":"Pinsky Properties",
    "wof:placetype":"venue"
},
  "geometry": {"coordinates":[-80.261478,25.864311],"type":"Point"}
}