{
  "type": "Feature",
  "properties": {
    "iso:country":"US",
    "sg:address":"9930 SW 3rd St",
    "sg:city":"Miami",
    "sg:classifiers":[
        {
            "category":"Building & Trades",
            "subcategory":"Construction",
            "type":"Services"
        }
    ],
    "sg:phone":"+1 305 223 6197",
    "sg:postcode":"33174",
    "sg:province":"FL",
    "sg:tags":[
        "carpentry",
        "contractor"
    ],
    "wof:name":"Cella Enterprises Co",
    "wof:placetype":"venue"
},
  "geometry": {"coordinates":[-80.360587,25.765734],"type":"Point"}
}