{
  "type": "Feature",
  "properties": {
    "iso:country":"US",
    "sg:address":"2119 W Daughtery Rd",
    "sg:city":"Lakeland",
    "sg:classifiers":[
        {
            "category":"Building & Trades",
            "subcategory":"Construction",
            "type":"Services"
        }
    ],
    "sg:phone":"+1 863 859 5859",
    "sg:postcode":"33810",
    "sg:province":"FL",
    "wof:name":"R and B Curbing",
    "wof:placetype":"venue"
},
  "geometry": {"coordinates":[-81.99036,28.120216],"type":"Point"}
}