{
  "type": "Feature",
  "properties": {
    "addr:full":"1170 Eddington Pl Marco Island FL 34145",
    "addr:housenumber":"1170",
    "addr:postcode":"34145",
    "addr:street":"Eddington Pl",
    "iso:country":"US",
    "sg:address":"1170 Eddington Pl",
    "sg:city":"Marco Island",
    "sg:classifiers":[
        {
            "category":"Real Estate",
            "subcategory":"Real Estate Agent",
            "type":"Services"
        },
        {
            "category":"Real Estate",
            "subcategory":"Real Estate Operator",
            "type":"Services"
        }
    ],
    "sg:phone":"+1 239 394 3345",
    "sg:postcode":"34145",
    "sg:province":"FL",
    "sg:tags":[
        "condominium"
    ],
    "wof:name":"Pavillion Condo Of Marco",
    "wof:placetype":"venue"
},
  "geometry": {"coordinates":[-81.73090000000001,25.969682],"type":"Point"}
}