{
  "type": "Feature",
  "properties": {
    "addr:full":"1466 L and R Industrial Blvd Tarpon Springs FL 34689",
    "addr:housenumber":"1466",
    "addr:postcode":"34689",
    "addr:street":"L And;Industrial Blvd",
    "iso:country":"US",
    "sg:address":"1466 L and R Industrial Blvd",
    "sg:city":"Tarpon Springs",
    "sg:classifiers":[
        {
            "category":"Wholesale",
            "subcategory":"Non-durable Goods",
            "type":"Manufacturing & Wholesale Goods"
        }
    ],
    "sg:phone":"+1 727 943 9498",
    "sg:postcode":"34689",
    "sg:province":"FL",
    "sg:tags":[
        "sponge"
    ],
    "sg:website":"www.spongesdirect.com",
    "wof:name":"Sponges Direct Inc",
    "wof:placetype":"venue"
},
  "geometry": {"coordinates":[-82.765244,28.165865],"type":"Point"}
}