{
  "type": "Feature",
  "properties": {
    "iso:country":"US",
    "sg:address":"2401 NW 93rd Ave",
    "sg:city":"Doral",
    "sg:classifiers":[
        {
            "category":"Shopping",
            "subcategory":"Shoes",
            "type":"Retail Goods"
        }
    ],
    "sg:phone":"+1 305 477 4011",
    "sg:postcode":"33172",
    "sg:province":"FL",
    "sg:tags":[
        "store"
    ],
    "wof:name":"Kinderland European Chldren Shoes Inc",
    "wof:placetype":"venue"
},
  "geometry": {"coordinates":[-80.346603,25.7962],"type":"Point"}
}