{
  "type": "Feature",
  "properties": {
    "iso:country":"US",
    "sg:address":"435 Southern Blvd",
    "sg:city":"West Palm Beach",
    "sg:classifiers":[
        {
            "category":"Wholesale",
            "subcategory":"Construction Materials",
            "type":"Manufacturing & Wholesale Goods"
        },
        {
            "category":"Home & Garden",
            "subcategory":"Furniture",
            "type":"Retail Goods"
        }
    ],
    "sg:phone":"+1 561 659 3134",
    "sg:postcode":"33405",
    "sg:province":"FL",
    "sg:tags":[
        "installs",
        "equipment",
        "kitchen",
        "cabinetry",
        "cabinet"
    ],
    "wof:name":"Leeds Custom Design LLC",
    "wof:placetype":"venue"
},
  "geometry": {"coordinates":[-80.057248,26.675859],"type":"Point"}
}