{
  "type": "Feature",
  "properties": {
    "iso:country":"US",
    "sg:address":"10707 Country River Dr",
    "sg:city":"Parrish",
    "sg:classifiers":[
        {
            "category":"Building & Trades",
            "subcategory":"Construction",
            "type":"Services"
        }
    ],
    "sg:phone":"+1 941 776 9041",
    "sg:postcode":"34219",
    "sg:province":"FL",
    "sg:tags":[
        "concrete",
        "pumping"
    ],
    "wof:name":"Scott Ryan Concrete Pumping",
    "wof:placetype":"venue"
},
  "geometry": {"coordinates":[-82.450957,27.538342],"type":"Point"}
}