{
  "type": "Feature",
  "properties": {
    "addr:full":"115 N Laurel Ave Sanford FL 32771",
    "addr:housenumber":"115",
    "addr:postcode":"32771",
    "addr:street":"N Laurel Ave",
    "iso:country":"US",
    "sg:address":"115 N Laurel Ave",
    "sg:city":"Sanford",
    "sg:classifiers":[
        {
            "category":"Home & Garden",
            "subcategory":"Garden Supply",
            "type":"Retail Goods"
        }
    ],
    "sg:phone":"+1 407 322 1235",
    "sg:postcode":"32771",
    "sg:province":"FL",
    "sg:tags":[
        "farm"
    ],
    "wof:name":"Tuckers Farm and Garden Center",
    "wof:placetype":"venue"
},
  "geometry": {"coordinates":[-81.272085,28.812363],"type":"Point"}
}