{
  "type": "Feature",
  "properties": {
    "iso:country":"US",
    "sg:address":"250 Power Ct",
    "sg:city":"Sanford",
    "sg:classifiers":[
        {
            "category":"Manufacturing",
            "subcategory":"Rubber & Plastics",
            "type":"Manufacturing & Wholesale Goods"
        }
    ],
    "sg:phone":"+1 407 328 8500",
    "sg:postcode":"32771",
    "sg:province":"FL",
    "wof:name":"Icorp-Ifoam Specialty Products",
    "wof:placetype":"venue"
},
  "geometry": {"coordinates":[-81.32969799999999,28.816096],"type":"Point"}
}