{
  "type": "Feature",
  "properties": {
    "iso:country":"US",
    "sg:address":"1840 NW 29th St",
    "sg:city":"Fort Lauderdale",
    "sg:classifiers":[
        {
            "category":"Retail",
            "subcategory":"Auto Repair",
            "type":"Services"
        }
    ],
    "sg:phone":"+1 954 714 5800",
    "sg:postcode":"33311",
    "sg:province":"FL",
    "sg:tags":[
        "automobile",
        "electric",
        "automotive"
    ],
    "wof:name":"Ebanks Auto Electric",
    "wof:placetype":"venue"
},
  "geometry": {"coordinates":[-80.16823100000001,26.162466],"type":"Point"}
}