{
  "type": "Feature",
  "properties": {
    "iso:country":"US",
    "sg:address":"239 NW 26th St",
    "sg:city":"Miami",
    "sg:classifiers":[
        {
            "category":"Home & Garden",
            "subcategory":"Furniture",
            "type":"Retail Goods"
        }
    ],
    "sg:phone":"+1 305 438 1797",
    "sg:postcode":"33127",
    "sg:province":"FL",
    "sg:tags":[
        "store"
    ],
    "wof:name":"Kmp Furniture",
    "wof:placetype":"venue"
},
  "geometry": {"coordinates":[-80.199315,25.801468],"type":"Point"}
}