{
  "type": "Feature",
  "properties": {
    "iso:country":"US",
    "sg:address":"6501 Pensacola Blvd",
    "sg:city":"Pensacola",
    "sg:classifiers":[
        {
            "category":"Banks & Credit Unions",
            "subcategory":"Financial Services",
            "type":"Services"
        }
    ],
    "sg:phone":"+1 850 944 4900",
    "sg:postcode":"32505",
    "sg:province":"FL",
    "sg:tags":[
        "franchising"
    ],
    "wof:name":"Lodging Hospitality Systems",
    "wof:placetype":"venue"
},
  "geometry": {"coordinates":[-87.257182,30.483758],"type":"Point"}
}