{
  "type": "Feature",
  "properties": {
    "addr:full":"3082 Gulf Breeze Pkwy Gulf Breeze FL 32563",
    "addr:housenumber":"3082",
    "addr:postcode":"32563",
    "addr:street":"Gulf Breeze Pkwy",
    "iso:country":"US",
    "sg:address":"3082 Gulf Breeze Pkwy",
    "sg:city":"Gulf Breeze",
    "sg:classifiers":[
        {
            "category":"Building & Trades",
            "subcategory":"Construction",
            "type":"Services"
        }
    ],
    "sg:phone":"+1 850 995 0371",
    "sg:postcode":"32563",
    "sg:province":"FL",
    "sg:tags":[
        "designer",
        "marine",
        "contractor"
    ],
    "wof:name":"Dale's Marine Construction Inc",
    "wof:placetype":"venue"
},
  "geometry": {"coordinates":[-87.092358,30.385975],"type":"Point"}
}