{
  "type": "Feature",
  "properties": {
    "addr:full":"2250 Lake Ruby Rd Deland FL 32724",
    "addr:housenumber":"2250",
    "addr:postcode":"32724",
    "addr:street":"Lake Ruby Rd",
    "iso:country":"US",
    "sg:address":"2250 Lake Ruby Rd",
    "sg:city":"Deland",
    "sg:classifiers":[
        {
            "category":"Building & Trades",
            "subcategory":"Construction",
            "type":"Services"
        }
    ],
    "sg:phone":"+1 386 736 3163",
    "sg:postcode":"32724",
    "sg:province":"FL",
    "sg:tags":[
        "dry wall",
        "contractor"
    ],
    "wof:name":"Steve's Drywall",
    "wof:placetype":"venue"
},
  "geometry": {"coordinates":[-81.25886800000001,29.039727],"type":"Point"}
}