{
  "type": "Feature",
  "properties": {
    "iso:country":"US",
    "sg:address":"86000 Overseas Hwy",
    "sg:city":"Islamorada",
    "sg:classifiers":[
        {
            "category":"Retail",
            "subcategory":"Veterinary Services",
            "type":"Services"
        }
    ],
    "sg:phone":"+1 305 664 0011",
    "sg:postcode":"33036",
    "sg:province":"FL",
    "sg:tags":[
        "veterinarian"
    ],
    "wof:name":"Animal Hospital Of Islamorada",
    "wof:placetype":"venue"
},
  "geometry": {"coordinates":[-80.57847099999999,24.956096],"type":"Point"}
}