{
  "type": "Feature",
  "properties": {
    "addr:full":"9800 SW 77th Ave Miami FL 33156",
    "addr:housenumber":"9800",
    "addr:postcode":"33156",
    "addr:street":"Sw 77Th Ave",
    "iso:country":"US",
    "sg:address":"9800 SW 77th Ave",
    "sg:city":"Miami",
    "sg:classifiers":[
        {
            "category":"Shopping",
            "subcategory":"Florist",
            "type":"Retail Goods"
        }
    ],
    "sg:phone":"+1 305 271 4140",
    "sg:postcode":"33156",
    "sg:province":"FL",
    "wof:name":"Dadeland Florist",
    "wof:placetype":"venue"
},
  "geometry": {"coordinates":[-80.318783,25.678541],"type":"Point"}
}