{
  "type": "Feature",
  "properties": {
    "addr:full":"1847 NE 211th Ln Miami FL 33179",
    "addr:housenumber":"1847",
    "addr:postcode":"33179",
    "addr:street":"Ne 211Th Ln",
    "iso:country":"US",
    "sg:address":"1847 NE 211th Ln",
    "sg:city":"Miami",
    "sg:classifiers":[
        {
            "category":"Restaurant",
            "type":"Food & Drink"
        }
    ],
    "sg:phone":"+1 305 919 7761",
    "sg:postcode":"33179",
    "sg:province":"FL",
    "sg:tags":[
        "eating"
    ],
    "wof:name":"Rio Burrito Inc",
    "wof:placetype":"venue"
},
  "geometry": {"coordinates":[-80.164333,25.970777],"type":"Point"}
}