{
  "type": "Feature",
  "properties": {
    "iso:country":"US",
    "sg:address":"609 W Kennedy Blvd",
    "sg:city":"Tampa",
    "sg:classifiers":[
        {
            "category":"Professional",
            "subcategory":"Accounting & Tax Preparation",
            "type":"Services"
        },
        {
            "category":"Banks & Credit Unions",
            "subcategory":"Financial Services",
            "type":"Services"
        }
    ],
    "sg:phone":"+1 813 259 9420",
    "sg:postcode":"33606",
    "sg:province":"FL",
    "sg:tags":[
        "return",
        "preparation-business",
        "cashing",
        "money",
        "loan",
        "order",
        "check"
    ],
    "sg:website":"http://www.amscottax.com",
    "wof:name":"Amscot",
    "wof:placetype":"venue"
},
  "geometry": {"coordinates":[-82.466523,27.944583],"type":"Point"}
}