{
  "type": "Feature",
  "properties": {
    "iso:country":"US",
    "sg:address":"6 S Main St",
    "sg:city":"Gainesville",
    "sg:classifiers":[
        {
            "category":"Restaurant",
            "type":"Food & Drink"
        }
    ],
    "sg:menulink":"http://www.allmenus.com/fl/gainesville/248384-manuels-vintage-room/menu/",
    "sg:phone":"+1 352 375 7372",
    "sg:postcode":"32601",
    "sg:province":"FL",
    "sg:tags":[
        "american",
        "pizza"
    ],
    "wof:name":"Manuel's Vintage Room",
    "wof:placetype":"venue"
},
  "geometry": {"coordinates":[-82.32502700000001,29.651904],"type":"Point"}
}