{
  "type": "Feature",
  "properties": {
    "addr:full":"210 Bryan Rd Brandon FL 33511",
    "addr:housenumber":"210",
    "addr:postcode":"33511",
    "addr:street":"Bryan Rd",
    "iso:country":"US",
    "sg:address":"210 Bryan Rd",
    "sg:city":"Brandon",
    "sg:classifiers":[
        {
            "category":"Health Services",
            "subcategory":"Clinic",
            "type":"Services"
        }
    ],
    "sg:phone":"+1 813 655 1731",
    "sg:postcode":"33511",
    "sg:province":"FL",
    "sg:tags":[
        "home"
    ],
    "wof:name":"Comfort Keepers",
    "wof:placetype":"venue"
},
  "geometry": {"coordinates":[-82.27754899999999,27.93336],"type":"Point"}
}