{
  "type": "Feature",
  "properties": {
    "addr:full":"41 N Jefferson St Pensacola FL 32502",
    "addr:housenumber":"41",
    "addr:postcode":"32502",
    "addr:street":"N Jefferson St",
    "iso:country":"US",
    "sg:address":"41 N Jefferson St",
    "sg:city":"Pensacola",
    "sg:classifiers":[
        {
            "category":"Professional",
            "type":"Services"
        }
    ],
    "sg:phone":"+1 850 969 1770",
    "sg:postcode":"32502",
    "sg:province":"FL",
    "sg:tags":[
        "establishment"
    ],
    "wof:name":"Gulf Coast Internet",
    "wof:placetype":"venue"
},
  "geometry": {"coordinates":[-87.214664,30.414124],"type":"Point"}
}