{
  "type": "Feature",
  "properties": {
    "iso:country":"US",
    "sg:address":"662 W Lake Dr",
    "sg:city":"Naples",
    "sg:classifiers":[
        {
            "category":"Professional",
            "subcategory":"Art Services",
            "type":"Services"
        }
    ],
    "sg:phone":"+1 239 643 4669",
    "sg:postcode":"34102",
    "sg:province":"FL",
    "sg:tags":[
        "commercial",
        "design",
        "business"
    ],
    "wof:name":"Pixelvision Inc",
    "wof:placetype":"venue"
},
  "geometry": {"coordinates":[-81.801309,26.13961],"type":"Point"}
}