{
  "type": "Feature",
  "properties": {
    "addr:full":"5910 Taylor Rd Naples FL 34109",
    "addr:housenumber":"5910",
    "addr:postcode":"34109",
    "addr:street":"Taylor Rd",
    "iso:country":"US",
    "sg:address":"5910 Taylor Rd",
    "sg:city":"Naples",
    "sg:classifiers":[
        {
            "category":"Local Transit",
            "type":"Transportation"
        }
    ],
    "sg:phone":"+1 239 598 2600",
    "sg:postcode":"34109",
    "sg:province":"FL",
    "sg:tags":[
        "rental",
        "driver",
        "limousine"
    ],
    "sg:website":"www.maxitaxi.com",
    "wof:name":"Maxi Taxi Of Florida Inc",
    "wof:placetype":"venue"
},
  "geometry": {"coordinates":[-81.783523,26.217683],"type":"Point"}
}