{
  "type": "Feature",
  "properties": {
    "iso:country":"US",
    "sg:address":"7208 Muirfield Ln",
    "sg:city":"Eden Prairie",
    "sg:classifiers":[
        {
            "category":"Building & Trades",
            "subcategory":"Locksmith",
            "type":"Services"
        }
    ],
    "sg:phone":"+1 612 216 0118",
    "sg:postcode":"55401",
    "sg:province":"FL",
    "sg:tags":[
        "key"
    ],
    "wof:name":"0 A A A 24 Hr Locksmith",
    "wof:placetype":"venue"
},
  "geometry": {"coordinates":[-93.503455,44.873466],"type":"Point"}
}