{
  "type": "Feature",
  "properties": {
    "iso:country":"US",
    "sg:address":"1010 Bunnell Rd",
    "sg:city":"Altamonte Spgs",
    "sg:classifiers":[
        {
            "category":"Home & Garden",
            "subcategory":"Building Materials",
            "type":"Retail Goods"
        }
    ],
    "sg:phone":"+1 407 317 9163",
    "sg:postcode":"32714",
    "sg:province":"FL",
    "sg:tags":[
        "glass",
        "window",
        "plate"
    ],
    "wof:name":"Zee Auto Glass",
    "wof:placetype":"venue"
},
  "geometry": {"coordinates":[-81.42357,28.657857],"type":"Point"}
}