{
  "type": "Feature",
  "properties": {
    "iso:country":"US",
    "sg:address":"2105 Reynolds St",
    "sg:city":"Sarasota",
    "sg:classifiers":[
        {
            "category":"Freight",
            "type":"Transportation"
        }
    ],
    "sg:phone":"+1 941 924 8691",
    "sg:postcode":"34231",
    "sg:province":"FL",
    "sg:tags":[
        "warehouse"
    ],
    "wof:name":"Falconer Furnishings",
    "wof:placetype":"venue"
},
  "geometry": {"coordinates":[-82.517213,27.256052],"type":"Point"}
}