{
  "type": "Feature",
  "properties": {
    "iso:country":"US",
    "sg:address":"1903 W Kingsfield Rd",
    "sg:city":"Cantonment",
    "sg:classifiers":[
        {
            "category":"Building & Trades",
            "subcategory":"Electrical",
            "type":"Services"
        }
    ],
    "sg:phone":"+1 850 968 1984",
    "sg:postcode":"32533",
    "sg:province":"FL",
    "sg:tags":[
        "industrial",
        "electrician",
        "contractors-commercial",
        "electric"
    ],
    "wof:name":"Webco Electrical Contractors Inc",
    "wof:placetype":"venue"
},
  "geometry": {"coordinates":[-87.3579,30.57502],"type":"Point"}
}