{
  "type": "Feature",
  "properties": {
    "iso:country":"US",
    "sg:address":"301 Maguire Rd Exn",
    "sg:city":"Ocoee",
    "sg:classifiers":[
        {
            "category":"Government",
            "subcategory":"Office",
            "type":"Public Place"
        }
    ],
    "sg:phone":"+1 407 905 3172",
    "sg:postcode":"34761",
    "sg:province":"FL",
    "sg:tags":[
        "city",
        "program"
    ],
    "wof:name":"Ocoee City Sanitation",
    "wof:placetype":"venue"
},
  "geometry": {"coordinates":[-81.549187,28.564381],"type":"Point"}
}