{
  "type": "Feature",
  "properties": {
    "addr:full":"6365 Taft St Hollywood FL 33024",
    "addr:housenumber":"6365",
    "addr:postcode":"33024",
    "addr:street":"Taft St",
    "iso:country":"US",
    "sg:address":"6365 Taft St",
    "sg:city":"Hollywood",
    "sg:classifiers":[
        {
            "category":"Insurance",
            "subcategory":"Insurance Agent",
            "type":"Services"
        }
    ],
    "sg:phone":"+1 954 924 9394",
    "sg:postcode":"33024",
    "sg:province":"FL",
    "wof:name":"Allstate Insurance",
    "wof:placetype":"venue"
},
  "geometry": {"coordinates":[-80.21403100000001,26.024863],"type":"Point"}
}