{
  "type": "Feature",
  "properties": {
    "iso:country":"US",
    "sg:address":"3412 S Sanford Ave",
    "sg:city":"Sanford",
    "sg:classifiers":[
        {
            "category":"Building & Trades",
            "subcategory":"Construction",
            "type":"Services"
        }
    ],
    "sg:phone":"+1 407 302 4631",
    "sg:postcode":"32773",
    "sg:province":"FL",
    "sg:tags":[
        "roofing",
        "contractor"
    ],
    "wof:name":"American Roofing & Gen Maint",
    "wof:placetype":"venue"
},
  "geometry": {"coordinates":[-81.264664,28.767055],"type":"Point"}
}