{
  "type": "Feature",
  "properties": {
    "iso:country":"US",
    "sg:address":"22455 Cheraton Rd",
    "sg:city":"Brooksville",
    "sg:classifiers":[
        {
            "category":"Building & Trades",
            "subcategory":"Construction",
            "type":"Services"
        }
    ],
    "sg:phone":"+1 352 544 0831",
    "sg:postcode":"34602",
    "sg:province":"FL",
    "sg:tags":[
        "contractor"
    ],
    "wof:name":"Messer Installation Inc",
    "wof:placetype":"venue"
},
  "geometry": {"coordinates":[-82.36577699999999,28.461252],"type":"Point"}
}