{
  "type": "Feature",
  "properties": {
    "addr:full":"811 N State Rd 7 Hollywood FL 33021",
    "addr:housenumber":"811;7",
    "addr:postcode":"33021",
    "addr:street":"N State Rd",
    "iso:country":"US",
    "sg:address":"811 N State Rd 7",
    "sg:city":"Hollywood",
    "sg:classifiers":[
        {
            "category":"Insurance",
            "subcategory":"Insurance Agent",
            "type":"Services"
        }
    ],
    "sg:phone":"+1 954 965 6940",
    "sg:postcode":"33021",
    "sg:province":"FL",
    "wof:name":"Silva & Jael Insurance",
    "wof:placetype":"venue"
},
  "geometry": {"coordinates":[-80.207849,26.017589],"type":"Point"}
}