{
  "type": "Feature",
  "properties": {
    "addr:full":"1434 Collins Ave Miami Beach FL 33139",
    "addr:housenumber":"1434",
    "addr:postcode":"33139",
    "addr:street":"Collins Ave",
    "iso:country":"US",
    "sg:address":"1434 Collins Ave",
    "sg:city":"Miami Beach",
    "sg:classifiers":[
        {
            "category":"Restaurant",
            "type":"Food & Drink"
        }
    ],
    "sg:phone":"+1 305 695 9869",
    "sg:postcode":"33139",
    "sg:province":"FL",
    "sg:tags":[
        "pizza"
    ],
    "sg:website":"www.zestopizza.com/",
    "wof:name":"Zesto Pizza",
    "wof:placetype":"venue"
},
  "geometry": {"coordinates":[-80.130725,25.786571],"type":"Point"}
}