{
  "type": "Feature",
  "properties": {
    "iso:country":"US",
    "sg:address":"8670 54th Avenue Cir E",
    "sg:city":"Bradenton",
    "sg:classifiers":[
        {
            "category":"Real Estate",
            "subcategory":"Developer",
            "type":"Services"
        }
    ],
    "sg:phone":"+1 941 751 6227",
    "sg:postcode":"34211",
    "sg:province":"FL",
    "wof:name":"Rosedale Development Inc",
    "wof:placetype":"venue"
},
  "geometry": {"coordinates":[-82.453158,27.442923],"type":"Point"}
}