{
  "type": "Feature",
  "properties": {
    "addr:full":"602 Live Oak Rd Vero Beach FL 32963",
    "addr:housenumber":"602",
    "addr:postcode":"oak;32963",
    "addr:street":"Live;Rd",
    "iso:country":"US",
    "sg:address":"602 Live Oak Rd",
    "sg:city":"Vero Beach",
    "sg:classifiers":[
        {
            "category":"Shopping",
            "subcategory":"Computers & Home Electronics",
            "type":"Retail Goods"
        }
    ],
    "sg:phone":"+1 772 231 7771",
    "sg:postcode":"32963",
    "sg:province":"FL",
    "sg:tags":[
        "equipment",
        "electronic",
        "supply"
    ],
    "wof:name":"Uni Circuit Inc",
    "wof:placetype":"venue"
},
  "geometry": {"coordinates":[-80.363055,27.662962],"type":"Point"}
}