{
  "type": "Feature",
  "properties": {
    "addr:full":"2601 W Lake Mary Blvd Lake Mary FL 32746",
    "addr:housenumber":"2601",
    "addr:postcode":"32746",
    "addr:street":"W Lake Mary Blvd",
    "iso:country":"US",
    "sg:address":"2601 W Lake Mary Blvd",
    "sg:city":"Lake Mary",
    "sg:classifiers":[
        {
            "category":"Real Estate",
            "subcategory":"Real Estate Agent",
            "type":"Services"
        }
    ],
    "sg:phone":"+1 407 585 1660",
    "sg:postcode":"32746",
    "sg:province":"FL",
    "sg:website":"www.centralfloridarealestate4sale.com",
    "wof:name":"Century 21",
    "wof:placetype":"venue"
},
  "geometry": {"coordinates":[-81.325895,28.756045],"type":"Point"}
}