{
  "type": "Feature",
  "properties": {
    "iso:country":"US",
    "sg:address":"10691 N Kendall Dr",
    "sg:city":"Miami",
    "sg:classifiers":[
        {
            "category":"Professional",
            "subcategory":"Lawyer & Legal Services",
            "type":"Services"
        }
    ],
    "sg:phone":"+1 305 595 0424",
    "sg:postcode":"33176",
    "sg:province":"FL",
    "sg:website":"www.garcialawoffices.com",
    "wof:name":"Giosmas George Attorney",
    "wof:placetype":"venue"
},
  "geometry": {"coordinates":[-80.365898,25.687],"type":"Point"}
}