{
  "type": "Feature",
  "properties": {
    "addr:full":"25426 Barinas Dr Punta Gorda FL 33983",
    "addr:housenumber":"25426",
    "addr:postcode":"33983",
    "addr:street":"Barinas Dr",
    "iso:country":"US",
    "sg:address":"25426 Barinas Dr",
    "sg:city":"Punta Gorda",
    "sg:classifiers":[
        {
            "category":"Building & Trades",
            "subcategory":"Construction",
            "type":"Services"
        }
    ],
    "sg:phone":"+1 941 625 0595",
    "sg:postcode":"33983",
    "sg:province":"FL",
    "sg:tags":[
        "hanging",
        "contractor"
    ],
    "wof:name":"Haynes Quality Painting Inc",
    "wof:placetype":"venue"
},
  "geometry": {"coordinates":[-82.027074,27.019781],"type":"Point"}
}