{
  "type": "Feature",
  "properties": {
    "iso:country":"US",
    "sg:address":"4828 Cardinal Trl",
    "sg:city":"Palm Harbor",
    "sg:classifiers":[
        {
            "category":"Wholesale",
            "subcategory":"Home Furnishings",
            "type":"Manufacturing & Wholesale Goods"
        }
    ],
    "sg:phone":"+1 727 410 1199",
    "sg:postcode":"34683",
    "sg:province":"FL",
    "sg:tags":[
        "shutter",
        "window"
    ],
    "wof:name":"Carribean Shade",
    "wof:placetype":"venue"
},
  "geometry": {"coordinates":[-82.76882000000001,28.120939],"type":"Point"}
}