{
  "type": "Feature",
  "properties": {
    "addr:full":"1266 Posner Blvd Davenport FL 33837",
    "addr:housenumber":"1266",
    "addr:postcode":"33837",
    "addr:street":"Posner Blvd",
    "iso:country":"US",
    "sg:address":"1266 Posner Blvd",
    "sg:city":"Davenport",
    "sg:classifiers":[
        {
            "category":"Restaurant",
            "type":"Food & Drink"
        }
    ],
    "sg:phone":"+1 863 420 4453",
    "sg:postcode":"33837",
    "sg:province":"FL",
    "sg:tags":[
        "lunch",
        "brunch",
        "cafeteria",
        "breakfast"
    ],
    "sg:website":"http://www.camillessidewalkcafellc.com/",
    "wof:name":"Camille's Sidewalk Cafe",
    "wof:placetype":"venue"
},
  "geometry": {"coordinates":[-81.64398199999999,28.22575],"type":"Point"}
}