{
  "type": "Feature",
  "properties": {
    "addr:full":"3655 NW 107th Ave Doral FL 33178",
    "addr:housenumber":"3655",
    "addr:postcode":"33178",
    "addr:street":"Nw 107Th Ave",
    "iso:country":"US",
    "sg:address":"3655 NW 107th Ave",
    "sg:city":"Doral",
    "sg:classifiers":[
        {
            "category":"Restaurant",
            "type":"Food & Drink"
        }
    ],
    "sg:phone":"+1 305 477 9899",
    "sg:postcode":"33178",
    "sg:province":"FL",
    "wof:name":"Doral Subs One",
    "wof:placetype":"venue"
},
  "geometry": {"coordinates":[-80.38500999999999,25.809695],"type":"Point"}
}