{
  "type": "Feature",
  "properties": {
    "addr:full":"205 Golden Gate Pt Sarasota FL 34236",
    "addr:housenumber":"205",
    "addr:postcode":"34236",
    "addr:street":"Golden Gate Pt",
    "iso:country":"US",
    "sg:address":"205 Golden Gate Pt",
    "sg:city":"Sarasota",
    "sg:classifiers":[
        {
            "category":"Shopping",
            "subcategory":"Computers & Home Electronics",
            "type":"Retail Goods"
        }
    ],
    "sg:phone":"+1 941 906 7295",
    "sg:postcode":"34236",
    "sg:province":"FL",
    "sg:tags":[
        "re",
        "software"
    ],
    "wof:name":"Terrapin Group LLC",
    "wof:placetype":"venue"
},
  "geometry": {"coordinates":[-82.549724,27.334091],"type":"Point"}
}