{
  "type": "Feature",
  "properties": {
    "iso:country":"US",
    "sg:address":"209 Duval St NW",
    "sg:city":"Live Oak",
    "sg:classifiers":[
        {
            "category":"Autos & Motor Vehicles",
            "subcategory":"Auto Supplies",
            "type":"Retail Goods"
        }
    ],
    "sg:phone":"+1 386 362 2329",
    "sg:postcode":"32064",
    "sg:province":"FL",
    "sg:tags":[
        "automobile",
        "parts"
    ],
    "wof:name":"LIVE Oak Auto Parts Inc",
    "wof:placetype":"venue"
},
  "geometry": {"coordinates":[-82.986419,30.299151],"type":"Point"}
}