{
  "type": "Feature",
  "properties": {
    "addr:full":"3100 N Federal Hwy Lighthouse Point FL 33064",
    "addr:housenumber":"3100",
    "addr:postcode":"33064",
    "addr:street":"N Federal Hwy",
    "iso:country":"US",
    "sg:address":"3100 N Federal Hwy",
    "sg:city":"Lighthouse Point",
    "sg:classifiers":[
        {
            "category":"Restaurant",
            "type":"Food & Drink"
        }
    ],
    "sg:phone":"+1 954 781 5795",
    "sg:postcode":"33064",
    "sg:province":"FL",
    "sg:tags":[
        "eating"
    ],
    "wof:name":"Skippers Ice Cream Cafe Inc",
    "wof:placetype":"venue"
},
  "geometry": {"coordinates":[-80.098353,26.269412],"type":"Point"}
}