{
  "type": "Feature",
  "properties": {
    "addr:full":"1985 W Nine Mile Rd Pensacola FL 32534",
    "addr:housenumber":"1985",
    "addr:postcode":"32534",
    "addr:street":"W Nine Mile Rd",
    "iso:country":"US",
    "sg:address":"1985 W Nine Mile Rd",
    "sg:city":"Pensacola",
    "sg:classifiers":[
        {
            "category":"Real Estate",
            "subcategory":"Developer",
            "type":"Services"
        }
    ],
    "sg:phone":"+1 850 479 9223",
    "sg:postcode":"32534",
    "sg:province":"FL",
    "sg:tags":[
        "funeral",
        "cemetery"
    ],
    "wof:name":"SCI",
    "wof:placetype":"venue"
},
  "geometry": {"coordinates":[-87.308913,30.534114],"type":"Point"}
}