{
  "type": "Feature",
  "properties": {
    "iso:country":"US",
    "sg:address":"14755 NW 22nd Ct",
    "sg:city":"Opa Locka",
    "sg:classifiers":[
        {
            "category":"Manufacturing",
            "subcategory":"Tools & Machinery",
            "type":"Manufacturing & Wholesale Goods"
        }
    ],
    "sg:phone":"+1 305 681 1883",
    "sg:postcode":"33054",
    "sg:province":"FL",
    "sg:tags":[
        "industrial",
        "mfg"
    ],
    "wof:name":"A B Machine Shop",
    "wof:placetype":"venue"
},
  "geometry": {"coordinates":[-80.23678099999999,25.910965],"type":"Point"}
}