{
  "type": "Feature",
  "properties": {
    "addr:full":"18212 Hoot Owl Ln Brooksville FL 34610",
    "addr:housenumber":"18212",
    "addr:postcode":"34610",
    "addr:street":"Hoot Owl Ln",
    "iso:country":"US",
    "sg:address":"18212 Hoot Owl Ln",
    "sg:city":"Brooksville",
    "sg:classifiers":[
        {
            "category":"Health Services",
            "subcategory":"Health Practitioner",
            "type":"Services"
        }
    ],
    "sg:phone":"+1 727 856 8400",
    "sg:postcode":"34610",
    "sg:province":"FL",
    "sg:tags":[
        "nurse",
        "registry"
    ],
    "wof:name":"Stanton's Nursing Personnel",
    "wof:placetype":"venue"
},
  "geometry": {"coordinates":[-82.54884300000001,28.422375],"type":"Point"}
}