{
  "type": "Feature",
  "properties": {
    "iso:country":"US",
    "sg:address":"8181 NW 91st Ter",
    "sg:city":"Medley",
    "sg:classifiers":[
        {
            "category":"Retail",
            "subcategory":"Repair Shop",
            "type":"Services"
        }
    ],
    "sg:phone":"+1 305 888 9157",
    "sg:postcode":"33166",
    "sg:province":"FL",
    "sg:tags":[
        "reupholstery",
        "furniture"
    ],
    "wof:name":"Quiala Ramon",
    "wof:placetype":"venue"
},
  "geometry": {"coordinates":[-80.330299,25.8566],"type":"Point"}
}