{
  "type": "Feature",
  "properties": {
    "iso:country":"US",
    "sg:address":"1918 Harrison St",
    "sg:city":"Hollywood",
    "sg:classifiers":[
        {
            "category":"Real Estate",
            "subcategory":"Real Estate Services",
            "type":"Services"
        }
    ],
    "sg:phone":"+1 954 923 5001",
    "sg:postcode":"33020",
    "sg:province":"FL",
    "sg:tags":[
        "company",
        "title"
    ],
    "wof:name":"True Title & Escrow",
    "wof:placetype":"venue"
},
  "geometry": {"coordinates":[-80.146629,26.010417],"type":"Point"}
}