{
  "type": "Feature",
  "properties": {
    "addr:full":"110 Lithia Pinecrest Rd Brandon FL 33511",
    "addr:housenumber":"110",
    "addr:postcode":"33511",
    "addr:street":"Lithia Pinecrest Rd",
    "iso:country":"US",
    "sg:address":"110 Lithia Pinecrest Rd",
    "sg:city":"Brandon",
    "sg:classifiers":[
        {
            "category":"Real Estate",
            "subcategory":"Real Estate Agent",
            "type":"Services"
        }
    ],
    "sg:phone":"+1 813 654 5099",
    "sg:postcode":"33511",
    "sg:province":"FL",
    "sg:website":"www.baysiderealtyflorida.com",
    "wof:name":"Bayside Realty Group Inc",
    "wof:placetype":"venue"
},
  "geometry": {"coordinates":[-82.28088200000001,27.936663],"type":"Point"}
}