{
  "type": "Feature",
  "properties": {
    "addr:full":"1590 Margaret St Deland FL 32720",
    "addr:housenumber":"1590",
    "addr:postcode":"32720",
    "addr:street":"Margaret St",
    "iso:country":"US",
    "sg:address":"1590 Margaret St",
    "sg:city":"Deland",
    "sg:classifiers":[
        {
            "category":"Wholesale",
            "subcategory":"Machinery & Supplies",
            "type":"Manufacturing & Wholesale Goods"
        }
    ],
    "sg:phone":"+1 407 331 9040",
    "sg:postcode":"32720",
    "sg:province":"FL",
    "sg:tags":[
        "janitor"
    ],
    "wof:name":"Equipment Masters",
    "wof:placetype":"venue"
},
  "geometry": {"coordinates":[-81.324524,28.999459],"type":"Point"}
}