{
  "type": "Feature",
  "properties": {
    "iso:country":"US",
    "sg:address":"10501 NW 17th. Street",
    "sg:city":"Plantation",
    "sg:classifiers":[
        {
            "category":"Retail",
            "subcategory":"Repair Shop",
            "type":"Services"
        },
        {
            "category":"Professional",
            "subcategory":"Lawyer & Legal Services",
            "type":"Services"
        },
        {
            "category":"Banks & Credit Unions",
            "subcategory":"Financial Services",
            "type":"Services"
        }
    ],
    "sg:phone":"+1 954 667 3783",
    "sg:postcode":"33322",
    "sg:province":"FL",
    "sg:tags":[
        "process",
        "skip",
        "eviction",
        "tracing",
        "server"
    ],
    "sg:website":"http://www.LegalEaseProcess.com",
    "wof:name":"Legal Ease Process Service",
    "wof:placetype":"venue"
},
  "geometry": {"coordinates":[-80.289439,26.144247],"type":"Point"}
}