{
  "type": "Feature",
  "properties": {
    "iso:country":"US",
    "sg:address":"2724 Country Club Rd",
    "sg:city":"Sanford",
    "sg:classifiers":[
        {
            "category":"Organizations",
            "subcategory":"Religious Organization",
            "type":"Services"
        }
    ],
    "sg:phone":"+1 407 302 1981",
    "sg:postcode":"32771",
    "sg:province":"FL",
    "sg:tags":[
        "church"
    ],
    "wof:name":"Second Chance Ministry",
    "wof:placetype":"venue"
},
  "geometry": {"coordinates":[-81.301474,28.788852],"type":"Point"}
}