{
  "type": "Feature",
  "properties": {
    "addr:full":"3136 Moody Ave Orange Park FL 32065",
    "addr:housenumber":"3136",
    "addr:postcode":"32065",
    "addr:street":"Moody Ave",
    "iso:country":"US",
    "sg:address":"3136 Moody Ave",
    "sg:city":"Orange Park",
    "sg:classifiers":[
        {
            "category":"Real Estate",
            "subcategory":"Real Estate Agent",
            "type":"Services"
        }
    ],
    "sg:phone":"+1 904 278 7530",
    "sg:postcode":"32065",
    "sg:province":"FL",
    "wof:name":"Eggemeyer Property Preperation",
    "wof:placetype":"venue"
},
  "geometry": {"coordinates":[-81.75394900000001,30.144802],"type":"Point"}
}