{
  "type": "Feature",
  "properties": {
    "addr:full":"1509 Valley Rd Tallahassee FL 32301",
    "addr:housenumber":"1509",
    "addr:postcode":"32301",
    "addr:street":"Valley Rd",
    "iso:country":"US",
    "sg:address":"1509 Valley Rd",
    "sg:city":"Tallahassee",
    "sg:classifiers":[
        {
            "category":"Building & Trades",
            "subcategory":"Electrical",
            "type":"Services"
        }
    ],
    "sg:phone":"+1 850 671 5314",
    "sg:postcode":"32301",
    "sg:province":"FL",
    "sg:tags":[
        "electrical",
        "electric",
        "contractor"
    ],
    "wof:name":"Marlin Electrical Service",
    "wof:placetype":"venue"
},
  "geometry": {"coordinates":[-84.257927,30.445006],"type":"Point"}
}