{
  "type": "Feature",
  "properties": {
    "iso:country":"US",
    "sg:address":"3141 Lake Ellen Dr",
    "sg:city":"Tampa",
    "sg:classifiers":[
        {
            "category":"Real Estate",
            "subcategory":"Real Estate Services",
            "type":"Services"
        },
        {
            "category":"Real Estate",
            "subcategory":"Real Estate Agent",
            "type":"Services"
        }
    ],
    "sg:phone":"+1 813 431 1925",
    "sg:postcode":"33618",
    "sg:province":"FL",
    "sg:tags":[
        "buyer",
        "broker"
    ],
    "wof:name":"Suddath Realty Services",
    "wof:placetype":"venue"
},
  "geometry": {"coordinates":[-82.494637,28.058409],"type":"Point"}
}