{
  "type": "Feature",
  "properties": {
    "iso:country":"US",
    "sg:address":"335 E Linton Blvd",
    "sg:city":"Delray Beach",
    "sg:classifiers":[
        {
            "category":"Retail",
            "subcategory":"Repair Shop",
            "type":"Services"
        }
    ],
    "sg:phone":"+1 561 953 2064",
    "sg:postcode":"33483",
    "sg:province":"FL",
    "sg:tags":[
        "lock",
        "locksmith"
    ],
    "wof:name":"7 Day Always Emergency Lcksmth",
    "wof:placetype":"venue"
},
  "geometry": {"coordinates":[-80.066996,26.439823],"type":"Point"}
}