{
  "type": "Feature",
  "properties": {
    "iso:country":"US",
    "sg:address":"1461 Sea Gull Dr S",
    "sg:city":"Saint Petersburg",
    "sg:classifiers":[
        {
            "category":"Banks & Credit Unions",
            "subcategory":"Bank",
            "type":"Services"
        }
    ],
    "sg:phone":"+1 727 343 2488",
    "sg:postcode":"33707",
    "sg:province":"FL",
    "sg:tags":[
        "broker",
        "mortgage"
    ],
    "wof:name":"Mortgageloanscom Inc",
    "wof:placetype":"venue"
},
  "geometry": {"coordinates":[-82.731742,27.752192],"type":"Point"}
}