{
  "type": "Feature",
  "properties": {
    "iso:country":"US",
    "sg:address":"8401 Aiken Ct",
    "sg:city":"Tampa",
    "sg:classifiers":[
        {
            "category":"Real Estate",
            "subcategory":"Real Estate Operator",
            "type":"Services"
        }
    ],
    "sg:phone":"+1 813 886 4541",
    "sg:postcode":"33615",
    "sg:province":"FL",
    "sg:tags":[
        "building",
        "apartment"
    ],
    "wof:name":"Country Square Apartments",
    "wof:placetype":"venue"
},
  "geometry": {"coordinates":[-82.57408,28.027258],"type":"Point"}
}