{
  "type": "Feature",
  "properties": {
    "iso:country":"US",
    "sg:address":"5100 Korbin Ave",
    "sg:city":"Rockledge",
    "sg:classifiers":[
        {
            "category":"Home & Garden",
            "subcategory":"Building Materials",
            "type":"Retail Goods"
        }
    ],
    "sg:phone":"+1 321 633 9393",
    "sg:postcode":"32955",
    "sg:province":"FL",
    "sg:tags":[
        "lumber",
        "other"
    ],
    "wof:name":"Prestige Truss",
    "wof:placetype":"venue"
},
  "geometry": {"coordinates":[-80.694011,28.269233],"type":"Point"}
}