{
  "type": "Feature",
  "properties": {
    "iso:country":"US",
    "sg:address":"4851 Jerry Johns Rd",
    "sg:city":"Macclenny",
    "sg:classifiers":[
        {
            "category":"Retail",
            "subcategory":"Auto Repair",
            "type":"Services"
        }
    ],
    "sg:phone":"+1 904 259 2287",
    "sg:postcode":"32063",
    "sg:province":"FL",
    "sg:tags":[
        "repairing",
        "automobile"
    ],
    "wof:name":"Mechanic On Wheels",
    "wof:placetype":"venue"
},
  "geometry": {"coordinates":[-82.122761,30.253177],"type":"Point"}
}