{
  "type": "Feature",
  "properties": {
    "iso:country":"US",
    "sg:address":"8750 NW 36th St Ste 560",
    "sg:city":"Doral",
    "sg:classifiers":[
        {
            "category":"Health Services",
            "subcategory":"Podiatrist",
            "type":"Services"
        },
        {
            "category":"Shopping",
            "subcategory":"Florist",
            "type":"Retail Goods"
        }
    ],
    "sg:phone":"+1 305 597 9404",
    "sg:postcode":"33178",
    "sg:province":"FL",
    "sg:tags":[
        "equipment",
        "supply"
    ],
    "wof:name":"Zimmer Latin America",
    "wof:placetype":"venue"
},
  "geometry": {"coordinates":[-80.338311,25.809886],"type":"Point"}
}