{
  "type": "Feature",
  "properties": {
    "iso:country":"US",
    "sg:address":"26851 S Bay Dr",
    "sg:city":"Bonita Springs",
    "sg:classifiers":[
        {
            "category":"Cafe",
            "type":"Food & Drink"
        }
    ],
    "sg:menulink":"http://www.allmenus.com/fl/bonita-springs/39268-the-american-cafe/menu/",
    "sg:phone":"+1 239 992 2528",
    "sg:postcode":"34134",
    "sg:province":"FL",
    "sg:tags":[
        "american"
    ],
    "wof:name":"The American Cafe",
    "wof:placetype":"venue"
},
  "geometry": {"coordinates":[-81.80812299999999,26.350479],"type":"Point"}
}