{
  "type": "Feature",
  "properties": {
    "addr:full":"601 Industrial St Lake Worth FL 33461",
    "addr:housenumber":"601",
    "addr:postcode":"33461",
    "addr:street":"Industrial St",
    "iso:country":"US",
    "sg:address":"601 Industrial St",
    "sg:city":"Lake Worth",
    "sg:classifiers":[
        {
            "category":"Retail",
            "subcategory":"Auto Repair",
            "type":"Services"
        }
    ],
    "sg:phone":"+1 561 547 5471",
    "sg:postcode":"33461",
    "sg:province":"FL",
    "sg:tags":[
        "repairing",
        "automobile"
    ],
    "wof:name":"Carls' Auto Care",
    "wof:placetype":"venue"
},
  "geometry": {"coordinates":[-80.068091,26.624197],"type":"Point"}
}