{
  "type": "Feature",
  "properties": {
    "addr:full":"392 N Congress Ave Boynton Beach FL 33426",
    "addr:housenumber":"392",
    "addr:postcode":"33426",
    "addr:street":"N Congress Ave",
    "iso:country":"US",
    "sg:address":"392 N Congress Ave",
    "sg:city":"Boynton Beach",
    "sg:classifiers":[
        {
            "category":"Wholesale",
            "subcategory":"Machinery & Supplies",
            "type":"Manufacturing & Wholesale Goods"
        },
        {
            "category":"Shopping",
            "subcategory":"Beauty & Cosmetics",
            "type":"Retail Goods"
        }
    ],
    "sg:phone":"+1 561 738 5268",
    "sg:postcode":"33426",
    "sg:province":"FL",
    "sg:tags":[
        "salon"
    ],
    "wof:name":"Sally Beauty Supply 1209",
    "wof:placetype":"venue"
},
  "geometry": {"coordinates":[-80.09044400000001,26.529553],"type":"Point"}
}