{
  "type": "Feature",
  "properties": {
    "iso:country":"US",
    "sg:address":"8455 NW 30th Pl",
    "sg:city":"Miami",
    "sg:classifiers":[
        {
            "category":"Shopping",
            "subcategory":"Music",
            "type":"Retail Goods"
        }
    ],
    "sg:phone":"+1 305 599 9032",
    "sg:postcode":"33147",
    "sg:province":"FL",
    "sg:tags":[
        "dvd's"
    ],
    "wof:name":"Americ Disc USA Inc",
    "wof:placetype":"venue"
},
  "geometry": {"coordinates":[-80.247597,25.850833],"type":"Point"}
}