{
  "type": "Feature",
  "properties": {
    "iso:country":"US",
    "sg:address":"6359 SW Co Rd 307",
    "sg:city":"Trenton",
    "sg:classifiers":[
        {
            "category":"Farming",
            "subcategory":"Farm",
            "type":"Manufacturing & Wholesale Goods"
        }
    ],
    "sg:phone":"+1 352 463 3500",
    "sg:postcode":"32693",
    "sg:province":"FL",
    "sg:tags":[
        "general"
    ],
    "wof:name":"De Champlain Heaven Gate Farm",
    "wof:placetype":"venue"
},
  "geometry": {"coordinates":[-82.857016,29.644566],"type":"Point"}
}