{
  "type": "Feature",
  "properties": {
    "iso:country":"US",
    "sg:address":"7352 Hawks Point Ct",
    "sg:city":"Jacksonville",
    "sg:classifiers":[
        {
            "category":"Building & Trades",
            "subcategory":"Construction",
            "type":"Services"
        }
    ],
    "sg:phone":"+1 904 317 0069",
    "sg:postcode":"32222",
    "sg:province":"FL",
    "sg:tags":[
        "home",
        "builder"
    ],
    "wof:name":"Kb Homes",
    "wof:placetype":"venue"
},
  "geometry": {"coordinates":[-81.81813699999999,30.210044],"type":"Point"}
}