{
  "type": "Feature",
  "properties": {
    "iso:country":"US",
    "sg:address":"4240 Manton Ln",
    "sg:city":"Holiday",
    "sg:classifiers":[
        {
            "category":"Building & Trades",
            "subcategory":"Cleaning & Sanitation",
            "type":"Services"
        }
    ],
    "sg:phone":"+1 727 389 2097",
    "sg:postcode":"34691",
    "sg:province":"FL",
    "sg:tags":[
        "property",
        "maintenance"
    ],
    "wof:name":"Steven Bushway Property Mntnc",
    "wof:placetype":"venue"
},
  "geometry": {"coordinates":[-82.743376,28.182738],"type":"Point"}
}