{
  "type": "Feature",
  "properties": {
    "iso:country":"US",
    "sg:address":"1300 Co Rd 200",
    "sg:city":"Tallahassee",
    "sg:classifiers":[
        {
            "category":"Professional",
            "subcategory":"Engineering",
            "type":"Services"
        }
    ],
    "sg:phone":"+1 850 385 5441",
    "sg:postcode":"32347",
    "sg:province":"FL",
    "wof:name":"Trow Consultant Inc",
    "wof:placetype":"venue"
},
  "geometry": {"coordinates":[-83.57500400000001,30.127732],"type":"Point"}
}