{
  "type": "Feature",
  "properties": {
    "addr:full":"3802 Sugar Palm Dr Tampa FL 33619",
    "addr:housenumber":"3802",
    "addr:postcode":"33619",
    "addr:street":"Sugar Palm Dr",
    "iso:country":"US",
    "sg:address":"3802 Sugar Palm Dr",
    "sg:city":"Tampa",
    "sg:classifiers":[
        {
            "category":"Insurance",
            "subcategory":"Insurance Agent",
            "type":"Services"
        }
    ],
    "sg:phone":"+1 813 246 5050",
    "sg:postcode":"33619",
    "sg:province":"FL",
    "sg:tags":[
        "agency"
    ],
    "wof:name":"Liberty National Lf Insur 56",
    "wof:placetype":"venue"
},
  "geometry": {"coordinates":[-82.351249,27.976744],"type":"Point"}
}