{
  "type": "Feature",
  "properties": {
    "iso:country":"US",
    "sg:address":"2801 Moss Grove Blvd",
    "sg:city":"Orlando",
    "sg:classifiers":[
        {
            "category":"Professional",
            "subcategory":"Accounting & Tax Preparation",
            "type":"Services"
        }
    ],
    "sg:phone":"+1 407 657 4793",
    "sg:postcode":"32807",
    "sg:province":"FL",
    "sg:tags":[
        "return",
        "filing"
    ],
    "wof:name":"Scott Flanagan Bkpg Tax Svc",
    "wof:placetype":"venue"
},
  "geometry": {"coordinates":[-81.290835,28.582334],"type":"Point"}
}