{
  "type": "Feature",
  "properties": {
    "addr:full":"2329 Urban Rd Jacksonville FL 32210",
    "addr:housenumber":"2329",
    "addr:postcode":"32210",
    "addr:street":"Urban Rd",
    "iso:country":"US",
    "sg:address":"2329 Urban Rd",
    "sg:city":"Jacksonville",
    "sg:classifiers":[
        {
            "category":"Building & Trades",
            "subcategory":"Construction",
            "type":"Services"
        }
    ],
    "sg:phone":"+1 904 387 9303",
    "sg:postcode":"32210",
    "sg:province":"FL",
    "sg:tags":[
        "contractor",
        "commercial",
        "general"
    ],
    "wof:name":"Worsham Construction Co Inc",
    "wof:placetype":"venue"
},
  "geometry": {"coordinates":[-81.720872,30.27722],"type":"Point"}
}