{
  "type": "Feature",
  "properties": {
    "iso:country":"US",
    "sg:address":"4901 Paul Buchman Hwy",
    "sg:city":"Plant City",
    "sg:classifiers":[
        {
            "category":"Food & Beverages",
            "subcategory":"Groceries & Convenience Stores",
            "type":"Retail Goods"
        }
    ],
    "sg:phone":"+1 813 754 5547",
    "sg:postcode":"33565",
    "sg:province":"FL",
    "wof:name":"Presco Food",
    "wof:placetype":"venue"
},
  "geometry": {"coordinates":[-82.139213,28.083686],"type":"Point"}
}