{
  "type": "Feature",
  "properties": {
    "iso:country":"US",
    "sg:address":"5760 NW 40th Ter",
    "sg:city":"Coconut Creek",
    "sg:classifiers":[
        {
            "category":"Social Services",
            "subcategory":"Adult Care",
            "type":"Services"
        }
    ],
    "sg:phone":"+1 954 426 2935",
    "sg:postcode":"33073",
    "sg:province":"FL",
    "sg:tags":[
        "home"
    ],
    "wof:name":"D & D Special Care Svc",
    "wof:placetype":"venue"
},
  "geometry": {"coordinates":[-80.178089,26.300512],"type":"Point"}
}