{
  "type": "Feature",
  "properties": {
    "addr:full":"8940 N Kendall Dr Ste 804E Miami FL 33176",
    "addr:housenumber":"8940",
    "addr:postcode":"33176",
    "addr:street":"N Kendall Dr Ste 804E",
    "iso:country":"US",
    "sg:address":"8940 N Kendall Dr Ste 804E",
    "sg:city":"Miami",
    "sg:classifiers":[
        {
            "category":"Health Services",
            "subcategory":"Doctor",
            "type":"Services"
        }
    ],
    "sg:phone":"+1 305 270 2331",
    "sg:postcode":"33176",
    "sg:province":"FL",
    "sg:tags":[
        "obstetrician",
        "gynecologist"
    ],
    "wof:name":"Del Boca Andrian MD",
    "wof:placetype":"venue"
},
  "geometry": {"coordinates":[-80.340998,25.684655],"type":"Point"}
}