{
  "type": "Feature",
  "properties": {
    "addr:full":"2209 University Blvd S Jacksonville FL 32216",
    "addr:housenumber":"2209",
    "addr:postcode":"32216",
    "addr:street":"University Blvd S",
    "iso:country":"US",
    "sg:address":"2209 University Blvd S",
    "sg:city":"Jacksonville",
    "sg:classifiers":[
        {
            "category":"Health Services",
            "subcategory":"Chiropractor",
            "type":"Services"
        }
    ],
    "sg:phone":"+1 904 372 0623",
    "sg:postcode":"32216",
    "sg:province":"FL",
    "sg:tags":[
        "chiropractic"
    ],
    "sg:website":"http://jaxbeachchiro.com",
    "wof:name":"Jacksonville Beach Chiropractic",
    "wof:placetype":"venue"
},
  "geometry": {"coordinates":[-81.60070899999999,30.304878],"type":"Point"}
}