{
  "type": "Feature",
  "properties": {
    "addr:full":"285 NE 17th Ct Fort Lauderdale FL 33305",
    "addr:housenumber":"285",
    "addr:postcode":"33305",
    "addr:street":"Ne 17Th Ct",
    "iso:country":"US",
    "sg:address":"285 NE 17th Ct",
    "sg:city":"Fort Lauderdale",
    "sg:classifiers":[
        {
            "category":"Shopping",
            "subcategory":"Discount & Variety Stores",
            "type":"Retail Goods"
        }
    ],
    "sg:phone":"+1 954 767 0165",
    "sg:postcode":"33305",
    "sg:province":"FL",
    "sg:tags":[
        "based",
        "internet"
    ],
    "wof:name":"Latreys",
    "wof:placetype":"venue"
},
  "geometry": {"coordinates":[-80.141328,26.150069],"type":"Point"}
}