{
  "type": "Feature",
  "properties": {
    "addr:full":"5184 Norwood Ave Jacksonville FL 32208",
    "addr:housenumber":"5184",
    "addr:postcode":"32208",
    "addr:street":"Norwood Ave",
    "iso:country":"US",
    "sg:address":"5184 Norwood Ave",
    "sg:city":"Jacksonville",
    "sg:classifiers":[
        {
            "category":"Banks & Credit Unions",
            "subcategory":"Bank",
            "type":"Services"
        }
    ],
    "sg:phone":"+1 904 765 3899",
    "sg:postcode":"32208",
    "sg:province":"FL",
    "sg:tags":[
        "machine",
        "teller",
        "automated"
    ],
    "wof:name":"Atm USA LLC",
    "wof:placetype":"venue"
},
  "geometry": {"coordinates":[-81.66390199999999,30.371217],"type":"Point"}
}