{
  "type": "Feature",
  "properties": {
    "iso:country":"US",
    "sg:address":"722 Hoffner Ave",
    "sg:city":"Orlando",
    "sg:classifiers":[
        {
            "category":"Shopping",
            "type":"Retail Goods"
        }
    ],
    "sg:phone":"+1 407 851 8871",
    "sg:postcode":"32809",
    "sg:province":"FL",
    "sg:tags":[
        "supply",
        "pool",
        "swimming"
    ],
    "sg:website":"http://www.poolpleaser.net",
    "wof:name":"Pool Pleaser The",
    "wof:placetype":"venue"
},
  "geometry": {"coordinates":[-81.36863700000001,28.475229],"type":"Point"}
}