{
  "type": "Feature",
  "properties": {
    "addr:full":"7307 NW 79th Ter Medley FL 33166",
    "addr:housenumber":"7307",
    "addr:postcode":"33166",
    "addr:street":"Nw 79Th Ter",
    "iso:country":"US",
    "sg:address":"7307 NW 79th Ter",
    "sg:city":"Medley",
    "sg:classifiers":[
        {
            "category":"Freight",
            "type":"Transportation"
        }
    ],
    "sg:phone":"+1 305 885 4478",
    "sg:postcode":"33166",
    "sg:province":"FL",
    "sg:tags":[
        "hauling",
        "trucking"
    ],
    "wof:name":"Quick Dispatch Intl",
    "wof:placetype":"venue"
},
  "geometry": {"coordinates":[-80.31658899999999,25.845792],"type":"Point"}
}