{
  "type": "Feature",
  "properties": {
    "iso:country":"US",
    "sg:address":"509 Fairways Ln",
    "sg:city":"Ocala",
    "sg:classifiers":[
        {
            "category":"Real Estate",
            "subcategory":"Real Estate Agent",
            "type":"Services"
        }
    ],
    "sg:phone":"+1 352 680 0906",
    "sg:postcode":"34472",
    "sg:province":"FL",
    "sg:tags":[
        "buyer",
        "broker"
    ],
    "wof:name":"Fairways Condominium",
    "wof:placetype":"venue"
},
  "geometry": {"coordinates":[-82.008684,29.116263],"type":"Point"}
}