{
  "type": "Feature",
  "properties": {
    "iso:country":"US",
    "sg:address":"207 Sandal Ln",
    "sg:city":"West Palm Beach",
    "sg:classifiers":[
        {
            "category":"Real Estate",
            "subcategory":"Real Estate Operator",
            "type":"Services"
        }
    ],
    "sg:phone":"+1 561 863 1268",
    "sg:postcode":"33404",
    "sg:province":"FL",
    "sg:tags":[
        "building",
        "apartment"
    ],
    "wof:name":"Beach Walk Apts Inc",
    "wof:placetype":"venue"
},
  "geometry": {"coordinates":[-80.03886199999999,26.780684],"type":"Point"}
}