{
  "type": "Feature",
  "properties": {
    "iso:country":"US",
    "sg:address":"9160 Woodville Hwy",
    "sg:city":"Tallahassee",
    "sg:classifiers":[
        {
            "category":"Food & Beverages",
            "subcategory":"Groceries & Convenience Stores",
            "type":"Retail Goods"
        }
    ],
    "sg:phone":"+1 850 421 6889",
    "sg:postcode":"32305",
    "sg:province":"FL",
    "sg:tags":[
        "grocer"
    ],
    "wof:name":"Inland Food Store",
    "wof:placetype":"venue"
},
  "geometry": {"coordinates":[-84.24800399999999,30.316513],"type":"Point"}
}