{
  "type": "Feature",
  "properties": {
    "addr:full":"1029 W Brandon Blvd Brandon FL 33511",
    "addr:housenumber":"1029",
    "addr:postcode":"33511",
    "addr:street":"W Brandon Blvd",
    "iso:country":"US",
    "sg:address":"1029 W Brandon Blvd",
    "sg:city":"Brandon",
    "sg:classifiers":[
        {
            "category":"Personal",
            "subcategory":"Tanning Parlor",
            "type":"Services"
        }
    ],
    "sg:phone":"+1 813 657 8266",
    "sg:postcode":"33511",
    "sg:province":"FL",
    "sg:tags":[
        "salon"
    ],
    "wof:name":"Sun Bar Tanning Saloon",
    "wof:placetype":"venue"
},
  "geometry": {"coordinates":[-82.300415,27.937699],"type":"Point"}
}