{
  "type": "Feature",
  "properties": {
    "iso:country":"US",
    "sg:address":"2723 Riverview Dr",
    "sg:city":"Naples",
    "sg:classifiers":[
        {
            "category":"Shopping",
            "subcategory":"Luggage & Leather Goods",
            "type":"Retail Goods"
        }
    ],
    "sg:phone":"+1 239 775 1132",
    "sg:postcode":"34112",
    "sg:province":"FL",
    "wof:name":"Aircraft Luggage Bomb Protecti",
    "wof:placetype":"venue"
},
  "geometry": {"coordinates":[-81.77143100000001,26.121972],"type":"Point"}
}