{
  "type": "Feature",
  "properties": {
    "addr:full":"1271 Pinetta Cir West Palm Beach FL 33414",
    "addr:housenumber":"1271",
    "addr:postcode":"33414",
    "addr:street":"Pinetta Cir",
    "iso:country":"US",
    "sg:address":"1271 Pinetta Cir",
    "sg:city":"West Palm Beach",
    "sg:classifiers":[
        {
            "category":"Food & Beverages",
            "subcategory":"Groceries & Convenience Stores",
            "type":"Retail Goods"
        }
    ],
    "sg:phone":"+1 561 753 5657",
    "sg:postcode":"33414",
    "sg:province":"FL",
    "wof:name":"Caspian Food & Produce Inc",
    "wof:placetype":"venue"
},
  "geometry": {"coordinates":[-80.225663,26.662247],"type":"Point"}
}