{
  "type": "Feature",
  "properties": {
    "iso:country":"US",
    "sg:address":"4825 Anzio St",
    "sg:city":"Orlando",
    "sg:classifiers":[
        {
            "category":"Building & Trades",
            "subcategory":"Cleaning & Sanitation",
            "type":"Services"
        }
    ],
    "sg:phone":"+1 407 354 0184",
    "sg:postcode":"32819",
    "sg:province":"FL",
    "sg:tags":[
        "maintenance"
    ],
    "wof:name":"Shirley Redding Cleaning",
    "wof:placetype":"venue"
},
  "geometry": {"coordinates":[-81.443669,28.455806],"type":"Point"}
}