{
  "type": "Feature",
  "properties": {
    "addr:full":"5909 S Congress Ave Lantana FL 33462",
    "addr:housenumber":"5909",
    "addr:postcode":"33462",
    "addr:street":"S Congress Ave",
    "iso:country":"US",
    "sg:address":"5909 S Congress Ave",
    "sg:city":"Lantana",
    "sg:classifiers":[
        {
            "category":"Health Services",
            "subcategory":"Doctor",
            "type":"Services"
        }
    ],
    "sg:phone":"+1 561 967 6453",
    "sg:postcode":"33462",
    "sg:province":"FL",
    "sg:tags":[
        "dentist"
    ],
    "wof:name":"Gary M Cohen DDS",
    "wof:placetype":"venue"
},
  "geometry": {"coordinates":[-80.093625,26.593044],"type":"Point"}
}