{
  "type": "Feature",
  "properties": {
    "addr:full":"8320 Green Bay Ct Orlando FL 32819",
    "addr:housenumber":"8320",
    "addr:postcode":"32819",
    "addr:street":"Green Bay Ct",
    "iso:country":"US",
    "sg:address":"8320 Green Bay Ct",
    "sg:city":"Orlando",
    "sg:classifiers":[
        {
            "category":"Real Estate",
            "subcategory":"Real Estate Agent",
            "type":"Services"
        }
    ],
    "sg:phone":"+1 407 352 1709",
    "sg:postcode":"32819",
    "sg:province":"FL",
    "sg:tags":[
        "inspection"
    ],
    "wof:name":"National Property Inspections",
    "wof:placetype":"venue"
},
  "geometry": {"coordinates":[-81.49709300000001,28.469592],"type":"Point"}
}