{
  "type": "Feature",
  "properties": {
    "addr:full":"382 NE 3rd Ave Delray Beach FL 33444",
    "addr:housenumber":"382",
    "addr:postcode":"33444",
    "addr:street":"Ne 3Rd Ave",
    "iso:country":"US",
    "sg:address":"382 NE 3rd Ave",
    "sg:city":"Delray Beach",
    "sg:classifiers":[
        {
            "category":"Building & Trades",
            "subcategory":"Construction",
            "type":"Services"
        }
    ],
    "sg:phone":"+1 561 276 3955",
    "sg:postcode":"33444",
    "sg:province":"FL",
    "sg:tags":[
        "masonry",
        "contractor"
    ],
    "wof:name":"Spengler Construction",
    "wof:placetype":"venue"
},
  "geometry": {"coordinates":[-80.07027600000001,26.467263],"type":"Point"}
}