{
  "type": "Feature",
  "properties": {
    "addr:full":"2901 SE Monroe St Stuart FL 34997",
    "addr:housenumber":"2901",
    "addr:postcode":"34997",
    "addr:street":"Se Monroe St",
    "iso:country":"US",
    "sg:address":"2901 SE Monroe St",
    "sg:city":"Stuart",
    "sg:classifiers":[
        {
            "category":"Manufacturing",
            "subcategory":"Tools & Machinery",
            "type":"Manufacturing & Wholesale Goods"
        }
    ],
    "sg:phone":"+1 772 219 9449",
    "sg:postcode":"34997",
    "sg:province":"FL",
    "sg:tags":[
        "set",
        "mfg"
    ],
    "sg:website":"www.tapower.com",
    "wof:name":"Elliott Energy Systems Inc",
    "wof:placetype":"venue"
},
  "geometry": {"coordinates":[-80.21291600000001,27.154697],"type":"Point"}
}