{
  "type": "Feature",
  "properties": {
    "addr:full":"1726 Lee Janzen Dr Kissimmee FL 34744",
    "addr:housenumber":"1726",
    "addr:postcode":"34744",
    "addr:street":"Lee Janzen Dr",
    "iso:country":"US",
    "sg:address":"1726 Lee Janzen Dr",
    "sg:city":"Kissimmee",
    "sg:classifiers":[
        {
            "category":"Building & Trades",
            "subcategory":"Landscaping Services",
            "type":"Services"
        }
    ],
    "sg:phone":"+1 407 344 3533",
    "sg:postcode":"34744",
    "sg:province":"FL",
    "sg:tags":[
        "lawn",
        "maintenance",
        "grounds"
    ],
    "wof:name":"Miller's Lawn Svc",
    "wof:placetype":"venue"
},
  "geometry": {"coordinates":[-81.32191899999999,28.30585],"type":"Point"}
}