{
  "type": "Feature",
  "properties": {
    "iso:country":"US",
    "sg:address":"15610 SW 80th St",
    "sg:city":"Miami",
    "sg:classifiers":[
        {
            "category":"Professional",
            "type":"Services"
        }
    ],
    "sg:phone":"+1 305 752 3357",
    "sg:postcode":"33193",
    "sg:province":"FL",
    "wof:name":"Cobenas Marble Corp",
    "wof:placetype":"venue"
},
  "geometry": {"coordinates":[-80.445036,25.6924],"type":"Point"}
}