{
  "type": "Feature",
  "properties": {
    "iso:country":"US",
    "sg:address":"2216 Highway 44 W",
    "sg:city":"Inverness",
    "sg:classifiers":[
        {
            "category":"Health Services",
            "subcategory":"Doctor",
            "type":"Services"
        }
    ],
    "sg:phone":"+1 352 860 0633",
    "sg:postcode":"34453",
    "sg:province":"FL",
    "sg:tags":[
        "medicine",
        "physician",
        "practice",
        "surgeons",
        "family"
    ],
    "wof:name":"Inverness Family Practice Pa",
    "wof:placetype":"venue"
},
  "geometry": {"coordinates":[-82.359021,28.839722],"type":"Point"}
}