{
  "type": "Feature",
  "properties": {
    "iso:country":"US",
    "sg:address":"8750 SW 144th St",
    "sg:city":"Palmetto Bay",
    "sg:classifiers":[
        {
            "category":"Health Services",
            "subcategory":"Dentist",
            "type":"Services"
        }
    ],
    "sg:phone":"+1 786 242 1908",
    "sg:postcode":"33176",
    "sg:province":"FL",
    "sg:tags":[
        "pediatric"
    ],
    "wof:name":"Varon Dina DDS",
    "wof:placetype":"venue"
},
  "geometry": {"coordinates":[-80.33506,25.636223],"type":"Point"}
}