{
  "type": "Feature",
  "properties": {
    "iso:country":"US",
    "sg:address":"1500 Jake Rd",
    "sg:city":"Jacksonville",
    "sg:classifiers":[
        {
            "category":"Building & Trades",
            "subcategory":"Electrical",
            "type":"Services"
        }
    ],
    "sg:phone":"+1 904 757 7621",
    "sg:postcode":"32226",
    "sg:province":"FL",
    "sg:tags":[
        "industrial",
        "electrician",
        "contractors-commercial",
        "electric"
    ],
    "wof:name":"Donaldson Electric Co",
    "wof:placetype":"venue"
},
  "geometry": {"coordinates":[-81.59129900000001,30.523005],"type":"Point"}
}