{
  "type": "Feature",
  "properties": {
    "addr:full":"5590 W 20th Ave Ste 300 Hialeah FL 33016",
    "addr:housenumber":"5590",
    "addr:postcode":"33016",
    "addr:street":"W 20Th Ave Ste 300",
    "iso:country":"US",
    "sg:address":"5590 W 20th Ave Ste 300",
    "sg:city":"Hialeah",
    "sg:classifiers":[
        {
            "category":"Health Services",
            "subcategory":"Doctor",
            "type":"Services"
        }
    ],
    "sg:phone":"+1 305 821 3388",
    "sg:postcode":"33016",
    "sg:province":"FL",
    "wof:name":"Uriel Roberto MD",
    "wof:placetype":"venue"
},
  "geometry": {"coordinates":[-80.3237,25.873501],"type":"Point"}
}