{
  "type": "Feature",
  "properties": {
    "addr:full":"1721 NW 41st St Miami FL 33142",
    "addr:housenumber":"1721",
    "addr:postcode":"33142",
    "addr:street":"Nw 41St St",
    "iso:country":"US",
    "sg:address":"1721 NW 41st St",
    "sg:city":"Miami",
    "sg:classifiers":[
        {
            "category":"Building & Trades",
            "subcategory":"Construction",
            "type":"Services"
        }
    ],
    "sg:phone":"+1 305 456 3692",
    "sg:postcode":"33142",
    "sg:province":"FL",
    "sg:tags":[
        "repair",
        "air conditioning"
    ],
    "wof:name":"Esco Air",
    "wof:placetype":"venue"
},
  "geometry": {"coordinates":[-80.224476,25.813296],"type":"Point"}
}