{
  "type": "Feature",
  "properties": {
    "iso:country":"US",
    "sg:address":"5803 N Armenia Ave",
    "sg:city":"Tampa",
    "sg:classifiers":[
        {
            "category":"Autos & Motor Vehicles",
            "subcategory":"Automobile Sales",
            "type":"Retail Goods"
        }
    ],
    "sg:phone":"+1 813 870 3999",
    "sg:postcode":"33603",
    "sg:province":"FL",
    "sg:tags":[
        "car",
        "dealer"
    ],
    "wof:name":"Linus Intl Inc",
    "wof:placetype":"venue"
},
  "geometry": {"coordinates":[-82.48438899999999,27.999004],"type":"Point"}
}