{
  "type": "Feature",
  "properties": {
    "iso:country":"US",
    "sg:address":"3 SW 3rd Ave",
    "sg:city":"Hallandale",
    "sg:classifiers":[
        {
            "category":"Banks & Credit Unions",
            "subcategory":"Financial Services",
            "type":"Services"
        }
    ],
    "sg:phone":"+1 954 458 0643",
    "sg:postcode":"33009",
    "sg:province":"FL",
    "sg:tags":[
        "investor"
    ],
    "wof:name":"Polelo Investments LLC",
    "wof:placetype":"venue"
},
  "geometry": {"coordinates":[-80.151205,25.984649],"type":"Point"}
}