{
  "type": "Feature",
  "properties": {
    "addr:full":"6180 Babcock St SE Palm Bay FL 32909",
    "addr:housenumber":"6180",
    "addr:postcode":"32909",
    "addr:street":"Babcock St Se",
    "iso:country":"US",
    "sg:address":"6180 Babcock St SE",
    "sg:city":"Palm Bay",
    "sg:classifiers":[
        {
            "category":"Building & Trades",
            "subcategory":"Construction",
            "type":"Services"
        }
    ],
    "sg:phone":"+1 321 722 2022",
    "sg:postcode":"32909",
    "sg:province":"FL",
    "sg:tags":[
        "tile",
        "dealer"
    ],
    "wof:name":"Vern Mohesky Marble & Tile",
    "wof:placetype":"venue"
},
  "geometry": {"coordinates":[-80.62188399999999,27.99422],"type":"Point"}
}