{
  "type": "Feature",
  "properties": {
    "iso:country":"US",
    "sg:address":"16900 S Tamiami Trl",
    "sg:city":"Fort Myers",
    "sg:classifiers":[
        {
            "category":"Organizations",
            "subcategory":"Community Association",
            "type":"Services"
        }
    ],
    "sg:phone":"+1 239 267 3030",
    "sg:postcode":"33908",
    "sg:province":"FL",
    "sg:tags":[
        "condominium"
    ],
    "wof:name":"America Outdoors Condo Assoc",
    "wof:placetype":"venue"
},
  "geometry": {"coordinates":[-81.850891,26.49651],"type":"Point"}
}