{
  "type": "Feature",
  "properties": {
    "iso:country":"US",
    "sg:address":"5000 NW 36th Ave",
    "sg:city":"Miami",
    "sg:classifiers":[
        {
            "category":"Education",
            "subcategory":"Special Training",
            "type":"Public Place"
        }
    ],
    "sg:phone":"+1 305 871 2226",
    "sg:postcode":"33142",
    "sg:province":"FL",
    "sg:tags":[
        "program"
    ],
    "wof:name":"Groupo Taca Training",
    "wof:placetype":"venue"
},
  "geometry": {"coordinates":[-80.254891,25.820643],"type":"Point"}
}