{
  "type": "Feature",
  "properties": {
    "iso:country":"US",
    "sg:address":"4655 NE 58th Ave",
    "sg:city":"Silver Springs",
    "sg:classifiers":[
        {
            "category":"Professional",
            "subcategory":"Management & Consulting",
            "type":"Services"
        }
    ],
    "sg:phone":"+1 352 236 2351",
    "sg:postcode":"34488",
    "sg:province":"FL",
    "sg:tags":[
        "aviation",
        "consultant"
    ],
    "wof:name":"Aerotech Services",
    "wof:placetype":"venue"
},
  "geometry": {"coordinates":[-82.053635,29.232303],"type":"Point"}
}