{
  "type": "Feature",
  "properties": {
    "addr:full":"5742 W Hallandale Beach Blvd Hollywood FL 33023",
    "addr:housenumber":"5742",
    "addr:postcode":"33023",
    "addr:street":"W Hallandale Beach Blvd",
    "iso:country":"US",
    "sg:address":"5742 W Hallandale Beach Blvd",
    "sg:city":"Hollywood",
    "sg:classifiers":[
        {
            "category":"Professional",
            "subcategory":"Detective & Security Services",
            "type":"Services"
        }
    ],
    "sg:phone":"+1 954 963 0281",
    "sg:postcode":"33023",
    "sg:province":"FL",
    "sg:tags":[
        "car"
    ],
    "wof:name":"M D Standley Invstigative Svcs",
    "wof:placetype":"venue"
},
  "geometry": {"coordinates":[-80.20233899999999,25.984575],"type":"Point"}
}