{
  "type": "Feature",
  "properties": {
    "iso:country":"US",
    "sg:address":"3313 Mustang Dr",
    "sg:city":"Brooksville",
    "sg:classifiers":[
        {
            "category":"Organizations",
            "subcategory":"Professional Association",
            "type":"Services"
        }
    ],
    "sg:phone":"+1 352 799 9077",
    "sg:postcode":"34604",
    "sg:province":"FL",
    "wof:name":"Christian Contractors Assn",
    "wof:placetype":"venue"
},
  "geometry": {"coordinates":[-82.45028000000001,28.482012],"type":"Point"}
}