{
  "type": "Feature",
  "properties": {
    "addr:full":"3150 Seasons Way Estero FL 33928",
    "addr:housenumber":"3150",
    "addr:postcode":"33928",
    "addr:street":"Seasons Way",
    "iso:country":"US",
    "sg:address":"3150 Seasons Way",
    "sg:city":"Estero",
    "sg:classifiers":[
        {
            "category":"Home & Garden",
            "subcategory":"Building Materials",
            "type":"Retail Goods"
        }
    ],
    "sg:phone":"+1 239 949 0570",
    "sg:postcode":"33928",
    "sg:province":"FL",
    "sg:tags":[
        "garage",
        "opener",
        "door"
    ],
    "wof:name":"Precision Door Service",
    "wof:placetype":"venue"
},
  "geometry": {"coordinates":[-81.814904,26.416581],"type":"Point"}
}