{
  "type": "Feature",
  "properties": {
    "iso:country":"US",
    "sg:address":"9501 W Hillsborough Ave",
    "sg:city":"Tampa",
    "sg:classifiers":[
        {
            "category":"Retail",
            "subcategory":"Auto Repair",
            "type":"Services"
        }
    ],
    "sg:phone":"+1 813 886 5757",
    "sg:postcode":"33615",
    "sg:province":"FL",
    "sg:tags":[
        "body",
        "automobile",
        "painting"
    ],
    "wof:name":"Norrid Paint & Body Shop Inc",
    "wof:placetype":"venue"
},
  "geometry": {"coordinates":[-82.59193999999999,27.999976],"type":"Point"}
}