{
  "type": "Feature",
  "properties": {
    "iso:country":"US",
    "sg:address":"3607 Herschel St",
    "sg:city":"Jacksonville",
    "sg:classifiers":[
        {
            "category":"Health Services",
            "subcategory":"Nursing And Care Facility",
            "type":"Services"
        },
        {
            "category":"Social Services",
            "subcategory":"Retirement Home",
            "type":"Services"
        },
        {
            "category":"Social Services",
            "subcategory":"Adult Care",
            "type":"Services"
        }
    ],
    "sg:phone":"+1 904 387 4034",
    "sg:postcode":"32205",
    "sg:province":"FL",
    "sg:tags":[
        "living",
        "people",
        "residential",
        "assisted",
        "elder",
        "convalescent",
        "centers-adult",
        "homes-elderly",
        "day"
    ],
    "wof:name":"Independent Manor",
    "wof:placetype":"venue"
},
  "geometry": {"coordinates":[-81.706515,30.298256],"type":"Point"}
}