{
  "type": "Feature",
  "properties": {
    "addr:full":"8177 NW 8th St Apt D2 Miami FL 33126",
    "addr:housenumber":"8177",
    "addr:postcode":"33126",
    "addr:street":"Nw 8Th St Apt D2",
    "iso:country":"US",
    "sg:address":"8177 NW 8th St Apt D2",
    "sg:city":"Miami",
    "sg:classifiers":[
        {
            "category":"Wholesale",
            "subcategory":"Computers",
            "type":"Manufacturing & Wholesale Goods"
        }
    ],
    "sg:phone":"+1 786 275 0288",
    "sg:postcode":"33126",
    "sg:province":"FL",
    "sg:tags":[
        "equipment"
    ],
    "wof:name":"Microtechnologys Inc",
    "wof:placetype":"venue"
},
  "geometry": {"coordinates":[-80.325524,25.778185],"type":"Point"}
}