{
  "type": "Feature",
  "properties": {
    "iso:country":"US",
    "sg:address":"5460 Carter Rd",
    "sg:city":"Fort Myers",
    "sg:classifiers":[
        {
            "category":"Banks & Credit Unions",
            "subcategory":"Investment Brokerage",
            "type":"Services"
        }
    ],
    "sg:phone":"+1 239 693 6589",
    "sg:postcode":"33905",
    "sg:province":"FL",
    "sg:tags":[
        "security"
    ],
    "wof:name":"Frame A Stock",
    "wof:placetype":"venue"
},
  "geometry": {"coordinates":[-81.77905,26.665177],"type":"Point"}
}