{
  "type": "Feature",
  "properties": {
    "iso:country":"US",
    "sg:address":"805 Laurel Dr",
    "sg:city":"Fort Walton Bch",
    "sg:classifiers":[
        {
            "category":"Shopping",
            "subcategory":"Florist",
            "type":"Retail Goods"
        }
    ],
    "sg:phone":"+1 850 862 8121",
    "sg:postcode":"32547",
    "sg:province":"FL",
    "wof:name":"Hospital Plaza Florist",
    "wof:placetype":"venue"
},
  "geometry": {"coordinates":[-86.65312,30.438503],"type":"Point"}
}