{
  "type": "Feature",
  "properties": {
    "addr:full":"9401 N Davis Hwy Pensacola FL 32514",
    "addr:housenumber":"9401",
    "addr:postcode":"32514",
    "addr:street":"N Davis Hwy",
    "iso:country":"US",
    "sg:address":"9401 N Davis Hwy",
    "sg:city":"Pensacola",
    "sg:phone":"+1 850 474 4708",
    "sg:postcode":"32514",
    "sg:province":"FL",
    "wof:name":"Chancies Package & Tavern Inc",
    "wof:placetype":"venue"
},
  "geometry": {"coordinates":[-87.20736599999999,30.531221],"type":"Point"}
}