{
  "type": "Feature",
  "properties": {
    "addr:full":"9468 NW 13th St Doral FL 33172",
    "addr:housenumber":"9468",
    "addr:postcode":"33172",
    "addr:street":"Nw 13Th St",
    "iso:country":"US",
    "sg:address":"9468 NW 13th St",
    "sg:city":"Doral",
    "sg:classifiers":[
        {
            "category":"Professional",
            "type":"Services"
        }
    ],
    "sg:phone":"+1 305 463 0120",
    "sg:postcode":"33172",
    "sg:province":"FL",
    "sg:tags":[
        "establishment"
    ],
    "wof:name":"Express Press",
    "wof:placetype":"venue"
},
  "geometry": {"coordinates":[-80.349484,25.784671],"type":"Point"}
}