{
  "type": "Feature",
  "properties": {
    "iso:country":"US",
    "sg:address":"12663 Tamiami Trl",
    "sg:city":"Naples",
    "sg:classifiers":[
        {
            "category":"Shopping",
            "subcategory":"Department Store",
            "type":"Retail Goods"
        }
    ],
    "sg:phone":"+1 239 775 0310",
    "sg:postcode":"34113",
    "sg:province":"FL",
    "sg:tags":[
        "shop"
    ],
    "wof:name":"Beall's Outlet",
    "wof:placetype":"venue"
},
  "geometry": {"coordinates":[-81.700008,26.063964],"type":"Point"}
}