{
  "type": "Feature",
  "properties": {
    "iso:country":"US",
    "sg:address":"1173 Port Ct",
    "sg:city":"Spring Hill",
    "sg:classifiers":[
        {
            "category":"Autos & Motor Vehicles",
            "subcategory":"Auto Supplies",
            "type":"Retail Goods"
        }
    ],
    "sg:phone":"+1 352 688 2478",
    "sg:postcode":"34606",
    "sg:province":"FL",
    "wof:name":"I & R Enterprises",
    "wof:placetype":"venue"
},
  "geometry": {"coordinates":[-82.59430999999999,28.450886],"type":"Point"}
}