{
  "type": "Feature",
  "properties": {
    "iso:country":"US",
    "sg:address":"2065 Delta Way",
    "sg:city":"Tallahassee",
    "sg:classifiers":[
        {
            "category":"Health Services",
            "subcategory":"Health Practitioner",
            "type":"Services"
        }
    ],
    "sg:phone":"+1 850 656 1822",
    "sg:postcode":"32303",
    "sg:province":"FL",
    "sg:tags":[
        "psychologist"
    ],
    "wof:name":"Mary K Price PHD",
    "wof:placetype":"venue"
},
  "geometry": {"coordinates":[-84.280208,30.47311],"type":"Point"}
}