{
  "type": "Feature",
  "properties": {
    "addr:full":"5227 Cerny Rd Apt 400 Pensacola FL 32526",
    "addr:housenumber":"400",
    "addr:postcode":"5227;32526",
    "addr:street":"Cerny Rd Apt",
    "iso:country":"US",
    "sg:address":"5227 Cerny Rd Apt 400",
    "sg:city":"Pensacola",
    "sg:classifiers":[
        {
            "category":"Real Estate",
            "subcategory":"Real Estate Services",
            "type":"Services"
        },
        {
            "category":"Real Estate",
            "subcategory":"Real Estate Operator",
            "type":"Services"
        }
    ],
    "sg:phone":"+1 850 456 3145",
    "sg:postcode":"32526",
    "sg:province":"FL",
    "sg:tags":[
        "apartment",
        "vacancy",
        "listing",
        "rental",
        "finder"
    ],
    "wof:name":"Cerny Village Apts",
    "wof:placetype":"venue"
},
  "geometry": {"coordinates":[-87.31980799999999,30.44849],"type":"Point"}
}