{
  "type": "Feature",
  "properties": {
    "iso:country":"US",
    "sg:address":"994 E Altamonte Dr",
    "sg:city":"Altamonte Springs",
    "sg:classifiers":[
        {
            "category":"Retail",
            "subcategory":"Funeral Services",
            "type":"Services"
        }
    ],
    "sg:phone":"+1 407 831 2626",
    "sg:postcode":"32701",
    "sg:province":"FL",
    "sg:tags":[
        "cemetery"
    ],
    "wof:name":"Baldwin-Fairchild Funeral Homes Ltd",
    "wof:placetype":"venue"
},
  "geometry": {"coordinates":[-81.35790299999999,28.663],"type":"Point"}
}