{
  "type": "Feature",
  "properties": {
    "addr:full":"2121 Camden Rd Orlando FL 32803",
    "addr:housenumber":"2121",
    "addr:postcode":"32803",
    "addr:street":"Camden Rd",
    "iso:country":"US",
    "sg:address":"2121 Camden Rd",
    "sg:city":"Orlando",
    "sg:classifiers":[
        {
            "category":"Professional",
            "subcategory":"Management & Consulting",
            "type":"Services"
        }
    ],
    "sg:phone":"+1 407 893 5205",
    "sg:postcode":"32803",
    "sg:province":"FL",
    "sg:tags":[
        "marketing",
        "program"
    ],
    "wof:name":"Chick Fla Marketing-Orlando",
    "wof:placetype":"venue"
},
  "geometry": {"coordinates":[-81.369128,28.571564],"type":"Point"}
}