{
  "type": "Feature",
  "properties": {
    "addr:full":"3500 Oaks Clubhouse Dr Pompano Beach FL 33069",
    "addr:housenumber":"3500",
    "addr:postcode":"33069",
    "addr:street":"Oaks Clubhouse Dr",
    "iso:country":"US",
    "sg:address":"3500 Oaks Clubhouse Dr",
    "sg:city":"Pompano Beach",
    "sg:classifiers":[
        {
            "category":"Recreation",
            "type":"Entertainment"
        }
    ],
    "sg:phone":"+1 954 969 8899",
    "sg:postcode":"33069",
    "sg:province":"FL",
    "sg:tags":[
        "academy",
        "tennis"
    ],
    "wof:name":"Macci Sports",
    "wof:placetype":"venue"
},
  "geometry": {"coordinates":[-80.17725799999999,26.221335],"type":"Point"}
}