{
  "type": "Feature",
  "properties": {
    "addr:full":"24 Hollywood Blvd SW Fort Walton Bch FL 32548",
    "addr:housenumber":"24",
    "addr:postcode":"32548",
    "addr:street":"Hollywood Blvd Sw",
    "iso:country":"US",
    "sg:address":"24 Hollywood Blvd SW",
    "sg:city":"Fort Walton Bch",
    "sg:classifiers":[
        {
            "category":"Organizations",
            "subcategory":"Non-profit Organization",
            "type":"Services"
        }
    ],
    "sg:phone":"+1 850 244 2421",
    "sg:postcode":"32548",
    "sg:province":"FL",
    "sg:tags":[
        "information",
        "alcoholism",
        "treatment"
    ],
    "wof:name":"Alcoholics Anonymous",
    "wof:placetype":"venue"
},
  "geometry": {"coordinates":[-86.615646,30.412506],"type":"Point"}
}