{
  "type": "Feature",
  "properties": {
    "iso:country":"US",
    "sg:address":"4608 E Columbus Dr",
    "sg:city":"Tampa",
    "sg:classifiers":[
        {
            "category":"Building & Trades",
            "subcategory":"Electrical",
            "type":"Services"
        }
    ],
    "sg:phone":"+1 813 661 5954",
    "sg:postcode":"33605",
    "sg:province":"FL",
    "sg:tags":[
        "electrical",
        "contractor"
    ],
    "wof:name":"All Florida Co-Op Inc",
    "wof:placetype":"venue"
},
  "geometry": {"coordinates":[-82.405013,27.966862],"type":"Point"}
}