{
  "type": "Feature",
  "properties": {
    "addr:full":"18601 SW 98th Ave Miami FL 33157",
    "addr:housenumber":"18601",
    "addr:postcode":"33157",
    "addr:street":"Sw 98Th Ave",
    "iso:country":"US",
    "sg:address":"18601 SW 98th Ave",
    "sg:city":"Miami",
    "sg:classifiers":[
        {
            "category":"Building & Trades",
            "subcategory":"Plumbing",
            "type":"Services"
        }
    ],
    "sg:phone":"+1 305 235 3622",
    "sg:postcode":"33157",
    "sg:province":"FL",
    "sg:tags":[
        "septic"
    ],
    "wof:name":"Alain Septic Tank Corp",
    "wof:placetype":"venue"
},
  "geometry": {"coordinates":[-80.35038299999999,25.594407],"type":"Point"}
}