{
  "type": "Feature",
  "properties": {
    "addr:full":"5100 W Lemon St Tampa FL 33609",
    "addr:housenumber":"5100",
    "addr:postcode":"33609",
    "addr:street":"W Lemon St",
    "iso:country":"US",
    "sg:address":"5100 W Lemon St",
    "sg:city":"Tampa",
    "sg:classifiers":[
        {
            "category":"Manufacturing",
            "subcategory":"Retail Goods",
            "type":"Manufacturing & Wholesale Goods"
        },
        {
            "category":"Professional",
            "subcategory":"Management & Consulting",
            "type":"Services"
        }
    ],
    "sg:phone":"+1 813 288 9381",
    "sg:postcode":"33609",
    "sg:province":"FL",
    "sg:tags":[
        "consultant",
        "product",
        "mfg",
        "government"
    ],
    "wof:name":"Gemini Industries Inc",
    "wof:placetype":"venue"
},
  "geometry": {"coordinates":[-82.53281800000001,27.950428],"type":"Point"}
}