{
  "type": "Feature",
  "properties": {
    "iso:country":"US",
    "sg:address":"11750 Alden Rd",
    "sg:city":"Jacksonville",
    "sg:classifiers":[
        {
            "category":"Professional",
            "subcategory":"Management & Consulting",
            "type":"Services"
        }
    ],
    "sg:phone":"+1 904 998 1900",
    "sg:postcode":"32246",
    "sg:province":"FL",
    "sg:tags":[
        "personnel",
        "consultant"
    ],
    "wof:name":"Future Executive Personnel Co",
    "wof:placetype":"venue"
},
  "geometry": {"coordinates":[-81.514674,30.301662],"type":"Point"}
}