{
  "type": "Feature",
  "properties": {
    "iso:country":"US",
    "sg:address":"2313 E 27th Ave",
    "sg:city":"Tampa",
    "sg:classifiers":[
        {
            "category":"Organizations",
            "subcategory":"Religious Organization",
            "type":"Services"
        }
    ],
    "sg:phone":"+1 813 241 8321",
    "sg:postcode":"33605",
    "sg:province":"FL",
    "sg:tags":[
        "church"
    ],
    "wof:name":"Jurisdiction Of Sw Florida",
    "wof:placetype":"venue"
},
  "geometry": {"coordinates":[-82.432862,27.974706],"type":"Point"}
}