{
  "type": "Feature",
  "properties": {
    "addr:full":"448 Espanola Way Miami Beach FL 33139",
    "addr:housenumber":"448",
    "addr:postcode":"33139",
    "addr:street":"Espanola Way",
    "iso:country":"US",
    "sg:address":"448 Espanola Way",
    "sg:city":"Miami Beach",
    "sg:classifiers":[
        {
            "category":"Bars & Pubs",
            "type":"Food & Drink"
        }
    ],
    "sg:phone":"+1 305 538 8272",
    "sg:postcode":"33139",
    "sg:province":"FL",
    "sg:tags":[
        "spanish"
    ],
    "sg:website":"www.tapasytintos.com",
    "wof:name":"Tapas y Tintos",
    "wof:placetype":"venue"
},
  "geometry": {"coordinates":[-80.132599,25.7868],"type":"Point"}
}