{
  "type": "Feature",
  "properties": {
    "iso:country":"US",
    "sg:address":"586 el Camino Real",
    "sg:city":"Naples",
    "sg:classifiers":[
        {
            "category":"Building & Trades",
            "subcategory":"Construction",
            "type":"Services"
        }
    ],
    "sg:phone":"+1 239 353 8355",
    "sg:postcode":"34119",
    "sg:province":"FL",
    "sg:tags":[
        "contractor"
    ],
    "wof:name":"Premiere Builders",
    "wof:placetype":"venue"
},
  "geometry": {"coordinates":[-81.733384,26.23193],"type":"Point"}
}