{
  "type": "Feature",
  "properties": {
    "iso:country":"US",
    "sg:address":"4800 Balboa Dr",
    "sg:city":"Orlando",
    "sg:classifiers":[
        {
            "category":"Professional",
            "subcategory":"Business Services",
            "type":"Services"
        }
    ],
    "sg:phone":"+1 407 253 4175",
    "sg:postcode":"32808",
    "sg:province":"FL",
    "wof:name":"Fidemax Inc",
    "wof:placetype":"venue"
},
  "geometry": {"coordinates":[-81.448093,28.560679],"type":"Point"}
}