{
  "type": "Feature",
  "properties": {
    "addr:full":"5645 SE 29th Ave Ocala FL 34480",
    "addr:housenumber":"5645",
    "addr:postcode":"34480",
    "addr:street":"Se 29Th Ave",
    "iso:country":"US",
    "sg:address":"5645 SE 29th Ave",
    "sg:city":"Ocala",
    "sg:classifiers":[
        {
            "category":"Personal",
            "subcategory":"Adult",
            "type":"Services"
        }
    ],
    "sg:phone":"+1 352 620 2654",
    "sg:postcode":"34480",
    "sg:province":"FL",
    "sg:tags":[
        "escort"
    ],
    "wof:name":"Joy's Escorts",
    "wof:placetype":"venue"
},
  "geometry": {"coordinates":[-82.09681,29.129196],"type":"Point"}
}