{
  "type": "Feature",
  "properties": {
    "addr:full":"6409 9th St N Saint Petersburg FL 33702",
    "addr:housenumber":"6409",
    "addr:postcode":"33702",
    "addr:street":"9Th St N",
    "iso:country":"US",
    "sg:address":"6409 9th St N",
    "sg:city":"Saint Petersburg",
    "sg:classifiers":[
        {
            "category":"Health Services",
            "subcategory":"Doctor",
            "type":"Services"
        }
    ],
    "sg:phone":"+1 727 528 1138",
    "sg:postcode":"33702",
    "sg:province":"FL",
    "sg:tags":[
        "medical"
    ],
    "wof:name":"A R Parbhoo MD",
    "wof:placetype":"venue"
},
  "geometry": {"coordinates":[-82.646871,27.831024],"type":"Point"}
}