{
  "type": "Feature",
  "properties": {
    "addr:full":"4933 Royal Ct N West Palm Beach FL 33415",
    "addr:housenumber":"4933",
    "addr:postcode":"33415",
    "addr:street":"Royal Ct N",
    "iso:country":"US",
    "sg:address":"4933 Royal Ct N",
    "sg:city":"West Palm Beach",
    "sg:classifiers":[
        {
            "category":"Shopping",
            "type":"Retail Goods"
        }
    ],
    "sg:phone":"+1 561 616 3958",
    "sg:postcode":"33415",
    "sg:province":"FL",
    "sg:tags":[
        "merchandise"
    ],
    "wof:name":"Boxlotfish Co",
    "wof:placetype":"venue"
},
  "geometry": {"coordinates":[-80.119315,26.671708],"type":"Point"}
}