{
  "type": "Feature",
  "properties": {
    "iso:country":"US",
    "sg:address":"140 Ellington Pl",
    "sg:city":"Oviedo",
    "sg:classifiers":[
        {
            "category":"Insurance",
            "subcategory":"Hazard Insurance",
            "type":"Services"
        }
    ],
    "sg:phone":"+1 407 366 2826",
    "sg:postcode":"32765",
    "sg:province":"FL",
    "sg:tags":[
        "commercial",
        "business"
    ],
    "wof:name":"Shah Insurance Agency",
    "wof:placetype":"venue"
},
  "geometry": {"coordinates":[-81.212048,28.687145],"type":"Point"}
}