{
  "type": "Feature",
  "properties": {
    "iso:country":"US",
    "sg:address":"5660 Gulf Breeze Pkwy",
    "sg:city":"Gulf Breeze",
    "sg:classifiers":[
        {
            "category":"Home & Garden",
            "subcategory":"Hardware",
            "type":"Retail Goods"
        }
    ],
    "sg:phone":"+1 850 916 2880",
    "sg:postcode":"32563",
    "sg:province":"FL",
    "sg:tags":[
        "me",
        "merchandise"
    ],
    "wof:name":"Precision Products",
    "wof:placetype":"venue"
},
  "geometry": {"coordinates":[-86.98293700000001,30.402205],"type":"Point"}
}