{
  "type": "Feature",
  "properties": {
    "addr:full":"2081 SE Ocean Blvd Stuart FL 34996",
    "addr:housenumber":"2081",
    "addr:postcode":"34996",
    "addr:street":"Se Ocean Blvd",
    "iso:country":"US",
    "sg:address":"2081 SE Ocean Blvd",
    "sg:city":"Stuart",
    "sg:classifiers":[
        {
            "category":"Health Services",
            "subcategory":"Doctor",
            "type":"Services"
        }
    ],
    "sg:phone":"+1 772 286 9779",
    "sg:postcode":"34996",
    "sg:province":"FL",
    "sg:tags":[
        "physician",
        "surgeon"
    ],
    "wof:name":"Osteoporosis Regional Ctr",
    "wof:placetype":"venue"
},
  "geometry": {"coordinates":[-80.224236,27.197424],"type":"Point"}
}