{
  "type": "Feature",
  "properties": {
    "addr:full":"7857 W Homosassa Trl Homosassa FL 34448",
    "addr:housenumber":"7857",
    "addr:postcode":"34448",
    "addr:street":"W Homosassa Trl",
    "iso:country":"US",
    "sg:address":"7857 W Homosassa Trl",
    "sg:city":"Homosassa",
    "sg:phone":"+1 352 382 5437",
    "sg:postcode":"34448",
    "sg:province":"FL",
    "wof:name":"Kids Trading Post",
    "wof:placetype":"venue"
},
  "geometry": {"coordinates":[-82.563709,28.814967],"type":"Point"}
}