{
  "type": "Feature",
  "properties": {
    "addr:full":"375 Deanna Rd Lake City FL 32025",
    "addr:housenumber":"375",
    "addr:postcode":"32025",
    "addr:street":"Deanna Rd",
    "iso:country":"US",
    "sg:address":"375 Deanna Rd",
    "sg:city":"Lake City",
    "sg:classifiers":[
        {
            "category":"Retail",
            "subcategory":"Auto Repair",
            "type":"Services"
        }
    ],
    "sg:phone":"+1 386 755 4332",
    "sg:postcode":"32025",
    "sg:province":"FL",
    "sg:tags":[
        "automotive"
    ],
    "wof:name":"Melvins Mobile Service",
    "wof:placetype":"venue"
},
  "geometry": {"coordinates":[-82.65270700000001,30.160933],"type":"Point"}
}