{
  "type": "Feature",
  "properties": {
    "addr:full":"305 Royal Poinciana Way Palm Beach FL 33480",
    "addr:housenumber":"305",
    "addr:postcode":"33480",
    "addr:street":"Royal Poinciana Way",
    "iso:country":"US",
    "sg:address":"305 Royal Poinciana Way",
    "sg:city":"Palm Beach",
    "sg:classifiers":[
        {
            "category":"Professional",
            "subcategory":"Management & Consulting",
            "type":"Services"
        }
    ],
    "sg:phone":"+1 561 833 4562",
    "sg:postcode":"33480",
    "sg:province":"FL",
    "sg:tags":[
        "consultant",
        "business"
    ],
    "wof:name":"A E Pearson Consultant",
    "wof:placetype":"venue"
},
  "geometry": {"coordinates":[-80.04279099999999,26.718221],"type":"Point"}
}