{
  "type": "Feature",
  "properties": {
    "addr:full":"18151 NE 31st Ct Aventura FL 33160",
    "addr:housenumber":"18151",
    "addr:postcode":"33160",
    "addr:street":"Ne 31St Ct",
    "iso:country":"US",
    "sg:address":"18151 NE 31st Ct",
    "sg:city":"Aventura",
    "sg:classifiers":[
        {
            "category":"Professional",
            "subcategory":"Business Services",
            "type":"Services"
        }
    ],
    "sg:phone":"+1 305 761 5833",
    "sg:postcode":"33160",
    "sg:province":"FL",
    "sg:tags":[
        "translator",
        "interpreter"
    ],
    "wof:name":"Span-It",
    "wof:placetype":"venue"
},
  "geometry": {"coordinates":[-80.138423,25.94494],"type":"Point"}
}