{
  "type": "Feature",
  "properties": {
    "iso:country":"US",
    "sg:address":"1702 W 68th St",
    "sg:city":"Hialeah",
    "sg:classifiers":[
        {
            "category":"Shopping",
            "subcategory":"Clothing, Apparel, & Fashions",
            "type":"Retail Goods"
        }
    ],
    "sg:phone":"+1 305 828 1986",
    "sg:postcode":"33014",
    "sg:province":"FL",
    "sg:tags":[
        "toy",
        "wear",
        "store"
    ],
    "wof:name":"El Palacio De Los Juguetes",
    "wof:placetype":"venue"
},
  "geometry": {"coordinates":[-80.3172,25.884199],"type":"Point"}
}