{
  "type": "Feature",
  "properties": {
    "addr:full":"822 Garnet Cir Fort Lauderdale FL 33326",
    "addr:housenumber":"822",
    "addr:postcode":"33326",
    "addr:street":"Garnet Cir",
    "iso:country":"US",
    "sg:address":"822 Garnet Cir",
    "sg:city":"Fort Lauderdale",
    "sg:classifiers":[
        {
            "category":"Personal",
            "type":"Services"
        }
    ],
    "sg:phone":"+1 954 537 3737",
    "sg:postcode":"33326",
    "sg:province":"FL",
    "sg:tags":[
        "miscellaneous"
    ],
    "wof:name":"Sit & Stay",
    "wof:placetype":"venue"
},
  "geometry": {"coordinates":[-80.392628,26.108594],"type":"Point"}
}