{
  "type": "Feature",
  "properties": {
    "iso:country":"US",
    "sg:address":"353 Eglin Pkwy",
    "sg:city":"Fort Walton Bch",
    "sg:classifiers":[
        {
            "category":"Shopping",
            "type":"Retail Goods"
        },
        {
            "category":"Manufacturing",
            "subcategory":"Retail Goods",
            "type":"Manufacturing & Wholesale Goods"
        }
    ],
    "sg:phone":"+1 850 863 2254",
    "sg:postcode":"32547",
    "sg:province":"FL",
    "sg:tags":[
        "rubber",
        "stamp",
        "merchandise"
    ],
    "wof:name":"Southern Rubber Stamp Shop",
    "wof:placetype":"venue"
},
  "geometry": {"coordinates":[-86.602647,30.435035],"type":"Point"}
}