{
  "type": "Feature",
  "properties": {
    "iso:country":"US",
    "sg:address":"6030 S Florida Ave",
    "sg:city":"Lakeland",
    "sg:classifiers":[
        {
            "category":"Real Estate",
            "subcategory":"Real Estate Agent",
            "type":"Services"
        }
    ],
    "sg:phone":"+1 863 648 0042",
    "sg:postcode":"33813",
    "sg:province":"FL",
    "wof:name":"Majestic Property",
    "wof:placetype":"venue"
},
  "geometry": {"coordinates":[-81.97073899999999,27.94972],"type":"Point"}
}