{
  "type": "Feature",
  "properties": {
    "iso:country":"US",
    "sg:address":"712 Florida Ave",
    "sg:city":"Cocoa",
    "sg:classifiers":[
        {
            "category":"Professional",
            "type":"Services"
        }
    ],
    "sg:phone":"+1 321 690 1796",
    "sg:postcode":"32922",
    "sg:province":"FL",
    "sg:tags":[
        "agent",
        "real estate"
    ],
    "wof:name":"Vms, No Listing",
    "wof:placetype":"venue"
},
  "geometry": {"coordinates":[-80.72772999999999,28.351851],"type":"Point"}
}