{
  "type": "Feature",
  "properties": {
    "addr:full":"1967 Sherwood St Clearwater FL 33765",
    "addr:housenumber":"1967",
    "addr:postcode":"33765",
    "addr:street":"Sherwood St",
    "iso:country":"US",
    "sg:address":"1967 Sherwood St",
    "sg:city":"Clearwater",
    "sg:classifiers":[
        {
            "category":"Freight",
            "type":"Transportation"
        }
    ],
    "sg:phone":"+1 727 446 3060",
    "sg:postcode":"33765",
    "sg:province":"FL",
    "sg:tags":[
        "warehouse",
        "rental",
        "general"
    ],
    "wof:name":"Bradford Rental Workshops",
    "wof:placetype":"venue"
},
  "geometry": {"coordinates":[-82.757344,27.980588],"type":"Point"}
}