{
  "type": "Feature",
  "properties": {
    "addr:full":"5340 NW 2nd Ave Boca Raton FL 33487",
    "addr:housenumber":"5340",
    "addr:postcode":"33487",
    "addr:street":"Nw 2Nd Ave",
    "iso:country":"US",
    "sg:address":"5340 NW 2nd Ave",
    "sg:city":"Boca Raton",
    "sg:classifiers":[
        {
            "category":"Retail",
            "subcategory":"Animal Services",
            "type":"Services"
        }
    ],
    "sg:phone":"+1 561 702 8301",
    "sg:postcode":"33487",
    "sg:province":"FL",
    "wof:name":"Arthur A Kennel",
    "wof:placetype":"venue"
},
  "geometry": {"coordinates":[-80.08379499999999,26.397275],"type":"Point"}
}