{
  "type": "Feature",
  "properties": {
    "addr:full":"251 Jasmine Rd Casselberry FL 32707",
    "addr:housenumber":"251",
    "addr:postcode":"32707",
    "addr:street":"Jasmine Rd",
    "iso:country":"US",
    "sg:address":"251 Jasmine Rd",
    "sg:city":"Casselberry",
    "sg:classifiers":[
        {
            "category":"Building & Trades",
            "subcategory":"Plumbing",
            "type":"Services"
        }
    ],
    "sg:phone":"+1 407 322 8442",
    "sg:postcode":"32707",
    "sg:province":"FL",
    "sg:tags":[
        "conditioning",
        "air",
        "system",
        "contractor"
    ],
    "wof:name":"Air Flow Designs Htg & AC",
    "wof:placetype":"venue"
},
  "geometry": {"coordinates":[-81.329859,28.65417],"type":"Point"}
}