{
  "type": "Feature",
  "properties": {
    "iso:country":"US",
    "sg:address":"9200 S Dadeland Blvd",
    "sg:city":"Miami",
    "sg:classifiers":[
        {
            "category":"Banks & Credit Unions",
            "subcategory":"Bank",
            "type":"Services"
        }
    ],
    "sg:phone":"+1 305 670 9292",
    "sg:postcode":"33156",
    "sg:province":"FL",
    "sg:tags":[
        "product",
        "export"
    ],
    "wof:name":"Crisf Inc",
    "wof:placetype":"venue"
},
  "geometry": {"coordinates":[-80.311481,25.687591],"type":"Point"}
}