{
  "type": "Feature",
  "properties": {
    "addr:full":"3380 SW Bayfield St Cocoa FL 32926",
    "addr:housenumber":"3380",
    "addr:postcode":"32926",
    "addr:street":"Sw Bayfield St",
    "iso:country":"US",
    "sg:address":"3380 SW Bayfield St",
    "sg:city":"Cocoa",
    "sg:classifiers":[
        {
            "category":"Building & Trades",
            "subcategory":"Construction",
            "type":"Services"
        }
    ],
    "sg:phone":"+1 321 639 9727",
    "sg:postcode":"32926",
    "sg:province":"FL",
    "sg:tags":[
        "contractor"
    ],
    "wof:name":"Werle & Son Inc",
    "wof:placetype":"venue"
},
  "geometry": {"coordinates":[-80.79300600000001,28.417502],"type":"Point"}
}