{
  "type": "Feature",
  "properties": {
    "iso:country":"US",
    "sg:address":"1207 Quintuplet Ct",
    "sg:city":"Casselberry",
    "sg:classifiers":[
        {
            "category":"Building & Trades",
            "subcategory":"Construction",
            "type":"Services"
        }
    ],
    "sg:phone":"+1 407 695 6212",
    "sg:postcode":"32707",
    "sg:province":"FL",
    "sg:tags":[
        "house"
    ],
    "wof:name":"JW Remodeling Inc",
    "wof:placetype":"venue"
},
  "geometry": {"coordinates":[-81.31265500000001,28.671727],"type":"Point"}
}