{
  "type": "Feature",
  "properties": {
    "iso:country":"US",
    "sg:address":"4989 S Ridgewood Ave",
    "sg:city":"Daytona Beach",
    "sg:classifiers":[
        {
            "category":"Restaurant",
            "type":"Food & Drink"
        }
    ],
    "sg:phone":"+1 386 761 7946",
    "sg:postcode":"32127",
    "sg:province":"FL",
    "sg:tags":[
        "eating"
    ],
    "wof:name":"Dutch Treat Restaurant",
    "wof:placetype":"venue"
},
  "geometry": {"coordinates":[-80.983012,29.133918],"type":"Point"}
}