{
  "type": "Feature",
  "properties": {
    "iso:country":"US",
    "sg:address":"10703 Biscayne Blvd",
    "sg:city":"Miami",
    "sg:classifiers":[
        {
            "category":"Professional",
            "subcategory":"Advertising",
            "type":"Services"
        },
        {
            "category":"Professional",
            "subcategory":"Art Services",
            "type":"Services"
        },
        {
            "category":"Communications",
            "type":"Services"
        },
        {
            "category":"Professional",
            "subcategory":"Computer Services",
            "type":"Services"
        }
    ],
    "sg:phone":"+1 305 434 4698",
    "sg:postcode":"33161",
    "sg:province":"FL",
    "sg:tags":[
        "web",
        "graphic",
        "marketing",
        "internet",
        "design",
        "online"
    ],
    "sg:website":"http://www.bestwebsitesdesigner.com",
    "wof:name":"Best Websites Designer",
    "wof:placetype":"venue"
},
  "geometry": {"coordinates":[-80.171069,25.873744],"type":"Point"}
}