{
  "type": "Feature",
  "properties": {
    "iso:country":"US",
    "sg:address":"1822 N T St",
    "sg:city":"Pensacola",
    "sg:classifiers":[
        {
            "category":"Organizations",
            "subcategory":"Religious Organization",
            "type":"Services"
        }
    ],
    "sg:phone":"+1 850 432 2378",
    "sg:postcode":"32505",
    "sg:province":"FL",
    "sg:tags":[
        "church"
    ],
    "wof:name":"Mount Pilgrim Baptist Church",
    "wof:placetype":"venue"
},
  "geometry": {"coordinates":[-87.246152,30.431161],"type":"Point"}
}