{
  "type": "Feature",
  "properties": {
    "addr:full":"200 Malaga St Saint Augustine FL 32084",
    "addr:housenumber":"200",
    "addr:postcode":"32084",
    "addr:street":"Malaga St",
    "iso:country":"US",
    "sg:address":"200 Malaga St",
    "sg:city":"Saint Augustine",
    "sg:classifiers":[
        {
            "category":"Government",
            "subcategory":"Office",
            "type":"Public Place"
        }
    ],
    "sg:phone":"+1 904 824 9534",
    "sg:postcode":"32084",
    "sg:province":"FL",
    "sg:tags":[
        "navy",
        "recruiting"
    ],
    "wof:name":"Recruiting Office",
    "wof:placetype":"venue"
},
  "geometry": {"coordinates":[-81.32088400000001,29.892837],"type":"Point"}
}