{
  "type": "Feature",
  "properties": {
    "addr:full":"309 W Main St Avon Park FL 33825",
    "addr:housenumber":"309",
    "addr:postcode":"33825",
    "addr:street":"W Main St",
    "iso:country":"US",
    "sg:address":"309 W Main St",
    "sg:city":"Avon Park",
    "sg:classifiers":[
        {
            "category":"Wholesale",
            "subcategory":"Auto Parts",
            "type":"Manufacturing & Wholesale Goods"
        }
    ],
    "sg:phone":"+1 863 453 2030",
    "sg:postcode":"33825",
    "sg:province":"FL",
    "sg:tags":[
        "tire"
    ],
    "wof:name":"Florida Tire Terminal-Retail",
    "wof:placetype":"venue"
},
  "geometry": {"coordinates":[-81.505689,27.595541],"type":"Point"}
}