{
  "type": "Feature",
  "properties": {
    "addr:full":"3208 17th St E Palmetto FL 34221",
    "addr:housenumber":"3208",
    "addr:postcode":"34221",
    "addr:street":"17Th St E",
    "iso:country":"US",
    "sg:address":"3208 17th St E",
    "sg:city":"Palmetto",
    "sg:classifiers":[
        {
            "category":"Building & Trades",
            "subcategory":"Construction",
            "type":"Services"
        }
    ],
    "sg:phone":"+1 941 722 6613",
    "sg:postcode":"34221",
    "sg:province":"FL",
    "sg:tags":[
        "contractor"
    ],
    "sg:website":"www.huxtedtunneling.com",
    "wof:name":"Huxted Tunneling",
    "wof:placetype":"venue"
},
  "geometry": {"coordinates":[-82.533984,27.529167],"type":"Point"}
}