{
  "type": "Feature",
  "properties": {
    "addr:full":"13900 Old Cutler Rd Miami FL 33158",
    "addr:housenumber":"13900",
    "addr:postcode":"33158",
    "addr:street":"Old Cutler Rd",
    "iso:country":"US",
    "sg:address":"13900 Old Cutler Rd",
    "sg:city":"Miami",
    "sg:classifiers":[
        {
            "category":"Building & Trades",
            "subcategory":"Construction",
            "type":"Services"
        }
    ],
    "sg:phone":"+1 305 259 1950",
    "sg:postcode":"33158",
    "sg:province":"FL",
    "sg:tags":[
        "carpentry",
        "contractor"
    ],
    "wof:name":"Round Tuit Inc",
    "wof:placetype":"venue"
},
  "geometry": {"coordinates":[-80.306579,25.640459],"type":"Point"}
}