{
  "type": "Feature",
  "properties": {
    "addr:full":"144 Springwood Dr Daytona Beach FL 32119",
    "addr:housenumber":"144",
    "addr:postcode":"32119",
    "addr:street":"Springwood Dr",
    "iso:country":"US",
    "sg:address":"144 Springwood Dr",
    "sg:city":"Daytona Beach",
    "sg:classifiers":[
        {
            "category":"Building & Trades",
            "subcategory":"Equipment Rental",
            "type":"Services"
        }
    ],
    "sg:phone":"+1 386 788 0868",
    "sg:postcode":"32119",
    "sg:province":"FL",
    "wof:name":"N&F Beach Rentals Inc",
    "wof:placetype":"venue"
},
  "geometry": {"coordinates":[-81.042642,29.166074],"type":"Point"}
}