{
  "type": "Feature",
  "properties": {
    "iso:country":"US",
    "sg:address":"2404 North Rd",
    "sg:city":"Cottondale",
    "sg:phone":"+1 850 352 4692",
    "sg:postcode":"32431",
    "sg:province":"FL",
    "sg:tags":[
        "farm",
        "corn",
        "soybean"
    ],
    "wof:name":"Whitehead Donnell",
    "wof:placetype":"venue"
},
  "geometry": {"coordinates":[-85.41456100000001,30.807271],"type":"Point"}
}