{
  "type": "Feature",
  "properties": {
    "addr:full":"656 E Hallandale Beach Blvd Hallandale FL 33009",
    "addr:housenumber":"656",
    "addr:postcode":"33009",
    "addr:street":"E Hallandale Beach Blvd",
    "iso:country":"US",
    "sg:address":"656 E Hallandale Beach Blvd",
    "sg:city":"Hallandale",
    "sg:classifiers":[
        {
            "category":"Professional",
            "subcategory":"Management & Consulting",
            "type":"Services"
        }
    ],
    "sg:phone":"+1 954 454 3602",
    "sg:postcode":"33009",
    "sg:province":"FL",
    "wof:name":"Property Tax Consultants Ltd",
    "wof:placetype":"venue"
},
  "geometry": {"coordinates":[-80.142247,25.985662],"type":"Point"}
}