{
  "type": "Feature",
  "properties": {
    "iso:country":"US",
    "sg:address":"3223 S John Young Pkwy",
    "sg:city":"Kissimmee",
    "sg:classifiers":[
        {
            "category":"Retail",
            "subcategory":"Veterinary Services",
            "type":"Services"
        }
    ],
    "sg:phone":"+1 407 870 7410",
    "sg:postcode":"34746",
    "sg:province":"FL",
    "sg:tags":[
        "veterinarian"
    ],
    "wof:name":"Osceola Animal Clinic",
    "wof:placetype":"venue"
},
  "geometry": {"coordinates":[-81.433795,28.262063],"type":"Point"}
}