{
  "type": "Feature",
  "properties": {
    "addr:full":"8770 SW 129th St Miami FL 33176",
    "addr:housenumber":"8770",
    "addr:postcode":"33176",
    "addr:street":"Sw 129Th St",
    "iso:country":"US",
    "sg:address":"8770 SW 129th St",
    "sg:city":"Miami",
    "sg:classifiers":[
        {
            "category":"Home & Garden",
            "subcategory":"Furniture",
            "type":"Retail Goods"
        }
    ],
    "sg:phone":"+1 305 233 6534",
    "sg:postcode":"33176",
    "sg:province":"FL",
    "sg:tags":[
        "display",
        "store",
        "plastic"
    ],
    "wof:name":"Custom Creative Plastics Miami",
    "wof:placetype":"venue"
},
  "geometry": {"coordinates":[-80.338347,25.650511],"type":"Point"}
}