{
  "type": "Feature",
  "properties": {
    "iso:country":"US",
    "sg:address":"3610 Madaca Ln",
    "sg:city":"Tampa",
    "sg:classifiers":[
        {
            "category":"Banks & Credit Unions",
            "subcategory":"Bank",
            "type":"Services"
        }
    ],
    "sg:phone":"+1 813 960 6020",
    "sg:postcode":"33618",
    "sg:province":"FL",
    "wof:name":"North Shore Bank",
    "wof:placetype":"venue"
},
  "geometry": {"coordinates":[-82.50203399999999,28.084239],"type":"Point"}
}