{
  "type": "Feature",
  "properties": {
    "addr:full":"14589 SW Dr Martin L King Jr Dr Indiantown FL 34956",
    "addr:housenumber":"14589",
    "addr:postcode":"34956",
    "addr:street":"Sw Dr Martin L King Jr Dr",
    "iso:country":"US",
    "sg:address":"14589 SW Dr Martin L King Jr Dr",
    "sg:city":"Indiantown",
    "sg:classifiers":[
        {
            "category":"Organizations",
            "subcategory":"Religious Organization",
            "type":"Services"
        }
    ],
    "sg:phone":"+1 772 597 4764",
    "sg:postcode":"34956",
    "sg:province":"FL",
    "sg:tags":[
        "church"
    ],
    "wof:name":"Faith Temple Church Of God",
    "wof:placetype":"venue"
},
  "geometry": {"coordinates":[-80.48574600000001,27.029192],"type":"Point"}
}