{
  "type": "Feature",
  "properties": {
    "addr:full":"48 Imperial Dr E Mulberry FL 33860",
    "addr:housenumber":"48",
    "addr:postcode":"33860",
    "addr:street":"Imperial Dr E",
    "iso:country":"US",
    "sg:address":"48 Imperial Dr E",
    "sg:city":"Mulberry",
    "sg:classifiers":[
        {
            "category":"Building & Trades",
            "subcategory":"Construction",
            "type":"Services"
        }
    ],
    "sg:phone":"+1 863 425 1878",
    "sg:postcode":"33860",
    "sg:province":"FL",
    "sg:tags":[
        "hanging",
        "contractor"
    ],
    "wof:name":"Boswell Enterprises",
    "wof:placetype":"venue"
},
  "geometry": {"coordinates":[-82.051664,27.928802],"type":"Point"}
}