{
  "type": "Feature",
  "properties": {
    "iso:country":"US",
    "sg:address":"107 Palm Valley Woods Dr",
    "sg:city":"Ponte Vedra Bch",
    "sg:classifiers":[
        {
            "category":"Wholesale",
            "subcategory":"Machinery & Supplies",
            "type":"Manufacturing & Wholesale Goods"
        }
    ],
    "sg:phone":"+1 904 448 0113",
    "sg:postcode":"32082",
    "sg:province":"FL",
    "sg:tags":[
        "equipment",
        "printing"
    ],
    "sg:website":"www.graphicsusainc.net",
    "wof:name":"Graphics USA Inc",
    "wof:placetype":"venue"
},
  "geometry": {"coordinates":[-81.394188,30.165038],"type":"Point"}
}