{
  "type": "Feature",
  "properties": {
    "addr:full":"9242 Co Rd 635 Sebring FL 33875",
    "addr:housenumber":"9242;635",
    "addr:postcode":"33875",
    "addr:street":"Co Rd",
    "iso:country":"US",
    "sg:address":"9242 Co Rd 635",
    "sg:city":"Sebring",
    "sg:classifiers":[
        {
            "category":"Building & Trades",
            "subcategory":"Plumbing",
            "type":"Services"
        }
    ],
    "sg:phone":"+1 863 471 2120",
    "sg:postcode":"33875",
    "sg:province":"FL",
    "sg:tags":[
        "air",
        "heating",
        "electrical",
        "conditioning",
        "contractor"
    ],
    "wof:name":"Glarner Electric & AC",
    "wof:placetype":"venue"
},
  "geometry": {"coordinates":[-81.51491900000001,27.421516],"type":"Point"}
}