{
  "type": "Feature",
  "properties": {
    "iso:country":"US",
    "sg:address":"101 W Main St",
    "sg:city":"Lakeland",
    "sg:classifiers":[
        {
            "category":"Banks & Credit Unions",
            "subcategory":"Bank",
            "type":"Services"
        }
    ],
    "sg:phone":"+1 863 686 0845",
    "sg:postcode":"33815",
    "sg:province":"FL",
    "sg:tags":[
        "banker",
        "mortgage"
    ],
    "wof:name":"Veterans Mortgage & Benefits",
    "wof:placetype":"venue"
},
  "geometry": {"coordinates":[-81.958242,28.044114],"type":"Point"}
}