{
  "type": "Feature",
  "properties": {
    "iso:country":"US",
    "sg:address":"400 Royal Palm Way",
    "sg:city":"Palm Beach",
    "sg:classifiers":[
        {
            "category":"Organizations",
            "subcategory":"Professional Association",
            "type":"Services"
        }
    ],
    "sg:phone":"+1 561 655 3282",
    "sg:postcode":"33480",
    "sg:province":"FL",
    "sg:tags":[
        "chambers",
        "commerce"
    ],
    "sg:website":"www.palmbeachchamber.com",
    "wof:name":"Palm Beach Chamber Of Commerce",
    "wof:placetype":"venue"
},
  "geometry": {"coordinates":[-80.042351,26.705759],"type":"Point"}
}