{
  "type": "Feature",
  "properties": {
    "addr:full":"402 River Dr Debary FL 32713",
    "addr:housenumber":"402",
    "addr:postcode":"32713",
    "addr:street":"River Dr",
    "iso:country":"US",
    "sg:address":"402 River Dr",
    "sg:city":"Debary",
    "sg:classifiers":[
        {
            "category":"Shopping",
            "subcategory":"Books",
            "type":"Retail Goods"
        },
        {
            "category":"Wholesale",
            "subcategory":"Books, Periodicals, & Newspapers",
            "type":"Manufacturing & Wholesale Goods"
        }
    ],
    "sg:phone":"+1 386 753 1445",
    "sg:postcode":"32713",
    "sg:province":"FL",
    "sg:tags":[
        "books-wholesale",
        "store",
        "manufacturer"
    ],
    "wof:name":"Marehootie Books",
    "wof:placetype":"venue"
},
  "geometry": {"coordinates":[-81.358262,28.870854],"type":"Point"}
}