{
  "type": "Feature",
  "properties": {
    "iso:country":"US",
    "sg:address":"3040 Harbor Landing Way",
    "sg:city":"Casselberry",
    "sg:classifiers":[
        {
            "category":"Banks & Credit Unions",
            "subcategory":"Investment Brokerage",
            "type":"Services"
        }
    ],
    "sg:phone":"+1 407 646 6711",
    "sg:postcode":"32707",
    "sg:province":"FL",
    "sg:tags":[
        "security"
    ],
    "wof:name":"Merrill Lynch",
    "wof:placetype":"venue"
},
  "geometry": {"coordinates":[-81.297513,28.646521],"type":"Point"}
}