{
  "type": "Feature",
  "properties": {
    "iso:country":"US",
    "sg:address":"11 Newcastle Ct",
    "sg:city":"Niceville",
    "sg:classifiers":[
        {
            "category":"Professional",
            "subcategory":"Management & Consulting",
            "type":"Services"
        }
    ],
    "sg:phone":"+1 850 897 5927",
    "sg:postcode":"32578",
    "sg:province":"FL",
    "sg:tags":[
        "consultant",
        "resource",
        "human"
    ],
    "wof:name":"Gilbert Associates",
    "wof:placetype":"venue"
},
  "geometry": {"coordinates":[-86.42155200000001,30.465789],"type":"Point"}
}