{
  "type": "Feature",
  "properties": {
    "addr:full":"400 Freeman St New Smyrna Beach FL 32168",
    "addr:housenumber":"400",
    "addr:postcode":"32168",
    "addr:street":"Freeman St",
    "iso:country":"US",
    "sg:address":"400 Freeman St",
    "sg:city":"New Smyrna Beach",
    "sg:classifiers":[
        {
            "category":"Professional",
            "subcategory":"Business Services",
            "type":"Services"
        }
    ],
    "sg:phone":"+1 386 427 8481",
    "sg:postcode":"32168",
    "sg:province":"FL",
    "wof:name":"Charles Sigler Enterprises",
    "wof:placetype":"venue"
},
  "geometry": {"coordinates":[-80.93731,29.038413],"type":"Point"}
}