{
  "type": "Feature",
  "properties": {
    "iso:country":"US",
    "sg:address":"12647 Dixie Hwy",
    "sg:city":"Miami",
    "sg:classifiers":[
        {
            "category":"Restaurant",
            "type":"Food & Drink"
        }
    ],
    "sg:phone":"+1 305 233 0058",
    "sg:postcode":"33156",
    "sg:province":"FL",
    "sg:tags":[
        "eating"
    ],
    "wof:name":"McDonalds",
    "wof:placetype":"venue"
},
  "geometry": {"coordinates":[-80.329598,25.653682],"type":"Point"}
}