{
  "type": "Feature",
  "properties": {
    "addr:full":"5367 214th Ct S Boca Raton FL 33486",
    "addr:housenumber":"5367",
    "addr:postcode":"33486",
    "addr:street":"214Th Ct S Boca",
    "iso:country":"US",
    "sg:address":"5367 214th Ct S",
    "sg:city":"Boca Raton",
    "sg:classifiers":[
        {
            "category":"Wholesale",
            "subcategory":"Stationery",
            "type":"Manufacturing & Wholesale Goods"
        }
    ],
    "sg:phone":"+1 561 750 3453",
    "sg:postcode":"33486",
    "sg:province":"FL",
    "sg:tags":[
        "paper"
    ],
    "wof:name":"Occasional Occasions",
    "wof:placetype":"venue"
},
  "geometry": {"coordinates":[-80.127667,26.358783],"type":"Point"}
}