{
  "type": "Feature",
  "properties": {
    "addr:full":"294 W Granada Blvd Ormond Beach FL 32174",
    "addr:housenumber":"294",
    "addr:postcode":"32174",
    "addr:street":"W Granada Blvd",
    "iso:country":"US",
    "sg:address":"294 W Granada Blvd",
    "sg:city":"Ormond Beach",
    "sg:classifiers":[
        {
            "category":"Restaurant",
            "type":"Food & Drink"
        }
    ],
    "sg:menulink":"http://www.allmenus.com/fl/ormond-beach/189669-kfc---kentucky-fried-chicken/menu/",
    "sg:phone":"+1 904 672 8331",
    "sg:postcode":"32174",
    "sg:province":"FL",
    "sg:tags":[
        "american",
        "chicken"
    ],
    "wof:name":"KFC - Kentucky Fried Chicken",
    "wof:placetype":"venue"
},
  "geometry": {"coordinates":[-81.062911,29.28203],"type":"Point"}
}