{
  "type": "Feature",
  "properties": {
    "iso:country":"US",
    "sg:address":"706 13th Ave",
    "sg:city":"Vero Beach",
    "sg:classifiers":[
        {
            "category":"Professional",
            "subcategory":"Management & Consulting",
            "type":"Services"
        }
    ],
    "sg:phone":"+1 772 770 1955",
    "sg:postcode":"32962",
    "sg:province":"FL",
    "sg:tags":[
        "consultant",
        "engineering",
        "airport"
    ],
    "wof:name":"Southern Aeronautics",
    "wof:placetype":"venue"
},
  "geometry": {"coordinates":[-80.398595,27.615644],"type":"Point"}
}