{
  "type": "Feature",
  "properties": {
    "addr:full":"12515 SW 43rd St Miami FL 33175",
    "addr:housenumber":"12515",
    "addr:postcode":"33175",
    "addr:street":"Sw 43Rd St",
    "iso:country":"US",
    "sg:address":"12515 SW 43rd St",
    "sg:city":"Miami",
    "sg:classifiers":[
        {
            "category":"Building & Trades",
            "subcategory":"Plumbing",
            "type":"Services"
        }
    ],
    "sg:phone":"+1 305 480 8888",
    "sg:postcode":"33175",
    "sg:province":"FL",
    "sg:tags":[
        "conditioning",
        "air",
        "system",
        "contractor"
    ],
    "wof:name":"Air Texcon Corp",
    "wof:placetype":"venue"
},
  "geometry": {"coordinates":[-80.394076,25.728447],"type":"Point"}
}