{
  "type": "Feature",
  "properties": {
    "iso:country":"US",
    "sg:address":"246 Georgetown Loop",
    "sg:city":"Wauchula",
    "sg:classifiers":[
        {
            "category":"Professional",
            "subcategory":"Business Services",
            "type":"Services"
        }
    ],
    "sg:phone":"+1 863 773 9401",
    "sg:postcode":"33873",
    "sg:province":"FL",
    "sg:tags":[
        "water",
        "equipment",
        "filtration",
        "treatment",
        "purification"
    ],
    "wof:name":"Rg Systems Inc",
    "wof:placetype":"venue"
},
  "geometry": {"coordinates":[-81.829128,27.549533],"type":"Point"}
}