{
  "type": "Feature",
  "properties": {
    "addr:full":"1606 White Dove Dr Winter Springs FL 32708",
    "addr:housenumber":"1606",
    "addr:postcode":"32708",
    "addr:street":"White Dove Dr",
    "iso:country":"US",
    "sg:address":"1606 White Dove Dr",
    "sg:city":"Winter Springs",
    "sg:classifiers":[
        {
            "category":"Banks & Credit Unions",
            "subcategory":"Financial Services",
            "type":"Services"
        }
    ],
    "sg:phone":"+1 407 977 7801",
    "sg:postcode":"32708",
    "sg:province":"FL",
    "sg:tags":[
        "company",
        "holding"
    ],
    "wof:name":"BSN Holdings LLC",
    "wof:placetype":"venue"
},
  "geometry": {"coordinates":[-81.235073,28.675112],"type":"Point"}
}