{
  "type": "Feature",
  "properties": {
    "addr:full":"1061 Collier Center Way Naples FL 34110",
    "addr:housenumber":"1061",
    "addr:postcode":"34110",
    "addr:street":"Collier Center Way",
    "iso:country":"US",
    "sg:address":"1061 Collier Center Way",
    "sg:city":"Naples",
    "sg:classifiers":[
        {
            "category":"Real Estate",
            "subcategory":"Developer",
            "type":"Services"
        }
    ],
    "sg:phone":"+1 239 593 1000",
    "sg:postcode":"34110",
    "sg:province":"FL",
    "wof:name":"Century Holding LTD",
    "wof:placetype":"venue"
},
  "geometry": {"coordinates":[-81.79624200000001,26.302976],"type":"Point"}
}