{
  "type": "Feature",
  "properties": {
    "addr:full":"12659 Dixie Hwy Miami FL 33156",
    "addr:housenumber":"12659",
    "addr:postcode":"33156",
    "addr:street":"Dixie Hwy",
    "iso:country":"US",
    "sg:address":"12659 Dixie Hwy",
    "sg:city":"Miami",
    "sg:classifiers":[
        {
            "category":"Real Estate",
            "subcategory":"Real Estate Agent",
            "type":"Services"
        }
    ],
    "sg:phone":"+1 305 232 4700",
    "sg:postcode":"33156",
    "sg:province":"FL",
    "sg:website":"www.realestateteammates.com",
    "wof:name":"Real Estate Teammates",
    "wof:placetype":"venue"
},
  "geometry": {"coordinates":[-80.329551,25.653796],"type":"Point"}
}