{
  "type": "Feature",
  "properties": {
    "addr:full":"3609 S Clark Ave Tampa FL 33629",
    "addr:housenumber":"3609",
    "addr:postcode":"33629",
    "addr:street":"S Clark Ave",
    "iso:country":"US",
    "sg:address":"3609 S Clark Ave",
    "sg:city":"Tampa",
    "sg:classifiers":[
        {
            "category":"Building & Trades",
            "subcategory":"Plumbing",
            "type":"Services"
        }
    ],
    "sg:phone":"+1 813 831 6766",
    "sg:postcode":"33629",
    "sg:province":"FL",
    "sg:tags":[
        "contractor"
    ],
    "wof:name":"T M Madden Service Inc",
    "wof:placetype":"venue"
},
  "geometry": {"coordinates":[-82.51228399999999,27.90928],"type":"Point"}
}