{
  "type": "Feature",
  "properties": {
    "iso:country":"US",
    "sg:address":"16071 Siesta Dr",
    "sg:city":"Fort Myers",
    "sg:classifiers":[
        {
            "category":"Retail",
            "subcategory":"Laundry & Dry Cleaning",
            "type":"Services"
        }
    ],
    "sg:phone":"+1 239 454 6688",
    "sg:postcode":"33908",
    "sg:province":"FL",
    "sg:tags":[
        "cleaners",
        "rug",
        "carpet"
    ],
    "wof:name":"Matt's Carpet Cleaning",
    "wof:placetype":"venue"
},
  "geometry": {"coordinates":[-81.940012,26.506349],"type":"Point"}
}