{
  "type": "Feature",
  "properties": {
    "iso:country":"US",
    "sg:address":"355 N US Hwy 17/92",
    "sg:city":"Longwood",
    "sg:classifiers":[
        {
            "category":"Retail",
            "subcategory":"Auto Repair",
            "type":"Services"
        }
    ],
    "sg:phone":"+1 407 699 4622",
    "sg:postcode":"32750",
    "sg:province":"FL",
    "sg:tags":[
        "tire",
        "general"
    ],
    "wof:name":"Goodrich B F Service Center",
    "wof:placetype":"venue"
},
  "geometry": {"coordinates":[-81.32675999999999,28.70224],"type":"Point"}
}