{
  "type": "Feature",
  "properties": {
    "addr:full":"5104 N Orange Blossom Trl Orlando FL 32810",
    "addr:housenumber":"5104",
    "addr:postcode":"32810",
    "addr:street":"N Orange Blossom Trl",
    "iso:country":"US",
    "sg:address":"5104 N Orange Blossom Trl",
    "sg:city":"Orlando",
    "sg:classifiers":[
        {
            "category":"Insurance",
            "subcategory":"Insurance Agent",
            "type":"Services"
        }
    ],
    "sg:phone":"+1 407 290 5000",
    "sg:postcode":"32810",
    "sg:province":"FL",
    "wof:name":"Allstate Insurance",
    "wof:placetype":"venue"
},
  "geometry": {"coordinates":[-81.42148299999999,28.605373],"type":"Point"}
}