{
  "type": "Feature",
  "properties": {
    "addr:full":"2103 SW 22nd St Coral Gables FL 33145",
    "addr:housenumber":"2103",
    "addr:postcode":"33145",
    "addr:street":"Sw 22Nd St",
    "iso:country":"US",
    "sg:address":"2103 SW 22nd St",
    "sg:city":"Coral Gables",
    "sg:classifiers":[
        {
            "category":"Government",
            "subcategory":"Office",
            "type":"Public Place"
        }
    ],
    "sg:phone":"+1 305 858 7633",
    "sg:postcode":"33145",
    "sg:province":"FL",
    "sg:tags":[
        "federal",
        "affairs"
    ],
    "wof:name":"Australian Consulate",
    "wof:placetype":"venue"
},
  "geometry": {"coordinates":[-80.230099,25.75067],"type":"Point"}
}