{
  "type": "Feature",
  "properties": {
    "iso:country":"US",
    "sg:address":"5928 SE Hames Rd",
    "sg:city":"Belleview",
    "sg:classifiers":[
        {
            "category":"Shopping",
            "type":"Retail Goods"
        }
    ],
    "sg:phone":"+1 352 245 7999",
    "sg:postcode":"34420",
    "sg:province":"FL",
    "sg:tags":[
        "merchandise"
    ],
    "wof:name":"Critter Crossings",
    "wof:placetype":"venue"
},
  "geometry": {"coordinates":[-82.05290100000001,29.058887],"type":"Point"}
}