{
  "type": "Feature",
  "properties": {
    "iso:country":"US",
    "sg:address":"4027 Domestic Ave",
    "sg:city":"Naples",
    "sg:classifiers":[
        {
            "category":"Restaurant",
            "type":"Food & Drink"
        }
    ],
    "sg:phone":"+1 239 643 4411",
    "sg:postcode":"34104",
    "sg:province":"FL",
    "wof:name":"Massey's Sub Shop",
    "wof:placetype":"venue"
},
  "geometry": {"coordinates":[-81.75439299999999,26.162656],"type":"Point"}
}