{
  "type": "Feature",
  "properties": {
    "addr:full":"2046 14th Ave Vero Beach FL 32960",
    "addr:housenumber":"2046",
    "addr:postcode":"32960",
    "addr:street":"14Th Ave",
    "iso:country":"US",
    "sg:address":"2046 14th Ave",
    "sg:city":"Vero Beach",
    "sg:classifiers":[
        {
            "category":"Personal",
            "type":"Services"
        }
    ],
    "sg:phone":"+1 772 562 6512",
    "sg:postcode":"32960",
    "sg:province":"FL",
    "sg:tags":[
        "credit",
        "debt",
        "counseling"
    ],
    "wof:name":"Consumer Credit Counseling Svc",
    "wof:placetype":"venue"
},
  "geometry": {"coordinates":[-80.399272,27.639212],"type":"Point"}
}