{
  "type": "Feature",
  "properties": {
    "addr:full":"2469 SE Grand Dr Port Saint Lucie FL 34952",
    "addr:housenumber":"2469",
    "addr:postcode":"34952",
    "addr:street":"Se Grand Dr",
    "iso:country":"US",
    "sg:address":"2469 SE Grand Dr",
    "sg:city":"Port Saint Lucie",
    "sg:classifiers":[
        {
            "category":"Building & Trades",
            "subcategory":"Landscaping Services",
            "type":"Services"
        }
    ],
    "sg:phone":"+1 772 398 0093",
    "sg:postcode":"34952",
    "sg:province":"FL",
    "wof:name":"St Lucy Lawn Service",
    "wof:placetype":"venue"
},
  "geometry": {"coordinates":[-80.27295700000001,27.289258],"type":"Point"}
}