{
  "type": "Feature",
  "properties": {
    "iso:country":"US",
    "sg:address":"15616 Front Beach Rd",
    "sg:city":"Panama City Bch",
    "sg:classifiers":[
        {
            "category":"Manufacturing",
            "subcategory":"Apparel",
            "type":"Manufacturing & Wholesale Goods"
        }
    ],
    "sg:phone":"+1 850 234 7522",
    "sg:postcode":"32413",
    "sg:province":"FL",
    "sg:website":"www.lizandjane.com",
    "wof:name":"Liz & Jane Clothes",
    "wof:placetype":"venue"
},
  "geometry": {"coordinates":[-85.88515099999999,30.220238],"type":"Point"}
}