{
  "type": "Feature",
  "properties": {
    "iso:country":"US",
    "sg:address":"5621 NE 22nd Ave",
    "sg:city":"Fort Lauderdale",
    "sg:classifiers":[
        {
            "category":"Building & Trades",
            "subcategory":"Plumbing",
            "type":"Services"
        }
    ],
    "sg:phone":"+1 954 771 1002",
    "sg:postcode":"33308",
    "sg:province":"FL",
    "sg:tags":[
        "conditioning",
        "air",
        "system",
        "contractor"
    ],
    "wof:name":"Suntech Air Conditioning Inc",
    "wof:placetype":"venue"
},
  "geometry": {"coordinates":[-80.113834,26.197031],"type":"Point"}
}