{
  "type": "Feature",
  "properties": {
    "iso:country":"US",
    "sg:address":"21333 NW 2nd Ave",
    "sg:city":"Miami",
    "sg:classifiers":[
        {
            "category":"Shopping",
            "subcategory":"Clothing, Apparel, & Fashions",
            "type":"Retail Goods"
        }
    ],
    "sg:phone":"+1 305 249 8331",
    "sg:postcode":"33169",
    "sg:province":"FL",
    "sg:tags":[
        "sale",
        "rental",
        "wear",
        "formal"
    ],
    "wof:name":"Goodfellas",
    "wof:placetype":"venue"
},
  "geometry": {"coordinates":[-80.20604400000001,25.972492],"type":"Point"}
}