{
  "type": "Feature",
  "properties": {
    "iso:country":"US",
    "sg:address":"1015 S Main St",
    "sg:city":"Gainesville",
    "sg:classifiers":[
        {
            "category":"Wholesale",
            "subcategory":"Auto Parts",
            "type":"Manufacturing & Wholesale Goods"
        }
    ],
    "sg:phone":"+1 352 371 4130",
    "sg:postcode":"32601",
    "sg:province":"FL",
    "sg:tags":[
        "automobile"
    ],
    "wof:name":"Perfect Fit Mfg USA",
    "wof:placetype":"venue"
},
  "geometry": {"coordinates":[-82.32565700000001,29.641988],"type":"Point"}
}