{
  "type": "Feature",
  "properties": {
    "iso:country":"US",
    "sg:address":"11245 Causeway Blvd",
    "sg:city":"Brandon",
    "sg:classifiers":[
        {
            "category":"Shopping",
            "type":"Retail Goods"
        }
    ],
    "sg:phone":"+1 813 651 2751",
    "sg:postcode":"33511",
    "sg:province":"FL",
    "sg:tags":[
        "pet",
        "shop",
        "merchandise"
    ],
    "wof:name":"Pet Supermarket Inc",
    "wof:placetype":"venue"
},
  "geometry": {"coordinates":[-82.32544900000001,27.923058],"type":"Point"}
}