{
  "type": "Feature",
  "properties": {
    "addr:full":"7422 Edgewood Boys Ranch Rd Groveland FL 34736",
    "addr:housenumber":"7422",
    "addr:postcode":"34736",
    "addr:street":"Edgewood Boys Ranch Rd",
    "iso:country":"US",
    "sg:address":"7422 Edgewood Boys Ranch Rd",
    "sg:city":"Groveland",
    "sg:classifiers":[
        {
            "category":"Freight",
            "type":"Transportation"
        }
    ],
    "sg:phone":"+1 352 429 8171",
    "sg:postcode":"34736",
    "sg:province":"FL",
    "sg:tags":[
        "operator",
        "local",
        "trucking"
    ],
    "wof:name":"McClellan Trucking Company",
    "wof:placetype":"venue"
},
  "geometry": {"coordinates":[-81.834498,28.499486],"type":"Point"}
}