{
  "type": "Feature",
  "properties": {
    "iso:country":"US",
    "sg:address":"2231 NE 35th St",
    "sg:city":"Pompano Beach",
    "sg:classifiers":[
        {
            "category":"Professional",
            "subcategory":"Management & Consulting",
            "type":"Services"
        }
    ],
    "sg:phone":"+1 954 781 2459",
    "sg:postcode":"33064",
    "sg:province":"FL",
    "sg:tags":[
        "business"
    ],
    "wof:name":"Gary Johnston Mar Consulting",
    "wof:placetype":"venue"
},
  "geometry": {"coordinates":[-80.09366199999999,26.274343],"type":"Point"}
}