{
  "type": "Feature",
  "properties": {
    "iso:country":"US",
    "sg:address":"1000 Pine Ct",
    "sg:city":"Altamonte Springs",
    "sg:classifiers":[
        {
            "category":"Shopping",
            "subcategory":"Clothing, Apparel, & Fashions",
            "type":"Retail Goods"
        }
    ],
    "sg:phone":"+1 407 682 2693",
    "sg:postcode":"32714",
    "sg:province":"FL",
    "sg:tags":[
        "beachwear",
        "accessory"
    ],
    "wof:name":"Boardwalk Surf & Sport",
    "wof:placetype":"venue"
},
  "geometry": {"coordinates":[-81.412784,28.65306],"type":"Point"}
}