{
  "type": "Feature",
  "properties": {
    "iso:country":"US",
    "sg:address":"55 Rogers St",
    "sg:city":"Clearwater",
    "sg:classifiers":[
        {
            "category":"Banks & Credit Unions",
            "subcategory":"Investment Brokerage",
            "type":"Services"
        }
    ],
    "sg:phone":"+1 727 442 4030",
    "sg:postcode":"33756",
    "sg:province":"FL",
    "sg:tags":[
        "advisory"
    ],
    "wof:name":"Saber Financial Services Inc",
    "wof:placetype":"venue"
},
  "geometry": {"coordinates":[-82.803983,27.960425],"type":"Point"}
}