{
  "type": "Feature",
  "properties": {
    "iso:country":"US",
    "sg:address":"5970 20th St",
    "sg:city":"Vero Beach",
    "sg:classifiers":[
        {
            "category":"Restaurant",
            "type":"Food & Drink"
        }
    ],
    "sg:menulink":"http://www.allmenus.com/fl/vero-beach/38585-big-apple-pizza/menu/",
    "sg:phone":"+1 772 569 8900",
    "sg:postcode":"32966",
    "sg:province":"FL",
    "sg:tags":[
        "american",
        "pizza"
    ],
    "wof:name":"Big Apple Pizza",
    "wof:placetype":"venue"
},
  "geometry": {"coordinates":[-80.45016099999999,27.639084],"type":"Point"}
}