{
  "type": "Feature",
  "properties": {
    "iso:country":"US",
    "sg:address":"3355 E Gulf To Lake Hwy",
    "sg:city":"Inverness",
    "sg:classifiers":[
        {
            "category":"Personal",
            "subcategory":"Beauty Salon",
            "type":"Services"
        }
    ],
    "sg:phone":"+1 352 344 2838",
    "sg:postcode":"34453",
    "sg:province":"FL",
    "wof:name":"Lyons Mane",
    "wof:placetype":"venue"
},
  "geometry": {"coordinates":[-82.37853,28.850794],"type":"Point"}
}