{
  "type": "Feature",
  "properties": {
    "iso:country":"US",
    "sg:address":"602 Lantana Rd",
    "sg:city":"Lantana",
    "sg:classifiers":[
        {
            "category":"Real Estate",
            "subcategory":"Real Estate Services",
            "type":"Services"
        },
        {
            "category":"Real Estate",
            "subcategory":"Real Estate Agent",
            "type":"Services"
        }
    ],
    "sg:phone":"+1 561 533 8999",
    "sg:postcode":"33462",
    "sg:province":"FL",
    "sg:tags":[
        "buyer",
        "broker"
    ],
    "wof:name":"Real Estate Solutions Network",
    "wof:placetype":"venue"
},
  "geometry": {"coordinates":[-80.070432,26.587247],"type":"Point"}
}