{
  "type": "Feature",
  "properties": {
    "iso:country":"US",
    "sg:address":"2316 Mountain Spruce St",
    "sg:city":"Ocoee",
    "sg:classifiers":[
        {
            "category":"Professional",
            "subcategory":"Business Services",
            "type":"Services"
        }
    ],
    "sg:phone":"+1 407 905 9840",
    "sg:postcode":"34761",
    "sg:province":"FL",
    "wof:name":"Klassic Express",
    "wof:placetype":"venue"
},
  "geometry": {"coordinates":[-81.51494700000001,28.603485],"type":"Point"}
}