{
  "type": "Feature",
  "properties": {
    "addr:full":"748 Lagoon Dr North Palm Beach FL 33408",
    "addr:housenumber":"748",
    "addr:postcode":"33408",
    "addr:street":"Lagoon Dr North",
    "iso:country":"US",
    "sg:address":"748 Lagoon Dr",
    "sg:city":"North Palm Beach",
    "sg:classifiers":[
        {
            "category":"Real Estate",
            "subcategory":"Real Estate Agent",
            "type":"Services"
        }
    ],
    "sg:phone":"+1 561 627 2018",
    "sg:postcode":"33408",
    "sg:province":"FL",
    "wof:name":"McIntosh Realty Inc",
    "wof:placetype":"venue"
},
  "geometry": {"coordinates":[-80.070532,26.81916],"type":"Point"}
}