{
  "type": "Feature",
  "properties": {
    "iso:country":"US",
    "sg:address":"101 Channel Dr",
    "sg:city":"Lake Mary",
    "sg:classifiers":[
        {
            "category":"Retail",
            "subcategory":"Portrait Studio",
            "type":"Services"
        }
    ],
    "sg:phone":"+1 407 322 6076",
    "sg:postcode":"32746",
    "sg:province":"FL",
    "sg:tags":[
        "photographer"
    ],
    "wof:name":"Doug Forner Photographer",
    "wof:placetype":"venue"
},
  "geometry": {"coordinates":[-81.32594400000001,28.768179],"type":"Point"}
}