{
  "type": "Feature",
  "properties": {
    "iso:country":"US",
    "sg:address":"6011 Benjamin Rd",
    "sg:city":"Tampa",
    "sg:classifiers":[
        {
            "category":"Wholesale",
            "subcategory":"Groceries",
            "type":"Manufacturing & Wholesale Goods"
        }
    ],
    "sg:phone":"+1 813 282 3603",
    "sg:postcode":"33634",
    "sg:province":"FL",
    "sg:tags":[
        "manufacture",
        "m",
        "product",
        "nutritional",
        "also"
    ],
    "wof:name":"Systems Go International Corp",
    "wof:placetype":"venue"
},
  "geometry": {"coordinates":[-82.54195300000001,28.002763],"type":"Point"}
}