{
  "type": "Feature",
  "properties": {
    "addr:full":"7953 NW 21st St Miami FL 33122",
    "addr:housenumber":"7953",
    "addr:postcode":"33122",
    "addr:street":"Nw 21St St",
    "iso:country":"US",
    "sg:address":"7953 NW 21st St",
    "sg:city":"Miami",
    "sg:classifiers":[
        {
            "category":"Professional",
            "subcategory":"Business Services",
            "type":"Services"
        }
    ],
    "sg:phone":"+1 305 477 1828",
    "sg:postcode":"33122",
    "sg:province":"FL",
    "sg:tags":[
        "courier"
    ],
    "wof:name":"M & M International Courier",
    "wof:placetype":"venue"
},
  "geometry": {"coordinates":[-80.328501,25.793491],"type":"Point"}
}