{
  "type": "Feature",
  "properties": {
    "addr:full":"7650 N University Dr Fort Lauderdale FL 33321",
    "addr:housenumber":"7650",
    "addr:postcode":"33321",
    "addr:street":"N University Dr",
    "iso:country":"US",
    "sg:address":"7650 N University Dr",
    "sg:city":"Fort Lauderdale",
    "sg:classifiers":[
        {
            "category":"Real Estate",
            "subcategory":"Real Estate Operator",
            "type":"Services"
        }
    ],
    "sg:phone":"+1 954 722 6314",
    "sg:postcode":"33321",
    "sg:province":"FL",
    "sg:tags":[
        "retirement",
        "community"
    ],
    "wof:name":"Merrill Gardens & Tamarac",
    "wof:placetype":"venue"
},
  "geometry": {"coordinates":[-80.252411,26.216064],"type":"Point"}
}