{
  "type": "Feature",
  "properties": {
    "addr:full":"610 Jasmine Rd Altamonte Springs FL 32707",
    "addr:housenumber":"610",
    "addr:postcode":"32707",
    "addr:street":"Jasmine Rd",
    "iso:country":"US",
    "sg:address":"610 Jasmine Rd",
    "sg:city":"Altamonte Springs",
    "sg:classifiers":[
        {
            "category":"Personal",
            "subcategory":"Massage",
            "type":"Services"
        }
    ],
    "sg:phone":"+1 407 774 0844",
    "sg:postcode":"32707",
    "sg:province":"FL",
    "wof:name":"Comprehensive Muscular Therapy",
    "wof:placetype":"venue"
},
  "geometry": {"coordinates":[-81.322326,28.653988],"type":"Point"}
}