{
  "type": "Feature",
  "properties": {
    "addr:full":"4852 SW Hammock Creek Dr Palm City FL 34990",
    "addr:housenumber":"4852",
    "addr:postcode":"34990",
    "addr:street":"Sw Hammock Creek Dr",
    "iso:country":"US",
    "sg:address":"4852 SW Hammock Creek Dr",
    "sg:city":"Palm City",
    "sg:classifiers":[
        {
            "category":"Professional",
            "type":"Services"
        }
    ],
    "sg:phone":"+1 772 781 5605",
    "sg:postcode":"34990",
    "sg:province":"FL",
    "sg:tags":[
        "establishment"
    ],
    "wof:name":"Sanctuary At Hammock Creek",
    "wof:placetype":"venue"
},
  "geometry": {"coordinates":[-80.293729,27.148439],"type":"Point"}
}