{
  "type": "Feature",
  "properties": {
    "iso:country":"US",
    "sg:address":"450 Magnolia Ave",
    "sg:city":"Panama City",
    "sg:classifiers":[
        {
            "category":"Professional",
            "subcategory":"Credit Reporting & Collection",
            "type":"Services"
        }
    ],
    "sg:phone":"+1 850 785 0281",
    "sg:postcode":"32401",
    "sg:province":"FL",
    "sg:tags":[
        "agency"
    ],
    "wof:name":"Credit Bureau-Panama City LTD",
    "wof:placetype":"venue"
},
  "geometry": {"coordinates":[-85.658919,30.155638],"type":"Point"}
}