{
  "type": "Feature",
  "properties": {
    "addr:full":"5366 Gulf Dr Holmes Beach FL 34217",
    "addr:housenumber":"5366",
    "addr:postcode":"34217",
    "addr:street":"Gulf Dr",
    "iso:country":"US",
    "sg:address":"5366 Gulf Dr",
    "sg:city":"Holmes Beach",
    "sg:classifiers":[
        {
            "category":"Sports & Exercise",
            "subcategory":"Gym",
            "type":"Entertainment"
        }
    ],
    "sg:phone":"+1 941 779 2878",
    "sg:postcode":"34217",
    "sg:province":"FL",
    "sg:tags":[
        "club",
        "health",
        "studio",
        "gymnasium"
    ],
    "wof:name":"Curves For Women",
    "wof:placetype":"venue"
},
  "geometry": {"coordinates":[-82.71588199999999,27.505765],"type":"Point"}
}