{
  "type": "Feature",
  "properties": {
    "iso:country":"US",
    "sg:address":"4140 Flagler Estates Blvd",
    "sg:city":"Hastings",
    "sg:classifiers":[
        {
            "category":"Banks & Credit Unions",
            "subcategory":"Financial Services",
            "type":"Services"
        }
    ],
    "sg:phone":"+1 904 692 4501",
    "sg:postcode":"32145",
    "sg:province":"FL",
    "sg:tags":[
        "investment",
        "real estate"
    ],
    "wof:name":"Caldwell Property Group LLC",
    "wof:placetype":"venue"
},
  "geometry": {"coordinates":[-81.43124400000001,29.664275],"type":"Point"}
}