{
  "type": "Feature",
  "properties": {
    "iso:country":"US",
    "sg:address":"4420 Old Dixie Hwy",
    "sg:city":"Vero Beach",
    "sg:classifiers":[
        {
            "category":"Wholesale",
            "subcategory":"Durable Goods & Equipment",
            "type":"Manufacturing & Wholesale Goods"
        }
    ],
    "sg:phone":"+1 772 567 5353",
    "sg:postcode":"32967",
    "sg:province":"FL",
    "sg:tags":[
        "exporter"
    ],
    "wof:name":"Harbor Island Citrus Inc",
    "wof:placetype":"venue"
},
  "geometry": {"coordinates":[-80.408781,27.673544],"type":"Point"}
}