{
  "type": "Feature",
  "properties": {
    "iso:country":"US",
    "sg:address":"2215 Garden St",
    "sg:city":"Titusville",
    "sg:classifiers":[
        {
            "category":"Wholesale",
            "subcategory":"Toys & Hobbies",
            "type":"Manufacturing & Wholesale Goods"
        }
    ],
    "sg:phone":"+1 321 269 2775",
    "sg:postcode":"32796",
    "sg:province":"FL",
    "wof:name":"Tutti Bambini Inc",
    "wof:placetype":"venue"
},
  "geometry": {"coordinates":[-80.831751,28.615296],"type":"Point"}
}