{
  "type": "Feature",
  "properties": {
    "iso:country":"US",
    "sg:address":"2472 NW 50th Ave",
    "sg:city":"Okeechobee",
    "sg:classifiers":[
        {
            "category":"Wholesale",
            "subcategory":"Chemicals & Plastics",
            "type":"Manufacturing & Wholesale Goods"
        }
    ],
    "sg:phone":"+1 863 467 8338",
    "sg:postcode":"34972",
    "sg:province":"FL",
    "sg:tags":[
        "cleaning",
        "compound"
    ],
    "wof:name":"Pioneer Cleaning Products",
    "wof:placetype":"venue"
},
  "geometry": {"coordinates":[-80.88088999999999,27.265721],"type":"Point"}
}