{
  "type": "Feature",
  "properties": {
    "iso:country":"US",
    "sg:address":"2334 Ruth Ln",
    "sg:city":"Kissimmee",
    "sg:classifiers":[
        {
            "category":"Building & Trades",
            "subcategory":"Construction",
            "type":"Services"
        }
    ],
    "sg:phone":"+1 407 460 7180",
    "sg:postcode":"34744",
    "sg:province":"FL",
    "sg:tags":[
        "house"
    ],
    "wof:name":"Franks Home Improvement",
    "wof:placetype":"venue"
},
  "geometry": {"coordinates":[-81.333467,28.317138],"type":"Point"}
}