{
  "type": "Feature",
  "properties": {
    "iso:country":"US",
    "sg:address":"13180 Cleveland Ave",
    "sg:city":"Fort Myers",
    "sg:classifiers":[
        {
            "category":"Professional",
            "subcategory":"Employment Agencies",
            "type":"Services"
        }
    ],
    "sg:phone":"+1 239 997 0030",
    "sg:postcode":"33903",
    "sg:province":"FL",
    "sg:tags":[
        "opportunity"
    ],
    "wof:name":"Bay Personnel",
    "wof:placetype":"venue"
},
  "geometry": {"coordinates":[-81.88657499999999,26.663641],"type":"Point"}
}