{
  "type": "Feature",
  "properties": {
    "iso:country":"US",
    "sg:address":"2422 Island Club Way",
    "sg:city":"Orlando",
    "sg:classifiers":[
        {
            "category":"Building & Trades",
            "subcategory":"Construction",
            "type":"Services"
        }
    ],
    "sg:phone":"+1 407 249 3006",
    "sg:postcode":"32822",
    "sg:province":"FL",
    "sg:tags":[
        "residential"
    ],
    "wof:name":"G & S Enterprise",
    "wof:placetype":"venue"
},
  "geometry": {"coordinates":[-81.280456,28.515318],"type":"Point"}
}