{
  "type": "Feature",
  "properties": {
    "iso:country":"US",
    "sg:address":"2810 Enterprise Rd",
    "sg:city":"Debary",
    "sg:classifiers":[
        {
            "category":"Health Services",
            "subcategory":"Nursing And Care Facility",
            "type":"Services"
        }
    ],
    "sg:phone":"+1 386 668 8818",
    "sg:postcode":"32713",
    "sg:province":"FL",
    "sg:tags":[
        "personal",
        "home",
        "skilled",
        "convalescent"
    ],
    "wof:name":"Mariner Health of Orange City",
    "wof:placetype":"venue"
},
  "geometry": {"coordinates":[-81.287874,28.903515],"type":"Point"}
}