{
  "type": "Feature",
  "properties": {
    "iso:country":"US",
    "sg:address":"921 Carissa Ln",
    "sg:city":"Oviedo",
    "sg:classifiers":[
        {
            "category":"Professional",
            "subcategory":"Computer Services",
            "type":"Services"
        }
    ],
    "sg:phone":"+1 407 365 8947",
    "sg:postcode":"32765",
    "sg:province":"FL",
    "wof:name":"United Engineering Services",
    "wof:placetype":"venue"
},
  "geometry": {"coordinates":[-81.19568099999999,28.684289],"type":"Point"}
}