{
  "type": "Feature",
  "properties": {
    "addr:full":"17660 NW 37th Ave Opa Locka FL 33056",
    "addr:housenumber":"17660",
    "addr:postcode":"33056",
    "addr:street":"Nw 37Th Ave;Locka",
    "iso:country":"US",
    "sg:address":"17660 NW 37th Ave",
    "sg:city":"Opa Locka",
    "sg:classifiers":[
        {
            "category":"Shopping",
            "subcategory":"Florist",
            "type":"Retail Goods"
        }
    ],
    "sg:phone":"+1 305 628 2733",
    "sg:postcode":"33056",
    "sg:province":"FL",
    "wof:name":"Petals In Disguise",
    "wof:placetype":"venue"
},
  "geometry": {"coordinates":[-80.261139,25.934347],"type":"Point"}
}