{
  "type": "Feature",
  "properties": {
    "addr:full":"5 San Pablo Cir N Jacksonville Beach FL 32250",
    "addr:housenumber":"5",
    "addr:postcode":"32250",
    "addr:street":"San Pablo Cir N",
    "iso:country":"US",
    "sg:address":"5 San Pablo Cir N",
    "sg:city":"Jacksonville Beach",
    "sg:classifiers":[
        {
            "category":"Utilities",
            "subcategory":"Telephone",
            "type":"Services"
        }
    ],
    "sg:phone":"+1 904 249 0751",
    "sg:postcode":"32250",
    "sg:province":"FL",
    "sg:tags":[
        "consulting",
        "computer",
        "internet"
    ],
    "wof:name":"Net Magic of Jacksonville",
    "wof:placetype":"venue"
},
  "geometry": {"coordinates":[-81.40539,30.300308],"type":"Point"}
}