{
  "type": "Feature",
  "properties": {
    "iso:country":"US",
    "sg:address":"605 Suwannee St",
    "sg:city":"Tallahassee",
    "sg:classifiers":[
        {
            "category":"Government",
            "subcategory":"Office",
            "type":"Public Place"
        }
    ],
    "sg:phone":"+1 850 414 4370",
    "sg:postcode":"32301",
    "sg:province":"FL",
    "sg:tags":[
        "transportation"
    ],
    "wof:name":"Transprtation Pavement MGT Off",
    "wof:placetype":"venue"
},
  "geometry": {"coordinates":[-84.275668,30.43492],"type":"Point"}
}