{
  "type": "Feature",
  "properties": {
    "iso:country":"US",
    "sg:address":"7324 Kildare St",
    "sg:city":"New Port Richey",
    "sg:classifiers":[
        {
            "category":"Home & Garden",
            "subcategory":"Building Materials",
            "type":"Retail Goods"
        }
    ],
    "sg:phone":"+1 727 845 5563",
    "sg:postcode":"34653",
    "sg:province":"FL",
    "sg:tags":[
        "windows"
    ],
    "wof:name":"Keith Pinz Svcs",
    "wof:placetype":"venue"
},
  "geometry": {"coordinates":[-82.708613,28.263867],"type":"Point"}
}