{
  "type": "Feature",
  "properties": {
    "iso:country":"US",
    "sg:address":"5845 W Tennessee St",
    "sg:city":"Tallahassee",
    "sg:classifiers":[
        {
            "category":"Retail",
            "subcategory":"Auto Repair",
            "type":"Services"
        }
    ],
    "sg:phone":"+1 850 576 7159",
    "sg:postcode":"32304",
    "sg:province":"FL",
    "sg:tags":[
        "body",
        "automobile",
        "painting"
    ],
    "wof:name":"Walker Body Shop",
    "wof:placetype":"venue"
},
  "geometry": {"coordinates":[-84.37142799999999,30.456148],"type":"Point"}
}