{
  "type": "Feature",
  "properties": {
    "addr:full":"760 8th Ct Vero Beach FL 32962",
    "addr:housenumber":"760",
    "addr:postcode":"32962",
    "addr:street":"8Th Ct",
    "iso:country":"US",
    "sg:address":"760 8th Ct",
    "sg:city":"Vero Beach",
    "sg:classifiers":[
        {
            "category":"Food & Beverages",
            "subcategory":"Bakery",
            "type":"Retail Goods"
        }
    ],
    "sg:phone":"+1 772 569 6669",
    "sg:postcode":"32962",
    "sg:province":"FL",
    "sg:tags":[
        "baker"
    ],
    "wof:name":"Artistic Confections & Cake",
    "wof:placetype":"venue"
},
  "geometry": {"coordinates":[-80.389653,27.615277],"type":"Point"}
}