{
  "type": "Feature",
  "properties": {
    "iso:country":"US",
    "sg:address":"555 Dog Track Rd",
    "sg:city":"Longwood",
    "sg:classifiers":[
        {
            "category":"Manufacturing",
            "subcategory":"Rubber & Plastics",
            "type":"Manufacturing & Wholesale Goods"
        }
    ],
    "sg:phone":"+1 407 834 3000",
    "sg:postcode":"32750",
    "sg:province":"FL",
    "sg:tags":[
        "sticker",
        "mfg",
        "product",
        "label"
    ],
    "wof:name":"Florida Marking Products Inc",
    "wof:placetype":"venue"
},
  "geometry": {"coordinates":[-81.33598499999999,28.68449],"type":"Point"}
}