{
  "type": "Feature",
  "properties": {
    "iso:country":"US",
    "sg:address":"2570 S US Highway 17/92",
    "sg:city":"Casselberry",
    "sg:classifiers":[
        {
            "category":"Home & Garden",
            "subcategory":"Furniture",
            "type":"Retail Goods"
        }
    ],
    "sg:phone":"+1 407 834 1477",
    "sg:postcode":"32707",
    "sg:province":"FL",
    "sg:tags":[
        "store"
    ],
    "sg:website":"www.leadersfurniture.com",
    "wof:name":"Leader's Casual Furniture",
    "wof:placetype":"venue"
},
  "geometry": {"coordinates":[-81.33448199999999,28.682412],"type":"Point"}
}