{
  "type": "Feature",
  "properties": {
    "addr:full":"2707 Sadler Rd Fernandina Beach FL 32034",
    "addr:housenumber":"2707",
    "addr:postcode":"32034",
    "addr:street":"Sadler Rd",
    "iso:country":"US",
    "sg:address":"2707 Sadler Rd",
    "sg:city":"Fernandina Beach",
    "sg:classifiers":[
        {
            "category":"Travel",
            "subcategory":"Hotels & Motels",
            "type":"Entertainment"
        }
    ],
    "sg:phone":"+1 904 277 2300",
    "sg:postcode":"32034",
    "sg:province":"FL",
    "sg:website":"www.theinnatfernandinabeach.com",
    "wof:name":"Best Western Inn",
    "wof:placetype":"venue"
},
  "geometry": {"coordinates":[-81.43808300000001,30.638814],"type":"Point"}
}