{
  "type": "Feature",
  "properties": {
    "iso:country":"US",
    "sg:address":"5600 Greenwood Ave",
    "sg:city":"West Palm Beach",
    "sg:classifiers":[
        {
            "category":"Retail",
            "subcategory":"Auto Repair",
            "type":"Services"
        }
    ],
    "sg:phone":"+1 561 840 1915",
    "sg:postcode":"33407",
    "sg:province":"FL",
    "sg:tags":[
        "body",
        "automobile",
        "painting"
    ],
    "wof:name":"Tony's Body Shop",
    "wof:placetype":"venue"
},
  "geometry": {"coordinates":[-80.060086,26.760199],"type":"Point"}
}