{
  "type": "Feature",
  "properties": {
    "iso:country":"US",
    "sg:address":"614 S Howard Ave",
    "sg:city":"Tampa",
    "sg:classifiers":[
        {
            "category":"Personal",
            "subcategory":"Shoe Repair & Shine",
            "type":"Services"
        }
    ],
    "sg:phone":"+1 813 253 2690",
    "sg:postcode":"33606",
    "sg:province":"FL",
    "sg:tags":[
        "repairing",
        "equipment",
        "parlor",
        "industrial",
        "boot"
    ],
    "wof:name":"Shoe Masters Shoe Repair",
    "wof:placetype":"venue"
},
  "geometry": {"coordinates":[-82.482944,27.937547],"type":"Point"}
}