{
  "type": "Feature",
  "properties": {
    "addr:full":"2117 NW 42nd Pl Cape Coral FL 33993",
    "addr:housenumber":"2117",
    "addr:postcode":"33993",
    "addr:street":"Nw 42Nd Pl",
    "iso:country":"US",
    "sg:address":"2117 NW 42nd Pl",
    "sg:city":"Cape Coral",
    "sg:classifiers":[
        {
            "category":"Professional",
            "subcategory":"Business Services",
            "type":"Services"
        }
    ],
    "sg:phone":"+1 239 458 7595",
    "sg:postcode":"33993",
    "sg:province":"FL",
    "wof:name":"North Cape Exhausted Auto",
    "wof:placetype":"venue"
},
  "geometry": {"coordinates":[-82.060153,26.693264],"type":"Point"}
}