{
  "type": "Feature",
  "properties": {
    "addr:full":"577 Burlington St Opa Locka FL 33054",
    "addr:housenumber":"577",
    "addr:postcode":"33054",
    "addr:street":"Burlington St;Locka",
    "iso:country":"US",
    "sg:address":"577 Burlington St",
    "sg:city":"Opa Locka",
    "sg:classifiers":[
        {
            "category":"Wholesale",
            "subcategory":"Machinery & Supplies",
            "type":"Manufacturing & Wholesale Goods"
        }
    ],
    "sg:phone":"+1 305 685 6261",
    "sg:postcode":"33054",
    "sg:province":"FL",
    "sg:tags":[
        "food",
        "industry"
    ],
    "wof:name":"Mann-Holly Sales & Service",
    "wof:placetype":"venue"
},
  "geometry": {"coordinates":[-80.254841,25.898441],"type":"Point"}
}