{
  "type": "Feature",
  "properties": {
    "addr:full":"8320 Sherman Cir N Miramar FL 33025",
    "addr:housenumber":"8320",
    "addr:postcode":"33025",
    "addr:street":"Sherman Cir N",
    "iso:country":"US",
    "sg:address":"8320 Sherman Cir N",
    "sg:city":"Miramar",
    "sg:classifiers":[
        {
            "category":"Personal",
            "type":"Services"
        }
    ],
    "sg:phone":"+1 954 441 3581",
    "sg:postcode":"33025",
    "sg:province":"FL",
    "sg:tags":[
        "miscellaneous"
    ],
    "wof:name":"Elite Concierge Svc",
    "wof:placetype":"venue"
},
  "geometry": {"coordinates":[-80.25268,25.9929],"type":"Point"}
}