{
  "type": "Feature",
  "properties": {
    "addr:full":"310 Saint Andrews Dr Niceville FL 32578",
    "addr:housenumber":"310",
    "addr:postcode":"32578",
    "addr:street":"Saint Andrews Dr",
    "iso:country":"US",
    "sg:address":"310 Saint Andrews Dr",
    "sg:city":"Niceville",
    "sg:classifiers":[
        {
            "category":"Building & Trades",
            "subcategory":"Construction",
            "type":"Services"
        }
    ],
    "sg:phone":"+1 850 830 7093",
    "sg:postcode":"32578",
    "sg:province":"FL",
    "sg:tags":[
        "wallcoverings-installation",
        "wallpaper",
        "painting",
        "contractor"
    ],
    "wof:name":"Slick Finish Painting & Drywall",
    "wof:placetype":"venue"
},
  "geometry": {"coordinates":[-86.471588,30.499491],"type":"Point"}
}