{
  "type": "Feature",
  "properties": {
    "iso:country":"US",
    "sg:address":"11273 NW 5th Ter",
    "sg:city":"Miami",
    "sg:classifiers":[
        {
            "category":"Shopping",
            "subcategory":"Hobbies, Toys, & Games",
            "type":"Retail Goods"
        },
        {
            "category":"Shopping",
            "subcategory":"Crafts & Fabrics",
            "type":"Retail Goods"
        }
    ],
    "sg:phone":"+1 305 559 5692",
    "sg:postcode":"33172",
    "sg:province":"FL",
    "sg:tags":[
        "shop",
        "model",
        "hobby",
        "supply"
    ],
    "wof:name":"Daysi S Arts Crafts",
    "wof:placetype":"venue"
},
  "geometry": {"coordinates":[-80.381236,25.77393],"type":"Point"}
}