{
  "type": "Feature",
  "properties": {
    "addr:full":"4100 Evans Ave Fort Myers FL 33901",
    "addr:housenumber":"4100",
    "addr:postcode":"33901",
    "addr:street":"Evans Ave",
    "iso:country":"US",
    "sg:address":"4100 Evans Ave",
    "sg:city":"Fort Myers",
    "sg:classifiers":[
        {
            "category":"Banks & Credit Unions",
            "subcategory":"Bank",
            "type":"Services"
        }
    ],
    "sg:phone":"+1 239 693 9001",
    "sg:postcode":"33901",
    "sg:province":"FL",
    "sg:tags":[
        "loan",
        "real estate"
    ],
    "wof:name":"Family First Mortgage Corp",
    "wof:placetype":"venue"
},
  "geometry": {"coordinates":[-81.85959699999999,26.601429],"type":"Point"}
}