{
  "type": "Feature",
  "properties": {
    "addr:full":"6837 SW 39th Ter Miami FL 33155",
    "addr:housenumber":"6837",
    "addr:postcode":"33155",
    "addr:street":"Sw 39Th Ter",
    "iso:country":"US",
    "sg:address":"6837 SW 39th Ter",
    "sg:city":"Miami",
    "sg:classifiers":[
        {
            "category":"Professional",
            "type":"Services"
        }
    ],
    "sg:phone":"+1 305 385 9050",
    "sg:postcode":"33155",
    "sg:province":"FL",
    "wof:name":"Home Professional Intl",
    "wof:placetype":"venue"
},
  "geometry": {"coordinates":[-80.306147,25.734192],"type":"Point"}
}