{
  "type": "Feature",
  "properties": {
    "addr:full":"1948 Lawson Rd Tallahassee FL 32308",
    "addr:housenumber":"1948",
    "addr:postcode":"32308",
    "addr:street":"Lawson Rd",
    "iso:country":"US",
    "sg:address":"1948 Lawson Rd",
    "sg:city":"Tallahassee",
    "sg:classifiers":[
        {
            "category":"Real Estate",
            "subcategory":"Real Estate Agent",
            "type":"Services"
        }
    ],
    "sg:phone":"+1 850 878 1321",
    "sg:postcode":"32308",
    "sg:province":"FL",
    "wof:name":"Jerry Frances Patton",
    "wof:placetype":"venue"
},
  "geometry": {"coordinates":[-84.24184200000001,30.471097],"type":"Point"}
}