{
  "type": "Feature",
  "properties": {
    "iso:country":"US",
    "sg:address":"10831 Em en el Grove Rd",
    "sg:city":"Leesburg",
    "sg:classifiers":[
        {
            "category":"Mining & Drilling",
            "type":"Manufacturing & Wholesale Goods"
        }
    ],
    "sg:phone":"+1 352 250 9584",
    "sg:postcode":"34788",
    "sg:province":"FL",
    "sg:tags":[
        "woodwork",
        "repair"
    ],
    "wof:name":"Woodwork and Repair",
    "wof:placetype":"venue"
},
  "geometry": {"coordinates":[-81.77217,28.950368],"type":"Point"}
}