{
  "type": "Feature",
  "properties": {
    "iso:country":"US",
    "sg:address":"8317 NW 68th St",
    "sg:city":"Miami",
    "sg:classifiers":[
        {
            "category":"Building & Trades",
            "subcategory":"Cleaning & Sanitation",
            "type":"Services"
        }
    ],
    "sg:phone":"+1 305 716 0920",
    "sg:postcode":"33166",
    "sg:province":"FL",
    "sg:tags":[
        "maintenance"
    ],
    "wof:name":"Aetna Maintenance Inc",
    "wof:placetype":"venue"
},
  "geometry": {"coordinates":[-80.331945,25.835345],"type":"Point"}
}