{
  "type": "Feature",
  "properties": {
    "addr:full":"151 Chiappini Farm Rd Hawthorne FL 32640",
    "addr:housenumber":"151",
    "addr:postcode":"32640",
    "addr:street":"Chiappini Farm Rd",
    "iso:country":"US",
    "sg:address":"151 Chiappini Farm Rd",
    "sg:city":"Hawthorne",
    "sg:classifiers":[
        {
            "category":"Farming",
            "subcategory":"Farm",
            "type":"Manufacturing & Wholesale Goods"
        }
    ],
    "sg:phone":"+1 352 475 2019",
    "sg:postcode":"32640",
    "sg:province":"FL",
    "wof:name":"Prarie Oaks Farm LLC",
    "wof:placetype":"venue"
},
  "geometry": {"coordinates":[-82.018888,29.657833],"type":"Point"}
}