{
  "type": "Feature",
  "properties": {
    "iso:country":"US",
    "sg:address":"1815 Patterson Ave",
    "sg:city":"Deland",
    "sg:classifiers":[
        {
            "category":"Recreation",
            "subcategory":"Marina",
            "type":"Entertainment"
        }
    ],
    "sg:phone":"+1 386 738 3568",
    "sg:postcode":"32724",
    "sg:province":"FL",
    "sg:tags":[
        "repairing",
        "boat"
    ],
    "wof:name":"Boat Hospital",
    "wof:placetype":"venue"
},
  "geometry": {"coordinates":[-81.29864499999999,29.058891],"type":"Point"}
}