{
  "type": "Feature",
  "properties": {
    "iso:country":"US",
    "sg:address":"73 Evans Dr",
    "sg:city":"Jacksonville Beach",
    "sg:classifiers":[
        {
            "category":"Real Estate",
            "subcategory":"Real Estate Operator",
            "type":"Services"
        }
    ],
    "sg:phone":"+1 904 247 0475",
    "sg:postcode":"32250",
    "sg:province":"FL",
    "sg:tags":[
        "building",
        "nonresidential"
    ],
    "wof:name":"Global Property Rehab Corp",
    "wof:placetype":"venue"
},
  "geometry": {"coordinates":[-81.406741,30.27095],"type":"Point"}
}