{
  "type": "Feature",
  "properties": {
    "addr:full":"2601 SW 37th Ave Miami FL 33133",
    "addr:housenumber":"2601",
    "addr:postcode":"33133",
    "addr:street":"Sw 37Th Ave",
    "iso:country":"US",
    "sg:address":"2601 SW 37th Ave",
    "sg:city":"Miami",
    "sg:classifiers":[
        {
            "category":"Health Services",
            "subcategory":"Doctor",
            "type":"Services"
        }
    ],
    "sg:phone":"+1 305 447 4942",
    "sg:postcode":"33133",
    "sg:province":"FL",
    "wof:name":"Serrano Enrique MD",
    "wof:placetype":"venue"
},
  "geometry": {"coordinates":[-80.25428599999999,25.742983],"type":"Point"}
}