{
  "type": "Feature",
  "properties": {
    "iso:country":"US",
    "sg:address":"4887 Belfort Rd",
    "sg:city":"Jacksonville",
    "sg:classifiers":[
        {
            "category":"Airline",
            "type":"Transportation"
        }
    ],
    "sg:phone":"+1 904 245 6200",
    "sg:postcode":"32256",
    "sg:province":"FL",
    "sg:tags":[
        "scheduled",
        "air"
    ],
    "wof:name":"Flytele",
    "wof:placetype":"venue"
},
  "geometry": {"coordinates":[-81.58413,30.24785],"type":"Point"}
}