{
  "type": "Feature",
  "properties": {
    "iso:country":"US",
    "sg:address":"1399 NW 17th Ave Ste 302A",
    "sg:city":"Miami",
    "sg:classifiers":[
        {
            "category":"Retail",
            "subcategory":"Repair Shop",
            "type":"Services"
        },
        {
            "category":"Professional",
            "subcategory":"Detective & Security Services",
            "type":"Services"
        }
    ],
    "sg:phone":"+1 305 326 9141",
    "sg:postcode":"33125",
    "sg:province":"FL",
    "sg:tags":[
        "skip",
        "tracing",
        "bail",
        "bond"
    ],
    "wof:name":"Pronto Bial Bonds Inc",
    "wof:placetype":"venue"
},
  "geometry": {"coordinates":[-80.222931,25.7859],"type":"Point"}
}