{
  "type": "Feature",
  "properties": {
    "addr:full":"12664 Classic Dr Pompano Beach FL 33071",
    "addr:housenumber":"12664",
    "addr:postcode":"33071",
    "addr:street":"Classic Dr",
    "iso:country":"US",
    "sg:address":"12664 Classic Dr",
    "sg:city":"Pompano Beach",
    "sg:classifiers":[
        {
            "category":"Banks & Credit Unions",
            "subcategory":"Bank",
            "type":"Services"
        }
    ],
    "sg:phone":"+1 954 755 9291",
    "sg:postcode":"33071",
    "sg:province":"FL",
    "sg:tags":[
        "mortgage"
    ],
    "wof:name":"M K Mortgage Processing Inc",
    "wof:placetype":"venue"
},
  "geometry": {"coordinates":[-80.28398900000001,26.255685],"type":"Point"}
}