{
  "type": "Feature",
  "properties": {
    "iso:country":"US",
    "sg:address":"9400 N US Hwy 1",
    "sg:city":"Sebastian",
    "sg:classifiers":[
        {
            "category":"Wholesale",
            "subcategory":"Groceries",
            "type":"Manufacturing & Wholesale Goods"
        }
    ],
    "sg:phone":"+1 772 589 3113",
    "sg:postcode":"32958",
    "sg:province":"FL",
    "sg:tags":[
        "consulting",
        "management"
    ],
    "wof:name":"Lite Cookies Limited",
    "wof:placetype":"venue"
},
  "geometry": {"coordinates":[-80.44286200000001,27.76555],"type":"Point"}
}