{
  "type": "Feature",
  "properties": {
    "iso:country":"US",
    "sg:address":"6505 S Dale Mabry Hwy",
    "sg:city":"Tampa",
    "sg:classifiers":[
        {
            "category":"Restaurant",
            "type":"Food & Drink"
        }
    ],
    "sg:menulink":"http://www.allmenus.com/fl/tampa/187755-mcdonalds/menu/",
    "sg:phone":"+1 813 839 5252",
    "sg:postcode":"33611",
    "sg:province":"FL",
    "sg:tags":[
        "burger",
        "american"
    ],
    "wof:name":"McDonald's",
    "wof:placetype":"venue"
},
  "geometry": {"coordinates":[-82.50691500000001,27.871834],"type":"Point"}
}