{
  "type": "Feature",
  "properties": {
    "iso:country":"US",
    "sg:address":"2600 Dardanelle Dr",
    "sg:city":"Orlando",
    "sg:classifiers":[
        {
            "category":"Restaurant",
            "type":"Food & Drink"
        }
    ],
    "sg:menulink":"http://www.allmenus.com/fl/orlando/160220-burger-king/menu/",
    "sg:phone":"+1 407 578 9146",
    "sg:postcode":"32808",
    "sg:province":"FL",
    "sg:tags":[
        "burger",
        "american"
    ],
    "wof:name":"Burger King",
    "wof:placetype":"venue"
},
  "geometry": {"coordinates":[-81.43909600000001,28.578713],"type":"Point"}
}