{
  "type": "Feature",
  "properties": {
    "iso:country":"US",
    "sg:address":"1524 Sumatra Ave",
    "sg:city":"Deltona",
    "sg:classifiers":[
        {
            "category":"Professional",
            "subcategory":"Business Services",
            "type":"Services"
        }
    ],
    "sg:phone":"+1 386 789 4581",
    "sg:postcode":"32725",
    "sg:province":"FL",
    "wof:name":"Santiago Perez Business Svc",
    "wof:placetype":"venue"
},
  "geometry": {"coordinates":[-81.249711,28.906896],"type":"Point"}
}