{
  "type": "Feature",
  "properties": {
    "iso:country":"US",
    "sg:address":"1035 NE 106th St",
    "sg:city":"North Miami",
    "sg:classifiers":[
        {
            "category":"Communications",
            "subcategory":"Film & Video Production",
            "type":"Services"
        }
    ],
    "sg:phone":"+1 305 891 9508",
    "sg:postcode":"33161",
    "sg:province":"FL",
    "sg:tags":[
        "studio",
        "facility"
    ],
    "wof:name":"Ed Loz Media Group Inc",
    "wof:placetype":"venue"
},
  "geometry": {"coordinates":[-80.170596,25.872939],"type":"Point"}
}