{
  "type": "Feature",
  "properties": {
    "iso:country":"US",
    "sg:address":"14136 Wadsworth Dr",
    "sg:city":"Odessa",
    "sg:classifiers":[
        {
            "category":"Insurance",
            "subcategory":"Hazard Insurance",
            "type":"Services"
        }
    ],
    "sg:phone":"+1 813 920 3222",
    "sg:postcode":"33556",
    "sg:province":"FL",
    "sg:tags":[
        "commercial",
        "business"
    ],
    "wof:name":"Drake Insurance",
    "wof:placetype":"venue"
},
  "geometry": {"coordinates":[-82.581136,28.173305],"type":"Point"}
}