{
  "type": "Feature",
  "properties": {
    "addr:full":"1 SE 3rd Ave Ste 2130 Miami FL 33131",
    "addr:housenumber":"1",
    "addr:postcode":"33131",
    "addr:street":"Se 3Rd Ave Ste 2130",
    "iso:country":"US",
    "sg:address":"1 SE 3rd Ave Ste 2130",
    "sg:city":"Miami",
    "sg:classifiers":[
        {
            "category":"Professional",
            "subcategory":"Business Services",
            "type":"Services"
        }
    ],
    "sg:phone":"+1 305 377 4228",
    "sg:postcode":"33131",
    "sg:province":"FL",
    "sg:tags":[
        "consultant",
        "coach"
    ],
    "wof:name":"Fgh Consulting Usa Inc",
    "wof:placetype":"venue"
},
  "geometry": {"coordinates":[-80.189003,25.77426],"type":"Point"}
}