{
  "type": "Feature",
  "properties": {
    "addr:full":"11742 128th Ave N Largo FL 33778",
    "addr:housenumber":"11742",
    "addr:postcode":"33778",
    "addr:street":"128Th Ave N",
    "iso:country":"US",
    "sg:address":"11742 128th Ave N",
    "sg:city":"Largo",
    "sg:classifiers":[
        {
            "category":"Personal",
            "subcategory":"Beauty Salon",
            "type":"Services"
        }
    ],
    "sg:phone":"+1 727 584 1209",
    "sg:postcode":"33778",
    "sg:province":"FL",
    "wof:name":"Tammy's Hair & Nails",
    "wof:placetype":"venue"
},
  "geometry": {"coordinates":[-82.801526,27.889163],"type":"Point"}
}