{
  "type": "Feature",
  "properties": {
    "addr:full":"6644 NW 107th Pl Doral FL 33178",
    "addr:housenumber":"6644",
    "addr:postcode":"33178",
    "addr:street":"Nw 107Th Pl",
    "iso:country":"US",
    "sg:address":"6644 NW 107th Pl",
    "sg:city":"Doral",
    "sg:classifiers":[
        {
            "category":"Shopping",
            "subcategory":"Clothing, Apparel, & Fashions",
            "type":"Retail Goods"
        }
    ],
    "sg:phone":"+1 305 545 5755",
    "sg:postcode":"33178",
    "sg:province":"FL",
    "wof:name":"Sharon's Fashion",
    "wof:placetype":"venue"
},
  "geometry": {"coordinates":[-80.372074,25.840062],"type":"Point"}
}