{
  "type": "Feature",
  "properties": {
    "addr:full":"6314 International Dr Orlando FL 32819",
    "addr:housenumber":"6314",
    "addr:postcode":"32819",
    "addr:street":"International Dr",
    "iso:country":"US",
    "sg:address":"6314 International Dr",
    "sg:city":"Orlando",
    "sg:phone":"+1 407 351 3578",
    "sg:postcode":"32819",
    "sg:province":"FL",
    "wof:name":"Orlando George & Dragon",
    "wof:placetype":"venue"
},
  "geometry": {"coordinates":[-81.467395,28.460966],"type":"Point"}
}