{
  "type": "Feature",
  "properties": {
    "iso:country":"US",
    "sg:address":"3079 Landmark Blvd",
    "sg:city":"Palm Harbor",
    "sg:classifiers":[
        {
            "category":"Professional",
            "subcategory":"Management & Consulting",
            "type":"Services"
        }
    ],
    "sg:phone":"+1 727 781 2226",
    "sg:postcode":"34684",
    "sg:province":"FL",
    "sg:tags":[
        "marketing",
        "consultant"
    ],
    "wof:name":"Maximum Achievement",
    "wof:placetype":"venue"
},
  "geometry": {"coordinates":[-82.711906,28.05238],"type":"Point"}
}