{
  "type": "Feature",
  "properties": {
    "iso:country":"US",
    "sg:address":"1608 Alton Rd",
    "sg:city":"Miami Beach",
    "sg:classifiers":[
        {
            "category":"Retail",
            "subcategory":"Repair Shop",
            "type":"Services"
        }
    ],
    "sg:phone":"+1 305 357 4888",
    "sg:postcode":"33139",
    "sg:province":"FL",
    "sg:tags":[
        "lock",
        "key",
        "locksmith"
    ],
    "wof:name":"24 7 Emergency Locksmith",
    "wof:placetype":"venue"
},
  "geometry": {"coordinates":[-80.141311,25.789198],"type":"Point"}
}