{
  "type": "Feature",
  "properties": {
    "addr:full":"616 Collins Ave Miami Beach FL 33139",
    "addr:housenumber":"616",
    "addr:postcode":"33139",
    "addr:street":"Collins Ave",
    "iso:country":"US",
    "sg:address":"616 Collins Ave",
    "sg:city":"Miami Beach",
    "sg:classifiers":[
        {
            "category":"Restaurant",
            "type":"Food & Drink"
        }
    ],
    "sg:phone":"+1 305 673 5262",
    "sg:postcode":"33139",
    "sg:province":"FL",
    "sg:tags":[
        "mexican"
    ],
    "sg:website":"www.senorfrogsfla.com/",
    "wof:name":"Senor Frog's Miami Beach",
    "wof:placetype":"venue"
},
  "geometry": {"coordinates":[-80.132599,25.775801],"type":"Point"}
}