{
  "type": "Feature",
  "properties": {
    "iso:country":"US",
    "sg:address":"1020 Sistrunk St",
    "sg:city":"Atlantic Beach",
    "sg:classifiers":[
        {
            "category":"Real Estate",
            "subcategory":"Real Estate Operator",
            "type":"Services"
        }
    ],
    "sg:phone":"+1 904 246 7684",
    "sg:postcode":"32233",
    "sg:province":"FL",
    "sg:tags":[
        "mobile",
        "home",
        "community"
    ],
    "wof:name":"Oaks Of Atlantic Beach",
    "wof:placetype":"venue"
},
  "geometry": {"coordinates":[-81.41855,30.366434],"type":"Point"}
}