{
  "type": "Feature",
  "properties": {
    "iso:country":"US",
    "sg:address":"8378 SW 8th St",
    "sg:city":"Miami",
    "sg:classifiers":[
        {
            "category":"Shopping",
            "subcategory":"Pets & Pet Supplies",
            "type":"Retail Goods"
        },
        {
            "category":"Retail",
            "subcategory":"Animal Services",
            "type":"Services"
        }
    ],
    "sg:phone":"+1 305 263 1484",
    "sg:postcode":"33144",
    "sg:province":"FL",
    "sg:tags":[
        "dog",
        "cat",
        "furnishing",
        "grooming",
        "store"
    ],
    "wof:name":"Dgorach Pet Grooming Inc",
    "wof:placetype":"venue"
},
  "geometry": {"coordinates":[-80.331157,25.762023],"type":"Point"}
}