{
  "type": "Feature",
  "properties": {
    "addr:full":"331 Worth Ave Palm Beach FL 33480",
    "addr:housenumber":"331",
    "addr:postcode":"33480",
    "addr:street":"Worth Ave",
    "iso:country":"US",
    "sg:address":"331 Worth Ave",
    "sg:city":"Palm Beach",
    "sg:classifiers":[
        {
            "category":"Shopping",
            "subcategory":"Clothing, Apparel, & Fashions",
            "type":"Retail Goods"
        }
    ],
    "sg:phone":"+1 561 514 0923",
    "sg:postcode":"33480",
    "sg:province":"FL",
    "sg:tags":[
        "jewelry",
        "accessory"
    ],
    "wof:name":"Daven Palm Beach Inc",
    "wof:placetype":"venue"
},
  "geometry": {"coordinates":[-80.039771,26.700966],"type":"Point"}
}