{
  "type": "Feature",
  "properties": {
    "iso:country":"US",
    "sg:address":"1221 Melody Ln",
    "sg:city":"Sebring",
    "sg:classifiers":[
        {
            "category":"Professional",
            "subcategory":"Business Services",
            "type":"Services"
        }
    ],
    "sg:phone":"+1 863 385 4327",
    "sg:postcode":"33872",
    "sg:province":"FL",
    "wof:name":"Creech Industries Inc",
    "wof:placetype":"venue"
},
  "geometry": {"coordinates":[-81.494677,27.510865],"type":"Point"}
}