{
  "type": "Feature",
  "properties": {
    "iso:country":"US",
    "sg:address":"2172 Whisper Lakes Blvd",
    "sg:city":"Orlando",
    "sg:classifiers":[
        {
            "category":"Retail",
            "subcategory":"Laundry & Dry Cleaning",
            "type":"Services"
        }
    ],
    "sg:phone":"+1 407 856 6455",
    "sg:postcode":"32837",
    "sg:province":"FL",
    "sg:tags":[
        "drycleaning",
        "plant"
    ],
    "wof:name":"Whisper Lake Cleaners",
    "wof:placetype":"venue"
},
  "geometry": {"coordinates":[-81.40559399999999,28.400059],"type":"Point"}
}