{
  "type": "Feature",
  "properties": {
    "addr:full":"5904 N 9th Ave Pensacola FL 32504",
    "addr:housenumber":"5904",
    "addr:postcode":"32504",
    "addr:street":"N 9Th Ave",
    "iso:country":"US",
    "sg:address":"5904 N 9th Ave",
    "sg:city":"Pensacola",
    "sg:phone":"+1 850 484 4922",
    "sg:postcode":"32504",
    "sg:province":"FL",
    "wof:name":"Gateway Outreach Super Thrift",
    "wof:placetype":"venue"
},
  "geometry": {"coordinates":[-87.201622,30.48436],"type":"Point"}
}