{
  "type": "Feature",
  "properties": {
    "iso:country":"US",
    "sg:address":"3702 US Hwy 92",
    "sg:city":"Plant City",
    "sg:classifiers":[
        {
            "category":"Retail",
            "subcategory":"Auto Repair",
            "type":"Services"
        }
    ],
    "sg:phone":"+1 813 719 9000",
    "sg:postcode":"33566",
    "sg:province":"FL",
    "sg:tags":[
        "body",
        "automobile",
        "painting"
    ],
    "wof:name":"Vision Of Colors Inc",
    "wof:placetype":"venue"
},
  "geometry": {"coordinates":[-82.07014100000001,28.024805],"type":"Point"}
}