{
  "type": "Feature",
  "properties": {
    "addr:full":"9866 Baymeadows Rd Jacksonville FL 32256",
    "addr:housenumber":"9866",
    "addr:postcode":"32256",
    "addr:street":"Baymeadows Rd",
    "iso:country":"US",
    "sg:address":"9866 Baymeadows Rd",
    "sg:city":"Jacksonville",
    "sg:classifiers":[
        {
            "category":"Shopping",
            "subcategory":"Clothing, Apparel, & Fashions",
            "type":"Retail Goods"
        }
    ],
    "sg:phone":"+1 904 646 1262",
    "sg:postcode":"32256",
    "sg:province":"FL",
    "sg:tags":[
        "alteration"
    ],
    "wof:name":"Applause Alterations",
    "wof:placetype":"venue"
},
  "geometry": {"coordinates":[-81.554419,30.218638],"type":"Point"}
}