{
  "type": "Feature",
  "properties": {
    "iso:country":"US",
    "sg:address":"92 Oak Ave",
    "sg:city":"Palm Harbor",
    "sg:classifiers":[
        {
            "category":"Building & Trades",
            "subcategory":"Construction",
            "type":"Services"
        }
    ],
    "sg:phone":"+1 727 938 7192",
    "sg:postcode":"34684",
    "sg:province":"FL",
    "sg:tags":[
        "contractor"
    ],
    "wof:name":"Barry Hicks Masonry Inc",
    "wof:placetype":"venue"
},
  "geometry": {"coordinates":[-82.736576,28.105737],"type":"Point"}
}