{
  "type": "Feature",
  "properties": {
    "addr:full":"12431 US Hwy 41 Spring Hill FL 34610",
    "addr:housenumber":"12431",
    "addr:postcode":"34610",
    "addr:street":"Us Hwy 41",
    "iso:country":"US",
    "sg:address":"12431 US Hwy 41",
    "sg:city":"Spring Hill",
    "sg:classifiers":[
        {
            "category":"Manufacturing",
            "subcategory":"Signs",
            "type":"Manufacturing & Wholesale Goods"
        }
    ],
    "sg:phone":"+1 813 477 1466",
    "sg:postcode":"34610",
    "sg:province":"FL",
    "sg:tags":[
        "specialty",
        "mfg"
    ],
    "wof:name":"Genes Mobile Sign Shop",
    "wof:placetype":"venue"
},
  "geometry": {"coordinates":[-82.501411,28.338639],"type":"Point"}
}