{
  "type": "Feature",
  "properties": {
    "addr:full":"99 Lovejoy Rd NW Fort Walton Bch FL 32548",
    "addr:housenumber":"99",
    "addr:postcode":"32548",
    "addr:street":"Lovejoy Rd Nw Fort",
    "iso:country":"US",
    "sg:address":"99 Lovejoy Rd NW",
    "sg:city":"Fort Walton Bch",
    "sg:classifiers":[
        {
            "category":"Home & Garden",
            "subcategory":"Furniture",
            "type":"Retail Goods"
        }
    ],
    "sg:phone":"+1 850 244 7339",
    "sg:postcode":"32548",
    "sg:province":"FL",
    "sg:tags":[
        "top",
        "counter"
    ],
    "wof:name":"M & M Countertops",
    "wof:placetype":"venue"
},
  "geometry": {"coordinates":[-86.649383,30.424093],"type":"Point"}
}