{
  "type": "Feature",
  "properties": {
    "iso:country":"US",
    "sg:address":"12342 Wiles Rd",
    "sg:city":"Pompano Beach",
    "sg:classifiers":[
        {
            "category":"Manufacturing",
            "subcategory":"Metals",
            "type":"Manufacturing & Wholesale Goods"
        }
    ],
    "sg:phone":"+1 954 825 0558",
    "sg:postcode":"33076",
    "sg:province":"FL",
    "wof:name":"Finewood Finishing",
    "wof:placetype":"venue"
},
  "geometry": {"coordinates":[-80.291258,26.287288],"type":"Point"}
}