{
  "type": "Feature",
  "properties": {
    "addr:full":"4455 Baymeadows Rd Jacksonville FL 32217",
    "addr:housenumber":"4455",
    "addr:postcode":"32217",
    "addr:street":"Baymeadows Rd",
    "iso:country":"US",
    "sg:address":"4455 Baymeadows Rd",
    "sg:city":"Jacksonville",
    "sg:classifiers":[
        {
            "category":"Utilities",
            "subcategory":"Telephone",
            "type":"Services"
        }
    ],
    "sg:phone":"+1 904 448 3390",
    "sg:postcode":"32217",
    "sg:province":"FL",
    "sg:tags":[
        "communications"
    ],
    "wof:name":"Alternet",
    "wof:placetype":"venue"
},
  "geometry": {"coordinates":[-81.60727900000001,30.219341],"type":"Point"}
}