{
  "type": "Feature",
  "properties": {
    "addr:full":"2518 NW 64th Blvd Boca Raton FL 33496",
    "addr:housenumber":"2518",
    "addr:postcode":"33496",
    "addr:street":"Nw 64Th Blvd",
    "iso:country":"US",
    "sg:address":"2518 NW 64th Blvd",
    "sg:city":"Boca Raton",
    "sg:classifiers":[
        {
            "category":"Manufacturing",
            "subcategory":"Apparel",
            "type":"Manufacturing & Wholesale Goods"
        }
    ],
    "sg:phone":"+1 561 989 0908",
    "sg:postcode":"33496",
    "sg:province":"FL",
    "sg:tags":[
        "lady",
        "mfg"
    ],
    "wof:name":"Vargas Enterprises Inc",
    "wof:placetype":"venue"
},
  "geometry": {"coordinates":[-80.143153,26.407638],"type":"Point"}
}