{
  "type": "Feature",
  "properties": {
    "addr:full":"1660 NW 65th Ave Fort Lauderdale FL 33313",
    "addr:housenumber":"1660",
    "addr:postcode":"33313",
    "addr:street":"Nw 65Th Ave",
    "iso:country":"US",
    "sg:address":"1660 NW 65th Ave",
    "sg:city":"Fort Lauderdale",
    "sg:classifiers":[
        {
            "category":"Building & Trades",
            "subcategory":"Electrical",
            "type":"Services"
        },
        {
            "category":"Utilities",
            "subcategory":"Electric",
            "type":"Services"
        }
    ],
    "sg:phone":"+1 954 791 1114",
    "sg:postcode":"33313",
    "sg:province":"FL",
    "sg:tags":[
        "company",
        "electrical",
        "contractor"
    ],
    "wof:name":"C & F Electric Inc",
    "wof:placetype":"venue"
},
  "geometry": {"coordinates":[-80.23616,26.147939],"type":"Point"}
}