{
  "type": "Feature",
  "properties": {
    "iso:country":"US",
    "sg:address":"18320 Monteverde Dr",
    "sg:city":"Spring Hill",
    "sg:classifiers":[
        {
            "category":"Restaurant",
            "type":"Food & Drink"
        }
    ],
    "sg:phone":"+1 727 856 5722",
    "sg:postcode":"34610",
    "sg:province":"FL",
    "sg:tags":[
        "eating"
    ],
    "wof:name":"Hardee Marine Inc",
    "wof:placetype":"venue"
},
  "geometry": {"coordinates":[-82.543307,28.425482],"type":"Point"}
}