{
  "type": "Feature",
  "properties": {
    "addr:full":"7005 N Waterway Dr Miami FL 33155",
    "addr:housenumber":"7005",
    "addr:postcode":"33155",
    "addr:street":"N Waterway Dr",
    "iso:country":"US",
    "sg:address":"7005 N Waterway Dr",
    "sg:city":"Miami",
    "sg:classifiers":[
        {
            "category":"Professional",
            "subcategory":"Art Services",
            "type":"Services"
        }
    ],
    "sg:phone":"+1 305 266 3197",
    "sg:postcode":"33155",
    "sg:province":"FL",
    "sg:tags":[
        "photographer"
    ],
    "wof:name":"Nick Garcia Photography",
    "wof:placetype":"venue"
},
  "geometry": {"coordinates":[-80.308967,25.740966],"type":"Point"}
}