{
  "type": "Feature",
  "properties": {
    "addr:full":"24701 S Dixie Hwy Homestead FL 33032",
    "addr:housenumber":"24701",
    "addr:postcode":"33032",
    "addr:street":"S Dixie Hwy",
    "iso:country":"US",
    "sg:address":"24701 S Dixie Hwy",
    "sg:city":"Homestead",
    "sg:classifiers":[
        {
            "category":"Banks & Credit Unions",
            "subcategory":"Bank",
            "type":"Services"
        }
    ],
    "sg:phone":"+1 305 258 5094",
    "sg:postcode":"33032",
    "sg:province":"FL",
    "sg:website":"http://www.communitybankofflorida.com",
    "wof:name":"Community Bank",
    "wof:placetype":"venue"
},
  "geometry": {"coordinates":[-80.409711,25.537692],"type":"Point"}
}