{
  "type": "Feature",
  "properties": {
    "addr:full":"6480 Midnight Pass Rd Sarasota FL 34242",
    "addr:housenumber":"6480",
    "addr:postcode":"34242",
    "addr:street":"Midnight Pass Rd",
    "iso:country":"US",
    "sg:address":"6480 Midnight Pass Rd",
    "sg:city":"Sarasota",
    "sg:classifiers":[
        {
            "category":"Real Estate",
            "subcategory":"Real Estate Agent",
            "type":"Services"
        }
    ],
    "sg:phone":"+1 941 349 6505",
    "sg:postcode":"34242",
    "sg:province":"FL",
    "sg:tags":[
        "condo",
        "assoc"
    ],
    "sg:website":"www.siestabreakers.com",
    "wof:name":"Siesta Breakers Condominium",
    "wof:placetype":"venue"
},
  "geometry": {"coordinates":[-82.535173,27.251409],"type":"Point"}
}