{
  "type": "Feature",
  "properties": {
    "iso:country":"US",
    "sg:address":"5779 S University Dr",
    "sg:city":"Davie",
    "sg:classifiers":[
        {
            "category":"Personal",
            "subcategory":"Barber",
            "type":"Services"
        }
    ],
    "sg:phone":"+1 954 680 7050",
    "sg:postcode":"33328",
    "sg:province":"FL",
    "wof:name":"Edge Barber Shop",
    "wof:placetype":"venue"
},
  "geometry": {"coordinates":[-80.25191700000001,26.055697],"type":"Point"}
}