{
  "type": "Feature",
  "properties": {
    "iso:country":"US",
    "sg:address":"11362 SW 7th St",
    "sg:city":"Miami",
    "sg:classifiers":[
        {
            "category":"Building & Trades",
            "subcategory":"Construction",
            "type":"Services"
        }
    ],
    "sg:phone":"+1 305 226 8983",
    "sg:postcode":"33174",
    "sg:province":"FL",
    "sg:tags":[
        "concrete",
        "driveway",
        "staining"
    ],
    "sg:website":"http://www.americanstampedconcrete.com",
    "wof:name":"American Stamp Concrete Corp",
    "wof:placetype":"venue"
},
  "geometry": {"coordinates":[-80.37979199999999,25.762229],"type":"Point"}
}