{
  "type": "Feature",
  "properties": {
    "iso:country":"US",
    "sg:address":"235 S 21st Ave",
    "sg:city":"Hollywood",
    "sg:classifiers":[
        {
            "category":"Communications",
            "subcategory":"Film & Video Production",
            "type":"Services"
        }
    ],
    "sg:phone":"+1 954 929 4665",
    "sg:postcode":"33020",
    "sg:province":"FL",
    "sg:tags":[
        "motion",
        "picture"
    ],
    "wof:name":"Hollywood Film & Post",
    "wof:placetype":"venue"
},
  "geometry": {"coordinates":[-80.14871100000001,26.00983],"type":"Point"}
}