{
  "type": "Feature",
  "properties": {
    "iso:country":"US",
    "sg:address":"2512 Balsam Ter",
    "sg:city":"Tallahassee",
    "sg:classifiers":[
        {
            "category":"Real Estate",
            "subcategory":"Real Estate Services",
            "type":"Services"
        },
        {
            "category":"Real Estate",
            "subcategory":"Real Estate Agent",
            "type":"Services"
        }
    ],
    "sg:phone":"+1 850 205 2255",
    "sg:postcode":"32303",
    "sg:province":"FL",
    "sg:tags":[
        "buyer",
        "broker"
    ],
    "sg:website":"http://www.qazihaq.com",
    "wof:name":"Charles Rutenberg Realty",
    "wof:placetype":"venue"
},
  "geometry": {"coordinates":[-84.29918600000001,30.476089],"type":"Point"}
}