{
  "type": "Feature",
  "properties": {
    "iso:country":"US",
    "sg:address":"150 Oxford Rd",
    "sg:city":"Fern Park",
    "sg:classifiers":[
        {
            "category":"Travel",
            "subcategory":"Travel Agent",
            "type":"Entertainment"
        }
    ],
    "sg:phone":"+1 407 830 5151",
    "sg:postcode":"32730",
    "sg:province":"FL",
    "sg:tags":[
        "agency",
        "bureau"
    ],
    "wof:name":"Go Travel",
    "wof:placetype":"venue"
},
  "geometry": {"coordinates":[-81.33967699999999,28.656364],"type":"Point"}
}