{
  "type": "Feature",
  "properties": {
    "iso:country":"US",
    "sg:address":"7345 SW 148th St",
    "sg:city":"Miami",
    "sg:classifiers":[
        {
            "category":"Building & Trades",
            "subcategory":"Construction",
            "type":"Services"
        }
    ],
    "sg:phone":"+1 305 232 2913",
    "sg:postcode":"33158",
    "sg:province":"FL",
    "sg:tags":[
        "addition",
        "residential",
        "remodeling",
        "repair"
    ],
    "wof:name":"A & E Construction Services",
    "wof:placetype":"venue"
},
  "geometry": {"coordinates":[-80.311367,25.63345],"type":"Point"}
}