{
  "type": "Feature",
  "properties": {
    "iso:country":"US",
    "sg:address":"3030 Minuteman Ln",
    "sg:city":"Brandon",
    "sg:classifiers":[
        {
            "category":"Home & Garden",
            "subcategory":"Building Materials",
            "type":"Retail Goods"
        }
    ],
    "sg:phone":"+1 813 681 5350",
    "sg:postcode":"33511",
    "sg:province":"FL",
    "sg:tags":[
        "downspouts",
        "gutter"
    ],
    "wof:name":"C S C Seamless Gutters",
    "wof:placetype":"venue"
},
  "geometry": {"coordinates":[-82.280083,27.899843],"type":"Point"}
}