{
  "type": "Feature",
  "properties": {
    "iso:country":"US",
    "sg:address":"2700 NW 79th St",
    "sg:city":"Miami",
    "sg:classifiers":[
        {
            "category":"Insurance",
            "subcategory":"Health Insurance",
            "type":"Services"
        },
        {
            "category":"Food & Beverages",
            "subcategory":"Groceries & Convenience Stores",
            "type":"Retail Goods"
        }
    ],
    "sg:phone":"+1 305 691 0905",
    "sg:postcode":"33147",
    "sg:province":"FL",
    "sg:tags":[
        "market"
    ],
    "wof:name":"Florida Baby Food Center 2",
    "wof:placetype":"venue"
},
  "geometry": {"coordinates":[-80.241997,25.8461],"type":"Point"}
}