{
  "type": "Feature",
  "properties": {
    "iso:country":"US",
    "sg:address":"12906 SW 49th Ct",
    "sg:city":"Hollywood",
    "sg:classifiers":[
        {
            "category":"Freight",
            "type":"Transportation"
        }
    ],
    "sg:phone":"+1 305 816 1185",
    "sg:postcode":"33027",
    "sg:province":"FL",
    "sg:tags":[
        "sea",
        "foreign"
    ],
    "wof:name":"Mir 1 Exports Inc",
    "wof:placetype":"venue"
},
  "geometry": {"coordinates":[-80.31929,25.963282],"type":"Point"}
}