{
  "type": "Feature",
  "properties": {
    "iso:country":"US",
    "sg:address":"1310 N Railroad Ave",
    "sg:city":"Chipley",
    "sg:classifiers":[
        {
            "category":"Home & Garden",
            "subcategory":"Carpets & Floor Coverings",
            "type":"Retail Goods"
        }
    ],
    "sg:phone":"+1 850 638 2336",
    "sg:postcode":"32428",
    "sg:province":"FL",
    "sg:tags":[
        "material",
        "rug",
        "flooring",
        "contractor"
    ],
    "wof:name":"A Walk Of Elegance Inc",
    "wof:placetype":"venue"
},
  "geometry": {"coordinates":[-85.534593,30.781454],"type":"Point"}
}