{
  "type": "Feature",
  "properties": {
    "iso:country":"US",
    "sg:address":"12719 Boyette Rd",
    "sg:city":"Riverview",
    "sg:classifiers":[
        {
            "category":"Retail",
            "subcategory":"Auto Repair",
            "type":"Services"
        }
    ],
    "sg:phone":"+1 813 677 0190",
    "sg:postcode":"33569",
    "sg:province":"FL",
    "sg:tags":[
        "repairing",
        "automobile"
    ],
    "wof:name":"Yarbrough German Car Works",
    "wof:placetype":"venue"
},
  "geometry": {"coordinates":[-82.28904799999999,27.853505],"type":"Point"}
}