{
  "type": "Feature",
  "properties": {
    "iso:country":"US",
    "sg:address":"2885 S Federal Hwy",
    "sg:city":"Delray Beach",
    "sg:classifiers":[
        {
            "category":"Building & Trades",
            "subcategory":"Equipment Rental",
            "type":"Services"
        },
        {
            "category":"Wholesale",
            "subcategory":"Durable Goods & Equipment",
            "type":"Manufacturing & Wholesale Goods"
        }
    ],
    "sg:phone":"+1 561 272 8964",
    "sg:postcode":"33483",
    "sg:province":"FL",
    "sg:tags":[
        "exporter"
    ],
    "wof:name":"Gold Bell Furniture Inc",
    "wof:placetype":"venue"
},
  "geometry": {"coordinates":[-80.072653,26.429495],"type":"Point"}
}