{
  "type": "Feature",
  "properties": {
    "iso:country":"US",
    "sg:address":"252 NW 40th St",
    "sg:city":"Miami",
    "sg:classifiers":[
        {
            "category":"Manufacturing",
            "subcategory":"Printing",
            "type":"Manufacturing & Wholesale Goods"
        }
    ],
    "sg:phone":"+1 305 576 4985",
    "sg:postcode":"33127",
    "sg:province":"FL",
    "sg:tags":[
        "publishing"
    ],
    "wof:name":"Artistiko LLC",
    "wof:placetype":"venue"
},
  "geometry": {"coordinates":[-80.200577,25.813166],"type":"Point"}
}