{
  "type": "Feature",
  "properties": {
    "iso:country":"US",
    "sg:address":"275 Fontainebleau Blvd",
    "sg:city":"Miami",
    "sg:classifiers":[
        {
            "category":"Travel",
            "subcategory":"Travel Agent",
            "type":"Entertainment"
        }
    ],
    "sg:phone":"+1 305 225 2663",
    "sg:postcode":"33172",
    "sg:province":"FL",
    "sg:tags":[
        "agency",
        "bureau"
    ],
    "wof:name":"Mirvan Travel Inc",
    "wof:placetype":"venue"
},
  "geometry": {"coordinates":[-80.33757799999999,25.77229],"type":"Point"}
}