{
  "type": "Feature",
  "properties": {
    "iso:country":"US",
    "sg:address":"13806 Nighthawk Ter",
    "sg:city":"Bradenton",
    "sg:classifiers":[
        {
            "category":"Building & Trades",
            "subcategory":"Construction",
            "type":"Services"
        }
    ],
    "sg:phone":"+1 941 755 6205",
    "sg:postcode":"34202",
    "sg:province":"FL",
    "sg:tags":[
        "house"
    ],
    "wof:name":"Homes By Towne Lake Wood Ranch",
    "wof:placetype":"venue"
},
  "geometry": {"coordinates":[-82.401923,27.430027],"type":"Point"}
}