{
  "type": "Feature",
  "properties": {
    "addr:full":"2424 Az Park Rd Lakeland FL 33801",
    "addr:postcode":"2424;33801",
    "addr:street":"Park Rd",
    "iso:country":"US",
    "sg:address":"2424 Az Park Rd",
    "sg:city":"Lakeland",
    "sg:classifiers":[
        {
            "category":"Wholesale",
            "subcategory":"Machinery & Supplies",
            "type":"Manufacturing & Wholesale Goods"
        }
    ],
    "sg:phone":"+1 863 667 2916",
    "sg:postcode":"33801",
    "sg:province":"FL",
    "sg:tags":[
        "equipment",
        "layer",
        "carpet"
    ],
    "wof:name":"Shoreline Flooring Supplies",
    "wof:placetype":"venue"
},
  "geometry": {"coordinates":[-81.911587,28.016833],"type":"Point"}
}