{
  "type": "Feature",
  "properties": {
    "iso:country":"US",
    "sg:address":"4720 SW 2nd Ter",
    "sg:city":"Miami",
    "sg:classifiers":[
        {
            "category":"Retail",
            "subcategory":"Auto Repair",
            "type":"Services"
        }
    ],
    "sg:phone":"+1 305 389 9784",
    "sg:postcode":"33134",
    "sg:province":"FL",
    "sg:tags":[
        "automotive"
    ],
    "wof:name":"Victoria Y Luz Towing",
    "wof:placetype":"venue"
},
  "geometry": {"coordinates":[-80.273309,25.769109],"type":"Point"}
}