{
  "type": "Feature",
  "properties": {
    "iso:country":"US",
    "sg:address":"1902 Elsa St",
    "sg:city":"Naples",
    "sg:classifiers":[
        {
            "category":"Manufacturing",
            "subcategory":"Metals",
            "type":"Manufacturing & Wholesale Goods"
        }
    ],
    "sg:phone":"+1 239 592 6329",
    "sg:postcode":"34109",
    "sg:province":"FL",
    "sg:tags":[
        "steel"
    ],
    "wof:name":"Wix Fabrications",
    "wof:placetype":"venue"
},
  "geometry": {"coordinates":[-81.779588,26.21928],"type":"Point"}
}