{
  "type": "Feature",
  "properties": {
    "iso:country":"US",
    "sg:address":"220 SW 64th Way",
    "sg:city":"Hollywood",
    "sg:classifiers":[
        {
            "category":"Building & Trades",
            "subcategory":"Construction",
            "type":"Services"
        }
    ],
    "sg:phone":"+1 954 983 5456",
    "sg:postcode":"33023",
    "sg:province":"FL",
    "sg:tags":[
        "residential",
        "nonresidential"
    ],
    "wof:name":"Benitez Valdemer",
    "wof:placetype":"venue"
},
  "geometry": {"coordinates":[-80.217078,26.007825],"type":"Point"}
}