{
  "type": "Feature",
  "properties": {
    "iso:country":"US",
    "sg:address":"1574 NW 108th Ave",
    "sg:city":"Miami",
    "sg:classifiers":[
        {
            "category":"Professional",
            "subcategory":"Advertising",
            "type":"Services"
        },
        {
            "category":"Retail",
            "subcategory":"Repair Shop",
            "type":"Services"
        },
        {
            "category":"Manufacturing",
            "subcategory":"Signs",
            "type":"Manufacturing & Wholesale Goods"
        }
    ],
    "sg:phone":"+1 305 468 8986",
    "sg:postcode":"33172",
    "sg:province":"FL",
    "sg:tags":[
        "specialty",
        "signs-maintenance"
    ],
    "sg:website":"http://www.polisigns.com",
    "wof:name":"Poli Signs Inc",
    "wof:placetype":"venue"
},
  "geometry": {"coordinates":[-80.370875,25.788666],"type":"Point"}
}