{
  "type": "Feature",
  "properties": {
    "iso:country":"US",
    "sg:address":"717 N Palm Ave",
    "sg:city":"Kissimmee",
    "sg:classifiers":[
        {
            "category":"Government",
            "subcategory":"Office",
            "type":"Public Place"
        }
    ],
    "sg:phone":"+1 407 847 2388",
    "sg:postcode":"34741",
    "sg:province":"FL",
    "sg:tags":[
        "executive"
    ],
    "wof:name":"Kissimmee Municipal Govt",
    "wof:placetype":"venue"
},
  "geometry": {"coordinates":[-81.421088,28.298205],"type":"Point"}
}