{
  "type": "Feature",
  "properties": {
    "addr:full":"10405 Rocky River Ct Tampa FL 33647",
    "addr:housenumber":"10405",
    "addr:postcode":"33647",
    "addr:street":"Rocky River Ct",
    "iso:country":"US",
    "sg:address":"10405 Rocky River Ct",
    "sg:city":"Tampa",
    "sg:classifiers":[
        {
            "category":"Local Transit",
            "type":"Transportation"
        }
    ],
    "sg:phone":"+1 813 991 9755",
    "sg:postcode":"33647",
    "sg:province":"FL",
    "sg:tags":[
        "limousine"
    ],
    "wof:name":"Taj Limo",
    "wof:placetype":"venue"
},
  "geometry": {"coordinates":[-82.31931299999999,28.149001],"type":"Point"}
}