{
  "type": "Feature",
  "properties": {
    "iso:country":"US",
    "sg:address":"1402 W University Ave",
    "sg:city":"Gainesville",
    "sg:classifiers":[
        {
            "category":"Organizations",
            "subcategory":"Religious Organization",
            "type":"Services"
        }
    ],
    "sg:phone":"+1 352 376 7539",
    "sg:postcode":"32603",
    "sg:province":"FL",
    "wof:name":"Presbyterian/Discpls Stdnt Ctr",
    "wof:placetype":"venue"
},
  "geometry": {"coordinates":[-82.341762,29.652149],"type":"Point"}
}