{
  "type": "Feature",
  "properties": {
    "addr:full":"37623 Magnolia Ave Dade City FL 33523",
    "addr:housenumber":"37623",
    "addr:postcode":"33523",
    "addr:street":"Magnolia Ave",
    "iso:country":"US",
    "sg:address":"37623 Magnolia Ave",
    "sg:city":"Dade City",
    "sg:classifiers":[
        {
            "category":"Organizations",
            "subcategory":"Religious Organization",
            "type":"Services"
        }
    ],
    "sg:phone":"+1 352 567 3888",
    "sg:postcode":"33523",
    "sg:province":"FL",
    "sg:tags":[
        "episcopal",
        "church"
    ],
    "wof:name":"Saint Marys Episcopal Church",
    "wof:placetype":"venue"
},
  "geometry": {"coordinates":[-82.193264,28.365591],"type":"Point"}
}