{
  "type": "Feature",
  "properties": {
    "addr:full":"1051 SW 1st Way Deerfield Beach FL 33441",
    "addr:housenumber":"1051",
    "addr:postcode":"33441",
    "addr:street":"Sw 1St Way",
    "iso:country":"US",
    "sg:address":"1051 SW 1st Way",
    "sg:city":"Deerfield Beach",
    "sg:classifiers":[
        {
            "category":"Building & Trades",
            "subcategory":"Plumbing",
            "type":"Services"
        }
    ],
    "sg:phone":"+1 954 428 3140",
    "sg:postcode":"33441",
    "sg:province":"FL",
    "sg:tags":[
        "plumbing",
        "contractor"
    ],
    "wof:name":"Pedrick Plumbing Inc",
    "wof:placetype":"venue"
},
  "geometry": {"coordinates":[-80.106049,26.298965],"type":"Point"}
}