{
  "type": "Feature",
  "properties": {
    "iso:country":"US",
    "sg:address":"3503 67th Street Ct E",
    "sg:city":"Bradenton",
    "sg:classifiers":[
        {
            "category":"Shopping",
            "type":"Retail Goods"
        }
    ],
    "sg:phone":"+1 941 714 0635",
    "sg:postcode":"34208",
    "sg:province":"FL",
    "sg:tags":[
        "wedding",
        "supply"
    ],
    "wof:name":"Gamso & Gamso",
    "wof:placetype":"venue"
},
  "geometry": {"coordinates":[-82.47396999999999,27.468034],"type":"Point"}
}