{
  "type": "Feature",
  "properties": {
    "addr:full":"204 S Flamingo Rd Hollywood FL 33027",
    "addr:housenumber":"204",
    "addr:postcode":"33027",
    "addr:street":"S Flamingo Rd",
    "iso:country":"US",
    "sg:address":"204 S Flamingo Rd",
    "sg:city":"Hollywood",
    "sg:classifiers":[
        {
            "category":"Insurance",
            "subcategory":"Insurance Agent",
            "type":"Services"
        },
        {
            "category":"Banks & Credit Unions",
            "subcategory":"Bank",
            "type":"Services"
        }
    ],
    "sg:phone":"+1 954 392 4500",
    "sg:postcode":"33027",
    "sg:province":"FL",
    "wof:name":"Unibank",
    "wof:placetype":"venue"
},
  "geometry": {"coordinates":[-80.312068,26.00714],"type":"Point"}
}