{
  "type": "Feature",
  "properties": {
    "addr:full":"465 Brandon Town Center Mall Brandon FL 33511",
    "addr:housenumber":"465",
    "addr:postcode":"33511",
    "addr:street":"Brandon Town;Mall",
    "iso:country":"US",
    "sg:address":"465 Brandon Town Center Mall",
    "sg:city":"Brandon",
    "sg:classifiers":[
        {
            "category":"Utilities",
            "subcategory":"Mobile Phone",
            "type":"Services"
        }
    ],
    "sg:phone":"+1 813 685 7611",
    "sg:postcode":"33511",
    "sg:province":"FL",
    "sg:tags":[
        "telephone",
        "cellular"
    ],
    "wof:name":"Alltel",
    "wof:placetype":"venue"
},
  "geometry": {"coordinates":[-82.325596,27.931826],"type":"Point"}
}