{
  "type": "Feature",
  "properties": {
    "iso:country":"US",
    "sg:address":"6861 W 14th Ct",
    "sg:city":"Hialeah",
    "sg:classifiers":[
        {
            "category":"Social Services",
            "subcategory":"Child Care",
            "type":"Services"
        },
        {
            "category":"Education",
            "subcategory":"Preschool",
            "type":"Public Place"
        },
        {
            "category":"Education",
            "subcategory":"School",
            "type":"Public Place"
        }
    ],
    "sg:phone":"+1 305 821 5964",
    "sg:postcode":"33014",
    "sg:province":"FL",
    "sg:tags":[
        "elementary",
        "day"
    ],
    "wof:name":"Three Flags Academy",
    "wof:placetype":"venue"
},
  "geometry": {"coordinates":[-80.312202,25.885],"type":"Point"}
}