{
  "type": "Feature",
  "properties": {
    "addr:full":"3250 Mary St Miami FL 33133",
    "addr:housenumber":"3250",
    "addr:postcode":"33133",
    "addr:street":"Mary St",
    "iso:country":"US",
    "sg:address":"3250 Mary St",
    "sg:city":"Miami",
    "sg:classifiers":[
        {
            "category":"Real Estate",
            "subcategory":"Real Estate Operator",
            "type":"Services"
        }
    ],
    "sg:phone":"+1 305 445 4238",
    "sg:postcode":"33133",
    "sg:province":"FL",
    "sg:tags":[
        "management",
        "asset"
    ],
    "wof:name":"Gencom Group",
    "wof:placetype":"venue"
},
  "geometry": {"coordinates":[-80.23961799999999,25.730946],"type":"Point"}
}