{
  "type": "Feature",
  "properties": {
    "addr:full":"1515 S Nova Rd Daytona Beach FL 32114",
    "addr:housenumber":"1515",
    "addr:postcode":"32114",
    "addr:street":"S Nova Rd",
    "iso:country":"US",
    "sg:address":"1515 S Nova Rd",
    "sg:city":"Daytona Beach",
    "sg:classifiers":[
        {
            "category":"Health Services",
            "subcategory":"Doctor",
            "type":"Services"
        }
    ],
    "sg:phone":"+1 386 947 9318",
    "sg:postcode":"32114",
    "sg:province":"FL",
    "sg:tags":[
        "dentist"
    ],
    "wof:name":"Greenberg Dental",
    "wof:placetype":"venue"
},
  "geometry": {"coordinates":[-81.028567,29.175659],"type":"Point"}
}