{
  "type": "Feature",
  "properties": {
    "iso:country":"US",
    "sg:address":"115 Holly St",
    "sg:city":"Apopka",
    "sg:classifiers":[
        {
            "category":"Building & Trades",
            "subcategory":"Construction",
            "type":"Services"
        }
    ],
    "sg:phone":"+1 407 886 3750",
    "sg:postcode":"32712",
    "sg:province":"FL",
    "sg:tags":[
        "contractor",
        "carpenter",
        "carpentry"
    ],
    "wof:name":"Germain's Repairs",
    "wof:placetype":"venue"
},
  "geometry": {"coordinates":[-81.50796099999999,28.755601],"type":"Point"}
}