{
  "type": "Feature",
  "properties": {
    "iso:country":"US",
    "sg:address":"2353 Sunderland Rd",
    "sg:city":"Maitland",
    "sg:classifiers":[
        {
            "category":"Wholesale",
            "subcategory":"Home Furnishings",
            "type":"Manufacturing & Wholesale Goods"
        }
    ],
    "sg:phone":"+1 407 756 8708",
    "sg:postcode":"32751",
    "sg:province":"FL",
    "sg:tags":[
        "manufacturer",
        "baskets-wholesale"
    ],
    "wof:name":"Baskets Blooms",
    "wof:placetype":"venue"
},
  "geometry": {"coordinates":[-81.33860799999999,28.641631],"type":"Point"}
}