{
  "type": "Feature",
  "properties": {
    "addr:full":"29 S J St Lake Worth FL 33460",
    "addr:housenumber":"29",
    "addr:postcode":"33460",
    "addr:street":"S J St",
    "iso:country":"US",
    "sg:address":"29 S J St",
    "sg:city":"Lake Worth",
    "sg:classifiers":[
        {
            "category":"Food & Beverages",
            "subcategory":"Bakery",
            "type":"Retail Goods"
        }
    ],
    "sg:phone":"+1 561 523 1607",
    "sg:postcode":"33460",
    "sg:province":"FL",
    "sg:tags":[
        "baker"
    ],
    "wof:name":"Delicioso Cakes & Pastries Inc",
    "wof:placetype":"venue"
},
  "geometry": {"coordinates":[-80.05644700000001,26.615],"type":"Point"}
}