{
  "type": "Feature",
  "properties": {
    "iso:country":"US",
    "sg:address":"4504 Winderwood Cir",
    "sg:city":"Orlando",
    "sg:classifiers":[
        {
            "category":"Building & Trades",
            "subcategory":"Plumbing",
            "type":"Services"
        }
    ],
    "sg:phone":"+1 407 538 9880",
    "sg:postcode":"32835",
    "sg:province":"FL",
    "sg:tags":[
        "plumber",
        "industrial",
        "contractors-commercial"
    ],
    "wof:name":"Innovative Plumbing Solutions",
    "wof:placetype":"venue"
},
  "geometry": {"coordinates":[-81.49128399999999,28.496847],"type":"Point"}
}