{
  "type": "Feature",
  "properties": {
    "iso:country":"US",
    "sg:address":"1134 W Orange Ave",
    "sg:city":"Tallahassee",
    "sg:classifiers":[
        {
            "category":"Home & Garden",
            "subcategory":"Building Materials",
            "type":"Retail Goods"
        }
    ],
    "sg:phone":"+1 850 575 9611",
    "sg:postcode":"32310",
    "sg:province":"FL",
    "sg:tags":[
        "glass",
        "window",
        "plate"
    ],
    "sg:website":"www.leeandcatesglass.com",
    "wof:name":"Lee & Cates Tallahassee Glass",
    "wof:placetype":"venue"
},
  "geometry": {"coordinates":[-84.303411,30.412634],"type":"Point"}
}