{
  "type": "Feature",
  "properties": {
    "iso:country":"US",
    "sg:address":"1256 NE 38th St",
    "sg:city":"Fort Lauderdale",
    "sg:classifiers":[
        {
            "category":"Personal",
            "subcategory":"Barber",
            "type":"Services"
        }
    ],
    "sg:phone":"+1 954 563 6115",
    "sg:postcode":"33334",
    "sg:province":"FL",
    "sg:tags":[
        "shop"
    ],
    "wof:name":"Carmen's Barber Shop",
    "wof:placetype":"venue"
},
  "geometry": {"coordinates":[-80.13049599999999,26.174053],"type":"Point"}
}