{
  "type": "Feature",
  "properties": {
    "addr:full":"1910 Wells Rd Orange Park FL 32073",
    "addr:housenumber":"1910",
    "addr:postcode":"32073",
    "addr:street":"Wells Rd",
    "iso:country":"US",
    "sg:address":"1910 Wells Rd",
    "sg:city":"Orange Park",
    "sg:classifiers":[
        {
            "category":"Shopping",
            "subcategory":"Jewelry",
            "type":"Retail Goods"
        }
    ],
    "sg:phone":"+1 904 269 1211",
    "sg:postcode":"32073",
    "sg:province":"FL",
    "sg:tags":[
        "fine"
    ],
    "wof:name":"Gayfers",
    "wof:placetype":"venue"
},
  "geometry": {"coordinates":[-81.732506,30.186844],"type":"Point"}
}