{
  "type": "Feature",
  "properties": {
    "addr:full":"5305 S Pine Ave Ocala FL 34480",
    "addr:housenumber":"5305",
    "addr:postcode":"34480",
    "addr:street":"S Pine Ave",
    "iso:country":"US",
    "sg:address":"5305 S Pine Ave",
    "sg:city":"Ocala",
    "sg:classifiers":[
        {
            "category":"Real Estate",
            "subcategory":"Real Estate Agent",
            "type":"Services"
        }
    ],
    "sg:phone":"+1 352 732 6991",
    "sg:postcode":"34480",
    "sg:province":"FL",
    "wof:name":"Donald Eaton Realty",
    "wof:placetype":"venue"
},
  "geometry": {"coordinates":[-82.106703,29.133562],"type":"Point"}
}