{
  "type": "Feature",
  "properties": {
    "addr:full":"10 Fairway Dr Deerfield Beach FL 33441",
    "addr:housenumber":"10",
    "addr:postcode":"33441",
    "addr:street":"Fairway Dr",
    "iso:country":"US",
    "sg:address":"10 Fairway Dr",
    "sg:city":"Deerfield Beach",
    "sg:classifiers":[
        {
            "category":"Insurance",
            "subcategory":"Insurance Agent",
            "type":"Services"
        }
    ],
    "sg:phone":"+1 954 570 6900",
    "sg:postcode":"33441",
    "sg:province":"FL",
    "wof:name":"Affordable Insurance",
    "wof:placetype":"venue"
},
  "geometry": {"coordinates":[-80.11057,26.318588],"type":"Point"}
}