{
  "type": "Feature",
  "properties": {
    "addr:full":"5711 W Hallandale Beach Blvd Hollywood FL 33023",
    "addr:housenumber":"5711",
    "addr:postcode":"33023",
    "addr:street":"W Hallandale Beach Blvd",
    "iso:country":"US",
    "sg:address":"5711 W Hallandale Beach Blvd",
    "sg:city":"Hollywood",
    "sg:classifiers":[
        {
            "category":"Health Services",
            "subcategory":"Medical Lab",
            "type":"Services"
        }
    ],
    "sg:phone":"+1 954 986 1940",
    "sg:postcode":"33023",
    "sg:province":"FL",
    "sg:tags":[
        "laboratory"
    ],
    "wof:name":"Humanitas Laboratories Inc",
    "wof:placetype":"venue"
},
  "geometry": {"coordinates":[-80.201007,25.984732],"type":"Point"}
}