{
  "type": "Feature",
  "properties": {
    "iso:country":"US",
    "sg:address":"6640 Estero Blvd",
    "sg:city":"Fort Myers Beach",
    "sg:classifiers":[
        {
            "category":"Travel",
            "subcategory":"Hotels & Motels",
            "type":"Entertainment"
        },
        {
            "category":"Organizations",
            "subcategory":"Community Association",
            "type":"Services"
        }
    ],
    "sg:phone":"+1 239 765 1155",
    "sg:postcode":"33931",
    "sg:province":"FL",
    "sg:tags":[
        "resort"
    ],
    "wof:name":"Pointe Estero Condo Resort",
    "wof:placetype":"venue"
},
  "geometry": {"coordinates":[-81.902214,26.418702],"type":"Point"}
}