{
  "type": "Feature",
  "properties": {
    "iso:country":"US",
    "sg:address":"2600 S Suncoast Blvd",
    "sg:city":"Homosassa",
    "sg:classifiers":[
        {
            "category":"Autos & Motor Vehicles",
            "subcategory":"Automobile Sales",
            "type":"Retail Goods"
        }
    ],
    "sg:phone":"+1 352 621 6789",
    "sg:postcode":"34448",
    "sg:province":"FL",
    "sg:tags":[
        "car",
        "dealer"
    ],
    "wof:name":"Cojo's Inc",
    "wof:placetype":"venue"
},
  "geometry": {"coordinates":[-82.579279,28.824012],"type":"Point"}
}