{
  "type": "Feature",
  "properties": {
    "addr:full":"13300 NW 97th Ave Hialeah FL 33018",
    "addr:housenumber":"13300",
    "addr:postcode":"33018",
    "addr:street":"Nw 97Th Ave",
    "iso:country":"US",
    "sg:address":"13300 NW 97th Ave",
    "sg:city":"Hialeah",
    "sg:classifiers":[
        {
            "category":"Wholesale",
            "subcategory":"Non-durable Goods",
            "type":"Manufacturing & Wholesale Goods"
        }
    ],
    "sg:phone":"+1 305 558 0708",
    "sg:postcode":"33018",
    "sg:province":"FL",
    "wof:name":"Helpful Products Distributors",
    "wof:placetype":"venue"
},
  "geometry": {"coordinates":[-80.3584,25.89658],"type":"Point"}
}