{
  "type": "Feature",
  "properties": {
    "addr:full":"17050 NE 14th Ave North Miami Bch FL 33162",
    "addr:housenumber":"17050",
    "addr:postcode":"33162",
    "addr:street":"Ne 14Th Ave",
    "iso:country":"US",
    "sg:address":"17050 NE 14th Ave",
    "sg:city":"North Miami Bch",
    "sg:classifiers":[
        {
            "category":"Building & Trades",
            "subcategory":"Landscaping Services",
            "type":"Services"
        }
    ],
    "sg:phone":"+1 305 354 2282",
    "sg:postcode":"33162",
    "sg:province":"FL",
    "sg:tags":[
        "landscape",
        "contractor"
    ],
    "wof:name":"Mar Len Gardens",
    "wof:placetype":"venue"
},
  "geometry": {"coordinates":[-80.172393,25.932852],"type":"Point"}
}