{
  "type": "Feature",
  "properties": {
    "iso:country":"US",
    "sg:address":"13236 SW 46th Ln",
    "sg:city":"Miami",
    "sg:classifiers":[
        {
            "category":"Wholesale",
            "subcategory":"Apparel",
            "type":"Manufacturing & Wholesale Goods"
        }
    ],
    "sg:phone":"+1 305 553 5331",
    "sg:postcode":"33175",
    "sg:province":"FL",
    "sg:tags":[
        "clothing"
    ],
    "wof:name":"K Chys",
    "wof:placetype":"venue"
},
  "geometry": {"coordinates":[-80.408332,25.722592],"type":"Point"}
}