{
  "type": "Feature",
  "properties": {
    "iso:country":"US",
    "sg:address":"5416 Fruitville Rd",
    "sg:city":"Sarasota",
    "sg:classifiers":[
        {
            "category":"Restaurant",
            "type":"Food & Drink"
        }
    ],
    "sg:menulink":"http://www.allmenus.com/fl/sarasota/38377-firehouse-subs/menu/",
    "sg:phone":"+1 941 379 5561",
    "sg:postcode":"34232",
    "sg:province":"FL",
    "sg:tags":[
        "wrap",
        "american",
        "sandwich"
    ],
    "wof:name":"Firehouse Subs",
    "wof:placetype":"venue"
},
  "geometry": {"coordinates":[-82.461259,27.337806],"type":"Point"}
}