{
  "type": "Feature",
  "properties": {
    "addr:full":"1289 S Missouri Ave Clearwater FL 33756",
    "addr:housenumber":"1289",
    "addr:postcode":"33756",
    "addr:street":"S Missouri Ave",
    "iso:country":"US",
    "sg:address":"1289 S Missouri Ave",
    "sg:city":"Clearwater",
    "sg:classifiers":[
        {
            "category":"Wholesale",
            "subcategory":"Machinery & Supplies",
            "type":"Manufacturing & Wholesale Goods"
        }
    ],
    "sg:phone":"+1 727 446 1476",
    "sg:postcode":"33756",
    "sg:province":"FL",
    "sg:tags":[
        "shop",
        "equipment",
        "beauty"
    ],
    "wof:name":"Ace Beauty Co",
    "wof:placetype":"venue"
},
  "geometry": {"coordinates":[-82.787508,27.9528],"type":"Point"}
}