{
  "type": "Feature",
  "properties": {
    "addr:full":"3327 Forsyth Rd Winter Park FL 32792",
    "addr:housenumber":"3327",
    "addr:postcode":"32792",
    "addr:street":"Forsyth Rd",
    "iso:country":"US",
    "sg:address":"3327 Forsyth Rd",
    "sg:city":"Winter Park",
    "sg:classifiers":[
        {
            "category":"Restaurant",
            "type":"Food & Drink"
        }
    ],
    "sg:phone":"+1 407 679 5600",
    "sg:postcode":"32792",
    "sg:province":"FL",
    "sg:tags":[
        "middle",
        "eastern"
    ],
    "wof:name":"Elijah's Grill",
    "wof:placetype":"venue"
},
  "geometry": {"coordinates":[-81.298203,28.592899],"type":"Point"}
}