{
  "type": "Feature",
  "properties": {
    "iso:country":"US",
    "sg:address":"209 N Goldenrod Rd",
    "sg:city":"Orlando",
    "sg:classifiers":[
        {
            "category":"Professional",
            "subcategory":"Accounting & Tax Preparation",
            "type":"Services"
        }
    ],
    "sg:phone":"+1 407 277 3000",
    "sg:postcode":"32807",
    "sg:province":"FL",
    "wof:name":"Rogers Scruggs & Hoskins",
    "wof:placetype":"venue"
},
  "geometry": {"coordinates":[-81.285841,28.551701],"type":"Point"}
}