{
  "type": "Feature",
  "properties": {
    "iso:country":"US",
    "sg:address":"4926 Cottonwood",
    "sg:city":"Hernando",
    "sg:classifiers":[
        {
            "category":"Building & Trades",
            "subcategory":"Construction",
            "type":"Services"
        }
    ],
    "sg:phone":"+1 352 726 2710",
    "sg:postcode":"34442",
    "sg:province":"FL",
    "sg:tags":[
        "general",
        "contractor"
    ],
    "wof:name":"John Cordwell Builders",
    "wof:placetype":"venue"
},
  "geometry": {"coordinates":[-82.382879,28.933102],"type":"Point"}
}