{
  "type": "Feature",
  "properties": {
    "addr:full":"1415 Timberlane Rd Tallahassee FL 32312",
    "addr:housenumber":"1415",
    "addr:postcode":"32312",
    "addr:street":"Timberlane Rd",
    "iso:country":"US",
    "sg:address":"1415 Timberlane Rd",
    "sg:city":"Tallahassee",
    "sg:classifiers":[
        {
            "category":"Retail",
            "subcategory":"Laundry & Dry Cleaning",
            "type":"Services"
        }
    ],
    "sg:phone":"+1 850 893 7052",
    "sg:postcode":"32312",
    "sg:province":"FL",
    "sg:tags":[
        "cleaners"
    ],
    "wof:name":"Morrow Cleaners",
    "wof:placetype":"venue"
},
  "geometry": {"coordinates":[-84.254336,30.504662],"type":"Point"}
}