{
  "type": "Feature",
  "properties": {
    "addr:full":"9292 Jamaica Dr Miami FL 33189",
    "addr:housenumber":"9292",
    "addr:postcode":"33189",
    "addr:street":"Jamaica Dr",
    "iso:country":"US",
    "sg:address":"9292 Jamaica Dr",
    "sg:city":"Miami",
    "sg:classifiers":[
        {
            "category":"Professional",
            "type":"Services"
        }
    ],
    "sg:phone":"+1 305 232 8389",
    "sg:postcode":"33189",
    "sg:province":"FL",
    "wof:name":"Emmanuel Espinal Svc",
    "wof:placetype":"venue"
},
  "geometry": {"coordinates":[-80.34228899999999,25.58326],"type":"Point"}
}