{
  "type": "Feature",
  "properties": {
    "addr:full":"1458 10th Ct West Palm Beach FL 33403",
    "addr:housenumber":"1458",
    "addr:postcode":"33403",
    "addr:street":"10Th Ct",
    "iso:country":"US",
    "sg:address":"1458 10th Ct",
    "sg:city":"West Palm Beach",
    "sg:classifiers":[
        {
            "category":"Building & Trades",
            "subcategory":"Landscaping Services",
            "type":"Services"
        }
    ],
    "sg:phone":"+1 561 882 4040",
    "sg:postcode":"33403",
    "sg:province":"FL",
    "wof:name":"Joe Hnleys Tree Trmming Ldscpg",
    "wof:placetype":"venue"
},
  "geometry": {"coordinates":[-80.07596100000001,26.80608],"type":"Point"}
}