{
  "type": "Feature",
  "properties": {
    "iso:country":"US",
    "sg:address":"305 E New York Ave",
    "sg:city":"Deland",
    "sg:classifiers":[
        {
            "category":"Health Services",
            "subcategory":"Doctor",
            "type":"Services"
        }
    ],
    "sg:phone":"+1 386 734 2931",
    "sg:postcode":"32724",
    "sg:province":"FL",
    "sg:tags":[
        "ophthalmologist",
        "medical"
    ],
    "wof:name":"Central Florida Eye Specialists P L",
    "wof:placetype":"venue"
},
  "geometry": {"coordinates":[-81.299004,29.0282],"type":"Point"}
}