{
  "type": "Feature",
  "properties": {
    "iso:country":"US",
    "sg:address":"3250 Gulfview Dr",
    "sg:city":"Spring Hill",
    "sg:classifiers":[
        {
            "category":"Communications",
            "type":"Services"
        }
    ],
    "sg:phone":"+1 352 592 0279",
    "sg:postcode":"34607",
    "sg:province":"FL",
    "sg:tags":[
        "communication"
    ],
    "wof:name":"Princeton Communications",
    "wof:placetype":"venue"
},
  "geometry": {"coordinates":[-82.66215099999999,28.492459],"type":"Point"}
}