{
  "type": "Feature",
  "properties": {
    "addr:full":"5243 E Colonial Dr Orlando FL 32807",
    "addr:housenumber":"5243",
    "addr:postcode":"32807",
    "addr:street":"E Colonial Dr",
    "iso:country":"US",
    "sg:address":"5243 E Colonial Dr",
    "sg:city":"Orlando",
    "sg:classifiers":[
        {
            "category":"Health Services",
            "subcategory":"Chiropractor",
            "type":"Services"
        }
    ],
    "sg:phone":"+1 407 275 9335",
    "sg:postcode":"32807",
    "sg:province":"FL",
    "wof:name":"Orlando Pain Relief Ctr",
    "wof:placetype":"venue"
},
  "geometry": {"coordinates":[-81.31606600000001,28.554846],"type":"Point"}
}