{
  "type": "Feature",
  "properties": {
    "iso:country":"US",
    "sg:address":"330 Palm Beach Trace Dr",
    "sg:city":"West Palm Beach",
    "sg:classifiers":[
        {
            "category":"Freight",
            "type":"Transportation"
        }
    ],
    "sg:phone":"+1 561 798 6100",
    "sg:postcode":"33411",
    "sg:province":"FL",
    "sg:tags":[
        "general"
    ],
    "wof:name":"U Store It",
    "wof:placetype":"venue"
},
  "geometry": {"coordinates":[-80.22711099999999,26.712844],"type":"Point"}
}