{
  "type": "Feature",
  "properties": {
    "addr:full":"1730 NW 23rd St Miami FL 33142",
    "addr:housenumber":"1730",
    "addr:postcode":"33142",
    "addr:street":"Nw 23Rd St",
    "iso:country":"US",
    "sg:address":"1730 NW 23rd St",
    "sg:city":"Miami",
    "sg:classifiers":[
        {
            "category":"Shopping",
            "subcategory":"Shoes",
            "type":"Retail Goods"
        }
    ],
    "sg:phone":"+1 305 633 3500",
    "sg:postcode":"33142",
    "sg:province":"FL",
    "sg:tags":[
        "store"
    ],
    "wof:name":"D & B Footwear",
    "wof:placetype":"venue"
},
  "geometry": {"coordinates":[-80.22475900000001,25.79827],"type":"Point"}
}