{
  "type": "Feature",
  "properties": {
    "iso:country":"US",
    "sg:address":"6660 46th Ave N",
    "sg:city":"St Petersburg",
    "sg:classifiers":[
        {
            "category":"Retail",
            "subcategory":"Auto Repair",
            "type":"Services"
        }
    ],
    "sg:phone":"+1 727 544 3114",
    "sg:postcode":"33709",
    "sg:province":"FL",
    "sg:tags":[
        "repairing",
        "automobile"
    ],
    "wof:name":"Ace Motors & Garage",
    "wof:placetype":"venue"
},
  "geometry": {"coordinates":[-82.730142,27.813549],"type":"Point"}
}