{
  "type": "Feature",
  "properties": {
    "iso:country":"US",
    "sg:address":"1450 SW 3rd St",
    "sg:city":"Pompano Beach",
    "sg:classifiers":[
        {
            "category":"Manufacturing",
            "subcategory":"Tools & Machinery",
            "type":"Manufacturing & Wholesale Goods"
        }
    ],
    "sg:phone":"+1 954 781 2850",
    "sg:postcode":"33069",
    "sg:province":"FL",
    "sg:tags":[
        "cleaning",
        "system"
    ],
    "wof:name":"AAA Spray Equipment",
    "wof:placetype":"venue"
},
  "geometry": {"coordinates":[-80.144133,26.226523],"type":"Point"}
}