{
  "type": "Feature",
  "properties": {
    "addr:full":"135 N Atlas Dr Apopka FL 32703",
    "addr:housenumber":"135",
    "addr:postcode":"32703",
    "addr:street":"N Atlas Dr",
    "iso:country":"US",
    "sg:address":"135 N Atlas Dr",
    "sg:city":"Apopka",
    "sg:classifiers":[
        {
            "category":"Professional",
            "subcategory":"Art Services",
            "type":"Services"
        }
    ],
    "sg:phone":"+1 407 886 1571",
    "sg:postcode":"32703",
    "sg:province":"FL",
    "sg:tags":[
        "graphic",
        "designer"
    ],
    "sg:website":"www.floridaliteracy.com",
    "wof:name":"Inforgraphic",
    "wof:placetype":"venue"
},
  "geometry": {"coordinates":[-81.473327,28.679144],"type":"Point"}
}