{
  "type": "Feature",
  "properties": {
    "iso:country":"US",
    "sg:address":"315 Bayland Rd",
    "sg:city":"Fort Myers",
    "sg:classifiers":[
        {
            "category":"Utilities",
            "subcategory":"Telephone",
            "type":"Services"
        }
    ],
    "sg:phone":"+1 239 463 7411",
    "sg:postcode":"33931",
    "sg:province":"FL",
    "sg:tags":[
        "company"
    ],
    "wof:name":"Simmons Communications Inc",
    "wof:placetype":"venue"
},
  "geometry": {"coordinates":[-81.91927699999999,26.435823],"type":"Point"}
}