{
  "type": "Feature",
  "properties": {
    "iso:country":"US",
    "sg:address":"1660 Maravilla Ave",
    "sg:city":"Fort Myers",
    "sg:classifiers":[
        {
            "category":"Building & Trades",
            "subcategory":"Construction",
            "type":"Services"
        }
    ],
    "sg:phone":"+1 239 939 7758",
    "sg:postcode":"33901",
    "sg:province":"FL",
    "sg:tags":[
        "hanging",
        "painter",
        "contractor"
    ],
    "wof:name":"Peter's Fine Finishes",
    "wof:placetype":"venue"
},
  "geometry": {"coordinates":[-81.879046,26.615477],"type":"Point"}
}