{
  "type": "Feature",
  "properties": {
    "iso:country":"US",
    "sg:address":"5308 Coronet Dr",
    "sg:city":"Jacksonville",
    "sg:classifiers":[
        {
            "category":"Building & Trades",
            "subcategory":"Construction",
            "type":"Services"
        }
    ],
    "sg:phone":"+1 904 384 5770",
    "sg:postcode":"32205",
    "sg:province":"FL",
    "sg:tags":[
        "residential"
    ],
    "wof:name":"Olivers Repr Kit Installation",
    "wof:placetype":"venue"
},
  "geometry": {"coordinates":[-81.738142,30.294351],"type":"Point"}
}