{
  "type": "Feature",
  "properties": {
    "iso:country":"US",
    "sg:address":"2700 Meadowood Ct",
    "sg:city":"Fort Lauderdale",
    "sg:classifiers":[
        {
            "category":"Professional",
            "subcategory":"Engineering",
            "type":"Services"
        }
    ],
    "sg:phone":"+1 954 349 3291",
    "sg:postcode":"33332",
    "sg:province":"FL",
    "sg:tags":[
        "consulting"
    ],
    "wof:name":"Spectrum Development Corp",
    "wof:placetype":"venue"
},
  "geometry": {"coordinates":[-80.398833,26.08769],"type":"Point"}
}