{
  "type": "Feature",
  "properties": {
    "addr:full":"326 E Lake Rd Palm Harbor FL 34685",
    "addr:housenumber":"326",
    "addr:postcode":"34685",
    "addr:street":"E Lake Rd",
    "iso:country":"US",
    "sg:address":"326 E Lake Rd",
    "sg:city":"Palm Harbor",
    "sg:classifiers":[
        {
            "category":"Personal",
            "subcategory":"Beauty Salon",
            "type":"Services"
        }
    ],
    "sg:phone":"+1 727 787 4436",
    "sg:postcode":"34685",
    "sg:province":"FL",
    "wof:name":"Peter Anthony Salon",
    "wof:placetype":"venue"
},
  "geometry": {"coordinates":[-82.706524,28.06259],"type":"Point"}
}