{
  "type": "Feature",
  "properties": {
    "addr:full":"1130 SW Alcantarra Blvd Port Saint Lucie FL 34953",
    "addr:housenumber":"1130",
    "addr:postcode":"34953",
    "addr:street":"Sw Alcantarra Blvd",
    "iso:country":"US",
    "sg:address":"1130 SW Alcantarra Blvd",
    "sg:city":"Port Saint Lucie",
    "sg:classifiers":[
        {
            "category":"Building & Trades",
            "subcategory":"Construction",
            "type":"Services"
        }
    ],
    "sg:phone":"+1 772 336 1328",
    "sg:postcode":"34953",
    "sg:province":"FL",
    "sg:tags":[
        "contractor"
    ],
    "wof:name":"A & B Smless Gtters Downspouts",
    "wof:placetype":"venue"
},
  "geometry": {"coordinates":[-80.383109,27.239333],"type":"Point"}
}