{
  "type": "Feature",
  "properties": {
    "iso:country":"US",
    "sg:address":"571 Maitland Ave",
    "sg:city":"Altamonte Spgs",
    "sg:classifiers":[
        {
            "category":"Insurance",
            "subcategory":"Insurance Agent",
            "type":"Services"
        }
    ],
    "sg:phone":"+1 407 331 8891",
    "sg:postcode":"32701",
    "sg:province":"FL",
    "wof:name":"Clyde Biddle Insurance",
    "wof:placetype":"venue"
},
  "geometry": {"coordinates":[-81.36579500000001,28.652843],"type":"Point"}
}