{
  "type": "Feature",
  "properties": {
    "iso:country":"US",
    "sg:address":"5205 Spring Run Ave",
    "sg:city":"Orlando",
    "sg:classifiers":[
        {
            "category":"Travel",
            "subcategory":"Hotels & Motels",
            "type":"Entertainment"
        }
    ],
    "sg:phone":"+1 407 815 9795",
    "sg:postcode":"32819",
    "sg:province":"FL",
    "sg:tags":[
        "resort"
    ],
    "wof:name":"Ultimate Race Vacations Inc",
    "wof:placetype":"venue"
},
  "geometry": {"coordinates":[-81.484875,28.487115],"type":"Point"}
}