{
  "type": "Feature",
  "properties": {
    "iso:country":"US",
    "sg:address":"3164 Old Dixie Hwy",
    "sg:city":"Stuart",
    "sg:classifiers":[
        {
            "category":"Restaurant",
            "type":"Food & Drink"
        }
    ],
    "sg:phone":"+1 772 220 2440",
    "sg:postcode":"34994",
    "sg:province":"FL",
    "wof:name":"Montanyos Tacos",
    "wof:placetype":"venue"
},
  "geometry": {"coordinates":[-80.22005900000001,27.166117],"type":"Point"}
}