{
  "type": "Feature",
  "properties": {
    "addr:full":"8307 Double Branch Rd Tampa FL 33635",
    "addr:housenumber":"8307",
    "addr:postcode":"33635",
    "addr:street":"Double Branch Rd",
    "iso:country":"US",
    "sg:address":"8307 Double Branch Rd",
    "sg:city":"Tampa",
    "sg:classifiers":[
        {
            "category":"Organizations",
            "subcategory":"Religious Organization",
            "type":"Services"
        }
    ],
    "sg:phone":"+1 813 855 6161",
    "sg:postcode":"33635",
    "sg:province":"FL",
    "sg:tags":[
        "church"
    ],
    "wof:name":"Tampa Shores Baptist Church",
    "wof:placetype":"venue"
},
  "geometry": {"coordinates":[-82.636212,28.028192],"type":"Point"}
}