{
  "type": "Feature",
  "properties": {
    "addr:full":"500 Memorial Cir Ormond Beach FL 32174",
    "addr:housenumber":"500",
    "addr:postcode":"32174",
    "addr:street":"Memorial Cir",
    "iso:country":"US",
    "sg:address":"500 Memorial Cir",
    "sg:city":"Ormond Beach",
    "sg:classifiers":[
        {
            "category":"Health Services",
            "subcategory":"Doctor",
            "type":"Services"
        }
    ],
    "sg:phone":"+1 386 672 5881",
    "sg:postcode":"32174",
    "sg:province":"FL",
    "sg:tags":[
        "physician",
        "surgeon"
    ],
    "wof:name":"Suncoast RADIOLOGY",
    "wof:placetype":"venue"
},
  "geometry": {"coordinates":[-81.081643,29.283986],"type":"Point"}
}