{
  "type": "Feature",
  "properties": {
    "addr:full":"16034 SW 150th St Miami FL 33196",
    "addr:housenumber":"16034",
    "addr:postcode":"33196",
    "addr:street":"Sw 150Th St",
    "iso:country":"US",
    "sg:address":"16034 SW 150th St",
    "sg:city":"Miami",
    "sg:classifiers":[
        {
            "category":"Building & Trades",
            "subcategory":"Plumbing",
            "type":"Services"
        }
    ],
    "sg:phone":"+1 305 233 7600",
    "sg:postcode":"33196",
    "sg:province":"FL",
    "sg:tags":[
        "sprinkler"
    ],
    "wof:name":"Always Green Irrigation",
    "wof:placetype":"venue"
},
  "geometry": {"coordinates":[-80.45439399999999,25.626855],"type":"Point"}
}