{
  "type": "Feature",
  "properties": {
    "addr:full":"4500 Pga Blvd Palm Beach Gdns FL 33418",
    "addr:housenumber":"4500",
    "addr:postcode":"33418",
    "addr:street":"Pga Blvd Palm Beach Gdns",
    "iso:country":"US",
    "sg:address":"4500 Pga Blvd",
    "sg:city":"Palm Beach Gdns",
    "sg:classifiers":[
        {
            "category":"Building & Trades",
            "subcategory":"Construction",
            "type":"Services"
        }
    ],
    "sg:phone":"+1 561 627 2112",
    "sg:postcode":"33418",
    "sg:province":"FL",
    "sg:tags":[
        "home",
        "builder"
    ],
    "sg:website":"www.divosta.com",
    "wof:name":"Di Vosta Homes",
    "wof:placetype":"venue"
},
  "geometry": {"coordinates":[-80.107005,26.838281],"type":"Point"}
}