{
  "type": "Feature",
  "properties": {
    "addr:full":"4720 SW 83rd Ave Miami FL 33155",
    "addr:housenumber":"4720",
    "addr:postcode":"33155",
    "addr:street":"Sw 83Rd Ave",
    "iso:country":"US",
    "sg:address":"4720 SW 83rd Ave",
    "sg:city":"Miami",
    "sg:classifiers":[
        {
            "category":"Shopping",
            "subcategory":"Gifts & Souvenirs",
            "type":"Retail Goods"
        }
    ],
    "sg:phone":"+1 786 423 1240",
    "sg:postcode":"33155",
    "sg:province":"FL",
    "sg:tags":[
        "party",
        "favors",
        "supply"
    ],
    "wof:name":"Baby Showers Etc",
    "wof:placetype":"venue"
},
  "geometry": {"coordinates":[-80.329391,25.72558],"type":"Point"}
}