{
  "type": "Feature",
  "properties": {
    "iso:country":"US",
    "sg:address":"2500 Highland Ave",
    "sg:city":"Fort Myers",
    "sg:classifiers":[
        {
            "category":"Retail",
            "subcategory":"Car Wash",
            "type":"Services"
        }
    ],
    "sg:phone":"+1 239 633 1280",
    "sg:postcode":"33916",
    "sg:province":"FL",
    "sg:tags":[
        "automobile",
        "detail",
        "clean"
    ],
    "wof:name":"Robert Font's Auto Detailing",
    "wof:placetype":"venue"
},
  "geometry": {"coordinates":[-81.84209199999999,26.631211],"type":"Point"}
}