{
  "type": "Feature",
  "properties": {
    "iso:country":"US",
    "sg:address":"1 King St",
    "sg:city":"Saint Augustine",
    "sg:classifiers":[
        {
            "category":"Restaurant",
            "type":"Food & Drink"
        }
    ],
    "sg:menulink":"http://www.allmenus.com/fl/st-augustine/38114-a1a-ale-works/menu/",
    "sg:phone":"+1 904 829 2977",
    "sg:postcode":"32084",
    "sg:province":"FL",
    "sg:tags":[
        "american"
    ],
    "wof:name":"A1A Ale Works",
    "wof:placetype":"venue"
},
  "geometry": {"coordinates":[-81.31104999999999,29.892279],"type":"Point"}
}