{
  "type": "Feature",
  "properties": {
    "iso:country":"US",
    "sg:address":"2282 NW 21st Ter",
    "sg:city":"Miami",
    "sg:classifiers":[
        {
            "category":"Insurance",
            "subcategory":"Health Insurance",
            "type":"Services"
        }
    ],
    "sg:phone":"+1 305 634 7090",
    "sg:postcode":"33142",
    "sg:province":"FL",
    "sg:tags":[
        "market"
    ],
    "wof:name":"Select Source Nutrition Inc",
    "wof:placetype":"venue"
},
  "geometry": {"coordinates":[-80.233158,25.796066],"type":"Point"}
}