{
  "type": "Feature",
  "properties": {
    "addr:full":"6951 Springhill Rd Milton FL 32570",
    "addr:housenumber":"6951",
    "addr:postcode":"32570",
    "addr:street":"Springhill Rd",
    "iso:country":"US",
    "sg:address":"6951 Springhill Rd",
    "sg:city":"Milton",
    "sg:classifiers":[
        {
            "category":"Recreation",
            "subcategory":"Fishing",
            "type":"Entertainment"
        }
    ],
    "sg:phone":"+1 850 626 9496",
    "sg:postcode":"32570",
    "sg:province":"FL",
    "sg:tags":[
        "preserve",
        "hunting"
    ],
    "wof:name":"Branch Bass Hunting Club",
    "wof:placetype":"venue"
},
  "geometry": {"coordinates":[-87.026314,30.79141],"type":"Point"}
}