{
  "type": "Feature",
  "properties": {
    "iso:country":"US",
    "sg:address":"11252 SW 137th Ave",
    "sg:city":"Miami",
    "sg:classifiers":[
        {
            "category":"Insurance",
            "subcategory":"Insurance Agent",
            "type":"Services"
        }
    ],
    "sg:phone":"+1 305 352 5555",
    "sg:postcode":"33186",
    "sg:province":"FL",
    "wof:name":"State Farm Insurance",
    "wof:placetype":"venue"
},
  "geometry": {"coordinates":[-80.41582099999999,25.656354],"type":"Point"}
}