{
  "type": "Feature",
  "properties": {
    "addr:full":"19999 W Country Club Dr Aventura FL 33180",
    "addr:housenumber":"19999",
    "addr:postcode":"33180",
    "addr:street":"W Country Club Dr",
    "iso:country":"US",
    "sg:address":"19999 W Country Club Dr",
    "sg:city":"Aventura",
    "sg:classifiers":[
        {
            "category":"Shopping",
            "subcategory":"Computers & Home Electronics",
            "type":"Retail Goods"
        }
    ],
    "sg:phone":"+1 305 933 8426",
    "sg:postcode":"33180",
    "sg:province":"FL",
    "sg:tags":[
        "audio"
    ],
    "wof:name":"Audio Visual America Inc",
    "wof:placetype":"venue"
},
  "geometry": {"coordinates":[-80.139538,25.961071],"type":"Point"}
}