{
  "type": "Feature",
  "properties": {
    "addr:full":"348 N Congress Ave Boynton Beach FL 33426",
    "addr:housenumber":"348",
    "addr:postcode":"33426",
    "addr:street":"N Congress Ave",
    "iso:country":"US",
    "sg:address":"348 N Congress Ave",
    "sg:city":"Boynton Beach",
    "sg:classifiers":[
        {
            "category":"Travel",
            "subcategory":"Travel Agent",
            "type":"Entertainment"
        }
    ],
    "sg:phone":"+1 561 641 5763",
    "sg:postcode":"33426",
    "sg:province":"FL",
    "sg:tags":[
        "agency"
    ],
    "wof:name":"Seven Seas Travel",
    "wof:placetype":"venue"
},
  "geometry": {"coordinates":[-80.090429,26.528624],"type":"Point"}
}