{
  "type": "Feature",
  "properties": {
    "iso:country":"US",
    "sg:address":"8287 South Dixie Hwy",
    "sg:city":"Miami",
    "sg:classifiers":[
        {
            "category":"Restaurant",
            "type":"Food & Drink"
        }
    ],
    "sg:phone":"+1 305 663 2100",
    "sg:postcode":"33143",
    "sg:province":"FL",
    "sg:tags":[
        "new",
        "american",
        "french"
    ],
    "sg:website":"www.twochefsrestaurant.com/",
    "wof:name":"Two Chef's",
    "wof:placetype":"venue"
},
  "geometry": {"coordinates":[-80.302027,25.693924],"type":"Point"}
}