{
  "type": "Feature",
  "properties": {
    "addr:full":"10440 W Atlantic Blvd Pompano Beach FL 33071",
    "addr:housenumber":"10440",
    "addr:postcode":"33071",
    "addr:street":"W Atlantic Blvd",
    "iso:country":"US",
    "sg:address":"10440 W Atlantic Blvd",
    "sg:city":"Pompano Beach",
    "sg:classifiers":[
        {
            "category":"Insurance",
            "subcategory":"Insurance Agent",
            "type":"Services"
        }
    ],
    "sg:phone":"+1 954 753 5011",
    "sg:postcode":"33071",
    "sg:province":"FL",
    "wof:name":"George Catsimpiris",
    "wof:placetype":"venue"
},
  "geometry": {"coordinates":[-80.268714,26.240772],"type":"Point"}
}