{
  "type": "Feature",
  "properties": {
    "iso:country":"US",
    "sg:address":"6 N Melbourne St",
    "sg:city":"Beverly Hills",
    "sg:classifiers":[
        {
            "category":"Health Services",
            "subcategory":"Doctor",
            "type":"Services"
        }
    ],
    "sg:phone":"+1 352 746 1000",
    "sg:postcode":"34465",
    "sg:province":"FL",
    "sg:tags":[
        "medical"
    ],
    "wof:name":"Christopher Matyko MD",
    "wof:placetype":"venue"
},
  "geometry": {"coordinates":[-82.459514,28.927608],"type":"Point"}
}