{
  "type": "Feature",
  "properties": {
    "iso:country":"US",
    "sg:address":"7337 Camp Flowers Rd",
    "sg:city":"Youngstown",
    "sg:classifiers":[
        {
            "category":"Building & Trades",
            "subcategory":"Construction",
            "type":"Services"
        }
    ],
    "sg:phone":"+1 850 722 7935",
    "sg:postcode":"32466",
    "sg:province":"FL",
    "sg:tags":[
        "contractor"
    ],
    "wof:name":"Bushnell Drywall LLC",
    "wof:placetype":"venue"
},
  "geometry": {"coordinates":[-85.52731199999999,30.316727],"type":"Point"}
}