{
  "type": "Feature",
  "properties": {
    "addr:full":"3300 N Surf Rd Hollywood FL 33019",
    "addr:housenumber":"3300",
    "addr:postcode":"33019",
    "addr:street":"N Surf Rd",
    "iso:country":"US",
    "sg:address":"3300 N Surf Rd",
    "sg:city":"Hollywood",
    "sg:classifiers":[
        {
            "category":"Professional",
            "type":"Services"
        }
    ],
    "sg:phone":"+1 954 927 3230",
    "sg:postcode":"33019",
    "sg:province":"FL",
    "wof:name":"Tex TI International Inc",
    "wof:placetype":"venue"
},
  "geometry": {"coordinates":[-80.114666,26.032016],"type":"Point"}
}