{
  "type": "Feature",
  "properties": {
    "iso:country":"US",
    "sg:address":"1050 NW 21st St",
    "sg:city":"Miami",
    "sg:classifiers":[
        {
            "category":"Wholesale",
            "subcategory":"Machinery & Supplies",
            "type":"Manufacturing & Wholesale Goods"
        }
    ],
    "sg:phone":"+1 305 326 7766",
    "sg:postcode":"33127",
    "sg:province":"FL",
    "sg:tags":[
        "refrigeration",
        "equipment-parts"
    ],
    "wof:name":"Polar Bear Panel Company",
    "wof:placetype":"venue"
},
  "geometry": {"coordinates":[-80.21212,25.796],"type":"Point"}
}