{
  "type": "Feature",
  "properties": {
    "iso:country":"US",
    "sg:address":"35910 Unity Dr",
    "sg:city":"Fruitland Park",
    "sg:classifiers":[
        {
            "category":"Building & Trades",
            "subcategory":"Pest Control",
            "type":"Services"
        }
    ],
    "sg:phone":"+1 352 787 8463",
    "sg:postcode":"34731",
    "sg:province":"FL",
    "wof:name":"Cox Pest Control",
    "wof:placetype":"venue"
},
  "geometry": {"coordinates":[-81.876591,28.870329],"type":"Point"}
}