{
  "type": "Feature",
  "properties": {
    "addr:full":"210 SE 8th Ave Boynton Beach FL 33435",
    "addr:housenumber":"210",
    "addr:postcode":"33435",
    "addr:street":"Se 8Th Ave",
    "iso:country":"US",
    "sg:address":"210 SE 8th Ave",
    "sg:city":"Boynton Beach",
    "sg:classifiers":[
        {
            "category":"Wholesale",
            "subcategory":"Non-durable Goods",
            "type":"Manufacturing & Wholesale Goods"
        }
    ],
    "sg:phone":"+1 561 734 9665",
    "sg:postcode":"33435",
    "sg:province":"FL",
    "sg:tags":[
        "printing",
        "commercial"
    ],
    "wof:name":"Kluch Clothing Co",
    "wof:placetype":"venue"
},
  "geometry": {"coordinates":[-80.061184,26.520058],"type":"Point"}
}