{
  "type": "Feature",
  "properties": {
    "addr:full":"9127 Fort Caroline Rd Jacksonville FL 32225",
    "addr:housenumber":"9127",
    "addr:postcode":"32225",
    "addr:street":"Fort Caroline Rd",
    "iso:country":"US",
    "sg:address":"9127 Fort Caroline Rd",
    "sg:city":"Jacksonville",
    "sg:classifiers":[
        {
            "category":"Building & Trades",
            "subcategory":"Construction",
            "type":"Services"
        }
    ],
    "sg:phone":"+1 904 744 7490",
    "sg:postcode":"32225",
    "sg:province":"FL",
    "sg:tags":[
        "carpentry",
        "contractor"
    ],
    "wof:name":"WA Carpentry Inc",
    "wof:placetype":"venue"
},
  "geometry": {"coordinates":[-81.547028,30.356235],"type":"Point"}
}