{
  "type": "Feature",
  "properties": {
    "addr:full":"5613 Myrtice Ln Lakeland FL 33810",
    "addr:housenumber":"5613",
    "addr:postcode":"33810",
    "addr:street":"Myrtice Ln",
    "iso:country":"US",
    "sg:address":"5613 Myrtice Ln",
    "sg:city":"Lakeland",
    "sg:classifiers":[
        {
            "category":"Building & Trades",
            "subcategory":"Plumbing",
            "type":"Services"
        }
    ],
    "sg:phone":"+1 863 815 9797",
    "sg:postcode":"33810",
    "sg:province":"FL",
    "sg:tags":[
        "conditioning",
        "air",
        "system",
        "contractor"
    ],
    "wof:name":"J A Perkins Heating & Cooling",
    "wof:placetype":"venue"
},
  "geometry": {"coordinates":[-81.995469,28.117143],"type":"Point"}
}