{
  "type": "Feature",
  "properties": {
    "iso:country":"US",
    "sg:address":"7 Westward Dr",
    "sg:city":"Miami Springs",
    "sg:classifiers":[
        {
            "category":"Fast Food",
            "type":"Food & Drink"
        }
    ],
    "sg:phone":"+1 786 360 5347",
    "sg:postcode":"33166",
    "sg:province":"FL",
    "sg:tags":[
        "burger"
    ],
    "sg:website":"www.facebook.com/JrsGourmetburgers",
    "wof:name":"Jr's Gourmet Burger",
    "wof:placetype":"venue"
},
  "geometry": {"coordinates":[-80.28238399999999,25.821466],"type":"Point"}
}