{
  "type": "Feature",
  "properties": {
    "iso:country":"US",
    "sg:address":"190 112th Ave NE",
    "sg:city":"Saint Petersburg",
    "sg:classifiers":[
        {
            "category":"Wholesale",
            "subcategory":"Scrap",
            "type":"Manufacturing & Wholesale Goods"
        }
    ],
    "sg:phone":"+1 727 577 7113",
    "sg:postcode":"33716",
    "sg:province":"FL",
    "sg:tags":[
        "material"
    ],
    "wof:name":"Kelleher and Assoc Recycl Mgt",
    "wof:placetype":"venue"
},
  "geometry": {"coordinates":[-82.63732899999999,27.873823],"type":"Point"}
}