{
  "type": "Feature",
  "properties": {
    "iso:country":"US",
    "sg:address":"1418 Sopchoppy Hwy",
    "sg:city":"Sopchoppy",
    "sg:classifiers":[
        {
            "category":"Organizations",
            "subcategory":"Non-profit Organization",
            "type":"Services"
        }
    ],
    "sg:phone":"+1 850 926 2534",
    "sg:postcode":"32358",
    "sg:province":"FL",
    "sg:tags":[
        "fund",
        "raising"
    ],
    "wof:name":"Mt Trial Community Development Ctr",
    "wof:placetype":"venue"
},
  "geometry": {"coordinates":[-84.452939,30.068368],"type":"Point"}
}