{
  "type": "Feature",
  "properties": {
    "addr:full":"430 Coleman Dr Winter Haven FL 33884",
    "addr:housenumber":"430",
    "addr:postcode":"33884",
    "addr:street":"Coleman Dr",
    "iso:country":"US",
    "sg:address":"430 Coleman Dr",
    "sg:city":"Winter Haven",
    "sg:classifiers":[
        {
            "category":"Health Services",
            "subcategory":"Doctor",
            "type":"Services"
        }
    ],
    "sg:phone":"+1 863 294 3223",
    "sg:postcode":"33884",
    "sg:province":"FL",
    "sg:tags":[
        "medical"
    ],
    "wof:name":"Donald E Eason MD",
    "wof:placetype":"venue"
},
  "geometry": {"coordinates":[-81.664833,28.000939],"type":"Point"}
}