{
  "type": "Feature",
  "properties": {
    "iso:country":"US",
    "sg:address":"2162 NW 39th Ave",
    "sg:city":"Gainesville",
    "sg:classifiers":[
        {
            "category":"Restaurant",
            "type":"Food & Drink"
        }
    ],
    "sg:menulink":"http://www.allmenus.com/fl/gainesville/207024-sonic/menu/",
    "sg:phone":"+1 352 367 4461",
    "sg:postcode":"32605",
    "sg:province":"FL",
    "sg:tags":[
        "burger",
        "american"
    ],
    "wof:name":"Sonic",
    "wof:placetype":"venue"
},
  "geometry": {"coordinates":[-82.35391,29.688502],"type":"Point"}
}