{
  "type": "Feature",
  "properties": {
    "iso:country":"US",
    "sg:address":"2004 Hollywood Blvd",
    "sg:city":"Hollywood",
    "sg:classifiers":[
        {
            "category":"Recreation",
            "type":"Entertainment"
        }
    ],
    "sg:phone":"+1 954 925 7799",
    "sg:postcode":"33020",
    "sg:province":"FL",
    "sg:tags":[
        "parlor",
        "billiard"
    ],
    "wof:name":"Toby's Billiards",
    "wof:placetype":"venue"
},
  "geometry": {"coordinates":[-80.148753,26.011367],"type":"Point"}
}