{
  "type": "Feature",
  "properties": {
    "iso:country":"US",
    "sg:address":"1717 NW 17th Ave",
    "sg:city":"Miami",
    "sg:classifiers":[
        {
            "category":"Banks & Credit Unions",
            "subcategory":"Financial Services",
            "type":"Services"
        }
    ],
    "sg:phone":"+1 305 820 9677",
    "sg:postcode":"33125",
    "sg:province":"FL",
    "sg:tags":[
        "cashing",
        "check"
    ],
    "wof:name":"N Miami Check Cashing Inc",
    "wof:placetype":"venue"
},
  "geometry": {"coordinates":[-80.223164,25.791235],"type":"Point"}
}