{
  "type": "Feature",
  "properties": {
    "iso:country":"US",
    "sg:address":"1210 S Adams St",
    "sg:city":"Tallahassee",
    "sg:classifiers":[
        {
            "category":"Manufacturing",
            "subcategory":"Printing",
            "type":"Manufacturing & Wholesale Goods"
        }
    ],
    "sg:phone":"+1 850 224 8717",
    "sg:postcode":"32301",
    "sg:province":"FL",
    "sg:tags":[
        "lithographic",
        "commercial"
    ],
    "sg:website":"www.graphateria.com",
    "wof:name":"Graphateria",
    "wof:placetype":"venue"
},
  "geometry": {"coordinates":[-84.281947,30.431524],"type":"Point"}
}