{
  "type": "Feature",
  "properties": {
    "addr:full":"1200 Jacaranda Blvd Venice FL 34292",
    "addr:housenumber":"1200",
    "addr:postcode":"34292",
    "addr:street":"Jacaranda Blvd",
    "iso:country":"US",
    "sg:address":"1200 Jacaranda Blvd",
    "sg:city":"Venice",
    "sg:classifiers":[
        {
            "category":"Shopping",
            "subcategory":"Musical Instruments",
            "type":"Retail Goods"
        }
    ],
    "sg:phone":"+1 941 493 0887",
    "sg:postcode":"34292",
    "sg:province":"FL",
    "wof:name":"Fletcher Organ Studios",
    "wof:placetype":"venue"
},
  "geometry": {"coordinates":[-82.388886,27.080893],"type":"Point"}
}