{
  "type": "Feature",
  "properties": {
    "iso:country":"US",
    "sg:address":"13118 N Dale Mabry Hwy",
    "sg:city":"Tampa",
    "sg:classifiers":[
        {
            "category":"Real Estate",
            "subcategory":"Real Estate Agent",
            "type":"Services"
        }
    ],
    "sg:phone":"+1 813 960 4909",
    "sg:postcode":"33618",
    "sg:province":"FL",
    "sg:tags":[
        "investment"
    ],
    "wof:name":"W T Realty Inc",
    "wof:placetype":"venue"
},
  "geometry": {"coordinates":[-82.50601,28.06925],"type":"Point"}
}