{
  "type": "Feature",
  "properties": {
    "addr:full":"733 N 14th St Leesburg FL 34748",
    "addr:housenumber":"733",
    "addr:postcode":"34748",
    "addr:street":"N 14Th St",
    "iso:country":"US",
    "sg:address":"733 N 14th St",
    "sg:city":"Leesburg",
    "sg:classifiers":[
        {
            "category":"Building & Trades",
            "subcategory":"Equipment Rental",
            "type":"Services"
        }
    ],
    "sg:phone":"+1 352 435 5055",
    "sg:postcode":"34748",
    "sg:province":"FL",
    "sg:tags":[
        "yard"
    ],
    "wof:name":"Champion Rental Purchase Inc",
    "wof:placetype":"venue"
},
  "geometry": {"coordinates":[-81.887624,28.817744],"type":"Point"}
}