{
  "type": "Feature",
  "properties": {
    "iso:country":"US",
    "sg:address":"6597 US Hwy 331 S",
    "sg:city":"Defuniak Springs",
    "sg:classifiers":[
        {
            "category":"Building & Trades",
            "subcategory":"Construction",
            "type":"Services"
        }
    ],
    "sg:phone":"+1 850 892 6442",
    "sg:postcode":"32435",
    "sg:province":"FL",
    "sg:tags":[
        "contractor"
    ],
    "wof:name":"White Construction",
    "wof:placetype":"venue"
},
  "geometry": {"coordinates":[-86.115899,30.63324],"type":"Point"}
}