{
  "type": "Feature",
  "properties": {
    "addr:full":"1436 Schenley St Port Charlotte FL 33952",
    "addr:housenumber":"1436",
    "addr:postcode":"33952",
    "addr:street":"Schenley St",
    "iso:country":"US",
    "sg:address":"1436 Schenley St",
    "sg:city":"Port Charlotte",
    "sg:classifiers":[
        {
            "category":"Social Services",
            "type":"Services"
        }
    ],
    "sg:phone":"+1 941 625 2900",
    "sg:postcode":"33952",
    "sg:province":"FL",
    "wof:name":"Assoc In Cunseling Humn Servic",
    "wof:placetype":"venue"
},
  "geometry": {"coordinates":[-82.076768,27.005092],"type":"Point"}
}