{
  "type": "Feature",
  "properties": {
    "addr:full":"10745 SW 55th St Miami FL 33165",
    "addr:housenumber":"10745",
    "addr:postcode":"33165",
    "addr:street":"Sw 55Th St",
    "iso:country":"US",
    "sg:address":"10745 SW 55th St",
    "sg:city":"Miami",
    "sg:classifiers":[
        {
            "category":"Personal",
            "type":"Services"
        }
    ],
    "sg:phone":"+1 305 274 0551",
    "sg:postcode":"33165",
    "sg:province":"FL",
    "sg:tags":[
        "child",
        "care",
        "day",
        "facility"
    ],
    "wof:name":"Orosa Isabel Family Day Care",
    "wof:placetype":"venue"
},
  "geometry": {"coordinates":[-80.36726299999999,25.717764],"type":"Point"}
}