{
  "type": "Feature",
  "properties": {
    "iso:country":"US",
    "sg:address":"10496 Goodlette Rd",
    "sg:city":"Naples",
    "sg:classifiers":[
        {
            "category":"Building & Trades",
            "subcategory":"Construction",
            "type":"Services"
        }
    ],
    "sg:phone":"+1 239 592 5326",
    "sg:postcode":"34109",
    "sg:province":"FL",
    "sg:tags":[
        "contractor"
    ],
    "wof:name":"Encore Construction",
    "wof:placetype":"venue"
},
  "geometry": {"coordinates":[-81.789146,26.267042],"type":"Point"}
}