{
  "type": "Feature",
  "properties": {
    "addr:full":"2000 SW 71st Ter Davie FL 33317",
    "addr:housenumber":"2000",
    "addr:postcode":"33317",
    "addr:street":"Sw 71St Ter",
    "iso:country":"US",
    "sg:address":"2000 SW 71st Ter",
    "sg:city":"Davie",
    "sg:classifiers":[
        {
            "category":"Building & Trades",
            "subcategory":"Construction",
            "type":"Services"
        }
    ],
    "sg:phone":"+1 954 382 3491",
    "sg:postcode":"33317",
    "sg:province":"FL",
    "sg:tags":[
        "roofing",
        "contractor"
    ],
    "wof:name":"Century Roofing",
    "wof:placetype":"venue"
},
  "geometry": {"coordinates":[-80.241128,26.096317],"type":"Point"}
}