{
  "type": "Feature",
  "properties": {
    "iso:country":"US",
    "sg:address":"311 Park Place Blvd",
    "sg:city":"Clearwater",
    "sg:classifiers":[
        {
            "category":"Banks & Credit Unions",
            "subcategory":"Bank",
            "type":"Services"
        }
    ],
    "sg:phone":"+1 727 532 4343",
    "sg:postcode":"33759",
    "sg:province":"FL",
    "sg:tags":[
        "loan",
        "real estate"
    ],
    "sg:website":"www.1stfinancialmtg.com",
    "wof:name":"First Financial Mortgage",
    "wof:placetype":"venue"
},
  "geometry": {"coordinates":[-82.723631,27.965399],"type":"Point"}
}