{
  "type": "Feature",
  "properties": {
    "iso:country":"US",
    "sg:address":"3602 S Magnolia Ave",
    "sg:city":"Orlando",
    "sg:classifiers":[
        {
            "category":"Professional",
            "subcategory":"Engineering",
            "type":"Services"
        }
    ],
    "sg:phone":"+1 407 857 1831",
    "sg:postcode":"32806",
    "sg:province":"FL",
    "sg:tags":[
        "engineer"
    ],
    "sg:website":"http://www.MillwardEng.com",
    "wof:name":"Millward Engineering Inc",
    "wof:placetype":"venue"
},
  "geometry": {"coordinates":[-81.37529000000001,28.502473],"type":"Point"}
}