{
  "type": "Feature",
  "properties": {
    "addr:full":"19220 Immokalee Rd Naples FL 34120",
    "addr:postcode":"19220;34120",
    "addr:street":"Immokalee Rd",
    "iso:country":"US",
    "sg:address":"19220 Immokalee Rd",
    "sg:city":"Naples",
    "sg:classifiers":[
        {
            "category":"Building & Trades",
            "subcategory":"Construction",
            "type":"Services"
        }
    ],
    "sg:phone":"+1 239 450 7695",
    "sg:postcode":"34120",
    "sg:province":"FL",
    "sg:tags":[
        "house"
    ],
    "wof:name":"Big Island Builders",
    "wof:placetype":"venue"
},
  "geometry": {"coordinates":[-81.579176,26.366059],"type":"Point"}
}