{
  "type": "Feature",
  "properties": {
    "iso:country":"US",
    "sg:address":"2615 E Baldwin Rd",
    "sg:city":"Panama City",
    "sg:classifiers":[
        {
            "category":"Building & Trades",
            "subcategory":"Landscaping Services",
            "type":"Services"
        }
    ],
    "sg:phone":"+1 850 236 5296",
    "sg:postcode":"32405",
    "sg:province":"FL",
    "wof:name":"Panama Lawn of NW FL Inc",
    "wof:placetype":"venue"
},
  "geometry": {"coordinates":[-85.625506,30.202461],"type":"Point"}
}