{
  "type": "Feature",
  "properties": {
    "addr:full":"5239 Manatee Ave W Bradenton FL 34209",
    "addr:housenumber":"5239",
    "addr:postcode":"34209",
    "addr:street":"Manatee Ave W",
    "iso:country":"US",
    "sg:address":"5239 Manatee Ave W",
    "sg:city":"Bradenton",
    "sg:classifiers":[
        {
            "category":"Health Services",
            "subcategory":"Optometrist",
            "type":"Services"
        }
    ],
    "sg:phone":"+1 941 795 2020",
    "sg:postcode":"34209",
    "sg:province":"FL",
    "wof:name":"Eye Center Inc",
    "wof:placetype":"venue"
},
  "geometry": {"coordinates":[-82.613375,27.495993],"type":"Point"}
}