{
  "type": "Feature",
  "properties": {
    "addr:full":"132 Fairview E Jupiter FL 33469",
    "addr:housenumber":"132;e",
    "addr:postcode":"33469",
    "addr:street":"Fairview",
    "iso:country":"US",
    "sg:address":"132 Fairview E",
    "sg:city":"Jupiter",
    "sg:classifiers":[
        {
            "category":"Building & Trades",
            "subcategory":"Construction",
            "type":"Services"
        },
        {
            "category":"Real Estate",
            "subcategory":"Real Estate Operator",
            "type":"Services"
        }
    ],
    "sg:phone":"+1 561 575 1819",
    "sg:postcode":"33469",
    "sg:province":"FL",
    "sg:tags":[
        "patio",
        "deck",
        "cleaning",
        "restoration",
        "nonresidential"
    ],
    "wof:name":"Gulfstream Property Svcs LLC",
    "wof:placetype":"venue"
},
  "geometry": {"coordinates":[-80.111681,26.962499],"type":"Point"}
}