{
  "type": "Feature",
  "properties": {
    "iso:country":"US",
    "sg:address":"631 Mulberry Ave",
    "sg:city":"Kissimmee",
    "sg:classifiers":[
        {
            "category":"Manufacturing",
            "subcategory":"Signs",
            "type":"Manufacturing & Wholesale Goods"
        }
    ],
    "sg:phone":"+1 407 791 4654",
    "sg:postcode":"34747",
    "sg:province":"FL",
    "sg:tags":[
        "specialty",
        "mfg"
    ],
    "wof:name":"Your Name In Light",
    "wof:placetype":"venue"
},
  "geometry": {"coordinates":[-81.53660499999999,28.315152],"type":"Point"}
}