{
  "type": "Feature",
  "properties": {
    "iso:country":"US",
    "sg:address":"8901 Boggy Creek Rd",
    "sg:city":"Orlando",
    "sg:classifiers":[
        {
            "category":"Professional",
            "type":"Services"
        }
    ],
    "sg:phone":"+1 407 251 2280",
    "sg:postcode":"32824",
    "sg:province":"FL",
    "sg:tags":[
        "establishment"
    ],
    "wof:name":"Argo LLC",
    "wof:placetype":"venue"
},
  "geometry": {"coordinates":[-81.350033,28.432585],"type":"Point"}
}