{
  "type": "Feature",
  "properties": {
    "iso:country":"US",
    "sg:address":"6310 N Palafox St",
    "sg:city":"Pensacola",
    "sg:classifiers":[
        {
            "category":"Retail",
            "subcategory":"Auto Repair",
            "type":"Services"
        }
    ],
    "sg:phone":"+1 850 477 2713",
    "sg:postcode":"32503",
    "sg:province":"FL",
    "sg:tags":[
        "glass",
        "replacement"
    ],
    "wof:name":"Harmon Autoglass",
    "wof:placetype":"venue"
},
  "geometry": {"coordinates":[-87.247782,30.481336],"type":"Point"}
}