{
  "type": "Feature",
  "properties": {
    "iso:country":"US",
    "sg:address":"3555 S Falkenburg Rd",
    "sg:city":"Riverview",
    "sg:classifiers":[
        {
            "category":"Wholesale",
            "subcategory":"Motor Vehicles",
            "type":"Manufacturing & Wholesale Goods"
        },
        {
            "category":"Retail",
            "subcategory":"Auto Rental",
            "type":"Services"
        },
        {
            "category":"Travel",
            "subcategory":"Travel Agent",
            "type":"Entertainment"
        }
    ],
    "sg:phone":"+1 813 622 9390",
    "sg:postcode":"33578",
    "sg:province":"FL",
    "sg:tags":[
        "renting",
        "campers-wholesale",
        "leasing",
        "recreational",
        "trailer",
        "manufacturer"
    ],
    "sg:website":"http://www.premier-us.net",
    "wof:name":"Premier Trailer Leasing, Inc.",
    "wof:placetype":"venue"
},
  "geometry": {"coordinates":[-82.346965,27.915627],"type":"Point"}
}