{
  "type": "Feature",
  "properties": {
    "addr:full":"7345 SW 55th Ave Miami FL 33143",
    "addr:housenumber":"7345",
    "addr:postcode":"33143",
    "addr:street":"Sw 55Th Ave",
    "iso:country":"US",
    "sg:address":"7345 SW 55th Ave",
    "sg:city":"Miami",
    "sg:classifiers":[
        {
            "category":"Building & Trades",
            "subcategory":"Locksmith",
            "type":"Services"
        }
    ],
    "sg:phone":"+1 786 718 1419",
    "sg:postcode":"33143",
    "sg:province":"FL",
    "sg:tags":[
        "key"
    ],
    "wof:name":"123 24 7 Locksmith",
    "wof:placetype":"venue"
},
  "geometry": {"coordinates":[-80.28335,25.703136],"type":"Point"}
}