{
  "type": "Feature",
  "properties": {
    "iso:country":"US",
    "sg:address":"554 Jacksonville Dr",
    "sg:city":"Jacksonville Bch",
    "sg:classifiers":[
        {
            "category":"Professional",
            "subcategory":"Employment Agencies",
            "type":"Services"
        }
    ],
    "sg:phone":"+1 904 246 7500",
    "sg:postcode":"32250",
    "sg:province":"FL",
    "sg:tags":[
        "consultant",
        "search",
        "executive"
    ],
    "sg:website":"www.leadersinc.com",
    "wof:name":"Leaders Professional Recruitng",
    "wof:placetype":"venue"
},
  "geometry": {"coordinates":[-81.387585,30.260071],"type":"Point"}
}