{
  "type": "Feature",
  "properties": {
    "addr:full":"14540 State Rd 54 Odessa FL 33556",
    "addr:housenumber":"14540;54",
    "addr:postcode":"33556",
    "addr:street":"State Rd",
    "iso:country":"US",
    "sg:address":"14540 State Rd 54",
    "sg:city":"Odessa",
    "sg:classifiers":[
        {
            "category":"Organizations",
            "subcategory":"Community Association",
            "type":"Services"
        }
    ],
    "sg:phone":"+1 813 920 9023",
    "sg:postcode":"33556",
    "sg:province":"FL",
    "sg:tags":[
        "military"
    ],
    "wof:name":"Amvets Post 9",
    "wof:placetype":"venue"
},
  "geometry": {"coordinates":[-82.57588699999999,28.189593],"type":"Point"}
}