{
  "type": "Feature",
  "properties": {
    "addr:full":"731 Commerce Dr Venice FL 34292",
    "addr:housenumber":"731",
    "addr:postcode":"34292",
    "addr:street":"Commerce Dr",
    "iso:country":"US",
    "sg:address":"731 Commerce Dr",
    "sg:city":"Venice",
    "sg:classifiers":[
        {
            "category":"Wholesale",
            "subcategory":"Medical Equipment & Supplies",
            "type":"Manufacturing & Wholesale Goods"
        }
    ],
    "sg:phone":"+1 941 488 8909",
    "sg:postcode":"34292",
    "sg:province":"FL",
    "sg:tags":[
        "physician",
        "surgeon"
    ],
    "wof:name":"Hoveround Corp",
    "wof:placetype":"venue"
},
  "geometry": {"coordinates":[-82.378567,27.114866],"type":"Point"}
}