{
  "type": "Feature",
  "properties": {
    "iso:country":"US",
    "sg:address":"2475 Olsen Rd",
    "sg:city":"Haines City",
    "sg:classifiers":[
        {
            "category":"Building & Trades",
            "subcategory":"Construction",
            "type":"Services"
        }
    ],
    "sg:phone":"+1 863 419 8307",
    "sg:postcode":"33844",
    "sg:province":"FL",
    "sg:tags":[
        "contractor"
    ],
    "wof:name":"Britos Drywall",
    "wof:placetype":"venue"
},
  "geometry": {"coordinates":[-81.61126400000001,28.150383],"type":"Point"}
}