{
  "type": "Feature",
  "properties": {
    "iso:country":"US",
    "sg:address":"12113 SE US Hwy 441",
    "sg:city":"Belleview",
    "sg:classifiers":[
        {
            "category":"Personal",
            "subcategory":"Beauty Salon",
            "type":"Services"
        }
    ],
    "sg:phone":"+1 352 245 8181",
    "sg:postcode":"34420",
    "sg:province":"FL",
    "wof:name":"Kathleen's Cuttin Corner",
    "wof:placetype":"venue"
},
  "geometry": {"coordinates":[-82.03466899999999,29.046461],"type":"Point"}
}