{
  "type": "Feature",
  "properties": {
    "addr:full":"13664 State Hwy 84 Fort Lauderdale FL 33325",
    "addr:housenumber":"13664",
    "addr:postcode":"33325",
    "addr:street":"State Hwy 84",
    "iso:country":"US",
    "sg:address":"13664 State Hwy 84",
    "sg:city":"Fort Lauderdale",
    "sg:classifiers":[
        {
            "category":"Health Services",
            "subcategory":"Health Practitioner",
            "type":"Services"
        }
    ],
    "sg:phone":"+1 954 915 9944",
    "sg:postcode":"33325",
    "sg:province":"FL",
    "wof:name":"Shenandoah Chirpract & Inj Ctr",
    "wof:placetype":"venue"
},
  "geometry": {"coordinates":[-80.32208900000001,26.116877],"type":"Point"}
}