{
  "type": "Feature",
  "properties": {
    "iso:country":"US",
    "sg:address":"169 North Ct",
    "sg:city":"Miami",
    "sg:classifiers":[
        {
            "category":"Professional",
            "subcategory":"Accounting & Tax Preparation",
            "type":"Services"
        }
    ],
    "sg:phone":"+1 305 836 1040",
    "sg:postcode":"33147",
    "sg:province":"FL",
    "wof:name":"Accu Tax & Accounting",
    "wof:placetype":"venue"
},
  "geometry": {"coordinates":[-80.243599,25.849261],"type":"Point"}
}