{
  "type": "Feature",
  "properties": {
    "iso:country":"US",
    "sg:address":"10819 N US Hwy 441",
    "sg:city":"Ocala",
    "sg:classifiers":[
        {
            "category":"Restaurant",
            "type":"Food & Drink"
        }
    ],
    "sg:phone":"+1 352 694 3240",
    "sg:postcode":"34475",
    "sg:province":"FL",
    "sg:tags":[
        "eating"
    ],
    "wof:name":"Chicken Time Inc",
    "wof:placetype":"venue"
},
  "geometry": {"coordinates":[-82.151749,29.295952],"type":"Point"}
}