{
  "type": "Feature",
  "properties": {
    "addr:full":"1561 Cesery Blvd Jacksonville FL 32211",
    "addr:housenumber":"1561",
    "addr:postcode":"32211",
    "addr:street":"Cesery Blvd",
    "iso:country":"US",
    "sg:address":"1561 Cesery Blvd",
    "sg:city":"Jacksonville",
    "sg:classifiers":[
        {
            "category":"Shopping",
            "subcategory":"Books",
            "type":"Retail Goods"
        }
    ],
    "sg:phone":"+1 904 745 0058",
    "sg:postcode":"32211",
    "sg:province":"FL",
    "sg:tags":[
        "dealer"
    ],
    "wof:name":"Linda Lanier",
    "wof:placetype":"venue"
},
  "geometry": {"coordinates":[-81.59697300000001,30.336413],"type":"Point"}
}