{
  "type": "Feature",
  "properties": {
    "addr:full":"209 Miami Ave W Venice FL 34285",
    "addr:housenumber":"209",
    "addr:postcode":"34285",
    "addr:street":"Miami Ave W",
    "iso:country":"US",
    "sg:address":"209 Miami Ave W",
    "sg:city":"Venice",
    "sg:classifiers":[
        {
            "category":"Shopping",
            "subcategory":"Gifts & Souvenirs",
            "type":"Retail Goods"
        }
    ],
    "sg:phone":"+1 941 412 4383",
    "sg:postcode":"34285",
    "sg:province":"FL",
    "sg:tags":[
        "shop"
    ],
    "wof:name":"Islands Treasures",
    "wof:placetype":"venue"
},
  "geometry": {"coordinates":[-82.445921,27.098951],"type":"Point"}
}