{
  "type": "Feature",
  "properties": {
    "iso:country":"US",
    "sg:address":"5506 Metrowest Blvd",
    "sg:city":"Orlando",
    "sg:classifiers":[
        {
            "category":"Professional",
            "subcategory":"Management & Consulting",
            "type":"Services"
        }
    ],
    "sg:phone":"+1 407 370 6899",
    "sg:postcode":"32811",
    "sg:province":"FL",
    "wof:name":"Caoan Transportation Company",
    "wof:placetype":"venue"
},
  "geometry": {"coordinates":[-81.455388,28.514679],"type":"Point"}
}