{
  "type": "Feature",
  "properties": {
    "iso:country":"US",
    "sg:address":"5020 Glades Cut Off Rd",
    "sg:city":"Fort Pierce",
    "sg:classifiers":[
        {
            "category":"Wholesale",
            "subcategory":"Beer",
            "type":"Manufacturing & Wholesale Goods"
        }
    ],
    "sg:phone":"+1 772 461 9159",
    "sg:postcode":"34981",
    "sg:province":"FL",
    "wof:name":"Wm Thies & Sons Inc",
    "wof:placetype":"venue"
},
  "geometry": {"coordinates":[-80.37482,27.390387],"type":"Point"}
}