{
  "type": "Feature",
  "properties": {
    "addr:full":"240 W Caribbean Port Saint Lucie FL 34952",
    "addr:housenumber":"240",
    "addr:postcode":"34952",
    "addr:street":"W Caribbean",
    "iso:country":"US",
    "sg:address":"240 W Caribbean",
    "sg:city":"Port Saint Lucie",
    "sg:classifiers":[
        {
            "category":"Professional",
            "subcategory":"Business Services",
            "type":"Services"
        }
    ],
    "sg:phone":"+1 772 979 6823",
    "sg:postcode":"34952",
    "sg:province":"FL",
    "wof:name":"Robert Okon Home Inspections",
    "wof:placetype":"venue"
},
  "geometry": {"coordinates":[-80.29822,27.305122],"type":"Point"}
}