{
  "type": "Feature",
  "properties": {
    "iso:country":"US",
    "sg:address":"6225 NE 2nd Ave",
    "sg:city":"Miami",
    "sg:classifiers":[
        {
            "category":"Retail",
            "subcategory":"Auto Repair",
            "type":"Services"
        }
    ],
    "sg:phone":"+1 305 757 0034",
    "sg:postcode":"33138",
    "sg:province":"FL",
    "sg:tags":[
        "repairing",
        "automobile"
    ],
    "wof:name":"Jean Auto Repair",
    "wof:placetype":"venue"
},
  "geometry": {"coordinates":[-80.192172,25.8334],"type":"Point"}
}