{
  "type": "Feature",
  "properties": {
    "iso:country":"US",
    "sg:address":"7329 Alderwood Dr",
    "sg:city":"Sarasota",
    "sg:classifiers":[
        {
            "category":"Building & Trades",
            "subcategory":"Landscaping Services",
            "type":"Services"
        }
    ],
    "sg:phone":"+1 941 351 9200",
    "sg:postcode":"34243",
    "sg:province":"FL",
    "sg:tags":[
        "lawn",
        "garden"
    ],
    "wof:name":"Cpd Landscaping Inc",
    "wof:placetype":"venue"
},
  "geometry": {"coordinates":[-82.559466,27.409354],"type":"Point"}
}