{
  "type": "Feature",
  "properties": {
    "iso:country":"US",
    "sg:address":"540 State Hwy 434",
    "sg:city":"Altamonte Springs",
    "sg:classifiers":[
        {
            "category":"Manufacturing",
            "subcategory":"Furniture",
            "type":"Manufacturing & Wholesale Goods"
        }
    ],
    "sg:phone":"+1 407 682 0144",
    "sg:postcode":"32714",
    "sg:province":"FL",
    "sg:tags":[
        "home",
        "mfg",
        "custom"
    ],
    "wof:name":"Flynn John R Customs",
    "wof:placetype":"venue"
},
  "geometry": {"coordinates":[-81.417823,28.653809],"type":"Point"}
}