{
  "type": "Feature",
  "properties": {
    "addr:full":"1604 Idlewild Ave Green Cove Springs FL 32043",
    "addr:housenumber":"1604",
    "addr:postcode":"32043",
    "addr:street":"Idlewild Ave",
    "iso:country":"US",
    "sg:address":"1604 Idlewild Ave",
    "sg:city":"Green Cove Springs",
    "sg:classifiers":[
        {
            "category":"Restaurant",
            "type":"Food & Drink"
        }
    ],
    "sg:menulink":"http://www.allmenus.com/fl/green-cove-springs/237207-hungry-howies-pizza/menu/",
    "sg:phone":"+1 904 529 0008",
    "sg:postcode":"32043",
    "sg:province":"FL",
    "sg:tags":[
        "wrap",
        "american",
        "sandwich",
        "pizza"
    ],
    "wof:name":"Hungry Howie's Pizza",
    "wof:placetype":"venue"
},
  "geometry": {"coordinates":[-81.696269,29.985948],"type":"Point"}
}