{
  "type": "Feature",
  "properties": {
    "iso:country":"US",
    "sg:address":"1055 Ute St",
    "sg:city":"Labelle",
    "sg:classifiers":[
        {
            "category":"Retail",
            "subcategory":"Auto Repair",
            "type":"Services"
        }
    ],
    "sg:phone":"+1 863 674 0918",
    "sg:postcode":"33935",
    "sg:province":"FL",
    "sg:tags":[
        "body",
        "automobile",
        "painting"
    ],
    "wof:name":"A & A Auto & Truck Repair",
    "wof:placetype":"venue"
},
  "geometry": {"coordinates":[-81.44503899999999,26.746695],"type":"Point"}
}