{
  "type": "Feature",
  "properties": {
    "iso:country":"US",
    "sg:address":"635 Wiley Ct",
    "sg:city":"Merritt Island",
    "sg:classifiers":[
        {
            "category":"Building & Trades",
            "subcategory":"Construction",
            "type":"Services"
        }
    ],
    "sg:phone":"+1 321 459 1651",
    "sg:postcode":"32952",
    "sg:province":"FL",
    "sg:tags":[
        "house"
    ],
    "wof:name":"Darryl C Bratlie",
    "wof:placetype":"venue"
},
  "geometry": {"coordinates":[-80.673271,28.367382],"type":"Point"}
}