{
  "type": "Feature",
  "properties": {
    "addr:full":"1370 SE 7th Ave Pompano Beach FL 33060",
    "addr:housenumber":"1370",
    "addr:postcode":"33060",
    "addr:street":"Se 7Th Ave",
    "iso:country":"US",
    "sg:address":"1370 SE 7th Ave",
    "sg:city":"Pompano Beach",
    "sg:classifiers":[
        {
            "category":"Shopping",
            "subcategory":"Used Merchandise",
            "type":"Retail Goods"
        }
    ],
    "sg:phone":"+1 954 782 4056",
    "sg:postcode":"33060",
    "sg:province":"FL",
    "sg:tags":[
        "antique"
    ],
    "wof:name":"Antique Buyer Veronica Taber",
    "wof:placetype":"venue"
},
  "geometry": {"coordinates":[-80.111743,26.21527],"type":"Point"}
}