{
  "type": "Feature",
  "properties": {
    "iso:country":"US",
    "sg:address":"13960 Stringfellow Rd",
    "sg:city":"Bokeelia",
    "sg:classifiers":[
        {
            "category":"Government",
            "subcategory":"Office",
            "type":"Public Place"
        }
    ],
    "sg:phone":"+1 239 283 2929",
    "sg:postcode":"33922",
    "sg:province":"FL",
    "wof:name":"Charlotte Harbor Aquatic-State",
    "wof:placetype":"venue"
},
  "geometry": {"coordinates":[-82.139493,26.663267],"type":"Point"}
}