{
  "type": "Feature",
  "properties": {
    "iso:country":"US",
    "sg:address":"613 School House Rd",
    "sg:city":"Lakeland",
    "sg:classifiers":[
        {
            "category":"Building & Trades",
            "subcategory":"Construction",
            "type":"Services"
        }
    ],
    "sg:phone":"+1 863 646 7665",
    "sg:postcode":"33813",
    "sg:province":"FL",
    "sg:tags":[
        "designer",
        "dealer",
        "pool",
        "swimming"
    ],
    "sg:website":"www.caribbeanpoolsonline.com",
    "wof:name":"Caribbean Pools",
    "wof:placetype":"venue"
},
  "geometry": {"coordinates":[-81.964671,27.967682],"type":"Point"}
}