{
  "type": "Feature",
  "properties": {
    "iso:country":"US",
    "sg:address":"2304 Eleuthera Pl",
    "sg:city":"Seffner",
    "sg:classifiers":[
        {
            "category":"Shopping",
            "subcategory":"Catalog Store",
            "type":"Retail Goods"
        }
    ],
    "sg:phone":"+1 813 684 3894",
    "sg:postcode":"33584",
    "sg:province":"FL",
    "sg:tags":[
        "mail",
        "house"
    ],
    "wof:name":"Elegance In Bronze",
    "wof:placetype":"venue"
},
  "geometry": {"coordinates":[-82.28264799999999,27.975356],"type":"Point"}
}