{
  "type": "Feature",
  "properties": {
    "iso:country":"US",
    "sg:address":"445 S US Hwy 301",
    "sg:city":"Sumterville",
    "sg:classifiers":[
        {
            "category":"Government",
            "subcategory":"Post Office",
            "type":"Public Place"
        }
    ],
    "sg:phone":"+1 352 793 4397",
    "sg:postcode":"33585",
    "sg:province":"FL",
    "wof:name":"US Post Office",
    "wof:placetype":"venue"
},
  "geometry": {"coordinates":[-82.06211,28.749517],"type":"Point"}
}