{
  "type": "Feature",
  "properties": {
    "addr:full":"4930 Distribution Dr Tampa FL 33605",
    "addr:housenumber":"4930",
    "addr:postcode":"33605",
    "addr:street":"Distribution Dr",
    "iso:country":"US",
    "sg:address":"4930 Distribution Dr",
    "sg:city":"Tampa",
    "sg:classifiers":[
        {
            "category":"Wholesale",
            "subcategory":"Groceries",
            "type":"Manufacturing & Wholesale Goods"
        }
    ],
    "sg:phone":"+1 813 248 5680",
    "sg:postcode":"33605",
    "sg:province":"FL",
    "sg:tags":[
        "beverage"
    ],
    "wof:name":"Specialty Beverage Distr",
    "wof:placetype":"venue"
},
  "geometry": {"coordinates":[-82.40419799999999,27.956798],"type":"Point"}
}