{
  "type": "Feature",
  "properties": {
    "iso:country":"US",
    "sg:address":"6131 SE 85th Ln",
    "sg:city":"Ocala",
    "sg:classifiers":[
        {
            "category":"Farming",
            "subcategory":"Fish & Marine Products",
            "type":"Manufacturing & Wholesale Goods"
        }
    ],
    "sg:phone":"+1 352 245 3680",
    "sg:postcode":"34472",
    "sg:province":"FL",
    "sg:tags":[
        "fishing"
    ],
    "wof:name":"Cod Stan E Brown Inc",
    "wof:placetype":"venue"
},
  "geometry": {"coordinates":[-82.047641,29.097929],"type":"Point"}
}