{
  "type": "Feature",
  "properties": {
    "addr:full":"2201 N East Coast St Lake Worth FL 33460",
    "addr:housenumber":"2201",
    "addr:postcode":"33460",
    "addr:street":"N East Coast St",
    "iso:country":"US",
    "sg:address":"2201 N East Coast St",
    "sg:city":"Lake Worth",
    "sg:classifiers":[
        {
            "category":"Food & Beverages",
            "subcategory":"Groceries & Convenience Stores",
            "type":"Retail Goods"
        }
    ],
    "sg:phone":"+1 561 547 6470",
    "sg:postcode":"33460",
    "sg:province":"FL",
    "wof:name":"El Buty Grocery",
    "wof:placetype":"venue"
},
  "geometry": {"coordinates":[-80.05830400000001,26.641306],"type":"Point"}
}