{
  "type": "Feature",
  "properties": {
    "addr:full":"2983 N Powerline Rd Pompano Beach FL 33069",
    "addr:housenumber":"2983",
    "addr:postcode":"33069",
    "addr:street":"N Powerline Rd",
    "iso:country":"US",
    "sg:address":"2983 N Powerline Rd",
    "sg:city":"Pompano Beach",
    "sg:classifiers":[
        {
            "category":"Building & Trades",
            "subcategory":"Construction",
            "type":"Services"
        }
    ],
    "sg:phone":"+1 954 978 8000",
    "sg:postcode":"33069",
    "sg:province":"FL",
    "sg:tags":[
        "general",
        "contractor"
    ],
    "wof:name":"Cmsi",
    "wof:placetype":"venue"
},
  "geometry": {"coordinates":[-80.15196899999999,26.266996],"type":"Point"}
}