{
  "type": "Feature",
  "properties": {
    "iso:country":"US",
    "sg:address":"2600 Dog Track Rd",
    "sg:city":"Pensacola",
    "sg:classifiers":[
        {
            "category":"Shopping",
            "subcategory":"Clothing, Apparel, & Fashions",
            "type":"Retail Goods"
        }
    ],
    "sg:phone":"+1 850 453 1009",
    "sg:postcode":"32506",
    "sg:province":"FL",
    "sg:tags":[
        "alteration"
    ],
    "wof:name":"KAT-Lee-Mae Sewing Alterations",
    "wof:placetype":"venue"
},
  "geometry": {"coordinates":[-87.343864,30.36553],"type":"Point"}
}