{
  "type": "Feature",
  "properties": {
    "addr:full":"2742 Elkcam Blvd Deltona FL 32738",
    "addr:housenumber":"2742",
    "addr:postcode":"32738",
    "addr:street":"Elkcam Blvd",
    "iso:country":"US",
    "sg:address":"2742 Elkcam Blvd",
    "sg:city":"Deltona",
    "sg:classifiers":[
        {
            "category":"Restaurant",
            "type":"Food & Drink"
        },
        {
            "category":"Food & Beverages",
            "subcategory":"Bakery",
            "type":"Retail Goods"
        }
    ],
    "sg:phone":"+1 386 774 4841",
    "sg:postcode":"32738",
    "sg:province":"FL",
    "sg:tags":[
        "sandwich",
        "pizza"
    ],
    "wof:name":"2 Guys Pizza Subs 2 Inc",
    "wof:placetype":"venue"
},
  "geometry": {"coordinates":[-81.190448,28.926613],"type":"Point"}
}