{
  "type": "Feature",
  "properties": {
    "iso:country":"US",
    "sg:address":"1816 NE 22nd St",
    "sg:city":"Cape Coral",
    "sg:classifiers":[
        {
            "category":"Building & Trades",
            "subcategory":"Construction",
            "type":"Services"
        }
    ],
    "sg:phone":"+1 239 242 9942",
    "sg:postcode":"33909",
    "sg:province":"FL",
    "sg:tags":[
        "grading",
        "contractor"
    ],
    "wof:name":"Landmark Bobcat Svc",
    "wof:placetype":"venue"
},
  "geometry": {"coordinates":[-81.93770000000001,26.69245],"type":"Point"}
}