{
  "type": "Feature",
  "properties": {
    "addr:full":"313 Riverside Dr Wauchula FL 33873",
    "addr:housenumber":"313",
    "addr:postcode":"33873",
    "addr:street":"Riverside Dr",
    "iso:country":"US",
    "sg:address":"313 Riverside Dr",
    "sg:city":"Wauchula",
    "sg:classifiers":[
        {
            "category":"Building & Trades",
            "subcategory":"Pest Control",
            "type":"Services"
        }
    ],
    "sg:phone":"+1 863 773 5969",
    "sg:postcode":"33873",
    "sg:province":"FL",
    "wof:name":"Heartland Bug Doctor",
    "wof:placetype":"venue"
},
  "geometry": {"coordinates":[-81.796702,27.554458],"type":"Point"}
}