{
  "type": "Feature",
  "properties": {
    "iso:country":"US",
    "sg:address":"1020 E. Lafayette St. Suite 117",
    "sg:city":"Tallahassee",
    "sg:classifiers":[
        {
            "category":"Professional",
            "subcategory":"Lawyer & Legal Services",
            "type":"Services"
        }
    ],
    "sg:phone":"+1 850 728 8734",
    "sg:postcode":"32301",
    "sg:province":"FL",
    "sg:tags":[
        "attorney",
        "law",
        "duo",
        "violence",
        "domestic",
        "juvenile",
        "immigration",
        "criminal",
        "dwi"
    ],
    "wof:name":"The Law Office of Aisha N. Chaney, PLLC",
    "wof:placetype":"venue"
},
  "geometry": {"coordinates":[-84.267206,30.436493],"type":"Point"}
}