{
  "type": "Feature",
  "properties": {
    "iso:country":"US",
    "sg:address":"312 S Bumby Ave",
    "sg:city":"Orlando",
    "sg:classifiers":[
        {
            "category":"Personal",
            "type":"Services"
        }
    ],
    "sg:phone":"+1 407 897 7172",
    "sg:postcode":"32803",
    "sg:province":"FL",
    "wof:name":"Oneway Valet Inc",
    "wof:placetype":"venue"
},
  "geometry": {"coordinates":[-81.351924,28.538789],"type":"Point"}
}