{
  "type": "Feature",
  "properties": {
    "addr:full":"7281 Sunshine Grove Rd Brooksville FL 34613",
    "addr:housenumber":"7281",
    "addr:postcode":"34613",
    "addr:street":"Sunshine Grove Rd",
    "iso:country":"US",
    "sg:address":"7281 Sunshine Grove Rd",
    "sg:city":"Brooksville",
    "sg:classifiers":[
        {
            "category":"Real Estate",
            "subcategory":"Real Estate Services",
            "type":"Services"
        },
        {
            "category":"Real Estate",
            "subcategory":"Real Estate Agent",
            "type":"Services"
        }
    ],
    "sg:phone":"+1 352 592 1110",
    "sg:postcode":"34613",
    "sg:province":"FL",
    "sg:tags":[
        "buyer",
        "management",
        "broker"
    ],
    "wof:name":"R A Fessler Inc",
    "wof:placetype":"venue"
},
  "geometry": {"coordinates":[-82.499903,28.535656],"type":"Point"}
}