{
  "type": "Feature",
  "properties": {
    "iso:country":"US",
    "sg:address":"3132 Beach Blvd",
    "sg:city":"Jacksonville",
    "sg:classifiers":[
        {
            "category":"Personal",
            "subcategory":"Barber",
            "type":"Services"
        }
    ],
    "sg:phone":"+1 904 398 7118",
    "sg:postcode":"32207",
    "sg:province":"FL",
    "sg:tags":[
        "shop"
    ],
    "wof:name":"Jean T Proulx Inc",
    "wof:placetype":"venue"
},
  "geometry": {"coordinates":[-81.63305200000001,30.304454],"type":"Point"}
}