{
  "type": "Feature",
  "properties": {
    "iso:country":"US",
    "sg:address":"285 N Lakeview Blvd",
    "sg:city":"Cocoa",
    "sg:classifiers":[
        {
            "category":"Wholesale",
            "subcategory":"Auto Parts",
            "type":"Manufacturing & Wholesale Goods"
        }
    ],
    "sg:phone":"+1 321 638 4030",
    "sg:postcode":"32926",
    "sg:province":"FL",
    "sg:tags":[
        "supply"
    ],
    "wof:name":"Central Truck Parts Inc",
    "wof:placetype":"venue"
},
  "geometry": {"coordinates":[-80.78591,28.359406],"type":"Point"}
}