{
  "type": "Feature",
  "properties": {
    "addr:full":"327 Kepner Dr NE Fort Walton Bch FL 32548",
    "addr:housenumber":"327",
    "addr:postcode":"32548",
    "addr:street":"Kepner Dr Ne Fort",
    "iso:country":"US",
    "sg:address":"327 Kepner Dr NE",
    "sg:city":"Fort Walton Bch",
    "sg:classifiers":[
        {
            "category":"Building & Trades",
            "subcategory":"Construction",
            "type":"Services"
        }
    ],
    "sg:phone":"+1 850 243 0138",
    "sg:postcode":"32548",
    "sg:province":"FL",
    "sg:tags":[
        "tile",
        "dealer"
    ],
    "wof:name":"C & M Tile",
    "wof:placetype":"venue"
},
  "geometry": {"coordinates":[-86.591459,30.413023],"type":"Point"}
}