{
  "type": "Feature",
  "properties": {
    "iso:country":"US",
    "sg:address":"2410 Hollywood Blvd",
    "sg:city":"Hollywood",
    "sg:classifiers":[
        {
            "category":"Real Estate",
            "subcategory":"Real Estate Agent",
            "type":"Services"
        }
    ],
    "sg:phone":"+1 954 927 0866",
    "sg:postcode":"33020",
    "sg:province":"FL",
    "wof:name":"Senticore",
    "wof:placetype":"venue"
},
  "geometry": {"coordinates":[-80.15777199999999,26.011129],"type":"Point"}
}