{
  "type": "Feature",
  "properties": {
    "addr:full":"8360 NW 70th St Miami FL 33166",
    "addr:housenumber":"8360",
    "addr:postcode":"33166",
    "addr:street":"Nw 70Th St",
    "iso:country":"US",
    "sg:address":"8360 NW 70th St",
    "sg:city":"Miami",
    "sg:classifiers":[
        {
            "category":"Wholesale",
            "subcategory":"Groceries",
            "type":"Manufacturing & Wholesale Goods"
        }
    ],
    "sg:phone":"+1 305 591 3211",
    "sg:postcode":"33166",
    "sg:province":"FL",
    "sg:tags":[
        "distributor"
    ],
    "wof:name":"Los Andes Food Products Inc",
    "wof:placetype":"venue"
},
  "geometry": {"coordinates":[-80.33121300000001,25.837003],"type":"Point"}
}