{
  "type": "Feature",
  "properties": {
    "addr:full":"5562 Central Ave St Petersburg FL 33707",
    "addr:housenumber":"5562",
    "addr:postcode":"33707",
    "addr:street":"Central Ave",
    "iso:country":"US",
    "sg:address":"5562 Central Ave",
    "sg:city":"St Petersburg",
    "sg:classifiers":[
        {
            "category":"Shopping",
            "type":"Retail Goods"
        }
    ],
    "sg:phone":"+1 727 341 0540",
    "sg:postcode":"33707",
    "sg:province":"FL",
    "sg:tags":[
        "picture",
        "frame"
    ],
    "wof:name":"Poor Richard's",
    "wof:placetype":"venue"
},
  "geometry": {"coordinates":[-82.708614,27.770834],"type":"Point"}
}