{
  "type": "Feature",
  "properties": {
    "iso:country":"US",
    "sg:address":"16 SW 8th Ct",
    "sg:city":"Delray Beach",
    "sg:classifiers":[
        {
            "category":"Building & Trades",
            "subcategory":"Construction",
            "type":"Services"
        }
    ],
    "sg:phone":"+1 561 276 7240",
    "sg:postcode":"33444",
    "sg:province":"FL",
    "sg:tags":[
        "roofing",
        "contractor"
    ],
    "wof:name":"Wright's Way Roofing",
    "wof:placetype":"venue"
},
  "geometry": {"coordinates":[-80.074876,26.449179],"type":"Point"}
}