{
  "type": "Feature",
  "properties": {
    "addr:full":"2416 45th St Vero Beach FL 32967",
    "addr:housenumber":"2416",
    "addr:postcode":"32967",
    "addr:street":"45Th St",
    "iso:country":"US",
    "sg:address":"2416 45th St",
    "sg:city":"Vero Beach",
    "sg:classifiers":[
        {
            "category":"Food & Beverages",
            "subcategory":"Groceries & Convenience Stores",
            "type":"Retail Goods"
        }
    ],
    "sg:phone":"+1 772 567 3999",
    "sg:postcode":"32967",
    "sg:province":"FL",
    "wof:name":"Martin Luther King Plaza",
    "wof:placetype":"venue"
},
  "geometry": {"coordinates":[-80.41073299999999,27.675034],"type":"Point"}
}