{
  "type": "Feature",
  "properties": {
    "addr:full":"353 N Seaboard Rd Miami FL 33169",
    "addr:housenumber":"353",
    "addr:postcode":"33169",
    "addr:street":"N Seaboard Rd",
    "iso:country":"US",
    "sg:address":"353 N Seaboard Rd",
    "sg:city":"Miami",
    "sg:classifiers":[
        {
            "category":"Building & Trades",
            "subcategory":"Equipment Rental",
            "type":"Services"
        }
    ],
    "sg:phone":"+1 305 652 7888",
    "sg:postcode":"33169",
    "sg:province":"FL",
    "sg:tags":[
        "leasing",
        "equipment-renting",
        "audio-visual"
    ],
    "sg:website":"http://www.showtechnologyinc.com",
    "wof:name":"Show Technology Inc",
    "wof:placetype":"venue"
},
  "geometry": {"coordinates":[-80.20834499999999,25.929517],"type":"Point"}
}