{
  "type": "Feature",
  "properties": {
    "iso:country":"US",
    "sg:address":"6503 E Broadway Ave",
    "sg:city":"Tampa",
    "sg:classifiers":[
        {
            "category":"Insurance",
            "subcategory":"Hazard Insurance",
            "type":"Services"
        }
    ],
    "sg:phone":"+1 813 622 7232",
    "sg:postcode":"33619",
    "sg:province":"FL",
    "sg:tags":[
        "bond"
    ],
    "wof:name":"John Caldwell Bail Bonds",
    "wof:placetype":"venue"
},
  "geometry": {"coordinates":[-82.381215,27.966687],"type":"Point"}
}