{
  "type": "Feature",
  "properties": {
    "iso:country":"US",
    "sg:address":"15600 NW 32nd Ave",
    "sg:city":"Opa Locka",
    "sg:classifiers":[
        {
            "category":"Education",
            "subcategory":"School",
            "type":"Public Place"
        }
    ],
    "sg:phone":"+1 305 624 8534",
    "sg:postcode":"33054",
    "sg:province":"FL",
    "sg:tags":[
        "high",
        "middle",
        "elementary"
    ],
    "wof:name":"Monsignor Pace High School",
    "wof:placetype":"venue"
},
  "geometry": {"coordinates":[-80.252402,25.915914],"type":"Point"}
}