{
  "type": "Feature",
  "properties": {
    "iso:country":"US",
    "sg:address":"5750 Banos Ave",
    "sg:city":"Cocoa",
    "sg:classifiers":[
        {
            "category":"Arts & Performance",
            "subcategory":"Theater",
            "type":"Entertainment"
        }
    ],
    "sg:phone":"+1 321 255 2844",
    "sg:postcode":"32927",
    "sg:province":"FL",
    "sg:tags":[
        "group"
    ],
    "wof:name":"A A A A Clown Call Q-Tee",
    "wof:placetype":"venue"
},
  "geometry": {"coordinates":[-80.819193,28.469662],"type":"Point"}
}