{
  "type": "Feature",
  "properties": {
    "addr:full":"833 NE 3rd Pl Hialeah FL 33010",
    "addr:housenumber":"833",
    "addr:postcode":"33010",
    "addr:street":"Ne 3Rd Pl",
    "iso:country":"US",
    "sg:address":"833 NE 3rd Pl",
    "sg:city":"Hialeah",
    "sg:classifiers":[
        {
            "category":"Autos & Motor Vehicles",
            "subcategory":"Boat Sales",
            "type":"Retail Goods"
        }
    ],
    "sg:phone":"+1 305 947 1459",
    "sg:postcode":"33010",
    "sg:province":"FL",
    "sg:tags":[
        "dealer",
        "sales"
    ],
    "sg:website":"www.sunpowermarine.com",
    "wof:name":"Sun Power Diesel & Marine",
    "wof:placetype":"venue"
},
  "geometry": {"coordinates":[-80.26384400000001,25.825517],"type":"Point"}
}