{
  "type": "Feature",
  "properties": {
    "iso:country":"US",
    "sg:address":"1 Coke Rd",
    "sg:city":"Saint Augustine",
    "sg:classifiers":[
        {
            "category":"Home & Garden",
            "subcategory":"Building Materials",
            "type":"Retail Goods"
        }
    ],
    "sg:phone":"+1 904 825 1100",
    "sg:postcode":"32086",
    "sg:province":"FL",
    "sg:tags":[
        "lumber"
    ],
    "wof:name":"Manning of St Augustine",
    "wof:placetype":"venue"
},
  "geometry": {"coordinates":[-81.31853099999999,29.864825],"type":"Point"}
}