{
  "type": "Feature",
  "properties": {
    "iso:country":"US",
    "sg:address":"14051 E Co Rd 316",
    "sg:city":"Fort Mc Coy",
    "sg:classifiers":[
        {
            "category":"Professional",
            "type":"Services"
        }
    ],
    "sg:phone":"+1 352 236 3685",
    "sg:postcode":"32134",
    "sg:province":"FL",
    "sg:tags":[
        "establishment"
    ],
    "wof:name":"Ft Mc Coy Eureka Community",
    "wof:placetype":"venue"
},
  "geometry": {"coordinates":[-81.92914500000001,29.371355],"type":"Point"}
}