{
  "type": "Feature",
  "properties": {
    "iso:country":"US",
    "sg:address":"271 Brian Cir",
    "sg:city":"Mary Esther",
    "sg:classifiers":[
        {
            "category":"Building & Trades",
            "subcategory":"Construction",
            "type":"Services"
        }
    ],
    "sg:phone":"+1 850 243 5701",
    "sg:postcode":"32569",
    "sg:province":"FL",
    "sg:tags":[
        "house"
    ],
    "wof:name":"R J Home Repair Inc",
    "wof:placetype":"venue"
},
  "geometry": {"coordinates":[-86.66422300000001,30.416937],"type":"Point"}
}