{
  "type": "Feature",
  "properties": {
    "iso:country":"US",
    "sg:address":"201 SE 6th Ct",
    "sg:city":"Pompano Beach",
    "sg:classifiers":[
        {
            "category":"Building & Trades",
            "subcategory":"Landscaping Services",
            "type":"Services"
        }
    ],
    "sg:phone":"+1 954 784 6774",
    "sg:postcode":"33060",
    "sg:province":"FL",
    "wof:name":"Triumph Lawn Landscape",
    "wof:placetype":"venue"
},
  "geometry": {"coordinates":[-80.11991999999999,26.221351],"type":"Point"}
}