{
  "type": "Feature",
  "properties": {
    "addr:full":"11341 S Dixie Hwy Miami FL 33156",
    "addr:housenumber":"11341",
    "addr:postcode":"33156",
    "addr:street":"S Dixie Hwy",
    "iso:country":"US",
    "sg:address":"11341 S Dixie Hwy",
    "sg:city":"Miami",
    "sg:classifiers":[
        {
            "category":"Banks & Credit Unions",
            "subcategory":"Bank",
            "type":"Services"
        }
    ],
    "sg:phone":"+1 305 235 4922",
    "sg:postcode":"33156",
    "sg:province":"FL",
    "wof:name":"Citibank N A",
    "wof:placetype":"venue"
},
  "geometry": {"coordinates":[-80.323815,25.665404],"type":"Point"}
}