{
  "type": "Feature",
  "properties": {
    "iso:country":"US",
    "sg:address":"115 Elm Ct",
    "sg:city":"Lakeland",
    "sg:classifiers":[
        {
            "category":"Manufacturing",
            "subcategory":"Tools & Machinery",
            "type":"Manufacturing & Wholesale Goods"
        },
        {
            "category":"Wholesale",
            "subcategory":"Machinery & Supplies",
            "type":"Manufacturing & Wholesale Goods"
        }
    ],
    "sg:phone":"+1 863 644 1668",
    "sg:postcode":"33813",
    "sg:province":"FL",
    "sg:tags":[
        "equipment-wholesale",
        "equipment",
        "material",
        "handling",
        "manufacturer"
    ],
    "wof:name":"Oglesby & Associates Inc",
    "wof:placetype":"venue"
},
  "geometry": {"coordinates":[-81.958286,27.951427],"type":"Point"}
}