{
  "type": "Feature",
  "properties": {
    "addr:full":"5755 W Flagler St Ste 110 Miami FL 33144",
    "addr:housenumber":"5755",
    "addr:postcode":"33144",
    "addr:street":"W Flagler St Ste 110",
    "iso:country":"US",
    "sg:address":"5755 W Flagler St Ste 110",
    "sg:city":"Miami",
    "sg:classifiers":[
        {
            "category":"Shopping",
            "subcategory":"Department Store",
            "type":"Retail Goods"
        },
        {
            "category":"Shopping",
            "subcategory":"Pharmacy",
            "type":"Retail Goods"
        }
    ],
    "sg:phone":"+1 305 264 3122",
    "sg:postcode":"33144",
    "sg:province":"FL",
    "sg:tags":[
        "drugstore"
    ],
    "wof:name":"Ariguanabo Pharmacy",
    "wof:placetype":"venue"
},
  "geometry": {"coordinates":[-80.28939800000001,25.7708],"type":"Point"}
}