{
  "type": "Feature",
  "properties": {
    "iso:country":"US",
    "sg:address":"5241 Hawkes Bluff Ave",
    "sg:city":"Fort Lauderdale",
    "sg:classifiers":[
        {
            "category":"Building & Trades",
            "subcategory":"Landscaping Services",
            "type":"Services"
        }
    ],
    "sg:phone":"+1 954 880 0678",
    "sg:postcode":"33331",
    "sg:province":"FL",
    "wof:name":"Newland Landscaping & Lawn Svc",
    "wof:placetype":"venue"
},
  "geometry": {"coordinates":[-80.357186,26.061206],"type":"Point"}
}