{
  "type": "Feature",
  "properties": {
    "iso:country":"US",
    "sg:address":"25008 NW State Rd 73",
    "sg:city":"Altha",
    "sg:classifiers":[
        {
            "category":"Education",
            "subcategory":"Library",
            "type":"Public Place"
        }
    ],
    "sg:phone":"+1 850 762 3992",
    "sg:postcode":"32421",
    "sg:province":"FL",
    "wof:name":"Sheltons Park Library",
    "wof:placetype":"venue"
},
  "geometry": {"coordinates":[-85.183662,30.56448],"type":"Point"}
}