{
  "type": "Feature",
  "properties": {
    "iso:country":"US",
    "sg:address":"401 E Las Olas Blvd",
    "sg:city":"Fort Lauderdale",
    "sg:classifiers":[
        {
            "category":"Restaurant",
            "type":"Food & Drink"
        }
    ],
    "sg:phone":"+1 954 764 2949",
    "sg:postcode":"33301",
    "sg:province":"FL",
    "wof:name":"Subway Sandwiches & Salads",
    "wof:placetype":"venue"
},
  "geometry": {"coordinates":[-80.13861799999999,26.119204],"type":"Point"}
}