{
  "type": "Feature",
  "properties": {
    "iso:country":"US",
    "sg:address":"308 S Bay St",
    "sg:city":"Bunnell",
    "sg:classifiers":[
        {
            "category":"Building & Trades",
            "subcategory":"Plumbing",
            "type":"Services"
        }
    ],
    "sg:phone":"+1 386 437 4250",
    "sg:postcode":"32110",
    "sg:province":"FL",
    "sg:tags":[
        "contractor"
    ],
    "wof:name":"Superior Plumming Flagler Cnty",
    "wof:placetype":"venue"
},
  "geometry": {"coordinates":[-81.25614899999999,29.46322],"type":"Point"}
}