{
  "type": "Feature",
  "properties": {
    "addr:full":"1203 Mazarion Pl New Port Richey FL 34655",
    "addr:housenumber":"1203",
    "addr:postcode":"34655",
    "addr:street":"Mazarion Pl",
    "iso:country":"US",
    "sg:address":"1203 Mazarion Pl",
    "sg:city":"New Port Richey",
    "sg:classifiers":[
        {
            "category":"Building & Trades",
            "subcategory":"Construction",
            "type":"Services"
        }
    ],
    "sg:phone":"+1 727 375 0263",
    "sg:postcode":"34655",
    "sg:province":"FL",
    "sg:tags":[
        "house"
    ],
    "wof:name":"Brook Castle Builders Inc",
    "wof:placetype":"venue"
},
  "geometry": {"coordinates":[-82.683066,28.176503],"type":"Point"}
}