{
  "type": "Feature",
  "properties": {
    "addr:full":"731 N Ocean Blvd Pompano Beach FL 33062",
    "addr:housenumber":"731",
    "addr:postcode":"33062",
    "addr:street":"N Ocean Blvd",
    "iso:country":"US",
    "sg:address":"731 N Ocean Blvd",
    "sg:city":"Pompano Beach",
    "sg:classifiers":[
        {
            "category":"Education",
            "subcategory":"Special Training",
            "type":"Public Place"
        }
    ],
    "sg:phone":"+1 954 942 2517",
    "sg:postcode":"33062",
    "sg:province":"FL",
    "sg:tags":[
        "center"
    ],
    "wof:name":"St Gabriel Religious Education",
    "wof:placetype":"venue"
},
  "geometry": {"coordinates":[-80.08758899999999,26.244805],"type":"Point"}
}