{
  "type": "Feature",
  "properties": {
    "addr:full":"3303 Edgewood Ave N Jacksonville FL 32254",
    "addr:housenumber":"3303",
    "addr:postcode":"32254",
    "addr:street":"Edgewood Ave N",
    "iso:country":"US",
    "sg:address":"3303 Edgewood Ave N",
    "sg:city":"Jacksonville",
    "sg:classifiers":[
        {
            "category":"Autos & Motor Vehicles",
            "subcategory":"Automobile Sales",
            "type":"Retail Goods"
        }
    ],
    "sg:phone":"+1 904 353 6196",
    "sg:postcode":"32254",
    "sg:province":"FL",
    "sg:tags":[
        "used"
    ],
    "wof:name":"Paxon Motors Inc",
    "wof:placetype":"venue"
},
  "geometry": {"coordinates":[-81.73057,30.363302],"type":"Point"}
}