{
  "type": "Feature",
  "properties": {
    "iso:country":"US",
    "sg:address":"3108 Del Prado Blvd S",
    "sg:city":"Cape Coral",
    "sg:classifiers":[
        {
            "category":"Health Services",
            "subcategory":"Doctor",
            "type":"Services"
        }
    ],
    "sg:phone":"+1 239 541 3472",
    "sg:postcode":"33904",
    "sg:province":"FL",
    "sg:tags":[
        "orthopedist"
    ],
    "sg:website":"www.spinedisccare.lcdtherapy.com",
    "wof:name":"Spine & Disc Care Center",
    "wof:placetype":"venue"
},
  "geometry": {"coordinates":[-81.941908,26.594514],"type":"Point"}
}