{
  "type": "Feature",
  "properties": {
    "iso:country":"US",
    "sg:address":"2139 del Prado Blvd S",
    "sg:city":"Cape Coral",
    "sg:classifiers":[
        {
            "category":"Banks & Credit Unions",
            "subcategory":"Bank",
            "type":"Services"
        }
    ],
    "sg:phone":"+1 239 574 7936",
    "sg:postcode":"33904",
    "sg:province":"FL",
    "wof:name":"Sun Trust Bank",
    "wof:placetype":"venue"
},
  "geometry": {"coordinates":[-81.940907,26.612626],"type":"Point"}
}