{
  "type": "Feature",
  "properties": {
    "iso:country":"US",
    "sg:address":"5401 Alhambra Dr",
    "sg:city":"Orlando",
    "sg:classifiers":[
        {
            "category":"Health Services",
            "subcategory":"Doctor",
            "type":"Services"
        }
    ],
    "sg:phone":"+1 407 297 1497",
    "sg:postcode":"32808",
    "sg:province":"FL",
    "sg:tags":[
        "physician",
        "surgeon",
        "medical"
    ],
    "wof:name":"Richard M Sag MD",
    "wof:placetype":"venue"
},
  "geometry": {"coordinates":[-81.454241,28.554275],"type":"Point"}
}