{
  "type": "Feature",
  "properties": {
    "iso:country":"US",
    "sg:address":"202 S 3rd St",
    "sg:city":"Lake Wales",
    "sg:classifiers":[
        {
            "category":"Government",
            "subcategory":"Office",
            "type":"Public Place"
        }
    ],
    "sg:phone":"+1 863 678 4131",
    "sg:postcode":"33853",
    "sg:province":"FL",
    "sg:tags":[
        "state",
        "resource"
    ],
    "wof:name":"Aging & Adult Svc",
    "wof:placetype":"venue"
},
  "geometry": {"coordinates":[-81.585553,27.897851],"type":"Point"}
}