{
  "type": "Feature",
  "properties": {
    "iso:country":"US",
    "sg:address":"4276 SE Palmetto St",
    "sg:city":"Stuart",
    "sg:classifiers":[
        {
            "category":"Professional",
            "subcategory":"Management & Consulting",
            "type":"Services"
        }
    ],
    "sg:phone":"+1 772 288 3802",
    "sg:postcode":"34997",
    "sg:province":"FL",
    "sg:tags":[
        "public",
        "relations"
    ],
    "wof:name":"Guertin Misti E Pub Relations",
    "wof:placetype":"venue"
},
  "geometry": {"coordinates":[-80.197416,27.162742],"type":"Point"}
}