{
  "type": "Feature",
  "properties": {
    "iso:country":"US",
    "sg:address":"1718 Saint Johns Bluff Rd S",
    "sg:city":"Jacksonville",
    "sg:classifiers":[
        {
            "category":"Retail",
            "subcategory":"Auto Repair",
            "type":"Services"
        }
    ],
    "sg:phone":"+1 904 997 6006",
    "sg:postcode":"32246",
    "sg:province":"FL",
    "sg:tags":[
        "body",
        "automobile",
        "painting"
    ],
    "wof:name":"Star Automotive Reconditioning",
    "wof:placetype":"venue"
},
  "geometry": {"coordinates":[-81.523343,30.32087],"type":"Point"}
}