{
  "type": "Feature",
  "properties": {
    "addr:full":"1715 West Gray Street Tampa FL 33606",
    "addr:housenumber":"1715",
    "addr:postcode":"33606",
    "addr:street":"West Gray Street",
    "iso:country":"US",
    "sg:address":"1715 West Gray Street",
    "sg:city":"Tampa",
    "sg:classifiers":[
        {
            "category":"Home & Garden",
            "subcategory":"Building Materials",
            "type":"Retail Goods"
        },
        {
            "category":"Building & Trades",
            "subcategory":"Construction",
            "type":"Services"
        },
        {
            "category":"Home & Garden",
            "subcategory":"Carpets & Floor Coverings",
            "type":"Retail Goods"
        }
    ],
    "sg:phone":"+1 813 309 5211",
    "sg:postcode":"33606",
    "sg:province":"FL",
    "sg:tags":[
        "bathroom",
        "hardwood",
        "improvement",
        "planning",
        "tile-contractors",
        "remodeling",
        "kitchen"
    ],
    "sg:website":"http://www.infinitehomedesigns.com/",
    "wof:name":"Infinite Home Designs, Inc.",
    "wof:placetype":"venue"
},
  "geometry": {"coordinates":[-82.476949,27.948363],"type":"Point"}
}