{
  "type": "Feature",
  "properties": {
    "iso:country":"US",
    "sg:address":"1049 E Normandy Blvd",
    "sg:city":"Deltona",
    "sg:classifiers":[
        {
            "category":"Organizations",
            "subcategory":"Membership Organization",
            "type":"Services"
        },
        {
            "category":"Organizations",
            "subcategory":"Community Association",
            "type":"Services"
        }
    ],
    "sg:phone":"+1 386 574 2311",
    "sg:postcode":"32725",
    "sg:province":"FL",
    "sg:tags":[
        "club"
    ],
    "wof:name":"Deltona Woman's Club",
    "wof:placetype":"venue"
},
  "geometry": {"coordinates":[-81.24583199999999,28.890127],"type":"Point"}
}