{
  "type": "Feature",
  "properties": {
    "iso:country":"US",
    "sg:address":"17860 SE 109th Ave # 610",
    "sg:city":"Summerfield",
    "sg:classifiers":[
        {
            "category":"Personal",
            "subcategory":"Beauty Salon",
            "type":"Services"
        }
    ],
    "sg:phone":"+1 352 307 0099",
    "sg:postcode":"34491",
    "sg:province":"FL",
    "sg:tags":[
        "hair",
        "stylist"
    ],
    "wof:name":"Hair Care",
    "wof:placetype":"venue"
},
  "geometry": {"coordinates":[-81.968496,28.961589],"type":"Point"}
}