{
  "type": "Feature",
  "properties": {
    "iso:country":"US",
    "sg:address":"325 SE 1st Ave",
    "sg:city":"Delray Beach",
    "sg:classifiers":[
        {
            "category":"Wholesale",
            "subcategory":"Meat",
            "type":"Manufacturing & Wholesale Goods"
        }
    ],
    "sg:phone":"+1 561 272 1122",
    "sg:postcode":"33444",
    "sg:province":"FL",
    "sg:tags":[
        "personal",
        "mfg",
        "prepared"
    ],
    "wof:name":"Ostermann Sausage Co Inc",
    "wof:placetype":"venue"
},
  "geometry": {"coordinates":[-80.07186900000001,26.454791],"type":"Point"}
}