{
  "type": "Feature",
  "properties": {
    "iso:country":"US",
    "sg:address":"5497 Benchmark Ln",
    "sg:city":"Sanford",
    "sg:classifiers":[
        {
            "category":"Real Estate",
            "subcategory":"Real Estate Services",
            "type":"Services"
        },
        {
            "category":"Retail",
            "subcategory":"Laundry & Dry Cleaning",
            "type":"Services"
        },
        {
            "category":"Building & Trades",
            "subcategory":"Cleaning & Sanitation",
            "type":"Services"
        },
        {
            "category":"Home & Garden",
            "subcategory":"Carpets & Floor Coverings",
            "type":"Retail Goods"
        }
    ],
    "sg:phone":"+1 407 323 9722",
    "sg:postcode":"32773",
    "sg:province":"FL",
    "sg:tags":[
        "cleaner",
        "material",
        "rug",
        "maintenance",
        "cleaners-interior"
    ],
    "wof:name":"Capitol Carpet Care Inc",
    "wof:placetype":"venue"
},
  "geometry": {"coordinates":[-81.300104,28.729638],"type":"Point"}
}