{
  "type": "Feature",
  "properties": {
    "iso:country":"US",
    "sg:address":"1900 Summit Tower Blvd",
    "sg:city":"Orlando",
    "sg:classifiers":[
        {
            "category":"Professional",
            "type":"Services"
        }
    ],
    "sg:phone":"+1 407 919 1215",
    "sg:postcode":"32810",
    "sg:province":"FL",
    "wof:name":"Cornerstone Portfolio Svc Inc",
    "wof:placetype":"venue"
},
  "geometry": {"coordinates":[-81.402434,28.632832],"type":"Point"}
}