{
  "type": "Feature",
  "properties": {
    "iso:country":"US",
    "sg:address":"5216 NW Edgarton Ter",
    "sg:city":"Port Saint Lucie",
    "sg:classifiers":[
        {
            "category":"Building & Trades",
            "subcategory":"Construction",
            "type":"Services"
        }
    ],
    "sg:phone":"+1 772 340 3865",
    "sg:postcode":"34983",
    "sg:province":"FL",
    "sg:tags":[
        "contractor"
    ],
    "wof:name":"Bicentie Dry Wall",
    "wof:placetype":"venue"
},
  "geometry": {"coordinates":[-80.361237,27.342477],"type":"Point"}
}