{
  "type": "Feature",
  "properties": {
    "addr:full":"28384 US Hwy 19 Clearwater FL 33761",
    "addr:postcode":"28384;33761",
    "addr:street":"Us Hwy 19",
    "iso:country":"US",
    "sg:address":"28384 US Hwy 19",
    "sg:city":"Clearwater",
    "sg:classifiers":[
        {
            "category":"Shopping",
            "subcategory":"Shoes",
            "type":"Retail Goods"
        }
    ],
    "sg:phone":"+1 727 539 7006",
    "sg:postcode":"33761",
    "sg:province":"FL",
    "wof:name":"Happy Feet Plus",
    "wof:placetype":"venue"
},
  "geometry": {"coordinates":[-82.738235,28.028576],"type":"Point"}
}