{
  "type": "Feature",
  "properties": {
    "addr:full":"812 SE 8th Ave Deerfield Beach FL 33441",
    "addr:housenumber":"812",
    "addr:postcode":"33441",
    "addr:street":"Se 8Th Ave",
    "iso:country":"US",
    "sg:address":"812 SE 8th Ave",
    "sg:city":"Deerfield Beach",
    "sg:classifiers":[
        {
            "category":"Professional",
            "subcategory":"Management & Consulting",
            "type":"Services"
        }
    ],
    "sg:phone":"+1 954 418 0101",
    "sg:postcode":"33441",
    "sg:province":"FL",
    "sg:tags":[
        "consultant",
        "safety"
    ],
    "wof:name":"America's Toddler Guard",
    "wof:placetype":"venue"
},
  "geometry": {"coordinates":[-80.093857,26.306227],"type":"Point"}
}