{
  "type": "Feature",
  "properties": {
    "iso:country":"US",
    "sg:address":"5472 E Silver Springs Blvd",
    "sg:city":"Silver Springs",
    "sg:classifiers":[
        {
            "category":"Retail",
            "subcategory":"Car Wash",
            "type":"Services"
        }
    ],
    "sg:phone":"+1 352 401 4687",
    "sg:postcode":"34488",
    "sg:province":"FL",
    "sg:tags":[
        "automobile",
        "detail",
        "clean"
    ],
    "wof:name":"Al Proulx Auto Detailing",
    "wof:placetype":"venue"
},
  "geometry": {"coordinates":[-82.058847,29.215603],"type":"Point"}
}