{
  "type": "Feature",
  "properties": {
    "iso:country":"US",
    "sg:address":"16011 SW Archer Rd",
    "sg:city":"Archer",
    "sg:classifiers":[
        {
            "category":"Retail",
            "subcategory":"Veterinary Services",
            "type":"Services"
        }
    ],
    "sg:phone":"+1 352 495 9111",
    "sg:postcode":"32618",
    "sg:province":"FL",
    "sg:tags":[
        "animal"
    ],
    "wof:name":"Archer Road Pet Resort",
    "wof:placetype":"venue"
},
  "geometry": {"coordinates":[-82.51618499999999,29.538725],"type":"Point"}
}