{
  "type": "Feature",
  "properties": {
    "addr:full":"2403 W Oak Ridge Rd Orlando FL 32809",
    "addr:housenumber":"2403",
    "addr:postcode":"32809",
    "addr:street":"W Oak Ridge Rd",
    "iso:country":"US",
    "sg:address":"2403 W Oak Ridge Rd",
    "sg:city":"Orlando",
    "sg:classifiers":[
        {
            "category":"Insurance",
            "subcategory":"Insurance Agent",
            "type":"Services"
        }
    ],
    "sg:phone":"+1 407 447 1598",
    "sg:postcode":"32809",
    "sg:province":"FL",
    "wof:name":"Atlas Insurance",
    "wof:placetype":"venue"
},
  "geometry": {"coordinates":[-81.41184199999999,28.47247],"type":"Point"}
}