{
  "type": "Feature",
  "properties": {
    "addr:full":"5353 1st Ave S Saint Petersburg FL 33707",
    "addr:housenumber":"5353",
    "addr:postcode":"33707",
    "addr:street":"1St Ave S",
    "iso:country":"US",
    "sg:address":"5353 1st Ave S",
    "sg:city":"Saint Petersburg",
    "sg:classifiers":[
        {
            "category":"Health Services",
            "subcategory":"Doctor",
            "type":"Services"
        }
    ],
    "sg:phone":"+1 727 321 1515",
    "sg:postcode":"33707",
    "sg:province":"FL",
    "sg:tags":[
        "medical"
    ],
    "wof:name":"Pediatric Hlth Alance Pinellas",
    "wof:placetype":"venue"
},
  "geometry": {"coordinates":[-82.70605500000001,27.77012],"type":"Point"}
}