{
  "type": "Feature",
  "properties": {
    "addr:full":"1400 Glades Rd Boca Raton FL 33432",
    "addr:housenumber":"1400",
    "addr:postcode":"33432",
    "addr:street":"Glades Rd",
    "iso:country":"US",
    "sg:address":"1400 Glades Rd",
    "sg:city":"Boca Raton",
    "sg:classifiers":[
        {
            "category":"Shopping",
            "subcategory":"Computers & Home Electronics",
            "type":"Retail Goods"
        }
    ],
    "sg:phone":"+1 561 368 3871",
    "sg:postcode":"33432",
    "sg:province":"FL",
    "sg:tags":[
        "equipment",
        "electronic",
        "supply"
    ],
    "wof:name":"Circuit City",
    "wof:placetype":"venue"
},
  "geometry": {"coordinates":[-80.117681,26.368125],"type":"Point"}
}