{
  "type": "Feature",
  "properties": {
    "addr:full":"11345 US Hwy 41 Gibsonton FL 33534",
    "addr:housenumber":"11345",
    "addr:postcode":"33534",
    "addr:street":"Us Hwy 41",
    "iso:country":"US",
    "sg:address":"11345 US Hwy 41",
    "sg:city":"Gibsonton",
    "sg:classifiers":[
        {
            "category":"Retail",
            "subcategory":"Auto Repair",
            "type":"Services"
        }
    ],
    "sg:phone":"+1 813 741 3000",
    "sg:postcode":"33534",
    "sg:province":"FL",
    "sg:tags":[
        "repairing",
        "automobile"
    ],
    "wof:name":"G Town Automotive",
    "wof:placetype":"venue"
},
  "geometry": {"coordinates":[-82.381857,27.836188],"type":"Point"}
}