{
  "type": "Feature",
  "properties": {
    "addr:full":"305 Whispering Cir St Augustine FL 32084",
    "addr:housenumber":"305",
    "addr:postcode":"32084",
    "addr:street":"Whispering Cir St",
    "iso:country":"US",
    "sg:address":"305 Whispering Cir",
    "sg:city":"St Augustine",
    "sg:classifiers":[
        {
            "category":"Organizations",
            "subcategory":"Non-profit Organization",
            "type":"Services"
        }
    ],
    "sg:phone":"+1 904 797 9022",
    "sg:postcode":"32084",
    "sg:province":"FL",
    "wof:name":"New Life Community Of Promise",
    "wof:placetype":"venue"
},
  "geometry": {"coordinates":[-81.336611,29.871022],"type":"Point"}
}