{
  "type": "Feature",
  "properties": {
    "addr:full":"4605 4th St W Lehigh Acres FL 33971",
    "addr:housenumber":"4605",
    "addr:postcode":"33971",
    "addr:street":"4Th St W",
    "iso:country":"US",
    "sg:address":"4605 4th St W",
    "sg:city":"Lehigh Acres",
    "sg:classifiers":[
        {
            "category":"Retail",
            "subcategory":"Portrait Studio",
            "type":"Services"
        }
    ],
    "sg:phone":"+1 239 437 2111",
    "sg:postcode":"33971",
    "sg:province":"FL",
    "sg:tags":[
        "photographer"
    ],
    "wof:name":"G & T Photo Video",
    "wof:placetype":"venue"
},
  "geometry": {"coordinates":[-81.72202900000001,26.615775],"type":"Point"}
}