{
  "type": "Feature",
  "properties": {
    "addr:full":"550 S Eola Dr Orlando FL 32801",
    "addr:housenumber":"550",
    "addr:postcode":"32801",
    "addr:street":"S Eola Dr",
    "iso:country":"US",
    "sg:address":"550 S Eola Dr",
    "sg:city":"Orlando",
    "sg:classifiers":[
        {
            "category":"Education",
            "subcategory":"School",
            "type":"Public Place"
        }
    ],
    "sg:phone":"+1 407 897 6440",
    "sg:postcode":"32801",
    "sg:province":"FL",
    "wof:name":"Cherokee School",
    "wof:placetype":"venue"
},
  "geometry": {"coordinates":[-81.369806,28.536225],"type":"Point"}
}