{
  "type": "Feature",
  "properties": {
    "iso:country":"US",
    "sg:address":"2830 Country Club Blvd",
    "sg:city":"Cape Coral",
    "sg:classifiers":[
        {
            "category":"Social Services",
            "subcategory":"Child Care",
            "type":"Services"
        }
    ],
    "sg:phone":"+1 239 574 6994",
    "sg:postcode":"33904",
    "sg:province":"FL",
    "wof:name":"Anna Dato Family Daycare",
    "wof:placetype":"venue"
},
  "geometry": {"coordinates":[-81.95648,26.598542],"type":"Point"}
}