{
  "type": "Feature",
  "properties": {
    "iso:country":"US",
    "sg:address":"4247 W Kennedy Blvd",
    "sg:city":"Tampa",
    "sg:classifiers":[
        {
            "category":"Health Services",
            "subcategory":"Chiropractor",
            "type":"Services"
        }
    ],
    "sg:phone":"+1 813 289 5575",
    "sg:postcode":"33609",
    "sg:province":"FL",
    "wof:name":"Chiropractic Care Ctr",
    "wof:placetype":"venue"
},
  "geometry": {"coordinates":[-82.515199,27.944909],"type":"Point"}
}