{
  "type": "Feature",
  "properties": {
    "iso:country":"US",
    "sg:address":"8792 SE 165th Mulberry Ln",
    "sg:city":"Lady Lake",
    "sg:classifiers":[
        {
            "category":"Shopping",
            "type":"Retail Goods"
        }
    ],
    "sg:phone":"+1 352 751 2882",
    "sg:postcode":"32162",
    "sg:province":"FL",
    "sg:tags":[
        "merchandise"
    ],
    "wof:name":"One Stop Wireless Inc",
    "wof:placetype":"venue"
},
  "geometry": {"coordinates":[-82.008764,28.981111],"type":"Point"}
}