{
  "type": "Feature",
  "properties": {
    "iso:country":"US",
    "sg:address":"5580 Ships Channel Cir",
    "sg:city":"Sarasota",
    "sg:classifiers":[
        {
            "category":"Autos & Motor Vehicles",
            "subcategory":"Automobile Sales",
            "type":"Retail Goods"
        }
    ],
    "sg:phone":"+1 941 923 7474",
    "sg:postcode":"34231",
    "sg:province":"FL",
    "sg:tags":[
        "aircraft"
    ],
    "sg:website":"www.britanniaaviation.com",
    "wof:name":"Britannia Aviation Svc Intl",
    "wof:placetype":"venue"
},
  "geometry": {"coordinates":[-82.519239,27.272499],"type":"Point"}
}