{
  "type": "Feature",
  "properties": {
    "iso:country":"US",
    "sg:address":"2200 Ave G NW",
    "sg:city":"Winter Haven",
    "sg:classifiers":[
        {
            "category":"Education",
            "subcategory":"School",
            "type":"Public Place"
        }
    ],
    "sg:phone":"+1 863 291 5369",
    "sg:postcode":"33880",
    "sg:province":"FL",
    "sg:website":"www.polk-fl.net",
    "wof:name":"Inwood Elementary",
    "wof:placetype":"venue"
},
  "geometry": {"coordinates":[-81.755996,28.030018],"type":"Point"}
}