{
  "type": "Feature",
  "properties": {
    "addr:full":"16090 Okeechobee Rd Fort Pierce FL 34945",
    "addr:housenumber":"16090",
    "addr:postcode":"34945",
    "addr:street":"Okeechobee Rd",
    "iso:country":"US",
    "sg:address":"16090 Okeechobee Rd",
    "sg:city":"Fort Pierce",
    "sg:classifiers":[
        {
            "category":"Farming",
            "subcategory":"Orchard",
            "type":"Manufacturing & Wholesale Goods"
        }
    ],
    "sg:phone":"+1 772 465 5138",
    "sg:postcode":"34945",
    "sg:province":"FL",
    "sg:tags":[
        "citrus",
        "grove",
        "fruit"
    ],
    "wof:name":"Evans Properties Inc",
    "wof:placetype":"venue"
},
  "geometry": {"coordinates":[-80.487118,27.376133],"type":"Point"}
}