{
  "type": "Feature",
  "properties": {
    "addr:full":"38420 5th Ave Zephyrhills FL 33542",
    "addr:housenumber":"38420",
    "addr:postcode":"33542",
    "addr:street":"5Th Ave",
    "iso:country":"US",
    "sg:address":"38420 5th Ave",
    "sg:city":"Zephyrhills",
    "sg:classifiers":[
        {
            "category":"Education",
            "subcategory":"Special Training",
            "type":"Public Place"
        }
    ],
    "sg:phone":"+1 813 782 8219",
    "sg:postcode":"33542",
    "sg:province":"FL",
    "sg:tags":[
        "tutoring"
    ],
    "wof:name":"Sylvan Learning Ctr",
    "wof:placetype":"venue"
},
  "geometry": {"coordinates":[-82.18037699999999,28.233976],"type":"Point"}
}