{
  "type": "Feature",
  "properties": {
    "iso:country":"US",
    "sg:address":"2237 N Commerce Pkwy",
    "sg:city":"Fort Lauderdale",
    "sg:classifiers":[
        {
            "category":"Professional",
            "subcategory":"Lawyer & Legal Services",
            "type":"Services"
        }
    ],
    "sg:phone":"+1 954 385 3637",
    "sg:postcode":"33326",
    "sg:province":"FL",
    "wof:name":"Manella & Klapholz",
    "wof:placetype":"venue"
},
  "geometry": {"coordinates":[-80.365548,26.095615],"type":"Point"}
}