{
  "type": "Feature",
  "properties": {
    "iso:country":"US",
    "sg:address":"390 Piney Ridge Rd",
    "sg:city":"Casselberry",
    "sg:classifiers":[
        {
            "category":"Social Services",
            "subcategory":"Child Care",
            "type":"Services"
        }
    ],
    "sg:phone":"+1 407 339 3233",
    "sg:postcode":"32707",
    "sg:province":"FL",
    "sg:tags":[
        "day"
    ],
    "wof:name":"First Steps of Learningcamp Seminole",
    "wof:placetype":"venue"
},
  "geometry": {"coordinates":[-81.339203,28.6654],"type":"Point"}
}