{
  "type": "Feature",
  "properties": {
    "addr:full":"6710 Shady Acres Blvd New Port Richey FL 34653",
    "addr:housenumber":"6710",
    "addr:postcode":"34653",
    "addr:street":"Shady Acres Blvd",
    "iso:country":"US",
    "sg:address":"6710 Shady Acres Blvd",
    "sg:city":"New Port Richey",
    "sg:classifiers":[
        {
            "category":"Professional",
            "subcategory":"Business Services",
            "type":"Services"
        }
    ],
    "sg:phone":"+1 727 842 4299",
    "sg:postcode":"34653",
    "sg:province":"FL",
    "wof:name":"Phoenix Star Graphics",
    "wof:placetype":"venue"
},
  "geometry": {"coordinates":[-82.678844,28.256268],"type":"Point"}
}