{
  "type": "Feature",
  "properties": {
    "iso:country":"US",
    "sg:address":"3217 Plateau St",
    "sg:city":"Jacksonville",
    "sg:classifiers":[
        {
            "category":"Utilities",
            "subcategory":"Mobile Phone",
            "type":"Services"
        }
    ],
    "sg:phone":"+1 904 813 0217",
    "sg:postcode":"32206",
    "sg:province":"FL",
    "sg:tags":[
        "communication",
        "radiotelephone"
    ],
    "wof:name":"S & S Communications",
    "wof:placetype":"venue"
},
  "geometry": {"coordinates":[-81.63833099999999,30.358007],"type":"Point"}
}