{
  "type": "Feature",
  "properties": {
    "iso:country":"US",
    "sg:address":"415 Paigo St SE",
    "sg:city":"Palm Bay",
    "sg:classifiers":[
        {
            "category":"Wholesale",
            "subcategory":"Machinery & Supplies",
            "type":"Manufacturing & Wholesale Goods"
        }
    ],
    "sg:phone":"+1 321 952 3001",
    "sg:postcode":"32909",
    "sg:province":"FL",
    "sg:tags":[
        "equipment",
        "industrial"
    ],
    "wof:name":"Ringpower",
    "wof:placetype":"venue"
},
  "geometry": {"coordinates":[-80.66165100000001,27.929496],"type":"Point"}
}