{
  "type": "Feature",
  "properties": {
    "addr:full":"8808 Mescalero St Orlando FL 32829",
    "addr:housenumber":"8808",
    "addr:postcode":"32829",
    "addr:street":"Mescalero St",
    "iso:country":"US",
    "sg:address":"8808 Mescalero St",
    "sg:city":"Orlando",
    "sg:classifiers":[
        {
            "category":"Health Services",
            "subcategory":"Clinic",
            "type":"Services"
        }
    ],
    "sg:phone":"+1 407 277 9162",
    "sg:postcode":"32829",
    "sg:province":"FL",
    "sg:tags":[
        "welfare"
    ],
    "wof:name":"Drew Medical Clinic",
    "wof:placetype":"venue"
},
  "geometry": {"coordinates":[-81.263879,28.50522],"type":"Point"}
}