{
  "type": "Feature",
  "properties": {
    "addr:full":"6907 Southern Blvd West Palm Beach FL 33413",
    "addr:housenumber":"6907",
    "addr:postcode":"33413",
    "addr:street":"Southern Blvd",
    "iso:country":"US",
    "sg:address":"6907 Southern Blvd",
    "sg:city":"West Palm Beach",
    "sg:classifiers":[
        {
            "category":"Retail",
            "subcategory":"Auto Repair",
            "type":"Services"
        }
    ],
    "sg:phone":"+1 561 687 0820",
    "sg:postcode":"33413",
    "sg:province":"FL",
    "sg:tags":[
        "automotive"
    ],
    "wof:name":"Sisters Towing and Trnsp",
    "wof:placetype":"venue"
},
  "geometry": {"coordinates":[-80.15664,26.678947],"type":"Point"}
}