{
  "type": "Feature",
  "properties": {
    "addr:full":"1210 Mayer Dr Jacksonville FL 32211",
    "addr:housenumber":"1210",
    "addr:postcode":"32211",
    "addr:street":"Mayer Dr",
    "iso:country":"US",
    "sg:address":"1210 Mayer Dr",
    "sg:city":"Jacksonville",
    "sg:classifiers":[
        {
            "category":"Building & Trades",
            "subcategory":"Construction",
            "type":"Services"
        }
    ],
    "sg:phone":"+1 904 743 2793",
    "sg:postcode":"32211",
    "sg:province":"FL",
    "sg:tags":[
        "home",
        "remodeling",
        "general"
    ],
    "wof:name":"Remodeling Etc",
    "wof:placetype":"venue"
},
  "geometry": {"coordinates":[-81.592343,30.333516],"type":"Point"}
}