{
  "type": "Feature",
  "properties": {
    "iso:country":"US",
    "sg:address":"8220 NW 68th St",
    "sg:city":"Miami",
    "sg:classifiers":[
        {
            "category":"Wholesale",
            "subcategory":"Non-durable Goods",
            "type":"Manufacturing & Wholesale Goods"
        }
    ],
    "sg:phone":"+1 305 514 2878",
    "sg:postcode":"33166",
    "sg:province":"FL",
    "sg:tags":[
        "dry",
        "goods-wholesale"
    ],
    "wof:name":"Asa Distributors",
    "wof:placetype":"venue"
},
  "geometry": {"coordinates":[-80.33045199999999,25.835269],"type":"Point"}
}