{
  "type": "Feature",
  "properties": {
    "iso:country":"US",
    "sg:address":"2443 Polk St",
    "sg:city":"Hollywood",
    "sg:classifiers":[
        {
            "category":"Retail",
            "subcategory":"Auto Repair",
            "type":"Services"
        }
    ],
    "sg:phone":"+1 954 922 1401",
    "sg:postcode":"33020",
    "sg:province":"FL",
    "sg:tags":[
        "glass",
        "replacement"
    ],
    "wof:name":"Cool Spot",
    "wof:placetype":"venue"
},
  "geometry": {"coordinates":[-80.15822300000001,26.012475],"type":"Point"}
}