{
  "type": "Feature",
  "properties": {
    "addr:full":"150 N Nova Rd Daytona Beach FL 32114",
    "addr:housenumber":"150",
    "addr:postcode":"32114",
    "addr:street":"N Nova Rd",
    "iso:country":"US",
    "sg:address":"150 N Nova Rd",
    "sg:city":"Daytona Beach",
    "sg:classifiers":[
        {
            "category":"Professional",
            "subcategory":"Accounting & Tax Preparation",
            "type":"Services"
        }
    ],
    "sg:phone":"+1 386 258 3278",
    "sg:postcode":"32114",
    "sg:province":"FL",
    "sg:tags":[
        "return",
        "filing"
    ],
    "sg:website":"www.jacksonhewitt.com",
    "wof:name":"Jackson Hewitt Tax Svc",
    "wof:placetype":"venue"
},
  "geometry": {"coordinates":[-81.039885,29.203377],"type":"Point"}
}