{
  "type": "Feature",
  "properties": {
    "addr:full":"780 W 17th St Hialeah FL 33010",
    "addr:housenumber":"780",
    "addr:postcode":"33010",
    "addr:street":"W 17Th St",
    "iso:country":"US",
    "sg:address":"780 W 17th St",
    "sg:city":"Hialeah",
    "sg:classifiers":[
        {
            "category":"Food & Beverages",
            "subcategory":"Meat & Fish",
            "type":"Retail Goods"
        }
    ],
    "sg:phone":"+1 305 883 4911",
    "sg:postcode":"33010",
    "sg:province":"FL",
    "sg:tags":[
        "shop"
    ],
    "wof:name":"Zales Meat Procressing Market",
    "wof:placetype":"venue"
},
  "geometry": {"coordinates":[-80.29769899999999,25.837099],"type":"Point"}
}