{
  "type": "Feature",
  "properties": {
    "iso:country":"US",
    "sg:address":"5700 Midnight Pass Rd",
    "sg:city":"Sarasota",
    "sg:classifiers":[
        {
            "category":"Organizations",
            "subcategory":"Non-profit Organization",
            "type":"Services"
        }
    ],
    "sg:phone":"+1 941 312 0400",
    "sg:postcode":"34242",
    "sg:province":"FL",
    "sg:tags":[
        "social"
    ],
    "wof:name":"Prader Willi Syndrm Assc U S A",
    "wof:placetype":"venue"
},
  "geometry": {"coordinates":[-82.54489100000001,27.266344],"type":"Point"}
}