{
  "type": "Feature",
  "properties": {
    "iso:country":"US",
    "sg:address":"11532 State Hwy 84",
    "sg:city":"Davie",
    "sg:classifiers":[
        {
            "category":"Building & Trades",
            "subcategory":"Electrical",
            "type":"Services"
        },
        {
            "category":"Shopping",
            "type":"Retail Goods"
        }
    ],
    "sg:phone":"+1 954 452 9181",
    "sg:postcode":"33325",
    "sg:province":"FL",
    "sg:tags":[
        "supply",
        "telephone",
        "contractor",
        "equipment",
        "electrical",
        "merchandise"
    ],
    "sg:website":"www.specializedtelephones.com",
    "wof:name":"Specialized Telephone Systems",
    "wof:placetype":"venue"
},
  "geometry": {"coordinates":[-80.30406000000001,26.112536],"type":"Point"}
}