{
  "type": "Feature",
  "properties": {
    "iso:country":"US",
    "sg:address":"3765 Winkler Ave",
    "sg:city":"Fort Myers",
    "sg:classifiers":[
        {
            "category":"Retail",
            "subcategory":"Repair Shop",
            "type":"Services"
        }
    ],
    "sg:phone":"+1 239 246 5950",
    "sg:postcode":"33916",
    "sg:province":"FL",
    "sg:tags":[
        "related"
    ],
    "wof:name":"William Renner's Repair",
    "wof:placetype":"venue"
},
  "geometry": {"coordinates":[-81.821707,26.610053],"type":"Point"}
}