{
  "type": "Feature",
  "properties": {
    "iso:country":"US",
    "sg:address":"404 W Palmetto St",
    "sg:city":"Wauchula",
    "sg:classifiers":[
        {
            "category":"Retail",
            "subcategory":"Funeral Services",
            "type":"Services"
        }
    ],
    "sg:phone":"+1 863 773 4355",
    "sg:postcode":"33873",
    "sg:province":"FL",
    "sg:tags":[
        "director"
    ],
    "wof:name":"Brant Funeral Chapel",
    "wof:placetype":"venue"
},
  "geometry": {"coordinates":[-81.815504,27.548257],"type":"Point"}
}