{
  "type": "Feature",
  "properties": {
    "addr:full":"1854 Brookwood Rd Jacksonville FL 32207",
    "addr:housenumber":"1854",
    "addr:postcode":"32207",
    "addr:street":"Brookwood Rd",
    "iso:country":"US",
    "sg:address":"1854 Brookwood Rd",
    "sg:city":"Jacksonville",
    "sg:classifiers":[
        {
            "category":"Education",
            "subcategory":"Special Training",
            "type":"Public Place"
        }
    ],
    "sg:phone":"+1 904 398 1775",
    "sg:postcode":"32207",
    "sg:province":"FL",
    "sg:tags":[
        "tutoring"
    ],
    "wof:name":"Laura H Trippe",
    "wof:placetype":"venue"
},
  "geometry": {"coordinates":[-81.64723600000001,30.295039],"type":"Point"}
}