{
  "type": "Feature",
  "properties": {
    "iso:country":"US",
    "sg:address":"4792 S Kirkman Rd",
    "sg:city":"Orlando",
    "sg:classifiers":[
        {
            "category":"Food & Beverages",
            "subcategory":"Bakery",
            "type":"Retail Goods"
        }
    ],
    "sg:phone":"+1 407 822 9919",
    "sg:postcode":"32811",
    "sg:province":"FL",
    "sg:tags":[
        "baker"
    ],
    "wof:name":"Dessert Lady",
    "wof:placetype":"venue"
},
  "geometry": {"coordinates":[-81.45907099999999,28.493124],"type":"Point"}
}