{
  "type": "Feature",
  "properties": {
    "iso:country":"US",
    "sg:address":"1300 NW 167th St",
    "sg:city":"Miami",
    "sg:classifiers":[
        {
            "category":"Professional",
            "subcategory":"Computer Services",
            "type":"Services"
        }
    ],
    "sg:phone":"+1 305 627 9494",
    "sg:postcode":"33169",
    "sg:province":"FL",
    "sg:tags":[
        "information",
        "technology"
    ],
    "wof:name":"Silicon Beach Group",
    "wof:placetype":"venue"
},
  "geometry": {"coordinates":[-80.22520799999999,25.926648],"type":"Point"}
}