{
  "type": "Feature",
  "properties": {
    "addr:full":"3401 Old Polk City Rd Lakeland FL 33809",
    "addr:housenumber":"3401",
    "addr:postcode":"33809",
    "addr:street":"Old Polk City Rd",
    "iso:country":"US",
    "sg:address":"3401 Old Polk City Rd",
    "sg:city":"Lakeland",
    "sg:classifiers":[
        {
            "category":"Sports & Exercise",
            "subcategory":"Race Track",
            "type":"Entertainment"
        }
    ],
    "sg:phone":"+1 863 984 7311",
    "sg:postcode":"33809",
    "sg:province":"FL",
    "wof:name":"Drivetech Racing School",
    "wof:placetype":"venue"
},
  "geometry": {"coordinates":[-81.887236,28.153995],"type":"Point"}
}