{
  "type": "Feature",
  "properties": {
    "iso:country":"US",
    "sg:address":"4127 NW 16th Blvd",
    "sg:city":"Gainesville",
    "sg:classifiers":[
        {
            "category":"Shopping",
            "subcategory":"Florist",
            "type":"Retail Goods"
        }
    ],
    "sg:phone":"+1 352 338 9338",
    "sg:postcode":"32605",
    "sg:province":"FL",
    "wof:name":"West Farms Millhopper Florist",
    "wof:placetype":"venue"
},
  "geometry": {"coordinates":[-82.38866899999999,29.673884],"type":"Point"}
}