{
  "type": "Feature",
  "properties": {
    "addr:full":"4133 N Washington Blvd Sarasota FL 34234",
    "addr:housenumber":"4133",
    "addr:postcode":"34234",
    "addr:street":"N Washington Blvd",
    "iso:country":"US",
    "sg:address":"4133 N Washington Blvd",
    "sg:city":"Sarasota",
    "sg:classifiers":[
        {
            "category":"Manufacturing",
            "subcategory":"Chemicals & Compounds",
            "type":"Manufacturing & Wholesale Goods"
        },
        {
            "category":"Animal Shelter",
            "type":"Public Place"
        },
        {
            "category":"Building & Trades",
            "subcategory":"Pest Control",
            "type":"Services"
        }
    ],
    "sg:phone":"+1 866 574 1660",
    "sg:postcode":"34234",
    "sg:province":"FL",
    "sg:tags":[
        "industrial",
        "supply",
        "services-commercial",
        "termite",
        "bee",
        "equipment",
        "mothproofing",
        "removal"
    ],
    "sg:website":"http://signup.orkin.com/orkin/res/fun-Standard-pph_pcb_tph_tsch.aspx?cm_mmc=yahoo-yellowpages-_-yahoo-local-_-WEBYL-_-_&utm_source=yahoo-yellowpages&utm_content=yahoo-local&utm_medium=internet-yellow-pages&utm_campaign=WEBYL",
    "wof:name":"Orkin Pest & Termite Control",
    "wof:placetype":"venue"
},
  "geometry": {"coordinates":[-82.53081899999999,27.368359],"type":"Point"}
}