{
  "type": "Feature",
  "properties": {
    "addr:full":"15621 Carlton Lake Rd Wimauma FL 33598",
    "addr:housenumber":"15621",
    "addr:postcode":"33598",
    "addr:street":"Carlton Lake Rd",
    "iso:country":"US",
    "sg:address":"15621 Carlton Lake Rd",
    "sg:city":"Wimauma",
    "sg:classifiers":[
        {
            "category":"Real Estate",
            "subcategory":"Developer",
            "type":"Services"
        }
    ],
    "sg:phone":"+1 813 633 0133",
    "sg:postcode":"33598",
    "sg:province":"FL",
    "wof:name":"Sonrise Land Development",
    "wof:placetype":"venue"
},
  "geometry": {"coordinates":[-82.244795,27.744159],"type":"Point"}
}