{
  "type": "Feature",
  "properties": {
    "addr:full":"27220 Hiawatha Blvd Brooksville FL 34601",
    "addr:housenumber":"27220",
    "addr:postcode":"34601",
    "addr:street":"Hiawatha Blvd",
    "iso:country":"US",
    "sg:address":"27220 Hiawatha Blvd",
    "sg:city":"Brooksville",
    "sg:classifiers":[
        {
            "category":"Building & Trades",
            "subcategory":"Construction",
            "type":"Services"
        }
    ],
    "sg:phone":"+1 352 799 0771",
    "sg:postcode":"34601",
    "sg:province":"FL",
    "sg:tags":[
        "television",
        "telephone",
        "cable",
        "contractor"
    ],
    "wof:name":"West Florida Inc",
    "wof:placetype":"venue"
},
  "geometry": {"coordinates":[-82.29236899999999,28.664936],"type":"Point"}
}