{
  "type": "Feature",
  "properties": {
    "addr:full":"137 Saltwind Cir Neptune Beach FL 32266",
    "addr:housenumber":"137",
    "addr:postcode":"32266",
    "addr:street":"Saltwind Cir",
    "iso:country":"US",
    "sg:address":"137 Saltwind Cir",
    "sg:city":"Neptune Beach",
    "sg:classifiers":[
        {
            "category":"Professional",
            "subcategory":"Computer Services",
            "type":"Services"
        }
    ],
    "sg:phone":"+1 904 249 6910",
    "sg:postcode":"32266",
    "sg:province":"FL",
    "sg:tags":[
        "datum"
    ],
    "wof:name":"Helping Children Grow",
    "wof:placetype":"venue"
},
  "geometry": {"coordinates":[-81.417028,30.323468],"type":"Point"}
}