{
  "type": "Feature",
  "properties": {
    "iso:country":"US",
    "sg:address":"2928 McQueen Rd",
    "sg:city":"Apopka",
    "sg:classifiers":[
        {
            "category":"Building & Trades",
            "subcategory":"Cleaning & Sanitation",
            "type":"Services"
        }
    ],
    "sg:phone":"+1 407 886 4055",
    "sg:postcode":"32703",
    "sg:province":"FL",
    "sg:tags":[
        "maintenance"
    ],
    "wof:name":"Pearsons Cleaning & Hauling",
    "wof:placetype":"venue"
},
  "geometry": {"coordinates":[-81.51763699999999,28.633729],"type":"Point"}
}