{
  "type": "Feature",
  "properties": {
    "addr:full":"2101 Orange Ave Fort Pierce FL 34950",
    "addr:housenumber":"2101",
    "addr:postcode":"34950",
    "addr:street":"Orange Ave",
    "iso:country":"US",
    "sg:address":"2101 Orange Ave",
    "sg:city":"Fort Pierce",
    "sg:classifiers":[
        {
            "category":"Retail",
            "subcategory":"Auto Repair",
            "type":"Services"
        }
    ],
    "sg:phone":"+1 772 468 0079",
    "sg:postcode":"34950",
    "sg:province":"FL",
    "sg:tags":[
        "body",
        "automobile",
        "top",
        "upholstery"
    ],
    "wof:name":"Garna's Auto Upholstery",
    "wof:placetype":"venue"
},
  "geometry": {"coordinates":[-80.34675,27.44739],"type":"Point"}
}