{
  "type": "Feature",
  "properties": {
    "iso:country":"US",
    "sg:address":"816 NE Park St",
    "sg:city":"Okeechobee",
    "sg:classifiers":[
        {
            "category":"Shopping",
            "subcategory":"Discount & Variety Stores",
            "type":"Retail Goods"
        }
    ],
    "sg:phone":"+1 863 357 1900",
    "sg:postcode":"34972",
    "sg:province":"FL",
    "wof:name":"Family Dollar Stores",
    "wof:placetype":"venue"
},
  "geometry": {"coordinates":[-80.821535,27.24368],"type":"Point"}
}