{
  "type": "Feature",
  "properties": {
    "addr:full":"4830 John Carroll Rd S Lakeland FL 33801",
    "addr:housenumber":"4830",
    "addr:postcode":"33801",
    "addr:street":"John Carroll Rd S",
    "iso:country":"US",
    "sg:address":"4830 John Carroll Rd S",
    "sg:city":"Lakeland",
    "sg:classifiers":[
        {
            "category":"Building & Trades",
            "subcategory":"Landscaping Services",
            "type":"Services"
        }
    ],
    "sg:phone":"+1 863 668 8861",
    "sg:postcode":"33801",
    "sg:province":"FL",
    "sg:tags":[
        "tree"
    ],
    "wof:name":"Bozeman Tree Svc",
    "wof:placetype":"venue"
},
  "geometry": {"coordinates":[-81.86172500000001,28.04058],"type":"Point"}
}