{
  "type": "Feature",
  "properties": {
    "iso:country":"US",
    "sg:address":"2505 N Indian River Dr",
    "sg:city":"Fort Pierce",
    "sg:classifiers":[
        {
            "category":"Manufacturing",
            "subcategory":"Watercraft",
            "type":"Manufacturing & Wholesale Goods"
        }
    ],
    "sg:phone":"+1 772 468 9744",
    "sg:postcode":"34946",
    "sg:province":"FL",
    "sg:tags":[
        "rebuilt",
        "part",
        "boat"
    ],
    "wof:name":"Four R Marine Inc",
    "wof:placetype":"venue"
},
  "geometry": {"coordinates":[-80.334622,27.484443],"type":"Point"}
}