{
  "type": "Feature",
  "properties": {
    "iso:country":"US",
    "sg:address":"2524 Norfolk Rd",
    "sg:city":"Orlando",
    "sg:classifiers":[
        {
            "category":"Banks & Credit Unions",
            "subcategory":"Bank",
            "type":"Services"
        }
    ],
    "sg:phone":"+1 407 207 0988",
    "sg:postcode":"32803",
    "sg:province":"FL",
    "sg:tags":[
        "loan",
        "real estate"
    ],
    "wof:name":"Pan American Mortgage",
    "wof:placetype":"venue"
},
  "geometry": {"coordinates":[-81.36063900000001,28.574676],"type":"Point"}
}