{
  "type": "Feature",
  "properties": {
    "addr:full":"1323 E Silver Springs Blvd Ocala FL 34470",
    "addr:housenumber":"1323",
    "addr:postcode":"34470",
    "addr:street":"E Silver Springs Blvd",
    "iso:country":"US",
    "sg:address":"1323 E Silver Springs Blvd",
    "sg:city":"Ocala",
    "sg:classifiers":[
        {
            "category":"Health Services",
            "subcategory":"Doctor",
            "type":"Services"
        }
    ],
    "sg:phone":"+1 352 622 4994",
    "sg:postcode":"34470",
    "sg:province":"FL",
    "sg:tags":[
        "dentist"
    ],
    "wof:name":"Kevin B Wallace DDS",
    "wof:placetype":"venue"
},
  "geometry": {"coordinates":[-82.120293,29.187112],"type":"Point"}
}