{
  "type": "Feature",
  "properties": {
    "iso:country":"US",
    "sg:address":"2801 N Hiawassee Rd",
    "sg:city":"Orlando",
    "sg:classifiers":[
        {
            "category":"Food & Beverages",
            "subcategory":"Liquor & Beverages",
            "type":"Retail Goods"
        }
    ],
    "sg:phone":"+1 407 291 1239",
    "sg:postcode":"32818",
    "sg:province":"FL",
    "sg:tags":[
        "beer",
        "ale"
    ],
    "wof:name":"H & S Discount Beverages",
    "wof:placetype":"venue"
},
  "geometry": {"coordinates":[-81.475973,28.578553],"type":"Point"}
}