{
  "type": "Feature",
  "properties": {
    "addr:full":"3015 NW 79th St Miami FL 33147",
    "addr:housenumber":"3015",
    "addr:postcode":"33147",
    "addr:street":"Nw 79Th St",
    "iso:country":"US",
    "sg:address":"3015 NW 79th St",
    "sg:city":"Miami",
    "sg:classifiers":[
        {
            "category":"Shopping",
            "type":"Retail Goods"
        }
    ],
    "sg:phone":"+1 786 318 0632",
    "sg:postcode":"33147",
    "sg:province":"FL",
    "sg:tags":[
        "cosmetic",
        "perfume"
    ],
    "wof:name":"Perfumania",
    "wof:placetype":"venue"
},
  "geometry": {"coordinates":[-80.24704,25.845945],"type":"Point"}
}