{
  "type": "Feature",
  "properties": {
    "iso:country":"US",
    "sg:address":"1485 Lakeview Dr",
    "sg:city":"Deland",
    "sg:classifiers":[
        {
            "category":"Recreation",
            "subcategory":"Boat Charter",
            "type":"Entertainment"
        }
    ],
    "sg:phone":"+1 386 734 6776",
    "sg:postcode":"32720",
    "sg:province":"FL",
    "sg:tags":[
        "boat-rental"
    ],
    "wof:name":"Moonlighting Boat Rentals Inc",
    "wof:placetype":"venue"
},
  "geometry": {"coordinates":[-81.350138,29.004214],"type":"Point"}
}