{
  "type": "Feature",
  "properties": {
    "iso:country":"US",
    "sg:address":"5860 Wyndi Way",
    "sg:city":"Pace",
    "sg:classifiers":[
        {
            "category":"Building & Trades",
            "subcategory":"Construction",
            "type":"Services"
        }
    ],
    "sg:phone":"+1 850 994 1760",
    "sg:postcode":"32571",
    "sg:province":"FL",
    "sg:tags":[
        "home",
        "builder"
    ],
    "wof:name":"Bradford Builders",
    "wof:placetype":"venue"
},
  "geometry": {"coordinates":[-87.196955,30.65605],"type":"Point"}
}