{
  "type": "Feature",
  "properties": {
    "iso:country":"US",
    "sg:address":"1661 E Stardust Dr",
    "sg:city":"Malabar",
    "sg:classifiers":[
        {
            "category":"Manufacturing",
            "subcategory":"Tools & Machinery",
            "type":"Manufacturing & Wholesale Goods"
        }
    ],
    "sg:phone":"+1 321 728 5710",
    "sg:postcode":"32950",
    "sg:province":"FL",
    "sg:tags":[
        "equipment",
        "mfg"
    ],
    "wof:name":"Leon E Weaver",
    "wof:placetype":"venue"
},
  "geometry": {"coordinates":[-80.606646,27.998576],"type":"Point"}
}