{
  "type": "Feature",
  "properties": {
    "addr:full":"1771 Edgewood Ave W Jacksonville FL 32208",
    "addr:housenumber":"1771",
    "addr:postcode":"32208",
    "addr:street":"Edgewood Ave W",
    "iso:country":"US",
    "sg:address":"1771 Edgewood Ave W",
    "sg:city":"Jacksonville",
    "sg:classifiers":[
        {
            "category":"Personal",
            "subcategory":"Beauty Salon",
            "type":"Services"
        }
    ],
    "sg:phone":"+1 904 764 0600",
    "sg:postcode":"32208",
    "sg:province":"FL",
    "sg:tags":[
        "shop"
    ],
    "wof:name":"Godfather's Salon",
    "wof:placetype":"venue"
},
  "geometry": {"coordinates":[-81.690409,30.384439],"type":"Point"}
}