{
  "type": "Feature",
  "properties": {
    "iso:country":"US",
    "sg:address":"9324 SE Maricamp Rd",
    "sg:city":"Ocala",
    "sg:classifiers":[
        {
            "category":"Shopping",
            "subcategory":"Tobacco",
            "type":"Retail Goods"
        }
    ],
    "sg:phone":"+1 352 236 3412",
    "sg:postcode":"34472",
    "sg:province":"FL",
    "sg:tags":[
        "product",
        "grocery"
    ],
    "wof:name":"Smokers Outlet & Grocery Inc",
    "wof:placetype":"venue"
},
  "geometry": {"coordinates":[-82.013541,29.105],"type":"Point"}
}