{
  "type": "Feature",
  "properties": {
    "addr:full":"1657 Michigan Avenue exhibiting in front of ICEBOX- Lincoln Road Market Miami Beach FL 33139",
    "addr:housenumber":"1657",
    "addr:postcode":"market;33139",
    "addr:street":"Michigan Avenue Exhibiting In Front;Lincoln Road",
    "iso:country":"US",
    "sg:address":"1657 Michigan Avenue exhibiting in front of ICEBOX- Lincoln Road Market",
    "sg:city":"Miami Beach",
    "sg:classifiers":[
        {
            "category":"Shopping",
            "subcategory":"Jewelry",
            "type":"Retail Goods"
        },
        {
            "category":"Shopping",
            "subcategory":"Antiques",
            "type":"Retail Goods"
        }
    ],
    "sg:phone":"+1 646 620 5535",
    "sg:postcode":"33139",
    "sg:province":"FL",
    "wof:name":"dtADORN",
    "wof:placetype":"venue"
},
  "geometry": {"coordinates":[-80.138616,25.79085],"type":"Point"}
}