{
  "type": "Feature",
  "properties": {
    "addr:full":"16036 Magnolia Hill St Clermont FL 34714",
    "addr:housenumber":"16036",
    "addr:postcode":"34714",
    "addr:street":"Magnolia Hill St",
    "iso:country":"US",
    "sg:address":"16036 Magnolia Hill St",
    "sg:city":"Clermont",
    "sg:classifiers":[
        {
            "category":"Real Estate",
            "subcategory":"Real Estate Services",
            "type":"Services"
        }
    ],
    "sg:phone":"+1 352 394 1151",
    "sg:postcode":"34714",
    "sg:province":"FL",
    "sg:tags":[
        "buyer",
        "broker"
    ],
    "wof:name":"Roger P A Slover",
    "wof:placetype":"venue"
},
  "geometry": {"coordinates":[-81.68977099999999,28.387919],"type":"Point"}
}