{
  "type": "Feature",
  "properties": {
    "addr:full":"6832 14th St W Bradenton FL 34207",
    "addr:housenumber":"6832",
    "addr:postcode":"34207",
    "addr:street":"14Th St W",
    "iso:country":"US",
    "sg:address":"6832 14th St W",
    "sg:city":"Bradenton",
    "sg:classifiers":[
        {
            "category":"Autos & Motor Vehicles",
            "subcategory":"Auto Supplies",
            "type":"Retail Goods"
        }
    ],
    "sg:phone":"+1 941 756 2426",
    "sg:postcode":"34207",
    "sg:province":"FL",
    "sg:tags":[
        "automobile",
        "parts"
    ],
    "sg:website":"www.napaonline.com",
    "wof:name":"Brandenton South",
    "wof:placetype":"venue"
},
  "geometry": {"coordinates":[-82.575559,27.418477],"type":"Point"}
}