{
  "type": "Feature",
  "properties": {
    "addr:full":"9766 SW 24th St Miami FL 33165",
    "addr:housenumber":"9766",
    "addr:postcode":"33165",
    "addr:street":"Sw 24Th St",
    "iso:country":"US",
    "sg:address":"9766 SW 24th St",
    "sg:city":"Miami",
    "sg:classifiers":[
        {
            "category":"Government",
            "subcategory":"Office",
            "type":"Public Place"
        }
    ],
    "sg:phone":"+1 305 222 4120",
    "sg:postcode":"33165",
    "sg:province":"FL",
    "wof:name":"Benefit Recovery Program",
    "wof:placetype":"venue"
},
  "geometry": {"coordinates":[-80.352166,25.747128],"type":"Point"}
}