{
  "type": "Feature",
  "properties": {
    "addr:full":"3645 William Ave Miami FL 33133",
    "addr:housenumber":"3645",
    "addr:postcode":"33133",
    "addr:street":"William Ave",
    "iso:country":"US",
    "sg:address":"3645 William Ave",
    "sg:city":"Miami",
    "sg:classifiers":[
        {
            "category":"Building & Trades",
            "subcategory":"Construction",
            "type":"Services"
        }
    ],
    "sg:phone":"+1 305 446 9949",
    "sg:postcode":"33133",
    "sg:province":"FL",
    "sg:tags":[
        "painter"
    ],
    "wof:name":"James Painting Service",
    "wof:placetype":"venue"
},
  "geometry": {"coordinates":[-80.252537,25.726291],"type":"Point"}
}