{
  "type": "Feature",
  "properties": {
    "addr:full":"750 W New Haven Ave Melbourne FL 32901",
    "addr:housenumber":"750",
    "addr:postcode":"32901",
    "addr:street":"W New Haven Ave",
    "iso:country":"US",
    "sg:address":"750 W New Haven Ave",
    "sg:city":"Melbourne",
    "sg:classifiers":[
        {
            "category":"Manufacturing",
            "subcategory":"Retail Goods",
            "type":"Manufacturing & Wholesale Goods"
        }
    ],
    "sg:phone":"+1 321 952 0231",
    "sg:postcode":"32901",
    "sg:province":"FL",
    "sg:tags":[
        "magic",
        "entertainment"
    ],
    "wof:name":"Creative Magic & Costumes",
    "wof:placetype":"venue"
},
  "geometry": {"coordinates":[-80.633892,28.078846],"type":"Point"}
}