{
  "type": "Feature",
  "properties": {
    "addr:full":"14630 Palm Beach Blvd Fort Myers FL 33905",
    "addr:housenumber":"14630",
    "addr:postcode":"33905",
    "addr:street":"Palm Beach Blvd",
    "iso:country":"US",
    "sg:address":"14630 Palm Beach Blvd",
    "sg:city":"Fort Myers",
    "sg:classifiers":[
        {
            "category":"Banks & Credit Unions",
            "subcategory":"Bank",
            "type":"Services"
        }
    ],
    "sg:phone":"+1 239 437 8191",
    "sg:postcode":"33905",
    "sg:province":"FL",
    "wof:name":"First Bank",
    "wof:placetype":"venue"
},
  "geometry": {"coordinates":[-81.71360199999999,26.711305],"type":"Point"}
}