{
  "type": "Feature",
  "properties": {
    "iso:country":"US",
    "sg:address":"451 A1a Beach Blvd",
    "sg:city":"Saint Augustine",
    "sg:classifiers":[
        {
            "category":"Bars & Pubs",
            "type":"Food & Drink"
        }
    ],
    "sg:menulink":"http://www.allmenus.com/fl/st-augustine/237100-barnacle-bills-seafood-reastaurant/menu/",
    "sg:phone":"+1 904 471 2434",
    "sg:postcode":"32080",
    "sg:province":"FL",
    "sg:tags":[
        "seafood",
        "american"
    ],
    "wof:name":"Barnacle Bill's Seafood Reastaurant",
    "wof:placetype":"venue"
},
  "geometry": {"coordinates":[-81.267267,29.853707],"type":"Point"}
}