{
  "type": "Feature",
  "properties": {
    "iso:country":"US",
    "sg:address":"9500 Koger Blvd N",
    "sg:city":"St Petersburg",
    "sg:classifiers":[
        {
            "category":"Banks & Credit Unions",
            "subcategory":"Bank",
            "type":"Services"
        }
    ],
    "sg:phone":"+1 727 471 0098",
    "sg:postcode":"33702",
    "sg:province":"FL",
    "sg:tags":[
        "loan",
        "real estate"
    ],
    "wof:name":"Castle Mortgage Corp",
    "wof:placetype":"venue"
},
  "geometry": {"coordinates":[-82.641446,27.858187],"type":"Point"}
}