{
  "type": "Feature",
  "properties": {
    "addr:full":"5028 Wesley Dr Tampa FL 33647",
    "addr:housenumber":"5028",
    "addr:postcode":"33647",
    "addr:street":"Wesley Dr",
    "iso:country":"US",
    "sg:address":"5028 Wesley Dr",
    "sg:city":"Tampa",
    "sg:classifiers":[
        {
            "category":"Professional",
            "subcategory":"Advertising",
            "type":"Services"
        }
    ],
    "sg:phone":"+1 813 978 0039",
    "sg:postcode":"33647",
    "sg:province":"FL",
    "sg:tags":[
        "specialty",
        "promotional"
    ],
    "wof:name":"E O Dunbar Associates Inc",
    "wof:placetype":"venue"
},
  "geometry": {"coordinates":[-82.401359,28.107359],"type":"Point"}
}