{
  "type": "Feature",
  "properties": {
    "addr:full":"2842 Buccaneer Dr Winter Park FL 32792",
    "addr:housenumber":"2842",
    "addr:postcode":"32792",
    "addr:street":"Buccaneer Dr",
    "iso:country":"US",
    "sg:address":"2842 Buccaneer Dr",
    "sg:city":"Winter Park",
    "sg:classifiers":[
        {
            "category":"Travel",
            "subcategory":"Travel Agent",
            "type":"Entertainment"
        }
    ],
    "sg:phone":"+1 407 679 3922",
    "sg:postcode":"32792",
    "sg:province":"FL",
    "sg:tags":[
        "agency"
    ],
    "wof:name":"Signature Cruises",
    "wof:placetype":"venue"
},
  "geometry": {"coordinates":[-81.29310099999999,28.631336],"type":"Point"}
}