{
  "type": "Feature",
  "properties": {
    "iso:country":"US",
    "sg:address":"575 Scrubjay Ln",
    "sg:city":"Jupiter",
    "sg:classifiers":[
        {
            "category":"Professional",
            "type":"Services"
        }
    ],
    "sg:phone":"+1 561 745 0744",
    "sg:postcode":"33458",
    "sg:province":"FL",
    "wof:name":"Jilldon Inc",
    "wof:placetype":"venue"
},
  "geometry": {"coordinates":[-80.127999,26.908397],"type":"Point"}
}