{
  "type": "Feature",
  "properties": {
    "addr:full":"2506 Gulf Gate Dr Sarasota FL 34231",
    "addr:housenumber":"2506",
    "addr:postcode":"34231",
    "addr:street":"Gulf Gate Dr",
    "iso:country":"US",
    "sg:address":"2506 Gulf Gate Dr",
    "sg:city":"Sarasota",
    "sg:classifiers":[
        {
            "category":"Organizations",
            "subcategory":"Religious Organization",
            "type":"Services"
        }
    ],
    "sg:phone":"+1 941 923 1691",
    "sg:postcode":"34231",
    "sg:province":"FL",
    "wof:name":"St Thomas Mora",
    "wof:placetype":"venue"
},
  "geometry": {"coordinates":[-82.511658,27.258672],"type":"Point"}
}