{
  "type": "Feature",
  "properties": {
    "addr:full":"4901 SW 74th Ct Miami FL 33155",
    "addr:housenumber":"4901",
    "addr:postcode":"33155",
    "addr:street":"Sw 74Th Ct",
    "iso:country":"US",
    "sg:address":"4901 SW 74th Ct",
    "sg:city":"Miami",
    "sg:classifiers":[
        {
            "category":"Professional",
            "subcategory":"Engineering",
            "type":"Services"
        },
        {
            "category":"Professional",
            "subcategory":"Computer Services",
            "type":"Services"
        }
    ],
    "sg:phone":"+1 305 669 2777",
    "sg:postcode":"33155",
    "sg:province":"FL",
    "sg:tags":[
        "repair",
        "designer",
        "network",
        "consultant",
        "system",
        "integration",
        "design",
        "engineer"
    ],
    "sg:website":"www.ndsi.com",
    "wof:name":"Network Data Services Inc",
    "wof:placetype":"venue"
},
  "geometry": {"coordinates":[-80.315102,25.7243],"type":"Point"}
}