{
  "type": "Feature",
  "properties": {
    "iso:country":"US",
    "sg:address":"2225 Citrus Blvd",
    "sg:city":"Leesburg",
    "sg:classifiers":[
        {
            "category":"Health Services",
            "subcategory":"Optometrist",
            "type":"Services"
        }
    ],
    "sg:phone":"+1 352 787 9799",
    "sg:postcode":"34748",
    "sg:province":"FL",
    "wof:name":"James K Berry OD",
    "wof:placetype":"venue"
},
  "geometry": {"coordinates":[-81.89505,28.841516],"type":"Point"}
}