{
  "type": "Feature",
  "properties": {
    "iso:country":"US",
    "sg:address":"5705 La Costa Dr",
    "sg:city":"Orlando",
    "sg:classifiers":[
        {
            "category":"Bakery",
            "type":"Food & Drink"
        }
    ],
    "sg:menulink":"http://www.allmenus.com/fl/orlando/102009-perkins-restaurant--bakery/menu/",
    "sg:phone":"+1 407 275 5620",
    "sg:postcode":"32807",
    "sg:province":"FL",
    "sg:tags":[
        "sandwich",
        "salad",
        "soup",
        "american",
        "pastry",
        "wrap"
    ],
    "wof:name":"Perkins Restaurant & Bakery",
    "wof:placetype":"venue"
},
  "geometry": {"coordinates":[-81.309804,28.527945],"type":"Point"}
}