{
  "type": "Feature",
  "properties": {
    "addr:full":"1661 Chestnut Ct E Palm Harbor FL 34683",
    "addr:housenumber":"1661",
    "addr:postcode":"34683",
    "addr:street":"Chestnut Ct E",
    "iso:country":"US",
    "sg:address":"1661 Chestnut Ct E",
    "sg:city":"Palm Harbor",
    "sg:classifiers":[
        {
            "category":"Professional",
            "subcategory":"Business Services",
            "type":"Services"
        }
    ],
    "sg:phone":"+1 727 784 1531",
    "sg:postcode":"34683",
    "sg:province":"FL",
    "wof:name":"Jay Overton Golf Enterprises I",
    "wof:placetype":"venue"
},
  "geometry": {"coordinates":[-82.75720200000001,28.094348],"type":"Point"}
}