{
  "type": "Feature",
  "properties": {
    "addr:full":"908 Trumbull St Deltona FL 32725",
    "addr:housenumber":"908",
    "addr:postcode":"32725",
    "addr:street":"Trumbull St",
    "iso:country":"US",
    "sg:address":"908 Trumbull St",
    "sg:city":"Deltona",
    "sg:classifiers":[
        {
            "category":"Building & Trades",
            "subcategory":"Landscaping Services",
            "type":"Services"
        }
    ],
    "sg:phone":"+1 386 789 6041",
    "sg:postcode":"32725",
    "sg:province":"FL",
    "wof:name":"Jims Lawn Service",
    "wof:placetype":"venue"
},
  "geometry": {"coordinates":[-81.251364,28.91334],"type":"Point"}
}