{
  "type": "Feature",
  "properties": {
    "iso:country":"US",
    "sg:address":"1739 E Hillsborough Ave",
    "sg:city":"Tampa",
    "sg:classifiers":[
        {
            "category":"Shopping",
            "subcategory":"Music",
            "type":"Retail Goods"
        }
    ],
    "sg:phone":"+1 813 236 2723",
    "sg:postcode":"33610",
    "sg:province":"FL",
    "wof:name":"Music Maze",
    "wof:placetype":"venue"
},
  "geometry": {"coordinates":[-82.439553,27.995987],"type":"Point"}
}