{
  "type": "Feature",
  "properties": {
    "iso:country":"US",
    "sg:address":"1006 33rd St",
    "sg:city":"Vero Beach",
    "sg:classifiers":[
        {
            "category":"Social Services",
            "subcategory":"Adult Care",
            "type":"Services"
        }
    ],
    "sg:phone":"+1 772 567 5248",
    "sg:postcode":"32960",
    "sg:province":"FL",
    "sg:tags":[
        "home",
        "residential"
    ],
    "sg:website":"www.floridabaptist.org",
    "wof:name":"Florida Baptist Retirement Ctr",
    "wof:placetype":"venue"
},
  "geometry": {"coordinates":[-80.39249,27.652939],"type":"Point"}
}