{
  "type": "Feature",
  "properties": {
    "addr:full":"160 NE 82nd St Miami FL 33138",
    "addr:housenumber":"160",
    "addr:postcode":"33138",
    "addr:street":"Ne 82Nd St",
    "iso:country":"US",
    "sg:address":"160 NE 82nd St",
    "sg:city":"Miami",
    "sg:classifiers":[
        {
            "category":"Health Services",
            "subcategory":"Doctor",
            "type":"Services"
        }
    ],
    "sg:phone":"+1 305 756 7602",
    "sg:postcode":"33138",
    "sg:province":"FL",
    "sg:tags":[
        "surgeon",
        "oral"
    ],
    "wof:name":"Casthely Franklin DDS Dr",
    "wof:placetype":"venue"
},
  "geometry": {"coordinates":[-80.194199,25.849701],"type":"Point"}
}