{
  "type": "Feature",
  "properties": {
    "iso:country":"US",
    "sg:address":"740 Bluebird Ln",
    "sg:city":"Fort Lauderdale",
    "sg:classifiers":[
        {
            "category":"Insurance",
            "subcategory":"Insurance Agent",
            "type":"Services"
        }
    ],
    "sg:phone":"+1 954 473 8452",
    "sg:postcode":"33324",
    "sg:province":"FL",
    "wof:name":"Montiego Land Corp",
    "wof:placetype":"venue"
},
  "geometry": {"coordinates":[-80.262485,26.11124],"type":"Point"}
}