{
  "type": "Feature",
  "properties": {
    "iso:country":"US",
    "sg:address":"933 Airport Pulling Rd S",
    "sg:city":"Naples",
    "sg:classifiers":[
        {
            "category":"Shopping",
            "subcategory":"Shoes",
            "type":"Retail Goods"
        }
    ],
    "sg:phone":"+1 239 643 2559",
    "sg:postcode":"34104",
    "sg:province":"FL",
    "sg:tags":[
        "family"
    ],
    "wof:name":"Shoe Warehouse",
    "wof:placetype":"venue"
},
  "geometry": {"coordinates":[-81.766559,26.144388],"type":"Point"}
}