{
  "type": "Feature",
  "properties": {
    "iso:country":"US",
    "sg:address":"1677 Lakeshore Dr",
    "sg:city":"Eustis",
    "sg:classifiers":[
        {
            "category":"Shopping",
            "subcategory":"Used Merchandise",
            "type":"Retail Goods"
        }
    ],
    "sg:phone":"+1 352 483 1233",
    "sg:postcode":"32726",
    "sg:province":"FL",
    "sg:tags":[
        "shop",
        "antique",
        "gift",
        "store"
    ],
    "wof:name":"Rosecreek Antiques & Gifts",
    "wof:placetype":"venue"
},
  "geometry": {"coordinates":[-81.70416400000001,28.837457],"type":"Point"}
}