{
  "type": "Feature",
  "properties": {
    "addr:full":"691 Douglas Ave Altamonte Springs FL 32714",
    "addr:housenumber":"691",
    "addr:postcode":"32714",
    "addr:street":"Douglas Ave",
    "iso:country":"US",
    "sg:address":"691 Douglas Ave",
    "sg:city":"Altamonte Springs",
    "sg:classifiers":[
        {
            "category":"Health Services",
            "subcategory":"Medical Lab",
            "type":"Services"
        }
    ],
    "sg:phone":"+1 407 865 6544",
    "sg:postcode":"32714",
    "sg:province":"FL",
    "sg:tags":[
        "testing",
        "alcohol",
        "drug"
    ],
    "wof:name":"Rn Expertise Inc",
    "wof:placetype":"venue"
},
  "geometry": {"coordinates":[-81.39022,28.674746],"type":"Point"}
}