{
  "type": "Feature",
  "properties": {
    "addr:full":"12557 Biscayne Blvd North Miami FL 33181",
    "addr:housenumber":"12557",
    "addr:postcode":"33181",
    "addr:street":"Biscayne Blvd",
    "iso:country":"US",
    "sg:address":"12557 Biscayne Blvd",
    "sg:city":"North Miami",
    "sg:classifiers":[
        {
            "category":"Home & Garden",
            "subcategory":"Furniture",
            "type":"Retail Goods"
        }
    ],
    "sg:phone":"+1 305 892 0003",
    "sg:postcode":"33181",
    "sg:province":"FL",
    "sg:tags":[
        "mattress"
    ],
    "sg:website":"www.mattressgiant.com",
    "wof:name":"Mattress Giant",
    "wof:placetype":"venue"
},
  "geometry": {"coordinates":[-80.16300200000001,25.891899],"type":"Point"}
}