{
  "type": "Feature",
  "properties": {
    "iso:country":"US",
    "sg:address":"717 Espanola Way",
    "sg:city":"Miami Beach",
    "sg:classifiers":[
        {
            "category":"Arts & Performance",
            "subcategory":"Theater",
            "type":"Entertainment"
        }
    ],
    "sg:phone":"+1 305 532 0898",
    "sg:postcode":"33139",
    "sg:province":"FL",
    "sg:tags":[
        "music"
    ],
    "wof:name":"Michael J Everett Inc",
    "wof:placetype":"venue"
},
  "geometry": {"coordinates":[-80.136268,25.786893],"type":"Point"}
}