{
  "type": "Feature",
  "properties": {
    "iso:country":"US",
    "sg:address":"2086 Thomasville Rd",
    "sg:city":"Tallahassee",
    "sg:classifiers":[
        {
            "category":"Shopping",
            "subcategory":"Gifts & Souvenirs",
            "type":"Retail Goods"
        }
    ],
    "sg:phone":"+1 850 386 8525",
    "sg:postcode":"32308",
    "sg:province":"FL",
    "sg:tags":[
        "shop"
    ],
    "wof:name":"Vignettes",
    "wof:placetype":"venue"
},
  "geometry": {"coordinates":[-84.266238,30.470784],"type":"Point"}
}