{
  "type": "Feature",
  "properties": {
    "addr:full":"597 SW Wood Creek Dr Palm City FL 34990",
    "addr:housenumber":"597",
    "addr:postcode":"34990",
    "addr:street":"Sw Wood Creek Dr",
    "iso:country":"US",
    "sg:address":"597 SW Wood Creek Dr",
    "sg:city":"Palm City",
    "sg:classifiers":[
        {
            "category":"Real Estate",
            "subcategory":"Real Estate Agent",
            "type":"Services"
        }
    ],
    "sg:phone":"+1 772 220 4220",
    "sg:postcode":"34990",
    "sg:province":"FL",
    "wof:name":"Gifford Realty & Investments",
    "wof:placetype":"venue"
},
  "geometry": {"coordinates":[-80.300084,27.197162],"type":"Point"}
}