{
  "type": "Feature",
  "properties": {
    "addr:full":"501 W Ave A Jupiter FL 33430",
    "addr:housenumber":"501",
    "addr:postcode":"33430",
    "addr:street":"W Ave A",
    "iso:country":"US",
    "sg:address":"501 W Ave A",
    "sg:city":"Jupiter",
    "sg:classifiers":[
        {
            "category":"Professional",
            "type":"Services"
        }
    ],
    "sg:phone":"+1 561 745 2164",
    "sg:postcode":"33430",
    "sg:province":"FL",
    "sg:tags":[
        "establishment"
    ],
    "wof:name":"Adam Scott Co",
    "wof:placetype":"venue"
},
  "geometry": {"coordinates":[-80.67388099999999,26.6859],"type":"Point"}
}