{
  "type": "Feature",
  "properties": {
    "iso:country":"US",
    "sg:address":"9210 SW 43rd St",
    "sg:city":"Miami",
    "sg:classifiers":[
        {
            "category":"Building & Trades",
            "subcategory":"Landscaping Services",
            "type":"Services"
        }
    ],
    "sg:phone":"+1 305 299 7523",
    "sg:postcode":"33165",
    "sg:province":"FL",
    "sg:tags":[
        "landscape"
    ],
    "wof:name":"Alvarez Amaury",
    "wof:placetype":"venue"
},
  "geometry": {"coordinates":[-80.34555400000001,25.728548],"type":"Point"}
}