{
  "type": "Feature",
  "properties": {
    "iso:country":"US",
    "sg:address":"16851 NE 15th Ave",
    "sg:city":"North Miami Beach",
    "sg:classifiers":[
        {
            "category":"Food & Beverages",
            "subcategory":"Groceries & Convenience Stores",
            "type":"Retail Goods"
        }
    ],
    "sg:phone":"+1 305 945 7009",
    "sg:postcode":"33162",
    "sg:province":"FL",
    "wof:name":"Daily Supermarket",
    "wof:placetype":"venue"
},
  "geometry": {"coordinates":[-80.17040299999999,25.930901],"type":"Point"}
}