{
  "type": "Feature",
  "properties": {
    "addr:full":"12235 W Linebaugh Ave Tampa FL 33626",
    "addr:housenumber":"12235",
    "addr:postcode":"33626",
    "addr:street":"W Linebaugh Ave",
    "iso:country":"US",
    "sg:address":"12235 W Linebaugh Ave",
    "sg:city":"Tampa",
    "sg:classifiers":[
        {
            "category":"Restaurant",
            "type":"Food & Drink"
        }
    ],
    "sg:phone":"+1 813 814 7775",
    "sg:postcode":"33626",
    "sg:province":"FL",
    "sg:website":"www.subway.com",
    "wof:name":"Subway Sandwiches & Salads",
    "wof:placetype":"venue"
},
  "geometry": {"coordinates":[-82.62880800000001,28.055953],"type":"Point"}
}