{
  "type": "Feature",
  "properties": {
    "iso:country":"US",
    "sg:address":"2011 SW 70th Ave",
    "sg:city":"Davie",
    "sg:classifiers":[
        {
            "category":"Wholesale",
            "subcategory":"Computers",
            "type":"Manufacturing & Wholesale Goods"
        }
    ],
    "sg:phone":"+1 954 473 4762",
    "sg:postcode":"33317",
    "sg:province":"FL",
    "sg:tags":[
        "computer-wholesale",
        "manufacturer"
    ],
    "wof:name":"A R Whoul",
    "wof:placetype":"venue"
},
  "geometry": {"coordinates":[-80.23768,26.095177],"type":"Point"}
}