{
  "type": "Feature",
  "properties": {
    "addr:full":"3060 S Atlantic Ave Daytona Beach FL 32118",
    "addr:housenumber":"3060",
    "addr:postcode":"32118",
    "addr:street":"S Atlantic Ave",
    "iso:country":"US",
    "sg:address":"3060 S Atlantic Ave",
    "sg:city":"Daytona Beach",
    "sg:classifiers":[
        {
            "category":"Retail",
            "subcategory":"Laundry & Dry Cleaning",
            "type":"Services"
        }
    ],
    "sg:phone":"+1 386 767 8631",
    "sg:postcode":"32118",
    "sg:province":"FL",
    "sg:tags":[
        "drycleaning",
        "plant"
    ],
    "wof:name":"Oceanside Dry Cleaners",
    "wof:placetype":"venue"
},
  "geometry": {"coordinates":[-80.976979,29.165554],"type":"Point"}
}