{
  "type": "Feature",
  "properties": {
    "iso:country":"US",
    "sg:address":"952 Wesson Dr",
    "sg:city":"Casselberry",
    "sg:classifiers":[
        {
            "category":"Banks & Credit Unions",
            "subcategory":"Investment Brokerage",
            "type":"Services"
        }
    ],
    "sg:phone":"+1 407 695 6359",
    "sg:postcode":"32707",
    "sg:province":"FL",
    "wof:name":"Goldenrod Entertainment Inc",
    "wof:placetype":"venue"
},
  "geometry": {"coordinates":[-81.29250999999999,28.649609],"type":"Point"}
}