{
  "type": "Feature",
  "properties": {
    "iso:country":"US",
    "sg:address":"3461 Carlton Arms Dr",
    "sg:city":"Tampa",
    "sg:classifiers":[
        {
            "category":"Building & Trades",
            "subcategory":"Construction",
            "type":"Services"
        }
    ],
    "sg:phone":"+1 813 930 2575",
    "sg:postcode":"33614",
    "sg:province":"FL",
    "sg:tags":[
        "hanging",
        "contractor"
    ],
    "wof:name":"Steves Custom Painting Inc",
    "wof:placetype":"venue"
},
  "geometry": {"coordinates":[-82.50054900000001,28.013635],"type":"Point"}
}