{
  "type": "Feature",
  "properties": {
    "addr:full":"117 Pinoak Ct E Crestview FL 32539",
    "addr:housenumber":"117",
    "addr:postcode":"32539",
    "addr:street":"Pinoak Ct E",
    "iso:country":"US",
    "sg:address":"117 Pinoak Ct E",
    "sg:city":"Crestview",
    "sg:classifiers":[
        {
            "category":"Professional",
            "subcategory":"Art Services",
            "type":"Services"
        }
    ],
    "sg:phone":"+1 850 499 8403",
    "sg:postcode":"32539",
    "sg:province":"FL",
    "sg:tags":[
        "artist"
    ],
    "wof:name":"Shelley Settles Artist",
    "wof:placetype":"venue"
},
  "geometry": {"coordinates":[-86.542689,30.721758],"type":"Point"}
}