{
  "type": "Feature",
  "properties": {
    "addr:full":"1208 Ali Baba Ave Opa Locka FL 33054",
    "addr:housenumber":"1208",
    "addr:postcode":"33054",
    "addr:street":"Ali Baba Ave;Locka",
    "iso:country":"US",
    "sg:address":"1208 Ali Baba Ave",
    "sg:city":"Opa Locka",
    "sg:classifiers":[
        {
            "category":"Personal",
            "subcategory":"Beauty Salon",
            "type":"Services"
        }
    ],
    "sg:phone":"+1 305 687 3211",
    "sg:postcode":"33054",
    "sg:province":"FL",
    "sg:tags":[
        "shop"
    ],
    "wof:name":"Unique",
    "wof:placetype":"venue"
},
  "geometry": {"coordinates":[-80.24543199999999,25.904174],"type":"Point"}
}