{
  "type": "Feature",
  "properties": {
    "iso:country":"US",
    "sg:address":"243 N Village St",
    "sg:city":"Kissimmee",
    "sg:classifiers":[
        {
            "category":"Building & Trades",
            "subcategory":"Cleaning & Sanitation",
            "type":"Services"
        }
    ],
    "sg:phone":"+1 407 729 1805",
    "sg:postcode":"34747",
    "sg:province":"FL",
    "sg:tags":[
        "janitor"
    ],
    "wof:name":"Martha Teicher Cleaning",
    "wof:placetype":"venue"
},
  "geometry": {"coordinates":[-81.527418,28.325622],"type":"Point"}
}