{
  "type": "Feature",
  "properties": {
    "iso:country":"US",
    "sg:address":"13291 SW 135th Ave",
    "sg:city":"Miami",
    "sg:classifiers":[
        {
            "category":"Home & Garden",
            "subcategory":"Carpets & Floor Coverings",
            "type":"Retail Goods"
        }
    ],
    "sg:phone":"+1 305 259 3418",
    "sg:postcode":"33186",
    "sg:province":"FL",
    "sg:tags":[
        "material",
        "flooring",
        "contractor"
    ],
    "wof:name":"J & H Floors & More Inc",
    "wof:placetype":"venue"
},
  "geometry": {"coordinates":[-80.412783,25.643711],"type":"Point"}
}