{
  "type": "Feature",
  "properties": {
    "addr:full":"1012 McCall Ct Oviedo FL 32765",
    "addr:housenumber":"1012",
    "addr:postcode":"32765",
    "addr:street":"Mccall Ct",
    "iso:country":"US",
    "sg:address":"1012 McCall Ct",
    "sg:city":"Oviedo",
    "sg:classifiers":[
        {
            "category":"Social Services",
            "type":"Services"
        }
    ],
    "sg:phone":"+1 407 695 9200",
    "sg:postcode":"32765",
    "sg:province":"FL",
    "wof:name":"ServiceMaster",
    "wof:placetype":"venue"
},
  "geometry": {"coordinates":[-81.202922,28.648867],"type":"Point"}
}