{
  "type": "Feature",
  "properties": {
    "addr:full":"3521 W 2nd Ave Hialeah FL 33012",
    "addr:housenumber":"3521",
    "addr:postcode":"33012",
    "addr:street":"W 2Nd Ave",
    "iso:country":"US",
    "sg:address":"3521 W 2nd Ave",
    "sg:city":"Hialeah",
    "sg:classifiers":[
        {
            "category":"Building & Trades",
            "subcategory":"Construction",
            "type":"Services"
        }
    ],
    "sg:phone":"+1 305 884 8345",
    "sg:postcode":"33012",
    "sg:province":"FL",
    "sg:tags":[
        "welder"
    ],
    "wof:name":"Zuni Welding Corp.",
    "wof:placetype":"venue"
},
  "geometry": {"coordinates":[-80.286492,25.853987],"type":"Point"}
}