{
  "type": "Feature",
  "properties": {
    "iso:country":"US",
    "sg:address":"103 Security Sq",
    "sg:city":"Winter Haven",
    "sg:classifiers":[
        {
            "category":"Banks & Credit Unions",
            "subcategory":"Investment Brokerage",
            "type":"Services"
        }
    ],
    "sg:phone":"+1 863 293 4572",
    "sg:postcode":"33880",
    "sg:province":"FL",
    "sg:tags":[
        "advisory",
        "financial"
    ],
    "wof:name":"Patrick J Sheil Jr",
    "wof:placetype":"venue"
},
  "geometry": {"coordinates":[-81.730593,28.019421],"type":"Point"}
}