{
  "type": "Feature",
  "properties": {
    "iso:country":"US",
    "sg:address":"3565 Jones Rd",
    "sg:city":"Marianna",
    "sg:phone":"+1 850 579 2710",
    "sg:postcode":"32448",
    "sg:province":"FL",
    "sg:tags":[
        "farm"
    ],
    "wof:name":"Green Acres Farm",
    "wof:placetype":"venue"
},
  "geometry": {"coordinates":[-85.306606,30.584285],"type":"Point"}
}