{
  "type": "Feature",
  "properties": {
    "iso:country":"US",
    "sg:address":"7925 Merrill Rd",
    "sg:city":"Jacksonville",
    "sg:classifiers":[
        {
            "category":"Real Estate",
            "subcategory":"Real Estate Operator",
            "type":"Services"
        }
    ],
    "sg:phone":"+1 904 743 9090",
    "sg:postcode":"32277",
    "sg:province":"FL",
    "sg:tags":[
        "apartment"
    ],
    "wof:name":"Mid America Apt Communities",
    "wof:placetype":"venue"
},
  "geometry": {"coordinates":[-81.56583999999999,30.35231],"type":"Point"}
}