{
  "type": "Feature",
  "properties": {
    "iso:country":"US",
    "sg:address":"6818 Forest Hill Blvd",
    "sg:city":"Greenacres",
    "sg:classifiers":[
        {
            "category":"Personal",
            "subcategory":"Tanning Parlor",
            "type":"Services"
        }
    ],
    "sg:phone":"+1 561 641 0028",
    "sg:postcode":"33413",
    "sg:province":"FL",
    "sg:tags":[
        "salon"
    ],
    "wof:name":"Tan Factory",
    "wof:placetype":"venue"
},
  "geometry": {"coordinates":[-80.14947600000001,26.65108],"type":"Point"}
}