{
  "type": "Feature",
  "properties": {
    "iso:country":"US",
    "sg:address":"785 NE 5th St",
    "sg:city":"Crystal River",
    "sg:classifiers":[
        {
            "category":"Building & Trades",
            "subcategory":"Construction",
            "type":"Services"
        }
    ],
    "sg:phone":"+1 352 302 5923",
    "sg:postcode":"34429",
    "sg:province":"FL",
    "sg:tags":[
        "concrete",
        "contractor"
    ],
    "wof:name":"American Custom Crete",
    "wof:placetype":"venue"
},
  "geometry": {"coordinates":[-82.582459,28.898496],"type":"Point"}
}