{
  "type": "Feature",
  "properties": {
    "addr:full":"1308 22nd St Orlando FL 32805",
    "addr:housenumber":"1308",
    "addr:postcode":"32805",
    "addr:street":"22Nd St",
    "iso:country":"US",
    "sg:address":"1308 22nd St",
    "sg:city":"Orlando",
    "sg:classifiers":[
        {
            "category":"Taxi",
            "type":"Transportation"
        }
    ],
    "sg:phone":"+1 407 648 0607",
    "sg:postcode":"32805",
    "sg:province":"FL",
    "sg:tags":[
        "taxicab"
    ],
    "wof:name":"Big Apple Transportation",
    "wof:placetype":"venue"
},
  "geometry": {"coordinates":[-81.39900799999999,28.519022],"type":"Point"}
}