{
  "type": "Feature",
  "properties": {
    "addr:full":"224 Seahorse Ct Marco Island FL 34145",
    "addr:housenumber":"224",
    "addr:postcode":"34145",
    "addr:street":"Seahorse Ct",
    "iso:country":"US",
    "sg:address":"224 Seahorse Ct",
    "sg:city":"Marco Island",
    "sg:classifiers":[
        {
            "category":"Building & Trades",
            "subcategory":"Construction",
            "type":"Services"
        }
    ],
    "sg:phone":"+1 239 642 0220",
    "sg:postcode":"34145",
    "sg:province":"FL",
    "sg:tags":[
        "waterproofing",
        "contractor"
    ],
    "wof:name":"Reflecktor Coatings-Sw Fl",
    "wof:placetype":"venue"
},
  "geometry": {"coordinates":[-81.702326,25.943532],"type":"Point"}
}