{
  "type": "Feature",
  "properties": {
    "iso:country":"US",
    "sg:address":"967 W Lucy St",
    "sg:city":"Homestead",
    "sg:classifiers":[
        {
            "category":"Retail",
            "subcategory":"Funeral Services",
            "type":"Services"
        }
    ],
    "sg:phone":"+1 305 247 0159",
    "sg:postcode":"33034",
    "sg:province":"FL",
    "sg:tags":[
        "director",
        "embalmer",
        "plans-pre-arranged"
    ],
    "wof:name":"Donaldson & Fryar Funeral Home",
    "wof:placetype":"venue"
},
  "geometry": {"coordinates":[-80.464044,25.462518],"type":"Point"}
}