{
  "type": "Feature",
  "properties": {
    "addr:full":"8420 NW 188th Ter Hialeah FL 33015",
    "addr:housenumber":"8420",
    "addr:postcode":"33015",
    "addr:street":"Nw 188Th Ter",
    "iso:country":"US",
    "sg:address":"8420 NW 188th Ter",
    "sg:city":"Hialeah",
    "sg:classifiers":[
        {
            "category":"Organizations",
            "subcategory":"Religious Organization",
            "type":"Services"
        }
    ],
    "sg:phone":"+1 305 971 7400",
    "sg:postcode":"33015",
    "sg:province":"FL",
    "sg:tags":[
        "missouri",
        "synod",
        "churches-lutheran-lutheran",
        "church",
        "lcms"
    ],
    "wof:name":"Trinity Evangelical Lutheran Church Of Miami",
    "wof:placetype":"venue"
},
  "geometry": {"coordinates":[-80.338926,25.944559],"type":"Point"}
}