{
  "type": "Feature",
  "properties": {
    "addr:full":"5007 N Davis Hwy Pensacola FL 32503",
    "addr:housenumber":"5007",
    "addr:postcode":"32503",
    "addr:street":"N Davis Hwy",
    "iso:country":"US",
    "sg:address":"5007 N Davis Hwy",
    "sg:city":"Pensacola",
    "sg:classifiers":[
        {
            "category":"Shopping",
            "subcategory":"Department Store",
            "type":"Retail Goods"
        }
    ],
    "sg:phone":"+1 850 474 0028",
    "sg:postcode":"32503",
    "sg:province":"FL",
    "sg:tags":[
        "shop"
    ],
    "wof:name":"Dollar General",
    "wof:placetype":"venue"
},
  "geometry": {"coordinates":[-87.22510800000001,30.471415],"type":"Point"}
}