{
  "type": "Feature",
  "properties": {
    "addr:full":"97 NE 166th St Miami FL 33162",
    "addr:housenumber":"97",
    "addr:postcode":"33162",
    "addr:street":"Ne 166Th St",
    "iso:country":"US",
    "sg:address":"97 NE 166th St",
    "sg:city":"Miami",
    "sg:classifiers":[
        {
            "category":"Wholesale",
            "subcategory":"Books, Periodicals, & Newspapers",
            "type":"Manufacturing & Wholesale Goods"
        }
    ],
    "sg:phone":"+1 305 816 6737",
    "sg:postcode":"33162",
    "sg:province":"FL",
    "sg:tags":[
        "canvas-wholesale",
        "manufacturer"
    ],
    "wof:name":"Roxy's Canvas",
    "wof:placetype":"venue"
},
  "geometry": {"coordinates":[-80.198329,25.927239],"type":"Point"}
}