{
  "type": "Feature",
  "properties": {
    "iso:country":"US",
    "sg:address":"1414 Rail Head Blvd",
    "sg:city":"Naples",
    "sg:classifiers":[
        {
            "category":"Wholesale",
            "subcategory":"Office Equipment",
            "type":"Manufacturing & Wholesale Goods"
        }
    ],
    "sg:phone":"+1 239 596 1172",
    "sg:postcode":"34110",
    "sg:province":"FL",
    "sg:tags":[
        "machine",
        "duplicating",
        "copying"
    ],
    "wof:name":"DIGITAL Network Systems",
    "wof:placetype":"venue"
},
  "geometry": {"coordinates":[-81.79137799999999,26.309018],"type":"Point"}
}