{
  "type": "Feature",
  "properties": {
    "addr:full":"6650 Trixy St Jacksonville FL 32219",
    "addr:housenumber":"6650",
    "addr:postcode":"32219",
    "addr:street":"Trixy St",
    "iso:country":"US",
    "sg:address":"6650 Trixy St",
    "sg:city":"Jacksonville",
    "sg:classifiers":[
        {
            "category":"Building & Trades",
            "subcategory":"Construction",
            "type":"Services"
        }
    ],
    "sg:phone":"+1 904 693 5564",
    "sg:postcode":"32219",
    "sg:province":"FL",
    "sg:tags":[
        "welder"
    ],
    "wof:name":"Machine Shop & Fabrication",
    "wof:placetype":"venue"
},
  "geometry": {"coordinates":[-81.752072,30.379243],"type":"Point"}
}