{
  "type": "Feature",
  "properties": {
    "addr:full":"7800 SW 87th Ave Miami FL 33173",
    "addr:housenumber":"7800",
    "addr:postcode":"33173",
    "addr:street":"Sw 87Th Ave",
    "iso:country":"US",
    "sg:address":"7800 SW 87th Ave",
    "sg:city":"Miami",
    "sg:classifiers":[
        {
            "category":"Health Services",
            "subcategory":"Doctor",
            "type":"Services"
        }
    ],
    "sg:phone":"+1 305 595 4590",
    "sg:postcode":"33173",
    "sg:province":"FL",
    "sg:tags":[
        "physician",
        "surgeons",
        "infectious",
        "disease",
        "surgeon"
    ],
    "wof:name":"Rodriguez Gilberto MD",
    "wof:placetype":"venue"
},
  "geometry": {"coordinates":[-80.334,25.696899],"type":"Point"}
}