{
  "type": "Feature",
  "properties": {
    "iso:country":"US",
    "sg:address":"4830 SW 8th St",
    "sg:city":"Coral Gables",
    "sg:classifiers":[
        {
            "category":"Health Services",
            "subcategory":"Doctor",
            "type":"Services"
        }
    ],
    "sg:phone":"+1 305 446 1067",
    "sg:postcode":"33134",
    "sg:province":"FL",
    "sg:tags":[
        "surgeon",
        "oral"
    ],
    "wof:name":"Fernandez Maria-Cristina DDS",
    "wof:placetype":"venue"
},
  "geometry": {"coordinates":[-80.274002,25.7642],"type":"Point"}
}