{
  "type": "Feature",
  "properties": {
    "addr:full":"4675 Ponce de Leon Blvd Coral Gables FL 33146",
    "addr:housenumber":"4675",
    "addr:postcode":"33146",
    "addr:street":"Ponce De Leon Blvd",
    "iso:country":"US",
    "sg:address":"4675 Ponce de Leon Blvd",
    "sg:city":"Coral Gables",
    "sg:classifiers":[
        {
            "category":"Health Services",
            "subcategory":"Doctor",
            "type":"Services"
        }
    ],
    "sg:phone":"+1 305 663 4649",
    "sg:postcode":"33146",
    "sg:province":"FL",
    "sg:tags":[
        "physician",
        "surgeon"
    ],
    "sg:website":"www.cruiseguy.com",
    "wof:name":"South Florida Ent Assoc",
    "wof:placetype":"venue"
},
  "geometry": {"coordinates":[-80.262871,25.726929],"type":"Point"}
}