{
  "type": "Feature",
  "properties": {
    "addr:full":"1572 US Hwy 1 S St Augustine FL 32084",
    "addr:housenumber":"1572",
    "addr:postcode":"32084",
    "addr:street":"Us Hwy 1 S St",
    "iso:country":"US",
    "sg:address":"1572 US Hwy 1 S",
    "sg:city":"St Augustine",
    "sg:classifiers":[
        {
            "category":"Home & Garden",
            "subcategory":"Furniture",
            "type":"Retail Goods"
        }
    ],
    "sg:phone":"+1 904 824 0133",
    "sg:postcode":"32084",
    "sg:province":"FL",
    "sg:tags":[
        "unfinished"
    ],
    "wof:name":"Wood You Furniture Store",
    "wof:placetype":"venue"
},
  "geometry": {"coordinates":[-81.323347,29.873291],"type":"Point"}
}