{
  "type": "Feature",
  "properties": {
    "iso:country":"US",
    "sg:address":"8045 NW 36th St Ste 542",
    "sg:city":"Doral",
    "sg:classifiers":[
        {
            "category":"Shopping",
            "subcategory":"Mobile Phones",
            "type":"Retail Goods"
        }
    ],
    "sg:phone":"+1 305 629 9755",
    "sg:postcode":"33166",
    "sg:province":"FL",
    "wof:name":"Wireless Alternative Corp",
    "wof:placetype":"venue"
},
  "geometry": {"coordinates":[-80.32730100000001,25.809799],"type":"Point"}
}