{
  "type": "Feature",
  "properties": {
    "addr:full":"1718 W Baker St Plant City FL 33563",
    "addr:housenumber":"1718",
    "addr:postcode":"33563",
    "addr:street":"W Baker St",
    "iso:country":"US",
    "sg:address":"1718 W Baker St",
    "sg:city":"Plant City",
    "sg:classifiers":[
        {
            "category":"Professional",
            "subcategory":"Lawyer & Legal Services",
            "type":"Services"
        }
    ],
    "sg:phone":"+1 813 659 0338",
    "sg:postcode":"33563",
    "sg:province":"FL",
    "wof:name":"Dale Swope",
    "wof:placetype":"venue"
},
  "geometry": {"coordinates":[-82.13834799999999,28.018053],"type":"Point"}
}