{
  "type": "Feature",
  "properties": {
    "iso:country":"US",
    "sg:address":"16200 San Carlos Blvd",
    "sg:city":"Fort Myers",
    "sg:classifiers":[
        {
            "category":"Personal",
            "subcategory":"Beauty Salon",
            "type":"Services"
        }
    ],
    "sg:phone":"+1 239 466 8383",
    "sg:postcode":"33908",
    "sg:province":"FL",
    "sg:tags":[
        "shop"
    ],
    "wof:name":"Judy's Hair Designers",
    "wof:placetype":"venue"
},
  "geometry": {"coordinates":[-81.94367,26.505864],"type":"Point"}
}