{
  "type": "Feature",
  "properties": {
    "addr:full":"3992 Peninsular Dr Land O Lakes FL 34639",
    "addr:housenumber":"3992",
    "addr:postcode":"34639",
    "addr:street":"Peninsular Dr",
    "iso:country":"US",
    "sg:address":"3992 Peninsular Dr",
    "sg:city":"Land O Lakes",
    "sg:classifiers":[
        {
            "category":"Professional",
            "type":"Services"
        }
    ],
    "sg:phone":"+1 813 995 9221",
    "sg:postcode":"34639",
    "sg:province":"FL",
    "wof:name":"Susan M Draves",
    "wof:placetype":"venue"
},
  "geometry": {"coordinates":[-82.45623399999999,28.213487],"type":"Point"}
}