{
  "type": "Feature",
  "properties": {
    "addr:full":"130 Redstone Ave Crestview FL 32539",
    "addr:housenumber":"130",
    "addr:postcode":"32539",
    "addr:street":"Redstone Ave",
    "iso:country":"US",
    "sg:address":"130 Redstone Ave",
    "sg:city":"Crestview",
    "sg:classifiers":[
        {
            "category":"Health Services",
            "subcategory":"Hospital",
            "type":"Services"
        }
    ],
    "sg:phone":"+1 850 689 8300",
    "sg:postcode":"32539",
    "sg:province":"FL",
    "sg:tags":[
        "general"
    ],
    "wof:name":"Crestview Medical Clinic",
    "wof:placetype":"venue"
},
  "geometry": {"coordinates":[-86.563616,30.73703],"type":"Point"}
}