{
  "type": "Feature",
  "properties": {
    "iso:country":"US",
    "sg:address":"2178 Harbor View Dr",
    "sg:city":"Dunedin",
    "sg:classifiers":[
        {
            "category":"Manufacturing",
            "subcategory":"Motor Vehicles & Parts",
            "type":"Manufacturing & Wholesale Goods"
        }
    ],
    "sg:phone":"+1 727 733 9486",
    "sg:postcode":"34698",
    "sg:province":"FL",
    "sg:tags":[
        "bicycle",
        "related",
        "mfg"
    ],
    "wof:name":"Sport Kicks",
    "wof:placetype":"venue"
},
  "geometry": {"coordinates":[-82.78759599999999,28.03939],"type":"Point"}
}