{
  "type": "Feature",
  "properties": {
    "iso:country":"US",
    "sg:address":"3180 S Military Trl",
    "sg:city":"Lake Worth",
    "sg:classifiers":[
        {
            "category":"Retail",
            "subcategory":"Auto Repair",
            "type":"Services"
        }
    ],
    "sg:phone":"+1 561 582 3499",
    "sg:postcode":"33463",
    "sg:province":"FL",
    "sg:tags":[
        "transmission"
    ],
    "wof:name":"Atlas Transmissions Inc",
    "wof:placetype":"venue"
},
  "geometry": {"coordinates":[-80.112988,26.630457],"type":"Point"}
}