{
  "type": "Feature",
  "properties": {
    "iso:country":"US",
    "sg:address":"15060 SW 152nd Ter",
    "sg:city":"Miami",
    "sg:classifiers":[
        {
            "category":"Manufacturing",
            "subcategory":"Wood Products",
            "type":"Manufacturing & Wholesale Goods"
        }
    ],
    "sg:phone":"+1 305 815 1706",
    "sg:postcode":"33187",
    "sg:province":"FL",
    "sg:tags":[
        "millwork-wholesale",
        "millwork",
        "manufacturer"
    ],
    "wof:name":"Custom Wood Works By Jr Inc",
    "wof:placetype":"venue"
},
  "geometry": {"coordinates":[-80.435508,25.624957],"type":"Point"}
}