{
  "type": "Feature",
  "properties": {
    "iso:country":"US",
    "sg:address":"35753 Auston Dr",
    "sg:city":"Dade City",
    "sg:classifiers":[
        {
            "category":"Shopping",
            "subcategory":"Catalog Store",
            "type":"Retail Goods"
        }
    ],
    "sg:phone":"+1 352 521 5035",
    "sg:postcode":"33525",
    "sg:province":"FL",
    "sg:tags":[
        "mail",
        "house"
    ],
    "wof:name":"Lago International",
    "wof:placetype":"venue"
},
  "geometry": {"coordinates":[-82.22631699999999,28.350709],"type":"Point"}
}