{
  "type": "Feature",
  "properties": {
    "iso:country":"US",
    "sg:address":"8159 Arlington Expy",
    "sg:city":"Jacksonville",
    "sg:classifiers":[
        {
            "category":"Professional",
            "subcategory":"Management & Consulting",
            "type":"Services"
        }
    ],
    "sg:phone":"+1 904 425 3031",
    "sg:postcode":"32211",
    "sg:province":"FL",
    "sg:tags":[
        "consultant",
        "business"
    ],
    "wof:name":"Acumen Development",
    "wof:placetype":"venue"
},
  "geometry": {"coordinates":[-81.567179,30.326812],"type":"Point"}
}