{
  "type": "Feature",
  "properties": {
    "iso:country":"US",
    "sg:address":"5070 Pine Hollow Dr",
    "sg:city":"Pensacola",
    "sg:classifiers":[
        {
            "category":"Professional",
            "subcategory":"Engineering",
            "type":"Services"
        }
    ],
    "sg:phone":"+1 850 476 5428",
    "sg:postcode":"32505",
    "sg:province":"FL",
    "sg:tags":[
        "consulting"
    ],
    "wof:name":"Wartman Engineering Inc",
    "wof:placetype":"venue"
},
  "geometry": {"coordinates":[-87.271798,30.475467],"type":"Point"}
}