{
  "type": "Feature",
  "properties": {
    "iso:country":"US",
    "sg:address":"7400 SW 107th Ave",
    "sg:city":"Miami",
    "sg:classifiers":[
        {
            "category":"Real Estate",
            "subcategory":"Real Estate Operator",
            "type":"Services"
        }
    ],
    "sg:phone":"+1 305 279 6611",
    "sg:postcode":"33173",
    "sg:province":"FL",
    "sg:tags":[
        "apartment"
    ],
    "wof:name":"Sunset Gardens Apartments",
    "wof:placetype":"venue"
},
  "geometry": {"coordinates":[-80.366203,25.6992],"type":"Point"}
}