{
  "type": "Feature",
  "properties": {
    "iso:country":"US",
    "sg:address":"5415 Baptist Church Rd",
    "sg:city":"Tampa",
    "sg:classifiers":[
        {
            "category":"Retail",
            "subcategory":"Auto Repair",
            "type":"Services"
        }
    ],
    "sg:phone":"+1 813 621 4187",
    "sg:postcode":"33610",
    "sg:province":"FL",
    "sg:tags":[
        "machine",
        "automobile",
        "shop"
    ],
    "wof:name":"Miguel's Automotive",
    "wof:placetype":"venue"
},
  "geometry": {"coordinates":[-82.339394,27.996591],"type":"Point"}
}