{
  "type": "Feature",
  "properties": {
    "iso:country":"US",
    "sg:address":"3140 W 76th St",
    "sg:city":"Hialeah",
    "sg:classifiers":[
        {
            "category":"Banks & Credit Unions",
            "subcategory":"Bank",
            "type":"Services"
        }
    ],
    "sg:phone":"+1 305 698 3558",
    "sg:postcode":"33018",
    "sg:province":"FL",
    "sg:tags":[
        "loan",
        "real estate"
    ],
    "wof:name":"Realty Mortgage",
    "wof:placetype":"venue"
},
  "geometry": {"coordinates":[-80.34733,25.891429],"type":"Point"}
}