{
  "type": "Feature",
  "properties": {
    "iso:country":"US",
    "sg:address":"2959 N Annapolis Ave",
    "sg:city":"Hernando",
    "sg:classifiers":[
        {
            "category":"Shopping",
            "type":"Retail Goods"
        }
    ],
    "sg:phone":"+1 352 527 3033",
    "sg:postcode":"34442",
    "sg:province":"FL",
    "sg:tags":[
        "merchandise"
    ],
    "wof:name":"Mss Mobile Pet Service",
    "wof:placetype":"venue"
},
  "geometry": {"coordinates":[-82.419844,28.906417],"type":"Point"}
}