{
  "type": "Feature",
  "properties": {
    "addr:full":"13837 NW 19th Ave Opa Locka FL 33054",
    "addr:housenumber":"13837",
    "addr:postcode":"33054",
    "addr:street":"Nw 19Th Ave;Locka",
    "iso:country":"US",
    "sg:address":"13837 NW 19th Ave",
    "sg:city":"Opa Locka",
    "sg:classifiers":[
        {
            "category":"Shopping",
            "subcategory":"Gifts & Souvenirs",
            "type":"Retail Goods"
        }
    ],
    "sg:phone":"+1 305 681 7796",
    "sg:postcode":"33054",
    "sg:province":"FL",
    "sg:tags":[
        "novelty"
    ],
    "wof:name":"Lisa Tellis Custom Novelties",
    "wof:placetype":"venue"
},
  "geometry": {"coordinates":[-80.23142799999999,25.898901],"type":"Point"}
}