{
  "type": "Feature",
  "properties": {
    "addr:full":"1160 13th St Vero Beach FL 32960",
    "addr:housenumber":"1160",
    "addr:postcode":"32960",
    "addr:street":"13Th St",
    "iso:country":"US",
    "sg:address":"1160 13th St",
    "sg:city":"Vero Beach",
    "sg:classifiers":[
        {
            "category":"Building & Trades",
            "subcategory":"Construction",
            "type":"Services"
        }
    ],
    "sg:phone":"+1 772 299 0224",
    "sg:postcode":"32960",
    "sg:province":"FL",
    "sg:tags":[
        "home",
        "builder"
    ],
    "wof:name":"Holiday Builders Inc",
    "wof:placetype":"venue"
},
  "geometry": {"coordinates":[-80.394642,27.625346],"type":"Point"}
}