{
  "type": "Feature",
  "properties": {
    "addr:full":"6201 NW 21st Ct Boca Raton FL 33496",
    "addr:housenumber":"6201",
    "addr:postcode":"33496",
    "addr:street":"Nw 21St Ct",
    "iso:country":"US",
    "sg:address":"6201 NW 21st Ct",
    "sg:city":"Boca Raton",
    "sg:classifiers":[
        {
            "category":"Manufacturing",
            "subcategory":"Toys & Sporting Goods",
            "type":"Manufacturing & Wholesale Goods"
        }
    ],
    "sg:phone":"+1 561 994 4611",
    "sg:postcode":"33496",
    "sg:province":"FL",
    "sg:tags":[
        "manufacture"
    ],
    "wof:name":"Baja Products Industries Inc",
    "wof:placetype":"venue"
},
  "geometry": {"coordinates":[-80.12521,26.406432],"type":"Point"}
}