{
  "type": "Feature",
  "properties": {
    "addr:full":"8350 Estero Blvd Fort Myers Beach FL 33931",
    "addr:housenumber":"8350",
    "addr:postcode":"33931",
    "addr:street":"Estero Blvd",
    "iso:country":"US",
    "sg:address":"8350 Estero Blvd",
    "sg:city":"Fort Myers Beach",
    "sg:classifiers":[
        {
            "category":"Real Estate",
            "subcategory":"Real Estate Operator",
            "type":"Services"
        }
    ],
    "sg:phone":"+1 239 463 2135",
    "sg:postcode":"33931",
    "sg:province":"FL",
    "sg:tags":[
        "condominium"
    ],
    "wof:name":"Carlos Point Condominium Assoc",
    "wof:placetype":"venue"
},
  "geometry": {"coordinates":[-81.885576,26.404787],"type":"Point"}
}