{
  "type": "Feature",
  "properties": {
    "addr:full":"5601 Banos Ave Cocoa FL 32927",
    "addr:housenumber":"5601",
    "addr:postcode":"32927",
    "addr:street":"Banos Ave",
    "iso:country":"US",
    "sg:address":"5601 Banos Ave",
    "sg:city":"Cocoa",
    "sg:classifiers":[
        {
            "category":"Building & Trades",
            "subcategory":"Landscaping Services",
            "type":"Services"
        }
    ],
    "sg:phone":"+1 321 631 6909",
    "sg:postcode":"32927",
    "sg:province":"FL",
    "wof:name":"Arthur Mobley",
    "wof:placetype":"venue"
},
  "geometry": {"coordinates":[-80.815983,28.468266],"type":"Point"}
}