{
  "type": "Feature",
  "properties": {
    "addr:full":"2721 Forsyth Rd Ste 105 Winter Park FL 32792",
    "addr:housenumber":"2721",
    "addr:postcode":"32792",
    "addr:street":"Forsyth Rd Ste 105",
    "iso:country":"US",
    "sg:address":"2721 Forsyth Rd Ste 105",
    "sg:city":"Winter Park",
    "sg:classifiers":[
        {
            "category":"Building & Trades",
            "subcategory":"Pest Control",
            "type":"Services"
        }
    ],
    "sg:phone":"+1 407 678 2525",
    "sg:postcode":"32792",
    "sg:province":"FL",
    "wof:name":"Superior Pest Inspections Inc",
    "wof:placetype":"venue"
},
  "geometry": {"coordinates":[-81.29589799999999,28.5891],"type":"Point"}
}