{
  "type": "Feature",
  "properties": {
    "addr:full":"25 52nd St S St Petersburg FL 33707",
    "addr:housenumber":"25",
    "addr:postcode":"33707",
    "addr:street":"52Nd St S",
    "iso:country":"US",
    "sg:address":"25 52nd St S",
    "sg:city":"St Petersburg",
    "sg:classifiers":[
        {
            "category":"Banks & Credit Unions",
            "subcategory":"Bank",
            "type":"Services"
        }
    ],
    "sg:phone":"+1 727 258 5626",
    "sg:postcode":"33707",
    "sg:province":"FL",
    "sg:tags":[
        "loan",
        "real estate"
    ],
    "wof:name":"Source 1 Funding",
    "wof:placetype":"venue"
},
  "geometry": {"coordinates":[-82.70399500000001,27.770269],"type":"Point"}
}