{
  "type": "Feature",
  "properties": {
    "iso:country":"US",
    "sg:address":"1000 S Semoran Blvd",
    "sg:city":"Winter Park",
    "sg:classifiers":[
        {
            "category":"Building & Trades",
            "subcategory":"Construction",
            "type":"Services"
        }
    ],
    "sg:phone":"+1 407 671 5372",
    "sg:postcode":"32792",
    "sg:province":"FL",
    "sg:tags":[
        "residential"
    ],
    "wof:name":"Inm Construction Inc",
    "wof:placetype":"venue"
},
  "geometry": {"coordinates":[-81.307834,28.580935],"type":"Point"}
}