{
  "type": "Feature",
  "properties": {
    "iso:country":"US",
    "sg:address":"413 Anastasia Blvd",
    "sg:city":"St Augustine",
    "sg:classifiers":[
        {
            "category":"Shopping",
            "subcategory":"Used Merchandise",
            "type":"Retail Goods"
        }
    ],
    "sg:phone":"+1 904 826 1459",
    "sg:postcode":"32080",
    "sg:province":"FL",
    "sg:tags":[
        "shop",
        "consignment"
    ],
    "wof:name":"Designers Etc",
    "wof:placetype":"venue"
},
  "geometry": {"coordinates":[-81.29730499999999,29.890908],"type":"Point"}
}