{
  "type": "Feature",
  "properties": {
    "iso:country":"US",
    "sg:address":"1880 S Federal Hwy",
    "sg:city":"Delray Beach",
    "sg:classifiers":[
        {
            "category":"Health Services",
            "subcategory":"Health Practitioner",
            "type":"Services"
        }
    ],
    "sg:phone":"+1 561 272 7438",
    "sg:postcode":"33483",
    "sg:province":"FL",
    "wof:name":"Yc Health Service Center",
    "wof:placetype":"venue"
},
  "geometry": {"coordinates":[-80.0715,26.439436],"type":"Point"}
}