{
  "type": "Feature",
  "properties": {
    "iso:country":"US",
    "sg:address":"648 Heron Bay Dr",
    "sg:city":"Orlando",
    "sg:classifiers":[
        {
            "category":"Sports & Exercise",
            "subcategory":"Gym",
            "type":"Entertainment"
        },
        {
            "category":"Arena",
            "subcategory":"Sports Club",
            "type":"Entertainment"
        }
    ],
    "sg:phone":"+1 407 380 7906",
    "sg:postcode":"32825",
    "sg:province":"FL",
    "sg:tags":[
        "program",
        "health",
        "physical",
        "fitness"
    ],
    "sg:website":"http://www.jazzercise.com",
    "wof:name":"Jazzercise",
    "wof:placetype":"venue"
},
  "geometry": {"coordinates":[-81.22197,28.553659],"type":"Point"}
}