{
  "type": "Feature",
  "properties": {
    "iso:country":"US",
    "sg:address":"2546 Thompson St",
    "sg:city":"Fort Myers",
    "sg:classifiers":[
        {
            "category":"Home & Garden",
            "subcategory":"Furniture",
            "type":"Retail Goods"
        }
    ],
    "sg:phone":"+1 239 334 2571",
    "sg:postcode":"33901",
    "sg:province":"FL",
    "sg:tags":[
        "household",
        "store"
    ],
    "wof:name":"White Furniture Co",
    "wof:placetype":"venue"
},
  "geometry": {"coordinates":[-81.861,26.6432],"type":"Point"}
}