{
  "type": "Feature",
  "properties": {
    "addr:full":"22827 State Hwy 7 Boca Raton FL 33428",
    "addr:housenumber":"22827",
    "addr:postcode":"33428",
    "addr:street":"State Hwy 7",
    "iso:country":"US",
    "sg:address":"22827 State Hwy 7",
    "sg:city":"Boca Raton",
    "sg:classifiers":[
        {
            "category":"Retail",
            "subcategory":"Self-service Laundry",
            "type":"Services"
        }
    ],
    "sg:phone":"+1 561 483 8287",
    "sg:postcode":"33428",
    "sg:province":"FL",
    "wof:name":"Sunny Wash Coin Laundry",
    "wof:placetype":"venue"
},
  "geometry": {"coordinates":[-80.20321800000001,26.336724],"type":"Point"}
}