{
  "type": "Feature",
  "properties": {
    "iso:country":"US",
    "sg:address":"868 NW 21st Ter",
    "sg:city":"Miami",
    "sg:classifiers":[
        {
            "category":"Wholesale",
            "subcategory":"Groceries",
            "type":"Manufacturing & Wholesale Goods"
        },
        {
            "category":"Food & Beverages",
            "subcategory":"Supermarket",
            "type":"Retail Goods"
        },
        {
            "category":"Food & Beverages",
            "subcategory":"Groceries & Convenience Stores",
            "type":"Retail Goods"
        }
    ],
    "sg:phone":"+1 305 545 0044",
    "sg:postcode":"33127",
    "sg:province":"FL",
    "sg:tags":[
        "frozen",
        "super",
        "foods-wholesale"
    ],
    "sg:website":"www.lafe.com",
    "wof:name":"LAFE Foods",
    "wof:placetype":"venue"
},
  "geometry": {"coordinates":[-80.20909899999999,25.797001],"type":"Point"}
}