{
  "type": "Feature",
  "properties": {
    "iso:country":"US",
    "sg:address":"606 61st Ave",
    "sg:city":"Vero Beach",
    "sg:classifiers":[
        {
            "category":"Building & Trades",
            "subcategory":"Construction",
            "type":"Services"
        }
    ],
    "sg:phone":"+1 772 562 0345",
    "sg:postcode":"32968",
    "sg:province":"FL",
    "sg:tags":[
        "carpentry",
        "contractor"
    ],
    "wof:name":"Bernard R Riley Carpentry",
    "wof:placetype":"venue"
},
  "geometry": {"coordinates":[-80.452825,27.614115],"type":"Point"}
}