{
  "type": "Feature",
  "properties": {
    "addr:full":"8138 Anatto Ct Orlando FL 32822",
    "addr:housenumber":"8138",
    "addr:postcode":"32822",
    "addr:street":"Anatto Ct",
    "iso:country":"US",
    "sg:address":"8138 Anatto Ct",
    "sg:city":"Orlando",
    "sg:classifiers":[
        {
            "category":"Professional",
            "subcategory":"Business Services",
            "type":"Services"
        }
    ],
    "sg:phone":"+1 407 658 1615",
    "sg:postcode":"32822",
    "sg:province":"FL",
    "wof:name":"Rapport Associates Inc",
    "wof:placetype":"venue"
},
  "geometry": {"coordinates":[-81.27480799999999,28.515694],"type":"Point"}
}