{
  "type": "Feature",
  "properties": {
    "iso:country":"US",
    "sg:address":"810 Westwood Dr",
    "sg:city":"Perry",
    "sg:classifiers":[
        {
            "category":"Wholesale",
            "subcategory":"Durable Goods & Equipment",
            "type":"Manufacturing & Wholesale Goods"
        }
    ],
    "sg:phone":"+1 850 584 7507",
    "sg:postcode":"32348",
    "sg:province":"FL",
    "sg:tags":[
        "fire",
        "extinguisher"
    ],
    "wof:name":"Perry Fire Extinguisher Co",
    "wof:placetype":"venue"
},
  "geometry": {"coordinates":[-83.58723500000001,30.087277],"type":"Point"}
}