{
  "type": "Feature",
  "properties": {
    "iso:country":"US",
    "sg:address":"508 E 49th St",
    "sg:city":"Hialeah",
    "sg:classifiers":[
        {
            "category":"Health Services",
            "subcategory":"Doctor",
            "type":"Services"
        }
    ],
    "sg:phone":"+1 305 687 0112",
    "sg:postcode":"33013",
    "sg:province":"FL",
    "sg:tags":[
        "physician",
        "surgeon"
    ],
    "wof:name":"Reny H Kindelan MD",
    "wof:placetype":"venue"
},
  "geometry": {"coordinates":[-80.270848,25.867156],"type":"Point"}
}