{
  "type": "Feature",
  "properties": {
    "iso:country":"US",
    "sg:address":"3367 N University Dr",
    "sg:city":"Hollywood",
    "sg:classifiers":[
        {
            "category":"Recreation",
            "type":"Entertainment"
        }
    ],
    "sg:phone":"+1 954 433 2285",
    "sg:postcode":"33024",
    "sg:province":"FL",
    "sg:tags":[
        "range",
        "baseball",
        "batting"
    ],
    "wof:name":"South Florida Baseball Train",
    "wof:placetype":"venue"
},
  "geometry": {"coordinates":[-80.251462,26.044497],"type":"Point"}
}