{
  "type": "Feature",
  "properties": {
    "iso:country":"US",
    "sg:address":"1201 Sunset Point Rd",
    "sg:city":"Clearwater",
    "sg:classifiers":[
        {
            "category":"Food & Beverages",
            "subcategory":"Groceries & Convenience Stores",
            "type":"Retail Goods"
        }
    ],
    "sg:phone":"+1 727 446 6254",
    "sg:postcode":"33755",
    "sg:province":"FL",
    "wof:name":"Circle A Food Store",
    "wof:placetype":"venue"
},
  "geometry": {"coordinates":[-82.786868,27.990073],"type":"Point"}
}