{
  "type": "Feature",
  "properties": {
    "addr:full":"15385 Myrtle St Fort Myers FL 33908",
    "addr:housenumber":"15385",
    "addr:postcode":"33908",
    "addr:street":"Myrtle St",
    "iso:country":"US",
    "sg:address":"15385 Myrtle St",
    "sg:city":"Fort Myers",
    "sg:classifiers":[
        {
            "category":"Autos & Motor Vehicles",
            "subcategory":"Automobile Sales",
            "type":"Retail Goods"
        }
    ],
    "sg:phone":"+1 239 466 4423",
    "sg:postcode":"33908",
    "sg:province":"FL",
    "sg:tags":[
        "used"
    ],
    "wof:name":"Autobrokers",
    "wof:placetype":"venue"
},
  "geometry": {"coordinates":[-81.964983,26.517687],"type":"Point"}
}