{
  "type": "Feature",
  "properties": {
    "iso:country":"US",
    "sg:address":"1709 Arbor Knoll Loop",
    "sg:city":"Trinity",
    "sg:classifiers":[
        {
            "category":"Personal",
            "subcategory":"Beauty Salon",
            "type":"Services"
        }
    ],
    "sg:phone":"+1 727 375 5950",
    "sg:postcode":"34655",
    "sg:province":"FL",
    "sg:tags":[
        "hair",
        "stylist"
    ],
    "wof:name":"Hair Inn Inc",
    "wof:placetype":"venue"
},
  "geometry": {"coordinates":[-82.615573,28.183103],"type":"Point"}
}