{
  "type": "Feature",
  "properties": {
    "iso:country":"US",
    "sg:address":"3412 Little Country Rd",
    "sg:city":"Parrish",
    "sg:classifiers":[
        {
            "category":"Professional",
            "type":"Services"
        }
    ],
    "sg:phone":"+1 941 776 0230",
    "sg:postcode":"34219",
    "sg:province":"FL",
    "sg:tags":[
        "establishment"
    ],
    "wof:name":"Cline Products",
    "wof:placetype":"venue"
},
  "geometry": {"coordinates":[-82.432812,27.540932],"type":"Point"}
}