{
  "type": "Feature",
  "properties": {
    "iso:country":"US",
    "sg:address":"2064 E Edgewood Dr",
    "sg:city":"Lakeland",
    "sg:classifiers":[
        {
            "category":"Restaurant",
            "type":"Food & Drink"
        }
    ],
    "sg:phone":"+1 863 668 9336",
    "sg:postcode":"33803",
    "sg:province":"FL",
    "wof:name":"Plantation Cafe",
    "wof:placetype":"venue"
},
  "geometry": {"coordinates":[-81.92077500000001,28.013314],"type":"Point"}
}