{
  "type": "Feature",
  "properties": {
    "addr:full":"11722 Raintree Village Blvd Tampa FL 33617",
    "addr:housenumber":"11722",
    "addr:postcode":"33617",
    "addr:street":"Raintree Village Blvd",
    "iso:country":"US",
    "sg:address":"11722 Raintree Village Blvd",
    "sg:city":"Tampa",
    "sg:classifiers":[
        {
            "category":"Professional",
            "type":"Services"
        }
    ],
    "sg:phone":"+1 813 985 1811",
    "sg:postcode":"33617",
    "sg:province":"FL",
    "wof:name":"Greenwood Marina",
    "wof:placetype":"venue"
},
  "geometry": {"coordinates":[-82.386527,28.055059],"type":"Point"}
}