{
  "type": "Feature",
  "properties": {
    "addr:full":"1815 Griffin Rd Dania FL 33004",
    "addr:housenumber":"1815",
    "addr:postcode":"33004",
    "addr:street":"Griffin Rd",
    "iso:country":"US",
    "sg:address":"1815 Griffin Rd",
    "sg:city":"Dania",
    "sg:classifiers":[
        {
            "category":"Insurance",
            "subcategory":"Insurance Agent",
            "type":"Services"
        }
    ],
    "sg:phone":"+1 954 923 1900",
    "sg:postcode":"33004",
    "sg:province":"FL",
    "sg:tags":[
        "company"
    ],
    "wof:name":"Global Insurance MGT Co LLC",
    "wof:placetype":"venue"
},
  "geometry": {"coordinates":[-80.15945600000001,26.063163],"type":"Point"}
}