{
  "type": "Feature",
  "properties": {
    "iso:country":"US",
    "sg:address":"900 US Hwy 1",
    "sg:city":"Lake Park",
    "sg:classifiers":[
        {
            "category":"Insurance",
            "subcategory":"Insurance Agent",
            "type":"Services"
        }
    ],
    "sg:phone":"+1 561 842 7773",
    "sg:postcode":"33403",
    "sg:province":"FL",
    "wof:name":"TLC Insurance Assoc LLC",
    "wof:placetype":"venue"
},
  "geometry": {"coordinates":[-80.055041,26.801011],"type":"Point"}
}