{
  "type": "Feature",
  "properties": {
    "iso:country":"US",
    "sg:address":"5861 12th Ave SW",
    "sg:city":"Naples",
    "sg:classifiers":[
        {
            "category":"Real Estate",
            "subcategory":"Developer",
            "type":"Services"
        }
    ],
    "sg:phone":"+1 239 304 4614",
    "sg:postcode":"34116",
    "sg:province":"FL",
    "wof:name":"R & P Development LLC",
    "wof:placetype":"venue"
},
  "geometry": {"coordinates":[-81.72439,26.20651],"type":"Point"}
}