{
  "type": "Feature",
  "properties": {
    "addr:full":"947 W Taft Vineland Rd Orlando FL 32824",
    "addr:housenumber":"947",
    "addr:postcode":"32824",
    "addr:street":"W Taft Vineland Rd",
    "iso:country":"US",
    "sg:address":"947 W Taft Vineland Rd",
    "sg:city":"Orlando",
    "sg:classifiers":[
        {
            "category":"Retail",
            "subcategory":"Auto Repair",
            "type":"Services"
        }
    ],
    "sg:phone":"+1 407 438 0100",
    "sg:postcode":"32824",
    "sg:province":"FL",
    "sg:tags":[
        "general"
    ],
    "wof:name":"Trucklube 1 Inc",
    "wof:placetype":"venue"
},
  "geometry": {"coordinates":[-81.390919,28.421541],"type":"Point"}
}