{
  "type": "Feature",
  "properties": {
    "iso:country":"US",
    "sg:address":"722 W Flagler St",
    "sg:city":"Miami",
    "sg:classifiers":[
        {
            "category":"Restaurant",
            "type":"Food & Drink"
        }
    ],
    "sg:phone":"+1 305 547 2341",
    "sg:postcode":"33130",
    "sg:province":"FL",
    "wof:name":"Sabor Hondureno",
    "wof:placetype":"venue"
},
  "geometry": {"coordinates":[-80.207358,25.773653],"type":"Point"}
}