{
  "type": "Feature",
  "properties": {
    "addr:full":"2170 James Dr Oviedo FL 32765",
    "addr:housenumber":"2170",
    "addr:postcode":"32765",
    "addr:street":"James Dr",
    "iso:country":"US",
    "sg:address":"2170 James Dr",
    "sg:city":"Oviedo",
    "sg:classifiers":[
        {
            "category":"Place Of Worship",
            "type":"Public Place"
        }
    ],
    "sg:phone":"+1 407 977 1212",
    "sg:postcode":"32765",
    "sg:province":"FL",
    "sg:tags":[
        "church"
    ],
    "wof:name":"New Life Ministry",
    "wof:placetype":"venue"
},
  "geometry": {"coordinates":[-81.24032699999999,28.63078],"type":"Point"}
}