{
  "type": "Feature",
  "properties": {
    "addr:full":"7767 NW 25th St Pompano Beach FL 33063",
    "addr:housenumber":"7767",
    "addr:postcode":"33063",
    "addr:street":"Nw 25Th St",
    "iso:country":"US",
    "sg:address":"7767 NW 25th St",
    "sg:city":"Pompano Beach",
    "sg:classifiers":[
        {
            "category":"Shopping",
            "subcategory":"Florist",
            "type":"Retail Goods"
        }
    ],
    "sg:phone":"+1 954 341 2375",
    "sg:postcode":"33063",
    "sg:province":"FL",
    "wof:name":"Rose Garden of Grove Florist",
    "wof:placetype":"venue"
},
  "geometry": {"coordinates":[-80.22782599999999,26.25829],"type":"Point"}
}