{
  "type": "Feature",
  "properties": {
    "addr:full":"13550 Cleveland Ave Fort Myers FL 33903",
    "addr:housenumber":"13550",
    "addr:postcode":"33903",
    "addr:street":"Cleveland Ave",
    "iso:country":"US",
    "sg:address":"13550 Cleveland Ave",
    "sg:city":"Fort Myers",
    "sg:classifiers":[
        {
            "category":"Shopping",
            "subcategory":"Stationery & Office Supplies",
            "type":"Retail Goods"
        }
    ],
    "sg:phone":"+1 239 997 2440",
    "sg:postcode":"33903",
    "sg:province":"FL",
    "wof:name":"Office Depot",
    "wof:placetype":"venue"
},
  "geometry": {"coordinates":[-81.88542,26.662245],"type":"Point"}
}