{
  "type": "Feature",
  "properties": {
    "addr:full":"260 S Barfield Hwy Pahokee FL 33476",
    "addr:housenumber":"260",
    "addr:postcode":"33476",
    "addr:street":"S Barfield Hwy",
    "iso:country":"US",
    "sg:address":"260 S Barfield Hwy",
    "sg:city":"Pahokee",
    "sg:classifiers":[
        {
            "category":"Health Services",
            "subcategory":"Doctor",
            "type":"Services"
        }
    ],
    "sg:phone":"+1 561 924 7788",
    "sg:postcode":"33476",
    "sg:province":"FL",
    "sg:tags":[
        "physician",
        "surgeon"
    ],
    "wof:name":"Comprehensive Kare At Thelakes",
    "wof:placetype":"venue"
},
  "geometry": {"coordinates":[-80.66118,26.820954],"type":"Point"}
}