{
  "type": "Feature",
  "properties": {
    "iso:country":"US",
    "sg:address":"7601 SW 162nd Pl",
    "sg:city":"Miami",
    "sg:classifiers":[
        {
            "category":"Building & Trades",
            "subcategory":"Cleaning & Sanitation",
            "type":"Services"
        }
    ],
    "sg:phone":"+1 305 269 9000",
    "sg:postcode":"33193",
    "sg:province":"FL",
    "sg:tags":[
        "janitor"
    ],
    "wof:name":"First Service Group Inc Condo",
    "wof:placetype":"venue"
},
  "geometry": {"coordinates":[-80.456767,25.713594],"type":"Point"}
}