{
  "type": "Feature",
  "properties": {
    "addr:full":"2705 State Hwy 44 Inverness FL 34453",
    "addr:housenumber":"2705",
    "addr:postcode":"34453",
    "addr:street":"State Hwy 44",
    "iso:country":"US",
    "sg:address":"2705 State Hwy 44",
    "sg:city":"Inverness",
    "sg:classifiers":[
        {
            "category":"Retail",
            "subcategory":"Auto Repair",
            "type":"Services"
        }
    ],
    "sg:phone":"+1 352 344 0411",
    "sg:postcode":"34453",
    "sg:province":"FL",
    "sg:tags":[
        "transmission"
    ],
    "wof:name":"Gator Transmission",
    "wof:placetype":"venue"
},
  "geometry": {"coordinates":[-82.387795,28.853665],"type":"Point"}
}