{
  "type": "Feature",
  "properties": {
    "addr:full":"1414 NW 107th Ave Miami FL 33172",
    "addr:housenumber":"1414",
    "addr:postcode":"33172",
    "addr:street":"Nw 107Th Ave",
    "iso:country":"US",
    "sg:address":"1414 NW 107th Ave",
    "sg:city":"Miami",
    "sg:classifiers":[
        {
            "category":"Professional",
            "type":"Services"
        }
    ],
    "sg:phone":"+1 305 418 0064",
    "sg:postcode":"33172",
    "sg:province":"FL",
    "wof:name":"Tms-Imid Inc",
    "wof:placetype":"venue"
},
  "geometry": {"coordinates":[-80.368842,25.786796],"type":"Point"}
}