{
  "type": "Feature",
  "properties": {
    "addr:full":"5043 Bayou Blvd Pensacola FL 32503",
    "addr:housenumber":"5043",
    "addr:postcode":"32503",
    "addr:street":"Bayou Blvd",
    "iso:country":"US",
    "sg:address":"5043 Bayou Blvd",
    "sg:city":"Pensacola",
    "sg:classifiers":[
        {
            "category":"Government",
            "subcategory":"Office",
            "type":"Public Place"
        }
    ],
    "sg:phone":"+1 850 474 0567",
    "sg:postcode":"32503",
    "sg:province":"FL",
    "sg:tags":[
        "armed",
        "force",
        "recruiting"
    ],
    "wof:name":"US Army Recruiting",
    "wof:placetype":"venue"
},
  "geometry": {"coordinates":[-87.211645,30.472948],"type":"Point"}
}