{
  "type": "Feature",
  "properties": {
    "iso:country":"US",
    "sg:address":"9907 NW 9th Street Cir",
    "sg:city":"Miami",
    "sg:classifiers":[
        {
            "category":"Shopping",
            "subcategory":"Hobbies, Toys, & Games",
            "type":"Retail Goods"
        }
    ],
    "sg:phone":"+1 305 553 3898",
    "sg:postcode":"33172",
    "sg:province":"FL",
    "sg:tags":[
        "doll"
    ],
    "wof:name":"House Of Dolls Warehouse",
    "wof:placetype":"venue"
},
  "geometry": {"coordinates":[-80.361249,25.77789],"type":"Point"}
}