{
  "type": "Feature",
  "properties": {
    "iso:country":"US",
    "sg:address":"4251 Woodbrier Dr",
    "sg:city":"Fort Myers",
    "sg:classifiers":[
        {
            "category":"Retail",
            "subcategory":"Laundry & Dry Cleaning",
            "type":"Services"
        }
    ],
    "sg:phone":"+1 239 693 9494",
    "sg:postcode":"33905",
    "sg:province":"FL",
    "sg:tags":[
        "cleaners",
        "rug",
        "carpet"
    ],
    "wof:name":"Ocean Floors Inc",
    "wof:placetype":"venue"
},
  "geometry": {"coordinates":[-81.785141,26.681426],"type":"Point"}
}