{
  "type": "Feature",
  "properties": {
    "iso:country":"US",
    "sg:address":"520 44th Street Ct W",
    "sg:city":"Palmetto",
    "sg:classifiers":[
        {
            "category":"Building & Trades",
            "subcategory":"Plumbing",
            "type":"Services"
        }
    ],
    "sg:phone":"+1 941 723 9492",
    "sg:postcode":"34221",
    "sg:province":"FL",
    "sg:tags":[
        "contractor"
    ],
    "wof:name":"J B Air Conditioning Inc",
    "wof:placetype":"venue"
},
  "geometry": {"coordinates":[-82.567274,27.554049],"type":"Point"}
}