{
  "type": "Feature",
  "properties": {
    "addr:full":"1455 NW 107th Ave Sp 366 Doral FL 33172",
    "addr:housenumber":"1455;366",
    "addr:postcode":"33172",
    "addr:street":"Nw 107Th Ave Sp",
    "iso:country":"US",
    "sg:address":"1455 NW 107th Ave Sp 366",
    "sg:city":"Doral",
    "sg:classifiers":[
        {
            "category":"Shopping",
            "subcategory":"Hobbies, Toys, & Games",
            "type":"Retail Goods"
        },
        {
            "category":"Professional",
            "subcategory":"Computer Services",
            "type":"Services"
        }
    ],
    "sg:phone":"+1 305 406 1444",
    "sg:postcode":"33172",
    "sg:province":"FL",
    "sg:tags":[
        "toy",
        "supply",
        "video",
        "store",
        "software"
    ],
    "wof:name":"Eb Games",
    "wof:placetype":"venue"
},
  "geometry": {"coordinates":[-80.36866000000001,25.787121],"type":"Point"}
}