{
  "type": "Feature",
  "properties": {
    "iso:country":"US",
    "sg:address":"3974 S Lake Orlando Pkwy",
    "sg:city":"Orlando",
    "sg:classifiers":[
        {
            "category":"Retail",
            "subcategory":"Repair Shop",
            "type":"Services"
        }
    ],
    "sg:phone":"+1 407 295 3732",
    "sg:postcode":"32808",
    "sg:province":"FL",
    "sg:tags":[
        "television",
        "radio-service"
    ],
    "wof:name":"Michael Mcdaniel Tv Inc",
    "wof:placetype":"venue"
},
  "geometry": {"coordinates":[-81.427492,28.589833],"type":"Point"}
}