{
  "type": "Feature",
  "properties": {
    "iso:country":"US",
    "sg:address":"1515 N University Dr",
    "sg:city":"Coral Springs",
    "sg:classifiers":[
        {
            "category":"Professional",
            "type":"Services"
        }
    ],
    "sg:phone":"+1 954 255 0313",
    "sg:postcode":"33071",
    "sg:province":"FL",
    "sg:tags":[
        "establishment"
    ],
    "wof:name":"Estrellita Inc",
    "wof:placetype":"venue"
},
  "geometry": {"coordinates":[-80.253219,26.24924],"type":"Point"}
}