{
  "type": "Feature",
  "properties": {
    "addr:full":"50 S US Hwy 1 Jupiter FL 33477",
    "addr:housenumber":"50",
    "addr:postcode":"33477",
    "addr:street":"S Us Hwy 1",
    "iso:country":"US",
    "sg:address":"50 S US Hwy 1",
    "sg:city":"Jupiter",
    "sg:classifiers":[
        {
            "category":"Real Estate",
            "subcategory":"Real Estate Agent",
            "type":"Services"
        }
    ],
    "sg:phone":"+1 561 575 9722",
    "sg:postcode":"33477",
    "sg:province":"FL",
    "sg:tags":[
        "management"
    ],
    "wof:name":"Oak Tree Management",
    "wof:placetype":"venue"
},
  "geometry": {"coordinates":[-80.080724,26.933517],"type":"Point"}
}