{
  "type": "Feature",
  "properties": {
    "addr:full":"1145 33rd St S St Petersburg FL 33712",
    "addr:housenumber":"1145",
    "addr:postcode":"33712",
    "addr:street":"33Rd St S",
    "iso:country":"US",
    "sg:address":"1145 33rd St S",
    "sg:city":"St Petersburg",
    "sg:classifiers":[
        {
            "category":"Retail",
            "subcategory":"Auto Repair",
            "type":"Services"
        }
    ],
    "sg:phone":"+1 727 323 7393",
    "sg:postcode":"33712",
    "sg:province":"FL",
    "sg:tags":[
        "repairing",
        "automobile"
    ],
    "wof:name":"Shamie Auto Repair",
    "wof:placetype":"venue"
},
  "geometry": {"coordinates":[-82.67863199999999,27.757805],"type":"Point"}
}