{
  "type": "Feature",
  "properties": {
    "iso:country":"US",
    "sg:address":"14375 Okeechobee Blvd",
    "sg:city":"Loxahatchee",
    "sg:classifiers":[
        {
            "category":"Wholesale",
            "subcategory":"Plants",
            "type":"Manufacturing & Wholesale Goods"
        }
    ],
    "sg:phone":"+1 561 790 2530",
    "sg:postcode":"33470",
    "sg:province":"FL",
    "sg:tags":[
        "nursery",
        "tree"
    ],
    "wof:name":"Landscape Design Concepts",
    "wof:placetype":"venue"
},
  "geometry": {"coordinates":[-80.26858,26.70655],"type":"Point"}
}