{
  "type": "Feature",
  "properties": {
    "iso:country":"US",
    "sg:address":"350 E Burleigh Blvd",
    "sg:city":"Tavares",
    "sg:classifiers":[
        {
            "category":"Banks & Credit Unions",
            "subcategory":"Bank",
            "type":"Services"
        }
    ],
    "sg:phone":"+1 352 742 3660",
    "sg:postcode":"32778",
    "sg:province":"FL",
    "sg:tags":[
        "commercial",
        "saving"
    ],
    "sg:website":"https://www.wachovia.com/?DCMP=KNL-CPS-DS-Directory-0703&HBX_PK=Banks&HBX_OU=71",
    "wof:name":"Wachovia Bank",
    "wof:placetype":"venue"
},
  "geometry": {"coordinates":[-81.72572,28.816193],"type":"Point"}
}