{
  "type": "Feature",
  "properties": {
    "addr:full":"2303 US Hwy 17 Bartow FL 33830",
    "addr:housenumber":"2303",
    "addr:postcode":"33830",
    "addr:street":"Us Hwy 17",
    "iso:country":"US",
    "sg:address":"2303 US Hwy 17",
    "sg:city":"Bartow",
    "sg:classifiers":[
        {
            "category":"Autos & Motor Vehicles",
            "subcategory":"Automobile Sales",
            "type":"Retail Goods"
        }
    ],
    "sg:phone":"+1 863 533 8855",
    "sg:postcode":"33830",
    "sg:province":"FL",
    "sg:tags":[
        "truck"
    ],
    "wof:name":"Keith Tyson Truck & Equip",
    "wof:placetype":"venue"
},
  "geometry": {"coordinates":[-81.82866300000001,27.870745],"type":"Point"}
}