{
  "type": "Feature",
  "properties": {
    "iso:country":"US",
    "sg:address":"9601 SE Little Club Way N",
    "sg:city":"Jupiter",
    "sg:classifiers":[
        {
            "category":"Real Estate",
            "subcategory":"Real Estate Operator",
            "type":"Services"
        },
        {
            "category":"Organizations",
            "subcategory":"Community Association",
            "type":"Services"
        }
    ],
    "sg:phone":"+1 561 746 1869",
    "sg:postcode":"33469",
    "sg:province":"FL",
    "sg:tags":[
        "condominium"
    ],
    "wof:name":"Little Club Condominium Assn",
    "wof:placetype":"venue"
},
  "geometry": {"coordinates":[-80.124751,26.983266],"type":"Point"}
}