{
  "type": "Feature",
  "properties": {
    "iso:country":"US",
    "sg:address":"539 Bob Sikes Blvd",
    "sg:city":"Fort Walton Beach",
    "sg:classifiers":[
        {
            "category":"Building & Trades",
            "subcategory":"Construction",
            "type":"Services"
        }
    ],
    "sg:phone":"+1 850 864 5362",
    "sg:postcode":"32547",
    "sg:province":"FL",
    "sg:tags":[
        "general",
        "contractor"
    ],
    "wof:name":"Rdrj Construction",
    "wof:placetype":"venue"
},
  "geometry": {"coordinates":[-86.622587,30.445512],"type":"Point"}
}