{
  "type": "Feature",
  "properties": {
    "iso:country":"US",
    "sg:address":"4950 NW 85th Ter",
    "sg:city":"Lauderhill",
    "sg:phone":"+1 954 578 9727",
    "sg:postcode":"33351",
    "sg:province":"FL",
    "wof:name":"Acts Worldwide Evangelistic",
    "wof:placetype":"venue"
},
  "geometry": {"coordinates":[-80.26487,26.186108],"type":"Point"}
}