{
  "type": "Feature",
  "properties": {
    "iso:country":"US",
    "sg:address":"2015 E Main St",
    "sg:city":"Lakeland",
    "sg:classifiers":[
        {
            "category":"Retail",
            "subcategory":"Self-service Laundry",
            "type":"Services"
        }
    ],
    "sg:phone":"+1 863 667 3428",
    "sg:postcode":"33801",
    "sg:province":"FL",
    "sg:tags":[
        "operated",
        "washer",
        "coin",
        "dryer"
    ],
    "wof:name":"Anns Laundromats",
    "wof:placetype":"venue"
},
  "geometry": {"coordinates":[-81.924081,28.045909],"type":"Point"}
}