{
  "type": "Feature",
  "properties": {
    "iso:country":"US",
    "sg:address":"912 NW 19th St",
    "sg:city":"Fort Lauderdale",
    "sg:classifiers":[
        {
            "category":"Organizations",
            "subcategory":"Religious Organization",
            "type":"Services"
        }
    ],
    "sg:phone":"+1 954 763 1404",
    "sg:postcode":"33311",
    "sg:province":"FL",
    "sg:tags":[
        "church"
    ],
    "wof:name":"Church Of Christ Northside",
    "wof:placetype":"venue"
},
  "geometry": {"coordinates":[-80.158237,26.151377],"type":"Point"}
}