{
  "type": "Feature",
  "properties": {
    "iso:country":"US",
    "sg:address":"1101 Constitution Dr",
    "sg:city":"Port Saint Joe",
    "sg:classifiers":[
        {
            "category":"Professional",
            "subcategory":"Advertising",
            "type":"Services"
        }
    ],
    "sg:phone":"+1 850 229 2748",
    "sg:postcode":"32456",
    "sg:province":"FL",
    "sg:tags":[
        "agency"
    ],
    "wof:name":"Marketing & Media",
    "wof:placetype":"venue"
},
  "geometry": {"coordinates":[-85.30185299999999,29.805153],"type":"Point"}
}