{
  "type": "Feature",
  "properties": {
    "addr:full":"2220 Soutel Dr Jacksonville FL 32208",
    "addr:housenumber":"2220",
    "addr:postcode":"32208",
    "addr:street":"Soutel Dr",
    "iso:country":"US",
    "sg:address":"2220 Soutel Dr",
    "sg:city":"Jacksonville",
    "sg:classifiers":[
        {
            "category":"Retail",
            "subcategory":"Funeral Services",
            "type":"Services"
        }
    ],
    "sg:phone":"+1 904 764 2542",
    "sg:postcode":"32208",
    "sg:province":"FL",
    "sg:tags":[
        "floor",
        "laying",
        "contractor"
    ],
    "wof:name":"Peeples Funeral Home",
    "wof:placetype":"venue"
},
  "geometry": {"coordinates":[-81.69174099999999,30.408005],"type":"Point"}
}