{
  "type": "Feature",
  "properties": {
    "iso:country":"US",
    "sg:address":"2033 Shamrock Ln",
    "sg:city":"Lynn Haven",
    "sg:classifiers":[
        {
            "category":"Building & Trades",
            "subcategory":"Landscaping Services",
            "type":"Services"
        }
    ],
    "sg:phone":"+1 850 271 0402",
    "sg:postcode":"32444",
    "sg:province":"FL",
    "sg:tags":[
        "lawn",
        "maintenance",
        "grounds"
    ],
    "wof:name":"Franks Lawn Svc",
    "wof:placetype":"venue"
},
  "geometry": {"coordinates":[-85.62038,30.236867],"type":"Point"}
}