{
  "type": "Feature",
  "properties": {
    "addr:full":"907 Sonja Pl Apopka FL 32703",
    "addr:housenumber":"907",
    "addr:postcode":"32703",
    "addr:street":"Sonja Pl",
    "iso:country":"US",
    "sg:address":"907 Sonja Pl",
    "sg:city":"Apopka",
    "sg:classifiers":[
        {
            "category":"Professional",
            "subcategory":"Art Services",
            "type":"Services"
        }
    ],
    "sg:phone":"+1 407 774 1992",
    "sg:postcode":"32703",
    "sg:province":"FL",
    "sg:tags":[
        "photographer"
    ],
    "wof:name":"Jerry White Photography Inc",
    "wof:placetype":"venue"
},
  "geometry": {"coordinates":[-81.442621,28.666381],"type":"Point"}
}