{
  "type": "Feature",
  "properties": {
    "iso:country":"US",
    "sg:address":"19820 SW 101st Ave",
    "sg:city":"Miami",
    "sg:classifiers":[
        {
            "category":"Education",
            "subcategory":"Special Training",
            "type":"Public Place"
        }
    ],
    "sg:phone":"+1 305 256 7530",
    "sg:postcode":"33157",
    "sg:province":"FL",
    "wof:name":"Reading Camp",
    "wof:placetype":"venue"
},
  "geometry": {"coordinates":[-80.35530199999999,25.58218],"type":"Point"}
}