{
  "type": "Feature",
  "properties": {
    "iso:country":"US",
    "sg:address":"5032 Mile Stretch Dr",
    "sg:city":"Holiday",
    "sg:classifiers":[
        {
            "category":"Shopping",
            "subcategory":"Clothing, Apparel, & Fashions",
            "type":"Retail Goods"
        }
    ],
    "sg:phone":"+1 727 939 1721",
    "sg:postcode":"34690",
    "sg:province":"FL",
    "sg:tags":[
        "tailor",
        "alterations-clothing"
    ],
    "wof:name":"Brian The Tailor",
    "wof:placetype":"venue"
},
  "geometry": {"coordinates":[-82.730598,28.188017],"type":"Point"}
}