{
  "type": "Feature",
  "properties": {
    "addr:full":"9451 Richmond Cir Boca Raton FL 33434",
    "addr:housenumber":"9451",
    "addr:postcode":"33434",
    "addr:street":"Richmond Cir",
    "iso:country":"US",
    "sg:address":"9451 Richmond Cir",
    "sg:city":"Boca Raton",
    "sg:classifiers":[
        {
            "category":"Building & Trades",
            "subcategory":"Construction",
            "type":"Services"
        }
    ],
    "sg:phone":"+1 561 852 9447",
    "sg:postcode":"33434",
    "sg:province":"FL",
    "sg:tags":[
        "carpentry",
        "contractor"
    ],
    "wof:name":"Customized Carpentry Inc",
    "wof:placetype":"venue"
},
  "geometry": {"coordinates":[-80.19374500000001,26.390698],"type":"Point"}
}