{
  "type": "Feature",
  "properties": {
    "addr:full":"2421 4th St N St Petersburg FL 33704",
    "addr:housenumber":"2421",
    "addr:postcode":"33704",
    "addr:street":"4Th St N",
    "iso:country":"US",
    "sg:address":"2421 4th St N",
    "sg:city":"St Petersburg",
    "sg:classifiers":[
        {
            "category":"Professional",
            "subcategory":"Business Services",
            "type":"Services"
        }
    ],
    "sg:phone":"+1 727 895 7547",
    "sg:postcode":"33704",
    "sg:province":"FL",
    "sg:tags":[
        "packaging"
    ],
    "wof:name":"PKG'S",
    "wof:placetype":"venue"
},
  "geometry": {"coordinates":[-82.638474,27.794662],"type":"Point"}
}