{
  "type": "Feature",
  "properties": {
    "iso:country":"US",
    "sg:address":"4023 Lado Dr",
    "sg:city":"Wesley Chapel",
    "sg:classifiers":[
        {
            "category":"Building & Trades",
            "subcategory":"Cleaning & Sanitation",
            "type":"Services"
        }
    ],
    "sg:phone":"+1 813 469 5418",
    "sg:postcode":"33543",
    "sg:province":"FL",
    "sg:tags":[
        "property",
        "maintenance"
    ],
    "wof:name":"Wesley Chapel Property & Lands",
    "wof:placetype":"venue"
},
  "geometry": {"coordinates":[-82.263903,28.218124],"type":"Point"}
}