{
  "type": "Feature",
  "properties": {
    "addr:full":"13574 Village Park Dr Orlando FL 32837",
    "addr:housenumber":"13574",
    "addr:postcode":"32837",
    "addr:street":"Village Park Dr",
    "iso:country":"US",
    "sg:address":"13574 Village Park Dr",
    "sg:city":"Orlando",
    "sg:classifiers":[
        {
            "category":"Insurance",
            "subcategory":"Insurance Agent",
            "type":"Services"
        },
        {
            "category":"Insurance",
            "subcategory":"Hazard Insurance",
            "type":"Services"
        },
        {
            "category":"Insurance",
            "subcategory":"Title Insurance",
            "type":"Services"
        },
        {
            "category":"Insurance",
            "subcategory":"Life Insurance",
            "type":"Services"
        }
    ],
    "sg:phone":"+1 407 816 0844",
    "sg:postcode":"32837",
    "sg:province":"FL",
    "sg:tags":[
        "business",
        "auto",
        "commercial",
        "homeowner",
        "motorcycle",
        "renter"
    ],
    "wof:name":"Allstate Insurance Company - Cynthia Roman",
    "wof:placetype":"venue"
},
  "geometry": {"coordinates":[-81.42920599999999,28.368819],"type":"Point"}
}