{
  "type": "Feature",
  "properties": {
    "addr:full":"780 Wilson Ave Fort Myers FL 33919",
    "addr:housenumber":"780",
    "addr:postcode":"33919",
    "addr:street":"Wilson Ave",
    "iso:country":"US",
    "sg:address":"780 Wilson Ave",
    "sg:city":"Fort Myers",
    "sg:classifiers":[
        {
            "category":"Farming",
            "subcategory":"Fish & Marine Products",
            "type":"Manufacturing & Wholesale Goods"
        }
    ],
    "sg:phone":"+1 239 489 2136",
    "sg:postcode":"33919",
    "sg:province":"FL",
    "sg:tags":[
        "shellfish",
        "fishing"
    ],
    "wof:name":"Ricks Seafood Inc",
    "wof:placetype":"venue"
},
  "geometry": {"coordinates":[-81.905434,26.564361],"type":"Point"}
}