{
  "type": "Feature",
  "properties": {
    "iso:country":"US",
    "sg:address":"1030 Douglas Ave",
    "sg:city":"Altamonte Springs",
    "sg:classifiers":[
        {
            "category":"Real Estate",
            "subcategory":"Real Estate Operator",
            "type":"Services"
        }
    ],
    "sg:phone":"+1 321 282 6170",
    "sg:postcode":"32714",
    "sg:province":"FL",
    "sg:tags":[
        "apartment"
    ],
    "sg:website":"www.douglastonvillas.com/",
    "wof:name":"Douglaston Villas & Townhomes",
    "wof:placetype":"venue"
},
  "geometry": {"coordinates":[-81.390216,28.685938],"type":"Point"}
}