{
  "type": "Feature",
  "properties": {
    "addr:full":"4061 E 8th Ave Hialeah FL 33013",
    "addr:housenumber":"4061",
    "addr:postcode":"33013",
    "addr:street":"E 8Th Ave",
    "iso:country":"US",
    "sg:address":"4061 E 8th Ave",
    "sg:city":"Hialeah",
    "sg:classifiers":[
        {
            "category":"Shopping",
            "type":"Retail Goods"
        }
    ],
    "sg:phone":"+1 305 693 2794",
    "sg:postcode":"33013",
    "sg:province":"FL",
    "sg:tags":[
        "religious"
    ],
    "wof:name":"Rosy & Gorg Botanica Pet Shop",
    "wof:placetype":"venue"
},
  "geometry": {"coordinates":[-80.26656699999999,25.859414],"type":"Point"}
}