{
  "type": "Feature",
  "properties": {
    "iso:country":"US",
    "sg:address":"7760 W 20th Ave Ste 11",
    "sg:city":"Hialeah",
    "sg:classifiers":[
        {
            "category":"Education",
            "subcategory":"Music School",
            "type":"Public Place"
        }
    ],
    "sg:phone":"+1 305 821 0077",
    "sg:postcode":"33016",
    "sg:province":"FL",
    "sg:tags":[
        "instrument",
        "teacher",
        "musical"
    ],
    "wof:name":"Miami Vintage Guitars",
    "wof:placetype":"venue"
},
  "geometry": {"coordinates":[-80.325214,25.894133],"type":"Point"}
}