{
  "type": "Feature",
  "properties": {
    "addr:full":"3107 S Orlando Dr Sanford FL 32773",
    "addr:housenumber":"3107",
    "addr:postcode":"32773",
    "addr:street":"S Orlando Dr",
    "iso:country":"US",
    "sg:address":"3107 S Orlando Dr",
    "sg:city":"Sanford",
    "sg:classifiers":[
        {
            "category":"Retail",
            "subcategory":"Auto Rental",
            "type":"Services"
        }
    ],
    "sg:phone":"+1 407 302 7520",
    "sg:postcode":"32773",
    "sg:province":"FL",
    "sg:tags":[
        "renting",
        "automobile"
    ],
    "wof:name":"E Z Rent A Car Inc",
    "wof:placetype":"venue"
},
  "geometry": {"coordinates":[-81.280073,28.770377],"type":"Point"}
}