{
  "type": "Feature",
  "properties": {
    "iso:country":"US",
    "sg:address":"900 SE Ocean Blvd Ste 232",
    "sg:city":"Stuart",
    "sg:classifiers":[
        {
            "category":"Health Services",
            "subcategory":"Doctor",
            "type":"Services"
        }
    ],
    "sg:phone":"+1 772 288 1811",
    "sg:postcode":"34994",
    "sg:province":"FL",
    "sg:tags":[
        "physician",
        "family",
        "practice",
        "surgeons",
        "medicine"
    ],
    "wof:name":"R I C Corp",
    "wof:placetype":"venue"
},
  "geometry": {"coordinates":[-80.238533,27.1975],"type":"Point"}
}