{
  "type": "Feature",
  "properties": {
    "addr:full":"4516 SE 11th Pl Cape Coral FL 33904",
    "addr:housenumber":"4516",
    "addr:postcode":"33904",
    "addr:street":"Se 11Th Pl",
    "iso:country":"US",
    "sg:address":"4516 SE 11th Pl",
    "sg:city":"Cape Coral",
    "sg:classifiers":[
        {
            "category":"Building & Trades",
            "subcategory":"Plumbing",
            "type":"Services"
        }
    ],
    "sg:phone":"+1 239 542 8389",
    "sg:postcode":"33904",
    "sg:province":"FL",
    "sg:tags":[
        "conditioning",
        "air",
        "system",
        "contractor"
    ],
    "wof:name":"Bruce Mee Air Conditioning",
    "wof:placetype":"venue"
},
  "geometry": {"coordinates":[-81.951184,26.567315],"type":"Point"}
}