{
  "type": "Feature",
  "properties": {
    "iso:country":"US",
    "sg:address":"20500 SW 112th Ave",
    "sg:city":"Miami",
    "sg:classifiers":[
        {
            "category":"Shopping",
            "subcategory":"Department Store",
            "type":"Retail Goods"
        }
    ],
    "sg:phone":"+1 305 235 0839",
    "sg:postcode":"33189",
    "sg:province":"FL",
    "sg:website":"www.target.com",
    "wof:name":"Target",
    "wof:placetype":"venue"
},
  "geometry": {"coordinates":[-80.372427,25.575687],"type":"Point"}
}