{
  "type": "Feature",
  "properties": {
    "iso:country":"US",
    "sg:address":"10705 SW 104th St",
    "sg:city":"Miami",
    "sg:classifiers":[
        {
            "category":"Professional",
            "subcategory":"Detective & Security Services",
            "type":"Services"
        },
        {
            "category":"Manufacturing",
            "subcategory":"Electronics",
            "type":"Manufacturing & Wholesale Goods"
        },
        {
            "category":"Shopping",
            "subcategory":"Computers & Home Electronics",
            "type":"Retail Goods"
        }
    ],
    "sg:phone":"+1 305 598 5357",
    "sg:postcode":"33176",
    "sg:province":"FL",
    "sg:tags":[
        "control",
        "monitoring",
        "equipment-wholesale",
        "system",
        "surveillance",
        "equipment",
        "manufacturer"
    ],
    "wof:name":"Nightline",
    "wof:placetype":"venue"
},
  "geometry": {"coordinates":[-80.367817,25.672468],"type":"Point"}
}