{
  "type": "Feature",
  "properties": {
    "iso:country":"US",
    "sg:address":"2196 Howland Blvd",
    "sg:city":"Deltona",
    "sg:classifiers":[
        {
            "category":"Food & Beverages",
            "subcategory":"Groceries & Convenience Stores",
            "type":"Retail Goods"
        }
    ],
    "sg:phone":"+1 386 789 6999",
    "sg:postcode":"32738",
    "sg:province":"FL",
    "wof:name":"Publix Pix",
    "wof:placetype":"venue"
},
  "geometry": {"coordinates":[-81.189796,28.924801],"type":"Point"}
}