{
  "type": "Feature",
  "properties": {
    "iso:country":"US",
    "sg:address":"4707 NW 72nd Ave",
    "sg:city":"Miami",
    "sg:classifiers":[
        {
            "category":"Transit Center",
            "subcategory":"Freight",
            "type":"Transportation"
        },
        {
            "category":"Professional",
            "subcategory":"Business Services",
            "type":"Services"
        }
    ],
    "sg:phone":"+1 305 471 9007",
    "sg:postcode":"33166",
    "sg:province":"FL",
    "sg:tags":[
        "mail",
        "container",
        "broker",
        "shipping"
    ],
    "sg:website":"http://www.enterprises.com",
    "wof:name":"Santo Domingo Shipping Inc",
    "wof:placetype":"venue"
},
  "geometry": {"coordinates":[-80.313371,25.816225],"type":"Point"}
}