{
  "type": "Feature",
  "properties": {
    "addr:full":"800 E Palmetto Park Rd Boca Raton FL 33432",
    "addr:housenumber":"800",
    "addr:postcode":"33432",
    "addr:street":"E Palmetto Park Rd",
    "iso:country":"US",
    "sg:address":"800 E Palmetto Park Rd",
    "sg:city":"Boca Raton",
    "sg:classifiers":[
        {
            "category":"Real Estate",
            "subcategory":"Real Estate Agent",
            "type":"Services"
        }
    ],
    "sg:phone":"+1 561 394 7700",
    "sg:postcode":"33432",
    "sg:province":"FL",
    "sg:tags":[
        "manager"
    ],
    "wof:name":"Premier Estate Properties Inc",
    "wof:placetype":"venue"
},
  "geometry": {"coordinates":[-80.071573,26.350651],"type":"Point"}
}