{
  "type": "Feature",
  "properties": {
    "iso:country":"US",
    "sg:address":"506 W Canal St",
    "sg:city":"Mulberry",
    "sg:classifiers":[
        {
            "category":"Autos & Motor Vehicles",
            "subcategory":"Fuel & Gas Station",
            "type":"Retail Goods"
        }
    ],
    "sg:phone":"+1 863 425 9781",
    "sg:postcode":"33860",
    "sg:province":"FL",
    "sg:tags":[
        "oil"
    ],
    "wof:name":"Marathon",
    "wof:placetype":"venue"
},
  "geometry": {"coordinates":[-81.97736,27.894914],"type":"Point"}
}