{
  "type": "Feature",
  "properties": {
    "addr:full":"5552 Greenland Rd Jacksonville FL 32258",
    "addr:housenumber":"5552",
    "addr:postcode":"32258",
    "addr:street":"Greenland Rd",
    "iso:country":"US",
    "sg:address":"5552 Greenland Rd",
    "sg:city":"Jacksonville",
    "sg:classifiers":[
        {
            "category":"Insurance",
            "subcategory":"Insurance Agent",
            "type":"Services"
        }
    ],
    "sg:phone":"+1 904 880 6784",
    "sg:postcode":"32258",
    "sg:province":"FL",
    "wof:name":"R Stephen Lee Insurance Inc",
    "wof:placetype":"venue"
},
  "geometry": {"coordinates":[-81.559731,30.161673],"type":"Point"}
}