{
  "type": "Feature",
  "properties": {
    "iso:country":"US",
    "sg:address":"6149 Westfall Rd",
    "sg:city":"Lake Worth",
    "sg:classifiers":[
        {
            "category":"Shopping",
            "type":"Retail Goods"
        }
    ],
    "sg:phone":"+1 561 433 9277",
    "sg:postcode":"33463",
    "sg:province":"FL",
    "sg:tags":[
        "merchandise"
    ],
    "wof:name":"Engrave-A-Frame",
    "wof:placetype":"venue"
},
  "geometry": {"coordinates":[-80.140103,26.598652],"type":"Point"}
}