{
  "type": "Feature",
  "properties": {
    "addr:full":"2510 Tamiami Trl Nokomis FL 34275",
    "addr:housenumber":"2510",
    "addr:postcode":"34275",
    "addr:street":"Tamiami Trl",
    "iso:country":"US",
    "sg:address":"2510 Tamiami Trl",
    "sg:city":"Nokomis",
    "sg:classifiers":[
        {
            "category":"Health Services",
            "subcategory":"Health Practitioner",
            "type":"Services"
        }
    ],
    "sg:phone":"+1 941 966 1177",
    "sg:postcode":"34275",
    "sg:province":"FL",
    "wof:name":"Lynn Burnstein & Associates",
    "wof:placetype":"venue"
},
  "geometry": {"coordinates":[-82.472252,27.160274],"type":"Point"}
}