{
  "type": "Feature",
  "properties": {
    "iso:country":"US",
    "sg:address":"406 Canal St",
    "sg:city":"New Smyrna Beach",
    "sg:classifiers":[
        {
            "category":"Shopping",
            "subcategory":"Stationery & Office Supplies",
            "type":"Retail Goods"
        }
    ],
    "sg:phone":"+1 386 428 2034",
    "sg:postcode":"32168",
    "sg:province":"FL",
    "wof:name":"Cibu Office Supplies",
    "wof:placetype":"venue"
},
  "geometry": {"coordinates":[-80.92536699999999,29.024053],"type":"Point"}
}