{
  "type": "Feature",
  "properties": {
    "iso:country":"US",
    "sg:address":"929 NE 19th Ave",
    "sg:city":"Fort Lauderdale",
    "sg:classifiers":[
        {
            "category":"Retail",
            "subcategory":"Animal Services",
            "type":"Services"
        }
    ],
    "sg:phone":"+1 954 524 2275",
    "sg:postcode":"33304",
    "sg:province":"FL",
    "sg:tags":[
        "pet",
        "grooming",
        "washing"
    ],
    "wof:name":"Tracy's Pet Grooming Ctr",
    "wof:placetype":"venue"
},
  "geometry": {"coordinates":[-80.121127,26.137027],"type":"Point"}
}