{
  "type": "Feature",
  "properties": {
    "iso:country":"US",
    "sg:address":"1435 W 49th Pl Ste 207",
    "sg:city":"Hialeah",
    "sg:classifiers":[
        {
            "category":"Health Services",
            "subcategory":"Doctor",
            "type":"Services"
        }
    ],
    "sg:phone":"+1 305 556 6137",
    "sg:postcode":"33012",
    "sg:province":"FL",
    "sg:tags":[
        "physician",
        "family",
        "practice",
        "surgeons",
        "internal",
        "medicine",
        "surgeon"
    ],
    "wof:name":"Marquez Farid MD",
    "wof:placetype":"venue"
},
  "geometry": {"coordinates":[-80.311302,25.8675],"type":"Point"}
}