{
  "type": "Feature",
  "properties": {
    "addr:full":"1651 Edgewood Ave W Jacksonville FL 32208",
    "addr:housenumber":"1651",
    "addr:postcode":"32208",
    "addr:street":"Edgewood Ave W",
    "iso:country":"US",
    "sg:address":"1651 Edgewood Ave W",
    "sg:city":"Jacksonville",
    "sg:classifiers":[
        {
            "category":"Retail",
            "subcategory":"Auto Rental",
            "type":"Services"
        }
    ],
    "sg:phone":"+1 904 764 2516",
    "sg:postcode":"32208",
    "sg:province":"FL",
    "sg:tags":[
        "tool",
        "truck",
        "trailer"
    ],
    "wof:name":"U-Haul",
    "wof:placetype":"venue"
},
  "geometry": {"coordinates":[-81.68526,30.387427],"type":"Point"}
}