{
  "type": "Feature",
  "properties": {
    "iso:country":"US",
    "sg:address":"7598 NW 6th Ave",
    "sg:city":"Boca Raton",
    "sg:classifiers":[
        {
            "category":"Wholesale",
            "subcategory":"Groceries",
            "type":"Manufacturing & Wholesale Goods"
        }
    ],
    "sg:phone":"+1 561 994 8500",
    "sg:postcode":"33487",
    "sg:province":"FL",
    "sg:tags":[
        "grocer"
    ],
    "sg:website":"www.usfoodservice.com",
    "wof:name":"US Foodservice",
    "wof:placetype":"venue"
},
  "geometry": {"coordinates":[-80.093958,26.414662],"type":"Point"}
}