{
  "type": "Feature",
  "properties": {
    "iso:country":"US",
    "sg:address":"301 NW 79th St",
    "sg:city":"Miami",
    "sg:classifiers":[
        {
            "category":"Autos & Motor Vehicles",
            "subcategory":"Automobile Sales",
            "type":"Retail Goods"
        }
    ],
    "sg:phone":"+1 305 757 7776",
    "sg:postcode":"33150",
    "sg:province":"FL",
    "sg:tags":[
        "used"
    ],
    "wof:name":"Two In One Auto Sales Inc",
    "wof:placetype":"venue"
},
  "geometry": {"coordinates":[-80.202568,25.847343],"type":"Point"}
}