{
  "type": "Feature",
  "properties": {
    "addr:full":"4639 Cortez Rd W Bradenton FL 34210",
    "addr:housenumber":"4639",
    "addr:postcode":"34210",
    "addr:street":"Cortez Rd W",
    "iso:country":"US",
    "sg:address":"4639 Cortez Rd W",
    "sg:city":"Bradenton",
    "sg:classifiers":[
        {
            "category":"Personal",
            "subcategory":"Beauty Salon",
            "type":"Services"
        }
    ],
    "sg:phone":"+1 941 794 3346",
    "sg:postcode":"34210",
    "sg:province":"FL",
    "sg:tags":[
        "manicuring"
    ],
    "wof:name":"Bobbie Lachiusa The Nail Co",
    "wof:placetype":"venue"
},
  "geometry": {"coordinates":[-82.606922,27.462329],"type":"Point"}
}