{
  "type": "Feature",
  "properties": {
    "addr:full":"8255 Sunset Strip Sunrise FL 33322",
    "addr:housenumber":"8255",
    "addr:postcode":"33322",
    "addr:street":"Sunset Strip",
    "iso:country":"US",
    "sg:address":"8255 Sunset Strip",
    "sg:city":"Sunrise",
    "sg:classifiers":[
        {
            "category":"Personal",
            "subcategory":"Beauty Salon",
            "type":"Services"
        }
    ],
    "sg:phone":"+1 954 749 7546",
    "sg:postcode":"33322",
    "sg:province":"FL",
    "wof:name":"Skin Deep Skin Care & Cosmetics",
    "wof:placetype":"venue"
},
  "geometry": {"coordinates":[-80.255185,26.15296],"type":"Point"}
}