{
  "type": "Feature",
  "properties": {
    "iso:country":"US",
    "sg:address":"2071 Dundee Dr",
    "sg:city":"Winter Park",
    "sg:classifiers":[
        {
            "category":"Health Services",
            "subcategory":"Doctor",
            "type":"Services"
        }
    ],
    "sg:phone":"+1 407 628 4188",
    "sg:postcode":"32792",
    "sg:province":"FL",
    "sg:tags":[
        "practice",
        "family"
    ],
    "wof:name":"Hudson John B Jr MD PA",
    "wof:placetype":"venue"
},
  "geometry": {"coordinates":[-81.32550000000001,28.5944],"type":"Point"}
}