{
  "type": "Feature",
  "properties": {
    "iso:country":"US",
    "sg:address":"2231 Aurora Rd",
    "sg:city":"Melbourne",
    "sg:classifiers":[
        {
            "category":"Autos & Motor Vehicles",
            "subcategory":"Automobile Sales",
            "type":"Retail Goods"
        }
    ],
    "sg:phone":"+1 321 242 6500",
    "sg:postcode":"32935",
    "sg:province":"FL",
    "sg:tags":[
        "car",
        "dealer"
    ],
    "wof:name":"Motor City",
    "wof:placetype":"venue"
},
  "geometry": {"coordinates":[-80.656144,28.135823],"type":"Point"}
}