{
  "type": "Feature",
  "properties": {
    "iso:country":"US",
    "sg:address":"9755 NW 52nd St Apt 221",
    "sg:city":"Doral",
    "sg:classifiers":[
        {
            "category":"Shopping",
            "type":"Retail Goods"
        },
        {
            "category":"Manufacturing",
            "subcategory":"Paper Products",
            "type":"Manufacturing & Wholesale Goods"
        }
    ],
    "sg:phone":"+1 305 531 5276",
    "sg:postcode":"33178",
    "sg:province":"FL",
    "sg:tags":[
        "packaging",
        "materials-wholesale",
        "material",
        "manufacturer"
    ],
    "wof:name":"Packing Solutions",
    "wof:placetype":"venue"
},
  "geometry": {"coordinates":[-80.35454,25.82087],"type":"Point"}
}