{
  "type": "Feature",
  "properties": {
    "addr:full":"2431 Galiano St Coral Gables FL 33134",
    "addr:housenumber":"2431",
    "addr:postcode":"33134",
    "addr:street":"Galiano St",
    "iso:country":"US",
    "sg:address":"2431 Galiano St",
    "sg:city":"Coral Gables",
    "sg:classifiers":[
        {
            "category":"Personal",
            "subcategory":"Beauty Salon",
            "type":"Services"
        }
    ],
    "sg:phone":"+1 305 444 3464",
    "sg:postcode":"33134",
    "sg:province":"FL",
    "sg:tags":[
        "nail"
    ],
    "wof:name":"Hairy Ape Hair Designing the",
    "wof:placetype":"venue"
},
  "geometry": {"coordinates":[-80.2565,25.7488],"type":"Point"}
}