{
  "type": "Feature",
  "properties": {
    "addr:full":"211 50th Street Ct NW Bradenton FL 34209",
    "addr:housenumber":"211",
    "addr:postcode":"34209",
    "addr:street":"50Th Street",
    "iso:country":"US",
    "sg:address":"211 50th Street Ct NW",
    "sg:city":"Bradenton",
    "sg:classifiers":[
        {
            "category":"Wholesale",
            "subcategory":"Computers",
            "type":"Manufacturing & Wholesale Goods"
        }
    ],
    "sg:phone":"+1 941 749 5221",
    "sg:postcode":"34209",
    "sg:province":"FL",
    "wof:name":"Action Computer Technologies",
    "wof:placetype":"venue"
},
  "geometry": {"coordinates":[-82.611574,27.500625],"type":"Point"}
}