{
  "type": "Feature",
  "properties": {
    "iso:country":"US",
    "sg:address":"12721 Metro Pkwy",
    "sg:city":"Fort Myers",
    "sg:classifiers":[
        {
            "category":"Manufacturing",
            "subcategory":"Printing",
            "type":"Manufacturing & Wholesale Goods"
        }
    ],
    "sg:phone":"+1 239 561 2040",
    "sg:postcode":"33966",
    "sg:province":"FL",
    "sg:tags":[
        "publishes",
        "publisher",
        "classified",
        "advertising",
        "periodical"
    ],
    "sg:website":"www.traderonline.com",
    "wof:name":"Trader Publishing Company",
    "wof:placetype":"venue"
},
  "geometry": {"coordinates":[-81.852647,26.549279],"type":"Point"}
}