{
  "type": "Feature",
  "properties": {
    "addr:full":"2736 SE Gay St Stuart FL 34997",
    "addr:housenumber":"2736",
    "addr:postcode":"34997",
    "addr:street":"Se Gay St",
    "iso:country":"US",
    "sg:address":"2736 SE Gay St",
    "sg:city":"Stuart",
    "sg:classifiers":[
        {
            "category":"Retail",
            "subcategory":"Animal Services",
            "type":"Services"
        }
    ],
    "sg:phone":"+1 772 781 2001",
    "sg:postcode":"34997",
    "sg:province":"FL",
    "sg:tags":[
        "training",
        "dog"
    ],
    "wof:name":"Man's Best Friend Inc",
    "wof:placetype":"venue"
},
  "geometry": {"coordinates":[-80.216402,27.151488],"type":"Point"}
}