{
  "type": "Feature",
  "properties": {
    "iso:country":"US",
    "sg:address":"13899 Biscayne Blvd Ofc 110",
    "sg:city":"North Miami Beach",
    "sg:classifiers":[
        {
            "category":"Professional",
            "subcategory":"Lawyer & Legal Services",
            "type":"Services"
        }
    ],
    "sg:phone":"+1 305 702 6373",
    "sg:postcode":"33181",
    "sg:province":"FL",
    "wof:name":"Behar Maria Atty",
    "wof:placetype":"venue"
},
  "geometry": {"coordinates":[-80.159015,25.904048],"type":"Point"}
}