{
  "type": "Feature",
  "properties": {
    "iso:country":"US",
    "sg:address":"1426 Palmetto Ave",
    "sg:city":"Fort Myers",
    "sg:classifiers":[
        {
            "category":"Building & Trades",
            "subcategory":"Construction",
            "type":"Services"
        }
    ],
    "sg:phone":"+1 239 334 9210",
    "sg:postcode":"33916",
    "sg:province":"FL",
    "sg:tags":[
        "plastering",
        "contractor"
    ],
    "wof:name":"Robert Blanks Plastering",
    "wof:placetype":"venue"
},
  "geometry": {"coordinates":[-81.840591,26.649638],"type":"Point"}
}