{
  "type": "Feature",
  "properties": {
    "iso:country":"US",
    "sg:address":"6501 Seaboard Ave",
    "sg:city":"Jacksonville",
    "sg:classifiers":[
        {
            "category":"Organizations",
            "subcategory":"Membership Organization",
            "type":"Services"
        }
    ],
    "sg:phone":"+1 904 779 7536",
    "sg:postcode":"32244",
    "sg:province":"FL",
    "wof:name":"Florida Police Mtn Bike Assn",
    "wof:placetype":"venue"
},
  "geometry": {"coordinates":[-81.730647,30.233152],"type":"Point"}
}