{
  "type": "Feature",
  "properties": {
    "iso:country":"US",
    "sg:address":"503 E 63rd St",
    "sg:city":"Jacksonville",
    "sg:classifiers":[
        {
            "category":"Organizations",
            "subcategory":"Religious Organization",
            "type":"Services"
        }
    ],
    "sg:phone":"+1 904 768 0140",
    "sg:postcode":"32208",
    "sg:province":"FL",
    "sg:tags":[
        "church"
    ],
    "wof:name":"Faith Hope & Charity Church",
    "wof:placetype":"venue"
},
  "geometry": {"coordinates":[-81.643985,30.384882],"type":"Point"}
}