{
  "type": "Feature",
  "properties": {
    "iso:country":"US",
    "sg:address":"2618 Park St",
    "sg:city":"Lake Worth",
    "sg:classifiers":[
        {
            "category":"Autos & Motor Vehicles",
            "subcategory":"Automobile Sales",
            "type":"Retail Goods"
        }
    ],
    "sg:phone":"+1 561 547 7931",
    "sg:postcode":"33460",
    "sg:province":"FL",
    "sg:tags":[
        "equipment",
        "aircraft",
        "parts",
        "supply"
    ],
    "wof:name":"D & E Aircraft",
    "wof:placetype":"venue"
},
  "geometry": {"coordinates":[-80.059282,26.643837],"type":"Point"}
}