{
  "type": "Feature",
  "properties": {
    "iso:country":"US",
    "sg:address":"2495 N Park Pt",
    "sg:city":"Hernando",
    "sg:classifiers":[
        {
            "category":"Home & Garden",
            "subcategory":"Household Appliances",
            "type":"Retail Goods"
        },
        {
            "category":"Retail",
            "subcategory":"Repair Shop",
            "type":"Services"
        }
    ],
    "sg:phone":"+1 352 860 2322",
    "sg:postcode":"34442",
    "sg:province":"FL",
    "wof:name":"Dependable Appliance Repair",
    "wof:placetype":"venue"
},
  "geometry": {"coordinates":[-82.366618,28.899394],"type":"Point"}
}