{
  "type": "Feature",
  "properties": {
    "addr:full":"707 SE 7th Ave Pompano Beach FL 33060",
    "addr:housenumber":"707",
    "addr:postcode":"33060",
    "addr:street":"Se 7Th Ave",
    "iso:country":"US",
    "sg:address":"707 SE 7th Ave",
    "sg:city":"Pompano Beach",
    "sg:classifiers":[
        {
            "category":"Building & Trades",
            "subcategory":"Electrical",
            "type":"Services"
        }
    ],
    "sg:phone":"+1 954 943 1398",
    "sg:postcode":"33060",
    "sg:province":"FL",
    "sg:tags":[
        "electrical",
        "contractor"
    ],
    "wof:name":"Mrd Electric",
    "wof:placetype":"venue"
},
  "geometry": {"coordinates":[-80.11196099999999,26.217188],"type":"Point"}
}