{
  "type": "Feature",
  "properties": {
    "iso:country":"US",
    "sg:address":"6630 W 5th Pl",
    "sg:city":"Hialeah",
    "sg:classifiers":[
        {
            "category":"Building & Trades",
            "subcategory":"Electrical",
            "type":"Services"
        }
    ],
    "sg:phone":"+1 305 827 4228",
    "sg:postcode":"33012",
    "sg:province":"FL",
    "sg:tags":[
        "electric",
        "industrial",
        "contractors-commercial",
        "contractor"
    ],
    "wof:name":"Sunset Electric Inc",
    "wof:placetype":"venue"
},
  "geometry": {"coordinates":[-80.294895,25.882997],"type":"Point"}
}