{
  "type": "Feature",
  "properties": {
    "addr:full":"8799 Tamiami Trl N Naples FL 34108",
    "addr:housenumber":"8799",
    "addr:postcode":"34108",
    "addr:street":"Tamiami Trl N",
    "iso:country":"US",
    "sg:address":"8799 Tamiami Trl N",
    "sg:city":"Naples",
    "sg:classifiers":[
        {
            "category":"Shopping",
            "subcategory":"Shoes",
            "type":"Retail Goods"
        }
    ],
    "sg:phone":"+1 239 596 8788",
    "sg:postcode":"34108",
    "sg:province":"FL",
    "wof:name":"New Balance Naples",
    "wof:placetype":"venue"
},
  "geometry": {"coordinates":[-81.801269,26.249618],"type":"Point"}
}