{
  "type": "Feature",
  "properties": {
    "addr:full":"390 Melody Ln W Casselberry FL 32707",
    "addr:housenumber":"390",
    "addr:postcode":"32707",
    "addr:street":"Melody Ln W",
    "iso:country":"US",
    "sg:address":"390 Melody Ln W",
    "sg:city":"Casselberry",
    "sg:classifiers":[
        {
            "category":"Autos & Motor Vehicles",
            "subcategory":"Auto Supplies",
            "type":"Retail Goods"
        }
    ],
    "sg:phone":"+1 407 831 2111",
    "sg:postcode":"32707",
    "sg:province":"FL",
    "sg:tags":[
        "automotive",
        "repair"
    ],
    "wof:name":"Elliott Automotive Inc",
    "wof:placetype":"venue"
},
  "geometry": {"coordinates":[-81.342181,28.672258],"type":"Point"}
}