{
  "type": "Feature",
  "properties": {
    "addr:full":"2207 Culbreath Rd Brooksville FL 34602",
    "addr:housenumber":"2207",
    "addr:postcode":"34602",
    "addr:street":"Culbreath Rd",
    "iso:country":"US",
    "sg:address":"2207 Culbreath Rd",
    "sg:city":"Brooksville",
    "sg:classifiers":[
        {
            "category":"Building & Trades",
            "subcategory":"Construction",
            "type":"Services"
        }
    ],
    "sg:phone":"+1 352 279 1569",
    "sg:postcode":"34602",
    "sg:province":"FL",
    "sg:tags":[
        "contractor"
    ],
    "wof:name":"Cole Chandler Fence",
    "wof:placetype":"venue"
},
  "geometry": {"coordinates":[-82.37073100000001,28.469937],"type":"Point"}
}