{
  "type": "Feature",
  "properties": {
    "addr:full":"1025 S Semoran Blvd Winter Park FL 32792",
    "addr:housenumber":"1025",
    "addr:postcode":"32792",
    "addr:street":"S Semoran Blvd",
    "iso:country":"US",
    "sg:address":"1025 S Semoran Blvd",
    "sg:city":"Winter Park",
    "sg:classifiers":[
        {
            "category":"Banks & Credit Unions",
            "subcategory":"Bank",
            "type":"Services"
        }
    ],
    "sg:phone":"+1 407 671 5102",
    "sg:postcode":"32792",
    "sg:province":"FL",
    "wof:name":"Bank Of The West",
    "wof:placetype":"venue"
},
  "geometry": {"coordinates":[-81.30767,28.581095],"type":"Point"}
}