{
  "type": "Feature",
  "properties": {
    "addr:full":"2440 N State Rd 7 Hollywood FL 33021",
    "addr:housenumber":"2440;7",
    "addr:postcode":"33021",
    "addr:street":"N State Rd",
    "iso:country":"US",
    "sg:address":"2440 N State Rd 7",
    "sg:city":"Hollywood",
    "sg:classifiers":[
        {
            "category":"Professional",
            "type":"Services"
        }
    ],
    "sg:phone":"+1 954 967 1188",
    "sg:postcode":"33021",
    "sg:province":"FL",
    "sg:tags":[
        "establishment"
    ],
    "wof:name":"Radha Gobindo Inc",
    "wof:placetype":"venue"
},
  "geometry": {"coordinates":[-80.208437,26.030883],"type":"Point"}
}