{
  "type": "Feature",
  "properties": {
    "addr:full":"1721 Tarpon Dr Tallahassee FL 32308",
    "addr:housenumber":"1721",
    "addr:postcode":"32308",
    "addr:street":"Tarpon Dr",
    "iso:country":"US",
    "sg:address":"1721 Tarpon Dr",
    "sg:city":"Tallahassee",
    "sg:classifiers":[
        {
            "category":"Health Services",
            "subcategory":"Doctor",
            "type":"Services"
        }
    ],
    "sg:phone":"+1 850 386 6508",
    "sg:postcode":"32308",
    "sg:province":"FL",
    "sg:tags":[
        "medical"
    ],
    "wof:name":"Julian E Hurt MD PA",
    "wof:placetype":"venue"
},
  "geometry": {"coordinates":[-84.25099899999999,30.471012],"type":"Point"}
}