{
  "type": "Feature",
  "properties": {
    "iso:country":"US",
    "sg:address":"13263 Lawrence St",
    "sg:city":"Spring Hill",
    "sg:classifiers":[
        {
            "category":"Real Estate",
            "subcategory":"Real Estate Agent",
            "type":"Services"
        }
    ],
    "sg:phone":"+1 352 688 2086",
    "sg:postcode":"34609",
    "sg:province":"FL",
    "wof:name":"C K L Inc",
    "wof:placetype":"venue"
},
  "geometry": {"coordinates":[-82.507964,28.515857],"type":"Point"}
}