{
  "type": "Feature",
  "properties": {
    "iso:country":"US",
    "sg:address":"4659 Bluff Ave",
    "sg:city":"Jacksonville",
    "sg:classifiers":[
        {
            "category":"Professional",
            "subcategory":"Management & Consulting",
            "type":"Services"
        }
    ],
    "sg:phone":"+1 904 646 0462",
    "sg:postcode":"32225",
    "sg:province":"FL",
    "sg:tags":[
        "consultant",
        "business"
    ],
    "wof:name":"BDBH Sales & Consulting Inc",
    "wof:placetype":"venue"
},
  "geometry": {"coordinates":[-81.50514099999999,30.380917],"type":"Point"}
}