{
  "type": "Feature",
  "properties": {
    "iso:country":"US",
    "sg:address":"2811 Tamiami Trl",
    "sg:city":"Port Charlotte",
    "sg:classifiers":[
        {
            "category":"Shopping",
            "subcategory":"Jewelry",
            "type":"Retail Goods"
        }
    ],
    "sg:phone":"+1 941 743 8184",
    "sg:postcode":"33952",
    "sg:province":"FL",
    "sg:tags":[
        "jeweler"
    ],
    "wof:name":"Goldsmith Jewelers",
    "wof:placetype":"venue"
},
  "geometry": {"coordinates":[-82.109409,26.989427],"type":"Point"}
}