{
  "type": "Feature",
  "properties": {
    "addr:full":"1669 Watson Blvd Big Pine Key FL 33043",
    "addr:housenumber":"1669",
    "addr:postcode":"33043",
    "addr:street":"Watson Blvd",
    "iso:country":"US",
    "sg:address":"1669 Watson Blvd",
    "sg:city":"Big Pine Key",
    "sg:classifiers":[
        {
            "category":"Building & Trades",
            "subcategory":"Electrical",
            "type":"Services"
        }
    ],
    "sg:phone":"+1 305 872 3212",
    "sg:postcode":"33043",
    "sg:province":"FL",
    "sg:tags":[
        "electrical",
        "contractor"
    ],
    "wof:name":"K Lectric Inc",
    "wof:placetype":"venue"
},
  "geometry": {"coordinates":[-81.356234,24.696901],"type":"Point"}
}