{
  "type": "Feature",
  "properties": {
    "addr:full":"3774 SW Whispering Sound Dr Palm City FL 34990",
    "addr:housenumber":"3774",
    "addr:postcode":"34990",
    "addr:street":"Sw Whispering Sound Dr",
    "iso:country":"US",
    "sg:address":"3774 SW Whispering Sound Dr",
    "sg:city":"Palm City",
    "sg:classifiers":[
        {
            "category":"Professional",
            "subcategory":"Engineering",
            "type":"Services"
        }
    ],
    "sg:phone":"+1 772 223 1337",
    "sg:postcode":"34990",
    "sg:province":"FL",
    "wof:name":"Frederic L Blum Engineering",
    "wof:placetype":"venue"
},
  "geometry": {"coordinates":[-80.27449900000001,27.158326],"type":"Point"}
}