{
  "type": "Feature",
  "properties": {
    "addr:full":"5405 Twin Creeks Dr Valrico FL 33596",
    "addr:housenumber":"5405",
    "addr:postcode":"33596",
    "addr:street":"Twin Creeks Dr",
    "iso:country":"US",
    "sg:address":"5405 Twin Creeks Dr",
    "sg:city":"Valrico",
    "sg:classifiers":[
        {
            "category":"Building & Trades",
            "subcategory":"Equipment Rental",
            "type":"Services"
        }
    ],
    "sg:phone":"+1 813 988 8829",
    "sg:postcode":"33596",
    "sg:province":"FL",
    "sg:tags":[
        "heavy",
        "construction"
    ],
    "wof:name":"Fusion Equipment Corporation",
    "wof:placetype":"venue"
},
  "geometry": {"coordinates":[-82.207893,27.8965],"type":"Point"}
}