{
  "type": "Feature",
  "properties": {
    "addr:full":"1011 Maryland Ave Saint Cloud FL 34769",
    "addr:housenumber":"1011",
    "addr:postcode":"34769",
    "addr:street":"Maryland Ave",
    "iso:country":"US",
    "sg:address":"1011 Maryland Ave",
    "sg:city":"Saint Cloud",
    "sg:classifiers":[
        {
            "category":"Banks & Credit Unions",
            "subcategory":"Financial Services",
            "type":"Services"
        }
    ],
    "sg:phone":"+1 407 892 4447",
    "sg:postcode":"34769",
    "sg:province":"FL",
    "sg:tags":[
        "investor"
    ],
    "wof:name":"A & E Investment Corp",
    "wof:placetype":"venue"
},
  "geometry": {"coordinates":[-81.27460000000001,28.248083],"type":"Point"}
}