{
  "type": "Feature",
  "properties": {
    "iso:country":"US",
    "sg:address":"1620 Alden Rd",
    "sg:city":"Orlando",
    "sg:classifiers":[
        {
            "category":"Food & Beverages",
            "subcategory":"Specialty",
            "type":"Retail Goods"
        }
    ],
    "sg:phone":"+1 321 251 5445",
    "sg:postcode":"32803",
    "sg:province":"FL",
    "sg:tags":[
        "sauce",
        "condiment"
    ],
    "wof:name":"Mama's Sauce",
    "wof:placetype":"venue"
},
  "geometry": {"coordinates":[-81.37212100000001,28.565642],"type":"Point"}
}