{
  "type": "Feature",
  "properties": {
    "iso:country":"US",
    "sg:address":"6992 N Atlantic Ave",
    "sg:city":"Cape Canaveral",
    "sg:classifiers":[
        {
            "category":"Shopping",
            "subcategory":"Jewelry",
            "type":"Retail Goods"
        },
        {
            "category":"Professional",
            "subcategory":"Lawyer & Legal Services",
            "type":"Services"
        },
        {
            "category":"Shopping",
            "subcategory":"Pawn Shop",
            "type":"Retail Goods"
        }
    ],
    "sg:phone":"+1 321 868 2274",
    "sg:postcode":"32920",
    "sg:province":"FL",
    "sg:tags":[
        "notary"
    ],
    "wof:name":"Beach Pawn",
    "wof:placetype":"venue"
},
  "geometry": {"coordinates":[-80.60541499999999,28.380498],"type":"Point"}
}