{
  "type": "Feature",
  "properties": {
    "addr:full":"1455 State Hwy 436 Casselberry FL 32707",
    "addr:housenumber":"1455",
    "addr:postcode":"32707",
    "addr:street":"State Hwy 436",
    "iso:country":"US",
    "sg:address":"1455 State Hwy 436",
    "sg:city":"Casselberry",
    "sg:classifiers":[
        {
            "category":"Building & Trades",
            "subcategory":"Equipment Rental",
            "type":"Services"
        }
    ],
    "sg:phone":"+1 407 671 3783",
    "sg:postcode":"32707",
    "sg:province":"FL",
    "sg:tags":[
        "leasing",
        "furniture"
    ],
    "wof:name":"Buddy's Home Furnishings",
    "wof:placetype":"venue"
},
  "geometry": {"coordinates":[-81.31610999999999,28.626039],"type":"Point"}
}