{
  "type": "Feature",
  "properties": {
    "addr:full":"3101 3rd St W Bradenton FL 34205",
    "addr:housenumber":"3101",
    "addr:postcode":"34205",
    "addr:street":"3Rd St W",
    "iso:country":"US",
    "sg:address":"3101 3rd St W",
    "sg:city":"Bradenton",
    "sg:classifiers":[
        {
            "category":"Freight",
            "type":"Transportation"
        }
    ],
    "sg:phone":"+1 941 746 9399",
    "sg:postcode":"34205",
    "sg:province":"FL",
    "sg:tags":[
        "mover"
    ],
    "wof:name":"Covered Wagons Moving Inc",
    "wof:placetype":"venue"
},
  "geometry": {"coordinates":[-82.565001,27.472526],"type":"Point"}
}