{
  "type": "Feature",
  "properties": {
    "iso:country":"US",
    "sg:address":"510 Mariposa St",
    "sg:city":"Orlando",
    "sg:classifiers":[
        {
            "category":"Building & Trades",
            "subcategory":"Electrical",
            "type":"Services"
        }
    ],
    "sg:phone":"+1 407 649 8333",
    "sg:postcode":"32801",
    "sg:province":"FL",
    "sg:tags":[
        "electric",
        "contractor"
    ],
    "wof:name":"Palmer Electric Co",
    "wof:placetype":"venue"
},
  "geometry": {"coordinates":[-81.37000399999999,28.539767],"type":"Point"}
}