{
  "type": "Feature",
  "properties": {
    "addr:full":"5041 Glover Ln Baker FL 32570",
    "addr:housenumber":"5041",
    "addr:postcode":"32570",
    "addr:street":"Glover Ln",
    "iso:country":"US",
    "sg:address":"5041 Glover Ln",
    "sg:city":"Baker",
    "sg:classifiers":[
        {
            "category":"Building & Trades",
            "subcategory":"Construction",
            "type":"Services"
        }
    ],
    "sg:phone":"+1 850 537 3109",
    "sg:postcode":"32570",
    "sg:province":"FL",
    "sg:tags":[
        "general",
        "contractor"
    ],
    "wof:name":"Michael Kelley Construction",
    "wof:placetype":"venue"
},
  "geometry": {"coordinates":[-87.06440499999999,30.62351],"type":"Point"}
}