{
  "type": "Feature",
  "properties": {
    "iso:country":"US",
    "sg:address":"3631 22nd Ave S",
    "sg:city":"St Petersburg",
    "sg:classifiers":[
        {
            "category":"Organizations",
            "subcategory":"Religious Organization",
            "type":"Services"
        }
    ],
    "sg:phone":"+1 727 327 1507",
    "sg:postcode":"33711",
    "sg:province":"FL",
    "sg:tags":[
        "church"
    ],
    "wof:name":"Moses Tabernacle Missionary",
    "wof:placetype":"venue"
},
  "geometry": {"coordinates":[-82.681752,27.748319],"type":"Point"}
}