{
  "type": "Feature",
  "properties": {
    "addr:full":"5866 Triphammer Rd Lake Worth FL 33463",
    "addr:housenumber":"5866",
    "addr:postcode":"33463",
    "addr:street":"Triphammer Rd",
    "iso:country":"US",
    "sg:address":"5866 Triphammer Rd",
    "sg:city":"Lake Worth",
    "sg:classifiers":[
        {
            "category":"Freight",
            "type":"Transportation"
        }
    ],
    "sg:phone":"+1 561 649 4031",
    "sg:postcode":"33463",
    "sg:province":"FL",
    "sg:tags":[
        "operator",
        "trucking"
    ],
    "wof:name":"Charlot Beauvolr Joseph",
    "wof:placetype":"venue"
},
  "geometry": {"coordinates":[-80.138358,26.603669],"type":"Point"}
}