{
  "type": "Feature",
  "properties": {
    "iso:country":"US",
    "sg:address":"4901 Sunbeam Rd",
    "sg:city":"Jacksonville",
    "sg:classifiers":[
        {
            "category":"Real Estate",
            "subcategory":"Real Estate Operator",
            "type":"Services"
        }
    ],
    "sg:phone":"+1 904 256 4650",
    "sg:postcode":"32257",
    "sg:province":"FL",
    "sg:tags":[
        "apartment"
    ],
    "wof:name":"Thomas Chase Apartments",
    "wof:placetype":"venue"
},
  "geometry": {"coordinates":[-81.589158,30.206035],"type":"Point"}
}