{
  "type": "Feature",
  "properties": {
    "iso:country":"US",
    "sg:address":"1921 NW 79th St",
    "sg:city":"Miami",
    "sg:classifiers":[
        {
            "category":"Building & Trades",
            "subcategory":"Construction",
            "type":"Services"
        }
    ],
    "sg:phone":"+1 305 835 7380",
    "sg:postcode":"33147",
    "sg:province":"FL",
    "sg:tags":[
        "house"
    ],
    "wof:name":"Diaz Vivar Construction Co",
    "wof:placetype":"venue"
},
  "geometry": {"coordinates":[-80.229878,25.846467],"type":"Point"}
}