{
  "type": "Feature",
  "properties": {
    "iso:country":"US",
    "sg:address":"975 Arthur Godfrey Rd",
    "sg:city":"Miami Beach",
    "sg:classifiers":[
        {
            "category":"Shopping",
            "subcategory":"Bicycles & Sporting Goods",
            "type":"Retail Goods"
        }
    ],
    "sg:phone":"+1 305 531 8142",
    "sg:postcode":"33140",
    "sg:province":"FL",
    "wof:name":"Ammoworks Inc",
    "wof:placetype":"venue"
},
  "geometry": {"coordinates":[-80.13547,25.813271],"type":"Point"}
}