{
  "type": "Feature",
  "properties": {
    "iso:country":"US",
    "sg:address":"3304 43rd St W",
    "sg:city":"Bradenton",
    "sg:classifiers":[
        {
            "category":"Education",
            "subcategory":"School",
            "type":"Public Place"
        }
    ],
    "sg:phone":"+1 941 792 5454",
    "sg:postcode":"34209",
    "sg:province":"FL",
    "wof:name":"Christian Bradenton School Soc",
    "wof:placetype":"venue"
},
  "geometry": {"coordinates":[-82.604167,27.470326],"type":"Point"}
}