{
  "type": "Feature",
  "properties": {
    "iso:country":"US",
    "sg:address":"2501 Biscayne Blvd",
    "sg:city":"Miami",
    "sg:classifiers":[
        {
            "category":"Restaurant",
            "type":"Food & Drink"
        }
    ],
    "sg:phone":"+1 305 576 3838",
    "sg:postcode":"33137",
    "sg:province":"FL",
    "sg:tags":[
        "cuban"
    ],
    "wof:name":"Latin Cafe 2000",
    "wof:placetype":"venue"
},
  "geometry": {"coordinates":[-80.189301,25.801201],"type":"Point"}
}