{
  "type": "Feature",
  "properties": {
    "addr:full":"424 S Deleon Ave Titusville FL 32796",
    "addr:housenumber":"424",
    "addr:postcode":"32796",
    "addr:street":"S Deleon Ave",
    "iso:country":"US",
    "sg:address":"424 S Deleon Ave",
    "sg:city":"Titusville",
    "sg:classifiers":[
        {
            "category":"Manufacturing",
            "subcategory":"Metals",
            "type":"Manufacturing & Wholesale Goods"
        }
    ],
    "sg:phone":"+1 321 269 7812",
    "sg:postcode":"32796",
    "sg:province":"FL",
    "sg:tags":[
        "hardware"
    ],
    "wof:name":"Seabrite Stainless Steel",
    "wof:placetype":"venue"
},
  "geometry": {"coordinates":[-80.814667,28.610624],"type":"Point"}
}