{
  "type": "Feature",
  "properties": {
    "iso:country":"US",
    "sg:address":"88 Riberia St",
    "sg:city":"Saint Augustine",
    "sg:classifiers":[
        {
            "category":"Professional",
            "subcategory":"Business Services",
            "type":"Services"
        }
    ],
    "sg:phone":"+1 904 829 1711",
    "sg:postcode":"32084",
    "sg:province":"FL",
    "sg:tags":[
        "visitor",
        "bureau",
        "convention"
    ],
    "wof:name":"St Johns County Visitor Bureau",
    "wof:placetype":"venue"
},
  "geometry": {"coordinates":[-81.318303,29.891343],"type":"Point"}
}