{
  "type": "Feature",
  "properties": {
    "addr:full":"1025 NW 127th St Miami FL 33168",
    "addr:housenumber":"1025",
    "addr:postcode":"33168",
    "addr:street":"Nw 127Th St",
    "iso:country":"US",
    "sg:address":"1025 NW 127th St",
    "sg:city":"Miami",
    "sg:classifiers":[
        {
            "category":"Building & Trades",
            "subcategory":"Landscaping Services",
            "type":"Services"
        }
    ],
    "sg:phone":"+1 305 687 6009",
    "sg:postcode":"33168",
    "sg:province":"FL",
    "sg:tags":[
        "lawn",
        "tree",
        "landscape"
    ],
    "wof:name":"Mamas Exprt Complete Property",
    "wof:placetype":"venue"
},
  "geometry": {"coordinates":[-80.216534,25.890852],"type":"Point"}
}