{
  "type": "Feature",
  "properties": {
    "iso:country":"US",
    "sg:address":"624 SW 35th Ter",
    "sg:city":"Cape Coral",
    "sg:classifiers":[
        {
            "category":"Building & Trades",
            "subcategory":"Landscaping Services",
            "type":"Services"
        }
    ],
    "sg:phone":"+1 239 281 8586",
    "sg:postcode":"33914",
    "sg:province":"FL",
    "sg:tags":[
        "landscape"
    ],
    "wof:name":"Fernando Rangel Landscape",
    "wof:placetype":"venue"
},
  "geometry": {"coordinates":[-81.98788399999999,26.586057],"type":"Point"}
}