{
  "type": "Feature",
  "properties": {
    "iso:country":"US",
    "sg:address":"12735 Knights Griffin Rd",
    "sg:city":"Thonotosassa",
    "sg:classifiers":[
        {
            "category":"Place Of Worship",
            "subcategory":"Church",
            "type":"Public Place"
        },
        {
            "category":"Place Of Worship",
            "type":"Public Place"
        }
    ],
    "sg:phone":"+1 813 986 4346",
    "sg:postcode":"33592",
    "sg:province":"FL",
    "sg:tags":[
        "churches-baptist-general",
        "churches-baptist"
    ],
    "wof:name":"East Thonotosassa Baptist Church",
    "wof:placetype":"venue"
},
  "geometry": {"coordinates":[-82.251322,28.076318],"type":"Point"}
}