{
  "type": "Feature",
  "properties": {
    "iso:country":"US",
    "sg:address":"3201 W Parkland Blvd",
    "sg:city":"Tampa",
    "sg:classifiers":[
        {
            "category":"Professional",
            "subcategory":"Employment Agencies",
            "type":"Services"
        }
    ],
    "sg:phone":"+1 813 348 4611",
    "sg:postcode":"33609",
    "sg:province":"FL",
    "sg:tags":[
        "consultant",
        "search",
        "executive"
    ],
    "wof:name":"DHR Intl",
    "wof:placetype":"venue"
},
  "geometry": {"coordinates":[-82.49751999999999,27.934814],"type":"Point"}
}