{
  "type": "Feature",
  "properties": {
    "addr:full":"19 W Vining St Winter Garden FL 34787",
    "addr:housenumber":"19",
    "addr:postcode":"34787",
    "addr:street":"W Vining St",
    "iso:country":"US",
    "sg:address":"19 W Vining St",
    "sg:city":"Winter Garden",
    "sg:classifiers":[
        {
            "category":"Building & Trades",
            "subcategory":"Landscaping Services",
            "type":"Services"
        }
    ],
    "sg:phone":"+1 407 656 4446",
    "sg:postcode":"34787",
    "sg:province":"FL",
    "wof:name":"Hancock Tree Service",
    "wof:placetype":"venue"
},
  "geometry": {"coordinates":[-81.58597,28.559889],"type":"Point"}
}