{
  "type": "Feature",
  "properties": {
    "iso:country":"US",
    "sg:address":"8851 SW 168th St",
    "sg:city":"Palmetto Bay",
    "sg:classifiers":[
        {
            "category":"Education",
            "subcategory":"School",
            "type":"Public Place"
        }
    ],
    "sg:phone":"+1 305 235 2442",
    "sg:postcode":"33157",
    "sg:province":"FL",
    "sg:tags":[
        "high",
        "middle",
        "elementary"
    ],
    "wof:name":"Miami-Dade County Public Schools",
    "wof:placetype":"venue"
},
  "geometry": {"coordinates":[-80.335978,25.614423],"type":"Point"}
}