{
  "type": "Feature",
  "properties": {
    "iso:country":"US",
    "sg:address":"16605 NW 10th St",
    "sg:city":"Hollywood",
    "sg:classifiers":[
        {
            "category":"Professional",
            "subcategory":"Management & Consulting",
            "type":"Services"
        }
    ],
    "sg:phone":"+1 954 559 1255",
    "sg:postcode":"33028",
    "sg:province":"FL",
    "sg:tags":[
        "wholesale",
        "good",
        "trade"
    ],
    "wof:name":"Panda Enterprises Usa  Inc",
    "wof:placetype":"venue"
},
  "geometry": {"coordinates":[-80.36799999999999,26.015898],"type":"Point"}
}