{
  "type": "Feature",
  "properties": {
    "addr:full":"265 Fareham Dr Venice FL 34293",
    "addr:housenumber":"265",
    "addr:postcode":"34293",
    "addr:street":"Fareham Dr",
    "iso:country":"US",
    "sg:address":"265 Fareham Dr",
    "sg:city":"Venice",
    "sg:classifiers":[
        {
            "category":"Real Estate",
            "subcategory":"Real Estate Services",
            "type":"Services"
        },
        {
            "category":"Building & Trades",
            "subcategory":"Cleaning & Sanitation",
            "type":"Services"
        }
    ],
    "sg:phone":"+1 941 496 8571",
    "sg:postcode":"34293",
    "sg:province":"FL",
    "sg:tags":[
        "maintenance",
        "cleaners-interior"
    ],
    "wof:name":"Cjs Cleaning Service",
    "wof:placetype":"venue"
},
  "geometry": {"coordinates":[-82.352943,27.050871],"type":"Point"}
}