{
  "type": "Feature",
  "properties": {
    "addr:full":"2480 Treasure Isle Dr Palm Beach Gardens FL 33410",
    "addr:housenumber":"2480",
    "addr:postcode":"33410",
    "addr:street":"Treasure Isle Dr",
    "iso:country":"US",
    "sg:address":"2480 Treasure Isle Dr",
    "sg:city":"Palm Beach Gardens",
    "sg:classifiers":[
        {
            "category":"Shopping",
            "subcategory":"Crafts & Fabrics",
            "type":"Retail Goods"
        }
    ],
    "sg:phone":"+1 561 626 9413",
    "sg:postcode":"33410",
    "sg:province":"FL",
    "sg:tags":[
        "sewing",
        "notion"
    ],
    "wof:name":"Designer Fabric Collection",
    "wof:placetype":"venue"
},
  "geometry": {"coordinates":[-80.07093500000001,26.872303],"type":"Point"}
}