{
  "type": "Feature",
  "properties": {
    "addr:full":"100 NW 25th St Miami FL 33127",
    "addr:housenumber":"100",
    "addr:postcode":"33127",
    "addr:street":"Nw 25Th St",
    "iso:country":"US",
    "sg:address":"100 NW 25th St",
    "sg:city":"Miami",
    "sg:classifiers":[
        {
            "category":"Manufacturing",
            "subcategory":"Apparel",
            "type":"Manufacturing & Wholesale Goods"
        }
    ],
    "sg:phone":"+1 305 573 5142",
    "sg:postcode":"33127",
    "sg:province":"FL",
    "sg:tags":[
        "unisex",
        "athletic",
        "clothing",
        "mfg"
    ],
    "wof:name":"Universal Athletic",
    "wof:placetype":"venue"
},
  "geometry": {"coordinates":[-80.199095,25.800732],"type":"Point"}
}