{
  "type": "Feature",
  "properties": {
    "iso:country":"US",
    "sg:address":"9302 Florida Palm Dr",
    "sg:city":"Tampa",
    "sg:classifiers":[
        {
            "category":"Wholesale",
            "subcategory":"Furniture",
            "type":"Manufacturing & Wholesale Goods"
        }
    ],
    "sg:phone":"+1 813 620 0048",
    "sg:postcode":"33619",
    "sg:province":"FL",
    "wof:name":"Herman Mller Wrkplace Resource",
    "wof:placetype":"venue"
},
  "geometry": {"coordinates":[-82.351389,27.944705],"type":"Point"}
}