{
  "type": "Feature",
  "properties": {
    "addr:full":"8471 Casa del Lago Boca Raton FL 33433",
    "addr:housenumber":"8471",
    "addr:postcode":"33433",
    "addr:street":"Casa Del Lago",
    "iso:country":"US",
    "sg:address":"8471 Casa del Lago",
    "sg:city":"Boca Raton",
    "sg:classifiers":[
        {
            "category":"Banks & Credit Unions",
            "subcategory":"Financial Services",
            "type":"Services"
        }
    ],
    "sg:phone":"+1 561 482 0797",
    "sg:postcode":"33433",
    "sg:province":"FL",
    "sg:tags":[
        "company",
        "holding"
    ],
    "wof:name":"Kenmor Holdings Corp",
    "wof:placetype":"venue"
},
  "geometry": {"coordinates":[-80.17885,26.35696],"type":"Point"}
}