{
  "type": "Feature",
  "properties": {
    "iso:country":"US",
    "sg:address":"16640 Bachmann Ave",
    "sg:city":"Hudson",
    "sg:classifiers":[
        {
            "category":"Wholesale",
            "subcategory":"Machinery & Supplies",
            "type":"Manufacturing & Wholesale Goods"
        }
    ],
    "sg:phone":"+1 727 869 1521",
    "sg:postcode":"34667",
    "sg:province":"FL",
    "sg:tags":[
        "crane",
        "derrick"
    ],
    "wof:name":"Liftek Corp",
    "wof:placetype":"venue"
},
  "geometry": {"coordinates":[-82.66096899999999,28.401657],"type":"Point"}
}