{
  "type": "Feature",
  "properties": {
    "iso:country":"US",
    "sg:address":"12122 Dawn Vista Dr",
    "sg:city":"Riverview",
    "sg:classifiers":[
        {
            "category":"Retail",
            "subcategory":"Repair Shop",
            "type":"Services"
        }
    ],
    "sg:phone":"+1 813 433 6384",
    "sg:postcode":"33578",
    "sg:province":"FL",
    "sg:tags":[
        "cleaning"
    ],
    "wof:name":"Diana Mangroo",
    "wof:placetype":"venue"
},
  "geometry": {"coordinates":[-82.33392499999999,27.81542],"type":"Point"}
}