{
  "type": "Feature",
  "properties": {
    "addr:full":"308 E Martin Luther King Jr Blvd Tampa FL 33603",
    "addr:housenumber":"308",
    "addr:postcode":"33603",
    "addr:street":"E Martin Luther King Jr Blvd",
    "iso:country":"US",
    "sg:address":"308 E Martin Luther King Jr Blvd",
    "sg:city":"Tampa",
    "sg:classifiers":[
        {
            "category":"Social Services",
            "subcategory":"Job Training",
            "type":"Services"
        }
    ],
    "sg:phone":"+1 813 236 8936",
    "sg:postcode":"33603",
    "sg:province":"FL",
    "sg:tags":[
        "rehabilitation"
    ],
    "wof:name":"Preferred Medical & Rehab",
    "wof:placetype":"venue"
},
  "geometry": {"coordinates":[-82.456925,27.981591],"type":"Point"}
}