{
  "type": "Feature",
  "properties": {
    "iso:country":"US",
    "sg:address":"4711 Gall Blvd",
    "sg:city":"Zephyrhills",
    "sg:classifiers":[
        {
            "category":"Bars & Pubs",
            "type":"Food & Drink"
        }
    ],
    "sg:phone":"+1 813 788 6409",
    "sg:postcode":"33542",
    "sg:province":"FL",
    "sg:tags":[
        "drinking"
    ],
    "wof:name":"Anchor Inn",
    "wof:placetype":"venue"
},
  "geometry": {"coordinates":[-82.180029,28.225858],"type":"Point"}
}