{
  "type": "Feature",
  "properties": {
    "addr:full":"8695 College Pkwy Fort Myers FL 33919",
    "addr:housenumber":"8695",
    "addr:postcode":"33919",
    "addr:street":"College Pkwy",
    "iso:country":"US",
    "sg:address":"8695 College Pkwy",
    "sg:city":"Fort Myers",
    "sg:classifiers":[
        {
            "category":"Professional",
            "subcategory":"Accounting & Tax Preparation",
            "type":"Services"
        }
    ],
    "sg:phone":"+1 239 489 2808",
    "sg:postcode":"33919",
    "sg:province":"FL",
    "wof:name":"ADP",
    "wof:placetype":"venue"
},
  "geometry": {"coordinates":[-81.89860899999999,26.556502],"type":"Point"}
}