{
  "type": "Feature",
  "properties": {
    "addr:full":"795 E Sunrise Blvd Fort Lauderdale FL 33304",
    "addr:housenumber":"795",
    "addr:postcode":"33304",
    "addr:street":"E Sunrise Blvd",
    "iso:country":"US",
    "sg:address":"795 E Sunrise Blvd",
    "sg:city":"Fort Lauderdale",
    "sg:classifiers":[
        {
            "category":"Building & Trades",
            "subcategory":"Construction",
            "type":"Services"
        }
    ],
    "sg:phone":"+1 954 523 0840",
    "sg:postcode":"33304",
    "sg:province":"FL",
    "sg:tags":[
        "contractor"
    ],
    "wof:name":"Broward Discount Carpet & Tile",
    "wof:placetype":"venue"
},
  "geometry": {"coordinates":[-80.136048,26.137085],"type":"Point"}
}