{
  "type": "Feature",
  "properties": {
    "iso:country":"US",
    "sg:address":"9113 W Highway 98",
    "sg:city":"Pensacola",
    "sg:classifiers":[
        {
            "category":"Personal",
            "type":"Services"
        },
        {
            "category":"Retail",
            "subcategory":"Storage",
            "type":"Services"
        }
    ],
    "sg:phone":"+1 866 320 6309",
    "sg:postcode":"32506",
    "sg:province":"FL",
    "sg:tags":[
        "self",
        "full",
        "commercial",
        "mover",
        "household"
    ],
    "sg:website":"http://www.unclebobs.com/stores/UB356/?source=Yellowpages.com&howheard=ISM",
    "wof:name":"Uncle Bob's Self Storage",
    "wof:placetype":"venue"
},
  "geometry": {"coordinates":[-87.338658,30.403153],"type":"Point"}
}