{
  "type": "Feature",
  "properties": {
    "addr:full":"910 Villa Lagoon Dr Tavares FL 32778",
    "addr:housenumber":"910",
    "addr:postcode":"32778",
    "addr:street":"Villa Lagoon Dr",
    "iso:country":"US",
    "sg:address":"910 Villa Lagoon Dr",
    "sg:city":"Tavares",
    "sg:classifiers":[
        {
            "category":"Real Estate",
            "subcategory":"Real Estate Operator",
            "type":"Services"
        }
    ],
    "sg:phone":"+1 352 343 4468",
    "sg:postcode":"32778",
    "sg:province":"FL",
    "sg:tags":[
        "mobile",
        "home",
        "site"
    ],
    "wof:name":"Lagoon Park Inc",
    "wof:placetype":"venue"
},
  "geometry": {"coordinates":[-81.73723,28.811457],"type":"Point"}
}