{
  "type": "Feature",
  "properties": {
    "iso:country":"US",
    "sg:address":"919 Spanish Dr S",
    "sg:city":"Longboat Key",
    "sg:classifiers":[
        {
            "category":"Building & Trades",
            "subcategory":"Construction",
            "type":"Services"
        }
    ],
    "sg:phone":"+1 941 383 2269",
    "sg:postcode":"34228",
    "sg:province":"FL",
    "sg:tags":[
        "house"
    ],
    "wof:name":"Northwest Homes",
    "wof:placetype":"venue"
},
  "geometry": {"coordinates":[-82.658186,27.420323],"type":"Point"}
}