{
  "type": "Feature",
  "properties": {
    "iso:country":"US",
    "sg:address":"7921 Bird Rd",
    "sg:city":"Miami",
    "sg:classifiers":[
        {
            "category":"Building & Trades",
            "subcategory":"Locksmith",
            "type":"Services"
        }
    ],
    "sg:phone":"+1 786 228 5419",
    "sg:postcode":"33155",
    "sg:province":"FL",
    "sg:tags":[
        "key"
    ],
    "wof:name":"Locksmith Available On Bird Rd",
    "wof:placetype":"venue"
},
  "geometry": {"coordinates":[-80.323624,25.733293],"type":"Point"}
}