{
  "type": "Feature",
  "properties": {
    "iso:country":"US",
    "sg:address":"1380 Cypress Ave",
    "sg:city":"Melbourne",
    "sg:classifiers":[
        {
            "category":"Personal",
            "subcategory":"Tattoo Parlor",
            "type":"Services"
        }
    ],
    "sg:phone":"+1 321 255 9449",
    "sg:postcode":"32935",
    "sg:province":"FL",
    "sg:tags":[
        "tattooing"
    ],
    "sg:website":"http://againstthegraintattoo.com",
    "wof:name":"Against The Grain Tattoos",
    "wof:placetype":"venue"
},
  "geometry": {"coordinates":[-80.631225,28.12936],"type":"Point"}
}