{
  "type": "Feature",
  "properties": {
    "iso:country":"US",
    "sg:address":"55 Columbia St",
    "sg:city":"Orlando",
    "sg:classifiers":[
        {
            "category":"Community Center",
            "type":"Public Place"
        }
    ],
    "sg:phone":"+1 407 237 6319",
    "sg:postcode":"32806",
    "sg:province":"FL",
    "sg:tags":[
        "medical"
    ],
    "wof:name":"Pediatric Outpatient Center Orlando Regional Medical Center",
    "wof:placetype":"venue"
},
  "geometry": {"coordinates":[-81.378736,28.527886],"type":"Point"}
}