{
  "type": "Feature",
  "properties": {
    "iso:country":"US",
    "sg:address":"11945 Southern Blvd",
    "sg:city":"Royal Palm Beach",
    "sg:classifiers":[
        {
            "category":"Insurance",
            "subcategory":"Insurance Agent",
            "type":"Services"
        }
    ],
    "sg:phone":"+1 561 333 3855",
    "sg:postcode":"33411",
    "sg:province":"FL",
    "wof:name":"Fed USA Insurance",
    "wof:placetype":"venue"
},
  "geometry": {"coordinates":[-80.233405,26.681201],"type":"Point"}
}