{
  "type": "Feature",
  "properties": {
    "addr:full":"5436A Millstone Cir Milton FL 32570",
    "addr:housenumber":"5436a",
    "addr:postcode":"32570",
    "addr:street":"Millstone Cir",
    "iso:country":"US",
    "sg:address":"5436A Millstone Cir",
    "sg:city":"Milton",
    "sg:classifiers":[
        {
            "category":"Shopping",
            "subcategory":"Jewelry",
            "type":"Retail Goods"
        }
    ],
    "sg:phone":"+1 850 626 3538",
    "sg:postcode":"32570",
    "sg:province":"FL",
    "sg:tags":[
        "precious",
        "semi-precious",
        "stone"
    ],
    "wof:name":"Original Design Jewelry",
    "wof:placetype":"venue"
},
  "geometry": {"coordinates":[-87.064348,30.633188],"type":"Point"}
}