{
  "type": "Feature",
  "properties": {
    "addr:full":"810 Florida Ave Lynn Haven FL 32444",
    "addr:housenumber":"810",
    "addr:postcode":"32444",
    "addr:street":"Florida Ave",
    "iso:country":"US",
    "sg:address":"810 Florida Ave",
    "sg:city":"Lynn Haven",
    "sg:classifiers":[
        {
            "category":"Banks & Credit Unions",
            "subcategory":"Investment Brokerage",
            "type":"Services"
        }
    ],
    "sg:phone":"+1 850 265 5040",
    "sg:postcode":"32444",
    "sg:province":"FL",
    "sg:tags":[
        "stock",
        "bond"
    ],
    "wof:name":"Edward Jones Co",
    "wof:placetype":"venue"
},
  "geometry": {"coordinates":[-85.64985799999999,30.24545],"type":"Point"}
}