{
  "type": "Feature",
  "properties": {
    "iso:country":"US",
    "sg:address":"9445 SW 40th St",
    "sg:city":"Miami",
    "sg:classifiers":[
        {
            "category":"Insurance",
            "subcategory":"Insurance Agent",
            "type":"Services"
        }
    ],
    "sg:phone":"+1 305 207 8900",
    "sg:postcode":"33165",
    "sg:province":"FL",
    "sg:tags":[
        "travel",
        "services-commercial"
    ],
    "wof:name":"America's Best Coverage Insurance Agency",
    "wof:placetype":"venue"
},
  "geometry": {"coordinates":[-80.348677,25.732852],"type":"Point"}
}