{
  "type": "Feature",
  "properties": {
    "iso:country":"US",
    "sg:address":"1945 W Lumsden Rd",
    "sg:city":"Brandon",
    "sg:classifiers":[
        {
            "category":"Food & Beverages",
            "subcategory":"Groceries & Convenience Stores",
            "type":"Retail Goods"
        }
    ],
    "sg:phone":"+1 813 657 6554",
    "sg:postcode":"33511",
    "sg:province":"FL",
    "wof:name":"Win Dixie Store 615",
    "wof:placetype":"venue"
},
  "geometry": {"coordinates":[-82.315341,27.923238],"type":"Point"}
}