{
  "type": "Feature",
  "properties": {
    "iso:country":"US",
    "sg:address":"1080 S Collier Blvd",
    "sg:city":"Marco Island",
    "sg:classifiers":[
        {
            "category":"Manufacturing",
            "subcategory":"Retail Goods",
            "type":"Manufacturing & Wholesale Goods"
        }
    ],
    "sg:phone":"+1 239 394 8733",
    "sg:postcode":"34145",
    "sg:province":"FL",
    "sg:tags":[
        "product",
        "mfg"
    ],
    "wof:name":"Belco Industries Inc",
    "wof:placetype":"venue"
},
  "geometry": {"coordinates":[-81.72306,25.910533],"type":"Point"}
}