{
  "type": "Feature",
  "properties": {
    "iso:country":"US",
    "sg:address":"4765 SW 8th St",
    "sg:city":"Coral Gables",
    "sg:classifiers":[
        {
            "category":"Personal",
            "subcategory":"Shoe Repair & Shine",
            "type":"Services"
        }
    ],
    "sg:phone":"+1 305 441 1501",
    "sg:postcode":"33134",
    "sg:province":"FL",
    "wof:name":"Fortunato's Shoe Repair",
    "wof:placetype":"venue"
},
  "geometry": {"coordinates":[-80.272898,25.764244],"type":"Point"}
}