{
  "type": "Feature",
  "properties": {
    "iso:country":"US",
    "sg:address":"36 NE 1st Ave",
    "sg:city":"Miami",
    "sg:classifiers":[
        {
            "category":"Manufacturing",
            "subcategory":"Jewelry",
            "type":"Manufacturing & Wholesale Goods"
        },
        {
            "category":"Wholesale",
            "subcategory":"Jewelry",
            "type":"Manufacturing & Wholesale Goods"
        }
    ],
    "sg:phone":"+1 305 358 9162",
    "sg:postcode":"33132",
    "sg:province":"FL",
    "sg:tags":[
        "material",
        "mfg"
    ],
    "wof:name":"Jay Bee Gems Inc",
    "wof:placetype":"venue"
},
  "geometry": {"coordinates":[-80.19202900000001,25.774825],"type":"Point"}
}