{
  "type": "Feature",
  "properties": {
    "addr:full":"2379 Beville Rd Daytona Beach FL 32119",
    "addr:housenumber":"2379",
    "addr:postcode":"32119",
    "addr:street":"Beville Rd",
    "iso:country":"US",
    "sg:address":"2379 Beville Rd",
    "sg:city":"Daytona Beach",
    "sg:classifiers":[
        {
            "category":"Banks & Credit Unions",
            "subcategory":"Bank",
            "type":"Services"
        }
    ],
    "sg:phone":"+1 386 763 3334",
    "sg:postcode":"32119",
    "sg:province":"FL",
    "sg:tags":[
        "escrow"
    ],
    "wof:name":"Southern Title",
    "wof:placetype":"venue"
},
  "geometry": {"coordinates":[-81.064623,29.160176],"type":"Point"}
}