{
  "type": "Feature",
  "properties": {
    "addr:full":"3763 Enterprise Ave Naples FL 34104",
    "addr:housenumber":"3763",
    "addr:postcode":"34104",
    "addr:street":"Enterprise Ave",
    "iso:country":"US",
    "sg:address":"3763 Enterprise Ave",
    "sg:city":"Naples",
    "sg:classifiers":[
        {
            "category":"Home & Garden",
            "subcategory":"Building Materials",
            "type":"Retail Goods"
        }
    ],
    "sg:phone":"+1 239 643 3664",
    "sg:postcode":"34104",
    "sg:province":"FL",
    "sg:tags":[
        "paint"
    ],
    "wof:name":"Florida All State Paint",
    "wof:placetype":"venue"
},
  "geometry": {"coordinates":[-81.763677,26.160695],"type":"Point"}
}