{
  "type": "Feature",
  "properties": {
    "iso:country":"US",
    "sg:address":"7124 Aloma Ave",
    "sg:city":"Winter Park",
    "sg:classifiers":[
        {
            "category":"Bars & Pubs",
            "type":"Food & Drink"
        }
    ],
    "sg:phone":"+1 407 678 3043",
    "sg:postcode":"32792",
    "sg:province":"FL",
    "sg:tags":[
        "lounge",
        "cocktail"
    ],
    "wof:name":"Ladies Lounge",
    "wof:placetype":"venue"
},
  "geometry": {"coordinates":[-81.29427800000001,28.607128],"type":"Point"}
}