{
  "type": "Feature",
  "properties": {
    "addr:full":"9360 Lem Turner Rd Jacksonville FL 32208",
    "addr:postcode":"9360;32208",
    "addr:street":"Turner Rd",
    "iso:country":"US",
    "sg:address":"9360 Lem Turner Rd",
    "sg:city":"Jacksonville",
    "sg:classifiers":[
        {
            "category":"Health Services",
            "subcategory":"Chiropractor",
            "type":"Services"
        }
    ],
    "sg:phone":"+1 904 764 3434",
    "sg:postcode":"32208",
    "sg:province":"FL",
    "wof:name":"Accident Care & Wellness",
    "wof:placetype":"venue"
},
  "geometry": {"coordinates":[-81.688895,30.410262],"type":"Point"}
}