{
  "type": "Feature",
  "properties": {
    "iso:country":"US",
    "sg:address":"1900 W 44th Pl",
    "sg:city":"Hialeah",
    "sg:classifiers":[
        {
            "category":"Education",
            "subcategory":"School",
            "type":"Public Place"
        }
    ],
    "sg:phone":"+1 305 556 5409",
    "sg:postcode":"33012",
    "sg:province":"FL",
    "wof:name":"Our Lady of Charity Private School",
    "wof:placetype":"venue"
},
  "geometry": {"coordinates":[-80.319603,25.8624],"type":"Point"}
}