{
  "type": "Feature",
  "properties": {
    "iso:country":"US",
    "sg:address":"2224 Tipperary Ct",
    "sg:city":"Orlando",
    "sg:classifiers":[
        {
            "category":"Professional",
            "subcategory":"Accounting & Tax Preparation",
            "type":"Services"
        }
    ],
    "sg:phone":"+1 407 273 8382",
    "sg:postcode":"32812",
    "sg:province":"FL",
    "sg:tags":[
        "billing"
    ],
    "wof:name":"Kevin W Snider Billing Svc",
    "wof:placetype":"venue"
},
  "geometry": {"coordinates":[-81.316742,28.517449],"type":"Point"}
}