{
  "type": "Feature",
  "properties": {
    "addr:full":"7614 Navarre Pkwy Navarre FL 32566",
    "addr:housenumber":"7614",
    "addr:postcode":"32566",
    "addr:street":"Navarre Pkwy",
    "iso:country":"US",
    "sg:address":"7614 Navarre Pkwy",
    "sg:city":"Navarre",
    "sg:classifiers":[
        {
            "category":"Food & Beverages",
            "subcategory":"Groceries & Convenience Stores",
            "type":"Retail Goods"
        }
    ],
    "sg:phone":"+1 850 939 1136",
    "sg:postcode":"32566",
    "sg:province":"FL",
    "wof:name":"Tom Thumb Food Store",
    "wof:placetype":"venue"
},
  "geometry": {"coordinates":[-86.91264099999999,30.401989],"type":"Point"}
}