{
  "type": "Feature",
  "properties": {
    "addr:full":"7964 NW 66th St Miami FL 33166",
    "addr:housenumber":"7964",
    "addr:postcode":"33166",
    "addr:street":"Nw 66Th St",
    "iso:country":"US",
    "sg:address":"7964 NW 66th St",
    "sg:city":"Miami",
    "sg:classifiers":[
        {
            "category":"Professional",
            "type":"Services"
        }
    ],
    "sg:phone":"+1 305 477 0477",
    "sg:postcode":"33166",
    "sg:province":"FL",
    "wof:name":"Sarah Paz Inc",
    "wof:placetype":"venue"
},
  "geometry": {"coordinates":[-80.326003,25.833407],"type":"Point"}
}