{
  "type": "Feature",
  "properties": {
    "addr:full":"300 Alhambra Cir Coral Gables FL 33134",
    "addr:housenumber":"300",
    "addr:postcode":"33134",
    "addr:street":"Alhambra Cir",
    "iso:country":"US",
    "sg:address":"300 Alhambra Cir",
    "sg:city":"Coral Gables",
    "sg:classifiers":[
        {
            "category":"Coffee & Tea",
            "type":"Food & Drink"
        }
    ],
    "sg:phone":"+1 305 448 4949",
    "sg:postcode":"33134",
    "sg:province":"FL",
    "sg:website":"www.cafedemetrio.com/",
    "wof:name":"Cafe Demetrio",
    "wof:placetype":"venue"
},
  "geometry": {"coordinates":[-80.261002,25.752001],"type":"Point"}
}