{
  "type": "Feature",
  "properties": {
    "addr:full":"5408 Silver Star Rd Orlando FL 32808",
    "addr:housenumber":"5408",
    "addr:postcode":"32808",
    "addr:street":"Silver Star Rd",
    "iso:country":"US",
    "sg:address":"5408 Silver Star Rd",
    "sg:city":"Orlando",
    "sg:classifiers":[
        {
            "category":"Autos & Motor Vehicles",
            "subcategory":"Auto Supplies",
            "type":"Retail Goods"
        },
        {
            "category":"Wholesale",
            "subcategory":"Electrical",
            "type":"Manufacturing & Wholesale Goods"
        },
        {
            "category":"Wholesale",
            "subcategory":"Auto Parts",
            "type":"Manufacturing & Wholesale Goods"
        },
        {
            "category":"Retail",
            "subcategory":"Auto Repair",
            "type":"Services"
        }
    ],
    "sg:phone":"+1 407 298 8230",
    "sg:postcode":"32808",
    "sg:province":"FL",
    "sg:tags":[
        "engines-rebuild",
        "exchange",
        "battery",
        "automobile",
        "accessory",
        "equipment",
        "supplies-used",
        "truck",
        "rebuilt",
        "batteries-storage"
    ],
    "sg:website":"http://www.advanceautoparts.com",
    "wof:name":"Advance Auto Parts",
    "wof:placetype":"venue"
},
  "geometry": {"coordinates":[-81.454308,28.577869],"type":"Point"}
}