{
  "type": "Feature",
  "properties": {
    "addr:full":"4359 Coconut Blvd West Palm Beach FL 33411",
    "addr:housenumber":"4359",
    "addr:postcode":"33411",
    "addr:street":"Coconut Blvd",
    "iso:country":"US",
    "sg:address":"4359 Coconut Blvd",
    "sg:city":"West Palm Beach",
    "sg:classifiers":[
        {
            "category":"Utilities",
            "type":"Services"
        }
    ],
    "sg:phone":"+1 561 795 7737",
    "sg:postcode":"33411",
    "sg:province":"FL",
    "sg:tags":[
        "sweeping"
    ],
    "wof:name":"Hurricane Sweeping Svc",
    "wof:placetype":"venue"
},
  "geometry": {"coordinates":[-80.239914,26.739957],"type":"Point"}
}