{
  "type": "Feature",
  "properties": {
    "addr:full":"380 NW 26th St Miami FL 33127",
    "addr:housenumber":"380",
    "addr:postcode":"33127",
    "addr:street":"Nw 26Th St",
    "iso:country":"US",
    "sg:address":"380 NW 26th St",
    "sg:city":"Miami",
    "sg:classifiers":[
        {
            "category":"Wholesale",
            "subcategory":"Apparel",
            "type":"Manufacturing & Wholesale Goods"
        }
    ],
    "sg:phone":"+1 305 576 1722",
    "sg:postcode":"33127",
    "sg:province":"FL",
    "sg:tags":[
        "rubber",
        "clothing",
        "shoe",
        "footwear"
    ],
    "wof:name":"Sawat Inc",
    "wof:placetype":"venue"
},
  "geometry": {"coordinates":[-80.20190599999999,25.801382],"type":"Point"}
}