{
  "type": "Feature",
  "properties": {
    "iso:country":"US",
    "sg:address":"5700 NW 79th Ave",
    "sg:city":"Doral",
    "sg:classifiers":[
        {
            "category":"Fast Food",
            "type":"Food & Drink"
        },
        {
            "category":"Restaurant",
            "type":"Food & Drink"
        }
    ],
    "sg:phone":"+1 305 599 2660",
    "sg:postcode":"33166",
    "sg:province":"FL",
    "sg:tags":[
        "hamburger",
        "hot",
        "dog",
        "american",
        "take",
        "chicken"
    ],
    "sg:website":"www.mcdonalds.com",
    "wof:name":"McDonald's",
    "wof:placetype":"venue"
},
  "geometry": {"coordinates":[-80.326131,25.825463],"type":"Point"}
}