{
  "type": "Feature",
  "properties": {
    "iso:country":"US",
    "sg:address":"2 Cuillan Cir",
    "sg:city":"Palm Beach Gardens",
    "sg:classifiers":[
        {
            "category":"Professional",
            "type":"Services"
        }
    ],
    "sg:phone":"+1 561 627 2606",
    "sg:postcode":"33418",
    "sg:province":"FL",
    "wof:name":"Ms Networks Inc",
    "wof:placetype":"venue"
},
  "geometry": {"coordinates":[-80.15661299999999,26.837785],"type":"Point"}
}