{
  "type": "Feature",
  "properties": {
    "addr:full":"1074 SE Spinnaker Ave Port Saint Lucie FL 34983",
    "addr:housenumber":"1074",
    "addr:postcode":"34983",
    "addr:street":"Se Spinnaker Ave",
    "iso:country":"US",
    "sg:address":"1074 SE Spinnaker Ave",
    "sg:city":"Port Saint Lucie",
    "sg:classifiers":[
        {
            "category":"Building & Trades",
            "subcategory":"Cleaning & Sanitation",
            "type":"Services"
        }
    ],
    "sg:phone":"+1 772 579 8372",
    "sg:postcode":"34983",
    "sg:province":"FL",
    "sg:tags":[
        "maintenance"
    ],
    "wof:name":"Woodlands Cleaning Service",
    "wof:placetype":"venue"
},
  "geometry": {"coordinates":[-80.322575,27.289283],"type":"Point"}
}