{
  "type": "Feature",
  "properties": {
    "iso:country":"US",
    "sg:address":"413 State Rd 80",
    "sg:city":"Labelle",
    "sg:classifiers":[
        {
            "category":"Shopping",
            "subcategory":"Clothing, Apparel, & Fashions",
            "type":"Retail Goods"
        }
    ],
    "sg:phone":"+1 863 675 1887",
    "sg:postcode":"33935",
    "sg:province":"FL",
    "sg:tags":[
        "shop",
        "bridal"
    ],
    "wof:name":"J & G Bridal",
    "wof:placetype":"venue"
},
  "geometry": {"coordinates":[-81.46430700000001,26.74318],"type":"Point"}
}