{
  "type": "Feature",
  "properties": {
    "iso:country":"US",
    "sg:address":"25379 Busy Bee Dr",
    "sg:city":"Bonita Springs",
    "sg:classifiers":[
        {
            "category":"Building & Trades",
            "subcategory":"Construction",
            "type":"Services"
        }
    ],
    "sg:phone":"+1 239 992 9481",
    "sg:postcode":"34135",
    "sg:province":"FL",
    "sg:tags":[
        "carpentry",
        "contractor"
    ],
    "wof:name":"Joseph M Harlan",
    "wof:placetype":"venue"
},
  "geometry": {"coordinates":[-81.791808,26.373693],"type":"Point"}
}