{
  "type": "Feature",
  "properties": {
    "addr:full":"432 NE 89th St El Portal FL 33138",
    "addr:housenumber":"432",
    "addr:postcode":"33138",
    "addr:street":"Ne 89Th St",
    "iso:country":"US",
    "sg:address":"432 NE 89th St",
    "sg:city":"El Portal",
    "sg:classifiers":[
        {
            "category":"Organizations",
            "subcategory":"Religious Organization",
            "type":"Services"
        }
    ],
    "sg:phone":"+1 305 751 0474",
    "sg:postcode":"33138",
    "sg:province":"FL",
    "sg:tags":[
        "church"
    ],
    "wof:name":"First Russian Ukrain Bapt Ch",
    "wof:placetype":"venue"
},
  "geometry": {"coordinates":[-80.187617,25.856916],"type":"Point"}
}