{
  "type": "Feature",
  "properties": {
    "iso:country":"US",
    "sg:address":"113 S Pine St",
    "sg:city":"Deland",
    "sg:classifiers":[
        {
            "category":"Building & Trades",
            "subcategory":"Landscaping Services",
            "type":"Services"
        },
        {
            "category":"Farming",
            "subcategory":"Nursery",
            "type":"Manufacturing & Wholesale Goods"
        },
        {
            "category":"Wholesale",
            "subcategory":"Construction Materials",
            "type":"Manufacturing & Wholesale Goods"
        }
    ],
    "sg:phone":"+1 386 748 4365",
    "sg:postcode":"32724",
    "sg:province":"FL",
    "sg:tags":[
        "control",
        "lawn",
        "nurseries-plants",
        "tree",
        "contractor",
        "weed",
        "erosion",
        "landscape"
    ],
    "wof:name":"Sun Springs Landscaping & Lawn Maintenance",
    "wof:placetype":"venue"
},
  "geometry": {"coordinates":[-81.28883399999999,29.02668],"type":"Point"}
}