{
  "type": "Feature",
  "properties": {
    "iso:country":"US",
    "sg:address":"6220 S Orange Blossom Trl",
    "sg:city":"Orlando",
    "sg:classifiers":[
        {
            "category":"Building & Trades",
            "subcategory":"Cleaning & Sanitation",
            "type":"Services"
        },
        {
            "category":"Retail",
            "subcategory":"Laundry & Dry Cleaning",
            "type":"Services"
        }
    ],
    "sg:phone":"+1 407 438 4177",
    "sg:postcode":"32809",
    "sg:province":"FL",
    "sg:tags":[
        "cleaner",
        "contractor",
        "cleaning-industrial",
        "house"
    ],
    "wof:name":"Green & Sparkling Clean",
    "wof:placetype":"venue"
},
  "geometry": {"coordinates":[-81.39675,28.467237],"type":"Point"}
}