{
  "type": "Feature",
  "properties": {
    "addr:full":"4532 Commander Dr # 2132 Orlando FL 32822",
    "addr:housenumber":"4532",
    "addr:postcode":"32822",
    "addr:street":"Commander Dr # 2132",
    "iso:country":"US",
    "sg:address":"4532 Commander Dr # 2132",
    "sg:city":"Orlando",
    "sg:classifiers":[
        {
            "category":"Utilities",
            "type":"Services"
        }
    ],
    "sg:phone":"+1 407 466 7827",
    "sg:postcode":"32822",
    "sg:province":"FL",
    "wof:name":"Abby's Cleaning Services",
    "wof:placetype":"venue"
},
  "geometry": {"coordinates":[-81.306196,28.498404],"type":"Point"}
}