{
  "type": "Feature",
  "properties": {
    "iso:country":"US",
    "sg:address":"2613 Shoreline Ave",
    "sg:city":"Panama City",
    "sg:classifiers":[
        {
            "category":"Professional",
            "subcategory":"Business Services",
            "type":"Services"
        }
    ],
    "sg:phone":"+1 850 769 2733",
    "sg:postcode":"32405",
    "sg:province":"FL",
    "sg:tags":[
        "embroidery"
    ],
    "wof:name":"B & S Enterprises",
    "wof:placetype":"venue"
},
  "geometry": {"coordinates":[-85.706717,30.200904],"type":"Point"}
}