{
  "type": "Feature",
  "properties": {
    "addr:full":"30394 Old Dixie Hwy Homestead FL 33033",
    "addr:housenumber":"30394",
    "addr:postcode":"33033",
    "addr:street":"Old Dixie Hwy",
    "iso:country":"US",
    "sg:address":"30394 Old Dixie Hwy",
    "sg:city":"Homestead",
    "sg:classifiers":[
        {
            "category":"Restaurant",
            "type":"Food & Drink"
        }
    ],
    "sg:phone":"+1 305 245 5420",
    "sg:postcode":"33033",
    "sg:province":"FL",
    "sg:tags":[
        "style",
        "family"
    ],
    "wof:name":"Loly's Restaurant",
    "wof:placetype":"venue"
},
  "geometry": {"coordinates":[-80.460993,25.485996],"type":"Point"}
}