{
  "type": "Feature",
  "properties": {
    "addr:full":"6703 W Hwy 98 Panama City Bch FL 32407",
    "addr:housenumber":"6703",
    "addr:postcode":"32407",
    "addr:street":"W Hwy 98",
    "iso:country":"US",
    "sg:address":"6703 W Hwy 98",
    "sg:city":"Panama City Bch",
    "sg:classifiers":[
        {
            "category":"Utilities",
            "subcategory":"Telephone",
            "type":"Services"
        }
    ],
    "sg:phone":"+1 850 236 2500",
    "sg:postcode":"32407",
    "sg:province":"FL",
    "sg:tags":[
        "telecommunication"
    ],
    "wof:name":"A T & T Acus",
    "wof:placetype":"venue"
},
  "geometry": {"coordinates":[-85.75349300000001,30.18824],"type":"Point"}
}