{
  "type": "Feature",
  "properties": {
    "addr:full":"3500 N 34th Ave Hollywood FL 33021",
    "addr:housenumber":"3500",
    "addr:postcode":"33021",
    "addr:street":"N 34Th Ave",
    "iso:country":"US",
    "sg:address":"3500 N 34th Ave",
    "sg:city":"Hollywood",
    "sg:classifiers":[
        {
            "category":"Building & Trades",
            "subcategory":"Construction",
            "type":"Services"
        }
    ],
    "sg:phone":"+1 954 989 3904",
    "sg:postcode":"33021",
    "sg:province":"FL",
    "sg:tags":[
        "speculative",
        "builder"
    ],
    "wof:name":"Lowe Development Inc",
    "wof:placetype":"venue"
},
  "geometry": {"coordinates":[-80.17832799999999,26.043568],"type":"Point"}
}