{
  "type": "Feature",
  "properties": {
    "addr:full":"100 N Atlantic Ave Daytona Beach FL 32118",
    "addr:housenumber":"100",
    "addr:postcode":"32118",
    "addr:street":"N Atlantic Ave",
    "iso:country":"US",
    "sg:address":"100 N Atlantic Ave",
    "sg:city":"Daytona Beach",
    "sg:classifiers":[
        {
            "category":"Travel",
            "subcategory":"Hotels & Motels",
            "type":"Entertainment"
        }
    ],
    "sg:phone":"+1 386 254 8200",
    "sg:postcode":"32118",
    "sg:province":"FL",
    "sg:tags":[
        "operation",
        "eating"
    ],
    "wof:name":"Adams Mark Daytona Bch Resort",
    "wof:placetype":"venue"
},
  "geometry": {"coordinates":[-81.009697,29.229853],"type":"Point"}
}