{
  "type": "Feature",
  "properties": {
    "iso:country":"US",
    "sg:address":"13220 Houston Ave",
    "sg:city":"Port Richey",
    "sg:classifiers":[
        {
            "category":"Professional",
            "subcategory":"Management & Consulting",
            "type":"Services"
        }
    ],
    "sg:phone":"+1 727 863 5226",
    "sg:postcode":"34667",
    "sg:province":"FL",
    "sg:tags":[
        "public",
        "relations"
    ],
    "wof:name":"Sports Promotion Inc",
    "wof:placetype":"venue"
},
  "geometry": {"coordinates":[-82.596424,28.40466],"type":"Point"}
}