{
  "type": "Feature",
  "properties": {
    "addr:full":"7000 SW 62nd Ave South Miami FL 33143",
    "addr:housenumber":"7000",
    "addr:postcode":"33143",
    "addr:street":"Sw 62Nd Ave",
    "iso:country":"US",
    "sg:address":"7000 SW 62nd Ave",
    "sg:city":"South Miami",
    "sg:classifiers":[
        {
            "category":"Health Services",
            "subcategory":"Doctor",
            "type":"Services"
        }
    ],
    "sg:phone":"+1 305 662 1444",
    "sg:postcode":"33143",
    "sg:province":"FL",
    "sg:tags":[
        "podiatrist"
    ],
    "wof:name":"Hanft Jason R DPM Facfas",
    "wof:placetype":"venue"
},
  "geometry": {"coordinates":[-80.29401900000001,25.705412],"type":"Point"}
}