{
  "type": "Feature",
  "properties": {
    "iso:country":"US",
    "sg:address":"1002 Woodward Oak Cir",
    "sg:city":"Eustis",
    "sg:classifiers":[
        {
            "category":"Freight",
            "type":"Transportation"
        }
    ],
    "sg:phone":"+1 352 357 8785",
    "sg:postcode":"32726",
    "sg:province":"FL",
    "sg:tags":[
        "operator",
        "local",
        "trucking"
    ],
    "wof:name":"Dun-Rite Transport",
    "wof:placetype":"venue"
},
  "geometry": {"coordinates":[-81.674384,28.82702],"type":"Point"}
}