{
  "type": "Feature",
  "properties": {
    "iso:country":"US",
    "sg:address":"2050 N Andrews Ave Exd",
    "sg:city":"Pompano Beach",
    "sg:classifiers":[
        {
            "category":"Professional",
            "type":"Services"
        }
    ],
    "sg:phone":"+1 954 970 7030",
    "sg:postcode":"33069",
    "sg:province":"FL",
    "sg:tags":[
        "establishment"
    ],
    "wof:name":"Twin Design",
    "wof:placetype":"venue"
},
  "geometry": {"coordinates":[-80.141705,26.210616],"type":"Point"}
}