{
  "type": "Feature",
  "properties": {
    "iso:country":"US",
    "sg:address":"223 E Flagler St",
    "sg:city":"Miami",
    "sg:classifiers":[
        {
            "category":"Communications",
            "subcategory":"Newspaper",
            "type":"Services"
        }
    ],
    "sg:phone":"+1 954 348 7805",
    "sg:postcode":"33131",
    "sg:province":"FL",
    "sg:tags":[
        "advertising"
    ],
    "sg:website":"levesquedigitalmedia.com",
    "wof:name":"Levesque Digital Media",
    "wof:placetype":"venue"
},
  "geometry": {"coordinates":[-80.189702,25.774275],"type":"Point"}
}