{
  "type": "Feature",
  "properties": {
    "addr:full":"10104 NW 53rd St Fort Lauderdale FL 33351",
    "addr:housenumber":"10104",
    "addr:postcode":"33351",
    "addr:street":"Nw 53Rd St",
    "iso:country":"US",
    "sg:address":"10104 NW 53rd St",
    "sg:city":"Fort Lauderdale",
    "sg:classifiers":[
        {
            "category":"Wholesale",
            "subcategory":"Construction Materials",
            "type":"Manufacturing & Wholesale Goods"
        }
    ],
    "sg:phone":"+1 954 572 0247",
    "sg:postcode":"33351",
    "sg:province":"FL",
    "sg:tags":[
        "hurricane",
        "panel"
    ],
    "wof:name":"Bourvain Enterprises Inc",
    "wof:placetype":"venue"
},
  "geometry": {"coordinates":[-80.285083,26.189351],"type":"Point"}
}