{
  "type": "Feature",
  "properties": {
    "addr:full":"705 W Colonial Dr Orlando FL 32804",
    "addr:housenumber":"705",
    "addr:postcode":"32804",
    "addr:street":"W Colonial Dr",
    "iso:country":"US",
    "sg:address":"705 W Colonial Dr",
    "sg:city":"Orlando",
    "sg:classifiers":[
        {
            "category":"Shopping",
            "subcategory":"Bicycles & Sporting Goods",
            "type":"Retail Goods"
        }
    ],
    "sg:phone":"+1 407 872 3278",
    "sg:postcode":"32804",
    "sg:province":"FL",
    "sg:tags":[
        "shop"
    ],
    "wof:name":"Kings Row",
    "wof:placetype":"venue"
},
  "geometry": {"coordinates":[-81.38883199999999,28.552989],"type":"Point"}
}