{
  "type": "Feature",
  "properties": {
    "addr:full":"2001 SE Bisbee St Port St Lucie FL 34952",
    "addr:housenumber":"2001",
    "addr:postcode":"34952",
    "addr:street":"Se Bisbee St;St",
    "iso:country":"US",
    "sg:address":"2001 SE Bisbee St",
    "sg:city":"Port St Lucie",
    "sg:classifiers":[
        {
            "category":"Building & Trades",
            "subcategory":"Construction",
            "type":"Services"
        }
    ],
    "sg:phone":"+1 772 337 1597",
    "sg:postcode":"34952",
    "sg:province":"FL",
    "sg:tags":[
        "stucco",
        "contractor"
    ],
    "wof:name":"Robert J Leroy Stucco Cutting",
    "wof:placetype":"venue"
},
  "geometry": {"coordinates":[-80.30363,27.27834],"type":"Point"}
}