{
  "type": "Feature",
  "properties": {
    "addr:full":"4000 N State Rd 7 Fort Lauderdale FL 33319",
    "addr:housenumber":"4000",
    "addr:postcode":"33319",
    "addr:street":"N State Rd 7",
    "iso:country":"US",
    "sg:address":"4000 N State Rd 7",
    "sg:city":"Fort Lauderdale",
    "sg:classifiers":[
        {
            "category":"Shopping",
            "subcategory":"Jewelry",
            "type":"Retail Goods"
        }
    ],
    "sg:phone":"+1 954 739 8292",
    "sg:postcode":"33319",
    "sg:province":"FL",
    "sg:tags":[
        "repair"
    ],
    "wof:name":"Modern Time Systems Inc",
    "wof:placetype":"venue"
},
  "geometry": {"coordinates":[-80.203337,26.17424],"type":"Point"}
}