{
  "type": "Feature",
  "properties": {
    "addr:full":"15335 SW 288th St Homestead FL 33033",
    "addr:housenumber":"15335",
    "addr:postcode":"33033",
    "addr:street":"Sw 288Th St",
    "iso:country":"US",
    "sg:address":"15335 SW 288th St",
    "sg:city":"Homestead",
    "sg:classifiers":[
        {
            "category":"Health Services",
            "subcategory":"Doctor",
            "type":"Services"
        }
    ],
    "sg:phone":"+1 305 248 3814",
    "sg:postcode":"33033",
    "sg:province":"FL",
    "sg:tags":[
        "medical"
    ],
    "wof:name":"Barkett M M MD",
    "wof:placetype":"venue"
},
  "geometry": {"coordinates":[-80.439487,25.499481],"type":"Point"}
}