{
  "type": "Feature",
  "properties": {
    "addr:full":"20422 NW 22nd Ct Opa Locka FL 33056",
    "addr:housenumber":"20422",
    "addr:postcode":"33056",
    "addr:street":"Nw 22Nd Ct",
    "iso:country":"US",
    "sg:address":"20422 NW 22nd Ct",
    "sg:city":"Opa Locka",
    "sg:classifiers":[
        {
            "category":"Building & Trades",
            "subcategory":"Landscaping Services",
            "type":"Services"
        }
    ],
    "sg:phone":"+1 305 622 7469",
    "sg:postcode":"33056",
    "sg:province":"FL",
    "wof:name":"Derrick Neil Clarke Lawn Care",
    "wof:placetype":"venue"
},
  "geometry": {"coordinates":[-80.239152,25.964255],"type":"Point"}
}