{
  "type": "Feature",
  "properties": {
    "addr:full":"3128 Obrien Dr Tallahassee FL 32309",
    "addr:housenumber":"3128",
    "addr:postcode":"32309",
    "addr:street":"Obrien Dr",
    "iso:country":"US",
    "sg:address":"3128 Obrien Dr",
    "sg:city":"Tallahassee",
    "sg:classifiers":[
        {
            "category":"Professional",
            "subcategory":"Management & Consulting",
            "type":"Services"
        }
    ],
    "sg:phone":"+1 850 907 0080",
    "sg:postcode":"32309",
    "sg:province":"FL",
    "sg:tags":[
        "consultant",
        "business"
    ],
    "wof:name":"Weiner & Assoc Inc",
    "wof:placetype":"venue"
},
  "geometry": {"coordinates":[-84.20399999999999,30.528128],"type":"Point"}
}