{
  "type": "Feature",
  "properties": {
    "iso:country":"US",
    "sg:address":"8512 Shadow Wood Blvd",
    "sg:city":"Coral Springs",
    "sg:classifiers":[
        {
            "category":"Retail",
            "subcategory":"Repair Shop",
            "type":"Services"
        }
    ],
    "sg:phone":"+1 954 753 9841",
    "sg:postcode":"33071",
    "sg:province":"FL",
    "sg:tags":[
        "typewriter"
    ],
    "wof:name":"Charles O'Brien Office Eqpt",
    "wof:placetype":"venue"
},
  "geometry": {"coordinates":[-80.240077,26.246039],"type":"Point"}
}