{
  "type": "Feature",
  "properties": {
    "iso:country":"US",
    "sg:address":"4712 SW 74th Ave",
    "sg:city":"Miami",
    "sg:classifiers":[
        {
            "category":"Wholesale",
            "subcategory":"Durable Goods & Equipment",
            "type":"Manufacturing & Wholesale Goods"
        }
    ],
    "sg:phone":"+1 305 265 5672",
    "sg:postcode":"33155",
    "sg:province":"FL",
    "sg:tags":[
        "exporter"
    ],
    "wof:name":"Distrivalto USA Inc",
    "wof:placetype":"venue"
},
  "geometry": {"coordinates":[-80.314751,25.726289],"type":"Point"}
}