{
  "type": "Feature",
  "properties": {
    "addr:full":"3111 95th Dr E Parrish FL 34219",
    "addr:housenumber":"3111",
    "addr:postcode":"34219",
    "addr:street":"95Th Dr E",
    "iso:country":"US",
    "sg:address":"3111 95th Dr E",
    "sg:city":"Parrish",
    "sg:classifiers":[
        {
            "category":"Manufacturing",
            "subcategory":"Chemicals & Compounds",
            "type":"Manufacturing & Wholesale Goods"
        }
    ],
    "sg:phone":"+1 941 776 0318",
    "sg:postcode":"34219",
    "sg:province":"FL",
    "sg:tags":[
        "pesticide",
        "mfg"
    ],
    "wof:name":"Pesticide Service Consultant",
    "wof:placetype":"venue"
},
  "geometry": {"coordinates":[-82.46678300000001,27.540747],"type":"Point"}
}