{
  "type": "Feature",
  "properties": {
    "addr:full":"3628 Murrow St New Port Richey FL 34655",
    "addr:housenumber":"3628",
    "addr:postcode":"34655",
    "addr:street":"Murrow St",
    "iso:country":"US",
    "sg:address":"3628 Murrow St",
    "sg:city":"New Port Richey",
    "sg:classifiers":[
        {
            "category":"Building & Trades",
            "subcategory":"Construction",
            "type":"Services"
        }
    ],
    "sg:phone":"+1 727 372 2564",
    "sg:postcode":"34655",
    "sg:province":"FL",
    "sg:tags":[
        "hanging",
        "contractor"
    ],
    "wof:name":"Tim Pressure Washing & Pntg",
    "wof:placetype":"venue"
},
  "geometry": {"coordinates":[-82.685903,28.21284],"type":"Point"}
}