{
  "type": "Feature",
  "properties": {
    "iso:country":"US",
    "sg:address":"2009 E Recreation Dr",
    "sg:city":"Sebring",
    "sg:classifiers":[
        {
            "category":"Professional",
            "subcategory":"Management & Consulting",
            "type":"Services"
        }
    ],
    "sg:phone":"+1 863 386 1005",
    "sg:postcode":"33875",
    "sg:province":"FL",
    "sg:tags":[
        "marketing",
        "program"
    ],
    "wof:name":"Excell Marketing Co",
    "wof:placetype":"venue"
},
  "geometry": {"coordinates":[-81.483289,27.46974],"type":"Point"}
}