{
  "type": "Feature",
  "properties": {
    "iso:country":"US",
    "sg:address":"6436 Ridge Rd",
    "sg:city":"Port Richey",
    "sg:classifiers":[
        {
            "category":"Building & Trades",
            "subcategory":"Equipment Rental",
            "type":"Services"
        }
    ],
    "sg:phone":"+1 727 849 5647",
    "sg:postcode":"34668",
    "sg:province":"FL",
    "sg:tags":[
        "moving",
        "supply"
    ],
    "wof:name":"Jesse's Moving Svc",
    "wof:placetype":"venue"
},
  "geometry": {"coordinates":[-82.70756799999999,28.280538],"type":"Point"}
}