{
  "type": "Feature",
  "properties": {
    "addr:full":"342 Autumn Breeze Way Winter Park FL 32792",
    "addr:housenumber":"342",
    "addr:postcode":"32792",
    "addr:street":"Autumn Breeze Way",
    "iso:country":"US",
    "sg:address":"342 Autumn Breeze Way",
    "sg:city":"Winter Park",
    "sg:classifiers":[
        {
            "category":"Building & Trades",
            "subcategory":"Construction",
            "type":"Services"
        }
    ],
    "sg:phone":"+1 407 657 8801",
    "sg:postcode":"32792",
    "sg:province":"FL",
    "sg:tags":[
        "contractor"
    ],
    "wof:name":"Vogel Bros Building Co",
    "wof:placetype":"venue"
},
  "geometry": {"coordinates":[-81.30580399999999,28.601918],"type":"Point"}
}