{
  "type": "Feature",
  "properties": {
    "addr:full":"4900 N State Rd 7 Tamarac FL 33319",
    "addr:housenumber":"4900",
    "addr:postcode":"33319",
    "addr:street":"N State Rd 7",
    "iso:country":"US",
    "sg:address":"4900 N State Rd 7",
    "sg:city":"Tamarac",
    "sg:classifiers":[
        {
            "category":"Food & Beverages",
            "subcategory":"Bakery",
            "type":"Retail Goods"
        }
    ],
    "sg:phone":"+1 954 730 9008",
    "sg:postcode":"33319",
    "sg:province":"FL",
    "sg:tags":[
        "doughnut"
    ],
    "wof:name":"Dunkin Donuts",
    "wof:placetype":"venue"
},
  "geometry": {"coordinates":[-80.203744,26.186536],"type":"Point"}
}