{
  "type": "Feature",
  "properties": {
    "iso:country":"US",
    "sg:address":"535 N Interlachen Ave",
    "sg:city":"Winter Park",
    "sg:classifiers":[
        {
            "category":"Real Estate",
            "subcategory":"Real Estate Agent",
            "type":"Services"
        }
    ],
    "sg:phone":"+1 407 644 0415",
    "sg:postcode":"32789",
    "sg:province":"FL",
    "wof:name":"Cecil R Cummings",
    "wof:placetype":"venue"
},
  "geometry": {"coordinates":[-81.348767,28.601023],"type":"Point"}
}