{
  "type": "Feature",
  "properties": {
    "addr:full":"3952 3rd St S Jacksonville Beach FL 32250",
    "addr:housenumber":"3952",
    "addr:postcode":"32250",
    "addr:street":"3Rd St S",
    "iso:country":"US",
    "sg:address":"3952 3rd St S",
    "sg:city":"Jacksonville Beach",
    "sg:classifiers":[
        {
            "category":"Restaurant",
            "type":"Food & Drink"
        }
    ],
    "sg:menulink":"http://www.allmenus.com/fl/jacksonville/71202-pizza-hut/menu/",
    "sg:phone":"+1 904 241 2929",
    "sg:postcode":"32250",
    "sg:province":"FL",
    "sg:tags":[
        "american",
        "pizza"
    ],
    "wof:name":"Pizza Hut",
    "wof:placetype":"venue"
},
  "geometry": {"coordinates":[-81.388183,30.256927],"type":"Point"}
}