{
  "type": "Feature",
  "properties": {
    "addr:full":"4526 W State Rd 200 Callahan FL 32011",
    "addr:housenumber":"4526;200",
    "addr:postcode":"32011",
    "addr:street":"W State Rd",
    "iso:country":"US",
    "sg:address":"4526 W State Rd 200",
    "sg:city":"Callahan",
    "sg:classifiers":[
        {
            "category":"Utilities",
            "subcategory":"Refuse",
            "type":"Services"
        }
    ],
    "sg:phone":"+1 904 879 2301",
    "sg:postcode":"32011",
    "sg:province":"FL",
    "sg:tags":[
        "garbage",
        "collection"
    ],
    "sg:website":"www.bfi.com",
    "wof:name":"BFI Inc",
    "wof:placetype":"venue"
},
  "geometry": {"coordinates":[-81.79567900000001,30.587123],"type":"Point"}
}