{
  "type": "Feature",
  "properties": {
    "iso:country":"US",
    "sg:address":"968 E Bradford Ln",
    "sg:city":"Hernando",
    "sg:classifiers":[
        {
            "category":"Retail",
            "subcategory":"Repair Shop",
            "type":"Services"
        }
    ],
    "sg:phone":"+1 352 489 3576",
    "sg:postcode":"34442",
    "sg:province":"FL",
    "sg:tags":[
        "upholsterer"
    ],
    "wof:name":"Phil Regan Enterprises",
    "wof:placetype":"venue"
},
  "geometry": {"coordinates":[-82.420503,28.967523],"type":"Point"}
}