{
  "type": "Feature",
  "properties": {
    "addr:full":"511 Cliff Dr Tampa FL 33617",
    "addr:housenumber":"511",
    "addr:postcode":"33617",
    "addr:street":"Cliff Dr",
    "iso:country":"US",
    "sg:address":"511 Cliff Dr",
    "sg:city":"Tampa",
    "sg:classifiers":[
        {
            "category":"Communications",
            "subcategory":"Film & Video Production",
            "type":"Services"
        }
    ],
    "sg:phone":"+1 813 985 4390",
    "sg:postcode":"33617",
    "sg:province":"FL",
    "sg:tags":[
        "tv",
        "radio",
        "services-commercial",
        "companies-film"
    ],
    "wof:name":"Creative Carbon",
    "wof:placetype":"venue"
},
  "geometry": {"coordinates":[-82.37084400000001,28.045123],"type":"Point"}
}