{
  "type": "Feature",
  "properties": {
    "iso:country":"US",
    "sg:address":"10001 Satellite Blvd",
    "sg:city":"Orlando",
    "sg:classifiers":[
        {
            "category":"Professional",
            "subcategory":"Engineering",
            "type":"Services"
        },
        {
            "category":"Building & Trades",
            "subcategory":"Equipment Rental",
            "type":"Services"
        }
    ],
    "sg:phone":"+1 407 812 6695",
    "sg:postcode":"32837",
    "sg:province":"FL",
    "sg:tags":[
        "system",
        "conditioning-emergency",
        "air conditioning"
    ],
    "wof:name":"Spot Coolers",
    "wof:placetype":"venue"
},
  "geometry": {"coordinates":[-81.401522,28.410136],"type":"Point"}
}