{
  "type": "Feature",
  "properties": {
    "addr:full":"6301 NW 6th Ave Miami FL 33150",
    "addr:housenumber":"6301",
    "addr:postcode":"33150",
    "addr:street":"Nw 6Th Ave",
    "iso:country":"US",
    "sg:address":"6301 NW 6th Ave",
    "sg:city":"Miami",
    "sg:classifiers":[
        {
            "category":"Retail",
            "subcategory":"Event Space",
            "type":"Services"
        }
    ],
    "sg:phone":"+1 786 360 3219",
    "sg:postcode":"33150",
    "sg:province":"FL",
    "sg:tags":[
        "ticket",
        "sale"
    ],
    "wof:name":"Great",
    "wof:placetype":"venue"
},
  "geometry": {"coordinates":[-80.206993,25.83325],"type":"Point"}
}