{
  "type": "Feature",
  "properties": {
    "iso:country":"US",
    "sg:address":"18239 NE 4th Ct",
    "sg:city":"Miami",
    "sg:classifiers":[
        {
            "category":"Personal",
            "type":"Services"
        }
    ],
    "sg:phone":"+1 305 249 2209",
    "sg:postcode":"33162",
    "sg:province":"FL",
    "sg:tags":[
        "mover"
    ],
    "sg:website":"www.abcvanlines.com",
    "wof:name":"AAA Apartment & House Movers 305x249x2209",
    "wof:placetype":"venue"
},
  "geometry": {"coordinates":[-80.192888,25.942565],"type":"Point"}
}