{
  "type": "Feature",
  "properties": {
    "iso:country":"US",
    "sg:address":"4123 W Waters Ave",
    "sg:city":"Tampa",
    "sg:classifiers":[
        {
            "category":"Professional",
            "subcategory":"Detective & Security Services",
            "type":"Services"
        }
    ],
    "sg:phone":"+1 813 495 3521",
    "sg:postcode":"33614",
    "sg:province":"FL",
    "sg:tags":[
        "car",
        "armored",
        "private",
        "investigator"
    ],
    "wof:name":"Diplomatic Security International",
    "wof:placetype":"venue"
},
  "geometry": {"coordinates":[-82.512124,28.025528],"type":"Point"}
}