{
  "type": "Feature",
  "properties": {
    "iso:country":"US",
    "sg:address":"2725 N Hiawassee Rd",
    "sg:city":"Orlando",
    "sg:classifiers":[
        {
            "category":"Shopping",
            "subcategory":"Department Store",
            "type":"Retail Goods"
        }
    ],
    "sg:phone":"+1 407 445 4047",
    "sg:postcode":"32818",
    "sg:province":"FL",
    "sg:tags":[
        "shop"
    ],
    "wof:name":"Price Rite",
    "wof:placetype":"venue"
},
  "geometry": {"coordinates":[-81.475964,28.57957],"type":"Point"}
}