{
  "type": "Feature",
  "properties": {
    "addr:full":"3018 W New Haven Ave West Melbourne FL 32904",
    "addr:housenumber":"3018",
    "addr:postcode":"32904",
    "addr:street":"W New Haven Ave",
    "iso:country":"US",
    "sg:address":"3018 W New Haven Ave",
    "sg:city":"West Melbourne",
    "sg:classifiers":[
        {
            "category":"Health Services",
            "subcategory":"Doctor",
            "type":"Services"
        }
    ],
    "sg:phone":"+1 321 727 0498",
    "sg:postcode":"32904",
    "sg:province":"FL",
    "sg:tags":[
        "dentist"
    ],
    "wof:name":"TMJ Treatment & Research Ctr",
    "wof:placetype":"venue"
},
  "geometry": {"coordinates":[-80.672223,28.078981],"type":"Point"}
}