{
  "type": "Feature",
  "properties": {
    "iso:country":"US",
    "sg:address":"12635 US Hwy 19",
    "sg:city":"Hudson",
    "sg:classifiers":[
        {
            "category":"Autos & Motor Vehicles",
            "subcategory":"Auto Supplies",
            "type":"Retail Goods"
        }
    ],
    "sg:phone":"+1 727 868 7466",
    "sg:postcode":"34667",
    "sg:province":"FL",
    "sg:tags":[
        "equipment",
        "racing",
        "car",
        "automobile"
    ],
    "wof:name":"Bayonet Performance",
    "wof:placetype":"venue"
},
  "geometry": {"coordinates":[-82.69906,28.342616],"type":"Point"}
}