{
  "type": "Feature",
  "properties": {
    "addr:full":"1326 N Dixie Hwy Lake Worth FL 33460",
    "addr:housenumber":"1326",
    "addr:postcode":"33460",
    "addr:street":"N Dixie Hwy",
    "iso:country":"US",
    "sg:address":"1326 N Dixie Hwy",
    "sg:city":"Lake Worth",
    "sg:classifiers":[
        {
            "category":"Professional",
            "subcategory":"Detective & Security Services",
            "type":"Services"
        }
    ],
    "sg:phone":"+1 561 533 0445",
    "sg:postcode":"33460",
    "sg:province":"FL",
    "sg:tags":[
        "car",
        "armored"
    ],
    "wof:name":"Empire Protective Services",
    "wof:placetype":"venue"
},
  "geometry": {"coordinates":[-80.05673299999999,26.63152],"type":"Point"}
}