{
  "type": "Feature",
  "properties": {
    "iso:country":"US",
    "sg:address":"3323 Alice St",
    "sg:city":"Melbourne",
    "sg:classifiers":[
        {
            "category":"Building & Trades",
            "subcategory":"Landscaping Services",
            "type":"Services"
        }
    ],
    "sg:phone":"+1 321 724 1345",
    "sg:postcode":"32904",
    "sg:province":"FL",
    "wof:name":"Fews Lawn Service",
    "wof:placetype":"venue"
},
  "geometry": {"coordinates":[-80.63945699999999,28.070909],"type":"Point"}
}