{
  "type": "Feature",
  "properties": {
    "iso:country":"US",
    "sg:address":"302 7th St S",
    "sg:city":"Dundee",
    "sg:classifiers":[
        {
            "category":"Professional",
            "subcategory":"Accounting & Tax Preparation",
            "type":"Services"
        }
    ],
    "sg:phone":"+1 863 439 3756",
    "sg:postcode":"33838",
    "sg:province":"FL",
    "sg:tags":[
        "bookkeeping",
        "payroll",
        "billing"
    ],
    "wof:name":"Deborah Webb",
    "wof:placetype":"venue"
},
  "geometry": {"coordinates":[-81.612537,28.019301],"type":"Point"}
}