{
  "type": "Feature",
  "properties": {
    "iso:country":"US",
    "sg:address":"305 E Langsner St",
    "sg:city":"Englewood",
    "sg:classifiers":[
        {
            "category":"Building & Trades",
            "subcategory":"Landscaping Services",
            "type":"Services"
        }
    ],
    "sg:phone":"+1 941 650 3987",
    "sg:postcode":"34223",
    "sg:province":"FL",
    "sg:tags":[
        "tree"
    ],
    "wof:name":"Kenneth Method Tree Svc",
    "wof:placetype":"venue"
},
  "geometry": {"coordinates":[-82.346863,26.960179],"type":"Point"}
}