{
  "type": "Feature",
  "properties": {
    "iso:country":"US",
    "sg:address":"2400 NW 78th St",
    "sg:city":"Miami",
    "sg:classifiers":[
        {
            "category":"Retail",
            "subcategory":"Auto Repair",
            "type":"Services"
        }
    ],
    "sg:phone":"+1 305 696 4003",
    "sg:postcode":"33147",
    "sg:province":"FL",
    "sg:tags":[
        "automotive",
        "carburetor"
    ],
    "wof:name":"Discount Carburetors Inc",
    "wof:placetype":"venue"
},
  "geometry": {"coordinates":[-80.239676,25.845463],"type":"Point"}
}