{
  "type": "Feature",
  "properties": {
    "addr:full":"1174 Capital Cir SE Tallahassee FL 32301",
    "addr:housenumber":"1174",
    "addr:postcode":"32301",
    "addr:street":"Capital Cir Se",
    "iso:country":"US",
    "sg:address":"1174 Capital Cir SE",
    "sg:city":"Tallahassee",
    "sg:classifiers":[
        {
            "category":"Professional",
            "type":"Services"
        }
    ],
    "sg:phone":"+1 850 671 3000",
    "sg:postcode":"32301",
    "sg:province":"FL",
    "wof:name":"Patmos Inc of Tallahassee",
    "wof:placetype":"venue"
},
  "geometry": {"coordinates":[-84.226862,30.431276],"type":"Point"}
}