{
  "type": "Feature",
  "properties": {
    "addr:full":"5791 54th Ave N Kenneth City FL 33709",
    "addr:housenumber":"5791",
    "addr:postcode":"33709",
    "addr:street":"54Th Ave N",
    "iso:country":"US",
    "sg:address":"5791 54th Ave N",
    "sg:city":"Kenneth City",
    "sg:classifiers":[
        {
            "category":"Wholesale",
            "subcategory":"Farm Supplies",
            "type":"Manufacturing & Wholesale Goods"
        }
    ],
    "sg:phone":"+1 727 545 2490",
    "sg:postcode":"33709",
    "sg:province":"FL",
    "sg:tags":[
        "control",
        "chemical",
        "pest",
        "equipment"
    ],
    "wof:name":"Do It Yourself Pest Control",
    "wof:placetype":"venue"
},
  "geometry": {"coordinates":[-82.70965,27.821018],"type":"Point"}
}