{
  "type": "Feature",
  "properties": {
    "iso:country":"US",
    "sg:address":"6100 Coral Ridge Dr",
    "sg:city":"Coral Springs",
    "sg:classifiers":[
        {
            "category":"Social Services",
            "subcategory":"Child Care",
            "type":"Services"
        }
    ],
    "sg:phone":"+1 954 796 1177",
    "sg:postcode":"33076",
    "sg:province":"FL",
    "wof:name":"Cambridge School",
    "wof:placetype":"venue"
},
  "geometry": {"coordinates":[-80.27895599999999,26.308243],"type":"Point"}
}