{
  "type": "Feature",
  "properties": {
    "addr:full":"5201 SW 31st Ave Fort Lauderdale FL 33312",
    "addr:housenumber":"5201",
    "addr:postcode":"33312",
    "addr:street":"Sw 31St Ave",
    "iso:country":"US",
    "sg:address":"5201 SW 31st Ave",
    "sg:city":"Fort Lauderdale",
    "sg:classifiers":[
        {
            "category":"Real Estate",
            "subcategory":"Real Estate Operator",
            "type":"Services"
        }
    ],
    "sg:phone":"+1 954 989 2348",
    "sg:postcode":"33312",
    "sg:province":"FL",
    "sg:tags":[
        "building",
        "nonresidential"
    ],
    "wof:name":"Key North Homeowners Assn",
    "wof:placetype":"venue"
},
  "geometry": {"coordinates":[-80.18452000000001,26.055781],"type":"Point"}
}