{
  "type": "Feature",
  "properties": {
    "addr:full":"6610 70th Ave N Pinellas Park FL 33781",
    "addr:housenumber":"6610",
    "addr:postcode":"33781",
    "addr:street":"70Th Ave N",
    "iso:country":"US",
    "sg:address":"6610 70th Ave N",
    "sg:city":"Pinellas Park",
    "sg:classifiers":[
        {
            "category":"Retail",
            "subcategory":"Auto Repair",
            "type":"Services"
        }
    ],
    "sg:phone":"+1 727 541 1415",
    "sg:postcode":"33781",
    "sg:province":"FL",
    "sg:tags":[
        "automotive",
        "general"
    ],
    "wof:name":"Leading Edge Automotive Inc",
    "wof:placetype":"venue"
},
  "geometry": {"coordinates":[-82.729304,27.835452],"type":"Point"}
}