{
  "type": "Feature",
  "properties": {
    "addr:full":"817 W Brevard St Tallahassee FL 32304",
    "addr:housenumber":"817",
    "addr:postcode":"32304",
    "addr:street":"W Brevard St",
    "iso:country":"US",
    "sg:address":"817 W Brevard St",
    "sg:city":"Tallahassee",
    "sg:classifiers":[
        {
            "category":"Personal",
            "subcategory":"Beauty Salon",
            "type":"Services"
        }
    ],
    "sg:phone":"+1 850 224 8522",
    "sg:postcode":"32304",
    "sg:province":"FL",
    "wof:name":"Private Quarters Hair Salon",
    "wof:placetype":"venue"
},
  "geometry": {"coordinates":[-84.296389,30.448998],"type":"Point"}
}