{
  "type": "Feature",
  "properties": {
    "addr:full":"981 N Collier Blvd Marco Island FL 34145",
    "addr:housenumber":"981;collier blvd",
    "addr:postcode":"34145",
    "addr:street":"N",
    "iso:country":"US",
    "sg:address":"981 N Collier Blvd",
    "sg:city":"Marco Island",
    "sg:classifiers":[
        {
            "category":"Personal",
            "subcategory":"Beauty Salon",
            "type":"Services"
        }
    ],
    "sg:phone":"+1 239 394 0163",
    "sg:postcode":"34145",
    "sg:province":"FL",
    "sg:tags":[
        "shop"
    ],
    "wof:name":"Royal Palm Hair Studio Inc",
    "wof:placetype":"venue"
},
  "geometry": {"coordinates":[-81.72218100000001,25.955099],"type":"Point"}
}