{
  "type": "Feature",
  "properties": {
    "iso:country":"US",
    "sg:address":"1749 SW Victor Ln",
    "sg:city":"Port St Lucie",
    "sg:classifiers":[
        {
            "category":"Building & Trades",
            "subcategory":"Pest Control",
            "type":"Services"
        }
    ],
    "sg:phone":"+1 772 344 5647",
    "sg:postcode":"34984",
    "sg:province":"FL",
    "wof:name":"Blake Pest Control Inc",
    "wof:placetype":"venue"
},
  "geometry": {"coordinates":[-80.357415,27.290277],"type":"Point"}
}