{
  "type": "Feature",
  "properties": {
    "addr:full":"270 NE 4th St Miami FL 33132",
    "addr:housenumber":"270",
    "addr:postcode":"33132",
    "addr:street":"Ne 4Th St",
    "iso:country":"US",
    "sg:address":"270 NE 4th St",
    "sg:city":"Miami",
    "sg:classifiers":[
        {
            "category":"Travel",
            "subcategory":"Hotels & Motels",
            "type":"Entertainment"
        }
    ],
    "sg:phone":"+1 305 374 2050",
    "sg:postcode":"33132",
    "sg:province":"FL",
    "sg:website":"www.soundhospitality.com",
    "wof:name":"Sound Hospitality Management",
    "wof:placetype":"venue"
},
  "geometry": {"coordinates":[-80.18879699999999,25.778],"type":"Point"}
}