{
  "type": "Feature",
  "properties": {
    "iso:country":"US",
    "sg:address":"975 6th Ave S",
    "sg:city":"Naples",
    "sg:classifiers":[
        {
            "category":"Professional",
            "subcategory":"Lawyer & Legal Services",
            "type":"Services"
        }
    ],
    "sg:phone":"+1 239 775 8962",
    "sg:postcode":"34102",
    "sg:province":"FL",
    "wof:name":"Kruchten Law Firm",
    "wof:placetype":"venue"
},
  "geometry": {"coordinates":[-81.794281,26.140924],"type":"Point"}
}