{
  "type": "Feature",
  "properties": {
    "iso:country":"US",
    "sg:address":"20200 Old Cutler Rd",
    "sg:city":"Miami",
    "sg:classifiers":[
        {
            "category":"Social Services",
            "subcategory":"Child Care",
            "type":"Services"
        }
    ],
    "sg:phone":"+1 305 252 2104",
    "sg:postcode":"33189",
    "sg:province":"FL",
    "wof:name":"Sun Rise To Midnight Childcare",
    "wof:placetype":"venue"
},
  "geometry": {"coordinates":[-80.334576,25.579212],"type":"Point"}
}