{
  "type": "Feature",
  "properties": {
    "iso:country":"US",
    "sg:address":"108 Robin Rd Ste 2002",
    "sg:city":"Altamonte Springs",
    "sg:classifiers":[
        {
            "category":"Professional",
            "subcategory":"Lawyer & Legal Services",
            "type":"Services"
        }
    ],
    "sg:phone":"+1 407 260 6853",
    "sg:postcode":"32701",
    "sg:province":"FL",
    "wof:name":"Craig A Sonner P.A.",
    "wof:placetype":"venue"
},
  "geometry": {"coordinates":[-81.35440199999999,28.662879],"type":"Point"}
}