{
  "type": "Feature",
  "properties": {
    "iso:country":"US",
    "sg:address":"11530 Tamiami Trl",
    "sg:city":"Naples",
    "sg:classifiers":[
        {
            "category":"Autos & Motor Vehicles",
            "subcategory":"Auto Supplies",
            "type":"Retail Goods"
        }
    ],
    "sg:phone":"+1 239 775 4429",
    "sg:postcode":"34113",
    "sg:province":"FL",
    "sg:tags":[
        "automobile",
        "accessory"
    ],
    "wof:name":"Performance Plus Accessories",
    "wof:placetype":"venue"
},
  "geometry": {"coordinates":[-81.719506,26.076146],"type":"Point"}
}