{
  "type": "Feature",
  "properties": {
    "addr:full":"5574 8th St SW Coral Gables FL 33134",
    "addr:housenumber":"5574",
    "addr:postcode":"33134",
    "addr:street":"8Th St Sw",
    "iso:country":"US",
    "sg:address":"5574 8th St SW",
    "sg:city":"Coral Gables",
    "sg:classifiers":[
        {
            "category":"Home & Garden",
            "subcategory":"Furniture",
            "type":"Retail Goods"
        }
    ],
    "sg:phone":"+1 305 444 3131",
    "sg:postcode":"33134",
    "sg:province":"FL",
    "wof:name":"Mahogany Furniture",
    "wof:placetype":"venue"
},
  "geometry": {"coordinates":[-80.284378,25.76362],"type":"Point"}
}