{
  "type": "Feature",
  "properties": {
    "iso:country":"US",
    "sg:address":"1699 Prideaux Rd",
    "sg:city":"Osteen",
    "sg:classifiers":[
        {
            "category":"Building & Trades",
            "subcategory":"Construction",
            "type":"Services"
        }
    ],
    "sg:phone":"+1 407 323 7460",
    "sg:postcode":"32764",
    "sg:province":"FL",
    "sg:tags":[
        "heavy",
        "excavating",
        "contractor"
    ],
    "wof:name":"C & D Land Clearing",
    "wof:placetype":"venue"
},
  "geometry": {"coordinates":[-81.063169,28.891308],"type":"Point"}
}