{
  "type": "Feature",
  "properties": {
    "addr:full":"5687 McIntosh Rd Sarasota FL 34233",
    "addr:housenumber":"5687",
    "addr:postcode":"34233",
    "addr:street":"Mcintosh Rd",
    "iso:country":"US",
    "sg:address":"5687 McIntosh Rd",
    "sg:city":"Sarasota",
    "sg:classifiers":[
        {
            "category":"Home & Garden",
            "subcategory":"Furniture",
            "type":"Retail Goods"
        }
    ],
    "sg:phone":"+1 941 743 7090",
    "sg:postcode":"34233",
    "sg:province":"FL",
    "wof:name":"Interior Furniture Ltd",
    "wof:placetype":"venue"
},
  "geometry": {"coordinates":[-82.48098400000001,27.27523],"type":"Point"}
}