{
  "type": "Feature",
  "properties": {
    "addr:full":"5332 Jones Ct New Port Richey FL 34652",
    "addr:housenumber":"5332",
    "addr:postcode":"34652",
    "addr:street":"Jones Ct",
    "iso:country":"US",
    "sg:address":"5332 Jones Ct",
    "sg:city":"New Port Richey",
    "sg:classifiers":[
        {
            "category":"Professional",
            "subcategory":"Computer Services",
            "type":"Services"
        }
    ],
    "sg:phone":"+1 727 849 6156",
    "sg:postcode":"34652",
    "sg:province":"FL",
    "sg:tags":[
        "programing",
        "custom"
    ],
    "wof:name":"Sun System Solutions Inc",
    "wof:placetype":"venue"
},
  "geometry": {"coordinates":[-82.742025,28.23636],"type":"Point"}
}