{
  "type": "Feature",
  "properties": {
    "iso:country":"US",
    "sg:address":"2777 Enterprise Rd",
    "sg:city":"Orange City",
    "sg:classifiers":[
        {
            "category":"Health Services",
            "subcategory":"Doctor",
            "type":"Services"
        }
    ],
    "sg:phone":"+1 386 775 3496",
    "sg:postcode":"32763",
    "sg:province":"FL",
    "sg:tags":[
        "orthopedist"
    ],
    "wof:name":"Volusia Hand Surgery Clinic",
    "wof:placetype":"venue"
},
  "geometry": {"coordinates":[-81.28873900000001,28.90561],"type":"Point"}
}