{
  "type": "Feature",
  "properties": {
    "iso:country":"US",
    "sg:address":"12148 S Cleveland Ave",
    "sg:city":"Fort Myers",
    "sg:classifiers":[
        {
            "category":"Restaurant",
            "type":"Food & Drink"
        }
    ],
    "sg:phone":"+1 239 690 3283",
    "sg:postcode":"33901",
    "sg:province":"FL",
    "sg:tags":[
        "barbeque"
    ],
    "sg:website":"www.famousdaves.com",
    "wof:name":"Famous Dave's",
    "wof:placetype":"venue"
},
  "geometry": {"coordinates":[-81.872705,26.564872],"type":"Point"}
}