{
  "type": "Feature",
  "properties": {
    "addr:full":"2670 S McCall Rd Englewood FL 34224",
    "addr:housenumber":"2670",
    "addr:postcode":"34224",
    "addr:street":"S Mccall Rd",
    "iso:country":"US",
    "sg:address":"2670 S McCall Rd",
    "sg:city":"Englewood",
    "sg:classifiers":[
        {
            "category":"Health Services",
            "subcategory":"Clinic",
            "type":"Services"
        }
    ],
    "sg:phone":"+1 941 460 0698",
    "sg:postcode":"34224",
    "sg:province":"FL",
    "sg:tags":[
        "banks",
        "blood",
        "center"
    ],
    "wof:name":"Englewood Community Blood Ctr",
    "wof:placetype":"venue"
},
  "geometry": {"coordinates":[-82.316253,26.934639],"type":"Point"}
}