{
  "type": "Feature",
  "properties": {
    "addr:full":"10401 SW 186th Ave Miami FL 33196",
    "addr:housenumber":"10401",
    "addr:postcode":"33196",
    "addr:street":"Sw 186Th Ave",
    "iso:country":"US",
    "sg:address":"10401 SW 186th Ave",
    "sg:city":"Miami",
    "sg:classifiers":[
        {
            "category":"Manufacturing",
            "subcategory":"Tools & Machinery",
            "type":"Manufacturing & Wholesale Goods"
        },
        {
            "category":"Wholesale",
            "subcategory":"Machinery & Supplies",
            "type":"Manufacturing & Wholesale Goods"
        },
        {
            "category":"Home & Garden",
            "subcategory":"Building Materials",
            "type":"Retail Goods"
        }
    ],
    "sg:phone":"+1 305 235 6844",
    "sg:postcode":"33196",
    "sg:province":"FL",
    "sg:tags":[
        "equipment",
        "fasteners-industrial",
        "industrial"
    ],
    "wof:name":"American Fasteners Corp",
    "wof:placetype":"venue"
},
  "geometry": {"coordinates":[-80.49494900000001,25.66688],"type":"Point"}
}