{
  "type": "Feature",
  "properties": {
    "addr:full":"510 Julia St Jacksonville FL 32202",
    "addr:housenumber":"510",
    "addr:postcode":"32202",
    "addr:street":"Julia St",
    "iso:country":"US",
    "sg:address":"510 Julia St",
    "sg:city":"Jacksonville",
    "sg:classifiers":[
        {
            "category":"Real Estate",
            "subcategory":"Architect",
            "type":"Services"
        }
    ],
    "sg:phone":"+1 904 356 9491",
    "sg:postcode":"32202",
    "sg:province":"FL",
    "sg:website":"www.kbj.org",
    "wof:name":"KBJ Architects Inc",
    "wof:placetype":"venue"
},
  "geometry": {"coordinates":[-81.660613,30.331518],"type":"Point"}
}