{
  "type": "Feature",
  "properties": {
    "addr:full":"5539 8th St SW Miami FL 33134",
    "addr:housenumber":"5539",
    "addr:postcode":"33134",
    "addr:street":"8Th St Sw",
    "iso:country":"US",
    "sg:address":"5539 8th St SW",
    "sg:city":"Miami",
    "sg:classifiers":[
        {
            "category":"Health Services",
            "subcategory":"Doctor",
            "type":"Services"
        }
    ],
    "sg:phone":"+1 305 261 2331",
    "sg:postcode":"33134",
    "sg:province":"FL",
    "sg:tags":[
        "medical"
    ],
    "wof:name":"Fundora Joaquin MD PA",
    "wof:placetype":"venue"
},
  "geometry": {"coordinates":[-80.284988,25.763746],"type":"Point"}
}