{
  "type": "Feature",
  "properties": {
    "addr:full":"106 Commerce St Lake Mary FL 32746",
    "addr:housenumber":"106",
    "addr:postcode":"32746",
    "addr:street":"Commerce St",
    "iso:country":"US",
    "sg:address":"106 Commerce St",
    "sg:city":"Lake Mary",
    "sg:classifiers":[
        {
            "category":"Wholesale",
            "subcategory":"Medical Equipment & Supplies",
            "type":"Manufacturing & Wholesale Goods"
        }
    ],
    "sg:phone":"+1 407 320 9901",
    "sg:postcode":"32746",
    "sg:province":"FL",
    "sg:tags":[
        "surgical"
    ],
    "wof:name":"American Hospital Supply Inc",
    "wof:placetype":"venue"
},
  "geometry": {"coordinates":[-81.363148,28.74016],"type":"Point"}
}