{
  "type": "Feature",
  "properties": {
    "addr:full":"4600 Sheridan St Hollywood FL 33021",
    "addr:housenumber":"4600",
    "addr:postcode":"33021",
    "addr:street":"Sheridan St",
    "iso:country":"US",
    "sg:address":"4600 Sheridan St",
    "sg:city":"Hollywood",
    "sg:classifiers":[
        {
            "category":"Professional",
            "subcategory":"Lawyer & Legal Services",
            "type":"Services"
        }
    ],
    "sg:phone":"+1 954 961 3466",
    "sg:postcode":"33021",
    "sg:province":"FL",
    "sg:tags":[
        "information",
        "attorney",
        "property",
        "personal",
        "automobile",
        "practice",
        "damage",
        "wrongful",
        "death",
        "accident",
        "injury",
        "referral",
        "law"
    ],
    "sg:website":"http://www.realpagessites.com/schiffrinmark",
    "wof:name":"Schiffrin, Mark",
    "wof:placetype":"venue"
},
  "geometry": {"coordinates":[-80.190231,26.032619],"type":"Point"}
}