{
  "type": "Feature",
  "properties": {
    "addr:full":"2800 Fiore Way Delray Beach FL 33445",
    "addr:housenumber":"2800",
    "addr:postcode":"33445",
    "addr:street":"Fiore Way",
    "iso:country":"US",
    "sg:address":"2800 Fiore Way",
    "sg:city":"Delray Beach",
    "sg:classifiers":[
        {
            "category":"Banks & Credit Unions",
            "subcategory":"Bank",
            "type":"Services"
        }
    ],
    "sg:phone":"+1 561 265 0921",
    "sg:postcode":"33445",
    "sg:province":"FL",
    "sg:tags":[
        "loan",
        "real estate"
    ],
    "wof:name":"Nikosoma",
    "wof:placetype":"venue"
},
  "geometry": {"coordinates":[-80.101797,26.447489],"type":"Point"}
}