{
  "type": "Feature",
  "properties": {
    "addr:full":"2608 Coventry Ave Lakeland FL 33803",
    "addr:housenumber":"2608",
    "addr:postcode":"33803",
    "addr:street":"Coventry Ave",
    "iso:country":"US",
    "sg:address":"2608 Coventry Ave",
    "sg:city":"Lakeland",
    "sg:classifiers":[
        {
            "category":"Professional",
            "subcategory":"Management & Consulting",
            "type":"Services"
        }
    ],
    "sg:phone":"+1 863 802 1330",
    "sg:postcode":"33803",
    "sg:province":"FL",
    "sg:tags":[
        "marketing",
        "consultant"
    ],
    "wof:name":"Karen Kovach Co Inc",
    "wof:placetype":"venue"
},
  "geometry": {"coordinates":[-81.948453,28.011394],"type":"Point"}
}