{
  "type": "Feature",
  "properties": {
    "iso:country":"US",
    "sg:address":"9150 NW 87th Ave",
    "sg:city":"Medley",
    "sg:classifiers":[
        {
            "category":"Wholesale",
            "subcategory":"Construction Materials",
            "type":"Manufacturing & Wholesale Goods"
        }
    ],
    "sg:phone":"+1 305 887 3250",
    "sg:postcode":"33178",
    "sg:province":"FL",
    "sg:tags":[
        "mixed",
        "concrete-ready"
    ],
    "wof:name":"Quickcrete Ready Mix Inc",
    "wof:placetype":"venue"
},
  "geometry": {"coordinates":[-80.338624,25.856647],"type":"Point"}
}