{
  "type": "Feature",
  "properties": {
    "iso:country":"US",
    "sg:address":"904 Magnolia Ave",
    "sg:city":"Auburndale",
    "sg:classifiers":[
        {
            "category":"Professional",
            "subcategory":"Computer Services",
            "type":"Services"
        }
    ],
    "sg:phone":"+1 863 967 1912",
    "sg:postcode":"33823",
    "sg:province":"FL",
    "sg:tags":[
        "repair",
        "maintenance",
        "cable",
        "provides"
    ],
    "sg:website":"www.kablelink.com",
    "wof:name":"Kablelink Communications LLC",
    "wof:placetype":"venue"
},
  "geometry": {"coordinates":[-81.792721,28.05897],"type":"Point"}
}