{
  "type": "Feature",
  "properties": {
    "iso:country":"US",
    "sg:address":"11950 NW 12th St",
    "sg:city":"Hollywood",
    "sg:classifiers":[
        {
            "category":"Autos & Motor Vehicles",
            "subcategory":"Fuel & Gas Station",
            "type":"Retail Goods"
        }
    ],
    "sg:phone":"+1 954 431 2924",
    "sg:postcode":"33026",
    "sg:province":"FL",
    "sg:tags":[
        "station",
        "gasoline"
    ],
    "wof:name":"Shell Sensations",
    "wof:placetype":"venue"
},
  "geometry": {"coordinates":[-80.307525,26.01584],"type":"Point"}
}