{
  "type": "Feature",
  "properties": {
    "addr:full":"37508 Laurel Hammock Dr Zephyrhills FL 33541",
    "addr:housenumber":"37508",
    "addr:postcode":"33541",
    "addr:street":"Laurel Hammock Dr",
    "iso:country":"US",
    "sg:address":"37508 Laurel Hammock Dr",
    "sg:city":"Zephyrhills",
    "sg:classifiers":[
        {
            "category":"Shopping",
            "subcategory":"Crafts & Fabrics",
            "type":"Retail Goods"
        },
        {
            "category":"Manufacturing",
            "subcategory":"Pottery",
            "type":"Manufacturing & Wholesale Goods"
        }
    ],
    "sg:phone":"+1 813 782 2738",
    "sg:postcode":"33541",
    "sg:province":"FL",
    "sg:tags":[
        "products-decorative",
        "ceramics-equipment",
        "ceramic",
        "supply"
    ],
    "wof:name":"Delta Slip Inc",
    "wof:placetype":"venue"
},
  "geometry": {"coordinates":[-82.195199,28.263325],"type":"Point"}
}