{
  "type": "Feature",
  "properties": {
    "addr:full":"4095 SE 45th Ct Ocala FL 34480",
    "addr:housenumber":"4095",
    "addr:postcode":"34480",
    "addr:street":"Se 45Th Ct",
    "iso:country":"US",
    "sg:address":"4095 SE 45th Ct",
    "sg:city":"Ocala",
    "sg:classifiers":[
        {
            "category":"Retail",
            "subcategory":"Auto Repair",
            "type":"Services"
        }
    ],
    "sg:phone":"+1 352 694 3044",
    "sg:postcode":"34480",
    "sg:province":"FL",
    "sg:tags":[
        "repairing",
        "automobile"
    ],
    "wof:name":"Dick's Auto Svc",
    "wof:placetype":"venue"
},
  "geometry": {"coordinates":[-82.072098,29.147325],"type":"Point"}
}