{
  "type": "Feature",
  "properties": {
    "addr:full":"15960 Chamberlin Pkwy Fort Myers FL 33913",
    "addr:housenumber":"15960",
    "addr:postcode":"33913",
    "addr:street":"Chamberlin Pkwy",
    "iso:country":"US",
    "sg:address":"15960 Chamberlin Pkwy",
    "sg:city":"Fort Myers",
    "sg:classifiers":[
        {
            "category":"Airport",
            "type":"Transportation"
        }
    ],
    "sg:phone":"+1 239 871 1001",
    "sg:postcode":"33913",
    "sg:province":"FL",
    "wof:name":"Jet Aircraft Mtc Inc",
    "wof:placetype":"venue"
},
  "geometry": {"coordinates":[-81.760971,26.540146],"type":"Point"}
}