{
  "type": "Feature",
  "properties": {
    "iso:country":"US",
    "sg:address":"240 Commercial Blvd",
    "sg:city":"Fort Lauderdale",
    "sg:classifiers":[
        {
            "category":"Banks & Credit Unions",
            "subcategory":"Financial Services",
            "type":"Services"
        }
    ],
    "sg:phone":"+1 954 351 9681",
    "sg:postcode":"33308",
    "sg:province":"FL",
    "sg:tags":[
        "investor"
    ],
    "wof:name":"Geobac Corp",
    "wof:placetype":"venue"
},
  "geometry": {"coordinates":[-80.100971,26.189786],"type":"Point"}
}