{
  "type": "Feature",
  "properties": {
    "iso:country":"US",
    "sg:address":"11428 117th Ave",
    "sg:city":"Largo",
    "sg:classifiers":[
        {
            "category":"Shopping",
            "subcategory":"Computers & Home Electronics",
            "type":"Retail Goods"
        }
    ],
    "sg:phone":"+1 727 210 1478",
    "sg:postcode":"33778",
    "sg:province":"FL",
    "sg:tags":[
        "audio"
    ],
    "wof:name":"Us Audio",
    "wof:placetype":"venue"
},
  "geometry": {"coordinates":[-82.795536,27.879278],"type":"Point"}
}