{
  "type": "Feature",
  "properties": {
    "iso:country":"US",
    "sg:address":"1211 Reynolds Ave",
    "sg:city":"Clearwater",
    "sg:classifiers":[
        {
            "category":"Health Services",
            "subcategory":"Doctor",
            "type":"Services"
        }
    ],
    "sg:phone":"+1 727 466 6564",
    "sg:postcode":"33756",
    "sg:province":"FL",
    "sg:tags":[
        "medical"
    ],
    "wof:name":"Steven J Sheilds MD",
    "wof:placetype":"venue"
},
  "geometry": {"coordinates":[-82.801597,27.952888],"type":"Point"}
}