{
  "type": "Feature",
  "properties": {
    "iso:country":"US",
    "sg:address":"2150 NE 163rd St",
    "sg:city":"North Miami Beach",
    "sg:classifiers":[
        {
            "category":"Autos & Motor Vehicles",
            "subcategory":"Automobile Sales",
            "type":"Retail Goods"
        }
    ],
    "sg:phone":"+1 800 515 2170",
    "sg:postcode":"33162",
    "sg:province":"FL",
    "sg:tags":[
        "car"
    ],
    "wof:name":"Potamkin Honda",
    "wof:placetype":"venue"
},
  "geometry": {"coordinates":[-80.166511,25.925918],"type":"Point"}
}