{
  "type": "Feature",
  "properties": {
    "addr:full":"3728 NW 39th St Lauderdale Lakes FL 33309",
    "addr:housenumber":"3728",
    "addr:postcode":"33309",
    "addr:street":"Nw 39Th St",
    "iso:country":"US",
    "sg:address":"3728 NW 39th St",
    "sg:city":"Lauderdale Lakes",
    "sg:classifiers":[
        {
            "category":"Building & Trades",
            "subcategory":"Cleaning & Sanitation",
            "type":"Services"
        }
    ],
    "sg:phone":"+1 954 966 4474",
    "sg:postcode":"33309",
    "sg:province":"FL",
    "sg:tags":[
        "janitor"
    ],
    "wof:name":"Taly Inc",
    "wof:placetype":"venue"
},
  "geometry": {"coordinates":[-80.19925600000001,26.173782],"type":"Point"}
}