{
  "type": "Feature",
  "properties": {
    "addr:full":"1930 Silver Star Rd Orlando FL 32804",
    "addr:housenumber":"1930",
    "addr:postcode":"32804",
    "addr:street":"Silver Star Rd",
    "iso:country":"US",
    "sg:address":"1930 Silver Star Rd",
    "sg:city":"Orlando",
    "sg:classifiers":[
        {
            "category":"Building & Trades",
            "subcategory":"Construction",
            "type":"Services"
        }
    ],
    "sg:phone":"+1 407 293 4261",
    "sg:postcode":"32804",
    "sg:province":"FL",
    "sg:tags":[
        "paving",
        "contractor"
    ],
    "sg:website":"www.hubbard.com",
    "wof:name":"Orlando Paving Company",
    "wof:placetype":"venue"
},
  "geometry": {"coordinates":[-81.408002,28.578117],"type":"Point"}
}