{
  "type": "Feature",
  "properties": {
    "addr:full":"401 Meade Ave Cocoa Beach FL 32931",
    "addr:housenumber":"401",
    "addr:postcode":"32931",
    "addr:street":"Meade Ave",
    "iso:country":"US",
    "sg:address":"401 Meade Ave",
    "sg:city":"Cocoa Beach",
    "sg:classifiers":[
        {
            "category":"Ice Cream",
            "type":"Food & Drink"
        }
    ],
    "sg:menulink":"http://www.allmenus.com/fl/cocoa-beach-cape-canaveral/165867-rickys-ice-cream-club/menu/",
    "sg:phone":"+1 321 868 2990",
    "sg:postcode":"32931",
    "sg:province":"FL",
    "sg:tags":[
        "american"
    ],
    "wof:name":"Ricky's Ice Cream Club",
    "wof:placetype":"venue"
},
  "geometry": {"coordinates":[-80.603229,28.367692],"type":"Point"}
}