{
  "type": "Feature",
  "properties": {
    "iso:country":"US",
    "sg:address":"22099 Elmira Blvd",
    "sg:city":"Port Charlotte",
    "sg:classifiers":[
        {
            "category":"Health Services",
            "subcategory":"Doctor",
            "type":"Services"
        }
    ],
    "sg:phone":"+1 941 766 0400",
    "sg:postcode":"33952",
    "sg:province":"FL",
    "sg:tags":[
        "gynecology",
        "physician",
        "surgeon",
        "obstetrics"
    ],
    "wof:name":"Ruben Guzman DO",
    "wof:placetype":"venue"
},
  "geometry": {"coordinates":[-82.08686299999999,26.976985],"type":"Point"}
}