{
  "type": "Feature",
  "properties": {
    "iso:country":"US",
    "sg:address":"1001 SW 86th Ct",
    "sg:city":"Miami",
    "sg:classifiers":[
        {
            "category":"Retail",
            "subcategory":"Event Space",
            "type":"Services"
        }
    ],
    "sg:phone":"+1 305 267 0311",
    "sg:postcode":"33144",
    "sg:province":"FL",
    "sg:tags":[
        "banquet",
        "hall",
        "reception",
        "facility"
    ],
    "sg:website":"http://www.bluebanquethallmiami.com",
    "wof:name":"Blue Banquet Hall",
    "wof:placetype":"venue"
},
  "geometry": {"coordinates":[-80.335083,25.760309],"type":"Point"}
}