{
  "type": "Feature",
  "properties": {
    "addr:full":"2633 W State Road 434 Longwood FL 32779",
    "addr:housenumber":"2633",
    "addr:postcode":"32779",
    "addr:street":"W State Road 434",
    "iso:country":"US",
    "sg:address":"2633 W State Road 434",
    "sg:city":"Longwood",
    "sg:classifiers":[
        {
            "category":"Professional",
            "type":"Services"
        }
    ],
    "sg:phone":"+1 407 774 4428",
    "sg:postcode":"32779",
    "sg:province":"FL",
    "sg:tags":[
        "processing",
        "data"
    ],
    "wof:name":"Specialized Computer Services",
    "wof:placetype":"venue"
},
  "geometry": {"coordinates":[-81.410467,28.687732],"type":"Point"}
}