{
  "type": "Feature",
  "properties": {
    "addr:full":"3199 NW 36th St Miami FL 33142",
    "addr:housenumber":"3199",
    "addr:postcode":"33142",
    "addr:street":"Nw 36Th St",
    "iso:country":"US",
    "sg:address":"3199 NW 36th St",
    "sg:city":"Miami",
    "sg:classifiers":[
        {
            "category":"Autos & Motor Vehicles",
            "subcategory":"Automobile Sales",
            "type":"Retail Goods"
        },
        {
            "category":"Retail",
            "subcategory":"Auto Repair",
            "type":"Services"
        }
    ],
    "sg:phone":"+1 305 635 9200",
    "sg:postcode":"33142",
    "sg:province":"FL",
    "sg:tags":[
        "body",
        "shop",
        "car"
    ],
    "wof:name":"Hyundai At Bill Seidle's",
    "wof:placetype":"venue"
},
  "geometry": {"coordinates":[-80.24630000000001,25.808901],"type":"Point"}
}