{
  "type": "Feature",
  "properties": {
    "addr:full":"870 Cypress Pkwy Kissimmee FL 34759",
    "addr:housenumber":"870",
    "addr:postcode":"34759",
    "addr:street":"Cypress Pkwy",
    "iso:country":"US",
    "sg:address":"870 Cypress Pkwy",
    "sg:city":"Kissimmee",
    "sg:classifiers":[
        {
            "category":"Home & Garden",
            "subcategory":"Hardware",
            "type":"Retail Goods"
        }
    ],
    "sg:phone":"+1 407 847 6640",
    "sg:postcode":"34759",
    "sg:province":"FL",
    "wof:name":"Poinciana Do It Best Hardware",
    "wof:placetype":"venue"
},
  "geometry": {"coordinates":[-81.45151,28.14631],"type":"Point"}
}