{
  "type": "Feature",
  "properties": {
    "addr:full":"8257 Normandy Blvd Jacksonville FL 32221",
    "addr:housenumber":"8257",
    "addr:postcode":"32221",
    "addr:street":"Normandy Blvd",
    "iso:country":"US",
    "sg:address":"8257 Normandy Blvd",
    "sg:city":"Jacksonville",
    "sg:classifiers":[
        {
            "category":"Professional",
            "type":"Services"
        },
        {
            "category":"Restaurant",
            "type":"Food & Drink"
        },
        {
            "category":"Fast Food",
            "type":"Food & Drink"
        }
    ],
    "sg:phone":"+1 904 781 5656",
    "sg:postcode":"32221",
    "sg:province":"FL",
    "sg:tags":[
        "delivery",
        "take",
        "pizza"
    ],
    "sg:website":"http://www.hungryhowies.com",
    "wof:name":"Hungry Howie's Pizza",
    "wof:placetype":"venue"
},
  "geometry": {"coordinates":[-81.786772,30.29073],"type":"Point"}
}