{
  "type": "Feature",
  "properties": {
    "iso:country":"US",
    "sg:address":"655 W Flagler St",
    "sg:city":"Miami",
    "sg:classifiers":[
        {
            "category":"Retail",
            "subcategory":"Portrait Studio",
            "type":"Services"
        }
    ],
    "sg:phone":"+1 305 631 0404",
    "sg:postcode":"33130",
    "sg:province":"FL",
    "sg:tags":[
        "photo"
    ],
    "wof:name":"Fenix Photo Center Services",
    "wof:placetype":"venue"
},
  "geometry": {"coordinates":[-80.20523,25.773881],"type":"Point"}
}