{
  "type": "Feature",
  "properties": {
    "addr:full":"1801 Co Rd 19A Eustis FL 32726",
    "addr:housenumber":"1801;19a",
    "addr:postcode":"32726",
    "addr:street":"Co Rd",
    "iso:country":"US",
    "sg:address":"1801 Co Rd 19A",
    "sg:city":"Eustis",
    "sg:classifiers":[
        {
            "category":"Real Estate",
            "subcategory":"Real Estate Operator",
            "type":"Services"
        }
    ],
    "sg:phone":"+1 352 357 2600",
    "sg:postcode":"32726",
    "sg:province":"FL",
    "sg:tags":[
        "building",
        "apartment"
    ],
    "wof:name":"Rosemont Manor",
    "wof:placetype":"venue"
},
  "geometry": {"coordinates":[-81.691931,28.868363],"type":"Point"}
}