{
  "type": "Feature",
  "properties": {
    "iso:country":"US",
    "sg:address":"1858 University Pkwy",
    "sg:city":"Sarasota",
    "sg:classifiers":[
        {
            "category":"Wholesale",
            "subcategory":"Non-durable Goods",
            "type":"Manufacturing & Wholesale Goods"
        }
    ],
    "sg:phone":"+1 941 359 3336",
    "sg:postcode":"34243",
    "sg:province":"FL",
    "sg:tags":[
        "business"
    ],
    "wof:name":"Waters Cleaning Co Inc",
    "wof:placetype":"venue"
},
  "geometry": {"coordinates":[-82.531915,27.388741],"type":"Point"}
}