{
  "type": "Feature",
  "properties": {
    "addr:full":"8130 N Jog Rd West Palm Beach FL 33412",
    "addr:housenumber":"8130",
    "addr:postcode":"33412",
    "addr:street":"N Jog Rd",
    "iso:country":"US",
    "sg:address":"8130 N Jog Rd",
    "sg:city":"West Palm Beach",
    "sg:classifiers":[
        {
            "category":"Government",
            "subcategory":"Police Station",
            "type":"Public Place"
        }
    ],
    "sg:phone":"+1 561 776 2000",
    "sg:postcode":"33412",
    "sg:province":"FL",
    "sg:tags":[
        "sheriff"
    ],
    "sg:website":"www.pbso.org",
    "wof:name":"Palm Beach Cnty Sheriff Dept",
    "wof:placetype":"venue"
},
  "geometry": {"coordinates":[-80.13736900000001,26.798804],"type":"Point"}
}