{
  "type": "Feature",
  "properties": {
    "addr:full":"3075 NW 107th Ave Miami FL 33172",
    "addr:housenumber":"3075",
    "addr:postcode":"33172",
    "addr:street":"Nw 107Th Ave",
    "iso:country":"US",
    "sg:address":"3075 NW 107th Ave",
    "sg:city":"Miami",
    "sg:classifiers":[
        {
            "category":"Health Services",
            "subcategory":"Doctor",
            "type":"Services"
        }
    ],
    "sg:phone":"+1 305 592 1644",
    "sg:postcode":"33172",
    "sg:province":"FL",
    "sg:tags":[
        "medical",
        "center"
    ],
    "wof:name":"Belo Medical Center and Whsng",
    "wof:placetype":"venue"
},
  "geometry": {"coordinates":[-80.369182,25.80215],"type":"Point"}
}