{
  "type": "Feature",
  "properties": {
    "iso:country":"US",
    "sg:address":"1475 N Tamiami Trl",
    "sg:city":"Fort Myers",
    "sg:classifiers":[
        {
            "category":"Bars & Pubs",
            "type":"Food & Drink"
        }
    ],
    "sg:phone":"+1 239 574 8196",
    "sg:postcode":"33903",
    "sg:province":"FL",
    "sg:tags":[
        "drinking"
    ],
    "wof:name":"Jealous Rebel Inc",
    "wof:placetype":"venue"
},
  "geometry": {"coordinates":[-81.882786,26.671062],"type":"Point"}
}