{
  "type": "Feature",
  "properties": {
    "iso:country":"US",
    "sg:address":"1835 Nestle Dr",
    "sg:city":"Pensacola",
    "sg:classifiers":[
        {
            "category":"Professional",
            "subcategory":"Management & Consulting",
            "type":"Services"
        }
    ],
    "sg:phone":"+1 850 494 0910",
    "sg:postcode":"32534",
    "sg:province":"FL",
    "sg:tags":[
        "business"
    ],
    "wof:name":"Bem Systems Inc",
    "wof:placetype":"venue"
},
  "geometry": {"coordinates":[-87.29942200000001,30.521566],"type":"Point"}
}