{
  "type": "Feature",
  "properties": {
    "iso:country":"US",
    "sg:address":"2221 Lee Rd",
    "sg:city":"Winter Park",
    "sg:classifiers":[
        {
            "category":"Professional",
            "subcategory":"Accounting & Tax Preparation",
            "type":"Services"
        }
    ],
    "sg:phone":"+1 407 599 1214",
    "sg:postcode":"32789",
    "sg:province":"FL",
    "sg:tags":[
        "accountant"
    ],
    "wof:name":"J Douglas Eason",
    "wof:placetype":"venue"
},
  "geometry": {"coordinates":[-81.379608,28.605935],"type":"Point"}
}