{
  "type": "Feature",
  "properties": {
    "iso:country":"US",
    "sg:address":"914 E Orange Ave",
    "sg:city":"Eustis",
    "sg:classifiers":[
        {
            "category":"Building & Trades",
            "subcategory":"Landscaping Services",
            "type":"Services"
        }
    ],
    "sg:phone":"+1 352 357 8836",
    "sg:postcode":"32726",
    "sg:province":"FL",
    "wof:name":"Tonys TLC Lawn Care",
    "wof:placetype":"venue"
},
  "geometry": {"coordinates":[-81.676146,28.852743],"type":"Point"}
}