{
  "type": "Feature",
  "properties": {
    "addr:full":"196 NW 69th Ter Pompano Beach FL 33063",
    "addr:housenumber":"196",
    "addr:postcode":"33063",
    "addr:street":"Nw 69Th Ter",
    "iso:country":"US",
    "sg:address":"196 NW 69th Ter",
    "sg:city":"Pompano Beach",
    "sg:classifiers":[
        {
            "category":"Building & Trades",
            "subcategory":"Construction",
            "type":"Services"
        }
    ],
    "sg:phone":"+1 954 818 7453",
    "sg:postcode":"33063",
    "sg:province":"FL",
    "sg:tags":[
        "contracting"
    ],
    "wof:name":"Gannons General Contracting",
    "wof:placetype":"venue"
},
  "geometry": {"coordinates":[-80.217972,26.233369],"type":"Point"}
}