{
  "type": "Feature",
  "properties": {
    "iso:country":"US",
    "sg:address":"12401 SW 134th Court #15",
    "sg:city":"Miami",
    "sg:classifiers":[
        {
            "category":"Home & Garden",
            "subcategory":"Home Furnishings",
            "type":"Retail Goods"
        },
        {
            "category":"Manufacturing",
            "subcategory":"Glass & Minerals",
            "type":"Manufacturing & Wholesale Goods"
        },
        {
            "category":"Manufacturing",
            "subcategory":"Building Materials",
            "type":"Manufacturing & Wholesale Goods"
        },
        {
            "category":"Building & Trades",
            "subcategory":"Construction",
            "type":"Services"
        }
    ],
    "sg:phone":"+1 786 242 9371",
    "sg:postcode":"33186",
    "sg:province":"FL",
    "sg:tags":[
        "plate",
        "glazier",
        "window",
        "glass-auto",
        "board",
        "mirror"
    ],
    "sg:website":"http://perfectionglassandmirror.net",
    "wof:name":"Perfection Glass And Mirror",
    "wof:placetype":"venue"
},
  "geometry": {"coordinates":[-80.41239899999999,25.652361],"type":"Point"}
}