{
  "type": "Feature",
  "properties": {
    "addr:full":"106 Gumbo Limbo Rd Islamorada FL 33036",
    "addr:housenumber":"106",
    "addr:postcode":"33036",
    "addr:street":"Gumbo Limbo Rd",
    "iso:country":"US",
    "sg:address":"106 Gumbo Limbo Rd",
    "sg:city":"Islamorada",
    "sg:classifiers":[
        {
            "category":"Real Estate",
            "subcategory":"Real Estate Services",
            "type":"Services"
        },
        {
            "category":"Real Estate",
            "subcategory":"Real Estate Agent",
            "type":"Services"
        }
    ],
    "sg:phone":"+1 305 852 8610",
    "sg:postcode":"33036",
    "sg:province":"FL",
    "sg:tags":[
        "buyer",
        "broker"
    ],
    "wof:name":"Carroll Walsh Realtor",
    "wof:placetype":"venue"
},
  "geometry": {"coordinates":[-80.56418499999999,24.964998],"type":"Point"}
}