{
  "type": "Feature",
  "properties": {
    "iso:country":"US",
    "sg:address":"18960 NW 63rd Court Cir",
    "sg:city":"Hialeah",
    "sg:classifiers":[
        {
            "category":"Home & Garden",
            "subcategory":"Furniture",
            "type":"Retail Goods"
        },
        {
            "category":"Wholesale",
            "subcategory":"Home Furnishings",
            "type":"Manufacturing & Wholesale Goods"
        }
    ],
    "sg:phone":"+1 305 628 1037",
    "sg:postcode":"33015",
    "sg:province":"FL",
    "sg:tags":[
        "equipment-wholesale",
        "kitchen",
        "equipment-household",
        "manufacturer",
        "cabinet"
    ],
    "wof:name":"Gf Cabintery Inc",
    "wof:placetype":"venue"
},
  "geometry": {"coordinates":[-80.303686,25.945312],"type":"Point"}
}