{
  "type": "Feature",
  "properties": {
    "iso:country":"US",
    "sg:address":"1264 W 40th St",
    "sg:city":"Hialeah",
    "sg:classifiers":[
        {
            "category":"Retail",
            "subcategory":"Car Wash",
            "type":"Services"
        }
    ],
    "sg:phone":"+1 305 558 1591",
    "sg:postcode":"33012",
    "sg:province":"FL",
    "wof:name":"Sunnyside Car Wash",
    "wof:placetype":"venue"
},
  "geometry": {"coordinates":[-80.308863,25.858046],"type":"Point"}
}