{
  "type": "Feature",
  "properties": {
    "iso:country":"US",
    "sg:address":"1541 N Nova Rd",
    "sg:city":"Holly Hill",
    "sg:classifiers":[
        {
            "category":"Professional",
            "type":"Services"
        }
    ],
    "sg:phone":"+1 386 253 3080",
    "sg:postcode":"32117",
    "sg:province":"FL",
    "sg:tags":[
        "establishment"
    ],
    "wof:name":"Cardtronics",
    "wof:placetype":"venue"
},
  "geometry": {"coordinates":[-81.056915,29.237459],"type":"Point"}
}