{
  "type": "Feature",
  "properties": {
    "addr:full":"1253 Woodlawn Ter Clearwater FL 33755",
    "addr:housenumber":"1253",
    "addr:postcode":"33755",
    "addr:street":"Woodlawn Ter",
    "iso:country":"US",
    "sg:address":"1253 Woodlawn Ter",
    "sg:city":"Clearwater",
    "sg:classifiers":[
        {
            "category":"Building & Trades",
            "subcategory":"Construction",
            "type":"Services"
        }
    ],
    "sg:phone":"+1 727 443 3873",
    "sg:postcode":"33755",
    "sg:province":"FL",
    "sg:tags":[
        "residential"
    ],
    "wof:name":"J & ME Services",
    "wof:placetype":"venue"
},
  "geometry": {"coordinates":[-82.786244,27.994253],"type":"Point"}
}