{
  "type": "Feature",
  "properties": {
    "addr:full":"1335 Dew Bloom Rd Valrico FL 33594",
    "addr:housenumber":"1335",
    "addr:postcode":"33594",
    "addr:street":"Dew Bloom Rd",
    "iso:country":"US",
    "sg:address":"1335 Dew Bloom Rd",
    "sg:city":"Valrico",
    "sg:classifiers":[
        {
            "category":"Travel",
            "subcategory":"Travel Agent",
            "type":"Entertainment"
        }
    ],
    "sg:phone":"+1 813 598 1879",
    "sg:postcode":"33594",
    "sg:province":"FL",
    "sg:tags":[
        "agency",
        "services-commercial"
    ],
    "wof:name":"Ytb Travel",
    "wof:placetype":"venue"
},
  "geometry": {"coordinates":[-82.261403,27.930293],"type":"Point"}
}