{
  "type": "Feature",
  "properties": {
    "iso:country":"US",
    "sg:address":"31 Cavallini Dr",
    "sg:city":"Nokomis",
    "sg:classifiers":[
        {
            "category":"Health Services",
            "subcategory":"Clinic",
            "type":"Services"
        }
    ],
    "sg:phone":"+1 941 445 4701",
    "sg:postcode":"34275",
    "sg:province":"FL",
    "sg:tags":[
        "welfare"
    ],
    "wof:name":"Wellness Purpose And Abundance",
    "wof:placetype":"venue"
},
  "geometry": {"coordinates":[-82.466075,27.14935],"type":"Point"}
}