{
  "type": "Feature",
  "properties": {
    "addr:full":"107 W 23rd St Panama City FL 32405",
    "addr:housenumber":"107",
    "addr:postcode":"32405",
    "addr:street":"W 23Rd St",
    "iso:country":"US",
    "sg:address":"107 W 23rd St",
    "sg:city":"Panama City",
    "sg:classifiers":[
        {
            "category":"Insurance",
            "subcategory":"Title Insurance",
            "type":"Services"
        }
    ],
    "sg:phone":"+1 850 522 3000",
    "sg:postcode":"32405",
    "sg:province":"FL",
    "wof:name":"Lanco Title & Escrow",
    "wof:placetype":"venue"
},
  "geometry": {"coordinates":[-85.660554,30.189545],"type":"Point"}
}