{
  "type": "Feature",
  "properties": {
    "addr:full":"9207 Little Rd New Port Richey FL 34654",
    "addr:housenumber":"9207",
    "addr:postcode":"34654",
    "addr:street":"Little Rd",
    "iso:country":"US",
    "sg:address":"9207 Little Rd",
    "sg:city":"New Port Richey",
    "sg:classifiers":[
        {
            "category":"Home & Garden",
            "subcategory":"Hardware",
            "type":"Retail Goods"
        }
    ],
    "sg:phone":"+1 727 868 0222",
    "sg:postcode":"34654",
    "sg:province":"FL",
    "wof:name":"Vision Ace Hardware",
    "wof:placetype":"venue"
},
  "geometry": {"coordinates":[-82.67572699999999,28.291653],"type":"Point"}
}