{
  "type": "Feature",
  "properties": {
    "addr:full":"6 Office Park Dr Palm Coast FL 32137",
    "addr:postcode":"32137",
    "addr:street":"Park Dr",
    "iso:country":"US",
    "sg:address":"6 Office Park Dr",
    "sg:city":"Palm Coast",
    "sg:classifiers":[
        {
            "category":"Real Estate",
            "subcategory":"Real Estate Operator",
            "type":"Services"
        }
    ],
    "sg:phone":"+1 386 447 6615",
    "sg:postcode":"32137",
    "sg:province":"FL",
    "sg:tags":[
        "building",
        "medical",
        "nonresidential"
    ],
    "wof:name":"Medical Building Associates",
    "wof:placetype":"venue"
},
  "geometry": {"coordinates":[-81.20327,29.55997],"type":"Point"}
}