{
  "type": "Feature",
  "properties": {
    "iso:country":"US",
    "sg:address":"1100 E North Blvd",
    "sg:city":"Leesburg",
    "sg:classifiers":[
        {
            "category":"Insurance",
            "subcategory":"Insurance Agent",
            "type":"Services"
        },
        {
            "category":"Insurance",
            "subcategory":"Hazard Insurance",
            "type":"Services"
        },
        {
            "category":"Insurance",
            "subcategory":"Title Insurance",
            "type":"Services"
        },
        {
            "category":"Insurance",
            "subcategory":"Life Insurance",
            "type":"Services"
        }
    ],
    "sg:phone":"+1 352 787 3320",
    "sg:postcode":"34748",
    "sg:province":"FL",
    "sg:tags":[
        "business",
        "auto",
        "commercial",
        "homeowner",
        "motorcycle",
        "renter"
    ],
    "wof:name":"Allstate Insurance Company - Victor Puig",
    "wof:placetype":"venue"
},
  "geometry": {"coordinates":[-81.860542,28.813347],"type":"Point"}
}