{
  "type": "Feature",
  "properties": {
    "addr:full":"20765 Walnut St Dunnellon FL 34431",
    "addr:housenumber":"20765",
    "addr:postcode":"34431",
    "addr:street":"Walnut St",
    "iso:country":"US",
    "sg:address":"20765 Walnut St",
    "sg:city":"Dunnellon",
    "sg:classifiers":[
        {
            "category":"Building & Trades",
            "subcategory":"Electrical",
            "type":"Services"
        },
        {
            "category":"Wholesale",
            "subcategory":"Electrical",
            "type":"Manufacturing & Wholesale Goods"
        }
    ],
    "sg:phone":"+1 352 465 3352",
    "sg:postcode":"34431",
    "sg:province":"FL",
    "sg:tags":[
        "installation"
    ],
    "wof:name":"Shyam Baldeo Installation Svc",
    "wof:placetype":"venue"
},
  "geometry": {"coordinates":[-82.464356,29.050412],"type":"Point"}
}