{
  "type": "Feature",
  "properties": {
    "iso:country":"US",
    "sg:address":"767 W Lancaster Rd",
    "sg:city":"Orlando",
    "sg:classifiers":[
        {
            "category":"Retail",
            "subcategory":"Laundry & Dry Cleaning",
            "type":"Services"
        }
    ],
    "sg:phone":"+1 407 855 4410",
    "sg:postcode":"32809",
    "sg:province":"FL",
    "sg:tags":[
        "cleaner",
        "operated",
        "dryer",
        "laundries-self",
        "washer",
        "coin"
    ],
    "wof:name":"Ambassador Coin Laundry",
    "wof:placetype":"venue"
},
  "geometry": {"coordinates":[-81.387199,28.465361],"type":"Point"}
}