{
  "type": "Feature",
  "properties": {
    "addr:full":"607 S Market Ave Fort Pierce FL 34982",
    "addr:housenumber":"607",
    "addr:postcode":"34982",
    "addr:street":"S Market Ave",
    "iso:country":"US",
    "sg:address":"607 S Market Ave",
    "sg:city":"Fort Pierce",
    "sg:classifiers":[
        {
            "category":"Building & Trades",
            "subcategory":"Construction",
            "type":"Services"
        },
        {
            "category":"Home & Garden",
            "subcategory":"Home Furnishings",
            "type":"Retail Goods"
        }
    ],
    "sg:phone":"+1 772 460 0717",
    "sg:postcode":"34982",
    "sg:province":"FL",
    "sg:tags":[
        "venetian",
        "blind",
        "business",
        "contractor"
    ],
    "wof:name":"Exquisite Designs",
    "wof:placetype":"venue"
},
  "geometry": {"coordinates":[-80.330348,27.392419],"type":"Point"}
}