{
  "type": "Feature",
  "properties": {
    "addr:full":"1845 SE 3rd Ct Crystal River FL 34429",
    "addr:housenumber":"1845",
    "addr:postcode":"34429",
    "addr:street":"Se 3Rd Ct",
    "iso:country":"US",
    "sg:address":"1845 SE 3rd Ct",
    "sg:city":"Crystal River",
    "sg:classifiers":[
        {
            "category":"Building & Trades",
            "subcategory":"Construction",
            "type":"Services"
        }
    ],
    "sg:phone":"+1 352 795 5836",
    "sg:postcode":"34429",
    "sg:province":"FL",
    "sg:tags":[
        "concrete",
        "contractor"
    ],
    "wof:name":"Cart Path Concepts Inc",
    "wof:placetype":"venue"
},
  "geometry": {"coordinates":[-82.588219,28.8824],"type":"Point"}
}