{
  "type": "Feature",
  "properties": {
    "addr:full":"1550 Madruga Ave Coral Gables FL 33146",
    "addr:housenumber":"1550",
    "addr:postcode":"33146",
    "addr:street":"Madruga Ave",
    "iso:country":"US",
    "sg:address":"1550 Madruga Ave",
    "sg:city":"Coral Gables",
    "sg:classifiers":[
        {
            "category":"Shopping",
            "type":"Retail Goods"
        }
    ],
    "sg:phone":"+1 305 665 3167",
    "sg:postcode":"33146",
    "sg:province":"FL",
    "sg:tags":[
        "art",
        "gallery",
        "dealer"
    ],
    "wof:name":"Jma Art Design & Creativity",
    "wof:placetype":"venue"
},
  "geometry": {"coordinates":[-80.2837,25.707812],"type":"Point"}
}