{
  "type": "Feature",
  "properties": {
    "iso:country":"US",
    "sg:address":"7998 Royal Birkdale Cir",
    "sg:city":"Bradenton",
    "sg:classifiers":[
        {
            "category":"Professional",
            "subcategory":"Management & Consulting",
            "type":"Services"
        }
    ],
    "sg:phone":"+1 941 907 4146",
    "sg:postcode":"34202",
    "sg:province":"FL",
    "wof:name":"Rice Assoc Inc",
    "wof:placetype":"venue"
},
  "geometry": {"coordinates":[-82.418463,27.397832],"type":"Point"}
}