{
  "type": "Feature",
  "properties": {
    "iso:country":"US",
    "sg:address":"451 Richard Rd",
    "sg:city":"Rockledge",
    "sg:classifiers":[
        {
            "category":"Autos & Motor Vehicles",
            "subcategory":"Auto Supplies",
            "type":"Retail Goods"
        }
    ],
    "sg:phone":"+1 321 433 1255",
    "sg:postcode":"32955",
    "sg:province":"FL",
    "wof:name":"Central Florida Off Road",
    "wof:placetype":"venue"
},
  "geometry": {"coordinates":[-80.73482300000001,28.325392],"type":"Point"}
}