{
  "type": "Feature",
  "properties": {
    "iso:country":"US",
    "sg:address":"5785 Devonshire Blvd",
    "sg:city":"Miami",
    "sg:classifiers":[
        {
            "category":"Home & Garden",
            "subcategory":"Building Materials",
            "type":"Retail Goods"
        }
    ],
    "sg:phone":"+1 305 663 8718",
    "sg:postcode":"33155",
    "sg:province":"FL",
    "wof:name":"Miami Building Materials",
    "wof:placetype":"venue"
},
  "geometry": {"coordinates":[-80.288636,25.743995],"type":"Point"}
}