{
  "type": "Feature",
  "properties": {
    "iso:country":"US",
    "sg:address":"11 SW 59th Ave",
    "sg:city":"Miami",
    "sg:classifiers":[
        {
            "category":"Building & Trades",
            "subcategory":"Locksmith",
            "type":"Services"
        }
    ],
    "sg:phone":"+1 305 434 7245",
    "sg:postcode":"33144",
    "sg:province":"FL",
    "sg:tags":[
        "locksmiths-commercial",
        "industrial",
        "key",
        "lock"
    ],
    "wof:name":"Master Locksmith Inc",
    "wof:placetype":"venue"
},
  "geometry": {"coordinates":[-80.291528,25.770651],"type":"Point"}
}