{
  "type": "Feature",
  "properties": {
    "iso:country":"US",
    "sg:address":"926 W 18th St",
    "sg:city":"Jacksonville",
    "sg:classifiers":[
        {
            "category":"Professional",
            "type":"Services"
        }
    ],
    "sg:phone":"+1 904 359 0016",
    "sg:postcode":"32209",
    "sg:province":"FL",
    "sg:tags":[
        "establishment"
    ],
    "wof:name":"C P's",
    "wof:placetype":"venue"
},
  "geometry": {"coordinates":[-81.66794400000001,30.354681],"type":"Point"}
}