{
  "type": "Feature",
  "properties": {
    "iso:country":"US",
    "sg:address":"1139 Grand Ave",
    "sg:city":"Sebring",
    "sg:classifiers":[
        {
            "category":"Manufacturing",
            "subcategory":"Apparel",
            "type":"Manufacturing & Wholesale Goods"
        }
    ],
    "sg:phone":"+1 863 402 0555",
    "sg:postcode":"33870",
    "sg:province":"FL",
    "sg:tags":[
        "sewing",
        "contractor"
    ],
    "wof:name":"Jessica's Sewing & Repair",
    "wof:placetype":"venue"
},
  "geometry": {"coordinates":[-81.430284,27.502551],"type":"Point"}
}