{
  "type": "Feature",
  "properties": {
    "iso:country":"US",
    "sg:address":"4463 Lafayette St",
    "sg:city":"Marianna",
    "sg:classifiers":[
        {
            "category":"Autos & Motor Vehicles",
            "subcategory":"Auto Supplies",
            "type":"Retail Goods"
        },
        {
            "category":"Wholesale",
            "subcategory":"Auto Parts",
            "type":"Manufacturing & Wholesale Goods"
        }
    ],
    "sg:phone":"+1 850 482 7026",
    "sg:postcode":"32446",
    "sg:province":"FL",
    "sg:tags":[
        "automotive",
        "automobile"
    ],
    "wof:name":"Auto Electric Company",
    "wof:placetype":"venue"
},
  "geometry": {"coordinates":[-85.22478700000001,30.774023],"type":"Point"}
}