{
  "type": "Feature",
  "properties": {
    "iso:country":"US",
    "sg:address":"7268 State Rd 54",
    "sg:city":"New Port Richey",
    "sg:classifiers":[
        {
            "category":"Shopping",
            "subcategory":"Florist",
            "type":"Retail Goods"
        }
    ],
    "sg:phone":"+1 727 376 2962",
    "sg:postcode":"34653",
    "sg:province":"FL",
    "sg:website":"www.granddesigns.com",
    "wof:name":"Grand Designs",
    "wof:placetype":"venue"
},
  "geometry": {"coordinates":[-82.693575,28.216964],"type":"Point"}
}