{
  "type": "Feature",
  "properties": {
    "iso:country":"US",
    "sg:address":"4914 Augusta Ave",
    "sg:city":"Oldsmar",
    "sg:classifiers":[
        {
            "category":"Health Services",
            "subcategory":"Clinic",
            "type":"Services"
        }
    ],
    "sg:phone":"+1 813 789 9869",
    "sg:postcode":"34677",
    "sg:province":"FL",
    "sg:tags":[
        "specialty",
        "outpatient"
    ],
    "wof:name":"Ot Resource Inc",
    "wof:placetype":"venue"
},
  "geometry": {"coordinates":[-82.69116699999999,28.057597],"type":"Point"}
}