{
  "type": "Feature",
  "properties": {
    "addr:full":"5451 NW 24th St Margate FL 33063",
    "addr:housenumber":"5451",
    "addr:postcode":"33063",
    "addr:street":"Nw 24Th St Margate",
    "iso:country":"US",
    "sg:address":"5451 NW 24th St",
    "sg:city":"Margate",
    "sg:classifiers":[
        {
            "category":"Building & Trades",
            "subcategory":"Plumbing",
            "type":"Services"
        }
    ],
    "sg:phone":"+1 954 973 6599",
    "sg:postcode":"33063",
    "sg:province":"FL",
    "sg:tags":[
        "conditioning",
        "air",
        "system",
        "contractor"
    ],
    "wof:name":"Air America AC Htg & Refrig",
    "wof:placetype":"venue"
},
  "geometry": {"coordinates":[-80.200485,26.257137],"type":"Point"}
}