{
  "type": "Feature",
  "properties": {
    "iso:country":"US",
    "sg:address":"400 SW 2nd St",
    "sg:city":"Miami",
    "sg:classifiers":[
        {
            "category":"Real Estate",
            "subcategory":"Real Estate Services",
            "type":"Services"
        }
    ],
    "sg:phone":"+1 305 326 8503",
    "sg:postcode":"33130",
    "sg:province":"FL",
    "sg:tags":[
        "management",
        "condominium"
    ],
    "wof:name":"Miami Riverview Condominium",
    "wof:placetype":"venue"
},
  "geometry": {"coordinates":[-80.200974,25.771971],"type":"Point"}
}