{
  "type": "Feature",
  "properties": {
    "addr:full":"6629 Da Lisa Rd Milton FL 32583",
    "addr:housenumber":"6629",
    "addr:postcode":"32583",
    "addr:street":"Da Lisa Rd",
    "iso:country":"US",
    "sg:address":"6629 Da Lisa Rd",
    "sg:city":"Milton",
    "sg:classifiers":[
        {
            "category":"Manufacturing",
            "subcategory":"Rubber & Plastics",
            "type":"Manufacturing & Wholesale Goods"
        }
    ],
    "sg:phone":"+1 850 450 5136",
    "sg:postcode":"32583",
    "sg:province":"FL",
    "sg:tags":[
        "product",
        "mfg"
    ],
    "wof:name":"Earls Engravables",
    "wof:placetype":"venue"
},
  "geometry": {"coordinates":[-87.047234,30.580009],"type":"Point"}
}