{
  "type": "Feature",
  "properties": {
    "iso:country":"US",
    "sg:address":"659 Cohn Ln",
    "sg:city":"Safety Harbor",
    "sg:classifiers":[
        {
            "category":"Building & Trades",
            "subcategory":"Construction",
            "type":"Services"
        }
    ],
    "sg:phone":"+1 727 848 6600",
    "sg:postcode":"34695",
    "sg:province":"FL",
    "sg:tags":[
        "home",
        "builder"
    ],
    "wof:name":"Arista Builders Inc",
    "wof:placetype":"venue"
},
  "geometry": {"coordinates":[-82.70499599999999,27.996568],"type":"Point"}
}