{
  "type": "Feature",
  "properties": {
    "addr:full":"2805 US Hwy 98 Lakeland FL 33805",
    "addr:housenumber":"2805",
    "addr:postcode":"33805",
    "addr:street":"Us Hwy 98",
    "iso:country":"US",
    "sg:address":"2805 US Hwy 98",
    "sg:city":"Lakeland",
    "sg:classifiers":[
        {
            "category":"Home & Garden",
            "subcategory":"Building Materials",
            "type":"Retail Goods"
        }
    ],
    "sg:phone":"+1 863 688 6800",
    "sg:postcode":"33805",
    "sg:province":"FL",
    "wof:name":"Home Depot",
    "wof:placetype":"venue"
},
  "geometry": {"coordinates":[-81.965373,28.080458],"type":"Point"}
}