{
  "type": "Feature",
  "properties": {
    "iso:country":"US",
    "sg:address":"5159 SW 71st Pl",
    "sg:city":"Miami",
    "sg:classifiers":[
        {
            "category":"Professional",
            "subcategory":"Lawyer & Legal Services",
            "type":"Services"
        }
    ],
    "sg:phone":"+1 305 669 3011",
    "sg:postcode":"33155",
    "sg:province":"FL",
    "wof:name":"Hunter Charlton Lee",
    "wof:placetype":"venue"
},
  "geometry": {"coordinates":[-80.310078,25.722002],"type":"Point"}
}