{
  "type": "Feature",
  "properties": {
    "addr:full":"870 NW 203rd St Miami FL 33169",
    "addr:housenumber":"870",
    "addr:postcode":"33169",
    "addr:street":"Nw 203Rd St",
    "iso:country":"US",
    "sg:address":"870 NW 203rd St",
    "sg:city":"Miami",
    "sg:classifiers":[
        {
            "category":"Recreation",
            "type":"Entertainment"
        }
    ],
    "sg:phone":"+1 305 655 3149",
    "sg:postcode":"33169",
    "sg:province":"FL",
    "wof:name":"Roderick Singleton Inc",
    "wof:placetype":"venue"
},
  "geometry": {"coordinates":[-80.219413,25.961146],"type":"Point"}
}