{
  "type": "Feature",
  "properties": {
    "iso:country":"US",
    "sg:address":"2549 W Tennessee St",
    "sg:city":"Tallahassee",
    "sg:classifiers":[
        {
            "category":"Restaurant",
            "type":"Food & Drink"
        }
    ],
    "sg:phone":"+1 850 878 0351",
    "sg:postcode":"32304",
    "sg:province":"FL",
    "sg:tags":[
        "mexican"
    ],
    "wof:name":"El Mercadito Mexican Store Inc",
    "wof:placetype":"venue"
},
  "geometry": {"coordinates":[-84.334602,30.45116],"type":"Point"}
}