{
  "type": "Feature",
  "properties": {
    "iso:country":"US",
    "sg:address":"4400 Rickenbacker Cswy",
    "sg:city":"Key Biscayne",
    "sg:classifiers":[
        {
            "category":"Professional",
            "subcategory":"Business Services",
            "type":"Services"
        }
    ],
    "sg:phone":"+1 305 365 8676",
    "sg:postcode":"33149",
    "sg:province":"FL",
    "sg:tags":[
        "event"
    ],
    "wof:name":"Event Imaging Solutions Inc",
    "wof:placetype":"venue"
},
  "geometry": {"coordinates":[-80.152528,25.716503],"type":"Point"}
}