{
  "type": "Feature",
  "properties": {
    "iso:country":"US",
    "sg:address":"4595 Palm Beach Blvd",
    "sg:city":"Fort Myers",
    "sg:classifiers":[
        {
            "category":"Autos & Motor Vehicles",
            "subcategory":"Fuel & Gas Station",
            "type":"Retail Goods"
        }
    ],
    "sg:phone":"+1 239 694 0769",
    "sg:postcode":"33905",
    "sg:province":"FL",
    "sg:tags":[
        "oil"
    ],
    "wof:name":"Mobil Image",
    "wof:placetype":"venue"
},
  "geometry": {"coordinates":[-81.81857100000001,26.672975],"type":"Point"}
}