{
  "type": "Feature",
  "properties": {
    "iso:country":"US",
    "sg:address":"5167 8th St SW",
    "sg:city":"Coral Gables",
    "sg:classifiers":[
        {
            "category":"Shopping",
            "subcategory":"Used Merchandise",
            "type":"Retail Goods"
        }
    ],
    "sg:phone":"+1 305 445 1052",
    "sg:postcode":"33134",
    "sg:province":"FL",
    "sg:tags":[
        "antique"
    ],
    "wof:name":"Luxurious Antiques",
    "wof:placetype":"venue"
},
  "geometry": {"coordinates":[-80.278288,25.763928],"type":"Point"}
}