{
  "type": "Feature",
  "properties": {
    "iso:country":"US",
    "sg:address":"1463 NW 97th Ave",
    "sg:city":"Doral",
    "sg:classifiers":[
        {
            "category":"Manufacturing",
            "subcategory":"Rubber & Plastics",
            "type":"Manufacturing & Wholesale Goods"
        }
    ],
    "sg:phone":"+1 786 336 0739",
    "sg:postcode":"33172",
    "sg:province":"FL",
    "sg:tags":[
        "product"
    ],
    "wof:name":"Techno Rubber Industries Corp",
    "wof:placetype":"venue"
},
  "geometry": {"coordinates":[-80.35277499999999,25.788709],"type":"Point"}
}