{
  "type": "Feature",
  "properties": {
    "addr:full":"4530 9th St E Bradenton FL 34203",
    "addr:housenumber":"4530",
    "addr:postcode":"34203",
    "addr:street":"9Th St",
    "iso:country":"US",
    "sg:address":"4530 9th St E",
    "sg:city":"Bradenton",
    "sg:classifiers":[
        {
            "category":"Real Estate",
            "subcategory":"Real Estate Operator",
            "type":"Services"
        }
    ],
    "sg:phone":"+1 941 753 3913",
    "sg:postcode":"34203",
    "sg:province":"FL",
    "sg:tags":[
        "mobile",
        "home",
        "community"
    ],
    "wof:name":"Twin Oaks Mobile Home Park",
    "wof:placetype":"venue"
},
  "geometry": {"coordinates":[-82.55497699999999,27.459509],"type":"Point"}
}