{
  "type": "Feature",
  "properties": {
    "iso:country":"US",
    "sg:address":"512 Sherry Ave",
    "sg:city":"Lake Helen",
    "sg:classifiers":[
        {
            "category":"Restaurant",
            "type":"Food & Drink"
        }
    ],
    "sg:phone":"+1 386 228 3380",
    "sg:postcode":"32744",
    "sg:province":"FL",
    "sg:tags":[
        "parlor",
        "ice",
        "cream"
    ],
    "wof:name":"Sutton's Ice Cream Truck",
    "wof:placetype":"venue"
},
  "geometry": {"coordinates":[-81.24147600000001,28.993033],"type":"Point"}
}