{
  "type": "Feature",
  "properties": {
    "iso:country":"US",
    "sg:address":"2346 Worthington Rd",
    "sg:city":"Maitland",
    "sg:classifiers":[
        {
            "category":"Organizations",
            "subcategory":"Professional Association",
            "type":"Services"
        }
    ],
    "sg:phone":"+1 407 831 3749",
    "sg:postcode":"32751",
    "sg:province":"FL",
    "wof:name":"Seminole Sunrise Chapter",
    "wof:placetype":"venue"
},
  "geometry": {"coordinates":[-81.338515,28.643157],"type":"Point"}
}