{
  "type": "Feature",
  "properties": {
    "addr:full":"2843 47th St Sarasota FL 34234",
    "addr:housenumber":"2843",
    "addr:postcode":"34234",
    "addr:street":"47Th St",
    "iso:country":"US",
    "sg:address":"2843 47th St",
    "sg:city":"Sarasota",
    "sg:classifiers":[
        {
            "category":"Travel",
            "subcategory":"Travel Agent",
            "type":"Entertainment"
        }
    ],
    "sg:phone":"+1 941 360 9851",
    "sg:postcode":"34234",
    "sg:province":"FL",
    "sg:tags":[
        "agency",
        "bureau"
    ],
    "wof:name":"Sarasota Travel Corp",
    "wof:placetype":"venue"
},
  "geometry": {"coordinates":[-82.51277,27.374589],"type":"Point"}
}