{
  "type": "Feature",
  "properties": {
    "addr:full":"7361 International Pl Sarasota FL 34240",
    "addr:housenumber":"7361",
    "addr:postcode":"34240",
    "addr:street":"International Pl",
    "iso:country":"US",
    "sg:address":"7361 International Pl",
    "sg:city":"Sarasota",
    "sg:classifiers":[
        {
            "category":"Professional",
            "subcategory":"Advertising",
            "type":"Services"
        }
    ],
    "sg:phone":"+1 941 907 4749",
    "sg:postcode":"34240",
    "sg:province":"FL",
    "sg:tags":[
        "counselor"
    ],
    "wof:name":"Be Creative",
    "wof:placetype":"venue"
},
  "geometry": {"coordinates":[-82.422946,27.380404],"type":"Point"}
}