{
  "type": "Feature",
  "properties": {
    "addr:full":"1121 Boxwood Dr Delray Beach FL 33445",
    "addr:housenumber":"1121",
    "addr:postcode":"33445",
    "addr:street":"Boxwood Dr",
    "iso:country":"US",
    "sg:address":"1121 Boxwood Dr",
    "sg:city":"Delray Beach",
    "sg:classifiers":[
        {
            "category":"Real Estate",
            "subcategory":"Real Estate Agent",
            "type":"Services"
        }
    ],
    "sg:phone":"+1 561 265 2845",
    "sg:postcode":"33445",
    "sg:province":"FL",
    "wof:name":"Mirror Realty Corp",
    "wof:placetype":"venue"
},
  "geometry": {"coordinates":[-80.099878,26.44281],"type":"Point"}
}