{
  "type": "Feature",
  "properties": {
    "iso:country":"US",
    "sg:address":"205 S Dillard St",
    "sg:city":"Winter Garden",
    "sg:classifiers":[
        {
            "category":"Personal",
            "subcategory":"Beauty Salon",
            "type":"Services"
        }
    ],
    "sg:phone":"+1 407 656 3494",
    "sg:postcode":"34787",
    "sg:province":"FL",
    "sg:tags":[
        "shop"
    ],
    "wof:name":"Magic Wand",
    "wof:placetype":"venue"
},
  "geometry": {"coordinates":[-81.583465,28.562098],"type":"Point"}
}