{
  "type": "Feature",
  "properties": {
    "iso:country":"US",
    "sg:address":"234 King St",
    "sg:city":"Cocoa",
    "sg:classifiers":[
        {
            "category":"Shopping",
            "type":"Retail Goods"
        }
    ],
    "sg:phone":"+1 321 433 0145",
    "sg:postcode":"32922",
    "sg:province":"FL",
    "sg:tags":[
        "art",
        "gallery",
        "dealer"
    ],
    "wof:name":"R L Lewis Art Gallery",
    "wof:placetype":"venue"
},
  "geometry": {"coordinates":[-80.727287,28.355945],"type":"Point"}
}