{
  "type": "Feature",
  "properties": {
    "iso:country":"US",
    "sg:address":"14600 NW 7th Ave",
    "sg:city":"Miami",
    "sg:classifiers":[
        {
            "category":"Shopping",
            "subcategory":"Pawn Shop",
            "type":"Retail Goods"
        }
    ],
    "sg:phone":"+1 305 688 1926",
    "sg:postcode":"33168",
    "sg:province":"FL",
    "wof:name":"Car Dome Inc",
    "wof:placetype":"venue"
},
  "geometry": {"coordinates":[-80.212008,25.908553],"type":"Point"}
}