{
  "type": "Feature",
  "properties": {
    "iso:country":"US",
    "sg:address":"2533 34th Ave E",
    "sg:city":"Bradenton",
    "sg:classifiers":[
        {
            "category":"Building & Trades",
            "subcategory":"Landscaping Services",
            "type":"Services"
        }
    ],
    "sg:phone":"+1 941 266 7172",
    "sg:postcode":"34208",
    "sg:province":"FL",
    "sg:tags":[
        "tree"
    ],
    "wof:name":"Angel Carino Tree Service",
    "wof:placetype":"venue"
},
  "geometry": {"coordinates":[-82.531328,27.469326],"type":"Point"}
}