{
  "type": "Feature",
  "properties": {
    "iso:country":"US",
    "sg:address":"825 SW 13th Ave",
    "sg:city":"Miami",
    "sg:classifiers":[
        {
            "category":"Professional",
            "subcategory":"Business Services",
            "type":"Services"
        }
    ],
    "sg:phone":"+1 305 858 1766",
    "sg:postcode":"33135",
    "sg:province":"FL",
    "sg:tags":[
        "telemarketing"
    ],
    "wof:name":"Natural Deal Co",
    "wof:placetype":"venue"
},
  "geometry": {"coordinates":[-80.216348,25.764473],"type":"Point"}
}