{
  "type": "Feature",
  "properties": {
    "addr:full":"695 Grant Rd Palm Bay FL 32909",
    "addr:housenumber":"695",
    "addr:postcode":"32909",
    "addr:street":"Grant Rd",
    "iso:country":"US",
    "sg:address":"695 Grant Rd",
    "sg:city":"Palm Bay",
    "sg:classifiers":[
        {
            "category":"Building & Trades",
            "subcategory":"Landscaping Services",
            "type":"Services"
        }
    ],
    "sg:phone":"+1 321 508 8111",
    "sg:postcode":"32909",
    "sg:province":"FL",
    "wof:name":"Warren Wright Lawn Mtc",
    "wof:placetype":"venue"
},
  "geometry": {"coordinates":[-80.604457,27.924439],"type":"Point"}
}