{
  "type": "Feature",
  "properties": {
    "addr:full":"1 Alameda Grande Englewood FL 34223",
    "addr:housenumber":"1",
    "addr:postcode":"34223",
    "addr:street":"Alameda Grande",
    "iso:country":"US",
    "sg:address":"1 Alameda Grande",
    "sg:city":"Englewood",
    "sg:classifiers":[
        {
            "category":"Real Estate",
            "subcategory":"Developer",
            "type":"Services"
        }
    ],
    "sg:phone":"+1 941 474 5079",
    "sg:postcode":"34223",
    "sg:province":"FL",
    "sg:tags":[
        "mobile",
        "home"
    ],
    "wof:name":"Alameda Isles Home Owners Assn",
    "wof:placetype":"venue"
},
  "geometry": {"coordinates":[-82.371968,26.994937],"type":"Point"}
}