{
  "type": "Feature",
  "properties": {
    "iso:country":"US",
    "sg:address":"308 W Bridgers Ave",
    "sg:city":"Auburndale",
    "sg:classifiers":[
        {
            "category":"Personal",
            "subcategory":"Beauty Salon",
            "type":"Services"
        }
    ],
    "sg:phone":"+1 863 967 6351",
    "sg:postcode":"33823",
    "sg:province":"FL",
    "wof:name":"One Stop Hair Shop",
    "wof:placetype":"venue"
},
  "geometry": {"coordinates":[-81.78919999999999,28.062415],"type":"Point"}
}