{
  "type": "Feature",
  "properties": {
    "addr:full":"196 Palmetto St Tallahassee FL 32301",
    "addr:housenumber":"196",
    "addr:postcode":"32301",
    "addr:street":"Palmetto St",
    "iso:country":"US",
    "sg:address":"196 Palmetto St",
    "sg:city":"Tallahassee",
    "sg:classifiers":[
        {
            "category":"Restaurant",
            "type":"Food & Drink"
        }
    ],
    "sg:menulink":"http://www.allmenus.com/fl/tallahassee-central/122616-quiznos-sub/menu/",
    "sg:phone":"+1 850 645 2835",
    "sg:postcode":"32301",
    "sg:province":"FL",
    "sg:tags":[
        "wrap",
        "american",
        "sandwich"
    ],
    "wof:name":"Quiznos Sub",
    "wof:placetype":"venue"
},
  "geometry": {"coordinates":[-84.283023,30.41991],"type":"Point"}
}