{
  "type": "Feature",
  "properties": {
    "addr:full":"1768 N Davis St Jacksonville FL 32209",
    "addr:housenumber":"1768",
    "addr:postcode":"32209",
    "addr:street":"N Davis St",
    "iso:country":"US",
    "sg:address":"1768 N Davis St",
    "sg:city":"Jacksonville",
    "sg:classifiers":[
        {
            "category":"Fast Food",
            "type":"Food & Drink"
        },
        {
            "category":"Restaurant",
            "type":"Food & Drink"
        }
    ],
    "sg:phone":"+1 904 356 1981",
    "sg:postcode":"32209",
    "sg:province":"FL",
    "sg:tags":[
        "hamburger",
        "hot",
        "dog",
        "american",
        "take",
        "chicken"
    ],
    "sg:website":"http://www.mcdonalds.com",
    "wof:name":"McDonald's",
    "wof:placetype":"venue"
},
  "geometry": {"coordinates":[-81.667061,30.34643],"type":"Point"}
}