{
  "type": "Feature",
  "properties": {
    "addr:full":"1 Old Kings Rd Palm Coast FL 32137",
    "addr:housenumber":"1",
    "addr:postcode":"32137",
    "addr:street":"Old Kings Rd",
    "iso:country":"US",
    "sg:address":"1 Old Kings Rd",
    "sg:city":"Palm Coast",
    "sg:classifiers":[
        {
            "category":"Restaurant",
            "type":"Food & Drink"
        }
    ],
    "sg:menulink":"http://www.allmenus.com/fl/flagler-beach/169496-wendys/menu/",
    "sg:phone":"+1 386 445 4213",
    "sg:postcode":"32137",
    "sg:province":"FL",
    "sg:tags":[
        "burger",
        "american",
        "soup"
    ],
    "wof:name":"Wendy's",
    "wof:placetype":"venue"
},
  "geometry": {"coordinates":[-81.211716,29.555164],"type":"Point"}
}