{
  "type": "Feature",
  "properties": {
    "iso:country":"US",
    "sg:address":"11120 Monet Woods Rd",
    "sg:city":"Palm Beach Gardens",
    "sg:classifiers":[
        {
            "category":"Recreation",
            "type":"Entertainment"
        }
    ],
    "sg:phone":"+1 561 626 4389",
    "sg:postcode":"33410",
    "sg:province":"FL",
    "wof:name":"Underwater Horizons",
    "wof:placetype":"venue"
},
  "geometry": {"coordinates":[-80.08571000000001,26.839897],"type":"Point"}
}