{
  "type": "Feature",
  "properties": {
    "iso:country":"US",
    "sg:address":"622 2nd Ln",
    "sg:city":"Vero Beach",
    "sg:classifiers":[
        {
            "category":"Autos & Motor Vehicles",
            "subcategory":"Fuel & Gas Station",
            "type":"Retail Goods"
        }
    ],
    "sg:phone":"+1 772 569 2496",
    "sg:postcode":"32962",
    "sg:province":"FL",
    "sg:tags":[
        "station"
    ],
    "wof:name":"Automotive Service By Mike",
    "wof:placetype":"venue"
},
  "geometry": {"coordinates":[-80.38619199999999,27.606355],"type":"Point"}
}