{
  "type": "Feature",
  "properties": {
    "iso:country":"US",
    "sg:address":"12125 US Hwy 19",
    "sg:city":"Port Richey",
    "sg:classifiers":[
        {
            "category":"Shopping",
            "subcategory":"Department Store",
            "type":"Retail Goods"
        }
    ],
    "sg:phone":"+1 727 868 3203",
    "sg:postcode":"34667",
    "sg:province":"FL",
    "wof:name":"Bealls 11",
    "wof:placetype":"venue"
},
  "geometry": {"coordinates":[-82.69937400000001,28.333455],"type":"Point"}
}