{
  "type": "Feature",
  "properties": {
    "iso:country":"US",
    "sg:address":"5840 Red Bug Lake Rd",
    "sg:city":"Winter Springs",
    "sg:classifiers":[
        {
            "category":"Professional",
            "subcategory":"Lawyer & Legal Services",
            "type":"Services"
        }
    ],
    "sg:phone":"+1 407 696 1069",
    "sg:postcode":"32708",
    "sg:province":"FL",
    "sg:tags":[
        "attorney",
        "bureau"
    ],
    "wof:name":"Enterprise Legal Svc",
    "wof:placetype":"venue"
},
  "geometry": {"coordinates":[-81.26514299999999,28.647685],"type":"Point"}
}