{
  "type": "Feature",
  "properties": {
    "addr:full":"629 W Britain St Hernando FL 34442",
    "addr:housenumber":"629",
    "addr:postcode":"34442",
    "addr:street":"W Britain St",
    "iso:country":"US",
    "sg:address":"629 W Britain St",
    "sg:city":"Hernando",
    "sg:classifiers":[
        {
            "category":"Professional",
            "type":"Services"
        }
    ],
    "sg:phone":"+1 352 527 0119",
    "sg:postcode":"34442",
    "sg:province":"FL",
    "wof:name":"Nathan Family Ltd",
    "wof:placetype":"venue"
},
  "geometry": {"coordinates":[-82.444845,28.884606],"type":"Point"}
}