{
  "type": "Feature",
  "properties": {
    "iso:country":"US",
    "sg:address":"1550 Hendricks Ave",
    "sg:city":"Jacksonville",
    "sg:classifiers":[
        {
            "category":"Manufacturing",
            "subcategory":"Metals",
            "type":"Manufacturing & Wholesale Goods"
        },
        {
            "category":"Shopping",
            "type":"Retail Goods"
        }
    ],
    "sg:phone":"+1 904 396 7653",
    "sg:postcode":"32207",
    "sg:province":"FL",
    "sg:tags":[
        "trophy",
        "trophies",
        "item",
        "advertising",
        "medal",
        "plaque"
    ],
    "sg:website":"http://www.aujax.com",
    "wof:name":"Awards Unlimited",
    "wof:placetype":"venue"
},
  "geometry": {"coordinates":[-81.654697,30.309653],"type":"Point"}
}