{
  "type": "Feature",
  "properties": {
    "addr:full":"33001 Damon Ct Leesburg FL 34788",
    "addr:postcode":"33001;34788",
    "addr:street":"Damon Ct",
    "iso:country":"US",
    "sg:address":"33001 Damon Ct",
    "sg:city":"Leesburg",
    "sg:classifiers":[
        {
            "category":"Shopping",
            "subcategory":"Discount & Variety Stores",
            "type":"Retail Goods"
        }
    ],
    "sg:phone":"+1 352 315 1948",
    "sg:postcode":"34788",
    "sg:province":"FL",
    "sg:tags":[
        "merchandise",
        "general"
    ],
    "wof:name":"Data Base Managemnt Mrktn",
    "wof:placetype":"venue"
},
  "geometry": {"coordinates":[-81.793898,28.830274],"type":"Point"}
}