{
  "type": "Feature",
  "properties": {
    "addr:full":"17411 NW 8th St Hollywood FL 33029",
    "addr:housenumber":"17411",
    "addr:postcode":"33029",
    "addr:street":"Nw 8Th St",
    "iso:country":"US",
    "sg:address":"17411 NW 8th St",
    "sg:city":"Hollywood",
    "sg:classifiers":[
        {
            "category":"Professional",
            "subcategory":"Business Services",
            "type":"Services"
        }
    ],
    "sg:phone":"+1 954 436 5099",
    "sg:postcode":"33029",
    "sg:province":"FL",
    "wof:name":"Amoral S Enterprises",
    "wof:placetype":"venue"
},
  "geometry": {"coordinates":[-80.380752,26.012689],"type":"Point"}
}