{
  "type": "Feature",
  "properties": {
    "addr:full":"8619 Dixie Hwy Miami FL 33143",
    "addr:housenumber":"8619",
    "addr:postcode":"33143",
    "addr:street":"Dixie Hwy",
    "iso:country":"US",
    "sg:address":"8619 Dixie Hwy",
    "sg:city":"Miami",
    "sg:classifiers":[
        {
            "category":"Restaurant",
            "type":"Food & Drink"
        }
    ],
    "sg:phone":"+1 305 663 1750",
    "sg:postcode":"33143",
    "sg:province":"FL",
    "sg:tags":[
        "eating"
    ],
    "wof:name":"Papa Johns",
    "wof:placetype":"venue"
},
  "geometry": {"coordinates":[-80.306827,25.690291],"type":"Point"}
}