{
  "type": "Feature",
  "properties": {
    "iso:country":"US",
    "sg:address":"2290 NE 197th St",
    "sg:city":"Miami",
    "sg:classifiers":[
        {
            "category":"Professional",
            "subcategory":"Management & Consulting",
            "type":"Services"
        }
    ],
    "sg:phone":"+1 305 682 1075",
    "sg:postcode":"33180",
    "sg:province":"FL",
    "sg:tags":[
        "consultant",
        "business"
    ],
    "wof:name":"Soti Inc",
    "wof:placetype":"venue"
},
  "geometry": {"coordinates":[-80.15688400000001,25.957331],"type":"Point"}
}