{
  "type": "Feature",
  "properties": {
    "addr:full":"2404 US Hwy 19 Holiday FL 34691",
    "addr:housenumber":"2404",
    "addr:postcode":"34691",
    "addr:street":"Us Hwy 19",
    "iso:country":"US",
    "sg:address":"2404 US Hwy 19",
    "sg:city":"Holiday",
    "sg:classifiers":[
        {
            "category":"Health Services",
            "subcategory":"Doctor",
            "type":"Services"
        }
    ],
    "sg:phone":"+1 727 944 8800",
    "sg:postcode":"34691",
    "sg:province":"FL",
    "sg:tags":[
        "medical"
    ],
    "wof:name":"Gulfview Walk In Clinics",
    "wof:placetype":"venue"
},
  "geometry": {"coordinates":[-82.73986499999999,28.195136],"type":"Point"}
}