{
  "type": "Feature",
  "properties": {
    "iso:country":"US",
    "sg:address":"85 SE 4th Ave",
    "sg:city":"Delray Beach",
    "sg:classifiers":[
        {
            "category":"Professional",
            "subcategory":"Accounting & Tax Preparation",
            "type":"Services"
        }
    ],
    "sg:phone":"+1 561 272 8447",
    "sg:postcode":"33483",
    "sg:province":"FL",
    "sg:tags":[
        "accountant"
    ],
    "wof:name":"Hilsman & Weaver",
    "wof:placetype":"venue"
},
  "geometry": {"coordinates":[-80.068977,26.461391],"type":"Point"}
}