{
  "type": "Feature",
  "properties": {
    "addr:full":"3501 W University Ave Gainesville FL 32607",
    "addr:housenumber":"3501",
    "addr:postcode":"32607",
    "addr:street":"W University Ave",
    "iso:country":"US",
    "sg:address":"3501 W University Ave",
    "sg:city":"Gainesville",
    "sg:classifiers":[
        {
            "category":"Banks & Credit Unions",
            "subcategory":"Bank",
            "type":"Services"
        }
    ],
    "sg:phone":"+1 352 335 3353",
    "sg:postcode":"32607",
    "sg:province":"FL",
    "wof:name":"Wachovia Bank",
    "wof:placetype":"venue"
},
  "geometry": {"coordinates":[-82.375125,29.651831],"type":"Point"}
}