{
  "type": "Feature",
  "properties": {
    "iso:country":"US",
    "sg:address":"1549 Sunset Dr",
    "sg:city":"Miami",
    "sg:classifiers":[
        {
            "category":"Restaurant",
            "type":"Food & Drink"
        }
    ],
    "sg:phone":"+1 305 284 9989",
    "sg:postcode":"33143",
    "sg:province":"FL",
    "sg:tags":[
        "new",
        "american",
        "french"
    ],
    "wof:name":"George's In South Miami",
    "wof:placetype":"venue"
},
  "geometry": {"coordinates":[-80.27819700000001,25.704801],"type":"Point"}
}