{
  "type": "Feature",
  "properties": {
    "iso:country":"US",
    "sg:address":"3564 S Military Trl",
    "sg:city":"Lake Worth",
    "sg:classifiers":[
        {
            "category":"Insurance",
            "subcategory":"Insurance Agent",
            "type":"Services"
        }
    ],
    "sg:phone":"+1 561 965 2200",
    "sg:postcode":"33463",
    "sg:province":"FL",
    "sg:tags":[
        "agency"
    ],
    "wof:name":"Federal Insurance Co",
    "wof:placetype":"venue"
},
  "geometry": {"coordinates":[-80.113196,26.625194],"type":"Point"}
}