{
  "type": "Feature",
  "properties": {
    "iso:country":"US",
    "sg:address":"421 Montgomery Rd Ste 101",
    "sg:city":"Altamonte Springs",
    "sg:classifiers":[
        {
            "category":"Professional",
            "subcategory":"Lawyer & Legal Services",
            "type":"Services"
        }
    ],
    "sg:phone":"+1 407 862 0199",
    "sg:postcode":"32714",
    "sg:province":"FL",
    "wof:name":"Garcia-Crews Antonio",
    "wof:placetype":"venue"
},
  "geometry": {"coordinates":[-81.402185,28.668163],"type":"Point"}
}