{
  "type": "Feature",
  "properties": {
    "addr:full":"1527 University Blvd W Jacksonville FL 32217",
    "addr:housenumber":"1527",
    "addr:postcode":"32217",
    "addr:street":"University Blvd W",
    "iso:country":"US",
    "sg:address":"1527 University Blvd W",
    "sg:city":"Jacksonville",
    "sg:classifiers":[
        {
            "category":"Shopping",
            "subcategory":"Beauty & Cosmetics",
            "type":"Retail Goods"
        }
    ],
    "sg:phone":"+1 904 739 1361",
    "sg:postcode":"32217",
    "sg:province":"FL",
    "sg:tags":[
        "merchandise"
    ],
    "wof:name":"Merle Norman Cosmetics",
    "wof:placetype":"venue"
},
  "geometry": {"coordinates":[-81.644147,30.260982],"type":"Point"}
}