{
  "type": "Feature",
  "properties": {
    "iso:country":"US",
    "sg:address":"310 SE 5th Ter",
    "sg:city":"Pompano Beach",
    "sg:classifiers":[
        {
            "category":"Professional",
            "type":"Services"
        }
    ],
    "sg:phone":"+1 954 943 4989",
    "sg:postcode":"33060",
    "sg:province":"FL",
    "wof:name":"Prolux US Inc",
    "wof:placetype":"venue"
},
  "geometry": {"coordinates":[-80.11488,26.225634],"type":"Point"}
}