{
  "type": "Feature",
  "properties": {
    "addr:full":"5720 Mifflin Ave Pensacola FL 32526",
    "addr:housenumber":"5720",
    "addr:postcode":"32526",
    "addr:street":"Mifflin Ave",
    "iso:country":"US",
    "sg:address":"5720 Mifflin Ave",
    "sg:city":"Pensacola",
    "sg:classifiers":[
        {
            "category":"Home & Garden",
            "subcategory":"Building Materials",
            "type":"Retail Goods"
        }
    ],
    "sg:phone":"+1 850 941 1276",
    "sg:postcode":"32526",
    "sg:province":"FL",
    "sg:tags":[
        "tile",
        "ceramic"
    ],
    "wof:name":"Cottons Ceramic Tile",
    "wof:placetype":"venue"
},
  "geometry": {"coordinates":[-87.275948,30.465022],"type":"Point"}
}