{
  "type": "Feature",
  "properties": {
    "addr:full":"8221 Glades Rd Boca Raton FL 33431",
    "addr:housenumber":"8221",
    "addr:postcode":"33431",
    "addr:street":"Glades Rd",
    "iso:country":"US",
    "sg:address":"8221 Glades Rd",
    "sg:city":"Boca Raton",
    "sg:classifiers":[
        {
            "category":"Food & Beverages",
            "subcategory":"Bakery",
            "type":"Retail Goods"
        }
    ],
    "sg:phone":"+1 561 470 5855",
    "sg:postcode":"33431",
    "sg:province":"FL",
    "sg:tags":[
        "doughnut"
    ],
    "wof:name":"Dunkin Donuts",
    "wof:placetype":"venue"
},
  "geometry": {"coordinates":[-80.17497400000001,26.367969],"type":"Point"}
}