{
  "type": "Feature",
  "properties": {
    "addr:full":"5362 NW 110th Ave Miami FL 33178",
    "addr:housenumber":"5362",
    "addr:postcode":"33178",
    "addr:street":"Nw 110Th Ave",
    "iso:country":"US",
    "sg:address":"5362 NW 110th Ave",
    "sg:city":"Miami",
    "sg:classifiers":[
        {
            "category":"Communications",
            "type":"Services"
        }
    ],
    "sg:phone":"+1 305 591 3571",
    "sg:postcode":"33178",
    "sg:province":"FL",
    "sg:tags":[
        "communication"
    ],
    "wof:name":"Nevarez Communications Inc",
    "wof:placetype":"venue"
},
  "geometry": {"coordinates":[-80.373977,25.832437],"type":"Point"}
}