{
  "type": "Feature",
  "properties": {
    "iso:country":"US",
    "sg:address":"4714 Halifax Dr",
    "sg:city":"Daytona Beach",
    "sg:classifiers":[
        {
            "category":"Social Services",
            "subcategory":"Adult Care",
            "type":"Services"
        }
    ],
    "sg:phone":"+1 386 760 5026",
    "sg:postcode":"32127",
    "sg:province":"FL",
    "sg:tags":[
        "residential"
    ],
    "wof:name":"Riverview Assisted Living",
    "wof:placetype":"venue"
},
  "geometry": {"coordinates":[-80.98219899999999,29.136804],"type":"Point"}
}