{
  "type": "Feature",
  "properties": {
    "addr:full":"3350 Cherokee Dr Vero Beach FL 32960",
    "addr:housenumber":"3350",
    "addr:postcode":"32960",
    "addr:street":"Cherokee Dr",
    "iso:country":"US",
    "sg:address":"3350 Cherokee Dr",
    "sg:city":"Vero Beach",
    "sg:classifiers":[
        {
            "category":"Airport",
            "type":"Transportation"
        }
    ],
    "sg:phone":"+1 772 562 2857",
    "sg:postcode":"32960",
    "sg:province":"FL",
    "sg:tags":[
        "aircraft",
        "storage"
    ],
    "wof:name":"Vero Beach Airport Svc",
    "wof:placetype":"venue"
},
  "geometry": {"coordinates":[-80.41785900000001,27.65092],"type":"Point"}
}