{
  "type": "Feature",
  "properties": {
    "iso:country":"US",
    "sg:address":"4049 S Orange Blossom Trl",
    "sg:city":"Orlando",
    "sg:classifiers":[
        {
            "category":"Real Estate",
            "subcategory":"Real Estate Operator",
            "type":"Services"
        }
    ],
    "sg:phone":"+1 407 447 1211",
    "sg:postcode":"32839",
    "sg:province":"FL",
    "sg:tags":[
        "building",
        "apartment"
    ],
    "wof:name":"Maxwell Garden Apts",
    "wof:placetype":"venue"
},
  "geometry": {"coordinates":[-81.39689199999999,28.502234],"type":"Point"}
}