{
  "type": "Feature",
  "properties": {
    "iso:country":"US",
    "sg:address":"445 SE Benchmark Dr",
    "sg:city":"Lee",
    "sg:classifiers":[
        {
            "category":"Freight",
            "type":"Transportation"
        },
        {
            "category":"Retail",
            "subcategory":"Auto Rental",
            "type":"Services"
        }
    ],
    "sg:phone":"+1 850 971 7216",
    "sg:postcode":"32059",
    "sg:province":"FL",
    "sg:tags":[
        "local",
        "truck",
        "trucking"
    ],
    "wof:name":"North Florida Express",
    "wof:placetype":"venue"
},
  "geometry": {"coordinates":[-83.30775800000001,30.40654],"type":"Point"}
}