{
  "type": "Feature",
  "properties": {
    "iso:country":"US",
    "sg:address":"4910 Bulls Bay Hwy",
    "sg:city":"Jacksonville",
    "sg:classifiers":[
        {
            "category":"Shopping",
            "subcategory":"Luggage & Leather Goods",
            "type":"Retail Goods"
        }
    ],
    "sg:phone":"+1 904 695 0022",
    "sg:postcode":"32219",
    "sg:province":"FL",
    "wof:name":"Samsonite Corp",
    "wof:placetype":"venue"
},
  "geometry": {"coordinates":[-81.788499,30.375558],"type":"Point"}
}