{
  "type": "Feature",
  "properties": {
    "addr:full":"402 N Collins St Plant City FL 33563",
    "addr:housenumber":"402",
    "addr:postcode":"33563",
    "addr:street":"N Collins St",
    "iso:country":"US",
    "sg:address":"402 N Collins St",
    "sg:city":"Plant City",
    "sg:classifiers":[
        {
            "category":"Social Services",
            "subcategory":"Child Care",
            "type":"Services"
        }
    ],
    "sg:phone":"+1 813 754 1773",
    "sg:postcode":"33563",
    "sg:province":"FL",
    "wof:name":"First Baptist Learning Ctr",
    "wof:placetype":"venue"
},
  "geometry": {"coordinates":[-82.123726,28.017825],"type":"Point"}
}