{
  "type": "Feature",
  "properties": {
    "addr:full":"3804 Wells St Orlando FL 32805",
    "addr:housenumber":"3804",
    "addr:postcode":"32805",
    "addr:street":"Wells St",
    "iso:country":"US",
    "sg:address":"3804 Wells St",
    "sg:city":"Orlando",
    "sg:classifiers":[
        {
            "category":"Building & Trades",
            "subcategory":"Landscaping Services",
            "type":"Services"
        }
    ],
    "sg:phone":"+1 407 294 6875",
    "sg:postcode":"32805",
    "sg:province":"FL",
    "wof:name":"Top Notch Lawn Care Inc",
    "wof:placetype":"venue"
},
  "geometry": {"coordinates":[-81.423332,28.522243],"type":"Point"}
}