{
  "type": "Feature",
  "properties": {
    "addr:full":"4498 US Hwy 90 Milton FL 32571",
    "addr:housenumber":"4498",
    "addr:postcode":"32571",
    "addr:street":"Us Hwy 90",
    "iso:country":"US",
    "sg:address":"4498 US Hwy 90",
    "sg:city":"Milton",
    "sg:classifiers":[
        {
            "category":"Health Services",
            "subcategory":"Doctor",
            "type":"Services"
        }
    ],
    "sg:phone":"+1 850 994 2771",
    "sg:postcode":"32571",
    "sg:province":"FL",
    "sg:tags":[
        "medical"
    ],
    "wof:name":"Pamela Schurman DO",
    "wof:placetype":"venue"
},
  "geometry": {"coordinates":[-87.136844,30.603623],"type":"Point"}
}