{
  "type": "Feature",
  "properties": {
    "iso:country":"US",
    "sg:address":"Gansevoort South 2323 Collins Ave",
    "sg:city":"Miami Beach",
    "sg:classifiers":[
        {
            "category":"Sports & Exercise",
            "subcategory":"Gym",
            "type":"Entertainment"
        }
    ],
    "sg:phone":"+1 305 534 1660",
    "sg:postcode":"33139",
    "sg:province":"FL",
    "sg:tags":[
        "trainer"
    ],
    "sg:website":"www.davidbartongym.com",
    "wof:name":"David Barton Gym",
    "wof:placetype":"venue"
},
  "geometry": {"coordinates":[-80.127771,25.798837],"type":"Point"}
}