{
  "type": "Feature",
  "properties": {
    "iso:country":"US",
    "sg:address":"9802 Baymeadows Rd",
    "sg:city":"Jacksonville",
    "sg:classifiers":[
        {
            "category":"Retail",
            "subcategory":"Laundry & Dry Cleaning",
            "type":"Services"
        }
    ],
    "sg:phone":"+1 904 642 3639",
    "sg:postcode":"32256",
    "sg:province":"FL",
    "sg:tags":[
        "cleaners"
    ],
    "wof:name":"Art-Craft Zoric Cleaners",
    "wof:placetype":"venue"
},
  "geometry": {"coordinates":[-81.555588,30.21895],"type":"Point"}
}