{
  "type": "Feature",
  "properties": {
    "iso:country":"US",
    "sg:address":"2701 W Nasa Blvd",
    "sg:city":"Melbourne",
    "sg:classifiers":[
        {
            "category":"Wholesale",
            "subcategory":"Electrical",
            "type":"Manufacturing & Wholesale Goods"
        }
    ],
    "sg:phone":"+1 321 724 5880",
    "sg:postcode":"32904",
    "sg:province":"FL",
    "sg:tags":[
        "equipment",
        "electric",
        "supply"
    ],
    "sg:website":"www.hughessupply.com",
    "wof:name":"Hughes Supply Inc",
    "wof:placetype":"venue"
},
  "geometry": {"coordinates":[-80.66628799999999,28.097845],"type":"Point"}
}