{
  "type": "Feature",
  "properties": {
    "iso:country":"US",
    "sg:address":"5628 Strand Blvd",
    "sg:city":"Naples",
    "sg:classifiers":[
        {
            "category":"Personal",
            "subcategory":"Beauty Salon",
            "type":"Services"
        }
    ],
    "sg:phone":"+1 239 566 1776",
    "sg:postcode":"34110",
    "sg:province":"FL",
    "sg:tags":[
        "hair"
    ],
    "sg:website":"www.supercuts.com",
    "wof:name":"Supercuts",
    "wof:placetype":"venue"
},
  "geometry": {"coordinates":[-81.746621,26.275662],"type":"Point"}
}