{
  "type": "Feature",
  "properties": {
    "addr:full":"6150 Kentucky Ave New Port Richey FL 34653",
    "addr:housenumber":"6150",
    "addr:postcode":"34653",
    "addr:street":"Kentucky Ave",
    "iso:country":"US",
    "sg:address":"6150 Kentucky Ave",
    "sg:city":"New Port Richey",
    "sg:classifiers":[
        {
            "category":"Recreation",
            "subcategory":"Marina",
            "type":"Entertainment"
        }
    ],
    "sg:phone":"+1 727 841 6240",
    "sg:postcode":"34653",
    "sg:province":"FL",
    "sg:tags":[
        "repairing",
        "boat"
    ],
    "wof:name":"Chester Moran Boat Detailing",
    "wof:placetype":"venue"
},
  "geometry": {"coordinates":[-82.71265099999999,28.257037],"type":"Point"}
}