{
  "type": "Feature",
  "properties": {
    "iso:country":"US",
    "sg:address":"1245 W 69th St",
    "sg:city":"Hialeah",
    "sg:classifiers":[
        {
            "category":"Shopping",
            "subcategory":"Gifts & Souvenirs",
            "type":"Retail Goods"
        }
    ],
    "sg:phone":"+1 305 824 3531",
    "sg:postcode":"33014",
    "sg:province":"FL",
    "sg:tags":[
        "party",
        "supply"
    ],
    "wof:name":"Alegre Birthday Co",
    "wof:placetype":"venue"
},
  "geometry": {"coordinates":[-80.308751,25.885778],"type":"Point"}
}