{
  "type": "Feature",
  "properties": {
    "addr:full":"21467 Webbwood Ave Port Charlotte FL 33954",
    "addr:postcode":"21467;33954",
    "addr:street":"Webbwood Ave",
    "iso:country":"US",
    "sg:address":"21467 Webbwood Ave",
    "sg:city":"Port Charlotte",
    "sg:classifiers":[
        {
            "category":"Professional",
            "subcategory":"Computer Services",
            "type":"Services"
        }
    ],
    "sg:phone":"+1 941 380 1033",
    "sg:postcode":"33954",
    "sg:province":"FL",
    "sg:tags":[
        "consultant",
        "designer"
    ],
    "wof:name":"Dan Dula Computer Consultant",
    "wof:placetype":"venue"
},
  "geometry": {"coordinates":[-82.092848,27.019169],"type":"Point"}
}