{
  "type": "Feature",
  "properties": {
    "iso:country":"US",
    "sg:address":"64 Sleepy Hollow Rd",
    "sg:city":"Middleburg",
    "sg:classifiers":[
        {
            "category":"Manufacturing",
            "subcategory":"Tools & Machinery",
            "type":"Manufacturing & Wholesale Goods"
        },
        {
            "category":"Farming",
            "subcategory":"Fish & Marine Products",
            "type":"Manufacturing & Wholesale Goods"
        },
        {
            "category":"Wholesale",
            "subcategory":"Machinery & Supplies",
            "type":"Manufacturing & Wholesale Goods"
        },
        {
            "category":"Building & Trades",
            "subcategory":"Construction",
            "type":"Services"
        },
        {
            "category":"Home & Garden",
            "subcategory":"Carpets & Floor Coverings",
            "type":"Retail Goods"
        }
    ],
    "sg:phone":"+1 904 276 2252",
    "sg:postcode":"32068",
    "sg:province":"FL",
    "sg:tags":[
        "used",
        "machinery-new",
        "rigger",
        "equipment",
        "erectors",
        "crane",
        "mover"
    ],
    "sg:website":"http://www.allsouthrigging.com",
    "wof:name":"All South Rigging Inc",
    "wof:placetype":"venue"
},
  "geometry": {"coordinates":[-81.766111,30.09564],"type":"Point"}
}