{
  "type": "Feature",
  "properties": {
    "iso:country":"US",
    "sg:address":"9314 NW 13th Ct",
    "sg:city":"Miami",
    "sg:classifiers":[
        {
            "category":"Building & Trades",
            "subcategory":"Plumbing",
            "type":"Services"
        }
    ],
    "sg:phone":"+1 305 597 9800",
    "sg:postcode":"33147",
    "sg:province":"FL",
    "wof:name":"Atlas Plumbing Inc",
    "wof:placetype":"venue"
},
  "geometry": {"coordinates":[-80.22104400000001,25.85935],"type":"Point"}
}