{
  "type": "Feature",
  "properties": {
    "iso:country":"US",
    "sg:address":"3760 Andover Cay Blvd",
    "sg:city":"Orlando",
    "sg:classifiers":[
        {
            "category":"Professional",
            "subcategory":"Advertising",
            "type":"Services"
        }
    ],
    "sg:phone":"+1 407 306 9691",
    "sg:postcode":"32825",
    "sg:province":"FL",
    "sg:tags":[
        "distribution"
    ],
    "wof:name":"Polyone Distribution",
    "wof:placetype":"venue"
},
  "geometry": {"coordinates":[-81.212,28.506877],"type":"Point"}
}