{
  "type": "Feature",
  "properties": {
    "addr:full":"804 S Douglas Rd Coral Gables FL 33134",
    "addr:housenumber":"804",
    "addr:postcode":"33134",
    "addr:street":"S Douglas Rd",
    "iso:country":"US",
    "sg:address":"804 S Douglas Rd",
    "sg:city":"Coral Gables",
    "sg:classifiers":[
        {
            "category":"Shopping",
            "subcategory":"Mobile Phones",
            "type":"Retail Goods"
        }
    ],
    "sg:phone":"+1 305 443 5896",
    "sg:postcode":"33134",
    "sg:province":"FL",
    "sg:website":"www.sprint.com",
    "wof:name":"Nextel Communications",
    "wof:placetype":"venue"
},
  "geometry": {"coordinates":[-80.25509599999999,25.7633],"type":"Point"}
}