{
  "type": "Feature",
  "properties": {
    "iso:country":"US",
    "sg:address":"2255 W New Haven Ave",
    "sg:city":"West Melbourne",
    "sg:classifiers":[
        {
            "category":"Wholesale",
            "subcategory":"Machinery & Supplies",
            "type":"Manufacturing & Wholesale Goods"
        }
    ],
    "sg:phone":"+1 321 952 1387",
    "sg:postcode":"32904",
    "sg:province":"FL",
    "sg:tags":[
        "salon",
        "beauty"
    ],
    "wof:name":"Sally Beauty Supply",
    "wof:placetype":"venue"
},
  "geometry": {"coordinates":[-80.658548,28.078767],"type":"Point"}
}