{
  "type": "Feature",
  "properties": {
    "addr:full":"801 E Cervantes St Pensacola FL 32501",
    "addr:housenumber":"801",
    "addr:postcode":"32501",
    "addr:street":"E Cervantes St",
    "iso:country":"US",
    "sg:address":"801 E Cervantes St",
    "sg:city":"Pensacola",
    "sg:classifiers":[
        {
            "category":"Sports & Exercise",
            "subcategory":"Gym",
            "type":"Entertainment"
        }
    ],
    "sg:phone":"+1 850 438 0111",
    "sg:postcode":"32501",
    "sg:province":"FL",
    "sg:tags":[
        "fitness",
        "physical",
        "facility"
    ],
    "wof:name":"Body Bizz Health & Fitnes Ctr",
    "wof:placetype":"venue"
},
  "geometry": {"coordinates":[-87.207087,30.423091],"type":"Point"}
}