{
  "type": "Feature",
  "properties": {
    "iso:country":"US",
    "sg:address":"520 Sabal Lake Dr Apt 108",
    "sg:city":"Longwood",
    "sg:classifiers":[
        {
            "category":"Communications",
            "subcategory":"Television Station",
            "type":"Services"
        }
    ],
    "sg:phone":"+1 407 788 6407",
    "sg:postcode":"32779",
    "sg:province":"FL",
    "sg:tags":[
        "distributor",
        "program",
        "producer"
    ],
    "sg:website":"http://www.tvsco.com",
    "wof:name":"T V S",
    "wof:placetype":"venue"
},
  "geometry": {"coordinates":[-81.41280500000001,28.700128],"type":"Point"}
}