{
  "type": "Feature",
  "properties": {
    "iso:country":"US",
    "sg:address":"707 N Franklin St",
    "sg:city":"Tampa",
    "sg:classifiers":[
        {
            "category":"Professional",
            "subcategory":"Lawyer & Legal Services",
            "type":"Services"
        }
    ],
    "sg:phone":"+1 813 221 8815",
    "sg:postcode":"33602",
    "sg:province":"FL",
    "wof:name":"Terrance A Bostic PA",
    "wof:placetype":"venue"
},
  "geometry": {"coordinates":[-82.45918,27.950637],"type":"Point"}
}