{
  "type": "Feature",
  "properties": {
    "addr:full":"115 Country Side Dr Longwood FL 32779",
    "addr:housenumber":"115",
    "addr:postcode":"32779",
    "addr:street":"Country Side Dr",
    "iso:country":"US",
    "sg:address":"115 Country Side Dr",
    "sg:city":"Longwood",
    "sg:classifiers":[
        {
            "category":"Travel",
            "subcategory":"Travel Agent",
            "type":"Entertainment"
        }
    ],
    "sg:phone":"+1 407 788 3009",
    "sg:postcode":"32779",
    "sg:province":"FL",
    "sg:tags":[
        "agency",
        "bureau"
    ],
    "sg:website":"www.cruiseone.com",
    "wof:name":"Cruise One",
    "wof:placetype":"venue"
},
  "geometry": {"coordinates":[-81.42907200000001,28.698484],"type":"Point"}
}