{
  "type": "Feature",
  "properties": {
    "iso:country":"US",
    "sg:address":"5263 Golden Gate Pkwy",
    "sg:city":"Naples",
    "sg:classifiers":[
        {
            "category":"Professional",
            "subcategory":"Accounting & Tax Preparation",
            "type":"Services"
        }
    ],
    "sg:phone":"+1 239 354 2700",
    "sg:postcode":"34116",
    "sg:province":"FL",
    "sg:tags":[
        "return",
        "filing"
    ],
    "wof:name":"Wynns International Inc",
    "wof:placetype":"venue"
},
  "geometry": {"coordinates":[-81.713432,26.175358],"type":"Point"}
}