{
  "type": "Feature",
  "properties": {
    "addr:full":"2632 Pemberton Dr Ste 104 Apopka FL 32703",
    "addr:housenumber":"2632",
    "addr:postcode":"32703",
    "addr:street":"Pemberton Dr Ste 104",
    "iso:country":"US",
    "sg:address":"2632 Pemberton Dr Ste 104",
    "sg:city":"Apopka",
    "sg:classifiers":[
        {
            "category":"Wholesale",
            "subcategory":"Non-durable Goods",
            "type":"Manufacturing & Wholesale Goods"
        }
    ],
    "sg:phone":"+1 407 538 5898",
    "sg:postcode":"32703",
    "sg:province":"FL",
    "sg:tags":[
        "sandwiches-wholesale"
    ],
    "sg:website":"http://www.osw.com",
    "wof:name":"Osw",
    "wof:placetype":"venue"
},
  "geometry": {"coordinates":[-81.45248100000001,28.639725],"type":"Point"}
}