{
  "type": "Feature",
  "properties": {
    "iso:country":"US",
    "sg:address":"2001 4th St N",
    "sg:city":"St Petersburg",
    "sg:classifiers":[
        {
            "category":"Food & Beverages",
            "subcategory":"Groceries & Convenience Stores",
            "type":"Retail Goods"
        }
    ],
    "sg:phone":"+1 727 823 6565",
    "sg:postcode":"33704",
    "sg:province":"FL",
    "sg:tags":[
        "grocer"
    ],
    "wof:name":"Shep's Food Mart",
    "wof:placetype":"venue"
},
  "geometry": {"coordinates":[-82.63858999999999,27.791273],"type":"Point"}
}