{
  "type": "Feature",
  "properties": {
    "iso:country":"US",
    "sg:address":"12888 SW 62nd Ln",
    "sg:city":"Miami",
    "sg:classifiers":[
        {
            "category":"Wholesale",
            "subcategory":"Office Equipment",
            "type":"Manufacturing & Wholesale Goods"
        }
    ],
    "sg:phone":"+1 305 470 9390",
    "sg:postcode":"33183",
    "sg:province":"FL",
    "sg:tags":[
        "equipment-wholesale",
        "manufacturer",
        "furniture"
    ],
    "wof:name":"Caribbean Copiers & Supplies Inc",
    "wof:placetype":"venue"
},
  "geometry": {"coordinates":[-80.402455,25.708582],"type":"Point"}
}