{
  "type": "Feature",
  "properties": {
    "iso:country":"US",
    "sg:address":"501 1st Ave",
    "sg:city":"Satellite Beach",
    "sg:classifiers":[
        {
            "category":"Building & Trades",
            "subcategory":"Construction",
            "type":"Services"
        }
    ],
    "sg:phone":"+1 321 777 9074",
    "sg:postcode":"32937",
    "sg:province":"FL",
    "sg:tags":[
        "concrete",
        "contractor"
    ],
    "wof:name":"D & A Concrete Pumping",
    "wof:placetype":"venue"
},
  "geometry": {"coordinates":[-80.59861600000001,28.199786],"type":"Point"}
}