{
  "type": "Feature",
  "properties": {
    "addr:full":"505 W de Leon St Tampa FL 33606",
    "addr:housenumber":"505",
    "addr:postcode":"33606",
    "addr:street":"W De Leon St",
    "iso:country":"US",
    "sg:address":"505 W de Leon St",
    "sg:city":"Tampa",
    "sg:classifiers":[
        {
            "category":"Health Services",
            "subcategory":"Doctor",
            "type":"Services"
        }
    ],
    "sg:phone":"+1 813 251 0194",
    "sg:postcode":"33606",
    "sg:province":"FL",
    "sg:tags":[
        "medicine",
        "physician",
        "surgeon",
        "internal",
        "surgeons"
    ],
    "wof:name":"Sanchez Jose A MD",
    "wof:placetype":"venue"
},
  "geometry": {"coordinates":[-82.46493599999999,27.938801],"type":"Point"}
}