{
  "type": "Feature",
  "properties": {
    "iso:country":"US",
    "sg:address":"302 W Palm Dr",
    "sg:city":"Homestead",
    "sg:classifiers":[
        {
            "category":"Banks & Credit Unions",
            "subcategory":"Bank",
            "type":"Services"
        }
    ],
    "sg:phone":"+1 305 245 1493",
    "sg:postcode":"33034",
    "sg:province":"FL",
    "sg:website":"http://www.communitybankofflorida.com",
    "wof:name":"Community Bank",
    "wof:placetype":"venue"
},
  "geometry": {"coordinates":[-80.472281,25.44799],"type":"Point"}
}