{
  "type": "Feature",
  "properties": {
    "iso:country":"US",
    "sg:address":"770 Opa Locka Blvd",
    "sg:city":"Opa Locka",
    "sg:classifiers":[
        {
            "category":"Professional",
            "subcategory":"Accounting & Tax Preparation",
            "type":"Services"
        }
    ],
    "sg:phone":"+1 305 688 6996",
    "sg:postcode":"33054",
    "sg:province":"FL",
    "sg:tags":[
        "return",
        "filing"
    ],
    "wof:name":"Taxes By Natasha",
    "wof:placetype":"venue"
},
  "geometry": {"coordinates":[-80.24999200000001,25.90034],"type":"Point"}
}