{
  "type": "Feature",
  "properties": {
    "iso:country":"US",
    "sg:address":"11 NW 33 Ct",
    "sg:city":"Gainesville",
    "sg:classifiers":[
        {
            "category":"Insurance",
            "subcategory":"Insurance Agent",
            "type":"Services"
        }
    ],
    "sg:phone":"+1 352 338 0082",
    "sg:postcode":"32607",
    "sg:province":"FL",
    "wof:name":"Edward Lacombe",
    "wof:placetype":"venue"
},
  "geometry": {"coordinates":[-82.370891,29.653061],"type":"Point"}
}