{
  "type": "Feature",
  "properties": {
    "iso:country":"US",
    "sg:address":"17402 Dona Michelle Dr",
    "sg:city":"Tampa",
    "sg:classifiers":[
        {
            "category":"Restaurant",
            "type":"Food & Drink"
        }
    ],
    "sg:phone":"+1 813 631 8699",
    "sg:postcode":"33647",
    "sg:province":"FL",
    "sg:website":"http://www.tacobell.com",
    "wof:name":"Taco Bell",
    "wof:placetype":"venue"
},
  "geometry": {"coordinates":[-82.36908,28.12534],"type":"Point"}
}