{
  "type": "Feature",
  "properties": {
    "addr:full":"36649 US Hwy 19 N Palm Harbor FL 34684",
    "addr:postcode":"36649;34684",
    "addr:street":"Us Hwy 19 N",
    "iso:country":"US",
    "sg:address":"36649 US Hwy 19 N",
    "sg:city":"Palm Harbor",
    "sg:classifiers":[
        {
            "category":"Shopping",
            "subcategory":"Clothing, Apparel, & Fashions",
            "type":"Retail Goods"
        }
    ],
    "sg:phone":"+1 727 939 0397",
    "sg:postcode":"34684",
    "sg:province":"FL",
    "sg:website":"www.renas.com",
    "wof:name":"Renas Wild Wear",
    "wof:placetype":"venue"
},
  "geometry": {"coordinates":[-82.739699,28.102824],"type":"Point"}
}