{
  "type": "Feature",
  "properties": {
    "iso:country":"US",
    "sg:address":"104 Commercial Way",
    "sg:city":"Spring Hill",
    "sg:classifiers":[
        {
            "category":"Retail",
            "subcategory":"Laundry & Dry Cleaning",
            "type":"Services"
        }
    ],
    "sg:phone":"+1 352 686 2590",
    "sg:postcode":"34606",
    "sg:province":"FL",
    "sg:tags":[
        "curtain",
        "drapery",
        "cleaners"
    ],
    "wof:name":"Mc Comb's Drapery & Furniture",
    "wof:placetype":"venue"
},
  "geometry": {"coordinates":[-82.637439,28.438574],"type":"Point"}
}