{
  "type": "Feature",
  "properties": {
    "iso:country":"US",
    "sg:address":"12399 W Dixie Hwy",
    "sg:city":"North Miami",
    "sg:classifiers":[
        {
            "category":"Travel",
            "subcategory":"Travel Agent",
            "type":"Entertainment"
        }
    ],
    "sg:phone":"+1 305 308 3623",
    "sg:postcode":"33161",
    "sg:province":"FL",
    "sg:tags":[
        "agency",
        "bureau"
    ],
    "wof:name":"Quiskeya Travel",
    "wof:placetype":"venue"
},
  "geometry": {"coordinates":[-80.18927499999999,25.88831],"type":"Point"}
}