{
  "type": "Feature",
  "properties": {
    "iso:country":"US",
    "sg:address":"6627 Forest Hill Blvd",
    "sg:city":"Greenacres",
    "sg:classifiers":[
        {
            "category":"Real Estate",
            "subcategory":"Real Estate Agent",
            "type":"Services"
        }
    ],
    "sg:phone":"+1 561 296 7844",
    "sg:postcode":"33413",
    "sg:province":"FL",
    "wof:name":"United Properties Of Florida",
    "wof:placetype":"venue"
},
  "geometry": {"coordinates":[-80.14704999999999,26.651255],"type":"Point"}
}