{
  "type": "Feature",
  "properties": {
    "addr:full":"12442 Indian Rocks Rd Largo FL 33774",
    "addr:housenumber":"12442",
    "addr:postcode":"33774",
    "addr:street":"Indian Rocks Rd",
    "iso:country":"US",
    "sg:address":"12442 Indian Rocks Rd",
    "sg:city":"Largo",
    "sg:classifiers":[
        {
            "category":"Professional",
            "subcategory":"Management & Consulting",
            "type":"Services"
        }
    ],
    "sg:phone":"+1 727 595 6200",
    "sg:postcode":"33774",
    "sg:province":"FL",
    "wof:name":"Ward Financial",
    "wof:placetype":"venue"
},
  "geometry": {"coordinates":[-82.832421,27.884024],"type":"Point"}
}