{
  "type": "Feature",
  "properties": {
    "addr:full":"5475 Bellview Ave Pensacola FL 32526",
    "addr:housenumber":"5475",
    "addr:postcode":"32526",
    "addr:street":"Bellview Ave",
    "iso:country":"US",
    "sg:address":"5475 Bellview Ave",
    "sg:city":"Pensacola",
    "sg:classifiers":[
        {
            "category":"Building & Trades",
            "subcategory":"Landscaping Services",
            "type":"Services"
        }
    ],
    "sg:phone":"+1 850 944 6862",
    "sg:postcode":"32526",
    "sg:province":"FL",
    "wof:name":"Champion Lawn Care",
    "wof:placetype":"venue"
},
  "geometry": {"coordinates":[-87.32682,30.468922],"type":"Point"}
}