{
  "type": "Feature",
  "properties": {
    "addr:full":"2184 Jog Rd Greenacres FL 33415",
    "addr:housenumber":"2184",
    "addr:postcode":"33415",
    "addr:street":"Jog Rd",
    "iso:country":"US",
    "sg:address":"2184 Jog Rd",
    "sg:city":"Greenacres",
    "sg:classifiers":[
        {
            "category":"Home & Garden",
            "subcategory":"Carpets & Floor Coverings",
            "type":"Retail Goods"
        }
    ],
    "sg:phone":"+1 561 432 3544",
    "sg:postcode":"33415",
    "sg:province":"FL",
    "sg:tags":[
        "dealer",
        "rug"
    ],
    "wof:name":"Floor Store Of The Palm Beach",
    "wof:placetype":"venue"
},
  "geometry": {"coordinates":[-80.14543399999999,26.648581],"type":"Point"}
}