{
  "type": "Feature",
  "properties": {
    "iso:country":"US",
    "sg:address":"1445 Howell Ave",
    "sg:city":"Brooksville",
    "sg:classifiers":[
        {
            "category":"Social Services",
            "type":"Services"
        }
    ],
    "sg:phone":"+1 352 799 1451",
    "sg:postcode":"34601",
    "sg:province":"FL",
    "sg:tags":[
        "senior",
        "citizen"
    ],
    "wof:name":"Heron Point Health & Rehab",
    "wof:placetype":"venue"
},
  "geometry": {"coordinates":[-82.377099,28.577163],"type":"Point"}
}