{
  "type": "Feature",
  "properties": {
    "addr:full":"4200 Lenox Ave Jacksonville FL 32205",
    "addr:housenumber":"4200",
    "addr:postcode":"32205",
    "addr:street":"Lenox Ave",
    "iso:country":"US",
    "sg:address":"4200 Lenox Ave",
    "sg:city":"Jacksonville",
    "sg:classifiers":[
        {
            "category":"Building & Trades",
            "subcategory":"Landscaping Services",
            "type":"Services"
        }
    ],
    "sg:phone":"+1 904 381 0707",
    "sg:postcode":"32205",
    "sg:province":"FL",
    "sg:tags":[
        "lawn",
        "maintenance",
        "grounds"
    ],
    "wof:name":"A C Pest Control",
    "wof:placetype":"venue"
},
  "geometry": {"coordinates":[-81.722301,30.319695],"type":"Point"}
}