{
  "type": "Feature",
  "properties": {
    "addr:full":"1702 NW 17 Ln Gainesville FL 32605",
    "addr:housenumber":"1702",
    "addr:postcode":"32605",
    "addr:street":"Nw 17 Ln",
    "iso:country":"US",
    "sg:address":"1702 NW 17 Ln",
    "sg:city":"Gainesville",
    "sg:classifiers":[
        {
            "category":"Professional",
            "subcategory":"Business Services",
            "type":"Services"
        }
    ],
    "sg:phone":"+1 352 376 8346",
    "sg:postcode":"32605",
    "sg:province":"FL",
    "sg:tags":[
        "interior",
        "consultant",
        "design",
        "decorator"
    ],
    "wof:name":"Mansell Interior Designs",
    "wof:placetype":"venue"
},
  "geometry": {"coordinates":[-82.346874,29.667283],"type":"Point"}
}