{
  "type": "Feature",
  "properties": {
    "iso:country":"US",
    "sg:address":"17875 Collins Ave",
    "sg:city":"North Miami Beach",
    "sg:classifiers":[
        {
            "category":"Restaurant",
            "type":"Food & Drink"
        }
    ],
    "sg:phone":"+1 305 466 9191",
    "sg:postcode":"33160",
    "sg:province":"FL",
    "sg:tags":[
        "italian"
    ],
    "sg:website":"www.ilmulino.com/miami.html",
    "wof:name":"Il Mulino",
    "wof:placetype":"venue"
},
  "geometry": {"coordinates":[-80.120498,25.940941],"type":"Point"}
}