{
  "type": "Feature",
  "properties": {
    "addr:full":"9075 Seminole Blvd Seminole FL 33772",
    "addr:housenumber":"9075",
    "addr:postcode":"33772",
    "addr:street":"Seminole Blvd",
    "iso:country":"US",
    "sg:address":"9075 Seminole Blvd",
    "sg:city":"Seminole",
    "sg:classifiers":[
        {
            "category":"Professional",
            "subcategory":"Lawyer & Legal Services",
            "type":"Services"
        }
    ],
    "sg:phone":"+1 727 398 0011",
    "sg:postcode":"33772",
    "sg:province":"FL",
    "sg:tags":[
        "attorney"
    ],
    "wof:name":"Timothy C Schuler",
    "wof:placetype":"venue"
},
  "geometry": {"coordinates":[-82.787004,27.85546],"type":"Point"}
}