{
  "type": "Feature",
  "properties": {
    "iso:country":"US",
    "sg:address":"1190 NE 125th St",
    "sg:city":"Miami",
    "sg:classifiers":[
        {
            "category":"Professional",
            "subcategory":"Accounting & Tax Preparation",
            "type":"Services"
        }
    ],
    "sg:phone":"+1 305 891 0112",
    "sg:postcode":"33161",
    "sg:province":"FL",
    "sg:tags":[
        "bookkeeping",
        "general"
    ],
    "wof:name":"Dade County Business Mgmt",
    "wof:placetype":"venue"
},
  "geometry": {"coordinates":[-80.17478699999999,25.890669],"type":"Point"}
}