{
  "type": "Feature",
  "properties": {
    "addr:full":"1610 Blanding Blvd Middleburg FL 32068",
    "addr:housenumber":"1610",
    "addr:postcode":"32068",
    "addr:street":"Blanding Blvd",
    "iso:country":"US",
    "sg:address":"1610 Blanding Blvd",
    "sg:city":"Middleburg",
    "sg:classifiers":[
        {
            "category":"Education",
            "subcategory":"School",
            "type":"Public Place"
        }
    ],
    "sg:phone":"+1 904 282 0504",
    "sg:postcode":"32068",
    "sg:province":"FL",
    "sg:tags":[
        "secondary"
    ],
    "sg:website":"www.annunciationcatholic.org",
    "wof:name":"Annunciation Catholic School",
    "wof:placetype":"venue"
},
  "geometry": {"coordinates":[-81.813939,30.113684],"type":"Point"}
}