{
  "type": "Feature",
  "properties": {
    "addr:full":"1727 Winter Green Blvd Winter Park FL 32792",
    "addr:housenumber":"1727",
    "addr:postcode":"32792",
    "addr:street":"Winter Green Blvd",
    "iso:country":"US",
    "sg:address":"1727 Winter Green Blvd",
    "sg:city":"Winter Park",
    "sg:classifiers":[
        {
            "category":"Professional",
            "type":"Services"
        }
    ],
    "sg:phone":"+1 407 671 0532",
    "sg:postcode":"32792",
    "sg:province":"FL",
    "sg:tags":[
        "information",
        "bureau"
    ],
    "wof:name":"Search Of Significance",
    "wof:placetype":"venue"
},
  "geometry": {"coordinates":[-81.31224899999999,28.61516],"type":"Point"}
}