{
  "type": "Feature",
  "properties": {
    "addr:full":"4911 20th Pl SW Naples FL 34116",
    "addr:housenumber":"4911",
    "addr:postcode":"34116",
    "addr:street":"20Th Pl Sw",
    "iso:country":"US",
    "sg:address":"4911 20th Pl SW",
    "sg:city":"Naples",
    "sg:classifiers":[
        {
            "category":"Education",
            "subcategory":"School",
            "type":"Public Place"
        }
    ],
    "sg:phone":"+1 239 455 1051",
    "sg:postcode":"34116",
    "sg:province":"FL",
    "wof:name":"Golden Gate Elementary School",
    "wof:placetype":"venue"
},
  "geometry": {"coordinates":[-81.704691,26.190637],"type":"Point"}
}