{
  "type": "Feature",
  "properties": {
    "iso:country":"US",
    "sg:address":"9010 SW 150th Ave",
    "sg:city":"Miami",
    "sg:classifiers":[
        {
            "category":"Building & Trades",
            "subcategory":"Cleaning & Sanitation",
            "type":"Services"
        }
    ],
    "sg:phone":"+1 305 380 0435",
    "sg:postcode":"33196",
    "sg:province":"FL",
    "sg:tags":[
        "maintenance"
    ],
    "wof:name":"Astral Cleaning Corp",
    "wof:placetype":"venue"
},
  "geometry": {"coordinates":[-80.434479,25.682414],"type":"Point"}
}