{
  "type": "Feature",
  "properties": {
    "addr:full":"14571 104th St Live Oak FL 32060",
    "addr:housenumber":"14571",
    "addr:postcode":"32060",
    "addr:street":"104Th St",
    "iso:country":"US",
    "sg:address":"14571 104th St",
    "sg:city":"Live Oak",
    "sg:classifiers":[
        {
            "category":"Building & Trades",
            "subcategory":"Construction",
            "type":"Services"
        }
    ],
    "sg:phone":"+1 386 364 6485",
    "sg:postcode":"32060",
    "sg:province":"FL",
    "sg:tags":[
        "insulation",
        "heat",
        "contractor"
    ],
    "wof:name":"Morgan's Insulation",
    "wof:placetype":"venue"
},
  "geometry": {"coordinates":[-83.06074700000001,30.260604],"type":"Point"}
}