{
  "type": "Feature",
  "properties": {
    "addr:full":"6106 Siesta Ln Port Richey FL 34668",
    "addr:housenumber":"6106",
    "addr:postcode":"34668",
    "addr:street":"Siesta Ln",
    "iso:country":"US",
    "sg:address":"6106 Siesta Ln",
    "sg:city":"Port Richey",
    "sg:classifiers":[
        {
            "category":"Retail",
            "subcategory":"Auto Repair",
            "type":"Services"
        }
    ],
    "sg:phone":"+1 727 843 0900",
    "sg:postcode":"34668",
    "sg:province":"FL",
    "sg:tags":[
        "wrecker"
    ],
    "wof:name":"National Auto Towing Svc",
    "wof:placetype":"venue"
},
  "geometry": {"coordinates":[-82.714894,28.277254],"type":"Point"}
}