{
  "type": "Feature",
  "properties": {
    "addr:full":"7718 N Florida Ave Tampa FL 33604",
    "addr:housenumber":"7718",
    "addr:postcode":"33604",
    "addr:street":"N Florida Ave",
    "iso:country":"US",
    "sg:address":"7718 N Florida Ave",
    "sg:city":"Tampa",
    "sg:classifiers":[
        {
            "category":"Wholesale",
            "subcategory":"Office Equipment",
            "type":"Manufacturing & Wholesale Goods"
        }
    ],
    "sg:phone":"+1 813 238 6384",
    "sg:postcode":"33604",
    "sg:province":"FL",
    "wof:name":"1908 Cash Register Co",
    "wof:placetype":"venue"
},
  "geometry": {"coordinates":[-82.459575,28.018734],"type":"Point"}
}