{
  "type": "Feature",
  "properties": {
    "addr:full":"12200 Washington St Pembroke Pines FL 33025",
    "addr:housenumber":"12200",
    "addr:postcode":"33025",
    "addr:street":"Washington St",
    "iso:country":"US",
    "sg:address":"12200 Washington St",
    "sg:city":"Pembroke Pines",
    "sg:classifiers":[
        {
            "category":"Real Estate",
            "subcategory":"Real Estate Agent",
            "type":"Services"
        }
    ],
    "sg:phone":"+1 954 436 6408",
    "sg:postcode":"33025",
    "sg:province":"FL",
    "sg:tags":[
        "management"
    ],
    "wof:name":"Waterton Property Management",
    "wof:placetype":"venue"
},
  "geometry": {"coordinates":[-80.306781,26.000474],"type":"Point"}
}