{
  "type": "Feature",
  "properties": {
    "iso:country":"US",
    "sg:address":"1216 SE 2nd St",
    "sg:city":"Pompano Beach",
    "sg:classifiers":[
        {
            "category":"Real Estate",
            "subcategory":"Real Estate Operator",
            "type":"Services"
        }
    ],
    "sg:phone":"+1 954 942 0035",
    "sg:postcode":"33060",
    "sg:province":"FL",
    "sg:tags":[
        "building",
        "nonresidential"
    ],
    "wof:name":"Nies Realty",
    "wof:placetype":"venue"
},
  "geometry": {"coordinates":[-80.11083000000001,26.229935],"type":"Point"}
}