{
  "type": "Feature",
  "properties": {
    "addr:full":"5622 NW 117th Ave Coral Springs FL 33076",
    "addr:housenumber":"5622",
    "addr:postcode":"33076",
    "addr:street":"Nw 117Th Ave",
    "iso:country":"US",
    "sg:address":"5622 NW 117th Ave",
    "sg:city":"Coral Springs",
    "sg:classifiers":[
        {
            "category":"Retail",
            "subcategory":"Laundry & Dry Cleaning",
            "type":"Services"
        }
    ],
    "sg:phone":"+1 954 257 9062",
    "sg:postcode":"33076",
    "sg:province":"FL",
    "sg:tags":[
        "valet"
    ],
    "wof:name":"Universal Valet Parking",
    "wof:placetype":"venue"
},
  "geometry": {"coordinates":[-80.283963,26.301053],"type":"Point"}
}