{
  "type": "Feature",
  "properties": {
    "addr:full":"4570 NW 93rd Doral Ct Miami FL 33178",
    "addr:housenumber":"4570",
    "addr:postcode":"33178",
    "addr:street":"Nw 93Rd Doral Ct",
    "iso:country":"US",
    "sg:address":"4570 NW 93rd Doral Ct",
    "sg:city":"Miami",
    "sg:classifiers":[
        {
            "category":"Shopping",
            "subcategory":"Clothing, Apparel, & Fashions",
            "type":"Retail Goods"
        }
    ],
    "sg:phone":"+1 305 471 7873",
    "sg:postcode":"33178",
    "sg:province":"FL",
    "sg:tags":[
        "hospital",
        "wear",
        "specialty"
    ],
    "wof:name":"Sharing For Kids",
    "wof:placetype":"venue"
},
  "geometry": {"coordinates":[-80.348381,25.816885],"type":"Point"}
}