{
  "type": "Feature",
  "properties": {
    "iso:country":"US",
    "sg:address":"5542 Lake Howell Rd",
    "sg:city":"Winter Park",
    "sg:classifiers":[
        {
            "category":"Manufacturing",
            "subcategory":"Jewelry",
            "type":"Manufacturing & Wholesale Goods"
        }
    ],
    "sg:phone":"+1 407 677 6979",
    "sg:postcode":"32792",
    "sg:province":"FL",
    "sg:tags":[
        "precious",
        "metal",
        "mfg"
    ],
    "wof:name":"Amyx & Christy Inc",
    "wof:placetype":"venue"
},
  "geometry": {"coordinates":[-81.324038,28.622909],"type":"Point"}
}