{
  "type": "Feature",
  "properties": {
    "addr:full":"2488 N Federal Hwy Pompano Beach FL 33064",
    "addr:housenumber":"2488",
    "addr:postcode":"33064",
    "addr:street":"N Federal Hwy",
    "iso:country":"US",
    "sg:address":"2488 N Federal Hwy",
    "sg:city":"Pompano Beach",
    "sg:classifiers":[
        {
            "category":"Restaurant",
            "type":"Food & Drink"
        },
        {
            "category":"Ice Cream",
            "type":"Food & Drink"
        }
    ],
    "sg:menulink":"http://www.allmenus.com/fl/deerfield-beach/172322-dairy-queen/menu/",
    "sg:phone":"+1 954 943 8390",
    "sg:postcode":"33064",
    "sg:province":"FL",
    "sg:tags":[
        "burger",
        "american",
        "ice",
        "cream"
    ],
    "wof:name":"Dairy Queen",
    "wof:placetype":"venue"
},
  "geometry": {"coordinates":[-80.099155,26.262358],"type":"Point"}
}