{
  "type": "Feature",
  "properties": {
    "addr:full":"1780 Oberry Ct Kissimmee FL 34746",
    "addr:housenumber":"1780",
    "addr:postcode":"34746",
    "addr:street":"Oberry Ct",
    "iso:country":"US",
    "sg:address":"1780 Oberry Ct",
    "sg:city":"Kissimmee",
    "sg:classifiers":[
        {
            "category":"Building & Trades",
            "subcategory":"Landscaping Services",
            "type":"Services"
        }
    ],
    "sg:phone":"+1 407 933 1589",
    "sg:postcode":"34746",
    "sg:province":"FL",
    "wof:name":"Toads Lawn Care Inc",
    "wof:placetype":"venue"
},
  "geometry": {"coordinates":[-81.44529300000001,28.254445],"type":"Point"}
}