{
  "type": "Feature",
  "properties": {
    "iso:country":"US",
    "sg:address":"9542 W Aberdare Ave",
    "sg:city":"Jacksonville",
    "sg:classifiers":[
        {
            "category":"Building & Trades",
            "subcategory":"Landscaping Services",
            "type":"Services"
        }
    ],
    "sg:phone":"+1 904 765 3241",
    "sg:postcode":"32208",
    "sg:province":"FL",
    "sg:tags":[
        "landscape"
    ],
    "wof:name":"T Williams Landscaping",
    "wof:placetype":"venue"
},
  "geometry": {"coordinates":[-81.722994,30.410404],"type":"Point"}
}