{
  "type": "Feature",
  "properties": {
    "addr:full":"1942 W New Hampshire St Orlando FL 32804",
    "addr:housenumber":"1942",
    "addr:postcode":"32804",
    "addr:street":"W New Hampshire St",
    "iso:country":"US",
    "sg:address":"1942 W New Hampshire St",
    "sg:city":"Orlando",
    "sg:classifiers":[
        {
            "category":"Professional",
            "subcategory":"Advertising",
            "type":"Services"
        },
        {
            "category":"Wholesale",
            "subcategory":"Auto Parts",
            "type":"Manufacturing & Wholesale Goods"
        },
        {
            "category":"Retail",
            "subcategory":"Auto Repair",
            "type":"Services"
        }
    ],
    "sg:phone":"+1 407 843 1900",
    "sg:postcode":"32804",
    "sg:province":"FL",
    "sg:tags":[
        "equipment",
        "injection",
        "truck",
        "engines-diesel-fuel",
        "accessory"
    ],
    "sg:website":"http://www.truckpro.com/referral/yellowpages.html",
    "wof:name":"TruckPro",
    "wof:placetype":"venue"
},
  "geometry": {"coordinates":[-81.407865,28.567196],"type":"Point"}
}