{
  "type": "Feature",
  "properties": {
    "iso:country":"US",
    "sg:address":"602 19th Ave W",
    "sg:city":"Bradenton",
    "sg:classifiers":[
        {
            "category":"Retail",
            "subcategory":"Auto Repair",
            "type":"Services"
        }
    ],
    "sg:phone":"+1 941 748 1050",
    "sg:postcode":"34205",
    "sg:province":"FL",
    "sg:tags":[
        "repairing",
        "automobile"
    ],
    "wof:name":"Bob's Auto Repair",
    "wof:placetype":"venue"
},
  "geometry": {"coordinates":[-82.567328,27.482683],"type":"Point"}
}