{
  "type": "Feature",
  "properties": {
    "iso:country":"US",
    "sg:address":"10527 Parkcrest Dr",
    "sg:city":"Tampa",
    "sg:classifiers":[
        {
            "category":"Building & Trades",
            "subcategory":"Construction",
            "type":"Services"
        }
    ],
    "sg:phone":"+1 813 264 6855",
    "sg:postcode":"33624",
    "sg:province":"FL",
    "sg:tags":[
        "contractor"
    ],
    "wof:name":"Miguel Jorva",
    "wof:placetype":"venue"
},
  "geometry": {"coordinates":[-82.528553,28.04464],"type":"Point"}
}