{
  "type": "Feature",
  "properties": {
    "iso:country":"US",
    "sg:address":"6920 Barbara Jean Ln",
    "sg:city":"Polk City",
    "sg:classifiers":[
        {
            "category":"Building & Trades",
            "subcategory":"Construction",
            "type":"Services"
        }
    ],
    "sg:phone":"+1 863 984 4007",
    "sg:postcode":"33868",
    "sg:province":"FL",
    "sg:tags":[
        "roofing",
        "contractor"
    ],
    "wof:name":"O'Neal Roofing Co-Lakeland Inc",
    "wof:placetype":"venue"
},
  "geometry": {"coordinates":[-81.827564,28.25152],"type":"Point"}
}