{
  "type": "Feature",
  "properties": {
    "addr:full":"260 19th St SW Naples FL 34117",
    "addr:housenumber":"260",
    "addr:postcode":"34117",
    "addr:street":"19Th St Sw",
    "iso:country":"US",
    "sg:address":"260 19th St SW",
    "sg:city":"Naples",
    "sg:classifiers":[
        {
            "category":"Building & Trades",
            "subcategory":"Construction",
            "type":"Services"
        },
        {
            "category":"Building & Trades",
            "subcategory":"Landscaping Services",
            "type":"Services"
        }
    ],
    "sg:phone":"+1 239 455 0036",
    "sg:postcode":"34117",
    "sg:province":"FL",
    "sg:tags":[
        "masonry",
        "contractor"
    ],
    "wof:name":"Nelson Steve Masonry",
    "wof:placetype":"venue"
},
  "geometry": {"coordinates":[-81.64491,26.226801],"type":"Point"}
}