{
  "type": "Feature",
  "properties": {
    "addr:full":"26259 US Hwy 19 Clearwater FL 33761",
    "addr:postcode":"26259;33761",
    "addr:street":"Us Hwy 19",
    "iso:country":"US",
    "sg:address":"26259 US Hwy 19",
    "sg:city":"Clearwater",
    "sg:classifiers":[
        {
            "category":"Real Estate",
            "subcategory":"Real Estate Agent",
            "type":"Services"
        }
    ],
    "sg:phone":"+1 727 771 9127",
    "sg:postcode":"33761",
    "sg:province":"FL",
    "wof:name":"Lori Polin",
    "wof:placetype":"venue"
},
  "geometry": {"coordinates":[-82.73218199999999,28.010308],"type":"Point"}
}