{
  "type": "Feature",
  "properties": {
    "addr:full":"2625 Edgewater Dr Orlando FL 32804",
    "addr:housenumber":"2625",
    "addr:postcode":"32804",
    "addr:street":"Edgewater Dr",
    "iso:country":"US",
    "sg:address":"2625 Edgewater Dr",
    "sg:city":"Orlando",
    "sg:classifiers":[
        {
            "category":"Restaurant",
            "type":"Food & Drink"
        }
    ],
    "sg:phone":"+1 407 423 0081",
    "sg:postcode":"32804",
    "sg:province":"FL",
    "sg:tags":[
        "american",
        "soul"
    ],
    "sg:website":"http://www.adairsrestaurant.com",
    "wof:name":"Adair's",
    "wof:placetype":"venue"
},
  "geometry": {"coordinates":[-81.389511,28.5753],"type":"Point"}
}