{
  "type": "Feature",
  "properties": {
    "addr:full":"160 13th St NW Naples FL 34120",
    "addr:housenumber":"160",
    "addr:postcode":"34120",
    "addr:street":"13Th St Nw",
    "iso:country":"US",
    "sg:address":"160 13th St NW",
    "sg:city":"Naples",
    "sg:classifiers":[
        {
            "category":"Airport",
            "type":"Transportation"
        }
    ],
    "sg:phone":"+1 239 643 1717",
    "sg:postcode":"34120",
    "sg:province":"FL",
    "sg:tags":[
        "aircraft",
        "maintenance"
    ],
    "wof:name":"Naples Air Ctr Inc",
    "wof:placetype":"venue"
},
  "geometry": {"coordinates":[-81.63306799999999,26.243443],"type":"Point"}
}