{
  "type": "Feature",
  "properties": {
    "iso:country":"US",
    "sg:address":"8270 NW 66th St",
    "sg:city":"Miami",
    "sg:classifiers":[
        {
            "category":"Wholesale",
            "subcategory":"Machinery & Supplies",
            "type":"Manufacturing & Wholesale Goods"
        }
    ],
    "sg:phone":"+1 305 592 5600",
    "sg:postcode":"33166",
    "sg:province":"FL",
    "sg:tags":[
        "equipment",
        "part",
        "tractor",
        "contractor"
    ],
    "sg:website":"http://www.tigerparts.com",
    "wof:name":"Construction Equipment Services Inc",
    "wof:placetype":"venue"
},
  "geometry": {"coordinates":[-80.331408,25.833456],"type":"Point"}
}