{
  "type": "Feature",
  "properties": {
    "addr:full":"4595 W Hwy 316 Reddick FL 32686",
    "addr:housenumber":"4595",
    "addr:postcode":"32686",
    "addr:street":"W Hwy 316",
    "iso:country":"US",
    "sg:address":"4595 W Hwy 316",
    "sg:city":"Reddick",
    "sg:classifiers":[
        {
            "category":"Education",
            "subcategory":"School",
            "type":"Public Place"
        }
    ],
    "sg:phone":"+1 352 671 6070",
    "sg:postcode":"32686",
    "sg:province":"FL",
    "wof:name":"Reddick-Cllier Elementary Schl",
    "wof:placetype":"venue"
},
  "geometry": {"coordinates":[-82.19990199999999,29.366969],"type":"Point"}
}