{
  "type": "Feature",
  "properties": {
    "iso:country":"US",
    "sg:address":"701 Cypress Gardens Blvd",
    "sg:city":"Winter Haven",
    "sg:classifiers":[
        {
            "category":"Shopping",
            "subcategory":"Florist",
            "type":"Retail Goods"
        }
    ],
    "sg:phone":"+1 863 291 3112",
    "sg:postcode":"33880",
    "sg:province":"FL",
    "wof:name":"A Heavenly Scent Florist",
    "wof:placetype":"venue"
},
  "geometry": {"coordinates":[-81.717052,28.003986],"type":"Point"}
}