{
  "type": "Feature",
  "properties": {
    "addr:full":"93 NW 166th St Miami FL 33169",
    "addr:housenumber":"93",
    "addr:postcode":"33169",
    "addr:street":"Nw 166Th St",
    "iso:country":"US",
    "sg:address":"93 NW 166th St",
    "sg:city":"Miami",
    "sg:classifiers":[
        {
            "category":"Wholesale",
            "subcategory":"Hardware",
            "type":"Manufacturing & Wholesale Goods"
        }
    ],
    "sg:phone":"+1 305 947 4852",
    "sg:postcode":"33169",
    "sg:province":"FL",
    "sg:tags":[
        "hardware-wholesale",
        "manufacturer"
    ],
    "wof:name":"Pasy Dld & Associates",
    "wof:placetype":"venue"
},
  "geometry": {"coordinates":[-80.20217100000001,25.927085],"type":"Point"}
}