{
  "type": "Feature",
  "properties": {
    "iso:country":"US",
    "sg:address":"7620 Old Polk City Rd",
    "sg:city":"Lakeland",
    "sg:classifiers":[
        {
            "category":"Personal",
            "subcategory":"Beauty Salon",
            "type":"Services"
        }
    ],
    "sg:phone":"+1 863 853 4068",
    "sg:postcode":"33809",
    "sg:province":"FL",
    "wof:name":"Mark's Hair Stylist",
    "wof:placetype":"venue"
},
  "geometry": {"coordinates":[-81.939311,28.128485],"type":"Point"}
}