{
  "type": "Feature",
  "properties": {
    "addr:full":"19889 SW 280th St Homestead FL 33031",
    "addr:housenumber":"19889",
    "addr:postcode":"33031",
    "addr:street":"Sw 280Th St",
    "iso:country":"US",
    "sg:address":"19889 SW 280th St",
    "sg:city":"Homestead",
    "sg:classifiers":[
        {
            "category":"Freight",
            "type":"Transportation"
        }
    ],
    "sg:phone":"+1 305 245 4524",
    "sg:postcode":"33031",
    "sg:province":"FL",
    "sg:tags":[
        "transport",
        "boat"
    ],
    "wof:name":"Custom Boat Transporters Inc",
    "wof:placetype":"venue"
},
  "geometry": {"coordinates":[-80.510818,25.506207],"type":"Point"}
}