{
  "type": "Feature",
  "properties": {
    "iso:country":"US",
    "sg:address":"581 S Duncan Ave",
    "sg:city":"Clearwater",
    "sg:classifiers":[
        {
            "category":"Professional",
            "subcategory":"Lawyer & Legal Services",
            "type":"Services"
        }
    ],
    "sg:phone":"+1 727 442 6773",
    "sg:postcode":"33756",
    "sg:province":"FL",
    "sg:tags":[
        "attorney"
    ],
    "wof:name":"Francis M Curran",
    "wof:placetype":"venue"
},
  "geometry": {"coordinates":[-82.76683800000001,27.960312],"type":"Point"}
}