{
  "type": "Feature",
  "properties": {
    "addr:full":"1995 E Hallandale Beach Blvd Hallandale Beach FL 33009",
    "addr:housenumber":"1995",
    "addr:postcode":"33009",
    "addr:street":"E Hallandale Beach Blvd",
    "iso:country":"US",
    "sg:address":"1995 E Hallandale Beach Blvd",
    "sg:city":"Hallandale Beach",
    "sg:classifiers":[
        {
            "category":"Banks & Credit Unions",
            "subcategory":"Bank",
            "type":"Services"
        }
    ],
    "sg:phone":"+1 954 454 5000",
    "sg:postcode":"33009",
    "sg:province":"FL",
    "sg:website":"www.citynational.com",
    "wof:name":"City National Bank Of Fl",
    "wof:placetype":"venue"
},
  "geometry": {"coordinates":[-80.128393,25.986197],"type":"Point"}
}