{
  "type": "Feature",
  "properties": {
    "iso:country":"US",
    "sg:address":"1395 Brickell Ave Ste 800",
    "sg:city":"Miami",
    "sg:classifiers":[
        {
            "category":"Health Services",
            "subcategory":"Clinic",
            "type":"Services"
        },
        {
            "category":"Health Services",
            "subcategory":"Health Practitioner",
            "type":"Services"
        },
        {
            "category":"Health Services",
            "subcategory":"Chiropractor",
            "type":"Services"
        }
    ],
    "sg:phone":"+1 305 459 1560",
    "sg:postcode":"33131",
    "sg:province":"FL",
    "sg:tags":[
        "nutritionist",
        "loss",
        "weight"
    ],
    "sg:website":"www.functionalholisticwellness.com",
    "wof:name":"Functional Holistic Wellness",
    "wof:placetype":"venue"
},
  "geometry": {"coordinates":[-80.19121199999999,25.76058],"type":"Point"}
}