{
  "type": "Feature",
  "properties": {
    "iso:country":"US",
    "sg:address":"15518 N Dale Mabry Hwy",
    "sg:city":"Tampa",
    "sg:classifiers":[
        {
            "category":"Banks & Credit Unions",
            "subcategory":"Bank",
            "type":"Services"
        }
    ],
    "sg:phone":"+1 813 960 5591",
    "sg:postcode":"33618",
    "sg:province":"FL",
    "wof:name":"Wachovia Bank",
    "wof:placetype":"venue"
},
  "geometry": {"coordinates":[-82.50221500000001,28.093853],"type":"Point"}
}