{
  "type": "Feature",
  "properties": {
    "iso:country":"US",
    "sg:address":"1651 NW 69th St",
    "sg:city":"Tamarac",
    "sg:classifiers":[
        {
            "category":"Wholesale",
            "subcategory":"Toys & Hobbies",
            "type":"Manufacturing & Wholesale Goods"
        }
    ],
    "sg:phone":"+1 954 972 9644",
    "sg:postcode":"33069",
    "sg:province":"FL",
    "sg:tags":[
        "wholesaler"
    ],
    "wof:name":"R M Wholesale Copiers Inc",
    "wof:placetype":"venue"
},
  "geometry": {"coordinates":[-80.16784800000001,26.2102],"type":"Point"}
}