{
  "type": "Feature",
  "properties": {
    "iso:country":"US",
    "sg:address":"1040 US Hwy 17",
    "sg:city":"Bartow",
    "sg:classifiers":[
        {
            "category":"Retail",
            "subcategory":"Repair Shop",
            "type":"Services"
        },
        {
            "category":"Manufacturing",
            "subcategory":"Apparel",
            "type":"Manufacturing & Wholesale Goods"
        }
    ],
    "sg:phone":"+1 863 519 9610",
    "sg:postcode":"33830",
    "sg:province":"FL",
    "sg:tags":[
        "canvas",
        "product",
        "upholsterer",
        "mfg"
    ],
    "wof:name":"Tuna's Marine Canvas",
    "wof:placetype":"venue"
},
  "geometry": {"coordinates":[-81.830281,27.903814],"type":"Point"}
}