{
  "type": "Feature",
  "properties": {
    "iso:country":"US",
    "sg:address":"4220 Lake Worth Rd",
    "sg:city":"Lake Worth",
    "sg:classifiers":[
        {
            "category":"Professional",
            "subcategory":"Employment Agencies",
            "type":"Services"
        }
    ],
    "sg:phone":"+1 561 963 3125",
    "sg:postcode":"33461",
    "sg:province":"FL",
    "wof:name":"Work Force Development Center",
    "wof:placetype":"venue"
},
  "geometry": {"coordinates":[-80.106702,26.618164],"type":"Point"}
}