{
  "type": "Feature",
  "properties": {
    "addr:full":"111 2nd Ave NE St Petersburg FL 33701",
    "addr:housenumber":"111",
    "addr:postcode":"33701",
    "addr:street":"2Nd Ave Ne",
    "iso:country":"US",
    "sg:address":"111 2nd Ave NE",
    "sg:city":"St Petersburg",
    "sg:classifiers":[
        {
            "category":"Banks & Credit Unions",
            "subcategory":"Investment Brokerage",
            "type":"Services"
        }
    ],
    "sg:phone":"+1 727 898 1500",
    "sg:postcode":"33701",
    "sg:province":"FL",
    "sg:tags":[
        "management"
    ],
    "wof:name":"Pritchard Hubble & Herr",
    "wof:placetype":"venue"
},
  "geometry": {"coordinates":[-82.63287099999999,27.773467],"type":"Point"}
}