{
  "type": "Feature",
  "properties": {
    "iso:country":"US",
    "sg:address":"10069 Sunset Strip",
    "sg:city":"Sunrise",
    "sg:classifiers":[
        {
            "category":"Recreation",
            "type":"Entertainment"
        }
    ],
    "sg:phone":"+1 954 748 5804",
    "sg:postcode":"33322",
    "sg:province":"FL",
    "sg:tags":[
        "paint",
        "ball",
        "sport"
    ],
    "wof:name":"Ultimate Paintball Two",
    "wof:placetype":"venue"
},
  "geometry": {"coordinates":[-80.283948,26.152943],"type":"Point"}
}