{
  "type": "Feature",
  "properties": {
    "addr:full":"8496 Palm Pkwy Orlando FL 32836",
    "addr:housenumber":"8496",
    "addr:postcode":"32836",
    "addr:street":"Palm Pkwy",
    "iso:country":"US",
    "sg:address":"8496 Palm Pkwy",
    "sg:city":"Orlando",
    "sg:classifiers":[
        {
            "category":"Restaurant",
            "type":"Food & Drink"
        }
    ],
    "sg:menulink":"http://www.allmenus.com/fl/southwest-orange/33121-the-crab-house/menu/",
    "sg:phone":"+1 407 239 1888",
    "sg:postcode":"32836",
    "sg:province":"FL",
    "sg:tags":[
        "seafood",
        "american"
    ],
    "wof:name":"The Crab House",
    "wof:placetype":"venue"
},
  "geometry": {"coordinates":[-81.49961999999999,28.386695],"type":"Point"}
}