{
  "type": "Feature",
  "properties": {
    "addr:full":"6982 SW 19th Pl Pompano Beach FL 33068",
    "addr:housenumber":"6982",
    "addr:postcode":"33068",
    "addr:street":"Sw 19Th Pl",
    "iso:country":"US",
    "sg:address":"6982 SW 19th Pl",
    "sg:city":"Pompano Beach",
    "sg:classifiers":[
        {
            "category":"Building & Trades",
            "subcategory":"Construction",
            "type":"Services"
        }
    ],
    "sg:phone":"+1 954 978 9709",
    "sg:postcode":"33068",
    "sg:province":"FL",
    "sg:tags":[
        "floor",
        "laying",
        "contractor"
    ],
    "wof:name":"Carlos Tamayo",
    "wof:placetype":"venue"
},
  "geometry": {"coordinates":[-80.21854500000001,26.202991],"type":"Point"}
}