{
  "type": "Feature",
  "properties": {
    "iso:country":"US",
    "sg:address":"4404 Blountstown Hwy",
    "sg:city":"Tallahassee",
    "sg:classifiers":[
        {
            "category":"Wholesale",
            "subcategory":"Auto Parts",
            "type":"Manufacturing & Wholesale Goods"
        }
    ],
    "sg:phone":"+1 850 576 3500",
    "sg:postcode":"32304",
    "sg:province":"FL",
    "sg:tags":[
        "equipment",
        "truck"
    ],
    "wof:name":"Truck Pro",
    "wof:placetype":"venue"
},
  "geometry": {"coordinates":[-84.35626499999999,30.434969],"type":"Point"}
}