{
  "type": "Feature",
  "properties": {
    "iso:country":"US",
    "sg:address":"237 Troy St NE",
    "sg:city":"Fort Walton Beach",
    "sg:classifiers":[
        {
            "category":"Personal",
            "subcategory":"Beauty Salon",
            "type":"Services"
        }
    ],
    "sg:phone":"+1 850 243 7755",
    "sg:postcode":"32548",
    "sg:province":"FL",
    "sg:tags":[
        "shop"
    ],
    "wof:name":"Harrelson & Lambeth Inc",
    "wof:placetype":"venue"
},
  "geometry": {"coordinates":[-86.608417,30.423067],"type":"Point"}
}