{
  "type": "Feature",
  "properties": {
    "iso:country":"US",
    "sg:address":"1287 Cheney Hwy",
    "sg:city":"Titusville",
    "sg:classifiers":[
        {
            "category":"Building & Trades",
            "subcategory":"Cleaning & Sanitation",
            "type":"Services"
        }
    ],
    "sg:phone":"+1 321 385 2359",
    "sg:postcode":"32780",
    "sg:province":"FL",
    "sg:tags":[
        "maintenance"
    ],
    "wof:name":"Jacqueline McKenzie Cleaning",
    "wof:placetype":"venue"
},
  "geometry": {"coordinates":[-80.821375,28.557722],"type":"Point"}
}