{
  "type": "Feature",
  "properties": {
    "iso:country":"US",
    "sg:address":"100 W Citrus St",
    "sg:city":"Altamonte Springs",
    "sg:classifiers":[
        {
            "category":"Professional",
            "subcategory":"Lawyer & Legal Services",
            "type":"Services"
        }
    ],
    "sg:phone":"+1 407 772 0900",
    "sg:postcode":"32714",
    "sg:province":"FL",
    "wof:name":"Gary E Massey PA",
    "wof:placetype":"venue"
},
  "geometry": {"coordinates":[-81.39030099999999,28.674576],"type":"Point"}
}