{
  "type": "Feature",
  "properties": {
    "iso:country":"US",
    "sg:address":"4075 NW 19th Ter",
    "sg:city":"Fort Lauderdale",
    "sg:classifiers":[
        {
            "category":"Retail",
            "subcategory":"Car Wash",
            "type":"Services"
        }
    ],
    "sg:phone":"+1 954 484 3938",
    "sg:postcode":"33309",
    "sg:province":"FL",
    "sg:tags":[
        "carwash"
    ],
    "wof:name":"Wise Wash & Wax",
    "wof:placetype":"venue"
},
  "geometry": {"coordinates":[-80.16866400000001,26.177932],"type":"Point"}
}