{
  "type": "Feature",
  "properties": {
    "addr:full":"2314 Holly Ridge Dr Ocoee FL 34761",
    "addr:housenumber":"2314",
    "addr:postcode":"34761",
    "addr:street":"Holly Ridge Dr",
    "iso:country":"US",
    "sg:address":"2314 Holly Ridge Dr",
    "sg:city":"Ocoee",
    "sg:classifiers":[
        {
            "category":"Professional",
            "subcategory":"Accounting & Tax Preparation",
            "type":"Services"
        }
    ],
    "sg:phone":"+1 407 654 0749",
    "sg:postcode":"34761",
    "sg:province":"FL",
    "wof:name":"Gillen Consulting",
    "wof:placetype":"venue"
},
  "geometry": {"coordinates":[-81.54673,28.535832],"type":"Point"}
}