{
  "type": "Feature",
  "properties": {
    "addr:full":"8445 SW 54th Ct Miami FL 33143",
    "addr:housenumber":"8445",
    "addr:postcode":"33143",
    "addr:street":"Sw 54Th Ct",
    "iso:country":"US",
    "sg:address":"8445 SW 54th Ct",
    "sg:city":"Miami",
    "sg:classifiers":[
        {
            "category":"Real Estate",
            "subcategory":"Real Estate Operator",
            "type":"Services"
        }
    ],
    "sg:phone":"+1 305 667 8920",
    "sg:postcode":"33143",
    "sg:province":"FL",
    "sg:tags":[
        "building",
        "nonresidential"
    ],
    "wof:name":"Santa Maria Shopping Ctr",
    "wof:placetype":"venue"
},
  "geometry": {"coordinates":[-80.281847,25.692554],"type":"Point"}
}