{
  "type": "Feature",
  "properties": {
    "addr:full":"2685 Executive Park Dr Fort Lauderdale FL 33331",
    "addr:housenumber":"2685",
    "addr:postcode":"33331",
    "addr:street":"Executive Park Dr",
    "iso:country":"US",
    "sg:address":"2685 Executive Park Dr",
    "sg:city":"Fort Lauderdale",
    "sg:classifiers":[
        {
            "category":"Professional",
            "subcategory":"Employment Agencies",
            "type":"Services"
        }
    ],
    "sg:phone":"+1 954 659 0010",
    "sg:postcode":"33331",
    "sg:province":"FL",
    "sg:tags":[
        "help",
        "supply"
    ],
    "wof:name":"Medical Staffing Network Inc",
    "wof:placetype":"venue"
},
  "geometry": {"coordinates":[-80.372803,26.085131],"type":"Point"}
}