{
  "type": "Feature",
  "properties": {
    "iso:country":"US",
    "sg:address":"812 Maydell Dr",
    "sg:city":"Tampa",
    "sg:classifiers":[
        {
            "category":"Social Services",
            "subcategory":"Child Care",
            "type":"Services"
        }
    ],
    "sg:phone":"+1 813 621 2838",
    "sg:postcode":"33619",
    "sg:province":"FL",
    "sg:tags":[
        "day"
    ],
    "wof:name":"Wrights Head Start",
    "wof:placetype":"venue"
},
  "geometry": {"coordinates":[-82.38547699999999,27.939926],"type":"Point"}
}