{
  "type": "Feature",
  "properties": {
    "addr:full":"660 US Hwy 92 Longwood FL 32750",
    "addr:housenumber":"660",
    "addr:postcode":"32750",
    "addr:street":"Us Hwy 92",
    "iso:country":"US",
    "sg:address":"660 US Hwy 92",
    "sg:city":"Longwood",
    "sg:classifiers":[
        {
            "category":"Retail",
            "subcategory":"Repair Shop",
            "type":"Services"
        }
    ],
    "sg:phone":"+1 407 830 5397",
    "sg:postcode":"32750",
    "sg:province":"FL",
    "sg:tags":[
        "lock",
        "safe",
        "key",
        "locksmith"
    ],
    "wof:name":"A-Aaron Locksmiths",
    "wof:placetype":"venue"
},
  "geometry": {"coordinates":[-81.32640000000001,28.70763],"type":"Point"}
}