{
  "type": "Feature",
  "properties": {
    "addr:full":"1221 NW 76th Ave Fort Lauderdale FL 33322",
    "addr:housenumber":"1221",
    "addr:postcode":"33322",
    "addr:street":"Nw 76Th Ave",
    "iso:country":"US",
    "sg:address":"1221 NW 76th Ave",
    "sg:city":"Fort Lauderdale",
    "sg:classifiers":[
        {
            "category":"Professional",
            "subcategory":"Business Services",
            "type":"Services"
        }
    ],
    "sg:phone":"+1 954 723 0161",
    "sg:postcode":"33322",
    "sg:province":"FL",
    "wof:name":"Benny & Steph Inc",
    "wof:placetype":"venue"
},
  "geometry": {"coordinates":[-80.251627,26.139974],"type":"Point"}
}