{
  "type": "Feature",
  "properties": {
    "addr:full":"7020 Anderson Rd Tampa FL 33634",
    "addr:housenumber":"7020",
    "addr:postcode":"33634",
    "addr:street":"Anderson Rd",
    "iso:country":"US",
    "sg:address":"7020 Anderson Rd",
    "sg:city":"Tampa",
    "sg:classifiers":[
        {
            "category":"Wholesale",
            "subcategory":"Chemicals & Plastics",
            "type":"Manufacturing & Wholesale Goods"
        }
    ],
    "sg:phone":"+1 813 885 2343",
    "sg:postcode":"33634",
    "sg:province":"FL",
    "sg:tags":[
        "adhesive",
        "glue"
    ],
    "sg:website":"www.impactdistributing.com",
    "wof:name":"Impact Industrial Supplies",
    "wof:placetype":"venue"
},
  "geometry": {"coordinates":[-82.53365700000001,28.015138],"type":"Point"}
}