{
  "type": "Feature",
  "properties": {
    "addr:full":"110 Wateredge Ct Safety Harbor FL 34695",
    "addr:housenumber":"110",
    "addr:postcode":"34695",
    "addr:street":"Wateredge Ct",
    "iso:country":"US",
    "sg:address":"110 Wateredge Ct",
    "sg:city":"Safety Harbor",
    "sg:classifiers":[
        {
            "category":"Education",
            "subcategory":"School",
            "type":"Public Place"
        }
    ],
    "sg:phone":"+1 727 725 5889",
    "sg:postcode":"34695",
    "sg:province":"FL",
    "sg:tags":[
        "organization",
        "religious"
    ],
    "wof:name":"Christian Northbay Academy",
    "wof:placetype":"venue"
},
  "geometry": {"coordinates":[-82.684889,28.018147],"type":"Point"}
}