{
  "type": "Feature",
  "properties": {
    "addr:full":"6037 N Dale Mabry Hwy Tampa FL 33614",
    "addr:housenumber":"6037",
    "addr:postcode":"33614",
    "addr:street":"N Dale Mabry Hwy",
    "iso:country":"US",
    "sg:address":"6037 N Dale Mabry Hwy",
    "sg:city":"Tampa",
    "sg:classifiers":[
        {
            "category":"Restaurant",
            "type":"Food & Drink"
        }
    ],
    "sg:menulink":"http://www.allmenus.com/fl/tampa/81403-papa-johns-pizza/menu/",
    "sg:phone":"+1 813 879 7272",
    "sg:postcode":"33614",
    "sg:province":"FL",
    "sg:tags":[
        "american",
        "pizza"
    ],
    "wof:name":"Papa John's Pizza",
    "wof:placetype":"venue"
},
  "geometry": {"coordinates":[-82.505162,28.003238],"type":"Point"}
}