{
  "type": "Feature",
  "properties": {
    "addr:full":"225 N Duncan Dr Tavares FL 32778",
    "addr:housenumber":"225",
    "addr:postcode":"32778",
    "addr:street":"N Duncan Dr",
    "iso:country":"US",
    "sg:address":"225 N Duncan Dr",
    "sg:city":"Tavares",
    "sg:classifiers":[
        {
            "category":"Building & Trades",
            "subcategory":"Construction",
            "type":"Services"
        }
    ],
    "sg:phone":"+1 352 343 7100",
    "sg:postcode":"32778",
    "sg:province":"FL",
    "sg:tags":[
        "contractor"
    ],
    "wof:name":"Val Coursey Homes Inc",
    "wof:placetype":"venue"
},
  "geometry": {"coordinates":[-81.737556,28.804023],"type":"Point"}
}