{
  "type": "Feature",
  "properties": {
    "iso:country":"US",
    "sg:address":"1971 Kindling Ct",
    "sg:city":"Casselberry",
    "sg:classifiers":[
        {
            "category":"Building & Trades",
            "subcategory":"Construction",
            "type":"Services"
        }
    ],
    "sg:phone":"+1 407 949 9569",
    "sg:postcode":"32707",
    "sg:province":"FL",
    "sg:tags":[
        "wallcoverings-installation",
        "wallpaper",
        "painting",
        "contractor"
    ],
    "wof:name":"Done Rite Painting Inc",
    "wof:placetype":"venue"
},
  "geometry": {"coordinates":[-81.29102399999999,28.66528],"type":"Point"}
}