{
  "type": "Feature",
  "properties": {
    "iso:country":"US",
    "sg:address":"10070 Chesterton Rd",
    "sg:city":"Jacksonville",
    "sg:classifiers":[
        {
            "category":"Home & Garden",
            "subcategory":"Garden Supply",
            "type":"Retail Goods"
        }
    ],
    "sg:phone":"+1 904 721 2965",
    "sg:postcode":"32246",
    "sg:province":"FL",
    "wof:name":"Roots Gardens Inc",
    "wof:placetype":"venue"
},
  "geometry": {"coordinates":[-81.53918400000001,30.30878],"type":"Point"}
}