{
  "type": "Feature",
  "properties": {
    "addr:full":"1323 E Parker St Lakeland FL 33801",
    "addr:housenumber":"1323",
    "addr:postcode":"33801",
    "addr:street":"E Parker St",
    "iso:country":"US",
    "sg:address":"1323 E Parker St",
    "sg:city":"Lakeland",
    "sg:classifiers":[
        {
            "category":"Real Estate",
            "subcategory":"Real Estate Agent",
            "type":"Services"
        }
    ],
    "sg:phone":"+1 863 686 7698",
    "sg:postcode":"33801",
    "sg:province":"FL",
    "sg:tags":[
        "house",
        "construct"
    ],
    "wof:name":"Orange Belt Realty Company",
    "wof:placetype":"venue"
},
  "geometry": {"coordinates":[-81.93901200000001,28.051423],"type":"Point"}
}