{
  "type": "Feature",
  "properties": {
    "addr:full":"4050 Laurelwood Dr Jacksonville FL 32257",
    "addr:housenumber":"4050",
    "addr:postcode":"32257",
    "addr:street":"Laurelwood Dr",
    "iso:country":"US",
    "sg:address":"4050 Laurelwood Dr",
    "sg:city":"Jacksonville",
    "sg:classifiers":[
        {
            "category":"Professional",
            "subcategory":"Computer Services",
            "type":"Services"
        }
    ],
    "sg:phone":"+1 904 716 2916",
    "sg:postcode":"32257",
    "sg:province":"FL",
    "sg:tags":[
        "consultant",
        "designer"
    ],
    "wof:name":"Tech Gear",
    "wof:placetype":"venue"
},
  "geometry": {"coordinates":[-81.61133700000001,30.199828],"type":"Point"}
}