{
  "type": "Feature",
  "properties": {
    "iso:country":"US",
    "sg:address":"5760 Alton Rd",
    "sg:city":"Miami Beach",
    "sg:classifiers":[
        {
            "category":"Building & Trades",
            "subcategory":"Construction",
            "type":"Services"
        }
    ],
    "sg:phone":"+1 305 868 9088",
    "sg:postcode":"33140",
    "sg:province":"FL",
    "sg:tags":[
        "interior",
        "design"
    ],
    "wof:name":"Victor A Diaz Inc",
    "wof:placetype":"venue"
},
  "geometry": {"coordinates":[-80.13110399999999,25.837999],"type":"Point"}
}