{
  "type": "Feature",
  "properties": {
    "iso:country":"US",
    "sg:address":"3132 SW 16th St",
    "sg:city":"Miami",
    "sg:classifiers":[
        {
            "category":"Wholesale",
            "subcategory":"Durable Goods & Equipment",
            "type":"Manufacturing & Wholesale Goods"
        }
    ],
    "sg:phone":"+1 305 443 3322",
    "sg:postcode":"33145",
    "sg:province":"FL",
    "sg:tags":[
        "exporter"
    ],
    "wof:name":"Real Enterprises",
    "wof:placetype":"venue"
},
  "geometry": {"coordinates":[-80.246177,25.757454],"type":"Point"}
}