{
  "type": "Feature",
  "properties": {
    "iso:country":"US",
    "sg:address":"683 Olean Ct",
    "sg:city":"Winter Springs",
    "sg:classifiers":[
        {
            "category":"Home & Garden",
            "subcategory":"Building Materials",
            "type":"Retail Goods"
        },
        {
            "category":"Recreation",
            "type":"Entertainment"
        }
    ],
    "sg:phone":"+1 407 365 6374",
    "sg:postcode":"32708",
    "sg:province":"FL",
    "sg:tags":[
        "consulting",
        "ball",
        "wallpaper",
        "paint",
        "management",
        "sport"
    ],
    "wof:name":"Hooked Up Paintball Supplies",
    "wof:placetype":"venue"
},
  "geometry": {"coordinates":[-81.231503,28.678917],"type":"Point"}
}