{
  "type": "Feature",
  "properties": {
    "addr:full":"3626 E Industrial Way Riviera Beach FL 33404",
    "addr:housenumber":"3626",
    "addr:postcode":"33404",
    "addr:street":"E Industrial Way",
    "iso:country":"US",
    "sg:address":"3626 E Industrial Way",
    "sg:city":"Riviera Beach",
    "sg:classifiers":[
        {
            "category":"Building & Trades",
            "subcategory":"Construction",
            "type":"Services"
        }
    ],
    "sg:phone":"+1 561 845 7760",
    "sg:postcode":"33404",
    "sg:province":"FL",
    "sg:tags":[
        "coping",
        "plastering",
        "tiling",
        "pool",
        "swimming"
    ],
    "wof:name":"Pool Services Of NPB",
    "wof:placetype":"venue"
},
  "geometry": {"coordinates":[-80.09363500000001,26.785404],"type":"Point"}
}