{
  "type": "Feature",
  "properties": {
    "iso:country":"US",
    "sg:address":"442 E New York Ave Ste 10",
    "sg:city":"Deland",
    "sg:classifiers":[
        {
            "category":"Health Services",
            "subcategory":"Clinic",
            "type":"Services"
        }
    ],
    "sg:phone":"+1 386 738 1085",
    "sg:postcode":"32724",
    "sg:province":"FL",
    "sg:tags":[
        "counseling",
        "mental"
    ],
    "wof:name":"McCullough H Ken MA Lmhc",
    "wof:placetype":"venue"
},
  "geometry": {"coordinates":[-81.278503,29.040199],"type":"Point"}
}