{
  "type": "Feature",
  "properties": {
    "iso:country":"US",
    "sg:address":"216 E Church Ave",
    "sg:city":"Longwood",
    "sg:classifiers":[
        {
            "category":"Retail",
            "subcategory":"Auto Repair",
            "type":"Services"
        }
    ],
    "sg:phone":"+1 407 831 2102",
    "sg:postcode":"32750",
    "sg:province":"FL",
    "sg:tags":[
        "wrecker"
    ],
    "wof:name":"East Longwood Automotive",
    "wof:placetype":"venue"
},
  "geometry": {"coordinates":[-81.34259400000001,28.700775],"type":"Point"}
}