{
  "type": "Feature",
  "properties": {
    "addr:full":"2750 W 68th St Hialeah FL 33016",
    "addr:housenumber":"2750",
    "addr:postcode":"33016",
    "addr:street":"W 68Th St",
    "iso:country":"US",
    "sg:address":"2750 W 68th St",
    "sg:city":"Hialeah",
    "sg:classifiers":[
        {
            "category":"Shopping",
            "subcategory":"Clothing, Apparel, & Fashions",
            "type":"Retail Goods"
        }
    ],
    "sg:phone":"+1 305 819 0777",
    "sg:postcode":"33016",
    "sg:province":"FL",
    "sg:tags":[
        "accessory",
        "clothing",
        "women's"
    ],
    "wof:name":"La Milagrosa",
    "wof:placetype":"venue"
},
  "geometry": {"coordinates":[-80.3386,25.8841],"type":"Point"}
}