{
  "type": "Feature",
  "properties": {
    "addr:full":"2209 Sw 37th Ave Miami FL 33145",
    "addr:housenumber":"2209",
    "addr:postcode":"33145",
    "addr:street":"Sw 37Th Ave",
    "iso:country":"US",
    "sg:address":"2209 Sw 37th Ave",
    "sg:city":"Miami",
    "sg:classifiers":[
        {
            "category":"Shopping",
            "subcategory":"Hobbies, Toys, & Games",
            "type":"Retail Goods"
        }
    ],
    "sg:phone":"+1 305 444 0343",
    "sg:postcode":"33145",
    "sg:province":"FL",
    "sg:tags":[
        "toy",
        "video",
        "store",
        "supply"
    ],
    "sg:website":"www.toysrus.com",
    "wof:name":"Toys R Us",
    "wof:placetype":"venue"
},
  "geometry": {"coordinates":[-80.25426,25.749391],"type":"Point"}
}