{
  "type": "Feature",
  "properties": {
    "iso:country":"US",
    "sg:address":"335 SE 2nd Ave",
    "sg:city":"South Bay",
    "sg:classifiers":[
        {
            "category":"Government",
            "subcategory":"Office",
            "type":"Public Place"
        }
    ],
    "sg:phone":"+1 561 996 0520",
    "sg:postcode":"33493",
    "sg:province":"FL",
    "sg:tags":[
        "village"
    ],
    "wof:name":"Water Plant",
    "wof:placetype":"venue"
},
  "geometry": {"coordinates":[-80.71096,26.66205],"type":"Point"}
}