{
  "type": "Feature",
  "properties": {
    "addr:full":"744 W Colonial Dr Orlando FL 32804",
    "addr:housenumber":"744",
    "addr:postcode":"32804",
    "addr:street":"W Colonial Dr",
    "iso:country":"US",
    "sg:address":"744 W Colonial Dr",
    "sg:city":"Orlando",
    "sg:classifiers":[
        {
            "category":"Restaurant",
            "type":"Food & Drink"
        }
    ],
    "sg:menulink":"http://www.allmenus.com/fl/orlando/160428-burger-king/menu/",
    "sg:phone":"+1 407 425 3010",
    "sg:postcode":"32804",
    "sg:province":"FL",
    "sg:tags":[
        "burger",
        "american"
    ],
    "wof:name":"Burger King",
    "wof:placetype":"venue"
},
  "geometry": {"coordinates":[-81.390863,28.552524],"type":"Point"}
}