{
  "type": "Feature",
  "properties": {
    "iso:country":"US",
    "sg:address":"5021 Mobile Hwy",
    "sg:city":"Pensacola",
    "sg:classifiers":[
        {
            "category":"Travel",
            "subcategory":"Hotels & Motels",
            "type":"Entertainment"
        }
    ],
    "sg:phone":"+1 850 455 4542",
    "sg:postcode":"32506",
    "sg:province":"FL",
    "wof:name":"Long's Motel",
    "wof:placetype":"venue"
},
  "geometry": {"coordinates":[-87.290117,30.447989],"type":"Point"}
}