{
  "type": "Feature",
  "properties": {
    "iso:country":"US",
    "sg:address":"2814 W Averill Ave",
    "sg:city":"Tampa",
    "sg:classifiers":[
        {
            "category":"Building & Trades",
            "subcategory":"Pest Control",
            "type":"Services"
        }
    ],
    "sg:phone":"+1 813 831 2355",
    "sg:postcode":"33611",
    "sg:province":"FL",
    "wof:name":"Reliable Pest Control",
    "wof:placetype":"venue"
},
  "geometry": {"coordinates":[-82.489171,27.874441],"type":"Point"}
}