{
  "type": "Feature",
  "properties": {
    "iso:country":"US",
    "sg:address":"1635 W 44th Pl Apt 515",
    "sg:city":"Hialeah",
    "sg:classifiers":[
        {
            "category":"Health Services",
            "subcategory":"Health Practitioner",
            "type":"Services"
        }
    ],
    "sg:phone":"+1 305 364 8113",
    "sg:postcode":"33012",
    "sg:province":"FL",
    "sg:tags":[
        "hypnotherapy",
        "hypnotist"
    ],
    "wof:name":"Enrique Baltar",
    "wof:placetype":"venue"
},
  "geometry": {"coordinates":[-80.31572199999999,25.862507],"type":"Point"}
}