{
  "type": "Feature",
  "properties": {
    "iso:country":"US",
    "sg:address":"136 Sunway Ave",
    "sg:city":"Sarasota",
    "sg:classifiers":[
        {
            "category":"Building & Trades",
            "subcategory":"Construction",
            "type":"Services"
        }
    ],
    "sg:phone":"+1 941 400 6559",
    "sg:postcode":"34237",
    "sg:province":"FL",
    "sg:tags":[
        "painter"
    ],
    "wof:name":"R Phillips Painting Inc",
    "wof:placetype":"venue"
},
  "geometry": {"coordinates":[-82.519248,27.338994],"type":"Point"}
}