{
  "type": "Feature",
  "properties": {
    "iso:country":"US",
    "sg:address":"343 Broadway Ave",
    "sg:city":"Orlando",
    "sg:classifiers":[
        {
            "category":"Bars & Pubs",
            "type":"Food & Drink"
        }
    ],
    "sg:phone":"+1 407 426 8336",
    "sg:postcode":"32803",
    "sg:province":"FL",
    "sg:tags":[
        "club",
        "night"
    ],
    "wof:name":"Central Station Bar",
    "wof:placetype":"venue"
},
  "geometry": {"coordinates":[-81.372574,28.547343],"type":"Point"}
}