{
  "type": "Feature",
  "properties": {
    "addr:full":"1421 Alton Rd Miami Beach FL 33139",
    "addr:housenumber":"1421",
    "addr:postcode":"33139",
    "addr:street":"Alton Rd",
    "iso:country":"US",
    "sg:address":"1421 Alton Rd",
    "sg:city":"Miami Beach",
    "sg:classifiers":[
        {
            "category":"Shopping",
            "subcategory":"Pharmacy",
            "type":"Retail Goods"
        }
    ],
    "sg:phone":"+1 305 538 1571",
    "sg:postcode":"33139",
    "sg:province":"FL",
    "sg:tags":[
        "drugstore"
    ],
    "sg:website":"www.cvs.com",
    "wof:name":"CVS",
    "wof:placetype":"venue"
},
  "geometry": {"coordinates":[-80.140682,25.785749],"type":"Point"}
}