{
  "type": "Feature",
  "properties": {
    "addr:full":"3253 Dartmouth Dr Tallahassee FL 32317",
    "addr:housenumber":"3253",
    "addr:postcode":"32317",
    "addr:street":"Dartmouth Dr",
    "iso:country":"US",
    "sg:address":"3253 Dartmouth Dr",
    "sg:city":"Tallahassee",
    "sg:classifiers":[
        {
            "category":"Shopping",
            "subcategory":"Beauty & Cosmetics",
            "type":"Retail Goods"
        }
    ],
    "sg:phone":"+1 850 877 2426",
    "sg:postcode":"32317",
    "sg:province":"FL",
    "sg:tags":[
        "perfume",
        "salons-equipment",
        "supply"
    ],
    "wof:name":"Person, M",
    "wof:placetype":"venue"
},
  "geometry": {"coordinates":[-84.220169,30.457439],"type":"Point"}
}