{
  "type": "Feature",
  "properties": {
    "iso:country":"US",
    "sg:address":"5652 Meadowlane St",
    "sg:city":"New Port Richey",
    "sg:classifiers":[
        {
            "category":"Professional",
            "subcategory":"Research",
            "type":"Services"
        }
    ],
    "sg:phone":"+1 727 835 3261",
    "sg:postcode":"34652",
    "sg:province":"FL",
    "sg:tags":[
        "medical",
        "commercial"
    ],
    "wof:name":"Advanced Research Institute",
    "wof:placetype":"venue"
},
  "geometry": {"coordinates":[-82.72048599999999,28.236882],"type":"Point"}
}