{
  "type": "Feature",
  "properties": {
    "iso:country":"US",
    "sg:address":"3974 Avalon Blvd",
    "sg:city":"Milton",
    "sg:classifiers":[
        {
            "category":"Restaurant",
            "type":"Food & Drink"
        }
    ],
    "sg:menulink":"http://www.allmenus.com/fl/pace/32392-recanatis-italian-restaurant/menu/",
    "sg:phone":"+1 850 623 8666",
    "sg:postcode":"32583",
    "sg:province":"FL",
    "sg:tags":[
        "italian"
    ],
    "wof:name":"Recanati's Italian Restaurant",
    "wof:placetype":"venue"
},
  "geometry": {"coordinates":[-87.08627799999999,30.581115],"type":"Point"}
}