{
  "type": "Feature",
  "properties": {
    "iso:country":"US",
    "sg:address":"200 S Orange St",
    "sg:city":"New Smyrna Beach",
    "sg:classifiers":[
        {
            "category":"Building & Trades",
            "subcategory":"Landscaping Services",
            "type":"Services"
        }
    ],
    "sg:phone":"+1 386 428 4018",
    "sg:postcode":"32168",
    "sg:province":"FL",
    "sg:tags":[
        "landscape",
        "contractor"
    ],
    "wof:name":"Shannon's Garden & Gifts",
    "wof:placetype":"venue"
},
  "geometry": {"coordinates":[-80.92461900000001,29.022164],"type":"Point"}
}