{
  "type": "Feature",
  "properties": {
    "addr:full":"7243 SW 24th St Miami FL 33155",
    "addr:housenumber":"7243",
    "addr:postcode":"33155",
    "addr:street":"Sw 24Th St",
    "iso:country":"US",
    "sg:address":"7243 SW 24th St",
    "sg:city":"Miami",
    "sg:classifiers":[
        {
            "category":"Shopping",
            "type":"Retail Goods"
        }
    ],
    "sg:phone":"+1 305 265 9996",
    "sg:postcode":"33155",
    "sg:province":"FL",
    "sg:tags":[
        "religious"
    ],
    "wof:name":"Obatala",
    "wof:placetype":"venue"
},
  "geometry": {"coordinates":[-80.31496300000001,25.748176],"type":"Point"}
}