{
  "type": "Feature",
  "properties": {
    "addr:full":"9100 SW 136th St Miami FL 33176",
    "addr:housenumber":"9100",
    "addr:postcode":"33176",
    "addr:street":"Sw 136Th St",
    "iso:country":"US",
    "sg:address":"9100 SW 136th St",
    "sg:city":"Miami",
    "sg:classifiers":[
        {
            "category":"Shopping",
            "subcategory":"Clothing, Apparel, & Fashions",
            "type":"Retail Goods"
        }
    ],
    "sg:phone":"+1 305 259 7389",
    "sg:postcode":"33176",
    "sg:province":"FL",
    "sg:tags":[
        "maternity"
    ],
    "wof:name":"Motherhood Maternity",
    "wof:placetype":"venue"
},
  "geometry": {"coordinates":[-80.33697600000001,25.643607],"type":"Point"}
}