{
  "type": "Feature",
  "properties": {
    "iso:country":"US",
    "sg:address":"4220 Mahan Dr",
    "sg:city":"Tallahassee",
    "sg:classifiers":[
        {
            "category":"Organizations",
            "subcategory":"Religious Organization",
            "type":"Services"
        }
    ],
    "sg:phone":"+1 850 877 4428",
    "sg:postcode":"32308",
    "sg:province":"FL",
    "sg:website":"www.l-p-c.net",
    "wof:name":"Lafayette Presbyterian Church",
    "wof:placetype":"venue"
},
  "geometry": {"coordinates":[-84.206615,30.467857],"type":"Point"}
}