{
  "type": "Feature",
  "properties": {
    "iso:country":"US",
    "sg:address":"2555 Old Dixie Hwy",
    "sg:city":"Stuart",
    "sg:classifiers":[
        {
            "category":"Retail",
            "subcategory":"Auto Rental",
            "type":"Services"
        }
    ],
    "sg:phone":"+1 772 223 7718",
    "sg:postcode":"34996",
    "sg:province":"FL",
    "sg:tags":[
        "renting",
        "automobile"
    ],
    "wof:name":"Hertz",
    "wof:placetype":"venue"
},
  "geometry": {"coordinates":[-80.231285,27.176204],"type":"Point"}
}