{
  "type": "Feature",
  "properties": {
    "addr:full":"615 NE 8th Ave Hallandale FL 33009",
    "addr:housenumber":"615",
    "addr:postcode":"33009",
    "addr:street":"Ne 8Th Ave",
    "iso:country":"US",
    "sg:address":"615 NE 8th Ave",
    "sg:city":"Hallandale",
    "sg:classifiers":[
        {
            "category":"Real Estate",
            "subcategory":"Real Estate Operator",
            "type":"Services"
        }
    ],
    "sg:phone":"+1 954 457 9300",
    "sg:postcode":"33009",
    "sg:province":"FL",
    "sg:tags":[
        "building",
        "apartment"
    ],
    "wof:name":"Aurora Apts",
    "wof:placetype":"venue"
},
  "geometry": {"coordinates":[-80.140614,25.992977],"type":"Point"}
}