{
  "type": "Feature",
  "properties": {
    "iso:country":"US",
    "sg:address":"1022 Richmond Ave N",
    "sg:city":"Lehigh Acres",
    "sg:classifiers":[
        {
            "category":"Building & Trades",
            "subcategory":"Electrical",
            "type":"Services"
        }
    ],
    "sg:phone":"+1 239 369 6503",
    "sg:postcode":"33972",
    "sg:province":"FL",
    "sg:tags":[
        "electrical"
    ],
    "wof:name":"Rankor Corporation",
    "wof:placetype":"venue"
},
  "geometry": {"coordinates":[-81.62538499999999,26.63852],"type":"Point"}
}