{
  "type": "Feature",
  "properties": {
    "addr:full":"9370 SW 72nd St Miami FL 33173",
    "addr:housenumber":"9370",
    "addr:postcode":"33173",
    "addr:street":"Sw 72Nd St",
    "iso:country":"US",
    "sg:address":"9370 SW 72nd St",
    "sg:city":"Miami",
    "sg:classifiers":[
        {
            "category":"Health Services",
            "subcategory":"Clinic",
            "type":"Services"
        }
    ],
    "sg:phone":"+1 305 412 5553",
    "sg:postcode":"33173",
    "sg:province":"FL",
    "sg:tags":[
        "home"
    ],
    "wof:name":"Advanced Home Health Care",
    "wof:placetype":"venue"
},
  "geometry": {"coordinates":[-80.34475999999999,25.701873],"type":"Point"}
}