{
  "type": "Feature",
  "properties": {
    "addr:full":"2778 US Hwy 27 Avon Park FL 33825",
    "addr:housenumber":"2778",
    "addr:postcode":"33825",
    "addr:street":"Us Hwy 27",
    "iso:country":"US",
    "sg:address":"2778 US Hwy 27",
    "sg:city":"Avon Park",
    "sg:classifiers":[
        {
            "category":"Health Services",
            "subcategory":"Clinic",
            "type":"Services"
        }
    ],
    "sg:phone":"+1 863 314 9858",
    "sg:postcode":"33825",
    "sg:province":"FL",
    "sg:tags":[
        "home"
    ],
    "sg:website":"www.healthessentialsinc.com",
    "wof:name":"Best Choice Home Health Care",
    "wof:placetype":"venue"
},
  "geometry": {"coordinates":[-81.521298,27.637456],"type":"Point"}
}