{
  "type": "Feature",
  "properties": {
    "addr:full":"85 Marsh Dr Freeport FL 32439",
    "addr:housenumber":"85",
    "addr:postcode":"32439",
    "addr:street":"Marsh Dr",
    "iso:country":"US",
    "sg:address":"85 Marsh Dr",
    "sg:city":"Freeport",
    "sg:classifiers":[
        {
            "category":"Professional",
            "subcategory":"Engineering",
            "type":"Services"
        }
    ],
    "sg:phone":"+1 850 835 4238",
    "sg:postcode":"32439",
    "sg:province":"FL",
    "sg:tags":[
        "engineer"
    ],
    "wof:name":"Elcor Inc",
    "wof:placetype":"venue"
},
  "geometry": {"coordinates":[-86.24324900000001,30.480821],"type":"Point"}
}