{
  "type": "Feature",
  "properties": {
    "iso:country":"US",
    "sg:address":"8591 Dynasty Dr",
    "sg:city":"Boca Raton",
    "sg:classifiers":[
        {
            "category":"Building & Trades",
            "subcategory":"Plumbing",
            "type":"Services"
        }
    ],
    "sg:phone":"+1 561 852 7703",
    "sg:postcode":"33433",
    "sg:province":"FL",
    "sg:tags":[
        "conditioning",
        "air",
        "system",
        "contractor"
    ],
    "wof:name":"Temperature Control Inc",
    "wof:placetype":"venue"
},
  "geometry": {"coordinates":[-80.179919,26.332522],"type":"Point"}
}