{
  "type": "Feature",
  "properties": {
    "iso:country":"US",
    "sg:address":"2611 Poinsettia Ave",
    "sg:city":"West Palm Beach",
    "sg:classifiers":[
        {
            "category":"Health Services",
            "subcategory":"Clinic",
            "type":"Services"
        }
    ],
    "sg:phone":"+1 561 833 0776",
    "sg:postcode":"33407",
    "sg:province":"FL",
    "sg:tags":[
        "kidney",
        "dialysis",
        "center"
    ],
    "wof:name":"Dialysis Associates Palm Beach",
    "wof:placetype":"venue"
},
  "geometry": {"coordinates":[-80.052881,26.736801],"type":"Point"}
}