{
  "type": "Feature",
  "properties": {
    "addr:full":"2454 N McMullen Booth Rd Clearwater FL 33759",
    "addr:housenumber":"2454",
    "addr:postcode":"33759",
    "addr:street":"N Mcmullen Booth Rd",
    "iso:country":"US",
    "sg:address":"2454 N McMullen Booth Rd",
    "sg:city":"Clearwater",
    "sg:classifiers":[
        {
            "category":"Wholesale",
            "subcategory":"Fruits & Vegetables",
            "type":"Manufacturing & Wholesale Goods"
        }
    ],
    "sg:phone":"+1 727 796 8700",
    "sg:postcode":"33759",
    "sg:province":"FL",
    "wof:name":"G W Palmer Company",
    "wof:placetype":"venue"
},
  "geometry": {"coordinates":[-82.70893100000001,28.01024],"type":"Point"}
}