{
  "type": "Feature",
  "properties": {
    "iso:country":"US",
    "sg:address":"1015 E Hibiscus Dr",
    "sg:city":"Bartow",
    "sg:classifiers":[
        {
            "category":"Building & Trades",
            "subcategory":"Construction",
            "type":"Services"
        }
    ],
    "sg:phone":"+1 863 533 8181",
    "sg:postcode":"33830",
    "sg:province":"FL",
    "sg:tags":[
        "house"
    ],
    "wof:name":"OConnor JM Construction",
    "wof:placetype":"venue"
},
  "geometry": {"coordinates":[-81.835177,27.879211],"type":"Point"}
}