{
  "type": "Feature",
  "properties": {
    "addr:full":"10641 Boca Pointe Dr Orlando FL 32836",
    "addr:housenumber":"10641",
    "addr:postcode":"32836",
    "addr:street":"Boca Pointe Dr",
    "iso:country":"US",
    "sg:address":"10641 Boca Pointe Dr",
    "sg:city":"Orlando",
    "sg:classifiers":[
        {
            "category":"Real Estate",
            "subcategory":"Real Estate Operator",
            "type":"Services"
        }
    ],
    "sg:phone":"+1 407 876 8679",
    "sg:postcode":"32836",
    "sg:province":"FL",
    "sg:tags":[
        "building",
        "nonresidential"
    ],
    "wof:name":"Rusmar Properties Inc",
    "wof:placetype":"venue"
},
  "geometry": {"coordinates":[-81.506924,28.413579],"type":"Point"}
}