{
  "type": "Feature",
  "properties": {
    "iso:country":"US",
    "sg:address":"4131 Lamson Ave",
    "sg:city":"Spring Hill",
    "sg:classifiers":[
        {
            "category":"Wholesale",
            "subcategory":"Metals & Minerals",
            "type":"Manufacturing & Wholesale Goods"
        }
    ],
    "sg:phone":"+1 352 686 8917",
    "sg:postcode":"34608",
    "sg:province":"FL",
    "sg:tags":[
        "aluminum"
    ],
    "wof:name":"Top-Notch Aluminum Products",
    "wof:placetype":"venue"
},
  "geometry": {"coordinates":[-82.544511,28.491576],"type":"Point"}
}