{
  "type": "Feature",
  "properties": {
    "addr:full":"910 N 25th St Fort Pierce FL 34947",
    "addr:housenumber":"910",
    "addr:postcode":"34947",
    "addr:street":"N 25Th St",
    "iso:country":"US",
    "sg:address":"910 N 25th St",
    "sg:city":"Fort Pierce",
    "sg:classifiers":[
        {
            "category":"Insurance",
            "subcategory":"Hazard Insurance",
            "type":"Services"
        }
    ],
    "sg:phone":"+1 772 461 6575",
    "sg:postcode":"34947",
    "sg:province":"FL",
    "sg:tags":[
        "bond"
    ],
    "wof:name":"Blakely Bail Bonds",
    "wof:placetype":"venue"
},
  "geometry": {"coordinates":[-80.349755,27.458307],"type":"Point"}
}