{
  "type": "Feature",
  "properties": {
    "iso:country":"US",
    "sg:address":"1118 Lake Ter",
    "sg:city":"Boynton Beach",
    "sg:classifiers":[
        {
            "category":"Building & Trades",
            "subcategory":"Construction",
            "type":"Services"
        }
    ],
    "sg:phone":"+1 561 735 4169",
    "sg:postcode":"33426",
    "sg:province":"FL",
    "sg:tags":[
        "hanging",
        "painter",
        "contractor"
    ],
    "wof:name":"Mooar Painting Co",
    "wof:placetype":"venue"
},
  "geometry": {"coordinates":[-80.086009,26.52724],"type":"Point"}
}