{
  "type": "Feature",
  "properties": {
    "iso:country":"US",
    "sg:address":"1107 Prospect Ave",
    "sg:city":"Melbourne",
    "sg:classifiers":[
        {
            "category":"Building & Trades",
            "subcategory":"Plumbing",
            "type":"Services"
        }
    ],
    "sg:phone":"+1 321 452 2999",
    "sg:postcode":"32901",
    "sg:province":"FL",
    "sg:tags":[
        "plumbing",
        "contractor"
    ],
    "wof:name":"Noble Plumbing-Fire Protection",
    "wof:placetype":"venue"
},
  "geometry": {"coordinates":[-80.601771,28.074844],"type":"Point"}
}