{
  "type": "Feature",
  "properties": {
    "iso:country":"US",
    "sg:address":"320 Thor Ave SE",
    "sg:city":"Palm Bay",
    "sg:classifiers":[
        {
            "category":"Building & Trades",
            "subcategory":"Cleaning & Sanitation",
            "type":"Services"
        }
    ],
    "sg:phone":"+1 321 724 5422",
    "sg:postcode":"32909",
    "sg:province":"FL",
    "sg:tags":[
        "janitor"
    ],
    "wof:name":"Swisher International Inc",
    "wof:placetype":"venue"
},
  "geometry": {"coordinates":[-80.619182,27.991852],"type":"Point"}
}