{
  "type": "Feature",
  "properties": {
    "addr:full":"2326 44th St S Saint Petersburg FL 33711",
    "addr:housenumber":"2326",
    "addr:postcode":"33711",
    "addr:street":"44Th St S",
    "iso:country":"US",
    "sg:address":"2326 44th St S",
    "sg:city":"Saint Petersburg",
    "sg:classifiers":[
        {
            "category":"Professional",
            "type":"Services"
        }
    ],
    "sg:phone":"+1 727 327 6655",
    "sg:postcode":"33711",
    "sg:province":"FL",
    "wof:name":"Sylvias Flowers",
    "wof:placetype":"venue"
},
  "geometry": {"coordinates":[-82.69298000000001,27.745839],"type":"Point"}
}