{
  "type": "Feature",
  "properties": {
    "addr:full":"6288 Indian Meadow St Orlando FL 32819",
    "addr:housenumber":"6288",
    "addr:postcode":"32819",
    "addr:street":"Indian Meadow St",
    "iso:country":"US",
    "sg:address":"6288 Indian Meadow St",
    "sg:city":"Orlando",
    "sg:classifiers":[
        {
            "category":"Personal",
            "type":"Services"
        }
    ],
    "sg:phone":"+1 407 876 6433",
    "sg:postcode":"32819",
    "sg:province":"FL",
    "sg:tags":[
        "wedding",
        "chapel"
    ],
    "wof:name":"A Beautiful Wedding",
    "wof:placetype":"venue"
},
  "geometry": {"coordinates":[-81.506981,28.454683],"type":"Point"}
}