{
  "type": "Feature",
  "properties": {
    "addr:full":"120 Oak Ave Altamonte Springs FL 32701",
    "addr:housenumber":"120",
    "addr:postcode":"32701",
    "addr:street":"Oak Ave",
    "iso:country":"US",
    "sg:address":"120 Oak Ave",
    "sg:city":"Altamonte Springs",
    "sg:classifiers":[
        {
            "category":"Building & Trades",
            "subcategory":"Construction",
            "type":"Services"
        }
    ],
    "sg:phone":"+1 407 332 0571",
    "sg:postcode":"32701",
    "sg:province":"FL",
    "sg:tags":[
        "contractor"
    ],
    "wof:name":"Houston Fence Co",
    "wof:placetype":"venue"
},
  "geometry": {"coordinates":[-81.353988,28.675304],"type":"Point"}
}