{
  "type": "Feature",
  "properties": {
    "iso:country":"US",
    "sg:address":"3415 W Hillsborough Ave",
    "sg:city":"Tampa",
    "sg:classifiers":[
        {
            "category":"Retail",
            "subcategory":"Auto Repair",
            "type":"Services"
        }
    ],
    "sg:phone":"+1 813 458 2390",
    "sg:postcode":"33614",
    "sg:province":"FL",
    "sg:tags":[
        "automotive",
        "tune"
    ],
    "wof:name":"J & D Car Wash Services",
    "wof:placetype":"venue"
},
  "geometry": {"coordinates":[-82.498734,27.99614],"type":"Point"}
}