{
  "type": "Feature",
  "properties": {
    "addr:full":"6841 Farragut St Hollywood FL 33024",
    "addr:housenumber":"6841",
    "addr:postcode":"33024",
    "addr:street":"Farragut St",
    "iso:country":"US",
    "sg:address":"6841 Farragut St",
    "sg:city":"Hollywood",
    "sg:classifiers":[
        {
            "category":"Home & Garden",
            "subcategory":"Home Furnishings",
            "type":"Retail Goods"
        }
    ],
    "sg:phone":"+1 954 921 4338",
    "sg:postcode":"33024",
    "sg:province":"FL",
    "sg:tags":[
        "beveled",
        "glass",
        "ornamental"
    ],
    "wof:name":"Sandman",
    "wof:placetype":"venue"
},
  "geometry": {"coordinates":[-80.22586,26.033926],"type":"Point"}
}