{
  "type": "Feature",
  "properties": {
    "addr:full":"500 W Flagler St Miami FL 33130",
    "addr:housenumber":"500",
    "addr:postcode":"33130",
    "addr:street":"W Flagler St",
    "iso:country":"US",
    "sg:address":"500 W Flagler St",
    "sg:city":"Miami",
    "sg:classifiers":[
        {
            "category":"Shopping",
            "subcategory":"Hobbies, Toys, & Games",
            "type":"Retail Goods"
        },
        {
            "category":"Education",
            "subcategory":"Junior College",
            "type":"Public Place"
        }
    ],
    "sg:phone":"+1 305 545 8302",
    "sg:postcode":"33130",
    "sg:province":"FL",
    "sg:tags":[
        "house",
        "doll",
        "accessory"
    ],
    "wof:name":"Indo-Americana",
    "wof:placetype":"venue"
},
  "geometry": {"coordinates":[-80.202698,25.77383],"type":"Point"}
}