{
  "type": "Feature",
  "properties": {
    "addr:full":"1737 Regal Mist Loop Trinity FL 34655",
    "addr:housenumber":"1737",
    "addr:postcode":"34655",
    "addr:street":"Regal Mist Loop",
    "iso:country":"US",
    "sg:address":"1737 Regal Mist Loop",
    "sg:city":"Trinity",
    "sg:classifiers":[
        {
            "category":"Shopping",
            "type":"Retail Goods"
        }
    ],
    "sg:phone":"+1 727 365 9357",
    "sg:postcode":"34655",
    "sg:province":"FL",
    "sg:tags":[
        "merchandise"
    ],
    "wof:name":"Camera Depot",
    "wof:placetype":"venue"
},
  "geometry": {"coordinates":[-82.662164,28.18495],"type":"Point"}
}