{
  "type": "Feature",
  "properties": {
    "addr:full":"429 Virginia Dr Lake Worth FL 33461",
    "addr:housenumber":"429",
    "addr:postcode":"33461",
    "addr:street":"Virginia Dr",
    "iso:country":"US",
    "sg:address":"429 Virginia Dr",
    "sg:city":"Lake Worth",
    "sg:classifiers":[
        {
            "category":"Building & Trades",
            "subcategory":"Cleaning & Sanitation",
            "type":"Services"
        }
    ],
    "sg:phone":"+1 561 202 5690",
    "sg:postcode":"33461",
    "sg:province":"FL",
    "sg:tags":[
        "butler",
        "maid"
    ],
    "wof:name":"R L Construction Svc",
    "wof:placetype":"venue"
},
  "geometry": {"coordinates":[-80.072048,26.609725],"type":"Point"}
}