{
  "type": "Feature",
  "properties": {
    "addr:full":"893 Spanish Dr N Longboat Key FL 34228",
    "addr:housenumber":"893",
    "addr:postcode":"34228",
    "addr:street":"Spanish Dr N",
    "iso:country":"US",
    "sg:address":"893 Spanish Dr N",
    "sg:city":"Longboat Key",
    "sg:classifiers":[
        {
            "category":"Banks & Credit Unions",
            "subcategory":"Financial Services",
            "type":"Services"
        }
    ],
    "sg:phone":"+1 941 383 1144",
    "sg:postcode":"34228",
    "sg:province":"FL",
    "sg:tags":[
        "trust",
        "nonprofit",
        "management"
    ],
    "wof:name":"Howard Charitable Trust",
    "wof:placetype":"venue"
},
  "geometry": {"coordinates":[-82.659126,27.420569],"type":"Point"}
}