{
  "type": "Feature",
  "properties": {
    "addr:full":"2921 S Orlando Dr Ste 200 Sanford FL 32773",
    "addr:housenumber":"2921",
    "addr:postcode":"32773",
    "addr:street":"S Orlando Dr Ste 200",
    "iso:country":"US",
    "sg:address":"2921 S Orlando Dr Ste 200",
    "sg:city":"Sanford",
    "sg:classifiers":[
        {
            "category":"Autos & Motor Vehicles",
            "subcategory":"Auto Supplies",
            "type":"Retail Goods"
        }
    ],
    "sg:phone":"+1 407 936 0955",
    "sg:postcode":"32773",
    "sg:province":"FL",
    "sg:tags":[
        "automobile",
        "part",
        "tire",
        "accessory"
    ],
    "wof:name":"Rent A Wheel",
    "wof:placetype":"venue"
},
  "geometry": {"coordinates":[-81.279916,28.770824],"type":"Point"}
}