{
  "type": "Feature",
  "properties": {
    "addr:full":"355 US Hwy 90 W Defuniak Springs FL 32433",
    "addr:housenumber":"355",
    "addr:postcode":"32433",
    "addr:street":"Us Hwy 90 W",
    "iso:country":"US",
    "sg:address":"355 US Hwy 90 W",
    "sg:city":"Defuniak Springs",
    "sg:classifiers":[
        {
            "category":"Home & Garden",
            "subcategory":"Mobile Homes",
            "type":"Retail Goods"
        }
    ],
    "sg:phone":"+1 850 892 7775",
    "sg:postcode":"32433",
    "sg:province":"FL",
    "wof:name":"Celebration Homes",
    "wof:placetype":"venue"
},
  "geometry": {"coordinates":[-86.124579,30.723962],"type":"Point"}
}