{
  "type": "Feature",
  "properties": {
    "iso:country":"US",
    "sg:address":"5811 Abelia Rd",
    "sg:city":"Jacksonville",
    "sg:classifiers":[
        {
            "category":"Social Services",
            "subcategory":"Child Care",
            "type":"Services"
        }
    ],
    "sg:phone":"+1 904 764 8934",
    "sg:postcode":"32209",
    "sg:province":"FL",
    "wof:name":"Love's Family Day Care",
    "wof:placetype":"venue"
},
  "geometry": {"coordinates":[-81.707764,30.376717],"type":"Point"}
}