{
  "type": "Feature",
  "properties": {
    "iso:country":"US",
    "sg:address":"4405 Pinebark Ave",
    "sg:city":"Orlando",
    "sg:classifiers":[
        {
            "category":"Recreation",
            "subcategory":"Arcade",
            "type":"Entertainment"
        }
    ],
    "sg:phone":"+1 407 290 1407",
    "sg:postcode":"32811",
    "sg:province":"FL",
    "sg:tags":[
        "casino"
    ],
    "wof:name":"Casino Parties Orlando",
    "wof:placetype":"venue"
},
  "geometry": {"coordinates":[-81.455421,28.498417],"type":"Point"}
}