{
  "type": "Feature",
  "properties": {
    "iso:country":"US",
    "sg:address":"2806 10th St W",
    "sg:city":"Palmetto",
    "sg:classifiers":[
        {
            "category":"Personal",
            "subcategory":"Beauty Salon",
            "type":"Services"
        }
    ],
    "sg:phone":"+1 941 722 3862",
    "sg:postcode":"34221",
    "sg:province":"FL",
    "wof:name":"B & B's Haircare Co",
    "wof:placetype":"venue"
},
  "geometry": {"coordinates":[-82.59908299999999,27.521448],"type":"Point"}
}