{
  "type": "Feature",
  "properties": {
    "iso:country":"US",
    "sg:address":"5017 66th St N",
    "sg:city":"St Petersburg",
    "sg:classifiers":[
        {
            "category":"Restaurant",
            "type":"Food & Drink"
        }
    ],
    "sg:phone":"+1 727 547 0230",
    "sg:postcode":"33709",
    "sg:province":"FL",
    "sg:tags":[
        "eating"
    ],
    "wof:name":"Fast Eddie's An American Bar",
    "wof:placetype":"venue"
},
  "geometry": {"coordinates":[-82.728448,27.81814],"type":"Point"}
}