{
  "type": "Feature",
  "properties": {
    "iso:country":"US",
    "sg:address":"97 NE 15th St",
    "sg:city":"Homestead",
    "sg:classifiers":[
        {
            "category":"Professional",
            "subcategory":"Lawyer & Legal Services",
            "type":"Services"
        }
    ],
    "sg:phone":"+1 305 247 1651",
    "sg:postcode":"33030",
    "sg:province":"FL",
    "wof:name":"Kenneth D Lemoine PA",
    "wof:placetype":"venue"
},
  "geometry": {"coordinates":[-80.475747,25.484544],"type":"Point"}
}