{
  "type": "Feature",
  "properties": {
    "addr:full":"17888 68th St N Loxahatchee FL 33470",
    "addr:housenumber":"17888",
    "addr:postcode":"33470",
    "addr:street":"68Th St N",
    "iso:country":"US",
    "sg:address":"17888 68th St N",
    "sg:city":"Loxahatchee",
    "sg:classifiers":[
        {
            "category":"Building & Trades",
            "subcategory":"Landscaping Services",
            "type":"Services"
        }
    ],
    "sg:phone":"+1 561 248 3102",
    "sg:postcode":"33470",
    "sg:province":"FL",
    "sg:tags":[
        "lawn",
        "maintenance",
        "grounds"
    ],
    "wof:name":"Martinez Lawn Svc",
    "wof:placetype":"venue"
},
  "geometry": {"coordinates":[-80.32526799999999,26.777439],"type":"Point"}
}