{
  "type": "Feature",
  "properties": {
    "iso:country":"US",
    "sg:address":"928 Mar Walt Dr",
    "sg:city":"Fort Walton Beach",
    "sg:classifiers":[
        {
            "category":"Health Services",
            "subcategory":"Doctor",
            "type":"Services"
        }
    ],
    "sg:phone":"+1 850 862 4377",
    "sg:postcode":"32547",
    "sg:province":"FL",
    "sg:tags":[
        "anesthesiologist"
    ],
    "wof:name":"Decroos Francis C F",
    "wof:placetype":"venue"
},
  "geometry": {"coordinates":[-86.632192,30.452128],"type":"Point"}
}