{
  "type": "Feature",
  "properties": {
    "addr:full":"9835 Lake Worth Rd Lake Worth FL 33467",
    "addr:housenumber":"9835",
    "addr:postcode":"33467",
    "addr:street":"Lake Worth Rd",
    "iso:country":"US",
    "sg:address":"9835 Lake Worth Rd",
    "sg:city":"Lake Worth",
    "sg:classifiers":[
        {
            "category":"Personal",
            "subcategory":"Beauty Salon",
            "type":"Services"
        }
    ],
    "sg:phone":"+1 561 968 0060",
    "sg:postcode":"33467",
    "sg:province":"FL",
    "sg:tags":[
        "shop"
    ],
    "wof:name":"Sister Act Of The Palm Beaches",
    "wof:placetype":"venue"
},
  "geometry": {"coordinates":[-80.20272300000001,26.61721],"type":"Point"}
}