{
  "type": "Feature",
  "properties": {
    "iso:country":"US",
    "sg:address":"6431 NW 32nd Ave",
    "sg:city":"Miami",
    "sg:classifiers":[
        {
            "category":"Manufacturing",
            "subcategory":"Rubber & Plastics",
            "type":"Manufacturing & Wholesale Goods"
        },
        {
            "category":"Shopping",
            "subcategory":"Stationery & Office Supplies",
            "type":"Retail Goods"
        },
        {
            "category":"Manufacturing",
            "subcategory":"Signs",
            "type":"Manufacturing & Wholesale Goods"
        },
        {
            "category":"Professional",
            "subcategory":"Printing & Photocopies",
            "type":"Services"
        },
        {
            "category":"Organizations",
            "subcategory":"Professional Association",
            "type":"Services"
        }
    ],
    "sg:phone":"+1 305 691 1941",
    "sg:postcode":"33147",
    "sg:province":"FL",
    "sg:tags":[
        "engraving",
        "stencil",
        "stamp",
        "corporation",
        "metal",
        "stamps-rubber",
        "seals-notary"
    ],
    "sg:website":"http://www.americanstamp.net",
    "wof:name":"American Stamp Works",
    "wof:placetype":"venue"
},
  "geometry": {"coordinates":[-80.249358,25.832711],"type":"Point"}
}