{
  "type": "Feature",
  "properties": {
    "iso:country":"US",
    "sg:address":"2779 Capital Cir NE",
    "sg:city":"Tallahassee",
    "sg:classifiers":[
        {
            "category":"Shopping",
            "type":"Retail Goods"
        }
    ],
    "sg:phone":"+1 850 297 2422",
    "sg:postcode":"32308",
    "sg:province":"FL",
    "sg:tags":[
        "merchandise"
    ],
    "wof:name":"Signature Gallery",
    "wof:placetype":"venue"
},
  "geometry": {"coordinates":[-84.24166099999999,30.490787],"type":"Point"}
}