{
  "type": "Feature",
  "properties": {
    "iso:country":"US",
    "sg:address":"14041 US Hwy 1",
    "sg:city":"North Palm Beach",
    "sg:classifiers":[
        {
            "category":"Home & Garden",
            "subcategory":"Hardware",
            "type":"Retail Goods"
        }
    ],
    "sg:phone":"+1 561 776 5988",
    "sg:postcode":"33408",
    "sg:province":"FL",
    "wof:name":"True John",
    "wof:placetype":"venue"
},
  "geometry": {"coordinates":[-80.05655299999999,26.881614],"type":"Point"}
}