{
  "type": "Feature",
  "properties": {
    "addr:full":"1447 Redstart Rd Venice FL 34293",
    "addr:housenumber":"1447",
    "addr:postcode":"34293",
    "addr:street":"Redstart Rd",
    "iso:country":"US",
    "sg:address":"1447 Redstart Rd",
    "sg:city":"Venice",
    "sg:classifiers":[
        {
            "category":"Home & Garden",
            "subcategory":"Building Materials",
            "type":"Retail Goods"
        }
    ],
    "sg:phone":"+1 941 493 6235",
    "sg:postcode":"34293",
    "sg:province":"FL",
    "wof:name":"Wallpaper By Connie",
    "wof:placetype":"venue"
},
  "geometry": {"coordinates":[-82.43227400000001,27.056782],"type":"Point"}
}