{
  "type": "Feature",
  "properties": {
    "iso:country":"US",
    "sg:address":"2000 1st St",
    "sg:city":"Bradenton",
    "sg:classifiers":[
        {
            "category":"Autos & Motor Vehicles",
            "subcategory":"Auto Supplies",
            "type":"Retail Goods"
        },
        {
            "category":"Wholesale",
            "subcategory":"Electrical",
            "type":"Manufacturing & Wholesale Goods"
        }
    ],
    "sg:phone":"+1 941 746 4181",
    "sg:postcode":"34208",
    "sg:province":"FL",
    "sg:tags":[
        "battery",
        "automobile",
        "part",
        "accessory"
    ],
    "sg:website":"http://www.genpt.com",
    "wof:name":"Napa Auto Parts",
    "wof:placetype":"venue"
},
  "geometry": {"coordinates":[-82.56307200000001,27.481541],"type":"Point"}
}