{
  "type": "Feature",
  "properties": {
    "iso:country":"US",
    "sg:address":"2901 Union Hill Rd",
    "sg:city":"Bonifay",
    "sg:classifiers":[
        {
            "category":"Building & Trades",
            "subcategory":"Construction",
            "type":"Services"
        }
    ],
    "sg:phone":"+1 850 535 1163",
    "sg:postcode":"32425",
    "sg:province":"FL",
    "sg:tags":[
        "house"
    ],
    "wof:name":"Ross Pritchard Builders Inc",
    "wof:placetype":"venue"
},
  "geometry": {"coordinates":[-85.67833400000001,30.682869],"type":"Point"}
}