{
  "type": "Feature",
  "properties": {
    "addr:full":"3305 Spainwood Dr Sarasota FL 34232",
    "addr:housenumber":"3305",
    "addr:postcode":"34232",
    "addr:street":"Spainwood Dr",
    "iso:country":"US",
    "sg:address":"3305 Spainwood Dr",
    "sg:city":"Sarasota",
    "sg:classifiers":[
        {
            "category":"Building & Trades",
            "subcategory":"Construction",
            "type":"Services"
        }
    ],
    "sg:phone":"+1 941 378 2554",
    "sg:postcode":"34232",
    "sg:province":"FL",
    "sg:tags":[
        "nonresidential"
    ],
    "wof:name":"Productive Construction Inc",
    "wof:placetype":"venue"
},
  "geometry": {"coordinates":[-82.45901499999999,27.30395],"type":"Point"}
}