{
  "type": "Feature",
  "properties": {
    "addr:full":"9705 Lake Bess Rd SE Winter Haven FL 33884",
    "addr:housenumber":"9705",
    "addr:postcode":"33884",
    "addr:street":"Lake Bess Rd Se;Haven",
    "iso:country":"US",
    "sg:address":"9705 Lake Bess Rd SE",
    "sg:city":"Winter Haven",
    "sg:classifiers":[
        {
            "category":"Professional",
            "type":"Services"
        }
    ],
    "sg:phone":"+1 863 318 8129",
    "sg:postcode":"33884",
    "sg:province":"FL",
    "sg:tags":[
        "establishment"
    ],
    "wof:name":"Adams Marketing",
    "wof:placetype":"venue"
},
  "geometry": {"coordinates":[-81.652598,27.975997],"type":"Point"}
}