{
  "type": "Feature",
  "properties": {
    "iso:country":"US",
    "sg:address":"5812 Johnson St",
    "sg:city":"Hollywood",
    "sg:classifiers":[
        {
            "category":"Building & Trades",
            "subcategory":"Pest Control",
            "type":"Services"
        }
    ],
    "sg:phone":"+1 954 962 7847",
    "sg:postcode":"33021",
    "sg:province":"FL",
    "wof:name":"We-Kill Pest Control",
    "wof:placetype":"venue"
},
  "geometry": {"coordinates":[-80.205637,26.01763],"type":"Point"}
}