{
  "type": "Feature",
  "properties": {
    "addr:full":"7742 Atherton Ave New Port Richey FL 34655",
    "addr:housenumber":"7742",
    "addr:postcode":"34655",
    "addr:street":"Atherton Ave",
    "iso:country":"US",
    "sg:address":"7742 Atherton Ave",
    "sg:city":"New Port Richey",
    "sg:classifiers":[
        {
            "category":"Communications",
            "subcategory":"Film & Video Production",
            "type":"Services"
        }
    ],
    "sg:phone":"+1 727 372 0715",
    "sg:postcode":"34655",
    "sg:province":"FL",
    "sg:tags":[
        "taping"
    ],
    "wof:name":"Gandalf Productions",
    "wof:placetype":"venue"
},
  "geometry": {"coordinates":[-82.686064,28.214313],"type":"Point"}
}