{
  "type": "Feature",
  "properties": {
    "iso:country":"US",
    "sg:address":"305 Alcazar Ave",
    "sg:city":"Coral Gables",
    "sg:classifiers":[
        {
            "category":"Professional",
            "subcategory":"Art Services",
            "type":"Services"
        }
    ],
    "sg:phone":"+1 305 461 2922",
    "sg:postcode":"33134",
    "sg:province":"FL",
    "sg:tags":[
        "photographer"
    ],
    "wof:name":"Gort Photography",
    "wof:placetype":"venue"
},
  "geometry": {"coordinates":[-80.260918,25.752852],"type":"Point"}
}