{
  "type": "Feature",
  "properties": {
    "addr:full":"5002 N Federal Hwy Lighthouse Point FL 33064",
    "addr:housenumber":"5002",
    "addr:postcode":"33064",
    "addr:street":"N Federal Hwy",
    "iso:country":"US",
    "sg:address":"5002 N Federal Hwy",
    "sg:city":"Lighthouse Point",
    "sg:classifiers":[
        {
            "category":"Health Services",
            "subcategory":"Chiropractor",
            "type":"Services"
        }
    ],
    "sg:phone":"+1 954 421 9171",
    "sg:postcode":"33064",
    "sg:province":"FL",
    "wof:name":"Steven M Pollack DC",
    "wof:placetype":"venue"
},
  "geometry": {"coordinates":[-80.094922,26.292709],"type":"Point"}
}