{
  "type": "Feature",
  "properties": {
    "addr:full":"10308 Tooke Lake Blvd Brooksville FL 34613",
    "addr:postcode":"10308;34613",
    "addr:street":"Tooke Lake Blvd",
    "iso:country":"US",
    "sg:address":"10308 Tooke Lake Blvd",
    "sg:city":"Brooksville",
    "sg:classifiers":[
        {
            "category":"Freight",
            "type":"Transportation"
        }
    ],
    "sg:phone":"+1 352 596 3423",
    "sg:postcode":"34613",
    "sg:province":"FL",
    "sg:tags":[
        "operator",
        "local",
        "trucking"
    ],
    "wof:name":"Pasco Trucking",
    "wof:placetype":"venue"
},
  "geometry": {"coordinates":[-82.552741,28.57474],"type":"Point"}
}