{
  "type": "Feature",
  "properties": {
    "addr:full":"1004 S Duval St Madison FL 32340",
    "addr:housenumber":"1004",
    "addr:postcode":"32340",
    "addr:street":"S Duval St",
    "iso:country":"US",
    "sg:address":"1004 S Duval St",
    "sg:city":"Madison",
    "sg:classifiers":[
        {
            "category":"Personal",
            "type":"Services"
        },
        {
            "category":"Retail",
            "subcategory":"Auto Rental",
            "type":"Services"
        }
    ],
    "sg:phone":"+1 800 468 4285",
    "sg:postcode":"32340",
    "sg:province":"FL",
    "sg:tags":[
        "mover",
        "truck"
    ],
    "wof:name":"U-Haul Co.",
    "wof:placetype":"venue"
},
  "geometry": {"coordinates":[-83.409498,30.458499],"type":"Point"}
}