{
  "type": "Feature",
  "properties": {
    "iso:country":"US",
    "sg:address":"218 E Pine St",
    "sg:city":"Lakeland",
    "sg:classifiers":[
        {
            "category":"Banks & Credit Unions",
            "subcategory":"Bank",
            "type":"Services"
        }
    ],
    "sg:phone":"+1 863 683 3811",
    "sg:postcode":"33801",
    "sg:province":"FL",
    "sg:tags":[
        "loan",
        "real estate"
    ],
    "wof:name":"Lakeland Regional Mortgage",
    "wof:placetype":"venue"
},
  "geometry": {"coordinates":[-81.955359,28.045994],"type":"Point"}
}