{
  "type": "Feature",
  "properties": {
    "iso:country":"US",
    "sg:address":"1408 Brickell Bay Dr",
    "sg:city":"Miami",
    "sg:classifiers":[
        {
            "category":"Real Estate",
            "subcategory":"Real Estate Operator",
            "type":"Services"
        }
    ],
    "sg:phone":"+1 305 373 4250",
    "sg:postcode":"33131",
    "sg:province":"FL",
    "sg:tags":[
        "management",
        "condominium"
    ],
    "wof:name":"Brickell Bay Tower Condominium",
    "wof:placetype":"venue"
},
  "geometry": {"coordinates":[-80.189072,25.75914],"type":"Point"}
}