{
  "type": "Feature",
  "properties": {
    "addr:full":"16223 SW 88th St Miami FL 33196",
    "addr:housenumber":"16223",
    "addr:postcode":"33196",
    "addr:street":"Sw 88Th St",
    "iso:country":"US",
    "sg:address":"16223 SW 88th St",
    "sg:city":"Miami",
    "sg:classifiers":[
        {
            "category":"Professional",
            "subcategory":"Accounting & Tax Preparation",
            "type":"Services"
        },
        {
            "category":"Wholesale",
            "subcategory":"Office Equipment",
            "type":"Manufacturing & Wholesale Goods"
        },
        {
            "category":"Banks & Credit Unions",
            "subcategory":"Financial Services",
            "type":"Services"
        }
    ],
    "sg:phone":"+1 305 742 0047",
    "sg:postcode":"33196",
    "sg:province":"FL",
    "sg:tags":[
        "return",
        "preparation-business",
        "taxes-consultants",
        "loan",
        "supply",
        "machine",
        "representative",
        "alternative",
        "bookkeeping"
    ],
    "sg:website":"http://miami.citysearch.com/profile/external/45122080/miami_fl/h_r_block.html?publisher=yellowpages&reference_id=1&placement=ypwebsitemip",
    "wof:name":"H&R BLOCK",
    "wof:placetype":"venue"
},
  "geometry": {"coordinates":[-80.454471,25.684186],"type":"Point"}
}