{
  "type": "Feature",
  "properties": {
    "addr:full":"2491 NW 7th St Miami FL 33125",
    "addr:housenumber":"2491",
    "addr:postcode":"33125",
    "addr:street":"Nw 7Th St",
    "iso:country":"US",
    "sg:address":"2491 NW 7th St",
    "sg:city":"Miami",
    "sg:classifiers":[
        {
            "category":"Health Services",
            "subcategory":"Doctor",
            "type":"Services"
        }
    ],
    "sg:phone":"+1 305 541 2610",
    "sg:postcode":"33125",
    "sg:province":"FL",
    "sg:tags":[
        "medical"
    ],
    "wof:name":"Gloria Piedra Mendizabal MD",
    "wof:placetype":"venue"
},
  "geometry": {"coordinates":[-80.237196,25.779537],"type":"Point"}
}