{
  "type": "Feature",
  "properties": {
    "addr:full":"5816 N Hubert Ave Tampa FL 33614",
    "addr:housenumber":"5816",
    "addr:postcode":"33614",
    "addr:street":"N Hubert Ave",
    "iso:country":"US",
    "sg:address":"5816 N Hubert Ave",
    "sg:city":"Tampa",
    "sg:classifiers":[
        {
            "category":"Building & Trades",
            "subcategory":"Construction",
            "type":"Services"
        }
    ],
    "sg:phone":"+1 813 884 2354",
    "sg:postcode":"33614",
    "sg:province":"FL",
    "sg:tags":[
        "contractor"
    ],
    "wof:name":"ABC Tile of Tampa Inc",
    "wof:placetype":"venue"
},
  "geometry": {"coordinates":[-82.515686,28.003476],"type":"Point"}
}