{
  "type": "Feature",
  "properties": {
    "iso:country":"US",
    "sg:address":"4364 Shadow Crest Pl",
    "sg:city":"Orlando",
    "sg:classifiers":[
        {
            "category":"Wholesale",
            "subcategory":"Non-durable Goods",
            "type":"Manufacturing & Wholesale Goods"
        }
    ],
    "sg:phone":"+1 407 293 5010",
    "sg:postcode":"32811",
    "sg:province":"FL",
    "sg:tags":[
        "vendor",
        "an",
        "to",
        "market",
        "flea",
        "general",
        "merchandise"
    ],
    "wof:name":"Goodons",
    "wof:placetype":"venue"
},
  "geometry": {"coordinates":[-81.455028,28.498722],"type":"Point"}
}