{
  "type": "Feature",
  "properties": {
    "addr:full":"327 Central Ave Clewiston FL 33440",
    "addr:housenumber":"327",
    "addr:postcode":"33440",
    "addr:street":"Central Ave",
    "iso:country":"US",
    "sg:address":"327 Central Ave",
    "sg:city":"Clewiston",
    "sg:classifiers":[
        {
            "category":"Health Services",
            "subcategory":"Doctor",
            "type":"Services"
        }
    ],
    "sg:phone":"+1 863 983 5121",
    "sg:postcode":"33440",
    "sg:province":"FL",
    "sg:tags":[
        "dentist"
    ],
    "wof:name":"Edwards Orthodontics",
    "wof:placetype":"venue"
},
  "geometry": {"coordinates":[-80.934258,26.751648],"type":"Point"}
}