{
  "type": "Feature",
  "properties": {
    "iso:country":"US",
    "sg:address":"365 Main St",
    "sg:city":"Dunedin",
    "sg:classifiers":[
        {
            "category":"Shopping",
            "subcategory":"Used Merchandise",
            "type":"Retail Goods"
        }
    ],
    "sg:phone":"+1 727 736 0778",
    "sg:postcode":"34698",
    "sg:province":"FL",
    "sg:tags":[
        "antique"
    ],
    "wof:name":"Amanda Austins",
    "wof:placetype":"venue"
},
  "geometry": {"coordinates":[-82.78815400000001,28.0117],"type":"Point"}
}