{
  "type": "Feature",
  "properties": {
    "iso:country":"US",
    "sg:address":"450 Caravan Ter",
    "sg:city":"Sebastian",
    "sg:classifiers":[
        {
            "category":"Professional",
            "type":"Services"
        }
    ],
    "sg:phone":"+1 772 589 5897",
    "sg:postcode":"32958",
    "sg:province":"FL",
    "wof:name":"Ms Captain Inc",
    "wof:placetype":"venue"
},
  "geometry": {"coordinates":[-80.481272,27.767511],"type":"Point"}
}