{
  "type": "Feature",
  "properties": {
    "iso:country":"US",
    "sg:address":"1908 Deerview Pl",
    "sg:city":"Longwood",
    "sg:classifiers":[
        {
            "category":"Social Services",
            "type":"Services"
        }
    ],
    "sg:phone":"+1 407 332 5726",
    "sg:postcode":"32750",
    "sg:province":"FL",
    "wof:name":"St Stevens Church",
    "wof:placetype":"venue"
},
  "geometry": {"coordinates":[-81.35890499999999,28.720529],"type":"Point"}
}