{
  "type": "Feature",
  "properties": {
    "addr:full":"2960 Melaleuca Rd West Palm Beach FL 33406",
    "addr:housenumber":"2960",
    "addr:postcode":"33406",
    "addr:street":"Melaleuca Rd",
    "iso:country":"US",
    "sg:address":"2960 Melaleuca Rd",
    "sg:city":"West Palm Beach",
    "sg:classifiers":[
        {
            "category":"Building & Trades",
            "subcategory":"Construction",
            "type":"Services"
        }
    ],
    "sg:phone":"+1 561 313 1763",
    "sg:postcode":"33406",
    "sg:province":"FL",
    "sg:tags":[
        "designer"
    ],
    "wof:name":"Joseph F Houston & Assoc",
    "wof:placetype":"venue"
},
  "geometry": {"coordinates":[-80.08471299999999,26.655323],"type":"Point"}
}