{
  "type": "Feature",
  "properties": {
    "addr:full":"2308 Pavilion Dr Quincy FL 32351",
    "addr:housenumber":"2308",
    "addr:postcode":"32351",
    "addr:street":"Pavilion Dr",
    "iso:country":"US",
    "sg:address":"2308 Pavilion Dr",
    "sg:city":"Quincy",
    "sg:classifiers":[
        {
            "category":"Home & Garden",
            "subcategory":"Building Materials",
            "type":"Retail Goods"
        }
    ],
    "sg:phone":"+1 850 627 2478",
    "sg:postcode":"32351",
    "sg:province":"FL",
    "sg:tags":[
        "glass",
        "window",
        "plate"
    ],
    "wof:name":"Gilbert Glass Co",
    "wof:placetype":"venue"
},
  "geometry": {"coordinates":[-84.60939500000001,30.586873],"type":"Point"}
}