{
  "type": "Feature",
  "properties": {
    "addr:full":"1717 Costa del Sol Boca Raton FL 33432",
    "addr:housenumber":"1717",
    "addr:postcode":"33432",
    "addr:street":"Costa",
    "iso:country":"US",
    "sg:address":"1717 Costa del Sol",
    "sg:city":"Boca Raton",
    "sg:classifiers":[
        {
            "category":"Professional",
            "subcategory":"Art Services",
            "type":"Services"
        }
    ],
    "sg:phone":"+1 561 447 4245",
    "sg:postcode":"33432",
    "sg:province":"FL",
    "sg:tags":[
        "graphic",
        "designer"
    ],
    "wof:name":"Robert Cerri Group Inc",
    "wof:placetype":"venue"
},
  "geometry": {"coordinates":[-80.089561,26.367381],"type":"Point"}
}