{
  "type": "Feature",
  "properties": {
    "addr:full":"827 Bentwood Dr Naples FL 34108",
    "addr:housenumber":"827",
    "addr:postcode":"34108",
    "addr:street":"Bentwood Dr",
    "iso:country":"US",
    "sg:address":"827 Bentwood Dr",
    "sg:city":"Naples",
    "sg:classifiers":[
        {
            "category":"Professional",
            "subcategory":"Lawyer & Legal Services",
            "type":"Services"
        }
    ],
    "sg:phone":"+1 239 566 1066",
    "sg:postcode":"34108",
    "sg:province":"FL",
    "sg:tags":[
        "attorney"
    ],
    "wof:name":"Joseph E Crehan",
    "wof:placetype":"venue"
},
  "geometry": {"coordinates":[-81.801484,26.227721],"type":"Point"}
}