{
  "type": "Feature",
  "properties": {
    "iso:country":"US",
    "sg:address":"1640 N Cove Blvd",
    "sg:city":"Panama City",
    "sg:classifiers":[
        {
            "category":"Wholesale",
            "subcategory":"Meat",
            "type":"Manufacturing & Wholesale Goods"
        }
    ],
    "sg:phone":"+1 850 785 7775",
    "sg:postcode":"32405",
    "sg:province":"FL",
    "wof:name":"DPJ Enterprises",
    "wof:placetype":"venue"
},
  "geometry": {"coordinates":[-85.65006700000001,30.177952],"type":"Point"}
}