{
  "type": "Feature",
  "properties": {
    "addr:full":"9237 N 56th St Tampa FL 33617",
    "addr:housenumber":"9237",
    "addr:postcode":"33617",
    "addr:street":"N 56Th St",
    "iso:country":"US",
    "sg:address":"9237 N 56th St",
    "sg:city":"Tampa",
    "sg:classifiers":[
        {
            "category":"Professional",
            "subcategory":"Computer Services",
            "type":"Services"
        }
    ],
    "sg:phone":"+1 813 985 0760",
    "sg:postcode":"33617",
    "sg:province":"FL",
    "sg:tags":[
        "leasing"
    ],
    "wof:name":"Buddy's Home Furnishings",
    "wof:placetype":"venue"
},
  "geometry": {"coordinates":[-82.393396,28.033157],"type":"Point"}
}