{
  "type": "Feature",
  "properties": {
    "iso:country":"US",
    "sg:address":"2611 Mercer Ave",
    "sg:city":"West Palm Beach",
    "sg:classifiers":[
        {
            "category":"Professional",
            "subcategory":"Business Services",
            "type":"Services"
        }
    ],
    "sg:phone":"+1 561 659 4459",
    "sg:postcode":"33401",
    "sg:province":"FL",
    "sg:tags":[
        "interior",
        "design"
    ],
    "wof:name":"Jack Fhillips Design Inc",
    "wof:placetype":"venue"
},
  "geometry": {"coordinates":[-80.06982000000001,26.692458],"type":"Point"}
}