{
  "type": "Feature",
  "properties": {
    "iso:country":"US",
    "sg:address":"243 N Texas Ave",
    "sg:city":"Orlando",
    "sg:classifiers":[
        {
            "category":"Building & Trades",
            "subcategory":"Landscaping Services",
            "type":"Services"
        }
    ],
    "sg:phone":"+1 407 246 1274",
    "sg:postcode":"32805",
    "sg:province":"FL",
    "sg:tags":[
        "tree"
    ],
    "wof:name":"Shake N Roll Tree Svc",
    "wof:placetype":"venue"
},
  "geometry": {"coordinates":[-81.409555,28.542407],"type":"Point"}
}