{
  "type": "Feature",
  "properties": {
    "addr:full":"1930 W 60th St Hialeah FL 33012",
    "addr:housenumber":"1930",
    "addr:postcode":"33012",
    "addr:street":"W 60Th St",
    "iso:country":"US",
    "sg:address":"1930 W 60th St",
    "sg:city":"Hialeah",
    "sg:classifiers":[
        {
            "category":"Freight",
            "type":"Transportation"
        }
    ],
    "sg:phone":"+1 305 818 2285",
    "sg:postcode":"33012",
    "sg:province":"FL",
    "sg:tags":[
        "arrangement"
    ],
    "wof:name":"Las Americas Express Inc",
    "wof:placetype":"venue"
},
  "geometry": {"coordinates":[-80.322903,25.876919],"type":"Point"}
}