{
  "type": "Feature",
  "properties": {
    "addr:full":"19327 NW 2nd Ave Miami FL 33169",
    "addr:housenumber":"19327",
    "addr:postcode":"33169",
    "addr:street":"Nw 2Nd Ave",
    "iso:country":"US",
    "sg:address":"19327 NW 2nd Ave",
    "sg:city":"Miami",
    "sg:classifiers":[
        {
            "category":"Professional",
            "type":"Services"
        }
    ],
    "sg:phone":"+1 305 249 3005",
    "sg:postcode":"33169",
    "sg:province":"FL",
    "sg:tags":[
        "establishment"
    ],
    "wof:name":"New Chance LLC",
    "wof:placetype":"venue"
},
  "geometry": {"coordinates":[-80.20547999999999,25.953221],"type":"Point"}
}