{
  "type": "Feature",
  "properties": {
    "addr:full":"5627 Gulfport Blvd S Gulfport FL 33707",
    "addr:housenumber":"5627",
    "addr:postcode":"33707",
    "addr:street":"Gulfport Blvd S",
    "iso:country":"US",
    "sg:address":"5627 Gulfport Blvd S",
    "sg:city":"Gulfport",
    "sg:classifiers":[
        {
            "category":"Health Services",
            "subcategory":"Chiropractor",
            "type":"Services"
        }
    ],
    "sg:phone":"+1 727 384 2611",
    "sg:postcode":"33707",
    "sg:province":"FL",
    "sg:tags":[
        "chiropractic"
    ],
    "wof:name":"Probeck Chiropractic Clinic",
    "wof:placetype":"venue"
},
  "geometry": {"coordinates":[-82.73263900000001,27.75807],"type":"Point"}
}