{
  "type": "Feature",
  "properties": {
    "iso:country":"US",
    "sg:address":"6800 Golden Gate Pkwy",
    "sg:city":"Naples",
    "sg:classifiers":[
        {
            "category":"Sports & Exercise",
            "subcategory":"Gym",
            "type":"Entertainment"
        }
    ],
    "sg:phone":"+1 239 643 4488",
    "sg:postcode":"34105",
    "sg:province":"FL",
    "sg:tags":[
        "club",
        "health",
        "studio",
        "gymnasium"
    ],
    "wof:name":"Fitness Plex",
    "wof:placetype":"venue"
},
  "geometry": {"coordinates":[-81.746359,26.173998],"type":"Point"}
}