{
  "type": "Feature",
  "properties": {
    "addr:full":"13610 SW 142nd Ave Miami FL 33186",
    "addr:housenumber":"13610",
    "addr:postcode":"33186",
    "addr:street":"Sw 142Nd Ave",
    "iso:country":"US",
    "sg:address":"13610 SW 142nd Ave",
    "sg:city":"Miami",
    "sg:classifiers":[
        {
            "category":"Building & Trades",
            "subcategory":"Construction",
            "type":"Services"
        }
    ],
    "sg:phone":"+1 305 968 2628",
    "sg:postcode":"33186",
    "sg:province":"FL",
    "sg:tags":[
        "heavy"
    ],
    "wof:name":"Sea Power Inc",
    "wof:placetype":"venue"
},
  "geometry": {"coordinates":[-80.422977,25.637369],"type":"Point"}
}