{
  "type": "Feature",
  "properties": {
    "iso:country":"US",
    "sg:address":"3419 32nd Ave N",
    "sg:city":"St Petersburg",
    "sg:classifiers":[
        {
            "category":"Shopping",
            "type":"Retail Goods"
        },
        {
            "category":"Building & Trades",
            "subcategory":"Construction",
            "type":"Services"
        }
    ],
    "sg:phone":"+1 727 526 6603",
    "sg:postcode":"33713",
    "sg:province":"FL",
    "sg:tags":[
        "equipment",
        "swimming",
        "merchandise",
        "pool",
        "contractor"
    ],
    "wof:name":"Royal Liner Pools Inc",
    "wof:placetype":"venue"
},
  "geometry": {"coordinates":[-82.680516,27.801081],"type":"Point"}
}