{
  "type": "Feature",
  "properties": {
    "iso:country":"US",
    "sg:address":"210 Old Kings Rd S",
    "sg:city":"Flagler Beach",
    "sg:classifiers":[
        {
            "category":"Wholesale",
            "subcategory":"Hardware",
            "type":"Manufacturing & Wholesale Goods"
        }
    ],
    "sg:phone":"+1 386 439 7906",
    "sg:postcode":"32136",
    "sg:province":"FL",
    "sg:tags":[
        "box",
        "mail"
    ],
    "wof:name":"Mailbox Studio",
    "wof:placetype":"venue"
},
  "geometry": {"coordinates":[-81.176659,29.472883],"type":"Point"}
}