{
  "type": "Feature",
  "properties": {
    "iso:country":"US",
    "sg:address":"10 US Hwy 90 W",
    "sg:city":"Jacksonville",
    "sg:classifiers":[
        {
            "category":"Government",
            "subcategory":"Office",
            "type":"Public Place"
        }
    ],
    "sg:phone":"+1 904 266 4221",
    "sg:postcode":"32234",
    "sg:province":"FL",
    "sg:tags":[
        "city"
    ],
    "wof:name":"Town of Baldwin",
    "wof:placetype":"venue"
},
  "geometry": {"coordinates":[-81.976405,30.302781],"type":"Point"}
}