{
  "type": "Feature",
  "properties": {
    "iso:country":"US",
    "sg:address":"713 S Orange Ave",
    "sg:city":"Sarasota",
    "sg:classifiers":[
        {
            "category":"Professional",
            "subcategory":"Accounting & Tax Preparation",
            "type":"Services"
        },
        {
            "category":"Banks & Credit Unions",
            "subcategory":"Financial Services",
            "type":"Services"
        }
    ],
    "sg:phone":"+1 941 953 4585",
    "sg:postcode":"34236",
    "sg:province":"FL",
    "sg:tags":[
        "consultant",
        "planning",
        "return",
        "bookkeeping"
    ],
    "sg:website":"http://www.cohenflorida.com",
    "wof:name":"Cohen Florida CPA'S",
    "wof:placetype":"venue"
},
  "geometry": {"coordinates":[-82.53854699999999,27.330148],"type":"Point"}
}