{
  "type": "Feature",
  "properties": {
    "addr:full":"1747 Sparkling Water Cir Ocoee FL 34761",
    "addr:housenumber":"1747",
    "addr:postcode":"34761",
    "addr:street":"Sparkling Water Cir",
    "iso:country":"US",
    "sg:address":"1747 Sparkling Water Cir",
    "sg:city":"Ocoee",
    "sg:classifiers":[
        {
            "category":"Shopping",
            "subcategory":"Bicycles & Sporting Goods",
            "type":"Retail Goods"
        },
        {
            "category":"Wholesale",
            "subcategory":"Sporting Goods",
            "type":"Manufacturing & Wholesale Goods"
        }
    ],
    "sg:phone":"+1 407 445 5141",
    "sg:postcode":"34761",
    "sg:province":"FL",
    "sg:tags":[
        "equipment",
        "manufacturer",
        "golf",
        "supplies-wholesale",
        "supply"
    ],
    "wof:name":"Unique Towels & Accessories",
    "wof:placetype":"venue"
},
  "geometry": {"coordinates":[-81.516993,28.584015],"type":"Point"}
}