{
  "type": "Feature",
  "properties": {
    "addr:full":"13186 NW 18th Ct Pembroke Pines FL 33028",
    "addr:housenumber":"13186",
    "addr:postcode":"33028",
    "addr:street":"Nw 18Th Ct",
    "iso:country":"US",
    "sg:address":"13186 NW 18th Ct",
    "sg:city":"Pembroke Pines",
    "sg:classifiers":[
        {
            "category":"Retail",
            "subcategory":"Car Wash",
            "type":"Services"
        }
    ],
    "sg:phone":"+1 954 592 3164",
    "sg:postcode":"33028",
    "sg:province":"FL",
    "sg:tags":[
        "automobile",
        "detail",
        "clean"
    ],
    "wof:name":"Boat Detailing & Marine Svc",
    "wof:placetype":"venue"
},
  "geometry": {"coordinates":[-80.32540299999999,26.024976],"type":"Point"}
}