{
  "type": "Feature",
  "properties": {
    "addr:full":"9400 Atlantic Blvd Jacksonville FL 32225",
    "addr:housenumber":"9400",
    "addr:postcode":"32225",
    "addr:street":"Atlantic Blvd",
    "iso:country":"US",
    "sg:address":"9400 Atlantic Blvd",
    "sg:city":"Jacksonville",
    "sg:classifiers":[
        {
            "category":"Professional",
            "subcategory":"Business Services",
            "type":"Services"
        }
    ],
    "sg:phone":"+1 904 855 0701",
    "sg:postcode":"32225",
    "sg:province":"FL",
    "sg:tags":[
        "embroidery"
    ],
    "wof:name":"Embroidme",
    "wof:placetype":"venue"
},
  "geometry": {"coordinates":[-81.55272600000001,30.3199],"type":"Point"}
}