{
  "type": "Feature",
  "properties": {
    "addr:full":"109 W Ponkan Rd Apopka FL 32712",
    "addr:housenumber":"109",
    "addr:postcode":"32712",
    "addr:street":"W Ponkan Rd",
    "iso:country":"US",
    "sg:address":"109 W Ponkan Rd",
    "sg:city":"Apopka",
    "sg:classifiers":[
        {
            "category":"Building & Trades",
            "subcategory":"Construction",
            "type":"Services"
        }
    ],
    "sg:phone":"+1 407 814 9165",
    "sg:postcode":"32712",
    "sg:province":"FL",
    "sg:tags":[
        "residential"
    ],
    "wof:name":"Henson Homes Inc",
    "wof:placetype":"venue"
},
  "geometry": {"coordinates":[-81.51377599999999,28.728292],"type":"Point"}
}