{
  "type": "Feature",
  "properties": {
    "iso:country":"US",
    "sg:address":"5001 W Sand Lake Rd",
    "sg:city":"Orlando",
    "sg:classifiers":[
        {
            "category":"Retail",
            "subcategory":"Auto Repair",
            "type":"Services"
        }
    ],
    "sg:phone":"+1 407 226 8321",
    "sg:postcode":"32819",
    "sg:province":"FL",
    "sg:tags":[
        "body",
        "automobile",
        "painting"
    ],
    "wof:name":"Specialty Auto Body Inc",
    "wof:placetype":"venue"
},
  "geometry": {"coordinates":[-81.448982,28.450048],"type":"Point"}
}