{
  "type": "Feature",
  "properties": {
    "addr:full":"3129 11th St SW Vero Beach FL 32968",
    "addr:housenumber":"3129",
    "addr:postcode":"32968",
    "addr:street":"11Th St Sw",
    "iso:country":"US",
    "sg:address":"3129 11th St SW",
    "sg:city":"Vero Beach",
    "sg:classifiers":[
        {
            "category":"Building & Trades",
            "subcategory":"Construction",
            "type":"Services"
        }
    ],
    "sg:phone":"+1 772 770 0814",
    "sg:postcode":"32968",
    "sg:province":"FL",
    "sg:tags":[
        "marble",
        "terrazzo"
    ],
    "wof:name":"Classic Terrazzo & Marble",
    "wof:placetype":"venue"
},
  "geometry": {"coordinates":[-80.419139,27.58336],"type":"Point"}
}