{
  "type": "Feature",
  "properties": {
    "addr:full":"4377 Aldon Ct Palm Harbor FL 34685",
    "addr:housenumber":"4377",
    "addr:postcode":"34685",
    "addr:street":"Aldon Ct",
    "iso:country":"US",
    "sg:address":"4377 Aldon Ct",
    "sg:city":"Palm Harbor",
    "sg:classifiers":[
        {
            "category":"Building & Trades",
            "subcategory":"Construction",
            "type":"Services"
        }
    ],
    "sg:phone":"+1 727 785 1961",
    "sg:postcode":"34685",
    "sg:province":"FL",
    "sg:tags":[
        "builder",
        "operative"
    ],
    "wof:name":"Jjc Development Inc",
    "wof:placetype":"venue"
},
  "geometry": {"coordinates":[-82.698965,28.114177],"type":"Point"}
}