{
  "type": "Feature",
  "properties": {
    "iso:country":"US",
    "sg:address":"11070 Intermodal Way",
    "sg:city":"Orlando",
    "sg:classifiers":[
        {
            "category":"Local Transit",
            "type":"Transportation"
        },
        {
            "category":"Taxi",
            "type":"Transportation"
        }
    ],
    "sg:phone":"+1 407 855 4600",
    "sg:postcode":"32824",
    "sg:province":"FL",
    "sg:tags":[
        "operator",
        "taxicab",
        "tour"
    ],
    "wof:name":"Tropical Tours & Trnsprtn",
    "wof:placetype":"venue"
},
  "geometry": {"coordinates":[-81.375945,28.404965],"type":"Point"}
}