{
  "type": "Feature",
  "properties": {
    "iso:country":"US",
    "sg:address":"208 Red Coach Ct",
    "sg:city":"Sanford",
    "sg:classifiers":[
        {
            "category":"Building & Trades",
            "subcategory":"Cleaning & Sanitation",
            "type":"Services"
        }
    ],
    "sg:phone":"+1 407 328 5118",
    "sg:postcode":"32773",
    "sg:province":"FL",
    "sg:tags":[
        "butler",
        "maid"
    ],
    "wof:name":"Dawn Martocchio Housework Maid",
    "wof:placetype":"venue"
},
  "geometry": {"coordinates":[-81.27711499999999,28.756116],"type":"Point"}
}