{
  "type": "Feature",
  "properties": {
    "iso:country":"US",
    "sg:address":"13930 Grover Rd",
    "sg:city":"Jacksonville",
    "sg:classifiers":[
        {
            "category":"Personal",
            "subcategory":"Beauty Salon",
            "type":"Services"
        }
    ],
    "sg:phone":"+1 904 751 8800",
    "sg:postcode":"32226",
    "sg:province":"FL",
    "sg:tags":[
        "shop"
    ],
    "wof:name":"Upper Cuts Lawn Maintance",
    "wof:placetype":"venue"
},
  "geometry": {"coordinates":[-81.554329,30.464686],"type":"Point"}
}