{
  "type": "Feature",
  "properties": {
    "iso:country":"US",
    "sg:address":"5120 Station Way",
    "sg:city":"Sarasota",
    "sg:classifiers":[
        {
            "category":"Retail",
            "subcategory":"Event Space",
            "type":"Services"
        },
        {
            "category":"Conference Center",
            "type":"Public Place"
        }
    ],
    "sg:phone":"+1 941 922 1948",
    "sg:postcode":"34233",
    "sg:province":"FL",
    "sg:tags":[
        "convention",
        "planning",
        "meeting",
        "facility"
    ],
    "sg:website":"http://www.coordinationplus.com",
    "wof:name":"Coordination Plus",
    "wof:placetype":"venue"
},
  "geometry": {"coordinates":[-82.46531400000001,27.2723],"type":"Point"}
}