{
  "type": "Feature",
  "properties": {
    "iso:country":"US",
    "sg:address":"1205 Chesterfield Ct",
    "sg:city":"Eustis",
    "sg:classifiers":[
        {
            "category":"Manufacturing",
            "subcategory":"Printing",
            "type":"Manufacturing & Wholesale Goods"
        }
    ],
    "sg:phone":"+1 352 589 6318",
    "sg:postcode":"32726",
    "sg:province":"FL",
    "sg:tags":[
        "publishing"
    ],
    "wof:name":"Blb Studios",
    "wof:placetype":"venue"
},
  "geometry": {"coordinates":[-81.675556,28.838931],"type":"Point"}
}