{
  "type": "Feature",
  "properties": {
    "iso:country":"US",
    "sg:address":"1741 45th St",
    "sg:city":"West Palm Beach",
    "sg:classifiers":[
        {
            "category":"Banks & Credit Unions",
            "subcategory":"Bank",
            "type":"Services"
        }
    ],
    "sg:phone":"+1 561 842 4952",
    "sg:postcode":"33407",
    "sg:province":"FL",
    "sg:tags":[
        "loan"
    ],
    "wof:name":"Florida Advance Internet",
    "wof:placetype":"venue"
},
  "geometry": {"coordinates":[-80.08152,26.755999],"type":"Point"}
}