{
  "type": "Feature",
  "properties": {
    "iso:country":"US",
    "sg:address":"2746 Leonard Reid Ave",
    "sg:city":"Sarasota",
    "sg:classifiers":[
        {
            "category":"Shopping",
            "subcategory":"Catalog Store",
            "type":"Retail Goods"
        },
        {
            "category":"Government",
            "subcategory":"Post Office",
            "type":"Public Place"
        }
    ],
    "sg:phone":"+1 941 358 1981",
    "sg:postcode":"34234",
    "sg:province":"FL",
    "sg:tags":[
        "stamp",
        "mail",
        "order",
        "online"
    ],
    "wof:name":"R & P Auto Works Inc",
    "wof:placetype":"venue"
},
  "geometry": {"coordinates":[-82.527584,27.360078],"type":"Point"}
}