{
  "type": "Feature",
  "properties": {
    "iso:country":"US",
    "sg:address":"2151 Loch Rane Blvd",
    "sg:city":"Orange Park",
    "sg:classifiers":[
        {
            "category":"Restaurant",
            "type":"Food & Drink"
        }
    ],
    "sg:phone":"+1 904 298 8080",
    "sg:postcode":"32073",
    "sg:province":"FL",
    "sg:tags":[
        "eating"
    ],
    "wof:name":"Hot Wok",
    "wof:placetype":"venue"
},
  "geometry": {"coordinates":[-81.750094,30.164335],"type":"Point"}
}