{
  "type": "Feature",
  "properties": {
    "iso:country":"US",
    "sg:address":"907 Park Ave",
    "sg:city":"West Palm Beach",
    "sg:classifiers":[
        {
            "category":"Insurance",
            "subcategory":"Insurance Agent",
            "type":"Services"
        }
    ],
    "sg:phone":"+1 561 844 8008",
    "sg:postcode":"33403",
    "sg:province":"FL",
    "wof:name":"Any Kind Insurance",
    "wof:placetype":"venue"
},
  "geometry": {"coordinates":[-80.072468,26.798902],"type":"Point"}
}