{
  "type": "Feature",
  "properties": {
    "iso:country":"US",
    "sg:address":"4540 Dixie Hwy NE",
    "sg:city":"Palm Bay",
    "sg:classifiers":[
        {
            "category":"Autos & Motor Vehicles",
            "subcategory":"Automobile Sales",
            "type":"Retail Goods"
        }
    ],
    "sg:phone":"+1 321 779 0144",
    "sg:postcode":"32905",
    "sg:province":"FL",
    "sg:tags":[
        "car",
        "dealer"
    ],
    "wof:name":"Auto Edge Inc",
    "wof:placetype":"venue"
},
  "geometry": {"coordinates":[-80.575671,28.027157],"type":"Point"}
}