{
  "type": "Feature",
  "properties": {
    "iso:country":"US",
    "sg:address":"4350 Fowler St",
    "sg:city":"Fort Myers",
    "sg:classifiers":[
        {
            "category":"Retail",
            "subcategory":"Auto Rental",
            "type":"Services"
        }
    ],
    "sg:phone":"+1 239 275 3393",
    "sg:postcode":"33901",
    "sg:province":"FL",
    "sg:tags":[
        "renting",
        "car",
        "agency",
        "automobile"
    ],
    "sg:website":"www.enterprise.com",
    "wof:name":"Enterprise Rent-A-Car Company",
    "wof:placetype":"venue"
},
  "geometry": {"coordinates":[-81.86184299999999,26.599318],"type":"Point"}
}