{
  "type": "Feature",
  "properties": {
    "addr:full":"17021 W Dixie Hwy North Miami Beach FL 33160",
    "addr:housenumber":"17021",
    "addr:postcode":"33160",
    "addr:street":"W Dixie Hwy",
    "iso:country":"US",
    "sg:address":"17021 W Dixie Hwy",
    "sg:city":"North Miami Beach",
    "sg:classifiers":[
        {
            "category":"Banks & Credit Unions",
            "subcategory":"Financial Services",
            "type":"Services"
        }
    ],
    "sg:phone":"+1 305 682 8384",
    "sg:postcode":"33160",
    "sg:province":"FL",
    "sg:tags":[
        "broker",
        "mortgage"
    ],
    "wof:name":"Jc Mortgage Financing",
    "wof:placetype":"venue"
},
  "geometry": {"coordinates":[-80.153603,25.932501],"type":"Point"}
}