{
  "type": "Feature",
  "properties": {
    "addr:full":"3875 S Kirkman Rd Orlando FL 32811",
    "addr:housenumber":"3875",
    "addr:postcode":"32811",
    "addr:street":"S Kirkman Rd",
    "iso:country":"US",
    "sg:address":"3875 S Kirkman Rd",
    "sg:city":"Orlando",
    "sg:classifiers":[
        {
            "category":"Restaurant",
            "type":"Food & Drink"
        }
    ],
    "sg:menulink":"http://www.allmenus.com/fl/orlando/36806-ruby-tuesdays/menu/",
    "sg:phone":"+1 407 578 8442",
    "sg:postcode":"32811",
    "sg:province":"FL",
    "sg:tags":[
        "burger",
        "american"
    ],
    "wof:name":"Ruby Tuesdays",
    "wof:placetype":"venue"
},
  "geometry": {"coordinates":[-81.458878,28.507804],"type":"Point"}
}