{
  "type": "Feature",
  "properties": {
    "iso:country":"US",
    "sg:address":"543 US Hwy 92",
    "sg:city":"Longwood",
    "sg:classifiers":[
        {
            "category":"Home & Garden",
            "subcategory":"Carpets & Floor Coverings",
            "type":"Retail Goods"
        }
    ],
    "sg:phone":"+1 407 699 4300",
    "sg:postcode":"32750",
    "sg:province":"FL",
    "wof:name":"Custom Carpet Care Inc",
    "wof:placetype":"venue"
},
  "geometry": {"coordinates":[-81.326466,28.705546],"type":"Point"}
}