{
  "type": "Feature",
  "properties": {
    "iso:country":"US",
    "sg:address":"337 Tidewater Dr",
    "sg:city":"Jacksonville",
    "sg:classifiers":[
        {
            "category":"Building & Trades",
            "subcategory":"Cleaning & Sanitation",
            "type":"Services"
        }
    ],
    "sg:phone":"+1 904 720 2266",
    "sg:postcode":"32211",
    "sg:province":"FL",
    "sg:tags":[
        "janitor"
    ],
    "wof:name":"Unique Hands Cleaning Svc",
    "wof:placetype":"venue"
},
  "geometry": {"coordinates":[-81.588843,30.32036],"type":"Point"}
}