{
  "type": "Feature",
  "properties": {
    "addr:full":"1977 Lanier Ct Winter Park FL 32792",
    "addr:housenumber":"1977",
    "addr:postcode":"32792",
    "addr:street":"Lanier Ct",
    "iso:country":"US",
    "sg:address":"1977 Lanier Ct",
    "sg:city":"Winter Park",
    "sg:classifiers":[
        {
            "category":"Arts & Performance",
            "subcategory":"Theater",
            "type":"Entertainment"
        }
    ],
    "sg:phone":"+1 407 644 5899",
    "sg:postcode":"32792",
    "sg:province":"FL",
    "sg:tags":[
        "musician"
    ],
    "wof:name":"Rent A Rican",
    "wof:placetype":"venue"
},
  "geometry": {"coordinates":[-81.32754199999999,28.581146],"type":"Point"}
}