{
  "type": "Feature",
  "properties": {
    "iso:country":"US",
    "sg:address":"2640 NW 17th Ln",
    "sg:city":"Pompano Beach",
    "sg:classifiers":[
        {
            "category":"Professional",
            "subcategory":"Advertising",
            "type":"Services"
        }
    ],
    "sg:phone":"+1 954 971 2995",
    "sg:postcode":"33064",
    "sg:province":"FL",
    "sg:tags":[
        "outdoor",
        "spec",
        "mfg"
    ],
    "wof:name":"3 M National Advertising",
    "wof:placetype":"venue"
},
  "geometry": {"coordinates":[-80.147665,26.262964],"type":"Point"}
}