{
  "type": "Feature",
  "properties": {
    "addr:full":"10951 Emerald Chase Dr Orlando FL 32836",
    "addr:housenumber":"10951",
    "addr:postcode":"32836",
    "addr:street":"Emerald Chase Dr",
    "iso:country":"US",
    "sg:address":"10951 Emerald Chase Dr",
    "sg:city":"Orlando",
    "sg:classifiers":[
        {
            "category":"Building & Trades",
            "subcategory":"Construction",
            "type":"Services"
        }
    ],
    "sg:phone":"+1 407 876 8688",
    "sg:postcode":"32836",
    "sg:province":"FL",
    "sg:tags":[
        "home",
        "builder"
    ],
    "wof:name":"Stonebridge Homes Model",
    "wof:placetype":"venue"
},
  "geometry": {"coordinates":[-81.510161,28.412087],"type":"Point"}
}