{
  "type": "Feature",
  "properties": {
    "iso:country":"US",
    "sg:address":"5900 Old Ocean Blvd",
    "sg:city":"Boynton Beach",
    "sg:classifiers":[
        {
            "category":"Travel",
            "subcategory":"Travel Agent",
            "type":"Entertainment"
        }
    ],
    "sg:phone":"+1 561 732 3304",
    "sg:postcode":"33435",
    "sg:province":"FL",
    "sg:tags":[
        "agency"
    ],
    "wof:name":"Travel Mart Inc",
    "wof:placetype":"venue"
},
  "geometry": {"coordinates":[-80.049134,26.51745],"type":"Point"}
}