{
  "type": "Feature",
  "properties": {
    "iso:country":"US",
    "sg:address":"405 Horseshoe Ln",
    "sg:city":"Winter Haven",
    "sg:classifiers":[
        {
            "category":"Shopping",
            "type":"Retail Goods"
        },
        {
            "category":"Professional",
            "subcategory":"Business Services",
            "type":"Services"
        }
    ],
    "sg:phone":"+1 863 297 9373",
    "sg:postcode":"33881",
    "sg:province":"FL",
    "sg:tags":[
        "water",
        "equipment",
        "treatment",
        "purification"
    ],
    "wof:name":"Central Florida Resources Inc",
    "wof:placetype":"venue"
},
  "geometry": {"coordinates":[-81.666946,28.046578],"type":"Point"}
}