{
  "type": "Feature",
  "properties": {
    "addr:full":"5485 NW 49th Ct Pompano Beach FL 33073",
    "addr:housenumber":"5485",
    "addr:postcode":"33073",
    "addr:street":"Nw 49Th Ct",
    "iso:country":"US",
    "sg:address":"5485 NW 49th Ct",
    "sg:city":"Pompano Beach",
    "sg:classifiers":[
        {
            "category":"Freight",
            "type":"Transportation"
        }
    ],
    "sg:phone":"+1 954 420 1080",
    "sg:postcode":"33073",
    "sg:province":"FL",
    "sg:tags":[
        "operator",
        "local",
        "trucking"
    ],
    "wof:name":"Parchies Trucking Inc",
    "wof:placetype":"venue"
},
  "geometry": {"coordinates":[-80.188619,26.290745],"type":"Point"}
}