{
  "type": "Feature",
  "properties": {
    "iso:country":"US",
    "sg:address":"2142 NW 20th St",
    "sg:city":"Miami",
    "sg:classifiers":[
        {
            "category":"Manufacturing",
            "subcategory":"Jewelry",
            "type":"Manufacturing & Wholesale Goods"
        },
        {
            "category":"Shopping",
            "subcategory":"Jewelry",
            "type":"Retail Goods"
        }
    ],
    "sg:phone":"+1 305 545 5511",
    "sg:postcode":"33142",
    "sg:province":"FL",
    "sg:tags":[
        "stone"
    ],
    "sg:website":"www.orolaminado.com",
    "wof:name":"Skill Jewelry Inc",
    "wof:placetype":"venue"
},
  "geometry": {"coordinates":[-80.231475,25.79452],"type":"Point"}
}