{
  "type": "Feature",
  "properties": {
    "addr:full":"1101 J W Hunt Blvd Panama City FL 32404",
    "addr:housenumber":"1101",
    "addr:postcode":"32404",
    "addr:street":"J W Hunt Blvd",
    "iso:country":"US",
    "sg:address":"1101 J W Hunt Blvd",
    "sg:city":"Panama City",
    "sg:classifiers":[
        {
            "category":"Organizations",
            "subcategory":"Religious Organization",
            "type":"Services"
        }
    ],
    "sg:phone":"+1 850 785 4097",
    "sg:postcode":"32404",
    "sg:province":"FL",
    "wof:name":"Springfield Community Church",
    "wof:placetype":"venue"
},
  "geometry": {"coordinates":[-85.603607,30.167558],"type":"Point"}
}