{
  "type": "Feature",
  "properties": {
    "iso:country":"US",
    "sg:address":"11240 N Kendall Dr",
    "sg:city":"Miami",
    "sg:classifiers":[
        {
            "category":"Real Estate",
            "subcategory":"Real Estate Services",
            "type":"Services"
        },
        {
            "category":"Banks & Credit Unions",
            "subcategory":"Financial Services",
            "type":"Services"
        }
    ],
    "sg:phone":"+1 305 271 1884",
    "sg:postcode":"33176",
    "sg:province":"FL",
    "sg:tags":[
        "loan",
        "processing"
    ],
    "wof:name":"Marie's Florals",
    "wof:placetype":"venue"
},
  "geometry": {"coordinates":[-80.378069,25.686476],"type":"Point"}
}