{
  "type": "Feature",
  "properties": {
    "addr:full":"4244 Evans Ave Fort Myers FL 33901",
    "addr:housenumber":"4244",
    "addr:postcode":"33901",
    "addr:street":"Evans Ave",
    "iso:country":"US",
    "sg:address":"4244 Evans Ave",
    "sg:city":"Fort Myers",
    "sg:classifiers":[
        {
            "category":"Social Services",
            "subcategory":"Child Care",
            "type":"Services"
        }
    ],
    "sg:phone":"+1 239 277 0514",
    "sg:postcode":"33901",
    "sg:province":"FL",
    "wof:name":"Shining Stars Children's Ctr",
    "wof:placetype":"venue"
},
  "geometry": {"coordinates":[-81.858721,26.598291],"type":"Point"}
}