{
  "type": "Feature",
  "properties": {
    "iso:country":"US",
    "sg:address":"13192 SW 130th Ter",
    "sg:city":"Miami",
    "sg:classifiers":[
        {
            "category":"Wholesale",
            "subcategory":"Computers",
            "type":"Manufacturing & Wholesale Goods"
        }
    ],
    "sg:phone":"+1 786 573 5446",
    "sg:postcode":"33186",
    "sg:province":"FL",
    "sg:tags":[
        "repair",
        "printer",
        "laser",
        "supply"
    ],
    "wof:name":"Graphictechnologies",
    "wof:placetype":"venue"
},
  "geometry": {"coordinates":[-80.405874,25.64611],"type":"Point"}
}