{
  "type": "Feature",
  "properties": {
    "addr:full":"8000 NW 21st St Doral FL 33122",
    "addr:housenumber":"8000",
    "addr:postcode":"33122",
    "addr:street":"Nw 21St St",
    "iso:country":"US",
    "sg:address":"8000 NW 21st St",
    "sg:city":"Doral",
    "sg:classifiers":[
        {
            "category":"Health Services",
            "subcategory":"Doctor",
            "type":"Services"
        }
    ],
    "sg:phone":"+1 305 477 2329",
    "sg:postcode":"33122",
    "sg:province":"FL",
    "sg:tags":[
        "clinic"
    ],
    "wof:name":"Metro Dade Fire Fighters",
    "wof:placetype":"venue"
},
  "geometry": {"coordinates":[-80.32810499999999,25.793346],"type":"Point"}
}