{
  "type": "Feature",
  "properties": {
    "addr:full":"423 Co Rd 21 Hawthorne FL 32640",
    "addr:housenumber":"423;21",
    "addr:postcode":"32640",
    "addr:street":"Co Rd",
    "iso:country":"US",
    "sg:address":"423 Co Rd 21",
    "sg:city":"Hawthorne",
    "sg:classifiers":[
        {
            "category":"Organizations",
            "subcategory":"Religious Organization",
            "type":"Services"
        }
    ],
    "sg:phone":"+1 352 481 0011",
    "sg:postcode":"32640",
    "sg:province":"FL",
    "sg:tags":[
        "church"
    ],
    "wof:name":"Community Church Of God",
    "wof:placetype":"venue"
},
  "geometry": {"coordinates":[-81.973575,29.568772],"type":"Point"}
}