{
  "type": "Feature",
  "properties": {
    "addr:full":"5625 Strand Blvd Naples FL 34110",
    "addr:housenumber":"5625",
    "addr:postcode":"34110",
    "addr:street":"Strand Blvd",
    "iso:country":"US",
    "sg:address":"5625 Strand Blvd",
    "sg:city":"Naples",
    "sg:classifiers":[
        {
            "category":"Banks & Credit Unions",
            "subcategory":"Bank",
            "type":"Services"
        }
    ],
    "sg:phone":"+1 239 597 4614",
    "sg:postcode":"34110",
    "sg:province":"FL",
    "sg:tags":[
        "loan"
    ],
    "wof:name":"Wells Fargo Private Client Svc",
    "wof:placetype":"venue"
},
  "geometry": {"coordinates":[-81.746009,26.276263],"type":"Point"}
}