{
  "type": "Feature",
  "properties": {
    "addr:full":"3102 Old Dixie Hwy Stuart FL 34994",
    "addr:housenumber":"3102",
    "addr:postcode":"34994",
    "addr:street":"Old Dixie Hwy",
    "iso:country":"US",
    "sg:address":"3102 Old Dixie Hwy",
    "sg:city":"Stuart",
    "sg:classifiers":[
        {
            "category":"Freight",
            "type":"Transportation"
        }
    ],
    "sg:phone":"+1 772 287 6065",
    "sg:postcode":"34994",
    "sg:province":"FL",
    "sg:tags":[
        "mover"
    ],
    "wof:name":"Stuart Moving Svc",
    "wof:placetype":"venue"
},
  "geometry": {"coordinates":[-80.220811,27.166892],"type":"Point"}
}