{
  "type": "Feature",
  "properties": {
    "addr:full":"6800 SW 40th St Miami FL 33155",
    "addr:housenumber":"6800",
    "addr:postcode":"33155",
    "addr:street":"Sw 40Th St",
    "iso:country":"US",
    "sg:address":"6800 SW 40th St",
    "sg:city":"Miami",
    "sg:classifiers":[
        {
            "category":"Retail",
            "subcategory":"Auto Repair",
            "type":"Services"
        }
    ],
    "sg:phone":"+1 305 266 7790",
    "sg:postcode":"33155",
    "sg:province":"FL",
    "sg:tags":[
        "wrecker"
    ],
    "wof:name":"A1A Wrecker Svc",
    "wof:placetype":"venue"
},
  "geometry": {"coordinates":[-80.306325,25.733234],"type":"Point"}
}