{
  "type": "Feature",
  "properties": {
    "iso:country":"US",
    "sg:address":"4554 Central Ave",
    "sg:city":"St Petersburg",
    "sg:classifiers":[
        {
            "category":"Freight",
            "type":"Transportation"
        }
    ],
    "sg:phone":"+1 727 525 8559",
    "sg:postcode":"33711",
    "sg:province":"FL",
    "sg:tags":[
        "hauling",
        "trucking"
    ],
    "wof:name":"A Able Roofing Co & Hauling",
    "wof:placetype":"venue"
},
  "geometry": {"coordinates":[-82.695064,27.770848],"type":"Point"}
}