{
  "type": "Feature",
  "properties": {
    "iso:country":"US",
    "sg:address":"5003 N 40th St",
    "sg:city":"Tampa",
    "sg:classifiers":[
        {
            "category":"Building & Trades",
            "subcategory":"Construction",
            "type":"Services"
        }
    ],
    "sg:phone":"+1 813 626 7709",
    "sg:postcode":"33610",
    "sg:province":"FL",
    "sg:tags":[
        "acoustical",
        "insulation",
        "drywall",
        "contractor"
    ],
    "wof:name":"Smith & Hudson Interiors Inc",
    "wof:placetype":"venue"
},
  "geometry": {"coordinates":[-82.41401999999999,27.990991],"type":"Point"}
}