{
  "type": "Feature",
  "properties": {
    "iso:country":"US",
    "sg:address":"1028 14th Ave N",
    "sg:city":"Jacksonville Beach",
    "sg:classifiers":[
        {
            "category":"Building & Trades",
            "subcategory":"Landscaping Services",
            "type":"Services"
        }
    ],
    "sg:phone":"+1 904 246 4722",
    "sg:postcode":"32250",
    "sg:province":"FL",
    "wof:name":"Mr Gs Lawn Care",
    "wof:placetype":"venue"
},
  "geometry": {"coordinates":[-81.405342,30.302105],"type":"Point"}
}