{
  "type": "Feature",
  "properties": {
    "iso:country":"US",
    "sg:address":"721 Industrial Dr",
    "sg:city":"Wildwood",
    "sg:classifiers":[
        {
            "category":"Manufacturing",
            "subcategory":"Metals",
            "type":"Manufacturing & Wholesale Goods"
        }
    ],
    "sg:phone":"+1 352 748 7200",
    "sg:postcode":"34785",
    "sg:province":"FL",
    "sg:tags":[
        "steel",
        "shape",
        "structural",
        "cold",
        "mfg"
    ],
    "sg:website":"www.dietrichindustries.com",
    "wof:name":"Dietrich Industries Inc",
    "wof:placetype":"venue"
},
  "geometry": {"coordinates":[-82.05382,28.85228],"type":"Point"}
}