{
  "type": "Feature",
  "properties": {
    "addr:full":"4141 Southpoint Dr E Jacksonville FL 32216",
    "addr:housenumber":"4141",
    "addr:postcode":"32216",
    "addr:street":"Southpoint Dr E",
    "iso:country":"US",
    "sg:address":"4141 Southpoint Dr E",
    "sg:city":"Jacksonville",
    "sg:classifiers":[
        {
            "category":"Building & Trades",
            "subcategory":"Construction",
            "type":"Services"
        }
    ],
    "sg:phone":"+1 904 332 6111",
    "sg:postcode":"32216",
    "sg:province":"FL",
    "sg:tags":[
        "home",
        "builder"
    ],
    "wof:name":"Vintage Group",
    "wof:placetype":"venue"
},
  "geometry": {"coordinates":[-81.586112,30.256731],"type":"Point"}
}