{
  "type": "Feature",
  "properties": {
    "iso:country":"US",
    "sg:address":"4290 NE Indian River Dr",
    "sg:city":"Jensen Beach",
    "sg:classifiers":[
        {
            "category":"Shopping",
            "type":"Retail Goods"
        }
    ],
    "sg:phone":"+1 772 334 0800",
    "sg:postcode":"34957",
    "sg:province":"FL",
    "sg:tags":[
        "merchandise"
    ],
    "wof:name":"Pratt Design",
    "wof:placetype":"venue"
},
  "geometry": {"coordinates":[-80.23082100000001,27.257846],"type":"Point"}
}