{
  "type": "Feature",
  "properties": {
    "addr:full":"4007 Post St Jacksonville FL 32205",
    "addr:housenumber":"4007",
    "addr:postcode":"32205",
    "addr:street":"Post St",
    "iso:country":"US",
    "sg:address":"4007 Post St",
    "sg:city":"Jacksonville",
    "sg:classifiers":[
        {
            "category":"Retail",
            "subcategory":"Auto Repair",
            "type":"Services"
        }
    ],
    "sg:phone":"+1 904 388 2340",
    "sg:postcode":"32205",
    "sg:province":"FL",
    "sg:tags":[
        "repairing",
        "automobile"
    ],
    "wof:name":"Mc Corvey Auto Repair",
    "wof:placetype":"venue"
},
  "geometry": {"coordinates":[-81.717404,30.313135],"type":"Point"}
}