{
  "type": "Feature",
  "properties": {
    "iso:country":"US",
    "sg:address":"6805 33rd St E",
    "sg:city":"Sarasota",
    "sg:classifiers":[
        {
            "category":"Wholesale",
            "subcategory":"Medical Equipment & Supplies",
            "type":"Manufacturing & Wholesale Goods"
        }
    ],
    "sg:phone":"+1 941 758 1772",
    "sg:postcode":"34243",
    "sg:province":"FL",
    "sg:tags":[
        "instrument",
        "ophthalmic"
    ],
    "wof:name":"Standard Antiseptic Inc",
    "wof:placetype":"venue"
},
  "geometry": {"coordinates":[-82.52187499999999,27.424871],"type":"Point"}
}