{
  "type": "Feature",
  "properties": {
    "iso:country":"US",
    "sg:address":"6040 Pennsylvania Ave",
    "sg:city":"New Port Richey",
    "sg:classifiers":[
        {
            "category":"Health Services",
            "subcategory":"Doctor",
            "type":"Services"
        }
    ],
    "sg:phone":"+1 727 849 1700",
    "sg:postcode":"34653",
    "sg:province":"FL",
    "sg:tags":[
        "dentist"
    ],
    "wof:name":"Theodore Kaduk DDS",
    "wof:placetype":"venue"
},
  "geometry": {"coordinates":[-82.71418199999999,28.252534],"type":"Point"}
}