{
  "type": "Feature",
  "properties": {
    "iso:country":"US",
    "sg:address":"8204 NW 14th St",
    "sg:city":"Doral",
    "sg:classifiers":[
        {
            "category":"Retail",
            "subcategory":"Auto Rental",
            "type":"Services"
        }
    ],
    "sg:phone":"+1 305 379 7041",
    "sg:postcode":"33126",
    "sg:province":"FL",
    "sg:tags":[
        "car"
    ],
    "wof:name":"Vetromile & Associates",
    "wof:placetype":"venue"
},
  "geometry": {"coordinates":[-80.32881500000001,25.786124],"type":"Point"}
}