{
  "type": "Feature",
  "properties": {
    "addr:full":"2100 Lake Ida Rd Delray Beach FL 33445",
    "addr:housenumber":"2100",
    "addr:postcode":"33445",
    "addr:street":"Lake Ida Rd",
    "iso:country":"US",
    "sg:address":"2100 Lake Ida Rd",
    "sg:city":"Delray Beach",
    "sg:classifiers":[
        {
            "category":"Health Services",
            "subcategory":"Medical Lab",
            "type":"Services"
        }
    ],
    "sg:phone":"+1 561 750 4686",
    "sg:postcode":"33445",
    "sg:province":"FL",
    "sg:tags":[
        "laboratory"
    ],
    "wof:name":"Dental Technologies",
    "wof:placetype":"venue"
},
  "geometry": {"coordinates":[-80.09854199999999,26.473052],"type":"Point"}
}