{
  "type": "Feature",
  "properties": {
    "addr:full":"840 S Harbor City Blvd Melbourne FL 32901",
    "addr:housenumber":"840",
    "addr:postcode":"32901",
    "addr:street":"S Harbor City Blvd",
    "iso:country":"US",
    "sg:address":"840 S Harbor City Blvd",
    "sg:city":"Melbourne",
    "sg:classifiers":[
        {
            "category":"Autos & Motor Vehicles",
            "subcategory":"Auto Supplies",
            "type":"Retail Goods"
        },
        {
            "category":"Retail",
            "subcategory":"Auto Repair",
            "type":"Services"
        }
    ],
    "sg:phone":"+1 321 727 7715",
    "sg:postcode":"32901",
    "sg:province":"FL",
    "sg:tags":[
        "tire"
    ],
    "wof:name":"Gator Chrysler Dodge Jeep",
    "wof:placetype":"venue"
},
  "geometry": {"coordinates":[-80.611549,28.09687],"type":"Point"}
}