{
  "type": "Feature",
  "properties": {
    "addr:full":"3225 E 4th Ave Tampa FL 33605",
    "addr:housenumber":"3225",
    "addr:postcode":"33605",
    "addr:street":"E 4Th Ave",
    "iso:country":"US",
    "sg:address":"3225 E 4th Ave",
    "sg:city":"Tampa",
    "sg:classifiers":[
        {
            "category":"Building & Trades",
            "subcategory":"Electrical",
            "type":"Services"
        }
    ],
    "sg:phone":"+1 813 248 1711",
    "sg:postcode":"33605",
    "sg:province":"FL",
    "sg:tags":[
        "electrician"
    ],
    "wof:name":"Electric Properties",
    "wof:placetype":"venue"
},
  "geometry": {"coordinates":[-82.42369600000001,27.958031],"type":"Point"}
}