{
  "type": "Feature",
  "properties": {
    "iso:country":"US",
    "sg:address":"1403 W Boynton Beach Blvd",
    "sg:city":"Boynton Beach",
    "sg:classifiers":[
        {
            "category":"Building & Trades",
            "subcategory":"Construction",
            "type":"Services"
        }
    ],
    "sg:phone":"+1 561 737 4914",
    "sg:postcode":"33426",
    "sg:province":"FL",
    "sg:tags":[
        "tile",
        "dealer"
    ],
    "wof:name":"Ross Interiors",
    "wof:placetype":"venue"
},
  "geometry": {"coordinates":[-80.090487,26.527683],"type":"Point"}
}