{
  "type": "Feature",
  "properties": {
    "iso:country":"US",
    "sg:address":"6248 Halyard Ct",
    "sg:city":"Rockledge",
    "sg:classifiers":[
        {
            "category":"Banks & Credit Unions",
            "subcategory":"Investment Brokerage",
            "type":"Services"
        }
    ],
    "sg:phone":"+1 321 636 5737",
    "sg:postcode":"32955",
    "sg:province":"FL",
    "sg:tags":[
        "advisory"
    ],
    "wof:name":"National Assoc 401 K Investors",
    "wof:placetype":"venue"
},
  "geometry": {"coordinates":[-80.67675800000001,28.240944],"type":"Point"}
}