{
  "type": "Feature",
  "properties": {
    "iso:country":"US",
    "sg:address":"1147 Caravan Loop",
    "sg:city":"Davenport",
    "sg:classifiers":[
        {
            "category":"Real Estate",
            "subcategory":"Real Estate Agent",
            "type":"Services"
        }
    ],
    "sg:phone":"+1 863 420 6522",
    "sg:postcode":"33868",
    "sg:province":"FL",
    "wof:name":"R D & C Management",
    "wof:placetype":"venue"
},
  "geometry": {"coordinates":[-81.84072,28.177512],"type":"Point"}
}