{
  "type": "Feature",
  "properties": {
    "addr:full":"113 49th St S St Petersburg FL 33707",
    "addr:housenumber":"113",
    "addr:postcode":"33707",
    "addr:street":"49Th St S",
    "iso:country":"US",
    "sg:address":"113 49th St S",
    "sg:city":"St Petersburg",
    "sg:classifiers":[
        {
            "category":"Personal",
            "subcategory":"Beauty Salon",
            "type":"Services"
        }
    ],
    "sg:phone":"+1 727 328 0763",
    "sg:postcode":"33707",
    "sg:province":"FL",
    "wof:name":"West African Hair Braiding",
    "wof:placetype":"venue"
},
  "geometry": {"coordinates":[-82.699928,27.769249],"type":"Point"}
}