{
  "type": "Feature",
  "properties": {
    "addr:full":"7260 Reserve Creek Dr Port Saint Lucie FL 34986",
    "addr:housenumber":"7260",
    "addr:postcode":"34986",
    "addr:street":"Reserve Creek Dr",
    "iso:country":"US",
    "sg:address":"7260 Reserve Creek Dr",
    "sg:city":"Port Saint Lucie",
    "sg:classifiers":[
        {
            "category":"Professional",
            "type":"Services"
        }
    ],
    "sg:phone":"+1 772 467 0555",
    "sg:postcode":"34986",
    "sg:province":"FL",
    "wof:name":"Kay Rodriguez Inc",
    "wof:placetype":"venue"
},
  "geometry": {"coordinates":[-80.428331,27.330312],"type":"Point"}
}