{
  "type": "Feature",
  "properties": {
    "iso:country":"US",
    "sg:address":"4150 Brentwood Park Cir",
    "sg:city":"Tampa",
    "sg:classifiers":[
        {
            "category":"Health Services",
            "subcategory":"Doctor",
            "type":"Services"
        }
    ],
    "sg:phone":"+1 813 269 9295",
    "sg:postcode":"33624",
    "sg:province":"FL",
    "sg:tags":[
        "medical"
    ],
    "wof:name":"Carrie Elk Dr",
    "wof:placetype":"venue"
},
  "geometry": {"coordinates":[-82.514213,28.100266],"type":"Point"}
}