{
  "type": "Feature",
  "properties": {
    "iso:country":"US",
    "sg:address":"7345 49th St N",
    "sg:city":"Pinellas Park",
    "sg:classifiers":[
        {
            "category":"Restaurant",
            "type":"Food & Drink"
        }
    ],
    "sg:phone":"+1 727 546 1093",
    "sg:postcode":"33781",
    "sg:province":"FL",
    "sg:tags":[
        "eating"
    ],
    "wof:name":"Busy Bee Restaurant",
    "wof:placetype":"venue"
},
  "geometry": {"coordinates":[-82.699884,27.838815],"type":"Point"}
}