{
  "type": "Feature",
  "properties": {
    "addr:full":"11281 SW 152nd St Miami FL 33157",
    "addr:housenumber":"11281",
    "addr:postcode":"33157",
    "addr:street":"Sw 152Nd St",
    "iso:country":"US",
    "sg:address":"11281 SW 152nd St",
    "sg:city":"Miami",
    "sg:classifiers":[
        {
            "category":"Restaurant",
            "type":"Food & Drink"
        }
    ],
    "sg:menulink":"http://www.allmenus.com/fl/kendall-perrine/46275-subway/menu/",
    "sg:phone":"+1 305 234 6644",
    "sg:postcode":"33157",
    "sg:province":"FL",
    "sg:tags":[
        "american",
        "sandwich"
    ],
    "wof:name":"Subway",
    "wof:placetype":"venue"
},
  "geometry": {"coordinates":[-80.376333,25.627656],"type":"Point"}
}