{
  "type": "Feature",
  "properties": {
    "iso:country":"US",
    "sg:address":"2542 Swanson Ave",
    "sg:city":"Miami",
    "sg:classifiers":[
        {
            "category":"Arts & Performance",
            "subcategory":"Art Gallery",
            "type":"Entertainment"
        }
    ],
    "sg:phone":"+1 305 854 0891",
    "sg:postcode":"33133",
    "sg:province":"FL",
    "sg:tags":[
        "fine",
        "artist"
    ],
    "sg:website":"http://www.lynnfecteau.com",
    "wof:name":"Fecteau Enterprises Inc",
    "wof:placetype":"venue"
},
  "geometry": {"coordinates":[-80.235784,25.736154],"type":"Point"}
}