{
  "type": "Feature",
  "properties": {
    "iso:country":"US",
    "sg:address":"3728 Phillips Hwy",
    "sg:city":"Jacksonville",
    "sg:classifiers":[
        {
            "category":"Professional",
            "subcategory":"Management & Consulting",
            "type":"Services"
        }
    ],
    "sg:phone":"+1 904 346 0356",
    "sg:postcode":"32207",
    "sg:province":"FL",
    "sg:tags":[
        "personnel",
        "consultant"
    ],
    "wof:name":"Ablest Staffing Svc Suite 10",
    "wof:placetype":"venue"
},
  "geometry": {"coordinates":[-81.62900399999999,30.28108],"type":"Point"}
}