{
  "type": "Feature",
  "properties": {
    "addr:full":"431 Roberts Cemetery Rd Wewahitchka FL 32465",
    "addr:housenumber":"431",
    "addr:postcode":"32465",
    "addr:street":"Roberts Cemetery Rd",
    "iso:country":"US",
    "sg:address":"431 Roberts Cemetery Rd",
    "sg:city":"Wewahitchka",
    "sg:classifiers":[
        {
            "category":"Building & Trades",
            "subcategory":"Construction",
            "type":"Services"
        }
    ],
    "sg:phone":"+1 850 639 2144",
    "sg:postcode":"32465",
    "sg:province":"FL",
    "sg:tags":[
        "residential"
    ],
    "wof:name":"Bidwell Co LLC",
    "wof:placetype":"venue"
},
  "geometry": {"coordinates":[-85.18637,30.056471],"type":"Point"}
}