{
  "type": "Feature",
  "properties": {
    "iso:country":"US",
    "sg:address":"316 Ash St",
    "sg:city":"Fernandina Beach",
    "sg:classifiers":[
        {
            "category":"Home & Garden",
            "subcategory":"Home Furnishings",
            "type":"Retail Goods"
        }
    ],
    "sg:phone":"+1 904 277 3737",
    "sg:postcode":"32034",
    "sg:province":"FL",
    "sg:tags":[
        "housewares",
        "gift"
    ],
    "wof:name":"Front & Centre",
    "wof:placetype":"venue"
},
  "geometry": {"coordinates":[-81.463071,30.669829],"type":"Point"}
}