{
  "type": "Feature",
  "properties": {
    "addr:full":"5910 Havana Hwy Havana FL 32333",
    "addr:housenumber":"5910",
    "addr:postcode":"32333",
    "addr:street":"Havana Hwy",
    "iso:country":"US",
    "sg:address":"5910 Havana Hwy",
    "sg:city":"Havana",
    "sg:classifiers":[
        {
            "category":"Place Of Worship",
            "subcategory":"Church",
            "type":"Public Place"
        },
        {
            "category":"Place Of Worship",
            "type":"Public Place"
        }
    ],
    "sg:phone":"+1 850 539 1181",
    "sg:postcode":"32333",
    "sg:province":"FL",
    "sg:tags":[
        "churches-non-denominational"
    ],
    "sg:website":"http://www.tallavana.org",
    "wof:name":"Tallavana Community Church",
    "wof:placetype":"venue"
},
  "geometry": {"coordinates":[-84.47071699999999,30.608133],"type":"Point"}
}