{
  "type": "Feature",
  "properties": {
    "iso:country":"US",
    "sg:address":"123 SE 35th Ter",
    "sg:city":"Cape Coral",
    "sg:classifiers":[
        {
            "category":"Professional",
            "subcategory":"Advertising",
            "type":"Services"
        }
    ],
    "sg:phone":"+1 239 540 1456",
    "sg:postcode":"33904",
    "sg:province":"FL",
    "sg:tags":[
        "designer",
        "display",
        "producer"
    ],
    "wof:name":"Creative Designs",
    "wof:placetype":"venue"
},
  "geometry": {"coordinates":[-81.972284,26.586839],"type":"Point"}
}