{
  "type": "Feature",
  "properties": {
    "iso:country":"US",
    "sg:address":"190 State Rd 62",
    "sg:city":"Bowling Green",
    "sg:classifiers":[
        {
            "category":"Education",
            "subcategory":"Special Training",
            "type":"Public Place"
        }
    ],
    "sg:phone":"+1 863 773 6148",
    "sg:postcode":"33834",
    "sg:province":"FL",
    "wof:name":"Als Tin Cup Driving Range",
    "wof:placetype":"venue"
},
  "geometry": {"coordinates":[-81.825459,27.594972],"type":"Point"}
}