{
  "type": "Feature",
  "properties": {
    "addr:full":"9551 NW 79th Ave Ste 1 Hialeah FL 33016",
    "addr:housenumber":"9551",
    "addr:postcode":"33016",
    "addr:street":"Nw 79Th Ave Ste 1",
    "iso:country":"US",
    "sg:address":"9551 NW 79th Ave Ste 1",
    "sg:city":"Hialeah",
    "sg:classifiers":[
        {
            "category":"Retail",
            "subcategory":"Auto Repair",
            "type":"Services"
        }
    ],
    "sg:phone":"+1 305 828 2877",
    "sg:postcode":"33016",
    "sg:province":"FL",
    "wof:name":"Carrazana Auto Repair & Services",
    "wof:placetype":"venue"
},
  "geometry": {"coordinates":[-80.32558299999999,25.860626],"type":"Point"}
}