{
  "type": "Feature",
  "properties": {
    "addr:full":"3016 US Hwy 301 Tampa FL 33619",
    "addr:housenumber":"3016",
    "addr:postcode":"33619",
    "addr:street":"Us Hwy 301",
    "iso:country":"US",
    "sg:address":"3016 US Hwy 301",
    "sg:city":"Tampa",
    "sg:classifiers":[
        {
            "category":"Real Estate",
            "subcategory":"Architect",
            "type":"Services"
        },
        {
            "category":"Building & Trades",
            "subcategory":"Construction",
            "type":"Services"
        }
    ],
    "sg:phone":"+1 813 630 9578",
    "sg:postcode":"33619",
    "sg:province":"FL",
    "sg:tags":[
        "roofing",
        "engineering",
        "architectural",
        "consultant"
    ],
    "wof:name":"Lyons/Waldron Consulting Group",
    "wof:placetype":"venue"
},
  "geometry": {"coordinates":[-82.360478,27.972811],"type":"Point"}
}