{
  "type": "Feature",
  "properties": {
    "iso:country":"US",
    "sg:address":"19251 NE 26th Ave",
    "sg:city":"Miami",
    "sg:classifiers":[
        {
            "category":"Health Services",
            "subcategory":"Chiropractor",
            "type":"Services"
        }
    ],
    "sg:phone":"+1 305 937 7622",
    "sg:postcode":"33125",
    "sg:province":"FL",
    "wof:name":"Tower Health Center",
    "wof:placetype":"venue"
},
  "geometry": {"coordinates":[-80.149029,25.953922],"type":"Point"}
}