{
  "type": "Feature",
  "properties": {
    "iso:country":"US",
    "sg:address":"29 5th St NW",
    "sg:city":"Winter Haven",
    "sg:classifiers":[
        {
            "category":"Home & Garden",
            "subcategory":"Furniture",
            "type":"Retail Goods"
        },
        {
            "category":"Shopping",
            "subcategory":"Clothing, Apparel, & Fashions",
            "type":"Retail Goods"
        }
    ],
    "sg:phone":"+1 863 294 4911",
    "sg:postcode":"33881",
    "sg:province":"FL",
    "sg:tags":[
        "wear",
        "merchandise"
    ],
    "wof:name":"Baby Carriage Inc",
    "wof:placetype":"venue"
},
  "geometry": {"coordinates":[-81.73199099999999,28.023478],"type":"Point"}
}