{
  "type": "Feature",
  "properties": {
    "iso:country":"US",
    "sg:address":"335 Volusia Ave",
    "sg:city":"Arcadia",
    "sg:classifiers":[
        {
            "category":"Home & Garden",
            "subcategory":"Building Materials",
            "type":"Retail Goods"
        }
    ],
    "sg:phone":"+1 863 993 9633",
    "sg:postcode":"34266",
    "sg:province":"FL",
    "wof:name":"S G O of Sarasota",
    "wof:placetype":"venue"
},
  "geometry": {"coordinates":[-81.856376,27.218264],"type":"Point"}
}