{
  "type": "Feature",
  "properties": {
    "iso:country":"US",
    "sg:address":"5425 Factory Shops Blvd",
    "sg:city":"Ellenton",
    "sg:classifiers":[
        {
            "category":"Food & Beverages",
            "subcategory":"Specialty",
            "type":"Retail Goods"
        }
    ],
    "sg:phone":"+1 941 723 1142",
    "sg:postcode":"34222",
    "sg:province":"FL",
    "sg:tags":[
        "dietary",
        "supplement",
        "vitamin"
    ],
    "wof:name":"Vitamin World 3922",
    "wof:placetype":"venue"
},
  "geometry": {"coordinates":[-82.50433700000001,27.534408],"type":"Point"}
}