{
  "type": "Feature",
  "properties": {
    "addr:full":"1218 Sutton Trl Geneva FL 32732",
    "addr:housenumber":"1218",
    "addr:postcode":"32732",
    "addr:street":"Sutton Trl",
    "iso:country":"US",
    "sg:address":"1218 Sutton Trl",
    "sg:city":"Geneva",
    "sg:classifiers":[
        {
            "category":"Manufacturing",
            "subcategory":"Glass & Minerals",
            "type":"Manufacturing & Wholesale Goods"
        }
    ],
    "sg:phone":"+1 407 349 3225",
    "sg:postcode":"32732",
    "sg:province":"FL",
    "sg:tags":[
        "contractor"
    ],
    "wof:name":"USG Corporation",
    "wof:placetype":"venue"
},
  "geometry": {"coordinates":[-81.089393,28.770087],"type":"Point"}
}