{
  "type": "Feature",
  "properties": {
    "addr:full":"329 Ave de Mayo Sarasota FL 34242",
    "addr:housenumber":"329",
    "addr:postcode":"34242",
    "addr:street":"Ave De Mayo",
    "iso:country":"US",
    "sg:address":"329 Ave de Mayo",
    "sg:city":"Sarasota",
    "sg:classifiers":[
        {
            "category":"Freight",
            "type":"Transportation"
        }
    ],
    "sg:phone":"+1 941 349 6084",
    "sg:postcode":"34242",
    "sg:province":"FL",
    "sg:tags":[
        "commercial",
        "storage"
    ],
    "wof:name":"Add-A-Closet",
    "wof:placetype":"venue"
},
  "geometry": {"coordinates":[-82.56275599999999,27.27616],"type":"Point"}
}