{
  "type": "Feature",
  "properties": {
    "iso:country":"US",
    "sg:address":"143 Palmetto Ave",
    "sg:city":"Freeport",
    "sg:classifiers":[
        {
            "category":"Building & Trades",
            "subcategory":"Construction",
            "type":"Services"
        }
    ],
    "sg:phone":"+1 850 835 1360",
    "sg:postcode":"32439",
    "sg:province":"FL",
    "sg:tags":[
        "wallcoverings-installation",
        "wallpaper",
        "painting",
        "contractor"
    ],
    "wof:name":"Mt's Quality Painting",
    "wof:placetype":"venue"
},
  "geometry": {"coordinates":[-86.11621100000001,30.433639],"type":"Point"}
}