{
  "type": "Feature",
  "properties": {
    "addr:full":"18550 Lynn Rd Fort Myers FL 33917",
    "addr:housenumber":"18550",
    "addr:postcode":"33917",
    "addr:street":"Lynn Rd",
    "iso:country":"US",
    "sg:address":"18550 Lynn Rd",
    "sg:city":"Fort Myers",
    "sg:classifiers":[
        {
            "category":"Building & Trades",
            "subcategory":"Equipment Rental",
            "type":"Services"
        }
    ],
    "sg:phone":"+1 239 543 0862",
    "sg:postcode":"33917",
    "sg:province":"FL",
    "wof:name":"Premier Refreshment Services",
    "wof:placetype":"venue"
},
  "geometry": {"coordinates":[-81.828091,26.728772],"type":"Point"}
}