{
  "type": "Feature",
  "properties": {
    "iso:country":"US",
    "sg:address":"2125 Garnet Ct",
    "sg:city":"Merritt Island",
    "sg:classifiers":[
        {
            "category":"Building & Trades",
            "subcategory":"Plumbing",
            "type":"Services"
        }
    ],
    "sg:phone":"+1 321 452 5114",
    "sg:postcode":"32953",
    "sg:province":"FL",
    "sg:tags":[
        "conditioning",
        "air",
        "system",
        "contractor"
    ],
    "wof:name":"W S Black Co Inc",
    "wof:placetype":"venue"
},
  "geometry": {"coordinates":[-80.70231099999999,28.395562],"type":"Point"}
}