{
  "type": "Feature",
  "properties": {
    "iso:country":"US",
    "sg:address":"3144 SW 61st Ave",
    "sg:city":"Fort Lauderdale",
    "sg:classifiers":[
        {
            "category":"Retail",
            "subcategory":"Auto Repair",
            "type":"Services"
        }
    ],
    "sg:phone":"+1 954 610 8941",
    "sg:postcode":"33314",
    "sg:province":"FL",
    "sg:tags":[
        "automotive"
    ],
    "wof:name":"AJS All Purpose Detailing",
    "wof:placetype":"venue"
},
  "geometry": {"coordinates":[-80.22797,26.081956],"type":"Point"}
}