{
  "type": "Feature",
  "properties": {
    "addr:full":"12520 NW 21st Pl Miami FL 33167",
    "addr:housenumber":"12520",
    "addr:postcode":"33167",
    "addr:street":"Nw 21St Pl",
    "iso:country":"US",
    "sg:address":"12520 NW 21st Pl",
    "sg:city":"Miami",
    "sg:classifiers":[
        {
            "category":"Manufacturing",
            "subcategory":"Printing",
            "type":"Manufacturing & Wholesale Goods"
        }
    ],
    "sg:phone":"+1 305 687 3290",
    "sg:postcode":"33167",
    "sg:province":"FL",
    "sg:tags":[
        "periodical"
    ],
    "wof:name":"Foe Magazine",
    "wof:placetype":"venue"
},
  "geometry": {"coordinates":[-80.23424900000001,25.88807],"type":"Point"}
}