{
  "type": "Feature",
  "properties": {
    "iso:country":"US",
    "sg:address":"66 Crest Dr",
    "sg:city":"Destin",
    "sg:classifiers":[
        {
            "category":"Building & Trades",
            "subcategory":"Construction",
            "type":"Services"
        }
    ],
    "sg:phone":"+1 850 650 1514",
    "sg:postcode":"32550",
    "sg:province":"FL",
    "sg:tags":[
        "framing",
        "custom"
    ],
    "wof:name":"Johnson & White Builders Inc",
    "wof:placetype":"venue"
},
  "geometry": {"coordinates":[-86.359161,30.385855],"type":"Point"}
}