{
  "type": "Feature",
  "properties": {
    "iso:country":"US",
    "sg:address":"8181 W Broward Blvd",
    "sg:city":"Fort Lauderdale",
    "sg:classifiers":[
        {
            "category":"Insurance",
            "subcategory":"Insurance Agent",
            "type":"Services"
        }
    ],
    "sg:phone":"+1 954 370 9429",
    "sg:postcode":"33324",
    "sg:province":"FL",
    "wof:name":"Brodsky & Associates Inc",
    "wof:placetype":"venue"
},
  "geometry": {"coordinates":[-80.25909,26.120823],"type":"Point"}
}