{
  "type": "Feature",
  "properties": {
    "addr:full":"3861 Winter Berry Rd E Jacksonville FL 32210",
    "addr:housenumber":"3861",
    "addr:postcode":"32210",
    "addr:street":"Winter Berry Rd E",
    "iso:country":"US",
    "sg:address":"3861 Winter Berry Rd E",
    "sg:city":"Jacksonville",
    "sg:classifiers":[
        {
            "category":"Retail",
            "subcategory":"Car Wash",
            "type":"Services"
        }
    ],
    "sg:phone":"+1 904 781 3813",
    "sg:postcode":"32210",
    "sg:province":"FL",
    "sg:tags":[
        "automobile",
        "detail",
        "clean"
    ],
    "wof:name":"L J's Detail",
    "wof:placetype":"venue"
},
  "geometry": {"coordinates":[-81.781633,30.265159],"type":"Point"}
}