{
  "type": "Feature",
  "properties": {
    "iso:country":"US",
    "sg:address":"1127 S University Dr",
    "sg:city":"Fort Lauderdale",
    "sg:classifiers":[
        {
            "category":"Health Services",
            "subcategory":"Doctor",
            "type":"Services"
        }
    ],
    "sg:phone":"+1 954 424 4600",
    "sg:postcode":"33324",
    "sg:province":"FL",
    "sg:tags":[
        "clinic",
        "dentist"
    ],
    "wof:name":"Steven M Gilson DMD",
    "wof:placetype":"venue"
},
  "geometry": {"coordinates":[-80.25017200000001,26.106824],"type":"Point"}
}