{
  "type": "Feature",
  "properties": {
    "addr:full":"8840 NW 13th St Hollywood FL 33024",
    "addr:housenumber":"8840",
    "addr:postcode":"33024",
    "addr:street":"Nw 13Th St",
    "iso:country":"US",
    "sg:address":"8840 NW 13th St",
    "sg:city":"Hollywood",
    "sg:classifiers":[
        {
            "category":"Building & Trades",
            "subcategory":"Plumbing",
            "type":"Services"
        }
    ],
    "sg:phone":"+1 954 249 6411",
    "sg:postcode":"33024",
    "sg:province":"FL",
    "sg:tags":[
        "contractor"
    ],
    "wof:name":"Roys Yacht Plumbing",
    "wof:placetype":"venue"
},
  "geometry": {"coordinates":[-80.26219399999999,26.019538],"type":"Point"}
}