{
  "type": "Feature",
  "properties": {
    "iso:country":"US",
    "sg:address":"685 Cloverleaf Blvd",
    "sg:city":"Deltona",
    "sg:classifiers":[
        {
            "category":"Building & Trades",
            "subcategory":"Construction",
            "type":"Services"
        }
    ],
    "sg:phone":"+1 386 574 3156",
    "sg:postcode":"32725",
    "sg:province":"FL",
    "sg:tags":[
        "hanging",
        "contractor"
    ],
    "wof:name":"Ajm Painting Inc",
    "wof:placetype":"venue"
},
  "geometry": {"coordinates":[-81.26506999999999,28.877832],"type":"Point"}
}