{
  "type": "Feature",
  "properties": {
    "addr:full":"3086 Emerson Ave Palm Springs FL 33461",
    "addr:housenumber":"3086",
    "addr:postcode":"33461",
    "addr:street":"Emerson Ave",
    "iso:country":"US",
    "sg:address":"3086 Emerson Ave",
    "sg:city":"Palm Springs",
    "sg:classifiers":[
        {
            "category":"Building & Trades",
            "subcategory":"Plumbing",
            "type":"Services"
        }
    ],
    "sg:phone":"+1 561 965 0144",
    "sg:postcode":"33461",
    "sg:province":"FL",
    "sg:tags":[
        "conditioning",
        "air",
        "system",
        "contractor"
    ],
    "wof:name":"Rice Air Conditioning",
    "wof:placetype":"venue"
},
  "geometry": {"coordinates":[-80.091594,26.635239],"type":"Point"}
}