{
  "type": "Feature",
  "properties": {
    "addr:full":"6900 Silver Star Rd Orlando FL 32818",
    "addr:housenumber":"6900",
    "addr:postcode":"32818",
    "addr:street":"Silver Star Rd",
    "iso:country":"US",
    "sg:address":"6900 Silver Star Rd",
    "sg:city":"Orlando",
    "sg:classifiers":[
        {
            "category":"Organizations",
            "subcategory":"Religious Organization",
            "type":"Services"
        }
    ],
    "sg:phone":"+1 407 522 7275",
    "sg:postcode":"32818",
    "sg:province":"FL",
    "sg:tags":[
        "church"
    ],
    "wof:name":"Cornerstone Christian Comm Chr",
    "wof:placetype":"venue"
},
  "geometry": {"coordinates":[-81.47418999999999,28.577534],"type":"Point"}
}