{
  "type": "Feature",
  "properties": {
    "iso:country":"US",
    "sg:address":"543 Giralda Ave",
    "sg:city":"Deltona",
    "sg:classifiers":[
        {
            "category":"Professional",
            "subcategory":"Accounting & Tax Preparation",
            "type":"Services"
        }
    ],
    "sg:phone":"+1 386 860 6766",
    "sg:postcode":"32725",
    "sg:province":"FL",
    "sg:tags":[
        "return",
        "filing"
    ],
    "wof:name":"Keep Trucking Road Tax Svc",
    "wof:placetype":"venue"
},
  "geometry": {"coordinates":[-81.24199400000001,28.878398],"type":"Point"}
}