{
  "type": "Feature",
  "properties": {
    "iso:country":"US",
    "sg:address":"2245 Darby Ln",
    "sg:city":"Saint Cloud",
    "sg:classifiers":[
        {
            "category":"Retail",
            "subcategory":"Car Wash",
            "type":"Services"
        }
    ],
    "sg:phone":"+1 407 957 1688",
    "sg:postcode":"34769",
    "sg:province":"FL",
    "sg:tags":[
        "carwash"
    ],
    "wof:name":"Charles Perkins Pressure Wash",
    "wof:placetype":"venue"
},
  "geometry": {"coordinates":[-81.291391,28.237153],"type":"Point"}
}