{
  "type": "Feature",
  "properties": {
    "addr:full":"3175 Seagrape Rd Lake Worth FL 33462",
    "addr:housenumber":"3175",
    "addr:postcode":"33462",
    "addr:street":"Seagrape Rd",
    "iso:country":"US",
    "sg:address":"3175 Seagrape Rd",
    "sg:city":"Lake Worth",
    "sg:classifiers":[
        {
            "category":"Professional",
            "subcategory":"Employment Agencies",
            "type":"Services"
        }
    ],
    "sg:phone":"+1 561 432 8812",
    "sg:postcode":"33462",
    "sg:province":"FL",
    "sg:tags":[
        "opportunity"
    ],
    "wof:name":"Continental Job",
    "wof:placetype":"venue"
},
  "geometry": {"coordinates":[-80.09287,26.577031],"type":"Point"}
}