{
  "type": "Feature",
  "properties": {
    "addr:full":"5439 Catalyst Ave Sarasota FL 34233",
    "addr:housenumber":"5439",
    "addr:postcode":"34233",
    "addr:street":"Catalyst Ave",
    "iso:country":"US",
    "sg:address":"5439 Catalyst Ave",
    "sg:city":"Sarasota",
    "sg:classifiers":[
        {
            "category":"Retail",
            "subcategory":"Auto Repair",
            "type":"Services"
        }
    ],
    "sg:phone":"+1 941 922 7484",
    "sg:postcode":"34233",
    "sg:province":"FL",
    "sg:tags":[
        "repairing",
        "automobile"
    ],
    "wof:name":"Performance Auto Care",
    "wof:placetype":"venue"
},
  "geometry": {"coordinates":[-82.474841,27.273658],"type":"Point"}
}