{
  "type": "Feature",
  "properties": {
    "iso:country":"US",
    "sg:address":"10618 Riverview Dr",
    "sg:city":"Riverview",
    "sg:classifiers":[
        {
            "category":"Health Services",
            "subcategory":"Chiropractor",
            "type":"Services"
        }
    ],
    "sg:phone":"+1 813 523 8681",
    "sg:postcode":"33578",
    "sg:province":"FL",
    "sg:tags":[
        "chiropractic"
    ],
    "wof:name":"Carline Chiropractic",
    "wof:placetype":"venue"
},
  "geometry": {"coordinates":[-82.327968,27.871712],"type":"Point"}
}