{
  "type": "Feature",
  "properties": {
    "iso:country":"US",
    "sg:address":"145 Liberty St",
    "sg:city":"Atmore",
    "sg:classifiers":[
        {
            "category":"Organizations",
            "subcategory":"Religious Organization",
            "type":"Services"
        }
    ],
    "sg:phone":"+1 251 368 7233",
    "sg:postcode":"36502",
    "sg:province":"FL",
    "wof:name":"God Huse Tbernacle Deliverance",
    "wof:placetype":"venue"
},
  "geometry": {"coordinates":[-87.484861,31.034204],"type":"Point"}
}