{
  "type": "Feature",
  "properties": {
    "iso:country":"US",
    "sg:address":"610 E Nine Mile Rd",
    "sg:city":"Pensacola",
    "sg:classifiers":[
        {
            "category":"Bars & Pubs",
            "type":"Food & Drink"
        }
    ],
    "sg:phone":"+1 850 477 9961",
    "sg:postcode":"32514",
    "sg:province":"FL",
    "sg:tags":[
        "club",
        "night"
    ],
    "wof:name":"Chan's Saloon & Eatery",
    "wof:placetype":"venue"
},
  "geometry": {"coordinates":[-87.251999,30.532885],"type":"Point"}
}