{
  "type": "Feature",
  "properties": {
    "addr:full":"5073 Tamiami Trl Naples FL 34113",
    "addr:housenumber":"5073",
    "addr:postcode":"34113",
    "addr:street":"Tamiami Trl",
    "iso:country":"US",
    "sg:address":"5073 Tamiami Trl",
    "sg:city":"Naples",
    "sg:classifiers":[
        {
            "category":"Professional",
            "subcategory":"Accounting & Tax Preparation",
            "type":"Services"
        }
    ],
    "sg:phone":"+1 239 774 6216",
    "sg:postcode":"34113",
    "sg:province":"FL",
    "sg:tags":[
        "return",
        "filing"
    ],
    "wof:name":"Osnel's Multi Svc",
    "wof:placetype":"venue"
},
  "geometry": {"coordinates":[-81.74838099999999,26.107783],"type":"Point"}
}