{
  "type": "Feature",
  "properties": {
    "iso:country":"US",
    "sg:address":"129 N Miami Ave",
    "sg:city":"Miami",
    "sg:classifiers":[
        {
            "category":"Shopping",
            "type":"Retail Goods"
        }
    ],
    "sg:phone":"+1 305 358 9686",
    "sg:postcode":"33128",
    "sg:province":"FL",
    "sg:tags":[
        "item",
        "boutique"
    ],
    "wof:name":"Fina Hogar & More Inc",
    "wof:placetype":"venue"
},
  "geometry": {"coordinates":[-80.193624,25.775388],"type":"Point"}
}