{
  "type": "Feature",
  "properties": {
    "addr:full":"9080 Boggy Creek Rd # 500 Orlando FL 32824",
    "addr:housenumber":"9080",
    "addr:postcode":"32824",
    "addr:street":"Boggy Creek Rd # 500",
    "iso:country":"US",
    "sg:address":"9080 Boggy Creek Rd # 500",
    "sg:city":"Orlando",
    "sg:classifiers":[
        {
            "category":"Transit Center",
            "subcategory":"Freight",
            "type":"Transportation"
        }
    ],
    "sg:phone":"+1 407 851 9070",
    "sg:postcode":"32824",
    "sg:province":"FL",
    "sg:tags":[
        "container",
        "broker"
    ],
    "wof:name":"Eagle Usa Air Freight",
    "wof:placetype":"venue"
},
  "geometry": {"coordinates":[-81.34895299999999,28.434372],"type":"Point"}
}