{
  "type": "Feature",
  "properties": {
    "addr:full":"2320 Bruner Ln Fort Myers FL 33912",
    "addr:housenumber":"2320",
    "addr:postcode":"33912",
    "addr:street":"Bruner Ln",
    "iso:country":"US",
    "sg:address":"2320 Bruner Ln",
    "sg:city":"Fort Myers",
    "sg:classifiers":[
        {
            "category":"Building & Trades",
            "subcategory":"Construction",
            "type":"Services"
        }
    ],
    "sg:phone":"+1 239 481 8554",
    "sg:postcode":"33912",
    "sg:province":"FL",
    "sg:tags":[
        "contractor"
    ],
    "wof:name":"Flagler Construction Eqpt LLC",
    "wof:placetype":"venue"
},
  "geometry": {"coordinates":[-81.863602,26.53271],"type":"Point"}
}