{
  "type": "Feature",
  "properties": {
    "iso:country":"US",
    "sg:address":"888 Brickell Ave",
    "sg:city":"Miami",
    "sg:classifiers":[
        {
            "category":"Professional",
            "subcategory":"Lawyer & Legal Services",
            "type":"Services"
        }
    ],
    "sg:phone":"+1 305 379 7101",
    "sg:postcode":"33131",
    "sg:province":"FL",
    "wof:name":"Levin Albert Z Law Frim",
    "wof:placetype":"venue"
},
  "geometry": {"coordinates":[-80.19083500000001,25.765974],"type":"Point"}
}