{
  "type": "Feature",
  "properties": {
    "addr:full":"511 Ramona Ln Orlando FL 32805",
    "addr:housenumber":"511",
    "addr:postcode":"32805",
    "addr:street":"Ramona Ln",
    "iso:country":"US",
    "sg:address":"511 Ramona Ln",
    "sg:city":"Orlando",
    "sg:classifiers":[
        {
            "category":"Manufacturing",
            "subcategory":"Apparel",
            "type":"Manufacturing & Wholesale Goods"
        }
    ],
    "sg:phone":"+1 407 481 9519",
    "sg:postcode":"32805",
    "sg:province":"FL",
    "sg:tags":[
        "sewing",
        "contractor"
    ],
    "wof:name":"Lydia's House Of Purple",
    "wof:placetype":"venue"
},
  "geometry": {"coordinates":[-81.400499,28.551814],"type":"Point"}
}