{
  "type": "Feature",
  "properties": {
    "addr:full":"8600 Jesse B Smith Ct Jacksonville FL 32219",
    "addr:housenumber":"8600",
    "addr:postcode":"32219",
    "addr:street":"Jesse B Smith Ct",
    "iso:country":"US",
    "sg:address":"8600 Jesse B Smith Ct",
    "sg:city":"Jacksonville",
    "sg:classifiers":[
        {
            "category":"Utilities",
            "subcategory":"Electric",
            "type":"Services"
        }
    ],
    "sg:phone":"+1 904 783 0679",
    "sg:postcode":"32219",
    "sg:province":"FL",
    "sg:tags":[
        "equipment",
        "strapping"
    ],
    "wof:name":"All Pack Inc",
    "wof:placetype":"venue"
},
  "geometry": {"coordinates":[-81.792957,30.376488],"type":"Point"}
}