{
  "type": "Feature",
  "properties": {
    "addr:full":"4301 32nd St W Bradenton FL 34205",
    "addr:housenumber":"4301",
    "addr:postcode":"34205",
    "addr:street":"32Nd St W",
    "iso:country":"US",
    "sg:address":"4301 32nd St W",
    "sg:city":"Bradenton",
    "sg:classifiers":[
        {
            "category":"Retail",
            "subcategory":"Repair Shop",
            "type":"Services"
        }
    ],
    "sg:phone":"+1 941 751 1688",
    "sg:postcode":"34205",
    "sg:province":"FL",
    "sg:tags":[
        "upholsterer"
    ],
    "wof:name":"Dorothy's Upholstery",
    "wof:placetype":"venue"
},
  "geometry": {"coordinates":[-82.593784,27.462505],"type":"Point"}
}