{
  "type": "Feature",
  "properties": {
    "iso:country":"US",
    "sg:address":"58 S Lucille St",
    "sg:city":"Beverly Hills",
    "sg:classifiers":[
        {
            "category":"Local Transit",
            "type":"Transportation"
        }
    ],
    "sg:phone":"+1 352 746 6603",
    "sg:postcode":"34465",
    "sg:province":"FL",
    "sg:tags":[
        "limousine"
    ],
    "wof:name":"John Wingfield Limousine Svc",
    "wof:placetype":"venue"
},
  "geometry": {"coordinates":[-82.45128800000001,28.913274],"type":"Point"}
}