{
  "type": "Feature",
  "properties": {
    "addr:full":"4269 State Rd 29 S Labelle FL 33935",
    "addr:housenumber":"4269;29",
    "addr:postcode":"33935",
    "addr:street":"State Rd;S Labelle",
    "iso:country":"US",
    "sg:address":"4269 State Rd 29 S",
    "sg:city":"Labelle",
    "sg:classifiers":[
        {
            "category":"Food & Beverages",
            "subcategory":"Groceries & Convenience Stores",
            "type":"Retail Goods"
        }
    ],
    "sg:phone":"+1 863 674 1500",
    "sg:postcode":"33935",
    "sg:province":"FL",
    "sg:tags":[
        "grocer"
    ],
    "wof:name":"Aztec Mexican Foods",
    "wof:placetype":"venue"
},
  "geometry": {"coordinates":[-81.437622,26.731241],"type":"Point"}
}