{
  "type": "Feature",
  "properties": {
    "iso:country":"US",
    "sg:address":"10631 N Kendall Dr Ste 260",
    "sg:city":"Miami",
    "sg:classifiers":[
        {
            "category":"Professional",
            "subcategory":"Lawyer & Legal Services",
            "type":"Services"
        }
    ],
    "sg:phone":"+1 305 262 2728",
    "sg:postcode":"33176",
    "sg:province":"FL",
    "sg:website":"www.ferrerlaw.com",
    "wof:name":"Law Offices of Ferrer and Associates Pl the",
    "wof:placetype":"venue"
},
  "geometry": {"coordinates":[-80.365189,25.687168],"type":"Point"}
}