{
  "type": "Feature",
  "properties": {
    "addr:full":"1805 Drew St Clearwater FL 33765",
    "addr:housenumber":"1805",
    "addr:postcode":"33765",
    "addr:street":"Drew St",
    "iso:country":"US",
    "sg:address":"1805 Drew St",
    "sg:city":"Clearwater",
    "sg:classifiers":[
        {
            "category":"Professional",
            "subcategory":"Computer Services",
            "type":"Services"
        }
    ],
    "sg:phone":"+1 727 442 1822",
    "sg:postcode":"33765",
    "sg:province":"FL",
    "sg:tags":[
        "publisher",
        "software",
        "developer",
        "services-wholesale"
    ],
    "sg:website":"http://www.linkfixerplus.com",
    "wof:name":"Linktek Corporation",
    "wof:placetype":"venue"
},
  "geometry": {"coordinates":[-82.762766,27.967964],"type":"Point"}
}