{
  "type": "Feature",
  "properties": {
    "iso:country":"US",
    "sg:address":"9466 Navarre Pkwy Ste F",
    "sg:city":"Navarre",
    "sg:phone":"+1 850 936 9800",
    "sg:postcode":"32566",
    "sg:province":"FL",
    "wof:name":"Steve's Ink Spot",
    "wof:placetype":"venue"
},
  "geometry": {"coordinates":[-86.826525,30.409752],"type":"Point"}
}