{
  "type": "Feature",
  "properties": {
    "iso:country":"US",
    "sg:address":"3723 Guadiato Ct",
    "sg:city":"Naples",
    "sg:classifiers":[
        {
            "category":"Food & Beverages",
            "subcategory":"Specialty",
            "type":"Retail Goods"
        }
    ],
    "sg:phone":"+1 239 514 2194",
    "sg:postcode":"34109",
    "sg:province":"FL",
    "wof:name":"J&D Langolis Inc",
    "wof:placetype":"venue"
},
  "geometry": {"coordinates":[-81.748142,26.235255],"type":"Point"}
}