{
  "type": "Feature",
  "properties": {
    "iso:country":"US",
    "sg:address":"6977 E Fowler Ave",
    "sg:city":"Tampa",
    "sg:classifiers":[
        {
            "category":"Professional",
            "subcategory":"Advertising",
            "type":"Services"
        }
    ],
    "sg:phone":"+1 813 899 4566",
    "sg:postcode":"33617",
    "sg:province":"FL",
    "sg:tags":[
        "mail"
    ],
    "wof:name":"Direct Hit Marketing",
    "wof:placetype":"venue"
},
  "geometry": {"coordinates":[-82.37526200000001,28.054302],"type":"Point"}
}