{
  "type": "Feature",
  "properties": {
    "addr:full":"6811 State Rd 54 New Port Richey FL 34653",
    "addr:housenumber":"6811;54",
    "addr:postcode":"34653",
    "addr:street":"State Rd",
    "iso:country":"US",
    "sg:address":"6811 State Rd 54",
    "sg:city":"New Port Richey",
    "sg:classifiers":[
        {
            "category":"Health Services",
            "subcategory":"Doctor",
            "type":"Services"
        }
    ],
    "sg:phone":"+1 727 815 1550",
    "sg:postcode":"34653",
    "sg:province":"FL",
    "sg:tags":[
        "clinic",
        "medical"
    ],
    "wof:name":"Greenbrook Medical Center",
    "wof:placetype":"venue"
},
  "geometry": {"coordinates":[-82.70211,28.217041],"type":"Point"}
}