{
  "type": "Feature",
  "properties": {
    "iso:country":"US",
    "sg:address":"11306 Causeway Blvd",
    "sg:city":"Brandon",
    "sg:phone":"+1 813 681 5112",
    "sg:postcode":"33511",
    "sg:province":"FL",
    "sg:website":"http://www.steakandshake.com",
    "wof:name":"Steak 'n Shake",
    "wof:placetype":"venue"
},
  "geometry": {"coordinates":[-82.32262900000001,27.923323],"type":"Point"}
}