{
  "type": "Feature",
  "properties": {
    "addr:full":"11 E Hazel St Orlando FL 32804",
    "addr:housenumber":"11",
    "addr:postcode":"32804",
    "addr:street":"E Hazel St",
    "iso:country":"US",
    "sg:address":"11 E Hazel St",
    "sg:city":"Orlando",
    "sg:classifiers":[
        {
            "category":"Real Estate",
            "subcategory":"Real Estate Agent",
            "type":"Services"
        }
    ],
    "sg:phone":"+1 407 894 7429",
    "sg:postcode":"32804",
    "sg:province":"FL",
    "wof:name":"Andrews Appraisal Services",
    "wof:placetype":"venue"
},
  "geometry": {"coordinates":[-81.378792,28.578599],"type":"Point"}
}