{
  "type": "Feature",
  "properties": {
    "addr:full":"3834 Jog Rd Greenacres FL 33467",
    "addr:housenumber":"3834",
    "addr:postcode":"33467",
    "addr:street":"Jog Rd",
    "iso:country":"US",
    "sg:address":"3834 Jog Rd",
    "sg:city":"Greenacres",
    "sg:classifiers":[
        {
            "category":"Professional",
            "subcategory":"Management & Consulting",
            "type":"Services"
        }
    ],
    "sg:phone":"+1 561 963 9311",
    "sg:postcode":"33467",
    "sg:province":"FL",
    "sg:tags":[
        "fuel"
    ],
    "wof:name":"Dubois Management Inc",
    "wof:placetype":"venue"
},
  "geometry": {"coordinates":[-80.146483,26.622416],"type":"Point"}
}