{
  "type": "Feature",
  "properties": {
    "addr:full":"1516 Royal Palm Dr Niceville FL 32578",
    "addr:housenumber":"1516",
    "addr:postcode":"32578",
    "addr:street":"Royal Palm Dr",
    "iso:country":"US",
    "sg:address":"1516 Royal Palm Dr",
    "sg:city":"Niceville",
    "sg:classifiers":[
        {
            "category":"Real Estate",
            "subcategory":"Real Estate Agent",
            "type":"Services"
        }
    ],
    "sg:phone":"+1 850 729 2276",
    "sg:postcode":"32578",
    "sg:province":"FL",
    "wof:name":"Pierson Appraisals",
    "wof:placetype":"venue"
},
  "geometry": {"coordinates":[-86.472157,30.494909],"type":"Point"}
}