{
  "type": "Feature",
  "properties": {
    "addr:full":"2333 Feather Sound Dr Clearwater FL 33762",
    "addr:housenumber":"2333",
    "addr:postcode":"33762",
    "addr:street":"Feather Sound Dr",
    "iso:country":"US",
    "sg:address":"2333 Feather Sound Dr",
    "sg:city":"Clearwater",
    "sg:classifiers":[
        {
            "category":"Professional",
            "subcategory":"Lawyer & Legal Services",
            "type":"Services"
        }
    ],
    "sg:phone":"+1 727 573 4057",
    "sg:postcode":"33762",
    "sg:province":"FL",
    "wof:name":"Law Office of Dawn Weiger",
    "wof:placetype":"venue"
},
  "geometry": {"coordinates":[-82.671406,27.905827],"type":"Point"}
}