{
  "type": "Feature",
  "properties": {
    "iso:country":"US",
    "sg:address":"3561 Sanctuary Blvd",
    "sg:city":"Jacksonville Beach",
    "sg:classifiers":[
        {
            "category":"Insurance",
            "subcategory":"Insurance Agent",
            "type":"Services"
        }
    ],
    "sg:phone":"+1 904 246 3112",
    "sg:postcode":"32250",
    "sg:province":"FL",
    "wof:name":"Hillegass Ins Agency",
    "wof:placetype":"venue"
},
  "geometry": {"coordinates":[-81.402663,30.259909],"type":"Point"}
}