{
  "type": "Feature",
  "properties": {
    "iso:country":"US",
    "sg:address":"3920 NW 169th Ter",
    "sg:city":"Opa Locka",
    "sg:classifiers":[
        {
            "category":"Manufacturing",
            "subcategory":"Apparel",
            "type":"Manufacturing & Wholesale Goods"
        }
    ],
    "sg:phone":"+1 305 627 0390",
    "sg:postcode":"33055",
    "sg:province":"FL",
    "sg:tags":[
        "sewing",
        "contractor"
    ],
    "wof:name":"Sew What Inc",
    "wof:placetype":"venue"
},
  "geometry": {"coordinates":[-80.26664100000001,25.927745],"type":"Point"}
}