{
  "type": "Feature",
  "properties": {
    "addr:full":"1800 E Merritt Island Cswy Merritt Island FL 32952",
    "addr:housenumber":"1800",
    "addr:postcode":"32952",
    "addr:street":"E",
    "iso:country":"US",
    "sg:address":"1800 E Merritt Island Cswy",
    "sg:city":"Merritt Island",
    "sg:classifiers":[
        {
            "category":"Food & Beverages",
            "subcategory":"Groceries & Convenience Stores",
            "type":"Retail Goods"
        },
        {
            "category":"Autos & Motor Vehicles",
            "subcategory":"Fuel & Gas Station",
            "type":"Retail Goods"
        }
    ],
    "sg:phone":"+1 321 449 9550",
    "sg:postcode":"32952",
    "sg:province":"FL",
    "sg:tags":[
        "oil"
    ],
    "wof:name":"Island Gas LLC",
    "wof:placetype":"venue"
},
  "geometry": {"coordinates":[-80.66451600000001,28.357362],"type":"Point"}
}