{
  "type": "Feature",
  "properties": {
    "iso:country":"US",
    "sg:address":"1550 Madruga Ave",
    "sg:city":"Coral Gables",
    "sg:classifiers":[
        {
            "category":"Professional",
            "subcategory":"Lawyer & Legal Services",
            "type":"Services"
        },
        {
            "category":"Social Services",
            "type":"Services"
        }
    ],
    "sg:phone":"+1 305 662 2173",
    "sg:postcode":"33146",
    "sg:province":"FL",
    "sg:tags":[
        "counseling",
        "health"
    ],
    "wof:name":"A Dynamic Potential LLC",
    "wof:placetype":"venue"
},
  "geometry": {"coordinates":[-80.2837,25.707812],"type":"Point"}
}