{
  "type": "Feature",
  "properties": {
    "iso:country":"US",
    "sg:address":"28205 SW 167th Pl",
    "sg:city":"Homestead",
    "sg:classifiers":[
        {
            "category":"Health Services",
            "subcategory":"Doctor",
            "type":"Services"
        }
    ],
    "sg:phone":"+1 305 246 3219",
    "sg:postcode":"33030",
    "sg:province":"FL",
    "sg:tags":[
        "medicine",
        "physician",
        "surgeon",
        "internal",
        "surgeons"
    ],
    "wof:name":"Doc At Your Door",
    "wof:placetype":"venue"
},
  "geometry": {"coordinates":[-80.46308000000001,25.504865],"type":"Point"}
}