{
  "type": "Feature",
  "properties": {
    "iso:country":"US",
    "sg:address":"252 SW 31st St",
    "sg:city":"Fort Lauderdale",
    "sg:classifiers":[
        {
            "category":"Autos & Motor Vehicles",
            "subcategory":"Boat Sales",
            "type":"Retail Goods"
        },
        {
            "category":"Retail",
            "subcategory":"Repair Shop",
            "type":"Services"
        }
    ],
    "sg:phone":"+1 954 462 0269",
    "sg:postcode":"33315",
    "sg:province":"FL",
    "sg:tags":[
        "top",
        "upholstery",
        "cover"
    ],
    "sg:website":"www.rorysmarine.com",
    "wof:name":"Rory's Marine Canvas & Uphlstr",
    "wof:placetype":"venue"
},
  "geometry": {"coordinates":[-80.14352700000001,26.086154],"type":"Point"}
}