{
  "type": "Feature",
  "properties": {
    "iso:country":"US",
    "sg:address":"742 NE 79th St",
    "sg:city":"Miami",
    "sg:classifiers":[
        {
            "category":"Retail",
            "subcategory":"Animal Services",
            "type":"Services"
        }
    ],
    "sg:phone":"+1 305 756 0200",
    "sg:postcode":"33138",
    "sg:province":"FL",
    "sg:tags":[
        "pet",
        "grooming",
        "washing"
    ],
    "wof:name":"4 Paws Only",
    "wof:placetype":"venue"
},
  "geometry": {"coordinates":[-80.182543,25.847819],"type":"Point"}
}