{
  "type": "Feature",
  "properties": {
    "iso:country":"US",
    "sg:address":"9272 Arlington Expy",
    "sg:city":"Jacksonville",
    "sg:classifiers":[
        {
            "category":"Health Services",
            "subcategory":"Doctor",
            "type":"Services"
        }
    ],
    "sg:phone":"+1 904 725 6262",
    "sg:postcode":"32225",
    "sg:province":"FL",
    "sg:tags":[
        "dentist"
    ],
    "wof:name":"Orthodontic Centers Of America",
    "wof:placetype":"venue"
},
  "geometry": {"coordinates":[-81.556982,30.322045],"type":"Point"}
}