{
  "type": "Feature",
  "properties": {
    "iso:country":"US",
    "sg:address":"25716 State Road 46",
    "sg:city":"Sorrento",
    "sg:classifiers":[
        {
            "category":"Sports & Exercise",
            "subcategory":"Golf",
            "type":"Entertainment"
        }
    ],
    "sg:phone":"+1 352 735 5757",
    "sg:postcode":"32776",
    "sg:province":"FL",
    "sg:tags":[
        "car",
        "cart"
    ],
    "wof:name":"Executive Golf Cars",
    "wof:placetype":"venue"
},
  "geometry": {"coordinates":[-81.53111199999999,28.80957],"type":"Point"}
}