{
  "type": "Feature",
  "properties": {
    "addr:full":"2122 US Hwy 92 Auburndale FL 33823",
    "addr:housenumber":"2122",
    "addr:postcode":"33823",
    "addr:street":"Us Hwy 92",
    "iso:country":"US",
    "sg:address":"2122 US Hwy 92",
    "sg:city":"Auburndale",
    "sg:classifiers":[
        {
            "category":"Restaurant",
            "type":"Food & Drink"
        }
    ],
    "sg:phone":"+1 863 965 0536",
    "sg:postcode":"33823",
    "sg:province":"FL",
    "wof:name":"Subway Sandwiches & Salads",
    "wof:placetype":"venue"
},
  "geometry": {"coordinates":[-81.817543,28.05696],"type":"Point"}
}