{
  "type": "Feature",
  "properties": {
    "addr:full":"363 NE Spanish Trl Boca Raton FL 33432",
    "addr:housenumber":"363",
    "addr:postcode":"33432",
    "addr:street":"Ne Spanish Trl",
    "iso:country":"US",
    "sg:address":"363 NE Spanish Trl",
    "sg:city":"Boca Raton",
    "sg:classifiers":[
        {
            "category":"Professional",
            "type":"Services"
        }
    ],
    "sg:phone":"+1 561 447 9322",
    "sg:postcode":"33432",
    "sg:province":"FL",
    "sg:tags":[
        "establishment"
    ],
    "wof:name":"Cortese Casa",
    "wof:placetype":"venue"
},
  "geometry": {"coordinates":[-80.075039,26.351778],"type":"Point"}
}