{
  "type": "Feature",
  "properties": {
    "addr:full":"104 Giralda Ave Coral Gables FL 33134",
    "addr:housenumber":"104",
    "addr:postcode":"33134",
    "addr:street":"Giralda Ave",
    "iso:country":"US",
    "sg:address":"104 Giralda Ave",
    "sg:city":"Coral Gables",
    "sg:classifiers":[
        {
            "category":"Personal",
            "subcategory":"Beauty Salon",
            "type":"Services"
        },
        {
            "category":"Personal",
            "subcategory":"Nail Salon",
            "type":"Services"
        }
    ],
    "sg:phone":"+1 305 447 0600",
    "sg:postcode":"33134",
    "sg:province":"FL",
    "sg:tags":[
        "hair"
    ],
    "sg:website":"www.BeautyStrategy.com",
    "wof:name":"Beauty Strategy",
    "wof:placetype":"venue"
},
  "geometry": {"coordinates":[-80.25720200000001,25.751499],"type":"Point"}
}