{
  "type": "Feature",
  "properties": {
    "iso:country":"US",
    "sg:address":"2708 Garden St",
    "sg:city":"Titusville",
    "sg:classifiers":[
        {
            "category":"Organizations",
            "subcategory":"Religious Organization",
            "type":"Services"
        }
    ],
    "sg:phone":"+1 321 383 8005",
    "sg:postcode":"32796",
    "sg:province":"FL",
    "sg:tags":[
        "church"
    ],
    "wof:name":"Evangel Christian Ctr",
    "wof:placetype":"venue"
},
  "geometry": {"coordinates":[-80.83686899999999,28.615413],"type":"Point"}
}