{
  "type": "Feature",
  "properties": {
    "iso:country":"US",
    "sg:address":"2622 Crawfordville Hwy",
    "sg:city":"Crawfordville",
    "sg:classifiers":[
        {
            "category":"Shopping",
            "subcategory":"Computers & Home Electronics",
            "type":"Retail Goods"
        }
    ],
    "sg:phone":"+1 850 926 5092",
    "sg:postcode":"32327",
    "sg:province":"FL",
    "sg:tags":[
        "player",
        "recorder",
        "video"
    ],
    "sg:website":"www.scubaroo.com",
    "wof:name":"Sights & Sounds Co",
    "wof:placetype":"venue"
},
  "geometry": {"coordinates":[-84.37139999999999,30.19364],"type":"Point"}
}