{
  "type": "Feature",
  "properties": {
    "addr:full":"4471 Saddleworth Cir Orlando FL 32826",
    "addr:housenumber":"4471",
    "addr:postcode":"32826",
    "addr:street":"Saddleworth Cir",
    "iso:country":"US",
    "sg:address":"4471 Saddleworth Cir",
    "sg:city":"Orlando",
    "sg:classifiers":[
        {
            "category":"Real Estate",
            "subcategory":"Real Estate Agent",
            "type":"Services"
        }
    ],
    "sg:phone":"+1 407 306 9854",
    "sg:postcode":"32826",
    "sg:province":"FL",
    "wof:name":"Carl C Cunningham",
    "wof:placetype":"venue"
},
  "geometry": {"coordinates":[-81.176232,28.605793],"type":"Point"}
}