{
  "type": "Feature",
  "properties": {
    "iso:country":"US",
    "sg:address":"10100 NW 25th St",
    "sg:city":"Doral",
    "sg:classifiers":[
        {
            "category":"Manufacturing",
            "subcategory":"Printing",
            "type":"Manufacturing & Wholesale Goods"
        },
        {
            "category":"Wholesale",
            "subcategory":"Books, Periodicals, & Newspapers",
            "type":"Manufacturing & Wholesale Goods"
        }
    ],
    "sg:phone":"+1 305 592 8260",
    "sg:postcode":"33172",
    "sg:province":"FL",
    "sg:tags":[
        "dealers-wholesale",
        "news",
        "magazine"
    ],
    "sg:website":"http://www.prologix.com",
    "wof:name":"Anderson News",
    "wof:placetype":"venue"
},
  "geometry": {"coordinates":[-80.360117,25.796829],"type":"Point"}
}