{
  "type": "Feature",
  "properties": {
    "iso:country":"US",
    "sg:address":"39 Cunningham Dr",
    "sg:city":"New Smyrna Beach",
    "sg:classifiers":[
        {
            "category":"Building & Trades",
            "subcategory":"Construction",
            "type":"Services"
        }
    ],
    "sg:phone":"+1 386 427 3164",
    "sg:postcode":"32168",
    "sg:province":"FL",
    "sg:tags":[
        "house"
    ],
    "wof:name":"D R Custom Homes LLC",
    "wof:placetype":"venue"
},
  "geometry": {"coordinates":[-80.930069,29.057598],"type":"Point"}
}