{
  "type": "Feature",
  "properties": {
    "iso:country":"US",
    "sg:address":"38920 2nd Ave",
    "sg:city":"Zephyrhills",
    "sg:classifiers":[
        {
            "category":"Building & Trades",
            "subcategory":"Construction",
            "type":"Services"
        }
    ],
    "sg:phone":"+1 813 782 2293",
    "sg:postcode":"33542",
    "sg:province":"FL",
    "sg:tags":[
        "residential"
    ],
    "wof:name":"Master Craft Homes-S M",
    "wof:placetype":"venue"
},
  "geometry": {"coordinates":[-82.173103,28.232596],"type":"Point"}
}