{
  "type": "Feature",
  "properties": {
    "iso:country":"US",
    "sg:address":"733 W Granada Blvd",
    "sg:city":"Ormond Beach",
    "sg:classifiers":[
        {
            "category":"Retail",
            "subcategory":"Funeral Services",
            "type":"Services"
        }
    ],
    "sg:phone":"+1 386 673 1100",
    "sg:postcode":"32174",
    "sg:province":"FL",
    "sg:tags":[
        "director"
    ],
    "sg:website":"www.lohmanfuneralhomes.com",
    "wof:name":"Lohman Ormond Funeral Home",
    "wof:placetype":"venue"
},
  "geometry": {"coordinates":[-81.07744700000001,29.278953],"type":"Point"}
}