{
  "type": "Feature",
  "properties": {
    "iso:country":"US",
    "sg:address":"2028 Hollywood Blvd",
    "sg:city":"Hollywood",
    "sg:classifiers":[
        {
            "category":"Arena",
            "subcategory":"Sports Club",
            "type":"Entertainment"
        }
    ],
    "sg:phone":"+1 954 929 2656",
    "sg:postcode":"33020",
    "sg:province":"FL",
    "sg:tags":[
        "martial art",
        "instruction"
    ],
    "sg:website":"http://www.aikidosouthflorida.com",
    "wof:name":"Aikido Of South Florida",
    "wof:placetype":"venue"
},
  "geometry": {"coordinates":[-80.147508,26.011377],"type":"Point"}
}