{
  "type": "Feature",
  "properties": {
    "iso:country":"US",
    "sg:address":"1886 59th St W",
    "sg:city":"Bradenton",
    "sg:classifiers":[
        {
            "category":"Health Services",
            "subcategory":"Doctor",
            "type":"Services"
        }
    ],
    "sg:phone":"+1 941 794 1980",
    "sg:postcode":"34209",
    "sg:province":"FL",
    "sg:tags":[
        "physician",
        "stomach",
        "gastroenterology",
        "surgeons",
        "surgeon",
        "intestines"
    ],
    "wof:name":"Gastroenterology Associates of Manatee PA",
    "wof:placetype":"venue"
},
  "geometry": {"coordinates":[-82.62044400000001,27.483639],"type":"Point"}
}