{
  "type": "Feature",
  "properties": {
    "iso:country":"US",
    "sg:address":"227 Park St",
    "sg:city":"Jacksonville",
    "sg:classifiers":[
        {
            "category":"Government",
            "subcategory":"Office",
            "type":"Public Place"
        }
    ],
    "sg:phone":"+1 904 359 6803",
    "sg:postcode":"32204",
    "sg:province":"FL",
    "wof:name":"Children & Families Dept",
    "wof:placetype":"venue"
},
  "geometry": {"coordinates":[-81.674707,30.324049],"type":"Point"}
}