{
  "type": "Feature",
  "properties": {
    "iso:country":"US",
    "sg:address":"1701 N Mills Ave",
    "sg:city":"Orlando",
    "sg:classifiers":[
        {
            "category":"Health Services",
            "subcategory":"Doctor",
            "type":"Services"
        }
    ],
    "sg:phone":"+1 407 647 3960",
    "sg:postcode":"32803",
    "sg:province":"FL",
    "sg:tags":[
        "physician",
        "surgeons",
        "infectious",
        "disease"
    ],
    "sg:website":"http://oicorlando.com/",
    "wof:name":"Orlando Immunology Center",
    "wof:placetype":"venue"
},
  "geometry": {"coordinates":[-81.36444899999999,28.566759],"type":"Point"}
}