{
  "type": "Feature",
  "properties": {
    "iso:country":"US",
    "sg:address":"303 Tamiami Trl",
    "sg:city":"Nokomis",
    "sg:classifiers":[
        {
            "category":"Shopping",
            "subcategory":"Used Merchandise",
            "type":"Retail Goods"
        }
    ],
    "sg:phone":"+1 941 412 3443",
    "sg:postcode":"34275",
    "sg:province":"FL",
    "wof:name":"Anderson Paperback Book Exch",
    "wof:placetype":"venue"
},
  "geometry": {"coordinates":[-82.453723,27.129666],"type":"Point"}
}