{
  "type": "Feature",
  "properties": {
    "addr:full":"735 Arlington Ave N St Petersburg FL 33701",
    "addr:housenumber":"735",
    "addr:postcode":"33701",
    "addr:street":"Arlington Ave N",
    "iso:country":"US",
    "sg:address":"735 Arlington Ave N",
    "sg:city":"St Petersburg",
    "sg:classifiers":[
        {
            "category":"Recreation",
            "type":"Entertainment"
        }
    ],
    "sg:phone":"+1 727 420 8184",
    "sg:postcode":"33701",
    "sg:province":"FL",
    "sg:tags":[
        "instruction",
        "yoga"
    ],
    "wof:name":"Mirror Lake Yoga",
    "wof:placetype":"venue"
},
  "geometry": {"coordinates":[-82.64345,27.772724],"type":"Point"}
}