{
  "type": "Feature",
  "properties": {
    "addr:full":"551 National Health Care Dr Daytona Beach FL 32114",
    "addr:housenumber":"551",
    "addr:postcode":"32114",
    "addr:street":"Dr",
    "iso:country":"US",
    "sg:address":"551 National Health Care Dr",
    "sg:city":"Daytona Beach",
    "sg:classifiers":[
        {
            "category":"Government",
            "subcategory":"Office",
            "type":"Public Place"
        }
    ],
    "sg:phone":"+1 386 274 4600",
    "sg:postcode":"32114",
    "sg:province":"FL",
    "sg:tags":[
        "clinic"
    ],
    "wof:name":"Daytona Bch V A Otptent Clinic",
    "wof:placetype":"venue"
},
  "geometry": {"coordinates":[-81.06165799999999,29.204849],"type":"Point"}
}