{
  "type": "Feature",
  "properties": {
    "iso:country":"US",
    "sg:address":"4800 NE Sandpebble Trce",
    "sg:city":"Stuart",
    "sg:classifiers":[
        {
            "category":"Real Estate",
            "subcategory":"Real Estate Operator",
            "type":"Services"
        }
    ],
    "sg:phone":"+1 772 225 2525",
    "sg:postcode":"34996",
    "sg:province":"FL",
    "sg:tags":[
        "condominium"
    ],
    "wof:name":"Sandpebble Beach Condominiums",
    "wof:placetype":"venue"
},
  "geometry": {"coordinates":[-80.189525,27.235541],"type":"Point"}
}