{
  "type": "Feature",
  "properties": {
    "iso:country":"US",
    "sg:address":"232 Australian Ave",
    "sg:city":"Palm Beach",
    "sg:classifiers":[
        {
            "category":"Real Estate",
            "subcategory":"Developer",
            "type":"Services"
        },
        {
            "category":"Real Estate",
            "subcategory":"Real Estate Agent",
            "type":"Services"
        }
    ],
    "sg:phone":"+1 561 655 3127",
    "sg:postcode":"33480",
    "sg:province":"FL",
    "sg:tags":[
        "investment"
    ],
    "wof:name":"First Palm Beach Trust",
    "wof:placetype":"venue"
},
  "geometry": {"coordinates":[-80.03810300000001,26.703256],"type":"Point"}
}