{
  "type": "Feature",
  "properties": {
    "addr:full":"14861 Summerlin Woods Dr Fort Myers FL 33919",
    "addr:housenumber":"14861",
    "addr:postcode":"33919",
    "addr:street":"Summerlin Woods Dr",
    "iso:country":"US",
    "sg:address":"14861 Summerlin Woods Dr",
    "sg:city":"Fort Myers",
    "sg:classifiers":[
        {
            "category":"Building & Trades",
            "subcategory":"Landscaping Services",
            "type":"Services"
        }
    ],
    "sg:phone":"+1 239 433 3252",
    "sg:postcode":"33919",
    "sg:province":"FL",
    "wof:name":"Pro Mow of Lee County Inc",
    "wof:placetype":"venue"
},
  "geometry": {"coordinates":[-81.89017699999999,26.526851],"type":"Point"}
}