{
  "type": "Feature",
  "properties": {
    "iso:country":"US",
    "sg:address":"2315 Beach Blvd",
    "sg:city":"Jacksonville Beach",
    "sg:classifiers":[
        {
            "category":"Professional",
            "subcategory":"Management & Consulting",
            "type":"Services"
        }
    ],
    "sg:phone":"+1 904 249 8009",
    "sg:postcode":"32250",
    "sg:province":"FL",
    "sg:tags":[
        "environmental"
    ],
    "wof:name":"Applied Technology & Mgt",
    "wof:placetype":"venue"
},
  "geometry": {"coordinates":[-81.41747599999999,30.288181],"type":"Point"}
}