{
  "type": "Feature",
  "properties": {
    "iso:country":"US",
    "sg:address":"1805 Co Rd 951",
    "sg:city":"Naples",
    "sg:classifiers":[
        {
            "category":"Real Estate",
            "subcategory":"Surveying",
            "type":"Services"
        }
    ],
    "sg:phone":"+1 239 353 9300",
    "sg:postcode":"34119",
    "sg:province":"FL",
    "sg:tags":[
        "surveyor"
    ],
    "wof:name":"Bill Macrides Field Crew Svc",
    "wof:placetype":"venue"
},
  "geometry": {"coordinates":[-81.687236,26.195821],"type":"Point"}
}