{
  "type": "Feature",
  "properties": {
    "iso:country":"US",
    "sg:address":"1010 Mcduff Ave N",
    "sg:city":"Jacksonville",
    "sg:classifiers":[
        {
            "category":"Professional",
            "subcategory":"Management & Consulting",
            "type":"Services"
        },
        {
            "category":"Government",
            "subcategory":"Office",
            "type":"Public Place"
        }
    ],
    "sg:phone":"+1 904 387 8850",
    "sg:postcode":"32254",
    "sg:province":"FL",
    "sg:tags":[
        "agricultural",
        "consultant"
    ],
    "wof:name":"Jacksonville Agriculture Dept",
    "wof:placetype":"venue"
},
  "geometry": {"coordinates":[-81.70552600000001,30.336912],"type":"Point"}
}