{
  "type": "Feature",
  "properties": {
    "iso:country":"US",
    "sg:address":"8253 Valencia College Ln",
    "sg:city":"Orlando",
    "sg:classifiers":[
        {
            "category":"Personal",
            "subcategory":"Barber",
            "type":"Services"
        }
    ],
    "sg:phone":"+1 407 243 2430",
    "sg:postcode":"32825",
    "sg:province":"FL",
    "sg:tags":[
        "shop"
    ],
    "wof:name":"Ground Zero Barber Shop",
    "wof:placetype":"venue"
},
  "geometry": {"coordinates":[-81.27396,28.55382],"type":"Point"}
}