{
  "type": "Feature",
  "properties": {
    "iso:country":"US",
    "sg:address":"14551 SW 136th Pl",
    "sg:city":"Miami",
    "sg:classifiers":[
        {
            "category":"Professional",
            "subcategory":"Detective & Security Services",
            "type":"Services"
        }
    ],
    "sg:phone":"+1 786 242 9912",
    "sg:postcode":"33186",
    "sg:province":"FL",
    "sg:tags":[
        "information",
        "bureau"
    ],
    "wof:name":"C & A Pool Services, Inc.",
    "wof:placetype":"venue"
},
  "geometry": {"coordinates":[-80.414404,25.63194],"type":"Point"}
}