{
  "type": "Feature",
  "properties": {
    "iso:country":"US",
    "sg:address":"17 E Flagler St Ste 108",
    "sg:city":"Miami",
    "sg:classifiers":[
        {
            "category":"Shopping",
            "subcategory":"Jewelry",
            "type":"Retail Goods"
        },
        {
            "category":"Retail",
            "subcategory":"Repair Shop",
            "type":"Services"
        }
    ],
    "sg:phone":"+1 305 358 8175",
    "sg:postcode":"33131",
    "sg:province":"FL",
    "sg:tags":[
        "jeweler",
        "watch",
        "clock"
    ],
    "wof:name":"Tumi Watch Co",
    "wof:placetype":"venue"
},
  "geometry": {"coordinates":[-80.19313699999999,25.774131],"type":"Point"}
}