{
  "type": "Feature",
  "properties": {
    "iso:country":"US",
    "sg:address":"3708 NW 50th St",
    "sg:city":"Miami",
    "sg:classifiers":[
        {
            "category":"Retail",
            "subcategory":"Repair Shop",
            "type":"Services"
        }
    ],
    "sg:phone":"+1 305 634 6454",
    "sg:postcode":"33142",
    "sg:province":"FL",
    "sg:tags":[
        "welding"
    ],
    "wof:name":"Blanco Iron Work",
    "wof:placetype":"venue"
},
  "geometry": {"coordinates":[-80.25842900000001,25.819621],"type":"Point"}
}