{
  "type": "Feature",
  "properties": {
    "iso:country":"US",
    "sg:address":"870 Providence Reserve Loop",
    "sg:city":"Lakeland",
    "sg:classifiers":[
        {
            "category":"Social Services",
            "subcategory":"Child Care",
            "type":"Services"
        }
    ],
    "sg:phone":"+1 863 603 7973",
    "sg:postcode":"33805",
    "sg:province":"FL",
    "wof:name":"Temesha Kids",
    "wof:placetype":"venue"
},
  "geometry": {"coordinates":[-81.972443,28.075758],"type":"Point"}
}