{
  "type": "Feature",
  "properties": {
    "iso:country":"US",
    "sg:address":"1232 W Wellington Dr",
    "sg:city":"Deltona",
    "sg:classifiers":[
        {
            "category":"Building & Trades",
            "subcategory":"Construction",
            "type":"Services"
        }
    ],
    "sg:phone":"+1 386 860 4751",
    "sg:postcode":"32725",
    "sg:province":"FL",
    "sg:tags":[
        "painter"
    ],
    "wof:name":"Links Painting Co",
    "wof:placetype":"venue"
},
  "geometry": {"coordinates":[-81.263553,28.89692],"type":"Point"}
}