{
  "type": "Feature",
  "properties": {
    "addr:full":"8920 Fordham St Fort Myers FL 33907",
    "addr:housenumber":"8920",
    "addr:postcode":"33907",
    "addr:street":"Fordham St",
    "iso:country":"US",
    "sg:address":"8920 Fordham St",
    "sg:city":"Fort Myers",
    "sg:classifiers":[
        {
            "category":"Real Estate",
            "subcategory":"Real Estate Agent",
            "type":"Services"
        }
    ],
    "sg:phone":"+1 239 939 0755",
    "sg:postcode":"33907",
    "sg:province":"FL",
    "wof:name":"MLS Realty",
    "wof:placetype":"venue"
},
  "geometry": {"coordinates":[-81.856081,26.552201],"type":"Point"}
}