{
  "type": "Feature",
  "properties": {
    "addr:full":"434 N Central Ave Oviedo FL 32765",
    "addr:housenumber":"434",
    "addr:postcode":"32765",
    "addr:street":"N Central Ave",
    "iso:country":"US",
    "sg:address":"434 N Central Ave",
    "sg:city":"Oviedo",
    "sg:classifiers":[
        {
            "category":"Health Services",
            "subcategory":"Health Practitioner",
            "type":"Services"
        }
    ],
    "sg:phone":"+1 407 227 8348",
    "sg:postcode":"32765",
    "sg:province":"FL",
    "sg:tags":[
        "psychologist"
    ],
    "wof:name":"Robert Harman",
    "wof:placetype":"venue"
},
  "geometry": {"coordinates":[-81.208394,28.676364],"type":"Point"}
}