{
  "type": "Feature",
  "properties": {
    "addr:full":"2879 17th Ave N St Petersburg FL 33713",
    "addr:housenumber":"2879",
    "addr:postcode":"33713",
    "addr:street":"17Th Ave N",
    "iso:country":"US",
    "sg:address":"2879 17th Ave N",
    "sg:city":"St Petersburg",
    "sg:classifiers":[
        {
            "category":"Building & Trades",
            "subcategory":"Cleaning & Sanitation",
            "type":"Services"
        }
    ],
    "sg:phone":"+1 727 323 3547",
    "sg:postcode":"33713",
    "sg:province":"FL",
    "sg:tags":[
        "janitor"
    ],
    "wof:name":"Sparkling Sisters Cleaning",
    "wof:placetype":"venue"
},
  "geometry": {"coordinates":[-82.67192300000001,27.788329],"type":"Point"}
}