{
  "type": "Feature",
  "properties": {
    "addr:full":"7301 SW 57th Ct South Miami FL 33143",
    "addr:housenumber":"7301",
    "addr:postcode":"33143",
    "addr:street":"Sw 57Th Ct",
    "iso:country":"US",
    "sg:address":"7301 SW 57th Ct",
    "sg:city":"South Miami",
    "sg:classifiers":[
        {
            "category":"Professional",
            "subcategory":"Lawyer & Legal Services",
            "type":"Services"
        }
    ],
    "sg:phone":"+1 305 661 1556",
    "sg:postcode":"33143",
    "sg:province":"FL",
    "sg:tags":[
        "divorce",
        "law",
        "family"
    ],
    "wof:name":"Schneiderman Seth E",
    "wof:placetype":"venue"
},
  "geometry": {"coordinates":[-80.286342,25.703485],"type":"Point"}
}