{
  "type": "Feature",
  "properties": {
    "iso:country":"US",
    "sg:address":"1221 Shackleton Rd",
    "sg:city":"Jacksonville",
    "sg:classifiers":[
        {
            "category":"Organizations",
            "subcategory":"Religious Organization",
            "type":"Services"
        }
    ],
    "sg:phone":"+1 904 744 9113",
    "sg:postcode":"32211",
    "sg:province":"FL",
    "sg:tags":[
        "church"
    ],
    "wof:name":"Truth Baptist Church",
    "wof:placetype":"venue"
},
  "geometry": {"coordinates":[-81.592967,30.333438],"type":"Point"}
}