{
  "type": "Feature",
  "properties": {
    "iso:country":"US",
    "sg:address":"6236 US Hwy 90",
    "sg:city":"Milton",
    "sg:classifiers":[
        {
            "category":"Freight",
            "type":"Transportation"
        }
    ],
    "sg:phone":"+1 850 983 7756",
    "sg:postcode":"32583",
    "sg:province":"FL",
    "sg:tags":[
        "general"
    ],
    "wof:name":"Dollar Tree Distribution Inc",
    "wof:placetype":"venue"
},
  "geometry": {"coordinates":[-87.07580900000001,30.602426],"type":"Point"}
}