{
  "type": "Feature",
  "properties": {
    "iso:country":"US",
    "sg:address":"9859 Lake Worth Rd",
    "sg:city":"Wellington",
    "sg:classifiers":[
        {
            "category":"Utilities",
            "subcategory":"Mobile Phone",
            "type":"Services"
        }
    ],
    "sg:phone":"+1 561 296 1420",
    "sg:postcode":"33467",
    "sg:province":"FL",
    "sg:tags":[
        "telephone",
        "cellular"
    ],
    "wof:name":"Cingular Wireless",
    "wof:placetype":"venue"
},
  "geometry": {"coordinates":[-80.20292499999999,26.617213],"type":"Point"}
}