{
  "type": "Feature",
  "properties": {
    "addr:full":"2650 Bahia Vista St Sarasota FL 34239",
    "addr:housenumber":"2650",
    "addr:postcode":"34239",
    "addr:street":"Bahia Vista St",
    "iso:country":"US",
    "sg:address":"2650 Bahia Vista St",
    "sg:city":"Sarasota",
    "sg:classifiers":[
        {
            "category":"Health Services",
            "subcategory":"Health Practitioner",
            "type":"Services"
        }
    ],
    "sg:phone":"+1 941 365 6510",
    "sg:postcode":"34239",
    "sg:province":"FL",
    "sg:tags":[
        "psychologist"
    ],
    "wof:name":"Paloma Ibarra PHD",
    "wof:placetype":"venue"
},
  "geometry": {"coordinates":[-82.51689399999999,27.322736],"type":"Point"}
}