{
  "type": "Feature",
  "properties": {
    "addr:full":"1500 W Washington St Monticello FL 32344",
    "addr:housenumber":"1500",
    "addr:postcode":"32344",
    "addr:street":"W Washington St",
    "iso:country":"US",
    "sg:address":"1500 W Washington St",
    "sg:city":"Monticello",
    "sg:classifiers":[
        {
            "category":"Banks & Credit Unions",
            "subcategory":"Bank",
            "type":"Services"
        }
    ],
    "sg:phone":"+1 850 342 0250",
    "sg:postcode":"32344",
    "sg:province":"FL",
    "sg:tags":[
        "federal"
    ],
    "wof:name":"Jefferson Cnty Teachers Cr Un",
    "wof:placetype":"venue"
},
  "geometry": {"coordinates":[-83.883337,30.545],"type":"Point"}
}