{
  "type": "Feature",
  "properties": {
    "iso:country":"US",
    "sg:address":"5175 W Irlo Bronson Memorial Hwy",
    "sg:city":"Kissimmee",
    "sg:classifiers":[
        {
            "category":"Autos & Motor Vehicles",
            "subcategory":"Recreational Vehicle Sales",
            "type":"Retail Goods"
        }
    ],
    "sg:phone":"+1 407 396 2600",
    "sg:postcode":"34746",
    "sg:province":"FL",
    "wof:name":"Camping World",
    "wof:placetype":"venue"
},
  "geometry": {"coordinates":[-81.49061,28.332857],"type":"Point"}
}