{
  "type": "Feature",
  "properties": {
    "iso:country":"US",
    "sg:address":"108 Windsor Pointe Dr",
    "sg:city":"Palm Beach Gardens",
    "sg:classifiers":[
        {
            "category":"Professional",
            "type":"Services"
        }
    ],
    "sg:phone":"+1 561 626 1028",
    "sg:postcode":"33418",
    "sg:province":"FL",
    "wof:name":"E&J Global Inc",
    "wof:placetype":"venue"
},
  "geometry": {"coordinates":[-80.11348099999999,26.82011],"type":"Point"}
}