{
  "type": "Feature",
  "properties": {
    "iso:country":"US",
    "sg:address":"1062 Montgomery Rd",
    "sg:city":"Altamonte Springs",
    "sg:classifiers":[
        {
            "category":"Restaurant",
            "type":"Food & Drink"
        }
    ],
    "sg:menulink":"http://www.allmenus.com/fl/casselberry-altamonte-springs/38618-china-gate/menu/",
    "sg:phone":"+1 407 774 5445",
    "sg:postcode":"32714",
    "sg:province":"FL",
    "sg:tags":[
        "asian",
        "chinese"
    ],
    "wof:name":"China Gate",
    "wof:placetype":"venue"
},
  "geometry": {"coordinates":[-81.40281299999999,28.685575],"type":"Point"}
}