{
  "type": "Feature",
  "properties": {
    "iso:country":"US",
    "sg:address":"2840 NE 21 Way",
    "sg:city":"Gainesville",
    "sg:classifiers":[
        {
            "category":"Building & Trades",
            "subcategory":"Construction",
            "type":"Services"
        }
    ],
    "sg:phone":"+1 352 338 0617",
    "sg:postcode":"32609",
    "sg:province":"FL",
    "sg:tags":[
        "house",
        "carpentry",
        "contractor"
    ],
    "wof:name":"Robert Eddy",
    "wof:placetype":"venue"
},
  "geometry": {"coordinates":[-82.29510399999999,29.679849],"type":"Point"}
}