{
  "type": "Feature",
  "properties": {
    "addr:full":"3188 Curtis Dr Apopka FL 32703",
    "addr:housenumber":"3188",
    "addr:postcode":"32703",
    "addr:street":"Curtis Dr",
    "iso:country":"US",
    "sg:address":"3188 Curtis Dr",
    "sg:city":"Apopka",
    "sg:classifiers":[
        {
            "category":"Autos & Motor Vehicles",
            "subcategory":"Auto Supplies",
            "type":"Retail Goods"
        }
    ],
    "sg:phone":"+1 407 754 9461",
    "sg:postcode":"32703",
    "sg:province":"FL",
    "sg:tags":[
        "tire"
    ],
    "wof:name":"Burkes Tires",
    "wof:placetype":"venue"
},
  "geometry": {"coordinates":[-81.451224,28.662142],"type":"Point"}
}