{
  "type": "Feature",
  "properties": {
    "iso:country":"US",
    "sg:address":"1532 King Arthur Rd",
    "sg:city":"Jacksonville",
    "sg:classifiers":[
        {
            "category":"Building & Trades",
            "subcategory":"Construction",
            "type":"Services"
        }
    ],
    "sg:phone":"+1 904 744 0565",
    "sg:postcode":"32211",
    "sg:province":"FL",
    "sg:tags":[
        "hanging",
        "contractor"
    ],
    "wof:name":"P T A Painting",
    "wof:placetype":"venue"
},
  "geometry": {"coordinates":[-81.586947,30.338158],"type":"Point"}
}