{
  "type": "Feature",
  "properties": {
    "iso:country":"US",
    "sg:address":"11110 Causeway Blvd",
    "sg:city":"Brandon",
    "sg:classifiers":[
        {
            "category":"Utilities",
            "subcategory":"Mobile Phone",
            "type":"Services"
        },
        {
            "category":"Shopping",
            "subcategory":"Mobile Phones",
            "type":"Retail Goods"
        },
        {
            "category":"Utilities",
            "subcategory":"Telephone",
            "type":"Services"
        },
        {
            "category":"Professional",
            "subcategory":"Computer Services",
            "type":"Services"
        }
    ],
    "sg:phone":"+1 813 661 4426",
    "sg:postcode":"33511",
    "sg:province":"FL",
    "sg:tags":[
        "telecommunication",
        "supply",
        "communication",
        "system",
        "wireless",
        "equipment",
        "cellular"
    ],
    "sg:website":"http://clickserve.dartsearch.net/link/click?lid=43000000308049899",
    "wof:name":"T-Mobile",
    "wof:placetype":"venue"
},
  "geometry": {"coordinates":[-82.326593,27.923234],"type":"Point"}
}