{
  "type": "Feature",
  "properties": {
    "iso:country":"US",
    "sg:address":"868 N Hambletonian Dr",
    "sg:city":"Inverness",
    "sg:classifiers":[
        {
            "category":"Insurance",
            "subcategory":"Insurance Agent",
            "type":"Services"
        }
    ],
    "sg:phone":"+1 352 860 0087",
    "sg:postcode":"34453",
    "sg:province":"FL",
    "wof:name":"Elvira S Vizon",
    "wof:placetype":"venue"
},
  "geometry": {"coordinates":[-82.414304,28.875349],"type":"Point"}
}