{
  "type": "Feature",
  "properties": {
    "iso:country":"US",
    "sg:address":"11840 SW 70th Ave",
    "sg:city":"Miami",
    "sg:classifiers":[
        {
            "category":"Professional",
            "subcategory":"Engineering",
            "type":"Services"
        },
        {
            "category":"Wholesale",
            "subcategory":"Electrical",
            "type":"Manufacturing & Wholesale Goods"
        }
    ],
    "sg:phone":"+1 828 693 1645",
    "sg:postcode":"33156",
    "sg:province":"FL",
    "sg:tags":[
        "system",
        "systems-wholesale",
        "equipment",
        "air conditioning",
        "manufacturer"
    ],
    "wof:name":"The Buchanan Group Inc",
    "wof:placetype":"venue"
},
  "geometry": {"coordinates":[-80.308536,25.65983],"type":"Point"}
}