{
  "type": "Feature",
  "properties": {
    "iso:country":"US",
    "sg:address":"27001 US Hwy 19",
    "sg:city":"Clearwater",
    "sg:classifiers":[
        {
            "category":"Shopping",
            "subcategory":"Musical Instruments",
            "type":"Retail Goods"
        }
    ],
    "sg:phone":"+1 727 796 9411",
    "sg:postcode":"33761",
    "sg:province":"FL",
    "sg:tags":[
        "organs"
    ],
    "wof:name":"Fletcher Music Ctr",
    "wof:placetype":"venue"
},
  "geometry": {"coordinates":[-82.737661,28.016987],"type":"Point"}
}