{
  "type": "Feature",
  "properties": {
    "iso:country":"US",
    "sg:address":"2319 University Blvd W",
    "sg:city":"Jacksonville",
    "sg:classifiers":[
        {
            "category":"Shopping",
            "subcategory":"Florist",
            "type":"Retail Goods"
        }
    ],
    "sg:phone":"+1 904 737 8655",
    "sg:postcode":"32217",
    "sg:province":"FL",
    "wof:name":"Rose of Sharon European Flor",
    "wof:placetype":"venue"
},
  "geometry": {"coordinates":[-81.63515200000001,30.260958],"type":"Point"}
}