{
  "type": "Feature",
  "properties": {
    "addr:full":"525 SE Sunnybrook Ter Port Saint Lucie FL 34983",
    "addr:housenumber":"525",
    "addr:postcode":"34983",
    "addr:street":"Se Sunnybrook Ter;Lucie",
    "iso:country":"US",
    "sg:address":"525 SE Sunnybrook Ter",
    "sg:city":"Port Saint Lucie",
    "sg:classifiers":[
        {
            "category":"Professional",
            "subcategory":"Business Services",
            "type":"Services"
        }
    ],
    "sg:phone":"+1 772 873 2008",
    "sg:postcode":"34983",
    "sg:province":"FL",
    "wof:name":"Your Electronic Solutions LLC",
    "wof:placetype":"venue"
},
  "geometry": {"coordinates":[-80.33501699999999,27.31064],"type":"Point"}
}