{
  "type": "Feature",
  "properties": {
    "addr:full":"450 E Copans Rd Pompano Beach FL 33064",
    "addr:housenumber":"450",
    "addr:postcode":"33064",
    "addr:street":"E Copans Rd",
    "iso:country":"US",
    "sg:address":"450 E Copans Rd",
    "sg:city":"Pompano Beach",
    "sg:classifiers":[
        {
            "category":"Manufacturing",
            "subcategory":"Metals",
            "type":"Manufacturing & Wholesale Goods"
        }
    ],
    "sg:phone":"+1 954 782 2221",
    "sg:postcode":"33064",
    "sg:province":"FL",
    "sg:tags":[
        "forging"
    ],
    "sg:website":"www.usanchor.com",
    "wof:name":"U S Anchor Corp",
    "wof:placetype":"venue"
},
  "geometry": {"coordinates":[-80.116781,26.260115],"type":"Point"}
}