{
  "type": "Feature",
  "properties": {
    "iso:country":"US",
    "sg:address":"408 4th Pl SW",
    "sg:city":"Vero Beach",
    "sg:classifiers":[
        {
            "category":"Wholesale",
            "subcategory":"Metals & Minerals",
            "type":"Manufacturing & Wholesale Goods"
        }
    ],
    "sg:phone":"+1 772 978 4477",
    "sg:postcode":"32962",
    "sg:province":"FL",
    "sg:tags":[
        "aluminum"
    ],
    "wof:name":"Tripod Aluminum",
    "wof:placetype":"venue"
},
  "geometry": {"coordinates":[-80.383183,27.594883],"type":"Point"}
}