{
  "type": "Feature",
  "properties": {
    "iso:country":"US",
    "sg:address":"2 David St",
    "sg:city":"Fort Walton Bch",
    "sg:classifiers":[
        {
            "category":"Manufacturing",
            "subcategory":"Printing",
            "type":"Manufacturing & Wholesale Goods"
        }
    ],
    "sg:phone":"+1 850 863 1996",
    "sg:postcode":"32547",
    "sg:province":"FL",
    "sg:tags":[
        "printer"
    ],
    "wof:name":"Pen Graphix's Printing",
    "wof:placetype":"venue"
},
  "geometry": {"coordinates":[-86.60323,30.445552],"type":"Point"}
}