{
  "type": "Feature",
  "properties": {
    "addr:full":"1952 S Conway Rd Orlando FL 32812",
    "addr:housenumber":"1952",
    "addr:postcode":"32812",
    "addr:street":"S Conway Rd",
    "iso:country":"US",
    "sg:address":"1952 S Conway Rd",
    "sg:city":"Orlando",
    "sg:classifiers":[
        {
            "category":"Building & Trades",
            "subcategory":"Construction",
            "type":"Services"
        }
    ],
    "sg:phone":"+1 407 509 6914",
    "sg:postcode":"32812",
    "sg:province":"FL",
    "sg:tags":[
        "floor",
        "laying",
        "contractor"
    ],
    "wof:name":"Richard L Harlow",
    "wof:placetype":"venue"
},
  "geometry": {"coordinates":[-81.33108,28.520382],"type":"Point"}
}