{
  "type": "Feature",
  "properties": {
    "addr:full":"3410 Old Hampton Dr Wellington FL 33414",
    "addr:housenumber":"3410",
    "addr:postcode":"33414",
    "addr:street":"Old Hampton Dr",
    "iso:country":"US",
    "sg:address":"3410 Old Hampton Dr",
    "sg:city":"Wellington",
    "sg:classifiers":[
        {
            "category":"Banks & Credit Unions",
            "subcategory":"Bank",
            "type":"Services"
        }
    ],
    "sg:phone":"+1 561 795 3728",
    "sg:postcode":"33414",
    "sg:province":"FL",
    "wof:name":"Iberiabank",
    "wof:placetype":"venue"
},
  "geometry": {"coordinates":[-80.284081,26.633151],"type":"Point"}
}