{
  "type": "Feature",
  "properties": {
    "iso:country":"US",
    "sg:address":"34760 US Hwy 19 N",
    "sg:city":"Palm Harbor",
    "sg:classifiers":[
        {
            "category":"Professional",
            "subcategory":"Engineering",
            "type":"Services"
        }
    ],
    "sg:phone":"+1 727 375 8888",
    "sg:postcode":"34684",
    "sg:province":"FL",
    "wof:name":"Facts Engineering Inc",
    "wof:placetype":"venue"
},
  "geometry": {"coordinates":[-82.73941000000001,28.086277],"type":"Point"}
}