{
  "type": "Feature",
  "properties": {
    "iso:country":"US",
    "sg:address":"4618 Pine Island Rd NW",
    "sg:city":"Cape Coral",
    "sg:classifiers":[
        {
            "category":"Shopping",
            "subcategory":"Jewelry",
            "type":"Retail Goods"
        }
    ],
    "sg:phone":"+1 239 283 4040",
    "sg:postcode":"33993",
    "sg:province":"FL",
    "sg:tags":[
        "jeweler"
    ],
    "wof:name":"Trader's Hitching Post",
    "wof:placetype":"venue"
},
  "geometry": {"coordinates":[-82.07192000000001,26.628268],"type":"Point"}
}