{
  "type": "Feature",
  "properties": {
    "iso:country":"US",
    "sg:address":"111 E 36th St",
    "sg:city":"Pensacola",
    "sg:classifiers":[
        {
            "category":"Organizations",
            "subcategory":"Religious Organization",
            "type":"Services"
        }
    ],
    "sg:phone":"+1 850 438 3520",
    "sg:postcode":"32503",
    "sg:province":"FL",
    "sg:website":"www.apostolicfaith.com",
    "wof:name":"Apostolic Faith Church",
    "wof:placetype":"venue"
},
  "geometry": {"coordinates":[-87.221047,30.449888],"type":"Point"}
}