{
  "type": "Feature",
  "properties": {
    "iso:country":"US",
    "sg:address":"917 S Bluebird Ln",
    "sg:city":"Homestead",
    "sg:classifiers":[
        {
            "category":"Building & Trades",
            "subcategory":"Landscaping Services",
            "type":"Services"
        }
    ],
    "sg:phone":"+1 305 245 8946",
    "sg:postcode":"33035",
    "sg:province":"FL",
    "wof:name":"Bradley & Sheri Lambert",
    "wof:placetype":"venue"
},
  "geometry": {"coordinates":[-80.455726,25.460855],"type":"Point"}
}