{
  "type": "Feature",
  "properties": {
    "iso:country":"US",
    "sg:address":"5948 Viola Rd",
    "sg:city":"Venice",
    "sg:classifiers":[
        {
            "category":"Building & Trades",
            "subcategory":"Construction",
            "type":"Services"
        }
    ],
    "sg:phone":"+1 941 497 3207",
    "sg:postcode":"34293",
    "sg:province":"FL",
    "sg:tags":[
        "contractor"
    ],
    "wof:name":"South West Fencing",
    "wof:placetype":"venue"
},
  "geometry": {"coordinates":[-82.408832,27.025886],"type":"Point"}
}