{
  "type": "Feature",
  "properties": {
    "iso:country":"US",
    "sg:address":"3819 Bentford Ct",
    "sg:city":"Orlando",
    "sg:classifiers":[
        {
            "category":"Real Estate",
            "subcategory":"Real Estate Services",
            "type":"Services"
        },
        {
            "category":"Real Estate",
            "subcategory":"Real Estate Agent",
            "type":"Services"
        }
    ],
    "sg:phone":"+1 407 677 7173",
    "sg:postcode":"32817",
    "sg:province":"FL",
    "sg:tags":[
        "buyer",
        "broker"
    ],
    "sg:website":"http://www.realestateoakislandnc.com",
    "wof:name":"Realtor Diane N Gossard",
    "wof:placetype":"venue"
},
  "geometry": {"coordinates":[-81.281616,28.596133],"type":"Point"}
}