{
  "type": "Feature",
  "properties": {
    "iso:country":"US",
    "sg:address":"15911 Kemper Dr",
    "sg:city":"Hudson",
    "sg:classifiers":[
        {
            "category":"Real Estate",
            "subcategory":"Real Estate Operator",
            "type":"Services"
        }
    ],
    "sg:phone":"+1 727 869 5923",
    "sg:postcode":"34667",
    "sg:province":"FL",
    "sg:tags":[
        "apartment"
    ],
    "wof:name":"Seapines Townhouse Apartments",
    "wof:placetype":"venue"
},
  "geometry": {"coordinates":[-82.677139,28.387344],"type":"Point"}
}