{
  "type": "Feature",
  "properties": {
    "addr:full":"4459 Lafayette St Marianna FL 32446",
    "addr:housenumber":"4459",
    "addr:postcode":"32446",
    "addr:street":"Lafayette St",
    "iso:country":"US",
    "sg:address":"4459 Lafayette St",
    "sg:city":"Marianna",
    "sg:classifiers":[
        {
            "category":"Personal",
            "subcategory":"Tanning Parlor",
            "type":"Services"
        },
        {
            "category":"Personal",
            "subcategory":"Beauty Salon",
            "type":"Services"
        },
        {
            "category":"Personal",
            "subcategory":"Nail Salon",
            "type":"Services"
        }
    ],
    "sg:phone":"+1 850 482 5833",
    "sg:postcode":"32446",
    "sg:province":"FL",
    "wof:name":"Shore Tan & Nails",
    "wof:placetype":"venue"
},
  "geometry": {"coordinates":[-85.224639,30.77401],"type":"Point"}
}