{
  "type": "Feature",
  "properties": {
    "iso:country":"US",
    "sg:address":"158 Joewood Trl",
    "sg:city":"Davenport",
    "sg:classifiers":[
        {
            "category":"Real Estate",
            "subcategory":"Real Estate Services",
            "type":"Services"
        },
        {
            "category":"Real Estate",
            "subcategory":"Real Estate Agent",
            "type":"Services"
        }
    ],
    "sg:phone":"+1 863 420 4294",
    "sg:postcode":"33837",
    "sg:province":"FL",
    "sg:tags":[
        "buyer",
        "broker"
    ],
    "wof:name":"Florida Spirit Real Estate Services, Inc",
    "wof:placetype":"venue"
},
  "geometry": {"coordinates":[-81.62225100000001,28.185372],"type":"Point"}
}