{
  "type": "Feature",
  "properties": {
    "iso:country":"US",
    "sg:address":"129 Shore Dr",
    "sg:city":"Eagle Lake",
    "sg:classifiers":[
        {
            "category":"Building & Trades",
            "subcategory":"Construction",
            "type":"Services"
        }
    ],
    "sg:phone":"+1 863 293 7106",
    "sg:postcode":"33884",
    "sg:province":"FL",
    "sg:tags":[
        "contractor"
    ],
    "wof:name":"Carlos L Collins",
    "wof:placetype":"venue"
},
  "geometry": {"coordinates":[-81.661506,28.002125],"type":"Point"}
}