{
  "type": "Feature",
  "properties": {
    "addr:full":"4560 NW 24th Way Boca Raton FL 33431",
    "addr:housenumber":"4560",
    "addr:postcode":"33431",
    "addr:street":"Nw 24Th Way",
    "iso:country":"US",
    "sg:address":"4560 NW 24th Way",
    "sg:city":"Boca Raton",
    "sg:classifiers":[
        {
            "category":"Health Services",
            "subcategory":"Doctor",
            "type":"Services"
        }
    ],
    "sg:phone":"+1 561 997 7033",
    "sg:postcode":"33431",
    "sg:province":"FL",
    "sg:tags":[
        "medical"
    ],
    "wof:name":"Jeffrey L Stanger Dr",
    "wof:placetype":"venue"
},
  "geometry": {"coordinates":[-80.134472,26.390631],"type":"Point"}
}