{
  "type": "Feature",
  "properties": {
    "addr:full":"999 Cattlemen Rd Sarasota FL 34232",
    "addr:housenumber":"999",
    "addr:postcode":"34232",
    "addr:street":"Cattlemen Rd",
    "iso:country":"US",
    "sg:address":"999 Cattlemen Rd",
    "sg:city":"Sarasota",
    "sg:classifiers":[
        {
            "category":"Freight",
            "type":"Transportation"
        }
    ],
    "sg:phone":"+1 941 342 8484",
    "sg:postcode":"34232",
    "sg:province":"FL",
    "sg:tags":[
        "trucking"
    ],
    "wof:name":"Gingerich Trucking Inc",
    "wof:placetype":"venue"
},
  "geometry": {"coordinates":[-82.45138300000001,27.325149],"type":"Point"}
}