{
  "type": "Feature",
  "properties": {
    "addr:full":"6060 Deacon Rd Sarasota FL 34238",
    "addr:postcode":"6060;34238",
    "addr:street":"Deacon Rd",
    "iso:country":"US",
    "sg:address":"6060 Deacon Rd",
    "sg:city":"Sarasota",
    "sg:classifiers":[
        {
            "category":"Wholesale",
            "subcategory":"Hardware",
            "type":"Manufacturing & Wholesale Goods"
        }
    ],
    "sg:phone":"+1 941 924 1760",
    "sg:postcode":"34238",
    "sg:province":"FL",
    "sg:tags":[
        "fastener"
    ],
    "wof:name":"Midwest Fastener Corp",
    "wof:placetype":"venue"
},
  "geometry": {"coordinates":[-82.477839,27.266916],"type":"Point"}
}