{
  "type": "Feature",
  "properties": {
    "addr:full":"1421 E Commercial Blvd Fort Lauderdale FL 33334",
    "addr:housenumber":"1421",
    "addr:postcode":"33334",
    "addr:street":"E Commercial Blvd",
    "iso:country":"US",
    "sg:address":"1421 E Commercial Blvd",
    "sg:city":"Fort Lauderdale",
    "sg:classifiers":[
        {
            "category":"Shopping",
            "type":"Retail Goods"
        }
    ],
    "sg:phone":"+1 954 776 3702",
    "sg:postcode":"33334",
    "sg:province":"FL",
    "sg:tags":[
        "spa",
        "hot",
        "tub"
    ],
    "wof:name":"Hot Spring Spa South Florida",
    "wof:placetype":"venue"
},
  "geometry": {"coordinates":[-80.129544,26.188992],"type":"Point"}
}