{
  "type": "Feature",
  "properties": {
    "iso:country":"US",
    "sg:address":"2310 N Orange Ave",
    "sg:city":"Orlando",
    "sg:classifiers":[
        {
            "category":"Shopping",
            "subcategory":"Florist",
            "type":"Retail Goods"
        }
    ],
    "sg:phone":"+1 407 894 4320",
    "sg:postcode":"32804",
    "sg:province":"FL",
    "sg:tags":[
        "business"
    ],
    "sg:website":"www.orlandoflorist.net",
    "wof:name":"Orlando Florist",
    "wof:placetype":"venue"
},
  "geometry": {"coordinates":[-81.372917,28.573048],"type":"Point"}
}