{
  "type": "Feature",
  "properties": {
    "addr:full":"16393 NW 18th St Hollywood FL 33028",
    "addr:housenumber":"16393",
    "addr:postcode":"33028",
    "addr:street":"Nw 18Th St",
    "iso:country":"US",
    "sg:address":"16393 NW 18th St",
    "sg:city":"Hollywood",
    "sg:classifiers":[
        {
            "category":"Building & Trades",
            "subcategory":"Construction",
            "type":"Services"
        }
    ],
    "sg:phone":"+1 954 432 4382",
    "sg:postcode":"33028",
    "sg:province":"FL",
    "sg:tags":[
        "tile",
        "installation",
        "dealer"
    ],
    "wof:name":"Del Rio Tiles",
    "wof:placetype":"venue"
},
  "geometry": {"coordinates":[-80.36396000000001,26.024432],"type":"Point"}
}