{
  "type": "Feature",
  "properties": {
    "addr:full":"1720 Tamiami Trl S Venice FL 34293",
    "addr:housenumber":"1720",
    "addr:postcode":"34293",
    "addr:street":"Tamiami Trl S",
    "iso:country":"US",
    "sg:address":"1720 Tamiami Trl S",
    "sg:city":"Venice",
    "sg:classifiers":[
        {
            "category":"Restaurant",
            "type":"Food & Drink"
        }
    ],
    "sg:menulink":"http://www.allmenus.com/fl/venice/187775-mcdonalds/menu/",
    "sg:postcode":"34293",
    "sg:province":"FL",
    "sg:tags":[
        "burger",
        "american"
    ],
    "wof:name":"McDonald's",
    "wof:placetype":"venue"
},
  "geometry": {"coordinates":[-82.423153,27.071431],"type":"Point"}
}