{
  "type": "Feature",
  "properties": {
    "addr:full":"9200 Michael Cir Naples FL 34113",
    "addr:housenumber":"9200",
    "addr:postcode":"34113",
    "addr:street":"Michael Cir",
    "iso:country":"US",
    "sg:address":"9200 Michael Cir",
    "sg:city":"Naples",
    "sg:classifiers":[
        {
            "category":"Organizations",
            "subcategory":"Professional Association",
            "type":"Services"
        }
    ],
    "sg:phone":"+1 239 793 7003",
    "sg:postcode":"34113",
    "sg:province":"FL",
    "wof:name":"Sunstone Master Assn",
    "wof:placetype":"venue"
},
  "geometry": {"coordinates":[-81.706845,26.071998],"type":"Point"}
}