{
  "type": "Feature",
  "properties": {
    "iso:country":"US",
    "sg:address":"642 Briarwood Blvd",
    "sg:city":"Naples",
    "sg:classifiers":[
        {
            "category":"Building & Trades",
            "subcategory":"Equipment Rental",
            "type":"Services"
        }
    ],
    "sg:phone":"+1 239 455 8335",
    "sg:postcode":"34104",
    "sg:province":"FL",
    "wof:name":"CNE Vacation Rental",
    "wof:placetype":"venue"
},
  "geometry": {"coordinates":[-81.74891700000001,26.159627],"type":"Point"}
}