{
  "type": "Feature",
  "properties": {
    "iso:country":"US",
    "sg:address":"4130 SW 53rd Ave",
    "sg:city":"Davie",
    "sg:classifiers":[
        {
            "category":"Building & Trades",
            "subcategory":"Landscaping Services",
            "type":"Services"
        }
    ],
    "sg:phone":"+1 954 877 3265",
    "sg:postcode":"33314",
    "sg:province":"FL",
    "sg:tags":[
        "lawn",
        "maintenance",
        "grounds"
    ],
    "wof:name":"Tru Green Chem Lawn",
    "wof:placetype":"venue"
},
  "geometry": {"coordinates":[-80.21713699999999,26.072734],"type":"Point"}
}