{
  "type": "Feature",
  "properties": {
    "iso:country":"US",
    "sg:address":"110 SW 5th Ave",
    "sg:city":"Okeechobee",
    "sg:classifiers":[
        {
            "category":"Building & Trades",
            "subcategory":"Construction",
            "type":"Services"
        }
    ],
    "sg:phone":"+1 863 357 8668",
    "sg:postcode":"34974",
    "sg:province":"FL",
    "sg:tags":[
        "water",
        "well",
        "drilling"
    ],
    "wof:name":"Tri County Water Treatment",
    "wof:placetype":"venue"
},
  "geometry": {"coordinates":[-80.834563,27.243029],"type":"Point"}
}