{
  "type": "Feature",
  "properties": {
    "iso:country":"US",
    "sg:address":"19181 NW 57th Ct",
    "sg:city":"Hialeah",
    "sg:classifiers":[
        {
            "category":"Home & Garden",
            "subcategory":"Household Appliances",
            "type":"Retail Goods"
        }
    ],
    "sg:phone":"+1 305 620 7005",
    "sg:postcode":"33015",
    "sg:province":"FL",
    "sg:tags":[
        "pump"
    ],
    "wof:name":"Pump Outs R Us",
    "wof:placetype":"venue"
},
  "geometry": {"coordinates":[-80.29498,25.94872],"type":"Point"}
}