{
  "type": "Feature",
  "properties": {
    "addr:full":"1520 Bay Rd Mount Dora FL 32757",
    "addr:housenumber":"1520",
    "addr:postcode":"32757",
    "addr:street":"Bay Rd",
    "iso:country":"US",
    "sg:address":"1520 Bay Rd",
    "sg:city":"Mount Dora",
    "sg:classifiers":[
        {
            "category":"Professional",
            "subcategory":"Accounting & Tax Preparation",
            "type":"Services"
        }
    ],
    "sg:phone":"+1 352 735 4673",
    "sg:postcode":"32757",
    "sg:province":"FL",
    "wof:name":"Zanella & Assoc",
    "wof:placetype":"venue"
},
  "geometry": {"coordinates":[-81.68547,28.811791],"type":"Point"}
}