{
  "type": "Feature",
  "properties": {
    "addr:full":"2836 S Adams St Tallahassee FL 32301",
    "addr:housenumber":"2836",
    "addr:postcode":"32301",
    "addr:street":"S Adams St",
    "iso:country":"US",
    "sg:address":"2836 S Adams St",
    "sg:city":"Tallahassee",
    "sg:classifiers":[
        {
            "category":"Retail",
            "subcategory":"Laundry & Dry Cleaning",
            "type":"Services"
        }
    ],
    "sg:phone":"+1 850 570 9504",
    "sg:postcode":"32301",
    "sg:province":"FL",
    "sg:tags":[
        "cleaners"
    ],
    "wof:name":"Door To Door Cleaners",
    "wof:placetype":"venue"
},
  "geometry": {"coordinates":[-84.283492,30.409837],"type":"Point"}
}