{
  "type": "Feature",
  "properties": {
    "addr:full":"2502 N Dale Mabry Hwy Tampa FL 33607",
    "addr:housenumber":"2502",
    "addr:postcode":"33607",
    "addr:street":"N Dale Mabry Hwy",
    "iso:country":"US",
    "sg:address":"2502 N Dale Mabry Hwy",
    "sg:city":"Tampa",
    "sg:classifiers":[
        {
            "category":"Restaurant",
            "type":"Food & Drink"
        }
    ],
    "sg:phone":"+1 813 350 0727",
    "sg:postcode":"33607",
    "sg:province":"FL",
    "wof:name":"Subway Sandwiches & Salads",
    "wof:placetype":"venue"
},
  "geometry": {"coordinates":[-82.505573,27.963008],"type":"Point"}
}