{
  "type": "Feature",
  "properties": {
    "iso:country":"US",
    "sg:address":"4900 Ocean Blvd Apt 402",
    "sg:city":"Sarasota",
    "sg:classifiers":[
        {
            "category":"Professional",
            "type":"Services"
        },
        {
            "category":"Personal",
            "type":"Services"
        }
    ],
    "sg:phone":"+1 941 465 3000",
    "sg:postcode":"34242",
    "sg:province":"FL",
    "sg:tags":[
        "full",
        "organ",
        "material",
        "storage",
        "moving",
        "services-labor",
        "mover",
        "piano"
    ],
    "sg:website":"http://www.bestratemoverssarasota.com",
    "wof:name":"Best Rate Movers",
    "wof:placetype":"venue"
},
  "geometry": {"coordinates":[-82.564339,27.282],"type":"Point"}
}