{
  "type": "Feature",
  "properties": {
    "addr:full":"4000 Collins Ave Miami Beach FL 33140",
    "addr:housenumber":"4000",
    "addr:postcode":"33140",
    "addr:street":"Collins Ave",
    "iso:country":"US",
    "sg:address":"4000 Collins Ave",
    "sg:city":"Miami Beach",
    "sg:classifiers":[
        {
            "category":"Professional",
            "subcategory":"Computer Services",
            "type":"Services"
        }
    ],
    "sg:phone":"+1 305 891 5062",
    "sg:postcode":"33140",
    "sg:province":"FL",
    "sg:tags":[
        "consultant",
        "designer"
    ],
    "wof:name":"Granot Inc",
    "wof:placetype":"venue"
},
  "geometry": {"coordinates":[-80.122996,25.813088],"type":"Point"}
}