{
  "type": "Feature",
  "properties": {
    "iso:country":"US",
    "sg:address":"151 Russ Dr",
    "sg:city":"Gulf Breeze",
    "sg:classifiers":[
        {
            "category":"Building & Trades",
            "subcategory":"Construction",
            "type":"Services"
        }
    ],
    "sg:phone":"+1 850 932 7839",
    "sg:postcode":"32561",
    "sg:province":"FL",
    "sg:tags":[
        "house",
        "builder",
        "operative"
    ],
    "wof:name":"Flowers Construction Inc",
    "wof:placetype":"venue"
},
  "geometry": {"coordinates":[-87.17201300000001,30.361433],"type":"Point"}
}