{
  "type": "Feature",
  "properties": {
    "iso:country":"US",
    "sg:address":"1660 Indian River Dr",
    "sg:city":"Sebastian",
    "sg:classifiers":[
        {
            "category":"Recreation",
            "type":"Entertainment"
        }
    ],
    "sg:phone":"+1 772 388 2950",
    "sg:postcode":"32958",
    "sg:province":"FL",
    "sg:tags":[
        "guide"
    ],
    "wof:name":"Rogue Wave Charters",
    "wof:placetype":"venue"
},
  "geometry": {"coordinates":[-80.472504,27.824951],"type":"Point"}
}