{
  "type": "Feature",
  "properties": {
    "addr:full":"385 S Burnett Rd Cocoa FL 32926",
    "addr:housenumber":"385",
    "addr:postcode":"32926",
    "addr:street":"S Burnett Rd",
    "iso:country":"US",
    "sg:address":"385 S Burnett Rd",
    "sg:city":"Cocoa",
    "sg:classifiers":[
        {
            "category":"Organizations",
            "subcategory":"Religious Organization",
            "type":"Services"
        }
    ],
    "sg:phone":"+1 321 636 6980",
    "sg:postcode":"32926",
    "sg:province":"FL",
    "sg:tags":[
        "church"
    ],
    "wof:name":"Friendship Primitive Bapt Chr",
    "wof:placetype":"venue"
},
  "geometry": {"coordinates":[-80.779847,28.350071],"type":"Point"}
}