{
  "type": "Feature",
  "properties": {
    "iso:country":"US",
    "sg:address":"11 Island Ave",
    "sg:city":"Miami Beach",
    "sg:classifiers":[
        {
            "category":"Real Estate",
            "subcategory":"Real Estate Agent",
            "type":"Services"
        }
    ],
    "sg:phone":"+1 786 621 6004",
    "sg:postcode":"33139",
    "sg:province":"FL",
    "wof:name":"DAK Realty",
    "wof:placetype":"venue"
},
  "geometry": {"coordinates":[-80.147487,25.790608],"type":"Point"}
}