{
  "type": "Feature",
  "properties": {
    "iso:country":"US",
    "sg:address":"1600 NW 93rd Ave",
    "sg:city":"Doral",
    "sg:classifiers":[
        {
            "category":"Professional",
            "subcategory":"Management & Consulting",
            "type":"Services"
        }
    ],
    "sg:phone":"+1 305 593 1881",
    "sg:postcode":"33172",
    "sg:province":"FL",
    "sg:tags":[
        "international",
        "consultant"
    ],
    "wof:name":"Imepa International",
    "wof:placetype":"venue"
},
  "geometry": {"coordinates":[-80.34651100000001,25.790317],"type":"Point"}
}