{
  "type": "Feature",
  "properties": {
    "addr:full":"10843 Dylan Loren Cir Orlando FL 32825",
    "addr:housenumber":"10843",
    "addr:postcode":"32825",
    "addr:street":"Dylan Loren Cir",
    "iso:country":"US",
    "sg:address":"10843 Dylan Loren Cir",
    "sg:city":"Orlando",
    "sg:classifiers":[
        {
            "category":"Health Services",
            "subcategory":"Dentist",
            "type":"Services"
        }
    ],
    "sg:phone":"+1 407 207 4416",
    "sg:postcode":"32825",
    "sg:province":"FL",
    "sg:tags":[
        "product",
        "dentists-cosmetic",
        "dental",
        "teeth",
        "clinic",
        "whitening",
        "dentistry",
        "implant",
        "dentists-implantology"
    ],
    "sg:website":"http://makingorlandosmile.com",
    "wof:name":"Moncrieffe Maxine DDS",
    "wof:placetype":"venue"
},
  "geometry": {"coordinates":[-81.227926,28.539874],"type":"Point"}
}