{
  "type": "Feature",
  "properties": {
    "iso:country":"US",
    "sg:address":"8100 Belvedere Rd",
    "sg:city":"West Palm Beach",
    "sg:classifiers":[
        {
            "category":"Shopping",
            "subcategory":"Bicycles & Sporting Goods",
            "type":"Retail Goods"
        }
    ],
    "sg:phone":"+1 561 790 7101",
    "sg:postcode":"33411",
    "sg:province":"FL",
    "sg:tags":[
        "equipment",
        "golf",
        "supply"
    ],
    "sg:website":"www.golfclubs.net",
    "wof:name":"Golfclubs.Net Inc",
    "wof:placetype":"venue"
},
  "geometry": {"coordinates":[-80.17538399999999,26.691642],"type":"Point"}
}