{
  "type": "Feature",
  "properties": {
    "iso:country":"US",
    "sg:address":"3534 Ontario Rd",
    "sg:city":"Marianna",
    "sg:classifiers":[
        {
            "category":"Organizations",
            "subcategory":"Religious Organization",
            "type":"Services"
        }
    ],
    "sg:phone":"+1 850 482 5878",
    "sg:postcode":"32448",
    "sg:province":"FL",
    "sg:tags":[
        "church"
    ],
    "wof:name":"Damascus Freewill Baptist Chr",
    "wof:placetype":"venue"
},
  "geometry": {"coordinates":[-85.302842,30.741002],"type":"Point"}
}