{
  "type": "Feature",
  "properties": {
    "iso:country":"US",
    "sg:address":"2695 W 70th St",
    "sg:city":"Hialeah",
    "sg:classifiers":[
        {
            "category":"Building & Trades",
            "subcategory":"Construction",
            "type":"Services"
        }
    ],
    "sg:phone":"+1 305 821 3153",
    "sg:postcode":"33016",
    "sg:province":"FL",
    "sg:tags":[
        "house"
    ],
    "wof:name":"Gkte Construction Inc",
    "wof:placetype":"venue"
},
  "geometry": {"coordinates":[-80.33773100000001,25.886176],"type":"Point"}
}