{
  "type": "Feature",
  "properties": {
    "addr:full":"203 S 7th Ave Wauchula FL 33873",
    "addr:housenumber":"203",
    "addr:postcode":"33873",
    "addr:street":"S 7Th Ave",
    "iso:country":"US",
    "sg:address":"203 S 7th Ave",
    "sg:city":"Wauchula",
    "sg:classifiers":[
        {
            "category":"Professional",
            "subcategory":"Accounting & Tax Preparation",
            "type":"Services"
        }
    ],
    "sg:phone":"+1 863 773 6768",
    "sg:postcode":"33873",
    "sg:province":"FL",
    "sg:tags":[
        "accountant"
    ],
    "wof:name":"Manley & Assoc",
    "wof:placetype":"venue"
},
  "geometry": {"coordinates":[-81.812613,27.546101],"type":"Point"}
}