{
  "type": "Feature",
  "properties": {
    "iso:country":"US",
    "sg:address":"261 Bayou Vista St",
    "sg:city":"De Bary",
    "sg:classifiers":[
        {
            "category":"Organizations",
            "subcategory":"Membership Organization",
            "type":"Services"
        }
    ],
    "sg:phone":"+1 386 668 5968",
    "sg:postcode":"32713",
    "sg:province":"FL",
    "wof:name":"Autism Society of America Inc",
    "wof:placetype":"venue"
},
  "geometry": {"coordinates":[-81.303059,28.868702],"type":"Point"}
}