{
  "type": "Feature",
  "properties": {
    "addr:full":"2414 SW 57th Way Hollywood FL 33023",
    "addr:housenumber":"2414",
    "addr:postcode":"33023",
    "addr:street":"Sw 57Th Way",
    "iso:country":"US",
    "sg:address":"2414 SW 57th Way",
    "sg:city":"Hollywood",
    "sg:classifiers":[
        {
            "category":"Wholesale",
            "subcategory":"Motor Vehicles",
            "type":"Manufacturing & Wholesale Goods"
        }
    ],
    "sg:phone":"+1 954 965 9993",
    "sg:postcode":"33023",
    "sg:province":"FL",
    "sg:tags":[
        "automobile",
        "truck",
        "broker"
    ],
    "wof:name":"Cheap Cars",
    "wof:placetype":"venue"
},
  "geometry": {"coordinates":[-80.201961,25.988937],"type":"Point"}
}