{
  "type": "Feature",
  "properties": {
    "iso:country":"US",
    "sg:address":"11631 Columbia Park Dr E",
    "sg:city":"Jacksonville",
    "sg:classifiers":[
        {
            "category":"Building & Trades",
            "subcategory":"Plumbing",
            "type":"Services"
        }
    ],
    "sg:phone":"+1 904 268 5167",
    "sg:postcode":"32258",
    "sg:province":"FL",
    "sg:tags":[
        "conditioning",
        "air",
        "system",
        "contractor"
    ],
    "wof:name":"Kelley's Heating & Air Cond Co",
    "wof:placetype":"venue"
},
  "geometry": {"coordinates":[-81.536704,30.157452],"type":"Point"}
}