{
  "type": "Feature",
  "properties": {
    "addr:full":"8719 US Hwy 1 Port St Lucie FL 34982",
    "addr:housenumber":"8719",
    "addr:postcode":"34982",
    "addr:street":"Us Hwy 1",
    "iso:country":"US",
    "sg:address":"8719 US Hwy 1",
    "sg:city":"Port St Lucie",
    "sg:classifiers":[
        {
            "category":"Shopping",
            "subcategory":"Used Merchandise",
            "type":"Retail Goods"
        }
    ],
    "sg:phone":"+1 772 878 9101",
    "sg:postcode":"34982",
    "sg:province":"FL",
    "sg:tags":[
        "book",
        "rare",
        "dealer"
    ],
    "wof:name":"Mary Loper's Book Xchange",
    "wof:placetype":"venue"
},
  "geometry": {"coordinates":[-80.31101099999999,27.310051],"type":"Point"}
}