{
  "type": "Feature",
  "properties": {
    "addr:full":"5830 9th Ave N Saint Petersburg FL 33710",
    "addr:housenumber":"5830",
    "addr:postcode":"33710",
    "addr:street":"9Th Ave N",
    "iso:country":"US",
    "sg:address":"5830 9th Ave N",
    "sg:city":"Saint Petersburg",
    "sg:classifiers":[
        {
            "category":"Restaurant",
            "type":"Food & Drink"
        }
    ],
    "sg:menulink":"http://www.allmenus.com/fl/st-petersburg/82202-dominos-pizza/menu/",
    "sg:phone":"+1 727 323 1202",
    "sg:postcode":"33710",
    "sg:province":"FL",
    "sg:tags":[
        "american",
        "wing",
        "pizza"
    ],
    "wof:name":"Domino's Pizza",
    "wof:placetype":"venue"
},
  "geometry": {"coordinates":[-82.712959,27.780562],"type":"Point"}
}