{
  "type": "Feature",
  "properties": {
    "iso:country":"US",
    "sg:address":"9700 Collins Ave",
    "sg:city":"Bal Harbour",
    "sg:classifiers":[
        {
            "category":"Shopping",
            "subcategory":"Luggage & Leather Goods",
            "type":"Retail Goods"
        },
        {
            "category":"Real Estate",
            "subcategory":"Real Estate Operator",
            "type":"Services"
        }
    ],
    "sg:phone":"+1 305 868 0118",
    "sg:postcode":"33154",
    "sg:province":"FL",
    "sg:tags":[
        "building",
        "clothing",
        "nonresidential"
    ],
    "wof:name":"Hermes of Paris",
    "wof:placetype":"venue"
},
  "geometry": {"coordinates":[-80.12346100000001,25.887939],"type":"Point"}
}