{
  "type": "Feature",
  "properties": {
    "iso:country":"US",
    "sg:address":"9527 Pine Cone Dr",
    "sg:city":"Cantonment",
    "sg:classifiers":[
        {
            "category":"Farming",
            "subcategory":"Nursery",
            "type":"Manufacturing & Wholesale Goods"
        }
    ],
    "sg:phone":"+1 850 477 4935",
    "sg:postcode":"32533",
    "sg:province":"FL",
    "sg:tags":[
        "ornamental"
    ],
    "wof:name":"J & M Tropicals",
    "wof:placetype":"venue"
},
  "geometry": {"coordinates":[-87.32617500000001,30.535215],"type":"Point"}
}