{
  "type": "Feature",
  "properties": {
    "addr:full":"3919 Phillips Hwy Jacksonville FL 32207",
    "addr:housenumber":"3919",
    "addr:postcode":"32207",
    "addr:street":"Phillips Hwy",
    "iso:country":"US",
    "sg:address":"3919 Phillips Hwy",
    "sg:city":"Jacksonville",
    "sg:classifiers":[
        {
            "category":"Autos & Motor Vehicles",
            "subcategory":"Automobile Sales",
            "type":"Retail Goods"
        }
    ],
    "sg:phone":"+1 904 733 7786",
    "sg:postcode":"32207",
    "sg:province":"FL",
    "sg:tags":[
        "car",
        "dealer"
    ],
    "wof:name":"Buddy Hutchinson Pontiac",
    "wof:placetype":"venue"
},
  "geometry": {"coordinates":[-81.630714,30.283819],"type":"Point"}
}