{
  "type": "Feature",
  "properties": {
    "iso:country":"US",
    "sg:address":"3500 SW 50th Ave",
    "sg:city":"Davie",
    "sg:classifiers":[
        {
            "category":"Building & Trades",
            "subcategory":"Construction",
            "type":"Services"
        }
    ],
    "sg:phone":"+1 954 587 2628",
    "sg:postcode":"33314",
    "sg:province":"FL",
    "sg:tags":[
        "designer",
        "marine",
        "contractor"
    ],
    "wof:name":"Bill Cooper Marine Contractors",
    "wof:placetype":"venue"
},
  "geometry": {"coordinates":[-80.21544299999999,26.07868],"type":"Point"}
}