{
  "type": "Feature",
  "properties": {
    "iso:country":"US",
    "sg:address":"1413 Kilrush Dr",
    "sg:city":"Ormond Beach",
    "sg:classifiers":[
        {
            "category":"Building & Trades",
            "subcategory":"Construction",
            "type":"Services"
        }
    ],
    "sg:phone":"+1 386 447 0705",
    "sg:postcode":"32174",
    "sg:province":"FL",
    "sg:tags":[
        "floor",
        "laying",
        "contractor"
    ],
    "wof:name":"Prestige Wood Floors Inc",
    "wof:placetype":"venue"
},
  "geometry": {"coordinates":[-81.139482,29.380095],"type":"Point"}
}