{
  "type": "Feature",
  "properties": {
    "iso:country":"US",
    "sg:address":"4000 S Sandestin Blvd",
    "sg:city":"Destin",
    "sg:classifiers":[
        {
            "category":"Personal",
            "subcategory":"Beauty Salon",
            "type":"Services"
        }
    ],
    "sg:phone":"+1 850 622 9595",
    "sg:postcode":"32550",
    "sg:province":"FL",
    "sg:tags":[
        "spa",
        "day"
    ],
    "wof:name":"Serenity By The Sea",
    "wof:placetype":"venue"
},
  "geometry": {"coordinates":[-86.33170699999999,30.373216],"type":"Point"}
}