{
  "type": "Feature",
  "properties": {
    "addr:full":"605 S Miramar Ave # 3401 Indialantic FL 32903",
    "addr:housenumber":"605",
    "addr:postcode":"32903",
    "addr:street":"S Miramar Ave # 3401",
    "iso:country":"US",
    "sg:address":"605 S Miramar Ave # 3401",
    "sg:city":"Indialantic",
    "sg:classifiers":[
        {
            "category":"Education",
            "subcategory":"Special Training",
            "type":"Public Place"
        }
    ],
    "sg:phone":"+1 321 724 6651",
    "sg:postcode":"32903",
    "sg:province":"FL",
    "sg:tags":[
        "tutoring"
    ],
    "wof:name":"Action Math Group",
    "wof:placetype":"venue"
},
  "geometry": {"coordinates":[-80.565527,28.088052],"type":"Point"}
}