{
  "type": "Feature",
  "properties": {
    "addr:full":"3490 Pinewalk Dr N Margate FL 33063",
    "addr:housenumber":"3490",
    "addr:postcode":"33063",
    "addr:street":"Pinewalk Dr N Margate",
    "iso:country":"US",
    "sg:address":"3490 Pinewalk Dr N",
    "sg:city":"Margate",
    "sg:classifiers":[
        {
            "category":"Real Estate",
            "subcategory":"Real Estate Operator",
            "type":"Services"
        }
    ],
    "sg:phone":"+1 954 345 0088",
    "sg:postcode":"33063",
    "sg:province":"FL",
    "sg:tags":[
        "building",
        "apartment"
    ],
    "wof:name":"Coral Keys Apartments",
    "wof:placetype":"venue"
},
  "geometry": {"coordinates":[-80.22335,26.269649],"type":"Point"}
}