{
  "type": "Feature",
  "properties": {
    "addr:full":"2702 Goodwood Ct Sarasota FL 34235",
    "addr:housenumber":"2702",
    "addr:postcode":"34235",
    "addr:street":"Goodwood Ct",
    "iso:country":"US",
    "sg:address":"2702 Goodwood Ct",
    "sg:city":"Sarasota",
    "sg:classifiers":[
        {
            "category":"Banks & Credit Unions",
            "subcategory":"Financial Services",
            "type":"Services"
        }
    ],
    "sg:phone":"+1 941 371 0713",
    "sg:postcode":"34235",
    "sg:province":"FL",
    "sg:tags":[
        "trust",
        "management"
    ],
    "wof:name":"Anita Grogan",
    "wof:placetype":"venue"
},
  "geometry": {"coordinates":[-82.456754,27.359717],"type":"Point"}
}