{
  "type": "Feature",
  "properties": {
    "addr:full":"915 8th Ave S Jacksonville Beach FL 32250",
    "addr:housenumber":"915",
    "addr:postcode":"32250",
    "addr:street":"8Th Ave S Jacksonville",
    "iso:country":"US",
    "sg:address":"915 8th Ave S",
    "sg:city":"Jacksonville Beach",
    "sg:classifiers":[
        {
            "category":"Organizations",
            "subcategory":"Community Association",
            "type":"Services"
        }
    ],
    "sg:phone":"+1 904 249 7366",
    "sg:postcode":"32250",
    "sg:province":"FL",
    "wof:name":"VFW Post 3270",
    "wof:placetype":"venue"
},
  "geometry": {"coordinates":[-81.397829,30.279642],"type":"Point"}
}