{
  "type": "Feature",
  "properties": {
    "iso:country":"US",
    "sg:address":"11804 Bruce B Downs Blvd",
    "sg:city":"Tampa",
    "sg:classifiers":[
        {
            "category":"Banks & Credit Unions",
            "subcategory":"Bank",
            "type":"Services"
        }
    ],
    "sg:phone":"+1 813 979 7026",
    "sg:postcode":"33612",
    "sg:province":"FL",
    "sg:tags":[
        "state",
        "commercial"
    ],
    "wof:name":"AmSouth",
    "wof:placetype":"venue"
},
  "geometry": {"coordinates":[-82.42613799999999,28.056976],"type":"Point"}
}