{
  "type": "Feature",
  "properties": {
    "iso:country":"US",
    "sg:address":"12355 SW 129th Ct",
    "sg:city":"Miami",
    "sg:classifiers":[
        {
            "category":"Government",
            "subcategory":"Fire Station",
            "type":"Public Place"
        }
    ],
    "sg:phone":"+1 305 969 1445",
    "sg:postcode":"33186",
    "sg:province":"FL",
    "sg:tags":[
        "equipment-repairing",
        "equipment",
        "protection",
        "servicing",
        "supply"
    ],
    "wof:name":"General Fire Protection",
    "wof:placetype":"venue"
},
  "geometry": {"coordinates":[-80.404416,25.65275],"type":"Point"}
}