{
  "type": "Feature",
  "properties": {
    "iso:country":"US",
    "sg:address":"4526 Lake Calabay Dr",
    "sg:city":"Orlando",
    "sg:classifiers":[
        {
            "category":"Wholesale",
            "subcategory":"Durable Goods & Equipment",
            "type":"Manufacturing & Wholesale Goods"
        }
    ],
    "sg:phone":"+1 407 812 8400",
    "sg:postcode":"32837",
    "sg:province":"FL",
    "sg:tags":[
        "exporter"
    ],
    "wof:name":"BCE For Life Inc",
    "wof:placetype":"venue"
},
  "geometry": {"coordinates":[-81.42812000000001,28.354246],"type":"Point"}
}