{
  "type": "Feature",
  "properties": {
    "iso:country":"US",
    "sg:address":"7254 SW 48th St",
    "sg:city":"Miami",
    "sg:classifiers":[
        {
            "category":"Real Estate",
            "subcategory":"Architect",
            "type":"Services"
        }
    ],
    "sg:phone":"+1 305 661 2070",
    "sg:postcode":"33155",
    "sg:province":"FL",
    "sg:tags":[
        "architectural"
    ],
    "sg:website":"www.chisholmarchitects.com",
    "wof:name":"R E Chisholm Architects Inc",
    "wof:placetype":"venue"
},
  "geometry": {"coordinates":[-80.31210299999999,25.7257],"type":"Point"}
}