{
  "type": "Feature",
  "properties": {
    "iso:country":"US",
    "sg:address":"4124 Kivey Dr",
    "sg:city":"Lake Worth",
    "sg:classifiers":[
        {
            "category":"Building & Trades",
            "subcategory":"Construction",
            "type":"Services"
        }
    ],
    "sg:phone":"+1 561 963 8234",
    "sg:postcode":"33461",
    "sg:province":"FL",
    "sg:tags":[
        "carpentry",
        "contractor"
    ],
    "wof:name":"Caser Window Corp",
    "wof:placetype":"venue"
},
  "geometry": {"coordinates":[-80.1066,26.63336],"type":"Point"}
}