{
  "type": "Feature",
  "properties": {
    "iso:country":"US",
    "sg:address":"7178 NW 12th St",
    "sg:city":"Miami",
    "sg:classifiers":[
        {
            "category":"Shopping",
            "type":"Retail Goods"
        },
        {
            "category":"Organizations",
            "subcategory":"Non-profit Organization",
            "type":"Services"
        }
    ],
    "sg:phone":"+1 305 599 9035",
    "sg:postcode":"33126",
    "sg:province":"FL",
    "sg:tags":[
        "fund",
        "games",
        "raising",
        "merchandise",
        "supply"
    ],
    "wof:name":"Silverman Enterprises",
    "wof:placetype":"venue"
},
  "geometry": {"coordinates":[-80.31246,25.782591],"type":"Point"}
}