{
  "type": "Feature",
  "properties": {
    "addr:full":"6625 Forest Hill Blvd West Palm Beach FL 33413",
    "addr:housenumber":"6625",
    "addr:postcode":"33413",
    "addr:street":"Forest Hill Blvd",
    "iso:country":"US",
    "sg:address":"6625 Forest Hill Blvd",
    "sg:city":"West Palm Beach",
    "sg:classifiers":[
        {
            "category":"Government",
            "subcategory":"Office",
            "type":"Public Place"
        }
    ],
    "sg:phone":"+1 561 969 0778",
    "sg:postcode":"33413",
    "sg:province":"FL",
    "sg:tags":[
        "function",
        "limited",
        "for",
        "provide",
        "citizen",
        "senior",
        "care"
    ],
    "wof:name":"Community Services",
    "wof:placetype":"venue"
},
  "geometry": {"coordinates":[-80.147025,26.651255],"type":"Point"}
}