{
  "type": "Feature",
  "properties": {
    "iso:country":"US",
    "sg:address":"10201 SW 58th Ct",
    "sg:city":"Miami",
    "sg:classifiers":[
        {
            "category":"Education",
            "subcategory":"Special Training",
            "type":"Public Place"
        },
        {
            "category":"Restaurant",
            "type":"Food & Drink"
        },
        {
            "category":"Education",
            "subcategory":"Vocational School",
            "type":"Public Place"
        }
    ],
    "sg:phone":"+1 305 667 8231",
    "sg:postcode":"33156",
    "sg:province":"FL",
    "sg:tags":[
        "cooking",
        "instruction"
    ],
    "wof:name":"Taste of Royalty",
    "wof:placetype":"venue"
},
  "geometry": {"coordinates":[-80.287308,25.675985],"type":"Point"}
}