{
  "type": "Feature",
  "properties": {
    "addr:full":"128 Pinedale Rd Longwood FL 32713",
    "addr:housenumber":"128",
    "addr:postcode":"32713",
    "addr:street":"Pinedale Rd",
    "iso:country":"US",
    "sg:address":"128 Pinedale Rd",
    "sg:city":"Longwood",
    "sg:classifiers":[
        {
            "category":"Wholesale",
            "subcategory":"Groceries",
            "type":"Manufacturing & Wholesale Goods"
        }
    ],
    "sg:phone":"+1 407 489 7342",
    "sg:postcode":"32713",
    "sg:province":"FL",
    "sg:tags":[
        "general"
    ],
    "wof:name":"Buildernet Inc",
    "wof:placetype":"venue"
},
  "geometry": {"coordinates":[-81.319405,28.881415],"type":"Point"}
}