{
  "type": "Feature",
  "properties": {
    "addr:full":"3001 Edgewater Dr Orlando FL 32804",
    "addr:housenumber":"3001",
    "addr:postcode":"32804",
    "addr:street":"Edgewater Dr",
    "iso:country":"US",
    "sg:address":"3001 Edgewater Dr",
    "sg:city":"Orlando",
    "sg:classifiers":[
        {
            "category":"Cinema",
            "subcategory":"Movie Rental",
            "type":"Entertainment"
        }
    ],
    "sg:phone":"+1 407 422 9989",
    "sg:postcode":"32804",
    "sg:province":"FL",
    "sg:tags":[
        "video",
        "used",
        "tape",
        "merchandise"
    ],
    "wof:name":"College Park Video",
    "wof:placetype":"venue"
},
  "geometry": {"coordinates":[-81.38959699999999,28.581111],"type":"Point"}
}