{
  "type": "Feature",
  "properties": {
    "addr:full":"1242 Dinnerbell Ln E Dunedin FL 34698",
    "addr:housenumber":"1242",
    "addr:postcode":"34698",
    "addr:street":"Dinnerbell Ln E",
    "iso:country":"US",
    "sg:address":"1242 Dinnerbell Ln E",
    "sg:city":"Dunedin",
    "sg:classifiers":[
        {
            "category":"Wholesale",
            "subcategory":"Non-durable Goods",
            "type":"Manufacturing & Wholesale Goods"
        }
    ],
    "sg:phone":"+1 727 733 2228",
    "sg:postcode":"34698",
    "sg:province":"FL",
    "sg:tags":[
        "advertising"
    ],
    "wof:name":"Brewer's Graphics",
    "wof:placetype":"venue"
},
  "geometry": {"coordinates":[-82.751515,28.024353],"type":"Point"}
}