{
  "type": "Feature",
  "properties": {
    "addr:full":"1913 SE 9th Ter Cape Coral FL 33990",
    "addr:housenumber":"1913",
    "addr:postcode":"33990",
    "addr:street":"Se 9Th Ter",
    "iso:country":"US",
    "sg:address":"1913 SE 9th Ter",
    "sg:city":"Cape Coral",
    "sg:classifiers":[
        {
            "category":"Building & Trades",
            "subcategory":"Construction",
            "type":"Services"
        }
    ],
    "sg:phone":"+1 239 574 5135",
    "sg:postcode":"33990",
    "sg:province":"FL",
    "sg:tags":[
        "floor",
        "laying",
        "contractor"
    ],
    "wof:name":"Fuzzy Side Floors Inc",
    "wof:placetype":"venue"
},
  "geometry": {"coordinates":[-81.93326,26.63552],"type":"Point"}
}