{
  "type": "Feature",
  "properties": {
    "iso:country":"US",
    "sg:address":"309 NE 13th St",
    "sg:city":"Cape Coral",
    "sg:classifiers":[
        {
            "category":"Building & Trades",
            "subcategory":"Construction",
            "type":"Services"
        }
    ],
    "sg:phone":"+1 239 772 0152",
    "sg:postcode":"33909",
    "sg:province":"FL",
    "sg:tags":[
        "general",
        "contractor"
    ],
    "wof:name":"Kurt Love Construction Inc",
    "wof:placetype":"venue"
},
  "geometry": {"coordinates":[-81.967868,26.676853],"type":"Point"}
}