{
  "type": "Feature",
  "properties": {
    "addr:full":"7541 Glenmoor Ln Winter Park FL 32792",
    "addr:housenumber":"7541",
    "addr:postcode":"32792",
    "addr:street":"Glenmoor Ln",
    "iso:country":"US",
    "sg:address":"7541 Glenmoor Ln",
    "sg:city":"Winter Park",
    "sg:classifiers":[
        {
            "category":"Manufacturing",
            "subcategory":"Apparel",
            "type":"Manufacturing & Wholesale Goods"
        }
    ],
    "sg:phone":"+1 407 671 3505",
    "sg:postcode":"32792",
    "sg:province":"FL",
    "sg:tags":[
        "textile",
        "product",
        "fabricated",
        "mfg"
    ],
    "wof:name":"Kids Klothesline",
    "wof:placetype":"venue"
},
  "geometry": {"coordinates":[-81.284233,28.602463],"type":"Point"}
}