{
  "type": "Feature",
  "properties": {
    "iso:country":"US",
    "sg:address":"5771 NW 7th St",
    "sg:city":"Miami",
    "sg:classifiers":[
        {
            "category":"Health Services",
            "subcategory":"Doctor",
            "type":"Services"
        }
    ],
    "sg:phone":"+1 305 267 3751",
    "sg:postcode":"33126",
    "sg:province":"FL",
    "sg:tags":[
        "surgeon",
        "oral"
    ],
    "wof:name":"Claro Rita M DDS",
    "wof:placetype":"venue"
},
  "geometry": {"coordinates":[-80.290001,25.7778],"type":"Point"}
}