{
  "type": "Feature",
  "properties": {
    "iso:country":"US",
    "sg:address":"4976 SW Leighton Farm Ave",
    "sg:city":"Palm City",
    "sg:classifiers":[
        {
            "category":"Shopping",
            "type":"Retail Goods"
        }
    ],
    "sg:phone":"+1 772 223 8780",
    "sg:postcode":"34990",
    "sg:province":"FL",
    "sg:tags":[
        "pet",
        "shop"
    ],
    "wof:name":"Exotic Reptiles Jungle",
    "wof:placetype":"venue"
},
  "geometry": {"coordinates":[-80.30251699999999,27.145021],"type":"Point"}
}