{
  "type": "Feature",
  "properties": {
    "addr:full":"730 E Strawbridge Ave Melbourne FL 32901",
    "addr:housenumber":"730",
    "addr:postcode":"32901",
    "addr:street":"E Strawbridge Ave",
    "iso:country":"US",
    "sg:address":"730 E Strawbridge Ave",
    "sg:city":"Melbourne",
    "sg:classifiers":[
        {
            "category":"Professional",
            "subcategory":"Lawyer & Legal Services",
            "type":"Services"
        }
    ],
    "sg:phone":"+1 321 254 4040",
    "sg:postcode":"32901",
    "sg:province":"FL",
    "sg:tags":[
        "attorney"
    ],
    "wof:name":"Whittington Energy",
    "wof:placetype":"venue"
},
  "geometry": {"coordinates":[-80.608352,28.079507],"type":"Point"}
}