{
  "type": "Feature",
  "properties": {
    "addr:full":"38 NE 20th Ave Pompano Beach FL 33060",
    "addr:housenumber":"38",
    "addr:postcode":"33060",
    "addr:street":"Ne 20Th Ave",
    "iso:country":"US",
    "sg:address":"38 NE 20th Ave",
    "sg:city":"Pompano Beach",
    "sg:classifiers":[
        {
            "category":"Health Services",
            "subcategory":"Doctor",
            "type":"Services"
        }
    ],
    "sg:phone":"+1 954 942 2550",
    "sg:postcode":"33060",
    "sg:province":"FL",
    "wof:name":"Jacobson Mc DDS PA",
    "wof:placetype":"venue"
},
  "geometry": {"coordinates":[-80.10383299999999,26.23327],"type":"Point"}
}