{
  "type": "Feature",
  "properties": {
    "iso:country":"US",
    "sg:address":"1100 NW 95th St",
    "sg:city":"Miami",
    "sg:classifiers":[
        {
            "category":"Health Services",
            "subcategory":"Medical Lab",
            "type":"Services"
        },
        {
            "category":"Organizations",
            "subcategory":"Non-profit Organization",
            "type":"Services"
        },
        {
            "category":"Insurance",
            "subcategory":"Health Insurance",
            "type":"Services"
        },
        {
            "category":"Science Facility",
            "type":"Public Place"
        }
    ],
    "sg:phone":"+1 305 835 2449",
    "sg:postcode":"33150",
    "sg:province":"FL",
    "sg:tags":[
        "development",
        "foundations-educational",
        "philanthropic",
        "laboratories-research",
        "research",
        "maintenance"
    ],
    "wof:name":"Alzheimer's Association",
    "wof:placetype":"venue"
},
  "geometry": {"coordinates":[-80.21423799999999,25.861689],"type":"Point"}
}