{
  "type": "Feature",
  "properties": {
    "addr:full":"846 Lincoln Rd Miami Beach FL 33139",
    "addr:housenumber":"846",
    "addr:postcode":"33139",
    "addr:street":"Lincoln Rd",
    "iso:country":"US",
    "sg:address":"846 Lincoln Rd",
    "sg:city":"Miami Beach",
    "sg:classifiers":[
        {
            "category":"Arena",
            "subcategory":"Sports Club",
            "type":"Entertainment"
        }
    ],
    "sg:phone":"+1 305 529 0166",
    "sg:postcode":"33139",
    "sg:province":"FL",
    "sg:tags":[
        "marketing"
    ],
    "wof:name":"Sports & Sponsorships Inc",
    "wof:placetype":"venue"
},
  "geometry": {"coordinates":[-80.137201,25.79046],"type":"Point"}
}