{
  "type": "Feature",
  "properties": {
    "addr:full":"2039 Soutel Dr Jacksonville FL 32208",
    "addr:housenumber":"2039",
    "addr:postcode":"32208",
    "addr:street":"Soutel Dr",
    "iso:country":"US",
    "sg:address":"2039 Soutel Dr",
    "sg:city":"Jacksonville",
    "sg:classifiers":[
        {
            "category":"Professional",
            "subcategory":"Accounting & Tax Preparation",
            "type":"Services"
        }
    ],
    "sg:phone":"+1 904 924 7820",
    "sg:postcode":"32208",
    "sg:province":"FL",
    "sg:tags":[
        "return",
        "filing"
    ],
    "wof:name":"Jones Tax Offices Inc",
    "wof:placetype":"venue"
},
  "geometry": {"coordinates":[-81.68960199999999,30.409063],"type":"Point"}
}