{
  "type": "Feature",
  "properties": {
    "iso:country":"US",
    "sg:address":"7873 Gunn Hwy",
    "sg:city":"Tampa",
    "sg:classifiers":[
        {
            "category":"Restaurant",
            "type":"Food & Drink"
        }
    ],
    "sg:menulink":"http://www.allmenus.com/fl/citrus-park-fern-lake/93254-smoothie-king/menu/",
    "sg:phone":"+1 813 926 0700",
    "sg:postcode":"33626",
    "sg:province":"FL",
    "sg:tags":[
        "smoothy",
        "juice",
        "american"
    ],
    "wof:name":"Smoothie King",
    "wof:placetype":"venue"
},
  "geometry": {"coordinates":[-82.577023,28.078817],"type":"Point"}
}