{
  "type": "Feature",
  "properties": {
    "addr:full":"7721 NW 64th St Miami FL 33166",
    "addr:housenumber":"7721",
    "addr:postcode":"33166",
    "addr:street":"Nw 64Th St",
    "iso:country":"US",
    "sg:address":"7721 NW 64th St",
    "sg:city":"Miami",
    "sg:classifiers":[
        {
            "category":"Freight",
            "type":"Transportation"
        }
    ],
    "sg:phone":"+1 786 367 1659",
    "sg:postcode":"33166",
    "sg:province":"FL",
    "sg:tags":[
        "trucking"
    ],
    "wof:name":"R & M Millenium Transport Inc",
    "wof:placetype":"venue"
},
  "geometry": {"coordinates":[-80.322568,25.831747],"type":"Point"}
}