{
  "type": "Feature",
  "properties": {
    "iso:country":"US",
    "sg:address":"10680 S Ocean Dr",
    "sg:city":"Jensen Beach",
    "sg:classifiers":[
        {
            "category":"Real Estate",
            "subcategory":"Real Estate Agent",
            "type":"Services"
        }
    ],
    "sg:phone":"+1 772 229 3088",
    "sg:postcode":"34957",
    "sg:province":"FL",
    "wof:name":"Island Crest Condominium",
    "wof:placetype":"venue"
},
  "geometry": {"coordinates":[-80.20437200000001,27.269296],"type":"Point"}
}