{
  "type": "Feature",
  "properties": {
    "iso:country":"US",
    "sg:address":"3640 SE 26th Ave",
    "sg:city":"Ocala",
    "sg:classifiers":[
        {
            "category":"Manufacturing",
            "subcategory":"Chemicals & Compounds",
            "type":"Manufacturing & Wholesale Goods"
        },
        {
            "category":"Building & Trades",
            "subcategory":"Cleaning & Sanitation",
            "type":"Services"
        },
        {
            "category":"Building & Trades",
            "subcategory":"Equipment Rental",
            "type":"Services"
        }
    ],
    "sg:phone":"+1 352 867 1198",
    "sg:postcode":"34471",
    "sg:province":"FL",
    "sg:tags":[
        "systems-pressure",
        "steam",
        "indust-wholesale",
        "manufacturer"
    ],
    "wof:name":"Candu Services",
    "wof:placetype":"venue"
},
  "geometry": {"coordinates":[-82.102142,29.150903],"type":"Point"}
}