{
  "type": "Feature",
  "properties": {
    "addr:full":"477 Palm St West Palm Beach FL 33401",
    "addr:housenumber":"477",
    "addr:postcode":"33401",
    "addr:street":"Palm St",
    "iso:country":"US",
    "sg:address":"477 Palm St",
    "sg:city":"West Palm Beach",
    "sg:classifiers":[
        {
            "category":"Banks & Credit Unions",
            "subcategory":"Investment Brokerage",
            "type":"Services"
        }
    ],
    "sg:phone":"+1 561 832 3277",
    "sg:postcode":"33401",
    "sg:province":"FL",
    "sg:tags":[
        "commodity"
    ],
    "wof:name":"Investor One Financial",
    "wof:placetype":"venue"
},
  "geometry": {"coordinates":[-80.054501,26.699357],"type":"Point"}
}