{
  "type": "Feature",
  "properties": {
    "iso:country":"US",
    "sg:address":"2927 Kerry Forest Pkwy",
    "sg:city":"Tallahassee",
    "sg:classifiers":[
        {
            "category":"Banks & Credit Unions",
            "subcategory":"Investment Brokerage",
            "type":"Services"
        }
    ],
    "sg:phone":"+1 850 668 3426",
    "sg:postcode":"32309",
    "sg:province":"FL",
    "sg:tags":[
        "advisory",
        "financial"
    ],
    "wof:name":"Old World Financial Svc",
    "wof:placetype":"venue"
},
  "geometry": {"coordinates":[-84.223896,30.540364],"type":"Point"}
}