{
  "type": "Feature",
  "properties": {
    "iso:country":"US",
    "sg:address":"5009 Old Howell Branch Rd",
    "sg:city":"Winter Park",
    "sg:classifiers":[
        {
            "category":"Travel",
            "subcategory":"Travel Agent",
            "type":"Entertainment"
        }
    ],
    "sg:phone":"+1 407 657 6462",
    "sg:postcode":"32792",
    "sg:province":"FL",
    "sg:tags":[
        "agency",
        "bureau"
    ],
    "wof:name":"X L Shaved Ice",
    "wof:placetype":"venue"
},
  "geometry": {"coordinates":[-81.282398,28.613621],"type":"Point"}
}