{
  "type": "Feature",
  "properties": {
    "addr:full":"213 S Sunland Dr Sanford FL 32773",
    "addr:housenumber":"213",
    "addr:postcode":"32773",
    "addr:street":"S Sunland Dr",
    "iso:country":"US",
    "sg:address":"213 S Sunland Dr",
    "sg:city":"Sanford",
    "sg:classifiers":[
        {
            "category":"Education",
            "subcategory":"Special Training",
            "type":"Public Place"
        }
    ],
    "sg:phone":"+1 407 321 4882",
    "sg:postcode":"32773",
    "sg:province":"FL",
    "sg:tags":[
        "instruction",
        "music"
    ],
    "sg:website":"www.thecentralspot.com",
    "wof:name":"Affordable Singing Voice Lsns",
    "wof:placetype":"venue"
},
  "geometry": {"coordinates":[-81.28513599999999,28.748063],"type":"Point"}
}