{
  "type": "Feature",
  "properties": {
    "iso:country":"US",
    "sg:address":"611 Crosby Dr",
    "sg:city":"Altamonte Springs",
    "sg:classifiers":[
        {
            "category":"Building & Trades",
            "subcategory":"Electrical",
            "type":"Services"
        }
    ],
    "sg:phone":"+1 407 862 3640",
    "sg:postcode":"32714",
    "sg:province":"FL",
    "sg:tags":[
        "electrical",
        "contractor"
    ],
    "wof:name":"Donnellan Electric Inc",
    "wof:placetype":"venue"
},
  "geometry": {"coordinates":[-81.42361099999999,28.67504],"type":"Point"}
}