{
  "type": "Feature",
  "properties": {
    "iso:country":"US",
    "sg:address":"2675 Flamingo Dr",
    "sg:city":"Miami Beach",
    "sg:classifiers":[
        {
            "category":"Professional",
            "subcategory":"Management & Consulting",
            "type":"Services"
        }
    ],
    "sg:phone":"+1 305 531 8844",
    "sg:postcode":"33140",
    "sg:province":"FL",
    "wof:name":"Bill Bard Associates Inc",
    "wof:placetype":"venue"
},
  "geometry": {"coordinates":[-80.12779,25.802014],"type":"Point"}
}