{
  "type": "Feature",
  "properties": {
    "addr:full":"228 Towne Center Cir Sanford FL 32771",
    "addr:housenumber":"228",
    "addr:postcode":"32771",
    "addr:street":"Towne Center Cir",
    "iso:country":"US",
    "sg:address":"228 Towne Center Cir",
    "sg:city":"Sanford",
    "sg:classifiers":[
        {
            "category":"Shopping",
            "subcategory":"Gifts & Souvenirs",
            "type":"Retail Goods"
        }
    ],
    "sg:phone":"+1 407 328 9338",
    "sg:postcode":"32771",
    "sg:province":"FL",
    "sg:tags":[
        "store",
        "variety"
    ],
    "wof:name":"Brookstone",
    "wof:placetype":"venue"
},
  "geometry": {"coordinates":[-81.336755,28.808653],"type":"Point"}
}