{
  "type": "Feature",
  "properties": {
    "iso:country":"US",
    "sg:address":"401 1st Ave",
    "sg:city":"Melbourne Beach",
    "sg:phone":"+1 321 725 5023",
    "sg:postcode":"32951",
    "sg:province":"FL",
    "sg:tags":[
        "irrigation",
        "system"
    ],
    "wof:name":"Mikes Pump & Irrigation Inc",
    "wof:placetype":"venue"
},
  "geometry": {"coordinates":[-80.563138,28.067363],"type":"Point"}
}