{
  "type": "Feature",
  "properties": {
    "iso:country":"US",
    "sg:address":"2827 Ballard Ave",
    "sg:city":"Orlando",
    "sg:classifiers":[
        {
            "category":"Real Estate",
            "subcategory":"Real Estate Operator",
            "type":"Services"
        }
    ],
    "sg:phone":"+1 407 568 8150",
    "sg:postcode":"32833",
    "sg:province":"FL",
    "sg:tags":[
        "property",
        "lessor"
    ],
    "wof:name":"Leola Corporation",
    "wof:placetype":"venue"
},
  "geometry": {"coordinates":[-81.077546,28.506238],"type":"Point"}
}