{
  "type": "Feature",
  "properties": {
    "iso:country":"US",
    "sg:address":"1012 SW 8th St",
    "sg:city":"Miami",
    "sg:classifiers":[
        {
            "category":"Home & Garden",
            "subcategory":"Furniture",
            "type":"Retail Goods"
        }
    ],
    "sg:phone":"+1 305 858 8190",
    "sg:postcode":"33130",
    "sg:province":"FL",
    "sg:tags":[
        "store"
    ],
    "wof:name":"New Designs Furniture Corp",
    "wof:placetype":"venue"
},
  "geometry": {"coordinates":[-80.2118,25.766001],"type":"Point"}
}