{
  "type": "Feature",
  "properties": {
    "addr:full":"3955 E Hwy 98 Panama City FL 32401",
    "addr:housenumber":"3955",
    "addr:postcode":"32401",
    "addr:street":"E Hwy 98",
    "iso:country":"US",
    "sg:address":"3955 E Hwy 98",
    "sg:city":"Panama City",
    "sg:classifiers":[
        {
            "category":"Bars & Pubs",
            "type":"Food & Drink"
        }
    ],
    "sg:phone":"+1 850 872 0730",
    "sg:postcode":"32401",
    "sg:province":"FL",
    "wof:name":"Eddie's Red House",
    "wof:placetype":"venue"
},
  "geometry": {"coordinates":[-85.615611,30.141748],"type":"Point"}
}