{
  "type": "Feature",
  "properties": {
    "iso:country":"US",
    "sg:address":"6000 Glades Rd",
    "sg:city":"Boca Raton",
    "sg:classifiers":[
        {
            "category":"Wholesale",
            "subcategory":"Groceries",
            "type":"Manufacturing & Wholesale Goods"
        }
    ],
    "sg:phone":"+1 561 394 6631",
    "sg:postcode":"33432",
    "sg:province":"FL",
    "sg:tags":[
        "pretzel"
    ],
    "wof:name":"Auntie Anne's Hand Rolled Soft",
    "wof:placetype":"venue"
},
  "geometry": {"coordinates":[-80.136458,26.368633],"type":"Point"}
}