{
  "type": "Feature",
  "properties": {
    "addr:full":"14434 N Dale Mabry Hwy Tampa FL 33618",
    "addr:housenumber":"14434",
    "addr:postcode":"33618",
    "addr:street":"N Dale Mabry Hwy",
    "iso:country":"US",
    "sg:address":"14434 N Dale Mabry Hwy",
    "sg:city":"Tampa",
    "sg:classifiers":[
        {
            "category":"Wholesale",
            "subcategory":"Farm Supplies",
            "type":"Manufacturing & Wholesale Goods"
        },
        {
            "category":"Shopping",
            "subcategory":"Bicycles & Sporting Goods",
            "type":"Retail Goods"
        }
    ],
    "sg:phone":"+1 813 962 6610",
    "sg:postcode":"33618",
    "sg:province":"FL",
    "sg:tags":[
        "harness",
        "saddlery",
        "distribute",
        "equestrian"
    ],
    "sg:website":"www.whipnspur.com",
    "wof:name":"Whip N Spur Catalog & Tack Shp",
    "wof:placetype":"venue"
},
  "geometry": {"coordinates":[-82.505679,28.083135],"type":"Point"}
}