{
  "type": "Feature",
  "properties": {
    "iso:country":"US",
    "sg:address":"2434 Remington Blvd",
    "sg:city":"Kissimmee",
    "sg:classifiers":[
        {
            "category":"Education",
            "subcategory":"School",
            "type":"Public Place"
        }
    ],
    "sg:phone":"+1 407 518 2000",
    "sg:postcode":"34744",
    "sg:province":"FL",
    "sg:website":"http://www.osceola.k12.fl.us",
    "wof:name":"Partin Settlement Elem School",
    "wof:placetype":"venue"
},
  "geometry": {"coordinates":[-81.332848,28.28154],"type":"Point"}
}