{
  "type": "Feature",
  "properties": {
    "iso:country":"US",
    "sg:address":"844 SW 1st St",
    "sg:city":"Miami",
    "sg:classifiers":[
        {
            "category":"Professional",
            "subcategory":"Lawyer & Legal Services",
            "type":"Services"
        }
    ],
    "sg:phone":"+1 305 545 1000",
    "sg:postcode":"33130",
    "sg:province":"FL",
    "wof:name":"Parets Juan Carlos Law Office",
    "wof:placetype":"venue"
},
  "geometry": {"coordinates":[-80.20819899999999,25.7728],"type":"Point"}
}