{
  "type": "Feature",
  "properties": {
    "addr:full":"4512 NW 94th Ct Doral FL 33178",
    "addr:housenumber":"4512",
    "addr:postcode":"33178",
    "addr:street":"Nw 94Th Ct",
    "iso:country":"US",
    "sg:address":"4512 NW 94th Ct",
    "sg:city":"Doral",
    "sg:classifiers":[
        {
            "category":"Wholesale",
            "subcategory":"Durable Goods & Equipment",
            "type":"Manufacturing & Wholesale Goods"
        }
    ],
    "sg:phone":"+1 305 479 5165",
    "sg:postcode":"33178",
    "sg:province":"FL",
    "sg:tags":[
        "exporter"
    ],
    "wof:name":"L D Trade Inc",
    "wof:placetype":"venue"
},
  "geometry": {"coordinates":[-80.350033,25.815707],"type":"Point"}
}