{
  "type": "Feature",
  "properties": {
    "iso:country":"US",
    "sg:address":"3201 E Colonial Dr",
    "sg:city":"Orlando",
    "sg:classifiers":[
        {
            "category":"Shopping",
            "subcategory":"Discount & Variety Stores",
            "type":"Retail Goods"
        }
    ],
    "sg:phone":"+1 407 897 5340",
    "sg:postcode":"32803",
    "sg:province":"FL",
    "sg:tags":[
        "merchandise",
        "general"
    ],
    "wof:name":"Dollar Plus",
    "wof:placetype":"venue"
},
  "geometry": {"coordinates":[-81.343277,28.553407],"type":"Point"}
}