{
  "type": "Feature",
  "properties": {
    "iso:country":"US",
    "sg:address":"1220 Ortega Rd",
    "sg:city":"West Palm Beach",
    "sg:classifiers":[
        {
            "category":"Wholesale",
            "subcategory":"Fruits & Vegetables",
            "type":"Manufacturing & Wholesale Goods"
        }
    ],
    "sg:phone":"+1 561 832 2446",
    "sg:postcode":"33405",
    "sg:province":"FL",
    "sg:tags":[
        "fresh"
    ],
    "wof:name":"Erneston & Sons Produce Inc",
    "wof:placetype":"venue"
},
  "geometry": {"coordinates":[-80.06965599999999,26.689874],"type":"Point"}
}