{
  "type": "Feature",
  "properties": {
    "addr:full":"7225 W Colonial Dr Orlando FL 32818",
    "addr:housenumber":"7225",
    "addr:postcode":"32818",
    "addr:street":"W Colonial Dr",
    "iso:country":"US",
    "sg:address":"7225 W Colonial Dr",
    "sg:city":"Orlando",
    "sg:classifiers":[
        {
            "category":"Restaurant",
            "type":"Food & Drink"
        }
    ],
    "sg:menulink":"http://www.allmenus.com/fl/winter-garden-ocoee/101088-smokey-bones/menu/",
    "sg:phone":"+1 407 293 3330",
    "sg:postcode":"32818",
    "sg:province":"FL",
    "sg:tags":[
        "barbecue",
        "american"
    ],
    "wof:name":"Smokey Bones",
    "wof:placetype":"venue"
},
  "geometry": {"coordinates":[-81.478847,28.552072],"type":"Point"}
}