{
  "type": "Feature",
  "properties": {
    "iso:country":"US",
    "sg:address":"4039 NW Blitchton Rd",
    "sg:city":"Ocala",
    "sg:classifiers":[
        {
            "category":"Real Estate",
            "subcategory":"Real Estate Services",
            "type":"Services"
        },
        {
            "category":"Building & Trades",
            "subcategory":"Cleaning & Sanitation",
            "type":"Services"
        }
    ],
    "sg:phone":"+1 352 629 7947",
    "sg:postcode":"34482",
    "sg:province":"FL",
    "sg:tags":[
        "maintenance",
        "cleaners-interior"
    ],
    "wof:name":"Davis Cleaning Service",
    "wof:placetype":"venue"
},
  "geometry": {"coordinates":[-82.188349,29.20816],"type":"Point"}
}