{
  "type": "Feature",
  "properties": {
    "iso:country":"US",
    "sg:address":"7761 Templeton Rd",
    "sg:city":"Pensacola",
    "sg:classifiers":[
        {
            "category":"Professional",
            "type":"Services"
        }
    ],
    "sg:phone":"+1 850 457 7617",
    "sg:postcode":"32506",
    "sg:province":"FL",
    "wof:name":"Homefront",
    "wof:placetype":"venue"
},
  "geometry": {"coordinates":[-87.31340299999999,30.407445],"type":"Point"}
}