{
  "type": "Feature",
  "properties": {
    "iso:country":"US",
    "sg:address":"12411 SW 106th Ter",
    "sg:city":"Miami",
    "sg:classifiers":[
        {
            "category":"Travel",
            "subcategory":"Travel Agent",
            "type":"Entertainment"
        }
    ],
    "sg:phone":"+1 305 595 0102",
    "sg:postcode":"33186",
    "sg:province":"FL",
    "sg:tags":[
        "agency"
    ],
    "wof:name":"Transamerica Co",
    "wof:placetype":"venue"
},
  "geometry": {"coordinates":[-80.39686399999999,25.667937],"type":"Point"}
}