{
  "type": "Feature",
  "properties": {
    "iso:country":"US",
    "sg:address":"220 SW 36th Ave",
    "sg:city":"Miami",
    "sg:classifiers":[
        {
            "category":"Building & Trades",
            "subcategory":"Construction",
            "type":"Services"
        }
    ],
    "sg:phone":"+1 305 461 2352",
    "sg:postcode":"33135",
    "sg:province":"FL",
    "sg:tags":[
        "floor",
        "laying",
        "contractor"
    ],
    "wof:name":"Pablo Marquez Flooring Corp",
    "wof:placetype":"venue"
},
  "geometry": {"coordinates":[-80.253398,25.769405],"type":"Point"}
}