{
  "type": "Feature",
  "properties": {
    "addr:full":"1337 Oakfield Dr Brandon FL 33511",
    "addr:housenumber":"1337",
    "addr:postcode":"33511",
    "addr:street":"Oakfield Dr",
    "iso:country":"US",
    "sg:address":"1337 Oakfield Dr",
    "sg:city":"Brandon",
    "sg:classifiers":[
        {
            "category":"Building & Trades",
            "subcategory":"Equipment Rental",
            "type":"Services"
        }
    ],
    "sg:phone":"+1 813 689 8616",
    "sg:postcode":"33511",
    "sg:province":"FL",
    "sg:tags":[
        "yard"
    ],
    "wof:name":"United Rentals",
    "wof:placetype":"venue"
},
  "geometry": {"coordinates":[-82.303859,27.934023],"type":"Point"}
}