{
  "type": "Feature",
  "properties": {
    "addr:full":"17947 SE 89th Natchez Ave Lady Lake FL 32162",
    "addr:housenumber":"17947",
    "addr:postcode":"32162",
    "addr:street":"Se 89Th Natchez Ave",
    "iso:country":"US",
    "sg:address":"17947 SE 89th Natchez Ave",
    "sg:city":"Lady Lake",
    "sg:classifiers":[
        {
            "category":"Shopping",
            "subcategory":"Hobbies, Toys, & Games",
            "type":"Retail Goods"
        }
    ],
    "sg:phone":"+1 352 751 2588",
    "sg:postcode":"32162",
    "sg:province":"FL",
    "wof:name":"Village Hobby",
    "wof:placetype":"venue"
},
  "geometry": {"coordinates":[-82.00805,28.961223],"type":"Point"}
}