{
  "type": "Feature",
  "properties": {
    "addr:full":"4810 Alhambra Cir Miami FL 33146",
    "addr:housenumber":"4810",
    "addr:postcode":"33146",
    "addr:street":"Alhambra Cir",
    "iso:country":"US",
    "sg:address":"4810 Alhambra Cir",
    "sg:city":"Miami",
    "sg:classifiers":[
        {
            "category":"Real Estate",
            "subcategory":"Developer",
            "type":"Services"
        }
    ],
    "sg:phone":"+1 305 662 1001",
    "sg:postcode":"33146",
    "sg:province":"FL",
    "wof:name":"Venelandia Acres",
    "wof:placetype":"venue"
},
  "geometry": {"coordinates":[-80.2842,25.726262],"type":"Point"}
}