{
  "type": "Feature",
  "properties": {
    "iso:country":"US",
    "sg:address":"9322 7th Ave",
    "sg:city":"Orlando",
    "sg:classifiers":[
        {
            "category":"Building & Trades",
            "subcategory":"Landscaping Services",
            "type":"Services"
        }
    ],
    "sg:phone":"+1 407 856 6272",
    "sg:postcode":"32824",
    "sg:province":"FL",
    "sg:tags":[
        "gardener"
    ],
    "wof:name":"Daniel S Mccard",
    "wof:placetype":"venue"
},
  "geometry": {"coordinates":[-81.362717,28.431442],"type":"Point"}
}