{
  "type": "Feature",
  "properties": {
    "addr:full":"2292 W Palma Cir West Palm Beach FL 33415",
    "addr:housenumber":"2292",
    "addr:postcode":"33415",
    "addr:street":"W Palma Cir",
    "iso:country":"US",
    "sg:address":"2292 W Palma Cir",
    "sg:city":"West Palm Beach",
    "sg:classifiers":[
        {
            "category":"Shopping",
            "subcategory":"Computers & Home Electronics",
            "type":"Retail Goods"
        }
    ],
    "sg:phone":"+1 561 968 9577",
    "sg:postcode":"33415",
    "sg:province":"FL",
    "wof:name":"Phase Computers",
    "wof:placetype":"venue"
},
  "geometry": {"coordinates":[-80.116046,26.646198],"type":"Point"}
}