{
  "type": "Feature",
  "properties": {
    "iso:country":"US",
    "sg:address":"1502 SE Pruitt Rd",
    "sg:city":"Port St Lucie",
    "sg:classifiers":[
        {
            "category":"Retail",
            "subcategory":"Veterinary Services",
            "type":"Services"
        }
    ],
    "sg:phone":"+1 772 337 9926",
    "sg:postcode":"34952",
    "sg:province":"FL",
    "sg:tags":[
        "veterinarian"
    ],
    "wof:name":"Animal Planet Veterinary Hosp",
    "wof:placetype":"venue"
},
  "geometry": {"coordinates":[-80.31774900000001,27.25858],"type":"Point"}
}