{
  "type": "Feature",
  "properties": {
    "iso:country":"US",
    "sg:address":"1778 Nettington Ct",
    "sg:city":"Jacksonville",
    "sg:classifiers":[
        {
            "category":"Home & Garden",
            "subcategory":"Furniture",
            "type":"Retail Goods"
        }
    ],
    "sg:phone":"+1 904 998 0424",
    "sg:postcode":"32246",
    "sg:province":"FL",
    "sg:tags":[
        "store"
    ],
    "wof:name":"Baby's Away Of Jacksonville",
    "wof:placetype":"venue"
},
  "geometry": {"coordinates":[-81.513266,30.3202],"type":"Point"}
}