{
  "type": "Feature",
  "properties": {
    "iso:country":"US",
    "sg:address":"8651 Navarre Pkwy",
    "sg:city":"Navarre",
    "sg:classifiers":[
        {
            "category":"Restaurant",
            "type":"Food & Drink"
        }
    ],
    "sg:phone":"+1 850 396 6568",
    "sg:postcode":"32566",
    "sg:province":"FL",
    "sg:tags":[
        "pizza"
    ],
    "wof:name":"Helen Back Again Navarre",
    "wof:placetype":"venue"
},
  "geometry": {"coordinates":[-86.86162400000001,30.401464],"type":"Point"}
}