{
  "type": "Feature",
  "properties": {
    "iso:country":"US",
    "sg:address":"2880 Orange St",
    "sg:city":"Marianna",
    "sg:classifiers":[
        {
            "category":"Professional",
            "subcategory":"Accounting & Tax Preparation",
            "type":"Services"
        }
    ],
    "sg:phone":"+1 850 526 5800",
    "sg:postcode":"32448",
    "sg:province":"FL",
    "sg:tags":[
        "return",
        "filing"
    ],
    "wof:name":"Dumas Tax Svc",
    "wof:placetype":"venue"
},
  "geometry": {"coordinates":[-85.24185,30.772253],"type":"Point"}
}