{
  "type": "Feature",
  "properties": {
    "addr:full":"4601 W Hallandale Beach Blvd Hollywood FL 33023",
    "addr:housenumber":"4601",
    "addr:postcode":"33023",
    "addr:street":"W Hallandale Beach Blvd",
    "iso:country":"US",
    "sg:address":"4601 W Hallandale Beach Blvd",
    "sg:city":"Hollywood",
    "sg:classifiers":[
        {
            "category":"Autos & Motor Vehicles",
            "subcategory":"Automobile Sales",
            "type":"Retail Goods"
        }
    ],
    "sg:phone":"+1 954 965 7133",
    "sg:postcode":"33023",
    "sg:province":"FL",
    "sg:tags":[
        "used"
    ],
    "wof:name":"Maurices Enterprises Inc",
    "wof:placetype":"venue"
},
  "geometry": {"coordinates":[-80.191147,25.984344],"type":"Point"}
}