{
  "type": "Feature",
  "properties": {
    "iso:country":"US",
    "sg:address":"8833 Waynell Ct",
    "sg:city":"Gulf Breeze",
    "sg:classifiers":[
        {
            "category":"Shopping",
            "subcategory":"Clothing, Apparel, & Fashions",
            "type":"Retail Goods"
        }
    ],
    "sg:phone":"+1 850 217 1179",
    "sg:postcode":"32566",
    "sg:province":"FL",
    "wof:name":"Men & Women Apparel Inc",
    "wof:placetype":"venue"
},
  "geometry": {"coordinates":[-86.853408,30.426578],"type":"Point"}
}