{
  "type": "Feature",
  "properties": {
    "iso:country":"US",
    "sg:address":"3121 Overhill Dr",
    "sg:city":"Jacksonville",
    "sg:classifiers":[
        {
            "category":"Building & Trades",
            "subcategory":"Construction",
            "type":"Services"
        }
    ],
    "sg:phone":"+1 904 744 0112",
    "sg:postcode":"32277",
    "sg:province":"FL",
    "sg:tags":[
        "contractor"
    ],
    "wof:name":"Jacob Contracting Co",
    "wof:placetype":"venue"
},
  "geometry": {"coordinates":[-81.586201,30.358351],"type":"Point"}
}