{
  "type": "Feature",
  "properties": {
    "addr:full":"800 Ave L SE Winter Haven FL 33880",
    "addr:housenumber":"800",
    "addr:postcode":"33880",
    "addr:street":"Ave;Se",
    "iso:country":"US",
    "sg:address":"800 Ave L SE",
    "sg:city":"Winter Haven",
    "sg:classifiers":[
        {
            "category":"Building & Trades",
            "subcategory":"Construction",
            "type":"Services"
        }
    ],
    "sg:phone":"+1 863 299 7665",
    "sg:postcode":"33880",
    "sg:province":"FL",
    "sg:tags":[
        "coping",
        "plastering",
        "tiling",
        "pool",
        "swimming"
    ],
    "wof:name":"Guardian Pool Svc & Repair",
    "wof:placetype":"venue"
},
  "geometry": {"coordinates":[-81.712895,28.010386],"type":"Point"}
}