{
  "type": "Feature",
  "properties": {
    "iso:country":"US",
    "sg:address":"7332 Castle Dr",
    "sg:city":"Sarasota",
    "sg:classifiers":[
        {
            "category":"Wholesale",
            "subcategory":"Jewelry",
            "type":"Manufacturing & Wholesale Goods"
        }
    ],
    "sg:phone":"+1 941 378 9998",
    "sg:postcode":"34240",
    "sg:province":"FL",
    "sg:tags":[
        "stone"
    ],
    "wof:name":"Tempus Limited Enterprises",
    "wof:placetype":"venue"
},
  "geometry": {"coordinates":[-82.421846,27.348381],"type":"Point"}
}