{
  "type": "Feature",
  "properties": {
    "iso:country":"US",
    "sg:address":"950 NW 1st Ave",
    "sg:city":"Miami",
    "sg:classifiers":[
        {
            "category":"Professional",
            "subcategory":"Business Services",
            "type":"Services"
        }
    ],
    "sg:phone":"+1 786 287 0565",
    "sg:postcode":"33136",
    "sg:province":"FL",
    "sg:tags":[
        "performance",
        "parts",
        "accessory"
    ],
    "wof:name":"All In One",
    "wof:placetype":"venue"
},
  "geometry": {"coordinates":[-80.19644599999999,25.783206],"type":"Point"}
}