{
  "type": "Feature",
  "properties": {
    "iso:country":"US",
    "sg:address":"6302 SW 131st Ln",
    "sg:city":"Ocala",
    "sg:classifiers":[
        {
            "category":"Building & Trades",
            "subcategory":"Construction",
            "type":"Services"
        }
    ],
    "sg:phone":"+1 352 502 6929",
    "sg:postcode":"34473",
    "sg:province":"FL",
    "sg:tags":[
        "carpenter"
    ],
    "wof:name":"Carpentry Services",
    "wof:placetype":"venue"
},
  "geometry": {"coordinates":[-82.223968,29.030773],"type":"Point"}
}