{
  "type": "Feature",
  "properties": {
    "addr:full":"5501 W Waters Ave Tampa FL 33634",
    "addr:housenumber":"5501",
    "addr:postcode":"33634",
    "addr:street":"W Waters Ave",
    "iso:country":"US",
    "sg:address":"5501 W Waters Ave",
    "sg:city":"Tampa",
    "sg:classifiers":[
        {
            "category":"Wholesale",
            "subcategory":"Hardware",
            "type":"Manufacturing & Wholesale Goods"
        }
    ],
    "sg:phone":"+1 813 884 9767",
    "sg:postcode":"33634",
    "sg:province":"FL",
    "sg:tags":[
        "fastener"
    ],
    "wof:name":"Fastening Systems",
    "wof:placetype":"venue"
},
  "geometry": {"coordinates":[-82.53482200000001,28.025641],"type":"Point"}
}