{
  "type": "Feature",
  "properties": {
    "iso:country":"US",
    "sg:address":"213 S Washington Ave",
    "sg:city":"Titusville",
    "sg:classifiers":[
        {
            "category":"Shopping",
            "subcategory":"Used Merchandise",
            "type":"Retail Goods"
        }
    ],
    "sg:phone":"+1 321 264 7475",
    "sg:postcode":"32796",
    "sg:province":"FL",
    "wof:name":"Central Garage Antiques",
    "wof:placetype":"venue"
},
  "geometry": {"coordinates":[-80.80747700000001,28.612722],"type":"Point"}
}