{
  "type": "Feature",
  "properties": {
    "addr:full":"1090 Bella Vista Blvd St Augustine FL 32084",
    "addr:housenumber":"1090",
    "addr:postcode":"32084",
    "addr:street":"Bella Vista Blvd St",
    "iso:country":"US",
    "sg:address":"1090 Bella Vista Blvd",
    "sg:city":"St Augustine",
    "sg:classifiers":[
        {
            "category":"Real Estate",
            "subcategory":"Real Estate Operator",
            "type":"Services"
        }
    ],
    "sg:phone":"+1 904 826 0019",
    "sg:postcode":"32084",
    "sg:province":"FL",
    "sg:tags":[
        "condominium"
    ],
    "wof:name":"Las Palmas",
    "wof:placetype":"venue"
},
  "geometry": {"coordinates":[-81.32111399999999,29.922614],"type":"Point"}
}