{
  "type": "Feature",
  "properties": {
    "iso:country":"US",
    "sg:address":"150 S Charles Richard Beall Blvd",
    "sg:city":"Debary",
    "sg:classifiers":[
        {
            "category":"Professional",
            "subcategory":"Lawyer & Legal Services",
            "type":"Services"
        }
    ],
    "sg:phone":"+1 386 668 4451",
    "sg:postcode":"32713",
    "sg:province":"FL",
    "sg:tags":[
        "attorney",
        "estate",
        "wills",
        "practice",
        "planning",
        "plan",
        "trust"
    ],
    "wof:name":"Stonestreet Daphne K Atty",
    "wof:placetype":"venue"
},
  "geometry": {"coordinates":[-81.31101200000001,28.879335],"type":"Point"}
}