{
  "type": "Feature",
  "properties": {
    "iso:country":"US",
    "sg:address":"5555 S Kirkman Rd",
    "sg:city":"Orlando",
    "sg:classifiers":[
        {
            "category":"Shopping",
            "subcategory":"Clothing, Apparel, & Fashions",
            "type":"Retail Goods"
        }
    ],
    "sg:phone":"+1 407 345 1400",
    "sg:postcode":"32811",
    "sg:province":"FL",
    "sg:tags":[
        "item",
        "bathing",
        "t",
        "gift",
        "suit"
    ],
    "wof:name":"S Mart",
    "wof:placetype":"venue"
},
  "geometry": {"coordinates":[-81.45874999999999,28.481975],"type":"Point"}
}