{
  "type": "Feature",
  "properties": {
    "iso:country":"US",
    "sg:address":"7813 S Dixie Hwy",
    "sg:city":"West Palm Beach",
    "sg:classifiers":[
        {
            "category":"Shopping",
            "subcategory":"Discount & Variety Stores",
            "type":"Retail Goods"
        }
    ],
    "sg:phone":"+1 561 493 3882",
    "sg:postcode":"33405",
    "sg:province":"FL",
    "sg:website":"www.dollartree.com",
    "wof:name":"Dollar Tree",
    "wof:placetype":"venue"
},
  "geometry": {"coordinates":[-80.05637400000001,26.646231],"type":"Point"}
}