{
  "type": "Feature",
  "properties": {
    "iso:country":"US",
    "sg:address":"38862 Pattie Rd",
    "sg:city":"Zephyrhills",
    "sg:classifiers":[
        {
            "category":"Wholesale",
            "subcategory":"Meat",
            "type":"Manufacturing & Wholesale Goods"
        }
    ],
    "sg:phone":"+1 813 782 1878",
    "sg:postcode":"33540",
    "sg:province":"FL",
    "sg:tags":[
        "butchering"
    ],
    "wof:name":"Weicht's Custom Slaughter Inc",
    "wof:placetype":"venue"
},
  "geometry": {"coordinates":[-82.169127,28.197271],"type":"Point"}
}