{
  "type": "Feature",
  "properties": {
    "iso:country":"US",
    "sg:address":"3725 NW 80th St",
    "sg:city":"Miami",
    "sg:classifiers":[
        {
            "category":"Home & Garden",
            "subcategory":"Furniture",
            "type":"Retail Goods"
        }
    ],
    "sg:phone":"+1 305 696 9951",
    "sg:postcode":"33147",
    "sg:province":"FL",
    "sg:tags":[
        "cabinet"
    ],
    "wof:name":"Reality Kitchen Cabinets",
    "wof:placetype":"venue"
},
  "geometry": {"coordinates":[-80.258149,25.84651],"type":"Point"}
}