{
  "type": "Feature",
  "properties": {
    "addr:full":"817 Ohio Ave St Cloud FL 34769",
    "addr:housenumber":"817",
    "addr:postcode":"34769",
    "addr:street":"Ohio Ave",
    "iso:country":"US",
    "sg:address":"817 Ohio Ave",
    "sg:city":"St Cloud",
    "sg:classifiers":[
        {
            "category":"Building & Trades",
            "subcategory":"Construction",
            "type":"Services"
        }
    ],
    "sg:phone":"+1 407 414 2008",
    "sg:postcode":"34769",
    "sg:province":"FL",
    "sg:tags":[
        "home",
        "improvement"
    ],
    "wof:name":"Larry Davis Home Repair",
    "wof:placetype":"venue"
},
  "geometry": {"coordinates":[-81.280052,28.249838],"type":"Point"}
}