{
  "type": "Feature",
  "properties": {
    "iso:country":"US",
    "sg:address":"3280 45th Ave NE",
    "sg:city":"Naples",
    "sg:classifiers":[
        {
            "category":"Autos & Motor Vehicles",
            "subcategory":"Automobile Sales",
            "type":"Retail Goods"
        }
    ],
    "sg:phone":"+1 239 455 3917",
    "sg:postcode":"34120",
    "sg:province":"FL",
    "sg:tags":[
        "new",
        "used",
        "car"
    ],
    "wof:name":"Capital Motors Corp",
    "wof:placetype":"venue"
},
  "geometry": {"coordinates":[-81.542096,26.314365],"type":"Point"}
}