{
  "type": "Feature",
  "properties": {
    "iso:country":"US",
    "sg:address":"280 Wekiva Springs Rd",
    "sg:city":"Longwood",
    "sg:classifiers":[
        {
            "category":"Health Services",
            "subcategory":"Doctor",
            "type":"Services"
        }
    ],
    "sg:phone":"+1 407 788 2273",
    "sg:postcode":"32779",
    "sg:province":"FL",
    "sg:tags":[
        "medicine",
        "internal"
    ],
    "wof:name":"Tamayo Raul MD",
    "wof:placetype":"venue"
},
  "geometry": {"coordinates":[-81.408165,28.690806],"type":"Point"}
}