{
  "type": "Feature",
  "properties": {
    "addr:full":"5201 W Laurel St Tampa FL 33607",
    "addr:housenumber":"5201",
    "addr:postcode":"33607",
    "addr:street":"W Laurel St",
    "iso:country":"US",
    "sg:address":"5201 W Laurel St",
    "sg:city":"Tampa",
    "sg:classifiers":[
        {
            "category":"Professional",
            "subcategory":"Management & Consulting",
            "type":"Services"
        }
    ],
    "sg:phone":"+1 813 286 3434",
    "sg:postcode":"33607",
    "sg:province":"FL",
    "sg:tags":[
        "food"
    ],
    "wof:name":"Hopco Food Svc",
    "wof:placetype":"venue"
},
  "geometry": {"coordinates":[-82.52899600000001,27.95598],"type":"Point"}
}