{
  "type": "Feature",
  "properties": {
    "addr:full":"5985 Logan Ave Cocoa FL 32927",
    "addr:housenumber":"5985",
    "addr:postcode":"32927",
    "addr:street":"Logan Ave",
    "iso:country":"US",
    "sg:address":"5985 Logan Ave",
    "sg:city":"Cocoa",
    "sg:classifiers":[
        {
            "category":"Home & Garden",
            "subcategory":"Building Materials",
            "type":"Retail Goods"
        },
        {
            "category":"Building & Trades",
            "subcategory":"Construction",
            "type":"Services"
        }
    ],
    "sg:phone":"+1 321 213 6389",
    "sg:postcode":"32927",
    "sg:province":"FL",
    "sg:tags":[
        "concrete",
        "staining",
        "contractor"
    ],
    "wof:name":"3 Buds Concrete",
    "wof:placetype":"venue"
},
  "geometry": {"coordinates":[-80.822197,28.463611],"type":"Point"}
}