{
  "type": "Feature",
  "properties": {
    "iso:country":"US",
    "sg:address":"4508 27th Ave W",
    "sg:city":"Bradenton",
    "sg:classifiers":[
        {
            "category":"Banks & Credit Unions",
            "subcategory":"Investment Brokerage",
            "type":"Services"
        }
    ],
    "sg:phone":"+1 941 798 3065",
    "sg:postcode":"34209",
    "sg:province":"FL",
    "sg:tags":[
        "advisory"
    ],
    "wof:name":"Tom S Enterprise USA Inc",
    "wof:placetype":"venue"
},
  "geometry": {"coordinates":[-82.60690200000001,27.476675],"type":"Point"}
}