{
  "type": "Feature",
  "properties": {
    "iso:country":"US",
    "sg:address":"127 E New York Ave",
    "sg:city":"Deland",
    "sg:classifiers":[
        {
            "category":"Professional",
            "subcategory":"Lawyer & Legal Services",
            "type":"Services"
        }
    ],
    "sg:phone":"+1 386 822 5633",
    "sg:postcode":"32724",
    "sg:province":"FL",
    "sg:website":"www.philpottandsawtelle.com",
    "wof:name":"Philpott & Sawtelle Pllc",
    "wof:placetype":"venue"
},
  "geometry": {"coordinates":[-81.302832,29.028233],"type":"Point"}
}