{
  "type": "Feature",
  "properties": {
    "iso:country":"US",
    "sg:address":"3004 Central Ave",
    "sg:city":"St Petersburg",
    "sg:classifiers":[
        {
            "category":"Personal",
            "subcategory":"Beauty Salon",
            "type":"Services"
        }
    ],
    "sg:phone":"+1 727 327 0468",
    "sg:postcode":"33712",
    "sg:province":"FL",
    "sg:tags":[
        "shop"
    ],
    "wof:name":"Touba Africian Hair Braiding",
    "wof:placetype":"venue"
},
  "geometry": {"coordinates":[-82.675265,27.770909],"type":"Point"}
}