{
  "type": "Feature",
  "properties": {
    "iso:country":"US",
    "sg:address":"7349 N Kendall Dr",
    "sg:city":"Miami",
    "sg:classifiers":[
        {
            "category":"Personal",
            "subcategory":"Beauty Salon",
            "type":"Services"
        }
    ],
    "sg:phone":"+1 305 661 5428",
    "sg:postcode":"33156",
    "sg:province":"FL",
    "sg:tags":[
        "hair"
    ],
    "wof:name":"Mia & Maxx Hair Studio",
    "wof:placetype":"venue"
},
  "geometry": {"coordinates":[-80.31240099999999,25.688601],"type":"Point"}
}