{
  "type": "Feature",
  "properties": {
    "iso:country":"US",
    "sg:address":"4817 NW 72nd Ln",
    "sg:city":"Gainesville",
    "sg:classifiers":[
        {
            "category":"Real Estate",
            "subcategory":"Real Estate Services",
            "type":"Services"
        },
        {
            "category":"Real Estate",
            "subcategory":"Real Estate Agent",
            "type":"Services"
        }
    ],
    "sg:phone":"+1 352 372 5067",
    "sg:postcode":"32653",
    "sg:province":"FL",
    "sg:tags":[
        "buyer",
        "broker"
    ],
    "wof:name":"Barry E Hubbard Pa",
    "wof:placetype":"venue"
},
  "geometry": {"coordinates":[-82.394488,29.721046],"type":"Point"}
}