{
  "type": "Feature",
  "properties": {
    "iso:country":"US",
    "sg:address":"1201 George Bush Blvd",
    "sg:city":"Delray Beach",
    "sg:classifiers":[
        {
            "category":"Professional",
            "subcategory":"Lawyer & Legal Services",
            "type":"Services"
        }
    ],
    "sg:phone":"+1 561 330 3615",
    "sg:postcode":"33483",
    "sg:province":"FL",
    "sg:tags":[
        "attorney"
    ],
    "wof:name":"Anthony J Thompson Law Office",
    "wof:placetype":"venue"
},
  "geometry": {"coordinates":[-80.05896,26.474724],"type":"Point"}
}