{
  "type": "Feature",
  "properties": {
    "iso:country":"US",
    "sg:address":"256 NW 7th St",
    "sg:city":"Boca Raton",
    "sg:classifiers":[
        {
            "category":"Retail",
            "subcategory":"Car Wash",
            "type":"Services"
        }
    ],
    "sg:phone":"+1 561 393 9184",
    "sg:postcode":"33432",
    "sg:province":"FL",
    "sg:tags":[
        "automobile",
        "detail",
        "clean"
    ],
    "wof:name":"Autobahnd",
    "wof:placetype":"venue"
},
  "geometry": {"coordinates":[-80.091291,26.356614],"type":"Point"}
}