{
  "type": "Feature",
  "properties": {
    "addr:full":"13185 Cairo Ln Opa Locka FL 33054",
    "addr:housenumber":"13185",
    "addr:postcode":"33054",
    "addr:street":"Cairo Ln",
    "iso:country":"US",
    "sg:address":"13185 Cairo Ln",
    "sg:city":"Opa Locka",
    "sg:classifiers":[
        {
            "category":"Wholesale",
            "subcategory":"Auto Parts",
            "type":"Manufacturing & Wholesale Goods"
        }
    ],
    "sg:phone":"+1 305 687 7878",
    "sg:postcode":"33054",
    "sg:province":"FL",
    "sg:tags":[
        "automobile",
        "rebuilt"
    ],
    "wof:name":"J C Motors",
    "wof:placetype":"venue"
},
  "geometry": {"coordinates":[-80.257643,25.892747],"type":"Point"}
}