{
  "type": "Feature",
  "properties": {
    "iso:country":"US",
    "sg:address":"1250 Mount Homer Rd",
    "sg:city":"Eustis",
    "sg:classifiers":[
        {
            "category":"Wholesale",
            "subcategory":"Groceries",
            "type":"Manufacturing & Wholesale Goods"
        }
    ],
    "sg:phone":"+1 352 483 0828",
    "sg:postcode":"32726",
    "sg:province":"FL",
    "sg:tags":[
        "confectionery",
        "candy"
    ],
    "wof:name":"D & D Sweets",
    "wof:placetype":"venue"
},
  "geometry": {"coordinates":[-81.69541599999999,28.829235],"type":"Point"}
}