{
  "type": "Feature",
  "properties": {
    "iso:country":"US",
    "sg:address":"1740 W Fairbanks Ave",
    "sg:city":"Winter Park",
    "sg:classifiers":[
        {
            "category":"Shopping",
            "subcategory":"Antiques",
            "type":"Retail Goods"
        }
    ],
    "sg:phone":"+1 407 644 1060",
    "sg:postcode":"32789",
    "sg:province":"FL",
    "sg:website":"www.flosantiqueaccents.com",
    "wof:name":"Flo's Attic Antiques",
    "wof:placetype":"venue"
},
  "geometry": {"coordinates":[-81.37266,28.593159],"type":"Point"}
}