{
  "type": "Feature",
  "properties": {
    "addr:full":"860 S State Rd 415 New Smyrna Beach FL 32168",
    "addr:housenumber":"860;415",
    "addr:postcode":"32168",
    "addr:street":"S State Rd",
    "iso:country":"US",
    "sg:address":"860 S State Rd 415",
    "sg:city":"New Smyrna Beach",
    "sg:classifiers":[
        {
            "category":"Building & Trades",
            "subcategory":"Construction",
            "type":"Services"
        }
    ],
    "sg:phone":"+1 386 322 4304",
    "sg:postcode":"32168",
    "sg:province":"FL",
    "sg:tags":[
        "demolition",
        "contractor"
    ],
    "wof:name":"Bobs Dozer & Backhoe Svc Inc",
    "wof:placetype":"venue"
},
  "geometry": {"coordinates":[-81.091638,28.958818],"type":"Point"}
}