{
  "type": "Feature",
  "properties": {
    "iso:country":"US",
    "sg:address":"403 NE 12th Ave",
    "sg:city":"Fort Lauderdale",
    "sg:classifiers":[
        {
            "category":"Professional",
            "subcategory":"Employment Agencies",
            "type":"Services"
        }
    ],
    "sg:phone":"+1 954 766 9857",
    "sg:postcode":"33301",
    "sg:province":"FL",
    "sg:tags":[
        "help",
        "supply"
    ],
    "wof:name":"Vogue Staffing Inc",
    "wof:placetype":"venue"
},
  "geometry": {"coordinates":[-80.13146399999999,26.128083],"type":"Point"}
}