{
  "type": "Feature",
  "properties": {
    "addr:full":"7930 SW 58th Ct Miami FL 33143",
    "addr:housenumber":"7930",
    "addr:postcode":"33143",
    "addr:street":"Sw 58Th Ct",
    "iso:country":"US",
    "sg:address":"7930 SW 58th Ct",
    "sg:city":"Miami",
    "sg:classifiers":[
        {
            "category":"Insurance",
            "subcategory":"Insurance Agent",
            "type":"Services"
        }
    ],
    "sg:phone":"+1 305 661 7316",
    "sg:postcode":"33143",
    "sg:province":"FL",
    "wof:name":"Susan P Redding",
    "wof:placetype":"venue"
},
  "geometry": {"coordinates":[-80.288331,25.698074],"type":"Point"}
}