{
  "type": "Feature",
  "properties": {
    "iso:country":"US",
    "sg:address":"121 Red Water Pt",
    "sg:city":"Lake Placid",
    "sg:classifiers":[
        {
            "category":"Retail",
            "subcategory":"Auto Repair",
            "type":"Services"
        }
    ],
    "sg:phone":"+1 863 699 2725",
    "sg:postcode":"33852",
    "sg:province":"FL",
    "sg:tags":[
        "transmission"
    ],
    "wof:name":"C P Competition Race Trans",
    "wof:placetype":"venue"
},
  "geometry": {"coordinates":[-81.392915,27.343373],"type":"Point"}
}