{
  "type": "Feature",
  "properties": {
    "iso:country":"US",
    "sg:address":"2909 Vistamar St",
    "sg:city":"Fort Lauderdale",
    "sg:classifiers":[
        {
            "category":"Travel",
            "subcategory":"Hotels & Motels",
            "type":"Entertainment"
        }
    ],
    "sg:phone":"+1 954 566 2491",
    "sg:postcode":"33304",
    "sg:province":"FL",
    "sg:tags":[
        "operation"
    ],
    "wof:name":"Sea Gate Motel Apartments",
    "wof:placetype":"venue"
},
  "geometry": {"coordinates":[-80.105996,26.133641],"type":"Point"}
}