{
  "type": "Feature",
  "properties": {
    "iso:country":"US",
    "sg:address":"3837 Northdale Blvd",
    "sg:city":"Tampa",
    "sg:classifiers":[
        {
            "category":"Wholesale",
            "subcategory":"Medical Equipment & Supplies",
            "type":"Manufacturing & Wholesale Goods"
        }
    ],
    "sg:phone":"+1 813 908 5302",
    "sg:postcode":"33624",
    "sg:province":"FL",
    "wof:name":"C V I Medical Liquidators",
    "wof:placetype":"venue"
},
  "geometry": {"coordinates":[-82.504892,28.093953],"type":"Point"}
}