{
  "type": "Feature",
  "properties": {
    "iso:country":"US",
    "sg:address":"4333 Gunn Hwy",
    "sg:city":"Tampa",
    "sg:classifiers":[
        {
            "category":"Arts & Performance",
            "subcategory":"Theater",
            "type":"Entertainment"
        }
    ],
    "sg:phone":"+1 813 265 4000",
    "sg:postcode":"33618",
    "sg:province":"FL",
    "sg:tags":[
        "theatrical"
    ],
    "wof:name":"Carrollwood Cmnty Playhouse",
    "wof:placetype":"venue"
},
  "geometry": {"coordinates":[-82.514298,28.044722],"type":"Point"}
}