{
  "type": "Feature",
  "properties": {
    "iso:country":"US",
    "sg:address":"3659 S Miami Ave",
    "sg:city":"Miami",
    "sg:classifiers":[
        {
            "category":"Health Services",
            "subcategory":"Podiatrist",
            "type":"Services"
        }
    ],
    "sg:phone":"+1 305 859 7777",
    "sg:postcode":"33133",
    "sg:province":"FL",
    "wof:name":"Barry University",
    "wof:placetype":"venue"
},
  "geometry": {"coordinates":[-80.216301,25.743299],"type":"Point"}
}