{
  "type": "Feature",
  "properties": {
    "iso:country":"US",
    "sg:address":"1201 State Hwy 17",
    "sg:city":"Avon Park",
    "sg:classifiers":[
        {
            "category":"Organizations",
            "subcategory":"Professional Association",
            "type":"Services"
        }
    ],
    "sg:phone":"+1 863 453 2100",
    "sg:postcode":"33825",
    "sg:province":"FL",
    "wof:name":"ARC-Ridge Area",
    "wof:placetype":"venue"
},
  "geometry": {"coordinates":[-81.48027,27.588373],"type":"Point"}
}