{
  "type": "Feature",
  "properties": {
    "iso:country":"US",
    "sg:address":"2009 1st Ave E",
    "sg:city":"Bradenton",
    "sg:classifiers":[
        {
            "category":"Professional",
            "type":"Services"
        }
    ],
    "sg:phone":"+1 941 745 1452",
    "sg:postcode":"34208",
    "sg:province":"FL",
    "wof:name":"David Cadena Inc",
    "wof:placetype":"venue"
},
  "geometry": {"coordinates":[-82.539098,27.499668],"type":"Point"}
}