{
  "type": "Feature",
  "properties": {
    "iso:country":"US",
    "sg:address":"3100 SW College Rd",
    "sg:city":"Ocala",
    "sg:classifiers":[
        {
            "category":"Shopping",
            "subcategory":"Clothing, Apparel, & Fashions",
            "type":"Retail Goods"
        }
    ],
    "sg:phone":"+1 352 237 8747",
    "sg:postcode":"34474",
    "sg:province":"FL",
    "wof:name":"Rainbow",
    "wof:placetype":"venue"
},
  "geometry": {"coordinates":[-82.176284,29.158949],"type":"Point"}
}