{
  "type": "Feature",
  "properties": {
    "iso:country":"US",
    "sg:address":"502 Capital Cir SE Ste C",
    "sg:city":"Tallahassee",
    "sg:classifiers":[
        {
            "category":"Real Estate",
            "subcategory":"Real Estate Services",
            "type":"Services"
        },
        {
            "category":"Real Estate",
            "subcategory":"Real Estate Agent",
            "type":"Services"
        }
    ],
    "sg:phone":"+1 850 656 4663",
    "sg:postcode":"32301",
    "sg:province":"FL",
    "sg:tags":[
        "management"
    ],
    "wof:name":"Capital Circle Commerce Center",
    "wof:placetype":"venue"
},
  "geometry": {"coordinates":[-84.22671099999999,30.43834],"type":"Point"}
}