{
  "type": "Feature",
  "properties": {
    "iso:country":"US",
    "sg:address":"5260 Hammock",
    "sg:city":"Saint Cloud",
    "sg:classifiers":[
        {
            "category":"Building & Trades",
            "subcategory":"Construction",
            "type":"Services"
        }
    ],
    "sg:phone":"+1 407 892 1524",
    "sg:postcode":"34771",
    "sg:province":"FL",
    "wof:name":"Paving Way By Patrick Chasteen",
    "wof:placetype":"venue"
},
  "geometry": {"coordinates":[-81.231388,28.33825],"type":"Point"}
}