{
  "type": "Feature",
  "properties": {
    "iso:country":"US",
    "sg:address":"256 NE 2nd St",
    "sg:city":"Miami",
    "sg:classifiers":[
        {
            "category":"Retail",
            "subcategory":"Car Wash",
            "type":"Services"
        }
    ],
    "sg:phone":"+1 786 288 6526",
    "sg:postcode":"33132",
    "sg:province":"FL",
    "wof:name":"The Car Wash People",
    "wof:placetype":"venue"
},
  "geometry": {"coordinates":[-80.189672,25.776203],"type":"Point"}
}