{
  "type": "Feature",
  "properties": {
    "iso:country":"US",
    "sg:address":"306 Alegriano Ct",
    "sg:city":"Kissimmee",
    "sg:classifiers":[
        {
            "category":"Retail",
            "subcategory":"Laundry & Dry Cleaning",
            "type":"Services"
        }
    ],
    "sg:phone":"+1 407 414 6486",
    "sg:postcode":"34758",
    "sg:province":"FL",
    "sg:tags":[
        "cleaners",
        "rug",
        "carpet"
    ],
    "wof:name":"Samuels Chemdry",
    "wof:placetype":"venue"
},
  "geometry": {"coordinates":[-81.474777,28.157938],"type":"Point"}
}