{
  "type": "Feature",
  "properties": {
    "addr:full":"2204 Parkview Dr Plant City FL 33563",
    "addr:housenumber":"2204",
    "addr:postcode":"33563",
    "addr:street":"Parkview Dr",
    "iso:country":"US",
    "sg:address":"2204 Parkview Dr",
    "sg:city":"Plant City",
    "sg:classifiers":[
        {
            "category":"Food & Beverages",
            "subcategory":"Groceries & Convenience Stores",
            "type":"Retail Goods"
        }
    ],
    "sg:phone":"+1 813 754 7628",
    "sg:postcode":"33563",
    "sg:province":"FL",
    "wof:name":"Shop-N-Gas Food Stores Inc",
    "wof:placetype":"venue"
},
  "geometry": {"coordinates":[-82.10039399999999,28.035713],"type":"Point"}
}