{
  "type": "Feature",
  "properties": {
    "iso:country":"US",
    "sg:address":"1212 N Ferdon Blvd",
    "sg:city":"Crestview",
    "sg:classifiers":[
        {
            "category":"Home & Garden",
            "subcategory":"Building Materials",
            "type":"Retail Goods"
        }
    ],
    "sg:phone":"+1 850 682 5155",
    "sg:postcode":"32536",
    "sg:province":"FL",
    "sg:tags":[
        "plumbing",
        "fixture",
        "supply"
    ],
    "wof:name":"Bogan Supply Co",
    "wof:placetype":"venue"
},
  "geometry": {"coordinates":[-86.5595,30.786079],"type":"Point"}
}