{
  "type": "Feature",
  "properties": {
    "iso:country":"US",
    "sg:address":"995 N State Rd 434",
    "sg:city":"Altamonte Springs",
    "sg:classifiers":[
        {
            "category":"Shopping",
            "subcategory":"Musical Instruments",
            "type":"Retail Goods"
        }
    ],
    "sg:phone":"+1 407 774 2667",
    "sg:postcode":"32714",
    "sg:province":"FL",
    "sg:tags":[
        "piano"
    ],
    "wof:name":"Bob & Elliotts Piano Shoppe",
    "wof:placetype":"venue"
},
  "geometry": {"coordinates":[-81.41895100000001,28.682706],"type":"Point"}
}