{
  "type": "Feature",
  "properties": {
    "addr:full":"1027 S Town and River Dr Fort Myers FL 33919",
    "addr:housenumber":"1027",
    "addr:postcode":"33919",
    "addr:street":"S Town And River Dr",
    "iso:country":"US",
    "sg:address":"1027 S Town and River Dr",
    "sg:city":"Fort Myers",
    "sg:classifiers":[
        {
            "category":"Recreation",
            "type":"Entertainment"
        }
    ],
    "sg:phone":"+1 239 433 9300",
    "sg:postcode":"33919",
    "sg:province":"FL",
    "sg:tags":[
        "instruction",
        "swimming"
    ],
    "wof:name":"Sara's Aquatic Fitness Instr",
    "wof:placetype":"venue"
},
  "geometry": {"coordinates":[-81.91970999999999,26.54233],"type":"Point"}
}