{
  "type": "Feature",
  "properties": {
    "iso:country":"US",
    "sg:address":"2173 SW Gemini Ln",
    "sg:city":"Port Saint Lucie",
    "sg:classifiers":[
        {
            "category":"Manufacturing",
            "subcategory":"Metals",
            "type":"Manufacturing & Wholesale Goods"
        }
    ],
    "sg:phone":"+1 772 873 4014",
    "sg:postcode":"34984",
    "sg:province":"FL",
    "sg:tags":[
        "cutlery",
        "mfg"
    ],
    "wof:name":"Caton Security & Recovery",
    "wof:placetype":"venue"
},
  "geometry": {"coordinates":[-80.346608,27.277749],"type":"Point"}
}