{
  "type": "Feature",
  "properties": {
    "addr:full":"7318 Alabama Ave Port Saint Joe FL 32456",
    "addr:housenumber":"7318",
    "addr:postcode":"32456",
    "addr:street":"Alabama Ave",
    "iso:country":"US",
    "sg:address":"7318 Alabama Ave",
    "sg:city":"Port Saint Joe",
    "sg:classifiers":[
        {
            "category":"Building & Trades",
            "subcategory":"Construction",
            "type":"Services"
        }
    ],
    "sg:phone":"+1 850 647 3497",
    "sg:postcode":"32456",
    "sg:province":"FL",
    "sg:tags":[
        "house"
    ],
    "wof:name":"A & P Builders Inc",
    "wof:placetype":"venue"
},
  "geometry": {"coordinates":[-85.363214,29.904751],"type":"Point"}
}