{
  "type": "Feature",
  "properties": {
    "iso:country":"US",
    "sg:address":"419 Ave M NE",
    "sg:city":"Winter Haven",
    "sg:classifiers":[
        {
            "category":"Building & Trades",
            "subcategory":"Construction",
            "type":"Services"
        }
    ],
    "sg:phone":"+1 863 294 7486",
    "sg:postcode":"33881",
    "sg:province":"FL",
    "sg:tags":[
        "concrete",
        "contractor"
    ],
    "wof:name":"Martin House Repair",
    "wof:placetype":"venue"
},
  "geometry": {"coordinates":[-81.721093,28.034737],"type":"Point"}
}