{
  "type": "Feature",
  "properties": {
    "addr:full":"3868 Garnet Dr Mulberry FL 33860",
    "addr:housenumber":"3868",
    "addr:postcode":"33860",
    "addr:street":"Garnet Dr",
    "iso:country":"US",
    "sg:address":"3868 Garnet Dr",
    "sg:city":"Mulberry",
    "sg:classifiers":[
        {
            "category":"Shopping",
            "subcategory":"Crafts & Fabrics",
            "type":"Retail Goods"
        }
    ],
    "sg:phone":"+1 863 425 5018",
    "sg:postcode":"33860",
    "sg:province":"FL",
    "sg:tags":[
        "sewing"
    ],
    "wof:name":"Julie Ann Mc Glamory",
    "wof:placetype":"venue"
},
  "geometry": {"coordinates":[-82.003815,27.923198],"type":"Point"}
}