{
  "type": "Feature",
  "properties": {
    "addr:full":"6605 N Florida Ave Tampa FL 33604",
    "addr:housenumber":"6605",
    "addr:postcode":"33604",
    "addr:street":"N Florida Ave",
    "iso:country":"US",
    "sg:address":"6605 N Florida Ave",
    "sg:city":"Tampa",
    "sg:classifiers":[
        {
            "category":"Shopping",
            "subcategory":"Used Merchandise",
            "type":"Retail Goods"
        }
    ],
    "sg:phone":"+1 813 231 2298",
    "sg:postcode":"33604",
    "sg:province":"FL",
    "sg:tags":[
        "antique"
    ],
    "wof:name":"Now & Again",
    "wof:placetype":"venue"
},
  "geometry": {"coordinates":[-82.45941000000001,28.007998],"type":"Point"}
}