{
  "type": "Feature",
  "properties": {
    "addr:full":"2145 Palm Ave Indialantic FL 32903",
    "addr:housenumber":"2145",
    "addr:postcode":"32903",
    "addr:street":"Palm Ave",
    "iso:country":"US",
    "sg:address":"2145 Palm Ave",
    "sg:city":"Indialantic",
    "sg:classifiers":[
        {
            "category":"Real Estate",
            "subcategory":"Real Estate Agent",
            "type":"Services"
        }
    ],
    "sg:phone":"+1 321 724 6571",
    "sg:postcode":"32903",
    "sg:province":"FL",
    "sg:tags":[
        "agency",
        "rental"
    ],
    "wof:name":"Thomas D Lee Space Coast Beach",
    "wof:placetype":"venue"
},
  "geometry": {"coordinates":[-80.574935,28.105005],"type":"Point"}
}