{
  "type": "Feature",
  "properties": {
    "addr:full":"801 Madrid St Coral Gables FL 33134",
    "addr:housenumber":"801",
    "addr:postcode":"33134",
    "addr:street":"Madrid St",
    "iso:country":"US",
    "sg:address":"801 Madrid St",
    "sg:city":"Coral Gables",
    "sg:classifiers":[
        {
            "category":"Health Services",
            "subcategory":"Clinic",
            "type":"Services"
        }
    ],
    "sg:phone":"+1 305 774 7314",
    "sg:postcode":"33134",
    "sg:province":"FL",
    "sg:tags":[
        "parapsychologist"
    ],
    "wof:name":"Systems Sueno Magico",
    "wof:placetype":"venue"
},
  "geometry": {"coordinates":[-80.28227,25.763023],"type":"Point"}
}