{
  "type": "Feature",
  "properties": {
    "iso:country":"US",
    "sg:address":"5706 W Flagler St",
    "sg:city":"Miami",
    "sg:classifiers":[
        {
            "category":"Restaurant",
            "type":"Food & Drink"
        }
    ],
    "sg:phone":"+1 305 266 0447",
    "sg:postcode":"33144",
    "sg:province":"FL",
    "wof:name":"Mi Cafetal",
    "wof:placetype":"venue"
},
  "geometry": {"coordinates":[-80.288903,25.770696],"type":"Point"}
}