{
  "type": "Feature",
  "properties": {
    "iso:country":"US",
    "sg:address":"492 Palm Ave",
    "sg:city":"Hialeah",
    "sg:classifiers":[
        {
            "category":"Professional",
            "type":"Services"
        }
    ],
    "sg:phone":"+1 305 882 5830",
    "sg:postcode":"33010",
    "sg:province":"FL",
    "sg:tags":[
        "establishment"
    ],
    "wof:name":"Agustin Mendoza",
    "wof:placetype":"venue"
},
  "geometry": {"coordinates":[-80.281503,25.825419],"type":"Point"}
}