{
  "type": "Feature",
  "properties": {
    "iso:country":"US",
    "sg:address":"7535 N Kendall Dr",
    "sg:city":"Miami",
    "sg:classifiers":[
        {
            "category":"Building & Trades",
            "subcategory":"Locksmith",
            "type":"Services"
        }
    ],
    "sg:phone":"+1 786 228 5403",
    "sg:postcode":"33156",
    "sg:province":"FL",
    "sg:tags":[
        "key"
    ],
    "wof:name":"Anytime Emergency Locksmith On N Kendall Dr",
    "wof:placetype":"venue"
},
  "geometry": {"coordinates":[-80.313451,25.688621],"type":"Point"}
}