{
  "type": "Feature",
  "properties": {
    "iso:country":"US",
    "sg:address":"14701 W Dixie Hwy",
    "sg:city":"North Miami",
    "sg:classifiers":[
        {
            "category":"Shopping",
            "subcategory":"Used Merchandise",
            "type":"Retail Goods"
        }
    ],
    "sg:phone":"+1 305 940 1188",
    "sg:postcode":"33181",
    "sg:province":"FL",
    "sg:tags":[
        "vintage",
        "consignment"
    ],
    "wof:name":"Salvation Army",
    "wof:placetype":"venue"
},
  "geometry": {"coordinates":[-80.167297,25.9112],"type":"Point"}
}