{
  "type": "Feature",
  "properties": {
    "addr:full":"5580 NW 84th Ave Doral FL 33166",
    "addr:housenumber":"5580",
    "addr:postcode":"33166",
    "addr:street":"Nw 84Th Ave",
    "iso:country":"US",
    "sg:address":"5580 NW 84th Ave",
    "sg:city":"Doral",
    "sg:classifiers":[
        {
            "category":"Real Estate",
            "subcategory":"Real Estate Agent",
            "type":"Services"
        }
    ],
    "sg:phone":"+1 305 470 9915",
    "sg:postcode":"33166",
    "sg:province":"FL",
    "wof:name":"Model Realty LLC",
    "wof:placetype":"venue"
},
  "geometry": {"coordinates":[-80.333794,25.82272],"type":"Point"}
}