{
  "type": "Feature",
  "properties": {
    "iso:country":"US",
    "sg:address":"1627 Brickell Ave # 2305",
    "sg:city":"Miami",
    "sg:classifiers":[
        {
            "category":"Professional",
            "subcategory":"Management & Consulting",
            "type":"Services"
        }
    ],
    "sg:phone":"+1 786 268 2916",
    "sg:postcode":"33129",
    "sg:province":"FL",
    "sg:tags":[
        "consultant"
    ],
    "wof:name":"Epyrus Consulting Grp",
    "wof:placetype":"venue"
},
  "geometry": {"coordinates":[-80.198125,25.754249],"type":"Point"}
}