{
  "type": "Feature",
  "properties": {
    "addr:full":"5395 NE 20th Ave Pompano Beach FL 33064",
    "addr:housenumber":"5395",
    "addr:postcode":"33064",
    "addr:street":"Ne 20Th Ave",
    "iso:country":"US",
    "sg:address":"5395 NE 20th Ave",
    "sg:city":"Pompano Beach",
    "sg:classifiers":[
        {
            "category":"Government",
            "subcategory":"Office",
            "type":"Public Place"
        }
    ],
    "sg:phone":"+1 954 971 7010",
    "sg:postcode":"33064",
    "sg:province":"FL",
    "sg:tags":[
        "legislative",
        "body"
    ],
    "wof:name":"Fire Department",
    "wof:placetype":"venue"
},
  "geometry": {"coordinates":[-80.09657900000001,26.295209],"type":"Point"}
}