{
  "type": "Feature",
  "properties": {
    "addr:full":"2919 Hickory St Bunnell FL 32110",
    "addr:housenumber":"2919",
    "addr:postcode":"32110",
    "addr:street":"Hickory St",
    "iso:country":"US",
    "sg:address":"2919 Hickory St",
    "sg:city":"Bunnell",
    "sg:classifiers":[
        {
            "category":"Freight",
            "type":"Transportation"
        }
    ],
    "sg:phone":"+1 386 437 0305",
    "sg:postcode":"32110",
    "sg:province":"FL",
    "sg:tags":[
        "operator",
        "local",
        "trucking"
    ],
    "wof:name":"Hlw Trucking Inc",
    "wof:placetype":"venue"
},
  "geometry": {"coordinates":[-81.388031,29.439997],"type":"Point"}
}