{
  "type": "Feature",
  "properties": {
    "addr:full":"4919 State Rd 54 New Port Richey FL 34652",
    "addr:housenumber":"4919;54",
    "addr:postcode":"34652",
    "addr:street":"State Rd",
    "iso:country":"US",
    "sg:address":"4919 State Rd 54",
    "sg:city":"New Port Richey",
    "sg:classifiers":[
        {
            "category":"Manufacturing",
            "subcategory":"Printing",
            "type":"Manufacturing & Wholesale Goods"
        }
    ],
    "sg:phone":"+1 727 743 4953",
    "sg:postcode":"34652",
    "sg:province":"FL",
    "sg:tags":[
        "commercial"
    ],
    "wof:name":"Community Advisor",
    "wof:placetype":"venue"
},
  "geometry": {"coordinates":[-82.732902,28.217014],"type":"Point"}
}