{
  "type": "Feature",
  "properties": {
    "addr:full":"7101 Wells Ave Gulf Breeze FL 32566",
    "addr:housenumber":"7101",
    "addr:postcode":"32566",
    "addr:street":"Wells Ave",
    "iso:country":"US",
    "sg:address":"7101 Wells Ave",
    "sg:city":"Gulf Breeze",
    "sg:classifiers":[
        {
            "category":"Real Estate",
            "subcategory":"Developer",
            "type":"Services"
        }
    ],
    "sg:phone":"+1 850 939 3925",
    "sg:postcode":"32566",
    "sg:province":"FL",
    "sg:tags":[
        "cemetery"
    ],
    "wof:name":"Clopton Cemetery Association",
    "wof:placetype":"venue"
},
  "geometry": {"coordinates":[-86.92512499999999,30.459839],"type":"Point"}
}