{
  "type": "Feature",
  "properties": {
    "iso:country":"US",
    "sg:address":"1626 Riggins Rd",
    "sg:city":"Tallahassee",
    "sg:classifiers":[
        {
            "category":"Health Services",
            "subcategory":"Doctor",
            "type":"Services"
        }
    ],
    "sg:phone":"+1 850 656 3653",
    "sg:postcode":"32308",
    "sg:province":"FL",
    "sg:tags":[
        "physician",
        "medical",
        "thoracic",
        "surgeons",
        "surgery",
        "cardiovascular"
    ],
    "wof:name":"Dalal, Jo Md Facc Fccp",
    "wof:placetype":"venue"
},
  "geometry": {"coordinates":[-84.23733900000001,30.458341],"type":"Point"}
}