{
  "type": "Feature",
  "properties": {
    "iso:country":"US",
    "sg:address":"1224 N Peacock Ave",
    "sg:city":"Perry",
    "sg:classifiers":[
        {
            "category":"Shopping",
            "type":"Retail Goods"
        }
    ],
    "sg:phone":"+1 850 584 8123",
    "sg:postcode":"32347",
    "sg:province":"FL",
    "sg:tags":[
        "merchandise"
    ],
    "wof:name":"Hamdan Ear Nose & Throat Ctr",
    "wof:placetype":"venue"
},
  "geometry": {"coordinates":[-83.57639500000001,30.119627],"type":"Point"}
}