{
  "type": "Feature",
  "properties": {
    "iso:country":"US",
    "sg:address":"8367 Bird Rd",
    "sg:city":"Miami",
    "sg:classifiers":[
        {
            "category":"Professional",
            "subcategory":"Lawyer & Legal Services",
            "type":"Services"
        }
    ],
    "sg:phone":"+1 305 226 4080",
    "sg:postcode":"33155",
    "sg:province":"FL",
    "wof:name":"Zoberg David H Atty",
    "wof:placetype":"venue"
},
  "geometry": {"coordinates":[-80.330803,25.7332],"type":"Point"}
}