{
  "type": "Feature",
  "properties": {
    "addr:full":"13490 Memorial Hwy Miami FL 33161",
    "addr:housenumber":"13490",
    "addr:postcode":"33161",
    "addr:street":"Memorial Hwy",
    "iso:country":"US",
    "sg:address":"13490 Memorial Hwy",
    "sg:city":"Miami",
    "sg:classifiers":[
        {
            "category":"Building & Trades",
            "subcategory":"Locksmith",
            "type":"Services"
        }
    ],
    "sg:phone":"+1 305 423 2617",
    "sg:postcode":"33161",
    "sg:province":"FL",
    "sg:tags":[
        "key"
    ],
    "wof:name":"1 Badass 24 Hour Locksmith",
    "wof:placetype":"venue"
},
  "geometry": {"coordinates":[-80.19430699999999,25.898946],"type":"Point"}
}