{
  "type": "Feature",
  "properties": {
    "addr:full":"20 Sovereign Way Fort Pierce FL 34949",
    "addr:housenumber":"20",
    "addr:postcode":"34949",
    "addr:street":"Sovereign Way",
    "iso:country":"US",
    "sg:address":"20 Sovereign Way",
    "sg:city":"Fort Pierce",
    "sg:classifiers":[
        {
            "category":"Professional",
            "subcategory":"Business Services",
            "type":"Services"
        }
    ],
    "sg:phone":"+1 772 467 0308",
    "sg:postcode":"34949",
    "sg:province":"FL",
    "wof:name":"Waterfront Group",
    "wof:placetype":"venue"
},
  "geometry": {"coordinates":[-80.31688200000001,27.514443],"type":"Point"}
}