{
  "type": "Feature",
  "properties": {
    "iso:country":"US",
    "sg:address":"5661 Pacific Blvd",
    "sg:city":"Boca Raton",
    "sg:classifiers":[
        {
            "category":"Wholesale",
            "subcategory":"Electrical",
            "type":"Manufacturing & Wholesale Goods"
        }
    ],
    "sg:phone":"+1 561 347 6206",
    "sg:postcode":"33433",
    "sg:province":"FL",
    "sg:tags":[
        "equipment",
        "industrial",
        "supply"
    ],
    "wof:name":"Wesco Distribution Inc",
    "wof:placetype":"venue"
},
  "geometry": {"coordinates":[-80.135051,26.338586],"type":"Point"}
}