{
  "type": "Feature",
  "properties": {
    "iso:country":"US",
    "sg:address":"7357 NW Miami Ct",
    "sg:city":"Miami Shores",
    "sg:classifiers":[
        {
            "category":"Building & Trades",
            "subcategory":"Construction",
            "type":"Services"
        }
    ],
    "sg:phone":"+1 305 757 2612",
    "sg:postcode":"33150",
    "sg:province":"FL",
    "sg:tags":[
        "roofing",
        "contractor"
    ],
    "wof:name":"Obenour Roofing Sheet Metal Co",
    "wof:placetype":"venue"
},
  "geometry": {"coordinates":[-80.197154,25.84292],"type":"Point"}
}