{
  "type": "Feature",
  "properties": {
    "iso:country":"US",
    "sg:address":"1200 S Pine Island Rd",
    "sg:city":"Fort Lauderdale",
    "sg:classifiers":[
        {
            "category":"Professional",
            "subcategory":"Lawyer & Legal Services",
            "type":"Services"
        }
    ],
    "sg:phone":"+1 954 473 4500",
    "sg:postcode":"33324",
    "sg:province":"FL",
    "sg:tags":[
        "attorney"
    ],
    "wof:name":"Barry E Witlin Pa",
    "wof:placetype":"venue"
},
  "geometry": {"coordinates":[-80.265137,26.103552],"type":"Point"}
}