{
  "type": "Feature",
  "properties": {
    "addr:full":"7240 W Commercial Blvd Fort Lauderdale FL 33319",
    "addr:housenumber":"7240",
    "addr:postcode":"33319",
    "addr:street":"W Commercial Blvd",
    "iso:country":"US",
    "sg:address":"7240 W Commercial Blvd",
    "sg:city":"Fort Lauderdale",
    "sg:classifiers":[
        {
            "category":"Restaurant",
            "type":"Food & Drink"
        }
    ],
    "sg:menulink":"http://www.allmenus.com/fl/plantation/45718-emilios-italian-restaurant/menu/",
    "sg:phone":"+1 954 598 0888",
    "sg:postcode":"33319",
    "sg:province":"FL",
    "sg:tags":[
        "italian"
    ],
    "wof:name":"Emilios Italian Restaurant",
    "wof:placetype":"venue"
},
  "geometry": {"coordinates":[-80.247257,26.193727],"type":"Point"}
}