{
  "type": "Feature",
  "properties": {
    "iso:country":"US",
    "sg:address":"2124 Sunnydale Blvd",
    "sg:city":"Clearwater",
    "sg:classifiers":[
        {
            "category":"Manufacturing",
            "subcategory":"Building Materials",
            "type":"Manufacturing & Wholesale Goods"
        }
    ],
    "sg:phone":"+1 727 442 6939",
    "sg:postcode":"33765",
    "sg:province":"FL",
    "sg:tags":[
        "cabinet"
    ],
    "wof:name":"Viking Cabinets",
    "wof:placetype":"venue"
},
  "geometry": {"coordinates":[-82.74955199999999,27.987141],"type":"Point"}
}