{
  "type": "Feature",
  "properties": {
    "iso:country":"US",
    "sg:address":"409 N Main St",
    "sg:city":"Trenton",
    "sg:classifiers":[
        {
            "category":"Shopping",
            "type":"Retail Goods"
        }
    ],
    "sg:phone":"+1 352 463 3841",
    "sg:postcode":"32693",
    "sg:province":"FL",
    "sg:tags":[
        "art",
        "gallery",
        "dealer"
    ],
    "wof:name":"Suwannee Valley Artisans",
    "wof:placetype":"venue"
},
  "geometry": {"coordinates":[-82.818404,29.61618],"type":"Point"}
}