{
  "type": "Feature",
  "properties": {
    "iso:country":"US",
    "sg:address":"8421 Arborfield Ct",
    "sg:city":"Fort Myers",
    "sg:classifiers":[
        {
            "category":"Real Estate",
            "subcategory":"Real Estate Agent",
            "type":"Services"
        }
    ],
    "sg:phone":"+1 239 225 1099",
    "sg:postcode":"33912",
    "sg:province":"FL",
    "wof:name":"Boscore",
    "wof:placetype":"venue"
},
  "geometry": {"coordinates":[-81.81637499999999,26.560996],"type":"Point"}
}