{
  "type": "Feature",
  "properties": {
    "iso:country":"US",
    "sg:address":"695 W 65th Dr",
    "sg:city":"Hialeah",
    "sg:phone":"+1 305 608 7167",
    "sg:postcode":"33012",
    "sg:province":"FL",
    "wof:name":"El Bodegon Espanol Inc",
    "wof:placetype":"venue"
},
  "geometry": {"coordinates":[-80.297059,25.883427],"type":"Point"}
}