{
  "type": "Feature",
  "properties": {
    "iso:country":"US",
    "sg:address":"7256 Exline Rd",
    "sg:city":"Jacksonville",
    "sg:classifiers":[
        {
            "category":"Professional",
            "subcategory":"Business Services",
            "type":"Services"
        }
    ],
    "sg:phone":"+1 904 573 2155",
    "sg:postcode":"32222",
    "sg:province":"FL",
    "wof:name":"A A & R Enterprises Inc",
    "wof:placetype":"venue"
},
  "geometry": {"coordinates":[-81.80645800000001,30.211918],"type":"Point"}
}