{
  "type": "Feature",
  "properties": {
    "iso:country":"US",
    "sg:address":"6313 Corporate Ct",
    "sg:city":"Fort Myers",
    "sg:classifiers":[
        {
            "category":"Professional",
            "type":"Services"
        }
    ],
    "sg:phone":"+1 239 415 2245",
    "sg:postcode":"33919",
    "sg:province":"FL",
    "sg:tags":[
        "establishment"
    ],
    "wof:name":"Wmi",
    "wof:placetype":"venue"
},
  "geometry": {"coordinates":[-81.887643,26.5584],"type":"Point"}
}