{
  "type": "Feature",
  "properties": {
    "iso:country":"US",
    "sg:address":"208 Beech St",
    "sg:city":"Fernandina Beach",
    "sg:classifiers":[
        {
            "category":"Wholesale",
            "subcategory":"Construction Materials",
            "type":"Manufacturing & Wholesale Goods"
        }
    ],
    "sg:phone":"+1 904 321 2335",
    "sg:postcode":"32034",
    "sg:province":"FL",
    "wof:name":"American System International",
    "wof:placetype":"venue"
},
  "geometry": {"coordinates":[-81.46426200000001,30.668714],"type":"Point"}
}