{
  "type": "Feature",
  "properties": {
    "iso:country":"US",
    "sg:address":"7996 Conroy Windermere Rd",
    "sg:city":"Orlando",
    "sg:classifiers":[
        {
            "category":"Shopping",
            "subcategory":"Pharmacy",
            "type":"Retail Goods"
        }
    ],
    "sg:phone":"+1 407 291 7170",
    "sg:postcode":"32835",
    "sg:province":"FL",
    "sg:tags":[
        "photofinishing",
        "laboratory"
    ],
    "wof:name":"CVS",
    "wof:placetype":"venue"
},
  "geometry": {"coordinates":[-81.490959,28.493599],"type":"Point"}
}