{
  "type": "Feature",
  "properties": {
    "iso:country":"US",
    "sg:address":"3850 NW 21st St",
    "sg:city":"Pompano Beach",
    "sg:classifiers":[
        {
            "category":"Wholesale",
            "subcategory":"Machinery & Supplies",
            "type":"Manufacturing & Wholesale Goods"
        }
    ],
    "sg:phone":"+1 561 301 8153",
    "sg:postcode":"33066",
    "sg:province":"FL",
    "sg:tags":[
        "industrial"
    ],
    "wof:name":"Scanice Trading",
    "wof:placetype":"venue"
},
  "geometry": {"coordinates":[-80.17507999999999,26.25415],"type":"Point"}
}