{
  "type": "Feature",
  "properties": {
    "iso:country":"US",
    "sg:address":"1241 Virginia Dr",
    "sg:city":"Orlando",
    "sg:classifiers":[
        {
            "category":"Retail",
            "subcategory":"Animal Services",
            "type":"Services"
        }
    ],
    "sg:phone":"+1 407 896 9336",
    "sg:postcode":"32803",
    "sg:province":"FL",
    "sg:tags":[
        "pet",
        "grooming",
        "washing"
    ],
    "wof:name":"Lucky Dog Pet Pro Inc",
    "wof:placetype":"venue"
},
  "geometry": {"coordinates":[-81.36265400000001,28.564115],"type":"Point"}
}