{
  "type": "Feature",
  "properties": {
    "addr:full":"928 W Brandon Blvd Brandon FL 33511",
    "addr:housenumber":"928",
    "addr:postcode":"33511",
    "addr:street":"W Brandon Blvd",
    "iso:country":"US",
    "sg:address":"928 W Brandon Blvd",
    "sg:city":"Brandon",
    "sg:classifiers":[
        {
            "category":"Professional",
            "subcategory":"Accounting & Tax Preparation",
            "type":"Services"
        }
    ],
    "sg:phone":"+1 813 643 4300",
    "sg:postcode":"33511",
    "sg:province":"FL",
    "sg:tags":[
        "return",
        "filing"
    ],
    "wof:name":"Jackson Hewitt Tax Svc",
    "wof:placetype":"venue"
},
  "geometry": {"coordinates":[-82.29816599999999,27.937839],"type":"Point"}
}