{
  "type": "Feature",
  "properties": {
    "iso:country":"US",
    "sg:address":"299 SW 8th St",
    "sg:city":"Miami",
    "sg:classifiers":[
        {
            "category":"Fast Food",
            "type":"Food & Drink"
        }
    ],
    "sg:phone":"+1 305 856 6770",
    "sg:postcode":"33130",
    "sg:province":"FL",
    "sg:website":"www.mcdonalds.com",
    "wof:name":"McDonald's",
    "wof:placetype":"venue"
},
  "geometry": {"coordinates":[-80.199119,25.766306],"type":"Point"}
}