{
  "type": "Feature",
  "properties": {
    "iso:country":"US",
    "sg:address":"801 Maplewood Dr",
    "sg:city":"Jupiter",
    "sg:classifiers":[
        {
            "category":"Banks & Credit Unions",
            "subcategory":"Bank",
            "type":"Services"
        }
    ],
    "sg:phone":"+1 561 747 7726",
    "sg:postcode":"33458",
    "sg:province":"FL",
    "sg:tags":[
        "loan",
        "real estate"
    ],
    "wof:name":"Freedom Mortgage & Loan",
    "wof:placetype":"venue"
},
  "geometry": {"coordinates":[-80.12342200000001,26.929251],"type":"Point"}
}