{
  "type": "Feature",
  "properties": {
    "iso:country":"US",
    "sg:address":"2015 Centre Pointe Blvd",
    "sg:city":"Tallahassee",
    "sg:classifiers":[
        {
            "category":"Banks & Credit Unions",
            "subcategory":"Bank",
            "type":"Services"
        }
    ],
    "sg:phone":"+1 850 878 5870",
    "sg:postcode":"32308",
    "sg:province":"FL",
    "sg:tags":[
        "loan",
        "real estate"
    ],
    "wof:name":"Belinda Dearing Mortgage",
    "wof:placetype":"venue"
},
  "geometry": {"coordinates":[-84.23813199999999,30.473025],"type":"Point"}
}