{
  "type": "Feature",
  "properties": {
    "iso:country":"US",
    "sg:address":"12210 SW 8th St",
    "sg:city":"Miami",
    "sg:classifiers":[
        {
            "category":"Retail",
            "subcategory":"Car Wash",
            "type":"Services"
        }
    ],
    "sg:phone":"+1 305 554 5514",
    "sg:postcode":"33184",
    "sg:province":"FL",
    "wof:name":"F & W Car Wash",
    "wof:placetype":"venue"
},
  "geometry": {"coordinates":[-80.392899,25.761],"type":"Point"}
}