{
  "type": "Feature",
  "properties": {
    "iso:country":"US",
    "sg:address":"1542 Kingsley Ave",
    "sg:city":"Orange Park",
    "sg:classifiers":[
        {
            "category":"Education",
            "subcategory":"School",
            "type":"Public Place"
        }
    ],
    "sg:phone":"+1 904 637 0637",
    "sg:postcode":"32073",
    "sg:province":"FL",
    "sg:tags":[
        "academic",
        "special"
    ],
    "wof:name":"Lighthouse Christian School",
    "wof:placetype":"venue"
},
  "geometry": {"coordinates":[-81.73012799999999,30.164368],"type":"Point"}
}