{
  "type": "Feature",
  "properties": {
    "iso:country":"US",
    "sg:address":"631 Thousand Oaks Blvd",
    "sg:city":"Davenport",
    "sg:classifiers":[
        {
            "category":"Retail",
            "subcategory":"Self-service Laundry",
            "type":"Services"
        }
    ],
    "sg:phone":"+1 863 424 7143",
    "sg:postcode":"33896",
    "sg:province":"FL",
    "sg:tags":[
        "coin"
    ],
    "wof:name":"David P Hamper",
    "wof:placetype":"venue"
},
  "geometry": {"coordinates":[-81.572086,28.24768],"type":"Point"}
}