{
  "type": "Feature",
  "properties": {
    "addr:full":"5769 NW 69th Way Parkland FL 33067",
    "addr:housenumber":"5769",
    "addr:postcode":"33067",
    "addr:street":"Nw 69Th Way",
    "iso:country":"US",
    "sg:address":"5769 NW 69th Way",
    "sg:city":"Parkland",
    "sg:classifiers":[
        {
            "category":"Building & Trades",
            "subcategory":"Plumbing",
            "type":"Services"
        }
    ],
    "sg:phone":"+1 954 491 2466",
    "sg:postcode":"33067",
    "sg:province":"FL",
    "sg:tags":[
        "conditioning",
        "air",
        "system",
        "contractor"
    ],
    "wof:name":"Automatic Control Air Cond",
    "wof:placetype":"venue"
},
  "geometry": {"coordinates":[-80.219463,26.309686],"type":"Point"}
}