{
  "type": "Feature",
  "properties": {
    "addr:full":"2669 NW 79th Ave Doral FL 33122",
    "addr:housenumber":"2669",
    "addr:postcode":"33122",
    "addr:street":"Nw 79Th Ave",
    "iso:country":"US",
    "sg:address":"2669 NW 79th Ave",
    "sg:city":"Doral",
    "sg:classifiers":[
        {
            "category":"Bars & Pubs",
            "type":"Food & Drink"
        },
        {
            "category":"Restaurant",
            "type":"Food & Drink"
        },
        {
            "category":"Bars & Pubs",
            "subcategory":"Lounge",
            "type":"Food & Drink"
        }
    ],
    "sg:phone":"+1 305 599 6362",
    "sg:postcode":"33122",
    "sg:province":"FL",
    "sg:tags":[
        "seafood",
        "sushi",
        "japanese",
        "cocktail"
    ],
    "wof:name":"Kamiko Sushi Bar",
    "wof:placetype":"venue"
},
  "geometry": {"coordinates":[-80.324989,25.797025],"type":"Point"}
}