{
  "type": "Feature",
  "properties": {
    "iso:country":"US",
    "sg:address":"244 9th St",
    "sg:city":"Daytona Beach",
    "sg:classifiers":[
        {
            "category":"Personal",
            "subcategory":"Beauty Salon",
            "type":"Services"
        }
    ],
    "sg:phone":"+1 386 947 8345",
    "sg:postcode":"32117",
    "sg:province":"FL",
    "wof:name":"Fabulous Creations",
    "wof:placetype":"venue"
},
  "geometry": {"coordinates":[-81.038139,29.241344],"type":"Point"}
}