{
  "type": "Feature",
  "properties": {
    "iso:country":"US",
    "sg:address":"517 Trenton St",
    "sg:city":"Fort Walton Beach",
    "sg:classifiers":[
        {
            "category":"Building & Trades",
            "subcategory":"Construction",
            "type":"Services"
        }
    ],
    "sg:phone":"+1 850 862 4109",
    "sg:postcode":"32547",
    "sg:province":"FL",
    "sg:tags":[
        "hanging",
        "contractor"
    ],
    "wof:name":"Tom Knight",
    "wof:placetype":"venue"
},
  "geometry": {"coordinates":[-86.60848900000001,30.441109],"type":"Point"}
}