{
  "type": "Feature",
  "properties": {
    "iso:country":"US",
    "sg:address":"1546 SW 27th Ave",
    "sg:city":"Miami",
    "sg:classifiers":[
        {
            "category":"Food & Beverages",
            "subcategory":"Groceries & Convenience Stores",
            "type":"Retail Goods"
        }
    ],
    "sg:phone":"+1 305 442 2574",
    "sg:postcode":"33145",
    "sg:province":"FL",
    "wof:name":"Kwik Stop",
    "wof:placetype":"venue"
},
  "geometry": {"coordinates":[-80.23870100000001,25.758101],"type":"Point"}
}