{
  "type": "Feature",
  "properties": {
    "iso:country":"US",
    "sg:address":"803 Malaga Ave",
    "sg:city":"Miami",
    "sg:classifiers":[
        {
            "category":"Real Estate",
            "subcategory":"Real Estate Agent",
            "type":"Services"
        }
    ],
    "sg:phone":"+1 305 443 9329",
    "sg:postcode":"33134",
    "sg:province":"FL",
    "wof:name":"Euro Keys Corp",
    "wof:placetype":"venue"
},
  "geometry": {"coordinates":[-80.27264099999999,25.742646],"type":"Point"}
}