{
  "type": "Feature",
  "properties": {
    "addr:full":"4160 Cleveland Ave Fort Myers FL 33901",
    "addr:housenumber":"4160",
    "addr:postcode":"33901",
    "addr:street":"Cleveland Ave",
    "iso:country":"US",
    "sg:address":"4160 Cleveland Ave",
    "sg:city":"Fort Myers",
    "sg:classifiers":[
        {
            "category":"Food & Beverages",
            "subcategory":"Groceries & Convenience Stores",
            "type":"Retail Goods"
        }
    ],
    "sg:phone":"+1 239 278 3500",
    "sg:postcode":"33901",
    "sg:province":"FL",
    "wof:name":"Young Asian Market",
    "wof:placetype":"venue"
},
  "geometry": {"coordinates":[-81.871961,26.601848],"type":"Point"}
}