{
  "type": "Feature",
  "properties": {
    "addr:full":"1046 SW 5th St Miami FL 33130",
    "addr:housenumber":"1046",
    "addr:postcode":"33130",
    "addr:street":"Sw 5Th St",
    "iso:country":"US",
    "sg:address":"1046 SW 5th St",
    "sg:city":"Miami",
    "sg:classifiers":[
        {
            "category":"Shopping",
            "subcategory":"Optical Goods",
            "type":"Retail Goods"
        }
    ],
    "sg:phone":"+1 305 643 1028",
    "sg:postcode":"33130",
    "sg:province":"FL",
    "sg:tags":[
        "optician"
    ],
    "wof:name":"Optica Futura Opticians",
    "wof:placetype":"venue"
},
  "geometry": {"coordinates":[-80.21219000000001,25.768676],"type":"Point"}
}