{
  "type": "Feature",
  "properties": {
    "addr:full":"4771 NE 6th St Ocala FL 34470",
    "addr:housenumber":"4771",
    "addr:postcode":"34470",
    "addr:street":"Ne 6Th St",
    "iso:country":"US",
    "sg:address":"4771 NE 6th St",
    "sg:city":"Ocala",
    "sg:classifiers":[
        {
            "category":"Building & Trades",
            "subcategory":"Plumbing",
            "type":"Services"
        }
    ],
    "sg:phone":"+1 352 622 8250",
    "sg:postcode":"34470",
    "sg:province":"FL",
    "sg:tags":[
        "conditioning",
        "air",
        "system",
        "contractor"
    ],
    "wof:name":"Southeastern Refrigeration",
    "wof:placetype":"venue"
},
  "geometry": {"coordinates":[-82.06934800000001,29.192706],"type":"Point"}
}