{
  "type": "Feature",
  "properties": {
    "addr:full":"302 Lockhart St Daytona Beach FL 32114",
    "addr:housenumber":"302",
    "addr:postcode":"32114",
    "addr:street":"Lockhart St",
    "iso:country":"US",
    "sg:address":"302 Lockhart St",
    "sg:city":"Daytona Beach",
    "sg:classifiers":[
        {
            "category":"Building & Trades",
            "subcategory":"Construction",
            "type":"Services"
        }
    ],
    "sg:phone":"+1 386 253 8161",
    "sg:postcode":"32114",
    "sg:province":"FL",
    "sg:tags":[
        "fence",
        "contractor"
    ],
    "wof:name":"Fence Services Inc",
    "wof:placetype":"venue"
},
  "geometry": {"coordinates":[-81.030446,29.202171],"type":"Point"}
}