{
  "type": "Feature",
  "properties": {
    "iso:country":"US",
    "sg:address":"9146 Glades Rd",
    "sg:city":"Boca Raton",
    "sg:classifiers":[
        {
            "category":"Shopping",
            "subcategory":"Clothing, Apparel, & Fashions",
            "type":"Retail Goods"
        }
    ],
    "sg:phone":"+1 561 488 5532",
    "sg:postcode":"33434",
    "sg:province":"FL",
    "sg:tags":[
        "tailor"
    ],
    "wof:name":"Christina's Alterations",
    "wof:placetype":"venue"
},
  "geometry": {"coordinates":[-80.18823500000001,26.367819],"type":"Point"}
}