{
  "type": "Feature",
  "properties": {
    "iso:country":"US",
    "sg:address":"1116 Lancaster Dr",
    "sg:city":"Orlando",
    "sg:classifiers":[
        {
            "category":"Professional",
            "subcategory":"Accounting & Tax Preparation",
            "type":"Services"
        }
    ],
    "sg:phone":"+1 407 895 1941",
    "sg:postcode":"32806",
    "sg:province":"FL",
    "sg:tags":[
        "bookkeeping"
    ],
    "wof:name":"J Calder Inc",
    "wof:placetype":"venue"
},
  "geometry": {"coordinates":[-81.365039,28.525752],"type":"Point"}
}