{
  "type": "Feature",
  "properties": {
    "iso:country":"US",
    "sg:address":"727 W Smith St",
    "sg:city":"Orlando",
    "sg:classifiers":[
        {
            "category":"Wholesale",
            "subcategory":"Home Furnishings",
            "type":"Manufacturing & Wholesale Goods"
        }
    ],
    "sg:phone":"+1 407 650 0680",
    "sg:postcode":"32804",
    "sg:province":"FL",
    "sg:tags":[
        "curtain",
        "drapery"
    ],
    "wof:name":"Pamela Jean's Designers Wkshp",
    "wof:placetype":"venue"
},
  "geometry": {"coordinates":[-81.39326199999999,28.572085],"type":"Point"}
}