{
  "type": "Feature",
  "properties": {
    "addr:full":"1140 71st St Miami Beach FL 33141",
    "addr:housenumber":"1140",
    "addr:postcode":"33141",
    "addr:street":"71St St",
    "iso:country":"US",
    "sg:address":"1140 71st St",
    "sg:city":"Miami Beach",
    "sg:classifiers":[
        {
            "category":"Manufacturing",
            "subcategory":"Printing",
            "type":"Manufacturing & Wholesale Goods"
        }
    ],
    "sg:phone":"+1 305 866 9091",
    "sg:postcode":"33141",
    "sg:province":"FL",
    "wof:name":"Print Shop",
    "wof:placetype":"venue"
},
  "geometry": {"coordinates":[-80.130358,25.854708],"type":"Point"}
}