{
  "type": "Feature",
  "properties": {
    "iso:country":"US",
    "sg:address":"6299 Powers Ave",
    "sg:city":"Jacksonville",
    "sg:classifiers":[
        {
            "category":"Manufacturing",
            "subcategory":"Metals",
            "type":"Manufacturing & Wholesale Goods"
        }
    ],
    "sg:phone":"+1 904 731 3460",
    "sg:postcode":"32217",
    "sg:province":"FL",
    "sg:tags":[
        "steel"
    ],
    "wof:name":"Sherman's Welding & Mntnc Inc",
    "wof:placetype":"venue"
},
  "geometry": {"coordinates":[-81.617503,30.256854],"type":"Point"}
}