{
  "type": "Feature",
  "properties": {
    "addr:full":"734 S Federal Hwy Deerfield Beach FL 33443",
    "addr:housenumber":"734",
    "addr:postcode":"33443",
    "addr:street":"S Federal Hwy",
    "iso:country":"US",
    "sg:address":"734 S Federal Hwy",
    "sg:city":"Deerfield Beach",
    "sg:classifiers":[
        {
            "category":"Shopping",
            "type":"Retail Goods"
        }
    ],
    "sg:phone":"+1 954 418 6448",
    "sg:postcode":"33443",
    "sg:province":"FL",
    "sg:tags":[
        "aquarium"
    ],
    "wof:name":"A World Of Tropical Fish",
    "wof:placetype":"venue"
},
  "geometry": {"coordinates":[-80.092573,26.306905],"type":"Point"}
}