{
  "type": "Feature",
  "properties": {
    "iso:country":"US",
    "sg:address":"18541 River Estates Ln",
    "sg:city":"Alva",
    "sg:classifiers":[
        {
            "category":"Professional",
            "subcategory":"Detective & Security Services",
            "type":"Services"
        }
    ],
    "sg:phone":"+1 239 693 9342",
    "sg:postcode":"33920",
    "sg:province":"FL",
    "sg:tags":[
        "information",
        "bureau"
    ],
    "wof:name":"Sparkys Outboard Mobile Service",
    "wof:placetype":"venue"
},
  "geometry": {"coordinates":[-81.68319,26.733352],"type":"Point"}
}