{
  "type": "Feature",
  "properties": {
    "iso:country":"US",
    "sg:address":"1216 NE 93rd St",
    "sg:city":"Miami",
    "sg:classifiers":[
        {
            "category":"Wholesale",
            "subcategory":"Non-durable Goods",
            "type":"Manufacturing & Wholesale Goods"
        }
    ],
    "sg:phone":"+1 305 751 2253",
    "sg:postcode":"33138",
    "sg:province":"FL",
    "wof:name":"Aussie Trading LLC",
    "wof:placetype":"venue"
},
  "geometry": {"coordinates":[-80.172273,25.861287],"type":"Point"}
}