{
  "type": "Feature",
  "properties": {
    "addr:full":"3000 Nautilus Rd Middleburg FL 32068",
    "addr:housenumber":"3000",
    "addr:postcode":"32068",
    "addr:street":"Nautilus Rd",
    "iso:country":"US",
    "sg:address":"3000 Nautilus Rd",
    "sg:city":"Middleburg",
    "sg:classifiers":[
        {
            "category":"Building & Trades",
            "subcategory":"Construction",
            "type":"Services"
        }
    ],
    "sg:phone":"+1 904 269 6585",
    "sg:postcode":"32068",
    "sg:province":"FL",
    "sg:tags":[
        "concrete",
        "contractor"
    ],
    "wof:name":"Angela C Roberson Concrete",
    "wof:placetype":"venue"
},
  "geometry": {"coordinates":[-81.76008,30.10277],"type":"Point"}
}