{
  "type": "Feature",
  "properties": {
    "iso:country":"US",
    "sg:address":"20372 E Pennsylvania Ave",
    "sg:city":"Dunnellon",
    "sg:classifiers":[
        {
            "category":"Building & Trades",
            "subcategory":"Construction",
            "type":"Services"
        }
    ],
    "sg:phone":"+1 352 465 1092",
    "sg:postcode":"34432",
    "sg:province":"FL",
    "sg:tags":[
        "contractor"
    ],
    "wof:name":"Florida Builders Direct",
    "wof:placetype":"venue"
},
  "geometry": {"coordinates":[-82.459138,29.049408],"type":"Point"}
}