{
  "type": "Feature",
  "properties": {
    "iso:country":"US",
    "sg:address":"1609 W Brandon Blvd",
    "sg:city":"Brandon",
    "sg:classifiers":[
        {
            "category":"Food & Beverages",
            "subcategory":"Groceries & Convenience Stores",
            "type":"Retail Goods"
        }
    ],
    "sg:phone":"+1 813 657 1664",
    "sg:postcode":"33511",
    "sg:province":"FL",
    "wof:name":"Showcase Gallery",
    "wof:placetype":"venue"
},
  "geometry": {"coordinates":[-82.31017799999999,27.937681],"type":"Point"}
}