{
  "type": "Feature",
  "properties": {
    "iso:country":"US",
    "sg:address":"2451 NW 109th Ave Unit 2",
    "sg:city":"Miami",
    "sg:classifiers":[
        {
            "category":"Building & Trades",
            "subcategory":"Construction",
            "type":"Services"
        }
    ],
    "sg:phone":"+1 305 592 6353",
    "sg:postcode":"33172",
    "sg:province":"FL",
    "sg:tags":[
        "contractor"
    ],
    "wof:name":"Quality Construction Performance Inc",
    "wof:placetype":"venue"
},
  "geometry": {"coordinates":[-80.371663,25.746314],"type":"Point"}
}