{
  "type": "Feature",
  "properties": {
    "iso:country":"US",
    "sg:address":"1 Harbourside Dr",
    "sg:city":"Delray Beach",
    "sg:classifiers":[
        {
            "category":"Organizations",
            "subcategory":"Community Association",
            "type":"Services"
        }
    ],
    "sg:phone":"+1 561 278 7088",
    "sg:postcode":"33483",
    "sg:province":"FL",
    "wof:name":"Harbourside Condominium Assn",
    "wof:placetype":"venue"
},
  "geometry": {"coordinates":[-80.067143,26.443534],"type":"Point"}
}