{
  "type": "Feature",
  "properties": {
    "iso:country":"US",
    "sg:address":"11420 US Hwy 19",
    "sg:city":"Port Richey",
    "sg:classifiers":[
        {
            "category":"Social Services",
            "subcategory":"Child Care",
            "type":"Services"
        }
    ],
    "sg:phone":"+1 727 868 5526",
    "sg:postcode":"34668",
    "sg:province":"FL",
    "sg:tags":[
        "day"
    ],
    "wof:name":"Kiddie Crossroads",
    "wof:placetype":"venue"
},
  "geometry": {"coordinates":[-82.69923199999999,28.322662],"type":"Point"}
}