{
  "type": "Feature",
  "properties": {
    "iso:country":"US",
    "sg:address":"503 5th Ave",
    "sg:city":"Indialantic",
    "sg:classifiers":[
        {
            "category":"Wholesale",
            "subcategory":"Electrical",
            "type":"Manufacturing & Wholesale Goods"
        }
    ],
    "sg:phone":"+1 321 725 7550",
    "sg:postcode":"32903",
    "sg:province":"FL",
    "sg:tags":[
        "alarm",
        "burglar",
        "system"
    ],
    "wof:name":"Innovative Security Systems",
    "wof:placetype":"venue"
},
  "geometry": {"coordinates":[-80.57579200000001,28.088914],"type":"Point"}
}