{
  "type": "Feature",
  "properties": {
    "addr:full":"7060 Thistlebrook Ln Brooksville FL 34602",
    "addr:postcode":"7060;34602",
    "addr:street":"Thistlebrook Ln",
    "iso:country":"US",
    "sg:address":"7060 Thistlebrook Ln",
    "sg:city":"Brooksville",
    "sg:classifiers":[
        {
            "category":"Building & Trades",
            "subcategory":"Plumbing",
            "type":"Services"
        },
        {
            "category":"Building & Trades",
            "subcategory":"Construction",
            "type":"Services"
        }
    ],
    "sg:phone":"+1 352 799 1277",
    "sg:postcode":"34602",
    "sg:province":"FL",
    "sg:tags":[
        "plumber",
        "industrial",
        "contractors-commercial",
        "contractor"
    ],
    "wof:name":"Wolf Contracting Inc",
    "wof:placetype":"venue"
},
  "geometry": {"coordinates":[-82.263426,28.530012],"type":"Point"}
}