{
  "type": "Feature",
  "properties": {
    "addr:full":"612 N Ridgewood Ave Daytona Beach FL 32114",
    "addr:housenumber":"612",
    "addr:postcode":"32114",
    "addr:street":"N Ridgewood Ave",
    "iso:country":"US",
    "sg:address":"612 N Ridgewood Ave",
    "sg:city":"Daytona Beach",
    "sg:classifiers":[
        {
            "category":"Manufacturing",
            "subcategory":"Signs",
            "type":"Manufacturing & Wholesale Goods"
        }
    ],
    "sg:phone":"+1 386 258 8300",
    "sg:postcode":"32114",
    "sg:province":"FL",
    "sg:tags":[
        "specialty",
        "mfg"
    ],
    "wof:name":"Super Sign",
    "wof:placetype":"venue"
},
  "geometry": {"coordinates":[-81.029093,29.222452],"type":"Point"}
}