{
  "type": "Feature",
  "properties": {
    "addr:full":"205 Centre St Fernandina Beach FL 32034",
    "addr:housenumber":"205",
    "addr:postcode":"32034",
    "addr:street":"Centre St",
    "iso:country":"US",
    "sg:address":"205 Centre St",
    "sg:city":"Fernandina Beach",
    "sg:classifiers":[
        {
            "category":"Professional",
            "type":"Services"
        }
    ],
    "sg:phone":"+1 904 261 3665",
    "sg:postcode":"32034",
    "sg:province":"FL",
    "wof:name":"Studio",
    "wof:placetype":"venue"
},
  "geometry": {"coordinates":[-81.463848,30.671381],"type":"Point"}
}