{
  "type": "Feature",
  "properties": {
    "iso:country":"US",
    "sg:address":"301 W Platt St 404",
    "sg:city":"Tampa",
    "sg:classifiers":[
        {
            "category":"Real Estate",
            "subcategory":"Real Estate Services",
            "type":"Services"
        },
        {
            "category":"Real Estate",
            "subcategory":"Real Estate Agent",
            "type":"Services"
        }
    ],
    "sg:phone":"+1 813 943 2209",
    "sg:postcode":"33606",
    "sg:province":"FL",
    "sg:tags":[
        "buyer",
        "broker"
    ],
    "wof:name":"Rentals First",
    "wof:placetype":"venue"
},
  "geometry": {"coordinates":[-82.462799,27.941681],"type":"Point"}
}