{
  "type": "Feature",
  "properties": {
    "iso:country":"US",
    "sg:address":"1920 4th St N",
    "sg:city":"St Petersburg",
    "sg:classifiers":[
        {
            "category":"Recreation",
            "type":"Entertainment"
        },
        {
            "category":"Sports & Exercise",
            "subcategory":"Gym",
            "type":"Entertainment"
        }
    ],
    "sg:phone":"+1 727 822 4722",
    "sg:postcode":"33704",
    "sg:province":"FL",
    "sg:tags":[
        "club",
        "instruction",
        "gymnasium",
        "health",
        "fitness",
        "studio",
        "physical"
    ],
    "wof:name":"Pilates Premier Studios Inc",
    "wof:placetype":"venue"
},
  "geometry": {"coordinates":[-82.638638,27.790272],"type":"Point"}
}