{
  "type": "Feature",
  "properties": {
    "iso:country":"US",
    "sg:address":"1610 E Hallandale Beach Blvd",
    "sg:city":"Hallandale Beach",
    "sg:classifiers":[
        {
            "category":"Retail",
            "subcategory":"Laundry & Dry Cleaning",
            "type":"Services"
        }
    ],
    "sg:phone":"+1 954 454 8484",
    "sg:postcode":"33009",
    "sg:province":"FL",
    "sg:tags":[
        "cleaners",
        "tailoring",
        "drop",
        "store"
    ],
    "wof:name":"Crystal Cleaners",
    "wof:placetype":"venue"
},
  "geometry": {"coordinates":[-80.129227,25.986016],"type":"Point"}
}