{
  "type": "Feature",
  "properties": {
    "addr:full":"5219 W Colonial Dr Orlando FL 32808",
    "addr:housenumber":"5219",
    "addr:postcode":"32808",
    "addr:street":"W Colonial Dr",
    "iso:country":"US",
    "sg:address":"5219 W Colonial Dr",
    "sg:city":"Orlando",
    "sg:classifiers":[
        {
            "category":"Shopping",
            "type":"Retail Goods"
        }
    ],
    "sg:phone":"+1 407 578 3883",
    "sg:postcode":"32808",
    "sg:province":"FL",
    "sg:tags":[
        "cosmetic",
        "perfume"
    ],
    "wof:name":"Excellent Beauty Supls & Hair",
    "wof:placetype":"venue"
},
  "geometry": {"coordinates":[-81.45189000000001,28.552529],"type":"Point"}
}