{
  "type": "Feature",
  "properties": {
    "iso:country":"US",
    "sg:address":"10267 158th St N",
    "sg:city":"Jupiter",
    "sg:classifiers":[
        {
            "category":"Building & Trades",
            "subcategory":"Construction",
            "type":"Services"
        }
    ],
    "sg:phone":"+1 561 747 9233",
    "sg:postcode":"33478",
    "sg:province":"FL",
    "sg:tags":[
        "concrete",
        "contractor"
    ],
    "wof:name":"Catalina Concrete",
    "wof:placetype":"venue"
},
  "geometry": {"coordinates":[-80.195696,26.910078],"type":"Point"}
}