{
  "type": "Feature",
  "properties": {
    "iso:country":"US",
    "sg:address":"425 N Orange Ave",
    "sg:city":"Orlando",
    "sg:classifiers":[
        {
            "category":"Government",
            "subcategory":"Court House",
            "type":"Public Place"
        }
    ],
    "sg:phone":"+1 407 836 2350",
    "sg:postcode":"32801",
    "sg:province":"FL",
    "sg:tags":[
        "justice"
    ],
    "sg:website":"http://www.duvalclerk.com",
    "wof:name":"Judge Mihok Chambers",
    "wof:placetype":"venue"
},
  "geometry": {"coordinates":[-81.379108,28.548057],"type":"Point"}
}