{
  "type": "Feature",
  "properties": {
    "addr:full":"14657 SW 96th Ter Miami FL 33186",
    "addr:housenumber":"14657",
    "addr:postcode":"33186",
    "addr:street":"Sw 96Th Ter",
    "iso:country":"US",
    "sg:address":"14657 SW 96th Ter",
    "sg:city":"Miami",
    "sg:classifiers":[
        {
            "category":"Retail",
            "subcategory":"Auto Repair",
            "type":"Services"
        }
    ],
    "sg:phone":"+1 305 388 7176",
    "sg:postcode":"33186",
    "sg:province":"FL",
    "sg:tags":[
        "general"
    ],
    "wof:name":"Supreme Foreign Auto Inc",
    "wof:placetype":"venue"
},
  "geometry": {"coordinates":[-80.42724800000001,25.677112],"type":"Point"}
}