{
  "type": "Feature",
  "properties": {
    "iso:country":"US",
    "sg:address":"21541 SW 94th Ave",
    "sg:city":"Miami",
    "sg:classifiers":[
        {
            "category":"Banks & Credit Unions",
            "subcategory":"Financial Services",
            "type":"Services"
        }
    ],
    "sg:phone":"+1 305 235 4927",
    "sg:postcode":"33189",
    "sg:province":"FL",
    "sg:tags":[
        "trust",
        "investment",
        "real estate"
    ],
    "wof:name":"Cheeburger Cheeburger",
    "wof:placetype":"venue"
},
  "geometry": {"coordinates":[-80.344207,25.567148],"type":"Point"}
}