{
  "type": "Feature",
  "properties": {
    "iso:country":"US",
    "sg:address":"3716 Summer Wind Dr",
    "sg:city":"Winter Park",
    "sg:classifiers":[
        {
            "category":"Professional",
            "type":"Services"
        }
    ],
    "sg:phone":"+1 407 671 5167",
    "sg:postcode":"32792",
    "sg:province":"FL",
    "wof:name":"Murderboys",
    "wof:placetype":"venue"
},
  "geometry": {"coordinates":[-81.307609,28.582879],"type":"Point"}
}