{
  "type": "Feature",
  "properties": {
    "addr:full":"14849 Hormuth St Dade City FL 33525",
    "addr:housenumber":"14849",
    "addr:postcode":"33525",
    "addr:street":"Hormuth St",
    "iso:country":"US",
    "sg:address":"14849 Hormuth St",
    "sg:city":"Dade City",
    "sg:classifiers":[
        {
            "category":"Professional",
            "type":"Services"
        }
    ],
    "sg:phone":"+1 352 567 9744",
    "sg:postcode":"33525",
    "sg:province":"FL",
    "wof:name":"Linda West Home Care Svc",
    "wof:placetype":"venue"
},
  "geometry": {"coordinates":[-82.186481,28.373569],"type":"Point"}
}