{
  "type": "Feature",
  "properties": {
    "iso:country":"US",
    "sg:address":"13821 Folkstone Cir",
    "sg:city":"Wellington",
    "sg:classifiers":[
        {
            "category":"Professional",
            "subcategory":"Engineering",
            "type":"Services"
        }
    ],
    "sg:phone":"+1 561 798 7750",
    "sg:postcode":"33414",
    "sg:province":"FL",
    "sg:tags":[
        "engineer"
    ],
    "wof:name":"Hustad Structural Engineering",
    "wof:placetype":"venue"
},
  "geometry": {"coordinates":[-80.267967,26.647232],"type":"Point"}
}