{
  "type": "Feature",
  "properties": {
    "iso:country":"US",
    "sg:address":"434 W Pipkin Rd",
    "sg:city":"Lakeland",
    "sg:classifiers":[
        {
            "category":"Food & Beverages",
            "subcategory":"Fruits & Vegetables",
            "type":"Retail Goods"
        }
    ],
    "sg:phone":"+1 863 647 3695",
    "sg:postcode":"33813",
    "sg:province":"FL",
    "sg:tags":[
        "produce"
    ],
    "wof:name":"Pam's Fruit Stand",
    "wof:placetype":"venue"
},
  "geometry": {"coordinates":[-81.96075999999999,27.974822],"type":"Point"}
}