{
  "type": "Feature",
  "properties": {
    "addr:full":"501 N State Rd 7 Royal Palm Beach FL 33411",
    "addr:housenumber":"501;7",
    "addr:postcode":"33411",
    "addr:street":"N State Rd",
    "iso:country":"US",
    "sg:address":"501 N State Rd 7",
    "sg:city":"Royal Palm Beach",
    "sg:classifiers":[
        {
            "category":"Shopping",
            "subcategory":"Hobbies, Toys, & Games",
            "type":"Retail Goods"
        }
    ],
    "sg:phone":"+1 561 795 2393",
    "sg:postcode":"33411",
    "sg:province":"FL",
    "wof:name":"Toys R Us",
    "wof:placetype":"venue"
},
  "geometry": {"coordinates":[-80.202083,26.686596],"type":"Point"}
}