{
  "type": "Feature",
  "properties": {
    "iso:country":"US",
    "sg:address":"501 E Sheridan St",
    "sg:city":"Dania",
    "sg:classifiers":[
        {
            "category":"Shopping",
            "subcategory":"Pharmacy",
            "type":"Retail Goods"
        }
    ],
    "sg:phone":"+1 954 923 7611",
    "sg:postcode":"33004",
    "sg:province":"FL",
    "wof:name":"Walgreens",
    "wof:placetype":"venue"
},
  "geometry": {"coordinates":[-80.131244,26.033913],"type":"Point"}
}