{
  "type": "Feature",
  "properties": {
    "addr:full":"3211 Taragrove Dr Tampa FL 33618",
    "addr:housenumber":"3211",
    "addr:postcode":"33618",
    "addr:street":"Taragrove Dr",
    "iso:country":"US",
    "sg:address":"3211 Taragrove Dr",
    "sg:city":"Tampa",
    "sg:classifiers":[
        {
            "category":"Insurance",
            "subcategory":"Hazard Insurance",
            "type":"Services"
        },
        {
            "category":"Insurance",
            "subcategory":"Health Insurance",
            "type":"Services"
        }
    ],
    "sg:phone":"+1 813 968 9900",
    "sg:postcode":"33618",
    "sg:province":"FL",
    "sg:tags":[
        "employee",
        "benefit",
        "commercial",
        "business"
    ],
    "wof:name":"Richard Neitz Insurance",
    "wof:placetype":"venue"
},
  "geometry": {"coordinates":[-82.495504,28.073836],"type":"Point"}
}