{
  "type": "Feature",
  "properties": {
    "addr:full":"3200 13th St St Cloud FL 34769",
    "addr:housenumber":"3200",
    "addr:postcode":"34769",
    "addr:street":"13Th St",
    "iso:country":"US",
    "sg:address":"3200 13th St",
    "sg:city":"St Cloud",
    "sg:classifiers":[
        {
            "category":"Real Estate",
            "subcategory":"Real Estate Operator",
            "type":"Services"
        }
    ],
    "sg:phone":"+1 407 892 3979",
    "sg:postcode":"34769",
    "sg:province":"FL",
    "sg:tags":[
        "mobile",
        "home",
        "community"
    ],
    "wof:name":"Mark Mobile Home Park LTD",
    "wof:placetype":"venue"
},
  "geometry": {"coordinates":[-81.30546,28.247125],"type":"Point"}
}