{
  "type": "Feature",
  "properties": {
    "addr:full":"1510 SW 17th Ave Ocala FL 34471",
    "addr:housenumber":"1510",
    "addr:postcode":"34471",
    "addr:street":"Sw 17Th Ave",
    "iso:country":"US",
    "sg:address":"1510 SW 17th Ave",
    "sg:city":"Ocala",
    "sg:classifiers":[
        {
            "category":"Home & Garden",
            "subcategory":"Furniture",
            "type":"Retail Goods"
        }
    ],
    "sg:phone":"+1 352 369 9444",
    "sg:postcode":"34471",
    "sg:province":"FL",
    "sg:tags":[
        "bedding"
    ],
    "wof:name":"Mattress Barn",
    "wof:placetype":"venue"
},
  "geometry": {"coordinates":[-82.15405,29.175238],"type":"Point"}
}