{
  "type": "Feature",
  "properties": {
    "iso:country":"US",
    "sg:address":"920 Shaded Water Way",
    "sg:city":"Lutz",
    "sg:classifiers":[
        {
            "category":"Wholesale",
            "subcategory":"Electrical",
            "type":"Manufacturing & Wholesale Goods"
        }
    ],
    "sg:phone":"+1 813 948 3552",
    "sg:postcode":"33549",
    "sg:province":"FL",
    "sg:tags":[
        "electronic"
    ],
    "wof:name":"Components Sales of Florida",
    "wof:placetype":"venue"
},
  "geometry": {"coordinates":[-82.44879899999999,28.121937],"type":"Point"}
}