{
  "type": "Feature",
  "properties": {
    "addr:full":"4095 SW 137th Ave Ste 2 Miami FL 33175",
    "addr:housenumber":"4095",
    "addr:postcode":"33175",
    "addr:street":"Sw 137Th Ave Ste 2",
    "iso:country":"US",
    "sg:address":"4095 SW 137th Ave Ste 2",
    "sg:city":"Miami",
    "sg:classifiers":[
        {
            "category":"Personal",
            "subcategory":"Nail Salon",
            "type":"Services"
        }
    ],
    "sg:phone":"+1 305 227 7464",
    "sg:postcode":"33175",
    "sg:province":"FL",
    "wof:name":"Yen Nails Inc",
    "wof:placetype":"venue"
},
  "geometry": {"coordinates":[-80.415638,25.730196],"type":"Point"}
}