{
  "type": "Feature",
  "properties": {
    "addr:full":"111 Thurston Pl Crestview FL 32536",
    "addr:housenumber":"111",
    "addr:postcode":"32536",
    "addr:street":"Thurston Pl",
    "iso:country":"US",
    "sg:address":"111 Thurston Pl",
    "sg:city":"Crestview",
    "sg:classifiers":[
        {
            "category":"Banks & Credit Unions",
            "subcategory":"Investment Brokerage",
            "type":"Services"
        }
    ],
    "sg:phone":"+1 850 689 1756",
    "sg:postcode":"32536",
    "sg:province":"FL",
    "sg:tags":[
        "stock",
        "bond"
    ],
    "wof:name":"Total Financial Group Inc",
    "wof:placetype":"venue"
},
  "geometry": {"coordinates":[-86.610167,30.774604],"type":"Point"}
}