{
  "type": "Feature",
  "properties": {
    "addr:full":"127 W Jenkins Cir Sanford FL 32773",
    "addr:housenumber":"127",
    "addr:postcode":"32773",
    "addr:street":"W Jenkins Cir",
    "iso:country":"US",
    "sg:address":"127 W Jenkins Cir",
    "sg:city":"Sanford",
    "sg:classifiers":[
        {
            "category":"Wholesale",
            "subcategory":"Durable Goods & Equipment",
            "type":"Manufacturing & Wholesale Goods"
        }
    ],
    "sg:phone":"+1 407 323 7311",
    "sg:postcode":"32773",
    "sg:province":"FL",
    "sg:tags":[
        "used",
        "merchandise"
    ],
    "wof:name":"Somewhere In Time",
    "wof:placetype":"venue"
},
  "geometry": {"coordinates":[-81.269081,28.766051],"type":"Point"}
}