{
  "type": "Feature",
  "properties": {
    "addr:full":"3766 Coco Lake Dr Coconut Creek FL 33073",
    "addr:housenumber":"3766",
    "addr:postcode":"33073",
    "addr:street":"Coco Lake Dr",
    "iso:country":"US",
    "sg:address":"3766 Coco Lake Dr",
    "sg:city":"Coconut Creek",
    "sg:classifiers":[
        {
            "category":"Banks & Credit Unions",
            "subcategory":"Bank",
            "type":"Services"
        }
    ],
    "sg:phone":"+1 954 571 4000",
    "sg:postcode":"33073",
    "sg:province":"FL",
    "sg:tags":[
        "cashing",
        "check"
    ],
    "wof:name":"Checks Cashed Etc",
    "wof:placetype":"venue"
},
  "geometry": {"coordinates":[-80.17380199999999,26.301723],"type":"Point"}
}