{
  "type": "Feature",
  "properties": {
    "addr:full":"303 13th Ave E Bradenton FL 34208",
    "addr:housenumber":"303",
    "addr:postcode":"34208",
    "addr:street":"13Th Ave E",
    "iso:country":"US",
    "sg:address":"303 13th Ave E",
    "sg:city":"Bradenton",
    "sg:classifiers":[
        {
            "category":"Government",
            "subcategory":"Office",
            "type":"Public Place"
        }
    ],
    "sg:phone":"+1 941 741 3681",
    "sg:postcode":"34208",
    "sg:province":"FL",
    "sg:tags":[
        "executive"
    ],
    "wof:name":"Children & Families Department",
    "wof:placetype":"venue"
},
  "geometry": {"coordinates":[-82.558353,27.488113],"type":"Point"}
}