{
  "type": "Feature",
  "properties": {
    "iso:country":"US",
    "sg:address":"1813 Palm Way",
    "sg:city":"Largo",
    "sg:classifiers":[
        {
            "category":"Real Estate",
            "subcategory":"Real Estate Operator",
            "type":"Services"
        },
        {
            "category":"Building & Trades",
            "subcategory":"Construction",
            "type":"Services"
        },
        {
            "category":"Manufacturing",
            "subcategory":"Building Materials",
            "type":"Manufacturing & Wholesale Goods"
        }
    ],
    "sg:phone":"+1 727 536 0892",
    "sg:postcode":"33771",
    "sg:province":"FL",
    "sg:tags":[
        "plastering",
        "coating",
        "contractor",
        "gunite",
        "exterior",
        "grouting",
        "stucco"
    ],
    "wof:name":"West Coast Stucco And Plastering Inc",
    "wof:placetype":"venue"
},
  "geometry": {"coordinates":[-82.75083600000001,27.899465],"type":"Point"}
}