{
  "type": "Feature",
  "properties": {
    "addr:full":"3001 N Rocky Point Dr Tampa FL 33607",
    "addr:housenumber":"3001",
    "addr:postcode":"33607",
    "addr:street":"N Rocky Point Dr",
    "iso:country":"US",
    "sg:address":"3001 N Rocky Point Dr",
    "sg:city":"Tampa",
    "sg:classifiers":[
        {
            "category":"Health Services",
            "subcategory":"Doctor",
            "type":"Services"
        }
    ],
    "sg:phone":"+1 813 281 1014",
    "sg:postcode":"33607",
    "sg:province":"FL",
    "sg:tags":[
        "physician",
        "surgeon"
    ],
    "wof:name":"National Medical System",
    "wof:placetype":"venue"
},
  "geometry": {"coordinates":[-82.567868,27.967737],"type":"Point"}
}