{
  "type": "Feature",
  "properties": {
    "iso:country":"US",
    "sg:address":"55 Eglin Pkwy NE",
    "sg:city":"Fort Walton Beach",
    "sg:classifiers":[
        {
            "category":"Restaurant",
            "type":"Food & Drink"
        }
    ],
    "sg:menulink":"http://www.allmenus.com/fl/fort-walton-beach/174714-popeyes-chicken--biscuits/menu/",
    "sg:phone":"+1 850 243 6633",
    "sg:postcode":"32548",
    "sg:province":"FL",
    "sg:tags":[
        "american",
        "wing"
    ],
    "wof:name":"Popeyes Chicken & Biscuits",
    "wof:placetype":"venue"
},
  "geometry": {"coordinates":[-86.60630500000001,30.41506],"type":"Point"}
}