{
  "type": "Feature",
  "properties": {
    "iso:country":"US",
    "sg:address":"2311 SE Ocean Blvd",
    "sg:city":"Stuart",
    "sg:classifiers":[
        {
            "category":"Real Estate",
            "subcategory":"Real Estate Services",
            "type":"Services"
        },
        {
            "category":"Real Estate",
            "subcategory":"Real Estate Agent",
            "type":"Services"
        }
    ],
    "sg:phone":"+1 772 215 4093",
    "sg:postcode":"34996",
    "sg:province":"FL",
    "sg:tags":[
        "buyer",
        "broker"
    ],
    "wof:name":"Dockside Realty Group Inc",
    "wof:placetype":"venue"
},
  "geometry": {"coordinates":[-80.22170300000001,27.196893],"type":"Point"}
}