{
  "type": "Feature",
  "properties": {
    "addr:full":"7461 N Kendall Dr Miami FL 33156",
    "addr:housenumber":"7461",
    "addr:postcode":"33156",
    "addr:street":"N Kendall Dr",
    "iso:country":"US",
    "sg:address":"7461 N Kendall Dr",
    "sg:city":"Miami",
    "sg:classifiers":[
        {
            "category":"Shopping",
            "subcategory":"Shoes",
            "type":"Retail Goods"
        }
    ],
    "sg:phone":"+1 305 668 1789",
    "sg:postcode":"33156",
    "sg:province":"FL",
    "sg:tags":[
        "shoe",
        "store"
    ],
    "wof:name":"Kenneth Cole 36",
    "wof:placetype":"venue"
},
  "geometry": {"coordinates":[-80.316344,25.688633],"type":"Point"}
}