{
  "type": "Feature",
  "properties": {
    "addr:full":"4907 NE 12th Ave Fort Lauderdale FL 33334",
    "addr:housenumber":"4907",
    "addr:postcode":"33334",
    "addr:street":"Ne 12Th Ave",
    "iso:country":"US",
    "sg:address":"4907 NE 12th Ave",
    "sg:city":"Fort Lauderdale",
    "sg:classifiers":[
        {
            "category":"Health Services",
            "subcategory":"Medical Lab",
            "type":"Services"
        }
    ],
    "sg:phone":"+1 954 772 8277",
    "sg:postcode":"33334",
    "sg:province":"FL",
    "sg:tags":[
        "laboratory",
        "dental"
    ],
    "wof:name":"J P Dental Lab",
    "wof:placetype":"venue"
},
  "geometry": {"coordinates":[-80.13132899999999,26.188822],"type":"Point"}
}