{
  "type": "Feature",
  "properties": {
    "addr:full":"2520 NW 6th St Fort Lauderdale FL 33311",
    "addr:housenumber":"2520",
    "addr:postcode":"33311",
    "addr:street":"Nw 6Th St",
    "iso:country":"US",
    "sg:address":"2520 NW 6th St",
    "sg:city":"Fort Lauderdale",
    "sg:classifiers":[
        {
            "category":"Recreation",
            "type":"Entertainment"
        }
    ],
    "sg:phone":"+1 954 791 1036",
    "sg:postcode":"33311",
    "sg:province":"FL",
    "sg:tags":[
        "rec",
        "parks"
    ],
    "wof:name":"Broward County Parks & Recrea",
    "wof:placetype":"venue"
},
  "geometry": {"coordinates":[-80.17706800000001,26.128798],"type":"Point"}
}