{
  "type": "Feature",
  "properties": {
    "iso:country":"US",
    "sg:address":"2638 Ramsdale Dr SE",
    "sg:city":"Palm Bay",
    "sg:classifiers":[
        {
            "category":"Building & Trades",
            "subcategory":"Cleaning & Sanitation",
            "type":"Services"
        }
    ],
    "sg:phone":"+1 321 722 1912",
    "sg:postcode":"32909",
    "sg:province":"FL",
    "sg:tags":[
        "janitor"
    ],
    "wof:name":"Brite & Clean",
    "wof:placetype":"venue"
},
  "geometry": {"coordinates":[-80.629783,27.929113],"type":"Point"}
}