{
  "type": "Feature",
  "properties": {
    "iso:country":"US",
    "sg:address":"8169 Woodville Hwy",
    "sg:city":"Tallahassee",
    "sg:classifiers":[
        {
            "category":"Freight",
            "type":"Transportation"
        }
    ],
    "sg:phone":"+1 850 421 5039",
    "sg:postcode":"32305",
    "sg:province":"FL",
    "sg:tags":[
        "commercial",
        "storage"
    ],
    "wof:name":"Lewiswood Center & Storage LLC",
    "wof:placetype":"venue"
},
  "geometry": {"coordinates":[-84.249899,30.32536],"type":"Point"}
}