{
  "type": "Feature",
  "properties": {
    "iso:country":"US",
    "sg:address":"1040 NW 10th Ave",
    "sg:city":"Fort Lauderdale",
    "sg:classifiers":[
        {
            "category":"Health Services",
            "subcategory":"Doctor",
            "type":"Services"
        }
    ],
    "sg:phone":"+1 954 728 9200",
    "sg:postcode":"33311",
    "sg:province":"FL",
    "sg:tags":[
        "medical"
    ],
    "wof:name":"Manor Medical Assoc Inc",
    "wof:placetype":"venue"
},
  "geometry": {"coordinates":[-80.156093,26.138636],"type":"Point"}
}