{
  "type": "Feature",
  "properties": {
    "iso:country":"US",
    "sg:address":"6110 NW 1st Pl",
    "sg:city":"Gainesville",
    "sg:classifiers":[
        {
            "category":"Real Estate",
            "subcategory":"Real Estate Services",
            "type":"Services"
        },
        {
            "category":"Real Estate",
            "subcategory":"Real Estate Agent",
            "type":"Services"
        }
    ],
    "sg:phone":"+1 352 331 1133",
    "sg:postcode":"32607",
    "sg:province":"FL",
    "sg:tags":[
        "rental",
        "management",
        "commercial"
    ],
    "sg:website":"http://www.action-realtors.com",
    "wof:name":"Action Real Estate Services",
    "wof:placetype":"venue"
},
  "geometry": {"coordinates":[-82.408777,29.653325],"type":"Point"}
}