{
  "type": "Feature",
  "properties": {
    "addr:full":"1806 SE 51 St Gainesville FL 32641",
    "addr:housenumber":"1806;51",
    "addr:postcode":"32641",
    "addr:street":"Se;St",
    "iso:country":"US",
    "sg:address":"1806 SE 51 St",
    "sg:city":"Gainesville",
    "sg:classifiers":[
        {
            "category":"Building & Trades",
            "subcategory":"Electrical",
            "type":"Services"
        }
    ],
    "sg:phone":"+1 352 378 5783",
    "sg:postcode":"32641",
    "sg:province":"FL",
    "sg:tags":[
        "electrical",
        "contractor"
    ],
    "wof:name":"Paul Howard Inc",
    "wof:placetype":"venue"
},
  "geometry": {"coordinates":[-82.264004,29.634106],"type":"Point"}
}