{
  "type": "Feature",
  "properties": {
    "iso:country":"US",
    "sg:address":"8740 US Hwy 98",
    "sg:city":"Lakeland",
    "sg:classifiers":[
        {
            "category":"Home & Garden",
            "subcategory":"Garden Supply",
            "type":"Retail Goods"
        }
    ],
    "sg:phone":"+1 863 858 5296",
    "sg:postcode":"33809",
    "sg:province":"FL",
    "sg:tags":[
        "lawn",
        "mower"
    ],
    "wof:name":"North Lakeland Lawn Equipment",
    "wof:placetype":"venue"
},
  "geometry": {"coordinates":[-81.973905,28.159534],"type":"Point"}
}