{
  "type": "Feature",
  "properties": {
    "iso:country":"US",
    "sg:address":"12528 Forest Highlands Dr",
    "sg:city":"Dade City",
    "sg:classifiers":[
        {
            "category":"Building & Trades",
            "subcategory":"Construction",
            "type":"Services"
        }
    ],
    "sg:phone":"+1 352 588 0030",
    "sg:postcode":"33525",
    "sg:province":"FL",
    "sg:tags":[
        "contractor"
    ],
    "wof:name":"Palmwood Builders",
    "wof:placetype":"venue"
},
  "geometry": {"coordinates":[-82.247609,28.340289],"type":"Point"}
}