{
  "type": "Feature",
  "properties": {
    "addr:full":"8110 Cardena Ln Sarasota FL 34238",
    "addr:housenumber":"8110",
    "addr:postcode":"34238",
    "addr:street":"Cardena Ln",
    "iso:country":"US",
    "sg:address":"8110 Cardena Ln",
    "sg:city":"Sarasota",
    "sg:classifiers":[
        {
            "category":"Building & Trades",
            "subcategory":"Construction",
            "type":"Services"
        }
    ],
    "sg:phone":"+1 941 924 1612",
    "sg:postcode":"34238",
    "sg:province":"FL",
    "sg:tags":[
        "home",
        "builder"
    ],
    "wof:name":"Divosta Homes LP",
    "wof:placetype":"venue"
},
  "geometry": {"coordinates":[-82.45978100000001,27.234346],"type":"Point"}
}