{
  "type": "Feature",
  "properties": {
    "addr:full":"1610 Landon Ave Jacksonville FL 32207",
    "addr:housenumber":"1610",
    "addr:postcode":"32207",
    "addr:street":"Landon Ave",
    "iso:country":"US",
    "sg:address":"1610 Landon Ave",
    "sg:city":"Jacksonville",
    "sg:classifiers":[
        {
            "category":"Shopping",
            "subcategory":"Books",
            "type":"Retail Goods"
        }
    ],
    "sg:phone":"+1 904 306 0581",
    "sg:postcode":"32207",
    "sg:province":"FL",
    "sg:tags":[
        "dealer"
    ],
    "wof:name":"Little Black Book For Every",
    "wof:placetype":"venue"
},
  "geometry": {"coordinates":[-81.652434,30.30812],"type":"Point"}
}