{
  "type": "Feature",
  "properties": {
    "addr:full":"1001 E Hwy 98 Panama City FL 32401",
    "addr:housenumber":"1001",
    "addr:postcode":"32401",
    "addr:street":"E Hwy 98",
    "iso:country":"US",
    "sg:address":"1001 E Hwy 98",
    "sg:city":"Panama City",
    "sg:classifiers":[
        {
            "category":"Real Estate",
            "subcategory":"Real Estate Services",
            "type":"Services"
        }
    ],
    "sg:phone":"+1 850 769 1641",
    "sg:postcode":"32401",
    "sg:province":"FL",
    "sg:tags":[
        "company",
        "title"
    ],
    "wof:name":"First American Title Ins Co",
    "wof:placetype":"venue"
},
  "geometry": {"coordinates":[-85.645004,30.15634],"type":"Point"}
}