{
  "type": "Feature",
  "properties": {
    "addr:full":"1004 NW 65th Ave Miami FL 33126",
    "addr:housenumber":"1004",
    "addr:postcode":"33126",
    "addr:street":"Nw 65Th Ave",
    "iso:country":"US",
    "sg:address":"1004 NW 65th Ave",
    "sg:city":"Miami",
    "sg:classifiers":[
        {
            "category":"Banks & Credit Unions",
            "subcategory":"Financial Services",
            "type":"Services"
        }
    ],
    "sg:phone":"+1 305 328 1371",
    "sg:postcode":"33126",
    "sg:province":"FL",
    "sg:tags":[
        "card",
        "card-merchant"
    ],
    "sg:website":"http://www.visa.com",
    "wof:name":"Visa",
    "wof:placetype":"venue"
},
  "geometry": {"coordinates":[-80.301367,25.778013],"type":"Point"}
}