{
  "type": "Feature",
  "properties": {
    "iso:country":"US",
    "sg:address":"15100 NW 67th Ave Ste 300",
    "sg:city":"Miami Lakes",
    "sg:classifiers":[
        {
            "category":"Banks & Credit Unions",
            "subcategory":"Bank",
            "type":"Services"
        }
    ],
    "sg:phone":"+1 786 313 0509",
    "sg:postcode":"33014",
    "sg:province":"FL",
    "sg:website":"www.americanexpress.com",
    "wof:name":"American Express",
    "wof:placetype":"venue"
},
  "geometry": {"coordinates":[-80.30978,25.910673],"type":"Point"}
}