{
  "type": "Feature",
  "properties": {
    "addr:full":"535 Cypress Tree Ct Orlando FL 32825",
    "addr:housenumber":"535",
    "addr:postcode":"32825",
    "addr:street":"Cypress Tree Ct",
    "iso:country":"US",
    "sg:address":"535 Cypress Tree Ct",
    "sg:city":"Orlando",
    "sg:classifiers":[
        {
            "category":"Building & Trades",
            "subcategory":"Construction",
            "type":"Services"
        }
    ],
    "sg:phone":"+1 407 306 0873",
    "sg:postcode":"32825",
    "sg:province":"FL",
    "sg:tags":[
        "floor",
        "laying",
        "contractor"
    ],
    "wof:name":"NC Flooring Inc",
    "wof:placetype":"venue"
},
  "geometry": {"coordinates":[-81.226069,28.549686],"type":"Point"}
}