{
  "type": "Feature",
  "properties": {
    "iso:country":"US",
    "sg:address":"2561 NW 54th St",
    "sg:city":"Miami",
    "sg:classifiers":[
        {
            "category":"Retail",
            "subcategory":"Laundry & Dry Cleaning",
            "type":"Services"
        }
    ],
    "sg:phone":"+1 305 635 4343",
    "sg:postcode":"33142",
    "sg:province":"FL",
    "wof:name":"Spin Cycle Coin Laundry",
    "wof:placetype":"venue"
},
  "geometry": {"coordinates":[-80.239481,25.824035],"type":"Point"}
}