{
  "type": "Feature",
  "properties": {
    "addr:full":"1979 State Hwy 20 Hawthorne FL 32640",
    "addr:housenumber":"1979",
    "addr:postcode":"32640",
    "addr:street":"State Hwy 20",
    "iso:country":"US",
    "sg:address":"1979 State Hwy 20",
    "sg:city":"Hawthorne",
    "sg:classifiers":[
        {
            "category":"Manufacturing",
            "subcategory":"Wood Products",
            "type":"Manufacturing & Wholesale Goods"
        }
    ],
    "sg:phone":"+1 352 481 4909",
    "sg:postcode":"32640",
    "sg:province":"FL",
    "sg:tags":[
        "mfg"
    ],
    "wof:name":"Charles Mikes Pallets",
    "wof:placetype":"venue"
},
  "geometry": {"coordinates":[-82.02519599999999,29.607815],"type":"Point"}
}