{
  "type": "Feature",
  "properties": {
    "addr:full":"2051 Consulate Dr Orlando FL 32837",
    "addr:housenumber":"2051",
    "addr:postcode":"32837",
    "addr:street":"Consulate Dr",
    "iso:country":"US",
    "sg:address":"2051 Consulate Dr",
    "sg:city":"Orlando",
    "sg:classifiers":[
        {
            "category":"Travel",
            "subcategory":"Hotels & Motels",
            "type":"Entertainment"
        }
    ],
    "sg:phone":"+1 407 240 0500",
    "sg:postcode":"32837",
    "sg:province":"FL",
    "sg:tags":[
        "corporate",
        "lodging"
    ],
    "sg:website":"http://redirect.searchignite.com/si/cm/tracking/DGTrackingRedirect.aspx?siclientid=2537&siredirect=http://www.lq.com/lq/properties/propertyProfile.do%3Fident%3DLQ1013%26IATA%3D99020726%26WT.srch%3D1&sisearchengine=155&siproduct=LQ+Orlando+South",
    "wof:name":"La Quinta Inn & Suites Orlando - South",
    "wof:placetype":"venue"
},
  "geometry": {"coordinates":[-81.406159,28.428347],"type":"Point"}
}