{
  "type": "Feature",
  "properties": {
    "iso:country":"US",
    "sg:address":"5350 Sandhurst Cir N",
    "sg:city":"Lake Worth",
    "sg:classifiers":[
        {
            "category":"Real Estate",
            "subcategory":"Real Estate Agent",
            "type":"Services"
        }
    ],
    "sg:phone":"+1 561 641 5121",
    "sg:postcode":"33463",
    "sg:province":"FL",
    "wof:name":"4 Realty Investors Inc",
    "wof:placetype":"venue"
},
  "geometry": {"coordinates":[-80.144801,26.598796],"type":"Point"}
}