{
  "type": "Feature",
  "properties": {
    "iso:country":"US",
    "sg:address":"2006 Jackson St N",
    "sg:city":"St Petersburg",
    "sg:classifiers":[
        {
            "category":"Social Services",
            "subcategory":"Child Care",
            "type":"Services"
        }
    ],
    "sg:phone":"+1 727 821 0027",
    "sg:postcode":"33704",
    "sg:province":"FL",
    "wof:name":"Keisha Day Care Ctr",
    "wof:placetype":"venue"
},
  "geometry": {"coordinates":[-82.648849,27.790415],"type":"Point"}
}