{
  "type": "Feature",
  "properties": {
    "iso:country":"US",
    "sg:address":"6698 Sandsdale Rd",
    "sg:city":"Macclenny",
    "sg:classifiers":[
        {
            "category":"Personal",
            "subcategory":"Beauty Salon",
            "type":"Services"
        },
        {
            "category":"Personal",
            "subcategory":"Barber",
            "type":"Services"
        }
    ],
    "sg:phone":"+1 904 259 6891",
    "sg:postcode":"32063",
    "sg:province":"FL",
    "wof:name":"Margaret's Kut 'N Kurl",
    "wof:placetype":"venue"
},
  "geometry": {"coordinates":[-82.150064,30.308341],"type":"Point"}
}