{
  "type": "Feature",
  "properties": {
    "addr:full":"2841 NE North Miami Beach Blvd Sunny Isles Beach FL 33160",
    "addr:housenumber":"2841",
    "addr:postcode":"33160",
    "addr:street":"Ne North Miami Beach Blvd",
    "iso:country":"US",
    "sg:address":"2841 NE North Miami Beach Blvd",
    "sg:city":"Sunny Isles Beach",
    "sg:classifiers":[
        {
            "category":"Building & Trades",
            "subcategory":"Locksmith",
            "type":"Services"
        }
    ],
    "sg:phone":"+1 305 851 5836",
    "sg:postcode":"33160",
    "sg:province":"FL",
    "sg:tags":[
        "key"
    ],
    "wof:name":"0.01 Emergency Locksmith",
    "wof:placetype":"venue"
},
  "geometry": {"coordinates":[-80.142822,25.926949],"type":"Point"}
}