{
  "type": "Feature",
  "properties": {
    "iso:country":"US",
    "sg:address":"10305 NW 41st St",
    "sg:city":"Doral",
    "sg:classifiers":[
        {
            "category":"Communications",
            "subcategory":"Radio Station",
            "type":"Services"
        }
    ],
    "sg:phone":"+1 305 718 8050",
    "sg:postcode":"33178",
    "sg:province":"FL",
    "sg:tags":[
        "medium",
        "broker"
    ],
    "wof:name":"Up Mobile",
    "wof:placetype":"venue"
},
  "geometry": {"coordinates":[-80.36346399999999,25.811702],"type":"Point"}
}