{
  "type": "Feature",
  "properties": {
    "iso:country":"US",
    "sg:address":"10445 Trianon Pl",
    "sg:city":"Wellington",
    "sg:classifiers":[
        {
            "category":"Building & Trades",
            "subcategory":"Construction",
            "type":"Services"
        }
    ],
    "sg:phone":"+1 561 963 4756",
    "sg:postcode":"33449",
    "sg:province":"FL",
    "sg:tags":[
        "system",
        "contractor",
        "air conditioning"
    ],
    "wof:name":"Perfect Cooling Inc",
    "wof:placetype":"venue"
},
  "geometry": {"coordinates":[-80.21319699999999,26.623032],"type":"Point"}
}