{
  "type": "Feature",
  "properties": {
    "iso:country":"US",
    "sg:address":"1000 37th Pl",
    "sg:city":"Vero Beach",
    "sg:classifiers":[
        {
            "category":"Health Services",
            "subcategory":"Doctor",
            "type":"Services"
        }
    ],
    "sg:phone":"+1 772 770 9191",
    "sg:postcode":"32960",
    "sg:province":"FL",
    "sg:tags":[
        "dentist"
    ],
    "wof:name":"Vero Beach Surgical Arts",
    "wof:placetype":"venue"
},
  "geometry": {"coordinates":[-80.39671300000001,27.660842],"type":"Point"}
}