{
  "type": "Feature",
  "properties": {
    "addr:full":"320 San Lorenzo Ave Coral Gables FL 33146",
    "addr:housenumber":"320",
    "addr:postcode":"33146",
    "addr:street":"San Lorenzo Ave",
    "iso:country":"US",
    "sg:address":"320 San Lorenzo Ave",
    "sg:city":"Coral Gables",
    "sg:classifiers":[
        {
            "category":"Shopping",
            "subcategory":"Clothing, Apparel, & Fashions",
            "type":"Retail Goods"
        }
    ],
    "sg:phone":"+1 305 446 1499",
    "sg:postcode":"33146",
    "sg:province":"FL",
    "sg:tags":[
        "furnishing"
    ],
    "wof:name":"Canali",
    "wof:placetype":"venue"
},
  "geometry": {"coordinates":[-80.26195,25.732101],"type":"Point"}
}