{
  "type": "Feature",
  "properties": {
    "addr:full":"1531 Hammondville Rd Pompano Beach FL 33069",
    "addr:housenumber":"1531",
    "addr:postcode":"33069",
    "addr:street":"Hammondville Rd",
    "iso:country":"US",
    "sg:address":"1531 Hammondville Rd",
    "sg:city":"Pompano Beach",
    "sg:classifiers":[
        {
            "category":"Wholesale",
            "subcategory":"Auto Parts",
            "type":"Manufacturing & Wholesale Goods"
        }
    ],
    "sg:phone":"+1 954 969 8491",
    "sg:postcode":"33069",
    "sg:province":"FL",
    "sg:tags":[
        "tire"
    ],
    "wof:name":"A M Tires Inc",
    "wof:placetype":"venue"
},
  "geometry": {"coordinates":[-80.144277,26.239074],"type":"Point"}
}