{
  "type": "Feature",
  "properties": {
    "iso:country":"US",
    "sg:address":"8000 W Sample Rd",
    "sg:city":"Margate",
    "sg:classifiers":[
        {
            "category":"Restaurant",
            "type":"Food & Drink"
        }
    ],
    "sg:phone":"+1 954 255 8108",
    "sg:postcode":"33065",
    "sg:province":"FL",
    "wof:name":"Roy's",
    "wof:placetype":"venue"
},
  "geometry": {"coordinates":[-80.231043,26.272282],"type":"Point"}
}