{
  "type": "Feature",
  "properties": {
    "addr:full":"509 Poinsettia Ln Kissimmee FL 34744",
    "addr:housenumber":"509",
    "addr:postcode":"34744",
    "addr:street":"Poinsettia Ln",
    "iso:country":"US",
    "sg:address":"509 Poinsettia Ln",
    "sg:city":"Kissimmee",
    "sg:classifiers":[
        {
            "category":"Manufacturing",
            "subcategory":"Motor Vehicles & Parts",
            "type":"Manufacturing & Wholesale Goods"
        }
    ],
    "sg:phone":"+1 407 847 3954",
    "sg:postcode":"34744",
    "sg:province":"FL",
    "sg:tags":[
        "home",
        "mfg"
    ],
    "wof:name":"Aabus Abode Services",
    "wof:placetype":"venue"
},
  "geometry": {"coordinates":[-81.39959,28.293465],"type":"Point"}
}