{
  "type": "Feature",
  "properties": {
    "iso:country":"US",
    "sg:address":"10202 Casa Palarmo Dr",
    "sg:city":"Riverview",
    "sg:classifiers":[
        {
            "category":"Wholesale",
            "subcategory":"Construction Materials",
            "type":"Manufacturing & Wholesale Goods"
        },
        {
            "category":"Home & Garden",
            "subcategory":"Building Materials",
            "type":"Retail Goods"
        }
    ],
    "sg:phone":"+1 813 526 4809",
    "sg:postcode":"33578",
    "sg:province":"FL",
    "sg:tags":[
        "windows-wholesale",
        "window",
        "manufacturer"
    ],
    "wof:name":"Window Magic",
    "wof:placetype":"venue"
},
  "geometry": {"coordinates":[-82.34213099999999,27.919925],"type":"Point"}
}