{
  "type": "Feature",
  "properties": {
    "addr:full":"7353 International Pl Sarasota FL 34240",
    "addr:housenumber":"7353",
    "addr:postcode":"34240",
    "addr:street":"International Pl",
    "iso:country":"US",
    "sg:address":"7353 International Pl",
    "sg:city":"Sarasota",
    "sg:classifiers":[
        {
            "category":"Recreation",
            "type":"Entertainment"
        }
    ],
    "sg:phone":"+1 941 373 6475",
    "sg:postcode":"34240",
    "sg:province":"FL",
    "sg:tags":[
        "amusement"
    ],
    "wof:name":"Fundamentals Kid's Play",
    "wof:placetype":"venue"
},
  "geometry": {"coordinates":[-82.42253700000001,27.380382],"type":"Point"}
}