{
  "type": "Feature",
  "properties": {
    "iso:country":"US",
    "sg:address":"2630 Victoria Dr NE",
    "sg:city":"Palm Bay",
    "sg:classifiers":[
        {
            "category":"Manufacturing",
            "subcategory":"Glass & Minerals",
            "type":"Manufacturing & Wholesale Goods"
        }
    ],
    "sg:phone":"+1 321 432 2323",
    "sg:postcode":"32905",
    "sg:province":"FL",
    "sg:tags":[
        "concrete",
        "brick",
        "prod",
        "block"
    ],
    "wof:name":"MOMAC Precast Inc",
    "wof:placetype":"venue"
},
  "geometry": {"coordinates":[-80.59384300000001,28.06228],"type":"Point"}
}