{
  "type": "Feature",
  "properties": {
    "addr:full":"9280 College Pkwy Ste 1 Fort Myers FL 33919",
    "addr:housenumber":"9280",
    "addr:postcode":"myers fl 33919",
    "addr:street":"College Pkwy Ste 1",
    "iso:country":"US",
    "sg:address":"9280 College Pkwy Ste 1",
    "sg:city":"Fort Myers",
    "sg:classifiers":[
        {
            "category":"Personal",
            "type":"Services"
        }
    ],
    "sg:phone":"+1 239 489 2880",
    "sg:postcode":"33919",
    "sg:province":"FL",
    "sg:tags":[
        "sewing",
        "alteration"
    ],
    "wof:name":"Name Game the",
    "wof:placetype":"venue"
},
  "geometry": {"coordinates":[-81.9011,26.5536],"type":"Point"}
}