{
  "type": "Feature",
  "properties": {
    "iso:country":"US",
    "sg:address":"2561 South St",
    "sg:city":"Fort Myers",
    "sg:classifiers":[
        {
            "category":"Building & Trades",
            "subcategory":"Pest Control",
            "type":"Services"
        }
    ],
    "sg:phone":"+1 239 337 1519",
    "sg:postcode":"33901",
    "sg:province":"FL",
    "sg:website":"www.lanmac.com",
    "wof:name":"Lan Mac Pest Control",
    "wof:placetype":"venue"
},
  "geometry": {"coordinates":[-81.860497,26.6301],"type":"Point"}
}