{
  "type": "Feature",
  "properties": {
    "iso:country":"US",
    "sg:address":"390 Dubsdread Cir",
    "sg:city":"Orlando",
    "sg:classifiers":[
        {
            "category":"Real Estate",
            "subcategory":"Real Estate Operator",
            "type":"Services"
        }
    ],
    "sg:phone":"+1 407 898 3127",
    "sg:postcode":"32804",
    "sg:province":"FL",
    "sg:tags":[
        "building",
        "apartment"
    ],
    "wof:name":"Central Place",
    "wof:placetype":"venue"
},
  "geometry": {"coordinates":[-81.382097,28.582948],"type":"Point"}
}