{
  "type": "Feature",
  "properties": {
    "addr:full":"1246 E Brandon Blvd Brandon FL 33511",
    "addr:housenumber":"1246",
    "addr:postcode":"33511",
    "addr:street":"E Brandon Blvd",
    "iso:country":"US",
    "sg:address":"1246 E Brandon Blvd",
    "sg:city":"Brandon",
    "sg:classifiers":[
        {
            "category":"Restaurant",
            "type":"Food & Drink"
        }
    ],
    "sg:menulink":"http://www.allmenus.com/fl/brandon/87199-little-caesars-pizza/menu/",
    "sg:phone":"+1 813 657 1278",
    "sg:postcode":"33511",
    "sg:province":"FL",
    "sg:tags":[
        "american",
        "pizza"
    ],
    "wof:name":"Little Caesar's Pizza",
    "wof:placetype":"venue"
},
  "geometry": {"coordinates":[-82.263699,27.937891],"type":"Point"}
}