{
  "type": "Feature",
  "properties": {
    "iso:country":"US",
    "sg:address":"6158 NW 113th Pl",
    "sg:city":"Miami",
    "sg:classifiers":[
        {
            "category":"Arena",
            "subcategory":"Sports Club",
            "type":"Entertainment"
        }
    ],
    "sg:phone":"+1 305 513 0265",
    "sg:postcode":"33178",
    "sg:province":"FL",
    "wof:name":"GS Golf LLC",
    "wof:placetype":"venue"
},
  "geometry": {"coordinates":[-80.382406,25.831303],"type":"Point"}
}