{
  "type": "Feature",
  "properties": {
    "iso:country":"US",
    "sg:address":"8200 Kona Ave",
    "sg:city":"Jacksonville",
    "sg:classifiers":[
        {
            "category":"Recreation",
            "type":"Entertainment"
        }
    ],
    "sg:phone":"+1 904 724 6169",
    "sg:postcode":"32211",
    "sg:province":"FL",
    "sg:tags":[
        "pool",
        "swimming"
    ],
    "wof:name":"Woodland Acres Swimming Pool",
    "wof:placetype":"venue"
},
  "geometry": {"coordinates":[-81.569784,30.322865],"type":"Point"}
}