{
  "type": "Feature",
  "properties": {
    "iso:country":"US",
    "sg:address":"5312 Broadway",
    "sg:city":"West Palm Beach",
    "sg:classifiers":[
        {
            "category":"Organizations",
            "subcategory":"Religious Organization",
            "type":"Services"
        }
    ],
    "sg:phone":"+1 561 881 8736",
    "sg:postcode":"33407",
    "sg:province":"FL",
    "sg:tags":[
        "church"
    ],
    "wof:name":"Iglesia Del Nazareno Belen",
    "wof:placetype":"venue"
},
  "geometry": {"coordinates":[-80.05552,26.758711],"type":"Point"}
}