{
  "type": "Feature",
  "properties": {
    "iso:country":"US",
    "sg:address":"2158 S Orange Blossom Trl",
    "sg:city":"Apopka",
    "sg:classifiers":[
        {
            "category":"Home & Garden",
            "subcategory":"Hardware",
            "type":"Retail Goods"
        }
    ],
    "sg:phone":"+1 407 886 2200",
    "sg:postcode":"32703",
    "sg:province":"FL",
    "sg:tags":[
        "body",
        "auto",
        "supply"
    ],
    "wof:name":"Southern Rack & Ladder of Cent",
    "wof:placetype":"venue"
},
  "geometry": {"coordinates":[-81.460432,28.645112],"type":"Point"}
}