{
  "type": "Feature",
  "properties": {
    "addr:full":"1700 SW 57th Ave Ste 219 Miami FL 33155",
    "addr:housenumber":"1700",
    "addr:postcode":"33155",
    "addr:street":"Sw 57Th Ave Ste 219",
    "iso:country":"US",
    "sg:address":"1700 SW 57th Ave Ste 219",
    "sg:city":"Miami",
    "sg:classifiers":[
        {
            "category":"Professional",
            "subcategory":"Accounting & Tax Preparation",
            "type":"Services"
        }
    ],
    "sg:phone":"+1 786 693 9358",
    "sg:postcode":"33155",
    "sg:province":"FL",
    "sg:tags":[
        "accountant"
    ],
    "sg:website":"www.heyerinc.com",
    "wof:name":"Heyer & Associates EA, PA",
    "wof:placetype":"venue"
},
  "geometry": {"coordinates":[-80.28759700000001,25.756212],"type":"Point"}
}