{
  "type": "Feature",
  "properties": {
    "addr:full":"1160 Kane Concourse Bay Harbor Islands FL 33154",
    "addr:housenumber":"1160",
    "addr:postcode":"33154",
    "addr:street":"Kane Concourse",
    "iso:country":"US",
    "sg:address":"1160 Kane Concourse",
    "sg:city":"Bay Harbor Islands",
    "sg:classifiers":[
        {
            "category":"Personal",
            "subcategory":"Hair Removal",
            "type":"Services"
        }
    ],
    "sg:phone":"+1 305 861 7211",
    "sg:postcode":"33154",
    "sg:province":"FL",
    "wof:name":"Electro Artzs",
    "wof:placetype":"venue"
},
  "geometry": {"coordinates":[-80.132451,25.886485],"type":"Point"}
}