{
  "type": "Feature",
  "properties": {
    "iso:country":"US",
    "sg:address":"3161 Taft St",
    "sg:city":"Hollywood",
    "sg:classifiers":[
        {
            "category":"Sports & Exercise",
            "subcategory":"Gym",
            "type":"Entertainment"
        }
    ],
    "sg:phone":"+1 954 989 9622",
    "sg:postcode":"33021",
    "sg:province":"FL",
    "sg:tags":[
        "consultant",
        "program",
        "health",
        "fitness"
    ],
    "sg:website":"http://www.ymca.net",
    "wof:name":"Ymca",
    "wof:placetype":"venue"
},
  "geometry": {"coordinates":[-80.172089,26.0257],"type":"Point"}
}