{
  "type": "Feature",
  "properties": {
    "iso:country":"US",
    "sg:address":"825 Orange Ave",
    "sg:city":"Penney Farms",
    "sg:classifiers":[
        {
            "category":"Government",
            "subcategory":"Office",
            "type":"Public Place"
        }
    ],
    "sg:phone":"+1 904 529 3668",
    "sg:postcode":"32092",
    "sg:province":"FL",
    "wof:name":"Clay County General Master",
    "wof:placetype":"venue"
},
  "geometry": {"coordinates":[-81.535359,29.827093],"type":"Point"}
}