{
  "type": "Feature",
  "properties": {
    "iso:country":"US",
    "sg:address":"1227 S Patrick Dr",
    "sg:city":"Satellite Beach",
    "sg:classifiers":[
        {
            "category":"Real Estate",
            "subcategory":"Real Estate Services",
            "type":"Services"
        }
    ],
    "sg:phone":"+1 321 779 9700",
    "sg:postcode":"32937",
    "sg:province":"FL",
    "sg:tags":[
        "company",
        "title"
    ],
    "sg:website":"www.townandcountrytitle.com",
    "wof:name":"Town & Country Title Guaranty",
    "wof:placetype":"venue"
},
  "geometry": {"coordinates":[-80.60598,28.179097],"type":"Point"}
}