{
  "type": "Feature",
  "properties": {
    "iso:country":"US",
    "sg:address":"140 N Parsons Ave",
    "sg:city":"Brandon",
    "sg:phone":"+1 813 684 1948",
    "sg:postcode":"33510",
    "sg:province":"FL",
    "wof:name":"La Septima Cafe",
    "wof:placetype":"venue"
},
  "geometry": {"coordinates":[-82.285782,27.939131],"type":"Point"}
}