{
  "type": "Feature",
  "properties": {
    "addr:full":"425 Thomez Ct Lake Mary FL 32746",
    "addr:housenumber":"425",
    "addr:postcode":"32746",
    "addr:street":"Thomez Ct",
    "iso:country":"US",
    "sg:address":"425 Thomez Ct",
    "sg:city":"Lake Mary",
    "sg:classifiers":[
        {
            "category":"Food & Beverages",
            "subcategory":"Specialty",
            "type":"Retail Goods"
        }
    ],
    "sg:phone":"+1 407 330 3201",
    "sg:postcode":"32746",
    "sg:province":"FL",
    "wof:name":"Reliv Health Food Supplements",
    "wof:placetype":"venue"
},
  "geometry": {"coordinates":[-81.33122899999999,28.776657],"type":"Point"}
}