{
  "type": "Feature",
  "properties": {
    "iso:country":"US",
    "sg:address":"5930 N Port Blvd",
    "sg:city":"North Port",
    "sg:classifiers":[
        {
            "category":"Shopping",
            "subcategory":"Luggage & Leather Goods",
            "type":"Retail Goods"
        }
    ],
    "sg:phone":"+1 941 429 0999",
    "sg:postcode":"34287",
    "sg:province":"FL",
    "wof:name":"Acosta's Leather Care & Repair",
    "wof:placetype":"venue"
},
  "geometry": {"coordinates":[-82.235541,27.04468],"type":"Point"}
}