{
  "type": "Feature",
  "properties": {
    "iso:country":"US",
    "sg:address":"3321 5th Ave S",
    "sg:city":"Saint Petersburg",
    "sg:classifiers":[
        {
            "category":"Retail",
            "subcategory":"Photofinishing",
            "type":"Services"
        }
    ],
    "sg:phone":"+1 727 323 9104",
    "sg:postcode":"33712",
    "sg:province":"FL",
    "sg:tags":[
        "laboratory",
        "photography",
        "commercial"
    ],
    "wof:name":"Clm Photography",
    "wof:placetype":"venue"
},
  "geometry": {"coordinates":[-82.67917300000001,27.766534],"type":"Point"}
}