{
  "type": "Feature",
  "properties": {
    "iso:country":"US",
    "sg:address":"1927 27th Ave",
    "sg:city":"Vero Beach",
    "sg:classifiers":[
        {
            "category":"Organizations",
            "subcategory":"Religious Organization",
            "type":"Services"
        }
    ],
    "sg:phone":"+1 772 562 9110",
    "sg:postcode":"32960",
    "sg:province":"FL",
    "sg:tags":[
        "church"
    ],
    "wof:name":"First Christian Church",
    "wof:placetype":"venue"
},
  "geometry": {"coordinates":[-80.41384600000001,27.638141],"type":"Point"}
}