{
  "type": "Feature",
  "properties": {
    "iso:country":"US",
    "sg:address":"33225 E Lake Joanna Dr",
    "sg:city":"Eustis",
    "sg:classifiers":[
        {
            "category":"Insurance",
            "subcategory":"Insurance Agent",
            "type":"Services"
        }
    ],
    "sg:phone":"+1 352 383 7407",
    "sg:postcode":"32736",
    "sg:province":"FL",
    "wof:name":"Dezie Tropicals Inc",
    "wof:placetype":"venue"
},
  "geometry": {"coordinates":[-81.64281200000001,28.835265],"type":"Point"}
}