{
  "type": "Feature",
  "properties": {
    "iso:country":"US",
    "sg:address":"4407 N Nebraska Ave",
    "sg:city":"Tampa",
    "sg:classifiers":[
        {
            "category":"Shopping",
            "subcategory":"Discount & Variety Stores",
            "type":"Retail Goods"
        }
    ],
    "sg:phone":"+1 813 237 6871",
    "sg:postcode":"33603",
    "sg:province":"FL",
    "sg:tags":[
        "merchandise",
        "general"
    ],
    "wof:name":"Mega Super Market",
    "wof:placetype":"venue"
},
  "geometry": {"coordinates":[-82.451077,27.986002],"type":"Point"}
}