{
  "type": "Feature",
  "properties": {
    "addr:full":"3297 S John Young Pkwy Kissimmee FL 34746",
    "addr:housenumber":"3297",
    "addr:postcode":"34746",
    "addr:street":"S John Young Pkwy",
    "iso:country":"US",
    "sg:address":"3297 S John Young Pkwy",
    "sg:city":"Kissimmee",
    "sg:classifiers":[
        {
            "category":"Retail",
            "subcategory":"Auto Rental",
            "type":"Services"
        }
    ],
    "sg:phone":"+1 407 846 4012",
    "sg:postcode":"34746",
    "sg:province":"FL",
    "sg:tags":[
        "renting",
        "truck",
        "leasing"
    ],
    "wof:name":"U-Haul Co",
    "wof:placetype":"venue"
},
  "geometry": {"coordinates":[-81.43474000000001,28.261407],"type":"Point"}
}