{
  "type": "Feature",
  "properties": {
    "addr:full":"556 W 27th St Hialeah FL 33010",
    "addr:housenumber":"556",
    "addr:postcode":"33010",
    "addr:street":"W 27Th St",
    "iso:country":"US",
    "sg:address":"556 W 27th St",
    "sg:city":"Hialeah",
    "sg:classifiers":[
        {
            "category":"Building & Trades",
            "subcategory":"Construction",
            "type":"Services"
        }
    ],
    "sg:phone":"+1 305 885 6333",
    "sg:postcode":"33010",
    "sg:province":"FL",
    "sg:tags":[
        "carpenter",
        "maker",
        "cabinet"
    ],
    "wof:name":"Illusions Carpentry Inc",
    "wof:placetype":"venue"
},
  "geometry": {"coordinates":[-80.29334900000001,25.84618],"type":"Point"}
}