{
  "type": "Feature",
  "properties": {
    "addr:full":"1020 E Main St Pahokee FL 33476",
    "addr:housenumber":"1020",
    "addr:postcode":"33476",
    "addr:street":"E Main St",
    "iso:country":"US",
    "sg:address":"1020 E Main St",
    "sg:city":"Pahokee",
    "sg:classifiers":[
        {
            "category":"Place Of Worship",
            "subcategory":"Church",
            "type":"Public Place"
        },
        {
            "category":"Place Of Worship",
            "type":"Public Place"
        }
    ],
    "sg:phone":"+1 561 924 0026",
    "sg:postcode":"33476",
    "sg:province":"FL",
    "sg:tags":[
        "churches-seventh-day",
        "adventist",
        "christian",
        "churches-advent"
    ],
    "wof:name":"Pahokee Seventh Day Adventist",
    "wof:placetype":"venue"
},
  "geometry": {"coordinates":[-80.65782799999999,26.828366],"type":"Point"}
}