{
  "type": "Feature",
  "properties": {
    "addr:full":"8408 NW 17th St Doral FL 33126",
    "addr:housenumber":"8408",
    "addr:postcode":"33126",
    "addr:street":"Nw 17Th St",
    "iso:country":"US",
    "sg:address":"8408 NW 17th St",
    "sg:city":"Doral",
    "sg:classifiers":[
        {
            "category":"Shopping",
            "subcategory":"Computers & Home Electronics",
            "type":"Retail Goods"
        }
    ],
    "sg:phone":"+1 305 418 4645",
    "sg:postcode":"33126",
    "sg:province":"FL",
    "sg:tags":[
        "hardware",
        "supply"
    ],
    "sg:website":"http://www.mollsystem.com",
    "wof:name":"Moll Systems Corp",
    "wof:placetype":"venue"
},
  "geometry": {"coordinates":[-80.333714,25.789826],"type":"Point"}
}