{
  "type": "Feature",
  "properties": {
    "addr:full":"2496 Indian Springs Rd Marianna FL 32446",
    "addr:housenumber":"2496",
    "addr:postcode":"32446",
    "addr:street":"Indian Springs Rd",
    "iso:country":"US",
    "sg:address":"2496 Indian Springs Rd",
    "sg:city":"Marianna",
    "sg:classifiers":[
        {
            "category":"Building & Trades",
            "subcategory":"Construction",
            "type":"Services"
        }
    ],
    "sg:phone":"+1 850 526 1964",
    "sg:postcode":"32446",
    "sg:province":"FL",
    "sg:tags":[
        "house",
        "contractor"
    ],
    "wof:name":"Ted Tyus Construction Co Inc",
    "wof:placetype":"venue"
},
  "geometry": {"coordinates":[-85.17214300000001,30.749175],"type":"Point"}
}