{
  "type": "Feature",
  "properties": {
    "iso:country":"US",
    "sg:address":"3357 NW 97th Ave",
    "sg:city":"Miami",
    "sg:classifiers":[
        {
            "category":"Shopping",
            "subcategory":"Computers & Home Electronics",
            "type":"Retail Goods"
        }
    ],
    "sg:phone":"+1 305 477 9282",
    "sg:postcode":"33172",
    "sg:province":"FL",
    "sg:tags":[
        "consumer",
        "appliance"
    ],
    "wof:name":"Bush & Cohen",
    "wof:placetype":"venue"
},
  "geometry": {"coordinates":[-80.353171,25.800614],"type":"Point"}
}