{
  "type": "Feature",
  "properties": {
    "addr:full":"3300 Shamrock St E Tallahassee FL 32309",
    "addr:housenumber":"3300",
    "addr:postcode":"32309",
    "addr:street":"Shamrock St",
    "iso:country":"US",
    "sg:address":"3300 Shamrock St E",
    "sg:city":"Tallahassee",
    "sg:classifiers":[
        {
            "category":"Organizations",
            "subcategory":"Religious Organization",
            "type":"Services"
        }
    ],
    "sg:phone":"+1 850 893 1709",
    "sg:postcode":"32309",
    "sg:province":"FL",
    "sg:tags":[
        "church"
    ],
    "sg:website":"www.icelebration.org",
    "wof:name":"Celebration Baptist Church",
    "wof:placetype":"venue"
},
  "geometry": {"coordinates":[-84.202595,30.516035],"type":"Point"}
}