{
  "type": "Feature",
  "properties": {
    "addr:full":"1372 Gibralter St SW Palm Bay FL 32908",
    "addr:housenumber":"1372",
    "addr:postcode":"32908",
    "addr:street":"Gibralter St Sw",
    "iso:country":"US",
    "sg:address":"1372 Gibralter St SW",
    "sg:city":"Palm Bay",
    "sg:classifiers":[
        {
            "category":"Building & Trades",
            "subcategory":"Construction",
            "type":"Services"
        }
    ],
    "sg:phone":"+1 321 676 6564",
    "sg:postcode":"32908",
    "sg:province":"FL",
    "sg:tags":[
        "handyman"
    ],
    "wof:name":"Do Handyman Svc",
    "wof:placetype":"venue"
},
  "geometry": {"coordinates":[-80.71113,27.979718],"type":"Point"}
}