{
  "type": "Feature",
  "properties": {
    "addr:full":"3309 Royal Canadian Trce Fort Myers FL 33907",
    "addr:housenumber":"3309",
    "addr:postcode":"33907",
    "addr:street":"Royal Canadian Trce",
    "iso:country":"US",
    "sg:address":"3309 Royal Canadian Trce",
    "sg:city":"Fort Myers",
    "sg:classifiers":[
        {
            "category":"Building & Trades",
            "subcategory":"Cleaning & Sanitation",
            "type":"Services"
        }
    ],
    "sg:phone":"+1 239 839 9375",
    "sg:postcode":"33907",
    "sg:province":"FL",
    "sg:tags":[
        "maintenance"
    ],
    "wof:name":"Timothy J Melich Inc",
    "wof:placetype":"venue"
},
  "geometry": {"coordinates":[-81.88059,26.555],"type":"Point"}
}