{
  "type": "Feature",
  "properties": {
    "addr:full":"7663 2nd Ter Lake Worth FL 33463",
    "addr:housenumber":"7663",
    "addr:postcode":"33463",
    "addr:street":"2Nd Ter",
    "iso:country":"US",
    "sg:address":"7663 2nd Ter",
    "sg:city":"Lake Worth",
    "sg:classifiers":[
        {
            "category":"Building & Trades",
            "subcategory":"Electrical",
            "type":"Services"
        }
    ],
    "sg:phone":"+1 561 967 6022",
    "sg:postcode":"33463",
    "sg:province":"FL",
    "sg:tags":[
        "electrical",
        "contractor"
    ],
    "wof:name":"Contact Electric",
    "wof:placetype":"venue"
},
  "geometry": {"coordinates":[-80.120347,26.562171],"type":"Point"}
}