{
  "type": "Feature",
  "properties": {
    "addr:full":"12304 Coronado Dr Spring Hill FL 34609",
    "addr:housenumber":"12304",
    "addr:postcode":"34609",
    "addr:street":"Coronado Dr",
    "iso:country":"US",
    "sg:address":"12304 Coronado Dr",
    "sg:city":"Spring Hill",
    "sg:classifiers":[
        {
            "category":"Shopping",
            "subcategory":"Discount & Variety Stores",
            "type":"Retail Goods"
        }
    ],
    "sg:phone":"+1 352 684 2277",
    "sg:postcode":"34609",
    "sg:province":"FL",
    "sg:tags":[
        "merchandise",
        "general"
    ],
    "wof:name":"Hatfield Dad",
    "wof:placetype":"venue"
},
  "geometry": {"coordinates":[-82.526118,28.45855],"type":"Point"}
}