{
  "type": "Feature",
  "properties": {
    "iso:country":"US",
    "sg:address":"31337 Skyline Dr",
    "sg:city":"De Land",
    "sg:classifiers":[
        {
            "category":"Building & Trades",
            "subcategory":"Construction",
            "type":"Services"
        }
    ],
    "sg:phone":"+1 352 669 2999",
    "sg:postcode":"32720",
    "sg:province":"FL",
    "sg:tags":[
        "contractor"
    ],
    "wof:name":"Kevin E Dolan & Sons Drywall",
    "wof:placetype":"venue"
},
  "geometry": {"coordinates":[-81.435636,29.000929],"type":"Point"}
}