{
  "type": "Feature",
  "properties": {
    "iso:country":"US",
    "sg:address":"121 Jane Creek Dr",
    "sg:city":"Geneva",
    "sg:classifiers":[
        {
            "category":"Building & Trades",
            "subcategory":"Construction",
            "type":"Services"
        }
    ],
    "sg:phone":"+1 407 349 0881",
    "sg:postcode":"32732",
    "sg:province":"FL",
    "sg:tags":[
        "carpentry",
        "contractor"
    ],
    "wof:name":"Carpentry Southern & Cons",
    "wof:placetype":"venue"
},
  "geometry": {"coordinates":[-81.071152,28.72922],"type":"Point"}
}