{
  "type": "Feature",
  "properties": {
    "iso:country":"US",
    "sg:address":"1255 Viscaya Pkwy",
    "sg:city":"Cape Coral",
    "sg:classifiers":[
        {
            "category":"Health Services",
            "subcategory":"Doctor",
            "type":"Services"
        }
    ],
    "sg:phone":"+1 239 574 1988",
    "sg:postcode":"33990",
    "sg:province":"FL",
    "sg:tags":[
        "practice",
        "family"
    ],
    "sg:website":"www.ppcswfl.com",
    "wof:name":"Curtis Charles H MD",
    "wof:placetype":"venue"
},
  "geometry": {"coordinates":[-81.947158,26.636614],"type":"Point"}
}