{
  "type": "Feature",
  "properties": {
    "iso:country":"US",
    "sg:address":"2864 Bay Oaks Dr",
    "sg:city":"Sarasota",
    "sg:classifiers":[
        {
            "category":"Shopping",
            "subcategory":"Bicycles & Sporting Goods",
            "type":"Retail Goods"
        }
    ],
    "sg:phone":"+1 941 360 9506",
    "sg:postcode":"34234",
    "sg:province":"FL",
    "wof:name":"Ko Sport First Inc",
    "wof:placetype":"venue"
},
  "geometry": {"coordinates":[-82.51331399999999,27.361228],"type":"Point"}
}