{
  "type": "Feature",
  "properties": {
    "addr:full":"6220 US Hwy 98 Lakeland FL 33809",
    "addr:housenumber":"6220",
    "addr:postcode":"33809",
    "addr:street":"Us Hwy 98",
    "iso:country":"US",
    "sg:address":"6220 US Hwy 98",
    "sg:city":"Lakeland",
    "sg:classifiers":[
        {
            "category":"Food & Beverages",
            "subcategory":"Groceries & Convenience Stores",
            "type":"Retail Goods"
        }
    ],
    "sg:phone":"+1 863 858 7597",
    "sg:postcode":"33809",
    "sg:province":"FL",
    "sg:tags":[
        "grocer"
    ],
    "sg:website":"www.kashnkarry.com",
    "wof:name":"KASH N' Karry",
    "wof:placetype":"venue"
},
  "geometry": {"coordinates":[-81.97375599999999,28.124415],"type":"Point"}
}