{
  "type": "Feature",
  "properties": {
    "addr:full":"3670 N L St Pensacola FL 32505",
    "addr:housenumber":"3670",
    "addr:postcode":"32505",
    "addr:street":"N L St",
    "iso:country":"US",
    "sg:address":"3670 N L St",
    "sg:city":"Pensacola",
    "sg:classifiers":[
        {
            "category":"Government",
            "subcategory":"Office",
            "type":"Public Place"
        }
    ],
    "sg:phone":"+1 850 595 5170",
    "sg:postcode":"32505",
    "sg:province":"FL",
    "sg:website":"http://www.floridagovernmentonline.com",
    "wof:name":"Taxation Office",
    "wof:placetype":"venue"
},
  "geometry": {"coordinates":[-87.235707,30.448546],"type":"Point"}
}