{
  "type": "Feature",
  "properties": {
    "addr:full":"1303 Carpenter Branch Ct Oviedo FL 32765",
    "addr:housenumber":"1303",
    "addr:postcode":"32765",
    "addr:street":"Carpenter Branch Ct",
    "iso:country":"US",
    "sg:address":"1303 Carpenter Branch Ct",
    "sg:city":"Oviedo",
    "sg:classifiers":[
        {
            "category":"Building & Trades",
            "subcategory":"Cleaning & Sanitation",
            "type":"Services"
        }
    ],
    "sg:phone":"+1 407 977 1561",
    "sg:postcode":"32765",
    "sg:province":"FL",
    "sg:tags":[
        "maintenance"
    ],
    "wof:name":"Spirit Janitorial Service",
    "wof:placetype":"venue"
},
  "geometry": {"coordinates":[-81.175411,28.640247],"type":"Point"}
}