{
  "type": "Feature",
  "properties": {
    "iso:country":"US",
    "sg:address":"5841 Medinah Way",
    "sg:city":"Orlando",
    "sg:classifiers":[
        {
            "category":"Professional",
            "subcategory":"Computer Services",
            "type":"Services"
        }
    ],
    "sg:phone":"+1 407 909 9715",
    "sg:postcode":"32819",
    "sg:province":"FL",
    "sg:tags":[
        "publisher",
        "software",
        "developer"
    ],
    "wof:name":"Dewight Hooper",
    "wof:placetype":"venue"
},
  "geometry": {"coordinates":[-81.50492300000001,28.466599],"type":"Point"}
}