{
  "type": "Feature",
  "properties": {
    "iso:country":"US",
    "sg:address":"2880 Aragon Ter",
    "sg:city":"Lake Mary",
    "sg:classifiers":[
        {
            "category":"Travel",
            "subcategory":"Travel Agent",
            "type":"Entertainment"
        }
    ],
    "sg:phone":"+1 407 688 8018",
    "sg:postcode":"32746",
    "sg:province":"FL",
    "sg:tags":[
        "agency",
        "bureau"
    ],
    "wof:name":"Us A Travel",
    "wof:placetype":"venue"
},
  "geometry": {"coordinates":[-81.304759,28.776081],"type":"Point"}
}