{
  "type": "Feature",
  "properties": {
    "addr:full":"3824 Stonemont Dr Cocoa FL 32926",
    "addr:housenumber":"3824",
    "addr:postcode":"32926",
    "addr:street":"Stonemont Dr",
    "iso:country":"US",
    "sg:address":"3824 Stonemont Dr",
    "sg:city":"Cocoa",
    "sg:classifiers":[
        {
            "category":"Professional",
            "subcategory":"Business Services",
            "type":"Services"
        }
    ],
    "sg:phone":"+1 321 636 2686",
    "sg:postcode":"32926",
    "sg:province":"FL",
    "sg:tags":[
        "trade",
        "contractor"
    ],
    "wof:name":"Actions Resurfacing & Hm Imprv",
    "wof:placetype":"venue"
},
  "geometry": {"coordinates":[-80.78185999999999,28.393241],"type":"Point"}
}