{
  "type": "Feature",
  "properties": {
    "addr:full":"621 S Collins St Plant City FL 33563",
    "addr:housenumber":"621",
    "addr:postcode":"33563",
    "addr:street":"S Collins St",
    "iso:country":"US",
    "sg:address":"621 S Collins St",
    "sg:city":"Plant City",
    "sg:classifiers":[
        {
            "category":"Personal",
            "subcategory":"Beauty Salon",
            "type":"Services"
        }
    ],
    "sg:phone":"+1 813 759 0022",
    "sg:postcode":"33563",
    "sg:province":"FL",
    "sg:tags":[
        "shop",
        "fitness",
        "physical",
        "facility"
    ],
    "wof:name":"Family Hair Affair",
    "wof:placetype":"venue"
},
  "geometry": {"coordinates":[-82.12204800000001,28.009712],"type":"Point"}
}