{
  "type": "Feature",
  "properties": {
    "iso:country":"US",
    "sg:address":"3682 N Wickham Rd",
    "sg:city":"Melbourne",
    "sg:classifiers":[
        {
            "category":"Shopping",
            "subcategory":"Clothing, Apparel, & Fashions",
            "type":"Retail Goods"
        }
    ],
    "sg:phone":"+1 321 254 8001",
    "sg:postcode":"32935",
    "sg:province":"FL",
    "sg:tags":[
        "item",
        "boutique"
    ],
    "wof:name":"ETC",
    "wof:placetype":"venue"
},
  "geometry": {"coordinates":[-80.672034,28.16307],"type":"Point"}
}