{
  "type": "Feature",
  "properties": {
    "addr:full":"90 S Hwy 17/92 De Bary FL 32750",
    "addr:housenumber":"90;92",
    "addr:postcode":"32750",
    "addr:street":"S Hwy 17 /;De Bary",
    "iso:country":"US",
    "sg:address":"90 S Hwy 17/92",
    "sg:city":"De Bary",
    "sg:classifiers":[
        {
            "category":"Retail",
            "subcategory":"Auto Repair",
            "type":"Services"
        }
    ],
    "sg:phone":"+1 386 668 4931",
    "sg:postcode":"32750",
    "sg:province":"FL",
    "wof:name":"Debary Auto Service Inc",
    "wof:placetype":"venue"
},
  "geometry": {"coordinates":[-81.327146,28.697365],"type":"Point"}
}