{
  "type": "Feature",
  "properties": {
    "iso:country":"US",
    "sg:address":"6013 SE Hames Rd",
    "sg:city":"Belleview",
    "sg:classifiers":[
        {
            "category":"Personal",
            "subcategory":"Beauty Salon",
            "type":"Services"
        }
    ],
    "sg:phone":"+1 352 245 9255",
    "sg:postcode":"34420",
    "sg:province":"FL",
    "wof:name":"Helen's Beauty Salon",
    "wof:placetype":"venue"
},
  "geometry": {"coordinates":[-82.04979899999999,29.061382],"type":"Point"}
}