{
  "type": "Feature",
  "properties": {
    "iso:country":"US",
    "sg:address":"1413 E Scott St",
    "sg:city":"Pensacola",
    "sg:classifiers":[
        {
            "category":"Personal",
            "subcategory":"Beauty Salon",
            "type":"Services"
        }
    ],
    "sg:phone":"+1 850 432 1173",
    "sg:postcode":"32503",
    "sg:province":"FL",
    "wof:name":"D R Hair Studio",
    "wof:placetype":"venue"
},
  "geometry": {"coordinates":[-87.20200199999999,30.440554],"type":"Point"}
}