{
  "type": "Feature",
  "properties": {
    "addr:full":"4230 Sb Merrion Rd Lakeland FL 33810",
    "addr:postcode":"4230 sb;33810",
    "addr:street":"Merrion Rd",
    "iso:country":"US",
    "sg:address":"4230 Sb Merrion Rd",
    "sg:city":"Lakeland",
    "sg:classifiers":[
        {
            "category":"Place Of Worship",
            "type":"Public Place"
        }
    ],
    "sg:phone":"+1 863 858 0663",
    "sg:postcode":"33810",
    "sg:province":"FL",
    "sg:tags":[
        "church"
    ],
    "wof:name":"John Wesley Borders",
    "wof:placetype":"venue"
},
  "geometry": {"coordinates":[-82.02941199999999,28.164552],"type":"Point"}
}