{
  "type": "Feature",
  "properties": {
    "iso:country":"US",
    "sg:address":"13301 NW Miami Ct",
    "sg:city":"North Miami",
    "sg:classifiers":[
        {
            "category":"Retail",
            "subcategory":"Veterinary Services",
            "type":"Services"
        }
    ],
    "sg:phone":"+1 305 685 0095",
    "sg:postcode":"33168",
    "sg:province":"FL",
    "sg:tags":[
        "veterinarian"
    ],
    "wof:name":"Avenue Animal Clinic",
    "wof:placetype":"venue"
},
  "geometry": {"coordinates":[-80.19996500000001,25.896951],"type":"Point"}
}