{
  "type": "Feature",
  "properties": {
    "addr:full":"504 Martin Luther King Jr Stuart FL 34994",
    "addr:housenumber":"504",
    "addr:postcode":"34994",
    "addr:street":"Martin Luther King Jr",
    "iso:country":"US",
    "sg:address":"504 Martin Luther King Jr",
    "sg:city":"Stuart",
    "sg:classifiers":[
        {
            "category":"Shopping",
            "subcategory":"Clothing, Apparel, & Fashions",
            "type":"Retail Goods"
        }
    ],
    "sg:phone":"+1 772 287 3837",
    "sg:postcode":"34994",
    "sg:province":"FL",
    "sg:tags":[
        "hair",
        "supply"
    ],
    "wof:name":"Tip Top Mini Mart",
    "wof:placetype":"venue"
},
  "geometry": {"coordinates":[-80.245136,27.193769],"type":"Point"}
}