{
  "type": "Feature",
  "properties": {
    "addr:full":"108 Palo de Oro Dr Islamorada FL 33036",
    "addr:housenumber":"108",
    "addr:postcode":"33036",
    "addr:street":"Palo De Oro Dr",
    "iso:country":"US",
    "sg:address":"108 Palo de Oro Dr",
    "sg:city":"Islamorada",
    "sg:classifiers":[
        {
            "category":"Professional",
            "subcategory":"Business Services",
            "type":"Services"
        }
    ],
    "sg:phone":"+1 305 517 9556",
    "sg:postcode":"33036",
    "sg:province":"FL",
    "sg:tags":[
        "eating"
    ],
    "wof:name":"Subway",
    "wof:placetype":"venue"
},
  "geometry": {"coordinates":[-80.585491,24.958747],"type":"Point"}
}