{
  "type": "Feature",
  "properties": {
    "addr:full":"525 Arthur Godfrey Rd Miami Beach FL 33140",
    "addr:housenumber":"525",
    "addr:postcode":"33140",
    "addr:street":"Arthur Godfrey Rd",
    "iso:country":"US",
    "sg:address":"525 Arthur Godfrey Rd",
    "sg:city":"Miami Beach",
    "sg:classifiers":[
        {
            "category":"Restaurant",
            "type":"Food & Drink"
        }
    ],
    "sg:phone":"+1 305 531 7691",
    "sg:postcode":"33140",
    "sg:province":"FL",
    "sg:website":"www.roastersntoasters.com",
    "wof:name":"Roasters & Toasters",
    "wof:placetype":"venue"
},
  "geometry": {"coordinates":[-80.129828,25.813864],"type":"Point"}
}