{
  "type": "Feature",
  "properties": {
    "iso:country":"US",
    "sg:address":"6577 Superior Ave",
    "sg:city":"Sarasota",
    "sg:classifiers":[
        {
            "category":"Professional",
            "subcategory":"Accounting & Tax Preparation",
            "type":"Services"
        }
    ],
    "sg:phone":"+1 941 921 6681",
    "sg:postcode":"34231",
    "sg:province":"FL",
    "wof:name":"6585 Billing Services Inc",
    "wof:placetype":"venue"
},
  "geometry": {"coordinates":[-82.51548200000001,27.259864],"type":"Point"}
}