{
  "type": "Feature",
  "properties": {
    "iso:country":"US",
    "sg:address":"4497 US Hwy 1",
    "sg:city":"Edgewater",
    "sg:classifiers":[
        {
            "category":"Autos & Motor Vehicles",
            "subcategory":"Boat Sales",
            "type":"Retail Goods"
        }
    ],
    "sg:phone":"+1 386 345 3633",
    "sg:postcode":"32141",
    "sg:province":"FL",
    "sg:tags":[
        "repair",
        "accessory",
        "sales",
        "dealer"
    ],
    "sg:website":"www.ggmarinecenter.com",
    "wof:name":"G & G Marine Center Inc",
    "wof:placetype":"venue"
},
  "geometry": {"coordinates":[-80.86679700000001,28.909516],"type":"Point"}
}