{
  "type": "Feature",
  "properties": {
    "addr:full":"12311 Lillian Hwy Pensacola FL 32506",
    "addr:housenumber":"12311",
    "addr:postcode":"32506",
    "addr:street":"Lillian Hwy",
    "iso:country":"US",
    "sg:address":"12311 Lillian Hwy",
    "sg:city":"Pensacola",
    "sg:classifiers":[
        {
            "category":"Food & Beverages",
            "subcategory":"Groceries & Convenience Stores",
            "type":"Retail Goods"
        }
    ],
    "sg:phone":"+1 850 453 8534",
    "sg:postcode":"32506",
    "sg:province":"FL",
    "sg:tags":[
        "station",
        "gasoline"
    ],
    "wof:name":"Tom Thumb 111",
    "wof:placetype":"venue"
},
  "geometry": {"coordinates":[-87.402106,30.39768],"type":"Point"}
}