{
  "type": "Feature",
  "properties": {
    "addr:full":"2400 Hartridge Point Dr W Winter Haven FL 33881",
    "addr:housenumber":"2400",
    "addr:postcode":"33881",
    "addr:street":"Hartridge Point Dr W",
    "iso:country":"US",
    "sg:address":"2400 Hartridge Point Dr W",
    "sg:city":"Winter Haven",
    "sg:classifiers":[
        {
            "category":"Professional",
            "type":"Services"
        }
    ],
    "sg:phone":"+1 863 298 9869",
    "sg:postcode":"33881",
    "sg:province":"FL",
    "wof:name":"Tibados Country Cupboard",
    "wof:placetype":"venue"
},
  "geometry": {"coordinates":[-81.75102099999999,28.052747],"type":"Point"}
}