{
  "type": "Feature",
  "properties": {
    "iso:country":"US",
    "sg:address":"876 Grand Hughey Ct",
    "sg:city":"Apopka",
    "sg:classifiers":[
        {
            "category":"Real Estate",
            "subcategory":"Real Estate Services",
            "type":"Services"
        },
        {
            "category":"Real Estate",
            "subcategory":"Real Estate Agent",
            "type":"Services"
        }
    ],
    "sg:phone":"+1 407 257 6230",
    "sg:postcode":"32712",
    "sg:province":"FL",
    "sg:tags":[
        "buyer",
        "broker"
    ],
    "wof:name":"Paulette Daaron Gabbidon Realt",
    "wof:placetype":"venue"
},
  "geometry": {"coordinates":[-81.526791,28.714922],"type":"Point"}
}