{
  "type": "Feature",
  "properties": {
    "addr:full":"1100 Oak Ridge Rd Saint Augustine FL 32086",
    "addr:housenumber":"1100",
    "addr:postcode":"32086",
    "addr:street":"Oak Ridge Rd",
    "iso:country":"US",
    "sg:address":"1100 Oak Ridge Rd",
    "sg:city":"Saint Augustine",
    "sg:classifiers":[
        {
            "category":"Retail",
            "subcategory":"Veterinary Services",
            "type":"Services"
        }
    ],
    "sg:phone":"+1 904 794 7946",
    "sg:postcode":"32086",
    "sg:province":"FL",
    "wof:name":"Animal House Calls",
    "wof:placetype":"venue"
},
  "geometry": {"coordinates":[-81.346647,29.838283],"type":"Point"}
}