{
  "type": "Feature",
  "properties": {
    "addr:full":"121 Louise Dr Crestview FL 32536",
    "addr:housenumber":"121",
    "addr:postcode":"32536",
    "addr:street":"Louise Dr",
    "iso:country":"US",
    "sg:address":"121 Louise Dr",
    "sg:city":"Crestview",
    "sg:classifiers":[
        {
            "category":"Professional",
            "subcategory":"Computer Services",
            "type":"Services"
        }
    ],
    "sg:phone":"+1 850 689 0877",
    "sg:postcode":"32536",
    "sg:province":"FL",
    "sg:tags":[
        "programing",
        "custom"
    ],
    "wof:name":"Joe Hecht Associates",
    "wof:placetype":"venue"
},
  "geometry": {"coordinates":[-86.593846,30.713197],"type":"Point"}
}