{
  "type": "Feature",
  "properties": {
    "iso:country":"US",
    "sg:address":"2155 N Dixie Hwy",
    "sg:city":"Fort Lauderdale",
    "sg:classifiers":[
        {
            "category":"Shopping",
            "subcategory":"Used Merchandise",
            "type":"Retail Goods"
        }
    ],
    "sg:phone":"+1 954 563 0603",
    "sg:postcode":"33305",
    "sg:province":"FL",
    "sg:tags":[
        "antique"
    ],
    "wof:name":"Bobby V's Antiques",
    "wof:placetype":"venue"
},
  "geometry": {"coordinates":[-80.133146,26.155228],"type":"Point"}
}