{
  "type": "Feature",
  "properties": {
    "addr:full":"4902 Eisenhower Blvd N Tampa FL 33634",
    "addr:housenumber":"4902",
    "addr:postcode":"33634",
    "addr:street":"Eisenhower Blvd N",
    "iso:country":"US",
    "sg:address":"4902 Eisenhower Blvd N",
    "sg:city":"Tampa",
    "sg:classifiers":[
        {
            "category":"Insurance",
            "subcategory":"Health Insurance",
            "type":"Services"
        },
        {
            "category":"Insurance",
            "subcategory":"Insurance Agent",
            "type":"Services"
        }
    ],
    "sg:phone":"+1 813 888 8255",
    "sg:postcode":"33634",
    "sg:province":"FL",
    "sg:tags":[
        "consultant",
        "company"
    ],
    "wof:name":"Lincoln General Insurance Co",
    "wof:placetype":"venue"
},
  "geometry": {"coordinates":[-82.545483,27.99454],"type":"Point"}
}