{
  "type": "Feature",
  "properties": {
    "addr:full":"3780 Sweepstakes Ct Palm Harbor FL 34684",
    "addr:housenumber":"3780",
    "addr:postcode":"34684",
    "addr:street":"Sweepstakes Ct",
    "iso:country":"US",
    "sg:address":"3780 Sweepstakes Ct",
    "sg:city":"Palm Harbor",
    "sg:classifiers":[
        {
            "category":"Insurance",
            "subcategory":"Insurance Agent",
            "type":"Services"
        }
    ],
    "sg:phone":"+1 727 771 1348",
    "sg:postcode":"34684",
    "sg:province":"FL",
    "wof:name":"George E Lufkin",
    "wof:placetype":"venue"
},
  "geometry": {"coordinates":[-82.71616,28.064378],"type":"Point"}
}