{
  "type": "Feature",
  "properties": {
    "addr:full":"2007 Hibernia Ct Jacksonville FL 32223",
    "addr:housenumber":"2007",
    "addr:postcode":"32223",
    "addr:street":"Hibernia Ct",
    "iso:country":"US",
    "sg:address":"2007 Hibernia Ct",
    "sg:city":"Jacksonville",
    "sg:classifiers":[
        {
            "category":"Building & Trades",
            "subcategory":"Construction",
            "type":"Services"
        }
    ],
    "sg:phone":"+1 904 260 6737",
    "sg:postcode":"32223",
    "sg:province":"FL",
    "sg:tags":[
        "contractor"
    ],
    "wof:name":"Eugene Joy Jr Contractor",
    "wof:placetype":"venue"
},
  "geometry": {"coordinates":[-81.65228,30.146063],"type":"Point"}
}