{
  "type": "Feature",
  "properties": {
    "iso:country":"US",
    "sg:address":"955 25th Ct",
    "sg:city":"West Palm Beach",
    "sg:classifiers":[
        {
            "category":"Building & Trades",
            "subcategory":"Landscaping Services",
            "type":"Services"
        }
    ],
    "sg:phone":"+1 561 832 0519",
    "sg:postcode":"33407",
    "sg:province":"FL",
    "wof:name":"Schmidt Stump Removal",
    "wof:placetype":"venue"
},
  "geometry": {"coordinates":[-80.062208,26.736859],"type":"Point"}
}