{
  "type": "Feature",
  "properties": {
    "addr:full":"2901 S Pine Ridge Ave Homosassa FL 34448",
    "addr:housenumber":"2901",
    "addr:postcode":"34448",
    "addr:street":"S Pine Ridge Ave",
    "iso:country":"US",
    "sg:address":"2901 S Pine Ridge Ave",
    "sg:city":"Homosassa",
    "sg:classifiers":[
        {
            "category":"Building & Trades",
            "subcategory":"Pest Control",
            "type":"Services"
        }
    ],
    "sg:phone":"+1 352 628 4300",
    "sg:postcode":"34448",
    "sg:province":"FL",
    "sg:tags":[
        "mothproofing"
    ],
    "wof:name":"Brenda B's Bugs & Pest Control",
    "wof:placetype":"venue"
},
  "geometry": {"coordinates":[-82.543037,28.820299],"type":"Point"}
}