{
  "type": "Feature",
  "properties": {
    "addr:full":"133 Pine Hammock Ct Jupiter FL 33458",
    "addr:housenumber":"133",
    "addr:postcode":"33458",
    "addr:street":"Pine Hammock Ct",
    "iso:country":"US",
    "sg:address":"133 Pine Hammock Ct",
    "sg:city":"Jupiter",
    "sg:classifiers":[
        {
            "category":"Building & Trades",
            "subcategory":"Construction",
            "type":"Services"
        }
    ],
    "sg:phone":"+1 561 747 5575",
    "sg:postcode":"33458",
    "sg:province":"FL",
    "sg:tags":[
        "contractor"
    ],
    "wof:name":"Ultimate Mobility Designs Inc",
    "wof:placetype":"venue"
},
  "geometry": {"coordinates":[-80.108346,26.929721],"type":"Point"}
}