{
  "type": "Feature",
  "properties": {
    "iso:country":"US",
    "sg:address":"584 Santa Clara Trl",
    "sg:city":"Wellington",
    "sg:classifiers":[
        {
            "category":"Wholesale",
            "subcategory":"Electrical",
            "type":"Manufacturing & Wholesale Goods"
        }
    ],
    "sg:phone":"+1 561 753 4374",
    "sg:postcode":"33414",
    "sg:province":"FL",
    "sg:tags":[
        "alarm",
        "burglar",
        "system"
    ],
    "wof:name":"Security Resources",
    "wof:placetype":"venue"
},
  "geometry": {"coordinates":[-80.253895,26.672425],"type":"Point"}
}