{
  "type": "Feature",
  "properties": {
    "addr:full":"6701 Sunset Dr Ste 114 South Miami FL 33143",
    "addr:housenumber":"6701",
    "addr:postcode":"33143",
    "addr:street":"Sunset Dr Ste 114",
    "iso:country":"US",
    "sg:address":"6701 Sunset Dr Ste 114",
    "sg:city":"South Miami",
    "sg:classifiers":[
        {
            "category":"Health Services",
            "subcategory":"Doctor",
            "type":"Services"
        }
    ],
    "sg:phone":"+1 305 666 4334",
    "sg:postcode":"33143",
    "sg:province":"FL",
    "sg:tags":[
        "surgeon",
        "oral"
    ],
    "wof:name":"Moo Young Paul W DDS",
    "wof:placetype":"venue"
},
  "geometry": {"coordinates":[-80.302299,25.7038],"type":"Point"}
}