{
  "type": "Feature",
  "properties": {
    "addr:full":"123 Vera Ln NW Lake Placid FL 33852",
    "addr:housenumber":"123",
    "addr:postcode":"33852",
    "addr:street":"Vera Ln Nw",
    "iso:country":"US",
    "sg:address":"123 Vera Ln NW",
    "sg:city":"Lake Placid",
    "sg:classifiers":[
        {
            "category":"Building & Trades",
            "subcategory":"Electrical",
            "type":"Services"
        }
    ],
    "sg:phone":"+1 863 465 1506",
    "sg:postcode":"33852",
    "sg:province":"FL",
    "sg:tags":[
        "electrical",
        "contractor"
    ],
    "wof:name":"Franks Electrical Service",
    "wof:placetype":"venue"
},
  "geometry": {"coordinates":[-81.41033899999999,27.279734],"type":"Point"}
}