{
  "type": "Feature",
  "properties": {
    "addr:full":"137 W Marion Ave Edgewater FL 32132",
    "addr:housenumber":"137",
    "addr:postcode":"32132",
    "addr:street":"W Marion Ave",
    "iso:country":"US",
    "sg:address":"137 W Marion Ave",
    "sg:city":"Edgewater",
    "sg:classifiers":[
        {
            "category":"Manufacturing",
            "subcategory":"Retail Goods",
            "type":"Manufacturing & Wholesale Goods"
        }
    ],
    "sg:phone":"+1 386 424 1900",
    "sg:postcode":"32132",
    "sg:province":"FL",
    "sg:tags":[
        "product",
        "mfg"
    ],
    "wof:name":"Renaissance Source",
    "wof:placetype":"venue"
},
  "geometry": {"coordinates":[-80.900485,28.977132],"type":"Point"}
}