{
  "type": "Feature",
  "properties": {
    "addr:full":"1730 Dunlawton Ave Port Orange FL 32127",
    "addr:housenumber":"1730",
    "addr:postcode":"32127",
    "addr:street":"Dunlawton Ave",
    "iso:country":"US",
    "sg:address":"1730 Dunlawton Ave",
    "sg:city":"Port Orange",
    "sg:classifiers":[
        {
            "category":"Education",
            "subcategory":"Special Training",
            "type":"Public Place"
        }
    ],
    "sg:phone":"+1 386 756 1511",
    "sg:postcode":"32127",
    "sg:province":"FL",
    "sg:tags":[
        "tutoring"
    ],
    "sg:website":"www.sylvanvolusia.com",
    "wof:name":"Sylvan Learning Ctr",
    "wof:placetype":"venue"
},
  "geometry": {"coordinates":[-81.02594999999999,29.110081],"type":"Point"}
}