{
  "type": "Feature",
  "properties": {
    "addr:full":"910 Lincoln Road Miami Beach FL 33139",
    "addr:housenumber":"910",
    "addr:postcode":"33139",
    "addr:street":"Lincoln Road",
    "iso:country":"US",
    "sg:address":"910 Lincoln Road",
    "sg:city":"Miami Beach",
    "sg:classifiers":[
        {
            "category":"Restaurant",
            "type":"Food & Drink"
        }
    ],
    "sg:phone":"+1 305 534 5511",
    "sg:postcode":"33139",
    "sg:province":"FL",
    "wof:name":"South Beach Brasserie",
    "wof:placetype":"venue"
},
  "geometry": {"coordinates":[-80.137901,25.7903],"type":"Point"}
}