{
  "type": "Feature",
  "properties": {
    "addr:full":"792 NE 40th Ct Fort Lauderdale FL 33334",
    "addr:housenumber":"792",
    "addr:postcode":"33334",
    "addr:street":"Ne 40Th Ct",
    "iso:country":"US",
    "sg:address":"792 NE 40th Ct",
    "sg:city":"Fort Lauderdale",
    "sg:classifiers":[
        {
            "category":"Building & Trades",
            "subcategory":"Construction",
            "type":"Services"
        }
    ],
    "sg:phone":"+1 954 564 6560",
    "sg:postcode":"33334",
    "sg:province":"FL",
    "sg:tags":[
        "plain",
        "plastering",
        "contractor"
    ],
    "wof:name":"Israels Brothers Plastering",
    "wof:placetype":"venue"
},
  "geometry": {"coordinates":[-80.136791,26.176663],"type":"Point"}
}