{
  "type": "Feature",
  "properties": {
    "addr:full":"605 E Terrace Dr Plant City FL 33563",
    "addr:housenumber":"605",
    "addr:postcode":"33563",
    "addr:street":"E Terrace Dr",
    "iso:country":"US",
    "sg:address":"605 E Terrace Dr",
    "sg:city":"Plant City",
    "sg:classifiers":[
        {
            "category":"Retail",
            "subcategory":"Auto Repair",
            "type":"Services"
        }
    ],
    "sg:phone":"+1 813 752 8646",
    "sg:postcode":"33563",
    "sg:province":"FL",
    "sg:tags":[
        "repairing",
        "automobile"
    ],
    "wof:name":"Tom's Automotive",
    "wof:placetype":"venue"
},
  "geometry": {"coordinates":[-82.117816,28.040204],"type":"Point"}
}