{
  "type": "Feature",
  "properties": {
    "addr:full":"3920 Freeman Rd Jacksonville FL 32207",
    "addr:housenumber":"3920",
    "addr:postcode":"32207",
    "addr:street":"Freeman Rd",
    "iso:country":"US",
    "sg:address":"3920 Freeman Rd",
    "sg:city":"Jacksonville",
    "sg:classifiers":[
        {
            "category":"Personal",
            "subcategory":"Beauty Salon",
            "type":"Services"
        }
    ],
    "sg:phone":"+1 904 396 6467",
    "sg:postcode":"32207",
    "sg:province":"FL",
    "wof:name":"All About You Hair Design",
    "wof:placetype":"venue"
},
  "geometry": {"coordinates":[-81.63952500000001,30.28389],"type":"Point"}
}