{
  "type": "Feature",
  "properties": {
    "iso:country":"US",
    "sg:address":"1205 S US Hwy 17/92",
    "sg:city":"Longwood",
    "sg:classifiers":[
        {
            "category":"Bars & Pubs",
            "type":"Food & Drink"
        }
    ],
    "sg:phone":"+1 407 696 7024",
    "sg:postcode":"32750",
    "sg:province":"FL",
    "sg:tags":[
        "club",
        "night"
    ],
    "wof:name":"Rendezvous Dance Hall",
    "wof:placetype":"venue"
},
  "geometry": {"coordinates":[-81.328464,28.689971],"type":"Point"}
}