{
  "type": "Feature",
  "properties": {
    "addr:full":"1108 Haymarket Dr Lakeland FL 33809",
    "addr:housenumber":"1108",
    "addr:postcode":"33809",
    "addr:street":"Haymarket Dr",
    "iso:country":"US",
    "sg:address":"1108 Haymarket Dr",
    "sg:city":"Lakeland",
    "sg:classifiers":[
        {
            "category":"Building & Trades",
            "subcategory":"Electrical",
            "type":"Services"
        }
    ],
    "sg:phone":"+1 863 858 5886",
    "sg:postcode":"33809",
    "sg:province":"FL",
    "sg:tags":[
        "electrical",
        "contractor"
    ],
    "wof:name":"Fortin Electric Inc",
    "wof:placetype":"venue"
},
  "geometry": {"coordinates":[-81.934423,28.137104],"type":"Point"}
}