{
  "type": "Feature",
  "properties": {
    "iso:country":"US",
    "sg:address":"1510 Grande Magnolia Ct.",
    "sg:city":"Tallahassee",
    "sg:classifiers":[
        {
            "category":"Building & Trades",
            "subcategory":"Landscaping Services",
            "type":"Services"
        }
    ],
    "sg:phone":"+1 850 320 4196",
    "sg:postcode":"32310",
    "sg:province":"FL",
    "sg:tags":[
        "tree"
    ],
    "wof:name":"Southern Tree & Outdoors LLC>",
    "wof:placetype":"venue"
},
  "geometry": {"coordinates":[-84.425867,30.441491],"type":"Point"}
}