{
  "type": "Feature",
  "properties": {
    "addr:full":"5956 W 16th Ave Hialeah FL 33012",
    "addr:housenumber":"5956",
    "addr:postcode":"33012",
    "addr:street":"W 16Th Ave",
    "iso:country":"US",
    "sg:address":"5956 W 16th Ave",
    "sg:city":"Hialeah",
    "sg:classifiers":[
        {
            "category":"Real Estate",
            "subcategory":"Real Estate Agent",
            "type":"Services"
        }
    ],
    "sg:phone":"+1 305 823 8665",
    "sg:postcode":"33012",
    "sg:province":"FL",
    "wof:name":"Deaco Realty Inc",
    "wof:placetype":"venue"
},
  "geometry": {"coordinates":[-80.315288,25.875584],"type":"Point"}
}