{
  "type": "Feature",
  "properties": {
    "iso:country":"US",
    "sg:address":"7713 SW 8th St",
    "sg:city":"Pompano Beach",
    "sg:classifiers":[
        {
            "category":"Building & Trades",
            "subcategory":"Construction",
            "type":"Services"
        }
    ],
    "sg:phone":"+1 954 721 4598",
    "sg:postcode":"33068",
    "sg:province":"FL",
    "sg:tags":[
        "contractor"
    ],
    "wof:name":"Hollaway Drywall Inc",
    "wof:placetype":"venue"
},
  "geometry": {"coordinates":[-80.22984099999999,26.219964],"type":"Point"}
}