{
  "type": "Feature",
  "properties": {
    "addr:full":"14700 SW 29th St Miramar FL 33027",
    "addr:housenumber":"14700",
    "addr:postcode":"33027",
    "addr:street":"Sw 29Th St",
    "iso:country":"US",
    "sg:address":"14700 SW 29th St",
    "sg:city":"Miramar",
    "sg:classifiers":[
        {
            "category":"Travel",
            "subcategory":"Hotels & Motels",
            "type":"Entertainment"
        }
    ],
    "sg:phone":"+1 954 450 2717",
    "sg:postcode":"33027",
    "sg:province":"FL",
    "sg:website":"http://www.marriott.com/fllmr",
    "wof:name":"Residence Inn-Southwest",
    "wof:placetype":"venue"
},
  "geometry": {"coordinates":[-80.34387599999999,25.982281],"type":"Point"}
}