{
  "type": "Feature",
  "properties": {
    "addr:full":"1600 SE 15th St Fort Lauderdale FL 33316",
    "addr:housenumber":"1600",
    "addr:postcode":"33316",
    "addr:street":"Se 15Th St",
    "iso:country":"US",
    "sg:address":"1600 SE 15th St",
    "sg:city":"Fort Lauderdale",
    "sg:classifiers":[
        {
            "category":"Real Estate",
            "subcategory":"Real Estate Agent",
            "type":"Services"
        }
    ],
    "sg:phone":"+1 954 523 4890",
    "sg:postcode":"33316",
    "sg:province":"FL",
    "wof:name":"Plaza 15 Condominium",
    "wof:placetype":"venue"
},
  "geometry": {"coordinates":[-80.125472,26.103225],"type":"Point"}
}