{
  "type": "Feature",
  "properties": {
    "iso:country":"US",
    "sg:address":"3661 S Miami Ave Ste 509",
    "sg:city":"Miami",
    "sg:classifiers":[
        {
            "category":"Health Services",
            "subcategory":"Doctor",
            "type":"Services"
        }
    ],
    "sg:phone":"+1 305 856 3030",
    "sg:postcode":"33133",
    "sg:province":"FL",
    "sg:tags":[
        "surgeon",
        "cosmetic"
    ],
    "wof:name":"Zaydon Thomas J MD",
    "wof:placetype":"venue"
},
  "geometry": {"coordinates":[-80.216202,25.743299],"type":"Point"}
}