{
  "type": "Feature",
  "properties": {
    "iso:country":"US",
    "sg:address":"905 Brickell Bay Dr",
    "sg:city":"Miami",
    "sg:classifiers":[
        {
            "category":"Shopping",
            "subcategory":"Computers & Home Electronics",
            "type":"Retail Goods"
        }
    ],
    "sg:phone":"+1 305 371 3254",
    "sg:postcode":"33131",
    "sg:province":"FL",
    "sg:tags":[
        "equipment",
        "audio-visual"
    ],
    "wof:name":"Claudio Castillo",
    "wof:placetype":"venue"
},
  "geometry": {"coordinates":[-80.189792,25.764707],"type":"Point"}
}