{
  "type": "Feature",
  "properties": {
    "iso:country":"US",
    "sg:address":"19342 NW 67th Pl",
    "sg:city":"Hialeah",
    "sg:classifiers":[
        {
            "category":"Wholesale",
            "subcategory":"Machinery & Supplies",
            "type":"Manufacturing & Wholesale Goods"
        }
    ],
    "sg:phone":"+1 786 486 4348",
    "sg:postcode":"33015",
    "sg:province":"FL",
    "sg:tags":[
        "aviation",
        "parts"
    ],
    "wof:name":"H & R Aviation International",
    "wof:placetype":"venue"
},
  "geometry": {"coordinates":[-80.309573,25.944809],"type":"Point"}
}