{
  "type": "Feature",
  "properties": {
    "addr:full":"8910 N Military Trl Palm Beach Gardens FL 33410",
    "addr:housenumber":"8910",
    "addr:postcode":"33410",
    "addr:street":"N Military Trl",
    "iso:country":"US",
    "sg:address":"8910 N Military Trl",
    "sg:city":"Palm Beach Gardens",
    "sg:classifiers":[
        {
            "category":"Professional",
            "subcategory":"Management & Consulting",
            "type":"Services"
        }
    ],
    "sg:phone":"+1 561 842 3092",
    "sg:postcode":"33410",
    "sg:province":"FL",
    "wof:name":"Managed Business Assoc Inc",
    "wof:placetype":"venue"
},
  "geometry": {"coordinates":[-80.106455,26.805752],"type":"Point"}
}