{
  "type": "Feature",
  "properties": {
    "iso:country":"US",
    "sg:address":"13020 N Miami Ave",
    "sg:city":"North Miami",
    "sg:classifiers":[
        {
            "category":"Personal",
            "subcategory":"Beauty Salon",
            "type":"Services"
        }
    ],
    "sg:phone":"+1 305 681 6343",
    "sg:postcode":"33168",
    "sg:province":"FL",
    "wof:name":"Jolly Madame Hair Designs",
    "wof:placetype":"venue"
},
  "geometry": {"coordinates":[-80.198958,25.89485],"type":"Point"}
}