{
  "type": "Feature",
  "properties": {
    "addr:full":"761 US Hwy 92 De Bary FL 32713",
    "addr:housenumber":"761",
    "addr:postcode":"32713",
    "addr:street":"Us Hwy 92 De Bary",
    "iso:country":"US",
    "sg:address":"761 US Hwy 92",
    "sg:city":"De Bary",
    "sg:classifiers":[
        {
            "category":"Shopping",
            "subcategory":"Bicycles & Sporting Goods",
            "type":"Retail Goods"
        }
    ],
    "sg:phone":"+1 386 717 4666",
    "sg:postcode":"32713",
    "sg:province":"FL",
    "wof:name":"Ata Golf Carts",
    "wof:placetype":"venue"
},
  "geometry": {"coordinates":[-81.32216699999999,28.850797],"type":"Point"}
}