{
  "type": "Feature",
  "properties": {
    "iso:country":"US",
    "sg:address":"4305 NW 97th Ave",
    "sg:city":"Miami",
    "sg:classifiers":[
        {
            "category":"Retail",
            "subcategory":"Laundry & Dry Cleaning",
            "type":"Services"
        }
    ],
    "sg:phone":"+1 305 593 9293",
    "sg:postcode":"33178",
    "sg:province":"FL",
    "wof:name":"Millenium Cleaners S FL LLC",
    "wof:placetype":"venue"
},
  "geometry": {"coordinates":[-80.35323,25.813678],"type":"Point"}
}