{
  "type": "Feature",
  "properties": {
    "iso:country":"US",
    "sg:address":"1700 Lakeside Ave",
    "sg:city":"Saint Augustine",
    "sg:classifiers":[
        {
            "category":"Wholesale",
            "subcategory":"Apparel",
            "type":"Manufacturing & Wholesale Goods"
        }
    ],
    "sg:phone":"+1 904 823 1590",
    "sg:postcode":"32084",
    "sg:province":"FL",
    "sg:tags":[
        "dry",
        "other",
        "notion",
        "piece"
    ],
    "wof:name":"Touchtape Inc",
    "wof:placetype":"venue"
},
  "geometry": {"coordinates":[-81.331563,29.870013],"type":"Point"}
}