{
  "type": "Feature",
  "properties": {
    "addr:full":"4516 W North B St Tampa FL 33609",
    "addr:housenumber":"4516",
    "addr:postcode":"33609",
    "addr:street":"W North B",
    "iso:country":"US",
    "sg:address":"4516 W North B St",
    "sg:city":"Tampa",
    "sg:classifiers":[
        {
            "category":"Real Estate",
            "subcategory":"Real Estate Agent",
            "type":"Services"
        }
    ],
    "sg:phone":"+1 813 286 1003",
    "sg:postcode":"33609",
    "sg:province":"FL",
    "wof:name":"Pat Calderoni Realty",
    "wof:placetype":"venue"
},
  "geometry": {"coordinates":[-82.521894,27.946652],"type":"Point"}
}