{
  "type": "Feature",
  "properties": {
    "iso:country":"US",
    "sg:address":"920 E Park St",
    "sg:city":"Panama City",
    "sg:classifiers":[
        {
            "category":"Local Transit",
            "type":"Transportation"
        }
    ],
    "sg:phone":"+1 850 871 2828",
    "sg:postcode":"32404",
    "sg:province":"FL",
    "sg:tags":[
        "limousine"
    ],
    "wof:name":"J & R Limo Svc",
    "wof:placetype":"venue"
},
  "geometry": {"coordinates":[-85.604095,30.128909],"type":"Point"}
}