{
  "type": "Feature",
  "properties": {
    "addr:full":"10535 State Rd 52 Hudson FL 34669",
    "addr:housenumber":"10535;52",
    "addr:postcode":"34669",
    "addr:street":"State Rd",
    "iso:country":"US",
    "sg:address":"10535 State Rd 52",
    "sg:city":"Hudson",
    "sg:classifiers":[
        {
            "category":"Autos & Motor Vehicles",
            "subcategory":"Automobile Sales",
            "type":"Retail Goods"
        }
    ],
    "sg:phone":"+1 727 856 3939",
    "sg:postcode":"34669",
    "sg:province":"FL",
    "sg:tags":[
        "car",
        "dealer"
    ],
    "wof:name":"Golden Oldies Auto Sales Inc",
    "wof:placetype":"venue"
},
  "geometry": {"coordinates":[-82.637334,28.331418],"type":"Point"}
}