{
  "type": "Feature",
  "properties": {
    "iso:country":"US",
    "sg:address":"7500 Ulmerton Rd",
    "sg:city":"Largo",
    "sg:classifiers":[
        {
            "category":"Professional",
            "subcategory":"Business Services",
            "type":"Services"
        }
    ],
    "sg:phone":"+1 727 536 8542",
    "sg:postcode":"33771",
    "sg:province":"FL",
    "sg:tags":[
        "packaging"
    ],
    "wof:name":"B & D Pack & Ship",
    "wof:placetype":"venue"
},
  "geometry": {"coordinates":[-82.74358599999999,27.894149],"type":"Point"}
}