{
  "type": "Feature",
  "properties": {
    "addr:full":"1870 Orange Picker Rd Jacksonville FL 32223",
    "addr:housenumber":"1870",
    "addr:postcode":"32223",
    "addr:street":"Orange Picker Rd",
    "iso:country":"US",
    "sg:address":"1870 Orange Picker Rd",
    "sg:city":"Jacksonville",
    "sg:classifiers":[
        {
            "category":"Recreation",
            "type":"Entertainment"
        }
    ],
    "sg:phone":"+1 904 262 1450",
    "sg:postcode":"32223",
    "sg:province":"FL",
    "wof:name":"Dragon Martial Arts LLC",
    "wof:placetype":"venue"
},
  "geometry": {"coordinates":[-81.65596600000001,30.144916],"type":"Point"}
}