{
  "type": "Feature",
  "properties": {
    "addr:full":"1117 NE 1st Ter Crystal River FL 34429",
    "addr:housenumber":"1117",
    "addr:postcode":"34429",
    "addr:street":"Ne 1St Ter",
    "iso:country":"US",
    "sg:address":"1117 NE 1st Ter",
    "sg:city":"Crystal River",
    "sg:classifiers":[
        {
            "category":"Shopping",
            "type":"Retail Goods"
        }
    ],
    "sg:phone":"+1 352 795 3859",
    "sg:postcode":"34429",
    "sg:province":"FL",
    "sg:tags":[
        "miscellaneous",
        "store"
    ],
    "wof:name":"Summerlin Figurines",
    "wof:placetype":"venue"
},
  "geometry": {"coordinates":[-82.574089,28.895056],"type":"Point"}
}