{
  "type": "Feature",
  "properties": {
    "iso:country":"US",
    "sg:address":"4661 NW 31st Ave",
    "sg:city":"Fort Lauderdale",
    "sg:classifiers":[
        {
            "category":"Cinema",
            "subcategory":"Movie Rental",
            "type":"Entertainment"
        }
    ],
    "sg:phone":"+1 954 485 4569",
    "sg:postcode":"33309",
    "sg:province":"FL",
    "sg:tags":[
        "video",
        "tape"
    ],
    "wof:name":"Reel Image Video",
    "wof:placetype":"venue"
},
  "geometry": {"coordinates":[-80.187534,26.184417],"type":"Point"}
}