{
  "type": "Feature",
  "properties": {
    "addr:full":"670 Penfield St Longboat Key FL 34228",
    "addr:housenumber":"670",
    "addr:postcode":"34228",
    "addr:street":"Penfield St",
    "iso:country":"US",
    "sg:address":"670 Penfield St",
    "sg:city":"Longboat Key",
    "sg:classifiers":[
        {
            "category":"Recreation",
            "subcategory":"Marina",
            "type":"Entertainment"
        }
    ],
    "sg:phone":"+1 941 383 8550",
    "sg:postcode":"34228",
    "sg:province":"FL",
    "sg:tags":[
        "operation"
    ],
    "wof:name":"Parrot Cove Marina LLC",
    "wof:placetype":"venue"
},
  "geometry": {"coordinates":[-82.670198,27.429147],"type":"Point"}
}