{
  "type": "Feature",
  "properties": {
    "addr:full":"3772 Idlebrook Cir Casselberry FL 32707",
    "addr:housenumber":"3772",
    "addr:postcode":"32707",
    "addr:street":"Idlebrook Cir",
    "iso:country":"US",
    "sg:address":"3772 Idlebrook Cir",
    "sg:city":"Casselberry",
    "sg:classifiers":[
        {
            "category":"Real Estate",
            "subcategory":"Real Estate Operator",
            "type":"Services"
        }
    ],
    "sg:phone":"+1 407 699 0706",
    "sg:postcode":"32707",
    "sg:province":"FL",
    "sg:tags":[
        "condominium"
    ],
    "wof:name":"Cabana Key Condominiums",
    "wof:placetype":"venue"
},
  "geometry": {"coordinates":[-81.279652,28.649115],"type":"Point"}
}