{
  "type": "Feature",
  "properties": {
    "iso:country":"US",
    "sg:address":"10500 Ulmerton Rd",
    "sg:city":"Largo",
    "sg:classifiers":[
        {
            "category":"Professional",
            "subcategory":"Business Services",
            "type":"Services"
        }
    ],
    "sg:phone":"+1 727 584 2992",
    "sg:postcode":"33771",
    "sg:province":"FL",
    "sg:tags":[
        "packaging"
    ],
    "wof:name":"Pak Mail Ctr",
    "wof:placetype":"venue"
},
  "geometry": {"coordinates":[-82.78296,27.89461],"type":"Point"}
}