{
  "type": "Feature",
  "properties": {
    "iso:country":"US",
    "sg:address":"4300 N University Dr Ste A202",
    "sg:city":"Sunrise",
    "sg:classifiers":[
        {
            "category":"Health Services",
            "subcategory":"Doctor",
            "type":"Services"
        }
    ],
    "sg:phone":"+1 954 769 0729",
    "sg:postcode":"33351",
    "sg:province":"FL",
    "sg:tags":[
        "physician",
        "reconstructive",
        "surgeons",
        "cosmetic",
        "plastic",
        "surgery",
        "surgeon"
    ],
    "sg:website":"http://fortlauderdale.citysearch.com/profile/external/603308062/sunrise_fl/strax_rejuvenation.html?publisher=yellowpages&reference_id=1&placement=ypwebsitemip",
    "wof:name":"Strax Rejuvenation",
    "wof:placetype":"venue"
},
  "geometry": {"coordinates":[-80.25185999999999,26.177752],"type":"Point"}
}