{
  "type": "Feature",
  "properties": {
    "addr:full":"3550 Biscayne Blvd Miami FL 33137",
    "addr:housenumber":"3550",
    "addr:postcode":"33137",
    "addr:street":"Biscayne Blvd",
    "iso:country":"US",
    "sg:address":"3550 Biscayne Blvd",
    "sg:city":"Miami",
    "sg:classifiers":[
        {
            "category":"Professional",
            "subcategory":"Advertising",
            "type":"Services"
        }
    ],
    "sg:phone":"+1 305 438 0098",
    "sg:postcode":"33137",
    "sg:province":"FL",
    "sg:tags":[
        "advertising-promotional",
        "product"
    ],
    "sg:website":"http://www.starlightad.com",
    "wof:name":"Starlight Advertising & Promotions Inc",
    "wof:placetype":"venue"
},
  "geometry": {"coordinates":[-80.189491,25.81015],"type":"Point"}
}