{
  "type": "Feature",
  "properties": {
    "iso:country":"US",
    "sg:address":"6911 Pensacola Blvd",
    "sg:city":"Pensacola",
    "sg:classifiers":[
        {
            "category":"Restaurant",
            "type":"Food & Drink"
        }
    ],
    "sg:menulink":"http://www.allmenus.com/fl/pensacola/12845-founaris-bros-greek-restaurant/menu/",
    "sg:phone":"+1 850 969 9099",
    "sg:postcode":"32505",
    "sg:province":"FL",
    "sg:tags":[
        "greek"
    ],
    "wof:name":"Founaris Bros. Greek Restaurant",
    "wof:placetype":"venue"
},
  "geometry": {"coordinates":[-87.260856,30.49129],"type":"Point"}
}