{
  "type": "Feature",
  "properties": {
    "iso:country":"US",
    "sg:address":"1959 Dr Martin Luther King Way Martin",
    "sg:city":"Sarasota",
    "sg:classifiers":[
        {
            "category":"Place Of Worship",
            "subcategory":"Church",
            "type":"Public Place"
        },
        {
            "category":"Place Of Worship",
            "type":"Public Place"
        }
    ],
    "sg:phone":"+1 941 355 9750",
    "sg:postcode":"34234",
    "sg:province":"FL",
    "sg:tags":[
        "churches-interdenominational",
        "churches-various",
        "denomination"
    ],
    "wof:name":"Bethesda Outreach Ministries Inc",
    "wof:placetype":"venue"
},
  "geometry": {"coordinates":[-82.53156300000001,27.359653],"type":"Point"}
}