{
  "type": "Feature",
  "properties": {
    "addr:full":"1318 N Ocean Dr Hollywood FL 33019",
    "addr:housenumber":"1318",
    "addr:postcode":"33019",
    "addr:street":"N Ocean Dr",
    "iso:country":"US",
    "sg:address":"1318 N Ocean Dr",
    "sg:city":"Hollywood",
    "sg:classifiers":[
        {
            "category":"Restaurant",
            "type":"Food & Drink"
        }
    ],
    "sg:phone":"+1 954 929 0550",
    "sg:postcode":"33019",
    "sg:province":"FL",
    "sg:tags":[
        "eating"
    ],
    "wof:name":"Las Palmas",
    "wof:placetype":"venue"
},
  "geometry": {"coordinates":[-80.116941,26.020598],"type":"Point"}
}