{
  "type": "Feature",
  "properties": {
    "iso:country":"US",
    "sg:address":"2219 Gulf Dr N",
    "sg:city":"Bradenton Beach",
    "sg:classifiers":[
        {
            "category":"Shopping",
            "subcategory":"Gifts & Souvenirs",
            "type":"Retail Goods"
        }
    ],
    "sg:phone":"+1 941 778 7688",
    "sg:postcode":"34217",
    "sg:province":"FL",
    "sg:tags":[
        "tackle",
        "equipment",
        "bait",
        "fishing",
        "shop"
    ],
    "wof:name":"Island Discount Tackle",
    "wof:placetype":"venue"
},
  "geometry": {"coordinates":[-82.703828,27.478742],"type":"Point"}
}