{
  "type": "Feature",
  "properties": {
    "addr:full":"508 Katherwood Ct Deltona FL 32738",
    "addr:housenumber":"508",
    "addr:postcode":"32738",
    "addr:street":"Katherwood Ct",
    "iso:country":"US",
    "sg:address":"508 Katherwood Ct",
    "sg:city":"Deltona",
    "sg:classifiers":[
        {
            "category":"Building & Trades",
            "subcategory":"Construction",
            "type":"Services"
        }
    ],
    "sg:phone":"+1 386 574 7771",
    "sg:postcode":"32738",
    "sg:province":"FL",
    "sg:tags":[
        "contractor"
    ],
    "wof:name":"Decked Out Inc",
    "wof:placetype":"venue"
},
  "geometry": {"coordinates":[-81.186082,28.875441],"type":"Point"}
}