{
  "type": "Feature",
  "properties": {
    "addr:full":"175 Forest Lakes Blvd Oldsmar FL 34677",
    "addr:housenumber":"175",
    "addr:postcode":"34677",
    "addr:street":"Forest Lakes Blvd",
    "iso:country":"US",
    "sg:address":"175 Forest Lakes Blvd",
    "sg:city":"Oldsmar",
    "sg:classifiers":[
        {
            "category":"Retail",
            "subcategory":"Auto Rental",
            "type":"Services"
        }
    ],
    "sg:phone":"+1 813 891 6671",
    "sg:postcode":"34677",
    "sg:province":"FL",
    "sg:tags":[
        "renting",
        "truck",
        "leasing"
    ],
    "wof:name":"Budget Truck Rental",
    "wof:placetype":"venue"
},
  "geometry": {"coordinates":[-82.678787,28.041005],"type":"Point"}
}