{
  "type": "Feature",
  "properties": {
    "iso:country":"US",
    "sg:address":"2123 Tamiami Trl",
    "sg:city":"Venice",
    "sg:classifiers":[
        {
            "category":"Retail",
            "subcategory":"Self-service Laundry",
            "type":"Services"
        }
    ],
    "sg:phone":"+1 941 493 9265",
    "sg:postcode":"34293",
    "sg:province":"FL",
    "sg:tags":[
        "laundromat"
    ],
    "wof:name":"Laundramat",
    "wof:placetype":"venue"
},
  "geometry": {"coordinates":[-82.41193199999999,27.056258],"type":"Point"}
}