{
  "type": "Feature",
  "properties": {
    "iso:country":"US",
    "sg:address":"3509 Kingston St",
    "sg:city":"Jacksonville",
    "sg:classifiers":[
        {
            "category":"Social Services",
            "subcategory":"Child Care",
            "type":"Services"
        }
    ],
    "sg:phone":"+1 904 693 1133",
    "sg:postcode":"32254",
    "sg:province":"FL",
    "sg:tags":[
        "day"
    ],
    "wof:name":"Amazing Kids Learning Center",
    "wof:placetype":"venue"
},
  "geometry": {"coordinates":[-81.730925,30.338192],"type":"Point"}
}