{
  "type": "Feature",
  "properties": {
    "iso:country":"US",
    "sg:address":"6223 Pottsburgh Plantation Blvd",
    "sg:city":"Jacksonville",
    "sg:classifiers":[
        {
            "category":"Wholesale",
            "subcategory":"Machinery & Supplies",
            "type":"Manufacturing & Wholesale Goods"
        }
    ],
    "sg:phone":"+1 904 805 8801",
    "sg:postcode":"32216",
    "sg:province":"FL",
    "sg:tags":[
        "sprinkler"
    ],
    "wof:name":"Davis Fire Protection Inc",
    "wof:placetype":"venue"
},
  "geometry": {"coordinates":[-81.595077,30.311155],"type":"Point"}
}