{
  "type": "Feature",
  "properties": {
    "iso:country":"US",
    "sg:address":"2245 Balsam Ct",
    "sg:city":"Land O Lakes",
    "sg:classifiers":[
        {
            "category":"Shopping",
            "subcategory":"Catalog Store",
            "type":"Retail Goods"
        }
    ],
    "sg:phone":"+1 813 949 1520",
    "sg:postcode":"34639",
    "sg:province":"FL",
    "sg:tags":[
        "mail",
        "house"
    ],
    "wof:name":"Robert Dicaire",
    "wof:placetype":"venue"
},
  "geometry": {"coordinates":[-82.41283300000001,28.190256],"type":"Point"}
}