{
  "type": "Feature",
  "properties": {
    "iso:country":"US",
    "sg:address":"1382 Howland Blvd Ste 108",
    "sg:city":"Deltona",
    "sg:classifiers":[
        {
            "category":"Personal",
            "subcategory":"Nail Salon",
            "type":"Services"
        }
    ],
    "sg:phone":"+1 386 860 2228",
    "sg:postcode":"32738",
    "sg:province":"FL",
    "wof:name":"In Style Nails",
    "wof:placetype":"venue"
},
  "geometry": {"coordinates":[-81.171207,28.90253],"type":"Point"}
}