{
  "type": "Feature",
  "properties": {
    "iso:country":"US",
    "sg:address":"70 Hypolita St",
    "sg:city":"Saint Augustine",
    "sg:classifiers":[
        {
            "category":"Restaurant",
            "type":"Food & Drink"
        }
    ],
    "sg:menulink":"http://www.allmenus.com/fl/st-augustine/142135-scarlett-oharas-/menu/",
    "sg:phone":"+1 904 824 6535",
    "sg:postcode":"32084",
    "sg:province":"FL",
    "sg:tags":[
        "american"
    ],
    "wof:name":"Scarlett O'hara's ",
    "wof:placetype":"venue"
},
  "geometry": {"coordinates":[-81.313951,29.894666],"type":"Point"}
}