{
  "type": "Feature",
  "properties": {
    "iso:country":"US",
    "sg:address":"1954 Southside Blvd",
    "sg:city":"Jacksonville",
    "sg:classifiers":[
        {
            "category":"Banks & Credit Unions",
            "subcategory":"Bank",
            "type":"Services"
        }
    ],
    "sg:phone":"+1 904 720 5480",
    "sg:postcode":"32216",
    "sg:province":"FL",
    "sg:tags":[
        "loan",
        "real estate"
    ],
    "wof:name":"J D Mortgage Broker Inc",
    "wof:placetype":"venue"
},
  "geometry": {"coordinates":[-81.558851,30.310262],"type":"Point"}
}