{
  "type": "Feature",
  "properties": {
    "iso:country":"US",
    "sg:address":"1923 W Durkee Dr",
    "sg:city":"Jacksonville",
    "sg:classifiers":[
        {
            "category":"Manufacturing",
            "subcategory":"Textiles",
            "type":"Manufacturing & Wholesale Goods"
        }
    ],
    "sg:phone":"+1 904 632 1955",
    "sg:postcode":"32209",
    "sg:province":"FL",
    "sg:tags":[
        "mfg"
    ],
    "wof:name":"Sassy Matte Enterprises",
    "wof:placetype":"venue"
},
  "geometry": {"coordinates":[-81.67465,30.348813],"type":"Point"}
}