{
  "type": "Feature",
  "properties": {
    "iso:country":"US",
    "sg:address":"34 S Federal Hwy",
    "sg:city":"Fort Lauderdale",
    "sg:classifiers":[
        {
            "category":"Retail",
            "subcategory":"Repair Shop",
            "type":"Services"
        }
    ],
    "sg:phone":"+1 954 321 6666",
    "sg:postcode":"33301",
    "sg:province":"FL",
    "sg:tags":[
        "lock",
        "locksmith"
    ],
    "wof:name":"Budget Locksmiths",
    "wof:placetype":"venue"
},
  "geometry": {"coordinates":[-80.137103,26.121851],"type":"Point"}
}