{
  "type": "Feature",
  "properties": {
    "iso:country":"US",
    "sg:address":"10702 NW 7th Ave",
    "sg:city":"Miami",
    "sg:classifiers":[
        {
            "category":"Bars & Pubs",
            "type":"Food & Drink"
        }
    ],
    "sg:phone":"+1 305 756 5306",
    "sg:postcode":"33168",
    "sg:province":"FL",
    "sg:tags":[
        "lounge",
        "nightlife",
        "cocktail"
    ],
    "wof:name":"Chicagoan Bar",
    "wof:placetype":"venue"
},
  "geometry": {"coordinates":[-80.209999,25.872999],"type":"Point"}
}