{
  "type": "Feature",
  "properties": {
    "iso:country":"US",
    "sg:address":"1242 Olive St",
    "sg:city":"Lakeland",
    "sg:classifiers":[
        {
            "category":"Building & Trades",
            "subcategory":"Construction",
            "type":"Services"
        }
    ],
    "sg:phone":"+1 863 683 5599",
    "sg:postcode":"33815",
    "sg:province":"FL",
    "sg:tags":[
        "heavy",
        "utility",
        "electrical",
        "contractor"
    ],
    "wof:name":"P & M Communications Contr Inc",
    "wof:placetype":"venue"
},
  "geometry": {"coordinates":[-81.974726,28.039254],"type":"Point"}
}