{
  "type": "Feature",
  "properties": {
    "addr:full":"206 N Lotela Ave Avon Park FL 33825",
    "addr:housenumber":"206",
    "addr:postcode":"33825",
    "addr:street":"N Lotela Ave",
    "iso:country":"US",
    "sg:address":"206 N Lotela Ave",
    "sg:city":"Avon Park",
    "sg:classifiers":[
        {
            "category":"Professional",
            "subcategory":"Management & Consulting",
            "type":"Services"
        }
    ],
    "sg:phone":"+1 863 453 3755",
    "sg:postcode":"33825",
    "sg:province":"FL",
    "sg:tags":[
        "marketing",
        "consultant"
    ],
    "wof:name":"Onesource Marketing & Business",
    "wof:placetype":"venue"
},
  "geometry": {"coordinates":[-81.48988799999999,27.599421],"type":"Point"}
}