{
  "type": "Feature",
  "properties": {
    "iso:country":"US",
    "sg:address":"6670 114th Ave",
    "sg:city":"Largo",
    "sg:classifiers":[
        {
            "category":"Retail",
            "subcategory":"Auto Repair",
            "type":"Services"
        }
    ],
    "sg:phone":"+1 727 541 2695",
    "sg:postcode":"33773",
    "sg:province":"FL",
    "sg:tags":[
        "wrecker"
    ],
    "wof:name":"Joe's Towing & Recovery Inc",
    "wof:placetype":"venue"
},
  "geometry": {"coordinates":[-82.73198600000001,27.875593],"type":"Point"}
}