{
  "type": "Feature",
  "properties": {
    "iso:country":"US",
    "sg:address":"1954 W State Road 426",
    "sg:city":"Oviedo",
    "sg:classifiers":[
        {
            "category":"Personal",
            "subcategory":"Tanning Parlor",
            "type":"Services"
        }
    ],
    "sg:phone":"+1 407 977 3837",
    "sg:postcode":"32765",
    "sg:province":"FL",
    "wof:name":"Hot Bodies USA",
    "wof:placetype":"venue"
},
  "geometry": {"coordinates":[-81.22786499999999,28.653602],"type":"Point"}
}