{
  "type": "Feature",
  "properties": {
    "addr:full":"141 Cheshire Way Naples FL 34110",
    "addr:housenumber":"141",
    "addr:postcode":"34110",
    "addr:street":"Cheshire Way",
    "iso:country":"US",
    "sg:address":"141 Cheshire Way",
    "sg:city":"Naples",
    "sg:classifiers":[
        {
            "category":"Shopping",
            "subcategory":"Computers & Home Electronics",
            "type":"Retail Goods"
        }
    ],
    "sg:phone":"+1 239 254 9472",
    "sg:postcode":"34110",
    "sg:province":"FL",
    "sg:tags":[
        "equipment",
        "dealer"
    ],
    "wof:name":"Armac Computer Inc",
    "wof:placetype":"venue"
},
  "geometry": {"coordinates":[-81.822715,26.313692],"type":"Point"}
}