{
  "type": "Feature",
  "properties": {
    "iso:country":"US",
    "sg:address":"3198 S Dixie Hwy",
    "sg:city":"Miami",
    "sg:classifiers":[
        {
            "category":"Building & Trades",
            "subcategory":"Locksmith",
            "type":"Services"
        }
    ],
    "sg:phone":"+1 305 423 0795",
    "sg:postcode":"33133",
    "sg:province":"FL",
    "sg:tags":[
        "key"
    ],
    "wof:name":"1 Alpha Emergency Locksmith",
    "wof:placetype":"venue"
},
  "geometry": {"coordinates":[-80.245848,25.736791],"type":"Point"}
}