{
  "type": "Feature",
  "properties": {
    "iso:country":"US",
    "sg:address":"1672 N Hercules Ave",
    "sg:city":"Clearwater",
    "sg:classifiers":[
        {
            "category":"Restaurant",
            "type":"Food & Drink"
        }
    ],
    "sg:phone":"+1 727 791 8011",
    "sg:postcode":"33765",
    "sg:province":"FL",
    "sg:tags":[
        "parlor",
        "ice",
        "cream"
    ],
    "wof:name":"KOOL Penguin Ice Cream",
    "wof:placetype":"venue"
},
  "geometry": {"coordinates":[-82.75469,27.981401],"type":"Point"}
}