{
  "type": "Feature",
  "properties": {
    "addr:full":"435 Dean Creek Ln Orlando FL 32825",
    "addr:housenumber":"435",
    "addr:postcode":"32825",
    "addr:street":"Dean Creek Ln",
    "iso:country":"US",
    "sg:address":"435 Dean Creek Ln",
    "sg:city":"Orlando",
    "sg:classifiers":[
        {
            "category":"Professional",
            "subcategory":"Engineering",
            "type":"Services"
        }
    ],
    "sg:phone":"+1 321 235 8730",
    "sg:postcode":"32825",
    "sg:province":"FL",
    "sg:tags":[
        "engineer"
    ],
    "wof:name":"Gai Consultants",
    "wof:placetype":"venue"
},
  "geometry": {"coordinates":[-81.24307899999999,28.538437],"type":"Point"}
}