{
  "type": "Feature",
  "properties": {
    "iso:country":"US",
    "sg:address":"22864 Bluegill Ln",
    "sg:city":"Summerland Key",
    "sg:classifiers":[
        {
            "category":"Retail",
            "subcategory":"Repair Shop",
            "type":"Services"
        }
    ],
    "sg:phone":"+1 305 360 0625",
    "sg:postcode":"33042",
    "sg:province":"FL",
    "sg:tags":[
        "appliance"
    ],
    "wof:name":"K D's Repair Svc Inc",
    "wof:placetype":"venue"
},
  "geometry": {"coordinates":[-81.47423499999999,24.665885],"type":"Point"}
}