{
  "type": "Feature",
  "properties": {
    "iso:country":"US",
    "sg:address":"17850 SW 280th St",
    "sg:city":"Homestead",
    "sg:classifiers":[
        {
            "category":"Animal Shelter",
            "type":"Public Place"
        },
        {
            "category":"Retail",
            "subcategory":"Pet Boarding",
            "type":"Services"
        }
    ],
    "sg:phone":"+1 786 243 0502",
    "sg:postcode":"33031",
    "sg:province":"FL",
    "sg:tags":[
        "kennel"
    ],
    "wof:name":"Red Runner Kennel",
    "wof:placetype":"venue"
},
  "geometry": {"coordinates":[-80.480198,25.506362],"type":"Point"}
}