{
  "type": "Feature",
  "properties": {
    "iso:country":"US",
    "sg:address":"7110 Bird Rd",
    "sg:city":"Miami",
    "sg:classifiers":[
        {
            "category":"Health Services",
            "subcategory":"Chiropractor",
            "type":"Services"
        }
    ],
    "sg:phone":"+1 305 661 4775",
    "sg:postcode":"33155",
    "sg:province":"FL",
    "wof:name":"Savedoff Family Chiropractic Center",
    "wof:placetype":"venue"
},
  "geometry": {"coordinates":[-80.309246,25.733148],"type":"Point"}
}