{
  "type": "Feature",
  "properties": {
    "addr:full":"4965 Blue Springs Rd Marianna FL 32446",
    "addr:housenumber":"4965",
    "addr:postcode":"32446",
    "addr:street":"Blue Springs Rd",
    "iso:country":"US",
    "sg:address":"4965 Blue Springs Rd",
    "sg:city":"Marianna",
    "sg:classifiers":[
        {
            "category":"Real Estate",
            "subcategory":"Real Estate Services",
            "type":"Services"
        },
        {
            "category":"Real Estate",
            "subcategory":"Real Estate Agent",
            "type":"Services"
        }
    ],
    "sg:phone":"+1 850 482 4312",
    "sg:postcode":"32446",
    "sg:province":"FL",
    "sg:tags":[
        "buyer",
        "broker"
    ],
    "wof:name":"Ajg Co Inc",
    "wof:placetype":"venue"
},
  "geometry": {"coordinates":[-85.182106,30.782403],"type":"Point"}
}