{
  "type": "Feature",
  "properties": {
    "iso:country":"US",
    "sg:address":"6973 SW Wisteria Ter",
    "sg:city":"Palm City",
    "sg:classifiers":[
        {
            "category":"Building & Trades",
            "subcategory":"Construction",
            "type":"Services"
        }
    ],
    "sg:phone":"+1 772 283 1006",
    "sg:postcode":"34990",
    "sg:province":"FL",
    "sg:tags":[
        "house"
    ],
    "wof:name":"Mike Grannemann Construction",
    "wof:placetype":"venue"
},
  "geometry": {"coordinates":[-80.348394,27.136269],"type":"Point"}
}