{
  "type": "Feature",
  "properties": {
    "iso:country":"US",
    "sg:address":"3115 Coral Hills Dr",
    "sg:city":"Pompano Beach",
    "sg:classifiers":[
        {
            "category":"Building & Trades",
            "subcategory":"Construction",
            "type":"Services"
        }
    ],
    "sg:phone":"+1 954 345 2637",
    "sg:postcode":"33065",
    "sg:province":"FL",
    "sg:tags":[
        "hanging",
        "contractor"
    ],
    "wof:name":"E Jorge Flores",
    "wof:placetype":"venue"
},
  "geometry": {"coordinates":[-80.254098,26.269558],"type":"Point"}
}