{
  "type": "Feature",
  "properties": {
    "addr:full":"2920 Hyde Park St Sarasota FL 34239",
    "addr:housenumber":"2920",
    "addr:postcode":"34239",
    "addr:street":"Hyde Park St",
    "iso:country":"US",
    "sg:address":"2920 Hyde Park St",
    "sg:city":"Sarasota",
    "sg:classifiers":[
        {
            "category":"Retail",
            "subcategory":"Auto Repair",
            "type":"Services"
        }
    ],
    "sg:phone":"+1 941 924 8456",
    "sg:postcode":"34239",
    "sg:province":"FL",
    "sg:tags":[
        "body",
        "mfg"
    ],
    "wof:name":"King Signs",
    "wof:placetype":"venue"
},
  "geometry": {"coordinates":[-82.51133799999999,27.315434],"type":"Point"}
}