{
  "type": "Feature",
  "properties": {
    "iso:country":"US",
    "sg:address":"107 SE Turtle Creek Dr",
    "sg:city":"Jupiter",
    "sg:classifiers":[
        {
            "category":"Real Estate",
            "subcategory":"Real Estate Agent",
            "type":"Services"
        }
    ],
    "sg:phone":"+1 561 743 6398",
    "sg:postcode":"33469",
    "sg:province":"FL",
    "sg:tags":[
        "consultant"
    ],
    "wof:name":"Sales Team Solutions Inc",
    "wof:placetype":"venue"
},
  "geometry": {"coordinates":[-80.126772,26.981498],"type":"Point"}
}