{
  "type": "Feature",
  "properties": {
    "addr:full":"11019 NW 19th St Coral Springs FL 33071",
    "addr:housenumber":"11019",
    "addr:postcode":"33071",
    "addr:street":"Nw 19Th St",
    "iso:country":"US",
    "sg:address":"11019 NW 19th St",
    "sg:city":"Coral Springs",
    "sg:classifiers":[
        {
            "category":"Real Estate",
            "subcategory":"Architect",
            "type":"Services"
        }
    ],
    "sg:phone":"+1 954 753 0018",
    "sg:postcode":"33071",
    "sg:province":"FL",
    "wof:name":"RJS Architects",
    "wof:placetype":"venue"
},
  "geometry": {"coordinates":[-80.27336699999999,26.254752],"type":"Point"}
}