{
  "type": "Feature",
  "properties": {
    "iso:country":"US",
    "sg:address":"2102 W 16th St",
    "sg:city":"Sanford",
    "sg:classifiers":[
        {
            "category":"Personal",
            "subcategory":"Beauty Salon",
            "type":"Services"
        }
    ],
    "sg:phone":"+1 407 688 2058",
    "sg:postcode":"32771",
    "sg:province":"FL",
    "wof:name":"Comer Hair & Nails",
    "wof:placetype":"venue"
},
  "geometry": {"coordinates":[-81.289609,28.797648],"type":"Point"}
}