{
  "type": "Feature",
  "properties": {
    "iso:country":"US",
    "sg:address":"1685 Dunn Ave",
    "sg:city":"Jacksonville",
    "sg:classifiers":[
        {
            "category":"Government",
            "subcategory":"Office",
            "type":"Public Place"
        }
    ],
    "sg:phone":"+1 904 751 2169",
    "sg:postcode":"32218",
    "sg:province":"FL",
    "sg:tags":[
        "government-united",
        "state"
    ],
    "wof:name":"Us Social Security Adm",
    "wof:placetype":"venue"
},
  "geometry": {"coordinates":[-81.674209,30.432312],"type":"Point"}
}