{
  "type": "Feature",
  "properties": {
    "iso:country":"US",
    "sg:address":"522 Joel Blvd",
    "sg:city":"Lehigh Acres",
    "sg:classifiers":[
        {
            "category":"Food & Beverages",
            "subcategory":"Groceries & Convenience Stores",
            "type":"Retail Goods"
        }
    ],
    "sg:phone":"+1 239 369 5305",
    "sg:postcode":"33972",
    "sg:province":"FL",
    "wof:name":"Angela & Rudis Deli",
    "wof:placetype":"venue"
},
  "geometry": {"coordinates":[-81.59783899999999,26.619971],"type":"Point"}
}