{
  "type": "Feature",
  "properties": {
    "iso:country":"US",
    "sg:address":"41 S Arlington Rd",
    "sg:city":"Jacksonville",
    "sg:classifiers":[
        {
            "category":"Banks & Credit Unions",
            "subcategory":"Bank",
            "type":"Services"
        }
    ],
    "sg:phone":"+1 904 744 5530",
    "sg:postcode":"32216",
    "sg:province":"FL",
    "sg:tags":[
        "cashing",
        "check"
    ],
    "wof:name":"Pawn Etc",
    "wof:placetype":"venue"
},
  "geometry": {"coordinates":[-81.57879200000001,30.311241],"type":"Point"}
}