{
  "type": "Feature",
  "properties": {
    "iso:country":"US",
    "sg:address":"5040 Clock Rd",
    "sg:city":"Lake Worth",
    "sg:classifiers":[
        {
            "category":"Building & Trades",
            "subcategory":"Construction",
            "type":"Services"
        }
    ],
    "sg:phone":"+1 561 252 0564",
    "sg:postcode":"33463",
    "sg:province":"FL",
    "sg:tags":[
        "housing"
    ],
    "wof:name":"Larry Deese",
    "wof:placetype":"venue"
},
  "geometry": {"coordinates":[-80.122626,26.567292],"type":"Point"}
}