{
  "type": "Feature",
  "properties": {
    "iso:country":"US",
    "sg:address":"1207 S Ridgewood Ave",
    "sg:city":"Edgewater",
    "sg:classifiers":[
        {
            "category":"Wholesale",
            "subcategory":"Hardware",
            "type":"Manufacturing & Wholesale Goods"
        }
    ],
    "sg:phone":"+1 386 427 2665",
    "sg:postcode":"32132",
    "sg:province":"FL",
    "sg:tags":[
        "fastener",
        "nut",
        "bolt"
    ],
    "sg:website":"http://www.daytonabolt.com",
    "wof:name":"Daytona Bolt & Nut Co",
    "wof:placetype":"venue"
},
  "geometry": {"coordinates":[-80.901039,28.980952],"type":"Point"}
}