{
  "type": "Feature",
  "properties": {
    "iso:country":"US",
    "sg:address":"2101 SE Lennard Rd",
    "sg:city":"Port St Lucie",
    "sg:classifiers":[
        {
            "category":"Food & Beverages",
            "subcategory":"Groceries & Convenience Stores",
            "type":"Retail Goods"
        }
    ],
    "sg:phone":"+1 772 335 8383",
    "sg:postcode":"34952",
    "sg:province":"FL",
    "wof:name":"El Coqui Market",
    "wof:placetype":"venue"
},
  "geometry": {"coordinates":[-80.28478200000001,27.278162],"type":"Point"}
}