{
  "type": "Feature",
  "properties": {
    "iso:country":"US",
    "sg:address":"1181 Via Salerno",
    "sg:city":"Winter Park",
    "sg:classifiers":[
        {
            "category":"Building & Trades",
            "subcategory":"Construction",
            "type":"Services"
        }
    ],
    "sg:phone":"+1 407 740 7858",
    "sg:postcode":"32789",
    "sg:province":"FL",
    "sg:tags":[
        "concrete",
        "contractor"
    ],
    "wof:name":"Universal Con & Ceiling Contrs",
    "wof:placetype":"venue"
},
  "geometry": {"coordinates":[-81.338176,28.610976],"type":"Point"}
}