{
  "type": "Feature",
  "properties": {
    "iso:country":"US",
    "sg:address":"60 Carriage Hill Cir",
    "sg:city":"Casselberry",
    "sg:classifiers":[
        {
            "category":"Local Transit",
            "type":"Transportation"
        }
    ],
    "sg:phone":"+1 407 260 1751",
    "sg:postcode":"32707",
    "sg:province":"FL",
    "sg:tags":[
        "limousine"
    ],
    "wof:name":"Sta-Shines Svc Inc",
    "wof:placetype":"venue"
},
  "geometry": {"coordinates":[-81.330247,28.657573],"type":"Point"}
}