{
  "type": "Feature",
  "properties": {
    "addr:full":"119 W Sunrise Blvd Fort Lauderdale FL 33311",
    "addr:housenumber":"119",
    "addr:postcode":"33311",
    "addr:street":"W Sunrise Blvd",
    "iso:country":"US",
    "sg:address":"119 W Sunrise Blvd",
    "sg:city":"Fort Lauderdale",
    "sg:classifiers":[
        {
            "category":"Restaurant",
            "type":"Food & Drink"
        }
    ],
    "sg:phone":"+1 954 467 8054",
    "sg:postcode":"33311",
    "sg:province":"FL",
    "wof:name":"Eddy Caribean Restaurant",
    "wof:placetype":"venue"
},
  "geometry": {"coordinates":[-80.145951,26.136788],"type":"Point"}
}