{
  "type": "Feature",
  "properties": {
    "iso:country":"US",
    "sg:address":"7235 US Highway 19",
    "sg:city":"New Port Richey",
    "sg:classifiers":[
        {
            "category":"Professional",
            "subcategory":"Computer Services",
            "type":"Services"
        }
    ],
    "sg:phone":"+1 877 907 8483",
    "sg:postcode":"34652",
    "sg:province":"FL",
    "sg:tags":[
        "credit-repair-software",
        "credit-repair-business-software"
    ],
    "sg:website":"http://www.disputesuite.com/",
    "wof:name":"DisputeSuite",
    "wof:placetype":"venue"
},
  "geometry": {"coordinates":[-82.727935,28.263094],"type":"Point"}
}