{
  "type": "Feature",
  "properties": {
    "iso:country":"US",
    "sg:address":"3302 W Azeele St",
    "sg:city":"Tampa",
    "sg:classifiers":[
        {
            "category":"Professional",
            "subcategory":"Accounting & Tax Preparation",
            "type":"Services"
        }
    ],
    "sg:phone":"+1 813 877 9609",
    "sg:postcode":"33609",
    "sg:province":"FL",
    "sg:tags":[
        "accountant"
    ],
    "wof:name":"Ferlita Walsh & Gonzalez Pa",
    "wof:placetype":"venue"
},
  "geometry": {"coordinates":[-82.498481,27.941102],"type":"Point"}
}