{
  "type": "Feature",
  "properties": {
    "iso:country":"US",
    "sg:address":"830 7th St NW",
    "sg:city":"Naples",
    "sg:classifiers":[
        {
            "category":"Personal",
            "subcategory":"Beauty Salon",
            "type":"Services"
        }
    ],
    "sg:phone":"+1 239 353 2910",
    "sg:postcode":"34120",
    "sg:province":"FL",
    "wof:name":"About Faces Of Naples",
    "wof:placetype":"venue"
},
  "geometry": {"coordinates":[-81.621049,26.244446],"type":"Point"}
}