{
  "type": "Feature",
  "properties": {
    "iso:country":"US",
    "sg:address":"2180 Immokalee Rd",
    "sg:city":"Naples",
    "sg:classifiers":[
        {
            "category":"Professional",
            "subcategory":"Accounting & Tax Preparation",
            "type":"Services"
        }
    ],
    "sg:phone":"+1 239 596 0105",
    "sg:postcode":"34142",
    "sg:province":"FL",
    "sg:tags":[
        "return",
        "filing"
    ],
    "wof:name":"RSM Mc Gladrey Inc",
    "wof:placetype":"venue"
},
  "geometry": {"coordinates":[-81.48845900000001,26.499072],"type":"Point"}
}