{
  "type": "Feature",
  "properties": {
    "iso:country":"US",
    "sg:address":"1071 Edgewood Ave S",
    "sg:city":"Jacksonville",
    "sg:classifiers":[
        {
            "category":"Social Services",
            "subcategory":"Adult Care",
            "type":"Services"
        }
    ],
    "sg:phone":"+1 904 381 4816",
    "sg:postcode":"32205",
    "sg:province":"FL",
    "sg:tags":[
        "home",
        "residential"
    ],
    "wof:name":"Hillyer House Assisted Living",
    "wof:placetype":"venue"
},
  "geometry": {"coordinates":[-81.715733,30.310302],"type":"Point"}
}