{
  "type": "Feature",
  "properties": {
    "iso:country":"US",
    "sg:address":"7248 W Oakland Park Blvd",
    "sg:city":"Fort Lauderdale",
    "sg:classifiers":[
        {
            "category":"Insurance",
            "subcategory":"Insurance Agent",
            "type":"Services"
        }
    ],
    "sg:phone":"+1 954 748 1310",
    "sg:postcode":"33313",
    "sg:province":"FL",
    "wof:name":"State Farm Insurance",
    "wof:placetype":"venue"
},
  "geometry": {"coordinates":[-80.245701,26.165756],"type":"Point"}
}