{
  "type": "Feature",
  "properties": {
    "addr:full":"1155 S Dale Mabry Hwy Tampa FL 33629",
    "addr:housenumber":"1155",
    "addr:postcode":"33629",
    "addr:street":"S Dale Mabry Hwy",
    "iso:country":"US",
    "sg:address":"1155 S Dale Mabry Hwy",
    "sg:city":"Tampa",
    "sg:classifiers":[
        {
            "category":"Real Estate",
            "subcategory":"Real Estate Agent",
            "type":"Services"
        }
    ],
    "sg:phone":"+1 813 288 0636",
    "sg:postcode":"33629",
    "sg:province":"FL",
    "sg:tags":[
        "finding",
        "apartment",
        "rental"
    ],
    "wof:name":"Apartment Hunters",
    "wof:placetype":"venue"
},
  "geometry": {"coordinates":[-82.505889,27.932542],"type":"Point"}
}