{
  "type": "Feature",
  "properties": {
    "iso:country":"US",
    "sg:address":"35 E 25th St",
    "sg:city":"West Palm Beach",
    "sg:classifiers":[
        {
            "category":"Professional",
            "subcategory":"Lawyer & Legal Services",
            "type":"Services"
        }
    ],
    "sg:phone":"+1 561 881 0111",
    "sg:postcode":"33404",
    "sg:province":"FL",
    "sg:tags":[
        "attorney"
    ],
    "wof:name":"Dominque Geller Attorney",
    "wof:placetype":"venue"
},
  "geometry": {"coordinates":[-80.050468,26.782501],"type":"Point"}
}