{
  "type": "Feature",
  "properties": {
    "iso:country":"US",
    "sg:address":"169 E Flagler St Ste 1620",
    "sg:city":"Miami",
    "sg:classifiers":[
        {
            "category":"Professional",
            "subcategory":"Lawyer & Legal Services",
            "type":"Services"
        }
    ],
    "sg:phone":"+1 305 375 8181",
    "sg:postcode":"33131",
    "sg:province":"FL",
    "wof:name":"Tuttle II William Atty",
    "wof:placetype":"venue"
},
  "geometry": {"coordinates":[-80.190804,25.7742],"type":"Point"}
}