{
  "type": "Feature",
  "properties": {
    "addr:full":"850 Trafalgar Ct Maitland FL 32751",
    "addr:housenumber":"850",
    "addr:postcode":"32751",
    "addr:street":"Trafalgar Ct",
    "iso:country":"US",
    "sg:address":"850 Trafalgar Ct",
    "sg:city":"Maitland",
    "sg:classifiers":[
        {
            "category":"Building & Trades",
            "subcategory":"Construction",
            "type":"Services"
        }
    ],
    "sg:phone":"+1 407 875 8500",
    "sg:postcode":"32751",
    "sg:province":"FL",
    "sg:tags":[
        "contractor"
    ],
    "wof:name":"Welbro Ellis-Don Construction",
    "wof:placetype":"venue"
},
  "geometry": {"coordinates":[-81.391143,28.634405],"type":"Point"}
}