{
  "type": "Feature",
  "properties": {
    "iso:country":"US",
    "sg:address":"5805-1 Ramona Blvd",
    "sg:city":"Jacksonville",
    "sg:classifiers":[
        {
            "category":"Health Services",
            "subcategory":"Health Practitioner",
            "type":"Services"
        }
    ],
    "sg:phone":"+1 904 693 0866",
    "sg:postcode":"32205",
    "sg:province":"FL",
    "sg:tags":[
        "occupational",
        "therapist"
    ],
    "wof:name":"Lovett, James MD",
    "wof:placetype":"venue"
},
  "geometry": {"coordinates":[-81.745994,30.314087],"type":"Point"}
}