{
  "type": "Feature",
  "properties": {
    "addr:full":"75 Concord Dr Casselberry FL 32707",
    "addr:housenumber":"75",
    "addr:postcode":"32707",
    "addr:street":"Concord Dr",
    "iso:country":"US",
    "sg:address":"75 Concord Dr",
    "sg:city":"Casselberry",
    "sg:classifiers":[
        {
            "category":"Building & Trades",
            "subcategory":"Construction",
            "type":"Services"
        }
    ],
    "sg:phone":"+1 407 388 1838",
    "sg:postcode":"32707",
    "sg:province":"FL",
    "sg:tags":[
        "roofing",
        "contractor"
    ],
    "wof:name":"Guaranteed Weatherproof Rfng",
    "wof:placetype":"venue"
},
  "geometry": {"coordinates":[-81.338171,28.674337],"type":"Point"}
}