{
  "type": "Feature",
  "properties": {
    "iso:country":"US",
    "sg:address":"374 S Atlantic Ave",
    "sg:city":"Ormond Beach",
    "sg:classifiers":[
        {
            "category":"Professional",
            "subcategory":"Lawyer & Legal Services",
            "type":"Services"
        }
    ],
    "sg:phone":"+1 386 672 1190",
    "sg:postcode":"32176",
    "sg:province":"FL",
    "sg:tags":[
        "attorney"
    ],
    "wof:name":"Kim F Heller II Attorney",
    "wof:placetype":"venue"
},
  "geometry": {"coordinates":[-81.03514,29.282061],"type":"Point"}
}