{
  "type": "Feature",
  "properties": {
    "addr:full":"2390 NW 122nd Dr Pompano Beach FL 33065",
    "addr:housenumber":"2390",
    "addr:postcode":"33065",
    "addr:street":"Nw 122Nd Dr",
    "iso:country":"US",
    "sg:address":"2390 NW 122nd Dr",
    "sg:city":"Pompano Beach",
    "sg:classifiers":[
        {
            "category":"Shopping",
            "subcategory":"Gifts & Souvenirs",
            "type":"Retail Goods"
        }
    ],
    "sg:phone":"+1 954 720 0995",
    "sg:postcode":"33065",
    "sg:province":"FL",
    "wof:name":"OH Baby Baby Shwer Specialist",
    "wof:placetype":"venue"
},
  "geometry": {"coordinates":[-80.28871700000001,26.260551],"type":"Point"}
}