{
  "type": "Feature",
  "properties": {
    "addr:full":"1179 State Hwy 79 Bonifay FL 32425",
    "addr:housenumber":"1179",
    "addr:postcode":"32425",
    "addr:street":"State Hwy 79",
    "iso:country":"US",
    "sg:address":"1179 State Hwy 79",
    "sg:city":"Bonifay",
    "sg:classifiers":[
        {
            "category":"Food & Beverages",
            "subcategory":"Liquor & Beverages",
            "type":"Retail Goods"
        }
    ],
    "sg:phone":"+1 850 263 5268",
    "sg:postcode":"32425",
    "sg:province":"FL",
    "wof:name":"Big Daddy's Liquors",
    "wof:placetype":"venue"
},
  "geometry": {"coordinates":[-85.68010200000001,30.779086],"type":"Point"}
}