{
  "type": "Feature",
  "properties": {
    "iso:country":"US",
    "sg:address":"7438 Harbor View Dr",
    "sg:city":"Leesburg",
    "sg:classifiers":[
        {
            "category":"Shopping",
            "type":"Retail Goods"
        }
    ],
    "sg:phone":"+1 352 315 4384",
    "sg:postcode":"34788",
    "sg:province":"FL",
    "sg:tags":[
        "merchandise"
    ],
    "wof:name":"Travel Depot",
    "wof:placetype":"venue"
},
  "geometry": {"coordinates":[-81.831704,28.828881],"type":"Point"}
}