{
  "type": "Feature",
  "properties": {
    "addr:full":"8257 Mercado St Navarre FL 32566",
    "addr:housenumber":"8257",
    "addr:postcode":"32566",
    "addr:street":"Mercado St",
    "iso:country":"US",
    "sg:address":"8257 Mercado St",
    "sg:city":"Navarre",
    "sg:classifiers":[
        {
            "category":"Building & Trades",
            "subcategory":"Construction",
            "type":"Services"
        }
    ],
    "sg:phone":"+1 850 936 7784",
    "sg:postcode":"32566",
    "sg:province":"FL",
    "sg:tags":[
        "roofing",
        "contractor"
    ],
    "wof:name":"Built Right Construction",
    "wof:placetype":"venue"
},
  "geometry": {"coordinates":[-86.87696099999999,30.415871],"type":"Point"}
}