{
  "type": "Feature",
  "properties": {
    "iso:country":"US",
    "sg:address":"3711 SW 122nd Ave",
    "sg:city":"Miami",
    "sg:classifiers":[
        {
            "category":"Building & Trades",
            "subcategory":"Construction",
            "type":"Services"
        }
    ],
    "sg:phone":"+1 305 815 0677",
    "sg:postcode":"33175",
    "sg:province":"FL",
    "sg:tags":[
        "concrete",
        "pumping",
        "contractor"
    ],
    "wof:name":"Oscar Concrete Pumping Co",
    "wof:placetype":"venue"
},
  "geometry": {"coordinates":[-80.391728,25.734388],"type":"Point"}
}