{
  "type": "Feature",
  "properties": {
    "iso:country":"US",
    "sg:address":"2611 E Bearss Ave",
    "sg:city":"Tampa",
    "sg:classifiers":[
        {
            "category":"Social Services",
            "type":"Services"
        }
    ],
    "sg:phone":"+1 813 972 2608",
    "sg:postcode":"33613",
    "sg:province":"FL",
    "sg:tags":[
        "organization",
        "welfare"
    ],
    "sg:website":"www.questinc.org",
    "wof:name":"Quest Inc",
    "wof:placetype":"venue"
},
  "geometry": {"coordinates":[-82.429199,28.080342],"type":"Point"}
}