{
  "type": "Feature",
  "properties": {
    "addr:full":"4835 Hatteras Rd Jacksonville FL 32208",
    "addr:housenumber":"4835",
    "addr:postcode":"32208",
    "addr:street":"Hatteras Rd",
    "iso:country":"US",
    "sg:address":"4835 Hatteras Rd",
    "sg:city":"Jacksonville",
    "sg:classifiers":[
        {
            "category":"Place Of Worship",
            "type":"Public Place"
        }
    ],
    "sg:phone":"+1 904 765 0251",
    "sg:postcode":"32208",
    "sg:province":"FL",
    "sg:tags":[
        "church"
    ],
    "wof:name":"Gods Love Of Faith Assembly",
    "wof:placetype":"venue"
},
  "geometry": {"coordinates":[-81.72180899999999,30.399199],"type":"Point"}
}