{
  "type": "Feature",
  "properties": {
    "iso:country":"US",
    "sg:address":"5509 Commerce Dr",
    "sg:city":"Orlando",
    "sg:classifiers":[
        {
            "category":"Wholesale",
            "subcategory":"Groceries",
            "type":"Manufacturing & Wholesale Goods"
        }
    ],
    "sg:phone":"+1 407 240 9933",
    "sg:postcode":"32839",
    "sg:province":"FL",
    "sg:tags":[
        "food",
        "broker",
        "general"
    ],
    "wof:name":"Victoria Food Packing",
    "wof:placetype":"venue"
},
  "geometry": {"coordinates":[-81.372387,28.477424],"type":"Point"}
}