{
  "type": "Feature",
  "properties": {
    "iso:country":"US",
    "sg:address":"4251 NE 1st Ter",
    "sg:city":"Pompano Beach",
    "sg:classifiers":[
        {
            "category":"Building & Trades",
            "subcategory":"Plumbing",
            "type":"Services"
        }
    ],
    "sg:phone":"+1 954 366 5423",
    "sg:postcode":"33064",
    "sg:province":"FL",
    "sg:tags":[
        "contractor"
    ],
    "wof:name":"Kens Services",
    "wof:placetype":"venue"
},
  "geometry": {"coordinates":[-80.12311,26.284655],"type":"Point"}
}