{
  "type": "Feature",
  "properties": {
    "addr:full":"1615 Country Ln Dunedin FL 34698",
    "addr:housenumber":"1615",
    "addr:postcode":"34698",
    "addr:street":"Country Ln",
    "iso:country":"US",
    "sg:address":"1615 Country Ln",
    "sg:city":"Dunedin",
    "sg:classifiers":[
        {
            "category":"Professional",
            "subcategory":"Management & Consulting",
            "type":"Services"
        }
    ],
    "sg:phone":"+1 727 781 5846",
    "sg:postcode":"34698",
    "sg:province":"FL",
    "sg:tags":[
        "business"
    ],
    "wof:name":"Taylor & Thomas Environmental",
    "wof:placetype":"venue"
},
  "geometry": {"coordinates":[-82.763053,28.044557],"type":"Point"}
}