{
  "type": "Feature",
  "properties": {
    "iso:country":"US",
    "sg:address":"3045 Bent Oak Rd",
    "sg:city":"Pensacola",
    "sg:classifiers":[
        {
            "category":"Building & Trades",
            "subcategory":"Cleaning & Sanitation",
            "type":"Services"
        }
    ],
    "sg:phone":"+1 850 457 0279",
    "sg:postcode":"32526",
    "sg:province":"FL",
    "sg:tags":[
        "maintenance"
    ],
    "wof:name":"Sundance Maintenance",
    "wof:placetype":"venue"
},
  "geometry": {"coordinates":[-87.304723,30.446182],"type":"Point"}
}