{
  "type": "Feature",
  "properties": {
    "iso:country":"US",
    "sg:address":"22690 SW 54th Ave",
    "sg:city":"Boca Raton",
    "sg:classifiers":[
        {
            "category":"Sports & Exercise",
            "subcategory":"Gym",
            "type":"Entertainment"
        }
    ],
    "sg:phone":"+1 561 488 2337",
    "sg:postcode":"33433",
    "sg:province":"FL",
    "sg:tags":[
        "fitness",
        "physical",
        "facility"
    ],
    "wof:name":"Link Into Fitness Inc",
    "wof:placetype":"venue"
},
  "geometry": {"coordinates":[-80.18187500000001,26.339974],"type":"Point"}
}