{
  "type": "Feature",
  "properties": {
    "iso:country":"US",
    "sg:address":"5875 20th St",
    "sg:city":"Vero Beach",
    "sg:classifiers":[
        {
            "category":"Restaurant",
            "type":"Food & Drink"
        }
    ],
    "sg:menulink":"http://www.allmenus.com/fl/vero-beach/187781-mcdonalds/menu/",
    "sg:phone":"+1 772 569 2230",
    "sg:postcode":"32966",
    "sg:province":"FL",
    "sg:tags":[
        "burger",
        "american"
    ],
    "wof:name":"McDonald's",
    "wof:placetype":"venue"
},
  "geometry": {"coordinates":[-80.4485,27.638819],"type":"Point"}
}