{
  "type": "Feature",
  "properties": {
    "iso:country":"US",
    "sg:address":"13180 Cleveland Ave",
    "sg:city":"Fort Myers",
    "sg:classifiers":[
        {
            "category":"Education",
            "subcategory":"Special Training",
            "type":"Public Place"
        }
    ],
    "sg:phone":"+1 239 656 6604",
    "sg:postcode":"33903",
    "sg:province":"FL",
    "sg:tags":[
        "program"
    ],
    "wof:name":"Pure Energy Seminars LLC",
    "wof:placetype":"venue"
},
  "geometry": {"coordinates":[-81.88657499999999,26.663641],"type":"Point"}
}