{
  "type": "Feature",
  "properties": {
    "iso:country":"US",
    "sg:address":"524 Story Rd",
    "sg:city":"Lake Wales",
    "sg:classifiers":[
        {
            "category":"Manufacturing",
            "subcategory":"Glass & Minerals",
            "type":"Manufacturing & Wholesale Goods"
        }
    ],
    "sg:phone":"+1 863 676 6774",
    "sg:postcode":"33898",
    "sg:province":"FL",
    "sg:tags":[
        "product",
        "nonmetallic"
    ],
    "sg:website":"www.standardsand.com",
    "wof:name":"Standard Sand Fleet Shop",
    "wof:placetype":"venue"
},
  "geometry": {"coordinates":[-81.506147,27.90127],"type":"Point"}
}