{
  "type": "Feature",
  "properties": {
    "iso:country":"US",
    "sg:address":"1212 Ridgewood Ave",
    "sg:city":"Holly Hill",
    "sg:classifiers":[
        {
            "category":"Insurance",
            "subcategory":"Insurance Agent",
            "type":"Services"
        }
    ],
    "sg:phone":"+1 386 441 7283",
    "sg:postcode":"32117",
    "sg:province":"FL",
    "wof:name":"A Auto Insurance World",
    "wof:placetype":"venue"
},
  "geometry": {"coordinates":[-81.043421,29.248855],"type":"Point"}
}