{
  "type": "Feature",
  "properties": {
    "iso:country":"US",
    "sg:address":"4463 NW 99th Ave",
    "sg:city":"Fort Lauderdale",
    "sg:classifiers":[
        {
            "category":"Freight",
            "type":"Transportation"
        },
        {
            "category":"Retail",
            "subcategory":"Auto Repair",
            "type":"Services"
        }
    ],
    "sg:phone":"+1 954 214 6079",
    "sg:postcode":"33351",
    "sg:province":"FL",
    "sg:tags":[
        "automobile",
        "co",
        "drive",
        "transporter"
    ],
    "wof:name":"Untamed Transport Inc",
    "wof:placetype":"venue"
},
  "geometry": {"coordinates":[-80.28177599999999,26.180331],"type":"Point"}
}