{
  "type": "Feature",
  "properties": {
    "iso:country":"US",
    "sg:address":"11302 NW 65th St",
    "sg:city":"Miami",
    "sg:classifiers":[
        {
            "category":"Professional",
            "type":"Services"
        }
    ],
    "sg:phone":"+1 305 226 1610",
    "sg:postcode":"33178",
    "sg:province":"FL",
    "wof:name":"Kanga Sports Inc",
    "wof:placetype":"venue"
},
  "geometry": {"coordinates":[-80.381558,25.832594],"type":"Point"}
}