{
  "type": "Feature",
  "properties": {
    "iso:country":"US",
    "sg:address":"1021 Altamont Ln",
    "sg:city":"Odessa",
    "sg:classifiers":[
        {
            "category":"Building & Trades",
            "subcategory":"Construction",
            "type":"Services"
        }
    ],
    "sg:phone":"+1 727 457 3251",
    "sg:postcode":"33556",
    "sg:province":"FL",
    "sg:tags":[
        "carpentry",
        "contractor"
    ],
    "wof:name":"Edward McCune",
    "wof:placetype":"venue"
},
  "geometry": {"coordinates":[-82.555407,28.176253],"type":"Point"}
}