{
  "type": "Feature",
  "properties": {
    "iso:country":"US",
    "sg:address":"9626 53rd Dr E",
    "sg:city":"Bradenton",
    "sg:classifiers":[
        {
            "category":"Banks & Credit Unions",
            "subcategory":"Bank",
            "type":"Services"
        }
    ],
    "sg:phone":"+1 941 752 1952",
    "sg:postcode":"34211",
    "sg:province":"FL",
    "sg:tags":[
        "financing"
    ],
    "wof:name":"Blackrock Liquidity Funds",
    "wof:placetype":"venue"
},
  "geometry": {"coordinates":[-82.443305,27.444805],"type":"Point"}
}