{
  "type": "Feature",
  "properties": {
    "addr:full":"27608 Pullen Ave Bonita Springs FL 34135",
    "addr:housenumber":"27608",
    "addr:postcode":"34135",
    "addr:street":"Pullen Ave",
    "iso:country":"US",
    "sg:address":"27608 Pullen Ave",
    "sg:city":"Bonita Springs",
    "sg:classifiers":[
        {
            "category":"Building & Trades",
            "subcategory":"Electrical",
            "type":"Services"
        }
    ],
    "sg:phone":"+1 239 495 9995",
    "sg:postcode":"34135",
    "sg:province":"FL",
    "sg:tags":[
        "electrical",
        "contractor"
    ],
    "wof:name":"Mading Industries Inc",
    "wof:placetype":"venue"
},
  "geometry": {"coordinates":[-81.775696,26.337565],"type":"Point"}
}