{
  "type": "Feature",
  "properties": {
    "iso:country":"US",
    "sg:address":"10901 Harts Rd",
    "sg:city":"Jacksonville",
    "sg:classifiers":[
        {
            "category":"Travel",
            "subcategory":"Hotels & Motels",
            "type":"Entertainment"
        },
        {
            "category":"Travel",
            "subcategory":"Bed & Breakfast",
            "type":"Entertainment"
        }
    ],
    "sg:phone":"+1 904 751 3888",
    "sg:postcode":"32218",
    "sg:province":"FL",
    "sg:tags":[
        "inn",
        "lodging"
    ],
    "sg:website":"http://www.abvijacksonville.com",
    "wof:name":"Americas Best Value Inn - Jacksonville",
    "wof:placetype":"venue"
},
  "geometry": {"coordinates":[-81.659352,30.434044],"type":"Point"}
}