{
  "type": "Feature",
  "properties": {
    "addr:full":"6700 SW 132nd Ave Miami FL 33183",
    "addr:housenumber":"6700",
    "addr:postcode":"33183",
    "addr:street":"Sw 132Nd Ave",
    "iso:country":"US",
    "sg:address":"6700 SW 132nd Ave",
    "sg:city":"Miami",
    "sg:classifiers":[
        {
            "category":"Social Services",
            "subcategory":"Child Care",
            "type":"Services"
        }
    ],
    "sg:phone":"+1 305 385 0371",
    "sg:postcode":"33183",
    "sg:province":"FL",
    "wof:name":"Kidz Korner Day Care Ctr",
    "wof:placetype":"venue"
},
  "geometry": {"coordinates":[-80.40690600000001,25.705344],"type":"Point"}
}