{
  "type": "Feature",
  "properties": {
    "addr:full":"682 Green Meadow Ave Maitland FL 32751",
    "addr:housenumber":"682",
    "addr:postcode":"32751",
    "addr:street":"Green Meadow Ave",
    "iso:country":"US",
    "sg:address":"682 Green Meadow Ave",
    "sg:city":"Maitland",
    "sg:classifiers":[
        {
            "category":"Banks & Credit Unions",
            "subcategory":"Investment Brokerage",
            "type":"Services"
        }
    ],
    "sg:phone":"+1 407 645 1301",
    "sg:postcode":"32751",
    "sg:province":"FL",
    "sg:tags":[
        "advisory",
        "financial"
    ],
    "wof:name":"Wall Street Financial",
    "wof:placetype":"venue"
},
  "geometry": {"coordinates":[-81.32705799999999,28.634065],"type":"Point"}
}