{
  "type": "Feature",
  "properties": {
    "addr:full":"1480 Main St Sarasota FL 34236",
    "addr:housenumber":"1480",
    "addr:postcode":"34236",
    "addr:street":"Main St",
    "iso:country":"US",
    "sg:address":"1480 Main St",
    "sg:city":"Sarasota",
    "sg:classifiers":[
        {
            "category":"Shopping",
            "type":"Retail Goods"
        }
    ],
    "sg:phone":"+1 941 955 6443",
    "sg:postcode":"34236",
    "sg:province":"FL",
    "sg:tags":[
        "art",
        "gallery",
        "dealer"
    ],
    "wof:name":"Sonnet Design Inc",
    "wof:placetype":"venue"
},
  "geometry": {"coordinates":[-82.542288,27.336402],"type":"Point"}
}