{
  "type": "Feature",
  "properties": {
    "addr:full":"854 E Cape Coral Pkwy Cape Coral FL 33904",
    "addr:housenumber":"854",
    "addr:postcode":"33904",
    "addr:street":"E Cape Coral Pkwy",
    "iso:country":"US",
    "sg:address":"854 E Cape Coral Pkwy",
    "sg:city":"Cape Coral",
    "sg:classifiers":[
        {
            "category":"Manufacturing",
            "subcategory":"Signs",
            "type":"Manufacturing & Wholesale Goods"
        }
    ],
    "sg:phone":"+1 239 542 3436",
    "sg:postcode":"33904",
    "sg:province":"FL",
    "sg:tags":[
        "specialty",
        "mfg"
    ],
    "wof:name":"Falcon Sign Co",
    "wof:placetype":"venue"
},
  "geometry": {"coordinates":[-81.954375,26.562544],"type":"Point"}
}