{
  "type": "Feature",
  "properties": {
    "addr:full":"7921 Bird Rd Ste 58 Miami FL 33155",
    "addr:housenumber":"7921",
    "addr:postcode":"33155",
    "addr:street":"Bird Rd Ste 58",
    "iso:country":"US",
    "sg:address":"7921 Bird Rd Ste 58",
    "sg:city":"Miami",
    "sg:classifiers":[
        {
            "category":"Home & Garden",
            "subcategory":"Carpets & Floor Coverings",
            "type":"Retail Goods"
        }
    ],
    "sg:phone":"+1 305 592 4396",
    "sg:postcode":"33155",
    "sg:province":"FL",
    "sg:tags":[
        "carpeting"
    ],
    "sg:website":"www.allfloridacarpet.com",
    "wof:name":"All Florida Carpet Inc",
    "wof:placetype":"venue"
},
  "geometry": {"coordinates":[-80.323601,25.733299],"type":"Point"}
}