{
  "type": "Feature",
  "properties": {
    "addr:full":"2829 Waldens Pond Cv Longwood FL 32779",
    "addr:housenumber":"2829",
    "addr:postcode":"32779",
    "addr:street":"Waldens Pond Cv",
    "iso:country":"US",
    "sg:address":"2829 Waldens Pond Cv",
    "sg:city":"Longwood",
    "sg:classifiers":[
        {
            "category":"Social Services",
            "subcategory":"Child Care",
            "type":"Services"
        }
    ],
    "sg:phone":"+1 407 889 3435",
    "sg:postcode":"32779",
    "sg:province":"FL",
    "sg:tags":[
        "day"
    ],
    "wof:name":"Let's Learn Academy",
    "wof:placetype":"venue"
},
  "geometry": {"coordinates":[-81.370003,28.741699],"type":"Point"}
}