{
  "type": "Feature",
  "properties": {
    "iso:country":"US",
    "sg:address":"2120 Santa Barbara Blvd",
    "sg:city":"Cape Coral",
    "sg:classifiers":[
        {
            "category":"Autos & Motor Vehicles",
            "subcategory":"Motorcycle Sales",
            "type":"Retail Goods"
        }
    ],
    "sg:phone":"+1 239 573 7388",
    "sg:postcode":"33991",
    "sg:province":"FL",
    "sg:tags":[
        "scooter"
    ],
    "wof:name":"Backstreet Scooters",
    "wof:placetype":"venue"
},
  "geometry": {"coordinates":[-81.97426400000001,26.610747],"type":"Point"}
}