{
  "type": "Feature",
  "properties": {
    "addr:full":"8330 N Florida Ave Tampa FL 33604",
    "addr:housenumber":"8330",
    "addr:postcode":"33604",
    "addr:street":"N Florida Ave",
    "iso:country":"US",
    "sg:address":"8330 N Florida Ave",
    "sg:city":"Tampa",
    "sg:classifiers":[
        {
            "category":"Professional",
            "subcategory":"Business Services",
            "type":"Services"
        }
    ],
    "sg:phone":"+1 813 931 5770",
    "sg:postcode":"33604",
    "sg:province":"FL",
    "wof:name":"Magic Mall Inc",
    "wof:placetype":"venue"
},
  "geometry": {"coordinates":[-82.45959000000001,28.024809],"type":"Point"}
}