{
  "type": "Feature",
  "properties": {
    "iso:country":"US",
    "sg:address":"465 State Hwy 13",
    "sg:city":"Jacksonville",
    "sg:classifiers":[
        {
            "category":"Personal",
            "subcategory":"Beauty Salon",
            "type":"Services"
        }
    ],
    "sg:phone":"+1 904 230 0401",
    "sg:postcode":"32259",
    "sg:province":"FL",
    "sg:tags":[
        "manicuring"
    ],
    "wof:name":"Nail Depot",
    "wof:placetype":"venue"
},
  "geometry": {"coordinates":[-81.625598,30.119763],"type":"Point"}
}