{
  "type": "Feature",
  "properties": {
    "addr:full":"38051 State Hwy 19 Umatilla FL 32784",
    "addr:housenumber":"38051",
    "addr:postcode":"32784",
    "addr:street":"State Hwy 19 Umatilla",
    "iso:country":"US",
    "sg:address":"38051 State Hwy 19",
    "sg:city":"Umatilla",
    "sg:classifiers":[
        {
            "category":"Manufacturing",
            "subcategory":"Metals",
            "type":"Manufacturing & Wholesale Goods"
        }
    ],
    "sg:phone":"+1 352 669 1254",
    "sg:postcode":"32784",
    "sg:province":"FL",
    "wof:name":"Chase Metals Inc",
    "wof:placetype":"venue"
},
  "geometry": {"coordinates":[-81.684034,28.903231],"type":"Point"}
}