{
  "type": "Feature",
  "properties": {
    "iso:country":"US",
    "sg:address":"30705 Iverson Dr",
    "sg:city":"Zephyrhills",
    "sg:classifiers":[
        {
            "category":"Professional",
            "subcategory":"Accounting & Tax Preparation",
            "type":"Services"
        }
    ],
    "sg:phone":"+1 813 994 2868",
    "sg:postcode":"33543",
    "sg:province":"FL",
    "sg:tags":[
        "billing"
    ],
    "wof:name":"Laura Bonfiglio Billing Svc",
    "wof:placetype":"venue"
},
  "geometry": {"coordinates":[-82.30618699999999,28.176161],"type":"Point"}
}