{
  "type": "Feature",
  "properties": {
    "addr:full":"1144 Fairfield Meadows Dr Fort Lauderdale FL 33327",
    "addr:housenumber":"1144",
    "addr:postcode":"33327",
    "addr:street":"Fairfield Meadows Dr",
    "iso:country":"US",
    "sg:address":"1144 Fairfield Meadows Dr",
    "sg:city":"Fort Lauderdale",
    "sg:classifiers":[
        {
            "category":"Utilities",
            "subcategory":"Telephone",
            "type":"Services"
        }
    ],
    "sg:phone":"+1 954 384 9041",
    "sg:postcode":"33327",
    "sg:province":"FL",
    "sg:tags":[
        "connectivity",
        "internet"
    ],
    "wof:name":"Toddlerwatchcom Inc",
    "wof:placetype":"venue"
},
  "geometry": {"coordinates":[-80.409713,26.132112],"type":"Point"}
}