{
  "type": "Feature",
  "properties": {
    "addr:full":"2015 W 1st St Ste B Fort Myers FL 33901",
    "addr:housenumber":"2015",
    "addr:postcode":"33901",
    "addr:street":"W 1St St Ste B",
    "iso:country":"US",
    "sg:address":"2015 W 1st St Ste B",
    "sg:city":"Fort Myers",
    "sg:classifiers":[
        {
            "category":"Real Estate",
            "subcategory":"Real Estate Services",
            "type":"Services"
        }
    ],
    "sg:phone":"+1 239 344 9923",
    "sg:postcode":"33901",
    "sg:province":"FL",
    "sg:tags":[
        "management",
        "property"
    ],
    "wof:name":"Waterfront Realty",
    "wof:placetype":"venue"
},
  "geometry": {"coordinates":[-81.874021,26.641786],"type":"Point"}
}