{
  "type": "Feature",
  "properties": {
    "addr:full":"4601 N Central Ave Tampa FL 33603",
    "addr:housenumber":"4601",
    "addr:postcode":"33603",
    "addr:street":"N Central Ave",
    "iso:country":"US",
    "sg:address":"4601 N Central Ave",
    "sg:city":"Tampa",
    "sg:classifiers":[
        {
            "category":"Recreation",
            "type":"Entertainment"
        }
    ],
    "sg:phone":"+1 813 231 5299",
    "sg:postcode":"33603",
    "sg:province":"FL",
    "sg:tags":[
        "pool",
        "swimming"
    ],
    "wof:name":"Angus Goss Memorial Pool",
    "wof:placetype":"venue"
},
  "geometry": {"coordinates":[-82.455265,27.988799],"type":"Point"}
}