{
  "type": "Feature",
  "properties": {
    "iso:country":"US",
    "sg:address":"21135 Falls Ridge Way",
    "sg:city":"Boca Raton",
    "sg:classifiers":[
        {
            "category":"Professional",
            "type":"Services"
        }
    ],
    "sg:phone":"+1 561 483 3694",
    "sg:postcode":"33428",
    "sg:province":"FL",
    "wof:name":"Alma Foundation Inc",
    "wof:placetype":"venue"
},
  "geometry": {"coordinates":[-80.238941,26.361514],"type":"Point"}
}