{
  "type": "Feature",
  "properties": {
    "addr:full":"140 NW 14th Ave Appt14 Miami FL 33125",
    "addr:housenumber":"140",
    "addr:postcode":"33125",
    "addr:street":"Nw 14Th Ave",
    "iso:country":"US",
    "sg:address":"140 NW 14th Ave Appt14",
    "sg:city":"Miami",
    "sg:classifiers":[
        {
            "category":"Wholesale",
            "subcategory":"Computers",
            "type":"Manufacturing & Wholesale Goods"
        }
    ],
    "sg:phone":"+1 305 528 6267",
    "sg:postcode":"33125",
    "sg:province":"FL",
    "sg:tags":[
        "equipment",
        "computer-wholesale",
        "manufacturer"
    ],
    "wof:name":"Distrileim",
    "wof:placetype":"venue"
},
  "geometry": {"coordinates":[-80.218036,25.774782],"type":"Point"}
}