{
  "type": "Feature",
  "properties": {
    "addr:full":"719 Bridgeway Blvd Orlando FL 32828",
    "addr:housenumber":"719",
    "addr:postcode":"32828",
    "addr:street":"Bridgeway Blvd",
    "iso:country":"US",
    "sg:address":"719 Bridgeway Blvd",
    "sg:city":"Orlando",
    "sg:classifiers":[
        {
            "category":"Professional",
            "subcategory":"Management & Consulting",
            "type":"Services"
        }
    ],
    "sg:phone":"+1 407 658 9318",
    "sg:postcode":"32828",
    "sg:province":"FL",
    "sg:tags":[
        "business"
    ],
    "wof:name":"Lead The Future Inc",
    "wof:placetype":"venue"
},
  "geometry": {"coordinates":[-81.180413,28.559032],"type":"Point"}
}