{
  "type": "Feature",
  "properties": {
    "addr:full":"2424 W 60th St Hialeah FL 33016",
    "addr:housenumber":"2424",
    "addr:postcode":"33016",
    "addr:street":"W 60Th St",
    "iso:country":"US",
    "sg:address":"2424 W 60th St",
    "sg:city":"Hialeah",
    "sg:classifiers":[
        {
            "category":"Shopping",
            "subcategory":"Pharmacy",
            "type":"Retail Goods"
        }
    ],
    "sg:phone":"+1 305 362 5339",
    "sg:postcode":"33016",
    "sg:province":"FL",
    "sg:website":"www.eckerd.com",
    "wof:name":"Eckerd",
    "wof:placetype":"venue"
},
  "geometry": {"coordinates":[-80.33242799999999,25.876938],"type":"Point"}
}