{
  "type": "Feature",
  "properties": {
    "iso:country":"US",
    "sg:address":"7950 Airport Pulling Rd N",
    "sg:city":"Naples",
    "sg:classifiers":[
        {
            "category":"Banks & Credit Unions",
            "subcategory":"Bank",
            "type":"Services"
        }
    ],
    "sg:phone":"+1 239 435 0505",
    "sg:postcode":"34109",
    "sg:province":"FL",
    "wof:name":"AM South Bank",
    "wof:placetype":"venue"
},
  "geometry": {"coordinates":[-81.768835,26.23705],"type":"Point"}
}