{
  "type": "Feature",
  "properties": {
    "iso:country":"US",
    "sg:address":"3834 Park Ave",
    "sg:city":"Miami",
    "sg:classifiers":[
        {
            "category":"Professional",
            "subcategory":"Management & Consulting",
            "type":"Services"
        }
    ],
    "sg:phone":"+1 305 662 1220",
    "sg:postcode":"33133",
    "sg:province":"FL",
    "sg:tags":[
        "public",
        "relations"
    ],
    "wof:name":"Shapiro & Zarikian Inc",
    "wof:placetype":"venue"
},
  "geometry": {"coordinates":[-80.254915,25.714143],"type":"Point"}
}