{
  "type": "Feature",
  "properties": {
    "iso:country":"US",
    "sg:address":"5110 Bayshore Blvd",
    "sg:city":"Tampa",
    "sg:classifiers":[
        {
            "category":"Manufacturing",
            "subcategory":"Tools & Machinery",
            "type":"Manufacturing & Wholesale Goods"
        },
        {
            "category":"Industrial Area",
            "type":"Public Place"
        }
    ],
    "sg:phone":"+1 813 205 6464",
    "sg:postcode":"33611",
    "sg:province":"FL",
    "sg:tags":[
        "repair",
        "equipment-repairing",
        "machinery-rebuild"
    ],
    "wof:name":"Arthur Machinery-Florida",
    "wof:placetype":"venue"
},
  "geometry": {"coordinates":[-82.48571,27.890395],"type":"Point"}
}