{
  "type": "Feature",
  "properties": {
    "addr:full":"135 Lakeside Dr Jupiter FL 33458",
    "addr:housenumber":"135",
    "addr:postcode":"33458",
    "addr:street":"Lakeside Dr",
    "iso:country":"US",
    "sg:address":"135 Lakeside Dr",
    "sg:city":"Jupiter",
    "sg:classifiers":[
        {
            "category":"Professional",
            "subcategory":"Business Services",
            "type":"Services"
        }
    ],
    "sg:phone":"+1 561 744 7686",
    "sg:postcode":"33458",
    "sg:province":"FL",
    "wof:name":"Accessories-Etccom",
    "wof:placetype":"venue"
},
  "geometry": {"coordinates":[-80.13283699999999,26.923909],"type":"Point"}
}