{
  "type": "Feature",
  "properties": {
    "iso:country":"US",
    "sg:address":"7355 NW 54th St",
    "sg:city":"Miami",
    "sg:classifiers":[
        {
            "category":"Freight",
            "type":"Transportation"
        }
    ],
    "sg:phone":"+1 305 805 9293",
    "sg:postcode":"33166",
    "sg:province":"FL",
    "sg:tags":[
        "arrangement"
    ],
    "wof:name":"A & A Cargo",
    "wof:placetype":"venue"
},
  "geometry": {"coordinates":[-80.31723700000001,25.822641],"type":"Point"}
}