{
  "type": "Feature",
  "properties": {
    "addr:full":"1501 NW 9th Ave Miami FL 33136",
    "addr:housenumber":"1501",
    "addr:postcode":"33136",
    "addr:street":"Nw 9Th Ave",
    "iso:country":"US",
    "sg:address":"1501 NW 9th Ave",
    "sg:city":"Miami",
    "sg:classifiers":[
        {
            "category":"Health Services",
            "subcategory":"Doctor",
            "type":"Services"
        }
    ],
    "sg:phone":"+1 305 243 6536",
    "sg:postcode":"33136",
    "sg:province":"FL",
    "sg:tags":[
        "medical"
    ],
    "wof:name":"John Ragheb MD",
    "wof:placetype":"venue"
},
  "geometry": {"coordinates":[-80.210219,25.791414],"type":"Point"}
}