{
  "type": "Feature",
  "properties": {
    "addr:full":"7319 W Flagler St Miami FL 33144",
    "addr:housenumber":"7319",
    "addr:postcode":"33144",
    "addr:street":"W Flagler St",
    "iso:country":"US",
    "sg:address":"7319 W Flagler St",
    "sg:city":"Miami",
    "sg:classifiers":[
        {
            "category":"Real Estate",
            "subcategory":"Surveying",
            "type":"Services"
        }
    ],
    "sg:phone":"+1 305 551 4393",
    "sg:postcode":"33144",
    "sg:province":"FL",
    "sg:tags":[
        "surveyor",
        "land",
        "engineer"
    ],
    "wof:name":"Roberto Brizuela & Assoc Inc",
    "wof:placetype":"venue"
},
  "geometry": {"coordinates":[-80.314651,25.77015],"type":"Point"}
}