{
  "type": "Feature",
  "properties": {
    "iso:country":"US",
    "sg:address":"4850 Osprey Dr S",
    "sg:city":"Saint Petersburg",
    "sg:classifiers":[
        {
            "category":"Real Estate",
            "subcategory":"Real Estate Agent",
            "type":"Services"
        }
    ],
    "sg:phone":"+1 727 867 0282",
    "sg:postcode":"33711",
    "sg:province":"FL",
    "wof:name":"Bay Ray Development Inc",
    "wof:placetype":"venue"
},
  "geometry": {"coordinates":[-82.69282699999999,27.71964],"type":"Point"}
}