{
  "type": "Feature",
  "properties": {
    "iso:country":"US",
    "sg:address":"1410 Homestead Rd N",
    "sg:city":"Lehigh Acres",
    "sg:classifiers":[
        {
            "category":"Real Estate",
            "subcategory":"Real Estate Agent",
            "type":"Services"
        }
    ],
    "sg:phone":"+1 239 368 1888",
    "sg:postcode":"33936",
    "sg:province":"FL",
    "wof:name":"Rental & Land Sales",
    "wof:placetype":"venue"
},
  "geometry": {"coordinates":[-81.654133,26.611263],"type":"Point"}
}