{
  "type": "Feature",
  "properties": {
    "iso:country":"US",
    "sg:address":"3835 McCoy Rd",
    "sg:city":"Orlando",
    "sg:classifiers":[
        {
            "category":"Freight",
            "type":"Transportation"
        }
    ],
    "sg:phone":"+1 407 854 3302",
    "sg:postcode":"32812",
    "sg:province":"FL",
    "wof:name":"Jetport Transportation",
    "wof:placetype":"venue"
},
  "geometry": {"coordinates":[-81.33778700000001,28.451335],"type":"Point"}
}