{
  "type": "Feature",
  "properties": {
    "addr:full":"8821 SW 107th Ave Miami FL 33176",
    "addr:housenumber":"8821",
    "addr:postcode":"33176",
    "addr:street":"Sw 107Th Ave",
    "iso:country":"US",
    "sg:address":"8821 SW 107th Ave",
    "sg:city":"Miami",
    "sg:classifiers":[
        {
            "category":"Health Services",
            "subcategory":"Dentist",
            "type":"Services"
        }
    ],
    "sg:phone":"+1 305 279 0202",
    "sg:postcode":"33176",
    "sg:province":"FL",
    "wof:name":"Stein Larry DMD",
    "wof:placetype":"venue"
},
  "geometry": {"coordinates":[-80.365684,25.686691],"type":"Point"}
}