{
  "type": "Feature",
  "properties": {
    "addr:full":"20801 Biscayne Blvd Miami FL 33180",
    "addr:housenumber":"20801",
    "addr:postcode":"33180",
    "addr:street":"Biscayne Blvd",
    "iso:country":"US",
    "sg:address":"20801 Biscayne Blvd",
    "sg:city":"Miami",
    "sg:classifiers":[
        {
            "category":"Shopping",
            "subcategory":"Department Store",
            "type":"Retail Goods"
        }
    ],
    "sg:phone":"+1 305 933 8608",
    "sg:postcode":"33180",
    "sg:province":"FL",
    "sg:tags":[
        "shop"
    ],
    "wof:name":"Blunauta USA",
    "wof:placetype":"venue"
},
  "geometry": {"coordinates":[-80.144882,25.968049],"type":"Point"}
}