{
  "type": "Feature",
  "properties": {
    "iso:country":"US",
    "sg:address":"8148 NW 68th Ave",
    "sg:city":"Fort Lauderdale",
    "sg:classifiers":[
        {
            "category":"Building & Trades",
            "subcategory":"Electrical",
            "type":"Services"
        }
    ],
    "sg:phone":"+1 954 718 1558",
    "sg:postcode":"33321",
    "sg:province":"FL",
    "sg:tags":[
        "electrical",
        "contractor"
    ],
    "wof:name":"Empire Electrical Inc",
    "wof:placetype":"venue"
},
  "geometry": {"coordinates":[-80.24286499999999,26.224691],"type":"Point"}
}