{
  "type": "Feature",
  "properties": {
    "iso:country":"US",
    "sg:address":"1206 N Young Blvd",
    "sg:city":"Chiefland",
    "sg:classifiers":[
        {
            "category":"Autos & Motor Vehicles",
            "subcategory":"Recreational Vehicle Sales",
            "type":"Retail Goods"
        }
    ],
    "sg:phone":"+1 352 493 1351",
    "sg:postcode":"32626",
    "sg:province":"FL",
    "wof:name":"Finnlad Mobile Hm & Rv Supply",
    "wof:placetype":"venue"
},
  "geometry": {"coordinates":[-82.862968,29.490537],"type":"Point"}
}