{
  "type": "Feature",
  "properties": {
    "addr:full":"5700 NW 47th Ln Tamarac FL 33319",
    "addr:housenumber":"5700",
    "addr:postcode":"33319",
    "addr:street":"Nw 47Th Ln",
    "iso:country":"US",
    "sg:address":"5700 NW 47th Ln",
    "sg:city":"Tamarac",
    "sg:classifiers":[
        {
            "category":"Professional",
            "subcategory":"Advertising",
            "type":"Services"
        }
    ],
    "sg:phone":"+1 954 733 3557",
    "sg:postcode":"33319",
    "sg:province":"FL",
    "sg:tags":[
        "marketing",
        "program"
    ],
    "wof:name":"Eaglesnest Marketing Group",
    "wof:placetype":"venue"
},
  "geometry": {"coordinates":[-80.21193700000001,26.19533],"type":"Point"}
}