{
  "type": "Feature",
  "properties": {
    "iso:country":"US",
    "sg:address":"4103 Gulf Blvd",
    "sg:city":"Saint Petersburg",
    "sg:classifiers":[
        {
            "category":"Building & Trades",
            "subcategory":"Construction",
            "type":"Services"
        }
    ],
    "sg:phone":"+1 727 360 5733",
    "sg:postcode":"33706",
    "sg:province":"FL",
    "sg:tags":[
        "carpentry",
        "contractor"
    ],
    "wof:name":"Energy Conservtn Svc",
    "wof:placetype":"venue"
},
  "geometry": {"coordinates":[-82.73836,27.715731],"type":"Point"}
}