{
  "type": "Feature",
  "properties": {
    "iso:country":"US",
    "sg:address":"10710 NW 66th St",
    "sg:city":"Miami",
    "sg:classifiers":[
        {
            "category":"Professional",
            "subcategory":"Engineering",
            "type":"Services"
        }
    ],
    "sg:phone":"+1 305 591 2966",
    "sg:postcode":"33178",
    "sg:province":"FL",
    "wof:name":"Bitca U S A Corp",
    "wof:placetype":"venue"
},
  "geometry": {"coordinates":[-80.382846,25.833047],"type":"Point"}
}