{
  "type": "Feature",
  "properties": {
    "addr:full":"3321 Cortez Rd W Bradenton FL 34207",
    "addr:housenumber":"3321",
    "addr:postcode":"34207",
    "addr:street":"Cortez Rd W",
    "iso:country":"US",
    "sg:address":"3321 Cortez Rd W",
    "sg:city":"Bradenton",
    "sg:classifiers":[
        {
            "category":"Autos & Motor Vehicles",
            "subcategory":"Fuel & Gas Station",
            "type":"Retail Goods"
        }
    ],
    "sg:phone":"+1 941 758 2271",
    "sg:postcode":"34207",
    "sg:province":"FL",
    "sg:tags":[
        "station",
        "gasoline"
    ],
    "wof:name":"Chevron",
    "wof:placetype":"venue"
},
  "geometry": {"coordinates":[-82.595438,27.462292],"type":"Point"}
}