{
  "type": "Feature",
  "properties": {
    "addr:full":"1017 N State Rd 7 Royal Palm Beach FL 33411",
    "addr:housenumber":"1017;7",
    "addr:postcode":"33411",
    "addr:street":"N State Rd",
    "iso:country":"US",
    "sg:address":"1017 N State Rd 7",
    "sg:city":"Royal Palm Beach",
    "sg:classifiers":[
        {
            "category":"Health Services",
            "subcategory":"Doctor",
            "type":"Services"
        }
    ],
    "sg:phone":"+1 561 798 9417",
    "sg:postcode":"33411",
    "sg:province":"FL",
    "sg:tags":[
        "physician",
        "surgeon"
    ],
    "wof:name":"Pediatric Associates",
    "wof:placetype":"venue"
},
  "geometry": {"coordinates":[-80.20102199999999,26.708614],"type":"Point"}
}