{
  "type": "Feature",
  "properties": {
    "addr:full":"326 NE 30th St Boca Raton FL 33431",
    "addr:housenumber":"326",
    "addr:postcode":"33431",
    "addr:street":"Ne 30Th St",
    "iso:country":"US",
    "sg:address":"326 NE 30th St",
    "sg:city":"Boca Raton",
    "sg:classifiers":[
        {
            "category":"Building & Trades",
            "subcategory":"Construction",
            "type":"Services"
        }
    ],
    "sg:phone":"+1 561 392 7609",
    "sg:postcode":"33431",
    "sg:province":"FL",
    "sg:tags":[
        "restoration",
        "cleaning",
        "patio",
        "deck"
    ],
    "wof:name":"Eric Pardi Pressure Cleaning",
    "wof:placetype":"venue"
},
  "geometry": {"coordinates":[-80.079375,26.378313],"type":"Point"}
}