{
  "type": "Feature",
  "properties": {
    "addr:full":"7824 Grand Blvd Port Richey FL 34668",
    "addr:housenumber":"7824",
    "addr:postcode":"34668",
    "addr:street":"Grand Blvd",
    "iso:country":"US",
    "sg:address":"7824 Grand Blvd",
    "sg:city":"Port Richey",
    "sg:classifiers":[
        {
            "category":"Government",
            "subcategory":"Fire Station",
            "type":"Public Place"
        }
    ],
    "sg:phone":"+1 727 816 1910",
    "sg:postcode":"34668",
    "sg:province":"FL",
    "sg:tags":[
        "protection"
    ],
    "sg:website":"www.copr.net",
    "wof:name":"Port Richey Fire Dept",
    "wof:placetype":"venue"
},
  "geometry": {"coordinates":[-82.721784,28.272468],"type":"Point"}
}