{
  "type": "Feature",
  "properties": {
    "iso:country":"US",
    "sg:address":"29 Port Royal Dr",
    "sg:city":"Palm Coast",
    "sg:classifiers":[
        {
            "category":"Building & Trades",
            "subcategory":"Construction",
            "type":"Services"
        }
    ],
    "sg:phone":"+1 386 437 9848",
    "sg:postcode":"32164",
    "sg:province":"FL",
    "sg:tags":[
        "house"
    ],
    "wof:name":"Apex Coastal Construction Inc",
    "wof:placetype":"venue"
},
  "geometry": {"coordinates":[-81.20658899999999,29.508223],"type":"Point"}
}