{
  "type": "Feature",
  "properties": {
    "addr:full":"5224 NW 163rd St Hialeah FL 33014",
    "addr:housenumber":"5224",
    "addr:postcode":"33014",
    "addr:street":"Nw 163Rd St",
    "iso:country":"US",
    "sg:address":"5224 NW 163rd St",
    "sg:city":"Hialeah",
    "sg:classifiers":[
        {
            "category":"Building & Trades",
            "subcategory":"Plumbing",
            "type":"Services"
        }
    ],
    "sg:phone":"+1 305 626 9257",
    "sg:postcode":"33014",
    "sg:province":"FL",
    "sg:tags":[
        "contractor"
    ],
    "wof:name":"Colony Air Conditioning Inc",
    "wof:placetype":"venue"
},
  "geometry": {"coordinates":[-80.285815,25.921257],"type":"Point"}
}