{
  "type": "Feature",
  "properties": {
    "iso:country":"US",
    "sg:address":"3260 Mahan Dr",
    "sg:city":"Tallahassee",
    "sg:classifiers":[
        {
            "category":"Wholesale",
            "subcategory":"Construction Materials",
            "type":"Manufacturing & Wholesale Goods"
        }
    ],
    "sg:phone":"+1 850 701 0340",
    "sg:postcode":"32308",
    "sg:province":"FL",
    "sg:tags":[
        "nailing",
        "machinery"
    ],
    "wof:name":"Fastening Systems Inc",
    "wof:placetype":"venue"
},
  "geometry": {"coordinates":[-84.22136,30.462536],"type":"Point"}
}