{
  "type": "Feature",
  "properties": {
    "iso:country":"US",
    "sg:address":"1216 E Atlantic Blvd",
    "sg:city":"Pompano Beach",
    "sg:classifiers":[
        {
            "category":"Professional",
            "subcategory":"Lawyer & Legal Services",
            "type":"Services"
        }
    ],
    "sg:phone":"+1 954 942 9774",
    "sg:postcode":"33060",
    "sg:province":"FL",
    "wof:name":"Dunleavy & Trick",
    "wof:placetype":"venue"
},
  "geometry": {"coordinates":[-80.110866,26.231671],"type":"Point"}
}