{
  "type": "Feature",
  "properties": {
    "iso:country":"US",
    "sg:address":"2306 SE Harrington Ave",
    "sg:city":"Port Saint Lucie",
    "sg:classifiers":[
        {
            "category":"Building & Trades",
            "subcategory":"Construction",
            "type":"Services"
        }
    ],
    "sg:phone":"+1 772 335 5887",
    "sg:postcode":"34952",
    "sg:province":"FL",
    "sg:tags":[
        "hanging",
        "contractor"
    ],
    "wof:name":"ABF Painting",
    "wof:placetype":"venue"
},
  "geometry": {"coordinates":[-80.27822,27.264781],"type":"Point"}
}