{
  "type": "Feature",
  "properties": {
    "addr:full":"19689 Black Olive Ln Boca Raton FL 33498",
    "addr:housenumber":"19689",
    "addr:postcode":"33498",
    "addr:street":"Black Olive Ln",
    "iso:country":"US",
    "sg:address":"19689 Black Olive Ln",
    "sg:city":"Boca Raton",
    "sg:classifiers":[
        {
            "category":"Professional",
            "subcategory":"Research",
            "type":"Services"
        }
    ],
    "sg:phone":"+1 561 477 1858",
    "sg:postcode":"33498",
    "sg:province":"FL",
    "sg:tags":[
        "development",
        "laboratory"
    ],
    "wof:name":"Pharmaceutical Clinical Corp",
    "wof:placetype":"venue"
},
  "geometry": {"coordinates":[-80.217913,26.384161],"type":"Point"}
}