{
  "type": "Feature",
  "properties": {
    "iso:country":"US",
    "sg:address":"1950 NW 15th St",
    "sg:city":"Pompano Beach",
    "sg:classifiers":[
        {
            "category":"Manufacturing",
            "subcategory":"Chemicals & Compounds",
            "type":"Manufacturing & Wholesale Goods"
        }
    ],
    "sg:phone":"+1 954 979 3200",
    "sg:postcode":"33069",
    "sg:province":"FL",
    "sg:tags":[
        "paint",
        "mfg"
    ],
    "wof:name":"Color Your World",
    "wof:placetype":"venue"
},
  "geometry": {"coordinates":[-80.150655,26.2454],"type":"Point"}
}