{
  "type": "Feature",
  "properties": {
    "addr:full":"740 S Central Ave Apopka FL 32703",
    "addr:housenumber":"740",
    "addr:postcode":"32703",
    "addr:street":"S Central Ave",
    "iso:country":"US",
    "sg:address":"740 S Central Ave",
    "sg:city":"Apopka",
    "sg:classifiers":[
        {
            "category":"Shopping",
            "subcategory":"Baby Store",
            "type":"Retail Goods"
        },
        {
            "category":"Home & Garden",
            "subcategory":"Home Furnishings",
            "type":"Retail Goods"
        }
    ],
    "sg:phone":"+1 407 814 0700",
    "sg:postcode":"32703",
    "sg:province":"FL",
    "sg:tags":[
        "furniture-children's",
        "accessories"
    ],
    "wof:name":"Mr B's Rib Crib",
    "wof:placetype":"venue"
},
  "geometry": {"coordinates":[-81.51149700000001,28.66898],"type":"Point"}
}