{
  "type": "Feature",
  "properties": {
    "iso:country":"US",
    "sg:address":"2247 NW 20th St",
    "sg:city":"Miami",
    "sg:classifiers":[
        {
            "category":"Shopping",
            "subcategory":"Beauty & Cosmetics",
            "type":"Retail Goods"
        }
    ],
    "sg:phone":"+1 305 638 1478",
    "sg:postcode":"33142",
    "sg:province":"FL",
    "sg:tags":[
        "supply"
    ],
    "wof:name":"La Diora Inc",
    "wof:placetype":"venue"
},
  "geometry": {"coordinates":[-80.232536,25.794636],"type":"Point"}
}