{
  "type": "Feature",
  "properties": {
    "iso:country":"US",
    "sg:address":"22220 SW 184th Ave",
    "sg:city":"Miami",
    "sg:classifiers":[
        {
            "category":"Shopping",
            "subcategory":"Used Merchandise",
            "type":"Retail Goods"
        }
    ],
    "sg:phone":"+1 305 245 5179",
    "sg:postcode":"33170",
    "sg:province":"FL",
    "wof:name":"Jo Crafton Antiques",
    "wof:placetype":"venue"
},
  "geometry": {"coordinates":[-80.49042799999999,25.55782],"type":"Point"}
}