{
  "type": "Feature",
  "properties": {
    "iso:country":"US",
    "sg:address":"1200 Brickell Bay Dr",
    "sg:city":"Miami",
    "sg:classifiers":[
        {
            "category":"Personal",
            "subcategory":"Beauty Salon",
            "type":"Services"
        }
    ],
    "sg:phone":"+1 786 866 2798",
    "sg:postcode":"33131",
    "sg:province":"FL",
    "sg:tags":[
        "hair"
    ],
    "sg:website":"www.biguine.com",
    "wof:name":"Jean-Claude Biguine",
    "wof:placetype":"venue"
},
  "geometry": {"coordinates":[-80.19046,25.7618],"type":"Point"}
}