{
  "type": "Feature",
  "properties": {
    "addr:full":"15408 SW 138th Pl Miami FL 33177",
    "addr:housenumber":"15408",
    "addr:postcode":"33177",
    "addr:street":"Sw 138Th Pl",
    "iso:country":"US",
    "sg:address":"15408 SW 138th Pl",
    "sg:city":"Miami",
    "sg:classifiers":[
        {
            "category":"Professional",
            "type":"Services"
        }
    ],
    "sg:phone":"+1 305 235 3120",
    "sg:postcode":"33177",
    "sg:province":"FL",
    "wof:name":"Eddy Goza Inc",
    "wof:placetype":"venue"
},
  "geometry": {"coordinates":[-80.418121,25.624295],"type":"Point"}
}