{
  "type": "Feature",
  "properties": {
    "addr:full":"15535 Warfield Hwy Indiantown FL 34956",
    "addr:housenumber":"15535",
    "addr:postcode":"34956",
    "addr:street":"Warfield Hwy",
    "iso:country":"US",
    "sg:address":"15535 Warfield Hwy",
    "sg:city":"Indiantown",
    "sg:classifiers":[
        {
            "category":"Restaurant",
            "type":"Food & Drink"
        }
    ],
    "sg:phone":"+1 772 597 2460",
    "sg:postcode":"34956",
    "sg:province":"FL",
    "wof:name":"Cafe Los Amigos",
    "wof:placetype":"venue"
},
  "geometry": {"coordinates":[-80.465115,27.01955],"type":"Point"}
}