{
  "type": "Feature",
  "properties": {
    "iso:country":"US",
    "sg:address":"503 Sunset Rd",
    "sg:city":"Plant City",
    "sg:classifiers":[
        {
            "category":"Real Estate",
            "subcategory":"Real Estate Agent",
            "type":"Services"
        }
    ],
    "sg:phone":"+1 813 754 2637",
    "sg:postcode":"33563",
    "sg:province":"FL",
    "sg:tags":[
        "appraiser"
    ],
    "wof:name":"Bernard W Caton Appraiser",
    "wof:placetype":"venue"
},
  "geometry": {"coordinates":[-82.127202,28.021445],"type":"Point"}
}