{
  "type": "Feature",
  "properties": {
    "addr:full":"2712 John Moore Rd Brandon FL 33511",
    "addr:housenumber":"2712",
    "addr:postcode":"33511",
    "addr:street":"John Moore Rd",
    "iso:country":"US",
    "sg:address":"2712 John Moore Rd",
    "sg:city":"Brandon",
    "sg:classifiers":[
        {
            "category":"Manufacturing",
            "subcategory":"Apparel",
            "type":"Manufacturing & Wholesale Goods"
        }
    ],
    "sg:phone":"+1 813 657 5406",
    "sg:postcode":"33511",
    "sg:province":"FL",
    "sg:tags":[
        "embroidery"
    ],
    "wof:name":"Kats Design Shop",
    "wof:placetype":"venue"
},
  "geometry": {"coordinates":[-82.28565399999999,27.905467],"type":"Point"}
}