{
  "type": "Feature",
  "properties": {
    "addr:full":"214 W Alexander St Plant City FL 33563",
    "addr:housenumber":"214",
    "addr:postcode":"33563",
    "addr:street":"W Alexander St",
    "iso:country":"US",
    "sg:address":"214 W Alexander St",
    "sg:city":"Plant City",
    "sg:classifiers":[
        {
            "category":"Health Services",
            "subcategory":"Health Practitioner",
            "type":"Services"
        }
    ],
    "sg:phone":"+1 813 707 1509",
    "sg:postcode":"33563",
    "sg:province":"FL",
    "sg:tags":[
        "therapist",
        "physical"
    ],
    "wof:name":"Kessler Rehabilitation Ctr",
    "wof:placetype":"venue"
},
  "geometry": {"coordinates":[-82.12520000000001,27.988059],"type":"Point"}
}