{
  "type": "Feature",
  "properties": {
    "addr:full":"800 W Euclid Ave Dlnd Deland FL 32720",
    "addr:housenumber":"800",
    "addr:postcode":"32720",
    "addr:street":"W Euclid Ave",
    "iso:country":"US",
    "sg:address":"800 W Euclid Ave Dlnd",
    "sg:city":"Deland",
    "sg:classifiers":[
        {
            "category":"Sports & Exercise",
            "subcategory":"Golf",
            "type":"Entertainment"
        }
    ],
    "sg:phone":"+1 386 736 0733",
    "sg:postcode":"32720",
    "sg:province":"FL",
    "sg:tags":[
        "course"
    ],
    "wof:name":"Southridge Public Golf Course",
    "wof:placetype":"venue"
},
  "geometry": {"coordinates":[-81.31777200000001,29.02079],"type":"Point"}
}