{
  "type": "Feature",
  "properties": {
    "iso:country":"US",
    "sg:address":"250 Raby Ave",
    "sg:city":"Pensacola",
    "sg:classifiers":[
        {
            "category":"Professional",
            "subcategory":"Computer Services",
            "type":"Services"
        }
    ],
    "sg:phone":"+1 850 452 2990",
    "sg:postcode":"32509",
    "sg:province":"FL",
    "sg:tags":[
        "engineering",
        "system",
        "software"
    ],
    "wof:name":"S D C Inc",
    "wof:placetype":"venue"
},
  "geometry": {"coordinates":[-87.341588,30.464016],"type":"Point"}
}