{
  "type": "Feature",
  "properties": {
    "iso:country":"US",
    "sg:address":"8400 N Century Blvd",
    "sg:city":"Century",
    "sg:classifiers":[
        {
            "category":"Autos & Motor Vehicles",
            "subcategory":"Fuel & Gas Station",
            "type":"Retail Goods"
        }
    ],
    "sg:phone":"+1 850 256 5859",
    "sg:postcode":"32535",
    "sg:province":"FL",
    "sg:tags":[
        "oil"
    ],
    "wof:name":"Panhandle Service Ctr",
    "wof:placetype":"venue"
},
  "geometry": {"coordinates":[-87.256986,30.983349],"type":"Point"}
}