{
  "type": "Feature",
  "properties": {
    "addr:full":"1701 NE 8 Ave Gainesville FL 32641",
    "addr:housenumber":"1701",
    "addr:postcode":"32641",
    "addr:street":"Ne 8 Ave",
    "iso:country":"US",
    "sg:address":"1701 NE 8 Ave",
    "sg:city":"Gainesville",
    "sg:classifiers":[
        {
            "category":"Recreation",
            "type":"Entertainment"
        }
    ],
    "sg:phone":"+1 352 334 2185",
    "sg:postcode":"32641",
    "sg:province":"FL",
    "sg:tags":[
        "center"
    ],
    "wof:name":"Northeast Community Ctr",
    "wof:placetype":"venue"
},
  "geometry": {"coordinates":[-82.30278199999999,29.659194],"type":"Point"}
}