{
  "type": "Feature",
  "properties": {
    "iso:country":"US",
    "sg:address":"935 Carswell Ave",
    "sg:city":"Holly Hill",
    "sg:classifiers":[
        {
            "category":"Building & Trades",
            "subcategory":"Construction",
            "type":"Services"
        }
    ],
    "sg:phone":"+1 386 255 6243",
    "sg:postcode":"32117",
    "sg:province":"FL",
    "sg:tags":[
        "fire",
        "restoration",
        "damage"
    ],
    "wof:name":"Servpro",
    "wof:placetype":"venue"
},
  "geometry": {"coordinates":[-81.04060699999999,29.23954],"type":"Point"}
}