{
  "type": "Feature",
  "properties": {
    "addr:full":"2268 Glenmoore Rd N Clearwater FL 33764",
    "addr:housenumber":"2268",
    "addr:postcode":"33764",
    "addr:street":"Glenmoore Rd N",
    "iso:country":"US",
    "sg:address":"2268 Glenmoore Rd N",
    "sg:city":"Clearwater",
    "sg:classifiers":[
        {
            "category":"Manufacturing",
            "subcategory":"Apparel",
            "type":"Manufacturing & Wholesale Goods"
        }
    ],
    "sg:phone":"+1 727 539 7866",
    "sg:postcode":"33764",
    "sg:province":"FL",
    "wof:name":"Cyber Stitch",
    "wof:placetype":"venue"
},
  "geometry": {"coordinates":[-82.745057,27.952564],"type":"Point"}
}