{
  "type": "Feature",
  "properties": {
    "iso:country":"US",
    "sg:address":"41 N Bombay Ave",
    "sg:city":"Winter Springs",
    "sg:classifiers":[
        {
            "category":"Wholesale",
            "subcategory":"Home Furnishings",
            "type":"Manufacturing & Wholesale Goods"
        }
    ],
    "sg:phone":"+1 407 327 1560",
    "sg:postcode":"32708",
    "sg:province":"FL",
    "wof:name":"Seibert Inc",
    "wof:placetype":"venue"
},
  "geometry": {"coordinates":[-81.31133199999999,28.698774],"type":"Point"}
}