{
  "type": "Feature",
  "properties": {
    "iso:country":"US",
    "sg:address":"1964 19th Ave",
    "sg:city":"Vero Beach",
    "sg:classifiers":[
        {
            "category":"Banks & Credit Unions",
            "subcategory":"Bank",
            "type":"Services"
        }
    ],
    "sg:phone":"+1 772 567 2052",
    "sg:postcode":"32960",
    "sg:province":"FL",
    "sg:tags":[
        "loan",
        "real estate"
    ],
    "wof:name":"Evergreen Mortgage Co",
    "wof:placetype":"venue"
},
  "geometry": {"coordinates":[-80.40447899999999,27.63768],"type":"Point"}
}