{
  "type": "Feature",
  "properties": {
    "iso:country":"US",
    "sg:address":"1201 E Sunrise Blvd",
    "sg:city":"Fort Lauderdale",
    "sg:classifiers":[
        {
            "category":"Autos & Motor Vehicles",
            "subcategory":"Motorcycle Sales",
            "type":"Retail Goods"
        }
    ],
    "sg:phone":"+1 954 779 3669",
    "sg:postcode":"33304",
    "sg:province":"FL",
    "sg:tags":[
        "repair",
        "parts",
        "accessory"
    ],
    "wof:name":"Chaotic Motors",
    "wof:placetype":"venue"
},
  "geometry": {"coordinates":[-80.13059199999999,26.137152],"type":"Point"}
}