{
  "type": "Feature",
  "properties": {
    "addr:full":"742 W Ocean Dr Boynton Beach FL 33426",
    "addr:housenumber":"742",
    "addr:postcode":"33426",
    "addr:street":"W Ocean Dr",
    "iso:country":"US",
    "sg:address":"742 W Ocean Dr",
    "sg:city":"Boynton Beach",
    "sg:classifiers":[
        {
            "category":"Shopping",
            "subcategory":"Clothing, Apparel, & Fashions",
            "type":"Retail Goods"
        }
    ],
    "sg:phone":"+1 561 733 9459",
    "sg:postcode":"33426",
    "sg:province":"FL",
    "sg:tags":[
        "alteration"
    ],
    "wof:name":"Matadeen Enterprises",
    "wof:placetype":"venue"
},
  "geometry": {"coordinates":[-80.07846499999999,26.524762],"type":"Point"}
}