{
  "type": "Feature",
  "properties": {
    "iso:country":"US",
    "sg:address":"5660 Swift Rd",
    "sg:city":"Sarasota",
    "sg:classifiers":[
        {
            "category":"Education",
            "subcategory":"Dance Studio",
            "type":"Public Place"
        }
    ],
    "sg:phone":"+1 941 925 2411",
    "sg:postcode":"34231",
    "sg:province":"FL",
    "wof:name":"Ballroom",
    "wof:placetype":"venue"
},
  "geometry": {"coordinates":[-82.51424299999999,27.271442],"type":"Point"}
}