{
  "type": "Feature",
  "properties": {
    "iso:country":"US",
    "sg:address":"3648 Dubsdread Circle",
    "sg:city":"Orlando",
    "sg:classifiers":[
        {
            "category":"Professional",
            "type":"Services"
        }
    ],
    "sg:phone":"+1 407 451 2800",
    "sg:postcode":"32804",
    "sg:province":"FL",
    "sg:website":"finaltouchconstruction.net#cid=yelp",
    "wof:name":"Final Touch Construction, Inc",
    "wof:placetype":"venue"
},
  "geometry": {"coordinates":[-81.384558,28.588363],"type":"Point"}
}