{
  "type": "Feature",
  "properties": {
    "iso:country":"US",
    "sg:address":"7387 NW 36th St.",
    "sg:city":"Miami",
    "sg:classifiers":[
        {
            "category":"Restaurant",
            "type":"Food & Drink"
        }
    ],
    "sg:phone":"+1 305 499 9494",
    "sg:postcode":"33166",
    "sg:province":"FL",
    "wof:name":"El Rinconcito Latino",
    "wof:placetype":"venue"
},
  "geometry": {"coordinates":[-80.317021,25.809436],"type":"Point"}
}