{
  "type": "Feature",
  "properties": {
    "iso:country":"US",
    "sg:address":"1430 Rail Head Blvd",
    "sg:city":"Naples",
    "sg:phone":"+1 239 596 2005",
    "sg:postcode":"34110",
    "sg:province":"FL",
    "sg:tags":[
        "food",
        "equipment",
        "processing"
    ],
    "wof:name":"Itm",
    "wof:placetype":"venue"
},
  "geometry": {"coordinates":[-81.79164299999999,26.310241],"type":"Point"}
}