{
  "type": "Feature",
  "properties": {
    "addr:full":"10650 NW South River Dr Medley FL 33178",
    "addr:housenumber":"10650",
    "addr:postcode":"33178",
    "addr:street":"Nw South River Dr",
    "iso:country":"US",
    "sg:address":"10650 NW South River Dr",
    "sg:city":"Medley",
    "sg:classifiers":[
        {
            "category":"Wholesale",
            "subcategory":"Machinery & Supplies",
            "type":"Manufacturing & Wholesale Goods"
        }
    ],
    "sg:phone":"+1 305 888 8978",
    "sg:postcode":"33178",
    "sg:province":"FL",
    "sg:tags":[
        "compressor",
        "industrial",
        "gas"
    ],
    "sg:website":"www.arlecompressor.com",
    "wof:name":"Arle Compressor Systems Corp",
    "wof:placetype":"venue"
},
  "geometry": {"coordinates":[-80.345156,25.870093],"type":"Point"}
}