{
  "type": "Feature",
  "properties": {
    "iso:country":"US",
    "sg:address":"5305 Palm Aire Dr",
    "sg:city":"Sarasota",
    "sg:classifiers":[
        {
            "category":"Health Services",
            "subcategory":"Doctor",
            "type":"Services"
        }
    ],
    "sg:phone":"+1 941 351 8069",
    "sg:postcode":"34243",
    "sg:province":"FL",
    "sg:tags":[
        "osteopathic"
    ],
    "wof:name":"Dean Silverberg Do PA",
    "wof:placetype":"venue"
},
  "geometry": {"coordinates":[-82.500719,27.403723],"type":"Point"}
}