{
  "type": "Feature",
  "properties": {
    "addr:full":"11155 NW 33rd St Doral FL 33172",
    "addr:housenumber":"11155",
    "addr:postcode":"33172",
    "addr:street":"Nw 33Rd St",
    "iso:country":"US",
    "sg:address":"11155 NW 33rd St",
    "sg:city":"Doral",
    "sg:classifiers":[
        {
            "category":"Freight",
            "type":"Transportation"
        }
    ],
    "sg:phone":"+1 305 436 0402",
    "sg:postcode":"33172",
    "sg:province":"FL",
    "sg:tags":[
        "packing",
        "crating"
    ],
    "wof:name":"Bisac Freight",
    "wof:placetype":"venue"
},
  "geometry": {"coordinates":[-80.376448,25.804293],"type":"Point"}
}