{
  "type": "Feature",
  "properties": {
    "addr:full":"7602 Coronet Dr Sarasota FL 34240",
    "addr:housenumber":"7602",
    "addr:postcode":"34240",
    "addr:street":"Coronet Dr",
    "iso:country":"US",
    "sg:address":"7602 Coronet Dr",
    "sg:city":"Sarasota",
    "sg:classifiers":[
        {
            "category":"Wholesale",
            "subcategory":"Auto Parts",
            "type":"Manufacturing & Wholesale Goods"
        }
    ],
    "sg:phone":"+1 941 341 0292",
    "sg:postcode":"34240",
    "sg:province":"FL",
    "sg:tags":[
        "automobile"
    ],
    "wof:name":"Dye Works Auto Svc",
    "wof:placetype":"venue"
},
  "geometry": {"coordinates":[-82.418408,27.351466],"type":"Point"}
}