{
  "type": "Feature",
  "properties": {
    "iso:country":"US",
    "sg:address":"6711 2nd Avenue Cir W",
    "sg:city":"Bradenton",
    "sg:classifiers":[
        {
            "category":"Manufacturing",
            "subcategory":"Retail Goods",
            "type":"Manufacturing & Wholesale Goods"
        }
    ],
    "sg:phone":"+1 941 761 7950",
    "sg:postcode":"34209",
    "sg:province":"FL",
    "sg:tags":[
        "mfg",
        "hard",
        "floor",
        "covering"
    ],
    "wof:name":"Frank Berndt",
    "wof:placetype":"venue"
},
  "geometry": {"coordinates":[-82.629212,27.498167],"type":"Point"}
}