{
  "type": "Feature",
  "properties": {
    "addr:full":"2371 Kingston St S Saint Petersburg FL 33711",
    "addr:housenumber":"2371",
    "addr:postcode":"33711",
    "addr:street":"Kingston St S",
    "iso:country":"US",
    "sg:address":"2371 Kingston St S",
    "sg:city":"Saint Petersburg",
    "sg:classifiers":[
        {
            "category":"Building & Trades",
            "subcategory":"Landscaping Services",
            "type":"Services"
        }
    ],
    "sg:phone":"+1 727 415 4077",
    "sg:postcode":"33711",
    "sg:province":"FL",
    "sg:tags":[
        "landscape"
    ],
    "wof:name":"Vincent E Bell",
    "wof:placetype":"venue"
},
  "geometry": {"coordinates":[-82.68451899999999,27.746266],"type":"Point"}
}