{
  "type": "Feature",
  "properties": {
    "iso:country":"US",
    "sg:address":"5400 S University Dr",
    "sg:city":"Fort Lauderdale",
    "sg:classifiers":[
        {
            "category":"Banks & Credit Unions",
            "subcategory":"Bank",
            "type":"Services"
        }
    ],
    "sg:phone":"+1 954 915 8199",
    "sg:postcode":"33328",
    "sg:province":"FL",
    "sg:tags":[
        "loan",
        "broker"
    ],
    "wof:name":"Seascape Home Loans Inc",
    "wof:placetype":"venue"
},
  "geometry": {"coordinates":[-80.251636,26.050852],"type":"Point"}
}