{
  "type": "Feature",
  "properties": {
    "addr:full":"12137 SW 131st Ave Miami FL 33186",
    "addr:housenumber":"12137",
    "addr:postcode":"33186",
    "addr:street":"Sw 131St Ave",
    "iso:country":"US",
    "sg:address":"12137 SW 131st Ave",
    "sg:city":"Miami",
    "sg:classifiers":[
        {
            "category":"Building & Trades",
            "subcategory":"Electrical",
            "type":"Services"
        }
    ],
    "sg:phone":"+1 305 971 2011",
    "sg:postcode":"33186",
    "sg:province":"FL",
    "sg:tags":[
        "general",
        "electric",
        "contractor"
    ],
    "wof:name":"Falcon Redro Electrical Contrs",
    "wof:placetype":"venue"
},
  "geometry": {"coordinates":[-80.406401,25.654009],"type":"Point"}
}