{
  "type": "Feature",
  "properties": {
    "addr:full":"214 Boone Dr Auburndale FL 33823",
    "addr:housenumber":"214",
    "addr:postcode":"33823",
    "addr:street":"Boone Dr",
    "iso:country":"US",
    "sg:address":"214 Boone Dr",
    "sg:city":"Auburndale",
    "sg:classifiers":[
        {
            "category":"Health Services",
            "subcategory":"Podiatrist",
            "type":"Services"
        }
    ],
    "sg:phone":"+1 863 968 0489",
    "sg:postcode":"33823",
    "sg:province":"FL",
    "sg:tags":[
        "physician",
        "surgeons"
    ],
    "wof:name":"Cathrine T Benenati",
    "wof:placetype":"venue"
},
  "geometry": {"coordinates":[-81.77410999999999,28.066827],"type":"Point"}
}