{
  "type": "Feature",
  "properties": {
    "addr:full":"3253 Justina Rd Jacksonville FL 32211",
    "addr:housenumber":"3253",
    "addr:postcode":"32211",
    "addr:street":"Justina Rd",
    "iso:country":"US",
    "sg:address":"3253 Justina Rd",
    "sg:city":"Jacksonville",
    "sg:classifiers":[
        {
            "category":"Freight",
            "type":"Transportation"
        }
    ],
    "sg:phone":"+1 904 743 6803",
    "sg:postcode":"32211",
    "sg:province":"FL",
    "sg:tags":[
        "local",
        "trucking"
    ],
    "wof:name":"Rick Mills Trucking",
    "wof:placetype":"venue"
},
  "geometry": {"coordinates":[-81.60083899999999,30.357884],"type":"Point"}
}