{
  "type": "Feature",
  "properties": {
    "addr:full":"45 Spyglass Aly Placida FL 33946",
    "addr:housenumber":"45",
    "addr:postcode":"33946",
    "addr:street":"Spyglass Aly",
    "iso:country":"US",
    "sg:address":"45 Spyglass Aly",
    "sg:city":"Placida",
    "sg:classifiers":[
        {
            "category":"Manufacturing",
            "subcategory":"Tools & Machinery",
            "type":"Manufacturing & Wholesale Goods"
        }
    ],
    "sg:phone":"+1 941 697 3595",
    "sg:postcode":"33946",
    "sg:province":"FL",
    "sg:tags":[
        "flashlight"
    ],
    "wof:name":"Bill French",
    "wof:placetype":"venue"
},
  "geometry": {"coordinates":[-82.29861200000001,26.853004],"type":"Point"}
}