{
  "type": "Feature",
  "properties": {
    "addr:full":"2020 Mo Ho Dr Orlando FL 32839",
    "addr:postcode":"2020;32839",
    "addr:street":"Ho Dr",
    "iso:country":"US",
    "sg:address":"2020 Mo Ho Dr",
    "sg:city":"Orlando",
    "sg:classifiers":[
        {
            "category":"Local Transit",
            "type":"Transportation"
        }
    ],
    "sg:phone":"+1 407 241 0345",
    "sg:postcode":"32839",
    "sg:province":"FL",
    "sg:tags":[
        "limousine"
    ],
    "wof:name":"Selective Limousine",
    "wof:placetype":"venue"
},
  "geometry": {"coordinates":[-81.412882,28.508301],"type":"Point"}
}