{
  "type": "Feature",
  "properties": {
    "iso:country":"US",
    "sg:address":"824 Edward St",
    "sg:city":"Daytona Beach",
    "sg:classifiers":[
        {
            "category":"Retail",
            "subcategory":"Auto Repair",
            "type":"Services"
        }
    ],
    "sg:phone":"+1 386 258 8557",
    "sg:postcode":"32114",
    "sg:province":"FL",
    "sg:tags":[
        "body",
        "automobile",
        "painting"
    ],
    "wof:name":"Daytona Collision",
    "wof:placetype":"venue"
},
  "geometry": {"coordinates":[-81.04086700000001,29.221546],"type":"Point"}
}