{
  "type": "Feature",
  "properties": {
    "addr:full":"322 W Lake Mary Blvd Sanford FL 32773",
    "addr:housenumber":"322",
    "addr:postcode":"32773",
    "addr:street":"W Lake Mary Blvd",
    "iso:country":"US",
    "sg:address":"322 W Lake Mary Blvd",
    "sg:city":"Sanford",
    "sg:classifiers":[
        {
            "category":"Retail",
            "subcategory":"Laundry & Dry Cleaning",
            "type":"Services"
        }
    ],
    "sg:phone":"+1 407 330 7585",
    "sg:postcode":"32773",
    "sg:province":"FL",
    "sg:tags":[
        "cleaners"
    ],
    "wof:name":"Dry Clean America",
    "wof:placetype":"venue"
},
  "geometry": {"coordinates":[-81.29019,28.757605],"type":"Point"}
}