{
  "type": "Feature",
  "properties": {
    "iso:country":"US",
    "sg:address":"9407 Glades Rd",
    "sg:city":"Boca Raton",
    "sg:classifiers":[
        {
            "category":"Personal",
            "subcategory":"Adult",
            "type":"Services"
        }
    ],
    "sg:phone":"+1 561 368 3331",
    "sg:postcode":"33434",
    "sg:province":"FL",
    "sg:tags":[
        "escort"
    ],
    "wof:name":"A Angela Escorts Inc",
    "wof:placetype":"venue"
},
  "geometry": {"coordinates":[-80.192955,26.367969],"type":"Point"}
}