{
  "type": "Feature",
  "properties": {
    "iso:country":"US",
    "sg:address":"31840 Orange St",
    "sg:city":"Sorrento",
    "sg:classifiers":[
        {
            "category":"Farming",
            "subcategory":"Nursery",
            "type":"Manufacturing & Wholesale Goods"
        }
    ],
    "sg:phone":"+1 352 383 5061",
    "sg:postcode":"32776",
    "sg:province":"FL",
    "sg:tags":[
        "ornamental",
        "tree",
        "nurseries-plants"
    ],
    "wof:name":"Spring Valley Nursery",
    "wof:placetype":"venue"
},
  "geometry": {"coordinates":[-81.568274,28.81202],"type":"Point"}
}