{
  "type": "Feature",
  "properties": {
    "addr:full":"333 Kimi Ct Casselberry FL 32707",
    "addr:housenumber":"333",
    "addr:postcode":"32707",
    "addr:street":"Kimi Ct",
    "iso:country":"US",
    "sg:address":"333 Kimi Ct",
    "sg:city":"Casselberry",
    "sg:classifiers":[
        {
            "category":"Real Estate",
            "subcategory":"Real Estate Agent",
            "type":"Services"
        }
    ],
    "sg:phone":"+1 407 699 1758",
    "sg:postcode":"32707",
    "sg:province":"FL",
    "sg:tags":[
        "appraiser"
    ],
    "wof:name":"Eagle Appraisals",
    "wof:placetype":"venue"
},
  "geometry": {"coordinates":[-81.28760200000001,28.665061],"type":"Point"}
}