{
  "type": "Feature",
  "properties": {
    "addr:full":"2600 N E St Pensacola FL 32501",
    "addr:housenumber":"2600",
    "addr:postcode":"32501",
    "addr:street":"N E St",
    "iso:country":"US",
    "sg:address":"2600 N E St",
    "sg:city":"Pensacola",
    "sg:classifiers":[
        {
            "category":"Organizations",
            "subcategory":"Religious Organization",
            "type":"Services"
        }
    ],
    "sg:phone":"+1 850 469 9449",
    "sg:postcode":"32501",
    "sg:province":"FL",
    "sg:tags":[
        "church"
    ],
    "wof:name":"Church Of Christ E Street",
    "wof:placetype":"venue"
},
  "geometry": {"coordinates":[-87.228945,30.439411],"type":"Point"}
}