{
  "type": "Feature",
  "properties": {
    "iso:country":"US",
    "sg:address":"5950 Hazeltine National Dr",
    "sg:city":"Orlando",
    "sg:classifiers":[
        {
            "category":"Education",
            "subcategory":"Vocational School",
            "type":"Public Place"
        }
    ],
    "sg:phone":"+1 407 438 8875",
    "sg:postcode":"32822",
    "sg:province":"FL",
    "sg:tags":[
        "training",
        "computer"
    ],
    "wof:name":"Dcc Of Orlando",
    "wof:placetype":"venue"
},
  "geometry": {"coordinates":[-81.29626399999999,28.459159],"type":"Point"}
}