{
  "type": "Feature",
  "properties": {
    "iso:country":"US",
    "sg:address":"3200 NE 36th St",
    "sg:city":"Fort Lauderdale",
    "sg:classifiers":[
        {
            "category":"Farming",
            "subcategory":"Fish & Marine Products",
            "type":"Manufacturing & Wholesale Goods"
        }
    ],
    "sg:phone":"+1 954 801 8808",
    "sg:postcode":"33308",
    "sg:province":"FL",
    "sg:tags":[
        "management"
    ],
    "wof:name":"Capt Jackie Moore",
    "wof:placetype":"venue"
},
  "geometry": {"coordinates":[-80.10096799999999,26.172613],"type":"Point"}
}