{
  "type": "Feature",
  "properties": {
    "addr:full":"4520 el Mar Dr Lauderdl By Sea FL 33308",
    "addr:housenumber":"4520",
    "addr:postcode":"33308",
    "addr:street":"El Mar Dr",
    "iso:country":"US",
    "sg:address":"4520 el Mar Dr",
    "sg:city":"Lauderdl By Sea",
    "sg:classifiers":[
        {
            "category":"Travel",
            "subcategory":"Hotels & Motels",
            "type":"Entertainment"
        }
    ],
    "sg:phone":"+1 954 772 1660",
    "sg:postcode":"33308",
    "sg:province":"FL",
    "wof:name":"Souters Apartments",
    "wof:placetype":"venue"
},
  "geometry": {"coordinates":[-80.095299,26.194284],"type":"Point"}
}