{
  "type": "Feature",
  "properties": {
    "iso:country":"US",
    "sg:address":"1117 Arlington Ave N",
    "sg:city":"St Petersburg",
    "sg:classifiers":[
        {
            "category":"Health Services",
            "subcategory":"Doctor",
            "type":"Services"
        }
    ],
    "sg:phone":"+1 727 896 9029",
    "sg:postcode":"33705",
    "sg:province":"FL",
    "sg:tags":[
        "clinic"
    ],
    "wof:name":"Gambro Healthcare",
    "wof:placetype":"venue"
},
  "geometry": {"coordinates":[-82.65107999999999,27.772602],"type":"Point"}
}