{
  "type": "Feature",
  "properties": {
    "addr:full":"100 E Broward Blvd Fort Lauderdale FL 33301",
    "addr:housenumber":"100",
    "addr:postcode":"33301",
    "addr:street":"E Broward Blvd",
    "iso:country":"US",
    "sg:address":"100 E Broward Blvd",
    "sg:city":"Fort Lauderdale",
    "sg:classifiers":[
        {
            "category":"Retail",
            "subcategory":"Repair Shop",
            "type":"Services"
        }
    ],
    "sg:phone":"+1 954 446 7327",
    "sg:postcode":"33301",
    "sg:province":"FL",
    "sg:tags":[
        "lock",
        "locksmith"
    ],
    "wof:name":"24 Hour 7 Day Emergency",
    "wof:placetype":"venue"
},
  "geometry": {"coordinates":[-80.14152,26.12228],"type":"Point"}
}