{
  "type": "Feature",
  "properties": {
    "iso:country":"US",
    "sg:address":"333 Tamiami Trl",
    "sg:city":"Venice",
    "sg:classifiers":[
        {
            "category":"Health Services",
            "subcategory":"Health Practitioner",
            "type":"Services"
        }
    ],
    "sg:phone":"+1 941 486 1990",
    "sg:postcode":"34285",
    "sg:province":"FL",
    "sg:tags":[
        "psychotherapist"
    ],
    "wof:name":"Vincent Capano",
    "wof:placetype":"venue"
},
  "geometry": {"coordinates":[-82.444248,27.094787],"type":"Point"}
}