{
  "type": "Feature",
  "properties": {
    "addr:full":"112 Consoweld Dr Tampa FL 33619",
    "addr:housenumber":"112",
    "addr:postcode":"33619",
    "addr:street":"Consoweld Dr",
    "iso:country":"US",
    "sg:address":"112 Consoweld Dr",
    "sg:city":"Tampa",
    "sg:classifiers":[
        {
            "category":"Professional",
            "subcategory":"Business Services",
            "type":"Services"
        }
    ],
    "sg:phone":"+1 813 627 3288",
    "sg:postcode":"33619",
    "sg:province":"FL",
    "sg:tags":[
        "interior",
        "consultant",
        "design",
        "decorator"
    ],
    "wof:name":"Juliano Interior Millwork",
    "wof:placetype":"venue"
},
  "geometry": {"coordinates":[-82.36210800000001,27.948819],"type":"Point"}
}