{
  "type": "Feature",
  "properties": {
    "addr:full":"8195 SW 40th St Miami FL 33155",
    "addr:housenumber":"8195",
    "addr:postcode":"33155",
    "addr:street":"Sw 40Th St",
    "iso:country":"US",
    "sg:address":"8195 SW 40th St",
    "sg:city":"Miami",
    "sg:classifiers":[
        {
            "category":"Restaurant",
            "type":"Food & Drink"
        }
    ],
    "sg:phone":"+1 305 388 9337",
    "sg:postcode":"33155",
    "sg:province":"FL",
    "wof:name":"Empanadas 48 Inc",
    "wof:placetype":"venue"
},
  "geometry": {"coordinates":[-80.326758,25.733337],"type":"Point"}
}