{
  "type": "Feature",
  "properties": {
    "addr:full":"745 32nd Ter Vero Beach FL 32968",
    "addr:housenumber":"745",
    "addr:postcode":"32968",
    "addr:street":"32Nd Ter",
    "iso:country":"US",
    "sg:address":"745 32nd Ter",
    "sg:city":"Vero Beach",
    "sg:classifiers":[
        {
            "category":"Recreation",
            "type":"Entertainment"
        }
    ],
    "sg:phone":"+1 772 299 0057",
    "sg:postcode":"32968",
    "sg:province":"FL",
    "sg:tags":[
        "diving",
        "instruction"
    ],
    "wof:name":"Dive Training Co",
    "wof:placetype":"venue"
},
  "geometry": {"coordinates":[-80.418989,27.614141],"type":"Point"}
}