{
  "type": "Feature",
  "properties": {
    "addr:full":"3591 Fairgreen St Malabar FL 32950",
    "addr:housenumber":"3591",
    "addr:postcode":"32950",
    "addr:street":"Fairgreen St",
    "iso:country":"US",
    "sg:address":"3591 Fairgreen St",
    "sg:city":"Malabar",
    "sg:classifiers":[
        {
            "category":"Restaurant",
            "type":"Food & Drink"
        }
    ],
    "sg:phone":"+1 321 676 0531",
    "sg:postcode":"32950",
    "sg:province":"FL",
    "sg:tags":[
        "shop",
        "snack"
    ],
    "wof:name":"Birdies Egles Hbitat Golf Crse",
    "wof:placetype":"venue"
},
  "geometry": {"coordinates":[-80.567471,27.958701],"type":"Point"}
}