{
  "type": "Feature",
  "properties": {
    "iso:country":"US",
    "sg:address":"1350 Marseille Dr",
    "sg:city":"Miami Beach",
    "sg:classifiers":[
        {
            "category":"Restaurant",
            "type":"Food & Drink"
        }
    ],
    "sg:phone":"+1 305 284 1840",
    "sg:postcode":"33141",
    "sg:province":"FL",
    "sg:tags":[
        "chinese"
    ],
    "wof:name":"University Mami Panda Ex L331",
    "wof:placetype":"venue"
},
  "geometry": {"coordinates":[-80.135588,25.854597],"type":"Point"}
}