{
  "type": "Feature",
  "properties": {
    "addr:full":"4735 Sunbeam Rd Jacksonville FL 32257",
    "addr:postcode":"4735;32257",
    "addr:street":"Sunbeam Rd",
    "iso:country":"US",
    "sg:address":"4735 Sunbeam Rd",
    "sg:city":"Jacksonville",
    "sg:classifiers":[
        {
            "category":"Professional",
            "subcategory":"Lawyer & Legal Services",
            "type":"Services"
        }
    ],
    "sg:phone":"+1 904 251 1111",
    "sg:postcode":"32257",
    "sg:province":"FL",
    "sg:tags":[
        "attorney"
    ],
    "sg:website":"www.harrellandjohnson.com",
    "wof:name":"Harrell & Johnson PA",
    "wof:placetype":"venue"
},
  "geometry": {"coordinates":[-81.593338,30.206128],"type":"Point"}
}