{
  "type": "Feature",
  "properties": {
    "addr:full":"77 Carolina Ct Crawfordville FL 32327",
    "addr:housenumber":"77",
    "addr:postcode":"32327",
    "addr:street":"Carolina Ct",
    "iso:country":"US",
    "sg:address":"77 Carolina Ct",
    "sg:city":"Crawfordville",
    "sg:classifiers":[
        {
            "category":"Building & Trades",
            "subcategory":"Construction",
            "type":"Services"
        }
    ],
    "sg:phone":"+1 850 926 2833",
    "sg:postcode":"32327",
    "sg:province":"FL",
    "sg:tags":[
        "residential"
    ],
    "wof:name":"Greg Hensley Builder Inc",
    "wof:placetype":"venue"
},
  "geometry": {"coordinates":[-84.40017,30.125799],"type":"Point"}
}