{
  "type": "Feature",
  "properties": {
    "addr:full":"807 Lucerne Ave Lake Worth FL 33460",
    "addr:housenumber":"807",
    "addr:postcode":"33460",
    "addr:street":"Lucerne Ave",
    "iso:country":"US",
    "sg:address":"807 Lucerne Ave",
    "sg:city":"Lake Worth",
    "sg:classifiers":[
        {
            "category":"Organizations",
            "subcategory":"Professional Association",
            "type":"Services"
        }
    ],
    "sg:phone":"+1 561 582 4401",
    "sg:postcode":"33460",
    "sg:province":"FL",
    "sg:tags":[
        "chambers",
        "commerce"
    ],
    "sg:website":"www.lwchamber.com",
    "wof:name":"Greater Lake Worth Chmbr-Cmmrc",
    "wof:placetype":"venue"
},
  "geometry": {"coordinates":[-80.057271,26.616548],"type":"Point"}
}