{
  "type": "Feature",
  "properties": {
    "addr:full":"2916 69th St E Bradenton FL 34208",
    "addr:housenumber":"2916",
    "addr:postcode":"34208",
    "addr:street":"69Th St",
    "iso:country":"US",
    "sg:address":"2916 69th St E",
    "sg:city":"Bradenton",
    "sg:classifiers":[
        {
            "category":"Building & Trades",
            "subcategory":"Electrical",
            "type":"Services"
        }
    ],
    "sg:phone":"+1 941 746 3668",
    "sg:postcode":"34208",
    "sg:province":"FL",
    "sg:tags":[
        "electrical",
        "contractor"
    ],
    "wof:name":"Desoto Electric Corp",
    "wof:placetype":"venue"
},
  "geometry": {"coordinates":[-82.471238,27.471622],"type":"Point"}
}