{
  "type": "Feature",
  "properties": {
    "iso:country":"US",
    "sg:address":"14133 Us Hwy 1",
    "sg:city":"North Palm Beach",
    "sg:classifiers":[
        {
            "category":"Restaurant",
            "type":"Food & Drink"
        }
    ],
    "sg:menulink":"http://www.allmenus.com/fl/riviera-beach/28996-classicos-fine-italian/menu/",
    "sg:phone":"+1 561 622 9772",
    "sg:postcode":"33408",
    "sg:province":"FL",
    "sg:tags":[
        "italian"
    ],
    "wof:name":"Classicos Fine Italian",
    "wof:placetype":"venue"
},
  "geometry": {"coordinates":[-80.055351,26.862781],"type":"Point"}
}