{
  "type": "Feature",
  "properties": {
    "iso:country":"US",
    "sg:address":"8006 NW 154th St",
    "sg:city":"Hialeah",
    "sg:classifiers":[
        {
            "category":"Shopping",
            "type":"Retail Goods"
        }
    ],
    "sg:phone":"+1 305 823 5438",
    "sg:postcode":"33016",
    "sg:province":"FL",
    "sg:tags":[
        "merchandise"
    ],
    "wof:name":"Sparkling Pools",
    "wof:placetype":"venue"
},
  "geometry": {"coordinates":[-80.332949,25.91323],"type":"Point"}
}