{
  "type": "Feature",
  "properties": {
    "iso:country":"US",
    "sg:address":"3515 30th Ave N",
    "sg:city":"St Petersburg",
    "sg:classifiers":[
        {
            "category":"Food & Beverages",
            "subcategory":"Groceries & Convenience Stores",
            "type":"Retail Goods"
        }
    ],
    "sg:phone":"+1 727 521 4545",
    "sg:postcode":"33713",
    "sg:province":"FL",
    "sg:tags":[
        "grocer"
    ],
    "wof:name":"Orlando Produce",
    "wof:placetype":"venue"
},
  "geometry": {"coordinates":[-82.681496,27.799251],"type":"Point"}
}