{
  "type": "Feature",
  "properties": {
    "iso:country":"US",
    "sg:address":"8071 W 21st Ct",
    "sg:city":"Hialeah",
    "sg:classifiers":[
        {
            "category":"Retail",
            "subcategory":"Repair Shop",
            "type":"Services"
        }
    ],
    "sg:phone":"+1 305 822 6833",
    "sg:postcode":"33016",
    "sg:province":"FL",
    "sg:tags":[
        "conditioning",
        "air"
    ],
    "wof:name":"R & R Appliance & AC",
    "wof:placetype":"venue"
},
  "geometry": {"coordinates":[-80.327091,25.895442],"type":"Point"}
}