{
  "type": "Feature",
  "properties": {
    "addr:full":"1206 SW Sudder Ave Port St Lucie FL 34953",
    "addr:housenumber":"1206",
    "addr:postcode":"34953",
    "addr:street":"Sw Sudder Ave",
    "iso:country":"US",
    "sg:address":"1206 SW Sudder Ave",
    "sg:city":"Port St Lucie",
    "sg:classifiers":[
        {
            "category":"Building & Trades",
            "subcategory":"Construction",
            "type":"Services"
        }
    ],
    "sg:phone":"+1 772 340 0068",
    "sg:postcode":"34953",
    "sg:province":"FL",
    "sg:tags":[
        "carpenter"
    ],
    "wof:name":"Reubin Bishop's Carpentry",
    "wof:placetype":"venue"
},
  "geometry": {"coordinates":[-80.38891700000001,27.286615],"type":"Point"}
}