{
  "type": "Feature",
  "properties": {
    "addr:full":"1260 S Ferdon Blvd Crestview FL 32536",
    "addr:housenumber":"1260",
    "addr:postcode":"32536",
    "addr:street":"S Ferdon Blvd",
    "iso:country":"US",
    "sg:address":"1260 S Ferdon Blvd",
    "sg:city":"Crestview",
    "sg:classifiers":[
        {
            "category":"Food & Beverages",
            "subcategory":"Meat & Fish",
            "type":"Retail Goods"
        }
    ],
    "sg:phone":"+1 850 683 1818",
    "sg:postcode":"32536",
    "sg:province":"FL",
    "sg:tags":[
        "seafood"
    ],
    "wof:name":"Destin Seafood Market",
    "wof:placetype":"venue"
},
  "geometry": {"coordinates":[-86.563931,30.746583],"type":"Point"}
}