{
  "type": "Feature",
  "properties": {
    "iso:country":"US",
    "sg:address":"8600 NW 81st Rd",
    "sg:city":"Miami",
    "sg:classifiers":[
        {
            "category":"Freight",
            "type":"Transportation"
        }
    ],
    "sg:phone":"+1 305 805 2285",
    "sg:postcode":"33166",
    "sg:province":"FL",
    "sg:tags":[
        "provides",
        "arrangement"
    ],
    "sg:website":"www.bertlinglogistics.com",
    "wof:name":"Bertling Logistics Inc",
    "wof:placetype":"venue"
},
  "geometry": {"coordinates":[-80.331576,25.853882],"type":"Point"}
}