{
  "type": "Feature",
  "properties": {
    "addr:full":"1821 NE 24th St Lighthouse Point FL 33064",
    "addr:housenumber":"1821",
    "addr:postcode":"33064",
    "addr:street":"Ne 24Th St",
    "iso:country":"US",
    "sg:address":"1821 NE 24th St",
    "sg:city":"Lighthouse Point",
    "sg:classifiers":[
        {
            "category":"Insurance",
            "subcategory":"Insurance Agent",
            "type":"Services"
        }
    ],
    "sg:phone":"+1 954 941 0883",
    "sg:postcode":"33064",
    "sg:province":"FL",
    "wof:name":"Allstate Insurance",
    "wof:placetype":"venue"
},
  "geometry": {"coordinates":[-80.098603,26.261256],"type":"Point"}
}