{
  "type": "Feature",
  "properties": {
    "iso:country":"US",
    "sg:address":"6590 Swissco Dr",
    "sg:city":"Orlando",
    "sg:classifiers":[
        {
            "category":"Real Estate",
            "subcategory":"Real Estate Operator",
            "type":"Services"
        }
    ],
    "sg:phone":"+1 407 888 8695",
    "sg:postcode":"32822",
    "sg:province":"FL",
    "sg:tags":[
        "apartment"
    ],
    "wof:name":"Courtney Landing",
    "wof:placetype":"venue"
},
  "geometry": {"coordinates":[-81.300336,28.466133],"type":"Point"}
}