{
  "type": "Feature",
  "properties": {
    "addr:full":"2077 1st St Fort Myers FL 33901",
    "addr:housenumber":"2077",
    "addr:postcode":"33901",
    "addr:street":"1St St",
    "iso:country":"US",
    "sg:address":"2077 1st St",
    "sg:city":"Fort Myers",
    "sg:classifiers":[
        {
            "category":"Professional",
            "subcategory":"Accounting & Tax Preparation",
            "type":"Services"
        }
    ],
    "sg:phone":"+1 239 337 1979",
    "sg:postcode":"33901",
    "sg:province":"FL",
    "sg:tags":[
        "accountant"
    ],
    "wof:name":"Holt Joanne CPA",
    "wof:placetype":"venue"
},
  "geometry": {"coordinates":[-81.872398,26.643],"type":"Point"}
}