{
  "type": "Feature",
  "properties": {
    "addr:full":"14740 Biscayne Blvd North Miami Beach FL 33181",
    "addr:housenumber":"14740",
    "addr:postcode":"33181",
    "addr:street":"Biscayne Blvd",
    "iso:country":"US",
    "sg:address":"14740 Biscayne Blvd",
    "sg:city":"North Miami Beach",
    "sg:classifiers":[
        {
            "category":"Sports & Exercise",
            "subcategory":"Gym",
            "type":"Entertainment"
        }
    ],
    "sg:phone":"+1 305 947 5722",
    "sg:postcode":"33181",
    "sg:province":"FL",
    "sg:website":"www.snapfitness.com/northmiamibeach",
    "wof:name":"Snap Fitness 24/7",
    "wof:placetype":"venue"
},
  "geometry": {"coordinates":[-80.157481,25.910615],"type":"Point"}
}