{
  "type": "Feature",
  "properties": {
    "addr:full":"10670 Biscayne Blvd Jacksonville FL 32218",
    "addr:housenumber":"10670",
    "addr:postcode":"32218",
    "addr:street":"Biscayne Blvd",
    "iso:country":"US",
    "sg:address":"10670 Biscayne Blvd",
    "sg:city":"Jacksonville",
    "sg:classifiers":[
        {
            "category":"Restaurant",
            "type":"Food & Drink"
        }
    ],
    "sg:phone":"+1 904 696 3244",
    "sg:postcode":"32218",
    "sg:province":"FL",
    "wof:name":"Papa's Bbq Pit & Detailing",
    "wof:placetype":"venue"
},
  "geometry": {"coordinates":[-81.671668,30.429375],"type":"Point"}
}