{
  "type": "Feature",
  "properties": {
    "iso:country":"US",
    "sg:address":"810 NE Park St",
    "sg:city":"Okeechobee",
    "sg:classifiers":[
        {
            "category":"Home & Garden",
            "subcategory":"Furniture",
            "type":"Retail Goods"
        }
    ],
    "sg:phone":"+1 863 763 6293",
    "sg:postcode":"34972",
    "sg:province":"FL",
    "wof:name":"Royal's Furniture",
    "wof:placetype":"venue"
},
  "geometry": {"coordinates":[-80.821578,27.24368],"type":"Point"}
}