{
  "type": "Feature",
  "properties": {
    "iso:country":"US",
    "sg:address":"6741 Land O Lakes Blvd",
    "sg:city":"Land O Lakes",
    "sg:classifiers":[
        {
            "category":"Real Estate",
            "subcategory":"Real Estate Agent",
            "type":"Services"
        }
    ],
    "sg:phone":"+1 813 996 4588",
    "sg:postcode":"34638",
    "sg:province":"FL",
    "sg:tags":[
        "appraiser"
    ],
    "wof:name":"Rice Appraisals Inc",
    "wof:placetype":"venue"
},
  "geometry": {"coordinates":[-82.472902,28.256119],"type":"Point"}
}