{
  "type": "Feature",
  "properties": {
    "addr:full":"15885 NW 16th Ct Pembroke Pines FL 33028",
    "addr:housenumber":"15885",
    "addr:postcode":"33028",
    "addr:street":"Nw 16Th Ct",
    "iso:country":"US",
    "sg:address":"15885 NW 16th Ct",
    "sg:city":"Pembroke Pines",
    "sg:classifiers":[
        {
            "category":"Retail",
            "subcategory":"Repair Shop",
            "type":"Services"
        }
    ],
    "sg:phone":"+1 954 392 1301",
    "sg:postcode":"33028",
    "sg:province":"FL",
    "sg:tags":[
        "equipment",
        "conditioning",
        "air"
    ],
    "wof:name":"A & H Air Conditioning",
    "wof:placetype":"venue"
},
  "geometry": {"coordinates":[-80.360056,26.026585],"type":"Point"}
}