{
  "type": "Feature",
  "properties": {
    "addr:full":"1030 N Orange Ave Orlando FL 32801",
    "addr:housenumber":"1030",
    "addr:postcode":"32801",
    "addr:street":"N Orange Ave",
    "iso:country":"US",
    "sg:address":"1030 N Orange Ave",
    "sg:city":"Orlando",
    "sg:classifiers":[
        {
            "category":"Health Services",
            "subcategory":"Medical Lab",
            "type":"Services"
        }
    ],
    "sg:phone":"+1 407 367 0944",
    "sg:postcode":"32801",
    "sg:province":"FL",
    "sg:tags":[
        "control",
        "pain"
    ],
    "wof:name":"Pain Care Holdings Inc",
    "wof:placetype":"venue"
},
  "geometry": {"coordinates":[-81.37693,28.559545],"type":"Point"}
}