{
  "type": "Feature",
  "properties": {
    "iso:country":"US",
    "sg:address":"7311 Orange Blossom Ave",
    "sg:city":"Port Richey",
    "sg:classifiers":[
        {
            "category":"Building & Trades",
            "subcategory":"Construction",
            "type":"Services"
        }
    ],
    "sg:phone":"+1 727 868 0212",
    "sg:postcode":"34668",
    "sg:province":"FL",
    "sg:tags":[
        "coping",
        "plastering",
        "tiling",
        "pool",
        "swimming"
    ],
    "wof:name":"Sta-Brite Pool Svc",
    "wof:placetype":"venue"
},
  "geometry": {"coordinates":[-82.694424,28.309826],"type":"Point"}
}