{
  "type": "Feature",
  "properties": {
    "iso:country":"US",
    "sg:address":"728 Parkside Pointe Blvd",
    "sg:city":"Apopka",
    "sg:classifiers":[
        {
            "category":"Place Of Worship",
            "subcategory":"Church",
            "type":"Public Place"
        },
        {
            "category":"Place Of Worship",
            "type":"Public Place"
        }
    ],
    "sg:phone":"+1 407 889 3253",
    "sg:postcode":"32712",
    "sg:province":"FL",
    "sg:tags":[
        "churches-pentecostal-independent",
        "churches-pentecostal"
    ],
    "wof:name":"First United Pentecostal Church Of Greater Dayto",
    "wof:placetype":"venue"
},
  "geometry": {"coordinates":[-81.52808,28.68725],"type":"Point"}
}