{
  "type": "Feature",
  "properties": {
    "addr:full":"1601 S County Rd 427 Casselberry FL 32707",
    "addr:housenumber":"1601",
    "addr:postcode":"32707",
    "addr:street":"S County Rd 427",
    "iso:country":"US",
    "sg:address":"1601 S County Rd 427",
    "sg:city":"Casselberry",
    "sg:classifiers":[
        {
            "category":"Home & Garden",
            "subcategory":"Building Materials",
            "type":"Retail Goods"
        }
    ],
    "sg:phone":"+1 407 339 5311",
    "sg:postcode":"32707",
    "sg:province":"FL",
    "sg:tags":[
        "supply"
    ],
    "wof:name":"Inland Materials Inc",
    "wof:placetype":"venue"
},
  "geometry": {"coordinates":[-81.31300400000001,28.659901],"type":"Point"}
}