{
  "type": "Feature",
  "properties": {
    "addr:full":"118 Ridge Rd Crescent City FL 32180",
    "addr:housenumber":"118",
    "addr:postcode":"32180",
    "addr:street":"Ridge Rd Crescent",
    "iso:country":"US",
    "sg:address":"118 Ridge Rd",
    "sg:city":"Crescent City",
    "sg:classifiers":[
        {
            "category":"Manufacturing",
            "subcategory":"Lumber",
            "type":"Manufacturing & Wholesale Goods"
        }
    ],
    "sg:phone":"+1 386 698 2773",
    "sg:postcode":"32180",
    "sg:province":"FL",
    "sg:tags":[
        "mill"
    ],
    "wof:name":"Palmer Sawmill",
    "wof:placetype":"venue"
},
  "geometry": {"coordinates":[-81.438213,29.249257],"type":"Point"}
}