{
  "type": "Feature",
  "properties": {
    "addr:full":"923 Country Club Blvd Cape Coral FL 33990",
    "addr:housenumber":"923",
    "addr:postcode":"33990",
    "addr:street":"Country Club Blvd",
    "iso:country":"US",
    "sg:address":"923 Country Club Blvd",
    "sg:city":"Cape Coral",
    "sg:classifiers":[
        {
            "category":"Building & Trades",
            "subcategory":"Construction",
            "type":"Services"
        }
    ],
    "sg:phone":"+1 239 574 5633",
    "sg:postcode":"33990",
    "sg:province":"FL",
    "sg:tags":[
        "tile",
        "dealer"
    ],
    "wof:name":"East Cape Stone & Tile",
    "wof:placetype":"venue"
},
  "geometry": {"coordinates":[-81.95250299999999,26.633557],"type":"Point"}
}