{
  "type": "Feature",
  "properties": {
    "iso:country":"US",
    "sg:address":"15372 Fiddlesticks Blvd",
    "sg:city":"Fort Myers",
    "sg:classifiers":[
        {
            "category":"Real Estate",
            "subcategory":"Developer",
            "type":"Services"
        }
    ],
    "sg:phone":"+1 239 225 1532",
    "sg:postcode":"33912",
    "sg:province":"FL",
    "wof:name":"Nddc Inc",
    "wof:placetype":"venue"
},
  "geometry": {"coordinates":[-81.815831,26.51085],"type":"Point"}
}