{
  "type": "Feature",
  "properties": {
    "addr:full":"16480 S Oleander Dr Fort Myers FL 33908",
    "addr:housenumber":"16480",
    "addr:postcode":"33908",
    "addr:street":"S Oleander Dr",
    "iso:country":"US",
    "sg:address":"16480 S Oleander Dr",
    "sg:city":"Fort Myers",
    "sg:classifiers":[
        {
            "category":"Building & Trades",
            "subcategory":"Landscaping Services",
            "type":"Services"
        }
    ],
    "sg:phone":"+1 239 466 5314",
    "sg:postcode":"33908",
    "sg:province":"FL",
    "sg:tags":[
        "landscape"
    ],
    "wof:name":"Yardworks Ltd SW Florida",
    "wof:placetype":"venue"
},
  "geometry": {"coordinates":[-81.96911,26.49941],"type":"Point"}
}