{
  "type": "Feature",
  "properties": {
    "iso:country":"US",
    "sg:address":"3801 Eagle Preserve Pt",
    "sg:city":"Sanford",
    "sg:classifiers":[
        {
            "category":"Building & Trades",
            "subcategory":"Construction",
            "type":"Services"
        }
    ],
    "sg:phone":"+1 407 322 8155",
    "sg:postcode":"32773",
    "sg:province":"FL",
    "sg:tags":[
        "contractor"
    ],
    "sg:website":"www.kbhome.com",
    "wof:name":"Kb Home Orlando",
    "wof:placetype":"venue"
},
  "geometry": {"coordinates":[-81.270788,28.752643],"type":"Point"}
}