{
  "type": "Feature",
  "properties": {
    "addr:full":"1305 N Paul Russell Rd Tallahassee FL 32301",
    "addr:housenumber":"1305",
    "addr:postcode":"32301",
    "addr:street":"N Paul Russell Rd",
    "iso:country":"US",
    "sg:address":"1305 N Paul Russell Rd",
    "sg:city":"Tallahassee",
    "sg:classifiers":[
        {
            "category":"Personal",
            "subcategory":"Beauty Salon",
            "type":"Services"
        }
    ],
    "sg:phone":"+1 850 878 7722",
    "sg:postcode":"32301",
    "sg:province":"FL",
    "wof:name":"Artisan Salon & Spa",
    "wof:placetype":"venue"
},
  "geometry": {"coordinates":[-84.243579,30.428819],"type":"Point"}
}