{
  "type": "Feature",
  "properties": {
    "addr:full":"3400 SW 17th Pl Cape Coral FL 33914",
    "addr:housenumber":"3400",
    "addr:postcode":"33914",
    "addr:street":"Sw 17Th Pl",
    "iso:country":"US",
    "sg:address":"3400 SW 17th Pl",
    "sg:city":"Cape Coral",
    "sg:classifiers":[
        {
            "category":"Education",
            "subcategory":"School",
            "type":"Public Place"
        }
    ],
    "sg:phone":"+1 239 549 2726",
    "sg:postcode":"33914",
    "sg:province":"FL",
    "wof:name":"Gulf Elementary School",
    "wof:placetype":"venue"
},
  "geometry": {"coordinates":[-82.01066,26.587494],"type":"Point"}
}