{
  "type": "Feature",
  "properties": {
    "addr:full":"7115 Karden Way Orlando FL 32822",
    "addr:housenumber":"7115",
    "addr:postcode":"32822",
    "addr:street":"Karden Way",
    "iso:country":"US",
    "sg:address":"7115 Karden Way",
    "sg:city":"Orlando",
    "sg:classifiers":[
        {
            "category":"Communications",
            "type":"Services"
        }
    ],
    "sg:phone":"+1 407 925 3778",
    "sg:postcode":"32822",
    "sg:province":"FL",
    "wof:name":"Tito Communications Inc",
    "wof:placetype":"venue"
},
  "geometry": {"coordinates":[-81.29157499999999,28.52449],"type":"Point"}
}