{
  "type": "Feature",
  "properties": {
    "iso:country":"US",
    "sg:address":"14036 Port Cir",
    "sg:city":"Palm Beach Gardens",
    "sg:classifiers":[
        {
            "category":"Professional",
            "type":"Services"
        }
    ],
    "sg:phone":"+1 561 622 8589",
    "sg:postcode":"33410",
    "sg:province":"FL",
    "wof:name":"Healthy Happy Hour Inc",
    "wof:placetype":"venue"
},
  "geometry": {"coordinates":[-80.07323100000001,26.882942],"type":"Point"}
}