{
  "type": "Feature",
  "properties": {
    "addr:full":"2274 SW 22nd St Coral Gables FL 33145",
    "addr:housenumber":"2274",
    "addr:postcode":"33145",
    "addr:street":"Sw 22Nd St",
    "iso:country":"US",
    "sg:address":"2274 SW 22nd St",
    "sg:city":"Coral Gables",
    "sg:classifiers":[
        {
            "category":"Personal",
            "subcategory":"Beauty Salon",
            "type":"Services"
        }
    ],
    "sg:phone":"+1 305 857 0107",
    "sg:postcode":"33145",
    "sg:province":"FL",
    "wof:name":"Head To Toe",
    "wof:placetype":"venue"
},
  "geometry": {"coordinates":[-80.230788,25.750505],"type":"Point"}
}