{
  "type": "Feature",
  "properties": {
    "iso:country":"US",
    "sg:address":"1775 Lake Pl",
    "sg:city":"Venice",
    "sg:classifiers":[
        {
            "category":"Building & Trades",
            "subcategory":"Cleaning & Sanitation",
            "type":"Services"
        }
    ],
    "sg:phone":"+1 941 408 7078",
    "sg:postcode":"34293",
    "sg:province":"FL",
    "sg:tags":[
        "janitor"
    ],
    "wof:name":"Gretchen Otto Cleaning",
    "wof:placetype":"venue"
},
  "geometry": {"coordinates":[-82.398574,27.071724],"type":"Point"}
}