{
  "type": "Feature",
  "properties": {
    "addr:full":"9131 Gene Johnson Rd St Augustine FL 32080",
    "addr:housenumber":"9131",
    "addr:postcode":"32080",
    "addr:street":"Gene Johnson Rd St",
    "iso:country":"US",
    "sg:address":"9131 Gene Johnson Rd",
    "sg:city":"St Augustine",
    "sg:classifiers":[
        {
            "category":"Professional",
            "type":"Services"
        }
    ],
    "sg:phone":"+1 904 461 0028",
    "sg:postcode":"32080",
    "sg:province":"FL",
    "sg:tags":[
        "establishment"
    ],
    "wof:name":"T C Enterprises",
    "wof:placetype":"venue"
},
  "geometry": {"coordinates":[-81.22587900000001,29.698461],"type":"Point"}
}