{
  "type": "Feature",
  "properties": {
    "iso:country":"US",
    "sg:address":"2807 38th Ave N",
    "sg:city":"St Petersburg",
    "sg:classifiers":[
        {
            "category":"Restaurant",
            "type":"Food & Drink"
        }
    ],
    "sg:phone":"+1 727 522 6168",
    "sg:postcode":"33713",
    "sg:province":"FL",
    "wof:name":"Astra",
    "wof:placetype":"venue"
},
  "geometry": {"coordinates":[-82.673293,27.806583],"type":"Point"}
}