{
  "type": "Feature",
  "properties": {
    "iso:country":"US",
    "sg:address":"7451 NW 63rd St",
    "sg:city":"Miami",
    "sg:classifiers":[
        {
            "category":"Shopping",
            "subcategory":"Party Supplies",
            "type":"Retail Goods"
        },
        {
            "category":"Personal",
            "type":"Services"
        }
    ],
    "sg:phone":"+1 305 477 2021",
    "sg:postcode":"33166",
    "sg:province":"FL",
    "sg:tags":[
        "planning",
        "event",
        "toilets-portable"
    ],
    "wof:name":"Able Sanitation Inc",
    "wof:placetype":"venue"
},
  "geometry": {"coordinates":[-80.3181,25.830601],"type":"Point"}
}