{
  "type": "Feature",
  "properties": {
    "addr:full":"104 N Magnolia Dr Tallahassee FL 32301",
    "addr:housenumber":"104",
    "addr:postcode":"32301",
    "addr:street":"N Magnolia Dr",
    "iso:country":"US",
    "sg:address":"104 N Magnolia Dr",
    "sg:city":"Tallahassee",
    "sg:classifiers":[
        {
            "category":"Professional",
            "subcategory":"Accounting & Tax Preparation",
            "type":"Services"
        }
    ],
    "sg:phone":"+1 850 224 4178",
    "sg:postcode":"32301",
    "sg:province":"FL",
    "sg:tags":[
        "accountant"
    ],
    "wof:name":"Betts Rogers Schenck & Jones",
    "wof:placetype":"venue"
},
  "geometry": {"coordinates":[-84.26183899999999,30.442675],"type":"Point"}
}