{
  "type": "Feature",
  "properties": {
    "iso:country":"US",
    "sg:address":"8501 Philatelic Dr",
    "sg:city":"Spring Hill",
    "sg:classifiers":[
        {
            "category":"Professional",
            "type":"Services"
        }
    ],
    "sg:phone":"+1 352 683 3780",
    "sg:postcode":"34606",
    "sg:province":"FL",
    "wof:name":"Post Office Inc",
    "wof:placetype":"venue"
},
  "geometry": {"coordinates":[-82.575564,28.484446],"type":"Point"}
}