{
  "type": "Feature",
  "properties": {
    "iso:country":"US",
    "sg:address":"12336 Sarah Towers Ln S",
    "sg:city":"Jacksonville",
    "sg:classifiers":[
        {
            "category":"Building & Trades",
            "subcategory":"Construction",
            "type":"Services"
        }
    ],
    "sg:phone":"+1 904 434 9955",
    "sg:postcode":"32225",
    "sg:province":"FL",
    "sg:tags":[
        "paint",
        "contractor"
    ],
    "wof:name":"Jls Family Enterprises Inc",
    "wof:placetype":"venue"
},
  "geometry": {"coordinates":[-81.47592400000001,30.351377],"type":"Point"}
}