{
  "type": "Feature",
  "properties": {
    "iso:country":"US",
    "sg:address":"3766 Barkis Ave",
    "sg:city":"Boynton Beach",
    "sg:classifiers":[
        {
            "category":"Building & Trades",
            "subcategory":"Pest Control",
            "type":"Services"
        }
    ],
    "sg:phone":"+1 561 733 1312",
    "sg:postcode":"33436",
    "sg:province":"FL",
    "wof:name":"Coastal Pest Control",
    "wof:placetype":"venue"
},
  "geometry": {"coordinates":[-80.10292,26.541726],"type":"Point"}
}