{
  "type": "Feature",
  "properties": {
    "iso:country":"US",
    "sg:address":"4972 NE 73rd Dr",
    "sg:city":"Wildwood",
    "sg:classifiers":[
        {
            "category":"Health Services",
            "subcategory":"Medical Lab",
            "type":"Services"
        }
    ],
    "sg:phone":"+1 352 748 3861",
    "sg:postcode":"34785",
    "sg:province":"FL",
    "sg:tags":[
        "laboratory",
        "dental"
    ],
    "wof:name":"Crown Dental Laboratories Inc",
    "wof:placetype":"venue"
},
  "geometry": {"coordinates":[-81.98209300000001,28.826905],"type":"Point"}
}