{
  "type": "Feature",
  "properties": {
    "iso:country":"US",
    "sg:address":"2538 NW 6th St",
    "sg:city":"Ocala",
    "sg:classifiers":[
        {
            "category":"Manufacturing",
            "subcategory":"Glass & Minerals",
            "type":"Manufacturing & Wholesale Goods"
        }
    ],
    "sg:phone":"+1 352 629 8691",
    "sg:postcode":"34475",
    "sg:province":"FL",
    "sg:tags":[
        "plate",
        "window",
        "replacement",
        "repair"
    ],
    "wof:name":"Sun Glass & Mirror Co Inc",
    "wof:placetype":"venue"
},
  "geometry": {"coordinates":[-82.166151,29.192297],"type":"Point"}
}