{
  "type": "Feature",
  "properties": {
    "iso:country":"US",
    "sg:address":"4053 Ilex Cir N",
    "sg:city":"Palm Beach Gdns",
    "sg:classifiers":[
        {
            "category":"Wholesale",
            "subcategory":"Electrical",
            "type":"Manufacturing & Wholesale Goods"
        }
    ],
    "sg:phone":"+1 561 775 6995",
    "sg:postcode":"33410",
    "sg:province":"FL",
    "sg:tags":[
        "system",
        "repair",
        "power",
        "emergency",
        "supply"
    ],
    "wof:name":"Absolute Power & Technologies",
    "wof:placetype":"venue"
},
  "geometry": {"coordinates":[-80.10024199999999,26.819222],"type":"Point"}
}