{
  "type": "Feature",
  "properties": {
    "addr:full":"292 S County Rd Palm Beach FL 33480",
    "addr:housenumber":"292",
    "addr:postcode":"33480",
    "addr:street":"S County Rd",
    "iso:country":"US",
    "sg:address":"292 S County Rd",
    "sg:city":"Palm Beach",
    "sg:classifiers":[
        {
            "category":"Professional",
            "subcategory":"Business Services",
            "type":"Services"
        }
    ],
    "sg:phone":"+1 561 659 1545",
    "sg:postcode":"33480",
    "sg:province":"FL",
    "wof:name":"World Class Yachts Inc",
    "wof:placetype":"venue"
},
  "geometry": {"coordinates":[-80.036489,26.704789],"type":"Point"}
}