{
  "type": "Feature",
  "properties": {
    "addr:full":"317 Prestwick Ct Oviedo FL 32765",
    "addr:housenumber":"317",
    "addr:postcode":"32765",
    "addr:street":"Prestwick Ct",
    "iso:country":"US",
    "sg:address":"317 Prestwick Ct",
    "sg:city":"Oviedo",
    "sg:classifiers":[
        {
            "category":"Real Estate",
            "subcategory":"Real Estate Agent",
            "type":"Services"
        }
    ],
    "sg:phone":"+1 407 366 5082",
    "sg:postcode":"32765",
    "sg:province":"FL",
    "wof:name":"Agb Properties Inc",
    "wof:placetype":"venue"
},
  "geometry": {"coordinates":[-81.21922600000001,28.640446],"type":"Point"}
}