{
  "type": "Feature",
  "properties": {
    "addr:full":"2090 Palm Ave Hialeah FL 33010",
    "addr:housenumber":"2090",
    "addr:postcode":"33010",
    "addr:street":"Palm Ave",
    "iso:country":"US",
    "sg:address":"2090 Palm Ave",
    "sg:city":"Hialeah",
    "sg:classifiers":[
        {
            "category":"Autos & Motor Vehicles",
            "subcategory":"Fuel & Gas Station",
            "type":"Retail Goods"
        }
    ],
    "sg:phone":"+1 305 887 6754",
    "sg:postcode":"33010",
    "sg:province":"FL",
    "wof:name":"Palm Ave Enterprises",
    "wof:placetype":"venue"
},
  "geometry": {"coordinates":[-80.281898,25.840799],"type":"Point"}
}