{
  "type": "Feature",
  "properties": {
    "addr:full":"4905 34th St S Saint Petersburg FL 33711",
    "addr:housenumber":"4905",
    "addr:postcode":"33711",
    "addr:street":"34Th St S",
    "iso:country":"US",
    "sg:address":"4905 34th St S",
    "sg:city":"Saint Petersburg",
    "sg:classifiers":[
        {
            "category":"Real Estate",
            "subcategory":"Real Estate Agent",
            "type":"Services"
        }
    ],
    "sg:phone":"+1 727 866 1491",
    "sg:postcode":"33711",
    "sg:province":"FL",
    "wof:name":"Realty Solutions of Tampa",
    "wof:placetype":"venue"
},
  "geometry": {"coordinates":[-82.679366,27.725515],"type":"Point"}
}