{
  "type": "Feature",
  "properties": {
    "addr:full":"7180 Silver Oak Dr Port Saint Lucie FL 34952",
    "addr:housenumber":"7180",
    "addr:postcode":"34952",
    "addr:street":"Silver Oak Dr",
    "iso:country":"US",
    "sg:address":"7180 Silver Oak Dr",
    "sg:city":"Port Saint Lucie",
    "sg:classifiers":[
        {
            "category":"Farming",
            "subcategory":"Nursery",
            "type":"Manufacturing & Wholesale Goods"
        }
    ],
    "sg:phone":"+1 772 878 3911",
    "sg:postcode":"34952",
    "sg:province":"FL",
    "wof:name":"Dorough Nursery",
    "wof:placetype":"venue"
},
  "geometry": {"coordinates":[-80.30967,27.33446],"type":"Point"}
}