{
  "type": "Feature",
  "properties": {
    "addr:full":"9200 S Dadeland Blvd # 515 Miami FL 33156",
    "addr:housenumber":"9200",
    "addr:postcode":"33156",
    "addr:street":"S Dadeland Blvd # 515",
    "iso:country":"US",
    "sg:address":"9200 S Dadeland Blvd # 515",
    "sg:city":"Miami",
    "sg:classifiers":[
        {
            "category":"Professional",
            "subcategory":"Lawyer & Legal Services",
            "type":"Services"
        }
    ],
    "sg:phone":"+1 305 670 8188",
    "sg:postcode":"33156",
    "sg:province":"FL",
    "sg:tags":[
        "attorney",
        "practice"
    ],
    "sg:website":"http://www.computexweb.com",
    "wof:name":"Bruce Alexander",
    "wof:placetype":"venue"
},
  "geometry": {"coordinates":[-80.314869,25.685443],"type":"Point"}
}