{
  "type": "Feature",
  "properties": {
    "addr:full":"165 Arlington Rd N Jacksonville FL 32211",
    "addr:housenumber":"165",
    "addr:postcode":"32211",
    "addr:street":"Arlington Rd N",
    "iso:country":"US",
    "sg:address":"165 Arlington Rd N",
    "sg:city":"Jacksonville",
    "sg:classifiers":[
        {
            "category":"Real Estate",
            "subcategory":"Real Estate Services",
            "type":"Services"
        },
        {
            "category":"Real Estate",
            "subcategory":"Real Estate Agent",
            "type":"Services"
        }
    ],
    "sg:phone":"+1 904 721 1546",
    "sg:postcode":"32211",
    "sg:province":"FL",
    "sg:tags":[
        "buyer",
        "broker"
    ],
    "sg:website":"http://www.century21.com",
    "wof:name":"Century 21",
    "wof:placetype":"venue"
},
  "geometry": {"coordinates":[-81.57933800000001,30.316574],"type":"Point"}
}