{
  "type": "Feature",
  "properties": {
    "iso:country":"US",
    "sg:address":"401 SW 28th Rd",
    "sg:city":"Miami",
    "sg:classifiers":[
        {
            "category":"Building & Trades",
            "subcategory":"Locksmith",
            "type":"Services"
        }
    ],
    "sg:phone":"+1 305 423 3386",
    "sg:postcode":"33129",
    "sg:province":"FL",
    "sg:tags":[
        "key"
    ],
    "wof:name":"Emergency A 24 Locksmith",
    "wof:placetype":"venue"
},
  "geometry": {"coordinates":[-80.21087300000001,25.755538],"type":"Point"}
}