{
  "type": "Feature",
  "properties": {
    "iso:country":"US",
    "sg:address":"1559 Coral Ridge Dr",
    "sg:city":"Coral Springs",
    "sg:classifiers":[
        {
            "category":"Retail",
            "subcategory":"Auto Repair",
            "type":"Services"
        }
    ],
    "sg:phone":"+1 954 796 5030",
    "sg:postcode":"33071",
    "sg:province":"FL",
    "sg:tags":[
        "repairing",
        "automobile"
    ],
    "wof:name":"AM PM Car Care Inc",
    "wof:placetype":"venue"
},
  "geometry": {"coordinates":[-80.279439,26.247998],"type":"Point"}
}