{
  "type": "Feature",
  "properties": {
    "iso:country":"US",
    "sg:address":"4342 Winners Cir",
    "sg:city":"Sarasota",
    "sg:classifiers":[
        {
            "category":"Professional",
            "subcategory":"Detective & Security Services",
            "type":"Services"
        }
    ],
    "sg:phone":"+1 941 926 2888",
    "sg:postcode":"34238",
    "sg:province":"FL",
    "sg:tags":[
        "car",
        "investigator"
    ],
    "wof:name":"ICU Investigations Inc",
    "wof:placetype":"venue"
},
  "geometry": {"coordinates":[-82.48626,27.232401],"type":"Point"}
}