{
  "type": "Feature",
  "properties": {
    "iso:country":"US",
    "sg:address":"1339 W Palmetto Park Rd",
    "sg:city":"Boca Raton",
    "sg:classifiers":[
        {
            "category":"Food & Beverages",
            "subcategory":"Groceries & Convenience Stores",
            "type":"Retail Goods"
        }
    ],
    "sg:phone":"+1 561 362 5305",
    "sg:postcode":"33486",
    "sg:province":"FL",
    "sg:tags":[
        "grocer",
        "prod",
        "mfg"
    ],
    "wof:name":"Publix Super Market 553",
    "wof:placetype":"venue"
},
  "geometry": {"coordinates":[-80.114141,26.350825],"type":"Point"}
}