{
  "type": "Feature",
  "properties": {
    "addr:full":"1216 Bluebird Ave Marco Island FL 34145",
    "addr:housenumber":"1216",
    "addr:postcode":"34145",
    "addr:street":"Bluebird Ave",
    "iso:country":"US",
    "sg:address":"1216 Bluebird Ave",
    "sg:city":"Marco Island",
    "sg:classifiers":[
        {
            "category":"Real Estate",
            "subcategory":"Real Estate Operator",
            "type":"Services"
        }
    ],
    "sg:phone":"+1 239 389 5773",
    "sg:postcode":"34145",
    "sg:province":"FL",
    "sg:tags":[
        "building",
        "nonresidential"
    ],
    "wof:name":"Cottonwood Properties Inc",
    "wof:placetype":"venue"
},
  "geometry": {"coordinates":[-81.714957,25.955594],"type":"Point"}
}