{
  "type": "Feature",
  "properties": {
    "iso:country":"US",
    "sg:address":"4301 Anchor Plaza Pkwy",
    "sg:city":"Tampa",
    "sg:classifiers":[
        {
            "category":"Real Estate",
            "subcategory":"Real Estate Services",
            "type":"Services"
        }
    ],
    "sg:phone":"+1 813 393 4737",
    "sg:postcode":"33634",
    "sg:province":"FL",
    "sg:tags":[
        "company",
        "title"
    ],
    "wof:name":"Express Financial Corp",
    "wof:placetype":"venue"
},
  "geometry": {"coordinates":[-82.548255,27.978007],"type":"Point"}
}