{
  "type": "Feature",
  "properties": {
    "iso:country":"US",
    "sg:address":"1171 NE 204th Ter",
    "sg:city":"Miami",
    "sg:classifiers":[
        {
            "category":"Building & Trades",
            "subcategory":"Electrical",
            "type":"Services"
        }
    ],
    "sg:phone":"+1 305 770 2650",
    "sg:postcode":"33179",
    "sg:province":"FL",
    "sg:tags":[
        "contractor"
    ],
    "wof:name":"Infinity Plus Electric",
    "wof:placetype":"venue"
},
  "geometry": {"coordinates":[-80.179597,25.964025],"type":"Point"}
}