{
  "type": "Feature",
  "properties": {
    "addr:full":"2426 Palm Ln West Palm Beach FL 33410",
    "addr:housenumber":"2426",
    "addr:postcode":"33410",
    "addr:street":"Palm Ln",
    "iso:country":"US",
    "sg:address":"2426 Palm Ln",
    "sg:city":"West Palm Beach",
    "sg:classifiers":[
        {
            "category":"Wholesale",
            "subcategory":"Medical Equipment & Supplies",
            "type":"Manufacturing & Wholesale Goods"
        }
    ],
    "sg:phone":"+1 561 625 1515",
    "sg:postcode":"33410",
    "sg:province":"FL",
    "sg:tags":[
        "dental"
    ],
    "wof:name":"Lustgarten Multi-Tech",
    "wof:placetype":"venue"
},
  "geometry": {"coordinates":[-80.075205,26.826193],"type":"Point"}
}