{
  "type": "Feature",
  "properties": {
    "addr:full":"691 Ridge Lake Rd Crestview FL 32536",
    "addr:housenumber":"691",
    "addr:postcode":"32536",
    "addr:street":"Ridge Lake Rd",
    "iso:country":"US",
    "sg:address":"691 Ridge Lake Rd",
    "sg:city":"Crestview",
    "sg:classifiers":[
        {
            "category":"Building & Trades",
            "subcategory":"Construction",
            "type":"Services"
        }
    ],
    "sg:phone":"+1 850 259 6125",
    "sg:postcode":"32536",
    "sg:province":"FL",
    "sg:tags":[
        "home",
        "improvement"
    ],
    "wof:name":"Customized Carpentry & Trim",
    "wof:placetype":"venue"
},
  "geometry": {"coordinates":[-86.588148,30.792312],"type":"Point"}
}