{
  "type": "Feature",
  "properties": {
    "iso:country":"US",
    "sg:address":"1850 Harley Pl",
    "sg:city":"Merritt Island",
    "sg:classifiers":[
        {
            "category":"Communications",
            "type":"Services"
        }
    ],
    "sg:phone":"+1 321 454 9228",
    "sg:postcode":"32952",
    "sg:province":"FL",
    "wof:name":"CJC Communications LLC",
    "wof:placetype":"venue"
},
  "geometry": {"coordinates":[-80.661192,28.325521],"type":"Point"}
}