{
  "type": "Feature",
  "properties": {
    "iso:country":"US",
    "sg:address":"11406 N Dale Mabry Hwy",
    "sg:city":"Tampa",
    "sg:classifiers":[
        {
            "category":"Professional",
            "subcategory":"Employment Agencies",
            "type":"Services"
        }
    ],
    "sg:phone":"+1 813 964 0655",
    "sg:postcode":"33618",
    "sg:province":"FL",
    "sg:tags":[
        "opportunity"
    ],
    "wof:name":"A-1 Temps",
    "wof:placetype":"venue"
},
  "geometry": {"coordinates":[-82.504096,28.051596],"type":"Point"}
}