{
  "type": "Feature",
  "properties": {
    "iso:country":"US",
    "sg:address":"21 NW 5th St",
    "sg:city":"Fort Lauderdale",
    "sg:classifiers":[
        {
            "category":"Professional",
            "subcategory":"Computer Services",
            "type":"Services"
        }
    ],
    "sg:phone":"+1 954 747 3301",
    "sg:postcode":"33301",
    "sg:province":"FL",
    "sg:tags":[
        "development",
        "software"
    ],
    "wof:name":"Global Data Solutions Inc",
    "wof:placetype":"venue"
},
  "geometry": {"coordinates":[-80.14446700000001,26.127892],"type":"Point"}
}