{
  "type": "Feature",
  "properties": {
    "iso:country":"US",
    "sg:address":"13901 SW 142nd Ave",
    "sg:city":"Miami",
    "sg:classifiers":[
        {
            "category":"Building & Trades",
            "subcategory":"Landscaping Services",
            "type":"Services"
        },
        {
            "category":"Building & Trades",
            "subcategory":"Electrical",
            "type":"Services"
        }
    ],
    "sg:phone":"+1 305 259 0503",
    "sg:postcode":"33186",
    "sg:province":"FL",
    "sg:tags":[
        "lawn",
        "industrial",
        "electric",
        "contractor",
        "contractors-commercial",
        "landscape"
    ],
    "wof:name":"Plant Professionals Inc",
    "wof:placetype":"venue"
},
  "geometry": {"coordinates":[-80.42290199999999,25.638155],"type":"Point"}
}