{
  "type": "Feature",
  "properties": {
    "iso:country":"US",
    "sg:address":"1942 Truman Dr",
    "sg:city":"Navarre",
    "sg:classifiers":[
        {
            "category":"Building & Trades",
            "subcategory":"Landscaping Services",
            "type":"Services"
        }
    ],
    "sg:phone":"+1 850 748 5717",
    "sg:postcode":"32566",
    "sg:province":"FL",
    "sg:tags":[
        "landscape",
        "contractor"
    ],
    "wof:name":"Ted Freeman Landscaping",
    "wof:placetype":"venue"
},
  "geometry": {"coordinates":[-86.92712400000001,30.407408],"type":"Point"}
}