{
  "type": "Feature",
  "properties": {
    "iso:country":"US",
    "sg:address":"7387 Shoal Line Blvd",
    "sg:city":"Spring Hill",
    "sg:classifiers":[
        {
            "category":"Shopping",
            "subcategory":"Discount & Variety Stores",
            "type":"Retail Goods"
        }
    ],
    "sg:phone":"+1 352 684 2505",
    "sg:postcode":"34607",
    "sg:province":"FL",
    "sg:tags":[
        "merchandise",
        "general"
    ],
    "wof:name":"Sand & Shore",
    "wof:placetype":"venue"
},
  "geometry": {"coordinates":[-82.615999,28.535631],"type":"Point"}
}