{
  "type": "Feature",
  "properties": {
    "addr:full":"1798 Tamiami Trl N Naples FL 34102",
    "addr:housenumber":"1798",
    "addr:postcode":"34102",
    "addr:street":"Tamiami Trl N",
    "iso:country":"US",
    "sg:address":"1798 Tamiami Trl N",
    "sg:city":"Naples",
    "sg:classifiers":[
        {
            "category":"Shopping",
            "type":"Retail Goods"
        }
    ],
    "sg:phone":"+1 239 261 3013",
    "sg:postcode":"34102",
    "sg:province":"FL",
    "sg:tags":[
        "cosmetic",
        "perfume"
    ],
    "wof:name":"Mac Cosmetics",
    "wof:placetype":"venue"
},
  "geometry": {"coordinates":[-81.798467,26.164256],"type":"Point"}
}