{
  "type": "Feature",
  "properties": {
    "iso:country":"US",
    "sg:address":"6718 Cocos Dr",
    "sg:city":"Orlando",
    "sg:classifiers":[
        {
            "category":"Shopping",
            "subcategory":"Hobbies, Toys, & Games",
            "type":"Retail Goods"
        }
    ],
    "sg:phone":"+1 407 277 8310",
    "sg:postcode":"32807",
    "sg:province":"FL",
    "wof:name":"Clay Creations By Robert",
    "wof:placetype":"venue"
},
  "geometry": {"coordinates":[-81.29287100000001,28.542286],"type":"Point"}
}