{
  "type": "Feature",
  "properties": {
    "iso:country":"US",
    "sg:address":"305 SW Depot Ave",
    "sg:city":"Gainesville",
    "sg:classifiers":[
        {
            "category":"Manufacturing",
            "subcategory":"Glass & Minerals",
            "type":"Manufacturing & Wholesale Goods"
        }
    ],
    "sg:phone":"+1 352 375 3038",
    "sg:postcode":"32601",
    "sg:province":"FL",
    "sg:tags":[
        "ready",
        "concrete",
        "l",
        "mfg"
    ],
    "wof:name":"Concrete Products Gainesville",
    "wof:placetype":"venue"
},
  "geometry": {"coordinates":[-82.32951799999999,29.643769],"type":"Point"}
}