{
  "type": "Feature",
  "properties": {
    "iso:country":"US",
    "sg:address":"3953 Cattlemen Rd",
    "sg:city":"Sarasota",
    "sg:classifiers":[
        {
            "category":"Personal",
            "subcategory":"Beauty Salon",
            "type":"Services"
        }
    ],
    "sg:phone":"+1 941 377 6060",
    "sg:postcode":"34233",
    "sg:province":"FL",
    "sg:tags":[
        "shop"
    ],
    "wof:name":"Idols Inc",
    "wof:placetype":"venue"
},
  "geometry": {"coordinates":[-82.451543,27.295997],"type":"Point"}
}