{
  "type": "Feature",
  "properties": {
    "iso:country":"US",
    "sg:address":"9404 Octavia Ln",
    "sg:city":"Gulf Breeze",
    "sg:classifiers":[
        {
            "category":"Building & Trades",
            "subcategory":"Construction",
            "type":"Services"
        }
    ],
    "sg:phone":"+1 850 939 8990",
    "sg:postcode":"32566",
    "sg:province":"FL",
    "sg:tags":[
        "swimming",
        "designer",
        "dealer",
        "pool",
        "contractor"
    ],
    "wof:name":"Pools Plus",
    "wof:placetype":"venue"
},
  "geometry": {"coordinates":[-86.827732,30.413921],"type":"Point"}
}