{
  "type": "Feature",
  "properties": {
    "iso:country":"US",
    "sg:address":"8415 S Park Pl # 100",
    "sg:city":"Orlando",
    "sg:classifiers":[
        {
            "category":"Travel",
            "subcategory":"Travel Agent",
            "type":"Entertainment"
        }
    ],
    "sg:phone":"+1 407 857 3939",
    "sg:postcode":"32819",
    "sg:province":"FL",
    "sg:tags":[
        "agency",
        "services-commercial"
    ],
    "sg:website":"http://www.marktravel.com",
    "wof:name":"Southwest Vacations",
    "wof:placetype":"venue"
},
  "geometry": {"coordinates":[-81.42318299999999,28.447548],"type":"Point"}
}