{
  "type": "Feature",
  "properties": {
    "addr:full":"13730 W Colonial Dr Winter Garden FL 34787",
    "addr:housenumber":"13730",
    "addr:postcode":"34787",
    "addr:street":"W Colonial Dr",
    "iso:country":"US",
    "sg:address":"13730 W Colonial Dr",
    "sg:city":"Winter Garden",
    "sg:classifiers":[
        {
            "category":"Banks & Credit Unions",
            "subcategory":"Bank",
            "type":"Services"
        }
    ],
    "sg:phone":"+1 407 656 4876",
    "sg:postcode":"34787",
    "sg:province":"FL",
    "wof:name":"Washington Mutual",
    "wof:placetype":"venue"
},
  "geometry": {"coordinates":[-81.587962,28.550962],"type":"Point"}
}