{
  "type": "Feature",
  "properties": {
    "addr:full":"8275 Northwest 36th Street Doral FL 33166",
    "addr:housenumber":"8275",
    "addr:postcode":"33166",
    "addr:street":"Northwest 36Th Street",
    "iso:country":"US",
    "sg:address":"8275 Northwest 36th Street",
    "sg:city":"Doral",
    "sg:classifiers":[
        {
            "category":"Personal",
            "subcategory":"Beauty Salon",
            "type":"Services"
        }
    ],
    "sg:phone":"+1 786 318 8278",
    "sg:postcode":"33166",
    "sg:province":"FL",
    "sg:tags":[
        "makeup",
        "artist"
    ],
    "wof:name":"Elizabeth Olivera",
    "wof:placetype":"venue"
},
  "geometry": {"coordinates":[-80.33121199999999,25.810317],"type":"Point"}
}