{
  "type": "Feature",
  "properties": {
    "iso:country":"US",
    "sg:address":"8133 SW 103rd St",
    "sg:city":"Miami",
    "sg:classifiers":[
        {
            "category":"Wholesale",
            "subcategory":"Home Furnishings",
            "type":"Manufacturing & Wholesale Goods"
        }
    ],
    "sg:phone":"+1 305 596 2621",
    "sg:postcode":"33156",
    "sg:province":"FL",
    "sg:tags":[
        "fixtures-wholesale",
        "lighting",
        "manufacturer"
    ],
    "wof:name":"Oak Glen Corp",
    "wof:placetype":"venue"
},
  "geometry": {"coordinates":[-80.32646200000001,25.674643],"type":"Point"}
}