{
  "type": "Feature",
  "properties": {
    "iso:country":"US",
    "sg:address":"3804 Treasure Cir",
    "sg:city":"Panama City",
    "sg:classifiers":[
        {
            "category":"Wholesale",
            "subcategory":"Non-durable Goods",
            "type":"Manufacturing & Wholesale Goods"
        }
    ],
    "sg:phone":"+1 850 230 4115",
    "sg:postcode":"32408",
    "sg:province":"FL",
    "wof:name":"David Plauche Distributing",
    "wof:placetype":"venue"
},
  "geometry": {"coordinates":[-85.75023,30.14366],"type":"Point"}
}