{
  "type": "Feature",
  "properties": {
    "iso:country":"US",
    "sg:address":"182 Douglas Rd E",
    "sg:city":"Oldsmar",
    "sg:classifiers":[
        {
            "category":"Real Estate",
            "subcategory":"Developer",
            "type":"Services"
        }
    ],
    "sg:phone":"+1 813 891 6577",
    "sg:postcode":"34677",
    "sg:province":"FL",
    "wof:name":"Vollmer Corp",
    "wof:placetype":"venue"
},
  "geometry": {"coordinates":[-82.66249500000001,28.041476],"type":"Point"}
}