{
  "type": "Feature",
  "properties": {
    "addr:full":"1725 N Galloway Rd Lakeland FL 33810",
    "addr:housenumber":"1725",
    "addr:postcode":"33810",
    "addr:street":"N Galloway Rd",
    "iso:country":"US",
    "sg:address":"1725 N Galloway Rd",
    "sg:city":"Lakeland",
    "sg:classifiers":[
        {
            "category":"Building & Trades",
            "subcategory":"Construction",
            "type":"Services"
        }
    ],
    "sg:phone":"+1 863 815 4874",
    "sg:postcode":"33810",
    "sg:province":"FL",
    "sg:tags":[
        "contractor"
    ],
    "wof:name":"Preece Siding Inc",
    "wof:placetype":"venue"
},
  "geometry": {"coordinates":[-82.006491,28.064238],"type":"Point"}
}