{
  "type": "Feature",
  "properties": {
    "iso:country":"US",
    "sg:address":"25241 Elementary Way",
    "sg:city":"Bonita Springs",
    "sg:classifiers":[
        {
            "category":"Professional",
            "subcategory":"Business Services",
            "type":"Services"
        }
    ],
    "sg:phone":"+1 239 590 0003",
    "sg:postcode":"34135",
    "sg:province":"FL",
    "wof:name":"Sterling Appraisals",
    "wof:placetype":"venue"
},
  "geometry": {"coordinates":[-81.80667099999999,26.370718],"type":"Point"}
}