{
  "type": "Feature",
  "properties": {
    "iso:country":"US",
    "sg:address":"3444 Belfort Rd",
    "sg:city":"Jacksonville",
    "sg:classifiers":[
        {
            "category":"Professional",
            "subcategory":"Engineering",
            "type":"Services"
        }
    ],
    "sg:phone":"+1 904 527 8300",
    "sg:postcode":"32216",
    "sg:province":"FL",
    "sg:tags":[
        "refrigeration",
        "engineer"
    ],
    "wof:name":"Miles Airconditioning Refrigeration",
    "wof:placetype":"venue"
},
  "geometry": {"coordinates":[-81.574736,30.264191],"type":"Point"}
}