{
  "type": "Feature",
  "properties": {
    "iso:country":"US",
    "sg:address":"8600 NW S River Dr Ste 101",
    "sg:city":"Medley",
    "sg:classifiers":[
        {
            "category":"Professional",
            "subcategory":"Accounting & Tax Preparation",
            "type":"Services"
        }
    ],
    "sg:phone":"+1 305 885 5099",
    "sg:postcode":"33166",
    "sg:province":"FL",
    "sg:tags":[
        "accountant"
    ],
    "wof:name":"Barbara Hernandez, CPA",
    "wof:placetype":"venue"
},
  "geometry": {"coordinates":[-80.320936,25.850764],"type":"Point"}
}