{
  "type": "Feature",
  "properties": {
    "addr:full":"1859 S Dixie Hwy Pompano Beach FL 33060",
    "addr:housenumber":"1859",
    "addr:postcode":"33060",
    "addr:street":"S Dixie Hwy",
    "iso:country":"US",
    "sg:address":"1859 S Dixie Hwy",
    "sg:city":"Pompano Beach",
    "sg:classifiers":[
        {
            "category":"Organizations",
            "subcategory":"Religious Organization",
            "type":"Services"
        }
    ],
    "sg:phone":"+1 954 545 5596",
    "sg:postcode":"33060",
    "sg:province":"FL",
    "sg:tags":[
        "synagogue"
    ],
    "wof:name":"Biblical Alternative Fllwshp",
    "wof:placetype":"venue"
},
  "geometry": {"coordinates":[-80.132546,26.210134],"type":"Point"}
}