{
  "type": "Feature",
  "properties": {
    "addr:full":"1218 Sablewood Dr Apopka FL 32712",
    "addr:housenumber":"1218",
    "addr:postcode":"32712",
    "addr:street":"Sablewood Dr",
    "iso:country":"US",
    "sg:address":"1218 Sablewood Dr",
    "sg:city":"Apopka",
    "sg:classifiers":[
        {
            "category":"Building & Trades",
            "subcategory":"Construction",
            "type":"Services"
        }
    ],
    "sg:phone":"+1 407 814 4276",
    "sg:postcode":"32712",
    "sg:province":"FL",
    "sg:tags":[
        "management"
    ],
    "wof:name":"Evergreen Construction Management Inc",
    "wof:placetype":"venue"
},
  "geometry": {"coordinates":[-81.496256,28.702864],"type":"Point"}
}