{
  "type": "Feature",
  "properties": {
    "iso:country":"US",
    "sg:address":"8437 Honore Ave",
    "sg:city":"Bradenton",
    "sg:classifiers":[
        {
            "category":"Shopping",
            "subcategory":"Pets & Pet Supplies",
            "type":"Retail Goods"
        }
    ],
    "sg:phone":"+1 941 359 3039",
    "sg:postcode":"34201",
    "sg:province":"FL",
    "sg:tags":[
        "store"
    ],
    "wof:name":"Roxys Pet Depot",
    "wof:placetype":"venue"
},
  "geometry": {"coordinates":[-82.46347,27.389681],"type":"Point"}
}