{
  "type": "Feature",
  "properties": {
    "addr:full":"18915 Cortez Blvd Brooksville FL 34601",
    "addr:housenumber":"18915",
    "addr:postcode":"34601",
    "addr:street":"Cortez Blvd",
    "iso:country":"US",
    "sg:address":"18915 Cortez Blvd",
    "sg:city":"Brooksville",
    "sg:classifiers":[
        {
            "category":"Banks & Credit Unions",
            "subcategory":"Bank",
            "type":"Services"
        }
    ],
    "sg:phone":"+1 352 799 6322",
    "sg:postcode":"34601",
    "sg:province":"FL",
    "sg:tags":[
        "federal"
    ],
    "wof:name":"Suncoast Schools Federal Cr Un",
    "wof:placetype":"venue"
},
  "geometry": {"coordinates":[-82.42031799999999,28.546854],"type":"Point"}
}