{
  "type": "Feature",
  "properties": {
    "iso:country":"US",
    "sg:address":"318 NW 18th St",
    "sg:city":"Delray Beach",
    "sg:classifiers":[
        {
            "category":"Professional",
            "type":"Services"
        }
    ],
    "sg:phone":"+1 561 272 6177",
    "sg:postcode":"33444",
    "sg:province":"FL",
    "sg:tags":[
        "establishment"
    ],
    "wof:name":"PBG",
    "wof:placetype":"venue"
},
  "geometry": {"coordinates":[-80.07632599999999,26.483334],"type":"Point"}
}