{
  "type": "Feature",
  "properties": {
    "addr:full":"7350 Sandlake Commons Blvd Orlando FL 32819",
    "addr:postcode":"7350;32819",
    "addr:street":"Sandlake Commons Blvd",
    "iso:country":"US",
    "sg:address":"7350 Sandlake Commons Blvd",
    "sg:city":"Orlando",
    "sg:classifiers":[
        {
            "category":"Health Services",
            "subcategory":"Doctor",
            "type":"Services"
        }
    ],
    "sg:phone":"+1 407 352 9717",
    "sg:postcode":"32819",
    "sg:province":"FL",
    "sg:tags":[
        "medicine",
        "physician",
        "practice",
        "surgeons",
        "family"
    ],
    "wof:name":"Patrick P Gonzalez Md",
    "wof:placetype":"venue"
},
  "geometry": {"coordinates":[-81.479073,28.431049],"type":"Point"}
}