{
  "type": "Feature",
  "properties": {
    "iso:country":"US",
    "sg:address":"9629 Morehead Ln",
    "sg:city":"Port Richey",
    "sg:classifiers":[
        {
            "category":"Building & Trades",
            "subcategory":"Cleaning & Sanitation",
            "type":"Services"
        }
    ],
    "sg:phone":"+1 727 862 4626",
    "sg:postcode":"34668",
    "sg:province":"FL",
    "sg:tags":[
        "property",
        "maintenance"
    ],
    "wof:name":"Joe Fratus Property Mntnc",
    "wof:placetype":"venue"
},
  "geometry": {"coordinates":[-82.677503,28.29748],"type":"Point"}
}