{
  "type": "Feature",
  "properties": {
    "addr:full":"24 N Homestead Blvd Homestead FL 33030",
    "addr:housenumber":"24",
    "addr:postcode":"33030",
    "addr:street":"N Homestead Blvd",
    "iso:country":"US",
    "sg:address":"24 N Homestead Blvd",
    "sg:city":"Homestead",
    "sg:classifiers":[
        {
            "category":"Shopping",
            "subcategory":"Clothing, Apparel, & Fashions",
            "type":"Retail Goods"
        },
        {
            "category":"Shopping",
            "type":"Retail Goods"
        }
    ],
    "sg:phone":"+1 305 248 9005",
    "sg:postcode":"33030",
    "sg:province":"FL",
    "sg:tags":[
        "apparel",
        "item",
        "boutique",
        "women's"
    ],
    "wof:name":"S & W Boutique",
    "wof:placetype":"venue"
},
  "geometry": {"coordinates":[-80.46463799999999,25.478055],"type":"Point"}
}