{
  "type": "Feature",
  "properties": {
    "iso:country":"US",
    "sg:address":"2601 60th Ave S",
    "sg:city":"Saint Petersburg",
    "sg:classifiers":[
        {
            "category":"Professional",
            "type":"Services"
        }
    ],
    "sg:phone":"+1 727 866 0737",
    "sg:postcode":"33712",
    "sg:province":"FL",
    "wof:name":"Rick Wagner Inc",
    "wof:placetype":"venue"
},
  "geometry": {"coordinates":[-82.669327,27.713489],"type":"Point"}
}