{
  "type": "Feature",
  "properties": {
    "iso:country":"US",
    "sg:address":"11933 Amber Leaf Ct",
    "sg:city":"Jacksonville",
    "sg:classifiers":[
        {
            "category":"Professional",
            "subcategory":"Management & Consulting",
            "type":"Services"
        }
    ],
    "sg:phone":"+1 904 288 0264",
    "sg:postcode":"32223",
    "sg:province":"FL",
    "sg:tags":[
        "consultant"
    ],
    "wof:name":"Drew Edwards & Assoc Inc",
    "wof:placetype":"venue"
},
  "geometry": {"coordinates":[-81.622568,30.155378],"type":"Point"}
}