{
  "type": "Feature",
  "properties": {
    "addr:full":"4706 Coconut Creek Pkwy Margate FL 33063",
    "addr:housenumber":"4706",
    "addr:postcode":"33063",
    "addr:street":"Coconut Creek Pkwy Margate",
    "iso:country":"US",
    "sg:address":"4706 Coconut Creek Pkwy",
    "sg:city":"Margate",
    "sg:classifiers":[
        {
            "category":"Government",
            "subcategory":"Post Office",
            "type":"Public Place"
        }
    ],
    "sg:phone":"+1 954 971 9569",
    "sg:postcode":"33063",
    "sg:province":"FL",
    "sg:tags":[
        "postal",
        "us"
    ],
    "wof:name":"US Post Office",
    "wof:placetype":"venue"
},
  "geometry": {"coordinates":[-80.201173,26.244365],"type":"Point"}
}