{
  "type": "Feature",
  "properties": {
    "iso:country":"US",
    "sg:address":"225 College Dr",
    "sg:city":"Orange Park",
    "sg:classifiers":[
        {
            "category":"Government",
            "subcategory":"Post Office",
            "type":"Public Place"
        }
    ],
    "sg:phone":"+1 904 000 1111",
    "sg:postcode":"32065",
    "sg:province":"FL",
    "wof:name":"US Post Office",
    "wof:placetype":"venue"
},
  "geometry": {"coordinates":[-81.776448,30.119759],"type":"Point"}
}