{
  "type": "Feature",
  "properties": {
    "addr:full":"8808 Beach Blvd Jacksonville FL 32216",
    "addr:housenumber":"8808",
    "addr:postcode":"32216",
    "addr:street":"Beach Blvd",
    "iso:country":"US",
    "sg:address":"8808 Beach Blvd",
    "sg:city":"Jacksonville",
    "sg:classifiers":[
        {
            "category":"Shopping",
            "subcategory":"Mobile Phones",
            "type":"Retail Goods"
        }
    ],
    "sg:phone":"+1 904 645 9370",
    "sg:postcode":"32216",
    "sg:province":"FL",
    "sg:tags":[
        "equipment",
        "telephone",
        "cellular",
        "supply"
    ],
    "sg:website":"http://www.cingular.com",
    "wof:name":"AT&T Wireless",
    "wof:placetype":"venue"
},
  "geometry": {"coordinates":[-81.562757,30.286763],"type":"Point"}
}