{
  "type": "Feature",
  "properties": {
    "iso:country":"US",
    "sg:address":"27 E Prospect Rd",
    "sg:city":"Fort Lauderdale",
    "sg:classifiers":[
        {
            "category":"Travel",
            "subcategory":"Travel Agent",
            "type":"Entertainment"
        }
    ],
    "sg:phone":"+1 954 566 6539",
    "sg:postcode":"33334",
    "sg:province":"FL",
    "sg:tags":[
        "agency"
    ],
    "wof:name":"Dolphin Travel Inc",
    "wof:placetype":"venue"
},
  "geometry": {"coordinates":[-80.145128,26.181417],"type":"Point"}
}