{
  "type": "Feature",
  "properties": {
    "addr:full":"1104 Eagles Nest Ave Deltona FL 32725",
    "addr:housenumber":"1104",
    "addr:postcode":"32725",
    "addr:street":"Eagles Nest Ave",
    "iso:country":"US",
    "sg:address":"1104 Eagles Nest Ave",
    "sg:city":"Deltona",
    "sg:classifiers":[
        {
            "category":"Building & Trades",
            "subcategory":"Construction",
            "type":"Services"
        }
    ],
    "sg:phone":"+1 386 574 2802",
    "sg:postcode":"32725",
    "sg:province":"FL",
    "sg:tags":[
        "hanging",
        "contractor"
    ],
    "wof:name":"Rustys Handyman Service",
    "wof:placetype":"venue"
},
  "geometry": {"coordinates":[-81.27552900000001,28.89326],"type":"Point"}
}