{
  "type": "Feature",
  "properties": {
    "iso:country":"US",
    "sg:address":"1771 SE 15 St",
    "sg:city":"Oak Ridge",
    "sg:classifiers":[
        {
            "category":"Real Estate",
            "subcategory":"Real Estate Agent",
            "type":"Services"
        }
    ],
    "sg:phone":"+1 973 663 9000",
    "sg:postcode":"32641",
    "sg:province":"FL",
    "wof:name":"Re/Max Team Vision",
    "wof:placetype":"venue"
},
  "geometry": {"coordinates":[-82.305772,29.632945],"type":"Point"}
}