{
  "type": "Feature",
  "properties": {
    "iso:country":"US",
    "sg:address":"836 Belvedere Rd",
    "sg:city":"West Palm Beach",
    "sg:classifiers":[
        {
            "category":"Professional",
            "type":"Services"
        }
    ],
    "sg:phone":"+1 561 366 9996",
    "sg:postcode":"33405",
    "sg:province":"FL",
    "sg:tags":[
        "arts",
        "artist"
    ],
    "wof:name":"Andreasen & Associates",
    "wof:placetype":"venue"
},
  "geometry": {"coordinates":[-80.061891,26.690445],"type":"Point"}
}