{
  "type": "Feature",
  "properties": {
    "addr:full":"1403 29th St Niceville FL 32578",
    "addr:housenumber":"1403",
    "addr:postcode":"32578",
    "addr:street":"29Th St",
    "iso:country":"US",
    "sg:address":"1403 29th St",
    "sg:city":"Niceville",
    "sg:classifiers":[
        {
            "category":"Real Estate",
            "subcategory":"Real Estate Agent",
            "type":"Services"
        }
    ],
    "sg:phone":"+1 850 678 1151",
    "sg:postcode":"32578",
    "sg:province":"FL",
    "wof:name":"Joel Barton Agency Inc",
    "wof:placetype":"venue"
},
  "geometry": {"coordinates":[-86.465773,30.514476],"type":"Point"}
}