{
  "type": "Feature",
  "properties": {
    "addr:full":"2701 Michigan Ave Kissimmee FL 34744",
    "addr:housenumber":"2701",
    "addr:postcode":"34744",
    "addr:street":"Michigan Ave",
    "iso:country":"US",
    "sg:address":"2701 Michigan Ave",
    "sg:city":"Kissimmee",
    "sg:classifiers":[
        {
            "category":"Shopping",
            "subcategory":"Clothing, Apparel, & Fashions",
            "type":"Retail Goods"
        }
    ],
    "sg:phone":"+1 407 847 6500",
    "sg:postcode":"34744",
    "sg:province":"FL",
    "sg:tags":[
        "shop",
        "bridal"
    ],
    "wof:name":"Esther Collection Canastilla",
    "wof:placetype":"venue"
},
  "geometry": {"coordinates":[-81.39115,28.327318],"type":"Point"}
}