{
  "type": "Feature",
  "properties": {
    "iso:country":"US",
    "sg:address":"8505 NW 12th St",
    "sg:city":"Miami",
    "sg:classifiers":[
        {
            "category":"Retail",
            "subcategory":"Auto Repair",
            "type":"Services"
        }
    ],
    "sg:phone":"+1 305 436 8400",
    "sg:postcode":"33126",
    "sg:province":"FL",
    "sg:website":"www.doralautomotive.com",
    "wof:name":"Doral Buick Pontiac GMC",
    "wof:placetype":"venue"
},
  "geometry": {"coordinates":[-80.334782,25.783871],"type":"Point"}
}