{
  "type": "Feature",
  "properties": {
    "addr:full":"614 W 27th St Hialeah FL 33010",
    "addr:housenumber":"614",
    "addr:postcode":"33010",
    "addr:street":"W 27Th St",
    "iso:country":"US",
    "sg:address":"614 W 27th St",
    "sg:city":"Hialeah",
    "sg:classifiers":[
        {
            "category":"Retail",
            "subcategory":"Repair Shop",
            "type":"Services"
        },
        {
            "category":"Travel",
            "subcategory":"Travel Agent",
            "type":"Entertainment"
        }
    ],
    "sg:phone":"+1 305 888 6546",
    "sg:postcode":"33010",
    "sg:province":"FL",
    "sg:tags":[
        "operator",
        "sharpening",
        "tour"
    ],
    "wof:name":"Prado's Precision Tools",
    "wof:placetype":"venue"
},
  "geometry": {"coordinates":[-80.295033,25.846097],"type":"Point"}
}