{
  "type": "Feature",
  "properties": {
    "iso:country":"US",
    "sg:address":"14434 Lake Junietta Dr",
    "sg:city":"Tavares",
    "sg:classifiers":[
        {
            "category":"Utilities",
            "subcategory":"Telephone",
            "type":"Services"
        }
    ],
    "sg:phone":"+1 352 343 1894",
    "sg:postcode":"32778",
    "sg:province":"FL",
    "sg:tags":[
        "communications"
    ],
    "wof:name":"Custom Telephone & Data Comm",
    "wof:placetype":"venue"
},
  "geometry": {"coordinates":[-81.717333,28.823859],"type":"Point"}
}