{
  "type": "Feature",
  "properties": {
    "addr:full":"10401 SW 9th Ln Hollywood FL 33025",
    "addr:housenumber":"10401",
    "addr:postcode":"33025",
    "addr:street":"Sw 9Th Ln",
    "iso:country":"US",
    "sg:address":"10401 SW 9th Ln",
    "sg:city":"Hollywood",
    "sg:classifiers":[
        {
            "category":"Shopping",
            "subcategory":"Bicycles & Sporting Goods",
            "type":"Retail Goods"
        }
    ],
    "sg:phone":"+1 954 436 3025",
    "sg:postcode":"33025",
    "sg:province":"FL",
    "wof:name":"Genesis Waterhouse Sports",
    "wof:placetype":"venue"
},
  "geometry": {"coordinates":[-80.282826,26.000606],"type":"Point"}
}