{
  "type": "Feature",
  "properties": {
    "iso:country":"US",
    "sg:address":"802 W Retta Esplanade",
    "sg:city":"Punta Gorda",
    "sg:classifiers":[
        {
            "category":"Organizations",
            "subcategory":"Community Association",
            "type":"Services"
        }
    ],
    "sg:phone":"+1 941 639 3828",
    "sg:postcode":"33950",
    "sg:province":"FL",
    "sg:tags":[
        "club"
    ],
    "wof:name":"Punta Gorda Boat Club",
    "wof:placetype":"venue"
},
  "geometry": {"coordinates":[-82.05997000000001,26.93002],"type":"Point"}
}