{
  "type": "Feature",
  "properties": {
    "addr:full":"3421 Bonita Beach Rd SW Bonita Springs FL 34134",
    "addr:housenumber":"3421",
    "addr:postcode":"34134",
    "addr:street":"Bonita Beach Rd Sw Bonita Springs",
    "iso:country":"US",
    "sg:address":"3421 Bonita Beach Rd SW",
    "sg:city":"Bonita Springs",
    "sg:classifiers":[
        {
            "category":"Health Services",
            "subcategory":"Clinic",
            "type":"Services"
        },
        {
            "category":"Professional",
            "subcategory":"Employment Agencies",
            "type":"Services"
        }
    ],
    "sg:phone":"+1 239 949 1070",
    "sg:postcode":"34134",
    "sg:province":"FL",
    "sg:tags":[
        "home",
        "help",
        "supply"
    ],
    "wof:name":"Right At Home",
    "wof:placetype":"venue"
},
  "geometry": {"coordinates":[-81.809327,26.330587],"type":"Point"}
}