{
  "type": "Feature",
  "properties": {
    "addr:full":"995 SW 84th Ave Miami FL 33144",
    "addr:housenumber":"995",
    "addr:postcode":"33144",
    "addr:street":"Sw 84Th Ave",
    "iso:country":"US",
    "sg:address":"995 SW 84th Ave",
    "sg:city":"Miami",
    "sg:classifiers":[
        {
            "category":"Professional",
            "type":"Services"
        }
    ],
    "sg:phone":"+1 786 388 8980",
    "sg:postcode":"33144",
    "sg:province":"FL",
    "sg:tags":[
        "establishment"
    ],
    "wof:name":"RMLS Inc",
    "wof:placetype":"venue"
},
  "geometry": {"coordinates":[-80.33149299999999,25.761509],"type":"Point"}
}