{
  "type": "Feature",
  "properties": {
    "iso:country":"US",
    "sg:address":"929 NE 27th Ave",
    "sg:city":"Hallandale",
    "sg:classifiers":[
        {
            "category":"Professional",
            "type":"Services"
        }
    ],
    "sg:phone":"+1 954 456 6669",
    "sg:postcode":"33009",
    "sg:province":"FL",
    "wof:name":"Hotch Kiss Co",
    "wof:placetype":"venue"
},
  "geometry": {"coordinates":[-80.122299,25.996766],"type":"Point"}
}