{
  "type": "Feature",
  "properties": {
    "iso:country":"US",
    "sg:address":"1221 E 16th St",
    "sg:city":"Jacksonville",
    "sg:classifiers":[
        {
            "category":"Education",
            "subcategory":"School",
            "type":"Public Place"
        }
    ],
    "sg:phone":"+1 904 630 6880",
    "sg:postcode":"32206",
    "sg:province":"FL",
    "sg:tags":[
        "elementary"
    ],
    "wof:name":"J Allen Axson Elementary",
    "wof:placetype":"venue"
},
  "geometry": {"coordinates":[-81.637484,30.353695],"type":"Point"}
}