{
  "type": "Feature",
  "properties": {
    "iso:country":"US",
    "sg:address":"4220 Fairway Run",
    "sg:city":"Tampa",
    "sg:classifiers":[
        {
            "category":"Retail",
            "subcategory":"Self-service Laundry",
            "type":"Services"
        }
    ],
    "sg:phone":"+1 813 968 8636",
    "sg:postcode":"33618",
    "sg:province":"FL",
    "sg:tags":[
        "coin"
    ],
    "wof:name":"Starkey Coin Laundry Inc",
    "wof:placetype":"venue"
},
  "geometry": {"coordinates":[-82.511262,28.065702],"type":"Point"}
}