{
  "type": "Feature",
  "properties": {
    "addr:full":"5600 SE Federal Hwy Stuart FL 34997",
    "addr:housenumber":"5600",
    "addr:postcode":"34997",
    "addr:street":"Se Federal Hwy",
    "iso:country":"US",
    "sg:address":"5600 SE Federal Hwy",
    "sg:city":"Stuart",
    "sg:classifiers":[
        {
            "category":"Insurance",
            "subcategory":"Insurance Agent",
            "type":"Services"
        }
    ],
    "sg:phone":"+1 772 287 2030",
    "sg:postcode":"34997",
    "sg:province":"FL",
    "sg:website":"www.deakinscarroll.com",
    "wof:name":"Deakins-Carroll Insurance",
    "wof:placetype":"venue"
},
  "geometry": {"coordinates":[-80.209827,27.138054],"type":"Point"}
}