{
  "type": "Feature",
  "properties": {
    "iso:country":"US",
    "sg:address":"5821 NE 15th Ave",
    "sg:city":"Ocala",
    "sg:classifiers":[
        {
            "category":"Professional",
            "type":"Services"
        }
    ],
    "sg:phone":"+1 352 620 9909",
    "sg:postcode":"34479",
    "sg:province":"FL",
    "wof:name":"Connie H Muldrow",
    "wof:placetype":"venue"
},
  "geometry": {"coordinates":[-82.118047,29.247809],"type":"Point"}
}