{
  "type": "Feature",
  "properties": {
    "addr:full":"7807 N Dale Mabry Hwy Tampa FL 33614",
    "addr:housenumber":"7807",
    "addr:postcode":"33614",
    "addr:street":"N Dale Mabry Hwy",
    "iso:country":"US",
    "sg:address":"7807 N Dale Mabry Hwy",
    "sg:city":"Tampa",
    "sg:classifiers":[
        {
            "category":"Recreation",
            "type":"Entertainment"
        }
    ],
    "sg:phone":"+1 813 933 6995",
    "sg:postcode":"33614",
    "sg:province":"FL",
    "sg:tags":[
        "amusement"
    ],
    "sg:website":"www.qzartampa.com",
    "wof:name":"Q-Zar Lazer Tag",
    "wof:placetype":"venue"
},
  "geometry": {"coordinates":[-82.50488900000001,28.019839],"type":"Point"}
}