{
  "type": "Feature",
  "properties": {
    "iso:country":"US",
    "sg:address":"322 SW 10 St",
    "sg:city":"Gainesville",
    "sg:classifiers":[
        {
            "category":"Food & Beverages",
            "subcategory":"Groceries & Convenience Stores",
            "type":"Retail Goods"
        }
    ],
    "sg:phone":"+1 352 375 1981",
    "sg:postcode":"32601",
    "sg:province":"FL",
    "wof:name":"Parks Place",
    "wof:placetype":"venue"
},
  "geometry": {"coordinates":[-82.33510800000001,29.648636],"type":"Point"}
}