{
  "type": "Feature",
  "properties": {
    "iso:country":"US",
    "sg:address":"8934 SW 129th Ter",
    "sg:city":"Miami",
    "sg:classifiers":[
        {
            "category":"Real Estate",
            "subcategory":"Real Estate Agent",
            "type":"Services"
        }
    ],
    "sg:phone":"+1 305 234 1944",
    "sg:postcode":"33176",
    "sg:province":"FL",
    "wof:name":"Kathe Eagleton",
    "wof:placetype":"venue"
},
  "geometry": {"coordinates":[-80.33905799999999,25.649526],"type":"Point"}
}