{
  "type": "Feature",
  "properties": {
    "addr:full":"13055 SW 89th Pl Miami FL 33176",
    "addr:housenumber":"13055",
    "addr:postcode":"33176",
    "addr:street":"Sw 89Th Pl",
    "iso:country":"US",
    "sg:address":"13055 SW 89th Pl",
    "sg:city":"Miami",
    "sg:classifiers":[
        {
            "category":"Professional",
            "subcategory":"Business Services",
            "type":"Services"
        }
    ],
    "sg:phone":"+1 305 259 5428",
    "sg:postcode":"33176",
    "sg:province":"FL",
    "sg:tags":[
        "interior",
        "consultant",
        "design",
        "decorator"
    ],
    "wof:name":"Galeria",
    "wof:placetype":"venue"
},
  "geometry": {"coordinates":[-80.339916,25.648256],"type":"Point"}
}