{
  "type": "Feature",
  "properties": {
    "addr:full":"501 Fairway Dr Deerfield Beach FL 33441",
    "addr:housenumber":"501",
    "addr:postcode":"33441",
    "addr:street":"Fairway Dr",
    "iso:country":"US",
    "sg:address":"501 Fairway Dr",
    "sg:city":"Deerfield Beach",
    "sg:classifiers":[
        {
            "category":"Travel",
            "subcategory":"Travel Agent",
            "type":"Entertainment"
        }
    ],
    "sg:phone":"+1 954 418 5850",
    "sg:postcode":"33441",
    "sg:province":"FL",
    "sg:tags":[
        "agency",
        "bureau"
    ],
    "wof:name":"Circle Travel Svc",
    "wof:placetype":"venue"
},
  "geometry": {"coordinates":[-80.114892,26.324576],"type":"Point"}
}