{
  "type": "Feature",
  "properties": {
    "addr:full":"16340 W Dixie Hwy Miami FL 33160",
    "addr:housenumber":"16340",
    "addr:postcode":"33160",
    "addr:street":"W Dixie Hwy",
    "iso:country":"US",
    "sg:address":"16340 W Dixie Hwy",
    "sg:city":"Miami",
    "sg:classifiers":[
        {
            "category":"Manufacturing",
            "subcategory":"Printing",
            "type":"Manufacturing & Wholesale Goods"
        }
    ],
    "sg:phone":"+1 305 945 3064",
    "sg:postcode":"33160",
    "sg:province":"FL",
    "sg:tags":[
        "lithographic",
        "commercial",
        "photocopying"
    ],
    "wof:name":"Bee- Jat Printing",
    "wof:placetype":"venue"
},
  "geometry": {"coordinates":[-80.15604,25.926729],"type":"Point"}
}