{
  "type": "Feature",
  "properties": {
    "iso:country":"US",
    "sg:address":"6820 NW 17th Ave",
    "sg:city":"Miami",
    "sg:classifiers":[
        {
            "category":"Building & Trades",
            "subcategory":"Locksmith",
            "type":"Services"
        }
    ],
    "sg:phone":"+1 786 718 1386",
    "sg:postcode":"33147",
    "sg:province":"FL",
    "sg:tags":[
        "key"
    ],
    "wof:name":"24 Hour Locksmith",
    "wof:placetype":"venue"
},
  "geometry": {"coordinates":[-80.225255,25.836243],"type":"Point"}
}