{
  "type": "Feature",
  "properties": {
    "iso:country":"US",
    "sg:address":"2109 SW Olympic Club Ter",
    "sg:city":"Palm City",
    "sg:classifiers":[
        {
            "category":"Professional",
            "subcategory":"Art Services",
            "type":"Services"
        }
    ],
    "sg:phone":"+1 772 221 1119",
    "sg:postcode":"34990",
    "sg:province":"FL",
    "sg:tags":[
        "commercial",
        "design"
    ],
    "wof:name":"Neumann Design",
    "wof:placetype":"venue"
},
  "geometry": {"coordinates":[-80.282873,27.17163],"type":"Point"}
}