{
  "type": "Feature",
  "properties": {
    "iso:country":"US",
    "sg:address":"1422 Lantana Rd",
    "sg:city":"Lantana",
    "sg:classifiers":[
        {
            "category":"Shopping",
            "subcategory":"Bicycles & Sporting Goods",
            "type":"Retail Goods"
        },
        {
            "category":"Sports & Exercise",
            "subcategory":"Swimming Pool",
            "type":"Entertainment"
        },
        {
            "category":"Building & Trades",
            "subcategory":"Construction",
            "type":"Services"
        },
        {
            "category":"Personal",
            "subcategory":"Sauna",
            "type":"Services"
        }
    ],
    "sg:phone":"+1 561 533 7713",
    "sg:postcode":"33462",
    "sg:province":"FL",
    "sg:tags":[
        "equipment",
        "supply"
    ],
    "wof:name":"Pinch A Penny",
    "wof:placetype":"venue"
},
  "geometry": {"coordinates":[-80.07142,26.587277],"type":"Point"}
}