{
  "type": "Feature",
  "properties": {
    "addr:full":"3000 NW 116th Ave Pompano Beach FL 33065",
    "addr:housenumber":"3000",
    "addr:postcode":"33065",
    "addr:street":"Nw 116Th Ave",
    "iso:country":"US",
    "sg:address":"3000 NW 116th Ave",
    "sg:city":"Pompano Beach",
    "sg:classifiers":[
        {
            "category":"Shopping",
            "subcategory":"Florist",
            "type":"Retail Goods"
        }
    ],
    "sg:phone":"+1 954 755 5658",
    "sg:postcode":"33065",
    "sg:province":"FL",
    "wof:name":"Plant Lady of South Florida",
    "wof:placetype":"venue"
},
  "geometry": {"coordinates":[-80.28081,26.269009],"type":"Point"}
}