{
  "type": "Feature",
  "properties": {
    "iso:country":"US",
    "sg:address":"1595 State Road 472",
    "sg:city":"Deland",
    "sg:classifiers":[
        {
            "category":"Sports & Exercise",
            "subcategory":"Golf",
            "type":"Entertainment"
        }
    ],
    "sg:phone":"+1 386 456 0689",
    "sg:postcode":"32724",
    "sg:province":"FL",
    "wof:name":"Victoria Park",
    "wof:placetype":"venue"
},
  "geometry": {"coordinates":[-81.293297,28.9734],"type":"Point"}
}