{
  "type": "Feature",
  "properties": {
    "iso:country":"US",
    "sg:address":"4654 Hazleton Ln",
    "sg:city":"Lake Worth",
    "sg:classifiers":[
        {
            "category":"Professional",
            "type":"Services"
        }
    ],
    "sg:phone":"+1 561 965 7392",
    "sg:postcode":"33449",
    "sg:province":"FL",
    "wof:name":"Arnold & Marsha Stock Cor",
    "wof:placetype":"venue"
},
  "geometry": {"coordinates":[-80.217508,26.612392],"type":"Point"}
}