{
  "type": "Feature",
  "properties": {
    "iso:country":"US",
    "sg:address":"12390 SW 128th St",
    "sg:city":"Miami",
    "sg:classifiers":[
        {
            "category":"Food & Beverages",
            "subcategory":"Meat & Fish",
            "type":"Retail Goods"
        }
    ],
    "sg:phone":"+1 305 255 7230",
    "sg:postcode":"33186",
    "sg:province":"FL",
    "sg:tags":[
        "shop"
    ],
    "wof:name":"Balter Meat Co",
    "wof:placetype":"venue"
},
  "geometry": {"coordinates":[-80.393799,25.6492],"type":"Point"}
}