{
  "type": "Feature",
  "properties": {
    "addr:full":"11345 Distribution Ave W Jacksonville FL 32256",
    "addr:housenumber":"11345",
    "addr:postcode":"32256",
    "addr:street":"Distribution Ave W",
    "iso:country":"US",
    "sg:address":"11345 Distribution Ave W",
    "sg:city":"Jacksonville",
    "sg:classifiers":[
        {
            "category":"Building & Trades",
            "subcategory":"Landscaping Services",
            "type":"Services"
        }
    ],
    "sg:phone":"+1 904 262 6089",
    "sg:postcode":"32256",
    "sg:province":"FL",
    "sg:tags":[
        "lawn",
        "care",
        "maintenance",
        "grounds"
    ],
    "wof:name":"Precision Turf Inc",
    "wof:placetype":"venue"
},
  "geometry": {"coordinates":[-81.534446,30.164423],"type":"Point"}
}