{
  "type": "Feature",
  "properties": {
    "iso:country":"US",
    "sg:address":"211 Windsong Way",
    "sg:city":"Titusville",
    "sg:classifiers":[
        {
            "category":"Shopping",
            "subcategory":"Bicycles & Sporting Goods",
            "type":"Retail Goods"
        }
    ],
    "sg:phone":"+1 321 383 8896",
    "sg:postcode":"32780",
    "sg:province":"FL",
    "wof:name":"Sterling Meadows Apparel & TAC",
    "wof:placetype":"venue"
},
  "geometry": {"coordinates":[-80.869485,28.514668],"type":"Point"}
}