{
  "type": "Feature",
  "properties": {
    "addr:full":"3224 Proud Clarion Trl Tallahassee FL 32309",
    "addr:housenumber":"3224",
    "addr:postcode":"32309",
    "addr:street":"Proud Clarion Trl",
    "iso:country":"US",
    "sg:address":"3224 Proud Clarion Trl",
    "sg:city":"Tallahassee",
    "sg:classifiers":[
        {
            "category":"Utilities",
            "subcategory":"Telephone",
            "type":"Services"
        }
    ],
    "sg:phone":"+1 850 668 8779",
    "sg:postcode":"32309",
    "sg:province":"FL",
    "sg:tags":[
        "communications"
    ],
    "wof:name":"Florida Telecard Distrg Co",
    "wof:placetype":"venue"
},
  "geometry": {"coordinates":[-84.196957,30.543838],"type":"Point"}
}