{
  "type": "Feature",
  "properties": {
    "addr:full":"5285 85th St Vero Beach FL 32967",
    "addr:housenumber":"5285",
    "addr:postcode":"32967",
    "addr:street":"85Th St",
    "iso:country":"US",
    "sg:address":"5285 85th St",
    "sg:city":"Vero Beach",
    "sg:classifiers":[
        {
            "category":"Building & Trades",
            "subcategory":"Construction",
            "type":"Services"
        }
    ],
    "sg:phone":"+1 772 589 1614",
    "sg:postcode":"32967",
    "sg:province":"FL",
    "sg:tags":[
        "painter"
    ],
    "wof:name":"C & D Painting",
    "wof:placetype":"venue"
},
  "geometry": {"coordinates":[-80.43844199999999,27.748345],"type":"Point"}
}