{
  "type": "Feature",
  "properties": {
    "iso:country":"US",
    "sg:address":"1335 Bennett Dr",
    "sg:city":"Longwood",
    "sg:classifiers":[
        {
            "category":"Wholesale",
            "subcategory":"Sporting Goods",
            "type":"Manufacturing & Wholesale Goods"
        },
        {
            "category":"Manufacturing",
            "subcategory":"Tools & Machinery",
            "type":"Manufacturing & Wholesale Goods"
        }
    ],
    "sg:phone":"+1 407 678 6417",
    "sg:postcode":"32750",
    "sg:province":"FL",
    "sg:tags":[
        "equipment",
        "mfg",
        "golf",
        "course"
    ],
    "wof:name":"Flow Tronex",
    "wof:placetype":"venue"
},
  "geometry": {"coordinates":[-81.353369,28.690292],"type":"Point"}
}