{
  "type": "Feature",
  "properties": {
    "iso:country":"US",
    "sg:address":"7648 River Rd",
    "sg:city":"Milton",
    "sg:classifiers":[
        {
            "category":"Building & Trades",
            "subcategory":"Plumbing",
            "type":"Services"
        }
    ],
    "sg:phone":"+1 850 626 2876",
    "sg:postcode":"32583",
    "sg:province":"FL",
    "sg:tags":[
        "contractor"
    ],
    "wof:name":"Saylors Air Conditioning & Htg",
    "wof:placetype":"venue"
},
  "geometry": {"coordinates":[-86.998476,30.650152],"type":"Point"}
}