{
  "type": "Feature",
  "properties": {
    "addr:full":"1171 Bluff Rd Apalachicola FL 32320",
    "addr:housenumber":"1171",
    "addr:postcode":"32320",
    "addr:street":"Bluff Rd",
    "iso:country":"US",
    "sg:address":"1171 Bluff Rd",
    "sg:city":"Apalachicola",
    "sg:classifiers":[
        {
            "category":"Building & Trades",
            "subcategory":"Electrical",
            "type":"Services"
        }
    ],
    "sg:phone":"+1 850 653 1855",
    "sg:postcode":"32320",
    "sg:province":"FL",
    "sg:tags":[
        "electrical",
        "contractor"
    ],
    "wof:name":"David Buck",
    "wof:placetype":"venue"
},
  "geometry": {"coordinates":[-85.02085,29.738039],"type":"Point"}
}