{
  "type": "Feature",
  "properties": {
    "addr:full":"3238 San Jose Mission Dr Dover FL 33527",
    "addr:housenumber":"3238",
    "addr:postcode":"33527",
    "addr:street":"San Jose Mission Dr",
    "iso:country":"US",
    "sg:address":"3238 San Jose Mission Dr",
    "sg:city":"Dover",
    "sg:classifiers":[
        {
            "category":"Social Services",
            "subcategory":"Child Care",
            "type":"Services"
        },
        {
            "category":"Education",
            "subcategory":"Preschool",
            "type":"Public Place"
        }
    ],
    "sg:phone":"+1 813 707 7002",
    "sg:postcode":"33527",
    "sg:province":"FL",
    "sg:tags":[
        "kindergarten",
        "nursery",
        "day"
    ],
    "wof:name":"Dover Migrant Headstart",
    "wof:placetype":"venue"
},
  "geometry": {"coordinates":[-82.233131,27.994274],"type":"Point"}
}