{
  "type": "Feature",
  "properties": {
    "iso:country":"US",
    "sg:address":"7100 Thomas Dr",
    "sg:city":"Panama City",
    "sg:classifiers":[
        {
            "category":"Shopping",
            "subcategory":"Gifts & Souvenirs",
            "type":"Retail Goods"
        }
    ],
    "sg:phone":"+1 850 249 7427",
    "sg:postcode":"32408",
    "sg:province":"FL",
    "wof:name":"Jaws Souvenirs",
    "wof:placetype":"venue"
},
  "geometry": {"coordinates":[-85.775733,30.15887],"type":"Point"}
}