{
  "type": "Feature",
  "properties": {
    "addr:full":"203 SW 2nd Ave Hallandale FL 33009",
    "addr:housenumber":"203",
    "addr:postcode":"33009",
    "addr:street":"Sw 2Nd Ave",
    "iso:country":"US",
    "sg:address":"203 SW 2nd Ave",
    "sg:city":"Hallandale",
    "sg:classifiers":[
        {
            "category":"Building & Trades",
            "subcategory":"Construction",
            "type":"Services"
        }
    ],
    "sg:phone":"+1 954 455 3485",
    "sg:postcode":"33009",
    "sg:province":"FL",
    "sg:tags":[
        "contractor"
    ],
    "wof:name":"Nelson Lopez Marble & Tile",
    "wof:placetype":"venue"
},
  "geometry": {"coordinates":[-80.15021400000001,25.981858],"type":"Point"}
}