{
  "type": "Feature",
  "properties": {
    "iso:country":"US",
    "sg:address":"6576 Seminole Pratt Whitney Rd",
    "sg:city":"Loxahatchee",
    "sg:classifiers":[
        {
            "category":"Home & Garden",
            "subcategory":"Garden Supply",
            "type":"Retail Goods"
        }
    ],
    "sg:phone":"+1 561 333 9651",
    "sg:postcode":"33470",
    "sg:province":"FL",
    "sg:tags":[
        "nurseryman"
    ],
    "wof:name":"Acreage Plant Nursery",
    "wof:placetype":"venue"
},
  "geometry": {"coordinates":[-80.29827400000001,26.773238],"type":"Point"}
}