{
  "type": "Feature",
  "properties": {
    "iso:country":"US",
    "sg:address":"26261 Imperial Harbor Blvd",
    "sg:city":"Bonita Springs",
    "sg:classifiers":[
        {
            "category":"Professional",
            "subcategory":"Computer Services",
            "type":"Services"
        }
    ],
    "sg:phone":"+1 239 287 3264",
    "sg:postcode":"34135",
    "sg:province":"FL",
    "wof:name":"Universal Co Inc",
    "wof:placetype":"venue"
},
  "geometry": {"coordinates":[-81.79294899999999,26.35451],"type":"Point"}
}