{
  "type": "Feature",
  "properties": {
    "addr:full":"1899 N Highland Ave Clearwater FL 33755",
    "addr:housenumber":"1899",
    "addr:postcode":"33755",
    "addr:street":"N Highland Ave",
    "iso:country":"US",
    "sg:address":"1899 N Highland Ave",
    "sg:city":"Clearwater",
    "sg:classifiers":[
        {
            "category":"Retail",
            "subcategory":"Auto Repair",
            "type":"Services"
        }
    ],
    "sg:phone":"+1 727 447 4754",
    "sg:postcode":"33755",
    "sg:province":"FL",
    "sg:tags":[
        "repairing",
        "automobile"
    ],
    "wof:name":"Sandy's Auto Svc",
    "wof:placetype":"venue"
},
  "geometry": {"coordinates":[-82.77540999999999,27.987633],"type":"Point"}
}