{
  "type": "Feature",
  "properties": {
    "iso:country":"US",
    "sg:address":"11502 Thonotosassa Rd",
    "sg:city":"Thonotosassa",
    "sg:classifiers":[
        {
            "category":"Travel",
            "subcategory":"Campground",
            "type":"Entertainment"
        }
    ],
    "sg:phone":"+1 813 986 4193",
    "sg:postcode":"33592",
    "sg:province":"FL",
    "sg:tags":[
        "camp",
        "fishing"
    ],
    "wof:name":"Reese's Fish Camp",
    "wof:placetype":"venue"
},
  "geometry": {"coordinates":[-82.281781,28.050318],"type":"Point"}
}