{
  "type": "Feature",
  "properties": {
    "iso:country":"US",
    "sg:address":"1801 Lewis Turner Blvd",
    "sg:city":"Fort Walton Bch",
    "sg:classifiers":[
        {
            "category":"Real Estate",
            "subcategory":"Real Estate Services",
            "type":"Services"
        }
    ],
    "sg:phone":"+1 850 862 2143",
    "sg:postcode":"32547",
    "sg:province":"FL",
    "sg:tags":[
        "company",
        "title"
    ],
    "wof:name":"First National Land Title Inc",
    "wof:placetype":"venue"
},
  "geometry": {"coordinates":[-86.626777,30.461632],"type":"Point"}
}