{
  "type": "Feature",
  "properties": {
    "addr:full":"10650 NW 29th Ter Doral FL 33172",
    "addr:housenumber":"10650",
    "addr:postcode":"33172",
    "addr:street":"Nw 29Th Ter",
    "iso:country":"US",
    "sg:address":"10650 NW 29th Ter",
    "sg:city":"Doral",
    "sg:classifiers":[
        {
            "category":"Shopping",
            "subcategory":"Mobile Phones",
            "type":"Retail Goods"
        }
    ],
    "sg:phone":"+1 305 514 3000",
    "sg:postcode":"33172",
    "sg:province":"FL",
    "wof:name":"Ccm Cellular",
    "wof:placetype":"venue"
},
  "geometry": {"coordinates":[-80.368554,25.801048],"type":"Point"}
}