{
  "type": "Feature",
  "properties": {
    "addr:full":"1085 S Main St Belle Glade FL 33430",
    "addr:housenumber":"1085",
    "addr:postcode":"33430",
    "addr:street":"S Main St",
    "iso:country":"US",
    "sg:address":"1085 S Main St",
    "sg:city":"Belle Glade",
    "sg:classifiers":[
        {
            "category":"Health Services",
            "subcategory":"Doctor",
            "type":"Services"
        }
    ],
    "sg:phone":"+1 561 992 0933",
    "sg:postcode":"33430",
    "sg:province":"FL",
    "sg:tags":[
        "physician",
        "surgeon"
    ],
    "wof:name":"Adult & Pediatric Dermatology",
    "wof:placetype":"venue"
},
  "geometry": {"coordinates":[-80.670439,26.672199],"type":"Point"}
}