{
  "type": "Feature",
  "properties": {
    "iso:country":"US",
    "sg:address":"425 NW 27th Ave",
    "sg:city":"Miami",
    "sg:classifiers":[
        {
            "category":"Professional",
            "subcategory":"Business Services",
            "type":"Services"
        },
        {
            "category":"Government",
            "subcategory":"Post Office",
            "type":"Public Place"
        }
    ],
    "sg:phone":"+1 305 541 2478",
    "sg:postcode":"33125",
    "sg:province":"FL",
    "sg:tags":[
        "mail",
        "shipping"
    ],
    "sg:website":"http://www.usps.com",
    "wof:name":"USPS - United States Post Office",
    "wof:placetype":"venue"
},
  "geometry": {"coordinates":[-80.23917400000001,25.77671],"type":"Point"}
}