{
  "type": "Feature",
  "properties": {
    "iso:country":"US",
    "sg:address":"46 W. Flagler St",
    "sg:city":"Miami",
    "sg:classifiers":[
        {
            "category":"Landmark",
            "subcategory":"Historic",
            "type":"Public Place"
        }
    ],
    "sg:postcode":"33130",
    "sg:province":"FL",
    "sg:tags":[
        "building",
        "historical"
    ],
    "wof:name":"Paul S. Walker Urbanscape",
    "wof:placetype":"venue"
},
  "geometry": {"coordinates":[-80.19453900000001,25.773855],"type":"Point"}
}