{
  "type": "Feature",
  "properties": {
    "addr:full":"12009 S. Williams St. Dunnellon FL 34432",
    "addr:housenumber":"12009",
    "addr:postcode":"34432",
    "addr:street":"S. Williams St.",
    "iso:country":"US",
    "sg:address":"12009 S. Williams St.",
    "sg:city":"Dunnellon",
    "sg:classifiers":[
        {
            "category":"Banks & Credit Unions",
            "subcategory":"Bureau De Change",
            "type":"Services"
        },
        {
            "category":"Manufacturing",
            "subcategory":"Printing",
            "type":"Manufacturing & Wholesale Goods"
        },
        {
            "category":"Professional",
            "subcategory":"Art Services",
            "type":"Services"
        },
        {
            "category":"Professional",
            "subcategory":"Printing & Photocopies",
            "type":"Services"
        }
    ],
    "sg:phone":"+1 352 207 7142",
    "sg:postcode":"34432",
    "sg:province":"FL",
    "sg:tags":[
        "photographers-portrait",
        "graphic",
        "business",
        "color",
        "designer",
        "imaging",
        "transparency",
        "digital",
        "print",
        "photographic",
        "card"
    ],
    "sg:website":"http://www.hitgraphixdesigns.com",
    "wof:name":"Hit Graphic Studios - Graphic Design & Studio Photography",
    "wof:placetype":"venue"
},
  "geometry": {"coordinates":[-82.462019,29.048527],"type":"Point"}
}