{
  "type": "Feature",
  "properties": {
    "addr:full":"725 Ohio Ave N Live Oak FL 32064",
    "addr:housenumber":"725",
    "addr:postcode":"32064",
    "addr:street":"Ohio Ave N",
    "iso:country":"US",
    "sg:address":"725 Ohio Ave N",
    "sg:city":"Live Oak",
    "sg:classifiers":[
        {
            "category":"Shopping",
            "subcategory":"Discount & Variety Stores",
            "type":"Retail Goods"
        },
        {
            "category":"Shopping",
            "subcategory":"Department Store",
            "type":"Retail Goods"
        }
    ],
    "sg:phone":"+1 386 362 1198",
    "sg:postcode":"32064",
    "sg:province":"FL",
    "sg:tags":[
        "shop"
    ],
    "wof:name":"Family Dollar Stores",
    "wof:placetype":"venue"
},
  "geometry": {"coordinates":[-82.981866,30.301644],"type":"Point"}
}