{
  "type": "Feature",
  "properties": {
    "addr:full":"8861 Oak Cir Tampa FL 33615",
    "addr:housenumber":"8861",
    "addr:postcode":"33615",
    "addr:street":"Oak Cir",
    "iso:country":"US",
    "sg:address":"8861 Oak Cir",
    "sg:city":"Tampa",
    "sg:classifiers":[
        {
            "category":"Manufacturing",
            "subcategory":"Toys & Sporting Goods",
            "type":"Manufacturing & Wholesale Goods"
        }
    ],
    "sg:phone":"+1 813 884 6810",
    "sg:postcode":"33615",
    "sg:province":"FL",
    "sg:tags":[
        "mfg"
    ],
    "wof:name":"Deb On Ear Bear & Friends",
    "wof:placetype":"venue"
},
  "geometry": {"coordinates":[-82.573795,28.030234],"type":"Point"}
}