{
  "type": "Feature",
  "properties": {
    "iso:country":"US",
    "sg:address":"3845 Old Tampa Hwy",
    "sg:city":"Lakeland",
    "sg:classifiers":[
        {
            "category":"Building & Trades",
            "subcategory":"Construction",
            "type":"Services"
        }
    ],
    "sg:phone":"+1 863 682 3464",
    "sg:postcode":"33811",
    "sg:province":"FL",
    "sg:tags":[
        "contractor"
    ],
    "wof:name":"Mike Peters Contracting",
    "wof:placetype":"venue"
},
  "geometry": {"coordinates":[-82.021294,28.029677],"type":"Point"}
}