{
  "type": "Feature",
  "properties": {
    "addr:full":"6705 SW 57th Ave Ste 702 South Miami FL 33143",
    "addr:housenumber":"6705",
    "addr:postcode":"33143",
    "addr:street":"Sw 57Th Ave Ste 702",
    "iso:country":"US",
    "sg:address":"6705 SW 57th Ave Ste 702",
    "sg:city":"South Miami",
    "sg:classifiers":[
        {
            "category":"Health Services",
            "subcategory":"Chiropractor",
            "type":"Services"
        }
    ],
    "sg:phone":"+1 305 662 6433",
    "sg:postcode":"33143",
    "sg:province":"FL",
    "sg:website":"www.pagechiropractic.com",
    "wof:name":"Page Chiropractic Life Center",
    "wof:placetype":"venue"
},
  "geometry": {"coordinates":[-80.30233800000001,25.716903],"type":"Point"}
}