{
  "type": "Feature",
  "properties": {
    "iso:country":"US",
    "sg:address":"8375 Baymeadows Way",
    "sg:city":"Jacksonville",
    "sg:classifiers":[
        {
            "category":"Professional",
            "type":"Services"
        }
    ],
    "sg:phone":"+1 904 230 2202",
    "sg:postcode":"32256",
    "sg:province":"FL",
    "wof:name":"Julington Loop Inc",
    "wof:placetype":"venue"
},
  "geometry": {"coordinates":[-81.576396,30.221625],"type":"Point"}
}