{
  "type": "Feature",
  "properties": {
    "addr:full":"1901 SW 118th Ave Fort Lauderdale FL 33325",
    "addr:housenumber":"1901",
    "addr:postcode":"33325",
    "addr:street":"Sw 118Th Ave",
    "iso:country":"US",
    "sg:address":"1901 SW 118th Ave",
    "sg:city":"Fort Lauderdale",
    "sg:classifiers":[
        {
            "category":"Building & Trades",
            "subcategory":"Construction",
            "type":"Services"
        }
    ],
    "sg:phone":"+1 954 424 9414",
    "sg:postcode":"33325",
    "sg:province":"FL",
    "sg:tags":[
        "general",
        "contractor"
    ],
    "wof:name":"Sherrod Contracting Inc",
    "wof:placetype":"venue"
},
  "geometry": {"coordinates":[-80.30637,26.08764],"type":"Point"}
}