{
  "type": "Feature",
  "properties": {
    "addr:full":"5345 Lake Jessamine Dr Orlando FL 32839",
    "addr:housenumber":"5345",
    "addr:postcode":"32839",
    "addr:street":"Lake Jessamine Dr",
    "iso:country":"US",
    "sg:address":"5345 Lake Jessamine Dr",
    "sg:city":"Orlando",
    "sg:classifiers":[
        {
            "category":"Arts & Performance",
            "subcategory":"Theater",
            "type":"Entertainment"
        }
    ],
    "sg:phone":"+1 407 812 6100",
    "sg:postcode":"32839",
    "sg:province":"FL",
    "sg:tags":[
        "talent",
        "agency",
        "casting"
    ],
    "wof:name":"Netane Entertainment",
    "wof:placetype":"venue"
},
  "geometry": {"coordinates":[-81.391468,28.483489],"type":"Point"}
}