{
  "type": "Feature",
  "properties": {
    "iso:country":"US",
    "sg:address":"3699 Eversholt St",
    "sg:city":"Clermont",
    "sg:classifiers":[
        {
            "category":"Wholesale",
            "subcategory":"Machinery & Supplies",
            "type":"Manufacturing & Wholesale Goods"
        }
    ],
    "sg:phone":"+1 352 242 2005",
    "sg:postcode":"34711",
    "sg:province":"FL",
    "sg:tags":[
        "equipment",
        "establishment"
    ],
    "wof:name":"Aquarius Building Maintenace",
    "wof:placetype":"venue"
},
  "geometry": {"coordinates":[-81.70866100000001,28.512103],"type":"Point"}
}