{
  "type": "Feature",
  "properties": {
    "iso:country":"US",
    "sg:address":"1270 Biscayne Blvd",
    "sg:city":"Deland",
    "sg:classifiers":[
        {
            "category":"Banks & Credit Unions",
            "subcategory":"Investment Brokerage",
            "type":"Services"
        },
        {
            "category":"Wholesale",
            "subcategory":"Non-durable Goods",
            "type":"Manufacturing & Wholesale Goods"
        }
    ],
    "sg:phone":"+1 386 822 9685",
    "sg:postcode":"32724",
    "sg:province":"FL",
    "sg:tags":[
        "wholesaler",
        "consultant",
        "planning",
        "financial"
    ],
    "wof:name":"Guaranteed Plus Inc",
    "wof:placetype":"venue"
},
  "geometry": {"coordinates":[-81.281723,29.059637],"type":"Point"}
}