{
  "type": "Feature",
  "properties": {
    "iso:country":"US",
    "sg:address":"2499 Parrot St",
    "sg:city":"North Port",
    "sg:classifiers":[
        {
            "category":"Home & Garden",
            "subcategory":"Carpets & Floor Coverings",
            "type":"Retail Goods"
        }
    ],
    "sg:phone":"+1 941 266 6461",
    "sg:postcode":"34286",
    "sg:province":"FL",
    "wof:name":"Amigos Carpet Corporation",
    "wof:placetype":"venue"
},
  "geometry": {"coordinates":[-82.20621300000001,27.079093],"type":"Point"}
}