{
  "type": "Feature",
  "properties": {
    "iso:country":"US",
    "sg:address":"4751 46th St N",
    "sg:city":"Saint Petersburg",
    "sg:classifiers":[
        {
            "category":"Organizations",
            "subcategory":"Religious Organization",
            "type":"Services"
        }
    ],
    "sg:phone":"+1 727 531 0316",
    "sg:postcode":"33714",
    "sg:province":"FL",
    "wof:name":"Church of God Union Assembly",
    "wof:placetype":"venue"
},
  "geometry": {"coordinates":[-82.69586,27.815801],"type":"Point"}
}