{
  "type": "Feature",
  "properties": {
    "addr:full":"5562 Wendy Lee Dr Titusville FL 32780",
    "addr:housenumber":"5562",
    "addr:postcode":"32780",
    "addr:street":"Wendy Lee Dr",
    "iso:country":"US",
    "sg:address":"5562 Wendy Lee Dr",
    "sg:city":"Titusville",
    "sg:classifiers":[
        {
            "category":"Building & Trades",
            "subcategory":"Plumbing",
            "type":"Services"
        }
    ],
    "sg:phone":"+1 321 637 1905",
    "sg:postcode":"32780",
    "sg:province":"FL",
    "sg:tags":[
        "conditioning",
        "air",
        "system",
        "contractor"
    ],
    "wof:name":"Arrigo Air & Heat",
    "wof:placetype":"venue"
},
  "geometry": {"coordinates":[-80.810571,28.542617],"type":"Point"}
}