{
  "type": "Feature",
  "properties": {
    "iso:country":"US",
    "sg:address":"2620 Ohio Ave",
    "sg:city":"Altamonte Spgs",
    "sg:classifiers":[
        {
            "category":"Building & Trades",
            "subcategory":"Plumbing",
            "type":"Services"
        }
    ],
    "sg:phone":"+1 407 908 2313",
    "sg:postcode":"32714",
    "sg:province":"FL",
    "sg:tags":[
        "plumbing",
        "contractor"
    ],
    "wof:name":"Brian Kierstead Plumbing",
    "wof:placetype":"venue"
},
  "geometry": {"coordinates":[-81.434802,28.676529],"type":"Point"}
}