{
  "type": "Feature",
  "properties": {
    "addr:full":"505 Anclote Rd Tarpon Springs FL 34689",
    "addr:housenumber":"505",
    "addr:postcode":"34689",
    "addr:street":"Anclote Rd",
    "iso:country":"US",
    "sg:address":"505 Anclote Rd",
    "sg:city":"Tarpon Springs",
    "sg:classifiers":[
        {
            "category":"Real Estate",
            "subcategory":"Developer",
            "type":"Services"
        },
        {
            "category":"Real Estate",
            "subcategory":"Real Estate Operator",
            "type":"Services"
        }
    ],
    "sg:phone":"+1 727 938 3788",
    "sg:postcode":"34689",
    "sg:province":"FL",
    "sg:tags":[
        "mobile",
        "home",
        "site"
    ],
    "wof:name":"Meadows Mobile Home Park",
    "wof:placetype":"venue"
},
  "geometry": {"coordinates":[-82.765213,28.163624],"type":"Point"}
}