{
  "type": "Feature",
  "properties": {
    "iso:country":"US",
    "sg:address":"701 N Mobley St",
    "sg:city":"Plant City",
    "sg:classifiers":[
        {
            "category":"Real Estate",
            "subcategory":"Real Estate Operator",
            "type":"Services"
        }
    ],
    "sg:phone":"+1 813 752 7398",
    "sg:postcode":"33563",
    "sg:province":"FL",
    "sg:tags":[
        "apartment"
    ],
    "wof:name":"Grove Court Apartments",
    "wof:placetype":"venue"
},
  "geometry": {"coordinates":[-82.142071,28.019813],"type":"Point"}
}