{
  "type": "Feature",
  "properties": {
    "iso:country":"US",
    "sg:address":"3035 Turnbull Bay Rd",
    "sg:city":"New Smyrna Beach",
    "sg:classifiers":[
        {
            "category":"Building & Trades",
            "subcategory":"Construction",
            "type":"Services"
        }
    ],
    "sg:phone":"+1 386 314 8727",
    "sg:postcode":"32168",
    "sg:province":"FL",
    "sg:tags":[
        "boring",
        "drilling",
        "contractor"
    ],
    "wof:name":"Turnbull Directional Drilling",
    "wof:placetype":"venue"
},
  "geometry": {"coordinates":[-80.998558,29.049643],"type":"Point"}
}