{
  "type": "Feature",
  "properties": {
    "addr:full":"3700 NW 124th Ave Coral Springs FL 33065",
    "addr:housenumber":"3700",
    "addr:postcode":"33065",
    "addr:street":"Nw 124Th Ave",
    "iso:country":"US",
    "sg:address":"3700 NW 124th Ave",
    "sg:city":"Coral Springs",
    "sg:classifiers":[
        {
            "category":"Real Estate",
            "subcategory":"Architect",
            "type":"Services"
        }
    ],
    "sg:phone":"+1 954 255 8812",
    "sg:postcode":"33065",
    "sg:province":"FL",
    "sg:tags":[
        "food",
        "equipment",
        "dealer",
        "supply"
    ],
    "sg:website":"www.advantageequipment.cc",
    "wof:name":"Advantage Equipment & Design",
    "wof:placetype":"venue"
},
  "geometry": {"coordinates":[-80.29127200000001,26.276591],"type":"Point"}
}