{
  "type": "Feature",
  "properties": {
    "addr:full":"425 SE 1st Ave Homestead FL 33034",
    "addr:housenumber":"425",
    "addr:postcode":"33034",
    "addr:street":"Se 1St Ave",
    "iso:country":"US",
    "sg:address":"425 SE 1st Ave",
    "sg:city":"Homestead",
    "sg:classifiers":[
        {
            "category":"Restaurant",
            "type":"Food & Drink"
        }
    ],
    "sg:menulink":"http://www.allmenus.com/fl/homestead/187139-mcdonalds/menu/",
    "sg:phone":"+1 305 248 9285",
    "sg:postcode":"33034",
    "sg:province":"FL",
    "sg:tags":[
        "burger",
        "american"
    ],
    "wof:name":"McDonald's",
    "wof:placetype":"venue"
},
  "geometry": {"coordinates":[-80.474386,25.442639],"type":"Point"}
}