{
  "type": "Feature",
  "properties": {
    "addr:full":"5871 Linn Ave Pensacola FL 32507",
    "addr:housenumber":"5871",
    "addr:postcode":"32507",
    "addr:street":"Linn Ave",
    "iso:country":"US",
    "sg:address":"5871 Linn Ave",
    "sg:city":"Pensacola",
    "sg:classifiers":[
        {
            "category":"Retail",
            "subcategory":"Laundry & Dry Cleaning",
            "type":"Services"
        }
    ],
    "sg:phone":"+1 850 492 0006",
    "sg:postcode":"32507",
    "sg:province":"FL",
    "sg:tags":[
        "cleaners"
    ],
    "wof:name":"Dry Cleaning To Your Door",
    "wof:placetype":"venue"
},
  "geometry": {"coordinates":[-87.43793599999999,30.314729],"type":"Point"}
}