{
  "type": "Feature",
  "properties": {
    "iso:country":"US",
    "sg:address":"113 Maryland Ave",
    "sg:city":"Cocoa",
    "sg:classifiers":[
        {
            "category":"Health Services",
            "subcategory":"Optometrist",
            "type":"Services"
        }
    ],
    "sg:phone":"+1 321 636 4422",
    "sg:postcode":"32922",
    "sg:province":"FL",
    "wof:name":"Howard B Bolos OD",
    "wof:placetype":"venue"
},
  "geometry": {"coordinates":[-80.72613800000001,28.352351],"type":"Point"}
}