{
  "type": "Feature",
  "properties": {
    "addr:full":"7865 Proctor Rd Tallahassee FL 32309",
    "addr:housenumber":"7865",
    "addr:postcode":"32309",
    "addr:street":"Proctor Rd",
    "iso:country":"US",
    "sg:address":"7865 Proctor Rd",
    "sg:city":"Tallahassee",
    "sg:classifiers":[
        {
            "category":"Building & Trades",
            "subcategory":"Construction",
            "type":"Services"
        }
    ],
    "sg:phone":"+1 850 668 2311",
    "sg:postcode":"32309",
    "sg:province":"FL",
    "sg:tags":[
        "house",
        "builder",
        "commercial",
        "construct",
        "home"
    ],
    "wof:name":"Williams Glen Contractor Inc",
    "wof:placetype":"venue"
},
  "geometry": {"coordinates":[-84.135142,30.575506],"type":"Point"}
}