{
  "type": "Feature",
  "properties": {
    "iso:country":"US",
    "sg:address":"5225 NW 89th Dr",
    "sg:city":"Pompano Beach",
    "sg:classifiers":[
        {
            "category":"Manufacturing",
            "subcategory":"Chemicals & Compounds",
            "type":"Manufacturing & Wholesale Goods"
        }
    ],
    "sg:phone":"+1 954 341 0307",
    "sg:postcode":"33067",
    "sg:province":"FL",
    "sg:tags":[
        "preparation",
        "pharmaceutical",
        "mfg"
    ],
    "wof:name":"S Lion National Inc",
    "wof:placetype":"venue"
},
  "geometry": {"coordinates":[-80.244472,26.295286],"type":"Point"}
}