{
  "type": "Feature",
  "properties": {
    "addr:full":"2554 Capital Cir NE Tallahassee FL 32308",
    "addr:housenumber":"2554",
    "addr:postcode":"32308",
    "addr:street":"Capital Cir Ne",
    "iso:country":"US",
    "sg:address":"2554 Capital Cir NE",
    "sg:city":"Tallahassee",
    "sg:classifiers":[
        {
            "category":"Professional",
            "subcategory":"Management & Consulting",
            "type":"Services"
        }
    ],
    "sg:phone":"+1 850 422 2258",
    "sg:postcode":"32308",
    "sg:province":"FL",
    "sg:tags":[
        "consultant",
        "elevator"
    ],
    "wof:name":"Schindler Elevator Corp",
    "wof:placetype":"venue"
},
  "geometry": {"coordinates":[-84.238299,30.486912],"type":"Point"}
}