{
  "type": "Feature",
  "properties": {
    "iso:country":"US",
    "sg:address":"1421 Border Dr",
    "sg:city":"Winter Park",
    "sg:classifiers":[
        {
            "category":"Building & Trades",
            "subcategory":"Construction",
            "type":"Services"
        }
    ],
    "sg:phone":"+1 407 679 7663",
    "sg:postcode":"32789",
    "sg:province":"FL",
    "sg:tags":[
        "roofing",
        "contractor"
    ],
    "wof:name":"Weather All Roofing",
    "wof:placetype":"venue"
},
  "geometry": {"coordinates":[-81.333709,28.622542],"type":"Point"}
}