{
  "type": "Feature",
  "properties": {
    "addr:full":"1614 Colonial Blvd Fort Myers FL 33907",
    "addr:housenumber":"1614",
    "addr:postcode":"33907",
    "addr:street":"Colonial Blvd",
    "iso:country":"US",
    "sg:address":"1614 Colonial Blvd",
    "sg:city":"Fort Myers",
    "sg:classifiers":[
        {
            "category":"Professional",
            "subcategory":"Lawyer & Legal Services",
            "type":"Services"
        }
    ],
    "sg:phone":"+1 239 476 8899",
    "sg:postcode":"33907",
    "sg:province":"FL",
    "wof:name":"Leonard Michael W PA Attorney At Law",
    "wof:placetype":"venue"
},
  "geometry": {"coordinates":[-81.87981000000001,26.596593],"type":"Point"}
}