{
  "type": "Feature",
  "properties": {
    "iso:country":"US",
    "sg:address":"5455 NW 24th St",
    "sg:city":"Margate",
    "sg:classifiers":[
        {
            "category":"Building & Trades",
            "subcategory":"Pest Control",
            "type":"Services"
        }
    ],
    "sg:phone":"+1 954 753 7986",
    "sg:postcode":"33063",
    "sg:province":"FL",
    "sg:website":"www.summerrain.net",
    "wof:name":"Summer Rain Fertilization Co",
    "wof:placetype":"venue"
},
  "geometry": {"coordinates":[-80.200569,26.257137],"type":"Point"}
}