{
  "type": "Feature",
  "properties": {
    "addr:full":"2201 Lucien Way Maitland FL 32751",
    "addr:housenumber":"2201",
    "addr:postcode":"32751",
    "addr:street":"Lucien Way",
    "iso:country":"US",
    "sg:address":"2201 Lucien Way",
    "sg:city":"Maitland",
    "sg:classifiers":[
        {
            "category":"Building & Trades",
            "subcategory":"Construction",
            "type":"Services"
        }
    ],
    "sg:phone":"+1 407 475 0526",
    "sg:postcode":"32751",
    "sg:province":"FL",
    "sg:tags":[
        "contractor"
    ],
    "wof:name":"Florida Bramingham Construction Inc",
    "wof:placetype":"venue"
},
  "geometry": {"coordinates":[-81.387199,28.625299],"type":"Point"}
}