{
  "type": "Feature",
  "properties": {
    "addr:full":"2011 W Garden St Pensacola FL 32501",
    "addr:housenumber":"2011",
    "addr:postcode":"32501",
    "addr:street":"W Garden St",
    "iso:country":"US",
    "sg:address":"2011 W Garden St",
    "sg:city":"Pensacola",
    "sg:classifiers":[
        {
            "category":"Building & Trades",
            "subcategory":"Landscaping Services",
            "type":"Services"
        }
    ],
    "sg:phone":"+1 850 458 8988",
    "sg:postcode":"32501",
    "sg:province":"FL",
    "wof:name":"A Affrdable Tree Lawn Pool Svc",
    "wof:placetype":"venue"
},
  "geometry": {"coordinates":[-87.24059099999999,30.411748],"type":"Point"}
}