{
  "type": "Feature",
  "properties": {
    "iso:country":"US",
    "sg:address":"4035 W Breckenridge Ct",
    "sg:city":"Beverly Hills",
    "sg:classifiers":[
        {
            "category":"Shopping",
            "subcategory":"Used Merchandise",
            "type":"Retail Goods"
        }
    ],
    "sg:phone":"+1 352 563 5200",
    "sg:postcode":"34465",
    "sg:province":"FL",
    "sg:tags":[
        "shop",
        "consignment"
    ],
    "wof:name":"Town-N-Country Consignment Btq",
    "wof:placetype":"venue"
},
  "geometry": {"coordinates":[-82.50128599999999,28.901582],"type":"Point"}
}