{
  "type": "Feature",
  "properties": {
    "iso:country":"US",
    "sg:address":"12425 SW 224th St",
    "sg:city":"Miami",
    "sg:classifiers":[
        {
            "category":"Organizations",
            "subcategory":"Religious Organization",
            "type":"Services"
        }
    ],
    "sg:phone":"+1 305 258 5554",
    "sg:postcode":"33170",
    "sg:province":"FL",
    "sg:tags":[
        "god",
        "churches-assemblies"
    ],
    "wof:name":"Last Harvest International Ministry",
    "wof:placetype":"venue"
},
  "geometry": {"coordinates":[-80.392734,25.558797],"type":"Point"}
}