{
  "type": "Feature",
  "properties": {
    "addr:full":"1905 E Olive Rd Pensacola FL 32514",
    "addr:housenumber":"1905",
    "addr:postcode":"32514",
    "addr:street":"E Olive Rd",
    "iso:country":"US",
    "sg:address":"1905 E Olive Rd",
    "sg:city":"Pensacola",
    "sg:classifiers":[
        {
            "category":"Building & Trades",
            "subcategory":"Construction",
            "type":"Services"
        }
    ],
    "sg:phone":"+1 850 484 2877",
    "sg:postcode":"32514",
    "sg:province":"FL",
    "sg:tags":[
        "general",
        "contractor"
    ],
    "sg:website":"www.walshgroup.com",
    "wof:name":"Archer Western",
    "wof:placetype":"venue"
},
  "geometry": {"coordinates":[-87.22693599999999,30.510657],"type":"Point"}
}