{
  "type": "Feature",
  "properties": {
    "addr:full":"2657 NW 20th St Miami FL 33142",
    "addr:housenumber":"2657",
    "addr:postcode":"33142",
    "addr:street":"Nw 20Th St",
    "iso:country":"US",
    "sg:address":"2657 NW 20th St",
    "sg:city":"Miami",
    "sg:classifiers":[
        {
            "category":"Wholesale",
            "subcategory":"Drugs",
            "type":"Manufacturing & Wholesale Goods"
        }
    ],
    "sg:phone":"+1 305 638 3077",
    "sg:postcode":"33142",
    "sg:province":"FL",
    "sg:tags":[
        "perfume"
    ],
    "wof:name":"Promotional Perfumes Inc",
    "wof:placetype":"venue"
},
  "geometry": {"coordinates":[-80.23909399999999,25.794368],"type":"Point"}
}