{
  "type": "Feature",
  "properties": {
    "iso:country":"US",
    "sg:address":"4 NE Milton St",
    "sg:city":"Lake City",
    "sg:classifiers":[
        {
            "category":"Food & Beverages",
            "subcategory":"Groceries & Convenience Stores",
            "type":"Retail Goods"
        }
    ],
    "sg:phone":"+1 386 752 4583",
    "sg:postcode":"32055",
    "sg:province":"FL",
    "wof:name":"S & S Food Store 17",
    "wof:placetype":"venue"
},
  "geometry": {"coordinates":[-82.61663799999999,30.190679],"type":"Point"}
}