{
  "type": "Feature",
  "properties": {
    "addr:full":"11524 SW 98th Pl Miami FL 33176",
    "addr:housenumber":"11524",
    "addr:postcode":"33176",
    "addr:street":"Sw 98Th Pl",
    "iso:country":"US",
    "sg:address":"11524 SW 98th Pl",
    "sg:city":"Miami",
    "sg:classifiers":[
        {
            "category":"Wholesale",
            "subcategory":"Machinery & Supplies",
            "type":"Manufacturing & Wholesale Goods"
        }
    ],
    "sg:phone":"+1 305 252 7999",
    "sg:postcode":"33176",
    "sg:province":"FL",
    "sg:tags":[
        "equipment",
        "establishment"
    ],
    "wof:name":"Cohen Technologies",
    "wof:placetype":"venue"
},
  "geometry": {"coordinates":[-80.35469399999999,25.661444],"type":"Point"}
}