{
  "type": "Feature",
  "properties": {
    "addr:full":"390 Bus Park Way Royal Palm Beach FL 33411",
    "addr:housenumber":"390",
    "addr:postcode":"33411",
    "addr:street":"Bus Park Way",
    "iso:country":"US",
    "sg:address":"390 Bus Park Way",
    "sg:city":"Royal Palm Beach",
    "sg:classifiers":[
        {
            "category":"Freight",
            "type":"Transportation"
        }
    ],
    "sg:phone":"+1 561 792 5533",
    "sg:postcode":"33411",
    "sg:province":"FL",
    "sg:tags":[
        "trucking"
    ],
    "wof:name":"Acres Agregate Svc Corp",
    "wof:placetype":"venue"
},
  "geometry": {"coordinates":[-80.20579600000001,26.699399],"type":"Point"}
}