{
  "type": "Feature",
  "properties": {
    "addr:full":"8142 Woodland Center Blvd Tampa FL 33614",
    "addr:housenumber":"8142",
    "addr:postcode":"33614",
    "addr:street":"Woodland Center Blvd",
    "iso:country":"US",
    "sg:address":"8142 Woodland Center Blvd",
    "sg:city":"Tampa",
    "sg:classifiers":[
        {
            "category":"Professional",
            "subcategory":"Advertising",
            "type":"Services"
        }
    ],
    "sg:phone":"+1 813 888 6471",
    "sg:postcode":"33614",
    "sg:province":"FL",
    "sg:tags":[
        "distribution"
    ],
    "wof:name":"Trader Distribution Svc",
    "wof:placetype":"venue"
},
  "geometry": {"coordinates":[-82.52396400000001,28.024033],"type":"Point"}
}