{
  "type": "Feature",
  "properties": {
    "iso:country":"US",
    "sg:address":"2734 Grand Blvd",
    "sg:city":"Holiday",
    "sg:classifiers":[
        {
            "category":"Shopping",
            "subcategory":"Musical Instruments",
            "type":"Retail Goods"
        }
    ],
    "sg:phone":"+1 727 938 7287",
    "sg:postcode":"34690",
    "sg:province":"FL",
    "wof:name":"Music Center of Holiday Inc",
    "wof:placetype":"venue"
},
  "geometry": {"coordinates":[-82.723331,28.198572],"type":"Point"}
}