{
  "type": "Feature",
  "properties": {
    "iso:country":"US",
    "sg:address":"9990 International Dr",
    "sg:city":"Orlando",
    "sg:classifiers":[
        {
            "category":"Travel",
            "subcategory":"Hotels & Motels",
            "type":"Entertainment"
        }
    ],
    "sg:phone":"+1 407 352 8700",
    "sg:postcode":"32819",
    "sg:province":"FL",
    "sg:tags":[
        "lodging"
    ],
    "wof:name":"Days Inn - Orlando (SeaWorld)",
    "wof:placetype":"venue"
},
  "geometry": {"coordinates":[-81.46032599999999,28.423184],"type":"Point"}
}