{
  "type": "Feature",
  "properties": {
    "addr:full":"7258 SW 8th St Miami FL 33144",
    "addr:housenumber":"7258",
    "addr:postcode":"33144",
    "addr:street":"Sw 8Th St",
    "iso:country":"US",
    "sg:address":"7258 SW 8th St",
    "sg:city":"Miami",
    "sg:classifiers":[
        {
            "category":"Shopping",
            "subcategory":"Mobile Phones",
            "type":"Retail Goods"
        }
    ],
    "sg:phone":"+1 305 260 0015",
    "sg:postcode":"33144",
    "sg:province":"FL",
    "wof:name":"America Cell Inc",
    "wof:placetype":"venue"
},
  "geometry": {"coordinates":[-80.312804,25.762774],"type":"Point"}
}