{
  "type": "Feature",
  "properties": {
    "iso:country":"US",
    "sg:address":"2609 Delaney Ave",
    "sg:city":"Orlando",
    "sg:classifiers":[
        {
            "category":"Food & Beverages",
            "subcategory":"Groceries & Convenience Stores",
            "type":"Retail Goods"
        }
    ],
    "sg:phone":"+1 407 423 3570",
    "sg:postcode":"32806",
    "sg:province":"FL",
    "wof:name":"7-Eleven",
    "wof:placetype":"venue"
},
  "geometry": {"coordinates":[-81.37213199999999,28.513033],"type":"Point"}
}