{
  "type": "Feature",
  "properties": {
    "addr:full":"838 Salzedo St Miami FL 33134",
    "addr:housenumber":"838",
    "addr:postcode":"33134",
    "addr:street":"Salzedo St",
    "iso:country":"US",
    "sg:address":"838 Salzedo St",
    "sg:city":"Miami",
    "sg:classifiers":[
        {
            "category":"Real Estate",
            "subcategory":"Real Estate Operator",
            "type":"Services"
        }
    ],
    "sg:phone":"+1 305 444 8063",
    "sg:postcode":"33134",
    "sg:province":"FL",
    "sg:tags":[
        "building",
        "apartment"
    ],
    "wof:name":"Eight Thirty Eight Salzedo APT",
    "wof:placetype":"venue"
},
  "geometry": {"coordinates":[-80.26090600000001,25.764166],"type":"Point"}
}