{
  "type": "Feature",
  "properties": {
    "iso:country":"US",
    "sg:address":"7887 NW 53rd St",
    "sg:city":"Miami",
    "sg:classifiers":[
        {
            "category":"Retail",
            "subcategory":"Auto Repair",
            "type":"Services"
        }
    ],
    "sg:phone":"+1 305 629 8806",
    "sg:postcode":"33166",
    "sg:province":"FL",
    "sg:tags":[
        "body",
        "shop"
    ],
    "wof:name":"Collision Center At Doral the",
    "wof:placetype":"venue"
},
  "geometry": {"coordinates":[-80.32550000000001,25.821501],"type":"Point"}
}