{
  "type": "Feature",
  "properties": {
    "addr:full":"4331 N Federal Hwy Fort Lauderdale FL 33308",
    "addr:housenumber":"4331",
    "addr:postcode":"33308",
    "addr:street":"N Federal Hwy",
    "iso:country":"US",
    "sg:address":"4331 N Federal Hwy",
    "sg:city":"Fort Lauderdale",
    "sg:classifiers":[
        {
            "category":"Organizations",
            "subcategory":"Professional Association",
            "type":"Services"
        }
    ],
    "sg:phone":"+1 954 776 2626",
    "sg:postcode":"33308",
    "sg:province":"FL",
    "sg:tags":[
        "travel",
        "agency"
    ],
    "wof:name":"IGTA",
    "wof:placetype":"venue"
},
  "geometry": {"coordinates":[-80.11969000000001,26.181546],"type":"Point"}
}