{
  "type": "Feature",
  "properties": {
    "iso:country":"US",
    "sg:address":"2389 NW 54th St",
    "sg:city":"Miami",
    "sg:classifiers":[
        {
            "category":"Social Services",
            "type":"Services"
        }
    ],
    "sg:phone":"+1 305 637 1018",
    "sg:postcode":"33142",
    "sg:province":"FL",
    "sg:tags":[
        "agency",
        "family"
    ],
    "wof:name":"JESCA",
    "wof:placetype":"venue"
},
  "geometry": {"coordinates":[-80.235117,25.824164],"type":"Point"}
}