{
  "type": "Feature",
  "properties": {
    "addr:full":"11495 W Flagler St Miami FL 33174",
    "addr:housenumber":"11495",
    "addr:postcode":"33174",
    "addr:street":"W Flagler St",
    "iso:country":"US",
    "sg:address":"11495 W Flagler St",
    "sg:city":"Miami",
    "sg:classifiers":[
        {
            "category":"Professional",
            "type":"Services"
        }
    ],
    "sg:phone":"+1 305 551 1951",
    "sg:postcode":"33174",
    "sg:province":"FL",
    "sg:tags":[
        "establishment"
    ],
    "wof:name":"Gaudendio F Tamayo",
    "wof:placetype":"venue"
},
  "geometry": {"coordinates":[-80.38182399999999,25.768331],"type":"Point"}
}