{
  "type": "Feature",
  "properties": {
    "iso:country":"US",
    "sg:address":"12320 Abberton Ct",
    "sg:city":"Orlando",
    "sg:classifiers":[
        {
            "category":"Building & Trades",
            "subcategory":"Landscaping Services",
            "type":"Services"
        }
    ],
    "sg:phone":"+1 407 694 7844",
    "sg:postcode":"32837",
    "sg:province":"FL",
    "sg:tags":[
        "landscape"
    ],
    "wof:name":"Greenlawn Design & Maintenance",
    "wof:placetype":"venue"
},
  "geometry": {"coordinates":[-81.39769099999999,28.387624],"type":"Point"}
}