{
  "type": "Feature",
  "properties": {
    "iso:country":"US",
    "sg:address":"1944 Aurora Rd",
    "sg:city":"Melbourne",
    "sg:phone":"+1 321 242 1123",
    "sg:postcode":"32935",
    "sg:province":"FL",
    "sg:website":"http://www.foremanmotors.com",
    "wof:name":"Foreman Motors Inc",
    "wof:placetype":"venue"
},
  "geometry": {"coordinates":[-80.653119,28.1359],"type":"Point"}
}