{
  "type": "Feature",
  "properties": {
    "addr:full":"7995 N Century Blvd Century FL 32535",
    "addr:housenumber":"7995",
    "addr:postcode":"32535",
    "addr:street":"N Century Blvd",
    "iso:country":"US",
    "sg:address":"7995 N Century Blvd",
    "sg:city":"Century",
    "sg:classifiers":[
        {
            "category":"Government",
            "subcategory":"Police Station",
            "type":"Public Place"
        }
    ],
    "sg:phone":"+1 850 256 3241",
    "sg:postcode":"32535",
    "sg:province":"FL",
    "sg:tags":[
        "sheriff"
    ],
    "wof:name":"Escambia Sheriff's Office",
    "wof:placetype":"venue"
},
  "geometry": {"coordinates":[-87.262249,30.97555],"type":"Point"}
}