{
  "type": "Feature",
  "properties": {
    "iso:country":"US",
    "sg:address":"10280 Javelin Rd",
    "sg:city":"Brooksville",
    "sg:classifiers":[
        {
            "category":"Building & Trades",
            "subcategory":"Construction",
            "type":"Services"
        }
    ],
    "sg:phone":"+1 352 754 9151",
    "sg:postcode":"34601",
    "sg:province":"FL",
    "sg:tags":[
        "coping",
        "plastering",
        "tiling",
        "pool",
        "swimming"
    ],
    "wof:name":"Amphibian Tile Inc",
    "wof:placetype":"venue"
},
  "geometry": {"coordinates":[-82.364413,28.572715],"type":"Point"}
}