{
  "type": "Feature",
  "properties": {
    "addr:full":"842 1st St Miami Beach FL 33139",
    "addr:housenumber":"842",
    "addr:postcode":"33139",
    "addr:street":"1St St",
    "iso:country":"US",
    "sg:address":"842 1st St",
    "sg:city":"Miami Beach",
    "sg:classifiers":[
        {
            "category":"Restaurant",
            "type":"Food & Drink"
        }
    ],
    "sg:phone":"+1 305 373 9991",
    "sg:postcode":"33139",
    "sg:province":"FL",
    "sg:tags":[
        "eating"
    ],
    "wof:name":"Chicken Kitchen",
    "wof:placetype":"venue"
},
  "geometry": {"coordinates":[-80.13614200000001,25.76985],"type":"Point"}
}