{
  "type": "Feature",
  "properties": {
    "addr:full":"3052 7th Ave N St Petersburg FL 33713",
    "addr:housenumber":"3052",
    "addr:postcode":"33713",
    "addr:street":"7Th Ave N",
    "iso:country":"US",
    "sg:address":"3052 7th Ave N",
    "sg:city":"St Petersburg",
    "sg:classifiers":[
        {
            "category":"Real Estate",
            "subcategory":"Real Estate Agent",
            "type":"Services"
        }
    ],
    "sg:phone":"+1 727 323 3101",
    "sg:postcode":"33713",
    "sg:province":"FL",
    "wof:name":"Specialty Sales Realty",
    "wof:placetype":"venue"
},
  "geometry": {"coordinates":[-82.67473099999999,27.77905],"type":"Point"}
}