{
  "type": "Feature",
  "properties": {
    "iso:country":"US",
    "sg:address":"5421 Beaumont Center Blvd",
    "sg:city":"Tampa",
    "sg:classifiers":[
        {
            "category":"Banks & Credit Unions",
            "subcategory":"Bank",
            "type":"Services"
        }
    ],
    "sg:phone":"+1 813 886 8705",
    "sg:postcode":"33634",
    "sg:province":"FL",
    "sg:tags":[
        "loan",
        "real estate"
    ],
    "sg:website":"www.communitycapitalmortgage.com",
    "wof:name":"Community Capital Mortgage",
    "wof:placetype":"venue"
},
  "geometry": {"coordinates":[-82.54758,27.996623],"type":"Point"}
}