{
  "type": "Feature",
  "properties": {
    "addr:full":"3195 Sea Shell Way Melbourne Beach FL 32951",
    "addr:housenumber":"3195",
    "addr:postcode":"32951",
    "addr:street":"Sea Shell Way",
    "iso:country":"US",
    "sg:address":"3195 Sea Shell Way",
    "sg:city":"Melbourne Beach",
    "sg:classifiers":[
        {
            "category":"Freight",
            "type":"Transportation"
        }
    ],
    "sg:phone":"+1 321 724 5769",
    "sg:postcode":"32951",
    "sg:province":"FL",
    "sg:tags":[
        "arrangement"
    ],
    "wof:name":"Advantage Transfer Intl LLC",
    "wof:placetype":"venue"
},
  "geometry": {"coordinates":[-80.542534,28.030477],"type":"Point"}
}