{
  "type": "Feature",
  "properties": {
    "addr:full":"7371 Pinnacle Pines Dr Fort Myers FL 33907",
    "addr:housenumber":"7371",
    "addr:postcode":"33907",
    "addr:street":"Pinnacle Pines Dr",
    "iso:country":"US",
    "sg:address":"7371 Pinnacle Pines Dr",
    "sg:city":"Fort Myers",
    "sg:classifiers":[
        {
            "category":"Real Estate",
            "subcategory":"Real Estate Operator",
            "type":"Services"
        }
    ],
    "sg:phone":"+1 239 275 6849",
    "sg:postcode":"33907",
    "sg:province":"FL",
    "sg:tags":[
        "apartment"
    ],
    "wof:name":"Seville Apartments",
    "wof:placetype":"venue"
},
  "geometry": {"coordinates":[-81.87879100000001,26.565625],"type":"Point"}
}