{
  "type": "Feature",
  "properties": {
    "addr:full":"3140 SW 7th St Ocala FL 34474",
    "addr:housenumber":"3140",
    "addr:postcode":"34474",
    "addr:street":"Sw 7Th St",
    "iso:country":"US",
    "sg:address":"3140 SW 7th St",
    "sg:city":"Ocala",
    "sg:classifiers":[
        {
            "category":"Freight",
            "type":"Transportation"
        }
    ],
    "sg:phone":"+1 352 867 1850",
    "sg:postcode":"34474",
    "sg:province":"FL",
    "sg:tags":[
        "delivery"
    ],
    "wof:name":"Delivery Specialist Inc",
    "wof:placetype":"venue"
},
  "geometry": {"coordinates":[-82.17653199999999,29.179879],"type":"Point"}
}