{
  "type": "Feature",
  "properties": {
    "iso:country":"US",
    "sg:address":"9299 County Line Rd",
    "sg:city":"Spring Hill",
    "sg:classifiers":[
        {
            "category":"Professional",
            "type":"Services"
        }
    ],
    "sg:phone":"+1 352 688 8788",
    "sg:postcode":"34608",
    "sg:province":"FL",
    "wof:name":"Suncoast Water Gardens",
    "wof:placetype":"venue"
},
  "geometry": {"coordinates":[-82.56556500000001,28.433847],"type":"Point"}
}