{
  "type": "Feature",
  "properties": {
    "iso:country":"US",
    "sg:address":"1100 Commercial Blvd",
    "sg:city":"Naples",
    "sg:classifiers":[
        {
            "category":"Shopping",
            "type":"Retail Goods"
        },
        {
            "category":"Wholesale",
            "subcategory":"Electrical",
            "type":"Manufacturing & Wholesale Goods"
        }
    ],
    "sg:phone":"+1 239 430 3892",
    "sg:postcode":"34104",
    "sg:province":"FL",
    "sg:tags":[
        "repair",
        "rad",
        "installation",
        "system",
        "microwave",
        "sales",
        "critical",
        "comm",
        "maintenance"
    ],
    "wof:name":"Communications International",
    "wof:placetype":"venue"
},
  "geometry": {"coordinates":[-81.752844,26.1635],"type":"Point"}
}