{
  "type": "Feature",
  "properties": {
    "iso:country":"US",
    "sg:address":"21346 Gladis Ave",
    "sg:city":"Port Charlotte",
    "sg:classifiers":[
        {
            "category":"Building & Trades",
            "subcategory":"Construction",
            "type":"Services"
        }
    ],
    "sg:phone":"+1 941 255 9475",
    "sg:postcode":"33952",
    "sg:province":"FL",
    "sg:tags":[
        "dry wall",
        "contractor"
    ],
    "wof:name":"Luis Garza Drywall Inc",
    "wof:placetype":"venue"
},
  "geometry": {"coordinates":[-82.096667,26.997343],"type":"Point"}
}