{
  "type": "Feature",
  "properties": {
    "addr:full":"1146 E Blue Heron Blvd Riviera Beach FL 33404",
    "addr:housenumber":"1146",
    "addr:postcode":"33404",
    "addr:street":"E Blue Heron Blvd",
    "iso:country":"US",
    "sg:address":"1146 E Blue Heron Blvd",
    "sg:city":"Riviera Beach",
    "sg:classifiers":[
        {
            "category":"Health Services",
            "subcategory":"Doctor",
            "type":"Services"
        }
    ],
    "sg:phone":"+1 561 845 8000",
    "sg:postcode":"33404",
    "sg:province":"FL",
    "sg:tags":[
        "physician",
        "surgeon"
    ],
    "wof:name":"Singer Island Medical Clinic",
    "wof:placetype":"venue"
},
  "geometry": {"coordinates":[-80.03709600000001,26.783753],"type":"Point"}
}