{
  "type": "Feature",
  "properties": {
    "iso:country":"US",
    "sg:address":"21333 Sweetwater Branch Rd",
    "sg:city":"Fountain",
    "sg:classifiers":[
        {
            "category":"Utilities",
            "subcategory":"Mobile Phone",
            "type":"Services"
        }
    ],
    "sg:phone":"+1 850 722 6303",
    "sg:postcode":"32438",
    "sg:province":"FL",
    "sg:tags":[
        "civil",
        "tower",
        "construction",
        "for",
        "cellular"
    ],
    "wof:name":"Albert Hancock Enterprises",
    "wof:placetype":"venue"
},
  "geometry": {"coordinates":[-85.426801,30.535241],"type":"Point"}
}