{
  "type": "Feature",
  "properties": {
    "iso:country":"US",
    "sg:address":"4365 Reflections Pkwy",
    "sg:city":"Sarasota",
    "sg:classifiers":[
        {
            "category":"Banks & Credit Unions",
            "subcategory":"Financial Services",
            "type":"Services"
        }
    ],
    "sg:phone":"+1 941 343 9323",
    "sg:postcode":"34233",
    "sg:province":"FL",
    "sg:tags":[
        "company",
        "holding"
    ],
    "wof:name":"Kyle Group Ltd",
    "wof:placetype":"venue"
},
  "geometry": {"coordinates":[-82.470816,27.294804],"type":"Point"}
}