{
  "type": "Feature",
  "properties": {
    "iso:country":"US",
    "sg:address":"6040 Medici Ct",
    "sg:city":"Sarasota",
    "sg:classifiers":[
        {
            "category":"Professional",
            "subcategory":"Management & Consulting",
            "type":"Services"
        }
    ],
    "sg:phone":"+1 941 782 5522",
    "sg:postcode":"34243",
    "sg:province":"FL",
    "sg:tags":[
        "consultant",
        "business"
    ],
    "wof:name":"Samuels & Samuels Assocaites",
    "wof:placetype":"venue"
},
  "geometry": {"coordinates":[-82.470628,27.387431],"type":"Point"}
}