{
  "type": "Feature",
  "properties": {
    "addr:full":"3813 Marianna Rd Jacksonville FL 32217",
    "addr:housenumber":"3813",
    "addr:postcode":"32217",
    "addr:street":"Marianna Rd",
    "iso:country":"US",
    "sg:address":"3813 Marianna Rd",
    "sg:city":"Jacksonville",
    "sg:classifiers":[
        {
            "category":"Building & Trades",
            "subcategory":"Construction",
            "type":"Services"
        }
    ],
    "sg:phone":"+1 904 737 3006",
    "sg:postcode":"32217",
    "sg:province":"FL",
    "sg:tags":[
        "residential"
    ],
    "wof:name":"Michael Daniel Dempsey",
    "wof:placetype":"venue"
},
  "geometry": {"coordinates":[-81.62045500000001,30.245801],"type":"Point"}
}