{
  "type": "Feature",
  "properties": {
    "iso:country":"US",
    "sg:address":"8809 Commodity Cir",
    "sg:city":"Orlando",
    "sg:classifiers":[
        {
            "category":"Shopping",
            "subcategory":"Optical Goods",
            "type":"Retail Goods"
        }
    ],
    "sg:phone":"+1 407 345 9814",
    "sg:postcode":"32819",
    "sg:province":"FL",
    "wof:name":"American Optical",
    "wof:placetype":"venue"
},
  "geometry": {"coordinates":[-81.431736,28.443238],"type":"Point"}
}