{
  "type": "Feature",
  "properties": {
    "addr:full":"5619 Sabena Rd Jacksonville FL 32207",
    "addr:housenumber":"5619",
    "addr:postcode":"32207",
    "addr:street":"Sabena Rd",
    "iso:country":"US",
    "sg:address":"5619 Sabena Rd",
    "sg:city":"Jacksonville",
    "sg:classifiers":[
        {
            "category":"Home & Garden",
            "subcategory":"Building Materials",
            "type":"Retail Goods"
        },
        {
            "category":"Building & Trades",
            "subcategory":"Construction",
            "type":"Services"
        },
        {
            "category":"Home & Garden",
            "subcategory":"Furniture",
            "type":"Retail Goods"
        }
    ],
    "sg:phone":"+1 904 626 2598",
    "sg:postcode":"32207",
    "sg:province":"FL",
    "sg:tags":[
        "bathroom",
        "altering",
        "top",
        "counter",
        "contractor",
        "planning",
        "cabinet",
        "remodeling",
        "kitchen"
    ],
    "sg:website":"http://www.freewebs.com/rroj",
    "wof:name":"Reliable Renovations of Jacksonville",
    "wof:placetype":"venue"
},
  "geometry": {"coordinates":[-81.609315,30.279162],"type":"Point"}
}