{
  "type": "Feature",
  "properties": {
    "iso:country":"US",
    "sg:address":"2559 N Dixie Hwy",
    "sg:city":"Lake Worth",
    "sg:classifiers":[
        {
            "category":"Travel",
            "subcategory":"Travel Agent",
            "type":"Entertainment"
        }
    ],
    "sg:phone":"+1 561 233 9068",
    "sg:postcode":"33460",
    "sg:province":"FL",
    "sg:tags":[
        "agency",
        "bureau"
    ],
    "wof:name":"Cartagena Travel West Palm",
    "wof:placetype":"venue"
},
  "geometry": {"coordinates":[-80.05641,26.644289],"type":"Point"}
}