{
  "type": "Feature",
  "properties": {
    "iso:country":"US",
    "sg:address":"5420 Gulf Breeze Pkwy",
    "sg:city":"Gulf Breeze",
    "sg:classifiers":[
        {
            "category":"Building & Trades",
            "subcategory":"Construction",
            "type":"Services"
        }
    ],
    "sg:phone":"+1 850 934 8161",
    "sg:postcode":"32563",
    "sg:province":"FL",
    "sg:tags":[
        "contractor"
    ],
    "wof:name":"SGI Builders Inc",
    "wof:placetype":"venue"
},
  "geometry": {"coordinates":[-86.998581,30.399932],"type":"Point"}
}