{
  "type": "Feature",
  "properties": {
    "iso:country":"US",
    "sg:address":"143 107th Ave",
    "sg:city":"Saint Petersburg",
    "sg:classifiers":[
        {
            "category":"Personal",
            "subcategory":"Beauty Salon",
            "type":"Services"
        }
    ],
    "sg:phone":"+1 727 360 2400",
    "sg:postcode":"33706",
    "sg:province":"FL",
    "sg:tags":[
        "shop"
    ],
    "wof:name":"LA Russo's Hair Design",
    "wof:placetype":"venue"
},
  "geometry": {"coordinates":[-82.767875,27.769524],"type":"Point"}
}