{
  "type": "Feature",
  "properties": {
    "iso:country":"US",
    "sg:address":"212 Summerbrooke Dr",
    "sg:city":"Tallahassee",
    "sg:classifiers":[
        {
            "category":"Professional",
            "subcategory":"Employment Agencies",
            "type":"Services"
        }
    ],
    "sg:phone":"+1 805 893 9268",
    "sg:postcode":"32312",
    "sg:province":"FL",
    "sg:tags":[
        "employer"
    ],
    "wof:name":"Dianne Tice",
    "wof:placetype":"venue"
},
  "geometry": {"coordinates":[-84.274986,30.57365],"type":"Point"}
}