{
  "type": "Feature",
  "properties": {
    "iso:country":"US",
    "sg:address":"12280 Southshore Blvd",
    "sg:city":"Wellington",
    "sg:classifiers":[
        {
            "category":"Banks & Credit Unions",
            "subcategory":"Bank",
            "type":"Services"
        }
    ],
    "sg:phone":"+1 561 422 1768",
    "sg:postcode":"33414",
    "sg:province":"FL",
    "sg:tags":[
        "saving",
        "commercial"
    ],
    "sg:website":"http://www.riversidenb.com",
    "wof:name":"Riverside Bank",
    "wof:placetype":"venue"
},
  "geometry": {"coordinates":[-80.239985,26.649111],"type":"Point"}
}