{
  "type": "Feature",
  "properties": {
    "iso:country":"US",
    "sg:address":"7002 Parke East Blvd",
    "sg:city":"Tampa",
    "sg:classifiers":[
        {
            "category":"Wholesale",
            "subcategory":"Books, Periodicals, & Newspapers",
            "type":"Manufacturing & Wholesale Goods"
        }
    ],
    "sg:phone":"+1 813 622 8087",
    "sg:postcode":"33610",
    "sg:province":"FL",
    "sg:tags":[
        "magazine"
    ],
    "sg:website":"www.andersonnews.com",
    "wof:name":"Anderson News Co",
    "wof:placetype":"venue"
},
  "geometry": {"coordinates":[-82.376122,28.000863],"type":"Point"}
}