{
  "type": "Feature",
  "properties": {
    "addr:full":"368 Pine Ranch East Rd Osprey FL 34229",
    "addr:housenumber":"368",
    "addr:postcode":"34229",
    "addr:street":"Pine Ranch East Rd",
    "iso:country":"US",
    "sg:address":"368 Pine Ranch East Rd",
    "sg:city":"Osprey",
    "sg:classifiers":[
        {
            "category":"Home & Garden",
            "subcategory":"Furniture",
            "type":"Retail Goods"
        }
    ],
    "sg:phone":"+1 941 232 0660",
    "sg:postcode":"34229",
    "sg:province":"FL",
    "sg:tags":[
        "store"
    ],
    "wof:name":"Igotkidsfurniture, Inc.",
    "wof:placetype":"venue"
},
  "geometry": {"coordinates":[-82.465515,27.202671],"type":"Point"}
}