{
  "type": "Feature",
  "properties": {
    "iso:country":"US",
    "sg:address":"1739 Verde Dr",
    "sg:city":"Clearwater",
    "sg:classifiers":[
        {
            "category":"Professional",
            "type":"Services"
        }
    ],
    "sg:phone":"+1 727 796 5360",
    "sg:postcode":"33765",
    "sg:province":"FL",
    "wof:name":"Loud and Proud Inc",
    "wof:placetype":"venue"
},
  "geometry": {"coordinates":[-82.742901,27.98428],"type":"Point"}
}