{
  "type": "Feature",
  "properties": {
    "addr:full":"25 S Osprey Ave Sarasota FL 34236",
    "addr:housenumber":"25",
    "addr:postcode":"34236",
    "addr:street":"S Osprey Ave",
    "iso:country":"US",
    "sg:address":"25 S Osprey Ave",
    "sg:city":"Sarasota",
    "sg:classifiers":[
        {
            "category":"Real Estate",
            "subcategory":"Real Estate Agent",
            "type":"Services"
        }
    ],
    "sg:phone":"+1 941 364 3604",
    "sg:postcode":"34236",
    "sg:province":"FL",
    "wof:name":"Tivoli Realty",
    "wof:placetype":"venue"
},
  "geometry": {"coordinates":[-82.534301,27.336223],"type":"Point"}
}