{
  "type": "Feature",
  "properties": {
    "addr:full":"22968 Bayshore Rd Port Charlotte FL 33980",
    "addr:housenumber":"22968",
    "addr:postcode":"33980",
    "addr:street":"Bayshore Rd",
    "iso:country":"US",
    "sg:address":"22968 Bayshore Rd",
    "sg:city":"Port Charlotte",
    "sg:classifiers":[
        {
            "category":"Travel",
            "subcategory":"Hotels & Motels",
            "type":"Entertainment"
        }
    ],
    "sg:phone":"+1 941 629 4046",
    "sg:postcode":"33980",
    "sg:province":"FL",
    "sg:tags":[
        "operation"
    ],
    "wof:name":"Sunnybrook Motel",
    "wof:placetype":"venue"
},
  "geometry": {"coordinates":[-82.074547,26.957924],"type":"Point"}
}