{
  "type": "Feature",
  "properties": {
    "addr:full":"2950 NW 24th St Miami FL 33142",
    "addr:housenumber":"2950",
    "addr:postcode":"33142",
    "addr:street":"Nw 24Th St",
    "iso:country":"US",
    "sg:address":"2950 NW 24th St",
    "sg:city":"Miami",
    "sg:classifiers":[
        {
            "category":"Utilities",
            "subcategory":"Natural Gas",
            "type":"Services"
        }
    ],
    "sg:phone":"+1 305 634 0215",
    "sg:postcode":"33142",
    "sg:province":"FL",
    "wof:name":"Economy Gas",
    "wof:placetype":"venue"
},
  "geometry": {"coordinates":[-80.24298899999999,25.7988],"type":"Point"}
}