{
  "type": "Feature",
  "properties": {
    "iso:country":"US",
    "sg:address":"599 S Collier Blvd",
    "sg:city":"Marco Island",
    "sg:classifiers":[
        {
            "category":"Restaurant",
            "type":"Food & Drink"
        }
    ],
    "sg:phone":"+1 239 394 5100",
    "sg:postcode":"34145",
    "sg:province":"FL",
    "sg:tags":[
        "eating"
    ],
    "wof:name":"5 Brothers Pizza",
    "wof:placetype":"venue"
},
  "geometry": {"coordinates":[-81.72619,25.919895],"type":"Point"}
}