{
  "type": "Feature",
  "properties": {
    "addr:full":"180 US Hwy 90 W Baldwin FL 32234",
    "addr:housenumber":"180",
    "addr:postcode":"32234",
    "addr:street":"Us Hwy 90 W",
    "iso:country":"US",
    "sg:address":"180 US Hwy 90 W",
    "sg:city":"Baldwin",
    "sg:classifiers":[
        {
            "category":"Home & Garden",
            "subcategory":"Hardware",
            "type":"Retail Goods"
        },
        {
            "category":"Home & Garden",
            "subcategory":"Furniture",
            "type":"Retail Goods"
        }
    ],
    "sg:phone":"+1 904 266 4622",
    "sg:postcode":"32234",
    "sg:province":"FL",
    "sg:tags":[
        "household",
        "appliance"
    ],
    "wof:name":"Baldwin Home Appliance Co",
    "wof:placetype":"venue"
},
  "geometry": {"coordinates":[-81.976741,30.302783],"type":"Point"}
}