{
  "type": "Feature",
  "properties": {
    "iso:country":"US",
    "sg:address":"4560 Via Royale",
    "sg:city":"Fort Myers",
    "sg:classifiers":[
        {
            "category":"Insurance",
            "subcategory":"Hazard Insurance",
            "type":"Services"
        }
    ],
    "sg:phone":"+1 239 939 5705",
    "sg:postcode":"33919",
    "sg:province":"FL",
    "sg:tags":[
        "fund"
    ],
    "wof:name":"Puls Robert Cert Pnsn Conslnt",
    "wof:placetype":"venue"
},
  "geometry": {"coordinates":[-81.888682,26.595037],"type":"Point"}
}