{
  "type": "Feature",
  "properties": {
    "iso:country":"US",
    "sg:address":"134 N Federal Hwy ",
    "sg:city":"Hallandale",
    "sg:classifiers":[
        {
            "category":"Restaurant",
            "type":"Food & Drink"
        }
    ],
    "sg:menulink":"http://www.allmenus.com/fl/hallandale-beach/292603-eddie-hill/menu/",
    "sg:phone":"+1 954 454 0023",
    "sg:postcode":"33009",
    "sg:province":"FL",
    "sg:tags":[
        "thai",
        "sushi"
    ],
    "wof:name":"Eddie Hill",
    "wof:placetype":"venue"
},
  "geometry": {"coordinates":[-80.142236,25.987434],"type":"Point"}
}