{
  "type": "Feature",
  "properties": {
    "iso:country":"US",
    "sg:address":"560 US Hwy 1",
    "sg:city":"North Palm Beach",
    "sg:classifiers":[
        {
            "category":"Government",
            "subcategory":"Police Station",
            "type":"Public Place"
        }
    ],
    "sg:phone":"+1 561 848 2525",
    "sg:postcode":"33408",
    "sg:province":"FL",
    "sg:tags":[
        "department"
    ],
    "wof:name":"North Palm Beach Police Dept",
    "wof:placetype":"venue"
},
  "geometry": {"coordinates":[-80.054531,26.796644],"type":"Point"}
}