{
  "type": "Feature",
  "properties": {
    "iso:country":"US",
    "sg:address":"655 Oleander Dr",
    "sg:city":"Merritt Island",
    "sg:classifiers":[
        {
            "category":"Building & Trades",
            "subcategory":"Landscaping Services",
            "type":"Services"
        }
    ],
    "sg:phone":"+1 321 452 1373",
    "sg:postcode":"32952",
    "sg:province":"FL",
    "sg:tags":[
        "landscape"
    ],
    "wof:name":"R Vanepp Landscape Arch",
    "wof:placetype":"venue"
},
  "geometry": {"coordinates":[-80.694846,28.345984],"type":"Point"}
}