{
  "type": "Feature",
  "properties": {
    "addr:full":"25 Beal Pkwy NW Fort Walton Bch FL 32548",
    "addr:housenumber":"25",
    "addr:postcode":"32548",
    "addr:street":"Beal Pkwy Nw Fort",
    "iso:country":"US",
    "sg:address":"25 Beal Pkwy NW",
    "sg:city":"Fort Walton Bch",
    "sg:classifiers":[
        {
            "category":"Professional",
            "subcategory":"Lawyer & Legal Services",
            "type":"Services"
        }
    ],
    "sg:phone":"+1 850 244 0400",
    "sg:postcode":"32548",
    "sg:province":"FL",
    "sg:tags":[
        "attorney"
    ],
    "sg:website":"www.crewlaw.com",
    "wof:name":"Crew & Crew PA",
    "wof:placetype":"venue"
},
  "geometry": {"coordinates":[-86.61361599999999,30.415404],"type":"Point"}
}