{
  "type": "Feature",
  "properties": {
    "iso:country":"US",
    "sg:address":"740 NW 45th Ave Apt G1",
    "sg:city":"Miami",
    "sg:classifiers":[
        {
            "category":"Recreation",
            "type":"Entertainment"
        }
    ],
    "sg:phone":"+1 305 529 1646",
    "sg:postcode":"33126",
    "sg:province":"FL",
    "sg:tags":[
        "entertainers-family",
        "business"
    ],
    "wof:name":"Jrv Productions & Entertainment Group Corp.",
    "wof:placetype":"venue"
},
  "geometry": {"coordinates":[-80.26955,25.779142],"type":"Point"}
}