{
  "type": "Feature",
  "properties": {
    "iso:country":"US",
    "sg:address":"3702 Muir Woods Way",
    "sg:city":"Naples",
    "sg:classifiers":[
        {
            "category":"Wholesale",
            "subcategory":"Non-durable Goods",
            "type":"Manufacturing & Wholesale Goods"
        }
    ],
    "sg:phone":"+1 239 353 9133",
    "sg:postcode":"34116",
    "sg:province":"FL",
    "wof:name":"Massa Travel Trade",
    "wof:placetype":"venue"
},
  "geometry": {"coordinates":[-81.70867800000001,26.167161],"type":"Point"}
}