{
  "type": "Feature",
  "properties": {
    "iso:country":"US",
    "sg:address":"2500 W International Speedway Blvd",
    "sg:city":"Daytona Beach",
    "sg:classifiers":[
        {
            "category":"Home & Garden",
            "subcategory":"Furniture",
            "type":"Retail Goods"
        }
    ],
    "sg:phone":"+1 386 226 0122",
    "sg:postcode":"32114",
    "sg:province":"FL",
    "sg:tags":[
        "mattress"
    ],
    "wof:name":"Mattress Zone",
    "wof:placetype":"venue"
},
  "geometry": {"coordinates":[-81.082779,29.175109],"type":"Point"}
}