{
  "type": "Feature",
  "properties": {
    "addr:full":"15471 SW 137th Ave Miami FL 33177",
    "addr:housenumber":"15471",
    "addr:postcode":"33177",
    "addr:street":"Sw 137Th Ave",
    "iso:country":"US",
    "sg:address":"15471 SW 137th Ave",
    "sg:city":"Miami",
    "sg:classifiers":[
        {
            "category":"Communications",
            "subcategory":"News Services",
            "type":"Services"
        },
        {
            "category":"Transit Center",
            "subcategory":"Freight",
            "type":"Transportation"
        },
        {
            "category":"Professional",
            "subcategory":"Business Services",
            "type":"Services"
        },
        {
            "category":"Professional",
            "subcategory":"Printing & Photocopies",
            "type":"Services"
        }
    ],
    "sg:phone":"+1 305 234 3132",
    "sg:postcode":"33177",
    "sg:province":"FL",
    "sg:tags":[
        "cargo",
        "fax",
        "transparency",
        "package",
        "color",
        "express",
        "duplicating",
        "shipping",
        "air",
        "copying",
        "print",
        "mail",
        "photographic"
    ],
    "sg:website":"http://www.kinkos.com",
    "wof:name":"Fedex Kinko's",
    "wof:placetype":"venue"
},
  "geometry": {"coordinates":[-80.414428,25.623788],"type":"Point"}
}