{
  "type": "Feature",
  "properties": {
    "iso:country":"US",
    "sg:address":"6111 S Dixie Hwy",
    "sg:city":"West Palm Beach",
    "sg:classifiers":[
        {
            "category":"Personal",
            "subcategory":"Beauty Salon",
            "type":"Services"
        }
    ],
    "sg:phone":"+1 561 582 4222",
    "sg:postcode":"33405",
    "sg:province":"FL",
    "sg:tags":[
        "shop"
    ],
    "wof:name":"Hair & Nail Station",
    "wof:placetype":"venue"
},
  "geometry": {"coordinates":[-80.05593399999999,26.659579],"type":"Point"}
}