{
  "type": "Feature",
  "properties": {
    "addr:full":"801 US Hwy 27 Avon Park FL 33825",
    "addr:housenumber":"801",
    "addr:postcode":"33825",
    "addr:street":"Us Hwy 27",
    "iso:country":"US",
    "sg:address":"801 US Hwy 27",
    "sg:city":"Avon Park",
    "sg:classifiers":[
        {
            "category":"Professional",
            "subcategory":"Accounting & Tax Preparation",
            "type":"Services"
        }
    ],
    "sg:phone":"+1 863 453 2525",
    "sg:postcode":"33825",
    "sg:province":"FL",
    "sg:tags":[
        "return",
        "filing"
    ],
    "wof:name":"Jackson Hewitt Tax Svc",
    "wof:placetype":"venue"
},
  "geometry": {"coordinates":[-81.51444499999999,27.605625],"type":"Point"}
}