{
  "type": "Feature",
  "properties": {
    "iso:country":"US",
    "sg:address":"368 N Turkey Pine Loop",
    "sg:city":"Lecanto",
    "sg:classifiers":[
        {
            "category":"Home & Garden",
            "subcategory":"Building Materials",
            "type":"Retail Goods"
        }
    ],
    "sg:phone":"+1 352 527 1940",
    "sg:postcode":"34461",
    "sg:province":"FL",
    "wof:name":"Olde English Finer Bathroom",
    "wof:placetype":"venue"
},
  "geometry": {"coordinates":[-82.519244,28.869516],"type":"Point"}
}