{
  "type": "Feature",
  "properties": {
    "iso:country":"US",
    "sg:address":"1819 N Alafaya Trl",
    "sg:city":"Orlando",
    "sg:classifiers":[
        {
            "category":"Food & Beverages",
            "subcategory":"Groceries & Convenience Stores",
            "type":"Retail Goods"
        }
    ],
    "sg:phone":"+1 407 275 1555",
    "sg:postcode":"32826",
    "sg:province":"FL",
    "wof:name":"Racetrac Petroleum Inc",
    "wof:placetype":"venue"
},
  "geometry": {"coordinates":[-81.207663,28.569073],"type":"Point"}
}