{
  "type": "Feature",
  "properties": {
    "iso:country":"US",
    "sg:address":"271 N Babcock St",
    "sg:city":"Melbourne",
    "sg:classifiers":[
        {
            "category":"Wholesale",
            "subcategory":"Electrical",
            "type":"Manufacturing & Wholesale Goods"
        }
    ],
    "sg:phone":"+1 321 242 2255",
    "sg:postcode":"32935",
    "sg:province":"FL",
    "sg:tags":[
        "household",
        "appliance"
    ],
    "wof:name":"Advance Appliance Parts Inc",
    "wof:placetype":"venue"
},
  "geometry": {"coordinates":[-80.62175499999999,28.111316],"type":"Point"}
}