{
  "type": "Feature",
  "properties": {
    "addr:full":"1190 W 54th St Hialeah FL 33012",
    "addr:housenumber":"1190",
    "addr:postcode":"33012",
    "addr:street":"W 54Th St",
    "iso:country":"US",
    "sg:address":"1190 W 54th St",
    "sg:city":"Hialeah",
    "sg:classifiers":[
        {
            "category":"Retail",
            "subcategory":"Auto Repair",
            "type":"Services"
        }
    ],
    "sg:phone":"+1 305 828 7356",
    "sg:postcode":"33012",
    "sg:province":"FL",
    "sg:tags":[
        "automobile",
        "equipment-service",
        "air conditioning"
    ],
    "wof:name":"American Auto Air",
    "wof:placetype":"venue"
},
  "geometry": {"coordinates":[-80.306905,25.8718],"type":"Point"}
}