{
  "type": "Feature",
  "properties": {
    "iso:country":"US",
    "sg:address":"848 1st Ave N",
    "sg:city":"Naples",
    "sg:classifiers":[
        {
            "category":"Social Services",
            "type":"Services"
        }
    ],
    "sg:phone":"+1 239 649 1414",
    "sg:postcode":"34102",
    "sg:province":"FL",
    "sg:tags":[
        "counseling"
    ],
    "wof:name":"Counseling Associates",
    "wof:placetype":"venue"
},
  "geometry": {"coordinates":[-81.796318,26.148337],"type":"Point"}
}