{
  "type": "Feature",
  "properties": {
    "addr:full":"14691 Biscayne Blvd North Miami FL 33181",
    "addr:housenumber":"14691",
    "addr:postcode":"33181",
    "addr:street":"Biscayne Blvd",
    "iso:country":"US",
    "sg:address":"14691 Biscayne Blvd",
    "sg:city":"North Miami",
    "sg:classifiers":[
        {
            "category":"Food & Beverages",
            "subcategory":"Bakery",
            "type":"Retail Goods"
        }
    ],
    "sg:phone":"+1 305 945 5316",
    "sg:postcode":"33181",
    "sg:province":"FL",
    "sg:tags":[
        "sandwich"
    ],
    "sg:website":"www.subway.com",
    "wof:name":"Subway",
    "wof:placetype":"venue"
},
  "geometry": {"coordinates":[-80.157093,25.910969],"type":"Point"}
}