{
  "type": "Feature",
  "properties": {
    "addr:full":"4210 Saltwater Blvd Tampa FL 33615",
    "addr:postcode":"4210;33615",
    "addr:street":"Saltwater Blvd",
    "iso:country":"US",
    "sg:address":"4210 Saltwater Blvd",
    "sg:city":"Tampa",
    "sg:classifiers":[
        {
            "category":"Professional",
            "subcategory":"Management & Consulting",
            "type":"Services"
        }
    ],
    "sg:phone":"+1 813 249 5564",
    "sg:postcode":"33615",
    "sg:province":"FL",
    "wof:name":"Professional Materials Managem",
    "wof:placetype":"venue"
},
  "geometry": {"coordinates":[-82.56250799999999,27.977674],"type":"Point"}
}