{
  "type": "Feature",
  "properties": {
    "addr:full":"301 N 25th St Fort Pierce FL 34947",
    "addr:housenumber":"301",
    "addr:postcode":"34947",
    "addr:street":"N 25Th St",
    "iso:country":"US",
    "sg:address":"301 N 25th St",
    "sg:city":"Fort Pierce",
    "sg:classifiers":[
        {
            "category":"Food & Beverages",
            "subcategory":"Meat & Fish",
            "type":"Retail Goods"
        }
    ],
    "sg:phone":"+1 772 464 8519",
    "sg:postcode":"34947",
    "sg:province":"FL",
    "sg:tags":[
        "eating"
    ],
    "wof:name":"McManus Seafood Inc",
    "wof:placetype":"venue"
},
  "geometry": {"coordinates":[-80.34989,27.450499],"type":"Point"}
}