{
  "type": "Feature",
  "properties": {
    "addr:full":"12100 Kendra Ct Orlando FL 32824",
    "addr:housenumber":"12100",
    "addr:postcode":"32824",
    "addr:street":"Kendra Ct",
    "iso:country":"US",
    "sg:address":"12100 Kendra Ct",
    "sg:city":"Orlando",
    "sg:classifiers":[
        {
            "category":"Social Services",
            "subcategory":"Child Care",
            "type":"Services"
        }
    ],
    "sg:phone":"+1 407 826 9287",
    "sg:postcode":"32824",
    "sg:province":"FL",
    "sg:tags":[
        "day"
    ],
    "wof:name":"Ada Hickey Family Child Care H",
    "wof:placetype":"venue"
},
  "geometry": {"coordinates":[-81.38804399999999,28.391316],"type":"Point"}
}