{
  "type": "Feature",
  "properties": {
    "iso:country":"US",
    "sg:address":"843 Hickory Springs Ln",
    "sg:city":"Jacksonville",
    "sg:classifiers":[
        {
            "category":"Personal",
            "subcategory":"Beauty Salon",
            "type":"Services"
        }
    ],
    "sg:phone":"+1 904 786 1733",
    "sg:postcode":"32221",
    "sg:province":"FL",
    "wof:name":"Opal Beauty Shop",
    "wof:placetype":"venue"
},
  "geometry": {"coordinates":[-81.8325,30.300226],"type":"Point"}
}