{
  "type": "Feature",
  "properties": {
    "iso:country":"US",
    "sg:address":"5401 S Kirkman Rd",
    "sg:city":"Orlando",
    "sg:classifiers":[
        {
            "category":"Insurance",
            "subcategory":"Insurance Agent",
            "type":"Services"
        }
    ],
    "sg:phone":"+1 407 345 8033",
    "sg:postcode":"32819",
    "sg:province":"FL",
    "sg:tags":[
        "broker"
    ],
    "wof:name":"Monumental Life Insurance Co",
    "wof:placetype":"venue"
},
  "geometry": {"coordinates":[-81.458786,28.484312],"type":"Point"}
}