{
  "type": "Feature",
  "properties": {
    "addr:full":"141 Coconut Dr Indialantic FL 32903",
    "addr:housenumber":"141",
    "addr:postcode":"32903",
    "addr:street":"Coconut Dr",
    "iso:country":"US",
    "sg:address":"141 Coconut Dr",
    "sg:city":"Indialantic",
    "sg:classifiers":[
        {
            "category":"Real Estate",
            "subcategory":"Real Estate Agent",
            "type":"Services"
        }
    ],
    "sg:phone":"+1 321 777 4111",
    "sg:postcode":"32903",
    "sg:province":"FL",
    "sg:tags":[
        "agency"
    ],
    "sg:website":"http://www.realestateofbrevard.com",
    "wof:name":"Re/Max",
    "wof:placetype":"venue"
},
  "geometry": {"coordinates":[-80.57327100000001,28.110945],"type":"Point"}
}