{
  "type": "Feature",
  "properties": {
    "iso:country":"US",
    "sg:address":"45 Homestead Rd S",
    "sg:city":"Lehigh Acres",
    "sg:classifiers":[
        {
            "category":"Recreation",
            "type":"Entertainment"
        }
    ],
    "sg:phone":"+1 239 369 1331",
    "sg:postcode":"33936",
    "sg:province":"FL",
    "sg:tags":[
        "parlor",
        "billiard"
    ],
    "wof:name":"Homestead Inn Bar & Grill",
    "wof:placetype":"venue"
},
  "geometry": {"coordinates":[-81.638137,26.59627],"type":"Point"}
}