{
  "type": "Feature",
  "properties": {
    "iso:country":"US",
    "sg:address":"901 SW Martin Downs Blvd",
    "sg:city":"Palm City",
    "sg:classifiers":[
        {
            "category":"Manufacturing",
            "subcategory":"Electronics",
            "type":"Manufacturing & Wholesale Goods"
        }
    ],
    "sg:phone":"+1 772 221 0744",
    "sg:postcode":"34990",
    "sg:province":"FL",
    "sg:tags":[
        "electronic",
        "component",
        "mfg"
    ],
    "wof:name":"Advanced Circuits",
    "wof:placetype":"venue"
},
  "geometry": {"coordinates":[-80.265246,27.17218],"type":"Point"}
}