{
  "type": "Feature",
  "properties": {
    "iso:country":"US",
    "sg:address":"1118 NE 18th Ave",
    "sg:city":"Fort Lauderdale",
    "sg:classifiers":[
        {
            "category":"Organizations",
            "subcategory":"Community Association",
            "type":"Services"
        }
    ],
    "sg:phone":"+1 954 523 8812",
    "sg:postcode":"33304",
    "sg:province":"FL",
    "wof:name":"Lake Ridge Civic Association",
    "wof:placetype":"venue"
},
  "geometry": {"coordinates":[-80.122157,26.140998],"type":"Point"}
}