{
  "type": "Feature",
  "properties": {
    "iso:country":"US",
    "sg:address":"4910 Tamiami Trl N",
    "sg:city":"Naples",
    "sg:classifiers":[
        {
            "category":"Shopping",
            "subcategory":"Used Merchandise",
            "type":"Retail Goods"
        }
    ],
    "sg:phone":"+1 239 649 7571",
    "sg:postcode":"34103",
    "sg:province":"FL",
    "sg:tags":[
        "business"
    ],
    "wof:name":"Nearly New",
    "wof:placetype":"venue"
},
  "geometry": {"coordinates":[-81.800284,26.207788],"type":"Point"}
}