{
  "type": "Feature",
  "properties": {
    "iso:country":"US",
    "sg:address":"300 SW 136th Ave",
    "sg:city":"Miami",
    "sg:classifiers":[
        {
            "category":"Health Services",
            "subcategory":"Clinic",
            "type":"Services"
        }
    ],
    "sg:phone":"+1 786 295 2604",
    "sg:postcode":"33184",
    "sg:province":"FL",
    "sg:tags":[
        "information",
        "alcoholism",
        "treatment"
    ],
    "wof:name":"Shannnon's Equine Massage Therapy Inc.",
    "wof:placetype":"venue"
},
  "geometry": {"coordinates":[-80.414558,25.764595],"type":"Point"}
}