{
  "type": "Feature",
  "properties": {
    "addr:full":"3300 Rice St Miami FL 33133",
    "addr:housenumber":"3300",
    "addr:postcode":"33133",
    "addr:street":"Rice St",
    "iso:country":"US",
    "sg:address":"3300 Rice St",
    "sg:city":"Miami",
    "sg:classifiers":[
        {
            "category":"Autos & Motor Vehicles",
            "subcategory":"Motorcycle Sales",
            "type":"Retail Goods"
        }
    ],
    "sg:phone":"+1 305 445 1316",
    "sg:postcode":"33133",
    "sg:province":"FL",
    "sg:tags":[
        "scooter"
    ],
    "wof:name":"International Motorcycle Shows",
    "wof:placetype":"venue"
},
  "geometry": {"coordinates":[-80.240511,25.729094],"type":"Point"}
}