{
  "type": "Feature",
  "properties": {
    "iso:country":"US",
    "sg:address":"240 N Lime Ave",
    "sg:city":"Sarasota",
    "sg:classifiers":[
        {
            "category":"Shopping",
            "subcategory":"Department Store",
            "type":"Retail Goods"
        },
        {
            "category":"Shopping",
            "subcategory":"Discount & Variety Stores",
            "type":"Retail Goods"
        }
    ],
    "sg:phone":"+1 941 364 9351",
    "sg:postcode":"34237",
    "sg:province":"FL",
    "sg:tags":[
        "shop"
    ],
    "sg:website":"http://www.familydollar.com",
    "wof:name":"Family Dollar Stores",
    "wof:placetype":"venue"
},
  "geometry": {"coordinates":[-82.524193,27.338777],"type":"Point"}
}