{
  "type": "Feature",
  "properties": {
    "addr:full":"6821 Southpoint Dr N Jacksonville FL 32216",
    "addr:housenumber":"6821",
    "addr:postcode":"32216",
    "addr:street":"Southpoint Dr N",
    "iso:country":"US",
    "sg:address":"6821 Southpoint Dr N",
    "sg:city":"Jacksonville",
    "sg:classifiers":[
        {
            "category":"Real Estate",
            "subcategory":"Real Estate Agent",
            "type":"Services"
        }
    ],
    "sg:phone":"+1 904 281 9105",
    "sg:postcode":"32216",
    "sg:province":"FL",
    "sg:tags":[
        "desk",
        "space"
    ],
    "wof:name":"Southpoint Square I & II",
    "wof:placetype":"venue"
},
  "geometry": {"coordinates":[-81.58667,30.256639],"type":"Point"}
}