{
  "type": "Feature",
  "properties": {
    "addr:full":"6300 NW 114th St Hialeah FL 33012",
    "addr:housenumber":"6300",
    "addr:postcode":"33012",
    "addr:street":"Nw 114Th St",
    "iso:country":"US",
    "sg:address":"6300 NW 114th St",
    "sg:city":"Hialeah",
    "sg:classifiers":[
        {
            "category":"Building & Trades",
            "subcategory":"Electrical",
            "type":"Services"
        }
    ],
    "sg:phone":"+1 786 267 6661",
    "sg:postcode":"33012",
    "sg:province":"FL",
    "sg:tags":[
        "installation"
    ],
    "wof:name":"Manuel Farizo Installation",
    "wof:placetype":"venue"
},
  "geometry": {"coordinates":[-80.30002399999999,25.877027],"type":"Point"}
}