{
  "type": "Feature",
  "properties": {
    "iso:country":"US",
    "sg:address":"17 Winding Creek Way",
    "sg:city":"Ormond Beach",
    "sg:classifiers":[
        {
            "category":"Building & Trades",
            "subcategory":"Landscaping Services",
            "type":"Services"
        }
    ],
    "sg:phone":"+1 386 671 9201",
    "sg:postcode":"32174",
    "sg:province":"FL",
    "wof:name":"Colemans Lawn Service",
    "wof:placetype":"venue"
},
  "geometry": {"coordinates":[-81.13865699999999,29.258972],"type":"Point"}
}