{
  "type": "Feature",
  "properties": {
    "iso:country":"US",
    "sg:address":"4697 Millenia Plaza Way",
    "sg:city":"Orlando",
    "sg:classifiers":[
        {
            "category":"Utilities",
            "subcategory":"Mobile Phone",
            "type":"Services"
        },
        {
            "category":"Shopping",
            "subcategory":"Mobile Phones",
            "type":"Retail Goods"
        }
    ],
    "sg:phone":"+1 407 363 4591",
    "sg:postcode":"32839",
    "sg:province":"FL",
    "sg:tags":[
        "supply",
        "communication",
        "telephone",
        "wireless",
        "equipment",
        "cellular"
    ],
    "wof:name":"Verizon Wireless",
    "wof:placetype":"venue"
},
  "geometry": {"coordinates":[-81.428388,28.494193],"type":"Point"}
}