{
  "type": "Feature",
  "properties": {
    "iso:country":"US",
    "sg:address":"3280 Tamiami Trl",
    "sg:city":"Port Charlotte",
    "sg:classifiers":[
        {
            "category":"Professional",
            "type":"Services"
        }
    ],
    "sg:phone":"+1 941 629 1166",
    "sg:postcode":"33952",
    "sg:province":"FL",
    "sg:tags":[
        "establishment"
    ],
    "wof:name":"Bio-Med",
    "wof:placetype":"venue"
},
  "geometry": {"coordinates":[-82.098383,26.98207],"type":"Point"}
}