{
  "type": "Feature",
  "properties": {
    "iso:country":"US",
    "sg:address":"3477 Silver Star Rd",
    "sg:city":"Orlando",
    "sg:classifiers":[
        {
            "category":"Building & Trades",
            "subcategory":"Plumbing",
            "type":"Services"
        }
    ],
    "sg:phone":"+1 407 241 2041",
    "sg:postcode":"32808",
    "sg:province":"FL",
    "sg:tags":[
        "conditioning",
        "air",
        "system",
        "contractor"
    ],
    "wof:name":"A-1 Heat & Air Conditioning",
    "wof:placetype":"venue"
},
  "geometry": {"coordinates":[-81.4251,28.578164],"type":"Point"}
}