{
  "type": "Feature",
  "properties": {
    "addr:full":"6221 US Hwy 1 Cocoa FL 32927",
    "addr:housenumber":"6221",
    "addr:postcode":"32927",
    "addr:street":"Us Hwy 1",
    "iso:country":"US",
    "sg:address":"6221 US Hwy 1",
    "sg:city":"Cocoa",
    "sg:classifiers":[
        {
            "category":"Shopping",
            "subcategory":"Department Store",
            "type":"Retail Goods"
        }
    ],
    "sg:phone":"+1 321 636 8789",
    "sg:postcode":"32927",
    "sg:province":"FL",
    "sg:tags":[
        "shop"
    ],
    "wof:name":"Family Dollar Store",
    "wof:placetype":"venue"
},
  "geometry": {"coordinates":[-80.766272,28.470161],"type":"Point"}
}