{
  "type": "Feature",
  "properties": {
    "iso:country":"US",
    "sg:address":"321 Deer Cove Ln",
    "sg:city":"Lutz",
    "sg:classifiers":[
        {
            "category":"Organizations",
            "subcategory":"Religious Organization",
            "type":"Services"
        }
    ],
    "sg:phone":"+1 813 949 1912",
    "sg:postcode":"33548",
    "sg:province":"FL",
    "sg:tags":[
        "church"
    ],
    "wof:name":"Trinity Assembly Of God",
    "wof:placetype":"venue"
},
  "geometry": {"coordinates":[-82.463618,28.170702],"type":"Point"}
}