{
  "type": "Feature",
  "properties": {
    "iso:country":"US",
    "sg:address":"8415 SE Palm St",
    "sg:city":"Hobe Sound",
    "sg:classifiers":[
        {
            "category":"Manufacturing",
            "subcategory":"Apparel",
            "type":"Manufacturing & Wholesale Goods"
        }
    ],
    "sg:phone":"+1 772 545 3972",
    "sg:postcode":"33455",
    "sg:province":"FL",
    "sg:tags":[
        "household",
        "furnishing",
        "mfg"
    ],
    "wof:name":"Captains Choice Services Inc",
    "wof:placetype":"venue"
},
  "geometry": {"coordinates":[-80.14026,27.095078],"type":"Point"}
}