{
  "type": "Feature",
  "properties": {
    "iso:country":"US",
    "sg:address":"17718 Crystal Cove Pl",
    "sg:city":"Lutz",
    "sg:classifiers":[
        {
            "category":"Professional",
            "subcategory":"Business Services",
            "type":"Services"
        }
    ],
    "sg:phone":"+1 813 948 7908",
    "sg:postcode":"33548",
    "sg:province":"FL",
    "wof:name":"Devore Inc",
    "wof:placetype":"venue"
},
  "geometry": {"coordinates":[-82.473012,28.131851],"type":"Point"}
}