{
  "type": "Feature",
  "properties": {
    "iso:country":"US",
    "sg:address":"4481 107th Cir N",
    "sg:city":"Clearwater",
    "sg:classifiers":[
        {
            "category":"Manufacturing",
            "subcategory":"Motor Vehicles & Parts",
            "type":"Manufacturing & Wholesale Goods"
        }
    ],
    "sg:phone":"+1 727 572 6319",
    "sg:postcode":"33762",
    "sg:province":"FL",
    "sg:tags":[
        "body",
        "metalwork",
        "sheet",
        "mfg"
    ],
    "sg:website":"www.actionfabrication.com",
    "wof:name":"Action Fabricating",
    "wof:placetype":"venue"
},
  "geometry": {"coordinates":[-82.698876,27.87035],"type":"Point"}
}