{
  "type": "Feature",
  "properties": {
    "iso:country":"US",
    "sg:address":"2275 Pine Ridge Rd",
    "sg:city":"Naples",
    "sg:classifiers":[
        {
            "category":"Home & Garden",
            "subcategory":"Furniture",
            "type":"Retail Goods"
        }
    ],
    "sg:phone":"+1 239 591 4761",
    "sg:postcode":"34109",
    "sg:province":"FL",
    "sg:tags":[
        "mattress"
    ],
    "wof:name":"Mattress Giant",
    "wof:placetype":"venue"
},
  "geometry": {"coordinates":[-81.769217,26.211737],"type":"Point"}
}