{
  "type": "Feature",
  "properties": {
    "iso:country":"US",
    "sg:address":"1239 W Island Club Sq",
    "sg:city":"Vero Beach",
    "sg:classifiers":[
        {
            "category":"Organizations",
            "subcategory":"Community Association",
            "type":"Services"
        }
    ],
    "sg:phone":"+1 772 234 5879",
    "sg:postcode":"32963",
    "sg:province":"FL",
    "sg:tags":[
        "club"
    ],
    "wof:name":"Island Club Riverside Clbhs",
    "wof:placetype":"venue"
},
  "geometry": {"coordinates":[-80.39935,27.74738],"type":"Point"}
}