{
  "type": "Feature",
  "properties": {
    "addr:full":"3125 Heron Lake Dr Kissimmee FL 34741",
    "addr:housenumber":"3125",
    "addr:postcode":"34741",
    "addr:street":"Heron Lake Dr",
    "iso:country":"US",
    "sg:address":"3125 Heron Lake Dr",
    "sg:city":"Kissimmee",
    "sg:classifiers":[
        {
            "category":"Restaurant",
            "type":"Food & Drink"
        }
    ],
    "sg:phone":"+1 407 343 9769",
    "sg:postcode":"34741",
    "sg:province":"FL",
    "sg:tags":[
        "parlor",
        "ice",
        "cream"
    ],
    "wof:name":"Gloria Uribe Ice Cream Van",
    "wof:placetype":"venue"
},
  "geometry": {"coordinates":[-81.433626,28.297747],"type":"Point"}
}