{
  "type": "Feature",
  "properties": {
    "iso:country":"US",
    "sg:address":"5941 NE 19th Ave",
    "sg:city":"Fort Lauderdale",
    "sg:classifiers":[
        {
            "category":"Retail",
            "subcategory":"Portrait Studio",
            "type":"Services"
        }
    ],
    "sg:phone":"+1 954 493 7401",
    "sg:postcode":"33308",
    "sg:province":"FL",
    "sg:tags":[
        "photographer"
    ],
    "wof:name":"Black Tie Photography",
    "wof:placetype":"venue"
},
  "geometry": {"coordinates":[-80.121503,26.203382],"type":"Point"}
}