{
  "type": "Feature",
  "properties": {
    "iso:country":"US",
    "sg:address":"1201 Sexton Dr",
    "sg:city":"Baker",
    "sg:classifiers":[
        {
            "category":"Retail",
            "subcategory":"Animal Services",
            "type":"Services"
        }
    ],
    "sg:phone":"+1 850 537 4885",
    "sg:postcode":"32531",
    "sg:province":"FL",
    "wof:name":"L A Image Pets",
    "wof:placetype":"venue"
},
  "geometry": {"coordinates":[-86.681541,30.840958],"type":"Point"}
}