{
  "type": "Feature",
  "properties": {
    "iso:country":"US",
    "sg:address":"17035 SW 189th Ave",
    "sg:city":"Miami",
    "sg:classifiers":[
        {
            "category":"Home & Garden",
            "subcategory":"Garden Supply",
            "type":"Retail Goods"
        }
    ],
    "sg:phone":"+1 786 293 8212",
    "sg:postcode":"33187",
    "sg:province":"FL",
    "sg:tags":[
        "nurseryman"
    ],
    "wof:name":"Capote Nursery",
    "wof:placetype":"venue"
},
  "geometry": {"coordinates":[-80.49881600000001,25.606371],"type":"Point"}
}