{
  "type": "Feature",
  "properties": {
    "addr:full":"689 W 26th St Hialeah FL 33010",
    "addr:housenumber":"689",
    "addr:postcode":"33010",
    "addr:street":"W 26Th St",
    "iso:country":"US",
    "sg:address":"689 W 26th St",
    "sg:city":"Hialeah",
    "sg:classifiers":[
        {
            "category":"Manufacturing",
            "subcategory":"Textiles",
            "type":"Manufacturing & Wholesale Goods"
        }
    ],
    "sg:phone":"+1 305 883 4990",
    "sg:postcode":"33010",
    "sg:province":"FL",
    "sg:tags":[
        "cloth",
        "cutting"
    ],
    "sg:website":"http://www.josesusi.com",
    "wof:name":"Kutting & Slitting Service Usa",
    "wof:placetype":"venue"
},
  "geometry": {"coordinates":[-80.295311,25.845224],"type":"Point"}
}