{
  "type": "Feature",
  "properties": {
    "iso:country":"US",
    "sg:address":"1000 Lakeview Rd",
    "sg:city":"Clearwater",
    "sg:classifiers":[
        {
            "category":"Health Services",
            "subcategory":"Doctor",
            "type":"Services"
        }
    ],
    "sg:phone":"+1 727 441 9474",
    "sg:postcode":"33756",
    "sg:province":"FL",
    "sg:tags":[
        "physician",
        "family",
        "practice",
        "surgeons",
        "medicine",
        "surgeon"
    ],
    "wof:name":"J Martin Klein Md",
    "wof:placetype":"venue"
},
  "geometry": {"coordinates":[-82.792824,27.949881],"type":"Point"}
}