{
  "type": "Feature",
  "properties": {
    "iso:country":"US",
    "sg:address":"2730 SW 3rd Ave",
    "sg:city":"Miami",
    "sg:classifiers":[
        {
            "category":"Insurance",
            "subcategory":"Insurance Agent",
            "type":"Services"
        }
    ],
    "sg:phone":"+1 305 285 0916",
    "sg:postcode":"33129",
    "sg:province":"FL",
    "wof:name":"Midland National Life Insurance Co",
    "wof:placetype":"venue"
},
  "geometry": {"coordinates":[-80.209414,25.75466],"type":"Point"}
}