{
  "type": "Feature",
  "properties": {
    "iso:country":"US",
    "sg:address":"373 Coconut Cir",
    "sg:city":"Fort Lauderdale",
    "sg:classifiers":[
        {
            "category":"Professional",
            "subcategory":"Management & Consulting",
            "type":"Services"
        }
    ],
    "sg:phone":"+1 954 384 0925",
    "sg:postcode":"33326",
    "sg:province":"FL",
    "sg:tags":[
        "eating",
        "business"
    ],
    "wof:name":"F Z M International",
    "wof:placetype":"venue"
},
  "geometry": {"coordinates":[-80.400532,26.112904],"type":"Point"}
}