{
  "type": "Feature",
  "properties": {
    "iso:country":"US",
    "sg:address":"16782 SW 88 Street",
    "sg:city":"Miami",
    "sg:classifiers":[
        {
            "category":"Insurance",
            "subcategory":"Hazard Insurance",
            "type":"Services"
        },
        {
            "category":"Insurance",
            "subcategory":"Insurance Agent",
            "type":"Services"
        },
        {
            "category":"Insurance",
            "subcategory":"Life Insurance",
            "type":"Services"
        },
        {
            "category":"Insurance",
            "subcategory":"Title Insurance",
            "type":"Services"
        }
    ],
    "sg:phone":"+1 305 385 6696",
    "sg:postcode":"33196",
    "sg:province":"FL",
    "sg:tags":[
        "auto",
        "renter",
        "homeowner"
    ],
    "sg:website":"https://www.jimdiaz.com/",
    "wof:name":"State Farm Insurance Agent - Jim Diaz",
    "wof:placetype":"venue"
},
  "geometry": {"coordinates":[-80.466522,25.683671],"type":"Point"}
}