{
  "type": "Feature",
  "properties": {
    "addr:full":"642 N Auburn Rd Venice FL 34292",
    "addr:housenumber":"642",
    "addr:postcode":"34292",
    "addr:street":"N Auburn Rd",
    "iso:country":"US",
    "sg:address":"642 N Auburn Rd",
    "sg:city":"Venice",
    "sg:classifiers":[
        {
            "category":"Organizations",
            "subcategory":"Religious Organization",
            "type":"Services"
        }
    ],
    "sg:phone":"+1 941 485 3551",
    "sg:postcode":"34292",
    "sg:province":"FL",
    "wof:name":"Auburn Rd Presbt Church-P C A",
    "wof:placetype":"venue"
},
  "geometry": {"coordinates":[-82.40088,27.113967],"type":"Point"}
}