{
  "type": "Feature",
  "properties": {
    "iso:country":"US",
    "sg:address":"231 W Park Ave",
    "sg:city":"Winter Park",
    "sg:classifiers":[
        {
            "category":"Real Estate",
            "subcategory":"Developer",
            "type":"Services"
        }
    ],
    "sg:phone":"+1 407 599 4444",
    "sg:postcode":"32789",
    "sg:province":"FL",
    "wof:name":"Michael Collard Properties",
    "wof:placetype":"venue"
},
  "geometry": {"coordinates":[-81.352253,28.596971],"type":"Point"}
}