{
  "type": "Feature",
  "properties": {
    "addr:full":"13715 Attley Pl Tampa FL 33624",
    "addr:housenumber":"13715",
    "addr:postcode":"33624",
    "addr:street":"Attley Pl",
    "iso:country":"US",
    "sg:address":"13715 Attley Pl",
    "sg:city":"Tampa",
    "sg:classifiers":[
        {
            "category":"Banks & Credit Unions",
            "subcategory":"Financial Services",
            "type":"Services"
        }
    ],
    "sg:phone":"+1 813 962 8766",
    "sg:postcode":"33624",
    "sg:province":"FL",
    "sg:tags":[
        "investor"
    ],
    "wof:name":"S&H Investments of Tampa Inc",
    "wof:placetype":"venue"
},
  "geometry": {"coordinates":[-82.535983,28.07438],"type":"Point"}
}