{
  "type": "Feature",
  "properties": {
    "addr:full":"255 W 3rd St Chuluota FL 32766",
    "addr:housenumber":"255",
    "addr:postcode":"32766",
    "addr:street":"W 3Rd St",
    "iso:country":"US",
    "sg:address":"255 W 3rd St",
    "sg:city":"Chuluota",
    "sg:classifiers":[
        {
            "category":"Professional",
            "type":"Services"
        }
    ],
    "sg:phone":"+1 407 365 7294",
    "sg:postcode":"32766",
    "sg:province":"FL",
    "sg:tags":[
        "establishment"
    ],
    "wof:name":"Enviroscape",
    "wof:placetype":"venue"
},
  "geometry": {"coordinates":[-81.13288300000001,28.643955],"type":"Point"}
}