{
  "type": "Feature",
  "properties": {
    "iso:country":"US",
    "sg:address":"5703 Oakley Blvd",
    "sg:city":"Wesley Chapel",
    "sg:classifiers":[
        {
            "category":"Organizations",
            "subcategory":"Non-profit Organization",
            "type":"Services"
        }
    ],
    "sg:phone":"+1 813 907 7750",
    "sg:postcode":"33544",
    "sg:province":"FL",
    "sg:tags":[
        "disability"
    ],
    "wof:name":"William L Bissi & Assoc",
    "wof:placetype":"venue"
},
  "geometry": {"coordinates":[-82.355261,28.242707],"type":"Point"}
}