{
  "type": "Feature",
  "properties": {
    "addr:full":"162 W Park St Lake Helen FL 32744",
    "addr:housenumber":"162",
    "addr:postcode":"32744",
    "addr:street":"W Park St",
    "iso:country":"US",
    "sg:address":"162 W Park St",
    "sg:city":"Lake Helen",
    "sg:classifiers":[
        {
            "category":"Banks & Credit Unions",
            "subcategory":"Financial Services",
            "type":"Services"
        }
    ],
    "sg:phone":"+1 386 228 3160",
    "sg:postcode":"32744",
    "sg:province":"FL",
    "sg:tags":[
        "trust",
        "management"
    ],
    "wof:name":"Henson Family Trust",
    "wof:placetype":"venue"
},
  "geometry": {"coordinates":[-81.23262,28.980281],"type":"Point"}
}