{
  "type": "Feature",
  "properties": {
    "addr:full":"2601 NW 112th Ave Doral FL 33172",
    "addr:housenumber":"2601",
    "addr:postcode":"33172",
    "addr:street":"Nw 112Th Ave",
    "iso:country":"US",
    "sg:address":"2601 NW 112th Ave",
    "sg:city":"Doral",
    "sg:classifiers":[
        {
            "category":"Education",
            "subcategory":"School",
            "type":"Public Place"
        }
    ],
    "sg:phone":"+1 305 591 0020",
    "sg:postcode":"33172",
    "sg:province":"FL",
    "sg:tags":[
        "middle"
    ],
    "wof:name":"Doral Academy Middle School",
    "wof:placetype":"venue"
},
  "geometry": {"coordinates":[-80.37713599999999,25.797804],"type":"Point"}
}