{
  "type": "Feature",
  "properties": {
    "addr:full":"1815 W State Road 434 Longwood FL 32750",
    "addr:housenumber":"1815",
    "addr:postcode":"32750",
    "addr:street":"W State Road 434",
    "iso:country":"US",
    "sg:address":"1815 W State Road 434",
    "sg:city":"Longwood",
    "sg:classifiers":[
        {
            "category":"Banks & Credit Unions",
            "subcategory":"Financial Services",
            "type":"Services"
        }
    ],
    "sg:phone":"+1 800 454 1148",
    "sg:postcode":"32750",
    "sg:province":"FL",
    "sg:tags":[
        "broker",
        "mortgage"
    ],
    "wof:name":"Countrywide Home Loans Inc",
    "wof:placetype":"venue"
},
  "geometry": {"coordinates":[-81.385403,28.692828],"type":"Point"}
}