{
  "type": "Feature",
  "properties": {
    "iso:country":"US",
    "sg:address":"4848 S Apopka Vineland Rd",
    "sg:city":"Orlando",
    "sg:classifiers":[
        {
            "category":"Personal",
            "subcategory":"Beauty Salon",
            "type":"Services"
        }
    ],
    "sg:phone":"+1 407 876 9138",
    "sg:postcode":"32819",
    "sg:province":"FL",
    "wof:name":"Hair Masters",
    "wof:placetype":"venue"
},
  "geometry": {"coordinates":[-81.50858700000001,28.490345],"type":"Point"}
}