{
  "type": "Feature",
  "properties": {
    "iso:country":"US",
    "sg:address":"142 E Granada Blvd",
    "sg:city":"Ormond Beach",
    "sg:classifiers":[
        {
            "category":"Personal",
            "subcategory":"Beauty Salon",
            "type":"Services"
        }
    ],
    "sg:phone":"+1 386 672 6245",
    "sg:postcode":"32176",
    "sg:province":"FL",
    "sg:tags":[
        "manicuring"
    ],
    "wof:name":"Angelic Nails",
    "wof:placetype":"venue"
},
  "geometry": {"coordinates":[-81.040885,29.291476],"type":"Point"}
}