{
  "type": "Feature",
  "properties": {
    "iso:country":"US",
    "sg:address":"7281 Sunshine Grove Rd",
    "sg:city":"Brooksville",
    "sg:classifiers":[
        {
            "category":"Place Of Worship",
            "subcategory":"Church",
            "type":"Public Place"
        },
        {
            "category":"Place Of Worship",
            "type":"Public Place"
        }
    ],
    "sg:phone":"+1 352 597 7792",
    "sg:postcode":"34613",
    "sg:province":"FL",
    "sg:tags":[
        "churches-interdenominational",
        "denomination",
        "churches-various",
        "churches-non-denominational"
    ],
    "wof:name":"Journey Christian Center",
    "wof:placetype":"venue"
},
  "geometry": {"coordinates":[-82.499903,28.535656],"type":"Point"}
}