{
  "type": "Feature",
  "properties": {
    "iso:country":"US",
    "sg:address":"140 W Palmer Ave",
    "sg:city":"Tallahassee",
    "sg:classifiers":[
        {
            "category":"Real Estate",
            "subcategory":"Real Estate Operator",
            "type":"Services"
        }
    ],
    "sg:phone":"+1 850 575 3300",
    "sg:postcode":"32301",
    "sg:province":"FL",
    "sg:tags":[
        "building",
        "apartment"
    ],
    "wof:name":"Crumps Apts",
    "wof:placetype":"venue"
},
  "geometry": {"coordinates":[-84.283461,30.427183],"type":"Point"}
}