{
  "type": "Feature",
  "properties": {
    "addr:full":"1245 W 69th St Hialeah FL 33014",
    "addr:housenumber":"1245",
    "addr:postcode":"33014",
    "addr:street":"W 69Th St",
    "iso:country":"US",
    "sg:address":"1245 W 69th St",
    "sg:city":"Hialeah",
    "sg:classifiers":[
        {
            "category":"Shopping",
            "subcategory":"Clothing, Apparel, & Fashions",
            "type":"Retail Goods"
        }
    ],
    "sg:phone":"+1 305 557 0808",
    "sg:postcode":"33014",
    "sg:province":"FL",
    "wof:name":"Hydro Fashions",
    "wof:placetype":"venue"
},
  "geometry": {"coordinates":[-80.308751,25.885778],"type":"Point"}
}