{
  "type": "Feature",
  "properties": {
    "addr:full":"5700 International Dr Orlando FL 32819",
    "addr:housenumber":"5700",
    "addr:postcode":"32819",
    "addr:street":"International Dr",
    "iso:country":"US",
    "sg:address":"5700 International Dr",
    "sg:city":"Orlando",
    "sg:classifiers":[
        {
            "category":"Shopping",
            "subcategory":"Gifts & Souvenirs",
            "type":"Retail Goods"
        }
    ],
    "sg:phone":"+1 407 352 5423",
    "sg:postcode":"32819",
    "sg:province":"FL",
    "sg:tags":[
        "shop"
    ],
    "wof:name":"Fisac Enterprises Inc",
    "wof:placetype":"venue"
},
  "geometry": {"coordinates":[-81.457674,28.462262],"type":"Point"}
}