{
  "type": "Feature",
  "properties": {
    "iso:country":"US",
    "sg:address":"2501 SE Calusa Ave",
    "sg:city":"Port Saint Lucie",
    "sg:classifiers":[
        {
            "category":"Building & Trades",
            "subcategory":"Electrical",
            "type":"Services"
        }
    ],
    "sg:phone":"+1 772 337 4197",
    "sg:postcode":"34952",
    "sg:province":"FL",
    "sg:tags":[
        "electrical",
        "contractor"
    ],
    "wof:name":"Payuk Electric",
    "wof:placetype":"venue"
},
  "geometry": {"coordinates":[-80.276056,27.276387],"type":"Point"}
}