{
  "type": "Feature",
  "properties": {
    "iso:country":"US",
    "sg:address":"132 N Beach St",
    "sg:city":"Daytona Beach",
    "sg:classifiers":[
        {
            "category":"Restaurant",
            "type":"Food & Drink"
        }
    ],
    "sg:phone":"+1 386 253 1133",
    "sg:postcode":"32114",
    "sg:province":"FL",
    "wof:name":"Song Mongolian Grill",
    "wof:placetype":"venue"
},
  "geometry": {"coordinates":[-81.01949399999999,29.212297],"type":"Point"}
}