{
  "type": "Feature",
  "properties": {
    "iso:country":"US",
    "sg:address":"4754 SW 74th Ave",
    "sg:city":"Miami",
    "sg:classifiers":[
        {
            "category":"Wholesale",
            "subcategory":"Sporting Goods",
            "type":"Manufacturing & Wholesale Goods"
        },
        {
            "category":"Building & Trades",
            "subcategory":"Construction",
            "type":"Services"
        }
    ],
    "sg:phone":"+1 305 265 7400",
    "sg:postcode":"33155",
    "sg:province":"FL",
    "sg:tags":[
        "designer",
        "supply",
        "spa",
        "dealer",
        "pool",
        "swimming"
    ],
    "wof:name":"Gables Pool & Spa Supply Inc",
    "wof:placetype":"venue"
},
  "geometry": {"coordinates":[-80.314848,25.726707],"type":"Point"}
}