{
  "type": "Feature",
  "properties": {
    "iso:country":"US",
    "sg:address":"2251 Alexander Dr",
    "sg:city":"Titusville",
    "sg:classifiers":[
        {
            "category":"Bars & Pubs",
            "type":"Food & Drink"
        }
    ],
    "sg:phone":"+1 321 267 4288",
    "sg:postcode":"32796",
    "sg:province":"FL",
    "sg:tags":[
        "drinking"
    ],
    "wof:name":"Rei-TEC Lounge",
    "wof:placetype":"venue"
},
  "geometry": {"coordinates":[-80.850329,28.589047],"type":"Point"}
}