{
  "type": "Feature",
  "properties": {
    "addr:full":"8408 Bayshore Rd Palmetto FL 34221",
    "addr:housenumber":"8408",
    "addr:postcode":"34221",
    "addr:street":"Bayshore Rd",
    "iso:country":"US",
    "sg:address":"8408 Bayshore Rd",
    "sg:city":"Palmetto",
    "sg:classifiers":[
        {
            "category":"Shopping",
            "subcategory":"Computers & Home Electronics",
            "type":"Retail Goods"
        }
    ],
    "sg:phone":"+1 941 722 8346",
    "sg:postcode":"34221",
    "sg:province":"FL",
    "sg:tags":[
        "sound",
        "equipment",
        "system"
    ],
    "wof:name":"Flash Point Productions",
    "wof:placetype":"venue"
},
  "geometry": {"coordinates":[-82.54583,27.589957],"type":"Point"}
}