{
  "type": "Feature",
  "properties": {
    "iso:country":"US",
    "sg:address":"802 NE 39th St",
    "sg:city":"Fort Lauderdale",
    "sg:classifiers":[
        {
            "category":"Professional",
            "subcategory":"Detective & Security Services",
            "type":"Services"
        }
    ],
    "sg:phone":"+1 954 565 5936",
    "sg:postcode":"33334",
    "sg:province":"FL",
    "sg:tags":[
        "system"
    ],
    "wof:name":"A Alarm Company",
    "wof:placetype":"venue"
},
  "geometry": {"coordinates":[-80.13451000000001,26.174882],"type":"Point"}
}