{
  "type": "Feature",
  "properties": {
    "iso:country":"US",
    "sg:address":"20533 Biscayne Blvd",
    "sg:city":"Miami",
    "sg:classifiers":[
        {
            "category":"Travel",
            "subcategory":"Travel Agent",
            "type":"Entertainment"
        }
    ],
    "sg:phone":"+1 954 454 8040",
    "sg:postcode":"33180",
    "sg:province":"FL",
    "sg:tags":[
        "cruise"
    ],
    "wof:name":"A J Tours & Cruises",
    "wof:placetype":"venue"
},
  "geometry": {"coordinates":[-80.145946,25.966192],"type":"Point"}
}