{
  "type": "Feature",
  "properties": {
    "addr:full":"700 John Ringling Blvd Sarasota FL 34236",
    "addr:housenumber":"700",
    "addr:postcode":"34236",
    "addr:street":"John Ringling Blvd",
    "iso:country":"US",
    "sg:address":"700 John Ringling Blvd",
    "sg:city":"Sarasota",
    "sg:classifiers":[
        {
            "category":"Professional",
            "type":"Services"
        }
    ],
    "sg:phone":"+1 941 361 7189",
    "sg:postcode":"34236",
    "sg:province":"FL",
    "sg:tags":[
        "establishment"
    ],
    "wof:name":"Elkind & Elkind",
    "wof:placetype":"venue"
},
  "geometry": {"coordinates":[-82.56811999999999,27.323245],"type":"Point"}
}