{
  "type": "Feature",
  "properties": {
    "iso:country":"US",
    "sg:address":"8000 SW 67th Ave",
    "sg:city":"Miami",
    "sg:classifiers":[
        {
            "category":"Health Services",
            "subcategory":"Medical Lab",
            "type":"Services"
        }
    ],
    "sg:phone":"+1 305 666 9656",
    "sg:postcode":"33143",
    "sg:province":"FL",
    "sg:tags":[
        "laboratory"
    ],
    "wof:name":"Miami-Dade Patients Diagnostic",
    "wof:placetype":"venue"
},
  "geometry": {"coordinates":[-80.301101,25.695446],"type":"Point"}
}