{
  "type": "Feature",
  "properties": {
    "iso:country":"US",
    "sg:address":"53 Ave C",
    "sg:city":"Apalachicola",
    "sg:classifiers":[
        {
            "category":"Professional",
            "subcategory":"Lawyer & Legal Services",
            "type":"Services"
        }
    ],
    "sg:phone":"+1 850 653 9392",
    "sg:postcode":"32320",
    "sg:province":"FL",
    "sg:tags":[
        "attorney"
    ],
    "wof:name":"Sytsma Law Office",
    "wof:placetype":"venue"
},
  "geometry": {"coordinates":[-84.98353899999999,29.7257],"type":"Point"}
}