{
  "type": "Feature",
  "properties": {
    "iso:country":"US",
    "sg:address":"1403 W US Hwy 98",
    "sg:city":"Perry",
    "sg:classifiers":[
        {
            "category":"Retail",
            "subcategory":"Self-service Laundry",
            "type":"Services"
        }
    ],
    "sg:phone":"+1 850 584 7884",
    "sg:postcode":"32347",
    "sg:province":"FL",
    "sg:tags":[
        "coin"
    ],
    "wof:name":"Wyllie's Super Wash",
    "wof:placetype":"venue"
},
  "geometry": {"coordinates":[-83.600973,30.107468],"type":"Point"}
}