{
  "type": "Feature",
  "properties": {
    "addr:full":"3581 Palm Valley Cir Oviedo FL 32765",
    "addr:housenumber":"3581",
    "addr:postcode":"32765",
    "addr:street":"Palm Valley Cir",
    "iso:country":"US",
    "sg:address":"3581 Palm Valley Cir",
    "sg:city":"Oviedo",
    "sg:classifiers":[
        {
            "category":"Manufacturing",
            "subcategory":"Textiles",
            "type":"Manufacturing & Wholesale Goods"
        }
    ],
    "sg:phone":"+1 407 977 5968",
    "sg:postcode":"32765",
    "sg:province":"FL",
    "sg:tags":[
        "mill",
        "knit",
        "outerwear"
    ],
    "wof:name":"Tranquility Farms",
    "wof:placetype":"venue"
},
  "geometry": {"coordinates":[-81.19768999999999,28.619607],"type":"Point"}
}