{
  "type": "Feature",
  "properties": {
    "iso:country":"US",
    "sg:address":"1850 San Marco Rd",
    "sg:city":"Marco Island",
    "sg:classifiers":[
        {
            "category":"Shopping",
            "type":"Retail Goods"
        },
        {
            "category":"Wholesale",
            "subcategory":"Electrical",
            "type":"Manufacturing & Wholesale Goods"
        }
    ],
    "sg:phone":"+1 239 642 6661",
    "sg:postcode":"34145",
    "sg:province":"FL",
    "sg:tags":[
        "alarm",
        "burglar",
        "system",
        "install"
    ],
    "wof:name":"Alarms By Bell Inc",
    "wof:placetype":"venue"
},
  "geometry": {"coordinates":[-81.696714,25.935387],"type":"Point"}
}