{
  "type": "Feature",
  "properties": {
    "addr:full":"11173 SW 112th Ter Miami FL 33176",
    "addr:housenumber":"11173",
    "addr:postcode":"33176",
    "addr:street":"Sw 112Th Ter",
    "iso:country":"US",
    "sg:address":"11173 SW 112th Ter",
    "sg:city":"Miami",
    "sg:classifiers":[
        {
            "category":"Building & Trades",
            "subcategory":"Cleaning & Sanitation",
            "type":"Services"
        }
    ],
    "sg:phone":"+1 305 971 8429",
    "sg:postcode":"33176",
    "sg:province":"FL",
    "sg:tags":[
        "window"
    ],
    "wof:name":"Crystal Window Svc",
    "wof:placetype":"venue"
},
  "geometry": {"coordinates":[-80.374478,25.664263],"type":"Point"}
}