{
  "type": "Feature",
  "properties": {
    "addr:full":"1930 West Flagler St Miami FL 33135",
    "addr:housenumber":"1930",
    "addr:postcode":"33135",
    "addr:street":"West Flagler St",
    "iso:country":"US",
    "sg:address":"1930 West Flagler St",
    "sg:city":"Miami",
    "sg:classifiers":[
        {
            "category":"Shopping",
            "subcategory":"Party Supplies",
            "type":"Retail Goods"
        }
    ],
    "sg:phone":"+1 305 649 8558",
    "sg:postcode":"33135",
    "sg:province":"FL",
    "sg:website":"www.partyfiestarentals.com",
    "wof:name":"Party Fiesta Rental",
    "wof:placetype":"venue"
},
  "geometry": {"coordinates":[-80.227543,25.77235],"type":"Point"}
}