{
  "type": "Feature",
  "properties": {
    "addr:full":"3738 Land O Lakes Blvd Land O Lakes FL 34639",
    "addr:housenumber":"3738",
    "addr:postcode":"34639",
    "addr:street":"Land O Lakes Blvd Land",
    "iso:country":"US",
    "sg:address":"3738 Land O Lakes Blvd",
    "sg:city":"Land O Lakes",
    "sg:classifiers":[
        {
            "category":"Building & Trades",
            "subcategory":"Construction",
            "type":"Services"
        }
    ],
    "sg:phone":"+1 813 995 9330",
    "sg:postcode":"34639",
    "sg:province":"FL",
    "sg:tags":[
        "home",
        "improvement"
    ],
    "wof:name":"Tradesman Home Improvement",
    "wof:placetype":"venue"
},
  "geometry": {"coordinates":[-82.461583,28.210906],"type":"Point"}
}