{
  "type": "Feature",
  "properties": {
    "iso:country":"US",
    "sg:address":"1842 Needham Rd",
    "sg:city":"Apopka",
    "sg:classifiers":[
        {
            "category":"Wholesale",
            "subcategory":"Hardware",
            "type":"Manufacturing & Wholesale Goods"
        }
    ],
    "sg:phone":"+1 407 889 3605",
    "sg:postcode":"32712",
    "sg:province":"FL",
    "sg:tags":[
        "purifying",
        "cleaning",
        "air"
    ],
    "wof:name":"Breathe Easy Products",
    "wof:placetype":"venue"
},
  "geometry": {"coordinates":[-81.52670500000001,28.712542],"type":"Point"}
}