{
  "type": "Feature",
  "properties": {
    "iso:country":"US",
    "sg:address":"11423 Satellite Blvd",
    "sg:city":"Orlando",
    "sg:classifiers":[
        {
            "category":"Wholesale",
            "subcategory":"Painting Supplies",
            "type":"Manufacturing & Wholesale Goods"
        }
    ],
    "sg:phone":"+1 407 857 6000",
    "sg:postcode":"32837",
    "sg:province":"FL",
    "sg:tags":[
        "goods-wholesale",
        "art",
        "manufacturer"
    ],
    "wof:name":"Art & Frame Direct Inc",
    "wof:placetype":"venue"
},
  "geometry": {"coordinates":[-81.401512,28.400583],"type":"Point"}
}