{
  "type": "Feature",
  "properties": {
    "addr:full":"919 Creech Rd Naples FL 34103",
    "addr:housenumber":"919",
    "addr:postcode":"34103",
    "addr:street":"Creech Rd",
    "iso:country":"US",
    "sg:address":"919 Creech Rd",
    "sg:city":"Naples",
    "sg:classifiers":[
        {
            "category":"Retail",
            "subcategory":"Laundry & Dry Cleaning",
            "type":"Services"
        }
    ],
    "sg:phone":"+1 239 261 7717",
    "sg:postcode":"34103",
    "sg:province":"FL",
    "wof:name":"Creech Road Laundry Inc",
    "wof:placetype":"venue"
},
  "geometry": {"coordinates":[-81.798427,26.182075],"type":"Point"}
}