{
  "type": "Feature",
  "properties": {
    "addr:full":"20 S 2nd St Fernandina Beach FL 32034",
    "addr:housenumber":"20",
    "addr:postcode":"32034",
    "addr:street":"S 2Nd St",
    "iso:country":"US",
    "sg:address":"20 S 2nd St",
    "sg:city":"Fernandina Beach",
    "sg:classifiers":[
        {
            "category":"Restaurant",
            "type":"Food & Drink"
        }
    ],
    "sg:menulink":"http://www.allmenus.com/fl/fernandina-beach/38242-le-clos/menu/",
    "sg:phone":"+1 904 261 8100",
    "sg:postcode":"32034",
    "sg:province":"FL",
    "sg:tags":[
        "american"
    ],
    "wof:name":"Le Clos",
    "wof:placetype":"venue"
},
  "geometry": {"coordinates":[-81.463972,30.67102],"type":"Point"}
}