{
  "type": "Feature",
  "properties": {
    "addr:full":"909 N Fort Harrison Ave Clearwater FL 33755",
    "addr:housenumber":"909",
    "addr:postcode":"33755",
    "addr:street":"N Fort Harrison Ave",
    "iso:country":"US",
    "sg:address":"909 N Fort Harrison Ave",
    "sg:city":"Clearwater",
    "sg:classifiers":[
        {
            "category":"Health Services",
            "subcategory":"Optometrist",
            "type":"Services"
        }
    ],
    "sg:phone":"+1 727 461 2020",
    "sg:postcode":"33755",
    "sg:province":"FL",
    "wof:name":"Gilbert G Jannelli Od",
    "wof:placetype":"venue"
},
  "geometry": {"coordinates":[-82.79862,27.975626],"type":"Point"}
}