{
  "type": "Feature",
  "properties": {
    "addr:full":"1638 Debonair Dr Holiday FL 34690",
    "addr:housenumber":"1638",
    "addr:postcode":"34690",
    "addr:street":"Debonair Dr",
    "iso:country":"US",
    "sg:address":"1638 Debonair Dr",
    "sg:city":"Holiday",
    "sg:classifiers":[
        {
            "category":"Freight",
            "type":"Transportation"
        }
    ],
    "sg:phone":"+1 727 938 2017",
    "sg:postcode":"34690",
    "sg:province":"FL",
    "sg:tags":[
        "hauling",
        "trucking"
    ],
    "wof:name":"Richard Humphrey Hauling",
    "wof:placetype":"venue"
},
  "geometry": {"coordinates":[-82.726232,28.183346],"type":"Point"}
}