{
  "type": "Feature",
  "properties": {
    "iso:country":"US",
    "sg:address":"3731 Wilder Rd",
    "sg:city":"Cantonment",
    "sg:classifiers":[
        {
            "category":"Manufacturing",
            "subcategory":"Signs",
            "type":"Manufacturing & Wholesale Goods"
        }
    ],
    "sg:phone":"+1 850 587 2980",
    "sg:postcode":"32533",
    "sg:province":"FL",
    "sg:tags":[
        "specialty",
        "mfg"
    ],
    "wof:name":"Wood Grain Signs",
    "wof:placetype":"venue"
},
  "geometry": {"coordinates":[-87.355602,30.674183],"type":"Point"}
}