{
  "type": "Feature",
  "properties": {
    "iso:country":"US",
    "sg:address":"5001 N 12th Ave",
    "sg:city":"Pensacola",
    "sg:classifiers":[
        {
            "category":"Animal Shelter",
            "type":"Public Place"
        },
        {
            "category":"Retail",
            "subcategory":"Veterinary Services",
            "type":"Services"
        },
        {
            "category":"Retail",
            "subcategory":"Pet Boarding",
            "type":"Services"
        }
    ],
    "sg:phone":"+1 888 676 0388",
    "sg:postcode":"32504",
    "sg:province":"FL",
    "sg:tags":[
        "hospital",
        "laboratories-veterinary",
        "clinic",
        "veterinarian",
        "kennel"
    ],
    "sg:website":"http://local.ingenio.com/Listings/Details.aspx?NUM=a%3a9243442%3a13%3a4859924%3a14%3a0%3a7",
    "wof:name":"Animal Hospital of Pensacola",
    "wof:placetype":"venue"
},
  "geometry": {"coordinates":[-87.20182800000001,30.469839],"type":"Point"}
}