{
  "type": "Feature",
  "properties": {
    "iso:country":"US",
    "sg:address":"1155 E Atlantic Ave",
    "sg:city":"Delray Beach",
    "sg:classifiers":[
        {
            "category":"Restaurant",
            "type":"Food & Drink"
        }
    ],
    "sg:phone":"+1 561 272 3112",
    "sg:postcode":"33483",
    "sg:province":"FL",
    "sg:tags":[
        "eating"
    ],
    "wof:name":"Rosato Inc",
    "wof:placetype":"venue"
},
  "geometry": {"coordinates":[-80.059969,26.461763],"type":"Point"}
}