{
  "type": "Feature",
  "properties": {
    "addr:full":"242 Tampa Ave W Venice FL 34285",
    "addr:housenumber":"242",
    "addr:postcode":"34285",
    "addr:street":"Tampa Ave W",
    "iso:country":"US",
    "sg:address":"242 Tampa Ave W",
    "sg:city":"Venice",
    "sg:classifiers":[
        {
            "category":"Real Estate",
            "subcategory":"Real Estate Services",
            "type":"Services"
        },
        {
            "category":"Real Estate",
            "subcategory":"Real Estate Agent",
            "type":"Services"
        }
    ],
    "sg:phone":"+1 941 488 6262",
    "sg:postcode":"34285",
    "sg:province":"FL",
    "sg:tags":[
        "buyer",
        "broker"
    ],
    "wof:name":"Gae Stewart Inc",
    "wof:placetype":"venue"
},
  "geometry": {"coordinates":[-82.44655899999999,27.100811],"type":"Point"}
}