{
  "type": "Feature",
  "properties": {
    "iso:country":"US",
    "sg:address":"730 N 5th St",
    "sg:city":"Lantana",
    "sg:classifiers":[
        {
            "category":"Building & Trades",
            "subcategory":"Construction",
            "type":"Services"
        }
    ],
    "sg:phone":"+1 561 585 4457",
    "sg:postcode":"33462",
    "sg:province":"FL",
    "sg:tags":[
        "painter"
    ],
    "wof:name":"Action Painting & Waterproofng",
    "wof:placetype":"venue"
},
  "geometry": {"coordinates":[-80.055187,26.590086],"type":"Point"}
}