{
  "type": "Feature",
  "properties": {
    "iso:country":"US",
    "sg:address":"8525 111th St Apt 107",
    "sg:city":"Seminole",
    "sg:classifiers":[
        {
            "category":"Real Estate",
            "subcategory":"Developer",
            "type":"Services"
        }
    ],
    "sg:phone":"+1 727 393 8334",
    "sg:postcode":"33772",
    "sg:province":"FL",
    "wof:name":"Patomic Enterprises",
    "wof:placetype":"venue"
},
  "geometry": {"coordinates":[-82.792528,27.849441],"type":"Point"}
}