{
  "type": "Feature",
  "properties": {
    "addr:full":"6239 Lake Worth Rd Greenacres FL 33463",
    "addr:housenumber":"6239",
    "addr:postcode":"33463",
    "addr:street":"Lake Worth Rd",
    "iso:country":"US",
    "sg:address":"6239 Lake Worth Rd",
    "sg:city":"Greenacres",
    "sg:classifiers":[
        {
            "category":"Restaurant",
            "type":"Food & Drink"
        }
    ],
    "sg:phone":"+1 561 967 7529",
    "sg:postcode":"33463",
    "sg:province":"FL",
    "wof:name":"Checkers Drive-In Restaurant",
    "wof:placetype":"venue"
},
  "geometry": {"coordinates":[-80.14359399999999,26.619364],"type":"Point"}
}