{
  "type": "Feature",
  "properties": {
    "iso:country":"US",
    "sg:address":"4269 S Atlantic Ave",
    "sg:city":"Port Orange",
    "sg:classifiers":[
        {
            "category":"Professional",
            "subcategory":"Business Services",
            "type":"Services"
        }
    ],
    "sg:phone":"+1 386 760 6809",
    "sg:postcode":"32127",
    "sg:province":"FL",
    "sg:tags":[
        "lecture",
        "bureau",
        "seminar"
    ],
    "wof:name":"Kingdom Communications",
    "wof:placetype":"venue"
},
  "geometry": {"coordinates":[-80.953414,29.123977],"type":"Point"}
}