{
  "type": "Feature",
  "properties": {
    "addr:full":"41 SW 67th Ave Miami FL 33144",
    "addr:housenumber":"41",
    "addr:postcode":"33144",
    "addr:street":"Sw 67Th Ave",
    "iso:country":"US",
    "sg:address":"41 SW 67th Ave",
    "sg:city":"Miami",
    "sg:classifiers":[
        {
            "category":"Retail",
            "subcategory":"Auto Repair",
            "type":"Services"
        }
    ],
    "sg:phone":"+1 305 262 0120",
    "sg:postcode":"33144",
    "sg:province":"FL",
    "sg:tags":[
        "automotive"
    ],
    "wof:name":"Morejon Towing",
    "wof:placetype":"venue"
},
  "geometry": {"coordinates":[-80.304056,25.769029],"type":"Point"}
}