{
  "type": "Feature",
  "properties": {
    "addr:full":"205 E Nasa Blvd Melbourne FL 32901",
    "addr:housenumber":"205",
    "addr:postcode":"32901",
    "addr:street":"E Nasa Blvd",
    "iso:country":"US",
    "sg:address":"205 E Nasa Blvd",
    "sg:city":"Melbourne",
    "sg:classifiers":[
        {
            "category":"Shopping",
            "type":"Retail Goods"
        }
    ],
    "sg:phone":"+1 321 953 2143",
    "sg:postcode":"32901",
    "sg:province":"FL",
    "sg:tags":[
        "limb",
        "artificial"
    ],
    "wof:name":"Hanger Prosthetics & Orthotics",
    "wof:placetype":"venue"
},
  "geometry": {"coordinates":[-80.61533799999999,28.092928],"type":"Point"}
}