{
  "type": "Feature",
  "properties": {
    "addr:full":"470 E McNab Rd Pompano Beach FL 33060",
    "addr:housenumber":"470",
    "addr:postcode":"33060",
    "addr:street":"E Mcnab Rd",
    "iso:country":"US",
    "sg:address":"470 E McNab Rd",
    "sg:city":"Pompano Beach",
    "sg:classifiers":[
        {
            "category":"Shopping",
            "type":"Retail Goods"
        }
    ],
    "sg:phone":"+1 954 652 9166",
    "sg:postcode":"33060",
    "sg:province":"FL",
    "sg:tags":[
        "awning",
        "canopy"
    ],
    "wof:name":"Royal Awnings & Canvass",
    "wof:placetype":"venue"
},
  "geometry": {"coordinates":[-80.116518,26.211293],"type":"Point"}
}