{
  "type": "Feature",
  "properties": {
    "iso:country":"US",
    "sg:address":"7940 Glades Rd",
    "sg:city":"Boca Raton",
    "sg:classifiers":[
        {
            "category":"Restaurant",
            "type":"Food & Drink"
        }
    ],
    "sg:menulink":"http://www.allmenus.com/fl/boca-raton/24258-petes-boca-raton/menu/",
    "sg:phone":"+1 561 487 1600",
    "sg:postcode":"33434",
    "sg:province":"FL",
    "sg:tags":[
        "american"
    ],
    "wof:name":"Pete's Boca Raton",
    "wof:placetype":"venue"
},
  "geometry": {"coordinates":[-80.170098,26.367833],"type":"Point"}
}