{
  "type": "Feature",
  "properties": {
    "addr:full":"511 Astoria Dr De Land FL 32724",
    "addr:housenumber":"511",
    "addr:postcode":"32724",
    "addr:street":"Astoria Dr",
    "iso:country":"US",
    "sg:address":"511 Astoria Dr",
    "sg:city":"De Land",
    "sg:classifiers":[
        {
            "category":"Building & Trades",
            "subcategory":"Construction",
            "type":"Services"
        }
    ],
    "sg:phone":"+1 386 740 9089",
    "sg:postcode":"32724",
    "sg:province":"FL",
    "sg:tags":[
        "concrete",
        "contractor"
    ],
    "wof:name":"Concrete Solutions & Design LL",
    "wof:placetype":"venue"
},
  "geometry": {"coordinates":[-81.27817899999999,29.03681],"type":"Point"}
}