{
  "type": "Feature",
  "properties": {
    "addr:full":"962 8th Ave Graceville FL 32440",
    "addr:housenumber":"962",
    "addr:postcode":"32440",
    "addr:street":"8Th Ave",
    "iso:country":"US",
    "sg:address":"962 8th Ave",
    "sg:city":"Graceville",
    "sg:classifiers":[
        {
            "category":"Autos & Motor Vehicles",
            "subcategory":"Automobile Sales",
            "type":"Retail Goods"
        }
    ],
    "sg:phone":"+1 850 263 9955",
    "sg:postcode":"32440",
    "sg:province":"FL",
    "sg:tags":[
        "dealers-used",
        "car",
        "used",
        "cars-wholesale",
        "new"
    ],
    "wof:name":"Tommy Thomas Chevrolet-Cadillac Used Cars",
    "wof:placetype":"venue"
},
  "geometry": {"coordinates":[-85.51720299999999,30.957236],"type":"Point"}
}