{
  "type": "Feature",
  "properties": {
    "addr:full":"404 Webber Ct Babson Park FL 33827",
    "addr:housenumber":"404",
    "addr:postcode":"33827",
    "addr:street":"Webber Ct",
    "iso:country":"US",
    "sg:address":"404 Webber Ct",
    "sg:city":"Babson Park",
    "sg:classifiers":[
        {
            "category":"Shopping",
            "subcategory":"Gifts & Souvenirs",
            "type":"Retail Goods"
        }
    ],
    "sg:phone":"+1 863 528 5245",
    "sg:postcode":"33827",
    "sg:province":"FL",
    "wof:name":"Blessngs Gfts Baskets Apparell",
    "wof:placetype":"venue"
},
  "geometry": {"coordinates":[-81.53855900000001,27.845795],"type":"Point"}
}