{
  "type": "Feature",
  "properties": {
    "addr:full":"560 Blanding Blvd Orange Park FL 32073",
    "addr:housenumber":"560",
    "addr:postcode":"32073",
    "addr:street":"Blanding Blvd",
    "iso:country":"US",
    "sg:address":"560 Blanding Blvd",
    "sg:city":"Orange Park",
    "sg:classifiers":[
        {
            "category":"Wholesale",
            "subcategory":"Toys & Hobbies",
            "type":"Manufacturing & Wholesale Goods"
        }
    ],
    "sg:phone":"+1 904 272 4900",
    "sg:postcode":"32073",
    "sg:province":"FL",
    "sg:tags":[
        "wholesaler"
    ],
    "wof:name":"Bj's Wholesale Club",
    "wof:placetype":"venue"
},
  "geometry": {"coordinates":[-81.74813899999999,30.15455],"type":"Point"}
}