{
  "type": "Feature",
  "properties": {
    "addr:full":"16823 E Point Dr Summerland Key FL 33042",
    "addr:housenumber":"16823",
    "addr:postcode":"33042",
    "addr:street":"E Point Dr",
    "iso:country":"US",
    "sg:address":"16823 E Point Dr",
    "sg:city":"Summerland Key",
    "sg:classifiers":[
        {
            "category":"Arts & Performance",
            "subcategory":"Theater",
            "type":"Entertainment"
        }
    ],
    "sg:phone":"+1 305 745 1409",
    "sg:postcode":"33042",
    "sg:province":"FL",
    "sg:tags":[
        "theatrical"
    ],
    "wof:name":"Island Opera Theatre of FL",
    "wof:placetype":"venue"
},
  "geometry": {"coordinates":[-81.565561,24.636824],"type":"Point"}
}