{
  "type": "Feature",
  "properties": {
    "iso:country":"US",
    "sg:address":"2853 Ringwood Meadows",
    "sg:city":"Sarasota",
    "sg:classifiers":[
        {
            "category":"Banks & Credit Unions",
            "subcategory":"Investment Brokerage",
            "type":"Services"
        }
    ],
    "sg:phone":"+1 941 371 4833",
    "sg:postcode":"34235",
    "sg:province":"FL",
    "sg:tags":[
        "security"
    ],
    "wof:name":"M & M Associates Inc",
    "wof:placetype":"venue"
},
  "geometry": {"coordinates":[-82.470142,27.36408],"type":"Point"}
}