{
  "type": "Feature",
  "properties": {
    "iso:country":"US",
    "sg:address":"3272 SE Monte Vista St",
    "sg:city":"Port St Lucie",
    "sg:classifiers":[
        {
            "category":"Personal",
            "type":"Services"
        }
    ],
    "sg:phone":"+1 772 873 0503",
    "sg:postcode":"34952",
    "sg:province":"FL",
    "sg:tags":[
        "therapist",
        "massage"
    ],
    "wof:name":"Laurel Gordon Massage Therapy",
    "wof:placetype":"venue"
},
  "geometry": {"coordinates":[-80.310464,27.247165],"type":"Point"}
}