{
  "type": "Feature",
  "properties": {
    "addr:full":"139 NW 3rd St Boca Raton FL 33432",
    "addr:housenumber":"139",
    "addr:postcode":"33432",
    "addr:street":"Nw 3Rd St",
    "iso:country":"US",
    "sg:address":"139 NW 3rd St",
    "sg:city":"Boca Raton",
    "sg:classifiers":[
        {
            "category":"Manufacturing",
            "subcategory":"Printing",
            "type":"Manufacturing & Wholesale Goods"
        }
    ],
    "sg:phone":"+1 561 391 2229",
    "sg:postcode":"33432",
    "sg:province":"FL",
    "sg:tags":[
        "print",
        "printer",
        "lithographic",
        "typesetting"
    ],
    "sg:website":"www.bocacolorgraphics.com",
    "wof:name":"Boca Color Graphics Inc",
    "wof:placetype":"venue"
},
  "geometry": {"coordinates":[-80.089114,26.353139],"type":"Point"}
}