{
  "type": "Feature",
  "properties": {
    "iso:country":"US",
    "sg:address":"41020 Clay Gully Rd",
    "sg:city":"Myakka City",
    "sg:classifiers":[
        {
            "category":"Building & Trades",
            "subcategory":"Landscaping Services",
            "type":"Services"
        }
    ],
    "sg:phone":"+1 941 322 0897",
    "sg:postcode":"34251",
    "sg:province":"FL",
    "sg:tags":[
        "tree"
    ],
    "wof:name":"Treesmith Inc",
    "wof:placetype":"venue"
},
  "geometry": {"coordinates":[-82.144823,27.273558],"type":"Point"}
}