{
  "type": "Feature",
  "properties": {
    "iso:country":"US",
    "sg:address":"6281 104th Ave",
    "sg:city":"Pinellas Park",
    "sg:classifiers":[
        {
            "category":"Building & Trades",
            "subcategory":"Landscaping Services",
            "type":"Services"
        }
    ],
    "sg:phone":"+1 727 525 8622",
    "sg:postcode":"33782",
    "sg:province":"FL",
    "sg:tags":[
        "lawn",
        "garden"
    ],
    "wof:name":"Clean Cut Lawn Care",
    "wof:placetype":"venue"
},
  "geometry": {"coordinates":[-82.721988,27.866608],"type":"Point"}
}