{
  "type": "Feature",
  "properties": {
    "iso:country":"US",
    "sg:address":"304 E Lansdowne Ave",
    "sg:city":"Orange City",
    "sg:classifiers":[
        {
            "category":"Building & Trades",
            "subcategory":"Electrical",
            "type":"Services"
        }
    ],
    "sg:phone":"+1 386 774 7770",
    "sg:postcode":"32763",
    "sg:province":"FL",
    "sg:tags":[
        "electrical",
        "contractor"
    ],
    "wof:name":"Quality Electric of Centl Fla",
    "wof:placetype":"venue"
},
  "geometry": {"coordinates":[-81.296511,28.955768],"type":"Point"}
}