{
  "type": "Feature",
  "properties": {
    "addr:full":"25105 Northlake Dr Sanford FL 32773",
    "addr:postcode":"25105;32773",
    "addr:street":"Northlake Dr",
    "iso:country":"US",
    "sg:address":"25105 Northlake Dr",
    "sg:city":"Sanford",
    "sg:classifiers":[
        {
            "category":"Professional",
            "type":"Services"
        }
    ],
    "sg:phone":"+1 407 687 5376",
    "sg:postcode":"32773",
    "sg:province":"FL",
    "wof:name":"Ultrasonicplayground",
    "wof:placetype":"venue"
},
  "geometry": {"coordinates":[-81.29536400000001,28.752052],"type":"Point"}
}