{
  "type": "Feature",
  "properties": {
    "addr:full":"3181 Skyway Cir Melbourne FL 32934",
    "addr:housenumber":"3181",
    "addr:postcode":"32934",
    "addr:street":"Skyway Cir",
    "iso:country":"US",
    "sg:address":"3181 Skyway Cir",
    "sg:city":"Melbourne",
    "sg:classifiers":[
        {
            "category":"Home & Garden",
            "subcategory":"Building Materials",
            "type":"Retail Goods"
        }
    ],
    "sg:phone":"+1 321 259 4577",
    "sg:postcode":"32934",
    "sg:province":"FL",
    "wof:name":"Seacoast Supply",
    "wof:placetype":"venue"
},
  "geometry": {"coordinates":[-80.678437,28.112754],"type":"Point"}
}