{
  "type": "Feature",
  "properties": {
    "iso:country":"US",
    "sg:address":"15 Mitchell Ave",
    "sg:city":"Orange Park",
    "sg:classifiers":[
        {
            "category":"Professional",
            "subcategory":"Management & Consulting",
            "type":"Services"
        }
    ],
    "sg:phone":"+1 904 278 2898",
    "sg:postcode":"32073",
    "sg:province":"FL",
    "sg:tags":[
        "party",
        "planning"
    ],
    "wof:name":"Hire A Fire Truck",
    "wof:placetype":"venue"
},
  "geometry": {"coordinates":[-81.734257,30.154417],"type":"Point"}
}