{
  "type": "Feature",
  "properties": {
    "iso:country":"US",
    "sg:address":"321 Miracle Mile",
    "sg:city":"Coral Gables",
    "sg:classifiers":[
        {
            "category":"Restaurant",
            "type":"Food & Drink"
        }
    ],
    "sg:phone":"+1 305 442 8552",
    "sg:postcode":"33134",
    "sg:province":"FL",
    "sg:tags":[
        "new",
        "american"
    ],
    "sg:website":"www.seasons52.com/",
    "wof:name":"Seasons 52",
    "wof:placetype":"venue"
},
  "geometry": {"coordinates":[-80.26133900000001,25.74974],"type":"Point"}
}