{
  "type": "Feature",
  "properties": {
    "iso:country":"US",
    "sg:address":"7405 NW 88th Ave",
    "sg:city":"Tamarac",
    "sg:classifiers":[
        {
            "category":"Manufacturing",
            "subcategory":"Glass & Minerals",
            "type":"Manufacturing & Wholesale Goods"
        },
        {
            "category":"Retail",
            "subcategory":"Auto Repair",
            "type":"Services"
        }
    ],
    "sg:phone":"+1 954 633 4843",
    "sg:postcode":"33321",
    "sg:province":"FL",
    "sg:tags":[
        "plate",
        "window",
        "windshield",
        "glass-auto"
    ],
    "sg:website":"http://fortlauderdale.citysearch.com/profile/external/651223260/tamarac_fl/tint_world_tamarac.html?publisher=yellowpages&reference_id=7&placement=ypwebsitemip",
    "wof:name":"Tint World Tamarac",
    "wof:placetype":"venue"
},
  "geometry": {"coordinates":[-80.27042,26.212767],"type":"Point"}
}