{
  "type": "Feature",
  "properties": {
    "iso:country":"US",
    "sg:address":"1313 W Boynton Beach Blvd",
    "sg:city":"Boynton Beach",
    "sg:classifiers":[
        {
            "category":"Manufacturing",
            "subcategory":"Printing",
            "type":"Manufacturing & Wholesale Goods"
        }
    ],
    "sg:phone":"+1 561 736 1022",
    "sg:postcode":"33426",
    "sg:province":"FL",
    "sg:tags":[
        "printer",
        "commercial",
        "offset"
    ],
    "wof:name":"Allegra Print and Imaging",
    "wof:placetype":"venue"
},
  "geometry": {"coordinates":[-80.08297899999999,26.528167],"type":"Point"}
}