{
  "type": "Feature",
  "properties": {
    "iso:country":"US",
    "sg:address":"13235 SW 201st Ter",
    "sg:city":"Miami",
    "sg:classifiers":[
        {
            "category":"Retail",
            "subcategory":"Laundry & Dry Cleaning",
            "type":"Services"
        }
    ],
    "sg:phone":"+1 305 978 2880",
    "sg:postcode":"33177",
    "sg:province":"FL",
    "sg:tags":[
        "cleaner",
        "rug",
        "carpet"
    ],
    "wof:name":"Miami Kwik Dry",
    "wof:placetype":"venue"
},
  "geometry": {"coordinates":[-80.40638199999999,25.579523],"type":"Point"}
}