{
  "type": "Feature",
  "properties": {
    "iso:country":"US",
    "sg:address":"930 W Main St",
    "sg:city":"Avon Park",
    "sg:classifiers":[
        {
            "category":"Health Services",
            "subcategory":"Doctor",
            "type":"Services"
        }
    ],
    "sg:phone":"+1 863 453 8700",
    "sg:postcode":"33825",
    "sg:province":"FL",
    "sg:tags":[
        "physician",
        "surgeon"
    ],
    "wof:name":"Gerald Abraham MD",
    "wof:placetype":"venue"
},
  "geometry": {"coordinates":[-81.511816,27.595675],"type":"Point"}
}