{
  "type": "Feature",
  "properties": {
    "iso:country":"US",
    "sg:address":"1005 SW 10th Street",
    "sg:city":"Ocala",
    "sg:classifiers":[
        {
            "category":"Professional",
            "subcategory":"Employment Agencies",
            "type":"Services"
        }
    ],
    "sg:phone":"+1 352 867 8055",
    "sg:postcode":"34474",
    "sg:province":"FL",
    "sg:tags":[
        "consultant",
        "opportunity",
        "screening",
        "resume"
    ],
    "sg:website":"https://ocala.expresspros.com/?utm_source=yellowpages&utm_content=1281&utm_campaign=localmaps",
    "wof:name":"Express Employment Professionals - Staffing",
    "wof:placetype":"venue"
},
  "geometry": {"coordinates":[-82.14725799999999,29.179042],"type":"Point"}
}