{
  "type": "Feature",
  "properties": {
    "addr:full":"520 W State Road 436 Ste 1126 Altamonte Springs FL 32714",
    "addr:housenumber":"520",
    "addr:postcode":"32714",
    "addr:street":"W State Road 436 Ste 1126",
    "iso:country":"US",
    "sg:address":"520 W State Road 436 Ste 1126",
    "sg:city":"Altamonte Springs",
    "sg:classifiers":[
        {
            "category":"Restaurant",
            "type":"Food & Drink"
        }
    ],
    "sg:phone":"+1 407 388 1868",
    "sg:postcode":"32714",
    "sg:province":"FL",
    "sg:tags":[
        "chinese"
    ],
    "wof:name":"Golden City Chinese Restaurant",
    "wof:placetype":"venue"
},
  "geometry": {"coordinates":[-81.403615,28.661638],"type":"Point"}
}