{
  "type": "Feature",
  "properties": {
    "iso:country":"US",
    "sg:address":"1413 34th St",
    "sg:city":"Orlando",
    "sg:classifiers":[
        {
            "category":"Place Of Worship",
            "subcategory":"Church",
            "type":"Public Place"
        },
        {
            "category":"Place Of Worship",
            "type":"Public Place"
        }
    ],
    "sg:phone":"+1 407 648 0028",
    "sg:postcode":"32839",
    "sg:province":"FL",
    "sg:tags":[
        "testament",
        "churches-church",
        "christ-new",
        "christ"
    ],
    "wof:name":"United Open Door Church",
    "wof:placetype":"venue"
},
  "geometry": {"coordinates":[-81.399317,28.508097],"type":"Point"}
}