{
  "type": "Feature",
  "properties": {
    "iso:country":"US",
    "sg:address":"375 SW 65th Ave",
    "sg:city":"Pompano Beach",
    "sg:classifiers":[
        {
            "category":"Freight",
            "type":"Transportation"
        }
    ],
    "sg:phone":"+1 954 977 7500",
    "sg:postcode":"33068",
    "sg:province":"FL",
    "sg:tags":[
        "operator",
        "local",
        "trucking"
    ],
    "wof:name":"Sabrinas Trucking Inc",
    "wof:placetype":"venue"
},
  "geometry": {"coordinates":[-80.213801,26.226053],"type":"Point"}
}