{
  "type": "Feature",
  "properties": {
    "iso:country":"US",
    "sg:address":"2151 NE 205th St",
    "sg:city":"Miami",
    "sg:classifiers":[
        {
            "category":"Banks & Credit Unions",
            "subcategory":"Investment Brokerage",
            "type":"Services"
        },
        {
            "category":"Banks & Credit Unions",
            "subcategory":"Bank",
            "type":"Services"
        }
    ],
    "sg:phone":"+1 305 932 3070",
    "sg:postcode":"33179",
    "sg:province":"FL",
    "sg:tags":[
        "transfer",
        "bond",
        "broker",
        "agent",
        "stock"
    ],
    "wof:name":"Michael R Smith Stock Bro",
    "wof:placetype":"venue"
},
  "geometry": {"coordinates":[-80.159381,25.965181],"type":"Point"}
}