{
  "type": "Feature",
  "properties": {
    "addr:full":"3879 Scotts Plaza Dr Jay FL 32565",
    "addr:housenumber":"3879",
    "addr:postcode":"32565",
    "addr:street":"Scotts Plaza Dr",
    "iso:country":"US",
    "sg:address":"3879 Scotts Plaza Dr",
    "sg:city":"Jay",
    "sg:classifiers":[
        {
            "category":"Personal",
            "subcategory":"Beauty Salon",
            "type":"Services"
        }
    ],
    "sg:phone":"+1 850 675 4312",
    "sg:postcode":"32565",
    "sg:province":"FL",
    "wof:name":"A&J Custs & Curls",
    "wof:placetype":"venue"
},
  "geometry": {"coordinates":[-87.151674,30.950743],"type":"Point"}
}