{
  "type": "Feature",
  "properties": {
    "iso:country":"US",
    "sg:address":"7411 Vista Way",
    "sg:city":"Bradenton",
    "sg:classifiers":[
        {
            "category":"Professional",
            "type":"Services"
        }
    ],
    "sg:phone":"+1 941 373 6535",
    "sg:postcode":"34202",
    "sg:province":"FL",
    "sg:tags":[
        "establishment"
    ],
    "wof:name":"Rotondo Weirich Inc",
    "wof:placetype":"venue"
},
  "geometry": {"coordinates":[-82.44714399999999,27.406584],"type":"Point"}
}