{
  "type": "Feature",
  "properties": {
    "addr:full":"2120 S Ridgewood Ave Edgewater FL 32141",
    "addr:housenumber":"2120",
    "addr:postcode":"32141",
    "addr:street":"S Ridgewood Ave",
    "iso:country":"US",
    "sg:address":"2120 S Ridgewood Ave",
    "sg:city":"Edgewater",
    "sg:classifiers":[
        {
            "category":"Organizations",
            "subcategory":"Community Association",
            "type":"Services"
        }
    ],
    "sg:phone":"+1 386 426 6584",
    "sg:postcode":"32141",
    "sg:province":"FL",
    "sg:tags":[
        "club"
    ],
    "wof:name":"Dolphin Athletic Club",
    "wof:placetype":"venue"
},
  "geometry": {"coordinates":[-80.89252500000001,28.966949],"type":"Point"}
}