{
  "type": "Feature",
  "properties": {
    "addr:full":"251 Douglas Rd E Oldsmar FL 34677",
    "addr:housenumber":"251",
    "addr:postcode":"34677",
    "addr:street":"Douglas Rd E",
    "iso:country":"US",
    "sg:address":"251 Douglas Rd E",
    "sg:city":"Oldsmar",
    "sg:classifiers":[
        {
            "category":"Building & Trades",
            "subcategory":"Electrical",
            "type":"Services"
        }
    ],
    "sg:phone":"+1 813 855 0114",
    "sg:postcode":"34677",
    "sg:province":"FL",
    "sg:tags":[
        "electrical",
        "electric",
        "contractor"
    ],
    "wof:name":"Pelican Electrical Group Inc",
    "wof:placetype":"venue"
},
  "geometry": {"coordinates":[-82.66099,28.041636],"type":"Point"}
}