{
  "type": "Feature",
  "properties": {
    "iso:country":"US",
    "sg:address":"1625 W Marion Ave",
    "sg:city":"Punta Gorda",
    "sg:classifiers":[
        {
            "category":"Building & Trades",
            "subcategory":"Construction",
            "type":"Services"
        }
    ],
    "sg:phone":"+1 941 639 4663",
    "sg:postcode":"33950",
    "sg:province":"FL",
    "sg:tags":[
        "specializing",
        "new",
        "contractor",
        "remodeling",
        "general"
    ],
    "wof:name":"Diplomat Homes",
    "wof:placetype":"venue"
},
  "geometry": {"coordinates":[-82.069428,26.924697],"type":"Point"}
}