{
  "type": "Feature",
  "properties": {
    "iso:country":"US",
    "sg:address":"32 SE 1st Ave",
    "sg:city":"Miami",
    "sg:classifiers":[
        {
            "category":"Shopping",
            "subcategory":"Optical Goods",
            "type":"Retail Goods"
        }
    ],
    "sg:phone":"+1 305 381 6009",
    "sg:postcode":"33131",
    "sg:province":"FL",
    "sg:tags":[
        "optician",
        "eyewear"
    ],
    "wof:name":"Royal Eyewear",
    "wof:placetype":"venue"
},
  "geometry": {"coordinates":[-80.192001,25.7735],"type":"Point"}
}