{
  "type": "Feature",
  "properties": {
    "iso:country":"US",
    "sg:address":"13630 SW 120th St",
    "sg:city":"Miami",
    "sg:phone":"+1 305 238 0812",
    "sg:postcode":"33186",
    "sg:province":"FL",
    "wof:name":"Million Dollar Nails Of Kendall",
    "wof:placetype":"venue"
},
  "geometry": {"coordinates":[-80.41490400000001,25.656249],"type":"Point"}
}