{
  "type": "Feature",
  "properties": {
    "iso:country":"US",
    "sg:address":"120 E Main St",
    "sg:city":"Pensacola",
    "sg:classifiers":[
        {
            "category":"Restaurant",
            "type":"Food & Drink"
        }
    ],
    "sg:phone":"+1 850 429 8640",
    "sg:postcode":"32502",
    "sg:province":"FL",
    "sg:tags":[
        "beverage",
        "eating",
        "alcoholic"
    ],
    "wof:name":"Martines",
    "wof:placetype":"venue"
},
  "geometry": {"coordinates":[-87.21249,30.407986],"type":"Point"}
}