{
  "type": "Feature",
  "properties": {
    "iso:country":"US",
    "sg:address":"151 107th Ave",
    "sg:city":"Treasure Island",
    "sg:classifiers":[
        {
            "category":"Banks & Credit Unions",
            "subcategory":"Investment Brokerage",
            "type":"Services"
        }
    ],
    "sg:phone":"+1 727 367 1311",
    "sg:postcode":"33706",
    "sg:province":"FL",
    "sg:tags":[
        "management"
    ],
    "wof:name":"Municipal Tax Liens Inc",
    "wof:placetype":"venue"
},
  "geometry": {"coordinates":[-82.768029,27.769451],"type":"Point"}
}