{
  "type": "Feature",
  "properties": {
    "iso:country":"US",
    "sg:address":"103 Flagship Dr",
    "sg:city":"Lutz",
    "sg:classifiers":[
        {
            "category":"Shopping",
            "subcategory":"Florist",
            "type":"Retail Goods"
        }
    ],
    "sg:phone":"+1 813 963 2423",
    "sg:postcode":"33549",
    "sg:province":"FL",
    "wof:name":"Alle' Florist",
    "wof:placetype":"venue"
},
  "geometry": {"coordinates":[-82.463334,28.134854],"type":"Point"}
}