{
  "type": "Feature",
  "properties": {
    "iso:country":"US",
    "sg:address":"1100 Old Dixie Hwy",
    "sg:city":"Vero Beach",
    "sg:classifiers":[
        {
            "category":"Manufacturing",
            "subcategory":"Tools & Machinery",
            "type":"Manufacturing & Wholesale Goods"
        }
    ],
    "sg:phone":"+1 772 567 1240",
    "sg:postcode":"32960",
    "sg:province":"FL",
    "sg:tags":[
        "computer",
        "parts",
        "supply"
    ],
    "sg:website":"www.mundocorp.com",
    "wof:name":"Mundo Corp",
    "wof:placetype":"venue"
},
  "geometry": {"coordinates":[-80.39298599999999,27.620006],"type":"Point"}
}