{
  "type": "Feature",
  "properties": {
    "addr:full":"2742 N Hiawassee Rd Orlando FL 32818",
    "addr:housenumber":"2742",
    "addr:postcode":"32818",
    "addr:street":"N Hiawassee Rd",
    "iso:country":"US",
    "sg:address":"2742 N Hiawassee Rd",
    "sg:city":"Orlando",
    "sg:classifiers":[
        {
            "category":"Insurance",
            "subcategory":"Hazard Insurance",
            "type":"Services"
        }
    ],
    "sg:phone":"+1 407 299 1771",
    "sg:postcode":"32818",
    "sg:province":"FL",
    "sg:tags":[
        "carrier"
    ],
    "wof:name":"Florida No-Fault",
    "wof:placetype":"venue"
},
  "geometry": {"coordinates":[-81.476114,28.57933],"type":"Point"}
}