{
  "type": "Feature",
  "properties": {
    "iso:country":"US",
    "sg:address":"1306 S Riverside Dr",
    "sg:city":"Steinhatchee",
    "sg:classifiers":[
        {
            "category":"Restaurant",
            "type":"Food & Drink"
        }
    ],
    "sg:phone":"+1 352 498 7427",
    "sg:postcode":"32359",
    "sg:province":"FL",
    "wof:name":"Zaney Foods Incorporated",
    "wof:placetype":"venue"
},
  "geometry": {"coordinates":[-83.372421,29.667629],"type":"Point"}
}