{
  "type": "Feature",
  "properties": {
    "addr:full":"1695 Alton Rd Miami Beach FL 33139",
    "addr:housenumber":"1695",
    "addr:postcode":"33139",
    "addr:street":"Alton Rd",
    "iso:country":"US",
    "sg:address":"1695 Alton Rd",
    "sg:city":"Miami Beach",
    "sg:classifiers":[
        {
            "category":"Restaurant",
            "type":"Food & Drink"
        }
    ],
    "sg:menulink":"http://www.allmenus.com/fl/miami-beach/160119-burger-king/menu/",
    "sg:phone":"+1 305 672 3661",
    "sg:postcode":"33139",
    "sg:province":"FL",
    "sg:tags":[
        "burger",
        "american"
    ],
    "wof:name":"Burger King",
    "wof:placetype":"venue"
},
  "geometry": {"coordinates":[-80.140872,25.791906],"type":"Point"}
}