{
  "type": "Feature",
  "properties": {
    "addr:full":"6747 S Tamiami Trl Sarasota FL 34231",
    "addr:housenumber":"6747",
    "addr:postcode":"34231",
    "addr:street":"S Tamiami Trl",
    "iso:country":"US",
    "sg:address":"6747 S Tamiami Trl",
    "sg:city":"Sarasota",
    "sg:phone":"+1 941 924 1297",
    "sg:postcode":"34231",
    "sg:province":"FL",
    "sg:website":"http://www.redlobster.com",
    "wof:name":"Red Lobster",
    "wof:placetype":"venue"
},
  "geometry": {"coordinates":[-82.519989,27.257784],"type":"Point"}
}