{
  "type": "Feature",
  "properties": {
    "iso:country":"US",
    "sg:address":"6700 102nd Ave",
    "sg:city":"Pinellas Park",
    "sg:classifiers":[
        {
            "category":"Real Estate",
            "subcategory":"Real Estate Operator",
            "type":"Services"
        }
    ],
    "sg:phone":"+1 727 541 6557",
    "sg:postcode":"33782",
    "sg:province":"FL",
    "sg:tags":[
        "apartment"
    ],
    "wof:name":"Oceanside Estate Apartments",
    "wof:placetype":"venue"
},
  "geometry": {"coordinates":[-82.73190200000001,27.864563],"type":"Point"}
}