{
  "type": "Feature",
  "properties": {
    "iso:country":"US",
    "sg:address":"1400 59th St W",
    "sg:city":"Bradenton",
    "sg:classifiers":[
        {
            "category":"Health Services",
            "subcategory":"Doctor",
            "type":"Services"
        }
    ],
    "sg:phone":"+1 941 795 2468",
    "sg:postcode":"34209",
    "sg:province":"FL",
    "sg:tags":[
        "medical"
    ],
    "wof:name":"Liebert Hugh P",
    "wof:placetype":"venue"
},
  "geometry": {"coordinates":[-82.620574,27.485069],"type":"Point"}
}