{
  "type": "Feature",
  "properties": {
    "addr:full":"4507 Manatee Ave W Bradenton FL 34209",
    "addr:housenumber":"4507",
    "addr:postcode":"34209",
    "addr:street":"Manatee Ave W",
    "iso:country":"US",
    "sg:address":"4507 Manatee Ave W",
    "sg:city":"Bradenton",
    "sg:classifiers":[
        {
            "category":"Professional",
            "type":"Services"
        }
    ],
    "sg:phone":"+1 941 746 2233",
    "sg:postcode":"34209",
    "sg:province":"FL",
    "sg:tags":[
        "establishment"
    ],
    "wof:name":"Antonios",
    "wof:placetype":"venue"
},
  "geometry": {"coordinates":[-82.605991,27.495907],"type":"Point"}
}