{
  "type": "Feature",
  "properties": {
    "iso:country":"US",
    "sg:address":"6011 Rodman St",
    "sg:city":"Hollywood",
    "sg:classifiers":[
        {
            "category":"Professional",
            "subcategory":"Business Services",
            "type":"Services"
        }
    ],
    "sg:phone":"+1 954 272 0352",
    "sg:postcode":"33023",
    "sg:province":"FL",
    "sg:tags":[
        "appraiser"
    ],
    "wof:name":"Cyrus Appraisal",
    "wof:placetype":"venue"
},
  "geometry": {"coordinates":[-80.209063,25.999803],"type":"Point"}
}