{
  "type": "Feature",
  "properties": {
    "iso:country":"US",
    "sg:address":"9060 NW 97th Ter",
    "sg:city":"Miami",
    "sg:classifiers":[
        {
            "category":"Manufacturing",
            "subcategory":"Glass & Minerals",
            "type":"Manufacturing & Wholesale Goods"
        }
    ],
    "sg:phone":"+1 305 885 8076",
    "sg:postcode":"33178",
    "sg:province":"FL",
    "sg:tags":[
        "concrete",
        "product",
        "mfg"
    ],
    "wof:name":"Mediterranen Roof Tile Inc",
    "wof:placetype":"venue"
},
  "geometry": {"coordinates":[-80.346295,25.862584],"type":"Point"}
}