{
  "type": "Feature",
  "properties": {
    "iso:country":"US",
    "sg:address":"4601 Old Dixie Hwy",
    "sg:city":"Fort Pierce",
    "sg:classifiers":[
        {
            "category":"Organizations",
            "subcategory":"Religious Organization",
            "type":"Services"
        }
    ],
    "sg:phone":"+1 772 468 3123",
    "sg:postcode":"34946",
    "sg:province":"FL",
    "sg:tags":[
        "church"
    ],
    "wof:name":"Riverview Baptist Church",
    "wof:placetype":"venue"
},
  "geometry": {"coordinates":[-80.351935,27.51805],"type":"Point"}
}