{
  "type": "Feature",
  "properties": {
    "addr:full":"1335 Oviedo Marketplace Blvd Oviedo FL 32765",
    "addr:housenumber":"1335",
    "addr:postcode":"32765",
    "addr:street":"Oviedo Marketplace Blvd",
    "iso:country":"US",
    "sg:address":"1335 Oviedo Marketplace Blvd",
    "sg:city":"Oviedo",
    "sg:classifiers":[
        {
            "category":"Shopping",
            "subcategory":"Bicycles & Sporting Goods",
            "type":"Retail Goods"
        }
    ],
    "sg:phone":"+1 407 977 4480",
    "sg:postcode":"32765",
    "sg:province":"FL",
    "wof:name":"USS Extreme",
    "wof:placetype":"venue"
},
  "geometry": {"coordinates":[-81.23275700000001,28.665346],"type":"Point"}
}