{
  "type": "Feature",
  "properties": {
    "addr:full":"3645 Palm Beach Blvd Fort Myers FL 33916",
    "addr:housenumber":"3645",
    "addr:postcode":"33916",
    "addr:street":"Palm Beach Blvd",
    "iso:country":"US",
    "sg:address":"3645 Palm Beach Blvd",
    "sg:city":"Fort Myers",
    "sg:classifiers":[
        {
            "category":"Personal",
            "subcategory":"Beauty Salon",
            "type":"Services"
        }
    ],
    "sg:phone":"+1 239 694 4041",
    "sg:postcode":"33916",
    "sg:province":"FL",
    "sg:tags":[
        "shop"
    ],
    "wof:name":"Virgaleen Pitts Hair Care",
    "wof:placetype":"venue"
},
  "geometry": {"coordinates":[-81.839839,26.661148],"type":"Point"}
}