{
  "type": "Feature",
  "properties": {
    "iso:country":"US",
    "sg:address":"4204 Palm Beach Blvd",
    "sg:city":"Fort Myers",
    "sg:classifiers":[
        {
            "category":"Shopping",
            "subcategory":"Pharmacy",
            "type":"Retail Goods"
        }
    ],
    "sg:phone":"+1 239 694 2000",
    "sg:postcode":"33905",
    "sg:province":"FL",
    "sg:website":"www.walgreens.com",
    "wof:name":"Walgreens",
    "wof:placetype":"venue"
},
  "geometry": {"coordinates":[-81.826971,26.668146],"type":"Point"}
}