{
  "type": "Feature",
  "properties": {
    "addr:full":"13229 US Hwy 19 Hudson FL 34667",
    "addr:housenumber":"13229",
    "addr:postcode":"34667",
    "addr:street":"Us Hwy 19",
    "iso:country":"US",
    "sg:address":"13229 US Hwy 19",
    "sg:city":"Hudson",
    "sg:classifiers":[
        {
            "category":"Restaurant",
            "type":"Food & Drink"
        }
    ],
    "sg:phone":"+1 727 869 0888",
    "sg:postcode":"34667",
    "sg:province":"FL",
    "wof:name":"Clyde's Broasted Chicken",
    "wof:placetype":"venue"
},
  "geometry": {"coordinates":[-82.699259,28.350449],"type":"Point"}
}