{
  "type": "Feature",
  "properties": {
    "iso:country":"US",
    "sg:address":"3554 Old Dixie Hwy",
    "sg:city":"Stuart",
    "sg:classifiers":[
        {
            "category":"Building & Trades",
            "subcategory":"Plumbing",
            "type":"Services"
        }
    ],
    "sg:phone":"+1 772 878 1391",
    "sg:postcode":"34997",
    "sg:province":"FL",
    "sg:tags":[
        "product",
        "management",
        "energy",
        "system"
    ],
    "wof:name":"Commercial Energy Specialists",
    "wof:placetype":"venue"
},
  "geometry": {"coordinates":[-80.21549400000001,27.161515],"type":"Point"}
}