{
  "type": "Feature",
  "properties": {
    "iso:country":"US",
    "sg:address":"203 Canal Blvd",
    "sg:city":"Ponte Vedra Beach",
    "sg:classifiers":[
        {
            "category":"Building & Trades",
            "subcategory":"Construction",
            "type":"Services"
        }
    ],
    "sg:phone":"+1 904 285 7088",
    "sg:postcode":"32082",
    "sg:province":"FL",
    "sg:tags":[
        "residential"
    ],
    "wof:name":"C & D Trim Inc",
    "wof:placetype":"venue"
},
  "geometry": {"coordinates":[-81.39610399999999,30.177121],"type":"Point"}
}