{
  "type": "Feature",
  "properties": {
    "iso:country":"US",
    "sg:address":"1756 Dibble Cir E",
    "sg:city":"Jacksonville",
    "sg:classifiers":[
        {
            "category":"Freight",
            "type":"Transportation"
        }
    ],
    "sg:phone":"+1 904 641 5221",
    "sg:postcode":"32246",
    "sg:province":"FL",
    "sg:tags":[
        "operator",
        "trucking"
    ],
    "wof:name":"Michael A Jarzomkowski",
    "wof:placetype":"venue"
},
  "geometry": {"coordinates":[-81.528357,30.322632],"type":"Point"}
}