{
  "type": "Feature",
  "properties": {
    "iso:country":"US",
    "sg:address":"3902 Crill Ave",
    "sg:city":"Palatka",
    "sg:classifiers":[
        {
            "category":"Retail",
            "subcategory":"Auto Repair",
            "type":"Services"
        }
    ],
    "sg:phone":"+1 386 328 9927",
    "sg:postcode":"32177",
    "sg:province":"FL",
    "sg:tags":[
        "general"
    ],
    "wof:name":"Norris Automotive Repair",
    "wof:placetype":"venue"
},
  "geometry": {"coordinates":[-81.673614,29.641424],"type":"Point"}
}