{
  "type": "Feature",
  "properties": {
    "addr:full":"2490 SW 17th Ave Miami FL 33145",
    "addr:housenumber":"2490",
    "addr:postcode":"33145",
    "addr:street":"Sw 17Th Ave",
    "iso:country":"US",
    "sg:address":"2490 SW 17th Ave",
    "sg:city":"Miami",
    "sg:classifiers":[
        {
            "category":"Restaurant",
            "type":"Food & Drink"
        }
    ],
    "sg:menulink":"http://www.allmenus.com/fl/miami/122642-quiznos-sub/menu/",
    "sg:phone":"+1 305 854 3836",
    "sg:postcode":"33145",
    "sg:province":"FL",
    "sg:tags":[
        "wrap",
        "american",
        "sandwich"
    ],
    "wof:name":"Quiznos Sub",
    "wof:placetype":"venue"
},
  "geometry": {"coordinates":[-80.221788,25.746336],"type":"Point"}
}