{
  "type": "Feature",
  "properties": {
    "iso:country":"US",
    "sg:address":"440 Inglewood Dr",
    "sg:city":"Lake Worth",
    "sg:classifiers":[
        {
            "category":"Professional",
            "type":"Services"
        }
    ],
    "sg:phone":"+1 561 307 6981",
    "sg:postcode":"33461",
    "sg:province":"FL",
    "wof:name":"David Cavanaugh Svc",
    "wof:placetype":"venue"
},
  "geometry": {"coordinates":[-80.10345,26.642477],"type":"Point"}
}