{
  "type": "Feature",
  "properties": {
    "iso:country":"US",
    "sg:address":"5709 17th Ave S",
    "sg:city":"Gulfport",
    "sg:classifiers":[
        {
            "category":"Professional",
            "subcategory":"Management & Consulting",
            "type":"Services"
        }
    ],
    "sg:phone":"+1 727 343 6733",
    "sg:postcode":"33707",
    "sg:province":"FL",
    "sg:tags":[
        "construction"
    ],
    "wof:name":"David Griffith Construction",
    "wof:placetype":"venue"
},
  "geometry": {"coordinates":[-82.711945,27.753801],"type":"Point"}
}