{
  "type": "Feature",
  "properties": {
    "iso:country":"US",
    "sg:address":"2774 N Harbor City Blvd",
    "sg:city":"Melbourne",
    "sg:classifiers":[
        {
            "category":"Professional",
            "subcategory":"Management & Consulting",
            "type":"Services"
        }
    ],
    "sg:phone":"+1 321 480 3141",
    "sg:postcode":"32935",
    "sg:province":"FL",
    "sg:tags":[
        "party",
        "planning"
    ],
    "wof:name":"Play Plus",
    "wof:placetype":"venue"
},
  "geometry": {"coordinates":[-80.640472,28.152962],"type":"Point"}
}