{
  "type": "Feature",
  "properties": {
    "iso:country":"US",
    "sg:address":"1316 Coconut Palm Cir",
    "sg:city":"Daytona Beach",
    "sg:classifiers":[
        {
            "category":"Building & Trades",
            "subcategory":"Construction",
            "type":"Services"
        }
    ],
    "sg:phone":"+1 386 767 6738",
    "sg:postcode":"32128",
    "sg:province":"FL",
    "sg:tags":[
        "underground",
        "general",
        "utility",
        "contractor"
    ],
    "wof:name":"Orion Construction Co Inc",
    "wof:placetype":"venue"
},
  "geometry": {"coordinates":[-81.04336600000001,29.109074],"type":"Point"}
}