{
  "type": "Feature",
  "properties": {
    "addr:full":"5430 NW 114th Ave Miami FL 33178",
    "addr:housenumber":"5430",
    "addr:postcode":"33178",
    "addr:street":"Nw 114Th Ave",
    "iso:country":"US",
    "sg:address":"5430 NW 114th Ave",
    "sg:city":"Miami",
    "sg:classifiers":[
        {
            "category":"Building & Trades",
            "subcategory":"Landscaping Services",
            "type":"Services"
        }
    ],
    "sg:phone":"+1 305 640 0617",
    "sg:postcode":"33178",
    "sg:province":"FL",
    "sg:tags":[
        "landscape"
    ],
    "wof:name":"Rosalinda Corp",
    "wof:placetype":"venue"
},
  "geometry": {"coordinates":[-80.382037,25.825583],"type":"Point"}
}