{
  "type": "Feature",
  "properties": {
    "iso:country":"US",
    "sg:address":"1864 S Jefferson St",
    "sg:city":"Perry",
    "sg:classifiers":[
        {
            "category":"Real Estate",
            "subcategory":"Real Estate Operator",
            "type":"Services"
        }
    ],
    "sg:phone":"+1 850 584 6217",
    "sg:postcode":"32348",
    "sg:province":"FL",
    "sg:tags":[
        "mall",
        "shopping",
        "center"
    ],
    "wof:name":"Perry Shopping Ctr",
    "wof:placetype":"venue"
},
  "geometry": {"coordinates":[-83.582594,30.103273],"type":"Point"}
}