{
  "type": "Feature",
  "properties": {
    "iso:country":"US",
    "sg:address":"14135 NW 7th Ave",
    "sg:city":"Miami",
    "sg:classifiers":[
        {
            "category":"Restaurant",
            "type":"Food & Drink"
        }
    ],
    "sg:phone":"+1 305 681 2111",
    "sg:postcode":"33168",
    "sg:province":"FL",
    "wof:name":"Venus Restaurant & Sports Bar",
    "wof:placetype":"venue"
},
  "geometry": {"coordinates":[-80.211601,25.903601],"type":"Point"}
}