{
  "type": "Feature",
  "properties": {
    "iso:country":"US",
    "sg:address":"555 Pasadena Ave",
    "sg:city":"Longwood",
    "sg:classifiers":[
        {
            "category":"Building & Trades",
            "subcategory":"Construction",
            "type":"Services"
        }
    ],
    "sg:phone":"+1 407 331 4073",
    "sg:postcode":"32750",
    "sg:province":"FL",
    "sg:tags":[
        "concrete",
        "contractor"
    ],
    "wof:name":"Buckner Concrete",
    "wof:placetype":"venue"
},
  "geometry": {"coordinates":[-81.33718,28.704817],"type":"Point"}
}