{
  "type": "Feature",
  "properties": {
    "iso:country":"US",
    "sg:address":"2355 SE 17th St",
    "sg:city":"Ocala",
    "sg:classifiers":[
        {
            "category":"Real Estate",
            "subcategory":"Real Estate Agent",
            "type":"Services"
        }
    ],
    "sg:phone":"+1 352 622 9191",
    "sg:postcode":"34471",
    "sg:province":"FL",
    "sg:tags":[
        "appraiser",
        "business"
    ],
    "wof:name":"Albright & Assoc Of Ocala Inc",
    "wof:placetype":"venue"
},
  "geometry": {"coordinates":[-82.105276,29.171595],"type":"Point"}
}