{
  "type": "Feature",
  "properties": {
    "iso:country":"US",
    "sg:address":"5305 Ehrlich Rd",
    "sg:city":"Tampa",
    "sg:classifiers":[
        {
            "category":"Personal",
            "subcategory":"Beauty Salon",
            "type":"Services"
        }
    ],
    "sg:phone":"+1 813 962 1660",
    "sg:postcode":"33625",
    "sg:province":"FL",
    "wof:name":"Hairsmith",
    "wof:placetype":"venue"
},
  "geometry": {"coordinates":[-82.54006099999999,28.084265],"type":"Point"}
}