{
  "type": "Feature",
  "properties": {
    "addr:full":"619 Earle Ave N Saint Petersburg FL 33701",
    "addr:housenumber":"619",
    "addr:postcode":"33701",
    "addr:street":"Earle Ave N",
    "iso:country":"US",
    "sg:address":"619 Earle Ave N",
    "sg:city":"Saint Petersburg",
    "sg:classifiers":[
        {
            "category":"Building & Trades",
            "subcategory":"Landscaping Services",
            "type":"Services"
        }
    ],
    "sg:phone":"+1 727 515 8119",
    "sg:postcode":"33701",
    "sg:province":"FL",
    "sg:tags":[
        "landscape"
    ],
    "wof:name":"Labancas Landscaping",
    "wof:placetype":"venue"
},
  "geometry": {"coordinates":[-82.64243500000001,27.778184],"type":"Point"}
}