{
  "type": "Feature",
  "properties": {
    "iso:country":"US",
    "sg:address":"1120 Crestwood St",
    "sg:city":"Jacksonville",
    "sg:classifiers":[
        {
            "category":"Professional",
            "subcategory":"Advertising",
            "type":"Services"
        }
    ],
    "sg:phone":"+1 904 997 7727",
    "sg:postcode":"32208",
    "sg:province":"FL",
    "sg:tags":[
        "outdoor",
        "spec",
        "mfg"
    ],
    "wof:name":"Clear Channel Outdoor Inc",
    "wof:placetype":"venue"
},
  "geometry": {"coordinates":[-81.672,30.374182],"type":"Point"}
}