{
  "type": "Feature",
  "properties": {
    "iso:country":"US",
    "sg:address":"6081 Plantation Ln",
    "sg:city":"Crestview",
    "sg:classifiers":[
        {
            "category":"Building & Trades",
            "subcategory":"Construction",
            "type":"Services"
        }
    ],
    "sg:phone":"+1 850 683 1401",
    "sg:postcode":"32539",
    "sg:province":"FL",
    "sg:tags":[
        "house"
    ],
    "wof:name":"Lowell Scott Builders",
    "wof:placetype":"venue"
},
  "geometry": {"coordinates":[-86.53843000000001,30.817088],"type":"Point"}
}