{
  "type": "Feature",
  "properties": {
    "addr:full":"1325 Park Manor Dr Orlando FL 32825",
    "addr:housenumber":"1325",
    "addr:postcode":"32825",
    "addr:street":"Park Manor Dr",
    "iso:country":"US",
    "sg:address":"1325 Park Manor Dr",
    "sg:city":"Orlando",
    "sg:classifiers":[
        {
            "category":"Wholesale",
            "subcategory":"Construction Materials",
            "type":"Manufacturing & Wholesale Goods"
        },
        {
            "category":"Home & Garden",
            "subcategory":"Building Materials",
            "type":"Retail Goods"
        }
    ],
    "sg:phone":"+1 407 738 1405",
    "sg:postcode":"32825",
    "sg:province":"FL",
    "sg:tags":[
        "windows-wholesale",
        "window",
        "manufacturer"
    ],
    "wof:name":"J&Y Windows Inc",
    "wof:placetype":"venue"
},
  "geometry": {"coordinates":[-81.22551,28.564679],"type":"Point"}
}