{
  "type": "Feature",
  "properties": {
    "iso:country":"US",
    "sg:address":"1403 Mark Twain Ct",
    "sg:city":"Niceville",
    "sg:classifiers":[
        {
            "category":"Professional",
            "type":"Services"
        }
    ],
    "sg:phone":"+1 850 897 4524",
    "sg:postcode":"32578",
    "sg:province":"FL",
    "sg:tags":[
        "establishment"
    ],
    "wof:name":"Kelly Luchsinger Wnc",
    "wof:placetype":"venue"
},
  "geometry": {"coordinates":[-86.43041700000001,30.48984],"type":"Point"}
}