{
  "type": "Feature",
  "properties": {
    "iso:country":"US",
    "sg:address":"2911 Safe Harbor Dr",
    "sg:city":"Tampa",
    "sg:classifiers":[
        {
            "category":"Health Services",
            "subcategory":"Doctor",
            "type":"Services"
        }
    ],
    "sg:phone":"+1 813 932 8710",
    "sg:postcode":"33618",
    "sg:province":"FL",
    "sg:tags":[
        "medical"
    ],
    "wof:name":"Ralph E Rydell MD PA",
    "wof:placetype":"venue"
},
  "geometry": {"coordinates":[-82.490977,28.039261],"type":"Point"}
}