{
  "type": "Feature",
  "properties": {
    "iso:country":"US",
    "sg:address":"120 E New York Ave",
    "sg:city":"De Land",
    "sg:classifiers":[
        {
            "category":"Health Services",
            "subcategory":"Clinic",
            "type":"Services"
        }
    ],
    "sg:phone":"+1 386 740 7110",
    "sg:postcode":"32724",
    "sg:province":"FL",
    "sg:tags":[
        "specialty",
        "outpatient"
    ],
    "wof:name":"Devereuxvolusia Counseling",
    "wof:placetype":"venue"
},
  "geometry": {"coordinates":[-81.303012,29.028013],"type":"Point"}
}