{
  "type": "Feature",
  "properties": {
    "iso:country":"US",
    "sg:address":"3790 NW South River Dr",
    "sg:city":"Miami",
    "sg:classifiers":[
        {
            "category":"Retail",
            "subcategory":"Auto Repair",
            "type":"Services"
        }
    ],
    "sg:phone":"+1 305 635 5590",
    "sg:postcode":"33142",
    "sg:province":"FL",
    "sg:tags":[
        "repairing",
        "automobile",
        "general"
    ],
    "wof:name":"New New Concept In Auto Repair",
    "wof:placetype":"venue"
},
  "geometry": {"coordinates":[-80.25797,25.804499],"type":"Point"}
}