{
  "type": "Feature",
  "properties": {
    "iso:country":"US",
    "sg:address":"137 Stoney Ridge Dr",
    "sg:city":"Longwood",
    "sg:classifiers":[
        {
            "category":"Building & Trades",
            "subcategory":"Landscaping Services",
            "type":"Services"
        }
    ],
    "sg:phone":"+1 407 260 2356",
    "sg:postcode":"32750",
    "sg:province":"FL",
    "sg:tags":[
        "landscape"
    ],
    "wof:name":"D L Landscaping By Daniel",
    "wof:placetype":"venue"
},
  "geometry": {"coordinates":[-81.372839,28.706031],"type":"Point"}
}