{
  "type": "Feature",
  "properties": {
    "iso:country":"US",
    "sg:address":"8077 Anhinga Rd",
    "sg:city":"Fort Myers",
    "sg:classifiers":[
        {
            "category":"Health Services",
            "subcategory":"Medical Lab",
            "type":"Services"
        }
    ],
    "sg:phone":"+1 239 278 1591",
    "sg:postcode":"33967",
    "sg:province":"FL",
    "sg:tags":[
        "laboratory",
        "dental"
    ],
    "wof:name":"Caldwell Dental Laboratory",
    "wof:placetype":"venue"
},
  "geometry": {"coordinates":[-81.814543,26.467459],"type":"Point"}
}