{
  "type": "Feature",
  "properties": {
    "addr:full":"1745 Markham Woods Rd Longwood FL 32779",
    "addr:housenumber":"1745",
    "addr:postcode":"32779",
    "addr:street":"Markham Woods Rd",
    "iso:country":"US",
    "sg:address":"1745 Markham Woods Rd",
    "sg:city":"Longwood",
    "sg:classifiers":[
        {
            "category":"Professional",
            "type":"Services"
        }
    ],
    "sg:phone":"+1 407 788 1448",
    "sg:postcode":"32779",
    "sg:province":"FL",
    "wof:name":"Tobias Network",
    "wof:placetype":"venue"
},
  "geometry": {"coordinates":[-81.384533,28.723134],"type":"Point"}
}