{
  "type": "Feature",
  "properties": {
    "iso:country":"US",
    "sg:address":"1501 E Altamonte Dr",
    "sg:city":"Casselberry",
    "sg:classifiers":[
        {
            "category":"Building & Trades",
            "subcategory":"Construction",
            "type":"Services"
        }
    ],
    "sg:phone":"+1 407 622 0596",
    "sg:postcode":"32730",
    "sg:province":"FL",
    "sg:tags":[
        "contractor"
    ],
    "wof:name":"Bidbusters Construction",
    "wof:placetype":"venue"
},
  "geometry": {"coordinates":[-81.343549,28.662097],"type":"Point"}
}