{
  "type": "Feature",
  "properties": {
    "addr:full":"5435 Juno Dr Jacksonville FL 32207",
    "addr:housenumber":"5435",
    "addr:postcode":"32207",
    "addr:street":"Juno Dr",
    "iso:country":"US",
    "sg:address":"5435 Juno Dr",
    "sg:city":"Jacksonville",
    "sg:classifiers":[
        {
            "category":"Freight",
            "type":"Transportation"
        }
    ],
    "sg:phone":"+1 904 858 9522",
    "sg:postcode":"32207",
    "sg:province":"FL",
    "sg:tags":[
        "operator",
        "local",
        "trucking"
    ],
    "wof:name":"Salim Muminovic Trucking",
    "wof:placetype":"venue"
},
  "geometry": {"coordinates":[-81.610372,30.282198],"type":"Point"}
}