{
  "type": "Feature",
  "properties": {
    "iso:country":"US",
    "sg:address":"1110 Sterling Rd",
    "sg:city":"Inverness",
    "sg:classifiers":[
        {
            "category":"Professional",
            "subcategory":"Computer Services",
            "type":"Services"
        }
    ],
    "sg:phone":"+1 352 726 7710",
    "sg:postcode":"34450",
    "sg:province":"FL",
    "sg:tags":[
        "repair"
    ],
    "wof:name":"Computer Station 2000 Comps",
    "wof:placetype":"venue"
},
  "geometry": {"coordinates":[-82.34387599999999,28.838262],"type":"Point"}
}