{
  "type": "Feature",
  "properties": {
    "iso:country":"US",
    "sg:address":"15830 Old Johnston Rd",
    "sg:city":"Dade City",
    "sg:classifiers":[
        {
            "category":"Farming",
            "subcategory":"Farm & Veterinary Services",
            "type":"Manufacturing & Wholesale Goods"
        }
    ],
    "sg:phone":"+1 352 588 3167",
    "sg:postcode":"33523",
    "sg:province":"FL",
    "sg:tags":[
        "supervisor"
    ],
    "wof:name":"Tampa Farm Svc",
    "wof:placetype":"venue"
},
  "geometry": {"coordinates":[-82.331497,28.396688],"type":"Point"}
}