{
  "type": "Feature",
  "properties": {
    "iso:country":"US",
    "sg:address":"1460 S McCall Rd",
    "sg:city":"Englewood",
    "sg:classifiers":[
        {
            "category":"Building & Trades",
            "subcategory":"Construction",
            "type":"Services"
        }
    ],
    "sg:phone":"+1 941 474 2421",
    "sg:postcode":"34223",
    "sg:province":"FL",
    "sg:tags":[
        "residential",
        "commercial",
        "contractor"
    ],
    "wof:name":"Fiore Construction Inc",
    "wof:placetype":"venue"
},
  "geometry": {"coordinates":[-82.344302,26.938746],"type":"Point"}
}