{
  "type": "Feature",
  "properties": {
    "addr:full":"1668 Stickney Point Rd Sarasota FL 34231",
    "addr:housenumber":"1668",
    "addr:postcode":"34231",
    "addr:street":"Stickney Point Rd",
    "iso:country":"US",
    "sg:address":"1668 Stickney Point Rd",
    "sg:city":"Sarasota",
    "sg:classifiers":[
        {
            "category":"Professional",
            "subcategory":"Engineering",
            "type":"Services"
        }
    ],
    "sg:phone":"+1 941 921 3893",
    "sg:postcode":"34231",
    "sg:province":"FL",
    "sg:tags":[
        "engineer"
    ],
    "wof:name":"Eisman & Russo Inc",
    "wof:placetype":"venue"
},
  "geometry": {"coordinates":[-82.52752599999999,27.256743],"type":"Point"}
}