{
  "type": "Feature",
  "properties": {
    "iso:country":"US",
    "sg:address":"107 E Green St",
    "sg:city":"Perry",
    "sg:classifiers":[
        {
            "category":"Health Services",
            "subcategory":"Nursing And Care Facility",
            "type":"Services"
        }
    ],
    "sg:phone":"+1 850 838 3086",
    "sg:postcode":"32347",
    "sg:province":"FL",
    "sg:tags":[
        "hospice"
    ],
    "sg:website":"www.bigbendhospice.org",
    "wof:name":"Big Bend Hospice",
    "wof:placetype":"venue"
},
  "geometry": {"coordinates":[-83.58121199999999,30.117067],"type":"Point"}
}