{
  "type": "Feature",
  "properties": {
    "iso:country":"US",
    "sg:address":"100 SE 2nd St",
    "sg:city":"Miami",
    "sg:classifiers":[
        {
            "category":"Professional",
            "subcategory":"Lawyer & Legal Services",
            "type":"Services"
        }
    ],
    "sg:phone":"+1 305 374 5418",
    "sg:postcode":"33131",
    "sg:province":"FL",
    "sg:tags":[
        "litigation",
        "tort",
        "attorney"
    ],
    "wof:name":"Patel , Himanshu M. - Zarco Einhorn Salk",
    "wof:placetype":"venue"
},
  "geometry": {"coordinates":[-80.191849,25.77256],"type":"Point"}
}