{
  "type": "Feature",
  "properties": {
    "iso:country":"US",
    "sg:address":"7037 Benton Dr",
    "sg:city":"Panama City",
    "sg:classifiers":[
        {
            "category":"Travel",
            "subcategory":"Hotels & Motels",
            "type":"Entertainment"
        }
    ],
    "sg:phone":"+1 850 215 7037",
    "sg:postcode":"32404",
    "sg:province":"FL",
    "sg:tags":[
        "operation"
    ],
    "wof:name":"Gulf View Motel",
    "wof:placetype":"venue"
},
  "geometry": {"coordinates":[-85.572366,30.121605],"type":"Point"}
}