{
  "type": "Feature",
  "properties": {
    "addr:full":"445 SW 52nd Ave Ocala FL 34474",
    "addr:housenumber":"445",
    "addr:postcode":"34474",
    "addr:street":"Sw 52Nd Ave",
    "iso:country":"US",
    "sg:address":"445 SW 52nd Ave",
    "sg:city":"Ocala",
    "sg:classifiers":[
        {
            "category":"Wholesale",
            "subcategory":"Medical Equipment & Supplies",
            "type":"Manufacturing & Wholesale Goods"
        },
        {
            "category":"Shopping",
            "subcategory":"Pets & Pet Supplies",
            "type":"Retail Goods"
        },
        {
            "category":"Retail",
            "subcategory":"Veterinary Services",
            "type":"Services"
        }
    ],
    "sg:phone":"+1 352 237 1246",
    "sg:postcode":"34474",
    "sg:province":"FL",
    "sg:tags":[
        "veterinarian",
        "product",
        "health",
        "animal",
        "supply-wholesale"
    ],
    "wof:name":"Butler Animal Health Supply",
    "wof:placetype":"venue"
},
  "geometry": {"coordinates":[-82.206249,29.182579],"type":"Point"}
}