{
  "type": "Feature",
  "properties": {
    "addr:full":"4529 W Irlo Bronson Memorial Hwy Kissimmee FL 34746",
    "addr:housenumber":"4529",
    "addr:postcode":"34746",
    "addr:street":"W Irlo Bronson Memorial Hwy",
    "iso:country":"US",
    "sg:address":"4529 W Irlo Bronson Memorial Hwy",
    "sg:city":"Kissimmee",
    "sg:classifiers":[
        {
            "category":"Travel",
            "subcategory":"Hotels & Motels",
            "type":"Entertainment"
        }
    ],
    "sg:phone":"+1 407 809 4362",
    "sg:postcode":"34746",
    "sg:province":"FL",
    "sg:tags":[
        "hotels-apartment",
        "lodging"
    ],
    "sg:website":"http://dexknows.com",
    "wof:name":"Parkway Motel",
    "wof:placetype":"venue"
},
  "geometry": {"coordinates":[-81.462802,28.305713],"type":"Point"}
}