{
  "type": "Feature",
  "properties": {
    "addr:full":"5438 Bristol Bay Ct Jacksonville FL 32244",
    "addr:housenumber":"5438",
    "addr:postcode":"32244",
    "addr:street":"Bristol Bay Ct",
    "iso:country":"US",
    "sg:address":"5438 Bristol Bay Ct",
    "sg:city":"Jacksonville",
    "sg:classifiers":[
        {
            "category":"Organizations",
            "subcategory":"Religious Organization",
            "type":"Services"
        }
    ],
    "sg:phone":"+1 904 908 5950",
    "sg:postcode":"32244",
    "sg:province":"FL",
    "wof:name":"Berean Ambassadors For Christ",
    "wof:placetype":"venue"
},
  "geometry": {"coordinates":[-81.72066100000001,30.206589],"type":"Point"}
}