{
  "type": "Feature",
  "properties": {
    "iso:country":"US",
    "sg:address":"2706 N E St",
    "sg:city":"Pensacola",
    "sg:classifiers":[
        {
            "category":"Restaurant",
            "type":"Food & Drink"
        }
    ],
    "sg:phone":"+1 850 433 0460",
    "sg:postcode":"32501",
    "sg:province":"FL",
    "wof:name":"Cookin Cousins",
    "wof:placetype":"venue"
},
  "geometry": {"coordinates":[-87.22881599999999,30.440315],"type":"Point"}
}