{
  "type": "Feature",
  "properties": {
    "iso:country":"US",
    "sg:address":"895 Wymore Rd",
    "sg:city":"Altamonte Springs",
    "sg:classifiers":[
        {
            "category":"Professional",
            "subcategory":"Management & Consulting",
            "type":"Services"
        }
    ],
    "sg:phone":"+1 321 377 0548",
    "sg:postcode":"32714",
    "sg:province":"FL",
    "sg:tags":[
        "firm",
        "solution"
    ],
    "wof:name":"Sites and Things LLC",
    "wof:placetype":"venue"
},
  "geometry": {"coordinates":[-81.390236,28.64478],"type":"Point"}
}