{
  "type": "Feature",
  "properties": {
    "addr:full":"425 79th St S Saint Petersburg FL 33707",
    "addr:housenumber":"425",
    "addr:postcode":"33707",
    "addr:street":"79Th St S",
    "iso:country":"US",
    "sg:address":"425 79th St S",
    "sg:city":"Saint Petersburg",
    "sg:classifiers":[
        {
            "category":"Wholesale",
            "subcategory":"Machinery & Supplies",
            "type":"Manufacturing & Wholesale Goods"
        }
    ],
    "sg:phone":"+1 727 522 2572",
    "sg:postcode":"33707",
    "sg:province":"FL",
    "sg:tags":[
        "casket"
    ],
    "wof:name":"Aurora",
    "wof:placetype":"venue"
},
  "geometry": {"coordinates":[-82.747029,27.763096],"type":"Point"}
}