{
  "type": "Feature",
  "properties": {
    "addr:full":"3317 NW 10th Ter Fort Lauderdale FL 33309",
    "addr:housenumber":"3317",
    "addr:postcode":"33309",
    "addr:street":"Nw 10Th Ter",
    "iso:country":"US",
    "sg:address":"3317 NW 10th Ter",
    "sg:city":"Fort Lauderdale",
    "sg:classifiers":[
        {
            "category":"Banks & Credit Unions",
            "subcategory":"Bank",
            "type":"Services"
        }
    ],
    "sg:phone":"+1 954 563 2650",
    "sg:postcode":"33309",
    "sg:province":"FL",
    "sg:tags":[
        "loan",
        "real estate"
    ],
    "sg:website":"www.creditcounselorsofna.com",
    "wof:name":"Credit Counselors-N America",
    "wof:placetype":"venue"
},
  "geometry": {"coordinates":[-80.156741,26.169315],"type":"Point"}
}