{
  "type": "Feature",
  "properties": {
    "addr:full":"130 S Collier Blvd Marco Island FL 34145",
    "addr:housenumber":"130;collier blvd",
    "addr:postcode":"34145",
    "addr:street":"S",
    "iso:country":"US",
    "sg:address":"130 S Collier Blvd",
    "sg:city":"Marco Island",
    "sg:classifiers":[
        {
            "category":"Professional",
            "subcategory":"Detective & Security Services",
            "type":"Services"
        }
    ],
    "sg:phone":"+1 239 394 4260",
    "sg:postcode":"34145",
    "sg:province":"FL",
    "sg:tags":[
        "guard",
        "patrol"
    ],
    "wof:name":"Residents Beach Guard House",
    "wof:placetype":"venue"
},
  "geometry": {"coordinates":[-81.731087,25.935007],"type":"Point"}
}