{
  "type": "Feature",
  "properties": {
    "iso:country":"US",
    "sg:address":"125 Middle St",
    "sg:city":"Lake Mary",
    "sg:classifiers":[
        {
            "category":"Shopping",
            "subcategory":"Computers & Home Electronics",
            "type":"Retail Goods"
        }
    ],
    "sg:phone":"+1 407 321 2686",
    "sg:postcode":"32746",
    "sg:province":"FL",
    "sg:tags":[
        "audio"
    ],
    "wof:name":"Brake Media Inc",
    "wof:placetype":"venue"
},
  "geometry": {"coordinates":[-81.337262,28.755918],"type":"Point"}
}