{
  "type": "Feature",
  "properties": {
    "iso:country":"US",
    "sg:address":"6350 SE Lake Circle Dr",
    "sg:city":"Stuart",
    "sg:classifiers":[
        {
            "category":"Building & Trades",
            "subcategory":"Plumbing",
            "type":"Services"
        }
    ],
    "sg:phone":"+1 772 286 0042",
    "sg:postcode":"34997",
    "sg:province":"FL",
    "sg:tags":[
        "conditioning",
        "contractor",
        "refrigeration",
        "system",
        "air"
    ],
    "wof:name":"Neal's Refrigeration & AC",
    "wof:placetype":"venue"
},
  "geometry": {"coordinates":[-80.25044200000001,27.125304],"type":"Point"}
}