{
  "type": "Feature",
  "properties": {
    "iso:country":"US",
    "sg:address":"5331 NE 2nd Ave",
    "sg:city":"Miami",
    "sg:classifiers":[
        {
            "category":"Health Services",
            "subcategory":"Doctor",
            "type":"Services"
        }
    ],
    "sg:phone":"+1 305 758 7894",
    "sg:postcode":"33137",
    "sg:province":"FL",
    "wof:name":"Victor Jacques A MD",
    "wof:placetype":"venue"
},
  "geometry": {"coordinates":[-80.192001,25.8246],"type":"Point"}
}