{
  "type": "Feature",
  "properties": {
    "iso:country":"US",
    "sg:address":"203 Cloverdale Blvd",
    "sg:city":"Fort Walton Bch",
    "sg:classifiers":[
        {
            "category":"Retail",
            "subcategory":"Animal Services",
            "type":"Services"
        }
    ],
    "sg:phone":"+1 850 862 8798",
    "sg:postcode":"32547",
    "sg:province":"FL",
    "sg:tags":[
        "pet",
        "grooming",
        "washing"
    ],
    "sg:website":"www.abrapet.com",
    "wof:name":"Abracadabra Pet Motel & Groom",
    "wof:placetype":"venue"
},
  "geometry": {"coordinates":[-86.638808,30.451923],"type":"Point"}
}