{
  "type": "Feature",
  "properties": {
    "addr:full":"1424 NW 126th Ave Fort Lauderdale FL 33323",
    "addr:housenumber":"1424",
    "addr:postcode":"33323",
    "addr:street":"Nw 126Th Ave",
    "iso:country":"US",
    "sg:address":"1424 NW 126th Ave",
    "sg:city":"Fort Lauderdale",
    "sg:classifiers":[
        {
            "category":"Banks & Credit Unions",
            "subcategory":"Financial Services",
            "type":"Services"
        }
    ],
    "sg:phone":"+1 954 514 1098",
    "sg:postcode":"33323",
    "sg:province":"FL",
    "sg:tags":[
        "personal",
        "company",
        "holding"
    ],
    "wof:name":"Lakeview Group LLC",
    "wof:placetype":"venue"
},
  "geometry": {"coordinates":[-80.31816999999999,26.140246],"type":"Point"}
}