{
  "type": "Feature",
  "properties": {
    "iso:country":"US",
    "sg:address":"13034 SW 133rd Ct",
    "sg:city":"Miami",
    "sg:phone":"+1 305 232 9449",
    "sg:postcode":"33186",
    "sg:province":"FL",
    "wof:name":"Pegasus Aircraft Parts And Systems, Inc",
    "wof:placetype":"venue"
},
  "geometry": {"coordinates":[-80.410082,25.646324],"type":"Point"}
}