{
  "type": "Feature",
  "properties": {
    "addr:full":"11730 Houle Rd Jacksonville FL 32218",
    "addr:housenumber":"11730",
    "addr:postcode":"32218",
    "addr:street":"Houle Rd",
    "iso:country":"US",
    "sg:address":"11730 Houle Rd",
    "sg:city":"Jacksonville",
    "sg:classifiers":[
        {
            "category":"Retail",
            "subcategory":"Repair Shop",
            "type":"Services"
        }
    ],
    "sg:phone":"+1 904 757 7277",
    "sg:postcode":"32218",
    "sg:province":"FL",
    "wof:name":"Houle Truck Management Center",
    "wof:placetype":"venue"
},
  "geometry": {"coordinates":[-81.614334,30.445672],"type":"Point"}
}