{
  "type": "Feature",
  "properties": {
    "iso:country":"US",
    "sg:address":"3574 W Fairview St",
    "sg:city":"Miami",
    "sg:classifiers":[
        {
            "category":"Manufacturing",
            "subcategory":"Apparel",
            "type":"Manufacturing & Wholesale Goods"
        }
    ],
    "sg:phone":"+1 305 860 5757",
    "sg:postcode":"33133",
    "sg:province":"FL",
    "sg:tags":[
        "bedspread",
        "fabric",
        "drapery",
        "mfg"
    ],
    "wof:name":"Fabin",
    "wof:placetype":"venue"
},
  "geometry": {"coordinates":[-80.220033,25.740387],"type":"Point"}
}