{
  "type": "Feature",
  "properties": {
    "addr:full":"13751 NW 4th St Hollywood FL 33028",
    "addr:housenumber":"13751",
    "addr:postcode":"33028",
    "addr:street":"Nw 4Th St",
    "iso:country":"US",
    "sg:address":"13751 NW 4th St",
    "sg:city":"Hollywood",
    "sg:classifiers":[
        {
            "category":"Shopping",
            "subcategory":"Shoes",
            "type":"Retail Goods"
        }
    ],
    "sg:phone":"+1 954 435 7792",
    "sg:postcode":"33028",
    "sg:province":"FL",
    "wof:name":"Bambini Italian Design Co",
    "wof:placetype":"venue"
},
  "geometry": {"coordinates":[-80.330192,26.010311],"type":"Point"}
}