{
  "type": "Feature",
  "properties": {
    "addr:full":"1000 Douglas Ave Altamonte Spgs FL 32714",
    "addr:housenumber":"1000",
    "addr:postcode":"32714",
    "addr:street":"Douglas Ave;Spgs",
    "iso:country":"US",
    "sg:address":"1000 Douglas Ave",
    "sg:city":"Altamonte Spgs",
    "sg:classifiers":[
        {
            "category":"Building & Trades",
            "subcategory":"Construction",
            "type":"Services"
        }
    ],
    "sg:phone":"+1 407 616 2630",
    "sg:postcode":"32714",
    "sg:province":"FL",
    "sg:tags":[
        "resurfacing",
        "laying",
        "refinishing",
        "floor"
    ],
    "wof:name":"Artistic Construction",
    "wof:placetype":"venue"
},
  "geometry": {"coordinates":[-81.390243,28.685523],"type":"Point"}
}