{
  "type": "Feature",
  "properties": {
    "addr:full":"3763 Estepona Ave Miami FL 33178",
    "addr:housenumber":"3763",
    "addr:postcode":"33178",
    "addr:street":"Estepona Ave",
    "iso:country":"US",
    "sg:address":"3763 Estepona Ave",
    "sg:city":"Miami",
    "sg:classifiers":[
        {
            "category":"Wholesale",
            "subcategory":"Non-durable Goods",
            "type":"Manufacturing & Wholesale Goods"
        }
    ],
    "sg:phone":"+1 305 591 2213",
    "sg:postcode":"33178",
    "sg:province":"FL",
    "wof:name":"Howard Yasgar Properties",
    "wof:placetype":"venue"
},
  "geometry": {"coordinates":[-80.364153,25.808653],"type":"Point"}
}