{
  "type": "Feature",
  "properties": {
    "addr:full":"2290 Wood St Sarasota FL 34237",
    "addr:housenumber":"2290",
    "addr:postcode":"34237",
    "addr:street":"Wood St",
    "iso:country":"US",
    "sg:address":"2290 Wood St",
    "sg:city":"Sarasota",
    "sg:classifiers":[
        {
            "category":"Building & Trades",
            "subcategory":"Construction",
            "type":"Services"
        }
    ],
    "sg:phone":"+1 941 951 9090",
    "sg:postcode":"34237",
    "sg:province":"FL",
    "sg:tags":[
        "resurfacing",
        "laying",
        "refinishing",
        "floor"
    ],
    "wof:name":"Master's Newlife Inc",
    "wof:placetype":"venue"
},
  "geometry": {"coordinates":[-82.525477,27.328612],"type":"Point"}
}