{
  "type": "Feature",
  "properties": {
    "addr:full":"201 Grove St N Venice FL 34285",
    "addr:housenumber":"201",
    "addr:postcode":"34285",
    "addr:street":"Grove St N",
    "iso:country":"US",
    "sg:address":"201 Grove St N",
    "sg:city":"Venice",
    "sg:classifiers":[
        {
            "category":"Real Estate",
            "subcategory":"Real Estate Agent",
            "type":"Services"
        }
    ],
    "sg:phone":"+1 941 486 0319",
    "sg:postcode":"34285",
    "sg:province":"FL",
    "sg:tags":[
        "authorities",
        "housing"
    ],
    "wof:name":"Venice Housing Authority",
    "wof:placetype":"venue"
},
  "geometry": {"coordinates":[-82.435284,27.100828],"type":"Point"}
}