{
  "type": "Feature",
  "properties": {
    "addr:full":"1017 N Palafox St Pensacola FL 32501",
    "addr:housenumber":"1017",
    "addr:postcode":"32501",
    "addr:street":"N Palafox St",
    "iso:country":"US",
    "sg:address":"1017 N Palafox St",
    "sg:city":"Pensacola",
    "sg:classifiers":[
        {
            "category":"Shopping",
            "subcategory":"Used Merchandise",
            "type":"Retail Goods"
        }
    ],
    "sg:phone":"+1 850 436 4958",
    "sg:postcode":"32501",
    "sg:province":"FL",
    "sg:tags":[
        "resale",
        "shop",
        "antique"
    ],
    "wof:name":"Pots N' Kettles",
    "wof:placetype":"venue"
},
  "geometry": {"coordinates":[-87.217817,30.423381],"type":"Point"}
}