{
  "type": "Feature",
  "properties": {
    "iso:country":"US",
    "sg:address":"44 W 16th St",
    "sg:city":"Jacksonville",
    "sg:classifiers":[
        {
            "category":"Building & Trades",
            "subcategory":"Plumbing",
            "type":"Services"
        }
    ],
    "sg:phone":"+1 904 355 6630",
    "sg:postcode":"32206",
    "sg:province":"FL",
    "sg:tags":[
        "contractor"
    ],
    "wof:name":"4 Star Plumbing Co Inc",
    "wof:placetype":"venue"
},
  "geometry": {"coordinates":[-81.655019,30.353486],"type":"Point"}
}