{
  "type": "Feature",
  "properties": {
    "iso:country":"US",
    "sg:address":"1500 SE 3rd Ct",
    "sg:city":"Deerfield Beach",
    "sg:classifiers":[
        {
            "category":"Freight",
            "type":"Transportation"
        }
    ],
    "sg:phone":"+1 954 427 6060",
    "sg:postcode":"33441",
    "sg:province":"FL",
    "sg:tags":[
        "commercial",
        "storage"
    ],
    "wof:name":"Cove Executive Building",
    "wof:placetype":"venue"
},
  "geometry": {"coordinates":[-80.084901,26.313582],"type":"Point"}
}