{
  "type": "Feature",
  "properties": {
    "addr:full":"516 E Osceola Pkwy Kissimmee FL 34744",
    "addr:housenumber":"516",
    "addr:postcode":"34744",
    "addr:street":"E Osceola Pkwy",
    "iso:country":"US",
    "sg:address":"516 E Osceola Pkwy",
    "sg:city":"Kissimmee",
    "sg:classifiers":[
        {
            "category":"Autos & Motor Vehicles",
            "subcategory":"Automobile Sales",
            "type":"Retail Goods"
        },
        {
            "category":"Autos & Motor Vehicles",
            "subcategory":"Auto Supplies",
            "type":"Retail Goods"
        }
    ],
    "sg:phone":"+1 407 933 7793",
    "sg:postcode":"34744",
    "sg:province":"FL",
    "sg:tags":[
        "air conditioning",
        "equipment",
        "tire"
    ],
    "wof:name":"Tire Outlet",
    "wof:placetype":"venue"
},
  "geometry": {"coordinates":[-81.396244,28.338137],"type":"Point"}
}