{
  "type": "Feature",
  "properties": {
    "iso:country":"US",
    "sg:address":"4261 NW 36th Ave",
    "sg:city":"Miami",
    "sg:classifiers":[
        {
            "category":"Wholesale",
            "subcategory":"Auto Parts",
            "type":"Manufacturing & Wholesale Goods"
        }
    ],
    "sg:phone":"+1 305 633 5363",
    "sg:postcode":"33142",
    "sg:province":"FL",
    "sg:tags":[
        "automobile",
        "rebuilt"
    ],
    "wof:name":"BPI Intl",
    "wof:placetype":"venue"
},
  "geometry": {"coordinates":[-80.254519,25.812606],"type":"Point"}
}