{
  "type": "Feature",
  "properties": {
    "addr:full":"5205 37th St N Saint Petersburg FL 33714",
    "addr:housenumber":"5205",
    "addr:postcode":"33714",
    "addr:street":"37Th St N",
    "iso:country":"US",
    "sg:address":"5205 37th St N",
    "sg:city":"Saint Petersburg",
    "sg:classifiers":[
        {
            "category":"Building & Trades",
            "subcategory":"Landscaping Services",
            "type":"Services"
        }
    ],
    "sg:phone":"+1 727 527 2864",
    "sg:postcode":"33714",
    "sg:province":"FL",
    "wof:name":"Scott & Kims Lawn Service",
    "wof:placetype":"venue"
},
  "geometry": {"coordinates":[-82.683499,27.820122],"type":"Point"}
}