{
  "type": "Feature",
  "properties": {
    "addr:full":"9240 N Cedar Cove Rd Dunnellon FL 34434",
    "addr:housenumber":"9240",
    "addr:postcode":"34434",
    "addr:street":"N Cedar Cove Rd",
    "iso:country":"US",
    "sg:address":"9240 N Cedar Cove Rd",
    "sg:city":"Dunnellon",
    "sg:classifiers":[
        {
            "category":"Shopping",
            "subcategory":"Catalog Store",
            "type":"Retail Goods"
        }
    ],
    "sg:phone":"+1 352 341 0468",
    "sg:postcode":"34434",
    "sg:province":"FL",
    "sg:tags":[
        "mail",
        "house"
    ],
    "wof:name":"Lowes World of Products",
    "wof:placetype":"venue"
},
  "geometry": {"coordinates":[-82.37118599999999,28.998185],"type":"Point"}
}