{
  "type": "Feature",
  "properties": {
    "addr:full":"305 W 68th St Apt 503 Hialeah FL 33014",
    "addr:housenumber":"305;503",
    "addr:postcode":"33014",
    "addr:street":"W 68Th St Apt",
    "iso:country":"US",
    "sg:address":"305 W 68th St Apt 503",
    "sg:city":"Hialeah",
    "sg:classifiers":[
        {
            "category":"Professional",
            "type":"Services"
        }
    ],
    "sg:phone":"+1 305 512 4437",
    "sg:postcode":"33014",
    "sg:province":"FL",
    "sg:tags":[
        "motion",
        "picture",
        "technician"
    ],
    "wof:name":"Elaine Systems Inc",
    "wof:placetype":"venue"
},
  "geometry": {"coordinates":[-80.289441,25.884375],"type":"Point"}
}