{
  "type": "Feature",
  "properties": {
    "addr:full":"774 21st St Vero Beach FL 32960",
    "addr:housenumber":"774",
    "addr:postcode":"32960",
    "addr:street":"21St St",
    "iso:country":"US",
    "sg:address":"774 21st St",
    "sg:city":"Vero Beach",
    "sg:classifiers":[
        {
            "category":"Restaurant",
            "type":"Food & Drink"
        }
    ],
    "sg:phone":"+1 772 562 9170",
    "sg:postcode":"32960",
    "sg:province":"FL",
    "sg:tags":[
        "delicatessen",
        "eating"
    ],
    "wof:name":"Giordanos Italian Deli Inc",
    "wof:placetype":"venue"
},
  "geometry": {"coordinates":[-80.388796,27.639846],"type":"Point"}
}