{
  "type": "Feature",
  "properties": {
    "addr:full":"14630 SE 93rd Ave Summerfield FL 34491",
    "addr:postcode":"14630;34491",
    "addr:street":"Se 93Rd Ave",
    "iso:country":"US",
    "sg:address":"14630 SE 93rd Ave",
    "sg:city":"Summerfield",
    "sg:classifiers":[
        {
            "category":"Shopping",
            "subcategory":"Computers & Home Electronics",
            "type":"Retail Goods"
        }
    ],
    "sg:phone":"+1 352 245 4381",
    "sg:postcode":"34491",
    "sg:province":"FL",
    "sg:tags":[
        "equipment",
        "electronic",
        "supply"
    ],
    "wof:name":"Newsom Electronics",
    "wof:placetype":"venue"
},
  "geometry": {"coordinates":[-81.999059,29.008014],"type":"Point"}
}