{
  "type": "Feature",
  "properties": {
    "iso:country":"US",
    "sg:address":"1491 2nd St",
    "sg:city":"Sarasota",
    "sg:classifiers":[
        {
            "category":"Professional",
            "subcategory":"Engineering",
            "type":"Services"
        }
    ],
    "sg:phone":"+1 941 954 0681",
    "sg:postcode":"34236",
    "sg:province":"FL",
    "sg:tags":[
        "engineer"
    ],
    "wof:name":"Snell Engineering Consultants",
    "wof:placetype":"venue"
},
  "geometry": {"coordinates":[-82.54230800000001,27.338129],"type":"Point"}
}