{
  "type": "Feature",
  "properties": {
    "iso:country":"US",
    "sg:address":"4701 S 50th St",
    "sg:city":"Tampa",
    "sg:classifiers":[
        {
            "category":"Manufacturing",
            "subcategory":"Toys & Sporting Goods",
            "type":"Manufacturing & Wholesale Goods"
        }
    ],
    "sg:phone":"+1 813 247 2812",
    "sg:postcode":"33619",
    "sg:province":"FL",
    "sg:tags":[
        "equipment",
        "playground"
    ],
    "wof:name":"Florida Playground & Steel Co",
    "wof:placetype":"venue"
},
  "geometry": {"coordinates":[-82.401884,27.904153],"type":"Point"}
}