{
  "type": "Feature",
  "properties": {
    "addr:full":"2000 Biscayne Blvd Ste 2008 Miami FL 33137",
    "addr:housenumber":"2000",
    "addr:postcode":"33137",
    "addr:street":"Biscayne Blvd Ste 2008",
    "iso:country":"US",
    "sg:address":"2000 Biscayne Blvd Ste 2008",
    "sg:city":"Miami",
    "sg:classifiers":[
        {
            "category":"Shopping",
            "subcategory":"Clothing, Apparel, & Fashions",
            "type":"Retail Goods"
        }
    ],
    "sg:phone":"+1 305 333 8992",
    "sg:postcode":"33137",
    "sg:province":"FL",
    "sg:tags":[
        "accessory",
        "clothing",
        "women's"
    ],
    "sg:website":"www.deeversus.com",
    "wof:name":"Deeversus Fashion",
    "wof:placetype":"venue"
},
  "geometry": {"coordinates":[-80.189646,25.795608],"type":"Point"}
}