{
  "type": "Feature",
  "properties": {
    "iso:country":"US",
    "sg:address":"2132 US Hwy 90",
    "sg:city":"Defuniak Springs",
    "sg:classifiers":[
        {
            "category":"Organizations",
            "subcategory":"Religious Organization",
            "type":"Services"
        }
    ],
    "sg:phone":"+1 850 892 0582",
    "sg:postcode":"32433",
    "sg:province":"FL",
    "sg:tags":[
        "church"
    ],
    "wof:name":"Continental Worship Ctr",
    "wof:placetype":"venue"
},
  "geometry": {"coordinates":[-86.087084,30.727365],"type":"Point"}
}