{
  "type": "Feature",
  "properties": {
    "iso:country":"US",
    "sg:address":"15 SW 55th Avenue Rd",
    "sg:city":"Miami",
    "sg:classifiers":[
        {
            "category":"Wholesale",
            "subcategory":"Non-durable Goods",
            "type":"Manufacturing & Wholesale Goods"
        }
    ],
    "sg:phone":"+1 305 260 0400",
    "sg:postcode":"33134",
    "sg:province":"FL",
    "wof:name":"Belle-Mings Design",
    "wof:placetype":"venue"
},
  "geometry": {"coordinates":[-80.285082,25.770066],"type":"Point"}
}