{
  "type": "Feature",
  "properties": {
    "iso:country":"US",
    "sg:address":"25805 Belle Helene",
    "sg:city":"Leesburg",
    "sg:classifiers":[
        {
            "category":"Building & Trades",
            "subcategory":"Construction",
            "type":"Services"
        }
    ],
    "sg:phone":"+1 352 728 1556",
    "sg:postcode":"34748",
    "sg:province":"FL",
    "sg:tags":[
        "general",
        "contractor"
    ],
    "wof:name":"Casablanka Contractors Inc",
    "wof:placetype":"venue"
},
  "geometry": {"coordinates":[-81.877075,28.721792],"type":"Point"}
}