{
  "type": "Feature",
  "properties": {
    "iso:country":"US",
    "sg:address":"11211 N Nebraska Ave",
    "sg:city":"Tampa",
    "sg:classifiers":[
        {
            "category":"Organizations",
            "subcategory":"Professional Association",
            "type":"Services"
        }
    ],
    "sg:phone":"+1 813 932 8566",
    "sg:postcode":"33612",
    "sg:province":"FL",
    "sg:tags":[
        "business"
    ],
    "wof:name":"Nmeda",
    "wof:placetype":"venue"
},
  "geometry": {"coordinates":[-82.451104,28.050501],"type":"Point"}
}