{
  "type": "Feature",
  "properties": {
    "iso:country":"US",
    "sg:address":"2620 Marble Ave",
    "sg:city":"Orlando",
    "sg:classifiers":[
        {
            "category":"Building & Trades",
            "subcategory":"Electrical",
            "type":"Services"
        }
    ],
    "sg:phone":"+1 407 895 5585",
    "sg:postcode":"32803",
    "sg:province":"FL",
    "sg:tags":[
        "electrical",
        "contractor"
    ],
    "wof:name":"Electric Ride",
    "wof:placetype":"venue"
},
  "geometry": {"coordinates":[-81.347387,28.568779],"type":"Point"}
}