{
  "type": "Feature",
  "properties": {
    "addr:full":"1518 Sunset Village Blvd Clermont FL 34711",
    "addr:housenumber":"1518",
    "addr:postcode":"34711",
    "addr:street":"Sunset Village Blvd",
    "iso:country":"US",
    "sg:address":"1518 Sunset Village Blvd",
    "sg:city":"Clermont",
    "sg:classifiers":[
        {
            "category":"Professional",
            "subcategory":"Art Services",
            "type":"Services"
        }
    ],
    "sg:phone":"+1 352 243 2257",
    "sg:postcode":"34711",
    "sg:province":"FL",
    "sg:tags":[
        "designer",
        "display",
        "producer"
    ],
    "wof:name":"Mvh Motion",
    "wof:placetype":"venue"
},
  "geometry": {"coordinates":[-81.729944,28.55871],"type":"Point"}
}