{
  "type": "Feature",
  "properties": {
    "iso:country":"US",
    "sg:address":"1660 Barrett Dr",
    "sg:city":"Rockledge",
    "sg:classifiers":[
        {
            "category":"Building & Trades",
            "subcategory":"Plumbing",
            "type":"Services"
        }
    ],
    "sg:phone":"+1 321 636 5060",
    "sg:postcode":"32955",
    "sg:province":"FL",
    "sg:tags":[
        "fire",
        "r",
        "protection",
        "contractor"
    ],
    "wof:name":"Southern Fire Systems Inc",
    "wof:placetype":"venue"
},
  "geometry": {"coordinates":[-80.733914,28.328471],"type":"Point"}
}