{
  "type": "Feature",
  "properties": {
    "iso:country":"US",
    "sg:address":"271 N Shore Dr",
    "sg:city":"Miami Beach",
    "sg:classifiers":[
        {
            "category":"Professional",
            "subcategory":"Management & Consulting",
            "type":"Services"
        }
    ],
    "sg:phone":"+1 305 861 3397",
    "sg:postcode":"33141",
    "sg:province":"FL",
    "sg:tags":[
        "fuel"
    ],
    "wof:name":"Glitsos Management Co",
    "wof:placetype":"venue"
},
  "geometry": {"coordinates":[-80.13457699999999,25.860953],"type":"Point"}
}