{
  "type": "Feature",
  "properties": {
    "addr:full":"1080 NW 54th St Miami FL 33127",
    "addr:housenumber":"1080",
    "addr:postcode":"33127",
    "addr:street":"Nw 54Th St",
    "iso:country":"US",
    "sg:address":"1080 NW 54th St",
    "sg:city":"Miami",
    "sg:classifiers":[
        {
            "category":"Food & Beverages",
            "subcategory":"Groceries & Convenience Stores",
            "type":"Retail Goods"
        }
    ],
    "sg:phone":"+1 305 751 6828",
    "sg:postcode":"33127",
    "sg:province":"FL",
    "sg:tags":[
        "grocer"
    ],
    "wof:name":"S & S Supermarket",
    "wof:placetype":"venue"
},
  "geometry": {"coordinates":[-80.212738,25.824729],"type":"Point"}
}