{
  "type": "Feature",
  "properties": {
    "iso:country":"US",
    "sg:address":"12036 SW 132nd Ct",
    "sg:city":"Miami",
    "sg:classifiers":[
        {
            "category":"Real Estate",
            "subcategory":"Real Estate Agent",
            "type":"Services"
        }
    ],
    "sg:phone":"+1 305 971 0500",
    "sg:postcode":"33186",
    "sg:province":"FL",
    "wof:name":"Centrex Realty",
    "wof:placetype":"venue"
},
  "geometry": {"coordinates":[-80.40864000000001,25.65541],"type":"Point"}
}