{
  "type": "Feature",
  "properties": {
    "addr:full":"910 S 8th St Fernandina Beach FL 32034",
    "addr:housenumber":"910",
    "addr:postcode":"32034",
    "addr:street":"S 8Th St",
    "iso:country":"US",
    "sg:address":"910 S 8th St",
    "sg:city":"Fernandina Beach",
    "sg:classifiers":[
        {
            "category":"Organizations",
            "subcategory":"Professional Association",
            "type":"Services"
        }
    ],
    "sg:phone":"+1 904 261 1779",
    "sg:postcode":"32034",
    "sg:province":"FL",
    "wof:name":"Amelia Island Chamber Music",
    "wof:placetype":"venue"
},
  "geometry": {"coordinates":[-81.460472,30.659257],"type":"Point"}
}