{
  "type": "Feature",
  "properties": {
    "addr:full":"13716 SW 145th Ct Miami FL 33186",
    "addr:housenumber":"13716",
    "addr:postcode":"33186",
    "addr:street":"Sw 145Th Ct",
    "iso:country":"US",
    "sg:address":"13716 SW 145th Ct",
    "sg:city":"Miami",
    "sg:classifiers":[
        {
            "category":"Banks & Credit Unions",
            "subcategory":"Bank",
            "type":"Services"
        }
    ],
    "sg:phone":"+1 786 295 1545",
    "sg:postcode":"33186",
    "sg:province":"FL",
    "wof:name":"International Data Systems Usa",
    "wof:placetype":"venue"
},
  "geometry": {"coordinates":[-80.429999,25.638409],"type":"Point"}
}