{
  "type": "Feature",
  "properties": {
    "iso:country":"US",
    "sg:address":"1146 Winter Green St",
    "sg:city":"Lake Placid",
    "sg:classifiers":[
        {
            "category":"Building & Trades",
            "subcategory":"Construction",
            "type":"Services"
        }
    ],
    "sg:phone":"+1 863 465 4012",
    "sg:postcode":"33852",
    "sg:province":"FL",
    "sg:tags":[
        "contractor"
    ],
    "wof:name":"Dragon Drywall Inc",
    "wof:placetype":"venue"
},
  "geometry": {"coordinates":[-81.417948,27.345823],"type":"Point"}
}