{
  "type": "Feature",
  "properties": {
    "iso:country":"US",
    "sg:address":"2343 NE 8th Rd",
    "sg:city":"Ocala",
    "sg:classifiers":[
        {
            "category":"Personal",
            "subcategory":"Beauty Salon",
            "type":"Services"
        }
    ],
    "sg:phone":"+1 352 351 1616",
    "sg:postcode":"34470",
    "sg:province":"FL",
    "sg:tags":[
        "shop"
    ],
    "wof:name":"Debbie's Shear Magic",
    "wof:placetype":"venue"
},
  "geometry": {"coordinates":[-82.128004,29.207965],"type":"Point"}
}