{
  "type": "Feature",
  "properties": {
    "iso:country":"US",
    "sg:address":"101 S Franklin St",
    "sg:city":"Tampa",
    "sg:classifiers":[
        {
            "category":"Professional",
            "subcategory":"Lawyer & Legal Services",
            "type":"Services"
        }
    ],
    "sg:phone":"+1 813 276 0999",
    "sg:postcode":"33602",
    "sg:province":"FL",
    "sg:tags":[
        "attorney"
    ],
    "wof:name":"Isom A Woodson Jr PA",
    "wof:placetype":"venue"
},
  "geometry": {"coordinates":[-82.456209,27.943744],"type":"Point"}
}