{
  "type": "Feature",
  "properties": {
    "iso:country":"US",
    "sg:address":"308 Saint Clair St",
    "sg:city":"Starke",
    "sg:classifiers":[
        {
            "category":"Farming",
            "subcategory":"Farm & Veterinary Services",
            "type":"Manufacturing & Wholesale Goods"
        }
    ],
    "sg:phone":"+1 904 964 4735",
    "sg:postcode":"32091",
    "sg:province":"FL",
    "sg:tags":[
        "preparation",
        "soil"
    ],
    "wof:name":"All Terrain Geotechnical Inc",
    "wof:placetype":"venue"
},
  "geometry": {"coordinates":[-82.10493,29.94436],"type":"Point"}
}