{
  "type": "Feature",
  "properties": {
    "addr:full":"3251 NE Co Rd 343 Bronson FL 32621",
    "addr:housenumber":"3251;343",
    "addr:postcode":"32621",
    "addr:street":"Ne Co Rd",
    "iso:country":"US",
    "sg:address":"3251 NE Co Rd 343",
    "sg:city":"Bronson",
    "sg:classifiers":[
        {
            "category":"Building & Trades",
            "subcategory":"Landscaping Services",
            "type":"Services"
        }
    ],
    "sg:phone":"+1 352 486 2369",
    "sg:postcode":"32621",
    "sg:province":"FL",
    "sg:tags":[
        "sod",
        "sodding"
    ],
    "wof:name":"DEC Sod",
    "wof:placetype":"venue"
},
  "geometry": {"coordinates":[-82.63732899999999,29.37137],"type":"Point"}
}