{
  "type": "Feature",
  "properties": {
    "iso:country":"US",
    "sg:address":"2775 NW 46th St",
    "sg:city":"Miami",
    "sg:classifiers":[
        {
            "category":"Social Services",
            "subcategory":"Child Care",
            "type":"Services"
        }
    ],
    "sg:phone":"+1 305 637 7799",
    "sg:postcode":"33142",
    "sg:province":"FL",
    "sg:tags":[
        "day"
    ],
    "wof:name":"Vickie's Learning Center",
    "wof:placetype":"venue"
},
  "geometry": {"coordinates":[-80.240601,25.8165],"type":"Point"}
}