{
  "type": "Feature",
  "properties": {
    "iso:country":"US",
    "sg:address":"8387 Warbler Rd",
    "sg:city":"Brooksville",
    "sg:classifiers":[
        {
            "category":"Building & Trades",
            "subcategory":"Construction",
            "type":"Services"
        }
    ],
    "sg:phone":"+1 352 596 9961",
    "sg:postcode":"34613",
    "sg:province":"FL",
    "sg:tags":[
        "contractor"
    ],
    "wof:name":"Scott D Gorton",
    "wof:placetype":"venue"
},
  "geometry": {"coordinates":[-82.551112,28.551333],"type":"Point"}
}