{
  "type": "Feature",
  "properties": {
    "iso:country":"US",
    "sg:address":"689 Bay Esplanade",
    "sg:city":"Clearwater",
    "sg:classifiers":[
        {
            "category":"Travel",
            "subcategory":"Hotels & Motels",
            "type":"Entertainment"
        }
    ],
    "sg:phone":"+1 727 449 0385",
    "sg:postcode":"33767",
    "sg:province":"FL",
    "wof:name":"Waters Edge Motel",
    "wof:placetype":"venue"
},
  "geometry": {"coordinates":[-82.825265,27.987708],"type":"Point"}
}