{
  "type": "Feature",
  "properties": {
    "addr:full":"3905 3rd St E Lehigh Acres FL 33972",
    "addr:housenumber":"3905",
    "addr:postcode":"33972",
    "addr:street":"3Rd St E",
    "iso:country":"US",
    "sg:address":"3905 3rd St E",
    "sg:city":"Lehigh Acres",
    "sg:classifiers":[
        {
            "category":"Building & Trades",
            "subcategory":"Construction",
            "type":"Services"
        }
    ],
    "sg:phone":"+1 239 369 0238",
    "sg:postcode":"33972",
    "sg:province":"FL",
    "sg:tags":[
        "house"
    ],
    "wof:name":"Brick Homes By Don White",
    "wof:placetype":"venue"
},
  "geometry": {"coordinates":[-81.575565,26.610737],"type":"Point"}
}