{
  "type": "Feature",
  "properties": {
    "addr:full":"2415 Ponce De Leon Blvd Miami FL 33134",
    "addr:housenumber":"2415",
    "addr:postcode":"33134",
    "addr:street":"Ponce De Leon Blvd",
    "iso:country":"US",
    "sg:address":"2415 Ponce De Leon Blvd",
    "sg:city":"Miami",
    "sg:classifiers":[
        {
            "category":"Restaurant",
            "type":"Food & Drink"
        }
    ],
    "sg:menulink":"http://www.allmenus.com/fl/miami/241535-les-halles-brasserie/menu/",
    "sg:phone":"+1 305 461 1099",
    "sg:postcode":"33134",
    "sg:province":"FL",
    "sg:tags":[
        "french"
    ],
    "wof:name":"Les Halles Brasserie",
    "wof:placetype":"venue"
},
  "geometry": {"coordinates":[-80.25827099999999,25.749009],"type":"Point"}
}