{
  "type": "Feature",
  "properties": {
    "addr:full":"2241 NW 251st St Lawtey FL 32058",
    "addr:housenumber":"2241",
    "addr:postcode":"32058",
    "addr:street":"Nw 251St St",
    "iso:country":"US",
    "sg:address":"2241 NW 251st St",
    "sg:city":"Lawtey",
    "sg:classifiers":[
        {
            "category":"Building & Trades",
            "subcategory":"Plumbing",
            "type":"Services"
        }
    ],
    "sg:phone":"+1 904 782 3293",
    "sg:postcode":"32058",
    "sg:province":"FL",
    "sg:tags":[
        "contractor"
    ],
    "wof:name":"Helmlinger Htg Air",
    "wof:placetype":"venue"
},
  "geometry": {"coordinates":[-82.07031000000001,30.081329],"type":"Point"}
}