{
  "type": "Feature",
  "properties": {
    "addr:full":"15675 McGregor Blvd Ste 8 Fort Myers FL 33908",
    "addr:housenumber":"15675",
    "addr:postcode":"myers fl 33908",
    "addr:street":"Mcgregor Blvd Ste 8",
    "iso:country":"US",
    "sg:address":"15675 McGregor Blvd Ste 8",
    "sg:city":"Fort Myers",
    "sg:classifiers":[
        {
            "category":"Personal",
            "subcategory":"Nail Salon",
            "type":"Services"
        }
    ],
    "sg:phone":"+1 239 482 8080",
    "sg:postcode":"33908",
    "sg:province":"FL",
    "wof:name":"Upper Cut Hair Designers of Lee Co Inc",
    "wof:placetype":"venue"
},
  "geometry": {"coordinates":[-81.94909699999999,26.514099],"type":"Point"}
}