{
  "type": "Feature",
  "properties": {
    "iso:country":"US",
    "sg:address":"845 N Garland Ave",
    "sg:city":"Orlando",
    "sg:classifiers":[
        {
            "category":"Real Estate",
            "subcategory":"Real Estate Services",
            "type":"Services"
        }
    ],
    "sg:phone":"+1 407 246 5253",
    "sg:postcode":"32801",
    "sg:province":"FL",
    "sg:tags":[
        "company",
        "title"
    ],
    "wof:name":"Kurt F Brewer",
    "wof:placetype":"venue"
},
  "geometry": {"coordinates":[-81.381592,28.554062],"type":"Point"}
}