{
  "type": "Feature",
  "properties": {
    "addr:full":"10825 SW Green Ridge Ln Palm City FL 34990",
    "addr:housenumber":"10825",
    "addr:postcode":"34990",
    "addr:street":"Sw Green Ridge Ln",
    "iso:country":"US",
    "sg:address":"10825 SW Green Ridge Ln",
    "sg:city":"Palm City",
    "sg:classifiers":[
        {
            "category":"Retail",
            "subcategory":"Animal Services",
            "type":"Services"
        }
    ],
    "sg:phone":"+1 772 286 8868",
    "sg:postcode":"34990",
    "sg:province":"FL",
    "wof:name":"Mystique Arabian Stud Inc",
    "wof:placetype":"venue"
},
  "geometry": {"coordinates":[-80.31422000000001,27.074705],"type":"Point"}
}