{
  "type": "Feature",
  "properties": {
    "iso:country":"US",
    "sg:address":"7910 Southwind Ct",
    "sg:city":"Orlando",
    "sg:classifiers":[
        {
            "category":"Home & Garden",
            "subcategory":"Furniture",
            "type":"Retail Goods"
        }
    ],
    "sg:phone":"+1 407 909 1669",
    "sg:postcode":"32819",
    "sg:province":"FL",
    "sg:tags":[
        "cabinet"
    ],
    "wof:name":"Victor Blackburn Cabinets",
    "wof:placetype":"venue"
},
  "geometry": {"coordinates":[-81.50412,28.450621],"type":"Point"}
}