{
  "type": "Feature",
  "properties": {
    "iso:country":"US",
    "sg:address":"5703 N Florida Ave",
    "sg:city":"Tampa",
    "sg:classifiers":[
        {
            "category":"Autos & Motor Vehicles",
            "subcategory":"Automobile Sales",
            "type":"Retail Goods"
        }
    ],
    "sg:phone":"+1 813 231 3340",
    "sg:postcode":"33604",
    "sg:province":"FL",
    "sg:tags":[
        "dealers-used",
        "car",
        "used",
        "cars-wholesale",
        "new"
    ],
    "wof:name":"B & A Auto Sales",
    "wof:placetype":"venue"
},
  "geometry": {"coordinates":[-82.459457,27.998779],"type":"Point"}
}