{
  "type": "Feature",
  "properties": {
    "iso:country":"US",
    "sg:address":"14838 Military Trl",
    "sg:city":"Delray Beach",
    "sg:classifiers":[
        {
            "category":"Health Services",
            "subcategory":"Health Practitioner",
            "type":"Services"
        }
    ],
    "sg:phone":"+1 561 865 3370",
    "sg:postcode":"33484",
    "sg:province":"FL",
    "sg:tags":[
        "therapist",
        "physical"
    ],
    "wof:name":"Aim Rehab Systems",
    "wof:placetype":"venue"
},
  "geometry": {"coordinates":[-80.122439,26.45715],"type":"Point"}
}