{
  "type": "Feature",
  "properties": {
    "iso:country":"US",
    "sg:address":"6160 N Davis Hwy",
    "sg:city":"Pensacola",
    "sg:classifiers":[
        {
            "category":"Health Services",
            "subcategory":"Doctor",
            "type":"Services"
        }
    ],
    "sg:phone":"+1 850 994 0927",
    "sg:postcode":"32503",
    "sg:province":"FL",
    "sg:tags":[
        "physician",
        "surgeon"
    ],
    "wof:name":"Frank J Castagna MD",
    "wof:placetype":"venue"
},
  "geometry": {"coordinates":[-87.222712,30.484274],"type":"Point"}
}