{
  "type": "Feature",
  "properties": {
    "addr:full":"355 Spring Lake Hills Dr Altamonte Springs FL 32714",
    "addr:housenumber":"355",
    "addr:postcode":"32714",
    "addr:street":"Spring;Hills Dr",
    "iso:country":"US",
    "sg:address":"355 Spring Lake Hills Dr",
    "sg:city":"Altamonte Springs",
    "sg:classifiers":[
        {
            "category":"Food & Beverages",
            "subcategory":"Specialty",
            "type":"Retail Goods"
        }
    ],
    "sg:phone":"+1 407 786 9439",
    "sg:postcode":"32714",
    "sg:province":"FL",
    "wof:name":"Herbal Consultants",
    "wof:placetype":"venue"
},
  "geometry": {"coordinates":[-81.397493,28.644112],"type":"Point"}
}