{
  "type": "Feature",
  "properties": {
    "addr:full":"144 E 23rd St Panama City FL 32405",
    "addr:housenumber":"144",
    "addr:postcode":"32405",
    "addr:street":"E 23Rd St",
    "iso:country":"US",
    "sg:address":"144 E 23rd St",
    "sg:city":"Panama City",
    "sg:classifiers":[
        {
            "category":"Restaurant",
            "type":"Food & Drink"
        }
    ],
    "sg:phone":"+1 850 763 3611",
    "sg:postcode":"32405",
    "sg:province":"FL",
    "wof:name":"Ryans",
    "wof:placetype":"venue"
},
  "geometry": {"coordinates":[-85.654646,30.1895],"type":"Point"}
}