{
  "type": "Feature",
  "properties": {
    "iso:country":"US",
    "sg:address":"8535 Baymeadows Rd",
    "sg:city":"Jacksonville",
    "sg:classifiers":[
        {
            "category":"Building & Trades",
            "subcategory":"Construction",
            "type":"Services"
        }
    ],
    "sg:phone":"+1 904 730 5135",
    "sg:postcode":"32256",
    "sg:province":"FL",
    "sg:tags":[
        "general",
        "contractor"
    ],
    "wof:name":"C Young Construction LLC",
    "wof:placetype":"venue"
},
  "geometry": {"coordinates":[-81.57898400000001,30.220875],"type":"Point"}
}