{
  "type": "Feature",
  "properties": {
    "iso:country":"US",
    "sg:address":"20412 NE 15th Ct",
    "sg:city":"Miami",
    "sg:classifiers":[
        {
            "category":"Wholesale",
            "subcategory":"Non-durable Goods",
            "type":"Manufacturing & Wholesale Goods"
        }
    ],
    "sg:phone":"+1 305 652 1535",
    "sg:postcode":"33179",
    "sg:province":"FL",
    "sg:tags":[
        "novelty",
        "gift",
        "merchandise",
        "general"
    ],
    "sg:website":"www.furad.com",
    "wof:name":"Furad Industries Inc",
    "wof:placetype":"venue"
},
  "geometry": {"coordinates":[-80.171114,25.959574],"type":"Point"}
}