{
  "type": "Feature",
  "properties": {
    "iso:country":"US",
    "sg:address":"100 73rd St",
    "sg:city":"Bradenton Beach",
    "sg:classifiers":[
        {
            "category":"Professional",
            "subcategory":"Management & Consulting",
            "type":"Services"
        }
    ],
    "sg:phone":"+1 941 778 2277",
    "sg:postcode":"34217",
    "sg:province":"FL",
    "sg:tags":[
        "operation"
    ],
    "wof:name":"Coconuts Resorts MGT Prpts",
    "wof:placetype":"venue"
},
  "geometry": {"coordinates":[-82.72478099999999,27.516083],"type":"Point"}
}