{
  "type": "Feature",
  "properties": {
    "iso:country":"US",
    "sg:address":"115 Margaret St",
    "sg:city":"Brandon",
    "sg:classifiers":[
        {
            "category":"Banks & Credit Unions",
            "subcategory":"Bank",
            "type":"Services"
        }
    ],
    "sg:phone":"+1 813 655 0407",
    "sg:postcode":"33511",
    "sg:province":"FL",
    "sg:tags":[
        "banker"
    ],
    "wof:name":"C U Mortgage Services Inc",
    "wof:placetype":"venue"
},
  "geometry": {"coordinates":[-82.28221499999999,27.936764],"type":"Point"}
}