{
  "type": "Feature",
  "properties": {
    "addr:full":"930 Mason Ct Daytona Beach FL 32117",
    "addr:housenumber":"930",
    "addr:postcode":"32117",
    "addr:street":"Mason Ct",
    "iso:country":"US",
    "sg:address":"930 Mason Ct",
    "sg:city":"Daytona Beach",
    "sg:classifiers":[
        {
            "category":"Wholesale",
            "subcategory":"Electrical",
            "type":"Manufacturing & Wholesale Goods"
        }
    ],
    "sg:phone":"+1 386 258 5461",
    "sg:postcode":"32117",
    "sg:province":"FL",
    "sg:tags":[
        "supply"
    ],
    "wof:name":"Graybar Electric Company Inc",
    "wof:placetype":"venue"
},
  "geometry": {"coordinates":[-81.046716,29.220609],"type":"Point"}
}