{
  "type": "Feature",
  "properties": {
    "iso:country":"US",
    "sg:address":"10216 NW 46th St",
    "sg:city":"Sunrise",
    "sg:classifiers":[
        {
            "category":"Banks & Credit Unions",
            "subcategory":"Financial Services",
            "type":"Services"
        }
    ],
    "sg:phone":"+1 954 356 1250",
    "sg:postcode":"33351",
    "sg:province":"FL",
    "sg:tags":[
        "loan"
    ],
    "wof:name":"Housing Modification Assistance",
    "wof:placetype":"venue"
},
  "geometry": {"coordinates":[-80.286953,26.18178],"type":"Point"}
}