{
  "type": "Feature",
  "properties": {
    "addr:full":"451 Harbor Dr N Indian Rocks Beach FL 33785",
    "addr:housenumber":"451",
    "addr:postcode":"33785",
    "addr:street":"Harbor Dr N",
    "iso:country":"US",
    "sg:address":"451 Harbor Dr N",
    "sg:city":"Indian Rocks Beach",
    "sg:classifiers":[
        {
            "category":"Real Estate",
            "subcategory":"Real Estate Agent",
            "type":"Services"
        }
    ],
    "sg:phone":"+1 727 595 6546",
    "sg:postcode":"33785",
    "sg:province":"FL",
    "wof:name":"Marie Mazzara",
    "wof:placetype":"venue"
},
  "geometry": {"coordinates":[-82.836108,27.906215],"type":"Point"}
}