{
  "type": "Feature",
  "properties": {
    "addr:full":"1606 29th Ave N St Petersburg FL 33713",
    "addr:housenumber":"1606",
    "addr:postcode":"33713",
    "addr:street":"29Th Ave N",
    "iso:country":"US",
    "sg:address":"1606 29th Ave N",
    "sg:city":"St Petersburg",
    "sg:classifiers":[
        {
            "category":"Shopping",
            "subcategory":"Clothing, Apparel, & Fashions",
            "type":"Retail Goods"
        }
    ],
    "sg:phone":"+1 727 823 7031",
    "sg:postcode":"33713",
    "sg:province":"FL",
    "sg:tags":[
        "alteration"
    ],
    "wof:name":"Long Alterations",
    "wof:placetype":"venue"
},
  "geometry": {"coordinates":[-82.656454,27.798325],"type":"Point"}
}