{
  "type": "Feature",
  "properties": {
    "iso:country":"US",
    "sg:address":"1601 Minnesota Ave",
    "sg:city":"Winter Park",
    "sg:classifiers":[
        {
            "category":"Retail",
            "subcategory":"Portrait Studio",
            "type":"Services"
        }
    ],
    "sg:phone":"+1 407 647 4215",
    "sg:postcode":"32789",
    "sg:province":"FL",
    "wof:name":"Little Creations Inc",
    "wof:placetype":"venue"
},
  "geometry": {"coordinates":[-81.370672,28.589478],"type":"Point"}
}