{
  "type": "Feature",
  "properties": {
    "iso:country":"US",
    "sg:address":"333 W Cocoa Beach Cswy Ste 6",
    "sg:city":"Cocoa Beach",
    "sg:classifiers":[
        {
            "category":"Health Services",
            "subcategory":"Doctor",
            "type":"Services"
        }
    ],
    "sg:phone":"+1 321 799 9797",
    "sg:postcode":"32931",
    "sg:province":"FL",
    "wof:name":"Widick Michael MD",
    "wof:placetype":"venue"
},
  "geometry": {"coordinates":[-80.610581,28.357997],"type":"Point"}
}