{
  "type": "Feature",
  "properties": {
    "iso:country":"US",
    "sg:address":"20491 The Granada",
    "sg:city":"Dunnellon",
    "sg:classifiers":[
        {
            "category":"Health Services",
            "subcategory":"Doctor",
            "type":"Services"
        }
    ],
    "sg:phone":"+1 352 489 6610",
    "sg:postcode":"34432",
    "sg:province":"FL",
    "sg:tags":[
        "dentist"
    ],
    "wof:name":"General Dentistry",
    "wof:placetype":"venue"
},
  "geometry": {"coordinates":[-82.459363,29.048654],"type":"Point"}
}