{
  "type": "Feature",
  "properties": {
    "iso:country":"US",
    "sg:address":"2006 Hollywood Blvd",
    "sg:city":"Hollywood",
    "sg:classifiers":[
        {
            "category":"Bars & Pubs",
            "type":"Food & Drink"
        }
    ],
    "sg:phone":"+1 954 920 8777",
    "sg:postcode":"33020",
    "sg:province":"FL",
    "sg:tags":[
        "club",
        "night"
    ],
    "wof:name":"Sonar",
    "wof:placetype":"venue"
},
  "geometry": {"coordinates":[-80.148719,26.011368],"type":"Point"}
}