{
  "type": "Feature",
  "properties": {
    "addr:full":"351 Colley Rd Starke FL 32091",
    "addr:housenumber":"351",
    "addr:postcode":"32091",
    "addr:street":"Colley Rd",
    "iso:country":"US",
    "sg:address":"351 Colley Rd",
    "sg:city":"Starke",
    "sg:classifiers":[
        {
            "category":"Utilities",
            "subcategory":"Electric",
            "type":"Services"
        }
    ],
    "sg:phone":"+1 386 758 2421",
    "sg:postcode":"32091",
    "sg:province":"FL",
    "wof:name":"FPL",
    "wof:placetype":"venue"
},
  "geometry": {"coordinates":[-82.102581,29.940737],"type":"Point"}
}