{
  "type": "Feature",
  "properties": {
    "iso:country":"US",
    "sg:address":"133 NE 20th St",
    "sg:city":"Cape Coral",
    "sg:classifiers":[
        {
            "category":"Manufacturing",
            "subcategory":"Chemicals & Compounds",
            "type":"Manufacturing & Wholesale Goods"
        }
    ],
    "sg:phone":"+1 239 573 7808",
    "sg:postcode":"33909",
    "sg:province":"FL",
    "sg:tags":[
        "agricultural",
        "mfg"
    ],
    "wof:name":"Webaway Usa LLC",
    "wof:placetype":"venue"
},
  "geometry": {"coordinates":[-81.968453,26.689805],"type":"Point"}
}