{
  "type": "Feature",
  "properties": {
    "iso:country":"US",
    "sg:address":"3566 Blanding Blvd",
    "sg:city":"Jacksonville",
    "sg:classifiers":[
        {
            "category":"Shopping",
            "subcategory":"Department Store",
            "type":"Retail Goods"
        }
    ],
    "sg:phone":"+1 904 573 0909",
    "sg:postcode":"32210",
    "sg:province":"FL",
    "sg:website":"http://www.bealls.com/",
    "wof:name":"Bealls Department Store",
    "wof:placetype":"venue"
},
  "geometry": {"coordinates":[-81.735839,30.270659],"type":"Point"}
}