{
  "type": "Feature",
  "properties": {
    "addr:full":"6255 Cedar Tree Ln Naples FL 34116",
    "addr:housenumber":"6255",
    "addr:postcode":"34116",
    "addr:street":"Cedar Tree Ln",
    "iso:country":"US",
    "sg:address":"6255 Cedar Tree Ln",
    "sg:city":"Naples",
    "sg:classifiers":[
        {
            "category":"Building & Trades",
            "subcategory":"Equipment Rental",
            "type":"Services"
        }
    ],
    "sg:phone":"+1 239 417 9878",
    "sg:postcode":"34116",
    "sg:province":"FL",
    "sg:tags":[
        "aircraft",
        "leasing",
        "charter"
    ],
    "wof:name":"Rex L Gasteiger Aircraft",
    "wof:placetype":"venue"
},
  "geometry": {"coordinates":[-81.734739,26.196146],"type":"Point"}
}