{
  "type": "Feature",
  "properties": {
    "addr:full":"1201 NE 85th St Miami FL 33138",
    "addr:housenumber":"1201",
    "addr:postcode":"33138",
    "addr:street":"Ne 85Th St",
    "iso:country":"US",
    "sg:address":"1201 NE 85th St",
    "sg:city":"Miami",
    "sg:classifiers":[
        {
            "category":"Home & Garden",
            "subcategory":"Kitchen Supply",
            "type":"Retail Goods"
        }
    ],
    "sg:phone":"+1 305 754 0782",
    "sg:postcode":"33138",
    "sg:province":"FL",
    "sg:tags":[
        "concession",
        "concessionaire"
    ],
    "wof:name":"J & K Concession Stand, Inc.",
    "wof:placetype":"venue"
},
  "geometry": {"coordinates":[-80.173372,25.853904],"type":"Point"}
}