{
  "type": "Feature",
  "properties": {
    "iso:country":"US",
    "sg:address":"4623 NW 19 Pl",
    "sg:city":"Gainesville",
    "sg:classifiers":[
        {
            "category":"Professional",
            "subcategory":"Computer Services",
            "type":"Services"
        }
    ],
    "sg:phone":"+1 352 367 3021",
    "sg:postcode":"32605",
    "sg:province":"FL",
    "sg:tags":[
        "development",
        "software"
    ],
    "wof:name":"Endless Loop Software",
    "wof:placetype":"venue"
},
  "geometry": {"coordinates":[-82.396446,29.670041],"type":"Point"}
}