{
  "type": "Feature",
  "properties": {
    "iso:country":"US",
    "sg:address":"1472 SE Huffman Rd",
    "sg:city":"Port St Lucie",
    "sg:classifiers":[
        {
            "category":"Manufacturing",
            "subcategory":"Retail Goods",
            "type":"Manufacturing & Wholesale Goods"
        }
    ],
    "sg:phone":"+1 772 337 0077",
    "sg:postcode":"34952",
    "sg:province":"FL",
    "sg:tags":[
        "assembly",
        "fabricating"
    ],
    "sg:website":"www.gulfstreamgoodwill.com",
    "wof:name":"Goodwillindustries-Gulfstream",
    "wof:placetype":"venue"
},
  "geometry": {"coordinates":[-80.30632,27.30593],"type":"Point"}
}