{
  "type": "Feature",
  "properties": {
    "iso:country":"US",
    "sg:address":"8235 Pelican Ln",
    "sg:city":"Seminole",
    "sg:classifiers":[
        {
            "category":"Building & Trades",
            "subcategory":"Cleaning & Sanitation",
            "type":"Services"
        }
    ],
    "sg:phone":"+1 727 895 9543",
    "sg:postcode":"33777",
    "sg:province":"FL",
    "sg:tags":[
        "protection",
        "fabric",
        "furniture"
    ],
    "wof:name":"J & G Carpet Cleaning",
    "wof:placetype":"venue"
},
  "geometry": {"coordinates":[-82.759972,27.84753],"type":"Point"}
}