{
  "type": "Feature",
  "properties": {
    "addr:full":"805 N Pine Hills Rd Orlando FL 32808",
    "addr:housenumber":"805",
    "addr:postcode":"32808",
    "addr:street":"N Pine Hills Rd",
    "iso:country":"US",
    "sg:address":"805 N Pine Hills Rd",
    "sg:city":"Orlando",
    "sg:classifiers":[
        {
            "category":"Education",
            "subcategory":"Special Training",
            "type":"Public Place"
        }
    ],
    "sg:phone":"+1 407 822 9700",
    "sg:postcode":"32808",
    "sg:province":"FL",
    "sg:tags":[
        "instruction",
        "driving"
    ],
    "wof:name":"A-Auto Club Driving School",
    "wof:placetype":"venue"
},
  "geometry": {"coordinates":[-81.447487,28.554367],"type":"Point"}
}