{
  "type": "Feature",
  "properties": {
    "iso:country":"US",
    "sg:address":"295 1st St S",
    "sg:city":"Winter Haven",
    "sg:classifiers":[
        {
            "category":"Building & Trades",
            "subcategory":"Construction",
            "type":"Services"
        }
    ],
    "sg:phone":"+1 863 324 3698",
    "sg:postcode":"33880",
    "sg:province":"FL",
    "sg:tags":[
        "general",
        "contractor"
    ],
    "sg:website":"www.cassidyhomes.com",
    "wof:name":"Cassidy Construction",
    "wof:placetype":"venue"
},
  "geometry": {"coordinates":[-81.726896,28.022096],"type":"Point"}
}