{
  "type": "Feature",
  "properties": {
    "iso:country":"US",
    "sg:address":"5935 Taft St",
    "sg:city":"Hollywood",
    "sg:classifiers":[
        {
            "category":"Professional",
            "type":"Services"
        },
        {
            "category":"Social Services",
            "subcategory":"Child Care",
            "type":"Services"
        }
    ],
    "sg:phone":"+1 954 981 6395",
    "sg:postcode":"33021",
    "sg:province":"FL",
    "sg:tags":[
        "adoption",
        "alternative",
        "abortion"
    ],
    "wof:name":"Shepherd Care Inc",
    "wof:placetype":"venue"
},
  "geometry": {"coordinates":[-80.20703899999999,26.024934],"type":"Point"}
}