{
  "type": "Feature",
  "properties": {
    "addr:full":"9803 Pines Blvd Hollywood FL 33024",
    "addr:housenumber":"9803",
    "addr:postcode":"33024",
    "addr:street":"Pines Blvd",
    "iso:country":"US",
    "sg:address":"9803 Pines Blvd",
    "sg:city":"Hollywood",
    "sg:classifiers":[
        {
            "category":"Food & Beverages",
            "subcategory":"Groceries & Convenience Stores",
            "type":"Retail Goods"
        }
    ],
    "sg:phone":"+1 954 438 1060",
    "sg:postcode":"33024",
    "sg:province":"FL",
    "sg:tags":[
        "grocer",
        "oriental"
    ],
    "wof:name":"Chung Hing Oriental Mart Inc",
    "wof:placetype":"venue"
},
  "geometry": {"coordinates":[-80.27528,26.008521],"type":"Point"}
}