{
  "type": "Feature",
  "properties": {
    "iso:country":"US",
    "sg:address":"1961 Prescott Blvd",
    "sg:city":"Deltona",
    "sg:classifiers":[
        {
            "category":"Building & Trades",
            "subcategory":"Construction",
            "type":"Services"
        }
    ],
    "sg:phone":"+1 386 575 0110",
    "sg:postcode":"32738",
    "sg:province":"FL",
    "sg:tags":[
        "contractor"
    ],
    "wof:name":"Bella Scorpio Construction Inc",
    "wof:placetype":"venue"
},
  "geometry": {"coordinates":[-81.201374,28.898678],"type":"Point"}
}