{
  "type": "Feature",
  "properties": {
    "addr:full":"5317 Palm Ridge Blvd Delray Beach FL 33484",
    "addr:housenumber":"5317",
    "addr:postcode":"33484",
    "addr:street":"Palm Ridge Blvd",
    "iso:country":"US",
    "sg:address":"5317 Palm Ridge Blvd",
    "sg:city":"Delray Beach",
    "sg:classifiers":[
        {
            "category":"Insurance",
            "subcategory":"Insurance Agent",
            "type":"Services"
        }
    ],
    "sg:phone":"+1 561 470 0001",
    "sg:postcode":"33484",
    "sg:province":"FL",
    "wof:name":"Hartford Empire Group",
    "wof:placetype":"venue"
},
  "geometry": {"coordinates":[-80.12767599999999,26.479924],"type":"Point"}
}