{
  "type": "Feature",
  "properties": {
    "addr:full":"5646 Jason Lee Pl Sarasota FL 34233",
    "addr:housenumber":"5646",
    "addr:postcode":"34233",
    "addr:street":"Jason Lee Pl",
    "iso:country":"US",
    "sg:address":"5646 Jason Lee Pl",
    "sg:city":"Sarasota",
    "sg:classifiers":[
        {
            "category":"Autos & Motor Vehicles",
            "subcategory":"Auto Supplies",
            "type":"Retail Goods"
        },
        {
            "category":"Retail",
            "subcategory":"Auto Repair",
            "type":"Services"
        }
    ],
    "sg:phone":"+1 941 922 8070",
    "sg:postcode":"34233",
    "sg:province":"FL",
    "sg:tags":[
        "alternator",
        "automotive",
        "generator"
    ],
    "wof:name":"Alternator & Starter Repair Co",
    "wof:placetype":"venue"
},
  "geometry": {"coordinates":[-82.47340699999999,27.271076],"type":"Point"}
}