{
  "type": "Feature",
  "properties": {
    "iso:country":"US",
    "sg:address":"12276 San Jose Blvd",
    "sg:city":"Jacksonville",
    "sg:classifiers":[
        {
            "category":"Insurance",
            "subcategory":"Insurance Agent",
            "type":"Services"
        }
    ],
    "sg:phone":"+1 904 262 6122",
    "sg:postcode":"32223",
    "sg:province":"FL",
    "wof:name":"First Coast Southeast Inc",
    "wof:placetype":"venue"
},
  "geometry": {"coordinates":[-81.63268600000001,30.146116],"type":"Point"}
}