{
  "type": "Feature",
  "properties": {
    "addr:full":"1779 W 79th St Hialeah FL 33014",
    "addr:housenumber":"1779",
    "addr:postcode":"33014",
    "addr:street":"W 79Th St",
    "iso:country":"US",
    "sg:address":"1779 W 79th St",
    "sg:city":"Hialeah",
    "sg:classifiers":[
        {
            "category":"Professional",
            "type":"Services"
        }
    ],
    "sg:phone":"+1 305 994 7255",
    "sg:postcode":"33014",
    "sg:province":"FL",
    "sg:tags":[
        "establishment"
    ],
    "wof:name":"Concept Trade",
    "wof:placetype":"venue"
},
  "geometry": {"coordinates":[-80.317791,25.894537],"type":"Point"}
}