{
  "type": "Feature",
  "properties": {
    "addr:full":"3030 Maingate Ln Kissimmee FL 34747",
    "addr:housenumber":"3030",
    "addr:postcode":"34747",
    "addr:street":"Maingate Ln",
    "iso:country":"US",
    "sg:address":"3030 Maingate Ln",
    "sg:city":"Kissimmee",
    "sg:classifiers":[
        {
            "category":"Freight",
            "type":"Transportation"
        }
    ],
    "sg:phone":"+1 407 397 6260",
    "sg:postcode":"34747",
    "sg:province":"FL",
    "sg:tags":[
        "grocery",
        "general"
    ],
    "wof:name":"Walt Disney World Co",
    "wof:placetype":"venue"
},
  "geometry": {"coordinates":[-81.587457,28.333081],"type":"Point"}
}