{
  "type": "Feature",
  "properties": {
    "iso:country":"US",
    "sg:address":"1910 N Ola Ave",
    "sg:city":"Tampa",
    "sg:classifiers":[
        {
            "category":"Wholesale",
            "subcategory":"Electrical",
            "type":"Manufacturing & Wholesale Goods"
        }
    ],
    "sg:phone":"+1 813 621 5661",
    "sg:postcode":"33602",
    "sg:province":"FL",
    "sg:tags":[
        "electric",
        "motor"
    ],
    "wof:name":"Tampa Armature Works Inc",
    "wof:placetype":"venue"
},
  "geometry": {"coordinates":[-82.46351799999999,27.961457],"type":"Point"}
}