{
  "type": "Feature",
  "properties": {
    "iso:country":"US",
    "sg:address":"446 SW Irving St",
    "sg:city":"Port St Lucie",
    "sg:classifiers":[
        {
            "category":"Organizations",
            "subcategory":"Religious Organization",
            "type":"Services"
        }
    ],
    "sg:phone":"+1 772 340 0105",
    "sg:postcode":"34983",
    "sg:province":"FL",
    "sg:tags":[
        "church"
    ],
    "wof:name":"St Lucie Catholic Church",
    "wof:placetype":"venue"
},
  "geometry": {"coordinates":[-80.353517,27.316327],"type":"Point"}
}