{
  "type": "Feature",
  "properties": {
    "iso:country":"US",
    "sg:address":"661 Blanding Blvd",
    "sg:city":"Orange Park",
    "sg:classifiers":[
        {
            "category":"Insurance",
            "subcategory":"Insurance Agent",
            "type":"Services"
        }
    ],
    "sg:phone":"+1 904 272 9600",
    "sg:postcode":"32073",
    "sg:province":"FL",
    "wof:name":"Allstate Insurance",
    "wof:placetype":"venue"
},
  "geometry": {"coordinates":[-81.75633999999999,30.14846],"type":"Point"}
}