{
  "type": "Feature",
  "properties": {
    "iso:country":"US",
    "sg:address":"1633 E Vine St",
    "sg:city":"Kissimmee",
    "sg:classifiers":[
        {
            "category":"Social Services",
            "type":"Services"
        }
    ],
    "sg:phone":"+1 407 343 6213",
    "sg:postcode":"34744",
    "sg:province":"FL",
    "sg:tags":[
        "professional",
        "counselor"
    ],
    "wof:name":"Jessie Williams",
    "wof:placetype":"venue"
},
  "geometry": {"coordinates":[-81.37521599999999,28.300773],"type":"Point"}
}