{
  "type": "Feature",
  "properties": {
    "iso:country":"US",
    "sg:address":"672 N Semoran Blvd",
    "sg:city":"Orlando",
    "sg:classifiers":[
        {
            "category":"Professional",
            "subcategory":"Computer Services",
            "type":"Services"
        }
    ],
    "sg:phone":"+1 407 207 8829",
    "sg:postcode":"32807",
    "sg:province":"FL",
    "sg:tags":[
        "info",
        "processing"
    ],
    "wof:name":"First Data",
    "wof:placetype":"venue"
},
  "geometry": {"coordinates":[-81.310806,28.553208],"type":"Point"}
}