{
  "type": "Feature",
  "properties": {
    "iso:country":"US",
    "sg:address":"3541 University Blvd W",
    "sg:city":"Jacksonville",
    "sg:classifiers":[
        {
            "category":"Cinema",
            "subcategory":"Movie Rental",
            "type":"Entertainment"
        }
    ],
    "sg:phone":"+1 904 731 3956",
    "sg:postcode":"32217",
    "sg:province":"FL",
    "sg:tags":[
        "video",
        "store"
    ],
    "wof:name":"Blockbuster",
    "wof:placetype":"venue"
},
  "geometry": {"coordinates":[-81.624117,30.262579],"type":"Point"}
}