{
  "type": "Feature",
  "properties": {
    "addr:full":"3717 Pickwick Dr Orlando FL 32817",
    "addr:housenumber":"3717",
    "addr:postcode":"32817",
    "addr:street":"Pickwick Dr",
    "iso:country":"US",
    "sg:address":"3717 Pickwick Dr",
    "sg:city":"Orlando",
    "sg:classifiers":[
        {
            "category":"Shopping",
            "type":"Retail Goods"
        }
    ],
    "sg:phone":"+1 407 908 2207",
    "sg:postcode":"32817",
    "sg:province":"FL",
    "sg:tags":[
        "merchandise"
    ],
    "wof:name":"Abound Direct",
    "wof:placetype":"venue"
},
  "geometry": {"coordinates":[-81.275952,28.59444],"type":"Point"}
}