{
  "type": "Feature",
  "properties": {
    "iso:country":"US",
    "sg:address":"10691 Santa Laguna Dr",
    "sg:city":"Boca Raton",
    "sg:classifiers":[
        {
            "category":"Real Estate",
            "subcategory":"Real Estate Operator",
            "type":"Services"
        }
    ],
    "sg:phone":"+1 561 479 0570",
    "sg:postcode":"33428",
    "sg:province":"FL",
    "sg:tags":[
        "building",
        "apartment"
    ],
    "wof:name":"Prime Properties Development L",
    "wof:placetype":"venue"
},
  "geometry": {"coordinates":[-80.216438,26.3679],"type":"Point"}
}