{
  "type": "Feature",
  "properties": {
    "iso:country":"US",
    "sg:address":"1900 Sunset Harbour Dr",
    "sg:city":"Miami Beach",
    "sg:classifiers":[
        {
            "category":"Home & Garden",
            "subcategory":"Furniture",
            "type":"Retail Goods"
        }
    ],
    "sg:phone":"+1 305 531 2331",
    "sg:postcode":"33139",
    "sg:province":"FL",
    "wof:name":"Rialto Italia Furniture",
    "wof:placetype":"venue"
},
  "geometry": {"coordinates":[-80.14432600000001,25.791757],"type":"Point"}
}