{
  "type": "Feature",
  "properties": {
    "iso:country":"US",
    "sg:address":"3693 NW 124th Ave",
    "sg:city":"Pompano Beach",
    "sg:classifiers":[
        {
            "category":"Building & Trades",
            "subcategory":"Construction",
            "type":"Services"
        }
    ],
    "sg:phone":"+1 954 345 4160",
    "sg:postcode":"33065",
    "sg:province":"FL",
    "sg:tags":[
        "sheet",
        "metal",
        "contractor"
    ],
    "wof:name":"Consolidated Metal Works Inc",
    "wof:placetype":"venue"
},
  "geometry": {"coordinates":[-80.291121,26.276679],"type":"Point"}
}