{
  "type": "Feature",
  "properties": {
    "addr:full":"3021 39th St Orlando FL 32839",
    "addr:housenumber":"3021",
    "addr:postcode":"32839",
    "addr:street":"39Th St",
    "iso:country":"US",
    "sg:address":"3021 39th St",
    "sg:city":"Orlando",
    "sg:classifiers":[
        {
            "category":"Shopping",
            "subcategory":"Gifts & Souvenirs",
            "type":"Retail Goods"
        }
    ],
    "sg:phone":"+1 407 648 1180",
    "sg:postcode":"32839",
    "sg:province":"FL",
    "sg:tags":[
        "basket",
        "parcel"
    ],
    "wof:name":"Cindy's Creations & Gifts",
    "wof:placetype":"venue"
},
  "geometry": {"coordinates":[-81.417754,28.503452],"type":"Point"}
}