{
  "type": "Feature",
  "properties": {
    "addr:full":"420 Lincoln Rd Miami Beach FL 33139",
    "addr:housenumber":"420",
    "addr:postcode":"33139",
    "addr:street":"Lincoln Rd",
    "iso:country":"US",
    "sg:address":"420 Lincoln Rd",
    "sg:city":"Miami Beach",
    "sg:classifiers":[
        {
            "category":"Recreation",
            "type":"Entertainment"
        }
    ],
    "sg:phone":"+1 305 535 8177",
    "sg:postcode":"33139",
    "sg:province":"FL",
    "sg:tags":[
        "amusement"
    ],
    "sg:website":"www.boucherbrothers.com",
    "wof:name":"Boucher Brothers Management",
    "wof:placetype":"venue"
},
  "geometry": {"coordinates":[-80.132887,25.790583],"type":"Point"}
}