{
  "type": "Feature",
  "properties": {
    "iso:country":"US",
    "sg:address":"14 Lakeview Ave",
    "sg:city":"Lake Placid",
    "sg:classifiers":[
        {
            "category":"Manufacturing",
            "subcategory":"Tools & Machinery",
            "type":"Manufacturing & Wholesale Goods"
        }
    ],
    "sg:phone":"+1 863 465 5757",
    "sg:postcode":"33852",
    "sg:province":"FL",
    "sg:tags":[
        "pump"
    ],
    "sg:website":"www.creelpump.com",
    "wof:name":"Creel Pump Inc",
    "wof:placetype":"venue"
},
  "geometry": {"coordinates":[-81.36275999999999,27.301304],"type":"Point"}
}