{
  "type": "Feature",
  "properties": {
    "iso:country":"US",
    "sg:address":"3560 NW 115th Ave",
    "sg:city":"Doral",
    "sg:classifiers":[
        {
            "category":"Wholesale",
            "subcategory":"Machinery & Supplies",
            "type":"Manufacturing & Wholesale Goods"
        }
    ],
    "sg:phone":"+1 305 599 2605",
    "sg:postcode":"33178",
    "sg:province":"FL",
    "sg:tags":[
        "salon",
        "beauty"
    ],
    "wof:name":"Fadiori",
    "wof:placetype":"venue"
},
  "geometry": {"coordinates":[-80.383943,25.809461],"type":"Point"}
}