{
  "type": "Feature",
  "properties": {
    "iso:country":"US",
    "sg:address":"11461 NW 34th St",
    "sg:city":"Doral",
    "sg:classifiers":[
        {
            "category":"Airline",
            "type":"Transportation"
        }
    ],
    "sg:phone":"+1 305 716 7606",
    "sg:postcode":"33178",
    "sg:province":"FL",
    "sg:tags":[
        "courier",
        "air"
    ],
    "wof:name":"Skorpios Courier",
    "wof:placetype":"venue"
},
  "geometry": {"coordinates":[-80.382991,25.805117],"type":"Point"}
}