{
  "type": "Feature",
  "properties": {
    "addr:full":"4977 US Hwy 98 Lakeland FL 33809",
    "addr:housenumber":"4977",
    "addr:postcode":"33809",
    "addr:street":"Us Hwy 98",
    "iso:country":"US",
    "sg:address":"4977 US Hwy 98",
    "sg:city":"Lakeland",
    "sg:classifiers":[
        {
            "category":"Insurance",
            "subcategory":"Insurance Agent",
            "type":"Services"
        }
    ],
    "sg:phone":"+1 863 859 7000",
    "sg:postcode":"33809",
    "sg:province":"FL",
    "wof:name":"Allstate",
    "wof:placetype":"venue"
},
  "geometry": {"coordinates":[-81.973681,28.104137],"type":"Point"}
}