{
  "type": "Feature",
  "properties": {
    "iso:country":"US",
    "sg:address":"11735 Plantation Rd",
    "sg:city":"Fort Myers",
    "sg:classifiers":[
        {
            "category":"Organizations",
            "subcategory":"Religious Organization",
            "type":"Services"
        }
    ],
    "sg:phone":"+1 239 931 0833",
    "sg:postcode":"33912",
    "sg:province":"FL",
    "sg:website":"www.lifechurch.net",
    "wof:name":"Life Church",
    "wof:placetype":"venue"
},
  "geometry": {"coordinates":[-81.84699999999999,26.5739],"type":"Point"}
}