{
  "type": "Feature",
  "properties": {
    "iso:country":"US",
    "sg:address":"1601 W 8th Ave",
    "sg:city":"Hialeah",
    "sg:classifiers":[
        {
            "category":"Professional",
            "subcategory":"Printing & Photocopies",
            "type":"Services"
        }
    ],
    "sg:phone":"+1 305 884 1450",
    "sg:postcode":"33010",
    "sg:province":"FL",
    "wof:name":"El Dollarazo",
    "wof:placetype":"venue"
},
  "geometry": {"coordinates":[-80.298103,25.8363],"type":"Point"}
}