{
  "type": "Feature",
  "properties": {
    "addr:full":"6110 Gunn Hwy Tampa FL 33625",
    "addr:housenumber":"6110",
    "addr:postcode":"33625",
    "addr:street":"Gunn Hwy",
    "iso:country":"US",
    "sg:address":"6110 Gunn Hwy",
    "sg:city":"Tampa",
    "sg:classifiers":[
        {
            "category":"Shopping",
            "subcategory":"Computers & Home Electronics",
            "type":"Retail Goods"
        }
    ],
    "sg:phone":"+1 813 964 0177",
    "sg:postcode":"33625",
    "sg:province":"FL",
    "sg:tags":[
        "tape",
        "game",
        "video",
        "sale",
        "dvds-rental"
    ],
    "wof:name":"Rhino Video Games",
    "wof:placetype":"venue"
},
  "geometry": {"coordinates":[-82.549826,28.063589],"type":"Point"}
}