{
  "type": "Feature",
  "properties": {
    "iso:country":"US",
    "sg:address":"7040 State Hwy 50",
    "sg:city":"Groveland",
    "sg:classifiers":[
        {
            "category":"Building & Trades",
            "subcategory":"Plumbing",
            "type":"Services"
        }
    ],
    "sg:phone":"+1 352 429 2285",
    "sg:postcode":"34736",
    "sg:province":"FL",
    "sg:tags":[
        "air",
        "heating",
        "contractor"
    ],
    "wof:name":"Galassi Services Inc",
    "wof:placetype":"venue"
},
  "geometry": {"coordinates":[-81.837734,28.558002],"type":"Point"}
}