{
  "type": "Feature",
  "properties": {
    "iso:country":"US",
    "sg:address":"220 W Main St",
    "sg:city":"Mayo",
    "sg:classifiers":[
        {
            "category":"Restaurant",
            "type":"Food & Drink"
        }
    ],
    "sg:phone":"+1 386 294 2187",
    "sg:postcode":"32054",
    "sg:province":"FL",
    "sg:tags":[
        "eating"
    ],
    "wof:name":"Mayo Cafe",
    "wof:placetype":"venue"
},
  "geometry": {"coordinates":[-82.34051700000001,30.022988],"type":"Point"}
}