{
  "type": "Feature",
  "properties": {
    "addr:full":"2002 E 5th Ave Ste 103 Tampa FL 33605",
    "addr:housenumber":"2002",
    "addr:postcode":"33605",
    "addr:street":"E 5Th Ave Ste 103",
    "iso:country":"US",
    "sg:address":"2002 E 5th Ave Ste 103",
    "sg:city":"Tampa",
    "sg:phone":"+1 813 248 5060",
    "sg:postcode":"33605",
    "sg:province":"FL",
    "wof:name":"H2o Salon",
    "wof:placetype":"venue"
},
  "geometry": {"coordinates":[-82.436734,27.95882],"type":"Point"}
}