{
  "type": "Feature",
  "properties": {
    "addr:full":"1125 White Dr Titusville FL 32780",
    "addr:housenumber":"1125",
    "addr:postcode":"32780",
    "addr:street":"White Dr",
    "iso:country":"US",
    "sg:address":"1125 White Dr",
    "sg:city":"Titusville",
    "sg:classifiers":[
        {
            "category":"Home & Garden",
            "subcategory":"Garden Supply",
            "type":"Retail Goods"
        }
    ],
    "sg:phone":"+1 321 267 4841",
    "sg:postcode":"32780",
    "sg:province":"FL",
    "sg:tags":[
        "nurseryman"
    ],
    "wof:name":"A & D Nurseries Inc",
    "wof:placetype":"venue"
},
  "geometry": {"coordinates":[-80.82033,28.527431],"type":"Point"}
}