{
  "type": "Feature",
  "properties": {
    "iso:country":"US",
    "sg:address":"14236 6th St",
    "sg:city":"Dade City",
    "sg:classifiers":[
        {
            "category":"Government",
            "subcategory":"Office",
            "type":"Public Place"
        }
    ],
    "sg:phone":"+1 352 521 4302",
    "sg:postcode":"33523",
    "sg:province":"FL",
    "sg:website":"www.pascovotes.com",
    "wof:name":"Supervisor Of Elections",
    "wof:placetype":"venue"
},
  "geometry": {"coordinates":[-82.188159,28.365767],"type":"Point"}
}