{
  "type": "Feature",
  "properties": {
    "iso:country":"US",
    "sg:address":"108 Louisiana Dr",
    "sg:city":"Pensacola",
    "sg:classifiers":[
        {
            "category":"Health Services",
            "subcategory":"Nursing And Care Facility",
            "type":"Services"
        },
        {
            "category":"Social Services",
            "subcategory":"Adult Care",
            "type":"Services"
        }
    ],
    "sg:phone":"+1 850 453 2301",
    "sg:postcode":"32505",
    "sg:province":"FL",
    "sg:tags":[
        "home",
        "retirement",
        "community"
    ],
    "wof:name":"Alpine Adult Care Center",
    "wof:placetype":"venue"
},
  "geometry": {"coordinates":[-87.268288,30.436215],"type":"Point"}
}