{
  "type": "Feature",
  "properties": {
    "iso:country":"US",
    "sg:address":"6345 NW 32nd Ave",
    "sg:city":"Miami",
    "sg:classifiers":[
        {
            "category":"Autos & Motor Vehicles",
            "subcategory":"Fuel & Gas Station",
            "type":"Retail Goods"
        }
    ],
    "sg:phone":"+1 305 696 8842",
    "sg:postcode":"33147",
    "sg:province":"FL",
    "sg:website":"http://www.chevron.com",
    "wof:name":"Chevron 32nd Av",
    "wof:placetype":"venue"
},
  "geometry": {"coordinates":[-80.249329,25.832068],"type":"Point"}
}