{
  "type": "Feature",
  "properties": {
    "iso:country":"US",
    "sg:address":"647 N Semoran Blvd",
    "sg:city":"Orlando",
    "sg:classifiers":[
        {
            "category":"Home & Garden",
            "subcategory":"Furniture",
            "type":"Retail Goods"
        }
    ],
    "sg:phone":"+1 407 384 8085",
    "sg:postcode":"32807",
    "sg:province":"FL",
    "sg:tags":[
        "mattress"
    ],
    "wof:name":"Manny's Furniture",
    "wof:placetype":"venue"
},
  "geometry": {"coordinates":[-81.31066,28.553543],"type":"Point"}
}