{
  "type": "Feature",
  "properties": {
    "addr:full":"4649 Ponce de Leon Blvd Coral Gables FL 33146",
    "addr:housenumber":"4649",
    "addr:postcode":"33146",
    "addr:street":"Ponce De Leon Blvd",
    "iso:country":"US",
    "sg:address":"4649 Ponce de Leon Blvd",
    "sg:city":"Coral Gables",
    "sg:classifiers":[
        {
            "category":"Professional",
            "subcategory":"Accounting & Tax Preparation",
            "type":"Services"
        }
    ],
    "sg:phone":"+1 305 662 9061",
    "sg:postcode":"33146",
    "sg:province":"FL",
    "sg:tags":[
        "accountant"
    ],
    "wof:name":"Pedro L Albemi",
    "wof:placetype":"venue"
},
  "geometry": {"coordinates":[-80.26347199999999,25.726391],"type":"Point"}
}