{
  "type": "Feature",
  "properties": {
    "addr:full":"4885 Aleff Rd Milton FL 32571",
    "addr:housenumber":"4885",
    "addr:postcode":"32571",
    "addr:street":"Aleff Rd",
    "iso:country":"US",
    "sg:address":"4885 Aleff Rd",
    "sg:city":"Milton",
    "sg:classifiers":[
        {
            "category":"Professional",
            "subcategory":"Management & Consulting",
            "type":"Services"
        }
    ],
    "sg:phone":"+1 850 994 2304",
    "sg:postcode":"32571",
    "sg:province":"FL",
    "sg:tags":[
        "marketing",
        "consultant"
    ],
    "wof:name":"Cd's Southern Enterprises",
    "wof:placetype":"venue"
},
  "geometry": {"coordinates":[-87.121844,30.591168],"type":"Point"}
}