{
  "type": "Feature",
  "properties": {
    "iso:country":"US",
    "sg:address":"7270 W McNab Rd",
    "sg:city":"North Lauderdale",
    "sg:classifiers":[
        {
            "category":"Shopping",
            "subcategory":"Clothing, Apparel, & Fashions",
            "type":"Retail Goods"
        }
    ],
    "sg:phone":"+1 954 722 4166",
    "sg:postcode":"33068",
    "sg:province":"FL",
    "wof:name":"Rainbow",
    "wof:placetype":"venue"
},
  "geometry": {"coordinates":[-80.22359,26.208365],"type":"Point"}
}