{
  "type": "Feature",
  "properties": {
    "addr:full":"7510 Thomas Dr Panama City Bch FL 32408",
    "addr:housenumber":"7510",
    "addr:postcode":"32408",
    "addr:street":"Thomas Dr",
    "iso:country":"US",
    "sg:address":"7510 Thomas Dr",
    "sg:city":"Panama City Bch",
    "sg:classifiers":[
        {
            "category":"Recreation",
            "subcategory":"Amusement Park",
            "type":"Entertainment"
        }
    ],
    "sg:phone":"+1 850 249 7545",
    "sg:postcode":"32408",
    "sg:province":"FL",
    "wof:name":"Skillz Arcade",
    "wof:placetype":"venue"
},
  "geometry": {"coordinates":[-85.778373,30.160734],"type":"Point"}
}