{
  "type": "Feature",
  "properties": {
    "iso:country":"US",
    "sg:address":"1012 Raulerson Rd",
    "sg:city":"Immokalee",
    "sg:classifiers":[
        {
            "category":"Wholesale",
            "subcategory":"Plants",
            "type":"Manufacturing & Wholesale Goods"
        }
    ],
    "sg:phone":"+1 239 657 2084",
    "sg:postcode":"34142",
    "sg:province":"FL",
    "sg:tags":[
        "palm",
        "tree"
    ],
    "wof:name":"J & J Palms Inc",
    "wof:placetype":"venue"
},
  "geometry": {"coordinates":[-81.46716600000001,26.430443],"type":"Point"}
}