{
  "type": "Feature",
  "properties": {
    "addr:full":"344 Main St Dunedin FL 34698",
    "addr:housenumber":"344",
    "addr:postcode":"34698",
    "addr:street":"Main St",
    "iso:country":"US",
    "sg:address":"344 Main St",
    "sg:city":"Dunedin",
    "sg:classifiers":[
        {
            "category":"Restaurant",
            "type":"Food & Drink"
        }
    ],
    "sg:phone":"+1 727 736 4299",
    "sg:postcode":"34698",
    "sg:province":"FL",
    "wof:name":"Cafe Alfresco",
    "wof:placetype":"venue"
},
  "geometry": {"coordinates":[-82.789641,28.012142],"type":"Point"}
}