{
  "type": "Feature",
  "properties": {
    "addr:full":"1544 E Harmony Lake Cir Fort Lauderdale FL 33324",
    "addr:housenumber":"1544",
    "addr:postcode":"33324",
    "addr:street":"E Harmony Lake Cir",
    "iso:country":"US",
    "sg:address":"1544 E Harmony Lake Cir",
    "sg:city":"Fort Lauderdale",
    "sg:classifiers":[
        {
            "category":"Building & Trades",
            "subcategory":"Construction",
            "type":"Services"
        }
    ],
    "sg:phone":"+1 954 474 3076",
    "sg:postcode":"33324",
    "sg:province":"FL",
    "sg:tags":[
        "house"
    ],
    "wof:name":"Nanc Construction Company",
    "wof:placetype":"venue"
},
  "geometry": {"coordinates":[-80.29156399999999,26.100424],"type":"Point"}
}