{
  "type": "Feature",
  "properties": {
    "iso:country":"US",
    "sg:address":"3371 NW 154th Ter",
    "sg:city":"Opa Locka",
    "sg:classifiers":[
        {
            "category":"Building & Trades",
            "subcategory":"Electrical",
            "type":"Services"
        }
    ],
    "sg:phone":"+1 305 681 9531",
    "sg:postcode":"33054",
    "sg:province":"FL",
    "sg:tags":[
        "commercial",
        "electric",
        "electrical",
        "installation",
        "contractor"
    ],
    "sg:website":"www.luzer.com",
    "wof:name":"Luzer Electric Inc",
    "wof:placetype":"venue"
},
  "geometry": {"coordinates":[-80.256576,25.914341],"type":"Point"}
}