{
  "type": "Feature",
  "properties": {
    "iso:country":"US",
    "sg:address":"815 NE 3rd St",
    "sg:city":"Dania",
    "sg:classifiers":[
        {
            "category":"Restaurant",
            "type":"Food & Drink"
        }
    ],
    "sg:phone":"+1 954 927 3232",
    "sg:postcode":"33004",
    "sg:province":"FL",
    "sg:tags":[
        "seafood"
    ],
    "sg:website":"http://www.harborgrille.com",
    "wof:name":"The Harbor Grille",
    "wof:placetype":"venue"
},
  "geometry": {"coordinates":[-80.130813,26.0578],"type":"Point"}
}