{
  "type": "Feature",
  "properties": {
    "iso:country":"US",
    "sg:address":"16 W Wall St",
    "sg:city":"Frostproof",
    "sg:classifiers":[
        {
            "category":"Shopping",
            "subcategory":"Pharmacy",
            "type":"Retail Goods"
        }
    ],
    "sg:phone":"+1 863 635 4568",
    "sg:postcode":"33843",
    "sg:province":"FL",
    "wof:name":"Watson's Pharmacy",
    "wof:placetype":"venue"
},
  "geometry": {"coordinates":[-81.530732,27.746094],"type":"Point"}
}