{
  "type": "Feature",
  "properties": {
    "addr:full":"3311 W San Pedro St Tampa FL 33629",
    "addr:housenumber":"3311",
    "addr:postcode":"33629",
    "addr:street":"W San Pedro St",
    "iso:country":"US",
    "sg:address":"3311 W San Pedro St",
    "sg:city":"Tampa",
    "sg:classifiers":[
        {
            "category":"Real Estate",
            "subcategory":"Real Estate Operator",
            "type":"Services"
        }
    ],
    "sg:phone":"+1 813 837 1617",
    "sg:postcode":"33629",
    "sg:province":"FL",
    "sg:tags":[
        "mobile",
        "home",
        "site"
    ],
    "wof:name":"Garhan Properties Group Inc",
    "wof:placetype":"venue"
},
  "geometry": {"coordinates":[-82.498622,27.91774],"type":"Point"}
}