{
  "type": "Feature",
  "properties": {
    "addr:full":"11749 N Dale Mabry Hwy Tampa FL 33614",
    "addr:housenumber":"11749",
    "addr:postcode":"33614",
    "addr:street":"N Dale Mabry Hwy",
    "iso:country":"US",
    "sg:address":"11749 N Dale Mabry Hwy",
    "sg:city":"Tampa",
    "sg:classifiers":[
        {
            "category":"Personal",
            "subcategory":"Beauty Salon",
            "type":"Services"
        }
    ],
    "sg:phone":"+1 813 269 0171",
    "sg:postcode":"33614",
    "sg:province":"FL",
    "wof:name":"Hair By Barbara",
    "wof:placetype":"venue"
},
  "geometry": {"coordinates":[-82.503845,28.05323],"type":"Point"}
}