{
  "type": "Feature",
  "properties": {
    "iso:country":"US",
    "sg:address":"9900 SW 139th St",
    "sg:city":"Miami",
    "sg:classifiers":[
        {
            "category":"Insurance",
            "subcategory":"Insurance Agent",
            "type":"Services"
        }
    ],
    "sg:phone":"+1 863 465 1662",
    "sg:postcode":"33176",
    "sg:province":"FL",
    "wof:name":"Protective Life Insurance Co",
    "wof:placetype":"venue"
},
  "geometry": {"coordinates":[-80.356387,25.640411],"type":"Point"}
}