{
  "type": "Feature",
  "properties": {
    "addr:full":"13575 58th St N Clearwater FL 33760",
    "addr:housenumber":"13575",
    "addr:postcode":"33760",
    "addr:street":"58Th St N",
    "iso:country":"US",
    "sg:address":"13575 58th St N",
    "sg:city":"Clearwater",
    "sg:classifiers":[
        {
            "category":"Banks & Credit Unions",
            "subcategory":"Investment Brokerage",
            "type":"Services"
        }
    ],
    "sg:phone":"+1 727 538 7716",
    "sg:postcode":"33760",
    "sg:province":"FL",
    "sg:tags":[
        "consultant",
        "planning",
        "financial"
    ],
    "wof:name":"Guardian Assurance Group",
    "wof:placetype":"venue"
},
  "geometry": {"coordinates":[-82.712357,27.895248],"type":"Point"}
}