{
  "type": "Feature",
  "properties": {
    "iso:country":"US",
    "sg:address":"541 Plover Ave",
    "sg:city":"Miami",
    "sg:classifiers":[
        {
            "category":"Real Estate",
            "subcategory":"Real Estate Agent",
            "type":"Services"
        }
    ],
    "sg:phone":"+1 305 887 8474",
    "sg:postcode":"33166",
    "sg:province":"FL",
    "wof:name":"Neal F Spangler Appraiser Inc",
    "wof:placetype":"venue"
},
  "geometry": {"coordinates":[-80.290876,25.824464],"type":"Point"}
}