{
  "type": "Feature",
  "properties": {
    "iso:country":"US",
    "sg:address":"1200 SW 26th Ave",
    "sg:city":"Boynton Beach",
    "sg:classifiers":[
        {
            "category":"Building & Trades",
            "subcategory":"Landscaping Services",
            "type":"Services"
        }
    ],
    "sg:phone":"+1 561 732 7894",
    "sg:postcode":"33426",
    "sg:province":"FL",
    "sg:tags":[
        "lawn",
        "care"
    ],
    "wof:name":"Top Lawn Care",
    "wof:placetype":"venue"
},
  "geometry": {"coordinates":[-80.087766,26.502485],"type":"Point"}
}