{
  "type": "Feature",
  "properties": {
    "addr:full":"702 Us 27 S Lake Placid FL 33852",
    "addr:housenumber":"702",
    "addr:postcode":"33852",
    "addr:street":"Us 27 S;Placid",
    "iso:country":"US",
    "sg:address":"702 Us 27 S",
    "sg:city":"Lake Placid",
    "sg:classifiers":[
        {
            "category":"Restaurant",
            "type":"Food & Drink"
        }
    ],
    "sg:menulink":"http://www.allmenus.com/fl/lake-placid/71166-pizza-hut/menu/",
    "sg:phone":"+1 863 465 7154",
    "sg:postcode":"33852",
    "sg:province":"FL",
    "sg:tags":[
        "american",
        "pizza"
    ],
    "wof:name":"Pizza Hut",
    "wof:placetype":"venue"
},
  "geometry": {"coordinates":[-81.358406,27.290407],"type":"Point"}
}