{
  "type": "Feature",
  "properties": {
    "addr:full":"9740 San Jose Blvd Jacksonville FL 32257",
    "addr:housenumber":"9740",
    "addr:postcode":"32257",
    "addr:street":"San Jose Blvd",
    "iso:country":"US",
    "sg:address":"9740 San Jose Blvd",
    "sg:city":"Jacksonville",
    "sg:classifiers":[
        {
            "category":"Building & Trades",
            "subcategory":"Construction",
            "type":"Services"
        }
    ],
    "sg:phone":"+1 904 262 2384",
    "sg:postcode":"32257",
    "sg:province":"FL",
    "sg:tags":[
        "spa",
        "pool",
        "swimming"
    ],
    "wof:name":"Martin Pools",
    "wof:placetype":"venue"
},
  "geometry": {"coordinates":[-81.620195,30.199124],"type":"Point"}
}