{
  "type": "Feature",
  "properties": {
    "iso:country":"US",
    "sg:address":"13713 Rockridge Rd",
    "sg:city":"Lakeland",
    "sg:classifiers":[
        {
            "category":"Building & Trades",
            "subcategory":"Construction",
            "type":"Services"
        }
    ],
    "sg:phone":"+1 863 838 1592",
    "sg:postcode":"33809",
    "sg:province":"FL",
    "sg:tags":[
        "decorative",
        "washing",
        "removal",
        "concrete",
        "brush",
        "handy"
    ],
    "wof:name":"American Decorative Concrete",
    "wof:placetype":"venue"
},
  "geometry": {"coordinates":[-81.965102,28.252354],"type":"Point"}
}