{
  "type": "Feature",
  "properties": {
    "iso:country":"US",
    "sg:address":"6828 NW 77th Ct",
    "sg:city":"Miami",
    "sg:classifiers":[
        {
            "category":"Manufacturing",
            "subcategory":"Rubber & Plastics",
            "type":"Manufacturing & Wholesale Goods"
        }
    ],
    "sg:phone":"+1 305 718 3814",
    "sg:postcode":"33166",
    "sg:province":"FL",
    "sg:tags":[
        "products-manufacturers"
    ],
    "sg:website":"http://www.ipsfl.org",
    "wof:name":"Industrial Product Supplier",
    "wof:placetype":"venue"
},
  "geometry": {"coordinates":[-80.322378,25.835703],"type":"Point"}
}