{
  "type": "Feature",
  "properties": {
    "iso:country":"US",
    "sg:address":"506 9th Ave E",
    "sg:city":"Havana",
    "sg:classifiers":[
        {
            "category":"Building & Trades",
            "subcategory":"Construction",
            "type":"Services"
        }
    ],
    "sg:phone":"+1 850 539 9100",
    "sg:postcode":"32333",
    "sg:province":"FL",
    "sg:tags":[
        "maker",
        "cabinet"
    ],
    "wof:name":"Lincicome Wood Fixtures",
    "wof:placetype":"venue"
},
  "geometry": {"coordinates":[-84.41004100000001,30.624075],"type":"Point"}
}