{
  "type": "Feature",
  "properties": {
    "addr:full":"4025 N Highway 19a Mount Dora FL 32757",
    "addr:housenumber":"4025",
    "addr:postcode":"32757",
    "addr:street":"N Highway 19A",
    "iso:country":"US",
    "sg:address":"4025 N Highway 19a",
    "sg:city":"Mount Dora",
    "sg:classifiers":[
        {
            "category":"Bars & Pubs",
            "type":"Food & Drink"
        }
    ],
    "sg:menulink":"http://www.allmenus.com/fl/mount-dora/39179-zellies-pub/menu/",
    "sg:phone":"+1 352 483 3855",
    "sg:postcode":"32757",
    "sg:province":"FL",
    "sg:tags":[
        "american"
    ],
    "wof:name":"Zellie's Pub",
    "wof:placetype":"venue"
},
  "geometry": {"coordinates":[-81.685013,28.811616],"type":"Point"}
}