{
  "type": "Feature",
  "properties": {
    "addr:full":"1772 SW Oakwood Rd Port St Lucie FL 34953",
    "addr:housenumber":"1772",
    "addr:postcode":"34953",
    "addr:street":"Sw Oakwood Rd;St",
    "iso:country":"US",
    "sg:address":"1772 SW Oakwood Rd",
    "sg:city":"Port St Lucie",
    "sg:classifiers":[
        {
            "category":"Professional",
            "type":"Services"
        }
    ],
    "sg:phone":"+1 772 879 2791",
    "sg:postcode":"34953",
    "sg:province":"FL",
    "sg:tags":[
        "establishment"
    ],
    "wof:name":"CLR Enterprises",
    "wof:placetype":"venue"
},
  "geometry": {"coordinates":[-80.402863,27.267077],"type":"Point"}
}