{
  "type": "Feature",
  "properties": {
    "addr:full":"37 S Orange Ave Orlando FL 32801",
    "addr:housenumber":"37",
    "addr:postcode":"32801",
    "addr:street":"S Orange Ave",
    "iso:country":"US",
    "sg:address":"37 S Orange Ave",
    "sg:city":"Orlando",
    "sg:classifiers":[
        {
            "category":"Real Estate",
            "subcategory":"Developer",
            "type":"Services"
        }
    ],
    "sg:phone":"+1 407 660 9444",
    "sg:postcode":"32801",
    "sg:province":"FL",
    "sg:website":"www.broadstreetadvisors.com",
    "wof:name":"Broad Street Advisors LLC",
    "wof:placetype":"venue"
},
  "geometry": {"coordinates":[-81.378957,28.541607],"type":"Point"}
}