{
  "type": "Feature",
  "properties": {
    "iso:country":"US",
    "sg:address":"13937 SW 84th St",
    "sg:city":"Miami",
    "sg:classifiers":[
        {
            "category":"Shopping",
            "subcategory":"Computers & Home Electronics",
            "type":"Retail Goods"
        }
    ],
    "sg:phone":"+1 305 752 6838",
    "sg:postcode":"33183",
    "sg:province":"FL",
    "sg:tags":[
        "accessory"
    ],
    "wof:name":"A1 Network Trading Corp",
    "wof:placetype":"venue"
},
  "geometry": {"coordinates":[-80.419661,25.688615],"type":"Point"}
}