{
  "type": "Feature",
  "properties": {
    "addr:full":"547 E Rosewood Ln Tavares FL 32778",
    "addr:housenumber":"547",
    "addr:postcode":"32778",
    "addr:street":"E Rosewood Ln",
    "iso:country":"US",
    "sg:address":"547 E Rosewood Ln",
    "sg:city":"Tavares",
    "sg:classifiers":[
        {
            "category":"Building & Trades",
            "subcategory":"Construction",
            "type":"Services"
        }
    ],
    "sg:phone":"+1 352 343 7320",
    "sg:postcode":"32778",
    "sg:province":"FL",
    "sg:tags":[
        "house"
    ],
    "wof:name":"Country Square Home Builders",
    "wof:placetype":"venue"
},
  "geometry": {"coordinates":[-81.75291199999999,28.798502],"type":"Point"}
}