{
  "type": "Feature",
  "properties": {
    "addr:full":"120 State Street E, Suite #104 Oldsmar FL 34677",
    "addr:housenumber":"120",
    "addr:postcode":"34677",
    "addr:street":"State Street E Suite # 104",
    "iso:country":"US",
    "sg:address":"120 State Street E, Suite #104",
    "sg:city":"Oldsmar",
    "sg:classifiers":[
        {
            "category":"Professional",
            "subcategory":"Computer Services",
            "type":"Services"
        }
    ],
    "sg:phone":"+1 813 381 5144",
    "sg:postcode":"34677",
    "sg:province":"FL",
    "sg:tags":[
        "online-reservations",
        "central-reservation-system",
        "real-time-reservation-software",
        "valet-ticketing-software"
    ],
    "sg:website":"http://www.smcsoftware.com",
    "wof:name":"SMC Software",
    "wof:placetype":"venue"
},
  "geometry": {"coordinates":[-82.663641,28.037433],"type":"Point"}
}