{
  "type": "Feature",
  "properties": {
    "addr:full":"2258 Ali Baba Ave Opa Locka FL 33054",
    "addr:housenumber":"2258",
    "addr:postcode":"33054",
    "addr:street":"Ali Baba Ave;Locka",
    "iso:country":"US",
    "sg:address":"2258 Ali Baba Ave",
    "sg:city":"Opa Locka",
    "sg:classifiers":[
        {
            "category":"Autos & Motor Vehicles",
            "subcategory":"Automobile Sales",
            "type":"Retail Goods"
        }
    ],
    "sg:phone":"+1 305 687 3433",
    "sg:postcode":"33054",
    "sg:province":"FL",
    "sg:tags":[
        "car",
        "dealer"
    ],
    "wof:name":"Judah Auto Sales",
    "wof:placetype":"venue"
},
  "geometry": {"coordinates":[-80.237095,25.908486],"type":"Point"}
}