{
  "type": "Feature",
  "properties": {
    "addr:full":"292 NE 62nd St Miami FL 33138",
    "addr:housenumber":"292",
    "addr:postcode":"33138",
    "addr:street":"Ne 62Nd St",
    "iso:country":"US",
    "sg:address":"292 NE 62nd St",
    "sg:city":"Miami",
    "sg:classifiers":[
        {
            "category":"Retail",
            "subcategory":"Auto Repair",
            "type":"Services"
        }
    ],
    "sg:phone":"+1 305 754 1770",
    "sg:postcode":"33138",
    "sg:province":"FL",
    "sg:tags":[
        "repairing",
        "automobile"
    ],
    "wof:name":"Joe Auto Repair",
    "wof:placetype":"venue"
},
  "geometry": {"coordinates":[-80.190697,25.833],"type":"Point"}
}