{
  "type": "Feature",
  "properties": {
    "iso:country":"US",
    "sg:address":"216 John Carroll Rd E",
    "sg:city":"Lakeland",
    "sg:classifiers":[
        {
            "category":"Autos & Motor Vehicles",
            "subcategory":"Boat Sales",
            "type":"Retail Goods"
        }
    ],
    "sg:phone":"+1 863 665 8345",
    "sg:postcode":"33801",
    "sg:province":"FL",
    "sg:tags":[
        "repair",
        "outboard"
    ],
    "wof:name":"Outboard Motor Parts-Polk Cnty",
    "wof:placetype":"venue"
},
  "geometry": {"coordinates":[-81.86046399999999,28.042669],"type":"Point"}
}