{
  "type": "Feature",
  "properties": {
    "iso:country":"US",
    "sg:address":"1501 Davis Dr",
    "sg:city":"Tallahassee",
    "sg:classifiers":[
        {
            "category":"Building & Trades",
            "subcategory":"Construction",
            "type":"Services"
        }
    ],
    "sg:phone":"+1 850 878 1947",
    "sg:postcode":"32317",
    "sg:province":"FL",
    "sg:tags":[
        "restoration",
        "cleaning",
        "patio",
        "deck"
    ],
    "wof:name":"Mr Pressure Clean",
    "wof:placetype":"venue"
},
  "geometry": {"coordinates":[-84.201498,30.461841],"type":"Point"}
}