{
  "type": "Feature",
  "properties": {
    "addr:full":"11200 S Orange Blossom Trl Orlando FL 32837",
    "addr:housenumber":"11200",
    "addr:postcode":"32837",
    "addr:street":"S Orange Blossom Trl",
    "iso:country":"US",
    "sg:address":"11200 S Orange Blossom Trl",
    "sg:city":"Orlando",
    "sg:classifiers":[
        {
            "category":"Banks & Credit Unions",
            "subcategory":"Bank",
            "type":"Services"
        }
    ],
    "sg:phone":"+1 407 762 4786",
    "sg:postcode":"32837",
    "sg:province":"FL",
    "wof:name":"Sun Trust Bank",
    "wof:placetype":"venue"
},
  "geometry": {"coordinates":[-81.404602,28.399562],"type":"Point"}
}