{
  "type": "Feature",
  "properties": {
    "iso:country":"US",
    "sg:address":"204 Northcliff Dr",
    "sg:city":"Gulf Breeze",
    "sg:classifiers":[
        {
            "category":"Professional",
            "type":"Services"
        }
    ],
    "sg:phone":"+1 850 932 5735",
    "sg:postcode":"32561",
    "sg:province":"FL",
    "wof:name":"Sun Sonic Inc",
    "wof:placetype":"venue"
},
  "geometry": {"coordinates":[-87.16642400000001,30.366909],"type":"Point"}
}