{
  "type": "Feature",
  "properties": {
    "iso:country":"US",
    "sg:address":"19519 Equestrian Ln",
    "sg:city":"Dade City",
    "sg:classifiers":[
        {
            "category":"Insurance",
            "subcategory":"Title Insurance",
            "type":"Services"
        }
    ],
    "sg:phone":"+1 352 567 1146",
    "sg:postcode":"33523",
    "sg:province":"FL",
    "sg:tags":[
        "carrier"
    ],
    "wof:name":"A & A Title Insurance Agency",
    "wof:placetype":"venue"
},
  "geometry": {"coordinates":[-82.197548,28.442393],"type":"Point"}
}