{
  "type": "Feature",
  "properties": {
    "iso:country":"US",
    "sg:address":"2115 S Le Jeune Rd",
    "sg:city":"Coral Gables",
    "sg:classifiers":[
        {
            "category":"Building & Trades",
            "subcategory":"Locksmith",
            "type":"Services"
        }
    ],
    "sg:phone":"+1 786 228 5451",
    "sg:postcode":"33134",
    "sg:province":"FL",
    "sg:tags":[
        "key"
    ],
    "wof:name":"Coral Gables 24 Emergency Locksmith",
    "wof:placetype":"venue"
},
  "geometry": {"coordinates":[-80.26272,25.75316],"type":"Point"}
}