{
  "type": "Feature",
  "properties": {
    "addr:full":"6209 Deltona Blvd Spring Hill FL 34606",
    "addr:housenumber":"6209",
    "addr:postcode":"34606",
    "addr:street":"Deltona Blvd",
    "iso:country":"US",
    "sg:address":"6209 Deltona Blvd",
    "sg:city":"Spring Hill",
    "sg:classifiers":[
        {
            "category":"Personal",
            "subcategory":"Beauty Salon",
            "type":"Services"
        }
    ],
    "sg:phone":"+1 352 592 1117",
    "sg:postcode":"34606",
    "sg:province":"FL",
    "sg:tags":[
        "shop",
        "manicuring"
    ],
    "wof:name":"Nicholas Nails",
    "wof:placetype":"venue"
},
  "geometry": {"coordinates":[-82.564221,28.520241],"type":"Point"}
}