{
  "type": "Feature",
  "properties": {
    "addr:full":"3105 SW Ivy Pl Dunnellon FL 34431",
    "addr:housenumber":"3105",
    "addr:postcode":"34431",
    "addr:street":"Sw Ivy Pl",
    "iso:country":"US",
    "sg:address":"3105 SW Ivy Pl",
    "sg:city":"Dunnellon",
    "sg:classifiers":[
        {
            "category":"Government",
            "subcategory":"Office",
            "type":"Public Place"
        }
    ],
    "sg:phone":"+1 352 489 2807",
    "sg:postcode":"34431",
    "sg:province":"FL",
    "sg:tags":[
        "executive"
    ],
    "wof:name":"Rainbow Lks Ests Municpl Svc",
    "wof:placetype":"venue"
},
  "geometry": {"coordinates":[-82.48307800000001,29.148997],"type":"Point"}
}