{
  "type": "Feature",
  "properties": {
    "addr:full":"425 Madison Ct Fort Myers Beach FL 33931",
    "addr:housenumber":"425",
    "addr:postcode":"33931",
    "addr:street":"Madison Ct",
    "iso:country":"US",
    "sg:address":"425 Madison Ct",
    "sg:city":"Fort Myers Beach",
    "sg:classifiers":[
        {
            "category":"Shopping",
            "subcategory":"Computers & Home Electronics",
            "type":"Retail Goods"
        }
    ],
    "sg:phone":"+1 239 463 5510",
    "sg:postcode":"33931",
    "sg:province":"FL",
    "sg:tags":[
        "equipment",
        "electronic",
        "supply"
    ],
    "wof:name":"Tri Signal Integration Inc",
    "wof:placetype":"venue"
},
  "geometry": {"coordinates":[-81.92927,26.447651],"type":"Point"}
}