{
  "type": "Feature",
  "properties": {
    "addr:full":"4555 Palm Beach Blvd Fort Myers FL 33905",
    "addr:housenumber":"4555",
    "addr:postcode":"33905",
    "addr:street":"Palm Beach Blvd",
    "iso:country":"US",
    "sg:address":"4555 Palm Beach Blvd",
    "sg:city":"Fort Myers",
    "sg:classifiers":[
        {
            "category":"Professional",
            "subcategory":"Employment Agencies",
            "type":"Services"
        }
    ],
    "sg:phone":"+1 239 694 1775",
    "sg:postcode":"33905",
    "sg:province":"FL",
    "sg:tags":[
        "labor",
        "contractor"
    ],
    "wof:name":"Able Body Temporary Svc",
    "wof:placetype":"venue"
},
  "geometry": {"coordinates":[-81.819097,26.672703],"type":"Point"}
}