{
  "type": "Feature",
  "properties": {
    "addr:full":"980 Brevard Ave Rockledge FL 32955",
    "addr:housenumber":"980",
    "addr:postcode":"32955",
    "addr:street":"Brevard Ave",
    "iso:country":"US",
    "sg:address":"980 Brevard Ave",
    "sg:city":"Rockledge",
    "sg:classifiers":[
        {
            "category":"Health Services",
            "subcategory":"Doctor",
            "type":"Services"
        }
    ],
    "sg:phone":"+1 321 633 9973",
    "sg:postcode":"32955",
    "sg:province":"FL",
    "sg:tags":[
        "physician",
        "surgeon",
        "pediatrics"
    ],
    "wof:name":"Florida Pediatrics PA",
    "wof:placetype":"venue"
},
  "geometry": {"coordinates":[-80.726101,28.347991],"type":"Point"}
}