{
  "type": "Feature",
  "properties": {
    "addr:full":"1930 SW 7th St Boca Raton FL 33486",
    "addr:housenumber":"1930",
    "addr:postcode":"33486",
    "addr:street":"Sw 7Th St",
    "iso:country":"US",
    "sg:address":"1930 SW 7th St",
    "sg:city":"Boca Raton",
    "sg:classifiers":[
        {
            "category":"Health Services",
            "subcategory":"Doctor",
            "type":"Services"
        }
    ],
    "sg:phone":"+1 561 394 3605",
    "sg:postcode":"33486",
    "sg:province":"FL",
    "sg:tags":[
        "medical"
    ],
    "wof:name":"Yolanda Cintron Dr",
    "wof:placetype":"venue"
},
  "geometry": {"coordinates":[-80.121315,26.343553],"type":"Point"}
}