{
  "type": "Feature",
  "properties": {
    "iso:country":"US",
    "sg:address":"809 E Hibiscus Blvd",
    "sg:city":"Melbourne",
    "sg:classifiers":[
        {
            "category":"Shopping",
            "type":"Retail Goods"
        }
    ],
    "sg:phone":"+1 321 952 6661",
    "sg:postcode":"32901",
    "sg:province":"FL",
    "sg:tags":[
        "pet",
        "shop"
    ],
    "wof:name":"Reef Rascals Aquarium Inc",
    "wof:placetype":"venue"
},
  "geometry": {"coordinates":[-80.608031,28.085133],"type":"Point"}
}