{
  "type": "Feature",
  "properties": {
    "iso:country":"US",
    "sg:address":"125 Lakeview Dr",
    "sg:city":"Lake Placid",
    "sg:classifiers":[
        {
            "category":"Building & Trades",
            "subcategory":"Landscaping Services",
            "type":"Services"
        }
    ],
    "sg:phone":"+1 863 465 2953",
    "sg:postcode":"33852",
    "sg:province":"FL",
    "sg:tags":[
        "sod",
        "sodding"
    ],
    "wof:name":"Baxter & Son 621 Sod Farm",
    "wof:placetype":"venue"
},
  "geometry": {"coordinates":[-81.334439,27.273431],"type":"Point"}
}