{
  "type": "Feature",
  "properties": {
    "iso:country":"US",
    "sg:address":"11455 Scott Mill Rd",
    "sg:city":"Jacksonville",
    "sg:classifiers":[
        {
            "category":"Retail",
            "subcategory":"Repair Shop",
            "type":"Services"
        }
    ],
    "sg:phone":"+1 904 288 6641",
    "sg:postcode":"32223",
    "sg:province":"FL",
    "sg:tags":[
        "equipment",
        "telephone",
        "system"
    ],
    "wof:name":"Advantage Tel Of N Fl",
    "wof:placetype":"venue"
},
  "geometry": {"coordinates":[-81.64064,30.163754],"type":"Point"}
}