{
  "type": "Feature",
  "properties": {
    "iso:country":"US",
    "sg:address":"5729 Central Ave",
    "sg:city":"St Petersburg",
    "sg:classifiers":[
        {
            "category":"Professional",
            "subcategory":"Computer Services",
            "type":"Services"
        }
    ],
    "sg:phone":"+1 727 343 0875",
    "sg:postcode":"33710",
    "sg:province":"FL",
    "sg:tags":[
        "repair"
    ],
    "wof:name":"Operating Systems Of Florida",
    "wof:placetype":"venue"
},
  "geometry": {"coordinates":[-82.711832,27.770951],"type":"Point"}
}