{
  "type": "Feature",
  "properties": {
    "iso:country":"US",
    "sg:address":"15261 Briarcrest Cir",
    "sg:city":"Fort Myers",
    "sg:classifiers":[
        {
            "category":"Home & Garden",
            "subcategory":"Carpets & Floor Coverings",
            "type":"Retail Goods"
        }
    ],
    "sg:phone":"+1 239 939 2219",
    "sg:postcode":"33912",
    "sg:province":"FL",
    "sg:tags":[
        "carpeting"
    ],
    "wof:name":"Holaday Carpet Inc",
    "wof:placetype":"venue"
},
  "geometry": {"coordinates":[-81.84974699999999,26.520545],"type":"Point"}
}