{
  "type": "Feature",
  "properties": {
    "addr:full":"5607 Birch Dr Fort Pierce FL 34982",
    "addr:housenumber":"5607",
    "addr:postcode":"34982",
    "addr:street":"Birch Dr",
    "iso:country":"US",
    "sg:address":"5607 Birch Dr",
    "sg:city":"Fort Pierce",
    "sg:classifiers":[
        {
            "category":"Building & Trades",
            "subcategory":"Landscaping Services",
            "type":"Services"
        }
    ],
    "sg:phone":"+1 772 466 1183",
    "sg:postcode":"34982",
    "sg:province":"FL",
    "sg:tags":[
        "refuse",
        "system"
    ],
    "wof:name":"Budget Tree Co",
    "wof:placetype":"venue"
},
  "geometry": {"coordinates":[-80.30621600000001,27.366735],"type":"Point"}
}