{
  "type": "Feature",
  "properties": {
    "addr:full":"26 Waterford Dr Englewood FL 34223",
    "addr:housenumber":"26",
    "addr:postcode":"34223",
    "addr:street":"Waterford Dr",
    "iso:country":"US",
    "sg:address":"26 Waterford Dr",
    "sg:city":"Englewood",
    "sg:classifiers":[
        {
            "category":"Shopping",
            "subcategory":"Computers & Home Electronics",
            "type":"Retail Goods"
        }
    ],
    "sg:phone":"+1 941 473 0598",
    "sg:postcode":"34223",
    "sg:province":"FL",
    "wof:name":"Harry Addison Fax Computer",
    "wof:placetype":"venue"
},
  "geometry": {"coordinates":[-82.377736,26.997787],"type":"Point"}
}