{
  "type": "Feature",
  "properties": {
    "iso:country":"US",
    "sg:address":"910 SW 15th Ave",
    "sg:city":"Delray Beach",
    "sg:classifiers":[
        {
            "category":"Professional",
            "subcategory":"Engineering",
            "type":"Services"
        }
    ],
    "sg:phone":"+1 561 272 2950",
    "sg:postcode":"33444",
    "sg:province":"FL",
    "wof:name":"Custom Application Products",
    "wof:placetype":"venue"
},
  "geometry": {"coordinates":[-80.088256,26.447757],"type":"Point"}
}