{
  "type": "Feature",
  "properties": {
    "iso:country":"US",
    "sg:address":"7311 NW 44th St",
    "sg:city":"Miami",
    "sg:classifiers":[
        {
            "category":"Autos & Motor Vehicles",
            "subcategory":"Auto Supplies",
            "type":"Retail Goods"
        },
        {
            "category":"Structure",
            "subcategory":"Warehouse",
            "type":"Public Place"
        },
        {
            "category":"Retail",
            "subcategory":"Storage",
            "type":"Services"
        }
    ],
    "sg:phone":"+1 305 392 7481",
    "sg:postcode":"33166",
    "sg:province":"FL",
    "sg:tags":[
        "automobile",
        "self",
        "part",
        "warehouses-merchandise"
    ],
    "wof:name":"Cold Air Distributors Warehouse Of Florida, Inc.",
    "wof:placetype":"venue"
},
  "geometry": {"coordinates":[-80.31557599999999,25.814339],"type":"Point"}
}