{
  "type": "Feature",
  "properties": {
    "addr:full":"5219 14th St W Bradenton FL 34207",
    "addr:housenumber":"5219",
    "addr:postcode":"34207",
    "addr:street":"14Th St W",
    "iso:country":"US",
    "sg:address":"5219 14th St W",
    "sg:city":"Bradenton",
    "sg:classifiers":[
        {
            "category":"Shopping",
            "subcategory":"Clothing, Apparel, & Fashions",
            "type":"Retail Goods"
        }
    ],
    "sg:phone":"+1 941 758 7038",
    "sg:postcode":"34207",
    "sg:province":"FL",
    "sg:tags":[
        "equipment",
        "tennis"
    ],
    "wof:name":"Tennis City",
    "wof:placetype":"venue"
},
  "geometry": {"coordinates":[-82.57532399999999,27.450008],"type":"Point"}
}