{
  "type": "Feature",
  "properties": {
    "iso:country":"US",
    "sg:address":"8725 Peggy Ave",
    "sg:city":"Sarasota",
    "sg:classifiers":[
        {
            "category":"Professional",
            "subcategory":"Art Services",
            "type":"Services"
        }
    ],
    "sg:phone":"+1 941 966 6382",
    "sg:postcode":"34231",
    "sg:province":"FL",
    "sg:tags":[
        "photographer"
    ],
    "wof:name":"Subsurface Media",
    "wof:placetype":"venue"
},
  "geometry": {"coordinates":[-82.498017,27.22347],"type":"Point"}
}