{
  "type": "Feature",
  "properties": {
    "iso:country":"US",
    "sg:address":"1112 Waverly Rd",
    "sg:city":"Fort Lauderdale",
    "sg:classifiers":[
        {
            "category":"Professional",
            "subcategory":"Lawyer & Legal Services",
            "type":"Services"
        }
    ],
    "sg:phone":"+1 954 523 6800",
    "sg:postcode":"33312",
    "sg:province":"FL",
    "wof:name":"Johnson H Wesly",
    "wof:placetype":"venue"
},
  "geometry": {"coordinates":[-80.156978,26.116274],"type":"Point"}
}