{
  "type": "Feature",
  "properties": {
    "addr:full":"20350 Summerlin Rd Ste 4125 Fort Myers FL 33908",
    "addr:housenumber":"20350",
    "addr:postcode":"fort myers fl 33908",
    "addr:street":"Summerlin Rd Ste 4125",
    "iso:country":"US",
    "sg:address":"20350 Summerlin Rd Ste 4125",
    "sg:city":"Fort Myers",
    "sg:classifiers":[
        {
            "category":"Shopping",
            "subcategory":"Shoes",
            "type":"Retail Goods"
        }
    ],
    "sg:phone":"+1 239 454 1508",
    "sg:postcode":"33908",
    "sg:province":"FL",
    "sg:tags":[
        "store"
    ],
    "wof:name":"Sas Factory Shoe Store",
    "wof:placetype":"venue"
},
  "geometry": {"coordinates":[-81.974733,26.494502],"type":"Point"}
}