{
  "type": "Feature",
  "properties": {
    "iso:country":"US",
    "sg:address":"893 S Spring Garden Ave",
    "sg:city":"Deland",
    "sg:classifiers":[
        {
            "category":"Wholesale",
            "subcategory":"Machinery & Supplies",
            "type":"Manufacturing & Wholesale Goods"
        }
    ],
    "sg:phone":"+1 386 736 9521",
    "sg:postcode":"32720",
    "sg:province":"FL",
    "sg:tags":[
        "washing",
        "mach"
    ],
    "wof:name":"Allstar Coin Laundry",
    "wof:placetype":"venue"
},
  "geometry": {"coordinates":[-81.32370299999999,29.013536],"type":"Point"}
}