{
  "type": "Feature",
  "properties": {
    "iso:country":"US",
    "sg:address":"800 S Main St",
    "sg:city":"Belle Glade",
    "sg:classifiers":[
        {
            "category":"Banks & Credit Unions",
            "subcategory":"Bank",
            "type":"Services"
        }
    ],
    "sg:phone":"+1 561 996 8000",
    "sg:postcode":"33430",
    "sg:province":"FL",
    "sg:tags":[
        "state",
        "commercial"
    ],
    "wof:name":"First Cmnty Bnk Palm Bch Cnty",
    "wof:placetype":"venue"
},
  "geometry": {"coordinates":[-80.670433,26.676564],"type":"Point"}
}