{
  "type": "Feature",
  "properties": {
    "addr:full":"419 E Polk St Tampa FL 33602",
    "addr:housenumber":"419",
    "addr:postcode":"33602",
    "addr:street":"E Polk St",
    "iso:country":"US",
    "sg:address":"419 E Polk St",
    "sg:city":"Tampa",
    "sg:classifiers":[
        {
            "category":"Education",
            "subcategory":"School",
            "type":"Public Place"
        }
    ],
    "sg:phone":"+1 813 233 2333",
    "sg:postcode":"33602",
    "sg:province":"FL",
    "sg:website":"www.sdhc.k12.fl.us",
    "wof:name":"Downtown Partnership School",
    "wof:placetype":"venue"
},
  "geometry": {"coordinates":[-82.457667,27.951117],"type":"Point"}
}