{
  "type": "Feature",
  "properties": {
    "iso:country":"US",
    "sg:address":"739 Industry Rd",
    "sg:city":"Longwood",
    "sg:classifiers":[
        {
            "category":"Autos & Motor Vehicles",
            "subcategory":"Auto Supplies",
            "type":"Retail Goods"
        }
    ],
    "sg:phone":"+1 407 332 8970",
    "sg:postcode":"32750",
    "sg:province":"FL",
    "sg:tags":[
        "tire"
    ],
    "wof:name":"Tire Center",
    "wof:placetype":"venue"
},
  "geometry": {"coordinates":[-81.32922499999999,28.709515],"type":"Point"}
}