{
  "type": "Feature",
  "properties": {
    "iso:country":"US",
    "sg:address":"2150 Collier Ave Ste R",
    "sg:city":"Fort Myers",
    "sg:classifiers":[
        {
            "category":"Communications",
            "subcategory":"Newspaper",
            "type":"Services"
        }
    ],
    "sg:phone":"+1 239 277 1988",
    "sg:postcode":"33901",
    "sg:province":"FL",
    "sg:tags":[
        "print",
        "medium"
    ],
    "wof:name":"Christian Life-Times Llc",
    "wof:placetype":"venue"
},
  "geometry": {"coordinates":[-81.869282,26.607923],"type":"Point"}
}