{
  "type": "Feature",
  "properties": {
    "iso:country":"US",
    "sg:address":"3110 US Hwy 92",
    "sg:city":"Lakeland",
    "sg:classifiers":[
        {
            "category":"Education",
            "subcategory":"School",
            "type":"Public Place"
        }
    ],
    "sg:phone":"+1 863 665 4188",
    "sg:postcode":"33801",
    "sg:province":"FL",
    "sg:website":"www.santafecatholic.org",
    "wof:name":"Sante Fe Catholic High School",
    "wof:placetype":"venue"
},
  "geometry": {"coordinates":[-81.89789500000001,28.047995],"type":"Point"}
}