{
  "type": "Feature",
  "properties": {
    "iso:country":"US",
    "sg:address":"333 W Cocoa Beach Cswy",
    "sg:city":"Cocoa Beach",
    "sg:classifiers":[
        {
            "category":"Health Services",
            "subcategory":"Clinic",
            "type":"Services"
        }
    ],
    "sg:phone":"+1 321 783 2662",
    "sg:postcode":"32931",
    "sg:province":"FL",
    "wof:name":"Space Coast Lactation Cons",
    "wof:placetype":"venue"
},
  "geometry": {"coordinates":[-80.61057099999999,28.357996],"type":"Point"}
}