{
  "type": "Feature",
  "properties": {
    "addr:full":"2904 E Hwy 98 Panama City FL 32401",
    "addr:housenumber":"2904",
    "addr:postcode":"32401",
    "addr:street":"E Hwy 98",
    "iso:country":"US",
    "sg:address":"2904 E Hwy 98",
    "sg:city":"Panama City",
    "sg:classifiers":[
        {
            "category":"Shopping",
            "subcategory":"Musical Instruments",
            "type":"Retail Goods"
        }
    ],
    "sg:phone":"+1 850 872 1686",
    "sg:postcode":"32401",
    "sg:province":"FL",
    "wof:name":"Dynamic Prosound Lighting & DJ",
    "wof:placetype":"venue"
},
  "geometry": {"coordinates":[-85.621059,30.155947],"type":"Point"}
}