{
  "type": "Feature",
  "properties": {
    "iso:country":"US",
    "sg:address":"1584 Kingsley Ave",
    "sg:city":"Orange Park",
    "sg:classifiers":[
        {
            "category":"Health Services",
            "subcategory":"Doctor",
            "type":"Services"
        }
    ],
    "sg:phone":"+1 904 269 1303",
    "sg:postcode":"32073",
    "sg:province":"FL",
    "sg:tags":[
        "dentist"
    ],
    "wof:name":"John Harrington DDS",
    "wof:placetype":"venue"
},
  "geometry": {"coordinates":[-81.72994,30.164372],"type":"Point"}
}