{
  "type": "Feature",
  "properties": {
    "addr:full":"2435 S Hiawassee Rd Orlando FL 32835",
    "addr:housenumber":"2435",
    "addr:postcode":"32835",
    "addr:street":"S Hiawassee Rd",
    "iso:country":"US",
    "sg:address":"2435 S Hiawassee Rd",
    "sg:city":"Orlando",
    "sg:classifiers":[
        {
            "category":"Food & Beverages",
            "subcategory":"Groceries & Convenience Stores",
            "type":"Retail Goods"
        }
    ],
    "sg:phone":"+1 407 294 7104",
    "sg:postcode":"32835",
    "sg:province":"FL",
    "sg:tags":[
        "grocer"
    ],
    "wof:name":"Publix Super Market",
    "wof:placetype":"venue"
},
  "geometry": {"coordinates":[-81.484802,28.516011],"type":"Point"}
}