{
  "type": "Feature",
  "properties": {
    "iso:country":"US",
    "sg:address":"105 7th Ave NE",
    "sg:city":"Ruskin",
    "sg:classifiers":[
        {
            "category":"Professional",
            "subcategory":"Accounting & Tax Preparation",
            "type":"Services"
        }
    ],
    "sg:phone":"+1 813 645 4000",
    "sg:postcode":"33570",
    "sg:province":"FL",
    "sg:tags":[
        "accountant"
    ],
    "wof:name":"Abacus Business & Tax Svc",
    "wof:placetype":"venue"
},
  "geometry": {"coordinates":[-82.432316,27.724225],"type":"Point"}
}