{
  "type": "Feature",
  "properties": {
    "addr:full":"11482 Columbia Park Dr W Jacksonville FL 32258",
    "addr:housenumber":"11482",
    "addr:postcode":"32258",
    "addr:street":"Columbia Park Dr W",
    "iso:country":"US",
    "sg:address":"11482 Columbia Park Dr W",
    "sg:city":"Jacksonville",
    "sg:classifiers":[
        {
            "category":"Home & Garden",
            "subcategory":"Hardware",
            "type":"Retail Goods"
        }
    ],
    "sg:phone":"+1 904 370 1045",
    "sg:postcode":"32258",
    "sg:province":"FL",
    "sg:tags":[
        "tool",
        "used"
    ],
    "wof:name":"Brock Tool Co",
    "wof:placetype":"venue"
},
  "geometry": {"coordinates":[-81.54131599999999,30.161712],"type":"Point"}
}