{
  "type": "Feature",
  "properties": {
    "addr:full":"1303 N 9th Ave Pensacola FL 32503",
    "addr:housenumber":"1303",
    "addr:postcode":"32503",
    "addr:street":"N 9Th Ave",
    "iso:country":"US",
    "sg:address":"1303 N 9th Ave",
    "sg:city":"Pensacola",
    "sg:classifiers":[
        {
            "category":"Shopping",
            "subcategory":"Discount & Variety Stores",
            "type":"Retail Goods"
        }
    ],
    "sg:phone":"+1 850 438 8999",
    "sg:postcode":"32503",
    "sg:province":"FL",
    "sg:tags":[
        "equipment",
        "establishment"
    ],
    "wof:name":"Unity Beauty",
    "wof:placetype":"venue"
},
  "geometry": {"coordinates":[-87.208018,30.426825],"type":"Point"}
}