{
  "type": "Feature",
  "properties": {
    "iso:country":"US",
    "sg:address":"231 SE 6th Ter",
    "sg:city":"Cape Coral",
    "sg:classifiers":[
        {
            "category":"Freight",
            "type":"Transportation"
        }
    ],
    "sg:phone":"+1 239 242 0851",
    "sg:postcode":"33990",
    "sg:province":"FL",
    "wof:name":"Befi Transport Inc",
    "wof:placetype":"venue"
},
  "geometry": {"coordinates":[-81.965458,26.639515],"type":"Point"}
}