{
  "type": "Feature",
  "properties": {
    "addr:full":"20070 Cortez Blvd Brooksville FL 34601",
    "addr:housenumber":"20070",
    "addr:postcode":"34601",
    "addr:street":"Cortez Blvd",
    "iso:country":"US",
    "sg:address":"20070 Cortez Blvd",
    "sg:city":"Brooksville",
    "sg:classifiers":[
        {
            "category":"Home & Garden",
            "subcategory":"Building Materials",
            "type":"Retail Goods"
        },
        {
            "category":"Wholesale",
            "subcategory":"Painting Supplies",
            "type":"Manufacturing & Wholesale Goods"
        }
    ],
    "sg:phone":"+1 352 796 2622",
    "sg:postcode":"34601",
    "sg:province":"FL",
    "sg:tags":[
        "paint"
    ],
    "wof:name":"PPG Porter Paints",
    "wof:placetype":"venue"
},
  "geometry": {"coordinates":[-82.40037100000001,28.539187],"type":"Point"}
}