{
  "type": "Feature",
  "properties": {
    "addr:full":"340 Hunters Point Ct Longwood FL 32779",
    "addr:housenumber":"340",
    "addr:postcode":"32779",
    "addr:street":"Hunters Point Ct",
    "iso:country":"US",
    "sg:address":"340 Hunters Point Ct",
    "sg:city":"Longwood",
    "sg:classifiers":[
        {
            "category":"Restaurant",
            "type":"Food & Drink"
        }
    ],
    "sg:phone":"+1 407 682 6364",
    "sg:postcode":"32779",
    "sg:province":"FL",
    "sg:tags":[
        "eating"
    ],
    "wof:name":"Eightyeight Inc",
    "wof:placetype":"venue"
},
  "geometry": {"coordinates":[-81.445305,28.697945],"type":"Point"}
}