{
  "type": "Feature",
  "properties": {
    "iso:country":"US",
    "sg:address":"13981 McGregor Blvd Suite 103",
    "sg:city":"Fort Myers",
    "sg:classifiers":[
        {
            "category":"Health Services",
            "subcategory":"Doctor",
            "type":"Services"
        }
    ],
    "sg:phone":"+1 239 333 1140",
    "sg:postcode":"33908",
    "sg:province":"FL",
    "sg:tags":[
        "surgeon",
        "oral"
    ],
    "sg:website":"draulino.com",
    "wof:name":"Carmen Aulino, DDS",
    "wof:placetype":"venue"
},
  "geometry": {"coordinates":[-81.917793,26.538657],"type":"Point"}
}