{
  "type": "Feature",
  "properties": {
    "addr:full":"7505 Alloway St Tampa FL 33625",
    "addr:housenumber":"7505",
    "addr:postcode":"33625",
    "addr:street":"Alloway St",
    "iso:country":"US",
    "sg:address":"7505 Alloway St",
    "sg:city":"Tampa",
    "sg:classifiers":[
        {
            "category":"Professional",
            "subcategory":"Accounting & Tax Preparation",
            "type":"Services"
        }
    ],
    "sg:phone":"+1 813 949 5544",
    "sg:postcode":"33625",
    "sg:province":"FL",
    "sg:tags":[
        "accountant",
        "public"
    ],
    "wof:name":"Aru Business Services PA",
    "wof:placetype":"venue"
},
  "geometry": {"coordinates":[-82.569349,28.077951],"type":"Point"}
}