{
  "type": "Feature",
  "properties": {
    "addr:full":"2257 N Palafox St Pensacola FL 32501",
    "addr:housenumber":"2257",
    "addr:postcode":"32501",
    "addr:street":"N Palafox St",
    "iso:country":"US",
    "sg:address":"2257 N Palafox St",
    "sg:city":"Pensacola",
    "sg:classifiers":[
        {
            "category":"Government",
            "subcategory":"Court House",
            "type":"Public Place"
        }
    ],
    "sg:phone":"+1 850 595 3728",
    "sg:postcode":"32501",
    "sg:province":"FL",
    "sg:tags":[
        "state"
    ],
    "sg:website":"www.flgal.com",
    "wof:name":"Guardian Ad Litem",
    "wof:placetype":"venue"
},
  "geometry": {"coordinates":[-87.220562,30.43494],"type":"Point"}
}