{
  "type": "Feature",
  "properties": {
    "iso:country":"US",
    "sg:address":"3853 5th Ave N",
    "sg:city":"St Petersburg",
    "sg:classifiers":[
        {
            "category":"Building & Trades",
            "subcategory":"Electrical",
            "type":"Services"
        }
    ],
    "sg:phone":"+1 727 560 2190",
    "sg:postcode":"33713",
    "sg:province":"FL",
    "sg:tags":[
        "installation"
    ],
    "wof:name":"Elisabeth Bink & Son Instltns",
    "wof:placetype":"venue"
},
  "geometry": {"coordinates":[-82.68605100000001,27.777351],"type":"Point"}
}