{
  "type": "Feature",
  "properties": {
    "iso:country":"US",
    "sg:address":"11509 Hidden Cove Ct",
    "sg:city":"New Port Richey",
    "sg:classifiers":[
        {
            "category":"Building & Trades",
            "subcategory":"Construction",
            "type":"Services"
        }
    ],
    "sg:phone":"+1 727 375 5536",
    "sg:postcode":"34655",
    "sg:province":"FL",
    "sg:tags":[
        "home",
        "builder",
        "operative"
    ],
    "wof:name":"Rutenberg Homes Inc",
    "wof:placetype":"venue"
},
  "geometry": {"coordinates":[-82.624882,28.179326],"type":"Point"}
}