{
  "type": "Feature",
  "properties": {
    "addr:full":"14788 Palm Beach Point Blvd West Palm Beach FL 33414",
    "addr:housenumber":"14788",
    "addr:postcode":"33414",
    "addr:street":"Palm Beach Point Blvd",
    "iso:country":"US",
    "sg:address":"14788 Palm Beach Point Blvd",
    "sg:city":"West Palm Beach",
    "sg:classifiers":[
        {
            "category":"Professional",
            "subcategory":"Engineering",
            "type":"Services"
        }
    ],
    "sg:phone":"+1 561 798 9708",
    "sg:postcode":"33414",
    "sg:province":"FL",
    "wof:name":"I R Associates",
    "wof:placetype":"venue"
},
  "geometry": {"coordinates":[-80.284175,26.613794],"type":"Point"}
}