{
  "type": "Feature",
  "properties": {
    "iso:country":"US",
    "sg:address":"2801 Ponce de Leon Blvd",
    "sg:city":"Miami",
    "sg:classifiers":[
        {
            "category":"Manufacturing",
            "subcategory":"Printing",
            "type":"Manufacturing & Wholesale Goods"
        }
    ],
    "sg:phone":"+1 305 446 3133",
    "sg:postcode":"33134",
    "sg:province":"FL",
    "sg:tags":[
        "periodical"
    ],
    "wof:name":"U S News & World Report",
    "wof:placetype":"venue"
},
  "geometry": {"coordinates":[-80.258138,25.745551],"type":"Point"}
}