{
  "type": "Feature",
  "properties": {
    "iso:country":"US",
    "sg:address":"1202 Homosassa Ct",
    "sg:city":"Longwood",
    "sg:classifiers":[
        {
            "category":"Shopping",
            "subcategory":"Clothing, Apparel, & Fashions",
            "type":"Retail Goods"
        }
    ],
    "sg:phone":"+1 407 862 4292",
    "sg:postcode":"32779",
    "sg:province":"FL",
    "sg:tags":[
        "western",
        "accessory"
    ],
    "wof:name":"American Cowboy Assn Inc",
    "wof:placetype":"venue"
},
  "geometry": {"coordinates":[-81.379791,28.713778],"type":"Point"}
}