{
  "type": "Feature",
  "properties": {
    "iso:country":"US",
    "sg:address":"312 Lagoon Ave",
    "sg:city":"Naples",
    "sg:classifiers":[
        {
            "category":"Building & Trades",
            "subcategory":"Construction",
            "type":"Services"
        }
    ],
    "sg:phone":"+1 239 594 6978",
    "sg:postcode":"34108",
    "sg:province":"FL",
    "sg:tags":[
        "general",
        "contractor"
    ],
    "wof:name":"Surety Construction Co",
    "wof:placetype":"venue"
},
  "geometry": {"coordinates":[-81.818635,26.260775],"type":"Point"}
}