{
  "type": "Feature",
  "properties": {
    "iso:country":"US",
    "sg:address":"3300 Windywood Dr",
    "sg:city":"Orlando",
    "sg:classifiers":[
        {
            "category":"Travel",
            "subcategory":"Travel Agent",
            "type":"Entertainment"
        }
    ],
    "sg:phone":"+1 407 823 9474",
    "sg:postcode":"32812",
    "sg:province":"FL",
    "sg:tags":[
        "operator",
        "tour"
    ],
    "wof:name":"Le Holiday Traveler",
    "wof:placetype":"venue"
},
  "geometry": {"coordinates":[-81.32240299999999,28.509304],"type":"Point"}
}