{
  "type": "Feature",
  "properties": {
    "iso:country":"US",
    "sg:address":"8230 NW 103rd St",
    "sg:city":"Hialeah",
    "sg:classifiers":[
        {
            "category":"Restaurant",
            "type":"Food & Drink"
        }
    ],
    "sg:phone":"+1 305 362 6199",
    "sg:postcode":"33016",
    "sg:province":"FL",
    "wof:name":"Fritanga Las Piedresitas",
    "wof:placetype":"venue"
},
  "geometry": {"coordinates":[-80.33005900000001,25.869178],"type":"Point"}
}