{
  "type": "Feature",
  "properties": {
    "iso:country":"US",
    "sg:address":"2996 Edgewater Dr",
    "sg:city":"Orlando",
    "sg:classifiers":[
        {
            "category":"Shopping",
            "subcategory":"Musical Instruments",
            "type":"Retail Goods"
        }
    ],
    "sg:phone":"+1 407 650 0183",
    "sg:postcode":"32804",
    "sg:province":"FL",
    "wof:name":"Southport Guitar Studio",
    "wof:placetype":"venue"
},
  "geometry": {"coordinates":[-81.389653,28.579916],"type":"Point"}
}