{
  "type": "Feature",
  "properties": {
    "addr:full":"10662 Fontainebleau Blvd Miami FL 33172",
    "addr:housenumber":"10662",
    "addr:postcode":"33172",
    "addr:street":"Fontainebleau Blvd",
    "iso:country":"US",
    "sg:address":"10662 Fontainebleau Blvd",
    "sg:city":"Miami",
    "sg:classifiers":[
        {
            "category":"Restaurant",
            "type":"Food & Drink"
        }
    ],
    "sg:phone":"+1 305 228 1233",
    "sg:postcode":"33172",
    "sg:province":"FL",
    "sg:tags":[
        "american",
        "latin"
    ],
    "wof:name":"Date Aqui Pana",
    "wof:placetype":"venue"
},
  "geometry": {"coordinates":[-80.369102,25.7756],"type":"Point"}
}