{
  "type": "Feature",
  "properties": {
    "addr:full":"14050 W Highway 326 Morriston FL 32668",
    "addr:housenumber":"14050",
    "addr:postcode":"32668",
    "addr:street":"W Highway 326",
    "iso:country":"US",
    "sg:address":"14050 W Highway 326",
    "sg:city":"Morriston",
    "sg:classifiers":[
        {
            "category":"Farming",
            "subcategory":"Farm",
            "type":"Manufacturing & Wholesale Goods"
        }
    ],
    "sg:phone":"+1 352 690 7671",
    "sg:postcode":"32668",
    "sg:province":"FL",
    "wof:name":"Stoneriggs Farm Inc",
    "wof:placetype":"venue"
},
  "geometry": {"coordinates":[-82.351737,29.283022],"type":"Point"}
}