{
  "type": "Feature",
  "properties": {
    "iso:country":"US",
    "sg:address":"2988 Cadiz Rd",
    "sg:city":"Boca Raton",
    "sg:classifiers":[
        {
            "category":"Manufacturing",
            "subcategory":"Lumber",
            "type":"Manufacturing & Wholesale Goods"
        }
    ],
    "sg:phone":"+1 561 395 2199",
    "sg:postcode":"33432",
    "sg:province":"FL",
    "sg:tags":[
        "insulation",
        "control",
        "pest",
        "contractor"
    ],
    "wof:name":"Nuisance Wildlife Solutions",
    "wof:placetype":"venue"
},
  "geometry": {"coordinates":[-80.07768299999999,26.321908],"type":"Point"}
}