{
  "type": "Feature",
  "properties": {
    "addr:full":"4291 E Hwy 316 Citra FL 32113",
    "addr:housenumber":"4291",
    "addr:postcode":"32113",
    "addr:street":"E Hwy 316",
    "iso:country":"US",
    "sg:address":"4291 E Hwy 316",
    "sg:city":"Citra",
    "sg:classifiers":[
        {
            "category":"Building & Trades",
            "subcategory":"Plumbing",
            "type":"Services"
        }
    ],
    "sg:phone":"+1 352 629 3848",
    "sg:postcode":"32113",
    "sg:province":"FL",
    "sg:tags":[
        "plumbing",
        "contractor"
    ],
    "wof:name":"D J's Root Scooter",
    "wof:placetype":"venue"
},
  "geometry": {"coordinates":[-82.072001,29.361227],"type":"Point"}
}