{
  "type": "Feature",
  "properties": {
    "iso:country":"US",
    "sg:address":"1813 Welland Dr",
    "sg:city":"Clearwater",
    "sg:classifiers":[
        {
            "category":"Wholesale",
            "subcategory":"Office Equipment",
            "type":"Manufacturing & Wholesale Goods"
        }
    ],
    "sg:phone":"+1 727 518 0288",
    "sg:postcode":"33756",
    "sg:province":"FL",
    "wof:name":"Blair Business Machines Inc",
    "wof:placetype":"venue"
},
  "geometry": {"coordinates":[-82.781598,27.928792],"type":"Point"}
}