{
  "type": "Feature",
  "properties": {
    "addr:full":"12551 Wainwright Dr Immokalee FL 34142",
    "addr:housenumber":"12551",
    "addr:postcode":"34142",
    "addr:street":"Wainwright Dr",
    "iso:country":"US",
    "sg:address":"12551 Wainwright Dr",
    "sg:city":"Immokalee",
    "sg:classifiers":[
        {
            "category":"Manufacturing",
            "subcategory":"Food",
            "type":"Manufacturing & Wholesale Goods"
        },
        {
            "category":"Wholesale",
            "subcategory":"Groceries",
            "type":"Manufacturing & Wholesale Goods"
        }
    ],
    "sg:phone":"+1 239 657 2887",
    "sg:postcode":"34142",
    "sg:province":"FL",
    "sg:tags":[
        "product",
        "products-wholesale"
    ],
    "wof:name":"Keefe Commissary Network",
    "wof:placetype":"venue"
},
  "geometry": {"coordinates":[-81.241801,26.311921],"type":"Point"}
}