{
  "type": "Feature",
  "properties": {
    "iso:country":"US",
    "sg:address":"1735 Palm Beach Trace Dr",
    "sg:city":"West Palm Beach",
    "sg:classifiers":[
        {
            "category":"Banks & Credit Unions",
            "subcategory":"Bank",
            "type":"Services"
        }
    ],
    "sg:phone":"+1 561 792 3977",
    "sg:postcode":"33411",
    "sg:province":"FL",
    "sg:tags":[
        "broker",
        "mortgage"
    ],
    "wof:name":"J B Mortgage Group Inc",
    "wof:placetype":"venue"
},
  "geometry": {"coordinates":[-80.225909,26.712566],"type":"Point"}
}