{
  "type": "Feature",
  "properties": {
    "iso:country":"US",
    "sg:address":"191 Eglin Pkwy S",
    "sg:city":"Fort Walton Bch",
    "sg:classifiers":[
        {
            "category":"Food & Beverages",
            "subcategory":"Groceries & Convenience Stores",
            "type":"Retail Goods"
        }
    ],
    "sg:phone":"+1 850 244 4808",
    "sg:postcode":"32548",
    "sg:province":"FL",
    "wof:name":"Exprezit",
    "wof:placetype":"venue"
},
  "geometry": {"coordinates":[-86.606306,30.405309],"type":"Point"}
}