{
  "type": "Feature",
  "properties": {
    "iso:country":"US",
    "sg:address":"1183 Groveland Dr",
    "sg:city":"Chuluota",
    "sg:classifiers":[
        {
            "category":"Personal",
            "subcategory":"Beauty Salon",
            "type":"Services"
        }
    ],
    "sg:phone":"+1 407 359 2303",
    "sg:postcode":"32766",
    "sg:province":"FL",
    "wof:name":"Totally You Llc",
    "wof:placetype":"venue"
},
  "geometry": {"coordinates":[-81.098122,28.658001],"type":"Point"}
}