{
  "type": "Feature",
  "properties": {
    "iso:country":"US",
    "sg:address":"125 SE 43rd Ter",
    "sg:city":"Cape Coral",
    "sg:classifiers":[
        {
            "category":"Building & Trades",
            "subcategory":"Construction",
            "type":"Services"
        }
    ],
    "sg:phone":"+1 239 549 7866",
    "sg:postcode":"33904",
    "sg:province":"FL",
    "sg:tags":[
        "floor",
        "laying",
        "contractor"
    ],
    "wof:name":"Frank E Walsh",
    "wof:placetype":"venue"
},
  "geometry": {"coordinates":[-81.972268,26.571914],"type":"Point"}
}