{
  "type": "Feature",
  "properties": {
    "addr:full":"5658 25th Street Cir E Bradenton FL 34203",
    "addr:housenumber":"5658",
    "addr:postcode":"34203",
    "addr:street":"25Th Street Cir E",
    "iso:country":"US",
    "sg:address":"5658 25th Street Cir E",
    "sg:city":"Bradenton",
    "sg:classifiers":[
        {
            "category":"Manufacturing",
            "subcategory":"Signs",
            "type":"Manufacturing & Wholesale Goods"
        }
    ],
    "sg:phone":"+1 941 727 1620",
    "sg:postcode":"34203",
    "sg:province":"FL",
    "wof:name":"Signs With Designs",
    "wof:placetype":"venue"
},
  "geometry": {"coordinates":[-82.53139299999999,27.440678],"type":"Point"}
}