{
  "type": "Feature",
  "properties": {
    "iso:country":"US",
    "sg:address":"6411 E 113th Ave",
    "sg:city":"Tampa",
    "sg:classifiers":[
        {
            "category":"Banks & Credit Unions",
            "subcategory":"Bank",
            "type":"Services"
        }
    ],
    "sg:phone":"+1 813 989 2501",
    "sg:postcode":"33617",
    "sg:province":"FL",
    "sg:tags":[
        "development",
        "financing",
        "plan",
        "business"
    ],
    "wof:name":"Crollick Enterprises Inc",
    "wof:placetype":"venue"
},
  "geometry": {"coordinates":[-82.378747,28.05071],"type":"Point"}
}