{
  "type": "Feature",
  "properties": {
    "iso:country":"US",
    "sg:address":"8243 Navarre Pkwy",
    "sg:city":"Navarre",
    "sg:classifiers":[
        {
            "category":"Personal",
            "subcategory":"Nail Salon",
            "type":"Services"
        }
    ],
    "sg:phone":"+1 850 939 3060",
    "sg:postcode":"32566",
    "sg:province":"FL",
    "wof:name":"Navarre Nails",
    "wof:placetype":"venue"
},
  "geometry": {"coordinates":[-86.877235,30.401564],"type":"Point"}
}