{
  "type": "Feature",
  "properties": {
    "addr:full":"590 Riverside Dr Coral Springs FL 33071",
    "addr:housenumber":"590",
    "addr:postcode":"33071",
    "addr:street":"Riverside Dr",
    "iso:country":"US",
    "sg:address":"590 Riverside Dr",
    "sg:city":"Coral Springs",
    "sg:classifiers":[
        {
            "category":"Travel",
            "subcategory":"Travel Agent",
            "type":"Entertainment"
        }
    ],
    "sg:phone":"+1 954 340 0410",
    "sg:postcode":"33071",
    "sg:province":"FL",
    "sg:tags":[
        "agency",
        "cruise"
    ],
    "wof:name":"All Ports of Call Inc",
    "wof:placetype":"venue"
},
  "geometry": {"coordinates":[-80.244551,26.238233],"type":"Point"}
}