{
  "type": "Feature",
  "properties": {
    "iso:country":"US",
    "sg:address":"5992 Ansel Ferrel Rd",
    "sg:city":"Tallahassee",
    "sg:classifiers":[
        {
            "category":"Professional",
            "subcategory":"Business Services",
            "type":"Services"
        }
    ],
    "sg:phone":"+1 850 668 3111",
    "sg:postcode":"32309",
    "sg:province":"FL",
    "sg:tags":[
        "drafting"
    ],
    "wof:name":"Oasis Designs Inc",
    "wof:placetype":"venue"
},
  "geometry": {"coordinates":[-84.178877,30.565811],"type":"Point"}
}