{
  "type": "Feature",
  "properties": {
    "addr:full":"8600 SW 67th Ave Miami FL 33143",
    "addr:housenumber":"8600",
    "addr:postcode":"33143",
    "addr:street":"Sw 67Th Ave",
    "iso:country":"US",
    "sg:address":"8600 SW 67th Ave",
    "sg:city":"Miami",
    "sg:classifiers":[
        {
            "category":"Social Services",
            "subcategory":"Job Training",
            "type":"Services"
        }
    ],
    "sg:phone":"+1 305 498 1908",
    "sg:postcode":"33143",
    "sg:province":"FL",
    "sg:tags":[
        "rehabilitation"
    ],
    "wof:name":"Quality Rehab Ctr Inc",
    "wof:placetype":"venue"
},
  "geometry": {"coordinates":[-80.30303499999999,25.689009],"type":"Point"}
}