{
  "type": "Feature",
  "properties": {
    "addr:full":"1780 S Woodland Blvd Deland FL 32720",
    "addr:housenumber":"1780",
    "addr:postcode":"32720",
    "addr:street":"S Woodland Blvd",
    "iso:country":"US",
    "sg:address":"1780 S Woodland Blvd",
    "sg:city":"Deland",
    "sg:classifiers":[
        {
            "category":"Recreation",
            "subcategory":"Arcade",
            "type":"Entertainment"
        }
    ],
    "sg:phone":"+1 386 734 0028",
    "sg:postcode":"32720",
    "sg:province":"FL",
    "sg:tags":[
        "device",
        "park",
        "amusement"
    ],
    "sg:website":"www.pooltablesflorida.com",
    "wof:name":"Pool Tables Plus",
    "wof:placetype":"venue"
},
  "geometry": {"coordinates":[-81.302803,28.9977],"type":"Point"}
}