{
  "type": "Feature",
  "properties": {
    "addr:full":"2223 Huntington Ave Sarasota FL 34232",
    "addr:housenumber":"2223",
    "addr:postcode":"34232",
    "addr:street":"Huntington Ave",
    "iso:country":"US",
    "sg:address":"2223 Huntington Ave",
    "sg:city":"Sarasota",
    "sg:classifiers":[
        {
            "category":"Building & Trades",
            "subcategory":"Construction",
            "type":"Services"
        }
    ],
    "sg:phone":"+1 941 927 2154",
    "sg:postcode":"34232",
    "sg:province":"FL",
    "sg:tags":[
        "house"
    ],
    "wof:name":"McD Home Repair & Improvement",
    "wof:placetype":"venue"
},
  "geometry": {"coordinates":[-82.49283,27.314988],"type":"Point"}
}