{
  "type": "Feature",
  "properties": {
    "addr:full":"4551 Whispering Inlet Dr Jacksonville FL 32277",
    "addr:housenumber":"4551",
    "addr:postcode":"32277",
    "addr:street":"Whispering Inlet Dr",
    "iso:country":"US",
    "sg:address":"4551 Whispering Inlet Dr",
    "sg:city":"Jacksonville",
    "sg:classifiers":[
        {
            "category":"Professional",
            "subcategory":"Computer Services",
            "type":"Services"
        }
    ],
    "sg:phone":"+1 904 744 7604",
    "sg:postcode":"32277",
    "sg:province":"FL",
    "sg:tags":[
        "programming"
    ],
    "wof:name":"Program Factory",
    "wof:placetype":"venue"
},
  "geometry": {"coordinates":[-81.606174,30.386623],"type":"Point"}
}