{
  "type": "Feature",
  "properties": {
    "addr:full":"13899 Biscayne Blvd Miami FL 33184",
    "addr:housenumber":"13899",
    "addr:postcode":"33184",
    "addr:street":"Biscayne Blvd",
    "iso:country":"US",
    "sg:address":"13899 Biscayne Blvd",
    "sg:city":"Miami",
    "sg:classifiers":[
        {
            "category":"Real Estate",
            "subcategory":"Real Estate Agent",
            "type":"Services"
        }
    ],
    "sg:phone":"+1 305 702 6321",
    "sg:postcode":"33184",
    "sg:province":"FL",
    "wof:name":"Sejour Otine Realty",
    "wof:placetype":"venue"
},
  "geometry": {"coordinates":[-80.15995100000001,25.901937],"type":"Point"}
}