{
  "type": "Feature",
  "properties": {
    "iso:country":"US",
    "sg:address":"343 Hammondville Rd",
    "sg:city":"Pompano Beach",
    "sg:classifiers":[
        {
            "category":"Personal",
            "subcategory":"Beauty Salon",
            "type":"Services"
        }
    ],
    "sg:phone":"+1 954 946 9653",
    "sg:postcode":"33069",
    "sg:province":"FL",
    "sg:tags":[
        "shop"
    ],
    "wof:name":"Josettes Beauty Salon",
    "wof:placetype":"venue"
},
  "geometry": {"coordinates":[-80.129245,26.234272],"type":"Point"}
}