{
  "type": "Feature",
  "properties": {
    "iso:country":"US",
    "sg:address":"1000 Virginia Ave",
    "sg:city":"Fort Pierce",
    "sg:classifiers":[
        {
            "category":"Professional",
            "subcategory":"Testing Lab",
            "type":"Services"
        }
    ],
    "sg:phone":"+1 772 466 5050",
    "sg:postcode":"34982",
    "sg:province":"FL",
    "sg:tags":[
        "specializing",
        "laboratory",
        "medical",
        "magnetic",
        "resonance"
    ],
    "wof:name":"Mri",
    "wof:placetype":"venue"
},
  "geometry": {"coordinates":[-80.33425,27.42543],"type":"Point"}
}