{
  "type": "Feature",
  "properties": {
    "iso:country":"US",
    "sg:address":"11821 SW 103rd Ln",
    "sg:city":"Miami",
    "sg:classifiers":[
        {
            "category":"Shopping",
            "subcategory":"Pharmacy",
            "type":"Retail Goods"
        }
    ],
    "sg:phone":"+1 786 263 0051",
    "sg:postcode":"33186",
    "sg:province":"FL",
    "wof:name":"Rx Doc Inc",
    "wof:placetype":"venue"
},
  "geometry": {"coordinates":[-80.38540399999999,25.672743],"type":"Point"}
}