{
  "type": "Feature",
  "properties": {
    "iso:country":"US",
    "sg:address":"11376 Kingsley Manor Way",
    "sg:city":"Jacksonville",
    "sg:classifiers":[
        {
            "category":"Professional",
            "type":"Services"
        }
    ],
    "sg:phone":"+1 904 997 8620",
    "sg:postcode":"32225",
    "sg:province":"FL",
    "sg:tags":[
        "establishment"
    ],
    "wof:name":"Dino's",
    "wof:placetype":"venue"
},
  "geometry": {"coordinates":[-81.512248,30.388324],"type":"Point"}
}