{
  "type": "Feature",
  "properties": {
    "iso:country":"US",
    "sg:address":"3135 Council Ct",
    "sg:city":"Kissimmee",
    "sg:classifiers":[
        {
            "category":"Personal",
            "type":"Services"
        },
        {
            "category":"Professional",
            "subcategory":"Art Services",
            "type":"Services"
        }
    ],
    "sg:phone":"+1 407 396 1223",
    "sg:postcode":"34746",
    "sg:province":"FL",
    "sg:tags":[
        "photography",
        "videography",
        "wedding"
    ],
    "wof:name":"Richard Willis",
    "wof:placetype":"venue"
},
  "geometry": {"coordinates":[-81.49691300000001,28.34148],"type":"Point"}
}