{
  "type": "Feature",
  "properties": {
    "addr:full":"2033 Pine Ridge Rd Naples FL 34109",
    "addr:housenumber":"2033",
    "addr:postcode":"34109",
    "addr:street":"Pine Ridge Rd",
    "iso:country":"US",
    "sg:address":"2033 Pine Ridge Rd",
    "sg:city":"Naples",
    "sg:classifiers":[
        {
            "category":"Shopping",
            "subcategory":"Used Merchandise",
            "type":"Retail Goods"
        },
        {
            "category":"Shopping",
            "subcategory":"Jewelry",
            "type":"Retail Goods"
        }
    ],
    "sg:phone":"+1 239 592 5400",
    "sg:postcode":"34109",
    "sg:province":"FL",
    "sg:tags":[
        "pawnbroker"
    ],
    "wof:name":"Pine Ridge Pawn & Jewelry Inc",
    "wof:placetype":"venue"
},
  "geometry": {"coordinates":[-81.775223,26.211636],"type":"Point"}
}