{
  "type": "Feature",
  "properties": {
    "addr:full":"4666 N Powerline Rd Pompano Beach FL 33073",
    "addr:housenumber":"4666",
    "addr:postcode":"33073",
    "addr:street":"N Powerline Rd",
    "iso:country":"US",
    "sg:address":"4666 N Powerline Rd",
    "sg:city":"Pompano Beach",
    "sg:classifiers":[
        {
            "category":"Manufacturing",
            "subcategory":"Tools & Machinery",
            "type":"Manufacturing & Wholesale Goods"
        }
    ],
    "sg:phone":"+1 954 971 5110",
    "sg:postcode":"33073",
    "sg:province":"FL",
    "sg:tags":[
        "industrial",
        "mfg"
    ],
    "wof:name":"Henderson Machine Inc",
    "wof:placetype":"venue"
},
  "geometry": {"coordinates":[-80.152248,26.287125],"type":"Point"}
}