{
  "type": "Feature",
  "properties": {
    "iso:country":"US",
    "sg:address":"13480 SW 5th Ct",
    "sg:city":"Fort Lauderdale",
    "sg:classifiers":[
        {
            "category":"Building & Trades",
            "subcategory":"Construction",
            "type":"Services"
        }
    ],
    "sg:phone":"+1 954 474 5994",
    "sg:postcode":"33325",
    "sg:province":"FL",
    "sg:tags":[
        "contractor"
    ],
    "wof:name":"Gene Fox Masonry",
    "wof:placetype":"venue"
},
  "geometry": {"coordinates":[-80.329244,26.113508],"type":"Point"}
}