{
  "type": "Feature",
  "properties": {
    "iso:country":"US",
    "sg:address":"5420 NW 168th Ter",
    "sg:city":"Opa Locka",
    "sg:classifiers":[
        {
            "category":"Manufacturing",
            "subcategory":"Glass & Minerals",
            "type":"Manufacturing & Wholesale Goods"
        }
    ],
    "sg:phone":"+1 305 626 5958",
    "sg:postcode":"33055",
    "sg:province":"FL",
    "sg:tags":[
        "concrete",
        "product",
        "mfg"
    ],
    "wof:name":"C&A Marble & Pre Cast Inc",
    "wof:placetype":"venue"
},
  "geometry": {"coordinates":[-80.28962,25.926154],"type":"Point"}
}