{
  "type": "Feature",
  "properties": {
    "iso:country":"US",
    "sg:address":"125 Timberline Trl",
    "sg:city":"Ormond Beach",
    "sg:classifiers":[
        {
            "category":"Professional",
            "subcategory":"Computer Services",
            "type":"Services"
        }
    ],
    "sg:phone":"+1 386 615 1860",
    "sg:postcode":"32174",
    "sg:province":"FL",
    "sg:tags":[
        "related"
    ],
    "wof:name":"Atlatl Tech",
    "wof:placetype":"venue"
},
  "geometry": {"coordinates":[-81.08747,29.282473],"type":"Point"}
}