{
  "type": "Feature",
  "properties": {
    "iso:country":"US",
    "sg:address":"6700 Kalamba St",
    "sg:city":"Orlando",
    "sg:classifiers":[
        {
            "category":"Professional",
            "subcategory":"Advertising",
            "type":"Services"
        }
    ],
    "sg:phone":"+1 407 208 0172",
    "sg:postcode":"32807",
    "sg:province":"FL",
    "sg:tags":[
        "representative"
    ],
    "wof:name":"Neighbor Publishing",
    "wof:placetype":"venue"
},
  "geometry": {"coordinates":[-81.29429399999999,28.551019],"type":"Point"}
}