{
  "type": "Feature",
  "properties": {
    "addr:full":"1312 Market Cir Port Charlotte FL 33953",
    "addr:housenumber":"1312",
    "addr:postcode":"33953",
    "addr:street":"Market Cir",
    "iso:country":"US",
    "sg:address":"1312 Market Cir",
    "sg:city":"Port Charlotte",
    "sg:classifiers":[
        {
            "category":"Manufacturing",
            "subcategory":"Printing",
            "type":"Manufacturing & Wholesale Goods"
        }
    ],
    "sg:phone":"+1 941 629 2228",
    "sg:postcode":"33953",
    "sg:province":"FL",
    "sg:tags":[
        "printer",
        "offset"
    ],
    "wof:name":"Quality Printing",
    "wof:placetype":"venue"
},
  "geometry": {"coordinates":[-82.152664,27.013726],"type":"Point"}
}