{
  "type": "Feature",
  "properties": {
    "iso:country":"US",
    "sg:address":"123 Date Palm Dr",
    "sg:city":"West Palm Beach",
    "sg:classifiers":[
        {
            "category":"Building & Trades",
            "subcategory":"Construction",
            "type":"Services"
        }
    ],
    "sg:phone":"+1 561 841 1666",
    "sg:postcode":"33403",
    "sg:province":"FL",
    "sg:tags":[
        "residential"
    ],
    "wof:name":"Integrity Building Contractors",
    "wof:placetype":"venue"
},
  "geometry": {"coordinates":[-80.055922,26.795404],"type":"Point"}
}