{
  "type": "Feature",
  "properties": {
    "iso:country":"US",
    "sg:address":"368 Laurie St",
    "sg:city":"Melbourne",
    "sg:classifiers":[
        {
            "category":"Retail",
            "subcategory":"Auto Repair",
            "type":"Services"
        }
    ],
    "sg:phone":"+1 321 254 5336",
    "sg:postcode":"32935",
    "sg:province":"FL",
    "sg:tags":[
        "body",
        "automobile",
        "top",
        "upholstery",
        "customizing"
    ],
    "sg:website":"http://www.realpagessites.com/treadwellauto",
    "wof:name":"Treadwell Auto Trim",
    "wof:placetype":"venue"
},
  "geometry": {"coordinates":[-80.623985,28.11446],"type":"Point"}
}