{
  "type": "Feature",
  "properties": {
    "addr:full":"10057 Eastern Lake Ave Orlando FL 32817",
    "addr:housenumber":"10057",
    "addr:postcode":"32817",
    "addr:street":"Eastern Lake Ave",
    "iso:country":"US",
    "sg:address":"10057 Eastern Lake Ave",
    "sg:city":"Orlando",
    "sg:classifiers":[
        {
            "category":"Building & Trades",
            "subcategory":"Construction",
            "type":"Services"
        }
    ],
    "sg:phone":"+1 407 673 0080",
    "sg:postcode":"32817",
    "sg:province":"FL",
    "sg:tags":[
        "contractor"
    ],
    "wof:name":"Davids Tile Cleaning",
    "wof:placetype":"venue"
},
  "geometry": {"coordinates":[-81.24420000000001,28.592267],"type":"Point"}
}