{
  "type": "Feature",
  "properties": {
    "addr:full":"1909 Blanding Blvd Jacksonville FL 32210",
    "addr:housenumber":"1909",
    "addr:postcode":"32210",
    "addr:street":"Blanding Blvd",
    "iso:country":"US",
    "sg:address":"1909 Blanding Blvd",
    "sg:city":"Jacksonville",
    "sg:classifiers":[
        {
            "category":"Personal",
            "subcategory":"Beauty Salon",
            "type":"Services"
        }
    ],
    "sg:phone":"+1 904 389 4792",
    "sg:postcode":"32210",
    "sg:province":"FL",
    "sg:tags":[
        "shop"
    ],
    "wof:name":"Polly's Beauty Box",
    "wof:placetype":"venue"
},
  "geometry": {"coordinates":[-81.72546699999999,30.283368],"type":"Point"}
}