{
  "type": "Feature",
  "properties": {
    "addr:full":"166 E Bayou Forest Dr Freeport FL 32439",
    "addr:housenumber":"166",
    "addr:postcode":"32439",
    "addr:street":"E Bayou Forest Dr",
    "iso:country":"US",
    "sg:address":"166 E Bayou Forest Dr",
    "sg:city":"Freeport",
    "sg:classifiers":[
        {
            "category":"Building & Trades",
            "subcategory":"Landscaping Services",
            "type":"Services"
        }
    ],
    "sg:phone":"+1 850 835 4764",
    "sg:postcode":"32439",
    "sg:province":"FL",
    "wof:name":"From Ground Up",
    "wof:placetype":"venue"
},
  "geometry": {"coordinates":[-86.139166,30.458304],"type":"Point"}
}