{
  "type": "Feature",
  "properties": {
    "iso:country":"US",
    "sg:address":"2101 Town St",
    "sg:city":"Pensacola",
    "sg:classifiers":[
        {
            "category":"Wholesale",
            "subcategory":"Hardware",
            "type":"Manufacturing & Wholesale Goods"
        }
    ],
    "sg:phone":"+1 850 432 2214",
    "sg:postcode":"32505",
    "sg:province":"FL",
    "sg:tags":[
        "refrigerating"
    ],
    "wof:name":"Bennink's Refrigeration Svc",
    "wof:placetype":"venue"
},
  "geometry": {"coordinates":[-87.24221799999999,30.447259],"type":"Point"}
}