{
  "type": "Feature",
  "properties": {
    "iso:country":"US",
    "sg:address":"6102 Syrcle Ave",
    "sg:city":"Milton",
    "sg:classifiers":[
        {
            "category":"Building & Trades",
            "subcategory":"Construction",
            "type":"Services"
        }
    ],
    "sg:phone":"+1 850 981 0191",
    "sg:postcode":"32570",
    "sg:province":"FL",
    "sg:tags":[
        "house"
    ],
    "wof:name":"C W Construction",
    "wof:placetype":"venue"
},
  "geometry": {"coordinates":[-87.050652,30.657373],"type":"Point"}
}