{
  "type": "Feature",
  "properties": {
    "addr:full":"3936 SW 12th Ct Fort Lauderdale FL 33312",
    "addr:housenumber":"3936",
    "addr:postcode":"33312",
    "addr:street":"Sw 12Th Ct",
    "iso:country":"US",
    "sg:address":"3936 SW 12th Ct",
    "sg:city":"Fort Lauderdale",
    "sg:classifiers":[
        {
            "category":"Professional",
            "subcategory":"Business Services",
            "type":"Services"
        }
    ],
    "sg:phone":"+1 954 587 8692",
    "sg:postcode":"33312",
    "sg:province":"FL",
    "sg:tags":[
        "specialty",
        "mfg"
    ],
    "wof:name":"A Better Sign & Supply Co",
    "wof:placetype":"venue"
},
  "geometry": {"coordinates":[-80.200875,26.105879],"type":"Point"}
}