{
  "type": "Feature",
  "properties": {
    "addr:full":"4133 NW 11th St Gainesville FL 32609",
    "addr:housenumber":"4133",
    "addr:postcode":"32609",
    "addr:street":"Nw 11Th St",
    "iso:country":"US",
    "sg:address":"4133 NW 11th St",
    "sg:city":"Gainesville",
    "sg:classifiers":[
        {
            "category":"Building & Trades",
            "subcategory":"Construction",
            "type":"Services"
        }
    ],
    "sg:phone":"+1 352 672 7489",
    "sg:postcode":"32609",
    "sg:province":"FL",
    "sg:tags":[
        "painting",
        "contractor"
    ],
    "wof:name":"The Green Painter",
    "wof:placetype":"venue"
},
  "geometry": {"coordinates":[-82.336039,29.691008],"type":"Point"}
}