{
  "type": "Feature",
  "properties": {
    "iso:country":"US",
    "sg:address":"3346 Saint Lucia Ct",
    "sg:city":"Tavares",
    "sg:classifiers":[
        {
            "category":"Building & Trades",
            "subcategory":"Locksmith",
            "type":"Services"
        }
    ],
    "sg:phone":"+1 352 343 5625",
    "sg:postcode":"32778",
    "sg:province":"FL",
    "sg:tags":[
        "locksmiths-commercial",
        "industrial",
        "key",
        "lock"
    ],
    "wof:name":"Tlc Safe & Lock",
    "wof:placetype":"venue"
},
  "geometry": {"coordinates":[-81.763462,28.751514],"type":"Point"}
}