{
  "type": "Feature",
  "properties": {
    "addr:full":"6956 Santa Clara Dr Gulf Breeze FL 32566",
    "addr:housenumber":"6956",
    "addr:postcode":"32566",
    "addr:street":"Santa Clara Dr",
    "iso:country":"US",
    "sg:address":"6956 Santa Clara Dr",
    "sg:city":"Gulf Breeze",
    "sg:classifiers":[
        {
            "category":"Real Estate",
            "subcategory":"Developer",
            "type":"Services"
        }
    ],
    "sg:phone":"+1 850 939 4282",
    "sg:postcode":"32566",
    "sg:province":"FL",
    "wof:name":"East Bay Properties Inc",
    "wof:placetype":"venue"
},
  "geometry": {"coordinates":[-86.932034,30.460611],"type":"Point"}
}