{
  "type": "Feature",
  "properties": {
    "iso:country":"US",
    "sg:address":"1200 Ocean Dr",
    "sg:city":"Miami Beach",
    "sg:classifiers":[
        {
            "category":"Ice Cream",
            "type":"Food & Drink"
        }
    ],
    "sg:phone":"+1 305 531 3301",
    "sg:postcode":"33139",
    "sg:province":"FL",
    "sg:tags":[
        "frozen",
        "yogurt"
    ],
    "wof:name":"Rocky's Italian Ice",
    "wof:placetype":"venue"
},
  "geometry": {"coordinates":[-80.13020299999999,25.7827],"type":"Point"}
}