{
  "type": "Feature",
  "properties": {
    "iso:country":"US",
    "sg:address":"6 W 16th St",
    "sg:city":"Jacksonville",
    "sg:classifiers":[
        {
            "category":"Food & Beverages",
            "subcategory":"Groceries & Convenience Stores",
            "type":"Retail Goods"
        }
    ],
    "sg:phone":"+1 904 356 6963",
    "sg:postcode":"32206",
    "sg:province":"FL",
    "sg:tags":[
        "grocer"
    ],
    "wof:name":"Buy Rite",
    "wof:placetype":"venue"
},
  "geometry": {"coordinates":[-81.654017,30.353499],"type":"Point"}
}