{
  "type": "Feature",
  "properties": {
    "iso:country":"US",
    "sg:address":"258 Omega Ct",
    "sg:city":"Pensacola",
    "sg:classifiers":[
        {
            "category":"Building & Trades",
            "subcategory":"Landscaping Services",
            "type":"Services"
        }
    ],
    "sg:phone":"+1 850 457 1340",
    "sg:postcode":"32506",
    "sg:province":"FL",
    "wof:name":"Jim Podojil Landscaping",
    "wof:placetype":"venue"
},
  "geometry": {"coordinates":[-87.28234999999999,30.414346],"type":"Point"}
}