{
  "type": "Feature",
  "properties": {
    "addr:full":"10301 9th St N St Petersburg FL 33716",
    "addr:housenumber":"10301",
    "addr:postcode":"33716",
    "addr:street":"9Th St N",
    "iso:country":"US",
    "sg:address":"10301 9th St N",
    "sg:city":"St Petersburg",
    "sg:classifiers":[
        {
            "category":"Professional",
            "type":"Services"
        }
    ],
    "sg:phone":"+1 727 563 5100",
    "sg:postcode":"33716",
    "sg:province":"FL",
    "sg:tags":[
        "technical",
        "preparation",
        "manual"
    ],
    "wof:name":"Celotex Corp",
    "wof:placetype":"venue"
},
  "geometry": {"coordinates":[-82.646914,27.866007],"type":"Point"}
}