{
  "type": "Feature",
  "properties": {
    "iso:country":"US",
    "sg:address":"661 Sebastian Blvd Eastbound",
    "sg:city":"Sebastian",
    "sg:classifiers":[
        {
            "category":"Travel",
            "subcategory":"Travel Agent",
            "type":"Entertainment"
        }
    ],
    "sg:phone":"+1 772 388 2552",
    "sg:postcode":"32958",
    "sg:province":"FL",
    "sg:tags":[
        "agency",
        "bureau"
    ],
    "wof:name":"Travel Gallery-Sebastian Inc",
    "wof:placetype":"venue"
},
  "geometry": {"coordinates":[-80.48313899999999,27.79524],"type":"Point"}
}