{
  "type": "Feature",
  "properties": {
    "addr:full":"7312 NW 7th Ave Miami FL 33150",
    "addr:housenumber":"7312",
    "addr:postcode":"33150",
    "addr:street":"Nw 7Th Ave",
    "iso:country":"US",
    "sg:address":"7312 NW 7th Ave",
    "sg:city":"Miami",
    "sg:classifiers":[
        {
            "category":"Retail",
            "subcategory":"Auto Repair",
            "type":"Services"
        }
    ],
    "sg:phone":"+1 305 835 9960",
    "sg:postcode":"33150",
    "sg:province":"FL",
    "sg:tags":[
        "body"
    ],
    "wof:name":"C & J Auto Installation",
    "wof:placetype":"venue"
},
  "geometry": {"coordinates":[-80.209019,25.842207],"type":"Point"}
}