{
  "type": "Feature",
  "properties": {
    "addr:full":"3064 Shamrock Dr Venice FL 34293",
    "addr:housenumber":"3064",
    "addr:postcode":"34293",
    "addr:street":"Shamrock Dr",
    "iso:country":"US",
    "sg:address":"3064 Shamrock Dr",
    "sg:city":"Venice",
    "sg:classifiers":[
        {
            "category":"Education",
            "subcategory":"Special Training",
            "type":"Public Place"
        },
        {
            "category":"Education",
            "subcategory":"Preschool",
            "type":"Public Place"
        }
    ],
    "sg:phone":"+1 941 493 4057",
    "sg:postcode":"34293",
    "sg:province":"FL",
    "sg:tags":[
        "kindergarten",
        "educational"
    ],
    "wof:name":"Shamrock Pre School",
    "wof:placetype":"venue"
},
  "geometry": {"coordinates":[-82.429151,27.060683],"type":"Point"}
}