{
  "type": "Feature",
  "properties": {
    "iso:country":"US",
    "sg:address":"377 China Hill Ct",
    "sg:city":"Apopka",
    "sg:classifiers":[
        {
            "category":"Building & Trades",
            "subcategory":"Plumbing",
            "type":"Services"
        }
    ],
    "sg:phone":"+1 407 884 7088",
    "sg:postcode":"32712",
    "sg:province":"FL",
    "sg:tags":[
        "plumbing",
        "contractor"
    ],
    "wof:name":"Pro Plumbing Inc",
    "wof:placetype":"venue"
},
  "geometry": {"coordinates":[-81.50484400000001,28.698911],"type":"Point"}
}