{
  "type": "Feature",
  "properties": {
    "iso:country":"US",
    "sg:address":"6533 Central Ave",
    "sg:city":"St Petersburg",
    "sg:classifiers":[
        {
            "category":"Shopping",
            "type":"Retail Goods"
        }
    ],
    "sg:phone":"+1 727 343 5230",
    "sg:postcode":"33710",
    "sg:province":"FL",
    "sg:tags":[
        "hearing",
        "equipment",
        "supply",
        "impaired",
        "aid"
    ],
    "wof:name":"Bay Area Hearing Aid Service",
    "wof:placetype":"venue"
},
  "geometry": {"coordinates":[-82.727825,27.7709],"type":"Point"}
}