{
  "type": "Feature",
  "properties": {
    "iso:country":"US",
    "sg:address":"5483 Vineland Rd",
    "sg:city":"Orlando",
    "sg:classifiers":[
        {
            "category":"Building & Trades",
            "subcategory":"Construction",
            "type":"Services"
        }
    ],
    "sg:phone":"+1 407 963 8918",
    "sg:postcode":"32811",
    "sg:province":"FL",
    "sg:tags":[
        "hanging",
        "contractor"
    ],
    "wof:name":"Below Budget Painting & Decora",
    "wof:placetype":"venue"
},
  "geometry": {"coordinates":[-81.446198,28.483123],"type":"Point"}
}