{
  "type": "Feature",
  "properties": {
    "addr:full":"760 S Brevard Ave Cocoa Beach FL 32931",
    "addr:housenumber":"760",
    "addr:postcode":"32931",
    "addr:street":"S Brevard Ave",
    "iso:country":"US",
    "sg:address":"760 S Brevard Ave",
    "sg:city":"Cocoa Beach",
    "sg:classifiers":[
        {
            "category":"Real Estate",
            "subcategory":"Real Estate Operator",
            "type":"Services"
        }
    ],
    "sg:phone":"+1 321 784 1029",
    "sg:postcode":"32931",
    "sg:province":"FL",
    "sg:tags":[
        "condominium"
    ],
    "wof:name":"River Lakes Condominium Assn",
    "wof:placetype":"venue"
},
  "geometry": {"coordinates":[-80.61079700000001,28.307003],"type":"Point"}
}