{
  "type": "Feature",
  "properties": {
    "iso:country":"US",
    "sg:address":"3704 SE 12th Ct",
    "sg:city":"Cape Coral",
    "sg:classifiers":[
        {
            "category":"Organizations",
            "subcategory":"Religious Organization",
            "type":"Services"
        }
    ],
    "sg:phone":"+1 239 549 0523",
    "sg:postcode":"33904",
    "sg:province":"FL",
    "sg:tags":[
        "church"
    ],
    "sg:website":"www.oca.org",
    "wof:name":"Holy Cross Orthodox Church",
    "wof:placetype":"venue"
},
  "geometry": {"coordinates":[-81.94899599999999,26.583324],"type":"Point"}
}