{
  "type": "Feature",
  "properties": {
    "addr:full":"5555 N Federal Hwy Fort Lauderdale FL 33308",
    "addr:housenumber":"5555",
    "addr:postcode":"33308",
    "addr:street":"N Federal Hwy",
    "iso:country":"US",
    "sg:address":"5555 N Federal Hwy",
    "sg:city":"Fort Lauderdale",
    "sg:classifiers":[
        {
            "category":"Arts & Performance",
            "subcategory":"Theater",
            "type":"Entertainment"
        }
    ],
    "sg:phone":"+1 954 491 1103",
    "sg:postcode":"33308",
    "sg:province":"FL",
    "sg:tags":[
        "opera",
        "company"
    ],
    "wof:name":"Coral Ridge Concert Series",
    "wof:placetype":"venue"
},
  "geometry": {"coordinates":[-80.111985,26.195909],"type":"Point"}
}