{
  "type": "Feature",
  "properties": {
    "addr:full":"9756 Atlantic Blvd Jacksonville FL 32225",
    "addr:housenumber":"9756",
    "addr:postcode":"32225",
    "addr:street":"Atlantic Blvd",
    "iso:country":"US",
    "sg:address":"9756 Atlantic Blvd",
    "sg:city":"Jacksonville",
    "sg:classifiers":[
        {
            "category":"Wholesale",
            "subcategory":"Office Equipment",
            "type":"Manufacturing & Wholesale Goods"
        },
        {
            "category":"Shopping",
            "subcategory":"Stationery & Office Supplies",
            "type":"Retail Goods"
        },
        {
            "category":"Professional",
            "subcategory":"Printing & Photocopies",
            "type":"Services"
        },
        {
            "category":"Shopping",
            "subcategory":"Computers & Home Electronics",
            "type":"Retail Goods"
        }
    ],
    "sg:phone":"+1 904 721 3331",
    "sg:postcode":"32225",
    "sg:province":"FL",
    "sg:tags":[
        "scanning",
        "printer",
        "register",
        "autographic",
        "duplicating",
        "copying",
        "plotting",
        "furniture"
    ],
    "sg:website":"http://www.officemax.com/",
    "wof:name":"OfficeMax",
    "wof:placetype":"venue"
},
  "geometry": {"coordinates":[-81.546333,30.322026],"type":"Point"}
}