{
  "type": "Feature",
  "properties": {
    "addr:full":"2020 W 26th St Jacksonville FL 32209",
    "addr:housenumber":"2020",
    "addr:postcode":"32209",
    "addr:street":"W 26Th St",
    "iso:country":"US",
    "sg:address":"2020 W 26th St",
    "sg:city":"Jacksonville",
    "sg:classifiers":[
        {
            "category":"Professional",
            "subcategory":"Employment Agencies",
            "type":"Services"
        }
    ],
    "sg:phone":"+1 904 765 8111",
    "sg:postcode":"32209",
    "sg:province":"FL",
    "sg:tags":[
        "help",
        "temp"
    ],
    "wof:name":"Spherion Corporation",
    "wof:placetype":"venue"
},
  "geometry": {"coordinates":[-81.694776,30.359629],"type":"Point"}
}