{
  "type": "Feature",
  "properties": {
    "addr:full":"3110 Cherry Palm Dr Tampa FL 33619",
    "addr:housenumber":"3110",
    "addr:postcode":"33619",
    "addr:street":"Cherry Palm Dr",
    "iso:country":"US",
    "sg:address":"3110 Cherry Palm Dr",
    "sg:city":"Tampa",
    "sg:classifiers":[
        {
            "category":"Building & Trades",
            "subcategory":"Equipment Rental",
            "type":"Services"
        }
    ],
    "sg:phone":"+1 813 626 9339",
    "sg:postcode":"33619",
    "sg:province":"FL",
    "sg:tags":[
        "hospital",
        "supply"
    ],
    "wof:name":"Mediq PRN",
    "wof:placetype":"venue"
},
  "geometry": {"coordinates":[-82.34453600000001,27.974653],"type":"Point"}
}