{
  "type": "Feature",
  "properties": {
    "addr:full":"5855 Placida Rd Englewood FL 34224",
    "addr:housenumber":"5855",
    "addr:postcode":"34224",
    "addr:street":"Placida Rd",
    "iso:country":"US",
    "sg:address":"5855 Placida Rd",
    "sg:city":"Englewood",
    "sg:classifiers":[
        {
            "category":"Shopping",
            "subcategory":"Optical Goods",
            "type":"Retail Goods"
        }
    ],
    "sg:phone":"+1 941 697 4488",
    "sg:postcode":"34224",
    "sg:province":"FL",
    "sg:tags":[
        "optician"
    ],
    "wof:name":"Eyewear Designs",
    "wof:placetype":"venue"
},
  "geometry": {"coordinates":[-82.309074,26.895081],"type":"Point"}
}