{
  "type": "Feature",
  "properties": {
    "addr:full":"14747 N Nebraska Ave Tampa FL 33613",
    "addr:housenumber":"14747",
    "addr:postcode":"33613",
    "addr:street":"N Nebraska Ave",
    "iso:country":"US",
    "sg:address":"14747 N Nebraska Ave",
    "sg:city":"Tampa",
    "sg:classifiers":[
        {
            "category":"Autos & Motor Vehicles",
            "subcategory":"Automobile Sales",
            "type":"Retail Goods"
        }
    ],
    "sg:phone":"+1 813 514 1615",
    "sg:postcode":"33613",
    "sg:province":"FL",
    "sg:tags":[
        "car",
        "used"
    ],
    "wof:name":"Auto Center Sales",
    "wof:placetype":"venue"
},
  "geometry": {"coordinates":[-82.451286,28.082601],"type":"Point"}
}