{
  "type": "Feature",
  "properties": {
    "iso:country":"US",
    "sg:address":"3606 S Peninsula Dr",
    "sg:city":"Daytona Beach",
    "sg:classifiers":[
        {
            "category":"Real Estate",
            "subcategory":"Real Estate Operator",
            "type":"Services"
        },
        {
            "category":"Organizations",
            "subcategory":"Community Association",
            "type":"Services"
        }
    ],
    "sg:phone":"+1 386 767 3882",
    "sg:postcode":"32127",
    "sg:province":"FL",
    "sg:tags":[
        "condominium"
    ],
    "wof:name":"Admiralty Club Condominiums",
    "wof:placetype":"venue"
},
  "geometry": {"coordinates":[-80.969837,29.146882],"type":"Point"}
}