{
  "type": "Feature",
  "properties": {
    "iso:country":"US",
    "sg:address":"1230 Seminola Blvd",
    "sg:city":"Casselberry",
    "sg:classifiers":[
        {
            "category":"Health Services",
            "subcategory":"Chiropractor",
            "type":"Services"
        }
    ],
    "sg:phone":"+1 407 695 0400",
    "sg:postcode":"32707",
    "sg:province":"FL",
    "wof:name":"Bartlett Leslie Ann DC",
    "wof:placetype":"venue"
},
  "geometry": {"coordinates":[-81.314003,28.6744],"type":"Point"}
}