{
  "type": "Feature",
  "properties": {
    "addr:full":"5320 53rd Ave E Bradenton FL 34203",
    "addr:housenumber":"5320",
    "addr:postcode":"34203",
    "addr:street":"53Rd Ave E",
    "iso:country":"US",
    "sg:address":"5320 53rd Ave E",
    "sg:city":"Bradenton",
    "sg:classifiers":[
        {
            "category":"Professional",
            "subcategory":"Management & Consulting",
            "type":"Services"
        }
    ],
    "sg:phone":"+1 941 755 2038",
    "sg:postcode":"34203",
    "sg:province":"FL",
    "sg:tags":[
        "consultant",
        "business"
    ],
    "wof:name":"Gulf Coast Automotive Cnslnts",
    "wof:placetype":"venue"
},
  "geometry": {"coordinates":[-82.49457200000001,27.44621],"type":"Point"}
}