{
  "type": "Feature",
  "properties": {
    "addr:full":"1300 Alden Rd Orlando FL 32803",
    "addr:housenumber":"1300",
    "addr:postcode":"32803",
    "addr:street":"Alden Rd",
    "iso:country":"US",
    "sg:address":"1300 Alden Rd",
    "sg:city":"Orlando",
    "sg:classifiers":[
        {
            "category":"Manufacturing",
            "subcategory":"Chemicals & Compounds",
            "type":"Manufacturing & Wholesale Goods"
        }
    ],
    "sg:phone":"+1 407 898 4341",
    "sg:postcode":"32803",
    "sg:province":"FL",
    "wof:name":"Hunter Chemical",
    "wof:placetype":"venue"
},
  "geometry": {"coordinates":[-81.371804,28.56405],"type":"Point"}
}