{
  "type": "Feature",
  "properties": {
    "addr:full":"184 N Center St Pierson FL 32180",
    "addr:housenumber":"184",
    "addr:postcode":"32180",
    "addr:street":"N Center St",
    "iso:country":"US",
    "sg:address":"184 N Center St",
    "sg:city":"Pierson",
    "sg:classifiers":[
        {
            "category":"Food & Beverages",
            "subcategory":"Groceries & Convenience Stores",
            "type":"Retail Goods"
        }
    ],
    "sg:phone":"+1 386 749 2222",
    "sg:postcode":"32180",
    "sg:province":"FL",
    "wof:name":"Pierson Discount & Groceries",
    "wof:placetype":"venue"
},
  "geometry": {"coordinates":[-81.463005,29.240127],"type":"Point"}
}