{
  "type": "Feature",
  "properties": {
    "iso:country":"US",
    "sg:address":"31 S 4th St",
    "sg:city":"Fernandina Beach",
    "sg:classifiers":[
        {
            "category":"Professional",
            "type":"Services"
        }
    ],
    "sg:phone":"+1 904 491 1133",
    "sg:postcode":"32034",
    "sg:province":"FL",
    "sg:tags":[
        "establishment"
    ],
    "wof:name":"Red Sector",
    "wof:placetype":"venue"
},
  "geometry": {"coordinates":[-81.462227,30.670724],"type":"Point"}
}