{
  "type": "Feature",
  "properties": {
    "iso:country":"US",
    "sg:address":"6434 SW 27th St",
    "sg:city":"Miami",
    "sg:classifiers":[
        {
            "category":"Professional",
            "subcategory":"Accounting & Tax Preparation",
            "type":"Services"
        }
    ],
    "sg:phone":"+1 305 662 2442",
    "sg:postcode":"33155",
    "sg:province":"FL",
    "sg:tags":[
        "bookkeeping",
        "billing"
    ],
    "wof:name":"Medi-Tech Management Services",
    "wof:placetype":"venue"
},
  "geometry": {"coordinates":[-80.300121,25.745245],"type":"Point"}
}