{
  "type": "Feature",
  "properties": {
    "addr:full":"501 E 4th St Lynn Haven FL 32444",
    "addr:housenumber":"501",
    "addr:postcode":"32444",
    "addr:street":"E 4Th St",
    "iso:country":"US",
    "sg:address":"501 E 4th St",
    "sg:city":"Lynn Haven",
    "sg:classifiers":[
        {
            "category":"Building & Trades",
            "subcategory":"Construction",
            "type":"Services"
        }
    ],
    "sg:phone":"+1 850 265 5876",
    "sg:postcode":"32444",
    "sg:province":"FL",
    "sg:tags":[
        "house"
    ],
    "wof:name":"Garrett and Sons Inc",
    "wof:placetype":"venue"
},
  "geometry": {"coordinates":[-85.643936,30.251548],"type":"Point"}
}