{
  "type": "Feature",
  "properties": {
    "iso:country":"US",
    "sg:address":"680 W 49th St",
    "sg:city":"Hialeah",
    "sg:classifiers":[
        {
            "category":"Restaurant",
            "type":"Food & Drink"
        }
    ],
    "sg:menulink":"http://www.allmenus.com/fl/hialeah/97202-ihop/menu/",
    "sg:phone":"+1 305 822 7962",
    "sg:postcode":"33012",
    "sg:province":"FL",
    "sg:tags":[
        "sandwich",
        "salad",
        "burger",
        "soup",
        "american",
        "steakhouse",
        "wrap"
    ],
    "wof:name":"IHOP",
    "wof:placetype":"venue"
},
  "geometry": {"coordinates":[-80.29662999999999,25.866579],"type":"Point"}
}