{
  "type": "Feature",
  "properties": {
    "iso:country":"US",
    "sg:address":"928 SE Waterside Way",
    "sg:city":"Stuart",
    "sg:classifiers":[
        {
            "category":"Wholesale",
            "subcategory":"Electrical",
            "type":"Manufacturing & Wholesale Goods"
        }
    ],
    "sg:phone":"+1 772 283 6160",
    "sg:postcode":"34997",
    "sg:province":"FL",
    "sg:tags":[
        "equipment"
    ],
    "wof:name":"Light Source",
    "wof:placetype":"venue"
},
  "geometry": {"coordinates":[-80.238157,27.107224],"type":"Point"}
}