{
  "type": "Feature",
  "properties": {
    "iso:country":"US",
    "sg:address":"1176 State St",
    "sg:city":"Sanford",
    "sg:classifiers":[
        {
            "category":"Food & Beverages",
            "subcategory":"Groceries & Convenience Stores",
            "type":"Retail Goods"
        }
    ],
    "sg:phone":"+1 407 322 4901",
    "sg:postcode":"32773",
    "sg:province":"FL",
    "sg:tags":[
        "grocer"
    ],
    "wof:name":"Save-A-Lot",
    "wof:placetype":"venue"
},
  "geometry": {"coordinates":[-81.277985,28.77106],"type":"Point"}
}