{
  "type": "Feature",
  "properties": {
    "iso:country":"US",
    "sg:address":"9420 Park Dr",
    "sg:city":"Miami",
    "sg:classifiers":[
        {
            "category":"Health Services",
            "subcategory":"Doctor",
            "type":"Services"
        }
    ],
    "sg:phone":"+1 305 757 6991",
    "sg:postcode":"33138",
    "sg:province":"FL",
    "wof:name":"Eng Gene Watkins DDS",
    "wof:placetype":"venue"
},
  "geometry": {"coordinates":[-80.184518,25.862545],"type":"Point"}
}