{
  "type": "Feature",
  "properties": {
    "addr:full":"18518 W Dixie Hwy Miami FL 33180",
    "addr:housenumber":"18518",
    "addr:postcode":"33180",
    "addr:street":"W Dixie Hwy",
    "iso:country":"US",
    "sg:address":"18518 W Dixie Hwy",
    "sg:city":"Miami",
    "sg:classifiers":[
        {
            "category":"Retail",
            "subcategory":"Event Space",
            "type":"Services"
        },
        {
            "category":"Arena",
            "subcategory":"Sports Club",
            "type":"Entertainment"
        }
    ],
    "sg:phone":"+1 305 466 1900",
    "sg:postcode":"33180",
    "sg:province":"FL",
    "sg:tags":[
        "ticket",
        "sale"
    ],
    "wof:name":"Poker Tickets",
    "wof:placetype":"venue"
},
  "geometry": {"coordinates":[-80.14863800000001,25.946774],"type":"Point"}
}