{
  "type": "Feature",
  "properties": {
    "iso:country":"US",
    "sg:address":"1007 S Sanford Ave",
    "sg:city":"Sanford",
    "sg:classifiers":[
        {
            "category":"Building & Trades",
            "subcategory":"Plumbing",
            "type":"Services"
        }
    ],
    "sg:phone":"+1 407 321 3999",
    "sg:postcode":"32771",
    "sg:province":"FL",
    "sg:tags":[
        "specializing",
        "heating",
        "contractor",
        "warm",
        "plumbing",
        "air"
    ],
    "wof:name":"Lees Air Conditioning & Plbg",
    "wof:placetype":"venue"
},
  "geometry": {"coordinates":[-81.264819,28.802696],"type":"Point"}
}