{
  "type": "Feature",
  "properties": {
    "addr:full":"112 W 3rd Ave Mount Dora FL 32757",
    "addr:housenumber":"112",
    "addr:postcode":"32757",
    "addr:street":"W 3Rd Ave",
    "iso:country":"US",
    "sg:address":"112 W 3rd Ave",
    "sg:city":"Mount Dora",
    "sg:classifiers":[
        {
            "category":"Restaurant",
            "type":"Food & Drink"
        }
    ],
    "sg:menulink":"http://www.allmenus.com/fl/mount-dora/39153-the-chew-chew-express-sandwich-express/menu/",
    "sg:phone":"+1 352 735 7760",
    "sg:postcode":"32757",
    "sg:province":"FL",
    "sg:tags":[
        "wrap",
        "american",
        "sandwich"
    ],
    "wof:name":"The Chew Chew Express Sandwich Express",
    "wof:placetype":"venue"
},
  "geometry": {"coordinates":[-81.644792,28.798614],"type":"Point"}
}