{
  "type": "Feature",
  "properties": {
    "iso:country":"US",
    "sg:address":"7558 Southland Blvd",
    "sg:city":"Orlando",
    "sg:classifiers":[
        {
            "category":"Shopping",
            "subcategory":"Beauty & Cosmetics",
            "type":"Retail Goods"
        }
    ],
    "sg:phone":"+1 407 888 9020",
    "sg:postcode":"32809",
    "sg:province":"FL",
    "sg:tags":[
        "product",
        "skin",
        "care"
    ],
    "wof:name":"Kara Vita LLC",
    "wof:placetype":"venue"
},
  "geometry": {"coordinates":[-81.40662,28.454418],"type":"Point"}
}