{
  "type": "Feature",
  "properties": {
    "addr:full":"726 Green St Wauchula FL 33873",
    "addr:housenumber":"726",
    "addr:postcode":"33873",
    "addr:street":"Green St",
    "iso:country":"US",
    "sg:address":"726 Green St",
    "sg:city":"Wauchula",
    "sg:classifiers":[
        {
            "category":"Building & Trades",
            "subcategory":"Construction",
            "type":"Services"
        }
    ],
    "sg:phone":"+1 863 773 0454",
    "sg:postcode":"33873",
    "sg:province":"FL",
    "sg:tags":[
        "marking",
        "maintenance",
        "parking"
    ],
    "wof:name":"Public Works Admin",
    "wof:placetype":"venue"
},
  "geometry": {"coordinates":[-81.803265,27.547017],"type":"Point"}
}