{
  "type": "Feature",
  "properties": {
    "addr:full":"2241 2nd Ave S St Petersburg FL 33712",
    "addr:housenumber":"2241",
    "addr:postcode":"33712",
    "addr:street":"2Nd Ave S",
    "iso:country":"US",
    "sg:address":"2241 2nd Ave S",
    "sg:city":"St Petersburg",
    "sg:classifiers":[
        {
            "category":"Building & Trades",
            "subcategory":"Landscaping Services",
            "type":"Services"
        }
    ],
    "sg:phone":"+1 727 328 9686",
    "sg:postcode":"33712",
    "sg:province":"FL",
    "sg:tags":[
        "landscape",
        "contractor"
    ],
    "wof:name":"Professional Grounds Mgmt",
    "wof:placetype":"venue"
},
  "geometry": {"coordinates":[-82.663937,27.769338],"type":"Point"}
}