{
  "type": "Feature",
  "properties": {
    "iso:country":"US",
    "sg:address":"130 Bomar Ct",
    "sg:city":"Longwood",
    "sg:classifiers":[
        {
            "category":"Shopping",
            "type":"Retail Goods"
        },
        {
            "category":"Shopping",
            "subcategory":"Computers & Home Electronics",
            "type":"Retail Goods"
        }
    ],
    "sg:phone":"+1 407 834 2033",
    "sg:postcode":"32750",
    "sg:province":"FL",
    "sg:tags":[
        "equipment",
        "electronic",
        "merchandise",
        "supply"
    ],
    "wof:name":"Effective Electronics",
    "wof:placetype":"venue"
},
  "geometry": {"coordinates":[-81.32847599999999,28.706333],"type":"Point"}
}