{
  "type": "Feature",
  "properties": {
    "iso:country":"US",
    "sg:address":"4560 NW 4th Ct",
    "sg:city":"Fort Lauderdale",
    "sg:classifiers":[
        {
            "category":"Building & Trades",
            "subcategory":"Landscaping Services",
            "type":"Services"
        }
    ],
    "sg:phone":"+1 954 584 4564",
    "sg:postcode":"33317",
    "sg:province":"FL",
    "sg:tags":[
        "landscape"
    ],
    "wof:name":"Y Kai",
    "wof:placetype":"venue"
},
  "geometry": {"coordinates":[-80.207109,26.126941],"type":"Point"}
}