{
  "type": "Feature",
  "properties": {
    "iso:country":"US",
    "sg:address":"101 N Garden Ave",
    "sg:city":"Clearwater",
    "sg:classifiers":[
        {
            "category":"Professional",
            "subcategory":"Advertising",
            "type":"Services"
        }
    ],
    "sg:phone":"+1 727 446 2854",
    "sg:postcode":"33755",
    "sg:province":"FL",
    "sg:tags":[
        "counselor"
    ],
    "sg:website":"www.hypecom.com",
    "wof:name":"Hype",
    "wof:placetype":"venue"
},
  "geometry": {"coordinates":[-82.79870099999999,27.968152],"type":"Point"}
}