{
  "type": "Feature",
  "properties": {
    "iso:country":"US",
    "sg:address":"15021 N Florida Ave",
    "sg:city":"Tampa",
    "sg:classifiers":[
        {
            "category":"Restaurant",
            "type":"Food & Drink"
        }
    ],
    "sg:phone":"+1 813 962 1560",
    "sg:postcode":"33613",
    "sg:province":"FL",
    "sg:tags":[
        "eating"
    ],
    "wof:name":"Tomo Japanese Sushi Bar",
    "wof:placetype":"venue"
},
  "geometry": {"coordinates":[-82.459688,28.090063],"type":"Point"}
}