{
  "type": "Feature",
  "properties": {
    "addr:full":"4802 S 32nd Dr Lake Worth FL 33461",
    "addr:housenumber":"4802",
    "addr:postcode":"33461",
    "addr:street":"S 32Nd Dr",
    "iso:country":"US",
    "sg:address":"4802 S 32nd Dr",
    "sg:city":"Lake Worth",
    "sg:classifiers":[
        {
            "category":"Building & Trades",
            "subcategory":"Cleaning & Sanitation",
            "type":"Services"
        }
    ],
    "sg:phone":"+1 561 502 2052",
    "sg:postcode":"33461",
    "sg:province":"FL",
    "sg:tags":[
        "janitor"
    ],
    "wof:name":"Vonny Creative Cleaning",
    "wof:placetype":"venue"
},
  "geometry": {"coordinates":[-80.093602,26.604244],"type":"Point"}
}