{
  "type": "Feature",
  "properties": {
    "iso:country":"US",
    "sg:address":"21000 NE 34th Ct",
    "sg:city":"Miami",
    "sg:classifiers":[
        {
            "category":"Manufacturing",
            "subcategory":"Apparel",
            "type":"Manufacturing & Wholesale Goods"
        }
    ],
    "sg:phone":"+1 305 792 4051",
    "sg:postcode":"33180",
    "sg:province":"FL",
    "sg:tags":[
        "sterling",
        "mfg",
        "jewelry",
        "scarf",
        "silver"
    ],
    "wof:name":"Dazzle Designs",
    "wof:placetype":"venue"
},
  "geometry": {"coordinates":[-80.13322599999999,25.970125],"type":"Point"}
}