{
  "type": "Feature",
  "properties": {
    "iso:country":"US",
    "sg:address":"1434 S Miami Ave",
    "sg:city":"Miami",
    "sg:classifiers":[
        {
            "category":"Professional",
            "subcategory":"Advertising",
            "type":"Services"
        }
    ],
    "sg:phone":"+1 305 372 1430",
    "sg:postcode":"33130",
    "sg:province":"FL",
    "sg:tags":[
        "marketing",
        "agency"
    ],
    "wof:name":"Shepard Lobe Costa Inc",
    "wof:placetype":"venue"
},
  "geometry": {"coordinates":[-80.193648,25.760381],"type":"Point"}
}