{
  "type": "Feature",
  "properties": {
    "iso:country":"US",
    "sg:address":"5675 Cypress Cir",
    "sg:city":"Tallahassee",
    "sg:classifiers":[
        {
            "category":"Building & Trades",
            "subcategory":"Construction",
            "type":"Services"
        }
    ],
    "sg:phone":"+1 850 591 6247",
    "sg:postcode":"32303",
    "sg:province":"FL",
    "sg:tags":[
        "wallcoverings-installation",
        "wallpaper",
        "painting",
        "contractor"
    ],
    "wof:name":"Rickey Palmer Painting",
    "wof:placetype":"venue"
},
  "geometry": {"coordinates":[-84.375308,30.515617],"type":"Point"}
}