{
  "type": "Feature",
  "properties": {
    "addr:full":"3150 46th Ave N Saint Petersburg FL 33714",
    "addr:housenumber":"3150",
    "addr:postcode":"33714",
    "addr:street":"46Th Ave N",
    "iso:country":"US",
    "sg:address":"3150 46th Ave N",
    "sg:city":"Saint Petersburg",
    "sg:classifiers":[
        {
            "category":"Building & Trades",
            "subcategory":"Construction",
            "type":"Services"
        }
    ],
    "sg:phone":"+1 727 527 6991",
    "sg:postcode":"33714",
    "sg:province":"FL",
    "sg:tags":[
        "residential",
        "commercial"
    ],
    "wof:name":"Moore Turner & Associates",
    "wof:placetype":"venue"
},
  "geometry": {"coordinates":[-82.678839,27.813734],"type":"Point"}
}