{
  "type": "Feature",
  "properties": {
    "addr:full":"1831 S Mccall Rd Englewood FL 34223",
    "addr:housenumber":"1831",
    "addr:postcode":"34223",
    "addr:street":"S Mccall Rd",
    "iso:country":"US",
    "sg:address":"1831 S Mccall Rd",
    "sg:city":"Englewood",
    "sg:classifiers":[
        {
            "category":"Banks & Credit Unions",
            "subcategory":"Bank",
            "type":"Services"
        },
        {
            "category":"Banks & Credit Unions",
            "subcategory":"Financial Services",
            "type":"Services"
        }
    ],
    "sg:phone":"+1 941 474 9347",
    "sg:postcode":"34223",
    "sg:province":"FL",
    "sg:tags":[
        "commercial",
        "loan",
        "saving",
        "mortgage"
    ],
    "sg:website":"https://www.wachovia.com/?DCMP=KNL-CPS-DS-Directory-0703&HBX_PK=Banks&HBX_OU=71",
    "wof:name":"Wachovia Bank",
    "wof:placetype":"venue"
},
  "geometry": {"coordinates":[-82.336984,26.93834],"type":"Point"}
}