{
  "type": "Feature",
  "properties": {
    "addr:full":"6400 Topaz Ct Fort Myers FL 33966",
    "addr:housenumber":"6400",
    "addr:postcode":"33966",
    "addr:street":"Topaz Ct",
    "iso:country":"US",
    "sg:address":"6400 Topaz Ct",
    "sg:city":"Fort Myers",
    "sg:classifiers":[
        {
            "category":"Professional",
            "subcategory":"Business Services",
            "type":"Services"
        }
    ],
    "sg:phone":"+1 239 936 8120",
    "sg:postcode":"33966",
    "sg:province":"FL",
    "wof:name":"Professional Writing & RES",
    "wof:placetype":"venue"
},
  "geometry": {"coordinates":[-81.851472,26.56915],"type":"Point"}
}