{
  "type": "Feature",
  "properties": {
    "addr:full":"804 Lake Ave Lake Worth FL 33460",
    "addr:housenumber":"804",
    "addr:postcode":"33460",
    "addr:street":"Lake Ave",
    "iso:country":"US",
    "sg:address":"804 Lake Ave",
    "sg:city":"Lake Worth",
    "sg:classifiers":[
        {
            "category":"Professional",
            "subcategory":"Business Services",
            "type":"Services"
        }
    ],
    "sg:phone":"+1 561 588 0138",
    "sg:postcode":"33460",
    "sg:province":"FL",
    "sg:tags":[
        "interior",
        "consultant",
        "design",
        "decorator"
    ],
    "wof:name":"Jamies Interior Consignment",
    "wof:placetype":"venue"
},
  "geometry": {"coordinates":[-80.057311,26.615984],"type":"Point"}
}