{
  "type": "Feature",
  "properties": {
    "addr:full":"125 E Boynton Beach Blvd Boynton Beach FL 33435",
    "addr:housenumber":"125",
    "addr:postcode":"33435",
    "addr:street":"E Boynton Beach Blvd",
    "iso:country":"US",
    "sg:address":"125 E Boynton Beach Blvd",
    "sg:city":"Boynton Beach",
    "sg:classifiers":[
        {
            "category":"Real Estate",
            "subcategory":"Real Estate Agent",
            "type":"Services"
        }
    ],
    "sg:phone":"+1 561 732 7370",
    "sg:postcode":"33435",
    "sg:province":"FL",
    "wof:name":"Sellers Only Real Estate Brkrg",
    "wof:placetype":"venue"
},
  "geometry": {"coordinates":[-80.062612,26.528984],"type":"Point"}
}