{
  "type": "Feature",
  "properties": {
    "iso:country":"US",
    "sg:address":"7500 NW 58th St",
    "sg:city":"Tamarac",
    "sg:classifiers":[
        {
            "category":"Retail",
            "subcategory":"Repair Shop",
            "type":"Services"
        },
        {
            "category":"Building & Trades",
            "subcategory":"Construction",
            "type":"Services"
        }
    ],
    "sg:phone":"+1 954 722 5773",
    "sg:postcode":"33321",
    "sg:province":"FL",
    "sg:tags":[
        "home",
        "fix-it",
        "maintenance"
    ],
    "wof:name":"Kurts Services",
    "wof:placetype":"venue"
},
  "geometry": {"coordinates":[-80.250615,26.196916],"type":"Point"}
}