{
  "type": "Feature",
  "properties": {
    "iso:country":"US",
    "sg:address":"1792 Bell Tower Ln",
    "sg:city":"Weston",
    "sg:classifiers":[
        {
            "category":"Professional",
            "subcategory":"Detective & Security Services",
            "type":"Services"
        }
    ],
    "sg:phone":"+1 954 315 3663",
    "sg:postcode":"33326",
    "sg:province":"FL",
    "sg:tags":[
        "information",
        "bureau"
    ],
    "wof:name":"Mbm Professional Svcs",
    "wof:placetype":"venue"
},
  "geometry": {"coordinates":[-80.379622,26.096442],"type":"Point"}
}