{
  "type": "Feature",
  "properties": {
    "addr:full":"8930 Seminole Blvd Seminole FL 33772",
    "addr:housenumber":"8930",
    "addr:postcode":"33772",
    "addr:street":"Seminole Blvd",
    "iso:country":"US",
    "sg:address":"8930 Seminole Blvd",
    "sg:city":"Seminole",
    "sg:classifiers":[
        {
            "category":"Personal",
            "subcategory":"Beauty Salon",
            "type":"Services"
        }
    ],
    "sg:phone":"+1 727 392 3686",
    "sg:postcode":"33772",
    "sg:province":"FL",
    "wof:name":"Amanda Jo Briody Hair",
    "wof:placetype":"venue"
},
  "geometry": {"coordinates":[-82.787173,27.853478],"type":"Point"}
}