{
  "type": "Feature",
  "properties": {
    "iso:country":"US",
    "sg:address":"5801 NW 151st St",
    "sg:city":"Hialeah",
    "sg:classifiers":[
        {
            "category":"Professional",
            "subcategory":"Lawyer & Legal Services",
            "type":"Services"
        }
    ],
    "sg:phone":"+1 305 821 5255",
    "sg:postcode":"33014",
    "sg:province":"FL",
    "sg:tags":[
        "litigation",
        "attorney",
        "family",
        "civil",
        "divorce",
        "immigration",
        "trial",
        "law"
    ],
    "wof:name":"Alfaro & Fernandez PA",
    "wof:placetype":"venue"
},
  "geometry": {"coordinates":[-80.294319,25.910749],"type":"Point"}
}