{
  "type": "Feature",
  "properties": {
    "addr:full":"1501 Lady Ave Ocoee FL 34761",
    "addr:housenumber":"1501",
    "addr:postcode":"34761",
    "addr:street":"Lady Ave",
    "iso:country":"US",
    "sg:address":"1501 Lady Ave",
    "sg:city":"Ocoee",
    "sg:classifiers":[
        {
            "category":"Building & Trades",
            "subcategory":"Construction",
            "type":"Services"
        }
    ],
    "sg:phone":"+1 407 656 6923",
    "sg:postcode":"34761",
    "sg:province":"FL",
    "sg:tags":[
        "mason",
        "masonry",
        "industrial",
        "contractors-commercial",
        "contractor"
    ],
    "wof:name":"Darryl James Schmidt Masonary",
    "wof:placetype":"venue"
},
  "geometry": {"coordinates":[-81.528221,28.588381],"type":"Point"}
}