{
  "type": "Feature",
  "properties": {
    "iso:country":"US",
    "sg:address":"10764 US Hwy 1",
    "sg:city":"Port St Lucie",
    "sg:classifiers":[
        {
            "category":"Food & Beverages",
            "subcategory":"Groceries & Convenience Stores",
            "type":"Retail Goods"
        }
    ],
    "sg:phone":"+1 772 337 2122",
    "sg:postcode":"34952",
    "sg:province":"FL",
    "sg:tags":[
        "grocer"
    ],
    "wof:name":"Patsys West Indian Grocery",
    "wof:placetype":"venue"
},
  "geometry": {"coordinates":[-80.28572,27.266965],"type":"Point"}
}