{
  "type": "Feature",
  "properties": {
    "addr:full":"8402 Boxwood Dr Tampa FL 33615",
    "addr:housenumber":"8402",
    "addr:postcode":"33615",
    "addr:street":"Boxwood Dr",
    "iso:country":"US",
    "sg:address":"8402 Boxwood Dr",
    "sg:city":"Tampa",
    "sg:classifiers":[
        {
            "category":"Social Services",
            "subcategory":"Job Training",
            "type":"Services"
        }
    ],
    "sg:phone":"+1 813 886 6633",
    "sg:postcode":"33615",
    "sg:province":"FL",
    "sg:tags":[
        "car"
    ],
    "wof:name":"Robinson Business Services",
    "wof:placetype":"venue"
},
  "geometry": {"coordinates":[-82.576801,27.986482],"type":"Point"}
}