{
  "type": "Feature",
  "properties": {
    "addr:full":"1008 Loring Ave Orange Park FL 32073",
    "addr:housenumber":"1008",
    "addr:postcode":"32073",
    "addr:street":"Loring Ave",
    "iso:country":"US",
    "sg:address":"1008 Loring Ave",
    "sg:city":"Orange Park",
    "sg:classifiers":[
        {
            "category":"Building & Trades",
            "subcategory":"Construction",
            "type":"Services"
        }
    ],
    "sg:phone":"+1 904 215 9711",
    "sg:postcode":"32073",
    "sg:province":"FL",
    "sg:tags":[
        "screen",
        "enclosure"
    ],
    "wof:name":"Aable Screenrooms & Enclosures",
    "wof:placetype":"venue"
},
  "geometry": {"coordinates":[-81.71105900000001,30.180195],"type":"Point"}
}