{
  "type": "Feature",
  "properties": {
    "iso:country":"US",
    "sg:address":"4940 Hoffner Ave",
    "sg:city":"Orlando",
    "sg:classifiers":[
        {
            "category":"Organizations",
            "subcategory":"Religious Organization",
            "type":"Services"
        }
    ],
    "sg:phone":"+1 407 856 7997",
    "sg:postcode":"32812",
    "sg:province":"FL",
    "sg:tags":[
        "church"
    ],
    "sg:website":"www.idpmisudeste.org",
    "wof:name":"Iglesia De Dios Pentecostal",
    "wof:placetype":"venue"
},
  "geometry": {"coordinates":[-81.322007,28.480485],"type":"Point"}
}