{
  "type": "Feature",
  "properties": {
    "addr:full":"12233 Lacewood Ln Wellington FL 33414",
    "addr:housenumber":"12233",
    "addr:postcode":"33414",
    "addr:street":"Lacewood Ln",
    "iso:country":"US",
    "sg:address":"12233 Lacewood Ln",
    "sg:city":"Wellington",
    "sg:classifiers":[
        {
            "category":"Building & Trades",
            "subcategory":"Construction",
            "type":"Services"
        }
    ],
    "sg:phone":"+1 561 308 9864",
    "sg:postcode":"33414",
    "sg:province":"FL",
    "sg:tags":[
        "carpenter"
    ],
    "wof:name":"James Knight Carpenter",
    "wof:placetype":"venue"
},
  "geometry": {"coordinates":[-80.238399,26.669267],"type":"Point"}
}