{
  "type": "Feature",
  "properties": {
    "addr:full":"4111 W Waters Ave Tampa FL 33614",
    "addr:housenumber":"4111",
    "addr:postcode":"33614",
    "addr:street":"W Waters Ave",
    "iso:country":"US",
    "sg:address":"4111 W Waters Ave",
    "sg:city":"Tampa",
    "sg:classifiers":[
        {
            "category":"Banks & Credit Unions",
            "subcategory":"Investment Brokerage",
            "type":"Services"
        }
    ],
    "sg:phone":"+1 813 890 9757",
    "sg:postcode":"33614",
    "sg:province":"FL",
    "wof:name":"Taylor Investments",
    "wof:placetype":"venue"
},
  "geometry": {"coordinates":[-82.51101300000001,28.02555],"type":"Point"}
}