{
  "type": "Feature",
  "properties": {
    "addr:full":"13822 Litewood Dr Hudson FL 34669",
    "addr:housenumber":"13822",
    "addr:postcode":"34669",
    "addr:street":"Litewood Dr",
    "iso:country":"US",
    "sg:address":"13822 Litewood Dr",
    "sg:city":"Hudson",
    "sg:classifiers":[
        {
            "category":"Building & Trades",
            "subcategory":"Construction",
            "type":"Services"
        }
    ],
    "sg:phone":"+1 727 869 8725",
    "sg:postcode":"34669",
    "sg:province":"FL",
    "sg:tags":[
        "handyman"
    ],
    "wof:name":"Warren Chapman Handyman Svc",
    "wof:placetype":"venue"
},
  "geometry": {"coordinates":[-82.652163,28.358344],"type":"Point"}
}