{
  "type": "Feature",
  "properties": {
    "iso:country":"US",
    "sg:address":"6217 E Hillsborough Ave",
    "sg:city":"Tampa",
    "sg:classifiers":[
        {
            "category":"Restaurant",
            "type":"Food & Drink"
        }
    ],
    "sg:phone":"+1 813 626 5085",
    "sg:postcode":"33610",
    "sg:province":"FL",
    "sg:tags":[
        "eating"
    ],
    "wof:name":"Subway",
    "wof:placetype":"venue"
},
  "geometry": {"coordinates":[-82.385525,27.996182],"type":"Point"}
}