{
  "type": "Feature",
  "properties": {
    "addr:full":"124 E Wright St Pensacola FL 32501",
    "addr:housenumber":"124",
    "addr:postcode":"32501",
    "addr:street":"E Wright St",
    "iso:country":"US",
    "sg:address":"124 E Wright St",
    "sg:city":"Pensacola",
    "sg:classifiers":[
        {
            "category":"Health Services",
            "subcategory":"Clinic",
            "type":"Services"
        }
    ],
    "sg:phone":"+1 850 432 9615",
    "sg:postcode":"32501",
    "sg:province":"FL",
    "sg:tags":[
        "home"
    ],
    "wof:name":"Sacred Heart Home Care",
    "wof:placetype":"venue"
},
  "geometry": {"coordinates":[-87.213993,30.417092],"type":"Point"}
}