{
  "type": "Feature",
  "properties": {
    "iso:country":"US",
    "sg:address":"2822 Huffman Blvd",
    "sg:city":"Jacksonville",
    "sg:classifiers":[
        {
            "category":"Building & Trades",
            "subcategory":"Plumbing",
            "type":"Services"
        }
    ],
    "sg:phone":"+1 904 641 0833",
    "sg:postcode":"32246",
    "sg:province":"FL",
    "sg:tags":[
        "plumbing",
        "contractor"
    ],
    "wof:name":"J D Vaughn & Sons Plumbing Co",
    "wof:placetype":"venue"
},
  "geometry": {"coordinates":[-81.50506300000001,30.295115],"type":"Point"}
}