{
  "type": "Feature",
  "properties": {
    "addr:full":"4311 Ravinnia Dr Orlando FL 32809",
    "addr:housenumber":"4311",
    "addr:postcode":"32809",
    "addr:street":"Ravinnia Dr",
    "iso:country":"US",
    "sg:address":"4311 Ravinnia Dr",
    "sg:city":"Orlando",
    "sg:classifiers":[
        {
            "category":"Building & Trades",
            "subcategory":"Landscaping Services",
            "type":"Services"
        }
    ],
    "sg:phone":"+1 407 248 9128",
    "sg:postcode":"32809",
    "sg:province":"FL",
    "sg:tags":[
        "landscape",
        "contractor"
    ],
    "wof:name":"Capley Landscaping & Mntnc",
    "wof:placetype":"venue"
},
  "geometry": {"coordinates":[-81.431147,28.466291],"type":"Point"}
}