{
  "type": "Feature",
  "properties": {
    "iso:country":"US",
    "sg:address":"2740 Prine Rd",
    "sg:city":"Lakeland",
    "sg:classifiers":[
        {
            "category":"Wholesale",
            "subcategory":"Non-durable Goods",
            "type":"Manufacturing & Wholesale Goods"
        }
    ],
    "sg:phone":"+1 863 858 8777",
    "sg:postcode":"33810",
    "sg:province":"FL",
    "sg:tags":[
        "merchandise",
        "general"
    ],
    "wof:name":"Auction Center Inc",
    "wof:placetype":"venue"
},
  "geometry": {"coordinates":[-82.00184900000001,28.08705],"type":"Point"}
}