{
  "type": "Feature",
  "properties": {
    "addr:full":"122 S Howard Ave Tampa FL 33606",
    "addr:housenumber":"122",
    "addr:postcode":"33606",
    "addr:street":"S Howard Ave",
    "iso:country":"US",
    "sg:address":"122 S Howard Ave",
    "sg:city":"Tampa",
    "sg:classifiers":[
        {
            "category":"Professional",
            "subcategory":"Lawyer & Legal Services",
            "type":"Services"
        }
    ],
    "sg:phone":"+1 813 254 3736",
    "sg:postcode":"33606",
    "sg:province":"FL",
    "wof:name":"Michael Celso Gonzalez PA",
    "wof:placetype":"venue"
},
  "geometry": {"coordinates":[-82.482917,27.943656],"type":"Point"}
}