{
  "type": "Feature",
  "properties": {
    "iso:country":"US",
    "sg:address":"2160 Vance Ave",
    "sg:city":"Palm Harbor",
    "sg:classifiers":[
        {
            "category":"Autos & Motor Vehicles",
            "subcategory":"Automobile Sales",
            "type":"Retail Goods"
        }
    ],
    "sg:phone":"+1 727 786 4654",
    "sg:postcode":"34683",
    "sg:province":"FL",
    "sg:tags":[
        "used"
    ],
    "wof:name":"Zs Cars Inc",
    "wof:placetype":"venue"
},
  "geometry": {"coordinates":[-82.74577600000001,28.075709],"type":"Point"}
}