{
  "type": "Feature",
  "properties": {
    "iso:country":"US",
    "sg:address":"1000 E. 16th Street",
    "sg:city":"Hialeah",
    "sg:classifiers":[
        {
            "category":"Deli",
            "type":"Food & Drink"
        }
    ],
    "sg:phone":"+1 305 887 8863",
    "sg:postcode":"33010",
    "sg:province":"FL",
    "wof:name":"Stephen's Restaurant and New York Style Deli",
    "wof:placetype":"venue"
},
  "geometry": {"coordinates":[-80.261487,25.836842],"type":"Point"}
}