{
  "type": "Feature",
  "properties": {
    "iso:country":"US",
    "sg:address":"2440 Dinneen Ave",
    "sg:city":"Orlando",
    "sg:classifiers":[
        {
            "category":"Shopping",
            "subcategory":"Clothing, Apparel, & Fashions",
            "type":"Retail Goods"
        }
    ],
    "sg:phone":"+1 407 522 0805",
    "sg:postcode":"32804",
    "sg:province":"FL",
    "sg:tags":[
        "t"
    ],
    "wof:name":"Casual Tee's",
    "wof:placetype":"venue"
},
  "geometry": {"coordinates":[-81.411214,28.576158],"type":"Point"}
}