{
  "type": "Feature",
  "properties": {
    "addr:full":"4017 Coralbrooke Grove Orlando FL 32826",
    "addr:housenumber":"4017",
    "addr:postcode":"32826",
    "addr:street":"Coralbrooke Grove",
    "iso:country":"US",
    "sg:address":"4017 Coralbrooke Grove",
    "sg:city":"Orlando",
    "sg:classifiers":[
        {
            "category":"Building & Trades",
            "subcategory":"Construction",
            "type":"Services"
        }
    ],
    "sg:phone":"+1 407 207 1953",
    "sg:postcode":"32826",
    "sg:province":"FL",
    "sg:tags":[
        "general",
        "contractor"
    ],
    "wof:name":"Canepa Construction Co",
    "wof:placetype":"venue"
},
  "geometry": {"coordinates":[-81.185571,28.598618],"type":"Point"}
}