{
  "type": "Feature",
  "properties": {
    "addr:full":"1056 N Pine Hills Rd Orlando FL 32808",
    "addr:housenumber":"1056",
    "addr:postcode":"32808",
    "addr:street":"N Pine Hills Rd",
    "iso:country":"US",
    "sg:address":"1056 N Pine Hills Rd",
    "sg:city":"Orlando",
    "sg:classifiers":[
        {
            "category":"Social Services",
            "subcategory":"Child Care",
            "type":"Services"
        }
    ],
    "sg:phone":"+1 407 521 6273",
    "sg:postcode":"32808",
    "sg:province":"FL",
    "sg:tags":[
        "day"
    ],
    "wof:name":"Gods Little Lambs Lrng Ctr",
    "wof:placetype":"venue"
},
  "geometry": {"coordinates":[-81.44972,28.559782],"type":"Point"}
}