{
  "type": "Feature",
  "properties": {
    "iso:country":"US",
    "sg:address":"3535 Central Ave",
    "sg:city":"St Petersburg",
    "sg:classifiers":[
        {
            "category":"Real Estate",
            "subcategory":"Real Estate Operator",
            "type":"Services"
        }
    ],
    "sg:phone":"+1 727 894 0185",
    "sg:postcode":"33713",
    "sg:province":"FL",
    "sg:tags":[
        "mall",
        "shopping",
        "center"
    ],
    "wof:name":"Insurance Mall-St Petersburg",
    "wof:placetype":"venue"
},
  "geometry": {"coordinates":[-82.681664,27.771075],"type":"Point"}
}