{
  "type": "Feature",
  "properties": {
    "addr:full":"1026 E Highland Dr Lakeland FL 33813",
    "addr:housenumber":"1026",
    "addr:postcode":"33813",
    "addr:street":"E Highland Dr",
    "iso:country":"US",
    "sg:address":"1026 E Highland Dr",
    "sg:city":"Lakeland",
    "sg:classifiers":[
        {
            "category":"Professional",
            "subcategory":"Employment Agencies",
            "type":"Services"
        }
    ],
    "sg:phone":"+1 863 646 5950",
    "sg:postcode":"33813",
    "sg:province":"FL",
    "sg:tags":[
        "help",
        "supply"
    ],
    "wof:name":"Chastain Skillman",
    "wof:placetype":"venue"
},
  "geometry": {"coordinates":[-81.94474099999999,27.986273],"type":"Point"}
}