{
  "type": "Feature",
  "properties": {
    "iso:country":"US",
    "sg:address":"265 S Lakeview Dr",
    "sg:city":"Lake Helen",
    "sg:classifiers":[
        {
            "category":"Local Transit",
            "type":"Transportation"
        }
    ],
    "sg:phone":"+1 386 574 1717",
    "sg:postcode":"32744",
    "sg:province":"FL",
    "sg:tags":[
        "limousine"
    ],
    "wof:name":"Kenahan Transportation Svc Inc",
    "wof:placetype":"venue"
},
  "geometry": {"coordinates":[-81.23169,28.981776],"type":"Point"}
}