{
  "type": "Feature",
  "properties": {
    "iso:country":"US",
    "sg:address":"3810 S Ocean Dr",
    "sg:city":"Hollywood",
    "sg:classifiers":[
        {
            "category":"Retail",
            "subcategory":"Laundry & Dry Cleaning",
            "type":"Services"
        }
    ],
    "sg:phone":"+1 954 458 5384",
    "sg:postcode":"33019",
    "sg:province":"FL",
    "sg:tags":[
        "cleaners"
    ],
    "wof:name":"Oceania Executive Cleaners",
    "wof:placetype":"venue"
},
  "geometry": {"coordinates":[-80.11833799999999,25.996918],"type":"Point"}
}