{
  "type": "Feature",
  "properties": {
    "addr:full":"235 Silver Oak Dr Havana FL 32333",
    "addr:housenumber":"235",
    "addr:postcode":"32333",
    "addr:street":"Silver Oak Dr",
    "iso:country":"US",
    "sg:address":"235 Silver Oak Dr",
    "sg:city":"Havana",
    "sg:classifiers":[
        {
            "category":"Personal",
            "subcategory":"Beauty Salon",
            "type":"Services"
        }
    ],
    "sg:phone":"+1 850 539 3723",
    "sg:postcode":"32333",
    "sg:province":"FL",
    "wof:name":"Brown Hair Salon",
    "wof:placetype":"venue"
},
  "geometry": {"coordinates":[-84.44001,30.61839],"type":"Point"}
}