{
  "type": "Feature",
  "properties": {
    "iso:country":"US",
    "sg:address":"1533 Sunset Dr Ste 150",
    "sg:city":"Miami",
    "sg:classifiers":[
        {
            "category":"Building & Trades",
            "subcategory":"Construction",
            "type":"Services"
        }
    ],
    "sg:phone":"+1 305 665 1146",
    "sg:postcode":"33143",
    "sg:province":"FL",
    "sg:tags":[
        "contractor"
    ],
    "wof:name":"First Florida Building Corp",
    "wof:placetype":"venue"
},
  "geometry": {"coordinates":[-80.277506,25.704816],"type":"Point"}
}