{
  "type": "Feature",
  "properties": {
    "addr:full":"811 E Base St Madison FL 32340",
    "addr:housenumber":"811",
    "addr:postcode":"32340",
    "addr:street":"E Base St",
    "iso:country":"US",
    "sg:address":"811 E Base St",
    "sg:city":"Madison",
    "sg:classifiers":[
        {
            "category":"Restaurant",
            "type":"Food & Drink"
        }
    ],
    "sg:phone":"+1 850 973 6100",
    "sg:postcode":"32340",
    "sg:province":"FL",
    "wof:name":"Subway Sandwiches & Salads",
    "wof:placetype":"venue"
},
  "geometry": {"coordinates":[-83.405342,30.469178],"type":"Point"}
}