{
  "type": "Feature",
  "properties": {
    "iso:country":"US",
    "sg:address":"2477 Stickney Point Rd",
    "sg:city":"Sarasota",
    "sg:classifiers":[
        {
            "category":"Health Services",
            "subcategory":"Health Practitioner",
            "type":"Services"
        }
    ],
    "sg:phone":"+1 941 927 8996",
    "sg:postcode":"34231",
    "sg:province":"FL",
    "wof:name":"Lynch Frank Acsw Lcsw Bcd",
    "wof:placetype":"venue"
},
  "geometry": {"coordinates":[-82.520636,27.26255],"type":"Point"}
}