{
  "type": "Feature",
  "properties": {
    "iso:country":"US",
    "sg:address":"3899 NE Skyline Dr",
    "sg:city":"Jensen Beach",
    "sg:classifiers":[
        {
            "category":"Recreation",
            "type":"Entertainment"
        }
    ],
    "sg:phone":"+1 772 334 9789",
    "sg:postcode":"34957",
    "sg:province":"FL",
    "wof:name":"Power Boat Club",
    "wof:placetype":"venue"
},
  "geometry": {"coordinates":[-80.23329,27.25305],"type":"Point"}
}