{
  "type": "Feature",
  "properties": {
    "addr:full":"2810 Scherer Dr Saint Petersburg FL 33716",
    "addr:housenumber":"2810",
    "addr:postcode":"33716",
    "addr:street":"Scherer Dr",
    "iso:country":"US",
    "sg:address":"2810 Scherer Dr",
    "sg:city":"Saint Petersburg",
    "sg:classifiers":[
        {
            "category":"Real Estate",
            "subcategory":"Real Estate Agent",
            "type":"Services"
        }
    ],
    "sg:phone":"+1 727 572 5075",
    "sg:postcode":"33716",
    "sg:province":"FL",
    "wof:name":"CB Richard Ellis Inc",
    "wof:placetype":"venue"
},
  "geometry": {"coordinates":[-82.676851,27.885657],"type":"Point"}
}