{
  "type": "Feature",
  "properties": {
    "addr:full":"10480 Oak St NE St Petersburg FL 33716",
    "addr:housenumber":"10480",
    "addr:postcode":"33716",
    "addr:street":"Oak St Ne",
    "iso:country":"US",
    "sg:address":"10480 Oak St NE",
    "sg:city":"St Petersburg",
    "sg:classifiers":[
        {
            "category":"Manufacturing",
            "subcategory":"Retail Goods",
            "type":"Manufacturing & Wholesale Goods"
        },
        {
            "category":"Manufacturing",
            "subcategory":"Wood Products",
            "type":"Manufacturing & Wholesale Goods"
        }
    ],
    "sg:phone":"+1 727 577 1216",
    "sg:postcode":"33716",
    "sg:province":"FL",
    "sg:tags":[
        "metal",
        "mfg",
        "container",
        "manufacturer",
        "luggage"
    ],
    "wof:name":"Viking Cases",
    "wof:placetype":"venue"
},
  "geometry": {"coordinates":[-82.63175,27.868437],"type":"Point"}
}