{
  "type": "Feature",
  "properties": {
    "addr:full":"1851 S Federal Hwy Fort Lauderdale FL 33316",
    "addr:housenumber":"1851",
    "addr:postcode":"33316",
    "addr:street":"S Federal Hwy",
    "iso:country":"US",
    "sg:address":"1851 S Federal Hwy",
    "sg:city":"Fort Lauderdale",
    "sg:classifiers":[
        {
            "category":"Travel",
            "subcategory":"Hotels & Motels",
            "type":"Entertainment"
        }
    ],
    "sg:phone":"+1 954 462 5146",
    "sg:postcode":"33316",
    "sg:province":"FL",
    "wof:name":"Relax Inn",
    "wof:placetype":"venue"
},
  "geometry": {"coordinates":[-80.13669899999999,26.097825],"type":"Point"}
}