{
  "type": "Feature",
  "properties": {
    "iso:country":"US",
    "sg:address":"7835 Gunn Hwy",
    "sg:city":"Tampa",
    "sg:classifiers":[
        {
            "category":"Food & Beverages",
            "subcategory":"Groceries & Convenience Stores",
            "type":"Retail Goods"
        }
    ],
    "sg:phone":"+1 813 926 6664",
    "sg:postcode":"33626",
    "sg:province":"FL",
    "sg:tags":[
        "grocer"
    ],
    "wof:name":"Publix Super Market",
    "wof:placetype":"venue"
},
  "geometry": {"coordinates":[-82.57489700000001,28.078776],"type":"Point"}
}