{
  "type": "Feature",
  "properties": {
    "addr:full":"2218 Saint Mary Ave Pensacola FL 32505",
    "addr:housenumber":"2218",
    "addr:postcode":"32505",
    "addr:street":"Saint Mary Ave",
    "iso:country":"US",
    "sg:address":"2218 Saint Mary Ave",
    "sg:city":"Pensacola",
    "sg:classifiers":[
        {
            "category":"Building & Trades",
            "subcategory":"Construction",
            "type":"Services"
        }
    ],
    "sg:phone":"+1 850 478 3679",
    "sg:postcode":"32505",
    "sg:province":"FL",
    "sg:tags":[
        "company",
        "painting",
        "contractor"
    ],
    "wof:name":"Dufrain Construction Inc",
    "wof:placetype":"venue"
},
  "geometry": {"coordinates":[-87.24138600000001,30.441647],"type":"Point"}
}