{
  "type": "Feature",
  "properties": {
    "iso:country":"US",
    "sg:address":"301 E Atlantic Ave",
    "sg:city":"Delray Beach",
    "sg:classifiers":[
        {
            "category":"Restaurant",
            "type":"Food & Drink"
        }
    ],
    "sg:phone":"+1 561 272 7427",
    "sg:postcode":"33483",
    "sg:province":"FL",
    "sg:tags":[
        "eating"
    ],
    "wof:name":"Elwood's Dixie Barbecue",
    "wof:placetype":"venue"
},
  "geometry": {"coordinates":[-80.069062,26.461651],"type":"Point"}
}