{
  "type": "Feature",
  "properties": {
    "iso:country":"US",
    "sg:address":"1875 NW 79th St",
    "sg:city":"Miami",
    "sg:classifiers":[
        {
            "category":"Building & Trades",
            "subcategory":"Landscaping Services",
            "type":"Services"
        }
    ],
    "sg:phone":"+1 305 691 8313",
    "sg:postcode":"33147",
    "sg:province":"FL",
    "sg:tags":[
        "sod",
        "sodding"
    ],
    "wof:name":"Aaron Agricultural",
    "wof:placetype":"venue"
},
  "geometry": {"coordinates":[-80.229051,25.846498],"type":"Point"}
}