{
  "type": "Feature",
  "properties": {
    "addr:full":"3415 Kori Rd Jacksonville FL 32257",
    "addr:housenumber":"3415",
    "addr:postcode":"32257",
    "addr:street":"Kori Rd",
    "iso:country":"US",
    "sg:address":"3415 Kori Rd",
    "sg:city":"Jacksonville",
    "sg:classifiers":[
        {
            "category":"Professional",
            "subcategory":"Testing Lab",
            "type":"Services"
        }
    ],
    "sg:phone":"+1 904 262 9991",
    "sg:postcode":"32257",
    "sg:province":"FL",
    "sg:website":"www.qore.com",
    "wof:name":"Qore Property Sciences",
    "wof:placetype":"venue"
},
  "geometry": {"coordinates":[-81.620507,30.203611],"type":"Point"}
}