{
  "type": "Feature",
  "properties": {
    "addr:full":"14090 W Dixie Hwy Miami FL 33161",
    "addr:housenumber":"14090",
    "addr:postcode":"33161",
    "addr:street":"W Dixie Hwy",
    "iso:country":"US",
    "sg:address":"14090 W Dixie Hwy",
    "sg:city":"Miami",
    "sg:classifiers":[
        {
            "category":"Autos & Motor Vehicles",
            "subcategory":"Fuel & Gas Station",
            "type":"Retail Goods"
        }
    ],
    "sg:phone":"+1 305 891 6350",
    "sg:postcode":"33161",
    "sg:province":"FL",
    "sg:tags":[
        "station",
        "gasoline"
    ],
    "wof:name":"West Dixie Service",
    "wof:placetype":"venue"
},
  "geometry": {"coordinates":[-80.173457,25.905119],"type":"Point"}
}