{
  "type": "Feature",
  "properties": {
    "iso:country":"US",
    "sg:address":"7803 N Orange Blossom Trl",
    "sg:city":"Orlando",
    "sg:classifiers":[
        {
            "category":"Manufacturing",
            "subcategory":"Tools & Machinery",
            "type":"Manufacturing & Wholesale Goods"
        }
    ],
    "sg:phone":"+1 407 578 9948",
    "sg:postcode":"32810",
    "sg:province":"FL",
    "sg:tags":[
        "industrial",
        "retailer",
        "scale"
    ],
    "wof:name":"A B S C O Indus Wghing Eqipmen",
    "wof:placetype":"venue"
},
  "geometry": {"coordinates":[-81.448994,28.628751],"type":"Point"}
}