{
  "type": "Feature",
  "properties": {
    "iso:country":"US",
    "sg:address":"1834 Talbot Ave",
    "sg:city":"Jacksonville",
    "sg:classifiers":[
        {
            "category":"Professional",
            "subcategory":"Research",
            "type":"Services"
        }
    ],
    "sg:phone":"+1 904 389 9222",
    "sg:postcode":"32205",
    "sg:province":"FL",
    "sg:tags":[
        "environmental",
        "ecological"
    ],
    "wof:name":"Hydro Terra Environment",
    "wof:placetype":"venue"
},
  "geometry": {"coordinates":[-81.70172599999999,30.296368],"type":"Point"}
}