{
  "type": "Feature",
  "properties": {
    "addr:full":"5941 18th St Zephyrhills FL 33542",
    "addr:housenumber":"5941",
    "addr:postcode":"33542",
    "addr:street":"18Th St",
    "iso:country":"US",
    "sg:address":"5941 18th St",
    "sg:city":"Zephyrhills",
    "sg:classifiers":[
        {
            "category":"Wholesale",
            "subcategory":"Construction Materials",
            "type":"Manufacturing & Wholesale Goods"
        },
        {
            "category":"Building & Trades",
            "subcategory":"Construction",
            "type":"Services"
        }
    ],
    "sg:phone":"+1 813 783 8704",
    "sg:postcode":"33542",
    "sg:province":"FL",
    "sg:tags":[
        "stucco",
        "contractor"
    ],
    "wof:name":"Acapulco Plasters & Stucco Inc",
    "wof:placetype":"venue"
},
  "geometry": {"coordinates":[-82.173709,28.244222],"type":"Point"}
}