{
  "type": "Feature",
  "properties": {
    "iso:country":"US",
    "sg:address":"106 E 4th Ave",
    "sg:city":"Tallahassee",
    "sg:classifiers":[
        {
            "category":"Retail",
            "subcategory":"Portrait Studio",
            "type":"Services"
        },
        {
            "category":"Professional",
            "subcategory":"Art Services",
            "type":"Services"
        }
    ],
    "sg:phone":"+1 850 878 9996",
    "sg:postcode":"32303",
    "sg:province":"FL",
    "sg:tags":[
        "rental",
        "photographers-portrait",
        "photographic",
        "darkroom"
    ],
    "sg:website":"http://www.portraitsociety.com",
    "wof:name":"Portrait Society Of America Inc",
    "wof:placetype":"venue"
},
  "geometry": {"coordinates":[-84.28182,30.45363],"type":"Point"}
}