{
  "type": "Feature",
  "properties": {
    "addr:full":"10752 Royal Caribbean Cir Boynton Beach FL 33437",
    "addr:housenumber":"10752",
    "addr:postcode":"33437",
    "addr:street":"Royal Caribbean Cir",
    "iso:country":"US",
    "sg:address":"10752 Royal Caribbean Cir",
    "sg:city":"Boynton Beach",
    "sg:classifiers":[
        {
            "category":"Insurance",
            "subcategory":"Insurance Agent",
            "type":"Services"
        }
    ],
    "sg:phone":"+1 561 736 1992",
    "sg:postcode":"33437",
    "sg:province":"FL",
    "sg:tags":[
        "audit"
    ],
    "wof:name":"Regional Reporting Service",
    "wof:placetype":"venue"
},
  "geometry": {"coordinates":[-80.132154,26.515058],"type":"Point"}
}