{
  "type": "Feature",
  "properties": {
    "iso:country":"US",
    "sg:address":"3480 Turtle Mound Rd",
    "sg:city":"Melbourne",
    "sg:classifiers":[
        {
            "category":"Building & Trades",
            "subcategory":"Construction",
            "type":"Services"
        }
    ],
    "sg:phone":"+1 321 242 9582",
    "sg:postcode":"32934",
    "sg:province":"FL",
    "sg:tags":[
        "house"
    ],
    "wof:name":"John A Barnes",
    "wof:placetype":"venue"
},
  "geometry": {"coordinates":[-80.688542,28.16467],"type":"Point"}
}