{
  "type": "Feature",
  "properties": {
    "iso:country":"US",
    "sg:address":"5712 E Arbor St",
    "sg:city":"Inverness",
    "sg:classifiers":[
        {
            "category":"Retail",
            "subcategory":"Auto Repair",
            "type":"Services"
        }
    ],
    "sg:phone":"+1 352 341 2005",
    "sg:postcode":"34452",
    "sg:province":"FL",
    "sg:tags":[
        "glass",
        "replacement"
    ],
    "wof:name":"Roadrunner Auto Glass & Access",
    "wof:placetype":"venue"
},
  "geometry": {"coordinates":[-82.338947,28.79652],"type":"Point"}
}