{
  "type": "Feature",
  "properties": {
    "addr:full":"1928 E 26th St Panama City FL 32405",
    "addr:housenumber":"1928",
    "addr:postcode":"32405",
    "addr:street":"E 26Th St",
    "iso:country":"US",
    "sg:address":"1928 E 26th St",
    "sg:city":"Panama City",
    "sg:classifiers":[
        {
            "category":"Building & Trades",
            "subcategory":"Cleaning & Sanitation",
            "type":"Services"
        }
    ],
    "sg:phone":"+1 850 785 4830",
    "sg:postcode":"32405",
    "sg:province":"FL",
    "sg:tags":[
        "janitor"
    ],
    "wof:name":"Cleaning Lady Svc",
    "wof:placetype":"venue"
},
  "geometry": {"coordinates":[-85.63864599999999,30.194906],"type":"Point"}
}