{
  "type": "Feature",
  "properties": {
    "addr:full":"200 E Forsyth St Jacksonville FL 32202",
    "addr:housenumber":"200",
    "addr:postcode":"32202",
    "addr:street":"E Forsyth St",
    "iso:country":"US",
    "sg:address":"200 E Forsyth St",
    "sg:city":"Jacksonville",
    "sg:classifiers":[
        {
            "category":"Professional",
            "subcategory":"Lawyer & Legal Services",
            "type":"Services"
        }
    ],
    "sg:phone":"+1 904 854 4400",
    "sg:postcode":"32202",
    "sg:province":"FL",
    "sg:tags":[
        "practice",
        "attorney",
        "criminal",
        "plan",
        "law"
    ],
    "wof:name":"Law Offices Of Alan Ceballos",
    "wof:placetype":"venue"
},
  "geometry": {"coordinates":[-81.655342,30.32646],"type":"Point"}
}