{
  "type": "Feature",
  "properties": {
    "iso:country":"US",
    "sg:address":"3086 S Jog Rd",
    "sg:city":"Greenacres",
    "sg:classifiers":[
        {
            "category":"Insurance",
            "subcategory":"Insurance Agent",
            "type":"Services"
        },
        {
            "category":"Insurance",
            "subcategory":"Hazard Insurance",
            "type":"Services"
        },
        {
            "category":"Insurance",
            "subcategory":"Health Insurance",
            "type":"Services"
        }
    ],
    "sg:phone":"+1 561 432 5984",
    "sg:postcode":"33467",
    "sg:province":"FL",
    "sg:tags":[
        "employee",
        "auto",
        "benefit",
        "commercial",
        "business"
    ],
    "sg:website":"http://www.glennsinsurance.com/",
    "wof:name":"Glenn's Insurance Agency",
    "wof:placetype":"venue"
},
  "geometry": {"coordinates":[-80.145995,26.630669],"type":"Point"}
}