{
  "type": "Feature",
  "properties": {
    "iso:country":"US",
    "sg:address":"550 5th Ave SE",
    "sg:city":"St Petersburg",
    "sg:classifiers":[
        {
            "category":"Government",
            "subcategory":"Office",
            "type":"Public Place"
        }
    ],
    "sg:phone":"+1 727 823 8897",
    "sg:postcode":"33701",
    "sg:province":"FL",
    "sg:tags":[
        "federal"
    ],
    "wof:name":"US Air Traffic Control",
    "wof:placetype":"venue"
},
  "geometry": {"coordinates":[-82.631085,27.765332],"type":"Point"}
}