{
  "type": "Feature",
  "properties": {
    "iso:country":"US",
    "sg:address":"4255 5th Ave SW",
    "sg:city":"Naples",
    "sg:classifiers":[
        {
            "category":"Autos & Motor Vehicles",
            "subcategory":"Auto Supplies",
            "type":"Retail Goods"
        }
    ],
    "sg:phone":"+1 239 352 8378",
    "sg:postcode":"34119",
    "sg:province":"FL",
    "sg:tags":[
        "high",
        "performance",
        "parts",
        "car",
        "accessory"
    ],
    "wof:name":"Topspeed Performance",
    "wof:placetype":"venue"
},
  "geometry": {"coordinates":[-81.696399,26.219678],"type":"Point"}
}