{
  "type": "Feature",
  "properties": {
    "iso:country":"US",
    "sg:address":"5400 NW 22nd Ave",
    "sg:city":"Miami",
    "sg:classifiers":[
        {
            "category":"Social Services",
            "subcategory":"Job Training",
            "type":"Services"
        }
    ],
    "sg:phone":"+1 305 636 2480",
    "sg:postcode":"33142",
    "sg:province":"FL",
    "sg:tags":[
        "rehab",
        "government"
    ],
    "wof:name":"Labor & Employment Security",
    "wof:placetype":"venue"
},
  "geometry": {"coordinates":[-80.232754,25.826006],"type":"Point"}
}