{
  "type": "Feature",
  "properties": {
    "iso:country":"US",
    "sg:address":"2704 Laurel Oak Dr",
    "sg:city":"Plant City",
    "sg:classifiers":[
        {
            "category":"Professional",
            "subcategory":"Management & Consulting",
            "type":"Services"
        }
    ],
    "sg:phone":"+1 813 757 6914",
    "sg:postcode":"33566",
    "sg:province":"FL",
    "sg:tags":[
        "business"
    ],
    "wof:name":"Fastrak Consulting",
    "wof:placetype":"venue"
},
  "geometry": {"coordinates":[-82.150352,27.984882],"type":"Point"}
}