{
  "type": "Feature",
  "properties": {
    "iso:country":"US",
    "sg:address":"3101 SW 34th Avenue Cir",
    "sg:city":"Ocala",
    "sg:classifiers":[
        {
            "category":"Shopping",
            "subcategory":"Jewelry",
            "type":"Retail Goods"
        }
    ],
    "sg:phone":"+1 352 291 2002",
    "sg:postcode":"34474",
    "sg:province":"FL",
    "wof:name":"Jewelers Bench",
    "wof:placetype":"venue"
},
  "geometry": {"coordinates":[-82.18234699999999,29.15657],"type":"Point"}
}