{
  "type": "Feature",
  "properties": {
    "iso:country":"US",
    "sg:address":"2424 NW 46th St",
    "sg:city":"Miami",
    "sg:classifiers":[
        {
            "category":"Wholesale",
            "subcategory":"Groceries",
            "type":"Manufacturing & Wholesale Goods"
        }
    ],
    "sg:phone":"+1 305 638 5161",
    "sg:postcode":"33142",
    "sg:province":"FL",
    "sg:tags":[
        "frozen",
        "foods-wholesale"
    ],
    "sg:website":"http://www.elsembrador.com",
    "wof:name":"El Sembrador",
    "wof:placetype":"venue"
},
  "geometry": {"coordinates":[-80.236942,25.81663],"type":"Point"}
}