{
  "type": "Feature",
  "properties": {
    "iso:country":"US",
    "sg:address":"5402 Beaumont Center Blvd",
    "sg:city":"Tampa",
    "sg:classifiers":[
        {
            "category":"Professional",
            "subcategory":"Employment Agencies",
            "type":"Services"
        }
    ],
    "sg:phone":"+1 813 249 9955",
    "sg:postcode":"33634",
    "sg:province":"FL",
    "sg:tags":[
        "full",
        "temporary",
        "help"
    ],
    "wof:name":"Manpower",
    "wof:placetype":"venue"
},
  "geometry": {"coordinates":[-82.547183,27.996874],"type":"Point"}
}