{
  "type": "Feature",
  "properties": {
    "iso:country":"US",
    "sg:address":"314 Brandon Town Center Mall",
    "sg:city":"Brandon",
    "sg:classifiers":[
        {
            "category":"Shopping",
            "subcategory":"Shoes",
            "type":"Retail Goods"
        }
    ],
    "sg:phone":"+1 813 653 2260",
    "sg:postcode":"33511",
    "sg:province":"FL",
    "sg:tags":[
        "store"
    ],
    "sg:website":"http://www.rackroomshoes.com",
    "wof:name":"Rack Room Shoes",
    "wof:placetype":"venue"
},
  "geometry": {"coordinates":[-82.324898,27.93549],"type":"Point"}
}