{
  "type": "Feature",
  "properties": {
    "addr:full":"7421 E Comanche Ave Tampa FL 33610",
    "addr:housenumber":"7421",
    "addr:postcode":"33610",
    "addr:street":"E Comanche Ave",
    "iso:country":"US",
    "sg:address":"7421 E Comanche Ave",
    "sg:city":"Tampa",
    "sg:classifiers":[
        {
            "category":"Real Estate",
            "subcategory":"Real Estate Agent",
            "type":"Services"
        }
    ],
    "sg:phone":"+1 813 936 9559",
    "sg:postcode":"33610",
    "sg:province":"FL",
    "wof:name":"Angel Realty",
    "wof:placetype":"venue"
},
  "geometry": {"coordinates":[-82.370902,27.998157],"type":"Point"}
}