{
  "type": "Feature",
  "properties": {
    "addr:full":"5602 S Ridgewood Ave Port Orange FL 32127",
    "addr:housenumber":"5602",
    "addr:postcode":"32127",
    "addr:street":"S Ridgewood Ave",
    "iso:country":"US",
    "sg:address":"5602 S Ridgewood Ave",
    "sg:city":"Port Orange",
    "sg:classifiers":[
        {
            "category":"Organizations",
            "subcategory":"Community Association",
            "type":"Services"
        }
    ],
    "sg:phone":"+1 386 788 1014",
    "sg:postcode":"32127",
    "sg:province":"FL",
    "sg:tags":[
        "military"
    ],
    "wof:name":"Amvets",
    "wof:placetype":"venue"
},
  "geometry": {"coordinates":[-80.974726,29.116998],"type":"Point"}
}