{
  "type": "Feature",
  "properties": {
    "addr:full":"1088 Fernlea Dr West Palm Beach FL 33417",
    "addr:housenumber":"1088",
    "addr:postcode":"33417",
    "addr:street":"Fernlea Dr",
    "iso:country":"US",
    "sg:address":"1088 Fernlea Dr",
    "sg:city":"West Palm Beach",
    "sg:classifiers":[
        {
            "category":"Professional",
            "type":"Services"
        }
    ],
    "sg:phone":"+1 561 615 0713",
    "sg:postcode":"33417",
    "sg:province":"FL",
    "wof:name":"Harold F Zimmer",
    "wof:placetype":"venue"
},
  "geometry": {"coordinates":[-80.14405499999999,26.694691],"type":"Point"}
}