{
  "type": "Feature",
  "properties": {
    "addr:full":"5533 Monterrey Rd Crestview FL 32539",
    "addr:housenumber":"5533",
    "addr:postcode":"32539",
    "addr:street":"Monterrey Rd",
    "iso:country":"US",
    "sg:address":"5533 Monterrey Rd",
    "sg:city":"Crestview",
    "sg:classifiers":[
        {
            "category":"Manufacturing",
            "subcategory":"Jewelry",
            "type":"Manufacturing & Wholesale Goods"
        }
    ],
    "sg:phone":"+1 850 689 4476",
    "sg:postcode":"32539",
    "sg:province":"FL",
    "sg:tags":[
        "precious",
        "metal",
        "mfg"
    ],
    "wof:name":"Business Mann Gold",
    "wof:placetype":"venue"
},
  "geometry": {"coordinates":[-86.53992100000001,30.774942],"type":"Point"}
}