{
  "type": "Feature",
  "properties": {
    "addr:full":"1773 Grande Pointe Blvd Orlando FL 32839",
    "addr:housenumber":"1773",
    "addr:postcode":"32839",
    "addr:street":"Grande Pointe Blvd",
    "iso:country":"US",
    "sg:address":"1773 Grande Pointe Blvd",
    "sg:city":"Orlando",
    "sg:classifiers":[
        {
            "category":"Airline",
            "type":"Transportation"
        }
    ],
    "sg:phone":"+1 407 816 3086",
    "sg:postcode":"32839",
    "sg:province":"FL",
    "sg:website":"http://www.alaskaair.com",
    "wof:name":"Alaska Airlines",
    "wof:placetype":"venue"
},
  "geometry": {"coordinates":[-81.40373200000001,28.49246],"type":"Point"}
}