{
  "type": "Feature",
  "properties": {
    "iso:country":"US",
    "sg:address":"4061 Turner Rd",
    "sg:city":"Mulberry",
    "sg:classifiers":[
        {
            "category":"Autos & Motor Vehicles",
            "subcategory":"Auto Supplies",
            "type":"Retail Goods"
        }
    ],
    "sg:phone":"+1 863 425 5646",
    "sg:postcode":"33860",
    "sg:province":"FL",
    "wof:name":"Friendly Tire & Auto",
    "wof:placetype":"venue"
},
  "geometry": {"coordinates":[-82.020955,27.912809],"type":"Point"}
}