{
  "type": "Feature",
  "properties": {
    "iso:country":"US",
    "sg:address":"3163 Cypress Grove Rd",
    "sg:city":"Grand Ridge",
    "sg:classifiers":[
        {
            "category":"Farming",
            "subcategory":"Farm",
            "type":"Manufacturing & Wholesale Goods"
        }
    ],
    "sg:phone":"+1 850 592 5957",
    "sg:postcode":"32442",
    "sg:province":"FL",
    "sg:tags":[
        "crop",
        "general"
    ],
    "wof:name":"Lh & Iola Alford Farms Inc",
    "wof:placetype":"venue"
},
  "geometry": {"coordinates":[-85.04430000000001,30.786917],"type":"Point"}
}