{
  "type": "Feature",
  "properties": {
    "iso:country":"US",
    "sg:address":"5701 Boynton Bay Cir",
    "sg:city":"Boynton Beach",
    "sg:classifiers":[
        {
            "category":"Building & Trades",
            "subcategory":"Cleaning & Sanitation",
            "type":"Services"
        }
    ],
    "sg:phone":"+1 561 731 0196",
    "sg:postcode":"33437",
    "sg:province":"FL",
    "sg:tags":[
        "janitor"
    ],
    "wof:name":"Nora Samane Janitorial",
    "wof:placetype":"venue"
},
  "geometry": {"coordinates":[-80.134084,26.521719],"type":"Point"}
}