{
  "type": "Feature",
  "properties": {
    "iso:country":"US",
    "sg:address":"695 W 17th St",
    "sg:city":"Hialeah",
    "sg:classifiers":[
        {
            "category":"Professional",
            "subcategory":"Computer Services",
            "type":"Services"
        }
    ],
    "sg:phone":"+1 305 885 9070",
    "sg:postcode":"33010",
    "sg:province":"FL",
    "sg:tags":[
        "apparel",
        "cad"
    ],
    "wof:name":"Marker Express",
    "wof:placetype":"venue"
},
  "geometry": {"coordinates":[-80.29758,25.837174],"type":"Point"}
}