{
  "type": "Feature",
  "properties": {
    "iso:country":"US",
    "sg:address":"2515 SW 27th Ave",
    "sg:city":"Miami",
    "sg:classifiers":[
        {
            "category":"Retail",
            "subcategory":"Veterinary Services",
            "type":"Services"
        }
    ],
    "sg:phone":"+1 305 859 7979",
    "sg:postcode":"33133",
    "sg:province":"FL",
    "sg:tags":[
        "veterinarian"
    ],
    "sg:website":"www.silverbluffanimalclinic.com",
    "wof:name":"Silver Bluff Animal Clinic",
    "wof:placetype":"venue"
},
  "geometry": {"coordinates":[-80.237801,25.7446],"type":"Point"}
}