{
  "type": "Feature",
  "properties": {
    "iso:country":"US",
    "sg:address":"4813 Winton Cir",
    "sg:city":"Saint Augustine",
    "sg:classifiers":[
        {
            "category":"Banks & Credit Unions",
            "subcategory":"Bank",
            "type":"Services"
        }
    ],
    "sg:phone":"+1 904 797 8742",
    "sg:postcode":"32086",
    "sg:province":"FL",
    "sg:tags":[
        "mortgage"
    ],
    "wof:name":"Peterson Mortgage Svcs",
    "wof:placetype":"venue"
},
  "geometry": {"coordinates":[-81.323429,29.803519],"type":"Point"}
}