{
  "type": "Feature",
  "properties": {
    "iso:country":"US",
    "sg:address":"753 Saxon Blvd",
    "sg:city":"Orange City",
    "sg:classifiers":[
        {
            "category":"Building & Trades",
            "subcategory":"Construction",
            "type":"Services"
        }
    ],
    "sg:phone":"+1 386 774 7370",
    "sg:postcode":"32763",
    "sg:province":"FL",
    "sg:tags":[
        "residential"
    ],
    "wof:name":"Contravest Construction",
    "wof:placetype":"venue"
},
  "geometry": {"coordinates":[-81.297077,28.912048],"type":"Point"}
}