{
  "type": "Feature",
  "properties": {
    "iso:country":"US",
    "sg:address":"1954 S Orange Ave",
    "sg:city":"Orlando",
    "sg:classifiers":[
        {
            "category":"Wholesale",
            "subcategory":"Auto Parts",
            "type":"Manufacturing & Wholesale Goods"
        }
    ],
    "sg:phone":"+1 407 859 9225",
    "sg:postcode":"32806",
    "sg:province":"FL",
    "sg:tags":[
        "automobile",
        "supply"
    ],
    "wof:name":"SMD Automotive",
    "wof:placetype":"venue"
},
  "geometry": {"coordinates":[-81.376439,28.51983],"type":"Point"}
}