{
  "type": "Feature",
  "properties": {
    "iso:country":"US",
    "sg:address":"432 Sugar Mill Rd",
    "sg:city":"Oviedo",
    "sg:classifiers":[
        {
            "category":"Personal",
            "type":"Services"
        }
    ],
    "sg:phone":"+1 407 365 1925",
    "sg:postcode":"32765",
    "sg:province":"FL",
    "sg:tags":[
        "miscellaneous"
    ],
    "wof:name":"Rhonda Kamper Svc",
    "wof:placetype":"venue"
},
  "geometry": {"coordinates":[-81.224414,28.662886],"type":"Point"}
}