{
  "type": "Feature",
  "properties": {
    "iso:country":"US",
    "sg:address":"6224 Arlington Rd",
    "sg:city":"Jacksonville",
    "sg:classifiers":[
        {
            "category":"Personal",
            "subcategory":"Beauty Salon",
            "type":"Services"
        }
    ],
    "sg:phone":"+1 904 743 5181",
    "sg:postcode":"32211",
    "sg:province":"FL",
    "wof:name":"Running Water Natrl Hair Care",
    "wof:placetype":"venue"
},
  "geometry": {"coordinates":[-81.59477,30.333519],"type":"Point"}
}