{
  "type": "Feature",
  "properties": {
    "iso:country":"US",
    "sg:address":"28129 Co Rd 561",
    "sg:city":"Tavares",
    "sg:classifiers":[
        {
            "category":"Government",
            "subcategory":"Office",
            "type":"Public Place"
        }
    ],
    "sg:phone":"+1 352 742 6165",
    "sg:postcode":"34705",
    "sg:province":"FL",
    "sg:tags":[
        "state",
        "program"
    ],
    "wof:name":"Driver License Office",
    "wof:placetype":"venue"
},
  "geometry": {"coordinates":[-81.736876,28.757693],"type":"Point"}
}