{
  "type": "Feature",
  "properties": {
    "iso:country":"US",
    "sg:address":"3865 Crosley Ave",
    "sg:city":"St Cloud",
    "sg:classifiers":[
        {
            "category":"Building & Trades",
            "subcategory":"Landscaping Services",
            "type":"Services"
        }
    ],
    "sg:phone":"+1 407 957 8972",
    "sg:postcode":"34772",
    "sg:province":"FL",
    "sg:tags":[
        "lawn",
        "maintenance",
        "grounds"
    ],
    "wof:name":"Terry Miller Co",
    "wof:placetype":"venue"
},
  "geometry": {"coordinates":[-81.274085,28.179403],"type":"Point"}
}