{
  "type": "Feature",
  "properties": {
    "addr:full":"204 SE 16th Pl Cape Coral FL 33904",
    "addr:housenumber":"204",
    "addr:postcode":"33904",
    "addr:street":"Se 16Th Pl",
    "iso:country":"US",
    "sg:address":"204 SE 16th Pl",
    "sg:city":"Cape Coral",
    "sg:classifiers":[
        {
            "category":"Health Services",
            "subcategory":"Doctor",
            "type":"Services"
        }
    ],
    "sg:phone":"+1 239 573 2001",
    "sg:postcode":"33904",
    "sg:province":"FL",
    "wof:name":"MacKoul David A MD",
    "wof:placetype":"venue"
},
  "geometry": {"coordinates":[-81.939981,26.648498],"type":"Point"}
}