{
  "type": "Feature",
  "properties": {
    "iso:country":"US",
    "sg:address":"214 Airport Rd",
    "sg:city":"Panama City",
    "sg:classifiers":[
        {
            "category":"Retail",
            "subcategory":"Funeral Services",
            "type":"Services"
        }
    ],
    "sg:phone":"+1 850 785 5272",
    "sg:postcode":"32405",
    "sg:province":"FL",
    "sg:tags":[
        "director"
    ],
    "wof:name":"Wilson Funeral Home",
    "wof:placetype":"venue"
},
  "geometry": {"coordinates":[-85.663158,30.178912],"type":"Point"}
}