{
  "type": "Feature",
  "properties": {
    "iso:country":"US",
    "sg:address":"11750 SW 18th St",
    "sg:city":"Miami",
    "sg:classifiers":[
        {
            "category":"Shopping",
            "subcategory":"Gifts & Souvenirs",
            "type":"Retail Goods"
        }
    ],
    "sg:phone":"+1 305 221 0338",
    "sg:postcode":"33175",
    "sg:province":"FL",
    "wof:name":"All Occasions By Our Hands Cor",
    "wof:placetype":"venue"
},
  "geometry": {"coordinates":[-80.386999,25.751727],"type":"Point"}
}