{
  "type": "Feature",
  "properties": {
    "iso:country":"US",
    "sg:address":"2801 E Irlo Bronson Memorial Hwy",
    "sg:city":"Kissimmee",
    "sg:classifiers":[
        {
            "category":"Shopping",
            "subcategory":"Gifts & Souvenirs",
            "type":"Retail Goods"
        }
    ],
    "sg:phone":"+1 407 925 1090",
    "sg:postcode":"34744",
    "sg:province":"FL",
    "wof:name":"Heaven On Earth Gifts & Collec",
    "wof:placetype":"venue"
},
  "geometry": {"coordinates":[-81.32754,28.26071],"type":"Point"}
}