{
  "type": "Feature",
  "properties": {
    "iso:country":"US",
    "sg:address":"135 San Marco Dr",
    "sg:city":"Venice",
    "sg:classifiers":[
        {
            "category":"Health Services",
            "subcategory":"Doctor",
            "type":"Services"
        }
    ],
    "sg:phone":"+1 941 484 6836",
    "sg:postcode":"34285",
    "sg:province":"FL",
    "sg:tags":[
        "medical"
    ],
    "wof:name":"F Nicholas Gahhos MD",
    "wof:placetype":"venue"
},
  "geometry": {"coordinates":[-82.446425,27.088849],"type":"Point"}
}