{
  "type": "Feature",
  "properties": {
    "addr:full":"5130 Eisenhower Blvd N Tampa FL 33634",
    "addr:housenumber":"5130",
    "addr:postcode":"33634",
    "addr:street":"Eisenhower Blvd N",
    "iso:country":"US",
    "sg:address":"5130 Eisenhower Blvd N",
    "sg:city":"Tampa",
    "sg:classifiers":[
        {
            "category":"Real Estate",
            "subcategory":"Real Estate Agent",
            "type":"Services"
        }
    ],
    "sg:phone":"+1 813 290 7717",
    "sg:postcode":"33634",
    "sg:province":"FL",
    "sg:tags":[
        "support"
    ],
    "wof:name":"Trammell Crow Co",
    "wof:placetype":"venue"
},
  "geometry": {"coordinates":[-82.545439,27.991477],"type":"Point"}
}