{
  "type": "Feature",
  "properties": {
    "iso:country":"US",
    "sg:address":"330 62th Ave N",
    "sg:city":"St Petersburg",
    "sg:classifiers":[
        {
            "category":"Retail",
            "subcategory":"Laundry & Dry Cleaning",
            "type":"Services"
        }
    ],
    "sg:phone":"+1 727 528 4850",
    "sg:postcode":"33702",
    "sg:province":"FL",
    "sg:tags":[
        "cleaners"
    ],
    "wof:name":"Spirit CLEANERS",
    "wof:placetype":"venue"
},
  "geometry": {"coordinates":[-82.637829,27.828406],"type":"Point"}
}