{
  "type": "Feature",
  "properties": {
    "iso:country":"US",
    "sg:address":"4443 Hollywood Blvd",
    "sg:city":"Hollywood",
    "sg:classifiers":[
        {
            "category":"Building & Trades",
            "subcategory":"Construction",
            "type":"Services"
        }
    ],
    "sg:phone":"+1 954 964 1123",
    "sg:postcode":"33021",
    "sg:province":"FL",
    "sg:tags":[
        "planning",
        "remodeling",
        "kitchen"
    ],
    "wof:name":"City Home Improvement",
    "wof:placetype":"venue"
},
  "geometry": {"coordinates":[-80.18909600000001,26.010595],"type":"Point"}
}