{
  "type": "Feature",
  "properties": {
    "addr:full":"1615 NW 13th St Gainesville FL 32609",
    "addr:housenumber":"1615",
    "addr:postcode":"32609",
    "addr:street":"Nw 13Th St",
    "iso:country":"US",
    "sg:address":"1615 NW 13th St",
    "sg:city":"Gainesville",
    "sg:classifiers":[
        {
            "category":"Wholesale",
            "subcategory":"Medical Equipment & Supplies",
            "type":"Manufacturing & Wholesale Goods"
        },
        {
            "category":"Shopping",
            "subcategory":"Pharmacy",
            "type":"Retail Goods"
        }
    ],
    "sg:phone":"+1 352 380 9039",
    "sg:postcode":"32609",
    "sg:province":"FL",
    "sg:tags":[
        "home",
        "care",
        "health",
        "first",
        "aid"
    ],
    "sg:website":"http://www.walgreens.com",
    "wof:name":"Walgreen Drug Stores",
    "wof:placetype":"venue"
},
  "geometry": {"coordinates":[-82.33910400000001,29.66681],"type":"Point"}
}