{
  "type": "Feature",
  "properties": {
    "addr:full":"6305 Sanson Dr Apopka FL 32712",
    "addr:housenumber":"6305",
    "addr:postcode":"32712",
    "addr:street":"Sanson Dr",
    "iso:country":"US",
    "sg:address":"6305 Sanson Dr",
    "sg:city":"Apopka",
    "sg:classifiers":[
        {
            "category":"Building & Trades",
            "subcategory":"Construction",
            "type":"Services"
        }
    ],
    "sg:phone":"+1 407 461 5935",
    "sg:postcode":"32712",
    "sg:province":"FL",
    "sg:tags":[
        "carpentry",
        "contractor"
    ],
    "wof:name":"Lws Handyman Services",
    "wof:placetype":"venue"
},
  "geometry": {"coordinates":[-81.518715,28.768661],"type":"Point"}
}