{
  "type": "Feature",
  "properties": {
    "addr:full":"13850 Stirling Rd Fort Lauderdale FL 33330",
    "addr:housenumber":"13850",
    "addr:postcode":"33330",
    "addr:street":"Stirling Rd",
    "iso:country":"US",
    "sg:address":"13850 Stirling Rd",
    "sg:city":"Fort Lauderdale",
    "sg:classifiers":[
        {
            "category":"Travel",
            "subcategory":"Hotels & Motels",
            "type":"Entertainment"
        }
    ],
    "sg:phone":"+1 954 252 3380",
    "sg:postcode":"33330",
    "sg:province":"FL",
    "wof:name":"Suez Ocean Resort",
    "wof:placetype":"venue"
},
  "geometry": {"coordinates":[-80.332958,26.04406],"type":"Point"}
}