{
  "type": "Feature",
  "properties": {
    "iso:country":"US",
    "sg:address":"12610 World Plaza Ln Ste 1",
    "sg:city":"Fort Myers",
    "sg:classifiers":[
        {
            "category":"Banks & Credit Unions",
            "subcategory":"Financial Services",
            "type":"Services"
        }
    ],
    "sg:phone":"+1 239 454 4499",
    "sg:postcode":"33907",
    "sg:province":"FL",
    "sg:tags":[
        "broker",
        "mortgage"
    ],
    "wof:name":"Palm Mortgage Group",
    "wof:placetype":"venue"
},
  "geometry": {"coordinates":[-81.87872900000001,26.560187],"type":"Point"}
}