{
  "type": "Feature",
  "properties": {
    "iso:country":"US",
    "sg:address":"10310 Cone Grove Rd",
    "sg:city":"Riverview",
    "sg:classifiers":[
        {
            "category":"Farming",
            "subcategory":"Fish & Marine Products",
            "type":"Manufacturing & Wholesale Goods"
        }
    ],
    "sg:phone":"+1 813 677 6427",
    "sg:postcode":"33578",
    "sg:province":"FL",
    "sg:tags":[
        "catching"
    ],
    "wof:name":"Florida Aqua Scape",
    "wof:placetype":"venue"
},
  "geometry": {"coordinates":[-82.334138,27.846267],"type":"Point"}
}