{
  "type": "Feature",
  "properties": {
    "addr:full":"1223 N Mills Ave Orlando FL 32803",
    "addr:housenumber":"1223",
    "addr:postcode":"32803",
    "addr:street":"N Mills Ave",
    "iso:country":"US",
    "sg:address":"1223 N Mills Ave",
    "sg:city":"Orlando",
    "sg:classifiers":[
        {
            "category":"Shopping",
            "subcategory":"Clothing, Apparel, & Fashions",
            "type":"Retail Goods"
        }
    ],
    "sg:phone":"+1 407 898 4123",
    "sg:postcode":"32803",
    "sg:province":"FL",
    "sg:tags":[
        "personal"
    ],
    "wof:name":"Nancys Alterations",
    "wof:placetype":"venue"
},
  "geometry": {"coordinates":[-81.364373,28.562053],"type":"Point"}
}