{
  "type": "Feature",
  "properties": {
    "iso:country":"US",
    "sg:address":"1827 NW Pine Lake Dr",
    "sg:city":"Stuart",
    "sg:classifiers":[
        {
            "category":"Sports & Exercise",
            "subcategory":"Golf",
            "type":"Entertainment"
        }
    ],
    "sg:phone":"+1 772 692 0346",
    "sg:postcode":"34994",
    "sg:province":"FL",
    "sg:tags":[
        "club",
        "practice",
        "membership",
        "course",
        "range",
        "public"
    ],
    "sg:website":"http://www.golflink.com/golf-courses/course.aspx?course=349345",
    "wof:name":"Pine Lakes Golf Club",
    "wof:placetype":"venue"
},
  "geometry": {"coordinates":[-80.275992,27.22744],"type":"Point"}
}