{
  "type": "Feature",
  "properties": {
    "iso:country":"US",
    "sg:address":"430 Summerhaven Dr",
    "sg:city":"Debary",
    "sg:classifiers":[
        {
            "category":"Personal",
            "subcategory":"Beauty Salon",
            "type":"Services"
        }
    ],
    "sg:phone":"+1 386 668 6789",
    "sg:postcode":"32713",
    "sg:province":"FL",
    "sg:tags":[
        "hair",
        "stylist"
    ],
    "wof:name":"Bella Vie Hair Salon",
    "wof:placetype":"venue"
},
  "geometry": {"coordinates":[-81.28489399999999,28.898651],"type":"Point"}
}