{
  "type": "Feature",
  "properties": {
    "addr:full":"1270 31st St SW Naples FL 34117",
    "addr:housenumber":"1270",
    "addr:postcode":"34117",
    "addr:street":"31St St Sw",
    "iso:country":"US",
    "sg:address":"1270 31st St SW",
    "sg:city":"Naples",
    "sg:classifiers":[
        {
            "category":"Building & Trades",
            "subcategory":"Construction",
            "type":"Services"
        }
    ],
    "sg:phone":"+1 239 353 4411",
    "sg:postcode":"34117",
    "sg:province":"FL",
    "sg:tags":[
        "grading",
        "contractor"
    ],
    "wof:name":"Holland Kendall Inc",
    "wof:placetype":"venue"
},
  "geometry": {"coordinates":[-81.66869699999999,26.207682],"type":"Point"}
}