{
  "type": "Feature",
  "properties": {
    "iso:country":"US",
    "sg:address":"20 N Charles Richard Beall Blvd",
    "sg:city":"Debary",
    "sg:classifiers":[
        {
            "category":"Restaurant",
            "type":"Food & Drink"
        }
    ],
    "sg:phone":"+1 386 668 0104",
    "sg:postcode":"32713",
    "sg:province":"FL",
    "wof:name":"Debarry Diner",
    "wof:placetype":"venue"
},
  "geometry": {"coordinates":[-81.306245,28.892789],"type":"Point"}
}