{
  "type": "Feature",
  "properties": {
    "addr:full":"711 Hensel Hill Dr E Daytona Beach FL 32127",
    "addr:housenumber":"711",
    "addr:postcode":"32127",
    "addr:street":"Hensel Hill Dr E",
    "iso:country":"US",
    "sg:address":"711 Hensel Hill Dr E",
    "sg:city":"Daytona Beach",
    "sg:classifiers":[
        {
            "category":"Professional",
            "type":"Services"
        }
    ],
    "sg:phone":"+1 386 756 6884",
    "sg:postcode":"32127",
    "sg:province":"FL",
    "wof:name":"Ronald L Peretta Ink",
    "wof:placetype":"venue"
},
  "geometry": {"coordinates":[-81.007132,29.104087],"type":"Point"}
}