{
  "type": "Feature",
  "properties": {
    "addr:full":"4717 Swift Rd Sarasota FL 34231",
    "addr:housenumber":"4717",
    "addr:postcode":"34231",
    "addr:street":"Swift Rd",
    "iso:country":"US",
    "sg:address":"4717 Swift Rd",
    "sg:city":"Sarasota",
    "sg:classifiers":[
        {
            "category":"Health Services",
            "subcategory":"Podiatrist",
            "type":"Services"
        }
    ],
    "sg:phone":"+1 941 929 1234",
    "sg:postcode":"34231",
    "sg:province":"FL",
    "wof:name":"Accredited Podiatry",
    "wof:placetype":"venue"
},
  "geometry": {"coordinates":[-82.514096,27.284218],"type":"Point"}
}