{
  "type": "Feature",
  "properties": {
    "iso:country":"US",
    "sg:address":"1665 W 68th St",
    "sg:city":"Hialeah",
    "sg:classifiers":[
        {
            "category":"Shopping",
            "subcategory":"Discount & Variety Stores",
            "type":"Retail Goods"
        }
    ],
    "sg:phone":"+1 305 825 2837",
    "sg:postcode":"33014",
    "sg:province":"FL",
    "wof:name":"Lucy Dollar Store Discount",
    "wof:placetype":"venue"
},
  "geometry": {"coordinates":[-80.317497,25.884643],"type":"Point"}
}