{
  "type": "Feature",
  "properties": {
    "iso:country":"US",
    "sg:address":"38017 Live Oak Ave",
    "sg:city":"Dade City",
    "sg:classifiers":[
        {
            "category":"Government",
            "subcategory":"Office",
            "type":"Public Place"
        }
    ],
    "sg:phone":"+1 352 567 5655",
    "sg:postcode":"33523",
    "sg:province":"FL",
    "sg:tags":[
        "federal",
        "security"
    ],
    "wof:name":"Florida Army National Guard",
    "wof:placetype":"venue"
},
  "geometry": {"coordinates":[-82.187595,28.365246],"type":"Point"}
}