{
  "type": "Feature",
  "properties": {
    "addr:full":"15255 NW 46th Ln Chiefland FL 32626",
    "addr:housenumber":"15255",
    "addr:postcode":"32626",
    "addr:street":"Nw 46Th Ln",
    "iso:country":"US",
    "sg:address":"15255 NW 46th Ln",
    "sg:city":"Chiefland",
    "sg:classifiers":[
        {
            "category":"Travel",
            "subcategory":"Hotels & Motels",
            "type":"Entertainment"
        }
    ],
    "sg:phone":"+1 352 493 0014",
    "sg:postcode":"32626",
    "sg:province":"FL",
    "sg:tags":[
        "operation",
        "camp",
        "drinking",
        "pl"
    ],
    "wof:name":"Treasure Camp",
    "wof:placetype":"venue"
},
  "geometry": {"coordinates":[-83.023398,29.397023],"type":"Point"}
}