{
  "type": "Feature",
  "properties": {
    "addr:full":"1306 N John Young Pkwy Kissimmee FL 34741",
    "addr:housenumber":"1306",
    "addr:postcode":"34741",
    "addr:street":"N John Young Pkwy",
    "iso:country":"US",
    "sg:address":"1306 N John Young Pkwy",
    "sg:city":"Kissimmee",
    "sg:classifiers":[
        {
            "category":"Building & Trades",
            "subcategory":"Equipment Rental",
            "type":"Services"
        }
    ],
    "sg:phone":"+1 407 847 8550",
    "sg:postcode":"34741",
    "sg:province":"FL",
    "sg:tags":[
        "rent",
        "furniture"
    ],
    "wof:name":"Aaarons",
    "wof:placetype":"venue"
},
  "geometry": {"coordinates":[-81.41599100000001,28.304409],"type":"Point"}
}