{
  "type": "Feature",
  "properties": {
    "iso:country":"US",
    "sg:address":"8574 Gunn Hwy",
    "sg:city":"Odessa",
    "sg:classifiers":[
        {
            "category":"Restaurant",
            "type":"Food & Drink"
        }
    ],
    "sg:phone":"+1 813 920 7994",
    "sg:postcode":"33556",
    "sg:province":"FL",
    "sg:tags":[
        "eating"
    ],
    "wof:name":"Subway",
    "wof:placetype":"venue"
},
  "geometry": {"coordinates":[-82.578986,28.090918],"type":"Point"}
}