{
  "type": "Feature",
  "properties": {
    "addr:full":"5940 Robins Rd Lakeland FL 33810",
    "addr:housenumber":"5940",
    "addr:postcode":"33810",
    "addr:street":"Robins Rd",
    "iso:country":"US",
    "sg:address":"5940 Robins Rd",
    "sg:city":"Lakeland",
    "sg:classifiers":[
        {
            "category":"Building & Trades",
            "subcategory":"Construction",
            "type":"Services"
        }
    ],
    "sg:phone":"+1 863 853 3138",
    "sg:postcode":"33810",
    "sg:province":"FL",
    "sg:tags":[
        "heavy"
    ],
    "wof:name":"P W S",
    "wof:placetype":"venue"
},
  "geometry": {"coordinates":[-82.037728,28.120046],"type":"Point"}
}