{
  "type": "Feature",
  "properties": {
    "iso:country":"US",
    "sg:address":"13121 W Sunrise Blvd",
    "sg:city":"Sunrise",
    "sg:classifiers":[
        {
            "category":"Home & Garden",
            "subcategory":"Home Furnishings",
            "type":"Retail Goods"
        },
        {
            "category":"Wholesale",
            "subcategory":"Home Furnishings",
            "type":"Manufacturing & Wholesale Goods"
        }
    ],
    "sg:phone":"+1 954 838 7082",
    "sg:postcode":"33323",
    "sg:province":"FL",
    "sg:tags":[
        "fixture",
        "lamp",
        "fixtures-wholesale",
        "lighting",
        "shade",
        "manufacturer"
    ],
    "sg:website":"http://www.thelightingoutlet.net",
    "wof:name":"Lighting Outlet The",
    "wof:placetype":"venue"
},
  "geometry": {"coordinates":[-80.32613499999999,26.145642],"type":"Point"}
}