{
  "type": "Feature",
  "properties": {
    "addr:full":"7020 Beracasa Way Boca Raton FL 33433",
    "addr:housenumber":"7020",
    "addr:postcode":"33433",
    "addr:street":"Beracasa Way",
    "iso:country":"US",
    "sg:address":"7020 Beracasa Way",
    "sg:city":"Boca Raton",
    "sg:classifiers":[
        {
            "category":"Restaurant",
            "type":"Food & Drink"
        }
    ],
    "sg:menulink":"http://www.allmenus.com/fl/boca-raton/105842-boston-market/menu/",
    "sg:phone":"+1 561 392 2795",
    "sg:postcode":"33433",
    "sg:province":"FL",
    "sg:tags":[
        "barbecue",
        "american",
        "soup"
    ],
    "wof:name":"Boston Market",
    "wof:placetype":"venue"
},
  "geometry": {"coordinates":[-80.15594,26.352291],"type":"Point"}
}