{
  "type": "Feature",
  "properties": {
    "iso:country":"US",
    "sg:address":"3997 1st Ave",
    "sg:city":"Fernandina Beach",
    "sg:classifiers":[
        {
            "category":"Recreation",
            "type":"Entertainment"
        }
    ],
    "sg:phone":"+1 904 753 2388",
    "sg:postcode":"32034",
    "sg:province":"FL",
    "sg:tags":[
        "charter",
        "boat"
    ],
    "wof:name":"Voyager Ventures Inc",
    "wof:placetype":"venue"
},
  "geometry": {"coordinates":[-81.443298,30.611823],"type":"Point"}
}