{
  "type": "Feature",
  "properties": {
    "addr:full":"6644 Celeste Ln New Port Richey FL 34653",
    "addr:housenumber":"6644",
    "addr:postcode":"34653",
    "addr:street":"Celeste Ln",
    "iso:country":"US",
    "sg:address":"6644 Celeste Ln",
    "sg:city":"New Port Richey",
    "sg:classifiers":[
        {
            "category":"Shopping",
            "subcategory":"Books",
            "type":"Retail Goods"
        }
    ],
    "sg:phone":"+1 727 842 6639",
    "sg:postcode":"34653",
    "sg:province":"FL",
    "wof:name":"Cozy Corner Books",
    "wof:placetype":"venue"
},
  "geometry": {"coordinates":[-82.70528299999999,28.262883],"type":"Point"}
}