{
  "type": "Feature",
  "properties": {
    "iso:country":"US",
    "sg:address":"409 Big Tree Rd",
    "sg:city":"Daytona Beach",
    "sg:classifiers":[
        {
            "category":"Freight",
            "type":"Transportation"
        }
    ],
    "sg:phone":"+1 386 767 0430",
    "sg:postcode":"32119",
    "sg:province":"FL",
    "sg:tags":[
        "datum",
        "special"
    ],
    "wof:name":"File Tech LLC",
    "wof:placetype":"venue"
},
  "geometry": {"coordinates":[-81.006612,29.172912],"type":"Point"}
}