{
  "type": "Feature",
  "properties": {
    "iso:country":"US",
    "sg:address":"1807 Windsor Oak Dr",
    "sg:city":"Apopka",
    "sg:classifiers":[
        {
            "category":"Building & Trades",
            "subcategory":"Construction",
            "type":"Services"
        }
    ],
    "sg:phone":"+1 407 880 5859",
    "sg:postcode":"32703",
    "sg:province":"FL",
    "sg:tags":[
        "contractor"
    ],
    "wof:name":"Charles McDaniel Pools",
    "wof:placetype":"venue"
},
  "geometry": {"coordinates":[-81.474625,28.646855],"type":"Point"}
}