{
  "type": "Feature",
  "properties": {
    "iso:country":"US",
    "sg:address":"564 Jim Garrett Rd",
    "sg:city":"Defuniak Springs",
    "sg:classifiers":[
        {
            "category":"Retail",
            "subcategory":"Repair Shop",
            "type":"Services"
        }
    ],
    "sg:phone":"+1 850 892 2057",
    "sg:postcode":"32433",
    "sg:province":"FL",
    "sg:tags":[
        "upholsterer"
    ],
    "wof:name":"G T Custom Upholstery",
    "wof:placetype":"venue"
},
  "geometry": {"coordinates":[-86.0685,30.771262],"type":"Point"}
}