{
  "type": "Feature",
  "properties": {
    "iso:country":"US",
    "sg:address":"3040 Hoyt Ave",
    "sg:city":"Clearwater",
    "sg:classifiers":[
        {
            "category":"Utilities",
            "subcategory":"Refuse",
            "type":"Services"
        },
        {
            "category":"Transit Center",
            "subcategory":"Freight",
            "type":"Transportation"
        },
        {
            "category":"Utilities",
            "subcategory":"Recycling",
            "type":"Services"
        }
    ],
    "sg:phone":"+1 727 458 7487",
    "sg:postcode":"33759",
    "sg:province":"FL",
    "sg:tags":[
        "container",
        "dumpster",
        "garbage",
        "trucking-light",
        "hauling",
        "removal",
        "rubbish",
        "trash"
    ],
    "sg:website":"http://www.ezfillhauling.com",
    "wof:name":"E Z Fill Hauling",
    "wof:placetype":"venue"
},
  "geometry": {"coordinates":[-82.710886,27.97084],"type":"Point"}
}