{
  "type": "Feature",
  "properties": {
    "iso:country":"US",
    "sg:address":"161 Crandon Blvd",
    "sg:city":"Key Biscayne",
    "sg:classifiers":[
        {
            "category":"Real Estate",
            "subcategory":"Real Estate Operator",
            "type":"Services"
        }
    ],
    "sg:phone":"+1 305 220 3020",
    "sg:postcode":"33149",
    "sg:province":"FL",
    "sg:tags":[
        "building",
        "nonresidential"
    ],
    "wof:name":"Bird Gate Inc",
    "wof:placetype":"venue"
},
  "geometry": {"coordinates":[-80.16176900000001,25.699969],"type":"Point"}
}