{
  "type": "Feature",
  "properties": {
    "iso:country":"US",
    "sg:address":"5001 Hiatus Rd",
    "sg:city":"Fort Lauderdale",
    "sg:classifiers":[
        {
            "category":"Manufacturing",
            "subcategory":"Electronics",
            "type":"Manufacturing & Wholesale Goods"
        }
    ],
    "sg:phone":"+1 954 578 1447",
    "sg:postcode":"33351",
    "sg:province":"FL",
    "sg:tags":[
        "repair",
        "assembly",
        "mfg",
        "board",
        "circuit",
        "electronic"
    ],
    "wof:name":"Viatech Industries",
    "wof:placetype":"venue"
},
  "geometry": {"coordinates":[-80.289261,26.190081],"type":"Point"}
}