{
  "type": "Feature",
  "properties": {
    "iso:country":"US",
    "sg:address":"8292 NW 14th St",
    "sg:city":"Miami",
    "sg:classifiers":[
        {
            "category":"Wholesale",
            "subcategory":"Construction Materials",
            "type":"Manufacturing & Wholesale Goods"
        }
    ],
    "sg:phone":"+1 305 933 4164",
    "sg:postcode":"33126",
    "sg:province":"FL",
    "sg:tags":[
        "interior",
        "tile",
        "design",
        "ceramic",
        "export"
    ],
    "wof:name":"Mnid",
    "wof:placetype":"venue"
},
  "geometry": {"coordinates":[-80.32750799999999,25.786192],"type":"Point"}
}