{
  "type": "Feature",
  "properties": {
    "iso:country":"US",
    "sg:address":"1457 W Baya Ave",
    "sg:city":"Lake City",
    "sg:classifiers":[
        {
            "category":"Personal",
            "subcategory":"Beauty Salon",
            "type":"Services"
        }
    ],
    "sg:phone":"+1 386 752 8036",
    "sg:postcode":"32025",
    "sg:province":"FL",
    "wof:name":"Ultimate Illusions",
    "wof:placetype":"venue"
},
  "geometry": {"coordinates":[-82.648797,30.187428],"type":"Point"}
}