{
  "type": "Feature",
  "properties": {
    "iso:country":"US",
    "sg:address":"900 Orchid Springs Dr",
    "sg:city":"Winter Haven",
    "sg:classifiers":[
        {
            "category":"Building & Trades",
            "subcategory":"Construction",
            "type":"Services"
        }
    ],
    "sg:phone":"+1 863 324 9112",
    "sg:postcode":"33884",
    "sg:province":"FL",
    "sg:tags":[
        "general",
        "contractor"
    ],
    "wof:name":"Jeffrey M Ryan Construction",
    "wof:placetype":"venue"
},
  "geometry": {"coordinates":[-81.681928,28.007933],"type":"Point"}
}