{
  "type": "Feature",
  "properties": {
    "addr:full":"7409 Osage Dr Hudson FL 34667",
    "addr:housenumber":"7409",
    "addr:postcode":"34667",
    "addr:street":"Osage Dr",
    "iso:country":"US",
    "sg:address":"7409 Osage Dr",
    "sg:city":"Hudson",
    "sg:classifiers":[
        {
            "category":"Building & Trades",
            "subcategory":"Construction",
            "type":"Services"
        }
    ],
    "sg:phone":"+1 727 819 9473",
    "sg:postcode":"34667",
    "sg:province":"FL",
    "sg:tags":[
        "restoration",
        "cleaning",
        "patio",
        "deck"
    ],
    "wof:name":"Mc Kissack Pressure Cleaning",
    "wof:placetype":"venue"
},
  "geometry": {"coordinates":[-82.691372,28.337027],"type":"Point"}
}