{
  "type": "Feature",
  "properties": {
    "addr:full":"5830 Painted Leaf Ln Naples FL 34116",
    "addr:housenumber":"5830",
    "addr:postcode":"34116",
    "addr:street":"Painted Leaf Ln",
    "iso:country":"US",
    "sg:address":"5830 Painted Leaf Ln",
    "sg:city":"Naples",
    "sg:classifiers":[
        {
            "category":"Recreation",
            "subcategory":"Boat Charter",
            "type":"Entertainment"
        }
    ],
    "sg:phone":"+1 239 262 7882",
    "sg:postcode":"34116",
    "sg:province":"FL",
    "sg:tags":[
        "boat-rental"
    ],
    "wof:name":"Gulf Shore Fisheries",
    "wof:placetype":"venue"
},
  "geometry": {"coordinates":[-81.72336900000001,26.178052],"type":"Point"}
}