{
  "type": "Feature",
  "properties": {
    "iso:country":"US",
    "sg:address":"115 New Smyrna Blvd",
    "sg:city":"Osteen",
    "sg:classifiers":[
        {
            "category":"Wholesale",
            "subcategory":"Farm Supplies",
            "type":"Manufacturing & Wholesale Goods"
        }
    ],
    "sg:phone":"+1 407 322 8383",
    "sg:postcode":"32764",
    "sg:province":"FL",
    "sg:tags":[
        "feed"
    ],
    "wof:name":"Osteen Feed",
    "wof:placetype":"venue"
},
  "geometry": {"coordinates":[-81.161952,28.845655],"type":"Point"}
}