{
  "type": "Feature",
  "properties": {
    "iso:country":"US",
    "sg:address":"3032 NW 72nd Ave",
    "sg:city":"Miami",
    "sg:classifiers":[
        {
            "category":"Wholesale",
            "subcategory":"Durable Goods & Equipment",
            "type":"Manufacturing & Wholesale Goods"
        }
    ],
    "sg:phone":"+1 305 463 7150",
    "sg:postcode":"33122",
    "sg:province":"FL",
    "sg:tags":[
        "importer"
    ],
    "wof:name":"Flower Central Inc",
    "wof:placetype":"venue"
},
  "geometry": {"coordinates":[-80.313141,25.802027],"type":"Point"}
}