{
  "type": "Feature",
  "properties": {
    "iso:country":"US",
    "sg:address":"695 SW 11th St",
    "sg:city":"Miami",
    "sg:classifiers":[
        {
            "category":"Building & Trades",
            "subcategory":"Construction",
            "type":"Services"
        }
    ],
    "sg:phone":"+1 786 314 5522",
    "sg:postcode":"33129",
    "sg:province":"FL",
    "sg:tags":[
        "painter"
    ],
    "wof:name":"Shamuel Painting Svc Inc",
    "wof:placetype":"venue"
},
  "geometry": {"coordinates":[-80.20542500000001,25.763186],"type":"Point"}
}