{
  "type": "Feature",
  "properties": {
    "addr:full":"8701 World Center Dr Orlando FL 32821",
    "addr:housenumber":"8701",
    "addr:postcode":"32821",
    "addr:street":"World Center Dr",
    "iso:country":"US",
    "sg:address":"8701 World Center Dr",
    "sg:city":"Orlando",
    "sg:classifiers":[
        {
            "category":"Communications",
            "subcategory":"Television Station",
            "type":"Services"
        }
    ],
    "sg:phone":"+1 407 238 7762",
    "sg:postcode":"32821",
    "sg:province":"FL",
    "sg:tags":[
        "broadcast"
    ],
    "wof:name":"T V 62",
    "wof:placetype":"venue"
},
  "geometry": {"coordinates":[-81.508568,28.3599],"type":"Point"}
}