{
  "type": "Feature",
  "properties": {
    "addr:full":"2451 US Hwy 98 Lakeland FL 33805",
    "addr:housenumber":"2451",
    "addr:postcode":"33805",
    "addr:street":"Us Hwy 98",
    "iso:country":"US",
    "sg:address":"2451 US Hwy 98",
    "sg:city":"Lakeland",
    "sg:classifiers":[
        {
            "category":"Personal",
            "subcategory":"Beauty Salon",
            "type":"Services"
        }
    ],
    "sg:phone":"+1 863 686 8386",
    "sg:postcode":"33805",
    "sg:province":"FL",
    "sg:tags":[
        "manicuring"
    ],
    "wof:name":"Top Nails",
    "wof:placetype":"venue"
},
  "geometry": {"coordinates":[-81.960233,28.075608],"type":"Point"}
}