{
  "type": "Feature",
  "properties": {
    "iso:country":"US",
    "sg:address":"9710 NW 91st Ct",
    "sg:city":"Medley",
    "sg:classifiers":[
        {
            "category":"Wholesale",
            "subcategory":"Construction Materials",
            "type":"Manufacturing & Wholesale Goods"
        },
        {
            "category":"Wholesale",
            "subcategory":"Durable Goods & Equipment",
            "type":"Manufacturing & Wholesale Goods"
        }
    ],
    "sg:phone":"+1 305 885 6299",
    "sg:postcode":"33178",
    "sg:province":"FL",
    "sg:tags":[
        "building",
        "import",
        "exporter",
        "export"
    ],
    "wof:name":"International Building Prods",
    "wof:placetype":"venue"
},
  "geometry": {"coordinates":[-80.34604,25.864482],"type":"Point"}
}