{
  "type": "Feature",
  "properties": {
    "iso:country":"US",
    "sg:address":"3208 Gulf Gate Dr",
    "sg:city":"Sarasota",
    "sg:classifiers":[
        {
            "category":"Professional",
            "subcategory":"Accounting & Tax Preparation",
            "type":"Services"
        }
    ],
    "sg:phone":"+1 941 922 3443",
    "sg:postcode":"34231",
    "sg:province":"FL",
    "sg:tags":[
        "return"
    ],
    "wof:name":"Albert A Haab CPA",
    "wof:placetype":"venue"
},
  "geometry": {"coordinates":[-82.497742,27.254021],"type":"Point"}
}