{
  "type": "Feature",
  "properties": {
    "iso:country":"US",
    "sg:address":"8340 Ulmerton Rd",
    "sg:city":"Largo",
    "sg:classifiers":[
        {
            "category":"Shopping",
            "subcategory":"Clothing, Apparel, & Fashions",
            "type":"Retail Goods"
        }
    ],
    "sg:phone":"+1 727 533 8454",
    "sg:postcode":"33771",
    "sg:province":"FL",
    "sg:tags":[
        "t"
    ],
    "wof:name":"Tiki T Shirts",
    "wof:placetype":"venue"
},
  "geometry": {"coordinates":[-82.756112,27.894398],"type":"Point"}
}