{
  "type": "Feature",
  "properties": {
    "iso:country":"US",
    "sg:address":"3330 Spanish Moss Ter # 410",
    "sg:city":"Lauderhill",
    "sg:classifiers":[
        {
            "category":"Cinema",
            "subcategory":"Movie Rental",
            "type":"Entertainment"
        }
    ],
    "sg:phone":"+1 954 485 9391",
    "sg:postcode":"33319",
    "sg:province":"FL",
    "sg:tags":[
        "motion",
        "picture",
        "distributor",
        "film",
        "exchange"
    ],
    "wof:name":"S.D.M. Productions",
    "wof:placetype":"venue"
},
  "geometry": {"coordinates":[-80.232196,26.168415],"type":"Point"}
}