{
  "type": "Feature",
  "properties": {
    "addr:full":"9720 61st Way N Pinellas Park FL 33782",
    "addr:housenumber":"9720",
    "addr:postcode":"33782",
    "addr:street":"61St Way N",
    "iso:country":"US",
    "sg:address":"9720 61st Way N",
    "sg:city":"Pinellas Park",
    "sg:classifiers":[
        {
            "category":"Retail",
            "subcategory":"Repair Shop",
            "type":"Services"
        }
    ],
    "sg:phone":"+1 727 545 1960",
    "sg:postcode":"33782",
    "sg:province":"FL",
    "sg:tags":[
        "appliance"
    ],
    "wof:name":"Bob Hansen's Appliance & AC",
    "wof:placetype":"venue"
},
  "geometry": {"coordinates":[-82.719104,27.861239],"type":"Point"}
}