{
  "type": "Feature",
  "properties": {
    "iso:country":"US",
    "sg:address":"3410 N Harbor City Blvd",
    "sg:city":"Melbourne",
    "sg:classifiers":[
        {
            "category":"Personal",
            "type":"Services"
        }
    ],
    "sg:phone":"+1 321 253 6900",
    "sg:postcode":"32935",
    "sg:province":"FL",
    "sg:tags":[
        "credit",
        "debt",
        "counseling"
    ],
    "wof:name":"A-Family Budget Counseling",
    "wof:placetype":"venue"
},
  "geometry": {"coordinates":[-80.64290800000001,28.163],"type":"Point"}
}