{
  "type": "Feature",
  "properties": {
    "iso:country":"US",
    "sg:address":"4281 W McNab Rd",
    "sg:city":"Pompano Beach",
    "sg:classifiers":[
        {
            "category":"Shopping",
            "subcategory":"Computers & Home Electronics",
            "type":"Retail Goods"
        }
    ],
    "sg:phone":"+1 954 971 5420",
    "sg:postcode":"33069",
    "sg:province":"FL",
    "sg:tags":[
        "equipment",
        "dealer"
    ],
    "wof:name":"Computer Dimension Network",
    "wof:placetype":"venue"
},
  "geometry": {"coordinates":[-80.189601,26.20971],"type":"Point"}
}