{
  "type": "Feature",
  "properties": {
    "iso:country":"US",
    "sg:address":"124 Monarch Cir",
    "sg:city":"Casselberry",
    "sg:classifiers":[
        {
            "category":"Building & Trades",
            "subcategory":"Construction",
            "type":"Services"
        }
    ],
    "sg:phone":"+1 407 331 1939",
    "sg:postcode":"32730",
    "sg:province":"FL",
    "sg:tags":[
        "house"
    ],
    "wof:name":"Mark T Forester",
    "wof:placetype":"venue"
},
  "geometry": {"coordinates":[-81.333175,28.652975],"type":"Point"}
}