{
  "type": "Feature",
  "properties": {
    "addr:full":"8795 SE May Ter Hobe Sound FL 33455",
    "addr:housenumber":"8795",
    "addr:postcode":"33455",
    "addr:street":"Se May Ter",
    "iso:country":"US",
    "sg:address":"8795 SE May Ter",
    "sg:city":"Hobe Sound",
    "sg:classifiers":[
        {
            "category":"Retail",
            "subcategory":"Repair Shop",
            "type":"Services"
        }
    ],
    "sg:phone":"+1 772 545 2266",
    "sg:postcode":"33455",
    "sg:province":"FL",
    "sg:tags":[
        "related"
    ],
    "wof:name":"New Century Gas Svc",
    "wof:placetype":"venue"
},
  "geometry": {"coordinates":[-80.13543900000001,27.046516],"type":"Point"}
}