{
  "type": "Feature",
  "properties": {
    "addr:full":"2625 Gulf To Bay Blvd Clearwater FL 33759",
    "addr:housenumber":"2625",
    "addr:postcode":"33759",
    "addr:street":"Gulf To Bay Blvd",
    "iso:country":"US",
    "sg:address":"2625 Gulf To Bay Blvd",
    "sg:city":"Clearwater",
    "sg:classifiers":[
        {
            "category":"Retail",
            "subcategory":"Veterinary Services",
            "type":"Services"
        }
    ],
    "sg:phone":"+1 727 724 1866",
    "sg:postcode":"33759",
    "sg:province":"FL",
    "sg:tags":[
        "veterinarian"
    ],
    "wof:name":"Banfield The Pet Hospital",
    "wof:placetype":"venue"
},
  "geometry": {"coordinates":[-82.727653,27.960473],"type":"Point"}
}