{
  "type": "Feature",
  "properties": {
    "iso:country":"US",
    "sg:address":"2614 Sheridan St",
    "sg:city":"Hollywood",
    "sg:classifiers":[
        {
            "category":"Building & Trades",
            "subcategory":"Electrical",
            "type":"Services"
        }
    ],
    "sg:phone":"+1 954 920 0059",
    "sg:postcode":"33020",
    "sg:province":"FL",
    "sg:tags":[
        "electrician"
    ],
    "wof:name":"Navarro Electrical Consultants",
    "wof:placetype":"venue"
},
  "geometry": {"coordinates":[-80.159803,26.033252],"type":"Point"}
}