{
  "type": "Feature",
  "properties": {
    "iso:country":"US",
    "sg:address":"7826 Photonics Dr",
    "sg:city":"Trinity",
    "sg:classifiers":[
        {
            "category":"Wholesale",
            "subcategory":"Medical Equipment & Supplies",
            "type":"Manufacturing & Wholesale Goods"
        },
        {
            "category":"Shopping",
            "subcategory":"Optical Goods",
            "type":"Retail Goods"
        }
    ],
    "sg:phone":"+1 727 375 8562",
    "sg:postcode":"34655",
    "sg:province":"FL",
    "sg:tags":[
        "goods-wholesale",
        "manufacturer",
        "optometrists'",
        "machinery"
    ],
    "sg:website":"http://www.vloc.com",
    "wof:name":"V L O C",
    "wof:placetype":"venue"
},
  "geometry": {"coordinates":[-82.685361,28.191181],"type":"Point"}
}