{
  "type": "Feature",
  "properties": {
    "addr:full":"3224 River Rd Gulf Breeze FL 32566",
    "addr:housenumber":"3224",
    "addr:postcode":"32566",
    "addr:street":"River Rd",
    "iso:country":"US",
    "sg:address":"3224 River Rd",
    "sg:city":"Gulf Breeze",
    "sg:classifiers":[
        {
            "category":"Wholesale",
            "subcategory":"Construction Materials",
            "type":"Manufacturing & Wholesale Goods"
        },
        {
            "category":"Building & Trades",
            "subcategory":"Construction",
            "type":"Services"
        }
    ],
    "sg:phone":"+1 850 939 4949",
    "sg:postcode":"32566",
    "sg:province":"FL",
    "sg:tags":[
        "refuse",
        "gravel",
        "system",
        "sand",
        "contractor"
    ],
    "wof:name":"Bayside Development Co",
    "wof:placetype":"venue"
},
  "geometry": {"coordinates":[-86.86659400000001,30.455948],"type":"Point"}
}