{
  "type": "Feature",
  "properties": {
    "iso:country":"US",
    "sg:address":"1148 Nantucket Rd",
    "sg:city":"Venice",
    "sg:classifiers":[
        {
            "category":"Home & Garden",
            "subcategory":"Mobile Homes",
            "type":"Retail Goods"
        }
    ],
    "sg:phone":"+1 941 496 8175",
    "sg:postcode":"34293",
    "sg:province":"FL",
    "sg:tags":[
        "homes-repair"
    ],
    "wof:name":"Kathy & Brian Decko",
    "wof:placetype":"venue"
},
  "geometry": {"coordinates":[-82.428015,27.054802],"type":"Point"}
}