{
  "type": "Feature",
  "properties": {
    "iso:country":"US",
    "sg:address":"4926 69th Ct E",
    "sg:city":"Palmetto",
    "sg:classifiers":[
        {
            "category":"Building & Trades",
            "subcategory":"Construction",
            "type":"Services"
        }
    ],
    "sg:phone":"+1 941 722 0550",
    "sg:postcode":"34221",
    "sg:province":"FL",
    "sg:tags":[
        "tile",
        "ceramic",
        "contractor"
    ],
    "wof:name":"Empire Tile",
    "wof:placetype":"venue"
},
  "geometry": {"coordinates":[-82.518282,27.576421],"type":"Point"}
}