{
  "type": "Feature",
  "properties": {
    "iso:country":"US",
    "sg:address":"1700 Osceola Blvd",
    "sg:city":"Pensacola",
    "sg:classifiers":[
        {
            "category":"Professional",
            "subcategory":"Lawyer & Legal Services",
            "type":"Services"
        }
    ],
    "sg:phone":"+1 850 438 3543",
    "sg:postcode":"32503",
    "sg:province":"FL",
    "sg:tags":[
        "plan"
    ],
    "wof:name":"The Warren Ted Brown And Kathleen Horton Brown F",
    "wof:placetype":"venue"
},
  "geometry": {"coordinates":[-87.18720999999999,30.43364],"type":"Point"}
}