{
  "type": "Feature",
  "properties": {
    "addr:full":"9000 S Orange Blossom Trl Orlando FL 32809",
    "addr:housenumber":"9000",
    "addr:postcode":"32809",
    "addr:street":"S Orange Blossom Trl",
    "iso:country":"US",
    "sg:address":"9000 S Orange Blossom Trl",
    "sg:city":"Orlando",
    "sg:classifiers":[
        {
            "category":"Travel",
            "subcategory":"Travel Agent",
            "type":"Entertainment"
        }
    ],
    "sg:phone":"+1 407 240 5536",
    "sg:postcode":"32809",
    "sg:province":"FL",
    "sg:tags":[
        "operator",
        "attraction",
        "tour",
        "selling",
        "ticket"
    ],
    "wof:name":"Florida Holidays Inc",
    "wof:placetype":"venue"
},
  "geometry": {"coordinates":[-81.404522,28.435969],"type":"Point"}
}