{
  "type": "Feature",
  "properties": {
    "iso:country":"US",
    "sg:address":"606 E Memorial Blvd",
    "sg:city":"Lakeland",
    "sg:classifiers":[
        {
            "category":"Shopping",
            "subcategory":"Jewelry",
            "type":"Retail Goods"
        }
    ],
    "sg:phone":"+1 863 603 0846",
    "sg:postcode":"33801",
    "sg:province":"FL",
    "sg:tags":[
        "jeweler"
    ],
    "wof:name":"Value Pawn & Jewelry",
    "wof:placetype":"venue"
},
  "geometry": {"coordinates":[-81.95124,28.055089],"type":"Point"}
}