{
  "type": "Feature",
  "properties": {
    "iso:country":"US",
    "sg:address":"1353 S Volusia Ave",
    "sg:city":"Orange City",
    "sg:classifiers":[
        {
            "category":"Building & Trades",
            "subcategory":"Construction",
            "type":"Services"
        }
    ],
    "sg:phone":"+1 386 804 9417",
    "sg:postcode":"32763",
    "sg:province":"FL",
    "sg:tags":[
        "stucco",
        "contractor"
    ],
    "wof:name":"Greg Delong Construction",
    "wof:placetype":"venue"
},
  "geometry": {"coordinates":[-81.298963,28.934477],"type":"Point"}
}