{
  "type": "Feature",
  "properties": {
    "iso:country":"US",
    "sg:address":"8390 NW 53rd St",
    "sg:city":"Doral",
    "sg:classifiers":[
        {
            "category":"Shopping",
            "type":"Retail Goods"
        }
    ],
    "sg:phone":"+1 305 412 7849",
    "sg:postcode":"33166",
    "sg:province":"FL",
    "sg:tags":[
        "equipment",
        "telephone",
        "supply"
    ],
    "wof:name":"Noya Telcom Inc",
    "wof:placetype":"venue"
},
  "geometry": {"coordinates":[-80.333792,25.820128],"type":"Point"}
}