{
  "type": "Feature",
  "properties": {
    "addr:full":"28951 W Dixie Hwy Homestead FL 33033",
    "addr:housenumber":"28951",
    "addr:postcode":"33033",
    "addr:street":"W Dixie Hwy",
    "iso:country":"US",
    "sg:address":"28951 W Dixie Hwy",
    "sg:city":"Homestead",
    "sg:classifiers":[
        {
            "category":"Social Services",
            "type":"Services"
        }
    ],
    "sg:phone":"+1 305 248 6200",
    "sg:postcode":"33033",
    "sg:province":"FL",
    "sg:tags":[
        "day",
        "center",
        "adult",
        "care"
    ],
    "wof:name":"Golden Age ADC & Respite Ctr",
    "wof:placetype":"venue"
},
  "geometry": {"coordinates":[-80.452496,25.494671],"type":"Point"}
}