{
  "type": "Feature",
  "properties": {
    "iso:country":"US",
    "sg:address":"215 Fairpoint Dr",
    "sg:city":"Gulf Breeze",
    "sg:classifiers":[
        {
            "category":"Building & Trades",
            "subcategory":"Plumbing",
            "type":"Services"
        }
    ],
    "sg:phone":"+1 850 934 5747",
    "sg:postcode":"32561",
    "sg:province":"FL",
    "sg:tags":[
        "plumbing",
        "contractor"
    ],
    "wof:name":"Casey Hyman Plumbing Inc",
    "wof:placetype":"venue"
},
  "geometry": {"coordinates":[-87.178539,30.361398],"type":"Point"}
}