{
  "type": "Feature",
  "properties": {
    "iso:country":"US",
    "sg:address":"3371 NW 27th Ave",
    "sg:city":"Miami",
    "sg:classifiers":[
        {
            "category":"Building & Trades",
            "subcategory":"Plumbing",
            "type":"Services"
        }
    ],
    "sg:phone":"+1 866 897 0343",
    "sg:postcode":"33142",
    "sg:province":"FL",
    "sg:tags":[
        "plumber",
        "tank",
        "system",
        "septic"
    ],
    "wof:name":"NCH Plumbing, Inc.",
    "wof:placetype":"venue"
},
  "geometry": {"coordinates":[-80.240081,25.80697],"type":"Point"}
}