{
  "type": "Feature",
  "properties": {
    "iso:country":"US",
    "sg:address":"18901 Dixie Hwy",
    "sg:city":"Miami",
    "sg:classifiers":[
        {
            "category":"Professional",
            "type":"Services"
        }
    ],
    "sg:phone":"+1 305 259 1822",
    "sg:postcode":"33157",
    "sg:province":"FL",
    "sg:tags":[
        "establishment"
    ],
    "wof:name":"B Iomen Intl",
    "wof:placetype":"venue"
},
  "geometry": {"coordinates":[-80.357591,25.591543],"type":"Point"}
}