{
  "type": "Feature",
  "properties": {
    "iso:country":"US",
    "sg:address":"947 Wedgewood Dr N",
    "sg:city":"Winter Springs",
    "sg:classifiers":[
        {
            "category":"Banks & Credit Unions",
            "subcategory":"Financial Services",
            "type":"Services"
        }
    ],
    "sg:phone":"+1 407 977 3642",
    "sg:postcode":"32708",
    "sg:province":"FL",
    "sg:tags":[
        "club",
        "investment"
    ],
    "wof:name":"Nielson Family Partnership",
    "wof:placetype":"venue"
},
  "geometry": {"coordinates":[-81.261212,28.672256],"type":"Point"}
}