{
  "type": "Feature",
  "properties": {
    "iso:country":"US",
    "sg:address":"1233 Bartow Rd",
    "sg:city":"Lakeland",
    "sg:classifiers":[
        {
            "category":"Banks & Credit Unions",
            "subcategory":"Investment Brokerage",
            "type":"Services"
        }
    ],
    "sg:phone":"+1 863 687 3400",
    "sg:postcode":"33801",
    "sg:province":"FL",
    "sg:tags":[
        "security",
        "legal"
    ],
    "wof:name":"Paine Robert M PA",
    "wof:placetype":"venue"
},
  "geometry": {"coordinates":[-81.930193,28.028628],"type":"Point"}
}