{
  "type": "Feature",
  "properties": {
    "addr:full":"716 SE 47th Ter Cape Coral FL 33904",
    "addr:housenumber":"716",
    "addr:postcode":"33904",
    "addr:street":"Se 47Th Ter",
    "iso:country":"US",
    "sg:address":"716 SE 47th Ter",
    "sg:city":"Cape Coral",
    "sg:classifiers":[
        {
            "category":"Manufacturing",
            "subcategory":"Signs",
            "type":"Manufacturing & Wholesale Goods"
        }
    ],
    "sg:phone":"+1 239 542 3354",
    "sg:postcode":"33904",
    "sg:province":"FL",
    "sg:tags":[
        "specialty",
        "mfg"
    ],
    "wof:name":"Artistix Sign & Graphix Inc",
    "wof:placetype":"venue"
},
  "geometry": {"coordinates":[-81.960122,26.563699],"type":"Point"}
}