{
  "type": "Feature",
  "properties": {
    "iso:country":"US",
    "sg:address":"2261 W New Haven Ave",
    "sg:city":"Melbourne",
    "sg:classifiers":[
        {
            "category":"Food & Beverages",
            "subcategory":"Groceries & Convenience Stores",
            "type":"Retail Goods"
        }
    ],
    "sg:phone":"+1 321 676 1441",
    "sg:postcode":"32904",
    "sg:province":"FL",
    "sg:tags":[
        "product",
        "grocer",
        "mfg"
    ],
    "wof:name":"Publix Super Market 258",
    "wof:placetype":"venue"
},
  "geometry": {"coordinates":[-80.658475,28.078766],"type":"Point"}
}