{
  "type": "Feature",
  "properties": {
    "addr:full":"728 NW 53rd St Miami FL 33127",
    "addr:housenumber":"728",
    "addr:postcode":"33127",
    "addr:street":"Nw 53Rd St",
    "iso:country":"US",
    "sg:address":"728 NW 53rd St",
    "sg:city":"Miami",
    "sg:classifiers":[
        {
            "category":"Personal",
            "subcategory":"Nail Salon",
            "type":"Services"
        }
    ],
    "sg:phone":"+1 305 754 4004",
    "sg:postcode":"33127",
    "sg:province":"FL",
    "wof:name":"Nails by Almeta",
    "wof:placetype":"venue"
},
  "geometry": {"coordinates":[-80.20880099999999,25.8241],"type":"Point"}
}