{
  "type": "Feature",
  "properties": {
    "addr:full":"700 1st St S Winter Haven FL 33880",
    "addr:housenumber":"700",
    "addr:postcode":"33880",
    "addr:street":"1St St S",
    "iso:country":"US",
    "sg:address":"700 1st St S",
    "sg:city":"Winter Haven",
    "sg:classifiers":[
        {
            "category":"Shopping",
            "subcategory":"Gifts & Souvenirs",
            "type":"Retail Goods"
        }
    ],
    "sg:phone":"+1 863 293 3335",
    "sg:postcode":"33880",
    "sg:province":"FL",
    "sg:tags":[
        "shop"
    ],
    "wof:name":"Long's Hallmark Shop",
    "wof:placetype":"venue"
},
  "geometry": {"coordinates":[-81.72673,28.018057],"type":"Point"}
}