{
  "type": "Feature",
  "properties": {
    "addr:full":"218 S Webb Rd Plant City FL 33566",
    "addr:housenumber":"218",
    "addr:postcode":"33566",
    "addr:street":"S Webb Rd",
    "iso:country":"US",
    "sg:address":"218 S Webb Rd",
    "sg:city":"Plant City",
    "sg:classifiers":[
        {
            "category":"Farming",
            "subcategory":"Aquatic Farm",
            "type":"Manufacturing & Wholesale Goods"
        }
    ],
    "sg:phone":"+1 813 757 0289",
    "sg:postcode":"33566",
    "sg:province":"FL",
    "wof:name":"Aquatica Tropicals Inc",
    "wof:placetype":"venue"
},
  "geometry": {"coordinates":[-82.059901,28.025485],"type":"Point"}
}