{
  "type": "Feature",
  "properties": {
    "addr:full":"702 S Magnolia Ave Ocala FL 34471",
    "addr:housenumber":"702",
    "addr:postcode":"34471",
    "addr:street":"S Magnolia Ave",
    "iso:country":"US",
    "sg:address":"702 S Magnolia Ave",
    "sg:city":"Ocala",
    "sg:classifiers":[
        {
            "category":"Retail",
            "subcategory":"Veterinary Services",
            "type":"Services"
        },
        {
            "category":"Retail",
            "subcategory":"Pet Boarding",
            "type":"Services"
        }
    ],
    "sg:phone":"+1 352 732 7877",
    "sg:postcode":"34471",
    "sg:province":"FL",
    "sg:tags":[
        "veterinarian",
        "kennel"
    ],
    "wof:name":"Brick City Cat Hospital",
    "wof:placetype":"venue"
},
  "geometry": {"coordinates":[-82.137017,29.181145],"type":"Point"}
}