{
  "type": "Feature",
  "properties": {
    "iso:country":"US",
    "sg:address":"507 S Palm Ave",
    "sg:city":"Titusville",
    "sg:classifiers":[
        {
            "category":"Professional",
            "subcategory":"Lawyer & Legal Services",
            "type":"Services"
        }
    ],
    "sg:phone":"+1 321 269 4328",
    "sg:postcode":"32796",
    "sg:province":"FL",
    "wof:name":"Carl Wasileski Atty Inc",
    "wof:placetype":"venue"
},
  "geometry": {"coordinates":[-80.809044,28.609271],"type":"Point"}
}