{
  "type": "Feature",
  "properties": {
    "iso:country":"US",
    "sg:address":"5850 Heronpark Pl",
    "sg:city":"Lithia",
    "sg:classifiers":[
        {
            "category":"Building & Trades",
            "subcategory":"Construction",
            "type":"Services"
        }
    ],
    "sg:phone":"+1 813 685 0175",
    "sg:postcode":"33547",
    "sg:province":"FL",
    "sg:tags":[
        "resurfacing",
        "laying",
        "refinishing",
        "floor"
    ],
    "wof:name":"Creative Custom Floors",
    "wof:placetype":"venue"
},
  "geometry": {"coordinates":[-82.233732,27.846874],"type":"Point"}
}