{
  "type": "Feature",
  "properties": {
    "iso:country":"US",
    "sg:address":"5518 Thomas Dr",
    "sg:city":"Panama City Bch",
    "sg:classifiers":[
        {
            "category":"Wholesale",
            "subcategory":"Groceries",
            "type":"Manufacturing & Wholesale Goods"
        }
    ],
    "sg:phone":"+1 850 230 2900",
    "sg:postcode":"32408",
    "sg:province":"FL",
    "sg:tags":[
        "beverage"
    ],
    "wof:name":"Drink Pink Of Bay County",
    "wof:placetype":"venue"
},
  "geometry": {"coordinates":[-85.756546,30.144511],"type":"Point"}
}