{
  "type": "Feature",
  "properties": {
    "iso:country":"US",
    "sg:address":"136 W Britain St",
    "sg:city":"Hernando",
    "sg:classifiers":[
        {
            "category":"Professional",
            "subcategory":"Lawyer & Legal Services",
            "type":"Services"
        }
    ],
    "sg:phone":"+1 352 746 9530",
    "sg:postcode":"34442",
    "sg:province":"FL",
    "sg:tags":[
        "plan"
    ],
    "wof:name":"Stephen Kauffman",
    "wof:placetype":"venue"
},
  "geometry": {"coordinates":[-82.435907,28.884543],"type":"Point"}
}