{
  "type": "Feature",
  "properties": {
    "addr:full":"6840 33rd St N St Petersburg FL 33702",
    "addr:housenumber":"6840",
    "addr:postcode":"33702",
    "addr:street":"33Rd St N",
    "iso:country":"US",
    "sg:address":"6840 33rd St N",
    "sg:city":"St Petersburg",
    "sg:classifiers":[
        {
            "category":"Retail",
            "subcategory":"Repair Shop",
            "type":"Services"
        }
    ],
    "sg:phone":"+1 727 528 8191",
    "sg:postcode":"33702",
    "sg:province":"FL",
    "sg:tags":[
        "equipment"
    ],
    "wof:name":"Equipment Doctors",
    "wof:placetype":"venue"
},
  "geometry": {"coordinates":[-82.679214,27.835249],"type":"Point"}
}