{
  "type": "Feature",
  "properties": {
    "addr:full":"1625 W Princeton St Orlando FL 32804",
    "addr:housenumber":"1625",
    "addr:postcode":"32804",
    "addr:street":"W Princeton St",
    "iso:country":"US",
    "sg:address":"1625 W Princeton St",
    "sg:city":"Orlando",
    "sg:classifiers":[
        {
            "category":"Home & Garden",
            "subcategory":"Furniture",
            "type":"Retail Goods"
        }
    ],
    "sg:phone":"+1 407 895 5557",
    "sg:postcode":"32804",
    "sg:province":"FL",
    "sg:tags":[
        "cabinet"
    ],
    "wof:name":"Exclusive Kitchens & Finishing",
    "wof:placetype":"venue"
},
  "geometry": {"coordinates":[-81.405368,28.571864],"type":"Point"}
}