{
  "type": "Feature",
  "properties": {
    "addr:full":"5927 N Rome Ave Tampa FL 33604",
    "addr:housenumber":"5927",
    "addr:postcode":"33604",
    "addr:street":"N Rome Ave",
    "iso:country":"US",
    "sg:address":"5927 N Rome Ave",
    "sg:city":"Tampa",
    "sg:classifiers":[
        {
            "category":"Social Services",
            "subcategory":"Adult Care",
            "type":"Services"
        }
    ],
    "sg:phone":"+1 813 234 6400",
    "sg:postcode":"33604",
    "sg:province":"FL",
    "sg:tags":[
        "residential"
    ],
    "wof:name":"Johns Crossing",
    "wof:placetype":"venue"
},
  "geometry": {"coordinates":[-82.476078,28.001646],"type":"Point"}
}