{
  "type": "Feature",
  "properties": {
    "addr:full":"6886 Royal Orchid Cir Delray Beach FL 33446",
    "addr:housenumber":"6886",
    "addr:postcode":"33446",
    "addr:street":"Royal Orchid Cir",
    "iso:country":"US",
    "sg:address":"6886 Royal Orchid Cir",
    "sg:city":"Delray Beach",
    "sg:classifiers":[
        {
            "category":"Professional",
            "subcategory":"Management & Consulting",
            "type":"Services"
        }
    ],
    "sg:phone":"+1 561 499 5744",
    "sg:postcode":"33446",
    "sg:province":"FL",
    "sg:tags":[
        "business"
    ],
    "wof:name":"Korey Consulting Inc",
    "wof:placetype":"venue"
},
  "geometry": {"coordinates":[-80.152153,26.429142],"type":"Point"}
}