{
  "type": "Feature",
  "properties": {
    "iso:country":"US",
    "sg:address":"1001 W Jasmine Dr",
    "sg:city":"Lake Park",
    "sg:classifiers":[
        {
            "category":"Manufacturing",
            "subcategory":"Printing",
            "type":"Manufacturing & Wholesale Goods"
        }
    ],
    "sg:phone":"+1 561 842 5516",
    "sg:postcode":"33403",
    "sg:province":"FL",
    "sg:tags":[
        "lithographic",
        "printer",
        "commercial",
        "typesetting"
    ],
    "wof:name":"Professional Printing Center",
    "wof:placetype":"venue"
},
  "geometry": {"coordinates":[-80.074218,26.800901],"type":"Point"}
}