{
  "type": "Feature",
  "properties": {
    "addr:full":"6222 Commercial Way Weeki Wachee FL 34613",
    "addr:housenumber":"6222",
    "addr:postcode":"34613",
    "addr:street":"Commercial Way",
    "iso:country":"US",
    "sg:address":"6222 Commercial Way",
    "sg:city":"Weeki Wachee",
    "sg:classifiers":[
        {
            "category":"Professional",
            "subcategory":"Accounting & Tax Preparation",
            "type":"Services"
        }
    ],
    "sg:phone":"+1 352 596 4916",
    "sg:postcode":"34613",
    "sg:province":"FL",
    "sg:tags":[
        "return",
        "filing"
    ],
    "wof:name":"H & R Block Tax Svc",
    "wof:placetype":"venue"
},
  "geometry": {"coordinates":[-82.57011300000001,28.522159],"type":"Point"}
}