{
  "type": "Feature",
  "properties": {
    "iso:country":"US",
    "sg:address":"118 Middle St",
    "sg:city":"Lake Mary",
    "sg:classifiers":[
        {
            "category":"Deli",
            "type":"Food & Drink"
        }
    ],
    "sg:phone":"+1 407 302 0555",
    "sg:postcode":"32746",
    "sg:province":"FL",
    "wof:name":"Mana Lou's Italian Deli",
    "wof:placetype":"venue"
},
  "geometry": {"coordinates":[-81.337255,28.755635],"type":"Point"}
}