{
  "type": "Feature",
  "properties": {
    "iso:country":"US",
    "sg:address":"4435 34th Ave N",
    "sg:city":"Saint Petersburg",
    "sg:classifiers":[
        {
            "category":"Manufacturing",
            "subcategory":"Tools & Machinery",
            "type":"Manufacturing & Wholesale Goods"
        }
    ],
    "sg:phone":"+1 727 527 7825",
    "sg:postcode":"33713",
    "sg:province":"FL",
    "sg:tags":[
        "woodworking",
        "mfg"
    ],
    "wof:name":"Slt Enterprises",
    "wof:placetype":"venue"
},
  "geometry": {"coordinates":[-82.69256,27.802842],"type":"Point"}
}