{
  "type": "Feature",
  "properties": {
    "iso:country":"US",
    "sg:address":"426 Canal St",
    "sg:city":"New Smyrna Beach",
    "sg:classifiers":[
        {
            "category":"Home & Garden",
            "subcategory":"Furniture",
            "type":"Retail Goods"
        }
    ],
    "sg:phone":"+1 386 409 0727",
    "sg:postcode":"32168",
    "sg:province":"FL",
    "wof:name":"Room Service",
    "wof:placetype":"venue"
},
  "geometry": {"coordinates":[-80.92491800000001,29.024227],"type":"Point"}
}