{
  "type": "Feature",
  "properties": {
    "addr:full":"667 NW 101st St Miami FL 33150",
    "addr:housenumber":"667",
    "addr:postcode":"33150",
    "addr:street":"Nw 101St St",
    "iso:country":"US",
    "sg:address":"667 NW 101st St",
    "sg:city":"Miami",
    "sg:classifiers":[
        {
            "category":"Building & Trades",
            "subcategory":"Construction",
            "type":"Services"
        }
    ],
    "sg:phone":"+1 305 754 5554",
    "sg:postcode":"33150",
    "sg:province":"FL",
    "sg:tags":[
        "roofing",
        "contractor"
    ],
    "sg:website":"http://www.miamiroofingsystems.com",
    "wof:name":"Miami Roofing Systems",
    "wof:placetype":"venue"
},
  "geometry": {"coordinates":[-80.209565,25.867766],"type":"Point"}
}