{
  "type": "Feature",
  "properties": {
    "iso:country":"US",
    "sg:address":"6412 W Colonial Dr",
    "sg:city":"Orlando",
    "sg:classifiers":[
        {
            "category":"Home & Garden",
            "subcategory":"Household Appliances",
            "type":"Retail Goods"
        }
    ],
    "sg:phone":"+1 407 296 2822",
    "sg:postcode":"32818",
    "sg:province":"FL",
    "sg:tags":[
        "cleaners",
        "vacuum"
    ],
    "wof:name":"Longwood Vacuum Cleaner Ctr",
    "wof:placetype":"venue"
},
  "geometry": {"coordinates":[-81.469126,28.552031],"type":"Point"}
}