{
  "type": "Feature",
  "properties": {
    "iso:country":"US",
    "sg:address":"4515 Virginia St",
    "sg:city":"Apopka",
    "sg:classifiers":[
        {
            "category":"Building & Trades",
            "subcategory":"Construction",
            "type":"Services"
        }
    ],
    "sg:phone":"+1 407 884 7476",
    "sg:postcode":"32712",
    "sg:province":"FL",
    "sg:tags":[
        "house"
    ],
    "wof:name":"Kyle & Cremer Contracting",
    "wof:placetype":"venue"
},
  "geometry": {"coordinates":[-81.51109,28.750285],"type":"Point"}
}