{
  "type": "Feature",
  "properties": {
    "addr:full":"4994 NW 39th Ave Gainesville FL 32606",
    "addr:housenumber":"4994",
    "addr:postcode":"32606",
    "addr:street":"Nw 39Th Ave",
    "iso:country":"US",
    "sg:address":"4994 NW 39th Ave",
    "sg:city":"Gainesville",
    "sg:classifiers":[
        {
            "category":"Cinema",
            "subcategory":"Movie Rental",
            "type":"Entertainment"
        }
    ],
    "sg:phone":"+1 352 377 5650",
    "sg:postcode":"32606",
    "sg:province":"FL",
    "sg:tags":[
        "video",
        "tape"
    ],
    "wof:name":"Blockbuster",
    "wof:placetype":"venue"
},
  "geometry": {"coordinates":[-82.394875,29.688721],"type":"Point"}
}