{
  "type": "Feature",
  "properties": {
    "addr:full":"2747 Bancroft Blvd Orlando FL 32833",
    "addr:housenumber":"2747",
    "addr:postcode":"32833",
    "addr:street":"Bancroft Blvd",
    "iso:country":"US",
    "sg:address":"2747 Bancroft Blvd",
    "sg:city":"Orlando",
    "sg:classifiers":[
        {
            "category":"Professional",
            "subcategory":"Computer Services",
            "type":"Services"
        }
    ],
    "sg:phone":"+1 407 568 3705",
    "sg:postcode":"32833",
    "sg:province":"FL",
    "sg:tags":[
        "consulting",
        "related"
    ],
    "wof:name":"Cabletechs of Central Florida",
    "wof:placetype":"venue"
},
  "geometry": {"coordinates":[-81.078577,28.505091],"type":"Point"}
}