{
  "type": "Feature",
  "properties": {
    "addr:full":"7935 NW 2nd St Miami FL 33126",
    "addr:housenumber":"7935",
    "addr:postcode":"33126",
    "addr:street":"Nw 2Nd St",
    "iso:country":"US",
    "sg:address":"7935 NW 2nd St",
    "sg:city":"Miami",
    "sg:classifiers":[
        {
            "category":"Education",
            "subcategory":"Special Training",
            "type":"Public Place"
        }
    ],
    "sg:phone":"+1 305 266 2855",
    "sg:postcode":"33126",
    "sg:province":"FL",
    "sg:tags":[
        "tutoring"
    ],
    "wof:name":"Academic Tutorial Institute",
    "wof:placetype":"venue"
},
  "geometry": {"coordinates":[-80.32541500000001,25.772227],"type":"Point"}
}