{
  "type": "Feature",
  "properties": {
    "iso:country":"US",
    "sg:address":"4817 Vision Ave",
    "sg:city":"Holiday",
    "sg:classifiers":[
        {
            "category":"Building & Trades",
            "subcategory":"Landscaping Services",
            "type":"Services"
        }
    ],
    "sg:phone":"+1 727 943 0725",
    "sg:postcode":"34690",
    "sg:province":"FL",
    "wof:name":"American Pest Control",
    "wof:placetype":"venue"
},
  "geometry": {"coordinates":[-82.73436,28.178806],"type":"Point"}
}