{
  "type": "Feature",
  "properties": {
    "iso:country":"US",
    "sg:address":"513 Meadoe Ridge Ct",
    "sg:city":"Tallahassee",
    "sg:classifiers":[
        {
            "category":"Building & Trades",
            "subcategory":"Construction",
            "type":"Services"
        }
    ],
    "sg:phone":"+1 850 668 2292",
    "sg:postcode":"32312",
    "sg:province":"FL",
    "sg:tags":[
        "painter"
    ],
    "wof:name":"Daniel A Pelletier Painting",
    "wof:placetype":"venue"
},
  "geometry": {"coordinates":[-84.26269499999999,30.566335],"type":"Point"}
}