{
  "type": "Feature",
  "properties": {
    "addr:full":"611 Pennsylvania Ave Saint Cloud FL 34769",
    "addr:housenumber":"611",
    "addr:postcode":"34769",
    "addr:street":"Pennsylvania Ave",
    "iso:country":"US",
    "sg:address":"611 Pennsylvania Ave",
    "sg:city":"Saint Cloud",
    "sg:classifiers":[
        {
            "category":"Restaurant",
            "type":"Food & Drink"
        }
    ],
    "sg:phone":"+1 407 957 1271",
    "sg:postcode":"34769",
    "sg:province":"FL",
    "sg:tags":[
        "eating"
    ],
    "wof:name":"Ryd Inc",
    "wof:placetype":"venue"
},
  "geometry": {"coordinates":[-81.282347,28.251704],"type":"Point"}
}