{
  "type": "Feature",
  "properties": {
    "addr:full":"25 Spruce Ln Valrico FL 33594",
    "addr:housenumber":"25",
    "addr:postcode":"33594",
    "addr:street":"Spruce Ln",
    "iso:country":"US",
    "sg:address":"25 Spruce Ln",
    "sg:city":"Valrico",
    "sg:classifiers":[
        {
            "category":"Real Estate",
            "subcategory":"Real Estate Operator",
            "type":"Services"
        }
    ],
    "sg:phone":"+1 813 654 2339",
    "sg:postcode":"33594",
    "sg:province":"FL",
    "sg:tags":[
        "mobile",
        "home",
        "site"
    ],
    "wof:name":"Cypress Mobile Home Rental Pk",
    "wof:placetype":"venue"
},
  "geometry": {"coordinates":[-82.235911,27.942291],"type":"Point"}
}