{
  "type": "Feature",
  "properties": {
    "addr:full":"6720 Grapeland Trl Orlando FL 32807",
    "addr:postcode":"6720;32807",
    "addr:street":"Grapeland Trl",
    "iso:country":"US",
    "sg:address":"6720 Grapeland Trl",
    "sg:city":"Orlando",
    "sg:classifiers":[
        {
            "category":"Retail",
            "subcategory":"Repair Shop",
            "type":"Services"
        }
    ],
    "sg:phone":"+1 407 277 1235",
    "sg:postcode":"32807",
    "sg:province":"FL",
    "sg:tags":[
        "miscellaneous"
    ],
    "wof:name":"Equipment Doctor",
    "wof:placetype":"venue"
},
  "geometry": {"coordinates":[-81.292736,28.548134],"type":"Point"}
}