{
  "type": "Feature",
  "properties": {
    "iso:country":"US",
    "sg:address":"223 Fentress Blvd",
    "sg:city":"Daytona Beach",
    "sg:classifiers":[
        {
            "category":"Manufacturing",
            "subcategory":"Electronics",
            "type":"Manufacturing & Wholesale Goods"
        }
    ],
    "sg:phone":"+1 386 238 1515",
    "sg:postcode":"32114",
    "sg:province":"FL",
    "sg:tags":[
        "electronic",
        "component",
        "mfg"
    ],
    "wof:name":"Space Coast Quartz Inc",
    "wof:placetype":"venue"
},
  "geometry": {"coordinates":[-81.083478,29.202216],"type":"Point"}
}