{
  "type": "Feature",
  "properties": {
    "iso:country":"US",
    "sg:address":"1100 Lee Wagener Blvd",
    "sg:city":"Fort Lauderdale",
    "sg:classifiers":[
        {
            "category":"Professional",
            "subcategory":"Management & Consulting",
            "type":"Services"
        }
    ],
    "sg:phone":"+1 954 359 9555",
    "sg:postcode":"33315",
    "sg:province":"FL",
    "sg:tags":[
        "marketing",
        "consultant"
    ],
    "wof:name":"Clever Kids & Co",
    "wof:placetype":"venue"
},
  "geometry": {"coordinates":[-80.155023,26.070225],"type":"Point"}
}