{
  "type": "Feature",
  "properties": {
    "iso:country":"US",
    "sg:address":"201 S Orange Ave",
    "sg:city":"Orlando",
    "sg:classifiers":[
        {
            "category":"Airline",
            "type":"Transportation"
        }
    ],
    "sg:phone":"+1 800 238 5355",
    "sg:postcode":"32801",
    "sg:province":"FL",
    "sg:tags":[
        "courier",
        "air"
    ],
    "wof:name":"Federal Express Corporation",
    "wof:placetype":"venue"
},
  "geometry": {"coordinates":[-81.37900500000001,28.539023],"type":"Point"}
}