{
  "type": "Feature",
  "properties": {
    "addr:full":"11410 Cypress Dr Clermont FL 34711",
    "addr:housenumber":"11410",
    "addr:postcode":"34711",
    "addr:street":"Cypress Dr",
    "iso:country":"US",
    "sg:address":"11410 Cypress Dr",
    "sg:city":"Clermont",
    "sg:classifiers":[
        {
            "category":"Professional",
            "subcategory":"Advertising",
            "type":"Services"
        }
    ],
    "sg:phone":"+1 352 394 4850",
    "sg:postcode":"34711",
    "sg:province":"FL",
    "wof:name":"Divine Outdoor Advertising Inc",
    "wof:placetype":"venue"
},
  "geometry": {"coordinates":[-81.76787,28.516082],"type":"Point"}
}