{
  "type": "Feature",
  "properties": {
    "addr:full":"10617 W Atlantic Blvd Pompano Beach FL 33071",
    "addr:housenumber":"10617",
    "addr:postcode":"33071",
    "addr:street":"W Atlantic Blvd",
    "iso:country":"US",
    "sg:address":"10617 W Atlantic Blvd",
    "sg:city":"Pompano Beach",
    "sg:classifiers":[
        {
            "category":"Health Services",
            "subcategory":"Chiropractor",
            "type":"Services"
        }
    ],
    "sg:phone":"+1 954 755 1434",
    "sg:postcode":"33071",
    "sg:province":"FL",
    "wof:name":"Mathesie Chiropractic Lif",
    "wof:placetype":"venue"
},
  "geometry": {"coordinates":[-80.26599,26.240866],"type":"Point"}
}