{
  "type": "Feature",
  "properties": {
    "addr:full":"5801 Congress Ave Boca Raton FL 33487",
    "addr:housenumber":"5801",
    "addr:postcode":"33487",
    "addr:street":"Congress Ave",
    "iso:country":"US",
    "sg:address":"5801 Congress Ave",
    "sg:city":"Boca Raton",
    "sg:classifiers":[
        {
            "category":"Manufacturing",
            "subcategory":"Printing",
            "type":"Manufacturing & Wholesale Goods"
        }
    ],
    "sg:phone":"+1 561 893 6400",
    "sg:postcode":"33487",
    "sg:province":"FL",
    "sg:tags":[
        "newspaper",
        "publishing"
    ],
    "wof:name":"Boca Raton News",
    "wof:placetype":"venue"
},
  "geometry": {"coordinates":[-80.10247,26.400563],"type":"Point"}
}