{
  "type": "Feature",
  "properties": {
    "iso:country":"US",
    "sg:address":"1710 Carandis Rd",
    "sg:city":"West Palm Beach",
    "sg:classifiers":[
        {
            "category":"Organizations",
            "subcategory":"Religious Organization",
            "type":"Services"
        }
    ],
    "sg:phone":"+1 561 547 0308",
    "sg:postcode":"33406",
    "sg:province":"FL",
    "wof:name":"West Palm Beach FM Group",
    "wof:placetype":"venue"
},
  "geometry": {"coordinates":[-80.080009,26.655771],"type":"Point"}
}