{
  "type": "Feature",
  "properties": {
    "iso:country":"US",
    "sg:address":"1550 Dixie Hwy",
    "sg:city":"Coral Gables",
    "sg:classifiers":[
        {
            "category":"Professional",
            "subcategory":"Business Services",
            "type":"Services"
        }
    ],
    "sg:phone":"+1 305 663 1628",
    "sg:postcode":"33146",
    "sg:province":"FL",
    "sg:tags":[
        "conference",
        "coordinator",
        "seminar"
    ],
    "sg:website":"www.meccinc.com",
    "wof:name":"Meetings Events & Conference",
    "wof:placetype":"venue"
},
  "geometry": {"coordinates":[-80.284977,25.707895],"type":"Point"}
}