{
  "type": "Feature",
  "properties": {
    "addr:full":"614 N Palmetto St Leesburg FL 34748",
    "addr:housenumber":"614",
    "addr:postcode":"34748",
    "addr:street":"N Palmetto St",
    "iso:country":"US",
    "sg:address":"614 N Palmetto St",
    "sg:city":"Leesburg",
    "sg:classifiers":[
        {
            "category":"Wholesale",
            "subcategory":"Auto Parts",
            "type":"Manufacturing & Wholesale Goods"
        }
    ],
    "sg:phone":"+1 352 323 8200",
    "sg:postcode":"34748",
    "sg:province":"FL",
    "wof:name":"Finishmaster Inc",
    "wof:placetype":"venue"
},
  "geometry": {"coordinates":[-81.875101,28.816298],"type":"Point"}
}