{
  "type": "Feature",
  "properties": {
    "addr:full":"51 Sierra Ave Tavares FL 32778",
    "addr:housenumber":"51",
    "addr:postcode":"32778",
    "addr:street":"Sierra Ave",
    "iso:country":"US",
    "sg:address":"51 Sierra Ave",
    "sg:city":"Tavares",
    "sg:classifiers":[
        {
            "category":"Real Estate",
            "subcategory":"Real Estate Operator",
            "type":"Services"
        }
    ],
    "sg:phone":"+1 352 343 2779",
    "sg:postcode":"32778",
    "sg:province":"FL",
    "wof:name":"Sierra Vlg Apartments Office",
    "wof:placetype":"venue"
},
  "geometry": {"coordinates":[-81.74852,28.796747],"type":"Point"}
}