{
  "type": "Feature",
  "properties": {
    "iso:country":"US",
    "sg:address":"2363 Swan St",
    "sg:city":"Jacksonville",
    "sg:classifiers":[
        {
            "category":"Retail",
            "subcategory":"Auto Repair",
            "type":"Services"
        }
    ],
    "sg:phone":"+1 904 353 4374",
    "sg:postcode":"32204",
    "sg:province":"FL",
    "sg:tags":[
        "shop",
        "automobile",
        "machine",
        "general"
    ],
    "wof:name":"Avid Engine & Cylinder Head Sp",
    "wof:placetype":"venue"
},
  "geometry": {"coordinates":[-81.689125,30.329868],"type":"Point"}
}