{
  "type": "Feature",
  "properties": {
    "iso:country":"US",
    "sg:address":"7911 NW 21st Ave",
    "sg:city":"Miami",
    "sg:classifiers":[
        {
            "category":"Shopping",
            "subcategory":"Florist",
            "type":"Retail Goods"
        }
    ],
    "sg:phone":"+1 305 468 8591",
    "sg:postcode":"33147",
    "sg:province":"FL",
    "wof:name":"Passion Flower",
    "wof:placetype":"venue"
},
  "geometry": {"coordinates":[-80.23154,25.846517],"type":"Point"}
}