{
  "type": "Feature",
  "properties": {
    "iso:country":"US",
    "sg:address":"771 SW 70th Way",
    "sg:city":"North Lauderdale",
    "sg:classifiers":[
        {
            "category":"Building & Trades",
            "subcategory":"Landscaping Services",
            "type":"Services"
        }
    ],
    "sg:phone":"+1 954 978 9924",
    "sg:postcode":"33068",
    "sg:province":"FL",
    "sg:tags":[
        "landscape",
        "contractor"
    ],
    "wof:name":"Ecotrim",
    "wof:placetype":"venue"
},
  "geometry": {"coordinates":[-80.21957399999999,26.220442],"type":"Point"}
}