{
  "type": "Feature",
  "properties": {
    "iso:country":"US",
    "sg:address":"2401 W 72nd St Ste 4",
    "sg:city":"Hialeah",
    "sg:classifiers":[
        {
            "category":"Food & Beverages",
            "subcategory":"Liquor & Beverages",
            "type":"Retail Goods"
        },
        {
            "category":"Wholesale",
            "subcategory":"Wine & Distilled Alcoholic Beverages",
            "type":"Manufacturing & Wholesale Goods"
        }
    ],
    "sg:phone":"+1 786 457 2710",
    "sg:postcode":"33016",
    "sg:province":"FL",
    "sg:tags":[
        "broker"
    ],
    "wof:name":"Gigante Liquors V",
    "wof:placetype":"venue"
},
  "geometry": {"coordinates":[-80.331818,25.88789],"type":"Point"}
}