{
  "type": "Feature",
  "properties": {
    "iso:country":"US",
    "sg:address":"1830 Buccaneer Dr",
    "sg:city":"Sarasota",
    "sg:classifiers":[
        {
            "category":"Building & Trades",
            "subcategory":"Plumbing",
            "type":"Services"
        }
    ],
    "sg:phone":"+1 941 922 4271",
    "sg:postcode":"34231",
    "sg:province":"FL",
    "sg:tags":[
        "contractor"
    ],
    "wof:name":"Cde",
    "wof:placetype":"venue"
},
  "geometry": {"coordinates":[-82.51734999999999,27.250413],"type":"Point"}
}