{
  "type": "Feature",
  "properties": {
    "addr:full":"111 S Monroe St Tallahassee FL 32301",
    "addr:housenumber":"111",
    "addr:postcode":"32301",
    "addr:street":"S Monroe St",
    "iso:country":"US",
    "sg:address":"111 S Monroe St",
    "sg:city":"Tallahassee",
    "sg:classifiers":[
        {
            "category":"Professional",
            "subcategory":"Management & Consulting",
            "type":"Services"
        }
    ],
    "sg:phone":"+1 850 681 7266",
    "sg:postcode":"32301",
    "sg:province":"FL",
    "sg:tags":[
        "lobbyist"
    ],
    "wof:name":"Wayne C Watters Inc",
    "wof:placetype":"venue"
},
  "geometry": {"coordinates":[-84.280576,30.440866],"type":"Point"}
}