{
  "type": "Feature",
  "properties": {
    "iso:country":"US",
    "sg:address":"2017 Tangerine St",
    "sg:city":"Orlando",
    "sg:classifiers":[
        {
            "category":"Manufacturing",
            "subcategory":"Petroleum Products",
            "type":"Manufacturing & Wholesale Goods"
        }
    ],
    "sg:phone":"+1 407 898 3460",
    "sg:postcode":"32803",
    "sg:province":"FL",
    "sg:tags":[
        "contract"
    ],
    "wof:name":"Halscott Industries Inc",
    "wof:placetype":"venue"
},
  "geometry": {"coordinates":[-81.355351,28.535821],"type":"Point"}
}