{
  "type": "Feature",
  "properties": {
    "iso:country":"US",
    "sg:address":"130 NE 1st St",
    "sg:city":"Delray Beach",
    "sg:classifiers":[
        {
            "category":"Building & Trades",
            "subcategory":"Plumbing",
            "type":"Services"
        }
    ],
    "sg:phone":"+1 561 499 5710",
    "sg:postcode":"33444",
    "sg:province":"FL",
    "sg:tags":[
        "roofing",
        "c",
        "general",
        "heating",
        "air",
        "conditioning",
        "licensed"
    ],
    "wof:name":"Seacrest Contractors Inc",
    "wof:placetype":"venue"
},
  "geometry": {"coordinates":[-80.07138500000001,26.463388],"type":"Point"}
}