{
  "type": "Feature",
  "properties": {
    "iso:country":"US",
    "sg:address":"870 N Hastings St",
    "sg:city":"Orlando",
    "sg:classifiers":[
        {
            "category":"Organizations",
            "subcategory":"Non-profit Organization",
            "type":"Services"
        }
    ],
    "sg:phone":"+1 407 299 4350",
    "sg:postcode":"32808",
    "sg:province":"FL",
    "sg:website":"www.centralfloridaymca.org",
    "wof:name":"Pine Hills YMCA",
    "wof:placetype":"venue"
},
  "geometry": {"coordinates":[-81.459463,28.554931],"type":"Point"}
}