{
  "type": "Feature",
  "properties": {
    "addr:full":"5620 Cerny Rd Pensacola FL 32526",
    "addr:postcode":"5620;32526",
    "addr:street":"Cerny Rd",
    "iso:country":"US",
    "sg:address":"5620 Cerny Rd",
    "sg:city":"Pensacola",
    "sg:classifiers":[
        {
            "category":"Building & Trades",
            "subcategory":"Construction",
            "type":"Services"
        }
    ],
    "sg:phone":"+1 850 456 0233",
    "sg:postcode":"32526",
    "sg:province":"FL",
    "sg:tags":[
        "house"
    ],
    "wof:name":"Clayton McPhaul Const",
    "wof:placetype":"venue"
},
  "geometry": {"coordinates":[-87.325181,30.448422],"type":"Point"}
}