{
  "type": "Feature",
  "properties": {
    "addr:full":"19 E Noble Ave Williston FL 32696",
    "addr:housenumber":"19",
    "addr:postcode":"32696",
    "addr:street":"E Noble Ave",
    "iso:country":"US",
    "sg:address":"19 E Noble Ave",
    "sg:city":"Williston",
    "sg:phone":"+1 352 528 5251",
    "sg:postcode":"32696",
    "sg:province":"FL",
    "sg:website":"http://www.stihldealer.net/default-dealer-041675.aspx",
    "wof:name":"Lanes Hardware",
    "wof:placetype":"venue"
},
  "geometry": {"coordinates":[-82.447115,29.387412],"type":"Point"}
}