{
  "type": "Feature",
  "properties": {
    "iso:country":"US",
    "sg:address":"1601 Sawgrass Corporate Pkwy",
    "sg:city":"Fort Lauderdale",
    "sg:classifiers":[
        {
            "category":"Professional",
            "subcategory":"Employment Agencies",
            "type":"Services"
        }
    ],
    "sg:phone":"+1 954 858 6000",
    "sg:postcode":"33323",
    "sg:province":"FL",
    "sg:tags":[
        "home",
        "care",
        "health",
        "personnel"
    ],
    "wof:name":"Interim Services",
    "wof:placetype":"venue"
},
  "geometry": {"coordinates":[-80.340237,26.14442],"type":"Point"}
}