{
  "type": "Feature",
  "properties": {
    "addr:full":"2026 Wilna St Fort Myers FL 33901",
    "addr:housenumber":"2026",
    "addr:postcode":"33901",
    "addr:street":"Wilna St",
    "iso:country":"US",
    "sg:address":"2026 Wilna St",
    "sg:city":"Fort Myers",
    "sg:classifiers":[
        {
            "category":"Recreation",
            "type":"Entertainment"
        }
    ],
    "sg:phone":"+1 239 671 3932",
    "sg:postcode":"33901",
    "sg:province":"FL",
    "sg:tags":[
        "party",
        "fishing"
    ],
    "wof:name":"Captain Rick Hilliker",
    "wof:placetype":"venue"
},
  "geometry": {"coordinates":[-81.87573399999999,26.63876],"type":"Point"}
}