{
  "type": "Feature",
  "properties": {
    "iso:country":"US",
    "sg:address":"465 S Croft Ave",
    "sg:city":"Inverness",
    "sg:classifiers":[
        {
            "category":"Sports & Exercise",
            "subcategory":"Gym",
            "type":"Entertainment"
        }
    ],
    "sg:phone":"+1 352 726 2424",
    "sg:postcode":"34453",
    "sg:province":"FL",
    "sg:tags":[
        "center",
        "fitness"
    ],
    "wof:name":"Curves For Women",
    "wof:placetype":"venue"
},
  "geometry": {"coordinates":[-82.386079,28.854355],"type":"Point"}
}