{
  "type": "Feature",
  "properties": {
    "addr:full":"1212 8th St SE Miami FL 33135",
    "addr:housenumber":"1212",
    "addr:postcode":"33135",
    "addr:street":"8Th St Se",
    "iso:country":"US",
    "sg:address":"1212 8th St SE",
    "sg:city":"Miami",
    "sg:classifiers":[
        {
            "category":"Personal",
            "subcategory":"Beauty Salon",
            "type":"Services"
        }
    ],
    "sg:phone":"+1 305 854 5888",
    "sg:postcode":"33135",
    "sg:province":"FL",
    "wof:name":"Kati's Salon",
    "wof:placetype":"venue"
},
  "geometry": {"coordinates":[-80.215423,25.765842],"type":"Point"}
}