{
  "type": "Feature",
  "properties": {
    "iso:country":"US",
    "sg:address":"1304 63rd St NW",
    "sg:city":"Bradenton",
    "sg:classifiers":[
        {
            "category":"Building & Trades",
            "subcategory":"Landscaping Services",
            "type":"Services"
        }
    ],
    "sg:phone":"+1 941 761 2388",
    "sg:postcode":"34209",
    "sg:province":"FL",
    "sg:tags":[
        "landscape"
    ],
    "wof:name":"Burdette & Assoc Landscap",
    "wof:placetype":"venue"
},
  "geometry": {"coordinates":[-82.624302,27.511239],"type":"Point"}
}