{
  "type": "Feature",
  "properties": {
    "addr:full":"3074 Pinecrest St Sarasota FL 34239",
    "addr:housenumber":"3074",
    "addr:postcode":"34239",
    "addr:street":"Pinecrest St",
    "iso:country":"US",
    "sg:address":"3074 Pinecrest St",
    "sg:city":"Sarasota",
    "sg:classifiers":[
        {
            "category":"Real Estate",
            "subcategory":"Real Estate Agent",
            "type":"Services"
        }
    ],
    "sg:phone":"+1 941 921 1934",
    "sg:postcode":"34239",
    "sg:province":"FL",
    "sg:tags":[
        "inspection"
    ],
    "wof:name":"Larry Johnson's Inspection Tm",
    "wof:placetype":"venue"
},
  "geometry": {"coordinates":[-82.508726,27.302349],"type":"Point"}
}