{
  "type": "Feature",
  "properties": {
    "iso:country":"US",
    "sg:address":"7652 Ashley Park Ct Ste 305",
    "sg:city":"Orlando",
    "sg:classifiers":[
        {
            "category":"Health Services",
            "subcategory":"Doctor",
            "type":"Services"
        }
    ],
    "sg:phone":"+1 407 299 7333",
    "sg:postcode":"32835",
    "sg:province":"FL",
    "sg:tags":[
        "physician",
        "family",
        "practice",
        "surgeons",
        "medicine",
        "dermatology",
        "surgeon"
    ],
    "wof:name":"Michael M Gutierrez Pa",
    "wof:placetype":"venue"
},
  "geometry": {"coordinates":[-81.485816,28.507558],"type":"Point"}
}