{
  "type": "Feature",
  "properties": {
    "addr:full":"301 Northpoint Pkwy West Palm Beach FL 33407",
    "addr:housenumber":"301",
    "addr:postcode":"33407",
    "addr:street":"Northpoint Pkwy",
    "iso:country":"US",
    "sg:address":"301 Northpoint Pkwy",
    "sg:city":"West Palm Beach",
    "sg:classifiers":[
        {
            "category":"Shopping",
            "subcategory":"Pharmacy",
            "type":"Retail Goods"
        }
    ],
    "sg:phone":"+1 561 689 6355",
    "sg:postcode":"33407",
    "sg:province":"FL",
    "wof:name":"Integrity Pharmacy",
    "wof:placetype":"venue"
},
  "geometry": {"coordinates":[-80.098248,26.760708],"type":"Point"}
}