{
  "type": "Feature",
  "properties": {
    "addr:full":"708 W Oakland Park Blvd Wilton Manors FL 33311",
    "addr:housenumber":"708",
    "addr:postcode":"33311",
    "addr:street":"W Oakland Park Blvd",
    "iso:country":"US",
    "sg:address":"708 W Oakland Park Blvd",
    "sg:city":"Wilton Manors",
    "sg:classifiers":[
        {
            "category":"Autos & Motor Vehicles",
            "subcategory":"Automobile Sales",
            "type":"Retail Goods"
        }
    ],
    "sg:phone":"+1 954 561 7000",
    "sg:postcode":"33311",
    "sg:province":"FL",
    "sg:tags":[
        "truck"
    ],
    "wof:name":"Car Search Inc",
    "wof:placetype":"venue"
},
  "geometry": {"coordinates":[-80.152475,26.166282],"type":"Point"}
}