{
  "type": "Feature",
  "properties": {
    "addr:full":"750 Office Plaza Blvd Kissimmee FL 34744",
    "addr:housenumber":"750",
    "addr:postcode":"34744",
    "addr:street":"Office Plaza Blvd",
    "iso:country":"US",
    "sg:address":"750 Office Plaza Blvd",
    "sg:city":"Kissimmee",
    "sg:classifiers":[
        {
            "category":"Travel",
            "subcategory":"Travel Agent",
            "type":"Entertainment"
        }
    ],
    "sg:phone":"+1 407 344 9031",
    "sg:postcode":"34744",
    "sg:province":"FL",
    "sg:tags":[
        "agency"
    ],
    "wof:name":"Sylvette Vacations",
    "wof:placetype":"venue"
},
  "geometry": {"coordinates":[-81.35590500000001,28.284705],"type":"Point"}
}