{
  "type": "Feature",
  "properties": {
    "addr:full":"2131 NW 79th Ave Doral FL 33122",
    "addr:housenumber":"2131",
    "addr:postcode":"33122",
    "addr:street":"Nw 79Th Ave",
    "iso:country":"US",
    "sg:address":"2131 NW 79th Ave",
    "sg:city":"Doral",
    "sg:classifiers":[
        {
            "category":"Professional",
            "subcategory":"Lawyer & Legal Services",
            "type":"Services"
        }
    ],
    "sg:phone":"+1 305 599 0839",
    "sg:postcode":"33122",
    "sg:province":"FL",
    "sg:tags":[
        "company",
        "incorporating"
    ],
    "wof:name":"Fastkit Corporate Kits",
    "wof:placetype":"venue"
},
  "geometry": {"coordinates":[-80.325129,25.79618],"type":"Point"}
}