{
  "type": "Feature",
  "properties": {
    "addr:full":"2400 9th St S St Petersburg FL 33705",
    "addr:housenumber":"2400",
    "addr:postcode":"33705",
    "addr:street":"9Th St S",
    "iso:country":"US",
    "sg:address":"2400 9th St S",
    "sg:city":"St Petersburg",
    "sg:classifiers":[
        {
            "category":"Personal",
            "subcategory":"Beauty Salon",
            "type":"Services"
        }
    ],
    "sg:phone":"+1 727 895 7117",
    "sg:postcode":"33705",
    "sg:province":"FL",
    "sg:tags":[
        "shop"
    ],
    "wof:name":"Preferred Performance",
    "wof:placetype":"venue"
},
  "geometry": {"coordinates":[-82.646546,27.744822],"type":"Point"}
}