{
  "type": "Feature",
  "properties": {
    "iso:country":"US",
    "sg:address":"135 Evernia St",
    "sg:city":"Jupiter",
    "sg:classifiers":[
        {
            "category":"Building & Trades",
            "subcategory":"Construction",
            "type":"Services"
        }
    ],
    "sg:phone":"+1 561 745 0555",
    "sg:postcode":"33458",
    "sg:province":"FL",
    "sg:tags":[
        "hanging",
        "contractor"
    ],
    "wof:name":"Randall J Klaker Interiors",
    "wof:placetype":"venue"
},
  "geometry": {"coordinates":[-80.09529999999999,26.936892],"type":"Point"}
}