{
  "type": "Feature",
  "properties": {
    "iso:country":"US",
    "sg:address":"280 State Road 436",
    "sg:city":"Casselberry",
    "sg:classifiers":[
        {
            "category":"Restaurant",
            "type":"Food & Drink"
        }
    ],
    "sg:phone":"+1 407 332 1599",
    "sg:postcode":"32707",
    "sg:province":"FL",
    "wof:name":"Green Parrot the",
    "wof:placetype":"venue"
},
  "geometry": {"coordinates":[-81.33560199999999,28.6572],"type":"Point"}
}