{
  "type": "Feature",
  "properties": {
    "iso:country":"US",
    "sg:address":"221 Miracle Mile",
    "sg:city":"Miami",
    "sg:classifiers":[
        {
            "category":"Professional",
            "subcategory":"Art Services",
            "type":"Services"
        }
    ],
    "sg:phone":"+1 305 866 6132",
    "sg:postcode":"33134",
    "sg:province":"FL",
    "sg:tags":[
        "designer",
        "display",
        "producer"
    ],
    "wof:name":"Paper & Design Usa Corp",
    "wof:placetype":"venue"
},
  "geometry": {"coordinates":[-80.259049,25.749565],"type":"Point"}
}