{
  "type": "Feature",
  "properties": {
    "addr:full":"3041 NW 7th St Ste 100 Miami FL 33125",
    "addr:housenumber":"3041",
    "addr:postcode":"33125",
    "addr:street":"Nw 7Th St Ste 100",
    "iso:country":"US",
    "sg:address":"3041 NW 7th St Ste 100",
    "sg:city":"Miami",
    "sg:classifiers":[
        {
            "category":"Education",
            "subcategory":"Vocational School",
            "type":"Public Place"
        }
    ],
    "sg:phone":"+1 305 541 2508",
    "sg:postcode":"33125",
    "sg:province":"FL",
    "sg:tags":[
        "supplies-wholesale",
        "manufacturer"
    ],
    "wof:name":"Educational Products Inc",
    "wof:placetype":"venue"
},
  "geometry": {"coordinates":[-80.244359,25.779314],"type":"Point"}
}