{
  "type": "Feature",
  "properties": {
    "iso:country":"US",
    "sg:address":"1610 NW 106th Ln",
    "sg:city":"Pompano Beach",
    "sg:classifiers":[
        {
            "category":"Banks & Credit Unions",
            "subcategory":"Investment Brokerage",
            "type":"Services"
        }
    ],
    "sg:phone":"+1 954 796 7181",
    "sg:postcode":"33071",
    "sg:province":"FL",
    "sg:tags":[
        "commodity",
        "contract"
    ],
    "wof:name":"Gingsberg R J Brokerage",
    "wof:placetype":"venue"
},
  "geometry": {"coordinates":[-80.26780599999999,26.250618],"type":"Point"}
}