{
  "type": "Feature",
  "properties": {
    "iso:country":"US",
    "sg:address":"2454 N Mcmullen Booth Rd",
    "sg:city":"Clearwater",
    "sg:classifiers":[
        {
            "category":"Shopping",
            "subcategory":"Department Store",
            "type":"Retail Goods"
        },
        {
            "category":"Home & Garden",
            "subcategory":"Hardware",
            "type":"Retail Goods"
        }
    ],
    "sg:phone":"+1 727 726 1677",
    "sg:postcode":"33759",
    "sg:province":"FL",
    "sg:tags":[
        "equipment",
        "cleaner",
        "janitor",
        "supply"
    ],
    "wof:name":"Spirit Cleaners",
    "wof:placetype":"venue"
},
  "geometry": {"coordinates":[-82.708845,28.009851],"type":"Point"}
}