{
  "type": "Feature",
  "properties": {
    "addr:full":"1561 Bridgeport Cir Rockledge FL 32955",
    "addr:housenumber":"1561",
    "addr:postcode":"32955",
    "addr:street":"Bridgeport Cir",
    "iso:country":"US",
    "sg:address":"1561 Bridgeport Cir",
    "sg:city":"Rockledge",
    "sg:classifiers":[
        {
            "category":"Social Services",
            "subcategory":"Child Care",
            "type":"Services"
        }
    ],
    "sg:phone":"+1 321 633 0674",
    "sg:postcode":"32955",
    "sg:province":"FL",
    "sg:tags":[
        "nursery",
        "day"
    ],
    "wof:name":"Mindworks Early Learning Inc",
    "wof:placetype":"venue"
},
  "geometry": {"coordinates":[-80.743921,28.305866],"type":"Point"}
}