{
  "type": "Feature",
  "properties": {
    "addr:full":"181 Oxford Rd Casselberry FL 32730",
    "addr:housenumber":"181",
    "addr:postcode":"32730",
    "addr:street":"Oxford Rd",
    "iso:country":"US",
    "sg:address":"181 Oxford Rd",
    "sg:city":"Casselberry",
    "sg:classifiers":[
        {
            "category":"Shopping",
            "subcategory":"Computers & Home Electronics",
            "type":"Retail Goods"
        }
    ],
    "sg:phone":"+1 407 265 2005",
    "sg:postcode":"32730",
    "sg:province":"FL",
    "sg:tags":[
        "hardware",
        "sales",
        "software"
    ],
    "wof:name":"Tiger Computer",
    "wof:placetype":"venue"
},
  "geometry": {"coordinates":[-81.339026,28.656897],"type":"Point"}
}