{
  "type": "Feature",
  "properties": {
    "addr:full":"1835 NW 112th Ave Miami FL 33172",
    "addr:housenumber":"1835",
    "addr:postcode":"33172",
    "addr:street":"Nw 112Th Ave",
    "iso:country":"US",
    "sg:address":"1835 NW 112th Ave",
    "sg:city":"Miami",
    "sg:classifiers":[
        {
            "category":"Autos & Motor Vehicles",
            "subcategory":"Auto Supplies",
            "type":"Retail Goods"
        }
    ],
    "sg:phone":"+1 305 639 2183",
    "sg:postcode":"33172",
    "sg:province":"FL",
    "sg:tags":[
        "tire"
    ],
    "sg:website":"www.wheelsperformance.com",
    "wof:name":"Wheels Performance",
    "wof:placetype":"venue"
},
  "geometry": {"coordinates":[-80.376588,25.791006],"type":"Point"}
}