{
  "type": "Feature",
  "properties": {
    "iso:country":"US",
    "sg:address":"2750 W 68th St Ste 103",
    "sg:city":"Hialeah",
    "sg:classifiers":[
        {
            "category":"Shopping",
            "subcategory":"Beauty & Cosmetics",
            "type":"Retail Goods"
        }
    ],
    "sg:phone":"+1 305 819 8300",
    "sg:postcode":"33016",
    "sg:province":"FL",
    "sg:tags":[
        "supply"
    ],
    "wof:name":"Florida Beauty Supply",
    "wof:placetype":"venue"
},
  "geometry": {"coordinates":[-80.33861899999999,25.88397],"type":"Point"}
}