{
  "type": "Feature",
  "properties": {
    "addr:full":"5267 Edgewood Dr Lake Worth FL 33467",
    "addr:housenumber":"5267",
    "addr:postcode":"33467",
    "addr:street":"Edgewood Dr",
    "iso:country":"US",
    "sg:address":"5267 Edgewood Dr",
    "sg:city":"Lake Worth",
    "sg:classifiers":[
        {
            "category":"Retail",
            "subcategory":"Car Wash",
            "type":"Services"
        }
    ],
    "sg:phone":"+1 561 308 6350",
    "sg:postcode":"33467",
    "sg:province":"FL",
    "sg:tags":[
        "automobile",
        "detail",
        "clean"
    ],
    "wof:name":"Show Room Shine",
    "wof:placetype":"venue"
},
  "geometry": {"coordinates":[-80.171644,26.601303],"type":"Point"}
}