{
  "type": "Feature",
  "properties": {
    "iso:country":"US",
    "sg:address":"1230 N Tamiami Trl",
    "sg:city":"Fort Myers",
    "sg:classifiers":[
        {
            "category":"Retail",
            "subcategory":"Veterinary Services",
            "type":"Services"
        }
    ],
    "sg:phone":"+1 239 995 2883",
    "sg:postcode":"33903",
    "sg:province":"FL",
    "wof:name":"North Shore Animal Hospital",
    "wof:placetype":"venue"
},
  "geometry": {"coordinates":[-81.881311,26.668756],"type":"Point"}
}