{
  "type": "Feature",
  "properties": {
    "addr:full":"1841 SW Bellevue Ave Port St Lucie FL 34953",
    "addr:housenumber":"1841",
    "addr:postcode":"34953",
    "addr:street":"Sw Bellevue Ave",
    "iso:country":"US",
    "sg:address":"1841 SW Bellevue Ave",
    "sg:city":"Port St Lucie",
    "sg:classifiers":[
        {
            "category":"Home & Garden",
            "subcategory":"Home Furnishings",
            "type":"Retail Goods"
        }
    ],
    "sg:phone":"+1 772 344 8482",
    "sg:postcode":"34953",
    "sg:province":"FL",
    "sg:tags":[
        "lighting",
        "fixture"
    ],
    "wof:name":"Helene's Nightlight Inc",
    "wof:placetype":"venue"
},
  "geometry": {"coordinates":[-80.403594,27.292189],"type":"Point"}
}