{
  "type": "Feature",
  "properties": {
    "iso:country":"US",
    "sg:address":"14 Bogey Dr",
    "sg:city":"Winter Haven",
    "sg:classifiers":[
        {
            "category":"Banks & Credit Unions",
            "subcategory":"Bank",
            "type":"Services"
        }
    ],
    "sg:phone":"+1 863 326 1830",
    "sg:postcode":"33881",
    "sg:province":"FL",
    "sg:tags":[
        "loan"
    ],
    "wof:name":"A L I",
    "wof:placetype":"venue"
},
  "geometry": {"coordinates":[-81.655991,28.028187],"type":"Point"}
}