{
  "type": "Feature",
  "properties": {
    "addr:full":"4346 Coleman Rd Jacksonville FL 32257",
    "addr:housenumber":"4346",
    "addr:postcode":"32257",
    "addr:street":"Coleman Rd",
    "iso:country":"US",
    "sg:address":"4346 Coleman Rd",
    "sg:city":"Jacksonville",
    "sg:classifiers":[
        {
            "category":"Retail",
            "subcategory":"Repair Shop",
            "type":"Services"
        }
    ],
    "sg:phone":"+1 904 262 1800",
    "sg:postcode":"32257",
    "sg:province":"FL",
    "sg:tags":[
        "related"
    ],
    "wof:name":"Royal Auto Repair",
    "wof:placetype":"venue"
},
  "geometry": {"coordinates":[-81.600131,30.182382],"type":"Point"}
}