{
  "type": "Feature",
  "properties": {
    "iso:country":"US",
    "sg:address":"4668 Ashton Rd",
    "sg:city":"Sarasota",
    "sg:classifiers":[
        {
            "category":"Home & Garden",
            "subcategory":"Carpets & Floor Coverings",
            "type":"Retail Goods"
        }
    ],
    "sg:phone":"+1 941 927 8910",
    "sg:postcode":"34233",
    "sg:province":"FL",
    "sg:tags":[
        "laying",
        "contractor"
    ],
    "wof:name":"Carpet Crafters",
    "wof:placetype":"venue"
},
  "geometry": {"coordinates":[-82.479665,27.276493],"type":"Point"}
}