{
  "type": "Feature",
  "properties": {
    "iso:country":"US",
    "sg:address":"500 NW 34th St",
    "sg:city":"Pompano Beach",
    "sg:classifiers":[
        {
            "category":"Professional",
            "subcategory":"Business Services",
            "type":"Services"
        }
    ],
    "sg:phone":"+1 954 781 4033",
    "sg:postcode":"33064",
    "sg:province":"FL",
    "wof:name":"EDS",
    "wof:placetype":"venue"
},
  "geometry": {"coordinates":[-80.12996,26.272381],"type":"Point"}
}