{
  "type": "Feature",
  "properties": {
    "iso:country":"US",
    "sg:address":"13861 Sand Crane Dr",
    "sg:city":"Palm Beach Gardens",
    "sg:classifiers":[
        {
            "category":"Banks & Credit Unions",
            "subcategory":"Bank",
            "type":"Services"
        }
    ],
    "sg:phone":"+1 561 622 5445",
    "sg:postcode":"33418",
    "sg:province":"FL",
    "sg:tags":[
        "short",
        "institution",
        "business"
    ],
    "wof:name":"Pilot Funding Corp",
    "wof:placetype":"venue"
},
  "geometry": {"coordinates":[-80.13729499999999,26.880499],"type":"Point"}
}