{
  "type": "Feature",
  "properties": {
    "iso:country":"US",
    "sg:address":"150 E Palmetto Park Rd",
    "sg:city":"Boca Raton",
    "sg:classifiers":[
        {
            "category":"Professional",
            "subcategory":"Management & Consulting",
            "type":"Services"
        }
    ],
    "sg:phone":"+1 561 368 7414",
    "sg:postcode":"33432",
    "sg:province":"FL",
    "sg:tags":[
        "life",
        "carrier",
        "insurance"
    ],
    "wof:name":"First Financial Resources",
    "wof:placetype":"venue"
},
  "geometry": {"coordinates":[-80.084585,26.350445],"type":"Point"}
}