{
  "type": "Feature",
  "properties": {
    "iso:country":"US",
    "sg:address":"4131 Stirling Rd",
    "sg:city":"Davie",
    "sg:classifiers":[
        {
            "category":"Home & Garden",
            "subcategory":"Building Materials",
            "type":"Retail Goods"
        },
        {
            "category":"Wholesale",
            "subcategory":"Home Furnishings",
            "type":"Manufacturing & Wholesale Goods"
        }
    ],
    "sg:phone":"+1 954 316 9111",
    "sg:postcode":"33314",
    "sg:province":"FL",
    "sg:tags":[
        "closet",
        "accessory"
    ],
    "wof:name":"Behind Closed Doors Inc",
    "wof:placetype":"venue"
},
  "geometry": {"coordinates":[-80.20276200000001,26.047016],"type":"Point"}
}