{
  "type": "Feature",
  "properties": {
    "iso:country":"US",
    "sg:address":"7710 NW 163rd St",
    "sg:city":"Hialeah",
    "sg:classifiers":[
        {
            "category":"Manufacturing",
            "subcategory":"Wood Products",
            "type":"Manufacturing & Wholesale Goods"
        }
    ],
    "sg:phone":"+1 305 819 3874",
    "sg:postcode":"33016",
    "sg:province":"FL",
    "sg:tags":[
        "container",
        "mfg"
    ],
    "wof:name":"Bunches of Baskets & More",
    "wof:placetype":"venue"
},
  "geometry": {"coordinates":[-80.325765,25.92167],"type":"Point"}
}