{
  "type": "Feature",
  "properties": {
    "addr:full":"63 Marsh Cove Dr Ponte Vedra Beach FL 32082",
    "addr:housenumber":"63",
    "addr:postcode":"32082",
    "addr:street":"Marsh Cove Dr",
    "iso:country":"US",
    "sg:address":"63 Marsh Cove Dr",
    "sg:city":"Ponte Vedra Beach",
    "sg:classifiers":[
        {
            "category":"Retail",
            "subcategory":"Auto Repair",
            "type":"Services"
        }
    ],
    "sg:phone":"+1 904 223 0208",
    "sg:postcode":"32082",
    "sg:province":"FL",
    "sg:tags":[
        "general"
    ],
    "wof:name":"Seroyer Automotive Group",
    "wof:placetype":"venue"
},
  "geometry": {"coordinates":[-81.394119,30.248139],"type":"Point"}
}