{
  "type": "Feature",
  "properties": {
    "iso:country":"US",
    "sg:address":"3435 Craftsman Blvd",
    "sg:city":"Lakeland",
    "sg:classifiers":[
        {
            "category":"Manufacturing",
            "subcategory":"Metals",
            "type":"Manufacturing & Wholesale Goods"
        }
    ],
    "sg:phone":"+1 863 665 5240",
    "sg:postcode":"33803",
    "sg:province":"FL",
    "sg:tags":[
        "structural",
        "fabrication",
        "nonresidential"
    ],
    "wof:name":"Mimbs",
    "wof:placetype":"venue"
},
  "geometry": {"coordinates":[-81.88657600000001,28.007822],"type":"Point"}
}