{
  "type": "Feature",
  "properties": {
    "addr:full":"3901 N 29th Ave Hollywood FL 33020",
    "addr:housenumber":"3901",
    "addr:postcode":"33020",
    "addr:street":"N 29Th Ave",
    "iso:country":"US",
    "sg:address":"3901 N 29th Ave",
    "sg:city":"Hollywood",
    "sg:classifiers":[
        {
            "category":"Transit Center",
            "subcategory":"Freight",
            "type":"Transportation"
        }
    ],
    "sg:phone":"+1 954 923 0952",
    "sg:postcode":"33020",
    "sg:province":"FL",
    "sg:tags":[
        "forwarding"
    ],
    "wof:name":"E Z Forwarding",
    "wof:placetype":"venue"
},
  "geometry": {"coordinates":[-80.16580999999999,26.041901],"type":"Point"}
}