{
  "type": "Feature",
  "properties": {
    "iso:country":"US",
    "sg:address":"3893 NW 67th Way",
    "sg:city":"Lauderhill",
    "sg:classifiers":[
        {
            "category":"Manufacturing",
            "subcategory":"Metals",
            "type":"Manufacturing & Wholesale Goods"
        }
    ],
    "sg:phone":"+1 954 288 6827",
    "sg:postcode":"33319",
    "sg:province":"FL",
    "sg:tags":[
        "stamping"
    ],
    "wof:name":"J & S Tool And Engineering",
    "wof:placetype":"venue"
},
  "geometry": {"coordinates":[-80.23950600000001,26.173505],"type":"Point"}
}