{
  "type": "Feature",
  "properties": {
    "iso:country":"US",
    "sg:address":"1932 SE Erwin Rd",
    "sg:city":"Port Saint Lucie",
    "sg:classifiers":[
        {
            "category":"Restaurant",
            "type":"Food & Drink"
        }
    ],
    "sg:phone":"+1 772 337 0810",
    "sg:postcode":"34952",
    "sg:province":"FL",
    "sg:tags":[
        "eating"
    ],
    "wof:name":"Silver Platter Entrees Inc",
    "wof:placetype":"venue"
},
  "geometry": {"coordinates":[-80.294967,27.262167],"type":"Point"}
}