{
  "type": "Feature",
  "properties": {
    "iso:country":"US",
    "sg:address":"13767 SW 139th Ct",
    "sg:city":"Miami",
    "sg:classifiers":[
        {
            "category":"Home & Garden",
            "subcategory":"Building Materials",
            "type":"Retail Goods"
        },
        {
            "category":"Manufacturing",
            "subcategory":"Building Materials",
            "type":"Manufacturing & Wholesale Goods"
        }
    ],
    "sg:phone":"+1 305 266 0740",
    "sg:postcode":"33186",
    "sg:province":"FL",
    "sg:tags":[
        "materials-wholesale",
        "manufacturer"
    ],
    "wof:name":"Foreign Commerce Inc",
    "wof:placetype":"venue"
},
  "geometry": {"coordinates":[-80.41983500000001,25.633707],"type":"Point"}
}