{
  "type": "Feature",
  "properties": {
    "iso:country":"US",
    "sg:address":"6303 Da Lisa Rd",
    "sg:city":"Milton",
    "sg:classifiers":[
        {
            "category":"Utilities",
            "subcategory":"Refuse",
            "type":"Services"
        }
    ],
    "sg:phone":"+1 850 934 9647",
    "sg:postcode":"32583",
    "sg:province":"FL",
    "sg:tags":[
        "garbage",
        "collection"
    ],
    "wof:name":"SUTTON Environmental",
    "wof:placetype":"venue"
},
  "geometry": {"coordinates":[-87.06254800000001,30.585339],"type":"Point"}
}