{
  "type": "Feature",
  "properties": {
    "iso:country":"US",
    "sg:address":"230 Brewer Ave",
    "sg:city":"Winter Park",
    "sg:classifiers":[
        {
            "category":"Banks & Credit Unions",
            "subcategory":"Financial Services",
            "type":"Services"
        }
    ],
    "sg:phone":"+1 407 629 2282",
    "sg:postcode":"32789",
    "sg:province":"FL",
    "sg:tags":[
        "broker",
        "mortgage"
    ],
    "sg:website":"www.fortenight.com",
    "wof:name":"Fortenight Mortgage Corp",
    "wof:placetype":"venue"
},
  "geometry": {"coordinates":[-81.33879899999999,28.6001],"type":"Point"}
}