{
  "type": "Feature",
  "properties": {
    "addr:full":"4508 Woodside Rd Sarasota FL 34242",
    "addr:housenumber":"4508",
    "addr:postcode":"34242",
    "addr:street":"Woodside Rd",
    "iso:country":"US",
    "sg:address":"4508 Woodside Rd",
    "sg:city":"Sarasota",
    "sg:classifiers":[
        {
            "category":"Wholesale",
            "subcategory":"Electrical",
            "type":"Manufacturing & Wholesale Goods"
        }
    ],
    "sg:phone":"+1 941 312 0800",
    "sg:postcode":"34242",
    "sg:province":"FL",
    "sg:tags":[
        "equipment"
    ],
    "wof:name":"Nite-Lite Landscape Lighting",
    "wof:placetype":"venue"
},
  "geometry": {"coordinates":[-82.55611399999999,27.285508],"type":"Point"}
}