{
  "type": "Feature",
  "properties": {
    "iso:country":"US",
    "sg:address":"6201 N Nebraska Ave",
    "sg:city":"Tampa",
    "sg:classifiers":[
        {
            "category":"Autos & Motor Vehicles",
            "subcategory":"Automobile Sales",
            "type":"Retail Goods"
        }
    ],
    "sg:phone":"+1 813 238 8451",
    "sg:postcode":"33604",
    "sg:province":"FL",
    "sg:tags":[
        "used",
        "truck"
    ],
    "wof:name":"Terry Cramer & Sons Inc",
    "wof:placetype":"venue"
},
  "geometry": {"coordinates":[-82.45131000000001,28.004303],"type":"Point"}
}