{
  "type": "Feature",
  "properties": {
    "iso:country":"US",
    "sg:address":"2317 S Volusia Ave",
    "sg:city":"Orange City",
    "sg:classifiers":[
        {
            "category":"Real Estate",
            "subcategory":"Real Estate Operator",
            "type":"Services"
        }
    ],
    "sg:phone":"+1 386 775 7639",
    "sg:postcode":"32763",
    "sg:province":"FL",
    "sg:tags":[
        "apartment"
    ],
    "wof:name":"Oakshade Apartments",
    "wof:placetype":"venue"
},
  "geometry": {"coordinates":[-81.301536,28.925476],"type":"Point"}
}