{
  "type": "Feature",
  "properties": {
    "iso:country":"US",
    "sg:address":"223 W Washington St",
    "sg:city":"Chattahoochee",
    "sg:classifiers":[
        {
            "category":"Autos & Motor Vehicles",
            "subcategory":"Fuel & Gas Station",
            "type":"Retail Goods"
        }
    ],
    "sg:phone":"+1 850 663 9212",
    "sg:postcode":"32324",
    "sg:province":"FL",
    "sg:tags":[
        "oil"
    ],
    "wof:name":"Rentz Service Station",
    "wof:placetype":"venue"
},
  "geometry": {"coordinates":[-84.845097,30.704881],"type":"Point"}
}