{
  "type": "Feature",
  "properties": {
    "iso:country":"US",
    "sg:address":"29928 Overseas Hwy",
    "sg:city":"Big Pine Key",
    "sg:classifiers":[
        {
            "category":"Personal",
            "subcategory":"Tattoo Parlor",
            "type":"Services"
        }
    ],
    "sg:phone":"+1 305 296 4727",
    "sg:postcode":"33043",
    "sg:province":"FL",
    "sg:tags":[
        "tattooing"
    ],
    "wof:name":"Goldies Southernmost Tattooing",
    "wof:placetype":"venue"
},
  "geometry": {"coordinates":[-81.36459000000001,24.669698],"type":"Point"}
}