{
  "type": "Feature",
  "properties": {
    "addr:full":"109 Galiano St West Palm Beach FL 33411",
    "addr:housenumber":"109",
    "addr:postcode":"33411",
    "addr:street":"Galiano St",
    "iso:country":"US",
    "sg:address":"109 Galiano St",
    "sg:city":"West Palm Beach",
    "sg:classifiers":[
        {
            "category":"Manufacturing",
            "subcategory":"Tools & Machinery",
            "type":"Manufacturing & Wholesale Goods"
        }
    ],
    "sg:phone":"+1 561 644 1048",
    "sg:postcode":"33411",
    "sg:province":"FL",
    "sg:tags":[
        "control",
        "environmental",
        "mfg"
    ],
    "wof:name":"Macs Atomic Power Washing",
    "wof:placetype":"venue"
},
  "geometry": {"coordinates":[-80.22103799999999,26.709506],"type":"Point"}
}