{
  "type": "Feature",
  "properties": {
    "addr:full":"1254 S Broad St Brooksville FL 34601",
    "addr:housenumber":"1254",
    "addr:postcode":"34601",
    "addr:street":"S Broad St",
    "iso:country":"US",
    "sg:address":"1254 S Broad St",
    "sg:city":"Brooksville",
    "sg:classifiers":[
        {
            "category":"Food & Beverages",
            "subcategory":"Specialty",
            "type":"Retail Goods"
        }
    ],
    "sg:phone":"+1 352 796 9798",
    "sg:postcode":"34601",
    "sg:province":"FL",
    "sg:tags":[
        "a",
        "cafe",
        "health",
        "diet",
        "operates"
    ],
    "wof:name":"Brooksville Natural Foods Inc",
    "wof:placetype":"venue"
},
  "geometry": {"coordinates":[-82.403282,28.54118],"type":"Point"}
}