{
  "type": "Feature",
  "properties": {
    "addr:full":"4366 Avalon Blvd Milton FL 32583",
    "addr:housenumber":"4366",
    "addr:postcode":"32583",
    "addr:street":"Avalon Blvd",
    "iso:country":"US",
    "sg:address":"4366 Avalon Blvd",
    "sg:city":"Milton",
    "sg:classifiers":[
        {
            "category":"Shopping",
            "subcategory":"Florist",
            "type":"Retail Goods"
        }
    ],
    "sg:phone":"+1 850 623 4864",
    "sg:postcode":"32583",
    "sg:province":"FL",
    "wof:name":"Avalon Florist",
    "wof:placetype":"venue"
},
  "geometry": {"coordinates":[-87.081407,30.592521],"type":"Point"}
}