{
  "type": "Feature",
  "properties": {
    "iso:country":"US",
    "sg:address":"968 SW 81st Ave",
    "sg:city":"North Lauderdale",
    "sg:classifiers":[
        {
            "category":"Shopping",
            "subcategory":"Computers & Home Electronics",
            "type":"Retail Goods"
        }
    ],
    "sg:phone":"+1 954 933 0900",
    "sg:postcode":"33068",
    "sg:province":"FL",
    "sg:tags":[
        "parts",
        "supply"
    ],
    "wof:name":"Softbrix Technologies Inc",
    "wof:placetype":"venue"
},
  "geometry": {"coordinates":[-80.236574,26.216357],"type":"Point"}
}