{
  "type": "Feature",
  "properties": {
    "iso:country":"US",
    "sg:address":"1651 Sherman St",
    "sg:city":"Orlando",
    "sg:classifiers":[
        {
            "category":"Health Services",
            "subcategory":"Doctor",
            "type":"Services"
        }
    ],
    "sg:phone":"+1 407 249 1234",
    "sg:postcode":"32828",
    "sg:province":"FL",
    "sg:tags":[
        "medical"
    ],
    "wof:name":"First Choice Pediatrics I",
    "wof:placetype":"venue"
},
  "geometry": {"coordinates":[-81.157989,28.563952],"type":"Point"}
}