{
  "type": "Feature",
  "properties": {
    "addr:full":"4712 NW 22nd St Coconut Creek FL 33063",
    "addr:housenumber":"4712",
    "addr:postcode":"33063",
    "addr:street":"Nw 22Nd St",
    "iso:country":"US",
    "sg:address":"4712 NW 22nd St",
    "sg:city":"Coconut Creek",
    "sg:classifiers":[
        {
            "category":"Shopping",
            "subcategory":"Gifts & Souvenirs",
            "type":"Retail Goods"
        }
    ],
    "sg:phone":"+1 954 984 9087",
    "sg:postcode":"33063",
    "sg:province":"FL",
    "sg:tags":[
        "basket",
        "parcel"
    ],
    "wof:name":"Sea Spray Gifts",
    "wof:placetype":"venue"
},
  "geometry": {"coordinates":[-80.189859,26.254418],"type":"Point"}
}