{
  "type": "Feature",
  "properties": {
    "iso:country":"US",
    "sg:address":"1015 Sunshine Ln Ste 103C",
    "sg:city":"Altamonte Springs",
    "sg:classifiers":[
        {
            "category":"Building & Trades",
            "subcategory":"Locksmith",
            "type":"Services"
        }
    ],
    "sg:phone":"+1 407 260 2727",
    "sg:postcode":"32714",
    "sg:province":"FL",
    "sg:tags":[
        "key"
    ],
    "sg:website":"www.orlando.org|www.libertylocks...",
    "wof:name":"Liberty Locksmiths",
    "wof:placetype":"venue"
},
  "geometry": {"coordinates":[-81.423497,28.655525],"type":"Point"}
}