{
  "type": "Feature",
  "properties": {
    "addr:full":"1671 Alton Rd Miami Beach FL 33119",
    "addr:housenumber":"1671",
    "addr:postcode":"33119",
    "addr:street":"Alton Rd",
    "iso:country":"US",
    "sg:address":"1671 Alton Rd",
    "sg:city":"Miami Beach",
    "sg:classifiers":[
        {
            "category":"Restaurant",
            "type":"Food & Drink"
        }
    ],
    "sg:phone":"+1 305 531 1880",
    "sg:postcode":"33119",
    "sg:province":"FL",
    "sg:tags":[
        "sushi",
        "bar",
        "chinese"
    ],
    "sg:website":"www.yummysobe.com",
    "wof:name":"Yummy Chinese & Sushi Bar",
    "wof:placetype":"venue"
},
  "geometry": {"coordinates":[-80.140856,25.791348],"type":"Point"}
}