{
  "type": "Feature",
  "properties": {
    "iso:country":"US",
    "sg:address":"1303 Rogers Rd",
    "sg:city":"Plant City",
    "sg:classifiers":[
        {
            "category":"Farming",
            "subcategory":"Berry Farm",
            "type":"Manufacturing & Wholesale Goods"
        }
    ],
    "sg:phone":"+1 813 754 5210",
    "sg:postcode":"33566",
    "sg:province":"FL",
    "sg:tags":[
        "crop"
    ],
    "wof:name":"Dukes Farm",
    "wof:placetype":"venue"
},
  "geometry": {"coordinates":[-82.19128000000001,28.02381],"type":"Point"}
}