{
  "type": "Feature",
  "properties": {
    "addr:full":"7759 Johnson St Pembroke Pines FL 33024",
    "addr:housenumber":"7759",
    "addr:postcode":"33024",
    "addr:street":"Johnson St",
    "iso:country":"US",
    "sg:address":"7759 Johnson St",
    "sg:city":"Pembroke Pines",
    "sg:classifiers":[
        {
            "category":"Restaurant",
            "type":"Food & Drink"
        }
    ],
    "sg:phone":"+1 954 985 4050",
    "sg:postcode":"33024",
    "sg:province":"FL",
    "sg:tags":[
        "caterer"
    ],
    "wof:name":"Amay's Carinderia & Catering",
    "wof:placetype":"venue"
},
  "geometry": {"coordinates":[-80.242463,26.01661],"type":"Point"}
}