{
  "type": "Feature",
  "properties": {
    "addr:full":"3232 W Silver Springs Blvd Ocala FL 34475",
    "addr:housenumber":"3232",
    "addr:postcode":"34475",
    "addr:street":"W Silver Springs Blvd",
    "iso:country":"US",
    "sg:address":"3232 W Silver Springs Blvd",
    "sg:city":"Ocala",
    "sg:classifiers":[
        {
            "category":"Professional",
            "type":"Services"
        }
    ],
    "sg:phone":"+1 352 629 9221",
    "sg:postcode":"34475",
    "sg:province":"FL",
    "sg:tags":[
        "establishment"
    ],
    "wof:name":"ATMUSA",
    "wof:placetype":"venue"
},
  "geometry": {"coordinates":[-82.174215,29.186301],"type":"Point"}
}