{
  "type": "Feature",
  "properties": {
    "addr:full":"12900 Walsingham Rd Largo FL 33774",
    "addr:housenumber":"12900",
    "addr:postcode":"33774",
    "addr:street":"Walsingham Rd",
    "iso:country":"US",
    "sg:address":"12900 Walsingham Rd",
    "sg:city":"Largo",
    "sg:classifiers":[
        {
            "category":"Utilities",
            "subcategory":"Water",
            "type":"Services"
        },
        {
            "category":"Shopping",
            "subcategory":"Bicycles & Sporting Goods",
            "type":"Retail Goods"
        }
    ],
    "sg:phone":"+1 727 517 7000",
    "sg:postcode":"33774",
    "sg:province":"FL",
    "sg:tags":[
        "equipment",
        "surfboard",
        "windsurfing"
    ],
    "sg:website":"http://www.watersportswest.com",
    "wof:name":"Watersports West",
    "wof:placetype":"venue"
},
  "geometry": {"coordinates":[-82.816485,27.880384],"type":"Point"}
}