{
  "type": "Feature",
  "properties": {
    "iso:country":"US",
    "sg:address":"1550 SE 8th St",
    "sg:city":"Ocala",
    "sg:classifiers":[
        {
            "category":"Building & Trades",
            "subcategory":"Plumbing",
            "type":"Services"
        }
    ],
    "sg:phone":"+1 352 598 3146",
    "sg:postcode":"34471",
    "sg:province":"FL",
    "sg:tags":[
        "plumber",
        "industrial",
        "contractors-commercial"
    ],
    "wof:name":"Hefner Plumbing Company, Inc.",
    "wof:placetype":"venue"
},
  "geometry": {"coordinates":[-82.117304,29.17939],"type":"Point"}
}