{
  "type": "Feature",
  "properties": {
    "addr:full":"7940 SW 139th Ct Miami FL 33183",
    "addr:housenumber":"7940",
    "addr:postcode":"33183",
    "addr:street":"Sw 139Th Ct",
    "iso:country":"US",
    "sg:address":"7940 SW 139th Ct",
    "sg:city":"Miami",
    "sg:classifiers":[
        {
            "category":"Arts & Performance",
            "subcategory":"Theater",
            "type":"Entertainment"
        }
    ],
    "sg:phone":"+1 305 233 2049",
    "sg:postcode":"33183",
    "sg:province":"FL",
    "sg:tags":[
        "television",
        "program",
        "producer"
    ],
    "wof:name":"DTV Home Movie Transfers",
    "wof:placetype":"venue"
},
  "geometry": {"coordinates":[-80.42059999999999,25.693546],"type":"Point"}
}