{
  "type": "Feature",
  "properties": {
    "iso:country":"US",
    "sg:address":"141 E Riverside Dr",
    "sg:city":"Jupiter",
    "sg:classifiers":[
        {
            "category":"Organizations",
            "subcategory":"Community Association",
            "type":"Services"
        }
    ],
    "sg:phone":"+1 561 747 9888",
    "sg:postcode":"33469",
    "sg:province":"FL",
    "wof:name":"North Rverside Homeowners Assn",
    "wof:placetype":"venue"
},
  "geometry": {"coordinates":[-80.09030799999999,26.950677],"type":"Point"}
}