{
  "type": "Feature",
  "properties": {
    "iso:country":"US",
    "sg:address":"2200 Tamiami Trl",
    "sg:city":"Port Charlotte",
    "sg:classifiers":[
        {
            "category":"Restaurant",
            "type":"Food & Drink"
        }
    ],
    "sg:phone":"+1 941 743 6636",
    "sg:postcode":"33948",
    "sg:province":"FL",
    "wof:name":"International Buffet Co",
    "wof:placetype":"venue"
},
  "geometry": {"coordinates":[-82.12405800000001,27.000096],"type":"Point"}
}