{
  "type": "Feature",
  "properties": {
    "addr:full":"1212 N Parsons Ave Brandon FL 33510",
    "addr:housenumber":"1212",
    "addr:postcode":"33510",
    "addr:street":"N Parsons Ave",
    "iso:country":"US",
    "sg:address":"1212 N Parsons Ave",
    "sg:city":"Brandon",
    "sg:classifiers":[
        {
            "category":"Wholesale",
            "subcategory":"Groceries",
            "type":"Manufacturing & Wholesale Goods"
        }
    ],
    "sg:phone":"+1 813 685 5969",
    "sg:postcode":"33510",
    "sg:province":"FL",
    "sg:tags":[
        "baker"
    ],
    "wof:name":"Merita Bakery",
    "wof:placetype":"venue"
},
  "geometry": {"coordinates":[-82.285966,27.958106],"type":"Point"}
}