{
  "type": "Feature",
  "properties": {
    "iso:country":"US",
    "sg:address":"2211 N 38th St",
    "sg:city":"Tampa",
    "sg:classifiers":[
        {
            "category":"Wholesale",
            "subcategory":"Stationery",
            "type":"Manufacturing & Wholesale Goods"
        }
    ],
    "sg:phone":"+1 813 242 8477",
    "sg:postcode":"33605",
    "sg:province":"FL",
    "sg:tags":[
        "box",
        "fiber"
    ],
    "wof:name":"Suncoast Cartons Inc",
    "wof:placetype":"venue"
},
  "geometry": {"coordinates":[-82.417204,27.964138],"type":"Point"}
}