{
  "type": "Feature",
  "properties": {
    "iso:country":"US",
    "sg:address":"5268 W State Road 46",
    "sg:city":"Sanford",
    "sg:classifiers":[
        {
            "category":"Health Services",
            "subcategory":"Doctor",
            "type":"Services"
        },
        {
            "category":"Wholesale",
            "subcategory":"Medical Equipment & Supplies",
            "type":"Manufacturing & Wholesale Goods"
        },
        {
            "category":"Health Services",
            "subcategory":"Health Practitioner",
            "type":"Services"
        },
        {
            "category":"Communications",
            "type":"Services"
        }
    ],
    "sg:phone":"+1 407 328 4540",
    "sg:postcode":"32771",
    "sg:province":"FL",
    "sg:tags":[
        "sound",
        "speech-language",
        "level",
        "testing",
        "hearing",
        "pathologist",
        "device",
        "assistive",
        "aid",
        "audiologists"
    ],
    "sg:website":"http://www.accuratehearingtech.com",
    "wof:name":"Accurate Hearing Technology Inc",
    "wof:placetype":"venue"
},
  "geometry": {"coordinates":[-81.35228600000001,28.811397],"type":"Point"}
}