{
  "type": "Feature",
  "properties": {
    "iso:country":"US",
    "sg:address":"12155 Regal Ct N",
    "sg:city":"West Palm Beach",
    "sg:classifiers":[
        {
            "category":"Professional",
            "type":"Services"
        }
    ],
    "sg:phone":"+1 561 301 4032",
    "sg:postcode":"33414",
    "sg:province":"FL",
    "wof:name":"KB Dairy Inc",
    "wof:placetype":"venue"
},
  "geometry": {"coordinates":[-80.237542,26.657705],"type":"Point"}
}