{
  "type": "Feature",
  "properties": {
    "iso:country":"US",
    "sg:address":"11290 SW 47th Ter",
    "sg:city":"Miami",
    "sg:classifiers":[
        {
            "category":"Building & Trades",
            "subcategory":"Landscaping Services",
            "type":"Services"
        }
    ],
    "sg:phone":"+1 305 226 2345",
    "sg:postcode":"33165",
    "sg:province":"FL",
    "sg:tags":[
        "landscape",
        "contractor"
    ],
    "wof:name":"Ooh LA Lawn Inc",
    "wof:placetype":"venue"
},
  "geometry": {"coordinates":[-80.375733,25.72296],"type":"Point"}
}