{
  "type": "Feature",
  "properties": {
    "iso:country":"US",
    "sg:address":"720 Fentress Blvd",
    "sg:city":"Daytona Beach",
    "sg:classifiers":[
        {
            "category":"Manufacturing",
            "subcategory":"Tools & Machinery",
            "type":"Manufacturing & Wholesale Goods"
        }
    ],
    "sg:phone":"+1 386 274 4567",
    "sg:postcode":"32114",
    "sg:province":"FL",
    "sg:tags":[
        "mold",
        "mfg"
    ],
    "sg:website":"www.daytonamold.com",
    "wof:name":"Daytona Mold",
    "wof:placetype":"venue"
},
  "geometry": {"coordinates":[-81.082314,29.211294],"type":"Point"}
}