{
  "type": "Feature",
  "properties": {
    "iso:country":"US",
    "sg:address":"11223 Hammock Dr",
    "sg:city":"Largo",
    "sg:classifiers":[
        {
            "category":"Food & Beverages",
            "subcategory":"Fruits & Vegetables",
            "type":"Retail Goods"
        }
    ],
    "sg:phone":"+1 727 517 3532",
    "sg:postcode":"33774",
    "sg:province":"FL",
    "sg:tags":[
        "produce"
    ],
    "wof:name":"Sunstate Produce",
    "wof:placetype":"venue"
},
  "geometry": {"coordinates":[-82.829092,27.875519],"type":"Point"}
}