{
  "type": "Feature",
  "properties": {
    "iso:country":"US",
    "sg:address":"500 W Platt St",
    "sg:city":"Tampa",
    "sg:classifiers":[
        {
            "category":"Social Services",
            "subcategory":"Child Care",
            "type":"Services"
        },
        {
            "category":"Organizations",
            "subcategory":"Religious Organization",
            "type":"Services"
        }
    ],
    "sg:phone":"+1 813 253 5388",
    "sg:postcode":"33606",
    "sg:province":"FL",
    "sg:tags":[
        "church"
    ],
    "wof:name":"Small Blessings Early Childhoo",
    "wof:placetype":"venue"
},
  "geometry": {"coordinates":[-82.465789,27.941703],"type":"Point"}
}