{
  "type": "Feature",
  "properties": {
    "iso:country":"US",
    "sg:address":"18201 E Colonial Dr",
    "sg:city":"Orlando",
    "sg:phone":"+1 407 568 5900",
    "sg:postcode":"32820",
    "sg:province":"FL",
    "sg:website":"http://www.stihldealer.net/default-dealer-044588.aspx",
    "wof:name":"Eastside Mower",
    "wof:placetype":"venue"
},
  "geometry": {"coordinates":[-81.107758,28.554041],"type":"Point"}
}