{
  "type": "Feature",
  "properties": {
    "iso:country":"US",
    "sg:address":"1350 Palm Ave Ste A",
    "sg:city":"Hialeah",
    "sg:classifiers":[
        {
            "category":"Personal",
            "subcategory":"Barber",
            "type":"Services"
        }
    ],
    "sg:phone":"+1 305 888 9330",
    "sg:postcode":"33010",
    "sg:province":"FL",
    "wof:name":"Akiko Barber Shop",
    "wof:placetype":"venue"
},
  "geometry": {"coordinates":[-80.28205699999999,25.834009],"type":"Point"}
}