{
  "type": "Feature",
  "properties": {
    "iso:country":"US",
    "sg:address":"2920 Forsyth Rd",
    "sg:city":"Winter Park",
    "sg:classifiers":[
        {
            "category":"Manufacturing",
            "subcategory":"Printing",
            "type":"Manufacturing & Wholesale Goods"
        }
    ],
    "sg:phone":"+1 407 695 3696",
    "sg:postcode":"32792",
    "sg:province":"FL",
    "sg:tags":[
        "printer"
    ],
    "wof:name":"Finishing Center",
    "wof:placetype":"venue"
},
  "geometry": {"coordinates":[-81.294712,28.586156],"type":"Point"}
}