{
  "type": "Feature",
  "properties": {
    "iso:country":"US",
    "sg:address":"2 80th St S",
    "sg:city":"Saint Petersburg",
    "sg:classifiers":[
        {
            "category":"Shopping",
            "subcategory":"Clothing, Apparel, & Fashions",
            "type":"Retail Goods"
        }
    ],
    "sg:phone":"+1 727 347 2804",
    "sg:postcode":"33707",
    "sg:province":"FL",
    "sg:tags":[
        "sporting"
    ],
    "wof:name":"In House Merchandise",
    "wof:placetype":"venue"
},
  "geometry": {"coordinates":[-82.75045,27.770331],"type":"Point"}
}