{
  "type": "Feature",
  "properties": {
    "iso:country":"US",
    "sg:address":"22273 Cortez Blvd",
    "sg:city":"Brooksville",
    "sg:classifiers":[
        {
            "category":"Retail",
            "subcategory":"Veterinary Services",
            "type":"Services"
        }
    ],
    "sg:phone":"+1 352 796 7559",
    "sg:postcode":"34601",
    "sg:province":"FL",
    "sg:tags":[
        "veterinarian"
    ],
    "wof:name":"Country Vet Animal Clinic",
    "wof:placetype":"venue"
},
  "geometry": {"coordinates":[-82.358345,28.539696],"type":"Point"}
}