{
  "type": "Feature",
  "properties": {
    "iso:country":"US",
    "sg:address":"2285 NW 74th Ave",
    "sg:city":"Fort Lauderdale",
    "sg:classifiers":[
        {
            "category":"Home & Garden",
            "subcategory":"Building Materials",
            "type":"Retail Goods"
        }
    ],
    "sg:phone":"+1 954 572 3476",
    "sg:postcode":"33313",
    "sg:province":"FL",
    "wof:name":"Ultra Window Tinting & Acc",
    "wof:placetype":"venue"
},
  "geometry": {"coordinates":[-80.24537100000001,26.153957],"type":"Point"}
}