{
  "type": "Feature",
  "properties": {
    "iso:country":"US",
    "sg:address":"1700 Oviedo Marketplace Blvd",
    "sg:city":"Oviedo",
    "sg:classifiers":[
        {
            "category":"Shopping",
            "subcategory":"Clothing, Apparel, & Fashions",
            "type":"Retail Goods"
        }
    ],
    "sg:phone":"+1 407 365 8776",
    "sg:postcode":"32765",
    "sg:province":"FL",
    "sg:tags":[
        "children's",
        "clothing"
    ],
    "sg:website":"www.childrensplace.com",
    "wof:name":"Children's Place Store the",
    "wof:placetype":"venue"
},
  "geometry": {"coordinates":[-81.23673700000001,28.659895],"type":"Point"}
}