{
  "type": "Feature",
  "properties": {
    "iso:country":"US",
    "sg:address":"3100 NW 7th Ave",
    "sg:city":"Miami",
    "sg:classifiers":[
        {
            "category":"Manufacturing",
            "subcategory":"Signs",
            "type":"Manufacturing & Wholesale Goods"
        }
    ],
    "sg:phone":"+1 305 633 5379",
    "sg:postcode":"33127",
    "sg:province":"FL",
    "sg:tags":[
        "specialty",
        "merchandise",
        "mfg"
    ],
    "wof:name":"ABC Sign Designs",
    "wof:placetype":"venue"
},
  "geometry": {"coordinates":[-80.207408,25.806455],"type":"Point"}
}