{
  "type": "Feature",
  "properties": {
    "iso:country":"US",
    "sg:address":"401 Arizona Ave",
    "sg:city":"Lakeland",
    "sg:classifiers":[
        {
            "category":"Building & Trades",
            "subcategory":"Construction",
            "type":"Services"
        }
    ],
    "sg:phone":"+1 863 640 1077",
    "sg:postcode":"33801",
    "sg:province":"FL",
    "sg:tags":[
        "restoration",
        "cleaning",
        "patio",
        "deck"
    ],
    "wof:name":"Central Fl Pressure Cleaning",
    "wof:placetype":"venue"
},
  "geometry": {"coordinates":[-81.914292,28.040754],"type":"Point"}
}