{
  "type": "Feature",
  "properties": {
    "iso:country":"US",
    "sg:address":"801 12th Ave S",
    "sg:city":"Naples",
    "sg:classifiers":[
        {
            "category":"Manufacturing",
            "subcategory":"Printing",
            "type":"Manufacturing & Wholesale Goods"
        }
    ],
    "sg:phone":"+1 239 649 7077",
    "sg:postcode":"34102",
    "sg:province":"FL",
    "sg:tags":[
        "publishes",
        "book"
    ],
    "wof:name":"Trident Press International",
    "wof:placetype":"venue"
},
  "geometry": {"coordinates":[-81.793835,26.132769],"type":"Point"}
}