{
  "type": "Feature",
  "properties": {
    "addr:full":"8020 Windy Hill Way Orlando FL 32818",
    "addr:housenumber":"8020",
    "addr:postcode":"32818",
    "addr:street":"Windy Hill Way",
    "iso:country":"US",
    "sg:address":"8020 Windy Hill Way",
    "sg:city":"Orlando",
    "sg:classifiers":[
        {
            "category":"Freight",
            "type":"Transportation"
        }
    ],
    "sg:phone":"+1 407 538 5821",
    "sg:postcode":"32818",
    "sg:province":"FL",
    "sg:tags":[
        "driver",
        "leasing",
        "truck"
    ],
    "wof:name":"Michael Dabney",
    "wof:placetype":"venue"
},
  "geometry": {"coordinates":[-81.495621,28.562423],"type":"Point"}
}