{
  "type": "Feature",
  "properties": {
    "iso:country":"US",
    "sg:address":"10600 SW 131st Ct",
    "sg:city":"Miami",
    "sg:classifiers":[
        {
            "category":"Education",
            "subcategory":"Special Training",
            "type":"Public Place"
        }
    ],
    "sg:phone":"+1 305 968 7136",
    "sg:postcode":"33186",
    "sg:province":"FL",
    "sg:tags":[
        "educational"
    ],
    "wof:name":"Marine & Coastal Research, Corp",
    "wof:placetype":"venue"
},
  "geometry": {"coordinates":[-80.40537999999999,25.68375],"type":"Point"}
}