{
  "type": "Feature",
  "properties": {
    "addr:full":"1276 10th St N Naples FL 34102",
    "addr:housenumber":"1276",
    "addr:postcode":"34102",
    "addr:street":"10Th St N",
    "iso:country":"US",
    "sg:address":"1276 10th St N",
    "sg:city":"Naples",
    "sg:classifiers":[
        {
            "category":"Building & Trades",
            "subcategory":"Construction",
            "type":"Services"
        }
    ],
    "sg:phone":"+1 239 262 3189",
    "sg:postcode":"34102",
    "sg:province":"FL",
    "sg:tags":[
        "hanging",
        "contractor"
    ],
    "wof:name":"Gerry Honegger Painting",
    "wof:placetype":"venue"
},
  "geometry": {"coordinates":[-81.79686100000001,26.163649],"type":"Point"}
}