{
  "type": "Feature",
  "properties": {
    "iso:country":"US",
    "sg:address":"18125 US Hwy 41",
    "sg:city":"Lutz",
    "sg:classifiers":[
        {
            "category":"Professional",
            "subcategory":"Business Services",
            "type":"Services"
        }
    ],
    "sg:phone":"+1 813 948 2706",
    "sg:postcode":"33549",
    "sg:province":"FL",
    "sg:tags":[
        "interior",
        "consultant",
        "design",
        "decorator"
    ],
    "wof:name":"Winchell Interiors Inc",
    "wof:placetype":"venue"
},
  "geometry": {"coordinates":[-82.462942,28.137922],"type":"Point"}
}