{
  "type": "Feature",
  "properties": {
    "addr:full":"4830 Kingston Cir Kissimmee FL 34746",
    "addr:housenumber":"4830",
    "addr:postcode":"34746",
    "addr:street":"Kingston Cir",
    "iso:country":"US",
    "sg:address":"4830 Kingston Cir",
    "sg:city":"Kissimmee",
    "sg:classifiers":[
        {
            "category":"Wholesale",
            "subcategory":"Machinery & Supplies",
            "type":"Manufacturing & Wholesale Goods"
        }
    ],
    "sg:phone":"+1 407 397 7363",
    "sg:postcode":"34746",
    "sg:province":"FL",
    "sg:tags":[
        "equipment",
        "industrial"
    ],
    "wof:name":"IMS Inc",
    "wof:placetype":"venue"
},
  "geometry": {"coordinates":[-81.477402,28.32102],"type":"Point"}
}