{
  "type": "Feature",
  "properties": {
    "iso:country":"US",
    "sg:address":"13121 Ring Neck Rd",
    "sg:city":"Tallahassee",
    "sg:classifiers":[
        {
            "category":"Building & Trades",
            "subcategory":"Landscaping Services",
            "type":"Services"
        }
    ],
    "sg:phone":"+1 850 893 7324",
    "sg:postcode":"32312",
    "sg:province":"FL",
    "wof:name":"Forevergreen Lawn Care & Maint",
    "wof:placetype":"venue"
},
  "geometry": {"coordinates":[-84.27421200000001,30.644185],"type":"Point"}
}