{
  "type": "Feature",
  "properties": {
    "iso:country":"US",
    "sg:address":"6550 N Federal Hwy",
    "sg:city":"Fort Lauderdale",
    "sg:classifiers":[
        {
            "category":"Health Services",
            "subcategory":"Doctor",
            "type":"Services"
        }
    ],
    "sg:phone":"+1 954 491 0510",
    "sg:postcode":"33308",
    "sg:province":"FL",
    "sg:tags":[
        "physician",
        "surgeon"
    ],
    "wof:name":"Dermatologic Laser & Surgery",
    "wof:placetype":"venue"
},
  "geometry": {"coordinates":[-80.10787999999999,26.207156],"type":"Point"}
}