{
  "type": "Feature",
  "properties": {
    "addr:full":"117 1st Ave SW Largo FL 33770",
    "addr:housenumber":"117",
    "addr:postcode":"33770",
    "addr:street":"1St Ave Sw",
    "iso:country":"US",
    "sg:address":"117 1st Ave SW",
    "sg:city":"Largo",
    "sg:classifiers":[
        {
            "category":"Home & Garden",
            "subcategory":"Home Furnishings",
            "type":"Retail Goods"
        }
    ],
    "sg:phone":"+1 727 585 9007",
    "sg:postcode":"33770",
    "sg:province":"FL",
    "sg:tags":[
        "venetian",
        "blind"
    ],
    "wof:name":"Gotcha Covered Blinds",
    "wof:placetype":"venue"
},
  "geometry": {"coordinates":[-82.789711,27.915981],"type":"Point"}
}