{
  "type": "Feature",
  "properties": {
    "iso:country":"US",
    "sg:address":"3813 Land O Lakes Blvd",
    "sg:city":"Land O Lakes",
    "sg:classifiers":[
        {
            "category":"Autos & Motor Vehicles",
            "subcategory":"Auto Supplies",
            "type":"Retail Goods"
        }
    ],
    "sg:phone":"+1 813 929 0461",
    "sg:postcode":"34639",
    "sg:province":"FL",
    "sg:tags":[
        "home"
    ],
    "wof:name":"Discount Auto Parts Inc",
    "wof:placetype":"venue"
},
  "geometry": {"coordinates":[-82.461682,28.211192],"type":"Point"}
}