{
  "type": "Feature",
  "properties": {
    "iso:country":"US",
    "sg:address":"934 E Rose St",
    "sg:city":"Lakeland",
    "sg:classifiers":[
        {
            "category":"Manufacturing",
            "subcategory":"Wood Products",
            "type":"Manufacturing & Wholesale Goods"
        }
    ],
    "sg:phone":"+1 863 678 1160",
    "sg:postcode":"33801",
    "sg:province":"FL",
    "wof:name":"Williams Fence Co",
    "wof:placetype":"venue"
},
  "geometry": {"coordinates":[-81.946527,28.045433],"type":"Point"}
}