{
  "type": "Feature",
  "properties": {
    "iso:country":"US",
    "sg:address":"2700 S Commerce Pkwy",
    "sg:city":"Weston",
    "sg:classifiers":[
        {
            "category":"Banks & Credit Unions",
            "subcategory":"Bank",
            "type":"Services"
        }
    ],
    "sg:phone":"+1 954 334 5626",
    "sg:postcode":"33331",
    "sg:province":"FL",
    "sg:tags":[
        "loan",
        "real estate"
    ],
    "wof:name":"APB Mortgage",
    "wof:placetype":"venue"
},
  "geometry": {"coordinates":[-80.36578799999999,26.084472],"type":"Point"}
}