{
  "type": "Feature",
  "properties": {
    "iso:country":"US",
    "sg:address":"601 W 53rd St",
    "sg:city":"Hialeah",
    "sg:classifiers":[
        {
            "category":"Autos & Motor Vehicles",
            "subcategory":"Automobile Sales",
            "type":"Retail Goods"
        }
    ],
    "sg:phone":"+1 305 456 3812",
    "sg:postcode":"33012",
    "sg:province":"FL",
    "sg:tags":[
        "trailer",
        "transport"
    ],
    "wof:name":"May Tech And Phones Sales Inc",
    "wof:placetype":"venue"
},
  "geometry": {"coordinates":[-80.29494800000001,25.870199],"type":"Point"}
}