{
  "type": "Feature",
  "properties": {
    "iso:country":"US",
    "sg:address":"2530 Capital Cir NE",
    "sg:city":"Tallahassee",
    "sg:classifiers":[
        {
            "category":"Health Services",
            "subcategory":"Health Practitioner",
            "type":"Services"
        }
    ],
    "sg:phone":"+1 850 385 8961",
    "sg:postcode":"32308",
    "sg:province":"FL",
    "sg:tags":[
        "acupuncture"
    ],
    "wof:name":"Tallahassee Acupuncture Ctr",
    "wof:placetype":"venue"
},
  "geometry": {"coordinates":[-84.23852599999999,30.487178],"type":"Point"}
}