{
  "type": "Feature",
  "properties": {
    "iso:country":"US",
    "sg:address":"111 NW 183rd St",
    "sg:city":"Miami",
    "sg:classifiers":[
        {
            "category":"Health Services",
            "subcategory":"Clinic",
            "type":"Services"
        },
        {
            "category":"Personal",
            "type":"Services"
        },
        {
            "category":"Health Services",
            "subcategory":"Health Practitioner",
            "type":"Services"
        }
    ],
    "sg:phone":"+1 305 892 4600",
    "sg:postcode":"33169",
    "sg:province":"FL",
    "sg:tags":[
        "information",
        "mental",
        "counselors-licensed",
        "abuse",
        "drug",
        "professional",
        "counseling",
        "addiction"
    ],
    "sg:website":"http://www.bayviewcenter.com",
    "wof:name":"Bayview Center For Mental Health Inc",
    "wof:placetype":"venue"
},
  "geometry": {"coordinates":[-80.203343,25.942671],"type":"Point"}
}