{
  "type": "Feature",
  "properties": {
    "iso:country":"US",
    "sg:address":"4940 Durant Rd",
    "sg:city":"Dover",
    "sg:classifiers":[
        {
            "category":"Building & Trades",
            "subcategory":"Electrical",
            "type":"Services"
        }
    ],
    "sg:phone":"+1 813 654 7701",
    "sg:postcode":"33527",
    "sg:province":"FL",
    "sg:tags":[
        "electric",
        "contractor"
    ],
    "wof:name":"Amos Electric Inc",
    "wof:placetype":"venue"
},
  "geometry": {"coordinates":[-82.215036,27.908396],"type":"Point"}
}