{
  "type": "Feature",
  "properties": {
    "iso:country":"US",
    "sg:address":"3736 Salisbury Rd",
    "sg:city":"Jacksonville",
    "sg:classifiers":[
        {
            "category":"Airline",
            "type":"Transportation"
        }
    ],
    "sg:phone":"+1 904 332 5400",
    "sg:postcode":"32216",
    "sg:province":"FL",
    "sg:tags":[
        "air",
        "cargo",
        "carrier",
        "ground"
    ],
    "wof:name":"Fedex",
    "wof:placetype":"venue"
},
  "geometry": {"coordinates":[-81.597172,30.261025],"type":"Point"}
}