{
  "type": "Feature",
  "properties": {
    "addr:full":"901 45th St West Palm Beach FL 33407",
    "addr:housenumber":"901",
    "addr:postcode":"33407",
    "addr:street":"45Th St",
    "iso:country":"US",
    "sg:address":"901 45th St",
    "sg:city":"West Palm Beach",
    "sg:classifiers":[
        {
            "category":"Professional",
            "type":"Services"
        }
    ],
    "sg:phone":"+1 561 882 2777",
    "sg:postcode":"33407",
    "sg:province":"FL",
    "sg:tags":[
        "establishment"
    ],
    "wof:name":"Childrens Miracle Network",
    "wof:placetype":"venue"
},
  "geometry": {"coordinates":[-80.063676,26.753148],"type":"Point"}
}