{
  "type": "Feature",
  "properties": {
    "iso:country":"US",
    "sg:address":"15942 Blue Skies Dr",
    "sg:city":"Fort Myers",
    "sg:classifiers":[
        {
            "category":"Organizations",
            "subcategory":"Labor Organization",
            "type":"Services"
        }
    ],
    "sg:phone":"+1 239 731 0701",
    "sg:postcode":"33917",
    "sg:province":"FL",
    "wof:name":"L and C Enterprises LLC",
    "wof:placetype":"venue"
},
  "geometry": {"coordinates":[-81.86161199999999,26.692091],"type":"Point"}
}