{
  "type": "Feature",
  "properties": {
    "iso:country":"US",
    "sg:address":"4101 SE Myrtle St",
    "sg:city":"Stuart",
    "sg:classifiers":[
        {
            "category":"Manufacturing",
            "subcategory":"Building Materials",
            "type":"Manufacturing & Wholesale Goods"
        }
    ],
    "sg:phone":"+1 561 818 3739",
    "sg:postcode":"34997",
    "sg:province":"FL",
    "sg:tags":[
        "mfg"
    ],
    "wof:name":"Robert P Shiffer Woodworking",
    "wof:placetype":"venue"
},
  "geometry": {"coordinates":[-80.19793300000001,27.165414],"type":"Point"}
}