{
  "type": "Feature",
  "properties": {
    "iso:country":"US",
    "sg:address":"1905 Grace Ave",
    "sg:city":"Fort Myers",
    "sg:classifiers":[
        {
            "category":"Building & Trades",
            "subcategory":"Construction",
            "type":"Services"
        }
    ],
    "sg:phone":"+1 239 281 1207",
    "sg:postcode":"33901",
    "sg:province":"FL",
    "sg:tags":[
        "site",
        "clean"
    ],
    "wof:name":"Tammy Whidby Cleanup",
    "wof:placetype":"venue"
},
  "geometry": {"coordinates":[-81.87226099999999,26.618042],"type":"Point"}
}