{
  "type": "Feature",
  "properties": {
    "addr:full":"1160 NW 159th Dr Miami FL 33169",
    "addr:housenumber":"1160",
    "addr:postcode":"33169",
    "addr:street":"Nw 159Th Dr",
    "iso:country":"US",
    "sg:address":"1160 NW 159th Dr",
    "sg:city":"Miami",
    "sg:classifiers":[
        {
            "category":"Manufacturing",
            "subcategory":"Electronics",
            "type":"Manufacturing & Wholesale Goods"
        }
    ],
    "sg:phone":"+1 407 294 3727",
    "sg:postcode":"33169",
    "sg:province":"FL",
    "sg:tags":[
        "a",
        "wireless",
        "operates",
        "content",
        "as",
        "video",
        "internet"
    ],
    "wof:name":"Global Triad",
    "wof:placetype":"venue"
},
  "geometry": {"coordinates":[-80.21833100000001,25.921286],"type":"Point"}
}