{
  "type": "Feature",
  "properties": {
    "iso:country":"US",
    "sg:address":"10570 SW 97th Ave",
    "sg:city":"Miami",
    "sg:classifiers":[
        {
            "category":"Social Services",
            "subcategory":"Child Care",
            "type":"Services"
        }
    ],
    "sg:phone":"+1 305 271 4622",
    "sg:postcode":"33176",
    "sg:province":"FL",
    "sg:tags":[
        "day"
    ],
    "wof:name":"Kiddie Kampus",
    "wof:placetype":"venue"
},
  "geometry": {"coordinates":[-80.35140199999999,25.6712],"type":"Point"}
}