{
  "type": "Feature",
  "properties": {
    "addr:full":"1705 W 32nd Pl Hialeah FL 33012",
    "addr:housenumber":"1705",
    "addr:postcode":"33012",
    "addr:street":"W 32Nd Pl",
    "iso:country":"US",
    "sg:address":"1705 W 32nd Pl",
    "sg:city":"Hialeah",
    "sg:classifiers":[
        {
            "category":"Manufacturing",
            "subcategory":"Metals",
            "type":"Manufacturing & Wholesale Goods"
        }
    ],
    "sg:phone":"+1 305 558 5777",
    "sg:postcode":"33012",
    "sg:province":"FL",
    "sg:tags":[
        "finisher"
    ],
    "wof:name":"Industrial Metal Spraying",
    "wof:placetype":"venue"
},
  "geometry": {"coordinates":[-80.31560399999999,25.851259],"type":"Point"}
}