{
  "type": "Feature",
  "properties": {
    "addr:full":"8724 N Temple Ave Tampa FL 33617",
    "addr:housenumber":"8724",
    "addr:postcode":"33617",
    "addr:street":"N Temple Ave",
    "iso:country":"US",
    "sg:address":"8724 N Temple Ave",
    "sg:city":"Tampa",
    "sg:classifiers":[
        {
            "category":"Building & Trades",
            "subcategory":"Construction",
            "type":"Services"
        }
    ],
    "sg:phone":"+1 813 985 7400",
    "sg:postcode":"33617",
    "sg:province":"FL",
    "sg:tags":[
        "resurfacing",
        "laying",
        "refinishing",
        "floor"
    ],
    "wof:name":"Kristaq Berdufi Floors",
    "wof:placetype":"venue"
},
  "geometry": {"coordinates":[-82.40741,28.031722],"type":"Point"}
}