{
  "type": "Feature",
  "properties": {
    "iso:country":"US",
    "sg:address":"6875 Estero Blvd",
    "sg:city":"Fort Myers Beach",
    "sg:classifiers":[
        {
            "category":"Health Services",
            "subcategory":"Doctor",
            "type":"Services"
        }
    ],
    "sg:phone":"+1 239 463 5741",
    "sg:postcode":"33931",
    "sg:province":"FL",
    "sg:tags":[
        "medical"
    ],
    "wof:name":"Michael H Millward MD",
    "wof:placetype":"venue"
},
  "geometry": {"coordinates":[-81.898363,26.409731],"type":"Point"}
}