{
  "type": "Feature",
  "properties": {
    "addr:full":"799 Highland Ave Dunedin FL 34698",
    "addr:housenumber":"799",
    "addr:postcode":"34698",
    "addr:street":"Highland Ave",
    "iso:country":"US",
    "sg:address":"799 Highland Ave",
    "sg:city":"Dunedin",
    "sg:classifiers":[
        {
            "category":"Personal",
            "subcategory":"Beauty Salon",
            "type":"Services"
        }
    ],
    "sg:phone":"+1 727 734 2617",
    "sg:postcode":"34698",
    "sg:province":"FL",
    "wof:name":"Paris Hair Design",
    "wof:placetype":"venue"
},
  "geometry": {"coordinates":[-82.78582299999999,28.011366],"type":"Point"}
}