{
  "type": "Feature",
  "properties": {
    "addr:full":"225 Tanglewood Dr Apopka FL 32712",
    "addr:housenumber":"225",
    "addr:postcode":"32712",
    "addr:street":"Tanglewood Dr",
    "iso:country":"US",
    "sg:address":"225 Tanglewood Dr",
    "sg:city":"Apopka",
    "sg:classifiers":[
        {
            "category":"Social Services",
            "type":"Services"
        }
    ],
    "sg:phone":"+1 407 410 0145",
    "sg:postcode":"32712",
    "sg:province":"FL",
    "sg:tags":[
        "senior",
        "citizen"
    ],
    "wof:name":"Outreach Senior Healthcare Inc",
    "wof:placetype":"venue"
},
  "geometry": {"coordinates":[-81.515794,28.71084],"type":"Point"}
}