{
  "type": "Feature",
  "properties": {
    "iso:country":"US",
    "sg:address":"19940 Castlewood Dr",
    "sg:city":"Jupiter",
    "sg:classifiers":[
        {
            "category":"Real Estate",
            "subcategory":"Real Estate Agent",
            "type":"Services"
        }
    ],
    "sg:phone":"+1 561 575 6452",
    "sg:postcode":"33458",
    "sg:province":"FL",
    "wof:name":"Kyle Maneney",
    "wof:placetype":"venue"
},
  "geometry": {"coordinates":[-80.135443,26.969194],"type":"Point"}
}