{
  "type": "Feature",
  "properties": {
    "addr:full":"905 Clint Moore Rd Boca Raton FL 33487",
    "addr:housenumber":"905",
    "addr:postcode":"33487",
    "addr:street":"Clint Moore Rd",
    "iso:country":"US",
    "sg:address":"905 Clint Moore Rd",
    "sg:city":"Boca Raton",
    "sg:classifiers":[
        {
            "category":"Wholesale",
            "subcategory":"Hardware",
            "type":"Manufacturing & Wholesale Goods"
        }
    ],
    "sg:phone":"+1 561 953 0722",
    "sg:postcode":"33487",
    "sg:province":"FL",
    "sg:tags":[
        "water"
    ],
    "wof:name":"Ultimate Water",
    "wof:placetype":"venue"
},
  "geometry": {"coordinates":[-80.102617,26.408325],"type":"Point"}
}