{
  "type": "Feature",
  "properties": {
    "iso:country":"US",
    "sg:address":"1535 SE 43rd Ter",
    "sg:city":"Ocala",
    "sg:classifiers":[
        {
            "category":"Building & Trades",
            "subcategory":"Construction",
            "type":"Services"
        }
    ],
    "sg:phone":"+1 352 245 9957",
    "sg:postcode":"34471",
    "sg:province":"FL",
    "sg:tags":[
        "contractor"
    ],
    "wof:name":"Daniels Installations",
    "wof:placetype":"venue"
},
  "geometry": {"coordinates":[-82.075928,29.171524],"type":"Point"}
}