{
  "type": "Feature",
  "properties": {
    "addr:full":"2820 Pleasure Ln St Augustine FL 32084",
    "addr:housenumber":"2820",
    "addr:postcode":"32084",
    "addr:street":"Pleasure Ln",
    "iso:country":"US",
    "sg:address":"2820 Pleasure Ln",
    "sg:city":"St Augustine",
    "sg:classifiers":[
        {
            "category":"Personal",
            "type":"Services"
        },
        {
            "category":"Building & Trades",
            "subcategory":"Equipment Rental",
            "type":"Services"
        }
    ],
    "sg:phone":"+1 904 829 1680",
    "sg:postcode":"32084",
    "sg:province":"FL",
    "sg:tags":[
        "toilet",
        "portable",
        "restroom"
    ],
    "wof:name":"Outhouse Portable Restrooms",
    "wof:placetype":"venue"
},
  "geometry": {"coordinates":[-81.38076700000001,29.910244],"type":"Point"}
}