{
  "type": "Feature",
  "properties": {
    "iso:country":"US",
    "sg:address":"8323 NW 12th St Ste 208",
    "sg:city":"Doral",
    "sg:classifiers":[
        {
            "category":"Social Services",
            "type":"Services"
        },
        {
            "category":"Organizations",
            "subcategory":"Non-profit Organization",
            "type":"Services"
        }
    ],
    "sg:phone":"+1 305 477 1192",
    "sg:postcode":"33126",
    "sg:province":"FL",
    "sg:tags":[
        "fund",
        "raising"
    ],
    "sg:website":"http://www.marchofdimes.com",
    "wof:name":"March Of Dimes",
    "wof:placetype":"venue"
},
  "geometry": {"coordinates":[-80.330752,25.782725],"type":"Point"}
}