{
  "type": "Feature",
  "properties": {
    "iso:country":"US",
    "sg:address":"9289 SW 192nd Court Rd",
    "sg:city":"Dunnellon",
    "sg:classifiers":[
        {
            "category":"Professional",
            "type":"Services"
        }
    ],
    "sg:phone":"+1 352 465 0642",
    "sg:postcode":"34432",
    "sg:province":"FL",
    "sg:tags":[
        "establishment"
    ],
    "wof:name":"William Burnett Enterprises",
    "wof:placetype":"venue"
},
  "geometry": {"coordinates":[-82.437828,29.089252],"type":"Point"}
}