{
  "type": "Feature",
  "properties": {
    "addr:full":"14379 E Hwy 40 Silver Springs FL 34488",
    "addr:housenumber":"14379",
    "addr:postcode":"34488",
    "addr:street":"E Hwy 40",
    "iso:country":"US",
    "sg:address":"14379 E Hwy 40",
    "sg:city":"Silver Springs",
    "sg:classifiers":[
        {
            "category":"Personal",
            "subcategory":"Beauty Salon",
            "type":"Services"
        }
    ],
    "sg:phone":"+1 352 625 5354",
    "sg:postcode":"34488",
    "sg:province":"FL",
    "wof:name":"Sherry's Beauty Salon",
    "wof:placetype":"venue"
},
  "geometry": {"coordinates":[-81.911418,29.193288],"type":"Point"}
}