{
  "type": "Feature",
  "properties": {
    "iso:country":"US",
    "sg:address":"2153 Pine Ridge Dr",
    "sg:city":"Clearwater",
    "sg:classifiers":[
        {
            "category":"Retail",
            "subcategory":"Car Wash",
            "type":"Services"
        }
    ],
    "sg:phone":"+1 727 688 1499",
    "sg:postcode":"33763",
    "sg:province":"FL",
    "wof:name":"Rick's Island Detail",
    "wof:placetype":"venue"
},
  "geometry": {"coordinates":[-82.748693,28.009875],"type":"Point"}
}