{
  "type": "Feature",
  "properties": {
    "iso:country":"US",
    "sg:address":"2010 Chavers Rd",
    "sg:city":"Cantonment",
    "sg:classifiers":[
        {
            "category":"Real Estate",
            "subcategory":"Real Estate Operator",
            "type":"Services"
        }
    ],
    "sg:phone":"+1 850 968 3551",
    "sg:postcode":"32533",
    "sg:province":"FL",
    "sg:tags":[
        "mobile",
        "home",
        "site"
    ],
    "wof:name":"TLC Mobile Home Park Inc",
    "wof:placetype":"venue"
},
  "geometry": {"coordinates":[-87.299261,30.640465],"type":"Point"}
}