{
  "type": "Feature",
  "properties": {
    "iso:country":"US",
    "sg:address":"1304 Trl Maple Lp",
    "sg:city":"Oviedo",
    "sg:classifiers":[
        {
            "category":"Professional",
            "type":"Services"
        }
    ],
    "sg:phone":"+1 407 977 5212",
    "sg:postcode":"32765",
    "sg:province":"FL",
    "wof:name":"Trish Wallace Inc",
    "wof:placetype":"venue"
},
  "geometry": {"coordinates":[-81.22287900000001,28.63326],"type":"Point"}
}