{
  "type": "Feature",
  "properties": {
    "addr:full":"212 N Central St Bristol FL 32321",
    "addr:housenumber":"212",
    "addr:postcode":"32321",
    "addr:street":"N Central St",
    "iso:country":"US",
    "sg:address":"212 N Central St",
    "sg:city":"Bristol",
    "sg:classifiers":[
        {
            "category":"Health Services",
            "subcategory":"Clinic",
            "type":"Services"
        }
    ],
    "sg:phone":"+1 850 643 1200",
    "sg:postcode":"32321",
    "sg:province":"FL",
    "sg:tags":[
        "agency",
        "welfare"
    ],
    "wof:name":"Liberty County Health Dept",
    "wof:placetype":"venue"
},
  "geometry": {"coordinates":[-84.981818,30.434039],"type":"Point"}
}