{
  "type": "Feature",
  "properties": {
    "addr:full":"1790 Lee Rd Orlando FL 32810",
    "addr:housenumber":"1790",
    "addr:postcode":"32810",
    "addr:street":"Lee Rd",
    "iso:country":"US",
    "sg:address":"1790 Lee Rd",
    "sg:city":"Orlando",
    "sg:classifiers":[
        {
            "category":"Professional",
            "subcategory":"Business Services",
            "type":"Services"
        }
    ],
    "sg:phone":"+1 407 767 5955",
    "sg:postcode":"32810",
    "sg:province":"FL",
    "sg:tags":[
        "paging",
        "answering"
    ],
    "wof:name":"Message Masters",
    "wof:placetype":"venue"
},
  "geometry": {"coordinates":[-81.40824499999999,28.602481],"type":"Point"}
}