{
  "type": "Feature",
  "properties": {
    "iso:country":"US",
    "sg:address":"4707 140th Ave N",
    "sg:city":"Clearwater",
    "sg:classifiers":[
        {
            "category":"Building & Trades",
            "subcategory":"Construction",
            "type":"Services"
        }
    ],
    "sg:phone":"+1 727 533 0433",
    "sg:postcode":"33762",
    "sg:province":"FL",
    "sg:tags":[
        "painter"
    ],
    "wof:name":"Straight Line Painting",
    "wof:placetype":"venue"
},
  "geometry": {"coordinates":[-82.698019,27.899242],"type":"Point"}
}