{
  "type": "Feature",
  "properties": {
    "iso:country":"US",
    "sg:address":"710 SW 170th St",
    "sg:city":"Newberry",
    "sg:classifiers":[
        {
            "category":"Building & Trades",
            "subcategory":"Construction",
            "type":"Services"
        }
    ],
    "sg:phone":"+1 352 472 4124",
    "sg:postcode":"32669",
    "sg:province":"FL",
    "sg:tags":[
        "carpentry",
        "contractor"
    ],
    "wof:name":"Ross & Sons Construction Inc",
    "wof:placetype":"venue"
},
  "geometry": {"coordinates":[-82.523552,29.648141],"type":"Point"}
}