{
  "type": "Feature",
  "properties": {
    "addr:full":"3500 Mystic Pointe Dr Aventura FL 33180",
    "addr:housenumber":"3500",
    "addr:postcode":"33180",
    "addr:street":"Mystic Pointe Dr",
    "iso:country":"US",
    "sg:address":"3500 Mystic Pointe Dr",
    "sg:city":"Aventura",
    "sg:classifiers":[
        {
            "category":"Wholesale",
            "subcategory":"Durable Goods & Equipment",
            "type":"Manufacturing & Wholesale Goods"
        }
    ],
    "sg:phone":"+1 305 610 5977",
    "sg:postcode":"33180",
    "sg:province":"FL",
    "sg:tags":[
        "representative",
        "manufacturer"
    ],
    "wof:name":"Manufacturers Representative",
    "wof:placetype":"venue"
},
  "geometry": {"coordinates":[-80.129333,25.953557],"type":"Point"}
}