{
  "type": "Feature",
  "properties": {
    "addr:full":"4185 W Lake Mary Blvd Lake Mary FL 32746",
    "addr:housenumber":"4185",
    "addr:postcode":"32746",
    "addr:street":"W Lake Mary Blvd",
    "iso:country":"US",
    "sg:address":"4185 W Lake Mary Blvd",
    "sg:city":"Lake Mary",
    "sg:classifiers":[
        {
            "category":"Professional",
            "subcategory":"Business Services",
            "type":"Services"
        }
    ],
    "sg:phone":"+1 407 324 7448",
    "sg:postcode":"32746",
    "sg:province":"FL",
    "sg:tags":[
        "packing",
        "shipping",
        "copying"
    ],
    "wof:name":"PostNet",
    "wof:placetype":"venue"
},
  "geometry": {"coordinates":[-81.349231,28.756093],"type":"Point"}
}