{
  "type": "Feature",
  "properties": {
    "iso:country":"US",
    "sg:address":"5545 Alexis Forest Ln",
    "sg:city":"Jacksonville",
    "sg:classifiers":[
        {
            "category":"Building & Trades",
            "subcategory":"Construction",
            "type":"Services"
        }
    ],
    "sg:phone":"+1 904 887 7334",
    "sg:postcode":"32258",
    "sg:province":"FL",
    "sg:tags":[
        "house"
    ],
    "wof:name":"Brothers Group Construction Co",
    "wof:placetype":"venue"
},
  "geometry": {"coordinates":[-81.565163,30.162162],"type":"Point"}
}