{
  "type": "Feature",
  "properties": {
    "iso:country":"US",
    "sg:address":"21370 Hepner Ave",
    "sg:city":"Port Charlotte",
    "sg:classifiers":[
        {
            "category":"Building & Trades",
            "subcategory":"Construction",
            "type":"Services"
        }
    ],
    "sg:phone":"+1 941 624 5681",
    "sg:postcode":"33952",
    "sg:province":"FL",
    "wof:name":"Matthew Aulabaugh Inc",
    "wof:placetype":"venue"
},
  "geometry": {"coordinates":[-82.096084,26.996513],"type":"Point"}
}