{
  "type": "Feature",
  "properties": {
    "iso:country":"US",
    "sg:address":"5130 SW 5th Ter",
    "sg:city":"Coral Gables",
    "sg:classifiers":[
        {
            "category":"Shopping",
            "subcategory":"Florist",
            "type":"Retail Goods"
        }
    ],
    "sg:phone":"+1 305 445 3637",
    "sg:postcode":"33134",
    "sg:province":"FL",
    "wof:name":"Baskets Emporium Inc",
    "wof:placetype":"venue"
},
  "geometry": {"coordinates":[-80.27780199999999,25.766199],"type":"Point"}
}