{
  "type": "Feature",
  "properties": {
    "iso:country":"US",
    "sg:address":"266 Wellington Dr",
    "sg:city":"Palm Coast",
    "sg:classifiers":[
        {
            "category":"Building & Trades",
            "subcategory":"Electrical",
            "type":"Services"
        }
    ],
    "sg:phone":"+1 386 447 3796",
    "sg:postcode":"32164",
    "sg:province":"FL",
    "sg:tags":[
        "electrical",
        "contractor"
    ],
    "wof:name":"Zip Electric Inc",
    "wof:placetype":"venue"
},
  "geometry": {"coordinates":[-81.248144,29.543142],"type":"Point"}
}