{
  "type": "Feature",
  "properties": {
    "iso:country":"US",
    "sg:address":"4032 Bryan Blvd",
    "sg:city":"Fort Lauderdale",
    "sg:classifiers":[
        {
            "category":"Autos & Motor Vehicles",
            "subcategory":"Auto Supplies",
            "type":"Retail Goods"
        }
    ],
    "sg:phone":"+1 954 792 6686",
    "sg:postcode":"33317",
    "sg:province":"FL",
    "sg:tags":[
        "general"
    ],
    "wof:name":"Kramers Auto Electric",
    "wof:placetype":"venue"
},
  "geometry": {"coordinates":[-80.20384900000001,26.119968],"type":"Point"}
}