{
  "type": "Feature",
  "properties": {
    "iso:country":"US",
    "sg:address":"21334 Saint Andrews Blvd",
    "sg:city":"Boca Raton",
    "sg:classifiers":[
        {
            "category":"Food & Beverages",
            "subcategory":"Bakery",
            "type":"Retail Goods"
        }
    ],
    "sg:phone":"+1 561 338 6300",
    "sg:postcode":"33433",
    "sg:province":"FL",
    "sg:tags":[
        "bagel"
    ],
    "wof:name":"Bread Box",
    "wof:placetype":"venue"
},
  "geometry": {"coordinates":[-80.137553,26.36082],"type":"Point"}
}