{
  "type": "Feature",
  "properties": {
    "iso:country":"US",
    "sg:address":"8405 NW 53rd St",
    "sg:city":"Miami",
    "sg:classifiers":[
        {
            "category":"Manufacturing",
            "subcategory":"Toys & Sporting Goods",
            "type":"Manufacturing & Wholesale Goods"
        }
    ],
    "sg:phone":"+1 305 994 1734",
    "sg:postcode":"33166",
    "sg:province":"FL",
    "sg:tags":[
        "toys-wholesale",
        "manufacturer"
    ],
    "wof:name":"Creative Play International",
    "wof:placetype":"venue"
},
  "geometry": {"coordinates":[-80.334761,25.819854],"type":"Point"}
}