{
  "type": "Feature",
  "properties": {
    "addr:full":"14231 SW 119th Ave Miami FL 33186",
    "addr:housenumber":"14231",
    "addr:postcode":"33186",
    "addr:street":"Sw 119Th Ave",
    "iso:country":"US",
    "sg:address":"14231 SW 119th Ave",
    "sg:city":"Miami",
    "sg:classifiers":[
        {
            "category":"Professional",
            "subcategory":"Management & Consulting",
            "type":"Services"
        }
    ],
    "sg:phone":"+1 305 278 4323",
    "sg:postcode":"33186",
    "sg:province":"FL",
    "sg:tags":[
        "party",
        "planning"
    ],
    "wof:name":"Mega Parties",
    "wof:placetype":"venue"
},
  "geometry": {"coordinates":[-80.38674399999999,25.634654],"type":"Point"}
}