{
  "type": "Feature",
  "properties": {
    "iso:country":"US",
    "sg:address":"3841 68th Ave N",
    "sg:city":"Pinellas Park",
    "sg:classifiers":[
        {
            "category":"Retail",
            "subcategory":"Auto Repair",
            "type":"Services"
        }
    ],
    "sg:phone":"+1 727 526 4148",
    "sg:postcode":"33781",
    "sg:province":"FL",
    "sg:tags":[
        "repairing",
        "automobile"
    ],
    "wof:name":"Just Miata",
    "wof:placetype":"venue"
},
  "geometry": {"coordinates":[-82.68737400000001,27.833858],"type":"Point"}
}