{
  "type": "Feature",
  "properties": {
    "addr:full":"4131 N Canal St Jacksonville FL 32209",
    "addr:housenumber":"4131",
    "addr:postcode":"32209",
    "addr:street":"N Canal St",
    "iso:country":"US",
    "sg:address":"4131 N Canal St",
    "sg:city":"Jacksonville",
    "sg:classifiers":[
        {
            "category":"Manufacturing",
            "subcategory":"Metals",
            "type":"Manufacturing & Wholesale Goods"
        },
        {
            "category":"Building & Trades",
            "subcategory":"Construction",
            "type":"Services"
        },
        {
            "category":"Manufacturing",
            "subcategory":"Building Materials",
            "type":"Manufacturing & Wholesale Goods"
        }
    ],
    "sg:phone":"+1 904 355 0560",
    "sg:postcode":"32209",
    "sg:province":"FL",
    "sg:tags":[
        "steel",
        "detailers",
        "sheet",
        "work",
        "metal-wholesale",
        "fabricator",
        "structural",
        "manufacturer"
    ],
    "wof:name":"Taylor Metals Inc",
    "wof:placetype":"venue"
},
  "geometry": {"coordinates":[-81.697248,30.363799],"type":"Point"}
}