{
  "type": "Feature",
  "properties": {
    "iso:country":"US",
    "sg:address":"1821 Alpine Dr",
    "sg:city":"Navarre",
    "sg:classifiers":[
        {
            "category":"Health Services",
            "subcategory":"Doctor",
            "type":"Services"
        }
    ],
    "sg:phone":"+1 850 939 8229",
    "sg:postcode":"32566",
    "sg:province":"FL",
    "sg:tags":[
        "dentist"
    ],
    "wof:name":"Trawick Orthodontics",
    "wof:placetype":"venue"
},
  "geometry": {"coordinates":[-86.885364,30.399507],"type":"Point"}
}