{
  "type": "Feature",
  "properties": {
    "addr:full":"513 Flotilla Rd West Palm Beach FL 33408",
    "addr:housenumber":"513",
    "addr:postcode":"33408",
    "addr:street":"Flotilla Rd",
    "iso:country":"US",
    "sg:address":"513 Flotilla Rd",
    "sg:city":"West Palm Beach",
    "sg:classifiers":[
        {
            "category":"Wholesale",
            "subcategory":"Durable Goods & Equipment",
            "type":"Manufacturing & Wholesale Goods"
        }
    ],
    "sg:phone":"+1 561 845 9077",
    "sg:postcode":"33408",
    "sg:province":"FL",
    "sg:tags":[
        "representative",
        "manufacturer"
    ],
    "wof:name":"International Process & Equip",
    "wof:placetype":"venue"
},
  "geometry": {"coordinates":[-80.063711,26.812787],"type":"Point"}
}