{
  "type": "Feature",
  "properties": {
    "iso:country":"US",
    "sg:address":"628 5th St N",
    "sg:city":"St Petersburg",
    "sg:classifiers":[
        {
            "category":"Real Estate",
            "subcategory":"Real Estate Agent",
            "type":"Services"
        }
    ],
    "sg:phone":"+1 727 821 6500",
    "sg:postcode":"33701",
    "sg:province":"FL",
    "wof:name":"Sun Quest Properties",
    "wof:placetype":"venue"
},
  "geometry": {"coordinates":[-82.640663,27.779262],"type":"Point"}
}