{
  "type": "Feature",
  "properties": {
    "iso:country":"US",
    "sg:address":"1023 N O St",
    "sg:city":"Lake Worth",
    "sg:classifiers":[
        {
            "category":"Professional",
            "subcategory":"Art Services",
            "type":"Services"
        }
    ],
    "sg:phone":"+1 561 585 7455",
    "sg:postcode":"33460",
    "sg:province":"FL",
    "sg:tags":[
        "graphic",
        "designer"
    ],
    "wof:name":"Elaine Weber Designs Inc",
    "wof:placetype":"venue"
},
  "geometry": {"coordinates":[-80.051084,26.628319],"type":"Point"}
}