{
  "type": "Feature",
  "properties": {
    "iso:country":"US",
    "sg:address":"4100 NW 10th Ave",
    "sg:city":"Fort Lauderdale",
    "sg:classifiers":[
        {
            "category":"Wholesale",
            "subcategory":"Machinery & Supplies",
            "type":"Manufacturing & Wholesale Goods"
        }
    ],
    "sg:phone":"+1 954 491 2099",
    "sg:postcode":"33309",
    "sg:province":"FL",
    "sg:tags":[
        "rep",
        "parts",
        "aircraft",
        "for"
    ],
    "wof:name":"International Aerospace",
    "wof:placetype":"venue"
},
  "geometry": {"coordinates":[-80.157483,26.179321],"type":"Point"}
}