{
  "type": "Feature",
  "properties": {
    "addr:full":"100 S Marjorie Ct Merritt Island FL 32952",
    "addr:housenumber":"100",
    "addr:postcode":"32952",
    "addr:street":"S Marjorie Ct",
    "iso:country":"US",
    "sg:address":"100 S Marjorie Ct",
    "sg:city":"Merritt Island",
    "sg:classifiers":[
        {
            "category":"Personal",
            "type":"Services"
        }
    ],
    "sg:phone":"+1 321 453 6645",
    "sg:postcode":"32952",
    "sg:province":"FL",
    "wof:name":"Raymond Itrurrino Handyman",
    "wof:placetype":"venue"
},
  "geometry": {"coordinates":[-80.66646299999999,28.354453],"type":"Point"}
}