{
  "type": "Feature",
  "properties": {
    "iso:country":"US",
    "sg:address":"1487 NW 54th St",
    "sg:city":"Miami",
    "sg:classifiers":[
        {
            "category":"Personal",
            "subcategory":"Barber",
            "type":"Services"
        }
    ],
    "sg:phone":"+1 305 693 1363",
    "sg:postcode":"33142",
    "sg:province":"FL",
    "wof:name":"Esquire Barber Shop & Clothing",
    "wof:placetype":"venue"
},
  "geometry": {"coordinates":[-80.222099,25.8244],"type":"Point"}
}