{
  "type": "Feature",
  "properties": {
    "addr:full":"9905 Marlin Rd Miami FL 33157",
    "addr:housenumber":"9905",
    "addr:postcode":"33157",
    "addr:street":"Marlin Rd",
    "iso:country":"US",
    "sg:address":"9905 Marlin Rd",
    "sg:city":"Miami",
    "sg:classifiers":[
        {
            "category":"Freight",
            "type":"Transportation"
        }
    ],
    "sg:phone":"+1 305 278 9005",
    "sg:postcode":"33157",
    "sg:province":"FL",
    "sg:tags":[
        "hauling",
        "trucking"
    ],
    "wof:name":"Family One Inc Trucking",
    "wof:placetype":"venue"
},
  "geometry": {"coordinates":[-80.35188599999999,25.584587],"type":"Point"}
}