{
  "type": "Feature",
  "properties": {
    "iso:country":"US",
    "sg:address":"23546 NE 154th Place Rd",
    "sg:city":"Fort Mc Coy",
    "sg:classifiers":[
        {
            "category":"Shopping",
            "subcategory":"Discount & Variety Stores",
            "type":"Retail Goods"
        }
    ],
    "sg:phone":"+1 352 685 0579",
    "sg:postcode":"32134",
    "sg:province":"FL",
    "sg:tags":[
        "merchandise",
        "general"
    ],
    "wof:name":"Gary Lee Withrow Retail",
    "wof:placetype":"venue"
},
  "geometry": {"coordinates":[-81.765097,29.377126],"type":"Point"}
}