{
  "type": "Feature",
  "properties": {
    "addr:full":"1829 SW 29th St Fort Lauderdale FL 33315",
    "addr:housenumber":"1829",
    "addr:postcode":"33315",
    "addr:street":"Sw 29Th St",
    "iso:country":"US",
    "sg:address":"1829 SW 29th St",
    "sg:city":"Fort Lauderdale",
    "sg:classifiers":[
        {
            "category":"Building & Trades",
            "subcategory":"Plumbing",
            "type":"Services"
        }
    ],
    "sg:phone":"+1 954 525 4074",
    "sg:postcode":"33315",
    "sg:province":"FL",
    "sg:tags":[
        "plumbing",
        "contractor"
    ],
    "wof:name":"Father & Son Plumbing Services",
    "wof:placetype":"venue"
},
  "geometry": {"coordinates":[-80.16422900000001,26.088357],"type":"Point"}
}