{
  "type": "Feature",
  "properties": {
    "iso:country":"US",
    "sg:address":"1509 SE 7th St",
    "sg:city":"Okeechobee",
    "sg:classifiers":[
        {
            "category":"Shopping",
            "subcategory":"Used Merchandise",
            "type":"Retail Goods"
        }
    ],
    "sg:phone":"+1 863 763 6347",
    "sg:postcode":"34974",
    "sg:province":"FL",
    "wof:name":"Kiddin Around",
    "wof:placetype":"venue"
},
  "geometry": {"coordinates":[-80.813667,27.237567],"type":"Point"}
}