{
  "type": "Feature",
  "properties": {
    "addr:full":"3176 Shoal Line Blvd Hernando Beach FL 34607",
    "addr:housenumber":"3176",
    "addr:postcode":"34607",
    "addr:street":"Shoal Line Blvd Hernando",
    "iso:country":"US",
    "sg:address":"3176 Shoal Line Blvd",
    "sg:city":"Hernando Beach",
    "sg:classifiers":[
        {
            "category":"Building & Trades",
            "subcategory":"Construction",
            "type":"Services"
        }
    ],
    "sg:phone":"+1 352 596 1619",
    "sg:postcode":"34607",
    "sg:province":"FL",
    "sg:tags":[
        "general",
        "contractor"
    ],
    "wof:name":"Samsson Construction",
    "wof:placetype":"venue"
},
  "geometry": {"coordinates":[-82.650227,28.479198],"type":"Point"}
}