{
  "type": "Feature",
  "properties": {
    "iso:country":"US",
    "sg:address":"2219 NE 5th Ave",
    "sg:city":"Cape Coral",
    "sg:classifiers":[
        {
            "category":"Building & Trades",
            "subcategory":"Cleaning & Sanitation",
            "type":"Services"
        }
    ],
    "sg:phone":"+1 239 458 8159",
    "sg:postcode":"33909",
    "sg:province":"FL",
    "sg:tags":[
        "window"
    ],
    "wof:name":"Diane Carroll A Brite Window",
    "wof:placetype":"venue"
},
  "geometry": {"coordinates":[-81.963009,26.693581],"type":"Point"}
}