{
  "type": "Feature",
  "properties": {
    "addr:full":"16244 Military Trl Delray Beach FL 33484",
    "addr:housenumber":"16244",
    "addr:postcode":"33484",
    "addr:street":"Military Trl",
    "iso:country":"US",
    "sg:address":"16244 Military Trl",
    "sg:city":"Delray Beach",
    "sg:classifiers":[
        {
            "category":"Health Services",
            "subcategory":"Clinic",
            "type":"Services"
        }
    ],
    "sg:phone":"+1 561 499 4314",
    "sg:postcode":"33484",
    "sg:province":"FL",
    "sg:tags":[
        "medical",
        "specialty",
        "outpatient"
    ],
    "wof:name":"Bon-Bone Medical Imaging Inc",
    "wof:placetype":"venue"
},
  "geometry": {"coordinates":[-80.122057,26.436103],"type":"Point"}
}