{
  "type": "Feature",
  "properties": {
    "iso:country":"US",
    "sg:address":"3016 38th St",
    "sg:city":"Orlando",
    "sg:classifiers":[
        {
            "category":"Bus Charters",
            "type":"Transportation"
        }
    ],
    "sg:phone":"+1 407 254 5100",
    "sg:postcode":"32839",
    "sg:province":"FL",
    "sg:tags":[
        "rental"
    ],
    "wof:name":"Bristol Trailways Of Florida",
    "wof:placetype":"venue"
},
  "geometry": {"coordinates":[-81.418515,28.504231],"type":"Point"}
}