{
  "type": "Feature",
  "properties": {
    "iso:country":"US",
    "sg:address":"8120 NW 12th St",
    "sg:city":"Hollywood",
    "sg:classifiers":[
        {
            "category":"Travel",
            "subcategory":"Travel Agent",
            "type":"Entertainment"
        }
    ],
    "sg:phone":"+1 954 392 7394",
    "sg:postcode":"33024",
    "sg:province":"FL",
    "sg:tags":[
        "operator",
        "tour"
    ],
    "wof:name":"1 Lighthouse Tours Corp",
    "wof:placetype":"venue"
},
  "geometry": {"coordinates":[-80.252949,26.019032],"type":"Point"}
}