{
  "type": "Feature",
  "properties": {
    "addr:full":"1024 Avalon Park North Blvd Orlando FL 32828",
    "addr:housenumber":"1024",
    "addr:postcode":"32828",
    "addr:street":"Avalon Park North Blvd",
    "iso:country":"US",
    "sg:address":"1024 Avalon Park North Blvd",
    "sg:city":"Orlando",
    "sg:classifiers":[
        {
            "category":"Restaurant",
            "type":"Food & Drink"
        }
    ],
    "sg:menulink":"http://www.allmenus.com/fl/union-park/122513-quiznos-sub/menu/",
    "sg:phone":"+1 407 207 3255",
    "sg:postcode":"32828",
    "sg:province":"FL",
    "sg:tags":[
        "wrap",
        "american",
        "sandwich"
    ],
    "wof:name":"Quiznos Sub",
    "wof:placetype":"venue"
},
  "geometry": {"coordinates":[-81.14987000000001,28.527748],"type":"Point"}
}