{
  "type": "Feature",
  "properties": {
    "addr:full":"800 Brickell Ave # 300 Miami FL 33131",
    "addr:housenumber":"800",
    "addr:postcode":"33131",
    "addr:street":"Brickell Ave # 300",
    "iso:country":"US",
    "sg:address":"800 Brickell Ave # 300",
    "sg:city":"Miami",
    "sg:classifiers":[
        {
            "category":"Banks & Credit Unions",
            "subcategory":"Financial Services",
            "type":"Services"
        },
        {
            "category":"Professional",
            "subcategory":"Credit Reporting & Collection",
            "type":"Services"
        }
    ],
    "sg:phone":"+1 786 573 5032",
    "sg:postcode":"33131",
    "sg:province":"FL",
    "sg:tags":[
        "repair",
        "investigator",
        "plan",
        "counseling",
        "debt"
    ],
    "wof:name":"A American Debt Consolidation",
    "wof:placetype":"venue"
},
  "geometry": {"coordinates":[-80.190781,25.76618],"type":"Point"}
}