{
  "type": "Feature",
  "properties": {
    "addr:full":"21126 State Rd 54 Lutz FL 33558",
    "addr:housenumber":"21126;54",
    "addr:postcode":"33558",
    "addr:street":"State Rd",
    "iso:country":"US",
    "sg:address":"21126 State Rd 54",
    "sg:city":"Lutz",
    "sg:classifiers":[
        {
            "category":"Home & Garden",
            "subcategory":"Furniture",
            "type":"Retail Goods"
        }
    ],
    "sg:phone":"+1 813 909 7777",
    "sg:postcode":"33558",
    "sg:province":"FL",
    "sg:tags":[
        "bedding"
    ],
    "wof:name":"Beds Beds Beds Inc",
    "wof:placetype":"venue"
},
  "geometry": {"coordinates":[-82.46726,28.19222],"type":"Point"}
}