{
  "type": "Feature",
  "properties": {
    "iso:country":"US",
    "sg:address":"230 Lochmond Dr",
    "sg:city":"Casselberry",
    "sg:classifiers":[
        {
            "category":"Farming",
            "subcategory":"Farm",
            "type":"Manufacturing & Wholesale Goods"
        }
    ],
    "sg:phone":"+1 407 830 0949",
    "sg:postcode":"32730",
    "sg:province":"FL",
    "sg:tags":[
        "crop",
        "general"
    ],
    "wof:name":"Fpb Farm Corp",
    "wof:placetype":"venue"
},
  "geometry": {"coordinates":[-81.333539,28.652438],"type":"Point"}
}