{
  "type": "Feature",
  "properties": {
    "addr:full":"106 Hillcrest Dr Stuart FL 34996",
    "addr:housenumber":"106",
    "addr:postcode":"34996",
    "addr:street":"Hillcrest Dr",
    "iso:country":"US",
    "sg:address":"106 Hillcrest Dr",
    "sg:city":"Stuart",
    "sg:classifiers":[
        {
            "category":"Wholesale",
            "subcategory":"Sporting Goods",
            "type":"Manufacturing & Wholesale Goods"
        }
    ],
    "sg:phone":"+1 772 219 2570",
    "sg:postcode":"34996",
    "sg:province":"FL",
    "wof:name":"Chang Young Inc",
    "wof:placetype":"venue"
},
  "geometry": {"coordinates":[-80.200045,27.196934],"type":"Point"}
}