{
  "type": "Feature",
  "properties": {
    "addr:full":"910 Lochmont Dr Brandon FL 33511",
    "addr:housenumber":"910",
    "addr:postcode":"33511",
    "addr:street":"Lochmont Dr",
    "iso:country":"US",
    "sg:address":"910 Lochmont Dr",
    "sg:city":"Brandon",
    "sg:classifiers":[
        {
            "category":"Shopping",
            "subcategory":"Clothing, Apparel, & Fashions",
            "type":"Retail Goods"
        }
    ],
    "sg:phone":"+1 813 380 5169",
    "sg:postcode":"33511",
    "sg:province":"FL",
    "sg:tags":[
        "furnishing"
    ],
    "wof:name":"Florida's Men Shop",
    "wof:placetype":"venue"
},
  "geometry": {"coordinates":[-82.31043,27.920574],"type":"Point"}
}