{
  "type": "Feature",
  "properties": {
    "addr:full":"2084 J and C Blvd Naples FL 34109",
    "addr:housenumber":"2084;and",
    "addr:postcode":"34109",
    "addr:street":"C Blvd",
    "iso:country":"US",
    "sg:address":"2084 J and C Blvd",
    "sg:city":"Naples",
    "sg:classifiers":[
        {
            "category":"Wholesale",
            "subcategory":"Electrical",
            "type":"Manufacturing & Wholesale Goods"
        }
    ],
    "sg:phone":"+1 239 591 1313",
    "sg:postcode":"34109",
    "sg:province":"FL",
    "sg:tags":[
        "electric",
        "motor"
    ],
    "wof:name":"Naples Electric Motor Works",
    "wof:placetype":"venue"
},
  "geometry": {"coordinates":[-81.781458,26.223654],"type":"Point"}
}