{
  "type": "Feature",
  "properties": {
    "iso:country":"US",
    "sg:address":"5101 Palm Hill Dr",
    "sg:city":"West Palm Beach",
    "sg:classifiers":[
        {
            "category":"Real Estate",
            "subcategory":"Real Estate Operator",
            "type":"Services"
        }
    ],
    "sg:phone":"+1 561 965 5616",
    "sg:postcode":"33415",
    "sg:province":"FL",
    "sg:tags":[
        "building",
        "apartment"
    ],
    "wof:name":"Palm Hill Apartments",
    "wof:placetype":"venue"
},
  "geometry": {"coordinates":[-80.121894,26.654054],"type":"Point"}
}