{
  "type": "Feature",
  "properties": {
    "addr:full":"3728 Phillips Hwy Jacksonville FL 32207",
    "addr:housenumber":"3728",
    "addr:postcode":"32207",
    "addr:street":"Phillips Hwy",
    "iso:country":"US",
    "sg:address":"3728 Phillips Hwy",
    "sg:city":"Jacksonville",
    "sg:classifiers":[
        {
            "category":"Wholesale",
            "subcategory":"Office Equipment",
            "type":"Manufacturing & Wholesale Goods"
        }
    ],
    "sg:phone":"+1 904 396 2288",
    "sg:postcode":"32207",
    "sg:province":"FL",
    "sg:tags":[
        "machine",
        "duplicating",
        "copying"
    ],
    "sg:website":"www.copytronics.com",
    "wof:name":"Copytronics Inc",
    "wof:placetype":"venue"
},
  "geometry": {"coordinates":[-81.62900399999999,30.28108],"type":"Point"}
}