{
  "type": "Feature",
  "properties": {
    "addr:full":"525 Margaret St Merritt Island FL 32953",
    "addr:housenumber":"525",
    "addr:postcode":"32953",
    "addr:street":"Margaret St",
    "iso:country":"US",
    "sg:address":"525 Margaret St",
    "sg:city":"Merritt Island",
    "sg:classifiers":[
        {
            "category":"Professional",
            "subcategory":"Business Services",
            "type":"Services"
        }
    ],
    "sg:phone":"+1 321 454 4282",
    "sg:postcode":"32953",
    "sg:province":"FL",
    "sg:tags":[
        "appraiser"
    ],
    "wof:name":"Pro Team & Assoc",
    "wof:placetype":"venue"
},
  "geometry": {"coordinates":[-80.688356,28.366975],"type":"Point"}
}