{
  "type": "Feature",
  "properties": {
    "iso:country":"US",
    "sg:address":"2002 N Parkton Dr",
    "sg:city":"Deltona",
    "sg:classifiers":[
        {
            "category":"Building & Trades",
            "subcategory":"Construction",
            "type":"Services"
        }
    ],
    "sg:phone":"+1 386 789 6224",
    "sg:postcode":"32725",
    "sg:province":"FL",
    "sg:tags":[
        "layer",
        "carpet"
    ],
    "wof:name":"Marty's Carpet Svc",
    "wof:placetype":"venue"
},
  "geometry": {"coordinates":[-81.26622,28.918804],"type":"Point"}
}