{
  "type": "Feature",
  "properties": {
    "addr:full":"318 NE 2nd Ave Delray Beach FL 33444",
    "addr:housenumber":"318",
    "addr:postcode":"33444",
    "addr:street":"Ne 2Nd Ave",
    "iso:country":"US",
    "sg:address":"318 NE 2nd Ave",
    "sg:city":"Delray Beach",
    "sg:classifiers":[
        {
            "category":"Shopping",
            "subcategory":"Pharmacy",
            "type":"Retail Goods"
        }
    ],
    "sg:phone":"+1 561 272 5754",
    "sg:postcode":"33444",
    "sg:province":"FL",
    "wof:name":"CVS Pharmacy",
    "wof:placetype":"venue"
},
  "geometry": {"coordinates":[-80.071315,26.468816],"type":"Point"}
}