{
  "type": "Feature",
  "properties": {
    "addr:full":"900 NW 17th Ave Boca Raton FL 33486",
    "addr:housenumber":"900",
    "addr:postcode":"33486",
    "addr:street":"Nw 17Th Ave",
    "iso:country":"US",
    "sg:address":"900 NW 17th Ave",
    "sg:city":"Boca Raton",
    "sg:classifiers":[
        {
            "category":"Wholesale",
            "subcategory":"Vending Machines",
            "type":"Manufacturing & Wholesale Goods"
        }
    ],
    "sg:phone":"+1 561 393 9729",
    "sg:postcode":"33486",
    "sg:province":"FL",
    "sg:tags":[
        "operator"
    ],
    "wof:name":"Snack A Way Vending",
    "wof:placetype":"venue"
},
  "geometry": {"coordinates":[-80.119072,26.359074],"type":"Point"}
}