{
  "type": "Feature",
  "properties": {
    "iso:country":"US",
    "sg:address":"1150 NE 4th Ave",
    "sg:city":"Boca Raton",
    "sg:classifiers":[
        {
            "category":"Professional",
            "subcategory":"Management & Consulting",
            "type":"Services"
        }
    ],
    "sg:phone":"+1 561 865 9570",
    "sg:postcode":"33432",
    "sg:province":"FL",
    "sg:tags":[
        "marketing",
        "consultant"
    ],
    "wof:name":"Archetype Discoveries World Wd",
    "wof:placetype":"venue"
},
  "geometry": {"coordinates":[-80.079869,26.361518],"type":"Point"}
}