{
  "type": "Feature",
  "properties": {
    "iso:country":"US",
    "sg:address":"11300 SW 77th Ave",
    "sg:city":"Miami",
    "sg:classifiers":[
        {
            "category":"Building & Trades",
            "subcategory":"Landscaping Services",
            "type":"Services"
        }
    ],
    "sg:phone":"+1 305 607 3268",
    "sg:postcode":"33156",
    "sg:province":"FL",
    "sg:tags":[
        "aged",
        "homes-institutional"
    ],
    "wof:name":"Our Group Home Inc",
    "wof:placetype":"venue"
},
  "geometry": {"coordinates":[-80.31855400000001,25.665837],"type":"Point"}
}