{
  "type": "Feature",
  "properties": {
    "iso:country":"US",
    "sg:address":"8225 State Rd 54",
    "sg:city":"New Port Richey",
    "sg:classifiers":[
        {
            "category":"Professional",
            "subcategory":"Research",
            "type":"Services"
        },
        {
            "category":"Professional",
            "subcategory":"Management & Consulting",
            "type":"Services"
        }
    ],
    "sg:phone":"+1 727 376 1770",
    "sg:postcode":"34655",
    "sg:province":"FL",
    "sg:tags":[
        "marketing",
        "medical",
        "education",
        "agency",
        "consultant"
    ],
    "wof:name":"R & R Healthcare Communication",
    "wof:placetype":"venue"
},
  "geometry": {"coordinates":[-82.677852,28.206833],"type":"Point"}
}