{
  "type": "Feature",
  "properties": {
    "addr:full":"1906 Entra Pl Tampa FL 33612",
    "addr:housenumber":"1906",
    "addr:postcode":"33612",
    "addr:street":"Entra Pl",
    "iso:country":"US",
    "sg:address":"1906 Entra Pl",
    "sg:city":"Tampa",
    "sg:classifiers":[
        {
            "category":"Building & Trades",
            "subcategory":"Construction",
            "type":"Services"
        }
    ],
    "sg:phone":"+1 813 935 3290",
    "sg:postcode":"33612",
    "sg:province":"FL",
    "sg:tags":[
        "contractor"
    ],
    "wof:name":"Alvarez Roofing",
    "wof:placetype":"venue"
},
  "geometry": {"coordinates":[-82.477822,28.035453],"type":"Point"}
}