{
  "type": "Feature",
  "properties": {
    "iso:country":"US",
    "sg:address":"660 Linton Blvd",
    "sg:city":"Delray Beach",
    "sg:classifiers":[
        {
            "category":"Arts & Performance",
            "subcategory":"Theater",
            "type":"Entertainment"
        }
    ],
    "sg:phone":"+1 561 330 2253",
    "sg:postcode":"33444",
    "sg:province":"FL",
    "sg:tags":[
        "bureau"
    ],
    "wof:name":"G & G Sports Entrtn Group Inc",
    "wof:placetype":"venue"
},
  "geometry": {"coordinates":[-80.08061499999999,26.43977],"type":"Point"}
}