{
  "type": "Feature",
  "properties": {
    "iso:country":"US",
    "sg:address":"2317 NW 30th St",
    "sg:city":"Fort Lauderdale",
    "sg:classifiers":[
        {
            "category":"Shopping",
            "subcategory":"Gifts & Souvenirs",
            "type":"Retail Goods"
        }
    ],
    "sg:phone":"+1 954 733 6440",
    "sg:postcode":"33311",
    "sg:province":"FL",
    "wof:name":"Balloonprintingcom",
    "wof:placetype":"venue"
},
  "geometry": {"coordinates":[-80.173846,26.16383],"type":"Point"}
}