{
  "type": "Feature",
  "properties": {
    "addr:full":"4110 Winners Cir Sarasota FL 34238",
    "addr:housenumber":"4110",
    "addr:postcode":"34238",
    "addr:street":"Winners Cir",
    "iso:country":"US",
    "sg:address":"4110 Winners Cir",
    "sg:city":"Sarasota",
    "sg:classifiers":[
        {
            "category":"Real Estate",
            "subcategory":"Real Estate Agent",
            "type":"Services"
        }
    ],
    "sg:phone":"+1 941 923 8002",
    "sg:postcode":"34238",
    "sg:province":"FL",
    "wof:name":"Beztak II Limited Partnership",
    "wof:placetype":"venue"
},
  "geometry": {"coordinates":[-82.484313,27.2339],"type":"Point"}
}