{
  "type": "Feature",
  "properties": {
    "iso:country":"US",
    "sg:address":"817 Craig St",
    "sg:city":"New Smyrna Beach",
    "sg:classifiers":[
        {
            "category":"Banks & Credit Unions",
            "subcategory":"Investment Brokerage",
            "type":"Services"
        }
    ],
    "sg:phone":"+1 386 427 4470",
    "sg:postcode":"32168",
    "sg:province":"FL",
    "sg:tags":[
        "security"
    ],
    "wof:name":"Raymond James",
    "wof:placetype":"venue"
},
  "geometry": {"coordinates":[-80.931895,29.038144],"type":"Point"}
}