{
  "type": "Feature",
  "properties": {
    "iso:country":"US",
    "sg:address":"1120 Homestead Rd N",
    "sg:city":"Lehigh Acres",
    "sg:classifiers":[
        {
            "category":"Government",
            "subcategory":"Post Office",
            "type":"Public Place"
        }
    ],
    "sg:phone":"+1 239 369 2159",
    "sg:postcode":"33936",
    "sg:province":"FL",
    "sg:tags":[
        "postal",
        "us"
    ],
    "wof:name":"Lehigh Acres PO",
    "wof:placetype":"venue"
},
  "geometry": {"coordinates":[-81.64886300000001,26.605963],"type":"Point"}
}