{
  "type": "Feature",
  "properties": {
    "addr:full":"5781 Lisa Lynn Rd Keystone Heights FL 32656",
    "addr:housenumber":"5781",
    "addr:postcode":"32656",
    "addr:street":"Lisa Lynn Rd",
    "iso:country":"US",
    "sg:address":"5781 Lisa Lynn Rd",
    "sg:city":"Keystone Heights",
    "sg:classifiers":[
        {
            "category":"Building & Trades",
            "subcategory":"Construction",
            "type":"Services"
        }
    ],
    "sg:phone":"+1 352 473 0534",
    "sg:postcode":"32656",
    "sg:province":"FL",
    "sg:tags":[
        "water",
        "well",
        "drilling"
    ],
    "wof:name":"Bronco Drilling Inc",
    "wof:placetype":"venue"
},
  "geometry": {"coordinates":[-81.89582900000001,29.84191],"type":"Point"}
}