{
  "type": "Feature",
  "properties": {
    "iso:country":"US",
    "sg:address":"265 Dorchester Dr",
    "sg:city":"Venice",
    "sg:classifiers":[
        {
            "category":"Health Services",
            "subcategory":"Health Practitioner",
            "type":"Services"
        }
    ],
    "sg:phone":"+1 941 429 5929",
    "sg:postcode":"34293",
    "sg:province":"FL",
    "sg:tags":[
        "psychotherapist"
    ],
    "wof:name":"Billie W Gimenez",
    "wof:placetype":"venue"
},
  "geometry": {"coordinates":[-82.38167,27.058338],"type":"Point"}
}