{
  "type": "Feature",
  "properties": {
    "iso:country":"US",
    "sg:address":"1700 S 23rd St",
    "sg:city":"Fort Pierce",
    "sg:classifiers":[
        {
            "category":"Health Services",
            "subcategory":"Hospital",
            "type":"Services"
        }
    ],
    "sg:phone":"+1 772 467 8132",
    "sg:postcode":"34950",
    "sg:province":"FL",
    "wof:name":"Company Care At Lawnwood",
    "wof:placetype":"venue"
},
  "geometry": {"coordinates":[-80.34739999999999,27.430149],"type":"Point"}
}