{
  "type": "Feature",
  "properties": {
    "iso:country":"US",
    "sg:address":"19 Louise St",
    "sg:city":"St Augustine",
    "sg:classifiers":[
        {
            "category":"Wholesale",
            "subcategory":"Jewelry",
            "type":"Manufacturing & Wholesale Goods"
        }
    ],
    "sg:phone":"+1 904 819 1972",
    "sg:postcode":"32084",
    "sg:province":"FL",
    "sg:tags":[
        "beads",
        "stone"
    ],
    "wof:name":"Aquatropicals",
    "wof:placetype":"venue"
},
  "geometry": {"coordinates":[-81.32605,29.919082],"type":"Point"}
}