{
  "type": "Feature",
  "properties": {
    "iso:country":"US",
    "sg:address":"200 Grapetree Dr",
    "sg:city":"Key Biscayne",
    "sg:classifiers":[
        {
            "category":"Building & Trades",
            "subcategory":"Locksmith",
            "type":"Services"
        }
    ],
    "sg:phone":"+1 305 744 5010",
    "sg:postcode":"33149",
    "sg:province":"FL",
    "sg:tags":[
        "key"
    ],
    "wof:name":"1 2 3 24 Hour A Locksmith",
    "wof:placetype":"venue"
},
  "geometry": {"coordinates":[-80.16001300000001,25.684699],"type":"Point"}
}