{
  "type": "Feature",
  "properties": {
    "iso:country":"US",
    "sg:address":"24295 US Hwy 331 S",
    "sg:city":"Santa Rosa Beach",
    "sg:classifiers":[
        {
            "category":"Shopping",
            "subcategory":"Used Merchandise",
            "type":"Retail Goods"
        }
    ],
    "sg:phone":"+1 850 267 5600",
    "sg:postcode":"32459",
    "sg:province":"FL",
    "sg:tags":[
        "antique"
    ],
    "wof:name":"Kathleen's Kottage",
    "wof:placetype":"venue"
},
  "geometry": {"coordinates":[-86.17401099999999,30.388161],"type":"Point"}
}