{
  "type": "Feature",
  "properties": {
    "addr:full":"400 N Federal Hwy Hallandale FL 33009",
    "addr:housenumber":"400",
    "addr:postcode":"33009",
    "addr:street":"N Federal Hwy",
    "iso:country":"US",
    "sg:address":"400 N Federal Hwy",
    "sg:city":"Hallandale",
    "sg:classifiers":[
        {
            "category":"Professional",
            "subcategory":"Lawyer & Legal Services",
            "type":"Services"
        }
    ],
    "sg:phone":"+1 954 455 9300",
    "sg:postcode":"33009",
    "sg:province":"FL",
    "wof:name":"Rodier & Rodier Attys At Law",
    "wof:placetype":"venue"
},
  "geometry": {"coordinates":[-80.142461,25.99082],"type":"Point"}
}