{
  "type": "Feature",
  "properties": {
    "addr:full":"2960 Riverside Dr Pompano Beach FL 33065",
    "addr:housenumber":"2960",
    "addr:postcode":"33065",
    "addr:street":"Riverside Dr",
    "iso:country":"US",
    "sg:address":"2960 Riverside Dr",
    "sg:city":"Pompano Beach",
    "sg:classifiers":[
        {
            "category":"Professional",
            "subcategory":"Computer Services",
            "type":"Services"
        }
    ],
    "sg:phone":"+1 954 796 6017",
    "sg:postcode":"33065",
    "sg:province":"FL",
    "sg:tags":[
        "programing",
        "custom"
    ],
    "wof:name":"Abiram Technologies Inc",
    "wof:placetype":"venue"
},
  "geometry": {"coordinates":[-80.23536300000001,26.264087],"type":"Point"}
}