{
  "type": "Feature",
  "properties": {
    "iso:country":"US",
    "sg:address":"324 Dorset Dr",
    "sg:city":"Cocoa Beach",
    "sg:classifiers":[
        {
            "category":"Building & Trades",
            "subcategory":"Construction",
            "type":"Services"
        }
    ],
    "sg:phone":"+1 321 960 1033",
    "sg:postcode":"32931",
    "sg:province":"FL",
    "sg:tags":[
        "handyman"
    ],
    "wof:name":"M & B Reed Enterprises Inc",
    "wof:placetype":"venue"
},
  "geometry": {"coordinates":[-80.613356,28.364206],"type":"Point"}
}