{
  "type": "Feature",
  "properties": {
    "iso:country":"US",
    "sg:address":"11950 5th St E",
    "sg:city":"Saint Petersburg",
    "sg:classifiers":[
        {
            "category":"Shopping",
            "subcategory":"Shoes",
            "type":"Retail Goods"
        }
    ],
    "sg:phone":"+1 727 360 4194",
    "sg:postcode":"33706",
    "sg:province":"FL",
    "wof:name":"Closeout Footwear Inc",
    "wof:placetype":"venue"
},
  "geometry": {"coordinates":[-82.769317,27.779756],"type":"Point"}
}