{
  "type": "Feature",
  "properties": {
    "iso:country":"US",
    "sg:address":"3010 Diana Dr",
    "sg:city":"Zephyrhills",
    "sg:classifiers":[
        {
            "category":"Shopping",
            "type":"Retail Goods"
        }
    ],
    "sg:phone":"+1 813 780 8187",
    "sg:postcode":"33541",
    "sg:province":"FL",
    "sg:tags":[
        "equipment",
        "beer",
        "supply"
    ],
    "wof:name":"Tap Technology",
    "wof:placetype":"venue"
},
  "geometry": {"coordinates":[-82.22142100000001,28.203121],"type":"Point"}
}