{
  "type": "Feature",
  "properties": {
    "iso:country":"US",
    "sg:address":"4025 Highway 90",
    "sg:city":"Milton",
    "sg:classifiers":[
        {
            "category":"Professional",
            "subcategory":"Business Services",
            "type":"Services"
        }
    ],
    "sg:phone":"+1 850 995 4828",
    "sg:postcode":"32571",
    "sg:province":"FL",
    "sg:tags":[
        "mail",
        "shipping"
    ],
    "wof:name":"Pace Contract Station",
    "wof:placetype":"venue"
},
  "geometry": {"coordinates":[-87.156476,30.601317],"type":"Point"}
}