{
  "type": "Feature",
  "properties": {
    "addr:full":"1550 S Highland Ave Clearwater FL 33756",
    "addr:housenumber":"1550",
    "addr:postcode":"33756",
    "addr:street":"S Highland Ave",
    "iso:country":"US",
    "sg:address":"1550 S Highland Ave",
    "sg:city":"Clearwater",
    "sg:classifiers":[
        {
            "category":"Restaurant",
            "type":"Food & Drink"
        }
    ],
    "sg:phone":"+1 727 441 4727",
    "sg:postcode":"33756",
    "sg:province":"FL",
    "wof:name":"Daytona Drive-Thru Inc",
    "wof:placetype":"venue"
},
  "geometry": {"coordinates":[-82.77510599999999,27.940656],"type":"Point"}
}