{
  "type": "Feature",
  "properties": {
    "addr:full":"7600 US Hwy 19 Pinellas Park FL 33781",
    "addr:housenumber":"7600",
    "addr:postcode":"33781",
    "addr:street":"Us Hwy 19",
    "iso:country":"US",
    "sg:address":"7600 US Hwy 19",
    "sg:city":"Pinellas Park",
    "sg:classifiers":[
        {
            "category":"Banks & Credit Unions",
            "subcategory":"Bank",
            "type":"Services"
        }
    ],
    "sg:phone":"+1 727 892 2000",
    "sg:postcode":"33781",
    "sg:province":"FL",
    "wof:name":"Wachovia Bank",
    "wof:placetype":"venue"
},
  "geometry": {"coordinates":[-82.686331,27.842882],"type":"Point"}
}