{
  "type": "Feature",
  "properties": {
    "addr:full":"4907 NE 9th Ave Oakland Park FL 33334",
    "addr:housenumber":"4907",
    "addr:postcode":"33334",
    "addr:street":"Ne 9Th Ave",
    "iso:country":"US",
    "sg:address":"4907 NE 9th Ave",
    "sg:city":"Oakland Park",
    "sg:classifiers":[
        {
            "category":"Health Services",
            "subcategory":"Health Practitioner",
            "type":"Services"
        }
    ],
    "sg:phone":"+1 954 489 1144",
    "sg:postcode":"33334",
    "sg:province":"FL",
    "sg:tags":[
        "acupuncture"
    ],
    "wof:name":"Acupuncture Physician Serena E",
    "wof:placetype":"venue"
},
  "geometry": {"coordinates":[-80.13546100000001,26.188723],"type":"Point"}
}