{
  "type": "Feature",
  "properties": {
    "addr:full":"1110 S Federal Hwy Delray Beach FL 33483",
    "addr:housenumber":"1110",
    "addr:postcode":"33483",
    "addr:street":"S Federal Hwy",
    "iso:country":"US",
    "sg:address":"1110 S Federal Hwy",
    "sg:city":"Delray Beach",
    "sg:classifiers":[
        {
            "category":"Wholesale",
            "subcategory":"Furniture",
            "type":"Manufacturing & Wholesale Goods"
        }
    ],
    "sg:phone":"+1 561 279 7338",
    "sg:postcode":"33483",
    "sg:province":"FL",
    "wof:name":"Office Depot",
    "wof:placetype":"venue"
},
  "geometry": {"coordinates":[-80.06764,26.445081],"type":"Point"}
}