{
  "type": "Feature",
  "properties": {
    "iso:country":"US",
    "sg:address":"639 E Ocean Ave",
    "sg:city":"Boynton Beach",
    "sg:classifiers":[
        {
            "category":"Social Services",
            "type":"Services"
        }
    ],
    "sg:phone":"+1 561 704 6506",
    "sg:postcode":"33435",
    "sg:province":"FL",
    "sg:tags":[
        "counselor",
        "marriage",
        "family"
    ],
    "wof:name":"Karen Loomis",
    "wof:placetype":"venue"
},
  "geometry": {"coordinates":[-80.05779099999999,26.527184],"type":"Point"}
}