{
  "type": "Feature",
  "properties": {
    "addr:full":"15706 60th Pl N Loxahatchee FL 33470",
    "addr:housenumber":"15706",
    "addr:postcode":"33470",
    "addr:street":"60Th Pl N",
    "iso:country":"US",
    "sg:address":"15706 60th Pl N",
    "sg:city":"Loxahatchee",
    "sg:classifiers":[
        {
            "category":"Building & Trades",
            "subcategory":"Construction",
            "type":"Services"
        }
    ],
    "sg:phone":"+1 561 791 4531",
    "sg:postcode":"33470",
    "sg:province":"FL",
    "sg:tags":[
        "hanging",
        "contractor"
    ],
    "wof:name":"James Dahl",
    "wof:placetype":"venue"
},
  "geometry": {"coordinates":[-80.28845699999999,26.766562],"type":"Point"}
}