{
  "type": "Feature",
  "properties": {
    "addr:full":"9271 Royal Palm Ave New Port Richey FL 34654",
    "addr:housenumber":"9271",
    "addr:postcode":"34654",
    "addr:street":"Royal Palm Ave",
    "iso:country":"US",
    "sg:address":"9271 Royal Palm Ave",
    "sg:city":"New Port Richey",
    "sg:classifiers":[
        {
            "category":"Freight",
            "type":"Transportation"
        }
    ],
    "sg:phone":"+1 727 919 0346",
    "sg:postcode":"34654",
    "sg:province":"FL",
    "sg:tags":[
        "trucking"
    ],
    "wof:name":"G P III Truck Inc",
    "wof:placetype":"venue"
},
  "geometry": {"coordinates":[-82.66152700000001,28.285836],"type":"Point"}
}