{
  "type": "Feature",
  "properties": {
    "iso:country":"US",
    "sg:address":"20572 Links Cir",
    "sg:city":"Boca Raton",
    "sg:classifiers":[
        {
            "category":"Banks & Credit Unions",
            "subcategory":"Investment Brokerage",
            "type":"Services"
        }
    ],
    "sg:phone":"+1 561 487 4647",
    "sg:postcode":"33434",
    "sg:province":"FL",
    "sg:tags":[
        "security"
    ],
    "wof:name":"Richard & Jeanne Spring",
    "wof:placetype":"venue"
},
  "geometry": {"coordinates":[-80.15137199999999,26.371395],"type":"Point"}
}