{
  "type": "Feature",
  "properties": {
    "addr:full":"170 S Orlando Ave Cocoa Beach FL 32931",
    "addr:housenumber":"170",
    "addr:postcode":"32931",
    "addr:street":"S Orlando Ave",
    "iso:country":"US",
    "sg:address":"170 S Orlando Ave",
    "sg:city":"Cocoa Beach",
    "sg:classifiers":[
        {
            "category":"Building & Trades",
            "subcategory":"Construction",
            "type":"Services"
        }
    ],
    "sg:phone":"+1 321 784 8226",
    "sg:postcode":"32931",
    "sg:province":"FL",
    "sg:tags":[
        "hanging",
        "contractor"
    ],
    "wof:name":"Ejs Painting Co",
    "wof:placetype":"venue"
},
  "geometry": {"coordinates":[-80.610146,28.316125],"type":"Point"}
}