{
  "type": "Feature",
  "properties": {
    "iso:country":"US",
    "sg:address":"4717 SW 28th Ave",
    "sg:city":"Fort Lauderdale",
    "sg:phone":"+1 954 962 8997",
    "sg:postcode":"33312",
    "sg:province":"FL",
    "sg:tags":[
        "equipment",
        "commercial"
    ],
    "wof:name":"A&A A/C & Restaurant Equipment",
    "wof:placetype":"venue"
},
  "geometry": {"coordinates":[-80.179163,26.06279],"type":"Point"}
}