{
  "type": "Feature",
  "properties": {
    "iso:country":"US",
    "sg:address":"5440 Schenck Ave",
    "sg:city":"Rockledge",
    "sg:classifiers":[
        {
            "category":"Wholesale",
            "subcategory":"Beer",
            "type":"Manufacturing & Wholesale Goods"
        },
        {
            "category":"Food & Beverages",
            "subcategory":"Liquor & Beverages",
            "type":"Retail Goods"
        }
    ],
    "sg:phone":"+1 321 636 7826",
    "sg:postcode":"32955",
    "sg:province":"FL",
    "sg:tags":[
        "bottler",
        "ale-wholesale",
        "beverages-distributors",
        "ale",
        "wine",
        "manufacturer"
    ],
    "sg:website":"http://www.schenckco.com",
    "wof:name":"Schenck Company",
    "wof:placetype":"venue"
},
  "geometry": {"coordinates":[-80.691551,28.266639],"type":"Point"}
}