{
  "type": "Feature",
  "properties": {
    "iso:country":"US",
    "sg:address":"221 NW 37th St",
    "sg:city":"Fort Lauderdale",
    "sg:classifiers":[
        {
            "category":"Personal",
            "subcategory":"Beauty Salon",
            "type":"Services"
        }
    ],
    "sg:phone":"+1 954 565 3758",
    "sg:postcode":"33309",
    "sg:province":"FL",
    "sg:tags":[
        "shop",
        "merchandise"
    ],
    "wof:name":"Unique Mailboxes By Dee Frank",
    "wof:placetype":"venue"
},
  "geometry": {"coordinates":[-80.14743799999999,26.173149],"type":"Point"}
}