{
  "type": "Feature",
  "properties": {
    "iso:country":"US",
    "sg:address":"2451 Brickell Ave Apt 17R",
    "sg:city":"Miami",
    "sg:classifiers":[
        {
            "category":"Education",
            "subcategory":"Special Training",
            "type":"Public Place"
        }
    ],
    "sg:phone":"+1 305 858 4528",
    "sg:postcode":"33129",
    "sg:province":"FL",
    "sg:tags":[
        "school",
        "tutoring",
        "language"
    ],
    "wof:name":"Conversationally Yours Certfd Trnsltrs & Intrprtrs",
    "wof:placetype":"venue"
},
  "geometry": {"coordinates":[-80.2024,25.7512],"type":"Point"}
}