{
  "type": "Feature",
  "properties": {
    "iso:country":"US",
    "sg:address":"5 Seagate Blvd",
    "sg:city":"Key Largo",
    "sg:classifiers":[
        {
            "category":"Recreation",
            "subcategory":"Marina",
            "type":"Entertainment"
        }
    ],
    "sg:phone":"+1 305 453 0101",
    "sg:postcode":"33037",
    "sg:province":"FL",
    "wof:name":"G & S Marine Enterprise Inc",
    "wof:placetype":"venue"
},
  "geometry": {"coordinates":[-80.440179,25.088265],"type":"Point"}
}