{
  "type": "Feature",
  "properties": {
    "iso:country":"US",
    "sg:address":"2543 Rosselle St",
    "sg:city":"Jacksonville",
    "sg:classifiers":[
        {
            "category":"Social Services",
            "subcategory":"Adult Care",
            "type":"Services"
        }
    ],
    "sg:phone":"+1 904 384 5683",
    "sg:postcode":"32204",
    "sg:province":"FL",
    "sg:tags":[
        "foster"
    ],
    "wof:name":"Jacksonville Youth Sanctuary",
    "wof:placetype":"venue"
},
  "geometry": {"coordinates":[-81.69192,30.319372],"type":"Point"}
}