{
  "type": "Feature",
  "properties": {
    "iso:country":"US",
    "sg:address":"9415 SW 72nd St Ste 125",
    "sg:city":"Miami",
    "sg:classifiers":[
        {
            "category":"Banks & Credit Unions",
            "subcategory":"Financial Services",
            "type":"Services"
        }
    ],
    "sg:phone":"+1 305 270 0500",
    "sg:postcode":"33173",
    "sg:province":"FL",
    "sg:tags":[
        "broker",
        "mortgage"
    ],
    "wof:name":"Nationwide Mortgage Co",
    "wof:placetype":"venue"
},
  "geometry": {"coordinates":[-80.346199,25.701799],"type":"Point"}
}