{
  "type": "Feature",
  "properties": {
    "addr:full":"7327 NW 173rd Dr Apt 102 Hialeah FL 33015",
    "addr:housenumber":"7327;102",
    "addr:postcode":"33015",
    "addr:street":"Nw 173Rd Dr Apt",
    "iso:country":"US",
    "sg:address":"7327 NW 173rd Dr Apt 102",
    "sg:city":"Hialeah",
    "sg:classifiers":[
        {
            "category":"Building & Trades",
            "subcategory":"Construction",
            "type":"Services"
        }
    ],
    "sg:phone":"+1 305 824 0084",
    "sg:postcode":"33015",
    "sg:province":"FL",
    "sg:tags":[
        "contractor"
    ],
    "wof:name":"Capital Construction Management",
    "wof:placetype":"venue"
},
  "geometry": {"coordinates":[-80.31905500000001,25.928732],"type":"Point"}
}