{
  "type": "Feature",
  "properties": {
    "iso:country":"US",
    "sg:address":"778 Main St",
    "sg:city":"Dunedin",
    "sg:classifiers":[
        {
            "category":"Retail",
            "subcategory":"Auto Repair",
            "type":"Services"
        }
    ],
    "sg:phone":"+1 727 734 4011",
    "sg:postcode":"34698",
    "sg:province":"FL",
    "sg:tags":[
        "transmission"
    ],
    "wof:name":"Dunedin Transmission",
    "wof:placetype":"venue"
},
  "geometry": {"coordinates":[-82.78154000000001,28.016269],"type":"Point"}
}