{
  "type": "Feature",
  "properties": {
    "iso:country":"US",
    "sg:address":"680 N State Rd 415",
    "sg:city":"Osteen",
    "sg:classifiers":[
        {
            "category":"Building & Trades",
            "subcategory":"Construction",
            "type":"Services"
        }
    ],
    "sg:phone":"+1 407 688 2657",
    "sg:postcode":"32764",
    "sg:province":"FL",
    "sg:tags":[
        "residential",
        "commercial",
        "contractor"
    ],
    "wof:name":"C & C Site Development Inc",
    "wof:placetype":"venue"
},
  "geometry": {"coordinates":[-81.16236600000001,28.864684],"type":"Point"}
}