{
  "type": "Feature",
  "properties": {
    "iso:country":"US",
    "sg:address":"12395 S Orange Blossom Trl",
    "sg:city":"Orlando",
    "sg:classifiers":[
        {
            "category":"Health Services",
            "subcategory":"Doctor",
            "type":"Services"
        }
    ],
    "sg:phone":"+1 407 438 8840",
    "sg:postcode":"32837",
    "sg:province":"FL",
    "sg:tags":[
        "physician",
        "family",
        "practice",
        "surgeons",
        "medicine",
        "surgeon"
    ],
    "wof:name":"Katherine Welty Md",
    "wof:placetype":"venue"
},
  "geometry": {"coordinates":[-81.404427,28.384794],"type":"Point"}
}