{
  "type": "Feature",
  "properties": {
    "iso:country":"US",
    "sg:address":"11474 Kaleel Rd",
    "sg:city":"Jacksonville",
    "sg:classifiers":[
        {
            "category":"Restaurant",
            "type":"Food & Drink"
        }
    ],
    "sg:phone":"+1 904 757 4844",
    "sg:postcode":"32218",
    "sg:province":"FL",
    "sg:tags":[
        "shop",
        "coffee"
    ],
    "wof:name":"Coffee Station",
    "wof:placetype":"venue"
},
  "geometry": {"coordinates":[-81.599738,30.444972],"type":"Point"}
}