{
  "type": "Feature",
  "properties": {
    "addr:full":"2255 Friday Ct Melbourne FL 32904",
    "addr:housenumber":"2255",
    "addr:postcode":"32904",
    "addr:street":"Friday Ct",
    "iso:country":"US",
    "sg:address":"2255 Friday Ct",
    "sg:city":"Melbourne",
    "sg:classifiers":[
        {
            "category":"Autos & Motor Vehicles",
            "subcategory":"Boat Sales",
            "type":"Retail Goods"
        }
    ],
    "sg:phone":"+1 321 951 2224",
    "sg:postcode":"32904",
    "sg:province":"FL",
    "sg:tags":[
        "equipment",
        "supply"
    ],
    "wof:name":"Cartier Watercraft Carriages",
    "wof:placetype":"venue"
},
  "geometry": {"coordinates":[-80.659104,28.074507],"type":"Point"}
}