{
  "type": "Feature",
  "properties": {
    "iso:country":"US",
    "sg:address":"1310 Dewitt Ln",
    "sg:city":"Sebastian",
    "sg:classifiers":[
        {
            "category":"Professional",
            "subcategory":"Detective & Security Services",
            "type":"Services"
        }
    ],
    "sg:phone":"+1 772 581 9045",
    "sg:postcode":"32958",
    "sg:province":"FL",
    "sg:tags":[
        "information",
        "bureau"
    ],
    "wof:name":"A Professional Notary Service",
    "wof:placetype":"venue"
},
  "geometry": {"coordinates":[-80.48754099999999,27.769125],"type":"Point"}
}