{
  "type": "Feature",
  "properties": {
    "addr:full":"6295 SW 29th St Miami FL 33155",
    "addr:housenumber":"6295",
    "addr:postcode":"33155",
    "addr:street":"Sw 29Th St",
    "iso:country":"US",
    "sg:address":"6295 SW 29th St",
    "sg:city":"Miami",
    "sg:classifiers":[
        {
            "category":"Building & Trades",
            "subcategory":"Construction",
            "type":"Services"
        }
    ],
    "sg:phone":"+1 305 661 4791",
    "sg:postcode":"33155",
    "sg:province":"FL",
    "sg:tags":[
        "contractor"
    ],
    "wof:name":"Arcee Lathing Inc",
    "wof:placetype":"venue"
},
  "geometry": {"coordinates":[-80.29687300000001,25.743473],"type":"Point"}
}