{
  "type": "Feature",
  "properties": {
    "iso:country":"US",
    "sg:address":"2528 Chapel Way",
    "sg:city":"Tampa",
    "sg:classifiers":[
        {
            "category":"Real Estate",
            "subcategory":"Real Estate Agent",
            "type":"Services"
        }
    ],
    "sg:phone":"+1 813 932 8443",
    "sg:postcode":"33618",
    "sg:province":"FL",
    "wof:name":"Westlake and Westlake Realtors",
    "wof:placetype":"venue"
},
  "geometry": {"coordinates":[-82.4872,28.038813],"type":"Point"}
}