{
  "type": "Feature",
  "properties": {
    "iso:country":"US",
    "sg:address":"5585 2nd Ave",
    "sg:city":"Key West",
    "sg:classifiers":[
        {
            "category":"Building & Trades",
            "subcategory":"Electrical",
            "type":"Services"
        }
    ],
    "sg:phone":"+1 305 294 4226",
    "sg:postcode":"33040",
    "sg:province":"FL",
    "sg:tags":[
        "electric",
        "contractor"
    ],
    "wof:name":"A D & T Electric",
    "wof:placetype":"venue"
},
  "geometry": {"coordinates":[-81.740048,24.571191],"type":"Point"}
}