{
  "type": "Feature",
  "properties": {
    "addr:full":"5320 Maravoss St Cocoa FL 32927",
    "addr:housenumber":"5320",
    "addr:postcode":"32927",
    "addr:street":"Maravoss St",
    "iso:country":"US",
    "sg:address":"5320 Maravoss St",
    "sg:city":"Cocoa",
    "sg:classifiers":[
        {
            "category":"Building & Trades",
            "subcategory":"Construction",
            "type":"Services"
        }
    ],
    "sg:phone":"+1 321 632 4203",
    "sg:postcode":"32927",
    "sg:province":"FL",
    "sg:tags":[
        "contractor"
    ],
    "wof:name":"Soffitt T J S & Siding Inc",
    "wof:placetype":"venue"
},
  "geometry": {"coordinates":[-80.811374,28.464963],"type":"Point"}
}