{
  "type": "Feature",
  "properties": {
    "addr:full":"2427 5th Ave N St Petersburg FL 33713",
    "addr:housenumber":"2427",
    "addr:postcode":"33713",
    "addr:street":"5Th Ave N",
    "iso:country":"US",
    "sg:address":"2427 5th Ave N",
    "sg:city":"St Petersburg",
    "sg:classifiers":[
        {
            "category":"Autos & Motor Vehicles",
            "subcategory":"Boat Sales",
            "type":"Retail Goods"
        }
    ],
    "sg:phone":"+1 727 328 8533",
    "sg:postcode":"33713",
    "sg:province":"FL",
    "sg:tags":[
        "top",
        "upholstery",
        "cover"
    ],
    "wof:name":"Brian Williams Custom Canvas",
    "wof:placetype":"venue"
},
  "geometry": {"coordinates":[-82.666892,27.777466],"type":"Point"}
}