{
  "type": "Feature",
  "properties": {
    "addr:full":"3733 University Blvd W Jacksonville FL 32217",
    "addr:housenumber":"3733",
    "addr:postcode":"32217",
    "addr:street":"University Blvd W",
    "iso:country":"US",
    "sg:address":"3733 University Blvd W",
    "sg:city":"Jacksonville",
    "sg:classifiers":[
        {
            "category":"Professional",
            "subcategory":"Management & Consulting",
            "type":"Services"
        }
    ],
    "sg:phone":"+1 904 448 0434",
    "sg:postcode":"32217",
    "sg:province":"FL",
    "sg:tags":[
        "firm",
        "marketing",
        "promotional"
    ],
    "wof:name":"Bmg",
    "wof:placetype":"venue"
},
  "geometry": {"coordinates":[-81.625727,30.261365],"type":"Point"}
}