{
  "type": "Feature",
  "properties": {
    "addr:full":"52 Centerline Rd Crawfordville FL 32327",
    "addr:housenumber":"52",
    "addr:postcode":"32327",
    "addr:street":"Centerline Rd",
    "iso:country":"US",
    "sg:address":"52 Centerline Rd",
    "sg:city":"Crawfordville",
    "sg:classifiers":[
        {
            "category":"Building & Trades",
            "subcategory":"Construction",
            "type":"Services"
        }
    ],
    "sg:phone":"+1 850 567 6356",
    "sg:postcode":"32327",
    "sg:province":"FL",
    "sg:tags":[
        "siding",
        "contractor"
    ],
    "wof:name":"Hines' Home Improvements",
    "wof:placetype":"venue"
},
  "geometry": {"coordinates":[-84.26728,30.28615],"type":"Point"}
}