{
  "type": "Feature",
  "properties": {
    "iso:country":"US",
    "sg:address":"11419 State Road 52",
    "sg:city":"Hudson",
    "sg:classifiers":[
        {
            "category":"Wholesale",
            "subcategory":"Construction Materials",
            "type":"Manufacturing & Wholesale Goods"
        },
        {
            "category":"Building & Trades",
            "subcategory":"Construction",
            "type":"Services"
        },
        {
            "category":"Manufacturing",
            "subcategory":"Building Materials",
            "type":"Manufacturing & Wholesale Goods"
        }
    ],
    "sg:phone":"+1 727 856 3430",
    "sg:postcode":"34669",
    "sg:province":"FL",
    "sg:tags":[
        "industrial",
        "supply",
        "contractor",
        "equipment",
        "paving",
        "masonry",
        "contractors-commercial"
    ],
    "sg:website":"http://www.servicemagic.com/rated.PristinePaverSolutions.14390580.AllCats.html?m=cahscitysrchxm&entry_point_id=479710",
    "wof:name":"Pristine Paver Solutions Inc.",
    "wof:placetype":"venue"
},
  "geometry": {"coordinates":[-82.626324,28.335812],"type":"Point"}
}