{
  "type": "Feature",
  "properties": {
    "iso:country":"US",
    "sg:address":"1545 Prairie Rd",
    "sg:city":"West Palm Beach",
    "sg:classifiers":[
        {
            "category":"Building & Trades",
            "subcategory":"Landscaping Services",
            "type":"Services"
        }
    ],
    "sg:phone":"+1 561 965 2124",
    "sg:postcode":"33406",
    "sg:province":"FL",
    "sg:tags":[
        "landscape"
    ],
    "wof:name":"Martin Burgoon",
    "wof:placetype":"venue"
},
  "geometry": {"coordinates":[-80.08414,26.653789],"type":"Point"}
}