{
  "type": "Feature",
  "properties": {
    "iso:country":"US",
    "sg:address":"1323 W Busch Blvd",
    "sg:city":"Tampa",
    "sg:classifiers":[
        {
            "category":"Health Services",
            "subcategory":"Doctor",
            "type":"Services"
        }
    ],
    "sg:phone":"+1 813 931 9311",
    "sg:postcode":"33612",
    "sg:province":"FL",
    "sg:tags":[
        "physician",
        "surgeon"
    ],
    "wof:name":"Healthcare Therapy Ctr",
    "wof:placetype":"venue"
},
  "geometry": {"coordinates":[-82.47253000000001,28.033489],"type":"Point"}
}