{
  "type": "Feature",
  "properties": {
    "iso:country":"US",
    "sg:address":"1470 NE 123rd St",
    "sg:city":"North Miami",
    "sg:classifiers":[
        {
            "category":"Wholesale",
            "subcategory":"Durable Goods & Equipment",
            "type":"Manufacturing & Wholesale Goods"
        }
    ],
    "sg:phone":"+1 305 891 9795",
    "sg:postcode":"33161",
    "sg:province":"FL",
    "sg:tags":[
        "exporter"
    ],
    "wof:name":"Lazer Manufacturing & Distr",
    "wof:placetype":"venue"
},
  "geometry": {"coordinates":[-80.168531,25.88973],"type":"Point"}
}