{
  "type": "Feature",
  "properties": {
    "addr:full":"11320 Lake Tree Ct Boca Raton FL 33498",
    "addr:housenumber":"11320",
    "addr:postcode":"33498",
    "addr:street":"Lake Tree Ct",
    "iso:country":"US",
    "sg:address":"11320 Lake Tree Ct",
    "sg:city":"Boca Raton",
    "sg:classifiers":[
        {
            "category":"Professional",
            "type":"Services"
        }
    ],
    "sg:phone":"+1 561 487 6779",
    "sg:postcode":"33498",
    "sg:province":"FL",
    "wof:name":"Timothy J Constantine",
    "wof:placetype":"venue"
},
  "geometry": {"coordinates":[-80.225495,26.370235],"type":"Point"}
}