{
  "type": "Feature",
  "properties": {
    "iso:country":"US",
    "sg:address":"601 E Altamonte Dr",
    "sg:city":"Altamonte Springs",
    "sg:classifiers":[
        {
            "category":"Health Services",
            "subcategory":"Hospital",
            "type":"Services"
        }
    ],
    "sg:phone":"+1 407 303 4321",
    "sg:postcode":"32701",
    "sg:province":"FL",
    "wof:name":"Florida Hospital",
    "wof:placetype":"venue"
},
  "geometry": {"coordinates":[-81.37069700000001,28.664101],"type":"Point"}
}