{
  "type": "Feature",
  "properties": {
    "iso:country":"US",
    "sg:address":"4626 NW 35 St",
    "sg:city":"Gainesville",
    "sg:classifiers":[
        {
            "category":"Professional",
            "type":"Services"
        }
    ],
    "sg:phone":"+1 352 337 9583",
    "sg:postcode":"32605",
    "sg:province":"FL",
    "wof:name":"Nb Comerford",
    "wof:placetype":"venue"
},
  "geometry": {"coordinates":[-82.37510899999999,29.697215],"type":"Point"}
}