{
  "type": "Feature",
  "properties": {
    "iso:country":"US",
    "sg:address":"4345 NW 97th Ave",
    "sg:city":"Miami",
    "sg:classifiers":[
        {
            "category":"Freight",
            "type":"Transportation"
        }
    ],
    "sg:phone":"+1 305 477 9996",
    "sg:postcode":"33178",
    "sg:province":"FL",
    "sg:tags":[
        "forwarding"
    ],
    "wof:name":"Caribe Express Inc",
    "wof:placetype":"venue"
},
  "geometry": {"coordinates":[-80.35324199999999,25.814074],"type":"Point"}
}