{
  "type": "Feature",
  "properties": {
    "addr:full":"3474 SE Jake Ct Stuart FL 34994",
    "addr:housenumber":"3474",
    "addr:postcode":"34994",
    "addr:street":"Se Jake Ct",
    "iso:country":"US",
    "sg:address":"3474 SE Jake Ct",
    "sg:city":"Stuart",
    "sg:classifiers":[
        {
            "category":"Professional",
            "type":"Services"
        }
    ],
    "sg:phone":"+1 772 287 5853",
    "sg:postcode":"34994",
    "sg:province":"FL",
    "wof:name":"Octane Plus Inc",
    "wof:placetype":"venue"
},
  "geometry": {"coordinates":[-80.24319,27.162825],"type":"Point"}
}