{
  "type": "Feature",
  "properties": {
    "addr:full":"1408 E Cape Coral Pkwy Cape Coral FL 33904",
    "addr:housenumber":"1408",
    "addr:postcode":"33904",
    "addr:street":"E Cape Coral Pkwy",
    "iso:country":"US",
    "sg:address":"1408 E Cape Coral Pkwy",
    "sg:city":"Cape Coral",
    "sg:classifiers":[
        {
            "category":"Shopping",
            "subcategory":"Beauty & Cosmetics",
            "type":"Retail Goods"
        }
    ],
    "sg:phone":"+1 239 540 0401",
    "sg:postcode":"33904",
    "sg:province":"FL",
    "sg:tags":[
        "merchandise"
    ],
    "wof:name":"Merle Norman Cosmetics",
    "wof:placetype":"venue"
},
  "geometry": {"coordinates":[-81.948593,26.562488],"type":"Point"}
}