{
  "type": "Feature",
  "properties": {
    "addr:full":"18723 Yocam Ave Lutz FL 33549",
    "addr:housenumber":"18723",
    "addr:postcode":"33549",
    "addr:street":"Yocam Ave",
    "iso:country":"US",
    "sg:address":"18723 Yocam Ave",
    "sg:city":"Lutz",
    "sg:classifiers":[
        {
            "category":"Home & Garden",
            "subcategory":"Carpets & Floor Coverings",
            "type":"Retail Goods"
        }
    ],
    "sg:phone":"+1 813 948 2224",
    "sg:postcode":"33549",
    "sg:province":"FL",
    "wof:name":"Troughton Ces Carpet Service",
    "wof:placetype":"venue"
},
  "geometry": {"coordinates":[-82.450941,28.145141],"type":"Point"}
}