{
  "type": "Feature",
  "properties": {
    "iso:country":"US",
    "sg:address":"971 SE Central Pkwy",
    "sg:city":"Stuart",
    "sg:classifiers":[
        {
            "category":"Health Services",
            "subcategory":"Health Practitioner",
            "type":"Services"
        }
    ],
    "sg:phone":"+1 772 215 3627",
    "sg:postcode":"34994",
    "sg:province":"FL",
    "sg:tags":[
        "therapist",
        "physical"
    ],
    "wof:name":"New Harbor Physical Therapy",
    "wof:placetype":"venue"
},
  "geometry": {"coordinates":[-80.240864,27.179798],"type":"Point"}
}