{
  "type": "Feature",
  "properties": {
    "addr:full":"14621 Balgowan Rd Hialeah FL 33016",
    "addr:housenumber":"14621",
    "addr:postcode":"33016",
    "addr:street":"Balgowan Rd",
    "iso:country":"US",
    "sg:address":"14621 Balgowan Rd",
    "sg:city":"Hialeah",
    "sg:classifiers":[
        {
            "category":"Banks & Credit Unions",
            "subcategory":"Investment Brokerage",
            "type":"Services"
        }
    ],
    "sg:phone":"+1 305 558 7744",
    "sg:postcode":"33016",
    "sg:province":"FL",
    "sg:tags":[
        "security"
    ],
    "wof:name":"SunAmerica",
    "wof:placetype":"venue"
},
  "geometry": {"coordinates":[-80.33629500000001,25.905256],"type":"Point"}
}