{
  "type": "Feature",
  "properties": {
    "iso:country":"US",
    "sg:address":"2108 NE 1st Ave",
    "sg:city":"Fort Lauderdale",
    "sg:classifiers":[
        {
            "category":"Real Estate",
            "subcategory":"Real Estate Operator",
            "type":"Services"
        }
    ],
    "sg:phone":"+1 954 561 3675",
    "sg:postcode":"33305",
    "sg:province":"FL",
    "sg:tags":[
        "property",
        "lessor"
    ],
    "wof:name":"Strouse Inc",
    "wof:placetype":"venue"
},
  "geometry": {"coordinates":[-80.14402,26.154686],"type":"Point"}
}