{
  "type": "Feature",
  "properties": {
    "addr:full":"1521 Oakfield Dr Brandon FL 33511",
    "addr:housenumber":"1521",
    "addr:postcode":"33511",
    "addr:street":"Oakfield Dr",
    "iso:country":"US",
    "sg:address":"1521 Oakfield Dr",
    "sg:city":"Brandon",
    "sg:classifiers":[
        {
            "category":"Banks & Credit Unions",
            "subcategory":"Investment Brokerage",
            "type":"Services"
        }
    ],
    "sg:phone":"+1 813 655 1493",
    "sg:postcode":"33511",
    "sg:province":"FL",
    "sg:tags":[
        "advisory",
        "financial"
    ],
    "wof:name":"Olde Towne Financial",
    "wof:placetype":"venue"
},
  "geometry": {"coordinates":[-82.30873099999999,27.934193],"type":"Point"}
}