{
  "type": "Feature",
  "properties": {
    "addr:full":"6539 SE 110th Ln Belleview FL 34420",
    "addr:housenumber":"6539",
    "addr:postcode":"34420",
    "addr:street":"Se 110Th Ln",
    "iso:country":"US",
    "sg:address":"6539 SE 110th Ln",
    "sg:city":"Belleview",
    "sg:classifiers":[
        {
            "category":"Shopping",
            "subcategory":"Department Store",
            "type":"Retail Goods"
        }
    ],
    "sg:phone":"+1 352 347 9988",
    "sg:postcode":"34420",
    "sg:province":"FL",
    "sg:tags":[
        "shop"
    ],
    "wof:name":"Belleview Discount Divorce",
    "wof:placetype":"venue"
},
  "geometry": {"coordinates":[-82.04175600000001,29.061381],"type":"Point"}
}