{
  "type": "Feature",
  "properties": {
    "iso:country":"US",
    "sg:address":"12201 NW 35th St",
    "sg:city":"Pompano Beach",
    "sg:classifiers":[
        {
            "category":"Shopping",
            "subcategory":"Clothing, Apparel, & Fashions",
            "type":"Retail Goods"
        }
    ],
    "sg:phone":"+1 954 752 7993",
    "sg:postcode":"33065",
    "sg:province":"FL",
    "sg:tags":[
        "business",
        "accessory"
    ],
    "wof:name":"Displays By Mr C & Co Inc",
    "wof:placetype":"venue"
},
  "geometry": {"coordinates":[-80.291044,26.274451],"type":"Point"}
}