{
  "type": "Feature",
  "properties": {
    "addr:full":"1003 Penman Rd Neptune Beach FL 32266",
    "addr:housenumber":"1003",
    "addr:postcode":"32266",
    "addr:street":"Penman Rd",
    "iso:country":"US",
    "sg:address":"1003 Penman Rd",
    "sg:city":"Neptune Beach",
    "sg:classifiers":[
        {
            "category":"Professional",
            "subcategory":"Computer Services",
            "type":"Services"
        }
    ],
    "sg:phone":"+1 904 241 6464",
    "sg:postcode":"32266",
    "sg:province":"FL",
    "sg:tags":[
        "website",
        "design"
    ],
    "wof:name":"GTS Computer Svc",
    "wof:placetype":"venue"
},
  "geometry": {"coordinates":[-81.407951,30.317307],"type":"Point"}
}