{
  "type": "Feature",
  "properties": {
    "addr:full":"4225 45th St West Palm Beach FL 33407",
    "addr:housenumber":"4225",
    "addr:postcode":"33407",
    "addr:street":"45Th St",
    "iso:country":"US",
    "sg:address":"4225 45th St",
    "sg:city":"West Palm Beach",
    "sg:classifiers":[
        {
            "category":"Organizations",
            "subcategory":"Non-profit Organization",
            "type":"Services"
        }
    ],
    "sg:phone":"+1 561 688 3064",
    "sg:postcode":"33407",
    "sg:province":"FL",
    "sg:tags":[
        "social"
    ],
    "wof:name":"Stanley Nichols",
    "wof:placetype":"venue"
},
  "geometry": {"coordinates":[-80.10527500000001,26.759681],"type":"Point"}
}