{
  "type": "Feature",
  "properties": {
    "iso:country":"US",
    "sg:address":"715 E Hallandale Beach Blvd",
    "sg:city":"Hallandale",
    "sg:classifiers":[
        {
            "category":"Professional",
            "subcategory":"Business Services",
            "type":"Services"
        }
    ],
    "sg:phone":"+1 954 458 2260",
    "sg:postcode":"33009",
    "sg:province":"FL",
    "sg:tags":[
        "record",
        "label"
    ],
    "wof:name":"Empire Music Works",
    "wof:placetype":"venue"
},
  "geometry": {"coordinates":[-80.138577,25.985888],"type":"Point"}
}