{
  "type": "Feature",
  "properties": {
    "iso:country":"US",
    "sg:address":"242 Pleasant St",
    "sg:city":"Lake Helen",
    "sg:classifiers":[
        {
            "category":"Professional",
            "subcategory":"Computer Services",
            "type":"Services"
        }
    ],
    "sg:phone":"+1 386 228 2411",
    "sg:postcode":"32744",
    "sg:province":"FL",
    "sg:tags":[
        "repair"
    ],
    "wof:name":"Bonne Terre Imc",
    "wof:placetype":"venue"
},
  "geometry": {"coordinates":[-81.22976800000001,28.982125],"type":"Point"}
}