{
  "type": "Feature",
  "properties": {
    "addr:full":"530 Seaboard Ave Venice FL 34285",
    "addr:housenumber":"530",
    "addr:postcode":"34285",
    "addr:street":"Seaboard Ave",
    "iso:country":"US",
    "sg:address":"530 Seaboard Ave",
    "sg:city":"Venice",
    "sg:classifiers":[
        {
            "category":"Autos & Motor Vehicles",
            "subcategory":"Auto Supplies",
            "type":"Retail Goods"
        }
    ],
    "sg:phone":"+1 941 485 3329",
    "sg:postcode":"34285",
    "sg:province":"FL",
    "sg:tags":[
        "tire"
    ],
    "wof:name":"Lanning Tire Sales Inc",
    "wof:placetype":"venue"
},
  "geometry": {"coordinates":[-82.43467099999999,27.092924],"type":"Point"}
}