{
  "type": "Feature",
  "properties": {
    "iso:country":"US",
    "sg:address":"502 Pleasant Grove Dr",
    "sg:city":"Winter Springs",
    "sg:classifiers":[
        {
            "category":"Insurance",
            "subcategory":"Insurance Agent",
            "type":"Services"
        }
    ],
    "sg:phone":"+1 407 977 7519",
    "sg:postcode":"32708",
    "sg:province":"FL",
    "wof:name":"CNA Insurance",
    "wof:placetype":"venue"
},
  "geometry": {"coordinates":[-81.260451,28.677372],"type":"Point"}
}