{
  "type": "Feature",
  "properties": {
    "addr:full":"7504 Wiles Rd Pompano Beach FL 33067",
    "addr:housenumber":"7504",
    "addr:postcode":"33067",
    "addr:street":"Wiles Rd",
    "iso:country":"US",
    "sg:address":"7504 Wiles Rd",
    "sg:city":"Pompano Beach",
    "sg:classifiers":[
        {
            "category":"Building & Trades",
            "subcategory":"Construction",
            "type":"Services"
        }
    ],
    "sg:phone":"+1 954 755 0690",
    "sg:postcode":"33067",
    "sg:province":"FL",
    "sg:tags":[
        "house"
    ],
    "wof:name":"Homes By Architechnic",
    "wof:placetype":"venue"
},
  "geometry": {"coordinates":[-80.227366,26.286627],"type":"Point"}
}