{
  "type": "Feature",
  "properties": {
    "iso:country":"US",
    "sg:address":"4430 Tiffany Dr S",
    "sg:city":"West Palm Beach",
    "sg:classifiers":[
        {
            "category":"Building & Trades",
            "subcategory":"Construction",
            "type":"Services"
        }
    ],
    "sg:phone":"+1 561 881 2055",
    "sg:postcode":"33407",
    "sg:province":"FL",
    "sg:tags":[
        "stucco",
        "contractor"
    ],
    "wof:name":"Palm Beach Stucco Inc",
    "wof:placetype":"venue"
},
  "geometry": {"coordinates":[-80.08205,26.753832],"type":"Point"}
}