{
  "type": "Feature",
  "properties": {
    "addr:full":"26302 State Rd 54 Lutz FL 33559",
    "addr:housenumber":"26302;54",
    "addr:postcode":"33559",
    "addr:street":"State Rd",
    "iso:country":"US",
    "sg:address":"26302 State Rd 54",
    "sg:city":"Lutz",
    "sg:classifiers":[
        {
            "category":"Shopping",
            "subcategory":"Hobbies, Toys, & Games",
            "type":"Retail Goods"
        }
    ],
    "sg:phone":"+1 813 929 3600",
    "sg:postcode":"33559",
    "sg:province":"FL",
    "sg:tags":[
        "craft",
        "supply"
    ],
    "wof:name":"Horizon Breeze Inc",
    "wof:placetype":"venue"
},
  "geometry": {"coordinates":[-82.38717,28.218404],"type":"Point"}
}