{
  "type": "Feature",
  "properties": {
    "addr:full":"3240 SE Maricamp Rd Ocala FL 34471",
    "addr:housenumber":"3240",
    "addr:postcode":"34471",
    "addr:street":"Se Maricamp Rd",
    "iso:country":"US",
    "sg:address":"3240 SE Maricamp Rd",
    "sg:city":"Ocala",
    "sg:classifiers":[
        {
            "category":"Retail",
            "subcategory":"Auto Repair",
            "type":"Services"
        }
    ],
    "sg:phone":"+1 352 694 0118",
    "sg:postcode":"34471",
    "sg:province":"FL",
    "sg:tags":[
        "automotive"
    ],
    "wof:name":"McBcc Fleet Management",
    "wof:placetype":"venue"
},
  "geometry": {"coordinates":[-82.094842,29.163569],"type":"Point"}
}