{
  "type": "Feature",
  "properties": {
    "iso:country":"US",
    "sg:address":"13035 SW 112th St",
    "sg:city":"Miami",
    "sg:phone":"+1 305 386 5506",
    "sg:postcode":"33186",
    "sg:province":"FL",
    "wof:name":"Angeli's Pizza",
    "wof:placetype":"venue"
},
  "geometry": {"coordinates":[-80.40629199999999,25.663187],"type":"Point"}
}