{
  "type": "Feature",
  "properties": {
    "iso:country":"US",
    "sg:address":"19301 NW 90th Ct",
    "sg:city":"Hialeah",
    "sg:classifiers":[
        {
            "category":"Health Services",
            "subcategory":"Clinic",
            "type":"Services"
        },
        {
            "category":"Health Services",
            "subcategory":"Medical Lab",
            "type":"Services"
        }
    ],
    "sg:phone":"+1 305 829 3127",
    "sg:postcode":"33018",
    "sg:province":"FL",
    "sg:tags":[
        "laboratory"
    ],
    "wof:name":"M & M Medical Diagnostics Inc",
    "wof:placetype":"venue"
},
  "geometry": {"coordinates":[-80.34862099999999,25.94858],"type":"Point"}
}