{
  "type": "Feature",
  "properties": {
    "iso:country":"US",
    "sg:address":"1620 NE 8th Rd",
    "sg:city":"Ocala",
    "sg:classifiers":[
        {
            "category":"Wholesale",
            "subcategory":"Hardware",
            "type":"Manufacturing & Wholesale Goods"
        },
        {
            "category":"Home & Garden",
            "subcategory":"Building Materials",
            "type":"Retail Goods"
        }
    ],
    "sg:phone":"+1 352 629 8191",
    "sg:postcode":"34470",
    "sg:province":"FL",
    "sg:tags":[
        "plumbing",
        "equipment",
        "fixture",
        "supply"
    ],
    "sg:website":"www.morganbros.com",
    "wof:name":"Morgan Brothers Supply Inc",
    "wof:placetype":"venue"
},
  "geometry": {"coordinates":[-82.129256,29.204073],"type":"Point"}
}