{
  "type": "Feature",
  "properties": {
    "iso:country":"US",
    "sg:address":"321 Washington Ave",
    "sg:city":"Cape Canaveral",
    "sg:classifiers":[
        {
            "category":"Building & Trades",
            "subcategory":"Landscaping Services",
            "type":"Services"
        }
    ],
    "sg:phone":"+1 321 783 4914",
    "sg:postcode":"32920",
    "sg:province":"FL",
    "wof:name":"AAA Tree Service of Brevard",
    "wof:placetype":"venue"
},
  "geometry": {"coordinates":[-80.601676,28.391199],"type":"Point"}
}