{
  "type": "Feature",
  "properties": {
    "iso:country":"US",
    "sg:address":"229 Palm Ave",
    "sg:city":"Eustis",
    "sg:classifiers":[
        {
            "category":"Restaurant",
            "type":"Food & Drink"
        }
    ],
    "sg:phone":"+1 352 357 7690",
    "sg:postcode":"32726",
    "sg:province":"FL",
    "sg:tags":[
        "pizza"
    ],
    "wof:name":"Pizza Place Of Sorrento",
    "wof:placetype":"venue"
},
  "geometry": {"coordinates":[-81.683217,28.843322],"type":"Point"}
}