{
  "type": "Feature",
  "properties": {
    "addr:full":"6971 N Deltona Blvd Citrus Springs FL 34434",
    "addr:housenumber":"6971",
    "addr:postcode":"34434",
    "addr:street":"N Deltona Blvd",
    "iso:country":"US",
    "sg:address":"6971 N Deltona Blvd",
    "sg:city":"Citrus Springs",
    "sg:classifiers":[
        {
            "category":"Professional",
            "subcategory":"Management & Consulting",
            "type":"Services"
        }
    ],
    "sg:phone":"+1 352 533 2307",
    "sg:postcode":"34434",
    "sg:province":"FL",
    "sg:tags":[
        "get-more-customers",
        "get-online",
        "start-a-business",
        "increase-profits"
    ],
    "sg:website":"http://www.1stpagelocal.com",
    "wof:name":"1stpagelocal",
    "wof:placetype":"venue"
},
  "geometry": {"coordinates":[-82.440924,28.965363],"type":"Point"}
}