{
  "type": "Feature",
  "properties": {
    "iso:country":"US",
    "sg:address":"3679 Barbary Dr",
    "sg:city":"Tallahassee",
    "sg:classifiers":[
        {
            "category":"Organizations",
            "subcategory":"Membership Organization",
            "type":"Services"
        }
    ],
    "sg:phone":"+1 850 668 0565",
    "sg:postcode":"32309",
    "sg:province":"FL",
    "wof:name":"Tallahassee Volkssport Club",
    "wof:placetype":"venue"
},
  "geometry": {"coordinates":[-84.23139999999999,30.518023],"type":"Point"}
}