{
  "type": "Feature",
  "properties": {
    "iso:country":"US",
    "sg:address":"5741 Briargate Ln",
    "sg:city":"Fort Pierce",
    "sg:classifiers":[
        {
            "category":"Wholesale",
            "subcategory":"Fruits & Vegetables",
            "type":"Manufacturing & Wholesale Goods"
        }
    ],
    "sg:phone":"+1 772 464 9991",
    "sg:postcode":"34981",
    "sg:province":"FL",
    "wof:name":"Augustine M Gonzalez",
    "wof:placetype":"venue"
},
  "geometry": {"coordinates":[-80.384782,27.407825],"type":"Point"}
}