{
  "type": "Feature",
  "properties": {
    "addr:full":"6045 Sherwin Dr Port Richey FL 34668",
    "addr:housenumber":"6045",
    "addr:postcode":"34668",
    "addr:street":"Sherwin Dr",
    "iso:country":"US",
    "sg:address":"6045 Sherwin Dr",
    "sg:city":"Port Richey",
    "sg:classifiers":[
        {
            "category":"Manufacturing",
            "subcategory":"Toys & Sporting Goods",
            "type":"Manufacturing & Wholesale Goods"
        }
    ],
    "sg:phone":"+1 727 845 3737",
    "sg:postcode":"34668",
    "sg:province":"FL",
    "sg:tags":[
        "lur",
        "fishing",
        "artificial",
        "mfg"
    ],
    "sg:website":"www.cotee.com",
    "wof:name":"Cotee Industries",
    "wof:placetype":"venue"
},
  "geometry": {"coordinates":[-82.713688,28.276518],"type":"Point"}
}