{
  "type": "Feature",
  "properties": {
    "addr:full":"701 E 47th St Hialeah FL 33013",
    "addr:housenumber":"701",
    "addr:postcode":"33013",
    "addr:street":"E 47Th St",
    "iso:country":"US",
    "sg:address":"701 E 47th St",
    "sg:city":"Hialeah",
    "sg:classifiers":[
        {
            "category":"Autos & Motor Vehicles",
            "subcategory":"Auto Supplies",
            "type":"Retail Goods"
        }
    ],
    "sg:phone":"+1 305 687 3980",
    "sg:postcode":"33013",
    "sg:province":"FL",
    "wof:name":"Eusebio Tires",
    "wof:placetype":"venue"
},
  "geometry": {"coordinates":[-80.26674800000001,25.865488],"type":"Point"}
}