{
  "type": "Feature",
  "properties": {
    "iso:country":"US",
    "sg:address":"10875 SW 216th St Unit 310",
    "sg:city":"Miami",
    "sg:classifiers":[
        {
            "category":"Home & Garden",
            "subcategory":"Building Materials",
            "type":"Retail Goods"
        },
        {
            "category":"Building & Trades",
            "subcategory":"Construction",
            "type":"Services"
        }
    ],
    "sg:phone":"+1 786 255 2647",
    "sg:postcode":"33170",
    "sg:province":"FL",
    "sg:tags":[
        "concrete-stamped",
        "decorative",
        "industrial",
        "excavation",
        "contractor",
        "concrete",
        "contractors-commercial",
        "staining",
        "masonry"
    ],
    "wof:name":"InShape Maintenance, Inc.",
    "wof:placetype":"venue"
},
  "geometry": {"coordinates":[-80.367926,25.566545],"type":"Point"}
}