{
  "type": "Feature",
  "properties": {
    "addr:full":"917 Louden Ave Dunedin FL 34698",
    "addr:housenumber":"917",
    "addr:postcode":"34698",
    "addr:street":"Louden Ave",
    "iso:country":"US",
    "sg:address":"917 Louden Ave",
    "sg:city":"Dunedin",
    "sg:classifiers":[
        {
            "category":"Organizations",
            "subcategory":"Community Association",
            "type":"Services"
        }
    ],
    "sg:phone":"+1 727 736 4121",
    "sg:postcode":"34698",
    "sg:province":"FL",
    "sg:tags":[
        "club"
    ],
    "wof:name":"Scottish American Society Inc",
    "wof:placetype":"venue"
},
  "geometry": {"coordinates":[-82.784699,28.014176],"type":"Point"}
}