{
  "type": "Feature",
  "properties": {
    "iso:country":"US",
    "sg:address":"3633 NW 59th St",
    "sg:city":"Pompano Beach",
    "sg:classifiers":[
        {
            "category":"Building & Trades",
            "subcategory":"Electrical",
            "type":"Services"
        }
    ],
    "sg:phone":"+1 954 425 8005",
    "sg:postcode":"33073",
    "sg:province":"FL",
    "sg:tags":[
        "electrical",
        "contractor"
    ],
    "wof:name":"D & M Electric Inc",
    "wof:placetype":"venue"
},
  "geometry": {"coordinates":[-80.173036,26.303282],"type":"Point"}
}