{
  "type": "Feature",
  "properties": {
    "addr:full":"612 NW 135th Ter Fort Lauderdale FL 33325",
    "addr:housenumber":"612",
    "addr:postcode":"33325",
    "addr:street":"Nw 135Th Ter",
    "iso:country":"US",
    "sg:address":"612 NW 135th Ter",
    "sg:city":"Fort Lauderdale",
    "sg:classifiers":[
        {
            "category":"Building & Trades",
            "subcategory":"Cleaning & Sanitation",
            "type":"Services"
        }
    ],
    "sg:phone":"+1 954 835 2201",
    "sg:postcode":"33325",
    "sg:province":"FL",
    "sg:tags":[
        "maintenance"
    ],
    "wof:name":"Amazon Facilities Maintenance",
    "wof:placetype":"venue"
},
  "geometry": {"coordinates":[-80.329301,26.12834],"type":"Point"}
}