{
  "type": "Feature",
  "properties": {
    "iso:country":"US",
    "sg:address":"3604 Dagon St",
    "sg:city":"Orlando",
    "sg:classifiers":[
        {
            "category":"Personal",
            "type":"Services"
        },
        {
            "category":"Professional",
            "subcategory":"Art Services",
            "type":"Services"
        }
    ],
    "sg:phone":"+1 407 812 9397",
    "sg:postcode":"32806",
    "sg:province":"FL",
    "sg:tags":[
        "photography",
        "videography",
        "wedding"
    ],
    "wof:name":"Michael Wise Photographers",
    "wof:placetype":"venue"
},
  "geometry": {"coordinates":[-81.341561,28.499916],"type":"Point"}
}