{
  "type": "Feature",
  "properties": {
    "addr:full":"2301 49th St S Saint Petersburg FL 33707",
    "addr:housenumber":"2301",
    "addr:postcode":"33707",
    "addr:street":"49Th St S",
    "iso:country":"US",
    "sg:address":"2301 49th St S",
    "sg:city":"Saint Petersburg",
    "sg:classifiers":[
        {
            "category":"Building & Trades",
            "subcategory":"Construction",
            "type":"Services"
        }
    ],
    "sg:phone":"+1 727 323 1331",
    "sg:postcode":"33707",
    "sg:province":"FL",
    "sg:tags":[
        "hanging",
        "contractor"
    ],
    "wof:name":"Steve Skinner Painting Inc",
    "wof:placetype":"venue"
},
  "geometry": {"coordinates":[-82.699657,27.746833],"type":"Point"}
}