{
  "type": "Feature",
  "properties": {
    "addr:full":"9150 Gall Blvd Zephyrhills FL 33541",
    "addr:housenumber":"9150",
    "addr:postcode":"33541",
    "addr:street":"Gall Blvd",
    "iso:country":"US",
    "sg:address":"9150 Gall Blvd",
    "sg:city":"Zephyrhills",
    "sg:classifiers":[
        {
            "category":"Building & Trades",
            "subcategory":"Construction",
            "type":"Services"
        }
    ],
    "sg:phone":"+1 813 780 7763",
    "sg:postcode":"33541",
    "sg:province":"FL",
    "sg:tags":[
        "contractor"
    ],
    "wof:name":"Mikes Welding",
    "wof:placetype":"venue"
},
  "geometry": {"coordinates":[-82.187763,28.288855],"type":"Point"}
}