{
  "type": "Feature",
  "properties": {
    "addr:full":"10575 68th Ave Seminole FL 33772",
    "addr:housenumber":"10575",
    "addr:postcode":"33772",
    "addr:street":"68Th Ave",
    "iso:country":"US",
    "sg:address":"10575 68th Ave",
    "sg:city":"Seminole",
    "sg:classifiers":[
        {
            "category":"Real Estate",
            "subcategory":"Real Estate Agent",
            "type":"Services"
        }
    ],
    "sg:phone":"+1 727 393 4370",
    "sg:postcode":"33772",
    "sg:province":"FL",
    "sg:tags":[
        "management"
    ],
    "wof:name":"Comprehensive Management Inc",
    "wof:placetype":"venue"
},
  "geometry": {"coordinates":[-82.785529,27.834006],"type":"Point"}
}