{
  "type": "Feature",
  "properties": {
    "iso:country":"US",
    "sg:address":"320 NW 148th St",
    "sg:city":"Miami",
    "sg:classifiers":[
        {
            "category":"Professional",
            "subcategory":"Business Services",
            "type":"Services"
        }
    ],
    "sg:phone":"+1 305 688 9784",
    "sg:postcode":"33168",
    "sg:province":"FL",
    "sg:tags":[
        "broker",
        "merchandise"
    ],
    "wof:name":"Michael Thompson Broker",
    "wof:placetype":"venue"
},
  "geometry": {"coordinates":[-80.20743400000001,25.910313],"type":"Point"}
}