{
  "type": "Feature",
  "properties": {
    "iso:country":"US",
    "sg:address":"3703 Mykonos Ct",
    "sg:city":"Boca Raton",
    "sg:classifiers":[
        {
            "category":"Real Estate",
            "subcategory":"Real Estate Operator",
            "type":"Services"
        }
    ],
    "sg:phone":"+1 561 994 8344",
    "sg:postcode":"33487",
    "sg:province":"FL",
    "sg:tags":[
        "building",
        "nonresidential"
    ],
    "wof:name":"Lsl Properties Inc",
    "wof:placetype":"venue"
},
  "geometry": {"coordinates":[-80.101406,26.423935],"type":"Point"}
}