{
  "type": "Feature",
  "properties": {
    "iso:country":"US",
    "sg:address":"1333 Golf Pt Lp",
    "sg:city":"Apopka",
    "sg:classifiers":[
        {
            "category":"Utilities",
            "subcategory":"Telephone",
            "type":"Services"
        }
    ],
    "sg:phone":"+1 407 464 0147",
    "sg:postcode":"32712",
    "sg:province":"FL",
    "sg:tags":[
        "web",
        "hosting",
        "internet"
    ],
    "wof:name":"Xrackhosting LLC",
    "wof:placetype":"venue"
},
  "geometry": {"coordinates":[-81.53286300000001,28.708804],"type":"Point"}
}