{
  "type": "Feature",
  "properties": {
    "iso:country":"US",
    "sg:address":"1329 W Cass St",
    "sg:city":"Tampa",
    "sg:classifiers":[
        {
            "category":"Banks & Credit Unions",
            "subcategory":"Bank",
            "type":"Services"
        }
    ],
    "sg:phone":"+1 813 258 8082",
    "sg:postcode":"33606",
    "sg:province":"FL",
    "sg:tags":[
        "mortgage"
    ],
    "wof:name":"Mortgage Approval Services",
    "wof:placetype":"venue"
},
  "geometry": {"coordinates":[-82.474158,27.949868],"type":"Point"}
}