{
  "type": "Feature",
  "properties": {
    "iso:country":"US",
    "sg:address":"701 Little Wekiva Rd",
    "sg:city":"Altamonte Springs",
    "sg:classifiers":[
        {
            "category":"Wholesale",
            "subcategory":"Vending Machines",
            "type":"Manufacturing & Wholesale Goods"
        }
    ],
    "sg:phone":"+1 407 782 4968",
    "sg:postcode":"32714",
    "sg:province":"FL",
    "sg:tags":[
        "operator"
    ],
    "wof:name":"On Time Vending Inc",
    "wof:placetype":"venue"
},
  "geometry": {"coordinates":[-81.412307,28.670064],"type":"Point"}
}