{
  "type": "Feature",
  "properties": {
    "iso:country":"US",
    "sg:address":"1722 Del Prado Blvd S Ste 11",
    "sg:city":"Cape Coral",
    "sg:classifiers":[
        {
            "category":"Sports & Exercise",
            "subcategory":"Gym",
            "type":"Entertainment"
        }
    ],
    "sg:phone":"+1 239 772 7111",
    "sg:postcode":"33990",
    "sg:province":"FL",
    "sg:website":"www.healthandstrengthgym.com",
    "wof:name":"Health & Strength Gym",
    "wof:placetype":"venue"
},
  "geometry": {"coordinates":[-81.94090300000001,26.620501],"type":"Point"}
}