{
  "type": "Feature",
  "properties": {
    "iso:country":"US",
    "sg:address":"20 Newport Dr",
    "sg:city":"Crestview",
    "sg:classifiers":[
        {
            "category":"Real Estate",
            "subcategory":"Surveying",
            "type":"Services"
        }
    ],
    "sg:phone":"+1 850 689 1594",
    "sg:postcode":"32539",
    "sg:province":"FL",
    "sg:tags":[
        "surveyor"
    ],
    "wof:name":"Bergschneider Land Surveying",
    "wof:placetype":"venue"
},
  "geometry": {"coordinates":[-86.55052499999999,30.758736],"type":"Point"}
}