{
  "type": "Feature",
  "properties": {
    "addr:full":"7560 15th St E Sarasota FL 34243",
    "addr:housenumber":"7560",
    "addr:postcode":"34243",
    "addr:street":"15Th St E",
    "iso:country":"US",
    "sg:address":"7560 15th St E",
    "sg:city":"Sarasota",
    "sg:classifiers":[
        {
            "category":"Bars & Pubs",
            "type":"Food & Drink"
        }
    ],
    "sg:phone":"+1 941 355 5783",
    "sg:postcode":"34243",
    "sg:province":"FL",
    "wof:name":"Johnny's",
    "wof:placetype":"venue"
},
  "geometry": {"coordinates":[-82.54685499999999,27.40571],"type":"Point"}
}