{
  "type": "Feature",
  "properties": {
    "addr:full":"723 Bently St E Lehigh Acres FL 33974",
    "addr:housenumber":"723",
    "addr:postcode":"33974",
    "addr:street":"Bently St E",
    "iso:country":"US",
    "sg:address":"723 Bently St E",
    "sg:city":"Lehigh Acres",
    "sg:classifiers":[
        {
            "category":"Real Estate",
            "subcategory":"Real Estate Operator",
            "type":"Services"
        }
    ],
    "sg:phone":"+1 239 872 8452",
    "sg:postcode":"33974",
    "sg:province":"FL",
    "sg:tags":[
        "building",
        "nonresidential"
    ],
    "wof:name":"Bhagwndin Vshwnand Prperty MGT",
    "wof:placetype":"venue"
},
  "geometry": {"coordinates":[-81.611119,26.555423],"type":"Point"}
}