{
  "type": "Feature",
  "properties": {
    "iso:country":"US",
    "sg:address":"9778 Airport Blvd",
    "sg:city":"Orlando",
    "sg:phone":"+1 407 438 5398",
    "sg:postcode":"32827",
    "sg:province":"FL",
    "sg:tags":[
        "transmission",
        "facsimile"
    ],
    "wof:name":"Action Fax",
    "wof:placetype":"venue"
},
  "geometry": {"coordinates":[-81.30688499999999,28.426959],"type":"Point"}
}