{
  "type": "Feature",
  "properties": {
    "iso:country":"US",
    "sg:address":"4040 N Dixie Hwy",
    "sg:city":"Boca Raton",
    "sg:classifiers":[
        {
            "category":"Autos & Motor Vehicles",
            "subcategory":"Auto Supplies",
            "type":"Retail Goods"
        },
        {
            "category":"Wholesale",
            "subcategory":"Auto Parts",
            "type":"Manufacturing & Wholesale Goods"
        }
    ],
    "sg:phone":"+1 561 368 2880",
    "sg:postcode":"33431",
    "sg:province":"FL",
    "sg:tags":[
        "automobile"
    ],
    "wof:name":"Bennett Auto Supply Inc",
    "wof:placetype":"venue"
},
  "geometry": {"coordinates":[-80.0814,26.387262],"type":"Point"}
}