{
  "type": "Feature",
  "properties": {
    "addr:full":"3945 Bayshore Dr Naples FL 34112",
    "addr:housenumber":"3945",
    "addr:postcode":"34112",
    "addr:street":"Bayshore Dr",
    "iso:country":"US",
    "sg:address":"3945 Bayshore Dr",
    "sg:city":"Naples",
    "sg:classifiers":[
        {
            "category":"Autos & Motor Vehicles",
            "subcategory":"Motorcycle Sales",
            "type":"Retail Goods"
        }
    ],
    "sg:phone":"+1 239 793 7368",
    "sg:postcode":"34112",
    "sg:province":"FL",
    "sg:tags":[
        "car",
        "golf",
        "cart"
    ],
    "wof:name":"Electric Motion Leasing Inc",
    "wof:placetype":"venue"
},
  "geometry": {"coordinates":[-81.770515,26.118396],"type":"Point"}
}