{
  "type": "Feature",
  "properties": {
    "iso:country":"US",
    "sg:address":"10641 Airport Pulling Rd N",
    "sg:city":"Naples",
    "sg:classifiers":[
        {
            "category":"Professional",
            "subcategory":"Engineering",
            "type":"Services"
        }
    ],
    "sg:phone":"+1 239 596 9191",
    "sg:postcode":"34109",
    "sg:province":"FL",
    "sg:tags":[
        "engineer"
    ],
    "wof:name":"Waldrop Engineering",
    "wof:placetype":"venue"
},
  "geometry": {"coordinates":[-81.769924,26.269207],"type":"Point"}
}