{
  "type": "Feature",
  "properties": {
    "iso:country":"US",
    "sg:address":"7200 S Florida Ave",
    "sg:city":"Floral City",
    "sg:classifiers":[
        {
            "category":"Building & Trades",
            "subcategory":"Plumbing",
            "type":"Services"
        }
    ],
    "sg:phone":"+1 352 637 5117",
    "sg:postcode":"34436",
    "sg:province":"FL",
    "sg:tags":[
        "contractor"
    ],
    "wof:name":"Fergeson & Hoolihan Plumbing",
    "wof:placetype":"venue"
},
  "geometry": {"coordinates":[-82.294246,28.758729],"type":"Point"}
}