{
  "type": "Feature",
  "properties": {
    "iso:country":"US",
    "sg:address":"6390 W Indiantown Rd",
    "sg:city":"Jupiter",
    "sg:classifiers":[
        {
            "category":"Home & Garden",
            "subcategory":"Building Materials",
            "type":"Retail Goods"
        }
    ],
    "sg:phone":"+1 561 745 1115",
    "sg:postcode":"33458",
    "sg:province":"FL",
    "wof:name":"Regal Paint Centers",
    "wof:placetype":"venue"
},
  "geometry": {"coordinates":[-80.132994,26.934456],"type":"Point"}
}