{
  "type": "Feature",
  "properties": {
    "addr:full":"2915 NW 7th St Miami FL 33125",
    "addr:housenumber":"2915",
    "addr:postcode":"33125",
    "addr:street":"Nw 7Th St",
    "iso:country":"US",
    "sg:address":"2915 NW 7th St",
    "sg:city":"Miami",
    "sg:classifiers":[
        {
            "category":"Health Services",
            "subcategory":"Dentist",
            "type":"Services"
        }
    ],
    "sg:phone":"+1 305 642 6330",
    "sg:postcode":"33125",
    "sg:province":"FL",
    "wof:name":"Sonia Olivares Dds",
    "wof:placetype":"venue"
},
  "geometry": {"coordinates":[-80.242502,25.779383],"type":"Point"}
}