{
  "type": "Feature",
  "properties": {
    "iso:country":"US",
    "sg:address":"7000 N Military Trl",
    "sg:city":"Palm Beach Gardens",
    "sg:classifiers":[
        {
            "category":"Freight",
            "type":"Transportation"
        }
    ],
    "sg:phone":"+1 561 844 3999",
    "sg:postcode":"33410",
    "sg:province":"FL",
    "sg:tags":[
        "general"
    ],
    "wof:name":"Buds Southern Self Storage",
    "wof:placetype":"venue"
},
  "geometry": {"coordinates":[-80.107356,26.78115],"type":"Point"}
}