{
  "type": "Feature",
  "properties": {
    "iso:country":"US",
    "sg:address":"408 S Casey Key Rd",
    "sg:city":"Nokomis",
    "sg:classifiers":[
        {
            "category":"Real Estate",
            "subcategory":"Real Estate Operator",
            "type":"Services"
        }
    ],
    "sg:phone":"+1 941 488 2508",
    "sg:postcode":"34275",
    "sg:province":"FL",
    "sg:tags":[
        "apartment"
    ],
    "wof:name":"West Wind Apartments",
    "wof:placetype":"venue"
},
  "geometry": {"coordinates":[-82.469363,27.12111],"type":"Point"}
}