{
  "type": "Feature",
  "properties": {
    "addr:full":"33 N Garden Ave Clearwater FL 33755",
    "addr:housenumber":"33",
    "addr:postcode":"33755",
    "addr:street":"N Garden Ave",
    "iso:country":"US",
    "sg:address":"33 N Garden Ave",
    "sg:city":"Clearwater",
    "sg:classifiers":[
        {
            "category":"Manufacturing",
            "subcategory":"Furniture",
            "type":"Manufacturing & Wholesale Goods"
        },
        {
            "category":"Manufacturing",
            "subcategory":"Tools & Machinery",
            "type":"Manufacturing & Wholesale Goods"
        }
    ],
    "sg:phone":"+1 727 446 0605",
    "sg:postcode":"33755",
    "sg:province":"FL",
    "sg:tags":[
        "physician",
        "floatation",
        "mfg",
        "powered",
        "bed",
        "therapy",
        "surgeon"
    ],
    "wof:name":"Biologics Inc",
    "wof:placetype":"venue"
},
  "geometry": {"coordinates":[-82.798625,27.966572],"type":"Point"}
}