{
  "type": "Feature",
  "properties": {
    "iso:country":"US",
    "sg:address":"137 S Tyndall Pkwy",
    "sg:city":"Panama City",
    "sg:classifiers":[
        {
            "category":"Food & Beverages",
            "subcategory":"Specialty",
            "type":"Retail Goods"
        }
    ],
    "sg:phone":"+1 850 763 4080",
    "sg:postcode":"32404",
    "sg:province":"FL",
    "sg:tags":[
        "health",
        "diet"
    ],
    "wof:name":"Natural Choice Health Foods",
    "wof:placetype":"venue"
},
  "geometry": {"coordinates":[-85.59102,30.142643],"type":"Point"}
}