{
  "type": "Feature",
  "properties": {
    "addr:full":"1500 W Washington St Orlando FL 32805",
    "addr:housenumber":"1500",
    "addr:postcode":"32805",
    "addr:street":"W Washington St",
    "iso:country":"US",
    "sg:address":"1500 W Washington St",
    "sg:city":"Orlando",
    "sg:classifiers":[
        {
            "category":"Manufacturing",
            "subcategory":"Motor Vehicles & Parts",
            "type":"Manufacturing & Wholesale Goods"
        }
    ],
    "sg:phone":"+1 407 425 0536",
    "sg:postcode":"32805",
    "sg:province":"FL",
    "sg:tags":[
        "float"
    ],
    "sg:website":"www.moderncontrol.com",
    "wof:name":"Modern Control & Supply Inc",
    "wof:placetype":"venue"
},
  "geometry": {"coordinates":[-81.40157499999999,28.543874],"type":"Point"}
}