{
  "type": "Feature",
  "properties": {
    "iso:country":"US",
    "sg:address":"2546 12th St",
    "sg:city":"Sarasota",
    "sg:classifiers":[
        {
            "category":"Freight",
            "type":"Transportation"
        }
    ],
    "sg:phone":"+1 941 365 9102",
    "sg:postcode":"34237",
    "sg:province":"FL",
    "sg:tags":[
        "operator",
        "storage",
        "trucking",
        "commercial",
        "local"
    ],
    "wof:name":"Economy Storage Inc",
    "wof:placetype":"venue"
},
  "geometry": {"coordinates":[-82.519491,27.348481],"type":"Point"}
}