{
  "type": "Feature",
  "properties": {
    "iso:country":"US",
    "sg:address":"1915 Collier Pkwy",
    "sg:city":"Lutz",
    "sg:classifiers":[
        {
            "category":"Retail",
            "subcategory":"Auto Repair",
            "type":"Services"
        }
    ],
    "sg:phone":"+1 813 909 4030",
    "sg:postcode":"33549",
    "sg:province":"FL",
    "sg:tags":[
        "repairing",
        "automobile",
        "general"
    ],
    "wof:name":"Quality Care Automotive Ctr",
    "wof:placetype":"venue"
},
  "geometry": {"coordinates":[-82.43791,28.185809],"type":"Point"}
}