{
  "type": "Feature",
  "properties": {
    "iso:country":"US",
    "sg:address":"3401 Pga Blvd",
    "sg:city":"West Palm Beach",
    "sg:classifiers":[
        {
            "category":"Organizations",
            "subcategory":"Non-profit Organization",
            "type":"Services"
        }
    ],
    "sg:phone":"+1 561 745 4205",
    "sg:postcode":"33410",
    "sg:province":"FL",
    "sg:tags":[
        "breastfeeding",
        "information",
        "supply"
    ],
    "wof:name":"Center For Lactation-Pediatric",
    "wof:placetype":"venue"
},
  "geometry": {"coordinates":[-80.086465,26.845087],"type":"Point"}
}