{
  "type": "Feature",
  "properties": {
    "addr:full":"31428 Co Rd 435 Sorrento FL 32776",
    "addr:housenumber":"31428;435",
    "addr:postcode":"32776",
    "addr:street":"Co Rd",
    "iso:country":"US",
    "sg:address":"31428 Co Rd 435",
    "sg:city":"Sorrento",
    "sg:classifiers":[
        {
            "category":"Personal",
            "subcategory":"Beauty Salon",
            "type":"Services"
        }
    ],
    "sg:phone":"+1 352 735 3351",
    "sg:postcode":"32776",
    "sg:province":"FL",
    "wof:name":"Tina's Total Hair Care",
    "wof:placetype":"venue"
},
  "geometry": {"coordinates":[-81.533108,28.807857],"type":"Point"}
}