{
  "type": "Feature",
  "properties": {
    "addr:full":"15660 San Carlos Blvd Fort Myers FL 33908",
    "addr:housenumber":"15660",
    "addr:postcode":"33908",
    "addr:street":"San Carlos Blvd",
    "iso:country":"US",
    "sg:address":"15660 San Carlos Blvd",
    "sg:city":"Fort Myers",
    "sg:classifiers":[
        {
            "category":"Travel",
            "subcategory":"Travel Agent",
            "type":"Entertainment"
        }
    ],
    "sg:phone":"+1 239 489 1160",
    "sg:postcode":"33908",
    "sg:province":"FL",
    "sg:tags":[
        "agency",
        "bureau"
    ],
    "wof:name":"Gulf Point Travel",
    "wof:placetype":"venue"
},
  "geometry": {"coordinates":[-81.94364400000001,26.510377],"type":"Point"}
}