{
  "type": "Feature",
  "properties": {
    "addr:full":"3504 Woodridge Pkwy Palm Harbor FL 34684",
    "addr:housenumber":"3504",
    "addr:postcode":"34684",
    "addr:street":"Woodridge Pkwy",
    "iso:country":"US",
    "sg:address":"3504 Woodridge Pkwy",
    "sg:city":"Palm Harbor",
    "sg:classifiers":[
        {
            "category":"Professional",
            "subcategory":"Computer Services",
            "type":"Services"
        }
    ],
    "sg:phone":"+1 727 771 8404",
    "sg:postcode":"34684",
    "sg:province":"FL",
    "sg:tags":[
        "prepackaged",
        "software"
    ],
    "wof:name":"Silco Software Technology Inc",
    "wof:placetype":"venue"
},
  "geometry": {"coordinates":[-82.72099799999999,28.088175],"type":"Point"}
}