{
  "type": "Feature",
  "properties": {
    "addr:full":"50 SW 84th Ave Plantation FL 33324",
    "addr:housenumber":"50",
    "addr:postcode":"33324",
    "addr:street":"Sw 84Th Ave",
    "iso:country":"US",
    "sg:address":"50 SW 84th Ave",
    "sg:city":"Plantation",
    "sg:classifiers":[
        {
            "category":"Banks & Credit Unions",
            "subcategory":"Bank",
            "type":"Services"
        }
    ],
    "sg:phone":"+1 954 468 2800",
    "sg:postcode":"33324",
    "sg:province":"FL",
    "wof:name":"Wachovia Bank",
    "wof:placetype":"venue"
},
  "geometry": {"coordinates":[-80.25443199999999,26.006892],"type":"Point"}
}