{
  "type": "Feature",
  "properties": {
    "iso:country":"US",
    "sg:address":"5620 NW 44th Ave",
    "sg:city":"Ocala",
    "sg:classifiers":[
        {
            "category":"Building & Trades",
            "subcategory":"Construction",
            "type":"Services"
        }
    ],
    "sg:phone":"+1 352 629 6277",
    "sg:postcode":"34482",
    "sg:province":"FL",
    "sg:tags":[
        "mobile",
        "home"
    ],
    "wof:name":"Broglin Mobile Home Contractor",
    "wof:placetype":"venue"
},
  "geometry": {"coordinates":[-82.193699,29.241632],"type":"Point"}
}