{
  "type": "Feature",
  "properties": {
    "iso:country":"US",
    "sg:address":"8000 Peters Rd",
    "sg:city":"Fort Lauderdale",
    "sg:classifiers":[
        {
            "category":"Insurance",
            "subcategory":"Title Insurance",
            "type":"Services"
        },
        {
            "category":"Real Estate",
            "subcategory":"Real Estate Services",
            "type":"Services"
        }
    ],
    "sg:phone":"+1 954 667 0026",
    "sg:postcode":"33324",
    "sg:province":"FL",
    "sg:tags":[
        "company",
        "carrier"
    ],
    "wof:name":"Southeast Land Title Group",
    "wof:placetype":"venue"
},
  "geometry": {"coordinates":[-80.254791,26.105361],"type":"Point"}
}