{
  "type": "Feature",
  "properties": {
    "addr:full":"6801 NW 77th Ave Miami FL 33166",
    "addr:housenumber":"6801",
    "addr:postcode":"33166",
    "addr:street":"Nw 77Th Ave",
    "iso:country":"US",
    "sg:address":"6801 NW 77th Ave",
    "sg:city":"Miami",
    "sg:classifiers":[
        {
            "category":"Social Services",
            "subcategory":"Job Training",
            "type":"Services"
        }
    ],
    "sg:phone":"+1 305 883 5399",
    "sg:postcode":"33166",
    "sg:province":"FL",
    "sg:tags":[
        "rehabilitation"
    ],
    "wof:name":"Rosa Rehabilitation Inc",
    "wof:placetype":"venue"
},
  "geometry": {"coordinates":[-80.321664,25.837137],"type":"Point"}
}