{
  "type": "Feature",
  "properties": {
    "addr:full":"5195 NW 15th St Margate FL 33063",
    "addr:housenumber":"5195",
    "addr:postcode":"33063",
    "addr:street":"Nw 15Th St Margate",
    "iso:country":"US",
    "sg:address":"5195 NW 15th St",
    "sg:city":"Margate",
    "sg:classifiers":[
        {
            "category":"Manufacturing",
            "subcategory":"Furniture",
            "type":"Manufacturing & Wholesale Goods"
        }
    ],
    "sg:phone":"+1 954 975 8158",
    "sg:postcode":"33063",
    "sg:province":"FL",
    "sg:tags":[
        "wood",
        "fixture",
        "spec",
        "store",
        "mfg"
    ],
    "wof:name":"Sam Weiss Woodworking Inc",
    "wof:placetype":"venue"
},
  "geometry": {"coordinates":[-80.193468,26.248675],"type":"Point"}
}