{
  "type": "Feature",
  "properties": {
    "iso:country":"US",
    "sg:address":"900 Beach Dr NE",
    "sg:city":"Saint Petersburg",
    "sg:classifiers":[
        {
            "category":"Professional",
            "subcategory":"Management & Consulting",
            "type":"Services"
        }
    ],
    "sg:phone":"+1 727 898 5507",
    "sg:postcode":"33701",
    "sg:province":"FL",
    "sg:tags":[
        "business"
    ],
    "wof:name":"Site Assessment Engineering",
    "wof:placetype":"venue"
},
  "geometry": {"coordinates":[-82.628564,27.782199],"type":"Point"}
}