{
  "type": "Feature",
  "properties": {
    "iso:country":"US",
    "sg:address":"1242 SW Pine Island Rd Ste 4",
    "sg:city":"Cape Coral",
    "sg:classifiers":[
        {
            "category":"Bars & Pubs",
            "subcategory":"Sports Bar",
            "type":"Food & Drink"
        }
    ],
    "sg:phone":"+1 239 573 7665",
    "sg:postcode":"33991",
    "sg:province":"FL",
    "sg:tags":[
        "hall",
        "pool"
    ],
    "wof:name":"Diamond Billiards",
    "wof:placetype":"venue"
},
  "geometry": {"coordinates":[-82.000818,26.640482],"type":"Point"}
}