{
  "type": "Feature",
  "properties": {
    "addr:full":"3786 Tamiami Trl Port Charlotte FL 33952",
    "addr:housenumber":"3786",
    "addr:postcode":"33952",
    "addr:street":"Tamiami Trl",
    "iso:country":"US",
    "sg:address":"3786 Tamiami Trl",
    "sg:city":"Port Charlotte",
    "sg:classifiers":[
        {
            "category":"Shopping",
            "type":"Retail Goods"
        }
    ],
    "sg:phone":"+1 941 629 1390",
    "sg:postcode":"33952",
    "sg:province":"FL",
    "sg:tags":[
        "religious"
    ],
    "sg:website":"www.gospelgiftsonline.com",
    "wof:name":"Gospel Gifts Christian Book",
    "wof:placetype":"venue"
},
  "geometry": {"coordinates":[-82.088769,26.975228],"type":"Point"}
}