{
  "type": "Feature",
  "properties": {
    "addr:full":"3800 Pine Forest Rd Cantonment FL 32533",
    "addr:housenumber":"3800",
    "addr:postcode":"32533",
    "addr:street":"Pine Forest Rd",
    "iso:country":"US",
    "sg:address":"3800 Pine Forest Rd",
    "sg:city":"Cantonment",
    "sg:classifiers":[
        {
            "category":"Organizations",
            "subcategory":"Religious Organization",
            "type":"Services"
        }
    ],
    "sg:phone":"+1 850 494 3010",
    "sg:postcode":"32533",
    "sg:province":"FL",
    "sg:website":"www.milestonebaptist.com",
    "wof:name":"Milestone Baptist Church",
    "wof:placetype":"venue"
},
  "geometry": {"coordinates":[-87.31281799999999,30.542015],"type":"Point"}
}