{
  "type": "Feature",
  "properties": {
    "addr:full":"9410 NW 100th St Medley FL 33178",
    "addr:housenumber":"9410",
    "addr:postcode":"33178",
    "addr:street":"Nw 100Th St",
    "iso:country":"US",
    "sg:address":"9410 NW 100th St",
    "sg:city":"Medley",
    "sg:classifiers":[
        {
            "category":"Personal",
            "type":"Services"
        }
    ],
    "sg:phone":"+1 305 888 3963",
    "sg:postcode":"33178",
    "sg:province":"FL",
    "sg:tags":[
        "mover"
    ],
    "sg:website":"www.joesmoving.com",
    "wof:name":"Joe's Moving & Storage",
    "wof:placetype":"venue"
},
  "geometry": {"coordinates":[-80.350899,25.863501],"type":"Point"}
}