{
  "type": "Feature",
  "properties": {
    "addr:full":"5870 SW 13th St West Miami FL 33144",
    "addr:housenumber":"5870",
    "addr:postcode":"33144",
    "addr:street":"Sw 13Th St",
    "iso:country":"US",
    "sg:address":"5870 SW 13th St",
    "sg:city":"West Miami",
    "sg:classifiers":[
        {
            "category":"Professional",
            "subcategory":"Accounting & Tax Preparation",
            "type":"Services"
        }
    ],
    "sg:phone":"+1 305 266 3793",
    "sg:postcode":"33144",
    "sg:province":"FL",
    "sg:tags":[
        "return",
        "filing"
    ],
    "wof:name":"Secure Block Corp",
    "wof:placetype":"venue"
},
  "geometry": {"coordinates":[-80.290485,25.759107],"type":"Point"}
}