{
  "type": "Feature",
  "properties": {
    "addr:full":"3081 Salzedo St Coral Gables FL 33134",
    "addr:housenumber":"3081",
    "addr:postcode":"33134",
    "addr:street":"Salzedo St",
    "iso:country":"US",
    "sg:address":"3081 Salzedo St",
    "sg:city":"Coral Gables",
    "sg:classifiers":[
        {
            "category":"Professional",
            "subcategory":"Lawyer & Legal Services",
            "type":"Services"
        }
    ],
    "sg:phone":"+1 305 448 4441",
    "sg:postcode":"33134",
    "sg:province":"FL",
    "wof:name":"Remy Michael Anthony PA",
    "wof:placetype":"venue"
},
  "geometry": {"coordinates":[-80.260273,25.744212],"type":"Point"}
}