{
  "type": "Feature",
  "properties": {
    "addr:full":"1315 W 1st St Sanford FL 32771",
    "addr:housenumber":"1315",
    "addr:postcode":"32771",
    "addr:street":"W 1St St",
    "iso:country":"US",
    "sg:address":"1315 W 1st St",
    "sg:city":"Sanford",
    "sg:classifiers":[
        {
            "category":"Autos & Motor Vehicles",
            "subcategory":"Automobile Sales",
            "type":"Retail Goods"
        }
    ],
    "sg:phone":"+1 407 323 9688",
    "sg:postcode":"32771",
    "sg:province":"FL",
    "sg:tags":[
        "sport",
        "trailer",
        "utility"
    ],
    "wof:name":"K-N-D Trailer Sales",
    "wof:placetype":"venue"
},
  "geometry": {"coordinates":[-81.2826,28.811659],"type":"Point"}
}