{
  "type": "Feature",
  "properties": {
    "addr:full":"6346 Rowan Rd New Port Richey FL 34653",
    "addr:housenumber":"6346",
    "addr:postcode":"34653",
    "addr:street":"Rowan Rd",
    "iso:country":"US",
    "sg:address":"6346 Rowan Rd",
    "sg:city":"New Port Richey",
    "sg:classifiers":[
        {
            "category":"Autos & Motor Vehicles",
            "subcategory":"Auto Supplies",
            "type":"Retail Goods"
        }
    ],
    "sg:phone":"+1 727 848 6934",
    "sg:postcode":"34653",
    "sg:province":"FL",
    "sg:tags":[
        "wheel",
        "cover"
    ],
    "wof:name":"National Wheel House",
    "wof:placetype":"venue"
},
  "geometry": {"coordinates":[-82.699091,28.252916],"type":"Point"}
}