{
  "type": "Feature",
  "properties": {
    "addr:full":"27 Southwind Ct Niceville FL 32578",
    "addr:housenumber":"27",
    "addr:postcode":"32578",
    "addr:street":"Southwind Ct",
    "iso:country":"US",
    "sg:address":"27 Southwind Ct",
    "sg:city":"Niceville",
    "sg:classifiers":[
        {
            "category":"Professional",
            "subcategory":"Management & Consulting",
            "type":"Services"
        }
    ],
    "sg:phone":"+1 850 897 0007",
    "sg:postcode":"32578",
    "sg:province":"FL",
    "sg:tags":[
        "consultant",
        "security",
        "system"
    ],
    "wof:name":"Blair Consulting Inc",
    "wof:placetype":"venue"
},
  "geometry": {"coordinates":[-86.42827699999999,30.473863],"type":"Point"}
}