{
  "type": "Feature",
  "properties": {
    "addr:full":"7482 Lake Worth Rd Lake Worth FL 33467",
    "addr:housenumber":"7482",
    "addr:postcode":"33467",
    "addr:street":"Lake Worth Rd",
    "iso:country":"US",
    "sg:address":"7482 Lake Worth Rd",
    "sg:city":"Lake Worth",
    "sg:classifiers":[
        {
            "category":"Retail",
            "subcategory":"Car Wash",
            "type":"Services"
        }
    ],
    "sg:phone":"+1 561 432 0908",
    "sg:postcode":"33467",
    "sg:province":"FL",
    "sg:tags":[
        "polishing",
        "washing"
    ],
    "wof:name":"AAA Auto Wax",
    "wof:placetype":"venue"
},
  "geometry": {"coordinates":[-80.162093,26.617501],"type":"Point"}
}