{
  "type": "Feature",
  "properties": {
    "iso:country":"US",
    "sg:address":"1701 Espanola Dr",
    "sg:city":"Miami",
    "sg:classifiers":[
        {
            "category":"Wholesale",
            "subcategory":"Machinery & Supplies",
            "type":"Manufacturing & Wholesale Goods"
        }
    ],
    "sg:phone":"+1 305 857 0343",
    "sg:postcode":"33133",
    "sg:province":"FL",
    "wof:name":"Kitesurfcom",
    "wof:placetype":"venue"
},
  "geometry": {"coordinates":[-80.224276,25.742924],"type":"Point"}
}