{
  "type": "Feature",
  "properties": {
    "addr:full":"790 NE 25th St Hialeah FL 33064",
    "addr:housenumber":"790",
    "addr:postcode":"33064",
    "addr:street":"Ne 25Th St",
    "iso:country":"US",
    "sg:address":"790 NE 25th St",
    "sg:city":"Hialeah",
    "sg:classifiers":[
        {
            "category":"Autos & Motor Vehicles",
            "subcategory":"Fuel & Gas Station",
            "type":"Retail Goods"
        }
    ],
    "sg:phone":"+1 305 696 3601",
    "sg:postcode":"33064",
    "sg:province":"FL",
    "sg:tags":[
        "station",
        "gasoline"
    ],
    "wof:name":"Amoco",
    "wof:placetype":"venue"
},
  "geometry": {"coordinates":[-80.112611,26.261727],"type":"Point"}
}