{
  "type": "Feature",
  "properties": {
    "addr:full":"16023 Duval Rd Jacksonville FL 32218",
    "addr:housenumber":"16023",
    "addr:postcode":"32218",
    "addr:street":"Duval Rd",
    "iso:country":"US",
    "sg:address":"16023 Duval Rd",
    "sg:city":"Jacksonville",
    "sg:classifiers":[
        {
            "category":"Bus Charters",
            "type":"Transportation"
        },
        {
            "category":"Recreation",
            "type":"Entertainment"
        }
    ],
    "sg:phone":"+1 904 714 2140",
    "sg:postcode":"32218",
    "sg:province":"FL",
    "sg:tags":[
        "rental"
    ],
    "wof:name":"Blane Greene Charters",
    "wof:placetype":"venue"
},
  "geometry": {"coordinates":[-81.625491,30.490838],"type":"Point"}
}