{
  "type": "Feature",
  "properties": {
    "addr:full":"712 110th Ave N Naples FL 34108",
    "addr:housenumber":"712",
    "addr:postcode":"34108",
    "addr:street":"110Th Ave N",
    "iso:country":"US",
    "sg:address":"712 110th Ave N",
    "sg:city":"Naples",
    "sg:classifiers":[
        {
            "category":"Building & Trades",
            "subcategory":"Construction",
            "type":"Services"
        }
    ],
    "sg:phone":"+1 239 591 0959",
    "sg:postcode":"34108",
    "sg:province":"FL",
    "sg:tags":[
        "builder",
        "operative"
    ],
    "wof:name":"Margaret A Fletcher Inc",
    "wof:placetype":"venue"
},
  "geometry": {"coordinates":[-81.805891,26.271406],"type":"Point"}
}