{
  "type": "Feature",
  "properties": {
    "addr:full":"11801 NW 101st Rd Ste 5 Medley FL 33178",
    "addr:housenumber":"11801",
    "addr:postcode":"33178",
    "addr:street":"Nw 101St Rd Ste 5",
    "iso:country":"US",
    "sg:address":"11801 NW 101st Rd Ste 5",
    "sg:city":"Medley",
    "sg:classifiers":[
        {
            "category":"Autos & Motor Vehicles",
            "subcategory":"Auto Supplies",
            "type":"Retail Goods"
        }
    ],
    "sg:phone":"+1 305 885 1601",
    "sg:postcode":"33178",
    "sg:province":"FL",
    "sg:tags":[
        "tire"
    ],
    "wof:name":"Yv Tire Distributors Inc",
    "wof:placetype":"venue"
},
  "geometry": {"coordinates":[-80.367104,25.8759],"type":"Point"}
}