{
  "type": "Feature",
  "properties": {
    "iso:country":"US",
    "sg:address":"12451 Harker St",
    "sg:city":"Brooksville",
    "sg:classifiers":[
        {
            "category":"Shopping",
            "subcategory":"Clothing, Apparel, & Fashions",
            "type":"Retail Goods"
        }
    ],
    "sg:phone":"+1 352 597 5627",
    "sg:postcode":"34613",
    "sg:province":"FL",
    "sg:tags":[
        "baby",
        "accessory"
    ],
    "wof:name":"Gladys Hill Babycraft",
    "wof:placetype":"venue"
},
  "geometry": {"coordinates":[-82.51727099999999,28.537402],"type":"Point"}
}