{
  "type": "Feature",
  "properties": {
    "addr:full":"11973 Co Rd 132 SE Jasper FL 32052",
    "addr:housenumber":"11973",
    "addr:postcode":"32052",
    "addr:street":"Co Rd 132 Se",
    "iso:country":"US",
    "sg:address":"11973 Co Rd 132 SE",
    "sg:city":"Jasper",
    "sg:classifiers":[
        {
            "category":"Home & Garden",
            "subcategory":"Carpets & Floor Coverings",
            "type":"Retail Goods"
        }
    ],
    "sg:phone":"+1 386 792 2297",
    "sg:postcode":"32052",
    "sg:province":"FL",
    "wof:name":"Towne & Country Home Ctr",
    "wof:placetype":"venue"
},
  "geometry": {"coordinates":[-82.921297,30.408103],"type":"Point"}
}