{
  "type": "Feature",
  "properties": {
    "iso:country":"US",
    "sg:address":"2443 Cleveland St",
    "sg:city":"Hollywood",
    "sg:classifiers":[
        {
            "category":"Real Estate",
            "subcategory":"Real Estate Agent",
            "type":"Services"
        }
    ],
    "sg:phone":"+1 954 925 9320",
    "sg:postcode":"33020",
    "sg:province":"FL",
    "wof:name":"Elite Properties",
    "wof:placetype":"venue"
},
  "geometry": {"coordinates":[-80.15644899999999,26.023307],"type":"Point"}
}