{
  "type": "Feature",
  "properties": {
    "iso:country":"US",
    "sg:address":"3016 Dade Ave",
    "sg:city":"Orlando",
    "sg:classifiers":[
        {
            "category":"Education",
            "subcategory":"School",
            "type":"Public Place"
        }
    ],
    "sg:phone":"+1 407 897 3623",
    "sg:postcode":"32804",
    "sg:province":"FL",
    "sg:tags":[
        "k-",
        "private"
    ],
    "wof:name":"Crosspointe",
    "wof:placetype":"venue"
},
  "geometry": {"coordinates":[-81.374353,28.579138],"type":"Point"}
}