{
  "type": "Feature",
  "properties": {
    "iso:country":"US",
    "sg:address":"546 Croton Rd",
    "sg:city":"Melbourne",
    "sg:classifiers":[
        {
            "category":"Banks & Credit Unions",
            "subcategory":"Bank",
            "type":"Services"
        }
    ],
    "sg:phone":"+1 321 242 6669",
    "sg:postcode":"32935",
    "sg:province":"FL",
    "sg:tags":[
        "mortgage"
    ],
    "wof:name":"Capital Mortgage Corp",
    "wof:placetype":"venue"
},
  "geometry": {"coordinates":[-80.654955,28.116551],"type":"Point"}
}