{
  "type": "Feature",
  "properties": {
    "iso:country":"US",
    "sg:address":"8750 W Oakland Park Blvd",
    "sg:city":"Sunrise",
    "sg:classifiers":[
        {
            "category":"Building & Trades",
            "subcategory":"Landscaping Services",
            "type":"Services"
        }
    ],
    "sg:phone":"+1 954 749 8031",
    "sg:postcode":"33351",
    "sg:province":"FL",
    "sg:tags":[
        "designer",
        "landscape"
    ],
    "wof:name":"Bamboo Best Landscaping",
    "wof:placetype":"venue"
},
  "geometry": {"coordinates":[-80.266133,26.168243],"type":"Point"}
}