{
  "type": "Feature",
  "properties": {
    "addr:full":"1610 13th St St Cloud FL 34769",
    "addr:housenumber":"1610",
    "addr:postcode":"34769",
    "addr:street":"13Th St",
    "iso:country":"US",
    "sg:address":"1610 13th St",
    "sg:city":"St Cloud",
    "sg:classifiers":[
        {
            "category":"Banks & Credit Unions",
            "subcategory":"Bank",
            "type":"Services"
        }
    ],
    "sg:phone":"+1 407 891 6565",
    "sg:postcode":"34769",
    "sg:province":"FL",
    "sg:tags":[
        "mortgage",
        "loan",
        "broker",
        "real estate"
    ],
    "wof:name":"Statewide Priority Mortgages",
    "wof:placetype":"venue"
},
  "geometry": {"coordinates":[-81.287019,28.246155],"type":"Point"}
}