{
  "type": "Feature",
  "properties": {
    "iso:country":"US",
    "sg:address":"2255 Kingston St",
    "sg:city":"Jacksonville",
    "sg:classifiers":[
        {
            "category":"Social Services",
            "subcategory":"Child Care",
            "type":"Services"
        }
    ],
    "sg:phone":"+1 904 356 4532",
    "sg:postcode":"32209",
    "sg:province":"FL",
    "sg:tags":[
        "day"
    ],
    "wof:name":"Children Our Future Lrng Ctr",
    "wof:placetype":"venue"
},
  "geometry": {"coordinates":[-81.70117999999999,30.337944],"type":"Point"}
}