{
  "type": "Feature",
  "properties": {
    "iso:country":"US",
    "sg:address":"700 W 2nd Ave",
    "sg:city":"Hialeah",
    "sg:classifiers":[
        {
            "category":"Utilities",
            "subcategory":"Sewage",
            "type":"Services"
        }
    ],
    "sg:phone":"+1 305 888 2522",
    "sg:postcode":"33010",
    "sg:province":"FL",
    "sg:tags":[
        "water",
        "plant",
        "treatment"
    ],
    "wof:name":"Miami Dade Water & Sewer Dept",
    "wof:placetype":"venue"
},
  "geometry": {"coordinates":[-80.285574,25.827088],"type":"Point"}
}