{
  "type": "Feature",
  "properties": {
    "addr:full":"3915 Henderson Blvd Tampa FL 33629",
    "addr:housenumber":"3915",
    "addr:postcode":"33629",
    "addr:street":"Henderson Blvd",
    "iso:country":"US",
    "sg:address":"3915 Henderson Blvd",
    "sg:city":"Tampa",
    "sg:phone":"+1 813 281 2100",
    "sg:postcode":"33629",
    "sg:province":"FL",
    "sg:website":"http://www.lauroristorante.com",
    "wof:name":"Lauro Ristorante",
    "wof:placetype":"venue"
},
  "geometry": {"coordinates":[-82.508695,27.93135],"type":"Point"}
}