{
  "type": "Feature",
  "properties": {
    "addr:full":"5100 Coronado Ridge Boca Raton FL 33486",
    "addr:housenumber":"5100",
    "addr:postcode":"33486",
    "addr:street":"Coronado Ridge",
    "iso:country":"US",
    "sg:address":"5100 Coronado Ridge",
    "sg:city":"Boca Raton",
    "sg:classifiers":[
        {
            "category":"Recreation",
            "type":"Entertainment"
        }
    ],
    "sg:phone":"+1 561 750 1060",
    "sg:postcode":"33486",
    "sg:province":"FL",
    "sg:tags":[
        "diving",
        "instruction"
    ],
    "wof:name":"Burgering Enterprises",
    "wof:placetype":"venue"
},
  "geometry": {"coordinates":[-80.122812,26.358647],"type":"Point"}
}