{
  "type": "Feature",
  "properties": {
    "addr:full":"3677 Central Ave Fort Myers FL 33901",
    "addr:housenumber":"3677",
    "addr:postcode":"33901",
    "addr:street":"Central Ave",
    "iso:country":"US",
    "sg:address":"3677 Central Ave",
    "sg:city":"Fort Myers",
    "sg:classifiers":[
        {
            "category":"Education",
            "subcategory":"School",
            "type":"Public Place"
        }
    ],
    "sg:phone":"+1 239 939 1992",
    "sg:postcode":"33901",
    "sg:province":"FL",
    "wof:name":"Horizons Healthcare Institute",
    "wof:placetype":"venue"
},
  "geometry": {"coordinates":[-81.86368299999999,26.609034],"type":"Point"}
}