{
  "type": "Feature",
  "properties": {
    "iso:country":"US",
    "sg:address":"3121 Lake Suzanne Dr",
    "sg:city":"Cantonment",
    "sg:classifiers":[
        {
            "category":"Building & Trades",
            "subcategory":"Construction",
            "type":"Services"
        }
    ],
    "sg:phone":"+1 850 937 0377",
    "sg:postcode":"32533",
    "sg:province":"FL",
    "sg:tags":[
        "clearing",
        "land",
        "leveling"
    ],
    "wof:name":"Castellani Backhoe & Dozer Svc",
    "wof:placetype":"venue"
},
  "geometry": {"coordinates":[-87.351772,30.570607],"type":"Point"}
}