{
  "type": "Feature",
  "properties": {
    "iso:country":"US",
    "sg:address":"7334 SW 42nd St",
    "sg:city":"Miami",
    "sg:classifiers":[
        {
            "category":"Banks & Credit Unions",
            "subcategory":"Investment Brokerage",
            "type":"Services"
        }
    ],
    "sg:phone":"+1 305 261 7070",
    "sg:postcode":"33155",
    "sg:province":"FL",
    "sg:tags":[
        "merger",
        "acquisition"
    ],
    "wof:name":"Paragon Acquisitions Inc",
    "wof:placetype":"venue"
},
  "geometry": {"coordinates":[-80.31285699999999,25.731518],"type":"Point"}
}