{
  "type": "Feature",
  "properties": {
    "iso:country":"US",
    "sg:address":"19836 N Riverside Dr",
    "sg:city":"Jupiter",
    "sg:classifiers":[
        {
            "category":"Manufacturing",
            "subcategory":"Watercraft",
            "type":"Manufacturing & Wholesale Goods"
        }
    ],
    "sg:phone":"+1 561 748 9541",
    "sg:postcode":"33469",
    "sg:province":"FL",
    "wof:name":"Resilience Boatworks Inc",
    "wof:placetype":"venue"
},
  "geometry": {"coordinates":[-80.10506700000001,26.968246],"type":"Point"}
}