{
  "type": "Feature",
  "properties": {
    "addr:full":"480 Maplewood Dr Jupiter FL 33458",
    "addr:housenumber":"480",
    "addr:postcode":"33458",
    "addr:street":"Maplewood Dr",
    "iso:country":"US",
    "sg:address":"480 Maplewood Dr",
    "sg:city":"Jupiter",
    "sg:classifiers":[
        {
            "category":"Building & Trades",
            "subcategory":"Construction",
            "type":"Services"
        }
    ],
    "sg:phone":"+1 561 747 1217",
    "sg:postcode":"33458",
    "sg:province":"FL",
    "sg:tags":[
        "home",
        "builder"
    ],
    "wof:name":"Home Investment Svc",
    "wof:placetype":"venue"
},
  "geometry": {"coordinates":[-80.12506399999999,26.934044],"type":"Point"}
}