{
  "type": "Feature",
  "properties": {
    "iso:country":"US",
    "sg:address":"1543 Kingsley Ave",
    "sg:city":"Orange Park",
    "sg:classifiers":[
        {
            "category":"Banks & Credit Unions",
            "subcategory":"Bank",
            "type":"Services"
        }
    ],
    "sg:phone":"+1 904 264 1730",
    "sg:postcode":"32073",
    "sg:province":"FL",
    "sg:tags":[
        "loan",
        "real estate"
    ],
    "wof:name":"First South Financial Group",
    "wof:placetype":"venue"
},
  "geometry": {"coordinates":[-81.730131,30.164518],"type":"Point"}
}