{
  "type": "Feature",
  "properties": {
    "iso:country":"US",
    "sg:address":"1906 Old Club Pt",
    "sg:city":"Maitland",
    "sg:classifiers":[
        {
            "category":"Building & Trades",
            "subcategory":"Construction",
            "type":"Services"
        }
    ],
    "sg:phone":"+1 407 628 2885",
    "sg:postcode":"32751",
    "sg:province":"FL",
    "sg:tags":[
        "house"
    ],
    "wof:name":"Core Engineering & Cnstr",
    "wof:placetype":"venue"
},
  "geometry": {"coordinates":[-81.343729,28.627054],"type":"Point"}
}