{
  "type": "Feature",
  "properties": {
    "iso:country":"US",
    "sg:address":"14 E Carroll St",
    "sg:city":"Kissimmee",
    "sg:classifiers":[
        {
            "category":"Autos & Motor Vehicles",
            "subcategory":"Auto Supplies",
            "type":"Retail Goods"
        },
        {
            "category":"Retail",
            "subcategory":"Auto Repair",
            "type":"Services"
        }
    ],
    "sg:phone":"+1 407 944 9663",
    "sg:postcode":"34744",
    "sg:province":"FL",
    "sg:tags":[
        "tire"
    ],
    "wof:name":"Tire Zone",
    "wof:placetype":"venue"
},
  "geometry": {"coordinates":[-81.403581,28.326239],"type":"Point"}
}