{
  "type": "Feature",
  "properties": {
    "addr:full":"5756 SW 31st St Miami FL 33155",
    "addr:housenumber":"5756",
    "addr:postcode":"33155",
    "addr:street":"Sw 31St St",
    "iso:country":"US",
    "sg:address":"5756 SW 31st St",
    "sg:city":"Miami",
    "sg:classifiers":[
        {
            "category":"Professional",
            "subcategory":"Engineering",
            "type":"Services"
        }
    ],
    "sg:phone":"+1 305 665 7243",
    "sg:postcode":"33155",
    "sg:province":"FL",
    "wof:name":"M B S Associates",
    "wof:placetype":"venue"
},
  "geometry": {"coordinates":[-80.28793,25.742026],"type":"Point"}
}