{
  "type": "Feature",
  "properties": {
    "iso:country":"US",
    "sg:address":"9017 Biscayne Blvd",
    "sg:city":"Miami Shores",
    "sg:classifiers":[
        {
            "category":"Shopping",
            "subcategory":"Mobile Phones",
            "type":"Retail Goods"
        }
    ],
    "sg:phone":"+1 305 751 3112",
    "sg:postcode":"33138",
    "sg:province":"FL",
    "wof:name":"On the Go",
    "wof:placetype":"venue"
},
  "geometry": {"coordinates":[-80.18409699999999,25.8582],"type":"Point"}
}