{
  "type": "Feature",
  "properties": {
    "iso:country":"US",
    "sg:address":"3818 Jog Rd",
    "sg:city":"Greenacres",
    "sg:classifiers":[
        {
            "category":"Retail",
            "subcategory":"Animal Services",
            "type":"Services"
        }
    ],
    "sg:phone":"+1 561 969 1282",
    "sg:postcode":"33467",
    "sg:province":"FL",
    "sg:tags":[
        "pet",
        "grooming",
        "washing"
    ],
    "wof:name":"Classy Pet Grooming Inc",
    "wof:placetype":"venue"
},
  "geometry": {"coordinates":[-80.14649,26.622258],"type":"Point"}
}