{
  "type": "Feature",
  "properties": {
    "iso:country":"US",
    "sg:address":"3735 Prospect Ave",
    "sg:city":"West Palm Beach",
    "sg:classifiers":[
        {
            "category":"Professional",
            "subcategory":"Advertising",
            "type":"Services"
        }
    ],
    "sg:phone":"+1 561 863 9093",
    "sg:postcode":"33404",
    "sg:province":"FL",
    "sg:tags":[
        "distribution"
    ],
    "wof:name":"Gemaire Distributors",
    "wof:placetype":"venue"
},
  "geometry": {"coordinates":[-80.09601499999999,26.790428],"type":"Point"}
}