{
  "type": "Feature",
  "properties": {
    "iso:country":"US",
    "sg:address":"132 Gomez Rd",
    "sg:city":"Hobe Sound",
    "sg:classifiers":[
        {
            "category":"Real Estate",
            "subcategory":"Real Estate Agent",
            "type":"Services"
        }
    ],
    "sg:phone":"+1 772 546 1914",
    "sg:postcode":"33455",
    "sg:province":"FL",
    "wof:name":"Gladys G Magnuson Estate",
    "wof:placetype":"venue"
},
  "geometry": {"coordinates":[-80.108486,27.047355],"type":"Point"}
}