{
  "type": "Feature",
  "properties": {
    "iso:country":"US",
    "sg:address":"17 N H St",
    "sg:city":"Lake Worth",
    "sg:classifiers":[
        {
            "category":"Health Services",
            "subcategory":"Chiropractor",
            "type":"Services"
        }
    ],
    "sg:phone":"+1 561 547 2210",
    "sg:postcode":"33460",
    "sg:province":"FL",
    "wof:name":"Jack Cacic & Co Inc",
    "wof:placetype":"venue"
},
  "geometry": {"coordinates":[-80.058414,26.616539],"type":"Point"}
}