{
  "type": "Feature",
  "properties": {
    "addr:full":"5181 Overseas Hwy Marathon FL 33050",
    "addr:housenumber":"5181",
    "addr:postcode":"33050",
    "addr:street":"Overseas Hwy",
    "iso:country":"US",
    "sg:address":"5181 Overseas Hwy",
    "sg:city":"Marathon",
    "sg:classifiers":[
        {
            "category":"Health Services",
            "subcategory":"Doctor",
            "type":"Services"
        }
    ],
    "sg:phone":"+1 305 289 4656",
    "sg:postcode":"33050",
    "sg:province":"FL",
    "sg:tags":[
        "physician",
        "surgeon"
    ],
    "wof:name":"Scott M Burns MD",
    "wof:placetype":"venue"
},
  "geometry": {"coordinates":[-81.07877499999999,24.715507],"type":"Point"}
}