{
  "type": "Feature",
  "properties": {
    "iso:country":"US",
    "sg:address":"2020 W Brandon Blvd",
    "sg:city":"Brandon",
    "sg:classifiers":[
        {
            "category":"Shopping",
            "subcategory":"Optical Goods",
            "type":"Retail Goods"
        }
    ],
    "sg:phone":"+1 813 643 7300",
    "sg:postcode":"33511",
    "sg:province":"FL",
    "wof:name":"Optics Soho",
    "wof:placetype":"venue"
},
  "geometry": {"coordinates":[-82.316318,27.937788],"type":"Point"}
}