{
  "type": "Feature",
  "properties": {
    "addr:full":"5433 Commercial Way Spring Hill FL 34606",
    "addr:housenumber":"5433",
    "addr:postcode":"34606",
    "addr:street":"Commercial Way",
    "iso:country":"US",
    "sg:address":"5433 Commercial Way",
    "sg:city":"Spring Hill",
    "sg:classifiers":[
        {
            "category":"Health Services",
            "subcategory":"Doctor",
            "type":"Services"
        }
    ],
    "sg:phone":"+1 352 596 3331",
    "sg:postcode":"34606",
    "sg:province":"FL",
    "sg:tags":[
        "physician",
        "medical",
        "surgeon"
    ],
    "wof:name":"Akel Riverside Walk-In Clinic",
    "wof:placetype":"venue"
},
  "geometry": {"coordinates":[-82.583232,28.5077],"type":"Point"}
}