{
  "type": "Feature",
  "properties": {
    "addr:full":"14660 Front Beach Rd Panama City Bch FL 32413",
    "addr:housenumber":"14660",
    "addr:postcode":"32413",
    "addr:street":"Front Beach Rd",
    "iso:country":"US",
    "sg:address":"14660 Front Beach Rd",
    "sg:city":"Panama City Bch",
    "sg:classifiers":[
        {
            "category":"Food & Beverages",
            "subcategory":"Dairy",
            "type":"Retail Goods"
        },
        {
            "category":"Restaurant",
            "type":"Food & Drink"
        }
    ],
    "sg:phone":"+1 850 230 6373",
    "sg:postcode":"32413",
    "sg:province":"FL",
    "sg:tags":[
        "product",
        "parlor",
        "ice",
        "cream"
    ],
    "wof:name":"Homemade Ice Cream Shoppe",
    "wof:placetype":"venue"
},
  "geometry": {"coordinates":[-85.864182,30.208981],"type":"Point"}
}