{
  "type": "Feature",
  "properties": {
    "iso:country":"US",
    "sg:address":"3399 NW 72nd Ave",
    "sg:city":"Miami",
    "sg:classifiers":[
        {
            "category":"Professional",
            "type":"Services"
        },
        {
            "category":"Health Services",
            "subcategory":"Doctor",
            "type":"Services"
        }
    ],
    "sg:phone":"+1 305 599 8550",
    "sg:postcode":"33122",
    "sg:province":"FL",
    "sg:tags":[
        "medicine",
        "occupational",
        "establishment"
    ],
    "wof:name":"Practice Partners Inc",
    "wof:placetype":"venue"
},
  "geometry": {"coordinates":[-80.31311100000001,25.804059],"type":"Point"}
}