{
  "type": "Feature",
  "properties": {
    "addr:full":"850 Maury Rd Unit 30 Orlando FL 32804",
    "addr:housenumber":"850;30",
    "addr:postcode":"32804",
    "addr:street":"Maury Rd Unit",
    "iso:country":"US",
    "sg:address":"850 Maury Rd Unit 30",
    "sg:city":"Orlando",
    "sg:classifiers":[
        {
            "category":"Home & Garden",
            "subcategory":"Mobile Homes",
            "type":"Retail Goods"
        }
    ],
    "sg:phone":"+1 800 433 3243",
    "sg:postcode":"32804",
    "sg:province":"FL",
    "sg:tags":[
        "park"
    ],
    "wof:name":"College Park Mobile Homes",
    "wof:placetype":"venue"
},
  "geometry": {"coordinates":[-81.39331799999999,28.583481],"type":"Point"}
}