{
  "type": "Feature",
  "properties": {
    "iso:country":"US",
    "sg:address":"1601 N Congress Ave",
    "sg:city":"Boynton Beach",
    "sg:classifiers":[
        {
            "category":"Organizations",
            "subcategory":"Religious Organization",
            "type":"Services"
        }
    ],
    "sg:phone":"+1 561 499 4893",
    "sg:postcode":"33426",
    "sg:province":"FL",
    "sg:tags":[
        "church"
    ],
    "wof:name":"Chosen People Ministries",
    "wof:placetype":"venue"
},
  "geometry": {"coordinates":[-80.090813,26.54117],"type":"Point"}
}