{
  "type": "Feature",
  "properties": {
    "addr:full":"1240 Airport Blvd Pensacola FL 32504",
    "addr:housenumber":"1240",
    "addr:postcode":"32504",
    "addr:street":"Airport Blvd",
    "iso:country":"US",
    "sg:address":"1240 Airport Blvd",
    "sg:city":"Pensacola",
    "sg:classifiers":[
        {
            "category":"Restaurant",
            "type":"Food & Drink"
        }
    ],
    "sg:menulink":"http://www.allmenus.com/fl/pensacola/75408-tgi-fridays/menu/",
    "sg:phone":"+1 850 477 5666",
    "sg:postcode":"32504",
    "sg:province":"FL",
    "sg:tags":[
        "american"
    ],
    "wof:name":"T.G.I. Friday's",
    "wof:placetype":"venue"
},
  "geometry": {"coordinates":[-87.216864,30.480107],"type":"Point"}
}