{
  "type": "Feature",
  "properties": {
    "iso:country":"US",
    "sg:address":"4310 Curry Ford Rd",
    "sg:city":"Orlando",
    "sg:classifiers":[
        {
            "category":"Retail",
            "subcategory":"Funeral Services",
            "type":"Services"
        }
    ],
    "sg:phone":"+1 407 898 7760",
    "sg:postcode":"32806",
    "sg:province":"FL",
    "sg:tags":[
        "crematory"
    ],
    "wof:name":"Caring Cremation Svc",
    "wof:placetype":"venue"
},
  "geometry": {"coordinates":[-81.331744,28.524177],"type":"Point"}
}