{
  "type": "Feature",
  "properties": {
    "addr:full":"7144 Boca Pointe Dr Boca Raton FL 33433",
    "addr:housenumber":"7144",
    "addr:postcode":"33433",
    "addr:street":"Boca Pointe Dr",
    "iso:country":"US",
    "sg:address":"7144 Boca Pointe Dr",
    "sg:city":"Boca Raton",
    "sg:classifiers":[
        {
            "category":"Restaurant",
            "type":"Food & Drink"
        },
        {
            "category":"Recreation",
            "type":"Entertainment"
        }
    ],
    "sg:phone":"+1 561 391 5100",
    "sg:postcode":"33433",
    "sg:province":"FL",
    "sg:tags":[
        "club",
        "membership",
        "sport",
        "eating",
        "caterer"
    ],
    "sg:website":"www.bocapointecc.com",
    "wof:name":"Boca Pointe Country Club Inc",
    "wof:placetype":"venue"
},
  "geometry": {"coordinates":[-80.156773,26.339829],"type":"Point"}
}