{
  "type": "Feature",
  "properties": {
    "addr:full":"484 Wilson St Crestview FL 32536",
    "addr:housenumber":"484",
    "addr:postcode":"32536",
    "addr:street":"Wilson St",
    "iso:country":"US",
    "sg:address":"484 Wilson St",
    "sg:city":"Crestview",
    "sg:classifiers":[
        {
            "category":"Insurance",
            "subcategory":"Insurance Agent",
            "type":"Services"
        }
    ],
    "sg:phone":"+1 850 682 2775",
    "sg:postcode":"32536",
    "sg:province":"FL",
    "sg:tags":[
        "life",
        "carrier"
    ],
    "wof:name":"Liberty National Lf Insur 81",
    "wof:placetype":"venue"
},
  "geometry": {"coordinates":[-86.567386,30.753886],"type":"Point"}
}