{
  "type": "Feature",
  "properties": {
    "addr:full":"16101 Alico Rd Fort Myers FL 33913",
    "addr:housenumber":"16101",
    "addr:postcode":"33913",
    "addr:street":"Alico Rd",
    "iso:country":"US",
    "sg:address":"16101 Alico Rd",
    "sg:city":"Fort Myers",
    "sg:classifiers":[
        {
            "category":"Professional",
            "subcategory":"Management & Consulting",
            "type":"Services"
        }
    ],
    "sg:phone":"+1 239 466 7430",
    "sg:postcode":"33913",
    "sg:province":"FL",
    "sg:tags":[
        "consultant"
    ],
    "wof:name":"Earth Tech Consulting Inc",
    "wof:placetype":"venue"
},
  "geometry": {"coordinates":[-81.707409,26.467523],"type":"Point"}
}