{
  "type": "Feature",
  "properties": {
    "iso:country":"US",
    "sg:address":"22423 Hancock Ave",
    "sg:city":"Port Charlotte",
    "sg:classifiers":[
        {
            "category":"Retail",
            "subcategory":"Auto Repair",
            "type":"Services"
        }
    ],
    "sg:phone":"+1 941 625 6833",
    "sg:postcode":"33980",
    "sg:province":"FL",
    "sg:tags":[
        "muffler",
        "exhaust",
        "system"
    ],
    "wof:name":"Charlotte Muffler",
    "wof:placetype":"venue"
},
  "geometry": {"coordinates":[-82.075379,26.967958],"type":"Point"}
}