{
  "type": "Feature",
  "properties": {
    "addr:full":"13864 S Garden Cove Cir Davie FL 33325",
    "addr:housenumber":"13864",
    "addr:postcode":"33325",
    "addr:street":"S Garden Cove Cir",
    "iso:country":"US",
    "sg:address":"13864 S Garden Cove Cir",
    "sg:city":"Davie",
    "sg:classifiers":[
        {
            "category":"Professional",
            "subcategory":"Computer Services",
            "type":"Services"
        }
    ],
    "sg:phone":"+1 954 472 6515",
    "sg:postcode":"33325",
    "sg:province":"FL",
    "sg:tags":[
        "repair"
    ],
    "sg:website":"www.poincianaparc.com",
    "wof:name":"Absolute Computer Consulting",
    "wof:placetype":"venue"
},
  "geometry": {"coordinates":[-80.33344200000001,26.115056],"type":"Point"}
}