{
  "type": "Feature",
  "properties": {
    "addr:full":"41660 Little Farm Rd Punta Gorda FL 33982",
    "addr:housenumber":"41660",
    "addr:postcode":"33982",
    "addr:street":"Little Farm Rd",
    "iso:country":"US",
    "sg:address":"41660 Little Farm Rd",
    "sg:city":"Punta Gorda",
    "sg:classifiers":[
        {
            "category":"Building & Trades",
            "subcategory":"Construction",
            "type":"Services"
        }
    ],
    "sg:phone":"+1 239 567 1089",
    "sg:postcode":"33982",
    "sg:province":"FL",
    "sg:tags":[
        "excavation",
        "contractor"
    ],
    "wof:name":"Cooke Land Clearing Inc",
    "wof:placetype":"venue"
},
  "geometry": {"coordinates":[-81.79583100000001,26.789901],"type":"Point"}
}