{
  "type": "Feature",
  "properties": {
    "iso:country":"US",
    "sg:address":"1237 W 68th St",
    "sg:city":"Hialeah",
    "sg:classifiers":[
        {
            "category":"Autos & Motor Vehicles",
            "subcategory":"Auto Supplies",
            "type":"Retail Goods"
        }
    ],
    "sg:phone":"+1 305 823 7533",
    "sg:postcode":"33014",
    "sg:province":"FL",
    "sg:tags":[
        "automobile",
        "part"
    ],
    "sg:website":"www.autozone.com",
    "wof:name":"Autozone",
    "wof:placetype":"venue"
},
  "geometry": {"coordinates":[-80.309212,25.884522],"type":"Point"}
}