{
  "type": "Feature",
  "properties": {
    "iso:country":"US",
    "sg:address":"3330 US Hwy 92",
    "sg:city":"Lakeland",
    "sg:classifiers":[
        {
            "category":"Shopping",
            "subcategory":"Used Merchandise",
            "type":"Retail Goods"
        }
    ],
    "sg:phone":"+1 863 666 9114",
    "sg:postcode":"33801",
    "sg:province":"FL",
    "wof:name":"Glt Inc",
    "wof:placetype":"venue"
},
  "geometry": {"coordinates":[-81.89202899999999,28.047983],"type":"Point"}
}