{
  "type": "Feature",
  "properties": {
    "addr:full":"8704 Doncaster Rd Orlando FL 32810",
    "addr:housenumber":"8704",
    "addr:postcode":"32810",
    "addr:street":"Doncaster Rd",
    "iso:country":"US",
    "sg:address":"8704 Doncaster Rd",
    "sg:city":"Orlando",
    "sg:classifiers":[
        {
            "category":"Building & Trades",
            "subcategory":"Construction",
            "type":"Services"
        }
    ],
    "sg:phone":"+1 407 298 2839",
    "sg:postcode":"32810",
    "sg:province":"FL",
    "sg:tags":[
        "tile",
        "dealer",
        "contractor"
    ],
    "wof:name":"Dan's Ceramic Tile",
    "wof:placetype":"venue"
},
  "geometry": {"coordinates":[-81.413003,28.636317],"type":"Point"}
}