{
  "type": "Feature",
  "properties": {
    "addr:full":"1985 NE 135th St North Miami FL 33181",
    "addr:housenumber":"1985",
    "addr:postcode":"33181",
    "addr:street":"Ne 135Th St",
    "iso:country":"US",
    "sg:address":"1985 NE 135th St",
    "sg:city":"North Miami",
    "sg:classifiers":[
        {
            "category":"Restaurant",
            "type":"Food & Drink"
        }
    ],
    "sg:phone":"+1 305 917 1717",
    "sg:postcode":"33181",
    "sg:province":"FL",
    "sg:tags":[
        "pizza"
    ],
    "wof:name":"Cosa Nostra Pizza",
    "wof:placetype":"venue"
},
  "geometry": {"coordinates":[-80.15710799999999,25.900252],"type":"Point"}
}