{
  "type": "Feature",
  "properties": {
    "iso:country":"US",
    "sg:address":"6845 Narcoossee Rd Ste 64",
    "sg:city":"Orlando",
    "sg:classifiers":[
        {
            "category":"Shopping",
            "subcategory":"Department Store",
            "type":"Retail Goods"
        },
        {
            "category":"Building & Trades",
            "subcategory":"Cleaning & Sanitation",
            "type":"Services"
        }
    ],
    "sg:phone":"+1 407 957 3582",
    "sg:postcode":"32822",
    "sg:province":"FL",
    "sg:tags":[
        "equipment",
        "cleaner",
        "supply",
        "house"
    ],
    "wof:name":"Econo Wipers Of Orlando",
    "wof:placetype":"venue"
},
  "geometry": {"coordinates":[-81.277086,28.467732],"type":"Point"}
}