{
  "type": "Feature",
  "properties": {
    "iso:country":"US",
    "sg:address":"16801 NE 14th Ave",
    "sg:city":"Miami",
    "sg:classifiers":[
        {
            "category":"Real Estate",
            "subcategory":"Real Estate Operator",
            "type":"Services"
        }
    ],
    "sg:phone":"+1 305 947 7467",
    "sg:postcode":"33162",
    "sg:province":"FL",
    "sg:tags":[
        "condominium"
    ],
    "wof:name":"Fountain View Condo",
    "wof:placetype":"venue"
},
  "geometry": {"coordinates":[-80.17216999999999,25.930994],"type":"Point"}
}