{
  "type": "Feature",
  "properties": {
    "iso:country":"US",
    "sg:address":"3535 W 74th Pl",
    "sg:city":"Hialeah",
    "sg:classifiers":[
        {
            "category":"Personal",
            "type":"Services"
        },
        {
            "category":"Professional",
            "subcategory":"Art Services",
            "type":"Services"
        }
    ],
    "sg:phone":"+1 305 557 4862",
    "sg:postcode":"33018",
    "sg:province":"FL",
    "sg:tags":[
        "photography",
        "videography",
        "wedding"
    ],
    "wof:name":"Richmond Photography",
    "wof:placetype":"venue"
},
  "geometry": {"coordinates":[-80.354696,25.890337],"type":"Point"}
}