{
  "type": "Feature",
  "properties": {
    "addr:full":"2400 SW 30th Ave Hallandale FL 33009",
    "addr:housenumber":"2400",
    "addr:postcode":"33009",
    "addr:street":"Sw 30Th Ave",
    "iso:country":"US",
    "sg:address":"2400 SW 30th Ave",
    "sg:city":"Hallandale",
    "sg:classifiers":[
        {
            "category":"Shopping",
            "subcategory":"Used Merchandise",
            "type":"Retail Goods"
        }
    ],
    "sg:phone":"+1 954 456 3377",
    "sg:postcode":"33009",
    "sg:province":"FL",
    "wof:name":"Jollys Antique Mall",
    "wof:placetype":"venue"
},
  "geometry": {"coordinates":[-80.166477,25.991545],"type":"Point"}
}