{
  "type": "Feature",
  "properties": {
    "iso:country":"US",
    "sg:address":"12026 NW Hwy 464B",
    "sg:city":"Ocala",
    "sg:classifiers":[
        {
            "category":"Banks & Credit Unions",
            "subcategory":"Financial Services",
            "type":"Services"
        }
    ],
    "sg:phone":"+1 434 977 1448",
    "sg:postcode":"34482",
    "sg:province":"FL",
    "sg:tags":[
        "co",
        "investment",
        "holding"
    ],
    "wof:name":"Stolz Family Ltd Partnership",
    "wof:placetype":"venue"
},
  "geometry": {"coordinates":[-82.318487,29.245827],"type":"Point"}
}