{
  "type": "Feature",
  "properties": {
    "iso:country":"US",
    "sg:address":"3594 SW 86th Ter",
    "sg:city":"Ocala",
    "sg:classifiers":[
        {
            "category":"Real Estate",
            "subcategory":"Real Estate Agent",
            "type":"Services"
        }
    ],
    "sg:phone":"+1 352 854 8117",
    "sg:postcode":"34481",
    "sg:province":"FL",
    "wof:name":"Colony Realty Inc",
    "wof:placetype":"venue"
},
  "geometry": {"coordinates":[-82.262427,29.152192],"type":"Point"}
}