{
  "type": "Feature",
  "properties": {
    "addr:full":"812 62nd Street Cir E Bradenton FL 34208",
    "addr:housenumber":"812",
    "addr:postcode":"34208",
    "addr:street":"62Nd Street Cir E",
    "iso:country":"US",
    "sg:address":"812 62nd Street Cir E",
    "sg:city":"Bradenton",
    "sg:classifiers":[
        {
            "category":"Restaurant",
            "type":"Food & Drink"
        }
    ],
    "sg:phone":"+1 941 747 7888",
    "sg:postcode":"34208",
    "sg:province":"FL",
    "sg:tags":[
        "pizza"
    ],
    "wof:name":"D Americo's Pizzeria",
    "wof:placetype":"venue"
},
  "geometry": {"coordinates":[-82.48229600000001,27.492527],"type":"Point"}
}