{
  "type": "Feature",
  "properties": {
    "iso:country":"US",
    "sg:address":"3253 N McMullen Booth Rd",
    "sg:city":"Clearwater",
    "sg:classifiers":[
        {
            "category":"Health Services",
            "subcategory":"Doctor",
            "type":"Services"
        }
    ],
    "sg:phone":"+1 727 725 6174",
    "sg:postcode":"33761",
    "sg:province":"FL",
    "sg:tags":[
        "physician",
        "medical",
        "surgeon"
    ],
    "wof:name":"Scranton Stephen L MD",
    "wof:placetype":"venue"
},
  "geometry": {"coordinates":[-82.709007,28.039787],"type":"Point"}
}