{
  "type": "Feature",
  "properties": {
    "addr:full":"4341 Thomas Dr Panama City Bch FL 32408",
    "addr:housenumber":"4341",
    "addr:postcode":"32408",
    "addr:street":"Thomas Dr",
    "iso:country":"US",
    "sg:address":"4341 Thomas Dr",
    "sg:city":"Panama City Bch",
    "sg:classifiers":[
        {
            "category":"Shopping",
            "subcategory":"Stationery & Office Supplies",
            "type":"Retail Goods"
        }
    ],
    "sg:phone":"+1 850 235 0180",
    "sg:postcode":"32408",
    "sg:province":"FL",
    "wof:name":"Warehouse Direct",
    "wof:placetype":"venue"
},
  "geometry": {"coordinates":[-85.750511,30.139409],"type":"Point"}
}