{
  "type": "Feature",
  "properties": {
    "iso:country":"US",
    "sg:address":"5411 Stirling Rd",
    "sg:city":"Davie",
    "sg:classifiers":[
        {
            "category":"Banks & Credit Unions",
            "subcategory":"Bank",
            "type":"Services"
        }
    ],
    "sg:phone":"+1 954 584 0519",
    "sg:postcode":"33314",
    "sg:province":"FL",
    "sg:tags":[
        "machine",
        "teller",
        "automated"
    ],
    "wof:name":"Commercial ATM Svc",
    "wof:placetype":"venue"
},
  "geometry": {"coordinates":[-80.21696799999999,26.046545],"type":"Point"}
}