{
  "type": "Feature",
  "properties": {
    "iso:country":"US",
    "sg:address":"377 China Hill Ct",
    "sg:city":"Apopka",
    "sg:classifiers":[
        {
            "category":"Shopping",
            "subcategory":"Computers & Home Electronics",
            "type":"Retail Goods"
        }
    ],
    "sg:phone":"+1 407 718 2340",
    "sg:postcode":"32712",
    "sg:province":"FL",
    "sg:tags":[
        "software"
    ],
    "wof:name":"Concise Software",
    "wof:placetype":"venue"
},
  "geometry": {"coordinates":[-81.50484400000001,28.698911],"type":"Point"}
}