{
  "type": "Feature",
  "properties": {
    "iso:country":"US",
    "sg:address":"3031 W Cypress St",
    "sg:city":"Tampa",
    "sg:classifiers":[
        {
            "category":"Health Services",
            "subcategory":"Health Practitioner",
            "type":"Services"
        }
    ],
    "sg:phone":"+1 813 870 6645",
    "sg:postcode":"33609",
    "sg:province":"FL",
    "sg:tags":[
        "therapist",
        "physical"
    ],
    "wof:name":"Synergy Medical & Rehab Thrpy",
    "wof:placetype":"venue"
},
  "geometry": {"coordinates":[-82.493222,27.952108],"type":"Point"}
}