{
  "type": "Feature",
  "properties": {
    "iso:country":"US",
    "sg:address":"3011 Beaver Pond Trl",
    "sg:city":"Valrico",
    "sg:classifiers":[
        {
            "category":"Professional",
            "subcategory":"Management & Consulting",
            "type":"Services"
        }
    ],
    "sg:phone":"+1 813 657 0757",
    "sg:postcode":"33596",
    "sg:province":"FL",
    "sg:tags":[
        "retail",
        "direct",
        "sales"
    ],
    "wof:name":"Ruby Pontatus",
    "wof:placetype":"venue"
},
  "geometry": {"coordinates":[-82.21176800000001,27.899777],"type":"Point"}
}