{
  "type": "Feature",
  "properties": {
    "addr:full":"221 S Grannis Ave Titusville FL 32796",
    "addr:housenumber":"221",
    "addr:postcode":"32796",
    "addr:street":"S Grannis Ave",
    "iso:country":"US",
    "sg:address":"221 S Grannis Ave",
    "sg:city":"Titusville",
    "sg:classifiers":[
        {
            "category":"Social Services",
            "type":"Services"
        },
        {
            "category":"Place Of Worship",
            "subcategory":"Church",
            "type":"Public Place"
        },
        {
            "category":"Place Of Worship",
            "type":"Public Place"
        },
        {
            "category":"Organizations",
            "subcategory":"Religious Organization",
            "type":"Services"
        }
    ],
    "sg:phone":"+1 321 269 3110",
    "sg:postcode":"32796",
    "sg:province":"FL",
    "sg:tags":[
        "churches-interdenominational",
        "churches-various",
        "denomination"
    ],
    "sg:website":"http://www.salvationarmysouth.org",
    "wof:name":"Salvation Army",
    "wof:placetype":"venue"
},
  "geometry": {"coordinates":[-80.817865,28.613389],"type":"Point"}
}