{
  "type": "Feature",
  "properties": {
    "iso:country":"US",
    "sg:address":"6911 NW 43rd St",
    "sg:city":"Miami",
    "sg:classifiers":[
        {
            "category":"Freight",
            "type":"Transportation"
        }
    ],
    "sg:phone":"+1 305 418 9139",
    "sg:postcode":"33166",
    "sg:province":"FL",
    "sg:tags":[
        "delivery"
    ],
    "wof:name":"C & F Delivery Svc",
    "wof:placetype":"venue"
},
  "geometry": {"coordinates":[-80.311228,25.813534],"type":"Point"}
}