{
  "type": "Feature",
  "properties": {
    "iso:country":"US",
    "sg:address":"2020 Elsa St",
    "sg:city":"Naples",
    "sg:classifiers":[
        {
            "category":"Wholesale",
            "subcategory":"Sporting Goods",
            "type":"Manufacturing & Wholesale Goods"
        }
    ],
    "sg:phone":"+1 239 598 4181",
    "sg:postcode":"34109",
    "sg:province":"FL",
    "sg:tags":[
        "equipment",
        "pool",
        "swimming"
    ],
    "wof:name":"SCP Distributors",
    "wof:placetype":"venue"
},
  "geometry": {"coordinates":[-81.781192,26.219242],"type":"Point"}
}