{
  "type": "Feature",
  "properties": {
    "iso:country":"US",
    "sg:address":"4545 Radio Rd",
    "sg:city":"Naples",
    "sg:classifiers":[
        {
            "category":"Freight",
            "type":"Transportation"
        }
    ],
    "sg:phone":"+1 239 262 7806",
    "sg:postcode":"34104",
    "sg:province":"FL",
    "sg:tags":[
        "recreational",
        "vehicle"
    ],
    "wof:name":"Duro Management Group",
    "wof:placetype":"venue"
},
  "geometry": {"coordinates":[-81.75645299999999,26.153331],"type":"Point"}
}