{
  "type": "Feature",
  "properties": {
    "iso:country":"US",
    "sg:address":"141 Candlewick Cir",
    "sg:city":"Panama City",
    "sg:classifiers":[
        {
            "category":"Professional",
            "subcategory":"Engineering",
            "type":"Services"
        }
    ],
    "sg:phone":"+1 850 271 8877",
    "sg:postcode":"32405",
    "sg:province":"FL",
    "sg:tags":[
        "engineer"
    ],
    "sg:website":"www.bishopgroup.net",
    "wof:name":"Bishop Group",
    "wof:placetype":"venue"
},
  "geometry": {"coordinates":[-85.669078,30.223437],"type":"Point"}
}