{
  "type": "Feature",
  "properties": {
    "addr:full":"4899 Sheridan St Hollywood FL 33021",
    "addr:housenumber":"4899",
    "addr:postcode":"33021",
    "addr:street":"Sheridan St",
    "iso:country":"US",
    "sg:address":"4899 Sheridan St",
    "sg:city":"Hollywood",
    "sg:classifiers":[
        {
            "category":"Restaurant",
            "type":"Food & Drink"
        }
    ],
    "sg:phone":"+1 954 965 1030",
    "sg:postcode":"33021",
    "sg:province":"FL",
    "sg:tags":[
        "house",
        "steak"
    ],
    "sg:website":"http://www.longhornsteakhouse.com",
    "wof:name":"Longhorn Steakhouse",
    "wof:placetype":"venue"
},
  "geometry": {"coordinates":[-80.193212,26.032715],"type":"Point"}
}