{
  "type": "Feature",
  "properties": {
    "addr:full":"1645 Alpha Dr Melbourne FL 32935",
    "addr:housenumber":"1645",
    "addr:postcode":"32935",
    "addr:street":"Alpha Dr",
    "iso:country":"US",
    "sg:address":"1645 Alpha Dr",
    "sg:city":"Melbourne",
    "sg:classifiers":[
        {
            "category":"Building & Trades",
            "subcategory":"Landscaping Services",
            "type":"Services"
        }
    ],
    "sg:phone":"+1 321 255 3566",
    "sg:postcode":"32935",
    "sg:province":"FL",
    "wof:name":"B & B Three Service",
    "wof:placetype":"venue"
},
  "geometry": {"coordinates":[-80.649176,28.135563],"type":"Point"}
}