{
  "type": "Feature",
  "properties": {
    "addr:full":"800 E Bay Dr Largo FL 33770",
    "addr:housenumber":"800",
    "addr:postcode":"33770",
    "addr:street":"E Bay Dr",
    "iso:country":"US",
    "sg:address":"800 E Bay Dr",
    "sg:city":"Largo",
    "sg:classifiers":[
        {
            "category":"Personal",
            "subcategory":"Beauty Salon",
            "type":"Services"
        }
    ],
    "sg:phone":"+1 727 584 8868",
    "sg:postcode":"33770",
    "sg:province":"FL",
    "sg:tags":[
        "hair",
        "stylist"
    ],
    "wof:name":"Hair Art Design Studio",
    "wof:placetype":"venue"
},
  "geometry": {"coordinates":[-82.77911400000001,27.916639],"type":"Point"}
}