{
  "type": "Feature",
  "properties": {
    "addr:full":"4325 Oak View Dr Sarasota FL 34232",
    "addr:housenumber":"4325",
    "addr:postcode":"34232",
    "addr:street":"Oak View Dr",
    "iso:country":"US",
    "sg:address":"4325 Oak View Dr",
    "sg:city":"Sarasota",
    "sg:classifiers":[
        {
            "category":"Banks & Credit Unions",
            "subcategory":"Bank",
            "type":"Services"
        }
    ],
    "sg:phone":"+1 941 379 2327",
    "sg:postcode":"34232",
    "sg:province":"FL",
    "sg:tags":[
        "personal",
        "institution"
    ],
    "wof:name":"Ejm Finacial Service",
    "wof:placetype":"venue"
},
  "geometry": {"coordinates":[-82.48045,27.318017],"type":"Point"}
}