{
  "type": "Feature",
  "properties": {
    "addr:full":"709 Bald Cypress Rd Weston FL 33327",
    "addr:housenumber":"709",
    "addr:postcode":"33327",
    "addr:street":"Bald Cypress Rd",
    "iso:country":"US",
    "sg:address":"709 Bald Cypress Rd",
    "sg:city":"Weston",
    "sg:classifiers":[
        {
            "category":"Ice Cream",
            "type":"Food & Drink"
        }
    ],
    "sg:phone":"+1 954 349 2565",
    "sg:postcode":"33327",
    "sg:province":"FL",
    "wof:name":"Magenta Soft Ice Cream",
    "wof:placetype":"venue"
},
  "geometry": {"coordinates":[-80.41851800000001,26.110451],"type":"Point"}
}