{
  "type": "Feature",
  "properties": {
    "addr:full":"2829 Badger Rd Lakeland FL 33811",
    "addr:housenumber":"2829",
    "addr:postcode":"33811",
    "addr:street":"Badger Rd",
    "iso:country":"US",
    "sg:address":"2829 Badger Rd",
    "sg:city":"Lakeland",
    "sg:classifiers":[
        {
            "category":"Building & Trades",
            "subcategory":"Construction",
            "type":"Services"
        }
    ],
    "sg:phone":"+1 863 709 8499",
    "sg:postcode":"33811",
    "sg:province":"FL",
    "sg:tags":[
        "general",
        "contractor"
    ],
    "wof:name":"Orbe Construction Inc",
    "wof:placetype":"venue"
},
  "geometry": {"coordinates":[-82.002225,27.991843],"type":"Point"}
}