{
  "type": "Feature",
  "properties": {
    "addr:full":"4025 NW Psge Tallahassee FL 32303",
    "addr:housenumber":"4025",
    "addr:postcode":"32303",
    "addr:street":"Nw Psge",
    "iso:country":"US",
    "sg:address":"4025 NW Psge",
    "sg:city":"Tallahassee",
    "sg:classifiers":[
        {
            "category":"Building & Trades",
            "subcategory":"Construction",
            "type":"Services"
        }
    ],
    "sg:phone":"+1 850 574 3843",
    "sg:postcode":"32303",
    "sg:province":"FL",
    "sg:tags":[
        "nonresidential",
        "dry wall",
        "contract",
        "contractor"
    ],
    "wof:name":"Nelson and Affiliates Inc",
    "wof:placetype":"venue"
},
  "geometry": {"coordinates":[-84.367361,30.469719],"type":"Point"}
}