{
  "type": "Feature",
  "properties": {
    "addr:full":"151 N 1st St Lake City FL 32055",
    "addr:housenumber":"151",
    "addr:postcode":"32055",
    "addr:street":"N 1St St",
    "iso:country":"US",
    "sg:address":"151 N 1st St",
    "sg:city":"Lake City",
    "sg:classifiers":[
        {
            "category":"Government",
            "subcategory":"Fire Station",
            "type":"Public Place"
        }
    ],
    "sg:phone":"+1 386 758 5442",
    "sg:postcode":"32055",
    "sg:province":"FL",
    "sg:tags":[
        "department"
    ],
    "wof:name":"Lake City/Columbia Fire Dept",
    "wof:placetype":"venue"
},
  "geometry": {"coordinates":[-82.639425,30.190322],"type":"Point"}
}