{
  "type": "Feature",
  "properties": {
    "iso:country":"US",
    "sg:address":"4651 Gulf of Mexico Dr",
    "sg:city":"Longboat Key",
    "sg:classifiers":[
        {
            "category":"Travel",
            "subcategory":"Hotels & Motels",
            "type":"Entertainment"
        }
    ],
    "sg:phone":"+1 941 383 5588",
    "sg:postcode":"34228",
    "sg:province":"FL",
    "sg:tags":[
        "resort",
        "operation"
    ],
    "wof:name":"Sun n Sea Cottages & Apts",
    "wof:placetype":"venue"
},
  "geometry": {"coordinates":[-82.647294,27.398475],"type":"Point"}
}