{
  "type": "Feature",
  "properties": {
    "addr:full":"1985 Howell Branch Rd Maitland FL 32751",
    "addr:housenumber":"1985",
    "addr:postcode":"32751",
    "addr:street":"Howell Branch Rd",
    "iso:country":"US",
    "sg:address":"1985 Howell Branch Rd",
    "sg:city":"Maitland",
    "sg:classifiers":[
        {
            "category":"Sports & Exercise",
            "subcategory":"Gym",
            "type":"Entertainment"
        }
    ],
    "sg:phone":"+1 321 332 2540",
    "sg:postcode":"32751",
    "sg:province":"FL",
    "sg:tags":[
        "pilate"
    ],
    "wof:name":"Matthew Comer Pilates",
    "wof:placetype":"venue"
},
  "geometry": {"coordinates":[-81.32490900000001,28.625454],"type":"Point"}
}