{
  "type": "Feature",
  "properties": {
    "iso:country":"US",
    "sg:address":"4484 N John Young Pkwy",
    "sg:city":"Orlando",
    "sg:classifiers":[
        {
            "category":"Place Of Worship",
            "subcategory":"Church",
            "type":"Public Place"
        }
    ],
    "sg:phone":"+1 407 246 0001",
    "sg:postcode":"32804",
    "sg:province":"FL",
    "sg:website":"www.churchintheson.com",
    "wof:name":"Church In the Son",
    "wof:placetype":"venue"
},
  "geometry": {"coordinates":[-81.419197,28.5938],"type":"Point"}
}