{
  "type": "Feature",
  "properties": {
    "iso:country":"US",
    "sg:address":"1862 94th Dr",
    "sg:city":"Vero Beach",
    "sg:classifiers":[
        {
            "category":"Shopping",
            "subcategory":"Shoes",
            "type":"Retail Goods"
        }
    ],
    "sg:phone":"+1 772 978 0663",
    "sg:postcode":"32966",
    "sg:province":"FL",
    "wof:name":"Dexter Shoe",
    "wof:placetype":"venue"
},
  "geometry": {"coordinates":[-80.524512,27.635386],"type":"Point"}
}