{
  "type": "Feature",
  "properties": {
    "iso:country":"US",
    "sg:address":"303 301 Blvd W # 903",
    "sg:city":"Bradenton",
    "sg:classifiers":[
        {
            "category":"Food & Beverages",
            "subcategory":"Groceries & Convenience Stores",
            "type":"Retail Goods"
        }
    ],
    "sg:phone":"+1 941 748 5723",
    "sg:postcode":"34205",
    "sg:province":"FL",
    "sg:tags":[
        "pretzel"
    ],
    "sg:website":"http://www.auntieannes.com",
    "wof:name":"Auntie Annes Soft Pretzels",
    "wof:placetype":"venue"
},
  "geometry": {"coordinates":[-82.565138,27.467169],"type":"Point"}
}