{
  "type": "Feature",
  "properties": {
    "iso:country":"US",
    "sg:address":"2060 SW 71st Ter",
    "sg:city":"Davie",
    "sg:classifiers":[
        {
            "category":"Autos & Motor Vehicles",
            "subcategory":"Auto Supplies",
            "type":"Retail Goods"
        }
    ],
    "sg:phone":"+1 954 382 3353",
    "sg:postcode":"33317",
    "sg:province":"FL",
    "sg:tags":[
        "automobile",
        "stereo",
        "radio"
    ],
    "wof:name":"Streetnstyle Auto Sound",
    "wof:placetype":"venue"
},
  "geometry": {"coordinates":[-80.24149199999999,26.09472],"type":"Point"}
}