{
  "type": "Feature",
  "properties": {
    "iso:country":"US",
    "sg:address":"174 Azalea Dr",
    "sg:city":"Destin",
    "sg:classifiers":[
        {
            "category":"Home & Garden",
            "subcategory":"Home Furnishings",
            "type":"Retail Goods"
        }
    ],
    "sg:phone":"+1 850 654 3060",
    "sg:postcode":"32541",
    "sg:province":"FL",
    "sg:tags":[
        "upholstery",
        "fabric",
        "drapery",
        "wallpaper"
    ],
    "wof:name":"Cotton Capers of Florida",
    "wof:placetype":"venue"
},
  "geometry": {"coordinates":[-86.499218,30.39635],"type":"Point"}
}