{
  "type": "Feature",
  "properties": {
    "iso:country":"US",
    "sg:address":"1531 S Dale Mabry Hwy",
    "sg:city":"Tampa",
    "sg:classifiers":[
        {
            "category":"Shopping",
            "subcategory":"Gifts & Souvenirs",
            "type":"Retail Goods"
        }
    ],
    "sg:phone":"+1 813 251 0262",
    "sg:postcode":"33629",
    "sg:province":"FL",
    "sg:tags":[
        "food",
        "oriental"
    ],
    "wof:name":"Oriental Food & Gift",
    "wof:placetype":"venue"
},
  "geometry": {"coordinates":[-82.50592899999999,27.928976],"type":"Point"}
}