{
  "type": "Feature",
  "properties": {
    "iso:country":"US",
    "sg:address":"1457 Navarre Beach Blvd",
    "sg:city":"Navarre",
    "sg:classifiers":[
        {
            "category":"Food & Beverages",
            "subcategory":"Groceries & Convenience Stores",
            "type":"Retail Goods"
        }
    ],
    "sg:phone":"+1 850 939 3066",
    "sg:postcode":"32566",
    "sg:province":"FL",
    "wof:name":"Tom Thumb Food Store",
    "wof:placetype":"venue"
},
  "geometry": {"coordinates":[-86.837716,30.408362],"type":"Point"}
}