{
  "type": "Feature",
  "properties": {
    "addr:full":"7354 Mulberry Ln Navarre FL 32566",
    "addr:housenumber":"7354",
    "addr:postcode":"32566",
    "addr:street":"Mulberry Ln",
    "iso:country":"US",
    "sg:address":"7354 Mulberry Ln",
    "sg:city":"Navarre",
    "sg:classifiers":[
        {
            "category":"Banks & Credit Unions",
            "subcategory":"Investment Brokerage",
            "type":"Services"
        }
    ],
    "sg:phone":"+1 850 936 0033",
    "sg:postcode":"32566",
    "sg:province":"FL",
    "sg:tags":[
        "advisory",
        "financial"
    ],
    "wof:name":"Jackson Money Management Inc",
    "wof:placetype":"venue"
},
  "geometry": {"coordinates":[-86.915589,30.39774],"type":"Point"}
}