{
  "type": "Feature",
  "properties": {
    "iso:country":"US",
    "sg:address":"2209 Chippewa Trl",
    "sg:city":"Maitland",
    "sg:classifiers":[
        {
            "category":"Wholesale",
            "subcategory":"Non-durable Goods",
            "type":"Manufacturing & Wholesale Goods"
        }
    ],
    "sg:phone":"+1 407 740 0008",
    "sg:postcode":"32751",
    "sg:province":"FL",
    "sg:tags":[
        "hanger",
        "clothes"
    ],
    "wof:name":"NC Supply",
    "wof:placetype":"venue"
},
  "geometry": {"coordinates":[-81.33390799999999,28.636008],"type":"Point"}
}