{
  "type": "Feature",
  "properties": {
    "addr:full":"751 Wren Ave Miami Springs FL 33166",
    "addr:housenumber":"751",
    "addr:postcode":"33166",
    "addr:street":"Wren Ave",
    "iso:country":"US",
    "sg:address":"751 Wren Ave",
    "sg:city":"Miami Springs",
    "sg:classifiers":[
        {
            "category":"Building & Trades",
            "subcategory":"Construction",
            "type":"Services"
        }
    ],
    "sg:phone":"+1 305 494 4863",
    "sg:postcode":"33166",
    "sg:province":"FL",
    "sg:tags":[
        "resurfacing",
        "laying",
        "refinishing",
        "floor"
    ],
    "wof:name":"Elegant Floors Inc",
    "wof:placetype":"venue"
},
  "geometry": {"coordinates":[-80.29474,25.825387],"type":"Point"}
}