{
  "type": "Feature",
  "properties": {
    "addr:full":"1211 E Cumberland Ave Tampa FL 33602",
    "addr:housenumber":"1211",
    "addr:postcode":"33602",
    "addr:street":"E Cumberland Ave",
    "iso:country":"US",
    "sg:address":"1211 E Cumberland Ave",
    "sg:city":"Tampa",
    "sg:classifiers":[
        {
            "category":"Manufacturing",
            "subcategory":"Metals",
            "type":"Manufacturing & Wholesale Goods"
        }
    ],
    "sg:phone":"+1 813 221 9801",
    "sg:postcode":"33602",
    "sg:province":"FL",
    "sg:tags":[
        "steel",
        "distributor",
        "mill",
        "warehouse"
    ],
    "wof:name":"The Towers Of Channelside Condominium Association",
    "wof:placetype":"venue"
},
  "geometry": {"coordinates":[-82.447664,27.94502],"type":"Point"}
}