{
  "type": "Feature",
  "properties": {
    "iso:country":"US",
    "sg:address":"29 S Orange Ave",
    "sg:city":"Orlando",
    "sg:classifiers":[
        {
            "category":"Coffee & Tea",
            "type":"Food & Drink"
        },
        {
            "category":"Restaurant",
            "type":"Food & Drink"
        }
    ],
    "sg:phone":"+1 407 423 4300",
    "sg:postcode":"32801",
    "sg:province":"FL",
    "sg:tags":[
        "shop",
        "espresso"
    ],
    "wof:name":"Roho Art & Coffee",
    "wof:placetype":"venue"
},
  "geometry": {"coordinates":[-81.37904399999999,28.542098],"type":"Point"}
}