{
  "type": "Feature",
  "properties": {
    "addr:full":"7310 NW 94th Way Fort Lauderdale FL 33321",
    "addr:housenumber":"7310",
    "addr:postcode":"33321",
    "addr:street":"Nw 94Th Way",
    "iso:country":"US",
    "sg:address":"7310 NW 94th Way",
    "sg:city":"Fort Lauderdale",
    "sg:classifiers":[
        {
            "category":"Retail",
            "subcategory":"Auto Repair",
            "type":"Services"
        }
    ],
    "sg:phone":"+1 954 720 8363",
    "sg:postcode":"33321",
    "sg:province":"FL",
    "sg:tags":[
        "automotive"
    ],
    "wof:name":"Auto Rescue Detailing",
    "wof:placetype":"venue"
},
  "geometry": {"coordinates":[-80.277477,26.213649],"type":"Point"}
}