{
  "type": "Feature",
  "properties": {
    "addr:full":"5532 41st St E Bradenton FL 34203",
    "addr:housenumber":"5532",
    "addr:postcode":"34203",
    "addr:street":"41St St",
    "iso:country":"US",
    "sg:address":"5532 41st St E",
    "sg:city":"Bradenton",
    "sg:classifiers":[
        {
            "category":"Building & Trades",
            "subcategory":"Construction",
            "type":"Services"
        }
    ],
    "sg:phone":"+1 941 755 2564",
    "sg:postcode":"34203",
    "sg:province":"FL",
    "sg:tags":[
        "hanging",
        "contractor"
    ],
    "wof:name":"George R Gillis",
    "wof:placetype":"venue"
},
  "geometry": {"coordinates":[-82.51078800000001,27.441021],"type":"Point"}
}