{
  "type": "Feature",
  "properties": {
    "iso:country":"US",
    "sg:address":"1433 Court St",
    "sg:city":"Clearwater",
    "sg:classifiers":[
        {
            "category":"Health Services",
            "subcategory":"Doctor",
            "type":"Services"
        }
    ],
    "sg:phone":"+1 727 442 6098",
    "sg:postcode":"33756",
    "sg:province":"FL",
    "wof:name":"Mc Dowell Orthodontics",
    "wof:placetype":"venue"
},
  "geometry": {"coordinates":[-82.77901900000001,27.960701],"type":"Point"}
}