{
  "type": "Feature",
  "properties": {
    "iso:country":"US",
    "sg:address":"3200 Maple St NE",
    "sg:city":"Saint Petersburg",
    "sg:classifiers":[
        {
            "category":"Wholesale",
            "subcategory":"Stationery",
            "type":"Manufacturing & Wholesale Goods"
        }
    ],
    "sg:phone":"+1 727 896 8030",
    "sg:postcode":"33704",
    "sg:province":"FL",
    "sg:tags":[
        "supply"
    ],
    "wof:name":"Coastal Data Systems Inc",
    "wof:placetype":"venue"
},
  "geometry": {"coordinates":[-82.624697,27.801758],"type":"Point"}
}