{
  "type": "Feature",
  "properties": {
    "iso:country":"US",
    "sg:address":"1382 Howland Blvd Ste 110",
    "sg:city":"Deltona",
    "sg:classifiers":[
        {
            "category":"Restaurant",
            "type":"Food & Drink"
        }
    ],
    "sg:phone":"+1 386 860 0035",
    "sg:postcode":"32738",
    "sg:province":"FL",
    "wof:name":"Chop Shop Of Volusia Inc",
    "wof:placetype":"venue"
},
  "geometry": {"coordinates":[-81.171288,28.902399],"type":"Point"}
}