{
  "type": "Feature",
  "properties": {
    "iso:country":"US",
    "sg:address":"11770 SW 173rd St",
    "sg:city":"Miami",
    "sg:classifiers":[
        {
            "category":"Health Services",
            "subcategory":"Health Practitioner",
            "type":"Services"
        }
    ],
    "sg:phone":"+1 305 389 0032",
    "sg:postcode":"33177",
    "sg:province":"FL",
    "sg:tags":[
        "hypnotherapy",
        "hypnotist"
    ],
    "wof:name":"Miami Hypnotic Center",
    "wof:placetype":"venue"
},
  "geometry": {"coordinates":[-80.38352999999999,25.607757],"type":"Point"}
}