{
  "type": "Feature",
  "properties": {
    "iso:country":"US",
    "sg:address":"7210 SW 57th Ave Ste 204",
    "sg:city":"Miami",
    "sg:classifiers":[
        {
            "category":"Health Services",
            "subcategory":"Dentist",
            "type":"Services"
        }
    ],
    "sg:phone":"+1 305 667 5738",
    "sg:postcode":"33143",
    "sg:province":"FL",
    "sg:tags":[
        "orthodontist"
    ],
    "wof:name":"Alquizar Orthodontics",
    "wof:placetype":"venue"
},
  "geometry": {"coordinates":[-80.28540599999999,25.704342],"type":"Point"}
}