{
  "type": "Feature",
  "properties": {
    "iso:country":"US",
    "sg:address":"1527 NW 29th Pl",
    "sg:city":"Cape Coral",
    "sg:classifiers":[
        {
            "category":"Banks & Credit Unions",
            "subcategory":"Investment Brokerage",
            "type":"Services"
        }
    ],
    "sg:phone":"+1 239 283 8299",
    "sg:postcode":"33993",
    "sg:province":"FL",
    "sg:tags":[
        "advisory",
        "financial"
    ],
    "wof:name":"Talbot Financial Svc",
    "wof:placetype":"venue"
},
  "geometry": {"coordinates":[-82.03403400000001,26.680279],"type":"Point"}
}