{
  "type": "Feature",
  "properties": {
    "addr:full":"3915 8th Ave W Bradenton FL 34205",
    "addr:housenumber":"3915",
    "addr:postcode":"34205",
    "addr:street":"8Th Ave W",
    "iso:country":"US",
    "sg:address":"3915 8th Ave W",
    "sg:city":"Bradenton",
    "sg:classifiers":[
        {
            "category":"Professional",
            "subcategory":"Research",
            "type":"Services"
        }
    ],
    "sg:phone":"+1 941 708 0005",
    "sg:postcode":"34205",
    "sg:province":"FL",
    "wof:name":"Bradenton Research Ctr",
    "wof:placetype":"venue"
},
  "geometry": {"coordinates":[-82.600815,27.493118],"type":"Point"}
}