{
  "type": "Feature",
  "properties": {
    "addr:full":"5130 SW 208th Ln Fort Lauderdale FL 33332",
    "addr:housenumber":"5130",
    "addr:postcode":"33332",
    "addr:street":"Sw 208Th Ln",
    "iso:country":"US",
    "sg:address":"5130 SW 208th Ln",
    "sg:city":"Fort Lauderdale",
    "sg:classifiers":[
        {
            "category":"Wholesale",
            "subcategory":"Plants",
            "type":"Manufacturing & Wholesale Goods"
        },
        {
            "category":"Home & Garden",
            "subcategory":"Garden Supply",
            "type":"Retail Goods"
        }
    ],
    "sg:phone":"+1 954 434 6458",
    "sg:postcode":"33332",
    "sg:province":"FL",
    "sg:tags":[
        "nurseryman"
    ],
    "wof:name":"Sabreena's Garden Nursery",
    "wof:placetype":"venue"
},
  "geometry": {"coordinates":[-80.426782,26.057591],"type":"Point"}
}