{
  "type": "Feature",
  "properties": {
    "addr:full":"8085 Cook Dr Fort Myers FL 33917",
    "addr:housenumber":"8085",
    "addr:postcode":"33917",
    "addr:street":"Cook Dr",
    "iso:country":"US",
    "sg:address":"8085 Cook Dr",
    "sg:city":"Fort Myers",
    "sg:classifiers":[
        {
            "category":"Building & Trades",
            "subcategory":"Construction",
            "type":"Services"
        }
    ],
    "sg:phone":"+1 239 994 5563",
    "sg:postcode":"33917",
    "sg:province":"FL",
    "sg:tags":[
        "concrete",
        "contractor"
    ],
    "wof:name":"Daniel Marsiglio Concrete Pump",
    "wof:placetype":"venue"
},
  "geometry": {"coordinates":[-81.86058800000001,26.715587],"type":"Point"}
}