{
  "type": "Feature",
  "properties": {
    "addr:full":"3401 W Columbus Dr Tampa FL 33607",
    "addr:housenumber":"3401",
    "addr:postcode":"33607",
    "addr:street":"W Columbus Dr",
    "iso:country":"US",
    "sg:address":"3401 W Columbus Dr",
    "sg:city":"Tampa",
    "sg:classifiers":[
        {
            "category":"Freight",
            "type":"Transportation"
        }
    ],
    "sg:phone":"+1 813 879 1168",
    "sg:postcode":"33607",
    "sg:province":"FL",
    "sg:tags":[
        "courier"
    ],
    "wof:name":"Paradise International Inc",
    "wof:placetype":"venue"
},
  "geometry": {"coordinates":[-82.501508,27.966756],"type":"Point"}
}