{
  "type": "Feature",
  "properties": {
    "iso:country":"US",
    "sg:address":"1159 Fundy Rd",
    "sg:city":"Venice",
    "sg:classifiers":[
        {
            "category":"Deli",
            "type":"Food & Drink"
        },
        {
            "category":"Restaurant",
            "type":"Food & Drink"
        }
    ],
    "sg:phone":"+1 941 349 4696",
    "sg:postcode":"34293",
    "sg:province":"FL",
    "sg:tags":[
        "delicatessen"
    ],
    "wof:name":"Siesta Key Deli",
    "wof:placetype":"venue"
},
  "geometry": {"coordinates":[-82.424331,27.049427],"type":"Point"}
}