{
  "type": "Feature",
  "properties": {
    "addr:full":"1135 Pierce St Clearwater FL 33756",
    "addr:housenumber":"1135",
    "addr:postcode":"33756",
    "addr:street":"Pierce St",
    "iso:country":"US",
    "sg:address":"1135 Pierce St",
    "sg:city":"Clearwater",
    "sg:classifiers":[
        {
            "category":"Building & Trades",
            "subcategory":"Electrical",
            "type":"Services"
        }
    ],
    "sg:phone":"+1 727 787 0091",
    "sg:postcode":"33756",
    "sg:province":"FL",
    "sg:tags":[
        "industrial",
        "electrician",
        "electric",
        "contractors-commercial"
    ],
    "wof:name":"Brico Electric Inc",
    "wof:placetype":"venue"
},
  "geometry": {"coordinates":[-82.790679,27.964047],"type":"Point"}
}