{
  "type": "Feature",
  "properties": {
    "iso:country":"US",
    "sg:address":"614 E 49th St",
    "sg:city":"Hialeah",
    "sg:classifiers":[
        {
            "category":"Health Services",
            "subcategory":"Doctor",
            "type":"Services"
        }
    ],
    "sg:phone":"+1 305 685 7494",
    "sg:postcode":"33013",
    "sg:province":"FL",
    "sg:tags":[
        "surgeon",
        "oral"
    ],
    "wof:name":"Miro Claudio L DDS",
    "wof:placetype":"venue"
},
  "geometry": {"coordinates":[-80.270302,25.8671],"type":"Point"}
}