{
  "type": "Feature",
  "properties": {
    "iso:country":"US",
    "sg:address":"17373 Allentown Rd",
    "sg:city":"Fort Myers",
    "sg:classifiers":[
        {
            "category":"Building & Trades",
            "subcategory":"Landscaping Services",
            "type":"Services"
        }
    ],
    "sg:phone":"+1 239 267 7694",
    "sg:postcode":"33967",
    "sg:province":"FL",
    "wof:name":"Krt Lawn & Landscape Maint",
    "wof:placetype":"venue"
},
  "geometry": {"coordinates":[-81.81307,26.483484],"type":"Point"}
}