{
  "type": "Feature",
  "properties": {
    "iso:country":"US",
    "sg:address":"15600 NW 67th Ave Ste 301",
    "sg:city":"Hialeah",
    "sg:classifiers":[
        {
            "category":"Health Services",
            "subcategory":"Doctor",
            "type":"Services"
        }
    ],
    "sg:phone":"+1 305 821 8611",
    "sg:postcode":"33014",
    "sg:province":"FL",
    "wof:name":"Tellechea Carlos MD",
    "wof:placetype":"venue"
},
  "geometry": {"coordinates":[-80.30909699999999,25.914801],"type":"Point"}
}