{
  "type": "Feature",
  "properties": {
    "addr:full":"1668 Collins Ave Miami Beach FL 33139",
    "addr:housenumber":"1668",
    "addr:postcode":"33139",
    "addr:street":"Collins Ave",
    "iso:country":"US",
    "sg:address":"1668 Collins Ave",
    "sg:city":"Miami Beach",
    "sg:classifiers":[
        {
            "category":"Shopping",
            "subcategory":"Shoes",
            "type":"Retail Goods"
        }
    ],
    "sg:phone":"+1 305 672 9577",
    "sg:postcode":"33139",
    "sg:province":"FL",
    "sg:tags":[
        "footwear"
    ],
    "wof:name":"Sport Time 2",
    "wof:placetype":"venue"
},
  "geometry": {"coordinates":[-80.12988300000001,25.791704],"type":"Point"}
}