{
  "type": "Feature",
  "properties": {
    "iso:country":"US",
    "sg:address":"601 Courtland Blvd",
    "sg:city":"Deltona",
    "sg:classifiers":[
        {
            "category":"Banks & Credit Unions",
            "subcategory":"Bank",
            "type":"Services"
        }
    ],
    "sg:phone":"+1 407 324 3147",
    "sg:postcode":"32738",
    "sg:province":"FL",
    "sg:website":"www.suntrust.com",
    "wof:name":"Suntrust",
    "wof:placetype":"venue"
},
  "geometry": {"coordinates":[-81.17878399999999,28.88047],"type":"Point"}
}