{
  "type": "Feature",
  "properties": {
    "iso:country":"US",
    "sg:address":"505 Canal St",
    "sg:city":"New Smyrna Beach",
    "sg:classifiers":[
        {
            "category":"Health Services",
            "subcategory":"Clinic",
            "type":"Services"
        }
    ],
    "sg:phone":"+1 386 423 7504",
    "sg:postcode":"32168",
    "sg:province":"FL",
    "sg:tags":[
        "home"
    ],
    "sg:website":"www.gentiva.com",
    "wof:name":"Gentiva Health Svc",
    "wof:placetype":"venue"
},
  "geometry": {"coordinates":[-80.926095,29.023788],"type":"Point"}
}