{
  "type": "Feature",
  "properties": {
    "iso:country":"US",
    "sg:address":"301 S Ridgewood Ave",
    "sg:city":"Daytona Beach",
    "sg:classifiers":[
        {
            "category":"Government",
            "subcategory":"Office",
            "type":"Public Place"
        }
    ],
    "sg:phone":"+1 386 671 8140",
    "sg:postcode":"32114",
    "sg:province":"FL",
    "sg:tags":[
        "village"
    ],
    "wof:name":"Daytona Beach Permits & Lcnsng",
    "wof:placetype":"venue"
},
  "geometry": {"coordinates":[-81.01976999999999,29.205129],"type":"Point"}
}