{
  "type": "Feature",
  "properties": {
    "addr:full":"8720 Somers Rd S Jacksonville FL 32226",
    "addr:housenumber":"8720",
    "addr:postcode":"32226",
    "addr:street":"Somers Rd",
    "iso:country":"US",
    "sg:address":"8720 Somers Rd S",
    "sg:city":"Jacksonville",
    "sg:classifiers":[
        {
            "category":"Freight",
            "type":"Transportation"
        }
    ],
    "sg:phone":"+1 904 757 0481",
    "sg:postcode":"32226",
    "sg:province":"FL",
    "sg:tags":[
        "trucking"
    ],
    "wof:name":"All Coast Intermodal Svc Inc",
    "wof:placetype":"venue"
},
  "geometry": {"coordinates":[-81.62684299999999,30.402258],"type":"Point"}
}