{
  "type": "Feature",
  "properties": {
    "addr:full":"2721 Michigan St Melbourne FL 32904",
    "addr:housenumber":"2721",
    "addr:postcode":"32904",
    "addr:street":"Michigan St",
    "iso:country":"US",
    "sg:address":"2721 Michigan St",
    "sg:city":"Melbourne",
    "sg:classifiers":[
        {
            "category":"Building & Trades",
            "subcategory":"Construction",
            "type":"Services"
        }
    ],
    "sg:phone":"+1 321 723 3420",
    "sg:postcode":"32904",
    "sg:province":"FL",
    "sg:tags":[
        "carpenter"
    ],
    "wof:name":"A Step Up",
    "wof:placetype":"venue"
},
  "geometry": {"coordinates":[-80.697446,28.061041],"type":"Point"}
}