{
  "type": "Feature",
  "properties": {
    "addr:full":"791 N Harbor City Blvd Melbourne FL 32935",
    "addr:housenumber":"791",
    "addr:postcode":"32935",
    "addr:street":"N Harbor City Blvd",
    "iso:country":"US",
    "sg:address":"791 N Harbor City Blvd",
    "sg:city":"Melbourne",
    "sg:phone":"+1 321 757 9993",
    "sg:postcode":"32935",
    "sg:province":"FL",
    "wof:name":"Ink Doktor Tattoo Studio",
    "wof:placetype":"venue"
},
  "geometry": {"coordinates":[-80.63054700000001,28.119749],"type":"Point"}
}