{
  "type": "Feature",
  "properties": {
    "iso:country":"US",
    "sg:address":"444 Huey Ave",
    "sg:city":"Tarpon Springs",
    "sg:classifiers":[
        {
            "category":"Government",
            "subcategory":"Fire Station",
            "type":"Public Place"
        }
    ],
    "sg:phone":"+1 727 938 3737",
    "sg:postcode":"34689",
    "sg:province":"FL",
    "sg:tags":[
        "protection"
    ],
    "wof:name":"Tarpon Springs Fire Department",
    "wof:placetype":"venue"
},
  "geometry": {"coordinates":[-82.74437,28.141746],"type":"Point"}
}