{
  "type": "Feature",
  "properties": {
    "iso:country":"US",
    "sg:address":"15366 SW 16th Ter",
    "sg:city":"Miami",
    "sg:classifiers":[
        {
            "category":"Home & Garden",
            "subcategory":"Furniture",
            "type":"Retail Goods"
        },
        {
            "category":"Wholesale",
            "subcategory":"Home Furnishings",
            "type":"Manufacturing & Wholesale Goods"
        }
    ],
    "sg:phone":"+1 305 519 3529",
    "sg:postcode":"33185",
    "sg:province":"FL",
    "sg:tags":[
        "equipment-wholesale",
        "kitchen",
        "equipment-household",
        "manufacturer",
        "cabinet"
    ],
    "wof:name":"Total Cabinets & Doors",
    "wof:placetype":"venue"
},
  "geometry": {"coordinates":[-80.443963,25.75145],"type":"Point"}
}