{
  "type": "Feature",
  "properties": {
    "addr:full":"1573 W Fairbanks Ave Ste 200 Winter Park FL 32789",
    "addr:housenumber":"1573",
    "addr:postcode":"32789",
    "addr:street":"W Fairbanks Ave Ste 200",
    "iso:country":"US",
    "sg:address":"1573 W Fairbanks Ave Ste 200",
    "sg:city":"Winter Park",
    "sg:classifiers":[
        {
            "category":"Health Services",
            "subcategory":"Chiropractor",
            "type":"Services"
        }
    ],
    "sg:phone":"+1 407 637 8300",
    "sg:postcode":"32789",
    "sg:province":"FL",
    "sg:website":"yeomanschiro.com",
    "wof:name":"Yeomans Chiropractic",
    "wof:placetype":"venue"
},
  "geometry": {"coordinates":[-81.37042700000001,28.595529],"type":"Point"}
}