{
  "type": "Feature",
  "properties": {
    "iso:country":"US",
    "sg:address":"969 E 8th Ave",
    "sg:city":"Hialeah",
    "sg:classifiers":[
        {
            "category":"Shopping",
            "subcategory":"Used Merchandise",
            "type":"Retail Goods"
        }
    ],
    "sg:phone":"+1 305 885 8848",
    "sg:postcode":"33010",
    "sg:province":"FL",
    "sg:tags":[
        "shop",
        "pawnbroker",
        "pawn",
        "jeweler"
    ],
    "wof:name":"T C Cash Inc",
    "wof:placetype":"venue"
},
  "geometry": {"coordinates":[-80.265602,25.8309],"type":"Point"}
}