{
  "type": "Feature",
  "properties": {
    "iso:country":"US",
    "sg:address":"437 W Vine St",
    "sg:city":"Kissimmee",
    "sg:classifiers":[
        {
            "category":"Banks & Credit Unions",
            "subcategory":"Bank",
            "type":"Services"
        }
    ],
    "sg:phone":"+1 407 483 0979",
    "sg:postcode":"34741",
    "sg:province":"FL",
    "sg:tags":[
        "loan",
        "real estate"
    ],
    "wof:name":"American Best Home Loan Corp",
    "wof:placetype":"venue"
},
  "geometry": {"coordinates":[-81.408511,28.304638],"type":"Point"}
}