{
  "type": "Feature",
  "properties": {
    "iso:country":"US",
    "sg:address":"5756 Descartes Cir",
    "sg:city":"Boynton Beach",
    "sg:classifiers":[
        {
            "category":"Shopping",
            "type":"Retail Goods"
        }
    ],
    "sg:phone":"+1 561 364 0907",
    "sg:postcode":"33472",
    "sg:province":"FL",
    "sg:tags":[
        "merchandise"
    ],
    "wof:name":"Eholy Co",
    "wof:placetype":"venue"
},
  "geometry": {"coordinates":[-80.13685599999999,26.543329],"type":"Point"}
}