{
  "type": "Feature",
  "properties": {
    "iso:country":"US",
    "sg:address":"2512 22nd Ave S",
    "sg:city":"St Petersburg",
    "sg:classifiers":[
        {
            "category":"Organizations",
            "subcategory":"Religious Organization",
            "type":"Services"
        }
    ],
    "sg:phone":"+1 727 327 0997",
    "sg:postcode":"33712",
    "sg:province":"FL",
    "sg:tags":[
        "church"
    ],
    "wof:name":"Christ Gospel Church",
    "wof:placetype":"venue"
},
  "geometry": {"coordinates":[-82.66733499999999,27.748315],"type":"Point"}
}