{
  "type": "Feature",
  "properties": {
    "addr:full":"1600 Woodland Dr Rockledge FL 32955",
    "addr:housenumber":"1600",
    "addr:postcode":"32955",
    "addr:street":"Woodland Dr",
    "iso:country":"US",
    "sg:address":"1600 Woodland Dr",
    "sg:city":"Rockledge",
    "sg:classifiers":[
        {
            "category":"Professional",
            "subcategory":"Computer Services",
            "type":"Services"
        }
    ],
    "sg:phone":"+1 321 639 9956",
    "sg:postcode":"32955",
    "sg:province":"FL",
    "sg:tags":[
        "datum"
    ],
    "wof:name":"Reid Electronic Images & Desig",
    "wof:placetype":"venue"
},
  "geometry": {"coordinates":[-80.75506799999999,28.334324],"type":"Point"}
}