{
  "type": "Feature",
  "properties": {
    "iso:country":"US",
    "sg:address":"327 Office Plz",
    "sg:city":"Tallahassee",
    "sg:classifiers":[
        {
            "category":"Health Services",
            "subcategory":"Clinic",
            "type":"Services"
        }
    ],
    "sg:phone":"+1 850 402 0051",
    "sg:postcode":"32301",
    "sg:province":"FL",
    "sg:tags":[
        "home",
        "care"
    ],
    "wof:name":"Watson Companion Care",
    "wof:placetype":"venue"
},
  "geometry": {"coordinates":[-84.25958,30.446215],"type":"Point"}
}