{
  "type": "Feature",
  "properties": {
    "addr:full":"988 Marbleridge Ct Orange Park FL 32065",
    "addr:housenumber":"988",
    "addr:postcode":"32065",
    "addr:street":"Marbleridge Ct",
    "iso:country":"US",
    "sg:address":"988 Marbleridge Ct",
    "sg:city":"Orange Park",
    "sg:classifiers":[
        {
            "category":"Real Estate",
            "subcategory":"Real Estate Agent",
            "type":"Services"
        }
    ],
    "sg:phone":"+1 904 272 9395",
    "sg:postcode":"32065",
    "sg:province":"FL",
    "wof:name":"Bryant Realty",
    "wof:placetype":"venue"
},
  "geometry": {"coordinates":[-81.78215400000001,30.150614],"type":"Point"}
}