{
  "type": "Feature",
  "properties": {
    "addr:full":"2591 SE 168 Ave Morriston FL 32668",
    "addr:housenumber":"2591",
    "addr:postcode":"32668",
    "addr:street":"Se 168 Ave",
    "iso:country":"US",
    "sg:address":"2591 SE 168 Ave",
    "sg:city":"Morriston",
    "sg:classifiers":[
        {
            "category":"Banks & Credit Unions",
            "subcategory":"Financial Services",
            "type":"Services"
        }
    ],
    "sg:phone":"+1 352 528 4478",
    "sg:postcode":"32668",
    "sg:province":"FL",
    "sg:tags":[
        "trust",
        "management"
    ],
    "wof:name":"Amik Run Equestrian Center",
    "wof:placetype":"venue"
},
  "geometry": {"coordinates":[-82.49217,29.29796],"type":"Point"}
}