{
  "type": "Feature",
  "properties": {
    "iso:country":"US",
    "sg:address":"5810 Normandy Blvd",
    "sg:city":"Jacksonville",
    "sg:classifiers":[
        {
            "category":"Sports & Exercise",
            "subcategory":"Gym",
            "type":"Entertainment"
        }
    ],
    "sg:phone":"+1 904 378 1551",
    "sg:postcode":"32205",
    "sg:province":"FL",
    "sg:tags":[
        "club",
        "health",
        "studio",
        "gymnasium"
    ],
    "sg:website":"www.worldgym.com",
    "wof:name":"World Gym & Fitness Inc",
    "wof:placetype":"venue"
},
  "geometry": {"coordinates":[-81.751834,30.306049],"type":"Point"}
}