{
  "type": "Feature",
  "properties": {
    "iso:country":"US",
    "sg:address":"108 W Cypress Rd",
    "sg:city":"Lake Worth",
    "sg:classifiers":[
        {
            "category":"Shopping",
            "type":"Retail Goods"
        }
    ],
    "sg:phone":"+1 561 965 5053",
    "sg:postcode":"33467",
    "sg:province":"FL",
    "sg:tags":[
        "merchandise"
    ],
    "wof:name":"APV Emporium Inc",
    "wof:placetype":"venue"
},
  "geometry": {"coordinates":[-80.17082600000001,26.604699],"type":"Point"}
}