{
  "type": "Feature",
  "properties": {
    "iso:country":"US",
    "sg:address":"1351 Bedford Dr",
    "sg:city":"Melbourne",
    "sg:classifiers":[
        {
            "category":"Building & Trades",
            "subcategory":"Construction",
            "type":"Services"
        }
    ],
    "sg:phone":"+1 321 254 0080",
    "sg:postcode":"32940",
    "sg:province":"FL",
    "sg:tags":[
        "residential",
        "designer"
    ],
    "wof:name":"Kendust Group",
    "wof:placetype":"venue"
},
  "geometry": {"coordinates":[-80.702561,28.230027],"type":"Point"}
}