{
  "type": "Feature",
  "properties": {
    "iso:country":"US",
    "sg:address":"6970 Collins Ave",
    "sg:city":"Miami Beach",
    "sg:classifiers":[
        {
            "category":"Restaurant",
            "type":"Food & Drink"
        }
    ],
    "sg:phone":"+1 305 864 1509",
    "sg:postcode":"33141",
    "sg:province":"FL",
    "wof:name":"Las Vegas Restaurant",
    "wof:placetype":"venue"
},
  "geometry": {"coordinates":[-80.1203,25.855499],"type":"Point"}
}