{
  "type": "Feature",
  "properties": {
    "iso:country":"US",
    "sg:address":"1000 Charlotte Ave",
    "sg:city":"Sarasota",
    "sg:classifiers":[
        {
            "category":"Building & Trades",
            "subcategory":"Construction",
            "type":"Services"
        }
    ],
    "sg:phone":"+1 941 955 7712",
    "sg:postcode":"34237",
    "sg:province":"FL",
    "sg:tags":[
        "carpentry",
        "contractor"
    ],
    "wof:name":"Maranatha Framing Inc",
    "wof:placetype":"venue"
},
  "geometry": {"coordinates":[-82.512456,27.323756],"type":"Point"}
}