{
  "type": "Feature",
  "properties": {
    "addr:full":"2400 N Commerce Pkwy Fort Lauderdale FL 33326",
    "addr:housenumber":"2400",
    "addr:postcode":"33326",
    "addr:street":"N Commerce Pkwy",
    "iso:country":"US",
    "sg:address":"2400 N Commerce Pkwy",
    "sg:city":"Fort Lauderdale",
    "sg:classifiers":[
        {
            "category":"Utilities",
            "subcategory":"Telephone",
            "type":"Services"
        }
    ],
    "sg:phone":"+1 954 306 0953",
    "sg:postcode":"33326",
    "sg:province":"FL",
    "sg:tags":[
        "web",
        "tracking"
    ],
    "wof:name":"Interamerican Technology Svcs",
    "wof:placetype":"venue"
},
  "geometry": {"coordinates":[-80.366681,26.091406],"type":"Point"}
}