{
  "type": "Feature",
  "properties": {
    "addr:full":"5017 Bella Terra Dr Venice FL 34293",
    "addr:housenumber":"5017",
    "addr:postcode":"34293",
    "addr:street":"Bella Terra Dr",
    "iso:country":"US",
    "sg:address":"5017 Bella Terra Dr",
    "sg:city":"Venice",
    "sg:classifiers":[
        {
            "category":"Building & Trades",
            "subcategory":"Construction",
            "type":"Services"
        }
    ],
    "sg:phone":"+1 941 408 0772",
    "sg:postcode":"34293",
    "sg:province":"FL",
    "sg:tags":[
        "contractor"
    ],
    "wof:name":"Polyashov Yuriy",
    "wof:placetype":"venue"
},
  "geometry": {"coordinates":[-82.39443300000001,27.039539],"type":"Point"}
}