{
  "type": "Feature",
  "properties": {
    "iso:country":"US",
    "sg:address":"5295 NW 161st St",
    "sg:city":"Hialeah",
    "sg:classifiers":[
        {
            "category":"Building & Trades",
            "subcategory":"Construction",
            "type":"Services"
        }
    ],
    "sg:phone":"+1 305 621 6100",
    "sg:postcode":"33014",
    "sg:province":"FL",
    "sg:tags":[
        "home",
        "improvement"
    ],
    "wof:name":"Noge Arnaiz Paint Contract",
    "wof:placetype":"venue"
},
  "geometry": {"coordinates":[-80.286884,25.919723],"type":"Point"}
}