{
  "type": "Feature",
  "properties": {
    "iso:country":"US",
    "sg:address":"3033 NE 32nd Ave",
    "sg:city":"Fort Lauderdale",
    "sg:classifiers":[
        {
            "category":"Cafe",
            "type":"Food & Drink"
        },
        {
            "category":"Restaurant",
            "type":"Food & Drink"
        }
    ],
    "sg:menulink":"http://www.allmenus.com/fl/fort-lauderdale/52375-shooters-waterfront-cafe/menu/",
    "sg:phone":"+1 954 566 2855",
    "sg:postcode":"33308",
    "sg:province":"FL",
    "sg:tags":[
        "american"
    ],
    "wof:name":"Shooters Waterfront Cafe",
    "wof:placetype":"venue"
},
  "geometry": {"coordinates":[-80.10323,26.166238],"type":"Point"}
}