{
  "type": "Feature",
  "properties": {
    "addr:full":"3415 S West Shore Blvd Tampa FL 33629",
    "addr:housenumber":"3415",
    "addr:postcode":"33629",
    "addr:street":"S West Shore Blvd",
    "iso:country":"US",
    "sg:address":"3415 S West Shore Blvd",
    "sg:city":"Tampa",
    "sg:classifiers":[
        {
            "category":"Building & Trades",
            "subcategory":"Landscaping Services",
            "type":"Services"
        }
    ],
    "sg:phone":"+1 813 831 5090",
    "sg:postcode":"33629",
    "sg:province":"FL",
    "sg:tags":[
        "sod",
        "sodding"
    ],
    "wof:name":"Rodriguez Sod",
    "wof:placetype":"venue"
},
  "geometry": {"coordinates":[-82.52671100000001,27.911659],"type":"Point"}
}