{
  "type": "Feature",
  "properties": {
    "iso:country":"US",
    "sg:address":"9416 Arlington Expy",
    "sg:city":"Jacksonville",
    "sg:classifiers":[
        {
            "category":"Home & Garden",
            "subcategory":"Household Appliances",
            "type":"Retail Goods"
        }
    ],
    "sg:phone":"+1 904 721 0300",
    "sg:postcode":"32225",
    "sg:province":"FL",
    "wof:name":"Oreck",
    "wof:placetype":"venue"
},
  "geometry": {"coordinates":[-81.552599,30.321318],"type":"Point"}
}