{
  "type": "Feature",
  "properties": {
    "iso:country":"US",
    "sg:address":"2315 NE 5th Ave",
    "sg:city":"Pompano Beach",
    "sg:classifiers":[
        {
            "category":"Home & Garden",
            "subcategory":"Furniture",
            "type":"Retail Goods"
        }
    ],
    "sg:phone":"+1 954 943 0323",
    "sg:postcode":"33064",
    "sg:province":"FL",
    "wof:name":"Save In Plus Furniture",
    "wof:placetype":"venue"
},
  "geometry": {"coordinates":[-80.11572200000001,26.260832],"type":"Point"}
}