{
  "type": "Feature",
  "properties": {
    "addr:full":"715 E 9th St Hialeah FL 33010",
    "addr:housenumber":"715",
    "addr:postcode":"33010",
    "addr:street":"E 9Th St",
    "iso:country":"US",
    "sg:address":"715 E 9th St",
    "sg:city":"Hialeah",
    "sg:classifiers":[
        {
            "category":"Building & Trades",
            "subcategory":"Locksmith",
            "type":"Services"
        }
    ],
    "sg:phone":"+1 305 357 2545",
    "sg:postcode":"33010",
    "sg:province":"FL",
    "sg:tags":[
        "key"
    ],
    "wof:name":"7 24 Anyplace Emergency Locksmith",
    "wof:placetype":"venue"
},
  "geometry": {"coordinates":[-80.26727,25.830615],"type":"Point"}
}