{
  "type": "Feature",
  "properties": {
    "addr:full":"325 Gardenia St West Palm Beach FL 33401",
    "addr:housenumber":"325",
    "addr:postcode":"33401",
    "addr:street":"Gardenia St",
    "iso:country":"US",
    "sg:address":"325 Gardenia St",
    "sg:city":"West Palm Beach",
    "sg:classifiers":[
        {
            "category":"Professional",
            "subcategory":"Business Services",
            "type":"Services"
        }
    ],
    "sg:phone":"+1 561 832 9989",
    "sg:postcode":"33401",
    "sg:province":"FL",
    "sg:tags":[
        "process",
        "server"
    ],
    "wof:name":"Legal Process",
    "wof:placetype":"venue"
},
  "geometry": {"coordinates":[-80.053275,26.709461],"type":"Point"}
}