{
  "type": "Feature",
  "properties": {
    "addr:full":"23 W Copeland Dr Orlando FL 32806",
    "addr:housenumber":"23",
    "addr:postcode":"32806",
    "addr:street":"W Copeland Dr",
    "iso:country":"US",
    "sg:address":"23 W Copeland Dr",
    "sg:city":"Orlando",
    "sg:classifiers":[
        {
            "category":"Health Services",
            "subcategory":"Doctor",
            "type":"Services"
        }
    ],
    "sg:phone":"+1 407 649 6865",
    "sg:postcode":"32806",
    "sg:province":"FL",
    "sg:tags":[
        "clinic"
    ],
    "wof:name":"M D Anderson Cancer Ctr",
    "wof:placetype":"venue"
},
  "geometry": {"coordinates":[-81.377144,28.526484],"type":"Point"}
}