{
  "type": "Feature",
  "properties": {
    "iso:country":"US",
    "sg:address":"1242 NE 145th St",
    "sg:city":"North Miami",
    "sg:classifiers":[
        {
            "category":"Manufacturing",
            "subcategory":"Motor Vehicles & Parts",
            "type":"Manufacturing & Wholesale Goods"
        }
    ],
    "sg:phone":"+1 305 944 3307",
    "sg:postcode":"33161",
    "sg:province":"FL",
    "sg:tags":[
        "automotive",
        "findings"
    ],
    "wof:name":"Kathryn Page Inc",
    "wof:placetype":"venue"
},
  "geometry": {"coordinates":[-80.172011,25.90901],"type":"Point"}
}