{
  "type": "Feature",
  "properties": {
    "addr:full":"1725 S Nova Rd Daytona Beach FL 32119",
    "addr:housenumber":"1725",
    "addr:postcode":"32119",
    "addr:street":"S Nova Rd",
    "iso:country":"US",
    "sg:address":"1725 S Nova Rd",
    "sg:city":"Daytona Beach",
    "sg:classifiers":[
        {
            "category":"Home & Garden",
            "subcategory":"Carpets & Floor Coverings",
            "type":"Retail Goods"
        }
    ],
    "sg:phone":"+1 386 788 0118",
    "sg:postcode":"32119",
    "sg:province":"FL",
    "sg:tags":[
        "linoleum",
        "including",
        "rug",
        "ce"
    ],
    "wof:name":"Trotts Carpet Inc",
    "wof:placetype":"venue"
},
  "geometry": {"coordinates":[-81.026355,29.17135],"type":"Point"}
}