{
  "type": "Feature",
  "properties": {
    "iso:country":"US",
    "sg:address":"5985 Bent Pine Dr",
    "sg:city":"Orlando",
    "sg:classifiers":[
        {
            "category":"Banks & Credit Unions",
            "subcategory":"Bank",
            "type":"Services"
        }
    ],
    "sg:phone":"+1 407 888 8575",
    "sg:postcode":"32822",
    "sg:province":"FL",
    "sg:tags":[
        "financing"
    ],
    "wof:name":"Double RR Financial",
    "wof:placetype":"venue"
},
  "geometry": {"coordinates":[-81.304695,28.473201],"type":"Point"}
}