{
  "type": "Feature",
  "properties": {
    "addr:full":"1502 E Fletcher Ave Tampa FL 33612",
    "addr:housenumber":"1502",
    "addr:postcode":"33612",
    "addr:street":"E Fletcher Ave",
    "iso:country":"US",
    "sg:address":"1502 E Fletcher Ave",
    "sg:city":"Tampa",
    "sg:classifiers":[
        {
            "category":"Food & Beverages",
            "subcategory":"Groceries & Convenience Stores",
            "type":"Retail Goods"
        }
    ],
    "sg:phone":"+1 813 971 1239",
    "sg:postcode":"33612",
    "sg:province":"FL",
    "sg:tags":[
        "grocer"
    ],
    "wof:name":"Fletcher Supermarket",
    "wof:placetype":"venue"
},
  "geometry": {"coordinates":[-82.43988899999999,28.069346],"type":"Point"}
}