{
  "type": "Feature",
  "properties": {
    "iso:country":"US",
    "sg:address":"2850 NW 7th Ave",
    "sg:city":"Miami",
    "sg:classifiers":[
        {
            "category":"Shopping",
            "subcategory":"Jewelry",
            "type":"Retail Goods"
        }
    ],
    "sg:phone":"+1 305 638 9099",
    "sg:postcode":"33127",
    "sg:province":"FL",
    "sg:tags":[
        "shop",
        "pawn"
    ],
    "wof:name":"Friendly Pawn Shop",
    "wof:placetype":"venue"
},
  "geometry": {"coordinates":[-80.20754599999999,25.803299],"type":"Point"}
}