{
  "type": "Feature",
  "properties": {
    "iso:country":"US",
    "sg:address":"2443 29th Ave NE",
    "sg:city":"Naples",
    "sg:classifiers":[
        {
            "category":"Building & Trades",
            "subcategory":"Construction",
            "type":"Services"
        }
    ],
    "sg:phone":"+1 239 353 1268",
    "sg:postcode":"34120",
    "sg:province":"FL",
    "sg:tags":[
        "house",
        "masonry",
        "contract",
        "contractor"
    ],
    "wof:name":"Artisan Block & Stone Inc",
    "wof:placetype":"venue"
},
  "geometry": {"coordinates":[-81.545995,26.28537],"type":"Point"}
}