{
  "type": "Feature",
  "properties": {
    "iso:country":"US",
    "sg:address":"6919 Pitts Rd",
    "sg:city":"Jacksonville",
    "sg:classifiers":[
        {
            "category":"Wholesale",
            "subcategory":"Plants",
            "type":"Manufacturing & Wholesale Goods"
        }
    ],
    "sg:phone":"+1 904 765 1609",
    "sg:postcode":"32219",
    "sg:province":"FL",
    "sg:tags":[
        "florist"
    ],
    "wof:name":"M J Mc Call Co",
    "wof:placetype":"venue"
},
  "geometry": {"coordinates":[-81.76247600000001,30.426839],"type":"Point"}
}