{
  "type": "Feature",
  "properties": {
    "addr:full":"301 Long Ave Port St Joe FL 32456",
    "addr:housenumber":"301",
    "addr:postcode":"32456",
    "addr:street":"Long Ave",
    "iso:country":"US",
    "sg:address":"301 Long Ave",
    "sg:city":"Port St Joe",
    "sg:classifiers":[
        {
            "category":"Home & Garden",
            "subcategory":"Household Appliances",
            "type":"Retail Goods"
        }
    ],
    "sg:phone":"+1 850 229 8217",
    "sg:postcode":"32456",
    "sg:province":"FL",
    "wof:name":"Appliance Solution",
    "wof:placetype":"venue"
},
  "geometry": {"coordinates":[-85.30162300000001,29.814259],"type":"Point"}
}