{
  "type": "Feature",
  "properties": {
    "iso:country":"US",
    "sg:address":"5100 110th Ave N",
    "sg:city":"Clearwater",
    "sg:classifiers":[
        {
            "category":"Retail",
            "subcategory":"Repair Shop",
            "type":"Services"
        }
    ],
    "sg:phone":"+1 727 556 2706",
    "sg:postcode":"33760",
    "sg:province":"FL",
    "sg:tags":[
        "sharpening"
    ],
    "wof:name":"Southern Tool Mfg",
    "wof:placetype":"venue"
},
  "geometry": {"coordinates":[-82.701932,27.872049],"type":"Point"}
}