{
  "type": "Feature",
  "properties": {
    "iso:country":"US",
    "sg:address":"1160 1st Ave S",
    "sg:city":"Naples",
    "sg:classifiers":[
        {
            "category":"Personal",
            "type":"Services"
        }
    ],
    "sg:phone":"+1 239 262 6002",
    "sg:postcode":"34102",
    "sg:province":"FL",
    "sg:tags":[
        "house",
        "sitter"
    ],
    "wof:name":"Quality Home Tenders Inc",
    "wof:placetype":"venue"
},
  "geometry": {"coordinates":[-81.79401799999999,26.146414],"type":"Point"}
}