{
  "type": "Feature",
  "properties": {
    "addr:full":"6680 Lantana Rd Lake Worth FL 33467",
    "addr:housenumber":"6680",
    "addr:postcode":"33467",
    "addr:street":"Lantana Rd",
    "iso:country":"US",
    "sg:address":"6680 Lantana Rd",
    "sg:city":"Lake Worth",
    "sg:classifiers":[
        {
            "category":"Home & Garden",
            "subcategory":"Carpets & Floor Coverings",
            "type":"Retail Goods"
        }
    ],
    "sg:phone":"+1 561 582 8444",
    "sg:postcode":"33467",
    "sg:province":"FL",
    "sg:tags":[
        "material"
    ],
    "wof:name":"Uban Corp",
    "wof:placetype":"venue"
},
  "geometry": {"coordinates":[-80.152219,26.58969],"type":"Point"}
}