{
  "type": "Feature",
  "properties": {
    "iso:country":"US",
    "sg:address":"11783 Lake Ride Dr",
    "sg:city":"Jacksonville",
    "sg:classifiers":[
        {
            "category":"Professional",
            "type":"Services"
        }
    ],
    "sg:phone":"+1 904 268 0992",
    "sg:postcode":"32223",
    "sg:province":"FL",
    "wof:name":"Michael Robert Nobles",
    "wof:placetype":"venue"
},
  "geometry": {"coordinates":[-81.614518,30.159006],"type":"Point"}
}