{
  "type": "Feature",
  "properties": {
    "iso:country":"US",
    "sg:address":"670 S Wickham Rd",
    "sg:city":"Melbourne",
    "sg:classifiers":[
        {
            "category":"Retail",
            "subcategory":"Auto Repair",
            "type":"Services"
        }
    ],
    "sg:phone":"+1 321 984 2271",
    "sg:postcode":"32904",
    "sg:province":"FL",
    "sg:tags":[
        "repairing",
        "automobile"
    ],
    "wof:name":"Ferrara's Garage",
    "wof:placetype":"venue"
},
  "geometry": {"coordinates":[-80.67271700000001,28.095548],"type":"Point"}
}