{
  "type": "Feature",
  "properties": {
    "addr:full":"13031 Park Blvd Seminole FL 33776",
    "addr:housenumber":"13031",
    "addr:postcode":"33776",
    "addr:street":"Park Blvd",
    "iso:country":"US",
    "sg:address":"13031 Park Blvd",
    "sg:city":"Seminole",
    "sg:classifiers":[
        {
            "category":"Travel",
            "subcategory":"Travel Agent",
            "type":"Entertainment"
        }
    ],
    "sg:phone":"+1 727 397 5000",
    "sg:postcode":"33776",
    "sg:province":"FL",
    "sg:tags":[
        "agency",
        "bureau"
    ],
    "wof:name":"Cruise Holidays",
    "wof:placetype":"venue"
},
  "geometry": {"coordinates":[-82.818397,27.84373],"type":"Point"}
}