{
  "type": "Feature",
  "properties": {
    "iso:country":"US",
    "sg:address":"1090 E 14th St",
    "sg:city":"Hialeah",
    "sg:classifiers":[
        {
            "category":"Wholesale",
            "subcategory":"Auto Parts",
            "type":"Manufacturing & Wholesale Goods"
        }
    ],
    "sg:phone":"+1 305 887 0255",
    "sg:postcode":"33010",
    "sg:province":"FL",
    "sg:tags":[
        "body",
        "automobile",
        "shop"
    ],
    "wof:name":"Finish Master",
    "wof:placetype":"venue"
},
  "geometry": {"coordinates":[-80.261387,25.835239],"type":"Point"}
}