{
  "type": "Feature",
  "properties": {
    "iso:country":"US",
    "sg:address":"4021 Gulf Shore Blvd N",
    "sg:city":"Naples",
    "sg:classifiers":[
        {
            "category":"Building & Trades",
            "subcategory":"Cleaning & Sanitation",
            "type":"Services"
        }
    ],
    "sg:phone":"+1 239 434 0305",
    "sg:postcode":"34103",
    "sg:province":"FL",
    "sg:tags":[
        "ventilating",
        "system"
    ],
    "wof:name":"Edenair Inc",
    "wof:placetype":"venue"
},
  "geometry": {"coordinates":[-81.812742,26.19659],"type":"Point"}
}