{
  "type": "Feature",
  "properties": {
    "iso:country":"US",
    "sg:address":"601 N Clyde Morris Blvd",
    "sg:city":"Daytona Beach",
    "sg:classifiers":[
        {
            "category":"Professional",
            "subcategory":"Testing Lab",
            "type":"Services"
        }
    ],
    "sg:phone":"+1 386 238 3405",
    "sg:postcode":"32114",
    "sg:province":"FL",
    "sg:tags":[
        "laboratory"
    ],
    "wof:name":"Diagnostic Ventures Inc",
    "wof:placetype":"venue"
},
  "geometry": {"coordinates":[-81.06203499999999,29.213533],"type":"Point"}
}