{
  "type": "Feature",
  "properties": {
    "iso:country":"US",
    "sg:address":"5810 Macy Ave",
    "sg:city":"Jacksonville",
    "sg:classifiers":[
        {
            "category":"Home & Garden",
            "subcategory":"Household Appliances",
            "type":"Retail Goods"
        }
    ],
    "sg:phone":"+1 904 743 0055",
    "sg:postcode":"32211",
    "sg:province":"FL",
    "sg:tags":[
        "cleaners",
        "vacuum"
    ],
    "wof:name":"Arlington Rainbow Sales & Svc",
    "wof:placetype":"venue"
},
  "geometry": {"coordinates":[-81.59963,30.335823],"type":"Point"}
}