{
  "type": "Feature",
  "properties": {
    "addr:full":"7824 Causeway Blvd Tampa FL 33619",
    "addr:housenumber":"7824",
    "addr:postcode":"33619",
    "addr:street":"Causeway Blvd",
    "iso:country":"US",
    "sg:address":"7824 Causeway Blvd",
    "sg:city":"Tampa",
    "sg:classifiers":[
        {
            "category":"Building & Trades",
            "subcategory":"Construction",
            "type":"Services"
        }
    ],
    "sg:phone":"+1 813 612 4454",
    "sg:postcode":"33619",
    "sg:province":"FL",
    "sg:tags":[
        "designer",
        "dealer",
        "pool",
        "swimming"
    ],
    "wof:name":"Freestyle Pools & Spas",
    "wof:placetype":"venue"
},
  "geometry": {"coordinates":[-82.368143,27.922756],"type":"Point"}
}