{
  "type": "Feature",
  "properties": {
    "addr:full":"1010 Spring Villas Pt Winter Springs FL 32708",
    "addr:housenumber":"1010",
    "addr:postcode":"32708",
    "addr:street":"Spring Villas Pt",
    "iso:country":"US",
    "sg:address":"1010 Spring Villas Pt",
    "sg:city":"Winter Springs",
    "sg:classifiers":[
        {
            "category":"Social Services",
            "subcategory":"Child Care",
            "type":"Services"
        }
    ],
    "sg:phone":"+1 407 699 1371",
    "sg:postcode":"32708",
    "sg:province":"FL",
    "sg:tags":[
        "day"
    ],
    "wof:name":"La Petite Academy Inc",
    "wof:placetype":"venue"
},
  "geometry": {"coordinates":[-81.270622,28.642806],"type":"Point"}
}