{
  "type": "Feature",
  "properties": {
    "iso:country":"US",
    "sg:address":"3270 Suntree Blvd",
    "sg:city":"Melbourne",
    "sg:classifiers":[
        {
            "category":"Organizations",
            "subcategory":"Professional Association",
            "type":"Services"
        }
    ],
    "sg:phone":"+1 321 255 3885",
    "sg:postcode":"32940",
    "sg:province":"FL",
    "sg:tags":[
        "home",
        "management",
        "co",
        "consultant"
    ],
    "wof:name":"Homecare Providers Co-Op Inc",
    "wof:placetype":"venue"
},
  "geometry": {"coordinates":[-80.678399,28.227919],"type":"Point"}
}