{
  "type": "Feature",
  "properties": {
    "iso:country":"US",
    "sg:address":"4050 NW 19th Ter",
    "sg:city":"Oakland Park",
    "sg:classifiers":[
        {
            "category":"Banks & Credit Unions",
            "subcategory":"Bank",
            "type":"Services"
        }
    ],
    "sg:phone":"+1 954 739 0551",
    "sg:postcode":"33309",
    "sg:province":"FL",
    "sg:tags":[
        "loan",
        "real estate"
    ],
    "wof:name":"Wright Mortgage",
    "wof:placetype":"venue"
},
  "geometry": {"coordinates":[-80.168514,26.178005],"type":"Point"}
}