{
  "type": "Feature",
  "properties": {
    "addr:full":"909 Tamiami Trl Port Charlotte FL 33953",
    "addr:housenumber":"909",
    "addr:postcode":"33953",
    "addr:street":"Tamiami Trl",
    "iso:country":"US",
    "sg:address":"909 Tamiami Trl",
    "sg:city":"Port Charlotte",
    "sg:classifiers":[
        {
            "category":"Personal",
            "subcategory":"Beauty Salon",
            "type":"Services"
        }
    ],
    "sg:phone":"+1 941 255 1088",
    "sg:postcode":"33953",
    "sg:province":"FL",
    "wof:name":"R S Warner",
    "wof:placetype":"venue"
},
  "geometry": {"coordinates":[-82.162486,27.018042],"type":"Point"}
}