{
  "type": "Feature",
  "properties": {
    "iso:country":"US",
    "sg:address":"1353 Lotus Path",
    "sg:city":"Clearwater",
    "sg:classifiers":[
        {
            "category":"Professional",
            "subcategory":"Business Services",
            "type":"Services"
        }
    ],
    "sg:phone":"+1 727 447 5900",
    "sg:postcode":"33756",
    "sg:province":"FL",
    "wof:name":"Devlin Group Inc",
    "wof:placetype":"venue"
},
  "geometry": {"coordinates":[-82.78085400000001,27.954382],"type":"Point"}
}