{
  "type": "Feature",
  "properties": {
    "addr:full":"1233 S Atlantic Ave Daytona Beach FL 32118",
    "addr:housenumber":"1233",
    "addr:postcode":"32118",
    "addr:street":"S Atlantic Ave",
    "iso:country":"US",
    "sg:address":"1233 S Atlantic Ave",
    "sg:city":"Daytona Beach",
    "sg:classifiers":[
        {
            "category":"Travel",
            "subcategory":"Hotels & Motels",
            "type":"Entertainment"
        },
        {
            "category":"Real Estate",
            "subcategory":"Real Estate Operator",
            "type":"Services"
        }
    ],
    "sg:phone":"+1 386 253 0334",
    "sg:postcode":"32118",
    "sg:province":"FL",
    "sg:tags":[
        "operation",
        "condominium"
    ],
    "wof:name":"Sea Dip Beach Resort Cond",
    "wof:placetype":"venue"
},
  "geometry": {"coordinates":[-81.000457,29.211318],"type":"Point"}
}