{
  "type": "Feature",
  "properties": {
    "iso:country":"US",
    "sg:address":"9020 Royal Palm Blvd",
    "sg:city":"Coral Springs",
    "sg:classifiers":[
        {
            "category":"Real Estate",
            "subcategory":"Real Estate Operator",
            "type":"Services"
        }
    ],
    "sg:phone":"+1 954 796 4088",
    "sg:postcode":"33065",
    "sg:province":"FL",
    "sg:tags":[
        "building",
        "apartment"
    ],
    "wof:name":"Royal Palm Towers",
    "wof:placetype":"venue"
},
  "geometry": {"coordinates":[-80.248114,26.259191],"type":"Point"}
}