{
  "type": "Feature",
  "properties": {
    "addr:full":"4254 SW 152nd Ave Miami FL 33185",
    "addr:housenumber":"4254",
    "addr:postcode":"33185",
    "addr:street":"Sw 152Nd Ave",
    "iso:country":"US",
    "sg:address":"4254 SW 152nd Ave",
    "sg:city":"Miami",
    "sg:classifiers":[
        {
            "category":"Restaurant",
            "type":"Food & Drink"
        }
    ],
    "sg:phone":"+1 305 551 2040",
    "sg:postcode":"33185",
    "sg:province":"FL",
    "sg:tags":[
        "italian",
        "pizza"
    ],
    "wof:name":"Mikes's & Sons Pizzeria & Italian Restaurant",
    "wof:placetype":"venue"
},
  "geometry": {"coordinates":[-80.439725,25.727647],"type":"Point"}
}