{
  "type": "Feature",
  "properties": {
    "iso:country":"US",
    "sg:address":"1808 4th St W",
    "sg:city":"Palmetto",
    "sg:classifiers":[
        {
            "category":"Manufacturing",
            "subcategory":"Building Materials",
            "type":"Manufacturing & Wholesale Goods"
        }
    ],
    "sg:phone":"+1 941 722 5631",
    "sg:postcode":"34221",
    "sg:province":"FL",
    "sg:tags":[
        "millwork",
        "mfg"
    ],
    "wof:name":"David W Sutton Woodworking Inc",
    "wof:placetype":"venue"
},
  "geometry": {"coordinates":[-82.58657599999999,27.51403],"type":"Point"}
}