{
  "type": "Feature",
  "properties": {
    "addr:full":"1401 King Sago Ct Naples FL 34119",
    "addr:housenumber":"1401",
    "addr:postcode":"34119",
    "addr:street":"King Sago Ct",
    "iso:country":"US",
    "sg:address":"1401 King Sago Ct",
    "sg:city":"Naples",
    "sg:classifiers":[
        {
            "category":"Real Estate",
            "subcategory":"Real Estate Agent",
            "type":"Services"
        }
    ],
    "sg:phone":"+1 239 593 5883",
    "sg:postcode":"34119",
    "sg:province":"FL",
    "sg:tags":[
        "inspection"
    ],
    "wof:name":"Slab 2 Shingles Hm Inspections",
    "wof:placetype":"venue"
},
  "geometry": {"coordinates":[-81.717523,26.265262],"type":"Point"}
}