{
  "type": "Feature",
  "properties": {
    "iso:country":"US",
    "sg:address":"18054 Clear Brook Cir",
    "sg:city":"Boca Raton",
    "sg:classifiers":[
        {
            "category":"Education",
            "subcategory":"Special Training",
            "type":"Public Place"
        }
    ],
    "sg:phone":"+1 561 218 2105",
    "sg:postcode":"33498",
    "sg:province":"FL",
    "sg:tags":[
        "school",
        "language"
    ],
    "wof:name":"Betty Besner",
    "wof:placetype":"venue"
},
  "geometry": {"coordinates":[-80.22564,26.40816],"type":"Point"}
}