{
  "type": "Feature",
  "properties": {
    "iso:country":"US",
    "sg:address":"5756 Dahlia Dr",
    "sg:city":"Orlando",
    "sg:classifiers":[
        {
            "category":"Retail",
            "subcategory":"Auto Repair",
            "type":"Services"
        }
    ],
    "sg:phone":"+1 407 282 4444",
    "sg:postcode":"32807",
    "sg:province":"FL",
    "sg:tags":[
        "wrecker"
    ],
    "wof:name":"AAL Automotive Towing",
    "wof:placetype":"venue"
},
  "geometry": {"coordinates":[-81.309749,28.545751],"type":"Point"}
}