{
  "type": "Feature",
  "properties": {
    "iso:country":"US",
    "sg:address":"13737 Automobile Blvd",
    "sg:city":"Clearwater",
    "sg:classifiers":[
        {
            "category":"Wholesale",
            "subcategory":"Groceries",
            "type":"Manufacturing & Wholesale Goods"
        }
    ],
    "sg:phone":"+1 813 572 5900",
    "sg:postcode":"33762",
    "sg:province":"FL",
    "wof:name":"Zephyrhills Water Co",
    "wof:placetype":"venue"
},
  "geometry": {"coordinates":[-82.696309,27.89714],"type":"Point"}
}