{
  "type": "Feature",
  "properties": {
    "addr:full":"2159 SE Ocean Blvd Stuart FL 34996",
    "addr:housenumber":"2159",
    "addr:postcode":"34996",
    "addr:street":"Se Ocean Blvd",
    "iso:country":"US",
    "sg:address":"2159 SE Ocean Blvd",
    "sg:city":"Stuart",
    "sg:classifiers":[
        {
            "category":"Insurance",
            "subcategory":"Insurance Agent",
            "type":"Services"
        }
    ],
    "sg:phone":"+1 772 283 1199",
    "sg:postcode":"34996",
    "sg:province":"FL",
    "wof:name":"J S Konkus Insurance",
    "wof:placetype":"venue"
},
  "geometry": {"coordinates":[-80.222978,27.197219],"type":"Point"}
}