{
  "type": "Feature",
  "properties": {
    "iso:country":"US",
    "sg:address":"220 E 6th St",
    "sg:city":"Jacksonville",
    "sg:classifiers":[
        {
            "category":"Wholesale",
            "subcategory":"Vending Machines",
            "type":"Manufacturing & Wholesale Goods"
        }
    ],
    "sg:phone":"+1 904 350 9123",
    "sg:postcode":"32206",
    "sg:province":"FL",
    "sg:tags":[
        "operator"
    ],
    "wof:name":"Florida Public Tel Co",
    "wof:placetype":"venue"
},
  "geometry": {"coordinates":[-81.649902,30.34271],"type":"Point"}
}