{
  "type": "Feature",
  "properties": {
    "iso:country":"US",
    "sg:address":"5053 Emerson Ave",
    "sg:city":"Fort Pierce",
    "sg:classifiers":[
        {
            "category":"Building & Trades",
            "subcategory":"Construction",
            "type":"Services"
        }
    ],
    "sg:phone":"+1 772 461 5030",
    "sg:postcode":"34951",
    "sg:province":"FL",
    "sg:tags":[
        "stucco",
        "contractor"
    ],
    "wof:name":"Quality Plastering Co",
    "wof:placetype":"venue"
},
  "geometry": {"coordinates":[-80.414767,27.538457],"type":"Point"}
}