{
  "type": "Feature",
  "properties": {
    "iso:country":"US",
    "sg:address":"9212 N 28th St",
    "sg:city":"Tampa",
    "sg:classifiers":[
        {
            "category":"Shopping",
            "subcategory":"Gifts & Souvenirs",
            "type":"Retail Goods"
        }
    ],
    "sg:phone":"+1 813 931 9703",
    "sg:postcode":"33612",
    "sg:province":"FL",
    "sg:tags":[
        "basket",
        "parcel"
    ],
    "wof:name":"Basket Expressions",
    "wof:placetype":"venue"
},
  "geometry": {"coordinates":[-82.4285,28.03603],"type":"Point"}
}