{
  "type": "Feature",
  "properties": {
    "iso:country":"US",
    "sg:address":"340 S Lost Lake Ln",
    "sg:city":"Casselberry",
    "sg:classifiers":[
        {
            "category":"Building & Trades",
            "subcategory":"Plumbing",
            "type":"Services"
        }
    ],
    "sg:phone":"+1 407 695 1170",
    "sg:postcode":"32707",
    "sg:province":"FL",
    "sg:tags":[
        "mechanical",
        "contractor"
    ],
    "wof:name":"Just Panels",
    "wof:placetype":"venue"
},
  "geometry": {"coordinates":[-81.322333,28.665829],"type":"Point"}
}