{
  "type": "Feature",
  "properties": {
    "addr:full":"3409 W Bay To Bay Blvd Tampa FL 33629",
    "addr:housenumber":"3409",
    "addr:postcode":"33629",
    "addr:street":"W Bay To Bay Blvd",
    "iso:country":"US",
    "sg:address":"3409 W Bay To Bay Blvd",
    "sg:city":"Tampa",
    "sg:classifiers":[
        {
            "category":"Personal",
            "subcategory":"Tanning Parlor",
            "type":"Services"
        },
        {
            "category":"Personal",
            "type":"Services"
        }
    ],
    "sg:phone":"+1 813 832 8267",
    "sg:postcode":"33629",
    "sg:province":"FL",
    "sg:tags":[
        "salon"
    ],
    "wof:name":"Soleil Tanning",
    "wof:placetype":"venue"
},
  "geometry": {"coordinates":[-82.500322,27.919823],"type":"Point"}
}