{
  "type": "Feature",
  "properties": {
    "iso:country":"US",
    "sg:address":"36 N 5th St",
    "sg:city":"Haines City",
    "sg:classifiers":[
        {
            "category":"Retail",
            "subcategory":"Funeral Services",
            "type":"Services"
        }
    ],
    "sg:phone":"+1 863 422 7128",
    "sg:postcode":"33844",
    "sg:province":"FL",
    "sg:tags":[
        "director"
    ],
    "wof:name":"Faith Funeral Home",
    "wof:placetype":"venue"
},
  "geometry": {"coordinates":[-81.627477,28.107216],"type":"Point"}
}