{
  "type": "Feature",
  "properties": {
    "iso:country":"US",
    "sg:address":"1288 W Cam Real",
    "sg:city":"Boca Raton",
    "sg:classifiers":[
        {
            "category":"Building & Trades",
            "subcategory":"Construction",
            "type":"Services"
        }
    ],
    "sg:phone":"+1 561 338 9714",
    "sg:postcode":"33486",
    "sg:province":"FL",
    "sg:tags":[
        "designer",
        "dealer",
        "pool",
        "swimming"
    ],
    "wof:name":"Classic Pools Of The Palm Bchs",
    "wof:placetype":"venue"
},
  "geometry": {"coordinates":[-80.112103,26.344086],"type":"Point"}
}