{
  "type": "Feature",
  "properties": {
    "iso:country":"US",
    "sg:address":"13262 Summerton Dr",
    "sg:city":"Orlando",
    "sg:classifiers":[
        {
            "category":"Building & Trades",
            "subcategory":"Construction",
            "type":"Services"
        }
    ],
    "sg:phone":"+1 407 403 5815",
    "sg:postcode":"32824",
    "sg:province":"FL",
    "sg:tags":[
        "wallcoverings-installation",
        "wallpaper",
        "painting",
        "contractor"
    ],
    "wof:name":"Polymath Painting",
    "wof:placetype":"venue"
},
  "geometry": {"coordinates":[-81.37070799999999,28.36507],"type":"Point"}
}