{
  "type": "Feature",
  "properties": {
    "iso:country":"US",
    "sg:address":"410 Government Ave",
    "sg:city":"Valparaiso",
    "sg:classifiers":[
        {
            "category":"Food & Beverages",
            "subcategory":"Specialty",
            "type":"Retail Goods"
        }
    ],
    "sg:phone":"+1 850 729 3993",
    "sg:postcode":"32580",
    "sg:province":"FL",
    "sg:tags":[
        "oriental"
    ],
    "wof:name":"Kim-Hoang Oriental Market",
    "wof:placetype":"venue"
},
  "geometry": {"coordinates":[-86.50754999999999,30.515902],"type":"Point"}
}