{
  "type": "Feature",
  "properties": {
    "iso:country":"US",
    "sg:address":"4400 S Hopkins Ave",
    "sg:city":"Titusville",
    "sg:classifiers":[
        {
            "category":"Home & Garden",
            "subcategory":"Carpets & Floor Coverings",
            "type":"Retail Goods"
        }
    ],
    "sg:phone":"+1 321 267 7070",
    "sg:postcode":"32780",
    "sg:province":"FL",
    "wof:name":"Custom Decor",
    "wof:placetype":"venue"
},
  "geometry": {"coordinates":[-80.80166199999999,28.561102],"type":"Point"}
}