{
  "type": "Feature",
  "properties": {
    "iso:country":"US",
    "sg:address":"3067 Mary St",
    "sg:city":"Miami",
    "sg:classifiers":[
        {
            "category":"Shopping",
            "subcategory":"Bicycles & Sporting Goods",
            "type":"Retail Goods"
        }
    ],
    "sg:phone":"+1 786 552 7533",
    "sg:postcode":"33133",
    "sg:province":"FL",
    "sg:tags":[
        "equipment",
        "exercise"
    ],
    "wof:name":"Life Fitness",
    "wof:placetype":"venue"
},
  "geometry": {"coordinates":[-80.239588,25.733961],"type":"Point"}
}