{
  "type": "Feature",
  "properties": {
    "iso:country":"US",
    "sg:address":"6963 Green Tree Dr",
    "sg:city":"Naples",
    "sg:classifiers":[
        {
            "category":"Professional",
            "subcategory":"Management & Consulting",
            "type":"Services"
        }
    ],
    "sg:phone":"+1 239 592 6892",
    "sg:postcode":"34108",
    "sg:province":"FL",
    "sg:tags":[
        "retail",
        "direct",
        "sales"
    ],
    "wof:name":"Golden Elegance",
    "wof:placetype":"venue"
},
  "geometry": {"coordinates":[-81.805899,26.239746],"type":"Point"}
}