{
  "type": "Feature",
  "properties": {
    "iso:country":"US",
    "sg:address":"1507 NW 82nd Ave",
    "sg:city":"Doral",
    "sg:classifiers":[
        {
            "category":"Professional",
            "subcategory":"Engineering",
            "type":"Services"
        },
        {
            "category":"Retail",
            "subcategory":"Repair Shop",
            "type":"Services"
        },
        {
            "category":"Manufacturing",
            "subcategory":"Aerospace",
            "type":"Manufacturing & Wholesale Goods"
        }
    ],
    "sg:phone":"+1 305 477 7005",
    "sg:postcode":"33126",
    "sg:province":"FL",
    "sg:tags":[
        "rebuilding",
        "supply",
        "equipment",
        "aircraft",
        "part",
        "maintenance"
    ],
    "wof:name":"Aviation Specialist",
    "wof:placetype":"venue"
},
  "geometry": {"coordinates":[-80.328613,25.787544],"type":"Point"}
}