{
  "type": "Feature",
  "properties": {
    "iso:country":"US",
    "sg:address":"2336 Bayview Ave",
    "sg:city":"Panama City",
    "sg:classifiers":[
        {
            "category":"Retail",
            "subcategory":"Repair Shop",
            "type":"Services"
        }
    ],
    "sg:phone":"+1 850 763 3763",
    "sg:postcode":"32405",
    "sg:province":"FL",
    "sg:tags":[
        "scooter",
        "motorcycle",
        "motor"
    ],
    "wof:name":"Eagles Cycles",
    "wof:placetype":"venue"
},
  "geometry": {"coordinates":[-85.70163100000001,30.191802],"type":"Point"}
}