{
  "type": "Feature",
  "properties": {
    "iso:country":"US",
    "sg:address":"2760 Dudley Dr E",
    "sg:city":"West Palm Beach",
    "sg:classifiers":[
        {
            "category":"Health Services",
            "subcategory":"Doctor",
            "type":"Services"
        }
    ],
    "sg:phone":"+1 561 967 4263",
    "sg:postcode":"33415",
    "sg:province":"FL",
    "sg:tags":[
        "medical"
    ],
    "wof:name":"William J Dunn Dr",
    "wof:placetype":"venue"
},
  "geometry": {"coordinates":[-80.126451,26.639603],"type":"Point"}
}