{
  "type": "Feature",
  "properties": {
    "iso:country":"US",
    "sg:address":"4611 SW 104th Ct",
    "sg:city":"Miami",
    "sg:classifiers":[
        {
            "category":"Building & Trades",
            "subcategory":"Construction",
            "type":"Services"
        }
    ],
    "sg:phone":"+1 305 227 0102",
    "sg:postcode":"33165",
    "sg:province":"FL",
    "sg:tags":[
        "general",
        "contractor"
    ],
    "wof:name":"Construction Consulting Svc",
    "wof:placetype":"venue"
},
  "geometry": {"coordinates":[-80.364316,25.724727],"type":"Point"}
}