{
  "type": "Feature",
  "properties": {
    "addr:full":"5725 Seminole Way Fort Lauderdale FL 33314",
    "addr:housenumber":"5725",
    "addr:postcode":"33314",
    "addr:street":"Seminole Way",
    "iso:country":"US",
    "sg:address":"5725 Seminole Way",
    "sg:city":"Fort Lauderdale",
    "sg:classifiers":[
        {
            "category":"Ice Cream",
            "type":"Food & Drink"
        }
    ],
    "sg:menulink":"http://www.allmenus.com/fl/davie/215370-ben--jerrys/menu/",
    "sg:phone":"+1 954 321 5144",
    "sg:postcode":"33314",
    "sg:province":"FL",
    "sg:tags":[
        "american"
    ],
    "wof:name":"Ben & Jerry's",
    "wof:placetype":"venue"
},
  "geometry": {"coordinates":[-80.210724,26.050351],"type":"Point"}
}