{
  "type": "Feature",
  "properties": {
    "iso:country":"US",
    "sg:address":"1885 S Highland Ave",
    "sg:city":"Clearwater",
    "sg:classifiers":[
        {
            "category":"Organizations",
            "subcategory":"Religious Organization",
            "type":"Services"
        }
    ],
    "sg:phone":"+1 727 584 1191",
    "sg:postcode":"33756",
    "sg:province":"FL",
    "sg:tags":[
        "church"
    ],
    "wof:name":"Highland Presbyterian Church",
    "wof:placetype":"venue"
},
  "geometry": {"coordinates":[-82.775014,27.92986],"type":"Point"}
}