{
  "type": "Feature",
  "properties": {
    "addr:full":"12500 SW 80th Ave Miami FL 33156",
    "addr:housenumber":"12500",
    "addr:postcode":"33156",
    "addr:street":"Sw 80Th Ave",
    "iso:country":"US",
    "sg:address":"12500 SW 80th Ave",
    "sg:city":"Miami",
    "sg:classifiers":[
        {
            "category":"Insurance",
            "subcategory":"Health Insurance",
            "type":"Services"
        }
    ],
    "sg:phone":"+1 305 238 9680",
    "sg:postcode":"33156",
    "sg:province":"FL",
    "sg:tags":[
        "life",
        "carrier",
        "carrie"
    ],
    "wof:name":"Pennsylvania Life Insurance Co",
    "wof:placetype":"venue"
},
  "geometry": {"coordinates":[-80.32403499999999,25.652905],"type":"Point"}
}