{
  "type": "Feature",
  "properties": {
    "iso:country":"US",
    "sg:address":"1820 Hawthorne Dr",
    "sg:city":"Vero Beach",
    "sg:classifiers":[
        {
            "category":"Health Services",
            "subcategory":"Clinic",
            "type":"Services"
        }
    ],
    "sg:phone":"+1 772 299 6326",
    "sg:postcode":"32962",
    "sg:province":"FL",
    "wof:name":"International Wellness",
    "wof:placetype":"venue"
},
  "geometry": {"coordinates":[-80.371162,27.569485],"type":"Point"}
}