{
  "type": "Feature",
  "properties": {
    "addr:full":"1224 Wellington Ter Maitland FL 32751",
    "addr:housenumber":"1224",
    "addr:postcode":"32751",
    "addr:street":"Wellington Ter",
    "iso:country":"US",
    "sg:address":"1224 Wellington Ter",
    "sg:city":"Maitland",
    "sg:classifiers":[
        {
            "category":"Professional",
            "subcategory":"Business Services",
            "type":"Services"
        }
    ],
    "sg:phone":"+1 407 331 1292",
    "sg:postcode":"32751",
    "sg:province":"FL",
    "wof:name":"J & S Enterprises of Maitland",
    "wof:placetype":"venue"
},
  "geometry": {"coordinates":[-81.34680299999999,28.640469],"type":"Point"}
}