{
  "type": "Feature",
  "properties": {
    "iso:country":"US",
    "sg:address":"1186 Bay Grove Rd",
    "sg:city":"Freeport",
    "sg:classifiers":[
        {
            "category":"Real Estate",
            "subcategory":"Real Estate Services",
            "type":"Services"
        }
    ],
    "sg:phone":"+1 850 835 4252",
    "sg:postcode":"32439",
    "sg:province":"FL",
    "sg:tags":[
        "information",
        "referral"
    ],
    "wof:name":"Eastern Lakes Estates Inc",
    "wof:placetype":"venue"
},
  "geometry": {"coordinates":[-86.15325300000001,30.453751],"type":"Point"}
}