{
  "type": "Feature",
  "properties": {
    "iso:country":"US",
    "sg:address":"19251 NE 26th Ave",
    "sg:city":"Miami",
    "sg:classifiers":[
        {
            "category":"Wholesale",
            "subcategory":"Computers",
            "type":"Manufacturing & Wholesale Goods"
        }
    ],
    "sg:phone":"+1 305 466 1197",
    "sg:postcode":"33125",
    "sg:province":"FL",
    "wof:name":"Compuscribe",
    "wof:placetype":"venue"
},
  "geometry": {"coordinates":[-80.233498,25.7815],"type":"Point"}
}