{
  "type": "Feature",
  "properties": {
    "iso:country":"US",
    "sg:address":"2404 Candado Ct",
    "sg:city":"Kissimmee",
    "sg:classifiers":[
        {
            "category":"Home & Garden",
            "subcategory":"Building Materials",
            "type":"Retail Goods"
        }
    ],
    "sg:phone":"+1 407 348 6522",
    "sg:postcode":"34743",
    "sg:province":"FL",
    "sg:tags":[
        "restroom",
        "supply"
    ],
    "wof:name":"Tissues & Toilettes Way",
    "wof:placetype":"venue"
},
  "geometry": {"coordinates":[-81.344987,28.314125],"type":"Point"}
}