{
  "type": "Feature",
  "properties": {
    "iso:country":"US",
    "sg:address":"8039 Mizner Ln",
    "sg:city":"Boca Raton",
    "sg:classifiers":[
        {
            "category":"Wholesale",
            "subcategory":"Electrical",
            "type":"Manufacturing & Wholesale Goods"
        }
    ],
    "sg:phone":"+1 561 218 0451",
    "sg:postcode":"33433",
    "sg:province":"FL",
    "sg:tags":[
        "electronic",
        "component",
        "broker"
    ],
    "wof:name":"Emergency Order Specialists",
    "wof:placetype":"venue"
},
  "geometry": {"coordinates":[-80.17508599999999,26.351266],"type":"Point"}
}