{
  "type": "Feature",
  "properties": {
    "iso:country":"US",
    "sg:address":"1508 Ledgestone Dr",
    "sg:city":"Brandon",
    "sg:classifiers":[
        {
            "category":"Shopping",
            "subcategory":"Computers & Home Electronics",
            "type":"Retail Goods"
        }
    ],
    "sg:phone":"+1 813 928 5453",
    "sg:postcode":"33511",
    "sg:province":"FL",
    "sg:tags":[
        "dvd",
        "sale"
    ],
    "wof:name":"York Video",
    "wof:placetype":"venue"
},
  "geometry": {"coordinates":[-82.303591,27.910506],"type":"Point"}
}