{
  "type": "Feature",
  "properties": {
    "addr:full":"1632 Feather Trl West Palm Beach FL 33411",
    "addr:housenumber":"1632",
    "addr:postcode":"33411",
    "addr:street":"Feather Trl",
    "iso:country":"US",
    "sg:address":"1632 Feather Trl",
    "sg:city":"West Palm Beach",
    "sg:classifiers":[
        {
            "category":"Building & Trades",
            "subcategory":"Construction",
            "type":"Services"
        }
    ],
    "sg:phone":"+1 561 640 8888",
    "sg:postcode":"33411",
    "sg:province":"FL",
    "sg:tags":[
        "mobile",
        "home"
    ],
    "wof:name":"Lirette's Aluminum",
    "wof:placetype":"venue"
},
  "geometry": {"coordinates":[-80.15257800000001,26.701851],"type":"Point"}
}