{
  "type": "Feature",
  "properties": {
    "addr:full":"47 Olive Cir Lp Ocala FL 34472",
    "addr:housenumber":"47",
    "addr:postcode":"34472",
    "addr:street":"Olive Cir",
    "iso:country":"US",
    "sg:address":"47 Olive Cir Lp",
    "sg:city":"Ocala",
    "sg:classifiers":[
        {
            "category":"Real Estate",
            "subcategory":"Real Estate Operator",
            "type":"Services"
        }
    ],
    "sg:phone":"+1 352 687 0167",
    "sg:postcode":"34472",
    "sg:province":"FL",
    "sg:tags":[
        "dwelling"
    ],
    "wof:name":"Kennedy Rentals",
    "wof:placetype":"venue"
},
  "geometry": {"coordinates":[-82.010324,29.066183],"type":"Point"}
}