{
  "type": "Feature",
  "properties": {
    "iso:country":"US",
    "sg:address":"11788 66th St N",
    "sg:city":"Largo",
    "sg:classifiers":[
        {
            "category":"Shopping",
            "type":"Retail Goods"
        }
    ],
    "sg:phone":"+1 727 546 0906",
    "sg:postcode":"33773",
    "sg:province":"FL",
    "sg:tags":[
        "factory",
        "outlet"
    ],
    "wof:name":"Star Outlet",
    "wof:placetype":"venue"
},
  "geometry": {"coordinates":[-82.729101,27.878726],"type":"Point"}
}