{
  "type": "Feature",
  "properties": {
    "iso:country":"US",
    "sg:address":"2059 NW 111th Loop",
    "sg:city":"Ocala",
    "sg:classifiers":[
        {
            "category":"Building & Trades",
            "subcategory":"Landscaping Services",
            "type":"Services"
        }
    ],
    "sg:phone":"+1 352 572 6904",
    "sg:postcode":"34475",
    "sg:province":"FL",
    "sg:tags":[
        "lawn",
        "maintenance",
        "grounds"
    ],
    "wof:name":"Ron Shellard Lawn Care",
    "wof:placetype":"venue"
},
  "geometry": {"coordinates":[-82.15937599999999,29.31526],"type":"Point"}
}