{
  "type": "Feature",
  "properties": {
    "iso:country":"US",
    "sg:address":"1311 Florida Mall Ave",
    "sg:city":"Orlando",
    "sg:classifiers":[
        {
            "category":"Restaurant",
            "type":"Food & Drink"
        }
    ],
    "sg:menulink":"http://www.allmenus.com/fl/orlando/29779-sushi-house/menu/",
    "sg:phone":"+1 407 812 9767",
    "sg:postcode":"32809",
    "sg:province":"FL",
    "sg:tags":[
        "sushi",
        "japanese",
        "asian"
    ],
    "wof:name":"Sushi House",
    "wof:placetype":"venue"
},
  "geometry": {"coordinates":[-81.39652,28.448783],"type":"Point"}
}