{
  "type": "Feature",
  "properties": {
    "iso:country":"US",
    "sg:address":"620 Birkdale Cir W",
    "sg:city":"Niceville",
    "sg:classifiers":[
        {
            "category":"Building & Trades",
            "subcategory":"Equipment Rental",
            "type":"Services"
        }
    ],
    "sg:phone":"+1 850 897 6549",
    "sg:postcode":"32578",
    "sg:province":"FL",
    "wof:name":"K & R Rentals LLC",
    "wof:placetype":"venue"
},
  "geometry": {"coordinates":[-86.437912,30.481882],"type":"Point"}
}