{
  "type": "Feature",
  "properties": {
    "iso:country":"US",
    "sg:address":"1125 12th St",
    "sg:city":"Vero Beach",
    "sg:classifiers":[
        {
            "category":"Real Estate",
            "subcategory":"Architect",
            "type":"Services"
        },
        {
            "category":"Professional",
            "subcategory":"Business Services",
            "type":"Services"
        }
    ],
    "sg:phone":"+1 772 567 5101",
    "sg:postcode":"32960",
    "sg:province":"FL",
    "sg:tags":[
        "architectural",
        "drafting"
    ],
    "sg:website":"www.customhouseplansofvero.com",
    "wof:name":"Custom House Plans of Vero",
    "wof:placetype":"venue"
},
  "geometry": {"coordinates":[-80.39471899999999,27.623389],"type":"Point"}
}