{
  "type": "Feature",
  "properties": {
    "iso:country":"US",
    "sg:address":"2850 Mine Mill Rd",
    "sg:city":"Lakeland",
    "sg:classifiers":[
        {
            "category":"Building & Trades",
            "subcategory":"Construction",
            "type":"Services"
        }
    ],
    "sg:phone":"+1 863 667 0400",
    "sg:postcode":"33801",
    "sg:province":"FL",
    "sg:tags":[
        "repairing",
        "remodeling",
        "contractor"
    ],
    "wof:name":"Install Services Inc",
    "wof:placetype":"venue"
},
  "geometry": {"coordinates":[-81.90314499999999,28.015484],"type":"Point"}
}