{
  "type": "Feature",
  "properties": {
    "addr:full":"2607 Davie Blvd Fort Lauderdale FL 33312",
    "addr:housenumber":"2607",
    "addr:postcode":"33312",
    "addr:street":"Davie Blvd",
    "iso:country":"US",
    "sg:address":"2607 Davie Blvd",
    "sg:city":"Fort Lauderdale",
    "sg:classifiers":[
        {
            "category":"Health Services",
            "subcategory":"Doctor",
            "type":"Services"
        }
    ],
    "sg:phone":"+1 954 587 7111",
    "sg:postcode":"33312",
    "sg:province":"FL",
    "wof:name":"J A Llera DDS",
    "wof:placetype":"venue"
},
  "geometry": {"coordinates":[-80.176783,26.10653],"type":"Point"}
}