{
  "type": "Feature",
  "properties": {
    "iso:country":"US",
    "sg:address":"825 S Bahama Dr",
    "sg:city":"Tallahassee",
    "sg:classifiers":[
        {
            "category":"Retail",
            "subcategory":"Portrait Studio",
            "type":"Services"
        }
    ],
    "sg:phone":"+1 850 877 5950",
    "sg:postcode":"32305",
    "sg:province":"FL",
    "sg:tags":[
        "photographer"
    ],
    "wof:name":"A J Studios",
    "wof:placetype":"venue"
},
  "geometry": {"coordinates":[-84.26517699999999,30.402787],"type":"Point"}
}