{
  "type": "Feature",
  "properties": {
    "iso:country":"US",
    "sg:address":"1943 Branchwater Trl",
    "sg:city":"Orlando",
    "sg:classifiers":[
        {
            "category":"Wholesale",
            "subcategory":"Books, Periodicals, & Newspapers",
            "type":"Manufacturing & Wholesale Goods"
        }
    ],
    "sg:phone":"+1 407 923 0841",
    "sg:postcode":"32825",
    "sg:province":"FL",
    "sg:tags":[
        "publishers-periodical"
    ],
    "sg:website":"http://www.fordsix.com",
    "wof:name":"Ford Six Performance",
    "wof:placetype":"venue"
},
  "geometry": {"coordinates":[-81.228031,28.516049],"type":"Point"}
}