{
  "type": "Feature",
  "properties": {
    "addr:full":"11401 NW 12th St Miami FL 33172",
    "addr:housenumber":"11401",
    "addr:postcode":"33172",
    "addr:street":"Nw 12Th St",
    "iso:country":"US",
    "sg:address":"11401 NW 12th St",
    "sg:city":"Miami",
    "sg:classifiers":[
        {
            "category":"Shopping",
            "subcategory":"Clothing, Apparel, & Fashions",
            "type":"Retail Goods"
        }
    ],
    "sg:phone":"+1 305 513 4557",
    "sg:postcode":"33172",
    "sg:province":"FL",
    "sg:tags":[
        "children's",
        "clothing"
    ],
    "wof:name":"Carter Children Wear",
    "wof:placetype":"venue"
},
  "geometry": {"coordinates":[-80.376503,25.782801],"type":"Point"}
}