{
  "type": "Feature",
  "properties": {
    "iso:country":"US",
    "sg:address":"10535 US Hwy 90",
    "sg:city":"Milton",
    "sg:classifiers":[
        {
            "category":"Food & Beverages",
            "subcategory":"Groceries & Convenience Stores",
            "type":"Retail Goods"
        }
    ],
    "sg:phone":"+1 850 983 1672",
    "sg:postcode":"32583",
    "sg:province":"FL",
    "sg:tags":[
        "merchandise",
        "general"
    ],
    "wof:name":"Harold Store",
    "wof:placetype":"venue"
},
  "geometry": {"coordinates":[-86.88548900000001,30.655869],"type":"Point"}
}