{
  "type": "Feature",
  "properties": {
    "iso:country":"US",
    "sg:address":"11492 SE Ella Ave",
    "sg:city":"Hobe Sound",
    "sg:classifiers":[
        {
            "category":"Building & Trades",
            "subcategory":"Landscaping Services",
            "type":"Services"
        }
    ],
    "sg:phone":"+1 772 546 6453",
    "sg:postcode":"33455",
    "sg:province":"FL",
    "wof:name":"Chad Snider Landscaping",
    "wof:placetype":"venue"
},
  "geometry": {"coordinates":[-80.131511,27.064069],"type":"Point"}
}