{
  "type": "Feature",
  "properties": {
    "iso:country":"US",
    "sg:address":"9991 NE 118th Ter",
    "sg:city":"Bronson",
    "sg:classifiers":[
        {
            "category":"Building & Trades",
            "subcategory":"Plumbing",
            "type":"Services"
        }
    ],
    "sg:phone":"+1 352 486 3509",
    "sg:postcode":"32621",
    "sg:province":"FL",
    "sg:tags":[
        "plumbing",
        "contractor"
    ],
    "wof:name":"A & M Plumbing Svc",
    "wof:placetype":"venue"
},
  "geometry": {"coordinates":[-82.57536500000001,29.479304],"type":"Point"}
}