{
  "type": "Feature",
  "properties": {
    "iso:country":"US",
    "sg:address":"519 N Howard Ave",
    "sg:city":"Tampa",
    "sg:classifiers":[
        {
            "category":"Professional",
            "subcategory":"Research",
            "type":"Services"
        }
    ],
    "sg:phone":"+1 813 258 5561",
    "sg:postcode":"33606",
    "sg:province":"FL",
    "sg:tags":[
        "environmental",
        "ecological"
    ],
    "sg:website":"www.streamlineenv.com",
    "wof:name":"Streamline Environmental",
    "wof:placetype":"venue"
},
  "geometry": {"coordinates":[-82.48291500000001,27.949022],"type":"Point"}
}