{
  "type": "Feature",
  "properties": {
    "iso:country":"US",
    "sg:address":"1535 N Park Dr",
    "sg:city":"Weston",
    "sg:classifiers":[
        {
            "category":"Professional",
            "subcategory":"Lawyer & Legal Services",
            "type":"Services"
        }
    ],
    "sg:phone":"+1 954 389 5719",
    "sg:postcode":"33326",
    "sg:province":"FL",
    "sg:tags":[
        "attorney",
        "practice"
    ],
    "wof:name":"Brad E. Coren, P.A.",
    "wof:placetype":"venue"
},
  "geometry": {"coordinates":[-80.364395,26.099344],"type":"Point"}
}