{
  "type": "Feature",
  "properties": {
    "addr:full":"1710 NW 17th Ave Miami FL 33125",
    "addr:housenumber":"1710",
    "addr:postcode":"33125",
    "addr:street":"Nw 17Th Ave",
    "iso:country":"US",
    "sg:address":"1710 NW 17th Ave",
    "sg:city":"Miami",
    "sg:classifiers":[
        {
            "category":"Building & Trades",
            "subcategory":"Locksmith",
            "type":"Services"
        }
    ],
    "sg:phone":"+1 305 260 6764",
    "sg:postcode":"33125",
    "sg:province":"FL",
    "sg:tags":[
        "key"
    ],
    "wof:name":"1 24 Hour Emergency Locksmith",
    "wof:placetype":"venue"
},
  "geometry": {"coordinates":[-80.223298,25.791216],"type":"Point"}
}