{
  "type": "Feature",
  "properties": {
    "iso:country":"US",
    "sg:address":"3387 W Silver Springs Blvd",
    "sg:city":"Ocala",
    "sg:classifiers":[
        {
            "category":"Retail",
            "subcategory":"Auto Repair",
            "type":"Services"
        }
    ],
    "sg:phone":"+1 352 867 9617",
    "sg:postcode":"34475",
    "sg:province":"FL",
    "sg:tags":[
        "automotive"
    ],
    "wof:name":"Exact Fit",
    "wof:placetype":"venue"
},
  "geometry": {"coordinates":[-82.177646,29.186474],"type":"Point"}
}