{
  "type": "Feature",
  "properties": {
    "addr:full":"3644 NW 16th St Lauderhill FL 33311",
    "addr:housenumber":"3644",
    "addr:postcode":"33311",
    "addr:street":"Nw 16Th St",
    "iso:country":"US",
    "sg:address":"3644 NW 16th St",
    "sg:city":"Lauderhill",
    "sg:classifiers":[
        {
            "category":"Building & Trades",
            "subcategory":"Construction",
            "type":"Services"
        }
    ],
    "sg:phone":"+1 954 791 4111",
    "sg:postcode":"33311",
    "sg:province":"FL",
    "sg:tags":[
        "repair",
        "system",
        "ventilating",
        "contractor",
        "air conditioning"
    ],
    "wof:name":"Ductmasters Usa",
    "wof:placetype":"venue"
},
  "geometry": {"coordinates":[-80.19927300000001,26.146187],"type":"Point"}
}