{
  "type": "Feature",
  "properties": {
    "iso:country":"US",
    "sg:address":"1909 Adamo Dr",
    "sg:city":"Tampa",
    "sg:classifiers":[
        {
            "category":"Autos & Motor Vehicles",
            "subcategory":"Fuel & Gas Station",
            "type":"Retail Goods"
        }
    ],
    "sg:phone":"+1 813 248 2725",
    "sg:postcode":"33605",
    "sg:province":"FL",
    "sg:tags":[
        "station"
    ],
    "wof:name":"Citgo",
    "wof:placetype":"venue"
},
  "geometry": {"coordinates":[-82.435597,27.955696],"type":"Point"}
}