{
  "type": "Feature",
  "properties": {
    "iso:country":"US",
    "sg:address":"6680 Dillman Rd",
    "sg:city":"Greenacres",
    "sg:classifiers":[
        {
            "category":"Education",
            "subcategory":"School",
            "type":"Public Place"
        }
    ],
    "sg:phone":"+1 561 681 2200",
    "sg:postcode":"33413",
    "sg:province":"FL",
    "wof:name":"Cholee Lake Elementary School",
    "wof:placetype":"venue"
},
  "geometry": {"coordinates":[-80.154342,26.662209],"type":"Point"}
}