{
  "type": "Feature",
  "properties": {
    "iso:country":"US",
    "sg:address":"1588 N Tamiami Trl",
    "sg:city":"Fort Myers",
    "sg:classifiers":[
        {
            "category":"Autos & Motor Vehicles",
            "subcategory":"Boat Sales",
            "type":"Retail Goods"
        }
    ],
    "sg:phone":"+1 239 997 9299",
    "sg:postcode":"33903",
    "sg:province":"FL",
    "sg:tags":[
        "repair",
        "dealer",
        "sales"
    ],
    "wof:name":"G & J's Boats",
    "wof:placetype":"venue"
},
  "geometry": {"coordinates":[-81.883042,26.676683],"type":"Point"}
}