{
  "type": "Feature",
  "properties": {
    "addr:full":"1177 W 35th St Hialeah FL 33012",
    "addr:housenumber":"1177",
    "addr:postcode":"33012",
    "addr:street":"W 35Th St",
    "iso:country":"US",
    "sg:address":"1177 W 35th St",
    "sg:city":"Hialeah",
    "sg:classifiers":[
        {
            "category":"Food & Beverages",
            "subcategory":"Groceries & Convenience Stores",
            "type":"Retail Goods"
        }
    ],
    "sg:phone":"+1 305 820 3926",
    "sg:postcode":"33012",
    "sg:province":"FL",
    "sg:tags":[
        "product"
    ],
    "wof:name":"Sarana Food",
    "wof:placetype":"venue"
},
  "geometry": {"coordinates":[-80.30506200000001,25.853611],"type":"Point"}
}