{
  "type": "Feature",
  "properties": {
    "addr:full":"15795 Rhodes Rd Clearwater FL 33760",
    "addr:housenumber":"15795",
    "addr:postcode":"33760",
    "addr:street":"Rhodes Rd",
    "iso:country":"US",
    "sg:address":"15795 Rhodes Rd",
    "sg:city":"Clearwater",
    "sg:classifiers":[
        {
            "category":"Building & Trades",
            "subcategory":"Construction",
            "type":"Services"
        }
    ],
    "sg:phone":"+1 727 539 0765",
    "sg:postcode":"33760",
    "sg:province":"FL",
    "sg:tags":[
        "floor",
        "laying",
        "contractor"
    ],
    "wof:name":"Gary Hoover",
    "wof:placetype":"venue"
},
  "geometry": {"coordinates":[-82.707846,27.915483],"type":"Point"}
}