{
  "type": "Feature",
  "properties": {
    "addr:full":"1840 N 56th Ave Hollywood FL 33021",
    "addr:housenumber":"1840",
    "addr:postcode":"33021",
    "addr:street":"N 56Th Ave",
    "iso:country":"US",
    "sg:address":"1840 N 56th Ave",
    "sg:city":"Hollywood",
    "sg:classifiers":[
        {
            "category":"Building & Trades",
            "subcategory":"Electrical",
            "type":"Services"
        }
    ],
    "sg:phone":"+1 954 893 6843",
    "sg:postcode":"33021",
    "sg:province":"FL",
    "sg:tags":[
        "electrical",
        "contractor"
    ],
    "wof:name":"Energy 2000 of USA Inc",
    "wof:placetype":"venue"
},
  "geometry": {"coordinates":[-80.20017900000001,26.025576],"type":"Point"}
}