{
  "type": "Feature",
  "properties": {
    "iso:country":"US",
    "sg:address":"1200 Circle Dr",
    "sg:city":"Defuniak Springs",
    "sg:classifiers":[
        {
            "category":"Health Services",
            "subcategory":"Hospital",
            "type":"Services"
        },
        {
            "category":"Health Services",
            "subcategory":"Clinic",
            "type":"Services"
        }
    ],
    "sg:phone":"+1 850 951 0037",
    "sg:postcode":"32435",
    "sg:province":"FL",
    "sg:tags":[
        "mental",
        "outpatient",
        "specialty"
    ],
    "wof:name":"Resources For Human Dev",
    "wof:placetype":"venue"
},
  "geometry": {"coordinates":[-86.11596900000001,30.718443],"type":"Point"}
}