{
  "type": "Feature",
  "properties": {
    "iso:country":"US",
    "sg:address":"14113 NW 19th Ave",
    "sg:city":"Opa Locka",
    "sg:classifiers":[
        {
            "category":"Retail",
            "subcategory":"Auto Repair",
            "type":"Services"
        }
    ],
    "sg:phone":"+1 305 681 8129",
    "sg:postcode":"33054",
    "sg:province":"FL",
    "sg:tags":[
        "wrecker"
    ],
    "wof:name":"Service One Towing",
    "wof:placetype":"venue"
},
  "geometry": {"coordinates":[-80.231593,25.904708],"type":"Point"}
}