{
  "type": "Feature",
  "properties": {
    "iso:country":"US",
    "sg:address":"8897 SW 129th Ter",
    "sg:city":"Miami",
    "sg:classifiers":[
        {
            "category":"Building & Trades",
            "subcategory":"Construction",
            "type":"Services"
        }
    ],
    "sg:phone":"+1 305 232 1527",
    "sg:postcode":"33176",
    "sg:province":"FL",
    "sg:tags":[
        "painting",
        "painter",
        "contractor"
    ],
    "wof:name":"Summers Professional Painting",
    "wof:placetype":"venue"
},
  "geometry": {"coordinates":[-80.33820299999999,25.6495],"type":"Point"}
}