{
  "type": "Feature",
  "properties": {
    "iso:country":"US",
    "sg:address":"882 Gardenia Ln",
    "sg:city":"Fort Lauderdale",
    "sg:classifiers":[
        {
            "category":"Professional",
            "subcategory":"Business Services",
            "type":"Services"
        }
    ],
    "sg:phone":"+1 954 321 8014",
    "sg:postcode":"33317",
    "sg:province":"FL",
    "wof:name":"Steven Deleon Enterprises Inc",
    "wof:placetype":"venue"
},
  "geometry": {"coordinates":[-80.225025,26.132448],"type":"Point"}
}