{
  "type": "Feature",
  "properties": {
    "addr:full":"12971 Tyler Run Ave Odessa FL 33556",
    "addr:housenumber":"12971",
    "addr:postcode":"33556",
    "addr:street":"Tyler Run Ave",
    "iso:country":"US",
    "sg:address":"12971 Tyler Run Ave",
    "sg:city":"Odessa",
    "sg:classifiers":[
        {
            "category":"Farming",
            "subcategory":"Livestock Farm",
            "type":"Manufacturing & Wholesale Goods"
        },
        {
            "category":"Farming",
            "subcategory":"Farm & Veterinary Services",
            "type":"Manufacturing & Wholesale Goods"
        }
    ],
    "sg:phone":"+1 813 792 7111",
    "sg:postcode":"33556",
    "sg:province":"FL",
    "sg:tags":[
        "breeder"
    ],
    "wof:name":"Noah's Ark On Wheels",
    "wof:placetype":"venue"
},
  "geometry": {"coordinates":[-82.640908,28.151341],"type":"Point"}
}