{
  "type": "Feature",
  "properties": {
    "iso:country":"US",
    "sg:address":"6257 Swan Ln",
    "sg:city":"Spring Hill",
    "sg:classifiers":[
        {
            "category":"Local Transit",
            "type":"Transportation"
        }
    ],
    "sg:phone":"+1 352 592 1011",
    "sg:postcode":"34608",
    "sg:province":"FL",
    "sg:tags":[
        "passenger"
    ],
    "wof:name":"Deluxe Rainbow Limousine",
    "wof:placetype":"venue"
},
  "geometry": {"coordinates":[-82.56047100000001,28.521349],"type":"Point"}
}