{
  "type": "Feature",
  "properties": {
    "addr:full":"1267 Cutlass Rd Orange Park FL 32065",
    "addr:housenumber":"1267",
    "addr:postcode":"32065",
    "addr:street":"Cutlass Rd",
    "iso:country":"US",
    "sg:address":"1267 Cutlass Rd",
    "sg:city":"Orange Park",
    "sg:classifiers":[
        {
            "category":"Autos & Motor Vehicles",
            "subcategory":"Automobile Sales",
            "type":"Retail Goods"
        }
    ],
    "sg:phone":"+1 904 276 6126",
    "sg:postcode":"32065",
    "sg:province":"FL",
    "sg:tags":[
        "used"
    ],
    "wof:name":"Cars Etc Inc",
    "wof:placetype":"venue"
},
  "geometry": {"coordinates":[-81.799145,30.132906],"type":"Point"}
}