{
  "type": "Feature",
  "properties": {
    "addr:full":"2303 N Congress Ave Boynton Beach FL 33426",
    "addr:housenumber":"2303",
    "addr:postcode":"33426",
    "addr:street":"N Congress Ave",
    "iso:country":"US",
    "sg:address":"2303 N Congress Ave",
    "sg:city":"Boynton Beach",
    "sg:classifiers":[
        {
            "category":"Manufacturing",
            "subcategory":"Signs",
            "type":"Manufacturing & Wholesale Goods"
        }
    ],
    "sg:phone":"+1 561 541 4466",
    "sg:postcode":"33426",
    "sg:province":"FL",
    "sg:tags":[
        "advertising",
        "specialty"
    ],
    "wof:name":"Sign Gallery Inc",
    "wof:placetype":"venue"
},
  "geometry": {"coordinates":[-80.090735,26.549002],"type":"Point"}
}