{
  "type": "Feature",
  "properties": {
    "addr:full":"5 Cordova St St Augustine FL 32084",
    "addr:housenumber":"5",
    "addr:postcode":"32084",
    "addr:street":"Cordova St",
    "iso:country":"US",
    "sg:address":"5 Cordova St",
    "sg:city":"St Augustine",
    "sg:classifiers":[
        {
            "category":"Professional",
            "subcategory":"Advertising",
            "type":"Services"
        }
    ],
    "sg:phone":"+1 904 825 4573",
    "sg:postcode":"32084",
    "sg:province":"FL",
    "sg:tags":[
        "counselor"
    ],
    "wof:name":"Mc Intosh & Talented Assoc",
    "wof:placetype":"venue"
},
  "geometry": {"coordinates":[-81.31474799999999,29.897388],"type":"Point"}
}