{
  "type": "Feature",
  "properties": {
    "iso:country":"US",
    "sg:address":"1108 Cornell Dr",
    "sg:city":"Sanford",
    "sg:classifiers":[
        {
            "category":"Building & Trades",
            "subcategory":"Cleaning & Sanitation",
            "type":"Services"
        }
    ],
    "sg:phone":"+1 407 321 4114",
    "sg:postcode":"32771",
    "sg:province":"FL",
    "sg:tags":[
        "house"
    ],
    "wof:name":"Denise Knudsen Cleaning",
    "wof:placetype":"venue"
},
  "geometry": {"coordinates":[-81.25634599999999,28.792502],"type":"Point"}
}