{
  "type": "Feature",
  "properties": {
    "iso:country":"US",
    "sg:address":"1402 Pineland Dr",
    "sg:city":"Bainbridge",
    "sg:classifiers":[
        {
            "category":"Travel",
            "subcategory":"Campground",
            "type":"Entertainment"
        }
    ],
    "sg:phone":"+1 229 246 5802",
    "sg:postcode":"39819",
    "sg:province":"FL",
    "wof:name":"Place To Be Rv Park",
    "wof:placetype":"venue"
},
  "geometry": {"coordinates":[-84.555626,30.890721],"type":"Point"}
}