{
  "type": "Feature",
  "properties": {
    "addr:full":"811 NE 125th St North Miami FL 33161",
    "addr:housenumber":"811",
    "addr:postcode":"33161",
    "addr:street":"Ne 125Th St",
    "iso:country":"US",
    "sg:address":"811 NE 125th St",
    "sg:city":"North Miami",
    "sg:classifiers":[
        {
            "category":"Recreation",
            "type":"Entertainment"
        }
    ],
    "sg:phone":"+1 305 899 4855",
    "sg:postcode":"33161",
    "sg:province":"FL",
    "sg:tags":[
        "martial",
        "arts",
        "instruction"
    ],
    "wof:name":"Institute Of Combat Science",
    "wof:placetype":"venue"
},
  "geometry": {"coordinates":[-80.180588,25.890596],"type":"Point"}
}