{
  "type": "Feature",
  "properties": {
    "iso:country":"US",
    "sg:address":"4526 Pine Hollow Dr",
    "sg:city":"Tampa",
    "sg:classifiers":[
        {
            "category":"Communications",
            "subcategory":"Film & Video Production",
            "type":"Services"
        }
    ],
    "sg:phone":"+1 813 973 7575",
    "sg:postcode":"33624",
    "sg:province":"FL",
    "sg:tags":[
        "services-commercial"
    ],
    "sg:website":"http://www.realtimetelevision.com",
    "wof:name":"Realtime Productions",
    "wof:placetype":"venue"
},
  "geometry": {"coordinates":[-82.51919100000001,28.06436],"type":"Point"}
}