{
  "type": "Feature",
  "properties": {
    "addr:full":"7813 Snapping Turtle Ct Hudson FL 34667",
    "addr:housenumber":"7813",
    "addr:postcode":"34667",
    "addr:street":"Snapping Turtle Ct",
    "iso:country":"US",
    "sg:address":"7813 Snapping Turtle Ct",
    "sg:city":"Hudson",
    "sg:classifiers":[
        {
            "category":"Building & Trades",
            "subcategory":"Construction",
            "type":"Services"
        }
    ],
    "sg:phone":"+1 727 868 3463",
    "sg:postcode":"34667",
    "sg:province":"FL",
    "sg:tags":[
        "builder",
        "patio",
        "deck"
    ],
    "wof:name":"Natural Floors",
    "wof:placetype":"venue"
},
  "geometry": {"coordinates":[-82.683674,28.353675],"type":"Point"}
}