{
  "type": "Feature",
  "properties": {
    "iso:country":"US",
    "sg:address":"3701 Sabal Palm Blvd",
    "sg:city":"Fort Myers",
    "sg:classifiers":[
        {
            "category":"Manufacturing",
            "subcategory":"Printing",
            "type":"Manufacturing & Wholesale Goods"
        }
    ],
    "sg:phone":"+1 239 334 6399",
    "sg:postcode":"33916",
    "sg:province":"FL",
    "sg:tags":[
        "multimedia"
    ],
    "wof:name":"Neilsen Media Research",
    "wof:placetype":"venue"
},
  "geometry": {"coordinates":[-81.83849499999999,26.643934],"type":"Point"}
}