{
  "type": "Feature",
  "properties": {
    "iso:country":"US",
    "sg:address":"705 Bond Way",
    "sg:city":"Boynton Beach",
    "sg:classifiers":[
        {
            "category":"Building & Trades",
            "subcategory":"Electrical",
            "type":"Services"
        }
    ],
    "sg:phone":"+1 561 738 1892",
    "sg:postcode":"33483",
    "sg:province":"FL",
    "sg:tags":[
        "electric",
        "contractor"
    ],
    "wof:name":"Jennings Electric",
    "wof:placetype":"venue"
},
  "geometry": {"coordinates":[-80.065395,26.477423],"type":"Point"}
}