{
  "type": "Feature",
  "properties": {
    "iso:country":"US",
    "sg:address":"3191 Coral Way Ste 303",
    "sg:city":"Coral Gables",
    "sg:classifiers":[
        {
            "category":"Health Services",
            "subcategory":"Doctor",
            "type":"Services"
        }
    ],
    "sg:phone":"+1 305 443 8988",
    "sg:postcode":"33145",
    "sg:province":"FL",
    "wof:name":"I Mg International Medical Group Inc",
    "wof:placetype":"venue"
},
  "geometry": {"coordinates":[-80.246399,25.7502],"type":"Point"}
}