{
  "type": "Feature",
  "properties": {
    "iso:country":"US",
    "sg:address":"2720 Rebecca Ln",
    "sg:city":"Orange City",
    "sg:classifiers":[
        {
            "category":"Health Services",
            "subcategory":"Doctor",
            "type":"Services"
        }
    ],
    "sg:phone":"+1 386 456 1160",
    "sg:postcode":"32763",
    "sg:province":"FL",
    "wof:name":"Pain Medicine Prc Associates",
    "wof:placetype":"venue"
},
  "geometry": {"coordinates":[-81.291901,28.9072],"type":"Point"}
}