{
  "type": "Feature",
  "properties": {
    "iso:country":"US",
    "sg:address":"802 Golden Pond Ct",
    "sg:city":"Orlando",
    "sg:classifiers":[
        {
            "category":"Manufacturing",
            "subcategory":"Toys & Sporting Goods",
            "type":"Manufacturing & Wholesale Goods"
        }
    ],
    "sg:phone":"+1 407 273 2888",
    "sg:postcode":"32828",
    "sg:province":"FL",
    "sg:tags":[
        "mfg"
    ],
    "wof:name":"Adoptables",
    "wof:placetype":"venue"
},
  "geometry": {"coordinates":[-81.179705,28.546139],"type":"Point"}
}