{
  "type": "Feature",
  "properties": {
    "iso:country":"US",
    "sg:address":"130 Nottoway Trl",
    "sg:city":"Maitland",
    "sg:classifiers":[
        {
            "category":"Banks & Credit Unions",
            "subcategory":"Investment Brokerage",
            "type":"Services"
        }
    ],
    "sg:phone":"+1 407 645 1061",
    "sg:postcode":"32751",
    "sg:province":"FL",
    "sg:tags":[
        "advisory"
    ],
    "wof:name":"Paul Lilling Business Services",
    "wof:placetype":"venue"
},
  "geometry": {"coordinates":[-81.38014200000001,28.626046],"type":"Point"}
}