{
  "type": "Feature",
  "properties": {
    "iso:country":"US",
    "sg:address":"1600 NW 63rd St",
    "sg:city":"Ocala",
    "sg:classifiers":[
        {
            "category":"Wholesale",
            "subcategory":"Machinery & Supplies",
            "type":"Manufacturing & Wholesale Goods"
        }
    ],
    "sg:phone":"+1 352 732 2800",
    "sg:postcode":"34475",
    "sg:province":"FL",
    "sg:tags":[
        "equipment",
        "industrial"
    ],
    "wof:name":"Ring Used Parts",
    "wof:placetype":"venue"
},
  "geometry": {"coordinates":[-82.16049,29.252333],"type":"Point"}
}