{
  "type": "Feature",
  "properties": {
    "iso:country":"US",
    "sg:address":"8010 SW Jack James Dr",
    "sg:city":"Stuart",
    "sg:classifiers":[
        {
            "category":"Wholesale",
            "subcategory":"Construction Materials",
            "type":"Manufacturing & Wholesale Goods"
        }
    ],
    "sg:phone":"+1 772 463 8535",
    "sg:postcode":"34997",
    "sg:province":"FL",
    "sg:tags":[
        "molding"
    ],
    "wof:name":"Distinctive Molding",
    "wof:placetype":"venue"
},
  "geometry": {"coordinates":[-80.267585,27.110608],"type":"Point"}
}