{
  "type": "Feature",
  "properties": {
    "iso:country":"US",
    "sg:address":"4355 Dow Rd",
    "sg:city":"Melbourne",
    "sg:classifiers":[
        {
            "category":"Building & Trades",
            "subcategory":"Construction",
            "type":"Services"
        }
    ],
    "sg:phone":"+1 321 752 7035",
    "sg:postcode":"32934",
    "sg:province":"FL",
    "sg:tags":[
        "handyman"
    ],
    "wof:name":"Donald Lachappelle Contractor",
    "wof:placetype":"venue"
},
  "geometry": {"coordinates":[-80.699063,28.10738],"type":"Point"}
}