{
  "type": "Feature",
  "properties": {
    "addr:full":"2136 Glenridge Dr Spring Hill FL 34609",
    "addr:housenumber":"2136",
    "addr:postcode":"34609",
    "addr:street":"Glenridge Dr",
    "iso:country":"US",
    "sg:address":"2136 Glenridge Dr",
    "sg:city":"Spring Hill",
    "sg:classifiers":[
        {
            "category":"Retail",
            "subcategory":"Auto Repair",
            "type":"Services"
        }
    ],
    "sg:phone":"+1 352 683 4868",
    "sg:postcode":"34609",
    "sg:province":"FL",
    "sg:tags":[
        "general"
    ],
    "wof:name":"Z Automotive Concepts Inc",
    "wof:placetype":"venue"
},
  "geometry": {"coordinates":[-82.51833499999999,28.462238],"type":"Point"}
}