{
  "type": "Feature",
  "properties": {
    "iso:country":"US",
    "sg:address":"37 NW 50th St",
    "sg:city":"Miami",
    "sg:classifiers":[
        {
            "category":"Professional",
            "subcategory":"Business Services",
            "type":"Services"
        }
    ],
    "sg:phone":"+1 305 757 9006",
    "sg:postcode":"33127",
    "sg:province":"FL",
    "sg:tags":[
        "interior",
        "consultant",
        "design",
        "decorator"
    ],
    "wof:name":"Gingerbread Design Group",
    "wof:placetype":"venue"
},
  "geometry": {"coordinates":[-80.197132,25.82161],"type":"Point"}
}