{
  "type": "Feature",
  "properties": {
    "addr:full":"6801 Gulfport Blvd S Saint Petersburg FL 33707",
    "addr:housenumber":"6801",
    "addr:postcode":"33707",
    "addr:street":"Gulfport Blvd S",
    "iso:country":"US",
    "sg:address":"6801 Gulfport Blvd S",
    "sg:city":"Saint Petersburg",
    "sg:classifiers":[
        {
            "category":"Restaurant",
            "type":"Food & Drink"
        }
    ],
    "sg:phone":"+1 727 381 1206",
    "sg:postcode":"33707",
    "sg:province":"FL",
    "wof:name":"Spiros Family Restaurant Inc",
    "wof:placetype":"venue"
},
  "geometry": {"coordinates":[-82.73605999999999,27.759259],"type":"Point"}
}