{
  "type": "Feature",
  "properties": {
    "iso:country":"US",
    "sg:address":"3501 Burris Rd",
    "sg:city":"Davie",
    "sg:classifiers":[
        {
            "category":"Manufacturing",
            "subcategory":"Building Materials",
            "type":"Manufacturing & Wholesale Goods"
        }
    ],
    "sg:phone":"+1 954 791 8200",
    "sg:postcode":"33314",
    "sg:province":"FL",
    "sg:tags":[
        "concrete",
        "products-wholesale",
        "manufacturer"
    ],
    "wof:name":"Filigree Wideslab Of Florida Inc",
    "wof:placetype":"venue"
},
  "geometry": {"coordinates":[-80.20854,26.078704],"type":"Point"}
}