{
  "type": "Feature",
  "properties": {
    "iso:country":"US",
    "sg:address":"3383 NW 7th St",
    "sg:city":"Miami",
    "sg:classifiers":[
        {
            "category":"Community Center",
            "type":"Public Place"
        }
    ],
    "sg:phone":"+1 305 642 9340",
    "sg:postcode":"33125",
    "sg:province":"FL",
    "sg:tags":[
        "medical"
    ],
    "wof:name":"C & D Medical Center Inc",
    "wof:placetype":"venue"
},
  "geometry": {"coordinates":[-80.251099,25.7791],"type":"Point"}
}