{
  "type": "Feature",
  "properties": {
    "iso:country":"US",
    "sg:address":"565 US Hwy 41 S",
    "sg:city":"Inverness",
    "sg:classifiers":[
        {
            "category":"Real Estate",
            "subcategory":"Real Estate Agent",
            "type":"Services"
        }
    ],
    "sg:phone":"+1 352 726 6644",
    "sg:postcode":"34450",
    "sg:province":"FL",
    "wof:name":"Crossland Realty Inc",
    "wof:placetype":"venue"
},
  "geometry": {"coordinates":[-82.32028699999999,28.82751],"type":"Point"}
}