{
  "type": "Feature",
  "properties": {
    "iso:country":"US",
    "sg:address":"1819 NE 6th St",
    "sg:city":"Ocala",
    "sg:classifiers":[
        {
            "category":"Wholesale",
            "subcategory":"Machinery & Supplies",
            "type":"Manufacturing & Wholesale Goods"
        }
    ],
    "sg:phone":"+1 352 622 2621",
    "sg:postcode":"34470",
    "sg:province":"FL",
    "sg:tags":[
        "cleaning"
    ],
    "wof:name":"Chinese Connection Pressure",
    "wof:placetype":"venue"
},
  "geometry": {"coordinates":[-82.110223,29.193278],"type":"Point"}
}