{
  "type": "Feature",
  "properties": {
    "iso:country":"US",
    "sg:address":"2582 N Miami Ave",
    "sg:city":"Miami",
    "sg:classifiers":[
        {
            "category":"Real Estate",
            "subcategory":"Real Estate Agent",
            "type":"Services"
        }
    ],
    "sg:phone":"+1 305 937 4995",
    "sg:postcode":"33127",
    "sg:province":"FL",
    "wof:name":"C N Group Properties",
    "wof:placetype":"venue"
},
  "geometry": {"coordinates":[-80.19508,25.800981],"type":"Point"}
}