{
  "type": "Feature",
  "properties": {
    "iso:country":"US",
    "sg:address":"333 E Nasa Blvd",
    "sg:city":"Melbourne",
    "sg:classifiers":[
        {
            "category":"Banks & Credit Unions",
            "subcategory":"Bank",
            "type":"Services"
        }
    ],
    "sg:phone":"+1 321 690 2328",
    "sg:postcode":"32901",
    "sg:province":"FL",
    "wof:name":"Community Educators Cu",
    "wof:placetype":"venue"
},
  "geometry": {"coordinates":[-80.616787,28.093209],"type":"Point"}
}