{
  "type": "Feature",
  "properties": {
    "iso:country":"US",
    "sg:address":"8725 SW 32nd St",
    "sg:city":"Miami",
    "sg:classifiers":[
        {
            "category":"Organizations",
            "subcategory":"Religious Organization",
            "type":"Services"
        }
    ],
    "sg:phone":"+1 305 221 2722",
    "sg:postcode":"33165",
    "sg:province":"FL",
    "wof:name":"St Brendan Catholic Church",
    "wof:placetype":"venue"
},
  "geometry": {"coordinates":[-80.338097,25.7402],"type":"Point"}
}