{
  "type": "Feature",
  "properties": {
    "addr:full":"333 W 41st St Miami Beach FL 33140",
    "addr:housenumber":"333",
    "addr:postcode":"33140",
    "addr:street":"W 41St St",
    "iso:country":"US",
    "sg:address":"333 W 41st St",
    "sg:city":"Miami Beach",
    "sg:classifiers":[
        {
            "category":"Health Services",
            "subcategory":"Doctor",
            "type":"Services"
        },
        {
            "category":"Health Services",
            "subcategory":"Dentist",
            "type":"Services"
        }
    ],
    "sg:phone":"+1 305 567 2772",
    "sg:postcode":"33140",
    "sg:province":"FL",
    "sg:tags":[
        "surgeon",
        "oral",
        "orthodontist"
    ],
    "wof:name":"Zambrano & Crabill Orthodontics DDS",
    "wof:placetype":"venue"
},
  "geometry": {"coordinates":[-80.127206,25.81406],"type":"Point"}
}