{
  "type": "Feature",
  "properties": {
    "iso:country":"US",
    "sg:address":"350 7th St N",
    "sg:city":"Naples",
    "sg:classifiers":[
        {
            "category":"Health Services",
            "subcategory":"Doctor",
            "type":"Services"
        }
    ],
    "sg:phone":"+1 239 436 5400",
    "sg:postcode":"34102",
    "sg:province":"FL",
    "sg:tags":[
        "clinic"
    ],
    "wof:name":"Sleep Medicine Ctr",
    "wof:placetype":"venue"
},
  "geometry": {"coordinates":[-81.799555,26.15137],"type":"Point"}
}