{
  "type": "Feature",
  "properties": {
    "addr:full":"9967 Glades Rd Boca Raton FL 33434",
    "addr:housenumber":"9967",
    "addr:postcode":"33434",
    "addr:street":"Glades Rd",
    "iso:country":"US",
    "sg:address":"9967 Glades Rd",
    "sg:city":"Boca Raton",
    "sg:classifiers":[
        {
            "category":"Restaurant",
            "type":"Food & Drink"
        }
    ],
    "sg:menulink":"http://www.allmenus.com/fl/sunshine-parkway/246551-brooklyn-boys/menu/",
    "sg:phone":"+1 561 477 3663",
    "sg:postcode":"33434",
    "sg:province":"FL",
    "sg:tags":[
        "american",
        "pizza"
    ],
    "wof:name":"Brooklyn Boys",
    "wof:placetype":"venue"
},
  "geometry": {"coordinates":[-80.202754,26.368025],"type":"Point"}
}