{
  "type": "Feature",
  "properties": {
    "iso:country":"US",
    "sg:address":"8301 NW 12th St",
    "sg:city":"Doral",
    "sg:classifiers":[
        {
            "category":"Health Services",
            "subcategory":"Hospital",
            "type":"Services"
        }
    ],
    "sg:phone":"+1 786 596 3860",
    "sg:postcode":"33126",
    "sg:province":"FL",
    "wof:name":"Baptist Health Center At Beacon",
    "wof:placetype":"venue"
},
  "geometry": {"coordinates":[-80.330399,25.7826],"type":"Point"}
}