{
  "type": "Feature",
  "properties": {
    "iso:country":"US",
    "sg:address":"1580 N Dale Mabry Hwy",
    "sg:city":"Tampa",
    "sg:classifiers":[
        {
            "category":"Restaurant",
            "type":"Food & Drink"
        }
    ],
    "sg:phone":"+1 813 873 2878",
    "sg:postcode":"33607",
    "sg:province":"FL",
    "wof:name":"Romano's Macaroni Grill",
    "wof:placetype":"venue"
},
  "geometry": {"coordinates":[-82.505645,27.957858],"type":"Point"}
}