{
  "type": "Feature",
  "properties": {
    "addr:full":"8886 Pine Forest Rd Pensacola FL 32534",
    "addr:housenumber":"8886",
    "addr:postcode":"32534",
    "addr:street":"Pine Forest Rd",
    "iso:country":"US",
    "sg:address":"8886 Pine Forest Rd",
    "sg:city":"Pensacola",
    "sg:classifiers":[
        {
            "category":"Retail",
            "subcategory":"Auto Repair",
            "type":"Services"
        }
    ],
    "sg:phone":"+1 850 477 6996",
    "sg:postcode":"32534",
    "sg:province":"FL",
    "sg:tags":[
        "general"
    ],
    "wof:name":"Bay Transmission",
    "wof:placetype":"venue"
},
  "geometry": {"coordinates":[-87.313254,30.52585],"type":"Point"}
}