{
  "type": "Feature",
  "properties": {
    "iso:country":"US",
    "sg:address":"2175 NW 23rd Ave",
    "sg:city":"Miami",
    "sg:classifiers":[
        {
            "category":"Building & Trades",
            "subcategory":"Construction",
            "type":"Services"
        }
    ],
    "sg:phone":"+1 305 634 9960",
    "sg:postcode":"33142",
    "sg:province":"FL",
    "sg:tags":[
        "general",
        "contractor"
    ],
    "wof:name":"Structural Contractors-Flrd",
    "wof:placetype":"venue"
},
  "geometry": {"coordinates":[-80.2336,25.797242],"type":"Point"}
}