{
  "type": "Feature",
  "properties": {
    "iso:country":"US",
    "sg:address":"1412 NW 82nd Ave",
    "sg:city":"Doral",
    "sg:classifiers":[
        {
            "category":"Wholesale",
            "subcategory":"Groceries",
            "type":"Manufacturing & Wholesale Goods"
        }
    ],
    "sg:phone":"+1 305 592 1717",
    "sg:postcode":"33126",
    "sg:province":"FL",
    "sg:tags":[
        "food",
        "products-wholesale"
    ],
    "wof:name":"Tama Corporation",
    "wof:placetype":"venue"
},
  "geometry": {"coordinates":[-80.328761,25.786396],"type":"Point"}
}