{
  "type": "Feature",
  "properties": {
    "iso:country":"US",
    "sg:address":"2753 E Oakland Park Blvd",
    "sg:city":"Fort Lauderdale",
    "sg:classifiers":[
        {
            "category":"Shopping",
            "subcategory":"Jewelry",
            "type":"Retail Goods"
        }
    ],
    "sg:phone":"+1 954 561 1769",
    "sg:postcode":"33306",
    "sg:province":"FL",
    "sg:tags":[
        "repair",
        "precious",
        "metal",
        "stone"
    ],
    "wof:name":"Bentleys 1900 Jewelers Inc",
    "wof:placetype":"venue"
},
  "geometry": {"coordinates":[-80.111705,26.167386],"type":"Point"}
}