{
  "type": "Feature",
  "properties": {
    "addr:full":"1114 S Main Ave Groveland FL 34736",
    "addr:housenumber":"1114",
    "addr:postcode":"34736",
    "addr:street":"S Main Ave",
    "iso:country":"US",
    "sg:address":"1114 S Main Ave",
    "sg:city":"Groveland",
    "sg:classifiers":[
        {
            "category":"Farming",
            "subcategory":"Orchard",
            "type":"Manufacturing & Wholesale Goods"
        }
    ],
    "sg:phone":"+1 352 429 2992",
    "sg:postcode":"34736",
    "sg:province":"FL",
    "sg:tags":[
        "beef",
        "citrus",
        "grove",
        "fruit",
        "cattle",
        "feedlot"
    ],
    "wof:name":"Micheloni Properties Inc",
    "wof:placetype":"venue"
},
  "geometry": {"coordinates":[-81.86139799999999,28.552271],"type":"Point"}
}