{
  "type": "Feature",
  "properties": {
    "addr:full":"4905 S Orange Ave Orlando FL 32806",
    "addr:housenumber":"4905",
    "addr:postcode":"32806",
    "addr:street":"S Orange Ave",
    "iso:country":"US",
    "sg:address":"4905 S Orange Ave",
    "sg:city":"Orlando",
    "sg:classifiers":[
        {
            "category":"Restaurant",
            "type":"Food & Drink"
        }
    ],
    "sg:phone":"+1 407 856 9565",
    "sg:postcode":"32806",
    "sg:province":"FL",
    "sg:tags":[
        "eating"
    ],
    "wof:name":"Sharons Place Inc",
    "wof:placetype":"venue"
},
  "geometry": {"coordinates":[-81.373109,28.489261],"type":"Point"}
}