{
  "type": "Feature",
  "properties": {
    "iso:country":"US",
    "sg:address":"515 N Park Ave Ste 116",
    "sg:city":"Winter Park",
    "sg:classifiers":[
        {
            "category":"Arts & Performance",
            "subcategory":"Art Gallery",
            "type":"Entertainment"
        }
    ],
    "sg:phone":"+1 321 282 6780",
    "sg:postcode":"32789",
    "sg:province":"FL",
    "sg:website":"mauruarendart.com",
    "wof:name":"Mauruarend New Visions Inc",
    "wof:placetype":"venue"
},
  "geometry": {"coordinates":[-81.351099,28.601593],"type":"Point"}
}