{
  "type": "Feature",
  "properties": {
    "iso:country":"US",
    "sg:address":"26880 Old 41 Rd",
    "sg:city":"Bonita Springs",
    "sg:classifiers":[
        {
            "category":"Banks & Credit Unions",
            "subcategory":"Bank",
            "type":"Services"
        }
    ],
    "sg:phone":"+1 239 948 8304",
    "sg:postcode":"34135",
    "sg:province":"FL",
    "sg:tags":[
        "money",
        "transfer"
    ],
    "wof:name":"Calssica & Telecard Corp",
    "wof:placetype":"venue"
},
  "geometry": {"coordinates":[-81.779194,26.347313],"type":"Point"}
}