{
  "type": "Feature",
  "properties": {
    "iso:country":"US",
    "sg:address":"15 S Broad St",
    "sg:city":"Brooksville",
    "sg:classifiers":[
        {
            "category":"Banks & Credit Unions",
            "subcategory":"Investment Brokerage",
            "type":"Services"
        }
    ],
    "sg:phone":"+1 727 797 0037",
    "sg:postcode":"34601",
    "sg:province":"FL",
    "sg:tags":[
        "security"
    ],
    "wof:name":"Richard Lambright Insurance",
    "wof:placetype":"venue"
},
  "geometry": {"coordinates":[-82.388577,28.554801],"type":"Point"}
}