{
  "type": "Feature",
  "properties": {
    "iso:country":"US",
    "sg:address":"350 Gulf Blvd",
    "sg:city":"Indian Rocks Bch",
    "sg:classifiers":[
        {
            "category":"Professional",
            "subcategory":"Computer Services",
            "type":"Services"
        }
    ],
    "sg:phone":"+1 727 517 2222",
    "sg:postcode":"33785",
    "sg:province":"FL",
    "sg:tags":[
        "website",
        "design",
        "system"
    ],
    "sg:website":"www.aksb2b.com",
    "wof:name":"Advanced Knowledge Systems",
    "wof:placetype":"venue"
},
  "geometry": {"coordinates":[-82.850488,27.881512],"type":"Point"}
}