{
  "type": "Feature",
  "properties": {
    "iso:country":"US",
    "sg:address":"184 NE 5th St Mia",
    "sg:city":"Miami",
    "sg:classifiers":[
        {
            "category":"Building & Trades",
            "subcategory":"Construction",
            "type":"Services"
        }
    ],
    "sg:phone":"+1 305 999 9975",
    "sg:postcode":"33132",
    "sg:province":"FL",
    "sg:tags":[
        "roofing",
        "contractor"
    ],
    "wof:name":"Pinnacle Roofing Inc",
    "wof:placetype":"venue"
},
  "geometry": {"coordinates":[-80.19071599999999,25.779062],"type":"Point"}
}