{
  "type": "Feature",
  "properties": {
    "addr:full":"7038 Hafford Ln Jacksonville FL 32244",
    "addr:housenumber":"7038",
    "addr:postcode":"32244",
    "addr:street":"Hafford Ln",
    "iso:country":"US",
    "sg:address":"7038 Hafford Ln",
    "sg:city":"Jacksonville",
    "sg:classifiers":[
        {
            "category":"Retail",
            "subcategory":"Repair Shop",
            "type":"Services"
        }
    ],
    "sg:phone":"+1 904 573 0043",
    "sg:postcode":"32244",
    "sg:province":"FL",
    "sg:tags":[
        "jewelry"
    ],
    "wof:name":"Priceless Jewelry Repairs",
    "wof:placetype":"venue"
},
  "geometry": {"coordinates":[-81.758636,30.242293],"type":"Point"}
}