{
  "type": "Feature",
  "properties": {
    "iso:country":"US",
    "sg:address":"1114 E Park Ave",
    "sg:city":"Tallahassee",
    "sg:classifiers":[
        {
            "category":"Professional",
            "subcategory":"Lawyer & Legal Services",
            "type":"Services"
        }
    ],
    "sg:phone":"+1 850 224 7332",
    "sg:postcode":"32301",
    "sg:province":"FL",
    "sg:tags":[
        "attorney"
    ],
    "wof:name":"David A Gheriaque",
    "wof:placetype":"venue"
},
  "geometry": {"coordinates":[-84.264149,30.441821],"type":"Point"}
}