{
  "type": "Feature",
  "properties": {
    "iso:country":"US",
    "sg:address":"13200 Byrd Dr",
    "sg:city":"Odessa",
    "sg:classifiers":[
        {
            "category":"Retail",
            "subcategory":"Repair Shop",
            "type":"Services"
        }
    ],
    "sg:phone":"+1 813 962 4946",
    "sg:postcode":"33556",
    "sg:province":"FL",
    "sg:tags":[
        "welding"
    ],
    "wof:name":"K & S Welding",
    "wof:placetype":"venue"
},
  "geometry": {"coordinates":[-82.59645399999999,28.173239],"type":"Point"}
}