{
  "type": "Feature",
  "properties": {
    "addr:full":"2174 S Ridgewood Ave Daytona Beach FL 32119",
    "addr:housenumber":"2174",
    "addr:postcode":"32119",
    "addr:street":"S Ridgewood Ave",
    "iso:country":"US",
    "sg:address":"2174 S Ridgewood Ave",
    "sg:city":"Daytona Beach",
    "sg:classifiers":[
        {
            "category":"Real Estate",
            "subcategory":"Real Estate Agent",
            "type":"Services"
        }
    ],
    "sg:phone":"+1 386 756 6866",
    "sg:postcode":"32119",
    "sg:province":"FL",
    "sg:tags":[
        "investor",
        "business"
    ],
    "wof:name":"Herb Lubansky Realty",
    "wof:placetype":"venue"
},
  "geometry": {"coordinates":[-81.000855,29.169955],"type":"Point"}
}