{
  "type": "Feature",
  "properties": {
    "addr:full":"1010 NW 76th Blvd Gainesville Gainesville FL 32606",
    "addr:housenumber":"1010",
    "addr:postcode":"32606",
    "addr:street":"Nw 76Th Blvd",
    "iso:country":"US",
    "sg:address":"1010 NW 76th Blvd Gainesville",
    "sg:city":"Gainesville",
    "sg:classifiers":[
        {
            "category":"Health Services",
            "subcategory":"Dentist",
            "type":"Services"
        }
    ],
    "sg:phone":"+1 352 332 4180",
    "sg:postcode":"32606",
    "sg:province":"FL",
    "sg:tags":[
        "dental",
        "clinic"
    ],
    "sg:website":"http://www.coastdental.com",
    "wof:name":"Coast Dental",
    "wof:placetype":"venue"
},
  "geometry": {"coordinates":[-82.423974,29.66145],"type":"Point"}
}