{
  "type": "Feature",
  "properties": {
    "iso:country":"US",
    "sg:address":"45 Lake Villa Way",
    "sg:city":"Kissimmee",
    "sg:classifiers":[
        {
            "category":"Professional",
            "type":"Services"
        }
    ],
    "sg:phone":"+1 407 344 9080",
    "sg:postcode":"34743",
    "sg:province":"FL",
    "wof:name":"M L Hawk LLC",
    "wof:placetype":"venue"
},
  "geometry": {"coordinates":[-81.344097,28.324467],"type":"Point"}
}