{
  "type": "Feature",
  "properties": {
    "iso:country":"US",
    "sg:address":"14441 7th St",
    "sg:city":"Dade City",
    "sg:classifiers":[
        {
            "category":"Shopping",
            "subcategory":"Clothing, Apparel, & Fashions",
            "type":"Retail Goods"
        }
    ],
    "sg:phone":"+1 352 521 6921",
    "sg:postcode":"33523",
    "sg:province":"FL",
    "sg:tags":[
        "item",
        "boutique"
    ],
    "wof:name":"Neyla Sanchez Fashion",
    "wof:placetype":"venue"
},
  "geometry": {"coordinates":[-82.18914700000001,28.367781],"type":"Point"}
}