{
  "type": "Feature",
  "properties": {
    "iso:country":"US",
    "sg:address":"2209 Alice Rd",
    "sg:city":"Sarasota",
    "sg:classifiers":[
        {
            "category":"Retail",
            "subcategory":"Photofinishing",
            "type":"Services"
        }
    ],
    "sg:phone":"+1 941 923 3531",
    "sg:postcode":"34231",
    "sg:province":"FL",
    "sg:tags":[
        "pict",
        "motion",
        "video",
        "laboratory",
        "tape",
        "rental"
    ],
    "wof:name":"Siesta Video & 1 Hour Photo",
    "wof:placetype":"venue"
},
  "geometry": {"coordinates":[-82.526725,27.279535],"type":"Point"}
}