{
  "type": "Feature",
  "properties": {
    "addr:full":"225 Main St Destin FL 32541",
    "addr:housenumber":"225",
    "addr:postcode":"32541",
    "addr:street":"Main St",
    "iso:country":"US",
    "sg:address":"225 Main St",
    "sg:city":"Destin",
    "sg:classifiers":[
        {
            "category":"Banks & Credit Unions",
            "subcategory":"Bank",
            "type":"Services"
        }
    ],
    "sg:phone":"+1 850 837 0181",
    "sg:postcode":"32541",
    "sg:province":"FL",
    "sg:tags":[
        "mortgage",
        "loan",
        "broker",
        "real estate"
    ],
    "wof:name":"Coastal Mortgage Funding Inc",
    "wof:placetype":"venue"
},
  "geometry": {"coordinates":[-86.48369099999999,30.396682],"type":"Point"}
}