{
  "type": "Feature",
  "properties": {
    "iso:country":"US",
    "sg:address":"4300 N University Dr",
    "sg:city":"Sunrise",
    "sg:classifiers":[
        {
            "category":"Insurance",
            "subcategory":"Insurance Agent",
            "type":"Services"
        }
    ],
    "sg:phone":"+1 954 578 7836",
    "sg:postcode":"33351",
    "sg:province":"FL",
    "sg:tags":[
        "auto"
    ],
    "wof:name":"AAA A to Z Insurance",
    "wof:placetype":"venue"
},
  "geometry": {"coordinates":[-80.25185999999999,26.177752],"type":"Point"}
}