{
  "type": "Feature",
  "properties": {
    "iso:country":"US",
    "sg:address":"2210 N Australian Ave",
    "sg:city":"West Palm Beach",
    "sg:classifiers":[
        {
            "category":"Real Estate",
            "subcategory":"Real Estate Operator",
            "type":"Services"
        }
    ],
    "sg:phone":"+1 561 835 8389",
    "sg:postcode":"33407",
    "sg:province":"FL",
    "sg:tags":[
        "apartment"
    ],
    "wof:name":"Mangonia Residence I LTD",
    "wof:placetype":"venue"
},
  "geometry": {"coordinates":[-80.06745600000001,26.736021],"type":"Point"}
}