{
  "type": "Feature",
  "properties": {
    "iso:country":"US",
    "sg:address":"189 W Davis St",
    "sg:city":"De Leon Springs",
    "sg:classifiers":[
        {
            "category":"Professional",
            "type":"Services"
        }
    ],
    "sg:phone":"+1 386 985 9833",
    "sg:postcode":"32130",
    "sg:province":"FL",
    "sg:tags":[
        "establishment"
    ],
    "wof:name":"Davis Cottage",
    "wof:placetype":"venue"
},
  "geometry": {"coordinates":[-81.351258,29.111584],"type":"Point"}
}