{
  "type": "Feature",
  "properties": {
    "iso:country":"US",
    "sg:address":"1760 Walnut St",
    "sg:city":"Jacksonville",
    "sg:classifiers":[
        {
            "category":"Autos & Motor Vehicles",
            "subcategory":"Fuel & Gas Station",
            "type":"Retail Goods"
        }
    ],
    "sg:phone":"+1 904 355 6878",
    "sg:postcode":"32206",
    "sg:province":"FL",
    "sg:tags":[
        "oil"
    ],
    "wof:name":"Speedway",
    "wof:placetype":"venue"
},
  "geometry": {"coordinates":[-81.647904,30.344977],"type":"Point"}
}