{
  "type": "Feature",
  "properties": {
    "addr:full":"7412 S Dixie Hwy West Palm Beach FL 33405",
    "addr:housenumber":"7412",
    "addr:postcode":"33405",
    "addr:street":"S Dixie Hwy",
    "iso:country":"US",
    "sg:address":"7412 S Dixie Hwy",
    "sg:city":"West Palm Beach",
    "sg:classifiers":[
        {
            "category":"Shopping",
            "type":"Retail Goods"
        },
        {
            "category":"Retail",
            "subcategory":"Animal Services",
            "type":"Services"
        }
    ],
    "sg:phone":"+1 561 582 5393",
    "sg:postcode":"33405",
    "sg:province":"FL",
    "sg:tags":[
        "pet",
        "grooming",
        "washing",
        "merchandise"
    ],
    "wof:name":"M & MS Kritter Korner",
    "wof:placetype":"venue"
},
  "geometry": {"coordinates":[-80.05615299999999,26.648372],"type":"Point"}
}