{
  "type": "Feature",
  "properties": {
    "addr:full":"11720 US Hwy 19 Port Richey FL 34668",
    "addr:housenumber":"11720",
    "addr:postcode":"34668",
    "addr:street":"Us Hwy 19",
    "iso:country":"US",
    "sg:address":"11720 US Hwy 19",
    "sg:city":"Port Richey",
    "sg:classifiers":[
        {
            "category":"Retail",
            "subcategory":"Veterinary Services",
            "type":"Services"
        }
    ],
    "sg:phone":"+1 727 819 1910",
    "sg:postcode":"34668",
    "sg:province":"FL",
    "sg:tags":[
        "veterinarian"
    ],
    "wof:name":"Paws Spay & Neutered Clinic",
    "wof:placetype":"venue"
},
  "geometry": {"coordinates":[-82.69922699999999,28.326462],"type":"Point"}
}