{
  "type": "Feature",
  "properties": {
    "addr:full":"850 E Lime St Lakeland FL 33801",
    "addr:housenumber":"850",
    "addr:postcode":"33801",
    "addr:street":"E Lime St",
    "iso:country":"US",
    "sg:address":"850 E Lime St",
    "sg:city":"Lakeland",
    "sg:classifiers":[
        {
            "category":"Professional",
            "subcategory":"Computer Services",
            "type":"Services"
        }
    ],
    "sg:phone":"+1 863 683 3342",
    "sg:postcode":"33801",
    "sg:province":"FL",
    "sg:tags":[
        "consultant",
        "designer"
    ],
    "wof:name":"Custer Consultants Inc",
    "wof:placetype":"venue"
},
  "geometry": {"coordinates":[-81.947447,28.04059],"type":"Point"}
}