{
  "type": "Feature",
  "properties": {
    "iso:country":"US",
    "sg:address":"220 Markham Woods Rd",
    "sg:city":"Longwood",
    "sg:classifiers":[
        {
            "category":"Arts & Performance",
            "subcategory":"Theater",
            "type":"Entertainment"
        }
    ],
    "sg:phone":"+1 407 862 8240",
    "sg:postcode":"32779",
    "sg:province":"FL",
    "sg:tags":[
        "group"
    ],
    "wof:name":"K & S Sports Entertainment",
    "wof:placetype":"venue"
},
  "geometry": {"coordinates":[-81.391938,28.6908],"type":"Point"}
}