{
  "type": "Feature",
  "properties": {
    "iso:country":"US",
    "sg:address":"9510 Marketplace Rd",
    "sg:city":"Fort Myers",
    "sg:classifiers":[
        {
            "category":"Restaurant",
            "type":"Food & Drink"
        }
    ],
    "sg:menulink":"http://www.allmenus.com/fl/lehigh-acres/68190-uno-chicago-grill/menu/",
    "sg:phone":"+1 239 693 8667",
    "sg:postcode":"33912",
    "sg:province":"FL",
    "sg:tags":[
        "american",
        "italian",
        "pizza"
    ],
    "wof:name":"Uno Chicago Grill",
    "wof:placetype":"venue"
},
  "geometry": {"coordinates":[-81.797588,26.548606],"type":"Point"}
}