{
  "type": "Feature",
  "properties": {
    "iso:country":"US",
    "sg:address":"206 SW 3rd Ave",
    "sg:city":"Okeechobee",
    "sg:classifiers":[
        {
            "category":"Professional",
            "subcategory":"Detective & Security Services",
            "type":"Services"
        },
        {
            "category":"Building & Trades",
            "subcategory":"Electrical",
            "type":"Services"
        }
    ],
    "sg:phone":"+1 863 634 3482",
    "sg:postcode":"34974",
    "sg:province":"FL",
    "sg:tags":[
        "control",
        "monitoring",
        "electrician",
        "system"
    ],
    "wof:name":"James Shockley Electrical Services",
    "wof:placetype":"venue"
},
  "geometry": {"coordinates":[-80.83219099999999,27.242058],"type":"Point"}
}