{
  "type": "Feature",
  "properties": {
    "addr:full":"4634 Ortega Farms Cir Jacksonville FL 32210",
    "addr:housenumber":"4634",
    "addr:postcode":"32210",
    "addr:street":"Ortega Farms Cir",
    "iso:country":"US",
    "sg:address":"4634 Ortega Farms Cir",
    "sg:city":"Jacksonville",
    "sg:classifiers":[
        {
            "category":"Home & Garden",
            "subcategory":"Household Appliances",
            "type":"Retail Goods"
        }
    ],
    "sg:phone":"+1 904 771 8050",
    "sg:postcode":"32210",
    "sg:province":"FL",
    "sg:tags":[
        "conditioning",
        "room",
        "unit",
        "air"
    ],
    "wof:name":"Tom Haley's Repair",
    "wof:placetype":"venue"
},
  "geometry": {"coordinates":[-81.72072900000001,30.257657],"type":"Point"}
}