{
  "type": "Feature",
  "properties": {
    "iso:country":"US",
    "sg:address":"7975 W McNab Rd",
    "sg:city":"Fort Lauderdale",
    "sg:classifiers":[
        {
            "category":"Professional",
            "subcategory":"Lawyer & Legal Services",
            "type":"Services"
        }
    ],
    "sg:phone":"+1 954 722 2280",
    "sg:postcode":"33321",
    "sg:province":"FL",
    "wof:name":"Kenneth S Rubin PA",
    "wof:placetype":"venue"
},
  "geometry": {"coordinates":[-80.234352,26.208504],"type":"Point"}
}