{
  "type": "Feature",
  "properties": {
    "addr:full":"124 Bushnell Plz Bushnell FL 33513",
    "addr:housenumber":"124",
    "addr:postcode":"33513",
    "addr:street":"Bushnell Plz",
    "iso:country":"US",
    "sg:address":"124 Bushnell Plz",
    "sg:city":"Bushnell",
    "sg:classifiers":[
        {
            "category":"Personal",
            "type":"Services"
        }
    ],
    "sg:phone":"+1 352 793 8003",
    "sg:postcode":"33513",
    "sg:province":"FL",
    "sg:tags":[
        "assistant"
    ],
    "wof:name":"U Name It",
    "wof:placetype":"venue"
},
  "geometry": {"coordinates":[-82.111587,28.66378],"type":"Point"}
}