{
  "type": "Feature",
  "properties": {
    "addr:full":"5267 Images Cir Kissimmee FL 34746",
    "addr:postcode":"5267;34746",
    "addr:street":"Images Cir",
    "iso:country":"US",
    "sg:address":"5267 Images Cir",
    "sg:city":"Kissimmee",
    "sg:classifiers":[
        {
            "category":"Organizations",
            "subcategory":"Non-profit Organization",
            "type":"Services"
        }
    ],
    "sg:phone":"+1 407 390 9168",
    "sg:postcode":"34746",
    "sg:province":"FL",
    "wof:name":"God's Way",
    "wof:placetype":"venue"
},
  "geometry": {"coordinates":[-81.492704,28.33914],"type":"Point"}
}