{
  "type": "Feature",
  "properties": {
    "addr:full":"2003 Lake Dr Casselberry FL 32789",
    "addr:housenumber":"2003",
    "addr:postcode":"32789",
    "addr:street":"Lake Dr",
    "iso:country":"US",
    "sg:address":"2003 Lake Dr",
    "sg:city":"Casselberry",
    "sg:classifiers":[
        {
            "category":"Professional",
            "type":"Services"
        }
    ],
    "sg:phone":"+1 407 740 5056",
    "sg:postcode":"32789",
    "sg:province":"FL",
    "sg:tags":[
        "establishment"
    ],
    "wof:name":"Security Financial",
    "wof:placetype":"venue"
},
  "geometry": {"coordinates":[-81.375101,28.60441],"type":"Point"}
}