{
  "type": "Feature",
  "properties": {
    "addr:full":"434 Chicago Ave Dunedin FL 34698",
    "addr:housenumber":"434",
    "addr:postcode":"34698",
    "addr:street":"Chicago Ave",
    "iso:country":"US",
    "sg:address":"434 Chicago Ave",
    "sg:city":"Dunedin",
    "sg:classifiers":[
        {
            "category":"Real Estate",
            "subcategory":"Real Estate Agent",
            "type":"Services"
        }
    ],
    "sg:phone":"+1 727 460 0689",
    "sg:postcode":"34698",
    "sg:province":"FL",
    "wof:name":"Jeffrey R Borgeson Inc",
    "wof:placetype":"venue"
},
  "geometry": {"coordinates":[-82.786933,28.006281],"type":"Point"}
}