{
  "type": "Feature",
  "properties": {
    "addr:full":"5928 Firestone Rd Jacksonville FL 32244",
    "addr:housenumber":"5928",
    "addr:postcode":"32244",
    "addr:street":"Firestone Rd",
    "iso:country":"US",
    "sg:address":"5928 Firestone Rd",
    "sg:city":"Jacksonville",
    "sg:classifiers":[
        {
            "category":"Real Estate",
            "subcategory":"Real Estate Operator",
            "type":"Services"
        }
    ],
    "sg:phone":"+1 904 771 6666",
    "sg:postcode":"32244",
    "sg:province":"FL",
    "sg:tags":[
        "building",
        "apartment"
    ],
    "wof:name":"Colonial Forest Apartments",
    "wof:placetype":"venue"
},
  "geometry": {"coordinates":[-81.76455,30.242262],"type":"Point"}
}