{
  "type": "Feature",
  "properties": {
    "iso:country":"US",
    "sg:address":"6 Barring Pl",
    "sg:city":"Palm Coast",
    "sg:classifiers":[
        {
            "category":"Shopping",
            "subcategory":"Catalog Store",
            "type":"Retail Goods"
        }
    ],
    "sg:phone":"+1 386 445 3237",
    "sg:postcode":"32137",
    "sg:province":"FL",
    "sg:tags":[
        "mail",
        "house"
    ],
    "wof:name":"Bigbuysandbargainscom",
    "wof:placetype":"venue"
},
  "geometry": {"coordinates":[-81.23639900000001,29.571617],"type":"Point"}
}