{
  "type": "Feature",
  "properties": {
    "iso:country":"US",
    "sg:address":"5211 Lake le Clare Rd",
    "sg:city":"Lutz",
    "sg:classifiers":[
        {
            "category":"Building & Trades",
            "subcategory":"Landscaping Services",
            "type":"Services"
        }
    ],
    "sg:phone":"+1 813 961 1475",
    "sg:postcode":"33558",
    "sg:province":"FL",
    "sg:tags":[
        "gardener"
    ],
    "wof:name":"Bromeliad Guild Of Tampa Bay",
    "wof:placetype":"venue"
},
  "geometry": {"coordinates":[-82.536873,28.113492],"type":"Point"}
}