{
  "type": "Feature",
  "properties": {
    "addr:full":"180 E Main St Apopka FL 32732",
    "addr:housenumber":"180",
    "addr:postcode":"32732",
    "addr:street":"E Main St",
    "iso:country":"US",
    "sg:address":"180 E Main St",
    "sg:city":"Apopka",
    "sg:classifiers":[
        {
            "category":"Organizations",
            "subcategory":"Professional Association",
            "type":"Services"
        }
    ],
    "sg:phone":"+1 407 886 1441",
    "sg:postcode":"32732",
    "sg:province":"FL",
    "sg:tags":[
        "chambers",
        "commerce"
    ],
    "wof:name":"Chamber Of Commerce",
    "wof:placetype":"venue"
},
  "geometry": {"coordinates":[-81.115036,28.739905],"type":"Point"}
}