{
  "type": "Feature",
  "properties": {
    "addr:full":"1631 Gulf To Bay Blvd Clearwater FL 33755",
    "addr:housenumber":"1631",
    "addr:postcode":"33755",
    "addr:street":"Gulf To Bay Blvd",
    "iso:country":"US",
    "sg:address":"1631 Gulf To Bay Blvd",
    "sg:city":"Clearwater",
    "sg:classifiers":[
        {
            "category":"Retail",
            "subcategory":"Repair Shop",
            "type":"Services"
        }
    ],
    "sg:phone":"+1 727 461 2233",
    "sg:postcode":"33755",
    "sg:province":"FL",
    "sg:tags":[
        "television",
        "radio"
    ],
    "wof:name":"Jackson Brothers TV Sales",
    "wof:placetype":"venue"
},
  "geometry": {"coordinates":[-82.76921400000001,27.96059],"type":"Point"}
}