{
  "type": "Feature",
  "properties": {
    "addr:full":"2947 SE Highway 31 Arcadia FL 34266",
    "addr:housenumber":"2947",
    "addr:postcode":"34266",
    "addr:street":"Se Highway 31",
    "iso:country":"US",
    "sg:address":"2947 SE Highway 31",
    "sg:city":"Arcadia",
    "sg:classifiers":[
        {
            "category":"Real Estate",
            "subcategory":"Real Estate Services",
            "type":"Services"
        },
        {
            "category":"Real Estate",
            "subcategory":"Real Estate Agent",
            "type":"Services"
        }
    ],
    "sg:phone":"+1 863 494 7900",
    "sg:postcode":"34266",
    "sg:province":"FL",
    "sg:tags":[
        "management"
    ],
    "wof:name":"Bermont Properties",
    "wof:placetype":"venue"
},
  "geometry": {"coordinates":[-81.827895,27.179591],"type":"Point"}
}