{
  "type": "Feature",
  "properties": {
    "addr:full":"10175 Flag Dr Palm Beach Gardens FL 33410",
    "addr:housenumber":"10175",
    "addr:postcode":"33410",
    "addr:street":"Flag Dr",
    "iso:country":"US",
    "sg:address":"10175 Flag Dr",
    "sg:city":"Palm Beach Gardens",
    "sg:classifiers":[
        {
            "category":"Professional",
            "subcategory":"Engineering",
            "type":"Services"
        }
    ],
    "sg:phone":"+1 561 799 5280",
    "sg:postcode":"33410",
    "sg:province":"FL",
    "sg:tags":[
        "engineer"
    ],
    "wof:name":"Team USA-5",
    "wof:placetype":"venue"
},
  "geometry": {"coordinates":[-80.095253,26.826461],"type":"Point"}
}