{
  "type": "Feature",
  "properties": {
    "iso:country":"US",
    "sg:address":"12635 US Hwy 19",
    "sg:city":"Hudson",
    "sg:classifiers":[
        {
            "category":"Building & Trades",
            "subcategory":"Construction",
            "type":"Services"
        }
    ],
    "sg:phone":"+1 727 863 7601",
    "sg:postcode":"34667",
    "sg:province":"FL",
    "sg:tags":[
        "general",
        "contractor"
    ],
    "wof:name":"Jones Construction Group",
    "wof:placetype":"venue"
},
  "geometry": {"coordinates":[-82.69906,28.342616],"type":"Point"}
}