{
  "type": "Feature",
  "properties": {
    "addr:full":"5019 Canal St Milton FL 32570",
    "addr:housenumber":"5019",
    "addr:postcode":"32570",
    "addr:street":"Canal St",
    "iso:country":"US",
    "sg:address":"5019 Canal St",
    "sg:city":"Milton",
    "sg:classifiers":[
        {
            "category":"Building & Trades",
            "subcategory":"Construction",
            "type":"Services"
        }
    ],
    "sg:phone":"+1 850 626 9707",
    "sg:postcode":"32570",
    "sg:province":"FL",
    "sg:tags":[
        "house"
    ],
    "wof:name":"Accent Renovation",
    "wof:placetype":"venue"
},
  "geometry": {"coordinates":[-87.039422,30.616678],"type":"Point"}
}