{
  "type": "Feature",
  "properties": {
    "addr:full":"1801 NW 93rd Ave Doral FL 33172",
    "addr:housenumber":"1801",
    "addr:postcode":"33172",
    "addr:street":"Nw 93Rd Ave",
    "iso:country":"US",
    "sg:address":"1801 NW 93rd Ave",
    "sg:city":"Doral",
    "sg:classifiers":[
        {
            "category":"Wholesale",
            "subcategory":"Home Furnishings",
            "type":"Manufacturing & Wholesale Goods"
        }
    ],
    "sg:phone":"+1 305 599 1331",
    "sg:postcode":"33172",
    "sg:province":"FL",
    "sg:tags":[
        "blind",
        "shade"
    ],
    "wof:name":"Rimar Blinds Inc",
    "wof:placetype":"venue"
},
  "geometry": {"coordinates":[-80.346603,25.792],"type":"Point"}
}