{
  "type": "Feature",
  "properties": {
    "iso:country":"US",
    "sg:address":"1131 W Lake Brantley Rd",
    "sg:city":"Altamonte Springs",
    "sg:classifiers":[
        {
            "category":"Social Services",
            "type":"Services"
        }
    ],
    "sg:phone":"+1 407 389 9930",
    "sg:postcode":"32714",
    "sg:province":"FL",
    "wof:name":"Annway Assisted Living",
    "wof:placetype":"venue"
},
  "geometry": {"coordinates":[-81.431309,28.679049],"type":"Point"}
}