{
  "type": "Feature",
  "properties": {
    "iso:country":"US",
    "sg:address":"351 NW 42nd Ave Ste 105",
    "sg:city":"Miami",
    "sg:classifiers":[
        {
            "category":"Health Services",
            "subcategory":"Doctor",
            "type":"Services"
        }
    ],
    "sg:phone":"+1 305 649 8955",
    "sg:postcode":"33126",
    "sg:province":"FL",
    "sg:tags":[
        "practice",
        "family"
    ],
    "wof:name":"Gonzalez Jorge A Dr",
    "wof:placetype":"venue"
},
  "geometry": {"coordinates":[-80.263617,25.775636],"type":"Point"}
}