{
  "type": "Feature",
  "properties": {
    "addr:full":"605 NW 72nd Ave Miami FL 33126",
    "addr:housenumber":"605",
    "addr:postcode":"ave;33126",
    "addr:street":"Nw 72Nd",
    "iso:country":"US",
    "sg:address":"605 NW 72nd Ave",
    "sg:city":"Miami",
    "sg:classifiers":[
        {
            "category":"Real Estate",
            "subcategory":"Real Estate Services",
            "type":"Services"
        }
    ],
    "sg:phone":"+1 305 266 8175",
    "sg:postcode":"33126",
    "sg:province":"FL",
    "sg:tags":[
        "management",
        "condominium"
    ],
    "wof:name":"Expo Condominium",
    "wof:placetype":"venue"
},
  "geometry": {"coordinates":[-80.31231699999999,25.776312],"type":"Point"}
}