{
  "type": "Feature",
  "properties": {
    "addr:full":"12111 Clover Dr Fort Myers FL 33905",
    "addr:housenumber":"12111",
    "addr:postcode":"33905",
    "addr:street":"Clover Dr",
    "iso:country":"US",
    "sg:address":"12111 Clover Dr",
    "sg:city":"Fort Myers",
    "sg:classifiers":[
        {
            "category":"Shopping",
            "subcategory":"Gifts & Souvenirs",
            "type":"Retail Goods"
        }
    ],
    "sg:phone":"+1 239 694 4509",
    "sg:postcode":"33905",
    "sg:province":"FL",
    "wof:name":"Scott T Margaret Evenson",
    "wof:placetype":"venue"
},
  "geometry": {"coordinates":[-81.757396,26.666087],"type":"Point"}
}