{
  "type": "Feature",
  "properties": {
    "iso:country":"US",
    "sg:address":"1515 S Andrews Ave",
    "sg:city":"Fort Lauderdale",
    "sg:classifiers":[
        {
            "category":"Shopping",
            "subcategory":"Books",
            "type":"Retail Goods"
        }
    ],
    "sg:phone":"+1 954 524 4731",
    "sg:postcode":"33316",
    "sg:province":"FL",
    "sg:tags":[
        "newsstand",
        "magazine",
        "store",
        "stand"
    ],
    "wof:name":"Bobs News and Books",
    "wof:placetype":"venue"
},
  "geometry": {"coordinates":[-80.142478,26.102119],"type":"Point"}
}