{
  "type": "Feature",
  "properties": {
    "iso:country":"US",
    "sg:address":"245 SE 1st St",
    "sg:city":"Miami",
    "sg:classifiers":[
        {
            "category":"Shopping",
            "subcategory":"Computers & Home Electronics",
            "type":"Retail Goods"
        }
    ],
    "sg:phone":"+1 305 416 7524",
    "sg:postcode":"33131",
    "sg:province":"FL",
    "sg:tags":[
        "system"
    ],
    "wof:name":"Aurix",
    "wof:placetype":"venue"
},
  "geometry": {"coordinates":[-80.18946,25.773497],"type":"Point"}
}