{
  "type": "Feature",
  "properties": {
    "iso:country":"US",
    "sg:address":"601 N Ferncreek Ave",
    "sg:city":"Orlando",
    "sg:classifiers":[
        {
            "category":"Professional",
            "subcategory":"Accounting & Tax Preparation",
            "type":"Services"
        }
    ],
    "sg:phone":"+1 407 894 6803",
    "sg:postcode":"32803",
    "sg:province":"FL",
    "sg:tags":[
        "accountant"
    ],
    "sg:website":"www.hollandandreilly.com",
    "wof:name":"Holland & Reilly",
    "wof:placetype":"venue"
},
  "geometry": {"coordinates":[-81.36029000000001,28.552379],"type":"Point"}
}