{
  "type": "Feature",
  "properties": {
    "iso:country":"US",
    "sg:address":"520 D St",
    "sg:city":"Clearwater",
    "sg:classifiers":[
        {
            "category":"Health Services",
            "subcategory":"Doctor",
            "type":"Services"
        }
    ],
    "sg:phone":"+1 727 443 6400",
    "sg:postcode":"33756",
    "sg:province":"FL",
    "sg:tags":[
        "medical"
    ],
    "wof:name":"Rosen Adam M MD PA",
    "wof:placetype":"venue"
},
  "geometry": {"coordinates":[-82.799779,27.947411],"type":"Point"}
}