{
  "type": "Feature",
  "properties": {
    "iso:country":"US",
    "sg:address":"2500 Aaron St",
    "sg:city":"Port Charlotte",
    "sg:classifiers":[
        {
            "category":"Social Services",
            "subcategory":"Adult Care",
            "type":"Services"
        }
    ],
    "sg:phone":"+1 941 627 6762",
    "sg:postcode":"33952",
    "sg:province":"FL",
    "sg:tags":[
        "home",
        "residential"
    ],
    "sg:website":"www.assistedsenior.com",
    "wof:name":"Royal Palm Retirement Centre",
    "wof:placetype":"venue"
},
  "geometry": {"coordinates":[-82.096937,26.985683],"type":"Point"}
}