{
  "type": "Feature",
  "properties": {
    "addr:full":"1635 S Monroe St Tallahassee FL 32301",
    "addr:housenumber":"1635",
    "addr:postcode":"32301",
    "addr:street":"S Monroe St",
    "iso:country":"US",
    "sg:address":"1635 S Monroe St",
    "sg:city":"Tallahassee",
    "sg:classifiers":[
        {
            "category":"Personal",
            "subcategory":"Beauty Salon",
            "type":"Services"
        }
    ],
    "sg:phone":"+1 850 513 0334",
    "sg:postcode":"32301",
    "sg:province":"FL",
    "wof:name":"Kelly's Cottage",
    "wof:placetype":"venue"
},
  "geometry": {"coordinates":[-84.280568,30.42266],"type":"Point"}
}