{
  "type": "Feature",
  "properties": {
    "addr:full":"2202 W McCormick Rd Apopka FL 32703",
    "addr:housenumber":"2202",
    "addr:postcode":"32703",
    "addr:street":"W Mccormick Rd",
    "iso:country":"US",
    "sg:address":"2202 W McCormick Rd",
    "sg:city":"Apopka",
    "sg:classifiers":[
        {
            "category":"Food & Beverages",
            "subcategory":"Groceries & Convenience Stores",
            "type":"Retail Goods"
        }
    ],
    "sg:phone":"+1 407 889 7715",
    "sg:postcode":"32703",
    "sg:province":"FL",
    "sg:tags":[
        "station",
        "gasoline"
    ],
    "wof:name":"Circle K",
    "wof:placetype":"venue"
},
  "geometry": {"coordinates":[-81.544421,28.621552],"type":"Point"}
}