{
  "type": "Feature",
  "properties": {
    "iso:country":"US",
    "sg:address":"27567 Grove Rd",
    "sg:city":"Bonita Springs",
    "sg:classifiers":[
        {
            "category":"Real Estate",
            "subcategory":"Real Estate Agent",
            "type":"Services"
        }
    ],
    "sg:phone":"+1 239 949 4990",
    "sg:postcode":"34135",
    "sg:province":"FL",
    "wof:name":"Meyer Manz Real Est",
    "wof:placetype":"venue"
},
  "geometry": {"coordinates":[-81.76647699999999,26.337747],"type":"Point"}
}