{
  "type": "Feature",
  "properties": {
    "iso:country":"US",
    "sg:address":"1611 S Douglas Rd",
    "sg:city":"Pembroke Pines",
    "sg:classifiers":[
        {
            "category":"Freight",
            "type":"Transportation"
        }
    ],
    "sg:phone":"+1 954 442 7233",
    "sg:postcode":"33025",
    "sg:province":"FL",
    "sg:tags":[
        "commercial",
        "storage"
    ],
    "wof:name":"Storsafe Self Storage",
    "wof:placetype":"venue"
},
  "geometry": {"coordinates":[-80.26326899999999,25.997964],"type":"Point"}
}