{
  "type": "Feature",
  "properties": {
    "iso:country":"US",
    "sg:address":"489 Bridge Creek Blvd",
    "sg:city":"Ocoee",
    "sg:classifiers":[
        {
            "category":"Real Estate",
            "subcategory":"Real Estate Services",
            "type":"Services"
        },
        {
            "category":"Real Estate",
            "subcategory":"Real Estate Agent",
            "type":"Services"
        }
    ],
    "sg:phone":"+1 407 361 6001",
    "sg:postcode":"34761",
    "sg:province":"FL",
    "sg:tags":[
        "buyer",
        "broker"
    ],
    "wof:name":"Main Street Realty",
    "wof:placetype":"venue"
},
  "geometry": {"coordinates":[-81.53415699999999,28.536784],"type":"Point"}
}