{
  "type": "Feature",
  "properties": {
    "iso:country":"US",
    "sg:address":"743 Silk Oak Dr",
    "sg:city":"Venice",
    "sg:classifiers":[
        {
            "category":"Manufacturing",
            "subcategory":"Jewelry",
            "type":"Manufacturing & Wholesale Goods"
        }
    ],
    "sg:phone":"+1 941 493 3196",
    "sg:postcode":"34293",
    "sg:province":"FL",
    "sg:tags":[
        "costume",
        "mfg"
    ],
    "wof:name":"Studio M Designs",
    "wof:placetype":"venue"
},
  "geometry": {"coordinates":[-82.375,27.06632],"type":"Point"}
}