{
  "type": "Feature",
  "properties": {
    "addr:full":"397 US Hwy 98 Okeechobee FL 34972",
    "addr:housenumber":"397",
    "addr:postcode":"34972",
    "addr:street":"Us Hwy 98",
    "iso:country":"US",
    "sg:address":"397 US Hwy 98",
    "sg:city":"Okeechobee",
    "sg:classifiers":[
        {
            "category":"Retail",
            "subcategory":"Auto Repair",
            "type":"Services"
        }
    ],
    "sg:phone":"+1 863 763 7992",
    "sg:postcode":"34972",
    "sg:province":"FL",
    "sg:tags":[
        "repairing",
        "automobile"
    ],
    "wof:name":"Superior Muffler & Tire",
    "wof:placetype":"venue"
},
  "geometry": {"coordinates":[-80.832365,27.243666],"type":"Point"}
}