{
  "type": "Feature",
  "properties": {
    "iso:country":"US",
    "sg:address":"4014 Tampa Rd",
    "sg:city":"Oldsmar",
    "sg:classifiers":[
        {
            "category":"Travel",
            "subcategory":"Hotels & Motels",
            "type":"Entertainment"
        }
    ],
    "sg:phone":"+1 813 925 8887",
    "sg:postcode":"34677",
    "sg:province":"FL",
    "sg:website":"www.courtyard.com/tpaol",
    "wof:name":"Courtyard-Tampa Oldsmar",
    "wof:placetype":"venue"
},
  "geometry": {"coordinates":[-82.655777,28.03598],"type":"Point"}
}