{
  "type": "Feature",
  "properties": {
    "addr:full":"3801 16th St N St Petersburg FL 33703",
    "addr:housenumber":"3801",
    "addr:postcode":"33703",
    "addr:street":"16Th St N",
    "iso:country":"US",
    "sg:address":"3801 16th St N",
    "sg:city":"St Petersburg",
    "sg:classifiers":[
        {
            "category":"Building & Trades",
            "subcategory":"Construction",
            "type":"Services"
        },
        {
            "category":"Retail",
            "subcategory":"Auto Repair",
            "type":"Services"
        }
    ],
    "sg:phone":"+1 727 522 5722",
    "sg:postcode":"33703",
    "sg:province":"FL",
    "sg:tags":[
        "glass",
        "coating",
        "tinting",
        "contractor"
    ],
    "wof:name":"Window-Kote of St Petersburg",
    "wof:placetype":"venue"
},
  "geometry": {"coordinates":[-82.655013,27.807332],"type":"Point"}
}