{
  "type": "Feature",
  "properties": {
    "addr:full":"6036 S Orange Blossom Trl Orlando FL 32809",
    "addr:housenumber":"6036",
    "addr:postcode":"32809",
    "addr:street":"S Orange Blossom Trl",
    "iso:country":"US",
    "sg:address":"6036 S Orange Blossom Trl",
    "sg:city":"Orlando",
    "sg:phone":"+1 407 982 3482",
    "sg:postcode":"32809",
    "sg:province":"FL",
    "sg:website":"https://www.drivetime.com/getapprovedppc/default.aspx?source=643BE6E832394CF885F6945FA9C66F5B&campaign=bc",
    "wof:name":"DriveTime",
    "wof:placetype":"venue"
},
  "geometry": {"coordinates":[-81.39662199999999,28.468952],"type":"Point"}
}