{
  "type": "Feature",
  "properties": {
    "iso:country":"US",
    "sg:address":"6300 Pasadena Point Blvd S",
    "sg:city":"Saint Petersburg",
    "sg:classifiers":[
        {
            "category":"Shopping",
            "subcategory":"Bicycles & Sporting Goods",
            "type":"Retail Goods"
        }
    ],
    "sg:phone":"+1 727 381 8337",
    "sg:postcode":"33707",
    "sg:province":"FL",
    "sg:tags":[
        "shop",
        "pro",
        "golf"
    ],
    "wof:name":"Pasadena Golf Shop",
    "wof:placetype":"venue"
},
  "geometry": {"coordinates":[-82.71755899999999,27.749366],"type":"Point"}
}