{
  "type": "Feature",
  "properties": {
    "addr:full":"2534 SE 14th St Pompano Beach FL 33062",
    "addr:housenumber":"2534",
    "addr:postcode":"33062",
    "addr:street":"Se 14Th St",
    "iso:country":"US",
    "sg:address":"2534 SE 14th St",
    "sg:city":"Pompano Beach",
    "sg:classifiers":[
        {
            "category":"Real Estate",
            "subcategory":"Real Estate Operator",
            "type":"Services"
        }
    ],
    "sg:phone":"+1 954 786 9774",
    "sg:postcode":"33062",
    "sg:province":"FL",
    "sg:tags":[
        "building",
        "nonresidential"
    ],
    "wof:name":"Govoni Sim Bianca",
    "wof:placetype":"venue"
},
  "geometry": {"coordinates":[-80.101377,26.212579],"type":"Point"}
}