{
  "type": "Feature",
  "properties": {
    "addr:full":"7175 N Cocoa Blvd Port St John FL 32927",
    "addr:housenumber":"7175",
    "addr:postcode":"32927",
    "addr:street":"N Cocoa Blvd",
    "iso:country":"US",
    "sg:address":"7175 N Cocoa Blvd",
    "sg:city":"Port St John",
    "sg:classifiers":[
        {
            "category":"Food & Beverages",
            "subcategory":"Groceries & Convenience Stores",
            "type":"Retail Goods"
        }
    ],
    "sg:phone":"+1 321 632 8577",
    "sg:postcode":"32927",
    "sg:province":"FL",
    "wof:name":"Lil' Champ Food Store",
    "wof:placetype":"venue"
},
  "geometry": {"coordinates":[-80.767082,28.47285],"type":"Point"}
}