{
  "type": "Feature",
  "properties": {
    "addr:full":"30324 Old Dixie Hwy Homestead FL 33033",
    "addr:housenumber":"30324",
    "addr:postcode":"33033",
    "addr:street":"Old Dixie Hwy",
    "iso:country":"US",
    "sg:address":"30324 Old Dixie Hwy",
    "sg:city":"Homestead",
    "sg:classifiers":[
        {
            "category":"Retail",
            "subcategory":"Laundry & Dry Cleaning",
            "type":"Services"
        }
    ],
    "sg:phone":"+1 305 248 0827",
    "sg:postcode":"33033",
    "sg:province":"FL",
    "sg:tags":[
        "cleaners"
    ],
    "wof:name":"Americlean Express Inc",
    "wof:placetype":"venue"
},
  "geometry": {"coordinates":[-80.46212199999999,25.48495],"type":"Point"}
}