{
  "type": "Feature",
  "properties": {
    "addr:full":"1500 Placida Rd Ste F1 Englewood FL 34223",
    "addr:housenumber":"1500",
    "addr:postcode":"34223",
    "addr:street":"Placida Rd Ste F1",
    "iso:country":"US",
    "sg:address":"1500 Placida Rd Ste F1",
    "sg:city":"Englewood",
    "sg:classifiers":[
        {
            "category":"Health Services",
            "subcategory":"Medical Lab",
            "type":"Services"
        }
    ],
    "sg:phone":"+1 941 460 2780",
    "sg:postcode":"34223",
    "sg:province":"FL",
    "sg:tags":[
        "laboratories-pathological",
        "laboratory"
    ],
    "sg:website":"http://www.questdiagnostics.com",
    "wof:name":"Quest Diagnostics",
    "wof:placetype":"venue"
},
  "geometry": {"coordinates":[-82.337318,26.93641],"type":"Point"}
}