{
  "type": "Feature",
  "properties": {
    "addr:full":"2884 34th St N St Petersburg FL 33713",
    "addr:housenumber":"2884",
    "addr:postcode":"33713",
    "addr:street":"34Th St N",
    "iso:country":"US",
    "sg:address":"2884 34th St N",
    "sg:city":"St Petersburg",
    "sg:classifiers":[
        {
            "category":"Building & Trades",
            "subcategory":"Equipment Rental",
            "type":"Services"
        }
    ],
    "sg:phone":"+1 727 520 1415",
    "sg:postcode":"33713",
    "sg:province":"FL",
    "sg:tags":[
        "leasing",
        "furniture"
    ],
    "wof:name":"Aaron's Rental Purchase",
    "wof:placetype":"venue"
},
  "geometry": {"coordinates":[-82.679565,27.798421],"type":"Point"}
}