{
  "type": "Feature",
  "properties": {
    "iso:country":"US",
    "sg:address":"7495 W Atlantic Ave",
    "sg:city":"Delray Beach",
    "sg:classifiers":[
        {
            "category":"Retail",
            "subcategory":"Repair Shop",
            "type":"Services"
        }
    ],
    "sg:phone":"+1 561 495 0310",
    "sg:postcode":"33446",
    "sg:province":"FL",
    "sg:tags":[
        "television",
        "set"
    ],
    "wof:name":"Murrystv",
    "wof:placetype":"venue"
},
  "geometry": {"coordinates":[-80.163426,26.453708],"type":"Point"}
}