{
  "type": "Feature",
  "properties": {
    "addr:full":"150 SE 2nd Ave Deerfield Beach FL 33441",
    "addr:housenumber":"150",
    "addr:postcode":"33441",
    "addr:street":"Se 2Nd Ave",
    "iso:country":"US",
    "sg:address":"150 SE 2nd Ave",
    "sg:city":"Deerfield Beach",
    "sg:classifiers":[
        {
            "category":"Government",
            "subcategory":"Office",
            "type":"Public Place"
        }
    ],
    "sg:phone":"+1 954 480 4264",
    "sg:postcode":"33441",
    "sg:province":"FL",
    "sg:tags":[
        "village"
    ],
    "wof:name":"City Commission",
    "wof:placetype":"venue"
},
  "geometry": {"coordinates":[-80.099644,26.316704],"type":"Point"}
}