{
  "type": "Feature",
  "properties": {
    "addr:full":"5216 Cortez Dr Orlando FL 32808",
    "addr:housenumber":"5216",
    "addr:postcode":"32808",
    "addr:street":"Cortez Dr",
    "iso:country":"US",
    "sg:address":"5216 Cortez Dr",
    "sg:city":"Orlando",
    "sg:classifiers":[
        {
            "category":"Building & Trades",
            "subcategory":"Cleaning & Sanitation",
            "type":"Services"
        }
    ],
    "sg:phone":"+1 407 298 0436",
    "sg:postcode":"32808",
    "sg:province":"FL",
    "sg:tags":[
        "janitor"
    ],
    "wof:name":"Toni's Cleaning Svc Inc",
    "wof:placetype":"venue"
},
  "geometry": {"coordinates":[-81.453985,28.561559],"type":"Point"}
}