{
  "type": "Feature",
  "properties": {
    "iso:country":"US",
    "sg:address":"2515 Enterprise Rd",
    "sg:city":"Orange City",
    "sg:classifiers":[
        {
            "category":"Real Estate",
            "subcategory":"Real Estate Operator",
            "type":"Services"
        }
    ],
    "sg:phone":"+1 386 775 2697",
    "sg:postcode":"32763",
    "sg:province":"FL",
    "sg:tags":[
        "building",
        "apartment"
    ],
    "wof:name":"Villas Of Orange City",
    "wof:placetype":"venue"
},
  "geometry": {"coordinates":[-81.29524000000001,28.917558],"type":"Point"}
}