{
  "type": "Feature",
  "properties": {
    "addr:full":"840 SW 8th St Miami FL 33130",
    "addr:housenumber":"840",
    "addr:postcode":"33130",
    "addr:street":"Sw 8Th St",
    "iso:country":"US",
    "sg:address":"840 SW 8th St",
    "sg:city":"Miami",
    "sg:classifiers":[
        {
            "category":"Retail",
            "subcategory":"Laundry & Dry Cleaning",
            "type":"Services"
        }
    ],
    "sg:phone":"+1 305 856 6513",
    "sg:postcode":"33130",
    "sg:province":"FL",
    "sg:tags":[
        "laundries-self",
        "commercial",
        "cleaner"
    ],
    "wof:name":"One Stop Cleaners & Laundry",
    "wof:placetype":"venue"
},
  "geometry": {"coordinates":[-80.20839700000001,25.7661],"type":"Point"}
}