{
  "type": "Feature",
  "properties": {
    "addr:full":"440 Turnbull Bay Rd New Smyrna Beach FL 32168",
    "addr:housenumber":"440",
    "addr:postcode":"32168",
    "addr:street":"Turnbull Bay Rd",
    "iso:country":"US",
    "sg:address":"440 Turnbull Bay Rd",
    "sg:city":"New Smyrna Beach",
    "sg:classifiers":[
        {
            "category":"Freight",
            "type":"Transportation"
        }
    ],
    "sg:phone":"+1 386 423 1607",
    "sg:postcode":"32168",
    "sg:province":"FL",
    "sg:tags":[
        "commercial",
        "storage"
    ],
    "wof:name":"Southeast Sheds & Self Storage",
    "wof:placetype":"venue"
},
  "geometry": {"coordinates":[-80.938255,29.03998],"type":"Point"}
}