{
  "type": "Feature",
  "properties": {
    "addr:full":"18440 Paulson Dr Port Charlotte FL 33954",
    "addr:housenumber":"18440",
    "addr:postcode":"33954",
    "addr:street":"Paulson Dr",
    "iso:country":"US",
    "sg:address":"18440 Paulson Dr",
    "sg:city":"Port Charlotte",
    "sg:classifiers":[
        {
            "category":"Building & Trades",
            "subcategory":"Construction",
            "type":"Services"
        }
    ],
    "sg:phone":"+1 941 624 3887",
    "sg:postcode":"33954",
    "sg:province":"FL",
    "sg:tags":[
        "dry wall",
        "contractor"
    ],
    "wof:name":"Shirley Construction & Drywall",
    "wof:placetype":"venue"
},
  "geometry": {"coordinates":[-82.14597999999999,27.016709],"type":"Point"}
}