{
  "type": "Feature",
  "properties": {
    "addr:full":"7978 Cooper Creek Blvd University Park FL 34201",
    "addr:housenumber":"7978",
    "addr:postcode":"34201",
    "addr:street":"Cooper Creek Blvd",
    "iso:country":"US",
    "sg:address":"7978 Cooper Creek Blvd",
    "sg:city":"University Park",
    "sg:classifiers":[
        {
            "category":"Health Services",
            "subcategory":"Doctor",
            "type":"Services"
        }
    ],
    "sg:phone":"+1 941 359 9255",
    "sg:postcode":"34201",
    "sg:province":"FL",
    "sg:tags":[
        "physician",
        "surgeon"
    ],
    "wof:name":"Family Medicine Specialists",
    "wof:placetype":"venue"
},
  "geometry": {"coordinates":[-82.454932,27.397503],"type":"Point"}
}