{
  "type": "Feature",
  "properties": {
    "iso:country":"US",
    "sg:address":"1485 Florida Mall Ave",
    "sg:city":"Orlando",
    "sg:classifiers":[
        {
            "category":"Shopping",
            "subcategory":"Clothing, Apparel, & Fashions",
            "type":"Retail Goods"
        }
    ],
    "sg:phone":"+1 407 855 0821",
    "sg:postcode":"32809",
    "sg:province":"FL",
    "sg:tags":[
        "theatrical",
        "costume"
    ],
    "wof:name":"Spirit Halloween",
    "wof:placetype":"venue"
},
  "geometry": {"coordinates":[-81.39904199999999,28.448282],"type":"Point"}
}