{
  "type": "Feature",
  "properties": {
    "iso:country":"US",
    "sg:address":"2929 Wilderness Blvd E",
    "sg:city":"Parrish",
    "sg:classifiers":[
        {
            "category":"Shopping",
            "subcategory":"Clothing, Apparel, & Fashions",
            "type":"Retail Goods"
        }
    ],
    "sg:phone":"+1 941 776 3451",
    "sg:postcode":"34219",
    "sg:province":"FL",
    "wof:name":"Dream Links Golf Center Bra",
    "wof:placetype":"venue"
},
  "geometry": {"coordinates":[-82.434575,27.545418],"type":"Point"}
}