{
  "type": "Feature",
  "properties": {
    "iso:country":"US",
    "sg:address":"7176 Cardinal St",
    "sg:city":"Florahome",
    "sg:classifiers":[
        {
            "category":"Home & Garden",
            "subcategory":"Carpets & Floor Coverings",
            "type":"Retail Goods"
        }
    ],
    "sg:phone":"+1 386 661 2097",
    "sg:postcode":"32140",
    "sg:province":"FL",
    "sg:tags":[
        "material"
    ],
    "wof:name":"R L P Flooring",
    "wof:placetype":"venue"
},
  "geometry": {"coordinates":[-81.87990600000001,29.801147],"type":"Point"}
}