{
  "type": "Feature",
  "properties": {
    "addr:full":"2952 Poinsettia Ave West Palm Beach FL 33407",
    "addr:housenumber":"2952",
    "addr:postcode":"33407",
    "addr:street":"Poinsettia Ave",
    "iso:country":"US",
    "sg:address":"2952 Poinsettia Ave",
    "sg:city":"West Palm Beach",
    "sg:classifiers":[
        {
            "category":"Building & Trades",
            "subcategory":"Pest Control",
            "type":"Services"
        }
    ],
    "sg:phone":"+1 561 243 8667",
    "sg:postcode":"33407",
    "sg:province":"FL",
    "wof:name":"Trapper John Animal Control",
    "wof:placetype":"venue"
},
  "geometry": {"coordinates":[-80.052648,26.739505],"type":"Point"}
}