{
  "type": "Feature",
  "properties": {
    "addr:full":"1360 Ocean Shore Blvd Ormond Beach FL 32176",
    "addr:housenumber":"1360",
    "addr:postcode":"32176",
    "addr:street":"Ocean Shore Blvd",
    "iso:country":"US",
    "sg:address":"1360 Ocean Shore Blvd",
    "sg:city":"Ormond Beach",
    "sg:classifiers":[
        {
            "category":"Home & Garden",
            "subcategory":"Building Materials",
            "type":"Retail Goods"
        }
    ],
    "sg:phone":"+1 386 441 3690",
    "sg:postcode":"32176",
    "sg:province":"FL",
    "sg:tags":[
        "door"
    ],
    "wof:name":"American Garage Door Sales",
    "wof:placetype":"venue"
},
  "geometry": {"coordinates":[-81.05685099999999,29.326255],"type":"Point"}
}