{
  "type": "Feature",
  "properties": {
    "iso:country":"US",
    "sg:address":"375 Iowa Woods Cir W",
    "sg:city":"Orlando",
    "sg:classifiers":[
        {
            "category":"Retail",
            "subcategory":"Animal Services",
            "type":"Services"
        }
    ],
    "sg:phone":"+1 321 276 2989",
    "sg:postcode":"32824",
    "sg:province":"FL",
    "sg:tags":[
        "pet",
        "grooming",
        "washing"
    ],
    "wof:name":"Deb's Groomin On The Go",
    "wof:placetype":"venue"
},
  "geometry": {"coordinates":[-81.371487,28.379428],"type":"Point"}
}