{
  "type": "Feature",
  "properties": {
    "iso:country":"US",
    "sg:address":"8711 Newton Rd",
    "sg:city":"Jacksonville",
    "sg:classifiers":[
        {
            "category":"Retail",
            "subcategory":"Self-service Laundry",
            "type":"Services"
        }
    ],
    "sg:phone":"+1 904 642 4210",
    "sg:postcode":"32216",
    "sg:province":"FL",
    "sg:tags":[
        "coin"
    ],
    "wof:name":"RC International Coin Laundry",
    "wof:placetype":"venue"
},
  "geometry": {"coordinates":[-81.560975,30.275627],"type":"Point"}
}