{
  "type": "Feature",
  "properties": {
    "iso:country":"US",
    "sg:address":"5913 N Ola Ave",
    "sg:city":"Tampa",
    "sg:classifiers":[
        {
            "category":"Home & Garden",
            "subcategory":"Carpets & Floor Coverings",
            "type":"Retail Goods"
        }
    ],
    "sg:phone":"+1 813 238 0910",
    "sg:postcode":"33604",
    "sg:province":"FL",
    "sg:tags":[
        "distributor",
        "rug",
        "manufacturer"
    ],
    "wof:name":"Jc Carpets Solutions Inc",
    "wof:placetype":"venue"
},
  "geometry": {"coordinates":[-82.463559,27.999735],"type":"Point"}
}