{
  "type": "Feature",
  "properties": {
    "addr:full":"11721 NW 38th Pl Fort Lauderdale FL 33323",
    "addr:housenumber":"11721",
    "addr:postcode":"33323",
    "addr:street":"Nw 38Th Pl",
    "iso:country":"US",
    "sg:address":"11721 NW 38th Pl",
    "sg:city":"Fort Lauderdale",
    "sg:classifiers":[
        {
            "category":"Shopping",
            "type":"Retail Goods"
        }
    ],
    "sg:phone":"+1 954 749 6443",
    "sg:postcode":"33323",
    "sg:province":"FL",
    "sg:tags":[
        "merchandise"
    ],
    "wof:name":"Sword Warehouse",
    "wof:placetype":"venue"
},
  "geometry": {"coordinates":[-80.304728,26.173571],"type":"Point"}
}