{
  "type": "Feature",
  "properties": {
    "addr:full":"1357 Tiber Ave Jacksonville FL 32207",
    "addr:housenumber":"1357",
    "addr:postcode":"32207",
    "addr:street":"Tiber Ave",
    "iso:country":"US",
    "sg:address":"1357 Tiber Ave",
    "sg:city":"Jacksonville",
    "sg:classifiers":[
        {
            "category":"Insurance",
            "subcategory":"Insurance Agent",
            "type":"Services"
        }
    ],
    "sg:phone":"+1 904 396 2612",
    "sg:postcode":"32207",
    "sg:province":"FL",
    "wof:name":"Joseph Foy",
    "wof:placetype":"venue"
},
  "geometry": {"coordinates":[-81.632513,30.309408],"type":"Point"}
}