{
  "type": "Feature",
  "properties": {
    "iso:country":"US",
    "sg:address":"1050 Riverside Ave",
    "sg:city":"Jacksonville",
    "sg:classifiers":[
        {
            "category":"Professional",
            "subcategory":"Lawyer & Legal Services",
            "type":"Services"
        }
    ],
    "sg:phone":"+1 904 354 9000",
    "sg:postcode":"32204",
    "sg:province":"FL",
    "wof:name":"McGiffin & Gibson Customs",
    "wof:placetype":"venue"
},
  "geometry": {"coordinates":[-81.677745,30.313882],"type":"Point"}
}