{
  "type": "Feature",
  "properties": {
    "iso:country":"US",
    "sg:address":"5605 Commercial Blvd",
    "sg:city":"Winter Haven",
    "sg:classifiers":[
        {
            "category":"Building & Trades",
            "subcategory":"Construction",
            "type":"Services"
        }
    ],
    "sg:phone":"+1 863 967 6550",
    "sg:postcode":"33880",
    "sg:province":"FL",
    "sg:tags":[
        "contractor"
    ],
    "wof:name":"American Truss Co",
    "wof:placetype":"venue"
},
  "geometry": {"coordinates":[-81.78377399999999,28.035257],"type":"Point"}
}