{
  "type": "Feature",
  "properties": {
    "addr:full":"4838 Camberlane Dr Orlando FL 32812",
    "addr:housenumber":"4838",
    "addr:postcode":"32812",
    "addr:street":"Camberlane Dr",
    "iso:country":"US",
    "sg:address":"4838 Camberlane Dr",
    "sg:city":"Orlando",
    "sg:classifiers":[
        {
            "category":"Building & Trades",
            "subcategory":"Landscaping Services",
            "type":"Services"
        }
    ],
    "sg:phone":"+1 407 273 2818",
    "sg:postcode":"32812",
    "sg:province":"FL",
    "wof:name":"Michael Withrow Orrin",
    "wof:placetype":"venue"
},
  "geometry": {"coordinates":[-81.31206899999999,28.485617],"type":"Point"}
}