{
  "type": "Feature",
  "properties": {
    "iso:country":"US",
    "sg:address":"6631 Falconsgate Ave",
    "sg:city":"Fort Lauderdale",
    "sg:classifiers":[
        {
            "category":"Building & Trades",
            "subcategory":"Construction",
            "type":"Services"
        }
    ],
    "sg:phone":"+1 954 680 9836",
    "sg:postcode":"33331",
    "sg:province":"FL",
    "sg:tags":[
        "specializing",
        "knock",
        "ceiling",
        "d",
        "contractor",
        "popcorn"
    ],
    "wof:name":"All County Textures Inc",
    "wof:placetype":"venue"
},
  "geometry": {"coordinates":[-80.346977,26.037157],"type":"Point"}
}