{
  "type": "Feature",
  "properties": {
    "iso:country":"US",
    "sg:address":"10855 SW 72nd St",
    "sg:city":"Miami",
    "sg:classifiers":[
        {
            "category":"Arts & Performance",
            "subcategory":"Dance",
            "type":"Entertainment"
        }
    ],
    "sg:phone":"+1 305 595 9002",
    "sg:postcode":"33173",
    "sg:province":"FL",
    "sg:tags":[
        "instruction",
        "dancing"
    ],
    "wof:name":"Miami Dance Theater",
    "wof:placetype":"venue"
},
  "geometry": {"coordinates":[-80.368809,25.701066],"type":"Point"}
}