{
  "type": "Feature",
  "properties": {
    "iso:country":"US",
    "sg:address":"450 Racetrack Rd NW",
    "sg:city":"Fort Walton Bch",
    "sg:classifiers":[
        {
            "category":"Retail",
            "subcategory":"Laundry & Dry Cleaning",
            "type":"Services"
        }
    ],
    "sg:phone":"+1 850 863 1705",
    "sg:postcode":"32547",
    "sg:province":"FL",
    "sg:tags":[
        "cleaners"
    ],
    "wof:name":"Dixie Service Cleaners",
    "wof:placetype":"venue"
},
  "geometry": {"coordinates":[-86.638451,30.449655],"type":"Point"}
}