{
  "type": "Feature",
  "properties": {
    "iso:country":"US",
    "sg:address":"2400 S Ridgewood Ave",
    "sg:city":"Daytona Beach",
    "sg:classifiers":[
        {
            "category":"Professional",
            "subcategory":"Research",
            "type":"Services"
        }
    ],
    "sg:phone":"+1 386 304 1300",
    "sg:postcode":"32119",
    "sg:province":"FL",
    "sg:tags":[
        "nonphysical",
        "consulting",
        "commercial",
        "business"
    ],
    "wof:name":"Faneuil Group",
    "wof:placetype":"venue"
},
  "geometry": {"coordinates":[-80.998042,29.164451],"type":"Point"}
}