{
  "type": "Feature",
  "properties": {
    "addr:full":"8617 E Colonial Dr Ste 1500 Orlando FL 32817",
    "addr:housenumber":"8617",
    "addr:postcode":"32817",
    "addr:street":"E Colonial Dr Ste 1500",
    "iso:country":"US",
    "sg:address":"8617 E Colonial Dr Ste 1500",
    "sg:city":"Orlando",
    "sg:classifiers":[
        {
            "category":"Professional",
            "subcategory":"Advertising",
            "type":"Services"
        }
    ],
    "sg:phone":"+1 407 249 8248",
    "sg:postcode":"32817",
    "sg:province":"FL",
    "sg:tags":[
        "advertising-telephone",
        "fax",
        "telemarketing"
    ],
    "wof:name":"Advanced Verification Systems, Inc",
    "wof:placetype":"venue"
},
  "geometry": {"coordinates":[-81.270618,28.56846],"type":"Point"}
}