{
  "type": "Feature",
  "properties": {
    "iso:country":"US",
    "sg:address":"1300 Mandan Ln",
    "sg:city":"Ormond Beach",
    "sg:classifiers":[
        {
            "category":"Professional",
            "subcategory":"Management & Consulting",
            "type":"Services"
        }
    ],
    "sg:phone":"+1 386 672 1944",
    "sg:postcode":"32174",
    "sg:province":"FL",
    "wof:name":"Ricwan Enterprises",
    "wof:placetype":"venue"
},
  "geometry": {"coordinates":[-81.140502,29.407134],"type":"Point"}
}