{
  "type": "Feature",
  "properties": {
    "iso:country":"US",
    "sg:address":"2201 Cuba St",
    "sg:city":"Fort Myers",
    "sg:classifiers":[
        {
            "category":"Bars & Pubs",
            "type":"Food & Drink"
        }
    ],
    "sg:phone":"+1 239 332 0525",
    "sg:postcode":"33916",
    "sg:province":"FL",
    "wof:name":"Ladies Beer Parlor",
    "wof:placetype":"venue"
},
  "geometry": {"coordinates":[-81.84759699999999,26.637496],"type":"Point"}
}