{
  "type": "Feature",
  "properties": {
    "iso:country":"US",
    "sg:address":"4707 Central Ave",
    "sg:city":"Saint Petersburg",
    "sg:classifiers":[
        {
            "category":"Health Services",
            "subcategory":"Health Practitioner",
            "type":"Services"
        }
    ],
    "sg:phone":"+1 727 328 9882",
    "sg:postcode":"33713",
    "sg:province":"FL",
    "wof:name":"Kirk Stokes PHD",
    "wof:placetype":"venue"
},
  "geometry": {"coordinates":[-82.69835999999999,27.771012],"type":"Point"}
}