{
  "type": "Feature",
  "properties": {
    "addr:full":"155 S Pompano Pkwy Pompano Beach FL 33069",
    "addr:housenumber":"155",
    "addr:postcode":"33069",
    "addr:street":"S Pompano Pkwy",
    "iso:country":"US",
    "sg:address":"155 S Pompano Pkwy",
    "sg:city":"Pompano Beach",
    "sg:classifiers":[
        {
            "category":"Social Services",
            "type":"Services"
        }
    ],
    "sg:phone":"+1 954 917 8099",
    "sg:postcode":"33069",
    "sg:province":"FL",
    "wof:name":"Tender Loving Care Adlt Day CT",
    "wof:placetype":"venue"
},
  "geometry": {"coordinates":[-80.156622,26.228829],"type":"Point"}
}