{
  "type": "Feature",
  "properties": {
    "iso:country":"US",
    "sg:address":"4205 S Hopkins Ave",
    "sg:city":"Titusville",
    "sg:classifiers":[
        {
            "category":"Retail",
            "subcategory":"Repair Shop",
            "type":"Services"
        }
    ],
    "sg:phone":"+1 321 267 9936",
    "sg:postcode":"32780",
    "sg:province":"FL",
    "sg:tags":[
        "upholsterer"
    ],
    "wof:name":"Fusco's Upholstery",
    "wof:placetype":"venue"
},
  "geometry": {"coordinates":[-80.802299,28.564849],"type":"Point"}
}