{
  "type": "Feature",
  "properties": {
    "iso:country":"US",
    "sg:address":"2853 S Pine Ave",
    "sg:city":"Ocala",
    "sg:classifiers":[
        {
            "category":"Retail",
            "subcategory":"Storage",
            "type":"Services"
        }
    ],
    "sg:phone":"+1 352 535 0981",
    "sg:postcode":"34471",
    "sg:province":"FL",
    "sg:tags":[
        "automobile",
        "self",
        "commercial",
        "household"
    ],
    "sg:website":"http://national.citysearch.com/profile/external/604193132/ocala_fl/1st_american_storage_ocala.html?publisher=yellowpages&reference_id=1&placement=ypwebsitemip",
    "wof:name":"1st American Storage - Ocala",
    "wof:placetype":"venue"
},
  "geometry": {"coordinates":[-82.131693,29.15974],"type":"Point"}
}