{
  "type": "Feature",
  "properties": {
    "iso:country":"US",
    "sg:address":"2371 S McCall Rd",
    "sg:city":"Englewood",
    "sg:classifiers":[
        {
            "category":"Manufacturing",
            "subcategory":"Signs",
            "type":"Manufacturing & Wholesale Goods"
        }
    ],
    "sg:phone":"+1 941 460 0260",
    "sg:postcode":"34224",
    "sg:province":"FL",
    "sg:tags":[
        "specialty",
        "mfg"
    ],
    "wof:name":"Quick Signs & Lettering",
    "wof:placetype":"venue"
},
  "geometry": {"coordinates":[-82.319835,26.93451],"type":"Point"}
}