{
  "type": "Feature",
  "properties": {
    "iso:country":"US",
    "sg:address":"723 N Bay St",
    "sg:city":"Eustis",
    "sg:classifiers":[
        {
            "category":"Banks & Credit Unions",
            "subcategory":"Bank",
            "type":"Services"
        }
    ],
    "sg:phone":"+1 352 357 4104",
    "sg:postcode":"32726",
    "sg:province":"FL",
    "sg:tags":[
        "personal",
        "institution"
    ],
    "wof:name":"William J Church Inc",
    "wof:placetype":"venue"
},
  "geometry": {"coordinates":[-81.685706,28.860197],"type":"Point"}
}