{
  "type": "Feature",
  "properties": {
    "iso:country":"US",
    "sg:address":"4201 N Washington Blvd",
    "sg:city":"Sarasota",
    "sg:classifiers":[
        {
            "category":"Autos & Motor Vehicles",
            "subcategory":"Motorcycle Sales",
            "type":"Retail Goods"
        }
    ],
    "sg:phone":"+1 941 358 7938",
    "sg:postcode":"34234",
    "sg:province":"FL",
    "sg:tags":[
        "scooter",
        "parts",
        "aftermarket",
        "accessory"
    ],
    "wof:name":"Sarasota Cycle World Inc",
    "wof:placetype":"venue"
},
  "geometry": {"coordinates":[-82.53088700000001,27.370405],"type":"Point"}
}