{
  "type": "Feature",
  "properties": {
    "addr:full":"4045 Christopher Ln Crestview FL 32539",
    "addr:housenumber":"4045",
    "addr:postcode":"32539",
    "addr:street":"Christopher Ln",
    "iso:country":"US",
    "sg:address":"4045 Christopher Ln",
    "sg:city":"Crestview",
    "sg:classifiers":[
        {
            "category":"Building & Trades",
            "subcategory":"Plumbing",
            "type":"Services"
        }
    ],
    "sg:phone":"+1 850 683 0974",
    "sg:postcode":"32539",
    "sg:province":"FL",
    "sg:tags":[
        "plumber",
        "industrial",
        "contractors-commercial"
    ],
    "wof:name":"Stan's Plumbing Inc",
    "wof:placetype":"venue"
},
  "geometry": {"coordinates":[-86.454189,30.815229],"type":"Point"}
}