{
  "type": "Feature",
  "properties": {
    "addr:full":"5142 8th St Zephyrhills FL 33542",
    "addr:housenumber":"5142",
    "addr:postcode":"33542",
    "addr:street":"8Th St",
    "iso:country":"US",
    "sg:address":"5142 8th St",
    "sg:city":"Zephyrhills",
    "sg:classifiers":[
        {
            "category":"Restaurant",
            "type":"Food & Drink"
        }
    ],
    "sg:phone":"+1 813 788 7756",
    "sg:postcode":"33542",
    "sg:province":"FL",
    "sg:tags":[
        "parlor",
        "ice",
        "cream"
    ],
    "wof:name":"Church's Treats LTD Co",
    "wof:placetype":"venue"
},
  "geometry": {"coordinates":[-82.179395,28.233324],"type":"Point"}
}