{
  "type": "Feature",
  "properties": {
    "iso:country":"US",
    "sg:address":"255 Old Sanford Oviedo Rd",
    "sg:city":"Winter Springs",
    "sg:classifiers":[
        {
            "category":"Building & Trades",
            "subcategory":"Plumbing",
            "type":"Services"
        }
    ],
    "sg:phone":"+1 407 327 6000",
    "sg:postcode":"32708",
    "sg:province":"FL",
    "sg:website":"www.modernpi.com",
    "wof:name":"Modern Plumbing Industries Inc",
    "wof:placetype":"venue"
},
  "geometry": {"coordinates":[-81.299132,28.706322],"type":"Point"}
}