{
  "type": "Feature",
  "properties": {
    "addr:full":"210 Lake Hollingsworth Dr Lakeland FL 33803",
    "addr:housenumber":"210",
    "addr:postcode":"33803",
    "addr:street":"Lake Hollingsworth Dr",
    "iso:country":"US",
    "sg:address":"210 Lake Hollingsworth Dr",
    "sg:city":"Lakeland",
    "sg:classifiers":[
        {
            "category":"Wholesale",
            "subcategory":"Toys & Hobbies",
            "type":"Manufacturing & Wholesale Goods"
        }
    ],
    "sg:phone":"+1 863 687 2299",
    "sg:postcode":"33803",
    "sg:province":"FL",
    "sg:tags":[
        "wholesaler"
    ],
    "wof:name":"Hickey's Wholesale",
    "wof:placetype":"venue"
},
  "geometry": {"coordinates":[-81.938457,28.026923],"type":"Point"}
}