{
  "type": "Feature",
  "properties": {
    "addr:full":"680 21st St Vero Beach FL 32960",
    "addr:housenumber":"680",
    "addr:postcode":"32960",
    "addr:street":"21St St",
    "iso:country":"US",
    "sg:address":"680 21st St",
    "sg:city":"Vero Beach",
    "sg:classifiers":[
        {
            "category":"Shopping",
            "subcategory":"Used Merchandise",
            "type":"Retail Goods"
        }
    ],
    "sg:phone":"+1 772 770 6030",
    "sg:postcode":"32960",
    "sg:province":"FL",
    "sg:tags":[
        "shop",
        "consignment"
    ],
    "wof:name":"Coco Couture Consignments",
    "wof:placetype":"venue"
},
  "geometry": {"coordinates":[-80.386866,27.639817],"type":"Point"}
}