{
  "type": "Feature",
  "properties": {
    "addr:full":"4803 E Hillsborough Ave Tampa FL 33610",
    "addr:housenumber":"4803",
    "addr:postcode":"33610",
    "addr:street":"E Hillsborough Ave",
    "iso:country":"US",
    "sg:address":"4803 E Hillsborough Ave",
    "sg:city":"Tampa",
    "sg:classifiers":[
        {
            "category":"Real Estate",
            "subcategory":"Real Estate Operator",
            "type":"Services"
        }
    ],
    "sg:phone":"+1 813 621 6799",
    "sg:postcode":"33610",
    "sg:province":"FL",
    "sg:tags":[
        "mobile",
        "home",
        "site"
    ],
    "wof:name":"Rainbow Mobile Home Park",
    "wof:placetype":"venue"
},
  "geometry": {"coordinates":[-82.403217,27.996027],"type":"Point"}
}