{
  "type": "Feature",
  "properties": {
    "iso:country":"US",
    "sg:address":"341 Yarmouth St",
    "sg:city":"Marco Island",
    "sg:classifiers":[
        {
            "category":"Manufacturing",
            "subcategory":"Signs",
            "type":"Manufacturing & Wholesale Goods"
        }
    ],
    "sg:phone":"+1 239 642 4006",
    "sg:postcode":"34145",
    "sg:province":"FL",
    "sg:tags":[
        "specialty",
        "mfg"
    ],
    "wof:name":"Sherry Allen Signs",
    "wof:placetype":"venue"
},
  "geometry": {"coordinates":[-81.70962,25.930055],"type":"Point"}
}