{
  "type": "Feature",
  "properties": {
    "iso:country":"US",
    "sg:address":"2775 NE 187 ST",
    "sg:city":"Aventura",
    "sg:classifiers":[
        {
            "category":"Professional",
            "subcategory":"Computer Services",
            "type":"Services"
        }
    ],
    "sg:phone":"+1 305 974 1368",
    "sg:postcode":"33180",
    "sg:province":"FL",
    "sg:tags":[
        "repair"
    ],
    "sg:website":"www.WOOPTI.com",
    "wof:name":"WOOPTI - Flat Rate Computer Repair",
    "wof:placetype":"venue"
},
  "geometry": {"coordinates":[-80.144184,25.949252],"type":"Point"}
}