{
  "type": "Feature",
  "properties": {
    "iso:country":"US",
    "sg:address":"13801 Innerarity Point Rd",
    "sg:city":"Pensacola",
    "sg:classifiers":[
        {
            "category":"Organizations",
            "subcategory":"Religious Organization",
            "type":"Services"
        }
    ],
    "sg:phone":"+1 850 492 1545",
    "sg:postcode":"32507",
    "sg:province":"FL",
    "sg:tags":[
        "church"
    ],
    "sg:website":"www.inneraritypointbaptist.org",
    "wof:name":"Innerarity Point Baptist",
    "wof:placetype":"venue"
},
  "geometry": {"coordinates":[-87.43028200000001,30.317953],"type":"Point"}
}