{
  "type": "Feature",
  "properties": {
    "addr:full":"50 Cocoanut Row Palm Beach FL 33480",
    "addr:housenumber":"50",
    "addr:postcode":"33480",
    "addr:street":"Cocoanut Row",
    "iso:country":"US",
    "sg:address":"50 Cocoanut Row",
    "sg:city":"Palm Beach",
    "sg:classifiers":[
        {
            "category":"Health Services",
            "subcategory":"Doctor",
            "type":"Services"
        }
    ],
    "sg:phone":"+1 561 833 2611",
    "sg:postcode":"33480",
    "sg:province":"FL",
    "sg:tags":[
        "dentist"
    ],
    "wof:name":"Francis P Conroy DMD PA",
    "wof:placetype":"venue"
},
  "geometry": {"coordinates":[-80.040983,26.71809],"type":"Point"}
}