{
  "type": "Feature",
  "properties": {
    "iso:country":"US",
    "sg:address":"10 NE 13th St",
    "sg:city":"Delray Beach",
    "sg:classifiers":[
        {
            "category":"Travel",
            "subcategory":"Travel Agent",
            "type":"Entertainment"
        }
    ],
    "sg:phone":"+1 561 272 7620",
    "sg:postcode":"33444",
    "sg:province":"FL",
    "sg:tags":[
        "agency",
        "bureau"
    ],
    "wof:name":"Travel Media",
    "wof:placetype":"venue"
},
  "geometry": {"coordinates":[-80.071077,26.478237],"type":"Point"}
}