{
  "type": "Feature",
  "properties": {
    "iso:country":"US",
    "sg:address":"3501 W Vine St",
    "sg:city":"Kissimmee",
    "sg:classifiers":[
        {
            "category":"Freight",
            "type":"Transportation"
        }
    ],
    "sg:phone":"+1 407 343 8383",
    "sg:postcode":"34741",
    "sg:province":"FL",
    "sg:tags":[
        "warehouse",
        "self",
        "storage"
    ],
    "wof:name":"AAA Mini Storage",
    "wof:placetype":"venue"
},
  "geometry": {"coordinates":[-81.440697,28.304506],"type":"Point"}
}