{
  "type": "Feature",
  "properties": {
    "iso:country":"US",
    "sg:address":"14821 Ben C Pratt/6 Mile Cypress Pkwy",
    "sg:city":"Fort Myers",
    "sg:classifiers":[
        {
            "category":"Shopping",
            "subcategory":"Department Store",
            "type":"Retail Goods"
        },
        {
            "category":"Health Services",
            "subcategory":"Optometrist",
            "type":"Services"
        }
    ],
    "sg:phone":"+1 239 437 1844",
    "sg:postcode":"33912",
    "sg:province":"FL",
    "wof:name":"Sills Richard OD",
    "wof:placetype":"venue"
},
  "geometry": {"coordinates":[-81.868493,26.526077],"type":"Point"}
}