{
  "type": "Feature",
  "properties": {
    "iso:country":"US",
    "sg:address":"3450 N Miami Ave",
    "sg:city":"Miami",
    "sg:classifiers":[
        {
            "category":"Arts & Performance",
            "subcategory":"Art Gallery",
            "type":"Entertainment"
        }
    ],
    "sg:postcode":"33127",
    "sg:province":"FL",
    "sg:website":"www.eastvillagegallery.net",
    "wof:name":"East Village Gallery",
    "wof:placetype":"venue"
},
  "geometry": {"coordinates":[-80.195566,25.808807],"type":"Point"}
}