{
  "type": "Feature",
  "properties": {
    "iso:country":"US",
    "sg:address":"11552 NW 34th Pl",
    "sg:city":"Fort Lauderdale",
    "sg:classifiers":[
        {
            "category":"Sports & Exercise",
            "subcategory":"Race Track",
            "type":"Entertainment"
        }
    ],
    "sg:phone":"+1 954 741 6881",
    "sg:postcode":"33323",
    "sg:province":"FL",
    "sg:tags":[
        "operation",
        "racing",
        "or"
    ],
    "wof:name":"Underdog Racing Enterprises",
    "wof:placetype":"venue"
},
  "geometry": {"coordinates":[-80.302931,26.168993],"type":"Point"}
}