{
  "type": "Feature",
  "properties": {
    "iso:country":"US",
    "sg:address":"1997 SE Co Hwy 484",
    "sg:city":"Belleview",
    "sg:classifiers":[
        {
            "category":"Recreation",
            "type":"Entertainment"
        }
    ],
    "sg:phone":"+1 352 245 4166",
    "sg:postcode":"34420",
    "sg:province":"FL",
    "sg:tags":[
        "range",
        "practice",
        "golf"
    ],
    "wof:name":"Hackaway's Driving Range",
    "wof:placetype":"venue"
},
  "geometry": {"coordinates":[-82.111706,29.025743],"type":"Point"}
}