{
  "type": "Feature",
  "properties": {
    "addr:full":"1370 NE 200th Ter Miami FL 33179",
    "addr:housenumber":"1370",
    "addr:postcode":"33179",
    "addr:street":"Ne 200Th Ter",
    "iso:country":"US",
    "sg:address":"1370 NE 200th Ter",
    "sg:city":"Miami",
    "sg:classifiers":[
        {
            "category":"Shopping",
            "subcategory":"Clothing, Apparel, & Fashions",
            "type":"Retail Goods"
        }
    ],
    "sg:phone":"+1 305 652 5624",
    "sg:postcode":"33179",
    "sg:province":"FL",
    "sg:tags":[
        "work",
        "uniform",
        "clothes"
    ],
    "wof:name":"City Uniforms Inc",
    "wof:placetype":"venue"
},
  "geometry": {"coordinates":[-80.17466,25.960431],"type":"Point"}
}