{
  "type": "Feature",
  "properties": {
    "iso:country":"US",
    "sg:address":"467 S Chickasaw Trl",
    "sg:city":"Orlando",
    "sg:classifiers":[
        {
            "category":"Retail",
            "subcategory":"Animal Services",
            "type":"Services"
        }
    ],
    "sg:phone":"+1 407 381 2400",
    "sg:postcode":"32825",
    "sg:province":"FL",
    "wof:name":"Best Friends Pet Grooming",
    "wof:placetype":"venue"
},
  "geometry": {"coordinates":[-81.275308,28.537087],"type":"Point"}
}