{
  "type": "Feature",
  "properties": {
    "addr:full":"22601 Cam del Mar Boca Raton FL 33433",
    "addr:housenumber":"22601",
    "addr:postcode":"33433",
    "addr:street":"Cam Del Mar",
    "iso:country":"US",
    "sg:address":"22601 Cam del Mar",
    "sg:city":"Boca Raton",
    "sg:classifiers":[
        {
            "category":"Health Services",
            "subcategory":"Nursing And Care Facility",
            "type":"Services"
        }
    ],
    "sg:phone":"+1 561 750 7100",
    "sg:postcode":"33433",
    "sg:province":"FL",
    "sg:tags":[
        "home",
        "retirement",
        "community"
    ],
    "wof:name":"Casa Del Mar",
    "wof:placetype":"venue"
},
  "geometry": {"coordinates":[-80.137299,26.343294],"type":"Point"}
}