{
  "type": "Feature",
  "properties": {
    "iso:country":"US",
    "sg:address":"4539 Old Military Trl",
    "sg:city":"West Palm Beach",
    "sg:classifiers":[
        {
            "category":"Shopping",
            "subcategory":"Computers & Home Electronics",
            "type":"Retail Goods"
        }
    ],
    "sg:phone":"+1 561 616 0157",
    "sg:postcode":"33417",
    "sg:province":"FL",
    "sg:tags":[
        "band",
        "radio"
    ],
    "wof:name":"Bob's Electronics",
    "wof:placetype":"venue"
},
  "geometry": {"coordinates":[-80.112161,26.714193],"type":"Point"}
}