{
  "type": "Feature",
  "properties": {
    "iso:country":"US",
    "sg:address":"221 Ruby Ave",
    "sg:city":"Kissimmee",
    "sg:classifiers":[
        {
            "category":"Insurance",
            "subcategory":"Insurance Agent",
            "type":"Services"
        }
    ],
    "sg:phone":"+1 407 846 6421",
    "sg:postcode":"34741",
    "sg:province":"FL",
    "wof:name":"Brooke Insurance",
    "wof:placetype":"venue"
},
  "geometry": {"coordinates":[-81.405537,28.290028],"type":"Point"}
}