{
  "type": "Feature",
  "properties": {
    "addr:full":"13213 Early Frost Cir Orlando FL 32828",
    "addr:housenumber":"13213",
    "addr:postcode":"32828",
    "addr:street":"Early Frost Cir",
    "iso:country":"US",
    "sg:address":"13213 Early Frost Cir",
    "sg:city":"Orlando",
    "sg:classifiers":[
        {
            "category":"Retail",
            "subcategory":"Car Wash",
            "type":"Services"
        }
    ],
    "sg:phone":"+1 407 281 4985",
    "sg:postcode":"32828",
    "sg:province":"FL",
    "sg:tags":[
        "carwash"
    ],
    "wof:name":"J&W Pressure Wash & General CL",
    "wof:placetype":"venue"
},
  "geometry": {"coordinates":[-81.15872400000001,28.530543],"type":"Point"}
}