{
  "type": "Feature",
  "properties": {
    "iso:country":"US",
    "sg:address":"6305 East 8th Ave",
    "sg:city":"Hialeah",
    "sg:classifiers":[
        {
            "category":"Building & Trades",
            "subcategory":"Construction",
            "type":"Services"
        },
        {
            "category":"Building & Trades",
            "subcategory":"Electrical",
            "type":"Services"
        }
    ],
    "sg:phone":"+1 786 879 3637",
    "sg:postcode":"33013",
    "sg:province":"FL",
    "sg:tags":[
        "roofing",
        "industrial",
        "electric",
        "mason",
        "contractors-commercial",
        "contractor",
        "demolition"
    ],
    "wof:name":"Sunshine Drywall Construction Services",
    "wof:placetype":"venue"
},
  "geometry": {"coordinates":[-80.26711400000001,25.880527],"type":"Point"}
}