{
  "type": "Feature",
  "properties": {
    "iso:country":"US",
    "sg:address":"21218 Saint Andrews Blvd",
    "sg:city":"Boca Raton",
    "sg:classifiers":[
        {
            "category":"Real Estate",
            "subcategory":"Real Estate Agent",
            "type":"Services"
        }
    ],
    "sg:phone":"+1 561 368 2879",
    "sg:postcode":"33433",
    "sg:province":"FL",
    "sg:tags":[
        "manager"
    ],
    "wof:name":"Pelican Management Services",
    "wof:placetype":"venue"
},
  "geometry": {"coordinates":[-80.13739200000001,26.359129],"type":"Point"}
}