{
  "type": "Feature",
  "properties": {
    "iso:country":"US",
    "sg:address":"1061 Riverside Ave",
    "sg:city":"Jacksonville",
    "sg:classifiers":[
        {
            "category":"Health Services",
            "subcategory":"Clinic",
            "type":"Services"
        }
    ],
    "sg:phone":"+1 904 281 0006",
    "sg:postcode":"32204",
    "sg:province":"FL",
    "sg:tags":[
        "information",
        "medical"
    ],
    "wof:name":"Specialty Disease Management",
    "wof:placetype":"venue"
},
  "geometry": {"coordinates":[-81.67835599999999,30.312892],"type":"Point"}
}