{
  "type": "Feature",
  "properties": {
    "iso:country":"US",
    "sg:address":"121 Iroquois St",
    "sg:city":"Tavernier",
    "sg:classifiers":[
        {
            "category":"Building & Trades",
            "subcategory":"Construction",
            "type":"Services"
        }
    ],
    "sg:phone":"+1 305 853 3343",
    "sg:postcode":"33070",
    "sg:province":"FL",
    "sg:tags":[
        "residential"
    ],
    "wof:name":"Mangrove Residential Contrs",
    "wof:placetype":"venue"
},
  "geometry": {"coordinates":[-80.54748600000001,24.983622],"type":"Point"}
}