{
  "type": "Feature",
  "properties": {
    "iso:country":"US",
    "sg:address":"430 NW 39th Ave",
    "sg:city":"Gainesville",
    "sg:classifiers":[
        {
            "category":"Building & Trades",
            "subcategory":"Landscaping Services",
            "type":"Services"
        },
        {
            "category":"Building & Trades",
            "subcategory":"Pest Control",
            "type":"Services"
        }
    ],
    "sg:phone":"+1 352 338 1013",
    "sg:postcode":"32609",
    "sg:province":"FL",
    "sg:tags":[
        "lawn",
        "industrial",
        "services-commercial",
        "termite",
        "maintenance"
    ],
    "sg:website":"http://www.realpagessites.com/gainesvillepestcontrol",
    "wof:name":"Gainesville Pest Control",
    "wof:placetype":"venue"
},
  "geometry": {"coordinates":[-82.328563,29.68855],"type":"Point"}
}