{
  "type": "Feature",
  "properties": {
    "iso:country":"US",
    "sg:address":"560 S Brevard Ave",
    "sg:city":"Cocoa Beach",
    "sg:classifiers":[
        {
            "category":"Professional",
            "subcategory":"Management & Consulting",
            "type":"Services"
        }
    ],
    "sg:phone":"+1 321 917 5679",
    "sg:postcode":"32931",
    "sg:province":"FL",
    "sg:tags":[
        "e",
        "database"
    ],
    "wof:name":"Sunburst Information Tech LLC",
    "wof:placetype":"venue"
},
  "geometry": {"coordinates":[-80.610658,28.304107],"type":"Point"}
}