{
  "type": "Feature",
  "properties": {
    "iso:country":"US",
    "sg:address":"236 14th St NE",
    "sg:city":"Naples",
    "sg:classifiers":[
        {
            "category":"Building & Trades",
            "subcategory":"Construction",
            "type":"Services"
        }
    ],
    "sg:phone":"+1 239 455 4670",
    "sg:postcode":"34120",
    "sg:province":"FL",
    "sg:tags":[
        "hanging",
        "contractor"
    ],
    "wof:name":"Franks Painting Inc",
    "wof:placetype":"venue"
},
  "geometry": {"coordinates":[-81.57847,26.243644],"type":"Point"}
}