{
  "type": "Feature",
  "properties": {
    "addr:full":"11570 S Orange Blossom Trl Orlando FL 32837",
    "addr:housenumber":"11570",
    "addr:postcode":"32837",
    "addr:street":"S Orange Blossom Trl",
    "iso:country":"US",
    "sg:address":"11570 S Orange Blossom Trl",
    "sg:city":"Orlando",
    "sg:classifiers":[
        {
            "category":"Restaurant",
            "type":"Food & Drink"
        }
    ],
    "sg:menulink":"http://www.allmenus.com/fl/southwest-orange/36540-delicias-bakery--restaurant/menu/",
    "sg:phone":"+1 407 888 8446",
    "sg:postcode":"32837",
    "sg:province":"FL",
    "sg:tags":[
        "caribbean"
    ],
    "wof:name":"Delicias Bakery & Restaurant",
    "wof:placetype":"venue"
},
  "geometry": {"coordinates":[-81.40460400000001,28.398406],"type":"Point"}
}