{
  "type": "Feature",
  "properties": {
    "addr:full":"6300 Clark St Hudson FL 34667",
    "addr:housenumber":"6300",
    "addr:postcode":"34667",
    "addr:street":"Clark St",
    "iso:country":"US",
    "sg:address":"6300 Clark St",
    "sg:city":"Hudson",
    "sg:classifiers":[
        {
            "category":"Recreation",
            "type":"Entertainment"
        }
    ],
    "sg:phone":"+1 727 534 7245",
    "sg:postcode":"34667",
    "sg:province":"FL",
    "sg:tags":[
        "instruction",
        "sailing"
    ],
    "wof:name":"Adventures In Sailing Inc",
    "wof:placetype":"venue"
},
  "geometry": {"coordinates":[-82.710652,28.361155],"type":"Point"}
}