{
  "type": "Feature",
  "properties": {
    "addr:full":"5950 SE Taylor Dr Stuart FL 34997",
    "addr:housenumber":"5950",
    "addr:postcode":"34997",
    "addr:street":"Se Taylor Dr",
    "iso:country":"US",
    "sg:address":"5950 SE Taylor Dr",
    "sg:city":"Stuart",
    "sg:classifiers":[
        {
            "category":"Building & Trades",
            "subcategory":"Electrical",
            "type":"Services"
        }
    ],
    "sg:phone":"+1 772 283 3369",
    "sg:postcode":"34997",
    "sg:province":"FL",
    "sg:tags":[
        "electrical",
        "contractor"
    ],
    "wof:name":"Ron Taylor Electric",
    "wof:placetype":"venue"
},
  "geometry": {"coordinates":[-80.23841899999999,27.132383],"type":"Point"}
}