{
  "type": "Feature",
  "properties": {
    "addr:full":"215 N Eola Dr Orlando FL 32801",
    "addr:housenumber":"215",
    "addr:postcode":"32801",
    "addr:street":"N Eola Dr",
    "iso:country":"US",
    "sg:address":"215 N Eola Dr",
    "sg:city":"Orlando",
    "sg:classifiers":[
        {
            "category":"Professional",
            "type":"Services"
        }
    ],
    "sg:phone":"+1 407 418 6463",
    "sg:postcode":"32801",
    "sg:province":"FL",
    "wof:name":"R Lddk",
    "wof:placetype":"venue"
},
  "geometry": {"coordinates":[-81.369874,28.544522],"type":"Point"}
}