{
  "type": "Feature",
  "properties": {
    "addr:full":"869 S.W. 107th Ave Miami FL 33174",
    "addr:housenumber":"869",
    "addr:postcode":"33174",
    "addr:street":"S.W. 107Th Ave",
    "iso:country":"US",
    "sg:address":"869 S.W. 107th Ave",
    "sg:city":"Miami",
    "sg:classifiers":[
        {
            "category":"Banks & Credit Unions",
            "subcategory":"Bank",
            "type":"Services"
        }
    ],
    "sg:phone":"+1 305 552 5303",
    "sg:postcode":"33174",
    "sg:province":"FL",
    "sg:tags":[
        "commercial",
        "saving"
    ],
    "sg:website":"www.bankatlantic.com/default.htm...",
    "wof:name":"Bank Atlantic",
    "wof:placetype":"venue"
},
  "geometry": {"coordinates":[-80.367745,25.760449],"type":"Point"}
}