{
  "type": "Feature",
  "properties": {
    "addr:full":"1021 N Wymore Rd Winter Park FL 32789",
    "addr:housenumber":"1021",
    "addr:postcode":"32789",
    "addr:street":"N Wymore Rd",
    "iso:country":"US",
    "sg:address":"1021 N Wymore Rd",
    "sg:city":"Winter Park",
    "sg:classifiers":[
        {
            "category":"Communications",
            "subcategory":"Television Station",
            "type":"Services"
        }
    ],
    "sg:phone":"+1 407 645 2222",
    "sg:postcode":"32789",
    "sg:province":"FL",
    "wof:name":"Chanel 2 Production Services",
    "wof:placetype":"venue"
},
  "geometry": {"coordinates":[-81.384804,28.611],"type":"Point"}
}