{
  "type": "Feature",
  "properties": {
    "iso:country":"US",
    "sg:address":"131 Harrison St",
    "sg:city":"Titusville",
    "sg:classifiers":[
        {
            "category":"Travel",
            "subcategory":"Travel Agent",
            "type":"Entertainment"
        }
    ],
    "sg:phone":"+1 321 267 7600",
    "sg:postcode":"32780",
    "sg:province":"FL",
    "sg:tags":[
        "agency"
    ],
    "wof:name":"Titusville Travel",
    "wof:placetype":"venue"
},
  "geometry": {"coordinates":[-80.801473,28.584237],"type":"Point"}
}