{
  "type": "Feature",
  "properties": {
    "iso:country":"US",
    "sg:address":"249 E Stuart Ave",
    "sg:city":"Lake Wales",
    "sg:classifiers":[
        {
            "category":"Manufacturing",
            "subcategory":"Retail Goods",
            "type":"Manufacturing & Wholesale Goods"
        }
    ],
    "sg:phone":"+1 863 676 2821",
    "sg:postcode":"33853",
    "sg:province":"FL",
    "sg:tags":[
        "picture",
        "frame"
    ],
    "wof:name":"Gallery & Frame Shop",
    "wof:placetype":"venue"
},
  "geometry": {"coordinates":[-81.587487,27.902042],"type":"Point"}
}