{
  "type": "Feature",
  "properties": {
    "addr:full":"8257 Gulf Blvd Gulf Breeze FL 32566",
    "addr:housenumber":"8257",
    "addr:postcode":"32566",
    "addr:street":"Gulf Blvd",
    "iso:country":"US",
    "sg:address":"8257 Gulf Blvd",
    "sg:city":"Gulf Breeze",
    "sg:classifiers":[
        {
            "category":"Organizations",
            "subcategory":"Community Association",
            "type":"Services"
        }
    ],
    "sg:phone":"+1 850 939 9378",
    "sg:postcode":"32566",
    "sg:province":"FL",
    "wof:name":"Owners Assoc of Summer Place",
    "wof:placetype":"venue"
},
  "geometry": {"coordinates":[-86.880425,30.37773],"type":"Point"}
}