{
  "type": "Feature",
  "properties": {
    "iso:country":"US",
    "sg:address":"1786 Columbia St",
    "sg:city":"Orlando",
    "sg:classifiers":[
        {
            "category":"Real Estate",
            "subcategory":"Real Estate Operator",
            "type":"Services"
        }
    ],
    "sg:phone":"+1 407 425 5967",
    "sg:postcode":"32805",
    "sg:province":"FL",
    "sg:tags":[
        "apartment"
    ],
    "wof:name":"Clear Lake Apartments",
    "wof:placetype":"venue"
},
  "geometry": {"coordinates":[-81.401447,28.527255],"type":"Point"}
}