{
  "type": "Feature",
  "properties": {
    "iso:country":"US",
    "sg:address":"2600 S Elm Ave",
    "sg:city":"Sanford",
    "sg:classifiers":[
        {
            "category":"Building & Trades",
            "subcategory":"Construction",
            "type":"Services"
        }
    ],
    "sg:phone":"+1 407 328 5063",
    "sg:postcode":"32773",
    "sg:province":"FL",
    "sg:tags":[
        "roofing",
        "industrial",
        "contractors-commercial",
        "contractor"
    ],
    "wof:name":"Reeds Roofing Contactor & Repair",
    "wof:placetype":"venue"
},
  "geometry": {"coordinates":[-81.270927,28.78208],"type":"Point"}
}