{
  "type": "Feature",
  "properties": {
    "addr:full":"8302 NW 56th St Miami FL 33166",
    "addr:housenumber":"8302",
    "addr:postcode":"33166",
    "addr:street":"Nw 56Th St",
    "iso:country":"US",
    "sg:address":"8302 NW 56th St",
    "sg:city":"Miami",
    "sg:classifiers":[
        {
            "category":"Shopping",
            "subcategory":"Beauty & Cosmetics",
            "type":"Retail Goods"
        }
    ],
    "sg:phone":"+1 305 436 7275",
    "sg:postcode":"33166",
    "sg:province":"FL",
    "sg:tags":[
        "merchandise"
    ],
    "wof:name":"Bm Fragrances Inc",
    "wof:placetype":"venue"
},
  "geometry": {"coordinates":[-80.331891,25.824315],"type":"Point"}
}