{
  "type": "Feature",
  "properties": {
    "addr:full":"2725 Park Dr Clearwater FL 33763",
    "addr:housenumber":"2725",
    "addr:postcode":"33763",
    "addr:street":"Park Dr",
    "iso:country":"US",
    "sg:address":"2725 Park Dr",
    "sg:city":"Clearwater",
    "sg:classifiers":[
        {
            "category":"Health Services",
            "subcategory":"Doctor",
            "type":"Services"
        }
    ],
    "sg:phone":"+1 727 799 4897",
    "sg:postcode":"33763",
    "sg:province":"FL",
    "sg:tags":[
        "dentist"
    ],
    "wof:name":"Ralph Kimbrough DDS",
    "wof:placetype":"venue"
},
  "geometry": {"coordinates":[-82.74360900000001,28.023103],"type":"Point"}
}