{
  "type": "Feature",
  "properties": {
    "addr:full":"2050 NW 27th St Fort Lauderdale FL 33311",
    "addr:housenumber":"2050",
    "addr:postcode":"33311",
    "addr:street":"Nw 27Th St",
    "iso:country":"US",
    "sg:address":"2050 NW 27th St",
    "sg:city":"Fort Lauderdale",
    "sg:classifiers":[
        {
            "category":"Organizations",
            "subcategory":"Religious Organization",
            "type":"Services"
        }
    ],
    "sg:phone":"+1 954 733 0727",
    "sg:postcode":"33311",
    "sg:province":"FL",
    "wof:name":"Pentecostal Temple Revival Ctr",
    "wof:placetype":"venue"
},
  "geometry": {"coordinates":[-80.170281,26.160113],"type":"Point"}
}