{
  "type": "Feature",
  "properties": {
    "iso:country":"US",
    "sg:address":"3488 E Lake Rd S",
    "sg:city":"Palm Harbor",
    "sg:classifiers":[
        {
            "category":"Health Services",
            "subcategory":"Clinic",
            "type":"Services"
        }
    ],
    "sg:phone":"+1 727 771 8306",
    "sg:postcode":"34685",
    "sg:province":"FL",
    "sg:tags":[
        "specialty",
        "outpatient"
    ],
    "wof:name":"Sports Orthpd Rhblitation Svcs",
    "wof:placetype":"venue"
},
  "geometry": {"coordinates":[-82.694142,28.098909],"type":"Point"}
}