{
  "type": "Feature",
  "properties": {
    "addr:full":"3326 Lake Shore Blvd Jacksonville FL 32210",
    "addr:housenumber":"3326",
    "addr:postcode":"32210",
    "addr:street":"Lake Shore Blvd",
    "iso:country":"US",
    "sg:address":"3326 Lake Shore Blvd",
    "sg:city":"Jacksonville",
    "sg:classifiers":[
        {
            "category":"Autos & Motor Vehicles",
            "subcategory":"Boat Sales",
            "type":"Retail Goods"
        }
    ],
    "sg:phone":"+1 904 388 2033",
    "sg:postcode":"32210",
    "sg:province":"FL",
    "sg:tags":[
        "top",
        "upholstery",
        "cover"
    ],
    "wof:name":"Calipso",
    "wof:placetype":"venue"
},
  "geometry": {"coordinates":[-81.721481,30.273156],"type":"Point"}
}