{
  "type": "Feature",
  "properties": {
    "addr:full":"4575 Skates Cir Fort Myers FL 33905",
    "addr:housenumber":"4575",
    "addr:postcode":"33905",
    "addr:street":"Skates Cir",
    "iso:country":"US",
    "sg:address":"4575 Skates Cir",
    "sg:city":"Fort Myers",
    "sg:classifiers":[
        {
            "category":"Manufacturing",
            "subcategory":"Tools & Machinery",
            "type":"Manufacturing & Wholesale Goods"
        }
    ],
    "sg:phone":"+1 239 693 8202",
    "sg:postcode":"33905",
    "sg:province":"FL",
    "sg:tags":[
        "equipment",
        "peripheral",
        "computer",
        "mfg"
    ],
    "wof:name":"Demers Graphics Marie Prod",
    "wof:placetype":"venue"
},
  "geometry": {"coordinates":[-81.71386800000001,26.679296],"type":"Point"}
}