{
  "type": "Feature",
  "properties": {
    "addr:full":"10950 Pembroke Rd Hollywood FL 33025",
    "addr:housenumber":"10950",
    "addr:postcode":"33025",
    "addr:street":"Pembroke Rd",
    "iso:country":"US",
    "sg:address":"10950 Pembroke Rd",
    "sg:city":"Hollywood",
    "sg:classifiers":[
        {
            "category":"Social Services",
            "subcategory":"Child Care",
            "type":"Services"
        }
    ],
    "sg:phone":"+1 954 441 4488",
    "sg:postcode":"33025",
    "sg:province":"FL",
    "sg:tags":[
        "day"
    ],
    "wof:name":"Adventure Bay Early Lrng Ctr",
    "wof:placetype":"venue"
},
  "geometry": {"coordinates":[-80.291354,25.993327],"type":"Point"}
}