{
  "type": "Feature",
  "properties": {
    "addr:full":"921 Ferndell Rd Orlando FL 32808",
    "addr:housenumber":"921",
    "addr:postcode":"32808",
    "addr:street":"Ferndell Rd",
    "iso:country":"US",
    "sg:address":"921 Ferndell Rd",
    "sg:city":"Orlando",
    "sg:classifiers":[
        {
            "category":"Building & Trades",
            "subcategory":"Landscaping Services",
            "type":"Services"
        }
    ],
    "sg:phone":"+1 407 351 9972",
    "sg:postcode":"32808",
    "sg:province":"FL",
    "wof:name":"James Campbell Lawn Maint",
    "wof:placetype":"venue"
},
  "geometry": {"coordinates":[-81.45563300000001,28.557189],"type":"Point"}
}