{
  "type": "Feature",
  "properties": {
    "iso:country":"US",
    "sg:address":"9714 N Nebraska Ave",
    "sg:city":"Tampa",
    "sg:classifiers":[
        {
            "category":"Home & Garden",
            "subcategory":"Building Materials",
            "type":"Retail Goods"
        }
    ],
    "sg:phone":"+1 813 935 6151",
    "sg:postcode":"33612",
    "sg:province":"FL",
    "sg:tags":[
        "glass",
        "window",
        "plate"
    ],
    "wof:name":"Columbia Auto Glass Corp",
    "wof:placetype":"venue"
},
  "geometry": {"coordinates":[-82.45123100000001,28.038511],"type":"Point"}
}