{
  "type": "Feature",
  "properties": {
    "addr:full":"2591 N Forsyth Rd Orlando FL 32807",
    "addr:housenumber":"2591",
    "addr:postcode":"32807",
    "addr:street":"N Forsyth Rd",
    "iso:country":"US",
    "sg:address":"2591 N Forsyth Rd",
    "sg:city":"Orlando",
    "sg:classifiers":[
        {
            "category":"Restaurant",
            "type":"Food & Drink"
        }
    ],
    "sg:phone":"+1 407 788 6203",
    "sg:postcode":"32807",
    "sg:province":"FL",
    "sg:tags":[
        "eating"
    ],
    "wof:name":"Gourmet To Go Party Planners",
    "wof:placetype":"venue"
},
  "geometry": {"coordinates":[-81.29455900000001,28.581571],"type":"Point"}
}