{
  "type": "Feature",
  "properties": {
    "iso:country":"US",
    "sg:address":"909 NW 45th St",
    "sg:city":"Pompano Beach",
    "sg:classifiers":[
        {
            "category":"Building & Trades",
            "subcategory":"Construction",
            "type":"Services"
        }
    ],
    "sg:phone":"+1 954 941 9558",
    "sg:postcode":"33064",
    "sg:province":"FL",
    "sg:tags":[
        "carpentry",
        "contractor"
    ],
    "wof:name":"ADT Cabinet Works Inc",
    "wof:placetype":"venue"
},
  "geometry": {"coordinates":[-80.13936,26.285315],"type":"Point"}
}