{
  "type": "Feature",
  "properties": {
    "iso:country":"US",
    "sg:address":"3600 Westview Dr",
    "sg:city":"Naples",
    "sg:classifiers":[
        {
            "category":"Manufacturing",
            "subcategory":"Metals",
            "type":"Manufacturing & Wholesale Goods"
        }
    ],
    "sg:phone":"+1 239 417 5368",
    "sg:postcode":"34104",
    "sg:province":"FL",
    "sg:tags":[
        "plumbing",
        "fixture",
        "supply"
    ],
    "sg:website":"www.herbeau.com",
    "wof:name":"Herbeau Creations Of America",
    "wof:placetype":"venue"
},
  "geometry": {"coordinates":[-81.761534,26.150464],"type":"Point"}
}