{
  "type": "Feature",
  "properties": {
    "iso:country":"US",
    "sg:address":"2608 Country Club Blvd",
    "sg:city":"Cape Coral",
    "sg:classifiers":[
        {
            "category":"Organizations",
            "subcategory":"Religious Organization",
            "type":"Services"
        }
    ],
    "sg:phone":"+1 239 574 2111",
    "sg:postcode":"33904",
    "sg:province":"FL",
    "sg:tags":[
        "church"
    ],
    "wof:name":"First Church-Christ Scientist",
    "wof:placetype":"venue"
},
  "geometry": {"coordinates":[-81.956412,26.603087],"type":"Point"}
}