{
  "type": "Feature",
  "properties": {
    "iso:country":"US",
    "sg:address":"7262 Old River Rd",
    "sg:city":"Baker",
    "sg:classifiers":[
        {
            "category":"Building & Trades",
            "subcategory":"Construction",
            "type":"Services"
        }
    ],
    "sg:phone":"+1 850 537 8279",
    "sg:postcode":"32531",
    "sg:province":"FL",
    "sg:tags":[
        "house"
    ],
    "wof:name":"Lyons Construction",
    "wof:placetype":"venue"
},
  "geometry": {"coordinates":[-86.59716299999999,30.889832],"type":"Point"}
}