{
  "type": "Feature",
  "properties": {
    "iso:country":"US",
    "sg:address":"1060 Greenwood Blvd",
    "sg:city":"Lake Mary",
    "sg:classifiers":[
        {
            "category":"Travel",
            "subcategory":"Hotels & Motels",
            "type":"Entertainment"
        }
    ],
    "sg:phone":"+1 407 805 9901",
    "sg:postcode":"32746",
    "sg:province":"FL",
    "wof:name":"La Quinta",
    "wof:placetype":"venue"
},
  "geometry": {"coordinates":[-81.363899,28.747499],"type":"Point"}
}