{
  "type": "Feature",
  "properties": {
    "addr:full":"8507 State Rd 54 New Port Richey FL 34655",
    "addr:housenumber":"8507;54",
    "addr:postcode":"34655",
    "addr:street":"State Rd",
    "iso:country":"US",
    "sg:address":"8507 State Rd 54",
    "sg:city":"New Port Richey",
    "sg:classifiers":[
        {
            "category":"Food & Beverages",
            "subcategory":"Liquor & Beverages",
            "type":"Retail Goods"
        }
    ],
    "sg:phone":"+1 727 376 0626",
    "sg:postcode":"34655",
    "sg:province":"FL",
    "sg:tags":[
        "beer",
        "ale"
    ],
    "wof:name":"True Price Discount Beverage",
    "wof:placetype":"venue"
},
  "geometry": {"coordinates":[-82.672989,28.206409],"type":"Point"}
}