{
  "type": "Feature",
  "properties": {
    "addr:full":"2713 Country Club Rd Sanford FL 32771",
    "addr:housenumber":"2713",
    "addr:postcode":"32771",
    "addr:street":"Country Club Rd",
    "iso:country":"US",
    "sg:address":"2713 Country Club Rd",
    "sg:city":"Sanford",
    "sg:classifiers":[
        {
            "category":"Shopping",
            "type":"Retail Goods"
        }
    ],
    "sg:phone":"+1 407 518 1245",
    "sg:postcode":"32771",
    "sg:province":"FL",
    "sg:tags":[
        "merchandise"
    ],
    "wof:name":"Sierra Audio Visual",
    "wof:placetype":"venue"
},
  "geometry": {"coordinates":[-81.30137000000001,28.788717],"type":"Point"}
}