{
  "type": "Feature",
  "properties": {
    "iso:country":"US",
    "sg:address":"1016 SW 4th Ave",
    "sg:city":"Chiefland",
    "sg:classifiers":[
        {
            "category":"Building & Trades",
            "subcategory":"Landscaping Services",
            "type":"Services"
        }
    ],
    "sg:phone":"+1 352 493 9201",
    "sg:postcode":"32644",
    "sg:province":"FL",
    "sg:tags":[
        "lawn",
        "landscape",
        "maintenance",
        "grounds"
    ],
    "wof:name":"Red Barron Landscape & Maint",
    "wof:placetype":"venue"
},
  "geometry": {"coordinates":[-82.86842900000001,29.47475],"type":"Point"}
}