{
  "type": "Feature",
  "properties": {
    "addr:full":"5104 Glover Ln Baker FL 32570",
    "addr:housenumber":"5104",
    "addr:postcode":"32570",
    "addr:street":"Glover Ln",
    "iso:country":"US",
    "sg:address":"5104 Glover Ln",
    "sg:city":"Baker",
    "sg:classifiers":[
        {
            "category":"Recreation",
            "type":"Entertainment"
        }
    ],
    "sg:phone":"+1 850 537 9984",
    "sg:postcode":"32570",
    "sg:province":"FL",
    "sg:tags":[
        "stable"
    ],
    "wof:name":"Second Change Ranch",
    "wof:placetype":"venue"
},
  "geometry": {"coordinates":[-87.064359,30.6246],"type":"Point"}
}