{
  "type": "Feature",
  "properties": {
    "iso:country":"US",
    "sg:address":"700 S Babcock St",
    "sg:city":"Melbourne",
    "sg:classifiers":[
        {
            "category":"Banks & Credit Unions",
            "subcategory":"Investment Brokerage",
            "type":"Services"
        }
    ],
    "sg:phone":"+1 321 728 7103",
    "sg:postcode":"32901",
    "sg:province":"FL",
    "sg:tags":[
        "security"
    ],
    "wof:name":"Raymond James & Assoc Inc",
    "wof:placetype":"venue"
},
  "geometry": {"coordinates":[-80.621872,28.097775],"type":"Point"}
}