{
  "type": "Feature",
  "properties": {
    "iso:country":"US",
    "sg:address":"3517 Kilgallen Ct",
    "sg:city":"Ormond Beach",
    "sg:classifiers":[
        {
            "category":"Professional",
            "subcategory":"Management & Consulting",
            "type":"Services"
        }
    ],
    "sg:phone":"+1 386 671 1014",
    "sg:postcode":"32174",
    "sg:province":"FL",
    "wof:name":"Jack Schmidt & Associates",
    "wof:placetype":"venue"
},
  "geometry": {"coordinates":[-81.136374,29.39357],"type":"Point"}
}