{
  "type": "Feature",
  "properties": {
    "iso:country":"US",
    "sg:address":"1120 N Stone St",
    "sg:city":"Deland",
    "sg:classifiers":[
        {
            "category":"Professional",
            "subcategory":"Lawyer & Legal Services",
            "type":"Services"
        }
    ],
    "sg:phone":"+1 386 734 1106",
    "sg:postcode":"32720",
    "sg:province":"FL",
    "wof:name":"Scarlett Joseph Alexander III Atty",
    "wof:placetype":"venue"
},
  "geometry": {"coordinates":[-81.316399,29.049801],"type":"Point"}
}