{
  "type": "Feature",
  "properties": {
    "addr:full":"3990 W Lake Mary Blvd Lake Mary FL 32746",
    "addr:housenumber":"3990",
    "addr:postcode":"32746",
    "addr:street":"W Lake Mary Blvd",
    "iso:country":"US",
    "sg:address":"3990 W Lake Mary Blvd",
    "sg:city":"Lake Mary",
    "sg:classifiers":[
        {
            "category":"Ice Cream",
            "type":"Food & Drink"
        },
        {
            "category":"Food & Beverages",
            "subcategory":"Meat & Fish",
            "type":"Retail Goods"
        }
    ],
    "sg:phone":"+1 407 322 4558",
    "sg:postcode":"32746",
    "sg:province":"FL",
    "sg:tags":[
        "frozen",
        "yogurt",
        "hot",
        "dog"
    ],
    "sg:website":"smittyslakemary.com/",
    "wof:name":"Smitty's Ice Cream",
    "wof:placetype":"venue"
},
  "geometry": {"coordinates":[-81.34662400000001,28.756607],"type":"Point"}
}