{
  "type": "Feature",
  "properties": {
    "iso:country":"US",
    "sg:address":"406 Cristobal St",
    "sg:city":"Naples",
    "sg:classifiers":[
        {
            "category":"Marine",
            "type":"Transportation"
        }
    ],
    "sg:phone":"+1 239 389 1177",
    "sg:postcode":"34113",
    "sg:province":"FL",
    "sg:tags":[
        "towing"
    ],
    "wof:name":"Southern Marine Towing",
    "wof:placetype":"venue"
},
  "geometry": {"coordinates":[-81.72527100000001,25.986521],"type":"Point"}
}