{
  "type": "Feature",
  "properties": {
    "iso:country":"US",
    "sg:address":"11010 Oleander Dr.",
    "sg:city":"Clermont",
    "sg:classifiers":[
        {
            "category":"Manufacturing",
            "subcategory":"Buildings",
            "type":"Manufacturing & Wholesale Goods"
        },
        {
            "category":"Professional",
            "subcategory":"Business Services",
            "type":"Services"
        },
        {
            "category":"Building & Trades",
            "subcategory":"Construction",
            "type":"Services"
        }
    ],
    "sg:phone":"+1 352 267 9571",
    "sg:postcode":"34711",
    "sg:province":"FL",
    "sg:tags":[
        "builder",
        "handyman",
        "carpenter",
        "contractor",
        "home",
        "referral"
    ],
    "sg:website":"http://www.PinnacleDreamHomes.com",
    "wof:name":"Pinnacle Construction and Design",
    "wof:placetype":"venue"
},
  "geometry": {"coordinates":[-81.771445,28.499153],"type":"Point"}
}