{
  "type": "Feature",
  "properties": {
    "addr:full":"2000 NW 7th Ave Miami FL 33127",
    "addr:housenumber":"2000",
    "addr:postcode":"33127",
    "addr:street":"Nw 7Th Ave",
    "iso:country":"US",
    "sg:address":"2000 NW 7th Ave",
    "sg:city":"Miami",
    "sg:classifiers":[
        {
            "category":"Retail",
            "subcategory":"Auto Repair",
            "type":"Services"
        }
    ],
    "sg:phone":"+1 305 324 1682",
    "sg:postcode":"33127",
    "sg:province":"FL",
    "wof:name":"Pinguinos Auto Care Inc",
    "wof:placetype":"venue"
},
  "geometry": {"coordinates":[-80.207162,25.795236],"type":"Point"}
}