{
  "type": "Feature",
  "properties": {
    "addr:full":"2845 Aventura Blvd Miami FL 33180",
    "addr:housenumber":"2845",
    "addr:postcode":"33180",
    "addr:street":"Aventura Blvd",
    "iso:country":"US",
    "sg:address":"2845 Aventura Blvd",
    "sg:city":"Miami",
    "sg:classifiers":[
        {
            "category":"Health Services",
            "subcategory":"Doctor",
            "type":"Services"
        }
    ],
    "sg:phone":"+1 305 692 2222",
    "sg:postcode":"33180",
    "sg:province":"FL",
    "sg:tags":[
        "medical"
    ],
    "wof:name":"Elite Imaging LLC Aventura",
    "wof:placetype":"venue"
},
  "geometry": {"coordinates":[-80.143171,25.961043],"type":"Point"}
}