{
  "type": "Feature",
  "properties": {
    "iso:country":"US",
    "sg:address":"621 Greenbriar Dr",
    "sg:city":"West Palm Beach",
    "sg:classifiers":[
        {
            "category":"Professional",
            "subcategory":"Business Services",
            "type":"Services"
        }
    ],
    "sg:phone":"+1 561 848 8466",
    "sg:postcode":"33403",
    "sg:province":"FL",
    "sg:tags":[
        "appraiser"
    ],
    "wof:name":"Antiques Appraiser",
    "wof:placetype":"venue"
},
  "geometry": {"coordinates":[-80.066151,26.799639],"type":"Point"}
}