{
  "type": "Feature",
  "properties": {
    "iso:country":"US",
    "sg:address":"6823 14th St W",
    "sg:city":"Bradenton",
    "sg:classifiers":[
        {
            "category":"Building & Trades",
            "subcategory":"Construction",
            "type":"Services"
        },
        {
            "category":"Home & Garden",
            "subcategory":"Carpets & Floor Coverings",
            "type":"Retail Goods"
        }
    ],
    "sg:phone":"+1 941 753 5200",
    "sg:postcode":"34207",
    "sg:province":"FL",
    "sg:tags":[
        "material",
        "installation",
        "rug",
        "tile-contractors"
    ],
    "sg:website":"http://www.bestvaluecarpet.com",
    "wof:name":"Carpet Depot",
    "wof:placetype":"venue"
},
  "geometry": {"coordinates":[-82.57553799999999,27.419625],"type":"Point"}
}