{
  "type": "Feature",
  "properties": {
    "iso:country":"US",
    "sg:address":"3490 64th St N",
    "sg:city":"St Petersburg",
    "sg:classifiers":[
        {
            "category":"Freight",
            "type":"Transportation"
        }
    ],
    "sg:phone":"+1 727 527 0171",
    "sg:postcode":"33710",
    "sg:province":"FL",
    "sg:tags":[
        "commercial",
        "storage"
    ],
    "wof:name":"Ralph's Storage",
    "wof:placetype":"venue"
},
  "geometry": {"coordinates":[-82.72409,27.804164],"type":"Point"}
}