{
  "type": "Feature",
  "properties": {
    "iso:country":"US",
    "sg:address":"7700 NW 81st Pl Ste 3",
    "sg:city":"Miami",
    "sg:classifiers":[
        {
            "category":"Transit Center",
            "subcategory":"Freight",
            "type":"Transportation"
        }
    ],
    "sg:phone":"+1 305 594 3445",
    "sg:postcode":"33166",
    "sg:province":"FL",
    "sg:tags":[
        "broker"
    ],
    "sg:website":"http://www.nacalogistics.com",
    "wof:name":"Brennan International",
    "wof:placetype":"venue"
},
  "geometry": {"coordinates":[-80.32975,25.843769],"type":"Point"}
}