{
  "type": "Feature",
  "properties": {
    "iso:country":"US",
    "sg:address":"285 8th St S",
    "sg:city":"Naples",
    "sg:classifiers":[
        {
            "category":"Health Services",
            "subcategory":"Health Practitioner",
            "type":"Services"
        }
    ],
    "sg:phone":"+1 239 649 4480",
    "sg:postcode":"34102",
    "sg:province":"FL",
    "wof:name":"Gene K Morgan Msw",
    "wof:placetype":"venue"
},
  "geometry": {"coordinates":[-81.796666,26.145948],"type":"Point"}
}