{
  "type": "Feature",
  "properties": {
    "iso:country":"US",
    "sg:address":"547 E New York Ave",
    "sg:city":"De Land",
    "sg:classifiers":[
        {
            "category":"Manufacturing",
            "subcategory":"Toys & Sporting Goods",
            "type":"Manufacturing & Wholesale Goods"
        }
    ],
    "sg:phone":"+1 386 785 0800",
    "sg:postcode":"32724",
    "sg:province":"FL",
    "sg:tags":[
        "athletic"
    ],
    "wof:name":"Birdman Inc",
    "wof:placetype":"venue"
},
  "geometry": {"coordinates":[-81.294166,29.0282],"type":"Point"}
}