{
  "type": "Feature",
  "properties": {
    "addr:full":"2250 SW 3rd Ave Ste 201 Miami FL 33129",
    "addr:housenumber":"2250",
    "addr:postcode":"33129",
    "addr:street":"Sw 3Rd Ave Ste 201",
    "iso:country":"US",
    "sg:address":"2250 SW 3rd Ave Ste 201",
    "sg:city":"Miami",
    "sg:classifiers":[
        {
            "category":"Professional",
            "subcategory":"Lawyer & Legal Services",
            "type":"Services"
        }
    ],
    "sg:phone":"+1 305 858 0888",
    "sg:postcode":"33129",
    "sg:province":"FL",
    "wof:name":"Law Offices of Troy D Ferguson",
    "wof:placetype":"venue"
},
  "geometry": {"coordinates":[-80.205322,25.757649],"type":"Point"}
}