{
  "type": "Feature",
  "properties": {
    "iso:country":"US",
    "sg:address":"4100 N 42nd Ave",
    "sg:city":"Hollywood",
    "sg:classifiers":[
        {
            "category":"Restaurant",
            "type":"Food & Drink"
        }
    ],
    "sg:phone":"+1 954 987 5078",
    "sg:postcode":"33021",
    "sg:province":"FL",
    "wof:name":"Cafe Report Inc",
    "wof:placetype":"venue"
},
  "geometry": {"coordinates":[-80.185931,26.046712],"type":"Point"}
}