{
  "type": "Feature",
  "properties": {
    "addr:full":"3812 Gunn Hwy Tampa FL 33618",
    "addr:housenumber":"3812",
    "addr:postcode":"33618",
    "addr:street":"Gunn Hwy",
    "iso:country":"US",
    "sg:address":"3812 Gunn Hwy",
    "sg:city":"Tampa",
    "sg:classifiers":[
        {
            "category":"Professional",
            "subcategory":"Lawyer & Legal Services",
            "type":"Services"
        }
    ],
    "sg:phone":"+1 813 963 7737",
    "sg:postcode":"33618",
    "sg:province":"FL",
    "sg:tags":[
        "plan"
    ],
    "wof:name":"Baker Enterprises",
    "wof:placetype":"venue"
},
  "geometry": {"coordinates":[-82.507794,28.037746],"type":"Point"}
}