{
  "type": "Feature",
  "properties": {
    "iso:country":"US",
    "sg:address":"124 NW 15th St",
    "sg:city":"Pompano Beach",
    "sg:classifiers":[
        {
            "category":"Building & Trades",
            "subcategory":"Construction",
            "type":"Services"
        }
    ],
    "sg:phone":"+1 954 943 7693",
    "sg:postcode":"33060",
    "sg:province":"FL",
    "sg:tags":[
        "concrete",
        "contractor"
    ],
    "wof:name":"Moreland Concrete Inc",
    "wof:placetype":"venue"
},
  "geometry": {"coordinates":[-80.123344,26.245939],"type":"Point"}
}