{
  "type": "Feature",
  "properties": {
    "iso:country":"US",
    "sg:address":"2615 Hollingsworth Hill Ave",
    "sg:city":"Lakeland",
    "sg:classifiers":[
        {
            "category":"Social Services",
            "type":"Services"
        }
    ],
    "sg:phone":"+1 863 682 6691",
    "sg:postcode":"33803",
    "sg:province":"FL",
    "sg:tags":[
        "senior",
        "citizen"
    ],
    "wof:name":"Caregivers For Seniors",
    "wof:placetype":"venue"
},
  "geometry": {"coordinates":[-81.941956,28.018052],"type":"Point"}
}