{
  "type": "Feature",
  "properties": {
    "addr:full":"2321 E 4th Ave Tampa FL 33605",
    "addr:housenumber":"2321",
    "addr:postcode":"33605",
    "addr:street":"E 4Th Ave",
    "iso:country":"US",
    "sg:address":"2321 E 4th Ave",
    "sg:city":"Tampa",
    "sg:classifiers":[
        {
            "category":"Building & Trades",
            "subcategory":"Plumbing",
            "type":"Services"
        }
    ],
    "sg:phone":"+1 813 241 4100",
    "sg:postcode":"33605",
    "sg:province":"FL",
    "sg:tags":[
        "plumbing",
        "contractor"
    ],
    "wof:name":"Atlantis Plumbing",
    "wof:placetype":"venue"
},
  "geometry": {"coordinates":[-82.432502,27.958009],"type":"Point"}
}