{
  "type": "Feature",
  "properties": {
    "addr:full":"107 Truman St Fort Walton Bch FL 32547",
    "addr:housenumber":"107",
    "addr:postcode":"32547",
    "addr:street":"Truman St",
    "iso:country":"US",
    "sg:address":"107 Truman St",
    "sg:city":"Fort Walton Bch",
    "sg:classifiers":[
        {
            "category":"Wholesale",
            "subcategory":"Machinery & Supplies",
            "type":"Manufacturing & Wholesale Goods"
        }
    ],
    "sg:phone":"+1 850 863 9400",
    "sg:postcode":"32547",
    "sg:province":"FL",
    "sg:tags":[
        "carpet",
        "cleaning",
        "rug"
    ],
    "wof:name":"Shore-Line Carpet Supplies",
    "wof:placetype":"venue"
},
  "geometry": {"coordinates":[-86.606712,30.446972],"type":"Point"}
}