{
  "type": "Feature",
  "properties": {
    "addr:full":"1304 53rd Ave W Bradenton FL 34207",
    "addr:housenumber":"1304",
    "addr:postcode":"34207",
    "addr:street":"53Rd Ave W",
    "iso:country":"US",
    "sg:address":"1304 53rd Ave W",
    "sg:city":"Bradenton",
    "sg:classifiers":[
        {
            "category":"Autos & Motor Vehicles",
            "subcategory":"Automobile Sales",
            "type":"Retail Goods"
        }
    ],
    "sg:phone":"+1 941 758 8555",
    "sg:postcode":"34207",
    "sg:province":"FL",
    "sg:tags":[
        "car",
        "dealer"
    ],
    "wof:name":"D & D Auto Sales",
    "wof:placetype":"venue"
},
  "geometry": {"coordinates":[-82.574147,27.447666],"type":"Point"}
}