{
  "type": "Feature",
  "properties": {
    "iso:country":"US",
    "sg:address":"2205 Frontera St",
    "sg:city":"Navarre",
    "sg:classifiers":[
        {
            "category":"Wholesale",
            "subcategory":"Machinery & Supplies",
            "type":"Manufacturing & Wholesale Goods"
        }
    ],
    "sg:phone":"+1 850 936 5779",
    "sg:postcode":"32566",
    "sg:province":"FL",
    "wof:name":"Qual Mark Corp",
    "wof:placetype":"venue"
},
  "geometry": {"coordinates":[-86.87121999999999,30.414593],"type":"Point"}
}