{
  "type": "Feature",
  "properties": {
    "iso:country":"US",
    "sg:address":"707 Richard St",
    "sg:city":"Satellite Beach",
    "sg:classifiers":[
        {
            "category":"Building & Trades",
            "subcategory":"Cleaning & Sanitation",
            "type":"Services"
        }
    ],
    "sg:phone":"+1 321 777 5289",
    "sg:postcode":"32937",
    "sg:province":"FL",
    "sg:tags":[
        "maintenance"
    ],
    "wof:name":"White Dove",
    "wof:placetype":"venue"
},
  "geometry": {"coordinates":[-80.59151300000001,28.158229],"type":"Point"}
}