{
  "type": "Feature",
  "properties": {
    "addr:full":"200 NE 26th St Boca Raton FL 33431",
    "addr:housenumber":"200",
    "addr:postcode":"33431",
    "addr:street":"Ne 26Th St",
    "iso:country":"US",
    "sg:address":"200 NE 26th St",
    "sg:city":"Boca Raton",
    "sg:classifiers":[
        {
            "category":"Real Estate",
            "subcategory":"Real Estate Agent",
            "type":"Services"
        }
    ],
    "sg:phone":"+1 561 362 7456",
    "sg:postcode":"33431",
    "sg:province":"FL",
    "sg:tags":[
        "loan",
        "broker"
    ],
    "wof:name":"Multifamily Services Inc",
    "wof:placetype":"venue"
},
  "geometry": {"coordinates":[-80.080872,26.373772],"type":"Point"}
}