{
  "type": "Feature",
  "properties": {
    "iso:country":"US",
    "sg:address":"9429 Discovery Ter # 201",
    "sg:city":"Bradenton",
    "sg:classifiers":[
        {
            "category":"Real Estate",
            "subcategory":"Real Estate Services",
            "type":"Services"
        }
    ],
    "sg:phone":"+1 941 812 1781",
    "sg:postcode":"34212",
    "sg:province":"FL",
    "sg:tags":[
        "management"
    ],
    "wof:name":"David Mcmurray",
    "wof:placetype":"venue"
},
  "geometry": {"coordinates":[-82.44792700000001,27.514074],"type":"Point"}
}