{
  "type": "Feature",
  "properties": {
    "iso:country":"US",
    "sg:address":"10420 Highland Manor Dr",
    "sg:city":"Tampa",
    "sg:classifiers":[
        {
            "category":"Banks & Credit Unions",
            "subcategory":"Bank",
            "type":"Services"
        }
    ],
    "sg:phone":"+1 813 432 5576",
    "sg:postcode":"33610",
    "sg:province":"FL",
    "sg:tags":[
        "saving",
        "commercial"
    ],
    "sg:website":"http://www.chase.com",
    "wof:name":"Jpmorgan Chase Bank, National Association",
    "wof:placetype":"venue"
},
  "geometry": {"coordinates":[-82.329109,27.984151],"type":"Point"}
}