{
  "type": "Feature",
  "properties": {
    "iso:country":"US",
    "sg:address":"6963 SW 117th Ave",
    "sg:city":"Miami",
    "sg:classifiers":[
        {
            "category":"Health Services",
            "subcategory":"Doctor",
            "type":"Services"
        }
    ],
    "sg:phone":"+1 305 595 3225",
    "sg:postcode":"33183",
    "sg:province":"FL",
    "sg:tags":[
        "physician",
        "pediatrics-emergency",
        "pediatrics",
        "surgeons",
        "medicine",
        "surgeon"
    ],
    "wof:name":"South Florida Pediatric Partners",
    "wof:placetype":"venue"
},
  "geometry": {"coordinates":[-80.382161,25.701391],"type":"Point"}
}