{
  "type": "Feature",
  "properties": {
    "iso:country":"US",
    "sg:address":"3427 Sweetwater Trl",
    "sg:city":"Clearwater",
    "sg:classifiers":[
        {
            "category":"Banks & Credit Unions",
            "subcategory":"Bank",
            "type":"Services"
        }
    ],
    "sg:phone":"+1 727 786 4978",
    "sg:postcode":"33761",
    "sg:province":"FL",
    "sg:tags":[
        "mortgage"
    ],
    "wof:name":"Maria T Aucremann",
    "wof:placetype":"venue"
},
  "geometry": {"coordinates":[-82.730278,28.046175],"type":"Point"}
}