{
  "type": "Feature",
  "properties": {
    "iso:country":"US",
    "sg:address":"2225 SW 131st Ct",
    "sg:city":"Miami",
    "sg:classifiers":[
        {
            "category":"Professional",
            "type":"Services"
        }
    ],
    "sg:phone":"+1 305 593 6319",
    "sg:postcode":"33175",
    "sg:province":"FL",
    "wof:name":"Antonio Antelo W Maria",
    "wof:placetype":"venue"
},
  "geometry": {"coordinates":[-80.408636,25.746683],"type":"Point"}
}