{
  "type": "Feature",
  "properties": {
    "addr:full":"16105 Opal Creek Dr Fort Lauderdale FL 33331",
    "addr:housenumber":"16105",
    "addr:postcode":"33331",
    "addr:street":"Opal Creek Dr",
    "iso:country":"US",
    "sg:address":"16105 Opal Creek Dr",
    "sg:city":"Fort Lauderdale",
    "sg:classifiers":[
        {
            "category":"Wholesale",
            "subcategory":"Machinery & Supplies",
            "type":"Manufacturing & Wholesale Goods"
        }
    ],
    "sg:phone":"+1 954 659 9467",
    "sg:postcode":"33331",
    "sg:province":"FL",
    "sg:tags":[
        "equipment",
        "establishment"
    ],
    "wof:name":"West Coast Enterprise",
    "wof:placetype":"venue"
},
  "geometry": {"coordinates":[-80.363466,26.070264],"type":"Point"}
}