{
  "type": "Feature",
  "properties": {
    "iso:country":"US",
    "sg:address":"1405 21st St",
    "sg:city":"Vero Beach",
    "sg:classifiers":[
        {
            "category":"Professional",
            "subcategory":"Lawyer & Legal Services",
            "type":"Services"
        }
    ],
    "sg:phone":"+1 772 778 9998",
    "sg:postcode":"32960",
    "sg:province":"FL",
    "sg:tags":[
        "attorney"
    ],
    "wof:name":"Dell & Schaefer",
    "wof:placetype":"venue"
},
  "geometry": {"coordinates":[-80.40033699999999,27.639703],"type":"Point"}
}