{
  "type": "Feature",
  "properties": {
    "iso:country":"US",
    "sg:address":"819 W Bloomingdale Ave",
    "sg:city":"Brandon",
    "sg:classifiers":[
        {
            "category":"Restaurant",
            "type":"Food & Drink"
        }
    ],
    "sg:menulink":"http://www.allmenus.com/fl/brandon/237182-hungry-howies-pizza/menu/",
    "sg:phone":"+1 813 684 0988",
    "sg:postcode":"33511",
    "sg:province":"FL",
    "sg:tags":[
        "wrap",
        "american",
        "sandwich",
        "pizza"
    ],
    "wof:name":"Hungry Howie's Pizza",
    "wof:placetype":"venue"
},
  "geometry": {"coordinates":[-82.295041,27.893589],"type":"Point"}
}