{
  "type": "Feature",
  "properties": {
    "addr:full":"523 E 25th St Hialeah FL 33013",
    "addr:housenumber":"523",
    "addr:postcode":"33013",
    "addr:street":"E 25Th St",
    "iso:country":"US",
    "sg:address":"523 E 25th St",
    "sg:city":"Hialeah",
    "sg:classifiers":[
        {
            "category":"Health Services",
            "subcategory":"Doctor",
            "type":"Services"
        }
    ],
    "sg:phone":"+1 305 696 5088",
    "sg:postcode":"33013",
    "sg:province":"FL",
    "wof:name":"Teng Peter MD",
    "wof:placetype":"venue"
},
  "geometry": {"coordinates":[-80.272003,25.8449],"type":"Point"}
}