{
  "type": "Feature",
  "properties": {
    "iso:country":"US",
    "sg:address":"1561 NW 28th St",
    "sg:city":"Miami",
    "sg:classifiers":[
        {
            "category":"Building & Trades",
            "subcategory":"Construction",
            "type":"Services"
        }
    ],
    "sg:phone":"+1 305 634 3970",
    "sg:postcode":"33142",
    "sg:province":"FL",
    "sg:tags":[
        "carpenter"
    ],
    "wof:name":"Amalia Carpentry Corp",
    "wof:placetype":"venue"
},
  "geometry": {"coordinates":[-80.222165,25.802192],"type":"Point"}
}