{
  "type": "Feature",
  "properties": {
    "iso:country":"US",
    "sg:address":"8900 SW 107th Ave",
    "sg:city":"Miami",
    "sg:classifiers":[
        {
            "category":"Banks & Credit Unions",
            "subcategory":"Investment Brokerage",
            "type":"Services"
        }
    ],
    "sg:phone":"+1 305 779 5060",
    "sg:postcode":"33176",
    "sg:province":"FL",
    "sg:tags":[
        "advisory",
        "financial"
    ],
    "wof:name":"Financial Services Group",
    "wof:placetype":"venue"
},
  "geometry": {"coordinates":[-80.366901,25.684433],"type":"Point"}
}