{
  "type": "Feature",
  "properties": {
    "iso:country":"US",
    "sg:address":"7920 NW 50th St",
    "sg:city":"Lauderhill",
    "sg:classifiers":[
        {
            "category":"Building & Trades",
            "subcategory":"Construction",
            "type":"Services"
        }
    ],
    "sg:phone":"+1 954 746 3794",
    "sg:postcode":"33351",
    "sg:province":"FL",
    "sg:tags":[
        "coping",
        "plastering",
        "tiling",
        "pool",
        "swimming"
    ],
    "wof:name":"Sparkling Blue Pools",
    "wof:placetype":"venue"
},
  "geometry": {"coordinates":[-80.256574,26.18716],"type":"Point"}
}