{
  "type": "Feature",
  "properties": {
    "addr:full":"3940 10th Ave N Lake Worth FL 33461",
    "addr:housenumber":"3940",
    "addr:postcode":"33461",
    "addr:street":"10Th Ave N",
    "iso:country":"US",
    "sg:address":"3940 10th Ave N",
    "sg:city":"Lake Worth",
    "sg:classifiers":[
        {
            "category":"Banks & Credit Unions",
            "subcategory":"Bank",
            "type":"Services"
        }
    ],
    "sg:phone":"+1 561 967 5066",
    "sg:postcode":"33461",
    "sg:province":"FL",
    "sg:tags":[
        "loan",
        "real estate"
    ],
    "wof:name":"Access E-Mortgage Inc",
    "wof:placetype":"venue"
},
  "geometry": {"coordinates":[-80.10481299999999,26.629151],"type":"Point"}
}