{
  "type": "Feature",
  "properties": {
    "addr:full":"70 S Charles Richard Beall Blvd Debary FL 32713",
    "addr:housenumber":"70",
    "addr:postcode":"32713",
    "addr:street":"S Charles Richard Beall Blvd",
    "iso:country":"US",
    "sg:address":"70 S Charles Richard Beall Blvd",
    "sg:city":"Debary",
    "sg:classifiers":[
        {
            "category":"Shopping",
            "subcategory":"Florist",
            "type":"Retail Goods"
        }
    ],
    "sg:phone":"+1 386 753 0585",
    "sg:postcode":"32713",
    "sg:province":"FL",
    "wof:name":"There's No Place Like Home Flowers & Gifts",
    "wof:placetype":"venue"
},
  "geometry": {"coordinates":[-81.308187,28.884892],"type":"Point"}
}