{
  "type": "Feature",
  "properties": {
    "addr:full":"12411 N Florida Ave Tampa FL 33612",
    "addr:housenumber":"12411",
    "addr:postcode":"33612",
    "addr:street":"N Florida Ave",
    "iso:country":"US",
    "sg:address":"12411 N Florida Ave",
    "sg:city":"Tampa",
    "sg:classifiers":[
        {
            "category":"Building & Trades",
            "subcategory":"Plumbing",
            "type":"Services"
        }
    ],
    "sg:phone":"+1 813 931 0749",
    "sg:postcode":"33612",
    "sg:province":"FL",
    "sg:tags":[
        "plumbing",
        "contractor"
    ],
    "wof:name":"JJJK Plumbing Systems Inc",
    "wof:placetype":"venue"
},
  "geometry": {"coordinates":[-82.45926900000001,28.061062],"type":"Point"}
}