{
  "type": "Feature",
  "properties": {
    "addr:full":"5573 S Kirkman Rd Orlando FL 32811",
    "addr:housenumber":"5573",
    "addr:postcode":"32811",
    "addr:street":"S Kirkman Rd",
    "iso:country":"US",
    "sg:address":"5573 S Kirkman Rd",
    "sg:city":"Orlando",
    "sg:classifiers":[
        {
            "category":"Restaurant",
            "type":"Food & Drink"
        }
    ],
    "sg:phone":"+1 407 248 0000",
    "sg:postcode":"32811",
    "sg:province":"FL",
    "wof:name":"Orlando Ale House",
    "wof:placetype":"venue"
},
  "geometry": {"coordinates":[-81.458748,28.481672],"type":"Point"}
}