{
  "type": "Feature",
  "properties": {
    "addr:full":"130 S Main St Williston FL 32696",
    "addr:housenumber":"130",
    "addr:postcode":"32696",
    "addr:street":"S Main St",
    "iso:country":"US",
    "sg:address":"130 S Main St",
    "sg:city":"Williston",
    "sg:classifiers":[
        {
            "category":"Government",
            "subcategory":"Police Station",
            "type":"Public Place"
        }
    ],
    "sg:phone":"+1 352 000 1111",
    "sg:postcode":"32696",
    "sg:province":"FL",
    "sg:tags":[
        "department"
    ],
    "wof:name":"Williston Police Dept",
    "wof:placetype":"venue"
},
  "geometry": {"coordinates":[-82.44676699999999,29.385401],"type":"Point"}
}