{
  "type": "Feature",
  "properties": {
    "iso:country":"US",
    "sg:address":"307 Genoa Rd",
    "sg:city":"St Augustine",
    "sg:classifiers":[
        {
            "category":"Manufacturing",
            "subcategory":"Electronics",
            "type":"Manufacturing & Wholesale Goods"
        }
    ],
    "sg:phone":"+1 904 827 0093",
    "sg:postcode":"32084",
    "sg:province":"FL",
    "sg:tags":[
        "mfg",
        "component",
        "printed",
        "circuit",
        "electronic",
        "etched"
    ],
    "wof:name":"Tekni Circuits Inc",
    "wof:placetype":"venue"
},
  "geometry": {"coordinates":[-81.294224,29.913273],"type":"Point"}
}