{
  "type": "Feature",
  "properties": {
    "addr:full":"4726 Seastar Vis Destin FL 32541",
    "addr:housenumber":"4726",
    "addr:postcode":"32541",
    "addr:street":"Seastar Vis",
    "iso:country":"US",
    "sg:address":"4726 Seastar Vis",
    "sg:city":"Destin",
    "sg:classifiers":[
        {
            "category":"Professional",
            "subcategory":"Detective & Security Services",
            "type":"Services"
        }
    ],
    "sg:phone":"+1 850 650 2695",
    "sg:postcode":"32541",
    "sg:province":"FL",
    "sg:tags":[
        "information",
        "bureau"
    ],
    "wof:name":"Business Services Distributors, Inc.",
    "wof:placetype":"venue"
},
  "geometry": {"coordinates":[-86.407516,30.385342],"type":"Point"}
}