{
  "type": "Feature",
  "properties": {
    "addr:full":"9974 Old Federal Rd Quincy FL 32351",
    "addr:housenumber":"9974",
    "addr:postcode":"32351",
    "addr:street":"Old Federal Rd",
    "iso:country":"US",
    "sg:address":"9974 Old Federal Rd",
    "sg:city":"Quincy",
    "sg:classifiers":[
        {
            "category":"Professional",
            "type":"Services"
        }
    ],
    "sg:phone":"+1 850 627 7966",
    "sg:postcode":"32351",
    "sg:province":"FL",
    "sg:tags":[
        "janitorial"
    ],
    "wof:name":"Tolleys",
    "wof:placetype":"venue"
},
  "geometry": {"coordinates":[-84.56694,30.51765],"type":"Point"}
}