{
  "type": "Feature",
  "properties": {
    "addr:full":"951 N 14th St Leesburg FL 34748",
    "addr:housenumber":"951",
    "addr:postcode":"34748",
    "addr:street":"N 14Th St",
    "iso:country":"US",
    "sg:address":"951 N 14th St",
    "sg:city":"Leesburg",
    "sg:classifiers":[
        {
            "category":"Restaurant",
            "type":"Food & Drink"
        }
    ],
    "sg:phone":"+1 352 787 5036",
    "sg:postcode":"34748",
    "sg:province":"FL",
    "sg:tags":[
        "barbecue"
    ],
    "wof:name":"Oakwood Smokehouse And Grill",
    "wof:placetype":"venue"
},
  "geometry": {"coordinates":[-81.887489,28.822128],"type":"Point"}
}