{
  "type": "Feature",
  "properties": {
    "iso:country":"US",
    "sg:address":"5117 Castello Dr",
    "sg:city":"Naples",
    "sg:classifiers":[
        {
            "category":"Professional",
            "subcategory":"Lawyer & Legal Services",
            "type":"Services"
        }
    ],
    "sg:phone":"+1 239 430 0000",
    "sg:postcode":"34103",
    "sg:province":"FL",
    "sg:tags":[
        "attorney"
    ],
    "wof:name":"Paul Murray",
    "wof:placetype":"venue"
},
  "geometry": {"coordinates":[-81.79788000000001,26.20943],"type":"Point"}
}