{
  "type": "Feature",
  "properties": {
    "addr:full":"3601 Lakemont Ct Palm Beach Gdns FL 33403",
    "addr:housenumber":"3601",
    "addr:postcode":"33403",
    "addr:street":"Lakemont Ct",
    "iso:country":"US",
    "sg:address":"3601 Lakemont Ct",
    "sg:city":"Palm Beach Gdns",
    "sg:classifiers":[
        {
            "category":"Communications",
            "subcategory":"Film & Video Production",
            "type":"Services"
        }
    ],
    "sg:phone":"+1 561 775 8773",
    "sg:postcode":"33403",
    "sg:province":"FL",
    "sg:tags":[
        "taping"
    ],
    "wof:name":"Animation Effects",
    "wof:placetype":"venue"
},
  "geometry": {"coordinates":[-80.090755,26.813413],"type":"Point"}
}