{
  "type": "Feature",
  "properties": {
    "iso:country":"US",
    "sg:address":"4 W Las Olas Blvd",
    "sg:city":"Fort Lauderdale",
    "sg:classifiers":[
        {
            "category":"Banks & Credit Unions",
            "subcategory":"Investment Brokerage",
            "type":"Services"
        }
    ],
    "sg:phone":"+1 954 524 7772",
    "sg:postcode":"33301",
    "sg:province":"FL",
    "sg:tags":[
        "security"
    ],
    "wof:name":"Brookstreet Securities Corp",
    "wof:placetype":"venue"
},
  "geometry": {"coordinates":[-80.14448299999999,26.119399],"type":"Point"}
}