{
  "type": "Feature",
  "properties": {
    "addr:full":"5297 Phillips Hwy Jacksonville FL 32207",
    "addr:housenumber":"5297",
    "addr:postcode":"32207",
    "addr:street":"Phillips Hwy",
    "iso:country":"US",
    "sg:address":"5297 Phillips Hwy",
    "sg:city":"Jacksonville",
    "sg:classifiers":[
        {
            "category":"Wholesale",
            "subcategory":"Auto Parts",
            "type":"Manufacturing & Wholesale Goods"
        }
    ],
    "sg:phone":"+1 904 732 2282",
    "sg:postcode":"32207",
    "sg:province":"FL",
    "wof:name":"Mattos Incorporated",
    "wof:placetype":"venue"
},
  "geometry": {"coordinates":[-81.620632,30.269256],"type":"Point"}
}