{
  "type": "Feature",
  "properties": {
    "addr:full":"7190 SE Federal Hwy Stuart FL 34997",
    "addr:housenumber":"7190",
    "addr:postcode":"34997",
    "addr:street":"Se Federal Hwy",
    "iso:country":"US",
    "sg:address":"7190 SE Federal Hwy",
    "sg:city":"Stuart",
    "sg:classifiers":[
        {
            "category":"Building & Trades",
            "subcategory":"Construction",
            "type":"Services"
        }
    ],
    "sg:phone":"+1 772 781 9112",
    "sg:postcode":"34997",
    "sg:province":"FL",
    "sg:tags":[
        "residential",
        "designer"
    ],
    "wof:name":"Johnson Designs",
    "wof:placetype":"venue"
},
  "geometry": {"coordinates":[-80.18395700000001,27.120017],"type":"Point"}
}