{
  "type": "Feature",
  "properties": {
    "iso:country":"US",
    "sg:address":"3221 Paradise Way",
    "sg:city":"Zephyrhills",
    "sg:classifiers":[
        {
            "category":"Real Estate",
            "subcategory":"Real Estate Operator",
            "type":"Services"
        }
    ],
    "sg:phone":"+1 813 782 8441",
    "sg:postcode":"33541",
    "sg:province":"FL",
    "sg:tags":[
        "mobile",
        "home",
        "community"
    ],
    "wof:name":"Tropical Acres Estates",
    "wof:placetype":"venue"
},
  "geometry": {"coordinates":[-82.19362599999999,28.20409],"type":"Point"}
}