{
  "type": "Feature",
  "properties": {
    "addr:full":"3695 Tamiami Trl Port Charlotte FL 33952",
    "addr:housenumber":"3695",
    "addr:postcode":"33952",
    "addr:street":"Tamiami Trl",
    "iso:country":"US",
    "sg:address":"3695 Tamiami Trl",
    "sg:city":"Port Charlotte",
    "sg:classifiers":[
        {
            "category":"Communications",
            "subcategory":"Film & Video Production",
            "type":"Services"
        }
    ],
    "sg:phone":"+1 941 764 8400",
    "sg:postcode":"33952",
    "sg:province":"FL",
    "sg:tags":[
        "duplication",
        "tape"
    ],
    "wof:name":"Video Services",
    "wof:placetype":"venue"
},
  "geometry": {"coordinates":[-82.090068,26.975112],"type":"Point"}
}