{
  "type": "Feature",
  "properties": {
    "iso:country":"US",
    "sg:address":"7218 Spring Hill Dr",
    "sg:city":"Spring Hill",
    "sg:classifiers":[
        {
            "category":"Shopping",
            "subcategory":"Gifts & Souvenirs",
            "type":"Retail Goods"
        }
    ],
    "sg:phone":"+1 352 684 7096",
    "sg:postcode":"34606",
    "sg:province":"FL",
    "wof:name":"Mystical Magic Gift Shop",
    "wof:placetype":"venue"
},
  "geometry": {"coordinates":[-82.599936,28.450404],"type":"Point"}
}