{
  "type": "Feature",
  "properties": {
    "iso:country":"US",
    "sg:address":"4000 10th St W",
    "sg:city":"Palmetto",
    "sg:classifiers":[
        {
            "category":"Autos & Motor Vehicles",
            "subcategory":"Boat Sales",
            "type":"Retail Goods"
        },
        {
            "category":"Recreation",
            "subcategory":"Marina",
            "type":"Entertainment"
        },
        {
            "category":"Retail",
            "subcategory":"Storage",
            "type":"Services"
        }
    ],
    "sg:phone":"+1 941 729 4878",
    "sg:postcode":"34221",
    "sg:province":"FL",
    "sg:tags":[
        "repair",
        "maintenance"
    ],
    "sg:website":"http://www.cutsedgemarina.com",
    "wof:name":"Cut's Edge Harbor Marina Inc",
    "wof:placetype":"venue"
},
  "geometry": {"coordinates":[-82.60839799999999,27.52375],"type":"Point"}
}