{
  "type": "Feature",
  "properties": {
    "addr:full":"1300 NW 7th St Miami FL 33125",
    "addr:housenumber":"1300",
    "addr:postcode":"33125",
    "addr:street":"Nw 7Th St",
    "iso:country":"US",
    "sg:address":"1300 NW 7th St",
    "sg:city":"Miami",
    "sg:classifiers":[
        {
            "category":"Building & Trades",
            "subcategory":"Locksmith",
            "type":"Services"
        }
    ],
    "sg:phone":"+1 305 755 4139",
    "sg:postcode":"33125",
    "sg:province":"FL",
    "sg:tags":[
        "key"
    ],
    "wof:name":"24 Hour 7 Day Emergency Locksmith",
    "wof:placetype":"venue"
},
  "geometry": {"coordinates":[-80.216505,25.780043],"type":"Point"}
}