{
  "type": "Feature",
  "properties": {
    "iso:country":"US",
    "sg:address":"12220 Atlantic Blvd",
    "sg:city":"Jacksonville",
    "sg:classifiers":[
        {
            "category":"Restaurant",
            "type":"Food & Drink"
        }
    ],
    "sg:menulink":"http://www.allmenus.com/fl/jacksonville/113968-kumo-japanese--sushi-grill/menu/",
    "sg:phone":"+1 904 220 2966",
    "sg:postcode":"32225",
    "sg:province":"FL",
    "sg:tags":[
        "japanese",
        "asian"
    ],
    "wof:name":"Kumo Japanese & Sushi Grill",
    "wof:placetype":"venue"
},
  "geometry": {"coordinates":[-81.480103,30.317937],"type":"Point"}
}