{
  "type": "Feature",
  "properties": {
    "iso:country":"US",
    "sg:address":"10280 NW 9th Street Cir",
    "sg:city":"Miami",
    "sg:classifiers":[
        {
            "category":"Banks & Credit Unions",
            "subcategory":"Bank",
            "type":"Services"
        }
    ],
    "sg:phone":"+1 305 485 4488",
    "sg:postcode":"33172",
    "sg:province":"FL",
    "sg:tags":[
        "loan",
        "real estate"
    ],
    "wof:name":"Prime Meridian Mortgage Group",
    "wof:placetype":"venue"
},
  "geometry": {"coordinates":[-80.36317200000001,25.777575],"type":"Point"}
}