{
  "type": "Feature",
  "properties": {
    "iso:country":"US",
    "sg:address":"88 Whiddon Lake Rd",
    "sg:city":"Crawfordville",
    "sg:classifiers":[
        {
            "category":"Professional",
            "subcategory":"Business Services",
            "type":"Services"
        }
    ],
    "sg:phone":"+1 850 926 3109",
    "sg:postcode":"32327",
    "sg:province":"FL",
    "sg:tags":[
        "inspection"
    ],
    "wof:name":"Ross Inspection Services Inc",
    "wof:placetype":"venue"
},
  "geometry": {"coordinates":[-84.365942,30.22506],"type":"Point"}
}