{
  "type": "Feature",
  "properties": {
    "iso:country":"US",
    "sg:address":"1189 E Altamonte Dr",
    "sg:city":"Altamonte Spgs",
    "sg:classifiers":[
        {
            "category":"Personal",
            "subcategory":"Beauty Salon",
            "type":"Services"
        }
    ],
    "sg:phone":"+1 407 834 7002",
    "sg:postcode":"32701",
    "sg:province":"FL",
    "wof:name":"Cache Beauty Salon",
    "wof:placetype":"venue"
},
  "geometry": {"coordinates":[-81.350781,28.663207],"type":"Point"}
}