{
  "type": "Feature",
  "properties": {
    "addr:full":"1424 Franklin St Jacksonville FL 32206",
    "addr:housenumber":"1424",
    "addr:postcode":"32206",
    "addr:street":"Franklin St",
    "iso:country":"US",
    "sg:address":"1424 Franklin St",
    "sg:city":"Jacksonville",
    "sg:classifiers":[
        {
            "category":"Education",
            "subcategory":"School",
            "type":"Public Place"
        }
    ],
    "sg:phone":"+1 904 630 6700",
    "sg:postcode":"32206",
    "sg:province":"FL",
    "sg:tags":[
        "elementary"
    ],
    "wof:name":"Gilbert Matthew W",
    "wof:placetype":"venue"
},
  "geometry": {"coordinates":[-81.639453,30.341547],"type":"Point"}
}