{
  "type": "Feature",
  "properties": {
    "addr:full":"9005 Baywood Park Dr Largo FL 33777",
    "addr:housenumber":"9005",
    "addr:postcode":"33777",
    "addr:street":"Baywood Park Dr",
    "iso:country":"US",
    "sg:address":"9005 Baywood Park Dr",
    "sg:city":"Largo",
    "sg:classifiers":[
        {
            "category":"Wholesale",
            "subcategory":"Non-durable Goods",
            "type":"Manufacturing & Wholesale Goods"
        }
    ],
    "sg:phone":"+1 727 398 5708",
    "sg:postcode":"33777",
    "sg:province":"FL",
    "wof:name":"There's A Fine Line Inc",
    "wof:placetype":"venue"
},
  "geometry": {"coordinates":[-82.76224000000001,27.827662],"type":"Point"}
}