{
  "type": "Feature",
  "properties": {
    "iso:country":"US",
    "sg:address":"1435 Piedmont Dr",
    "sg:city":"Tallahassee",
    "sg:classifiers":[
        {
            "category":"Real Estate",
            "subcategory":"Real Estate Agent",
            "type":"Services"
        }
    ],
    "sg:phone":"+1 850 386 1158",
    "sg:postcode":"32308",
    "sg:province":"FL",
    "wof:name":"Daniel G Vollmer Realtor",
    "wof:placetype":"venue"
},
  "geometry": {"coordinates":[-84.255663,30.495283],"type":"Point"}
}