{
  "type": "Feature",
  "properties": {
    "iso:country":"US",
    "sg:address":"220 US Hwy 1",
    "sg:city":"Lake Park",
    "sg:classifiers":[
        {
            "category":"Shopping",
            "subcategory":"Bicycles & Sporting Goods",
            "type":"Retail Goods"
        },
        {
            "category":"Wholesale",
            "subcategory":"Non-durable Goods",
            "type":"Manufacturing & Wholesale Goods"
        }
    ],
    "sg:phone":"+1 561 848 4484",
    "sg:postcode":"33403",
    "sg:province":"FL",
    "sg:tags":[
        "bait",
        "fishing"
    ],
    "sg:website":"www.williesbait.com",
    "wof:name":"Willies Custom Trolling Baits",
    "wof:placetype":"venue"
},
  "geometry": {"coordinates":[-80.05446499999999,26.79427],"type":"Point"}
}