{
  "type": "Feature",
  "properties": {
    "iso:country":"US",
    "sg:address":"4599 36th Ave N",
    "sg:city":"St Petersburg",
    "sg:classifiers":[
        {
            "category":"Personal",
            "subcategory":"Beauty Salon",
            "type":"Services"
        }
    ],
    "sg:phone":"+1 727 522 7131",
    "sg:postcode":"33713",
    "sg:province":"FL",
    "wof:name":"Dorothy Grant Stylist & Spa",
    "wof:placetype":"venue"
},
  "geometry": {"coordinates":[-82.693934,27.8049],"type":"Point"}
}