{
  "type": "Feature",
  "properties": {
    "iso:country":"US",
    "sg:address":"9487 Dixie Hwy",
    "sg:city":"Miami",
    "sg:classifiers":[
        {
            "category":"Personal",
            "type":"Services"
        }
    ],
    "sg:phone":"+1 305 661 0888",
    "sg:postcode":"33156",
    "sg:province":"FL",
    "sg:tags":[
        "wear",
        "formal"
    ],
    "wof:name":"Miami Tux",
    "wof:placetype":"venue"
},
  "geometry": {"coordinates":[-80.314987,25.682518],"type":"Point"}
}