{
  "type": "Feature",
  "properties": {
    "iso:country":"US",
    "sg:address":"634 Blanding Blvd",
    "sg:city":"Orange Park",
    "sg:classifiers":[
        {
            "category":"Retail",
            "subcategory":"Auto Repair",
            "type":"Services"
        }
    ],
    "sg:phone":"+1 904 272 1271",
    "sg:postcode":"32073",
    "sg:province":"FL",
    "sg:tags":[
        "automotive"
    ],
    "wof:name":"Jiffy Lube",
    "wof:placetype":"venue"
},
  "geometry": {"coordinates":[-81.751873,30.151162],"type":"Point"}
}