{
  "type": "Feature",
  "properties": {
    "iso:country":"US",
    "sg:address":"1471 NW 14th St",
    "sg:city":"Miami",
    "sg:classifiers":[
        {
            "category":"Professional",
            "subcategory":"Business Services",
            "type":"Services"
        }
    ],
    "sg:phone":"+1 954 483 6440",
    "sg:postcode":"33125",
    "sg:province":"FL",
    "sg:tags":[
        "company"
    ],
    "wof:name":"H E S Media LLC",
    "wof:placetype":"venue"
},
  "geometry": {"coordinates":[-80.21951900000001,25.787561],"type":"Point"}
}