{
  "type": "Feature",
  "properties": {
    "addr:full":"436 Shearer Blvd Cocoa FL 32922",
    "addr:housenumber":"436",
    "addr:postcode":"32922",
    "addr:street":"Shearer Blvd",
    "iso:country":"US",
    "sg:address":"436 Shearer Blvd",
    "sg:city":"Cocoa",
    "sg:classifiers":[
        {
            "category":"Building & Trades",
            "subcategory":"Construction",
            "type":"Services"
        }
    ],
    "sg:phone":"+1 321 795 0600",
    "sg:postcode":"32922",
    "sg:province":"FL",
    "sg:tags":[
        "contractor"
    ],
    "wof:name":"Jayson M Ruland",
    "wof:placetype":"venue"
},
  "geometry": {"coordinates":[-80.737399,28.362587],"type":"Point"}
}