{
  "type": "Feature",
  "properties": {
    "iso:country":"US",
    "sg:address":"140 Commercial Way",
    "sg:city":"Spring Hill",
    "sg:classifiers":[
        {
            "category":"Shopping",
            "subcategory":"Used Merchandise",
            "type":"Retail Goods"
        }
    ],
    "sg:phone":"+1 352 688 6970",
    "sg:postcode":"34606",
    "sg:province":"FL",
    "wof:name":"Browsery",
    "wof:placetype":"venue"
},
  "geometry": {"coordinates":[-82.63761,28.438168],"type":"Point"}
}