{
  "type": "Feature",
  "properties": {
    "iso:country":"US",
    "sg:address":"1810 Runners Way",
    "sg:city":"Pompano Beach",
    "sg:classifiers":[
        {
            "category":"Arts & Performance",
            "subcategory":"Theater",
            "type":"Entertainment"
        }
    ],
    "sg:phone":"+1 954 520 3247",
    "sg:postcode":"33068",
    "sg:province":"FL",
    "sg:tags":[
        "group"
    ],
    "wof:name":"Sporksounds Co",
    "wof:placetype":"venue"
},
  "geometry": {"coordinates":[-80.223017,26.204366],"type":"Point"}
}