{
  "type": "Feature",
  "properties": {
    "iso:country":"US",
    "sg:address":"944 4th St N",
    "sg:city":"Saint Petersburg",
    "sg:classifiers":[
        {
            "category":"Restaurant",
            "type":"Food & Drink"
        }
    ],
    "sg:menulink":"http://www.allmenus.com/fl/st-petersburg/36872-tijuana-flats/menu/",
    "sg:phone":"+1 727 823 5882",
    "sg:postcode":"33701",
    "sg:province":"FL",
    "sg:tags":[
        "mexican"
    ],
    "wof:name":"Tijuana Flats",
    "wof:placetype":"venue"
},
  "geometry": {"coordinates":[-82.638516,27.781639],"type":"Point"}
}