{
  "type": "Feature",
  "properties": {
    "iso:country":"US",
    "sg:address":"1236 13th St",
    "sg:city":"Daytona Beach",
    "sg:classifiers":[
        {
            "category":"Building & Trades",
            "subcategory":"Landscaping Services",
            "type":"Services"
        }
    ],
    "sg:phone":"+1 386 252 7181",
    "sg:postcode":"32117",
    "sg:province":"FL",
    "wof:name":"J&M Landscape & Lawn Mtc",
    "wof:placetype":"venue"
},
  "geometry": {"coordinates":[-81.065015,29.240019],"type":"Point"}
}