{
  "type": "Feature",
  "properties": {
    "iso:country":"US",
    "sg:address":"5820 Willard Norris Rd",
    "sg:city":"Milton",
    "sg:classifiers":[
        {
            "category":"Building & Trades",
            "subcategory":"Cleaning & Sanitation",
            "type":"Services"
        }
    ],
    "sg:phone":"+1 850 623 3300",
    "sg:postcode":"32570",
    "sg:province":"FL",
    "sg:tags":[
        "fireplace",
        "chimney"
    ],
    "wof:name":"Chiminey Cricket",
    "wof:placetype":"venue"
},
  "geometry": {"coordinates":[-87.08008100000001,30.657763],"type":"Point"}
}