{
  "type": "Feature",
  "properties": {
    "iso:country":"US",
    "sg:address":"575 Beal Pkwy NW",
    "sg:city":"Fort Walton Bch",
    "sg:classifiers":[
        {
            "category":"Building & Trades",
            "subcategory":"Construction",
            "type":"Services"
        }
    ],
    "sg:phone":"+1 850 863 2511",
    "sg:postcode":"32548",
    "sg:province":"FL",
    "wof:name":"Stuff Busters Portable Bldgs",
    "wof:placetype":"venue"
},
  "geometry": {"coordinates":[-86.63953600000001,30.430545],"type":"Point"}
}