{
  "type": "Feature",
  "properties": {
    "addr:full":"151 NW 71st St Miami FL 33150",
    "addr:housenumber":"151",
    "addr:postcode":"33150",
    "addr:street":"Nw 71St St",
    "iso:country":"US",
    "sg:address":"151 NW 71st St",
    "sg:city":"Miami",
    "sg:classifiers":[
        {
            "category":"Building & Trades",
            "subcategory":"Locksmith",
            "type":"Services"
        }
    ],
    "sg:phone":"+1 305 908 5728",
    "sg:postcode":"33150",
    "sg:province":"FL",
    "sg:tags":[
        "key"
    ],
    "wof:name":"0 Alwayes 1 24 A Locksmith",
    "wof:placetype":"venue"
},
  "geometry": {"coordinates":[-80.199696,25.840057],"type":"Point"}
}