{
  "type": "Feature",
  "properties": {
    "iso:country":"US",
    "sg:address":"4554 SW 71st Ave",
    "sg:city":"Miami",
    "sg:classifiers":[
        {
            "category":"Professional",
            "subcategory":"Art Services",
            "type":"Services"
        }
    ],
    "sg:phone":"+1 786 360 1738",
    "sg:postcode":"33155",
    "sg:province":"FL",
    "sg:tags":[
        "interior",
        "designer",
        "decorator"
    ],
    "wof:name":"International Design Group",
    "wof:placetype":"venue"
},
  "geometry": {"coordinates":[-80.308763,25.727761],"type":"Point"}
}