{
  "type": "Feature",
  "properties": {
    "addr:full":"27242 Townsend Ter Punta Gorda FL 33983",
    "addr:housenumber":"27242",
    "addr:postcode":"33983",
    "addr:street":"Townsend Ter",
    "iso:country":"US",
    "sg:address":"27242 Townsend Ter",
    "sg:city":"Punta Gorda",
    "sg:classifiers":[
        {
            "category":"Building & Trades",
            "subcategory":"Construction",
            "type":"Services"
        }
    ],
    "sg:phone":"+1 941 743 4088",
    "sg:postcode":"33983",
    "sg:province":"FL",
    "sg:tags":[
        "house",
        "improvement",
        "home"
    ],
    "wof:name":"Hewitt's Home Improvement",
    "wof:placetype":"venue"
},
  "geometry": {"coordinates":[-82.00170199999999,26.990648],"type":"Point"}
}