{
  "type": "Feature",
  "properties": {
    "addr:full":"8522 Gulf Blvd Gulf Breeze FL 32566",
    "addr:housenumber":"8522",
    "addr:postcode":"32566",
    "addr:street":"Gulf Blvd",
    "iso:country":"US",
    "sg:address":"8522 Gulf Blvd",
    "sg:city":"Gulf Breeze",
    "sg:classifiers":[
        {
            "category":"Building & Trades",
            "subcategory":"Construction",
            "type":"Services"
        }
    ],
    "sg:phone":"+1 850 936 9704",
    "sg:postcode":"32566",
    "sg:province":"FL",
    "sg:tags":[
        "masonry",
        "contractor"
    ],
    "wof:name":"Emerald Coast Masonry",
    "wof:placetype":"venue"
},
  "geometry": {"coordinates":[-86.866513,30.38094],"type":"Point"}
}