{
  "type": "Feature",
  "properties": {
    "addr:full":"921 Copperfield Ter Casselberry FL 32707",
    "addr:housenumber":"921",
    "addr:postcode":"32707",
    "addr:street":"Copperfield Ter",
    "iso:country":"US",
    "sg:address":"921 Copperfield Ter",
    "sg:city":"Casselberry",
    "sg:classifiers":[
        {
            "category":"Wholesale",
            "subcategory":"Construction Materials",
            "type":"Manufacturing & Wholesale Goods"
        }
    ],
    "sg:phone":"+1 407 695 6194",
    "sg:postcode":"32707",
    "sg:province":"FL",
    "wof:name":"Roofing Technology Inc",
    "wof:placetype":"venue"
},
  "geometry": {"coordinates":[-81.300516,28.648239],"type":"Point"}
}