{
  "type": "Feature",
  "properties": {
    "iso:country":"US",
    "sg:address":"2295 Corporate Blvd NW",
    "sg:city":"Boca Raton",
    "sg:classifiers":[
        {
            "category":"Real Estate",
            "subcategory":"Real Estate Agent",
            "type":"Services"
        }
    ],
    "sg:phone":"+1 561 999 8915",
    "sg:postcode":"33431",
    "sg:province":"FL",
    "wof:name":"Internet International Realty",
    "wof:placetype":"venue"
},
  "geometry": {"coordinates":[-80.127579,26.370772],"type":"Point"}
}