{
  "type": "Feature",
  "properties": {
    "iso:country":"US",
    "sg:address":"7007 Lely Cultural Pkwy",
    "sg:city":"Naples",
    "sg:classifiers":[
        {
            "category":"Education",
            "subcategory":"College",
            "type":"Public Place"
        }
    ],
    "sg:phone":"+1 239 732 3700",
    "sg:postcode":"34113",
    "sg:province":"FL",
    "wof:name":"Learning Resource Ctr Collier",
    "wof:placetype":"venue"
},
  "geometry": {"coordinates":[-81.699714,26.100495],"type":"Point"}
}