{
  "type": "Feature",
  "properties": {
    "addr:full":"4362 Avalon Blvd Milton FL 32583",
    "addr:housenumber":"4362",
    "addr:postcode":"32583",
    "addr:street":"Avalon Blvd",
    "iso:country":"US",
    "sg:address":"4362 Avalon Blvd",
    "sg:city":"Milton",
    "sg:classifiers":[
        {
            "category":"Retail",
            "subcategory":"Repair Shop",
            "type":"Services"
        }
    ],
    "sg:phone":"+1 850 626 1530",
    "sg:postcode":"32583",
    "sg:province":"FL",
    "sg:tags":[
        "equipment",
        "industrial"
    ],
    "wof:name":"Environmental Analytics Inc",
    "wof:placetype":"venue"
},
  "geometry": {"coordinates":[-87.081309,30.592649],"type":"Point"}
}