{
  "type": "Feature",
  "properties": {
    "iso:country":"US",
    "sg:address":"6000 Universal Blvd",
    "sg:city":"Orlando",
    "sg:classifiers":[
        {
            "category":"Professional",
            "type":"Services"
        }
    ],
    "sg:phone":"+1 407 363 5922",
    "sg:postcode":"32819",
    "sg:province":"FL",
    "sg:tags":[
        "establishment"
    ],
    "wof:name":"Latin Quarter",
    "wof:placetype":"venue"
},
  "geometry": {"coordinates":[-81.46295499999999,28.474999],"type":"Point"}
}