{
  "type": "Feature",
  "properties": {
    "iso:country":"US",
    "sg:address":"6380 Schwab Dr",
    "sg:city":"Pensacola",
    "sg:classifiers":[
        {
            "category":"Building & Trades",
            "subcategory":"Construction",
            "type":"Services"
        }
    ],
    "sg:phone":"+1 850 477 2018",
    "sg:postcode":"32504",
    "sg:province":"FL",
    "sg:tags":[
        "wallcoverings-installation",
        "wallpaper",
        "painting",
        "contractor"
    ],
    "wof:name":"Perfect Touch Painting",
    "wof:placetype":"venue"
},
  "geometry": {"coordinates":[-87.200962,30.489596],"type":"Point"}
}