{
  "type": "Feature",
  "properties": {
    "addr:full":"200 Dixie Ave Callahan FL 32011",
    "addr:housenumber":"200",
    "addr:postcode":"32011",
    "addr:street":"Dixie Ave",
    "iso:country":"US",
    "sg:address":"200 Dixie Ave",
    "sg:city":"Callahan",
    "sg:classifiers":[
        {
            "category":"Shopping",
            "subcategory":"Gifts & Souvenirs",
            "type":"Retail Goods"
        }
    ],
    "sg:phone":"+1 904 879 5900",
    "sg:postcode":"32011",
    "sg:province":"FL",
    "sg:tags":[
        "collectible"
    ],
    "wof:name":"Attic",
    "wof:placetype":"venue"
},
  "geometry": {"coordinates":[-81.83346,30.56362],"type":"Point"}
}