{
  "type": "Feature",
  "properties": {
    "iso:country":"US",
    "sg:address":"219 McKinley Dr",
    "sg:city":"Pensacola",
    "sg:classifiers":[
        {
            "category":"Professional",
            "type":"Services"
        }
    ],
    "sg:phone":"+1 850 457 2918",
    "sg:postcode":"32505",
    "sg:province":"FL",
    "wof:name":"Robbie Donaldson Svc",
    "wof:placetype":"venue"
},
  "geometry": {"coordinates":[-87.276358,30.443621],"type":"Point"}
}