{
  "type": "Feature",
  "properties": {
    "iso:country":"US",
    "sg:address":"6502 SW 102nd Ave",
    "sg:city":"Bushnell",
    "sg:classifiers":[
        {
            "category":"Real Estate",
            "subcategory":"Developer",
            "type":"Services"
        }
    ],
    "sg:phone":"+1 904 829 2661",
    "sg:postcode":"33513",
    "sg:province":"FL",
    "sg:tags":[
        "cemetery"
    ],
    "wof:name":"St Augustine National Cemetery",
    "wof:placetype":"venue"
},
  "geometry": {"coordinates":[-82.210921,28.606942],"type":"Point"}
}