{
  "type": "Feature",
  "properties": {
    "iso:country":"US",
    "sg:address":"1654 NW 35th St",
    "sg:city":"Miami",
    "sg:classifiers":[
        {
            "category":"Restaurant",
            "type":"Food & Drink"
        }
    ],
    "sg:phone":"+1 786 991 4843",
    "sg:postcode":"33142",
    "sg:province":"FL",
    "sg:tags":[
        "mexican"
    ],
    "wof:name":"Dwane Garcia",
    "wof:placetype":"venue"
},
  "geometry": {"coordinates":[-80.223395,25.808615],"type":"Point"}
}