{
  "type": "Feature",
  "properties": {
    "addr:full":"3875 Arnold Ave Naples FL 34104",
    "addr:housenumber":"3875",
    "addr:postcode":"34104",
    "addr:street":"Arnold Ave",
    "iso:country":"US",
    "sg:address":"3875 Arnold Ave",
    "sg:city":"Naples",
    "sg:classifiers":[
        {
            "category":"Professional",
            "subcategory":"Computer Services",
            "type":"Services"
        }
    ],
    "sg:phone":"+1 239 643 6596",
    "sg:postcode":"34104",
    "sg:province":"FL",
    "sg:tags":[
        "control",
        "mfg",
        "process",
        "system",
        "instrument",
        "design"
    ],
    "wof:name":"Pro-Tech Controls Company Inc",
    "wof:placetype":"venue"
},
  "geometry": {"coordinates":[-81.762584,26.167252],"type":"Point"}
}