{
  "type": "Feature",
  "properties": {
    "addr:full":"4601 SW 74th Ave Miami FL 33155",
    "addr:housenumber":"4601",
    "addr:postcode":"33155",
    "addr:street":"Sw 74Th Ave",
    "iso:country":"US",
    "sg:address":"4601 SW 74th Ave",
    "sg:city":"Miami",
    "sg:classifiers":[
        {
            "category":"Manufacturing",
            "subcategory":"Tools & Machinery",
            "type":"Manufacturing & Wholesale Goods"
        }
    ],
    "sg:phone":"+1 786 355 2934",
    "sg:postcode":"33155",
    "sg:province":"FL",
    "sg:tags":[
        "equipment",
        "computer",
        "original",
        "software"
    ],
    "wof:name":"Edison Solutions  Inc",
    "wof:placetype":"venue"
},
  "geometry": {"coordinates":[-80.314841,25.727169],"type":"Point"}
}