{
  "type": "Feature",
  "properties": {
    "iso:country":"US",
    "sg:address":"580 E Gateway Ct",
    "sg:city":"Merritt Island",
    "sg:classifiers":[
        {
            "category":"Cinema",
            "subcategory":"Movie Rental",
            "type":"Entertainment"
        }
    ],
    "sg:phone":"+1 321 452 8798",
    "sg:postcode":"32952",
    "sg:province":"FL",
    "sg:tags":[
        "video",
        "tape"
    ],
    "wof:name":"Digital Sports Video",
    "wof:placetype":"venue"
},
  "geometry": {"coordinates":[-80.666769,28.347987],"type":"Point"}
}