{
  "type": "Feature",
  "properties": {
    "iso:country":"US",
    "sg:address":"9357 Airport Blvd",
    "sg:city":"Orlando",
    "sg:classifiers":[
        {
            "category":"Shopping",
            "subcategory":"Clothing, Apparel, & Fashions",
            "type":"Retail Goods"
        }
    ],
    "sg:phone":"+1 407 825 2570",
    "sg:postcode":"32827",
    "sg:province":"FL",
    "sg:tags":[
        "sportswear"
    ],
    "wof:name":"All Sports USA Inc",
    "wof:placetype":"venue"
},
  "geometry": {"coordinates":[-81.30506200000001,28.430891],"type":"Point"}
}