{
  "type": "Feature",
  "properties": {
    "addr:full":"1589 SW Wildcat Trl Stuart FL 34997",
    "addr:housenumber":"1589",
    "addr:postcode":"34997",
    "addr:street":"Sw Wildcat Trl",
    "iso:country":"US",
    "sg:address":"1589 SW Wildcat Trl",
    "sg:city":"Stuart",
    "sg:classifiers":[
        {
            "category":"Home & Garden",
            "subcategory":"Carpets & Floor Coverings",
            "type":"Retail Goods"
        }
    ],
    "sg:phone":"+1 772 781 1192",
    "sg:postcode":"34997",
    "sg:province":"FL",
    "sg:tags":[
        "dealer",
        "rug"
    ],
    "wof:name":"Floor Medics",
    "wof:placetype":"venue"
},
  "geometry": {"coordinates":[-80.275199,27.106398],"type":"Point"}
}