{
  "type": "Feature",
  "properties": {
    "addr:full":"17451 San Carlos Blvd Fort Myers Beach FL 33931",
    "addr:housenumber":"17451",
    "addr:postcode":"33931",
    "addr:street":"San Carlos Blvd",
    "iso:country":"US",
    "sg:address":"17451 San Carlos Blvd",
    "sg:city":"Fort Myers Beach",
    "sg:classifiers":[
        {
            "category":"Food & Beverages",
            "subcategory":"Groceries & Convenience Stores",
            "type":"Retail Goods"
        }
    ],
    "sg:phone":"+1 239 433 9507",
    "sg:postcode":"33931",
    "sg:province":"FL",
    "wof:name":"7-Eleven Food Stores",
    "wof:placetype":"venue"
},
  "geometry": {"coordinates":[-81.942941,26.487943],"type":"Point"}
}