{
  "type": "Feature",
  "properties": {
    "iso:country":"US",
    "sg:address":"4484 Park Blvd",
    "sg:city":"Pinellas Park",
    "sg:classifiers":[
        {
            "category":"Personal",
            "subcategory":"Barber",
            "type":"Services"
        }
    ],
    "sg:phone":"+1 727 546 2913",
    "sg:postcode":"33781",
    "sg:province":"FL",
    "wof:name":"VIP Room Barber Hair Styling",
    "wof:placetype":"venue"
},
  "geometry": {"coordinates":[-82.69517999999999,27.839144],"type":"Point"}
}