{
  "type": "Feature",
  "properties": {
    "addr:full":"10920 W Flagler St Ste 211 Miami FL 33174",
    "addr:housenumber":"10920",
    "addr:postcode":"33174",
    "addr:street":"W Flagler St Ste 211",
    "iso:country":"US",
    "sg:address":"10920 W Flagler St Ste 211",
    "sg:city":"Miami",
    "sg:classifiers":[
        {
            "category":"Professional",
            "subcategory":"Computer Services",
            "type":"Services"
        }
    ],
    "sg:phone":"+1 305 552 0631",
    "sg:postcode":"33174",
    "sg:province":"FL",
    "sg:tags":[
        "repair"
    ],
    "wof:name":"PC Max USA",
    "wof:placetype":"venue"
},
  "geometry": {"coordinates":[-80.373362,25.768209],"type":"Point"}
}