{
  "type": "Feature",
  "properties": {
    "addr:full":"123 N 20th Ave Hollywood FL 33020",
    "addr:housenumber":"123",
    "addr:postcode":"33020",
    "addr:street":"N 20Th Ave",
    "iso:country":"US",
    "sg:address":"123 N 20th Ave",
    "sg:city":"Hollywood",
    "sg:classifiers":[
        {
            "category":"Personal",
            "subcategory":"Beauty Salon",
            "type":"Services"
        }
    ],
    "sg:phone":"+1 954 920 8738",
    "sg:postcode":"33020",
    "sg:province":"FL",
    "sg:tags":[
        "hair",
        "stylist"
    ],
    "wof:name":"Ranses Hair Stylist",
    "wof:placetype":"venue"
},
  "geometry": {"coordinates":[-80.14698199999999,26.011702],"type":"Point"}
}