{
  "type": "Feature",
  "properties": {
    "addr:full":"2322 W 78th St Hialeah FL 33016",
    "addr:housenumber":"2322",
    "addr:postcode":"33016",
    "addr:street":"W 78Th St",
    "iso:country":"US",
    "sg:address":"2322 W 78th St",
    "sg:city":"Hialeah",
    "sg:classifiers":[
        {
            "category":"Wholesale",
            "subcategory":"Hardware",
            "type":"Manufacturing & Wholesale Goods"
        },
        {
            "category":"Building & Trades",
            "subcategory":"Plumbing",
            "type":"Services"
        }
    ],
    "sg:phone":"+1 305 556 7849",
    "sg:postcode":"33016",
    "sg:province":"FL",
    "sg:tags":[
        "heater",
        "make",
        "heating",
        "contractor",
        "ventilation",
        "conditioning",
        "air"
    ],
    "wof:name":"A & P Air Conditioning Corp",
    "wof:placetype":"venue"
},
  "geometry": {"coordinates":[-80.330281,25.893227],"type":"Point"}
}