{
  "type": "Feature",
  "properties": {
    "iso:country":"US",
    "sg:address":"4915 Old Winter Garden Rd",
    "sg:city":"Orlando",
    "sg:classifiers":[
        {
            "category":"Wholesale",
            "subcategory":"Non-durable Goods",
            "type":"Manufacturing & Wholesale Goods"
        }
    ],
    "sg:phone":"+1 407 293 2651",
    "sg:postcode":"32811",
    "sg:province":"FL",
    "sg:tags":[
        "bag",
        "canvas",
        "cotton"
    ],
    "wof:name":"Central City Bag Co",
    "wof:placetype":"venue"
},
  "geometry": {"coordinates":[-81.445137,28.543577],"type":"Point"}
}