{
  "type": "Feature",
  "properties": {
    "iso:country":"US",
    "sg:address":"7995 W 26th Ct",
    "sg:city":"Hialeah",
    "sg:classifiers":[
        {
            "category":"Building & Trades",
            "subcategory":"Landscaping Services",
            "type":"Services"
        }
    ],
    "sg:phone":"+1 305 558 5718",
    "sg:postcode":"33016",
    "sg:province":"FL",
    "sg:tags":[
        "lawn",
        "maintenance",
        "grounds"
    ],
    "wof:name":"Gardner",
    "wof:placetype":"venue"
},
  "geometry": {"coordinates":[-80.33725,25.894272],"type":"Point"}
}