{
  "type": "Feature",
  "properties": {
    "addr:full":"6330 Jensen Rd Tampa FL 33619",
    "addr:postcode":"6330;33619",
    "addr:street":"Jensen Rd",
    "iso:country":"US",
    "sg:address":"6330 Jensen Rd",
    "sg:city":"Tampa",
    "sg:classifiers":[
        {
            "category":"Professional",
            "subcategory":"Business Services",
            "type":"Services"
        }
    ],
    "sg:phone":"+1 813 672 2747",
    "sg:postcode":"33619",
    "sg:province":"FL",
    "sg:tags":[
        "exporter",
        "export",
        "representative"
    ],
    "wof:name":"Dimacar Export Corp",
    "wof:placetype":"venue"
},
  "geometry": {"coordinates":[-82.38772400000001,27.889987],"type":"Point"}
}