{
  "type": "Feature",
  "properties": {
    "addr:full":"5804 Countrywood Dr Sarasota FL 34232",
    "addr:housenumber":"5804",
    "addr:postcode":"34232",
    "addr:street":"Countrywood Dr",
    "iso:country":"US",
    "sg:address":"5804 Countrywood Dr",
    "sg:city":"Sarasota",
    "sg:classifiers":[
        {
            "category":"Professional",
            "subcategory":"Printing & Photocopies",
            "type":"Services"
        }
    ],
    "sg:phone":"+1 941 377 0097",
    "sg:postcode":"34232",
    "sg:province":"FL",
    "sg:tags":[
        "form",
        "printers-business"
    ],
    "wof:name":"Tinas Ink Inc",
    "wof:placetype":"venue"
},
  "geometry": {"coordinates":[-82.456552,27.307416],"type":"Point"}
}