{
  "type": "Feature",
  "properties": {
    "addr:full":"1407 Piedmont Dr Tallahassee FL 32308",
    "addr:housenumber":"1407",
    "addr:postcode":"32308",
    "addr:street":"Piedmont Dr",
    "iso:country":"US",
    "sg:address":"1407 Piedmont Dr",
    "sg:city":"Tallahassee",
    "sg:classifiers":[
        {
            "category":"Banks & Credit Unions",
            "subcategory":"Investment Brokerage",
            "type":"Services"
        }
    ],
    "sg:phone":"+1 850 386 5588",
    "sg:postcode":"32308",
    "sg:province":"FL",
    "sg:tags":[
        "security"
    ],
    "wof:name":"Raymond James",
    "wof:placetype":"venue"
},
  "geometry": {"coordinates":[-84.255663,30.495283],"type":"Point"}
}