{
  "type": "Feature",
  "properties": {
    "addr:full":"2416 NW 27th Ave Miami FL 33142",
    "addr:housenumber":"2416",
    "addr:postcode":"33142",
    "addr:street":"Nw 27Th Ave",
    "iso:country":"US",
    "sg:address":"2416 NW 27th Ave",
    "sg:city":"Miami",
    "sg:classifiers":[
        {
            "category":"Shopping",
            "type":"Retail Goods"
        }
    ],
    "sg:phone":"+1 305 638 1818",
    "sg:postcode":"33142",
    "sg:province":"FL",
    "sg:tags":[
        "religious"
    ],
    "wof:name":"Citana Y Congole",
    "wof:placetype":"venue"
},
  "geometry": {"coordinates":[-80.240056,25.799756],"type":"Point"}
}