{
  "type": "Feature",
  "properties": {
    "iso:country":"US",
    "sg:address":"1584 Cedar St",
    "sg:city":"Niceville",
    "sg:classifiers":[
        {
            "category":"Building & Trades",
            "subcategory":"Construction",
            "type":"Services"
        }
    ],
    "sg:phone":"+1 850 897 4100",
    "sg:postcode":"32578",
    "sg:province":"FL",
    "sg:tags":[
        "roofing",
        "altering",
        "remodeling",
        "contractor"
    ],
    "wof:name":"White Steve Roofing",
    "wof:placetype":"venue"
},
  "geometry": {"coordinates":[-86.40880199999999,30.488067],"type":"Point"}
}