{
  "type": "Feature",
  "properties": {
    "iso:country":"US",
    "sg:address":"13440 Palm Beach Blvd",
    "sg:city":"Fort Myers",
    "sg:classifiers":[
        {
            "category":"Banks & Credit Unions",
            "subcategory":"Investment Brokerage",
            "type":"Services"
        }
    ],
    "sg:phone":"+1 239 694 0407",
    "sg:postcode":"33905",
    "sg:province":"FL",
    "sg:tags":[
        "consultant",
        "financing"
    ],
    "wof:name":"Lee County Acceptance Corp",
    "wof:placetype":"venue"
},
  "geometry": {"coordinates":[-81.74342,26.705185],"type":"Point"}
}