{
  "type": "Feature",
  "properties": {
    "iso:country":"US",
    "sg:address":"7336 Lake Worth Rd",
    "sg:city":"Lake Worth",
    "sg:classifiers":[
        {
            "category":"Real Estate",
            "subcategory":"Real Estate Agent",
            "type":"Services"
        }
    ],
    "sg:phone":"+1 561 433 0564",
    "sg:postcode":"33467",
    "sg:province":"FL",
    "wof:name":"Drummond Investment Group",
    "wof:placetype":"venue"
},
  "geometry": {"coordinates":[-80.163803,26.617467],"type":"Point"}
}