{
  "type": "Feature",
  "properties": {
    "iso:country":"US",
    "sg:address":"227 N Magnolia Dr",
    "sg:city":"Tallahassee",
    "sg:classifiers":[
        {
            "category":"Professional",
            "subcategory":"Art Services",
            "type":"Services"
        }
    ],
    "sg:phone":"+1 850 508 0482",
    "sg:postcode":"32301",
    "sg:province":"FL",
    "sg:tags":[
        "photographer"
    ],
    "wof:name":"Mika Fowler Photographer",
    "wof:placetype":"venue"
},
  "geometry": {"coordinates":[-84.26200799999999,30.446512],"type":"Point"}
}