{
  "type": "Feature",
  "properties": {
    "addr:full":"3000 NW 82nd Ave Doral FL 33122",
    "addr:housenumber":"3000",
    "addr:postcode":"33122",
    "addr:street":"Nw 82Nd Ave",
    "iso:country":"US",
    "sg:address":"3000 NW 82nd Ave",
    "sg:city":"Doral",
    "sg:classifiers":[
        {
            "category":"Mining & Drilling",
            "type":"Manufacturing & Wholesale Goods"
        },
        {
            "category":"Building & Trades",
            "subcategory":"Equipment Rental",
            "type":"Services"
        }
    ],
    "sg:phone":"+1 305 513 4595",
    "sg:postcode":"33122",
    "sg:province":"FL",
    "sg:tags":[
        "gravel",
        "sand",
        "handling",
        "supply"
    ],
    "wof:name":"Machinery Engineering & Supply Co Inc",
    "wof:placetype":"venue"
},
  "geometry": {"coordinates":[-80.329109,25.80167],"type":"Point"}
}