{
  "type": "Feature",
  "properties": {
    "iso:country":"US",
    "sg:address":"18900 N Tamiami Trl",
    "sg:city":"Fort Myers",
    "sg:classifiers":[
        {
            "category":"Building & Trades",
            "subcategory":"Plumbing",
            "type":"Services"
        }
    ],
    "sg:phone":"+1 239 731 6795",
    "sg:postcode":"33903",
    "sg:province":"FL",
    "sg:tags":[
        "mechanical",
        "contractor"
    ],
    "wof:name":"Jma Mechanical",
    "wof:placetype":"venue"
},
  "geometry": {"coordinates":[-81.91453300000001,26.739495],"type":"Point"}
}