{
  "type": "Feature",
  "properties": {
    "iso:country":"US",
    "sg:address":"10510 NW 28th Ct",
    "sg:city":"Miami",
    "sg:classifiers":[
        {
            "category":"Building & Trades",
            "subcategory":"Construction",
            "type":"Services"
        }
    ],
    "sg:phone":"+1 786 356 0798",
    "sg:postcode":"33147",
    "sg:province":"FL",
    "sg:tags":[
        "plastering",
        "contractor"
    ],
    "wof:name":"J G Plastering Corporation",
    "wof:placetype":"venue"
},
  "geometry": {"coordinates":[-80.244389,25.86996],"type":"Point"}
}