{
  "type": "Feature",
  "properties": {
    "addr:full":"475 NW Raymond Ln Port Saint Lucie FL 34983",
    "addr:housenumber":"475",
    "addr:postcode":"34983",
    "addr:street":"Nw Raymond Ln",
    "iso:country":"US",
    "sg:address":"475 NW Raymond Ln",
    "sg:city":"Port Saint Lucie",
    "sg:classifiers":[
        {
            "category":"Local Transit",
            "type":"Transportation"
        }
    ],
    "sg:phone":"+1 772 871 1522",
    "sg:postcode":"34983",
    "sg:province":"FL",
    "sg:tags":[
        "passenger"
    ],
    "wof:name":"A & G Limousine",
    "wof:placetype":"venue"
},
  "geometry": {"coordinates":[-80.352221,27.327463],"type":"Point"}
}