{
  "type": "Feature",
  "properties": {
    "iso:country":"US",
    "sg:address":"4230 Ortega Blvd",
    "sg:city":"Jacksonville",
    "sg:classifiers":[
        {
            "category":"Real Estate",
            "subcategory":"Real Estate Agent",
            "type":"Services"
        }
    ],
    "sg:phone":"+1 904 388 4000",
    "sg:postcode":"32210",
    "sg:province":"FL",
    "sg:website":"www.atkinson-knight.com",
    "wof:name":"Atkinson & Knight Realty Group",
    "wof:placetype":"venue"
},
  "geometry": {"coordinates":[-81.702904,30.271537],"type":"Point"}
}