{
  "type": "Feature",
  "properties": {
    "addr:full":"961 Armstrong Blvd Kissimmee FL 34741",
    "addr:housenumber":"961",
    "addr:postcode":"34741",
    "addr:street":"Armstrong Blvd",
    "iso:country":"US",
    "sg:address":"961 Armstrong Blvd",
    "sg:city":"Kissimmee",
    "sg:phone":"+1 321 402 5955",
    "sg:postcode":"34741",
    "sg:province":"FL",
    "wof:name":"Best Price Mobility",
    "wof:placetype":"venue"
},
  "geometry": {"coordinates":[-81.44119600000001,28.299204],"type":"Point"}
}