{
  "type": "Feature",
  "properties": {
    "addr:full":"6235 S Suncoast Blvd Homosassa FL 34446",
    "addr:housenumber":"6235",
    "addr:postcode":"34446",
    "addr:street":"S Suncoast Blvd",
    "iso:country":"US",
    "sg:address":"6235 S Suncoast Blvd",
    "sg:city":"Homosassa",
    "sg:classifiers":[
        {
            "category":"Shopping",
            "subcategory":"Hobbies, Toys, & Games",
            "type":"Retail Goods"
        }
    ],
    "sg:phone":"+1 352 621 5511",
    "sg:postcode":"34446",
    "sg:province":"FL",
    "sg:tags":[
        "craft",
        "supply"
    ],
    "wof:name":"All About Craft Creations",
    "wof:placetype":"venue"
},
  "geometry": {"coordinates":[-82.553173,28.768828],"type":"Point"}
}