{
  "type": "Feature",
  "properties": {
    "iso:country":"US",
    "sg:address":"2301 W Sample Rd",
    "sg:city":"Pompano Beach",
    "sg:classifiers":[
        {
            "category":"Health Services",
            "subcategory":"Doctor",
            "type":"Services"
        }
    ],
    "sg:phone":"+1 954 975 4661",
    "sg:postcode":"33073",
    "sg:province":"FL",
    "sg:tags":[
        "physician",
        "surgeon"
    ],
    "wof:name":"Sunlife Ob/Gyn Svc Of Pompano",
    "wof:placetype":"venue"
},
  "geometry": {"coordinates":[-80.155897,26.27457],"type":"Point"}
}