{
  "type": "Feature",
  "properties": {
    "addr:full":"6967 Phillips Hwy Jacksonville FL 32216",
    "addr:housenumber":"6967",
    "addr:postcode":"32216",
    "addr:street":"Phillips Hwy",
    "iso:country":"US",
    "sg:address":"6967 Phillips Hwy",
    "sg:city":"Jacksonville",
    "sg:classifiers":[
        {
            "category":"Banks & Credit Unions",
            "subcategory":"Bank",
            "type":"Services"
        }
    ],
    "sg:phone":"+1 904 296 1800",
    "sg:postcode":"32216",
    "sg:province":"FL",
    "sg:tags":[
        "loan",
        "real estate"
    ],
    "wof:name":"Professional Processing Of Fl",
    "wof:placetype":"venue"
},
  "geometry": {"coordinates":[-81.60229200000001,30.246759],"type":"Point"}
}