{
  "type": "Feature",
  "properties": {
    "iso:country":"US",
    "sg:address":"2320 SW 60th Way",
    "sg:city":"Miramar",
    "sg:classifiers":[
        {
            "category":"Shopping",
            "subcategory":"Clothing, Apparel, & Fashions",
            "type":"Retail Goods"
        }
    ],
    "sg:phone":"+1 954 966 1567",
    "sg:postcode":"33023",
    "sg:province":"FL",
    "sg:tags":[
        "handbag"
    ],
    "wof:name":"P And R Handbags Inc",
    "wof:placetype":"venue"
},
  "geometry": {"coordinates":[-80.20849800000001,25.989644],"type":"Point"}
}