{
  "type": "Feature",
  "properties": {
    "addr:full":"719 S Martin Luther King Blvd Daytona Beach FL 32114",
    "addr:housenumber":"719",
    "addr:postcode":"32114",
    "addr:street":"S Martin Luther King Blvd",
    "iso:country":"US",
    "sg:address":"719 S Martin Luther King Blvd",
    "sg:city":"Daytona Beach",
    "sg:classifiers":[
        {
            "category":"Food & Beverages",
            "subcategory":"Groceries & Convenience Stores",
            "type":"Retail Goods"
        }
    ],
    "sg:phone":"+1 386 947 8181",
    "sg:postcode":"32114",
    "sg:province":"FL",
    "wof:name":"Low Budget",
    "wof:placetype":"venue"
},
  "geometry": {"coordinates":[-81.022091,29.196712],"type":"Point"}
}