{
  "type": "Feature",
  "properties": {
    "iso:country":"US",
    "sg:address":"25 SE 2nd Ave",
    "sg:city":"Miami",
    "sg:classifiers":[
        {
            "category":"Arts & Performance",
            "subcategory":"Arts Center",
            "type":"Entertainment"
        }
    ],
    "sg:phone":"+1 305 374 2444",
    "sg:postcode":"33131",
    "sg:province":"FL",
    "sg:tags":[
        "performing"
    ],
    "wof:name":"Gusman Center For the Performing Arts",
    "wof:placetype":"venue"
},
  "geometry": {"coordinates":[-80.19009,25.774052],"type":"Point"}
}