{
  "type": "Feature",
  "properties": {
    "iso:country":"US",
    "sg:address":"3599 W Main St",
    "sg:city":"Leesburg",
    "sg:classifiers":[
        {
            "category":"Building & Trades",
            "subcategory":"Cleaning & Sanitation",
            "type":"Services"
        }
    ],
    "sg:phone":"+1 352 728 1668",
    "sg:postcode":"34748",
    "sg:province":"FL",
    "sg:tags":[
        "fabric",
        "fire",
        "damage",
        "water",
        "protection",
        "restoration",
        "furniture"
    ],
    "sg:website":"http://www.ccss.com",
    "wof:name":"Stanley Steemer",
    "wof:placetype":"venue"
},
  "geometry": {"coordinates":[-81.900238,28.81338],"type":"Point"}
}