{
  "type": "Feature",
  "properties": {
    "iso:country":"US",
    "sg:address":"2132 Rocway Dr",
    "sg:city":"Melbourne",
    "sg:classifiers":[
        {
            "category":"Building & Trades",
            "subcategory":"Construction",
            "type":"Services"
        }
    ],
    "sg:phone":"+1 321 508 4165",
    "sg:postcode":"32935",
    "sg:province":"FL",
    "sg:tags":[
        "tile",
        "dealer"
    ],
    "wof:name":"Robert Sardina Tile Contractor",
    "wof:placetype":"venue"
},
  "geometry": {"coordinates":[-80.65420399999999,28.179242],"type":"Point"}
}