{
  "type": "Feature",
  "properties": {
    "addr:full":"13326 US Hwy 19 Hudson FL 34667",
    "addr:housenumber":"13326",
    "addr:postcode":"34667",
    "addr:street":"Us Hwy 19",
    "iso:country":"US",
    "sg:address":"13326 US Hwy 19",
    "sg:city":"Hudson",
    "sg:classifiers":[
        {
            "category":"Wholesale",
            "subcategory":"Seafood",
            "type":"Manufacturing & Wholesale Goods"
        }
    ],
    "sg:phone":"+1 727 868 4044",
    "sg:postcode":"34667",
    "sg:province":"FL",
    "wof:name":"Whitney & Son Seafoods",
    "wof:placetype":"venue"
},
  "geometry": {"coordinates":[-82.69911,28.350782],"type":"Point"}
}