{
  "type": "Feature",
  "properties": {
    "iso:country":"US",
    "sg:address":"2086 E Edgewood Dr",
    "sg:city":"Lakeland",
    "sg:classifiers":[
        {
            "category":"Professional",
            "subcategory":"Engineering",
            "type":"Services"
        }
    ],
    "sg:phone":"+1 863 669 1327",
    "sg:postcode":"33803",
    "sg:province":"FL",
    "sg:tags":[
        "engineer"
    ],
    "sg:website":"www.hitech-sol-lakeland-fl.com",
    "wof:name":"Hitech Solutions Inc",
    "wof:placetype":"venue"
},
  "geometry": {"coordinates":[-81.92111300000001,28.013313],"type":"Point"}
}