{
  "type": "Feature",
  "properties": {
    "iso:country":"US",
    "sg:address":"12 N Charles Richard Beall Blvd",
    "sg:city":"Debary",
    "sg:classifiers":[
        {
            "category":"Sports & Exercise",
            "subcategory":"Gym",
            "type":"Entertainment"
        }
    ],
    "sg:phone":"+1 386 668 8830",
    "sg:postcode":"32713",
    "sg:province":"FL",
    "sg:tags":[
        "trainer"
    ],
    "sg:website":"www.curves.com",
    "wof:name":"Curves For Women",
    "wof:placetype":"venue"
},
  "geometry": {"coordinates":[-81.306539,28.891651],"type":"Point"}
}