{
  "type": "Feature",
  "properties": {
    "iso:country":"US",
    "sg:address":"26910 Nicki J Ct",
    "sg:city":"Bonita Springs",
    "sg:classifiers":[
        {
            "category":"Real Estate",
            "subcategory":"Real Estate Agent",
            "type":"Services"
        }
    ],
    "sg:phone":"+1 239 949 2969",
    "sg:postcode":"34135",
    "sg:province":"FL",
    "wof:name":"Northern Realty Trust",
    "wof:placetype":"venue"
},
  "geometry": {"coordinates":[-81.75844499999999,26.346446],"type":"Point"}
}