{
  "type": "Feature",
  "properties": {
    "iso:country":"US",
    "sg:address":"600 Fir Ct",
    "sg:city":"Deland",
    "sg:classifiers":[
        {
            "category":"Wholesale",
            "subcategory":"Construction Materials",
            "type":"Manufacturing & Wholesale Goods"
        }
    ],
    "sg:phone":"+1 386 822 9952",
    "sg:postcode":"32714",
    "sg:province":"FL",
    "sg:tags":[
        "concrete",
        "product"
    ],
    "wof:name":"Concrete Impressions-Florida",
    "wof:placetype":"venue"
},
  "geometry": {"coordinates":[-81.413684,28.652711],"type":"Point"}
}