{
  "type": "Feature",
  "properties": {
    "iso:country":"US",
    "sg:address":"2937 Edgewood Ave W",
    "sg:city":"Jacksonville",
    "sg:classifiers":[
        {
            "category":"Building & Trades",
            "subcategory":"Construction",
            "type":"Services"
        }
    ],
    "sg:phone":"+1 904 768 7976",
    "sg:postcode":"32209",
    "sg:province":"FL",
    "sg:tags":[
        "concrete",
        "restoration",
        "repair",
        "cleaning",
        "contractor"
    ],
    "wof:name":"E L Wilson Concrete Contractor",
    "wof:placetype":"venue"
},
  "geometry": {"coordinates":[-81.713476,30.3752],"type":"Point"}
}