{
  "type": "Feature",
  "properties": {
    "addr:full":"12062 SW 117th Ter Miami FL 33186",
    "addr:housenumber":"12062",
    "addr:postcode":"33186",
    "addr:street":"Sw 117Th Ter",
    "iso:country":"US",
    "sg:address":"12062 SW 117th Ter",
    "sg:city":"Miami",
    "sg:classifiers":[
        {
            "category":"Insurance",
            "subcategory":"Insurance Agent",
            "type":"Services"
        }
    ],
    "sg:phone":"+1 305 387 2977",
    "sg:postcode":"33186",
    "sg:province":"FL",
    "wof:name":"D A Saltzman & Associates",
    "wof:placetype":"venue"
},
  "geometry": {"coordinates":[-80.390057,25.659469],"type":"Point"}
}