{
  "type": "Feature",
  "properties": {
    "iso:country":"US",
    "sg:address":"1000 SW 98th Ter",
    "sg:city":"Hollywood",
    "sg:classifiers":[
        {
            "category":"Building & Trades",
            "subcategory":"Construction",
            "type":"Services"
        }
    ],
    "sg:phone":"+1 954 437 8946",
    "sg:postcode":"33025",
    "sg:province":"FL",
    "sg:tags":[
        "concrete",
        "contractor"
    ],
    "wof:name":"Victor Pumo",
    "wof:placetype":"venue"
},
  "geometry": {"coordinates":[-80.275992,25.998957],"type":"Point"}
}