{
  "type": "Feature",
  "properties": {
    "addr:full":"880 SW 12th Ave Pompano Beach FL 33069",
    "addr:housenumber":"880",
    "addr:postcode":"33069",
    "addr:street":"Sw 12Th Ave",
    "iso:country":"US",
    "sg:address":"880 SW 12th Ave",
    "sg:city":"Pompano Beach",
    "sg:classifiers":[
        {
            "category":"Building & Trades",
            "subcategory":"Construction",
            "type":"Services"
        }
    ],
    "sg:phone":"+1 954 946 3033",
    "sg:postcode":"33069",
    "sg:province":"FL",
    "sg:tags":[
        "masonry",
        "contractor"
    ],
    "sg:website":"www.pompanomasonry.com",
    "wof:name":"Pompano Masonry",
    "wof:placetype":"venue"
},
  "geometry": {"coordinates":[-80.138543,26.218106],"type":"Point"}
}