{
  "type": "Feature",
  "properties": {
    "iso:country":"US",
    "sg:address":"1205 Cape Coral Pkwy E",
    "sg:city":"Cape Coral",
    "sg:classifiers":[
        {
            "category":"Banks & Credit Unions",
            "subcategory":"Bank",
            "type":"Services"
        },
        {
            "category":"Banks & Credit Unions",
            "subcategory":"Financial Services",
            "type":"Services"
        }
    ],
    "sg:phone":"+1 239 549 6600",
    "sg:postcode":"33904",
    "sg:province":"FL",
    "sg:tags":[
        "broker",
        "mortgage"
    ],
    "sg:website":"www.libertybankflorida.com",
    "wof:name":"Liberty Bank",
    "wof:placetype":"venue"
},
  "geometry": {"coordinates":[-81.94992000000001,26.562827],"type":"Point"}
}