{
  "type": "Feature",
  "properties": {
    "iso:country":"US",
    "sg:address":"4179 NW 88th Ave",
    "sg:city":"Sunrise",
    "sg:classifiers":[
        {
            "category":"Health Services",
            "subcategory":"Doctor",
            "type":"Services"
        }
    ],
    "sg:phone":"+1 954 746 5803",
    "sg:postcode":"33351",
    "sg:province":"FL",
    "sg:tags":[
        "medicine",
        "physician",
        "surgeon",
        "internal",
        "surgeons"
    ],
    "wof:name":"Khan, Husman Md Pa Facp",
    "wof:placetype":"venue"
},
  "geometry": {"coordinates":[-80.268227,26.184225],"type":"Point"}
}