{
  "type": "Feature",
  "properties": {
    "iso:country":"US",
    "sg:address":"614 Orange Dr",
    "sg:city":"Altamonte Spgs",
    "sg:classifiers":[
        {
            "category":"Professional",
            "subcategory":"Computer Services",
            "type":"Services"
        }
    ],
    "sg:phone":"+1 407 339 1919",
    "sg:postcode":"32701",
    "sg:province":"FL",
    "sg:tags":[
        "repair"
    ],
    "wof:name":"Tom Cable",
    "wof:placetype":"venue"
},
  "geometry": {"coordinates":[-81.373746,28.66071],"type":"Point"}
}