{
  "type": "Feature",
  "properties": {
    "iso:country":"US",
    "sg:address":"9960 N Central Park Blvd",
    "sg:city":"Boca Raton",
    "sg:classifiers":[
        {
            "category":"Health Services",
            "subcategory":"Doctor",
            "type":"Services"
        }
    ],
    "sg:phone":"+1 561 487 0660",
    "sg:postcode":"33428",
    "sg:province":"FL",
    "sg:tags":[
        "physician",
        "surgeon"
    ],
    "wof:name":"South Florida Nephrology Assoc",
    "wof:placetype":"venue"
},
  "geometry": {"coordinates":[-80.202229,26.357175],"type":"Point"}
}