{
  "type": "Feature",
  "properties": {
    "addr:full":"9401 Biscayne Blvd Miami Shores FL 33138",
    "addr:housenumber":"9401",
    "addr:postcode":"33138",
    "addr:street":"Biscayne Blvd",
    "iso:country":"US",
    "sg:address":"9401 Biscayne Blvd",
    "sg:city":"Miami Shores",
    "sg:classifiers":[
        {
            "category":"Organizations",
            "subcategory":"Non-profit Organization",
            "type":"Services"
        }
    ],
    "sg:phone":"+1 305 754 2444",
    "sg:postcode":"33138",
    "sg:province":"FL",
    "sg:tags":[
        "service/non-profit",
        "community"
    ],
    "wof:name":"Catholic Charities of the Archdiocese of Miami Inc",
    "wof:placetype":"venue"
},
  "geometry": {"coordinates":[-80.18119799999999,25.8617],"type":"Point"}
}