{
  "type": "Feature",
  "properties": {
    "iso:country":"US",
    "sg:address":"5400 Royal Palm Blvd",
    "sg:city":"Pompano Beach",
    "sg:classifiers":[
        {
            "category":"Home & Garden",
            "subcategory":"Carpets & Floor Coverings",
            "type":"Retail Goods"
        }
    ],
    "sg:phone":"+1 954 973 4990",
    "sg:postcode":"33063",
    "sg:province":"FL",
    "sg:tags":[
        "dealer",
        "rug"
    ],
    "wof:name":"Carpets By Mr Jason",
    "wof:placetype":"venue"
},
  "geometry": {"coordinates":[-80.197504,26.25444],"type":"Point"}
}