{
  "type": "Feature",
  "properties": {
    "addr:full":"1625 W 49th St Hialeah FL 33012",
    "addr:housenumber":"1625",
    "addr:postcode":"33012",
    "addr:street":"W 49Th St",
    "iso:country":"US",
    "sg:address":"1625 W 49th St",
    "sg:city":"Hialeah",
    "sg:classifiers":[
        {
            "category":"Shopping",
            "subcategory":"Optical Goods",
            "type":"Retail Goods"
        }
    ],
    "sg:phone":"+1 305 364 3879",
    "sg:postcode":"33012",
    "sg:province":"FL",
    "sg:tags":[
        "store"
    ],
    "wof:name":"Sears Optical",
    "wof:placetype":"venue"
},
  "geometry": {"coordinates":[-80.317262,25.866663],"type":"Point"}
}