{
  "type": "Feature",
  "properties": {
    "iso:country":"US",
    "sg:address":"2660 W 2nd Ave",
    "sg:city":"Hialeah",
    "sg:classifiers":[
        {
            "category":"Manufacturing",
            "subcategory":"Metals",
            "type":"Manufacturing & Wholesale Goods"
        }
    ],
    "sg:phone":"+1 305 884 2489",
    "sg:postcode":"33010",
    "sg:province":"FL",
    "sg:tags":[
        "stampings",
        "mfg"
    ],
    "wof:name":"Los Vlencianos Lunch Box Bldrs",
    "wof:placetype":"venue"
},
  "geometry": {"coordinates":[-80.286287,25.845803],"type":"Point"}
}