{
  "type": "Feature",
  "properties": {
    "addr:full":"12941 Parkline Dr Fort Myers FL 33913",
    "addr:housenumber":"12941",
    "addr:postcode":"33913",
    "addr:street":"Parkline Dr",
    "iso:country":"US",
    "sg:address":"12941 Parkline Dr",
    "sg:city":"Fort Myers",
    "sg:classifiers":[
        {
            "category":"Professional",
            "subcategory":"Business Services",
            "type":"Services"
        }
    ],
    "sg:phone":"+1 800 485 9726",
    "sg:postcode":"33913",
    "sg:province":"FL",
    "wof:name":"Executive Leadership Solutions",
    "wof:placetype":"venue"
},
  "geometry": {"coordinates":[-81.74293299999999,26.572551],"type":"Point"}
}