{
  "type": "Feature",
  "properties": {
    "iso:country":"US",
    "sg:address":"1345 Thomasville Rd",
    "sg:city":"Tallahassee",
    "sg:classifiers":[
        {
            "category":"Professional",
            "subcategory":"Art Services",
            "type":"Services"
        }
    ],
    "sg:phone":"+1 850 224 9934",
    "sg:postcode":"32303",
    "sg:province":"FL",
    "sg:tags":[
        "artist"
    ],
    "wof:name":"Artist Series",
    "wof:placetype":"venue"
},
  "geometry": {"coordinates":[-84.277501,30.456263],"type":"Point"}
}