{
  "type": "Feature",
  "properties": {
    "iso:country":"US",
    "sg:address":"16600 SW 82nd Ave",
    "sg:city":"Miami",
    "sg:classifiers":[
        {
            "category":"Building & Trades",
            "subcategory":"Landscaping Services",
            "type":"Services"
        }
    ],
    "sg:phone":"+1 305 238 5172",
    "sg:postcode":"33157",
    "sg:province":"FL",
    "sg:tags":[
        "landscape"
    ],
    "wof:name":"Todd Hackett Landscaping",
    "wof:placetype":"venue"
},
  "geometry": {"coordinates":[-80.324535,25.614587],"type":"Point"}
}