{
  "type": "Feature",
  "properties": {
    "addr:full":"1800 34th St S St Petersburg FL 33711",
    "addr:housenumber":"1800",
    "addr:postcode":"33711",
    "addr:street":"34Th St S",
    "iso:country":"US",
    "sg:address":"1800 34th St S",
    "sg:city":"St Petersburg",
    "sg:classifiers":[
        {
            "category":"Autos & Motor Vehicles",
            "subcategory":"Fuel & Gas Station",
            "type":"Retail Goods"
        }
    ],
    "sg:phone":"+1 727 327 1692",
    "sg:postcode":"33711",
    "sg:province":"FL",
    "sg:tags":[
        "station",
        "gasoline",
        "oil"
    ],
    "wof:name":"U S Shell",
    "wof:placetype":"venue"
},
  "geometry": {"coordinates":[-82.67935799999999,27.751085],"type":"Point"}
}