{
  "type": "Feature",
  "properties": {
    "iso:country":"US",
    "sg:address":"9930 Grace Dr",
    "sg:city":"Port Richey",
    "sg:classifiers":[
        {
            "category":"Utilities",
            "subcategory":"Cable",
            "type":"Services"
        }
    ],
    "sg:phone":"+1 956 821 5809",
    "sg:postcode":"34668",
    "sg:province":"FL",
    "sg:tags":[
        "television"
    ],
    "wof:name":"Pablo E Flores",
    "wof:placetype":"venue"
},
  "geometry": {"coordinates":[-82.712137,28.300998],"type":"Point"}
}