{
  "type": "Feature",
  "properties": {
    "addr:full":"219 SW 40th St Cape Coral FL 33914",
    "addr:housenumber":"219",
    "addr:postcode":"33914",
    "addr:street":"Sw 40Th St",
    "iso:country":"US",
    "sg:address":"219 SW 40th St",
    "sg:city":"Cape Coral",
    "sg:classifiers":[
        {
            "category":"Banks & Credit Unions",
            "subcategory":"Financial Services",
            "type":"Services"
        }
    ],
    "sg:phone":"+1 239 549 6758",
    "sg:postcode":"33914",
    "sg:province":"FL",
    "sg:tags":[
        "investor"
    ],
    "wof:name":"K&S Investments of SW FL Inc",
    "wof:placetype":"venue"
},
  "geometry": {"coordinates":[-81.980762,26.577681],"type":"Point"}
}