{
  "type": "Feature",
  "properties": {
    "addr:full":"8327 E Missionwood Dr Hollywood FL 33025",
    "addr:housenumber":"8327",
    "addr:postcode":"33025",
    "addr:street":"E Missionwood Dr",
    "iso:country":"US",
    "sg:address":"8327 E Missionwood Dr",
    "sg:city":"Hollywood",
    "sg:classifiers":[
        {
            "category":"Wholesale",
            "subcategory":"Hardware",
            "type":"Manufacturing & Wholesale Goods"
        }
    ],
    "sg:phone":"+1 954 447 9176",
    "sg:postcode":"33025",
    "sg:province":"FL",
    "wof:name":"Caribe Puchasing Inc",
    "wof:placetype":"venue"
},
  "geometry": {"coordinates":[-80.25195100000001,25.982521],"type":"Point"}
}