{
  "type": "Feature",
  "properties": {
    "addr:full":"9339 Arbolita Way Jacksonville FL 32256",
    "addr:housenumber":"9339",
    "addr:postcode":"32256",
    "addr:street":"Arbolita Way",
    "iso:country":"US",
    "sg:address":"9339 Arbolita Way",
    "sg:city":"Jacksonville",
    "sg:classifiers":[
        {
            "category":"Real Estate",
            "subcategory":"Real Estate Agent",
            "type":"Services"
        }
    ],
    "sg:phone":"+1 904 737 4931",
    "sg:postcode":"32256",
    "sg:province":"FL",
    "wof:name":"Cochran Real Estate Services",
    "wof:placetype":"venue"
},
  "geometry": {"coordinates":[-81.563962,30.224605],"type":"Point"}
}