{
  "type": "Feature",
  "properties": {
    "addr:full":"410 W 17th St Apopka FL 32703",
    "addr:housenumber":"410",
    "addr:postcode":"32703",
    "addr:street":"W 17Th St",
    "iso:country":"US",
    "sg:address":"410 W 17th St",
    "sg:city":"Apopka",
    "sg:classifiers":[
        {
            "category":"Banks & Credit Unions",
            "subcategory":"Bank",
            "type":"Services"
        }
    ],
    "sg:phone":"+1 770 798 1648",
    "sg:postcode":"32703",
    "sg:province":"FL",
    "sg:tags":[
        "loan",
        "insurance",
        "mortgage",
        "travel"
    ],
    "wof:name":"Mj4 Multi-Services",
    "wof:placetype":"venue"
},
  "geometry": {"coordinates":[-81.519413,28.658433],"type":"Point"}
}