{
  "type": "Feature",
  "properties": {
    "addr:full":"7920 NW 170th Ter Hialeah FL 33015",
    "addr:housenumber":"7920",
    "addr:postcode":"33015",
    "addr:street":"Nw 170Th Ter",
    "iso:country":"US",
    "sg:address":"7920 NW 170th Ter",
    "sg:city":"Hialeah",
    "sg:classifiers":[
        {
            "category":"Building & Trades",
            "subcategory":"Cleaning & Sanitation",
            "type":"Services"
        }
    ],
    "sg:phone":"+1 305 822 6388",
    "sg:postcode":"33015",
    "sg:province":"FL",
    "sg:tags":[
        "maintenance"
    ],
    "wof:name":"United Maintenance Contracting",
    "wof:placetype":"venue"
},
  "geometry": {"coordinates":[-80.332593,25.928484],"type":"Point"}
}