{
  "type": "Feature",
  "properties": {
    "addr:full":"750 Washburn Rd Melbourne FL 32934",
    "addr:housenumber":"750",
    "addr:postcode":"32934",
    "addr:street":"Washburn Rd",
    "iso:country":"US",
    "sg:address":"750 Washburn Rd",
    "sg:city":"Melbourne",
    "sg:classifiers":[
        {
            "category":"Wholesale",
            "subcategory":"Construction Materials",
            "type":"Manufacturing & Wholesale Goods"
        },
        {
            "category":"Building & Trades",
            "subcategory":"Construction",
            "type":"Services"
        }
    ],
    "sg:phone":"+1 321 259 9976",
    "sg:postcode":"32934",
    "sg:province":"FL",
    "sg:tags":[
        "granite",
        "contractor"
    ],
    "wof:name":"Superior Granite & Marble Inc",
    "wof:placetype":"venue"
},
  "geometry": {"coordinates":[-80.68661299999999,28.119063],"type":"Point"}
}