{
  "type": "Feature",
  "properties": {
    "iso:country":"US",
    "sg:address":"15993 SW 303rd Ter",
    "sg:city":"Homestead",
    "sg:classifiers":[
        {
            "category":"Autos & Motor Vehicles",
            "subcategory":"Auto Supplies",
            "type":"Retail Goods"
        }
    ],
    "sg:phone":"+1 305 246 5837",
    "sg:postcode":"33033",
    "sg:province":"FL",
    "sg:tags":[
        "tire"
    ],
    "wof:name":"J.C. Tires Disposal",
    "wof:placetype":"venue"
},
  "geometry": {"coordinates":[-80.45078700000001,25.485421],"type":"Point"}
}