{
  "type": "Feature",
  "properties": {
    "iso:country":"US",
    "sg:address":"6917 Presidents Dr",
    "sg:city":"Orlando",
    "sg:classifiers":[
        {
            "category":"Freight",
            "type":"Transportation"
        }
    ],
    "sg:phone":"+1 407 295 0636",
    "sg:postcode":"32809",
    "sg:province":"FL",
    "sg:tags":[
        "operator",
        "mover",
        "local",
        "trucking"
    ],
    "sg:website":"www.beltmann.com",
    "wof:name":"Beltmann Group",
    "wof:placetype":"venue"
},
  "geometry": {"coordinates":[-81.422538,28.463589],"type":"Point"}
}