{
  "type": "Feature",
  "properties": {
    "iso:country":"US",
    "sg:address":"1605 Kingsley Rd",
    "sg:city":"Jupiter",
    "sg:classifiers":[
        {
            "category":"Building & Trades",
            "subcategory":"Construction",
            "type":"Services"
        }
    ],
    "sg:phone":"+1 561 743 1363",
    "sg:postcode":"33469",
    "sg:province":"FL",
    "sg:tags":[
        "carpentry",
        "contractor"
    ],
    "wof:name":"K G Carpentry",
    "wof:placetype":"venue"
},
  "geometry": {"coordinates":[-80.093598,26.953805],"type":"Point"}
}