{
  "type": "Feature",
  "properties": {
    "addr:full":"701 NE 12th St Homestead FL 33030",
    "addr:housenumber":"701",
    "addr:postcode":"33030",
    "addr:street":"Ne 12Th St",
    "iso:country":"US",
    "sg:address":"701 NE 12th St",
    "sg:city":"Homestead",
    "sg:classifiers":[
        {
            "category":"Building & Trades",
            "subcategory":"Landscaping Services",
            "type":"Services"
        }
    ],
    "sg:phone":"+1 305 248 8910",
    "sg:postcode":"33030",
    "sg:province":"FL",
    "sg:tags":[
        "landscape"
    ],
    "wof:name":"American Bobcat & Landscaping",
    "wof:placetype":"venue"
},
  "geometry": {"coordinates":[-80.46817,25.481899],"type":"Point"}
}