{
  "type": "Feature",
  "properties": {
    "addr:full":"3701 Franklin Rd Graceville FL 32440",
    "addr:housenumber":"3701",
    "addr:postcode":"32440",
    "addr:street":"Franklin Rd",
    "iso:country":"US",
    "sg:address":"3701 Franklin Rd",
    "sg:city":"Graceville",
    "sg:classifiers":[
        {
            "category":"Building & Trades",
            "subcategory":"Construction",
            "type":"Services"
        }
    ],
    "sg:phone":"+1 850 263 6995",
    "sg:postcode":"32440",
    "sg:province":"FL",
    "sg:tags":[
        "wallcoverings-installation",
        "wallpaper",
        "painting",
        "contractor"
    ],
    "wof:name":"Solid Coat Painting",
    "wof:placetype":"venue"
},
  "geometry": {"coordinates":[-85.579852,30.979524],"type":"Point"}
}