{
  "type": "Feature",
  "properties": {
    "addr:full":"4515 N Pine Island Rd Fort Lauderdale FL 33351",
    "addr:housenumber":"4515",
    "addr:postcode":"33351",
    "addr:street":"N Pine Island Rd",
    "iso:country":"US",
    "sg:address":"4515 N Pine Island Rd",
    "sg:city":"Fort Lauderdale",
    "sg:classifiers":[
        {
            "category":"Restaurant",
            "type":"Food & Drink"
        }
    ],
    "sg:menulink":"http://www.allmenus.com/fl/plantation/87300-little-caesars-pizza/menu/",
    "sg:phone":"+1 954 749 1920",
    "sg:postcode":"33351",
    "sg:province":"FL",
    "sg:tags":[
        "american",
        "pizza"
    ],
    "wof:name":"Little Caesar's Pizza",
    "wof:placetype":"venue"
},
  "geometry": {"coordinates":[-80.267951,26.180761],"type":"Point"}
}