{
  "type": "Feature",
  "properties": {
    "iso:country":"US",
    "sg:address":"10549 N Florida Ave",
    "sg:city":"Tampa",
    "sg:classifiers":[
        {
            "category":"Health Services",
            "subcategory":"Doctor",
            "type":"Services"
        }
    ],
    "sg:phone":"+1 813 935 3129",
    "sg:postcode":"33612",
    "sg:province":"FL",
    "sg:tags":[
        "dentist"
    ],
    "wof:name":"Ralph W Fortson DDS",
    "wof:placetype":"venue"
},
  "geometry": {"coordinates":[-82.45934200000001,28.046416],"type":"Point"}
}