{
  "type": "Feature",
  "properties": {
    "iso:country":"US",
    "sg:address":"713 N Main St",
    "sg:city":"Atmore",
    "sg:classifiers":[
        {
            "category":"Building & Trades",
            "subcategory":"Pest Control",
            "type":"Services"
        }
    ],
    "sg:phone":"+1 251 446 7880",
    "sg:postcode":"36502",
    "sg:province":"FL",
    "wof:name":"U Do It Pest Control",
    "wof:placetype":"venue"
},
  "geometry": {"coordinates":[-87.493191,31.035366],"type":"Point"}
}