{
  "type": "Feature",
  "properties": {
    "iso:country":"US",
    "sg:address":"5844 N Orange Blossom Trl",
    "sg:city":"Orlando",
    "sg:classifiers":[
        {
            "category":"Health Services",
            "subcategory":"Doctor",
            "type":"Services"
        }
    ],
    "sg:phone":"+1 407 578 2002",
    "sg:postcode":"32810",
    "sg:province":"FL",
    "wof:name":"Wasserman Lewis MD",
    "wof:placetype":"venue"
},
  "geometry": {"coordinates":[-81.429604,28.6112],"type":"Point"}
}