{
  "type": "Feature",
  "properties": {
    "iso:country":"US",
    "sg:address":"116 Dunlawton Ave",
    "sg:city":"Port Orange",
    "sg:classifiers":[
        {
            "category":"Shopping",
            "subcategory":"Clothing, Apparel, & Fashions",
            "type":"Retail Goods"
        }
    ],
    "sg:phone":"+1 386 756 0504",
    "sg:postcode":"32127",
    "sg:province":"FL",
    "sg:tags":[
        "swimwear",
        "accessory"
    ],
    "wof:name":"Bikini Co Swimwear Specialists",
    "wof:placetype":"venue"
},
  "geometry": {"coordinates":[-80.98706,29.143175],"type":"Point"}
}