{
  "type": "Feature",
  "properties": {
    "addr:full":"5700 Lake Worth Rd Greenacres FL 33463",
    "addr:housenumber":"5700",
    "addr:postcode":"33463",
    "addr:street":"Lake Worth Rd",
    "iso:country":"US",
    "sg:address":"5700 Lake Worth Rd",
    "sg:city":"Greenacres",
    "sg:classifiers":[
        {
            "category":"Professional",
            "subcategory":"Accounting & Tax Preparation",
            "type":"Services"
        }
    ],
    "sg:phone":"+1 561 533 1300",
    "sg:postcode":"33463",
    "sg:province":"FL",
    "sg:tags":[
        "accountant"
    ],
    "wof:name":"Ira Elblonk & Assoc",
    "wof:placetype":"venue"
},
  "geometry": {"coordinates":[-80.13831399999999,26.619142],"type":"Point"}
}