{
  "type": "Feature",
  "properties": {
    "addr:full":"1280 SW Briarwood Dr Port St Lucie FL 34986",
    "addr:housenumber":"1280",
    "addr:postcode":"34986",
    "addr:street":"Sw Briarwood Dr",
    "iso:country":"US",
    "sg:address":"1280 SW Briarwood Dr",
    "sg:city":"Port St Lucie",
    "sg:classifiers":[
        {
            "category":"Manufacturing",
            "subcategory":"Tools & Machinery",
            "type":"Manufacturing & Wholesale Goods"
        }
    ],
    "sg:phone":"+1 772 785 5106",
    "sg:postcode":"34986",
    "sg:province":"FL",
    "sg:tags":[
        "machine",
        "shop"
    ],
    "wof:name":"Premiere Machining",
    "wof:placetype":"venue"
},
  "geometry": {"coordinates":[-80.386343,27.297695],"type":"Point"}
}