{
  "type": "Feature",
  "properties": {
    "iso:country":"US",
    "sg:address":"121 Winterberry Ave",
    "sg:city":"Wildwood",
    "sg:classifiers":[
        {
            "category":"Manufacturing",
            "subcategory":"Rubber & Plastics",
            "type":"Manufacturing & Wholesale Goods"
        },
        {
            "category":"Shopping",
            "type":"Retail Goods"
        }
    ],
    "sg:phone":"+1 352 748 3720",
    "sg:postcode":"34785",
    "sg:province":"FL",
    "sg:tags":[
        "equipment",
        "clothing",
        "safety",
        "clothing-wholesale",
        "manufacturer"
    ],
    "wof:name":"Road Safety Various Product",
    "wof:placetype":"venue"
},
  "geometry": {"coordinates":[-81.985361,28.807734],"type":"Point"}
}