{
  "type": "Feature",
  "properties": {
    "iso:country":"US",
    "sg:address":"2737 NW 116th Ter",
    "sg:city":"Pompano Beach",
    "sg:classifiers":[
        {
            "category":"Manufacturing",
            "subcategory":"Tools & Machinery",
            "type":"Manufacturing & Wholesale Goods"
        }
    ],
    "sg:phone":"+1 954 752 7740",
    "sg:postcode":"33065",
    "sg:province":"FL",
    "sg:tags":[
        "consulting",
        "computer",
        "build"
    ],
    "wof:name":"T C G Consulting Inc",
    "wof:placetype":"venue"
},
  "geometry": {"coordinates":[-80.281128,26.26483],"type":"Point"}
}