{
  "type": "Feature",
  "properties": {
    "iso:country":"US",
    "sg:address":"8116 Pompano St",
    "sg:city":"Navarre",
    "sg:classifiers":[
        {
            "category":"Professional",
            "subcategory":"Art Services",
            "type":"Services"
        }
    ],
    "sg:phone":"+1 850 939 8805",
    "sg:postcode":"32566",
    "sg:province":"FL",
    "sg:tags":[
        "designer",
        "display",
        "producer"
    ],
    "wof:name":"Trellises Design",
    "wof:placetype":"venue"
},
  "geometry": {"coordinates":[-86.882831,30.399945],"type":"Point"}
}