{
  "type": "Feature",
  "properties": {
    "iso:country":"US",
    "sg:address":"200 Broadway",
    "sg:city":"West Palm Beach",
    "sg:classifiers":[
        {
            "category":"Utilities",
            "subcategory":"Electric",
            "type":"Services"
        }
    ],
    "sg:phone":"+1 561 845 3143",
    "sg:postcode":"33404",
    "sg:province":"FL",
    "wof:name":"FPL",
    "wof:placetype":"venue"
},
  "geometry": {"coordinates":[-80.055109,26.766],"type":"Point"}
}