{
  "type": "Feature",
  "properties": {
    "addr:full":"850 Park Ave West Palm Beach FL 33403",
    "addr:housenumber":"850",
    "addr:postcode":"33403",
    "addr:street":"Park Ave",
    "iso:country":"US",
    "sg:address":"850 Park Ave",
    "sg:city":"West Palm Beach",
    "sg:classifiers":[
        {
            "category":"Professional",
            "type":"Services"
        }
    ],
    "sg:phone":"+1 561 840 2185",
    "sg:postcode":"33403",
    "sg:province":"FL",
    "sg:tags":[
        "establishment"
    ],
    "wof:name":"O'Donuts",
    "wof:placetype":"venue"
},
  "geometry": {"coordinates":[-80.06963399999999,26.798647],"type":"Point"}
}