{
  "type": "Feature",
  "properties": {
    "addr:full":"901 NW 17th St Miami FL 33136",
    "addr:housenumber":"901",
    "addr:postcode":"33136",
    "addr:street":"Nw 17Th St",
    "iso:country":"US",
    "sg:address":"901 NW 17th St",
    "sg:city":"Miami",
    "sg:classifiers":[
        {
            "category":"Restaurant",
            "type":"Food & Drink"
        }
    ],
    "sg:menulink":"http://www.allmenus.com/fl/miami/46246-subway/menu/",
    "sg:phone":"+1 305 324 8862",
    "sg:postcode":"33136",
    "sg:province":"FL",
    "sg:tags":[
        "american",
        "sandwich"
    ],
    "wof:name":"Subway",
    "wof:placetype":"venue"
},
  "geometry": {"coordinates":[-80.210307,25.791362],"type":"Point"}
}