{
  "type": "Feature",
  "properties": {
    "iso:country":"US",
    "sg:address":"7951 Bird Rd",
    "sg:city":"Miami",
    "sg:classifiers":[
        {
            "category":"Education",
            "subcategory":"Special Training",
            "type":"Public Place"
        }
    ],
    "sg:phone":"+1 305 262 3201",
    "sg:postcode":"33155",
    "sg:province":"FL",
    "sg:tags":[
        "tutoring"
    ],
    "wof:name":"Almeyda Learning Center",
    "wof:placetype":"venue"
},
  "geometry": {"coordinates":[-80.32409699999999,25.733299],"type":"Point"}
}