{
  "type": "Feature",
  "properties": {
    "addr:full":"410 Broad St Brooksville FL 34604",
    "addr:housenumber":"410",
    "addr:postcode":"34604",
    "addr:street":"Broad St",
    "iso:country":"US",
    "sg:address":"410 Broad St",
    "sg:city":"Brooksville",
    "sg:classifiers":[
        {
            "category":"Real Estate",
            "subcategory":"Real Estate Agent",
            "type":"Services"
        }
    ],
    "sg:phone":"+1 813 996 7600",
    "sg:postcode":"34604",
    "sg:province":"FL",
    "wof:name":"Fred W Holland Realty",
    "wof:placetype":"venue"
},
  "geometry": {"coordinates":[-82.456897,28.442517],"type":"Point"}
}