{
  "type": "Feature",
  "properties": {
    "iso:country":"US",
    "sg:address":"54517 Vontz Cir",
    "sg:city":"Callahan",
    "sg:classifiers":[
        {
            "category":"Taxi",
            "type":"Transportation"
        },
        {
            "category":"Government",
            "subcategory":"Post Office",
            "type":"Public Place"
        }
    ],
    "sg:phone":"+1 904 879 1107",
    "sg:postcode":"32011",
    "sg:province":"FL",
    "sg:tags":[
        "delivery",
        "courier"
    ],
    "wof:name":"Big O Delivery",
    "wof:placetype":"venue"
},
  "geometry": {"coordinates":[-81.76827,30.537529],"type":"Point"}
}