{
  "type": "Feature",
  "properties": {
    "addr:full":"3024 SW 27th Ave Miami FL 33133",
    "addr:housenumber":"3024",
    "addr:postcode":"33133",
    "addr:street":"Sw 27Th Ave",
    "iso:country":"US",
    "sg:address":"3024 SW 27th Ave",
    "sg:city":"Miami",
    "sg:classifiers":[
        {
            "category":"Restaurant",
            "type":"Food & Drink"
        }
    ],
    "sg:phone":"+1 305 461 9190",
    "sg:postcode":"33133",
    "sg:province":"FL",
    "sg:tags":[
        "pizza"
    ],
    "wof:name":"Slice & Ice",
    "wof:placetype":"venue"
},
  "geometry": {"coordinates":[-80.237995,25.735113],"type":"Point"}
}