{
  "type": "Feature",
  "properties": {
    "addr:full":"829 Barton Blvd Rockledge FL 32955",
    "addr:housenumber":"829",
    "addr:postcode":"32955",
    "addr:street":"Barton Blvd",
    "iso:country":"US",
    "sg:address":"829 Barton Blvd",
    "sg:city":"Rockledge",
    "sg:classifiers":[
        {
            "category":"Restaurant",
            "type":"Food & Drink"
        }
    ],
    "sg:phone":"+1 321 504 4423",
    "sg:postcode":"32955",
    "sg:province":"FL",
    "sg:tags":[
        "parlor",
        "ice",
        "cream"
    ],
    "wof:name":"Burnham's Lighthouse",
    "wof:placetype":"venue"
},
  "geometry": {"coordinates":[-80.73798600000001,28.330752],"type":"Point"}
}