{
  "type": "Feature",
  "properties": {
    "addr:full":"3470 NW 4th Ct Fort Lauderdale FL 33311",
    "addr:housenumber":"3470",
    "addr:postcode":"33311",
    "addr:street":"Nw 4Th Ct",
    "iso:country":"US",
    "sg:address":"3470 NW 4th Ct",
    "sg:city":"Fort Lauderdale",
    "sg:classifiers":[
        {
            "category":"Building & Trades",
            "subcategory":"Landscaping Services",
            "type":"Services"
        }
    ],
    "sg:phone":"+1 954 791 6850",
    "sg:postcode":"33311",
    "sg:province":"FL",
    "sg:tags":[
        "counseling",
        "planning",
        "landscape"
    ],
    "wof:name":"Jj Landscaping",
    "wof:placetype":"venue"
},
  "geometry": {"coordinates":[-80.192272,26.125861],"type":"Point"}
}