{
  "type": "Feature",
  "properties": {
    "addr:full":"721 San Bruno Ave Miami FL 33143",
    "addr:housenumber":"721",
    "addr:postcode":"33143",
    "addr:street":"San Bruno Ave",
    "iso:country":"US",
    "sg:address":"721 San Bruno Ave",
    "sg:city":"Miami",
    "sg:classifiers":[
        {
            "category":"Professional",
            "subcategory":"Lawyer & Legal Services",
            "type":"Services"
        }
    ],
    "sg:phone":"+1 305 667 5049",
    "sg:postcode":"33143",
    "sg:province":"FL",
    "wof:name":"Glass James E Atty - CLOSED",
    "wof:placetype":"venue"
},
  "geometry": {"coordinates":[-80.267799,25.694201],"type":"Point"}
}