{
  "type": "Feature",
  "properties": {
    "addr:full":"4500 S Florida Ave Inverness FL 34450",
    "addr:housenumber":"4500",
    "addr:postcode":"34450",
    "addr:street":"S Florida Ave",
    "iso:country":"US",
    "sg:address":"4500 S Florida Ave",
    "sg:city":"Inverness",
    "sg:classifiers":[
        {
            "category":"Autos & Motor Vehicles",
            "subcategory":"Boat Sales",
            "type":"Retail Goods"
        }
    ],
    "sg:phone":"+1 352 344 1065",
    "sg:postcode":"34450",
    "sg:province":"FL",
    "sg:tags":[
        "canoe"
    ],
    "wof:name":"John Canoe Sales Purdin",
    "wof:placetype":"venue"
},
  "geometry": {"coordinates":[-82.305954,28.795935],"type":"Point"}
}