{
  "type": "Feature",
  "properties": {
    "iso:country":"US",
    "sg:address":"17035 SW 144th Pl",
    "sg:city":"Miami",
    "sg:classifiers":[
        {
            "category":"Communications",
            "subcategory":"Film & Video Production",
            "type":"Services"
        }
    ],
    "sg:phone":"+1 305 256 4115",
    "sg:postcode":"33177",
    "sg:province":"FL",
    "sg:tags":[
        "tv",
        "radio",
        "services-commercial",
        "companies-film"
    ],
    "wof:name":"Tambora Productions Inc",
    "wof:placetype":"venue"
},
  "geometry": {"coordinates":[-80.42697099999999,25.608374],"type":"Point"}
}