{
  "type": "Feature",
  "properties": {
    "addr:full":"7975 NW 155th St Hialeah FL 33016",
    "addr:housenumber":"7975",
    "addr:postcode":"33016",
    "addr:street":"Nw 155Th St",
    "iso:country":"US",
    "sg:address":"7975 NW 155th St",
    "sg:city":"Hialeah",
    "sg:classifiers":[
        {
            "category":"Professional",
            "subcategory":"Lawyer & Legal Services",
            "type":"Services"
        }
    ],
    "sg:phone":"+1 305 821 5419",
    "sg:postcode":"33016",
    "sg:province":"FL",
    "sg:tags":[
        "law"
    ],
    "wof:name":"Anon Wlter A Law Offces of PA",
    "wof:placetype":"venue"
},
  "geometry": {"coordinates":[-80.333096,25.9146],"type":"Point"}
}