{
  "type": "Feature",
  "properties": {
    "addr:full":"1259 NW 34th Ave Miami FL 33125",
    "addr:housenumber":"1259",
    "addr:postcode":"33125",
    "addr:street":"Nw 34Th Ave",
    "iso:country":"US",
    "sg:address":"1259 NW 34th Ave",
    "sg:city":"Miami",
    "sg:classifiers":[
        {
            "category":"Shopping",
            "subcategory":"Florist",
            "type":"Retail Goods"
        }
    ],
    "sg:phone":"+1 786 295 3396",
    "sg:postcode":"33125",
    "sg:province":"FL",
    "wof:name":"Omar Wholesale Flowers",
    "wof:placetype":"venue"
},
  "geometry": {"coordinates":[-80.25134300000001,25.784651],"type":"Point"}
}