{
  "type": "Feature",
  "properties": {
    "iso:country":"US",
    "sg:address":"130 Hollywood Blvd SW",
    "sg:city":"Fort Walton Beach",
    "sg:classifiers":[
        {
            "category":"Autos & Motor Vehicles",
            "subcategory":"Automobile Sales",
            "type":"Retail Goods"
        }
    ],
    "sg:phone":"+1 850 243 3171",
    "sg:postcode":"32548",
    "sg:province":"FL",
    "wof:name":"Lee Isuzu/Volkswagen/Subaru",
    "wof:placetype":"venue"
},
  "geometry": {"coordinates":[-86.627195,30.412744],"type":"Point"}
}