{
  "type": "Feature",
  "properties": {
    "iso:country":"US",
    "sg:address":"3700 Creighton Rd",
    "sg:city":"Pensacola",
    "sg:classifiers":[
        {
            "category":"Professional",
            "subcategory":"Accounting & Tax Preparation",
            "type":"Services"
        }
    ],
    "sg:phone":"+1 850 484 2900",
    "sg:postcode":"32504",
    "sg:province":"FL",
    "sg:tags":[
        "accountant"
    ],
    "wof:name":"Allen J Lambert CPA",
    "wof:placetype":"venue"
},
  "geometry": {"coordinates":[-87.17599800000001,30.499613],"type":"Point"}
}