{
  "type": "Feature",
  "properties": {
    "addr:full":"790 27th Ave Vero Beach FL 32968",
    "addr:housenumber":"790",
    "addr:postcode":"32968",
    "addr:street":"27Th Ave",
    "iso:country":"US",
    "sg:address":"790 27th Ave",
    "sg:city":"Vero Beach",
    "sg:classifiers":[
        {
            "category":"Education",
            "subcategory":"School",
            "type":"Public Place"
        }
    ],
    "sg:phone":"+1 772 569 1095",
    "sg:postcode":"32968",
    "sg:province":"FL",
    "sg:website":"www.glendale-baptist.org",
    "wof:name":"Glendale Baptist Church",
    "wof:placetype":"venue"
},
  "geometry": {"coordinates":[-80.413819,27.616251],"type":"Point"}
}