{
  "type": "Feature",
  "properties": {
    "iso:country":"US",
    "sg:address":"1411 NE 32nd St",
    "sg:city":"Pompano Beach",
    "sg:classifiers":[
        {
            "category":"Building & Trades",
            "subcategory":"Construction",
            "type":"Services"
        }
    ],
    "sg:phone":"+1 954 782 0845",
    "sg:postcode":"33064",
    "sg:province":"FL",
    "sg:tags":[
        "hanging",
        "contractor"
    ],
    "wof:name":"Paint Rite Painting",
    "wof:placetype":"venue"
},
  "geometry": {"coordinates":[-80.103146,26.270375],"type":"Point"}
}