{
  "type": "Feature",
  "properties": {
    "iso:country":"US",
    "sg:address":"2319 Tamiami Trl",
    "sg:city":"Venice",
    "sg:classifiers":[
        {
            "category":"Home & Garden",
            "subcategory":"Hardware",
            "type":"Retail Goods"
        }
    ],
    "sg:phone":"+1 941 922 8570",
    "sg:postcode":"34293",
    "sg:province":"FL",
    "sg:tags":[
        "water",
        "equipment",
        "pumping",
        "purification"
    ],
    "wof:name":"Water Pro",
    "wof:placetype":"venue"
},
  "geometry": {"coordinates":[-82.407308,27.050732],"type":"Point"}
}