{
  "type": "Feature",
  "properties": {
    "iso:country":"US",
    "sg:address":"230 SW 30th St",
    "sg:city":"Fort Lauderdale",
    "sg:classifiers":[
        {
            "category":"Professional",
            "type":"Services"
        }
    ],
    "sg:phone":"+1 954 525 2693",
    "sg:postcode":"33315",
    "sg:province":"FL",
    "sg:tags":[
        "establishment"
    ],
    "wof:name":"Berry Curtiss Inc",
    "wof:placetype":"venue"
},
  "geometry": {"coordinates":[-80.144019,26.087071],"type":"Point"}
}