{
  "type": "Feature",
  "properties": {
    "addr:full":"1708 6th St SE Winter Haven FL 33880",
    "addr:housenumber":"1708",
    "addr:postcode":"33880",
    "addr:street":"6Th St Se",
    "iso:country":"US",
    "sg:address":"1708 6th St SE",
    "sg:city":"Winter Haven",
    "sg:classifiers":[
        {
            "category":"Restaurant",
            "type":"Food & Drink"
        }
    ],
    "sg:phone":"+1 863 297 9840",
    "sg:postcode":"33880",
    "sg:province":"FL",
    "wof:name":"Tom's Steak & Seafood Rstrnts",
    "wof:placetype":"venue"
},
  "geometry": {"coordinates":[-81.71897199999999,28.000978],"type":"Point"}
}