{
  "type": "Feature",
  "properties": {
    "addr:full":"13773 Collina Ct Estero FL 33928",
    "addr:postcode":"13773;33928",
    "addr:street":"Collina Ct",
    "iso:country":"US",
    "sg:address":"13773 Collina Ct",
    "sg:city":"Estero",
    "sg:classifiers":[
        {
            "category":"Health Services",
            "subcategory":"Dentist",
            "type":"Services"
        }
    ],
    "sg:phone":"+1 239 948 9776",
    "sg:postcode":"33928",
    "sg:province":"FL",
    "wof:name":"Dest Assoc",
    "wof:placetype":"venue"
},
  "geometry": {"coordinates":[-81.725846,26.444599],"type":"Point"}
}