{
  "type": "Feature",
  "properties": {
    "iso:country":"US",
    "sg:address":"8131 San Felipe Ct",
    "sg:city":"Port Richey",
    "sg:classifiers":[
        {
            "category":"Organizations",
            "subcategory":"Community Association",
            "type":"Services"
        }
    ],
    "sg:phone":"+1 727 868 2175",
    "sg:postcode":"34668",
    "sg:province":"FL",
    "wof:name":"Masons",
    "wof:placetype":"venue"
},
  "geometry": {"coordinates":[-82.67959999999999,28.313354],"type":"Point"}
}