{
  "type": "Feature",
  "properties": {
    "iso:country":"US",
    "sg:address":"1817 Ponce de Leon Blvd",
    "sg:city":"Miami",
    "sg:classifiers":[
        {
            "category":"Retail",
            "subcategory":"Laundry & Dry Cleaning",
            "type":"Services"
        }
    ],
    "sg:phone":"+1 305 461 4010",
    "sg:postcode":"33134",
    "sg:province":"FL",
    "sg:tags":[
        "alteration"
    ],
    "wof:name":"Geovanni Alterations & Tlr Sp",
    "wof:placetype":"venue"
},
  "geometry": {"coordinates":[-80.258758,25.755316],"type":"Point"}
}