{
  "type": "Feature",
  "properties": {
    "iso:country":"US",
    "sg:address":"821 Cypress Ln",
    "sg:city":"Hallandale",
    "sg:classifiers":[
        {
            "category":"Freight",
            "type":"Transportation"
        }
    ],
    "sg:phone":"+1 954 455 9848",
    "sg:postcode":"33009",
    "sg:province":"FL",
    "sg:tags":[
        "operator",
        "trucking"
    ],
    "wof:name":"Carl Barnes Trucking",
    "wof:placetype":"venue"
},
  "geometry": {"coordinates":[-80.1601,25.980646],"type":"Point"}
}