{
  "type": "Feature",
  "properties": {
    "iso:country":"US",
    "sg:address":"6386 NW 97th Ave",
    "sg:city":"Doral",
    "sg:classifiers":[
        {
            "category":"Wholesale",
            "subcategory":"Medical Equipment & Supplies",
            "type":"Manufacturing & Wholesale Goods"
        }
    ],
    "sg:phone":"+1 305 551 6623",
    "sg:postcode":"33172",
    "sg:province":"FL",
    "sg:tags":[
        "physician",
        "surgeon"
    ],
    "wof:name":"D & B Medical Supply",
    "wof:placetype":"venue"
},
  "geometry": {"coordinates":[-80.354175,25.83173],"type":"Point"}
}