{
  "type": "Feature",
  "properties": {
    "addr:full":"3677 S Orlando Dr Sanford FL 32773",
    "addr:housenumber":"3677",
    "addr:postcode":"32773",
    "addr:street":"S Orlando Dr",
    "iso:country":"US",
    "sg:address":"3677 S Orlando Dr",
    "sg:city":"Sanford",
    "sg:classifiers":[
        {
            "category":"Restaurant",
            "type":"Food & Drink"
        }
    ],
    "sg:phone":"+1 407 302 1998",
    "sg:postcode":"32773",
    "sg:province":"FL",
    "sg:tags":[
        "eating"
    ],
    "wof:name":"Hong Kong Restaurant",
    "wof:placetype":"venue"
},
  "geometry": {"coordinates":[-81.285301,28.7603],"type":"Point"}
}