{
  "type": "Feature",
  "properties": {
    "iso:country":"US",
    "sg:address":"190 Post Ct",
    "sg:city":"Marco Island",
    "sg:classifiers":[
        {
            "category":"Banks & Credit Unions",
            "subcategory":"Financial Services",
            "type":"Services"
        }
    ],
    "sg:phone":"+1 239 389 1778",
    "sg:postcode":"34145",
    "sg:province":"FL",
    "sg:tags":[
        "investor"
    ],
    "wof:name":"Royal Marko Investments Inc",
    "wof:placetype":"venue"
},
  "geometry": {"coordinates":[-81.725037,25.940367],"type":"Point"}
}