{
  "type": "Feature",
  "properties": {
    "addr:full":"5042 N Woodcrest Dr Winter Park FL 32792",
    "addr:housenumber":"5042",
    "addr:postcode":"32792",
    "addr:street":"N Woodcrest Dr",
    "iso:country":"US",
    "sg:address":"5042 N Woodcrest Dr",
    "sg:city":"Winter Park",
    "sg:classifiers":[
        {
            "category":"Building & Trades",
            "subcategory":"Construction",
            "type":"Services"
        }
    ],
    "sg:phone":"+1 407 673 2205",
    "sg:postcode":"32792",
    "sg:province":"FL",
    "sg:tags":[
        "painter"
    ],
    "wof:name":"Glen Dettmer Painting",
    "wof:placetype":"venue"
},
  "geometry": {"coordinates":[-81.28859199999999,28.611554],"type":"Point"}
}