{
  "type": "Feature",
  "properties": {
    "addr:full":"15501 SW 86th Ave Miami FL 33157",
    "addr:housenumber":"15501",
    "addr:postcode":"33157",
    "addr:street":"Sw 86Th Ave",
    "iso:country":"US",
    "sg:address":"15501 SW 86th Ave",
    "sg:city":"Miami",
    "sg:classifiers":[
        {
            "category":"Professional",
            "subcategory":"Secretarial Services",
            "type":"Services"
        }
    ],
    "sg:phone":"+1 305 255 1883",
    "sg:postcode":"33157",
    "sg:province":"FL",
    "sg:tags":[
        "reporting"
    ],
    "wof:name":"Papersmith Reporting",
    "wof:placetype":"venue"
},
  "geometry": {"coordinates":[-80.332476,25.628397],"type":"Point"}
}