{
  "type": "Feature",
  "properties": {
    "addr:full":"350 Laurie Rd West Palm Beach FL 33405",
    "addr:housenumber":"350",
    "addr:postcode":"33405",
    "addr:street":"Laurie Rd",
    "iso:country":"US",
    "sg:address":"350 Laurie Rd",
    "sg:city":"West Palm Beach",
    "sg:classifiers":[
        {
            "category":"Shopping",
            "subcategory":"Catalog Store",
            "type":"Retail Goods"
        }
    ],
    "sg:phone":"+1 561 585 7112",
    "sg:postcode":"33405",
    "sg:province":"FL",
    "sg:tags":[
        "mail",
        "order"
    ],
    "wof:name":"Green Gables Gift Shop",
    "wof:placetype":"venue"
},
  "geometry": {"coordinates":[-80.05415600000001,26.649586],"type":"Point"}
}