{
  "type": "Feature",
  "properties": {
    "iso:country":"US",
    "sg:address":"8370 Juniper Rd",
    "sg:city":"Ocala",
    "sg:classifiers":[
        {
            "category":"Farming",
            "subcategory":"Farm",
            "type":"Manufacturing & Wholesale Goods"
        }
    ],
    "sg:phone":"+1 352 867 8079",
    "sg:postcode":"34480",
    "sg:province":"FL",
    "sg:tags":[
        "crop",
        "general"
    ],
    "wof:name":"Tucked Away Farm LLC",
    "wof:placetype":"venue"
},
  "geometry": {"coordinates":[-82.072549,29.104628],"type":"Point"}
}