{
  "type": "Feature",
  "properties": {
    "iso:country":"US",
    "sg:address":"1218 SW 132nd Ct",
    "sg:city":"Miami",
    "sg:classifiers":[
        {
            "category":"Building & Trades",
            "subcategory":"Electrical",
            "type":"Services"
        }
    ],
    "sg:phone":"+1 305 969 0062",
    "sg:postcode":"33184",
    "sg:province":"FL",
    "sg:tags":[
        "electrical",
        "contractor"
    ],
    "wof:name":"Allstar Electric",
    "wof:placetype":"venue"
},
  "geometry": {"coordinates":[-80.412128,25.755031],"type":"Point"}
}