{
  "type": "Feature",
  "properties": {
    "addr:full":"950 NW 18th Ave Homestead FL 33030",
    "addr:housenumber":"950",
    "addr:postcode":"33030",
    "addr:street":"Nw 18Th Ave",
    "iso:country":"US",
    "sg:address":"950 NW 18th Ave",
    "sg:city":"Homestead",
    "sg:classifiers":[
        {
            "category":"Building & Trades",
            "subcategory":"Construction",
            "type":"Services"
        }
    ],
    "sg:phone":"+1 305 248 9099",
    "sg:postcode":"33030",
    "sg:province":"FL",
    "sg:tags":[
        "hanging",
        "contractor"
    ],
    "wof:name":"Reagan Painting Corp",
    "wof:placetype":"venue"
},
  "geometry": {"coordinates":[-80.4978,25.477964],"type":"Point"}
}