{
  "type": "Feature",
  "properties": {
    "addr:full":"59 Keyton Dr Daytona Beach FL 32124",
    "addr:housenumber":"59",
    "addr:postcode":"32124",
    "addr:street":"Keyton Dr",
    "iso:country":"US",
    "sg:address":"59 Keyton Dr",
    "sg:city":"Daytona Beach",
    "sg:classifiers":[
        {
            "category":"Government",
            "subcategory":"Police Station",
            "type":"Public Place"
        }
    ],
    "sg:phone":"+1 386 248 1770",
    "sg:postcode":"32124",
    "sg:province":"FL",
    "sg:tags":[
        "communications",
        "dept"
    ],
    "wof:name":"Sheriffs Communications Admin",
    "wof:placetype":"venue"
},
  "geometry": {"coordinates":[-81.14418499999999,29.139538],"type":"Point"}
}