{
  "type": "Feature",
  "properties": {
    "iso:country":"US",
    "sg:address":"4666 Ashton Rd",
    "sg:city":"Sarasota",
    "sg:classifiers":[
        {
            "category":"Home & Garden",
            "subcategory":"Home Furnishings",
            "type":"Retail Goods"
        }
    ],
    "sg:phone":"+1 941 923 7622",
    "sg:postcode":"34233",
    "sg:province":"FL",
    "wof:name":"Coastal Window Treatments",
    "wof:placetype":"venue"
},
  "geometry": {"coordinates":[-82.47964,27.276493],"type":"Point"}
}