{
  "type": "Feature",
  "properties": {
    "addr:full":"1255 Pine Island Rd Merritt Island FL 32953",
    "addr:housenumber":"1255",
    "addr:postcode":"32953",
    "addr:street":"Pine Island Rd",
    "iso:country":"US",
    "sg:address":"1255 Pine Island Rd",
    "sg:city":"Merritt Island",
    "sg:classifiers":[
        {
            "category":"Manufacturing",
            "subcategory":"Textiles",
            "type":"Manufacturing & Wholesale Goods"
        }
    ],
    "sg:phone":"+1 321 456 5557",
    "sg:postcode":"32953",
    "sg:province":"FL",
    "sg:tags":[
        "print",
        "sport",
        "shirt",
        "t"
    ],
    "wof:name":"Space Coast T-Shirts",
    "wof:placetype":"venue"
},
  "geometry": {"coordinates":[-80.714022,28.492605],"type":"Point"}
}