{
  "type": "Feature",
  "properties": {
    "iso:country":"US",
    "sg:address":"5451 NW 15th St",
    "sg:city":"Margate",
    "sg:classifiers":[
        {
            "category":"Organizations",
            "subcategory":"Community Association",
            "type":"Services"
        }
    ],
    "sg:phone":"+1 954 971 9690",
    "sg:postcode":"33063",
    "sg:province":"FL",
    "sg:tags":[
        "fraternal"
    ],
    "wof:name":"Elks Lodge",
    "wof:placetype":"venue"
},
  "geometry": {"coordinates":[-80.199336,26.248673],"type":"Point"}
}