{
  "type": "Feature",
  "properties": {
    "addr:full":"3513 Apalachee Pkwy Tallahassee FL 32311",
    "addr:housenumber":"3513",
    "addr:postcode":"32311",
    "addr:street":"Apalachee Pkwy",
    "iso:country":"US",
    "sg:address":"3513 Apalachee Pkwy",
    "sg:city":"Tallahassee",
    "sg:classifiers":[
        {
            "category":"Banks & Credit Unions",
            "subcategory":"Bank",
            "type":"Services"
        }
    ],
    "sg:phone":"+1 850 942 3100",
    "sg:postcode":"32311",
    "sg:province":"FL",
    "wof:name":"Capital City Bank",
    "wof:placetype":"venue"
},
  "geometry": {"coordinates":[-84.21635499999999,30.428068],"type":"Point"}
}