{
  "type": "Feature",
  "properties": {
    "iso:country":"US",
    "sg:address":"304 Alabama Ave",
    "sg:city":"Saint Cloud",
    "sg:classifiers":[
        {
            "category":"Retail",
            "subcategory":"Auto Repair",
            "type":"Services"
        }
    ],
    "sg:phone":"+1 407 498 5030",
    "sg:postcode":"34769",
    "sg:province":"FL",
    "sg:tags":[
        "general"
    ],
    "wof:name":"Real Ponies",
    "wof:placetype":"venue"
},
  "geometry": {"coordinates":[-81.29592599999999,28.255058],"type":"Point"}
}