{
  "type": "Feature",
  "properties": {
    "iso:country":"US",
    "sg:address":"2950 Aloma Ave Ste 406",
    "sg:city":"Winter Park",
    "sg:classifiers":[
        {
            "category":"Shopping",
            "subcategory":"Clothing, Apparel, & Fashions",
            "type":"Retail Goods"
        },
        {
            "category":"Shopping",
            "subcategory":"Used Merchandise",
            "type":"Retail Goods"
        }
    ],
    "sg:phone":"+1 407 692 0504",
    "sg:postcode":"32792",
    "sg:province":"FL",
    "sg:tags":[
        "vintage",
        "clothing",
        "accessory",
        "consignment",
        "women's"
    ],
    "sg:website":"www.MetroChicInc.com",
    "wof:name":"MetroChic, Inc",
    "wof:placetype":"venue"
},
  "geometry": {"coordinates":[-81.31181100000001,28.602424],"type":"Point"}
}