{
  "type": "Feature",
  "properties": {
    "iso:country":"US",
    "sg:address":"5000 SW 75th Ave",
    "sg:city":"Miami",
    "sg:classifiers":[
        {
            "category":"Insurance",
            "subcategory":"Insurance Agent",
            "type":"Services"
        },
        {
            "category":"Insurance",
            "subcategory":"Hazard Insurance",
            "type":"Services"
        },
        {
            "category":"Insurance",
            "subcategory":"Health Insurance",
            "type":"Services"
        }
    ],
    "sg:phone":"+1 305 663 6270",
    "sg:postcode":"33155",
    "sg:province":"FL",
    "sg:tags":[
        "business",
        "auto",
        "commercial",
        "benefit",
        "employee"
    ],
    "sg:website":"http://www.autoinsurance-fl.com/",
    "wof:name":"Keyes Insurance",
    "wof:placetype":"venue"
},
  "geometry": {"coordinates":[-80.316742,25.72385],"type":"Point"}
}