{
  "type": "Feature",
  "properties": {
    "iso:country":"US",
    "sg:address":"9412 Fox Chapel Ln",
    "sg:city":"Spring Hill",
    "sg:classifiers":[
        {
            "category":"Education",
            "subcategory":"School",
            "type":"Public Place"
        }
    ],
    "sg:phone":"+1 352 797 7025",
    "sg:postcode":"34606",
    "sg:province":"FL",
    "wof:name":"Fox Chapel Middle School",
    "wof:placetype":"venue"
},
  "geometry": {"coordinates":[-82.563661,28.511893],"type":"Point"}
}