{
  "type": "Feature",
  "properties": {
    "addr:full":"6337 SW 40th St Miami FL 33155",
    "addr:housenumber":"6337",
    "addr:postcode":"33155",
    "addr:street":"Sw 40Th St",
    "iso:country":"US",
    "sg:address":"6337 SW 40th St",
    "sg:city":"Miami",
    "sg:classifiers":[
        {
            "category":"Professional",
            "subcategory":"Advertising",
            "type":"Services"
        }
    ],
    "sg:phone":"+1 305 661 5007",
    "sg:postcode":"33155",
    "sg:province":"FL",
    "sg:tags":[
        "counselor"
    ],
    "wof:name":"P & C Advertising",
    "wof:placetype":"venue"
},
  "geometry": {"coordinates":[-80.29810999999999,25.73367],"type":"Point"}
}