{
  "type": "Feature",
  "properties": {
    "iso:country":"US",
    "sg:address":"1777 Tamiami Trl",
    "sg:city":"Port Charlotte",
    "sg:classifiers":[
        {
            "category":"Banks & Credit Unions",
            "subcategory":"Bank",
            "type":"Services"
        }
    ],
    "sg:phone":"+1 941 764 1300",
    "sg:postcode":"33948",
    "sg:province":"FL",
    "sg:tags":[
        "financing",
        "broker",
        "mortgage"
    ],
    "wof:name":"Oak Street Mortgage LLC",
    "wof:placetype":"venue"
},
  "geometry": {"coordinates":[-82.13638899999999,27.008276],"type":"Point"}
}