{
  "type": "Feature",
  "properties": {
    "addr:full":"1725 Central Florida Pkwy Orlando FL 32837",
    "addr:housenumber":"1725",
    "addr:postcode":"32837",
    "addr:street":"Central Florida Pkwy",
    "iso:country":"US",
    "sg:address":"1725 Central Florida Pkwy",
    "sg:city":"Orlando",
    "sg:classifiers":[
        {
            "category":"Wholesale",
            "subcategory":"Vending Machines",
            "type":"Manufacturing & Wholesale Goods"
        }
    ],
    "sg:phone":"+1 407 857 1825",
    "sg:postcode":"32837",
    "sg:province":"FL",
    "wof:name":"Merch-A-Vend Co",
    "wof:placetype":"venue"
},
  "geometry": {"coordinates":[-81.39235499999999,28.406668],"type":"Point"}
}