{
  "type": "Feature",
  "properties": {
    "iso:country":"US",
    "sg:address":"4555 Anson Ln",
    "sg:city":"Orlando",
    "sg:classifiers":[
        {
            "category":"Manufacturing",
            "subcategory":"Printing",
            "type":"Manufacturing & Wholesale Goods"
        }
    ],
    "sg:phone":"+1 407 894 5777",
    "sg:postcode":"32814",
    "sg:province":"FL",
    "sg:tags":[
        "publisher"
    ],
    "wof:name":"Vnu Business Media",
    "wof:placetype":"venue"
},
  "geometry": {"coordinates":[-81.329747,28.562719],"type":"Point"}
}