{
  "type": "Feature",
  "properties": {
    "addr:full":"6268 Brookshire Ter Fort Myers FL 33912",
    "addr:housenumber":"6268",
    "addr:postcode":"33912",
    "addr:street":"Brookshire Ter",
    "iso:country":"US",
    "sg:address":"6268 Brookshire Ter",
    "sg:city":"Fort Myers",
    "sg:classifiers":[
        {
            "category":"Building & Trades",
            "subcategory":"Cleaning & Sanitation",
            "type":"Services"
        }
    ],
    "sg:phone":"+1 239 433 3305",
    "sg:postcode":"33912",
    "sg:province":"FL",
    "sg:tags":[
        "carpet"
    ],
    "wof:name":"Dial's Carpet Cleaning",
    "wof:placetype":"venue"
},
  "geometry": {"coordinates":[-81.84899900000001,26.5147],"type":"Point"}
}