{
  "type": "Feature",
  "properties": {
    "addr:full":"1075 S US Hwy 1 Vero Beach FL 32960",
    "addr:housenumber":"1075",
    "addr:postcode":"32960",
    "addr:street":"S Us Hwy 1",
    "iso:country":"US",
    "sg:address":"1075 S US Hwy 1",
    "sg:city":"Vero Beach",
    "sg:classifiers":[
        {
            "category":"Autos & Motor Vehicles",
            "subcategory":"Automobile Sales",
            "type":"Retail Goods"
        }
    ],
    "sg:phone":"+1 772 569 8000",
    "sg:postcode":"32960",
    "sg:province":"FL",
    "sg:tags":[
        "dealer"
    ],
    "sg:website":"www.verobeachtoyota.com",
    "wof:name":"Toyota Of Vero Beach",
    "wof:placetype":"venue"
},
  "geometry": {"coordinates":[-80.376975,27.583],"type":"Point"}
}