{
  "type": "Feature",
  "properties": {
    "addr:full":"1460 NW Britt Rd Stuart FL 34994",
    "addr:housenumber":"1460",
    "addr:postcode":"34994",
    "addr:street":"Nw Britt Rd",
    "iso:country":"US",
    "sg:address":"1460 NW Britt Rd",
    "sg:city":"Stuart",
    "sg:classifiers":[
        {
            "category":"Organizations",
            "subcategory":"Religious Organization",
            "type":"Services"
        }
    ],
    "sg:phone":"+1 772 692 3147",
    "sg:postcode":"34994",
    "sg:province":"FL",
    "sg:tags":[
        "church"
    ],
    "wof:name":"Jehovah's Witnesses",
    "wof:placetype":"venue"
},
  "geometry": {"coordinates":[-80.27394200000001,27.234861],"type":"Point"}
}