{
  "type": "Feature",
  "properties": {
    "iso:country":"US",
    "sg:address":"8201 S Tamiami Trl",
    "sg:city":"Sarasota",
    "sg:classifiers":[
        {
            "category":"Home & Garden",
            "subcategory":"Home Furnishings",
            "type":"Retail Goods"
        }
    ],
    "sg:phone":"+1 941 925 7187",
    "sg:postcode":"34238",
    "sg:province":"FL",
    "sg:tags":[
        "furniture"
    ],
    "wof:name":"Bombay Company 609",
    "wof:placetype":"venue"
},
  "geometry": {"coordinates":[-82.49618100000001,27.232028],"type":"Point"}
}