{
  "type": "Feature",
  "properties": {
    "iso:country":"US",
    "sg:address":"4720 SE 145th St",
    "sg:city":"Summerfield",
    "sg:classifiers":[
        {
            "category":"Professional",
            "type":"Services"
        }
    ],
    "sg:phone":"+1 352 347 5197",
    "sg:postcode":"34491",
    "sg:province":"FL",
    "wof:name":"Twilight Cruisers of Mari",
    "wof:placetype":"venue"
},
  "geometry": {"coordinates":[-82.06699500000001,29.01121],"type":"Point"}
}