{
  "type": "Feature",
  "properties": {
    "iso:country":"US",
    "sg:address":"2 Sawgrass Village Dr",
    "sg:city":"Ponte Vedra Beach",
    "sg:classifiers":[
        {
            "category":"Professional",
            "subcategory":"Lawyer & Legal Services",
            "type":"Services"
        }
    ],
    "sg:phone":"+1 904 285 2674",
    "sg:postcode":"32082",
    "sg:province":"FL",
    "wof:name":"Fisher Tousey Leas & Ball",
    "wof:placetype":"venue"
},
  "geometry": {"coordinates":[-81.38305699999999,30.206569],"type":"Point"}
}