{
  "type": "Feature",
  "properties": {
    "addr:full":"107 Whispering Pine Dr Palm Coast FL 32164",
    "addr:housenumber":"107",
    "addr:postcode":"32164",
    "addr:street":"Whispering Pine Dr",
    "iso:country":"US",
    "sg:address":"107 Whispering Pine Dr",
    "sg:city":"Palm Coast",
    "sg:classifiers":[
        {
            "category":"Shopping",
            "subcategory":"Computers & Home Electronics",
            "type":"Retail Goods"
        }
    ],
    "sg:phone":"+1 386 447 1461",
    "sg:postcode":"32164",
    "sg:province":"FL",
    "sg:tags":[
        "software"
    ],
    "wof:name":"Info Bid Corp",
    "wof:placetype":"venue"
},
  "geometry": {"coordinates":[-81.240073,29.526267],"type":"Point"}
}