{
  "type": "Feature",
  "properties": {
    "addr:full":"400 W Fairbanks Ave Winter Park FL 32789",
    "addr:housenumber":"400",
    "addr:postcode":"32789",
    "addr:street":"W Fairbanks Ave",
    "iso:country":"US",
    "sg:address":"400 W Fairbanks Ave",
    "sg:city":"Winter Park",
    "sg:classifiers":[
        {
            "category":"Building & Trades",
            "subcategory":"Construction",
            "type":"Services"
        }
    ],
    "sg:phone":"+1 407 647 6178",
    "sg:postcode":"32789",
    "sg:province":"FL",
    "sg:tags":[
        "general",
        "contractor"
    ],
    "sg:website":"www.kincaidconstruction.com",
    "wof:name":"Kincaid Construction Co",
    "wof:placetype":"venue"
},
  "geometry": {"coordinates":[-81.35396900000001,28.593092],"type":"Point"}
}