{
  "type": "Feature",
  "properties": {
    "addr:full":"61 Hancock Bridge Pkwy W Cape Coral FL 33991",
    "addr:housenumber":"61",
    "addr:postcode":"33991",
    "addr:street":"Hancock Bridge Pkwy W",
    "iso:country":"US",
    "sg:address":"61 Hancock Bridge Pkwy W",
    "sg:city":"Cape Coral",
    "sg:classifiers":[
        {
            "category":"Banks & Credit Unions",
            "subcategory":"Bank",
            "type":"Services"
        }
    ],
    "sg:phone":"+1 239 573 5100",
    "sg:postcode":"33991",
    "sg:province":"FL",
    "sg:website":"www.bankcapecoral.com",
    "wof:name":"Community Bank of Cape Coral",
    "wof:placetype":"venue"
},
  "geometry": {"coordinates":[-81.976916,26.649942],"type":"Point"}
}