{
  "type": "Feature",
  "properties": {
    "iso:country":"US",
    "sg:address":"1021 Bay Dr",
    "sg:city":"Miami Beach",
    "sg:classifiers":[
        {
            "category":"Professional",
            "subcategory":"Management & Consulting",
            "type":"Services"
        }
    ],
    "sg:phone":"+1 305 864 6040",
    "sg:postcode":"33141",
    "sg:province":"FL",
    "wof:name":"Burman Group The",
    "wof:placetype":"venue"
},
  "geometry": {"coordinates":[-80.12794700000001,25.853198],"type":"Point"}
}