{
  "type": "Feature",
  "properties": {
    "addr:full":"550 NW 27th Ave Miami FL 33125",
    "addr:housenumber":"550",
    "addr:postcode":"33125",
    "addr:street":"Nw 27Th Ave",
    "iso:country":"US",
    "sg:address":"550 NW 27th Ave",
    "sg:city":"Miami",
    "sg:classifiers":[
        {
            "category":"Home & Garden",
            "subcategory":"Building Materials",
            "type":"Retail Goods"
        }
    ],
    "sg:phone":"+1 305 649 6814",
    "sg:postcode":"33125",
    "sg:province":"FL",
    "sg:tags":[
        "paint",
        "painting",
        "contractor"
    ],
    "sg:website":"http://miami.citysearch.com/profile/external/2482244/miami_fl/sherwin_williams.html?publisher=yellowpages&reference_id=1&placement=ypwebsitemip",
    "wof:name":"Sherwin-Williams",
    "wof:placetype":"venue"
},
  "geometry": {"coordinates":[-80.239369,25.778273],"type":"Point"}
}