{
  "type": "Feature",
  "properties": {
    "addr:full":"10216 State Rd 52 Hudson FL 34669",
    "addr:housenumber":"10216;52",
    "addr:postcode":"34669",
    "addr:street":"State Rd",
    "iso:country":"US",
    "sg:address":"10216 State Rd 52",
    "sg:city":"Hudson",
    "sg:classifiers":[
        {
            "category":"Shopping",
            "subcategory":"Jewelry",
            "type":"Retail Goods"
        }
    ],
    "sg:phone":"+1 727 856 5084",
    "sg:postcode":"34669",
    "sg:province":"FL",
    "sg:tags":[
        "jeweler"
    ],
    "wof:name":"Gold Galore",
    "wof:placetype":"venue"
},
  "geometry": {"coordinates":[-82.648056,28.330907],"type":"Point"}
}