{
  "type": "Feature",
  "properties": {
    "iso:country":"US",
    "sg:address":"800 N Calhoun St",
    "sg:city":"Tallahassee",
    "sg:classifiers":[
        {
            "category":"Professional",
            "type":"Services"
        }
    ],
    "sg:phone":"+1 850 205 9474",
    "sg:postcode":"32303",
    "sg:province":"FL",
    "sg:tags":[
        "establishment"
    ],
    "wof:name":"Make A Wish Of Central",
    "wof:placetype":"venue"
},
  "geometry": {"coordinates":[-84.279681,30.450996],"type":"Point"}
}