{
  "type": "Feature",
  "properties": {
    "addr:full":"1225 N Orange Ave Orlando FL 32804",
    "addr:housenumber":"1225",
    "addr:postcode":"32804",
    "addr:street":"N Orange Ave",
    "iso:country":"US",
    "sg:address":"1225 N Orange Ave",
    "sg:city":"Orlando",
    "sg:classifiers":[
        {
            "category":"Real Estate",
            "subcategory":"Architect",
            "type":"Services"
        }
    ],
    "sg:phone":"+1 407 898 3092",
    "sg:postcode":"32804",
    "sg:province":"FL",
    "wof:name":"GANTT Partnership",
    "wof:placetype":"venue"
},
  "geometry": {"coordinates":[-81.372848,28.563825],"type":"Point"}
}