{
  "type": "Feature",
  "properties": {
    "iso:country":"US",
    "sg:address":"2114 Hillcrest St",
    "sg:city":"Orlando",
    "sg:classifiers":[
        {
            "category":"Professional",
            "subcategory":"Accounting & Tax Preparation",
            "type":"Services"
        }
    ],
    "sg:phone":"+1 407 896 1940",
    "sg:postcode":"32803",
    "sg:province":"FL",
    "sg:tags":[
        "accountant"
    ],
    "wof:name":"Sheila Lang CPA",
    "wof:placetype":"venue"
},
  "geometry": {"coordinates":[-81.355259,28.552177],"type":"Point"}
}