{
  "type": "Feature",
  "properties": {
    "iso:country":"US",
    "sg:address":"10511 NW 21st Ct",
    "sg:city":"Sunrise",
    "sg:classifiers":[
        {
            "category":"Professional",
            "subcategory":"Accounting & Tax Preparation",
            "type":"Services"
        }
    ],
    "sg:phone":"+1 954 937 7940",
    "sg:postcode":"33322",
    "sg:province":"FL",
    "sg:tags":[
        "bookkeeping",
        "billing"
    ],
    "wof:name":"Quality Bookkeeping Solutions",
    "wof:placetype":"venue"
},
  "geometry": {"coordinates":[-80.28855,26.15204],"type":"Point"}
}