{
  "type": "Feature",
  "properties": {
    "addr:full":"2171 13th St Sarasota FL 34237",
    "addr:housenumber":"2171",
    "addr:postcode":"34237",
    "addr:street":"13Th St",
    "iso:country":"US",
    "sg:address":"2171 13th St",
    "sg:city":"Sarasota",
    "sg:classifiers":[
        {
            "category":"Home & Garden",
            "subcategory":"Furniture",
            "type":"Retail Goods"
        }
    ],
    "sg:phone":"+1 941 953 6727",
    "sg:postcode":"34237",
    "sg:province":"FL",
    "sg:tags":[
        "cabinet"
    ],
    "wof:name":"Capital Cabinetry & Millwork",
    "wof:placetype":"venue"
},
  "geometry": {"coordinates":[-82.526445,27.349577],"type":"Point"}
}