{
  "type": "Feature",
  "properties": {
    "addr:full":"3121 E Hillsborough Ave Tampa FL 33610",
    "addr:housenumber":"3121",
    "addr:postcode":"33610",
    "addr:street":"E Hillsborough Ave",
    "iso:country":"US",
    "sg:address":"3121 E Hillsborough Ave",
    "sg:city":"Tampa",
    "sg:classifiers":[
        {
            "category":"Wholesale",
            "subcategory":"Fruits & Vegetables",
            "type":"Manufacturing & Wholesale Goods"
        }
    ],
    "sg:phone":"+1 813 237 3487",
    "sg:postcode":"33610",
    "sg:province":"FL",
    "wof:name":"Underwood's Produce",
    "wof:placetype":"venue"
},
  "geometry": {"coordinates":[-82.42585200000001,27.995967],"type":"Point"}
}