{
  "type": "Feature",
  "properties": {
    "iso:country":"US",
    "sg:address":"4856 SW 19th St",
    "sg:city":"Fort Lauderdale",
    "sg:classifiers":[
        {
            "category":"Manufacturing",
            "subcategory":"Building Materials",
            "type":"Manufacturing & Wholesale Goods"
        }
    ],
    "sg:phone":"+1 954 592 1401",
    "sg:postcode":"33317",
    "sg:province":"FL",
    "sg:tags":[
        "mfg",
        "wood",
        "kitchen",
        "cabinet"
    ],
    "wof:name":"Espinosa Obed Corp",
    "wof:placetype":"venue"
},
  "geometry": {"coordinates":[-80.215738,26.099916],"type":"Point"}
}