{
  "type": "Feature",
  "properties": {
    "iso:country":"US",
    "sg:address":"6746 Bonnie Bay Cir",
    "sg:city":"Pinellas Park",
    "sg:classifiers":[
        {
            "category":"Cinema",
            "subcategory":"Movie Theater",
            "type":"Entertainment"
        }
    ],
    "sg:phone":"+1 727 525 7777",
    "sg:postcode":"33781",
    "sg:province":"FL",
    "wof:name":"Parkside Movies 16",
    "wof:placetype":"venue"
},
  "geometry": {"coordinates":[-82.73861599999999,27.833909],"type":"Point"}
}