{
  "type": "Feature",
  "properties": {
    "iso:country":"US",
    "sg:address":"682 S Yonge St",
    "sg:city":"Ormond Beach",
    "sg:classifiers":[
        {
            "category":"Professional",
            "type":"Services"
        }
    ],
    "sg:phone":"+1 386 672 9890",
    "sg:postcode":"32174",
    "sg:province":"FL",
    "sg:tags":[
        "establishment"
    ],
    "wof:name":"Prindle Associates Inc",
    "wof:placetype":"venue"
},
  "geometry": {"coordinates":[-81.053214,29.266786],"type":"Point"}
}