{
  "type": "Feature",
  "properties": {
    "addr:full":"18020 NW 27th Ave Opa Locka FL 33056",
    "addr:housenumber":"18020",
    "addr:postcode":"33056",
    "addr:street":"Nw 27Th Ave;Locka",
    "iso:country":"US",
    "sg:address":"18020 NW 27th Ave",
    "sg:city":"Opa Locka",
    "sg:classifiers":[
        {
            "category":"Shopping",
            "subcategory":"Bicycles & Sporting Goods",
            "type":"Retail Goods"
        }
    ],
    "sg:phone":"+1 305 623 0048",
    "sg:postcode":"33056",
    "sg:province":"FL",
    "wof:name":"Sneaker Center",
    "wof:placetype":"venue"
},
  "geometry": {"coordinates":[-80.245217,25.940398],"type":"Point"}
}