{
  "type": "Feature",
  "properties": {
    "addr:full":"2121 Killarney Way Tallahassee FL 32309",
    "addr:housenumber":"2121",
    "addr:postcode":"32309",
    "addr:street":"Killarney Way",
    "iso:country":"US",
    "sg:address":"2121 Killarney Way",
    "sg:city":"Tallahassee",
    "sg:classifiers":[
        {
            "category":"Banks & Credit Unions",
            "subcategory":"Investment Brokerage",
            "type":"Services"
        }
    ],
    "sg:phone":"+1 850 906 0112",
    "sg:postcode":"32309",
    "sg:province":"FL",
    "sg:tags":[
        "consultant",
        "planning",
        "financial"
    ],
    "wof:name":"American Express Financial Adv",
    "wof:placetype":"venue"
},
  "geometry": {"coordinates":[-84.24335600000001,30.511609],"type":"Point"}
}