{
  "type": "Feature",
  "properties": {
    "iso:country":"US",
    "sg:address":"4686 E Michigan St",
    "sg:city":"Orlando",
    "sg:classifiers":[
        {
            "category":"Real Estate",
            "subcategory":"Real Estate Services",
            "type":"Services"
        },
        {
            "category":"Real Estate",
            "subcategory":"Real Estate Agent",
            "type":"Services"
        }
    ],
    "sg:phone":"+1 407 381 3437",
    "sg:postcode":"32812",
    "sg:province":"FL",
    "sg:tags":[
        "buyer",
        "management",
        "broker"
    ],
    "wof:name":"Regency Realty Group Inc",
    "wof:placetype":"venue"
},
  "geometry": {"coordinates":[-81.32792499999999,28.51351],"type":"Point"}
}