{
  "type": "Feature",
  "properties": {
    "addr:full":"3640 N Federal Hwy Pompano Beach FL 33064",
    "addr:housenumber":"3640",
    "addr:postcode":"33064",
    "addr:street":"N Federal Hwy",
    "iso:country":"US",
    "sg:address":"3640 N Federal Hwy",
    "sg:city":"Pompano Beach",
    "sg:classifiers":[
        {
            "category":"Banks & Credit Unions",
            "subcategory":"Investment Brokerage",
            "type":"Services"
        }
    ],
    "sg:phone":"+1 954 946 6610",
    "sg:postcode":"33064",
    "sg:province":"FL",
    "sg:tags":[
        "consulting",
        "financial",
        "security",
        "dealer"
    ],
    "wof:name":"Wachovia Securities LLC",
    "wof:placetype":"venue"
},
  "geometry": {"coordinates":[-80.09702299999999,26.278347],"type":"Point"}
}