{
  "type": "Feature",
  "properties": {
    "addr:full":"1189 Industrial Blvd Naples FL 34104",
    "addr:housenumber":"1189",
    "addr:postcode":"34104",
    "addr:street":"Industrial Blvd",
    "iso:country":"US",
    "sg:address":"1189 Industrial Blvd",
    "sg:city":"Naples",
    "sg:classifiers":[
        {
            "category":"Retail",
            "subcategory":"Animal Services",
            "type":"Services"
        }
    ],
    "sg:phone":"+1 239 643 2834",
    "sg:postcode":"34104",
    "sg:province":"FL",
    "wof:name":"Sailing Clippers Dog Grooming",
    "wof:placetype":"venue"
},
  "geometry": {"coordinates":[-81.758943,26.162603],"type":"Point"}
}