{
  "type": "Feature",
  "properties": {
    "addr:full":"18810 Lenaire Dr Miami FL 33157",
    "addr:housenumber":"18810",
    "addr:postcode":"33157",
    "addr:street":"Lenaire Dr",
    "iso:country":"US",
    "sg:address":"18810 Lenaire Dr",
    "sg:city":"Miami",
    "sg:classifiers":[
        {
            "category":"Building & Trades",
            "subcategory":"Construction",
            "type":"Services"
        }
    ],
    "sg:phone":"+1 305 255 7356",
    "sg:postcode":"33157",
    "sg:province":"FL",
    "sg:tags":[
        "house"
    ],
    "wof:name":"Aje Enterprises Inc",
    "wof:placetype":"venue"
},
  "geometry": {"coordinates":[-80.354935,25.591913],"type":"Point"}
}