{
  "type": "Feature",
  "properties": {
    "addr:full":"5301 SW 23rd St Hollywood FL 33023",
    "addr:housenumber":"5301",
    "addr:postcode":"33023",
    "addr:street":"Sw 23Rd St",
    "iso:country":"US",
    "sg:address":"5301 SW 23rd St",
    "sg:city":"Hollywood",
    "sg:classifiers":[
        {
            "category":"Banks & Credit Unions",
            "subcategory":"Financial Services",
            "type":"Services"
        }
    ],
    "sg:phone":"+1 954 448 0629",
    "sg:postcode":"33023",
    "sg:province":"FL",
    "sg:tags":[
        "company",
        "holding"
    ],
    "wof:name":"Strachan Holdings Inc",
    "wof:placetype":"venue"
},
  "geometry": {"coordinates":[-80.195914,25.989784],"type":"Point"}
}