{
  "type": "Feature",
  "properties": {
    "iso:country":"US",
    "sg:address":"217 SW 28th St",
    "sg:city":"Fort Lauderdale",
    "sg:classifiers":[
        {
            "category":"Wholesale",
            "subcategory":"Machinery & Supplies",
            "type":"Manufacturing & Wholesale Goods"
        },
        {
            "category":"Retail",
            "subcategory":"Repair Shop",
            "type":"Services"
        }
    ],
    "sg:phone":"+1 954 764 2678",
    "sg:postcode":"33315",
    "sg:province":"FL",
    "sg:tags":[
        "repairing",
        "light",
        "metal",
        "machining",
        "ship",
        "fabrication"
    ],
    "wof:name":"Advanced Mechanical Engineer",
    "wof:placetype":"venue"
},
  "geometry": {"coordinates":[-80.144401,26.089051],"type":"Point"}
}