{
  "type": "Feature",
  "properties": {
    "iso:country":"US",
    "sg:address":"21250 Sawmill Ct",
    "sg:city":"Boca Raton",
    "sg:classifiers":[
        {
            "category":"Shopping",
            "subcategory":"Florist",
            "type":"Retail Goods"
        }
    ],
    "sg:phone":"+1 561 477 6289",
    "sg:postcode":"33498",
    "sg:province":"FL",
    "wof:name":"Hernan Forero Flowers",
    "wof:placetype":"venue"
},
  "geometry": {"coordinates":[-80.22709399999999,26.402743],"type":"Point"}
}