{
  "type": "Feature",
  "properties": {
    "addr:full":"1924 Commercial Dr Fort Myers FL 33901",
    "addr:housenumber":"1924",
    "addr:postcode":"33901",
    "addr:street":"Commercial Dr",
    "iso:country":"US",
    "sg:address":"1924 Commercial Dr",
    "sg:city":"Fort Myers",
    "sg:classifiers":[
        {
            "category":"Bars & Pubs",
            "subcategory":"Nightclub",
            "type":"Food & Drink"
        }
    ],
    "sg:phone":"+1 239 936 0066",
    "sg:postcode":"33901",
    "sg:province":"FL",
    "sg:tags":[
        "nightlife"
    ],
    "wof:name":"Keg South Lounge",
    "wof:placetype":"venue"
},
  "geometry": {"coordinates":[-81.87449599999999,26.603001],"type":"Point"}
}