{
  "type": "Feature",
  "properties": {
    "addr:full":"3365 SE 19th Ave Ocala FL 34471",
    "addr:housenumber":"3365",
    "addr:postcode":"34471",
    "addr:street":"Se 19Th Ave",
    "iso:country":"US",
    "sg:address":"3365 SE 19th Ave",
    "sg:city":"Ocala",
    "sg:classifiers":[
        {
            "category":"Shopping",
            "type":"Retail Goods"
        }
    ],
    "sg:phone":"+1 352 237 8726",
    "sg:postcode":"34471",
    "sg:province":"FL",
    "sg:tags":[
        "item",
        "boutique"
    ],
    "wof:name":"Sonshine Creek Boutique",
    "wof:placetype":"venue"
},
  "geometry": {"coordinates":[-82.111654,29.153972],"type":"Point"}
}