{
  "type": "Feature",
  "properties": {
    "addr:full":"2034 Elk Spring Dr Brandon FL 33511",
    "addr:housenumber":"2034",
    "addr:postcode":"33511",
    "addr:street":"Elk Spring Dr",
    "iso:country":"US",
    "sg:address":"2034 Elk Spring Dr",
    "sg:city":"Brandon",
    "sg:classifiers":[
        {
            "category":"Retail",
            "subcategory":"Auto Repair",
            "type":"Services"
        }
    ],
    "sg:phone":"+1 813 689 5713",
    "sg:postcode":"33511",
    "sg:province":"FL",
    "sg:tags":[
        "repairing",
        "automobile"
    ],
    "wof:name":"B & P Mobile Auto Handyman Svc",
    "wof:placetype":"venue"
},
  "geometry": {"coordinates":[-82.32490199999999,27.906706],"type":"Point"}
}