{
  "type": "Feature",
  "properties": {
    "addr:full":"2067 Linton Blvd Delray Beach FL 33445",
    "addr:housenumber":"2067",
    "addr:postcode":"33445",
    "addr:street":"Linton Blvd",
    "iso:country":"US",
    "sg:address":"2067 Linton Blvd",
    "sg:city":"Delray Beach",
    "sg:classifiers":[
        {
            "category":"Wholesale",
            "subcategory":"Chemicals & Plastics",
            "type":"Manufacturing & Wholesale Goods"
        }
    ],
    "sg:phone":"+1 561 251 1932",
    "sg:postcode":"33445",
    "sg:province":"FL",
    "wof:name":"Victor Salinas Marble Polish",
    "wof:placetype":"venue"
},
  "geometry": {"coordinates":[-80.09305500000001,26.439494],"type":"Point"}
}