{
  "type": "Feature",
  "properties": {
    "addr:full":"120 9th St New Smyrna Beach FL 32168",
    "addr:housenumber":"120",
    "addr:postcode":"32168",
    "addr:street":"9Th St",
    "iso:country":"US",
    "sg:address":"120 9th St",
    "sg:city":"New Smyrna Beach",
    "sg:classifiers":[
        {
            "category":"Building & Trades",
            "subcategory":"Construction",
            "type":"Services"
        }
    ],
    "sg:phone":"+1 386 426 2345",
    "sg:postcode":"32168",
    "sg:province":"FL",
    "wof:name":"Burton Buildings Inc",
    "wof:placetype":"venue"
},
  "geometry": {"coordinates":[-80.914035,29.006113],"type":"Point"}
}