{
  "type": "Feature",
  "properties": {
    "addr:full":"48 Via Mizner Palm Beach FL 33480",
    "addr:postcode":"33480",
    "addr:street":"Via Mizner",
    "iso:country":"US",
    "sg:address":"48 Via Mizner",
    "sg:city":"Palm Beach",
    "sg:classifiers":[
        {
            "category":"Banks & Credit Unions",
            "subcategory":"Investment Brokerage",
            "type":"Services"
        }
    ],
    "sg:phone":"+1 561 514 0975",
    "sg:postcode":"33480",
    "sg:province":"FL",
    "sg:tags":[
        "advisory",
        "financial"
    ],
    "wof:name":"Mikus Capital Management Inc",
    "wof:placetype":"venue"
},
  "geometry": {"coordinates":[-80.04002800000001,26.701058],"type":"Point"}
}