{
  "type": "Feature",
  "properties": {
    "iso:country":"US",
    "sg:address":"28714 SW 147th Pl",
    "sg:city":"Homestead",
    "sg:classifiers":[
        {
            "category":"Social Services",
            "subcategory":"Child Care",
            "type":"Services"
        }
    ],
    "sg:phone":"+1 305 246 1090",
    "sg:postcode":"33033",
    "sg:province":"FL",
    "wof:name":"Geno Home Day Care",
    "wof:placetype":"venue"
},
  "geometry": {"coordinates":[-80.43050100000001,25.501557],"type":"Point"}
}