{
  "type": "Feature",
  "properties": {
    "addr:full":"62 Wood Hall Dr Mulberry FL 33860",
    "addr:housenumber":"62",
    "addr:postcode":"33860",
    "addr:street":"Wood Hall Dr",
    "iso:country":"US",
    "sg:address":"62 Wood Hall Dr",
    "sg:city":"Mulberry",
    "sg:classifiers":[
        {
            "category":"Building & Trades",
            "subcategory":"Construction",
            "type":"Services"
        }
    ],
    "sg:phone":"+1 863 425 8778",
    "sg:postcode":"33860",
    "sg:province":"FL",
    "sg:tags":[
        "home",
        "improvement"
    ],
    "wof:name":"Davis Home Repair",
    "wof:placetype":"venue"
},
  "geometry": {"coordinates":[-81.986774,27.925087],"type":"Point"}
}