{
  "type": "Feature",
  "properties": {
    "addr:full":"12503 Rhodine Rd Riverview FL 33579",
    "addr:housenumber":"12503",
    "addr:postcode":"33579",
    "addr:street":"Rhodine Rd",
    "iso:country":"US",
    "sg:address":"12503 Rhodine Rd",
    "sg:city":"Riverview",
    "sg:classifiers":[
        {
            "category":"Building & Trades",
            "subcategory":"Construction",
            "type":"Services"
        }
    ],
    "sg:phone":"+1 813 677 3269",
    "sg:postcode":"33579",
    "sg:province":"FL",
    "sg:tags":[
        "builder",
        "patio",
        "deck"
    ],
    "wof:name":"Aluminum Fabricators Inc",
    "wof:placetype":"venue"
},
  "geometry": {"coordinates":[-81.68732,30.406072],"type":"Point"}
}