{
  "type": "Feature",
  "properties": {
    "iso:country":"US",
    "sg:address":"844 NW 131st Ave",
    "sg:city":"Fort Lauderdale",
    "sg:classifiers":[
        {
            "category":"Building & Trades",
            "subcategory":"Electrical",
            "type":"Services"
        }
    ],
    "sg:phone":"+1 954 838 8021",
    "sg:postcode":"33325",
    "sg:province":"FL",
    "sg:tags":[
        "motion",
        "production",
        "electrical",
        "contractor"
    ],
    "wof:name":"Lisa Lupari Productions Inc",
    "wof:placetype":"venue"
},
  "geometry": {"coordinates":[-80.323375,26.132252],"type":"Point"}
}