{
  "type": "Feature",
  "properties": {
    "iso:country":"US",
    "sg:address":"11500 NW 30th Pl",
    "sg:city":"Fort Lauderdale",
    "sg:classifiers":[
        {
            "category":"Communications",
            "subcategory":"Film & Video Production",
            "type":"Services"
        }
    ],
    "sg:phone":"+1 954 746 9239",
    "sg:postcode":"33323",
    "sg:province":"FL",
    "sg:tags":[
        "motion"
    ],
    "wof:name":"Cmg Productions Inc",
    "wof:placetype":"venue"
},
  "geometry": {"coordinates":[-80.298805,26.164023],"type":"Point"}
}