{
  "type": "Feature",
  "properties": {
    "addr:full":"7467 Manatee Ave W Bradenton FL 34209",
    "addr:housenumber":"7467",
    "addr:postcode":"34209",
    "addr:street":"Manatee Ave W",
    "iso:country":"US",
    "sg:address":"7467 Manatee Ave W",
    "sg:city":"Bradenton",
    "sg:classifiers":[
        {
            "category":"Restaurant",
            "type":"Food & Drink"
        }
    ],
    "sg:phone":"+1 941 794 0678",
    "sg:postcode":"34209",
    "sg:province":"FL",
    "sg:tags":[
        "eating"
    ],
    "wof:name":"Prego Pizza Pasta",
    "wof:placetype":"venue"
},
  "geometry": {"coordinates":[-82.636557,27.496043],"type":"Point"}
}