{
  "type": "Feature",
  "properties": {
    "iso:country":"US",
    "sg:address":"2780 NE 209th St",
    "sg:city":"Miami",
    "sg:classifiers":[
        {
            "category":"Restaurant",
            "type":"Food & Drink"
        }
    ],
    "sg:phone":"+1 305 466 9300",
    "sg:postcode":"33180",
    "sg:province":"FL",
    "sg:tags":[
        "eating"
    ],
    "wof:name":"Telephone Take Out",
    "wof:placetype":"venue"
},
  "geometry": {"coordinates":[-80.146242,25.968906],"type":"Point"}
}