{
  "type": "Feature",
  "properties": {
    "iso:country":"US",
    "sg:address":"466 S Spring Garden Ave",
    "sg:city":"Deland",
    "sg:classifiers":[
        {
            "category":"Building & Trades",
            "subcategory":"Pest Control",
            "type":"Services"
        }
    ],
    "sg:phone":"+1 386 734 4877",
    "sg:postcode":"32720",
    "sg:province":"FL",
    "wof:name":"Holder Pest & Termite Control",
    "wof:placetype":"venue"
},
  "geometry": {"coordinates":[-81.324093,29.021785],"type":"Point"}
}