{
  "type": "Feature",
  "properties": {
    "addr:full":"620 Fern Lake Dr Orlando FL 32825",
    "addr:housenumber":"620",
    "addr:postcode":"32825",
    "addr:street":"Fern Lake Dr",
    "iso:country":"US",
    "sg:address":"620 Fern Lake Dr",
    "sg:city":"Orlando",
    "sg:classifiers":[
        {
            "category":"Manufacturing",
            "subcategory":"Apparel",
            "type":"Manufacturing & Wholesale Goods"
        }
    ],
    "sg:phone":"+1 407 273 4986",
    "sg:postcode":"32825",
    "sg:province":"FL",
    "sg:tags":[
        "outerwear",
        "mfg"
    ],
    "wof:name":"I Drops Inc",
    "wof:placetype":"venue"
},
  "geometry": {"coordinates":[-81.22417799999999,28.538514],"type":"Point"}
}