{
  "type": "Feature",
  "properties": {
    "iso:country":"US",
    "sg:address":"513 NE 2nd Ave",
    "sg:city":"Hallandale",
    "sg:classifiers":[
        {
            "category":"Wholesale",
            "subcategory":"Apparel",
            "type":"Manufacturing & Wholesale Goods"
        }
    ],
    "sg:phone":"+1 954 456 2116",
    "sg:postcode":"33009",
    "sg:province":"FL",
    "sg:tags":[
        "clothing"
    ],
    "wof:name":"Martin A Rubenstein Entps",
    "wof:placetype":"venue"
},
  "geometry": {"coordinates":[-80.14735,25.99279],"type":"Point"}
}