{
  "type": "Feature",
  "properties": {
    "addr:full":"10771 Beach Blvd Jacksonville FL 32246",
    "addr:housenumber":"10771",
    "addr:postcode":"32246",
    "addr:street":"Beach Blvd",
    "iso:country":"US",
    "sg:address":"10771 Beach Blvd",
    "sg:city":"Jacksonville",
    "sg:classifiers":[
        {
            "category":"Food & Beverages",
            "subcategory":"Groceries & Convenience Stores",
            "type":"Retail Goods"
        }
    ],
    "sg:phone":"+1 904 646 1987",
    "sg:postcode":"32246",
    "sg:province":"FL",
    "wof:name":"Lil' Champ Food Store",
    "wof:placetype":"venue"
},
  "geometry": {"coordinates":[-81.53679099999999,30.286862],"type":"Point"}
}