{
  "type": "Feature",
  "properties": {
    "addr:full":"5044 W Co Hwy 30A Santa Rosa Beach FL 32459",
    "addr:housenumber":"5044",
    "addr:postcode":"32459",
    "addr:street":"W Co Hwy 30A;Rosa",
    "iso:country":"US",
    "sg:address":"5044 W Co Hwy 30A",
    "sg:city":"Santa Rosa Beach",
    "sg:classifiers":[
        {
            "category":"Food & Beverages",
            "subcategory":"Groceries & Convenience Stores",
            "type":"Retail Goods"
        }
    ],
    "sg:phone":"+1 850 267 3546",
    "sg:postcode":"32459",
    "sg:province":"FL",
    "sg:tags":[
        "gasoline"
    ],
    "wof:name":"Jr Food Market",
    "wof:placetype":"venue"
},
  "geometry": {"coordinates":[-86.241013,30.350225],"type":"Point"}
}