{
  "type": "Feature",
  "properties": {
    "iso:country":"US",
    "sg:address":"2630 NW 21st Ter",
    "sg:city":"Miami",
    "sg:classifiers":[
        {
            "category":"Manufacturing",
            "subcategory":"Printing",
            "type":"Manufacturing & Wholesale Goods"
        }
    ],
    "sg:phone":"+1 305 635 3914",
    "sg:postcode":"33142",
    "sg:province":"FL",
    "sg:tags":[
        "printer"
    ],
    "wof:name":"National Printing Ent Inc",
    "wof:placetype":"venue"
},
  "geometry": {"coordinates":[-80.23956800000001,25.796047],"type":"Point"}
}