{
  "type": "Feature",
  "properties": {
    "iso:country":"US",
    "sg:address":"5300 NW 77th Ave",
    "sg:city":"Doral",
    "sg:classifiers":[
        {
            "category":"Banks & Credit Unions",
            "subcategory":"Bank",
            "type":"Services"
        }
    ],
    "sg:phone":"+1 305 392 5414",
    "sg:postcode":"33166",
    "sg:province":"FL",
    "sg:tags":[
        "loan",
        "real estate"
    ],
    "wof:name":"In House Mortgage Inc",
    "wof:placetype":"venue"
},
  "geometry": {"coordinates":[-80.321315,25.82165],"type":"Point"}
}