{
  "type": "Feature",
  "properties": {
    "addr:full":"301 W Atlantic Ave Delray Beach FL 33444",
    "addr:housenumber":"301",
    "addr:postcode":"33444",
    "addr:street":"W Atlantic Ave",
    "iso:country":"US",
    "sg:address":"301 W Atlantic Ave",
    "sg:city":"Delray Beach",
    "sg:classifiers":[
        {
            "category":"Food & Beverages",
            "subcategory":"Groceries & Convenience Stores",
            "type":"Retail Goods"
        }
    ],
    "sg:phone":"+1 561 276 1713",
    "sg:postcode":"33444",
    "sg:province":"FL",
    "wof:name":"Tony's Market & Deli",
    "wof:placetype":"venue"
},
  "geometry": {"coordinates":[-80.076724,26.461697],"type":"Point"}
}