{
  "type": "Feature",
  "properties": {
    "iso:country":"US",
    "sg:address":"125 S Swoope Ave",
    "sg:city":"Maitland",
    "sg:classifiers":[
        {
            "category":"Banks & Credit Unions",
            "subcategory":"Bank",
            "type":"Services"
        }
    ],
    "sg:phone":"+1 407 260 0404",
    "sg:postcode":"32751",
    "sg:province":"FL",
    "sg:tags":[
        "loan",
        "real estate"
    ],
    "wof:name":"AMB Mortgage Corp",
    "wof:placetype":"venue"
},
  "geometry": {"coordinates":[-81.361942,28.627297],"type":"Point"}
}