{
  "type": "Feature",
  "properties": {
    "addr:full":"24 N Swinton Ave Delray Beach FL 33444",
    "addr:housenumber":"24",
    "addr:postcode":"33444",
    "addr:street":"N Swinton Ave",
    "iso:country":"US",
    "sg:address":"24 N Swinton Ave",
    "sg:city":"Delray Beach",
    "sg:classifiers":[
        {
            "category":"Utilities",
            "subcategory":"Telephone",
            "type":"Services"
        }
    ],
    "sg:phone":"+1 561 243 6968",
    "sg:postcode":"33444",
    "sg:province":"FL",
    "sg:tags":[
        "cards",
        "phone",
        "prepaid",
        "mfg"
    ],
    "wof:name":"Intelecard Resources Inc",
    "wof:placetype":"venue"
},
  "geometry": {"coordinates":[-80.07321,26.463041],"type":"Point"}
}