{
  "type": "Feature",
  "properties": {
    "addr:full":"7400 Georgia Ave West Palm Beach FL 33405",
    "addr:housenumber":"7400",
    "addr:postcode":"33405",
    "addr:street":"Georgia Ave",
    "iso:country":"US",
    "sg:address":"7400 Georgia Ave",
    "sg:city":"West Palm Beach",
    "sg:classifiers":[
        {
            "category":"Professional",
            "type":"Services"
        }
    ],
    "sg:phone":"+1 561 533 0749",
    "sg:postcode":"33405",
    "sg:province":"FL",
    "sg:tags":[
        "arts",
        "artist"
    ],
    "wof:name":"Measelle Studio",
    "wof:placetype":"venue"
},
  "geometry": {"coordinates":[-80.05914300000001,26.649523],"type":"Point"}
}