{
  "type": "Feature",
  "properties": {
    "addr:full":"2405 N Baylen St Pensacola FL 32501",
    "addr:housenumber":"2405",
    "addr:postcode":"32501",
    "addr:street":"N Baylen St",
    "iso:country":"US",
    "sg:address":"2405 N Baylen St",
    "sg:city":"Pensacola",
    "sg:classifiers":[
        {
            "category":"Manufacturing",
            "subcategory":"Apparel",
            "type":"Manufacturing & Wholesale Goods"
        }
    ],
    "sg:phone":"+1 850 437 1123",
    "sg:postcode":"32501",
    "sg:province":"FL",
    "sg:tags":[
        "textile",
        "product",
        "fabricated",
        "mfg"
    ],
    "wof:name":"Rosemary Carter",
    "wof:placetype":"venue"
},
  "geometry": {"coordinates":[-87.222542,30.437096],"type":"Point"}
}