{
  "type": "Feature",
  "properties": {
    "addr:full":"1825 NW 87th Ave Miami FL 33172",
    "addr:housenumber":"1825",
    "addr:postcode":"33172",
    "addr:street":"Nw 87Th Ave",
    "iso:country":"US",
    "sg:address":"1825 NW 87th Ave",
    "sg:city":"Miami",
    "sg:classifiers":[
        {
            "category":"Wholesale",
            "subcategory":"Computers",
            "type":"Manufacturing & Wholesale Goods"
        }
    ],
    "sg:phone":"+1 305 718 8071",
    "sg:postcode":"33172",
    "sg:province":"FL",
    "sg:tags":[
        "automation",
        "supply"
    ],
    "wof:name":"Daisyteck Latin America Inc",
    "wof:placetype":"venue"
},
  "geometry": {"coordinates":[-80.33671699999999,25.790465],"type":"Point"}
}