{
  "type": "Feature",
  "properties": {
    "addr:full":"200 E Monument Ave Ste A Kissimmee FL 34741",
    "addr:housenumber":"200",
    "addr:postcode":"34741",
    "addr:street":"E Monument Ave Ste A",
    "iso:country":"US",
    "sg:address":"200 E Monument Ave Ste A",
    "sg:city":"Kissimmee",
    "sg:classifiers":[
        {
            "category":"Professional",
            "subcategory":"Accounting & Tax Preparation",
            "type":"Services"
        },
        {
            "category":"Banks & Credit Unions",
            "subcategory":"Financial Services",
            "type":"Services"
        }
    ],
    "sg:phone":"+1 407 846 6677",
    "sg:postcode":"34741",
    "sg:province":"FL",
    "sg:tags":[
        "return",
        "preparation-business",
        "taxes-consultants",
        "loan",
        "reporting",
        "representative",
        "alternative",
        "bookkeeping"
    ],
    "sg:website":"http://www.hrblock.com",
    "wof:name":"H&R Block",
    "wof:placetype":"venue"
},
  "geometry": {"coordinates":[-81.404741,28.292072],"type":"Point"}
}