{
  "type": "Feature",
  "properties": {
    "iso:country":"US",
    "sg:address":"8070 W 21st Ave",
    "sg:city":"Hialeah",
    "sg:classifiers":[
        {
            "category":"Recreation",
            "subcategory":"Marina",
            "type":"Entertainment"
        }
    ],
    "sg:phone":"+1 305 231 0240",
    "sg:postcode":"33016",
    "sg:province":"FL",
    "sg:tags":[
        "repairing",
        "boat"
    ],
    "wof:name":"Blue Water Marine Inc",
    "wof:placetype":"venue"
},
  "geometry": {"coordinates":[-80.326641,25.895357],"type":"Point"}
}