{
  "type": "Feature",
  "properties": {
    "iso:country":"US",
    "sg:address":"3704 W 23rd St",
    "sg:city":"Panama City",
    "sg:classifiers":[
        {
            "category":"Shopping",
            "subcategory":"Clothing, Apparel, & Fashions",
            "type":"Retail Goods"
        }
    ],
    "sg:phone":"+1 850 785 6797",
    "sg:postcode":"32405",
    "sg:province":"FL",
    "sg:tags":[
        "dancing",
        "supply"
    ],
    "wof:name":"D K's Discount Dance",
    "wof:placetype":"venue"
},
  "geometry": {"coordinates":[-85.708828,30.189924],"type":"Point"}
}