{
  "type": "Feature",
  "properties": {
    "addr:full":"18 S Riverside Dr Indialantic FL 32903",
    "addr:housenumber":"18",
    "addr:postcode":"32903",
    "addr:street":"S Riverside Dr",
    "iso:country":"US",
    "sg:address":"18 S Riverside Dr",
    "sg:city":"Indialantic",
    "sg:classifiers":[
        {
            "category":"Health Services",
            "subcategory":"Health Practitioner",
            "type":"Services"
        }
    ],
    "sg:phone":"+1 321 409 8808",
    "sg:postcode":"32903",
    "sg:province":"FL",
    "sg:tags":[
        "acupuncture"
    ],
    "wof:name":"Jere Proctor Acupuncture",
    "wof:placetype":"venue"
},
  "geometry": {"coordinates":[-80.57484599999999,28.088467],"type":"Point"}
}