{
  "type": "Feature",
  "properties": {
    "iso:country":"US",
    "sg:address":"17 Crown Ct",
    "sg:city":"Fort Pierce",
    "sg:classifiers":[
        {
            "category":"Wholesale",
            "subcategory":"Non-durable Goods",
            "type":"Manufacturing & Wholesale Goods"
        }
    ],
    "sg:phone":"+1 772 429 0220",
    "sg:postcode":"34949",
    "sg:province":"FL",
    "wof:name":"Halimeda Maritime Trade Inc",
    "wof:placetype":"venue"
},
  "geometry": {"coordinates":[-80.314059,27.516974],"type":"Point"}
}