{
  "type": "Feature",
  "properties": {
    "iso:country":"US",
    "sg:address":"2133 Turnbull Bay Rd",
    "sg:city":"New Smyrna Beach",
    "sg:classifiers":[
        {
            "category":"Professional",
            "subcategory":"Business Services",
            "type":"Services"
        }
    ],
    "sg:phone":"+1 386 423 3503",
    "sg:postcode":"32168",
    "sg:province":"FL",
    "sg:tags":[
        "inspection"
    ],
    "wof:name":"Mold Inspection",
    "wof:placetype":"venue"
},
  "geometry": {"coordinates":[-80.960877,29.051236],"type":"Point"}
}