{
  "type": "Feature",
  "properties": {
    "iso:country":"US",
    "sg:address":"325 14th St",
    "sg:city":"Quincy",
    "sg:classifiers":[
        {
            "category":"Building & Trades",
            "subcategory":"Construction",
            "type":"Services"
        }
    ],
    "sg:phone":"+1 850 570 2057",
    "sg:postcode":"32351",
    "sg:province":"FL",
    "sg:tags":[
        "carpentry",
        "contractor"
    ],
    "wof:name":"Darnell & Davis Construction",
    "wof:placetype":"venue"
},
  "geometry": {"coordinates":[-84.591883,30.593112],"type":"Point"}
}