{
  "type": "Feature",
  "properties": {
    "iso:country":"US",
    "sg:address":"10343 153rd Ct N",
    "sg:city":"Jupiter",
    "sg:classifiers":[
        {
            "category":"Building & Trades",
            "subcategory":"Construction",
            "type":"Services"
        }
    ],
    "sg:phone":"+1 561 745 8738",
    "sg:postcode":"33478",
    "sg:province":"FL",
    "sg:tags":[
        "nonresidential"
    ],
    "wof:name":"Licensed Contractors Inc",
    "wof:placetype":"venue"
},
  "geometry": {"coordinates":[-80.197879,26.902643],"type":"Point"}
}