{
  "type": "Feature",
  "properties": {
    "addr:full":"1732 W Flagler St Miami FL 33135",
    "addr:housenumber":"1732",
    "addr:postcode":"33135",
    "addr:street":"W Flagler St",
    "iso:country":"US",
    "sg:address":"1732 W Flagler St",
    "sg:city":"Miami",
    "sg:classifiers":[
        {
            "category":"Shopping",
            "subcategory":"Clothing, Apparel, & Fashions",
            "type":"Retail Goods"
        },
        {
            "category":"Shopping",
            "subcategory":"Crafts & Fabrics",
            "type":"Retail Goods"
        },
        {
            "category":"Professional",
            "subcategory":"Printing & Photocopies",
            "type":"Services"
        }
    ],
    "sg:phone":"+1 305 649 1303",
    "sg:postcode":"33135",
    "sg:province":"FL",
    "sg:tags":[
        "shop",
        "clothing",
        "screen",
        "sportswear",
        "t-shirt",
        "merchandise",
        "apparel",
        "racing",
        "store"
    ],
    "sg:website":"http://www.alinasportswear.com",
    "wof:name":"Alina Sportswear",
    "wof:placetype":"venue"
},
  "geometry": {"coordinates":[-80.223488,25.772869],"type":"Point"}
}