{
  "type": "Feature",
  "properties": {
    "addr:full":"8016 NW 66th St Miami FL 33166",
    "addr:housenumber":"8016",
    "addr:postcode":"33166",
    "addr:street":"Nw 66Th St",
    "iso:country":"US",
    "sg:address":"8016 NW 66th St",
    "sg:city":"Miami",
    "sg:classifiers":[
        {
            "category":"Wholesale",
            "subcategory":"Non-durable Goods",
            "type":"Manufacturing & Wholesale Goods"
        }
    ],
    "sg:phone":"+1 305 471 5122",
    "sg:postcode":"33166",
    "sg:province":"FL",
    "wof:name":"Li Da Trading USA Inc",
    "wof:placetype":"venue"
},
  "geometry": {"coordinates":[-80.32672100000001,25.833409],"type":"Point"}
}