{
  "type": "Feature",
  "properties": {
    "addr:full":"15 SE 1st Ave Gainesville FL 32601",
    "addr:housenumber":"15",
    "addr:postcode":"32601",
    "addr:street":"Se 1St Ave",
    "iso:country":"US",
    "sg:address":"15 SE 1st Ave",
    "sg:city":"Gainesville",
    "sg:classifiers":[
        {
            "category":"Organizations",
            "subcategory":"Community Association",
            "type":"Services"
        }
    ],
    "sg:phone":"+1 352 392 4493",
    "sg:postcode":"32601",
    "sg:province":"FL",
    "wof:name":"Wic",
    "wof:placetype":"venue"
},
  "geometry": {"coordinates":[-82.324842,29.65106],"type":"Point"}
}