{
  "type": "Feature",
  "properties": {
    "iso:country":"US",
    "sg:address":"800 14th St",
    "sg:city":"Key West",
    "sg:classifiers":[
        {
            "category":"Retail",
            "subcategory":"Auto Repair",
            "type":"Services"
        }
    ],
    "sg:phone":"+1 305 292 2266",
    "sg:postcode":"33040",
    "sg:province":"FL",
    "sg:tags":[
        "general"
    ],
    "wof:name":"Friendly Automotive",
    "wof:placetype":"venue"
},
  "geometry": {"coordinates":[-81.767056,24.569297],"type":"Point"}
}