{
  "type": "Feature",
  "properties": {
    "iso:country":"US",
    "sg:address":"5144 Spring Run Ave",
    "sg:city":"Orlando",
    "sg:classifiers":[
        {
            "category":"Shopping",
            "subcategory":"Gifts & Souvenirs",
            "type":"Retail Goods"
        }
    ],
    "sg:phone":"+1 407 299 9317",
    "sg:postcode":"32819",
    "sg:province":"FL",
    "wof:name":"Kardz N Things Inc",
    "wof:placetype":"venue"
},
  "geometry": {"coordinates":[-81.484936,28.489189],"type":"Point"}
}