{
  "type": "Feature",
  "properties": {
    "addr:full":"18836 Maisons Dr Lutz FL 33558",
    "addr:housenumber":"18836",
    "addr:postcode":"33558",
    "addr:street":"Dr",
    "iso:country":"US",
    "sg:address":"18836 Maisons Dr",
    "sg:city":"Lutz",
    "sg:classifiers":[
        {
            "category":"Real Estate",
            "subcategory":"Real Estate Agent",
            "type":"Services"
        }
    ],
    "sg:phone":"+1 813 215 7262",
    "sg:postcode":"33558",
    "sg:province":"FL",
    "sg:tags":[
        "inspection"
    ],
    "wof:name":"All County Home Inspectors",
    "wof:placetype":"venue"
},
  "geometry": {"coordinates":[-82.542883,28.143318],"type":"Point"}
}