{
  "type": "Feature",
  "properties": {
    "iso:country":"US",
    "sg:address":"1020 Orca Ct",
    "sg:city":"Holiday",
    "sg:classifiers":[
        {
            "category":"Health Services",
            "subcategory":"Clinic",
            "type":"Services"
        }
    ],
    "sg:phone":"+1 727 518 0681",
    "sg:postcode":"34691",
    "sg:province":"FL",
    "sg:tags":[
        "welfare"
    ],
    "wof:name":"Kasun Home Health",
    "wof:placetype":"venue"
},
  "geometry": {"coordinates":[-82.776939,28.173932],"type":"Point"}
}