{
  "type": "Feature",
  "properties": {
    "iso:country":"US",
    "sg:address":"752 W Flagler St",
    "sg:city":"Miami",
    "sg:classifiers":[
        {
            "category":"Professional",
            "type":"Services"
        }
    ],
    "sg:phone":"+1 305 326 1510",
    "sg:postcode":"33130",
    "sg:province":"FL",
    "sg:tags":[
        "establishment"
    ],
    "wof:name":"Body & Soul",
    "wof:placetype":"venue"
},
  "geometry": {"coordinates":[-80.206907,25.773671],"type":"Point"}
}