{
  "type": "Feature",
  "properties": {
    "addr:full":"1410 SE St Lucie Blvd Fort Pierce FL 34996",
    "addr:housenumber":"1410",
    "addr:postcode":"34996",
    "addr:street":"Se St Lucie Blvd",
    "iso:country":"US",
    "sg:address":"1410 SE St Lucie Blvd",
    "sg:city":"Fort Pierce",
    "sg:classifiers":[
        {
            "category":"Banks & Credit Unions",
            "subcategory":"Bank",
            "type":"Services"
        }
    ],
    "sg:phone":"+1 772 467 2280",
    "sg:postcode":"34996",
    "sg:province":"FL",
    "wof:name":"Wachovia Bank",
    "wof:placetype":"venue"
},
  "geometry": {"coordinates":[-80.211348,27.187644],"type":"Point"}
}