{
  "type": "Feature",
  "properties": {
    "addr:full":"172 Woodhaven Cir E Ormond Beach FL 32174",
    "addr:housenumber":"172",
    "addr:postcode":"32174",
    "addr:street":"Woodhaven Cir E",
    "iso:country":"US",
    "sg:address":"172 Woodhaven Cir E",
    "sg:city":"Ormond Beach",
    "sg:classifiers":[
        {
            "category":"Building & Trades",
            "subcategory":"Landscaping Services",
            "type":"Services"
        }
    ],
    "sg:phone":"+1 386 673 0554",
    "sg:postcode":"32174",
    "sg:province":"FL",
    "wof:name":"Diamond Lawn Service",
    "wof:placetype":"venue"
},
  "geometry": {"coordinates":[-81.217174,29.246481],"type":"Point"}
}