{
  "type": "Feature",
  "properties": {
    "iso:country":"US",
    "sg:address":"1295 W Bay Dr",
    "sg:city":"Largo",
    "sg:classifiers":[
        {
            "category":"Health Services",
            "subcategory":"Doctor",
            "type":"Services"
        }
    ],
    "sg:phone":"+1 727 559 9811",
    "sg:postcode":"33770",
    "sg:province":"FL",
    "sg:tags":[
        "physician",
        "surgeon",
        "medical"
    ],
    "wof:name":"Aesthetic Institute Of West Fl",
    "wof:placetype":"venue"
},
  "geometry": {"coordinates":[-82.80153900000001,27.916675],"type":"Point"}
}