{
  "type": "Feature",
  "properties": {
    "addr:full":"1250 W Hillsboro Blvd Deerfield Beach FL 33442",
    "addr:housenumber":"1250",
    "addr:postcode":"33442",
    "addr:street":"W Hillsboro Blvd",
    "iso:country":"US",
    "sg:address":"1250 W Hillsboro Blvd",
    "sg:city":"Deerfield Beach",
    "sg:classifiers":[
        {
            "category":"Restaurant",
            "type":"Food & Drink"
        }
    ],
    "sg:menulink":"http://www.allmenus.com/fl/deerfield-beach/49363-dennys/menu/",
    "sg:phone":"+1 954 428 3934",
    "sg:postcode":"33442",
    "sg:province":"FL",
    "sg:tags":[
        "american",
        "diner"
    ],
    "wof:name":"Denny's",
    "wof:placetype":"venue"
},
  "geometry": {"coordinates":[-80.120772,26.317934],"type":"Point"}
}