{
  "type": "Feature",
  "properties": {
    "iso:country":"US",
    "sg:address":"130 NE 40th St",
    "sg:city":"Miami",
    "sg:classifiers":[
        {
            "category":"Home & Garden",
            "subcategory":"Furniture",
            "type":"Retail Goods"
        }
    ],
    "sg:phone":"+1 305 576 6652",
    "sg:postcode":"33137",
    "sg:province":"FL",
    "sg:tags":[
        "equipment",
        "kitchen",
        "cabinet"
    ],
    "wof:name":"Rotpunkt Kitchens",
    "wof:placetype":"venue"
},
  "geometry": {"coordinates":[-80.191948,25.813364],"type":"Point"}
}