{
  "type": "Feature",
  "properties": {
    "iso:country":"US",
    "sg:address":"4210 US Hwy 1",
    "sg:city":"Rockledge",
    "sg:classifiers":[
        {
            "category":"Retail",
            "subcategory":"Animal Services",
            "type":"Services"
        }
    ],
    "sg:phone":"+1 321 636 7387",
    "sg:postcode":"32955",
    "sg:province":"FL",
    "sg:tags":[
        "pet",
        "boarding",
        "sitting"
    ],
    "wof:name":"Barkingham Palace",
    "wof:placetype":"venue"
},
  "geometry": {"coordinates":[-80.690603,28.268716],"type":"Point"}
}