{
  "type": "Feature",
  "properties": {
    "addr:full":"545 Atlantic Blvd Atlantic Beach FL 32233",
    "addr:housenumber":"545",
    "addr:postcode":"32233",
    "addr:street":"Atlantic Blvd",
    "iso:country":"US",
    "sg:address":"545 Atlantic Blvd",
    "sg:city":"Atlantic Beach",
    "sg:classifiers":[
        {
            "category":"Shopping",
            "subcategory":"Jewelry",
            "type":"Retail Goods"
        }
    ],
    "sg:phone":"+1 904 270 0005",
    "sg:postcode":"32233",
    "sg:province":"FL",
    "sg:tags":[
        "designer"
    ],
    "wof:name":"Mc Gills",
    "wof:placetype":"venue"
},
  "geometry": {"coordinates":[-81.402878,30.324662],"type":"Point"}
}