{
  "type": "Feature",
  "properties": {
    "iso:country":"US",
    "sg:address":"2038 N Dale Mabry Hwy",
    "sg:city":"Tampa",
    "sg:classifiers":[
        {
            "category":"Restaurant",
            "type":"Food & Drink"
        }
    ],
    "sg:phone":"+1 813 875 2780",
    "sg:postcode":"33607",
    "sg:province":"FL",
    "wof:name":"Taco Bell",
    "wof:placetype":"venue"
},
  "geometry": {"coordinates":[-82.50552399999999,27.961232],"type":"Point"}
}