{
  "type": "Feature",
  "properties": {
    "iso:country":"US",
    "sg:address":"14411 S Dixie Hwy Ste 215",
    "sg:city":"Miami",
    "sg:classifiers":[
        {
            "category":"Building & Trades",
            "subcategory":"Construction",
            "type":"Services"
        }
    ],
    "sg:phone":"+1 305 234 9197",
    "sg:postcode":"33176",
    "sg:province":"FL",
    "sg:tags":[
        "contractor"
    ],
    "wof:name":"Turnkey Construction Co Inc",
    "wof:placetype":"venue"
},
  "geometry": {"coordinates":[-80.337502,25.6362],"type":"Point"}
}