{
  "type": "Feature",
  "properties": {
    "iso:country":"US",
    "sg:address":"502 NW 7th St",
    "sg:city":"Delray Beach",
    "sg:classifiers":[
        {
            "category":"Wholesale",
            "subcategory":"Durable Goods & Equipment",
            "type":"Manufacturing & Wholesale Goods"
        }
    ],
    "sg:phone":"+1 561 278 2607",
    "sg:postcode":"33444",
    "sg:province":"FL",
    "sg:tags":[
        "representative",
        "manufacturer"
    ],
    "wof:name":"R & D Assoc",
    "wof:placetype":"venue"
},
  "geometry": {"coordinates":[-80.079362,26.473187],"type":"Point"}
}