{
  "type": "Feature",
  "properties": {
    "addr:full":"3684 Jericho Dr Casselberry FL 32707",
    "addr:housenumber":"3684",
    "addr:postcode":"32707",
    "addr:street":"Jericho Dr",
    "iso:country":"US",
    "sg:address":"3684 Jericho Dr",
    "sg:city":"Casselberry",
    "sg:classifiers":[
        {
            "category":"Shopping",
            "type":"Retail Goods"
        }
    ],
    "sg:phone":"+1 407 695 0307",
    "sg:postcode":"32707",
    "sg:province":"FL",
    "sg:tags":[
        "merchandise"
    ],
    "wof:name":"Juan & Kathryn Cukier Crafts",
    "wof:placetype":"venue"
},
  "geometry": {"coordinates":[-81.294901,28.644351],"type":"Point"}
}