{
  "type": "Feature",
  "properties": {
    "addr:full":"1201 College Blvd Pensacola FL 32504",
    "addr:housenumber":"1201",
    "addr:postcode":"32504",
    "addr:street":"College Blvd",
    "iso:country":"US",
    "sg:address":"1201 College Blvd",
    "sg:city":"Pensacola",
    "sg:classifiers":[
        {
            "category":"Education",
            "subcategory":"Special Training",
            "type":"Public Place"
        },
        {
            "category":"Education",
            "subcategory":"School",
            "type":"Public Place"
        },
        {
            "category":"Sports & Exercise",
            "subcategory":"Playing Field",
            "type":"Entertainment"
        }
    ],
    "sg:phone":"+1 850 478 7060",
    "sg:postcode":"32504",
    "sg:province":"FL",
    "sg:tags":[
        "development",
        "educational",
        "personal",
        "private",
        "high",
        "k-"
    ],
    "wof:name":"Pace Ctr For Girls",
    "wof:placetype":"venue"
},
  "geometry": {"coordinates":[-87.19757799999999,30.4774],"type":"Point"}
}