{
  "type": "Feature",
  "properties": {
    "iso:country":"US",
    "sg:address":"459 US Hwy 27",
    "sg:city":"Lake Placid",
    "sg:classifiers":[
        {
            "category":"Shopping",
            "subcategory":"Gifts & Souvenirs",
            "type":"Retail Goods"
        }
    ],
    "sg:phone":"+1 863 699 1711",
    "sg:postcode":"33852",
    "sg:province":"FL",
    "sg:tags":[
        "shop"
    ],
    "wof:name":"Goodness Gracious Inc",
    "wof:placetype":"venue"
},
  "geometry": {"coordinates":[-81.358459,27.300637],"type":"Point"}
}