{
  "type": "Feature",
  "properties": {
    "iso:country":"US",
    "sg:address":"1404 W Swann Ave",
    "sg:city":"Tampa",
    "sg:classifiers":[
        {
            "category":"Building & Trades",
            "subcategory":"Landscaping Services",
            "type":"Services"
        }
    ],
    "sg:phone":"+1 813 258 1997",
    "sg:postcode":"33606",
    "sg:province":"FL",
    "sg:tags":[
        "designer",
        "landscape"
    ],
    "wof:name":"David Conner & Associates Inc",
    "wof:placetype":"venue"
},
  "geometry": {"coordinates":[-82.474743,27.937238],"type":"Point"}
}