{
  "type": "Feature",
  "properties": {
    "iso:country":"US",
    "sg:address":"3908 W 12th Ave",
    "sg:city":"Hialeah",
    "sg:classifiers":[
        {
            "category":"Shopping",
            "subcategory":"Shoes",
            "type":"Retail Goods"
        }
    ],
    "sg:phone":"+1 305 828 5575",
    "sg:postcode":"33012",
    "sg:province":"FL",
    "wof:name":"Nice Shoes Inc",
    "wof:placetype":"venue"
},
  "geometry": {"coordinates":[-80.306686,25.858163],"type":"Point"}
}