{
  "type": "Feature",
  "properties": {
    "iso:country":"US",
    "sg:address":"400 Signorelli Dr",
    "sg:city":"Nokomis",
    "sg:classifiers":[
        {
            "category":"Professional",
            "type":"Services"
        }
    ],
    "sg:phone":"+1 941 483 9117",
    "sg:postcode":"34275",
    "sg:province":"FL",
    "wof:name":"Prisco Services Inc",
    "wof:placetype":"venue"
},
  "geometry": {"coordinates":[-82.46484,27.164811],"type":"Point"}
}