{
  "type": "Feature",
  "properties": {
    "addr:full":"12372 Quail Roost Dr Miami FL 33177",
    "addr:housenumber":"12372",
    "addr:postcode":"33177",
    "addr:street":"Quail Roost Dr",
    "iso:country":"US",
    "sg:address":"12372 Quail Roost Dr",
    "sg:city":"Miami",
    "sg:classifiers":[
        {
            "category":"Restaurant",
            "type":"Food & Drink"
        }
    ],
    "sg:phone":"+1 305 971 2554",
    "sg:postcode":"33177",
    "sg:province":"FL",
    "wof:name":"Los Helechos Corp",
    "wof:placetype":"venue"
},
  "geometry": {"coordinates":[-80.392447,25.581616],"type":"Point"}
}