{
  "type": "Feature",
  "properties": {
    "iso:country":"US",
    "sg:address":"9202 N 30th St",
    "sg:city":"Tampa",
    "sg:classifiers":[
        {
            "category":"Travel",
            "subcategory":"Hotels & Motels",
            "type":"Entertainment"
        }
    ],
    "sg:phone":"+1 813 930 6900",
    "sg:postcode":"33612",
    "sg:province":"FL",
    "wof:name":"Baymont Inn & Suites",
    "wof:placetype":"venue"
},
  "geometry": {"coordinates":[-82.426194,28.036248],"type":"Point"}
}