{
  "type": "Feature",
  "properties": {
    "addr:full":"1430 Valentine St Melbourne FL 32901",
    "addr:housenumber":"1430",
    "addr:postcode":"32901",
    "addr:street":"Valentine St",
    "iso:country":"US",
    "sg:address":"1430 Valentine St",
    "sg:city":"Melbourne",
    "sg:classifiers":[
        {
            "category":"Health Services",
            "subcategory":"Doctor",
            "type":"Services"
        }
    ],
    "sg:phone":"+1 321 725 5300",
    "sg:postcode":"32901",
    "sg:province":"FL",
    "sg:tags":[
        "medical"
    ],
    "wof:name":"Eugene M Shepherd MD",
    "wof:placetype":"venue"
},
  "geometry": {"coordinates":[-80.616873,28.085916],"type":"Point"}
}