{
  "type": "Feature",
  "properties": {
    "addr:full":"12133 96th Pl Seminole FL 33772",
    "addr:housenumber":"12133",
    "addr:postcode":"33772",
    "addr:street":"96Th Pl",
    "iso:country":"US",
    "sg:address":"12133 96th Pl",
    "sg:city":"Seminole",
    "sg:classifiers":[
        {
            "category":"Autos & Motor Vehicles",
            "subcategory":"Automobile Sales",
            "type":"Retail Goods"
        }
    ],
    "sg:phone":"+1 727 399 1737",
    "sg:postcode":"33772",
    "sg:province":"FL",
    "sg:tags":[
        "dealers-used",
        "car",
        "used",
        "cars-wholesale"
    ],
    "wof:name":"Bates Used Cars Inc",
    "wof:placetype":"venue"
},
  "geometry": {"coordinates":[-82.80541599999999,27.860813],"type":"Point"}
}