{
  "type": "Feature",
  "properties": {
    "addr:full":"8811 Mathog Rd Riverview FL 33578",
    "addr:housenumber":"8811",
    "addr:postcode":"33578",
    "addr:street":"Mathog Rd",
    "iso:country":"US",
    "sg:address":"8811 Mathog Rd",
    "sg:city":"Riverview",
    "sg:classifiers":[
        {
            "category":"Home & Garden",
            "subcategory":"Kitchen Supply",
            "type":"Retail Goods"
        }
    ],
    "sg:phone":"+1 813 240 3721",
    "sg:postcode":"33578",
    "sg:province":"FL",
    "sg:tags":[
        "concession",
        "concessionaire"
    ],
    "wof:name":"Gold Concession",
    "wof:placetype":"venue"
},
  "geometry": {"coordinates":[-82.333343,27.862787],"type":"Point"}
}