{
  "type": "Feature",
  "properties": {
    "addr:full":"230 N Tropical Trl Merritt Island FL 32953",
    "addr:housenumber":"230",
    "addr:postcode":"32953",
    "addr:street":"N Tropical Trl",
    "iso:country":"US",
    "sg:address":"230 N Tropical Trl",
    "sg:city":"Merritt Island",
    "sg:classifiers":[
        {
            "category":"Shopping",
            "subcategory":"Shoes",
            "type":"Retail Goods"
        }
    ],
    "sg:phone":"+1 321 456 5950",
    "sg:postcode":"32953",
    "sg:province":"FL",
    "sg:tags":[
        "store"
    ],
    "wof:name":"A-1 Uniforms",
    "wof:placetype":"venue"
},
  "geometry": {"coordinates":[-80.70610000000001,28.3599],"type":"Point"}
}