{
  "type": "Feature",
  "properties": {
    "addr:full":"124 Inlets Blvd Nokomis FL 34275",
    "addr:housenumber":"124",
    "addr:postcode":"34275",
    "addr:street":"Inlets Blvd",
    "iso:country":"US",
    "sg:address":"124 Inlets Blvd",
    "sg:city":"Nokomis",
    "sg:classifiers":[
        {
            "category":"Real Estate",
            "subcategory":"Real Estate Services",
            "type":"Services"
        },
        {
            "category":"Real Estate",
            "subcategory":"Real Estate Agent",
            "type":"Services"
        }
    ],
    "sg:phone":"+1 941 484 5188",
    "sg:postcode":"34275",
    "sg:province":"FL",
    "sg:tags":[
        "buyer",
        "broker"
    ],
    "wof:name":"Pabek Realty",
    "wof:placetype":"venue"
},
  "geometry": {"coordinates":[-82.4622,27.133347],"type":"Point"}
}