{
  "type": "Feature",
  "properties": {
    "iso:country":"US",
    "sg:address":"1928 Rose St",
    "sg:city":"Sarasota",
    "sg:classifiers":[
        {
            "category":"Building & Trades",
            "subcategory":"Landscaping Services",
            "type":"Services"
        }
    ],
    "sg:phone":"+1 941 232 2144",
    "sg:postcode":"34239",
    "sg:province":"FL",
    "sg:tags":[
        "clearing",
        "trimming",
        "tree",
        "spraying"
    ],
    "wof:name":"Branch Brothers Tree Service",
    "wof:placetype":"venue"
},
  "geometry": {"coordinates":[-82.532251,27.306651],"type":"Point"}
}