{
  "type": "Feature",
  "properties": {
    "iso:country":"US",
    "sg:address":"1025 W University Ave",
    "sg:city":"Gainesville",
    "sg:classifiers":[
        {
            "category":"Shopping",
            "subcategory":"Books",
            "type":"Retail Goods"
        }
    ],
    "sg:phone":"+1 352 377 0044",
    "sg:postcode":"32601",
    "sg:province":"FL",
    "sg:tags":[
        "dealer"
    ],
    "wof:name":"Third Stone",
    "wof:placetype":"venue"
},
  "geometry": {"coordinates":[-82.335787,29.651988],"type":"Point"}
}