{
  "type": "Feature",
  "properties": {
    "iso:country":"US",
    "sg:address":"4520 SE 62nd St",
    "sg:city":"Ocala",
    "sg:classifiers":[
        {
            "category":"Building & Trades",
            "subcategory":"Landscaping Services",
            "type":"Services"
        }
    ],
    "sg:phone":"+1 352 622 2170",
    "sg:postcode":"34480",
    "sg:province":"FL",
    "wof:name":"Chad C Cannaday Inc",
    "wof:placetype":"venue"
},
  "geometry": {"coordinates":[-82.07713699999999,29.125125],"type":"Point"}
}