{
  "type": "Feature",
  "properties": {
    "addr:full":"15501 Bruce B Downs Blvd Tampa FL 33647",
    "addr:housenumber":"15501",
    "addr:postcode":"33647",
    "addr:street":"Bruce B Downs Blvd",
    "iso:country":"US",
    "sg:address":"15501 Bruce B Downs Blvd",
    "sg:city":"Tampa",
    "sg:classifiers":[
        {
            "category":"Real Estate",
            "subcategory":"Real Estate Services",
            "type":"Services"
        }
    ],
    "sg:phone":"+1 866 519 7037",
    "sg:postcode":"33647",
    "sg:province":"FL",
    "sg:tags":[
        "apartment",
        "management",
        "rental",
        "finder"
    ],
    "sg:website":"http://tampabay.citysearch.com/profile/external/602964192/tampa_fl/cypress_run_at_tampa_palms.html?publisher=yellowpages&reference_id=1&placement=ypwebsitemip",
    "wof:name":"Cypress Run at Tampa Palms",
    "wof:placetype":"venue"
},
  "geometry": {"coordinates":[-82.40714,28.08892],"type":"Point"}
}