{
  "type": "Feature",
  "properties": {
    "addr:full":"4393 Old Bayou Trl Destin FL 32541",
    "addr:housenumber":"4393",
    "addr:postcode":"32541",
    "addr:street":"Old Bayou Trl",
    "iso:country":"US",
    "sg:address":"4393 Old Bayou Trl",
    "sg:city":"Destin",
    "sg:classifiers":[
        {
            "category":"Professional",
            "subcategory":"Business Services",
            "type":"Services"
        }
    ],
    "sg:phone":"+1 850 650 4804",
    "sg:postcode":"32541",
    "sg:province":"FL",
    "wof:name":"Wamble Enterprises Inc",
    "wof:placetype":"venue"
},
  "geometry": {"coordinates":[-86.44583299999999,30.400435],"type":"Point"}
}