{
  "type": "Feature",
  "properties": {
    "addr:full":"96 W Dearborn St Englewood FL 34223",
    "addr:housenumber":"96",
    "addr:postcode":"34223",
    "addr:street":"W Dearborn St",
    "iso:country":"US",
    "sg:address":"96 W Dearborn St",
    "sg:city":"Englewood",
    "sg:classifiers":[
        {
            "category":"Professional",
            "subcategory":"Lawyer & Legal Services",
            "type":"Services"
        }
    ],
    "sg:phone":"+1 941 475 6756",
    "sg:postcode":"34223",
    "sg:province":"FL",
    "sg:website":"www.lemonbayplayhouse.com",
    "wof:name":"Lemon Bay Playhouse Inc",
    "wof:placetype":"venue"
},
  "geometry": {"coordinates":[-82.35493200000001,26.962178],"type":"Point"}
}