{
  "type": "Feature",
  "properties": {
    "iso:country":"US",
    "sg:address":"7869 W 26th Ave",
    "sg:city":"Hialeah",
    "sg:classifiers":[
        {
            "category":"Professional",
            "type":"Services"
        }
    ],
    "sg:phone":"+1 305 825 9983",
    "sg:postcode":"33016",
    "sg:province":"FL",
    "sg:tags":[
        "establishment"
    ],
    "wof:name":"Agrilawn",
    "wof:placetype":"venue"
},
  "geometry": {"coordinates":[-80.336072,25.894382],"type":"Point"}
}