{
  "type": "Feature",
  "properties": {
    "addr:full":"1875 W Co Rd 419 Chuluota FL 32766",
    "addr:housenumber":"1875",
    "addr:postcode":"32766",
    "addr:street":"W Co Rd 419",
    "iso:country":"US",
    "sg:address":"1875 W Co Rd 419",
    "sg:city":"Chuluota",
    "sg:classifiers":[
        {
            "category":"Restaurant",
            "type":"Food & Drink"
        }
    ],
    "sg:phone":"+1 407 595 8233",
    "sg:postcode":"32766",
    "sg:province":"FL",
    "wof:name":"Cafe Laura",
    "wof:placetype":"venue"
},
  "geometry": {"coordinates":[-81.169117,28.65498],"type":"Point"}
}