{
  "type": "Feature",
  "properties": {
    "iso:country":"US",
    "sg:address":"3894 Tampa Rd",
    "sg:city":"Oldsmar",
    "sg:classifiers":[
        {
            "category":"Insurance",
            "subcategory":"Insurance Agent",
            "type":"Services"
        }
    ],
    "sg:phone":"+1 813 855 6639",
    "sg:postcode":"34677",
    "sg:province":"FL",
    "wof:name":"Schmalz Insurance",
    "wof:placetype":"venue"
},
  "geometry": {"coordinates":[-82.67052700000001,28.041023],"type":"Point"}
}