{
  "type": "Feature",
  "properties": {
    "addr:full":"325 Indian River Ave Titusville FL 32796",
    "addr:housenumber":"325",
    "addr:postcode":"32796",
    "addr:street":"Indian River Ave",
    "iso:country":"US",
    "sg:address":"325 Indian River Ave",
    "sg:city":"Titusville",
    "sg:classifiers":[
        {
            "category":"Professional",
            "subcategory":"Lawyer & Legal Services",
            "type":"Services"
        }
    ],
    "sg:phone":"+1 321 267 1330",
    "sg:postcode":"32796",
    "sg:province":"FL",
    "sg:tags":[
        "attorney"
    ],
    "wof:name":"James T Harper Jr",
    "wof:placetype":"venue"
},
  "geometry": {"coordinates":[-80.805655,28.61565],"type":"Point"}
}