{
  "type": "Feature",
  "properties": {
    "iso:country":"US",
    "sg:address":"4400 NW 19th Ave",
    "sg:city":"Pompano Beach",
    "sg:classifiers":[
        {
            "category":"Shopping",
            "subcategory":"Computers & Home Electronics",
            "type":"Retail Goods"
        }
    ],
    "sg:phone":"+1 954 970 9611",
    "sg:postcode":"33064",
    "sg:province":"FL",
    "sg:tags":[
        "equipment",
        "dealer"
    ],
    "wof:name":"Computer Data-Com Remarketing",
    "wof:placetype":"venue"
},
  "geometry": {"coordinates":[-80.149754,26.284506],"type":"Point"}
}