{
  "type": "Feature",
  "properties": {
    "addr:full":"14260 SW 36th St Miami FL 33175",
    "addr:housenumber":"14260",
    "addr:postcode":"33175",
    "addr:street":"Sw 36Th St",
    "iso:country":"US",
    "sg:address":"14260 SW 36th St",
    "sg:city":"Miami",
    "sg:classifiers":[
        {
            "category":"Wholesale",
            "subcategory":"Non-durable Goods",
            "type":"Manufacturing & Wholesale Goods"
        },
        {
            "category":"Manufacturing",
            "subcategory":"Chemicals & Compounds",
            "type":"Manufacturing & Wholesale Goods"
        },
        {
            "category":"Building & Trades",
            "subcategory":"Cleaning & Sanitation",
            "type":"Services"
        },
        {
            "category":"Home & Garden",
            "subcategory":"Hardware",
            "type":"Retail Goods"
        },
        {
            "category":"Shopping",
            "subcategory":"Department Store",
            "type":"Retail Goods"
        }
    ],
    "sg:phone":"+1 305 448 5670",
    "sg:postcode":"33175",
    "sg:province":"FL",
    "sg:tags":[
        "cleaner",
        "supply",
        "house",
        "equipment",
        "chemicals-wholesale",
        "janitor",
        "supplies-wholesale",
        "manufacturer"
    ],
    "wof:name":"U S A Chemical Int'l Inc",
    "wof:placetype":"venue"
},
  "geometry": {"coordinates":[-80.424412,25.734131],"type":"Point"}
}