{
  "type": "Feature",
  "properties": {
    "addr:full":"13960 NW 60th Ave Hialeah FL 33014",
    "addr:housenumber":"13960",
    "addr:postcode":"33014",
    "addr:street":"Nw 60Th Ave",
    "iso:country":"US",
    "sg:address":"13960 NW 60th Ave",
    "sg:city":"Hialeah",
    "sg:classifiers":[
        {
            "category":"Professional",
            "type":"Services"
        }
    ],
    "sg:phone":"+1 305 557 3236",
    "sg:postcode":"33014",
    "sg:province":"FL",
    "sg:tags":[
        "establishment"
    ],
    "wof:name":"Fired Up 2K",
    "wof:placetype":"venue"
},
  "geometry": {"coordinates":[-80.29831,25.901788],"type":"Point"}
}