{
  "type": "Feature",
  "properties": {
    "iso:country":"US",
    "sg:address":"9567 Harding Ave",
    "sg:city":"Miami Beach",
    "sg:classifiers":[
        {
            "category":"Shopping",
            "subcategory":"Clothing, Apparel, & Fashions",
            "type":"Retail Goods"
        }
    ],
    "sg:phone":"+1 305 864 3049",
    "sg:postcode":"33154",
    "sg:province":"FL",
    "sg:tags":[
        "ready"
    ],
    "wof:name":"Normans",
    "wof:placetype":"venue"
},
  "geometry": {"coordinates":[-80.123542,25.885833],"type":"Point"}
}