{
  "type": "Feature",
  "properties": {
    "addr:full":"1275 Cleveland St Clearwater FL 33755",
    "addr:housenumber":"1275",
    "addr:postcode":"33755",
    "addr:street":"Cleveland St",
    "iso:country":"US",
    "sg:address":"1275 Cleveland St",
    "sg:city":"Clearwater",
    "sg:classifiers":[
        {
            "category":"Professional",
            "subcategory":"Secretarial Services",
            "type":"Services"
        }
    ],
    "sg:phone":"+1 727 441 2404",
    "sg:postcode":"33755",
    "sg:province":"FL",
    "sg:tags":[
        "convention",
        "court",
        "reporter"
    ],
    "wof:name":"Deborah Kurtz & Assoc",
    "wof:placetype":"venue"
},
  "geometry": {"coordinates":[-82.78520399999999,27.965562],"type":"Point"}
}