{
  "type": "Feature",
  "properties": {
    "iso:country":"US",
    "sg:address":"9130 S Dadeland Blvd",
    "sg:city":"Miami",
    "sg:classifiers":[
        {
            "category":"Banks & Credit Unions",
            "subcategory":"Financial Services",
            "type":"Services"
        }
    ],
    "sg:phone":"+1 305 670 4433",
    "sg:postcode":"33156",
    "sg:province":"FL",
    "sg:tags":[
        "broker",
        "mortgage"
    ],
    "wof:name":"Prime Equity Lenders Llc",
    "wof:placetype":"venue"
},
  "geometry": {"coordinates":[-80.31497299999999,25.685142],"type":"Point"}
}