{
  "type": "Feature",
  "properties": {
    "addr:full":"2970 NW 22nd St Miami FL 33142",
    "addr:housenumber":"2970",
    "addr:postcode":"33142",
    "addr:street":"Nw 22Nd St",
    "iso:country":"US",
    "sg:address":"2970 NW 22nd St",
    "sg:city":"Miami",
    "sg:classifiers":[
        {
            "category":"Building & Trades",
            "subcategory":"Electrical",
            "type":"Services"
        }
    ],
    "sg:phone":"+1 305 367 4474",
    "sg:postcode":"33142",
    "sg:province":"FL",
    "sg:tags":[
        "electrical",
        "contractor"
    ],
    "wof:name":"Spike Electric Inc",
    "wof:placetype":"venue"
},
  "geometry": {"coordinates":[-80.242653,25.796915],"type":"Point"}
}