{
  "type": "Feature",
  "properties": {
    "iso:country":"US",
    "sg:address":"19061 SE 92nd Ln",
    "sg:city":"Ocklawaha",
    "sg:classifiers":[
        {
            "category":"Building & Trades",
            "subcategory":"Landscaping Services",
            "type":"Services"
        }
    ],
    "sg:phone":"+1 352 288 5435",
    "sg:postcode":"32179",
    "sg:province":"FL",
    "sg:tags":[
        "sod",
        "sodding"
    ],
    "wof:name":"Acre Ranger Sod",
    "wof:placetype":"venue"
},
  "geometry": {"coordinates":[-81.84144499999999,29.086657],"type":"Point"}
}