{
  "type": "Feature",
  "properties": {
    "iso:country":"US",
    "sg:address":"1000 E 1st St",
    "sg:city":"Sanford",
    "sg:classifiers":[
        {
            "category":"Organizations",
            "subcategory":"Religious Organization",
            "type":"Services"
        }
    ],
    "sg:phone":"+1 407 323 3430",
    "sg:postcode":"32771",
    "sg:province":"FL",
    "wof:name":"New Tribes Mission",
    "wof:placetype":"venue"
},
  "geometry": {"coordinates":[-81.25679,28.81144],"type":"Point"}
}