{
  "type": "Feature",
  "properties": {
    "addr:full":"7605 Conroy Windermere Rd Orlando FL 32835",
    "addr:housenumber":"7605",
    "addr:postcode":"32835",
    "addr:street":"Conroy Windermere Rd",
    "iso:country":"US",
    "sg:address":"7605 Conroy Windermere Rd",
    "sg:city":"Orlando",
    "sg:classifiers":[
        {
            "category":"Education",
            "subcategory":"School",
            "type":"Public Place"
        }
    ],
    "sg:phone":"+1 407 447 5511",
    "sg:postcode":"32835",
    "sg:province":"FL",
    "wof:name":"Magic Forest Institute",
    "wof:placetype":"venue"
},
  "geometry": {"coordinates":[-81.485179,28.493771],"type":"Point"}
}