{
  "type": "Feature",
  "properties": {
    "iso:country":"US",
    "sg:address":"14811 N 15th St",
    "sg:city":"Lutz",
    "sg:classifiers":[
        {
            "category":"Organizations",
            "subcategory":"Religious Organization",
            "type":"Services"
        }
    ],
    "sg:phone":"+1 813 971 8330",
    "sg:postcode":"33549",
    "sg:province":"FL",
    "sg:tags":[
        "church"
    ],
    "wof:name":"Church Of God North Tampa",
    "wof:placetype":"venue"
},
  "geometry": {"coordinates":[-82.442988,28.087128],"type":"Point"}
}