{
  "type": "Feature",
  "properties": {
    "addr:full":"102 1st Ave E Havana FL 32333",
    "addr:housenumber":"102",
    "addr:postcode":"32333",
    "addr:street":"1St Ave E",
    "iso:country":"US",
    "sg:address":"102 1st Ave E",
    "sg:city":"Havana",
    "sg:classifiers":[
        {
            "category":"Food & Beverages",
            "subcategory":"Groceries & Convenience Stores",
            "type":"Retail Goods"
        }
    ],
    "sg:phone":"+1 850 539 5827",
    "sg:postcode":"32333",
    "sg:province":"FL",
    "sg:tags":[
        "grocer"
    ],
    "wof:name":"Harvey's Supermarket",
    "wof:placetype":"venue"
},
  "geometry": {"coordinates":[-84.41556,30.63121],"type":"Point"}
}