{
  "type": "Feature",
  "properties": {
    "iso:country":"US",
    "sg:address":"2311 SW 51st Ct",
    "sg:city":"Fort Lauderdale",
    "sg:classifiers":[
        {
            "category":"Home & Garden",
            "subcategory":"Building Materials",
            "type":"Retail Goods"
        }
    ],
    "sg:phone":"+1 954 893 5608",
    "sg:postcode":"33312",
    "sg:province":"FL",
    "wof:name":"New Tech Glass Inc",
    "wof:placetype":"venue"
},
  "geometry": {"coordinates":[-80.17076,26.058649],"type":"Point"}
}