{
  "type": "Feature",
  "properties": {
    "iso:country":"US",
    "sg:address":"999 NW 51st St",
    "sg:city":"Boca Raton",
    "sg:classifiers":[
        {
            "category":"Banks & Credit Unions",
            "subcategory":"Investment Brokerage",
            "type":"Services"
        }
    ],
    "sg:phone":"+1 561 862 0134",
    "sg:postcode":"33431",
    "sg:province":"FL",
    "sg:tags":[
        "stock",
        "bond"
    ],
    "wof:name":"Geek Securities Inc",
    "wof:placetype":"venue"
},
  "geometry": {"coordinates":[-80.106404,26.394023],"type":"Point"}
}