{
  "type": "Feature",
  "properties": {
    "iso:country":"US",
    "sg:address":"1247 1st Ave N",
    "sg:city":"St Petersburg",
    "sg:classifiers":[
        {
            "category":"Professional",
            "subcategory":"Lawyer & Legal Services",
            "type":"Services"
        }
    ],
    "sg:phone":"+1 727 897 9495",
    "sg:postcode":"33705",
    "sg:province":"FL",
    "sg:tags":[
        "attorney"
    ],
    "wof:name":"Geoffrey R Cox Attorney At Law",
    "wof:placetype":"venue"
},
  "geometry": {"coordinates":[-82.65033099999999,27.772081],"type":"Point"}
}