{
  "type": "Feature",
  "properties": {
    "iso:country":"US",
    "sg:address":"1137 Londonderry Dr",
    "sg:city":"Orange Park",
    "sg:classifiers":[
        {
            "category":"Building & Trades",
            "subcategory":"Landscaping Services",
            "type":"Services"
        }
    ],
    "sg:phone":"+1 904 213 6537",
    "sg:postcode":"32065",
    "sg:province":"FL",
    "sg:tags":[
        "lawn",
        "maintenance",
        "grounds"
    ],
    "wof:name":"Designer Lawn Care & Landscape",
    "wof:placetype":"venue"
},
  "geometry": {"coordinates":[-81.76550899999999,30.138769],"type":"Point"}
}