{
  "type": "Feature",
  "properties": {
    "iso:country":"US",
    "sg:address":"609 E Central Blvd",
    "sg:city":"Orlando",
    "sg:classifiers":[
        {
            "category":"Professional",
            "subcategory":"Lawyer & Legal Services",
            "type":"Services"
        }
    ],
    "sg:phone":"+1 407 872 6816",
    "sg:postcode":"32801",
    "sg:province":"FL",
    "wof:name":"Weeden Roger L Atty",
    "wof:placetype":"venue"
},
  "geometry": {"coordinates":[-81.368549,28.542368],"type":"Point"}
}