{
  "type": "Feature",
  "properties": {
    "iso:country":"US",
    "sg:address":"91 Madison Dr",
    "sg:city":"Naples",
    "sg:classifiers":[
        {
            "category":"Building & Trades",
            "subcategory":"Construction",
            "type":"Services"
        }
    ],
    "sg:phone":"+1 239 594 9339",
    "sg:postcode":"34110",
    "sg:province":"FL",
    "sg:tags":[
        "hanging",
        "wallpaper",
        "contractor"
    ],
    "wof:name":"Mathy's Wallpapering",
    "wof:placetype":"venue"
},
  "geometry": {"coordinates":[-81.76732800000001,26.279634],"type":"Point"}
}