{
  "type": "Feature",
  "properties": {
    "iso:country":"US",
    "sg:address":"5049 NE 12th Ave",
    "sg:city":"Oakland Park",
    "sg:classifiers":[
        {
            "category":"Retail",
            "subcategory":"Repair Shop",
            "type":"Services"
        }
    ],
    "sg:phone":"+1 954 771 2505",
    "sg:postcode":"33334",
    "sg:province":"FL",
    "sg:tags":[
        "upholsterer"
    ],
    "wof:name":"Regal Upholstery",
    "wof:placetype":"venue"
},
  "geometry": {"coordinates":[-80.13137999999999,26.191937],"type":"Point"}
}