{
  "type": "Feature",
  "properties": {
    "addr:full":"6466 US Hwy 90 Milton FL 32570",
    "addr:housenumber":"6466",
    "addr:postcode":"32570",
    "addr:street":"Us Hwy 90",
    "iso:country":"US",
    "sg:address":"6466 US Hwy 90",
    "sg:city":"Milton",
    "sg:classifiers":[
        {
            "category":"Home & Garden",
            "subcategory":"Carpets & Floor Coverings",
            "type":"Retail Goods"
        }
    ],
    "sg:phone":"+1 850 983 0021",
    "sg:postcode":"32570",
    "sg:province":"FL",
    "wof:name":"Carpet & Tile Headquarters",
    "wof:placetype":"venue"
},
  "geometry": {"coordinates":[-87.063608,30.606347],"type":"Point"}
}