{
  "type": "Feature",
  "properties": {
    "addr:full":"798 107th Ave N Naples FL 34108",
    "addr:housenumber":"798",
    "addr:postcode":"34108",
    "addr:street":"107Th Ave N",
    "iso:country":"US",
    "sg:address":"798 107th Ave N",
    "sg:city":"Naples",
    "sg:classifiers":[
        {
            "category":"Real Estate",
            "subcategory":"Real Estate Agent",
            "type":"Services"
        }
    ],
    "sg:phone":"+1 239 597 5731",
    "sg:postcode":"34108",
    "sg:province":"FL",
    "sg:tags":[
        "management"
    ],
    "wof:name":"Gulf Winds Property Management",
    "wof:placetype":"venue"
},
  "geometry": {"coordinates":[-81.80945199999999,26.268753],"type":"Point"}
}