{
  "type": "Feature",
  "properties": {
    "addr:full":"899 W 18th St Hialeah FL 33010",
    "addr:housenumber":"899",
    "addr:postcode":"33010",
    "addr:street":"W 18Th St",
    "iso:country":"US",
    "sg:address":"899 W 18th St",
    "sg:city":"Hialeah",
    "sg:classifiers":[
        {
            "category":"Retail",
            "subcategory":"Repair Shop",
            "type":"Services"
        }
    ],
    "sg:phone":"+1 305 884 6414",
    "sg:postcode":"33010",
    "sg:province":"FL",
    "sg:tags":[
        "textile"
    ],
    "wof:name":"J C Cutting Svc",
    "wof:placetype":"venue"
},
  "geometry": {"coordinates":[-80.299199,25.838069],"type":"Point"}
}