{
  "type": "Feature",
  "properties": {
    "iso:country":"US",
    "sg:address":"1911 Okeechobee Rd",
    "sg:city":"Fort Pierce",
    "sg:classifiers":[
        {
            "category":"Retail",
            "subcategory":"Auto Repair",
            "type":"Services"
        }
    ],
    "sg:phone":"+1 772 461 6791",
    "sg:postcode":"34950",
    "sg:province":"FL",
    "sg:tags":[
        "repairing",
        "wheel",
        "lining",
        "brake",
        "automobile",
        "alignment"
    ],
    "wof:name":"Simons Wheel Alignment Inc",
    "wof:placetype":"venue"
},
  "geometry": {"coordinates":[-80.343453,27.442052],"type":"Point"}
}