{
  "type": "Feature",
  "properties": {
    "iso:country":"US",
    "sg:address":"1995 W Nasa Blvd",
    "sg:city":"Melbourne",
    "sg:classifiers":[
        {
            "category":"Health Services",
            "subcategory":"Doctor",
            "type":"Services"
        }
    ],
    "sg:phone":"+1 321 723 9885",
    "sg:postcode":"32904",
    "sg:province":"FL",
    "sg:tags":[
        "medical"
    ],
    "wof:name":"Bassin Center For Eyelid",
    "wof:placetype":"venue"
},
  "geometry": {"coordinates":[-80.654746,28.096052],"type":"Point"}
}