{
  "type": "Feature",
  "properties": {
    "addr:full":"1996 NE 8th St Homestead FL 33033",
    "addr:housenumber":"1996",
    "addr:postcode":"33033",
    "addr:street":"Ne 8Th St",
    "iso:country":"US",
    "sg:address":"1996 NE 8th St",
    "sg:city":"Homestead",
    "sg:classifiers":[
        {
            "category":"Wholesale",
            "subcategory":"Office Equipment",
            "type":"Manufacturing & Wholesale Goods"
        },
        {
            "category":"Shopping",
            "type":"Retail Goods"
        }
    ],
    "sg:phone":"+1 305 247 9700",
    "sg:postcode":"33033",
    "sg:province":"FL",
    "sg:tags":[
        "machine",
        "copy",
        "duplicating",
        "copying"
    ],
    "wof:name":"Copy Machine Specialists Inc",
    "wof:placetype":"venue"
},
  "geometry": {"coordinates":[-80.452742,25.477298],"type":"Point"}
}