{
  "type": "Feature",
  "properties": {
    "addr:full":"1106 Hospital Rd Fort Walton Bch FL 32547",
    "addr:housenumber":"1106",
    "addr:postcode":"32547",
    "addr:street":"Hospital Rd",
    "iso:country":"US",
    "sg:address":"1106 Hospital Rd",
    "sg:city":"Fort Walton Bch",
    "sg:classifiers":[
        {
            "category":"Health Services",
            "subcategory":"Doctor",
            "type":"Services"
        }
    ],
    "sg:phone":"+1 850 863 5655",
    "sg:postcode":"32547",
    "sg:province":"FL",
    "sg:tags":[
        "physician",
        "surgeon"
    ],
    "wof:name":"MRI Ctr",
    "wof:placetype":"venue"
},
  "geometry": {"coordinates":[-86.634197,30.455629],"type":"Point"}
}