{
  "type": "Feature",
  "properties": {
    "iso:country":"US",
    "sg:address":"16171 NW 57th Ave",
    "sg:city":"Miami Gardens",
    "sg:classifiers":[
        {
            "category":"Autos & Motor Vehicles",
            "subcategory":"Auto Supplies",
            "type":"Retail Goods"
        }
    ],
    "sg:phone":"+1 305 623 2884",
    "sg:postcode":"33014",
    "sg:province":"FL",
    "sg:tags":[
        "glass"
    ],
    "wof:name":"Affordable Auto Glass",
    "wof:placetype":"venue"
},
  "geometry": {"coordinates":[-80.29276900000001,25.920089],"type":"Point"}
}