{
  "type": "Feature",
  "properties": {
    "addr:full":"617 E Venice Ave Venice FL 34285",
    "addr:housenumber":"617",
    "addr:postcode":"34285",
    "addr:street":"E Venice Ave",
    "iso:country":"US",
    "sg:address":"617 E Venice Ave",
    "sg:city":"Venice",
    "sg:classifiers":[
        {
            "category":"Retail",
            "subcategory":"Repair Shop",
            "type":"Services"
        }
    ],
    "sg:phone":"+1 941 485 3894",
    "sg:postcode":"34285",
    "sg:province":"FL",
    "sg:tags":[
        "kitchen",
        "cabinet"
    ],
    "wof:name":"House Of Kitchens Baths & More",
    "wof:placetype":"venue"
},
  "geometry": {"coordinates":[-82.433916,27.09986],"type":"Point"}
}