{
  "type": "Feature",
  "properties": {
    "addr:full":"55 Causeway Blvd Clearwater FL 33767",
    "addr:housenumber":"55",
    "addr:postcode":"33767",
    "addr:street":"Causeway Blvd",
    "iso:country":"US",
    "sg:address":"55 Causeway Blvd",
    "sg:city":"Clearwater",
    "sg:classifiers":[
        {
            "category":"Recreation",
            "type":"Entertainment"
        }
    ],
    "sg:phone":"+1 727 461 4882",
    "sg:postcode":"33767",
    "sg:province":"FL",
    "wof:name":"Gypsy Charters Inc",
    "wof:placetype":"venue"
},
  "geometry": {"coordinates":[-82.8267,27.977161],"type":"Point"}
}