{
  "type": "Feature",
  "properties": {
    "iso:country":"US",
    "sg:address":"168 NW 51st St",
    "sg:city":"Boca Raton",
    "sg:classifiers":[
        {
            "category":"Shopping",
            "subcategory":"Clothing, Apparel, & Fashions",
            "type":"Retail Goods"
        }
    ],
    "sg:phone":"+1 561 241 1689",
    "sg:postcode":"33431",
    "sg:province":"FL",
    "sg:tags":[
        "alteration"
    ],
    "wof:name":"Boca Cleaners",
    "wof:placetype":"venue"
},
  "geometry": {"coordinates":[-80.08161699999999,26.39446],"type":"Point"}
}