{
  "type": "Feature",
  "properties": {
    "iso:country":"US",
    "sg:address":"260 Madeira Ave E",
    "sg:city":"Madeira Beach",
    "sg:classifiers":[
        {
            "category":"Building & Trades",
            "subcategory":"Construction",
            "type":"Services"
        }
    ],
    "sg:phone":"+1 727 392 7392",
    "sg:postcode":"33708",
    "sg:province":"FL",
    "sg:tags":[
        "contractor"
    ],
    "wof:name":"Joe Cassity Inc",
    "wof:placetype":"venue"
},
  "geometry": {"coordinates":[-82.79856599999999,27.801551],"type":"Point"}
}