{
  "type": "Feature",
  "properties": {
    "addr:full":"7470 W Commercial Blvd Lauderhill FL 33319",
    "addr:housenumber":"7470",
    "addr:postcode":"33319",
    "addr:street":"W Commercial Blvd",
    "iso:country":"US",
    "sg:address":"7470 W Commercial Blvd",
    "sg:city":"Lauderhill",
    "sg:classifiers":[
        {
            "category":"Shopping",
            "subcategory":"Department Store",
            "type":"Retail Goods"
        }
    ],
    "sg:phone":"+1 954 741 1588",
    "sg:postcode":"33319",
    "sg:province":"FL",
    "sg:tags":[
        "shop"
    ],
    "wof:name":"Dollar General",
    "wof:placetype":"venue"
},
  "geometry": {"coordinates":[-80.25013800000001,26.193629],"type":"Point"}
}