{
  "type": "Feature",
  "properties": {
    "iso:country":"US",
    "sg:address":"7720 Peters Rd",
    "sg:city":"Fort Lauderdale",
    "sg:classifiers":[
        {
            "category":"Food & Beverages",
            "subcategory":"Groceries & Convenience Stores",
            "type":"Retail Goods"
        },
        {
            "category":"Food & Beverages",
            "subcategory":"Specialty",
            "type":"Retail Goods"
        }
    ],
    "sg:phone":"+1 954 236 0600",
    "sg:postcode":"33324",
    "sg:province":"FL",
    "sg:tags":[
        "health",
        "diet"
    ],
    "wof:name":"Whole Foods Market Inc",
    "wof:placetype":"venue"
},
  "geometry": {"coordinates":[-80.250862,26.105353],"type":"Point"}
}