{
  "type": "Feature",
  "properties": {
    "addr:full":"12240 Orange River Blvd Fort Myers FL 33905",
    "addr:housenumber":"12240",
    "addr:postcode":"33905",
    "addr:street":"Orange River Blvd",
    "iso:country":"US",
    "sg:address":"12240 Orange River Blvd",
    "sg:city":"Fort Myers",
    "sg:classifiers":[
        {
            "category":"Farming",
            "subcategory":"Nursery",
            "type":"Manufacturing & Wholesale Goods"
        }
    ],
    "sg:phone":"+1 239 693 1347",
    "sg:postcode":"33905",
    "sg:province":"FL",
    "sg:tags":[
        "ornamental"
    ],
    "wof:name":"Brians Better Lawns & Garden",
    "wof:placetype":"venue"
},
  "geometry": {"coordinates":[-81.75415700000001,26.675795],"type":"Point"}
}