{
  "type": "Feature",
  "properties": {
    "iso:country":"US",
    "sg:address":"4711 95th St N",
    "sg:city":"St Petersburg",
    "sg:classifiers":[
        {
            "category":"Manufacturing",
            "subcategory":"Tools & Machinery",
            "type":"Manufacturing & Wholesale Goods"
        }
    ],
    "sg:phone":"+1 727 397 8130",
    "sg:postcode":"33708",
    "sg:province":"FL",
    "sg:tags":[
        "lift",
        "boat"
    ],
    "wof:name":"Pateco Inc",
    "wof:placetype":"venue"
},
  "geometry": {"coordinates":[-82.770903,27.818506],"type":"Point"}
}