{
  "type": "Feature",
  "properties": {
    "iso:country":"US",
    "sg:address":"9031 Sunset Dr",
    "sg:city":"Gulf Breeze",
    "sg:classifiers":[
        {
            "category":"Organizations",
            "subcategory":"Religious Organization",
            "type":"Services"
        }
    ],
    "sg:phone":"+1 850 939 4211",
    "sg:postcode":"32566",
    "sg:province":"FL",
    "sg:tags":[
        "church"
    ],
    "wof:name":"Living Word Evangelistic Assn",
    "wof:placetype":"venue"
},
  "geometry": {"coordinates":[-86.84304,30.417237],"type":"Point"}
}