{
  "type": "Feature",
  "properties": {
    "addr:full":"201 Parshley St SW Live Oak FL 32064",
    "addr:housenumber":"201",
    "addr:postcode":"32064",
    "addr:street":"Parshley St Sw",
    "iso:country":"US",
    "sg:address":"201 Parshley St SW",
    "sg:city":"Live Oak",
    "sg:classifiers":[
        {
            "category":"Health Services",
            "subcategory":"Hospital",
            "type":"Services"
        }
    ],
    "sg:phone":"+1 386 330 2086",
    "sg:postcode":"32064",
    "sg:province":"FL",
    "sg:tags":[
        "general"
    ],
    "wof:name":"Trinity Community Hospital",
    "wof:placetype":"venue"
},
  "geometry": {"coordinates":[-82.98788999999999,30.29461],"type":"Point"}
}