{
  "type": "Feature",
  "properties": {
    "iso:country":"US",
    "sg:address":"11603 N 22nd St",
    "sg:city":"Tampa",
    "sg:classifiers":[
        {
            "category":"Real Estate",
            "subcategory":"Real Estate Operator",
            "type":"Services"
        }
    ],
    "sg:phone":"+1 813 866 9168",
    "sg:postcode":"33612",
    "sg:province":"FL",
    "sg:tags":[
        "apartment"
    ],
    "wof:name":"Bentley Court Apartments",
    "wof:placetype":"venue"
},
  "geometry": {"coordinates":[-82.434488,28.054462],"type":"Point"}
}