{
  "type": "Feature",
  "properties": {
    "addr:full":"4221 Lafayette St Marianna FL 32446",
    "addr:housenumber":"4221",
    "addr:postcode":"32446",
    "addr:street":"Lafayette St",
    "iso:country":"US",
    "sg:address":"4221 Lafayette St",
    "sg:city":"Marianna",
    "sg:classifiers":[
        {
            "category":"Restaurant",
            "type":"Food & Drink"
        }
    ],
    "sg:menulink":"http://www.allmenus.com/fl/marianna/207051-sonic/menu/",
    "sg:phone":"+1 850 526 2069",
    "sg:postcode":"32446",
    "sg:province":"FL",
    "sg:tags":[
        "burger",
        "american"
    ],
    "wof:name":"Sonic",
    "wof:placetype":"venue"
},
  "geometry": {"coordinates":[-85.24376599999999,30.781299],"type":"Point"}
}