{
  "type": "Feature",
  "properties": {
    "iso:country":"US",
    "sg:address":"1803 Opa Locka Blvd",
    "sg:city":"Opa Locka",
    "sg:classifiers":[
        {
            "category":"Building & Trades",
            "subcategory":"Construction",
            "type":"Services"
        }
    ],
    "sg:phone":"+1 305 345 6247",
    "sg:postcode":"33054",
    "sg:province":"FL",
    "sg:tags":[
        "cabinet"
    ],
    "wof:name":"Yersaisy Marine",
    "wof:placetype":"venue"
},
  "geometry": {"coordinates":[-80.229525,25.899124],"type":"Point"}
}