{
  "type": "Feature",
  "properties": {
    "iso:country":"US",
    "sg:address":"3335 Stephanie Ln",
    "sg:city":"Ellenton",
    "sg:classifiers":[
        {
            "category":"Shopping",
            "subcategory":"Hobbies, Toys, & Games",
            "type":"Retail Goods"
        }
    ],
    "sg:phone":"+1 941 729 4833",
    "sg:postcode":"34222",
    "sg:province":"FL",
    "sg:tags":[
        "toy",
        "store",
        "supply"
    ],
    "wof:name":"Tr's Toys",
    "wof:placetype":"venue"
},
  "geometry": {"coordinates":[-82.498865,27.544159],"type":"Point"}
}