{
  "type": "Feature",
  "properties": {
    "addr:full":"791 Marseille Dr Indialantic FL 32903",
    "addr:housenumber":"791",
    "addr:postcode":"32903",
    "addr:street":"Marseille Dr",
    "iso:country":"US",
    "sg:address":"791 Marseille Dr",
    "sg:city":"Indialantic",
    "sg:classifiers":[
        {
            "category":"Retail",
            "subcategory":"Laundry & Dry Cleaning",
            "type":"Services"
        }
    ],
    "sg:phone":"+1 321 773 2881",
    "sg:postcode":"32903",
    "sg:province":"FL",
    "sg:tags":[
        "cleaners",
        "rug",
        "carpet"
    ],
    "wof:name":"A Able Magic Carpet Cleaning",
    "wof:placetype":"venue"
},
  "geometry": {"coordinates":[-80.587909,28.138347],"type":"Point"}
}