{
  "type": "Feature",
  "properties": {
    "addr:full":"608 Wisteria Ln Kissimmee FL 34747",
    "addr:housenumber":"608",
    "addr:postcode":"34747",
    "addr:street":"Wisteria Ln",
    "iso:country":"US",
    "sg:address":"608 Wisteria Ln",
    "sg:city":"Kissimmee",
    "sg:classifiers":[
        {
            "category":"Real Estate",
            "subcategory":"Real Estate Agent",
            "type":"Services"
        }
    ],
    "sg:phone":"+1 407 566 8846",
    "sg:postcode":"34747",
    "sg:province":"FL",
    "wof:name":"Trading Places Realty Inc",
    "wof:placetype":"venue"
},
  "geometry": {"coordinates":[-81.545872,28.311931],"type":"Point"}
}