{
  "type": "Feature",
  "properties": {
    "addr:full":"6142 SW Hwy 200 Ocala FL 34476",
    "addr:housenumber":"6142",
    "addr:postcode":"34476",
    "addr:street":"Sw Hwy 200",
    "iso:country":"US",
    "sg:address":"6142 SW Hwy 200",
    "sg:city":"Ocala",
    "sg:classifiers":[
        {
            "category":"Personal",
            "subcategory":"Beauty Salon",
            "type":"Services"
        }
    ],
    "sg:phone":"+1 352 237 4100",
    "sg:postcode":"34476",
    "sg:province":"FL",
    "wof:name":"Crossroads Hair & Nail Design",
    "wof:placetype":"venue"
},
  "geometry": {"coordinates":[-82.221997,29.113868],"type":"Point"}
}