{
  "type": "Feature",
  "properties": {
    "iso:country":"US",
    "sg:address":"806 E Hillsborough Ave",
    "sg:city":"Tampa",
    "sg:classifiers":[
        {
            "category":"Retail",
            "subcategory":"Auto Repair",
            "type":"Services"
        }
    ],
    "sg:phone":"+1 813 232 1383",
    "sg:postcode":"33604",
    "sg:province":"FL",
    "sg:tags":[
        "repairing",
        "automobile"
    ],
    "wof:name":"JDR Svc",
    "wof:placetype":"venue"
},
  "geometry": {"coordinates":[-82.451176,27.996146],"type":"Point"}
}