{
  "type": "Feature",
  "properties": {
    "addr:full":"55 Alhambra Plz Coral Gables FL 33134",
    "addr:housenumber":"55",
    "addr:postcode":"33134",
    "addr:street":"Alhambra Plz",
    "iso:country":"US",
    "sg:address":"55 Alhambra Plz",
    "sg:city":"Coral Gables",
    "sg:classifiers":[
        {
            "category":"Autos & Motor Vehicles",
            "subcategory":"Boat Sales",
            "type":"Retail Goods"
        }
    ],
    "sg:phone":"+1 305 461 7400",
    "sg:postcode":"33134",
    "sg:province":"FL",
    "sg:tags":[
        "equipment",
        "marine",
        "supply"
    ],
    "wof:name":"Marine Office Of America Corp",
    "wof:placetype":"venue"
},
  "geometry": {"coordinates":[-80.255762,25.75244],"type":"Point"}
}