{
  "type": "Feature",
  "properties": {
    "iso:country":"US",
    "sg:address":"20755 SW 177th Ave",
    "sg:city":"Miami",
    "sg:classifiers":[
        {
            "category":"Wholesale",
            "subcategory":"Plants",
            "type":"Manufacturing & Wholesale Goods"
        },
        {
            "category":"Shopping",
            "subcategory":"Crafts & Fabrics",
            "type":"Retail Goods"
        }
    ],
    "sg:phone":"+1 305 251 9217",
    "sg:postcode":"33187",
    "sg:province":"FL",
    "sg:tags":[
        "florists'",
        "supply",
        "florist",
        "supplies-wholesale",
        "plants-wholesale",
        "manufacturer"
    ],
    "wof:name":"Reliant Nursery Inc",
    "wof:placetype":"venue"
},
  "geometry": {"coordinates":[-80.478291,25.572813],"type":"Point"}
}