{
  "type": "Feature",
  "properties": {
    "iso:country":"US",
    "sg:address":"3819 4th St W",
    "sg:city":"Lehigh Acres",
    "sg:classifiers":[
        {
            "category":"Building & Trades",
            "subcategory":"Construction",
            "type":"Services"
        }
    ],
    "sg:phone":"+1 239 369 2622",
    "sg:postcode":"33971",
    "sg:province":"FL",
    "sg:tags":[
        "contractor"
    ],
    "wof:name":"Style Tile & Marble Inc",
    "wof:placetype":"venue"
},
  "geometry": {"coordinates":[-81.699682,26.616011],"type":"Point"}
}