{
  "type": "Feature",
  "properties": {
    "iso:country":"US",
    "sg:address":"17550 SE 85th Pl",
    "sg:city":"Ocklawaha",
    "sg:classifiers":[
        {
            "category":"Retail",
            "subcategory":"Repair Shop",
            "type":"Services"
        }
    ],
    "sg:phone":"+1 352 288 3007",
    "sg:postcode":"32179",
    "sg:province":"FL",
    "sg:tags":[
        "vinyl"
    ],
    "wof:name":"J B C Restoration",
    "wof:placetype":"venue"
},
  "geometry": {"coordinates":[-81.861407,29.098511],"type":"Point"}
}