{
  "type": "Feature",
  "properties": {
    "iso:country":"US",
    "sg:address":"12100 Hibiscus Dr",
    "sg:city":"Fort Myers",
    "sg:classifiers":[
        {
            "category":"Building & Trades",
            "subcategory":"Landscaping Services",
            "type":"Services"
        }
    ],
    "sg:phone":"+1 239 482 0293",
    "sg:postcode":"33908",
    "sg:province":"FL",
    "sg:tags":[
        "landscape"
    ],
    "wof:name":"Dwight Summer & Son Lawn Care",
    "wof:placetype":"venue"
},
  "geometry": {"coordinates":[-81.954249,26.512668],"type":"Point"}
}