{
  "type": "Feature",
  "properties": {
    "addr:full":"5580 Ulmerton Rd Clearwater FL 33760",
    "addr:housenumber":"5580",
    "addr:postcode":"33760",
    "addr:street":"Ulmerton Rd",
    "iso:country":"US",
    "sg:address":"5580 Ulmerton Rd",
    "sg:city":"Clearwater",
    "sg:classifiers":[
        {
            "category":"Retail",
            "subcategory":"Auto Repair",
            "type":"Services"
        }
    ],
    "sg:phone":"+1 727 572 0609",
    "sg:postcode":"33760",
    "sg:province":"FL",
    "sg:tags":[
        "body"
    ],
    "wof:name":"Collisiontec Inc",
    "wof:placetype":"venue"
},
  "geometry": {"coordinates":[-82.707336,27.893807],"type":"Point"}
}