{
  "type": "Feature",
  "properties": {
    "addr:full":"1511 Gulf Blvd Indian Rocks Bch FL 33785",
    "addr:housenumber":"1511",
    "addr:postcode":"33785",
    "addr:street":"Gulf Blvd Indian Rocks",
    "iso:country":"US",
    "sg:address":"1511 Gulf Blvd",
    "sg:city":"Indian Rocks Bch",
    "sg:classifiers":[
        {
            "category":"Banks & Credit Unions",
            "subcategory":"Bank",
            "type":"Services"
        }
    ],
    "sg:phone":"+1 727 596 7259",
    "sg:postcode":"33785",
    "sg:province":"FL",
    "sg:tags":[
        "loan",
        "real estate"
    ],
    "wof:name":"United Mortgage Affiliates",
    "wof:placetype":"venue"
},
  "geometry": {"coordinates":[-82.848201,27.898764],"type":"Point"}
}