{
  "type": "Feature",
  "properties": {
    "iso:country":"US",
    "sg:address":"8699 Astronaut Blvd",
    "sg:city":"Cape Canaveral",
    "sg:classifiers":[
        {
            "category":"Restaurant",
            "type":"Food & Drink"
        }
    ],
    "sg:phone":"+1 321 799 2844",
    "sg:postcode":"32920",
    "sg:province":"FL",
    "sg:website":"www.subway.com",
    "wof:name":"Subway Sandwich Shop",
    "wof:placetype":"venue"
},
  "geometry": {"coordinates":[-80.611603,28.395599],"type":"Point"}
}