{
  "type": "Feature",
  "properties": {
    "iso:country":"US",
    "sg:address":"1101 E Altamonte Dr",
    "sg:city":"Altamonte Springs",
    "sg:classifiers":[
        {
            "category":"Shopping",
            "subcategory":"Bicycles & Sporting Goods",
            "type":"Retail Goods"
        },
        {
            "category":"Shopping",
            "subcategory":"Shoes",
            "type":"Retail Goods"
        }
    ],
    "sg:phone":"+1 407 831 0777",
    "sg:postcode":"32701",
    "sg:province":"FL",
    "sg:tags":[
        "outdoor",
        "gear",
        "store"
    ],
    "wof:name":"Travel Country Outdoors",
    "wof:placetype":"venue"
},
  "geometry": {"coordinates":[-81.354202,28.6633],"type":"Point"}
}