{
  "type": "Feature",
  "properties": {
    "iso:country":"US",
    "sg:address":"17071 W Dixie Hwy",
    "sg:city":"North Miami Beach",
    "sg:classifiers":[
        {
            "category":"Professional",
            "subcategory":"Lawyer & Legal Services",
            "type":"Services"
        }
    ],
    "sg:phone":"+1 305 940 4746",
    "sg:postcode":"33160",
    "sg:province":"FL",
    "wof:name":"Miller Eric J PA",
    "wof:placetype":"venue"
},
  "geometry": {"coordinates":[-80.152603,25.9333],"type":"Point"}
}