{
  "type": "Feature",
  "properties": {
    "addr:full":"6215 N 9th Ave Pensacola FL 32504",
    "addr:housenumber":"6215",
    "addr:postcode":"32504",
    "addr:street":"N 9Th Ave",
    "iso:country":"US",
    "sg:address":"6215 N 9th Ave",
    "sg:city":"Pensacola",
    "sg:classifiers":[
        {
            "category":"Restaurant",
            "type":"Food & Drink"
        }
    ],
    "sg:menulink":"http://www.allmenus.com/fl/pensacola/93668-wing-zone/menu/",
    "sg:phone":"+1 999 999 9999",
    "sg:postcode":"32504",
    "sg:province":"FL",
    "sg:tags":[
        "american",
        "wing"
    ],
    "wof:name":"Wing Zone",
    "wof:placetype":"venue"
},
  "geometry": {"coordinates":[-87.199224,30.486558],"type":"Point"}
}