{
  "type": "Feature",
  "properties": {
    "iso:country":"US",
    "sg:address":"1411 El Paso Ave",
    "sg:city":"Orlando",
    "sg:classifiers":[
        {
            "category":"Health Services",
            "subcategory":"Nursing And Care Facility",
            "type":"Services"
        },
        {
            "category":"Social Services",
            "subcategory":"Retirement Home",
            "type":"Services"
        },
        {
            "category":"Social Services",
            "subcategory":"Adult Care",
            "type":"Services"
        }
    ],
    "sg:phone":"+1 407 898 3339",
    "sg:postcode":"32806",
    "sg:province":"FL",
    "sg:tags":[
        "living",
        "assisted",
        "rest",
        "elder",
        "community"
    ],
    "wof:name":"Harmony Retirement Living",
    "wof:placetype":"venue"
},
  "geometry": {"coordinates":[-81.345445,28.524287],"type":"Point"}
}