{
  "type": "Feature",
  "properties": {
    "addr:full":"3151 Clint Moore Rd Boca Raton FL 33496",
    "addr:housenumber":"3151",
    "addr:postcode":"33496",
    "addr:street":"Clint Moore Rd",
    "iso:country":"US",
    "sg:address":"3151 Clint Moore Rd",
    "sg:city":"Boca Raton",
    "sg:classifiers":[
        {
            "category":"Professional",
            "subcategory":"Management & Consulting",
            "type":"Services"
        }
    ],
    "sg:phone":"+1 561 989 0355",
    "sg:postcode":"33496",
    "sg:province":"FL",
    "sg:tags":[
        "consultant",
        "business"
    ],
    "wof:name":"Richard Tauman Assoc",
    "wof:placetype":"venue"
},
  "geometry": {"coordinates":[-80.155742,26.40886],"type":"Point"}
}