{
  "type": "Feature",
  "properties": {
    "iso:country":"US",
    "sg:address":"3000 N Ocean Blvd",
    "sg:city":"Delray Beach",
    "sg:classifiers":[
        {
            "category":"Banks & Credit Unions",
            "subcategory":"Financial Services",
            "type":"Services"
        }
    ],
    "sg:phone":"+1 561 278 7792",
    "sg:postcode":"33483",
    "sg:province":"FL",
    "sg:tags":[
        "investment",
        "closed"
    ],
    "wof:name":"Dockerty & Dockerty Inc",
    "wof:placetype":"venue"
},
  "geometry": {"coordinates":[-80.05411599999999,26.494585],"type":"Point"}
}