{
  "type": "Feature",
  "properties": {
    "iso:country":"US",
    "sg:address":"1750 King St",
    "sg:city":"Cocoa",
    "sg:classifiers":[
        {
            "category":"Retail",
            "subcategory":"Auto Rental",
            "type":"Services"
        }
    ],
    "sg:phone":"+1 321 633 7070",
    "sg:postcode":"32926",
    "sg:province":"FL",
    "sg:tags":[
        "renting",
        "automobile"
    ],
    "wof:name":"Enterprise Rent-A-Car",
    "wof:placetype":"venue"
},
  "geometry": {"coordinates":[-80.75523,28.355793],"type":"Point"}
}