{
  "type": "Feature",
  "properties": {
    "addr:full":"3051 SW 27th Ave Miami FL 33133",
    "addr:housenumber":"3051",
    "addr:postcode":"33133",
    "addr:street":"Sw 27Th Ave",
    "iso:country":"US",
    "sg:address":"3051 SW 27th Ave",
    "sg:city":"Miami",
    "sg:classifiers":[
        {
            "category":"Real Estate",
            "subcategory":"Real Estate Operator",
            "type":"Services"
        }
    ],
    "sg:phone":"+1 305 774 2956",
    "sg:postcode":"33133",
    "sg:province":"FL",
    "sg:tags":[
        "apartment"
    ],
    "wof:name":"Grove II Apartments Inc",
    "wof:placetype":"venue"
},
  "geometry": {"coordinates":[-80.237548,25.734781],"type":"Point"}
}