{
  "type": "Feature",
  "properties": {
    "iso:country":"US",
    "sg:address":"580 Sanford Ave",
    "sg:city":"Altamonte Spgs",
    "sg:classifiers":[
        {
            "category":"Wholesale",
            "subcategory":"Electrical",
            "type":"Manufacturing & Wholesale Goods"
        }
    ],
    "sg:phone":"+1 407 831 4160",
    "sg:postcode":"32701",
    "sg:province":"FL",
    "sg:tags":[
        "control",
        "security",
        "system"
    ],
    "wof:name":"Firstwatch Security Solutions",
    "wof:placetype":"venue"
},
  "geometry": {"coordinates":[-81.35820099999999,28.671171],"type":"Point"}
}