{
  "type": "Feature",
  "properties": {
    "addr:full":"8541 Fort King Rd Zephyrhills FL 33541",
    "addr:housenumber":"8541",
    "addr:postcode":"33541",
    "addr:street":"Fort King Rd",
    "iso:country":"US",
    "sg:address":"8541 Fort King Rd",
    "sg:city":"Zephyrhills",
    "sg:classifiers":[
        {
            "category":"Building & Trades",
            "subcategory":"Construction",
            "type":"Services"
        }
    ],
    "sg:phone":"+1 813 780 6594",
    "sg:postcode":"33541",
    "sg:province":"FL",
    "sg:tags":[
        "contractor"
    ],
    "wof:name":"Hinsz Fence",
    "wof:placetype":"venue"
},
  "geometry": {"coordinates":[-82.20441,28.27093],"type":"Point"}
}