{
  "type": "Feature",
  "properties": {
    "iso:country":"US",
    "sg:address":"1710 NW 7th St Ste 201",
    "sg:city":"Miami",
    "sg:classifiers":[
        {
            "category":"Professional",
            "subcategory":"Accounting & Tax Preparation",
            "type":"Services"
        }
    ],
    "sg:phone":"+1 305 649 8404",
    "sg:postcode":"33125",
    "sg:province":"FL",
    "sg:tags":[
        "bookkeeping"
    ],
    "wof:name":"Peres & Associates Enterprises Inc",
    "wof:placetype":"venue"
},
  "geometry": {"coordinates":[-80.223389,25.77997],"type":"Point"}
}