{
  "type": "Feature",
  "properties": {
    "iso:country":"US",
    "sg:address":"6355 N Federal Hwy",
    "sg:city":"Boca Raton",
    "sg:classifiers":[
        {
            "category":"Wholesale",
            "subcategory":"Sporting Goods",
            "type":"Manufacturing & Wholesale Goods"
        }
    ],
    "sg:phone":"+1 561 997 0442",
    "sg:postcode":"33487",
    "sg:province":"FL",
    "wof:name":"Davis Custom Interiors",
    "wof:placetype":"venue"
},
  "geometry": {"coordinates":[-80.07632,26.405987],"type":"Point"}
}