{
  "type": "Feature",
  "properties": {
    "iso:country":"US",
    "sg:address":"500 Roser Park Dr S",
    "sg:city":"St Petersburg",
    "sg:classifiers":[
        {
            "category":"Health Services",
            "subcategory":"Doctor",
            "type":"Services"
        }
    ],
    "sg:phone":"+1 727 898 4461",
    "sg:postcode":"33701",
    "sg:province":"FL",
    "sg:tags":[
        "physician",
        "surgeon"
    ],
    "wof:name":"Roser Park Medical Ctr",
    "wof:placetype":"venue"
},
  "geometry": {"coordinates":[-82.64182599999999,27.760389],"type":"Point"}
}