{
  "type": "Feature",
  "properties": {
    "addr:full":"9420 W Flagler St Miami FL 33174",
    "addr:housenumber":"9420",
    "addr:postcode":"33174",
    "addr:street":"W Flagler St",
    "iso:country":"US",
    "sg:address":"9420 W Flagler St",
    "sg:city":"Miami",
    "sg:classifiers":[
        {
            "category":"Wholesale",
            "subcategory":"Electrical",
            "type":"Manufacturing & Wholesale Goods"
        }
    ],
    "sg:phone":"+1 305 220 4045",
    "sg:postcode":"33174",
    "sg:province":"FL",
    "sg:tags":[
        "appliance"
    ],
    "wof:name":"Lyman & Assoc Co",
    "wof:placetype":"venue"
},
  "geometry": {"coordinates":[-80.349001,25.769153],"type":"Point"}
}