{
  "type": "Feature",
  "properties": {
    "iso:country":"US",
    "sg:address":"421 Collins Ave",
    "sg:city":"Miami Beach",
    "sg:classifiers":[
        {
            "category":"Building & Trades",
            "subcategory":"Construction",
            "type":"Services"
        }
    ],
    "sg:phone":"+1 305 674 8796",
    "sg:postcode":"33139",
    "sg:province":"FL",
    "sg:tags":[
        "contractor"
    ],
    "wof:name":"421 Collins Building",
    "wof:placetype":"venue"
},
  "geometry": {"coordinates":[-80.132969,25.774349],"type":"Point"}
}