{
  "type": "Feature",
  "properties": {
    "addr:full":"14967 Newport Rd Clearwater FL 33764",
    "addr:housenumber":"14967",
    "addr:postcode":"33764",
    "addr:street":"Newport Rd",
    "iso:country":"US",
    "sg:address":"14967 Newport Rd",
    "sg:city":"Clearwater",
    "sg:classifiers":[
        {
            "category":"Building & Trades",
            "subcategory":"Construction",
            "type":"Services"
        }
    ],
    "sg:phone":"+1 727 531 4326",
    "sg:postcode":"33764",
    "sg:province":"FL",
    "sg:tags":[
        "house"
    ],
    "wof:name":"CPB Enterprises",
    "wof:placetype":"venue"
},
  "geometry": {"coordinates":[-82.73946599999999,27.907871],"type":"Point"}
}