{
  "type": "Feature",
  "properties": {
    "iso:country":"US",
    "sg:address":"7085 University Blvd",
    "sg:city":"Winter Park",
    "sg:classifiers":[
        {
            "category":"Professional",
            "subcategory":"Employment Agencies",
            "type":"Services"
        }
    ],
    "sg:phone":"+1 407 671 5800",
    "sg:postcode":"32792",
    "sg:province":"FL",
    "sg:tags":[
        "supply",
        "help",
        "contractor"
    ],
    "wof:name":"Ategra Systems Inc",
    "wof:placetype":"venue"
},
  "geometry": {"coordinates":[-81.293809,28.597601],"type":"Point"}
}