{
  "type": "Feature",
  "properties": {
    "iso:country":"US",
    "sg:address":"309 S Chase Ct",
    "sg:city":"Altamonte Springs",
    "sg:classifiers":[
        {
            "category":"Travel",
            "subcategory":"Travel Agent",
            "type":"Entertainment"
        }
    ],
    "sg:phone":"+1 407 834 8920",
    "sg:postcode":"32714",
    "sg:province":"FL",
    "sg:tags":[
        "agency"
    ],
    "wof:name":"Travel Zoom Co Inc",
    "wof:placetype":"venue"
},
  "geometry": {"coordinates":[-81.401016,28.644155],"type":"Point"}
}