{
  "type": "Feature",
  "properties": {
    "iso:country":"US",
    "sg:address":"1980 NE 7th St",
    "sg:city":"Deerfield Beach",
    "sg:classifiers":[
        {
            "category":"Recreation",
            "type":"Entertainment"
        }
    ],
    "sg:phone":"+1 954 648 6567",
    "sg:postcode":"33441",
    "sg:province":"FL",
    "sg:tags":[
        "club",
        "membership"
    ],
    "wof:name":"Calypso Poet Yacht Services",
    "wof:placetype":"venue"
},
  "geometry": {"coordinates":[-80.07869599999999,26.320648],"type":"Point"}
}