{
  "type": "Feature",
  "properties": {
    "iso:country":"US",
    "sg:address":"2236 Gulf To Bay Blvd",
    "sg:city":"Clearwater",
    "sg:classifiers":[
        {
            "category":"Building & Trades",
            "subcategory":"Construction",
            "type":"Services"
        }
    ],
    "sg:phone":"+1 727 642 9051",
    "sg:postcode":"33765",
    "sg:province":"FL",
    "sg:tags":[
        "resurfacing",
        "laying",
        "refinishing",
        "floor"
    ],
    "wof:name":"Oscar Flooring Inc",
    "wof:placetype":"venue"
},
  "geometry": {"coordinates":[-82.744135,27.960528],"type":"Point"}
}