{
  "type": "Feature",
  "properties": {
    "addr:full":"3615 W Hillsborough Ave Tampa FL 33614",
    "addr:housenumber":"3615",
    "addr:postcode":"33614",
    "addr:street":"W Hillsborough Ave",
    "iso:country":"US",
    "sg:address":"3615 W Hillsborough Ave",
    "sg:city":"Tampa",
    "sg:classifiers":[
        {
            "category":"Personal",
            "subcategory":"Beauty Salon",
            "type":"Services"
        }
    ],
    "sg:phone":"+1 813 871 5666",
    "sg:postcode":"33614",
    "sg:province":"FL",
    "wof:name":"Innerface",
    "wof:placetype":"venue"
},
  "geometry": {"coordinates":[-82.503567,27.996001],"type":"Point"}
}