{
  "type": "Feature",
  "properties": {
    "addr:full":"12203 102nd St Largo FL 33773",
    "addr:housenumber":"12203",
    "addr:postcode":"33773",
    "addr:street":"102Nd St",
    "iso:country":"US",
    "sg:address":"12203 102nd St",
    "sg:city":"Largo",
    "sg:classifiers":[
        {
            "category":"Real Estate",
            "subcategory":"Real Estate Services",
            "type":"Services"
        },
        {
            "category":"Building & Trades",
            "subcategory":"Cleaning & Sanitation",
            "type":"Services"
        }
    ],
    "sg:phone":"+1 727 418 3384",
    "sg:postcode":"33773",
    "sg:province":"FL",
    "sg:tags":[
        "maintenance",
        "cleaners-interior"
    ],
    "wof:name":"On Call Maintenance Inc",
    "wof:placetype":"venue"
},
  "geometry": {"coordinates":[-82.781418,27.883676],"type":"Point"}
}