{
  "type": "Feature",
  "properties": {
    "addr:full":"7924 Rutillio Ct New Port Richey FL 34653",
    "addr:housenumber":"7924",
    "addr:postcode":"34653",
    "addr:street":"Rutillio Ct",
    "iso:country":"US",
    "sg:address":"7924 Rutillio Ct",
    "sg:city":"New Port Richey",
    "sg:classifiers":[
        {
            "category":"Building & Trades",
            "subcategory":"Plumbing",
            "type":"Services"
        }
    ],
    "sg:phone":"+1 727 849 8247",
    "sg:postcode":"34653",
    "sg:province":"FL",
    "sg:tags":[
        "conditioning",
        "air",
        "system",
        "contractor"
    ],
    "sg:website":"www.airxpressonline.com",
    "wof:name":"Air Xpress",
    "wof:placetype":"venue"
},
  "geometry": {"coordinates":[-82.70447799999999,28.271606],"type":"Point"}
}