{
  "type": "Feature",
  "properties": {
    "iso:country":"US",
    "sg:address":"600 N John Rodes Blvd",
    "sg:city":"Melbourne",
    "sg:classifiers":[
        {
            "category":"Manufacturing",
            "subcategory":"Electronics",
            "type":"Manufacturing & Wholesale Goods"
        }
    ],
    "sg:phone":"+1 321 308 8700",
    "sg:postcode":"32934",
    "sg:province":"FL",
    "sg:tags":[
        "mfg",
        "electronic",
        "boards",
        "circuit",
        "printed"
    ],
    "wof:name":"Tyco Electronics Power Group",
    "wof:placetype":"venue"
},
  "geometry": {"coordinates":[-80.700294,28.117579],"type":"Point"}
}