{
  "type": "Feature",
  "properties": {
    "addr:full":"16801 Ashwood Dr Tampa FL 33624",
    "addr:housenumber":"16801",
    "addr:postcode":"33624",
    "addr:street":"Ashwood Dr",
    "iso:country":"US",
    "sg:address":"16801 Ashwood Dr",
    "sg:city":"Tampa",
    "sg:classifiers":[
        {
            "category":"Organizations",
            "subcategory":"Community Association",
            "type":"Services"
        }
    ],
    "sg:phone":"+1 813 969 1462",
    "sg:postcode":"33624",
    "sg:province":"FL",
    "wof:name":"Krewe of Les Belles Unique De",
    "wof:placetype":"venue"
},
  "geometry": {"coordinates":[-82.526512,28.111043],"type":"Point"}
}