{
  "type": "Feature",
  "properties": {
    "iso:country":"US",
    "sg:address":"2161 SW 11th Ter",
    "sg:city":"Miami",
    "sg:classifiers":[
        {
            "category":"Arts & Performance",
            "subcategory":"Art Gallery",
            "type":"Entertainment"
        }
    ],
    "sg:phone":"+1 305 442 7732",
    "sg:postcode":"33135",
    "sg:province":"FL",
    "wof:name":"Cuban Collection Fine Arts",
    "wof:placetype":"venue"
},
  "geometry": {"coordinates":[-80.22965600000001,25.762062],"type":"Point"}
}