{
  "type": "Feature",
  "properties": {
    "iso:country":"US",
    "sg:address":"1705 Colonial Blvd Ste D1",
    "sg:city":"Fort Myers",
    "sg:classifiers":[
        {
            "category":"Professional",
            "subcategory":"Accounting & Tax Preparation",
            "type":"Services"
        }
    ],
    "sg:phone":"+1 239 939 2301",
    "sg:postcode":"33907",
    "sg:province":"FL",
    "sg:tags":[
        "accountant"
    ],
    "wof:name":"Bowman & Bowman Cpa's",
    "wof:placetype":"venue"
},
  "geometry": {"coordinates":[-81.877602,26.597],"type":"Point"}
}