{
  "type": "Feature",
  "properties": {
    "iso:country":"US",
    "sg:address":"90330 Overseas Hwy",
    "sg:city":"Tavernier",
    "sg:classifiers":[
        {
            "category":"Retail",
            "subcategory":"Repair Shop",
            "type":"Services"
        }
    ],
    "sg:phone":"+1 305 852 2724",
    "sg:postcode":"33070",
    "sg:province":"FL",
    "sg:tags":[
        "engine",
        "marine"
    ],
    "wof:name":"Caribee Boat Sales and Marina",
    "wof:placetype":"venue"
},
  "geometry": {"coordinates":[-80.536282,25.001406],"type":"Point"}
}