{
  "type": "Feature",
  "properties": {
    "iso:country":"US",
    "sg:address":"1244 Martinique Ct",
    "sg:city":"Marco Island",
    "sg:classifiers":[
        {
            "category":"Building & Trades",
            "subcategory":"Construction",
            "type":"Services"
        }
    ],
    "sg:phone":"+1 239 394 4788",
    "sg:postcode":"34145",
    "sg:province":"FL",
    "sg:tags":[
        "residential",
        "nonresidential"
    ],
    "wof:name":"Fc Romas Construction",
    "wof:placetype":"venue"
},
  "geometry": {"coordinates":[-81.71515599999999,25.961375],"type":"Point"}
}