{
  "type": "Feature",
  "properties": {
    "addr:full":"2720 W Waters Ave Tampa FL 33614",
    "addr:housenumber":"2720",
    "addr:postcode":"33614",
    "addr:street":"W Waters Ave",
    "iso:country":"US",
    "sg:address":"2720 W Waters Ave",
    "sg:city":"Tampa",
    "sg:classifiers":[
        {
            "category":"Shopping",
            "subcategory":"Bicycles & Sporting Goods",
            "type":"Retail Goods"
        }
    ],
    "sg:phone":"+1 813 932 9782",
    "sg:postcode":"33614",
    "sg:province":"FL",
    "sg:tags":[
        "equipment",
        "skateboard"
    ],
    "wof:name":"Kids Inc",
    "wof:placetype":"venue"
},
  "geometry": {"coordinates":[-82.48724900000001,28.025284],"type":"Point"}
}