{
  "type": "Feature",
  "properties": {
    "addr:full":"1110 Bahama Dr Orlando FL 32806",
    "addr:housenumber":"1110",
    "addr:postcode":"32806",
    "addr:street":"Bahama Dr",
    "iso:country":"US",
    "sg:address":"1110 Bahama Dr",
    "sg:city":"Orlando",
    "sg:classifiers":[
        {
            "category":"Professional",
            "type":"Services"
        }
    ],
    "sg:phone":"+1 407 898 1930",
    "sg:postcode":"32806",
    "sg:province":"FL",
    "wof:name":"Galano Terry Dale & Bob",
    "wof:placetype":"venue"
},
  "geometry": {"coordinates":[-81.359525,28.527818],"type":"Point"}
}