{
  "type": "Feature",
  "properties": {
    "iso:country":"US",
    "sg:address":"3821 Avalon Park East Blvd Blv 422",
    "sg:city":"Orlando",
    "sg:classifiers":[
        {
            "category":"Bakery",
            "type":"Food & Drink"
        }
    ],
    "sg:phone":"+1 407 952 0079",
    "sg:postcode":"32828",
    "sg:province":"FL",
    "sg:tags":[
        "cake",
        "pastry",
        "wedding"
    ],
    "wof:name":"Eve's Cakes",
    "wof:placetype":"venue"
},
  "geometry": {"coordinates":[-81.154533,28.509529],"type":"Point"}
}