{
  "type": "Feature",
  "properties": {
    "addr:full":"1390 SW Dorchester St Port St Lucie FL 34983",
    "addr:housenumber":"1390",
    "addr:postcode":"34983",
    "addr:street":"Sw Dorchester St;St",
    "iso:country":"US",
    "sg:address":"1390 SW Dorchester St",
    "sg:city":"Port St Lucie",
    "sg:classifiers":[
        {
            "category":"Organizations",
            "subcategory":"Religious Organization",
            "type":"Services"
        }
    ],
    "sg:phone":"+1 772 340 4135",
    "sg:postcode":"34983",
    "sg:province":"FL",
    "sg:tags":[
        "church"
    ],
    "wof:name":"St Lucie Presbyterian Church",
    "wof:placetype":"venue"
},
  "geometry": {"coordinates":[-80.36038600000001,27.300159],"type":"Point"}
}