{
  "type": "Feature",
  "properties": {
    "addr:full":"1 Airport Blvd Orlando FL 32827",
    "addr:housenumber":"1",
    "addr:postcode":"32827",
    "addr:street":"Airport Blvd",
    "iso:country":"US",
    "sg:address":"1 Airport Blvd",
    "sg:city":"Orlando",
    "sg:classifiers":[
        {
            "category":"Ice Cream",
            "type":"Food & Drink"
        }
    ],
    "sg:menulink":"http://www.allmenus.com/fl/orlando/217655-ben--jerrys/menu/",
    "sg:phone":"0",
    "sg:postcode":"32827",
    "sg:province":"FL",
    "sg:tags":[
        "american"
    ],
    "wof:name":"Ben & Jerry's",
    "wof:placetype":"venue"
},
  "geometry": {"coordinates":[-81.30516900000001,28.42983],"type":"Point"}
}