{
  "type": "Feature",
  "properties": {
    "iso:country":"US",
    "sg:address":"5323 Brown St",
    "sg:city":"Graceville",
    "sg:classifiers":[
        {
            "category":"Retail",
            "subcategory":"Auto Repair",
            "type":"Services"
        }
    ],
    "sg:phone":"+1 850 263 3271",
    "sg:postcode":"32440",
    "sg:province":"FL",
    "sg:tags":[
        "body",
        "automobile",
        "painting",
        "repairing"
    ],
    "sg:website":"http://www.fordvehicles.com",
    "wof:name":"Arnold, Henry Ford Co",
    "wof:placetype":"venue"
},
  "geometry": {"coordinates":[-85.51580800000001,30.958361],"type":"Point"}
}