{
  "type": "Feature",
  "properties": {
    "addr:full":"391 Lee Blvd Lehigh Acres FL 33936",
    "addr:housenumber":"391",
    "addr:postcode":"33936",
    "addr:street":"Lee Blvd",
    "iso:country":"US",
    "sg:address":"391 Lee Blvd",
    "sg:city":"Lehigh Acres",
    "sg:classifiers":[
        {
            "category":"Health Services",
            "subcategory":"Doctor",
            "type":"Services"
        }
    ],
    "sg:phone":"+1 239 369 2226",
    "sg:postcode":"33936",
    "sg:province":"FL",
    "sg:tags":[
        "physician",
        "surgeon"
    ],
    "wof:name":"Personal Family Healthcare Inc",
    "wof:placetype":"venue"
},
  "geometry": {"coordinates":[-81.64187800000001,26.611504],"type":"Point"}
}