{
  "type": "Feature",
  "properties": {
    "addr:full":"5551 Heckscher Dr Jacksonville FL 32226",
    "addr:housenumber":"5551",
    "addr:postcode":"32226",
    "addr:street":"Heckscher Dr",
    "iso:country":"US",
    "sg:address":"5551 Heckscher Dr",
    "sg:city":"Jacksonville",
    "sg:classifiers":[
        {
            "category":"Building & Trades",
            "subcategory":"Construction",
            "type":"Services"
        }
    ],
    "sg:phone":"+1 904 879 5129",
    "sg:postcode":"32226",
    "sg:province":"FL",
    "sg:tags":[
        "home",
        "new",
        "remodeling",
        "improvement"
    ],
    "wof:name":"Crazy Ted's Home Improvement",
    "wof:placetype":"venue"
},
  "geometry": {"coordinates":[-81.528964,30.416848],"type":"Point"}
}