{
  "type": "Feature",
  "properties": {
    "iso:country":"US",
    "sg:address":"10305 NW 41st St Ste 126",
    "sg:city":"Doral",
    "sg:classifiers":[
        {
            "category":"Professional",
            "subcategory":"Business Services",
            "type":"Services"
        }
    ],
    "sg:phone":"+1 305 591 1645",
    "sg:postcode":"33178",
    "sg:province":"FL",
    "sg:tags":[
        "consultant",
        "coach"
    ],
    "wof:name":"Central American Trailers",
    "wof:placetype":"venue"
},
  "geometry": {"coordinates":[-80.36346399999999,25.811702],"type":"Point"}
}