{
  "type": "Feature",
  "properties": {
    "addr:full":"4173 Chacato Cove Niceville FL 32578",
    "addr:housenumber":"4173",
    "addr:postcode":"32578",
    "addr:street":"Chacato Cove",
    "iso:country":"US",
    "sg:address":"4173 Chacato Cove",
    "sg:city":"Niceville",
    "sg:classifiers":[
        {
            "category":"Insurance",
            "subcategory":"Insurance Agent",
            "type":"Services"
        }
    ],
    "sg:phone":"+1 850 897 1025",
    "sg:postcode":"32578",
    "sg:province":"FL",
    "wof:name":"Adjusters Inc",
    "wof:placetype":"venue"
},
  "geometry": {"coordinates":[-86.445517,30.491139],"type":"Point"}
}