{
  "type": "Feature",
  "properties": {
    "iso:country":"US",
    "sg:address":"1924 N Pace Blvd",
    "sg:city":"Pensacola",
    "sg:classifiers":[
        {
            "category":"Building & Trades",
            "subcategory":"Equipment Rental",
            "type":"Services"
        }
    ],
    "sg:phone":"+1 850 434 2550",
    "sg:postcode":"32505",
    "sg:province":"FL",
    "sg:tags":[
        "party",
        "supply"
    ],
    "wof:name":"Rental Rite & Florist",
    "wof:placetype":"venue"
},
  "geometry": {"coordinates":[-87.240469,30.432852],"type":"Point"}
}