{
  "type": "Feature",
  "properties": {
    "addr:full":"1811 NW Pine Ave Ocala FL 34475",
    "addr:housenumber":"1811",
    "addr:postcode":"34475",
    "addr:street":"Nw Pine Ave",
    "iso:country":"US",
    "sg:address":"1811 NW Pine Ave",
    "sg:city":"Ocala",
    "sg:classifiers":[
        {
            "category":"Wholesale",
            "subcategory":"Furniture",
            "type":"Manufacturing & Wholesale Goods"
        }
    ],
    "sg:phone":"+1 352 622 3221",
    "sg:postcode":"34475",
    "sg:province":"FL",
    "wof:name":"Apex Office Supplies & Furn",
    "wof:placetype":"venue"
},
  "geometry": {"coordinates":[-82.141791,29.204793],"type":"Point"}
}