{
  "type": "Feature",
  "properties": {
    "iso:country":"US",
    "sg:address":"4236 William James Way",
    "sg:city":"Tallahassee",
    "sg:classifiers":[
        {
            "category":"Real Estate",
            "subcategory":"Real Estate Agent",
            "type":"Services"
        }
    ],
    "sg:phone":"+1 850 562 6400",
    "sg:postcode":"32303",
    "sg:province":"FL",
    "wof:name":"Vanguard Realty",
    "wof:placetype":"venue"
},
  "geometry": {"coordinates":[-84.337386,30.521324],"type":"Point"}
}