{
  "type": "Feature",
  "properties": {
    "iso:country":"US",
    "sg:address":"15841 Pines Blvd",
    "sg:city":"Hollywood",
    "sg:classifiers":[
        {
            "category":"Professional",
            "type":"Services"
        }
    ],
    "sg:phone":"+1 954 444 0643",
    "sg:postcode":"33027",
    "sg:province":"FL",
    "wof:name":"Cheepsale International",
    "wof:placetype":"venue"
},
  "geometry": {"coordinates":[-80.356475,26.007838],"type":"Point"}
}