{
  "type": "Feature",
  "properties": {
    "addr:full":"6225 US Hwy 27 Sebring FL 33870",
    "addr:housenumber":"6225",
    "addr:postcode":"33870",
    "addr:street":"Us Hwy 27",
    "iso:country":"US",
    "sg:address":"6225 US Hwy 27",
    "sg:city":"Sebring",
    "sg:classifiers":[
        {
            "category":"Restaurant",
            "type":"Food & Drink"
        }
    ],
    "sg:phone":"+1 863 385 4400",
    "sg:postcode":"33870",
    "sg:province":"FL",
    "wof:name":"Subway Sandwiches & Salads",
    "wof:placetype":"venue"
},
  "geometry": {"coordinates":[-81.499707,27.527334],"type":"Point"}
}