{
  "type": "Feature",
  "properties": {
    "addr:full":"1219 Miracle Strip Pkwy Fort Walton Bch FL 32548",
    "addr:housenumber":"1219",
    "addr:postcode":"32548",
    "addr:street":"Miracle Strip Pkwy Fort",
    "iso:country":"US",
    "sg:address":"1219 Miracle Strip Pkwy",
    "sg:city":"Fort Walton Bch",
    "sg:classifiers":[
        {
            "category":"Personal",
            "subcategory":"Tattoo Parlor",
            "type":"Services"
        }
    ],
    "sg:phone":"+1 850 244 4644",
    "sg:postcode":"32548",
    "sg:province":"FL",
    "sg:tags":[
        "tattooing"
    ],
    "wof:name":"Just Do It",
    "wof:placetype":"venue"
},
  "geometry": {"coordinates":[-86.596807,30.397276],"type":"Point"}
}