{
  "type": "Feature",
  "properties": {
    "iso:country":"US",
    "sg:address":"3999 Simms St",
    "sg:city":"Hollywood",
    "sg:classifiers":[
        {
            "category":"Manufacturing",
            "subcategory":"Printing",
            "type":"Manufacturing & Wholesale Goods"
        }
    ],
    "sg:phone":"+1 954 985 9498",
    "sg:postcode":"33021",
    "sg:province":"FL",
    "sg:tags":[
        "lithographic",
        "r",
        "commercial",
        "typesetting"
    ],
    "wof:name":"Marvin Pressman",
    "wof:placetype":"venue"
},
  "geometry": {"coordinates":[-80.18408599999999,26.035714],"type":"Point"}
}