{
  "type": "Feature",
  "properties": {
    "addr:full":"219 N Volusia Ave Orange City FL 32763",
    "addr:housenumber":"219",
    "addr:postcode":"32763",
    "addr:street":"N Volusia Ave",
    "iso:country":"US",
    "sg:address":"219 N Volusia Ave",
    "sg:city":"Orange City",
    "sg:classifiers":[
        {
            "category":"Building & Trades",
            "subcategory":"Locksmith",
            "type":"Services"
        }
    ],
    "sg:phone":"+1 386 774 0945",
    "sg:postcode":"32763",
    "sg:province":"FL",
    "sg:tags":[
        "key"
    ],
    "wof:name":"A-One Twenty Four Hour Locksmith",
    "wof:placetype":"venue"
},
  "geometry": {"coordinates":[-81.298997,28.949767],"type":"Point"}
}