{
  "type": "Feature",
  "properties": {
    "iso:country":"US",
    "sg:address":"7800 SW 58th St",
    "sg:city":"South Miami",
    "sg:classifiers":[
        {
            "category":"Professional",
            "type":"Services"
        }
    ],
    "sg:phone":"+1 305 669 5280",
    "sg:postcode":"33143",
    "sg:province":"FL",
    "sg:tags":[
        "establishment"
    ],
    "wof:name":"Jacqueline Salcines Pa",
    "wof:placetype":"venue"
},
  "geometry": {"coordinates":[-80.31943099999999,25.715721],"type":"Point"}
}