{
  "type": "Feature",
  "properties": {
    "addr:full":"9 River Oak Dr Sebastian FL 32958",
    "addr:housenumber":"9",
    "addr:postcode":"32958",
    "addr:street":"River Oak Dr",
    "iso:country":"US",
    "sg:address":"9 River Oak Dr",
    "sg:city":"Sebastian",
    "sg:classifiers":[
        {
            "category":"Building & Trades",
            "subcategory":"Construction",
            "type":"Services"
        }
    ],
    "sg:phone":"+1 772 589 5238",
    "sg:postcode":"32958",
    "sg:province":"FL",
    "sg:tags":[
        "wallcoverings-installation",
        "wallpaper",
        "painting",
        "contractor"
    ],
    "wof:name":"William Redner Painting",
    "wof:placetype":"venue"
},
  "geometry": {"coordinates":[-80.504851,27.772094],"type":"Point"}
}