{
  "type": "Feature",
  "properties": {
    "addr:full":"138 E French Ave Orange City FL 32763",
    "addr:housenumber":"138",
    "addr:postcode":"32763",
    "addr:street":"E French Ave",
    "iso:country":"US",
    "sg:address":"138 E French Ave",
    "sg:city":"Orange City",
    "sg:classifiers":[
        {
            "category":"Social Services",
            "subcategory":"Child Care",
            "type":"Services"
        },
        {
            "category":"Education",
            "subcategory":"Preschool",
            "type":"Public Place"
        },
        {
            "category":"Education",
            "subcategory":"School",
            "type":"Public Place"
        }
    ],
    "sg:phone":"+1 386 774 8600",
    "sg:postcode":"32763",
    "sg:province":"FL",
    "sg:tags":[
        "elementary",
        "day"
    ],
    "wof:name":"Happy Hands Early Learning Center",
    "wof:placetype":"venue"
},
  "geometry": {"coordinates":[-81.297859,28.951973],"type":"Point"}
}