{
  "type": "Feature",
  "properties": {
    "addr:full":"270 Kenilworth Ave Ormond Beach FL 32174",
    "addr:housenumber":"270",
    "addr:postcode":"32174",
    "addr:street":"Kenilworth Ave",
    "iso:country":"US",
    "sg:address":"270 Kenilworth Ave",
    "sg:city":"Ormond Beach",
    "sg:classifiers":[
        {
            "category":"Organizations",
            "subcategory":"Community Association",
            "type":"Services"
        }
    ],
    "sg:phone":"+1 386 677 5005",
    "sg:postcode":"32174",
    "sg:province":"FL",
    "wof:name":"Ormond Beach Masonic Temple",
    "wof:placetype":"venue"
},
  "geometry": {"coordinates":[-81.066469,29.290897],"type":"Point"}
}