{
  "type": "Feature",
  "properties": {
    "iso:country":"US",
    "sg:address":"3582 NW 32nd St",
    "sg:city":"Miami",
    "sg:classifiers":[
        {
            "category":"Retail",
            "subcategory":"Auto Repair",
            "type":"Services"
        }
    ],
    "sg:phone":"+1 305 634 7989",
    "sg:postcode":"33142",
    "sg:province":"FL",
    "sg:tags":[
        "body",
        "automobile",
        "painting",
        "repairing"
    ],
    "wof:name":"3 Point Paint And Body Works",
    "wof:placetype":"venue"
},
  "geometry": {"coordinates":[-80.254305,25.804971],"type":"Point"}
}