{
  "type": "Feature",
  "properties": {
    "addr:full":"1607 W Baker St Plant City FL 33563",
    "addr:housenumber":"1607",
    "addr:postcode":"33563",
    "addr:street":"W Baker St",
    "iso:country":"US",
    "sg:address":"1607 W Baker St",
    "sg:city":"Plant City",
    "sg:classifiers":[
        {
            "category":"Autos & Motor Vehicles",
            "subcategory":"Automobile Sales",
            "type":"Retail Goods"
        }
    ],
    "sg:phone":"+1 813 707 9700",
    "sg:postcode":"33563",
    "sg:province":"FL",
    "sg:tags":[
        "car",
        "dealer"
    ],
    "wof:name":"Billy Herold's Truck Car & Rv",
    "wof:placetype":"venue"
},
  "geometry": {"coordinates":[-82.13798800000001,28.01781],"type":"Point"}
}