{
  "type": "Feature",
  "properties": {
    "addr:full":"6950 NW 46th St Miami FL 33166",
    "addr:housenumber":"6950",
    "addr:postcode":"33166",
    "addr:street":"Nw 46Th St",
    "iso:country":"US",
    "sg:address":"6950 NW 46th St",
    "sg:city":"Miami",
    "sg:classifiers":[
        {
            "category":"Autos & Motor Vehicles",
            "subcategory":"Automobile Sales",
            "type":"Retail Goods"
        }
    ],
    "sg:phone":"+1 305 477 4220",
    "sg:postcode":"33166",
    "sg:province":"FL",
    "sg:tags":[
        "car",
        "dealer"
    ],
    "wof:name":"KARS Wheels To Go Co",
    "wof:placetype":"venue"
},
  "geometry": {"coordinates":[-80.31286,25.815193],"type":"Point"}
}