{
  "type": "Feature",
  "properties": {
    "iso:country":"US",
    "sg:address":"211 W Rich Ave",
    "sg:city":"Deland",
    "sg:classifiers":[
        {
            "category":"Retail",
            "subcategory":"Auto Repair",
            "type":"Services"
        }
    ],
    "sg:phone":"+1 386 734 4959",
    "sg:postcode":"32720",
    "sg:province":"FL",
    "sg:tags":[
        "repairing",
        "automobile"
    ],
    "wof:name":"Tom's Auto Repair",
    "wof:placetype":"venue"
},
  "geometry": {"coordinates":[-81.30619799999999,29.0298],"type":"Point"}
}