{
  "type": "Feature",
  "properties": {
    "iso:country":"US",
    "sg:address":"4940 SW 122nd Ter",
    "sg:city":"Fort Lauderdale",
    "sg:classifiers":[
        {
            "category":"Professional",
            "type":"Services"
        }
    ],
    "sg:phone":"+1 954 434 4488",
    "sg:postcode":"33330",
    "sg:province":"FL",
    "wof:name":"Dzel Inc",
    "wof:placetype":"venue"
},
  "geometry": {"coordinates":[-80.311595,26.05778],"type":"Point"}
}