{
  "type": "Feature",
  "properties": {
    "addr:full":"186 E Macclenny Ave Macclenny FL 32063",
    "addr:housenumber":"186",
    "addr:postcode":"32063",
    "addr:street":"E Macclenny Ave",
    "iso:country":"US",
    "sg:address":"186 E Macclenny Ave",
    "sg:city":"Macclenny",
    "sg:classifiers":[
        {
            "category":"Retail",
            "subcategory":"Repair Shop",
            "type":"Services"
        }
    ],
    "sg:phone":"+1 904 259 5106",
    "sg:postcode":"32063",
    "sg:province":"FL",
    "sg:tags":[
        "water",
        "equipment",
        "softening"
    ],
    "wof:name":"Carolyn Heights Water Co Inc",
    "wof:placetype":"venue"
},
  "geometry": {"coordinates":[-82.121444,30.282518],"type":"Point"}
}