{
  "type": "Feature",
  "properties": {
    "addr:full":"3449 NE 1st Ave Ste 112 Miami FL 33137",
    "addr:housenumber":"3449",
    "addr:postcode":"33137",
    "addr:street":"Ne 1St Ave Ste 112",
    "iso:country":"US",
    "sg:address":"3449 NE 1st Ave Ste 112",
    "sg:city":"Miami",
    "sg:classifiers":[
        {
            "category":"Education",
            "subcategory":"Dance Studio",
            "type":"Public Place"
        },
        {
            "category":"Arts & Performance",
            "subcategory":"Dance",
            "type":"Entertainment"
        }
    ],
    "sg:phone":"+1 305 799 9456",
    "sg:postcode":"33137",
    "sg:province":"FL",
    "sg:tags":[
        "school"
    ],
    "sg:website":"www.kittykatpoledancing.com/pole...",
    "wof:name":"Kitty Kat Pole Dancing Studio",
    "wof:placetype":"venue"
},
  "geometry": {"coordinates":[-80.19311399999999,25.810518],"type":"Point"}
}