{
  "type": "Feature",
  "properties": {
    "addr:full":"100 Ocean Trail Way Jupiter FL 33477",
    "addr:housenumber":"100",
    "addr:postcode":"33477",
    "addr:street":"Ocean Trail Way",
    "iso:country":"US",
    "sg:address":"100 Ocean Trail Way",
    "sg:city":"Jupiter",
    "sg:classifiers":[
        {
            "category":"Manufacturing",
            "subcategory":"Paper Products",
            "type":"Manufacturing & Wholesale Goods"
        }
    ],
    "sg:phone":"+1 561 747 0573",
    "sg:postcode":"33477",
    "sg:province":"FL",
    "sg:tags":[
        "wall",
        "painting"
    ],
    "wof:name":"Mark Leary Contractor",
    "wof:placetype":"venue"
},
  "geometry": {"coordinates":[-80.06996599999999,26.934143],"type":"Point"}
}