{
  "type": "Feature",
  "properties": {
    "addr:full":"8175 Navarre Pkwy Navarre FL 32566",
    "addr:housenumber":"8175",
    "addr:postcode":"32566",
    "addr:street":"Navarre Pkwy",
    "iso:country":"US",
    "sg:address":"8175 Navarre Pkwy",
    "sg:city":"Navarre",
    "sg:classifiers":[
        {
            "category":"Retail",
            "subcategory":"Auto Rental",
            "type":"Services"
        }
    ],
    "sg:phone":"+1 850 939 3973",
    "sg:postcode":"32566",
    "sg:province":"FL",
    "sg:tags":[
        "car"
    ],
    "wof:name":"Navarre Rent A Car Inc",
    "wof:placetype":"venue"
},
  "geometry": {"coordinates":[-86.88095199999999,30.401595],"type":"Point"}
}