{
  "type": "Feature",
  "properties": {
    "addr:full":"84001 Overseas Hwy Islamorada FL 33036",
    "addr:housenumber":"84001",
    "addr:postcode":"33036",
    "addr:street":"Overseas Hwy",
    "iso:country":"US",
    "sg:address":"84001 Overseas Hwy",
    "sg:city":"Islamorada",
    "sg:classifiers":[
        {
            "category":"Health Services",
            "subcategory":"Health Practitioner",
            "type":"Services"
        }
    ],
    "sg:phone":"+1 305 517 9099",
    "sg:postcode":"33036",
    "sg:province":"FL",
    "sg:tags":[
        "therapist",
        "physical"
    ],
    "wof:name":"Csc Holiday Land Lmt",
    "wof:placetype":"venue"
},
  "geometry": {"coordinates":[-80.60866900000001,24.941125],"type":"Point"}
}