{
  "type": "Feature",
  "properties": {
    "iso:country":"US",
    "sg:address":"910 W Main St",
    "sg:city":"Pensacola",
    "sg:classifiers":[
        {
            "category":"Building & Trades",
            "subcategory":"Plumbing",
            "type":"Services"
        }
    ],
    "sg:phone":"+1 850 432 3393",
    "sg:postcode":"32501",
    "sg:province":"FL",
    "sg:tags":[
        "plumbing",
        "contractor"
    ],
    "wof:name":"Warrington Plumbing Inc",
    "wof:placetype":"venue"
},
  "geometry": {"coordinates":[-87.22825899999999,30.405529],"type":"Point"}
}