{
  "type": "Feature",
  "properties": {
    "iso:country":"US",
    "sg:address":"129 W Hubbard Ave",
    "sg:city":"Deland",
    "sg:classifiers":[
        {
            "category":"Organizations",
            "subcategory":"Religious Organization",
            "type":"Services"
        }
    ],
    "sg:phone":"+1 386 736 6093",
    "sg:postcode":"32720",
    "sg:province":"FL",
    "sg:tags":[
        "church"
    ],
    "wof:name":"Apostolic Pentecost Church-God",
    "wof:placetype":"venue"
},
  "geometry": {"coordinates":[-81.30518499999999,29.01915],"type":"Point"}
}