{
  "type": "Feature",
  "properties": {
    "iso:country":"US",
    "sg:address":"1025 Linda Ln",
    "sg:city":"Lady Lake",
    "sg:classifiers":[
        {
            "category":"Building & Trades",
            "subcategory":"Landscaping Services",
            "type":"Services"
        }
    ],
    "sg:phone":"+1 352 753 3498",
    "sg:postcode":"32159",
    "sg:province":"FL",
    "wof:name":"Ptmi",
    "wof:placetype":"venue"
},
  "geometry": {"coordinates":[-81.93955200000001,28.94001],"type":"Point"}
}