{
  "type": "Feature",
  "properties": {
    "iso:country":"US",
    "sg:address":"384 N Lowder St",
    "sg:city":"Macclenny",
    "sg:classifiers":[
        {
            "category":"Personal",
            "subcategory":"Beauty Salon",
            "type":"Services"
        },
        {
            "category":"Personal",
            "subcategory":"Barber",
            "type":"Services"
        }
    ],
    "sg:phone":"+1 904 259 6497",
    "sg:postcode":"32063",
    "sg:province":"FL",
    "wof:name":"Rita's Classee Cuts",
    "wof:placetype":"venue"
},
  "geometry": {"coordinates":[-82.133591,30.285914],"type":"Point"}
}