{
  "type": "Feature",
  "properties": {
    "iso:country":"US",
    "sg:address":"12807 Madison Pointe Cir # 203",
    "sg:city":"Orlando",
    "sg:classifiers":[
        {
            "category":"Professional",
            "subcategory":"Computer Services",
            "type":"Services"
        }
    ],
    "sg:phone":"+1 407 842 6263",
    "sg:postcode":"32821",
    "sg:province":"FL",
    "sg:tags":[
        "systems-consultants",
        "designer",
        "data"
    ],
    "wof:name":"L & A Partners Inc",
    "wof:placetype":"venue"
},
  "geometry": {"coordinates":[-81.48801400000001,28.382879],"type":"Point"}
}