{
  "type": "Feature",
  "properties": {
    "iso:country":"US",
    "sg:address":"25 Seabreeze Ave",
    "sg:city":"Delray Beach",
    "sg:classifiers":[
        {
            "category":"Real Estate",
            "subcategory":"Real Estate Services",
            "type":"Services"
        }
    ],
    "sg:phone":"+1 561 276 8121",
    "sg:postcode":"33483",
    "sg:province":"FL",
    "sg:tags":[
        "company",
        "title"
    ],
    "wof:name":"Meridian Title",
    "wof:placetype":"venue"
},
  "geometry": {"coordinates":[-80.061342,26.463135],"type":"Point"}
}