{
  "type": "Feature",
  "properties": {
    "iso:country":"US",
    "sg:address":"10613 Lem Turner Rd",
    "sg:city":"Jacksonville",
    "sg:classifiers":[
        {
            "category":"Place Of Worship",
            "type":"Public Place"
        }
    ],
    "sg:phone":"+1 904 764 7781",
    "sg:postcode":"32218",
    "sg:province":"FL",
    "sg:tags":[
        "church"
    ],
    "wof:name":"VanDelinder, John",
    "wof:placetype":"venue"
},
  "geometry": {"coordinates":[-81.694277,30.427926],"type":"Point"}
}