{
  "type": "Feature",
  "properties": {
    "iso:country":"US",
    "sg:address":"1766 Sea Lark Ln",
    "sg:city":"Gulf Breeze",
    "sg:classifiers":[
        {
            "category":"Shopping",
            "subcategory":"Jewelry",
            "type":"Retail Goods"
        }
    ],
    "sg:phone":"+1 850 939 8300",
    "sg:postcode":"32566",
    "sg:province":"FL",
    "wof:name":"Sarah Ellis Jewelry",
    "wof:placetype":"venue"
},
  "geometry": {"coordinates":[-86.93402,30.401667],"type":"Point"}
}