{
  "type": "Feature",
  "properties": {
    "addr:full":"204 Sausalito Blvd Casselberry FL 32707",
    "addr:housenumber":"204",
    "addr:postcode":"32707",
    "addr:street":"Sausalito Blvd",
    "iso:country":"US",
    "sg:address":"204 Sausalito Blvd",
    "sg:city":"Casselberry",
    "sg:classifiers":[
        {
            "category":"Restaurant",
            "type":"Food & Drink"
        }
    ],
    "sg:menulink":"http://www.allmenus.com/fl/casselberry-altamonte-springs/113808-planet-smoothie/menu/",
    "sg:phone":"+1 407 260 0697",
    "sg:postcode":"32707",
    "sg:province":"FL",
    "sg:tags":[
        "smoothy",
        "juice",
        "american"
    ],
    "wof:name":"Planet Smoothie",
    "wof:placetype":"venue"
},
  "geometry": {"coordinates":[-81.32126,28.644301],"type":"Point"}
}