{
  "type": "Feature",
  "properties": {
    "addr:full":"1623 W Waters Ave Tampa FL 33604",
    "addr:housenumber":"1623",
    "addr:postcode":"33604",
    "addr:street":"W Waters Ave",
    "iso:country":"US",
    "sg:address":"1623 W Waters Ave",
    "sg:city":"Tampa",
    "sg:classifiers":[
        {
            "category":"Shopping",
            "subcategory":"Florist",
            "type":"Retail Goods"
        }
    ],
    "sg:phone":"+1 813 935 8400",
    "sg:postcode":"33604",
    "sg:province":"FL",
    "wof:name":"Quality Flowers And Decor",
    "wof:placetype":"venue"
},
  "geometry": {"coordinates":[-82.475471,28.025314],"type":"Point"}
}