{
  "type": "Feature",
  "properties": {
    "iso:country":"US",
    "sg:address":"5626 Tanglewood Ln",
    "sg:city":"Jacksonville",
    "sg:classifiers":[
        {
            "category":"Health Services",
            "subcategory":"Medical Lab",
            "type":"Services"
        }
    ],
    "sg:phone":"+1 904 855 0510",
    "sg:postcode":"32211",
    "sg:province":"FL",
    "sg:tags":[
        "laboratory"
    ],
    "wof:name":"B G Ortho Lab",
    "wof:placetype":"venue"
},
  "geometry": {"coordinates":[-81.60318599999999,30.325692],"type":"Point"}
}