{
  "type": "Feature",
  "properties": {
    "addr:full":"9254 Topohill Ct Jacksonville FL 32225",
    "addr:housenumber":"9254",
    "addr:postcode":"32225",
    "addr:street":"Topohill Ct",
    "iso:country":"US",
    "sg:address":"9254 Topohill Ct",
    "sg:city":"Jacksonville",
    "sg:classifiers":[
        {
            "category":"Social Services",
            "type":"Services"
        }
    ],
    "sg:phone":"+1 904 887 2191",
    "sg:postcode":"32225",
    "sg:province":"FL",
    "sg:tags":[
        "treatment",
        "homeless",
        "for"
    ],
    "wof:name":"TNT Connection Charities Inc",
    "wof:placetype":"venue"
},
  "geometry": {"coordinates":[-81.545828,30.351832],"type":"Point"}
}