{
  "type": "Feature",
  "properties": {
    "iso:country":"US",
    "sg:address":"1455 S.W. 13th. Ave.",
    "sg:city":"Miami",
    "sg:classifiers":[
        {
            "category":"Building & Trades",
            "subcategory":"Cleaning & Sanitation",
            "type":"Services"
        }
    ],
    "sg:phone":"+1 305 285 0030",
    "sg:postcode":"33145",
    "sg:province":"FL",
    "sg:tags":[
        "carpet"
    ],
    "sg:website":"www.carpetsaversusa.com",
    "wof:name":"C.S. Services Of Miami",
    "wof:placetype":"venue"
},
  "geometry": {"coordinates":[-80.21598299999999,25.759478],"type":"Point"}
}