{
  "type": "Feature",
  "properties": {
    "iso:country":"US",
    "sg:address":"1049 NE 6th Blvd",
    "sg:city":"Williston",
    "sg:classifiers":[
        {
            "category":"Organizations",
            "subcategory":"Community Association",
            "type":"Services"
        }
    ],
    "sg:phone":"+1 352 528 3222",
    "sg:postcode":"32696",
    "sg:province":"FL",
    "sg:tags":[
        "club"
    ],
    "wof:name":"Williston Woman's Club",
    "wof:placetype":"venue"
},
  "geometry": {"coordinates":[-82.439278,29.402096],"type":"Point"}
}