{
  "type": "Feature",
  "properties": {
    "iso:country":"US",
    "sg:address":"10920 NW 14th Ave Apt B35",
    "sg:city":"Miami",
    "sg:classifiers":[
        {
            "category":"Wholesale",
            "subcategory":"Music Publishers",
            "type":"Manufacturing & Wholesale Goods"
        },
        {
            "category":"Wholesale",
            "subcategory":"Books, Periodicals, & Newspapers",
            "type":"Manufacturing & Wholesale Goods"
        }
    ],
    "sg:phone":"+1 305 491 0235",
    "sg:postcode":"33167",
    "sg:province":"FL",
    "sg:tags":[
        "distribution"
    ],
    "wof:name":"Lyricsim Music Publishing Company",
    "wof:placetype":"venue"
},
  "geometry": {"coordinates":[-80.22292899999999,25.873837],"type":"Point"}
}