{
  "type": "Feature",
  "properties": {
    "addr:full":"4831 Shane Way Milton FL 32571",
    "addr:housenumber":"4831",
    "addr:postcode":"32571",
    "addr:street":"Shane Way",
    "iso:country":"US",
    "sg:address":"4831 Shane Way",
    "sg:city":"Milton",
    "sg:classifiers":[
        {
            "category":"Place Of Worship",
            "type":"Public Place"
        }
    ],
    "sg:phone":"+1 850 995 4632",
    "sg:postcode":"32571",
    "sg:province":"FL",
    "sg:tags":[
        "church"
    ],
    "wof:name":"Redeemer Church Of Pace Inc",
    "wof:placetype":"venue"
},
  "geometry": {"coordinates":[-87.140995,30.611486],"type":"Point"}
}