{
  "type": "Feature",
  "properties": {
    "addr:full":"5394 S Florida Ave Inverness FL 34450",
    "addr:housenumber":"5394",
    "addr:postcode":"34450",
    "addr:street":"S Florida Ave",
    "iso:country":"US",
    "sg:address":"5394 S Florida Ave",
    "sg:city":"Inverness",
    "sg:classifiers":[
        {
            "category":"Building & Trades",
            "subcategory":"Construction",
            "type":"Services"
        }
    ],
    "sg:phone":"+1 352 344 8989",
    "sg:postcode":"34450",
    "sg:province":"FL",
    "sg:tags":[
        "clearing",
        "land",
        "leveling"
    ],
    "wof:name":"Richard Debusk Inc",
    "wof:placetype":"venue"
},
  "geometry": {"coordinates":[-82.29827899999999,28.783536],"type":"Point"}
}