{
  "type": "Feature",
  "properties": {
    "addr:full":"1335 Edgewood Ave W Jacksonville FL 32208",
    "addr:housenumber":"1335",
    "addr:postcode":"32208",
    "addr:street":"Edgewood Ave W",
    "iso:country":"US",
    "sg:address":"1335 Edgewood Ave W",
    "sg:city":"Jacksonville",
    "sg:classifiers":[
        {
            "category":"Shopping",
            "subcategory":"Used Merchandise",
            "type":"Retail Goods"
        }
    ],
    "sg:phone":"+1 904 764 1119",
    "sg:postcode":"32208",
    "sg:province":"FL",
    "sg:tags":[
        "pawnbroker"
    ],
    "wof:name":"EZ Pawn Inc",
    "wof:placetype":"venue"
},
  "geometry": {"coordinates":[-81.680122,30.390557],"type":"Point"}
}