{
  "type": "Feature",
  "properties": {
    "iso:country":"US",
    "sg:address":"6745 Phillips Industrial Blvd",
    "sg:city":"Jacksonville",
    "sg:classifiers":[
        {
            "category":"Manufacturing",
            "subcategory":"Textiles",
            "type":"Manufacturing & Wholesale Goods"
        }
    ],
    "sg:phone":"+1 904 363 0196",
    "sg:postcode":"32256",
    "sg:province":"FL",
    "sg:tags":[
        "rug",
        "carpet"
    ],
    "wof:name":"Itel",
    "wof:placetype":"venue"
},
  "geometry": {"coordinates":[-81.529421,30.159218],"type":"Point"}
}