{
  "type": "Feature",
  "properties": {
    "addr:full":"9268 SE Island Pl Jupiter FL 33469",
    "addr:housenumber":"9268",
    "addr:postcode":"33469",
    "addr:street":"Se Island Pl",
    "iso:country":"US",
    "sg:address":"9268 SE Island Pl",
    "sg:city":"Jupiter",
    "sg:classifiers":[
        {
            "category":"Professional",
            "type":"Services"
        }
    ],
    "sg:phone":"+1 561 746 3962",
    "sg:postcode":"33469",
    "sg:province":"FL",
    "wof:name":"Underground Audio Promoti",
    "wof:placetype":"venue"
},
  "geometry": {"coordinates":[-80.129653,26.976251],"type":"Point"}
}