{
  "type": "Feature",
  "properties": {
    "addr:full":"1015 E 4th Ave Hialeah FL 33010",
    "addr:housenumber":"1015",
    "addr:postcode":"33010",
    "addr:street":"E 4Th Ave",
    "iso:country":"US",
    "sg:address":"1015 E 4th Ave",
    "sg:city":"Hialeah",
    "sg:classifiers":[
        {
            "category":"Structure",
            "subcategory":"Office Building",
            "type":"Public Place"
        },
        {
            "category":"Home & Garden",
            "subcategory":"Furniture",
            "type":"Retail Goods"
        }
    ],
    "sg:phone":"+1 786 953 4527",
    "sg:postcode":"33010",
    "sg:province":"FL",
    "sg:tags":[
        "renting",
        "leasing",
        "space",
        "desk",
        "rental"
    ],
    "wof:name":"K And Y Multiservices",
    "wof:placetype":"venue"
},
  "geometry": {"coordinates":[-80.273633,25.831208],"type":"Point"}
}