{
  "type": "Feature",
  "properties": {
    "addr:full":"6180 N Lockwood Ridge Rd Sarasota FL 34243",
    "addr:housenumber":"6180",
    "addr:postcode":"34243",
    "addr:street":"N Lockwood Ridge Rd",
    "iso:country":"US",
    "sg:address":"6180 N Lockwood Ridge Rd",
    "sg:city":"Sarasota",
    "sg:classifiers":[
        {
            "category":"Shopping",
            "subcategory":"Department Store",
            "type":"Retail Goods"
        }
    ],
    "sg:phone":"+1 941 351 8424",
    "sg:postcode":"34243",
    "sg:province":"FL",
    "wof:name":"Beall's Department Store",
    "wof:placetype":"venue"
},
  "geometry": {"coordinates":[-82.505546,27.388617],"type":"Point"}
}