{
  "type": "Feature",
  "properties": {
    "addr:full":"9391 N Meadows Cir Miramar FL 33025",
    "addr:housenumber":"9391",
    "addr:postcode":"33025",
    "addr:street":"N Meadows Cir",
    "iso:country":"US",
    "sg:address":"9391 N Meadows Cir",
    "sg:city":"Miramar",
    "sg:classifiers":[
        {
            "category":"Freight",
            "type":"Transportation"
        }
    ],
    "sg:phone":"+1 954 441 3511",
    "sg:postcode":"33025",
    "sg:province":"FL",
    "sg:tags":[
        "delivery"
    ],
    "wof:name":"Arboleda's Catering",
    "wof:placetype":"venue"
},
  "geometry": {"coordinates":[-80.269655,25.980417],"type":"Point"}
}