{
  "type": "Feature",
  "properties": {
    "iso:country":"US",
    "sg:address":"450 S Orange Ave",
    "sg:city":"Orlando",
    "sg:classifiers":[
        {
            "category":"Banks & Credit Unions",
            "subcategory":"Investment Brokerage",
            "type":"Services"
        }
    ],
    "sg:phone":"+1 407 650 1996",
    "sg:postcode":"32801",
    "sg:province":"FL",
    "sg:tags":[
        "stock",
        "exchange"
    ],
    "sg:website":"www.etradeprofessional.com",
    "wof:name":"E Trade",
    "wof:placetype":"venue"
},
  "geometry": {"coordinates":[-81.37876300000001,28.537727],"type":"Point"}
}