{
  "type": "Feature",
  "properties": {
    "addr:full":"6050 State Hwy 70 Bradenton FL 34203",
    "addr:housenumber":"6050",
    "addr:postcode":"34203",
    "addr:street":"State Hwy 70",
    "iso:country":"US",
    "sg:address":"6050 State Hwy 70",
    "sg:city":"Bradenton",
    "sg:classifiers":[
        {
            "category":"Health Services",
            "subcategory":"Doctor",
            "type":"Services"
        }
    ],
    "sg:phone":"+1 941 758 1285",
    "sg:postcode":"34203",
    "sg:province":"FL",
    "sg:tags":[
        "physician",
        "surgeon"
    ],
    "wof:name":"Joseph Placheril MD",
    "wof:placetype":"venue"
},
  "geometry": {"coordinates":[-82.482282,27.445855],"type":"Point"}
}