{
  "type": "Feature",
  "properties": {
    "iso:country":"US",
    "sg:address":"10001 66th St",
    "sg:city":"Pinellas Park",
    "sg:classifiers":[
        {
            "category":"Bars & Pubs",
            "type":"Food & Drink"
        }
    ],
    "sg:phone":"+1 727 545 0943",
    "sg:postcode":"33782",
    "sg:province":"FL",
    "sg:tags":[
        "lounge",
        "cocktail"
    ],
    "wof:name":"Hideaway Lounge",
    "wof:placetype":"venue"
},
  "geometry": {"coordinates":[-82.72887799999999,27.86463],"type":"Point"}
}