{
  "type": "Feature",
  "properties": {
    "addr:full":"12016 NW 47th St Coral Springs FL 33076",
    "addr:housenumber":"12016",
    "addr:postcode":"33076",
    "addr:street":"Nw 47Th St",
    "iso:country":"US",
    "sg:address":"12016 NW 47th St",
    "sg:city":"Coral Springs",
    "sg:classifiers":[
        {
            "category":"Retail",
            "subcategory":"Laundry & Dry Cleaning",
            "type":"Services"
        }
    ],
    "sg:phone":"+1 954 575 9993",
    "sg:postcode":"33076",
    "sg:province":"FL",
    "sg:tags":[
        "cleaners"
    ],
    "wof:name":"Ram T Udnani Inc",
    "wof:placetype":"venue"
},
  "geometry": {"coordinates":[-80.287429,26.290138],"type":"Point"}
}