{
  "type": "Feature",
  "properties": {
    "addr:full":"7008 W Colonial Dr Orlando FL 32818",
    "addr:housenumber":"7008",
    "addr:postcode":"32818",
    "addr:street":"W Colonial Dr",
    "iso:country":"US",
    "sg:address":"7008 W Colonial Dr",
    "sg:city":"Orlando",
    "sg:classifiers":[
        {
            "category":"Health Services",
            "subcategory":"Optometrist",
            "type":"Services"
        }
    ],
    "sg:phone":"+1 407 294 5691",
    "sg:postcode":"32818",
    "sg:province":"FL",
    "sg:website":"www.ecca.com",
    "wof:name":"Perry Perry & Assoc",
    "wof:placetype":"venue"
},
  "geometry": {"coordinates":[-81.47601899999999,28.552015],"type":"Point"}
}