{
  "type": "Feature",
  "properties": {
    "addr:full":"216 Banbury Pl Kissimmee FL 34758",
    "addr:housenumber":"216",
    "addr:postcode":"34758",
    "addr:street":"Banbury Pl",
    "iso:country":"US",
    "sg:address":"216 Banbury Pl",
    "sg:city":"Kissimmee",
    "sg:classifiers":[
        {
            "category":"Home & Garden",
            "subcategory":"Hardware",
            "type":"Retail Goods"
        }
    ],
    "sg:phone":"+1 407 343 5883",
    "sg:postcode":"34758",
    "sg:province":"FL",
    "sg:tags":[
        "toilet",
        "partition"
    ],
    "wof:name":"J & L Installings Inc",
    "wof:placetype":"venue"
},
  "geometry": {"coordinates":[-81.499129,28.190661],"type":"Point"}
}