{
  "type": "Feature",
  "properties": {
    "addr:full":"1709 Dale Mabry Hwy Lutz FL 33548",
    "addr:housenumber":"1709",
    "addr:postcode":"33548",
    "addr:street":"Dale Mabry Hwy",
    "iso:country":"US",
    "sg:address":"1709 Dale Mabry Hwy",
    "sg:city":"Lutz",
    "sg:classifiers":[
        {
            "category":"Insurance",
            "subcategory":"Hazard Insurance",
            "type":"Services"
        }
    ],
    "sg:phone":"+1 813 428 6930",
    "sg:postcode":"33548",
    "sg:province":"FL",
    "sg:tags":[
        "commercial",
        "business"
    ],
    "wof:name":"Safe Leverage Insurance Corp",
    "wof:placetype":"venue"
},
  "geometry": {"coordinates":[-82.468378,28.182122],"type":"Point"}
}