{
  "type": "Feature",
  "properties": {
    "addr:full":"808 W Base St Madison FL 32340",
    "addr:housenumber":"808",
    "addr:postcode":"32340",
    "addr:street":"W Base St",
    "iso:country":"US",
    "sg:address":"808 W Base St",
    "sg:city":"Madison",
    "sg:classifiers":[
        {
            "category":"Health Services",
            "subcategory":"Health Practitioner",
            "type":"Services"
        }
    ],
    "sg:phone":"+1 850 973 2187",
    "sg:postcode":"32340",
    "sg:province":"FL",
    "wof:name":"Allied Therapy Services",
    "wof:placetype":"venue"
},
  "geometry": {"coordinates":[-83.42261999999999,30.47048],"type":"Point"}
}