{
  "type": "Feature",
  "properties": {
    "addr:full":"22135 US Hwy 19 Clearwater FL 33765",
    "addr:postcode":"22135;33765",
    "addr:street":"Us Hwy 19",
    "iso:country":"US",
    "sg:address":"22135 US Hwy 19",
    "sg:city":"Clearwater",
    "sg:classifiers":[
        {
            "category":"Professional",
            "subcategory":"Business Services",
            "type":"Services"
        }
    ],
    "sg:phone":"+1 727 791 6011",
    "sg:postcode":"33765",
    "sg:province":"FL",
    "sg:tags":[
        "recording",
        "studio"
    ],
    "wof:name":"Panda Productions",
    "wof:placetype":"venue"
},
  "geometry": {"coordinates":[-82.72971800000001,27.974753],"type":"Point"}
}