{
  "type": "Feature",
  "properties": {
    "addr:full":"1507 Bay Palm Blvd Indian Rocks Bch FL 33785",
    "addr:housenumber":"1507",
    "addr:postcode":"33785",
    "addr:street":"Bay Palm Blvd Indian Rocks",
    "iso:country":"US",
    "sg:address":"1507 Bay Palm Blvd",
    "sg:city":"Indian Rocks Bch",
    "sg:classifiers":[
        {
            "category":"Government",
            "subcategory":"Office",
            "type":"Public Place"
        }
    ],
    "sg:phone":"+1 727 595 6889",
    "sg:postcode":"33785",
    "sg:province":"FL",
    "sg:tags":[
        "village"
    ],
    "wof:name":"Public Services",
    "wof:placetype":"venue"
},
  "geometry": {"coordinates":[-82.845951,27.898602],"type":"Point"}
}