{
  "type": "Feature",
  "properties": {
    "addr:full":"109 4th St SW Zolfo Springs FL 33841",
    "addr:housenumber":"109",
    "addr:postcode":"33841",
    "addr:street":"4Th St Sw Zolfo Springs",
    "iso:country":"US",
    "sg:address":"109 4th St SW",
    "sg:city":"Zolfo Springs",
    "sg:classifiers":[
        {
            "category":"Government",
            "subcategory":"Office",
            "type":"Public Place"
        }
    ],
    "sg:phone":"+1 863 735 0481",
    "sg:postcode":"33841",
    "sg:province":"FL",
    "sg:tags":[
        "county"
    ],
    "wof:name":"Hardy County Pro Firefighters",
    "wof:placetype":"venue"
},
  "geometry": {"coordinates":[-81.802941,27.746756],"type":"Point"}
}