{
  "type": "Feature",
  "properties": {
    "iso:country":"US",
    "sg:address":"19 W Flagler St Ste 802",
    "sg:city":"Miami",
    "sg:classifiers":[
        {
            "category":"Professional",
            "subcategory":"Lawyer & Legal Services",
            "type":"Services"
        }
    ],
    "sg:phone":"+1 305 371 1631",
    "sg:postcode":"33130",
    "sg:province":"FL",
    "sg:tags":[
        "attorney",
        "law",
        "family",
        "estate",
        "divorce",
        "wills",
        "planning",
        "trust"
    ],
    "wof:name":"Berg Martin David PA Atty",
    "wof:placetype":"venue"
},
  "geometry": {"coordinates":[-80.193901,25.774099],"type":"Point"}
}