{
  "type": "Feature",
  "properties": {
    "iso:country":"US",
    "sg:address":"4509 Struth Ln",
    "sg:city":"Milton",
    "sg:classifiers":[
        {
            "category":"Retail",
            "subcategory":"Repair Shop",
            "type":"Services"
        }
    ],
    "sg:phone":"+1 850 994 5160",
    "sg:postcode":"32571",
    "sg:province":"FL",
    "sg:tags":[
        "taxicab"
    ],
    "wof:name":"Donald Cooley Taxidermy",
    "wof:placetype":"venue"
},
  "geometry": {"coordinates":[-87.09860999999999,30.598788],"type":"Point"}
}