{
  "type": "Feature",
  "properties": {
    "iso:country":"US",
    "sg:address":"2901 Clint Moore Rd",
    "sg:city":"Boca Raton",
    "sg:classifiers":[
        {
            "category":"Wholesale",
            "subcategory":"Apparel",
            "type":"Manufacturing & Wholesale Goods"
        }
    ],
    "sg:phone":"+1 561 912 9894",
    "sg:postcode":"33496",
    "sg:province":"FL",
    "sg:tags":[
        "shoes"
    ],
    "wof:name":"Alex Blake Footwear",
    "wof:placetype":"venue"
},
  "geometry": {"coordinates":[-80.146287,26.407932],"type":"Point"}
}