{
  "type": "Feature",
  "properties": {
    "iso:country":"US",
    "sg:address":"3440 E Lake Rd S",
    "sg:city":"Palm Harbor",
    "sg:classifiers":[
        {
            "category":"Shopping",
            "type":"Retail Goods"
        }
    ],
    "sg:phone":"+1 727 781 5600",
    "sg:postcode":"34685",
    "sg:province":"FL",
    "sg:tags":[
        "merchandise"
    ],
    "wof:name":"Clearwater Limb Brace-Eastlake",
    "wof:placetype":"venue"
},
  "geometry": {"coordinates":[-82.694231,28.097598],"type":"Point"}
}