{
  "type": "Feature",
  "properties": {
    "iso:country":"US",
    "sg:address":"640 SE Ocean Blvd",
    "sg:city":"Stuart",
    "sg:classifiers":[
        {
            "category":"Health Services",
            "subcategory":"Doctor",
            "type":"Services"
        }
    ],
    "sg:phone":"+1 772 287 2448",
    "sg:postcode":"34994",
    "sg:province":"FL",
    "sg:tags":[
        "clinic",
        "medical"
    ],
    "wof:name":"Medical Partners Martin County",
    "wof:placetype":"venue"
},
  "geometry": {"coordinates":[-80.244012,27.19743],"type":"Point"}
}