{
  "type": "Feature",
  "properties": {
    "addr:full":"1805 Harbinger Ter Deltona FL 32738",
    "addr:housenumber":"1805",
    "addr:postcode":"32738",
    "addr:street":"Harbinger Ter",
    "iso:country":"US",
    "sg:address":"1805 Harbinger Ter",
    "sg:city":"Deltona",
    "sg:classifiers":[
        {
            "category":"Retail",
            "subcategory":"Animal Services",
            "type":"Services"
        }
    ],
    "sg:phone":"+1 386 789 2064",
    "sg:postcode":"32738",
    "sg:province":"FL",
    "sg:tags":[
        "cat",
        "dog",
        "kennel"
    ],
    "wof:name":"TLC Critter's Sitting",
    "wof:placetype":"venue"
},
  "geometry": {"coordinates":[-81.192437,28.914847],"type":"Point"}
}