{
  "type": "Feature",
  "properties": {
    "iso:country":"US",
    "sg:address":"6830 SW 25th Ter",
    "sg:city":"Miami",
    "sg:classifiers":[
        {
            "category":"Building & Trades",
            "subcategory":"Construction",
            "type":"Services"
        }
    ],
    "sg:phone":"+1 786 247 3923",
    "sg:postcode":"33155",
    "sg:province":"FL",
    "sg:tags":[
        "drywall",
        "contractor"
    ],
    "wof:name":"Jvr",
    "wof:placetype":"venue"
},
  "geometry": {"coordinates":[-80.305953,25.746528],"type":"Point"}
}