{
  "type": "Feature",
  "properties": {
    "iso:country":"US",
    "sg:address":"10916 Atlantic Blvd",
    "sg:city":"Jacksonville",
    "sg:classifiers":[
        {
            "category":"Restaurant",
            "type":"Food & Drink"
        }
    ],
    "sg:menulink":"http://www.allmenus.com/fl/jacksonville/157708-sushi--wok/menu/",
    "sg:phone":"+1 904 642 5522",
    "sg:postcode":"32225",
    "sg:province":"FL",
    "sg:tags":[
        "sushi",
        "asian"
    ],
    "wof:name":"Sushi & Wok",
    "wof:placetype":"venue"
},
  "geometry": {"coordinates":[-81.517642,30.324517],"type":"Point"}
}