{
  "type": "Feature",
  "properties": {
    "iso:country":"US",
    "sg:address":"5534 Hansel Ave",
    "sg:city":"Orlando",
    "sg:classifiers":[
        {
            "category":"Manufacturing",
            "subcategory":"Printing",
            "type":"Manufacturing & Wholesale Goods"
        }
    ],
    "sg:phone":"+1 407 855 9541",
    "sg:postcode":"32809",
    "sg:province":"FL",
    "sg:tags":[
        "newspaper"
    ],
    "wof:name":"Archers Brasileiros Newspaper",
    "wof:placetype":"venue"
},
  "geometry": {"coordinates":[-81.370092,28.479354],"type":"Point"}
}