{
  "type": "Feature",
  "properties": {
    "iso:country":"US",
    "sg:address":"113 Laurel Oak Dr",
    "sg:city":"Longwood",
    "sg:classifiers":[
        {
            "category":"Shopping",
            "subcategory":"Computers & Home Electronics",
            "type":"Retail Goods"
        }
    ],
    "sg:phone":"+1 407 774 9615",
    "sg:postcode":"32779",
    "sg:province":"FL",
    "wof:name":"Sam Samanis Computer Services",
    "wof:placetype":"venue"
},
  "geometry": {"coordinates":[-81.434,28.706665],"type":"Point"}
}