{
  "type": "Feature",
  "properties": {
    "iso:country":"US",
    "sg:address":"5850 NE 21st Ln",
    "sg:city":"Fort Lauderdale",
    "sg:classifiers":[
        {
            "category":"Professional",
            "type":"Services"
        }
    ],
    "sg:phone":"+1 954 938 0287",
    "sg:postcode":"33308",
    "sg:province":"FL",
    "wof:name":"Emilio Angelone",
    "wof:placetype":"venue"
},
  "geometry": {"coordinates":[-80.115037,26.201223],"type":"Point"}
}