{
  "type": "Feature",
  "properties": {
    "addr:full":"501 N Orange Ave Orlando FL 32801",
    "addr:housenumber":"501",
    "addr:postcode":"32801",
    "addr:street":"N Orange Ave",
    "iso:country":"US",
    "sg:address":"501 N Orange Ave",
    "sg:city":"Orlando",
    "sg:classifiers":[
        {
            "category":"Building & Trades",
            "subcategory":"Construction",
            "type":"Services"
        }
    ],
    "sg:phone":"+1 407 648 8572",
    "sg:postcode":"32801",
    "sg:province":"FL",
    "sg:tags":[
        "nonresidential"
    ],
    "wof:name":"Baker Hughes Oilfld Operations",
    "wof:placetype":"venue"
},
  "geometry": {"coordinates":[-81.379165,28.550946],"type":"Point"}
}