{
  "type": "Feature",
  "properties": {
    "iso:country":"US",
    "sg:address":"720 Thorpe Rd",
    "sg:city":"Orlando",
    "sg:classifiers":[
        {
            "category":"Building & Trades",
            "subcategory":"Construction",
            "type":"Services"
        }
    ],
    "sg:phone":"+1 407 812 1715",
    "sg:postcode":"32824",
    "sg:province":"FL",
    "sg:tags":[
        "development",
        "site"
    ],
    "wof:name":"B & H Asphalt Paving",
    "wof:placetype":"venue"
},
  "geometry": {"coordinates":[-81.39234399999999,28.428772],"type":"Point"}
}