{
  "type": "Feature",
  "properties": {
    "iso:country":"US",
    "sg:address":"700 Marine St SE",
    "sg:city":"Carrabelle",
    "sg:classifiers":[
        {
            "category":"Restaurant",
            "type":"Food & Drink"
        },
        {
            "category":"Food & Beverages",
            "subcategory":"Meat & Fish",
            "type":"Retail Goods"
        }
    ],
    "sg:phone":"+1 850 697 3301",
    "sg:postcode":"32322",
    "sg:province":"FL",
    "sg:tags":[
        "seafood",
        "seafood-wholesale",
        "market"
    ],
    "wof:name":"Millender & Son Seafood",
    "wof:placetype":"venue"
},
  "geometry": {"coordinates":[-84.66387899999999,29.84621],"type":"Point"}
}