{
  "type": "Feature",
  "properties": {
    "iso:country":"US",
    "sg:address":"6560 Old Winter Garden Rd",
    "sg:city":"Orlando",
    "sg:classifiers":[
        {
            "category":"Personal",
            "subcategory":"Nail Salon",
            "type":"Services"
        }
    ],
    "sg:phone":"+1 407 290 1664",
    "sg:postcode":"32835",
    "sg:province":"FL",
    "wof:name":"US Nail",
    "wof:placetype":"venue"
},
  "geometry": {"coordinates":[-81.472544,28.538761],"type":"Point"}
}