{
  "type": "Feature",
  "properties": {
    "addr:full":"1038 Shadick Dr Orange City FL 32763",
    "addr:housenumber":"1038",
    "addr:postcode":"32763",
    "addr:street":"Shadick Dr",
    "iso:country":"US",
    "sg:address":"1038 Shadick Dr",
    "sg:city":"Orange City",
    "sg:classifiers":[
        {
            "category":"Retail",
            "subcategory":"Auto Repair",
            "type":"Services"
        }
    ],
    "sg:phone":"+1 386 774 7011",
    "sg:postcode":"32763",
    "sg:province":"FL",
    "wof:name":"Premier Auto Work",
    "wof:placetype":"venue"
},
  "geometry": {"coordinates":[-81.28510300000001,28.9387],"type":"Point"}
}