{
  "type": "Feature",
  "properties": {
    "addr:full":"1490 Banks Rd Margate FL 33063",
    "addr:housenumber":"1490",
    "addr:postcode":"33063",
    "addr:street":"Banks Rd Margate",
    "iso:country":"US",
    "sg:address":"1490 Banks Rd",
    "sg:city":"Margate",
    "sg:classifiers":[
        {
            "category":"Organizations",
            "subcategory":"Religious Organization",
            "type":"Services"
        }
    ],
    "sg:phone":"+1 954 973 0152",
    "sg:postcode":"33063",
    "sg:province":"FL",
    "wof:name":"Seed Of Harvest Ministries",
    "wof:placetype":"venue"
},
  "geometry": {"coordinates":[-80.19420599999999,26.248289],"type":"Point"}
}