{
  "type": "Feature",
  "properties": {
    "addr:full":"32628 Vista Ave Leesburg FL 34788",
    "addr:housenumber":"32628",
    "addr:postcode":"34788",
    "addr:street":"Vista Ave",
    "iso:country":"US",
    "sg:address":"32628 Vista Ave",
    "sg:city":"Leesburg",
    "sg:classifiers":[
        {
            "category":"Retail",
            "subcategory":"Veterinary Services",
            "type":"Services"
        }
    ],
    "sg:phone":"+1 352 323 0001",
    "sg:postcode":"34788",
    "sg:province":"FL",
    "sg:tags":[
        "hospital",
        "full",
        "animal"
    ],
    "wof:name":"Lake Square Animal Hospital",
    "wof:placetype":"venue"
},
  "geometry": {"coordinates":[-81.78809699999999,28.825269],"type":"Point"}
}