{
  "type": "Feature",
  "properties": {
    "addr:full":"398 NE 38th St Fort Lauderdale FL 33334",
    "addr:housenumber":"398",
    "addr:postcode":"33334",
    "addr:street":"Ne 38Th St",
    "iso:country":"US",
    "sg:address":"398 NE 38th St",
    "sg:city":"Fort Lauderdale",
    "sg:classifiers":[
        {
            "category":"Manufacturing",
            "subcategory":"Electronics",
            "type":"Manufacturing & Wholesale Goods"
        },
        {
            "category":"Manufacturing",
            "subcategory":"Tools & Machinery",
            "type":"Manufacturing & Wholesale Goods"
        }
    ],
    "sg:phone":"+1 954 537 5577",
    "sg:postcode":"33334",
    "sg:province":"FL",
    "sg:tags":[
        "portable",
        "micro",
        "supply",
        "equipment",
        "test",
        "electronic"
    ],
    "wof:name":"Startek International Inc",
    "wof:placetype":"venue"
},
  "geometry": {"coordinates":[-80.142663,26.174041],"type":"Point"}
}