{
  "type": "Feature",
  "properties": {
    "addr:full":"570 Gleason St Orange City FL 32763",
    "addr:housenumber":"570",
    "addr:postcode":"32763",
    "addr:street":"Gleason St",
    "iso:country":"US",
    "sg:address":"570 Gleason St",
    "sg:city":"Orange City",
    "sg:classifiers":[
        {
            "category":"Building & Trades",
            "subcategory":"Construction",
            "type":"Services"
        }
    ],
    "sg:phone":"+1 386 804 2543",
    "sg:postcode":"32763",
    "sg:province":"FL",
    "sg:tags":[
        "house"
    ],
    "wof:name":"Michaels Home Repairs",
    "wof:placetype":"venue"
},
  "geometry": {"coordinates":[-81.31028499999999,28.953557],"type":"Point"}
}