{
  "type": "Feature",
  "properties": {
    "iso:country":"US",
    "sg:address":"9410 SW 77th Ave",
    "sg:city":"Miami",
    "sg:classifiers":[
        {
            "category":"Professional",
            "subcategory":"Lawyer & Legal Services",
            "type":"Services"
        }
    ],
    "sg:phone":"+1 305 274 7533",
    "sg:postcode":"33156",
    "sg:province":"FL",
    "sg:tags":[
        "litigation",
        "attorney",
        "accident",
        "trial",
        "personal",
        "damage",
        "civil",
        "malpractice",
        "injury",
        "property",
        "law"
    ],
    "sg:website":"http://www.kaplanfreedman.com",
    "wof:name":"Kaplan & Freedman",
    "wof:placetype":"venue"
},
  "geometry": {"coordinates":[-80.319199,25.6821],"type":"Point"}
}