{
  "type": "Feature",
  "properties": {
    "addr:full":"4142 Sunset Dr Zolfo Springs FL 33890",
    "addr:housenumber":"4142",
    "addr:postcode":"33890",
    "addr:street":"Sunset Dr Zolfo Springs",
    "iso:country":"US",
    "sg:address":"4142 Sunset Dr",
    "sg:city":"Zolfo Springs",
    "sg:classifiers":[
        {
            "category":"Organizations",
            "subcategory":"Religious Organization",
            "type":"Services"
        }
    ],
    "sg:phone":"+1 863 735 0555",
    "sg:postcode":"33890",
    "sg:province":"FL",
    "sg:tags":[
        "church"
    ],
    "wof:name":"New Beginning Church",
    "wof:placetype":"venue"
},
  "geometry": {"coordinates":[-81.737537,27.47587],"type":"Point"}
}