{
  "type": "Feature",
  "properties": {
    "iso:country":"US",
    "sg:address":"1600 W Marion Ave",
    "sg:city":"Punta Gorda",
    "sg:classifiers":[
        {
            "category":"Personal",
            "subcategory":"Beauty Salon",
            "type":"Services"
        }
    ],
    "sg:phone":"+1 941 637 1811",
    "sg:postcode":"33950",
    "sg:province":"FL",
    "sg:tags":[
        "shop",
        "manicuring"
    ],
    "wof:name":"Great Lengths Nail Boutique",
    "wof:placetype":"venue"
},
  "geometry": {"coordinates":[-82.068905,26.924763],"type":"Point"}
}