{
  "type": "Feature",
  "properties": {
    "addr:full":"9889 S Orange Blossom Trl Orlando FL 32837",
    "addr:housenumber":"9889",
    "addr:postcode":"32837",
    "addr:street":"S Orange Blossom Trl",
    "iso:country":"US",
    "sg:address":"9889 S Orange Blossom Trl",
    "sg:city":"Orlando",
    "sg:classifiers":[
        {
            "category":"Autos & Motor Vehicles",
            "subcategory":"Automobile Sales",
            "type":"Retail Goods"
        }
    ],
    "sg:phone":"+1 407 854 7332",
    "sg:postcode":"32837",
    "sg:province":"FL",
    "sg:tags":[
        "car",
        "dealer"
    ],
    "wof:name":"America's Choice Intl Inc",
    "wof:placetype":"venue"
},
  "geometry": {"coordinates":[-81.40461500000001,28.419587],"type":"Point"}
}