{
  "type": "Feature",
  "properties": {
    "addr:full":"3518 Shore Line Cir Palm Harbor FL 34684",
    "addr:housenumber":"3518",
    "addr:postcode":"34684",
    "addr:street":"Shore Line Cir",
    "iso:country":"US",
    "sg:address":"3518 Shore Line Cir",
    "sg:city":"Palm Harbor",
    "sg:classifiers":[
        {
            "category":"Professional",
            "type":"Services"
        }
    ],
    "sg:phone":"+1 727 786 8971",
    "sg:postcode":"34684",
    "sg:province":"FL",
    "wof:name":"Terry L Tillung PA",
    "wof:placetype":"venue"
},
  "geometry": {"coordinates":[-82.718074,28.088762],"type":"Point"}
}