{
  "type": "Feature",
  "properties": {
    "addr:full":"4340 Caryota Dr Boynton Beach FL 33436",
    "addr:postcode":"4340;33436",
    "addr:street":"Caryota Dr",
    "iso:country":"US",
    "sg:address":"4340 Caryota Dr",
    "sg:city":"Boynton Beach",
    "sg:classifiers":[
        {
            "category":"Marine",
            "type":"Transportation"
        }
    ],
    "sg:phone":"+1 561 659 0911",
    "sg:postcode":"33436",
    "sg:province":"FL",
    "sg:tags":[
        "cleaning",
        "boat"
    ],
    "wof:name":"Boat MD",
    "wof:placetype":"venue"
},
  "geometry": {"coordinates":[-80.113342,26.536469],"type":"Point"}
}