{
  "type": "Feature",
  "properties": {
    "addr:full":"6230 SW 44th St Miami FL 33155",
    "addr:housenumber":"6230",
    "addr:postcode":"33155",
    "addr:street":"Sw 44Th St",
    "iso:country":"US",
    "sg:address":"6230 SW 44th St",
    "sg:city":"Miami",
    "sg:classifiers":[
        {
            "category":"Communications",
            "subcategory":"Film & Video Production",
            "type":"Services"
        }
    ],
    "sg:phone":"+1 305 667 7381",
    "sg:postcode":"33155",
    "sg:province":"FL",
    "sg:tags":[
        "motion",
        "tv",
        "radio",
        "companies-film"
    ],
    "wof:name":"Boom Town Productions Inc",
    "wof:placetype":"venue"
},
  "geometry": {"coordinates":[-80.295447,25.729922],"type":"Point"}
}