{
  "type": "Feature",
  "properties": {
    "iso:country":"US",
    "sg:address":"4561 Douglas St",
    "sg:city":"Lake Monroe",
    "sg:classifiers":[
        {
            "category":"Organizations",
            "subcategory":"Religious Organization",
            "type":"Services"
        }
    ],
    "sg:phone":"+1 407 323 3984",
    "sg:postcode":"32771",
    "sg:province":"FL",
    "sg:tags":[
        "church"
    ],
    "wof:name":"Providence Missionary Baptist",
    "wof:placetype":"venue"
},
  "geometry": {"coordinates":[-81.331878,28.826007],"type":"Point"}
}