{
  "type": "Feature",
  "properties": {
    "iso:country":"US",
    "sg:address":"246 SW 18th Ave",
    "sg:city":"Miami",
    "sg:classifiers":[
        {
            "category":"Building & Trades",
            "subcategory":"Construction",
            "type":"Services"
        }
    ],
    "sg:phone":"+1 305 649 2046",
    "sg:postcode":"33135",
    "sg:province":"FL",
    "sg:tags":[
        "residential"
    ],
    "wof:name":"Sermin Zeron Inc",
    "wof:placetype":"venue"
},
  "geometry": {"coordinates":[-80.22487,25.771266],"type":"Point"}
}