{
  "type": "Feature",
  "properties": {
    "addr:full":"4315 Highland Park Blvd Lakeland FL 33813",
    "addr:housenumber":"4315",
    "addr:postcode":"33813",
    "addr:street":"Highland Park Blvd",
    "iso:country":"US",
    "sg:address":"4315 Highland Park Blvd",
    "sg:city":"Lakeland",
    "sg:classifiers":[
        {
            "category":"Personal",
            "type":"Services"
        }
    ],
    "sg:phone":"+1 863 648 1100",
    "sg:postcode":"33813",
    "sg:province":"FL",
    "sg:tags":[
        "control",
        "weight"
    ],
    "wof:name":"Jenny Craig Weight Loss Ctr",
    "wof:placetype":"venue"
},
  "geometry": {"coordinates":[-81.95423599999999,27.986874],"type":"Point"}
}