{
  "type": "Feature",
  "properties": {
    "iso:country":"US",
    "sg:address":"4921 Sheridan St",
    "sg:city":"Hollywood",
    "sg:classifiers":[
        {
            "category":"Personal",
            "subcategory":"Beauty Salon",
            "type":"Services"
        }
    ],
    "sg:phone":"+1 954 514 9827",
    "sg:postcode":"33021",
    "sg:province":"FL",
    "wof:name":"Mulcare Multicultural Hair Design",
    "wof:placetype":"venue"
},
  "geometry": {"coordinates":[-80.193432,26.032711],"type":"Point"}
}