{
  "type": "Feature",
  "properties": {
    "iso:country":"US",
    "sg:address":"19925 NW 2nd Ave",
    "sg:city":"Miami",
    "sg:classifiers":[
        {
            "category":"Building & Trades",
            "subcategory":"Locksmith",
            "type":"Services"
        }
    ],
    "sg:phone":"+1 305 357 3650",
    "sg:postcode":"33169",
    "sg:province":"FL",
    "sg:tags":[
        "key"
    ],
    "wof:name":"1 24 Hour 7 Day Emerg Locksmith",
    "wof:placetype":"venue"
},
  "geometry": {"coordinates":[-80.20546,25.957394],"type":"Point"}
}