{
  "type": "Feature",
  "properties": {
    "iso:country":"US",
    "sg:address":"14815 Seminole Trl",
    "sg:city":"Seminole",
    "sg:classifiers":[
        {
            "category":"Building & Trades",
            "subcategory":"Construction",
            "type":"Services"
        }
    ],
    "sg:phone":"+1 727 593 8600",
    "sg:postcode":"33776",
    "sg:province":"FL",
    "sg:tags":[
        "specializing",
        "concrete",
        "commercial",
        "remodeling"
    ],
    "sg:website":"www.chargerconcrete.com",
    "wof:name":"Charger Enterprises Inc",
    "wof:placetype":"venue"
},
  "geometry": {"coordinates":[-82.842358,27.864523],"type":"Point"}
}