{
  "type": "Feature",
  "properties": {
    "addr:full":"4420 NW 36 Ave Gainesville FL 32606",
    "addr:housenumber":"4420",
    "addr:postcode":"32606",
    "addr:street":"Nw 36 Ave",
    "iso:country":"US",
    "sg:address":"4420 NW 36 Ave",
    "sg:city":"Gainesville",
    "sg:classifiers":[
        {
            "category":"Building & Trades",
            "subcategory":"Construction",
            "type":"Services"
        }
    ],
    "sg:phone":"+1 352 384 0272",
    "sg:postcode":"32606",
    "sg:province":"FL",
    "sg:tags":[
        "general",
        "contractor"
    ],
    "sg:website":"www.aceconstructors.com",
    "wof:name":"Ace Constructors",
    "wof:placetype":"venue"
},
  "geometry": {"coordinates":[-82.39037,29.686459],"type":"Point"}
}