{
  "type": "Feature",
  "properties": {
    "iso:country":"US",
    "sg:address":"572 Appleyard Dr",
    "sg:city":"Tallahassee",
    "sg:classifiers":[
        {
            "category":"Insurance",
            "subcategory":"Hazard Insurance",
            "type":"Services"
        }
    ],
    "sg:phone":"+1 850 574 8900",
    "sg:postcode":"32304",
    "sg:province":"FL",
    "sg:tags":[
        "bond"
    ],
    "wof:name":"A Able Bail Bonds",
    "wof:placetype":"venue"
},
  "geometry": {"coordinates":[-84.337969,30.441834],"type":"Point"}
}