{
  "type": "Feature",
  "properties": {
    "iso:country":"US",
    "sg:address":"18151 Prairie Creek Blvd",
    "sg:city":"Punta Gorda",
    "sg:classifiers":[
        {
            "category":"Professional",
            "type":"Services"
        }
    ],
    "sg:phone":"+1 941 505 2188",
    "sg:postcode":"33982",
    "sg:province":"FL",
    "wof:name":"Historic Punta Gorda Inc",
    "wof:placetype":"venue"
},
  "geometry": {"coordinates":[-81.86468000000001,26.98686],"type":"Point"}
}