{
  "type": "Feature",
  "properties": {
    "iso:country":"US",
    "sg:address":"607 N Myrtle Ave",
    "sg:city":"Clearwater",
    "sg:classifiers":[
        {
            "category":"Shopping",
            "subcategory":"Florist",
            "type":"Retail Goods"
        }
    ],
    "sg:phone":"+1 727 443 1963",
    "sg:postcode":"33755",
    "sg:province":"FL",
    "sg:website":"www.flaflowers.com",
    "wof:name":"Open Air Florists Inc",
    "wof:placetype":"venue"
},
  "geometry": {"coordinates":[-82.795841,27.971847],"type":"Point"}
}