{
  "type": "Feature",
  "properties": {
    "addr:full":"455 E Mills Ave Eustis FL 32726",
    "addr:housenumber":"455",
    "addr:postcode":"32726",
    "addr:street":"E Mills Ave",
    "iso:country":"US",
    "sg:address":"455 E Mills Ave",
    "sg:city":"Eustis",
    "sg:classifiers":[
        {
            "category":"Building & Trades",
            "subcategory":"Construction",
            "type":"Services"
        }
    ],
    "sg:phone":"+1 352 483 4934",
    "sg:postcode":"32726",
    "sg:province":"FL",
    "sg:tags":[
        "hanging",
        "contractor"
    ],
    "wof:name":"Paulin Painting Inc",
    "wof:placetype":"venue"
},
  "geometry": {"coordinates":[-81.68089500000001,28.841132],"type":"Point"}
}