{
  "type": "Feature",
  "properties": {
    "addr:full":"825 NW 51 Ter Gainesville FL 32605",
    "addr:housenumber":"825",
    "addr:postcode":"32605",
    "addr:street":"Nw 51 Ter",
    "iso:country":"US",
    "sg:address":"825 NW 51 Ter",
    "sg:city":"Gainesville",
    "sg:classifiers":[
        {
            "category":"Banks & Credit Unions",
            "subcategory":"Investment Brokerage",
            "type":"Services"
        }
    ],
    "sg:phone":"+1 352 373 2788",
    "sg:postcode":"32605",
    "sg:province":"FL",
    "sg:tags":[
        "advisory"
    ],
    "wof:name":"Xernona Investments Servi",
    "wof:placetype":"venue"
},
  "geometry": {"coordinates":[-82.397783,29.660331],"type":"Point"}
}