{
  "type": "Feature",
  "properties": {
    "addr:full":"1091 SW 1st Way Deerfield Beach FL 33441",
    "addr:housenumber":"1091",
    "addr:postcode":"33441",
    "addr:street":"Sw 1St Way",
    "iso:country":"US",
    "sg:address":"1091 SW 1st Way",
    "sg:city":"Deerfield Beach",
    "sg:classifiers":[
        {
            "category":"Building & Trades",
            "subcategory":"Construction",
            "type":"Services"
        }
    ],
    "sg:phone":"+1 954 426 8484",
    "sg:postcode":"33441",
    "sg:province":"FL",
    "sg:tags":[
        "planning",
        "remodeling",
        "kitchen"
    ],
    "wof:name":"Atlantis Kitchens",
    "wof:placetype":"venue"
},
  "geometry": {"coordinates":[-80.10600599999999,26.29954],"type":"Point"}
}