{
  "type": "Feature",
  "properties": {
    "addr:full":"145 Estates Cir Lake Mary FL 32746",
    "addr:housenumber":"145",
    "addr:postcode":"32746",
    "addr:street":"Estates Cir",
    "iso:country":"US",
    "sg:address":"145 Estates Cir",
    "sg:city":"Lake Mary",
    "sg:classifiers":[
        {
            "category":"Banks & Credit Unions",
            "subcategory":"Bank",
            "type":"Services"
        }
    ],
    "sg:phone":"+1 407 688 7828",
    "sg:postcode":"32746",
    "sg:province":"FL",
    "sg:tags":[
        "broker",
        "mortgage"
    ],
    "wof:name":"American Trust Mortgage",
    "wof:placetype":"venue"
},
  "geometry": {"coordinates":[-81.311868,28.765423],"type":"Point"}
}