{
  "type": "Feature",
  "properties": {
    "iso:country":"US",
    "sg:address":"410 W 49th St",
    "sg:city":"Hialeah",
    "sg:classifiers":[
        {
            "category":"Restaurant",
            "type":"Food & Drink"
        }
    ],
    "sg:phone":"+1 305 824 1888",
    "sg:postcode":"33012",
    "sg:province":"FL",
    "sg:tags":[
        "eating"
    ],
    "wof:name":"Tops China Buffet",
    "wof:placetype":"venue"
},
  "geometry": {"coordinates":[-80.294777,25.866573],"type":"Point"}
}