{
  "type": "Feature",
  "properties": {
    "iso:country":"US",
    "sg:address":"925 N Lime Ave",
    "sg:city":"Sarasota",
    "sg:classifiers":[
        {
            "category":"Restaurant",
            "type":"Food & Drink"
        }
    ],
    "sg:phone":"+1 941 955 3898",
    "sg:postcode":"34237",
    "sg:province":"FL",
    "wof:name":"KFC",
    "wof:placetype":"venue"
},
  "geometry": {"coordinates":[-82.524248,27.3448],"type":"Point"}
}