{
  "type": "Feature",
  "properties": {
    "iso:country":"US",
    "sg:address":"3038 N Federal Hwy",
    "sg:city":"Fort Lauderdale",
    "sg:classifiers":[
        {
            "category":"Professional",
            "subcategory":"Management & Consulting",
            "type":"Services"
        }
    ],
    "sg:phone":"+1 954 670 0444",
    "sg:postcode":"33306",
    "sg:province":"FL",
    "sg:tags":[
        "communications",
        "consultant"
    ],
    "wof:name":"Blue Rock Solutions Inc",
    "wof:placetype":"venue"
},
  "geometry": {"coordinates":[-80.11608200000001,26.165815],"type":"Point"}
}