{
  "type": "Feature",
  "properties": {
    "addr:full":"1097 S Woodland Blvd Deland FL 32720",
    "addr:housenumber":"1097",
    "addr:postcode":"32720",
    "addr:street":"S Woodland Blvd",
    "iso:country":"US",
    "sg:address":"1097 S Woodland Blvd",
    "sg:city":"Deland",
    "sg:classifiers":[
        {
            "category":"Food & Beverages",
            "subcategory":"Groceries & Convenience Stores",
            "type":"Retail Goods"
        }
    ],
    "sg:phone":"+1 386 738 0584",
    "sg:postcode":"32720",
    "sg:province":"FL",
    "sg:tags":[
        "grocer"
    ],
    "wof:name":"La Guadalupana",
    "wof:placetype":"venue"
},
  "geometry": {"coordinates":[-81.302724,29.010188],"type":"Point"}
}