{
  "type": "Feature",
  "properties": {
    "addr:full":"204 E Emma St Tampa FL 33603",
    "addr:housenumber":"204",
    "addr:postcode":"33603",
    "addr:street":"E Emma St",
    "iso:country":"US",
    "sg:address":"204 E Emma St",
    "sg:city":"Tampa",
    "sg:classifiers":[
        {
            "category":"Personal",
            "type":"Services"
        }
    ],
    "sg:phone":"+1 813 231 0244",
    "sg:postcode":"33603",
    "sg:province":"FL",
    "sg:tags":[
        "car",
        "loading",
        "unloading"
    ],
    "wof:name":"On The Road Moving And Delivery",
    "wof:placetype":"venue"
},
  "geometry": {"coordinates":[-82.458314,27.986009],"type":"Point"}
}