{
  "type": "Feature",
  "properties": {
    "iso:country":"US",
    "sg:address":"10045 Canopy Tree Ct",
    "sg:city":"Orlando",
    "sg:classifiers":[
        {
            "category":"Personal",
            "subcategory":"Beauty Salon",
            "type":"Services"
        }
    ],
    "sg:phone":"+1 407 354 0231",
    "sg:postcode":"32836",
    "sg:province":"FL",
    "sg:tags":[
        "shop"
    ],
    "wof:name":"R&R Event Marketing Inc",
    "wof:placetype":"venue"
},
  "geometry": {"coordinates":[-81.498125,28.419376],"type":"Point"}
}