{
  "type": "Feature",
  "properties": {
    "addr:full":"10101 SW 154th Circle Ct Miami FL 33196",
    "addr:housenumber":"10101",
    "addr:postcode":"33196",
    "addr:street":"Sw 154Th Circle Ct",
    "iso:country":"US",
    "sg:address":"10101 SW 154th Circle Ct",
    "sg:city":"Miami",
    "sg:classifiers":[
        {
            "category":"Building & Trades",
            "subcategory":"Construction",
            "type":"Services"
        }
    ],
    "sg:phone":"+1 305 408 9382",
    "sg:postcode":"33196",
    "sg:province":"FL",
    "sg:tags":[
        "house"
    ],
    "wof:name":"Wrangler Construction Inc",
    "wof:placetype":"venue"
},
  "geometry": {"coordinates":[-80.445843,25.672324],"type":"Point"}
}