{
  "type": "Feature",
  "properties": {
    "iso:country":"US",
    "sg:address":"908 W Hampton Springs Ave",
    "sg:city":"Perry",
    "sg:classifiers":[
        {
            "category":"Personal",
            "subcategory":"Barber",
            "type":"Services"
        }
    ],
    "sg:phone":"+1 850 584 9283",
    "sg:postcode":"32347",
    "sg:province":"FL",
    "wof:name":"Daddy's Place",
    "wof:placetype":"venue"
},
  "geometry": {"coordinates":[-83.589268,30.111675],"type":"Point"}
}