{
  "type": "Feature",
  "properties": {
    "addr:full":"6571 43rd St N Pinellas Park FL 33781",
    "addr:housenumber":"6571",
    "addr:postcode":"33781",
    "addr:street":"43Rd St N",
    "iso:country":"US",
    "sg:address":"6571 43rd St N",
    "sg:city":"Pinellas Park",
    "sg:classifiers":[
        {
            "category":"Home & Garden",
            "subcategory":"Building Materials",
            "type":"Retail Goods"
        },
        {
            "category":"Building & Trades",
            "subcategory":"Construction",
            "type":"Services"
        }
    ],
    "sg:phone":"+1 727 521 4040",
    "sg:postcode":"33781",
    "sg:province":"FL",
    "sg:tags":[
        "screen",
        "contractor",
        "window",
        "enclosure"
    ],
    "wof:name":"Masterkraft Screen & Aluminum",
    "wof:placetype":"venue"
},
  "geometry": {"coordinates":[-82.69176,27.828575],"type":"Point"}
}