{
  "type": "Feature",
  "properties": {
    "addr:full":"5730 Jason Lee Pl Sarasota FL 34233",
    "addr:housenumber":"5730",
    "addr:postcode":"34233",
    "addr:street":"Jason Lee Pl",
    "iso:country":"US",
    "sg:address":"5730 Jason Lee Pl",
    "sg:city":"Sarasota",
    "sg:classifiers":[
        {
            "category":"Building & Trades",
            "subcategory":"Plumbing",
            "type":"Services"
        }
    ],
    "sg:phone":"+1 941 359 3382",
    "sg:postcode":"34233",
    "sg:province":"FL",
    "sg:tags":[
        "contractor"
    ],
    "wof:name":"Daniels Plumbing Service",
    "wof:placetype":"venue"
},
  "geometry": {"coordinates":[-82.473412,27.27002],"type":"Point"}
}