{
  "type": "Feature",
  "properties": {
    "iso:country":"US",
    "sg:address":"2750 NE 185th St",
    "sg:city":"Miami",
    "sg:classifiers":[
        {
            "category":"Professional",
            "subcategory":"Lawyer & Legal Services",
            "type":"Services"
        }
    ],
    "sg:phone":"+1 305 682 1328",
    "sg:postcode":"33180",
    "sg:province":"FL",
    "wof:name":"Schiffman Adam R Law Offices of",
    "wof:placetype":"venue"
},
  "geometry": {"coordinates":[-80.1451,25.94684],"type":"Point"}
}