{
  "type": "Feature",
  "properties": {
    "addr:full":"520 US Hwy 17 Yulee FL 32097",
    "addr:housenumber":"520",
    "addr:postcode":"32097",
    "addr:street":"Us Hwy 17",
    "iso:country":"US",
    "sg:address":"520 US Hwy 17",
    "sg:city":"Yulee",
    "sg:classifiers":[
        {
            "category":"Personal",
            "subcategory":"Tanning Parlor",
            "type":"Services"
        }
    ],
    "sg:phone":"+1 904 225 5030",
    "sg:postcode":"32097",
    "sg:province":"FL",
    "sg:tags":[
        "salon"
    ],
    "wof:name":"Tropical Tan & Nails",
    "wof:placetype":"venue"
},
  "geometry": {"coordinates":[-81.597928,30.606339],"type":"Point"}
}