{
  "type": "Feature",
  "properties": {
    "iso:country":"US",
    "sg:address":"319 Aylesbury Ct",
    "sg:city":"Kissimmee",
    "sg:classifiers":[
        {
            "category":"Freight",
            "type":"Transportation"
        }
    ],
    "sg:phone":"+1 407 721 8507",
    "sg:postcode":"34758",
    "sg:province":"FL",
    "wof:name":"R & R Transportation",
    "wof:placetype":"venue"
},
  "geometry": {"coordinates":[-81.49832000000001,28.15549],"type":"Point"}
}