{
  "type": "Feature",
  "properties": {
    "addr:full":"4061 Bonita Beach Rd Bonita Springs FL 34134",
    "addr:housenumber":"4061",
    "addr:postcode":"34134",
    "addr:street":"Bonita Beach Rd",
    "iso:country":"US",
    "sg:address":"4061 Bonita Beach Rd",
    "sg:city":"Bonita Springs",
    "sg:classifiers":[
        {
            "category":"Real Estate",
            "subcategory":"Real Estate Agent",
            "type":"Services"
        }
    ],
    "sg:phone":"+1 239 947 1885",
    "sg:postcode":"34134",
    "sg:province":"FL",
    "wof:name":"Meyer Manz Real Estate Inc",
    "wof:placetype":"venue"
},
  "geometry": {"coordinates":[-81.81972399999999,26.330433],"type":"Point"}
}