{
  "type": "Feature",
  "properties": {
    "iso:country":"US",
    "sg:address":"7305 W Sample Rd",
    "sg:city":"Coral Springs",
    "sg:classifiers":[
        {
            "category":"Professional",
            "subcategory":"Accounting & Tax Preparation",
            "type":"Services"
        }
    ],
    "sg:phone":"+1 954 757 1292",
    "sg:postcode":"33065",
    "sg:province":"FL",
    "sg:tags":[
        "billing"
    ],
    "wof:name":"Terzetto Financial Solutions",
    "wof:placetype":"venue"
},
  "geometry": {"coordinates":[-80.222527,26.272358],"type":"Point"}
}