{
  "type": "Feature",
  "properties": {
    "iso:country":"US",
    "sg:address":"18090 Collins Ave",
    "sg:city":"Sunny Isles Bch",
    "sg:classifiers":[
        {
            "category":"Utilities",
            "subcategory":"Mobile Phone",
            "type":"Services"
        }
    ],
    "sg:phone":"+1 305 792 4557",
    "sg:postcode":"33160",
    "sg:province":"FL",
    "sg:tags":[
        "telephone",
        "cellular"
    ],
    "wof:name":"Cingular Wireless",
    "wof:placetype":"venue"
},
  "geometry": {"coordinates":[-80.121348,25.941667],"type":"Point"}
}