{
  "type": "Feature",
  "properties": {
    "addr:full":"4345 11th Ave SW Naples FL 34116",
    "addr:housenumber":"4345",
    "addr:postcode":"34116",
    "addr:street":"11Th Ave Sw",
    "iso:country":"US",
    "sg:address":"4345 11th Ave SW",
    "sg:city":"Naples",
    "sg:classifiers":[
        {
            "category":"Professional",
            "type":"Services"
        }
    ],
    "sg:phone":"+1 239 353 7407",
    "sg:postcode":"34116",
    "sg:province":"FL",
    "sg:tags":[
        "establishment"
    ],
    "wof:name":"Blossom's Inc",
    "wof:placetype":"venue"
},
  "geometry": {"coordinates":[-81.69251199999999,26.208718],"type":"Point"}
}