{
  "type": "Feature",
  "properties": {
    "addr:full":"1970 S Semoran Blvd Orlando FL 32822",
    "addr:housenumber":"1970",
    "addr:postcode":"32822",
    "addr:street":"S Semoran Blvd",
    "iso:country":"US",
    "sg:address":"1970 S Semoran Blvd",
    "sg:city":"Orlando",
    "sg:classifiers":[
        {
            "category":"Retail",
            "subcategory":"Auto Rental",
            "type":"Services"
        }
    ],
    "sg:phone":"+1 407 657 5021",
    "sg:postcode":"32822",
    "sg:province":"FL",
    "sg:tags":[
        "car",
        "truck"
    ],
    "sg:website":"http://www.enterprise.com",
    "wof:name":"Enterprise Rent-A-Car",
    "wof:placetype":"venue"
},
  "geometry": {"coordinates":[-81.31048199999999,28.520839],"type":"Point"}
}