{
  "type": "Feature",
  "properties": {
    "iso:country":"US",
    "sg:address":"700 NW 30th Ave",
    "sg:city":"Ocala",
    "sg:classifiers":[
        {
            "category":"Manufacturing",
            "subcategory":"Food",
            "type":"Manufacturing & Wholesale Goods"
        },
        {
            "category":"Wholesale",
            "subcategory":"Groceries",
            "type":"Manufacturing & Wholesale Goods"
        }
    ],
    "sg:phone":"+1 352 694 0900",
    "sg:postcode":"34475",
    "sg:province":"FL",
    "sg:tags":[
        "product",
        "products-wholesale"
    ],
    "wof:name":"Keefe Commissary Network",
    "wof:placetype":"venue"
},
  "geometry": {"coordinates":[-82.17214199999999,29.19301],"type":"Point"}
}