{
  "type": "Feature",
  "properties": {
    "addr:full":"1215 S Bea Ave Inverness FL 34452",
    "addr:housenumber":"1215",
    "addr:postcode":"34452",
    "addr:street":"S Bea Ave",
    "iso:country":"US",
    "sg:address":"1215 S Bea Ave",
    "sg:city":"Inverness",
    "sg:classifiers":[
        {
            "category":"Organizations",
            "subcategory":"Religious Organization",
            "type":"Services"
        }
    ],
    "sg:phone":"+1 352 726 5478",
    "sg:postcode":"34452",
    "sg:province":"FL",
    "sg:tags":[
        "church"
    ],
    "wof:name":"United Pentecostal Church",
    "wof:placetype":"venue"
},
  "geometry": {"coordinates":[-82.378911,28.844988],"type":"Point"}
}