{
  "type": "Feature",
  "properties": {
    "iso:country":"US",
    "sg:address":"59 E Palmetto Park Rd",
    "sg:city":"Boca Raton",
    "sg:classifiers":[
        {
            "category":"Personal",
            "subcategory":"Beauty Salon",
            "type":"Services"
        }
    ],
    "sg:phone":"+1 561 395 2521",
    "sg:postcode":"33432",
    "sg:province":"FL",
    "sg:tags":[
        "shop"
    ],
    "wof:name":"Madison Avenue Nails Salon",
    "wof:placetype":"venue"
},
  "geometry": {"coordinates":[-80.085768,26.350584],"type":"Point"}
}