{
  "type": "Feature",
  "properties": {
    "addr:full":"1750 E Commercial Blvd Fort Lauderdale FL 33334",
    "addr:housenumber":"1750",
    "addr:postcode":"33334",
    "addr:street":"E Commercial Blvd",
    "iso:country":"US",
    "sg:address":"1750 E Commercial Blvd",
    "sg:city":"Fort Lauderdale",
    "sg:classifiers":[
        {
            "category":"Shopping",
            "subcategory":"Used Merchandise",
            "type":"Retail Goods"
        }
    ],
    "sg:phone":"+1 954 493 5155",
    "sg:postcode":"33334",
    "sg:province":"FL",
    "wof:name":"Gold-N-Pawn",
    "wof:placetype":"venue"
},
  "geometry": {"coordinates":[-80.12316,26.18894],"type":"Point"}
}