{
  "type": "Feature",
  "properties": {
    "iso:country":"US",
    "sg:address":"10970 E Co Hwy 30A",
    "sg:city":"Panama City Bch",
    "sg:classifiers":[
        {
            "category":"Food & Beverages",
            "subcategory":"Groceries & Convenience Stores",
            "type":"Retail Goods"
        }
    ],
    "sg:phone":"+1 850 534 0610",
    "sg:postcode":"32413",
    "sg:province":"FL",
    "wof:name":"Buddies Food Mart",
    "wof:placetype":"venue"
},
  "geometry": {"coordinates":[-86.01221200000001,30.278738],"type":"Point"}
}