{
  "type": "Feature",
  "properties": {
    "addr:full":"2150 W 10th Ct Hialeah FL 33010",
    "addr:housenumber":"2150",
    "addr:postcode":"33010",
    "addr:street":"W 10Th Ct",
    "iso:country":"US",
    "sg:address":"2150 W 10th Ct",
    "sg:city":"Hialeah",
    "sg:classifiers":[
        {
            "category":"Restaurant",
            "type":"Food & Drink"
        }
    ],
    "sg:phone":"+1 305 884 0181",
    "sg:postcode":"33010",
    "sg:province":"FL",
    "sg:tags":[
        "eating"
    ],
    "wof:name":"Perez Cafeteria",
    "wof:placetype":"venue"
},
  "geometry": {"coordinates":[-80.30321600000001,25.842215],"type":"Point"}
}