{
  "type": "Feature",
  "properties": {
    "iso:country":"US",
    "sg:address":"1697 Palm Beach Trace Dr",
    "sg:city":"West Palm Beach",
    "sg:classifiers":[
        {
            "category":"Professional",
            "subcategory":"Business Services",
            "type":"Services"
        }
    ],
    "sg:phone":"+1 561 791 8277",
    "sg:postcode":"33411",
    "sg:province":"FL",
    "wof:name":"Wallach Enterprises Inc",
    "wof:placetype":"venue"
},
  "geometry": {"coordinates":[-80.22584000000001,26.712504],"type":"Point"}
}