{
  "type": "Feature",
  "properties": {
    "addr:full":"13181 NW 19th St Pembroke Pines FL 33028",
    "addr:housenumber":"13181",
    "addr:postcode":"33028",
    "addr:street":"Nw 19Th St",
    "iso:country":"US",
    "sg:address":"13181 NW 19th St",
    "sg:city":"Pembroke Pines",
    "sg:classifiers":[
        {
            "category":"Professional",
            "type":"Services"
        }
    ],
    "sg:phone":"+1 954 436 6950",
    "sg:postcode":"33028",
    "sg:province":"FL",
    "sg:tags":[
        "establishment"
    ],
    "wof:name":"RLT",
    "wof:placetype":"venue"
},
  "geometry": {"coordinates":[-80.325591,26.025866],"type":"Point"}
}