{
  "type": "Feature",
  "properties": {
    "iso:country":"US",
    "sg:address":"12134 NW 76th Pl",
    "sg:city":"Pompano Beach",
    "sg:classifiers":[
        {
            "category":"Professional",
            "subcategory":"Management & Consulting",
            "type":"Services"
        }
    ],
    "sg:phone":"+1 954 345 0045",
    "sg:postcode":"33076",
    "sg:province":"FL",
    "sg:tags":[
        "business"
    ],
    "wof:name":"Mr Funding Consultants Inc",
    "wof:placetype":"venue"
},
  "geometry": {"coordinates":[-80.288138,26.325305],"type":"Point"}
}