{
  "type": "Feature",
  "properties": {
    "iso:country":"US",
    "sg:address":"300 Tamiami Trl",
    "sg:city":"Venice",
    "sg:classifiers":[
        {
            "category":"Health Services",
            "subcategory":"Health Practitioner",
            "type":"Services"
        }
    ],
    "sg:phone":"+1 941 485 0677",
    "sg:postcode":"34285",
    "sg:province":"FL",
    "wof:name":"Vivian Ann Lmt Rice",
    "wof:placetype":"venue"
},
  "geometry": {"coordinates":[-82.444327,27.094147],"type":"Point"}
}