{
  "type": "Feature",
  "properties": {
    "addr:full":"131 Palm Valley Woods Dr Ponte Vedra Beach FL 32082",
    "addr:housenumber":"131",
    "addr:postcode":"32082",
    "addr:street":"Palm Valley Woods Dr",
    "iso:country":"US",
    "sg:address":"131 Palm Valley Woods Dr",
    "sg:city":"Ponte Vedra Beach",
    "sg:classifiers":[
        {
            "category":"Manufacturing",
            "subcategory":"Building Materials",
            "type":"Manufacturing & Wholesale Goods"
        }
    ],
    "sg:phone":"+1 904 285 0965",
    "sg:postcode":"32082",
    "sg:province":"FL",
    "sg:tags":[
        "mfg"
    ],
    "wof:name":"Dunbar Framing Inc",
    "wof:placetype":"venue"
},
  "geometry": {"coordinates":[-81.396671,30.164554],"type":"Point"}
}