{
  "type": "Feature",
  "properties": {
    "iso:country":"US",
    "sg:address":"6029 Westfall Rd",
    "sg:city":"Lake Worth",
    "sg:classifiers":[
        {
            "category":"Communications",
            "subcategory":"Film & Video Production",
            "type":"Services"
        }
    ],
    "sg:phone":"+1 561 969 3498",
    "sg:postcode":"33463",
    "sg:province":"FL",
    "sg:tags":[
        "motion"
    ],
    "wof:name":"Ajah",
    "wof:placetype":"venue"
},
  "geometry": {"coordinates":[-80.139864,26.595987],"type":"Point"}
}