{
  "type": "Feature",
  "properties": {
    "addr:full":"5615 3rd Ave Key West FL 33040",
    "addr:housenumber":"5615",
    "addr:postcode":"33040",
    "addr:street":"3Rd Ave",
    "iso:country":"US",
    "sg:address":"5615 3rd Ave",
    "sg:city":"Key West",
    "sg:classifiers":[
        {
            "category":"Professional",
            "subcategory":"Computer Services",
            "type":"Services"
        }
    ],
    "sg:phone":"+1 305 294 6753",
    "sg:postcode":"33040",
    "sg:province":"FL",
    "sg:tags":[
        "design",
        "system"
    ],
    "wof:name":"Bas Fire & Security",
    "wof:placetype":"venue"
},
  "geometry": {"coordinates":[-81.73850899999999,24.569668],"type":"Point"}
}