{
  "type": "Feature",
  "properties": {
    "addr:full":"6100 Dogwood Dr Milton FL 32570",
    "addr:housenumber":"6100",
    "addr:postcode":"32570",
    "addr:street":"Dogwood Dr",
    "iso:country":"US",
    "sg:address":"6100 Dogwood Dr",
    "sg:city":"Milton",
    "sg:classifiers":[
        {
            "category":"Place Of Worship",
            "subcategory":"Church",
            "type":"Public Place"
        },
        {
            "category":"Place Of Worship",
            "type":"Public Place"
        },
        {
            "category":"Organizations",
            "subcategory":"Religious Organization",
            "type":"Services"
        }
    ],
    "sg:phone":"+1 850 981 9429",
    "sg:postcode":"32570",
    "sg:province":"FL",
    "sg:tags":[
        "churches-non-denominational"
    ],
    "wof:name":"Majestic Ministries Inc",
    "wof:placetype":"venue"
},
  "geometry": {"coordinates":[-87.055092,30.656481],"type":"Point"}
}