{
  "type": "Feature",
  "properties": {
    "iso:country":"US",
    "sg:address":"1155 8th St SW",
    "sg:city":"Vero Beach",
    "sg:classifiers":[
        {
            "category":"Manufacturing",
            "subcategory":"Glass & Minerals",
            "type":"Manufacturing & Wholesale Goods"
        }
    ],
    "sg:phone":"+1 772 589 2114",
    "sg:postcode":"32962",
    "sg:province":"FL",
    "sg:tags":[
        "stone",
        "cut",
        "product",
        "mfg"
    ],
    "wof:name":"Absolute Granite and Marble",
    "wof:placetype":"venue"
},
  "geometry": {"coordinates":[-80.396502,27.588645],"type":"Point"}
}