{
  "type": "Feature",
  "properties": {
    "iso:country":"US",
    "sg:address":"2850 NW 79th Ave",
    "sg:city":"Miami",
    "sg:classifiers":[
        {
            "category":"Health Services",
            "subcategory":"Clinic",
            "type":"Services"
        }
    ],
    "sg:phone":"+1 305 716 8822",
    "sg:postcode":"33122",
    "sg:province":"FL",
    "sg:tags":[
        "home",
        "care"
    ],
    "wof:name":"Gentiva Health Services",
    "wof:placetype":"venue"
},
  "geometry": {"coordinates":[-80.32506100000001,25.797762],"type":"Point"}
}