{
  "type": "Feature",
  "properties": {
    "addr:full":"2110 E 5th St Panama City FL 32401",
    "addr:housenumber":"2110",
    "addr:postcode":"32401",
    "addr:street":"E 5Th St",
    "iso:country":"US",
    "sg:address":"2110 E 5th St",
    "sg:city":"Panama City",
    "sg:classifiers":[
        {
            "category":"Retail",
            "subcategory":"Auto Repair",
            "type":"Services"
        }
    ],
    "sg:phone":"+1 850 747 9506",
    "sg:postcode":"32401",
    "sg:province":"FL",
    "sg:tags":[
        "repairing",
        "automobile"
    ],
    "wof:name":"Millville Auto & Truck Repair",
    "wof:placetype":"venue"
},
  "geometry": {"coordinates":[-85.63228700000001,30.156742],"type":"Point"}
}