{
  "type": "Feature",
  "properties": {
    "addr:full":"1384 Camellia Cir Fort Lauderdale FL 33326",
    "addr:housenumber":"1384",
    "addr:postcode":"33326",
    "addr:street":"Camellia Cir",
    "iso:country":"US",
    "sg:address":"1384 Camellia Cir",
    "sg:city":"Fort Lauderdale",
    "sg:classifiers":[
        {
            "category":"Communications",
            "subcategory":"Film & Video Production",
            "type":"Services"
        }
    ],
    "sg:phone":"+1 954 385 0737",
    "sg:postcode":"33326",
    "sg:province":"FL",
    "sg:tags":[
        "motion"
    ],
    "wof:name":"Alive Productions Entrmt",
    "wof:placetype":"venue"
},
  "geometry": {"coordinates":[-80.3854,26.103257],"type":"Point"}
}