{
  "type": "Feature",
  "properties": {
    "iso:country":"US",
    "sg:address":"236 Periwinkle Dr",
    "sg:city":"Sebastian",
    "sg:classifiers":[
        {
            "category":"Professional",
            "subcategory":"Business Services",
            "type":"Services"
        }
    ],
    "sg:phone":"+1 772 589 1237",
    "sg:postcode":"32958",
    "sg:province":"FL",
    "sg:tags":[
        "interior",
        "consultant",
        "design",
        "decorator"
    ],
    "wof:name":"Designing With Diane",
    "wof:placetype":"venue"
},
  "geometry": {"coordinates":[-80.47660999999999,27.76202],"type":"Point"}
}