{
  "type": "Feature",
  "properties": {
    "addr:full":"500 Coleman Dr W Winter Haven FL 33884",
    "addr:housenumber":"500",
    "addr:postcode":"33884",
    "addr:street":"Coleman Dr W",
    "iso:country":"US",
    "sg:address":"500 Coleman Dr W",
    "sg:city":"Winter Haven",
    "sg:classifiers":[
        {
            "category":"Professional",
            "subcategory":"Advertising",
            "type":"Services"
        }
    ],
    "sg:phone":"+1 863 318 9843",
    "sg:postcode":"33884",
    "sg:province":"FL",
    "sg:tags":[
        "designer",
        "display",
        "producer"
    ],
    "wof:name":"It's Showtime",
    "wof:placetype":"venue"
},
  "geometry": {"coordinates":[-81.66491000000001,27.999955],"type":"Point"}
}