{
  "type": "Feature",
  "properties": {
    "addr:full":"1045 Live Oak Ln Green Cove Springs FL 32043",
    "addr:housenumber":"1045",
    "addr:postcode":"32043",
    "addr:street":"Live Oak Ln",
    "iso:country":"US",
    "sg:address":"1045 Live Oak Ln",
    "sg:city":"Green Cove Springs",
    "sg:classifiers":[
        {
            "category":"Real Estate",
            "subcategory":"Real Estate Agent",
            "type":"Services"
        }
    ],
    "sg:phone":"+1 904 529 7924",
    "sg:postcode":"32043",
    "sg:province":"FL",
    "sg:tags":[
        "rental"
    ],
    "wof:name":"William P Overton",
    "wof:placetype":"venue"
},
  "geometry": {"coordinates":[-81.702629,30.060904],"type":"Point"}
}