{
  "type": "Feature",
  "properties": {
    "iso:country":"US",
    "sg:address":"400 N Ashley Dr",
    "sg:city":"Tampa",
    "sg:classifiers":[
        {
            "category":"Building & Trades",
            "subcategory":"Cleaning & Sanitation",
            "type":"Services"
        }
    ],
    "sg:phone":"+1 813 226 3998",
    "sg:postcode":"33602",
    "sg:province":"FL",
    "sg:tags":[
        "janitor",
        "maintenance"
    ],
    "wof:name":"High Quality Cleaning Services",
    "wof:placetype":"venue"
},
  "geometry": {"coordinates":[-82.45999999999999,27.947827],"type":"Point"}
}