{
  "type": "Feature",
  "properties": {
    "iso:country":"US",
    "sg:address":"13904 Lakeshore Blvd",
    "sg:city":"Port Richey",
    "sg:classifiers":[
        {
            "category":"Real Estate",
            "subcategory":"Real Estate Agent",
            "type":"Services"
        }
    ],
    "sg:phone":"+1 727 868 7831",
    "sg:postcode":"34667",
    "sg:province":"FL",
    "sg:tags":[
        "consulting",
        "management"
    ],
    "wof:name":"Hotel & Motel International",
    "wof:placetype":"venue"
},
  "geometry": {"coordinates":[-82.686729,28.354391],"type":"Point"}
}