{
  "type": "Feature",
  "properties": {
    "iso:country":"US",
    "sg:address":"178 W North Ave",
    "sg:city":"Crestview",
    "sg:classifiers":[
        {
            "category":"Organizations",
            "subcategory":"Religious Organization",
            "type":"Services"
        }
    ],
    "sg:phone":"+1 850 682 3154",
    "sg:postcode":"32536",
    "sg:province":"FL",
    "sg:tags":[
        "churches-lutheran"
    ],
    "wof:name":"Our Savior Lutheran Church",
    "wof:placetype":"venue"
},
  "geometry": {"coordinates":[-86.581457,30.769722],"type":"Point"}
}