{
  "type": "Feature",
  "properties": {
    "iso:country":"US",
    "sg:address":"3885 102nd Pl N",
    "sg:city":"Clearwater",
    "sg:classifiers":[
        {
            "category":"Professional",
            "subcategory":"Management & Consulting",
            "type":"Services"
        }
    ],
    "sg:phone":"+1 727 572 7514",
    "sg:postcode":"33762",
    "sg:province":"FL",
    "sg:tags":[
        "marketing",
        "program"
    ],
    "wof:name":"All Pro Marketing",
    "wof:placetype":"venue"
},
  "geometry": {"coordinates":[-82.68598799999999,27.865271],"type":"Point"}
}