{
  "type": "Feature",
  "properties": {
    "iso:country":"US",
    "sg:address":"104 25th Ave S",
    "sg:city":"Jacksonville Beach",
    "sg:classifiers":[
        {
            "category":"Professional",
            "type":"Services"
        }
    ],
    "sg:phone":"+1 904 247 0909",
    "sg:postcode":"32250",
    "sg:province":"FL",
    "wof:name":"Randolph D Steingart",
    "wof:placetype":"venue"
},
  "geometry": {"coordinates":[-81.38635499999999,30.267468],"type":"Point"}
}