{
  "type": "Feature",
  "properties": {
    "iso:country":"US",
    "sg:address":"108 Commerce St",
    "sg:city":"Longwood",
    "sg:classifiers":[
        {
            "category":"Shopping",
            "subcategory":"Hobbies, Toys, & Games",
            "type":"Retail Goods"
        }
    ],
    "sg:phone":"+1 407 331 7923",
    "sg:postcode":"32750",
    "sg:province":"FL",
    "sg:tags":[
        "equipment",
        "ceramic",
        "supply"
    ],
    "wof:name":"Dilip Ceramics Inc",
    "wof:placetype":"venue"
},
  "geometry": {"coordinates":[-81.34768800000001,28.69325],"type":"Point"}
}