{
  "type": "Feature",
  "properties": {
    "iso:country":"US",
    "sg:address":"5400 Summerwind Dr",
    "sg:city":"Naples",
    "sg:classifiers":[
        {
            "category":"Building & Trades",
            "subcategory":"Construction",
            "type":"Services"
        }
    ],
    "sg:phone":"+1 239 253 3849",
    "sg:postcode":"34109",
    "sg:province":"FL",
    "sg:tags":[
        "hanging",
        "contractor"
    ],
    "wof:name":"Alltex Painting",
    "wof:placetype":"venue"
},
  "geometry": {"coordinates":[-81.75886800000001,26.215629],"type":"Point"}
}