{
  "type": "Feature",
  "properties": {
    "iso:country":"US",
    "sg:address":"16023 Horizon Ct",
    "sg:city":"Clermont",
    "sg:classifiers":[
        {
            "category":"Professional",
            "subcategory":"Accounting & Tax Preparation",
            "type":"Services"
        }
    ],
    "sg:phone":"+1 407 877 5989",
    "sg:postcode":"34711",
    "sg:province":"FL",
    "sg:tags":[
        "return"
    ],
    "wof:name":"Tomasa Enterprises Inc",
    "wof:placetype":"venue"
},
  "geometry": {"coordinates":[-81.687984,28.53395],"type":"Point"}
}