{
  "type": "Feature",
  "properties": {
    "addr:full":"5131 NW 84th Ave Fort Lauderdale FL 33351",
    "addr:housenumber":"5131",
    "addr:postcode":"33351",
    "addr:street":"Nw 84Th Ave",
    "iso:country":"US",
    "sg:address":"5131 NW 84th Ave",
    "sg:city":"Fort Lauderdale",
    "sg:classifiers":[
        {
            "category":"Wholesale",
            "subcategory":"Hardware",
            "type":"Manufacturing & Wholesale Goods"
        }
    ],
    "sg:phone":"+1 954 749 0061",
    "sg:postcode":"33351",
    "sg:province":"FL",
    "sg:tags":[
        "refrigeration"
    ],
    "wof:name":"Mr Ice Inc",
    "wof:placetype":"venue"
},
  "geometry": {"coordinates":[-80.262933,26.187668],"type":"Point"}
}