{
  "type": "Feature",
  "properties": {
    "iso:country":"US",
    "sg:address":"141 W Cedarwood Cir",
    "sg:city":"Kissimmee",
    "sg:classifiers":[
        {
            "category":"Shopping",
            "subcategory":"Luggage & Leather Goods",
            "type":"Retail Goods"
        }
    ],
    "sg:phone":"+1 407 348 2966",
    "sg:postcode":"34743",
    "sg:province":"FL",
    "wof:name":"Tina Che Enterprises",
    "wof:placetype":"venue"
},
  "geometry": {"coordinates":[-81.361833,28.334514],"type":"Point"}
}