{
  "type": "Feature",
  "properties": {
    "addr:full":"616 Palomas Ave Ocoee FL 34761",
    "addr:housenumber":"616",
    "addr:postcode":"34761",
    "addr:street":"Palomas Ave",
    "iso:country":"US",
    "sg:address":"616 Palomas Ave",
    "sg:city":"Ocoee",
    "sg:classifiers":[
        {
            "category":"Building & Trades",
            "subcategory":"Construction",
            "type":"Services"
        },
        {
            "category":"Military Area",
            "subcategory":"Armory",
            "type":"Public Place"
        }
    ],
    "sg:phone":"+1 407 877 8659",
    "sg:postcode":"34761",
    "sg:province":"FL",
    "sg:tags":[
        "repair",
        "fence-sales",
        "fence",
        "contractor"
    ],
    "sg:website":"http://www.premierfence.com",
    "wof:name":"Premier Fence Inc",
    "wof:placetype":"venue"
},
  "geometry": {"coordinates":[-81.541687,28.560674],"type":"Point"}
}