{
  "type": "Feature",
  "properties": {
    "addr:full":"777 Lane Ave S Jacksonville FL 32205",
    "addr:housenumber":"777",
    "addr:postcode":"32205",
    "addr:street":"Lane Ave S",
    "iso:country":"US",
    "sg:address":"777 Lane Ave S",
    "sg:city":"Jacksonville",
    "sg:classifiers":[
        {
            "category":"Professional",
            "subcategory":"Accounting & Tax Preparation",
            "type":"Services"
        }
    ],
    "sg:phone":"+1 904 786 4784",
    "sg:postcode":"32205",
    "sg:province":"FL",
    "sg:tags":[
        "return"
    ],
    "wof:name":"Wilsons Tax Service",
    "wof:placetype":"venue"
},
  "geometry": {"coordinates":[-81.75187699999999,30.314036],"type":"Point"}
}