{
  "type": "Feature",
  "properties": {
    "iso:country":"US",
    "sg:address":"715 Mallard Dr",
    "sg:city":"Sanford",
    "sg:classifiers":[
        {
            "category":"Building & Trades",
            "subcategory":"Construction",
            "type":"Services"
        }
    ],
    "sg:phone":"+1 407 330 0579",
    "sg:postcode":"32771",
    "sg:province":"FL",
    "sg:tags":[
        "contractor",
        "specialty",
        "grading"
    ],
    "wof:name":"Seminole Site Services Inc",
    "wof:placetype":"venue"
},
  "geometry": {"coordinates":[-81.370805,28.829008],"type":"Point"}
}