{
  "type": "Feature",
  "properties": {
    "iso:country":"US",
    "sg:address":"3100 N Andrews Ave Exd",
    "sg:city":"Pompano Beach",
    "sg:classifiers":[
        {
            "category":"Home & Garden",
            "subcategory":"Furniture",
            "type":"Retail Goods"
        }
    ],
    "sg:phone":"+1 954 979 5777",
    "sg:postcode":"33064",
    "sg:province":"FL",
    "wof:name":"Sheribel Designs",
    "wof:placetype":"venue"
},
  "geometry": {"coordinates":[-80.137086,26.268908],"type":"Point"}
}