{
  "type": "Feature",
  "properties": {
    "iso:country":"US",
    "sg:address":"7822 N 56th St",
    "sg:city":"Tampa",
    "sg:classifiers":[
        {
            "category":"Social Services",
            "subcategory":"Child Care",
            "type":"Services"
        }
    ],
    "sg:phone":"+1 813 988 2875",
    "sg:postcode":"33617",
    "sg:province":"FL",
    "sg:website":"www.palnez.com",
    "wof:name":"Palnez School Inc-Temple Ter",
    "wof:placetype":"venue"
},
  "geometry": {"coordinates":[-82.393491,28.019735],"type":"Point"}
}