{
  "type": "Feature",
  "properties": {
    "iso:country":"US",
    "sg:address":"2038 Bonnie Ave",
    "sg:city":"Palm Harbor",
    "sg:classifiers":[
        {
            "category":"Farming",
            "subcategory":"Aquatic Farm",
            "type":"Manufacturing & Wholesale Goods"
        }
    ],
    "sg:phone":"+1 727 781 6993",
    "sg:postcode":"34683",
    "sg:province":"FL",
    "sg:tags":[
        "fish"
    ],
    "wof:name":"In Sight Charters",
    "wof:placetype":"venue"
},
  "geometry": {"coordinates":[-82.748041,28.071907],"type":"Point"}
}