{
  "type": "Feature",
  "properties": {
    "iso:country":"US",
    "sg:address":"3120 Commodore Plz",
    "sg:city":"Miami",
    "sg:classifiers":[
        {
            "category":"Arts & Performance",
            "subcategory":"Music",
            "type":"Entertainment"
        },
        {
            "category":"Bars & Pubs",
            "type":"Food & Drink"
        },
        {
            "category":"Restaurant",
            "type":"Food & Drink"
        }
    ],
    "sg:phone":"+1 305 443 0422",
    "sg:postcode":"33133",
    "sg:province":"FL",
    "sg:tags":[
        "irish",
        "venue"
    ],
    "sg:website":"www.11leprechauns.com/",
    "wof:name":"Eleven Leprechauns",
    "wof:placetype":"venue"
},
  "geometry": {"coordinates":[-80.244659,25.727122],"type":"Point"}
}