{
  "type": "Feature",
  "properties": {
    "addr:full":"1340 Coral Ridge Dr Pompano Beach FL 33071",
    "addr:housenumber":"1340",
    "addr:postcode":"33071",
    "addr:street":"Coral Ridge Dr",
    "iso:country":"US",
    "sg:address":"1340 Coral Ridge Dr",
    "sg:city":"Pompano Beach",
    "sg:classifiers":[
        {
            "category":"Professional",
            "subcategory":"Accounting & Tax Preparation",
            "type":"Services"
        }
    ],
    "sg:phone":"+1 954 796 7220",
    "sg:postcode":"33071",
    "sg:province":"FL",
    "wof:name":"H & R Block",
    "wof:placetype":"venue"
},
  "geometry": {"coordinates":[-80.280365,26.249892],"type":"Point"}
}