{
  "type": "Feature",
  "properties": {
    "iso:country":"US",
    "sg:address":"1608 W 68th St",
    "sg:city":"Hialeah",
    "sg:classifiers":[
        {
            "category":"Professional",
            "subcategory":"Printing & Photocopies",
            "type":"Services"
        }
    ],
    "sg:phone":"+1 305 512 0900",
    "sg:postcode":"33014",
    "sg:province":"FL",
    "sg:tags":[
        "lithographer"
    ],
    "wof:name":"Print It Xpress Inc",
    "wof:placetype":"venue"
},
  "geometry": {"coordinates":[-80.315727,25.884128],"type":"Point"}
}