{
  "type": "Feature",
  "properties": {
    "iso:country":"US",
    "sg:address":"7041 Grand National Dr Ste 232",
    "sg:city":"Orlando",
    "sg:classifiers":[
        {
            "category":"Landmark",
            "subcategory":"Tourist Information",
            "type":"Public Place"
        }
    ],
    "sg:phone":"+1 407 641 0760",
    "sg:postcode":"32819",
    "sg:province":"FL",
    "sg:tags":[
        "attraction"
    ],
    "wof:name":"Go Orlando Card",
    "wof:placetype":"venue"
},
  "geometry": {"coordinates":[-81.45623000000001,28.459582],"type":"Point"}
}