{
  "type": "Feature",
  "properties": {
    "addr:full":"101 Edinburgh Dr Winter Park FL 32792",
    "addr:housenumber":"101",
    "addr:postcode":"32792",
    "addr:street":"Edinburgh Dr",
    "iso:country":"US",
    "sg:address":"101 Edinburgh Dr",
    "sg:city":"Winter Park",
    "sg:classifiers":[
        {
            "category":"Health Services",
            "subcategory":"Doctor",
            "type":"Services"
        }
    ],
    "sg:phone":"+1 407 647 6886",
    "sg:postcode":"32792",
    "sg:province":"FL",
    "wof:name":"Rodriguez Antonio L MD",
    "wof:placetype":"venue"
},
  "geometry": {"coordinates":[-81.304703,28.605101],"type":"Point"}
}