{
  "type": "Feature",
  "properties": {
    "addr:full":"3443 Gulf Shore Blvd N Naples FL 34103",
    "addr:housenumber":"3443",
    "addr:postcode":"34103",
    "addr:street":"Gulf Shore Blvd N",
    "iso:country":"US",
    "sg:address":"3443 Gulf Shore Blvd N",
    "sg:city":"Naples",
    "sg:classifiers":[
        {
            "category":"Professional",
            "subcategory":"Business Services",
            "type":"Services"
        }
    ],
    "sg:phone":"+1 239 403 7818",
    "sg:postcode":"34103",
    "sg:province":"FL",
    "sg:tags":[
        "interior",
        "consultant",
        "design",
        "decorator"
    ],
    "wof:name":"By Sandri",
    "wof:placetype":"venue"
},
  "geometry": {"coordinates":[-81.814089,26.188365],"type":"Point"}
}