{
  "type": "Feature",
  "properties": {
    "addr:full":"3400 Jericho Pl Apopka FL 32712",
    "addr:postcode":"3400;32712",
    "addr:street":"Jericho Pl",
    "iso:country":"US",
    "sg:address":"3400 Jericho Pl",
    "sg:city":"Apopka",
    "sg:classifiers":[
        {
            "category":"Real Estate",
            "subcategory":"Real Estate Agent",
            "type":"Services"
        }
    ],
    "sg:phone":"+1 407 886 7374",
    "sg:postcode":"32712",
    "sg:province":"FL",
    "wof:name":"Shelter Renew",
    "wof:placetype":"venue"
},
  "geometry": {"coordinates":[-81.516443,28.73685],"type":"Point"}
}