{
  "type": "Feature",
  "properties": {
    "iso:country":"US",
    "sg:address":"343 Auburn Dr",
    "sg:city":"Daytona Beach",
    "sg:classifiers":[
        {
            "category":"Professional",
            "subcategory":"Art Services",
            "type":"Services"
        }
    ],
    "sg:phone":"+1 386 677 6650",
    "sg:postcode":"32118",
    "sg:province":"FL",
    "sg:tags":[
        "graphic",
        "designer"
    ],
    "wof:name":"Abelbodies Professional Svc",
    "wof:placetype":"venue"
},
  "geometry": {"coordinates":[-81.03131,29.260702],"type":"Point"}
}