{
  "type": "Feature",
  "properties": {
    "addr:full":"4263 Poverty Creek Rd Crestview FL 32539",
    "addr:housenumber":"4263",
    "addr:postcode":"32539",
    "addr:street":"Poverty Creek Rd",
    "iso:country":"US",
    "sg:address":"4263 Poverty Creek Rd",
    "sg:city":"Crestview",
    "sg:classifiers":[
        {
            "category":"Building & Trades",
            "subcategory":"Construction",
            "type":"Services"
        }
    ],
    "sg:phone":"+1 850 682 7048",
    "sg:postcode":"32539",
    "sg:province":"FL",
    "sg:tags":[
        "layer",
        "carpet"
    ],
    "wof:name":"Barger Flooring",
    "wof:placetype":"venue"
},
  "geometry": {"coordinates":[-86.435298,30.807662],"type":"Point"}
}