{
  "type": "Feature",
  "properties": {
    "iso:country":"US",
    "sg:address":"5718 Clark Rd",
    "sg:city":"Sarasota",
    "sg:classifiers":[
        {
            "category":"Retail",
            "subcategory":"Repair Shop",
            "type":"Services"
        }
    ],
    "sg:phone":"+1 941 925 2281",
    "sg:postcode":"34233",
    "sg:province":"FL",
    "sg:tags":[
        "store"
    ],
    "wof:name":"Mugs Inc",
    "wof:placetype":"venue"
},
  "geometry": {"coordinates":[-82.45764,27.268956],"type":"Point"}
}