{
  "type": "Feature",
  "properties": {
    "addr:full":"755 Rinehart Rd Lake Mary FL 32746",
    "addr:housenumber":"755",
    "addr:postcode":"32746",
    "addr:street":"Rinehart Rd",
    "iso:country":"US",
    "sg:address":"755 Rinehart Rd",
    "sg:city":"Lake Mary",
    "sg:classifiers":[
        {
            "category":"Wholesale",
            "subcategory":"Drugs",
            "type":"Manufacturing & Wholesale Goods"
        }
    ],
    "sg:phone":"+1 407 330 6455",
    "sg:postcode":"32746",
    "sg:province":"FL",
    "sg:tags":[
        "pharmaceutical",
        "product"
    ],
    "wof:name":"BJS Pharmaceuticals",
    "wof:placetype":"venue"
},
  "geometry": {"coordinates":[-81.347352,28.779628],"type":"Point"}
}