{
  "type": "Feature",
  "properties": {
    "iso:country":"US",
    "sg:address":"1775 Jamaica Way",
    "sg:city":"Punta Gorda",
    "sg:classifiers":[
        {
            "category":"Banks & Credit Unions",
            "subcategory":"Financial Services",
            "type":"Services"
        }
    ],
    "sg:phone":"+1 941 639 2545",
    "sg:postcode":"33950",
    "sg:province":"FL",
    "sg:tags":[
        "trust",
        "investment",
        "real estate"
    ],
    "wof:name":"Higgins Enterprises",
    "wof:placetype":"venue"
},
  "geometry": {"coordinates":[-82.0719,26.925393],"type":"Point"}
}