{
  "type": "Feature",
  "properties": {
    "addr:full":"6412 Steuben St Weeki Wachee FL 34613",
    "addr:housenumber":"6412",
    "addr:postcode":"34613",
    "addr:street":"Steuben St",
    "iso:country":"US",
    "sg:address":"6412 Steuben St",
    "sg:city":"Weeki Wachee",
    "sg:classifiers":[
        {
            "category":"Social Services",
            "subcategory":"Child Care",
            "type":"Services"
        }
    ],
    "sg:phone":"+1 352 597 5417",
    "sg:postcode":"34613",
    "sg:province":"FL",
    "wof:name":"Gingerbread House Daycare",
    "wof:placetype":"venue"
},
  "geometry": {"coordinates":[-82.583493,28.525831],"type":"Point"}
}