{
  "type": "Feature",
  "properties": {
    "iso:country":"US",
    "sg:address":"3609 Myrtle Ave",
    "sg:city":"Jacksonville",
    "sg:classifiers":[
        {
            "category":"Organizations",
            "subcategory":"Religious Organization",
            "type":"Services"
        }
    ],
    "sg:phone":"+1 904 768 8848",
    "sg:postcode":"32209",
    "sg:province":"FL",
    "wof:name":"James Graham Evangelist",
    "wof:placetype":"venue"
},
  "geometry": {"coordinates":[-81.675956,30.360849],"type":"Point"}
}