{
  "type": "Feature",
  "properties": {
    "iso:country":"US",
    "sg:address":"16191 San Carlos Blvd Ste 1",
    "sg:city":"Fort Myers",
    "sg:classifiers":[
        {
            "category":"Recreation",
            "subcategory":"Boat Charter",
            "type":"Entertainment"
        }
    ],
    "sg:phone":"+1 239 432 2628",
    "sg:postcode":"33908",
    "sg:province":"FL",
    "sg:tags":[
        "boating"
    ],
    "sg:website":"www.suncoastinflatables.com",
    "wof:name":"Suncoast Inflatables",
    "wof:placetype":"venue"
},
  "geometry": {"coordinates":[-81.943065,26.505994],"type":"Point"}
}