{
  "type": "Feature",
  "properties": {
    "addr:full":"9880 NW 56th Pl Pompano Beach FL 33076",
    "addr:housenumber":"9880",
    "addr:postcode":"33076",
    "addr:street":"Nw 56Th Pl",
    "iso:country":"US",
    "sg:address":"9880 NW 56th Pl",
    "sg:city":"Pompano Beach",
    "sg:classifiers":[
        {
            "category":"Manufacturing",
            "subcategory":"Tools & Machinery",
            "type":"Manufacturing & Wholesale Goods"
        }
    ],
    "sg:phone":"+1 954 575 2603",
    "sg:postcode":"33076",
    "sg:province":"FL",
    "sg:tags":[
        "surgical",
        "mfg"
    ],
    "wof:name":"American Hearing Technology",
    "wof:placetype":"venue"
},
  "geometry": {"coordinates":[-80.255285,26.299973],"type":"Point"}
}