{
  "type": "Feature",
  "properties": {
    "addr:full":"280 Linton Blvd Delray Beach FL 33444",
    "addr:housenumber":"280",
    "addr:postcode":"33444",
    "addr:street":"Linton Blvd",
    "iso:country":"US",
    "sg:address":"280 Linton Blvd",
    "sg:city":"Delray Beach",
    "sg:classifiers":[
        {
            "category":"Restaurant",
            "type":"Food & Drink"
        }
    ],
    "sg:menulink":"http://www.allmenus.com/fl/boynton-beach-delray-beach/158611-arbys/menu/",
    "sg:phone":"+1 561 276 2729",
    "sg:postcode":"33444",
    "sg:province":"FL",
    "sg:tags":[
        "burger",
        "american"
    ],
    "wof:name":"Arby's",
    "wof:placetype":"venue"
},
  "geometry": {"coordinates":[-80.07573600000001,26.439306],"type":"Point"}
}