{
  "type": "Feature",
  "properties": {
    "addr:full":"6408 W Colonial Dr Orlando FL 32818",
    "addr:housenumber":"6408",
    "addr:postcode":"32818",
    "addr:street":"W Colonial Dr",
    "iso:country":"US",
    "sg:address":"6408 W Colonial Dr",
    "sg:city":"Orlando",
    "sg:classifiers":[
        {
            "category":"Social Services",
            "subcategory":"Child Care",
            "type":"Services"
        }
    ],
    "sg:phone":"+1 407 292 7600",
    "sg:postcode":"32818",
    "sg:province":"FL",
    "sg:tags":[
        "day"
    ],
    "wof:name":"Day To Nite Child Care Center",
    "wof:placetype":"venue"
},
  "geometry": {"coordinates":[-81.46918100000001,28.55203],"type":"Point"}
}