{
  "type": "Feature",
  "properties": {
    "iso:country":"US",
    "sg:address":"2699 N Amaryllis Rd",
    "sg:city":"Avon Park",
    "sg:classifiers":[
        {
            "category":"Organizations",
            "subcategory":"Religious Organization",
            "type":"Services"
        }
    ],
    "sg:phone":"+1 863 452 1281",
    "sg:postcode":"33825",
    "sg:province":"FL",
    "sg:tags":[
        "church"
    ],
    "wof:name":"Orange Blossom Baptst Assn Inc",
    "wof:placetype":"venue"
},
  "geometry": {"coordinates":[-81.526331,27.635742],"type":"Point"}
}