{
  "type": "Feature",
  "properties": {
    "addr:full":"4232 Cardinal Blvd Port Orange FL 32127",
    "addr:housenumber":"4232",
    "addr:postcode":"32127",
    "addr:street":"Cardinal Blvd",
    "iso:country":"US",
    "sg:address":"4232 Cardinal Blvd",
    "sg:city":"Port Orange",
    "sg:classifiers":[
        {
            "category":"Building & Trades",
            "subcategory":"Construction",
            "type":"Services"
        }
    ],
    "sg:phone":"+1 386 767 9616",
    "sg:postcode":"32127",
    "sg:province":"FL",
    "sg:tags":[
        "handyman"
    ],
    "wof:name":"Ben's Help Around The House",
    "wof:placetype":"venue"
},
  "geometry": {"coordinates":[-80.955331,29.124374],"type":"Point"}
}