{
  "type": "Feature",
  "properties": {
    "iso:country":"US",
    "sg:address":"5205 S Orange Ave Ste 202",
    "sg:city":"Orlando",
    "sg:classifiers":[
        {
            "category":"Communications",
            "subcategory":"Film & Video Production",
            "type":"Services"
        },
        {
            "category":"Banks & Credit Unions",
            "subcategory":"Investment Brokerage",
            "type":"Services"
        }
    ],
    "sg:phone":"+1 407 851 3777",
    "sg:postcode":"32809",
    "sg:province":"FL",
    "sg:tags":[
        "dvd",
        "sale",
        "dvds-rental",
        "cassette",
        "duplicating",
        "tape",
        "cd"
    ],
    "wof:name":"Paramont Solutions",
    "wof:placetype":"venue"
},
  "geometry": {"coordinates":[-81.372131,28.484909],"type":"Point"}
}