{
  "type": "Feature",
  "properties": {
    "iso:country":"US",
    "sg:address":"1628 SE 13th Ter",
    "sg:city":"Cape Coral",
    "sg:classifiers":[
        {
            "category":"Wholesale",
            "subcategory":"Non-durable Goods",
            "type":"Manufacturing & Wholesale Goods"
        }
    ],
    "sg:phone":"+1 239 242 0189",
    "sg:postcode":"33990",
    "sg:province":"FL",
    "wof:name":"Dove Trading Inc",
    "wof:placetype":"venue"
},
  "geometry": {"coordinates":[-81.934573,26.627865],"type":"Point"}
}