{
  "type": "Feature",
  "properties": {
    "addr:full":"4975 Cerise St Jacksonville FL 32258",
    "addr:housenumber":"4975",
    "addr:postcode":"32258",
    "addr:street":"Cerise St",
    "iso:country":"US",
    "sg:address":"4975 Cerise St",
    "sg:city":"Jacksonville",
    "sg:classifiers":[
        {
            "category":"Bus Charters",
            "type":"Transportation"
        }
    ],
    "sg:phone":"+1 904 268 0721",
    "sg:postcode":"32258",
    "sg:province":"FL",
    "wof:name":"Foreman Coach",
    "wof:placetype":"venue"
},
  "geometry": {"coordinates":[-81.576554,30.144445],"type":"Point"}
}