{
  "type": "Feature",
  "properties": {
    "addr:full":"200 Coach Club Dr Titusville FL 32780",
    "addr:housenumber":"200",
    "addr:postcode":"32780",
    "addr:street":"Coach Club Dr",
    "iso:country":"US",
    "sg:address":"200 Coach Club Dr",
    "sg:city":"Titusville",
    "sg:classifiers":[
        {
            "category":"Wholesale",
            "subcategory":"Auto Parts",
            "type":"Manufacturing & Wholesale Goods"
        }
    ],
    "sg:phone":"+1 321 268 9733",
    "sg:postcode":"32780",
    "sg:province":"FL",
    "sg:tags":[
        "used"
    ],
    "wof:name":"Technivest Group",
    "wof:placetype":"venue"
},
  "geometry": {"coordinates":[-80.865358,28.521283],"type":"Point"}
}