{
  "type": "Feature",
  "properties": {
    "iso:country":"US",
    "sg:address":"9076 108th Ave",
    "sg:city":"Vero Beach",
    "sg:classifiers":[
        {
            "category":"Manufacturing",
            "subcategory":"Furniture",
            "type":"Manufacturing & Wholesale Goods"
        }
    ],
    "sg:phone":"+1 772 589 9540",
    "sg:postcode":"32967",
    "sg:province":"FL",
    "sg:tags":[
        "household",
        "wood",
        "mfg"
    ],
    "wof:name":"McElroys Southern Heirlooms",
    "wof:placetype":"venue"
},
  "geometry": {"coordinates":[-80.54794,27.758777],"type":"Point"}
}