{
  "type": "Feature",
  "properties": {
    "iso:country":"US",
    "sg:address":"2202 Sherbrook Dr",
    "sg:city":"Valrico",
    "sg:classifiers":[
        {
            "category":"Professional",
            "subcategory":"Employment Agencies",
            "type":"Services"
        }
    ],
    "sg:phone":"+1 813 689 2733",
    "sg:postcode":"33594",
    "sg:province":"FL",
    "wof:name":"Riddles Cabinetry & Odd Jobs",
    "wof:placetype":"venue"
},
  "geometry": {"coordinates":[-82.232783,27.910441],"type":"Point"}
}