{
  "type": "Feature",
  "properties": {
    "addr:full":"9825 Berkshire St Naples FL 34109",
    "addr:housenumber":"9825",
    "addr:postcode":"34109",
    "addr:street":"Berkshire St",
    "iso:country":"US",
    "sg:address":"9825 Berkshire St",
    "sg:city":"Naples",
    "sg:classifiers":[
        {
            "category":"Professional",
            "subcategory":"Advertising",
            "type":"Services"
        }
    ],
    "sg:phone":"+1 239 514 0845",
    "sg:postcode":"34109",
    "sg:province":"FL",
    "sg:tags":[
        "counselor"
    ],
    "wof:name":"Exceptional Marketing Concept",
    "wof:placetype":"venue"
},
  "geometry": {"coordinates":[-81.771595,26.260105],"type":"Point"}
}