{
  "type": "Feature",
  "properties": {
    "iso:country":"US",
    "sg:address":"5689 Indigo Ave",
    "sg:city":"Stuart",
    "sg:classifiers":[
        {
            "category":"Manufacturing",
            "subcategory":"Apparel",
            "type":"Manufacturing & Wholesale Goods"
        }
    ],
    "sg:phone":"+1 772 288 3721",
    "sg:postcode":"34997",
    "sg:province":"FL",
    "wof:name":"Thomas J Favors",
    "wof:placetype":"venue"
},
  "geometry": {"coordinates":[-80.21076499999999,27.135547],"type":"Point"}
}