{
  "type": "Feature",
  "properties": {
    "addr:full":"12761 NW 75th St Pompano Beach FL 33076",
    "addr:housenumber":"12761",
    "addr:postcode":"33076",
    "addr:street":"Nw 75Th St",
    "iso:country":"US",
    "sg:address":"12761 NW 75th St",
    "sg:city":"Pompano Beach",
    "sg:classifiers":[
        {
            "category":"Social Services",
            "type":"Services"
        }
    ],
    "sg:phone":"+1 954 575 8631",
    "sg:postcode":"33076",
    "sg:province":"FL",
    "wof:name":"Plushko Inc",
    "wof:placetype":"venue"
},
  "geometry": {"coordinates":[-80.295486,26.323868],"type":"Point"}
}