{
  "type": "Feature",
  "properties": {
    "addr:full":"1951 S McCall Rd Englewood FL 34223",
    "addr:housenumber":"1951",
    "addr:postcode":"34223",
    "addr:street":"S Mccall Rd",
    "iso:country":"US",
    "sg:address":"1951 S McCall Rd",
    "sg:city":"Englewood",
    "sg:classifiers":[
        {
            "category":"Home & Garden",
            "subcategory":"Building Materials",
            "type":"Retail Goods"
        }
    ],
    "sg:phone":"+1 941 475 9533",
    "sg:postcode":"34223",
    "sg:province":"FL",
    "sg:tags":[
        "supply"
    ],
    "wof:name":"Scottys 460",
    "wof:placetype":"venue"
},
  "geometry": {"coordinates":[-82.33451599999999,26.937301],"type":"Point"}
}