{
  "type": "Feature",
  "properties": {
    "addr:full":"2701 SW 145th Ave Miramar FL 33027",
    "addr:housenumber":"2701",
    "addr:postcode":"33027",
    "addr:street":"Sw 145Th Ave",
    "iso:country":"US",
    "sg:address":"2701 SW 145th Ave",
    "sg:city":"Miramar",
    "sg:classifiers":[
        {
            "category":"Building & Trades",
            "subcategory":"Equipment Rental",
            "type":"Services"
        }
    ],
    "sg:phone":"+1 954 392 5195",
    "sg:postcode":"33027",
    "sg:province":"FL",
    "sg:tags":[
        "appliance"
    ],
    "wof:name":"Appliance Warehouse",
    "wof:placetype":"venue"
},
  "geometry": {"coordinates":[-80.339946,25.984271],"type":"Point"}
}