{
  "type": "Feature",
  "properties": {
    "iso:country":"US",
    "sg:address":"1563 N Dixie Hwy",
    "sg:city":"Pompano Beach",
    "sg:classifiers":[
        {
            "category":"Restaurant",
            "type":"Food & Drink"
        }
    ],
    "sg:phone":"+1 954 941 7565",
    "sg:postcode":"33060",
    "sg:province":"FL",
    "wof:name":"Subs Subs Subs",
    "wof:placetype":"venue"
},
  "geometry": {"coordinates":[-80.121255,26.249119],"type":"Point"}
}