{
  "type": "Feature",
  "properties": {
    "iso:country":"US",
    "sg:address":"5422 Parkway Dr",
    "sg:city":"Orlando",
    "sg:classifiers":[
        {
            "category":"Building & Trades",
            "subcategory":"Construction",
            "type":"Services"
        }
    ],
    "sg:phone":"+1 407 851 5903",
    "sg:postcode":"32809",
    "sg:province":"FL",
    "sg:tags":[
        "coping",
        "plastering",
        "tiling",
        "pool",
        "swimming"
    ],
    "wof:name":"Deck Effects",
    "wof:placetype":"venue"
},
  "geometry": {"coordinates":[-81.35291100000001,28.4834],"type":"Point"}
}