{
  "type": "Feature",
  "properties": {
    "addr:full":"8877 Pensacola Blvd Pensacola FL 32534",
    "addr:housenumber":"8877",
    "addr:postcode":"32534",
    "addr:street":"Pensacola Blvd",
    "iso:country":"US",
    "sg:address":"8877 Pensacola Blvd",
    "sg:city":"Pensacola",
    "sg:classifiers":[
        {
            "category":"Autos & Motor Vehicles",
            "subcategory":"Auto Supplies",
            "type":"Retail Goods"
        }
    ],
    "sg:phone":"+1 850 476 2728",
    "sg:postcode":"32534",
    "sg:province":"FL",
    "sg:tags":[
        "automobile",
        "parts"
    ],
    "sg:website":"www.autozone.com",
    "wof:name":"Autozone",
    "wof:placetype":"venue"
},
  "geometry": {"coordinates":[-87.27480799999999,30.525697],"type":"Point"}
}