{
  "type": "Feature",
  "properties": {
    "addr:full":"3225 Aviation Ave Miami FL 33133",
    "addr:housenumber":"3225",
    "addr:postcode":"33133",
    "addr:street":"Aviation Ave",
    "iso:country":"US",
    "sg:address":"3225 Aviation Ave",
    "sg:city":"Miami",
    "sg:classifiers":[
        {
            "category":"Health Services",
            "subcategory":"Doctor",
            "type":"Services"
        }
    ],
    "sg:phone":"+1 305 854 8828",
    "sg:postcode":"33133",
    "sg:province":"FL",
    "sg:tags":[
        "physician",
        "surgeon",
        "medical"
    ],
    "wof:name":"James M Sutzin MD",
    "wof:placetype":"venue"
},
  "geometry": {"coordinates":[-80.23403999999999,25.733181],"type":"Point"}
}