{
  "type": "Feature",
  "properties": {
    "iso:country":"US",
    "sg:address":"809 Pine St",
    "sg:city":"Leesburg",
    "sg:classifiers":[
        {
            "category":"Health Services",
            "subcategory":"Doctor",
            "type":"Services"
        }
    ],
    "sg:phone":"+1 352 326 5961",
    "sg:postcode":"34748",
    "sg:province":"FL",
    "sg:tags":[
        "physician",
        "family",
        "practice",
        "surgeons",
        "medicine"
    ],
    "wof:name":"Medicus Forensics, Pa",
    "wof:placetype":"venue"
},
  "geometry": {"coordinates":[-81.866455,28.809031],"type":"Point"}
}