{
  "type": "Feature",
  "properties": {
    "addr:full":"1696 SW 101st Ave Miami FL 33165",
    "addr:housenumber":"1696",
    "addr:postcode":"33165",
    "addr:street":"Sw 101St Ave",
    "iso:country":"US",
    "sg:address":"1696 SW 101st Ave",
    "sg:city":"Miami",
    "sg:classifiers":[
        {
            "category":"Food & Beverages",
            "subcategory":"Groceries & Convenience Stores",
            "type":"Retail Goods"
        }
    ],
    "sg:phone":"+1 954 437 3418",
    "sg:postcode":"33165",
    "sg:province":"FL",
    "sg:website":"www.7-eleven.com",
    "wof:name":"7-Eleven Inc",
    "wof:placetype":"venue"
},
  "geometry": {"coordinates":[-80.35936,25.753545],"type":"Point"}
}