{
  "type": "Feature",
  "properties": {
    "iso:country":"US",
    "sg:address":"417 Laurel Rd E",
    "sg:city":"Nokomis",
    "sg:classifiers":[
        {
            "category":"Retail",
            "subcategory":"Auto Repair",
            "type":"Services"
        }
    ],
    "sg:phone":"+1 941 483 3717",
    "sg:postcode":"34275",
    "sg:province":"FL",
    "sg:tags":[
        "repairing",
        "automobile",
        "general"
    ],
    "wof:name":"Owen Service Center",
    "wof:placetype":"venue"
},
  "geometry": {"coordinates":[-82.45077999999999,27.138436],"type":"Point"}
}