{
  "type": "Feature",
  "properties": {
    "iso:country":"US",
    "sg:address":"5506 SW 4 Pl",
    "sg:city":"Gainesville",
    "sg:classifiers":[
        {
            "category":"Communications",
            "subcategory":"Film & Video Production",
            "type":"Services"
        }
    ],
    "sg:phone":"+1 352 377 1174",
    "sg:postcode":"32607",
    "sg:province":"FL",
    "sg:tags":[
        "motion"
    ],
    "wof:name":"Y Gen Productions Inc",
    "wof:placetype":"venue"
},
  "geometry": {"coordinates":[-82.40179999999999,29.648178],"type":"Point"}
}