{
  "type": "Feature",
  "properties": {
    "iso:country":"US",
    "sg:address":"5411 Ginger Way",
    "sg:city":"Lake Worth",
    "sg:classifiers":[
        {
            "category":"Building & Trades",
            "subcategory":"Construction",
            "type":"Services"
        }
    ],
    "sg:phone":"+1 561 312 3104",
    "sg:postcode":"33463",
    "sg:province":"FL",
    "sg:tags":[
        "carpenter"
    ],
    "wof:name":"Robert E Corbin Carpentry",
    "wof:placetype":"venue"
},
  "geometry": {"coordinates":[-80.128334,26.614881],"type":"Point"}
}