{
  "type": "Feature",
  "properties": {
    "iso:country":"US",
    "sg:address":"6633 Hartland St",
    "sg:city":"Fort Myers",
    "sg:classifiers":[
        {
            "category":"Building & Trades",
            "subcategory":"Electrical",
            "type":"Services"
        }
    ],
    "sg:phone":"+1 239 274 3010",
    "sg:postcode":"33966",
    "sg:province":"FL",
    "sg:tags":[
        "electric",
        "contractor"
    ],
    "wof:name":"JTE Electric",
    "wof:placetype":"venue"
},
  "geometry": {"coordinates":[-81.843817,26.58406],"type":"Point"}
}