{
  "type": "Feature",
  "properties": {
    "addr:full":"5228 Nimitz Rd Milton FL 32583",
    "addr:housenumber":"5228",
    "addr:postcode":"32583",
    "addr:street":"Nimitz Rd",
    "iso:country":"US",
    "sg:address":"5228 Nimitz Rd",
    "sg:city":"Milton",
    "sg:classifiers":[
        {
            "category":"Manufacturing",
            "subcategory":"Retail Goods",
            "type":"Manufacturing & Wholesale Goods"
        }
    ],
    "sg:phone":"+1 850 983 8042",
    "sg:postcode":"32583",
    "sg:province":"FL",
    "sg:tags":[
        "product",
        "mfg"
    ],
    "wof:name":"Happy Chimes",
    "wof:placetype":"venue"
},
  "geometry": {"coordinates":[-87.023612,30.623834],"type":"Point"}
}