{
  "type": "Feature",
  "properties": {
    "addr:full":"3503 Kernan Blvd S Jacksonville FL 32224",
    "addr:housenumber":"3503",
    "addr:postcode":"32224",
    "addr:street":"Kernan Blvd S",
    "iso:country":"US",
    "sg:address":"3503 Kernan Blvd S",
    "sg:city":"Jacksonville",
    "sg:classifiers":[
        {
            "category":"Restaurant",
            "type":"Food & Drink"
        }
    ],
    "sg:menulink":"http://www.allmenus.com/fl/jacksonville/245312-sienas-pizza--italian-cuisine/menu/",
    "sg:phone":"+1 904 645 8595",
    "sg:postcode":"32224",
    "sg:province":"FL",
    "sg:tags":[
        "italian"
    ],
    "wof:name":"Siena's Pizza & Italian Cuisine",
    "wof:placetype":"venue"
},
  "geometry": {"coordinates":[-81.490122,30.284148],"type":"Point"}
}