{
  "type": "Feature",
  "properties": {
    "addr:full":"1800 NW 79th St Miami FL 33147",
    "addr:housenumber":"1800",
    "addr:postcode":"33147",
    "addr:street":"Nw 79Th St",
    "iso:country":"US",
    "sg:address":"1800 NW 79th St",
    "sg:city":"Miami",
    "sg:classifiers":[
        {
            "category":"Bars & Pubs",
            "type":"Food & Drink"
        },
        {
            "category":"Bars & Pubs",
            "subcategory":"Nightclub",
            "type":"Food & Drink"
        },
        {
            "category":"Bars & Pubs",
            "subcategory":"Lounge",
            "type":"Food & Drink"
        }
    ],
    "sg:phone":"+1 305 691 5032",
    "sg:postcode":"33147",
    "sg:province":"FL",
    "sg:tags":[
        "club",
        "cocktail",
        "night"
    ],
    "wof:name":"Big Mac's Foxy Lady Lounge",
    "wof:placetype":"venue"
},
  "geometry": {"coordinates":[-80.22698200000001,25.846411],"type":"Point"}
}