{
  "type": "Feature",
  "properties": {
    "iso:country":"US",
    "sg:address":"407 5th Ave",
    "sg:city":"Indialantic",
    "sg:classifiers":[
        {
            "category":"Personal",
            "subcategory":"Barber",
            "type":"Services"
        }
    ],
    "sg:phone":"+1 321 725 2652",
    "sg:postcode":"32903",
    "sg:province":"FL",
    "wof:name":"Fifth Avenue Men's Hairstyling",
    "wof:placetype":"venue"
},
  "geometry": {"coordinates":[-80.57493100000001,28.089153],"type":"Point"}
}