{
  "type": "Feature",
  "properties": {
    "addr:full":"35410 Micro Racetrack Rd Fruitland Park FL 34731",
    "addr:postcode":"35410;34731",
    "addr:street":"Racetrack Rd",
    "iso:country":"US",
    "sg:address":"35410 Micro Racetrack Rd",
    "sg:city":"Fruitland Park",
    "sg:classifiers":[
        {
            "category":"Building & Trades",
            "subcategory":"Landscaping Services",
            "type":"Services"
        }
    ],
    "sg:phone":"+1 352 326 2190",
    "sg:postcode":"34731",
    "sg:province":"FL",
    "wof:name":"Steven James Rice",
    "wof:placetype":"venue"
},
  "geometry": {"coordinates":[-81.945126,28.866831],"type":"Point"}
}