{
  "type": "Feature",
  "properties": {
    "iso:country":"US",
    "sg:address":"320 Kings Lynn",
    "sg:city":"Delray Beach",
    "sg:classifiers":[
        {
            "category":"Food & Beverages",
            "subcategory":"Bakery",
            "type":"Retail Goods"
        }
    ],
    "sg:phone":"+1 561 254 8505",
    "sg:postcode":"33444",
    "sg:province":"FL",
    "wof:name":"Alpine Bakery",
    "wof:placetype":"venue"
},
  "geometry": {"coordinates":[-80.076302,26.471049],"type":"Point"}
}