{
  "type": "Feature",
  "properties": {
    "iso:country":"US",
    "sg:address":"10409 SW 186th Ave",
    "sg:city":"Miami",
    "sg:classifiers":[
        {
            "category":"Home & Garden",
            "subcategory":"Kitchen Supply",
            "type":"Retail Goods"
        }
    ],
    "sg:phone":"+1 786 242 9959",
    "sg:postcode":"33196",
    "sg:province":"FL",
    "sg:tags":[
        "utensil",
        "cookware"
    ],
    "wof:name":"Granite Kitchen & Baths Inc",
    "wof:placetype":"venue"
},
  "geometry": {"coordinates":[-80.49494799999999,25.666808],"type":"Point"}
}