{
  "type": "Feature",
  "properties": {
    "iso:country":"US",
    "sg:address":"12785 W Forest Hill Blvd",
    "sg:city":"West Palm Beach",
    "sg:classifiers":[
        {
            "category":"Restaurant",
            "type":"Food & Drink"
        }
    ],
    "sg:menulink":"http://www.allmenus.com/fl/sunshine-parkway/52230-wongs/menu/",
    "sg:phone":"+1 561 793 7275",
    "sg:postcode":"33414",
    "sg:province":"FL",
    "sg:tags":[
        "asian",
        "chinese"
    ],
    "wof:name":"Wong's",
    "wof:placetype":"venue"
},
  "geometry": {"coordinates":[-80.247023,26.671436],"type":"Point"}
}