{
  "type": "Feature",
  "properties": {
    "iso:country":"US",
    "sg:address":"13811 River Forest Dr",
    "sg:city":"Fort Myers",
    "sg:classifiers":[
        {
            "category":"Real Estate",
            "subcategory":"Real Estate Agent",
            "type":"Services"
        }
    ],
    "sg:phone":"+1 239 693 7850",
    "sg:postcode":"33905",
    "sg:province":"FL",
    "sg:tags":[
        "ban",
        "consulting",
        "mortgage"
    ],
    "wof:name":"Neighbor Wood Real Estate",
    "wof:placetype":"venue"
},
  "geometry": {"coordinates":[-81.732358,26.719382],"type":"Point"}
}