{
  "type": "Feature",
  "properties": {
    "addr:full":"8394 SW 152nd Ave Apt 32 Miami FL 33193",
    "addr:housenumber":"8394;32",
    "addr:postcode":"33193",
    "addr:street":"Sw 152Nd Ave Apt",
    "iso:country":"US",
    "sg:address":"8394 SW 152nd Ave Apt 32",
    "sg:city":"Miami",
    "sg:classifiers":[
        {
            "category":"Communications",
            "type":"Services"
        }
    ],
    "sg:phone":"+1 305 305 1802",
    "sg:postcode":"33193",
    "sg:province":"FL",
    "wof:name":"Bars And Tone Multimedia",
    "wof:placetype":"venue"
},
  "geometry": {"coordinates":[-80.439556,25.68987],"type":"Point"}
}