{
  "type": "Feature",
  "properties": {
    "addr:full":"4200 SE 24th St Ocala FL 34471",
    "addr:housenumber":"4200",
    "addr:postcode":"34471",
    "addr:street":"Se 24Th St",
    "iso:country":"US",
    "sg:address":"4200 SE 24th St",
    "sg:city":"Ocala",
    "sg:classifiers":[
        {
            "category":"Government",
            "subcategory":"Office",
            "type":"Public Place"
        }
    ],
    "sg:phone":"+1 352 401 6925",
    "sg:postcode":"34471",
    "sg:province":"FL",
    "sg:tags":[
        "village"
    ],
    "wof:name":"Ocala Water Reclamation",
    "wof:placetype":"venue"
},
  "geometry": {"coordinates":[-82.076019,29.164234],"type":"Point"}
}