{
  "type": "Feature",
  "properties": {
    "iso:country":"US",
    "sg:address":"6001 NW 29th Ave",
    "sg:city":"Fort Lauderdale",
    "sg:classifiers":[
        {
            "category":"Autos & Motor Vehicles",
            "subcategory":"Automobile Sales",
            "type":"Retail Goods"
        }
    ],
    "sg:phone":"+1 954 970 3200",
    "sg:postcode":"33309",
    "sg:province":"FL",
    "sg:tags":[
        "equipment",
        "aircraft",
        "parts",
        "supply"
    ],
    "sg:website":"www.airmarkoverhaul.com",
    "wof:name":"Airmark Overhaul Inc",
    "wof:placetype":"venue"
},
  "geometry": {"coordinates":[-80.18471,26.200557],"type":"Point"}
}