{
  "type": "Feature",
  "properties": {
    "iso:country":"US",
    "sg:address":"416 N Federal Hwy",
    "sg:city":"Boynton Beach",
    "sg:classifiers":[
        {
            "category":"Wholesale",
            "subcategory":"Machinery & Supplies",
            "type":"Manufacturing & Wholesale Goods"
        },
        {
            "category":"Shopping",
            "type":"Retail Goods"
        }
    ],
    "sg:phone":"+1 561 732 5404",
    "sg:postcode":"33435",
    "sg:province":"FL",
    "sg:tags":[
        "equipment",
        "establishment",
        "cosmetic",
        "perfume"
    ],
    "wof:name":"Elegant Beauty Supplies 4",
    "wof:placetype":"venue"
},
  "geometry": {"coordinates":[-80.05807,26.530617],"type":"Point"}
}