{
  "type": "Feature",
  "properties": {
    "addr:full":"102 NE 3rd Ave Miami FL 33132",
    "addr:housenumber":"102",
    "addr:postcode":"33132",
    "addr:street":"Ne 3Rd Ave",
    "iso:country":"US",
    "sg:address":"102 NE 3rd Ave",
    "sg:city":"Miami",
    "sg:classifiers":[
        {
            "category":"Wholesale",
            "subcategory":"Drugs",
            "type":"Manufacturing & Wholesale Goods"
        }
    ],
    "sg:phone":"+1 305 372 9988",
    "sg:postcode":"33132",
    "sg:province":"FL",
    "sg:tags":[
        "perfume"
    ],
    "sg:website":"www.etperfumes.com",
    "wof:name":"E T Perfumes",
    "wof:placetype":"venue"
},
  "geometry": {"coordinates":[-80.18863399999999,25.775263],"type":"Point"}
}