{
  "type": "Feature",
  "properties": {
    "addr:full":"5541 N Military Trl Boca Raton FL 33496",
    "addr:housenumber":"5541",
    "addr:postcode":"33496",
    "addr:street":"N Military Trl",
    "iso:country":"US",
    "sg:address":"5541 N Military Trl",
    "sg:city":"Boca Raton",
    "sg:classifiers":[
        {
            "category":"Manufacturing",
            "subcategory":"Tools & Machinery",
            "type":"Manufacturing & Wholesale Goods"
        }
    ],
    "sg:phone":"+1 561 912 9970",
    "sg:postcode":"33496",
    "sg:province":"FL",
    "sg:tags":[
        "equipment",
        "ionizer",
        "pool",
        "mfg"
    ],
    "wof:name":"Crystal Pool Technologies",
    "wof:placetype":"venue"
},
  "geometry": {"coordinates":[-80.12164900000001,26.400493],"type":"Point"}
}