{
  "type": "Feature",
  "properties": {
    "iso:country":"US",
    "sg:address":"5979 NW 151st St",
    "sg:city":"Hialeah",
    "sg:classifiers":[
        {
            "category":"Insurance",
            "subcategory":"Insurance Agent",
            "type":"Services"
        }
    ],
    "sg:phone":"+1 305 824 9430",
    "sg:postcode":"33014",
    "sg:province":"FL",
    "sg:tags":[
        "adjuster"
    ],
    "wof:name":"Cramer Johnson Wiggins & Assoc",
    "wof:placetype":"venue"
},
  "geometry": {"coordinates":[-80.297907,25.910855],"type":"Point"}
}