{
  "type": "Feature",
  "properties": {
    "iso:country":"US",
    "sg:address":"2315 Griffin Rd",
    "sg:city":"Leesburg",
    "sg:classifiers":[
        {
            "category":"Wholesale",
            "subcategory":"Office Equipment",
            "type":"Manufacturing & Wholesale Goods"
        }
    ],
    "sg:phone":"+1 352 323 0633",
    "sg:postcode":"34748",
    "sg:province":"FL",
    "sg:tags":[
        "machine",
        "repair",
        "retail",
        "duplicating",
        "copying"
    ],
    "wof:name":"Alpha Office Technologies Inc",
    "wof:placetype":"venue"
},
  "geometry": {"coordinates":[-81.90172099999999,28.828573],"type":"Point"}
}