{
  "type": "Feature",
  "properties": {
    "iso:country":"US",
    "sg:address":"6355 SW 48th St",
    "sg:city":"Miami",
    "sg:classifiers":[
        {
            "category":"Real Estate",
            "subcategory":"Developer",
            "type":"Services"
        }
    ],
    "sg:phone":"+1 305 667 2314",
    "sg:postcode":"33155",
    "sg:province":"FL",
    "wof:name":"Industrial Consultants & Mgmt",
    "wof:placetype":"venue"
},
  "geometry": {"coordinates":[-80.298321,25.726114],"type":"Point"}
}