{
  "type": "Feature",
  "properties": {
    "iso:country":"US",
    "sg:address":"160 W State Road 434",
    "sg:city":"Winter Springs",
    "sg:classifiers":[
        {
            "category":"Food & Beverages",
            "subcategory":"Groceries & Convenience Stores",
            "type":"Retail Goods"
        }
    ],
    "sg:phone":"+1 407 327 1723",
    "sg:postcode":"32708",
    "sg:province":"FL",
    "wof:name":"Auro International Inc",
    "wof:placetype":"venue"
},
  "geometry": {"coordinates":[-81.307148,28.699101],"type":"Point"}
}