{
  "type": "Feature",
  "properties": {
    "addr:full":"2200 Crescent Wood Rd Gulf Breeze FL 32566",
    "addr:housenumber":"2200",
    "addr:postcode":"32566",
    "addr:street":"Crescent Wood Rd",
    "iso:country":"US",
    "sg:address":"2200 Crescent Wood Rd",
    "sg:city":"Gulf Breeze",
    "sg:classifiers":[
        {
            "category":"Building & Trades",
            "subcategory":"Construction",
            "type":"Services"
        }
    ],
    "sg:phone":"+1 850 939 4310",
    "sg:postcode":"32566",
    "sg:province":"FL",
    "sg:tags":[
        "insulation",
        "plastering",
        "drywall"
    ],
    "wof:name":"McCasland Drywall & Paint",
    "wof:placetype":"venue"
},
  "geometry": {"coordinates":[-86.80719499999999,30.41337],"type":"Point"}
}