{
  "type": "Feature",
  "properties": {
    "addr:full":"637 Haftez St NE Palm Bay FL 32907",
    "addr:housenumber":"637",
    "addr:postcode":"32907",
    "addr:street":"Haftez St Ne",
    "iso:country":"US",
    "sg:address":"637 Haftez St NE",
    "sg:city":"Palm Bay",
    "sg:classifiers":[
        {
            "category":"Real Estate",
            "subcategory":"Real Estate Agent",
            "type":"Services"
        }
    ],
    "sg:phone":"+1 321 729 8327",
    "sg:postcode":"32907",
    "sg:province":"FL",
    "wof:name":"Jebco Real Estate Solutions",
    "wof:placetype":"venue"
},
  "geometry": {"coordinates":[-80.656058,28.020287],"type":"Point"}
}