{
  "type": "Feature",
  "properties": {
    "iso:country":"US",
    "sg:address":"11223 Beaverbank St",
    "sg:city":"Brooksville",
    "sg:classifiers":[
        {
            "category":"Building & Trades",
            "subcategory":"Cleaning & Sanitation",
            "type":"Services"
        }
    ],
    "sg:phone":"+1 352 596 4416",
    "sg:postcode":"34614",
    "sg:province":"FL",
    "sg:tags":[
        "maintenance"
    ],
    "wof:name":"J & B Maid Service",
    "wof:placetype":"venue"
},
  "geometry": {"coordinates":[-82.556162,28.591406],"type":"Point"}
}