{
  "type": "Feature",
  "properties": {
    "iso:country":"US",
    "sg:address":"1301 W 68th St",
    "sg:city":"Hialeah",
    "sg:classifiers":[
        {
            "category":"Banks & Credit Unions",
            "subcategory":"Financial Services",
            "type":"Services"
        }
    ],
    "sg:phone":"+1 786 360 1721",
    "sg:postcode":"33014",
    "sg:province":"FL",
    "sg:tags":[
        "money",
        "transfer"
    ],
    "wof:name":"King Multiservices Corp",
    "wof:placetype":"venue"
},
  "geometry": {"coordinates":[-80.31004299999999,25.88418],"type":"Point"}
}