{
  "type": "Feature",
  "properties": {
    "iso:country":"US",
    "sg:address":"7001 Environ Blvd",
    "sg:city":"Fort Lauderdale",
    "sg:classifiers":[
        {
            "category":"Wholesale",
            "subcategory":"Vending Machines",
            "type":"Manufacturing & Wholesale Goods"
        }
    ],
    "sg:phone":"+1 954 584 6578",
    "sg:postcode":"33319",
    "sg:province":"FL",
    "sg:tags":[
        "operator"
    ],
    "wof:name":"Apple Vending Corp",
    "wof:placetype":"venue"
},
  "geometry": {"coordinates":[-80.242745,26.174547],"type":"Point"}
}