{
  "type": "Feature",
  "properties": {
    "addr:full":"12075 NW 40th St Pompano Beach FL 33065",
    "addr:housenumber":"12075",
    "addr:postcode":"33065",
    "addr:street":"Nw 40Th St",
    "iso:country":"US",
    "sg:address":"12075 NW 40th St",
    "sg:city":"Pompano Beach",
    "sg:classifiers":[
        {
            "category":"Restaurant",
            "type":"Food & Drink"
        }
    ],
    "sg:phone":"+1 954 752 2299",
    "sg:postcode":"33065",
    "sg:province":"FL",
    "sg:tags":[
        "product",
        "eating",
        "mfg"
    ],
    "wof:name":"NTC Rehab",
    "wof:placetype":"venue"
},
  "geometry": {"coordinates":[-80.288168,26.280857],"type":"Point"}
}