{
  "type": "Feature",
  "properties": {
    "addr:full":"9539 US Hwy 98 Destin FL 32550",
    "addr:housenumber":"9539",
    "addr:postcode":"32550",
    "addr:street":"Us Hwy 98",
    "iso:country":"US",
    "sg:address":"9539 US Hwy 98",
    "sg:city":"Destin",
    "sg:classifiers":[
        {
            "category":"Shopping",
            "subcategory":"Clothing, Apparel, & Fashions",
            "type":"Retail Goods"
        }
    ],
    "sg:phone":"+1 850 654 4448",
    "sg:postcode":"32550",
    "sg:province":"FL",
    "wof:name":"Beach Bums",
    "wof:placetype":"venue"
},
  "geometry": {"coordinates":[-86.33431299999999,30.377676],"type":"Point"}
}