{
  "type": "Feature",
  "properties": {
    "iso:country":"US",
    "sg:address":"605 NW 53rd Ave",
    "sg:city":"Gainesville",
    "sg:classifiers":[
        {
            "category":"Real Estate",
            "subcategory":"Surveying",
            "type":"Services"
        }
    ],
    "sg:phone":"+1 352 338 9667",
    "sg:postcode":"32609",
    "sg:province":"FL",
    "sg:tags":[
        "surveyor",
        "land",
        "engineer"
    ],
    "sg:website":"http://www.degrove.com",
    "wof:name":"Degrove Surveyors Inc",
    "wof:placetype":"venue"
},
  "geometry": {"coordinates":[-82.33041799999999,29.703186],"type":"Point"}
}