{
  "type": "Feature",
  "properties": {
    "iso:country":"US",
    "sg:address":"618 Gap Creek Dr",
    "sg:city":"Fort Walton Bch",
    "sg:classifiers":[
        {
            "category":"Professional",
            "subcategory":"Business Services",
            "type":"Services"
        }
    ],
    "sg:phone":"+1 850 863 9808",
    "sg:postcode":"32548",
    "sg:province":"FL",
    "sg:tags":[
        "drafting"
    ],
    "wof:name":"Beth Haden Residential Design",
    "wof:placetype":"venue"
},
  "geometry": {"coordinates":[-86.640996,30.429598],"type":"Point"}
}