{
  "type": "Feature",
  "properties": {
    "iso:country":"US",
    "sg:address":"570 SW 87th Pl",
    "sg:city":"Ocala",
    "sg:classifiers":[
        {
            "category":"Shopping",
            "subcategory":"Used Merchandise",
            "type":"Retail Goods"
        }
    ],
    "sg:phone":"+1 352 237 1899",
    "sg:postcode":"34476",
    "sg:province":"FL",
    "wof:name":"Frazer Coal Co Antiques",
    "wof:placetype":"venue"
},
  "geometry": {"coordinates":[-82.140837,29.095345],"type":"Point"}
}