{
  "type": "Feature",
  "properties": {
    "addr:full":"921 SW 27th Ave Miami FL 33135",
    "addr:housenumber":"921",
    "addr:postcode":"33135",
    "addr:street":"Sw 27Th Ave",
    "iso:country":"US",
    "sg:address":"921 SW 27th Ave",
    "sg:city":"Miami",
    "sg:classifiers":[
        {
            "category":"Travel",
            "subcategory":"Travel Agent",
            "type":"Entertainment"
        },
        {
            "category":"Landmark",
            "subcategory":"Tourist Information",
            "type":"Public Place"
        }
    ],
    "sg:phone":"+1 305 642 6073",
    "sg:postcode":"33135",
    "sg:province":"FL",
    "sg:tags":[
        "agency",
        "services-commercial",
        "tours-operators",
        "promoter"
    ],
    "wof:name":"Tellez's Tour & Travel Agency",
    "wof:placetype":"venue"
},
  "geometry": {"coordinates":[-80.238742,25.764272],"type":"Point"}
}