{
  "type": "Feature",
  "properties": {
    "iso:country":"US",
    "sg:address":"100 2nd Ave SE",
    "sg:city":"St Petersburg",
    "sg:classifiers":[
        {
            "category":"Social Services",
            "type":"Services"
        }
    ],
    "sg:phone":"+1 727 864 9114",
    "sg:postcode":"33701",
    "sg:province":"FL",
    "sg:tags":[
        "counselor",
        "marriage",
        "family"
    ],
    "wof:name":"Roxanne M Griffin",
    "wof:placetype":"venue"
},
  "geometry": {"coordinates":[-82.63235299999999,27.769586],"type":"Point"}
}