{
  "type": "Feature",
  "properties": {
    "addr:full":"7274 SW 48th St Miami FL 33155",
    "addr:housenumber":"7274",
    "addr:postcode":"33155",
    "addr:street":"Sw 48Th St",
    "iso:country":"US",
    "sg:address":"7274 SW 48th St",
    "sg:city":"Miami",
    "sg:classifiers":[
        {
            "category":"Professional",
            "subcategory":"Accounting & Tax Preparation",
            "type":"Services"
        }
    ],
    "sg:phone":"+1 305 666 5548",
    "sg:postcode":"33155",
    "sg:province":"FL",
    "sg:tags":[
        "billing"
    ],
    "wof:name":"Medical Billing Solutions Inc",
    "wof:placetype":"venue"
},
  "geometry": {"coordinates":[-80.312487,25.725499],"type":"Point"}
}