{
  "type": "Feature",
  "properties": {
    "addr:full":"7205 Curry Ford Rd Orlando FL 32822",
    "addr:housenumber":"7205",
    "addr:postcode":"32822",
    "addr:street":"Curry Ford Rd",
    "iso:country":"US",
    "sg:address":"7205 Curry Ford Rd",
    "sg:city":"Orlando",
    "sg:classifiers":[
        {
            "category":"Banks & Credit Unions",
            "subcategory":"Bank",
            "type":"Services"
        }
    ],
    "sg:phone":"+1 407 447 4240",
    "sg:postcode":"32822",
    "sg:province":"FL",
    "sg:tags":[
        "loan",
        "real estate"
    ],
    "wof:name":"Action Realty Of Florida",
    "wof:placetype":"venue"
},
  "geometry": {"coordinates":[-81.291482,28.51666],"type":"Point"}
}