{
  "type": "Feature",
  "properties": {
    "iso:country":"US",
    "sg:address":"536 Tamiami Trl N",
    "sg:city":"Naples",
    "sg:classifiers":[
        {
            "category":"Cafe",
            "type":"Food & Drink"
        }
    ],
    "sg:menulink":"http://www.allmenus.com/fl/naples/63505-cosmos-cafe--pizzeria/menu/",
    "sg:phone":"+1 239 262 8181",
    "sg:postcode":"34102",
    "sg:province":"FL",
    "sg:tags":[
        "american",
        "pizza"
    ],
    "wof:name":"Cosmo's Cafe & Pizzeria",
    "wof:placetype":"venue"
},
  "geometry": {"coordinates":[-81.79617,26.153297],"type":"Point"}
}