{
  "type": "Feature",
  "properties": {
    "iso:country":"US",
    "sg:address":"499 NW 70th Ave Ste 100",
    "sg:city":"Plantation",
    "sg:classifiers":[
        {
            "category":"Health Services",
            "subcategory":"Doctor",
            "type":"Services"
        }
    ],
    "sg:phone":"+1 954 792 6411",
    "sg:postcode":"33317",
    "sg:province":"FL",
    "sg:tags":[
        "physician",
        "surgeon"
    ],
    "wof:name":"Cohn Leon F MD",
    "wof:placetype":"venue"
},
  "geometry": {"coordinates":[-80.24054,26.128321],"type":"Point"}
}