{
  "type": "Feature",
  "properties": {
    "addr:full":"721 E 49th St Hialeah FL 33013",
    "addr:housenumber":"721",
    "addr:postcode":"33013",
    "addr:street":"E 49Th St",
    "iso:country":"US",
    "sg:address":"721 E 49th St",
    "sg:city":"Hialeah",
    "sg:classifiers":[
        {
            "category":"Shopping",
            "subcategory":"Clothing, Apparel, & Fashions",
            "type":"Retail Goods"
        },
        {
            "category":"Shopping",
            "subcategory":"Party Supplies",
            "type":"Retail Goods"
        }
    ],
    "sg:phone":"+1 305 556 4260",
    "sg:postcode":"33013",
    "sg:province":"FL",
    "sg:tags":[
        "delivery",
        "favors",
        "decoration",
        "balloons-retail",
        "costume"
    ],
    "sg:website":"http://www.partycity.com",
    "wof:name":"Party City",
    "wof:placetype":"venue"
},
  "geometry": {"coordinates":[-80.268474,25.867344],"type":"Point"}
}