{
  "type": "Feature",
  "properties": {
    "addr:full":"120 Jumper Dr N Bushnell FL 33513",
    "addr:housenumber":"120",
    "addr:postcode":"33513",
    "addr:street":"Jumper Dr N",
    "iso:country":"US",
    "sg:address":"120 Jumper Dr N",
    "sg:city":"Bushnell",
    "sg:classifiers":[
        {
            "category":"Retail",
            "subcategory":"Auto Repair",
            "type":"Services"
        }
    ],
    "sg:phone":"+1 352 793 4118",
    "sg:postcode":"33513",
    "sg:province":"FL",
    "sg:tags":[
        "automobile",
        "lubrication"
    ],
    "wof:name":"Bushnell Quick Lube",
    "wof:placetype":"venue"
},
  "geometry": {"coordinates":[-82.111504,28.67906],"type":"Point"}
}