{
  "type": "Feature",
  "properties": {
    "iso:country":"US",
    "sg:address":"1102 Bloomingdale Ave",
    "sg:city":"Valrico",
    "sg:classifiers":[
        {
            "category":"Retail",
            "subcategory":"Animal Services",
            "type":"Services"
        },
        {
            "category":"Retail",
            "subcategory":"Veterinary Services",
            "type":"Services"
        },
        {
            "category":"Retail",
            "subcategory":"Pet Boarding",
            "type":"Services"
        }
    ],
    "sg:phone":"+1 813 654 6222",
    "sg:postcode":"33596",
    "sg:province":"FL",
    "sg:tags":[
        "emergency",
        "hospital",
        "specialty",
        "clinic",
        "veterinarian",
        "grooming",
        "kennel"
    ],
    "sg:website":"http://www.amdcvet.com",
    "wof:name":"Animal Medical Diagnositic Center",
    "wof:placetype":"venue"
},
  "geometry": {"coordinates":[-82.266614,27.89365],"type":"Point"}
}