{
  "type": "Feature",
  "properties": {
    "iso:country":"US",
    "sg:address":"324 Royal Palm Way",
    "sg:city":"Palm Beach",
    "sg:classifiers":[
        {
            "category":"Real Estate",
            "subcategory":"Real Estate Agent",
            "type":"Services"
        }
    ],
    "sg:phone":"+1 561 659 9027",
    "sg:postcode":"33480",
    "sg:province":"FL",
    "wof:name":"Michael Falk & Co",
    "wof:placetype":"venue"
},
  "geometry": {"coordinates":[-80.040476,26.705639],"type":"Point"}
}