{
  "type": "Feature",
  "properties": {
    "addr:full":"2037 Tamiami Trl Venice FL 34293",
    "addr:housenumber":"2037",
    "addr:postcode":"34293",
    "addr:street":"Tamiami Trl",
    "iso:country":"US",
    "sg:address":"2037 Tamiami Trl",
    "sg:city":"Venice",
    "sg:classifiers":[
        {
            "category":"Shopping",
            "type":"Retail Goods"
        }
    ],
    "sg:phone":"+1 941 408 8077",
    "sg:postcode":"34293",
    "sg:province":"FL",
    "sg:tags":[
        "hearing",
        "equipment",
        "supply",
        "impaired"
    ],
    "wof:name":"Beltone Hearing Aid Ctr",
    "wof:placetype":"venue"
},
  "geometry": {"coordinates":[-82.41312600000001,27.057822],"type":"Point"}
}