{
  "type": "Feature",
  "properties": {
    "iso:country":"US",
    "sg:address":"12592 Pines Blvd",
    "sg:city":"Hollywood",
    "sg:classifiers":[
        {
            "category":"Manufacturing",
            "subcategory":"Food",
            "type":"Manufacturing & Wholesale Goods"
        }
    ],
    "sg:phone":"+1 954 441 1222",
    "sg:postcode":"33027",
    "sg:province":"FL",
    "sg:tags":[
        "desert",
        "ice",
        "mfg"
    ],
    "wof:name":"Incredible Ices & Yogurt",
    "wof:placetype":"venue"
},
  "geometry": {"coordinates":[-80.31654,26.007779],"type":"Point"}
}