{
  "type": "Feature",
  "properties": {
    "iso:country":"US",
    "sg:address":"3738 SW 153rd Ct",
    "sg:city":"Miami",
    "sg:classifiers":[
        {
            "category":"Professional",
            "subcategory":"Business Services",
            "type":"Services"
        }
    ],
    "sg:phone":"+1 786 247 6367",
    "sg:postcode":"33185",
    "sg:province":"FL",
    "sg:tags":[
        "broker"
    ],
    "wof:name":"Tus Paquetes.Com Corp",
    "wof:placetype":"venue"
},
  "geometry": {"coordinates":[-80.44211199999999,25.732407],"type":"Point"}
}