{
  "type": "Feature",
  "properties": {
    "iso:country":"US",
    "sg:address":"2676 W 77th Pl",
    "sg:city":"Hialeah",
    "sg:classifiers":[
        {
            "category":"Building & Trades",
            "subcategory":"Construction",
            "type":"Services"
        }
    ],
    "sg:phone":"+1 305 558 4424",
    "sg:postcode":"33016",
    "sg:province":"FL",
    "sg:tags":[
        "elevators-repairing"
    ],
    "sg:website":"http://www.elevatorservicecorp.com",
    "wof:name":"Elevator Service Corp",
    "wof:placetype":"venue"
},
  "geometry": {"coordinates":[-80.33918300000001,25.892804],"type":"Point"}
}