{
  "type": "Feature",
  "properties": {
    "addr:full":"101 Polo Park Blvd E Davenport FL 33897",
    "addr:housenumber":"101",
    "addr:postcode":"33897",
    "addr:street":"Polo Park Blvd E",
    "iso:country":"US",
    "sg:address":"101 Polo Park Blvd E",
    "sg:city":"Davenport",
    "sg:classifiers":[
        {
            "category":"Food & Beverages",
            "subcategory":"Bakery",
            "type":"Retail Goods"
        }
    ],
    "sg:phone":"+1 863 424 8340",
    "sg:postcode":"33897",
    "sg:province":"FL",
    "sg:tags":[
        "sandwich"
    ],
    "sg:website":"subway.com/applications/storeloc...",
    "wof:name":"Subway",
    "wof:placetype":"venue"
},
  "geometry": {"coordinates":[-81.67089,28.336869],"type":"Point"}
}