{
  "type": "Feature",
  "properties": {
    "addr:full":"1405 S Waterview Dr Inverness FL 34450",
    "addr:housenumber":"1405",
    "addr:postcode":"34450",
    "addr:street":"S Waterview Dr",
    "iso:country":"US",
    "sg:address":"1405 S Waterview Dr",
    "sg:city":"Inverness",
    "sg:classifiers":[
        {
            "category":"Professional",
            "subcategory":"Computer Services",
            "type":"Services"
        }
    ],
    "sg:phone":"+1 352 860 1293",
    "sg:postcode":"34450",
    "sg:province":"FL",
    "sg:tags":[
        "datum"
    ],
    "wof:name":"Nature Coast Technical Service",
    "wof:placetype":"venue"
},
  "geometry": {"coordinates":[-82.307649,28.846074],"type":"Point"}
}