{
  "type": "Feature",
  "properties": {
    "addr:full":"5870 NE 77th Ave Bronson FL 32621",
    "addr:housenumber":"5870",
    "addr:postcode":"32621",
    "addr:street":"Ne 77Th Ave",
    "iso:country":"US",
    "sg:address":"5870 NE 77th Ave",
    "sg:city":"Bronson",
    "sg:classifiers":[
        {
            "category":"Home & Garden",
            "subcategory":"Garden Supply",
            "type":"Retail Goods"
        }
    ],
    "sg:phone":"+1 352 486 2509",
    "sg:postcode":"32621",
    "sg:province":"FL",
    "sg:tags":[
        "nurseryman"
    ],
    "wof:name":"Wekiva Road Nursery",
    "wof:placetype":"venue"
},
  "geometry": {"coordinates":[-82.64439,29.422991],"type":"Point"}
}