{
  "type": "Feature",
  "properties": {
    "iso:country":"US",
    "sg:address":"2500 Country Club Dr",
    "sg:city":"Lynn Haven",
    "sg:classifiers":[
        {
            "category":"Real Estate",
            "subcategory":"Developer",
            "type":"Services"
        }
    ],
    "sg:phone":"+1 850 265 2007",
    "sg:postcode":"32444",
    "sg:province":"FL",
    "wof:name":"Bay Magnolia Owners Assoc Inc",
    "wof:placetype":"venue"
},
  "geometry": {"coordinates":[-85.623203,30.254448],"type":"Point"}
}