{
  "type": "Feature",
  "properties": {
    "addr:full":"687 NE 79th St Miami FL 33138",
    "addr:housenumber":"687",
    "addr:postcode":"33138",
    "addr:street":"Ne 79Th St",
    "iso:country":"US",
    "sg:address":"687 NE 79th St",
    "sg:city":"Miami",
    "sg:classifiers":[
        {
            "category":"Professional",
            "type":"Services"
        }
    ],
    "sg:phone":"+1 305 758 0008",
    "sg:postcode":"33138",
    "sg:province":"FL",
    "sg:tags":[
        "establishment"
    ],
    "wof:name":"Beluga Caviar Fd Prods",
    "wof:placetype":"venue"
},
  "geometry": {"coordinates":[-80.184226,25.847919],"type":"Point"}
}