{
  "type": "Feature",
  "properties": {
    "iso:country":"US",
    "sg:address":"3820 S Tuttle Ave",
    "sg:city":"Sarasota",
    "sg:classifiers":[
        {
            "category":"Restaurant",
            "type":"Food & Drink"
        }
    ],
    "sg:menulink":"http://www.allmenus.com/fl/sarasota/210090-jersey-mikes-subs/menu/",
    "sg:phone":"+1 941 921 8111",
    "sg:postcode":"34239",
    "sg:province":"FL",
    "sg:tags":[
        "wrap",
        "american",
        "sandwich"
    ],
    "wof:name":"Jersey Mikes Subs",
    "wof:placetype":"venue"
},
  "geometry": {"coordinates":[-82.51420400000001,27.301472],"type":"Point"}
}