{
  "type": "Feature",
  "properties": {
    "iso:country":"US",
    "sg:address":"721 Front St Ste 110",
    "sg:city":"Celebration",
    "sg:classifiers":[
        {
            "category":"Bars & Pubs",
            "type":"Food & Drink"
        },
        {
            "category":"Restaurant",
            "type":"Food & Drink"
        }
    ],
    "sg:phone":"+1 407 566 2526",
    "sg:postcode":"34747",
    "sg:province":"FL",
    "sg:tags":[
        "traditional",
        "seafood",
        "american"
    ],
    "sg:website":"www.thecelebrationtowntavern.com",
    "wof:name":"Celebration Town Tavern",
    "wof:placetype":"venue"
},
  "geometry": {"coordinates":[-81.541285,28.318044],"type":"Point"}
}