{
  "type": "Feature",
  "properties": {
    "addr:full":"300 Walnut St Ormond Beach FL 32174",
    "addr:housenumber":"300",
    "addr:postcode":"32174",
    "addr:street":"Walnut St",
    "iso:country":"US",
    "sg:address":"300 Walnut St",
    "sg:city":"Ormond Beach",
    "sg:classifiers":[
        {
            "category":"Building & Trades",
            "subcategory":"Pest Control",
            "type":"Services"
        }
    ],
    "sg:phone":"+1 386 673 2552",
    "sg:postcode":"32174",
    "sg:province":"FL",
    "wof:name":"Ormond Pest Control Inc",
    "wof:placetype":"venue"
},
  "geometry": {"coordinates":[-81.06671,29.289695],"type":"Point"}
}