{
  "type": "Feature",
  "properties": {
    "iso:country":"US",
    "sg:address":"326 Bahia Vista Dr",
    "sg:city":"Indian Rocks Beach",
    "sg:classifiers":[
        {
            "category":"Professional",
            "type":"Services"
        }
    ],
    "sg:phone":"+1 727 596 9771",
    "sg:postcode":"33785",
    "sg:province":"FL",
    "wof:name":"Airplay Inc",
    "wof:placetype":"venue"
},
  "geometry": {"coordinates":[-82.844048,27.888748],"type":"Point"}
}