{
  "type": "Feature",
  "properties": {
    "iso:country":"US",
    "sg:address":"8540 N Dale Mabry Hwy",
    "sg:city":"Tampa",
    "sg:classifiers":[
        {
            "category":"Autos & Motor Vehicles",
            "subcategory":"Automobile Sales",
            "type":"Retail Goods"
        }
    ],
    "sg:phone":"+1 813 930 2828",
    "sg:postcode":"33614",
    "sg:province":"FL",
    "sg:tags":[
        "car",
        "used"
    ],
    "wof:name":"Reliable Motor Broker",
    "wof:placetype":"venue"
},
  "geometry": {"coordinates":[-82.505039,28.02773],"type":"Point"}
}