{
  "type": "Feature",
  "properties": {
    "addr:full":"333 Tamiami Trl Venice FL 34285",
    "addr:housenumber":"333",
    "addr:postcode":"34285",
    "addr:street":"Tamiami Trl",
    "iso:country":"US",
    "sg:address":"333 Tamiami Trl",
    "sg:city":"Venice",
    "sg:classifiers":[
        {
            "category":"Health Services",
            "subcategory":"Medical Lab",
            "type":"Services"
        }
    ],
    "sg:phone":"+1 941 484 4624",
    "sg:postcode":"34285",
    "sg:province":"FL",
    "sg:tags":[
        "laboratory"
    ],
    "wof:name":"Quest Diagnostics Inc",
    "wof:placetype":"venue"
},
  "geometry": {"coordinates":[-82.444248,27.094787],"type":"Point"}
}