{
  "type": "Feature",
  "properties": {
    "addr:full":"335 Beard St Tallahassee FL 32303",
    "addr:housenumber":"335",
    "addr:postcode":"32303",
    "addr:street":"Beard St",
    "iso:country":"US",
    "sg:address":"335 Beard St",
    "sg:city":"Tallahassee",
    "sg:classifiers":[
        {
            "category":"Organizations",
            "subcategory":"Membership Organization",
            "type":"Services"
        }
    ],
    "sg:phone":"+1 850 561 1234",
    "sg:postcode":"32303",
    "sg:province":"FL",
    "wof:name":"Hyatt Hotels Of Florida",
    "wof:placetype":"venue"
},
  "geometry": {"coordinates":[-84.27735699999999,30.455342],"type":"Point"}
}