{
  "type": "Feature",
  "properties": {
    "iso:country":"US",
    "sg:address":"10941 N Military Trl",
    "sg:city":"Palm Beach Gardens",
    "sg:classifiers":[
        {
            "category":"Shopping",
            "subcategory":"Hobbies, Toys, & Games",
            "type":"Retail Goods"
        }
    ],
    "sg:phone":"+1 561 799 2869",
    "sg:postcode":"33410",
    "sg:province":"FL",
    "sg:tags":[
        "specialty"
    ],
    "wof:name":"Learning Express",
    "wof:placetype":"venue"
},
  "geometry": {"coordinates":[-80.105312,26.836711],"type":"Point"}
}