{
  "type": "Feature",
  "properties": {
    "iso:country":"US",
    "sg:address":"2615 SW 147th Ave",
    "sg:city":"Miami",
    "sg:classifiers":[
        {
            "category":"Restaurant",
            "type":"Food & Drink"
        }
    ],
    "sg:menulink":"http://www.allmenus.com/fl/kendale-lakes-lindgren-acres/122652-quiznos-sub/menu/",
    "sg:phone":"+1 305 225 9885",
    "sg:postcode":"33185",
    "sg:province":"FL",
    "sg:tags":[
        "wrap",
        "american",
        "sandwich"
    ],
    "wof:name":"Quiznos Sub",
    "wof:placetype":"venue"
},
  "geometry": {"coordinates":[-80.432147,25.74287],"type":"Point"}
}