{
  "type": "Feature",
  "properties": {
    "iso:country":"US",
    "sg:address":"8010 N Atlantic Ave",
    "sg:city":"Cape Canaveral",
    "sg:classifiers":[
        {
            "category":"Restaurant",
            "type":"Food & Drink"
        }
    ],
    "sg:phone":"+1 321 783 9519",
    "sg:postcode":"32920",
    "sg:province":"FL",
    "sg:tags":[
        "mexican"
    ],
    "wof:name":"Vargas Cafe",
    "wof:placetype":"venue"
},
  "geometry": {"coordinates":[-80.605384,28.388936],"type":"Point"}
}