{
  "type": "Feature",
  "properties": {
    "iso:country":"US",
    "sg:address":"565 E Tennessee St",
    "sg:city":"Tallahassee",
    "sg:classifiers":[
        {
            "category":"Retail",
            "subcategory":"Portrait Studio",
            "type":"Services"
        }
    ],
    "sg:phone":"+1 850 222 6691",
    "sg:postcode":"32308",
    "sg:province":"FL",
    "sg:tags":[
        "photo"
    ],
    "wof:name":"Available Light Photography",
    "wof:placetype":"venue"
},
  "geometry": {"coordinates":[-84.27392500000001,30.444633],"type":"Point"}
}