{
  "type": "Feature",
  "properties": {
    "addr:full":"7411 114th Ave N Largo FL 33773",
    "addr:housenumber":"7411",
    "addr:postcode":"33773",
    "addr:street":"114Th Ave N",
    "iso:country":"US",
    "sg:address":"7411 114th Ave N",
    "sg:city":"Largo",
    "sg:classifiers":[
        {
            "category":"Wholesale",
            "subcategory":"Medical Equipment & Supplies",
            "type":"Manufacturing & Wholesale Goods"
        }
    ],
    "sg:phone":"+1 727 536 2000",
    "sg:postcode":"33773",
    "sg:province":"FL",
    "sg:tags":[
        "physician",
        "surgeon"
    ],
    "wof:name":"Quality Medical Group South",
    "wof:placetype":"venue"
},
  "geometry": {"coordinates":[-82.742841,27.875948],"type":"Point"}
}