{
  "type": "Feature",
  "properties": {
    "addr:full":"2169 Greenview Cove Dr Wellington FL 33414",
    "addr:housenumber":"2169",
    "addr:postcode":"33414",
    "addr:street":"Greenview Cove Dr",
    "iso:country":"US",
    "sg:address":"2169 Greenview Cove Dr",
    "sg:city":"Wellington",
    "sg:classifiers":[
        {
            "category":"Professional",
            "subcategory":"Management & Consulting",
            "type":"Services"
        }
    ],
    "sg:phone":"+1 561 346 6392",
    "sg:postcode":"33414",
    "sg:province":"FL",
    "sg:tags":[
        "personnel",
        "consultant"
    ],
    "wof:name":"Staff Connections",
    "wof:placetype":"venue"
},
  "geometry": {"coordinates":[-80.255977,26.650298],"type":"Point"}
}