{
  "type": "Feature",
  "properties": {
    "iso:country":"US",
    "sg:address":"485 NE 165th Ter",
    "sg:city":"Silver Springs",
    "sg:classifiers":[
        {
            "category":"Building & Trades",
            "subcategory":"Construction",
            "type":"Services"
        }
    ],
    "sg:phone":"+1 352 625 7200",
    "sg:postcode":"34488",
    "sg:province":"FL",
    "sg:tags":[
        "screen",
        "enclosure"
    ],
    "wof:name":"A Total Rescreen Svc",
    "wof:placetype":"venue"
},
  "geometry": {"coordinates":[-81.878461,29.192336],"type":"Point"}
}