{
  "type": "Feature",
  "properties": {
    "iso:country":"US",
    "sg:address":"1674 Charon Rd",
    "sg:city":"Jacksonville",
    "sg:classifiers":[
        {
            "category":"Manufacturing",
            "subcategory":"Food",
            "type":"Manufacturing & Wholesale Goods"
        }
    ],
    "sg:phone":"+1 904 388 4974",
    "sg:postcode":"32205",
    "sg:province":"FL",
    "sg:tags":[
        "mfg"
    ],
    "wof:name":"Harelle Inc",
    "wof:placetype":"venue"
},
  "geometry": {"coordinates":[-81.71657399999999,30.293588],"type":"Point"}
}