{
  "type": "Feature",
  "properties": {
    "addr:full":"12000 N Dale Mabry Hwy Tampa FL 33618",
    "addr:housenumber":"12000",
    "addr:postcode":"33618",
    "addr:street":"N Dale Mabry Hwy",
    "iso:country":"US",
    "sg:address":"12000 N Dale Mabry Hwy",
    "sg:city":"Tampa",
    "sg:classifiers":[
        {
            "category":"Banks & Credit Unions",
            "subcategory":"Investment Brokerage",
            "type":"Services"
        }
    ],
    "sg:phone":"+1 813 960 2186",
    "sg:postcode":"33618",
    "sg:province":"FL",
    "sg:tags":[
        "security"
    ],
    "wof:name":"Edward Jones 09706",
    "wof:placetype":"venue"
},
  "geometry": {"coordinates":[-82.503766,28.057649],"type":"Point"}
}