{
  "type": "Feature",
  "properties": {
    "iso:country":"US",
    "sg:address":"1418 Crest Dr",
    "sg:city":"Lake Worth",
    "sg:classifiers":[
        {
            "category":"Building & Trades",
            "subcategory":"Construction",
            "type":"Services"
        }
    ],
    "sg:phone":"+1 561 547 0480",
    "sg:postcode":"33461",
    "sg:province":"FL",
    "sg:tags":[
        "hanging",
        "contractor"
    ],
    "wof:name":"Wall To Wall Home Services",
    "wof:placetype":"venue"
},
  "geometry": {"coordinates":[-80.07591499999999,26.598731],"type":"Point"}
}