{
  "type": "Feature",
  "properties": {
    "iso:country":"US",
    "sg:address":"10756 NE 4th Ave",
    "sg:city":"Miami",
    "sg:classifiers":[
        {
            "category":"Building & Trades",
            "subcategory":"Pest Control",
            "type":"Services"
        }
    ],
    "sg:phone":"+1 305 754 4460",
    "sg:postcode":"33161",
    "sg:province":"FL",
    "sg:tags":[
        "mothproofing"
    ],
    "wof:name":"Natural Resources Pest Control Turf & Landscaping Services Inc",
    "wof:placetype":"venue"
},
  "geometry": {"coordinates":[-80.18982800000001,25.874394],"type":"Point"}
}