{
  "type": "Feature",
  "properties": {
    "iso:country":"US",
    "sg:address":"1244 SW 14th St",
    "sg:city":"Miami",
    "sg:classifiers":[
        {
            "category":"Arts & Performance",
            "subcategory":"Art Gallery",
            "type":"Entertainment"
        }
    ],
    "sg:phone":"+1 786 229 6305",
    "sg:postcode":"33145",
    "sg:province":"FL",
    "sg:tags":[
        "fine",
        "artist"
    ],
    "wof:name":"Hypno-Artists",
    "wof:placetype":"venue"
},
  "geometry": {"coordinates":[-80.215132,25.760036],"type":"Point"}
}