{
  "type": "Feature",
  "properties": {
    "addr:full":"1844 W Fairbanks Ave Winter Park FL 32789",
    "addr:housenumber":"1844",
    "addr:postcode":"32789",
    "addr:street":"W Fairbanks Ave",
    "iso:country":"US",
    "sg:address":"1844 W Fairbanks Ave",
    "sg:city":"Winter Park",
    "sg:classifiers":[
        {
            "category":"Home & Garden",
            "subcategory":"Carpets & Floor Coverings",
            "type":"Retail Goods"
        }
    ],
    "sg:phone":"+1 407 645 2090",
    "sg:postcode":"32789",
    "sg:province":"FL",
    "sg:tags":[
        "mattress"
    ],
    "wof:name":"Relax In Comfort Corporate Offices",
    "wof:placetype":"venue"
},
  "geometry": {"coordinates":[-81.37599899999999,28.592199],"type":"Point"}
}