{
  "type": "Feature",
  "properties": {
    "iso:country":"US",
    "sg:address":"6445 S Chickasaw Trl",
    "sg:city":"Orlando",
    "sg:classifiers":[
        {
            "category":"Professional",
            "subcategory":"Business Services",
            "type":"Services"
        }
    ],
    "sg:phone":"+1 407 282 4064",
    "sg:postcode":"32829",
    "sg:province":"FL",
    "sg:tags":[
        "development",
        "plan"
    ],
    "wof:name":"Show Production Resources",
    "wof:placetype":"venue"
},
  "geometry": {"coordinates":[-81.26851499999999,28.469592],"type":"Point"}
}