{
  "type": "Feature",
  "properties": {
    "iso:country":"US",
    "sg:address":"6332 Fern Ln",
    "sg:city":"Lakeland",
    "sg:classifiers":[
        {
            "category":"Professional",
            "subcategory":"Accounting & Tax Preparation",
            "type":"Services"
        }
    ],
    "sg:phone":"+1 863 648 5921",
    "sg:postcode":"33813",
    "sg:province":"FL",
    "sg:tags":[
        "computer"
    ],
    "wof:name":"All Business Solutions Inc",
    "wof:placetype":"venue"
},
  "geometry": {"coordinates":[-81.958055,27.948683],"type":"Point"}
}