{
  "type": "Feature",
  "properties": {
    "iso:country":"US",
    "sg:address":"702 S Albany Ave",
    "sg:city":"Tampa",
    "sg:classifiers":[
        {
            "category":"Recreation",
            "type":"Entertainment"
        }
    ],
    "sg:phone":"+1 813 259 1687",
    "sg:postcode":"33606",
    "sg:province":"FL",
    "wof:name":"City Tampa Parks & Recreation",
    "wof:placetype":"venue"
},
  "geometry": {"coordinates":[-82.480897,27.936024],"type":"Point"}
}