{
  "type": "Feature",
  "properties": {
    "addr:full":"8018 NW 128th Ln Parkland FL 33076",
    "addr:housenumber":"8018",
    "addr:postcode":"33076",
    "addr:street":"Nw 128Th Ln",
    "iso:country":"US",
    "sg:address":"8018 NW 128th Ln",
    "sg:city":"Parkland",
    "sg:classifiers":[
        {
            "category":"Manufacturing",
            "subcategory":"Buildings",
            "type":"Manufacturing & Wholesale Goods"
        },
        {
            "category":"Building & Trades",
            "subcategory":"Construction",
            "type":"Services"
        }
    ],
    "sg:phone":"+1 954 340 4310",
    "sg:postcode":"33076",
    "sg:province":"FL",
    "sg:tags":[
        "home",
        "builder",
        "contractor"
    ],
    "wof:name":"Maggie Valley Home Construction",
    "wof:placetype":"venue"
},
  "geometry": {"coordinates":[-80.296432,26.330017],"type":"Point"}
}