{
  "type": "Feature",
  "properties": {
    "iso:country":"US",
    "sg:address":"1132 Kane Concourse",
    "sg:city":"Bay Harbor Islands",
    "sg:classifiers":[
        {
            "category":"Real Estate",
            "subcategory":"Architect",
            "type":"Services"
        }
    ],
    "sg:phone":"+1 305 866 4700",
    "sg:postcode":"33154",
    "sg:province":"FL",
    "wof:name":"Gambach Architects",
    "wof:placetype":"venue"
},
  "geometry": {"coordinates":[-80.131883,25.886512],"type":"Point"}
}