{
  "type": "Feature",
  "properties": {
    "addr:full":"5441 Baker Dairy Rd Haines City FL 33844",
    "addr:housenumber":"5441",
    "addr:postcode":"33844",
    "addr:street":"Baker Dairy Rd",
    "iso:country":"US",
    "sg:address":"5441 Baker Dairy Rd",
    "sg:city":"Haines City",
    "sg:classifiers":[
        {
            "category":"Building & Trades",
            "subcategory":"Construction",
            "type":"Services"
        }
    ],
    "sg:phone":"+1 863 557 0602",
    "sg:postcode":"33844",
    "sg:province":"FL",
    "sg:tags":[
        "dry wall",
        "contractor"
    ],
    "wof:name":"Pedro Leon Drywall",
    "wof:placetype":"venue"
},
  "geometry": {"coordinates":[-81.574246,28.121323],"type":"Point"}
}