{
  "type": "Feature",
  "properties": {
    "addr:full":"7121 Grand National Dr Orlando FL 32819",
    "addr:housenumber":"7121",
    "addr:postcode":"32819",
    "addr:street":"Grand National Dr",
    "iso:country":"US",
    "sg:address":"7121 Grand National Dr",
    "sg:city":"Orlando",
    "sg:classifiers":[
        {
            "category":"Manufacturing",
            "subcategory":"Signs",
            "type":"Manufacturing & Wholesale Goods"
        }
    ],
    "sg:phone":"+1 407 264 9898",
    "sg:postcode":"32819",
    "sg:province":"FL",
    "wof:name":"Express Signs & Graphics",
    "wof:placetype":"venue"
},
  "geometry": {"coordinates":[-81.456153,28.459779],"type":"Point"}
}