{
  "type": "Feature",
  "properties": {
    "iso:country":"US",
    "sg:address":"5791 Staley Rd",
    "sg:city":"Fort Myers",
    "sg:classifiers":[
        {
            "category":"Farming",
            "subcategory":"Livestock Farm",
            "type":"Manufacturing & Wholesale Goods"
        }
    ],
    "sg:phone":"+1 239 694 7440",
    "sg:postcode":"33905",
    "sg:province":"FL",
    "sg:tags":[
        "beef",
        "feedlot",
        "cattle"
    ],
    "wof:name":"Vic Prevatt Construction Inc",
    "wof:placetype":"venue"
},
  "geometry": {"coordinates":[-81.775722,26.657903],"type":"Point"}
}