{
  "type": "Feature",
  "properties": {
    "addr:full":"85 NW 47th St Miami FL 33127",
    "addr:housenumber":"85",
    "addr:postcode":"33127",
    "addr:street":"Nw 47Th St",
    "iso:country":"US",
    "sg:address":"85 NW 47th St",
    "sg:city":"Miami",
    "sg:classifiers":[
        {
            "category":"Restaurant",
            "type":"Food & Drink"
        }
    ],
    "sg:phone":"+1 305 582 2611",
    "sg:postcode":"33127",
    "sg:province":"FL",
    "sg:tags":[
        "sushi",
        "bar",
        "japanese"
    ],
    "wof:name":"American Sushi",
    "wof:placetype":"venue"
},
  "geometry": {"coordinates":[-80.197524,25.818487],"type":"Point"}
}