{
  "type": "Feature",
  "properties": {
    "iso:country":"US",
    "sg:address":"13107 Ambrose Pl",
    "sg:city":"Riverview",
    "sg:classifiers":[
        {
            "category":"Wholesale",
            "subcategory":"Computers",
            "type":"Manufacturing & Wholesale Goods"
        },
        {
            "category":"Shopping",
            "subcategory":"Computers & Home Electronics",
            "type":"Retail Goods"
        }
    ],
    "sg:phone":"+1 813 677 4495",
    "sg:postcode":"33579",
    "sg:province":"FL",
    "sg:tags":[
        "communications",
        "datum"
    ],
    "sg:website":"www.cfsalesinc.com",
    "wof:name":"C F Sales",
    "wof:placetype":"venue"
},
  "geometry": {"coordinates":[-81.451905,30.329379],"type":"Point"}
}