{
  "type": "Feature",
  "properties": {
    "addr:full":"255 Jo-Katherine Ln Santa Rosa Beach FL 32459",
    "addr:housenumber":"255",
    "addr:postcode":"32459",
    "addr:street":"Jo-Katherine Ln",
    "iso:country":"US",
    "sg:address":"255 Jo-Katherine Ln",
    "sg:city":"Santa Rosa Beach",
    "sg:classifiers":[
        {
            "category":"Building & Trades",
            "subcategory":"Construction",
            "type":"Services"
        }
    ],
    "sg:phone":"+1 850 267 2778",
    "sg:postcode":"32459",
    "sg:province":"FL",
    "sg:tags":[
        "contractor"
    ],
    "wof:name":"Mahaffey Vinyl Siding Inc",
    "wof:placetype":"venue"
},
  "geometry": {"coordinates":[-86.304982,30.39248],"type":"Point"}
}