{
  "type": "Feature",
  "properties": {
    "iso:country":"US",
    "sg:address":"4702 Causeway Blvd",
    "sg:city":"Tampa",
    "sg:classifiers":[
        {
            "category":"Freight",
            "type":"Transportation"
        }
    ],
    "sg:phone":"+1 813 241 6329",
    "sg:postcode":"33619",
    "sg:province":"FL",
    "sg:tags":[
        "operator",
        "hauling",
        "trucking"
    ],
    "wof:name":"I P Enterprises",
    "wof:placetype":"venue"
},
  "geometry": {"coordinates":[-82.403891,27.923118],"type":"Point"}
}