{
  "type": "Feature",
  "properties": {
    "iso:country":"US",
    "sg:address":"1136 NE Pine Island Rd",
    "sg:city":"Cape Coral",
    "sg:classifiers":[
        {
            "category":"Wholesale",
            "subcategory":"Machinery & Supplies",
            "type":"Manufacturing & Wholesale Goods"
        }
    ],
    "sg:phone":"+1 239 573 1995",
    "sg:postcode":"33909",
    "sg:province":"FL",
    "sg:tags":[
        "equipment",
        "transportation"
    ],
    "wof:name":"Avionics Sales Corp",
    "wof:placetype":"venue"
},
  "geometry": {"coordinates":[-81.947484,26.664314],"type":"Point"}
}