{
  "type": "Feature",
  "properties": {
    "addr:full":"955 W Lancaster Rd Orlando FL 32809",
    "addr:housenumber":"955",
    "addr:postcode":"32809",
    "addr:street":"W Lancaster Rd",
    "iso:country":"US",
    "sg:address":"955 W Lancaster Rd",
    "sg:city":"Orlando",
    "sg:classifiers":[
        {
            "category":"Shopping",
            "type":"Retail Goods"
        }
    ],
    "sg:phone":"+1 407 826 9221",
    "sg:postcode":"32809",
    "sg:province":"FL",
    "sg:tags":[
        "religious"
    ],
    "wof:name":"Botanica LA Roye",
    "wof:placetype":"venue"
},
  "geometry": {"coordinates":[-81.39647600000001,28.465326],"type":"Point"}
}