{
  "type": "Feature",
  "properties": {
    "iso:country":"US",
    "sg:address":"13510 Tamiami Trl N",
    "sg:city":"Naples",
    "sg:classifiers":[
        {
            "category":"Professional",
            "subcategory":"Printing & Photocopies",
            "type":"Services"
        }
    ],
    "sg:phone":"+1 239 594 8844",
    "sg:postcode":"34110",
    "sg:province":"FL",
    "sg:tags":[
        "photocopying",
        "blueprinting"
    ],
    "wof:name":"Dittto",
    "wof:placetype":"venue"
},
  "geometry": {"coordinates":[-81.80195500000001,26.292985],"type":"Point"}
}