{
  "type": "Feature",
  "properties": {
    "addr:full":"9398 Oakhurst Rd Largo FL 33776",
    "addr:housenumber":"9398",
    "addr:postcode":"33776",
    "addr:street":"Oakhurst Rd",
    "iso:country":"US",
    "sg:address":"9398 Oakhurst Rd",
    "sg:city":"Largo",
    "sg:classifiers":[
        {
            "category":"Banks & Credit Unions",
            "subcategory":"Bank",
            "type":"Services"
        }
    ],
    "sg:phone":"+1 727 443 2000",
    "sg:postcode":"33776",
    "sg:province":"FL",
    "wof:name":"AM South Bank",
    "wof:placetype":"venue"
},
  "geometry": {"coordinates":[-82.831666,27.857447],"type":"Point"}
}