{
  "type": "Feature",
  "properties": {
    "addr:full":"18101 Longwater Run Dr Tampa FL 33647",
    "addr:housenumber":"18101",
    "addr:postcode":"33647",
    "addr:street":"Longwater Run Dr",
    "iso:country":"US",
    "sg:address":"18101 Longwater Run Dr",
    "sg:city":"Tampa",
    "sg:classifiers":[
        {
            "category":"Professional",
            "subcategory":"Business Services",
            "type":"Services"
        },
        {
            "category":"Recreation",
            "type":"Entertainment"
        }
    ],
    "sg:phone":"+1 813 973 1000",
    "sg:postcode":"33647",
    "sg:province":"FL",
    "sg:tags":[
        "course",
        "eating",
        "golf"
    ],
    "wof:name":"Hunter's Green Country Club",
    "wof:placetype":"venue"
},
  "geometry": {"coordinates":[-82.345771,28.137455],"type":"Point"}
}