{
  "type": "Feature",
  "properties": {
    "iso:country":"US",
    "sg:address":"3898 NW 124th Ave",
    "sg:city":"Coral Springs",
    "sg:classifiers":[
        {
            "category":"Wholesale",
            "subcategory":"Groceries",
            "type":"Manufacturing & Wholesale Goods"
        },
        {
            "category":"Wholesale",
            "subcategory":"Meat",
            "type":"Manufacturing & Wholesale Goods"
        }
    ],
    "sg:phone":"+1 954 575 9022",
    "sg:postcode":"33065",
    "sg:province":"FL",
    "sg:tags":[
        "food",
        "deli",
        "product",
        "distributes"
    ],
    "wof:name":"Showcase Deli Provisions",
    "wof:placetype":"venue"
},
  "geometry": {"coordinates":[-80.29120899999999,26.274379],"type":"Point"}
}