{
  "type": "Feature",
  "properties": {
    "iso:country":"US",
    "sg:address":"19693 Carolina Cir",
    "sg:city":"Boca Raton",
    "sg:classifiers":[
        {
            "category":"Building & Trades",
            "subcategory":"Construction",
            "type":"Services"
        }
    ],
    "sg:phone":"+1 954 931 7532",
    "sg:postcode":"33434",
    "sg:province":"FL",
    "sg:tags":[
        "hanging",
        "contractor"
    ],
    "wof:name":"Marco A Braga",
    "wof:placetype":"venue"
},
  "geometry": {"coordinates":[-80.200728,26.383697],"type":"Point"}
}