{
  "type": "Feature",
  "properties": {
    "iso:country":"US",
    "sg:address":"3205 Laurie Ave",
    "sg:city":"Panama City",
    "sg:classifiers":[
        {
            "category":"Building & Trades",
            "subcategory":"Construction",
            "type":"Services"
        }
    ],
    "sg:phone":"+1 850 233 7438",
    "sg:postcode":"32408",
    "sg:province":"FL",
    "sg:tags":[
        "gen"
    ],
    "wof:name":"Andrews Landclearing & Const",
    "wof:placetype":"venue"
},
  "geometry": {"coordinates":[-85.782269,30.169552],"type":"Point"}
}