{
  "type": "Feature",
  "properties": {
    "iso:country":"US",
    "sg:address":"7095 Pond Cypress Ct",
    "sg:city":"Naples",
    "sg:classifiers":[
        {
            "category":"Personal",
            "type":"Services"
        }
    ],
    "sg:phone":"+1 239 434 2557",
    "sg:postcode":"34109",
    "sg:province":"FL",
    "wof:name":"Place 2 Place",
    "wof:placetype":"venue"
},
  "geometry": {"coordinates":[-81.78899699999999,26.231593],"type":"Point"}
}