{
  "type": "Feature",
  "properties": {
    "addr:full":"414 W 6th St Lakeland FL 33805",
    "addr:housenumber":"414",
    "addr:postcode":"33805",
    "addr:street":"W 6Th St",
    "iso:country":"US",
    "sg:address":"414 W 6th St",
    "sg:city":"Lakeland",
    "sg:classifiers":[
        {
            "category":"Social Services",
            "subcategory":"Child Care",
            "type":"Services"
        }
    ],
    "sg:phone":"+1 863 688 0823",
    "sg:postcode":"33805",
    "sg:province":"FL",
    "wof:name":"Little Citizens Child Dev Ctr",
    "wof:placetype":"venue"
},
  "geometry": {"coordinates":[-81.960576,28.059399],"type":"Point"}
}