{
  "type": "Feature",
  "properties": {
    "addr:full":"1438 E Oak St Miami FL 33144",
    "addr:housenumber":"1438",
    "addr:postcode":"33144",
    "addr:street":"E Oak St",
    "iso:country":"US",
    "sg:address":"1438 E Oak St",
    "sg:city":"Miami",
    "sg:classifiers":[
        {
            "category":"Building & Trades",
            "subcategory":"Locksmith",
            "type":"Services"
        }
    ],
    "sg:phone":"+1 866 689 9172",
    "sg:postcode":"33144",
    "sg:province":"FL",
    "sg:tags":[
        "key"
    ],
    "wof:name":"Emergency 24 Hour 7 Day Locksmith",
    "wof:placetype":"venue"
},
  "geometry": {"coordinates":[-80.239526,25.730042],"type":"Point"}
}