{
  "type": "Feature",
  "properties": {
    "iso:country":"US",
    "sg:address":"1435 Oviedo Marketplace Blvd",
    "sg:city":"Oviedo",
    "sg:classifiers":[
        {
            "category":"Shopping",
            "subcategory":"Computers & Home Electronics",
            "type":"Retail Goods"
        }
    ],
    "sg:phone":"+1 407 977 4424",
    "sg:postcode":"32765",
    "sg:province":"FL",
    "sg:tags":[
        "equipment",
        "electronic",
        "supply"
    ],
    "wof:name":"Radio Shack",
    "wof:placetype":"venue"
},
  "geometry": {"coordinates":[-81.23363999999999,28.661078],"type":"Point"}
}