{
  "type": "Feature",
  "properties": {
    "iso:country":"US",
    "sg:address":"32 Bay Esplanade",
    "sg:city":"Clearwater",
    "sg:classifiers":[
        {
            "category":"Food & Beverages",
            "subcategory":"Groceries & Convenience Stores",
            "type":"Retail Goods"
        }
    ],
    "sg:phone":"+1 727 441 9674",
    "sg:postcode":"33767",
    "sg:province":"FL",
    "wof:name":"Hess Express",
    "wof:placetype":"venue"
},
  "geometry": {"coordinates":[-82.827422,27.98496],"type":"Point"}
}