{
  "type": "Feature",
  "properties": {
    "addr:full":"30387 Quail Roost Trl Big Pine Key FL 33043",
    "addr:housenumber":"30387",
    "addr:postcode":"33043",
    "addr:street":"Quail Roost Trl",
    "iso:country":"US",
    "sg:address":"30387 Quail Roost Trl",
    "sg:city":"Big Pine Key",
    "sg:classifiers":[
        {
            "category":"Shopping",
            "subcategory":"Florist",
            "type":"Retail Goods"
        }
    ],
    "sg:phone":"+1 305 745 9944",
    "sg:postcode":"33043",
    "sg:province":"FL",
    "wof:name":"Summer Island Flowers",
    "wof:placetype":"venue"
},
  "geometry": {"coordinates":[-81.35653000000001,24.66855],"type":"Point"}
}