{
  "type": "Feature",
  "properties": {
    "iso:country":"US",
    "sg:address":"155 S Miami Ave",
    "sg:city":"Miami",
    "sg:classifiers":[
        {
            "category":"Organizations",
            "subcategory":"Non-profit Organization",
            "type":"Services"
        }
    ],
    "sg:phone":"+1 305 358 9047",
    "sg:postcode":"33130",
    "sg:province":"FL",
    "sg:tags":[
        "deaf"
    ],
    "wof:name":"CaptioNation",
    "wof:placetype":"venue"
},
  "geometry": {"coordinates":[-80.19354,25.773136],"type":"Point"}
}