{
  "type": "Feature",
  "properties": {
    "iso:country":"US",
    "sg:address":"1568 W 37th St",
    "sg:city":"Hialeah",
    "sg:classifiers":[
        {
            "category":"Shopping",
            "type":"Retail Goods"
        }
    ],
    "sg:phone":"+1 305 824 8568",
    "sg:postcode":"33012",
    "sg:province":"FL",
    "sg:tags":[
        "pet",
        "shop",
        "store",
        "merchandise"
    ],
    "wof:name":"Janet Pet Shop & Supplies",
    "wof:placetype":"venue"
},
  "geometry": {"coordinates":[-80.314003,25.8554],"type":"Point"}
}