{
  "type": "Feature",
  "properties": {
    "addr:full":"12179 S Orange Blossom Trl Orlando FL 32837",
    "addr:housenumber":"12179",
    "addr:postcode":"32837",
    "addr:street":"S Orange Blossom Trl",
    "iso:country":"US",
    "sg:address":"12179 S Orange Blossom Trl",
    "sg:city":"Orlando",
    "sg:classifiers":[
        {
            "category":"Food & Beverages",
            "subcategory":"Specialty",
            "type":"Retail Goods"
        },
        {
            "category":"Professional",
            "subcategory":"Management & Consulting",
            "type":"Services"
        }
    ],
    "sg:phone":"+1 407 851 9936",
    "sg:postcode":"32837",
    "sg:province":"FL",
    "sg:tags":[
        "bulk",
        "water",
        "company",
        "direct",
        "sales"
    ],
    "sg:website":"www.watertogo.com",
    "wof:name":"Purified Water To Go Store 16",
    "wof:placetype":"venue"
},
  "geometry": {"coordinates":[-81.40449,28.388483],"type":"Point"}
}