{
  "type": "Feature",
  "properties": {
    "iso:country":"US",
    "sg:address":"2195 Tamiami Trl",
    "sg:city":"Port Charlotte",
    "sg:classifiers":[
        {
            "category":"Real Estate",
            "subcategory":"Real Estate Agent",
            "type":"Services"
        }
    ],
    "sg:phone":"+1 941 743 4200",
    "sg:postcode":"33948",
    "sg:province":"FL",
    "wof:name":"Barnes & Phillips Real Estate",
    "wof:placetype":"venue"
},
  "geometry": {"coordinates":[-82.124172,27.000186],"type":"Point"}
}