{
  "type": "Feature",
  "properties": {
    "iso:country":"US",
    "sg:address":"213 N Magnolia Ave",
    "sg:city":"Orlando",
    "sg:classifiers":[
        {
            "category":"Shopping",
            "type":"Retail Goods"
        }
    ],
    "sg:phone":"+1 407 423 4088",
    "sg:postcode":"32801",
    "sg:province":"FL",
    "sg:tags":[
        "picture",
        "frame"
    ],
    "wof:name":"Art Lando",
    "wof:placetype":"venue"
},
  "geometry": {"coordinates":[-81.377438,28.545546],"type":"Point"}
}