{
  "type": "Feature",
  "properties": {
    "addr:full":"3301 W Boynton Beach Blvd Boynton Beach FL 33436",
    "addr:housenumber":"3301",
    "addr:postcode":"33436",
    "addr:street":"W Boynton Beach Blvd",
    "iso:country":"US",
    "sg:address":"3301 W Boynton Beach Blvd",
    "sg:city":"Boynton Beach",
    "sg:classifiers":[
        {
            "category":"Building & Trades",
            "subcategory":"Cleaning & Sanitation",
            "type":"Services"
        }
    ],
    "sg:phone":"+1 561 740 1262",
    "sg:postcode":"33436",
    "sg:province":"FL",
    "sg:tags":[
        "maintenance"
    ],
    "wof:name":"Lamps and Shades By Mr D",
    "wof:placetype":"venue"
},
  "geometry": {"coordinates":[-80.095857,26.527581],"type":"Point"}
}