{
  "type": "Feature",
  "properties": {
    "addr:full":"303 US Hwy 27 Clermont FL 34711",
    "addr:housenumber":"303",
    "addr:postcode":"34711",
    "addr:street":"Us Hwy 27",
    "iso:country":"US",
    "sg:address":"303 US Hwy 27",
    "sg:city":"Clermont",
    "sg:classifiers":[
        {
            "category":"Home & Garden",
            "subcategory":"Carpets & Floor Coverings",
            "type":"Retail Goods"
        }
    ],
    "sg:phone":"+1 352 242 0000",
    "sg:postcode":"34711",
    "sg:province":"FL",
    "wof:name":"Warehouse Carpeting South Lake",
    "wof:placetype":"venue"
},
  "geometry": {"coordinates":[-81.678697,28.359363],"type":"Point"}
}