{
  "type": "Feature",
  "properties": {
    "addr:full":"7633 Helen St Melbourne FL 32904",
    "addr:housenumber":"7633",
    "addr:postcode":"32904",
    "addr:street":"Helen St",
    "iso:country":"US",
    "sg:address":"7633 Helen St",
    "sg:city":"Melbourne",
    "sg:classifiers":[
        {
            "category":"Freight",
            "type":"Transportation"
        }
    ],
    "sg:phone":"+1 321 723 6102",
    "sg:postcode":"32904",
    "sg:province":"FL",
    "sg:tags":[
        "courier"
    ],
    "wof:name":"Sansco Inc",
    "wof:placetype":"venue"
},
  "geometry": {"coordinates":[-80.674477,28.075508],"type":"Point"}
}