{
  "type": "Feature",
  "properties": {
    "addr:full":"9505 Hamlet Ln Tampa FL 33635",
    "addr:housenumber":"9505",
    "addr:postcode":"33635",
    "addr:street":"Hamlet Ln",
    "iso:country":"US",
    "sg:address":"9505 Hamlet Ln",
    "sg:city":"Tampa",
    "sg:classifiers":[
        {
            "category":"Arts & Performance",
            "subcategory":"Theater",
            "type":"Entertainment"
        }
    ],
    "sg:phone":"+1 813 854 4702",
    "sg:postcode":"33635",
    "sg:province":"FL",
    "sg:tags":[
        "live",
        "music"
    ],
    "wof:name":"Jeff Staples Mobile Disc Jcky",
    "wof:placetype":"venue"
},
  "geometry": {"coordinates":[-82.593524,28.036777],"type":"Point"}
}