{
  "type": "Feature",
  "properties": {
    "iso:country":"US",
    "sg:address":"6539 Orchid Lake Rd",
    "sg:city":"New Port Richey",
    "sg:classifiers":[
        {
            "category":"Home & Garden",
            "subcategory":"Garden Supply",
            "type":"Retail Goods"
        }
    ],
    "sg:phone":"+1 727 847 3881",
    "sg:postcode":"34653",
    "sg:province":"FL",
    "sg:tags":[
        "landscaping",
        "equipment"
    ],
    "wof:name":"T & K Landscape Equipment",
    "wof:placetype":"venue"
},
  "geometry": {"coordinates":[-82.706446,28.271661],"type":"Point"}
}