{
  "type": "Feature",
  "properties": {
    "addr:full":"3331 Lena Rd Bradenton FL 34211",
    "addr:housenumber":"3331",
    "addr:postcode":"34211",
    "addr:street":"Lena Rd",
    "iso:country":"US",
    "sg:address":"3331 Lena Rd",
    "sg:city":"Bradenton",
    "sg:classifiers":[
        {
            "category":"Government",
            "subcategory":"Office",
            "type":"Public Place"
        }
    ],
    "sg:phone":"+1 941 748 4978",
    "sg:postcode":"34211",
    "sg:province":"FL",
    "sg:tags":[
        "management"
    ],
    "wof:name":"Southeast Sbrgnl Wste Wtr Trtm",
    "wof:placetype":"venue"
},
  "geometry": {"coordinates":[-82.45700600000001,27.478664],"type":"Point"}
}