{
  "type": "Feature",
  "properties": {
    "iso:country":"US",
    "sg:address":"10453 Canoe Brook Cir",
    "sg:city":"Boca Raton",
    "sg:classifiers":[
        {
            "category":"Professional",
            "subcategory":"Management & Consulting",
            "type":"Services"
        }
    ],
    "sg:phone":"+1 561 477 5947",
    "sg:postcode":"33498",
    "sg:province":"FL",
    "sg:tags":[
        "business"
    ],
    "wof:name":"Star Group Consulting",
    "wof:placetype":"venue"
},
  "geometry": {"coordinates":[-80.209513,26.391846],"type":"Point"}
}