{
  "type": "Feature",
  "properties": {
    "iso:country":"US",
    "sg:address":"2033 W 62nd St",
    "sg:city":"Hialeah",
    "sg:classifiers":[
        {
            "category":"Professional",
            "subcategory":"Advertising",
            "type":"Services"
        },
        {
            "category":"Professional",
            "subcategory":"Business Services",
            "type":"Services"
        }
    ],
    "sg:phone":"+1 305 364 9099",
    "sg:postcode":"33016",
    "sg:province":"FL",
    "sg:tags":[
        "mail",
        "messenger",
        "direct",
        "shipping"
    ],
    "wof:name":"Wrapit Transit",
    "wof:placetype":"venue"
},
  "geometry": {"coordinates":[-80.32432300000001,25.87882],"type":"Point"}
}