{
  "type": "Feature",
  "properties": {
    "iso:country":"US",
    "sg:address":"5750 Hopson Rd",
    "sg:city":"Frostproof",
    "sg:classifiers":[
        {
            "category":"Place Of Worship",
            "subcategory":"Church",
            "type":"Public Place"
        },
        {
            "category":"Place Of Worship",
            "type":"Public Place"
        }
    ],
    "sg:phone":"+1 863 635 4028",
    "sg:postcode":"33843",
    "sg:province":"FL",
    "sg:tags":[
        "churches-christian"
    ],
    "wof:name":"Asghsmo Assembly Inc",
    "wof:placetype":"venue"
},
  "geometry": {"coordinates":[-81.547859,27.72583],"type":"Point"}
}