{
  "type": "Feature",
  "properties": {
    "iso:country":"US",
    "sg:address":"13350 SW 131st St",
    "sg:city":"Miami",
    "sg:classifiers":[
        {
            "category":"Professional",
            "subcategory":"Printing & Photocopies",
            "type":"Services"
        }
    ],
    "sg:phone":"+1 305 259 4377",
    "sg:postcode":"33186",
    "sg:province":"FL",
    "sg:tags":[
        "flag",
        "banners",
        "pennant"
    ],
    "wof:name":"Fbc And Associates",
    "wof:placetype":"venue"
},
  "geometry": {"coordinates":[-80.412994,25.645653],"type":"Point"}
}