{
  "type": "Feature",
  "properties": {
    "addr:full":"1708 Mira Ct Oviedo FL 32765",
    "addr:housenumber":"1708",
    "addr:postcode":"32765",
    "addr:street":"Mira Ct",
    "iso:country":"US",
    "sg:address":"1708 Mira Ct",
    "sg:city":"Oviedo",
    "sg:classifiers":[
        {
            "category":"Manufacturing",
            "subcategory":"Retail Goods",
            "type":"Manufacturing & Wholesale Goods"
        }
    ],
    "sg:phone":"+1 407 327 8110",
    "sg:postcode":"32765",
    "sg:province":"FL",
    "sg:tags":[
        "manufacturer"
    ],
    "wof:name":"Sugarplum Factory",
    "wof:placetype":"venue"
},
  "geometry": {"coordinates":[-81.26199800000001,28.635644],"type":"Point"}
}