{
  "type": "Feature",
  "properties": {
    "addr:full":"1390 S Dixie Hwy Coral Gables FL 33146",
    "addr:housenumber":"1390",
    "addr:postcode":"33146",
    "addr:street":"S Dixie Hwy",
    "iso:country":"US",
    "sg:address":"1390 S Dixie Hwy",
    "sg:city":"Coral Gables",
    "sg:classifiers":[
        {
            "category":"Professional",
            "subcategory":"Accounting & Tax Preparation",
            "type":"Services"
        }
    ],
    "sg:phone":"+1 305 663 3566",
    "sg:postcode":"33146",
    "sg:province":"FL",
    "sg:tags":[
        "accountant"
    ],
    "wof:name":"Frs Associates",
    "wof:placetype":"venue"
},
  "geometry": {"coordinates":[-80.2761,25.719],"type":"Point"}
}