{
  "type": "Feature",
  "properties": {
    "iso:country":"US",
    "sg:address":"1062 41st Ave NE",
    "sg:city":"St Petersburg",
    "sg:classifiers":[
        {
            "category":"Professional",
            "subcategory":"Accounting & Tax Preparation",
            "type":"Services"
        }
    ],
    "sg:phone":"+1 727 823 3865",
    "sg:postcode":"33703",
    "sg:province":"FL",
    "sg:tags":[
        "accountant"
    ],
    "wof:name":"Azazel Accounting Inc",
    "wof:placetype":"venue"
},
  "geometry": {"coordinates":[-82.62206500000001,27.809379],"type":"Point"}
}