{
  "type": "Feature",
  "properties": {
    "iso:country":"US",
    "sg:address":"11420 Fortune Cir",
    "sg:city":"Wellington",
    "sg:classifiers":[
        {
            "category":"Sports & Exercise",
            "subcategory":"Gym",
            "type":"Entertainment"
        }
    ],
    "sg:phone":"+1 561 204 5393",
    "sg:postcode":"33414",
    "sg:province":"FL",
    "sg:tags":[
        "club",
        "health",
        "studio",
        "gymnasium"
    ],
    "wof:name":"Pilates Wellness Ctr",
    "wof:placetype":"venue"
},
  "geometry": {"coordinates":[-80.22527599999999,26.634101],"type":"Point"}
}