{
  "type": "Feature",
  "properties": {
    "iso:country":"US",
    "sg:address":"7001 Old Plantation Ave",
    "sg:city":"Sebring",
    "sg:classifiers":[
        {
            "category":"Travel",
            "subcategory":"Resort",
            "type":"Entertainment"
        },
        {
            "category":"Recreation",
            "subcategory":"Campground",
            "type":"Entertainment"
        }
    ],
    "sg:phone":"+1 863 655 1685",
    "sg:postcode":"33876",
    "sg:province":"FL",
    "sg:tags":[
        "recreational",
        "park",
        "vehicle"
    ],
    "wof:name":"Highland Oaks Rv Resort Inc",
    "wof:placetype":"venue"
},
  "geometry": {"coordinates":[-81.413483,27.4347],"type":"Point"}
}