{
  "type": "Feature",
  "properties": {
    "addr:full":"2762 SW 5th St Delray Beach FL 33445",
    "addr:housenumber":"2762",
    "addr:postcode":"33445",
    "addr:street":"Sw 5Th St",
    "iso:country":"US",
    "sg:address":"2762 SW 5th St",
    "sg:city":"Delray Beach",
    "sg:classifiers":[
        {
            "category":"Building & Trades",
            "subcategory":"Landscaping Services",
            "type":"Services"
        }
    ],
    "sg:phone":"+1 561 496 3256",
    "sg:postcode":"33445",
    "sg:province":"FL",
    "sg:tags":[
        "landscape",
        "contractor"
    ],
    "wof:name":"Avant Gardens Inc",
    "wof:placetype":"venue"
},
  "geometry": {"coordinates":[-80.10341699999999,26.453256],"type":"Point"}
}