{
  "type": "Feature",
  "properties": {
    "addr:full":"3376 NW Federal Hwy Jensen Beach FL 34957",
    "addr:housenumber":"3376",
    "addr:postcode":"34957",
    "addr:street":"Nw Federal Hwy",
    "iso:country":"US",
    "sg:address":"3376 NW Federal Hwy",
    "sg:city":"Jensen Beach",
    "sg:classifiers":[
        {
            "category":"Personal",
            "subcategory":"Beauty Salon",
            "type":"Services"
        }
    ],
    "sg:phone":"+1 772 692 3221",
    "sg:postcode":"34957",
    "sg:province":"FL",
    "sg:tags":[
        "manicuring"
    ],
    "wof:name":"Nails First By Rosie",
    "wof:placetype":"venue"
},
  "geometry": {"coordinates":[-80.269246,27.23718],"type":"Point"}
}