{
  "type": "Feature",
  "properties": {
    "iso:country":"US",
    "sg:address":"4638 Gleason Ave",
    "sg:city":"Sarasota",
    "sg:classifiers":[
        {
            "category":"Building & Trades",
            "subcategory":"Construction",
            "type":"Services"
        }
    ],
    "sg:phone":"+1 941 349 1581",
    "sg:postcode":"34242",
    "sg:province":"FL",
    "sg:tags":[
        "general",
        "contractor"
    ],
    "wof:name":"CCH Design/Construction",
    "wof:placetype":"venue"
},
  "geometry": {"coordinates":[-82.561797,27.286743],"type":"Point"}
}