{
  "type": "Feature",
  "properties": {
    "iso:country":"US",
    "sg:address":"4500 Commercial Way",
    "sg:city":"Spring Hill",
    "sg:classifiers":[
        {
            "category":"Personal",
            "subcategory":"Beauty Salon",
            "type":"Services"
        }
    ],
    "sg:phone":"+1 352 597 4448",
    "sg:postcode":"34606",
    "sg:province":"FL",
    "sg:tags":[
        "shop",
        "manicuring"
    ],
    "wof:name":"Gayle's Nail Works",
    "wof:placetype":"venue"
},
  "geometry": {"coordinates":[-82.59751300000001,28.493069],"type":"Point"}
}