{
  "type": "Feature",
  "properties": {
    "addr:full":"13890 NW 5th Ct Miami FL 33168",
    "addr:housenumber":"13890",
    "addr:postcode":"33168",
    "addr:street":"Nw 5Th Ct",
    "iso:country":"US",
    "sg:address":"13890 NW 5th Ct",
    "sg:city":"Miami",
    "sg:classifiers":[
        {
            "category":"Freight",
            "type":"Transportation"
        }
    ],
    "sg:phone":"+1 305 687 8861",
    "sg:postcode":"33168",
    "sg:province":"FL",
    "sg:tags":[
        "trucking"
    ],
    "wof:name":"LA France Transport",
    "wof:placetype":"venue"
},
  "geometry": {"coordinates":[-80.20818,25.900886],"type":"Point"}
}