{
  "type": "Feature",
  "properties": {
    "addr:full":"10722 SW 113th Pl Miami FL 33176",
    "addr:housenumber":"10722",
    "addr:postcode":"33176",
    "addr:street":"Sw 113Th Pl",
    "iso:country":"US",
    "sg:address":"10722 SW 113th Pl",
    "sg:city":"Miami",
    "sg:classifiers":[
        {
            "category":"Retail",
            "subcategory":"Laundry & Dry Cleaning",
            "type":"Services"
        }
    ],
    "sg:phone":"+1 305 271 8548",
    "sg:postcode":"33176",
    "sg:province":"FL",
    "sg:tags":[
        "garment",
        "agent"
    ],
    "wof:name":"Dryclean USA",
    "wof:placetype":"venue"
},
  "geometry": {"coordinates":[-80.378147,25.66786],"type":"Point"}
}