{
  "type": "Feature",
  "properties": {
    "addr:full":"196 Brooks Cir Oak Hill FL 32759",
    "addr:housenumber":"196",
    "addr:postcode":"32759",
    "addr:street":"Brooks Cir",
    "iso:country":"US",
    "sg:address":"196 Brooks Cir",
    "sg:city":"Oak Hill",
    "sg:classifiers":[
        {
            "category":"Shopping",
            "subcategory":"Computers & Home Electronics",
            "type":"Retail Goods"
        }
    ],
    "sg:phone":"+1 386 345 0004",
    "sg:postcode":"32759",
    "sg:province":"FL",
    "sg:tags":[
        "equipment",
        "satellite",
        "system"
    ],
    "wof:name":"Spaceport Satellite",
    "wof:placetype":"venue"
},
  "geometry": {"coordinates":[-80.86123600000001,28.878891],"type":"Point"}
}