{
  "type": "Feature",
  "properties": {
    "iso:country":"US",
    "sg:address":"1650 Margaret St",
    "sg:city":"Jacksonville",
    "sg:classifiers":[
        {
            "category":"Restaurant",
            "type":"Food & Drink"
        }
    ],
    "sg:menulink":"http://www.allmenus.com/fl/jacksonville/81258-papa-johns-pizza/menu/",
    "sg:phone":"+1 904 387 7272",
    "sg:postcode":"32204",
    "sg:province":"FL",
    "sg:tags":[
        "american",
        "pizza"
    ],
    "wof:name":"Papa John's Pizza",
    "wof:placetype":"venue"
},
  "geometry": {"coordinates":[-81.68083300000001,30.312078],"type":"Point"}
}