{
  "type": "Feature",
  "properties": {
    "addr:full":"484 Club Dr Winter Springs FL 32708",
    "addr:housenumber":"484",
    "addr:postcode":"32708",
    "addr:street":"Club Dr",
    "iso:country":"US",
    "sg:address":"484 Club Dr",
    "sg:city":"Winter Springs",
    "sg:classifiers":[
        {
            "category":"Professional",
            "subcategory":"Business Services",
            "type":"Services"
        }
    ],
    "sg:phone":"+1 407 327 8372",
    "sg:postcode":"32708",
    "sg:province":"FL",
    "wof:name":"Innovtive Intrors Cntl Fla Inc",
    "wof:placetype":"venue"
},
  "geometry": {"coordinates":[-81.311629,28.708348],"type":"Point"}
}