{
  "type": "Feature",
  "properties": {
    "iso:country":"US",
    "sg:address":"701 NW 73rd St",
    "sg:city":"Miami",
    "sg:classifiers":[
        {
            "category":"Building & Trades",
            "subcategory":"Locksmith",
            "type":"Services"
        }
    ],
    "sg:phone":"+1 305 714 0320",
    "sg:postcode":"33150",
    "sg:province":"FL",
    "sg:tags":[
        "key"
    ],
    "wof:name":"Anderson Emergency Locksmith",
    "wof:placetype":"venue"
},
  "geometry": {"coordinates":[-80.208945,25.842117],"type":"Point"}
}