{
  "type": "Feature",
  "properties": {
    "addr:full":"4210 W Lake Mary Blvd Lake Mary FL 32746",
    "addr:housenumber":"4210",
    "addr:postcode":"32746",
    "addr:street":"W Lake Mary Blvd",
    "iso:country":"US",
    "sg:address":"4210 W Lake Mary Blvd",
    "sg:city":"Lake Mary",
    "sg:classifiers":[
        {
            "category":"Fast Food",
            "type":"Food & Drink"
        }
    ],
    "sg:phone":"+1 407 333 3590",
    "sg:postcode":"32746",
    "sg:province":"FL",
    "sg:website":"www.mcdonalds.com",
    "wof:name":"McDonalds",
    "wof:placetype":"venue"
},
  "geometry": {"coordinates":[-81.35086699999999,28.756374],"type":"Point"}
}