{
  "type": "Feature",
  "properties": {
    "iso:country":"US",
    "sg:address":"4678 E 10th Ln",
    "sg:city":"Hialeah",
    "sg:classifiers":[
        {
            "category":"Building & Trades",
            "subcategory":"Construction",
            "type":"Services"
        }
    ],
    "sg:phone":"+1 305 681 1060",
    "sg:postcode":"33013",
    "sg:province":"FL",
    "sg:tags":[
        "contractor"
    ],
    "wof:name":"Coda Roofing Inc",
    "wof:placetype":"venue"
},
  "geometry": {"coordinates":[-80.261477,25.863961],"type":"Point"}
}