{
  "type": "Feature",
  "properties": {
    "iso:country":"US",
    "sg:address":"13725 NW 7th Ave",
    "sg:city":"Miami",
    "sg:classifiers":[
        {
            "category":"Retail",
            "subcategory":"Laundry & Dry Cleaning",
            "type":"Services"
        }
    ],
    "sg:phone":"+1 305 392 0045",
    "sg:postcode":"33168",
    "sg:province":"FL",
    "sg:tags":[
        "cleaner",
        "operated",
        "dryer",
        "laundries-self",
        "washer",
        "coin"
    ],
    "wof:name":"Sqeaky Clean Coin Laundry",
    "wof:placetype":"venue"
},
  "geometry": {"coordinates":[-80.21131099999999,25.900621],"type":"Point"}
}