{
  "type": "Feature",
  "properties": {
    "addr:full":"401 Biscayne Blvd Ste R200 Miami FL 33132",
    "addr:housenumber":"401",
    "addr:postcode":"33132",
    "addr:street":"Biscayne Blvd Ste R200",
    "iso:country":"US",
    "sg:address":"401 Biscayne Blvd Ste R200",
    "sg:city":"Miami",
    "sg:classifiers":[
        {
            "category":"Restaurant",
            "type":"Food & Drink"
        }
    ],
    "sg:phone":"+1 305 377 3110",
    "sg:postcode":"33132",
    "sg:province":"FL",
    "sg:tags":[
        "traditional",
        "american"
    ],
    "sg:website":"www.hardrock.com/miami",
    "wof:name":"Hard Rock Cafe",
    "wof:placetype":"venue"
},
  "geometry": {"coordinates":[-80.18809,25.778351],"type":"Point"}
}