{
  "type": "Feature",
  "properties": {
    "iso:country":"US",
    "sg:address":"1570 Alton Rd # 3",
    "sg:city":"Miami Beach",
    "sg:classifiers":[
        {
            "category":"Bakery",
            "type":"Food & Drink"
        }
    ],
    "sg:phone":"+1 305 274 1742",
    "sg:postcode":"33139",
    "sg:province":"FL",
    "wof:name":"Dairy Queen of Dade County",
    "wof:placetype":"venue"
},
  "geometry": {"coordinates":[-80.14099899999999,25.788799],"type":"Point"}
}