{
  "type": "Feature",
  "properties": {
    "iso:country":"US",
    "sg:address":"210 Valencia Rd",
    "sg:city":"De Bary",
    "sg:classifiers":[
        {
            "category":"Building & Trades",
            "subcategory":"Landscaping Services",
            "type":"Services"
        }
    ],
    "sg:phone":"+1 386 668 5090",
    "sg:postcode":"32713",
    "sg:province":"FL",
    "wof:name":"Brians Lawn Maintenance",
    "wof:placetype":"venue"
},
  "geometry": {"coordinates":[-81.295754,28.876746],"type":"Point"}
}