{
  "type": "Feature",
  "properties": {
    "iso:country":"US",
    "sg:address":"2030 Dyan Way",
    "sg:city":"Maitland",
    "sg:classifiers":[
        {
            "category":"Building & Trades",
            "subcategory":"Construction",
            "type":"Services"
        }
    ],
    "sg:phone":"+1 407 695 8404",
    "sg:postcode":"32751",
    "sg:province":"FL",
    "sg:tags":[
        "restoration",
        "cleaning",
        "patio",
        "deck"
    ],
    "wof:name":"MAC Attack Pressure Washing",
    "wof:placetype":"venue"
},
  "geometry": {"coordinates":[-81.341779,28.633786],"type":"Point"}
}