{
  "type": "Feature",
  "properties": {
    "addr:full":"1246 NE 38th St Fort Lauderdale FL 33334",
    "addr:housenumber":"1246",
    "addr:postcode":"33334",
    "addr:street":"Ne 38Th St",
    "iso:country":"US",
    "sg:address":"1246 NE 38th St",
    "sg:city":"Fort Lauderdale",
    "sg:classifiers":[
        {
            "category":"Wholesale",
            "subcategory":"Furniture",
            "type":"Manufacturing & Wholesale Goods"
        },
        {
            "category":"Home & Garden",
            "subcategory":"Furniture",
            "type":"Retail Goods"
        }
    ],
    "sg:phone":"+1 954 630 8830",
    "sg:postcode":"33334",
    "sg:province":"FL",
    "sg:tags":[
        "relocation",
        "man"
    ],
    "wof:name":"Commercial Resource Group Intl",
    "wof:placetype":"venue"
},
  "geometry": {"coordinates":[-80.130351,26.174058],"type":"Point"}
}