{
  "type": "Feature",
  "properties": {
    "addr:full":"3184 Monticello Pl Orlando FL 32835",
    "addr:housenumber":"3184",
    "addr:postcode":"32835",
    "addr:street":"Monticello Pl",
    "iso:country":"US",
    "sg:address":"3184 Monticello Pl",
    "sg:city":"Orlando",
    "sg:classifiers":[
        {
            "category":"Professional",
            "type":"Services"
        },
        {
            "category":"Transit Center",
            "subcategory":"Freight",
            "type":"Transportation"
        },
        {
            "category":"Retail",
            "subcategory":"Auto Rental",
            "type":"Services"
        }
    ],
    "sg:phone":"+1 321 945 3506",
    "sg:postcode":"32835",
    "sg:province":"FL",
    "sg:tags":[
        "limousine",
        "advertising"
    ],
    "sg:website":"http://www.backstagelimousineorlando.com",
    "wof:name":"Orlando Transportation by Backstage Limousine",
    "wof:placetype":"venue"
},
  "geometry": {"coordinates":[-81.472482,28.51123],"type":"Point"}
}