{
  "type": "Feature",
  "properties": {
    "iso:country":"US",
    "sg:address":"1726 Red Cypress Dr",
    "sg:city":"Jacksonville",
    "sg:classifiers":[
        {
            "category":"Professional",
            "subcategory":"Management & Consulting",
            "type":"Services"
        }
    ],
    "sg:phone":"+1 904 268 1793",
    "sg:postcode":"32223",
    "sg:province":"FL",
    "sg:tags":[
        "business"
    ],
    "wof:name":"PC Support Associates",
    "wof:placetype":"venue"
},
  "geometry": {"coordinates":[-81.66449299999999,30.146108],"type":"Point"}
}