{
  "type": "Feature",
  "properties": {
    "iso:country":"US",
    "sg:address":"3741 W Broward Blvd",
    "sg:city":"Fort Lauderdale",
    "sg:classifiers":[
        {
            "category":"Organizations",
            "subcategory":"Religious Organization",
            "type":"Services"
        }
    ],
    "sg:phone":"+1 954 797 9020",
    "sg:postcode":"33312",
    "sg:province":"FL",
    "sg:tags":[
        "church"
    ],
    "wof:name":"Renaissance Evangelical",
    "wof:placetype":"venue"
},
  "geometry": {"coordinates":[-80.197847,26.121061],"type":"Point"}
}