{
  "type": "Feature",
  "properties": {
    "iso:country":"US",
    "sg:address":"1410 Market St",
    "sg:city":"Tallahassee",
    "sg:classifiers":[
        {
            "category":"Education",
            "subcategory":"Special Training",
            "type":"Public Place"
        }
    ],
    "sg:phone":"+1 850 385 8696",
    "sg:postcode":"32312",
    "sg:province":"FL",
    "sg:tags":[
        "tutoring"
    ],
    "sg:website":"www.educate.com",
    "wof:name":"Sylvan Learning Ctr",
    "wof:placetype":"venue"
},
  "geometry": {"coordinates":[-84.25006999999999,30.506494],"type":"Point"}
}