{
  "type": "Feature",
  "properties": {
    "iso:country":"US",
    "sg:address":"5330 SW 7th St",
    "sg:city":"Miami",
    "sg:classifiers":[
        {
            "category":"Retail",
            "subcategory":"Auto Repair",
            "type":"Services"
        }
    ],
    "sg:phone":"+1 305 567 9511",
    "sg:postcode":"33134",
    "sg:province":"FL",
    "sg:tags":[
        "body"
    ],
    "wof:name":"Oscar Lostal",
    "wof:placetype":"venue"
},
  "geometry": {"coordinates":[-80.28351000000001,25.764437],"type":"Point"}
}