{
  "type": "Feature",
  "properties": {
    "iso:country":"US",
    "sg:address":"4613 N University Dr",
    "sg:city":"Pompano Beach",
    "sg:classifiers":[
        {
            "category":"Banks & Credit Unions",
            "subcategory":"Bank",
            "type":"Services"
        }
    ],
    "sg:phone":"+1 954 755 9944",
    "sg:postcode":"33067",
    "sg:province":"FL",
    "sg:tags":[
        "mortgage"
    ],
    "wof:name":"First Trust Mortgage Services",
    "wof:placetype":"venue"
},
  "geometry": {"coordinates":[-80.24987299999999,26.289887],"type":"Point"}
}