{
  "type": "Feature",
  "properties": {
    "addr:full":"512 SW 80 Blvd Gainesville FL 32607",
    "addr:housenumber":"512",
    "addr:postcode":"32607",
    "addr:street":"Sw 80 Blvd",
    "iso:country":"US",
    "sg:address":"512 SW 80 Blvd",
    "sg:city":"Gainesville",
    "sg:classifiers":[
        {
            "category":"Shopping",
            "subcategory":"Gifts & Souvenirs",
            "type":"Retail Goods"
        }
    ],
    "sg:phone":"+1 352 331 4108",
    "sg:postcode":"32607",
    "sg:province":"FL",
    "wof:name":"Aacj Enterprises",
    "wof:placetype":"venue"
},
  "geometry": {"coordinates":[-82.429576,29.645411],"type":"Point"}
}