{
  "type": "Feature",
  "properties": {
    "iso:country":"US",
    "sg:address":"922 S 9th St",
    "sg:city":"Jacksonville Bch",
    "sg:classifiers":[
        {
            "category":"Utilities",
            "subcategory":"Fuel Oil & Lpg",
            "type":"Services"
        }
    ],
    "sg:phone":"+1 904 246 7316",
    "sg:postcode":"32250",
    "sg:province":"FL",
    "sg:tags":[
        "propane",
        "bottled",
        "gas"
    ],
    "sg:website":"www.ferrellgas.com",
    "wof:name":"Ferrellgas",
    "wof:placetype":"venue"
},
  "geometry": {"coordinates":[-81.39658799999999,30.277922],"type":"Point"}
}