{
  "type": "Feature",
  "properties": {
    "iso:country":"US",
    "sg:address":"817 N Tyndall Pkwy",
    "sg:city":"Panama City",
    "sg:classifiers":[
        {
            "category":"Shopping",
            "subcategory":"Jewelry",
            "type":"Retail Goods"
        }
    ],
    "sg:phone":"+1 850 769 2752",
    "sg:postcode":"32404",
    "sg:province":"FL",
    "sg:tags":[
        "jeweler"
    ],
    "wof:name":"Freidman's Jewelers",
    "wof:placetype":"venue"
},
  "geometry": {"coordinates":[-85.591275,30.160471],"type":"Point"}
}