{
  "type": "Feature",
  "properties": {
    "iso:country":"US",
    "sg:address":"18340 NW 7th Ave",
    "sg:city":"Miami",
    "sg:classifiers":[
        {
            "category":"Shopping",
            "subcategory":"Clothing, Apparel, & Fashions",
            "type":"Retail Goods"
        }
    ],
    "sg:phone":"+1 305 652 9551",
    "sg:postcode":"33169",
    "sg:province":"FL",
    "sg:tags":[
        "accessory",
        "clothing",
        "women's"
    ],
    "sg:website":"www.dots.com",
    "wof:name":"Dots",
    "wof:placetype":"venue"
},
  "geometry": {"coordinates":[-80.213097,25.943001],"type":"Point"}
}