{
  "type": "Feature",
  "properties": {
    "iso:country":"US",
    "sg:address":"6400 Madison St",
    "sg:city":"New Port Richey",
    "sg:classifiers":[
        {
            "category":"Professional",
            "subcategory":"Lawyer & Legal Services",
            "type":"Services"
        }
    ],
    "sg:phone":"+1 727 846 1777",
    "sg:postcode":"34652",
    "sg:province":"FL",
    "wof:name":"Mark A Spence PA",
    "wof:placetype":"venue"
},
  "geometry": {"coordinates":[-82.71541999999999,28.251807],"type":"Point"}
}