{
  "type": "Feature",
  "properties": {
    "addr:full":"616 S Miami Ave Miami FL 33130",
    "addr:housenumber":"616",
    "addr:postcode":"33130",
    "addr:street":"S Miami Ave",
    "iso:country":"US",
    "sg:address":"616 S Miami Ave",
    "sg:city":"Miami",
    "sg:classifiers":[
        {
            "category":"Arts & Performance",
            "subcategory":"Art Gallery",
            "type":"Entertainment"
        }
    ],
    "sg:phone":"+1 305 373 1772",
    "sg:postcode":"33130",
    "sg:province":"FL",
    "wof:name":"Brickell Village Gallery",
    "wof:placetype":"venue"
},
  "geometry": {"coordinates":[-80.194298,25.768],"type":"Point"}
}