{
  "type": "Feature",
  "properties": {
    "addr:full":"1736 University Blvd S Jacksonville FL 32216",
    "addr:housenumber":"1736",
    "addr:postcode":"32216",
    "addr:street":"University Blvd S",
    "iso:country":"US",
    "sg:address":"1736 University Blvd S",
    "sg:city":"Jacksonville",
    "sg:classifiers":[
        {
            "category":"Government",
            "subcategory":"Office",
            "type":"Public Place"
        }
    ],
    "sg:phone":"+1 904 727 6540",
    "sg:postcode":"32216",
    "sg:province":"FL",
    "sg:tags":[
        "village"
    ],
    "wof:name":"South Jacksonville Family Hlth",
    "wof:placetype":"venue"
},
  "geometry": {"coordinates":[-81.59971899999999,30.312317],"type":"Point"}
}