{
  "type": "Feature",
  "properties": {
    "addr:full":"700 Grouper Ln Key Largo FL 33037",
    "addr:housenumber":"700",
    "addr:postcode":"33037",
    "addr:street":"Grouper Ln",
    "iso:country":"US",
    "sg:address":"700 Grouper Ln",
    "sg:city":"Key Largo",
    "sg:classifiers":[
        {
            "category":"Banks & Credit Unions",
            "subcategory":"Financial Services",
            "type":"Services"
        }
    ],
    "sg:phone":"+1 305 852 4684",
    "sg:postcode":"33037",
    "sg:province":"FL",
    "sg:tags":[
        "trust",
        "management"
    ],
    "wof:name":"Robertson Partners Ltd",
    "wof:placetype":"venue"
},
  "geometry": {"coordinates":[-80.488812,25.046062],"type":"Point"}
}