{
  "type": "Feature",
  "properties": {
    "addr:full":"9323 Southampton Pl Boca Raton FL 33434",
    "addr:housenumber":"9323",
    "addr:postcode":"33434",
    "addr:street":"Southampton Pl",
    "iso:country":"US",
    "sg:address":"9323 Southampton Pl",
    "sg:city":"Boca Raton",
    "sg:classifiers":[
        {
            "category":"Real Estate",
            "subcategory":"Real Estate Agent",
            "type":"Services"
        }
    ],
    "sg:phone":"+1 561 558 9419",
    "sg:postcode":"33434",
    "sg:province":"FL",
    "sg:tags":[
        "management"
    ],
    "wof:name":"C B Richard Ellis",
    "wof:placetype":"venue"
},
  "geometry": {"coordinates":[-80.192474,26.383151],"type":"Point"}
}