{
  "type": "Feature",
  "properties": {
    "iso:country":"US",
    "sg:address":"500 SW 177th Ave",
    "sg:city":"Miami",
    "sg:classifiers":[
        {
            "category":"Wholesale",
            "subcategory":"Music Publishers",
            "type":"Manufacturing & Wholesale Goods"
        }
    ],
    "sg:phone":"+1 305 220 3008",
    "sg:postcode":"33194",
    "sg:province":"FL",
    "sg:tags":[
        "distribution"
    ],
    "wof:name":"Unavision Radio",
    "wof:placetype":"venue"
},
  "geometry": {"coordinates":[-80.48159800000001,25.764],"type":"Point"}
}