{
  "type": "Feature",
  "properties": {
    "iso:country":"US",
    "sg:address":"2700 SW 15th Ave",
    "sg:city":"Fort Lauderdale",
    "sg:classifiers":[
        {
            "category":"Freight",
            "type":"Transportation"
        }
    ],
    "sg:phone":"+1 954 527 5240",
    "sg:postcode":"33315",
    "sg:province":"FL",
    "sg:tags":[
        "operator",
        "trucking"
    ],
    "wof:name":"Tracy Transport USA Inc",
    "wof:placetype":"venue"
},
  "geometry": {"coordinates":[-80.16083999999999,26.089271],"type":"Point"}
}