{
  "type": "Feature",
  "properties": {
    "iso:country":"US",
    "sg:address":"12655 Tamiami Trl",
    "sg:city":"Naples",
    "sg:classifiers":[
        {
            "category":"Banks & Credit Unions",
            "subcategory":"Bank",
            "type":"Services"
        }
    ],
    "sg:phone":"+1 239 793 8800",
    "sg:postcode":"34113",
    "sg:province":"FL",
    "sg:tags":[
        "state"
    ],
    "wof:name":"Fifth Third Bank",
    "wof:placetype":"venue"
},
  "geometry": {"coordinates":[-81.69985699999999,26.06386],"type":"Point"}
}