{
  "type": "Feature",
  "properties": {
    "iso:country":"US",
    "sg:address":"243 Hollywood Blvd NW",
    "sg:city":"Fort Walton Bch",
    "sg:classifiers":[
        {
            "category":"Building & Trades",
            "subcategory":"Plumbing",
            "type":"Services"
        }
    ],
    "sg:phone":"+1 850 244 2213",
    "sg:postcode":"32548",
    "sg:province":"FL",
    "sg:tags":[
        "plumbing",
        "contractor"
    ],
    "wof:name":"Plumbersmith & Assoc Inc",
    "wof:placetype":"venue"
},
  "geometry": {"coordinates":[-86.62996099999999,30.412948],"type":"Point"}
}