{
  "type": "Feature",
  "properties": {
    "iso:country":"US",
    "sg:address":"835 Saint Clair St",
    "sg:city":"Melbourne",
    "sg:classifiers":[
        {
            "category":"Retail",
            "subcategory":"Auto Repair",
            "type":"Services"
        }
    ],
    "sg:phone":"+1 321 254 7521",
    "sg:postcode":"32935",
    "sg:province":"FL",
    "sg:tags":[
        "pa",
        "general",
        "supply"
    ],
    "wof:name":"Vans Radiator & AC Sls",
    "wof:placetype":"venue"
},
  "geometry": {"coordinates":[-80.632003,28.130009],"type":"Point"}
}