{
  "type": "Feature",
  "properties": {
    "addr:full":"7910 Hammond Blvd Jacksonville FL 32220",
    "addr:housenumber":"7910",
    "addr:postcode":"32220",
    "addr:street":"Hammond Blvd",
    "iso:country":"US",
    "sg:address":"7910 Hammond Blvd",
    "sg:city":"Jacksonville",
    "sg:classifiers":[
        {
            "category":"Manufacturing",
            "subcategory":"Wood Products",
            "type":"Manufacturing & Wholesale Goods"
        }
    ],
    "sg:phone":"+1 904 695 1672",
    "sg:postcode":"32220",
    "sg:province":"FL",
    "sg:tags":[
        "mfg"
    ],
    "wof:name":"Board King Inc",
    "wof:placetype":"venue"
},
  "geometry": {"coordinates":[-81.78130899999999,30.319243],"type":"Point"}
}