{
  "type": "Feature",
  "properties": {
    "iso:country":"US",
    "sg:address":"11224 Rabun Gap Dr",
    "sg:city":"Fort Myers",
    "sg:classifiers":[
        {
            "category":"Shopping",
            "subcategory":"Hobbies, Toys, & Games",
            "type":"Retail Goods"
        }
    ],
    "sg:phone":"+1 239 543 1667",
    "sg:postcode":"33917",
    "sg:province":"FL",
    "wof:name":"Carlas Crafts",
    "wof:placetype":"venue"
},
  "geometry": {"coordinates":[-81.773839,26.717932],"type":"Point"}
}