{
  "type": "Feature",
  "properties": {
    "addr:full":"3404 Mahan Dr Tallahassee FL 32308",
    "addr:housenumber":"3404",
    "addr:postcode":"32308",
    "addr:street":"Mahan Dr",
    "iso:country":"US",
    "sg:address":"3404 Mahan Dr",
    "sg:city":"Tallahassee",
    "sg:classifiers":[
        {
            "category":"Autos & Motor Vehicles",
            "subcategory":"Automobile Sales",
            "type":"Retail Goods"
        },
        {
            "category":"Retail",
            "subcategory":"Auto Rental",
            "type":"Services"
        }
    ],
    "sg:phone":"+1 850 878 1500",
    "sg:postcode":"32308",
    "sg:province":"FL",
    "sg:tags":[
        "truck",
        "leasing",
        "car"
    ],
    "sg:website":"http://www.enterprise.com/car_rental/deeplinkmap.do?gpbr=5542&bid=004&cnty=US&arc=YPTRL01&cm_mmc=Yellowpages.com-_-IYP-_-Tradelisting-_-branch",
    "wof:name":"Enterprise Rent-A-Car",
    "wof:placetype":"venue"
},
  "geometry": {"coordinates":[-84.220403,30.462908],"type":"Point"}
}