{
  "type": "Feature",
  "properties": {
    "iso:country":"US",
    "sg:address":"264 S Military Trl",
    "sg:city":"Deerfield Beach",
    "sg:classifiers":[
        {
            "category":"Autos & Motor Vehicles",
            "subcategory":"Auto Supplies",
            "type":"Retail Goods"
        }
    ],
    "sg:phone":"+1 954 725 2998",
    "sg:postcode":"33442",
    "sg:province":"FL",
    "sg:tags":[
        "battery"
    ],
    "wof:name":"American Technical Support Inc",
    "wof:placetype":"venue"
},
  "geometry": {"coordinates":[-80.12801899999999,26.31376],"type":"Point"}
}