{
  "type": "Feature",
  "properties": {
    "iso:country":"US",
    "sg:address":"216 Duval St NW",
    "sg:city":"Live Oak",
    "sg:classifiers":[
        {
            "category":"Real Estate",
            "subcategory":"Real Estate Agent",
            "type":"Services"
        }
    ],
    "sg:phone":"+1 386 362 1400",
    "sg:postcode":"32064",
    "sg:province":"FL",
    "wof:name":"Remax Professionals",
    "wof:placetype":"venue"
},
  "geometry": {"coordinates":[-82.986345,30.299282],"type":"Point"}
}