{
  "type": "Feature",
  "properties": {
    "iso:country":"US",
    "sg:address":"3306 20th St",
    "sg:city":"Vero Beach",
    "sg:classifiers":[
        {
            "category":"Organizations",
            "subcategory":"Religious Organization",
            "type":"Services"
        }
    ],
    "sg:phone":"+1 772 567 2465",
    "sg:postcode":"32960",
    "sg:province":"FL",
    "sg:tags":[
        "church"
    ],
    "wof:name":"Church Of Christ-Vero Beach",
    "wof:placetype":"venue"
},
  "geometry": {"coordinates":[-80.419444,27.638396],"type":"Point"}
}