{
  "type": "Feature",
  "properties": {
    "iso:country":"US",
    "sg:address":"2441 NW 93rd Ter",
    "sg:city":"Miami",
    "sg:classifiers":[
        {
            "category":"Restaurant",
            "type":"Food & Drink"
        }
    ],
    "sg:phone":"+1 305 406 9611",
    "sg:postcode":"33147",
    "sg:province":"FL",
    "sg:tags":[
        "seafood"
    ],
    "wof:name":"Dimarsa International Llc",
    "wof:placetype":"venue"
},
  "geometry": {"coordinates":[-80.23901499999999,25.859571],"type":"Point"}
}