{
  "type": "Feature",
  "properties": {
    "iso:country":"US",
    "sg:address":"250 Catalonia Ave Ste 802",
    "sg:city":"Coral Gables",
    "sg:classifiers":[
        {
            "category":"Health Services",
            "subcategory":"Clinic",
            "type":"Services"
        }
    ],
    "sg:phone":"+1 305 448 2888",
    "sg:postcode":"33134",
    "sg:province":"FL",
    "sg:tags":[
        "counseling",
        "mental"
    ],
    "wof:name":"Barbara L Goldman, PHD PA",
    "wof:placetype":"venue"
},
  "geometry": {"coordinates":[-80.25967799999999,25.74438],"type":"Point"}
}