{
  "type": "Feature",
  "properties": {
    "addr:full":"1395 Brickell Ave 14th Floor Miami FL 33131",
    "addr:housenumber":"1395",
    "addr:postcode":"33131",
    "addr:street":"Brickell Ave 14Th Floor",
    "iso:country":"US",
    "sg:address":"1395 Brickell Ave 14th Floor",
    "sg:city":"Miami",
    "sg:classifiers":[
        {
            "category":"Professional",
            "subcategory":"Lawyer & Legal Services",
            "type":"Services"
        }
    ],
    "sg:phone":"+1 305 789 9200",
    "sg:postcode":"33131",
    "sg:province":"FL",
    "sg:tags":[
        "arbitration",
        "attorney",
        "practice",
        "litigation",
        "mediation",
        "labor",
        "tort",
        "law",
        "employment"
    ],
    "wof:name":"Hartley , Damon - Fowler White Burnett P",
    "wof:placetype":"venue"
},
  "geometry": {"coordinates":[-80.192115,25.7604],"type":"Point"}
}