{
  "type": "Feature",
  "properties": {
    "iso:country":"US",
    "sg:address":"624 Fishtail Palm Blvd",
    "sg:city":"Melbourne",
    "sg:classifiers":[
        {
            "category":"Wholesale",
            "subcategory":"Computers",
            "type":"Manufacturing & Wholesale Goods"
        }
    ],
    "sg:phone":"+1 321 768 0006",
    "sg:postcode":"32901",
    "sg:province":"FL",
    "sg:tags":[
        "repairing",
        "test",
        "automated",
        "equipment"
    ],
    "wof:name":"Tarinc",
    "wof:placetype":"venue"
},
  "geometry": {"coordinates":[-80.630561,28.060264],"type":"Point"}
}