{
  "type": "Feature",
  "properties": {
    "iso:country":"US",
    "sg:address":"2459 Dean Rd",
    "sg:city":"Jacksonville",
    "sg:classifiers":[
        {
            "category":"Communications",
            "subcategory":"Film & Video Production",
            "type":"Services"
        }
    ],
    "sg:phone":"+1 904 727 9271",
    "sg:postcode":"32216",
    "sg:province":"FL",
    "sg:tags":[
        "taping"
    ],
    "wof:name":"Ware Productions",
    "wof:placetype":"venue"
},
  "geometry": {"coordinates":[-81.591875,30.278705],"type":"Point"}
}