{
  "type": "Feature",
  "properties": {
    "iso:country":"US",
    "sg:address":"1097 Ponce de Leon Blvd",
    "sg:city":"Brooksville",
    "sg:phone":"+1 352 799 8295",
    "sg:postcode":"34601",
    "sg:province":"FL",
    "sg:tags":[
        "shelving"
    ],
    "wof:name":"Montrose Shelving Inc",
    "wof:placetype":"venue"
},
  "geometry": {"coordinates":[-82.39776000000001,28.567272],"type":"Point"}
}