{
  "type": "Feature",
  "properties": {
    "iso:country":"US",
    "sg:address":"701 Manatee Ave W",
    "sg:city":"Bradenton",
    "sg:classifiers":[
        {
            "category":"Health Services",
            "subcategory":"Doctor",
            "type":"Services"
        }
    ],
    "sg:phone":"+1 941 748 2455",
    "sg:postcode":"34205",
    "sg:province":"FL",
    "sg:tags":[
        "physician",
        "surgeon"
    ],
    "wof:name":"Ear Nose & Throat",
    "wof:placetype":"venue"
},
  "geometry": {"coordinates":[-82.56985299999999,27.495381],"type":"Point"}
}