{
  "type": "Feature",
  "properties": {
    "iso:country":"US",
    "sg:address":"649 91st Ave N",
    "sg:city":"Naples",
    "sg:classifiers":[
        {
            "category":"Local Transit",
            "type":"Transportation"
        }
    ],
    "sg:phone":"+1 239 598 4666",
    "sg:postcode":"34108",
    "sg:province":"FL",
    "sg:tags":[
        "limousine"
    ],
    "wof:name":"Rockefeller Limo Of Florida",
    "wof:placetype":"venue"
},
  "geometry": {"coordinates":[-81.810896,26.254365],"type":"Point"}
}