{
  "type": "Feature",
  "properties": {
    "iso:country":"US",
    "sg:address":"4504 30th St W",
    "sg:city":"Bradenton",
    "sg:classifiers":[
        {
            "category":"Manufacturing",
            "subcategory":"Building Materials",
            "type":"Manufacturing & Wholesale Goods"
        }
    ],
    "sg:phone":"+1 941 755 1591",
    "sg:postcode":"34207",
    "sg:province":"FL",
    "sg:tags":[
        "product",
        "mfg",
        "metal",
        "plastic"
    ],
    "wof:name":"Norandex",
    "wof:placetype":"venue"
},
  "geometry": {"coordinates":[-82.59179899999999,27.461939],"type":"Point"}
}