{
  "type": "Feature",
  "properties": {
    "addr:full":"900 SW 12th St Pompano Beach FL 33060",
    "addr:housenumber":"900",
    "addr:postcode":"33060",
    "addr:street":"Sw 12Th St",
    "iso:country":"US",
    "sg:address":"900 SW 12th St",
    "sg:city":"Pompano Beach",
    "sg:classifiers":[
        {
            "category":"Building & Trades",
            "subcategory":"Cleaning & Sanitation",
            "type":"Services"
        }
    ],
    "sg:phone":"+1 954 788 6629",
    "sg:postcode":"33060",
    "sg:province":"FL",
    "sg:tags":[
        "maintenance"
    ],
    "wof:name":"Broward Cleaning & Maintenance",
    "wof:placetype":"venue"
},
  "geometry": {"coordinates":[-80.135626,26.215045],"type":"Point"}
}