{
  "type": "Feature",
  "properties": {
    "addr:full":"526 Morning Side Dr Ponte Vedra Beach FL 32082",
    "addr:housenumber":"526",
    "addr:postcode":"32082",
    "addr:street":"Morning Side Dr",
    "iso:country":"US",
    "sg:address":"526 Morning Side Dr",
    "sg:city":"Ponte Vedra Beach",
    "sg:classifiers":[
        {
            "category":"Real Estate",
            "subcategory":"Real Estate Agent",
            "type":"Services"
        }
    ],
    "sg:phone":"+1 904 285 8321",
    "sg:postcode":"32082",
    "sg:province":"FL",
    "wof:name":"Jeannette Moore Inc",
    "wof:placetype":"venue"
},
  "geometry": {"coordinates":[-81.38150400000001,30.225677],"type":"Point"}
}