{
  "type": "Feature",
  "properties": {
    "addr:full":"210 5th Ave S St Petersburg FL 33701",
    "addr:housenumber":"210",
    "addr:postcode":"33701",
    "addr:street":"5Th Ave S",
    "iso:country":"US",
    "sg:address":"210 5th Ave S",
    "sg:city":"St Petersburg",
    "sg:classifiers":[
        {
            "category":"Real Estate",
            "subcategory":"Real Estate Operator",
            "type":"Services"
        }
    ],
    "sg:phone":"+1 727 822 6700",
    "sg:postcode":"33701",
    "sg:province":"FL",
    "sg:tags":[
        "apartment"
    ],
    "wof:name":"Hilltop Investments Corp",
    "wof:placetype":"venue"
},
  "geometry": {"coordinates":[-82.63693000000001,27.765637],"type":"Point"}
}