{
  "type": "Feature",
  "properties": {
    "iso:country":"US",
    "sg:address":"2506 S Macdill Ave Ste B",
    "sg:city":"Tampa",
    "sg:phone":"+1 813 831 1117",
    "sg:postcode":"33629",
    "sg:province":"FL",
    "wof:name":"Gianpiero's Pick Of The Vine",
    "wof:placetype":"venue"
},
  "geometry": {"coordinates":[-82.49356899999999,27.923128],"type":"Point"}
}