{
  "type": "Feature",
  "properties": {
    "iso:country":"US",
    "sg:address":"558 Heatherton Village",
    "sg:city":"Altamonte Springs",
    "sg:classifiers":[
        {
            "category":"Building & Trades",
            "subcategory":"Cleaning & Sanitation",
            "type":"Services"
        }
    ],
    "sg:phone":"+1 407 869 5941",
    "sg:postcode":"32714",
    "sg:province":"FL",
    "sg:tags":[
        "home"
    ],
    "wof:name":"Domestic Cleaning Service Inc",
    "wof:placetype":"venue"
},
  "geometry": {"coordinates":[-81.404796,28.668047],"type":"Point"}
}