{
  "type": "Feature",
  "properties": {
    "iso:country":"US",
    "sg:address":"471 S Nova Rd",
    "sg:city":"Ormond Beach",
    "sg:classifiers":[
        {
            "category":"Professional",
            "subcategory":"Accounting & Tax Preparation",
            "type":"Services"
        }
    ],
    "sg:phone":"+1 386 671 1601",
    "sg:postcode":"32174",
    "sg:province":"FL",
    "sg:tags":[
        "return"
    ],
    "wof:name":"H & R Block",
    "wof:placetype":"venue"
},
  "geometry": {"coordinates":[-81.08098200000001,29.270892],"type":"Point"}
}