{
  "type": "Feature",
  "properties": {
    "iso:country":"US",
    "sg:address":"1414 Lindrose St",
    "sg:city":"Jacksonville",
    "sg:classifiers":[
        {
            "category":"Freight",
            "type":"Transportation"
        }
    ],
    "sg:phone":"+1 904 356 9322",
    "sg:postcode":"32206",
    "sg:province":"FL",
    "sg:tags":[
        "specializing",
        "distance",
        "hauling",
        "long",
        "trucking",
        "heavy"
    ],
    "sg:website":"www.cypresstruck.com",
    "wof:name":"Cypress Truck Lines Inc",
    "wof:placetype":"venue"
},
  "geometry": {"coordinates":[-81.634897,30.365307],"type":"Point"}
}