{
  "type": "Feature",
  "properties": {
    "iso:country":"US",
    "sg:address":"2519 E Milmar Dr",
    "sg:city":"Sarasota",
    "sg:classifiers":[
        {
            "category":"Professional",
            "subcategory":"Business Services",
            "type":"Services"
        }
    ],
    "sg:phone":"+1 941 953 5032",
    "sg:postcode":"34237",
    "sg:province":"FL",
    "sg:tags":[
        "pool",
        "swimming"
    ],
    "wof:name":"Charles Wacha Pools",
    "wof:placetype":"venue"
},
  "geometry": {"coordinates":[-82.51861100000001,27.331235],"type":"Point"}
}