{
  "type": "Feature",
  "properties": {
    "addr:full":"2906 NE 20 Way Gainesville FL 32609",
    "addr:housenumber":"2906;20",
    "addr:postcode":"32609",
    "addr:street":"Ne",
    "iso:country":"US",
    "sg:address":"2906 NE 20 Way",
    "sg:city":"Gainesville",
    "sg:classifiers":[
        {
            "category":"Retail",
            "subcategory":"Auto Repair",
            "type":"Services"
        }
    ],
    "sg:phone":"+1 352 337 3966",
    "sg:postcode":"32609",
    "sg:province":"FL",
    "sg:tags":[
        "body",
        "automobile",
        "painting"
    ],
    "wof:name":"Southeast Customs & Collision",
    "wof:placetype":"venue"
},
  "geometry": {"coordinates":[-82.296762,29.679146],"type":"Point"}
}