{
  "type": "Feature",
  "properties": {
    "addr:full":"2650 Creighton Rd Pensacola FL 32504",
    "addr:housenumber":"2650",
    "addr:postcode":"32504",
    "addr:street":"Creighton Rd",
    "iso:country":"US",
    "sg:address":"2650 Creighton Rd",
    "sg:city":"Pensacola",
    "sg:classifiers":[
        {
            "category":"Personal",
            "subcategory":"Beauty Salon",
            "type":"Services"
        }
    ],
    "sg:phone":"+1 850 484 7872",
    "sg:postcode":"32504",
    "sg:province":"FL",
    "sg:tags":[
        "nail",
        "manicuring"
    ],
    "sg:website":"http://regalnails.com",
    "wof:name":"Regal Nails",
    "wof:placetype":"venue"
},
  "geometry": {"coordinates":[-87.192128,30.495153],"type":"Point"}
}