{
  "type": "Feature",
  "properties": {
    "iso:country":"US",
    "sg:address":"3515 NW 51st St",
    "sg:city":"Miami",
    "sg:classifiers":[
        {
            "category":"Wholesale",
            "subcategory":"Sporting Goods",
            "type":"Manufacturing & Wholesale Goods"
        }
    ],
    "sg:phone":"+1 305 633 5443",
    "sg:postcode":"33142",
    "sg:province":"FL",
    "sg:tags":[
        "tackle",
        "car",
        "product",
        "used",
        "fishing"
    ],
    "wof:name":"Herdez Corp",
    "wof:placetype":"venue"
},
  "geometry": {"coordinates":[-80.253002,25.820756],"type":"Point"}
}