{
  "type": "Feature",
  "properties": {
    "addr:full":"945 20th St S Saint Petersburg FL 33712",
    "addr:housenumber":"945",
    "addr:postcode":"33712",
    "addr:street":"20Th St S",
    "iso:country":"US",
    "sg:address":"945 20th St S",
    "sg:city":"Saint Petersburg",
    "sg:classifiers":[
        {
            "category":"Organizations",
            "subcategory":"Non-profit Organization",
            "type":"Services"
        }
    ],
    "sg:phone":"+1 727 894 4311",
    "sg:postcode":"33712",
    "sg:province":"FL",
    "sg:tags":[
        "social"
    ],
    "wof:name":"Mount Zion Human Services Inc",
    "wof:placetype":"venue"
},
  "geometry": {"coordinates":[-82.660037,27.759736],"type":"Point"}
}