{
  "type": "Feature",
  "properties": {
    "addr:full":"306 S 6th St Leesburg FL 34748",
    "addr:housenumber":"306",
    "addr:postcode":"34748",
    "addr:street":"S 6Th St",
    "iso:country":"US",
    "sg:address":"306 S 6th St",
    "sg:city":"Leesburg",
    "sg:classifiers":[
        {
            "category":"Utilities",
            "subcategory":"Natural Gas",
            "type":"Services"
        }
    ],
    "sg:phone":"+1 352 728 9840",
    "sg:postcode":"34748",
    "sg:province":"FL",
    "sg:tags":[
        "company"
    ],
    "wof:name":"City Of Leesburg Gas Dept",
    "wof:placetype":"venue"
},
  "geometry": {"coordinates":[-81.877982,28.808416],"type":"Point"}
}