{
  "type": "Feature",
  "properties": {
    "iso:country":"US",
    "sg:address":"3074 W 1st St",
    "sg:city":"Jacksonville",
    "sg:classifiers":[
        {
            "category":"Retail",
            "subcategory":"Car Wash",
            "type":"Services"
        }
    ],
    "sg:phone":"+1 904 389 7096",
    "sg:postcode":"32254",
    "sg:province":"FL",
    "sg:tags":[
        "carwash"
    ],
    "wof:name":"Skylar C Yoachum Pressure Wash",
    "wof:placetype":"venue"
},
  "geometry": {"coordinates":[-81.71931600000001,30.34017],"type":"Point"}
}