{
  "type": "Feature",
  "properties": {
    "iso:country":"US",
    "sg:address":"451 SW Ravenswood Ln",
    "sg:city":"Port St Lucie",
    "sg:classifiers":[
        {
            "category":"Organizations",
            "subcategory":"Community Association",
            "type":"Services"
        }
    ],
    "sg:phone":"+1 772 878 7514",
    "sg:postcode":"34983",
    "sg:province":"FL",
    "sg:tags":[
        "fraternal"
    ],
    "wof:name":"Knights Of Columbus",
    "wof:placetype":"venue"
},
  "geometry": {"coordinates":[-80.351625,27.314795],"type":"Point"}
}