{
  "type": "Feature",
  "properties": {
    "iso:country":"US",
    "sg:address":"1990 Rockledge Dr",
    "sg:city":"Rockledge",
    "sg:classifiers":[
        {
            "category":"Professional",
            "subcategory":"Lawyer & Legal Services",
            "type":"Services"
        }
    ],
    "sg:phone":"+1 321 637 1990",
    "sg:postcode":"32955",
    "sg:province":"FL",
    "sg:tags":[
        "attorney"
    ],
    "wof:name":"Charles Steinberg",
    "wof:placetype":"venue"
},
  "geometry": {"coordinates":[-80.695277,28.28992],"type":"Point"}
}