{
  "type": "Feature",
  "properties": {
    "iso:country":"US",
    "sg:address":"654 Orangewood Dr",
    "sg:city":"Dunedin",
    "sg:classifiers":[
        {
            "category":"Professional",
            "subcategory":"Business Services",
            "type":"Services"
        }
    ],
    "sg:phone":"+1 727 210 4444",
    "sg:postcode":"34698",
    "sg:province":"FL",
    "sg:tags":[
        "interior",
        "consultant",
        "design",
        "decorator"
    ],
    "wof:name":"24 Hour Decor",
    "wof:placetype":"venue"
},
  "geometry": {"coordinates":[-82.782343,27.99947],"type":"Point"}
}