{
  "type": "Feature",
  "properties": {
    "iso:country":"US",
    "sg:address":"7203 NW 84th St",
    "sg:city":"Fort Lauderdale",
    "sg:classifiers":[
        {
            "category":"Wholesale",
            "subcategory":"Drugs",
            "type":"Manufacturing & Wholesale Goods"
        }
    ],
    "sg:phone":"+1 954 721 4920",
    "sg:postcode":"33321",
    "sg:province":"FL",
    "wof:name":"J & L Products",
    "wof:placetype":"venue"
},
  "geometry": {"coordinates":[-80.247381,26.227748],"type":"Point"}
}