{
  "type": "Feature",
  "properties": {
    "addr:full":"23696 US Hwy 19 Clearwater FL 33765",
    "addr:postcode":"23696;33765",
    "addr:street":"Us Hwy 19",
    "iso:country":"US",
    "sg:address":"23696 US Hwy 19",
    "sg:city":"Clearwater",
    "sg:classifiers":[
        {
            "category":"Personal",
            "subcategory":"Beauty Salon",
            "type":"Services"
        }
    ],
    "sg:phone":"+1 727 797 0649",
    "sg:postcode":"33765",
    "sg:province":"FL",
    "sg:tags":[
        "shop"
    ],
    "wof:name":"Town Nails",
    "wof:placetype":"venue"
},
  "geometry": {"coordinates":[-82.72971,27.98705],"type":"Point"}
}