{
  "type": "Feature",
  "properties": {
    "iso:country":"US",
    "sg:address":"13915 Shady Shores Dr",
    "sg:city":"Tampa",
    "sg:classifiers":[
        {
            "category":"Wholesale",
            "subcategory":"Groceries",
            "type":"Manufacturing & Wholesale Goods"
        }
    ],
    "sg:phone":"+1 813 888 6068",
    "sg:postcode":"33613",
    "sg:province":"FL",
    "sg:tags":[
        "food",
        "product"
    ],
    "wof:name":"Jim Cody Distribution Inc",
    "wof:placetype":"venue"
},
  "geometry": {"coordinates":[-82.480797,28.076766],"type":"Point"}
}