{
  "type": "Feature",
  "properties": {
    "iso:country":"US",
    "sg:address":"3922 NW 32nd Ave",
    "sg:city":"Miami",
    "sg:classifiers":[
        {
            "category":"Building & Trades",
            "subcategory":"Plumbing",
            "type":"Services"
        }
    ],
    "sg:phone":"+1 305 638 9417",
    "sg:postcode":"33142",
    "sg:province":"FL",
    "sg:tags":[
        "mechanical",
        "contractor"
    ],
    "wof:name":"Sea-Air Mechanical Inc",
    "wof:placetype":"venue"
},
  "geometry": {"coordinates":[-80.248537,25.81149],"type":"Point"}
}