{
  "type": "Feature",
  "properties": {
    "addr:full":"17455 Biscayne Blvd Aventura FL 33160",
    "addr:housenumber":"17455",
    "addr:postcode":"33160",
    "addr:street":"Biscayne Blvd",
    "iso:country":"US",
    "sg:address":"17455 Biscayne Blvd",
    "sg:city":"Aventura",
    "sg:classifiers":[
        {
            "category":"Restaurant",
            "type":"Food & Drink"
        }
    ],
    "sg:phone":"+1 305 957 1966",
    "sg:postcode":"33160",
    "sg:province":"FL",
    "sg:tags":[
        "asian",
        "chinese",
        "pan"
    ],
    "sg:website":"www.pfchangs.com",
    "wof:name":"P.F. Chang's China Bistro",
    "wof:placetype":"venue"
},
  "geometry": {"coordinates":[-80.149131,25.937409],"type":"Point"}
}