{
  "type": "Feature",
  "properties": {
    "iso:country":"US",
    "sg:address":"3545 Shore Line Cir",
    "sg:city":"Palm Harbor",
    "sg:classifiers":[
        {
            "category":"Wholesale",
            "subcategory":"Non-durable Goods",
            "type":"Manufacturing & Wholesale Goods"
        }
    ],
    "sg:phone":"+1 727 789 2653",
    "sg:postcode":"34684",
    "sg:province":"FL",
    "wof:name":"Al Nasser Trading Inc",
    "wof:placetype":"venue"
},
  "geometry": {"coordinates":[-82.718343,28.089067],"type":"Point"}
}