{
  "type": "Feature",
  "properties": {
    "addr:full":"1530 Washington Avenue Miami Beach FL 33139",
    "addr:housenumber":"1530",
    "addr:postcode":"33139",
    "addr:street":"Washington Avenue",
    "iso:country":"US",
    "sg:address":"1530 Washington Avenue",
    "sg:city":"Miami Beach",
    "sg:classifiers":[
        {
            "category":"Travel",
            "subcategory":"Hotels & Motels",
            "type":"Entertainment"
        }
    ],
    "sg:phone":"+1 305 604 8887",
    "sg:postcode":"33139",
    "sg:province":"FL",
    "sg:website":"www.marriott.com",
    "wof:name":"Courtyard Miami Beach South Beach",
    "wof:placetype":"venue"
},
  "geometry": {"coordinates":[-80.132189,25.788084],"type":"Point"}
}