{
  "type": "Feature",
  "properties": {
    "addr:full":"6133 Arcade Ct Lake Worth FL 33463",
    "addr:housenumber":"6133",
    "addr:postcode":"33463",
    "addr:street":"Arcade Ct",
    "iso:country":"US",
    "sg:address":"6133 Arcade Ct",
    "sg:city":"Lake Worth",
    "sg:classifiers":[
        {
            "category":"Building & Trades",
            "subcategory":"Construction",
            "type":"Services"
        }
    ],
    "sg:phone":"+1 561 963 8875",
    "sg:postcode":"33463",
    "sg:province":"FL",
    "sg:tags":[
        "carpenter"
    ],
    "wof:name":"Theodore J Sollohub Carpentry",
    "wof:placetype":"venue"
},
  "geometry": {"coordinates":[-80.14017200000001,26.59983],"type":"Point"}
}