{
  "type": "Feature",
  "properties": {
    "addr:full":"800 Brickell Ave Miami FL 33131",
    "addr:housenumber":"800",
    "addr:postcode":"33131",
    "addr:street":"Brickell Ave",
    "iso:country":"US",
    "sg:address":"800 Brickell Ave",
    "sg:city":"Miami",
    "sg:classifiers":[
        {
            "category":"Banks & Credit Unions",
            "subcategory":"Bank",
            "type":"Services"
        }
    ],
    "sg:phone":"+1 305 358 6314",
    "sg:postcode":"33131",
    "sg:province":"FL",
    "sg:tags":[
        "saving",
        "commercial"
    ],
    "wof:name":"Total Bank",
    "wof:placetype":"venue"
},
  "geometry": {"coordinates":[-80.190781,25.76618],"type":"Point"}
}