{
  "type": "Feature",
  "properties": {
    "addr:full":"3790 Countryside Rd Sarasota FL 34233",
    "addr:housenumber":"3790",
    "addr:postcode":"34233",
    "addr:street":"Countryside Rd",
    "iso:country":"US",
    "sg:address":"3790 Countryside Rd",
    "sg:city":"Sarasota",
    "sg:classifiers":[
        {
            "category":"Shopping",
            "subcategory":"Clothing, Apparel, & Fashions",
            "type":"Retail Goods"
        }
    ],
    "sg:phone":"+1 941 927 6022",
    "sg:postcode":"34233",
    "sg:province":"FL",
    "wof:name":"Francine",
    "wof:placetype":"venue"
},
  "geometry": {"coordinates":[-82.49034399999999,27.277236],"type":"Point"}
}