{
  "type": "Feature",
  "properties": {
    "iso:country":"US",
    "sg:address":"9833 Fruitville Rd",
    "sg:city":"Sarasota",
    "sg:classifiers":[
        {
            "category":"Building & Trades",
            "subcategory":"Construction",
            "type":"Services"
        }
    ],
    "sg:phone":"+1 941 377 1348",
    "sg:postcode":"34240",
    "sg:province":"FL",
    "wof:name":"Mc Graw Construction Inc",
    "wof:placetype":"venue"
},
  "geometry": {"coordinates":[-82.383662,27.338732],"type":"Point"}
}