{
  "type": "Feature",
  "properties": {
    "iso:country":"US",
    "sg:address":"8751 W Broward Blvd",
    "sg:city":"Plantation",
    "sg:classifiers":[
        {
            "category":"Building & Trades",
            "subcategory":"Construction",
            "type":"Services"
        }
    ],
    "sg:phone":"+1 954 390 3911",
    "sg:postcode":"33324",
    "sg:province":"FL",
    "sg:tags":[
        "designer"
    ],
    "wof:name":"Design Safety Corp",
    "wof:placetype":"venue"
},
  "geometry": {"coordinates":[-80.26639900000001,26.120727],"type":"Point"}
}