{
  "type": "Feature",
  "properties": {
    "addr:full":"5217 Martin St Naples FL 34113",
    "addr:housenumber":"5217",
    "addr:postcode":"34113",
    "addr:street":"Martin St",
    "iso:country":"US",
    "sg:address":"5217 Martin St",
    "sg:city":"Naples",
    "sg:classifiers":[
        {
            "category":"Building & Trades",
            "subcategory":"Construction",
            "type":"Services"
        }
    ],
    "sg:phone":"+1 239 250 2669",
    "sg:postcode":"34113",
    "sg:province":"FL",
    "sg:tags":[
        "house",
        "carpentry",
        "r",
        "contractor"
    ],
    "wof:name":"Temple Construction of Naples",
    "wof:placetype":"venue"
},
  "geometry": {"coordinates":[-81.726359,26.088044],"type":"Point"}
}