{
  "type": "Feature",
  "properties": {
    "iso:country":"US",
    "sg:address":"1161 Sun Century Rd",
    "sg:city":"Naples",
    "sg:classifiers":[
        {
            "category":"Retail",
            "subcategory":"Auto Repair",
            "type":"Services"
        }
    ],
    "sg:phone":"+1 239 596 0946",
    "sg:postcode":"34110",
    "sg:province":"FL",
    "sg:tags":[
        "repairing",
        "automobile"
    ],
    "wof:name":"Affordable Auto & Tire Svc",
    "wof:placetype":"venue"
},
  "geometry": {"coordinates":[-81.794403,26.305574],"type":"Point"}
}