{
  "type": "Feature",
  "properties": {
    "iso:country":"US",
    "sg:address":"15465 SW 288th St",
    "sg:city":"Homestead",
    "sg:classifiers":[
        {
            "category":"Personal",
            "subcategory":"Beauty Salon",
            "type":"Services"
        }
    ],
    "sg:phone":"+1 305 248 7569",
    "sg:postcode":"33033",
    "sg:province":"FL",
    "wof:name":"Ajah Salon",
    "wof:placetype":"venue"
},
  "geometry": {"coordinates":[-80.442013,25.499454],"type":"Point"}
}