{
  "type": "Feature",
  "properties": {
    "iso:country":"US",
    "sg:address":"12970 59th St N",
    "sg:city":"West Palm Beach",
    "sg:classifiers":[
        {
            "category":"Professional",
            "subcategory":"Business Services",
            "type":"Services"
        }
    ],
    "sg:phone":"+1 561 795 2668",
    "sg:postcode":"33411",
    "sg:province":"FL",
    "sg:tags":[
        "water",
        "treatment"
    ],
    "wof:name":"AAA Water Systems",
    "wof:placetype":"venue"
},
  "geometry": {"coordinates":[-80.246526,26.764249],"type":"Point"}
}