{
  "type": "Feature",
  "properties": {
    "iso:country":"US",
    "sg:address":"2805 Clayton Rd",
    "sg:city":"Bonifay",
    "sg:classifiers":[
        {
            "category":"Personal",
            "subcategory":"Beauty Salon",
            "type":"Services"
        }
    ],
    "sg:phone":"+1 850 638 2803",
    "sg:postcode":"32425",
    "sg:province":"FL",
    "wof:name":"Daymakers Hair Salon",
    "wof:placetype":"venue"
},
  "geometry": {"coordinates":[-85.64131399999999,30.692756],"type":"Point"}
}