{
  "type": "Feature",
  "properties": {
    "iso:country":"US",
    "sg:address":"4800 First Coast Hwy",
    "sg:city":"Fernandina Beach",
    "sg:classifiers":[
        {
            "category":"Restaurant",
            "type":"Food & Drink"
        }
    ],
    "sg:phone":"+1 904 491 4393",
    "sg:postcode":"32034",
    "sg:province":"FL",
    "wof:name":"China Wok",
    "wof:placetype":"venue"
},
  "geometry": {"coordinates":[-81.45585,30.585792],"type":"Point"}
}