{
  "type": "Feature",
  "properties": {
    "addr:full":"1782 Old Summerwood Blvd Sarasota FL 34232",
    "addr:housenumber":"1782",
    "addr:postcode":"34232",
    "addr:street":"Old Summerwood Blvd",
    "iso:country":"US",
    "sg:address":"1782 Old Summerwood Blvd",
    "sg:city":"Sarasota",
    "sg:classifiers":[
        {
            "category":"Landmark",
            "subcategory":"Tourist Information",
            "type":"Public Place"
        },
        {
            "category":"Landmark",
            "subcategory":"Tourist Attraction",
            "type":"Public Place"
        }
    ],
    "sg:phone":"+1 941 379 0517",
    "sg:postcode":"34232",
    "sg:province":"FL",
    "sg:tags":[
        "tour",
        "promoter",
        "tours-operators",
        "sightseeing"
    ],
    "wof:name":"Reel Native Charters",
    "wof:placetype":"venue"
},
  "geometry": {"coordinates":[-82.455096,27.317948],"type":"Point"}
}