{
  "type": "Feature",
  "properties": {
    "iso:country":"US",
    "sg:address":"691 E 30th St",
    "sg:city":"Hialeah",
    "sg:classifiers":[
        {
            "category":"Communications",
            "subcategory":"Film & Video Production",
            "type":"Services"
        }
    ],
    "sg:phone":"+1 305 835 9323",
    "sg:postcode":"33013",
    "sg:province":"FL",
    "sg:tags":[
        "services-commercial"
    ],
    "sg:website":"http://www.twinsvideo.com",
    "wof:name":"Twins Video Productions",
    "wof:placetype":"venue"
},
  "geometry": {"coordinates":[-80.268686,25.84977],"type":"Point"}
}