{
  "type": "Feature",
  "properties": {
    "addr:full":"4227 SW 153rd Ct Miami FL 33185",
    "addr:housenumber":"4227",
    "addr:postcode":"33185",
    "addr:street":"Sw 153Rd Ct",
    "iso:country":"US",
    "sg:address":"4227 SW 153rd Ct",
    "sg:city":"Miami",
    "sg:classifiers":[
        {
            "category":"Organizations",
            "subcategory":"Non-profit Organization",
            "type":"Services"
        }
    ],
    "sg:phone":"+1 305 552 1522",
    "sg:postcode":"33185",
    "sg:province":"FL",
    "wof:name":"Comite Santiago Apostol Miami",
    "wof:placetype":"venue"
},
  "geometry": {"coordinates":[-80.442077,25.726699],"type":"Point"}
}