{
  "type": "Feature",
  "properties": {
    "addr:full":"4713 SW 72nd Ave Miami FL 33155",
    "addr:housenumber":"4713",
    "addr:postcode":"33155",
    "addr:street":"Sw 72Nd Ave",
    "iso:country":"US",
    "sg:address":"4713 SW 72nd Ave",
    "sg:city":"Miami",
    "sg:classifiers":[
        {
            "category":"Manufacturing",
            "subcategory":"Printing",
            "type":"Manufacturing & Wholesale Goods"
        }
    ],
    "sg:phone":"+1 305 665 9220",
    "sg:postcode":"33155",
    "sg:province":"FL",
    "sg:tags":[
        "printer"
    ],
    "wof:name":"Jasma Graphics Inc",
    "wof:placetype":"venue"
},
  "geometry": {"coordinates":[-80.310652,25.72603],"type":"Point"}
}