{
  "type": "Feature",
  "properties": {
    "iso:country":"US",
    "sg:address":"1301 Saratoga St",
    "sg:city":"Deland",
    "sg:classifiers":[
        {
            "category":"Professional",
            "type":"Services"
        }
    ],
    "sg:phone":"+1 386 736 7615",
    "sg:postcode":"32724",
    "sg:province":"FL",
    "sg:tags":[
        "establishment"
    ],
    "wof:name":"Palomar East",
    "wof:placetype":"venue"
},
  "geometry": {"coordinates":[-81.278166,29.061276],"type":"Point"}
}