{
  "type": "Feature",
  "properties": {
    "addr:full":"International Mall 1603 NW 107th Ave Miami FL 33172",
    "addr:housenumber":"1603",
    "addr:postcode":"33172",
    "addr:street":"Nw 107Th Ave",
    "iso:country":"US",
    "sg:address":"International Mall 1603 NW 107th Ave",
    "sg:city":"Miami",
    "sg:classifiers":[
        {
            "category":"Food & Beverages",
            "subcategory":"Candy",
            "type":"Retail Goods"
        }
    ],
    "sg:postcode":"33172",
    "sg:province":"FL",
    "sg:tags":[
        "dessert"
    ],
    "wof:name":"Churromania",
    "wof:placetype":"venue"
},
  "geometry": {"coordinates":[-80.368652,25.78884],"type":"Point"}
}