{
  "type": "Feature",
  "properties": {
    "iso:country":"US",
    "sg:address":"845 7th Ave",
    "sg:city":"Vero Beach",
    "sg:classifiers":[
        {
            "category":"Shopping",
            "subcategory":"Shoes",
            "type":"Retail Goods"
        }
    ],
    "sg:phone":"+1 772 567 3168",
    "sg:postcode":"32960",
    "sg:province":"FL",
    "wof:name":"Conreco Shoes",
    "wof:placetype":"venue"
},
  "geometry": {"coordinates":[-80.38733499999999,27.617524],"type":"Point"}
}