{
  "type": "Feature",
  "properties": {
    "iso:country":"US",
    "sg:address":"2601 S Tamiami Trl",
    "sg:city":"Sarasota",
    "sg:classifiers":[
        {
            "category":"Real Estate",
            "subcategory":"Real Estate Operator",
            "type":"Services"
        }
    ],
    "sg:phone":"+1 941 228 1694",
    "sg:postcode":"34239",
    "sg:province":"FL",
    "sg:tags":[
        "building",
        "apartment"
    ],
    "wof:name":"Steve Lozo Carpentry",
    "wof:placetype":"venue"
},
  "geometry": {"coordinates":[-82.52981699999999,27.310976],"type":"Point"}
}