{
  "type": "Feature",
  "properties": {
    "iso:country":"US",
    "sg:address":"5051 Pine Dr",
    "sg:city":"Boynton Beach",
    "sg:classifiers":[
        {
            "category":"Home & Garden",
            "subcategory":"Home Furnishings",
            "type":"Retail Goods"
        }
    ],
    "sg:phone":"+1 561 737 0930",
    "sg:postcode":"33437",
    "sg:province":"FL",
    "wof:name":"Tye Assoc Inc",
    "wof:placetype":"venue"
},
  "geometry": {"coordinates":[-80.126848,26.525798],"type":"Point"}
}