{
  "type": "Feature",
  "properties": {
    "iso:country":"US",
    "sg:address":"1519 N 69th Ave",
    "sg:city":"Pensacola",
    "sg:classifiers":[
        {
            "category":"Manufacturing",
            "subcategory":"Metals",
            "type":"Manufacturing & Wholesale Goods"
        }
    ],
    "sg:phone":"+1 850 457 4442",
    "sg:postcode":"32506",
    "sg:province":"FL",
    "sg:tags":[
        "metalwork",
        "architectural",
        "mfg"
    ],
    "wof:name":"Vernon Holmes",
    "wof:placetype":"venue"
},
  "geometry": {"coordinates":[-87.30432,30.431708],"type":"Point"}
}