{
  "type": "Feature",
  "properties": {
    "addr:full":"8351 49th St N Pinellas Park FL 33781",
    "addr:housenumber":"8351",
    "addr:postcode":"33781",
    "addr:street":"49Th St N",
    "iso:country":"US",
    "sg:address":"8351 49th St N",
    "sg:city":"Pinellas Park",
    "sg:classifiers":[
        {
            "category":"Retail",
            "subcategory":"Auto Repair",
            "type":"Services"
        }
    ],
    "sg:phone":"+1 727 544 2887",
    "sg:postcode":"33781",
    "sg:province":"FL",
    "sg:tags":[
        "body",
        "automobile",
        "top",
        "upholstery"
    ],
    "wof:name":"Ernie's Auto Trim",
    "wof:placetype":"venue"
},
  "geometry": {"coordinates":[-82.700006,27.847533],"type":"Point"}
}