{
  "type": "Feature",
  "properties": {
    "iso:country":"US",
    "sg:address":"2685 NW 105th Ave",
    "sg:city":"Doral",
    "sg:classifiers":[
        {
            "category":"Autos & Motor Vehicles",
            "subcategory":"Motorcycle Sales",
            "type":"Retail Goods"
        }
    ],
    "sg:phone":"+1 305 592 6677",
    "sg:postcode":"33172",
    "sg:province":"FL",
    "sg:tags":[
        "scooter"
    ],
    "wof:name":"American Scooter Intl",
    "wof:placetype":"venue"
},
  "geometry": {"coordinates":[-80.367341,25.798726],"type":"Point"}
}