{
  "type": "Feature",
  "properties": {
    "iso:country":"US",
    "sg:address":"7511 NW 73rd St",
    "sg:city":"Miami",
    "sg:classifiers":[
        {
            "category":"Professional",
            "type":"Services"
        }
    ],
    "sg:phone":"+1 305 260 2959",
    "sg:postcode":"33166",
    "sg:province":"FL",
    "sg:tags":[
        "establishment"
    ],
    "wof:name":"Amarillo",
    "wof:placetype":"venue"
},
  "geometry": {"coordinates":[-80.318118,25.839865],"type":"Point"}
}