{
  "type": "Feature",
  "properties": {
    "iso:country":"US",
    "sg:address":"1616 Vernon Dicks Dr",
    "sg:city":"Melbourne",
    "sg:classifiers":[
        {
            "category":"Building & Trades",
            "subcategory":"Landscaping Services",
            "type":"Services"
        }
    ],
    "sg:phone":"+1 321 259 1953",
    "sg:postcode":"32935",
    "sg:province":"FL",
    "wof:name":"Gary K Votava",
    "wof:placetype":"venue"
},
  "geometry": {"coordinates":[-80.6382,28.134065],"type":"Point"}
}