{
  "type": "Feature",
  "properties": {
    "iso:country":"US",
    "sg:address":"287 E Indiantown Rd",
    "sg:city":"Jupiter",
    "sg:classifiers":[
        {
            "category":"Restaurant",
            "type":"Food & Drink"
        }
    ],
    "sg:menulink":"http://www.allmenus.com/fl/jupiter/16278-too-bizaare/menu/",
    "sg:phone":"+1 561 745 6262",
    "sg:postcode":"33477",
    "sg:province":"FL",
    "sg:tags":[
        "food",
        "soup",
        "american",
        "salad",
        "pub"
    ],
    "wof:name":"Too Bizaare",
    "wof:placetype":"venue"
},
  "geometry": {"coordinates":[-80.086798,26.934054],"type":"Point"}
}