{
  "type": "Feature",
  "properties": {
    "iso:country":"US",
    "sg:address":"4204 George Ln",
    "sg:city":"West Palm Beach",
    "sg:classifiers":[
        {
            "category":"Local Transit",
            "type":"Transportation"
        }
    ],
    "sg:phone":"+1 561 688 2230",
    "sg:postcode":"33406",
    "sg:province":"FL",
    "sg:tags":[
        "limousine"
    ],
    "wof:name":"Consolidated Services Inc",
    "wof:placetype":"venue"
},
  "geometry": {"coordinates":[-80.10709300000001,26.67008],"type":"Point"}
}