{
  "type": "Feature",
  "properties": {
    "addr:full":"20595 Old Cutler Rd Miami FL 33189",
    "addr:housenumber":"20595",
    "addr:postcode":"33189",
    "addr:street":"Old Cutler Rd",
    "iso:country":"US",
    "sg:address":"20595 Old Cutler Rd",
    "sg:city":"Miami",
    "sg:classifiers":[
        {
            "category":"Cinema",
            "subcategory":"Movie Rental",
            "type":"Entertainment"
        }
    ],
    "sg:phone":"+1 786 293 0594",
    "sg:postcode":"33189",
    "sg:province":"FL",
    "sg:tags":[
        "leasing",
        "video",
        "disc",
        "tape"
    ],
    "wof:name":"Blockbuster Video",
    "wof:placetype":"venue"
},
  "geometry": {"coordinates":[-80.335954,25.578708],"type":"Point"}
}