{
  "type": "Feature",
  "properties": {
    "addr:full":"2475 Blanding Blvd Middleburg FL 32068",
    "addr:housenumber":"2475",
    "addr:postcode":"32068",
    "addr:street":"Blanding Blvd",
    "iso:country":"US",
    "sg:address":"2475 Blanding Blvd",
    "sg:city":"Middleburg",
    "sg:classifiers":[
        {
            "category":"Restaurant",
            "type":"Food & Drink"
        }
    ],
    "sg:menulink":"http://www.allmenus.com/fl/middleburg-clay-hill/71165-pizza-hut/menu/",
    "sg:phone":"+1 904 282 0909",
    "sg:postcode":"32068",
    "sg:province":"FL",
    "sg:tags":[
        "american",
        "pizza"
    ],
    "wof:name":"Pizza Hut",
    "wof:placetype":"venue"
},
  "geometry": {"coordinates":[-81.87023000000001,30.064704],"type":"Point"}
}