{
  "type": "Feature",
  "properties": {
    "iso:country":"US",
    "sg:address":"502 E Hillsborough Ave",
    "sg:city":"Tampa",
    "sg:classifiers":[
        {
            "category":"Coffee & Tea",
            "type":"Food & Drink"
        }
    ],
    "sg:menulink":"http://www.allmenus.com/fl/tampa/116988-starbucks-coffee/menu/",
    "sg:phone":"+1 813 231 4276",
    "sg:postcode":"33604",
    "sg:province":"FL",
    "sg:tags":[
        "american"
    ],
    "wof:name":"Starbucks Coffee",
    "wof:placetype":"venue"
},
  "geometry": {"coordinates":[-82.454937,27.996536],"type":"Point"}
}