{
  "type": "Feature",
  "properties": {
    "iso:country":"US",
    "sg:address":"190 N Sunset Dr",
    "sg:city":"Casselberry",
    "sg:classifiers":[
        {
            "category":"Shopping",
            "subcategory":"Florist",
            "type":"Retail Goods"
        }
    ],
    "sg:phone":"+1 407 339 0663",
    "sg:postcode":"32707",
    "sg:province":"FL",
    "wof:name":"Peddles Wedding Flowers",
    "wof:placetype":"venue"
},
  "geometry": {"coordinates":[-81.333583,28.678141],"type":"Point"}
}