{
  "type": "Feature",
  "properties": {
    "addr:full":"3125 4th St N St Petersburg FL 33704",
    "addr:housenumber":"3125",
    "addr:postcode":"33704",
    "addr:street":"4Th St N",
    "iso:country":"US",
    "sg:address":"3125 4th St N",
    "sg:city":"St Petersburg",
    "sg:classifiers":[
        {
            "category":"Shopping",
            "subcategory":"Bicycles & Sporting Goods",
            "type":"Retail Goods"
        }
    ],
    "sg:phone":"+1 727 822 2453",
    "sg:postcode":"33704",
    "sg:province":"FL",
    "sg:tags":[
        "parts",
        "retailer"
    ],
    "sg:website":"www.revolutionbikes.com",
    "wof:name":"Revolution Bicycles",
    "wof:placetype":"venue"
},
  "geometry": {"coordinates":[-82.638503,27.801008],"type":"Point"}
}