{
  "type": "Feature",
  "properties": {
    "addr:full":"1150 11th Ave NW Ruskin FL 33570",
    "addr:housenumber":"1150",
    "addr:postcode":"33570",
    "addr:street":"11Th Ave Nw",
    "iso:country":"US",
    "sg:address":"1150 11th Ave NW",
    "sg:city":"Ruskin",
    "sg:classifiers":[
        {
            "category":"Farming",
            "subcategory":"Farm",
            "type":"Manufacturing & Wholesale Goods"
        }
    ],
    "sg:phone":"+1 813 645 0294",
    "sg:postcode":"33570",
    "sg:province":"FL",
    "wof:name":"Artesian Farms Shop",
    "wof:placetype":"venue"
},
  "geometry": {"coordinates":[-82.451083,27.727933],"type":"Point"}
}