{
  "type": "Feature",
  "properties": {
    "iso:country":"US",
    "sg:address":"1784 NW 40th St",
    "sg:city":"Fort Lauderdale",
    "sg:classifiers":[
        {
            "category":"Home & Garden",
            "subcategory":"Garden Supply",
            "type":"Retail Goods"
        }
    ],
    "sg:phone":"+1 954 731 3886",
    "sg:postcode":"33309",
    "sg:province":"FL",
    "wof:name":"Waterworx Inc",
    "wof:placetype":"venue"
},
  "geometry": {"coordinates":[-80.167402,26.176588],"type":"Point"}
}