{
  "type": "Feature",
  "properties": {
    "addr:full":"1705 N Congress Ave Boynton Beach FL 33426",
    "addr:housenumber":"1705",
    "addr:postcode":"33426",
    "addr:street":"N Congress Ave",
    "iso:country":"US",
    "sg:address":"1705 N Congress Ave",
    "sg:city":"Boynton Beach",
    "sg:classifiers":[
        {
            "category":"Professional",
            "subcategory":"Management & Consulting",
            "type":"Services"
        }
    ],
    "sg:phone":"+1 561 733 4161",
    "sg:postcode":"33426",
    "sg:province":"FL",
    "sg:tags":[
        "consultant",
        "business"
    ],
    "wof:name":"Gumberg Asset Management",
    "wof:placetype":"venue"
},
  "geometry": {"coordinates":[-80.09078100000001,26.546558],"type":"Point"}
}