{
  "type": "Feature",
  "properties": {
    "addr:full":"5515 NW 72nd Ave Miami FL 33166",
    "addr:housenumber":"5515",
    "addr:postcode":"33166",
    "addr:street":"Nw 72Nd Ave",
    "iso:country":"US",
    "sg:address":"5515 NW 72nd Ave",
    "sg:city":"Miami",
    "sg:classifiers":[
        {
            "category":"Manufacturing",
            "subcategory":"Printing",
            "type":"Manufacturing & Wholesale Goods"
        }
    ],
    "sg:phone":"+1 305 888 4995",
    "sg:postcode":"33166",
    "sg:province":"FL",
    "sg:tags":[
        "lithographic",
        "commercial"
    ],
    "wof:name":"National Printing Network Inc",
    "wof:placetype":"venue"
},
  "geometry": {"coordinates":[-80.31359999999999,25.82382],"type":"Point"}
}