{
  "type": "Feature",
  "properties": {
    "addr:full":"1429 Don St Naples FL 34104",
    "addr:housenumber":"1429",
    "addr:postcode":"34104",
    "addr:street":"Don St",
    "iso:country":"US",
    "sg:address":"1429 Don St",
    "sg:city":"Naples",
    "sg:classifiers":[
        {
            "category":"Building & Trades",
            "subcategory":"Construction",
            "type":"Services"
        },
        {
            "category":"Retail",
            "subcategory":"Auto Repair",
            "type":"Services"
        }
    ],
    "sg:phone":"+1 239 643 9722",
    "sg:postcode":"34104",
    "sg:province":"FL",
    "sg:tags":[
        "machine",
        "automobile",
        "marble",
        "shop",
        "contractor"
    ],
    "wof:name":"Coastal Machine Inc",
    "wof:placetype":"venue"
},
  "geometry": {"coordinates":[-81.75290099999999,26.166453],"type":"Point"}
}