{
  "type": "Feature",
  "properties": {
    "iso:country":"US",
    "sg:address":"1001 SW 2nd Ave",
    "sg:city":"Boca Raton",
    "sg:classifiers":[
        {
            "category":"Restaurant",
            "type":"Food & Drink"
        }
    ],
    "sg:phone":"+1 561 391 9240",
    "sg:postcode":"33432",
    "sg:province":"FL",
    "wof:name":"Sal's Restaurant & Pizzeria",
    "wof:placetype":"venue"
},
  "geometry": {"coordinates":[-80.09138299999999,26.339485],"type":"Point"}
}