{
  "type": "Feature",
  "properties": {
    "addr:full":"1700 Latham Rd West Palm Beach FL 33409",
    "addr:housenumber":"1700",
    "addr:postcode":"33409",
    "addr:street":"Latham Rd",
    "iso:country":"US",
    "sg:address":"1700 Latham Rd",
    "sg:city":"West Palm Beach",
    "sg:classifiers":[
        {
            "category":"Shopping",
            "subcategory":"Gifts & Souvenirs",
            "type":"Retail Goods"
        }
    ],
    "sg:phone":"+1 561 697 3241",
    "sg:postcode":"33409",
    "sg:province":"FL",
    "sg:tags":[
        "party",
        "supply"
    ],
    "wof:name":"Wholesale Ruby",
    "wof:placetype":"venue"
},
  "geometry": {"coordinates":[-80.08230399999999,26.701141],"type":"Point"}
}