{
  "type": "Feature",
  "properties": {
    "iso:country":"US",
    "sg:address":"1207 N Parsons Ave",
    "sg:city":"Brandon",
    "sg:classifiers":[
        {
            "category":"Personal",
            "type":"Services"
        }
    ],
    "sg:phone":"+1 813 651 3700",
    "sg:postcode":"33510",
    "sg:province":"FL",
    "sg:tags":[
        "mover",
        "full",
        "storage"
    ],
    "wof:name":"Family Moving Of Brandon",
    "wof:placetype":"venue"
},
  "geometry": {"coordinates":[-82.285912,27.958968],"type":"Point"}
}