{
  "type": "Feature",
  "properties": {
    "iso:country":"US",
    "sg:address":"158 Marshside Dr",
    "sg:city":"St Augustine",
    "sg:classifiers":[
        {
            "category":"Building & Trades",
            "subcategory":"Landscaping Services",
            "type":"Services"
        }
    ],
    "sg:phone":"+1 904 471 5212",
    "sg:postcode":"32080",
    "sg:province":"FL",
    "sg:tags":[
        "lawn",
        "maintenance",
        "grounds"
    ],
    "sg:website":"www.marshcreek.com",
    "wof:name":"Marsh Creek Course Maintenance",
    "wof:placetype":"venue"
},
  "geometry": {"coordinates":[-81.280047,29.83912],"type":"Point"}
}