{
  "type": "Feature",
  "properties": {
    "iso:country":"US",
    "sg:address":"22553 Meridiana Dr",
    "sg:city":"Boca Raton",
    "sg:classifiers":[
        {
            "category":"Wholesale",
            "subcategory":"Medical Equipment & Supplies",
            "type":"Manufacturing & Wholesale Goods"
        }
    ],
    "sg:phone":"+1 561 750 7997",
    "sg:postcode":"33433",
    "sg:province":"FL",
    "sg:tags":[
        "optical"
    ],
    "wof:name":"Librae Optical Inc",
    "wof:placetype":"venue"
},
  "geometry": {"coordinates":[-80.167125,26.340839],"type":"Point"}
}