{
  "type": "Feature",
  "properties": {
    "addr:full":"6939 NE 3rd Ave Miami FL 33138",
    "addr:housenumber":"6939",
    "addr:postcode":"33138",
    "addr:street":"Ne 3Rd Ave",
    "iso:country":"US",
    "sg:address":"6939 NE 3rd Ave",
    "sg:city":"Miami",
    "sg:classifiers":[
        {
            "category":"Manufacturing",
            "subcategory":"Textiles",
            "type":"Manufacturing & Wholesale Goods"
        }
    ],
    "sg:phone":"+1 305 759 3603",
    "sg:postcode":"33138",
    "sg:province":"FL",
    "sg:tags":[
        "curtain",
        "fabric",
        "drapery"
    ],
    "wof:name":"Aventura Window Covers",
    "wof:placetype":"venue"
},
  "geometry": {"coordinates":[-80.190354,25.838595],"type":"Point"}
}