{
  "type": "Feature",
  "properties": {
    "addr:full":"5879 Moncrief Rd Jacksonville FL 32209",
    "addr:housenumber":"5879",
    "addr:postcode":"32209",
    "addr:street":"Moncrief Rd",
    "iso:country":"US",
    "sg:address":"5879 Moncrief Rd",
    "sg:city":"Jacksonville",
    "sg:classifiers":[
        {
            "category":"Retail",
            "subcategory":"Funeral Services",
            "type":"Services"
        }
    ],
    "sg:phone":"+1 904 765 6664",
    "sg:postcode":"32209",
    "sg:province":"FL",
    "sg:tags":[
        "director"
    ],
    "wof:name":"Davis Funeral Home",
    "wof:placetype":"venue"
},
  "geometry": {"coordinates":[-81.693455,30.378709],"type":"Point"}
}