{
  "type": "Feature",
  "properties": {
    "iso:country":"US",
    "sg:address":"7050 Seminole Pratt Whitney Rd",
    "sg:city":"Loxahatchee",
    "sg:classifiers":[
        {
            "category":"Shopping",
            "subcategory":"Jewelry",
            "type":"Retail Goods"
        }
    ],
    "sg:phone":"+1 561 753 3638",
    "sg:postcode":"33470",
    "sg:province":"FL",
    "sg:tags":[
        "jeweler"
    ],
    "wof:name":"Van Dell Jewelers Inc",
    "wof:placetype":"venue"
},
  "geometry": {"coordinates":[-80.294551,26.780902],"type":"Point"}
}