{
  "type": "Feature",
  "properties": {
    "iso:country":"US",
    "sg:address":"3407 S Ocean Blvd",
    "sg:city":"Boca Raton",
    "sg:classifiers":[
        {
            "category":"Organizations",
            "subcategory":"Community Association",
            "type":"Services"
        }
    ],
    "sg:phone":"+1 561 276 8592",
    "sg:postcode":"33487",
    "sg:province":"FL",
    "wof:name":"Clarendon Condominium Inc",
    "wof:placetype":"venue"
},
  "geometry": {"coordinates":[-80.06481599999999,26.41409],"type":"Point"}
}