{
  "type": "Feature",
  "properties": {
    "addr:full":"12501 W Linebaugh Ave Tampa FL 33626",
    "addr:housenumber":"12501",
    "addr:postcode":"33626",
    "addr:street":"W Linebaugh Ave",
    "iso:country":"US",
    "sg:address":"12501 W Linebaugh Ave",
    "sg:city":"Tampa",
    "sg:classifiers":[
        {
            "category":"Retail",
            "subcategory":"Veterinary Services",
            "type":"Services"
        }
    ],
    "sg:phone":"+1 813 855 8123",
    "sg:postcode":"33626",
    "sg:province":"FL",
    "sg:tags":[
        "veterinarian"
    ],
    "wof:name":"Country Chase Vet Clinic Jbst",
    "wof:placetype":"venue"
},
  "geometry": {"coordinates":[-82.62937100000001,28.055975],"type":"Point"}
}