{
  "type": "Feature",
  "properties": {
    "iso:country":"US",
    "sg:address":"7333 Gall Blvd",
    "sg:city":"Zephyrhills",
    "sg:classifiers":[
        {
            "category":"Restaurant",
            "type":"Food & Drink"
        }
    ],
    "sg:menulink":"http://www.allmenus.com/fl/zephyrhills/122780-quiznos-sub/menu/",
    "sg:phone":"+1 813 788 8445",
    "sg:postcode":"33541",
    "sg:province":"FL",
    "sg:tags":[
        "wrap",
        "american",
        "sandwich"
    ],
    "wof:name":"Quiznos Sub",
    "wof:placetype":"venue"
},
  "geometry": {"coordinates":[-82.188208,28.265045],"type":"Point"}
}