{
  "type": "Feature",
  "properties": {
    "iso:country":"US",
    "sg:address":"10101 NW 79th Ave",
    "sg:city":"Hialeah",
    "sg:classifiers":[
        {
            "category":"Manufacturing",
            "subcategory":"Printing",
            "type":"Manufacturing & Wholesale Goods"
        }
    ],
    "sg:phone":"+1 305 826 0700",
    "sg:postcode":"33016",
    "sg:province":"FL",
    "sg:tags":[
        "printer"
    ],
    "sg:website":"www.genesispress.com",
    "wof:name":"Rose Graphics",
    "wof:placetype":"venue"
},
  "geometry": {"coordinates":[-80.325658,25.864939],"type":"Point"}
}