{
  "type": "Feature",
  "properties": {
    "addr:full":"31133 US Hwy 19 N Palm Harbor FL 34684",
    "addr:postcode":"31133;34684",
    "addr:street":"Us Hwy 19 N",
    "iso:country":"US",
    "sg:address":"31133 US Hwy 19 N",
    "sg:city":"Palm Harbor",
    "sg:classifiers":[
        {
            "category":"Personal",
            "subcategory":"Beauty Salon",
            "type":"Services"
        }
    ],
    "sg:phone":"+1 727 785 8579",
    "sg:postcode":"34684",
    "sg:province":"FL",
    "wof:name":"Sophisticated Styles",
    "wof:placetype":"venue"
},
  "geometry": {"coordinates":[-82.73866,28.051993],"type":"Point"}
}