{
  "type": "Feature",
  "properties": {
    "addr:full":"600 Industrial Way Boynton Beach FL 33426",
    "addr:housenumber":"600",
    "addr:postcode":"33426",
    "addr:street":"Industrial Way",
    "iso:country":"US",
    "sg:address":"600 Industrial Way",
    "sg:city":"Boynton Beach",
    "sg:classifiers":[
        {
            "category":"Wholesale",
            "subcategory":"Medical Equipment & Supplies",
            "type":"Manufacturing & Wholesale Goods"
        },
        {
            "category":"Shopping",
            "type":"Retail Goods"
        }
    ],
    "sg:phone":"+1 561 540 9993",
    "sg:postcode":"33426",
    "sg:province":"FL",
    "sg:tags":[
        "electronics",
        "merchandise"
    ],
    "wof:name":"Zurigch Corp",
    "wof:placetype":"venue"
},
  "geometry": {"coordinates":[-80.07320300000001,26.555985],"type":"Point"}
}