{
  "type": "Feature",
  "properties": {
    "iso:country":"US",
    "sg:address":"6620 Dahlia Dr",
    "sg:city":"Hollywood",
    "sg:classifiers":[
        {
            "category":"Professional",
            "subcategory":"Management & Consulting",
            "type":"Services"
        }
    ],
    "sg:phone":"+1 954 963 4336",
    "sg:postcode":"33023",
    "sg:province":"FL",
    "sg:tags":[
        "business"
    ],
    "wof:name":"Coatings Consultants Tech",
    "wof:placetype":"venue"
},
  "geometry": {"coordinates":[-80.217555,25.977638],"type":"Point"}
}