{
  "type": "Feature",
  "properties": {
    "addr:full":"5912 Breckenridge Pkwy Tampa FL 33610",
    "addr:housenumber":"5912",
    "addr:postcode":"33610",
    "addr:street":"Breckenridge Pkwy",
    "iso:country":"US",
    "sg:address":"5912 Breckenridge Pkwy",
    "sg:city":"Tampa",
    "sg:classifiers":[
        {
            "category":"Professional",
            "type":"Services"
        }
    ],
    "sg:phone":"+1 813 739 5400",
    "sg:postcode":"33610",
    "sg:province":"FL",
    "sg:tags":[
        "establishment"
    ],
    "wof:name":"Primeair Carrier",
    "wof:placetype":"venue"
},
  "geometry": {"coordinates":[-82.358025,28.007448],"type":"Point"}
}