{
  "type": "Feature",
  "properties": {
    "iso:country":"US",
    "sg:address":"18818 Geraci Rd",
    "sg:city":"Lutz",
    "sg:classifiers":[
        {
            "category":"Manufacturing",
            "subcategory":"Furniture",
            "type":"Manufacturing & Wholesale Goods"
        }
    ],
    "sg:phone":"+1 813 949 3240",
    "sg:postcode":"33548",
    "sg:province":"FL",
    "sg:tags":[
        "mfg",
        "top",
        "wood",
        "counter"
    ],
    "wof:name":"C J's Top Shop",
    "wof:placetype":"venue"
},
  "geometry": {"coordinates":[-82.490903,28.150084],"type":"Point"}
}