{
  "type": "Feature",
  "properties": {
    "iso:country":"US",
    "sg:address":"820 W Oak St",
    "sg:city":"Kissimmee",
    "sg:classifiers":[
        {
            "category":"Health Services",
            "subcategory":"Doctor",
            "type":"Services"
        }
    ],
    "sg:phone":"+1 407 847 9100",
    "sg:postcode":"34741",
    "sg:province":"FL",
    "sg:tags":[
        "medical"
    ],
    "wof:name":"Mamsa Abdul R H MD Inc",
    "wof:placetype":"venue"
},
  "geometry": {"coordinates":[-81.413811,28.300815],"type":"Point"}
}