{
  "type": "Feature",
  "properties": {
    "iso:country":"US",
    "sg:address":"216 Robbins Rest Cir",
    "sg:city":"Davenport",
    "sg:classifiers":[
        {
            "category":"Professional",
            "type":"Services"
        }
    ],
    "sg:phone":"+1 863 420 8901",
    "sg:postcode":"33896",
    "sg:province":"FL",
    "wof:name":"Stone Creations",
    "wof:placetype":"venue"
},
  "geometry": {"coordinates":[-81.591212,28.24662],"type":"Point"}
}