{
  "type": "Feature",
  "properties": {
    "iso:country":"US",
    "sg:address":"4124 20th St W",
    "sg:city":"Bradenton",
    "sg:classifiers":[
        {
            "category":"Professional",
            "subcategory":"Research",
            "type":"Services"
        }
    ],
    "sg:phone":"+1 941 752 6330",
    "sg:postcode":"34205",
    "sg:province":"FL",
    "sg:tags":[
        "economic",
        "analysis"
    ],
    "wof:name":"Hirons & Assoc",
    "wof:placetype":"venue"
},
  "geometry": {"coordinates":[-82.581385,27.464436],"type":"Point"}
}