{
  "type": "Feature",
  "properties": {
    "iso:country":"US",
    "sg:address":"7006 SW 46th St",
    "sg:city":"Miami",
    "sg:classifiers":[
        {
            "category":"Home & Garden",
            "subcategory":"Home Furnishings",
            "type":"Retail Goods"
        },
        {
            "category":"Commercial Area",
            "type":"Public Place"
        },
        {
            "category":"Manufacturing",
            "subcategory":"Glass & Minerals",
            "type":"Manufacturing & Wholesale Goods"
        },
        {
            "category":"Manufacturing",
            "subcategory":"Building Materials",
            "type":"Manufacturing & Wholesale Goods"
        }
    ],
    "sg:phone":"+1 305 740 6200",
    "sg:postcode":"33155",
    "sg:province":"FL",
    "sg:tags":[
        "doors-glass",
        "door",
        "top",
        "glazier",
        "shower",
        "mirror",
        "front",
        "table",
        "enclosure",
        "store"
    ],
    "sg:website":"http://www.calusaglass.net",
    "wof:name":"Calusa Glass Industries",
    "wof:placetype":"venue"
},
  "geometry": {"coordinates":[-80.30767299999999,25.728008],"type":"Point"}
}