{
  "type": "Feature",
  "properties": {
    "iso:country":"US",
    "sg:address":"3061 NE 163rd St",
    "sg:city":"North Miami Beach",
    "sg:classifiers":[
        {
            "category":"Food & Beverages",
            "subcategory":"Candy",
            "type":"Retail Goods"
        }
    ],
    "sg:phone":"+1 305 940 5001",
    "sg:postcode":"33160",
    "sg:province":"FL",
    "sg:tags":[
        "dessert"
    ],
    "sg:website":"www.bubblesnice.com/",
    "wof:name":"Bubbles 'n Ice",
    "wof:placetype":"venue"
},
  "geometry": {"coordinates":[-80.139567,25.927215],"type":"Point"}
}