{
  "type": "Feature",
  "properties": {
    "iso:country":"US",
    "sg:address":"13690 SW 288th St",
    "sg:city":"Homestead",
    "sg:classifiers":[
        {
            "category":"Autos & Motor Vehicles",
            "subcategory":"Fuel & Gas Station",
            "type":"Retail Goods"
        }
    ],
    "sg:phone":"+1 305 246 4009",
    "sg:postcode":"33033",
    "sg:province":"FL",
    "sg:tags":[
        "gasoline",
        "station",
        "truck",
        "t",
        "utility"
    ],
    "wof:name":"U-Haul",
    "wof:placetype":"venue"
},
  "geometry": {"coordinates":[-80.40872,25.499589],"type":"Point"}
}