{
  "type": "Feature",
  "properties": {
    "iso:country":"US",
    "sg:address":"2817 Gloria Ct",
    "sg:city":"Clearwater",
    "sg:classifiers":[
        {
            "category":"Professional",
            "subcategory":"Business Services",
            "type":"Services"
        }
    ],
    "sg:phone":"+1 727 797 9347",
    "sg:postcode":"33761",
    "sg:province":"FL",
    "sg:tags":[
        "interior",
        "consultant",
        "design",
        "decorator"
    ],
    "wof:name":"Uninhibited Decor Inc",
    "wof:placetype":"venue"
},
  "geometry": {"coordinates":[-82.720771,28.011427],"type":"Point"}
}