{
  "type": "Feature",
  "properties": {
    "iso:country":"US",
    "sg:address":"1550 Doehler St",
    "sg:city":"St Augustine",
    "sg:classifiers":[
        {
            "category":"Building & Trades",
            "subcategory":"Construction",
            "type":"Services"
        }
    ],
    "sg:phone":"+1 904 824 4636",
    "sg:postcode":"32084",
    "sg:province":"FL",
    "sg:tags":[
        "home",
        "improvement"
    ],
    "wof:name":"W H Coleman & Son",
    "wof:placetype":"venue"
},
  "geometry": {"coordinates":[-81.33631800000001,29.908541],"type":"Point"}
}