{
  "type": "Feature",
  "properties": {
    "iso:country":"US",
    "sg:address":"215 4th Ave S",
    "sg:city":"Jacksonville Bch",
    "sg:classifiers":[
        {
            "category":"Shopping",
            "subcategory":"Used Merchandise",
            "type":"Retail Goods"
        }
    ],
    "sg:phone":"+1 904 270 8665",
    "sg:postcode":"32250",
    "sg:province":"FL",
    "sg:tags":[
        "antique"
    ],
    "wof:name":"Not Just Chairs",
    "wof:placetype":"venue"
},
  "geometry": {"coordinates":[-81.39087000000001,30.284489],"type":"Point"}
}