{
  "type": "Feature",
  "properties": {
    "iso:country":"US",
    "sg:address":"8696 Griffin Rd",
    "sg:city":"Cooper City",
    "sg:classifiers":[
        {
            "category":"Building & Trades",
            "subcategory":"Construction",
            "type":"Services"
        }
    ],
    "sg:phone":"+1 954 680 9066",
    "sg:postcode":"33328",
    "sg:province":"FL",
    "sg:tags":[
        "tile",
        "dealer"
    ],
    "wof:name":"Sixto's Tile Corp",
    "wof:placetype":"venue"
},
  "geometry": {"coordinates":[-80.26212,26.064464],"type":"Point"}
}