{
  "type": "Feature",
  "properties": {
    "iso:country":"US",
    "sg:address":"1015 Baars St",
    "sg:city":"Pensacola",
    "sg:classifiers":[
        {
            "category":"Organizations",
            "subcategory":"Religious Organization",
            "type":"Services"
        }
    ],
    "sg:phone":"+1 850 432 6517",
    "sg:postcode":"32501",
    "sg:province":"FL",
    "sg:tags":[
        "church"
    ],
    "wof:name":"Friendly Baptist Church",
    "wof:placetype":"venue"
},
  "geometry": {"coordinates":[-87.23086600000001,30.442356],"type":"Point"}
}