{
  "type": "Feature",
  "properties": {
    "addr:full":"195 Plantation Ave Tavernier FL 33070",
    "addr:housenumber":"195",
    "addr:postcode":"33070",
    "addr:street":"Plantation Ave",
    "iso:country":"US",
    "sg:address":"195 Plantation Ave",
    "sg:city":"Tavernier",
    "sg:classifiers":[
        {
            "category":"Building & Trades",
            "subcategory":"Equipment Rental",
            "type":"Services"
        }
    ],
    "sg:phone":"+1 305 852 1279",
    "sg:postcode":"33070",
    "sg:province":"FL",
    "wof:name":"Barefoot Houseboat Rental",
    "wof:placetype":"venue"
},
  "geometry": {"coordinates":[-80.539222,25.001495],"type":"Point"}
}