{
  "type": "Feature",
  "properties": {
    "iso:country":"US",
    "sg:address":"6780 Forest Hill Blvd",
    "sg:city":"Greenacres",
    "sg:classifiers":[
        {
            "category":"Restaurant",
            "type":"Food & Drink"
        }
    ],
    "sg:phone":"+1 561 439 4188",
    "sg:postcode":"33413",
    "sg:province":"FL",
    "sg:tags":[
        "eating"
    ],
    "wof:name":"China Panda Restaurant Inc",
    "wof:placetype":"venue"
},
  "geometry": {"coordinates":[-80.148996,26.651085],"type":"Point"}
}