{
  "type": "Feature",
  "properties": {
    "addr:full":"35236 Nancy Rd Callahan FL 32011",
    "addr:housenumber":"35236",
    "addr:postcode":"32011",
    "addr:street":"Nancy Rd",
    "iso:country":"US",
    "sg:address":"35236 Nancy Rd",
    "sg:city":"Callahan",
    "sg:classifiers":[
        {
            "category":"Shopping",
            "subcategory":"Beauty & Cosmetics",
            "type":"Retail Goods"
        }
    ],
    "sg:phone":"+1 904 879 7308",
    "sg:postcode":"32011",
    "sg:province":"FL",
    "sg:tags":[
        "equipment",
        "perfume",
        "salons-equipment",
        "supply"
    ],
    "sg:website":"http://www.marykay.com",
    "wof:name":"Mary Kay Cosmetics",
    "wof:placetype":"venue"
},
  "geometry": {"coordinates":[-81.86259699999999,30.560039],"type":"Point"}
}