{
  "type": "Feature",
  "properties": {
    "iso:country":"US",
    "sg:address":"2830 Saint Charles St",
    "sg:city":"Fort Myers",
    "sg:classifiers":[
        {
            "category":"Retail",
            "subcategory":"Auto Repair",
            "type":"Services"
        }
    ],
    "sg:phone":"+1 239 337 7377",
    "sg:postcode":"33916",
    "sg:province":"FL",
    "sg:tags":[
        "body",
        "shop"
    ],
    "wof:name":"Gaskin's Auto Body Repair",
    "wof:placetype":"venue"
},
  "geometry": {"coordinates":[-81.855698,26.635401],"type":"Point"}
}