{
  "type": "Feature",
  "properties": {
    "iso:country":"US",
    "sg:address":"3018 Bloomsbury Dr",
    "sg:city":"Kissimmee",
    "sg:classifiers":[
        {
            "category":"Building & Trades",
            "subcategory":"Construction",
            "type":"Services"
        }
    ],
    "sg:phone":"+1 407 396 1294",
    "sg:postcode":"34747",
    "sg:province":"FL",
    "sg:tags":[
        "contractor"
    ],
    "wof:name":"V & V Painting & Ceramic Tile",
    "wof:placetype":"venue"
},
  "geometry": {"coordinates":[-81.641857,28.338339],"type":"Point"}
}