{
  "type": "Feature",
  "properties": {
    "iso:country":"US",
    "sg:address":"8135 River Country Dr",
    "sg:city":"Weeki Wachee",
    "sg:classifiers":[
        {
            "category":"Professional",
            "subcategory":"Detective & Security Services",
            "type":"Services"
        }
    ],
    "sg:phone":"+1 352 596 7561",
    "sg:postcode":"34607",
    "sg:province":"FL",
    "sg:tags":[
        "investigator"
    ],
    "wof:name":"Mac Path Investigations",
    "wof:placetype":"venue"
},
  "geometry": {"coordinates":[-82.587512,28.510753],"type":"Point"}
}