{
  "type": "Feature",
  "properties": {
    "iso:country":"US",
    "sg:address":"6500 W 20th Ave",
    "sg:city":"Hialeah",
    "sg:classifiers":[
        {
            "category":"Education",
            "subcategory":"Dance Studio",
            "type":"Public Place"
        }
    ],
    "sg:phone":"+1 305 295 9590",
    "sg:postcode":"33016",
    "sg:province":"FL",
    "wof:name":"Show Stopper Studio",
    "wof:placetype":"venue"
},
  "geometry": {"coordinates":[-80.324197,25.881445],"type":"Point"}
}