{
  "type": "Feature",
  "properties": {
    "iso:country":"US",
    "sg:address":"1300 Marsh Landing Pkwy",
    "sg:city":"Jacksonville Bch",
    "sg:classifiers":[
        {
            "category":"Health Services",
            "subcategory":"Doctor",
            "type":"Services"
        }
    ],
    "sg:phone":"+1 904 273 3001",
    "sg:postcode":"32250",
    "sg:province":"FL",
    "sg:tags":[
        "dentist"
    ],
    "wof:name":"Marsh Landing Dental Care",
    "wof:placetype":"venue"
},
  "geometry": {"coordinates":[-81.39830000000001,30.255801],"type":"Point"}
}