{
  "type": "Feature",
  "properties": {
    "iso:country":"US",
    "sg:address":"399 Carolina Ave Ste 100",
    "sg:city":"Winter Park",
    "sg:classifiers":[
        {
            "category":"Professional",
            "subcategory":"Lawyer & Legal Services",
            "type":"Services"
        }
    ],
    "sg:phone":"+1 407 599 2266",
    "sg:postcode":"32789",
    "sg:province":"FL",
    "wof:name":"Pearson Karl E Atty",
    "wof:placetype":"venue"
},
  "geometry": {"coordinates":[-81.35489699999999,28.5987],"type":"Point"}
}