{
  "type": "Feature",
  "properties": {
    "addr:full":"7224 E Colonial Dr Orlando FL 32807",
    "addr:housenumber":"7224",
    "addr:postcode":"32807",
    "addr:street":"E Colonial Dr",
    "iso:country":"US",
    "sg:address":"7224 E Colonial Dr",
    "sg:city":"Orlando",
    "sg:classifiers":[
        {
            "category":"Autos & Motor Vehicles",
            "subcategory":"Automobile Sales",
            "type":"Retail Goods"
        }
    ],
    "sg:phone":"+1 407 382 9960",
    "sg:postcode":"32807",
    "sg:province":"FL",
    "sg:tags":[
        "car",
        "used",
        "dealer"
    ],
    "wof:name":"Motor Car Concepts II",
    "wof:placetype":"venue"
},
  "geometry": {"coordinates":[-81.290426,28.567734],"type":"Point"}
}