{
  "type": "Feature",
  "properties": {
    "iso:country":"US",
    "sg:address":"5995 S Pointe Blvd Ste 108",
    "sg:city":"Fort Myers",
    "sg:classifiers":[
        {
            "category":"Food & Beverages",
            "subcategory":"Liquor & Beverages",
            "type":"Retail Goods"
        }
    ],
    "sg:phone":"+1 239 437 4400",
    "sg:postcode":"33919",
    "sg:province":"FL",
    "sg:tags":[
        "beer",
        "spirit",
        "wine"
    ],
    "sg:website":"www.friendlyfrankies.com",
    "wof:name":"Friendly Frankie's Liquor Store",
    "wof:placetype":"venue"
},
  "geometry": {"coordinates":[-81.904099,26.5571],"type":"Point"}
}