{
  "type": "Feature",
  "properties": {
    "addr:full":"109 Taylor St Punta Gorda FL 33950",
    "addr:housenumber":"109",
    "addr:postcode":"33950",
    "addr:street":"Taylor St",
    "iso:country":"US",
    "sg:address":"109 Taylor St",
    "sg:city":"Punta Gorda",
    "sg:classifiers":[
        {
            "category":"Banks & Credit Unions",
            "subcategory":"Investment Brokerage",
            "type":"Services"
        },
        {
            "category":"Professional",
            "subcategory":"Management & Consulting",
            "type":"Services"
        }
    ],
    "sg:phone":"+1 941 505 0305",
    "sg:postcode":"33950",
    "sg:province":"FL",
    "sg:tags":[
        "consultant",
        "planning",
        "financial"
    ],
    "wof:name":"Allstate Financial",
    "wof:placetype":"venue"
},
  "geometry": {"coordinates":[-82.052134,26.936105],"type":"Point"}
}