{
  "type": "Feature",
  "properties": {
    "addr:full":"2015 Lisenby Ave Panama City FL 32405",
    "addr:housenumber":"2015",
    "addr:postcode":"32405",
    "addr:street":"Lisenby Ave",
    "iso:country":"US",
    "sg:address":"2015 Lisenby Ave",
    "sg:city":"Panama City",
    "sg:classifiers":[
        {
            "category":"Building & Trades",
            "subcategory":"Landscaping Services",
            "type":"Services"
        }
    ],
    "sg:phone":"+1 850 763 2230",
    "sg:postcode":"32405",
    "sg:province":"FL",
    "sg:tags":[
        "landscape",
        "contractor"
    ],
    "wof:name":"Southeastern Outdoor Mgmt",
    "wof:placetype":"venue"
},
  "geometry": {"coordinates":[-85.683665,30.185479],"type":"Point"}
}