{
  "type": "Feature",
  "properties": {
    "iso:country":"US",
    "sg:address":"6813 Spencer Cir",
    "sg:city":"Tampa",
    "sg:classifiers":[
        {
            "category":"Real Estate",
            "subcategory":"Real Estate Operator",
            "type":"Services"
        }
    ],
    "sg:phone":"+1 813 626 6997",
    "sg:postcode":"33610",
    "sg:province":"FL",
    "sg:tags":[
        "building",
        "nonresidential"
    ],
    "wof:name":"Millie Heym",
    "wof:placetype":"venue"
},
  "geometry": {"coordinates":[-82.376571,27.992986],"type":"Point"}
}