{
  "type": "Feature",
  "properties": {
    "iso:country":"US",
    "sg:address":"1497 Market St",
    "sg:city":"Tallahassee",
    "sg:classifiers":[
        {
            "category":"Education",
            "subcategory":"Vocational School",
            "type":"Public Place"
        }
    ],
    "sg:phone":"+1 850 906 0007",
    "sg:postcode":"32312",
    "sg:province":"FL",
    "sg:tags":[
        "training",
        "computer",
        "software"
    ],
    "wof:name":"Productivity Point",
    "wof:placetype":"venue"
},
  "geometry": {"coordinates":[-84.249605,30.505972],"type":"Point"}
}