{
  "type": "Feature",
  "properties": {
    "iso:country":"US",
    "sg:address":"1399 Kass Cir",
    "sg:city":"Spring Hill",
    "sg:classifiers":[
        {
            "category":"Professional",
            "subcategory":"Management & Consulting",
            "type":"Services"
        },
        {
            "category":"Real Estate",
            "subcategory":"Real Estate Operator",
            "type":"Services"
        }
    ],
    "sg:phone":"+1 352 683 0320",
    "sg:postcode":"34606",
    "sg:province":"FL",
    "sg:tags":[
        "building",
        "consultant",
        "business",
        "nonresidential"
    ],
    "wof:name":"L & I Management Corporation",
    "wof:placetype":"venue"
},
  "geometry": {"coordinates":[-82.596514,28.453378],"type":"Point"}
}