{
  "type": "Feature",
  "properties": {
    "iso:country":"US",
    "sg:address":"8154 103rd St",
    "sg:city":"Jacksonville",
    "sg:classifiers":[
        {
            "category":"Retail",
            "subcategory":"Auto Repair",
            "type":"Services"
        }
    ],
    "sg:phone":"+1 904 317 8220",
    "sg:postcode":"32210",
    "sg:province":"FL",
    "sg:tags":[
        "repairing",
        "automobile"
    ],
    "wof:name":"Prestige Auto Imports",
    "wof:placetype":"venue"
},
  "geometry": {"coordinates":[-81.784645,30.247993],"type":"Point"}
}