{
  "type": "Feature",
  "properties": {
    "iso:country":"US",
    "sg:address":"9763 NW 41st St",
    "sg:city":"Doral",
    "sg:classifiers":[
        {
            "category":"Banks & Credit Unions",
            "subcategory":"Bank",
            "type":"Services"
        }
    ],
    "sg:phone":"+1 786 464 1616",
    "sg:postcode":"33178",
    "sg:province":"FL",
    "sg:tags":[
        "loan",
        "real estate"
    ],
    "wof:name":"Countrywide Home Loans",
    "wof:placetype":"venue"
},
  "geometry": {"coordinates":[-80.35523499999999,25.811729],"type":"Point"}
}