{
  "type": "Feature",
  "properties": {
    "iso:country":"US",
    "sg:address":"1918 Overview Dr",
    "sg:city":"New Port Richey",
    "sg:classifiers":[
        {
            "category":"Home & Garden",
            "subcategory":"Building Materials",
            "type":"Retail Goods"
        }
    ],
    "sg:phone":"+1 727 938 6315",
    "sg:postcode":"34655",
    "sg:province":"FL",
    "sg:tags":[
        "door"
    ],
    "wof:name":"Parker Doors",
    "wof:placetype":"venue"
},
  "geometry": {"coordinates":[-82.705685,28.186534],"type":"Point"}
}