{
  "type": "Feature",
  "properties": {
    "addr:full":"7850 128th St Seminole FL 33776",
    "addr:housenumber":"7850",
    "addr:postcode":"33776",
    "addr:street":"128Th St",
    "iso:country":"US",
    "sg:address":"7850 128th St",
    "sg:city":"Seminole",
    "sg:classifiers":[
        {
            "category":"Local Transit",
            "type":"Transportation"
        }
    ],
    "sg:phone":"+1 727 541 4354",
    "sg:postcode":"33776",
    "sg:province":"FL",
    "sg:tags":[
        "limousine"
    ],
    "wof:name":"Paradise Limousine Svc",
    "wof:placetype":"venue"
},
  "geometry": {"coordinates":[-82.815865,27.844684],"type":"Point"}
}