{
  "type": "Feature",
  "properties": {
    "iso:country":"US",
    "sg:address":"756 N Sun Dr",
    "sg:city":"Lake Mary",
    "sg:classifiers":[
        {
            "category":"Banks & Credit Unions",
            "subcategory":"Financial Services",
            "type":"Services"
        }
    ],
    "sg:phone":"+1 407 805 9332",
    "sg:postcode":"32746",
    "sg:province":"FL",
    "sg:tags":[
        "company",
        "holding"
    ],
    "wof:name":"Gim of Seminole County Inc",
    "wof:placetype":"venue"
},
  "geometry": {"coordinates":[-81.348984,28.75732],"type":"Point"}
}