{
  "type": "Feature",
  "properties": {
    "addr:full":"5555 NE 2nd Ave Miami FL 33137",
    "addr:housenumber":"5555",
    "addr:postcode":"33137",
    "addr:street":"Ne 2Nd Ave",
    "iso:country":"US",
    "sg:address":"5555 NE 2nd Ave",
    "sg:city":"Miami",
    "sg:classifiers":[
        {
            "category":"Restaurant",
            "type":"Food & Drink"
        },
        {
            "category":"Food & Beverages",
            "subcategory":"Meat & Fish",
            "type":"Retail Goods"
        }
    ],
    "sg:phone":"+1 305 757 5056",
    "sg:postcode":"33137",
    "sg:province":"FL",
    "sg:tags":[
        "seafood",
        "market"
    ],
    "wof:name":"Fish Corner",
    "wof:placetype":"venue"
},
  "geometry": {"coordinates":[-80.191704,25.82707],"type":"Point"}
}