{
  "type": "Feature",
  "properties": {
    "iso:country":"US",
    "sg:address":"4205 W Colonial Dr",
    "sg:city":"Orlando",
    "sg:classifiers":[
        {
            "category":"Retail",
            "subcategory":"Auto Repair",
            "type":"Services"
        }
    ],
    "sg:phone":"+1 407 294 2006",
    "sg:postcode":"32808",
    "sg:province":"FL",
    "sg:tags":[
        "repairing",
        "automobile"
    ],
    "wof:name":"Sports & Import Svc",
    "wof:placetype":"venue"
},
  "geometry": {"coordinates":[-81.432586,28.552687],"type":"Point"}
}