{
  "type": "Feature",
  "properties": {
    "iso:country":"US",
    "sg:address":"3290 US Hwy 27",
    "sg:city":"Fruitland Park",
    "sg:classifiers":[
        {
            "category":"Banks & Credit Unions",
            "subcategory":"Bank",
            "type":"Services"
        }
    ],
    "sg:phone":"+1 352 787 2028",
    "sg:postcode":"34731",
    "sg:province":"FL",
    "wof:name":"Sun Trust Bank",
    "wof:placetype":"venue"
},
  "geometry": {"coordinates":[-81.89923400000001,28.847084],"type":"Point"}
}