{
  "type": "Feature",
  "properties": {
    "iso:country":"US",
    "sg:address":"2421 Aloma Ave",
    "sg:city":"Winter Park",
    "sg:classifiers":[
        {
            "category":"Insurance",
            "subcategory":"Insurance Agent",
            "type":"Services"
        }
    ],
    "sg:phone":"+1 407 975 7526",
    "sg:postcode":"32792",
    "sg:province":"FL",
    "wof:name":"Aegis",
    "wof:placetype":"venue"
},
  "geometry": {"coordinates":[-81.323714,28.600706],"type":"Point"}
}