{
  "type": "Feature",
  "properties": {
    "addr:full":"3955 NW 35 St Gainesville FL 32605",
    "addr:housenumber":"3955",
    "addr:postcode":"32605",
    "addr:street":"Nw 35 St",
    "iso:country":"US",
    "sg:address":"3955 NW 35 St",
    "sg:city":"Gainesville",
    "sg:classifiers":[
        {
            "category":"Wholesale",
            "subcategory":"Vending Machines",
            "type":"Manufacturing & Wholesale Goods"
        }
    ],
    "sg:phone":"+1 352 378 4369",
    "sg:postcode":"32605",
    "sg:province":"FL",
    "sg:tags":[
        "operator"
    ],
    "wof:name":"Gator Vending",
    "wof:placetype":"venue"
},
  "geometry": {"coordinates":[-82.374689,29.688861],"type":"Point"}
}