{
  "type": "Feature",
  "properties": {
    "iso:country":"US",
    "sg:address":"13909 N Dale Mabry Hwy",
    "sg:city":"Tampa",
    "sg:classifiers":[
        {
            "category":"Personal",
            "subcategory":"Beauty Salon",
            "type":"Services"
        }
    ],
    "sg:phone":"+1 813 964 9268",
    "sg:postcode":"33618",
    "sg:province":"FL",
    "wof:name":"Anu Medispa",
    "wof:placetype":"venue"
},
  "geometry": {"coordinates":[-82.506648,28.074668],"type":"Point"}
}