{
  "type": "Feature",
  "properties": {
    "iso:country":"US",
    "sg:address":"5445 NW 72nd Ave",
    "sg:city":"Miami",
    "sg:classifiers":[
        {
            "category":"Home & Garden",
            "subcategory":"Furniture",
            "type":"Retail Goods"
        }
    ],
    "sg:phone":"+1 305 888 0774",
    "sg:postcode":"33166",
    "sg:province":"FL",
    "sg:tags":[
        "furniture-wholesale",
        "manufacturer"
    ],
    "sg:website":"www.caribbeanfiberglass.com",
    "wof:name":"Caribbean Fiberglass Products Inc",
    "wof:placetype":"venue"
},
  "geometry": {"coordinates":[-80.313563,25.822944],"type":"Point"}
}