{
  "type": "Feature",
  "properties": {
    "addr:full":"8994 Hickory Hammock Rd Milton FL 32583",
    "addr:housenumber":"8994",
    "addr:postcode":"32583",
    "addr:street":"Hickory Hammock Rd",
    "iso:country":"US",
    "sg:address":"8994 Hickory Hammock Rd",
    "sg:city":"Milton",
    "sg:classifiers":[
        {
            "category":"Building & Trades",
            "subcategory":"Construction",
            "type":"Services"
        }
    ],
    "sg:phone":"+1 850 232 1615",
    "sg:postcode":"32583",
    "sg:province":"FL",
    "sg:tags":[
        "residential",
        "commercial"
    ],
    "wof:name":"Johnny Pitts Construction",
    "wof:placetype":"venue"
},
  "geometry": {"coordinates":[-86.943484,30.594751],"type":"Point"}
}