{
  "type": "Feature",
  "properties": {
    "iso:country":"US",
    "sg:address":"698 W 84th St",
    "sg:city":"Hialeah",
    "sg:classifiers":[
        {
            "category":"Retail",
            "subcategory":"Auto Repair",
            "type":"Services"
        }
    ],
    "sg:phone":"+1 305 558 4351",
    "sg:postcode":"33014",
    "sg:province":"FL",
    "wof:name":"Lakes Auto Center",
    "wof:placetype":"venue"
},
  "geometry": {"coordinates":[-80.298103,25.8988],"type":"Point"}
}