{
  "type": "Feature",
  "properties": {
    "iso:country":"US",
    "sg:address":"2930 W 23rd St",
    "sg:city":"Sanford",
    "sg:classifiers":[
        {
            "category":"Building & Trades",
            "subcategory":"Construction",
            "type":"Services"
        }
    ],
    "sg:phone":"+1 407 323 3857",
    "sg:postcode":"32771",
    "sg:province":"FL",
    "sg:tags":[
        "concrete",
        "contractor"
    ],
    "wof:name":"DOT Concrete Inc",
    "wof:placetype":"venue"
},
  "geometry": {"coordinates":[-81.301376,28.791689],"type":"Point"}
}