{
  "type": "Feature",
  "properties": {
    "iso:country":"US",
    "sg:address":"108 Coastal Hwy",
    "sg:city":"Panacea",
    "sg:classifiers":[
        {
            "category":"Professional",
            "subcategory":"Research",
            "type":"Services"
        }
    ],
    "sg:phone":"+1 850 984 2966",
    "sg:postcode":"32346",
    "sg:province":"FL",
    "sg:tags":[
        "environmental",
        "ecological"
    ],
    "wof:name":"Bonnie Holub & Assoc",
    "wof:placetype":"venue"
},
  "geometry": {"coordinates":[-84.384213,29.982456],"type":"Point"}
}