{
  "type": "Feature",
  "properties": {
    "iso:country":"US",
    "sg:address":"8192 Philatelic Dr",
    "sg:city":"Spring Hill",
    "sg:classifiers":[
        {
            "category":"Home & Garden",
            "subcategory":"Carpets & Floor Coverings",
            "type":"Retail Goods"
        }
    ],
    "sg:phone":"+1 352 686 1238",
    "sg:postcode":"34606",
    "sg:province":"FL",
    "wof:name":"Edwin Lauer Crpt Installation",
    "wof:placetype":"venue"
},
  "geometry": {"coordinates":[-82.582797,28.485159],"type":"Point"}
}