{
  "type": "Feature",
  "properties": {
    "iso:country":"US",
    "sg:address":"6701 78th St",
    "sg:city":"Riverview",
    "sg:classifiers":[
        {
            "category":"Autos & Motor Vehicles",
            "subcategory":"Auto Supplies",
            "type":"Retail Goods"
        },
        {
            "category":"Wholesale",
            "subcategory":"Auto Parts",
            "type":"Manufacturing & Wholesale Goods"
        },
        {
            "category":"Retail",
            "subcategory":"Auto Repair",
            "type":"Services"
        }
    ],
    "sg:phone":"+1 813 677 4431",
    "sg:postcode":"33578",
    "sg:province":"FL",
    "sg:tags":[
        "transmission",
        "automobile",
        "accessory",
        "rebuilt-wholesale",
        "supplies-used",
        "rebuilt",
        "manufacturer"
    ],
    "sg:website":"http://www.gagelsautoparts.com",
    "wof:name":"Gagels Auto Parts Inc",
    "wof:placetype":"venue"
},
  "geometry": {"coordinates":[-82.368988,27.88253],"type":"Point"}
}