{
  "type": "Feature",
  "properties": {
    "addr:full":"8363 W Sunrise Blvd Plantation FL 33322",
    "addr:housenumber":"8363",
    "addr:postcode":"33322",
    "addr:street":"W Sunrise Blvd",
    "iso:country":"US",
    "sg:address":"8363 W Sunrise Blvd",
    "sg:city":"Plantation",
    "sg:classifiers":[
        {
            "category":"Shopping",
            "subcategory":"Bicycles & Sporting Goods",
            "type":"Retail Goods"
        }
    ],
    "sg:phone":"+1 954 473 1905",
    "sg:postcode":"33322",
    "sg:province":"FL",
    "sg:tags":[
        "equipment",
        "tennis",
        "supply"
    ],
    "wof:name":"Aardvark Tennis",
    "wof:placetype":"venue"
},
  "geometry": {"coordinates":[-80.25822700000001,26.148542],"type":"Point"}
}