{
  "type": "Feature",
  "properties": {
    "iso:country":"US",
    "sg:address":"236 S Dixie Hwy E",
    "sg:city":"Pompano Beach",
    "sg:classifiers":[
        {
            "category":"Manufacturing",
            "subcategory":"Tools & Machinery",
            "type":"Manufacturing & Wholesale Goods"
        }
    ],
    "sg:phone":"+1 954 783 0652",
    "sg:postcode":"33060",
    "sg:province":"FL",
    "sg:tags":[
        "compressor"
    ],
    "wof:name":"Budget Air Compressors",
    "wof:placetype":"venue"
},
  "geometry": {"coordinates":[-80.127628,26.227343],"type":"Point"}
}