{
  "type": "Feature",
  "properties": {
    "iso:country":"US",
    "sg:address":"2434 S Palmetto Ave",
    "sg:city":"Sanford",
    "sg:classifiers":[
        {
            "category":"Taxi",
            "type":"Transportation"
        }
    ],
    "sg:phone":"+1 407 324 2240",
    "sg:postcode":"32771",
    "sg:province":"FL",
    "sg:tags":[
        "taxicab"
    ],
    "wof:name":"Statewide Taxi Bill & Barb",
    "wof:placetype":"venue"
},
  "geometry": {"coordinates":[-81.26624099999999,28.786861],"type":"Point"}
}