{
  "type": "Feature",
  "properties": {
    "iso:country":"US",
    "sg:address":"440 Brandywine Dr",
    "sg:city":"Valrico",
    "sg:classifiers":[
        {
            "category":"Shopping",
            "subcategory":"Catalog Store",
            "type":"Retail Goods"
        }
    ],
    "sg:phone":"+1 813 571 9762",
    "sg:postcode":"33594",
    "sg:province":"FL",
    "sg:tags":[
        "mail",
        "house"
    ],
    "wof:name":"Internet Marketing Associates",
    "wof:placetype":"venue"
},
  "geometry": {"coordinates":[-82.24694100000001,27.944559],"type":"Point"}
}