{
  "type": "Feature",
  "properties": {
    "iso:country":"US",
    "sg:address":"7855 NW 12th St",
    "sg:city":"Doral",
    "sg:classifiers":[
        {
            "category":"Building & Trades",
            "subcategory":"Construction",
            "type":"Services"
        }
    ],
    "sg:phone":"+1 305 639 6015",
    "sg:postcode":"33126",
    "sg:province":"FL",
    "sg:tags":[
        "designer"
    ],
    "wof:name":"G & G Design",
    "wof:placetype":"venue"
},
  "geometry": {"coordinates":[-80.323002,25.782696],"type":"Point"}
}