{
  "type": "Feature",
  "properties": {
    "addr:full":"412 Brittany I Delray Beach FL 33446",
    "addr:housenumber":"412",
    "addr:postcode":"33446",
    "addr:street":"Brittany I",
    "iso:country":"US",
    "sg:address":"412 Brittany I",
    "sg:city":"Delray Beach",
    "sg:classifiers":[
        {
            "category":"Local Transit",
            "type":"Transportation"
        }
    ],
    "sg:phone":"+1 561 499 7538",
    "sg:postcode":"33446",
    "sg:province":"FL",
    "sg:tags":[
        "limousine"
    ],
    "wof:name":"M & M Car Svc Inc",
    "wof:placetype":"venue"
},
  "geometry": {"coordinates":[-80.154039,26.44403],"type":"Point"}
}