{
  "type": "Feature",
  "properties": {
    "addr:full":"14175 SW 140th St Miami FL 33186",
    "addr:housenumber":"14175",
    "addr:postcode":"33186",
    "addr:street":"Sw 140Th St",
    "iso:country":"US",
    "sg:address":"14175 SW 140th St",
    "sg:city":"Miami",
    "sg:classifiers":[
        {
            "category":"Professional",
            "subcategory":"Business Services",
            "type":"Services"
        }
    ],
    "sg:phone":"+1 305 251 5102",
    "sg:postcode":"33186",
    "sg:province":"FL",
    "sg:tags":[
        "recording",
        "studio"
    ],
    "wof:name":"Gallery Recording Studio",
    "wof:placetype":"venue"
},
  "geometry": {"coordinates":[-80.42268300000001,25.637359],"type":"Point"}
}