{
  "type": "Feature",
  "properties": {
    "iso:country":"US",
    "sg:address":"716 Bayway Blvd",
    "sg:city":"Clearwater",
    "sg:classifiers":[
        {
            "category":"Sports & Exercise",
            "subcategory":"Race Track",
            "type":"Entertainment"
        }
    ],
    "sg:phone":"+1 727 442 2490",
    "sg:postcode":"33767",
    "sg:province":"FL",
    "sg:tags":[
        "operation",
        "racing",
        "or"
    ],
    "wof:name":"Massell Motorsports",
    "wof:placetype":"venue"
},
  "geometry": {"coordinates":[-82.822425,27.967029],"type":"Point"}
}