{
  "type": "Feature",
  "properties": {
    "iso:country":"US",
    "sg:address":"6912 Anthurium Ln",
    "sg:city":"Naples",
    "sg:classifiers":[
        {
            "category":"Building & Trades",
            "subcategory":"Construction",
            "type":"Services"
        }
    ],
    "sg:phone":"+1 239 417 8029",
    "sg:postcode":"34113",
    "sg:province":"FL",
    "sg:tags":[
        "general",
        "contractor"
    ],
    "wof:name":"Artisan Enterprises",
    "wof:placetype":"venue"
},
  "geometry": {"coordinates":[-81.69606899999999,26.081487],"type":"Point"}
}