{
  "type": "Feature",
  "properties": {
    "iso:country":"US",
    "sg:address":"836 E Oyster Ln",
    "sg:city":"Lake Worth",
    "sg:classifiers":[
        {
            "category":"Wholesale",
            "subcategory":"Seafood",
            "type":"Manufacturing & Wholesale Goods"
        }
    ],
    "sg:phone":"+1 561 547 1083",
    "sg:postcode":"33462",
    "sg:province":"FL",
    "sg:tags":[
        "retail"
    ],
    "wof:name":"Capt Franks Seafood Market",
    "wof:placetype":"venue"
},
  "geometry": {"coordinates":[-80.042773,26.57628],"type":"Point"}
}