{
  "type": "Feature",
  "properties": {
    "iso:country":"US",
    "sg:address":"1289 Porter Rd",
    "sg:city":"Sarasota",
    "sg:classifiers":[
        {
            "category":"Wholesale",
            "subcategory":"Construction Materials",
            "type":"Manufacturing & Wholesale Goods"
        },
        {
            "category":"Building & Trades",
            "subcategory":"Construction",
            "type":"Services"
        }
    ],
    "sg:phone":"+1 941 342 1393",
    "sg:postcode":"34240",
    "sg:province":"FL",
    "sg:tags":[
        "designer",
        "dealer",
        "pool",
        "swimming"
    ],
    "wof:name":"National Pool Tile Group",
    "wof:placetype":"venue"
},
  "geometry": {"coordinates":[-82.446962,27.32444],"type":"Point"}
}