{
  "type": "Feature",
  "properties": {
    "iso:country":"US",
    "sg:address":"4701 SW 55th Ave",
    "sg:city":"Davie",
    "sg:classifiers":[
        {
            "category":"Retail",
            "subcategory":"Animal Services",
            "type":"Services"
        }
    ],
    "sg:phone":"+1 954 587 7252",
    "sg:postcode":"33314",
    "sg:province":"FL",
    "sg:tags":[
        "pet",
        "boarding",
        "sitting"
    ],
    "wof:name":"El Lobo Giant Schnauzers",
    "wof:placetype":"venue"
},
  "geometry": {"coordinates":[-80.22080699999999,26.064406],"type":"Point"}
}