{
  "type": "Feature",
  "properties": {
    "iso:country":"US",
    "sg:address":"14327 78th Pl N",
    "sg:city":"Loxahatchee",
    "sg:classifiers":[
        {
            "category":"Building & Trades",
            "subcategory":"Construction",
            "type":"Services"
        }
    ],
    "sg:phone":"+1 561 792 3857",
    "sg:postcode":"33470",
    "sg:province":"FL",
    "sg:tags":[
        "residential"
    ],
    "wof:name":"Claudio Gonzalez Construction",
    "wof:placetype":"venue"
},
  "geometry": {"coordinates":[-80.26659600000001,26.792724],"type":"Point"}
}