{
  "type": "Feature",
  "properties": {
    "addr:full":"3755 S Congress Ave Lake Worth FL 33461",
    "addr:housenumber":"3755",
    "addr:postcode":"33461",
    "addr:street":"S Congress Ave",
    "iso:country":"US",
    "sg:address":"3755 S Congress Ave",
    "sg:city":"Lake Worth",
    "sg:classifiers":[
        {
            "category":"Shopping",
            "subcategory":"Books",
            "type":"Retail Goods"
        }
    ],
    "sg:phone":"+1 561 439 0080",
    "sg:postcode":"33461",
    "sg:province":"FL",
    "sg:tags":[
        "dealer"
    ],
    "wof:name":"Libreria Cristiana El Montes",
    "wof:placetype":"venue"
},
  "geometry": {"coordinates":[-80.088953,26.620354],"type":"Point"}
}