{
  "type": "Feature",
  "properties": {
    "iso:country":"US",
    "sg:address":"4248 Magnolia Ridge Dr",
    "sg:city":"Fort Lauderdale",
    "sg:classifiers":[
        {
            "category":"Professional",
            "subcategory":"Advertising",
            "type":"Services"
        }
    ],
    "sg:phone":"+1 954 385 9535",
    "sg:postcode":"33331",
    "sg:province":"FL",
    "sg:tags":[
        "agency"
    ],
    "wof:name":"Max Mural Advertising Inc",
    "wof:placetype":"venue"
},
  "geometry": {"coordinates":[-80.377183,26.065205],"type":"Point"}
}