{
  "type": "Feature",
  "properties": {
    "addr:full":"8802 Heritage Bay Cir Orlando FL 32836",
    "addr:housenumber":"8802",
    "addr:postcode":"32836",
    "addr:street":"Heritage Bay Cir",
    "iso:country":"US",
    "sg:address":"8802 Heritage Bay Cir",
    "sg:city":"Orlando",
    "sg:classifiers":[
        {
            "category":"Building & Trades",
            "subcategory":"Construction",
            "type":"Services"
        }
    ],
    "sg:phone":"+1 407 370 9727",
    "sg:postcode":"32836",
    "sg:province":"FL",
    "sg:tags":[
        "house"
    ],
    "wof:name":"Camelot Custom Homes",
    "wof:placetype":"venue"
},
  "geometry": {"coordinates":[-81.50270399999999,28.435333],"type":"Point"}
}