{
  "type": "Feature",
  "properties": {
    "addr:full":"1022 Main St Dunedin FL 34698",
    "addr:housenumber":"1022",
    "addr:postcode":"34698",
    "addr:street":"Main St",
    "iso:country":"US",
    "sg:address":"1022 Main St",
    "sg:city":"Dunedin",
    "sg:classifiers":[
        {
            "category":"Health Services",
            "subcategory":"Clinic",
            "type":"Services"
        }
    ],
    "sg:phone":"+1 727 490 7000",
    "sg:postcode":"34698",
    "sg:province":"FL",
    "sg:tags":[
        "home"
    ],
    "wof:name":"Daughter On Call",
    "wof:placetype":"venue"
},
  "geometry": {"coordinates":[-82.774828,28.018974],"type":"Point"}
}