{
  "type": "Feature",
  "properties": {
    "iso:country":"US",
    "sg:address":"1863 Gulf Blvd",
    "sg:city":"Englewood",
    "sg:classifiers":[
        {
            "category":"Recreation",
            "type":"Entertainment"
        }
    ],
    "sg:phone":"+1 941 474 1022",
    "sg:postcode":"34223",
    "sg:province":"FL",
    "sg:tags":[
        "guide"
    ],
    "wof:name":"A 1 Grouper Fishing",
    "wof:placetype":"venue"
},
  "geometry": {"coordinates":[-82.360035,26.923615],"type":"Point"}
}