{
  "type": "Feature",
  "properties": {
    "iso:country":"US",
    "sg:address":"3237 Sawgrass Creek Cir",
    "sg:city":"St Cloud",
    "sg:classifiers":[
        {
            "category":"Professional",
            "subcategory":"Business Services",
            "type":"Services"
        }
    ],
    "sg:phone":"+1 407 891 8104",
    "sg:postcode":"34772",
    "sg:province":"FL",
    "sg:tags":[
        "interior",
        "consultant",
        "design",
        "decorator"
    ],
    "wof:name":"Interior Realities",
    "wof:placetype":"venue"
},
  "geometry": {"coordinates":[-81.29149700000001,28.196412],"type":"Point"}
}