{
  "type": "Feature",
  "properties": {
    "addr:full":"1371 W 80th St Hialeah FL 33014",
    "addr:housenumber":"1371",
    "addr:postcode":"33014",
    "addr:street":"W 80Th St",
    "iso:country":"US",
    "sg:address":"1371 W 80th St",
    "sg:city":"Hialeah",
    "sg:classifiers":[
        {
            "category":"Shopping",
            "subcategory":"Jewelry",
            "type":"Retail Goods"
        }
    ],
    "sg:phone":"+1 305 556 3410",
    "sg:postcode":"33014",
    "sg:province":"FL",
    "sg:tags":[
        "platinum",
        "silver",
        "gold"
    ],
    "wof:name":"South Gold Corp",
    "wof:placetype":"venue"
},
  "geometry": {"coordinates":[-80.310768,25.895275],"type":"Point"}
}