{
  "type": "Feature",
  "properties": {
    "iso:country":"US",
    "sg:address":"203 Briar Cliff Dr",
    "sg:city":"Longwood",
    "sg:classifiers":[
        {
            "category":"Wholesale",
            "subcategory":"Vending Machines",
            "type":"Manufacturing & Wholesale Goods"
        }
    ],
    "sg:phone":"+1 407 310 4084",
    "sg:postcode":"32779",
    "sg:province":"FL",
    "sg:tags":[
        "operator"
    ],
    "wof:name":"Amy Ayers Vending",
    "wof:placetype":"venue"
},
  "geometry": {"coordinates":[-81.411011,28.690386],"type":"Point"}
}