{
  "type": "Feature",
  "properties": {
    "addr:full":"11110 Immokalee Rd Naples FL 34120",
    "addr:postcode":"11110;34120",
    "addr:street":"Immokalee Rd",
    "iso:country":"US",
    "sg:address":"11110 Immokalee Rd",
    "sg:city":"Naples",
    "sg:classifiers":[
        {
            "category":"Manufacturing",
            "subcategory":"Lumber",
            "type":"Manufacturing & Wholesale Goods"
        }
    ],
    "sg:phone":"+1 239 353 7256",
    "sg:postcode":"34120",
    "sg:province":"FL",
    "sg:tags":[
        "tract",
        "real estate",
        "operation",
        "timber"
    ],
    "wof:name":"Treesource",
    "wof:placetype":"venue"
},
  "geometry": {"coordinates":[-81.643816,26.274062],"type":"Point"}
}