{
  "type": "Feature",
  "properties": {
    "iso:country":"US",
    "sg:address":"2221 Lee Rd #13",
    "sg:city":"Winter Park",
    "sg:classifiers":[
        {
            "category":"Insurance",
            "subcategory":"Hazard Insurance",
            "type":"Services"
        }
    ],
    "sg:phone":"+1 407 677 6200",
    "sg:postcode":"32789",
    "sg:province":"FL",
    "sg:website":"www.sterlingschmidt.com",
    "wof:name":"Sterling And Schmidt, Inc.",
    "wof:placetype":"venue"
},
  "geometry": {"coordinates":[-81.37806500000001,28.607238],"type":"Point"}
}