{
  "type": "Feature",
  "properties": {
    "addr:full":"2401 NW 30th Ave Miami FL 33142",
    "addr:housenumber":"2401",
    "addr:postcode":"33142",
    "addr:street":"Nw 30Th Ave",
    "iso:country":"US",
    "sg:address":"2401 NW 30th Ave",
    "sg:city":"Miami",
    "sg:phone":"+1 305 633 6030",
    "sg:postcode":"33142",
    "sg:province":"FL",
    "wof:name":"Petro Energy Alliance",
    "wof:placetype":"venue"
},
  "geometry": {"coordinates":[-80.244011,25.79879],"type":"Point"}
}