{
  "type": "Feature",
  "properties": {
    "addr:full":"8898 N 56th St Tampa FL 33617",
    "addr:housenumber":"8898",
    "addr:postcode":"33617",
    "addr:street":"N 56Th St",
    "iso:country":"US",
    "sg:address":"8898 N 56th St",
    "sg:city":"Tampa",
    "sg:classifiers":[
        {
            "category":"Personal",
            "subcategory":"Beauty Salon",
            "type":"Services"
        }
    ],
    "sg:phone":"+1 813 980 1923",
    "sg:postcode":"33617",
    "sg:province":"FL",
    "sg:tags":[
        "shop",
        "manicuring"
    ],
    "wof:name":"Cindy's Nails",
    "wof:placetype":"venue"
},
  "geometry": {"coordinates":[-82.393539,28.031389],"type":"Point"}
}