{
  "type": "Feature",
  "properties": {
    "iso:country":"US",
    "sg:address":"544 Washington Ave",
    "sg:city":"Miami Beach",
    "sg:classifiers":[
        {
            "category":"Food & Beverages",
            "subcategory":"Liquor & Beverages",
            "type":"Retail Goods"
        }
    ],
    "sg:phone":"+1 305 674 1992",
    "sg:postcode":"33139",
    "sg:province":"FL",
    "sg:tags":[
        "beer",
        "spirit",
        "wine"
    ],
    "wof:name":"Surf Liquor",
    "wof:placetype":"venue"
},
  "geometry": {"coordinates":[-80.134253,25.775081],"type":"Point"}
}