{
  "type": "Feature",
  "properties": {
    "iso:country":"US",
    "sg:address":"1810 Woodhaven Cir",
    "sg:city":"Sarasota",
    "sg:classifiers":[
        {
            "category":"Shopping",
            "subcategory":"Bridal",
            "type":"Retail Goods"
        }
    ],
    "sg:phone":"+1 941 376 9599",
    "sg:postcode":"34232",
    "sg:province":"FL",
    "sg:tags":[
        "shop"
    ],
    "wof:name":"Bridal Bootcamp",
    "wof:placetype":"venue"
},
  "geometry": {"coordinates":[-82.48484000000001,27.31686],"type":"Point"}
}