{
  "type": "Feature",
  "properties": {
    "addr:full":"3131 Capital Cir NE Tallahassee FL 32308",
    "addr:housenumber":"3131",
    "addr:postcode":"32308",
    "addr:street":"Capital Cir Ne",
    "iso:country":"US",
    "sg:address":"3131 Capital Cir NE",
    "sg:city":"Tallahassee",
    "sg:classifiers":[
        {
            "category":"Restaurant",
            "type":"Food & Drink"
        }
    ],
    "sg:phone":"+1 850 386 2480",
    "sg:postcode":"32308",
    "sg:province":"FL",
    "sg:website":"www.smokeybones.com",
    "wof:name":"Smokey Bones BBQ & Grill",
    "wof:placetype":"venue"
},
  "geometry": {"coordinates":[-84.246341,30.496957],"type":"Point"}
}