{
  "type": "Feature",
  "properties": {
    "iso:country":"US",
    "sg:address":"224 NE Lakeview Dr",
    "sg:city":"Sebring",
    "sg:classifiers":[
        {
            "category":"Professional",
            "subcategory":"Lawyer & Legal Services",
            "type":"Services"
        }
    ],
    "sg:phone":"+1 863 471 0003",
    "sg:postcode":"33870",
    "sg:province":"FL",
    "sg:tags":[
        "attorney"
    ],
    "wof:name":"Lilly O'Tolle & Brown LLP",
    "wof:placetype":"venue"
},
  "geometry": {"coordinates":[-81.443887,27.496081],"type":"Point"}
}