{
  "type": "Feature",
  "properties": {
    "iso:country":"US",
    "sg:address":"1725 Rita St",
    "sg:city":"Sarasota",
    "sg:classifiers":[
        {
            "category":"Professional",
            "type":"Services"
        }
    ],
    "sg:phone":"+1 941 966 1877",
    "sg:postcode":"34231",
    "sg:province":"FL",
    "wof:name":"Donald J Mc Gowan Charter Svc",
    "wof:placetype":"venue"
},
  "geometry": {"coordinates":[-82.497922,27.220264],"type":"Point"}
}