{
  "type": "Feature",
  "properties": {
    "iso:country":"US",
    "sg:address":"501 N State Rd 7",
    "sg:city":"Hollywood",
    "sg:classifiers":[
        {
            "category":"Autos & Motor Vehicles",
            "subcategory":"Automobile Sales",
            "type":"Retail Goods"
        }
    ],
    "sg:phone":"+1 954 961 0945",
    "sg:postcode":"33021",
    "sg:province":"FL",
    "sg:tags":[
        "used"
    ],
    "wof:name":"Worldwide Auto Sales Inc",
    "wof:placetype":"venue"
},
  "geometry": {"coordinates":[-80.207809,26.01482],"type":"Point"}
}