{
  "type": "Feature",
  "properties": {
    "iso:country":"US",
    "sg:address":"1314 Murray Dr",
    "sg:city":"Jacksonville",
    "sg:classifiers":[
        {
            "category":"Wholesale",
            "subcategory":"Groceries",
            "type":"Manufacturing & Wholesale Goods"
        }
    ],
    "sg:phone":"+1 904 389 8303",
    "sg:postcode":"32205",
    "sg:province":"FL",
    "wof:name":"Cromley Enterprises",
    "wof:placetype":"venue"
},
  "geometry": {"coordinates":[-81.726327,30.298112],"type":"Point"}
}