{
  "type": "Feature",
  "properties": {
    "iso:country":"US",
    "sg:address":"2181 34th Way N",
    "sg:city":"Largo",
    "sg:classifiers":[
        {
            "category":"Manufacturing",
            "subcategory":"Furniture",
            "type":"Manufacturing & Wholesale Goods"
        }
    ],
    "sg:phone":"+1 727 536 2207",
    "sg:postcode":"33771",
    "sg:province":"FL",
    "sg:tags":[
        "equipment",
        "supply"
    ],
    "wof:name":"CDI Svc & Mfg Inc",
    "wof:placetype":"venue"
},
  "geometry": {"coordinates":[-82.752489,27.895942],"type":"Point"}
}