{
  "type": "Feature",
  "properties": {
    "iso:country":"US",
    "sg:address":"5075 Carter St",
    "sg:city":"Cocoa",
    "sg:classifiers":[
        {
            "category":"Manufacturing",
            "subcategory":"Apparel",
            "type":"Manufacturing & Wholesale Goods"
        }
    ],
    "sg:phone":"+1 321 636 6474",
    "sg:postcode":"32927",
    "sg:province":"FL",
    "sg:tags":[
        "work",
        "clothing",
        "mfg"
    ],
    "wof:name":"Ron Youmans Acccssrs",
    "wof:placetype":"venue"
},
  "geometry": {"coordinates":[-80.80589000000001,28.480505],"type":"Point"}
}