{
  "type": "Feature",
  "properties": {
    "iso:country":"US",
    "sg:address":"217 Labelle Ave",
    "sg:city":"Fort Myers",
    "sg:classifiers":[
        {
            "category":"Building & Trades",
            "subcategory":"Landscaping Services",
            "type":"Services"
        }
    ],
    "sg:phone":"+1 239 694 2304",
    "sg:postcode":"33905",
    "sg:province":"FL",
    "sg:tags":[
        "lawn",
        "maintenance",
        "grounds"
    ],
    "wof:name":"Phil Harris Lawn Care & Mntnc",
    "wof:placetype":"venue"
},
  "geometry": {"coordinates":[-81.80918200000001,26.683543],"type":"Point"}
}