{
  "type": "Feature",
  "properties": {
    "iso:country":"US",
    "sg:address":"116 Marcia Dr",
    "sg:city":"Altamonte Springs",
    "sg:classifiers":[
        {
            "category":"Wholesale",
            "subcategory":"Computers",
            "type":"Manufacturing & Wholesale Goods"
        }
    ],
    "sg:phone":"+1 407 788 1906",
    "sg:postcode":"32714",
    "sg:province":"FL",
    "sg:website":"www.ncgmedical.com",
    "wof:name":"Ncg Medical Systems Inc",
    "wof:placetype":"venue"
},
  "geometry": {"coordinates":[-81.424109,28.665783],"type":"Point"}
}