{
  "type": "Feature",
  "properties": {
    "iso:country":"US",
    "sg:address":"603 Central Park Dr",
    "sg:city":"Sanford",
    "sg:classifiers":[
        {
            "category":"Professional",
            "subcategory":"Business Services",
            "type":"Services"
        }
    ],
    "sg:phone":"+1 407 321 2700",
    "sg:postcode":"32771",
    "sg:province":"FL",
    "sg:tags":[
        "industrial",
        "machinery",
        "mfg"
    ],
    "wof:name":"Conceptual Engineering Inc",
    "wof:placetype":"venue"
},
  "geometry": {"coordinates":[-81.317376,28.80722],"type":"Point"}
}