{
  "type": "Feature",
  "properties": {
    "iso:country":"US",
    "sg:address":"17688 Davenport Rd",
    "sg:city":"Winter Garden",
    "sg:classifiers":[
        {
            "category":"Building & Trades",
            "subcategory":"Landscaping Services",
            "type":"Services"
        }
    ],
    "sg:phone":"+1 407 877 0992",
    "sg:postcode":"34787",
    "sg:province":"FL",
    "sg:tags":[
        "picture",
        "lawn",
        "framing"
    ],
    "wof:name":"Spears & Sons Lawn & Home Svcs",
    "wof:placetype":"venue"
},
  "geometry": {"coordinates":[-81.651253,28.501906],"type":"Point"}
}