{
  "type": "Feature",
  "properties": {
    "addr:full":"1046 E Memorial Blvd Lakeland FL 33801",
    "addr:housenumber":"1046",
    "addr:postcode":"33801",
    "addr:street":"E Memorial Blvd",
    "iso:country":"US",
    "sg:address":"1046 E Memorial Blvd",
    "sg:city":"Lakeland",
    "sg:classifiers":[
        {
            "category":"Building & Trades",
            "subcategory":"Equipment Rental",
            "type":"Services"
        }
    ],
    "sg:phone":"+1 863 688 8163",
    "sg:postcode":"33801",
    "sg:province":"FL",
    "sg:tags":[
        "home",
        "electronics",
        "appliance",
        "furniture"
    ],
    "wof:name":"Rent-Way",
    "wof:placetype":"venue"
},
  "geometry": {"coordinates":[-81.943241,28.055182],"type":"Point"}
}