{
  "type": "Feature",
  "properties": {
    "iso:country":"US",
    "sg:address":"2865 Michigan Ave",
    "sg:city":"Kissimmee",
    "sg:classifiers":[
        {
            "category":"Home & Garden",
            "subcategory":"Building Materials",
            "type":"Retail Goods"
        }
    ],
    "sg:phone":"+1 407 846 6480",
    "sg:postcode":"34744",
    "sg:province":"FL",
    "sg:tags":[
        "windows"
    ],
    "wof:name":"Sunshine Window Tinting",
    "wof:placetype":"venue"
},
  "geometry": {"coordinates":[-81.39115,28.331607],"type":"Point"}
}