{
  "type": "Feature",
  "properties": {
    "iso:country":"US",
    "sg:address":"14340 SW 122nd Ct",
    "sg:city":"Miami",
    "sg:classifiers":[
        {
            "category":"Organizations",
            "subcategory":"Community Association",
            "type":"Services"
        }
    ],
    "sg:phone":"+1 305 253 6280",
    "sg:postcode":"33186",
    "sg:province":"FL",
    "sg:tags":[
        "club",
        "professional",
        "employer"
    ],
    "wof:name":"Bonita Lakes Poa Club",
    "wof:placetype":"venue"
},
  "geometry": {"coordinates":[-80.39093699999999,25.635039],"type":"Point"}
}