{
  "type": "Feature",
  "properties": {
    "iso:country":"US",
    "sg:address":"4474 Woodbine Rd",
    "sg:city":"Milton",
    "sg:classifiers":[
        {
            "category":"Personal",
            "subcategory":"Nail Salon",
            "type":"Services"
        }
    ],
    "sg:phone":"+1 850 995 0779",
    "sg:postcode":"32571",
    "sg:province":"FL",
    "wof:name":"Rosalinda's Nails & Fragrances",
    "wof:placetype":"venue"
},
  "geometry": {"coordinates":[-87.18232,30.602214],"type":"Point"}
}