{
  "type": "Feature",
  "properties": {
    "addr:full":"1185 W 37th St West Palm Beach FL 33404",
    "addr:housenumber":"1185",
    "addr:postcode":"33404",
    "addr:street":"W 37Th St",
    "iso:country":"US",
    "sg:address":"1185 W 37th St",
    "sg:city":"West Palm Beach",
    "sg:classifiers":[
        {
            "category":"Building & Trades",
            "subcategory":"Construction",
            "type":"Services"
        }
    ],
    "sg:phone":"+1 561 881 7008",
    "sg:postcode":"33404",
    "sg:province":"FL",
    "sg:tags":[
        "carpentry",
        "contractor"
    ],
    "wof:name":"Sanders Services",
    "wof:placetype":"venue"
},
  "geometry": {"coordinates":[-80.073031,26.792015],"type":"Point"}
}