{
  "type": "Feature",
  "properties": {
    "iso:country":"US",
    "sg:address":"16105 N Florida Ave",
    "sg:city":"Lutz",
    "sg:classifiers":[
        {
            "category":"Professional",
            "subcategory":"Business Services",
            "type":"Services"
        }
    ],
    "sg:phone":"+1 813 290 9785",
    "sg:postcode":"33549",
    "sg:province":"FL",
    "sg:tags":[
        "telemarketing"
    ],
    "wof:name":"Marketing One USA",
    "wof:placetype":"venue"
},
  "geometry": {"coordinates":[-82.460803,28.099541],"type":"Point"}
}