{
  "type": "Feature",
  "properties": {
    "addr:full":"4907 SW 75th Ave Miami FL 33155",
    "addr:housenumber":"4907",
    "addr:postcode":"33155",
    "addr:street":"Sw 75Th Ave",
    "iso:country":"US",
    "sg:address":"4907 SW 75th Ave",
    "sg:city":"Miami",
    "sg:classifiers":[
        {
            "category":"Organizations",
            "subcategory":"Professional Association",
            "type":"Services"
        }
    ],
    "sg:phone":"+1 305 934 4340",
    "sg:postcode":"33155",
    "sg:province":"FL",
    "wof:name":"Gateway Office Tech Assn",
    "wof:placetype":"venue"
},
  "geometry": {"coordinates":[-80.316688,25.723909],"type":"Point"}
}