{
  "type": "Feature",
  "properties": {
    "iso:country":"US",
    "sg:address":"6770 Lantana Rd",
    "sg:city":"Lake Worth",
    "sg:classifiers":[
        {
            "category":"Home & Garden",
            "subcategory":"Building Materials",
            "type":"Retail Goods"
        }
    ],
    "sg:phone":"+1 561 965 3597",
    "sg:postcode":"33467",
    "sg:province":"FL",
    "sg:tags":[
        "door",
        "install",
        "molding"
    ],
    "wof:name":"Freestyle Builders",
    "wof:placetype":"venue"
},
  "geometry": {"coordinates":[-80.150235,26.589621],"type":"Point"}
}