{
  "type": "Feature",
  "properties": {
    "iso:country":"US",
    "sg:address":"1520 Lee St",
    "sg:city":"Fort Myers",
    "sg:classifiers":[
        {
            "category":"Shopping",
            "type":"Retail Goods"
        }
    ],
    "sg:phone":"+1 239 344 0656",
    "sg:postcode":"33901",
    "sg:province":"FL",
    "sg:tags":[
        "merchandise"
    ],
    "wof:name":"Global Fire Protection",
    "wof:placetype":"venue"
},
  "geometry": {"coordinates":[-81.86779900000001,26.644725],"type":"Point"}
}