{
  "type": "Feature",
  "properties": {
    "addr:full":"604 Crandon Blvd Key Biscayne FL 33149",
    "addr:housenumber":"604",
    "addr:postcode":"33149",
    "addr:street":"Crandon Blvd",
    "iso:country":"US",
    "sg:address":"604 Crandon Blvd",
    "sg:city":"Key Biscayne",
    "sg:classifiers":[
        {
            "category":"Real Estate",
            "subcategory":"Real Estate Agent",
            "type":"Services"
        }
    ],
    "sg:phone":"+1 305 361 6800",
    "sg:postcode":"33149",
    "sg:province":"FL",
    "wof:name":"Tarafa & Iriondo Corporation",
    "wof:placetype":"venue"
},
  "geometry": {"coordinates":[-80.163858,25.689288],"type":"Point"}
}