{
  "type": "Feature",
  "properties": {
    "iso:country":"US",
    "sg:address":"4515 S Cleveland Ave",
    "sg:city":"Fort Myers",
    "sg:classifiers":[
        {
            "category":"Home & Garden",
            "subcategory":"Furniture",
            "type":"Retail Goods"
        }
    ],
    "sg:phone":"+1 239 275 9566",
    "sg:postcode":"33907",
    "sg:province":"FL",
    "sg:tags":[
        "store"
    ],
    "sg:website":"www.la-z-boy.com/",
    "wof:name":"La-Z-Boy Furniture Galleries",
    "wof:placetype":"venue"
},
  "geometry": {"coordinates":[-81.870704,26.595927],"type":"Point"}
}