{
  "type": "Feature",
  "properties": {
    "addr:full":"8401 S Tamiami Trl Sarasota FL 34238",
    "addr:housenumber":"8401",
    "addr:postcode":"34238",
    "addr:street":"S Tamiami Trl",
    "iso:country":"US",
    "sg:address":"8401 S Tamiami Trl",
    "sg:city":"Sarasota",
    "sg:classifiers":[
        {
            "category":"Social Services",
            "type":"Services"
        }
    ],
    "sg:phone":"+1 941 926 2620",
    "sg:postcode":"34238",
    "sg:province":"FL",
    "sg:tags":[
        "organization",
        "welfare"
    ],
    "wof:name":"Goodwill Industries",
    "wof:placetype":"venue"
},
  "geometry": {"coordinates":[-82.49411499999999,27.22831],"type":"Point"}
}