{
  "type": "Feature",
  "properties": {
    "addr:full":"812 Tamiami Trl Port Charlotte FL 33953",
    "addr:housenumber":"812",
    "addr:postcode":"33953",
    "addr:street":"Tamiami Trl",
    "iso:country":"US",
    "sg:address":"812 Tamiami Trl",
    "sg:city":"Port Charlotte",
    "sg:classifiers":[
        {
            "category":"Building & Trades",
            "subcategory":"Construction",
            "type":"Services"
        }
    ],
    "sg:phone":"+1 941 206 2055",
    "sg:postcode":"33953",
    "sg:province":"FL",
    "sg:tags":[
        "home",
        "builder"
    ],
    "wof:name":"David Weekley Homes",
    "wof:placetype":"venue"
},
  "geometry": {"coordinates":[-82.164857,27.018314],"type":"Point"}
}