{
  "type": "Feature",
  "properties": {
    "addr:full":"800 108th Ave N Naples FL 34108",
    "addr:housenumber":"800",
    "addr:postcode":"34108",
    "addr:street":"108Th Ave N",
    "iso:country":"US",
    "sg:address":"800 108th Ave N",
    "sg:city":"Naples",
    "sg:classifiers":[
        {
            "category":"Freight",
            "type":"Transportation"
        }
    ],
    "sg:phone":"+1 239 598 3278",
    "sg:postcode":"34108",
    "sg:province":"FL",
    "sg:tags":[
        "courier"
    ],
    "wof:name":"Asfast",
    "wof:placetype":"venue"
},
  "geometry": {"coordinates":[-81.80457199999999,26.269664],"type":"Point"}
}