{
  "type": "Feature",
  "properties": {
    "addr:full":"2136 S Porpoise Point Ln Vero Beach FL 32963",
    "addr:housenumber":"2136",
    "addr:postcode":"32963",
    "addr:street":"S Porpoise Point Ln",
    "iso:country":"US",
    "sg:address":"2136 S Porpoise Point Ln",
    "sg:city":"Vero Beach",
    "sg:classifiers":[
        {
            "category":"Organizations",
            "subcategory":"Community Association",
            "type":"Services"
        }
    ],
    "sg:phone":"+1 772 231 8161",
    "sg:postcode":"32963",
    "sg:province":"FL",
    "wof:name":"Porpoise Point Association",
    "wof:placetype":"venue"
},
  "geometry": {"coordinates":[-80.332246,27.594009],"type":"Point"}
}