{
  "type": "Feature",
  "properties": {
    "addr:full":"8105 Cooper Creek Blvd University Park FL 34201",
    "addr:housenumber":"8105",
    "addr:postcode":"34201",
    "addr:street":"Cooper Creek Blvd",
    "iso:country":"US",
    "sg:address":"8105 Cooper Creek Blvd",
    "sg:city":"University Park",
    "sg:classifiers":[
        {
            "category":"Restaurant",
            "type":"Food & Drink"
        }
    ],
    "sg:phone":"+1 941 360 6850",
    "sg:postcode":"34201",
    "sg:province":"FL",
    "wof:name":"Bamboo Bistro",
    "wof:placetype":"venue"
},
  "geometry": {"coordinates":[-82.45308900000001,27.393622],"type":"Point"}
}