{
  "type": "Feature",
  "properties": {
    "addr:full":"601 NW 131st St Miami FL 33168",
    "addr:housenumber":"601",
    "addr:postcode":"33168",
    "addr:street":"Nw 131St St",
    "iso:country":"US",
    "sg:address":"601 NW 131st St",
    "sg:city":"Miami",
    "sg:classifiers":[
        {
            "category":"Education",
            "subcategory":"School",
            "type":"Public Place"
        }
    ],
    "sg:phone":"+1 305 681 3822",
    "sg:postcode":"33168",
    "sg:province":"FL",
    "wof:name":"St James School",
    "wof:placetype":"venue"
},
  "geometry": {"coordinates":[-80.209541,25.894717],"type":"Point"}
}