{
  "type": "Feature",
  "properties": {
    "iso:country":"US",
    "sg:address":"450061 State Road 200 # 6",
    "sg:city":"Callahan",
    "sg:classifiers":[
        {
            "category":"Restaurant",
            "type":"Food & Drink"
        }
    ],
    "sg:phone":"+1 904 879 9464",
    "sg:postcode":"32011",
    "sg:province":"FL",
    "sg:tags":[
        "grill",
        "bar"
    ],
    "wof:name":"Sports Page Grill",
    "wof:placetype":"venue"
},
  "geometry": {"coordinates":[-81.82021400000001,30.574899],"type":"Point"}
}