{
  "type": "Feature",
  "properties": {
    "addr:full":"21 Wright Pkwy NW Fort Walton Beach FL 32548",
    "addr:housenumber":"21",
    "addr:postcode":"32548",
    "addr:street":"Wright Pkwy Nw",
    "iso:country":"US",
    "sg:address":"21 Wright Pkwy NW",
    "sg:city":"Fort Walton Beach",
    "sg:classifiers":[
        {
            "category":"Education",
            "subcategory":"Vocational School",
            "type":"Public Place"
        }
    ],
    "sg:phone":"+1 850 243 5896",
    "sg:postcode":"32548",
    "sg:province":"FL",
    "wof:name":"Laserschoolnet",
    "wof:placetype":"venue"
},
  "geometry": {"coordinates":[-86.639106,30.416726],"type":"Point"}
}