{
  "type": "Feature",
  "properties": {
    "iso:country":"US",
    "sg:address":"4902 E Hillsborough Ave",
    "sg:city":"Tampa",
    "sg:classifiers":[
        {
            "category":"Shopping",
            "subcategory":"Department Store",
            "type":"Retail Goods"
        },
        {
            "category":"Shopping",
            "subcategory":"Discount & Variety Stores",
            "type":"Retail Goods"
        }
    ],
    "sg:phone":"+1 813 621 5258",
    "sg:postcode":"33610",
    "sg:province":"FL",
    "sg:website":"http://www.familydollar.com",
    "wof:name":"Family Dollar",
    "wof:placetype":"venue"
},
  "geometry": {"coordinates":[-82.40318000000001,27.996099],"type":"Point"}
}