{
  "type": "Feature",
  "properties": {
    "addr:full":"3931 NW 34th Ave Fort Lauderdale FL 33309",
    "addr:housenumber":"3931",
    "addr:postcode":"33309",
    "addr:street":"Nw 34Th Ave",
    "iso:country":"US",
    "sg:address":"3931 NW 34th Ave",
    "sg:city":"Fort Lauderdale",
    "sg:classifiers":[
        {
            "category":"Freight",
            "type":"Transportation"
        }
    ],
    "sg:phone":"+1 954 296 8286",
    "sg:postcode":"33309",
    "sg:province":"FL",
    "sg:tags":[
        "operator",
        "local",
        "trucking"
    ],
    "wof:name":"R M Trucking Service Inc",
    "wof:placetype":"venue"
},
  "geometry": {"coordinates":[-80.193274,26.175302],"type":"Point"}
}