{
  "type": "Feature",
  "properties": {
    "iso:country":"US",
    "sg:address":"7006 SW 4th St",
    "sg:city":"Miami",
    "sg:classifiers":[
        {
            "category":"Real Estate",
            "subcategory":"Real Estate Agent",
            "type":"Services"
        }
    ],
    "sg:phone":"+1 305 261 8404",
    "sg:postcode":"33144",
    "sg:province":"FL",
    "wof:name":"Ariel Development Properties",
    "wof:placetype":"venue"
},
  "geometry": {"coordinates":[-80.30906400000001,25.766543],"type":"Point"}
}