{
  "type": "Feature",
  "properties": {
    "addr:full":"940 Highland Ave Orlando FL 32803",
    "addr:housenumber":"940",
    "addr:postcode":"32803",
    "addr:street":"Highland Ave",
    "iso:country":"US",
    "sg:address":"940 Highland Ave",
    "sg:city":"Orlando",
    "sg:classifiers":[
        {
            "category":"Professional",
            "subcategory":"Lawyer & Legal Services",
            "type":"Services"
        }
    ],
    "sg:phone":"+1 407 843 5885",
    "sg:postcode":"32803",
    "sg:province":"FL",
    "sg:tags":[
        "arbitration",
        "attorney",
        "practice"
    ],
    "wof:name":"Mediation Group",
    "wof:placetype":"venue"
},
  "geometry": {"coordinates":[-81.373741,28.557777],"type":"Point"}
}