{
  "type": "Feature",
  "properties": {
    "iso:country":"US",
    "sg:address":"21810 US Hwy 19",
    "sg:city":"Clearwater",
    "sg:classifiers":[
        {
            "category":"Shopping",
            "subcategory":"Computers & Home Electronics",
            "type":"Retail Goods"
        }
    ],
    "sg:phone":"+1 727 723 3380",
    "sg:postcode":"33765",
    "sg:province":"FL",
    "wof:name":"Radio Shack",
    "wof:placetype":"venue"
},
  "geometry": {"coordinates":[-82.72993099999999,27.969114],"type":"Point"}
}