{
  "type": "Feature",
  "properties": {
    "addr:full":"400 Co Rd 468 Leesburg FL 34748",
    "addr:housenumber":"400",
    "addr:postcode":"34748",
    "addr:street":"Co Rd 468",
    "iso:country":"US",
    "sg:address":"400 Co Rd 468",
    "sg:city":"Leesburg",
    "sg:classifiers":[
        {
            "category":"Manufacturing",
            "subcategory":"Metals",
            "type":"Manufacturing & Wholesale Goods"
        }
    ],
    "sg:phone":"+1 352 787 3157",
    "sg:postcode":"34748",
    "sg:province":"FL",
    "sg:tags":[
        "steel"
    ],
    "wof:name":"Trucker's Machine & Steel Svc",
    "wof:placetype":"venue"
},
  "geometry": {"coordinates":[-81.91636699999999,28.817132],"type":"Point"}
}