{
  "type": "Feature",
  "properties": {
    "addr:full":"2505 NW 72nd Ave Miami FL 33122",
    "addr:housenumber":"2505",
    "addr:postcode":"33122",
    "addr:street":"Nw 72Nd Ave",
    "iso:country":"US",
    "sg:address":"2505 NW 72nd Ave",
    "sg:city":"Miami",
    "sg:classifiers":[
        {
            "category":"Manufacturing",
            "subcategory":"Printing",
            "type":"Manufacturing & Wholesale Goods"
        }
    ],
    "sg:phone":"+1 305 599 3926",
    "sg:postcode":"33122",
    "sg:province":"FL",
    "sg:tags":[
        "printer"
    ],
    "wof:name":"Palmetto Printing",
    "wof:placetype":"venue"
},
  "geometry": {"coordinates":[-80.31285800000001,25.797276],"type":"Point"}
}