{
  "type": "Feature",
  "properties": {
    "addr:full":"2900 4th St N St Petersburg FL 33704",
    "addr:housenumber":"2900",
    "addr:postcode":"33704",
    "addr:street":"4Th St N",
    "iso:country":"US",
    "sg:address":"2900 4th St N",
    "sg:city":"St Petersburg",
    "sg:classifiers":[
        {
            "category":"Banks & Credit Unions",
            "subcategory":"Bank",
            "type":"Services"
        }
    ],
    "sg:phone":"+1 727 895 4355",
    "sg:postcode":"33704",
    "sg:province":"FL",
    "sg:tags":[
        "loan",
        "real estate"
    ],
    "wof:name":"Community Lending Group",
    "wof:placetype":"venue"
},
  "geometry": {"coordinates":[-82.63856199999999,27.799422],"type":"Point"}
}