{
  "type": "Feature",
  "properties": {
    "iso:country":"US",
    "sg:address":"1110 Nelson St",
    "sg:city":"Dunedin",
    "sg:classifiers":[
        {
            "category":"Shopping",
            "subcategory":"Computers & Home Electronics",
            "type":"Retail Goods"
        }
    ],
    "sg:phone":"+1 727 734 5554",
    "sg:postcode":"34698",
    "sg:province":"FL",
    "sg:tags":[
        "audio"
    ],
    "wof:name":"A V Specialists Inc",
    "wof:placetype":"venue"
},
  "geometry": {"coordinates":[-82.772049,28.045607],"type":"Point"}
}