{
  "type": "Feature",
  "properties": {
    "addr:full":"3902 Corporex Park Dr Tampa FL 33619",
    "addr:housenumber":"3902",
    "addr:postcode":"33619",
    "addr:street":"Corporex Park Dr",
    "iso:country":"US",
    "sg:address":"3902 Corporex Park Dr",
    "sg:city":"Tampa",
    "sg:classifiers":[
        {
            "category":"Wholesale",
            "subcategory":"Non-durable Goods",
            "type":"Manufacturing & Wholesale Goods"
        }
    ],
    "sg:phone":"+1 813 885 5880",
    "sg:postcode":"33619",
    "sg:province":"FL",
    "sg:tags":[
        "import",
        "export",
        "gift",
        "scottish"
    ],
    "sg:website":"www.dunedin-scottish.com",
    "wof:name":"Dunedin Scottish Inc",
    "wof:placetype":"venue"
},
  "geometry": {"coordinates":[-82.379251,27.979477],"type":"Point"}
}