{
  "type": "Feature",
  "properties": {
    "addr:full":"3253 Lenox Ave Jacksonville FL 32254",
    "addr:housenumber":"3253",
    "addr:postcode":"32254",
    "addr:street":"Lenox Ave",
    "iso:country":"US",
    "sg:address":"3253 Lenox Ave",
    "sg:city":"Jacksonville",
    "sg:classifiers":[
        {
            "category":"Building & Trades",
            "subcategory":"Construction",
            "type":"Services"
        }
    ],
    "sg:phone":"+1 904 388 9811",
    "sg:postcode":"32254",
    "sg:province":"FL",
    "sg:tags":[
        "home",
        "builder"
    ],
    "wof:name":"Bay Front Homes Of America Inc",
    "wof:placetype":"venue"
},
  "geometry": {"coordinates":[-81.711653,30.322011],"type":"Point"}
}