{
  "type": "Feature",
  "properties": {
    "addr:full":"4932 Sunbeam Rd Jacksonville FL 32257",
    "addr:postcode":"4932;32257",
    "addr:street":"Sunbeam Rd",
    "iso:country":"US",
    "sg:address":"4932 Sunbeam Rd",
    "sg:city":"Jacksonville",
    "sg:classifiers":[
        {
            "category":"Professional",
            "subcategory":"Accounting & Tax Preparation",
            "type":"Services"
        }
    ],
    "sg:phone":"+1 904 827 0507",
    "sg:postcode":"32257",
    "sg:province":"FL",
    "sg:tags":[
        "billing"
    ],
    "sg:website":"www.gottlieb.com",
    "wof:name":"Martin Gottlieb & Associates",
    "wof:placetype":"venue"
},
  "geometry": {"coordinates":[-81.583519,30.205921],"type":"Point"}
}