{
  "type": "Feature",
  "properties": {
    "iso:country":"US",
    "sg:address":"25 S Magnolia Ave",
    "sg:city":"Orlando",
    "sg:classifiers":[
        {
            "category":"Professional",
            "subcategory":"Accounting & Tax Preparation",
            "type":"Services"
        }
    ],
    "sg:phone":"+1 407 422 1530",
    "sg:postcode":"32801",
    "sg:province":"FL",
    "sg:tags":[
        "accountant"
    ],
    "wof:name":"Young & Haas",
    "wof:placetype":"venue"
},
  "geometry": {"coordinates":[-81.37738,28.541526],"type":"Point"}
}