{
  "type": "Feature",
  "properties": {
    "addr:full":"26316 State Rd 54 Lutz FL 33559",
    "addr:housenumber":"26316;54",
    "addr:postcode":"33559",
    "addr:street":"State Rd",
    "iso:country":"US",
    "sg:address":"26316 State Rd 54",
    "sg:city":"Lutz",
    "sg:classifiers":[
        {
            "category":"Food & Beverages",
            "subcategory":"Meat & Fish",
            "type":"Retail Goods"
        }
    ],
    "sg:phone":"+1 813 994 0112",
    "sg:postcode":"33559",
    "sg:province":"FL",
    "wof:name":"North Tampa Quality Meats",
    "wof:placetype":"venue"
},
  "geometry": {"coordinates":[-82.38736299999999,28.218121],"type":"Point"}
}