{
  "type": "Feature",
  "properties": {
    "addr:full":"4710 W Tambay Ave Tampa FL 33611",
    "addr:housenumber":"4710",
    "addr:postcode":"33611",
    "addr:street":"W Tambay Ave",
    "iso:country":"US",
    "sg:address":"4710 W Tambay Ave",
    "sg:city":"Tampa",
    "sg:classifiers":[
        {
            "category":"Wholesale",
            "subcategory":"Durable Goods & Equipment",
            "type":"Manufacturing & Wholesale Goods"
        }
    ],
    "sg:phone":"+1 813 839 1755",
    "sg:postcode":"33611",
    "sg:province":"FL",
    "wof:name":"Magnolia House",
    "wof:placetype":"venue"
},
  "geometry": {"coordinates":[-82.525423,27.904683],"type":"Point"}
}