{
  "type": "Feature",
  "properties": {
    "iso:country":"US",
    "sg:address":"8150 Alhambra Ct",
    "sg:city":"Spring Hill",
    "sg:classifiers":[
        {
            "category":"Freight",
            "type":"Transportation"
        }
    ],
    "sg:phone":"+1 352 666 7222",
    "sg:postcode":"34606",
    "sg:province":"FL",
    "sg:tags":[
        "operator",
        "local",
        "trucking"
    ],
    "wof:name":"All Florida Courier Express",
    "wof:placetype":"venue"
},
  "geometry": {"coordinates":[-82.586957,28.438019],"type":"Point"}
}