{
  "type": "Feature",
  "properties": {
    "iso:country":"US",
    "sg:address":"29 S Ivey Ln",
    "sg:city":"Orlando",
    "sg:classifiers":[
        {
            "category":"Place Of Worship",
            "subcategory":"Church",
            "type":"Public Place"
        },
        {
            "category":"Place Of Worship",
            "type":"Public Place"
        }
    ],
    "sg:phone":"+1 407 298 6635",
    "sg:postcode":"32811",
    "sg:province":"FL",
    "sg:tags":[
        "churches-pentecostal-independent",
        "churches-pentecostal"
    ],
    "wof:name":"True Deliverance Center",
    "wof:placetype":"venue"
},
  "geometry": {"coordinates":[-81.43446400000001,28.541447],"type":"Point"}
}