{
  "type": "Feature",
  "properties": {
    "addr:full":"7601 Biscayne Blvd Miami FL 33138",
    "addr:housenumber":"7601",
    "addr:postcode":"33138",
    "addr:street":"Biscayne Blvd",
    "iso:country":"US",
    "sg:address":"7601 Biscayne Blvd",
    "sg:city":"Miami",
    "sg:classifiers":[
        {
            "category":"Shopping",
            "subcategory":"Florist",
            "type":"Retail Goods"
        }
    ],
    "sg:phone":"+1 305 758 2717",
    "sg:postcode":"33138",
    "sg:province":"FL",
    "wof:name":"Belle Meade Florist",
    "wof:placetype":"venue"
},
  "geometry": {"coordinates":[-80.184524,25.84497],"type":"Point"}
}