{
  "type": "Feature",
  "properties": {
    "addr:full":"4302 W Broward Blvd Fort Lauderdale FL 33317",
    "addr:housenumber":"4302",
    "addr:postcode":"33317",
    "addr:street":"W Broward Blvd",
    "iso:country":"US",
    "sg:address":"4302 W Broward Blvd",
    "sg:city":"Fort Lauderdale",
    "sg:classifiers":[
        {
            "category":"Health Services",
            "subcategory":"Doctor",
            "type":"Services"
        }
    ],
    "sg:phone":"+1 954 583 0778",
    "sg:postcode":"33317",
    "sg:province":"FL",
    "sg:tags":[
        "medical"
    ],
    "wof:name":"Prieto O MD Faafp",
    "wof:placetype":"venue"
},
  "geometry": {"coordinates":[-80.20609,26.120804],"type":"Point"}
}