{
  "type": "Feature",
  "properties": {
    "iso:country":"US",
    "sg:address":"616 NE 8th St",
    "sg:city":"Hallandale",
    "sg:classifiers":[
        {
            "category":"Retail",
            "subcategory":"Self-service Laundry",
            "type":"Services"
        }
    ],
    "sg:phone":"+1 954 458 5494",
    "sg:postcode":"33009",
    "sg:province":"FL",
    "sg:tags":[
        "operated",
        "coin"
    ],
    "wof:name":"Mona Lisa Coin Laundry",
    "wof:placetype":"venue"
},
  "geometry": {"coordinates":[-80.140719,25.993906],"type":"Point"}
}