{
  "type": "Feature",
  "properties": {
    "iso:country":"US",
    "sg:address":"1655 SW 34th St",
    "sg:city":"Fort Lauderdale",
    "sg:classifiers":[
        {
            "category":"Retail",
            "subcategory":"Auto Rental",
            "type":"Services"
        }
    ],
    "sg:phone":"+1 954 359 4770",
    "sg:postcode":"33315",
    "sg:province":"FL",
    "sg:tags":[
        "renting",
        "automobile"
    ],
    "wof:name":"Budget Rent A Car",
    "wof:placetype":"venue"
},
  "geometry": {"coordinates":[-80.15876799999999,26.081066],"type":"Point"}
}