{
  "type": "Feature",
  "properties": {
    "iso:country":"US",
    "sg:address":"10341 Regent Cir",
    "sg:city":"Naples",
    "sg:classifiers":[
        {
            "category":"Insurance",
            "subcategory":"Insurance Agent",
            "type":"Services"
        }
    ],
    "sg:phone":"+1 239 591 3779",
    "sg:postcode":"34109",
    "sg:province":"FL",
    "sg:website":"www.dagency.com",
    "wof:name":"Downey Agency Inc",
    "wof:placetype":"venue"
},
  "geometry": {"coordinates":[-81.759986,26.267175],"type":"Point"}
}