{
  "type": "Feature",
  "properties": {
    "addr:full":"8222 Glades Rd Boca Raton FL 33432",
    "addr:housenumber":"8222",
    "addr:postcode":"33432",
    "addr:street":"Glades Rd",
    "iso:country":"US",
    "sg:address":"8222 Glades Rd",
    "sg:city":"Boca Raton",
    "sg:classifiers":[
        {
            "category":"Retail",
            "subcategory":"Photofinishing",
            "type":"Services"
        }
    ],
    "sg:phone":"+1 561 613 0360",
    "sg:postcode":"33432",
    "sg:province":"FL",
    "sg:tags":[
        "photo",
        "finishing"
    ],
    "wof:name":"Precision Photo",
    "wof:placetype":"venue"
},
  "geometry": {"coordinates":[-80.17493899999999,26.367819],"type":"Point"}
}