{
  "type": "Feature",
  "properties": {
    "addr:full":"7105 W McNab Rd North Lauderdale FL 33321",
    "addr:housenumber":"7105",
    "addr:postcode":"33321",
    "addr:street":"W Mcnab Rd",
    "iso:country":"US",
    "sg:address":"7105 W McNab Rd",
    "sg:city":"North Lauderdale",
    "sg:classifiers":[
        {
            "category":"Shopping",
            "subcategory":"Pharmacy",
            "type":"Retail Goods"
        }
    ],
    "sg:phone":"+1 954 718 6826",
    "sg:postcode":"33321",
    "sg:province":"FL",
    "sg:tags":[
        "photofinishing",
        "laboratory"
    ],
    "wof:name":"Walgreens",
    "wof:placetype":"venue"
},
  "geometry": {"coordinates":[-80.221037,26.208601],"type":"Point"}
}