{
  "type": "Feature",
  "properties": {
    "addr:full":"310 NE Olive Ave Port Saint Lucie FL 34952",
    "addr:housenumber":"310",
    "addr:postcode":"34952",
    "addr:street":"Ne Olive Ave",
    "iso:country":"US",
    "sg:address":"310 NE Olive Ave",
    "sg:city":"Port Saint Lucie",
    "sg:classifiers":[
        {
            "category":"Building & Trades",
            "subcategory":"Construction",
            "type":"Services"
        }
    ],
    "sg:phone":"+1 772 344 0255",
    "sg:postcode":"34952",
    "sg:province":"FL",
    "sg:tags":[
        "carpentry",
        "contractor"
    ],
    "wof:name":"Jay Waterbury Cab Installation",
    "wof:placetype":"venue"
},
  "geometry": {"coordinates":[-80.330158,27.331553],"type":"Point"}
}