{
  "type": "Feature",
  "properties": {
    "addr:full":"100 N Tyndall Pkwy Panama City FL 32404",
    "addr:housenumber":"100",
    "addr:postcode":"32404",
    "addr:street":"N Tyndall Pkwy",
    "iso:country":"US",
    "sg:address":"100 N Tyndall Pkwy",
    "sg:city":"Panama City",
    "sg:classifiers":[
        {
            "category":"Shopping",
            "subcategory":"Music",
            "type":"Retail Goods"
        }
    ],
    "sg:phone":"+1 850 785 5839",
    "sg:postcode":"32404",
    "sg:province":"FL",
    "sg:tags":[
        "video",
        "disc",
        "tape",
        "cassette"
    ],
    "wof:name":"Video Warehouse",
    "wof:placetype":"venue"
},
  "geometry": {"coordinates":[-85.59110099999999,30.145612],"type":"Point"}
}