{
  "type": "Feature",
  "properties": {
    "iso:country":"US",
    "sg:address":"2490 Bronco Dr",
    "sg:city":"St Cloud",
    "sg:classifiers":[
        {
            "category":"Building & Trades",
            "subcategory":"Construction",
            "type":"Services"
        }
    ],
    "sg:phone":"+1 407 873 9605",
    "sg:postcode":"34771",
    "sg:province":"FL",
    "sg:tags":[
        "sewer",
        "contractor"
    ],
    "wof:name":"Darrell Porter Sewer & Water",
    "wof:placetype":"venue"
},
  "geometry": {"coordinates":[-81.148585,28.231463],"type":"Point"}
}