{
  "type": "Feature",
  "properties": {
    "iso:country":"US",
    "sg:address":"6219 Lois St",
    "sg:city":"Panama City",
    "sg:classifiers":[
        {
            "category":"Building & Trades",
            "subcategory":"Construction",
            "type":"Services"
        }
    ],
    "sg:phone":"+1 850 874 9267",
    "sg:postcode":"32404",
    "sg:province":"FL",
    "sg:tags":[
        "house"
    ],
    "wof:name":"Peter Kaufman",
    "wof:placetype":"venue"
},
  "geometry": {"coordinates":[-85.58261400000001,30.149233],"type":"Point"}
}