{
  "type": "Feature",
  "properties": {
    "addr:full":"2501 S Park Rd Hallandale Beach FL 33009",
    "addr:housenumber":"2501",
    "addr:postcode":"33009",
    "addr:street":"S Park Rd",
    "iso:country":"US",
    "sg:address":"2501 S Park Rd",
    "sg:city":"Hallandale Beach",
    "sg:classifiers":[
        {
            "category":"Retail",
            "subcategory":"Repair Shop",
            "type":"Services"
        }
    ],
    "sg:phone":"+1 305 758 4731",
    "sg:postcode":"33009",
    "sg:province":"FL",
    "sg:tags":[
        "equipment",
        "conditioning",
        "air"
    ],
    "wof:name":"Reeve Air Conditioning Inc",
    "wof:placetype":"venue"
},
  "geometry": {"coordinates":[-80.17089799999999,25.987885],"type":"Point"}
}