{
  "type": "Feature",
  "properties": {
    "iso:country":"US",
    "sg:address":"5505 Johns Rd",
    "sg:city":"Tampa",
    "sg:classifiers":[
        {
            "category":"Wholesale",
            "subcategory":"Electrical",
            "type":"Manufacturing & Wholesale Goods"
        }
    ],
    "sg:phone":"+1 813 888 7436",
    "sg:postcode":"33634",
    "sg:province":"FL",
    "sg:tags":[
        "electronic",
        "representative"
    ],
    "wof:name":"Lewis & Clark",
    "wof:placetype":"venue"
},
  "geometry": {"coordinates":[-82.537931,28.008471],"type":"Point"}
}