{
  "type": "Feature",
  "properties": {
    "addr:full":"1416 59th St W Bradenton FL 34209",
    "addr:housenumber":"1416",
    "addr:postcode":"34209",
    "addr:street":"59Th St W",
    "iso:country":"US",
    "sg:address":"1416 59th St W",
    "sg:city":"Bradenton",
    "sg:phone":"+1 941 792 2934",
    "sg:postcode":"34209",
    "sg:province":"FL",
    "wof:name":"Catalano Philip M Md",
    "wof:placetype":"venue"
},
  "geometry": {"coordinates":[-82.620424,27.487435],"type":"Point"}
}