{
  "type": "Feature",
  "properties": {
    "addr:full":"900 S Orange Ave Orlando FL 32806",
    "addr:housenumber":"900",
    "addr:postcode":"32806",
    "addr:street":"S Orange Ave",
    "iso:country":"US",
    "sg:address":"900 S Orange Ave",
    "sg:city":"Orlando",
    "sg:classifiers":[
        {
            "category":"Food & Beverages",
            "subcategory":"Groceries & Convenience Stores",
            "type":"Retail Goods"
        }
    ],
    "sg:phone":"+1 407 872 1401",
    "sg:postcode":"32806",
    "sg:province":"FL",
    "wof:name":"Orange Texaco",
    "wof:placetype":"venue"
},
  "geometry": {"coordinates":[-81.376492,28.529166],"type":"Point"}
}