{
  "type": "Feature",
  "properties": {
    "addr:full":"1102 SW 27th Ave Miami FL 33135",
    "addr:housenumber":"1102",
    "addr:postcode":"33135",
    "addr:street":"Sw 27Th Ave",
    "iso:country":"US",
    "sg:address":"1102 SW 27th Ave",
    "sg:city":"Miami",
    "sg:classifiers":[
        {
            "category":"Social Services",
            "subcategory":"Child Care",
            "type":"Services"
        }
    ],
    "sg:phone":"+1 305 644 0024",
    "sg:postcode":"33135",
    "sg:province":"FL",
    "sg:tags":[
        "day"
    ],
    "wof:name":"Sunflowers Preschool & Daycare",
    "wof:placetype":"venue"
},
  "geometry": {"coordinates":[-80.238899,25.761999],"type":"Point"}
}