{
  "type": "Feature",
  "properties": {
    "iso:country":"US",
    "sg:address":"118 Mockingbird Ln",
    "sg:city":"Edgewater",
    "sg:classifiers":[
        {
            "category":"Real Estate",
            "subcategory":"Real Estate Operator",
            "type":"Services"
        }
    ],
    "sg:phone":"+1 386 428 8749",
    "sg:postcode":"32132",
    "sg:province":"FL",
    "sg:tags":[
        "building",
        "apartment"
    ],
    "wof:name":"Edgewater Park Apartments",
    "wof:placetype":"venue"
},
  "geometry": {"coordinates":[-80.910685,28.996444],"type":"Point"}
}