{
  "type": "Feature",
  "properties": {
    "addr:full":"4440 NW 74th Ave Miami FL 33166",
    "addr:housenumber":"4440",
    "addr:postcode":"33166",
    "addr:street":"Nw 74Th Ave",
    "iso:country":"US",
    "sg:address":"4440 NW 74th Ave",
    "sg:city":"Miami",
    "sg:classifiers":[
        {
            "category":"Professional",
            "subcategory":"Business Services",
            "type":"Services"
        }
    ],
    "sg:phone":"+1 305 477 3611",
    "sg:postcode":"33166",
    "sg:province":"FL",
    "sg:tags":[
        "exporter"
    ],
    "sg:website":"http://www.gabrielexport.com",
    "wof:name":"Gabriel Export Corp",
    "wof:placetype":"venue"
},
  "geometry": {"coordinates":[-80.317317,25.814378],"type":"Point"}
}