{
  "type": "Feature",
  "properties": {
    "iso:country":"US",
    "sg:address":"1102 Fillmore Ave",
    "sg:city":"Lehigh Acres",
    "sg:classifiers":[
        {
            "category":"Building & Trades",
            "subcategory":"Construction",
            "type":"Services"
        }
    ],
    "sg:phone":"+1 239 368 1800",
    "sg:postcode":"33936",
    "sg:province":"FL",
    "sg:tags":[
        "water",
        "well",
        "drilling"
    ],
    "wof:name":"Charlie Howard Well Drilling",
    "wof:placetype":"venue"
},
  "geometry": {"coordinates":[-81.64549700000001,26.603627],"type":"Point"}
}