{
  "type": "Feature",
  "properties": {
    "iso:country":"US",
    "sg:address":"3300 S Tamiami Trl Ste 8",
    "sg:city":"Sarasota",
    "sg:classifiers":[
        {
            "category":"Health Services",
            "subcategory":"Dentist",
            "type":"Services"
        }
    ],
    "sg:phone":"+1 941 953 7500",
    "sg:postcode":"34239",
    "sg:province":"FL",
    "sg:tags":[
        "dentists-orthodontists"
    ],
    "wof:name":"Winkler, David Dds Ms Pa",
    "wof:placetype":"venue"
},
  "geometry": {"coordinates":[-82.530243,27.304359],"type":"Point"}
}