{
  "type": "Feature",
  "properties": {
    "addr:full":"8348 NW 74th Ave Miami FL 33166",
    "addr:housenumber":"8348",
    "addr:postcode":"33166",
    "addr:street":"Nw 74Th Ave",
    "iso:country":"US",
    "sg:address":"8348 NW 74th Ave",
    "sg:city":"Miami",
    "sg:classifiers":[
        {
            "category":"Manufacturing",
            "subcategory":"Tools & Machinery",
            "type":"Manufacturing & Wholesale Goods"
        }
    ],
    "sg:phone":"+1 305 792 2656",
    "sg:postcode":"33166",
    "sg:province":"FL",
    "sg:tags":[
        "equipment",
        "peripheral",
        "computer",
        "mfg"
    ],
    "wof:name":"Toc Trading Inc",
    "wof:placetype":"venue"
},
  "geometry": {"coordinates":[-80.31881799999999,25.848404],"type":"Point"}
}