{
  "type": "Feature",
  "properties": {
    "addr:full":"1501 Venera Ave Miami FL 33146",
    "addr:housenumber":"1501",
    "addr:postcode":"33146",
    "addr:street":"Venera Ave",
    "iso:country":"US",
    "sg:address":"1501 Venera Ave",
    "sg:city":"Miami",
    "sg:classifiers":[
        {
            "category":"Wholesale",
            "subcategory":"Books, Periodicals, & Newspapers",
            "type":"Manufacturing & Wholesale Goods"
        }
    ],
    "sg:phone":"+1 305 740 7170",
    "sg:postcode":"33146",
    "sg:province":"FL",
    "sg:tags":[
        "dealers-wholesale",
        "news",
        "publishers-periodical"
    ],
    "wof:name":"Wine News",
    "wof:placetype":"venue"
},
  "geometry": {"coordinates":[-80.28280599999999,25.70676],"type":"Point"}
}