{
  "type": "Feature",
  "properties": {
    "iso:country":"US",
    "sg:address":"136 S Holiday Rd",
    "sg:city":"Miramar Beach",
    "sg:classifiers":[
        {
            "category":"Professional",
            "type":"Services"
        }
    ],
    "sg:phone":"+1 850 269 1081",
    "sg:postcode":"32550",
    "sg:province":"FL",
    "sg:tags":[
        "establishment"
    ],
    "wof:name":"Cappelletti Enterprises",
    "wof:placetype":"venue"
},
  "geometry": {"coordinates":[-86.380543,30.383044],"type":"Point"}
}