{
  "type": "Feature",
  "properties": {
    "iso:country":"US",
    "sg:address":"680 2nd Ave N",
    "sg:city":"Naples",
    "sg:classifiers":[
        {
            "category":"Health Services",
            "subcategory":"Doctor",
            "type":"Services"
        }
    ],
    "sg:phone":"+1 239 254 0535",
    "sg:postcode":"34102",
    "sg:province":"FL",
    "sg:tags":[
        "physician",
        "surgeon"
    ],
    "wof:name":"Comprehensive Psychiatric Svc",
    "wof:placetype":"venue"
},
  "geometry": {"coordinates":[-81.79982800000001,26.149037],"type":"Point"}
}