{
  "type": "Feature",
  "properties": {
    "iso:country":"US",
    "sg:address":"1402 Miller Ln",
    "sg:city":"Lakeland",
    "sg:classifiers":[
        {
            "category":"Wholesale",
            "subcategory":"Painting Supplies",
            "type":"Manufacturing & Wholesale Goods"
        },
        {
            "category":"Home & Garden",
            "subcategory":"Building Materials",
            "type":"Retail Goods"
        }
    ],
    "sg:phone":"+1 863 686 9014",
    "sg:postcode":"33801",
    "sg:province":"FL",
    "sg:tags":[
        "wall",
        "wallpaper",
        "coating",
        "wallcoverings"
    ],
    "wof:name":"Taylor Paint & Wallpaper",
    "wof:placetype":"venue"
},
  "geometry": {"coordinates":[-81.936036,28.02977],"type":"Point"}
}