{
  "type": "Feature",
  "properties": {
    "addr:full":"1019 Derbyshire Rd Daytona Beach FL 32117",
    "addr:housenumber":"1019",
    "addr:postcode":"32117",
    "addr:street":"Derbyshire Rd",
    "iso:country":"US",
    "sg:address":"1019 Derbyshire Rd",
    "sg:city":"Daytona Beach",
    "sg:classifiers":[
        {
            "category":"Building & Trades",
            "subcategory":"Landscaping Services",
            "type":"Services"
        }
    ],
    "sg:phone":"+1 386 238 6407",
    "sg:postcode":"32117",
    "sg:province":"FL",
    "sg:tags":[
        "tree"
    ],
    "wof:name":"Greg Driggers Tree Service",
    "wof:placetype":"venue"
},
  "geometry": {"coordinates":[-81.064859,29.233174],"type":"Point"}
}