{
  "type": "Feature",
  "properties": {
    "addr:full":"119 Habersham Dr Longwood FL 32779",
    "addr:housenumber":"119",
    "addr:postcode":"32779",
    "addr:street":"Habersham Dr",
    "iso:country":"US",
    "sg:address":"119 Habersham Dr",
    "sg:city":"Longwood",
    "sg:classifiers":[
        {
            "category":"Manufacturing",
            "subcategory":"Tools & Machinery",
            "type":"Manufacturing & Wholesale Goods"
        }
    ],
    "sg:phone":"+1 407 774 2747",
    "sg:postcode":"32779",
    "sg:province":"FL",
    "sg:tags":[
        "optical",
        "mfg"
    ],
    "wof:name":"Nicole Optical",
    "wof:placetype":"venue"
},
  "geometry": {"coordinates":[-81.450452,28.699059],"type":"Point"}
}