{
  "type": "Feature",
  "properties": {
    "iso:country":"US",
    "sg:address":"7870 NW 52nd St",
    "sg:city":"Doral",
    "sg:classifiers":[
        {
            "category":"Recreation",
            "subcategory":"Dog Park",
            "type":"Entertainment"
        },
        {
            "category":"Shopping",
            "subcategory":"Pets & Pet Supplies",
            "type":"Retail Goods"
        },
        {
            "category":"Retail",
            "subcategory":"Pet Boarding",
            "type":"Services"
        },
        {
            "category":"Retail",
            "subcategory":"Animal Services",
            "type":"Services"
        }
    ],
    "sg:phone":"+1 305 592 2558",
    "sg:postcode":"33166",
    "sg:province":"FL",
    "sg:tags":[
        "sitting",
        "exercising",
        "kennel",
        "grooming",
        "day",
        "store",
        "care"
    ],
    "sg:website":"http://www.puppyparadisedoral.com",
    "wof:name":"Puppy Paradise",
    "wof:placetype":"venue"
},
  "geometry": {"coordinates":[-80.32554,25.820721],"type":"Point"}
}