{
  "type": "Feature",
  "properties": {
    "iso:country":"US",
    "sg:address":"18621 NW 11th Rd",
    "sg:city":"Miami",
    "sg:classifiers":[
        {
            "category":"Shopping",
            "subcategory":"Stationery & Office Supplies",
            "type":"Retail Goods"
        }
    ],
    "sg:phone":"+1 305 493 0562",
    "sg:postcode":"33169",
    "sg:province":"FL",
    "sg:tags":[
        "equipment"
    ],
    "wof:name":"Office Elite Services Inc",
    "wof:placetype":"venue"
},
  "geometry": {"coordinates":[-80.219577,25.945032],"type":"Point"}
}