{
  "type": "Feature",
  "properties": {
    "addr:full":"655 Central Ave St Petersburg FL 33701",
    "addr:housenumber":"655",
    "addr:postcode":"33701",
    "addr:street":"Central Ave",
    "iso:country":"US",
    "sg:address":"655 Central Ave",
    "sg:city":"St Petersburg",
    "sg:classifiers":[
        {
            "category":"Shopping",
            "subcategory":"Jewelry",
            "type":"Retail Goods"
        },
        {
            "category":"Shopping",
            "subcategory":"Clothing, Apparel, & Fashions",
            "type":"Retail Goods"
        }
    ],
    "sg:phone":"+1 727 823 0823",
    "sg:postcode":"33701",
    "sg:province":"FL",
    "sg:tags":[
        "jeweler"
    ],
    "wof:name":"Gold Corner",
    "wof:placetype":"venue"
},
  "geometry": {"coordinates":[-82.641729,27.7712],"type":"Point"}
}