{
  "type": "Feature",
  "properties": {
    "iso:country":"US",
    "sg:address":"8384 Pines Blvd",
    "sg:city":"Hollywood",
    "sg:classifiers":[
        {
            "category":"Health Services",
            "subcategory":"Medical Lab",
            "type":"Services"
        }
    ],
    "sg:phone":"+1 954 450 4020",
    "sg:postcode":"33024",
    "sg:province":"FL",
    "sg:tags":[
        "laboratory"
    ],
    "wof:name":"Horizon Open M R I",
    "wof:placetype":"venue"
},
  "geometry": {"coordinates":[-80.254679,26.009001],"type":"Point"}
}