{
  "type": "Feature",
  "properties": {
    "iso:country":"US",
    "sg:address":"2018 Lewis Turner Blvd",
    "sg:city":"Fort Walton Bch",
    "sg:classifiers":[
        {
            "category":"Professional",
            "subcategory":"Computer Services",
            "type":"Services"
        }
    ],
    "sg:phone":"+1 850 864 2552",
    "sg:postcode":"32547",
    "sg:province":"FL",
    "sg:tags":[
        "consultant",
        "designer"
    ],
    "wof:name":"Decision Sciences Inc",
    "wof:placetype":"venue"
},
  "geometry": {"coordinates":[-86.60788599999999,30.469703],"type":"Point"}
}