{
  "type": "Feature",
  "properties": {
    "iso:country":"US",
    "sg:address":"141 9th St N",
    "sg:city":"Naples",
    "sg:classifiers":[
        {
            "category":"Food & Beverages",
            "subcategory":"Groceries & Convenience Stores",
            "type":"Retail Goods"
        }
    ],
    "sg:phone":"+1 877 352 1860",
    "sg:postcode":"34102",
    "sg:province":"FL",
    "sg:website":"http://www.wynnsonline.com",
    "wof:name":"Wynn's Market",
    "wof:placetype":"venue"
},
  "geometry": {"coordinates":[-81.79586,26.148908],"type":"Point"}
}