{
  "type": "Feature",
  "properties": {
    "iso:country":"US",
    "sg:address":"11021 SW 176th St",
    "sg:city":"Miami",
    "sg:classifiers":[
        {
            "category":"Restaurant",
            "type":"Food & Drink"
        }
    ],
    "sg:phone":"+1 305 234 7887",
    "sg:postcode":"33157",
    "sg:province":"FL",
    "wof:name":"J & L's Restaurant",
    "wof:placetype":"venue"
},
  "geometry": {"coordinates":[-80.372923,25.605449],"type":"Point"}
}