{
  "type": "Feature",
  "properties": {
    "iso:country":"US",
    "sg:address":"10730 NW 58th St",
    "sg:city":"Doral",
    "sg:classifiers":[
        {
            "category":"Education",
            "subcategory":"Special Training",
            "type":"Public Place"
        },
        {
            "category":"Arena",
            "subcategory":"Sports Club",
            "type":"Entertainment"
        }
    ],
    "sg:phone":"+1 305 592 4225",
    "sg:postcode":"33178",
    "sg:province":"FL",
    "sg:tags":[
        "instruction",
        "equipment",
        "self defense",
        "martial art"
    ],
    "wof:name":"New Age Karate Llc",
    "wof:placetype":"venue"
},
  "geometry": {"coordinates":[-80.37130000000001,25.8263],"type":"Point"}
}