{
  "type": "Feature",
  "properties": {
    "iso:country":"US",
    "sg:address":"2550 NW 5th Ave",
    "sg:city":"Miami",
    "sg:classifiers":[
        {
            "category":"Wholesale",
            "subcategory":"Apparel",
            "type":"Manufacturing & Wholesale Goods"
        },
        {
            "category":"Shopping",
            "subcategory":"Clothing, Apparel, & Fashions",
            "type":"Retail Goods"
        }
    ],
    "sg:phone":"+1 305 326 1004",
    "sg:postcode":"33127",
    "sg:province":"FL",
    "wof:name":"Postal International Corp",
    "wof:placetype":"venue"
},
  "geometry": {"coordinates":[-80.20320599999999,25.800851],"type":"Point"}
}