{
  "type": "Feature",
  "properties": {
    "iso:country":"US",
    "sg:address":"7222 Isle of Capri Rd",
    "sg:city":"Naples",
    "sg:classifiers":[
        {
            "category":"Shopping",
            "subcategory":"Gifts & Souvenirs",
            "type":"Retail Goods"
        }
    ],
    "sg:phone":"+1 239 417 5530",
    "sg:postcode":"34114",
    "sg:province":"FL",
    "sg:tags":[
        "shop"
    ],
    "wof:name":"Harry & David",
    "wof:placetype":"venue"
},
  "geometry": {"coordinates":[-81.700123,26.042791],"type":"Point"}
}