{
  "type": "Feature",
  "properties": {
    "iso:country":"US",
    "sg:address":"133 Inlet Harbor Rd",
    "sg:city":"Daytona Beach",
    "sg:classifiers":[
        {
            "category":"Recreation",
            "subcategory":"Marina",
            "type":"Entertainment"
        }
    ],
    "sg:phone":"+1 386 767 3266",
    "sg:postcode":"32127",
    "sg:province":"FL",
    "sg:tags":[
        "operation",
        "eating"
    ],
    "wof:name":"Inlet Harbor Marina & Rest",
    "wof:placetype":"venue"
},
  "geometry": {"coordinates":[-80.93684500000001,29.090532],"type":"Point"}
}