{
  "type": "Feature",
  "properties": {
    "iso:country":"US",
    "sg:address":"510 W Blount St",
    "sg:city":"Pensacola",
    "sg:classifiers":[
        {
            "category":"Organizations",
            "subcategory":"Membership Organization",
            "type":"Services"
        }
    ],
    "sg:phone":"+1 850 470 0691",
    "sg:postcode":"32501",
    "sg:province":"FL",
    "wof:name":"E & P Association",
    "wof:placetype":"venue"
},
  "geometry": {"coordinates":[-87.226195,30.42746],"type":"Point"}
}