{
  "type": "Feature",
  "properties": {
    "addr:full":"2892 Carew Ave Winter Park FL 32789",
    "addr:housenumber":"2892",
    "addr:postcode":"32789",
    "addr:street":"Carew Ave",
    "iso:country":"US",
    "sg:address":"2892 Carew Ave",
    "sg:city":"Winter Park",
    "sg:classifiers":[
        {
            "category":"Building & Trades",
            "subcategory":"Construction",
            "type":"Services"
        }
    ],
    "sg:phone":"+1 407 647 8567",
    "sg:postcode":"32789",
    "sg:province":"FL",
    "sg:tags":[
        "house"
    ],
    "wof:name":"Progressive Home Builders Inc",
    "wof:placetype":"venue"
},
  "geometry": {"coordinates":[-81.388514,28.5995],"type":"Point"}
}