{
  "type": "Feature",
  "properties": {
    "addr:full":"30210 US Hwy 19 Clearwater FL 33761",
    "addr:postcode":"30210;33761",
    "addr:street":"Us Hwy 19",
    "iso:country":"US",
    "sg:address":"30210 US Hwy 19",
    "sg:city":"Clearwater",
    "sg:classifiers":[
        {
            "category":"Shopping",
            "type":"Retail Goods"
        }
    ],
    "sg:phone":"+1 727 787 0200",
    "sg:postcode":"33761",
    "sg:province":"FL",
    "sg:tags":[
        "merchandise"
    ],
    "wof:name":"Silk Plants Plus",
    "wof:placetype":"venue"
},
  "geometry": {"coordinates":[-82.738581,28.046713],"type":"Point"}
}