{
  "type": "Feature",
  "properties": {
    "iso:country":"US",
    "sg:address":"13234 Saint Tropez Cir",
    "sg:city":"Palm Beach Gardens",
    "sg:classifiers":[
        {
            "category":"Retail",
            "subcategory":"Auto Repair",
            "type":"Services"
        }
    ],
    "sg:phone":"+1 561 624 2202",
    "sg:postcode":"33410",
    "sg:province":"FL",
    "sg:tags":[
        "body"
    ],
    "wof:name":"Automotive Resurfacing Tech",
    "wof:placetype":"venue"
},
  "geometry": {"coordinates":[-80.072934,26.871564],"type":"Point"}
}