{
  "type": "Feature",
  "properties": {
    "addr:full":"5200 Blue Lagoon Dr Miami FL 33126",
    "addr:housenumber":"5200",
    "addr:postcode":"33126",
    "addr:street":"Blue Lagoon Dr",
    "iso:country":"US",
    "sg:address":"5200 Blue Lagoon Dr",
    "sg:city":"Miami",
    "sg:classifiers":[
        {
            "category":"Travel",
            "subcategory":"Travel Agent",
            "type":"Entertainment"
        }
    ],
    "sg:phone":"+1 305 264 9090",
    "sg:postcode":"33126",
    "sg:province":"FL",
    "sg:tags":[
        "cruise"
    ],
    "wof:name":"Residiensea Limited",
    "wof:placetype":"venue"
},
  "geometry": {"coordinates":[-80.28168599999999,25.781923],"type":"Point"}
}