{
  "type": "Feature",
  "properties": {
    "iso:country":"US",
    "sg:address":"1225 Lake Rogers Cir",
    "sg:city":"Oviedo",
    "sg:classifiers":[
        {
            "category":"Wholesale",
            "subcategory":"Sporting Goods",
            "type":"Manufacturing & Wholesale Goods"
        }
    ],
    "sg:phone":"+1 407 366 8767",
    "sg:postcode":"32765",
    "sg:province":"FL",
    "wof:name":"Jnaf Inc",
    "wof:placetype":"venue"
},
  "geometry": {"coordinates":[-81.193253,28.652638],"type":"Point"}
}