{
  "type": "Feature",
  "properties": {
    "iso:country":"US",
    "sg:address":"301 21st St E",
    "sg:city":"Bradenton",
    "sg:classifiers":[
        {
            "category":"Manufacturing",
            "subcategory":"Printing",
            "type":"Manufacturing & Wholesale Goods"
        }
    ],
    "sg:phone":"+1 941 761 0155",
    "sg:postcode":"34208",
    "sg:province":"FL",
    "wof:name":"NTC",
    "wof:placetype":"venue"
},
  "geometry": {"coordinates":[-82.538479,27.496375],"type":"Point"}
}