{
  "type": "Feature",
  "properties": {
    "addr:full":"319 S Lake Ave Lakeland FL 33801",
    "addr:housenumber":"319",
    "addr:postcode":"33801",
    "addr:street":"S Lake Ave",
    "iso:country":"US",
    "sg:address":"319 S Lake Ave",
    "sg:city":"Lakeland",
    "sg:classifiers":[
        {
            "category":"Building & Trades",
            "subcategory":"Construction",
            "type":"Services"
        }
    ],
    "sg:phone":"+1 863 688 3438",
    "sg:postcode":"33801",
    "sg:province":"FL",
    "sg:tags":[
        "house"
    ],
    "wof:name":"Integrity Home Improvement",
    "wof:placetype":"venue"
},
  "geometry": {"coordinates":[-81.949063,28.040524],"type":"Point"}
}