{
  "type": "Feature",
  "properties": {
    "iso:country":"US",
    "sg:address":"6790 Mystic Ln",
    "sg:city":"Pensacola",
    "sg:classifiers":[
        {
            "category":"Building & Trades",
            "subcategory":"Construction",
            "type":"Services"
        }
    ],
    "sg:phone":"+1 850 944 0348",
    "sg:postcode":"32526",
    "sg:province":"FL",
    "sg:tags":[
        "masonry",
        "contractor"
    ],
    "wof:name":"Taylor Stucco Inc",
    "wof:placetype":"venue"
},
  "geometry": {"coordinates":[-87.29492,30.479139],"type":"Point"}
}