{
  "type": "Feature",
  "properties": {
    "iso:country":"US",
    "sg:address":"446 N Highland St",
    "sg:city":"Mount Dora",
    "sg:classifiers":[
        {
            "category":"Food & Beverages",
            "subcategory":"Groceries & Convenience Stores",
            "type":"Retail Goods"
        }
    ],
    "sg:phone":"+1 352 735 4054",
    "sg:postcode":"32757",
    "sg:province":"FL",
    "wof:name":"Cumberland Farms 9616",
    "wof:placetype":"venue"
},
  "geometry": {"coordinates":[-81.63633400000001,28.800109],"type":"Point"}
}