{
  "type": "Feature",
  "properties": {
    "iso:country":"US",
    "sg:address":"4652 Hiatus Rd",
    "sg:city":"Fort Lauderdale",
    "sg:classifiers":[
        {
            "category":"Wholesale",
            "subcategory":"Apparel",
            "type":"Manufacturing & Wholesale Goods"
        },
        {
            "category":"Manufacturing",
            "subcategory":"Apparel",
            "type":"Manufacturing & Wholesale Goods"
        }
    ],
    "sg:phone":"+1 954 747 6446",
    "sg:postcode":"33351",
    "sg:province":"FL",
    "sg:tags":[
        "textile",
        "bag",
        "handbag",
        "mfg"
    ],
    "wof:name":"Casablanca Bags",
    "wof:placetype":"venue"
},
  "geometry": {"coordinates":[-80.29083799999999,26.180823],"type":"Point"}
}