{
  "type": "Feature",
  "properties": {
    "addr:full":"6671 W Indiantown Rd Jupiter FL 33458",
    "addr:housenumber":"6671",
    "addr:postcode":"33458",
    "addr:street":"W Indiantown Rd",
    "iso:country":"US",
    "sg:address":"6671 W Indiantown Rd",
    "sg:city":"Jupiter",
    "sg:classifiers":[
        {
            "category":"Building & Trades",
            "subcategory":"Construction",
            "type":"Services"
        }
    ],
    "sg:phone":"+1 561 743 9349",
    "sg:postcode":"33458",
    "sg:province":"FL",
    "sg:tags":[
        "new",
        "remodeling",
        "contractor"
    ],
    "wof:name":"Europa Building Associates",
    "wof:placetype":"venue"
},
  "geometry": {"coordinates":[-80.136245,26.934539],"type":"Point"}
}