{
  "type": "Feature",
  "properties": {
    "iso:country":"US",
    "sg:address":"4065 S Military Trl",
    "sg:city":"Lake Worth",
    "sg:classifiers":[
        {
            "category":"Autos & Motor Vehicles",
            "subcategory":"Automobile Sales",
            "type":"Retail Goods"
        }
    ],
    "sg:phone":"+1 561 649 0280",
    "sg:postcode":"33463",
    "sg:province":"FL",
    "sg:tags":[
        "used"
    ],
    "wof:name":"Drive-Away Motors",
    "wof:placetype":"venue"
},
  "geometry": {"coordinates":[-80.113657,26.617221],"type":"Point"}
}