{
  "type": "Feature",
  "properties": {
    "iso:country":"US",
    "sg:address":"960 Arthur Godfrey Rd",
    "sg:city":"Miami Beach",
    "sg:classifiers":[
        {
            "category":"Insurance",
            "subcategory":"Insurance Agent",
            "type":"Services"
        }
    ],
    "sg:phone":"+1 305 532 1212",
    "sg:postcode":"33140",
    "sg:province":"FL",
    "sg:tags":[
        "real estate"
    ],
    "wof:name":"Eskridge Gee Realty",
    "wof:placetype":"venue"
},
  "geometry": {"coordinates":[-80.135304,25.813112],"type":"Point"}
}