{
  "type": "Feature",
  "properties": {
    "iso:country":"US",
    "sg:address":"126 Linstew Dr NW",
    "sg:city":"Fort Walton Beach",
    "sg:classifiers":[
        {
            "category":"Building & Trades",
            "subcategory":"Construction",
            "type":"Services"
        }
    ],
    "sg:phone":"+1 850 862 3439",
    "sg:postcode":"32548",
    "sg:province":"FL",
    "sg:tags":[
        "floor",
        "laying",
        "contractor"
    ],
    "wof:name":"Youngs Floor Installation",
    "wof:placetype":"venue"
},
  "geometry": {"coordinates":[-86.62357799999999,30.42726],"type":"Point"}
}