{
  "type": "Feature",
  "properties": {
    "addr:full":"3469 Docksider Dr N Jacksonville FL 32257",
    "addr:housenumber":"3469",
    "addr:postcode":"32257",
    "addr:street":"Docksider Dr N",
    "iso:country":"US",
    "sg:address":"3469 Docksider Dr N",
    "sg:city":"Jacksonville",
    "sg:classifiers":[
        {
            "category":"Restaurant",
            "type":"Food & Drink"
        }
    ],
    "sg:phone":"+1 904 262 3749",
    "sg:postcode":"32257",
    "sg:province":"FL",
    "sg:tags":[
        "eating"
    ],
    "wof:name":"Schlotzskys Deli",
    "wof:placetype":"venue"
},
  "geometry": {"coordinates":[-81.619563,30.189863],"type":"Point"}
}