{
  "type": "Feature",
  "properties": {
    "addr:full":"742 Carter St Orlando FL 32805",
    "addr:housenumber":"742",
    "addr:postcode":"32805",
    "addr:street":"Carter St",
    "iso:country":"US",
    "sg:address":"742 Carter St",
    "sg:city":"Orlando",
    "sg:classifiers":[
        {
            "category":"Restaurant",
            "type":"Food & Drink"
        }
    ],
    "sg:phone":"+1 407 425 5301",
    "sg:postcode":"32805",
    "sg:province":"FL",
    "sg:tags":[
        "home",
        "cooking"
    ],
    "wof:name":"Nikki's Place Southern Cuisine",
    "wof:placetype":"venue"
},
  "geometry": {"coordinates":[-81.390407,28.534649],"type":"Point"}
}