{
  "type": "Feature",
  "properties": {
    "addr:full":"8863 Phillips Hwy Jacksonville FL 32256",
    "addr:housenumber":"8863",
    "addr:postcode":"32256",
    "addr:street":"Phillips Hwy",
    "iso:country":"US",
    "sg:address":"8863 Phillips Hwy",
    "sg:city":"Jacksonville",
    "sg:classifiers":[
        {
            "category":"Local Transit",
            "type":"Transportation"
        }
    ],
    "sg:phone":"+1 904 519 5466",
    "sg:postcode":"32256",
    "sg:province":"FL",
    "sg:tags":[
        "limousine"
    ],
    "wof:name":"Black Tie Limousine",
    "wof:placetype":"venue"
},
  "geometry": {"coordinates":[-81.579151,30.21],"type":"Point"}
}