{
  "type": "Feature",
  "properties": {
    "addr:full":"2913 SW 160th Ave Miramar FL 33027",
    "addr:housenumber":"2913",
    "addr:postcode":"33027",
    "addr:street":"Sw 160Th Ave",
    "iso:country":"US",
    "sg:address":"2913 SW 160th Ave",
    "sg:city":"Miramar",
    "sg:classifiers":[
        {
            "category":"Restaurant",
            "type":"Food & Drink"
        }
    ],
    "sg:phone":"+1 954 318 7272",
    "sg:postcode":"33027",
    "sg:province":"FL",
    "wof:name":"Chick-N-Grill",
    "wof:placetype":"venue"
},
  "geometry": {"coordinates":[-80.359737,25.982106],"type":"Point"}
}