{
  "type": "Feature",
  "properties": {
    "iso:country":"US",
    "sg:address":"1104 S Westmoreland Dr # 3",
    "sg:city":"Orlando",
    "sg:classifiers":[
        {
            "category":"Wholesale",
            "subcategory":"Furniture",
            "type":"Manufacturing & Wholesale Goods"
        },
        {
            "category":"Home & Garden",
            "subcategory":"Furniture",
            "type":"Retail Goods"
        }
    ],
    "sg:phone":"+1 407 841 6422",
    "sg:postcode":"32805",
    "sg:province":"FL",
    "sg:tags":[
        "store",
        "furniture-wholesale",
        "manufacturer"
    ],
    "wof:name":"Innovtive Dsgns Furn Mnfacture",
    "wof:placetype":"venue"
},
  "geometry": {"coordinates":[-81.39298599999999,28.52874],"type":"Point"}
}