{
  "type": "Feature",
  "properties": {
    "iso:country":"US",
    "sg:address":"2500 NW 107th Ave",
    "sg:city":"Miami",
    "sg:classifiers":[
        {
            "category":"Utilities",
            "subcategory":"Telephone",
            "type":"Services"
        }
    ],
    "sg:phone":"+1 305 716 4277",
    "sg:postcode":"33172",
    "sg:province":"FL",
    "sg:tags":[
        "cards",
        "prepaid",
        "calling"
    ],
    "wof:name":"Cinco Telecom Corp",
    "wof:placetype":"venue"
},
  "geometry": {"coordinates":[-80.36915399999999,25.798827],"type":"Point"}
}