{
  "type": "Feature",
  "properties": {
    "iso:country":"US",
    "sg:address":"144 SW Horry Ave",
    "sg:city":"Madison",
    "sg:classifiers":[
        {
            "category":"Restaurant",
            "type":"Food & Drink"
        }
    ],
    "sg:phone":"+1 850 973 9099",
    "sg:postcode":"32340",
    "sg:province":"FL",
    "sg:tags":[
        "mexican"
    ],
    "wof:name":"La Reyna Mexican Restaurant",
    "wof:placetype":"venue"
},
  "geometry": {"coordinates":[-83.41407,30.46858],"type":"Point"}
}