{
  "type": "Feature",
  "properties": {
    "addr:full":"2970 Jog Rd Lake Worth FL 33467",
    "addr:postcode":"2970;33467",
    "addr:street":"Jog Rd",
    "iso:country":"US",
    "sg:address":"2970 Jog Rd",
    "sg:city":"Lake Worth",
    "sg:classifiers":[
        {
            "category":"Insurance",
            "subcategory":"Insurance Agent",
            "type":"Services"
        }
    ],
    "sg:phone":"+1 561 968 0551",
    "sg:postcode":"33467",
    "sg:province":"FL",
    "wof:name":"Patricia McGregor Insurance",
    "wof:placetype":"venue"
},
  "geometry": {"coordinates":[-80.14596,26.633093],"type":"Point"}
}