{
  "type": "Feature",
  "properties": {
    "addr:full":"420 Roberts Rd Oldsmar FL 34677",
    "addr:housenumber":"420",
    "addr:postcode":"34677",
    "addr:street":"Roberts Rd",
    "iso:country":"US",
    "sg:address":"420 Roberts Rd",
    "sg:city":"Oldsmar",
    "sg:classifiers":[
        {
            "category":"Wholesale",
            "subcategory":"Machinery & Supplies",
            "type":"Manufacturing & Wholesale Goods"
        }
    ],
    "sg:phone":"+1 813 855 6658",
    "sg:postcode":"34677",
    "sg:province":"FL",
    "sg:tags":[
        "pump"
    ],
    "wof:name":"Whittington Vacuum Pumps",
    "wof:placetype":"venue"
},
  "geometry": {"coordinates":[-82.652806,28.043445],"type":"Point"}
}