{
  "type": "Feature",
  "properties": {
    "addr:full":"5740 N Orange Blossom Trail Orlando FL 32810",
    "addr:housenumber":"5740",
    "addr:postcode":"32810",
    "addr:street":"N Orange Blossom Trail",
    "iso:country":"US",
    "sg:address":"5740 N Orange Blossom Trail",
    "sg:city":"Orlando",
    "sg:classifiers":[
        {
            "category":"Restaurant",
            "type":"Food & Drink"
        },
        {
            "category":"Food & Beverages",
            "subcategory":"Bakery",
            "type":"Retail Goods"
        }
    ],
    "sg:phone":"+1 407 299 7188",
    "sg:postcode":"32810",
    "sg:province":"FL",
    "sg:tags":[
        "sandwich",
        "pizza"
    ],
    "sg:website":"www.hungryhowies.com",
    "wof:name":"Hungry Howie's Pizza & Subs",
    "wof:placetype":"venue"
},
  "geometry": {"coordinates":[-81.430012,28.611308],"type":"Point"}
}