{
  "type": "Feature",
  "properties": {
    "iso:country":"US",
    "sg:address":"282 Mentor Dr",
    "sg:city":"Naples",
    "sg:classifiers":[
        {
            "category":"Real Estate",
            "subcategory":"Real Estate Agent",
            "type":"Services"
        }
    ],
    "sg:phone":"+1 239 594 8929",
    "sg:postcode":"34110",
    "sg:province":"FL",
    "wof:name":"Huntington Gardens",
    "wof:placetype":"venue"
},
  "geometry": {"coordinates":[-81.759118,26.277827],"type":"Point"}
}