{
  "type": "Feature",
  "properties": {
    "addr:full":"6333 Custer Rd Orange Park FL 32065",
    "addr:housenumber":"6333",
    "addr:postcode":"32065",
    "addr:street":"Custer Rd",
    "iso:country":"US",
    "sg:address":"6333 Custer Rd",
    "sg:city":"Orange Park",
    "sg:classifiers":[
        {
            "category":"Real Estate",
            "subcategory":"Real Estate Agent",
            "type":"Services"
        }
    ],
    "sg:phone":"+1 904 269 3328",
    "sg:postcode":"32065",
    "sg:province":"FL",
    "wof:name":"Management Plus Inc",
    "wof:placetype":"venue"
},
  "geometry": {"coordinates":[-81.76733400000001,30.12993],"type":"Point"}
}