{
  "type": "Feature",
  "properties": {
    "iso:country":"US",
    "sg:address":"1280 SW Shoreline Dr",
    "sg:city":"Palm City",
    "sg:classifiers":[
        {
            "category":"Wholesale",
            "subcategory":"Groceries",
            "type":"Manufacturing & Wholesale Goods"
        }
    ],
    "sg:phone":"+1 772 219 8081",
    "sg:postcode":"34990",
    "sg:province":"FL",
    "wof:name":"Loomis Assoc",
    "wof:placetype":"venue"
},
  "geometry": {"coordinates":[-80.274728,27.189808],"type":"Point"}
}