{
  "type": "Feature",
  "properties": {
    "iso:country":"US",
    "sg:address":"257 Worley St",
    "sg:city":"Chokoloskee",
    "sg:classifiers":[
        {
            "category":"Building & Trades",
            "subcategory":"Landscaping Services",
            "type":"Services"
        }
    ],
    "sg:phone":"+1 239 695 2538",
    "sg:postcode":"34138",
    "sg:province":"FL",
    "sg:tags":[
        "lawn",
        "maintenance",
        "grounds"
    ],
    "wof:name":"Renee Weeks Lawn Maintenance",
    "wof:placetype":"venue"
},
  "geometry": {"coordinates":[-81.36072,25.813341],"type":"Point"}
}