{
  "type": "Feature",
  "properties": {
    "iso:country":"US",
    "sg:address":"1786 NW Madrid Way",
    "sg:city":"Boca Raton",
    "sg:classifiers":[
        {
            "category":"Education",
            "subcategory":"Special Training",
            "type":"Public Place"
        }
    ],
    "sg:phone":"+1 561 620 0180",
    "sg:postcode":"33432",
    "sg:province":"FL",
    "sg:tags":[
        "instruction",
        "music"
    ],
    "wof:name":"Chris Risola Studio",
    "wof:placetype":"venue"
},
  "geometry": {"coordinates":[-80.087575,26.366108],"type":"Point"}
}