{
  "type": "Feature",
  "properties": {
    "addr:full":"9 Pecan Dr Ocala FL 34472",
    "addr:housenumber":"9",
    "addr:postcode":"34472",
    "addr:street":"Pecan Dr",
    "iso:country":"US",
    "sg:address":"9 Pecan Dr",
    "sg:city":"Ocala",
    "sg:classifiers":[
        {
            "category":"Shopping",
            "subcategory":"Hobbies, Toys, & Games",
            "type":"Retail Goods"
        }
    ],
    "sg:phone":"+1 352 680 0620",
    "sg:postcode":"34472",
    "sg:province":"FL",
    "sg:tags":[
        "craft",
        "supply"
    ],
    "wof:name":"Bernard O Hamilton",
    "wof:placetype":"venue"
},
  "geometry": {"coordinates":[-82.03244599999999,29.145172],"type":"Point"}
}