{
  "type": "Feature",
  "properties": {
    "addr:full":"280 SW 33rd St Fort Lauderdale FL 33315",
    "addr:housenumber":"280",
    "addr:postcode":"33315",
    "addr:street":"Sw 33Rd St",
    "iso:country":"US",
    "sg:address":"280 SW 33rd St",
    "sg:city":"Fort Lauderdale",
    "sg:classifiers":[
        {
            "category":"Manufacturing",
            "subcategory":"Wood Products",
            "type":"Manufacturing & Wholesale Goods"
        }
    ],
    "sg:phone":"+1 954 527 5742",
    "sg:postcode":"33315",
    "sg:province":"FL",
    "sg:tags":[
        "case",
        "packing",
        "crating",
        "mfg"
    ],
    "wof:name":"Custom Crate Co",
    "wof:placetype":"venue"
},
  "geometry": {"coordinates":[-80.144081,26.083372],"type":"Point"}
}