{
  "type": "Feature",
  "properties": {
    "addr:full":"4668 Cason Cove Dr Orlando FL 32811",
    "addr:housenumber":"4668",
    "addr:postcode":"32811",
    "addr:street":"Cason Cove Dr",
    "iso:country":"US",
    "sg:address":"4668 Cason Cove Dr",
    "sg:city":"Orlando",
    "sg:classifiers":[
        {
            "category":"Health Services",
            "subcategory":"Clinic",
            "type":"Services"
        }
    ],
    "sg:phone":"+1 407 246 7292",
    "sg:postcode":"32811",
    "sg:province":"FL",
    "wof:name":"Ocean Health Institute Inc",
    "wof:placetype":"venue"
},
  "geometry": {"coordinates":[-81.438779,28.497532],"type":"Point"}
}