{
  "type": "Feature",
  "properties": {
    "addr:full":"700 N Columbia St Lake City FL 32055",
    "addr:housenumber":"700",
    "addr:postcode":"32055",
    "addr:street":"N Columbia St",
    "iso:country":"US",
    "sg:address":"700 N Columbia St",
    "sg:city":"Lake City",
    "sg:classifiers":[
        {
            "category":"Social Services",
            "type":"Services"
        }
    ],
    "sg:phone":"+1 386 758 7722",
    "sg:postcode":"32055",
    "sg:province":"FL",
    "sg:tags":[
        "mission"
    ],
    "wof:name":"Hannah's House",
    "wof:placetype":"venue"
},
  "geometry": {"coordinates":[-82.63799899999999,30.19474],"type":"Point"}
}