{
  "type": "Feature",
  "properties": {
    "iso:country":"US",
    "sg:address":"1800 NE 23rd Ave",
    "sg:city":"Gainesville",
    "sg:classifiers":[
        {
            "category":"Restaurant",
            "type":"Food & Drink"
        }
    ],
    "sg:menulink":"http://www.allmenus.com/fl/gainesville/248400-satchels-pizza/menu/",
    "sg:phone":"+1 352 335 7272",
    "sg:postcode":"32609",
    "sg:province":"FL",
    "sg:tags":[
        "american",
        "pizza"
    ],
    "wof:name":"Satchel's Pizza",
    "wof:placetype":"venue"
},
  "geometry": {"coordinates":[-82.30115000000001,29.673809],"type":"Point"}
}