{
  "type": "Feature",
  "properties": {
    "iso:country":"US",
    "sg:address":"3467 W Daffodil Dr",
    "sg:city":"Beverly Hills",
    "sg:classifiers":[
        {
            "category":"Banks & Credit Unions",
            "subcategory":"Financial Services",
            "type":"Services"
        }
    ],
    "sg:phone":"+1 352 249 1091",
    "sg:postcode":"34465",
    "sg:province":"FL",
    "sg:tags":[
        "trust",
        "investment",
        "real estate"
    ],
    "wof:name":"Rolph Investments LLC",
    "wof:placetype":"venue"
},
  "geometry": {"coordinates":[-82.491885,28.948067],"type":"Point"}
}