{
  "type": "Feature",
  "properties": {
    "addr:full":"2050 Coral Way Ste 511 Coral Gables FL 33145",
    "addr:housenumber":"2050",
    "addr:postcode":"33145",
    "addr:street":"Coral Way Ste 511",
    "iso:country":"US",
    "sg:address":"2050 Coral Way Ste 511",
    "sg:city":"Coral Gables",
    "sg:classifiers":[
        {
            "category":"Professional",
            "subcategory":"Lawyer & Legal Services",
            "type":"Services"
        }
    ],
    "sg:phone":"+1 305 858 9595",
    "sg:postcode":"33145",
    "sg:province":"FL",
    "wof:name":"Seligman Earl PA",
    "wof:placetype":"venue"
},
  "geometry": {"coordinates":[-80.227564,25.750445],"type":"Point"}
}