{
  "type": "Feature",
  "properties": {
    "addr:full":"2780 Brickell Ave Miami FL 33129",
    "addr:housenumber":"2780",
    "addr:postcode":"33129",
    "addr:street":"Brickell Ave",
    "iso:country":"US",
    "sg:address":"2780 Brickell Ave",
    "sg:city":"Miami",
    "sg:classifiers":[
        {
            "category":"Professional",
            "subcategory":"Computer Services",
            "type":"Services"
        }
    ],
    "sg:phone":"+1 305 859 8179",
    "sg:postcode":"33129",
    "sg:province":"FL",
    "sg:tags":[
        "information",
        "engineering",
        "technology",
        "consulting"
    ],
    "wof:name":"Cerentis Consulting Inc",
    "wof:placetype":"venue"
},
  "geometry": {"coordinates":[-80.20905,25.746966],"type":"Point"}
}