{
  "type": "Feature",
  "properties": {
    "iso:country":"US",
    "sg:address":"16440 S Tamiami Trl",
    "sg:city":"Fort Myers",
    "sg:classifiers":[
        {
            "category":"Home & Garden",
            "subcategory":"Furniture",
            "type":"Retail Goods"
        }
    ],
    "sg:phone":"+1 239 415 2378",
    "sg:postcode":"33908",
    "sg:province":"FL",
    "sg:tags":[
        "store"
    ],
    "wof:name":"Best Used Furniture by Suzanne Abercrombie",
    "wof:placetype":"venue"
},
  "geometry": {"coordinates":[-81.857462,26.503637],"type":"Point"}
}