{
  "type": "Feature",
  "properties": {
    "addr:full":"822 Dodecanese Blvd Tarpon Springs FL 34689",
    "addr:housenumber":"822",
    "addr:postcode":"34689",
    "addr:street":"Dodecanese Blvd",
    "iso:country":"US",
    "sg:address":"822 Dodecanese Blvd",
    "sg:city":"Tarpon Springs",
    "sg:classifiers":[
        {
            "category":"Museum",
            "type":"Entertainment"
        }
    ],
    "sg:phone":"+1 727 934 6760",
    "sg:postcode":"34689",
    "sg:province":"FL",
    "sg:tags":[
        "gallery"
    ],
    "wof:name":"Medievel Brass Rubbing Center",
    "wof:placetype":"venue"
},
  "geometry": {"coordinates":[-82.764567,28.154788],"type":"Point"}
}