{
  "type": "Feature",
  "properties": {
    "addr:full":"2860 SW 64th Ave Fort Lauderdale FL 33314",
    "addr:housenumber":"2860",
    "addr:postcode":"33314",
    "addr:street":"Sw 64Th Ave",
    "iso:country":"US",
    "sg:address":"2860 SW 64th Ave",
    "sg:city":"Fort Lauderdale",
    "sg:classifiers":[
        {
            "category":"Deli",
            "type":"Food & Drink"
        }
    ],
    "sg:menulink":"http://www.allmenus.com/fl/davie/126024-blimpie-subs--sandwiches/menu/",
    "sg:phone":"+1 954 583 8198",
    "sg:postcode":"33314",
    "sg:province":"FL",
    "sg:tags":[
        "wrap",
        "american",
        "sandwich"
    ],
    "wof:name":"Blimpie Subs & Sandwiches",
    "wof:placetype":"venue"
},
  "geometry": {"coordinates":[-80.228938,26.086331],"type":"Point"}
}