{
  "type": "Feature",
  "properties": {
    "iso:country":"US",
    "sg:address":"2252 la Vista Dr",
    "sg:city":"Pensacola",
    "sg:classifiers":[
        {
            "category":"Shopping",
            "subcategory":"Jewelry",
            "type":"Retail Goods"
        }
    ],
    "sg:phone":"+1 850 474 1511",
    "sg:postcode":"32504",
    "sg:province":"FL",
    "sg:tags":[
        "repair"
    ],
    "wof:name":"Reeds Clock Gallery & Repair",
    "wof:placetype":"venue"
},
  "geometry": {"coordinates":[-87.00462899999999,30.400502],"type":"Point"}
}