{
  "type": "Feature",
  "properties": {
    "iso:country":"US",
    "sg:address":"15274 72nd Ct N",
    "sg:city":"Loxahatchee",
    "sg:classifiers":[
        {
            "category":"Home & Garden",
            "subcategory":"Garden Supply",
            "type":"Retail Goods"
        }
    ],
    "sg:phone":"+1 561 753 5951",
    "sg:postcode":"33470",
    "sg:province":"FL",
    "wof:name":"Southern Mowers Inc",
    "wof:placetype":"venue"
},
  "geometry": {"coordinates":[-80.282939,26.783333],"type":"Point"}
}