{
  "type": "Feature",
  "properties": {
    "addr:full":"4921 Pierce St Hollywood FL 33021",
    "addr:housenumber":"4921",
    "addr:postcode":"33021",
    "addr:street":"Pierce St",
    "iso:country":"US",
    "sg:address":"4921 Pierce St",
    "sg:city":"Hollywood",
    "sg:classifiers":[
        {
            "category":"Professional",
            "subcategory":"Art Services",
            "type":"Services"
        }
    ],
    "sg:phone":"+1 954 963 1415",
    "sg:postcode":"33021",
    "sg:province":"FL",
    "sg:tags":[
        "photographer"
    ],
    "wof:name":"Andrew Goldstein Photography",
    "wof:placetype":"venue"
},
  "geometry": {"coordinates":[-80.193701,26.015207],"type":"Point"}
}