{
  "type": "Feature",
  "properties": {
    "iso:country":"US",
    "sg:address":"4044 NW 19th St",
    "sg:city":"Lauderhill",
    "sg:classifiers":[
        {
            "category":"Recreation",
            "type":"Entertainment"
        }
    ],
    "sg:phone":"+1 954 791 2731",
    "sg:postcode":"33313",
    "sg:province":"FL",
    "sg:tags":[
        "carnival"
    ],
    "wof:name":"Sunshine Amusements",
    "wof:placetype":"venue"
},
  "geometry": {"coordinates":[-80.20342599999999,26.150534],"type":"Point"}
}