{
  "type": "Feature",
  "properties": {
    "addr:full":"1189 Hypoluxo Rd Lake Worth FL 33462",
    "addr:housenumber":"1189",
    "addr:postcode":"33462",
    "addr:street":"Hypoluxo Rd",
    "iso:country":"US",
    "sg:address":"1189 Hypoluxo Rd",
    "sg:city":"Lake Worth",
    "sg:classifiers":[
        {
            "category":"Banks & Credit Unions",
            "subcategory":"Bank",
            "type":"Services"
        }
    ],
    "sg:phone":"+1 561 968 1000",
    "sg:postcode":"33462",
    "sg:province":"FL",
    "sg:tags":[
        "federal",
        "savings",
        "banker",
        "mortgage"
    ],
    "wof:name":"Sterling Bancgroup Inc",
    "wof:placetype":"venue"
},
  "geometry": {"coordinates":[-80.060053,26.572073],"type":"Point"}
}