{
  "type": "Feature",
  "properties": {
    "iso:country":"US",
    "sg:address":"17881 31st Rd N",
    "sg:city":"Loxahatchee",
    "sg:classifiers":[
        {
            "category":"Building & Trades",
            "subcategory":"Construction",
            "type":"Services"
        }
    ],
    "sg:phone":"+1 561 753 2840",
    "sg:postcode":"33470",
    "sg:province":"FL",
    "sg:tags":[
        "interior",
        "trim",
        "carpentry"
    ],
    "wof:name":"Micheal P Cicaroni",
    "wof:placetype":"venue"
},
  "geometry": {"coordinates":[-80.328093,26.726188],"type":"Point"}
}