{
  "type": "Feature",
  "properties": {
    "addr:full":"1066 Salmon Isle West Palm Beach FL 33413",
    "addr:housenumber":"1066",
    "addr:postcode":"33413",
    "addr:street":"Salmon Isle",
    "iso:country":"US",
    "sg:address":"1066 Salmon Isle",
    "sg:city":"West Palm Beach",
    "sg:classifiers":[
        {
            "category":"Retail",
            "subcategory":"Repair Shop",
            "type":"Services"
        }
    ],
    "sg:phone":"+1 561 689 0570",
    "sg:postcode":"33413",
    "sg:province":"FL",
    "sg:tags":[
        "electrical"
    ],
    "wof:name":"Action Appliance Service Inc",
    "wof:placetype":"venue"
},
  "geometry": {"coordinates":[-80.149905,26.660562],"type":"Point"}
}