{
  "type": "Feature",
  "properties": {
    "addr:full":"2181 Corbett Rd Orlando FL 32826",
    "addr:housenumber":"2181",
    "addr:postcode":"32826",
    "addr:street":"Corbett Rd",
    "iso:country":"US",
    "sg:address":"2181 Corbett Rd",
    "sg:city":"Orlando",
    "sg:classifiers":[
        {
            "category":"Wholesale",
            "subcategory":"Machinery & Supplies",
            "type":"Manufacturing & Wholesale Goods"
        }
    ],
    "sg:phone":"+1 407 275 5602",
    "sg:postcode":"32826",
    "sg:province":"FL",
    "sg:tags":[
        "equipment",
        "industrial"
    ],
    "wof:name":"Walts Pump Service Inc",
    "wof:placetype":"venue"
},
  "geometry": {"coordinates":[-81.179326,28.570613],"type":"Point"}
}