{
  "type": "Feature",
  "properties": {
    "iso:country":"US",
    "sg:address":"1916 Boggy Creek Rd",
    "sg:city":"Kissimmee",
    "sg:classifiers":[
        {
            "category":"Manufacturing",
            "subcategory":"Food",
            "type":"Manufacturing & Wholesale Goods"
        },
        {
            "category":"Food & Beverages",
            "subcategory":"Groceries & Convenience Stores",
            "type":"Retail Goods"
        }
    ],
    "sg:phone":"+1 321 402 0480",
    "sg:postcode":"34744",
    "sg:province":"FL",
    "sg:tags":[
        "product"
    ],
    "wof:name":"Boggy Creek Food Store",
    "wof:placetype":"venue"
},
  "geometry": {"coordinates":[-81.36577,28.304171],"type":"Point"}
}