{
  "type": "Feature",
  "properties": {
    "iso:country":"US",
    "sg:address":"6130 15th St E",
    "sg:city":"Bradenton",
    "sg:classifiers":[
        {
            "category":"Restaurant",
            "type":"Food & Drink"
        }
    ],
    "sg:phone":"+1 941 756 7798",
    "sg:postcode":"34203",
    "sg:province":"FL",
    "wof:name":"Fayes Family Restaurant",
    "wof:placetype":"venue"
},
  "geometry": {"coordinates":[-82.54675400000001,27.432409],"type":"Point"}
}