{
  "type": "Feature",
  "properties": {
    "addr:full":"201 W University Ave Gainesville FL 32601",
    "addr:housenumber":"201",
    "addr:postcode":"32601",
    "addr:street":"W University Ave",
    "iso:country":"US",
    "sg:address":"201 W University Ave",
    "sg:city":"Gainesville",
    "sg:classifiers":[
        {
            "category":"Banks & Credit Unions",
            "subcategory":"Atm",
            "type":"Services"
        }
    ],
    "sg:phone":"+1 352 373 3173",
    "sg:postcode":"32601",
    "sg:province":"FL",
    "sg:tags":[
        "location"
    ],
    "wof:name":"Atm U S A",
    "wof:placetype":"venue"
},
  "geometry": {"coordinates":[-82.326599,29.651978],"type":"Point"}
}