{
  "type": "Feature",
  "properties": {
    "addr:full":"1173 Benjamin Chaires Rd Tallahassee FL 32317",
    "addr:housenumber":"1173",
    "addr:postcode":"32317",
    "addr:street":"Benjamin Chaires Rd",
    "iso:country":"US",
    "sg:address":"1173 Benjamin Chaires Rd",
    "sg:city":"Tallahassee",
    "sg:classifiers":[
        {
            "category":"Real Estate",
            "subcategory":"Real Estate Agent",
            "type":"Services"
        }
    ],
    "sg:phone":"+1 850 877 4776",
    "sg:postcode":"32317",
    "sg:province":"FL",
    "wof:name":"J Bixler Conn & Assoc Inc",
    "wof:placetype":"venue"
},
  "geometry": {"coordinates":[-84.10884799999999,30.451161],"type":"Point"}
}