{
  "type": "Feature",
  "properties": {
    "addr:full":"1750 W Roberts St Orange City FL 32763",
    "addr:housenumber":"1750",
    "addr:postcode":"32763",
    "addr:street":"W Roberts St",
    "iso:country":"US",
    "sg:address":"1750 W Roberts St",
    "sg:city":"Orange City",
    "sg:classifiers":[
        {
            "category":"Building & Trades",
            "subcategory":"Construction",
            "type":"Services"
        }
    ],
    "sg:phone":"+1 386 789 1700",
    "sg:postcode":"32763",
    "sg:province":"FL",
    "sg:tags":[
        "contractor"
    ],
    "wof:name":"Dave S Fence Inc",
    "wof:placetype":"venue"
},
  "geometry": {"coordinates":[-81.32881999999999,28.924666],"type":"Point"}
}