{
  "type": "Feature",
  "properties": {
    "addr:full":"7799 Styles Blvd Kissimmee FL 34747",
    "addr:housenumber":"7799",
    "addr:postcode":"34747",
    "addr:street":"Styles Blvd",
    "iso:country":"US",
    "sg:address":"7799 Styles Blvd",
    "sg:city":"Kissimmee",
    "sg:classifiers":[
        {
            "category":"Travel",
            "subcategory":"Hotels & Motels",
            "type":"Entertainment"
        }
    ],
    "sg:phone":"+1 888 782 9722",
    "sg:postcode":"34747",
    "sg:province":"FL",
    "sg:tags":[
        "lodging"
    ],
    "wof:name":"Bahama Bay Resort",
    "wof:placetype":"venue"
},
  "geometry": {"coordinates":[-81.640823,28.34581],"type":"Point"}
}