{
  "type": "Feature",
  "properties": {
    "iso:country":"US",
    "sg:address":"7109 Eight Mile Creek Rd",
    "sg:city":"Pensacola",
    "sg:classifiers":[
        {
            "category":"Shopping",
            "type":"Retail Goods"
        }
    ],
    "sg:phone":"+1 850 941 1787",
    "sg:postcode":"32526",
    "sg:province":"FL",
    "sg:tags":[
        "merchandise"
    ],
    "wof:name":"Scarlet Shockley 1",
    "wof:placetype":"venue"
},
  "geometry": {"coordinates":[-87.322884,30.500348],"type":"Point"}
}