{
  "type": "Feature",
  "properties": {
    "iso:country":"US",
    "sg:address":"8384 Co Hwy 1087",
    "sg:city":"Defuniak Springs",
    "sg:classifiers":[
        {
            "category":"Real Estate",
            "subcategory":"Real Estate Agent",
            "type":"Services"
        }
    ],
    "sg:phone":"+1 850 546 0872",
    "sg:postcode":"32433",
    "sg:province":"FL",
    "wof:name":"Kelley Properties",
    "wof:placetype":"venue"
},
  "geometry": {"coordinates":[-86.27855,30.832156],"type":"Point"}
}