{
  "type": "Feature",
  "properties": {
    "addr:full":"1755 W Brandon Blvd Brandon FL 33511",
    "addr:housenumber":"1755",
    "addr:postcode":"33511",
    "addr:street":"W Brandon Blvd",
    "iso:country":"US",
    "sg:address":"1755 W Brandon Blvd",
    "sg:city":"Brandon",
    "sg:classifiers":[
        {
            "category":"Real Estate",
            "subcategory":"Real Estate Agent",
            "type":"Services"
        }
    ],
    "sg:phone":"+1 813 643 8487",
    "sg:postcode":"33511",
    "sg:province":"FL",
    "wof:name":"Woodrow W Gore",
    "wof:placetype":"venue"
},
  "geometry": {"coordinates":[-82.313412,27.937666],"type":"Point"}
}