{
  "type": "Feature",
  "properties": {
    "iso:country":"US",
    "sg:address":"341 N Maitland Ave",
    "sg:city":"Maitland",
    "sg:classifiers":[
        {
            "category":"Health Services",
            "subcategory":"Doctor",
            "type":"Services"
        }
    ],
    "sg:phone":"+1 407 644 2729",
    "sg:postcode":"32751",
    "sg:province":"FL",
    "sg:tags":[
        "medical"
    ],
    "wof:name":"Mid Florida Med Group",
    "wof:placetype":"venue"
},
  "geometry": {"coordinates":[-81.365683,28.630831],"type":"Point"}
}