{
  "type": "Feature",
  "properties": {
    "iso:country":"US",
    "sg:address":"13941 15th St",
    "sg:city":"Dade City",
    "sg:classifiers":[
        {
            "category":"Government",
            "subcategory":"Office",
            "type":"Public Place"
        }
    ],
    "sg:phone":"+1 352 521 1454",
    "sg:postcode":"33525",
    "sg:province":"FL",
    "wof:name":"Pasco County Epidemiology",
    "wof:placetype":"venue"
},
  "geometry": {"coordinates":[-82.19792099999999,28.360919],"type":"Point"}
}