{
  "type": "Feature",
  "properties": {
    "addr:full":"4385 Collins Ave Miami Beach FL 33140",
    "addr:housenumber":"4385",
    "addr:postcode":"33140",
    "addr:street":"Collins Ave",
    "iso:country":"US",
    "sg:address":"4385 Collins Ave",
    "sg:city":"Miami Beach",
    "sg:classifiers":[
        {
            "category":"Education",
            "subcategory":"Vocational School",
            "type":"Public Place"
        }
    ],
    "sg:phone":"+1 715 256 9911",
    "sg:postcode":"33140",
    "sg:province":"FL",
    "sg:tags":[
        "training",
        "certification"
    ],
    "wof:name":"It Centers LLC",
    "wof:placetype":"venue"
},
  "geometry": {"coordinates":[-80.122641,25.814731],"type":"Point"}
}