{
  "type": "Feature",
  "properties": {
    "iso:country":"US",
    "sg:address":"3875 W 16th Ave",
    "sg:city":"Hialeah",
    "sg:classifiers":[
        {
            "category":"Shopping",
            "subcategory":"Books",
            "type":"Retail Goods"
        }
    ],
    "sg:phone":"+1 305 558 4355",
    "sg:postcode":"33012",
    "sg:province":"FL",
    "sg:tags":[
        "bookstore"
    ],
    "wof:name":"Serafin Catholic Books & Gifts",
    "wof:placetype":"venue"
},
  "geometry": {"coordinates":[-80.314697,25.856899],"type":"Point"}
}