{
  "type": "Feature",
  "properties": {
    "addr:full":"6108 Sherwin Dr Port Richey FL 34668",
    "addr:housenumber":"6108",
    "addr:postcode":"34668",
    "addr:street":"Sherwin Dr",
    "iso:country":"US",
    "sg:address":"6108 Sherwin Dr",
    "sg:city":"Port Richey",
    "sg:classifiers":[
        {
            "category":"Retail",
            "subcategory":"Auto Repair",
            "type":"Services"
        }
    ],
    "sg:phone":"+1 727 816 9970",
    "sg:postcode":"34668",
    "sg:province":"FL",
    "sg:tags":[
        "body",
        "automobile",
        "painting"
    ],
    "wof:name":"Brands Auto & Marine",
    "wof:placetype":"venue"
},
  "geometry": {"coordinates":[-82.71437,28.276368],"type":"Point"}
}