{
  "type": "Feature",
  "properties": {
    "addr:full":"1215 NW 65th Ter Miami FL 33147",
    "addr:housenumber":"1215",
    "addr:postcode":"33147",
    "addr:street":"Nw 65Th Ter",
    "iso:country":"US",
    "sg:address":"1215 NW 65th Ter",
    "sg:city":"Miami",
    "sg:classifiers":[
        {
            "category":"Personal",
            "subcategory":"Beauty Salon",
            "type":"Services"
        }
    ],
    "sg:phone":"+1 305 693 3601",
    "sg:postcode":"33147",
    "sg:province":"FL",
    "sg:tags":[
        "manicuring"
    ],
    "wof:name":"T's Nails",
    "wof:placetype":"venue"
},
  "geometry": {"coordinates":[-80.217249,25.834658],"type":"Point"}
}