{
  "type": "Feature",
  "properties": {
    "addr:full":"338 S Scenic Hwy Lake Wales FL 33853",
    "addr:housenumber":"338",
    "addr:postcode":"33853",
    "addr:street":"S Scenic Hwy",
    "iso:country":"US",
    "sg:address":"338 S Scenic Hwy",
    "sg:city":"Lake Wales",
    "sg:classifiers":[
        {
            "category":"Food & Beverages",
            "subcategory":"Groceries & Convenience Stores",
            "type":"Retail Goods"
        }
    ],
    "sg:phone":"+1 863 676 4133",
    "sg:postcode":"33853",
    "sg:province":"FL",
    "wof:name":"Pure Food Shop Inc",
    "wof:placetype":"venue"
},
  "geometry": {"coordinates":[-81.58398699999999,27.897137],"type":"Point"}
}