{
  "type": "Feature",
  "properties": {
    "iso:country":"US",
    "sg:address":"741 Providence Trace Cir",
    "sg:city":"Brandon",
    "sg:classifiers":[
        {
            "category":"Real Estate",
            "subcategory":"Real Estate Operator",
            "type":"Services"
        }
    ],
    "sg:phone":"+1 813 657 0506",
    "sg:postcode":"33511",
    "sg:province":"FL",
    "sg:tags":[
        "building",
        "apartment"
    ],
    "wof:name":"Cypress Trace",
    "wof:placetype":"venue"
},
  "geometry": {"coordinates":[-82.294386,27.900793],"type":"Point"}
}