{
  "type": "Feature",
  "properties": {
    "iso:country":"US",
    "sg:address":"635 S Bruton St",
    "sg:city":"Bainbridge",
    "sg:classifiers":[
        {
            "category":"Retail",
            "subcategory":"Funeral Services",
            "type":"Services"
        }
    ],
    "sg:phone":"+1 229 246 6042",
    "sg:postcode":"39819",
    "sg:province":"FL",
    "sg:tags":[
        "director"
    ],
    "wof:name":"Bruton Mortuary",
    "wof:placetype":"venue"
},
  "geometry": {"coordinates":[-84.581563,30.900918],"type":"Point"}
}