{
  "type": "Feature",
  "properties": {
    "iso:country":"US",
    "sg:address":"184 Aiken St",
    "sg:city":"Saint Augustine",
    "sg:classifiers":[
        {
            "category":"Wholesale",
            "subcategory":"Metals & Minerals",
            "type":"Manufacturing & Wholesale Goods"
        }
    ],
    "sg:phone":"+1 904 823 9886",
    "sg:postcode":"32084",
    "sg:province":"FL",
    "sg:tags":[
        "center"
    ],
    "wof:name":"Robert H Grimes Jr",
    "wof:placetype":"venue"
},
  "geometry": {"coordinates":[-81.337898,29.888792],"type":"Point"}
}