{
  "type": "Feature",
  "properties": {
    "addr:full":"5145 S Ridgewood Ave Port Orange FL 32127",
    "addr:housenumber":"5145",
    "addr:postcode":"32127",
    "addr:street":"S Ridgewood Ave",
    "iso:country":"US",
    "sg:address":"5145 S Ridgewood Ave",
    "sg:city":"Port Orange",
    "sg:classifiers":[
        {
            "category":"Autos & Motor Vehicles",
            "subcategory":"Automobile Sales",
            "type":"Retail Goods"
        }
    ],
    "sg:phone":"+1 386 767 2102",
    "sg:postcode":"32127",
    "sg:province":"FL",
    "sg:tags":[
        "car",
        "dealer"
    ],
    "wof:name":"All Value Motors Inc",
    "wof:placetype":"venue"
},
  "geometry": {"coordinates":[-80.97941299999999,29.127226],"type":"Point"}
}