{
  "type": "Feature",
  "properties": {
    "addr:full":"2501 Seacrest Blvd Delray Beach FL 33444",
    "addr:housenumber":"2501",
    "addr:postcode":"33444",
    "addr:street":"Seacrest Blvd",
    "iso:country":"US",
    "sg:address":"2501 Seacrest Blvd",
    "sg:city":"Delray Beach",
    "sg:classifiers":[
        {
            "category":"Education",
            "subcategory":"School",
            "type":"Public Place"
        }
    ],
    "sg:phone":"+1 561 243 1500",
    "sg:postcode":"33444",
    "sg:province":"FL",
    "sg:website":"www.atlantichs.org",
    "wof:name":"Atlantic Community High School",
    "wof:placetype":"venue"
},
  "geometry": {"coordinates":[-80.07131699999999,26.489157],"type":"Point"}
}