{
  "type": "Feature",
  "properties": {
    "iso:country":"US",
    "sg:address":"7100 W Flagler St",
    "sg:city":"Miami",
    "sg:classifiers":[
        {
            "category":"Autos & Motor Vehicles",
            "subcategory":"Fuel & Gas Station",
            "type":"Retail Goods"
        }
    ],
    "sg:phone":"+1 305 265 5747",
    "sg:postcode":"33144",
    "sg:province":"FL",
    "wof:name":"J & G West Flagler Inc",
    "wof:placetype":"venue"
},
  "geometry": {"coordinates":[-80.31059999999999,25.7703],"type":"Point"}
}