{
  "type": "Feature",
  "properties": {
    "addr:full":"684 110th Ave N Naples FL 34108",
    "addr:housenumber":"684",
    "addr:postcode":"34108",
    "addr:street":"110Th Ave N",
    "iso:country":"US",
    "sg:address":"684 110th Ave N",
    "sg:city":"Naples",
    "sg:classifiers":[
        {
            "category":"Professional",
            "type":"Services"
        }
    ],
    "sg:phone":"+1 239 598 2561",
    "sg:postcode":"34108",
    "sg:province":"FL",
    "wof:name":"Joe DOrazio Inc",
    "wof:placetype":"venue"
},
  "geometry": {"coordinates":[-81.81285099999999,26.271392],"type":"Point"}
}