{
  "type": "Feature",
  "properties": {
    "addr:full":"385 Golf Brook Cir Longwood FL 32779",
    "addr:housenumber":"385",
    "addr:postcode":"32779",
    "addr:street":"Golf Brook Cir",
    "iso:country":"US",
    "sg:address":"385 Golf Brook Cir",
    "sg:city":"Longwood",
    "sg:classifiers":[
        {
            "category":"Real Estate",
            "subcategory":"Real Estate Services",
            "type":"Services"
        }
    ],
    "sg:phone":"+1 866 751 5803",
    "sg:postcode":"32779",
    "sg:province":"FL",
    "sg:tags":[
        "apartment",
        "management",
        "rental",
        "finder"
    ],
    "sg:website":"http://orlando.citysearch.com/profile/external/602953322/longwood_fl/golf_brook_at_sabal_point.html?publisher=yellowpages&reference_id=1&placement=ypwebsitemip",
    "wof:name":"Golf Brook at Sabal Point",
    "wof:placetype":"venue"
},
  "geometry": {"coordinates":[-81.41062700000001,28.700072],"type":"Point"}
}