{
  "type": "Feature",
  "properties": {
    "addr:full":"295 Satellite Ave Satellite Beach FL 32937",
    "addr:housenumber":"295",
    "addr:postcode":"32937",
    "addr:street":"Satellite Ave",
    "iso:country":"US",
    "sg:address":"295 Satellite Ave",
    "sg:city":"Satellite Beach",
    "sg:classifiers":[
        {
            "category":"Building & Trades",
            "subcategory":"Landscaping Services",
            "type":"Services"
        }
    ],
    "sg:phone":"+1 321 777 9734",
    "sg:postcode":"32937",
    "sg:province":"FL",
    "wof:name":"Artistic Groundskeepers",
    "wof:placetype":"venue"
},
  "geometry": {"coordinates":[-80.594703,28.157936],"type":"Point"}
}