{
  "type": "Feature",
  "properties": {
    "addr:full":"555 NE 15th St Miami FL 33132",
    "addr:housenumber":"555",
    "addr:postcode":"33132",
    "addr:street":"Ne 15Th St",
    "iso:country":"US",
    "sg:address":"555 NE 15th St",
    "sg:city":"Miami",
    "sg:classifiers":[
        {
            "category":"Professional",
            "subcategory":"Lawyer & Legal Services",
            "type":"Services"
        }
    ],
    "sg:phone":"+1 305 375 0820",
    "sg:postcode":"33132",
    "sg:province":"FL",
    "wof:name":"Myers John H Atty",
    "wof:placetype":"venue"
},
  "geometry": {"coordinates":[-80.18609600000001,25.7897],"type":"Point"}
}