{
  "type": "Feature",
  "properties": {
    "addr:full":"9300 NW 17th Ave Miami FL 33147",
    "addr:housenumber":"9300",
    "addr:postcode":"33147",
    "addr:street":"Nw 17Th Ave",
    "iso:country":"US",
    "sg:address":"9300 NW 17th Ave",
    "sg:city":"Miami",
    "sg:classifiers":[
        {
            "category":"Food & Beverages",
            "subcategory":"Groceries & Convenience Stores",
            "type":"Retail Goods"
        }
    ],
    "sg:phone":"+1 305 696 3378",
    "sg:postcode":"33147",
    "sg:province":"FL",
    "wof:name":"Market Bawa Food",
    "wof:placetype":"venue"
},
  "geometry": {"coordinates":[-80.225962,25.859205],"type":"Point"}
}