{
  "type": "Feature",
  "properties": {
    "addr:full":"6426 Renwick Cir Tampa FL 33647",
    "addr:housenumber":"6426",
    "addr:postcode":"33647",
    "addr:street":"Renwick Cir",
    "iso:country":"US",
    "sg:address":"6426 Renwick Cir",
    "sg:city":"Tampa",
    "sg:classifiers":[
        {
            "category":"Shopping",
            "subcategory":"Catalog Store",
            "type":"Retail Goods"
        }
    ],
    "sg:phone":"+1 813 631 0702",
    "sg:postcode":"33647",
    "sg:province":"FL",
    "sg:tags":[
        "mail",
        "house"
    ],
    "wof:name":"Carol Armstrong",
    "wof:placetype":"venue"
},
  "geometry": {"coordinates":[-82.37830599999999,28.093797],"type":"Point"}
}