{
  "type": "Feature",
  "properties": {
    "iso:country":"US",
    "sg:address":"12401 Normandy Blvd",
    "sg:city":"Jacksonville",
    "sg:classifiers":[
        {
            "category":"Food & Beverages",
            "subcategory":"Groceries & Convenience Stores",
            "type":"Retail Goods"
        }
    ],
    "sg:phone":"+1 904 781 8990",
    "sg:postcode":"32221",
    "sg:province":"FL",
    "wof:name":"Mini Mart",
    "wof:placetype":"venue"
},
  "geometry": {"coordinates":[-81.86904,30.25772],"type":"Point"}
}