{
  "type": "Feature",
  "properties": {
    "iso:country":"US",
    "sg:address":"6692 Deering Cir",
    "sg:city":"Sarasota",
    "sg:classifiers":[
        {
            "category":"Wholesale",
            "subcategory":"Metals & Minerals",
            "type":"Manufacturing & Wholesale Goods"
        }
    ],
    "sg:phone":"+1 941 929 7113",
    "sg:postcode":"34240",
    "sg:province":"FL",
    "sg:tags":[
        "center"
    ],
    "wof:name":"A Gutter Co",
    "wof:placetype":"venue"
},
  "geometry": {"coordinates":[-82.436848,27.313969],"type":"Point"}
}