{
  "type": "Feature",
  "properties": {
    "iso:country":"US",
    "sg:address":"673 Sandy Neck Ln",
    "sg:city":"Altamonte Spgs",
    "sg:classifiers":[
        {
            "category":"Real Estate",
            "subcategory":"Real Estate Agent",
            "type":"Services"
        }
    ],
    "sg:phone":"+1 407 869 5868",
    "sg:postcode":"32714",
    "sg:province":"FL",
    "wof:name":"Realty Resource",
    "wof:placetype":"venue"
},
  "geometry": {"coordinates":[-81.420886,28.675061],"type":"Point"}
}