{
  "type": "Feature",
  "properties": {
    "addr:full":"2500 E Hallandale Beach Blvd Hallandale FL 33009",
    "addr:housenumber":"2500",
    "addr:postcode":"33009",
    "addr:street":"E Hallandale Beach Blvd",
    "iso:country":"US",
    "sg:address":"2500 E Hallandale Beach Blvd",
    "sg:city":"Hallandale",
    "sg:classifiers":[
        {
            "category":"Health Services",
            "subcategory":"Medical Lab",
            "type":"Services"
        }
    ],
    "sg:phone":"+1 954 456 0081",
    "sg:postcode":"33009",
    "sg:province":"FL",
    "sg:tags":[
        "manufacture",
        "dental"
    ],
    "wof:name":"D&C Dental Laboratories Inc",
    "wof:placetype":"venue"
},
  "geometry": {"coordinates":[-80.125091,25.986217],"type":"Point"}
}