{
  "type": "Feature",
  "properties": {
    "iso:country":"US",
    "sg:address":"301 Bonaventure Blvd",
    "sg:city":"Fort Lauderdale",
    "sg:classifiers":[
        {
            "category":"Building & Trades",
            "subcategory":"Landscaping Services",
            "type":"Services"
        }
    ],
    "sg:phone":"+1 954 530 8001",
    "sg:postcode":"33326",
    "sg:province":"FL",
    "wof:name":"Rgp Lawn Services Corp",
    "wof:placetype":"venue"
},
  "geometry": {"coordinates":[-80.373259,26.116513],"type":"Point"}
}