{
  "type": "Feature",
  "properties": {
    "iso:country":"US",
    "sg:address":"5305 Garden Cove Rd",
    "sg:city":"Panama City",
    "sg:classifiers":[
        {
            "category":"Building & Trades",
            "subcategory":"Cleaning & Sanitation",
            "type":"Services"
        }
    ],
    "sg:phone":"+1 850 872 8086",
    "sg:postcode":"32404",
    "sg:province":"FL",
    "sg:tags":[
        "house"
    ],
    "wof:name":"A Tidy Cottage",
    "wof:placetype":"venue"
},
  "geometry": {"coordinates":[-85.593363,30.156177],"type":"Point"}
}