{
  "type": "Feature",
  "properties": {
    "iso:country":"US",
    "sg:address":"14355 SW 158th Pl",
    "sg:city":"Miami",
    "sg:classifiers":[
        {
            "category":"Autos & Motor Vehicles",
            "subcategory":"Automobile Sales",
            "type":"Retail Goods"
        }
    ],
    "sg:phone":"+1 305 234 7757",
    "sg:postcode":"33196",
    "sg:province":"FL",
    "sg:tags":[
        "dealers-used",
        "car",
        "used",
        "cars-wholesale"
    ],
    "wof:name":"South Florida Auto Sales",
    "wof:placetype":"venue"
},
  "geometry": {"coordinates":[-80.450532,25.632957],"type":"Point"}
}