{
  "type": "Feature",
  "properties": {
    "addr:full":"82685 Overseas Hwy Islamorada FL 33036",
    "addr:housenumber":"82685",
    "addr:postcode":"33036",
    "addr:street":"Overseas Hwy",
    "iso:country":"US",
    "sg:address":"82685 Overseas Hwy",
    "sg:city":"Islamorada",
    "sg:classifiers":[
        {
            "category":"Restaurant",
            "type":"Food & Drink"
        }
    ],
    "sg:phone":"+1 305 664 0117",
    "sg:postcode":"33036",
    "sg:province":"FL",
    "sg:tags":[
        "eating"
    ],
    "wof:name":"Great Wall Chinese Restaurant",
    "wof:placetype":"venue"
},
  "geometry": {"coordinates":[-80.62567,24.926561],"type":"Point"}
}