{
  "type": "Feature",
  "properties": {
    "addr:full":"5511 SW 57th St Fort Lauderdale FL 33314",
    "addr:housenumber":"5511",
    "addr:postcode":"33314",
    "addr:street":"Sw 57Th St",
    "iso:country":"US",
    "sg:address":"5511 SW 57th St",
    "sg:city":"Fort Lauderdale",
    "sg:classifiers":[
        {
            "category":"Banks & Credit Unions",
            "subcategory":"Investment Brokerage",
            "type":"Services"
        }
    ],
    "sg:phone":"+1 954 792 8212",
    "sg:postcode":"33314",
    "sg:province":"FL",
    "sg:tags":[
        "advisory"
    ],
    "wof:name":"Cote Financial Corp",
    "wof:placetype":"venue"
},
  "geometry": {"coordinates":[-80.223527,26.049953],"type":"Point"}
}