{
  "type": "Feature",
  "properties": {
    "addr:full":"1096 W Church St Avon Park FL 33825",
    "addr:housenumber":"1096",
    "addr:postcode":"33825",
    "addr:street":"W Church St",
    "iso:country":"US",
    "sg:address":"1096 W Church St",
    "sg:city":"Avon Park",
    "sg:classifiers":[
        {
            "category":"Shopping",
            "subcategory":"Clothing, Apparel, & Fashions",
            "type":"Retail Goods"
        }
    ],
    "sg:phone":"+1 863 453 5525",
    "sg:postcode":"33825",
    "sg:province":"FL",
    "sg:tags":[
        "navy",
        "army"
    ],
    "wof:name":"Military & Police II",
    "wof:placetype":"venue"
},
  "geometry": {"coordinates":[-81.514348,27.59748],"type":"Point"}
}