{
  "type": "Feature",
  "properties": {
    "iso:country":"US",
    "sg:address":"1438 Sturbridge Pl",
    "sg:city":"Orange Park",
    "sg:classifiers":[
        {
            "category":"Manufacturing",
            "subcategory":"Tools & Machinery",
            "type":"Manufacturing & Wholesale Goods"
        }
    ],
    "sg:phone":"+1 904 269 4249",
    "sg:postcode":"32308",
    "sg:province":"FL",
    "sg:tags":[
        "machine",
        "vending",
        "mfg"
    ],
    "wof:name":"Paragon Services",
    "wof:placetype":"venue"
},
  "geometry": {"coordinates":[-84.251879,30.491349],"type":"Point"}
}