{
  "type": "Feature",
  "properties": {
    "iso:country":"US",
    "sg:address":"2320 Apalachee Pkwy",
    "sg:city":"Tallahassee",
    "sg:classifiers":[
        {
            "category":"Professional",
            "subcategory":"Business Services",
            "type":"Services"
        }
    ],
    "sg:phone":"+1 850 656 3483",
    "sg:postcode":"32301",
    "sg:province":"FL",
    "wof:name":"Blue Water Scuba and Trvl Ctr",
    "wof:placetype":"venue"
},
  "geometry": {"coordinates":[-84.243432,30.429989],"type":"Point"}
}