{
  "type": "Feature",
  "properties": {
    "addr:full":"1333 E Cape Coral Pkwy Cape Coral FL 33904",
    "addr:housenumber":"1333",
    "addr:postcode":"33904",
    "addr:street":"E Cape Coral Pkwy",
    "iso:country":"US",
    "sg:address":"1333 E Cape Coral Pkwy",
    "sg:city":"Cape Coral",
    "sg:classifiers":[
        {
            "category":"Personal",
            "subcategory":"Beauty Salon",
            "type":"Services"
        }
    ],
    "sg:phone":"+1 239 541 2244",
    "sg:postcode":"33904",
    "sg:province":"FL",
    "sg:tags":[
        "manicuring"
    ],
    "wof:name":"Nails By Carina",
    "wof:placetype":"venue"
},
  "geometry": {"coordinates":[-81.947563,26.562625],"type":"Point"}
}