{
  "type": "Feature",
  "properties": {
    "addr:full":"4744 Trouble Creek Rd New Port Richey FL 34652",
    "addr:housenumber":"4744",
    "addr:postcode":"34652",
    "addr:street":"Trouble Creek Rd",
    "iso:country":"US",
    "sg:address":"4744 Trouble Creek Rd",
    "sg:city":"New Port Richey",
    "sg:classifiers":[
        {
            "category":"Personal",
            "subcategory":"Beauty Salon",
            "type":"Services"
        }
    ],
    "sg:phone":"+1 727 848 3541",
    "sg:postcode":"34652",
    "sg:province":"FL",
    "sg:tags":[
        "shop"
    ],
    "wof:name":"Advanced Hair Hits",
    "wof:placetype":"venue"
},
  "geometry": {"coordinates":[-82.735004,28.224252],"type":"Point"}
}