{
  "type": "Feature",
  "properties": {
    "iso:country":"US",
    "sg:address":"1021 W Colonial Dr",
    "sg:city":"Orlando",
    "sg:classifiers":[
        {
            "category":"Health Services",
            "subcategory":"Chiropractor",
            "type":"Services"
        }
    ],
    "sg:phone":"+1 407 649 9699",
    "sg:postcode":"32804",
    "sg:province":"FL",
    "wof:name":"Regional Chiropractic Group",
    "wof:placetype":"venue"
},
  "geometry": {"coordinates":[-81.394397,28.553042],"type":"Point"}
}