{
  "type": "Feature",
  "properties": {
    "iso:country":"US",
    "sg:address":"903 Pondella Rd",
    "sg:city":"Fort Myers",
    "sg:classifiers":[
        {
            "category":"Organizations",
            "subcategory":"Religious Organization",
            "type":"Services"
        }
    ],
    "sg:phone":"+1 239 652 4125",
    "sg:postcode":"33903",
    "sg:province":"FL",
    "wof:name":"New Wine Ministries Inc",
    "wof:placetype":"venue"
},
  "geometry": {"coordinates":[-81.91540500000001,26.667395],"type":"Point"}
}