{
  "type": "Feature",
  "properties": {
    "addr:full":"1919 Thesy Dr Melbourne FL 32940",
    "addr:housenumber":"1919",
    "addr:postcode":"32940",
    "addr:street":"Thesy Dr",
    "iso:country":"US",
    "sg:address":"1919 Thesy Dr",
    "sg:city":"Melbourne",
    "sg:classifiers":[
        {
            "category":"Professional",
            "subcategory":"Business Services",
            "type":"Services"
        }
    ],
    "sg:phone":"+1 321 255 2100",
    "sg:postcode":"32940",
    "sg:province":"FL",
    "sg:tags":[
        "arbitration"
    ],
    "wof:name":"Christian Concilation Svc",
    "wof:placetype":"venue"
},
  "geometry": {"coordinates":[-80.718227,28.254363],"type":"Point"}
}