{
  "type": "Feature",
  "properties": {
    "iso:country":"US",
    "sg:address":"18600 NW 87th Ave Unit 121",
    "sg:city":"Hialeah",
    "sg:classifiers":[
        {
            "category":"Home & Garden",
            "subcategory":"Home Furnishings",
            "type":"Retail Goods"
        }
    ],
    "sg:phone":"+1 305 816 0049",
    "sg:postcode":"33015",
    "sg:province":"FL",
    "sg:tags":[
        "decor"
    ],
    "wof:name":"Yairemis Silk Flowers",
    "wof:placetype":"venue"
},
  "geometry": {"coordinates":[-80.34245799999999,25.942358],"type":"Point"}
}