{
  "type": "Feature",
  "properties": {
    "iso:country":"US",
    "sg:address":"211 Spoonwood Ct",
    "sg:city":"Winter Springs",
    "sg:classifiers":[
        {
            "category":"Manufacturing",
            "subcategory":"Tools & Machinery",
            "type":"Manufacturing & Wholesale Goods"
        }
    ],
    "sg:phone":"+1 407 695 9329",
    "sg:postcode":"32708",
    "sg:province":"FL",
    "sg:tags":[
        "industry",
        "mfg"
    ],
    "wof:name":"Charles D Stockton",
    "wof:placetype":"venue"
},
  "geometry": {"coordinates":[-81.306732,28.686524],"type":"Point"}
}