{
  "type": "Feature",
  "properties": {
    "iso:country":"US",
    "sg:address":"8375 Argyle Corners Ct",
    "sg:city":"Jacksonville",
    "sg:classifiers":[
        {
            "category":"Building & Trades",
            "subcategory":"Construction",
            "type":"Services"
        }
    ],
    "sg:phone":"+1 904 777 3869",
    "sg:postcode":"32244",
    "sg:province":"FL",
    "sg:tags":[
        "concrete",
        "contractor"
    ],
    "wof:name":"Cvn Concrete Poles Inc",
    "wof:placetype":"venue"
},
  "geometry": {"coordinates":[-81.764056,30.197743],"type":"Point"}
}