{
  "type": "Feature",
  "properties": {
    "addr:full":"275 Fontainebleau Blvd # 200 Miami FL 33172",
    "addr:housenumber":"275",
    "addr:postcode":"33172",
    "addr:street":"Fontainebleau Blvd # 200",
    "iso:country":"US",
    "sg:address":"275 Fontainebleau Blvd # 200",
    "sg:city":"Miami",
    "sg:classifiers":[
        {
            "category":"Real Estate",
            "subcategory":"Real Estate Services",
            "type":"Services"
        },
        {
            "category":"Building & Trades",
            "subcategory":"Construction",
            "type":"Services"
        }
    ],
    "sg:phone":"+1 305 222 6134",
    "sg:postcode":"33172",
    "sg:province":"FL",
    "sg:tags":[
        "management",
        "condominium"
    ],
    "sg:website":"http://jogcpa.com",
    "wof:name":"Jose O Garcia Cpa /Cpa",
    "wof:placetype":"venue"
},
  "geometry": {"coordinates":[-80.339158,25.771507],"type":"Point"}
}