{
  "type": "Feature",
  "properties": {
    "iso:country":"US",
    "sg:address":"2699 N University Dr",
    "sg:city":"Fort Lauderdale",
    "sg:classifiers":[
        {
            "category":"Restaurant",
            "type":"Food & Drink"
        }
    ],
    "sg:phone":"+1 954 741 7002",
    "sg:postcode":"33322",
    "sg:province":"FL",
    "sg:tags":[
        "eating"
    ],
    "wof:name":"Checkers Drive-In Restaurant",
    "wof:placetype":"venue"
},
  "geometry": {"coordinates":[-80.257165,26.157529],"type":"Point"}
}