{
  "type": "Feature",
  "properties": {
    "addr:full":"6225 Alvin Rd Jacksonville FL 32222",
    "addr:housenumber":"6225",
    "addr:postcode":"32222",
    "addr:street":"Alvin Rd",
    "iso:country":"US",
    "sg:address":"6225 Alvin Rd",
    "sg:city":"Jacksonville",
    "sg:classifiers":[
        {
            "category":"Real Estate",
            "subcategory":"Real Estate Agent",
            "type":"Services"
        }
    ],
    "sg:phone":"+1 904 573 2514",
    "sg:postcode":"32222",
    "sg:province":"FL",
    "wof:name":"Robert J Honkanen",
    "wof:placetype":"venue"
},
  "geometry": {"coordinates":[-81.83160599999999,30.232244],"type":"Point"}
}