{
  "type": "Feature",
  "properties": {
    "addr:full":"1099 W 67th St Hialeah FL 33012",
    "addr:housenumber":"1099",
    "addr:postcode":"33012",
    "addr:street":"W 67Th St",
    "iso:country":"US",
    "sg:address":"1099 W 67th St",
    "sg:city":"Hialeah",
    "sg:classifiers":[
        {
            "category":"Professional",
            "subcategory":"Business Services",
            "type":"Services"
        }
    ],
    "sg:phone":"+1 305 558 6489",
    "sg:postcode":"33012",
    "sg:province":"FL",
    "wof:name":"Penton Interiors",
    "wof:placetype":"venue"
},
  "geometry": {"coordinates":[-80.301856,25.883454],"type":"Point"}
}