{
  "type": "Feature",
  "properties": {
    "addr:full":"840 The Rialto Venice FL 34285",
    "addr:housenumber":"840",
    "addr:postcode":"34285",
    "addr:street":"The",
    "iso:country":"US",
    "sg:address":"840 The Rialto",
    "sg:city":"Venice",
    "sg:classifiers":[
        {
            "category":"Professional",
            "subcategory":"Computer Services",
            "type":"Services"
        }
    ],
    "sg:phone":"+1 941 484 4518",
    "sg:postcode":"34285",
    "sg:province":"FL",
    "sg:tags":[
        "internet"
    ],
    "wof:name":"Access Unlimited Of Venice",
    "wof:placetype":"venue"
},
  "geometry": {"coordinates":[-82.444469,27.085639],"type":"Point"}
}