{
  "type": "Feature",
  "properties": {
    "iso:country":"US",
    "sg:address":"5598 NW 7th Ave",
    "sg:city":"Miami",
    "sg:classifiers":[
        {
            "category":"Manufacturing",
            "subcategory":"Apparel",
            "type":"Manufacturing & Wholesale Goods"
        }
    ],
    "sg:phone":"+1 305 751 4549",
    "sg:postcode":"33127",
    "sg:province":"FL",
    "sg:tags":[
        "regalia",
        "fraternal",
        "supply"
    ],
    "wof:name":"Hamilton's Fraternity",
    "wof:placetype":"venue"
},
  "geometry": {"coordinates":[-80.208252,25.82716],"type":"Point"}
}