{
  "type": "Feature",
  "properties": {
    "iso:country":"US",
    "sg:address":"7403 Temple Terrace Hwy",
    "sg:city":"Tampa",
    "sg:classifiers":[
        {
            "category":"Social Services",
            "type":"Services"
        }
    ],
    "sg:phone":"+1 813 988 1992",
    "sg:postcode":"33637",
    "sg:province":"FL",
    "sg:tags":[
        "counselor",
        "marriage",
        "family"
    ],
    "wof:name":"Martha S Campbell PHD",
    "wof:placetype":"venue"
},
  "geometry": {"coordinates":[-82.37135000000001,28.032633],"type":"Point"}
}