{
  "type": "Feature",
  "properties": {
    "iso:country":"US",
    "sg:address":"110 Co Rd 470",
    "sg:city":"Okahumpka",
    "sg:classifiers":[
        {
            "category":"Manufacturing",
            "subcategory":"Petroleum Products",
            "type":"Manufacturing & Wholesale Goods"
        },
        {
            "category":"Building & Trades",
            "subcategory":"Construction",
            "type":"Services"
        }
    ],
    "sg:phone":"+1 352 787 6452",
    "sg:postcode":"34762",
    "sg:province":"FL",
    "sg:tags":[
        "asphalt",
        "mfg"
    ],
    "wof:name":"Asphalt Production Corp",
    "wof:placetype":"venue"
},
  "geometry": {"coordinates":[-81.951932,28.755242],"type":"Point"}
}