{
  "type": "Feature",
  "properties": {
    "addr:full":"1000 30th St S St Petersburg FL 33712",
    "addr:housenumber":"1000",
    "addr:postcode":"33712",
    "addr:street":"30Th St S",
    "iso:country":"US",
    "sg:address":"1000 30th St S",
    "sg:city":"St Petersburg",
    "sg:classifiers":[
        {
            "category":"Professional",
            "subcategory":"Business Services",
            "type":"Services"
        }
    ],
    "sg:phone":"+1 727 327 2617",
    "sg:postcode":"33712",
    "sg:province":"FL",
    "sg:tags":[
        "paper"
    ],
    "wof:name":"Confidential Paper Shredding",
    "wof:placetype":"venue"
},
  "geometry": {"coordinates":[-82.673221,27.758346],"type":"Point"}
}