{
  "type": "Feature",
  "properties": {
    "iso:country":"US",
    "sg:address":"13790 NW 4th St",
    "sg:city":"Fort Lauderdale",
    "sg:classifiers":[
        {
            "category":"Health Services",
            "subcategory":"Doctor",
            "type":"Services"
        }
    ],
    "sg:phone":"+1 954 467 7277",
    "sg:postcode":"33325",
    "sg:province":"FL",
    "sg:tags":[
        "firm",
        "law"
    ],
    "wof:name":"Leonard Zedeck",
    "wof:placetype":"venue"
},
  "geometry": {"coordinates":[-80.334333,26.125474],"type":"Point"}
}