{
  "type": "Feature",
  "properties": {
    "iso:country":"US",
    "sg:address":"3916 Valrico Grove Dr",
    "sg:city":"Valrico",
    "sg:classifiers":[
        {
            "category":"Professional",
            "subcategory":"Detective & Security Services",
            "type":"Services"
        }
    ],
    "sg:phone":"+1 813 653 1597",
    "sg:postcode":"33594",
    "sg:province":"FL",
    "sg:tags":[
        "information",
        "bureau"
    ],
    "wof:name":"I2eye Consulting Services",
    "wof:placetype":"venue"
},
  "geometry": {"coordinates":[-82.23378099999999,27.92265],"type":"Point"}
}