{
  "type": "Feature",
  "properties": {
    "addr:full":"2311 Whitfield Park Ave Sarasota FL 34243",
    "addr:housenumber":"2311",
    "addr:postcode":"34243",
    "addr:street":"Whitfield Park Ave",
    "iso:country":"US",
    "sg:address":"2311 Whitfield Park Ave",
    "sg:city":"Sarasota",
    "sg:classifiers":[
        {
            "category":"Home & Garden",
            "subcategory":"Building Materials",
            "type":"Retail Goods"
        }
    ],
    "sg:phone":"+1 941 753 7871",
    "sg:postcode":"34243",
    "sg:province":"FL",
    "sg:tags":[
        "screen",
        "window"
    ],
    "wof:name":"Casco Industries Of Florida",
    "wof:placetype":"venue"
},
  "geometry": {"coordinates":[-82.538397,27.420201],"type":"Point"}
}