{
  "type": "Feature",
  "properties": {
    "addr:full":"9300 Henderson Grade Fort Myers FL 33917",
    "addr:housenumber":"9300",
    "addr:postcode":"myers;33917",
    "addr:street":"Henderson Grade",
    "iso:country":"US",
    "sg:address":"9300 Henderson Grade",
    "sg:city":"Fort Myers",
    "sg:classifiers":[
        {
            "category":"Building & Trades",
            "subcategory":"Construction",
            "type":"Services"
        }
    ],
    "sg:phone":"+1 239 731 6898",
    "sg:postcode":"33917",
    "sg:province":"FL",
    "sg:tags":[
        "specializing",
        "co",
        "municipal",
        "contractor",
        "water",
        "sewer"
    ],
    "wof:name":"Best Electrical Construction",
    "wof:placetype":"venue"
},
  "geometry": {"coordinates":[-81.80719499999999,26.742442],"type":"Point"}
}