{
  "type": "Feature",
  "properties": {
    "addr:full":"6590 Old Winter Garden Rd Orlando FL 32835",
    "addr:housenumber":"6590",
    "addr:postcode":"32835",
    "addr:street":"Old Winter Garden Rd",
    "iso:country":"US",
    "sg:address":"6590 Old Winter Garden Rd",
    "sg:city":"Orlando",
    "sg:classifiers":[
        {
            "category":"Bars & Pubs",
            "type":"Food & Drink"
        }
    ],
    "sg:phone":"+1 407 578 9138",
    "sg:postcode":"32835",
    "sg:province":"FL",
    "sg:tags":[
        "tavern"
    ],
    "wof:name":"Scores Sports Pub & Grill",
    "wof:placetype":"venue"
},
  "geometry": {"coordinates":[-81.475388,28.538977],"type":"Point"}
}