{
  "type": "Feature",
  "properties": {
    "iso:country":"US",
    "sg:address":"5525 Pensacola Blvd",
    "sg:city":"Pensacola",
    "sg:classifiers":[
        {
            "category":"Restaurant",
            "type":"Food & Drink"
        }
    ],
    "sg:phone":"+1 850 475 8850",
    "sg:postcode":"32505",
    "sg:province":"FL",
    "wof:name":"Casa Del Sol",
    "wof:placetype":"venue"
},
  "geometry": {"coordinates":[-87.243596,30.46889],"type":"Point"}
}