{
  "type": "Feature",
  "properties": {
    "iso:country":"US",
    "sg:address":"1912 W Aileen St",
    "sg:city":"Tampa",
    "sg:classifiers":[
        {
            "category":"Professional",
            "subcategory":"Business Services",
            "type":"Services"
        }
    ],
    "sg:phone":"+1 813 251 2371",
    "sg:postcode":"33607",
    "sg:province":"FL",
    "wof:name":"Mervic Group",
    "wof:placetype":"venue"
},
  "geometry": {"coordinates":[-82.47994300000001,27.968079],"type":"Point"}
}