{
  "type": "Feature",
  "properties": {
    "addr:full":"226 N Amelia Ave Deland FL 32724",
    "addr:housenumber":"226",
    "addr:postcode":"32724",
    "addr:street":"N Amelia Ave",
    "iso:country":"US",
    "sg:address":"226 N Amelia Ave",
    "sg:city":"Deland",
    "sg:classifiers":[
        {
            "category":"Banks & Credit Unions",
            "subcategory":"Investment Brokerage",
            "type":"Services"
        }
    ],
    "sg:phone":"+1 386 822 4668",
    "sg:postcode":"32724",
    "sg:province":"FL",
    "sg:tags":[
        "security"
    ],
    "wof:name":"KCM Asset Management",
    "wof:placetype":"venue"
},
  "geometry": {"coordinates":[-81.299414,29.030339],"type":"Point"}
}