{
  "type": "Feature",
  "properties": {
    "iso:country":"US",
    "sg:address":"274 Cranes Roost Blvd",
    "sg:city":"Altamonte Springs",
    "sg:classifiers":[
        {
            "category":"Arts & Performance",
            "subcategory":"Festival",
            "type":"Entertainment"
        }
    ],
    "sg:postcode":"32701",
    "sg:province":"FL",
    "sg:website":"www.greatorlandobeerfestival.com",
    "wof:name":"Greater Orlando Beer Festival",
    "wof:placetype":"venue"
},
  "geometry": {"coordinates":[-81.382863,28.666582],"type":"Point"}
}