{
  "type": "Feature",
  "properties": {
    "addr:full":"2020 W Brandon Blvd Brandon FL 33511",
    "addr:housenumber":"2020",
    "addr:postcode":"33511",
    "addr:street":"W Brandon Blvd",
    "iso:country":"US",
    "sg:address":"2020 W Brandon Blvd",
    "sg:city":"Brandon",
    "sg:classifiers":[
        {
            "category":"Food & Beverages",
            "subcategory":"Specialty",
            "type":"Retail Goods"
        }
    ],
    "sg:phone":"+1 813 657 3100",
    "sg:postcode":"33511",
    "sg:province":"FL",
    "sg:tags":[
        "vitamin"
    ],
    "wof:name":"Glen Burkett",
    "wof:placetype":"venue"
},
  "geometry": {"coordinates":[-82.316318,27.937788],"type":"Point"}
}