{
  "type": "Feature",
  "properties": {
    "addr:full":"3274 S Military Trl Lake Worth FL 33463",
    "addr:housenumber":"3274",
    "addr:postcode":"33463",
    "addr:street":"S Military Trl",
    "iso:country":"US",
    "sg:address":"3274 S Military Trl",
    "sg:city":"Lake Worth",
    "sg:classifiers":[
        {
            "category":"Food & Beverages",
            "subcategory":"Groceries & Convenience Stores",
            "type":"Retail Goods"
        }
    ],
    "sg:phone":"+1 561 640 4010",
    "sg:postcode":"33463",
    "sg:province":"FL",
    "wof:name":"F&A Food Corp",
    "wof:placetype":"venue"
},
  "geometry": {"coordinates":[-80.113044,26.629035],"type":"Point"}
}