{
  "type": "Feature",
  "properties": {
    "addr:full":"295 Needles Trl Longwood FL 32779",
    "addr:housenumber":"295",
    "addr:postcode":"32779",
    "addr:street":"Needles Trl",
    "iso:country":"US",
    "sg:address":"295 Needles Trl",
    "sg:city":"Longwood",
    "sg:classifiers":[
        {
            "category":"Shopping",
            "subcategory":"Hobbies, Toys, & Games",
            "type":"Retail Goods"
        }
    ],
    "sg:phone":"+1 407 774 6030",
    "sg:postcode":"32779",
    "sg:province":"FL",
    "sg:tags":[
        "product",
        "mfg",
        "mineral",
        "nonmetallic"
    ],
    "wof:name":"Carol M Diehl",
    "wof:placetype":"venue"
},
  "geometry": {"coordinates":[-81.44078399999999,28.692051],"type":"Point"}
}