{
  "type": "Feature",
  "properties": {
    "iso:country":"US",
    "sg:address":"1512 E 4th Ave",
    "sg:city":"Tampa",
    "sg:classifiers":[
        {
            "category":"Building & Trades",
            "subcategory":"Equipment Rental",
            "type":"Services"
        }
    ],
    "sg:phone":"+1 813 248 2481",
    "sg:postcode":"33605",
    "sg:province":"FL",
    "sg:tags":[
        "yard",
        "leasing",
        "store"
    ],
    "wof:name":"P G & H Leasing Inc",
    "wof:placetype":"venue"
},
  "geometry": {"coordinates":[-82.442809,27.95813],"type":"Point"}
}