{
  "type": "Feature",
  "properties": {
    "iso:country":"US",
    "sg:address":"662 SE Walters Ter",
    "sg:city":"Port Saint Lucie",
    "sg:classifiers":[
        {
            "category":"Building & Trades",
            "subcategory":"Construction",
            "type":"Services"
        }
    ],
    "sg:phone":"+1 561 742 1903",
    "sg:postcode":"34983",
    "sg:province":"FL",
    "sg:tags":[
        "contractor"
    ],
    "wof:name":"Correia Drywall Finishing Inc",
    "wof:placetype":"venue"
},
  "geometry": {"coordinates":[-80.33215800000001,27.296619],"type":"Point"}
}