{
  "type": "Feature",
  "properties": {
    "iso:country":"US",
    "sg:address":"6140 Mimosa Dr",
    "sg:city":"Orlando",
    "sg:classifiers":[
        {
            "category":"Building & Trades",
            "subcategory":"Construction",
            "type":"Services"
        }
    ],
    "sg:phone":"+1 407 281 0007",
    "sg:postcode":"32807",
    "sg:province":"FL",
    "sg:tags":[
        "hanging",
        "contractor"
    ],
    "wof:name":"Islander Enterprises Painting",
    "wof:placetype":"venue"
},
  "geometry": {"coordinates":[-81.299786,28.54482],"type":"Point"}
}