{
  "type": "Feature",
  "properties": {
    "addr:full":"4076 N Beach Rd Englewood FL 34223",
    "addr:housenumber":"4076",
    "addr:postcode":"34223",
    "addr:street":"N Beach Rd",
    "iso:country":"US",
    "sg:address":"4076 N Beach Rd",
    "sg:city":"Englewood",
    "sg:classifiers":[
        {
            "category":"Real Estate",
            "subcategory":"Real Estate Operator",
            "type":"Services"
        }
    ],
    "sg:phone":"+1 941 474 2429",
    "sg:postcode":"34223",
    "sg:province":"FL",
    "sg:tags":[
        "building",
        "resort",
        "apartment"
    ],
    "wof:name":"Pelican Shore Cottages",
    "wof:placetype":"venue"
},
  "geometry": {"coordinates":[-82.370293,26.941791],"type":"Point"}
}