{
  "type": "Feature",
  "properties": {
    "iso:country":"US",
    "sg:address":"150 Balboa Rd",
    "sg:city":"Cantonment",
    "sg:classifiers":[
        {
            "category":"Personal",
            "subcategory":"Beauty Salon",
            "type":"Services"
        }
    ],
    "sg:phone":"+1 850 968 2259",
    "sg:postcode":"32533",
    "sg:province":"FL",
    "wof:name":"Clolas Beauty World Salon",
    "wof:placetype":"venue"
},
  "geometry": {"coordinates":[-87.348534,30.614811],"type":"Point"}
}