{
  "type": "Feature",
  "properties": {
    "addr:full":"1265 S Semoran Blvd Winter Park FL 32792",
    "addr:housenumber":"1265",
    "addr:postcode":"32792",
    "addr:street":"S Semoran Blvd",
    "iso:country":"US",
    "sg:address":"1265 S Semoran Blvd",
    "sg:city":"Winter Park",
    "sg:classifiers":[
        {
            "category":"Insurance",
            "subcategory":"Insurance Agent",
            "type":"Services"
        }
    ],
    "sg:phone":"+1 407 671 7331",
    "sg:postcode":"32792",
    "sg:province":"FL",
    "sg:tags":[
        "consultant"
    ],
    "sg:website":"www.pba-fl.com",
    "wof:name":"Professional Benefit Adm Inc",
    "wof:placetype":"venue"
},
  "geometry": {"coordinates":[-81.307914,28.580592],"type":"Point"}
}