{
  "type": "Feature",
  "properties": {
    "addr:full":"1 King St  St Augustine FL 32084",
    "addr:housenumber":"1",
    "addr:postcode":"32084",
    "addr:street":"King St",
    "iso:country":"US",
    "sg:address":"1 King St ",
    "sg:city":"St Augustine",
    "sg:classifiers":[
        {
            "category":"Restaurant",
            "type":"Food & Drink"
        }
    ],
    "sg:menulink":"http://www.allmenus.com/fl/st-augustine/293239-south-a-philly-steaks-and-hoagies/menu/",
    "sg:phone":"+1 904 824 0666",
    "sg:postcode":"32084",
    "sg:province":"FL",
    "sg:tags":[
        "hoagy"
    ],
    "wof:name":"South-A-Philly Steaks and Hoagies",
    "wof:placetype":"venue"
},
  "geometry": {"coordinates":[-81.31102199999999,29.892215],"type":"Point"}
}