{
  "type": "Feature",
  "properties": {
    "iso:country":"US",
    "sg:address":"8722 Pine Barnens Dr",
    "sg:city":"Orlando",
    "sg:classifiers":[
        {
            "category":"Professional",
            "subcategory":"Computer Services",
            "type":"Services"
        }
    ],
    "sg:phone":"+1 407 679 5056",
    "sg:postcode":"32817",
    "sg:province":"FL",
    "sg:tags":[
        "programing",
        "custom"
    ],
    "wof:name":"Software Engineering & Consult",
    "wof:placetype":"venue"
},
  "geometry": {"coordinates":[-81.262252,28.601714],"type":"Point"}
}