{
  "type": "Feature",
  "properties": {
    "addr:full":"2004 8th St NW Winter Haven FL 33881",
    "addr:housenumber":"2004",
    "addr:postcode":"33881",
    "addr:street":"8Th St Nw",
    "iso:country":"US",
    "sg:address":"2004 8th St NW",
    "sg:city":"Winter Haven",
    "sg:classifiers":[
        {
            "category":"Restaurant",
            "type":"Food & Drink"
        }
    ],
    "sg:phone":"+1 863 293 0627",
    "sg:postcode":"33881",
    "sg:province":"FL",
    "sg:tags":[
        "eating"
    ],
    "wof:name":"Burger King",
    "wof:placetype":"venue"
},
  "geometry": {"coordinates":[-81.73614600000001,28.0344],"type":"Point"}
}