{
  "type": "Feature",
  "properties": {
    "iso:country":"US",
    "sg:address":"600 General Harris St",
    "sg:city":"Longboat Key",
    "sg:classifiers":[
        {
            "category":"Building & Trades",
            "subcategory":"Construction",
            "type":"Services"
        }
    ],
    "sg:phone":"+1 941 316 1988",
    "sg:postcode":"34228",
    "sg:province":"FL",
    "sg:tags":[
        "marking",
        "maintenance",
        "parking"
    ],
    "wof:name":"Longboat Key Town Public Works",
    "wof:placetype":"venue"
},
  "geometry": {"coordinates":[-82.67210300000001,27.426733],"type":"Point"}
}