{
  "type": "Feature",
  "properties": {
    "iso:country":"US",
    "sg:address":"3111 Opportunity Ct",
    "sg:city":"Daytona Beach",
    "sg:classifiers":[
        {
            "category":"Professional",
            "subcategory":"Business Services",
            "type":"Services"
        }
    ],
    "sg:phone":"+1 386 760 3226",
    "sg:postcode":"32119",
    "sg:province":"FL",
    "wof:name":"R G I S Inventory Specialists",
    "wof:placetype":"venue"
},
  "geometry": {"coordinates":[-80.99437500000001,29.151652],"type":"Point"}
}