{
  "type": "Feature",
  "properties": {
    "iso:country":"US",
    "sg:address":"8867 SW 129th Ter",
    "sg:city":"Miami",
    "sg:classifiers":[
        {
            "category":"Wholesale",
            "subcategory":"Electrical",
            "type":"Manufacturing & Wholesale Goods"
        }
    ],
    "sg:phone":"+1 305 238 4830",
    "sg:postcode":"33176",
    "sg:province":"FL",
    "sg:tags":[
        "equipment",
        "electronic",
        "supply"
    ],
    "wof:name":"Ma'Kache Corp",
    "wof:placetype":"venue"
},
  "geometry": {"coordinates":[-80.339336,25.649687],"type":"Point"}
}