{
  "type": "Feature",
  "properties": {
    "iso:country":"US",
    "sg:address":"3402 Ocean Dr",
    "sg:city":"Vero Beach",
    "sg:classifiers":[
        {
            "category":"Shopping",
            "subcategory":"Shoes",
            "type":"Retail Goods"
        }
    ],
    "sg:phone":"+1 772 231 2772",
    "sg:postcode":"32963",
    "sg:province":"FL",
    "wof:name":"Kemp's Shoe Salon",
    "wof:placetype":"venue"
},
  "geometry": {"coordinates":[-80.356238,27.652436],"type":"Point"}
}