{
  "type": "Feature",
  "properties": {
    "iso:country":"US",
    "sg:address":"100 Thornton Dr",
    "sg:city":"Palm Beach Gdns",
    "sg:classifiers":[
        {
            "category":"Professional",
            "subcategory":"Detective & Security Services",
            "type":"Services"
        }
    ],
    "sg:phone":"+1 561 625 8405",
    "sg:postcode":"33418",
    "sg:province":"FL",
    "sg:tags":[
        "guard",
        "patrol"
    ],
    "wof:name":"Preston Security",
    "wof:placetype":"venue"
},
  "geometry": {"coordinates":[-80.13959199999999,26.812113],"type":"Point"}
}