{
  "type": "Feature",
  "properties": {
    "iso:country":"US",
    "sg:address":"3919 SE 4th Ave",
    "sg:city":"Cape Coral",
    "sg:classifiers":[
        {
            "category":"Restaurant",
            "type":"Food & Drink"
        }
    ],
    "sg:phone":"+1 239 540 4474",
    "sg:postcode":"33904",
    "sg:province":"FL",
    "sg:tags":[
        "eating"
    ],
    "wof:name":"PVP Catering",
    "wof:placetype":"venue"
},
  "geometry": {"coordinates":[-81.966537,26.578145],"type":"Point"}
}