{
  "type": "Feature",
  "properties": {
    "iso:country":"US",
    "sg:address":"5360 Gulf of Mexico Dr",
    "sg:city":"Longboat Key",
    "sg:classifiers":[
        {
            "category":"Real Estate",
            "subcategory":"Real Estate Agent",
            "type":"Services"
        }
    ],
    "sg:phone":"+1 941 383 5577",
    "sg:postcode":"34228",
    "sg:province":"FL",
    "sg:website":"www.wagnerrealty.com",
    "wof:name":"Wagner Realty",
    "wof:placetype":"venue"
},
  "geometry": {"coordinates":[-82.65623100000001,27.409615],"type":"Point"}
}