{
  "type": "Feature",
  "properties": {
    "addr:full":"536 67th St Bradenton Beach FL 34217",
    "addr:housenumber":"536",
    "addr:postcode":"34217",
    "addr:street":"67Th St",
    "iso:country":"US",
    "sg:address":"536 67th St",
    "sg:city":"Bradenton Beach",
    "sg:classifiers":[
        {
            "category":"Building & Trades",
            "subcategory":"Construction",
            "type":"Services"
        }
    ],
    "sg:phone":"+1 941 778 4290",
    "sg:postcode":"34217",
    "sg:province":"FL",
    "sg:tags":[
        "nonresidential"
    ],
    "wof:name":"Douglas Development Corp",
    "wof:placetype":"venue"
},
  "geometry": {"coordinates":[-82.715536,27.516784],"type":"Point"}
}