{
  "type": "Feature",
  "properties": {
    "addr:full":"7306 W 34th Ave Hialeah FL 33018",
    "addr:housenumber":"7306",
    "addr:postcode":"33018",
    "addr:street":"W 34Th Ave",
    "iso:country":"US",
    "sg:address":"7306 W 34th Ave",
    "sg:city":"Hialeah",
    "sg:classifiers":[
        {
            "category":"Home & Garden",
            "subcategory":"Carpets & Floor Coverings",
            "type":"Retail Goods"
        }
    ],
    "sg:phone":"+1 305 823 0878",
    "sg:postcode":"33018",
    "sg:province":"FL",
    "wof:name":"D&E Carpet Service Inc",
    "wof:placetype":"venue"
},
  "geometry": {"coordinates":[-80.352048,25.888878],"type":"Point"}
}