{
  "type": "Feature",
  "properties": {
    "iso:country":"US",
    "sg:address":"2550 Clairmont Ave",
    "sg:city":"Sanford",
    "sg:classifiers":[
        {
            "category":"Personal",
            "subcategory":"Beauty Salon",
            "type":"Services"
        }
    ],
    "sg:phone":"+1 407 268 9889",
    "sg:postcode":"32773",
    "sg:province":"FL",
    "wof:name":"Jay's Hair & Nail Salon",
    "wof:placetype":"venue"
},
  "geometry": {"coordinates":[-81.28279000000001,28.784535],"type":"Point"}
}