{
  "type": "Feature",
  "properties": {
    "addr:full":"8671 Ulmerton Rd Largo FL 33771",
    "addr:housenumber":"8671",
    "addr:postcode":"33771",
    "addr:street":"Ulmerton Rd",
    "iso:country":"US",
    "sg:address":"8671 Ulmerton Rd",
    "sg:city":"Largo",
    "sg:classifiers":[
        {
            "category":"Restaurant",
            "type":"Food & Drink"
        }
    ],
    "sg:phone":"+1 727 535 7666",
    "sg:postcode":"33771",
    "sg:province":"FL",
    "sg:tags":[
        "eating"
    ],
    "wof:name":"Taco Bell",
    "wof:placetype":"venue"
},
  "geometry": {"coordinates":[-82.76020699999999,27.894454],"type":"Point"}
}