{
  "type": "Feature",
  "properties": {
    "addr:full":"16725 Gulf Blvd N Redington Bch FL 33708",
    "addr:housenumber":"16725",
    "addr:postcode":"33708",
    "addr:street":"Gulf Blvd N Redington Bch",
    "iso:country":"US",
    "sg:address":"16725 Gulf Blvd",
    "sg:city":"N Redington Bch",
    "sg:classifiers":[
        {
            "category":"Restaurant",
            "type":"Food & Drink"
        }
    ],
    "sg:phone":"+1 727 391 0453",
    "sg:postcode":"33708",
    "sg:province":"FL",
    "sg:tags":[
        "eating"
    ],
    "wof:name":"Sweet Sage Coffee Co",
    "wof:placetype":"venue"
},
  "geometry": {"coordinates":[-82.821842,27.816875],"type":"Point"}
}