{
  "type": "Feature",
  "properties": {
    "iso:country":"US",
    "sg:address":"3949 14th St W",
    "sg:city":"Bradenton",
    "sg:classifiers":[
        {
            "category":"Autos & Motor Vehicles",
            "subcategory":"Auto Supplies",
            "type":"Retail Goods"
        }
    ],
    "sg:phone":"+1 941 746 7885",
    "sg:postcode":"34205",
    "sg:province":"FL",
    "sg:tags":[
        "tire"
    ],
    "wof:name":"Shepherd's Tire Svc",
    "wof:placetype":"venue"
},
  "geometry": {"coordinates":[-82.57533599999999,27.46247],"type":"Point"}
}