{
  "type": "Feature",
  "properties": {
    "addr:full":"5318 Balsam St New Port Richey FL 34652",
    "addr:housenumber":"5318",
    "addr:postcode":"34652",
    "addr:street":"Balsam St",
    "iso:country":"US",
    "sg:address":"5318 Balsam St",
    "sg:city":"New Port Richey",
    "sg:classifiers":[
        {
            "category":"Professional",
            "subcategory":"Lawyer & Legal Services",
            "type":"Services"
        }
    ],
    "sg:phone":"+1 727 845 3728",
    "sg:postcode":"34652",
    "sg:province":"FL",
    "wof:name":"Senior Law Series Inc",
    "wof:placetype":"venue"
},
  "geometry": {"coordinates":[-82.726377,28.239443],"type":"Point"}
}