{
  "type": "Feature",
  "properties": {
    "addr:full":"5701 34th St N St Petersburg FL 33714",
    "addr:housenumber":"5701",
    "addr:postcode":"33714",
    "addr:street":"34Th St N",
    "iso:country":"US",
    "sg:address":"5701 34th St N",
    "sg:city":"St Petersburg",
    "sg:classifiers":[
        {
            "category":"Home & Garden",
            "subcategory":"Building Materials",
            "type":"Retail Goods"
        }
    ],
    "sg:phone":"+1 727 521 1871",
    "sg:postcode":"33714",
    "sg:province":"FL",
    "sg:tags":[
        "glass",
        "window",
        "plate"
    ],
    "wof:name":"Safelite Auto Glass",
    "wof:placetype":"venue"
},
  "geometry": {"coordinates":[-82.679559,27.824704],"type":"Point"}
}