{
  "type": "Feature",
  "properties": {
    "addr:full":"11102 Biscayne Blvd Miami FL 33181",
    "addr:housenumber":"11102",
    "addr:postcode":"33181",
    "addr:street":"Biscayne Blvd",
    "iso:country":"US",
    "sg:address":"11102 Biscayne Blvd",
    "sg:city":"Miami",
    "sg:classifiers":[
        {
            "category":"Travel",
            "subcategory":"Hotels & Motels",
            "type":"Entertainment"
        }
    ],
    "sg:phone":"+1 305 893 4540",
    "sg:postcode":"33181",
    "sg:province":"FL",
    "sg:tags":[
        "operation",
        "lodging"
    ],
    "wof:name":"Sun'n Surf Motel",
    "wof:placetype":"venue"
},
  "geometry": {"coordinates":[-80.167603,25.878799],"type":"Point"}
}