{
  "type": "Feature",
  "properties": {
    "iso:country":"US",
    "sg:address":"7210 Oak Meadows Cir",
    "sg:city":"Orlando",
    "sg:classifiers":[
        {
            "category":"Professional",
            "subcategory":"Accounting & Tax Preparation",
            "type":"Services"
        }
    ],
    "sg:phone":"+1 407 296 2400",
    "sg:postcode":"32835",
    "sg:province":"FL",
    "wof:name":"Compumed By Bradley Kline",
    "wof:placetype":"venue"
},
  "geometry": {"coordinates":[-81.481488,28.541377],"type":"Point"}
}