{
  "type": "Feature",
  "properties": {
    "iso:country":"US",
    "sg:address":"2150 Tamiami Trl",
    "sg:city":"Port Charlotte",
    "sg:classifiers":[
        {
            "category":"Personal",
            "subcategory":"Beauty Salon",
            "type":"Services"
        }
    ],
    "sg:phone":"+1 941 627 6868",
    "sg:postcode":"33948",
    "sg:province":"FL",
    "sg:tags":[
        "manicuring"
    ],
    "wof:name":"Nails By Veronica",
    "wof:placetype":"venue"
},
  "geometry": {"coordinates":[-82.12520000000001,27.000995],"type":"Point"}
}