{
  "type": "Feature",
  "properties": {
    "addr:full":"1858 Andromeda Ln Fort Lauderdale FL 33327",
    "addr:housenumber":"1858",
    "addr:postcode":"33327",
    "addr:street":"Andromeda Ln",
    "iso:country":"US",
    "sg:address":"1858 Andromeda Ln",
    "sg:city":"Fort Lauderdale",
    "sg:classifiers":[
        {
            "category":"Health Services",
            "subcategory":"Medical Lab",
            "type":"Services"
        }
    ],
    "sg:phone":"+1 954 385 5587",
    "sg:postcode":"33327",
    "sg:province":"FL",
    "sg:tags":[
        "laboratory",
        "dental"
    ],
    "wof:name":"Santk Dental Lab LLC",
    "wof:placetype":"venue"
},
  "geometry": {"coordinates":[-80.42201799999999,26.131188],"type":"Point"}
}