{
  "type": "Feature",
  "properties": {
    "addr:full":"2518 Enterprise Rd Orange City FL 32763",
    "addr:housenumber":"2518",
    "addr:postcode":"32763",
    "addr:street":"Enterprise Rd",
    "iso:country":"US",
    "sg:address":"2518 Enterprise Rd",
    "sg:city":"Orange City",
    "sg:classifiers":[
        {
            "category":"Restaurant",
            "type":"Food & Drink"
        }
    ],
    "sg:phone":"+1 386 532 7427",
    "sg:postcode":"32763",
    "sg:province":"FL",
    "sg:tags":[
        "barbeque"
    ],
    "sg:website":"www.texasroadhouse.com/home.php",
    "wof:name":"Texas Roadhouse",
    "wof:placetype":"venue"
},
  "geometry": {"coordinates":[-81.295005,28.917094],"type":"Point"}
}