{
  "type": "Feature",
  "properties": {
    "iso:country":"US",
    "sg:address":"312 Oakhurst St",
    "sg:city":"Altamonte Springs",
    "sg:classifiers":[
        {
            "category":"Manufacturing",
            "subcategory":"Building Materials",
            "type":"Manufacturing & Wholesale Goods"
        }
    ],
    "sg:phone":"+1 407 788 7675",
    "sg:postcode":"32701",
    "sg:province":"FL",
    "sg:tags":[
        "mfg"
    ],
    "wof:name":"Salvatore Ausonio Window Svc",
    "wof:placetype":"venue"
},
  "geometry": {"coordinates":[-81.377987,28.678945],"type":"Point"}
}