{
  "type": "Feature",
  "properties": {
    "iso:country":"US",
    "sg:address":"5520 W Flagler St",
    "sg:city":"Coral Gables",
    "sg:classifiers":[
        {
            "category":"Organizations",
            "subcategory":"Professional Association",
            "type":"Services"
        }
    ],
    "sg:phone":"+1 305 264 9105",
    "sg:postcode":"33134",
    "sg:province":"FL",
    "wof:name":"Dade Electrical Assn",
    "wof:placetype":"venue"
},
  "geometry": {"coordinates":[-80.28529,25.770831],"type":"Point"}
}