{
  "type": "Feature",
  "properties": {
    "addr:full":"2301 del Prado Blvd S Cape Coral FL 33904",
    "addr:housenumber":"2301",
    "addr:postcode":"33904",
    "addr:street":"Del Prado Blvd S",
    "iso:country":"US",
    "sg:address":"2301 del Prado Blvd S",
    "sg:city":"Cape Coral",
    "sg:classifiers":[
        {
            "category":"Health Services",
            "subcategory":"Clinic",
            "type":"Services"
        }
    ],
    "sg:phone":"+1 239 573 7641",
    "sg:postcode":"33904",
    "sg:province":"FL",
    "sg:tags":[
        "hypnotherapy"
    ],
    "wof:name":"Lotus & The Frog",
    "wof:placetype":"venue"
},
  "geometry": {"coordinates":[-81.941039,26.607914],"type":"Point"}
}