{
  "type": "Feature",
  "properties": {
    "addr:full":"1350 Tradeport Dr Jacksonville FL 32218",
    "addr:housenumber":"1350",
    "addr:postcode":"32218",
    "addr:street":"Tradeport Dr",
    "iso:country":"US",
    "sg:address":"1350 Tradeport Dr",
    "sg:city":"Jacksonville",
    "sg:classifiers":[
        {
            "category":"Retail",
            "subcategory":"Repair Shop",
            "type":"Services"
        }
    ],
    "sg:phone":"+1 904 741 3951",
    "sg:postcode":"32218",
    "sg:province":"FL",
    "sg:tags":[
        "related"
    ],
    "wof:name":"Milestone Industries Inc",
    "wof:placetype":"venue"
},
  "geometry": {"coordinates":[-81.652159,30.479217],"type":"Point"}
}