{
  "type": "Feature",
  "properties": {
    "iso:country":"US",
    "sg:address":"524 9th St S",
    "sg:city":"St Petersburg",
    "sg:classifiers":[
        {
            "category":"Social Services",
            "type":"Services"
        }
    ],
    "sg:phone":"+1 727 823 4691",
    "sg:postcode":"33701",
    "sg:province":"FL",
    "sg:tags":[
        "crisis",
        "intervention"
    ],
    "wof:name":"House Of Mary Magdalene",
    "wof:placetype":"venue"
},
  "geometry": {"coordinates":[-82.646576,27.765325],"type":"Point"}
}