{
  "type": "Feature",
  "properties": {
    "addr:full":"13755 W Sunrise Blvd Fort Lauderdale FL 33323",
    "addr:housenumber":"13755",
    "addr:postcode":"33323",
    "addr:street":"W Sunrise Blvd",
    "iso:country":"US",
    "sg:address":"13755 W Sunrise Blvd",
    "sg:city":"Fort Lauderdale",
    "sg:classifiers":[
        {
            "category":"Coffee & Tea",
            "type":"Food & Drink"
        }
    ],
    "sg:menulink":"http://www.allmenus.com/fl/plantation/116745-starbucks-coffee/menu/",
    "sg:phone":"+1 954 845 0971",
    "sg:postcode":"33323",
    "sg:province":"FL",
    "sg:tags":[
        "american"
    ],
    "wof:name":"Starbucks Coffee",
    "wof:placetype":"venue"
},
  "geometry": {"coordinates":[-80.330834,26.145902],"type":"Point"}
}