{
  "type": "Feature",
  "properties": {
    "addr:full":"5024 W 12th Ave Hialeah FL 33012",
    "addr:housenumber":"5024",
    "addr:postcode":"33012",
    "addr:street":"W 12Th Ave",
    "iso:country":"US",
    "sg:address":"5024 W 12th Ave",
    "sg:city":"Hialeah",
    "sg:classifiers":[
        {
            "category":"Shopping",
            "subcategory":"Department Store",
            "type":"Retail Goods"
        }
    ],
    "sg:phone":"+1 305 698 8686",
    "sg:postcode":"33012",
    "sg:province":"FL",
    "sg:tags":[
        "shop"
    ],
    "wof:name":"Dollar Mas LA 49",
    "wof:placetype":"venue"
},
  "geometry": {"coordinates":[-80.30694,25.867763],"type":"Point"}
}