{
  "type": "Feature",
  "properties": {
    "addr:full":"128 Bearss Cir Longwood FL 32750",
    "addr:housenumber":"128",
    "addr:postcode":"32750",
    "addr:street":"Bearss Cir",
    "iso:country":"US",
    "sg:address":"128 Bearss Cir",
    "sg:city":"Longwood",
    "sg:classifiers":[
        {
            "category":"Manufacturing",
            "subcategory":"Printing",
            "type":"Manufacturing & Wholesale Goods"
        }
    ],
    "sg:phone":"+1 407 339 2941",
    "sg:postcode":"32750",
    "sg:province":"FL",
    "sg:tags":[
        "newspaper"
    ],
    "wof:name":"Sparetimes Inc",
    "wof:placetype":"venue"
},
  "geometry": {"coordinates":[-81.35485199999999,28.703686],"type":"Point"}
}