{
  "type": "Feature",
  "properties": {
    "addr:full":"1114 Chatman Blvd Brooksville FL 34601",
    "addr:housenumber":"1114",
    "addr:postcode":"34601",
    "addr:street":"Chatman Blvd",
    "iso:country":"US",
    "sg:address":"1114 Chatman Blvd",
    "sg:city":"Brooksville",
    "sg:classifiers":[
        {
            "category":"Health Services",
            "subcategory":"Nursing And Care Facility",
            "type":"Services"
        }
    ],
    "sg:phone":"+1 352 796 6701",
    "sg:postcode":"34601",
    "sg:province":"FL",
    "sg:tags":[
        "home",
        "convalescent"
    ],
    "wof:name":"Brooksville Health Care Ctr",
    "wof:placetype":"venue"
},
  "geometry": {"coordinates":[-82.403273,28.546135],"type":"Point"}
}