{
  "type": "Feature",
  "properties": {
    "iso:country":"US",
    "sg:address":"18557 SW 104th Ave",
    "sg:city":"Miami",
    "sg:classifiers":[
        {
            "category":"Manufacturing",
            "subcategory":"Textiles",
            "type":"Manufacturing & Wholesale Goods"
        },
        {
            "category":"Retail",
            "subcategory":"Repair Shop",
            "type":"Services"
        }
    ],
    "sg:phone":"+1 786 573 5050",
    "sg:postcode":"33157",
    "sg:province":"FL",
    "sg:tags":[
        "manufacture",
        "a",
        "complete",
        "line",
        "knit",
        "fabric"
    ],
    "wof:name":"Carmel Textiles Inc",
    "wof:placetype":"venue"
},
  "geometry": {"coordinates":[-80.360288,25.596242],"type":"Point"}
}