{
  "type": "Feature",
  "properties": {
    "iso:country":"US",
    "sg:address":"4618 Lotus Way",
    "sg:city":"Boynton Beach",
    "sg:classifiers":[
        {
            "category":"Building & Trades",
            "subcategory":"Plumbing",
            "type":"Services"
        }
    ],
    "sg:phone":"+1 561 732 8741",
    "sg:postcode":"33436",
    "sg:province":"FL",
    "sg:tags":[
        "plumbing",
        "contractor"
    ],
    "wof:name":"Ward's Plumbing Svc",
    "wof:placetype":"venue"
},
  "geometry": {"coordinates":[-80.117586,26.535461],"type":"Point"}
}