{
  "type": "Feature",
  "properties": {
    "iso:country":"US",
    "sg:address":"310 Williams Point Blvd # 4",
    "sg:city":"Cocoa",
    "sg:classifiers":[
        {
            "category":"Autos & Motor Vehicles",
            "subcategory":"Auto Supplies",
            "type":"Retail Goods"
        },
        {
            "category":"Retail",
            "subcategory":"Auto Repair",
            "type":"Services"
        }
    ],
    "sg:phone":"+1 321 631 3008",
    "sg:postcode":"32927",
    "sg:province":"FL",
    "sg:tags":[
        "body",
        "repairing",
        "upholstery",
        "automobile",
        "top",
        "covers",
        "seat",
        "part",
        "accessory",
        "painting"
    ],
    "wof:name":"Stitches Auto Upholstery",
    "wof:placetype":"venue"
},
  "geometry": {"coordinates":[-80.763282,28.451039],"type":"Point"}
}