{
  "type": "Feature",
  "properties": {
    "addr:full":"1633 San Marco Blvd Jacksonville FL 32207",
    "addr:housenumber":"1633",
    "addr:postcode":"32207",
    "addr:street":"San Marco Blvd",
    "iso:country":"US",
    "sg:address":"1633 San Marco Blvd",
    "sg:city":"Jacksonville",
    "sg:classifiers":[
        {
            "category":"Manufacturing",
            "subcategory":"Printing",
            "type":"Manufacturing & Wholesale Goods"
        }
    ],
    "sg:phone":"+1 904 388 5072",
    "sg:postcode":"32207",
    "sg:province":"FL",
    "sg:tags":[
        "publisher",
        "periodical"
    ],
    "wof:name":"Arbus Magazine",
    "wof:placetype":"venue"
},
  "geometry": {"coordinates":[-81.660461,30.307753],"type":"Point"}
}