{
  "type": "Feature",
  "properties": {
    "iso:country":"US",
    "sg:address":"2888 W Lake Mary Blvd",
    "sg:city":"Lake Mary",
    "sg:classifiers":[
        {
            "category":"Professional",
            "type":"Services"
        }
    ],
    "sg:phone":"+1 407 324 8557",
    "sg:postcode":"32746",
    "sg:province":"FL",
    "sg:tags":[
        "establishment"
    ],
    "wof:name":"Vital Technologies",
    "wof:placetype":"venue"
},
  "geometry": {"coordinates":[-81.33439799999999,28.756048],"type":"Point"}
}