{
  "type": "Feature",
  "properties": {
    "iso:country":"US",
    "sg:address":"8811 Dusty Ln",
    "sg:city":"New Port Richey",
    "sg:classifiers":[
        {
            "category":"Real Estate",
            "subcategory":"Developer",
            "type":"Services"
        }
    ],
    "sg:phone":"+1 727 848 1773",
    "sg:postcode":"34655",
    "sg:province":"FL",
    "wof:name":"G M B Investments Inc",
    "wof:placetype":"venue"
},
  "geometry": {"coordinates":[-82.669757,28.253456],"type":"Point"}
}