{
  "type": "Feature",
  "properties": {
    "iso:country":"US",
    "sg:address":"9148 Geneva St",
    "sg:city":"Spring Hill",
    "sg:classifiers":[
        {
            "category":"Manufacturing",
            "subcategory":"Retail Goods",
            "type":"Manufacturing & Wholesale Goods"
        }
    ],
    "sg:phone":"+1 352 683 1639",
    "sg:postcode":"34608",
    "sg:province":"FL",
    "sg:tags":[
        "picture",
        "merchandise",
        "mfg"
    ],
    "wof:name":"Art Specialties",
    "wof:placetype":"venue"
},
  "geometry": {"coordinates":[-82.57028200000001,28.4496],"type":"Point"}
}