{
  "type": "Feature",
  "properties": {
    "addr:full":"6860 W Kelly Ct Crystal River FL 34429",
    "addr:housenumber":"6860",
    "addr:postcode":"34429",
    "addr:street":"W Kelly Ct",
    "iso:country":"US",
    "sg:address":"6860 W Kelly Ct",
    "sg:city":"Crystal River",
    "sg:classifiers":[
        {
            "category":"Personal",
            "type":"Services"
        }
    ],
    "sg:phone":"+1 352 795 3703",
    "sg:postcode":"34429",
    "sg:province":"FL",
    "sg:tags":[
        "program",
        "physical",
        "exercise",
        "fitness"
    ],
    "wof:name":"Kelly's Health Club",
    "wof:placetype":"venue"
},
  "geometry": {"coordinates":[-82.548726,28.865583],"type":"Point"}
}