{
  "type": "Feature",
  "properties": {
    "iso:country":"US",
    "sg:address":"6605 Black Oak Pl",
    "sg:city":"Pensacola",
    "sg:classifiers":[
        {
            "category":"Manufacturing",
            "subcategory":"Tools & Machinery",
            "type":"Manufacturing & Wholesale Goods"
        }
    ],
    "sg:phone":"+1 850 232 2498",
    "sg:postcode":"32526",
    "sg:province":"FL",
    "sg:tags":[
        "maintenance",
        "supply"
    ],
    "wof:name":"SW 1 Innovation Inc",
    "wof:placetype":"venue"
},
  "geometry": {"coordinates":[-87.285775,30.474794],"type":"Point"}
}