{
  "type": "Feature",
  "properties": {
    "addr:full":"4151 Park Blvd Pinellas Park FL 33781",
    "addr:housenumber":"4151",
    "addr:postcode":"33781",
    "addr:street":"Park Blvd",
    "iso:country":"US",
    "sg:address":"4151 Park Blvd",
    "sg:city":"Pinellas Park",
    "sg:classifiers":[
        {
            "category":"Building & Trades",
            "subcategory":"Plumbing",
            "type":"Services"
        }
    ],
    "sg:phone":"+1 727 548 7660",
    "sg:postcode":"33781",
    "sg:province":"FL",
    "sg:tags":[
        "contractor"
    ],
    "wof:name":"Gulf To Bay Air Conditioning &",
    "wof:placetype":"venue"
},
  "geometry": {"coordinates":[-82.689723,27.839303],"type":"Point"}
}