{
  "type": "Feature",
  "properties": {
    "addr:full":"136 Swain Blvd Lake Worth FL 33463",
    "addr:housenumber":"136",
    "addr:postcode":"33463",
    "addr:street":"Swain Blvd",
    "iso:country":"US",
    "sg:address":"136 Swain Blvd",
    "sg:city":"Lake Worth",
    "sg:classifiers":[
        {
            "category":"Retail",
            "subcategory":"Auto Repair",
            "type":"Services"
        }
    ],
    "sg:phone":"+1 561 966 3773",
    "sg:postcode":"33463",
    "sg:province":"FL",
    "sg:tags":[
        "automotive"
    ],
    "wof:name":"Certified Auto Inspection",
    "wof:placetype":"venue"
},
  "geometry": {"coordinates":[-80.12519399999999,26.620391],"type":"Point"}
}