{
  "type": "Feature",
  "properties": {
    "addr:full":"4707 NW 22nd St Coconut Creek FL 33063",
    "addr:housenumber":"4707",
    "addr:postcode":"33063",
    "addr:street":"Nw 22Nd St",
    "iso:country":"US",
    "sg:address":"4707 NW 22nd St",
    "sg:city":"Coconut Creek",
    "sg:classifiers":[
        {
            "category":"Building & Trades",
            "subcategory":"Pest Control",
            "type":"Services"
        }
    ],
    "sg:phone":"+1 954 975 8012",
    "sg:postcode":"33063",
    "sg:province":"FL",
    "sg:website":"www.deadbugsociety.com",
    "wof:name":"Dead Bug Society Inc",
    "wof:placetype":"venue"
},
  "geometry": {"coordinates":[-80.18987,26.254568],"type":"Point"}
}