{
  "type": "Feature",
  "properties": {
    "addr:full":"16060 E Aintree Dr Loxahatchee FL 33470",
    "addr:housenumber":"16060",
    "addr:postcode":"33470",
    "addr:street":"E Aintree Dr",
    "iso:country":"US",
    "sg:address":"16060 E Aintree Dr",
    "sg:city":"Loxahatchee",
    "sg:classifiers":[
        {
            "category":"Retail",
            "subcategory":"Auto Repair",
            "type":"Services"
        }
    ],
    "sg:phone":"+1 561 876 2165",
    "sg:postcode":"33470",
    "sg:province":"FL",
    "sg:tags":[
        "body",
        "automobile",
        "painting",
        "repairing"
    ],
    "wof:name":"Magical Touch Auto Detail",
    "wof:placetype":"venue"
},
  "geometry": {"coordinates":[-80.302961,26.695832],"type":"Point"}
}