{
  "type": "Feature",
  "properties": {
    "addr:full":"150 SW 12th Ave Pompano Beach FL 33069",
    "addr:housenumber":"150",
    "addr:postcode":"33069",
    "addr:street":"Sw 12Th Ave",
    "iso:country":"US",
    "sg:address":"150 SW 12th Ave",
    "sg:city":"Pompano Beach",
    "sg:classifiers":[
        {
            "category":"Health Services",
            "subcategory":"Health Practitioner",
            "type":"Services"
        }
    ],
    "sg:phone":"+1 954 783 5100",
    "sg:postcode":"33069",
    "sg:province":"FL",
    "sg:tags":[
        "psychologist"
    ],
    "sg:website":"www.behavioralmedicine.com",
    "wof:name":"Behavioral Medicine & Biofeed",
    "wof:placetype":"venue"
},
  "geometry": {"coordinates":[-80.139222,26.22995],"type":"Point"}
}