{
  "type": "Feature",
  "properties": {
    "iso:country":"US",
    "sg:address":"224 E Pine St",
    "sg:city":"Lakeland",
    "sg:classifiers":[
        {
            "category":"Home & Garden",
            "subcategory":"Furniture",
            "type":"Retail Goods"
        }
    ],
    "sg:phone":"+1 863 682 2494",
    "sg:postcode":"33801",
    "sg:province":"FL",
    "sg:tags":[
        "business"
    ],
    "wof:name":"A Showcase Gallery Antiques",
    "wof:placetype":"venue"
},
  "geometry": {"coordinates":[-81.955414,28.045993],"type":"Point"}
}