{
  "type": "Feature",
  "properties": {
    "iso:country":"US",
    "sg:address":"201 W Flagler St",
    "sg:city":"Miami",
    "sg:classifiers":[
        {
            "category":"Professional",
            "subcategory":"Lawyer & Legal Services",
            "type":"Services"
        }
    ],
    "sg:phone":"+1 305 373 5313",
    "sg:postcode":"33130",
    "sg:province":"FL",
    "sg:tags":[
        "attorney"
    ],
    "wof:name":"Cosgrove Law Offices",
    "wof:placetype":"venue"
},
  "geometry": {"coordinates":[-80.198059,25.774],"type":"Point"}
}