{
  "type": "Feature",
  "properties": {
    "addr:full":"2107 63rd Ave E Bradenton FL 34203",
    "addr:housenumber":"2107",
    "addr:postcode":"34203",
    "addr:street":"63Rd Ave E",
    "iso:country":"US",
    "sg:address":"2107 63rd Ave E",
    "sg:city":"Bradenton",
    "sg:classifiers":[
        {
            "category":"Building & Trades",
            "subcategory":"Equipment Rental",
            "type":"Services"
        }
    ],
    "sg:phone":"+1 941 739 7755",
    "sg:postcode":"34203",
    "sg:province":"FL",
    "sg:tags":[
        "leasing"
    ],
    "wof:name":"Trane Leasing Svc",
    "wof:placetype":"venue"
},
  "geometry": {"coordinates":[-82.537215,27.429285],"type":"Point"}
}