{
  "type": "Feature",
  "properties": {
    "iso:country":"US",
    "sg:address":"6805 Visitors Cir",
    "sg:city":"Orlando",
    "sg:classifiers":[
        {
            "category":"Personal",
            "type":"Services"
        },
        {
            "category":"Education",
            "subcategory":"Special Training",
            "type":"Public Place"
        },
        {
            "category":"Recreation",
            "subcategory":"Picnic Area",
            "type":"Entertainment"
        },
        {
            "category":"Shopping",
            "subcategory":"Party Supplies",
            "type":"Retail Goods"
        },
        {
            "category":"Landmark",
            "subcategory":"Tourist Information",
            "type":"Public Place"
        }
    ],
    "sg:phone":"+1 407 903 1150",
    "sg:postcode":"32819",
    "sg:province":"FL",
    "sg:tags":[
        "arcade",
        "children's",
        "favors",
        "instruction",
        "promoter",
        "skydiving",
        "attraction",
        "planning",
        "tours-operators",
        "event",
        "amusement"
    ],
    "sg:website":"http://www.iflyorlando.com",
    "wof:name":"I Fly Orlando",
    "wof:placetype":"venue"
},
  "geometry": {"coordinates":[-81.465149,28.463461],"type":"Point"}
}