{
  "type": "Feature",
  "properties": {
    "iso:country":"US",
    "sg:address":"9123 NW 171st Ln",
    "sg:city":"Hialeah",
    "sg:classifiers":[
        {
            "category":"Home & Garden",
            "subcategory":"Building Materials",
            "type":"Retail Goods"
        }
    ],
    "sg:phone":"+1 305 823 4666",
    "sg:postcode":"33018",
    "sg:province":"FL",
    "sg:tags":[
        "device",
        "doors-operating"
    ],
    "wof:name":"Yosvani Automatic Gates Inc",
    "wof:placetype":"venue"
},
  "geometry": {"coordinates":[-80.34844699999999,25.929223],"type":"Point"}
}