{
  "type": "Feature",
  "properties": {
    "addr:full":"301 Cypress Ave Saint Cloud FL 34769",
    "addr:housenumber":"301",
    "addr:postcode":"34769",
    "addr:street":"Cypress Ave",
    "iso:country":"US",
    "sg:address":"301 Cypress Ave",
    "sg:city":"Saint Cloud",
    "sg:classifiers":[
        {
            "category":"Banks & Credit Unions",
            "subcategory":"Financial Services",
            "type":"Services"
        }
    ],
    "sg:phone":"+1 407 891 8887",
    "sg:postcode":"34769",
    "sg:province":"FL",
    "sg:tags":[
        "investor"
    ],
    "wof:name":"Bettyblanche Investments Inc",
    "wof:placetype":"venue"
},
  "geometry": {"coordinates":[-81.273309,28.258219],"type":"Point"}
}