{
  "type": "Feature",
  "properties": {
    "addr:full":"1749 Mainline Dr Quincy FL 32351",
    "addr:housenumber":"1749",
    "addr:postcode":"32351",
    "addr:street":"Mainline Dr",
    "iso:country":"US",
    "sg:address":"1749 Mainline Dr",
    "sg:city":"Quincy",
    "sg:classifiers":[
        {
            "category":"Retail",
            "subcategory":"Repair Shop",
            "type":"Services"
        },
        {
            "category":"Manufacturing",
            "subcategory":"Signs",
            "type":"Manufacturing & Wholesale Goods"
        }
    ],
    "sg:phone":"+1 850 627 6558",
    "sg:postcode":"32351",
    "sg:province":"FL",
    "sg:tags":[
        "signs-erectors",
        "hanger",
        "signs-maintenance"
    ],
    "wof:name":"Curtis Signs",
    "wof:placetype":"venue"
},
  "geometry": {"coordinates":[-84.613907,30.581751],"type":"Point"}
}