{
  "type": "Feature",
  "properties": {
    "addr:full":"1208 W Hampton Springs Ave Perry FL 32347",
    "addr:housenumber":"1208",
    "addr:postcode":"32347",
    "addr:street":"W Hampton Springs Ave",
    "iso:country":"US",
    "sg:address":"1208 W Hampton Springs Ave",
    "sg:city":"Perry",
    "sg:classifiers":[
        {
            "category":"Place Of Worship",
            "subcategory":"Church",
            "type":"Public Place"
        },
        {
            "category":"Place Of Worship",
            "type":"Public Place"
        }
    ],
    "sg:phone":"+1 850 223 2165",
    "sg:postcode":"32347",
    "sg:province":"FL",
    "sg:tags":[
        "churches-interdenominational",
        "churches-various",
        "denomination"
    ],
    "wof:name":"New Beginning Church Of God",
    "wof:placetype":"venue"
},
  "geometry": {"coordinates":[-83.59634699999999,30.109362],"type":"Point"}
}