{
  "type": "Feature",
  "properties": {
    "iso:country":"US",
    "sg:address":"1150 Lane Ave N",
    "sg:city":"Jacksonville",
    "sg:classifiers":[
        {
            "category":"Retail",
            "subcategory":"Auto Repair",
            "type":"Services"
        }
    ],
    "sg:phone":"+1 904 781 5566",
    "sg:postcode":"32254",
    "sg:province":"FL",
    "sg:tags":[
        "exchanging",
        "bonding",
        "brake",
        "shoe"
    ],
    "wof:name":"Florida Brake",
    "wof:placetype":"venue"
},
  "geometry": {"coordinates":[-81.752128,30.336427],"type":"Point"}
}