{
  "type": "Feature",
  "properties": {
    "addr:full":"413 161st Ave Saint Petersburg FL 33708",
    "addr:housenumber":"413",
    "addr:postcode":"33708",
    "addr:street":"161St Ave",
    "iso:country":"US",
    "sg:address":"413 161st Ave",
    "sg:city":"Saint Petersburg",
    "sg:classifiers":[
        {
            "category":"Real Estate",
            "subcategory":"Real Estate Agent",
            "type":"Services"
        }
    ],
    "sg:phone":"+1 727 943 8112",
    "sg:postcode":"33708",
    "sg:province":"FL",
    "wof:name":"Palin Appraisals Inc",
    "wof:placetype":"venue"
},
  "geometry": {"coordinates":[-82.808688,27.816369],"type":"Point"}
}