{
  "type": "Feature",
  "properties": {
    "iso:country":"US",
    "sg:address":"10223 Serene Meadow Dr N",
    "sg:city":"Boca Raton",
    "sg:classifiers":[
        {
            "category":"Restaurant",
            "type":"Food & Drink"
        }
    ],
    "sg:phone":"+1 561 852 8926",
    "sg:postcode":"33428",
    "sg:province":"FL",
    "sg:tags":[
        "eating"
    ],
    "wof:name":"Uncle Buffees",
    "wof:placetype":"venue"
},
  "geometry": {"coordinates":[-80.20839100000001,26.332538],"type":"Point"}
}