{
  "type": "Feature",
  "properties": {
    "addr:full":"2275 Macedo Rd NE Palm Bay FL 32907",
    "addr:housenumber":"2275",
    "addr:postcode":"32907",
    "addr:street":"Macedo Rd Ne",
    "iso:country":"US",
    "sg:address":"2275 Macedo Rd NE",
    "sg:city":"Palm Bay",
    "sg:classifiers":[
        {
            "category":"Wholesale",
            "subcategory":"Scrap",
            "type":"Manufacturing & Wholesale Goods"
        }
    ],
    "sg:phone":"+1 321 768 1055",
    "sg:postcode":"32907",
    "sg:province":"FL",
    "sg:tags":[
        "material"
    ],
    "wof:name":"Danny Monk",
    "wof:placetype":"venue"
},
  "geometry": {"coordinates":[-80.604918,28.004211],"type":"Point"}
}