{
  "type": "Feature",
  "properties": {
    "addr:full":"6200 20th St Vero Beach FL 32966",
    "addr:housenumber":"6200",
    "addr:postcode":"32966",
    "addr:street":"20Th St",
    "iso:country":"US",
    "sg:address":"6200 20th St",
    "sg:city":"Vero Beach",
    "sg:classifiers":[
        {
            "category":"Shopping",
            "subcategory":"Computers & Home Electronics",
            "type":"Retail Goods"
        }
    ],
    "sg:phone":"+1 772 567 9195",
    "sg:postcode":"32966",
    "sg:province":"FL",
    "sg:tags":[
        "equipment",
        "electronic",
        "supply"
    ],
    "wof:name":"Radio Shack",
    "wof:placetype":"venue"
},
  "geometry": {"coordinates":[-80.453451,27.639006],"type":"Point"}
}