{
  "type": "Feature",
  "properties": {
    "iso:country":"US",
    "sg:address":"14348 SW 23rd Ln",
    "sg:city":"Miami",
    "sg:classifiers":[
        {
            "category":"Professional",
            "type":"Services"
        }
    ],
    "sg:phone":"+1 305 221 7601",
    "sg:postcode":"33175",
    "sg:province":"FL",
    "wof:name":"Maria A Zaldua Inc",
    "wof:placetype":"venue"
},
  "geometry": {"coordinates":[-80.426366,25.745378],"type":"Point"}
}