{
  "type": "Feature",
  "properties": {
    "addr:full":"6809 Sparkman St Tampa FL 33616",
    "addr:housenumber":"6809",
    "addr:postcode":"33616",
    "addr:street":"Sparkman St",
    "iso:country":"US",
    "sg:address":"6809 Sparkman St",
    "sg:city":"Tampa",
    "sg:classifiers":[
        {
            "category":"Building & Trades",
            "subcategory":"Construction",
            "type":"Services"
        }
    ],
    "sg:phone":"+1 813 831 3320",
    "sg:postcode":"33616",
    "sg:province":"FL",
    "sg:tags":[
        "house"
    ],
    "wof:name":"Foster Construction",
    "wof:placetype":"venue"
},
  "geometry": {"coordinates":[-82.52461,27.867826],"type":"Point"}
}