{
  "type": "Feature",
  "properties": {
    "iso:country":"US",
    "sg:address":"3545 US Hwy 1 S",
    "sg:city":"St Augustine",
    "sg:classifiers":[
        {
            "category":"Manufacturing",
            "subcategory":"Printing",
            "type":"Manufacturing & Wholesale Goods"
        },
        {
            "category":"Manufacturing",
            "subcategory":"Motor Vehicles & Parts",
            "type":"Manufacturing & Wholesale Goods"
        }
    ],
    "sg:phone":"+1 904 797 1633",
    "sg:postcode":"32086",
    "sg:province":"FL",
    "sg:tags":[
        "screen"
    ],
    "wof:name":"Ancient City Screen Graphics",
    "wof:placetype":"venue"
},
  "geometry": {"coordinates":[-81.322237,29.828496],"type":"Point"}
}