{
  "type": "Feature",
  "properties": {
    "addr:full":"6300 Gulf Blvd St Pete Beach FL 33706",
    "addr:housenumber":"6300",
    "addr:postcode":"33706",
    "addr:street":"Gulf Blvd St Pete Beach",
    "iso:country":"US",
    "sg:address":"6300 Gulf Blvd",
    "sg:city":"St Pete Beach",
    "sg:classifiers":[
        {
            "category":"Shopping",
            "subcategory":"Gifts & Souvenirs",
            "type":"Retail Goods"
        }
    ],
    "sg:phone":"+1 727 360 6821",
    "sg:postcode":"33706",
    "sg:province":"FL",
    "sg:tags":[
        "shop"
    ],
    "wof:name":"Pelican Cove Gifts",
    "wof:placetype":"venue"
},
  "geometry": {"coordinates":[-82.745706,27.733548],"type":"Point"}
}