{
  "type": "Feature",
  "properties": {
    "addr:full":"5000 S Macdill Ave Tampa FL 33611",
    "addr:housenumber":"5000",
    "addr:postcode":"33611",
    "addr:street":"S Macdill Ave",
    "iso:country":"US",
    "sg:address":"5000 S Macdill Ave",
    "sg:city":"Tampa",
    "sg:classifiers":[
        {
            "category":"Building & Trades",
            "subcategory":"Electrical",
            "type":"Services"
        }
    ],
    "sg:phone":"+1 813 832 8306",
    "sg:postcode":"33611",
    "sg:province":"FL",
    "sg:tags":[
        "electric",
        "industrial",
        "contractors-commercial",
        "contractor"
    ],
    "wof:name":"Maurice J Scott Inc",
    "wof:placetype":"venue"
},
  "geometry": {"coordinates":[-82.49387400000001,27.89233],"type":"Point"}
}