{
  "type": "Feature",
  "properties": {
    "iso:country":"US",
    "sg:address":"500 W 29th St",
    "sg:city":"Hialeah",
    "sg:classifiers":[
        {
            "category":"Wholesale",
            "subcategory":"Machinery & Supplies",
            "type":"Manufacturing & Wholesale Goods"
        }
    ],
    "sg:phone":"+1 305 884 3088",
    "sg:postcode":"33012",
    "sg:province":"FL",
    "sg:tags":[
        "washing",
        "mach"
    ],
    "wof:name":"Laundry World",
    "wof:placetype":"venue"
},
  "geometry": {"coordinates":[-80.294263,25.848007],"type":"Point"}
}