{
  "type": "Feature",
  "properties": {
    "iso:country":"US",
    "sg:address":"3410 SW 110th Ave",
    "sg:city":"Miami",
    "sg:classifiers":[
        {
            "category":"Social Services",
            "subcategory":"Child Care",
            "type":"Services"
        }
    ],
    "sg:phone":"+1 305 554 4143",
    "sg:postcode":"33165",
    "sg:province":"FL",
    "sg:tags":[
        "day"
    ],
    "wof:name":"Smiling Faces Day Care Center",
    "wof:placetype":"venue"
},
  "geometry": {"coordinates":[-80.373901,25.737],"type":"Point"}
}