{
  "type": "Feature",
  "properties": {
    "addr:full":"5900 SW 43rd St Fort Lauderdale FL 33314",
    "addr:housenumber":"5900",
    "addr:postcode":"33314",
    "addr:street":"Sw 43Rd St",
    "iso:country":"US",
    "sg:address":"5900 SW 43rd St",
    "sg:city":"Fort Lauderdale",
    "sg:classifiers":[
        {
            "category":"Retail",
            "subcategory":"Repair Shop",
            "type":"Services"
        }
    ],
    "sg:phone":"+1 954 583 2883",
    "sg:postcode":"33314",
    "sg:province":"FL",
    "sg:tags":[
        "welding"
    ],
    "wof:name":"Waverly Trailer & Welding",
    "wof:placetype":"venue"
},
  "geometry": {"coordinates":[-80.226635,26.068057],"type":"Point"}
}