{
  "type": "Feature",
  "properties": {
    "addr:full":"3498 S Dixie Hwy Miami FL 33133",
    "addr:housenumber":"3498",
    "addr:postcode":"33133",
    "addr:street":"S Dixie Hwy",
    "iso:country":"US",
    "sg:address":"3498 S Dixie Hwy",
    "sg:city":"Miami",
    "sg:classifiers":[
        {
            "category":"Banks & Credit Unions",
            "subcategory":"Atm",
            "type":"Services"
        }
    ],
    "sg:phone":"+1 305 403 1534",
    "sg:postcode":"33133",
    "sg:province":"FL",
    "sg:tags":[
        "location"
    ],
    "wof:name":"D & B Atm Services Inc",
    "wof:placetype":"venue"
},
  "geometry": {"coordinates":[-80.250061,25.73542],"type":"Point"}
}