{
  "type": "Feature",
  "properties": {
    "iso:country":"US",
    "sg:address":"370 Center Pointe Cir Ste 1154",
    "sg:city":"Altamonte Springs",
    "sg:classifiers":[
        {
            "category":"Organizations",
            "subcategory":"Non-profit Organization",
            "type":"Services"
        }
    ],
    "sg:phone":"+1 407 774 2166",
    "sg:postcode":"32701",
    "sg:province":"FL",
    "sg:tags":[
        "service/non-profit",
        "community"
    ],
    "wof:name":"Juvenile Diabetes Research Foundation",
    "wof:placetype":"venue"
},
  "geometry": {"coordinates":[-81.384777,28.667834],"type":"Point"}
}