{
  "type": "Feature",
  "properties": {
    "iso:country":"US",
    "sg:address":"1665 Chaucer Rd",
    "sg:city":"Titusville",
    "sg:classifiers":[
        {
            "category":"Building & Trades",
            "subcategory":"Cleaning & Sanitation",
            "type":"Services"
        }
    ],
    "sg:phone":"+1 321 403 2717",
    "sg:postcode":"32780",
    "sg:province":"FL",
    "sg:tags":[
        "maintenance",
        "contractor"
    ],
    "wof:name":"Gregory Trew Exterior Inc",
    "wof:placetype":"venue"
},
  "geometry": {"coordinates":[-80.82136,28.558554],"type":"Point"}
}