{
  "type": "Feature",
  "properties": {
    "addr:full":"2481 Croton Rd Melbourne FL 32935",
    "addr:housenumber":"2481",
    "addr:postcode":"32935",
    "addr:street":"Croton Rd",
    "iso:country":"US",
    "sg:address":"2481 Croton Rd",
    "sg:city":"Melbourne",
    "sg:classifiers":[
        {
            "category":"Banks & Credit Unions",
            "subcategory":"Bank",
            "type":"Services"
        }
    ],
    "sg:phone":"+1 321 984 5315",
    "sg:postcode":"32935",
    "sg:province":"FL",
    "sg:tags":[
        "state",
        "commercial"
    ],
    "wof:name":"Wachovia Bank National Assn",
    "wof:placetype":"venue"
},
  "geometry": {"coordinates":[-80.655081,28.148554],"type":"Point"}
}