{
  "type": "Feature",
  "properties": {
    "iso:country":"US",
    "sg:address":"3476 Palm Beach Blvd",
    "sg:city":"Fort Myers",
    "sg:classifiers":[
        {
            "category":"Personal",
            "subcategory":"Beauty Salon",
            "type":"Services"
        }
    ],
    "sg:phone":"+1 239 226 4321",
    "sg:postcode":"33916",
    "sg:province":"FL",
    "wof:name":"Chispas",
    "wof:placetype":"venue"
},
  "geometry": {"coordinates":[-81.840732,26.660652],"type":"Point"}
}