{
  "type": "Feature",
  "properties": {
    "iso:country":"US",
    "sg:address":"2002 Lantana Rd",
    "sg:city":"Lantana",
    "sg:classifiers":[
        {
            "category":"Professional",
            "subcategory":"Detective & Security Services",
            "type":"Services"
        },
        {
            "category":"Building & Trades",
            "subcategory":"Locksmith",
            "type":"Services"
        },
        {
            "category":"Retail",
            "subcategory":"Auto Repair",
            "type":"Services"
        }
    ],
    "sg:phone":"+1 561 491 5422",
    "sg:postcode":"33462",
    "sg:province":"FL",
    "sg:tags":[
        "control",
        "monitoring",
        "lock",
        "system",
        "access",
        "road",
        "service-automotive"
    ],
    "sg:website":"http://your-keys.net??",
    "wof:name":"Locksmith Services Lantana FL",
    "wof:placetype":"venue"
},
  "geometry": {"coordinates":[-80.073691,26.58733],"type":"Point"}
}