{
  "type": "Feature",
  "properties": {
    "addr:full":"425 S Olive Ave West Palm Beach FL 33401",
    "addr:housenumber":"425",
    "addr:postcode":"33401",
    "addr:street":"S Olive Ave",
    "iso:country":"US",
    "sg:address":"425 S Olive Ave",
    "sg:city":"West Palm Beach",
    "sg:classifiers":[
        {
            "category":"Professional",
            "subcategory":"Business Services",
            "type":"Services"
        }
    ],
    "sg:phone":"+1 561 832 8999",
    "sg:postcode":"33401",
    "sg:province":"FL",
    "sg:tags":[
        "interior",
        "decorating"
    ],
    "wof:name":"Plumber Richard Design",
    "wof:placetype":"venue"
},
  "geometry": {"coordinates":[-80.052072,26.709573],"type":"Point"}
}