{
  "type": "Feature",
  "properties": {
    "addr:full":"106 Whitaker Rd Lutz FL 33549",
    "addr:housenumber":"106",
    "addr:postcode":"33549",
    "addr:street":"Whitaker Rd",
    "iso:country":"US",
    "sg:address":"106 Whitaker Rd",
    "sg:city":"Lutz",
    "sg:classifiers":[
        {
            "category":"Building & Trades",
            "subcategory":"Construction",
            "type":"Services"
        }
    ],
    "sg:phone":"+1 813 909 4432",
    "sg:postcode":"33549",
    "sg:province":"FL",
    "sg:tags":[
        "general",
        "contractor"
    ],
    "wof:name":"APCO Building Systems",
    "wof:placetype":"venue"
},
  "geometry": {"coordinates":[-82.458446,28.116584],"type":"Point"}
}