{
  "type": "Feature",
  "properties": {
    "iso:country":"US",
    "sg:address":"1415 E Idlewild Ave",
    "sg:city":"Tampa",
    "sg:classifiers":[
        {
            "category":"Banks & Credit Unions",
            "subcategory":"Financial Services",
            "type":"Services"
        }
    ],
    "sg:phone":"+1 813 238 2865",
    "sg:postcode":"33604",
    "sg:province":"FL",
    "sg:tags":[
        "trust",
        "management"
    ],
    "wof:name":"Fred D Steele Trustee",
    "wof:placetype":"venue"
},
  "geometry": {"coordinates":[-82.443219,28.001428],"type":"Point"}
}