{
  "type": "Feature",
  "properties": {
    "iso:country":"US",
    "sg:address":"400 N Hiatus Rd",
    "sg:city":"Hollywood",
    "sg:classifiers":[
        {
            "category":"Health Services",
            "subcategory":"Doctor",
            "type":"Services"
        }
    ],
    "sg:phone":"+1 954 442 3434",
    "sg:postcode":"33026",
    "sg:province":"FL",
    "sg:tags":[
        "medical",
        "osteopathy"
    ],
    "wof:name":"G Shawn Leslie Do",
    "wof:placetype":"venue"
},
  "geometry": {"coordinates":[-80.29644,26.01093],"type":"Point"}
}