{
  "type": "Feature",
  "properties": {
    "iso:country":"US",
    "sg:address":"2215 SW 60th Way",
    "sg:city":"Miramar",
    "sg:classifiers":[
        {
            "category":"Utilities",
            "subcategory":"Electric",
            "type":"Services"
        }
    ],
    "sg:phone":"+1 954 963 4834",
    "sg:postcode":"33023",
    "sg:province":"FL",
    "sg:tags":[
        "equipment",
        "supplies-repair",
        "electronic",
        "equipment-repair"
    ],
    "wof:name":"Alan Mincher",
    "wof:placetype":"venue"
},
  "geometry": {"coordinates":[-80.20852600000001,25.990606],"type":"Point"}
}