{
  "type": "Feature",
  "properties": {
    "addr:full":"3740 Abby Ln Jacksonville FL 32207",
    "addr:housenumber":"3740",
    "addr:postcode":"32207",
    "addr:street":"Abby Ln",
    "iso:country":"US",
    "sg:address":"3740 Abby Ln",
    "sg:city":"Jacksonville",
    "sg:classifiers":[
        {
            "category":"Building & Trades",
            "subcategory":"Landscaping Services",
            "type":"Services"
        }
    ],
    "sg:phone":"+1 904 396 0889",
    "sg:postcode":"32207",
    "sg:province":"FL",
    "wof:name":"Power Lawn Maintenance",
    "wof:placetype":"venue"
},
  "geometry": {"coordinates":[-81.62718700000001,30.287466],"type":"Point"}
}