{
  "type": "Feature",
  "properties": {
    "addr:full":"2829 Bird Ave Miami FL 33133",
    "addr:housenumber":"2829",
    "addr:postcode":"33133",
    "addr:street":"Bird Ave",
    "iso:country":"US",
    "sg:address":"2829 Bird Ave",
    "sg:city":"Miami",
    "sg:classifiers":[
        {
            "category":"Recreation",
            "subcategory":"Boat Charter",
            "type":"Entertainment"
        }
    ],
    "sg:phone":"+1 305 772 4221",
    "sg:postcode":"33133",
    "sg:province":"FL",
    "sg:tags":[
        "boat-rental"
    ],
    "wof:name":"Sailboat Charters",
    "wof:placetype":"venue"
},
  "geometry": {"coordinates":[-80.238986,25.735494],"type":"Point"}
}