{
  "type": "Feature",
  "properties": {
    "iso:country":"US",
    "sg:address":"2400 Capital Cir NE",
    "sg:city":"Tallahassee",
    "sg:classifiers":[
        {
            "category":"Retail",
            "subcategory":"Auto Repair",
            "type":"Services"
        }
    ],
    "sg:phone":"+1 850 386 8473",
    "sg:postcode":"32308",
    "sg:province":"FL",
    "sg:tags":[
        "tire"
    ],
    "sg:website":"http://www.goodyear.com",
    "wof:name":"Mc Gee Tire Stores Inc",
    "wof:placetype":"venue"
},
  "geometry": {"coordinates":[-84.237244,30.484949],"type":"Point"}
}