{
  "type": "Feature",
  "properties": {
    "iso:country":"US",
    "sg:address":"614 Old Hwy 50 W",
    "sg:city":"Clermont",
    "sg:classifiers":[
        {
            "category":"Professional",
            "subcategory":"Business Services",
            "type":"Services"
        }
    ],
    "sg:phone":"+1 352 243 0508",
    "sg:postcode":"34711",
    "sg:province":"FL",
    "sg:tags":[
        "interior",
        "design"
    ],
    "wof:name":"Rey Hernandez Interior Design",
    "wof:placetype":"venue"
},
  "geometry": {"coordinates":[-81.698336,28.565015],"type":"Point"}
}