{
  "type": "Feature",
  "properties": {
    "iso:country":"US",
    "sg:address":"5 Maple Ave",
    "sg:city":"Shalimar",
    "sg:classifiers":[
        {
            "category":"Building & Trades",
            "subcategory":"Landscaping Services",
            "type":"Services"
        }
    ],
    "sg:phone":"+1 850 609 1001",
    "sg:postcode":"32579",
    "sg:province":"FL",
    "wof:name":"Greencut",
    "wof:placetype":"venue"
},
  "geometry": {"coordinates":[-86.58313,30.457599],"type":"Point"}
}