{
  "type": "Feature",
  "properties": {
    "addr:full":"261 Goolsby Blvd Deerfield Beach FL 33442",
    "addr:housenumber":"261",
    "addr:postcode":"33442",
    "addr:street":"Goolsby Blvd",
    "iso:country":"US",
    "sg:address":"261 Goolsby Blvd",
    "sg:city":"Deerfield Beach",
    "sg:classifiers":[
        {
            "category":"Building & Trades",
            "subcategory":"Electrical",
            "type":"Services"
        }
    ],
    "sg:phone":"+1 954 725 3550",
    "sg:postcode":"33442",
    "sg:province":"FL",
    "sg:tags":[
        "electrical",
        "contractor"
    ],
    "wof:name":"Jme Electric Inc",
    "wof:placetype":"venue"
},
  "geometry": {"coordinates":[-80.126015,26.31311],"type":"Point"}
}