{
  "type": "Feature",
  "properties": {
    "addr:full":"10008 W Oakland Park Blvd Sunrise FL 33351",
    "addr:housenumber":"10008",
    "addr:postcode":"33351",
    "addr:street":"W Oakland Park Blvd",
    "iso:country":"US",
    "sg:address":"10008 W Oakland Park Blvd",
    "sg:city":"Sunrise",
    "sg:classifiers":[
        {
            "category":"Retail",
            "subcategory":"Repair Shop",
            "type":"Services"
        }
    ],
    "sg:phone":"+1 954 446 7307",
    "sg:postcode":"33351",
    "sg:province":"FL",
    "sg:tags":[
        "lock",
        "locksmith"
    ],
    "wof:name":"All Day Emergency Locksmith",
    "wof:placetype":"venue"
},
  "geometry": {"coordinates":[-80.284712,26.169758],"type":"Point"}
}