{
  "type": "Feature",
  "properties": {
    "addr:full":"1204 60th Ave W Bradenton FL 34207",
    "addr:housenumber":"1204",
    "addr:postcode":"34207",
    "addr:street":"60Th Ave W",
    "iso:country":"US",
    "sg:address":"1204 60th Ave W",
    "sg:city":"Bradenton",
    "sg:classifiers":[
        {
            "category":"Building & Trades",
            "subcategory":"Electrical",
            "type":"Services"
        }
    ],
    "sg:phone":"+1 941 758 3113",
    "sg:postcode":"34207",
    "sg:province":"FL",
    "sg:tags":[
        "industrial",
        "electrician",
        "contractors-commercial",
        "electric"
    ],
    "wof:name":"Benshoff Electric",
    "wof:placetype":"venue"
},
  "geometry": {"coordinates":[-82.57376499999999,27.43486],"type":"Point"}
}