{
  "type": "Feature",
  "properties": {
    "iso:country":"US",
    "sg:address":"1300 Marsh Landing Pkwy",
    "sg:city":"Jacksonville Beach",
    "sg:classifiers":[
        {
            "category":"Insurance",
            "subcategory":"Insurance Agent",
            "type":"Services"
        }
    ],
    "sg:phone":"+1 904 241 1164",
    "sg:postcode":"32250",
    "sg:province":"FL",
    "wof:name":"American First Coast Title Svc",
    "wof:placetype":"venue"
},
  "geometry": {"coordinates":[-81.39830000000001,30.255801],"type":"Point"}
}