{
  "type": "Feature",
  "properties": {
    "addr:full":"1920 Thomasville Rd Tallahassee FL 32303",
    "addr:housenumber":"1920",
    "addr:postcode":"32303",
    "addr:street":"Thomasville Rd",
    "iso:country":"US",
    "sg:address":"1920 Thomasville Rd",
    "sg:city":"Tallahassee",
    "sg:classifiers":[
        {
            "category":"Government",
            "subcategory":"Office",
            "type":"Public Place"
        }
    ],
    "sg:phone":"+1 850 577 4260",
    "sg:postcode":"32303",
    "sg:province":"FL",
    "sg:website":"www.clerk.leon.fl.us",
    "wof:name":"Leon Co Small Claims & Civil",
    "wof:placetype":"venue"
},
  "geometry": {"coordinates":[-84.26960699999999,30.465191],"type":"Point"}
}