{
  "type": "Feature",
  "properties": {
    "iso:country":"US",
    "sg:address":"6451 NW Co Rd 336",
    "sg:city":"Chiefland",
    "sg:classifiers":[
        {
            "category":"Retail",
            "subcategory":"Photofinishing",
            "type":"Services"
        }
    ],
    "sg:phone":"+1 352 490 8800",
    "sg:postcode":"32626",
    "sg:province":"FL",
    "sg:tags":[
        "laboratory"
    ],
    "wof:name":"Dave Eicher Photography",
    "wof:placetype":"venue"
},
  "geometry": {"coordinates":[-82.88871399999999,29.365661],"type":"Point"}
}