{
  "type": "Feature",
  "properties": {
    "addr:full":"6740 Hollywood Blvd Hollywood FL 33024",
    "addr:housenumber":"6740",
    "addr:postcode":"33024",
    "addr:street":"Hollywood Blvd",
    "iso:country":"US",
    "sg:address":"6740 Hollywood Blvd",
    "sg:city":"Hollywood",
    "sg:classifiers":[
        {
            "category":"Retail",
            "subcategory":"Auto Repair",
            "type":"Services"
        }
    ],
    "sg:phone":"+1 954 981 5500",
    "sg:postcode":"33024",
    "sg:province":"FL",
    "sg:tags":[
        "automotive"
    ],
    "wof:name":"Boulevard Radiator Hospital",
    "wof:placetype":"venue"
},
  "geometry": {"coordinates":[-80.22144299999999,26.009799],"type":"Point"}
}