{
  "type": "Feature",
  "properties": {
    "addr:full":"1378 W North Blvd Leesburg FL 34748",
    "addr:housenumber":"1378",
    "addr:postcode":"34748",
    "addr:street":"W North Blvd",
    "iso:country":"US",
    "sg:address":"1378 W North Blvd",
    "sg:city":"Leesburg",
    "sg:classifiers":[
        {
            "category":"Shopping",
            "subcategory":"Jewelry",
            "type":"Retail Goods"
        },
        {
            "category":"Shopping",
            "subcategory":"Pawn Shop",
            "type":"Retail Goods"
        }
    ],
    "sg:phone":"+1 352 323 8344",
    "sg:postcode":"34748",
    "sg:province":"FL",
    "sg:tags":[
        "precious",
        "pawnbroker",
        "semi-precious",
        "stone"
    ],
    "wof:name":"Value Pawn & Jewelry",
    "wof:placetype":"venue"
},
  "geometry": {"coordinates":[-81.886127,28.825504],"type":"Point"}
}