{
  "type": "Feature",
  "properties": {
    "addr:full":"381 Regatta St Marco Island FL 34145",
    "addr:housenumber":"381",
    "addr:postcode":"34145",
    "addr:street":"Regatta St",
    "iso:country":"US",
    "sg:address":"381 Regatta St",
    "sg:city":"Marco Island",
    "sg:classifiers":[
        {
            "category":"Building & Trades",
            "subcategory":"Landscaping Services",
            "type":"Services"
        }
    ],
    "sg:phone":"+1 239 389 7461",
    "sg:postcode":"34145",
    "sg:province":"FL",
    "wof:name":"Sal Centamores Lawncare",
    "wof:placetype":"venue"
},
  "geometry": {"coordinates":[-81.710469,25.929191],"type":"Point"}
}