{
  "type": "Feature",
  "properties": {
    "iso:country":"US",
    "sg:address":"711 NE 45th Ct",
    "sg:city":"Pompano Beach",
    "sg:classifiers":[
        {
            "category":"Wholesale",
            "subcategory":"Auto Parts",
            "type":"Manufacturing & Wholesale Goods"
        }
    ],
    "sg:phone":"+1 954 941 7070",
    "sg:postcode":"33064",
    "sg:province":"FL",
    "sg:tags":[
        "supply"
    ],
    "wof:name":"Jims Tire Supply",
    "wof:placetype":"venue"
},
  "geometry": {"coordinates":[-80.11479,26.286633],"type":"Point"}
}