{
  "type": "Feature",
  "properties": {
    "addr:full":"219 Clarke Ave Palm Beach FL 33480",
    "addr:housenumber":"219",
    "addr:postcode":"33480",
    "addr:street":"Clarke Ave",
    "iso:country":"US",
    "sg:address":"219 Clarke Ave",
    "sg:city":"Palm Beach",
    "sg:classifiers":[
        {
            "category":"Professional",
            "subcategory":"Management & Consulting",
            "type":"Services"
        }
    ],
    "sg:phone":"+1 561 833 0476",
    "sg:postcode":"33480",
    "sg:province":"FL",
    "sg:tags":[
        "business"
    ],
    "wof:name":"Gamma Machinery Inc",
    "wof:placetype":"venue"
},
  "geometry": {"coordinates":[-80.03917300000001,26.709721],"type":"Point"}
}