{
  "type": "Feature",
  "properties": {
    "iso:country":"US",
    "sg:address":"600 30th Ave W",
    "sg:city":"Bradenton",
    "sg:classifiers":[
        {
            "category":"Real Estate",
            "subcategory":"Real Estate Operator",
            "type":"Services"
        }
    ],
    "sg:phone":"+1 941 747 5590",
    "sg:postcode":"34205",
    "sg:province":"FL",
    "sg:tags":[
        "condominium"
    ],
    "wof:name":"Wood Park Owners Assn Inc",
    "wof:placetype":"venue"
},
  "geometry": {"coordinates":[-82.567554,27.473508],"type":"Point"}
}