{
  "type": "Feature",
  "properties": {
    "iso:country":"US",
    "sg:address":"2216 W 80th St",
    "sg:city":"Hialeah",
    "sg:classifiers":[
        {
            "category":"Wholesale",
            "subcategory":"Construction Materials",
            "type":"Manufacturing & Wholesale Goods"
        }
    ],
    "sg:phone":"+1 305 827 1935",
    "sg:postcode":"33016",
    "sg:province":"FL",
    "sg:tags":[
        "granite"
    ],
    "wof:name":"R R World Natural Stone",
    "wof:placetype":"venue"
},
  "geometry": {"coordinates":[-80.329177,25.895229],"type":"Point"}
}