{
  "type": "Feature",
  "properties": {
    "iso:country":"US",
    "sg:address":"9300 86th Ave",
    "sg:city":"Largo",
    "sg:classifiers":[
        {
            "category":"Building & Trades",
            "subcategory":"Construction",
            "type":"Services"
        }
    ],
    "sg:phone":"+1 727 392 6921",
    "sg:postcode":"33777",
    "sg:province":"FL",
    "sg:tags":[
        "general",
        "contractor"
    ],
    "wof:name":"Lincoln Construction Inc",
    "wof:placetype":"venue"
},
  "geometry": {"coordinates":[-82.76759699999999,27.850463],"type":"Point"}
}