{
  "type": "Feature",
  "properties": {
    "addr:full":"3241 N Federal Hwy Pompano Beach FL 33064",
    "addr:housenumber":"3241",
    "addr:postcode":"33064",
    "addr:street":"N Federal Hwy",
    "iso:country":"US",
    "sg:address":"3241 N Federal Hwy",
    "sg:city":"Pompano Beach",
    "sg:classifiers":[
        {
            "category":"Wholesale",
            "subcategory":"Electrical",
            "type":"Manufacturing & Wholesale Goods"
        }
    ],
    "sg:phone":"+1 954 788 6618",
    "sg:postcode":"33064",
    "sg:province":"FL",
    "sg:tags":[
        "equipment"
    ],
    "wof:name":"Betech Inc",
    "wof:placetype":"venue"
},
  "geometry": {"coordinates":[-80.098206,26.271018],"type":"Point"}
}