{
  "type": "Feature",
  "properties": {
    "iso:country":"US",
    "sg:address":"31 Cunningham Rd",
    "sg:city":"De Bary",
    "sg:classifiers":[
        {
            "category":"Manufacturing",
            "subcategory":"Toys & Sporting Goods",
            "type":"Manufacturing & Wholesale Goods"
        }
    ],
    "sg:phone":"+1 386 668 5516",
    "sg:postcode":"32713",
    "sg:province":"FL",
    "sg:tags":[
        "mfg"
    ],
    "wof:name":"Florida Backcountry Charter",
    "wof:placetype":"venue"
},
  "geometry": {"coordinates":[-81.283822,28.887991],"type":"Point"}
}