{
  "type": "Feature",
  "properties": {
    "iso:country":"US",
    "sg:address":"11310 Distribution Ave W",
    "sg:city":"Jacksonville",
    "sg:classifiers":[
        {
            "category":"Manufacturing",
            "subcategory":"Tools & Machinery",
            "type":"Manufacturing & Wholesale Goods"
        }
    ],
    "sg:phone":"+1 904 260 4566",
    "sg:postcode":"32256",
    "sg:province":"FL",
    "sg:tags":[
        "water",
        "equipment",
        "works",
        "supply"
    ],
    "sg:website":"www.nationalwaterworks.com",
    "wof:name":"National Waterworks",
    "wof:placetype":"venue"
},
  "geometry": {"coordinates":[-81.53407900000001,30.163801],"type":"Point"}
}