{
  "type": "Feature",
  "properties": {
    "addr:full":"730 Ridgewood Ave Holly Hill FL 32117",
    "addr:housenumber":"730",
    "addr:postcode":"32117",
    "addr:street":"Ridgewood Ave",
    "iso:country":"US",
    "sg:address":"730 Ridgewood Ave",
    "sg:city":"Holly Hill",
    "sg:classifiers":[
        {
            "category":"Autos & Motor Vehicles",
            "subcategory":"Boat Sales",
            "type":"Retail Goods"
        }
    ],
    "sg:phone":"+1 386 255 7790",
    "sg:postcode":"32117",
    "sg:province":"FL",
    "sg:tags":[
        "dealer",
        "sales"
    ],
    "sg:website":"www.bluewaterboat.com",
    "wof:name":"Blue Water Boats",
    "wof:placetype":"venue"
},
  "geometry": {"coordinates":[-81.03790499999999,29.238732],"type":"Point"}
}