{
  "type": "Feature",
  "properties": {
    "iso:country":"US",
    "sg:address":"888 SE 3rd Ave",
    "sg:city":"Fort Lauderdale",
    "sg:classifiers":[
        {
            "category":"Professional",
            "subcategory":"Accounting & Tax Preparation",
            "type":"Services"
        }
    ],
    "sg:phone":"+1 954 524 3000",
    "sg:postcode":"33316",
    "sg:province":"FL",
    "sg:tags":[
        "accountant"
    ],
    "wof:name":"Richard C Jarchow Cpas",
    "wof:placetype":"venue"
},
  "geometry": {"coordinates":[-80.14009299999999,26.112088],"type":"Point"}
}