{
  "type": "Feature",
  "properties": {
    "iso:country":"US",
    "sg:address":"3340 NW 73rd St",
    "sg:city":"Miami",
    "sg:phone":"+1 305 691 2213",
    "sg:postcode":"33147",
    "sg:province":"FL",
    "sg:tags":[
        "material",
        "fixture",
        "display"
    ],
    "sg:website":"www.rpcdisplay.com",
    "wof:name":"RPC Display",
    "wof:placetype":"venue"
},
  "geometry": {"coordinates":[-80.253539,25.840031],"type":"Point"}
}