{
  "type": "Feature",
  "properties": {
    "iso:country":"US",
    "sg:address":"12398 SW 128th St Ste 112",
    "sg:city":"Miami",
    "sg:classifiers":[
        {
            "category":"Retail",
            "subcategory":"Auto Repair",
            "type":"Services"
        }
    ],
    "sg:phone":"+1 305 378 1681",
    "sg:postcode":"33186",
    "sg:province":"FL",
    "sg:tags":[
        "repairing",
        "supply",
        "service-equipment",
        "automobile"
    ],
    "wof:name":"Kendal Car Repair Corp",
    "wof:placetype":"venue"
},
  "geometry": {"coordinates":[-80.395032,25.649038],"type":"Point"}
}