{
  "type": "Feature",
  "properties": {
    "iso:country":"US",
    "sg:address":"1620 Main St",
    "sg:city":"Sarasota",
    "sg:classifiers":[
        {
            "category":"Professional",
            "subcategory":"Advertising",
            "type":"Services"
        }
    ],
    "sg:phone":"+1 941 954 1467",
    "sg:postcode":"34236",
    "sg:province":"FL",
    "sg:tags":[
        "commercial",
        "agency",
        "design"
    ],
    "wof:name":"Rudisill/Mcsweeney Inc",
    "wof:placetype":"venue"
},
  "geometry": {"coordinates":[-82.53796800000001,27.336385],"type":"Point"}
}