{
  "type": "Feature",
  "properties": {
    "iso:country":"US",
    "sg:address":"1942 Passaic Ave",
    "sg:city":"Fort Myers",
    "sg:classifiers":[
        {
            "category":"Health Services",
            "subcategory":"Hospital",
            "type":"Services"
        }
    ],
    "sg:phone":"+1 239 939 3156",
    "sg:postcode":"33901",
    "sg:province":"FL",
    "sg:tags":[
        "mental"
    ],
    "wof:name":"Lee Mental Health Ctr",
    "wof:placetype":"venue"
},
  "geometry": {"coordinates":[-81.872992,26.616958],"type":"Point"}
}