{
  "type": "Feature",
  "properties": {
    "iso:country":"US",
    "sg:address":"13401 Dixie Hwy",
    "sg:city":"Miami",
    "sg:classifiers":[
        {
            "category":"Autos & Motor Vehicles",
            "subcategory":"Automobile Sales",
            "type":"Retail Goods"
        }
    ],
    "sg:phone":"+1 305 238 4040",
    "sg:postcode":"33156",
    "sg:province":"FL",
    "sg:tags":[
        "body",
        "repair",
        "general"
    ],
    "wof:name":"Hallett G M C Truck",
    "wof:placetype":"venue"
},
  "geometry": {"coordinates":[-80.33411099999999,25.64385],"type":"Point"}
}