{
  "type": "Feature",
  "properties": {
    "iso:country":"US",
    "sg:address":"1699 Hobbs Rd",
    "sg:city":"Auburndale",
    "sg:classifiers":[
        {
            "category":"Freight",
            "type":"Transportation"
        }
    ],
    "sg:phone":"+1 863 965 2949",
    "sg:postcode":"33823",
    "sg:province":"FL",
    "sg:tags":[
        "document",
        "storage"
    ],
    "wof:name":"Iron Mountain Information MGT",
    "wof:placetype":"venue"
},
  "geometry": {"coordinates":[-81.780243,28.045759],"type":"Point"}
}