{
  "type": "Feature",
  "properties": {
    "addr:full":"326 Eglin Pkwy Fort Walton Bch FL 32547",
    "addr:housenumber":"326",
    "addr:postcode":"32547",
    "addr:street":"Eglin Pkwy Fort",
    "iso:country":"US",
    "sg:address":"326 Eglin Pkwy",
    "sg:city":"Fort Walton Bch",
    "sg:classifiers":[
        {
            "category":"Food & Beverages",
            "subcategory":"Groceries & Convenience Stores",
            "type":"Retail Goods"
        }
    ],
    "sg:phone":"+1 850 864 4888",
    "sg:postcode":"32547",
    "sg:province":"FL",
    "sg:tags":[
        "grocer"
    ],
    "wof:name":"Hong Kong Food Mart",
    "wof:placetype":"venue"
},
  "geometry": {"coordinates":[-86.602334,30.436016],"type":"Point"}
}