{
  "type": "Feature",
  "properties": {
    "iso:country":"US",
    "sg:address":"562 N Ridgewood Ave",
    "sg:city":"Daytona Beach",
    "sg:classifiers":[
        {
            "category":"Wholesale",
            "subcategory":"Office Equipment",
            "type":"Manufacturing & Wholesale Goods"
        },
        {
            "category":"Retail",
            "subcategory":"Repair Shop",
            "type":"Services"
        }
    ],
    "sg:phone":"+1 386 238 3536",
    "sg:postcode":"32114",
    "sg:province":"FL",
    "sg:tags":[
        "machine",
        "duplicating",
        "copying"
    ],
    "wof:name":"Coastal Office Machines & Spls",
    "wof:placetype":"venue"
},
  "geometry": {"coordinates":[-81.028203,29.220801],"type":"Point"}
}