{
  "type": "Feature",
  "properties": {
    "iso:country":"US",
    "sg:address":"832 Stanton Dr",
    "sg:city":"Weston",
    "sg:classifiers":[
        {
            "category":"Communications",
            "subcategory":"Radio Station",
            "type":"Services"
        }
    ],
    "sg:phone":"+1 954 384 7940",
    "sg:postcode":"33326",
    "sg:province":"FL",
    "sg:tags":[
        "broadcast"
    ],
    "wof:name":"Am Dugre & Assoc Corp",
    "wof:placetype":"venue"
},
  "geometry": {"coordinates":[-80.39755,26.130994],"type":"Point"}
}