{
  "type": "Feature",
  "properties": {
    "addr:full":"2451 N University Dr Fort Lauderdale FL 33322",
    "addr:housenumber":"2451",
    "addr:postcode":"33322",
    "addr:street":"N University Dr",
    "iso:country":"US",
    "sg:address":"2451 N University Dr",
    "sg:city":"Fort Lauderdale",
    "sg:classifiers":[
        {
            "category":"Restaurant",
            "type":"Food & Drink"
        }
    ],
    "sg:menulink":"http://www.allmenus.com/fl/plantation/207589-taco-bell/menu/",
    "sg:phone":"+1 954 749 2400",
    "sg:postcode":"33322",
    "sg:province":"FL",
    "sg:tags":[
        "mexican"
    ],
    "wof:name":"Taco Bell",
    "wof:placetype":"venue"
},
  "geometry": {"coordinates":[-80.25727500000001,26.155154],"type":"Point"}
}