{
  "type": "Feature",
  "properties": {
    "iso:country":"US",
    "sg:address":"17777 Bali Blvd",
    "sg:city":"Winter Garden",
    "sg:classifiers":[
        {
            "category":"Shopping",
            "subcategory":"Gifts & Souvenirs",
            "type":"Retail Goods"
        }
    ],
    "sg:phone":"+1 407 239 5022",
    "sg:postcode":"34787",
    "sg:province":"FL",
    "sg:tags":[
        "shop"
    ],
    "wof:name":"Glazer Gifts",
    "wof:placetype":"venue"
},
  "geometry": {"coordinates":[-81.655704,28.348261],"type":"Point"}
}