{
  "type": "Feature",
  "properties": {
    "addr:full":"6967 Beardsley St Englewood FL 34224",
    "addr:housenumber":"6967",
    "addr:postcode":"34224",
    "addr:street":"Beardsley St",
    "iso:country":"US",
    "sg:address":"6967 Beardsley St",
    "sg:city":"Englewood",
    "sg:classifiers":[
        {
            "category":"Building & Trades",
            "subcategory":"Construction",
            "type":"Services"
        }
    ],
    "sg:phone":"+1 941 474 5427",
    "sg:postcode":"34224",
    "sg:province":"FL",
    "sg:tags":[
        "house"
    ],
    "wof:name":"Creative Homes & Remodeling",
    "wof:placetype":"venue"
},
  "geometry": {"coordinates":[-82.28734,26.932151],"type":"Point"}
}