{
  "type": "Feature",
  "properties": {
    "iso:country":"US",
    "sg:address":"5542 Palmetto St",
    "sg:city":"Fort Myers Beach",
    "sg:classifiers":[
        {
            "category":"Professional",
            "type":"Services"
        }
    ],
    "sg:phone":"+1 239 765 5406",
    "sg:postcode":"33931",
    "sg:province":"FL",
    "wof:name":"Maynard Inc",
    "wof:placetype":"venue"
},
  "geometry": {"coordinates":[-81.91363699999999,26.431788],"type":"Point"}
}