{
  "type": "Feature",
  "properties": {
    "addr:full":"2410 Campbell Rd Clearwater FL 33765",
    "addr:housenumber":"2410",
    "addr:postcode":"33765",
    "addr:street":"Campbell Rd",
    "iso:country":"US",
    "sg:address":"2410 Campbell Rd",
    "sg:city":"Clearwater",
    "sg:classifiers":[
        {
            "category":"Banks & Credit Unions",
            "subcategory":"Investment Brokerage",
            "type":"Services"
        }
    ],
    "sg:phone":"+1 727 712 3774",
    "sg:postcode":"33765",
    "sg:province":"FL",
    "wof:name":"Emory Partners",
    "wof:placetype":"venue"
},
  "geometry": {"coordinates":[-82.73774299999999,27.984541],"type":"Point"}
}