{
  "type": "Feature",
  "properties": {
    "addr:full":"225 N Cswy New Smyrna Beach FL 32169",
    "addr:housenumber":"225",
    "addr:postcode":"32169",
    "addr:street":"N Cswy",
    "iso:country":"US",
    "sg:address":"225 N Cswy",
    "sg:city":"New Smyrna Beach",
    "sg:classifiers":[
        {
            "category":"Health Services",
            "subcategory":"Chiropractor",
            "type":"Services"
        }
    ],
    "sg:phone":"+1 386 424 9977",
    "sg:postcode":"32169",
    "sg:province":"FL",
    "wof:name":"Atlantic Wellness Center",
    "wof:placetype":"venue"
},
  "geometry": {"coordinates":[-80.91352500000001,29.034802],"type":"Point"}
}