{
  "type": "Feature",
  "properties": {
    "iso:country":"US",
    "sg:address":"14150 SW 127th St",
    "sg:city":"Miami",
    "sg:classifiers":[
        {
            "category":"Government",
            "subcategory":"Fire Station",
            "type":"Public Place"
        }
    ],
    "sg:phone":"+1 305 233 5000",
    "sg:postcode":"33186",
    "sg:province":"FL",
    "sg:tags":[
        "county",
        "protection"
    ],
    "wof:name":"Miami Dade Fire Dept Air Rescu",
    "wof:placetype":"venue"
},
  "geometry": {"coordinates":[-80.422417,25.649641],"type":"Point"}
}