{
  "type": "Feature",
  "properties": {
    "addr:full":"7320 Aloma Ave Winter Park FL 32792",
    "addr:housenumber":"7320",
    "addr:postcode":"32792",
    "addr:street":"Aloma Ave",
    "iso:country":"US",
    "sg:address":"7320 Aloma Ave",
    "sg:city":"Winter Park",
    "sg:classifiers":[
        {
            "category":"Retail",
            "subcategory":"Auto Repair",
            "type":"Services"
        }
    ],
    "sg:phone":"+1 407 678 1110",
    "sg:postcode":"32792",
    "sg:province":"FL",
    "sg:tags":[
        "repairing",
        "automobile"
    ],
    "wof:name":"Ted Hayes Auto Svc",
    "wof:placetype":"venue"
},
  "geometry": {"coordinates":[-81.29014599999999,28.608452],"type":"Point"}
}