{
  "type": "Feature",
  "properties": {
    "addr:full":"307 N Mars Ave Clearwater FL 33755",
    "addr:housenumber":"307",
    "addr:postcode":"33755",
    "addr:street":"N Mars Ave",
    "iso:country":"US",
    "sg:address":"307 N Mars Ave",
    "sg:city":"Clearwater",
    "sg:classifiers":[
        {
            "category":"Home & Garden",
            "subcategory":"Carpets & Floor Coverings",
            "type":"Retail Goods"
        }
    ],
    "sg:phone":"+1 727 532 6773",
    "sg:postcode":"33755",
    "sg:province":"FL",
    "sg:tags":[
        "dealer",
        "rug"
    ],
    "wof:name":"Ilene's Flooring",
    "wof:placetype":"venue"
},
  "geometry": {"coordinates":[-82.763914,27.969013],"type":"Point"}
}