{
  "type": "Feature",
  "properties": {
    "iso:country":"US",
    "sg:address":"7346 el Barco Rd",
    "sg:city":"Jacksonville",
    "sg:classifiers":[
        {
            "category":"Freight",
            "type":"Transportation"
        }
    ],
    "sg:phone":"+1 904 720 0290",
    "sg:postcode":"32216",
    "sg:province":"FL",
    "sg:tags":[
        "operator",
        "local",
        "trucking"
    ],
    "wof:name":"Jasmin Hadziabdic Trucking",
    "wof:placetype":"venue"
},
  "geometry": {"coordinates":[-81.58128000000001,30.29216],"type":"Point"}
}