{
  "type": "Feature",
  "properties": {
    "iso:country":"US",
    "sg:address":"6046 Harvin Rd",
    "sg:city":"Jacksonville",
    "sg:classifiers":[
        {
            "category":"Social Services",
            "subcategory":"Child Care",
            "type":"Services"
        }
    ],
    "sg:phone":"+1 904 391 1285",
    "sg:postcode":"32216",
    "sg:province":"FL",
    "sg:tags":[
        "day"
    ],
    "wof:name":"Memorial Hospital",
    "wof:placetype":"venue"
},
  "geometry": {"coordinates":[-81.600779,30.286035],"type":"Point"}
}