{
  "type": "Feature",
  "properties": {
    "addr:full":"10750 Atlantic Blvd Jacksonville FL 32225",
    "addr:housenumber":"10750",
    "addr:postcode":"32225",
    "addr:street":"Atlantic Blvd",
    "iso:country":"US",
    "sg:address":"10750 Atlantic Blvd",
    "sg:city":"Jacksonville",
    "sg:classifiers":[
        {
            "category":"Shopping",
            "subcategory":"Computers & Home Electronics",
            "type":"Retail Goods"
        }
    ],
    "sg:phone":"+1 904 641 3886",
    "sg:postcode":"32225",
    "sg:province":"FL",
    "sg:tags":[
        "equipment",
        "dealer"
    ],
    "sg:website":"www.vision-jax.com",
    "wof:name":"Vision Computers",
    "wof:placetype":"venue"
},
  "geometry": {"coordinates":[-81.521049,30.324531],"type":"Point"}
}