{
  "type": "Feature",
  "properties": {
    "iso:country":"US",
    "sg:address":"150 E Sample Rd",
    "sg:city":"Pompano Beach",
    "sg:classifiers":[
        {
            "category":"Banks & Credit Unions",
            "subcategory":"Bank",
            "type":"Services"
        }
    ],
    "sg:phone":"+1 954 942 9011",
    "sg:postcode":"33064",
    "sg:province":"FL",
    "sg:tags":[
        "banker",
        "mortgage"
    ],
    "wof:name":"Moneyone Mortgage Bankers",
    "wof:placetype":"venue"
},
  "geometry": {"coordinates":[-80.120991,26.27507],"type":"Point"}
}