{
  "type": "Feature",
  "properties": {
    "iso:country":"US",
    "sg:address":"113 S Palafox St",
    "sg:city":"Pensacola",
    "sg:classifiers":[
        {
            "category":"Health Services",
            "subcategory":"Doctor",
            "type":"Services"
        }
    ],
    "sg:phone":"+1 850 434 2060",
    "sg:postcode":"32502",
    "sg:province":"FL",
    "sg:tags":[
        "physician",
        "surgeon"
    ],
    "wof:name":"J Courtney Ray MD",
    "wof:placetype":"venue"
},
  "geometry": {"coordinates":[-87.215244,30.412725],"type":"Point"}
}