{
  "type": "Feature",
  "properties": {
    "addr:full":"2355 S Ridgewood Ave South Daytona FL 32119",
    "addr:housenumber":"2355",
    "addr:postcode":"32119",
    "addr:street":"S Ridgewood Ave South",
    "iso:country":"US",
    "sg:address":"2355 S Ridgewood Ave",
    "sg:city":"South Daytona",
    "sg:classifiers":[
        {
            "category":"Insurance",
            "subcategory":"Insurance Agent",
            "type":"Services"
        }
    ],
    "sg:phone":"+1 386 788 7200",
    "sg:postcode":"32119",
    "sg:province":"FL",
    "wof:name":"Central Insurance",
    "wof:placetype":"venue"
},
  "geometry": {"coordinates":[-80.999253,29.166685],"type":"Point"}
}