{
  "type": "Feature",
  "properties": {
    "addr:full":"1643 State Ave Daytona Beach FL 32117",
    "addr:housenumber":"1643",
    "addr:postcode":"32117",
    "addr:street":"State Ave",
    "iso:country":"US",
    "sg:address":"1643 State Ave",
    "sg:city":"Daytona Beach",
    "sg:classifiers":[
        {
            "category":"Retail",
            "subcategory":"Auto Repair",
            "type":"Services"
        }
    ],
    "sg:phone":"+1 386 672 2900",
    "sg:postcode":"32117",
    "sg:province":"FL",
    "sg:tags":[
        "automotive"
    ],
    "wof:name":"Garys Drive Line Inc",
    "wof:placetype":"venue"
},
  "geometry": {"coordinates":[-81.05069,29.258348],"type":"Point"}
}