{
  "type": "Feature",
  "properties": {
    "addr:full":"12695 W Fort Island Trl Crystal River FL 34429",
    "addr:housenumber":"12695",
    "addr:postcode":"34429",
    "addr:street":"W Fort Island Trl",
    "iso:country":"US",
    "sg:address":"12695 W Fort Island Trl",
    "sg:city":"Crystal River",
    "sg:classifiers":[
        {
            "category":"Education",
            "subcategory":"School",
            "type":"Public Place"
        }
    ],
    "sg:phone":"+1 352 795 8793",
    "sg:postcode":"34429",
    "sg:province":"FL",
    "wof:name":"Acad of Environmental Science",
    "wof:placetype":"venue"
},
  "geometry": {"coordinates":[-82.573601,28.875902],"type":"Point"}
}