{
  "type": "Feature",
  "properties": {
    "iso:country":"US",
    "sg:address":"9776 Gardens East Dr",
    "sg:city":"Palm Beach Gardens",
    "sg:classifiers":[
        {
            "category":"Travel",
            "subcategory":"Travel Agent",
            "type":"Entertainment"
        }
    ],
    "sg:phone":"+1 561 775 0065",
    "sg:postcode":"33410",
    "sg:province":"FL",
    "sg:tags":[
        "agency"
    ],
    "wof:name":"National Travel Inc",
    "wof:placetype":"venue"
},
  "geometry": {"coordinates":[-80.087023,26.826316],"type":"Point"}
}