{
  "type": "Feature",
  "properties": {
    "addr:full":"532 Andes Ave Orlando FL 32807",
    "addr:housenumber":"532",
    "addr:postcode":"32807",
    "addr:street":"Andes Ave",
    "iso:country":"US",
    "sg:address":"532 Andes Ave",
    "sg:city":"Orlando",
    "sg:classifiers":[
        {
            "category":"Building & Trades",
            "subcategory":"Construction",
            "type":"Services"
        }
    ],
    "sg:phone":"+1 407 275 9352",
    "sg:postcode":"32807",
    "sg:province":"FL",
    "sg:tags":[
        "house"
    ],
    "wof:name":"Valliers Home Service",
    "wof:placetype":"venue"
},
  "geometry": {"coordinates":[-81.319328,28.536314],"type":"Point"}
}