{
  "type": "Feature",
  "properties": {
    "iso:country":"US",
    "sg:address":"1950 SW 27th Ave",
    "sg:city":"Miami",
    "sg:classifiers":[
        {
            "category":"Health Services",
            "subcategory":"Doctor",
            "type":"Services"
        }
    ],
    "sg:phone":"+1 305 648 0011",
    "sg:postcode":"33145",
    "sg:province":"FL",
    "sg:tags":[
        "medicine",
        "internal"
    ],
    "wof:name":"Delgado Mario MD",
    "wof:placetype":"venue"
},
  "geometry": {"coordinates":[-80.23856000000001,25.753247],"type":"Point"}
}