{
  "type": "Feature",
  "properties": {
    "iso:country":"US",
    "sg:address":"4451 8th Ave S",
    "sg:city":"St Petersburg",
    "sg:classifiers":[
        {
            "category":"Wholesale",
            "subcategory":"Construction Materials",
            "type":"Manufacturing & Wholesale Goods"
        }
    ],
    "sg:phone":"+1 727 321 6000",
    "sg:postcode":"33711",
    "sg:province":"FL",
    "sg:tags":[
        "concrete",
        "product"
    ],
    "sg:website":"www.atozprecast.com",
    "wof:name":"A-Z Precast Concrete Products",
    "wof:placetype":"venue"
},
  "geometry": {"coordinates":[-82.692746,27.76182],"type":"Point"}
}