{
  "type": "Feature",
  "properties": {
    "addr:full":"11606 Columbia Park Dr E Jacksonville FL 32258",
    "addr:housenumber":"11606",
    "addr:postcode":"32258",
    "addr:street":"Columbia Park Dr E",
    "iso:country":"US",
    "sg:address":"11606 Columbia Park Dr E",
    "sg:city":"Jacksonville",
    "sg:classifiers":[
        {
            "category":"Utilities",
            "subcategory":"Refuse",
            "type":"Services"
        }
    ],
    "sg:phone":"+1 904 288 8555",
    "sg:postcode":"32258",
    "sg:province":"FL",
    "sg:tags":[
        "shredding"
    ],
    "wof:name":"Shred-It First Coast",
    "wof:placetype":"venue"
},
  "geometry": {"coordinates":[-81.53676,30.155416],"type":"Point"}
}