{
  "type": "Feature",
  "properties": {
    "iso:country":"US",
    "sg:address":"2715 Success Dr",
    "sg:city":"Odessa",
    "sg:classifiers":[
        {
            "category":"Wholesale",
            "subcategory":"Construction Materials",
            "type":"Manufacturing & Wholesale Goods"
        }
    ],
    "sg:phone":"+1 727 849 0605",
    "sg:postcode":"33556",
    "sg:province":"FL",
    "wof:name":"Bergen Materials Corporation",
    "wof:placetype":"venue"
},
  "geometry": {"coordinates":[-82.62599299999999,28.197761],"type":"Point"}
}