{
  "type": "Feature",
  "properties": {
    "addr:full":"4020 Green Blvd Naples FL 34116",
    "addr:housenumber":"4020",
    "addr:postcode":"34116",
    "addr:street":"Green Blvd",
    "iso:country":"US",
    "sg:address":"4020 Green Blvd",
    "sg:city":"Naples",
    "sg:classifiers":[
        {
            "category":"Autos & Motor Vehicles",
            "subcategory":"Auto Supplies",
            "type":"Retail Goods"
        }
    ],
    "sg:phone":"+1 239 352 0001",
    "sg:postcode":"34116",
    "sg:province":"FL",
    "sg:tags":[
        "tire"
    ],
    "wof:name":"Rick Johnson Auto & Tire",
    "wof:placetype":"venue"
},
  "geometry": {"coordinates":[-81.688485,26.199493],"type":"Point"}
}