{
  "type": "Feature",
  "properties": {
    "iso:country":"US",
    "sg:address":"1160 NW North River Dr",
    "sg:city":"Miami",
    "sg:classifiers":[
        {
            "category":"Real Estate",
            "subcategory":"Real Estate Operator",
            "type":"Services"
        }
    ],
    "sg:phone":"+1 305 324 5947",
    "sg:postcode":"33136",
    "sg:province":"FL",
    "sg:tags":[
        "building",
        "apartment"
    ],
    "wof:name":"Bermuda House Apartments",
    "wof:placetype":"venue"
},
  "geometry": {"coordinates":[-80.214082,25.782948],"type":"Point"}
}