{
  "type": "Feature",
  "properties": {
    "addr:full":"6640 Garland St Fort Myers FL 33966",
    "addr:housenumber":"6640",
    "addr:postcode":"33966",
    "addr:street":"Garland St",
    "iso:country":"US",
    "sg:address":"6640 Garland St",
    "sg:city":"Fort Myers",
    "sg:classifiers":[
        {
            "category":"Wholesale",
            "subcategory":"Construction Materials",
            "type":"Manufacturing & Wholesale Goods"
        }
    ],
    "sg:phone":"+1 239 768 6969",
    "sg:postcode":"33966",
    "sg:province":"FL",
    "sg:tags":[
        "marble"
    ],
    "wof:name":"Marble Magic",
    "wof:placetype":"venue"
},
  "geometry": {"coordinates":[-81.84398,26.584761],"type":"Point"}
}