{
  "type": "Feature",
  "properties": {
    "iso:country":"US",
    "sg:address":"409 S Miramar Ave",
    "sg:city":"Indialantic",
    "sg:classifiers":[
        {
            "category":"Travel",
            "subcategory":"Hotels & Motels",
            "type":"Entertainment"
        }
    ],
    "sg:phone":"+1 321 951 0947",
    "sg:postcode":"32903",
    "sg:province":"FL",
    "wof:name":"Monterey Motel & Apts",
    "wof:placetype":"venue"
},
  "geometry": {"coordinates":[-80.56599799999999,28.089393],"type":"Point"}
}