{
  "type": "Feature",
  "properties": {
    "iso:country":"US",
    "sg:address":"9929 Costa del Sol Blvd",
    "sg:city":"Doral",
    "sg:classifiers":[
        {
            "category":"Professional",
            "subcategory":"Management & Consulting",
            "type":"Services"
        },
        {
            "category":"Professional",
            "subcategory":"Advertising",
            "type":"Services"
        },
        {
            "category":"Professional",
            "subcategory":"Business Services",
            "type":"Services"
        }
    ],
    "sg:phone":"+1 305 597 0055",
    "sg:postcode":"33178",
    "sg:province":"FL",
    "sg:tags":[
        "publicity",
        "marketing",
        "program",
        "relation",
        "consultant",
        "counselor",
        "public"
    ],
    "sg:website":"http://www.tenbrook.us",
    "wof:name":"Tenbrook Associates",
    "wof:placetype":"venue"
},
  "geometry": {"coordinates":[-80.356796,25.80624],"type":"Point"}
}