{
  "type": "Feature",
  "properties": {
    "addr:full":"2315 S Congress Ave Palm Springs FL 33406",
    "addr:housenumber":"2315",
    "addr:postcode":"33406",
    "addr:street":"S Congress Ave",
    "iso:country":"US",
    "sg:address":"2315 S Congress Ave",
    "sg:city":"Palm Springs",
    "sg:classifiers":[
        {
            "category":"Building & Trades",
            "subcategory":"Electrical",
            "type":"Services"
        }
    ],
    "sg:phone":"+1 561 968 1601",
    "sg:postcode":"33406",
    "sg:province":"FL",
    "sg:tags":[
        "telecommunication",
        "contractor"
    ],
    "wof:name":"Digital Communication Svc Inc",
    "wof:placetype":"venue"
},
  "geometry": {"coordinates":[-80.088258,26.642253],"type":"Point"}
}