{
  "type": "Feature",
  "properties": {
    "iso:country":"US",
    "sg:address":"4967 Solimartin Dr",
    "sg:city":"Orlando",
    "sg:classifiers":[
        {
            "category":"Shopping",
            "subcategory":"Clothing, Apparel, & Fashions",
            "type":"Retail Goods"
        }
    ],
    "sg:phone":"+1 407 856 4323",
    "sg:postcode":"32837",
    "sg:province":"FL",
    "sg:tags":[
        "apparel",
        "women's"
    ],
    "wof:name":"S & R Rags",
    "wof:placetype":"venue"
},
  "geometry": {"coordinates":[-81.454002,28.3624],"type":"Point"}
}