{
  "type": "Feature",
  "properties": {
    "iso:country":"US",
    "sg:address":"114 NE 54th St",
    "sg:city":"Miami",
    "sg:classifiers":[
        {
            "category":"Restaurant",
            "type":"Food & Drink"
        }
    ],
    "sg:phone":"+1 305 751 7639",
    "sg:postcode":"33137",
    "sg:province":"FL",
    "sg:tags":[
        "caribbean",
        "eating"
    ],
    "sg:website":"www.chezlebebe.com",
    "wof:name":"Chez Le Bebe",
    "wof:placetype":"venue"
},
  "geometry": {"coordinates":[-80.193703,25.825199],"type":"Point"}
}