{
  "type": "Feature",
  "properties": {
    "addr:full":"4741 Atlantic Blvd Jacksonville FL 32207",
    "addr:housenumber":"4741",
    "addr:postcode":"32207",
    "addr:street":"Atlantic Blvd",
    "iso:country":"US",
    "sg:address":"4741 Atlantic Blvd",
    "sg:city":"Jacksonville",
    "sg:classifiers":[
        {
            "category":"Health Services",
            "subcategory":"Health Practitioner",
            "type":"Services"
        }
    ],
    "sg:phone":"+1 904 398 1918",
    "sg:postcode":"32207",
    "sg:province":"FL",
    "sg:tags":[
        "counselor",
        "mental"
    ],
    "wof:name":"Jan Gallagher Med",
    "wof:placetype":"venue"
},
  "geometry": {"coordinates":[-81.614467,30.30949],"type":"Point"}
}