{
  "type": "Feature",
  "properties": {
    "iso:country":"US",
    "sg:address":"4425 Tarkington Dr",
    "sg:city":"Land O Lakes",
    "sg:classifiers":[
        {
            "category":"Wholesale",
            "subcategory":"Scrap",
            "type":"Manufacturing & Wholesale Goods"
        }
    ],
    "sg:phone":"+1 813 996 6501",
    "sg:postcode":"34639",
    "sg:province":"FL",
    "sg:tags":[
        "material"
    ],
    "wof:name":"Scrap N Doodle",
    "wof:placetype":"venue"
},
  "geometry": {"coordinates":[-82.439064,28.22024],"type":"Point"}
}