{
  "type": "Feature",
  "properties": {
    "iso:country":"US",
    "sg:address":"601 W Division St",
    "sg:city":"Deland",
    "sg:classifiers":[
        {
            "category":"Organizations",
            "subcategory":"Religious Organization",
            "type":"Services"
        }
    ],
    "sg:phone":"+1 386 740 1159",
    "sg:postcode":"32720",
    "sg:province":"FL",
    "sg:tags":[
        "church"
    ],
    "wof:name":"Accepting Responsibility Youth",
    "wof:placetype":"venue"
},
  "geometry": {"coordinates":[-81.315646,29.019927],"type":"Point"}
}