{
  "type": "Feature",
  "properties": {
    "iso:country":"US",
    "sg:address":"14923 SW 15th St",
    "sg:city":"Pembroke Pines",
    "sg:classifiers":[
        {
            "category":"Health Services",
            "subcategory":"Health Practitioner",
            "type":"Services"
        }
    ],
    "sg:phone":"+1 954 431 6257",
    "sg:postcode":"33027",
    "sg:province":"FL",
    "sg:tags":[
        "therapist",
        "physical"
    ],
    "wof:name":"Atlantic Rehabilitation Ctr",
    "wof:placetype":"venue"
},
  "geometry": {"coordinates":[-80.34634,25.996616],"type":"Point"}
}