{
  "type": "Feature",
  "properties": {
    "addr:full":"116 S Magnolia Ave Ocala FL 34471",
    "addr:housenumber":"116",
    "addr:postcode":"34471",
    "addr:street":"S Magnolia Ave",
    "iso:country":"US",
    "sg:address":"116 S Magnolia Ave",
    "sg:city":"Ocala",
    "sg:classifiers":[
        {
            "category":"Home & Garden",
            "subcategory":"Furniture",
            "type":"Retail Goods"
        }
    ],
    "sg:phone":"+1 352 629 2336",
    "sg:postcode":"34471",
    "sg:province":"FL",
    "wof:name":"Admirals Casual Furniture",
    "wof:placetype":"venue"
},
  "geometry": {"coordinates":[-82.137034,29.184872],"type":"Point"}
}