{
  "type": "Feature",
  "properties": {
    "addr:full":"742 NW 119th St Miami FL 33168",
    "addr:housenumber":"742",
    "addr:postcode":"33168",
    "addr:street":"Nw 119Th St",
    "iso:country":"US",
    "sg:address":"742 NW 119th St",
    "sg:city":"Miami",
    "sg:classifiers":[
        {
            "category":"Personal",
            "subcategory":"Nail Salon",
            "type":"Services"
        }
    ],
    "sg:phone":"+1 305 687 1977",
    "sg:postcode":"33168",
    "sg:province":"FL",
    "wof:name":"Nails Star",
    "wof:placetype":"venue"
},
  "geometry": {"coordinates":[-80.210999,25.883801],"type":"Point"}
}