{
  "type": "Feature",
  "properties": {
    "iso:country":"US",
    "sg:address":"401 S Broadway",
    "sg:city":"Englewood",
    "sg:classifiers":[
        {
            "category":"Organizations",
            "subcategory":"Religious Organization",
            "type":"Services"
        }
    ],
    "sg:phone":"+1 941 474 3140",
    "sg:postcode":"34223",
    "sg:province":"FL",
    "sg:tags":[
        "church"
    ],
    "wof:name":"St Davids Episcopal Church",
    "wof:placetype":"venue"
},
  "geometry": {"coordinates":[-82.351022,26.95425],"type":"Point"}
}