{
  "type": "Feature",
  "properties": {
    "addr:full":"5059 Canal Dr Lake Worth FL 33463",
    "addr:housenumber":"5059",
    "addr:postcode":"33463",
    "addr:street":"Canal Dr",
    "iso:country":"US",
    "sg:address":"5059 Canal Dr",
    "sg:city":"Lake Worth",
    "sg:classifiers":[
        {
            "category":"Organizations",
            "subcategory":"Community Association",
            "type":"Services"
        }
    ],
    "sg:phone":"+1 561 969 2306",
    "sg:postcode":"33463",
    "sg:province":"FL",
    "wof:name":"Fraternity House",
    "wof:placetype":"venue"
},
  "geometry": {"coordinates":[-80.128867,26.563598],"type":"Point"}
}