{
  "type": "Feature",
  "properties": {
    "iso:country":"US",
    "sg:address":"745 SE 19th Ave",
    "sg:city":"Deerfield Beach",
    "sg:classifiers":[
        {
            "category":"Organizations",
            "subcategory":"Community Association",
            "type":"Services"
        }
    ],
    "sg:phone":"+1 954 427 0854",
    "sg:postcode":"33441",
    "sg:province":"FL",
    "sg:tags":[
        "condominium"
    ],
    "wof:name":"Penthouse South Association",
    "wof:placetype":"venue"
},
  "geometry": {"coordinates":[-80.078746,26.307947],"type":"Point"}
}