{
  "type": "Feature",
  "properties": {
    "iso:country":"US",
    "sg:address":"1116 Missouri Ave",
    "sg:city":"Lynn Haven",
    "sg:classifiers":[
        {
            "category":"Real Estate",
            "subcategory":"Architect",
            "type":"Services"
        }
    ],
    "sg:phone":"+1 850 265 6500",
    "sg:postcode":"32444",
    "sg:province":"FL",
    "sg:tags":[
        "house",
        "construction",
        "architectural"
    ],
    "wof:name":"Chester A Parker Archt & Bldr",
    "wof:placetype":"venue"
},
  "geometry": {"coordinates":[-85.659099,30.239408],"type":"Point"}
}