{
  "type": "Feature",
  "properties": {
    "addr:full":"5845 Everglades Blvd N Naples FL 34120",
    "addr:housenumber":"5845",
    "addr:postcode":"34120",
    "addr:street":"Everglades Blvd N",
    "iso:country":"US",
    "sg:address":"5845 Everglades Blvd N",
    "sg:city":"Naples",
    "sg:classifiers":[
        {
            "category":"Real Estate",
            "subcategory":"Real Estate Services",
            "type":"Services"
        },
        {
            "category":"Building & Trades",
            "subcategory":"Cleaning & Sanitation",
            "type":"Services"
        }
    ],
    "sg:phone":"+1 239 200 6259",
    "sg:postcode":"34120",
    "sg:province":"FL",
    "sg:tags":[
        "maintenance",
        "cleaners-interior"
    ],
    "wof:name":"Stephanie D Perez",
    "wof:placetype":"venue"
},
  "geometry": {"coordinates":[-81.546027,26.338844],"type":"Point"}
}