{
  "type": "Feature",
  "properties": {
    "addr:full":"21 Madagascar Ct Marco Island FL 34145",
    "addr:housenumber":"21",
    "addr:postcode":"34145",
    "addr:street":"Madagascar Ct",
    "iso:country":"US",
    "sg:address":"21 Madagascar Ct",
    "sg:city":"Marco Island",
    "sg:classifiers":[
        {
            "category":"Building & Trades",
            "subcategory":"Cleaning & Sanitation",
            "type":"Services"
        }
    ],
    "sg:phone":"+1 239 394 1200",
    "sg:postcode":"34145",
    "sg:province":"FL",
    "sg:tags":[
        "janitor"
    ],
    "wof:name":"Barbara Young Cleaning",
    "wof:placetype":"venue"
},
  "geometry": {"coordinates":[-81.704268,25.938088],"type":"Point"}
}