{
  "type": "Feature",
  "properties": {
    "iso:country":"US",
    "sg:address":"305 Main St Ste B",
    "sg:city":"Auburndale",
    "sg:classifiers":[
        {
            "category":"Health Services",
            "subcategory":"Chiropractor",
            "type":"Services"
        }
    ],
    "sg:phone":"+1 863 968 0088",
    "sg:postcode":"33823",
    "sg:province":"FL",
    "sg:tags":[
        "chiropractic"
    ],
    "wof:name":"Auburndale Chiropractic",
    "wof:placetype":"venue"
},
  "geometry": {"coordinates":[-81.78868900000001,28.061399],"type":"Point"}
}