{
  "type": "Feature",
  "properties": {
    "iso:country":"US",
    "sg:address":"3100 Sanders Rd",
    "sg:city":"Davenport",
    "sg:classifiers":[
        {
            "category":"Wholesale",
            "subcategory":"Machinery & Supplies",
            "type":"Manufacturing & Wholesale Goods"
        }
    ],
    "sg:phone":"+1 863 422 3730",
    "sg:postcode":"33837",
    "sg:province":"FL",
    "sg:tags":[
        "equipment",
        "transportation"
    ],
    "wof:name":"Charlie Bass Inc",
    "wof:placetype":"venue"
},
  "geometry": {"coordinates":[-81.65324200000001,28.157866],"type":"Point"}
}