{
  "type": "Feature",
  "properties": {
    "addr:full":"2233 Cypress Landing Dr Atlantic Beach FL 32233",
    "addr:housenumber":"2233",
    "addr:postcode":"32233",
    "addr:street":"Cypress Landing Dr",
    "iso:country":"US",
    "sg:address":"2233 Cypress Landing Dr",
    "sg:city":"Atlantic Beach",
    "sg:classifiers":[
        {
            "category":"Shopping",
            "type":"Retail Goods"
        }
    ],
    "sg:phone":"+1 904 247 8582",
    "sg:postcode":"32233",
    "sg:province":"FL",
    "sg:tags":[
        "merchandise"
    ],
    "wof:name":"Military Coins",
    "wof:placetype":"venue"
},
  "geometry": {"coordinates":[-81.419585,30.347532],"type":"Point"}
}