{
  "type": "Feature",
  "properties": {
    "iso:country":"US",
    "sg:address":"9528 Moore Rd",
    "sg:city":"Lakeland",
    "sg:classifiers":[
        {
            "category":"Building & Trades",
            "subcategory":"Construction",
            "type":"Services"
        }
    ],
    "sg:phone":"+1 863 859 1362",
    "sg:postcode":"33809",
    "sg:province":"FL",
    "sg:tags":[
        "house"
    ],
    "wof:name":"Central Fla Elite Int",
    "wof:placetype":"venue"
},
  "geometry": {"coordinates":[-81.922431,28.174237],"type":"Point"}
}