{
  "type": "Feature",
  "properties": {
    "iso:country":"US",
    "sg:address":"14701 SW 18th Ct",
    "sg:city":"Fort Lauderdale",
    "sg:classifiers":[
        {
            "category":"Manufacturing",
            "subcategory":"Musical Instruments",
            "type":"Manufacturing & Wholesale Goods"
        }
    ],
    "sg:phone":"+1 954 424 6502",
    "sg:postcode":"33325",
    "sg:province":"FL",
    "sg:tags":[
        "mfg"
    ],
    "wof:name":"Eric The Flute Maker",
    "wof:placetype":"venue"
},
  "geometry": {"coordinates":[-80.343554,26.096846],"type":"Point"}
}