{
  "type": "Feature",
  "properties": {
    "iso:country":"US",
    "sg:address":"28480 S Tamiami Trl",
    "sg:city":"Bonita Springs",
    "sg:classifiers":[
        {
            "category":"Autos & Motor Vehicles",
            "subcategory":"Automobile Sales",
            "type":"Retail Goods"
        }
    ],
    "sg:phone":"+1 239 948 6357",
    "sg:postcode":"34134",
    "sg:province":"FL",
    "sg:tags":[
        "car",
        "used",
        "dealer",
        "new"
    ],
    "wof:name":"De Voe Infiniti",
    "wof:placetype":"venue"
},
  "geometry": {"coordinates":[-81.805502,26.321431],"type":"Point"}
}