{
  "type": "Feature",
  "properties": {
    "iso:country":"US",
    "sg:address":"10481 N Kendall Dr",
    "sg:city":"Miami",
    "sg:classifiers":[
        {
            "category":"Insurance",
            "subcategory":"Insurance Agent",
            "type":"Services"
        },
        {
            "category":"Insurance",
            "subcategory":"Hazard Insurance",
            "type":"Services"
        },
        {
            "category":"Insurance",
            "subcategory":"Title Insurance",
            "type":"Services"
        }
    ],
    "sg:phone":"+1 305 273 4530",
    "sg:postcode":"33176",
    "sg:province":"FL",
    "sg:tags":[
        "business",
        "auto",
        "commercial",
        "homeowner",
        "motorcycle"
    ],
    "sg:website":"http://www.realpagessites.com/flinsuranceconsultants/",
    "wof:name":"Insurance Professional Consultants Of Fl",
    "wof:placetype":"venue"
},
  "geometry": {"coordinates":[-80.363669,25.687084],"type":"Point"}
}