{
  "type": "Feature",
  "properties": {
    "addr:full":"8346 Marx Dr Fort Myers FL 33917",
    "addr:housenumber":"8346",
    "addr:postcode":"33917",
    "addr:street":"Marx Dr",
    "iso:country":"US",
    "sg:address":"8346 Marx Dr",
    "sg:city":"Fort Myers",
    "sg:classifiers":[
        {
            "category":"Professional",
            "type":"Services"
        }
    ],
    "sg:phone":"+1 239 731 5888",
    "sg:postcode":"33917",
    "sg:province":"FL",
    "sg:tags":[
        "establishment"
    ],
    "wof:name":"Abcaction",
    "wof:placetype":"venue"
},
  "geometry": {"coordinates":[-81.872151,26.722479],"type":"Point"}
}