{
  "type": "Feature",
  "properties": {
    "iso:country":"US",
    "sg:address":"1575 Richardson Rd",
    "sg:city":"Merritt Island",
    "sg:classifiers":[
        {
            "category":"Health Services",
            "subcategory":"Health Practitioner",
            "type":"Services"
        }
    ],
    "sg:phone":"+1 321 456 5732",
    "sg:postcode":"32952",
    "sg:province":"FL",
    "sg:tags":[
        "psychologist"
    ],
    "wof:name":"Richard La Machia",
    "wof:placetype":"venue"
},
  "geometry": {"coordinates":[-80.664855,28.370476],"type":"Point"}
}