{
  "type": "Feature",
  "properties": {
    "iso:country":"US",
    "sg:address":"9090 Bullrush Ct",
    "sg:city":"New Port Richey",
    "sg:classifiers":[
        {
            "category":"Building & Trades",
            "subcategory":"Landscaping Services",
            "type":"Services"
        }
    ],
    "sg:phone":"+1 727 863 0567",
    "sg:postcode":"34654",
    "sg:province":"FL",
    "sg:tags":[
        "landscape",
        "contractor"
    ],
    "wof:name":"Seitz Lawn & Landscape",
    "wof:placetype":"venue"
},
  "geometry": {"coordinates":[-82.664653,28.28928],"type":"Point"}
}