{
  "type": "Feature",
  "properties": {
    "addr:full":"5757 7th Ave N St Petersburg FL 33710",
    "addr:housenumber":"5757",
    "addr:postcode":"33710",
    "addr:street":"7Th Ave N",
    "iso:country":"US",
    "sg:address":"5757 7th Ave N",
    "sg:city":"St Petersburg",
    "sg:classifiers":[
        {
            "category":"Organizations",
            "subcategory":"Religious Organization",
            "type":"Services"
        }
    ],
    "sg:phone":"+1 727 343 1001",
    "sg:postcode":"33710",
    "sg:province":"FL",
    "sg:tags":[
        "clergy"
    ],
    "wof:name":"Missionaries Of Africa",
    "wof:placetype":"venue"
},
  "geometry": {"coordinates":[-82.710667,27.779101],"type":"Point"}
}