{
  "type": "Feature",
  "properties": {
    "iso:country":"US",
    "sg:address":"7301 SW 164th St",
    "sg:city":"Archer",
    "sg:classifiers":[
        {
            "category":"Building & Trades",
            "subcategory":"Construction",
            "type":"Services"
        }
    ],
    "sg:phone":"+1 269 788 5915",
    "sg:postcode":"32618",
    "sg:province":"FL",
    "sg:tags":[
        "carpenter"
    ],
    "wof:name":"Thomet Customs",
    "wof:placetype":"venue"
},
  "geometry": {"coordinates":[-82.517387,29.585468],"type":"Point"}
}