{
  "type": "Feature",
  "properties": {
    "addr:full":"5724 E Adamo Dr Tampa FL 33619",
    "addr:housenumber":"5724",
    "addr:postcode":"33619",
    "addr:street":"E Adamo Dr",
    "iso:country":"US",
    "sg:address":"5724 E Adamo Dr",
    "sg:city":"Tampa",
    "sg:classifiers":[
        {
            "category":"Wholesale",
            "subcategory":"Non-durable Goods",
            "type":"Manufacturing & Wholesale Goods"
        }
    ],
    "sg:phone":"+1 813 621 5428",
    "sg:postcode":"33619",
    "sg:province":"FL",
    "sg:tags":[
        "dry",
        "goods-wholesale"
    ],
    "wof:name":"Just Rite Supply Inc",
    "wof:placetype":"venue"
},
  "geometry": {"coordinates":[-82.391817,27.952207],"type":"Point"}
}