{
  "type": "Feature",
  "properties": {
    "iso:country":"US",
    "sg:address":"3730 Tampa Rd Ste 2",
    "sg:city":"Oldsmar",
    "sg:classifiers":[
        {
            "category":"Retail",
            "subcategory":"Laundry & Dry Cleaning",
            "type":"Services"
        }
    ],
    "sg:phone":"+1 813 814 5650",
    "sg:postcode":"34677",
    "sg:province":"FL",
    "sg:tags":[
        "cleaner"
    ],
    "sg:website":"http://www.spartancleaners.net",
    "wof:name":"Spartan Cleaners",
    "wof:placetype":"venue"
},
  "geometry": {"coordinates":[-82.679267,28.043911],"type":"Point"}
}