{
  "type": "Feature",
  "properties": {
    "iso:country":"US",
    "sg:address":"1315 Old Ridge Rd",
    "sg:city":"Bonifay",
    "sg:classifiers":[
        {
            "category":"Building & Trades",
            "subcategory":"Construction",
            "type":"Services"
        }
    ],
    "sg:phone":"+1 850 547 5516",
    "sg:postcode":"32425",
    "sg:province":"FL",
    "sg:tags":[
        "contractor"
    ],
    "wof:name":"Mr Fence",
    "wof:placetype":"venue"
},
  "geometry": {"coordinates":[-85.65028100000001,30.943437],"type":"Point"}
}