{
  "type": "Feature",
  "properties": {
    "iso:country":"US",
    "sg:address":"4643 Coronado Pkwy",
    "sg:city":"Cape Coral",
    "sg:classifiers":[
        {
            "category":"Food & Beverages",
            "subcategory":"Candy",
            "type":"Retail Goods"
        }
    ],
    "sg:phone":"+1 239 549 8111",
    "sg:postcode":"33904",
    "sg:province":"FL",
    "sg:tags":[
        "store"
    ],
    "wof:name":"Candy Station",
    "wof:placetype":"venue"
},
  "geometry": {"coordinates":[-81.957802,26.5653],"type":"Point"}
}