{
  "type": "Feature",
  "properties": {
    "addr:full":"1500 Biscayne Blvd # 127 Miami FL 33132",
    "addr:housenumber":"1500;127",
    "addr:postcode":"33132",
    "addr:street":"Biscayne Blvd #",
    "iso:country":"US",
    "sg:address":"1500 Biscayne Blvd # 127",
    "sg:city":"Miami",
    "sg:classifiers":[
        {
            "category":"Professional",
            "subcategory":"Management & Consulting",
            "type":"Services"
        }
    ],
    "sg:phone":"+1 305 995 7148",
    "sg:postcode":"33132",
    "sg:province":"FL",
    "sg:tags":[
        "consultant"
    ],
    "sg:website":"http://www.miamicommunitycharterschool.com",
    "wof:name":"Risk Management",
    "wof:placetype":"venue"
},
  "geometry": {"coordinates":[-80.189072,25.789539],"type":"Point"}
}