{
  "type": "Feature",
  "properties": {
    "iso:country":"US",
    "sg:address":"2001 E 5th Ave",
    "sg:city":"Tampa",
    "sg:classifiers":[
        {
            "category":"Wholesale",
            "subcategory":"Construction Materials",
            "type":"Manufacturing & Wholesale Goods"
        }
    ],
    "sg:phone":"+1 813 248 2283",
    "sg:postcode":"33605",
    "sg:province":"FL",
    "sg:tags":[
        "product",
        "industrial",
        "marine"
    ],
    "sg:website":"www.fmpusa.com",
    "wof:name":"Florida Marine Products Inc",
    "wof:placetype":"venue"
},
  "geometry": {"coordinates":[-82.43550999999999,27.958806],"type":"Point"}
}