{
  "type": "Feature",
  "properties": {
    "iso:country":"US",
    "sg:address":"2016 Plunkett St",
    "sg:city":"Hollywood",
    "sg:classifiers":[
        {
            "category":"Real Estate",
            "subcategory":"Real Estate Agent",
            "type":"Services"
        }
    ],
    "sg:phone":"+1 954 923 2126",
    "sg:postcode":"33020",
    "sg:province":"FL",
    "wof:name":"William Liebel",
    "wof:placetype":"venue"
},
  "geometry": {"coordinates":[-80.147375,26.000215],"type":"Point"}
}