{
  "type": "Feature",
  "properties": {
    "iso:country":"US",
    "sg:address":"8107 NW 73rd Ave",
    "sg:city":"Fort Lauderdale",
    "sg:classifiers":[
        {
            "category":"Building & Trades",
            "subcategory":"Plumbing",
            "type":"Services"
        }
    ],
    "sg:phone":"+1 954 721 5493",
    "sg:postcode":"33321",
    "sg:province":"FL",
    "sg:tags":[
        "conditioning",
        "air",
        "system",
        "contractor"
    ],
    "wof:name":"A-1 Aquatic Systems Inc",
    "wof:placetype":"venue"
},
  "geometry": {"coordinates":[-80.24829,26.223764],"type":"Point"}
}