{
  "type": "Feature",
  "properties": {
    "addr:full":"12423 158th St N Jupiter FL 33478",
    "addr:housenumber":"12423",
    "addr:postcode":"33478",
    "addr:street":"158Th St N",
    "iso:country":"US",
    "sg:address":"12423 158th St N",
    "sg:city":"Jupiter",
    "sg:classifiers":[
        {
            "category":"Building & Trades",
            "subcategory":"Construction",
            "type":"Services"
        }
    ],
    "sg:phone":"+1 561 747 5570",
    "sg:postcode":"33478",
    "sg:province":"FL",
    "sg:tags":[
        "trim",
        "carpentry"
    ],
    "wof:name":"William E Flora",
    "wof:placetype":"venue"
},
  "geometry": {"coordinates":[-80.22839,26.910141],"type":"Point"}
}