{
  "type": "Feature",
  "properties": {
    "addr:full":"230 N Woodland Blvd Deland FL 32720",
    "addr:housenumber":"230",
    "addr:postcode":"32720",
    "addr:street":"N Woodland Blvd",
    "iso:country":"US",
    "sg:address":"230 N Woodland Blvd",
    "sg:city":"Deland",
    "sg:classifiers":[
        {
            "category":"Government",
            "subcategory":"Office",
            "type":"Public Place"
        }
    ],
    "sg:phone":"+1 386 736 5963",
    "sg:postcode":"32720",
    "sg:province":"FL",
    "wof:name":"Volusia County Risk Management",
    "wof:placetype":"venue"
},
  "geometry": {"coordinates":[-81.30354699999999,29.030254],"type":"Point"}
}