{
  "type": "Feature",
  "properties": {
    "addr:full":"1740 Brentwood Dr Clearwater FL 33756",
    "addr:housenumber":"1740",
    "addr:postcode":"33756",
    "addr:street":"Brentwood Dr",
    "iso:country":"US",
    "sg:address":"1740 Brentwood Dr",
    "sg:city":"Clearwater",
    "sg:classifiers":[
        {
            "category":"Building & Trades",
            "subcategory":"Construction",
            "type":"Services"
        }
    ],
    "sg:phone":"+1 727 449 2911",
    "sg:postcode":"33756",
    "sg:province":"FL",
    "sg:tags":[
        "general",
        "contractor"
    ],
    "wof:name":"Grip Enterprises Inc",
    "wof:placetype":"venue"
},
  "geometry": {"coordinates":[-82.762638,27.95063],"type":"Point"}
}