{
  "type": "Feature",
  "properties": {
    "addr:full":"3415 W Lake Mary Blvd Lake Mary FL 32746",
    "addr:housenumber":"3415",
    "addr:postcode":"32746",
    "addr:street":"W Lake Mary Blvd",
    "iso:country":"US",
    "sg:address":"3415 W Lake Mary Blvd",
    "sg:city":"Lake Mary",
    "sg:classifiers":[
        {
            "category":"Government",
            "subcategory":"Post Office",
            "type":"Public Place"
        }
    ],
    "sg:phone":"+1 407 000 1111",
    "sg:postcode":"32746",
    "sg:province":"FL",
    "wof:name":"US Post Office",
    "wof:placetype":"venue"
},
  "geometry": {"coordinates":[-81.34062900000001,28.756198],"type":"Point"}
}