{
  "type": "Feature",
  "properties": {
    "iso:country":"US",
    "sg:address":"3000 Garcon Point Rd",
    "sg:city":"Milton",
    "sg:classifiers":[
        {
            "category":"Manufacturing",
            "subcategory":"Lumber",
            "type":"Manufacturing & Wholesale Goods"
        }
    ],
    "sg:phone":"+1 850 626 9814",
    "sg:postcode":"32583",
    "sg:province":"FL",
    "sg:tags":[
        "timberland",
        "timber"
    ],
    "wof:name":"Edmund Steadman Dr",
    "wof:placetype":"venue"
},
  "geometry": {"coordinates":[-87.04721000000001,30.544792],"type":"Point"}
}