{
  "type": "Feature",
  "properties": {
    "addr:full":"3223 Commerce Pl West Palm Beach FL 33407",
    "addr:housenumber":"3223",
    "addr:postcode":"33407",
    "addr:street":"Commerce Pl",
    "iso:country":"US",
    "sg:address":"3223 Commerce Pl",
    "sg:city":"West Palm Beach",
    "sg:classifiers":[
        {
            "category":"Wholesale",
            "subcategory":"Electrical",
            "type":"Manufacturing & Wholesale Goods"
        }
    ],
    "sg:phone":"+1 561 655 9956",
    "sg:postcode":"33407",
    "sg:province":"FL",
    "sg:tags":[
        "alarm",
        "burglar",
        "system"
    ],
    "wof:name":"Security Networks",
    "wof:placetype":"venue"
},
  "geometry": {"coordinates":[-80.10117099999999,26.761568],"type":"Point"}
}