{
  "type": "Feature",
  "properties": {
    "iso:country":"US",
    "sg:address":"6902 Causeway Blvd",
    "sg:city":"Tampa",
    "sg:classifiers":[
        {
            "category":"Wholesale",
            "subcategory":"Construction Materials",
            "type":"Manufacturing & Wholesale Goods"
        }
    ],
    "sg:phone":"+1 813 677 2625",
    "sg:postcode":"33619",
    "sg:province":"FL",
    "sg:tags":[
        "fence"
    ],
    "wof:name":"Stalnaker Farm & Ranch",
    "wof:placetype":"venue"
},
  "geometry": {"coordinates":[-82.37694,27.922797],"type":"Point"}
}