{
  "type": "Feature",
  "properties": {
    "iso:country":"US",
    "sg:address":"3766 Benson Ave N",
    "sg:city":"Saint Petersburg",
    "sg:classifiers":[
        {
            "category":"Banks & Credit Unions",
            "subcategory":"Financial Services",
            "type":"Services"
        }
    ],
    "sg:phone":"+1 727 527 5368",
    "sg:postcode":"33713",
    "sg:province":"FL",
    "sg:tags":[
        "trust",
        "management"
    ],
    "wof:name":"Pegasus Trust",
    "wof:placetype":"venue"
},
  "geometry": {"coordinates":[-82.68443000000001,27.797619],"type":"Point"}
}