{
  "type": "Feature",
  "properties": {
    "iso:country":"US",
    "sg:address":"992 Tamiami Trl",
    "sg:city":"Port Charlotte",
    "sg:classifiers":[
        {
            "category":"Banks & Credit Unions",
            "subcategory":"Bank",
            "type":"Services"
        }
    ],
    "sg:phone":"+1 941 625 3833",
    "sg:postcode":"33953",
    "sg:province":"FL",
    "sg:tags":[
        "banker",
        "mortgage"
    ],
    "wof:name":"CTX Charlotte Harbor",
    "wof:placetype":"venue"
},
  "geometry": {"coordinates":[-82.15568,27.017046],"type":"Point"}
}