{
  "type": "Feature",
  "properties": {
    "addr:full":"8213 Castinango St Orlando FL 32817",
    "addr:housenumber":"8213",
    "addr:postcode":"32817",
    "addr:street":"Castinango St",
    "iso:country":"US",
    "sg:address":"8213 Castinango St",
    "sg:city":"Orlando",
    "sg:classifiers":[
        {
            "category":"Building & Trades",
            "subcategory":"Construction",
            "type":"Services"
        }
    ],
    "sg:phone":"+1 407 678 7579",
    "sg:postcode":"32817",
    "sg:province":"FL",
    "sg:tags":[
        "carpentry",
        "contractor"
    ],
    "wof:name":"Eduardo Ortego Construction",
    "wof:placetype":"venue"
},
  "geometry": {"coordinates":[-81.27779700000001,28.584868],"type":"Point"}
}