{
  "type": "Feature",
  "properties": {
    "iso:country":"US",
    "sg:address":"36 NE 2nd St",
    "sg:city":"Miami",
    "sg:classifiers":[
        {
            "category":"Internet Cafe",
            "subcategory":"None",
            "type":"Food & Drink"
        },
        {
            "category":"Professional",
            "subcategory":"Computer Services",
            "type":"Services"
        }
    ],
    "sg:phone":"+1 305 371 5939",
    "sg:postcode":"33132",
    "sg:province":"FL",
    "sg:tags":[
        "product",
        "network",
        "isp",
        "system",
        "design",
        "provider"
    ],
    "wof:name":"Switch and Data",
    "wof:placetype":"venue"
},
  "geometry": {"coordinates":[-80.193062,25.776087],"type":"Point"}
}