{
  "type": "Feature",
  "properties": {
    "iso:country":"US",
    "sg:address":"40 S Heathwood Dr",
    "sg:city":"Marco Island",
    "sg:classifiers":[
        {
            "category":"Health Services",
            "subcategory":"Doctor",
            "type":"Services"
        }
    ],
    "sg:phone":"+1 239 394 8234",
    "sg:postcode":"34145",
    "sg:province":"FL",
    "sg:tags":[
        "clinic"
    ],
    "wof:name":"Marco Healthcare Ctr",
    "wof:placetype":"venue"
},
  "geometry": {"coordinates":[-81.71584,25.937058],"type":"Point"}
}