{
  "type": "Feature",
  "properties": {
    "addr:full":"7719 Forest City Rd Orlando FL 32810",
    "addr:housenumber":"7719",
    "addr:postcode":"32810",
    "addr:street":"Forest City Rd",
    "iso:country":"US",
    "sg:address":"7719 Forest City Rd",
    "sg:city":"Orlando",
    "sg:classifiers":[
        {
            "category":"Organizations",
            "subcategory":"Religious Organization",
            "type":"Services"
        }
    ],
    "sg:phone":"+1 407 295 3850",
    "sg:postcode":"32810",
    "sg:province":"FL",
    "sg:tags":[
        "churches-baptist",
        "church"
    ],
    "wof:name":"Riverside Baptist Church",
    "wof:placetype":"venue"
},
  "geometry": {"coordinates":[-81.415001,28.627199],"type":"Point"}
}