{
  "type": "Feature",
  "properties": {
    "iso:country":"US",
    "sg:address":"715 Francis Ave",
    "sg:city":"New Smyrna Beach",
    "sg:classifiers":[
        {
            "category":"Manufacturing",
            "subcategory":"Metals",
            "type":"Manufacturing & Wholesale Goods"
        }
    ],
    "sg:phone":"+1 386 428 1671",
    "sg:postcode":"32168",
    "sg:province":"FL",
    "sg:tags":[
        "metalwork",
        "architectural",
        "mfg"
    ],
    "wof:name":"Visionary Marble/Til",
    "wof:placetype":"venue"
},
  "geometry": {"coordinates":[-80.93649600000001,29.032995],"type":"Point"}
}