{
  "type": "Feature",
  "properties": {
    "addr:full":"8400 Roosevelt Blvd Orange Park FL 32073",
    "addr:housenumber":"8400",
    "addr:postcode":"32073",
    "addr:street":"Roosevelt Blvd",
    "iso:country":"US",
    "sg:address":"8400 Roosevelt Blvd",
    "sg:city":"Orange Park",
    "sg:classifiers":[
        {
            "category":"Retail",
            "subcategory":"Auto Repair",
            "type":"Services"
        }
    ],
    "sg:phone":"+1 904 777 8855",
    "sg:postcode":"32073",
    "sg:province":"FL",
    "sg:tags":[
        "body"
    ],
    "wof:name":"River City Auto Body & Repair",
    "wof:placetype":"venue"
},
  "geometry": {"coordinates":[-81.707386,30.195617],"type":"Point"}
}