{
  "type": "Feature",
  "properties": {
    "addr:full":"7610 Byron Ave Miami Beach FL 33141",
    "addr:housenumber":"7610",
    "addr:postcode":"33141",
    "addr:street":"Byron Ave",
    "iso:country":"US",
    "sg:address":"7610 Byron Ave",
    "sg:city":"Miami Beach",
    "sg:classifiers":[
        {
            "category":"Professional",
            "subcategory":"Computer Services",
            "type":"Services"
        }
    ],
    "sg:phone":"+1 305 866 0776",
    "sg:postcode":"33141",
    "sg:province":"FL",
    "sg:tags":[
        "internet"
    ],
    "wof:name":"Echo Pages",
    "wof:placetype":"venue"
},
  "geometry": {"coordinates":[-80.123915,25.862024],"type":"Point"}
}