{
  "type": "Feature",
  "properties": {
    "iso:country":"US",
    "sg:address":"189 W Ave A",
    "sg:city":"Belle Glade",
    "sg:classifiers":[
        {
            "category":"Shopping",
            "subcategory":"Gifts & Souvenirs",
            "type":"Retail Goods"
        }
    ],
    "sg:phone":"+1 561 996 6411",
    "sg:postcode":"33430",
    "sg:province":"FL",
    "sg:tags":[
        "shop"
    ],
    "wof:name":"Lena's Flower & Gift Shop",
    "wof:placetype":"venue"
},
  "geometry": {"coordinates":[-80.66907999999999,26.685817],"type":"Point"}
}