{
  "type": "Feature",
  "properties": {
    "iso:country":"US",
    "sg:address":"11038 State Rd 52",
    "sg:city":"Port Richey",
    "sg:classifiers":[
        {
            "category":"Building & Trades",
            "subcategory":"Electrical",
            "type":"Services"
        }
    ],
    "sg:phone":"+1 727 856 9295",
    "sg:postcode":"34669",
    "sg:province":"FL",
    "sg:tags":[
        "installation",
        "telephone",
        "system"
    ],
    "wof:name":"Inner-Phone Systems Inc",
    "wof:placetype":"venue"
},
  "geometry": {"coordinates":[-82.633386,28.331739],"type":"Point"}
}