{
  "type": "Feature",
  "properties": {
    "iso:country":"US",
    "sg:address":"11730 SE US Hwy 441",
    "sg:city":"Belleview",
    "sg:classifiers":[
        {
            "category":"Health Services",
            "subcategory":"Chiropractor",
            "type":"Services"
        }
    ],
    "sg:phone":"+1 352 245 0145",
    "sg:postcode":"34420",
    "sg:province":"FL",
    "wof:name":"Belleview Chiropractic Clinic",
    "wof:placetype":"venue"
},
  "geometry": {"coordinates":[-82.037834,29.050597],"type":"Point"}
}