{
  "type": "Feature",
  "properties": {
    "iso:country":"US",
    "sg:address":"1841 N Highland Ave",
    "sg:city":"Clearwater",
    "sg:classifiers":[
        {
            "category":"Organizations",
            "subcategory":"Religious Organization",
            "type":"Services"
        }
    ],
    "sg:phone":"+1 727 445 9660",
    "sg:postcode":"33755",
    "sg:province":"FL",
    "sg:tags":[
        "church"
    ],
    "wof:name":"Bridge of Love Ministries",
    "wof:placetype":"venue"
},
  "geometry": {"coordinates":[-82.77534199999999,27.989549],"type":"Point"}
}