{
  "type": "Feature",
  "properties": {
    "addr:full":"11791 Woodshire Cir Fort Myers FL 33913",
    "addr:housenumber":"11791",
    "addr:postcode":"33913",
    "addr:street":"Woodshire Cir",
    "iso:country":"US",
    "sg:address":"11791 Woodshire Cir",
    "sg:city":"Fort Myers",
    "sg:classifiers":[
        {
            "category":"Banks & Credit Unions",
            "subcategory":"Bank",
            "type":"Services"
        }
    ],
    "sg:phone":"+1 239 561 2544",
    "sg:postcode":"33913",
    "sg:province":"FL",
    "sg:tags":[
        "institution",
        "business"
    ],
    "wof:name":"Mark W Sheets PA",
    "wof:placetype":"venue"
},
  "geometry": {"coordinates":[-81.741489,26.573543],"type":"Point"}
}