{
  "type": "Feature",
  "properties": {
    "iso:country":"US",
    "sg:address":"4770 110th Ave N",
    "sg:city":"Clearwater",
    "sg:classifiers":[
        {
            "category":"Building & Trades",
            "subcategory":"Landscaping Services",
            "type":"Services"
        }
    ],
    "sg:phone":"+1 727 572 4112",
    "sg:postcode":"33762",
    "sg:province":"FL",
    "sg:tags":[
        "landscape",
        "contractor"
    ],
    "wof:name":"Emerald Grounds",
    "wof:placetype":"venue"
},
  "geometry": {"coordinates":[-82.70025099999999,27.871996],"type":"Point"}
}