{
  "type": "Feature",
  "properties": {
    "iso:country":"US",
    "sg:address":"13650 State Hwy 84",
    "sg:city":"Davie",
    "sg:classifiers":[
        {
            "category":"Utilities",
            "subcategory":"Mobile Phone",
            "type":"Services"
        }
    ],
    "sg:phone":"+1 954 723 0900",
    "sg:postcode":"33325",
    "sg:province":"FL",
    "sg:tags":[
        "telephone",
        "cellular"
    ],
    "wof:name":"Cingular Wireless",
    "wof:placetype":"venue"
},
  "geometry": {"coordinates":[-80.32214,26.116891],"type":"Point"}
}