{
  "type": "Feature",
  "properties": {
    "addr:full":"14341 Miramar Pkwy Miramar FL 33027",
    "addr:housenumber":"14341",
    "addr:postcode":"33027",
    "addr:street":"Miramar Pkwy",
    "iso:country":"US",
    "sg:address":"14341 Miramar Pkwy",
    "sg:city":"Miramar",
    "sg:classifiers":[
        {
            "category":"Restaurant",
            "type":"Food & Drink"
        }
    ],
    "sg:phone":"+1 954 443 0544",
    "sg:postcode":"33027",
    "sg:province":"FL",
    "wof:name":"Subway Sandwiches & Salads",
    "wof:placetype":"venue"
},
  "geometry": {"coordinates":[-80.337065,25.978817],"type":"Point"}
}