{
  "type": "Feature",
  "properties": {
    "iso:country":"US",
    "sg:address":"109 Park Lane East",
    "sg:city":"Hypoluxo",
    "sg:phone":"+1 561 588 7777",
    "sg:postcode":"33462",
    "sg:province":"FL",
    "sg:website":"http://www.naturallookmakeup.com",
    "wof:name":"A Natural Look Permanent Make Up Ctr",
    "wof:placetype":"venue"
},
  "geometry": {"coordinates":[-80.05357100000001,26.56938],"type":"Point"}
}