{
  "type": "Feature",
  "properties": {
    "iso:country":"US",
    "sg:address":"926 9th Ave N",
    "sg:city":"Jacksonville Beach",
    "sg:classifiers":[
        {
            "category":"Building & Trades",
            "subcategory":"Electrical",
            "type":"Services"
        }
    ],
    "sg:phone":"+1 904 249 9050",
    "sg:postcode":"32250",
    "sg:province":"FL",
    "sg:tags":[
        "electrical",
        "contractor"
    ],
    "wof:name":"Wireworks Electrical Contrs",
    "wof:placetype":"venue"
},
  "geometry": {"coordinates":[-81.40110199999999,30.296247],"type":"Point"}
}