{
  "type": "Feature",
  "properties": {
    "addr:full":"1705 9th Ave N St Petersburg FL 33713",
    "addr:housenumber":"1705",
    "addr:postcode":"33713",
    "addr:street":"9Th Ave N",
    "iso:country":"US",
    "sg:address":"1705 9th Ave N",
    "sg:city":"St Petersburg",
    "sg:classifiers":[
        {
            "category":"Organizations",
            "subcategory":"Community Association",
            "type":"Services"
        }
    ],
    "sg:phone":"+1 727 821 9771",
    "sg:postcode":"33713",
    "sg:province":"FL",
    "sg:tags":[
        "club"
    ],
    "wof:name":"Latvian American Ctr",
    "wof:placetype":"venue"
},
  "geometry": {"coordinates":[-82.656826,27.781197],"type":"Point"}
}