{
  "type": "Feature",
  "properties": {
    "iso:country":"US",
    "sg:address":"1820 S Florida Ave",
    "sg:city":"Lakeland",
    "sg:classifiers":[
        {
            "category":"Insurance",
            "subcategory":"Insurance Agent",
            "type":"Services"
        }
    ],
    "sg:phone":"+1 863 802 5050",
    "sg:postcode":"33803",
    "sg:province":"FL",
    "wof:name":"Central Florida Ins & Fnncl",
    "wof:placetype":"venue"
},
  "geometry": {"coordinates":[-81.95702,28.022006],"type":"Point"}
}