{
  "type": "Feature",
  "properties": {
    "addr:full":"117 W Bloomingdale Ave Brandon FL 33511",
    "addr:housenumber":"117",
    "addr:postcode":"33511",
    "addr:street":"W Bloomingdale Ave",
    "iso:country":"US",
    "sg:address":"117 W Bloomingdale Ave",
    "sg:city":"Brandon",
    "sg:classifiers":[
        {
            "category":"Ice Cream",
            "type":"Food & Drink"
        }
    ],
    "sg:menulink":"http://www.allmenus.com/fl/brandon/221386-carvel/menu/",
    "sg:phone":"+1 813 571 7841",
    "sg:postcode":"33511",
    "sg:province":"FL",
    "sg:tags":[
        "american"
    ],
    "wof:name":"Carvel",
    "wof:placetype":"venue"
},
  "geometry": {"coordinates":[-82.286222,27.893602],"type":"Point"}
}