{
  "type": "Feature",
  "properties": {
    "addr:full":"460 N Orlando Ave Ste 118 Winter Park FL 32789",
    "addr:housenumber":"460",
    "addr:postcode":"32789",
    "addr:street":"N Orlando Ave Ste 118",
    "iso:country":"US",
    "sg:address":"460 N Orlando Ave Ste 118",
    "sg:city":"Winter Park",
    "sg:classifiers":[
        {
            "category":"Personal",
            "subcategory":"Beauty Salon",
            "type":"Services"
        },
        {
            "category":"Personal",
            "subcategory":"Barber",
            "type":"Services"
        }
    ],
    "sg:phone":"+1 866 925 1355",
    "sg:postcode":"32789",
    "sg:province":"FL",
    "sg:tags":[
        "hair"
    ],
    "sg:website":"www.orlandohaircut.com",
    "wof:name":"Orlando Haircut & Salon",
    "wof:placetype":"venue"
},
  "geometry": {"coordinates":[-81.365101,28.601924],"type":"Point"}
}