{
  "type": "Feature",
  "properties": {
    "addr:full":"9240 Bonita Beach Rd Bonita Springs FL 34135",
    "addr:housenumber":"9240",
    "addr:postcode":"34135",
    "addr:street":"Bonita Beach Rd",
    "iso:country":"US",
    "sg:address":"9240 Bonita Beach Rd",
    "sg:city":"Bonita Springs",
    "sg:classifiers":[
        {
            "category":"Professional",
            "subcategory":"Business Services",
            "type":"Services"
        }
    ],
    "sg:phone":"+1 239 992 9533",
    "sg:postcode":"34135",
    "sg:province":"FL",
    "wof:name":"Dominion Business Group Inc",
    "wof:placetype":"venue"
},
  "geometry": {"coordinates":[-81.800635,26.330662],"type":"Point"}
}