{
  "type": "Feature",
  "properties": {
    "iso:country":"US",
    "sg:address":"10280 SW 144th St",
    "sg:city":"Miami",
    "sg:classifiers":[
        {
            "category":"Professional",
            "subcategory":"Business Services",
            "type":"Services"
        }
    ],
    "sg:phone":"+1 786 242 5224",
    "sg:postcode":"33176",
    "sg:province":"FL",
    "sg:tags":[
        "building",
        "inspection"
    ],
    "wof:name":"Florida Mit LLC",
    "wof:placetype":"venue"
},
  "geometry": {"coordinates":[-80.36009300000001,25.636227],"type":"Point"}
}