{
  "type": "Feature",
  "properties": {
    "iso:country":"US",
    "sg:address":"2601 NW 17th Ln",
    "sg:city":"Pompano Beach",
    "sg:classifiers":[
        {
            "category":"Wholesale",
            "subcategory":"Office Equipment",
            "type":"Manufacturing & Wholesale Goods"
        }
    ],
    "sg:phone":"+1 954 971 7474",
    "sg:postcode":"33064",
    "sg:province":"FL",
    "sg:tags":[
        "printer",
        "laser",
        "sales"
    ],
    "wof:name":"Imaging USA Corporation",
    "wof:placetype":"venue"
},
  "geometry": {"coordinates":[-80.14782200000001,26.263322],"type":"Point"}
}