{
  "type": "Feature",
  "properties": {
    "iso:country":"US",
    "sg:address":"3020 Florida Blvd",
    "sg:city":"Delray Beach",
    "sg:classifiers":[
        {
            "category":"Real Estate",
            "subcategory":"Real Estate Agent",
            "type":"Services"
        }
    ],
    "sg:phone":"+1 561 573 4338",
    "sg:postcode":"33483",
    "sg:province":"FL",
    "wof:name":"S G Rex & Company Inc",
    "wof:placetype":"venue"
},
  "geometry": {"coordinates":[-80.07027100000001,26.425146],"type":"Point"}
}