{
  "type": "Feature",
  "properties": {
    "iso:country":"US",
    "sg:address":"777 Brickell Ave",
    "sg:city":"Miami",
    "sg:classifiers":[
        {
            "category":"Health Services",
            "subcategory":"Clinic",
            "type":"Services"
        }
    ],
    "sg:phone":"+1 305 344 6232",
    "sg:postcode":"33129",
    "sg:province":"FL",
    "wof:name":"American Healthcare Management",
    "wof:placetype":"venue"
},
  "geometry": {"coordinates":[-80.19045800000001,25.766838],"type":"Point"}
}