{
  "type": "Feature",
  "properties": {
    "iso:country":"US",
    "sg:address":"4583 N Dixie Hwy",
    "sg:city":"Pompano Beach",
    "sg:classifiers":[
        {
            "category":"Banks & Credit Unions",
            "subcategory":"Bank",
            "type":"Services"
        }
    ],
    "sg:phone":"+1 954 783 4116",
    "sg:postcode":"33064",
    "sg:province":"FL",
    "sg:tags":[
        "mortgage"
    ],
    "wof:name":"Quick Close Mortgage Inc",
    "wof:placetype":"venue"
},
  "geometry": {"coordinates":[-80.110472,26.28713],"type":"Point"}
}