{
  "type": "Feature",
  "properties": {
    "iso:country":"US",
    "sg:address":"14730 Boland Ave",
    "sg:city":"Spring Hill",
    "sg:classifiers":[
        {
            "category":"Building & Trades",
            "subcategory":"Construction",
            "type":"Services"
        }
    ],
    "sg:phone":"+1 727 856 5163",
    "sg:postcode":"34610",
    "sg:province":"FL",
    "sg:tags":[
        "contractor"
    ],
    "wof:name":"Finch Masonry",
    "wof:placetype":"venue"
},
  "geometry": {"coordinates":[-82.57189200000001,28.406138],"type":"Point"}
}