{
  "type": "Feature",
  "properties": {
    "iso:country":"US",
    "sg:address":"596 SW 29th Ave",
    "sg:city":"Delray Beach",
    "sg:classifiers":[
        {
            "category":"Organizations",
            "subcategory":"Membership Organization",
            "type":"Services"
        }
    ],
    "sg:phone":"+1 561 272 6510",
    "sg:postcode":"33445",
    "sg:province":"FL",
    "wof:name":"Women of Woodlake",
    "wof:placetype":"venue"
},
  "geometry": {"coordinates":[-80.1056,26.45727],"type":"Point"}
}