{
  "type": "Feature",
  "properties": {
    "iso:country":"US",
    "sg:address":"15017 Emerald Coast Pkwy",
    "sg:city":"Destin",
    "sg:classifiers":[
        {
            "category":"Personal",
            "subcategory":"Beauty Salon",
            "type":"Services"
        }
    ],
    "sg:phone":"+1 850 654 9919",
    "sg:postcode":"32541",
    "sg:province":"FL",
    "sg:tags":[
        "shop"
    ],
    "wof:name":"Nailport Express",
    "wof:placetype":"venue"
},
  "geometry": {"coordinates":[-86.455809,30.387446],"type":"Point"}
}