{
  "type": "Feature",
  "properties": {
    "iso:country":"US",
    "sg:address":"832 62nd Street Cir E",
    "sg:city":"Bradenton",
    "sg:classifiers":[
        {
            "category":"Education",
            "subcategory":"Special Training",
            "type":"Public Place"
        },
        {
            "category":"Education",
            "subcategory":"Preschool",
            "type":"Public Place"
        },
        {
            "category":"Education",
            "subcategory":"School",
            "type":"Public Place"
        }
    ],
    "sg:phone":"+1 941 747 7710",
    "sg:postcode":"34208",
    "sg:province":"FL",
    "sg:tags":[
        "kindergarten",
        "educational",
        "k-",
        "private"
    ],
    "wof:name":"Smarty Pants Preschool",
    "wof:placetype":"venue"
},
  "geometry": {"coordinates":[-82.48230700000001,27.492133],"type":"Point"}
}