{
  "type": "Feature",
  "properties": {
    "addr:full":"5101 E Busch Blvd Tampa FL 33617",
    "addr:housenumber":"5101",
    "addr:postcode":"33617",
    "addr:street":"E Busch Blvd",
    "iso:country":"US",
    "sg:address":"5101 E Busch Blvd",
    "sg:city":"Tampa",
    "sg:classifiers":[
        {
            "category":"Health Services",
            "subcategory":"Doctor",
            "type":"Services"
        }
    ],
    "sg:phone":"+1 813 899 9089",
    "sg:postcode":"33617",
    "sg:province":"FL",
    "sg:tags":[
        "physician",
        "surgeon"
    ],
    "wof:name":"West Coast Family Practice",
    "wof:placetype":"venue"
},
  "geometry": {"coordinates":[-82.398066,28.032624],"type":"Point"}
}