{
  "type": "Feature",
  "properties": {
    "iso:country":"US",
    "sg:address":"7341 Glenwood Rd",
    "sg:city":"Cocoa",
    "sg:classifiers":[
        {
            "category":"Professional",
            "subcategory":"Management & Consulting",
            "type":"Services"
        }
    ],
    "sg:phone":"+1 321 635 8477",
    "sg:postcode":"32927",
    "sg:province":"FL",
    "sg:tags":[
        "environmental"
    ],
    "wof:name":"Ecoes Consulting Inc",
    "wof:placetype":"venue"
},
  "geometry": {"coordinates":[-80.79981600000001,28.487174],"type":"Point"}
}