{
  "type": "Feature",
  "properties": {
    "addr:full":"1600 Alton Rd Miami Beach FL 33139",
    "addr:housenumber":"1600",
    "addr:postcode":"33139",
    "addr:street":"Alton Rd",
    "iso:country":"US",
    "sg:address":"1600 Alton Rd",
    "sg:city":"Miami Beach",
    "sg:classifiers":[
        {
            "category":"Food & Beverages",
            "subcategory":"Groceries & Convenience Stores",
            "type":"Retail Goods"
        }
    ],
    "sg:phone":"+1 305 672 1050",
    "sg:postcode":"33139",
    "sg:province":"FL",
    "wof:name":"Compass Market Inc",
    "wof:placetype":"venue"
},
  "geometry": {"coordinates":[-80.141302,25.788906],"type":"Point"}
}