{
  "type": "Feature",
  "properties": {
    "addr:full":"2636 Bottomridge Dr Orange Park FL 32065",
    "addr:housenumber":"2636",
    "addr:postcode":"32065",
    "addr:street":"Bottomridge Dr",
    "iso:country":"US",
    "sg:address":"2636 Bottomridge Dr",
    "sg:city":"Orange Park",
    "sg:classifiers":[
        {
            "category":"Professional",
            "type":"Services"
        }
    ],
    "sg:phone":"+1 904 272 1044",
    "sg:postcode":"32065",
    "sg:province":"FL",
    "sg:tags":[
        "establishment"
    ],
    "wof:name":"Jensine Henderson Inc",
    "wof:placetype":"venue"
},
  "geometry": {"coordinates":[-81.781541,30.155488],"type":"Point"}
}