{
  "type": "Feature",
  "properties": {
    "addr:full":"128 Sugar Cove Rd Santa Rosa Beach FL 32459",
    "addr:housenumber":"128",
    "addr:postcode":"32459",
    "addr:street":"Sugar Cove Rd",
    "iso:country":"US",
    "sg:address":"128 Sugar Cove Rd",
    "sg:city":"Santa Rosa Beach",
    "sg:classifiers":[
        {
            "category":"Retail",
            "subcategory":"Repair Shop",
            "type":"Services"
        }
    ],
    "sg:phone":"+1 850 267 1049",
    "sg:postcode":"32459",
    "sg:province":"FL",
    "sg:tags":[
        "welding"
    ],
    "wof:name":"Aquatops Inc",
    "wof:placetype":"venue"
},
  "geometry": {"coordinates":[-86.25606500000001,30.364185],"type":"Point"}
}