{
  "type": "Feature",
  "properties": {
    "iso:country":"US",
    "sg:address":"1906 N Armenia Ave",
    "sg:city":"Tampa",
    "sg:classifiers":[
        {
            "category":"Retail",
            "subcategory":"Portrait Studio",
            "type":"Services"
        }
    ],
    "sg:phone":"+1 813 930 7390",
    "sg:postcode":"33607",
    "sg:province":"FL",
    "sg:tags":[
        "photographer"
    ],
    "wof:name":"Sargent Photography",
    "wof:placetype":"venue"
},
  "geometry": {"coordinates":[-82.485033,27.959327],"type":"Point"}
}