{
  "type": "Feature",
  "properties": {
    "addr:full":"10953 NW 47th Ln Miami FL 33178",
    "addr:housenumber":"10953",
    "addr:postcode":"33178",
    "addr:street":"Nw 47Th Ln",
    "iso:country":"US",
    "sg:address":"10953 NW 47th Ln",
    "sg:city":"Miami",
    "sg:classifiers":[
        {
            "category":"Professional",
            "subcategory":"Computer Services",
            "type":"Services"
        }
    ],
    "sg:phone":"+1 305 594 9322",
    "sg:postcode":"33178",
    "sg:province":"FL",
    "sg:tags":[
        "programing",
        "custom"
    ],
    "wof:name":"Ecusoft",
    "wof:placetype":"venue"
},
  "geometry": {"coordinates":[-80.37475999999999,25.816792],"type":"Point"}
}