{
  "type": "Feature",
  "properties": {
    "iso:country":"US",
    "sg:address":"6290 Corporate Ct",
    "sg:city":"Fort Myers",
    "sg:classifiers":[
        {
            "category":"Health Services",
            "subcategory":"Chiropractor",
            "type":"Services"
        }
    ],
    "sg:phone":"+1 505 577 2192",
    "sg:postcode":"33919",
    "sg:province":"FL",
    "wof:name":"Essence Chiropractic Ntrtn Ctr",
    "wof:placetype":"venue"
},
  "geometry": {"coordinates":[-81.887496,26.558568],"type":"Point"}
}