{
  "type": "Feature",
  "properties": {
    "iso:country":"US",
    "sg:address":"4298 Millenia Blvd",
    "sg:city":"Orlando",
    "sg:classifiers":[
        {
            "category":"Shopping",
            "subcategory":"Beauty & Cosmetics",
            "type":"Retail Goods"
        },
        {
            "category":"Personal",
            "subcategory":"Skin Care",
            "type":"Services"
        }
    ],
    "sg:phone":"+1 407 345 9925",
    "sg:postcode":"32839",
    "sg:province":"FL",
    "sg:tags":[
        "perfume"
    ],
    "sg:website":"http://www.danreadcosmetics.com",
    "wof:name":"Mac Cosmetics",
    "wof:placetype":"venue"
},
  "geometry": {"coordinates":[-81.43311199999999,28.488676],"type":"Point"}
}