{
  "type": "Feature",
  "properties": {
    "addr:full":"1960 NE Jensen Beach Blvd Jensen Beach FL 34957",
    "addr:housenumber":"1960",
    "addr:postcode":"34957",
    "addr:street":"Ne Jensen Beach Blvd",
    "iso:country":"US",
    "sg:address":"1960 NE Jensen Beach Blvd",
    "sg:city":"Jensen Beach",
    "sg:classifiers":[
        {
            "category":"Home & Garden",
            "subcategory":"Building Materials",
            "type":"Retail Goods"
        },
        {
            "category":"Professional",
            "type":"Services"
        }
    ],
    "sg:phone":"+1 772 334 8920",
    "sg:postcode":"34957",
    "sg:province":"FL",
    "sg:tags":[
        "glass",
        "leaded",
        "contractor"
    ],
    "wof:name":"Stain In The Glass",
    "wof:placetype":"venue"
},
  "geometry": {"coordinates":[-80.225407,27.244342],"type":"Point"}
}