{
  "type": "Feature",
  "properties": {
    "addr:full":"1606 S Arrawana Ave Tampa FL 33629",
    "addr:housenumber":"1606",
    "addr:postcode":"33629",
    "addr:street":"S Arrawana Ave",
    "iso:country":"US",
    "sg:address":"1606 S Arrawana Ave",
    "sg:city":"Tampa",
    "sg:classifiers":[
        {
            "category":"Retail",
            "subcategory":"Repair Shop",
            "type":"Services"
        }
    ],
    "sg:phone":"+1 813 254 2866",
    "sg:postcode":"33629",
    "sg:province":"FL",
    "sg:tags":[
        "television",
        "radio-service"
    ],
    "wof:name":"Tv Room",
    "wof:placetype":"venue"
},
  "geometry": {"coordinates":[-82.48844099999999,27.928728],"type":"Point"}
}