{
  "type": "Feature",
  "properties": {
    "iso:country":"US",
    "sg:address":"9264 Neptunes Basin Ct",
    "sg:city":"Boca Raton",
    "sg:classifiers":[
        {
            "category":"Wholesale",
            "subcategory":"Construction Materials",
            "type":"Manufacturing & Wholesale Goods"
        },
        {
            "category":"Wholesale",
            "subcategory":"Durable Goods & Equipment",
            "type":"Manufacturing & Wholesale Goods"
        }
    ],
    "sg:phone":"+1 561 477 6184",
    "sg:postcode":"33434",
    "sg:province":"FL",
    "sg:tags":[
        "building",
        "heavy",
        "importer",
        "export"
    ],
    "wof:name":"Exodus Import & Export Intl",
    "wof:placetype":"venue"
},
  "geometry": {"coordinates":[-80.191458,26.379587],"type":"Point"}
}