{
  "type": "Feature",
  "properties": {
    "addr:full":"3535 Egret Dr Melbourne FL 32901",
    "addr:housenumber":"3535",
    "addr:postcode":"32901",
    "addr:street":"Egret Dr",
    "iso:country":"US",
    "sg:address":"3535 Egret Dr",
    "sg:city":"Melbourne",
    "sg:classifiers":[
        {
            "category":"Professional",
            "subcategory":"Business Services",
            "type":"Services"
        }
    ],
    "sg:phone":"+1 321 652 5122",
    "sg:postcode":"32901",
    "sg:province":"FL",
    "sg:tags":[
        "process",
        "server"
    ],
    "wof:name":"Rosalie D Villareal Prcss Srvr",
    "wof:placetype":"venue"
},
  "geometry": {"coordinates":[-80.63403700000001,28.053934],"type":"Point"}
}