{
  "type": "Feature",
  "properties": {
    "addr:full":"9771 W McNab Rd Fort Lauderdale FL 33321",
    "addr:housenumber":"9771",
    "addr:postcode":"33321",
    "addr:street":"W Mcnab Rd",
    "iso:country":"US",
    "sg:address":"9771 W McNab Rd",
    "sg:city":"Fort Lauderdale",
    "sg:classifiers":[
        {
            "category":"Professional",
            "subcategory":"Employment Agencies",
            "type":"Services"
        }
    ],
    "sg:phone":"+1 954 366 6685",
    "sg:postcode":"33321",
    "sg:province":"FL",
    "sg:tags":[
        "help",
        "supply"
    ],
    "wof:name":"Abundant Medical Staffing",
    "wof:placetype":"venue"
},
  "geometry": {"coordinates":[-80.284266,26.208244],"type":"Point"}
}