{
  "type": "Feature",
  "properties": {
    "addr:full":"2490 4th Ln Vero Beach FL 32962",
    "addr:housenumber":"2490",
    "addr:postcode":"32962",
    "addr:street":"4Th Ln",
    "iso:country":"US",
    "sg:address":"2490 4th Ln",
    "sg:city":"Vero Beach",
    "sg:classifiers":[
        {
            "category":"Professional",
            "subcategory":"Business Services",
            "type":"Services"
        }
    ],
    "sg:phone":"+1 772 564 0174",
    "sg:postcode":"32962",
    "sg:province":"FL",
    "wof:name":"Dunlop Limited",
    "wof:placetype":"venue"
},
  "geometry": {"coordinates":[-80.41005199999999,27.610392],"type":"Point"}
}