{
  "type": "Feature",
  "properties": {
    "addr:full":"8706 SW 129th Ter Miami FL 33176",
    "addr:housenumber":"8706",
    "addr:postcode":"33176",
    "addr:street":"Sw 129Th Ter",
    "iso:country":"US",
    "sg:address":"8706 SW 129th Ter",
    "sg:city":"Miami",
    "sg:classifiers":[
        {
            "category":"Building & Trades",
            "subcategory":"Construction",
            "type":"Services"
        }
    ],
    "sg:phone":"+1 305 252 0797",
    "sg:postcode":"33176",
    "sg:province":"FL",
    "sg:tags":[
        "carpentry",
        "contractor"
    ],
    "wof:name":"Woodwitch Inc",
    "wof:placetype":"venue"
},
  "geometry": {"coordinates":[-80.337265,25.649602],"type":"Point"}
}