{
  "type": "Feature",
  "properties": {
    "iso:country":"US",
    "sg:address":"1101 6th Ave W",
    "sg:city":"Bradenton",
    "sg:classifiers":[
        {
            "category":"Real Estate",
            "subcategory":"Real Estate Agent",
            "type":"Services"
        }
    ],
    "sg:phone":"+1 941 746 7404",
    "sg:postcode":"34205",
    "sg:province":"FL",
    "sg:tags":[
        "appraiser"
    ],
    "wof:name":"Niles Smyth Appraisal",
    "wof:placetype":"venue"
},
  "geometry": {"coordinates":[-82.57347900000001,27.494176],"type":"Point"}
}