{
  "type": "Feature",
  "properties": {
    "iso:country":"US",
    "sg:address":"5705 Satel Dr",
    "sg:city":"Orlando",
    "sg:classifiers":[
        {
            "category":"Building & Trades",
            "subcategory":"Construction",
            "type":"Services"
        },
        {
            "category":"Sports & Exercise",
            "subcategory":"Swimming Pool",
            "type":"Entertainment"
        }
    ],
    "sg:phone":"+1 407 647 4256",
    "sg:postcode":"32810",
    "sg:province":"FL",
    "wof:name":"Dirt Dobber Pool Plastering",
    "wof:placetype":"venue"
},
  "geometry": {"coordinates":[-81.40778400000001,28.615176],"type":"Point"}
}