{
  "type": "Feature",
  "properties": {
    "iso:country":"US",
    "sg:address":"1511 N Morgan St",
    "sg:city":"Tampa",
    "sg:classifiers":[
        {
            "category":"Professional",
            "subcategory":"Lawyer & Legal Services",
            "type":"Services"
        }
    ],
    "sg:phone":"+1 813 868 1145",
    "sg:postcode":"33602",
    "sg:province":"FL",
    "sg:tags":[
        "attorney"
    ],
    "wof:name":"Tanya P O'Connor Pa",
    "wof:placetype":"venue"
},
  "geometry": {"coordinates":[-82.457967,27.958288],"type":"Point"}
}