{
  "type": "Feature",
  "properties": {
    "iso:country":"US",
    "sg:address":"7661 Dundas Dr",
    "sg:city":"Orlando",
    "sg:classifiers":[
        {
            "category":"Professional",
            "subcategory":"Lawyer & Legal Services",
            "type":"Services"
        }
    ],
    "sg:phone":"+1 407 521 7280",
    "sg:postcode":"32818",
    "sg:province":"FL",
    "sg:tags":[
        "convention",
        "reporters-court"
    ],
    "wof:name":"Mason Chery Court Reporter",
    "wof:placetype":"venue"
},
  "geometry": {"coordinates":[-81.48793499999999,28.580782],"type":"Point"}
}