{
  "type": "Feature",
  "properties": {
    "addr:full":"8809 SE 66th Cir Trenton FL 32693",
    "addr:housenumber":"8809",
    "addr:postcode":"32693",
    "addr:street":"Se 66Th Cir",
    "iso:country":"US",
    "sg:address":"8809 SE 66th Cir",
    "sg:city":"Trenton",
    "sg:classifiers":[
        {
            "category":"Building & Trades",
            "subcategory":"Landscaping Services",
            "type":"Services"
        }
    ],
    "sg:phone":"+1 352 472 2825",
    "sg:postcode":"32693",
    "sg:province":"FL",
    "sg:tags":[
        "lawn",
        "maintenance",
        "grounds"
    ],
    "wof:name":"Summerwind Lawn Maintenance",
    "wof:placetype":"venue"
},
  "geometry": {"coordinates":[-82.696776,29.614411],"type":"Point"}
}