{
  "type": "Feature",
  "properties": {
    "addr:full":"3100 US Hwy 1 S St Augustine FL 32086",
    "addr:housenumber":"3100",
    "addr:postcode":"32086",
    "addr:street":"Us Hwy 1 S St",
    "iso:country":"US",
    "sg:address":"3100 US Hwy 1 S",
    "sg:city":"St Augustine",
    "sg:classifiers":[
        {
            "category":"Health Services",
            "subcategory":"Doctor",
            "type":"Services"
        }
    ],
    "sg:phone":"+1 904 797 2902",
    "sg:postcode":"32086",
    "sg:province":"FL",
    "sg:tags":[
        "physician",
        "surgeon"
    ],
    "wof:name":"St Augustine Speciality Group",
    "wof:placetype":"venue"
},
  "geometry": {"coordinates":[-81.322346,29.836451],"type":"Point"}
}