{
  "type": "Feature",
  "properties": {
    "iso:country":"US",
    "sg:address":"6601 SW 62nd Ct",
    "sg:city":"South Miami",
    "sg:classifiers":[
        {
            "category":"Government",
            "subcategory":"Office",
            "type":"Public Place"
        }
    ],
    "sg:phone":"+1 305 669 6971",
    "sg:postcode":"33143",
    "sg:province":"FL",
    "sg:tags":[
        "county",
        "program",
        "health"
    ],
    "wof:name":"Dade County Health Dept",
    "wof:placetype":"venue"
},
  "geometry": {"coordinates":[-80.294523,25.70768],"type":"Point"}
}