{
  "type": "Feature",
  "properties": {
    "iso:country":"US",
    "sg:address":"8235 NW 64th St Unit 3",
    "sg:city":"Miami",
    "sg:classifiers":[
        {
            "category":"Shopping",
            "subcategory":"Mobile Phones",
            "type":"Retail Goods"
        }
    ],
    "sg:phone":"+1 305 640 9837",
    "sg:postcode":"33166",
    "sg:province":"FL",
    "wof:name":"Cellular Dealers.Com",
    "wof:placetype":"venue"
},
  "geometry": {"coordinates":[-80.330614,25.831794],"type":"Point"}
}