{
  "type": "Feature",
  "properties": {
    "iso:country":"US",
    "sg:address":"2105 W Kyra Dr",
    "sg:city":"Tampa",
    "sg:classifiers":[
        {
            "category":"Home & Garden",
            "subcategory":"Building Materials",
            "type":"Retail Goods"
        }
    ],
    "sg:phone":"+1 813 968 8888",
    "sg:postcode":"33612",
    "sg:province":"FL",
    "sg:tags":[
        "glass",
        "window",
        "plate"
    ],
    "wof:name":"Window Tinting On Wheels",
    "wof:placetype":"venue"
},
  "geometry": {"coordinates":[-82.480969,28.05516],"type":"Point"}
}