{
  "type": "Feature",
  "properties": {
    "addr:full":"777 Brickell Ave Miami FL 33129",
    "addr:housenumber":"777",
    "addr:postcode":"33129",
    "addr:street":"Brickell Ave",
    "iso:country":"US",
    "sg:address":"777 Brickell Ave",
    "sg:city":"Miami",
    "sg:classifiers":[
        {
            "category":"Professional",
            "subcategory":"Employment Agencies",
            "type":"Services"
        }
    ],
    "sg:phone":"+1 305 579 9033",
    "sg:postcode":"33129",
    "sg:province":"FL",
    "sg:tags":[
        "personnel",
        "temporary"
    ],
    "wof:name":"Adecco Staffing",
    "wof:placetype":"venue"
},
  "geometry": {"coordinates":[-80.19045800000001,25.766838],"type":"Point"}
}