{
  "type": "Feature",
  "properties": {
    "iso:country":"US",
    "sg:address":"3221 NW 13th St",
    "sg:city":"Gainesville",
    "sg:classifiers":[
        {
            "category":"Professional",
            "subcategory":"Management & Consulting",
            "type":"Services"
        }
    ],
    "sg:phone":"+1 352 373 6785",
    "sg:postcode":"32609",
    "sg:province":"FL",
    "sg:tags":[
        "engineer"
    ],
    "wof:name":"Comtech Electronics",
    "wof:placetype":"venue"
},
  "geometry": {"coordinates":[-82.33898000000001,29.682879],"type":"Point"}
}