{
  "type": "Feature",
  "properties": {
    "addr:full":"204 62nd St NW Bradenton FL 34209",
    "addr:housenumber":"204",
    "addr:postcode":"34209",
    "addr:street":"62Nd St Nw",
    "iso:country":"US",
    "sg:address":"204 62nd St NW",
    "sg:city":"Bradenton",
    "sg:classifiers":[
        {
            "category":"Real Estate",
            "subcategory":"Real Estate Agent",
            "type":"Services"
        }
    ],
    "sg:phone":"+1 941 761 9898",
    "sg:postcode":"34209",
    "sg:province":"FL",
    "wof:name":"Mobile Homes",
    "wof:placetype":"venue"
},
  "geometry": {"coordinates":[-82.623453,27.502013],"type":"Point"}
}