{
  "type": "Feature",
  "properties": {
    "addr:full":"4857 Poseidon Pl Lake Worth FL 33463",
    "addr:housenumber":"4857",
    "addr:postcode":"33463",
    "addr:street":"Poseidon Pl",
    "iso:country":"US",
    "sg:address":"4857 Poseidon Pl",
    "sg:city":"Lake Worth",
    "sg:classifiers":[
        {
            "category":"Building & Trades",
            "subcategory":"Plumbing",
            "type":"Services"
        }
    ],
    "sg:phone":"+1 561 432 4259",
    "sg:postcode":"33463",
    "sg:province":"FL",
    "sg:tags":[
        "plumbing",
        "contractor"
    ],
    "wof:name":"Anthony Tharpe Plumbing Inc",
    "wof:placetype":"venue"
},
  "geometry": {"coordinates":[-80.116586,26.576324],"type":"Point"}
}