{
  "type": "Feature",
  "properties": {
    "addr:full":"417 W Tarpon Blvd NW Port Charlotte FL 33952",
    "addr:housenumber":"417",
    "addr:postcode":"33952",
    "addr:street":"W Tarpon Blvd Nw",
    "iso:country":"US",
    "sg:address":"417 W Tarpon Blvd NW",
    "sg:city":"Port Charlotte",
    "sg:classifiers":[
        {
            "category":"Local Transit",
            "type":"Transportation"
        }
    ],
    "sg:phone":"+1 941 743 5777",
    "sg:postcode":"33952",
    "sg:province":"FL",
    "sg:tags":[
        "passenger"
    ],
    "wof:name":"West Coast Limo & Car Service",
    "wof:placetype":"venue"
},
  "geometry": {"coordinates":[-82.116356,26.982423],"type":"Point"}
}