{
  "type": "Feature",
  "properties": {
    "addr:full":"2107 Airport Blvd Pensacola FL 32504",
    "addr:housenumber":"2107",
    "addr:postcode":"32504",
    "addr:street":"Airport Blvd",
    "iso:country":"US",
    "sg:address":"2107 Airport Blvd",
    "sg:city":"Pensacola",
    "sg:classifiers":[
        {
            "category":"Real Estate",
            "subcategory":"Real Estate Services",
            "type":"Services"
        }
    ],
    "sg:phone":"+1 850 478 4141",
    "sg:postcode":"32504",
    "sg:province":"FL",
    "sg:tags":[
        "buyer",
        "broker"
    ],
    "wof:name":"Simon Jan rl est",
    "wof:placetype":"venue"
},
  "geometry": {"coordinates":[-87.20461899999999,30.477283],"type":"Point"}
}