{
  "type": "Feature",
  "properties": {
    "addr:full":"3960 SW 58th Ct Miami FL 33155",
    "addr:housenumber":"3960",
    "addr:postcode":"33155",
    "addr:street":"Sw 58Th Ct",
    "iso:country":"US",
    "sg:address":"3960 SW 58th Ct",
    "sg:city":"Miami",
    "sg:classifiers":[
        {
            "category":"Shopping",
            "subcategory":"Clothing, Apparel, & Fashions",
            "type":"Retail Goods"
        }
    ],
    "sg:phone":"+1 305 668 1805",
    "sg:postcode":"33155",
    "sg:province":"FL",
    "sg:tags":[
        "alterations-clothing"
    ],
    "wof:name":"Gongoras Alterations",
    "wof:placetype":"venue"
},
  "geometry": {"coordinates":[-80.289794,25.7344],"type":"Point"}
}