{
  "type": "Feature",
  "properties": {
    "iso:country":"US",
    "sg:address":"1100 State Hwy 60",
    "sg:city":"Lake Wales",
    "sg:classifiers":[
        {
            "category":"Banks & Credit Unions",
            "subcategory":"Bank",
            "type":"Services"
        }
    ],
    "sg:phone":"+1 863 676 4906",
    "sg:postcode":"33853",
    "sg:province":"FL",
    "wof:name":"Bank Of America",
    "wof:placetype":"venue"
},
  "geometry": {"coordinates":[-81.609172,27.902623],"type":"Point"}
}