{
  "type": "Feature",
  "properties": {
    "addr:full":"6298 Co Rd 249 Lake Panasoffkee FL 33538",
    "addr:housenumber":"6298",
    "addr:postcode":"33538",
    "addr:street":"Co Rd 249",
    "iso:country":"US",
    "sg:address":"6298 Co Rd 249",
    "sg:city":"Lake Panasoffkee",
    "sg:classifiers":[
        {
            "category":"Building & Trades",
            "subcategory":"Construction",
            "type":"Services"
        }
    ],
    "sg:phone":"+1 352 748 4060",
    "sg:postcode":"33538",
    "sg:province":"FL",
    "sg:tags":[
        "house"
    ],
    "wof:name":"Saporito Construction Inc",
    "wof:placetype":"venue"
},
  "geometry": {"coordinates":[-82.205675,28.845999],"type":"Point"}
}