{
  "type": "Feature",
  "properties": {
    "iso:country":"US",
    "sg:address":"7211 NW 79th Ter",
    "sg:city":"Medley",
    "sg:classifiers":[
        {
            "category":"Home & Garden",
            "subcategory":"Building Materials",
            "type":"Retail Goods"
        },
        {
            "category":"Manufacturing",
            "subcategory":"Building Materials",
            "type":"Manufacturing & Wholesale Goods"
        }
    ],
    "sg:phone":"+1 305 805 7050",
    "sg:postcode":"33166",
    "sg:province":"FL",
    "sg:tags":[
        "shutter",
        "shutters-wholesale",
        "manufacturer"
    ],
    "wof:name":"Gurdian Hurricane Protection Products Inc",
    "wof:placetype":"venue"
},
  "geometry": {"coordinates":[-80.31449000000001,25.8457],"type":"Point"}
}