{
  "type": "Feature",
  "properties": {
    "iso:country":"US",
    "sg:address":"1313 S Missouri Ave",
    "sg:city":"Clearwater",
    "sg:classifiers":[
        {
            "category":"Professional",
            "subcategory":"Accounting & Tax Preparation",
            "type":"Services"
        }
    ],
    "sg:phone":"+1 727 447 1040",
    "sg:postcode":"33756",
    "sg:province":"FL",
    "sg:tags":[
        "return",
        "filing"
    ],
    "wof:name":"Mr Tax",
    "wof:placetype":"venue"
},
  "geometry": {"coordinates":[-82.78747199999999,27.950232],"type":"Point"}
}