{
  "type": "Feature",
  "properties": {
    "iso:country":"US",
    "sg:address":"2212 SE 17th St",
    "sg:city":"Fort Lauderdale",
    "sg:classifiers":[
        {
            "category":"Professional",
            "type":"Services"
        }
    ],
    "sg:phone":"+1 954 525 2075",
    "sg:postcode":"33316",
    "sg:province":"FL",
    "sg:tags":[
        "establishment"
    ],
    "wof:name":"Special Moments",
    "wof:placetype":"venue"
},
  "geometry": {"coordinates":[-80.116767,26.100706],"type":"Point"}
}