{
  "type": "Feature",
  "properties": {
    "addr:full":"2200 E Fowler Ave Tampa FL 33612",
    "addr:housenumber":"2200",
    "addr:postcode":"33612",
    "addr:street":"E Fowler Ave",
    "iso:country":"US",
    "sg:address":"2200 E Fowler Ave",
    "sg:city":"Tampa",
    "sg:classifiers":[
        {
            "category":"Shopping",
            "type":"Retail Goods"
        }
    ],
    "sg:phone":"+1 813 977 3300",
    "sg:postcode":"33612",
    "sg:province":"FL",
    "sg:tags":[
        "telephone",
        "cellular"
    ],
    "wof:name":"Mobile Soulution",
    "wof:placetype":"venue"
},
  "geometry": {"coordinates":[-82.430588,28.054496],"type":"Point"}
}