{
  "type": "Feature",
  "properties": {
    "addr:full":"431 Lighthouse Landing St Satellite Beach FL 32937",
    "addr:housenumber":"431",
    "addr:postcode":"32937",
    "addr:street":"Lighthouse Landing St",
    "iso:country":"US",
    "sg:address":"431 Lighthouse Landing St",
    "sg:city":"Satellite Beach",
    "sg:classifiers":[
        {
            "category":"Shopping",
            "subcategory":"Clothing, Apparel, & Fashions",
            "type":"Retail Goods"
        }
    ],
    "sg:phone":"+1 321 779 9130",
    "sg:postcode":"32937",
    "sg:province":"FL",
    "wof:name":"Whats Your Style",
    "wof:placetype":"venue"
},
  "geometry": {"coordinates":[-80.610606,28.205442],"type":"Point"}
}