{
  "type": "Feature",
  "properties": {
    "iso:country":"US",
    "sg:address":"2071 Emerson St",
    "sg:city":"Jacksonville",
    "sg:classifiers":[
        {
            "category":"Professional",
            "subcategory":"Business Services",
            "type":"Services"
        },
        {
            "category":"Wholesale",
            "subcategory":"Electrical",
            "type":"Manufacturing & Wholesale Goods"
        }
    ],
    "sg:phone":"+1 904 399 0424",
    "sg:postcode":"32207",
    "sg:province":"FL",
    "sg:tags":[
        "recording",
        "cassette",
        "audio",
        "studio"
    ],
    "wof:name":"Warehouse Studio Sales",
    "wof:placetype":"venue"
},
  "geometry": {"coordinates":[-81.639842,30.284926],"type":"Point"}
}