{
  "type": "Feature",
  "properties": {
    "iso:country":"US",
    "sg:address":"18276 Deep Passage Ln",
    "sg:city":"Fort Myers Beach",
    "sg:classifiers":[
        {
            "category":"Real Estate",
            "subcategory":"Architect",
            "type":"Services"
        }
    ],
    "sg:phone":"+1 239 454 6400",
    "sg:postcode":"33931",
    "sg:province":"FL",
    "wof:name":"Williamson R D & Associates Inc",
    "wof:placetype":"venue"
},
  "geometry": {"coordinates":[-81.954803,26.4765],"type":"Point"}
}