{
  "type": "Feature",
  "properties": {
    "addr:full":"1895 SW 3rd Ave Miami FL 33129",
    "addr:housenumber":"1895",
    "addr:postcode":"33129",
    "addr:street":"Sw 3Rd Ave",
    "iso:country":"US",
    "sg:address":"1895 SW 3rd Ave",
    "sg:city":"Miami",
    "sg:classifiers":[
        {
            "category":"Banks & Credit Unions",
            "subcategory":"Financial Services",
            "type":"Services"
        },
        {
            "category":"Government",
            "subcategory":"Office",
            "type":"Public Place"
        }
    ],
    "sg:phone":"+1 305 858 6006",
    "sg:postcode":"33129",
    "sg:province":"FL",
    "sg:tags":[
        "sharing",
        "profit",
        "pension",
        "village",
        "township",
        "government-city",
        "plan"
    ],
    "wof:name":"City of Miami Fire Fighters' and Police Officers' Retirement Trust",
    "wof:placetype":"venue"
},
  "geometry": {"coordinates":[-80.20222,25.759415],"type":"Point"}
}