{
  "type": "Feature",
  "properties": {
    "iso:country":"US",
    "sg:address":"9345 NW 50th Doral Cir N",
    "sg:city":"Miami",
    "sg:classifiers":[
        {
            "category":"Wholesale",
            "subcategory":"Durable Goods & Equipment",
            "type":"Manufacturing & Wholesale Goods"
        }
    ],
    "sg:phone":"+1 305 592 3099",
    "sg:postcode":"33178",
    "sg:province":"FL",
    "wof:name":"Beverage Equipment Supplies",
    "wof:placetype":"venue"
},
  "geometry": {"coordinates":[-80.348096,25.819536],"type":"Point"}
}