{
  "type": "Feature",
  "properties": {
    "addr:full":"5447 NW 24th St Margate FL 33063",
    "addr:housenumber":"5447",
    "addr:postcode":"33063",
    "addr:street":"Nw 24Th St Margate",
    "iso:country":"US",
    "sg:address":"5447 NW 24th St",
    "sg:city":"Margate",
    "sg:classifiers":[
        {
            "category":"Manufacturing",
            "subcategory":"Printing",
            "type":"Manufacturing & Wholesale Goods"
        }
    ],
    "sg:phone":"+1 954 986 1254",
    "sg:postcode":"33063",
    "sg:province":"FL",
    "sg:tags":[
        "label"
    ],
    "wof:name":"Spectrum Labels",
    "wof:placetype":"venue"
},
  "geometry": {"coordinates":[-80.200402,26.257138],"type":"Point"}
}