{
  "type": "Feature",
  "properties": {
    "iso:country":"US",
    "sg:address":"1155 Anchor Pt",
    "sg:city":"Delray Beach",
    "sg:classifiers":[
        {
            "category":"Health Services",
            "subcategory":"Doctor",
            "type":"Services"
        }
    ],
    "sg:phone":"+1 954 596 9091",
    "sg:postcode":"33444",
    "sg:province":"FL",
    "sg:tags":[
        "physician",
        "surgeon"
    ],
    "wof:name":"Neurological Pain Medicine",
    "wof:placetype":"venue"
},
  "geometry": {"coordinates":[-80.08269,26.471082],"type":"Point"}
}