{
  "type": "Feature",
  "properties": {
    "addr:full":"3275 66th St N St Petersburg FL 33710",
    "addr:housenumber":"3275",
    "addr:postcode":"33710",
    "addr:street":"66Th St N",
    "iso:country":"US",
    "sg:address":"3275 66th St N",
    "sg:city":"St Petersburg",
    "sg:classifiers":[
        {
            "category":"Health Services",
            "subcategory":"Doctor",
            "type":"Services"
        }
    ],
    "sg:phone":"+1 727 343 2568",
    "sg:postcode":"33710",
    "sg:province":"FL",
    "sg:tags":[
        "physician",
        "surgeon",
        "medical"
    ],
    "wof:name":"Meena Jain MD",
    "wof:placetype":"venue"
},
  "geometry": {"coordinates":[-82.72849100000001,27.802153],"type":"Point"}
}