{
  "type": "Feature",
  "properties": {
    "addr:full":"13760 NW 19th Ave Opa Locka FL 33054",
    "addr:housenumber":"13760",
    "addr:postcode":"33054",
    "addr:street":"Nw 19Th Ave;Locka",
    "iso:country":"US",
    "sg:address":"13760 NW 19th Ave",
    "sg:city":"Opa Locka",
    "sg:classifiers":[
        {
            "category":"Retail",
            "subcategory":"Repair Shop",
            "type":"Services"
        }
    ],
    "sg:phone":"+1 305 688 3484",
    "sg:postcode":"33054",
    "sg:province":"FL",
    "sg:tags":[
        "welding"
    ],
    "wof:name":"Martin Pierra",
    "wof:placetype":"venue"
},
  "geometry": {"coordinates":[-80.23159800000001,25.89963],"type":"Point"}
}