{
  "type": "Feature",
  "properties": {
    "addr:full":"5250 E Bay Dr Clearwater FL 33764",
    "addr:housenumber":"5250",
    "addr:postcode":"33764",
    "addr:street":"E Bay Dr",
    "iso:country":"US",
    "sg:address":"5250 E Bay Dr",
    "sg:city":"Clearwater",
    "sg:classifiers":[
        {
            "category":"Banks & Credit Unions",
            "subcategory":"Bank",
            "type":"Services"
        }
    ],
    "sg:phone":"+1 727 538 4445",
    "sg:postcode":"33764",
    "sg:province":"FL",
    "wof:name":"Wachovia Bank",
    "wof:placetype":"venue"
},
  "geometry": {"coordinates":[-82.72972,27.916304],"type":"Point"}
}