{
  "type": "Feature",
  "properties": {
    "addr:full":"4155 NE 35th St Ocala FL 34479",
    "addr:housenumber":"4155",
    "addr:postcode":"34479",
    "addr:street":"Ne 35Th St",
    "iso:country":"US",
    "sg:address":"4155 NE 35th St",
    "sg:city":"Ocala",
    "sg:classifiers":[
        {
            "category":"Utilities",
            "subcategory":"Electric",
            "type":"Services"
        }
    ],
    "sg:phone":"+1 352 236 4200",
    "sg:postcode":"34479",
    "sg:province":"FL",
    "sg:tags":[
        "company"
    ],
    "wof:name":"Seminole Electric Co-Op Inc",
    "wof:placetype":"venue"
},
  "geometry": {"coordinates":[-82.07556,29.223014],"type":"Point"}
}