{
  "type": "Feature",
  "properties": {
    "addr:full":"6100 SW 90th Ct Miami FL 33173",
    "addr:housenumber":"6100",
    "addr:postcode":"33173",
    "addr:street":"Sw 90Th Ct",
    "iso:country":"US",
    "sg:address":"6100 SW 90th Ct",
    "sg:city":"Miami",
    "sg:classifiers":[
        {
            "category":"Building & Trades",
            "subcategory":"Locksmith",
            "type":"Services"
        }
    ],
    "sg:phone":"+1 305 423 8328",
    "sg:postcode":"33173",
    "sg:province":"FL",
    "sg:tags":[
        "key"
    ],
    "wof:name":"24 Hour Emergency Locksmith",
    "wof:placetype":"venue"
},
  "geometry": {"coordinates":[-80.340917,25.71135],"type":"Point"}
}