{
  "type": "Feature",
  "properties": {
    "addr:full":"607 Fannich Ct Leesburg FL 34788",
    "addr:housenumber":"607",
    "addr:postcode":"34788",
    "addr:street":"Fannich Ct",
    "iso:country":"US",
    "sg:address":"607 Fannich Ct",
    "sg:city":"Leesburg",
    "sg:classifiers":[
        {
            "category":"Building & Trades",
            "subcategory":"Construction",
            "type":"Services"
        }
    ],
    "sg:phone":"+1 352 343 3621",
    "sg:postcode":"34788",
    "sg:province":"FL",
    "sg:tags":[
        "house"
    ],
    "wof:name":"Aril Repairs & Renovation",
    "wof:placetype":"venue"
},
  "geometry": {"coordinates":[-81.77544,28.851874],"type":"Point"}
}