{
  "type": "Feature",
  "properties": {
    "iso:country":"US",
    "sg:address":"4645 S Semoran Blvd",
    "sg:city":"Orlando",
    "sg:classifiers":[
        {
            "category":"Restaurant",
            "type":"Food & Drink"
        }
    ],
    "sg:menulink":"http://www.allmenus.com/fl/orlando/9840-don-pablos/menu/",
    "sg:phone":"+1 407 208 0801",
    "sg:postcode":"32822",
    "sg:province":"FL",
    "sg:tags":[
        "sandwich",
        "mexican",
        "salad",
        "soup",
        "american",
        "wrap",
        "tex-mex"
    ],
    "wof:name":"Don Pablo's",
    "wof:placetype":"venue"
},
  "geometry": {"coordinates":[-81.31011700000001,28.494353],"type":"Point"}
}