{
  "type": "Feature",
  "properties": {
    "iso:country":"US",
    "sg:address":"230 Royal Palm Beach Blvd",
    "sg:city":"Royal Palm Beach",
    "sg:classifiers":[
        {
            "category":"Professional",
            "subcategory":"Lawyer & Legal Services",
            "type":"Services"
        }
    ],
    "sg:phone":"+1 561 333 1522",
    "sg:postcode":"33411",
    "sg:province":"FL",
    "sg:tags":[
        "attorney"
    ],
    "wof:name":"Gardner Constant",
    "wof:placetype":"venue"
},
  "geometry": {"coordinates":[-80.230037,26.683352],"type":"Point"}
}