{
  "type": "Feature",
  "properties": {
    "addr:full":"3030 Waterfield Ln Lakeland FL 33803",
    "addr:housenumber":"3030",
    "addr:postcode":"33803",
    "addr:street":"Waterfield Ln",
    "iso:country":"US",
    "sg:address":"3030 Waterfield Ln",
    "sg:city":"Lakeland",
    "sg:classifiers":[
        {
            "category":"Home & Garden",
            "subcategory":"Household Appliances",
            "type":"Retail Goods"
        },
        {
            "category":"Building & Trades",
            "subcategory":"Cleaning & Sanitation",
            "type":"Services"
        },
        {
            "category":"Building & Trades",
            "subcategory":"Construction",
            "type":"Services"
        }
    ],
    "sg:phone":"+1 863 667 0998",
    "sg:postcode":"33803",
    "sg:province":"FL",
    "sg:tags":[
        "site-clean-up",
        "floor",
        "waxing",
        "contractor",
        "window",
        "cleaning-industrial",
        "vacuum",
        "polishing",
        "janitorial"
    ],
    "sg:website":"https://smclean.custhelp.com/cgi-bin/smclean.cfg/php/enduser/doc_serve.php?2=BSYellowPages09",
    "wof:name":"ServiceMaster Clean",
    "wof:placetype":"venue"
},
  "geometry": {"coordinates":[-81.898307,28.000355],"type":"Point"}
}