{
  "type": "Feature",
  "properties": {
    "addr:full":"1162 Athlone Way Ormond Beach FL 32174",
    "addr:housenumber":"1162",
    "addr:postcode":"32174",
    "addr:street":"Athlone Way",
    "iso:country":"US",
    "sg:address":"1162 Athlone Way",
    "sg:city":"Ormond Beach",
    "sg:classifiers":[
        {
            "category":"Organizations",
            "subcategory":"Community Association",
            "type":"Services"
        }
    ],
    "sg:phone":"+1 386 299 5305",
    "sg:postcode":"32174",
    "sg:province":"FL",
    "sg:tags":[
        "club"
    ],
    "wof:name":"Democractic Club Of Halifax",
    "wof:placetype":"venue"
},
  "geometry": {"coordinates":[-81.139985,29.391647],"type":"Point"}
}