{
  "type": "Feature",
  "properties": {
    "addr:full":"8354 Baymeadows Rd Jacksonville FL 32256",
    "addr:housenumber":"8354",
    "addr:postcode":"32256",
    "addr:street":"Baymeadows Rd",
    "iso:country":"US",
    "sg:address":"8354 Baymeadows Rd",
    "sg:city":"Jacksonville",
    "sg:classifiers":[
        {
            "category":"Health Services",
            "subcategory":"Doctor",
            "type":"Services"
        }
    ],
    "sg:phone":"+1 904 737 7436",
    "sg:postcode":"32256",
    "sg:province":"FL",
    "sg:tags":[
        "dentist"
    ],
    "wof:name":"Deerwood Dental Ctr",
    "wof:placetype":"venue"
},
  "geometry": {"coordinates":[-81.58310299999999,30.220701],"type":"Point"}
}