{
  "type": "Feature",
  "properties": {
    "addr:full":"117 NW 42nd Ave Miami FL 33126",
    "addr:housenumber":"117",
    "addr:postcode":"33126",
    "addr:street":"Nw 42Nd Ave",
    "iso:country":"US",
    "sg:address":"117 NW 42nd Ave",
    "sg:city":"Miami",
    "sg:classifiers":[
        {
            "category":"Professional",
            "subcategory":"Management & Consulting",
            "type":"Services"
        },
        {
            "category":"Banks & Credit Unions",
            "subcategory":"Investment Brokerage",
            "type":"Services"
        },
        {
            "category":"Banks & Credit Unions",
            "subcategory":"Financial Services",
            "type":"Services"
        }
    ],
    "sg:phone":"+1 305 642 1057",
    "sg:postcode":"33126",
    "sg:province":"FL",
    "sg:tags":[
        "advisory",
        "financing",
        "planner",
        "consultant",
        "planning"
    ],
    "wof:name":"Austro Financial Services",
    "wof:placetype":"venue"
},
  "geometry": {"coordinates":[-80.26364599999999,25.772718],"type":"Point"}
}