{
  "type": "Feature",
  "properties": {
    "addr:full":"5645 NW 66th Ave Pompano Beach FL 33067",
    "addr:housenumber":"5645",
    "addr:postcode":"33067",
    "addr:street":"Nw 66Th Ave",
    "iso:country":"US",
    "sg:address":"5645 NW 66th Ave",
    "sg:city":"Pompano Beach",
    "sg:classifiers":[
        {
            "category":"Professional",
            "subcategory":"Management & Consulting",
            "type":"Services"
        }
    ],
    "sg:phone":"+1 954 344 0548",
    "sg:postcode":"33067",
    "sg:province":"FL",
    "wof:name":"Paul Rushfield Inc",
    "wof:placetype":"venue"
},
  "geometry": {"coordinates":[-80.21738999999999,26.298378],"type":"Point"}
}