{
  "type": "Feature",
  "properties": {
    "iso:country":"US",
    "sg:address":"1310 Glen Laura Rd",
    "sg:city":"Jacksonville",
    "sg:classifiers":[
        {
            "category":"Professional",
            "subcategory":"Engineering",
            "type":"Services"
        }
    ],
    "sg:phone":"+1 904 425 6617",
    "sg:postcode":"32205",
    "sg:province":"FL",
    "sg:tags":[
        "engineer"
    ],
    "wof:name":"Southern Engineering Svc",
    "wof:placetype":"venue"
},
  "geometry": {"coordinates":[-81.72352600000001,30.299943],"type":"Point"}
}