{
  "type": "Feature",
  "properties": {
    "iso:country":"US",
    "sg:address":"101 N Scenic Hwy",
    "sg:city":"Frostproof",
    "sg:classifiers":[
        {
            "category":"Autos & Motor Vehicles",
            "subcategory":"Fuel & Gas Station",
            "type":"Retail Goods"
        }
    ],
    "sg:phone":"+1 863 635 7965",
    "sg:postcode":"33843",
    "sg:province":"FL",
    "sg:tags":[
        "oil"
    ],
    "wof:name":"David Keen's Auto Repair",
    "wof:placetype":"venue"
},
  "geometry": {"coordinates":[-81.530562,27.746018],"type":"Point"}
}