{
  "type": "Feature",
  "properties": {
    "iso:country":"US",
    "sg:address":"1525 Wyncove Dr",
    "sg:city":"Vero Beach",
    "sg:classifiers":[
        {
            "category":"Arts & Performance",
            "subcategory":"Theater",
            "type":"Entertainment"
        }
    ],
    "sg:phone":"+1 772 234 8611",
    "sg:postcode":"32963",
    "sg:province":"FL",
    "sg:tags":[
        "band",
        "orchestra"
    ],
    "wof:name":"Atlantic Classical Orchestra",
    "wof:placetype":"venue"
},
  "geometry": {"coordinates":[-80.344905,27.612224],"type":"Point"}
}