{
  "type": "Feature",
  "properties": {
    "iso:country":"US",
    "sg:address":"5707 Stewart St",
    "sg:city":"Milton",
    "sg:classifiers":[
        {
            "category":"Place Of Worship",
            "subcategory":"Church",
            "type":"Public Place"
        },
        {
            "category":"Place Of Worship",
            "type":"Public Place"
        }
    ],
    "sg:phone":"+1 850 981 9000",
    "sg:postcode":"32570",
    "sg:province":"FL",
    "sg:tags":[
        "churches-interdenominational",
        "churches-various",
        "denomination"
    ],
    "wof:name":"Word Alive Christian Church",
    "wof:placetype":"venue"
},
  "geometry": {"coordinates":[-87.043239,30.641911],"type":"Point"}
}