{
  "type": "Feature",
  "properties": {
    "addr:full":"229 Whitcomb Dr Geneva FL 32732",
    "addr:housenumber":"229",
    "addr:postcode":"32732",
    "addr:street":"Whitcomb Dr",
    "iso:country":"US",
    "sg:address":"229 Whitcomb Dr",
    "sg:city":"Geneva",
    "sg:classifiers":[
        {
            "category":"Shopping",
            "subcategory":"Computers & Home Electronics",
            "type":"Retail Goods"
        }
    ],
    "sg:phone":"+1 407 349 3193",
    "sg:postcode":"32732",
    "sg:province":"FL",
    "wof:name":"Paradigm Computers Inc",
    "wof:placetype":"venue"
},
  "geometry": {"coordinates":[-81.084278,28.743294],"type":"Point"}
}