{
  "type": "Feature",
  "properties": {
    "iso:country":"US",
    "sg:address":"6010 N Ocean Blvd",
    "sg:city":"Boynton Beach",
    "sg:classifiers":[
        {
            "category":"Professional",
            "subcategory":"Lawyer & Legal Services",
            "type":"Services"
        }
    ],
    "sg:phone":"+1 561 732 6286",
    "sg:postcode":"33435",
    "sg:province":"FL",
    "sg:tags":[
        "attorney"
    ],
    "wof:name":"Leonard Brand",
    "wof:placetype":"venue"
},
  "geometry": {"coordinates":[-80.05009200000001,26.518611],"type":"Point"}
}