{
  "type": "Feature",
  "properties": {
    "addr:full":"7748 Pineapple Dr Orlando FL 32835",
    "addr:housenumber":"7748",
    "addr:postcode":"32835",
    "addr:street":"Pineapple Dr",
    "iso:country":"US",
    "sg:address":"7748 Pineapple Dr",
    "sg:city":"Orlando",
    "sg:classifiers":[
        {
            "category":"Building & Trades",
            "subcategory":"Construction",
            "type":"Services"
        }
    ],
    "sg:phone":"+1 407 298 5315",
    "sg:postcode":"32835",
    "sg:province":"FL",
    "sg:tags":[
        "contractor"
    ],
    "wof:name":"Donald A Mills Jr",
    "wof:placetype":"venue"
},
  "geometry": {"coordinates":[-81.490246,28.534085],"type":"Point"}
}