{
  "type": "Feature",
  "properties": {
    "addr:full":"924 Oakview Rd Tarpon Springs FL 34689",
    "addr:housenumber":"924",
    "addr:postcode":"34689",
    "addr:street":"Oakview Rd",
    "iso:country":"US",
    "sg:address":"924 Oakview Rd",
    "sg:city":"Tarpon Springs",
    "sg:classifiers":[
        {
            "category":"Insurance",
            "subcategory":"Insurance Agent",
            "type":"Services"
        }
    ],
    "sg:phone":"+1 813 872 9993",
    "sg:postcode":"34689",
    "sg:province":"FL",
    "wof:name":"A Plus Affordable Life Ins",
    "wof:placetype":"venue"
},
  "geometry": {"coordinates":[-82.764939,28.138187],"type":"Point"}
}