{
  "type": "Feature",
  "properties": {
    "addr:full":"2454 N University Dr Fort Lauderdale FL 33322",
    "addr:housenumber":"2454",
    "addr:postcode":"33322",
    "addr:street":"N University Dr",
    "iso:country":"US",
    "sg:address":"2454 N University Dr",
    "sg:city":"Fort Lauderdale",
    "sg:classifiers":[
        {
            "category":"Restaurant",
            "type":"Food & Drink"
        }
    ],
    "sg:menulink":"http://www.allmenus.com/fl/plantation/97276-ihop/menu/",
    "sg:phone":"+1 954 749 4545",
    "sg:postcode":"33322",
    "sg:province":"FL",
    "sg:tags":[
        "sandwich",
        "salad",
        "burger",
        "soup",
        "american",
        "steakhouse",
        "wrap"
    ],
    "wof:name":"IHOP",
    "wof:placetype":"venue"
},
  "geometry": {"coordinates":[-80.257097,26.155223],"type":"Point"}
}