{
  "type": "Feature",
  "properties": {
    "addr:full":"184 Treemonte Dr Orange City FL 32763",
    "addr:housenumber":"184",
    "addr:postcode":"32763",
    "addr:street":"Treemonte Dr",
    "iso:country":"US",
    "sg:address":"184 Treemonte Dr",
    "sg:city":"Orange City",
    "sg:classifiers":[
        {
            "category":"Building & Trades",
            "subcategory":"Construction",
            "type":"Services"
        }
    ],
    "sg:phone":"+1 386 775 0478",
    "sg:postcode":"32763",
    "sg:province":"FL",
    "sg:tags":[
        "contractor"
    ],
    "wof:name":"Mc Neil White Builders Inc",
    "wof:placetype":"venue"
},
  "geometry": {"coordinates":[-81.29781199999999,28.918616],"type":"Point"}
}