{
  "type": "Feature",
  "properties": {
    "iso:country":"US",
    "sg:address":"489 Sara Ave",
    "sg:city":"Mary Esther",
    "sg:classifiers":[
        {
            "category":"Building & Trades",
            "subcategory":"Plumbing",
            "type":"Services"
        }
    ],
    "sg:phone":"+1 850 598 0390",
    "sg:postcode":"32569",
    "sg:province":"FL",
    "sg:tags":[
        "plumbing",
        "contractor"
    ],
    "wof:name":"Walter F Sullivan Plumbing",
    "wof:placetype":"venue"
},
  "geometry": {"coordinates":[-86.762663,30.414818],"type":"Point"}
}