{
  "type": "Feature",
  "properties": {
    "iso:country":"US",
    "sg:address":"2204 Stone Cross Cir",
    "sg:city":"Orlando",
    "sg:classifiers":[
        {
            "category":"Transit Center",
            "subcategory":"Freight",
            "type":"Transportation"
        },
        {
            "category":"Freight",
            "type":"Transportation"
        }
    ],
    "sg:phone":"+1 407 493 0258",
    "sg:postcode":"32828",
    "sg:province":"FL",
    "sg:tags":[
        "trucking-motor",
        "trucking"
    ],
    "wof:name":"Dockwise Operations",
    "wof:placetype":"venue"
},
  "geometry": {"coordinates":[-81.189277,28.524579],"type":"Point"}
}