{
  "type": "Feature",
  "properties": {
    "addr:full":"1009 Capital Cir NW Tallahassee FL 32304",
    "addr:housenumber":"1009",
    "addr:postcode":"32304",
    "addr:street":"Capital Cir Nw",
    "iso:country":"US",
    "sg:address":"1009 Capital Cir NW",
    "sg:city":"Tallahassee",
    "sg:classifiers":[
        {
            "category":"Wholesale",
            "subcategory":"Metals & Minerals",
            "type":"Manufacturing & Wholesale Goods"
        }
    ],
    "sg:phone":"+1 850 576 0777",
    "sg:postcode":"32304",
    "sg:province":"FL",
    "sg:tags":[
        "center"
    ],
    "wof:name":"Ashley Aluminum LLC",
    "wof:placetype":"venue"
},
  "geometry": {"coordinates":[-84.35888199999999,30.451156],"type":"Point"}
}