{
  "type": "Feature",
  "properties": {
    "iso:country":"US",
    "sg:address":"1307 E 17th Ave",
    "sg:city":"Tampa",
    "sg:classifiers":[
        {
            "category":"Manufacturing",
            "subcategory":"Tobacco Products",
            "type":"Manufacturing & Wholesale Goods"
        }
    ],
    "sg:phone":"+1 813 526 4450",
    "sg:postcode":"33605",
    "sg:province":"FL",
    "sg:tags":[
        "cigarette",
        "cigar",
        "tobacco-wholesale",
        "manufacturer"
    ],
    "wof:name":"The Empire Of Cigars Inc",
    "wof:placetype":"venue"
},
  "geometry": {"coordinates":[-82.445424,27.967609],"type":"Point"}
}