{
  "type": "Feature",
  "properties": {
    "iso:country":"US",
    "sg:address":"3111 W Glen St",
    "sg:city":"Lecanto",
    "sg:classifiers":[
        {
            "category":"Ferry",
            "type":"Transportation"
        }
    ],
    "sg:phone":"+1 352 628 6390",
    "sg:postcode":"34461",
    "sg:province":"FL",
    "sg:tags":[
        "water",
        "passenger"
    ],
    "wof:name":"A Better Chance",
    "wof:placetype":"venue"
},
  "geometry": {"coordinates":[-82.485564,28.784432],"type":"Point"}
}