{
  "type": "Feature",
  "properties": {
    "addr:full":"800 Virginia Ave Fort Pierce FL 34982",
    "addr:housenumber":"800",
    "addr:postcode":"34982",
    "addr:street":"Virginia Ave",
    "iso:country":"US",
    "sg:address":"800 Virginia Ave",
    "sg:city":"Fort Pierce",
    "sg:classifiers":[
        {
            "category":"Organizations",
            "subcategory":"Religious Organization",
            "type":"Services"
        }
    ],
    "sg:phone":"+1 772 460 7171",
    "sg:postcode":"34982",
    "sg:province":"FL",
    "sg:tags":[
        "church"
    ],
    "wof:name":"Church Of God By Faith",
    "wof:placetype":"venue"
},
  "geometry": {"coordinates":[-80.330968,27.425468],"type":"Point"}
}