{
  "type": "Feature",
  "properties": {
    "iso:country":"US",
    "sg:address":"2304 Guy N Verger Blvd",
    "sg:city":"Tampa",
    "sg:classifiers":[
        {
            "category":"Education",
            "subcategory":"Special Training",
            "type":"Public Place"
        }
    ],
    "sg:phone":"+1 813 248 5091",
    "sg:postcode":"33605",
    "sg:province":"FL",
    "sg:tags":[
        "delinquent",
        "for",
        "marine",
        "bo",
        "program",
        "technology"
    ],
    "wof:name":"Tampa Marine Institute",
    "wof:placetype":"venue"
},
  "geometry": {"coordinates":[-82.434318,27.926834],"type":"Point"}
}