{
  "type": "Feature",
  "properties": {
    "addr:full":"132 SE 11th Ave Pompano Beach FL 33060",
    "addr:housenumber":"132",
    "addr:postcode":"33060",
    "addr:street":"Se 11Th Ave",
    "iso:country":"US",
    "sg:address":"132 SE 11th Ave",
    "sg:city":"Pompano Beach",
    "sg:classifiers":[
        {
            "category":"Social Services",
            "subcategory":"Child Care",
            "type":"Services"
        }
    ],
    "sg:phone":"+1 954 786 1007",
    "sg:postcode":"33060",
    "sg:province":"FL",
    "sg:tags":[
        "day"
    ],
    "wof:name":"Precious Moments Preschool",
    "wof:placetype":"venue"
},
  "geometry": {"coordinates":[-80.112443,26.230309],"type":"Point"}
}