{
  "type": "Feature",
  "properties": {
    "addr:full":"12194 Antibes St Jacksonville FL 32224",
    "addr:postcode":"12194;32224",
    "addr:street":"St",
    "iso:country":"US",
    "sg:address":"12194 Antibes St",
    "sg:city":"Jacksonville",
    "sg:classifiers":[
        {
            "category":"Home & Garden",
            "subcategory":"Hardware",
            "type":"Retail Goods"
        }
    ],
    "sg:phone":"+1 904 641 4445",
    "sg:postcode":"32224",
    "sg:province":"FL",
    "sg:tags":[
        "merchandise"
    ],
    "wof:name":"Rent Works",
    "wof:placetype":"venue"
},
  "geometry": {"coordinates":[-81.495306,30.285263],"type":"Point"}
}