{
  "type": "Feature",
  "properties": {
    "addr:full":"4215 Palm Forest Dr S Delray Beach FL 33445",
    "addr:housenumber":"4215",
    "addr:postcode":"33445",
    "addr:street":"Palm Forest Dr S",
    "iso:country":"US",
    "sg:address":"4215 Palm Forest Dr S",
    "sg:city":"Delray Beach",
    "sg:classifiers":[
        {
            "category":"Professional",
            "subcategory":"Accounting & Tax Preparation",
            "type":"Services"
        }
    ],
    "sg:phone":"+1 561 865 0310",
    "sg:postcode":"33445",
    "sg:province":"FL",
    "wof:name":"Accounting Services Plus",
    "wof:placetype":"venue"
},
  "geometry": {"coordinates":[-80.117529,26.440323],"type":"Point"}
}