{
  "type": "Feature",
  "properties": {
    "iso:country":"US",
    "sg:address":"2932 NW 72nd Ave",
    "sg:city":"Miami",
    "sg:classifiers":[
        {
            "category":"Shopping",
            "subcategory":"Beauty & Cosmetics",
            "type":"Retail Goods"
        }
    ],
    "sg:phone":"+1 786 464 1496",
    "sg:postcode":"33122",
    "sg:province":"FL",
    "sg:tags":[
        "perfume",
        "salons-equipment",
        "supply"
    ],
    "wof:name":"La Casa Del Perfume",
    "wof:placetype":"venue"
},
  "geometry": {"coordinates":[-80.31303,25.798191],"type":"Point"}
}