{
  "type": "Feature",
  "properties": {
    "addr:full":"1768 N University Dr Pembroke Pines FL 33024",
    "addr:housenumber":"1768",
    "addr:postcode":"33024",
    "addr:street":"N University Dr",
    "iso:country":"US",
    "sg:address":"1768 N University Dr",
    "sg:city":"Pembroke Pines",
    "sg:classifiers":[
        {
            "category":"Restaurant",
            "type":"Food & Drink"
        }
    ],
    "sg:phone":"+1 954 538 0409",
    "sg:postcode":"33024",
    "sg:province":"FL",
    "wof:name":"Tandoor Indian Pakistani Halal",
    "wof:placetype":"venue"
},
  "geometry": {"coordinates":[-80.248681,26.024312],"type":"Point"}
}