{
  "type": "Feature",
  "properties": {
    "iso:country":"US",
    "sg:address":"2995 Highland Lakes Dr",
    "sg:city":"Deltona",
    "sg:classifiers":[
        {
            "category":"Building & Trades",
            "subcategory":"Electrical",
            "type":"Services"
        }
    ],
    "sg:phone":"+1 407 268 4843",
    "sg:postcode":"32738",
    "sg:province":"FL",
    "sg:tags":[
        "electrical",
        "electric",
        "contractor"
    ],
    "wof:name":"Prelude Electrical Service",
    "wof:placetype":"venue"
},
  "geometry": {"coordinates":[-81.189476,28.863981],"type":"Point"}
}