{
  "type": "Feature",
  "properties": {
    "iso:country":"US",
    "sg:address":"3367 N Federal Hwy",
    "sg:city":"Fort Lauderdale",
    "sg:classifiers":[
        {
            "category":"Shopping",
            "subcategory":"Music",
            "type":"Retail Goods"
        }
    ],
    "sg:phone":"+1 954 390 7977",
    "sg:postcode":"33306",
    "sg:province":"FL",
    "wof:name":"Everglade Videos",
    "wof:placetype":"venue"
},
  "geometry": {"coordinates":[-80.117699,26.168011],"type":"Point"}
}