{
  "type": "Feature",
  "properties": {
    "iso:country":"US",
    "sg:address":"3400 NW 74th Ave",
    "sg:city":"Miami",
    "sg:classifiers":[
        {
            "category":"Farming",
            "subcategory":"Orchard",
            "type":"Manufacturing & Wholesale Goods"
        }
    ],
    "sg:phone":"+1 305 593 5420",
    "sg:postcode":"33122",
    "sg:province":"FL",
    "sg:tags":[
        "flowers-preserved"
    ],
    "wof:name":"All Star Orchids Flowers",
    "wof:placetype":"venue"
},
  "geometry": {"coordinates":[-80.31716900000001,25.80611],"type":"Point"}
}