{
  "type": "Feature",
  "properties": {
    "iso:country":"US",
    "sg:address":"1614 S Combee Rd",
    "sg:city":"Lakeland",
    "sg:classifiers":[
        {
            "category":"Place Of Worship",
            "type":"Public Place"
        }
    ],
    "sg:phone":"+1 863 665 4642",
    "sg:postcode":"33801",
    "sg:province":"FL",
    "sg:tags":[
        "church"
    ],
    "wof:name":"Miracle Deliverance Prophetic Temple Of God, Inc",
    "wof:placetype":"venue"
},
  "geometry": {"coordinates":[-81.90782299999999,28.022632],"type":"Point"}
}