{
  "type": "Feature",
  "properties": {
    "addr:full":"6437 Raymur St North Port FL 34286",
    "addr:housenumber":"6437",
    "addr:postcode":"34286",
    "addr:street":"Raymur St",
    "iso:country":"US",
    "sg:address":"6437 Raymur St",
    "sg:city":"North Port",
    "sg:classifiers":[
        {
            "category":"Building & Trades",
            "subcategory":"Landscaping Services",
            "type":"Services"
        }
    ],
    "sg:phone":"+1 941 830 0025",
    "sg:postcode":"34286",
    "sg:province":"FL",
    "sg:tags":[
        "landscape"
    ],
    "wof:name":"Scott Lee Landscaping & Mainte",
    "wof:placetype":"venue"
},
  "geometry": {"coordinates":[-82.160259,27.117096],"type":"Point"}
}