{
  "type": "Feature",
  "properties": {
    "iso:country":"US",
    "sg:address":"8857 Thunderbird Dr",
    "sg:city":"Pensacola",
    "sg:classifiers":[
        {
            "category":"Professional",
            "subcategory":"Management & Consulting",
            "type":"Services"
        }
    ],
    "sg:phone":"+1 850 478 0756",
    "sg:postcode":"32514",
    "sg:province":"FL",
    "sg:tags":[
        "retail",
        "direct",
        "sales"
    ],
    "wof:name":"Independent Sales Dir Mary Kay",
    "wof:placetype":"venue"
},
  "geometry": {"coordinates":[-87.233374,30.541162],"type":"Point"}
}