{
  "type": "Feature",
  "properties": {
    "addr:full":"7731 N Military Trl Palm Beach Gardens FL 33410",
    "addr:housenumber":"7731",
    "addr:postcode":"33410",
    "addr:street":"N Military Trl",
    "iso:country":"US",
    "sg:address":"7731 N Military Trl",
    "sg:city":"Palm Beach Gardens",
    "sg:classifiers":[
        {
            "category":"Insurance",
            "subcategory":"Insurance Agent",
            "type":"Services"
        }
    ],
    "sg:phone":"+1 561 841 8180",
    "sg:postcode":"33410",
    "sg:province":"FL",
    "wof:name":"Jakes Warcecer Insurance Agcy",
    "wof:placetype":"venue"
},
  "geometry": {"coordinates":[-80.10704800000001,26.789988],"type":"Point"}
}