{
  "type": "Feature",
  "properties": {
    "iso:country":"US",
    "sg:address":"21069 S Military Trl",
    "sg:city":"Boca Raton",
    "sg:classifiers":[
        {
            "category":"Sports & Exercise",
            "subcategory":"Gym",
            "type":"Entertainment"
        }
    ],
    "sg:phone":"+1 561 368 6441",
    "sg:postcode":"33486",
    "sg:province":"FL",
    "sg:tags":[
        "club",
        "health"
    ],
    "sg:website":"www.ballyfitness.com",
    "wof:name":"Bally Total Fitness",
    "wof:placetype":"venue"
},
  "geometry": {"coordinates":[-80.123412,26.364089],"type":"Point"}
}