{
  "type": "Feature",
  "properties": {
    "addr:full":"14130 Josephine St Largo FL 33774",
    "addr:housenumber":"14130",
    "addr:postcode":"33774",
    "addr:street":"Josephine St",
    "iso:country":"US",
    "sg:address":"14130 Josephine St",
    "sg:city":"Largo",
    "sg:classifiers":[
        {
            "category":"Professional",
            "subcategory":"Art Services",
            "type":"Services"
        }
    ],
    "sg:phone":"+1 727 596 6734",
    "sg:postcode":"33774",
    "sg:province":"FL",
    "sg:tags":[
        "designer",
        "display",
        "producer"
    ],
    "wof:name":"Creative Products Design Corp",
    "wof:placetype":"venue"
},
  "geometry": {"coordinates":[-82.833816,27.885873],"type":"Point"}
}