{
  "type": "Feature",
  "properties": {
    "iso:country":"US",
    "sg:address":"1001 Royal Fern Dr",
    "sg:city":"Melbourne",
    "sg:classifiers":[
        {
            "category":"Professional",
            "type":"Services"
        }
    ],
    "sg:phone":"+1 321 253 0417",
    "sg:postcode":"32940",
    "sg:province":"FL",
    "sg:tags":[
        "establishment"
    ],
    "wof:name":"Magnolia Pointe Homeowners",
    "wof:placetype":"venue"
},
  "geometry": {"coordinates":[-80.693442,28.234459],"type":"Point"}
}