{
  "type": "Feature",
  "properties": {
    "iso:country":"US",
    "sg:address":"4401 Gulf of Mexico Dr",
    "sg:city":"Longboat Key",
    "sg:classifiers":[
        {
            "category":"Health Services",
            "subcategory":"Doctor",
            "type":"Services"
        }
    ],
    "sg:phone":"+1 941 383 1695",
    "sg:postcode":"34228",
    "sg:province":"FL",
    "sg:tags":[
        "medical"
    ],
    "wof:name":"Frank Niemtzow Dr",
    "wof:placetype":"venue"
},
  "geometry": {"coordinates":[-82.644588,27.394343],"type":"Point"}
}