{
  "type": "Feature",
  "properties": {
    "iso:country":"US",
    "sg:address":"7964 Devoe St",
    "sg:city":"Jacksonville",
    "sg:classifiers":[
        {
            "category":"Building & Trades",
            "subcategory":"Construction",
            "type":"Services"
        }
    ],
    "sg:phone":"+1 904 378 0315",
    "sg:postcode":"32220",
    "sg:province":"FL",
    "sg:tags":[
        "general",
        "contractor"
    ],
    "wof:name":"Busby Co",
    "wof:placetype":"venue"
},
  "geometry": {"coordinates":[-81.783477,30.315634],"type":"Point"}
}