{
  "type": "Feature",
  "properties": {
    "addr:full":"540 Lake Ashley Cir West Melbourne FL 32904",
    "addr:housenumber":"540",
    "addr:postcode":"32904",
    "addr:street":"Lake Ashley Cir",
    "iso:country":"US",
    "sg:address":"540 Lake Ashley Cir",
    "sg:city":"West Melbourne",
    "sg:classifiers":[
        {
            "category":"Professional",
            "type":"Services"
        }
    ],
    "sg:phone":"+1 321 727 3115",
    "sg:postcode":"32904",
    "sg:province":"FL",
    "sg:tags":[
        "establishment"
    ],
    "wof:name":"Ashley Manor Subdivision Guard",
    "wof:placetype":"venue"
},
  "geometry": {"coordinates":[-80.694884,28.088196],"type":"Point"}
}