{
  "type": "Feature",
  "properties": {
    "addr:full":"3060 Cleveland Ave Fort Myers FL 33901",
    "addr:housenumber":"3060",
    "addr:postcode":"33901",
    "addr:street":"Cleveland Ave",
    "iso:country":"US",
    "sg:address":"3060 Cleveland Ave",
    "sg:city":"Fort Myers",
    "sg:classifiers":[
        {
            "category":"Shopping",
            "subcategory":"Computers & Home Electronics",
            "type":"Retail Goods"
        },
        {
            "category":"Shopping",
            "subcategory":"Music",
            "type":"Retail Goods"
        }
    ],
    "sg:phone":"+1 239 337 1693",
    "sg:postcode":"33901",
    "sg:province":"FL",
    "sg:tags":[
        "video",
        "disc",
        "tape",
        "cassette"
    ],
    "wof:name":"94 Cents Video",
    "wof:placetype":"venue"
},
  "geometry": {"coordinates":[-81.87231800000001,26.621327],"type":"Point"}
}