{
  "type": "Feature",
  "properties": {
    "iso:country":"US",
    "sg:address":"15539 SW 69th Ter",
    "sg:city":"Miami",
    "sg:classifiers":[
        {
            "category":"Recreation",
            "type":"Entertainment"
        }
    ],
    "sg:phone":"+1 305 386 9371",
    "sg:postcode":"33193",
    "sg:province":"FL",
    "sg:tags":[
        "entertainers-family",
        "business"
    ],
    "wof:name":"Funny Business Of Miami Inc",
    "wof:placetype":"venue"
},
  "geometry": {"coordinates":[-80.445786,25.701593],"type":"Point"}
}