{
  "type": "Feature",
  "properties": {
    "iso:country":"US",
    "sg:address":"703 Fishermans Wharf",
    "sg:city":"Fort Myers Beach",
    "sg:classifiers":[
        {
            "category":"Autos & Motor Vehicles",
            "subcategory":"Boat Sales",
            "type":"Retail Goods"
        },
        {
            "category":"Recreation",
            "subcategory":"Marina",
            "type":"Entertainment"
        }
    ],
    "sg:phone":"+1 239 463 9552",
    "sg:postcode":"33931",
    "sg:province":"FL",
    "sg:tags":[
        "dealer",
        "sales"
    ],
    "wof:name":"Fort Myers Beach Marina Inc",
    "wof:placetype":"venue"
},
  "geometry": {"coordinates":[-81.952243,26.459089],"type":"Point"}
}