{
  "type": "Feature",
  "properties": {
    "iso:country":"US",
    "sg:address":"906 W Bell St",
    "sg:city":"Avon Park",
    "sg:classifiers":[
        {
            "category":"Farming",
            "subcategory":"Farm & Veterinary Services",
            "type":"Manufacturing & Wholesale Goods"
        }
    ],
    "sg:phone":"+1 863 452 1226",
    "sg:postcode":"33825",
    "sg:province":"FL",
    "sg:tags":[
        "crop",
        "harvesting"
    ],
    "wof:name":"Rico & Sanchez Harvesting",
    "wof:placetype":"venue"
},
  "geometry": {"coordinates":[-81.512254,27.591131],"type":"Point"}
}