{
  "type": "Feature",
  "properties": {
    "iso:country":"US",
    "sg:address":"5803 Atlantic Blvd",
    "sg:city":"Jacksonville",
    "sg:classifiers":[
        {
            "category":"Retail",
            "subcategory":"Laundry & Dry Cleaning",
            "type":"Services"
        }
    ],
    "sg:phone":"+1 904 724 2022",
    "sg:postcode":"32207",
    "sg:province":"FL",
    "sg:tags":[
        "cleaners"
    ],
    "wof:name":"Butterfly Cleaners",
    "wof:placetype":"venue"
},
  "geometry": {"coordinates":[-81.603954,30.312615],"type":"Point"}
}