{
  "type": "Feature",
  "properties": {
    "iso:country":"US",
    "sg:address":"3990 8th Ave NE",
    "sg:city":"Naples",
    "sg:classifiers":[
        {
            "category":"Insurance",
            "subcategory":"Insurance Agent",
            "type":"Services"
        }
    ],
    "sg:phone":"+1 239 304 0910",
    "sg:postcode":"34120",
    "sg:province":"FL",
    "wof:name":"Insurance Education Corp",
    "wof:placetype":"venue"
},
  "geometry": {"coordinates":[-81.542287,26.245085],"type":"Point"}
}