{
  "type": "Feature",
  "properties": {
    "iso:country":"US",
    "sg:address":"450 US Hwy 1",
    "sg:city":"Lake Park",
    "sg:classifiers":[
        {
            "category":"Home & Garden",
            "subcategory":"Building Materials",
            "type":"Retail Goods"
        }
    ],
    "sg:phone":"+1 561 842 4231",
    "sg:postcode":"33403",
    "sg:province":"FL",
    "sg:tags":[
        "paint"
    ],
    "wof:name":"MAB Paint Store",
    "wof:placetype":"venue"
},
  "geometry": {"coordinates":[-80.054613,26.795872],"type":"Point"}
}