{
  "type": "Feature",
  "properties": {
    "iso:country":"US",
    "sg:address":"1285 W Palmetto Park Rd",
    "sg:city":"Boca Raton",
    "sg:classifiers":[
        {
            "category":"Restaurant",
            "type":"Food & Drink"
        }
    ],
    "sg:phone":"+1 561 417 7488",
    "sg:postcode":"33486",
    "sg:province":"FL",
    "sg:tags":[
        "eating"
    ],
    "wof:name":"Feng Liang Inc",
    "wof:placetype":"venue"
},
  "geometry": {"coordinates":[-80.114688,26.350827],"type":"Point"}
}