{
  "type": "Feature",
  "properties": {
    "iso:country":"US",
    "sg:address":"5008 Panther Dr",
    "sg:city":"Spring Hill",
    "sg:classifiers":[
        {
            "category":"Home & Garden",
            "subcategory":"Furniture",
            "type":"Retail Goods"
        }
    ],
    "sg:phone":"+1 352 592 2933",
    "sg:postcode":"34607",
    "sg:province":"FL",
    "wof:name":"Almost New Furniture",
    "wof:placetype":"venue"
},
  "geometry": {"coordinates":[-82.598704,28.50108],"type":"Point"}
}