{
  "type": "Feature",
  "properties": {
    "addr:full":"3211 S John Young Pkwy Kissimmee FL 34746",
    "addr:housenumber":"3211",
    "addr:postcode":"34746",
    "addr:street":"S John Young Pkwy",
    "iso:country":"US",
    "sg:address":"3211 S John Young Pkwy",
    "sg:city":"Kissimmee",
    "sg:classifiers":[
        {
            "category":"Health Services",
            "subcategory":"Clinic",
            "type":"Services"
        }
    ],
    "sg:phone":"+1 407 343 1919",
    "sg:postcode":"34746",
    "sg:province":"FL",
    "sg:tags":[
        "welfare"
    ],
    "wof:name":"Walk In Clinic",
    "wof:placetype":"venue"
},
  "geometry": {"coordinates":[-81.43454800000001,28.261695],"type":"Point"}
}