{
  "type": "Feature",
  "properties": {
    "iso:country":"US",
    "sg:address":"7232 Berry Ave",
    "sg:city":"Jacksonville",
    "sg:classifiers":[
        {
            "category":"Manufacturing",
            "subcategory":"Glass & Minerals",
            "type":"Manufacturing & Wholesale Goods"
        }
    ],
    "sg:phone":"+1 904 725 7983",
    "sg:postcode":"32211",
    "sg:province":"FL",
    "sg:tags":[
        "mfg",
        "ceramic",
        "laying",
        "contractor",
        "floor",
        "tile"
    ],
    "wof:name":"Dolphin Tile",
    "wof:placetype":"venue"
},
  "geometry": {"coordinates":[-81.58141000000001,30.314981],"type":"Point"}
}