{
  "type": "Feature",
  "properties": {
    "addr:full":"2413 N Atlantic Ave Daytona Beach FL 32118",
    "addr:housenumber":"2413",
    "addr:postcode":"32118",
    "addr:street":"N Atlantic Ave",
    "iso:country":"US",
    "sg:address":"2413 N Atlantic Ave",
    "sg:city":"Daytona Beach",
    "sg:classifiers":[
        {
            "category":"Retail",
            "subcategory":"Self-service Laundry",
            "type":"Services"
        },
        {
            "category":"Retail",
            "subcategory":"Laundry & Dry Cleaning",
            "type":"Services"
        }
    ],
    "sg:phone":"+1 386 677 8445",
    "sg:postcode":"32118",
    "sg:province":"FL",
    "sg:tags":[
        "drycleaning",
        "plant",
        "coin"
    ],
    "wof:name":"Snow White Laundromat Dry Clrs",
    "wof:placetype":"venue"
},
  "geometry": {"coordinates":[-81.024151,29.260194],"type":"Point"}
}