{
  "type": "Feature",
  "properties": {
    "iso:country":"US",
    "sg:address":"2655 E Atlantic Blvd",
    "sg:city":"Pompano Beach",
    "sg:classifiers":[
        {
            "category":"Personal",
            "subcategory":"Barber",
            "type":"Services"
        }
    ],
    "sg:phone":"+1 954 782 5939",
    "sg:postcode":"33062",
    "sg:province":"FL",
    "sg:tags":[
        "shop"
    ],
    "wof:name":"Tony G's Barber Style Shop",
    "wof:placetype":"venue"
},
  "geometry": {"coordinates":[-80.09728200000001,26.23197],"type":"Point"}
}