{
  "type": "Feature",
  "properties": {
    "addr:full":"4045 1st Ave N Saint Petersburg FL 33713",
    "addr:housenumber":"4045",
    "addr:postcode":"33713",
    "addr:street":"1St Ave N",
    "iso:country":"US",
    "sg:address":"4045 1st Ave N",
    "sg:city":"Saint Petersburg",
    "sg:classifiers":[
        {
            "category":"Professional",
            "subcategory":"Computer Services",
            "type":"Services"
        }
    ],
    "sg:phone":"+1 813 385 4020",
    "sg:postcode":"33713",
    "sg:province":"FL",
    "sg:tags":[
        "repair",
        "laptop",
        "network"
    ],
    "wof:name":"Advance Computer Solutions",
    "wof:placetype":"venue"
},
  "geometry": {"coordinates":[-82.688402,27.771902],"type":"Point"}
}