{
  "type": "Feature",
  "properties": {
    "addr:full":"334 2nd Ave N Jacksonville Bch FL 32250",
    "addr:housenumber":"334",
    "addr:postcode":"32250",
    "addr:street":"2Nd Ave N",
    "iso:country":"US",
    "sg:address":"334 2nd Ave N",
    "sg:city":"Jacksonville Bch",
    "sg:classifiers":[
        {
            "category":"Professional",
            "subcategory":"Lawyer & Legal Services",
            "type":"Services"
        }
    ],
    "sg:phone":"+1 904 270 0400",
    "sg:postcode":"32250",
    "sg:province":"FL",
    "sg:tags":[
        "attorney"
    ],
    "wof:name":"Johnston Hammond & Burnett",
    "wof:placetype":"venue"
},
  "geometry": {"coordinates":[-81.39313300000001,30.290754],"type":"Point"}
}