{
  "type": "Feature",
  "properties": {
    "iso:country":"US",
    "sg:address":"2678 W 84th St",
    "sg:city":"Hialeah",
    "sg:classifiers":[
        {
            "category":"Autos & Motor Vehicles",
            "subcategory":"Auto Supplies",
            "type":"Retail Goods"
        }
    ],
    "sg:phone":"+1 305 887 8656",
    "sg:postcode":"33016",
    "sg:province":"FL",
    "sg:tags":[
        "tire"
    ],
    "wof:name":"Exclusive Tire Sale & Service Inc",
    "wof:placetype":"venue"
},
  "geometry": {"coordinates":[-80.338898,25.8976],"type":"Point"}
}