{
  "type": "Feature",
  "properties": {
    "iso:country":"US",
    "sg:address":"3630 S Manhattan Ave",
    "sg:city":"Tampa",
    "sg:classifiers":[
        {
            "category":"Retail",
            "subcategory":"Repair Shop",
            "type":"Services"
        }
    ],
    "sg:phone":"+1 727 786 8118",
    "sg:postcode":"33629",
    "sg:province":"FL",
    "sg:tags":[
        "electrical"
    ],
    "wof:name":"A Able Appliance Service Tampa",
    "wof:placetype":"venue"
},
  "geometry": {"coordinates":[-82.51791299999999,27.90938],"type":"Point"}
}