{
  "type": "Feature",
  "properties": {
    "iso:country":"US",
    "sg:address":"695 S Ramona Ave",
    "sg:city":"Lake Alfred",
    "sg:classifiers":[
        {
            "category":"Insurance",
            "subcategory":"Health Insurance",
            "type":"Services"
        }
    ],
    "sg:phone":"+1 863 956 4837",
    "sg:postcode":"33850",
    "sg:province":"FL",
    "sg:tags":[
        "carrier"
    ],
    "wof:name":"Travelers Protective Assn Amer",
    "wof:placetype":"venue"
},
  "geometry": {"coordinates":[-81.71899500000001,28.086464],"type":"Point"}
}