{
  "type": "Feature",
  "properties": {
    "addr:full":"10741 NW 89th Ave Hialeah FL 33018",
    "addr:housenumber":"10741",
    "addr:postcode":"33018",
    "addr:street":"Nw 89Th Ave",
    "iso:country":"US",
    "sg:address":"10741 NW 89th Ave",
    "sg:city":"Hialeah",
    "sg:classifiers":[
        {
            "category":"Freight",
            "type":"Transportation"
        }
    ],
    "sg:phone":"+1 305 885 6464",
    "sg:postcode":"33018",
    "sg:province":"FL",
    "sg:tags":[
        "hauling",
        "trucking"
    ],
    "wof:name":"Allied Trucking Of Florida",
    "wof:placetype":"venue"
},
  "geometry": {"coordinates":[-80.34315100000001,25.871157],"type":"Point"}
}