{
  "type": "Feature",
  "properties": {
    "iso:country":"US",
    "sg:address":"3022 NW 50th Ter",
    "sg:city":"Gainesville",
    "sg:classifiers":[
        {
            "category":"Shopping",
            "subcategory":"Florist",
            "type":"Retail Goods"
        }
    ],
    "sg:phone":"+1 352 213 6992",
    "sg:postcode":"32606",
    "sg:province":"FL",
    "wof:name":"North Fl Econolawn",
    "wof:placetype":"venue"
},
  "geometry": {"coordinates":[-82.396727,29.680508],"type":"Point"}
}