{
  "type": "Feature",
  "properties": {
    "iso:country":"US",
    "sg:address":"2182 NW Settle Ave",
    "sg:city":"Port St Lucie",
    "sg:classifiers":[
        {
            "category":"Manufacturing",
            "subcategory":"Furniture",
            "type":"Manufacturing & Wholesale Goods"
        }
    ],
    "sg:phone":"+1 772 489 7675",
    "sg:postcode":"34986",
    "sg:province":"FL",
    "wof:name":"Maurice Antique Pine",
    "wof:placetype":"venue"
},
  "geometry": {"coordinates":[-80.422991,27.340833],"type":"Point"}
}