{
  "type": "Feature",
  "properties": {
    "addr:full":"110 Cleveland Rd Lake Worth FL 33467",
    "addr:housenumber":"110",
    "addr:postcode":"33467",
    "addr:street":"Cleveland Rd",
    "iso:country":"US",
    "sg:address":"110 Cleveland Rd",
    "sg:city":"Lake Worth",
    "sg:classifiers":[
        {
            "category":"Building & Trades",
            "subcategory":"Construction",
            "type":"Services"
        }
    ],
    "sg:phone":"+1 561 963 1263",
    "sg:postcode":"33467",
    "sg:province":"FL",
    "sg:tags":[
        "hanging",
        "contractor"
    ],
    "wof:name":"Kristal Painting REM",
    "wof:placetype":"venue"
},
  "geometry": {"coordinates":[-80.167619,26.61192],"type":"Point"}
}