{
  "type": "Feature",
  "properties": {
    "addr:full":"2921 S Orlando Dr Sanford FL 32773",
    "addr:housenumber":"2921",
    "addr:postcode":"32773",
    "addr:street":"S Orlando Dr",
    "iso:country":"US",
    "sg:address":"2921 S Orlando Dr",
    "sg:city":"Sanford",
    "sg:classifiers":[
        {
            "category":"Food & Beverages",
            "subcategory":"Groceries & Convenience Stores",
            "type":"Retail Goods"
        }
    ],
    "sg:phone":"+1 407 330 7336",
    "sg:postcode":"32773",
    "sg:province":"FL",
    "wof:name":"Indupeg Inc",
    "wof:placetype":"venue"
},
  "geometry": {"coordinates":[-81.27951299999999,28.771376],"type":"Point"}
}