{
  "type": "Feature",
  "properties": {
    "addr:full":"13736 NE 11th Ave Miami FL 33161",
    "addr:housenumber":"13736",
    "addr:postcode":"33161",
    "addr:street":"Ne 11Th Ave",
    "iso:country":"US",
    "sg:address":"13736 NE 11th Ave",
    "sg:city":"Miami",
    "sg:classifiers":[
        {
            "category":"Shopping",
            "subcategory":"Computers & Home Electronics",
            "type":"Retail Goods"
        }
    ],
    "sg:phone":"+1 305 895 2001",
    "sg:postcode":"33161",
    "sg:province":"FL",
    "wof:name":"Miami Computer 2000 Corp",
    "wof:placetype":"venue"
},
  "geometry": {"coordinates":[-80.177013,25.902394],"type":"Point"}
}