{
  "type": "Feature",
  "properties": {
    "addr:full":"4016 Land O Lakes Blvd Land O Lakes FL 34639",
    "addr:housenumber":"4016",
    "addr:postcode":"34639",
    "addr:street":"Land O Lakes Blvd Land",
    "iso:country":"US",
    "sg:address":"4016 Land O Lakes Blvd",
    "sg:city":"Land O Lakes",
    "sg:classifiers":[
        {
            "category":"Professional",
            "subcategory":"Business Services",
            "type":"Services"
        }
    ],
    "sg:phone":"+1 813 996 4479",
    "sg:postcode":"34639",
    "sg:province":"FL",
    "sg:tags":[
        "water",
        "treatment"
    ],
    "wof:name":"Land O Lakes Water Trtmnt",
    "wof:placetype":"venue"
},
  "geometry": {"coordinates":[-82.458316,28.218715],"type":"Point"}
}