{
  "type": "Feature",
  "properties": {
    "addr:full":"1117 Tall Pine Dr Apopka FL 32712",
    "addr:housenumber":"1117",
    "addr:postcode":"32712",
    "addr:street":"Tall Pine Dr",
    "iso:country":"US",
    "sg:address":"1117 Tall Pine Dr",
    "sg:city":"Apopka",
    "sg:classifiers":[
        {
            "category":"Restaurant",
            "type":"Food & Drink"
        }
    ],
    "sg:phone":"+1 407 358 8076",
    "sg:postcode":"32712",
    "sg:province":"FL",
    "wof:name":"Deja Vu Comedy Theatre Restaurant, Inc",
    "wof:placetype":"venue"
},
  "geometry": {"coordinates":[-81.466972,28.69879],"type":"Point"}
}