{
  "type": "Feature",
  "properties": {
    "addr:full":"9789 Wilshire Lakes Blvd Naples FL 34109",
    "addr:housenumber":"9789",
    "addr:postcode":"34109",
    "addr:street":"Wilshire Lakes Blvd",
    "iso:country":"US",
    "sg:address":"9789 Wilshire Lakes Blvd",
    "sg:city":"Naples",
    "sg:classifiers":[
        {
            "category":"Building & Trades",
            "subcategory":"Construction",
            "type":"Services"
        }
    ],
    "sg:phone":"+1 239 566 3074",
    "sg:postcode":"34109",
    "sg:province":"FL",
    "sg:tags":[
        "home",
        "builder"
    ],
    "wof:name":"Kay Homes Inc",
    "wof:placetype":"venue"
},
  "geometry": {"coordinates":[-81.744207,26.254193],"type":"Point"}
}