{
  "type": "Feature",
  "properties": {
    "iso:country":"US",
    "sg:address":"11985 US Hwy 1",
    "sg:city":"Juno Beach",
    "sg:classifiers":[
        {
            "category":"Personal",
            "subcategory":"Beauty Salon",
            "type":"Services"
        }
    ],
    "sg:phone":"+1 561 626 9266",
    "sg:postcode":"33408",
    "sg:province":"FL",
    "sg:tags":[
        "shop"
    ],
    "wof:name":"Carol Hanley Hair Design",
    "wof:placetype":"venue"
},
  "geometry": {"coordinates":[-80.05870299999999,26.851996],"type":"Point"}
}