{
  "type": "Feature",
  "properties": {
    "iso:country":"US",
    "sg:address":"21951 US Hwy 19",
    "sg:city":"Clearwater",
    "sg:classifiers":[
        {
            "category":"Wholesale",
            "subcategory":"Apparel",
            "type":"Manufacturing & Wholesale Goods"
        }
    ],
    "sg:phone":"+1 727 712 8089",
    "sg:postcode":"33765",
    "sg:province":"FL",
    "sg:tags":[
        "sport"
    ],
    "wof:name":"Baker Boys Corp & Spt AP Inc",
    "wof:placetype":"venue"
},
  "geometry": {"coordinates":[-82.729767,27.976457],"type":"Point"}
}