{
  "type": "Feature",
  "properties": {
    "iso:country":"US",
    "sg:address":"8220 Griffin Rd",
    "sg:city":"Davie",
    "sg:classifiers":[
        {
            "category":"Shopping",
            "subcategory":"Clothing, Apparel, & Fashions",
            "type":"Retail Goods"
        }
    ],
    "sg:phone":"+1 954 434 9228",
    "sg:postcode":"33328",
    "sg:province":"FL",
    "sg:tags":[
        "jockey",
        "disc"
    ],
    "wof:name":"A Number 1 Disc Jckey Entrmt B",
    "wof:placetype":"venue"
},
  "geometry": {"coordinates":[-80.256384,26.064409],"type":"Point"}
}