{
  "type": "Feature",
  "properties": {
    "addr:full":"7865 NW 46th St Doral FL 33166",
    "addr:housenumber":"7865",
    "addr:postcode":"33166",
    "addr:street":"Nw 46Th St",
    "iso:country":"US",
    "sg:address":"7865 NW 46th St",
    "sg:city":"Doral",
    "sg:classifiers":[
        {
            "category":"Wholesale",
            "subcategory":"Office Equipment",
            "type":"Manufacturing & Wholesale Goods"
        },
        {
            "category":"Manufacturing",
            "subcategory":"Tools & Machinery",
            "type":"Manufacturing & Wholesale Goods"
        },
        {
            "category":"Manufacturing",
            "subcategory":"Paper Products",
            "type":"Manufacturing & Wholesale Goods"
        }
    ],
    "sg:phone":"+1 305 594 9000",
    "sg:postcode":"33166",
    "sg:province":"FL",
    "sg:tags":[
        "packaging",
        "materials-wholesale",
        "machinery-wholesale",
        "manufacturer"
    ],
    "wof:name":"Technopack",
    "wof:placetype":"venue"
},
  "geometry": {"coordinates":[-80.32485699999999,25.815124],"type":"Point"}
}