{
  "type": "Feature",
  "properties": {
    "iso:country":"US",
    "sg:address":"11726 Camden Park Dr",
    "sg:city":"Windermere",
    "sg:classifiers":[
        {
            "category":"Manufacturing",
            "subcategory":"Soap",
            "type":"Manufacturing & Wholesale Goods"
        }
    ],
    "sg:phone":"+1 407 909 0051",
    "sg:postcode":"34786",
    "sg:province":"FL",
    "sg:tags":[
        "detergent"
    ],
    "wof:name":"Retail Concepts Of Minnesota, Inc.",
    "wof:placetype":"venue"
},
  "geometry": {"coordinates":[-81.548889,28.462187],"type":"Point"}
}