{
  "type": "Feature",
  "properties": {
    "iso:country":"US",
    "sg:address":"80925 Overseas Hwy",
    "sg:city":"Islamorada",
    "sg:classifiers":[
        {
            "category":"Personal",
            "subcategory":"Beauty Salon",
            "type":"Services"
        },
        {
            "category":"Personal",
            "subcategory":"Day Spa",
            "type":"Services"
        },
        {
            "category":"Food & Beverages",
            "subcategory":"Candy",
            "type":"Retail Goods"
        }
    ],
    "sg:phone":"+1 305 664 3100",
    "sg:postcode":"33036",
    "sg:province":"FL",
    "sg:tags":[
        "confectionery"
    ],
    "sg:website":"http://www.eyecandyboutique.com",
    "wof:name":"Eye Candy Salon",
    "wof:placetype":"venue"
},
  "geometry": {"coordinates":[-80.645094,24.909545],"type":"Point"}
}