{
  "type": "Feature",
  "properties": {
    "addr:full":"6000 NE 22nd Way Fort Lauderdale FL 33308",
    "addr:housenumber":"6000",
    "addr:postcode":"33308",
    "addr:street":"Ne 22Nd Way",
    "iso:country":"US",
    "sg:address":"6000 NE 22nd Way",
    "sg:city":"Fort Lauderdale",
    "sg:classifiers":[
        {
            "category":"Building & Trades",
            "subcategory":"Plumbing",
            "type":"Services"
        }
    ],
    "sg:phone":"+1 954 772 2626",
    "sg:postcode":"33308",
    "sg:province":"FL",
    "sg:tags":[
        "contractor"
    ],
    "wof:name":"Crain Plumbing Services",
    "wof:placetype":"venue"
},
  "geometry": {"coordinates":[-80.11055399999999,26.20337],"type":"Point"}
}