{
  "type": "Feature",
  "properties": {
    "addr:full":"3050 Alafaya Trl Oviedo FL 32765",
    "addr:housenumber":"3050",
    "addr:postcode":"32765",
    "addr:street":"Alafaya Trl",
    "iso:country":"US",
    "sg:address":"3050 Alafaya Trl",
    "sg:city":"Oviedo",
    "sg:classifiers":[
        {
            "category":"Retail",
            "subcategory":"Laundry & Dry Cleaning",
            "type":"Services"
        }
    ],
    "sg:phone":"+1 407 366 0867",
    "sg:postcode":"32765",
    "sg:province":"FL",
    "sg:tags":[
        "cleaners"
    ],
    "wof:name":"Red Bug Alafaya Cleaners",
    "wof:placetype":"venue"
},
  "geometry": {"coordinates":[-81.20784999999999,28.625226],"type":"Point"}
}