{
  "type": "Feature",
  "properties": {
    "iso:country":"US",
    "sg:address":"37189 SW 212th Ave",
    "sg:city":"Homestead",
    "sg:classifiers":[
        {
            "category":"Farming",
            "subcategory":"Nursery",
            "type":"Manufacturing & Wholesale Goods"
        }
    ],
    "sg:phone":"+1 305 245 4643",
    "sg:postcode":"33034",
    "sg:province":"FL",
    "sg:tags":[
        "supp",
        "ornamental",
        "flower"
    ],
    "wof:name":"Royal Palm Orchids",
    "wof:placetype":"venue"
},
  "geometry": {"coordinates":[-80.533643,25.425413],"type":"Point"}
}