{
  "type": "Feature",
  "properties": {
    "addr:full":"6215 Bayside Dr New Port Richey FL 34652",
    "addr:housenumber":"6215",
    "addr:postcode":"34652",
    "addr:street":"Bayside Dr",
    "iso:country":"US",
    "sg:address":"6215 Bayside Dr",
    "sg:city":"New Port Richey",
    "sg:classifiers":[
        {
            "category":"Manufacturing",
            "subcategory":"Metals",
            "type":"Manufacturing & Wholesale Goods"
        }
    ],
    "sg:phone":"+1 727 849 6232",
    "sg:postcode":"34652",
    "sg:province":"FL",
    "sg:tags":[
        "steel",
        "mfg"
    ],
    "wof:name":"Thermal Pipe Systems Inc",
    "wof:placetype":"venue"
},
  "geometry": {"coordinates":[-82.738579,28.249776],"type":"Point"}
}