{
  "type": "Feature",
  "properties": {
    "iso:country":"US",
    "sg:address":"321 29th Ave N",
    "sg:city":"St Petersburg",
    "sg:classifiers":[
        {
            "category":"Building & Trades",
            "subcategory":"Construction",
            "type":"Services"
        }
    ],
    "sg:phone":"+1 727 898 0008",
    "sg:postcode":"33704",
    "sg:province":"FL",
    "sg:tags":[
        "designer"
    ],
    "wof:name":"D C Multimedia Designcom",
    "wof:placetype":"venue"
},
  "geometry": {"coordinates":[-82.63735,27.798563],"type":"Point"}
}