{
  "type": "Feature",
  "properties": {
    "iso:country":"US",
    "sg:address":"2265 N Courtenay Pkwy",
    "sg:city":"Merritt Island",
    "sg:classifiers":[
        {
            "category":"Retail",
            "subcategory":"Veterinary Services",
            "type":"Services"
        }
    ],
    "sg:phone":"+1 321 452 3647",
    "sg:postcode":"32953",
    "sg:province":"FL",
    "sg:tags":[
        "veterinarian"
    ],
    "wof:name":"Maxwell Guy DVM",
    "wof:placetype":"venue"
},
  "geometry": {"coordinates":[-80.70500199999999,28.3978],"type":"Point"}
}