{
  "type": "Feature",
  "properties": {
    "addr:full":"3440 Conway Blvd Port Charlotte FL 33952",
    "addr:housenumber":"3440",
    "addr:postcode":"33952",
    "addr:street":"Conway Blvd",
    "iso:country":"US",
    "sg:address":"3440 Conway Blvd",
    "sg:city":"Port Charlotte",
    "sg:classifiers":[
        {
            "category":"Organizations",
            "subcategory":"Community Association",
            "type":"Services"
        }
    ],
    "sg:phone":"+1 941 629 7092",
    "sg:postcode":"33952",
    "sg:province":"FL",
    "wof:name":"Kiwanis Park Fndtn Port Charlo",
    "wof:placetype":"venue"
},
  "geometry": {"coordinates":[-82.088931,26.976208],"type":"Point"}
}