{
  "type": "Feature",
  "properties": {
    "addr:full":"16500 SW 88th St Miami FL 33196",
    "addr:housenumber":"16500",
    "addr:postcode":"33196",
    "addr:street":"Sw 88Th St",
    "iso:country":"US",
    "sg:address":"16500 SW 88th St",
    "sg:city":"Miami",
    "sg:classifiers":[
        {
            "category":"Wholesale",
            "subcategory":"Office Equipment",
            "type":"Manufacturing & Wholesale Goods"
        },
        {
            "category":"Shopping",
            "subcategory":"Stationery & Office Supplies",
            "type":"Retail Goods"
        },
        {
            "category":"Professional",
            "subcategory":"Printing & Photocopies",
            "type":"Services"
        },
        {
            "category":"Shopping",
            "subcategory":"Computers & Home Electronics",
            "type":"Retail Goods"
        }
    ],
    "sg:phone":"+1 305 408 1877",
    "sg:postcode":"33196",
    "sg:province":"FL",
    "sg:tags":[
        "scanning",
        "printer",
        "register",
        "autographic",
        "duplicating",
        "copying",
        "plotting",
        "furniture"
    ],
    "sg:website":"http://www.officemax.com/",
    "wof:name":"OfficeMax",
    "wof:placetype":"venue"
},
  "geometry": {"coordinates":[-80.460814,25.683842],"type":"Point"}
}