{
  "type": "Feature",
  "properties": {
    "iso:country":"US",
    "sg:address":"8270 Pascal Dr",
    "sg:city":"Punta Gorda",
    "sg:classifiers":[
        {
            "category":"Retail",
            "subcategory":"Auto Repair",
            "type":"Services"
        }
    ],
    "sg:phone":"+1 941 575 7076",
    "sg:postcode":"33950",
    "sg:province":"FL",
    "sg:tags":[
        "recreational",
        "vehicle"
    ],
    "sg:website":"www.rv-services.com",
    "wof:name":"R V Svc Unlimited Inc",
    "wof:placetype":"venue"
},
  "geometry": {"coordinates":[-82.02449799999999,26.910244],"type":"Point"}
}