{
  "type": "Feature",
  "properties": {
    "addr:full":"401 E Bearss Ave Tampa FL 33613",
    "addr:housenumber":"401",
    "addr:postcode":"33613",
    "addr:street":"E Bearss Ave",
    "iso:country":"US",
    "sg:address":"401 E Bearss Ave",
    "sg:city":"Tampa",
    "sg:classifiers":[
        {
            "category":"Restaurant",
            "type":"Food & Drink"
        }
    ],
    "sg:phone":"+1 813 962 0859",
    "sg:postcode":"33613",
    "sg:province":"FL",
    "wof:name":"Wendys",
    "wof:placetype":"venue"
},
  "geometry": {"coordinates":[-82.455201,28.088016],"type":"Point"}
}