{
  "type": "Feature",
  "properties": {
    "addr:full":"1720 E Edgewood Dr Lakeland FL 33803",
    "addr:housenumber":"1720",
    "addr:postcode":"33803",
    "addr:street":"E Edgewood Dr",
    "iso:country":"US",
    "sg:address":"1720 E Edgewood Dr",
    "sg:city":"Lakeland",
    "sg:classifiers":[
        {
            "category":"Building & Trades",
            "subcategory":"Cleaning & Sanitation",
            "type":"Services"
        },
        {
            "category":"Shopping",
            "type":"Retail Goods"
        }
    ],
    "sg:phone":"+1 863 688 9478",
    "sg:postcode":"33803",
    "sg:province":"FL",
    "sg:tags":[
        "janitor",
        "janitorial",
        "supply"
    ],
    "wof:name":"Sun State Janitorial Products",
    "wof:placetype":"venue"
},
  "geometry": {"coordinates":[-81.92886,28.011397],"type":"Point"}
}