{
  "type": "Feature",
  "properties": {
    "iso:country":"US",
    "sg:address":"8901 SW 149th Pl",
    "sg:city":"Miami",
    "sg:classifiers":[
        {
            "category":"Building & Trades",
            "subcategory":"Landscaping Services",
            "type":"Services"
        }
    ],
    "sg:phone":"+1 305 255 0380",
    "sg:postcode":"33196",
    "sg:province":"FL",
    "sg:tags":[
        "tree",
        "stump",
        "grinding",
        "removal"
    ],
    "wof:name":"Tompkins Tree Service",
    "wof:placetype":"venue"
},
  "geometry": {"coordinates":[-80.434067,25.683331],"type":"Point"}
}