{
  "type": "Feature",
  "properties": {
    "iso:country":"US",
    "sg:address":"905 S Spring Garden Ave",
    "sg:city":"De Land",
    "sg:classifiers":[
        {
            "category":"Food & Beverages",
            "subcategory":"Groceries & Convenience Stores",
            "type":"Retail Goods"
        }
    ],
    "sg:phone":"+1 386 736 3850",
    "sg:postcode":"32720",
    "sg:province":"FL",
    "wof:name":"Handy-Way",
    "wof:placetype":"venue"
},
  "geometry": {"coordinates":[-81.323716,29.013379],"type":"Point"}
}