{
  "type": "Feature",
  "properties": {
    "addr:full":"100 Buttonwood Ave Key Largo FL 33037",
    "addr:housenumber":"100",
    "addr:postcode":"33037",
    "addr:street":"Buttonwood Ave",
    "iso:country":"US",
    "sg:address":"100 Buttonwood Ave",
    "sg:city":"Key Largo",
    "sg:classifiers":[
        {
            "category":"Recreation",
            "type":"Entertainment"
        }
    ],
    "sg:phone":"+1 305 853 5161",
    "sg:postcode":"33037",
    "sg:province":"FL",
    "sg:tags":[
        "tour"
    ],
    "wof:name":"Captain Stlin Everglades Tours",
    "wof:placetype":"venue"
},
  "geometry": {"coordinates":[-80.42962300000001,25.112143],"type":"Point"}
}