{
  "type": "Feature",
  "properties": {
    "addr:full":"2465 Saint Johns Bluff Rd S Jacksonville FL 32246",
    "addr:housenumber":"2465",
    "addr:postcode":"32246",
    "addr:street":"Saint Johns Bluff Rd",
    "iso:country":"US",
    "sg:address":"2465 Saint Johns Bluff Rd S",
    "sg:city":"Jacksonville",
    "sg:classifiers":[
        {
            "category":"Government",
            "subcategory":"Fire Station",
            "type":"Public Place"
        },
        {
            "category":"Home & Garden",
            "subcategory":"Kitchen Supply",
            "type":"Retail Goods"
        }
    ],
    "sg:phone":"+1 877 857 4752",
    "sg:postcode":"32246",
    "sg:province":"FL",
    "sg:tags":[
        "extinguisher",
        "restaurant",
        "protection",
        "equipment"
    ],
    "sg:website":"http://www.commercialfire.com",
    "wof:name":"Commercial Fire Inc",
    "wof:placetype":"venue"
},
  "geometry": {"coordinates":[-81.52587800000001,30.304781],"type":"Point"}
}