{
  "type": "Feature",
  "properties": {
    "addr:full":"16951 Indrio Rd Fort Pierce FL 34945",
    "addr:housenumber":"16951",
    "addr:postcode":"34945",
    "addr:street":"Indrio Rd",
    "iso:country":"US",
    "sg:address":"16951 Indrio Rd",
    "sg:city":"Fort Pierce",
    "sg:classifiers":[
        {
            "category":"Wholesale",
            "subcategory":"Fruits & Vegetables",
            "type":"Manufacturing & Wholesale Goods"
        }
    ],
    "sg:phone":"+1 772 464 4622",
    "sg:postcode":"34945",
    "sg:province":"FL",
    "sg:tags":[
        "shipper"
    ],
    "wof:name":"Indrio Groves",
    "wof:placetype":"venue"
},
  "geometry": {"coordinates":[-80.509241,27.521695],"type":"Point"}
}