{
  "type": "Feature",
  "properties": {
    "addr:full":"6800 NW 22nd St Gainesville FL 32653",
    "addr:housenumber":"6800",
    "addr:postcode":"32653",
    "addr:street":"Nw 22Nd St",
    "iso:country":"US",
    "sg:address":"6800 NW 22nd St",
    "sg:city":"Gainesville",
    "sg:classifiers":[
        {
            "category":"Home & Garden",
            "subcategory":"Household Appliances",
            "type":"Retail Goods"
        },
        {
            "category":"Manufacturing",
            "subcategory":"Wood Products",
            "type":"Manufacturing & Wholesale Goods"
        },
        {
            "category":"Home & Garden",
            "subcategory":"Building Materials",
            "type":"Retail Goods"
        },
        {
            "category":"Building & Trades",
            "subcategory":"Construction",
            "type":"Services"
        },
        {
            "category":"Manufacturing",
            "subcategory":"Building Materials",
            "type":"Manufacturing & Wholesale Goods"
        }
    ],
    "sg:phone":"+1 352 372 1111",
    "sg:postcode":"32653",
    "sg:province":"FL",
    "sg:tags":[
        "doors-wood",
        "major",
        "installation",
        "windows-repair",
        "materials-wholesale",
        "accessory",
        "frames",
        "window",
        "lumber",
        "doors",
        "insulation",
        "contractor",
        "replacement",
        "manufacturer"
    ],
    "sg:website":"http://www.cbslbm.com",
    "wof:name":"Central Builder Supplies Of Gainesville",
    "wof:placetype":"venue"
},
  "geometry": {"coordinates":[-82.35366999999999,29.716589],"type":"Point"}
}