{
  "type": "Feature",
  "properties": {
    "addr:full":"3940 S Suncoast Blvd Homosassa FL 34448",
    "addr:housenumber":"3940",
    "addr:postcode":"34448",
    "addr:street":"S Suncoast Blvd",
    "iso:country":"US",
    "sg:address":"3940 S Suncoast Blvd",
    "sg:city":"Homosassa",
    "sg:classifiers":[
        {
            "category":"Restaurant",
            "type":"Food & Drink"
        }
    ],
    "sg:phone":"+1 352 628 9943",
    "sg:postcode":"34448",
    "sg:province":"FL",
    "sg:tags":[
        "parlor",
        "ice",
        "cream"
    ],
    "wof:name":"Sweet Georgia Browns Ice Cream",
    "wof:placetype":"venue"
},
  "geometry": {"coordinates":[-82.57649000000001,28.804731],"type":"Point"}
}