{
  "type": "Feature",
  "properties": {
    "iso:country":"US",
    "sg:address":"1063 Cephas Rd",
    "sg:city":"Clearwater",
    "sg:classifiers":[
        {
            "category":"Manufacturing",
            "subcategory":"Printing",
            "type":"Manufacturing & Wholesale Goods"
        }
    ],
    "sg:phone":"+1 727 446 8300",
    "sg:postcode":"33765",
    "sg:province":"FL",
    "wof:name":"Apartment News Of America",
    "wof:placetype":"venue"
},
  "geometry": {"coordinates":[-82.752623,27.976536],"type":"Point"}
}