{
  "type": "Feature",
  "properties": {
    "addr:full":"510 Duval Cir Baldwin FL 32234",
    "addr:housenumber":"510",
    "addr:postcode":"32234",
    "addr:street":"Duval Cir",
    "iso:country":"US",
    "sg:address":"510 Duval Cir",
    "sg:city":"Baldwin",
    "sg:classifiers":[
        {
            "category":"Real Estate",
            "subcategory":"Real Estate Operator",
            "type":"Services"
        }
    ],
    "sg:phone":"+1 904 266 4070",
    "sg:postcode":"32234",
    "sg:province":"FL",
    "sg:tags":[
        "building",
        "apartment"
    ],
    "wof:name":"Baldwin Groves Apartments",
    "wof:placetype":"venue"
},
  "geometry": {"coordinates":[-81.97348100000001,30.300061],"type":"Point"}
}