{
  "type": "Feature",
  "properties": {
    "iso:country":"US",
    "sg:address":"12444 SW 117th Ct",
    "sg:city":"Miami",
    "sg:classifiers":[
        {
            "category":"Retail",
            "subcategory":"Laundry & Dry Cleaning",
            "type":"Services"
        }
    ],
    "sg:phone":"+1 305 251 1194",
    "sg:postcode":"33186",
    "sg:province":"FL",
    "sg:tags":[
        "cleaner",
        "rug",
        "carpet"
    ],
    "wof:name":"Proclean of Miami",
    "wof:placetype":"venue"
},
  "geometry": {"coordinates":[-80.38484200000001,25.654022],"type":"Point"}
}