{
  "type": "Feature",
  "properties": {
    "iso:country":"US",
    "sg:address":"6164 S Congress Ave",
    "sg:city":"Lantana",
    "sg:classifiers":[
        {
            "category":"Shopping",
            "subcategory":"Discount & Variety Stores",
            "type":"Retail Goods"
        }
    ],
    "sg:phone":"+1 561 964 5177",
    "sg:postcode":"33462",
    "sg:province":"FL",
    "wof:name":"Maya Dollar Store",
    "wof:placetype":"venue"
},
  "geometry": {"coordinates":[-80.093914,26.586849],"type":"Point"}
}