{
  "type": "Feature",
  "properties": {
    "iso:country":"US",
    "sg:address":"8372 Beacon Blvd",
    "sg:city":"Fort Myers",
    "sg:classifiers":[
        {
            "category":"Real Estate",
            "subcategory":"Real Estate Operator",
            "type":"Services"
        }
    ],
    "sg:phone":"+1 239 938 0070",
    "sg:postcode":"33907",
    "sg:province":"FL",
    "sg:tags":[
        "apartment"
    ],
    "wof:name":"Palm Villas Apartments",
    "wof:placetype":"venue"
},
  "geometry": {"coordinates":[-81.86750000000001,26.57],"type":"Point"}
}