{
  "type": "Feature",
  "properties": {
    "iso:country":"US",
    "sg:address":"601 14th St S",
    "sg:city":"St Petersburg",
    "sg:classifiers":[
        {
            "category":"Social Services",
            "type":"Services"
        }
    ],
    "sg:phone":"+1 727 822 0298",
    "sg:postcode":"33705",
    "sg:province":"FL",
    "sg:tags":[
        "youth",
        "organization",
        "center"
    ],
    "wof:name":"St Petersburg Jr Football",
    "wof:placetype":"venue"
},
  "geometry": {"coordinates":[-82.65283700000001,27.763294],"type":"Point"}
}