{
  "type": "Feature",
  "properties": {
    "iso:country":"US",
    "sg:address":"5215 N Dixie Hwy",
    "sg:city":"Oakland Park",
    "sg:classifiers":[
        {
            "category":"Travel",
            "subcategory":"Travel Agent",
            "type":"Entertainment"
        }
    ],
    "sg:phone":"+1 954 938 4434",
    "sg:postcode":"33334",
    "sg:province":"FL",
    "sg:tags":[
        "cruise"
    ],
    "wof:name":"Cruises Inc",
    "wof:placetype":"venue"
},
  "geometry": {"coordinates":[-80.132526,26.196068],"type":"Point"}
}