{
  "type": "Feature",
  "properties": {
    "iso:country":"US",
    "sg:address":"1767 Hill Ave",
    "sg:city":"West Palm Beach",
    "sg:classifiers":[
        {
            "category":"Building & Trades",
            "subcategory":"Construction",
            "type":"Services"
        }
    ],
    "sg:phone":"+1 561 842 3196",
    "sg:postcode":"33407",
    "sg:province":"FL",
    "sg:tags":[
        "general",
        "contractor"
    ],
    "wof:name":"Cone & Graham",
    "wof:placetype":"venue"
},
  "geometry": {"coordinates":[-80.07740200000001,26.763085],"type":"Point"}
}