{
  "type": "Feature",
  "properties": {
    "addr:full":"9312 Everwood St Orlando FL 32825",
    "addr:housenumber":"9312",
    "addr:postcode":"32825",
    "addr:street":"Everwood St",
    "iso:country":"US",
    "sg:address":"9312 Everwood St",
    "sg:city":"Orlando",
    "sg:classifiers":[
        {
            "category":"Building & Trades",
            "subcategory":"Construction",
            "type":"Services"
        }
    ],
    "sg:phone":"+1 407 273 5312",
    "sg:postcode":"32825",
    "sg:province":"FL",
    "sg:tags":[
        "contractor"
    ],
    "wof:name":"PNP Tile Inc",
    "wof:placetype":"venue"
},
  "geometry": {"coordinates":[-81.253828,28.536872],"type":"Point"}
}