{
  "type": "Feature",
  "properties": {
    "iso:country":"US",
    "sg:address":"1890 NW 122nd Ter",
    "sg:city":"Hollywood",
    "sg:classifiers":[
        {
            "category":"Social Services",
            "subcategory":"Child Care",
            "type":"Services"
        }
    ],
    "sg:phone":"+1 954 438 4835",
    "sg:postcode":"33026",
    "sg:province":"FL",
    "sg:tags":[
        "day"
    ],
    "wof:name":"Ortiz - Parra Enterprises",
    "wof:placetype":"venue"
},
  "geometry": {"coordinates":[-80.310395,26.023173],"type":"Point"}
}