{
  "type": "Feature",
  "properties": {
    "iso:country":"US",
    "sg:address":"2140 W 68th St",
    "sg:city":"Hialeah",
    "sg:classifiers":[
        {
            "category":"Health Services",
            "subcategory":"Doctor",
            "type":"Services"
        }
    ],
    "sg:phone":"+1 305 557 0211",
    "sg:postcode":"33016",
    "sg:province":"FL",
    "sg:tags":[
        "physician"
    ],
    "wof:name":"Zambrano Carona M M D",
    "wof:placetype":"venue"
},
  "geometry": {"coordinates":[-80.325683,25.884003],"type":"Point"}
}