{
  "type": "Feature",
  "properties": {
    "iso:country":"US",
    "sg:address":"1933 Gamewell Rd",
    "sg:city":"Jacksonville",
    "sg:classifiers":[
        {
            "category":"Retail",
            "subcategory":"Repair Shop",
            "type":"Services"
        },
        {
            "category":"Manufacturing",
            "subcategory":"Building Materials",
            "type":"Manufacturing & Wholesale Goods"
        },
        {
            "category":"Home & Garden",
            "subcategory":"Carpets & Floor Coverings",
            "type":"Retail Goods"
        }
    ],
    "sg:phone":"+1 866 735 1747",
    "sg:postcode":"32211",
    "sg:province":"FL",
    "sg:tags":[
        "materials-wholesale",
        "installation",
        "rug",
        "manufacturer"
    ],
    "wof:name":"CB Flooring, Inc.",
    "wof:placetype":"venue"
},
  "geometry": {"coordinates":[-81.59050499999999,30.340862],"type":"Point"}
}