{
  "type": "Feature",
  "properties": {
    "iso:country":"US",
    "sg:address":"10008 N Dale Mabry Hwy # 110",
    "sg:city":"Tampa",
    "sg:classifiers":[
        {
            "category":"Real Estate",
            "subcategory":"Real Estate Services",
            "type":"Services"
        },
        {
            "category":"Real Estate",
            "subcategory":"Real Estate Agent",
            "type":"Services"
        }
    ],
    "sg:phone":"+1 813 264 7754",
    "sg:postcode":"33618",
    "sg:province":"FL",
    "sg:tags":[
        "buyer",
        "management",
        "broker"
    ],
    "wof:name":"Keller Williams Tampa Properties",
    "wof:placetype":"venue"
},
  "geometry": {"coordinates":[-82.504949,28.040247],"type":"Point"}
}