{
  "type": "Feature",
  "properties": {
    "addr:full":"1032 S Florida Ave Lakeland FL 33803",
    "addr:housenumber":"1032",
    "addr:postcode":"33803",
    "addr:street":"S Florida Ave",
    "iso:country":"US",
    "sg:address":"1032 S Florida Ave",
    "sg:city":"Lakeland",
    "sg:classifiers":[
        {
            "category":"Health Services",
            "subcategory":"Doctor",
            "type":"Services"
        }
    ],
    "sg:phone":"+1 863 619 7040",
    "sg:postcode":"33803",
    "sg:province":"FL",
    "sg:tags":[
        "physician",
        "surgeon"
    ],
    "wof:name":"Medcher Inc",
    "wof:placetype":"venue"
},
  "geometry": {"coordinates":[-81.95704499999999,28.030509],"type":"Point"}
}