{
  "type": "Feature",
  "properties": {
    "addr:full":"263 Tamiami Trl Venice FL 34285",
    "addr:housenumber":"263",
    "addr:postcode":"34285",
    "addr:street":"Tamiami Trl",
    "iso:country":"US",
    "sg:address":"263 Tamiami Trl",
    "sg:city":"Venice",
    "sg:classifiers":[
        {
            "category":"Manufacturing",
            "subcategory":"Printing",
            "type":"Manufacturing & Wholesale Goods"
        }
    ],
    "sg:phone":"+1 941 488 6060",
    "sg:postcode":"34285",
    "sg:province":"FL",
    "sg:tags":[
        "offset"
    ],
    "wof:name":"P & D Printing Inc",
    "wof:placetype":"venue"
},
  "geometry": {"coordinates":[-82.444227,27.09738],"type":"Point"}
}