{
  "type": "Feature",
  "properties": {
    "iso:country":"US",
    "sg:address":"6 Edith Ln",
    "sg:city":"Palm Coast",
    "sg:classifiers":[
        {
            "category":"Restaurant",
            "type":"Food & Drink"
        }
    ],
    "sg:phone":"+1 386 437 3195",
    "sg:postcode":"32164",
    "sg:province":"FL",
    "sg:tags":[
        "eating"
    ],
    "wof:name":"Red Gator Cafe Co",
    "wof:placetype":"venue"
},
  "geometry": {"coordinates":[-81.24594500000001,29.482862],"type":"Point"}
}