{
  "type": "Feature",
  "properties": {
    "iso:country":"US",
    "sg:address":"12706 Cambridge Ave",
    "sg:city":"Tampa",
    "sg:classifiers":[
        {
            "category":"Professional",
            "subcategory":"Management & Consulting",
            "type":"Services"
        }
    ],
    "sg:phone":"+1 813 908 2252",
    "sg:postcode":"33624",
    "sg:province":"FL",
    "sg:tags":[
        "retail",
        "direct",
        "sales"
    ],
    "wof:name":"Lauren A Huckabee",
    "wof:placetype":"venue"
},
  "geometry": {"coordinates":[-82.53034100000001,28.062279],"type":"Point"}
}