{
  "type": "Feature",
  "properties": {
    "iso:country":"US",
    "sg:address":"475 S Kirkman Rd",
    "sg:city":"Orlando",
    "sg:classifiers":[
        {
            "category":"Professional",
            "subcategory":"Business Services",
            "type":"Services"
        }
    ],
    "sg:phone":"+1 407 293 7528",
    "sg:postcode":"32811",
    "sg:province":"FL",
    "sg:tags":[
        "convention",
        "meeting",
        "facility"
    ],
    "wof:name":"Rotary Club Of West Orlando",
    "wof:placetype":"venue"
},
  "geometry": {"coordinates":[-81.458157,28.538002],"type":"Point"}
}