{
  "type": "Feature",
  "properties": {
    "addr:full":"4944 N University Dr Fort Lauderdale FL 33351",
    "addr:housenumber":"4944",
    "addr:postcode":"33351",
    "addr:street":"N University Dr",
    "iso:country":"US",
    "sg:address":"4944 N University Dr",
    "sg:city":"Fort Lauderdale",
    "sg:classifiers":[
        {
            "category":"Banks & Credit Unions",
            "subcategory":"Bank",
            "type":"Services"
        }
    ],
    "sg:phone":"+1 954 435 4786",
    "sg:postcode":"33351",
    "sg:province":"FL",
    "sg:tags":[
        "loan",
        "consumer",
        "institution"
    ],
    "wof:name":"Avco Financial",
    "wof:placetype":"venue"
},
  "geometry": {"coordinates":[-80.251681,26.184049],"type":"Point"}
}