{
  "type": "Feature",
  "properties": {
    "iso:country":"US",
    "sg:address":"3375 US Hwy 98",
    "sg:city":"Lakeland",
    "sg:classifiers":[
        {
            "category":"Manufacturing",
            "subcategory":"Buildings",
            "type":"Manufacturing & Wholesale Goods"
        }
    ],
    "sg:phone":"+1 863 667 2550",
    "sg:postcode":"33803",
    "sg:province":"FL",
    "sg:tags":[
        "prefab"
    ],
    "wof:name":"Michael Powell Mfr Homes",
    "wof:placetype":"venue"
},
  "geometry": {"coordinates":[-81.906233,28.006562],"type":"Point"}
}