{
  "type": "Feature",
  "properties": {
    "iso:country":"US",
    "sg:address":"9101 International Dr",
    "sg:city":"Orlando",
    "sg:classifiers":[
        {
            "category":"Restaurant",
            "type":"Food & Drink"
        }
    ],
    "sg:menulink":"http://www.allmenus.com/fl/southwest-orange/270032-taverna-opa---orlando/menu/",
    "sg:phone":"+1 407 351 8660",
    "sg:postcode":"32819",
    "sg:province":"FL",
    "sg:tags":[
        "greek"
    ],
    "wof:name":"Taverna Opa - Orlando",
    "wof:placetype":"venue"
},
  "geometry": {"coordinates":[-81.470226,28.432394],"type":"Point"}
}