{
  "type": "Feature",
  "properties": {
    "iso:country":"US",
    "sg:address":"901 NW 41st Ave",
    "sg:city":"Miami",
    "sg:classifiers":[
        {
            "category":"Retail",
            "subcategory":"Repair Shop",
            "type":"Services"
        }
    ],
    "sg:phone":"+1 305 541 3449",
    "sg:postcode":"33126",
    "sg:province":"FL",
    "sg:tags":[
        "typewriter"
    ],
    "wof:name":"Master Typewriter Svc",
    "wof:placetype":"venue"
},
  "geometry": {"coordinates":[-80.263026,25.782467],"type":"Point"}
}