{
  "type": "Feature",
  "properties": {
    "iso:country":"US",
    "sg:address":"631 US Hwy 231",
    "sg:city":"Panama City",
    "sg:classifiers":[
        {
            "category":"Banks & Credit Unions",
            "subcategory":"Bank",
            "type":"Services"
        }
    ],
    "sg:phone":"+1 850 522 5930",
    "sg:postcode":"32405",
    "sg:province":"FL",
    "sg:tags":[
        "loan"
    ],
    "wof:name":"Panama City Financial Svc Inc",
    "wof:placetype":"venue"
},
  "geometry": {"coordinates":[-85.650424,30.182803],"type":"Point"}
}