{
  "type": "Feature",
  "properties": {
    "addr:full":"700 S State St Bunnell FL 32110",
    "addr:housenumber":"700",
    "addr:postcode":"32110",
    "addr:street":"S State St",
    "iso:country":"US",
    "sg:address":"700 S State St",
    "sg:city":"Bunnell",
    "sg:classifiers":[
        {
            "category":"Shopping",
            "subcategory":"Bicycles & Sporting Goods",
            "type":"Retail Goods"
        }
    ],
    "sg:phone":"+1 386 437 4400",
    "sg:postcode":"32110",
    "sg:province":"FL",
    "sg:tags":[
        "horse",
        "furnishing"
    ],
    "wof:name":"Silver Bit Tack Resale Inc",
    "wof:placetype":"venue"
},
  "geometry": {"coordinates":[-81.25165,29.461579],"type":"Point"}
}