{
  "type": "Feature",
  "properties": {
    "iso:country":"US",
    "sg:address":"2525 W Sunset Dr",
    "sg:city":"Tampa",
    "sg:classifiers":[
        {
            "category":"Health Services",
            "subcategory":"Doctor",
            "type":"Services"
        }
    ],
    "sg:phone":"+1 813 974 2681",
    "sg:postcode":"33629",
    "sg:province":"FL",
    "sg:tags":[
        "medical"
    ],
    "wof:name":"Frank B Vasey",
    "wof:placetype":"venue"
},
  "geometry": {"coordinates":[-82.48997,27.931556],"type":"Point"}
}