{
  "type": "Feature",
  "properties": {
    "addr:full":"10655 NW 29th Ter Miami FL 33172",
    "addr:housenumber":"10655",
    "addr:postcode":"33172",
    "addr:street":"Nw 29Th Ter",
    "iso:country":"US",
    "sg:address":"10655 NW 29th Ter",
    "sg:city":"Miami",
    "sg:classifiers":[
        {
            "category":"Shopping",
            "subcategory":"Pharmacy",
            "type":"Retail Goods"
        }
    ],
    "sg:phone":"+1 305 463 2290",
    "sg:postcode":"33172",
    "sg:province":"FL",
    "sg:tags":[
        "drugstore"
    ],
    "wof:name":"Pharmacy Benefit Administrators",
    "wof:placetype":"venue"
},
  "geometry": {"coordinates":[-80.368497,25.801434],"type":"Point"}
}