{
  "type": "Feature",
  "properties": {
    "addr:full":"401 E Las Olas Blvd Fort Lauderdale FL 33301",
    "addr:housenumber":"401",
    "addr:postcode":"33301",
    "addr:street":"E Las Olas Blvd",
    "iso:country":"US",
    "sg:address":"401 E Las Olas Blvd",
    "sg:city":"Fort Lauderdale",
    "sg:classifiers":[
        {
            "category":"Banks & Credit Unions",
            "subcategory":"Bank",
            "type":"Services"
        }
    ],
    "sg:phone":"+1 954 524 6581",
    "sg:postcode":"33301",
    "sg:province":"FL",
    "wof:name":"Bank Of America",
    "wof:placetype":"venue"
},
  "geometry": {"coordinates":[-80.13861799999999,26.119204],"type":"Point"}
}