{
  "type": "Feature",
  "properties": {
    "iso:country":"US",
    "sg:address":"5041 Sandy Shore Ave",
    "sg:city":"Sarasota",
    "sg:classifiers":[
        {
            "category":"Recreation",
            "type":"Entertainment"
        }
    ],
    "sg:phone":"+1 941 346 5040",
    "sg:postcode":"34242",
    "sg:province":"FL",
    "wof:name":"Blue Dog Fishing Charters",
    "wof:placetype":"venue"
},
  "geometry": {"coordinates":[-82.556152,27.277717],"type":"Point"}
}