{
  "type": "Feature",
  "properties": {
    "iso:country":"US",
    "sg:address":"5474 Blue Pacific Dr",
    "sg:city":"Jacksonville",
    "sg:classifiers":[
        {
            "category":"Professional",
            "subcategory":"Research",
            "type":"Services"
        }
    ],
    "sg:phone":"+1 904 880 3300",
    "sg:postcode":"32257",
    "sg:province":"FL",
    "sg:tags":[
        "foundation",
        "philanthropic"
    ],
    "wof:name":"Aerospace Inc",
    "wof:placetype":"venue"
},
  "geometry": {"coordinates":[-81.566164,30.181955],"type":"Point"}
}