{
  "type": "Feature",
  "properties": {
    "iso:country":"US",
    "sg:address":"2401 Beneva Rd",
    "sg:city":"Sarasota",
    "sg:classifiers":[
        {
            "category":"Sports & Exercise",
            "subcategory":"Golf",
            "type":"Entertainment"
        }
    ],
    "sg:phone":"+1 941 922 9199",
    "sg:postcode":"34232",
    "sg:province":"FL",
    "sg:tags":[
        "country",
        "semi"
    ],
    "wof:name":"Forest Lakes Golf Club",
    "wof:placetype":"venue"
},
  "geometry": {"coordinates":[-82.49747499999999,27.30989],"type":"Point"}
}