{
  "type": "Feature",
  "properties": {
    "iso:country":"US",
    "sg:address":"997 Captiva Dr",
    "sg:city":"Hollywood",
    "sg:classifiers":[
        {
            "category":"Professional",
            "type":"Services"
        }
    ],
    "sg:phone":"+1 954 458 9333",
    "sg:postcode":"33019",
    "sg:province":"FL",
    "sg:tags":[
        "establishment"
    ],
    "wof:name":"Direct Source Intl Inc",
    "wof:placetype":"venue"
},
  "geometry": {"coordinates":[-80.125105,26.003697],"type":"Point"}
}