{
  "type": "Feature",
  "properties": {
    "addr:full":"13519 1st St E Saint Petersburg FL 33708",
    "addr:housenumber":"13519",
    "addr:postcode":"33708",
    "addr:street":"1St St E",
    "iso:country":"US",
    "sg:address":"13519 1st St E",
    "sg:city":"Saint Petersburg",
    "sg:classifiers":[
        {
            "category":"Real Estate",
            "subcategory":"Real Estate Agent",
            "type":"Services"
        }
    ],
    "sg:phone":"+1 727 391 2194",
    "sg:postcode":"33708",
    "sg:province":"FL",
    "wof:name":"Scott & Laura Ellis",
    "wof:placetype":"venue"
},
  "geometry": {"coordinates":[-82.787601,27.791225],"type":"Point"}
}