{
  "type": "Feature",
  "properties": {
    "iso:country":"US",
    "sg:address":"65 Harbor Dr",
    "sg:city":"Key Biscayne",
    "sg:classifiers":[
        {
            "category":"Shopping",
            "subcategory":"Florist",
            "type":"Retail Goods"
        }
    ],
    "sg:phone":"+1 305 365 9505",
    "sg:postcode":"33149",
    "sg:province":"FL",
    "wof:name":"Blooming Flowers Inc",
    "wof:placetype":"venue"
},
  "geometry": {"coordinates":[-80.16330000000001,25.6992],"type":"Point"}
}