{
  "type": "Feature",
  "properties": {
    "addr:full":"438 W Brevard St Tallahassee FL 32301",
    "addr:housenumber":"438",
    "addr:postcode":"32301",
    "addr:street":"W Brevard St",
    "iso:country":"US",
    "sg:address":"438 W Brevard St",
    "sg:city":"Tallahassee",
    "sg:classifiers":[
        {
            "category":"Social Services",
            "subcategory":"Child Care",
            "type":"Services"
        }
    ],
    "sg:phone":"+1 850 222 7356",
    "sg:postcode":"32301",
    "sg:province":"FL",
    "sg:tags":[
        "center"
    ],
    "wof:name":"Lincoln Child Care Center",
    "wof:placetype":"venue"
},
  "geometry": {"coordinates":[-84.28748899999999,30.449156],"type":"Point"}
}