{
  "type": "Feature",
  "properties": {
    "iso:country":"US",
    "sg:address":"1544 Saddle Ct",
    "sg:city":"Palm Harbor",
    "sg:classifiers":[
        {
            "category":"Manufacturing",
            "subcategory":"Building Materials",
            "type":"Manufacturing & Wholesale Goods"
        }
    ],
    "sg:phone":"+1 727 771 9187",
    "sg:postcode":"34683",
    "sg:province":"FL",
    "sg:tags":[
        "mfg"
    ],
    "wof:name":"Wood Creations",
    "wof:placetype":"venue"
},
  "geometry": {"coordinates":[-82.758634,28.059452],"type":"Point"}
}