{
  "type": "Feature",
  "properties": {
    "iso:country":"US",
    "sg:address":"195 E 9th St",
    "sg:city":"Hialeah",
    "sg:classifiers":[
        {
            "category":"Manufacturing",
            "subcategory":"Metals",
            "type":"Manufacturing & Wholesale Goods"
        },
        {
            "category":"Manufacturing",
            "subcategory":"Building Materials",
            "type":"Manufacturing & Wholesale Goods"
        }
    ],
    "sg:phone":"+1 305 887 8767",
    "sg:postcode":"33010",
    "sg:province":"FL",
    "sg:tags":[
        "door",
        "window",
        "windows-metal",
        "storm"
    ],
    "wof:name":"House Of Windows Inc",
    "wof:placetype":"venue"
},
  "geometry": {"coordinates":[-80.27767,25.830048],"type":"Point"}
}