{
  "type": "Feature",
  "properties": {
    "addr:full":"4452 Royal Fern Way Palm Beach Gardens FL 33410",
    "addr:housenumber":"4452",
    "addr:postcode":"33410",
    "addr:street":"Royal Fern Way",
    "iso:country":"US",
    "sg:address":"4452 Royal Fern Way",
    "sg:city":"Palm Beach Gardens",
    "sg:classifiers":[
        {
            "category":"Wholesale",
            "subcategory":"Wine & Distilled Alcoholic Beverages",
            "type":"Manufacturing & Wholesale Goods"
        }
    ],
    "sg:phone":"+1 561 622 7581",
    "sg:postcode":"33410",
    "sg:province":"FL",
    "sg:tags":[
        "import"
    ],
    "wof:name":"D & V International Inc",
    "wof:placetype":"venue"
},
  "geometry": {"coordinates":[-80.10591599999999,26.800753],"type":"Point"}
}