{
  "type": "Feature",
  "properties": {
    "addr:full":"6999 W Colonial Dr Orlando FL 32818",
    "addr:housenumber":"6999",
    "addr:postcode":"32818",
    "addr:street":"W Colonial Dr",
    "iso:country":"US",
    "sg:address":"6999 W Colonial Dr",
    "sg:city":"Orlando",
    "sg:classifiers":[
        {
            "category":"Autos & Motor Vehicles",
            "subcategory":"Fuel & Gas Station",
            "type":"Retail Goods"
        }
    ],
    "sg:phone":"+1 407 290 2414",
    "sg:postcode":"32818",
    "sg:province":"FL",
    "sg:tags":[
        "oil"
    ],
    "wof:name":"Shiva Food Mart Inc",
    "wof:placetype":"venue"
},
  "geometry": {"coordinates":[-81.47552399999999,28.552089],"type":"Point"}
}