{
  "type": "Feature",
  "properties": {
    "iso:country":"US",
    "sg:address":"738 Beachland Blvd",
    "sg:city":"Vero Beach",
    "sg:classifiers":[
        {
            "category":"Banks & Credit Unions",
            "subcategory":"Bank",
            "type":"Services"
        }
    ],
    "sg:phone":"+1 772 234 3977",
    "sg:postcode":"32963",
    "sg:province":"FL",
    "sg:tags":[
        "banker",
        "mortgage"
    ],
    "wof:name":"Chase Manhattan",
    "wof:placetype":"venue"
},
  "geometry": {"coordinates":[-80.359281,27.65332],"type":"Point"}
}