{
  "type": "Feature",
  "properties": {
    "iso:country":"US",
    "sg:address":"2901 Collins Ave",
    "sg:city":"Miami Beach",
    "sg:classifiers":[
        {
            "category":"Travel",
            "subcategory":"Hotels & Motels",
            "type":"Entertainment"
        }
    ],
    "sg:phone":"+1 305 672 5466",
    "sg:postcode":"33140",
    "sg:province":"FL",
    "wof:name":"Lionstone Hotels & Resort",
    "wof:placetype":"venue"
},
  "geometry": {"coordinates":[-80.12455,25.805882],"type":"Point"}
}