{
  "type": "Feature",
  "properties": {
    "addr:full":"902 Outback Rd Saint Cloud FL 34771",
    "addr:housenumber":"902",
    "addr:postcode":"34771",
    "addr:street":"Outback Rd",
    "iso:country":"US",
    "sg:address":"902 Outback Rd",
    "sg:city":"Saint Cloud",
    "sg:classifiers":[
        {
            "category":"Building & Trades",
            "subcategory":"Construction",
            "type":"Services"
        }
    ],
    "sg:phone":"+1 407 891 0651",
    "sg:postcode":"34771",
    "sg:province":"FL",
    "sg:tags":[
        "house"
    ],
    "wof:name":"Dwayne Clark Decking",
    "wof:placetype":"venue"
},
  "geometry": {"coordinates":[-81.19468999999999,28.301819],"type":"Point"}
}