{
  "type": "Feature",
  "properties": {
    "iso:country":"US",
    "sg:address":"7420 SW 8th St",
    "sg:city":"Miami",
    "sg:classifiers":[
        {
            "category":"Retail",
            "subcategory":"Auto Repair",
            "type":"Services"
        }
    ],
    "sg:phone":"+1 305 269 0039",
    "sg:postcode":"33144",
    "sg:province":"FL",
    "wof:name":"Jesus Auto Tech",
    "wof:placetype":"venue"
},
  "geometry": {"coordinates":[-80.31619999999999,25.762699],"type":"Point"}
}