{
  "type": "Feature",
  "properties": {
    "addr:full":"8652 NW 10th Ct Plantation FL 33322",
    "addr:housenumber":"8652",
    "addr:postcode":"33322",
    "addr:street":"Nw 10Th Ct",
    "iso:country":"US",
    "sg:address":"8652 NW 10th Ct",
    "sg:city":"Plantation",
    "sg:classifiers":[
        {
            "category":"Wholesale",
            "subcategory":"Machinery & Supplies",
            "type":"Manufacturing & Wholesale Goods"
        }
    ],
    "sg:phone":"+1 954 236 5705",
    "sg:postcode":"33322",
    "sg:province":"FL",
    "sg:tags":[
        "industrial",
        "equipment",
        "used",
        "machinery-new",
        "supplies-wholesale"
    ],
    "wof:name":"Hem International",
    "wof:placetype":"venue"
},
  "geometry": {"coordinates":[-80.26497000000001,26.136841],"type":"Point"}
}