{
  "type": "Feature",
  "properties": {
    "addr:full":"2523 US Hwy 27 Avon Park FL 33825",
    "addr:housenumber":"2523",
    "addr:postcode":"33825",
    "addr:street":"Us Hwy 27",
    "iso:country":"US",
    "sg:address":"2523 US Hwy 27",
    "sg:city":"Avon Park",
    "sg:classifiers":[
        {
            "category":"Social Services",
            "type":"Services"
        }
    ],
    "sg:phone":"+1 863 452 6900",
    "sg:postcode":"33825",
    "sg:province":"FL",
    "sg:tags":[
        "youth",
        "organization",
        "center"
    ],
    "wof:name":"Youth & Family Alternatives",
    "wof:placetype":"venue"
},
  "geometry": {"coordinates":[-81.51670900000001,27.631464],"type":"Point"}
}