{
  "type": "Feature",
  "properties": {
    "iso:country":"US",
    "sg:address":"2650 S Mccall Rd",
    "sg:city":"Englewood",
    "sg:classifiers":[
        {
            "category":"Health Services",
            "subcategory":"Doctor",
            "type":"Services"
        }
    ],
    "sg:phone":"+1 941 473 9505",
    "sg:postcode":"34224",
    "sg:province":"FL",
    "sg:tags":[
        "medicine",
        "physician",
        "practice",
        "surgeons",
        "family"
    ],
    "wof:name":"Susan Binoy, M.D., P.A.",
    "wof:placetype":"venue"
},
  "geometry": {"coordinates":[-82.315928,26.93466],"type":"Point"}
}