{
  "type": "Feature",
  "properties": {
    "addr:full":"1221 Brickell Avenue Suite 213 Miami FL 33131",
    "addr:housenumber":"1221",
    "addr:postcode":"33131",
    "addr:street":"Brickell Avenue Suite 213",
    "iso:country":"US",
    "sg:address":"1221 Brickell Avenue Suite 213",
    "sg:city":"Miami",
    "sg:classifiers":[
        {
            "category":"Manufacturing",
            "subcategory":"Petroleum Products",
            "type":"Manufacturing & Wholesale Goods"
        },
        {
            "category":"Food & Beverages",
            "subcategory":"Farmers Market",
            "type":"Retail Goods"
        },
        {
            "category":"Utilities",
            "subcategory":"Fuel Oil & Lpg",
            "type":"Services"
        }
    ],
    "sg:phone":"+1 305 576 7835",
    "sg:postcode":"33131",
    "sg:province":"FL",
    "sg:tags":[
        "operator",
        "oils-fuel",
        "oils-industrial",
        "oils-petroleum"
    ],
    "sg:website":"http://gettraders.com",
    "wof:name":"G.E.T International",
    "wof:placetype":"venue"
},
  "geometry": {"coordinates":[-80.191788,25.761721],"type":"Point"}
}