{
  "type": "Feature",
  "properties": {
    "iso:country":"US",
    "sg:address":"3500 NW 48th Ave",
    "sg:city":"Lauderdale Lakes",
    "sg:classifiers":[
        {
            "category":"Professional",
            "subcategory":"Business Services",
            "type":"Services"
        }
    ],
    "sg:phone":"+1 954 731 9139",
    "sg:postcode":"33319",
    "sg:province":"FL",
    "sg:tags":[
        "translator",
        "interpreter"
    ],
    "wof:name":"Total Translations Inc",
    "wof:placetype":"venue"
},
  "geometry": {"coordinates":[-80.21334899999999,26.172442],"type":"Point"}
}