{
  "type": "Feature",
  "properties": {
    "addr:full":"6750 Panther Ln Fort Myers FL 33919",
    "addr:housenumber":"6750",
    "addr:postcode":"33919",
    "addr:street":"Panther Ln",
    "iso:country":"US",
    "sg:address":"6750 Panther Ln",
    "sg:city":"Fort Myers",
    "sg:classifiers":[
        {
            "category":"Education",
            "subcategory":"School",
            "type":"Public Place"
        }
    ],
    "sg:phone":"+1 239 481 2233",
    "sg:postcode":"33919",
    "sg:province":"FL",
    "sg:tags":[
        "high",
        "middle",
        "elementary"
    ],
    "sg:website":"www.leeschools.net/schools/cyh",
    "wof:name":"School District of Lee County Elementary Schools",
    "wof:placetype":"venue"
},
  "geometry": {"coordinates":[-81.90075299999999,26.540425],"type":"Point"}
}