{
  "type": "Feature",
  "properties": {
    "iso:country":"US",
    "sg:address":"3987 W Tennessee St",
    "sg:city":"Tallahassee",
    "sg:classifiers":[
        {
            "category":"Retail",
            "subcategory":"Auto Rental",
            "type":"Services"
        }
    ],
    "sg:phone":"+1 850 574 4321",
    "sg:postcode":"32304",
    "sg:province":"FL",
    "sg:tags":[
        "renting",
        "automobile"
    ],
    "wof:name":"Enterprise Rent-A-Car",
    "wof:placetype":"venue"
},
  "geometry": {"coordinates":[-84.354191,30.459199],"type":"Point"}
}