{
  "type": "Feature",
  "properties": {
    "iso:country":"US",
    "sg:address":"3570 Palm Dr",
    "sg:city":"West Palm Beach",
    "sg:classifiers":[
        {
            "category":"Retail",
            "subcategory":"Repair Shop",
            "type":"Services"
        }
    ],
    "sg:phone":"+1 561 689 0003",
    "sg:postcode":"33404",
    "sg:province":"FL",
    "sg:tags":[
        "equipment",
        "telephone",
        "system"
    ],
    "wof:name":"INTEGRATED Telecom Sltns",
    "wof:placetype":"venue"
},
  "geometry": {"coordinates":[-80.05212,26.79126],"type":"Point"}
}