{
  "type": "Feature",
  "properties": {
    "iso:country":"US",
    "sg:address":"25 SE 7th St",
    "sg:city":"Deerfield Beach",
    "sg:classifiers":[
        {
            "category":"Manufacturing",
            "subcategory":"Wood Products",
            "type":"Manufacturing & Wholesale Goods"
        },
        {
            "category":"Building & Trades",
            "subcategory":"Construction",
            "type":"Services"
        }
    ],
    "sg:phone":"+1 954 421 1100",
    "sg:postcode":"33441",
    "sg:province":"FL",
    "sg:tags":[
        "mfg",
        "woodworker"
    ],
    "wof:name":"T & M Woodworking",
    "wof:placetype":"venue"
},
  "geometry": {"coordinates":[-80.10227500000001,26.309657],"type":"Point"}
}