{
  "type": "Feature",
  "properties": {
    "iso:country":"US",
    "sg:address":"220 SE Saint Johns St",
    "sg:city":"Lake City",
    "sg:classifiers":[
        {
            "category":"Insurance",
            "subcategory":"Insurance Agent",
            "type":"Services"
        }
    ],
    "sg:phone":"+1 386 752 3586",
    "sg:postcode":"32025",
    "sg:province":"FL",
    "wof:name":"Brown & Associates",
    "wof:placetype":"venue"
},
  "geometry": {"coordinates":[-82.63587200000001,30.187926],"type":"Point"}
}