{
  "type": "Feature",
  "properties": {
    "iso:country":"US",
    "sg:address":"1640 Lands End Rd",
    "sg:city":"Lake Worth",
    "sg:classifiers":[
        {
            "category":"Professional",
            "type":"Services"
        }
    ],
    "sg:phone":"+1 561 547 9700",
    "sg:postcode":"33462",
    "sg:province":"FL",
    "wof:name":"Product Counselors Inc",
    "wof:placetype":"venue"
},
  "geometry": {"coordinates":[-80.04568,26.559717],"type":"Point"}
}