{
  "type": "Feature",
  "properties": {
    "iso:country":"US",
    "sg:address":"4000 NW 31st Ave",
    "sg:city":"Miami",
    "sg:classifiers":[
        {
            "category":"Wholesale",
            "subcategory":"Machinery & Supplies",
            "type":"Manufacturing & Wholesale Goods"
        }
    ],
    "sg:phone":"+1 305 638 3343",
    "sg:postcode":"33142",
    "sg:province":"FL",
    "sg:tags":[
        "packaging",
        "rope"
    ],
    "sg:website":"http://www.edgecordage.com",
    "wof:name":"Edge Cordage Co Inc",
    "wof:placetype":"venue"
},
  "geometry": {"coordinates":[-80.246437,25.81168],"type":"Point"}
}