{
  "type": "Feature",
  "properties": {
    "addr:full":"231 21st Ave St Pete Beach FL 33706",
    "addr:housenumber":"231",
    "addr:postcode":"33706",
    "addr:street":"21St Ave St Pete Beach",
    "iso:country":"US",
    "sg:address":"231 21st Ave",
    "sg:city":"St Pete Beach",
    "sg:classifiers":[
        {
            "category":"Professional",
            "subcategory":"Advertising",
            "type":"Services"
        }
    ],
    "sg:phone":"+1 727 368 0060",
    "sg:postcode":"33706",
    "sg:province":"FL",
    "sg:tags":[
        "counselor",
        "agency"
    ],
    "wof:name":"Ausec Group",
    "wof:placetype":"venue"
},
  "geometry": {"coordinates":[-82.73399000000001,27.697002],"type":"Point"}
}