{
  "type": "Feature",
  "properties": {
    "iso:country":"US",
    "sg:address":"8120 Fieldside Dr W",
    "sg:city":"Jacksonville",
    "sg:classifiers":[
        {
            "category":"Travel",
            "subcategory":"Travel Agent",
            "type":"Entertainment"
        }
    ],
    "sg:phone":"+1 904 779 9375",
    "sg:postcode":"32244",
    "sg:province":"FL",
    "sg:tags":[
        "agency"
    ],
    "wof:name":"Lolitas Travel",
    "wof:placetype":"venue"
},
  "geometry": {"coordinates":[-81.80157699999999,30.19843],"type":"Point"}
}