{
  "type": "Feature",
  "properties": {
    "addr:full":"25 Gulf Manor Dr Venice FL 34285",
    "addr:housenumber":"25",
    "addr:postcode":"34285",
    "addr:street":"Gulf Manor Dr",
    "iso:country":"US",
    "sg:address":"25 Gulf Manor Dr",
    "sg:city":"Venice",
    "sg:classifiers":[
        {
            "category":"Autos & Motor Vehicles",
            "subcategory":"Automobile Sales",
            "type":"Retail Goods"
        }
    ],
    "sg:phone":"+1 941 483 9212",
    "sg:postcode":"34285",
    "sg:province":"FL",
    "sg:tags":[
        "sales"
    ],
    "wof:name":"Discount Motors",
    "wof:placetype":"venue"
},
  "geometry": {"coordinates":[-82.456614,27.092917],"type":"Point"}
}