{
  "type": "Feature",
  "properties": {
    "iso:country":"US",
    "sg:address":"3251 S Palm Ave",
    "sg:city":"Daytona Beach",
    "sg:classifiers":[
        {
            "category":"Manufacturing",
            "subcategory":"Apparel",
            "type":"Manufacturing & Wholesale Goods"
        }
    ],
    "sg:phone":"+1 386 763 3071",
    "sg:postcode":"32177",
    "sg:province":"FL",
    "sg:tags":[
        "product",
        "mfg"
    ],
    "wof:name":"Vivid Canvas LLC",
    "wof:placetype":"venue"
},
  "geometry": {"coordinates":[-81.66171,29.624313],"type":"Point"}
}