{
  "type": "Feature",
  "properties": {
    "addr:full":"7795 W Flagler St Miami FL 33144",
    "addr:housenumber":"7795",
    "addr:postcode":"33144",
    "addr:street":"W Flagler St",
    "iso:country":"US",
    "sg:address":"7795 W Flagler St",
    "sg:city":"Miami",
    "sg:classifiers":[
        {
            "category":"Shopping",
            "subcategory":"Department Store",
            "type":"Retail Goods"
        }
    ],
    "sg:phone":"+1 305 264 1203",
    "sg:postcode":"33144",
    "sg:province":"FL",
    "sg:website":"http://www.rossstores.com",
    "wof:name":"Ross Dress For Less",
    "wof:placetype":"venue"
},
  "geometry": {"coordinates":[-80.323764,25.76988],"type":"Point"}
}