{
  "type": "Feature",
  "properties": {
    "iso:country":"US",
    "sg:address":"6133 Stewart St",
    "sg:city":"Milton",
    "sg:classifiers":[
        {
            "category":"Education",
            "subcategory":"School",
            "type":"Public Place"
        }
    ],
    "sg:phone":"+1 850 983 5143",
    "sg:postcode":"32570",
    "sg:province":"FL",
    "sg:tags":[
        "district"
    ],
    "sg:website":"http://www.santarosa.k12.fl.us",
    "wof:name":"County Of Santa Rosa Board Of Public Instruction",
    "wof:placetype":"venue"
},
  "geometry": {"coordinates":[-87.048107,30.657942],"type":"Point"}
}