{
  "type": "Feature",
  "properties": {
    "addr:full":"340 NW 3rd Ave Deerfield Beach FL 33441",
    "addr:housenumber":"340",
    "addr:postcode":"33441",
    "addr:street":"Nw 3Rd Ave",
    "iso:country":"US",
    "sg:address":"340 NW 3rd Ave",
    "sg:city":"Deerfield Beach",
    "sg:classifiers":[
        {
            "category":"Social Services",
            "subcategory":"Child Care",
            "type":"Services"
        }
    ],
    "sg:phone":"+1 954 481 9977",
    "sg:postcode":"33441",
    "sg:province":"FL",
    "sg:tags":[
        "day"
    ],
    "wof:name":"Rattray Economic Dev Ctr",
    "wof:placetype":"venue"
},
  "geometry": {"coordinates":[-80.107978,26.323174],"type":"Point"}
}