{
  "type": "Feature",
  "properties": {
    "iso:country":"US",
    "sg:address":"5803 Tolman Ct",
    "sg:city":"Tampa",
    "sg:classifiers":[
        {
            "category":"Professional",
            "subcategory":"Accounting & Tax Preparation",
            "type":"Services"
        }
    ],
    "sg:phone":"+1 813 971 4067",
    "sg:postcode":"33647",
    "sg:province":"FL",
    "wof:name":"Gary D Meyer CPA",
    "wof:placetype":"venue"
},
  "geometry": {"coordinates":[-82.391424,28.098072],"type":"Point"}
}