{
  "type": "Feature",
  "properties": {
    "iso:country":"US",
    "sg:address":"1798 Thomasville Rd",
    "sg:city":"Tallahassee",
    "sg:classifiers":[
        {
            "category":"Professional",
            "subcategory":"Engineering",
            "type":"Services"
        }
    ],
    "sg:phone":"+1 850 668 7800",
    "sg:postcode":"32303",
    "sg:province":"FL",
    "sg:tags":[
        "engineer"
    ],
    "wof:name":"Hargraves Engineering",
    "wof:placetype":"venue"
},
  "geometry": {"coordinates":[-84.269884,30.464958],"type":"Point"}
}