{
  "type": "Feature",
  "properties": {
    "iso:country":"US",
    "sg:address":"7350 Blanding Blvd",
    "sg:city":"Jacksonville",
    "sg:classifiers":[
        {
            "category":"Building & Trades",
            "subcategory":"Construction",
            "type":"Services"
        }
    ],
    "sg:phone":"+1 904 908 9945",
    "sg:postcode":"32244",
    "sg:province":"FL",
    "sg:tags":[
        "painter"
    ],
    "wof:name":"Neslon Painting Svc",
    "wof:placetype":"venue"
},
  "geometry": {"coordinates":[-81.738541,30.20948],"type":"Point"}
}