{
  "type": "Feature",
  "properties": {
    "addr:full":"917 NE 24th Ave Hallandale FL 33009",
    "addr:housenumber":"917",
    "addr:postcode":"33009",
    "addr:street":"Ne 24Th Ave",
    "iso:country":"US",
    "sg:address":"917 NE 24th Ave",
    "sg:city":"Hallandale",
    "sg:classifiers":[
        {
            "category":"Real Estate",
            "subcategory":"Developer",
            "type":"Services"
        }
    ],
    "sg:phone":"+1 954 454 5626",
    "sg:postcode":"33009",
    "sg:province":"FL",
    "wof:name":"Alliage Development Inc",
    "wof:placetype":"venue"
},
  "geometry": {"coordinates":[-80.12543100000001,25.996707],"type":"Point"}
}