{
  "type": "Feature",
  "properties": {
    "iso:country":"US",
    "sg:address":"3008 Bonita Dr",
    "sg:city":"Plant City",
    "sg:classifiers":[
        {
            "category":"Home & Garden",
            "subcategory":"Garden Supply",
            "type":"Retail Goods"
        }
    ],
    "sg:phone":"+1 813 752 2887",
    "sg:postcode":"33566",
    "sg:province":"FL",
    "sg:tags":[
        "nurseryman"
    ],
    "wof:name":"Free's Nursery",
    "wof:placetype":"venue"
},
  "geometry": {"coordinates":[-82.135599,27.980047],"type":"Point"}
}