{
  "type": "Feature",
  "properties": {
    "addr:full":"6328 Memorial Hwy Tampa FL 33615",
    "addr:housenumber":"6328",
    "addr:postcode":"33615",
    "addr:street":"Memorial Hwy",
    "iso:country":"US",
    "sg:address":"6328 Memorial Hwy",
    "sg:city":"Tampa",
    "sg:classifiers":[
        {
            "category":"Building & Trades",
            "subcategory":"Cleaning & Sanitation",
            "type":"Services"
        }
    ],
    "sg:phone":"+1 813 884 8589",
    "sg:postcode":"33615",
    "sg:province":"FL",
    "sg:tags":[
        "butler",
        "maid"
    ],
    "wof:name":"Customized Cleaning",
    "wof:placetype":"venue"
},
  "geometry": {"coordinates":[-82.578003,27.992988],"type":"Point"}
}