{
  "type": "Feature",
  "properties": {
    "addr:full":"970 W 32nd St Hialeah FL 33012",
    "addr:housenumber":"970",
    "addr:postcode":"33012",
    "addr:street":"W 32Nd St",
    "iso:country":"US",
    "sg:address":"970 W 32nd St",
    "sg:city":"Hialeah",
    "sg:classifiers":[
        {
            "category":"Restaurant",
            "type":"Food & Drink"
        }
    ],
    "sg:phone":"+1 305 557 1988",
    "sg:postcode":"33012",
    "sg:province":"FL",
    "sg:tags":[
        "eating"
    ],
    "wof:name":"Rigoberto Diaz",
    "wof:placetype":"venue"
},
  "geometry": {"coordinates":[-80.301095,25.850668],"type":"Point"}
}