{
  "type": "Feature",
  "properties": {
    "iso:country":"US",
    "sg:address":"255 Forest Lakes Blvd",
    "sg:city":"Oldsmar",
    "sg:classifiers":[
        {
            "category":"Recreation",
            "type":"Entertainment"
        }
    ],
    "sg:phone":"+1 813 831 1927",
    "sg:postcode":"34677",
    "sg:province":"FL",
    "wof:name":"Flg Ice Limited Partnership",
    "wof:placetype":"venue"
},
  "geometry": {"coordinates":[-82.679394,28.039661],"type":"Point"}
}