{
  "type": "Feature",
  "properties": {
    "addr:full":"414 Lake Howell Rd Maitland FL 32751",
    "addr:housenumber":"414",
    "addr:postcode":"32751",
    "addr:street":"Lake Howell Rd",
    "iso:country":"US",
    "sg:address":"414 Lake Howell Rd",
    "sg:city":"Maitland",
    "sg:classifiers":[
        {
            "category":"Real Estate",
            "subcategory":"Real Estate Agent",
            "type":"Services"
        }
    ],
    "sg:phone":"+1 407 645 4440",
    "sg:postcode":"32751",
    "sg:province":"FL",
    "wof:name":"Freedom Realty LLC",
    "wof:placetype":"venue"
},
  "geometry": {"coordinates":[-81.3242,28.629058],"type":"Point"}
}