{
  "type": "Feature",
  "properties": {
    "iso:country":"US",
    "sg:address":"525 N Lakeside Dr",
    "sg:city":"Lake Worth",
    "sg:classifiers":[
        {
            "category":"Real Estate",
            "subcategory":"Real Estate Operator",
            "type":"Services"
        }
    ],
    "sg:phone":"+1 561 540 4286",
    "sg:postcode":"33460",
    "sg:province":"FL",
    "sg:tags":[
        "building",
        "nonresidential"
    ],
    "wof:name":"Purple Door Properties Inc",
    "wof:placetype":"venue"
},
  "geometry": {"coordinates":[-80.04933699999999,26.62219],"type":"Point"}
}