{
  "type": "Feature",
  "properties": {
    "iso:country":"US",
    "sg:address":"8585 Sunset Dr",
    "sg:city":"Miami",
    "sg:classifiers":[
        {
            "category":"Social Services",
            "type":"Services"
        }
    ],
    "sg:phone":"+1 305 271 4948",
    "sg:postcode":"33143",
    "sg:province":"FL",
    "sg:tags":[
        "counselor",
        "health",
        "mental"
    ],
    "wof:name":"Patricia D Isis",
    "wof:placetype":"venue"
},
  "geometry": {"coordinates":[-80.332527,25.706084],"type":"Point"}
}