{
  "type": "Feature",
  "properties": {
    "addr:full":"138 Toney Penna Dr Jupiter FL 33458",
    "addr:housenumber":"138",
    "addr:postcode":"33458",
    "addr:street":"Toney Penna Dr",
    "iso:country":"US",
    "sg:address":"138 Toney Penna Dr",
    "sg:city":"Jupiter",
    "sg:classifiers":[
        {
            "category":"Retail",
            "subcategory":"Repair Shop",
            "type":"Services"
        }
    ],
    "sg:phone":"+1 561 747 7347",
    "sg:postcode":"33458",
    "sg:province":"FL",
    "sg:tags":[
        "screen",
        "window"
    ],
    "wof:name":"C & C Glass & Screen",
    "wof:placetype":"venue"
},
  "geometry": {"coordinates":[-80.09503100000001,26.926216],"type":"Point"}
}