{
  "type": "Feature",
  "properties": {
    "iso:country":"US",
    "sg:address":"8225 SW 124th St",
    "sg:city":"Miami",
    "sg:classifiers":[
        {
            "category":"Restaurant",
            "type":"Food & Drink"
        }
    ],
    "sg:phone":"+1 305 238 8462",
    "sg:postcode":"33156",
    "sg:province":"FL",
    "sg:tags":[
        "asian",
        "pan",
        "japanese"
    ],
    "wof:name":"Sakura Japanese Restaurant",
    "wof:placetype":"venue"
},
  "geometry": {"coordinates":[-80.327202,25.6551],"type":"Point"}
}