{
  "type": "Feature",
  "properties": {
    "addr:full":"404 NW 8th St Ocala FL 34475",
    "addr:housenumber":"404",
    "addr:postcode":"34475",
    "addr:street":"Nw 8Th St",
    "iso:country":"US",
    "sg:address":"404 NW 8th St",
    "sg:city":"Ocala",
    "sg:phone":"+1 352 622 3780",
    "sg:postcode":"34475",
    "sg:province":"FL",
    "sg:website":"http://www.jerrysonline.com",
    "wof:name":"Jerry's Pawn & Gun Shop Inc",
    "wof:placetype":"venue"
},
  "geometry": {"coordinates":[-82.14072400000001,29.194321],"type":"Point"}
}