{
  "type": "Feature",
  "properties": {
    "iso:country":"US",
    "sg:address":"1501 Lake Ave SE",
    "sg:city":"Largo",
    "sg:classifiers":[
        {
            "category":"Retail",
            "subcategory":"Auto Repair",
            "type":"Services"
        }
    ],
    "sg:phone":"+1 727 584 1585",
    "sg:postcode":"33771",
    "sg:province":"FL",
    "sg:tags":[
        "truck"
    ],
    "wof:name":"Twiss Transport Inc",
    "wof:placetype":"venue"
},
  "geometry": {"coordinates":[-82.770741,27.90195],"type":"Point"}
}