{
  "type": "Feature",
  "properties": {
    "iso:country":"US",
    "sg:address":"4950 SW 72nd Ave",
    "sg:city":"Miami",
    "sg:classifiers":[
        {
            "category":"Professional",
            "type":"Services"
        }
    ],
    "sg:phone":"+1 305 667 7944",
    "sg:postcode":"33155",
    "sg:province":"FL",
    "sg:tags":[
        "establishment"
    ],
    "wof:name":"Maryndale Corporation-Florida",
    "wof:placetype":"venue"
},
  "geometry": {"coordinates":[-80.310717,25.723858],"type":"Point"}
}