{
  "type": "Feature",
  "properties": {
    "addr:full":"3109 Spring Park Rd Jacksonville FL 32207",
    "addr:housenumber":"3109",
    "addr:postcode":"32207",
    "addr:street":"Spring Park Rd",
    "iso:country":"US",
    "sg:address":"3109 Spring Park Rd",
    "sg:city":"Jacksonville",
    "sg:classifiers":[
        {
            "category":"Restaurant",
            "type":"Food & Drink"
        }
    ],
    "sg:phone":"+1 904 306 0777",
    "sg:postcode":"32207",
    "sg:province":"FL",
    "sg:tags":[
        "caterer"
    ],
    "wof:name":"Pat's Place & Catering",
    "wof:placetype":"venue"
},
  "geometry": {"coordinates":[-81.625721,30.291129],"type":"Point"}
}