{
  "type": "Feature",
  "properties": {
    "iso:country":"US",
    "sg:address":"1033 S Semoran Blvd",
    "sg:city":"Winter Park",
    "sg:classifiers":[
        {
            "category":"Communications",
            "subcategory":"Radio Station",
            "type":"Services"
        }
    ],
    "sg:phone":"+1 407 331 1030",
    "sg:postcode":"32792",
    "sg:province":"FL",
    "sg:tags":[
        "company",
        "broadcasting"
    ],
    "wof:name":"ONCEQ Spanish Radio",
    "wof:placetype":"venue"
},
  "geometry": {"coordinates":[-81.307638,28.581159],"type":"Point"}
}