{
  "type": "Feature",
  "properties": {
    "iso:country":"US",
    "sg:address":"2933 Jefferson St",
    "sg:city":"Marianna",
    "sg:classifiers":[
        {
            "category":"Professional",
            "subcategory":"Accounting & Tax Preparation",
            "type":"Services"
        }
    ],
    "sg:phone":"+1 850 482 3633",
    "sg:postcode":"32446",
    "sg:province":"FL",
    "sg:tags":[
        "insurance"
    ],
    "wof:name":"P M I Employee Leasing",
    "wof:placetype":"venue"
},
  "geometry": {"coordinates":[-85.22677299999999,30.777272],"type":"Point"}
}