{
  "type": "Feature",
  "properties": {
    "addr:full":"4810 W Dr Martin Luther King Jr Blvd Tampa FL 33614",
    "addr:housenumber":"4810",
    "addr:postcode":"33614",
    "addr:street":"W Dr Martin Luther King Jr Blvd",
    "iso:country":"US",
    "sg:address":"4810 W Dr Martin Luther King Jr Blvd",
    "sg:city":"Tampa",
    "sg:classifiers":[
        {
            "category":"Airline",
            "type":"Transportation"
        }
    ],
    "sg:phone":"+1 813 879 5835",
    "sg:postcode":"33614",
    "sg:province":"FL",
    "sg:tags":[
        "cargo",
        "air"
    ],
    "wof:name":"Pilot Air Freight Corp",
    "wof:placetype":"venue"
},
  "geometry": {"coordinates":[-82.525282,27.981576],"type":"Point"}
}