{
  "type": "Feature",
  "properties": {
    "iso:country":"US",
    "sg:address":"3730 Sutters Mill Cir",
    "sg:city":"Casselberry",
    "sg:classifiers":[
        {
            "category":"Shopping",
            "subcategory":"Clothing, Apparel, & Fashions",
            "type":"Retail Goods"
        }
    ],
    "sg:phone":"+1 407 699 4877",
    "sg:postcode":"32707",
    "sg:province":"FL",
    "sg:tags":[
        "sportswear"
    ],
    "wof:name":"Idea House Sales Inc",
    "wof:placetype":"venue"
},
  "geometry": {"coordinates":[-81.287003,28.643693],"type":"Point"}
}