{
  "type": "Feature",
  "properties": {
    "addr:full":"5503 12th St E Bradenton FL 34203",
    "addr:housenumber":"5503",
    "addr:postcode":"34203",
    "addr:street":"12Th St",
    "iso:country":"US",
    "sg:address":"5503 12th St E",
    "sg:city":"Bradenton",
    "sg:classifiers":[
        {
            "category":"Social Services",
            "subcategory":"Child Care",
            "type":"Services"
        }
    ],
    "sg:phone":"+1 941 753 0043",
    "sg:postcode":"34203",
    "sg:province":"FL",
    "wof:name":"Bee Happy Daycare",
    "wof:placetype":"venue"
},
  "geometry": {"coordinates":[-82.550696,27.443049],"type":"Point"}
}