{
  "type": "Feature",
  "properties": {
    "iso:country":"US",
    "sg:address":"1805 W Flagler St",
    "sg:city":"Miami",
    "sg:classifiers":[
        {
            "category":"Banks & Credit Unions",
            "subcategory":"Bank",
            "type":"Services"
        }
    ],
    "sg:phone":"+1 305 644 3511",
    "sg:postcode":"33135",
    "sg:province":"FL",
    "sg:tags":[
        "depository",
        "banking"
    ],
    "wof:name":"18 Cash Inc",
    "wof:placetype":"venue"
},
  "geometry": {"coordinates":[-80.22605,25.772778],"type":"Point"}
}