{
  "type": "Feature",
  "properties": {
    "iso:country":"US",
    "sg:address":"16580 NW 59th Ave",
    "sg:city":"Hialeah",
    "sg:classifiers":[
        {
            "category":"Shopping",
            "subcategory":"Optician",
            "type":"Retail Goods"
        },
        {
            "category":"Autos & Motor Vehicles",
            "subcategory":"Auto Supplies",
            "type":"Retail Goods"
        },
        {
            "category":"Bakery",
            "type":"Food & Drink"
        }
    ],
    "sg:phone":"+1 305 821 8502",
    "sg:postcode":"33014",
    "sg:province":"FL",
    "sg:tags":[
        "eyewear",
        "tire"
    ],
    "wof:name":"Costco Wholesale Club",
    "wof:placetype":"venue"
},
  "geometry": {"coordinates":[-80.297302,25.9226],"type":"Point"}
}