{
  "type": "Feature",
  "properties": {
    "iso:country":"US",
    "sg:address":"439 S Central Ave",
    "sg:city":"Apopka",
    "sg:classifiers":[
        {
            "category":"Food & Beverages",
            "subcategory":"Groceries & Convenience Stores",
            "type":"Retail Goods"
        }
    ],
    "sg:phone":"+1 407 886 2032",
    "sg:postcode":"32703",
    "sg:province":"FL",
    "sg:tags":[
        "grocer"
    ],
    "wof:name":"South Central Food & Meat Mkt",
    "wof:placetype":"venue"
},
  "geometry": {"coordinates":[-81.51152500000001,28.672843],"type":"Point"}
}