{
  "type": "Feature",
  "properties": {
    "addr:full":"1816 SW 85th Dr Gainesville FL 32607",
    "addr:housenumber":"1816",
    "addr:postcode":"32607",
    "addr:street":"Sw 85Th Dr",
    "iso:country":"US",
    "sg:address":"1816 SW 85th Dr",
    "sg:city":"Gainesville",
    "sg:classifiers":[
        {
            "category":"Restaurant",
            "type":"Food & Drink"
        },
        {
            "category":"Food & Beverages",
            "subcategory":"Groceries & Convenience Stores",
            "type":"Retail Goods"
        }
    ],
    "sg:phone":"+1 352 331 2558",
    "sg:postcode":"32607",
    "sg:province":"FL",
    "sg:tags":[
        "shop",
        "sandwich"
    ],
    "wof:name":"Quizno S Hays Of Inc",
    "wof:placetype":"venue"
},
  "geometry": {"coordinates":[-82.43331999999999,29.635875],"type":"Point"}
}