{
  "type": "Feature",
  "properties": {
    "addr:full":"3341 Coleus Ct Winter Park FL 32792",
    "addr:housenumber":"3341",
    "addr:postcode":"32792",
    "addr:street":"Coleus Ct",
    "iso:country":"US",
    "sg:address":"3341 Coleus Ct",
    "sg:city":"Winter Park",
    "sg:classifiers":[
        {
            "category":"Manufacturing",
            "subcategory":"Apparel",
            "type":"Manufacturing & Wholesale Goods"
        }
    ],
    "sg:phone":"+1 407 671 3505",
    "sg:postcode":"32792",
    "sg:province":"FL",
    "sg:tags":[
        "sewing",
        "contractor"
    ],
    "wof:name":"Deborah J Lewis Sewing",
    "wof:placetype":"venue"
},
  "geometry": {"coordinates":[-81.30543900000001,28.616926],"type":"Point"}
}