{
  "type": "Feature",
  "properties": {
    "iso:country":"US",
    "sg:address":"10116 US Hwy 19",
    "sg:city":"Port Richey",
    "sg:classifiers":[
        {
            "category":"Shopping",
            "subcategory":"Computers & Home Electronics",
            "type":"Retail Goods"
        }
    ],
    "sg:phone":"+1 727 697 1116",
    "sg:postcode":"34668",
    "sg:province":"FL",
    "wof:name":"Pasco Computer Outlet",
    "wof:placetype":"venue"
},
  "geometry": {"coordinates":[-82.705056,28.30058],"type":"Point"}
}