{
  "type": "Feature",
  "properties": {
    "iso:country":"US",
    "sg:address":"2125 Aruba Ave",
    "sg:city":"Fort Myers",
    "sg:classifiers":[
        {
            "category":"Building & Trades",
            "subcategory":"Plumbing",
            "type":"Services"
        }
    ],
    "sg:phone":"+1 239 693 7146",
    "sg:postcode":"33905",
    "sg:province":"FL",
    "sg:tags":[
        "conditioning",
        "air",
        "system",
        "contractor"
    ],
    "wof:name":"Scott Air",
    "wof:placetype":"venue"
},
  "geometry": {"coordinates":[-81.742535,26.712624],"type":"Point"}
}