{
  "type": "Feature",
  "properties": {
    "addr:full":"8118 Beach Blvd Jacksonville FL 32216",
    "addr:housenumber":"8118",
    "addr:postcode":"32216",
    "addr:street":"Beach Blvd",
    "iso:country":"US",
    "sg:address":"8118 Beach Blvd",
    "sg:city":"Jacksonville",
    "sg:classifiers":[
        {
            "category":"Shopping",
            "subcategory":"Computers & Home Electronics",
            "type":"Retail Goods"
        }
    ],
    "sg:phone":"+1 904 721 6015",
    "sg:postcode":"32216",
    "sg:province":"FL",
    "sg:tags":[
        "equipment",
        "playground",
        "spa"
    ],
    "wof:name":"Playnation Of Jacksonville",
    "wof:placetype":"venue"
},
  "geometry": {"coordinates":[-81.576739,30.288264],"type":"Point"}
}