{
  "type": "Feature",
  "properties": {
    "addr:full":"779 Talleyrand Ave Jacksonville FL 32202",
    "addr:housenumber":"779",
    "addr:postcode":"32202",
    "addr:street":"Talleyrand Ave",
    "iso:country":"US",
    "sg:address":"779 Talleyrand Ave",
    "sg:city":"Jacksonville",
    "sg:classifiers":[
        {
            "category":"Building & Trades",
            "subcategory":"Construction",
            "type":"Services"
        }
    ],
    "sg:phone":"+1 904 355 5885",
    "sg:postcode":"32202",
    "sg:province":"FL",
    "sg:tags":[
        "marina",
        "bridges",
        "general",
        "contractor"
    ],
    "sg:website":"www.haljonescontractor.com",
    "wof:name":"Hal Jones Contractors Inc",
    "wof:placetype":"venue"
},
  "geometry": {"coordinates":[-81.631569,30.329814],"type":"Point"}
}