{
  "type": "Feature",
  "properties": {
    "iso:country":"US",
    "sg:address":"31942 US Hwy 19 N",
    "sg:city":"Palm Harbor",
    "sg:classifiers":[
        {
            "category":"Health Services",
            "subcategory":"Clinic",
            "type":"Services"
        }
    ],
    "sg:phone":"+1 727 849 4788",
    "sg:postcode":"34684",
    "sg:province":"FL",
    "sg:tags":[
        "home",
        "care"
    ],
    "wof:name":"Cardinal Caregivers Inc",
    "wof:placetype":"venue"
},
  "geometry": {"coordinates":[-82.738966,28.065022],"type":"Point"}
}