{
  "type": "Feature",
  "properties": {
    "iso:country":"US",
    "sg:address":"627 Macarthur Dr",
    "sg:city":"Orlando",
    "sg:classifiers":[
        {
            "category":"Professional",
            "subcategory":"Management & Consulting",
            "type":"Services"
        }
    ],
    "sg:phone":"+1 407 438 3417",
    "sg:postcode":"32839",
    "sg:province":"FL",
    "sg:tags":[
        "science",
        "consultant",
        "academic"
    ],
    "wof:name":"J & B Environmental Service",
    "wof:placetype":"venue"
},
  "geometry": {"coordinates":[-81.384882,28.501743],"type":"Point"}
}