{
  "type": "Feature",
  "properties": {
    "iso:country":"US",
    "sg:address":"5559 Brookline Dr",
    "sg:city":"Orlando",
    "sg:classifiers":[
        {
            "category":"Travel",
            "subcategory":"Hotels & Motels",
            "type":"Entertainment"
        }
    ],
    "sg:phone":"+1 407 876 2156",
    "sg:postcode":"32819",
    "sg:province":"FL",
    "sg:tags":[
        "resort"
    ],
    "wof:name":"Global Resort Management Inc",
    "wof:placetype":"venue"
},
  "geometry": {"coordinates":[-81.50635200000001,28.468828],"type":"Point"}
}