{
  "type": "Feature",
  "properties": {
    "addr:full":"5032 Tampa West Blvd Tampa FL 33634",
    "addr:housenumber":"5032",
    "addr:postcode":"33634",
    "addr:street":"Tampa West Blvd",
    "iso:country":"US",
    "sg:address":"5032 Tampa West Blvd",
    "sg:city":"Tampa",
    "sg:classifiers":[
        {
            "category":"Banks & Credit Unions",
            "subcategory":"Financial Services",
            "type":"Services"
        }
    ],
    "sg:phone":"+1 813 885 7070",
    "sg:postcode":"33634",
    "sg:province":"FL",
    "sg:tags":[
        "escrow"
    ],
    "wof:name":"Awe Tampa West",
    "wof:placetype":"venue"
},
  "geometry": {"coordinates":[-82.52986300000001,28.017851],"type":"Point"}
}