{
  "type": "Feature",
  "properties": {
    "iso:country":"US",
    "sg:address":"1000 N Ashley Dr",
    "sg:city":"Tampa",
    "sg:classifiers":[
        {
            "category":"Real Estate",
            "subcategory":"Real Estate Services",
            "type":"Services"
        },
        {
            "category":"Real Estate",
            "subcategory":"Real Estate Agent",
            "type":"Services"
        }
    ],
    "sg:phone":"+1 813 221 2511",
    "sg:postcode":"33602",
    "sg:province":"FL",
    "sg:tags":[
        "vacancy",
        "management",
        "rental",
        "listing"
    ],
    "wof:name":"Denholtz Associates",
    "wof:placetype":"venue"
},
  "geometry": {"coordinates":[-82.461761,27.951521],"type":"Point"}
}