{
  "type": "Feature",
  "properties": {
    "iso:country":"US",
    "sg:address":"1960 Erving Cir",
    "sg:city":"Ocoee",
    "sg:classifiers":[
        {
            "category":"Real Estate",
            "subcategory":"Real Estate Operator",
            "type":"Services"
        }
    ],
    "sg:phone":"+1 407 578 4992",
    "sg:postcode":"34761",
    "sg:province":"FL",
    "sg:tags":[
        "building",
        "apartment"
    ],
    "wof:name":"Vintage At Lake Lotta",
    "wof:placetype":"venue"
},
  "geometry": {"coordinates":[-81.50958900000001,28.554957],"type":"Point"}
}