{
  "type": "Feature",
  "properties": {
    "iso:country":"US",
    "sg:address":"30 Medford Dr",
    "sg:city":"Palm Coast",
    "sg:classifiers":[
        {
            "category":"Professional",
            "subcategory":"Computer Services",
            "type":"Services"
        }
    ],
    "sg:phone":"+1 386 446 4909",
    "sg:postcode":"32137",
    "sg:province":"FL",
    "sg:tags":[
        "programing",
        "custom"
    ],
    "wof:name":"Back In Tyme",
    "wof:placetype":"venue"
},
  "geometry": {"coordinates":[-81.196091,29.62427],"type":"Point"}
}