{
  "type": "Feature",
  "properties": {
    "iso:country":"US",
    "sg:address":"7244 Central Ave",
    "sg:city":"St Petersburg",
    "sg:classifiers":[
        {
            "category":"Personal",
            "subcategory":"Beauty Salon",
            "type":"Services"
        }
    ],
    "sg:phone":"+1 727 345 1933",
    "sg:postcode":"33707",
    "sg:province":"FL",
    "sg:tags":[
        "shop"
    ],
    "wof:name":"Angel Hair Studio",
    "wof:placetype":"venue"
},
  "geometry": {"coordinates":[-82.73878000000001,27.770739],"type":"Point"}
}