{
  "type": "Feature",
  "properties": {
    "iso:country":"US",
    "sg:address":"4094 Lake Mira Dr",
    "sg:city":"Orlando",
    "sg:classifiers":[
        {
            "category":"Banks & Credit Unions",
            "subcategory":"Bank",
            "type":"Services"
        }
    ],
    "sg:phone":"+1 407 246 5555",
    "sg:postcode":"32817",
    "sg:province":"FL",
    "wof:name":"Amsouth Bank",
    "wof:placetype":"venue"
},
  "geometry": {"coordinates":[-81.2705,28.5979],"type":"Point"}
}