{
  "type": "Feature",
  "properties": {
    "addr:full":"776 NE River Ter Jensen Beach FL 34957",
    "addr:housenumber":"776",
    "addr:postcode":"34957",
    "addr:street":"Ne River Ter;Beach",
    "iso:country":"US",
    "sg:address":"776 NE River Ter",
    "sg:city":"Jensen Beach",
    "sg:classifiers":[
        {
            "category":"Building & Trades",
            "subcategory":"Construction",
            "type":"Services"
        }
    ],
    "sg:phone":"+1 772 334 1840",
    "sg:postcode":"34957",
    "sg:province":"FL",
    "sg:tags":[
        "house"
    ],
    "wof:name":"Dennis Proctor Construction",
    "wof:placetype":"venue"
},
  "geometry": {"coordinates":[-80.242445,27.215214],"type":"Point"}
}