{
  "type": "Feature",
  "properties": {
    "iso:country":"US",
    "sg:address":"2924 US Hwy 27",
    "sg:city":"Sebring",
    "sg:classifiers":[
        {
            "category":"Shopping",
            "subcategory":"Computers & Home Electronics",
            "type":"Retail Goods"
        }
    ],
    "sg:phone":"+1 863 471 9080",
    "sg:postcode":"33870",
    "sg:province":"FL",
    "sg:tags":[
        "equipment",
        "satellite",
        "system"
    ],
    "wof:name":"Cable Busters",
    "wof:placetype":"venue"
},
  "geometry": {"coordinates":[-81.442297,27.471041],"type":"Point"}
}