{
  "type": "Feature",
  "properties": {
    "addr:full":"5835 Davis Rd Lakeland FL 33810",
    "addr:housenumber":"5835",
    "addr:postcode":"33810",
    "addr:street":"Davis Rd",
    "iso:country":"US",
    "sg:address":"5835 Davis Rd",
    "sg:city":"Lakeland",
    "sg:classifiers":[
        {
            "category":"Wholesale",
            "subcategory":"Construction Materials",
            "type":"Manufacturing & Wholesale Goods"
        }
    ],
    "sg:phone":"+1 863 858 0983",
    "sg:postcode":"33810",
    "sg:province":"FL",
    "wof:name":"Central Florida Septic Tank Co",
    "wof:placetype":"venue"
},
  "geometry": {"coordinates":[-82.04284699999999,28.118867],"type":"Point"}
}