{
  "type": "Feature",
  "properties": {
    "iso:country":"US",
    "sg:address":"3954 Cordova Ave",
    "sg:city":"Jacksonville",
    "sg:classifiers":[
        {
            "category":"Manufacturing",
            "subcategory":"Tools & Machinery",
            "type":"Manufacturing & Wholesale Goods"
        }
    ],
    "sg:phone":"+1 904 396 9741",
    "sg:postcode":"32207",
    "sg:province":"FL",
    "sg:tags":[
        "manufacture",
        "equipment",
        "oil",
        "testing",
        "for"
    ],
    "wof:name":"Green Ideas Inc",
    "wof:placetype":"venue"
},
  "geometry": {"coordinates":[-81.660005,30.28474],"type":"Point"}
}