{
  "type": "Feature",
  "properties": {
    "addr:full":"5811 Memorial Hwy Tampa FL 33615",
    "addr:housenumber":"5811",
    "addr:postcode":"33615",
    "addr:street":"Memorial Hwy",
    "iso:country":"US",
    "sg:address":"5811 Memorial Hwy",
    "sg:city":"Tampa",
    "sg:classifiers":[
        {
            "category":"Organizations",
            "subcategory":"Community Association",
            "type":"Services"
        }
    ],
    "sg:phone":"+1 813 249 9100",
    "sg:postcode":"33615",
    "sg:province":"FL",
    "sg:tags":[
        "educational"
    ],
    "wof:name":"Studyworks",
    "wof:placetype":"venue"
},
  "geometry": {"coordinates":[-82.56897499999999,27.984195],"type":"Point"}
}