{
  "type": "Feature",
  "properties": {
    "iso:country":"US",
    "sg:address":"3360 Heath Dr",
    "sg:city":"Deltona",
    "sg:classifiers":[
        {
            "category":"Health Services",
            "subcategory":"Dentist",
            "type":"Services"
        }
    ],
    "sg:phone":"+1 386 218 6134",
    "sg:postcode":"32725",
    "sg:province":"FL",
    "wof:name":"O'neil, David",
    "wof:placetype":"venue"
},
  "geometry": {"coordinates":[-81.247651,28.958631],"type":"Point"}
}