{
  "type": "Feature",
  "properties": {
    "addr:full":"2308 N Dixie Hwy Hollywood FL 33020",
    "addr:housenumber":"2308",
    "addr:postcode":"33020",
    "addr:street":"N Dixie Hwy",
    "iso:country":"US",
    "sg:address":"2308 N Dixie Hwy",
    "sg:city":"Hollywood",
    "sg:classifiers":[
        {
            "category":"Restaurant",
            "type":"Food & Drink"
        }
    ],
    "sg:phone":"+1 954 924 8828",
    "sg:postcode":"33020",
    "sg:province":"FL",
    "sg:tags":[
        "eating"
    ],
    "wof:name":"Taste N Tell",
    "wof:placetype":"venue"
},
  "geometry": {"coordinates":[-80.150081,26.032474],"type":"Point"}
}