{
  "type": "Feature",
  "properties": {
    "addr:full":"1625 Les Ct Kissimmee FL 34744",
    "addr:housenumber":"1625",
    "addr:postcode":"34744",
    "addr:street":"Les Ct",
    "iso:country":"US",
    "sg:address":"1625 Les Ct",
    "sg:city":"Kissimmee",
    "sg:classifiers":[
        {
            "category":"Building & Trades",
            "subcategory":"Electrical",
            "type":"Services"
        }
    ],
    "sg:phone":"+1 407 931 0415",
    "sg:postcode":"34744",
    "sg:province":"FL",
    "sg:tags":[
        "electrician"
    ],
    "wof:name":"Lois A Feuerbach Processo",
    "wof:placetype":"venue"
},
  "geometry": {"coordinates":[-81.377987,28.318455],"type":"Point"}
}