{
  "type": "Feature",
  "properties": {
    "addr:full":"7363 W Colonial Dr Orlando FL 32818",
    "addr:housenumber":"7363",
    "addr:postcode":"32818",
    "addr:street":"W Colonial Dr",
    "iso:country":"US",
    "sg:address":"7363 W Colonial Dr",
    "sg:city":"Orlando",
    "sg:classifiers":[
        {
            "category":"Banks & Credit Unions",
            "subcategory":"Bank",
            "type":"Services"
        }
    ],
    "sg:phone":"+1 407 296 3416",
    "sg:postcode":"32818",
    "sg:province":"FL",
    "sg:tags":[
        "financing"
    ],
    "sg:website":"www.household.com",
    "wof:name":"Household Finance",
    "wof:placetype":"venue"
},
  "geometry": {"coordinates":[-81.481925,28.552093],"type":"Point"}
}