{
  "type": "Feature",
  "properties": {
    "addr:full":"2941 Farrington St Jacksonville FL 32224",
    "addr:housenumber":"2941",
    "addr:postcode":"32224",
    "addr:street":"Farrington St",
    "iso:country":"US",
    "sg:address":"2941 Farrington St",
    "sg:city":"Jacksonville",
    "sg:classifiers":[
        {
            "category":"Building & Trades",
            "subcategory":"Construction",
            "type":"Services"
        }
    ],
    "sg:phone":"+1 904 821 0930",
    "sg:postcode":"32224",
    "sg:province":"FL",
    "sg:tags":[
        "house"
    ],
    "wof:name":"Kpw Construction",
    "wof:placetype":"venue"
},
  "geometry": {"coordinates":[-81.43973699999999,30.294848],"type":"Point"}
}