{
  "type": "Feature",
  "properties": {
    "addr:full":"18200 NW 27th Ave Miami Gardens FL 33056",
    "addr:housenumber":"18200",
    "addr:postcode":"33056",
    "addr:street":"Nw 27Th Ave",
    "iso:country":"US",
    "sg:address":"18200 NW 27th Ave",
    "sg:city":"Miami Gardens",
    "sg:classifiers":[
        {
            "category":"Shopping",
            "subcategory":"Clothing, Apparel, & Fashions",
            "type":"Retail Goods"
        }
    ],
    "sg:phone":"+1 305 626 9555",
    "sg:postcode":"33056",
    "sg:province":"FL",
    "sg:tags":[
        "accessory",
        "clothing",
        "women's"
    ],
    "wof:name":"Sandy's Casuals",
    "wof:placetype":"venue"
},
  "geometry": {"coordinates":[-80.245529,25.940166],"type":"Point"}
}