{
  "type": "Feature",
  "properties": {
    "addr:full":"4600 SW 12th St Miami FL 33134",
    "addr:housenumber":"4600",
    "addr:postcode":"33134",
    "addr:street":"Sw 12Th St",
    "iso:country":"US",
    "sg:address":"4600 SW 12th St",
    "sg:city":"Miami",
    "sg:classifiers":[
        {
            "category":"Shopping",
            "subcategory":"Gifts & Souvenirs",
            "type":"Retail Goods"
        },
        {
            "category":"Manufacturing",
            "subcategory":"Retail Goods",
            "type":"Manufacturing & Wholesale Goods"
        }
    ],
    "sg:phone":"+1 305 446 2712",
    "sg:postcode":"33134",
    "sg:province":"FL",
    "sg:tags":[
        "shop",
        "giftware's-wholesale",
        "manufacturer"
    ],
    "wof:name":"Riera Enterprises Inc",
    "wof:placetype":"venue"
},
  "geometry": {"coordinates":[-80.270331,25.76054],"type":"Point"}
}