{
  "type": "Feature",
  "properties": {
    "iso:country":"US",
    "sg:address":"4670 S Orange Blossom Trl",
    "sg:city":"Orlando",
    "sg:classifiers":[
        {
            "category":"Health Services",
            "subcategory":"Chiropractor",
            "type":"Services"
        }
    ],
    "sg:phone":"+1 407 851 8810",
    "sg:postcode":"32839",
    "sg:province":"FL",
    "wof:name":"Topcare Chiropractic & Rehab",
    "wof:placetype":"venue"
},
  "geometry": {"coordinates":[-81.39693200000001,28.497294],"type":"Point"}
}