{
  "type": "Feature",
  "properties": {
    "addr:full":"3865 N Wickham Rd Melbourne FL 32935",
    "addr:housenumber":"3865",
    "addr:postcode":"32935",
    "addr:street":"N Wickham Rd",
    "iso:country":"US",
    "sg:address":"3865 N Wickham Rd",
    "sg:city":"Melbourne",
    "sg:classifiers":[
        {
            "category":"Building & Trades",
            "subcategory":"Plumbing",
            "type":"Services"
        }
    ],
    "sg:phone":"+1 321 752 0062",
    "sg:postcode":"32935",
    "sg:province":"FL",
    "sg:tags":[
        "conditioning",
        "air",
        "system",
        "contractor"
    ],
    "wof:name":"Trane Co",
    "wof:placetype":"venue"
},
  "geometry": {"coordinates":[-80.671949,28.170078],"type":"Point"}
}