{
  "type": "Feature",
  "properties": {
    "iso:country":"US",
    "sg:address":"6974 NW 12th St",
    "sg:city":"Miami",
    "sg:classifiers":[
        {
            "category":"Wholesale",
            "subcategory":"Durable Goods & Equipment",
            "type":"Manufacturing & Wholesale Goods"
        }
    ],
    "sg:phone":"+1 305 437 9798",
    "sg:postcode":"33126",
    "sg:province":"FL",
    "sg:tags":[
        "instrument",
        "exporter",
        "musical"
    ],
    "wof:name":"Consolidated Music",
    "wof:placetype":"venue"
},
  "geometry": {"coordinates":[-80.290693,25.785341],"type":"Point"}
}