{
  "type": "Feature",
  "properties": {
    "iso:country":"US",
    "sg:address":"1601 N 43rd St",
    "sg:city":"Tampa",
    "sg:classifiers":[
        {
            "category":"Wholesale",
            "subcategory":"Electrical",
            "type":"Manufacturing & Wholesale Goods"
        }
    ],
    "sg:phone":"+1 813 248 5980",
    "sg:postcode":"33605",
    "sg:province":"FL",
    "sg:tags":[
        "electric",
        "motor"
    ],
    "sg:website":"www.aardvarkautomation.com",
    "wof:name":"Aardvark Automation Inc",
    "wof:placetype":"venue"
},
  "geometry": {"coordinates":[-82.41002,27.95808],"type":"Point"}
}