{
  "type": "Feature",
  "properties": {
    "iso:country":"US",
    "sg:address":"3307 Clark Rd",
    "sg:city":"Sarasota",
    "sg:classifiers":[
        {
            "category":"Building & Trades",
            "subcategory":"Construction",
            "type":"Services"
        }
    ],
    "sg:phone":"+1 941 552 0240",
    "sg:postcode":"34231",
    "sg:province":"FL",
    "sg:tags":[
        "general",
        "contractor"
    ],
    "wof:name":"Core Construction Inc",
    "wof:placetype":"venue"
},
  "geometry": {"coordinates":[-82.50348700000001,27.269301],"type":"Point"}
}