{
  "type": "Feature",
  "properties": {
    "addr:full":"2630 Segrest Dr Panama City FL 32405",
    "addr:housenumber":"2630",
    "addr:postcode":"32405",
    "addr:street":"Segrest Dr",
    "iso:country":"US",
    "sg:address":"2630 Segrest Dr",
    "sg:city":"Panama City",
    "sg:classifiers":[
        {
            "category":"Wholesale",
            "subcategory":"Electrical",
            "type":"Manufacturing & Wholesale Goods"
        }
    ],
    "sg:phone":"+1 850 763 1343",
    "sg:postcode":"32405",
    "sg:province":"FL",
    "sg:tags":[
        "equipment"
    ],
    "wof:name":"GE",
    "wof:placetype":"venue"
},
  "geometry": {"coordinates":[-85.627679,30.183103],"type":"Point"}
}