{
  "type": "Feature",
  "properties": {
    "iso:country":"US",
    "sg:address":"2015 Parker Ave",
    "sg:city":"West Palm Beach",
    "sg:classifiers":[
        {
            "category":"Organizations",
            "subcategory":"Religious Organization",
            "type":"Services"
        }
    ],
    "sg:phone":"+1 561 833 1746",
    "sg:postcode":"33401",
    "sg:province":"FL",
    "sg:tags":[
        "church"
    ],
    "wof:name":"United Haitian Baptist Church",
    "wof:placetype":"venue"
},
  "geometry": {"coordinates":[-80.06240200000001,26.695741],"type":"Point"}
}