{
  "type": "Feature",
  "properties": {
    "addr:full":"4385 Co Rd 19A Mount Dora FL 32757",
    "addr:housenumber":"4385;19a",
    "addr:postcode":"32757",
    "addr:street":"Co Rd",
    "iso:country":"US",
    "sg:address":"4385 Co Rd 19A",
    "sg:city":"Mount Dora",
    "sg:classifiers":[
        {
            "category":"Building & Trades",
            "subcategory":"Construction",
            "type":"Services"
        }
    ],
    "sg:phone":"+1 352 589 5154",
    "sg:postcode":"32757",
    "sg:province":"FL",
    "sg:tags":[
        "residential",
        "tr",
        "nonresidential"
    ],
    "wof:name":"Pre Designs Inc",
    "wof:placetype":"venue"
},
  "geometry": {"coordinates":[-81.68537000000001,28.816277],"type":"Point"}
}