{
  "type": "Feature",
  "properties": {
    "addr:full":"1035 S Semoran Blvd Winter Park FL 32792",
    "addr:housenumber":"1035",
    "addr:postcode":"32792",
    "addr:street":"S Semoran Blvd",
    "iso:country":"US",
    "sg:address":"1035 S Semoran Blvd",
    "sg:city":"Winter Park",
    "sg:classifiers":[
        {
            "category":"Professional",
            "subcategory":"Engineering",
            "type":"Services"
        }
    ],
    "sg:phone":"+1 407 673 3130",
    "sg:postcode":"32792",
    "sg:province":"FL",
    "sg:tags":[
        "engineer"
    ],
    "wof:name":"M & T Co",
    "wof:placetype":"venue"
},
  "geometry": {"coordinates":[-81.30762900000001,28.581175],"type":"Point"}
}