{
  "type": "Feature",
  "properties": {
    "iso:country":"US",
    "sg:address":"13691 SW 145th Ct",
    "sg:city":"Miami",
    "sg:classifiers":[
        {
            "category":"Airline",
            "type":"Transportation"
        }
    ],
    "sg:phone":"+1 305 255 6973",
    "sg:postcode":"33186",
    "sg:province":"FL",
    "sg:tags":[
        "company"
    ],
    "sg:website":"www.africair.com",
    "wof:name":"Africair Inc",
    "wof:placetype":"venue"
},
  "geometry": {"coordinates":[-80.429959,25.6394],"type":"Point"}
}