{
  "type": "Feature",
  "properties": {
    "addr:full":"7990 Pines Blvd Hollywood FL 33024",
    "addr:housenumber":"7990",
    "addr:postcode":"33024",
    "addr:street":"Pines Blvd",
    "iso:country":"US",
    "sg:address":"7990 Pines Blvd",
    "sg:city":"Hollywood",
    "sg:classifiers":[
        {
            "category":"Restaurant",
            "type":"Food & Drink"
        }
    ],
    "sg:menulink":"http://www.allmenus.com/fl/miramar-pembroke-pines/9384-hooters/menu/",
    "sg:phone":"+1 954 962 6330",
    "sg:postcode":"33024",
    "sg:province":"FL",
    "sg:tags":[
        "american",
        "wing"
    ],
    "wof:name":"Hooters",
    "wof:placetype":"venue"
},
  "geometry": {"coordinates":[-80.24781900000001,26.009048],"type":"Point"}
}