{
  "type": "Feature",
  "properties": {
    "iso:country":"US",
    "sg:address":"2801 SW 186th Ave",
    "sg:city":"Miramar",
    "sg:classifiers":[
        {
            "category":"Organizations",
            "subcategory":"Religious Organization",
            "type":"Services"
        }
    ],
    "sg:phone":"+1 954 499 0505",
    "sg:postcode":"33029",
    "sg:province":"FL",
    "sg:tags":[
        "church"
    ],
    "wof:name":"Church In The Glades",
    "wof:placetype":"venue"
},
  "geometry": {"coordinates":[-80.394785,25.983326],"type":"Point"}
}