{
  "type": "Feature",
  "properties": {
    "iso:country":"US",
    "sg:address":"5213 Hammock Point Ct",
    "sg:city":"Saint Cloud",
    "sg:classifiers":[
        {
            "category":"Building & Trades",
            "subcategory":"Construction",
            "type":"Services"
        }
    ],
    "sg:phone":"+1 407 957 8694",
    "sg:postcode":"34771",
    "sg:province":"FL",
    "sg:tags":[
        "house"
    ],
    "wof:name":"Rdv Homes",
    "wof:placetype":"venue"
},
  "geometry": {"coordinates":[-81.233614,28.336597],"type":"Point"}
}