{
  "type": "Feature",
  "properties": {
    "iso:country":"US",
    "sg:address":"2948 Starwood Dr",
    "sg:city":"Oviedo",
    "sg:phone":"+1 407 880 7242",
    "sg:postcode":"32765",
    "sg:province":"FL",
    "sg:tags":[
        "oil"
    ],
    "wof:name":"Amsoil Synthetic Lubricants",
    "wof:placetype":"venue"
},
  "geometry": {"coordinates":[-81.255658,28.61644],"type":"Point"}
}