{
  "type": "Feature",
  "properties": {
    "addr:full":"3701 NW 7th St Miami FL 33126",
    "addr:housenumber":"3701",
    "addr:postcode":"33126",
    "addr:street":"Nw 7Th St",
    "iso:country":"US",
    "sg:address":"3701 NW 7th St",
    "sg:city":"Miami",
    "sg:classifiers":[
        {
            "category":"Food & Beverages",
            "subcategory":"Groceries & Convenience Stores",
            "type":"Retail Goods"
        }
    ],
    "sg:phone":"+1 305 541 8688",
    "sg:postcode":"33126",
    "sg:province":"FL",
    "sg:website":"http://www.winn-dixie.com",
    "wof:name":"Winn-Dixie",
    "wof:placetype":"venue"
},
  "geometry": {"coordinates":[-80.25765199999999,25.77891],"type":"Point"}
}