{
  "type": "Feature",
  "properties": {
    "iso:country":"US",
    "sg:address":"33907 US Hwy 19 N",
    "sg:city":"Palm Harbor",
    "sg:classifiers":[
        {
            "category":"Professional",
            "subcategory":"Employment Agencies",
            "type":"Services"
        }
    ],
    "sg:phone":"+1 727 781 2983",
    "sg:postcode":"34684",
    "sg:province":"FL",
    "sg:tags":[
        "opportunity"
    ],
    "wof:name":"Perso Net Inc",
    "wof:placetype":"venue"
},
  "geometry": {"coordinates":[-82.739137,28.080446],"type":"Point"}
}