{
  "type": "Feature",
  "properties": {
    "addr:full":"1823 Alpine Dr Gulf Breeze FL 32566",
    "addr:housenumber":"1823",
    "addr:postcode":"32566",
    "addr:street":"Alpine Dr",
    "iso:country":"US",
    "sg:address":"1823 Alpine Dr",
    "sg:city":"Gulf Breeze",
    "sg:classifiers":[
        {
            "category":"Personal",
            "subcategory":"Tanning Parlor",
            "type":"Services"
        },
        {
            "category":"Personal",
            "type":"Services"
        }
    ],
    "sg:phone":"+1 850 936 4443",
    "sg:postcode":"32566",
    "sg:province":"FL",
    "sg:tags":[
        "salon"
    ],
    "wof:name":"Emerald Coast Euro Tan",
    "wof:placetype":"venue"
},
  "geometry": {"coordinates":[-86.88530299999999,30.40165],"type":"Point"}
}