{
  "type": "Feature",
  "properties": {
    "iso:country":"US",
    "sg:address":"2521 13th St",
    "sg:city":"St Cloud",
    "sg:classifiers":[
        {
            "category":"Shopping",
            "subcategory":"Pharmacy",
            "type":"Retail Goods"
        }
    ],
    "sg:phone":"+1 407 892 7166",
    "sg:postcode":"34769",
    "sg:province":"FL",
    "wof:name":"Prescriptions Unlimited",
    "wof:placetype":"venue"
},
  "geometry": {"coordinates":[-81.297208,28.246013],"type":"Point"}
}