{
  "type": "Feature",
  "properties": {
    "iso:country":"US",
    "sg:address":"9951 Atlantic Blvd",
    "sg:city":"Jacksonville",
    "sg:classifiers":[
        {
            "category":"Shopping",
            "subcategory":"Clothing, Apparel, & Fashions",
            "type":"Retail Goods"
        }
    ],
    "sg:phone":"+1 904 805 0015",
    "sg:postcode":"32225",
    "sg:province":"FL",
    "sg:tags":[
        "manufacture",
        "woman",
        "sales",
        "man"
    ],
    "wof:name":"Streetsteel Sunglass & CL Co",
    "wof:placetype":"venue"
},
  "geometry": {"coordinates":[-81.539067,30.322836],"type":"Point"}
}