{
  "type": "Feature",
  "properties": {
    "addr:full":"343 Saint Armands Cir Sarasota FL 34236",
    "addr:housenumber":"343",
    "addr:postcode":"34236",
    "addr:street":"Saint Armands Cir",
    "iso:country":"US",
    "sg:address":"343 Saint Armands Cir",
    "sg:city":"Sarasota",
    "sg:phone":"+1 941 388 5115",
    "sg:postcode":"34236",
    "sg:province":"FL",
    "sg:website":"http://sunglassexpressoptical.com",
    "wof:name":"Sunglass Express Optical",
    "wof:placetype":"venue"
},
  "geometry": {"coordinates":[-82.57736300000001,27.317913],"type":"Point"}
}