{
  "type": "Feature",
  "properties": {
    "addr:full":"910 Beachview Dr NE Fort Walton Bch FL 32547",
    "addr:housenumber":"910",
    "addr:postcode":"32547",
    "addr:street":"Beachview Dr Ne Fort",
    "iso:country":"US",
    "sg:address":"910 Beachview Dr NE",
    "sg:city":"Fort Walton Bch",
    "sg:classifiers":[
        {
            "category":"Wholesale",
            "subcategory":"Office Equipment",
            "type":"Manufacturing & Wholesale Goods"
        }
    ],
    "sg:phone":"+1 850 864 2248",
    "sg:postcode":"32547",
    "sg:province":"FL",
    "sg:tags":[
        "repair",
        "register",
        "cash",
        "supply"
    ],
    "wof:name":"Rick Bryant's Office Machines",
    "wof:placetype":"venue"
},
  "geometry": {"coordinates":[-86.598581,30.436601],"type":"Point"}
}