{
  "type": "Feature",
  "properties": {
    "addr:full":"418 Coopers Cove Rd St Augustine FL 32095",
    "addr:housenumber":"418",
    "addr:postcode":"32095",
    "addr:street":"Coopers Cove Rd St",
    "iso:country":"US",
    "sg:address":"418 Coopers Cove Rd",
    "sg:city":"St Augustine",
    "sg:classifiers":[
        {
            "category":"Building & Trades",
            "subcategory":"Construction",
            "type":"Services"
        }
    ],
    "sg:phone":"+1 904 829 8321",
    "sg:postcode":"32095",
    "sg:province":"FL",
    "sg:tags":[
        "restoration",
        "cleaning",
        "patio",
        "deck"
    ],
    "wof:name":"Blast Off Pressure Cleaning",
    "wof:placetype":"venue"
},
  "geometry": {"coordinates":[-81.369586,30.009646],"type":"Point"}
}