{
  "type": "Feature",
  "properties": {
    "iso:country":"US",
    "sg:address":"2621 S Orlando Dr",
    "sg:city":"Sanford",
    "sg:classifiers":[
        {
            "category":"Insurance",
            "subcategory":"Hazard Insurance",
            "type":"Services"
        }
    ],
    "sg:phone":"+1 407 328 9109",
    "sg:postcode":"32773",
    "sg:province":"FL",
    "sg:tags":[
        "carrier",
        "surety",
        "business"
    ],
    "wof:name":"S Prophet C Wheeler Bail Bonds",
    "wof:placetype":"venue"
},
  "geometry": {"coordinates":[-81.273911,28.779761],"type":"Point"}
}