{
  "type": "Feature",
  "properties": {
    "iso:country":"US",
    "sg:address":"1203 Coral Way",
    "sg:city":"Miami",
    "sg:classifiers":[
        {
            "category":"Organizations",
            "subcategory":"Community Association",
            "type":"Services"
        }
    ],
    "sg:phone":"+1 305 250 5277",
    "sg:postcode":"33145",
    "sg:province":"FL",
    "sg:tags":[
        "opera"
    ],
    "wof:name":"Greater Miami Opera",
    "wof:placetype":"venue"
},
  "geometry": {"coordinates":[-80.214564,25.751121],"type":"Point"}
}