{
  "type": "Feature",
  "properties": {
    "addr:full":"9825 NE 7th Ave Miami Shores FL 33138",
    "addr:housenumber":"9825",
    "addr:postcode":"33138",
    "addr:street":"Ne 7Th Ave",
    "iso:country":"US",
    "sg:address":"9825 NE 7th Ave",
    "sg:city":"Miami Shores",
    "sg:classifiers":[
        {
            "category":"Government",
            "subcategory":"Office",
            "type":"Public Place"
        }
    ],
    "sg:phone":"+1 305 758 6701",
    "sg:postcode":"33138",
    "sg:province":"FL",
    "sg:tags":[
        "village"
    ],
    "wof:name":"Miami Shores Field House",
    "wof:placetype":"venue"
},
  "geometry": {"coordinates":[-80.18330400000001,25.86618],"type":"Point"}
}