{
  "type": "Feature",
  "properties": {
    "iso:country":"US",
    "sg:address":"743 NW 23rd St",
    "sg:city":"Miami",
    "sg:classifiers":[
        {
            "category":"Wholesale",
            "subcategory":"Groceries",
            "type":"Manufacturing & Wholesale Goods"
        }
    ],
    "sg:phone":"+1 305 637 7073",
    "sg:postcode":"33127",
    "sg:province":"FL",
    "sg:tags":[
        "food",
        "product"
    ],
    "wof:name":"LNG Food Distributors Inc",
    "wof:placetype":"venue"
},
  "geometry": {"coordinates":[-80.208156,25.798961],"type":"Point"}
}