{
  "type": "Feature",
  "properties": {
    "addr:full":"5186 Millenia Blvd Orlando FL 32839",
    "addr:housenumber":"5186",
    "addr:postcode":"32839",
    "addr:street":"Millenia Blvd",
    "iso:country":"US",
    "sg:address":"5186 Millenia Blvd",
    "sg:city":"Orlando",
    "sg:classifiers":[
        {
            "category":"Building & Trades",
            "subcategory":"Construction",
            "type":"Services"
        }
    ],
    "sg:phone":"+1 407 370 2636",
    "sg:postcode":"32839",
    "sg:province":"FL",
    "sg:tags":[
        "restoration",
        "cleaning",
        "patio",
        "deck"
    ],
    "wof:name":"Extreme Clean Pressure Clnng",
    "wof:placetype":"venue"
},
  "geometry": {"coordinates":[-81.44073,28.485053],"type":"Point"}
}