{
  "type": "Feature",
  "properties": {
    "iso:country":"US",
    "sg:address":"3920 W Navy Blvd",
    "sg:city":"Pensacola",
    "sg:classifiers":[
        {
            "category":"Home & Garden",
            "subcategory":"Furniture",
            "type":"Retail Goods"
        }
    ],
    "sg:phone":"+1 850 453 1286",
    "sg:postcode":"32507",
    "sg:province":"FL",
    "sg:tags":[
        "wood",
        "kitchen",
        "mfg"
    ],
    "wof:name":"Custom Wood Products",
    "wof:placetype":"venue"
},
  "geometry": {"coordinates":[-87.272268,30.408131],"type":"Point"}
}