{
  "type": "Feature",
  "properties": {
    "addr:full":"1991 Ziglar Rd Cantonment FL 32533",
    "addr:housenumber":"1991",
    "addr:postcode":"32533",
    "addr:street":"Ziglar Rd",
    "iso:country":"US",
    "sg:address":"1991 Ziglar Rd",
    "sg:city":"Cantonment",
    "sg:classifiers":[
        {
            "category":"Professional",
            "subcategory":"Management & Consulting",
            "type":"Services"
        }
    ],
    "sg:phone":"+1 850 968 5362",
    "sg:postcode":"32533",
    "sg:province":"FL",
    "wof:name":"Oliver Jones Mgmt Ctr",
    "wof:placetype":"venue"
},
  "geometry": {"coordinates":[-87.28646500000001,30.570281],"type":"Point"}
}