{
  "type": "Feature",
  "properties": {
    "iso:country":"US",
    "sg:address":"715 E Park St",
    "sg:city":"Lakeland",
    "sg:classifiers":[
        {
            "category":"Building & Trades",
            "subcategory":"Construction",
            "type":"Services"
        }
    ],
    "sg:phone":"+1 863 686 7963",
    "sg:postcode":"33803",
    "sg:province":"FL",
    "sg:tags":[
        "contractor"
    ],
    "wof:name":"Shawn Miller Tile",
    "wof:placetype":"venue"
},
  "geometry": {"coordinates":[-81.950001,28.029881],"type":"Point"}
}