{
  "type": "Feature",
  "properties": {
    "iso:country":"US",
    "sg:address":"1805 SW South Macedo Blvd",
    "sg:city":"Port Saint Lucie",
    "sg:classifiers":[
        {
            "category":"Autos & Motor Vehicles",
            "subcategory":"Motorcycle Sales",
            "type":"Retail Goods"
        }
    ],
    "sg:phone":"+1 772 344 0305",
    "sg:postcode":"34983",
    "sg:province":"FL",
    "sg:tags":[
        "repair"
    ],
    "wof:name":"Bc Choppers",
    "wof:placetype":"venue"
},
  "geometry": {"coordinates":[-80.36306500000001,27.283147],"type":"Point"}
}