{
  "type": "Feature",
  "properties": {
    "addr:full":"31 Bayshore Dr Destin FL 32550",
    "addr:housenumber":"31",
    "addr:postcode":"32550",
    "addr:street":"Bayshore Dr",
    "iso:country":"US",
    "sg:address":"31 Bayshore Dr",
    "sg:city":"Destin",
    "sg:classifiers":[
        {
            "category":"Professional",
            "subcategory":"Management & Consulting",
            "type":"Services"
        }
    ],
    "sg:phone":"+1 850 651 6514",
    "sg:postcode":"32550",
    "sg:province":"FL",
    "sg:tags":[
        "business"
    ],
    "wof:name":"Robert Loukota",
    "wof:placetype":"venue"
},
  "geometry": {"coordinates":[-86.360043,30.386533],"type":"Point"}
}