{
  "type": "Feature",
  "properties": {
    "iso:country":"US",
    "sg:address":"2010 W State Rd 40",
    "sg:city":"Ormond Beach",
    "sg:classifiers":[
        {
            "category":"Education",
            "subcategory":"School",
            "type":"Public Place"
        }
    ],
    "sg:phone":"+1 386 672 1620",
    "sg:postcode":"32174",
    "sg:province":"FL",
    "wof:name":"Childrens House of Ormond",
    "wof:placetype":"venue"
},
  "geometry": {"coordinates":[-81.13280399999999,29.252551],"type":"Point"}
}