{
  "type": "Feature",
  "properties": {
    "iso:country":"US",
    "sg:address":"4532 Edith St",
    "sg:city":"New Port Richey",
    "sg:classifiers":[
        {
            "category":"Building & Trades",
            "subcategory":"Landscaping Services",
            "type":"Services"
        }
    ],
    "sg:phone":"+1 727 847 4766",
    "sg:postcode":"34652",
    "sg:province":"FL",
    "wof:name":"Final Touch Landscape Services",
    "wof:placetype":"venue"
},
  "geometry": {"coordinates":[-82.73962400000001,28.226443],"type":"Point"}
}