{
  "type": "Feature",
  "properties": {
    "addr:full":"27 Montrano Ave Saint Augustine FL 32080",
    "addr:housenumber":"27",
    "addr:postcode":"32080",
    "addr:street":"Montrano Ave",
    "iso:country":"US",
    "sg:address":"27 Montrano Ave",
    "sg:city":"Saint Augustine",
    "sg:classifiers":[
        {
            "category":"Professional",
            "subcategory":"Business Services",
            "type":"Services"
        }
    ],
    "sg:phone":"+1 904 826 1672",
    "sg:postcode":"32080",
    "sg:province":"FL",
    "wof:name":"Cindy Wilson Advg Design",
    "wof:placetype":"venue"
},
  "geometry": {"coordinates":[-81.30143200000001,29.898518],"type":"Point"}
}