{
  "type": "Feature",
  "properties": {
    "addr:full":"17701 Biscayne Blvd Aventura FL 33160",
    "addr:housenumber":"17701",
    "addr:postcode":"33160",
    "addr:street":"Biscayne Blvd",
    "iso:country":"US",
    "sg:address":"17701 Biscayne Blvd",
    "sg:city":"Aventura",
    "sg:classifiers":[
        {
            "category":"Professional",
            "subcategory":"Accounting & Tax Preparation",
            "type":"Services"
        }
    ],
    "sg:phone":"+1 305 932 2120",
    "sg:postcode":"33160",
    "sg:province":"FL",
    "sg:tags":[
        "accountant"
    ],
    "wof:name":"Brown Steven M CPA",
    "wof:placetype":"venue"
},
  "geometry": {"coordinates":[-80.14919999999999,25.9398],"type":"Point"}
}