{
  "type": "Feature",
  "properties": {
    "addr:full":"417 W Belt Ave Bushnell FL 33513",
    "addr:housenumber":"417",
    "addr:postcode":"33513",
    "addr:street":"W Belt Ave",
    "iso:country":"US",
    "sg:address":"417 W Belt Ave",
    "sg:city":"Bushnell",
    "sg:classifiers":[
        {
            "category":"Personal",
            "subcategory":"Beauty Salon",
            "type":"Services"
        }
    ],
    "sg:phone":"+1 352 793 8700",
    "sg:postcode":"33513",
    "sg:province":"FL",
    "wof:name":"Southern Style",
    "wof:placetype":"venue"
},
  "geometry": {"coordinates":[-82.11900300000001,28.668505],"type":"Point"}
}