{
  "type": "Feature",
  "properties": {
    "iso:country":"US",
    "sg:address":"5318 Normandy Blvd",
    "sg:city":"Jacksonville",
    "sg:classifiers":[
        {
            "category":"Shopping",
            "subcategory":"Clothing, Apparel, & Fashions",
            "type":"Retail Goods"
        }
    ],
    "sg:phone":"+1 904 786 8770",
    "sg:postcode":"32205",
    "sg:province":"FL",
    "sg:tags":[
        "furnishing"
    ],
    "sg:website":"www.jimtatums.com",
    "wof:name":"Jim Tatum's Men's Shops Inc",
    "wof:placetype":"venue"
},
  "geometry": {"coordinates":[-81.739098,30.308938],"type":"Point"}
}