{
  "type": "Feature",
  "properties": {
    "iso:country":"US",
    "sg:address":"4689 Volunteer Rd",
    "sg:city":"Fort Lauderdale",
    "sg:classifiers":[
        {
            "category":"Restaurant",
            "type":"Food & Drink"
        }
    ],
    "sg:menulink":"http://www.allmenus.com/fl/davie/93289-waffle-house/menu/",
    "sg:phone":"+1 954 252 0867",
    "sg:postcode":"33330",
    "sg:province":"FL",
    "sg:tags":[
        "american"
    ],
    "wof:name":"Waffle House",
    "wof:placetype":"venue"
},
  "geometry": {"coordinates":[-80.346107,26.062054],"type":"Point"}
}