{
  "type": "Feature",
  "properties": {
    "addr:full":"7961 Gladiolus Dr Fort Myers FL 33908",
    "addr:housenumber":"7961",
    "addr:postcode":"33908",
    "addr:street":"Gladiolus Dr",
    "iso:country":"US",
    "sg:address":"7961 Gladiolus Dr",
    "sg:city":"Fort Myers",
    "sg:classifiers":[
        {
            "category":"Real Estate",
            "subcategory":"Real Estate Operator",
            "type":"Services"
        }
    ],
    "sg:phone":"+1 239 466 5652",
    "sg:postcode":"33908",
    "sg:province":"FL",
    "sg:tags":[
        "apartment"
    ],
    "wof:name":"Lakes Park Apartments",
    "wof:placetype":"venue"
},
  "geometry": {"coordinates":[-81.88556199999999,26.520721],"type":"Point"}
}