{
  "type": "Feature",
  "properties": {
    "addr:full":"10100 SW 216th St Miami FL 33190",
    "addr:housenumber":"10100",
    "addr:postcode":"33190",
    "addr:street":"Sw 216Th St",
    "iso:country":"US",
    "sg:address":"10100 SW 216th St",
    "sg:city":"Miami",
    "sg:classifiers":[
        {
            "category":"Freight",
            "type":"Transportation"
        }
    ],
    "sg:phone":"+1 305 254 1777",
    "sg:postcode":"33190",
    "sg:province":"FL",
    "sg:tags":[
        "general"
    ],
    "wof:name":"U-Store-It Mini Warehouse Co",
    "wof:placetype":"venue"
},
  "geometry": {"coordinates":[-80.354812,25.566663],"type":"Point"}
}