{
  "type": "Feature",
  "properties": {
    "addr:full":"279 Marion Oaks Mnr Ocala FL 34473",
    "addr:housenumber":"279",
    "addr:postcode":"34473",
    "addr:street":"Marion",
    "iso:country":"US",
    "sg:address":"279 Marion Oaks Mnr",
    "sg:city":"Ocala",
    "sg:classifiers":[
        {
            "category":"Place Of Worship",
            "subcategory":"Church",
            "type":"Public Place"
        },
        {
            "category":"Place Of Worship",
            "type":"Public Place"
        }
    ],
    "sg:phone":"+1 352 347 1161",
    "sg:postcode":"34473",
    "sg:province":"FL",
    "sg:tags":[
        "churches-presbyterian-arp",
        "churches-presbyterian"
    ],
    "wof:name":"Presbyterian Church At Marion Oaks",
    "wof:placetype":"venue"
},
  "geometry": {"coordinates":[-82.17150100000001,28.991039],"type":"Point"}
}