{
  "type": "Feature",
  "properties": {
    "iso:country":"US",
    "sg:address":"1 N Federal Hwy",
    "sg:city":"Pompano Beach",
    "sg:classifiers":[
        {
            "category":"Autos & Motor Vehicles",
            "subcategory":"Fuel & Gas Station",
            "type":"Retail Goods"
        }
    ],
    "sg:phone":"+1 954 942 2195",
    "sg:postcode":"33062",
    "sg:province":"FL",
    "sg:tags":[
        "oil"
    ],
    "wof:name":"Sunoco",
    "wof:placetype":"venue"
},
  "geometry": {"coordinates":[-80.10289299999999,26.23362],"type":"Point"}
}