{
  "type": "Feature",
  "properties": {
    "iso:country":"US",
    "sg:address":"153 SW 52nd St",
    "sg:city":"Cape Coral",
    "sg:classifiers":[
        {
            "category":"Organizations",
            "subcategory":"Professional Association",
            "type":"Services"
        }
    ],
    "sg:phone":"+1 239 542 5060",
    "sg:postcode":"33914",
    "sg:province":"FL",
    "sg:tags":[
        "business"
    ],
    "wof:name":"Cape Coral Absentee Prop Onr",
    "wof:placetype":"venue"
},
  "geometry": {"coordinates":[-81.97691500000001,26.555518],"type":"Point"}
}