{
  "type": "Feature",
  "properties": {
    "iso:country":"US",
    "sg:address":"1219 Citrus Terrace Dr",
    "sg:city":"Sebring",
    "sg:classifiers":[
        {
            "category":"Real Estate",
            "subcategory":"Real Estate Services",
            "type":"Services"
        },
        {
            "category":"Real Estate",
            "subcategory":"Real Estate Operator",
            "type":"Services"
        }
    ],
    "sg:phone":"+1 863 382 4664",
    "sg:postcode":"33870",
    "sg:province":"FL",
    "sg:tags":[
        "apartment",
        "vacancy",
        "listing",
        "rental",
        "finder"
    ],
    "wof:name":"Citrus Terrace Ltd",
    "wof:placetype":"venue"
},
  "geometry": {"coordinates":[-81.434517,27.508091],"type":"Point"}
}