{
  "type": "Feature",
  "properties": {
    "addr:full":"1927 NE 90th Pl Ste A Anthony FL 32617",
    "addr:housenumber":"1927",
    "addr:postcode":"32617",
    "addr:street":"Ne 90Th Pl Ste A Anthony",
    "iso:country":"US",
    "sg:address":"1927 NE 90th Pl Ste A",
    "sg:city":"Anthony",
    "sg:classifiers":[
        {
            "category":"Building & Trades",
            "subcategory":"Plumbing",
            "type":"Services"
        }
    ],
    "sg:phone":"+1 352 732 0646",
    "sg:postcode":"32617",
    "sg:province":"FL",
    "sg:tags":[
        "plumber",
        "industrial",
        "contractors-commercial"
    ],
    "wof:name":"Jim Thompson Plumbing",
    "wof:placetype":"venue"
},
  "geometry": {"coordinates":[-82.112201,29.281844],"type":"Point"}
}