{
  "type": "Feature",
  "properties": {
    "addr:full":"34106 US Hwy 19 N Palm Harbor FL 34684",
    "addr:housenumber":"34106",
    "addr:postcode":"34684",
    "addr:street":"Us Hwy 19 N",
    "iso:country":"US",
    "sg:address":"34106 US Hwy 19 N",
    "sg:city":"Palm Harbor",
    "sg:classifiers":[
        {
            "category":"Travel",
            "subcategory":"Hotels & Motels",
            "type":"Entertainment"
        }
    ],
    "sg:phone":"+1 727 789 2002",
    "sg:postcode":"34684",
    "sg:province":"FL",
    "sg:tags":[
        "operation"
    ],
    "sg:website":"www.knightsinn.com",
    "wof:name":"Knights Inn",
    "wof:placetype":"venue"
},
  "geometry": {"coordinates":[-82.739155,28.078903],"type":"Point"}
}