{
  "type": "Feature",
  "properties": {
    "iso:country":"US",
    "sg:address":"2350 S US Highway 17 92 Ste 1010",
    "sg:city":"Longwood",
    "sg:classifiers":[
        {
            "category":"Retail",
            "subcategory":"Auto Repair",
            "type":"Services"
        }
    ],
    "sg:phone":"+1 407 678 1505",
    "sg:postcode":"32750",
    "sg:province":"FL",
    "wof:name":"Euro Specialists",
    "wof:placetype":"venue"
},
  "geometry": {"coordinates":[-81.333855,28.6845],"type":"Point"}
}