{
  "type": "Feature",
  "properties": {
    "iso:country":"US",
    "sg:address":"9655 NW 26th Ct",
    "sg:city":"Pompano Beach",
    "sg:classifiers":[
        {
            "category":"Real Estate",
            "subcategory":"Architect",
            "type":"Services"
        }
    ],
    "sg:phone":"+1 954 575 9273",
    "sg:postcode":"33065",
    "sg:province":"FL",
    "sg:tags":[
        "architectural"
    ],
    "wof:name":"Five Star Millwork Inc",
    "wof:placetype":"venue"
},
  "geometry": {"coordinates":[-80.25461300000001,26.263075],"type":"Point"}
}