{
  "type": "Feature",
  "properties": {
    "addr:full":"2511 18th Ave NE Naples FL 34120",
    "addr:housenumber":"2511",
    "addr:postcode":"34120",
    "addr:street":"18Th Ave Ne",
    "iso:country":"US",
    "sg:address":"2511 18th Ave NE",
    "sg:city":"Naples",
    "sg:classifiers":[
        {
            "category":"Building & Trades",
            "subcategory":"Construction",
            "type":"Services"
        }
    ],
    "sg:phone":"+1 239 304 0749",
    "sg:postcode":"34120",
    "sg:province":"FL",
    "sg:tags":[
        "hanging",
        "contractor"
    ],
    "wof:name":"Armadillo Painting",
    "wof:placetype":"venue"
},
  "geometry": {"coordinates":[-81.54643299999999,26.263461],"type":"Point"}
}