{
  "type": "Feature",
  "properties": {
    "iso:country":"US",
    "sg:address":"230 NE 51st St Apt 2",
    "sg:city":"Miami",
    "sg:classifiers":[
        {
            "category":"Professional",
            "subcategory":"Printing & Photocopies",
            "type":"Services"
        }
    ],
    "sg:phone":"+1 786 222 9405",
    "sg:postcode":"33137",
    "sg:province":"FL",
    "sg:tags":[
        "photographers-commercial"
    ],
    "wof:name":"Jorge Parra Photography",
    "wof:placetype":"venue"
},
  "geometry": {"coordinates":[-80.190974,25.822985],"type":"Point"}
}