{
  "type": "Feature",
  "properties": {
    "iso:country":"US",
    "sg:address":"3800 Dixie Hwy NE",
    "sg:city":"Melbourne",
    "sg:classifiers":[
        {
            "category":"Autos & Motor Vehicles",
            "subcategory":"Boat Sales",
            "type":"Retail Goods"
        }
    ],
    "sg:phone":"+1 321 724 5153",
    "sg:postcode":"32905",
    "sg:province":"FL",
    "sg:tags":[
        "dealer",
        "sales"
    ],
    "wof:name":"Bill's Discount Marine",
    "wof:placetype":"venue"
},
  "geometry": {"coordinates":[-80.586023,28.045377],"type":"Point"}
}