{
  "type": "Feature",
  "properties": {
    "iso:country":"US",
    "sg:address":"612 Congressional Way",
    "sg:city":"Deerfield Beach",
    "sg:classifiers":[
        {
            "category":"Insurance",
            "subcategory":"Insurance Agent",
            "type":"Services"
        }
    ],
    "sg:phone":"+1 954 480 8568",
    "sg:postcode":"33442",
    "sg:province":"FL",
    "wof:name":"Soltes & Friedson Agency Inc",
    "wof:placetype":"venue"
},
  "geometry": {"coordinates":[-80.160562,26.296865],"type":"Point"}
}