{
  "type": "Feature",
  "properties": {
    "iso:country":"US",
    "sg:address":"16634 Saddle Club Rd",
    "sg:city":"Weston",
    "sg:classifiers":[
        {
            "category":"Shopping",
            "subcategory":"Florist",
            "type":"Retail Goods"
        }
    ],
    "sg:phone":"+1 954 384 9859",
    "sg:postcode":"33326",
    "sg:province":"FL",
    "wof:name":"Art Of Flowers",
    "wof:placetype":"venue"
},
  "geometry": {"coordinates":[-80.375387,26.115919],"type":"Point"}
}