{
  "type": "Feature",
  "properties": {
    "addr:full":"3826 E Gulf To Lake Hwy Inverness FL 34453",
    "addr:housenumber":"3826",
    "addr:postcode":"34453",
    "addr:street":"E Gulf To Lake Hwy",
    "iso:country":"US",
    "sg:address":"3826 E Gulf To Lake Hwy",
    "sg:city":"Inverness",
    "sg:classifiers":[
        {
            "category":"Food & Beverages",
            "subcategory":"Bakery",
            "type":"Retail Goods"
        }
    ],
    "sg:phone":"+1 352 344 8539",
    "sg:postcode":"34453",
    "sg:province":"FL",
    "wof:name":"Bakery Thrift N Stuff Pep",
    "wof:placetype":"venue"
},
  "geometry": {"coordinates":[-82.371292,28.847137],"type":"Point"}
}