{
  "type": "Feature",
  "properties": {
    "addr:full":"1 Curtiss Pkwy Ste 6 Miami Springs FL 33166",
    "addr:housenumber":"1",
    "addr:postcode":"33166",
    "addr:street":"Curtiss Pkwy Ste 6",
    "iso:country":"US",
    "sg:address":"1 Curtiss Pkwy Ste 6",
    "sg:city":"Miami Springs",
    "sg:classifiers":[
        {
            "category":"Health Services",
            "subcategory":"Health Practitioner",
            "type":"Services"
        }
    ],
    "sg:phone":"+1 786 972 1616",
    "sg:postcode":"33166",
    "sg:province":"FL",
    "sg:tags":[
        "acupuncture"
    ],
    "sg:website":"miamiacupuncturetherapy.com",
    "wof:name":"Miami Acupuncture Therapy",
    "wof:placetype":"venue"
},
  "geometry": {"coordinates":[-80.28074100000001,25.821767],"type":"Point"}
}