{
  "type": "Feature",
  "properties": {
    "addr:full":"6499 38th Ave N St Petersburg FL 33710",
    "addr:housenumber":"6499",
    "addr:postcode":"33710",
    "addr:street":"38Th Ave N",
    "iso:country":"US",
    "sg:address":"6499 38th Ave N",
    "sg:city":"St Petersburg",
    "sg:classifiers":[
        {
            "category":"Manufacturing",
            "subcategory":"Tools & Machinery",
            "type":"Manufacturing & Wholesale Goods"
        }
    ],
    "sg:phone":"+1 727 343 6528",
    "sg:postcode":"33710",
    "sg:province":"FL",
    "sg:tags":[
        "physician",
        "surgeon"
    ],
    "sg:website":"www.pinellascancercenter.com",
    "wof:name":"Pinellas Cancer Ctr",
    "wof:placetype":"venue"
},
  "geometry": {"coordinates":[-82.726767,27.806433],"type":"Point"}
}