{
  "type": "Feature",
  "properties": {
    "iso:country":"US",
    "sg:address":"42 E Magnolia Ave",
    "sg:city":"Eustis",
    "sg:classifiers":[
        {
            "category":"Shopping",
            "subcategory":"Jewelry",
            "type":"Retail Goods"
        }
    ],
    "sg:phone":"+1 352 589 4321",
    "sg:postcode":"32726",
    "sg:province":"FL",
    "wof:name":"Merry Jewelers Inc",
    "wof:placetype":"venue"
},
  "geometry": {"coordinates":[-81.685576,28.853552],"type":"Point"}
}