{
  "type": "Feature",
  "properties": {
    "addr:full":"249 N Hampton Dr Davenport FL 33897",
    "addr:housenumber":"249",
    "addr:postcode":"33897",
    "addr:street":"N Hampton Dr",
    "iso:country":"US",
    "sg:address":"249 N Hampton Dr",
    "sg:city":"Davenport",
    "sg:classifiers":[
        {
            "category":"Building & Trades",
            "subcategory":"Equipment Rental",
            "type":"Services"
        }
    ],
    "sg:phone":"+1 863 420 0437",
    "sg:postcode":"33897",
    "sg:province":"FL",
    "wof:name":"Brazell Rentals",
    "wof:placetype":"venue"
},
  "geometry": {"coordinates":[-81.676922,28.338772],"type":"Point"}
}