{
  "type": "Feature",
  "properties": {
    "addr:full":"776 NW 129th Pl Miami FL 33182",
    "addr:housenumber":"776",
    "addr:postcode":"33182",
    "addr:street":"Nw 129Th Pl",
    "iso:country":"US",
    "sg:address":"776 NW 129th Pl",
    "sg:city":"Miami",
    "sg:classifiers":[
        {
            "category":"Utilities",
            "subcategory":"Telephone",
            "type":"Services"
        }
    ],
    "sg:phone":"+1 786 515 3561",
    "sg:postcode":"33182",
    "sg:province":"FL",
    "sg:tags":[
        "distance",
        "companies-long"
    ],
    "wof:name":"Terra Telecom Inc.",
    "wof:placetype":"venue"
},
  "geometry": {"coordinates":[-80.40689399999999,25.775251],"type":"Point"}
}