{
  "type": "Feature",
  "properties": {
    "iso:country":"US",
    "sg:address":"3709 Ventura Dr E",
    "sg:city":"Lakeland",
    "sg:classifiers":[
        {
            "category":"Freight",
            "type":"Transportation"
        }
    ],
    "sg:phone":"+1 863 646 6918",
    "sg:postcode":"33811",
    "sg:province":"FL",
    "sg:tags":[
        "commercial",
        "storage"
    ],
    "wof:name":"U-Store-It",
    "wof:placetype":"venue"
},
  "geometry": {"coordinates":[-82.028199,27.997866],"type":"Point"}
}