{
  "type": "Feature",
  "properties": {
    "addr:full":"15700 NW 67th Ave Hialeah FL 33014",
    "addr:housenumber":"15700",
    "addr:postcode":"33014",
    "addr:street":"Nw 67Th Ave",
    "iso:country":"US",
    "sg:address":"15700 NW 67th Ave",
    "sg:city":"Hialeah",
    "sg:classifiers":[
        {
            "category":"Health Services",
            "subcategory":"Podiatrist",
            "type":"Services"
        }
    ],
    "sg:phone":"+1 305 655 1200",
    "sg:postcode":"33014",
    "sg:province":"FL",
    "wof:name":"Mark Feldman DPM",
    "wof:placetype":"venue"
},
  "geometry": {"coordinates":[-80.309173,25.917731],"type":"Point"}
}