{
  "type": "Feature",
  "properties": {
    "iso:country":"US",
    "sg:address":"15700 SE 73rd Ave",
    "sg:city":"Summerfield",
    "sg:classifiers":[
        {
            "category":"Building & Trades",
            "subcategory":"Equipment Rental",
            "type":"Services"
        }
    ],
    "sg:phone":"+1 352 307 3579",
    "sg:postcode":"34491",
    "sg:province":"FL",
    "sg:tags":[
        "toilet"
    ],
    "wof:name":"Tri County Portolet LLC",
    "wof:placetype":"venue"
},
  "geometry": {"coordinates":[-82.033027,28.9948],"type":"Point"}
}