{
  "type": "Feature",
  "properties": {
    "addr:full":"6400 Mallard Trace Dr Tallahassee FL 32312",
    "addr:housenumber":"6400",
    "addr:postcode":"32312",
    "addr:street":"Mallard Trace Dr",
    "iso:country":"US",
    "sg:address":"6400 Mallard Trace Dr",
    "sg:city":"Tallahassee",
    "sg:classifiers":[
        {
            "category":"Real Estate",
            "subcategory":"Real Estate Agent",
            "type":"Services"
        }
    ],
    "sg:phone":"+1 850 894 9788",
    "sg:postcode":"32312",
    "sg:province":"FL",
    "wof:name":"Sheila Jett Unique Realty Inc",
    "wof:placetype":"venue"
},
  "geometry": {"coordinates":[-84.272609,30.568524],"type":"Point"}
}