{
  "type": "Feature",
  "properties": {
    "iso:country":"US",
    "sg:address":"2522 Santa Barbara Blvd",
    "sg:city":"Cape Coral",
    "sg:classifiers":[
        {
            "category":"Restaurant",
            "type":"Food & Drink"
        }
    ],
    "sg:phone":"+1 239 573 1210",
    "sg:postcode":"33914",
    "sg:province":"FL",
    "sg:website":"www.subway.com",
    "wof:name":"Subway Sandwiches",
    "wof:placetype":"venue"
},
  "geometry": {"coordinates":[-81.974403,26.6054],"type":"Point"}
}