{
  "type": "Feature",
  "properties": {
    "iso:country":"US",
    "sg:address":"301 W Platt St",
    "sg:city":"Tampa",
    "sg:classifiers":[
        {
            "category":"Professional",
            "subcategory":"Management & Consulting",
            "type":"Services"
        }
    ],
    "sg:phone":"+1 813 254 1757",
    "sg:postcode":"33606",
    "sg:province":"FL",
    "sg:tags":[
        "marketing",
        "program"
    ],
    "wof:name":"365 Direct Marketing Co",
    "wof:placetype":"venue"
},
  "geometry": {"coordinates":[-82.46392299999999,27.941677],"type":"Point"}
}