{
  "type": "Feature",
  "properties": {
    "iso:country":"US",
    "sg:address":"505 Hardwood Cir",
    "sg:city":"Orlando",
    "sg:classifiers":[
        {
            "category":"Shopping",
            "type":"Retail Goods"
        }
    ],
    "sg:phone":"+1 407 489 9896",
    "sg:postcode":"32828",
    "sg:province":"FL",
    "sg:tags":[
        "merchandise"
    ],
    "wof:name":"Sol Casa",
    "wof:placetype":"venue"
},
  "geometry": {"coordinates":[-81.17140499999999,28.547565],"type":"Point"}
}