{
  "type": "Feature",
  "properties": {
    "addr:full":"26933 Red Farm Rd Mt Dora FL 32757",
    "addr:housenumber":"26933",
    "addr:postcode":"32757",
    "addr:street":"Red Farm Rd",
    "iso:country":"US",
    "sg:address":"26933 Red Farm Rd",
    "sg:city":"Mt Dora",
    "sg:classifiers":[
        {
            "category":"Building & Trades",
            "subcategory":"Construction",
            "type":"Services"
        }
    ],
    "sg:phone":"+1 352 383 2395",
    "sg:postcode":"32757",
    "sg:province":"FL",
    "sg:tags":[
        "carpentry",
        "carpenter",
        "contractor"
    ],
    "wof:name":"Southern Framing Enterprises",
    "wof:placetype":"venue"
},
  "geometry": {"coordinates":[-81.662707,28.732591],"type":"Point"}
}