{
  "type": "Feature",
  "properties": {
    "addr:full":"2476 Flamingo Rd Palm Beach Gdns FL 33410",
    "addr:housenumber":"2476",
    "addr:postcode":"33410",
    "addr:street":"Flamingo Rd;Beach Gdns",
    "iso:country":"US",
    "sg:address":"2476 Flamingo Rd",
    "sg:city":"Palm Beach Gdns",
    "sg:classifiers":[
        {
            "category":"Wholesale",
            "subcategory":"Motor Vehicles",
            "type":"Manufacturing & Wholesale Goods"
        },
        {
            "category":"Professional",
            "subcategory":"Advertising",
            "type":"Services"
        }
    ],
    "sg:phone":"+1 561 776 8117",
    "sg:postcode":"33410",
    "sg:province":"FL",
    "sg:tags":[
        "distribution"
    ],
    "wof:name":"Southeast Cross Lander Dealers",
    "wof:placetype":"venue"
},
  "geometry": {"coordinates":[-80.070228,26.86728],"type":"Point"}
}