{
  "type": "Feature",
  "properties": {
    "iso:country":"US",
    "sg:address":"913 W Fribley St",
    "sg:city":"Tampa",
    "sg:classifiers":[
        {
            "category":"Building & Trades",
            "subcategory":"Construction",
            "type":"Services"
        }
    ],
    "sg:phone":"+1 813 224 9631",
    "sg:postcode":"33603",
    "sg:province":"FL",
    "sg:tags":[
        "house"
    ],
    "wof:name":"Anew Homes",
    "wof:placetype":"venue"
},
  "geometry": {"coordinates":[-82.473496,27.974682],"type":"Point"}
}