{
  "type": "Feature",
  "properties": {
    "iso:country":"US",
    "sg:address":"714 17th St E",
    "sg:city":"Palmetto",
    "sg:classifiers":[
        {
            "category":"Building & Trades",
            "subcategory":"Construction",
            "type":"Services"
        }
    ],
    "sg:phone":"+1 941 727 1444",
    "sg:postcode":"34221",
    "sg:province":"FL",
    "sg:tags":[
        "fabricator",
        "industrial",
        "metal",
        "nonresidential"
    ],
    "sg:website":"www.ascifl.com",
    "wof:name":"All Steel Consultants Inc",
    "wof:placetype":"venue"
},
  "geometry": {"coordinates":[-82.551643,27.528494],"type":"Point"}
}