{
  "type": "Feature",
  "properties": {
    "iso:country":"US",
    "sg:address":"1380 NW 23rd St",
    "sg:city":"Miami",
    "sg:classifiers":[
        {
            "category":"Professional",
            "subcategory":"Business Services",
            "type":"Services"
        }
    ],
    "sg:phone":"+1 305 638 4005",
    "sg:postcode":"33142",
    "sg:province":"FL",
    "sg:tags":[
        "broker",
        "merchandise"
    ],
    "wof:name":"Superior Broker",
    "wof:placetype":"venue"
},
  "geometry": {"coordinates":[-80.21780800000001,25.798537],"type":"Point"}
}