{
  "type": "Feature",
  "properties": {
    "iso:country":"US",
    "sg:address":"9250 SW 152nd Pl",
    "sg:city":"Dunnellon",
    "sg:classifiers":[
        {
            "category":"Shopping",
            "subcategory":"Discount & Variety Stores",
            "type":"Retail Goods"
        }
    ],
    "sg:phone":"+1 352 861 4390",
    "sg:postcode":"34432",
    "sg:province":"FL",
    "sg:tags":[
        "merchandise",
        "general"
    ],
    "wof:name":"Charity Conner Retail",
    "wof:placetype":"venue"
},
  "geometry": {"coordinates":[-82.277734,29.000539],"type":"Point"}
}