{
  "type": "Feature",
  "properties": {
    "addr:full":"105 S Loxahatchee Dr Jupiter FL 33458",
    "addr:housenumber":"105",
    "addr:postcode":"33458",
    "addr:street":"S Loxahatchee Dr",
    "iso:country":"US",
    "sg:address":"105 S Loxahatchee Dr",
    "sg:city":"Jupiter",
    "sg:classifiers":[
        {
            "category":"Building & Trades",
            "subcategory":"Construction",
            "type":"Services"
        }
    ],
    "sg:phone":"+1 561 746 8130",
    "sg:postcode":"33458",
    "sg:province":"FL",
    "sg:tags":[
        "general",
        "contractor"
    ],
    "wof:name":"Corson Construction Inc",
    "wof:placetype":"venue"
},
  "geometry": {"coordinates":[-80.099681,26.933095],"type":"Point"}
}