{
  "type": "Feature",
  "properties": {
    "addr:full":"4000 Dow Rd Melbourne FL 32934",
    "addr:housenumber":"4000",
    "addr:postcode":"32934",
    "addr:street":"Dow Rd",
    "iso:country":"US",
    "sg:address":"4000 Dow Rd",
    "sg:city":"Melbourne",
    "sg:classifiers":[
        {
            "category":"Retail",
            "subcategory":"Laundry & Dry Cleaning",
            "type":"Services"
        }
    ],
    "sg:phone":"+1 321 779 0970",
    "sg:postcode":"32934",
    "sg:province":"FL",
    "sg:tags":[
        "rug",
        "carpet"
    ],
    "wof:name":"Dririte Carpet Cleaning",
    "wof:placetype":"venue"
},
  "geometry": {"coordinates":[-80.691053,28.107592],"type":"Point"}
}