{
  "type": "Feature",
  "properties": {
    "addr:full":"6831 Central Ave St Petersburg FL 33710",
    "addr:housenumber":"6831",
    "addr:postcode":"33710",
    "addr:street":"Central Ave",
    "iso:country":"US",
    "sg:address":"6831 Central Ave",
    "sg:city":"St Petersburg",
    "sg:classifiers":[
        {
            "category":"Home & Garden",
            "subcategory":"Garden Supply",
            "type":"Retail Goods"
        }
    ],
    "sg:phone":"+1 727 344 1668",
    "sg:postcode":"33710",
    "sg:province":"FL",
    "sg:tags":[
        "nurseryman"
    ],
    "sg:website":"www.tropicalfruit.com",
    "wof:name":"Jene's Tropical Fruit Trees",
    "wof:placetype":"venue"
},
  "geometry": {"coordinates":[-82.73237,27.770896],"type":"Point"}
}