{
  "type": "Feature",
  "properties": {
    "addr:full":"675 Kenwood Ct Satellite Beach FL 32937",
    "addr:housenumber":"675",
    "addr:postcode":"32937",
    "addr:street":"Kenwood Ct",
    "iso:country":"US",
    "sg:address":"675 Kenwood Ct",
    "sg:city":"Satellite Beach",
    "sg:classifiers":[
        {
            "category":"Freight",
            "type":"Transportation"
        }
    ],
    "sg:phone":"+1 321 777 9797",
    "sg:postcode":"32937",
    "sg:province":"FL",
    "sg:tags":[
        "operator",
        "local",
        "trucking"
    ],
    "wof:name":"Yacht Delivery Service",
    "wof:placetype":"venue"
},
  "geometry": {"coordinates":[-80.607388,28.17412],"type":"Point"}
}