{
  "type": "Feature",
  "properties": {
    "iso:country":"US",
    "sg:address":"110 NW 39th Ave",
    "sg:city":"Gainesville",
    "sg:classifiers":[
        {
            "category":"Real Estate",
            "subcategory":"Real Estate Operator",
            "type":"Services"
        }
    ],
    "sg:phone":"+1 352 378 3988",
    "sg:postcode":"32609",
    "sg:province":"FL",
    "sg:tags":[
        "building",
        "apartment"
    ],
    "wof:name":"Meadowcrest Apartments",
    "wof:placetype":"venue"
},
  "geometry": {"coordinates":[-82.330095,29.688597],"type":"Point"}
}