{
  "type": "Feature",
  "properties": {
    "addr:full":"1800 S Ocean Blvd Pompano Beach FL 33062",
    "addr:housenumber":"1800",
    "addr:postcode":"33062",
    "addr:street":"S Ocean Blvd",
    "iso:country":"US",
    "sg:address":"1800 S Ocean Blvd",
    "sg:city":"Pompano Beach",
    "sg:classifiers":[
        {
            "category":"Retail",
            "subcategory":"Auto Repair",
            "type":"Services"
        }
    ],
    "sg:phone":"+1 954 783 7502",
    "sg:postcode":"33062",
    "sg:province":"FL",
    "sg:tags":[
        "muffler"
    ],
    "wof:name":"Meineke Discount Mufflers",
    "wof:placetype":"venue"
},
  "geometry": {"coordinates":[-80.093385,26.210652],"type":"Point"}
}