{
  "type": "Feature",
  "properties": {
    "iso:country":"US",
    "sg:address":"3530 Old Dixie Hwy",
    "sg:city":"Mims",
    "sg:classifiers":[
        {
            "category":"Building & Trades",
            "subcategory":"Construction",
            "type":"Services"
        }
    ],
    "sg:phone":"+1 321 385 3135",
    "sg:postcode":"32754",
    "sg:province":"FL",
    "wof:name":"East Coast",
    "wof:placetype":"venue"
},
  "geometry": {"coordinates":[-80.857741,28.697228],"type":"Point"}
}