{
  "type": "Feature",
  "properties": {
    "addr:full":"214 Crystal Grove Blvd Lutz FL 33548",
    "addr:housenumber":"214",
    "addr:postcode":"33548",
    "addr:street":"Crystal Grove Blvd",
    "iso:country":"US",
    "sg:address":"214 Crystal Grove Blvd",
    "sg:city":"Lutz",
    "sg:classifiers":[
        {
            "category":"Wholesale",
            "subcategory":"Medical Equipment & Supplies",
            "type":"Manufacturing & Wholesale Goods"
        }
    ],
    "sg:phone":"+1 813 909 7160",
    "sg:postcode":"33548",
    "sg:province":"FL",
    "sg:tags":[
        "physician",
        "surgeon"
    ],
    "wof:name":"Medaright Inc",
    "wof:placetype":"venue"
},
  "geometry": {"coordinates":[-82.46343400000001,28.142398],"type":"Point"}
}