{
  "type": "Feature",
  "properties": {
    "addr:full":"2299 Sarno Rd Melbourne FL 32935",
    "addr:housenumber":"2299",
    "addr:postcode":"32935",
    "addr:street":"Sarno Rd",
    "iso:country":"US",
    "sg:address":"2299 Sarno Rd",
    "sg:city":"Melbourne",
    "sg:classifiers":[
        {
            "category":"Real Estate",
            "subcategory":"Real Estate Agent",
            "type":"Services"
        }
    ],
    "sg:phone":"+1 321 242 9230",
    "sg:postcode":"32935",
    "sg:province":"FL",
    "wof:name":"A Plus Schools Of Real Estate",
    "wof:placetype":"venue"
},
  "geometry": {"coordinates":[-80.660836,28.121561],"type":"Point"}
}