{
  "type": "Feature",
  "properties": {
    "addr:full":"38120 Theel Ave Zephyrhills FL 33540",
    "addr:postcode":"38120;33540",
    "addr:street":"Theel Ave",
    "iso:country":"US",
    "sg:address":"38120 Theel Ave",
    "sg:city":"Zephyrhills",
    "sg:classifiers":[
        {
            "category":"Shopping",
            "subcategory":"Discount & Variety Stores",
            "type":"Retail Goods"
        }
    ],
    "sg:phone":"+1 813 782 5296",
    "sg:postcode":"33540",
    "sg:province":"FL",
    "sg:tags":[
        "merchandise",
        "general"
    ],
    "wof:name":"Shane V Davis Enterprise",
    "wof:placetype":"venue"
},
  "geometry": {"coordinates":[-82.185267,28.283092],"type":"Point"}
}