{
  "type": "Feature",
  "properties": {
    "iso:country":"US",
    "sg:address":"111 Towne Center Blvd",
    "sg:city":"Sanford",
    "sg:classifiers":[
        {
            "category":"Home & Garden",
            "subcategory":"Home Furnishings",
            "type":"Retail Goods"
        }
    ],
    "sg:phone":"+1 407 322 7945",
    "sg:postcode":"32771",
    "sg:province":"FL",
    "sg:tags":[
        "housewares"
    ],
    "wof:name":"Bed Bath & Beyond",
    "wof:placetype":"venue"
},
  "geometry": {"coordinates":[-81.33470199999999,28.809438],"type":"Point"}
}