{
  "type": "Feature",
  "properties": {
    "iso:country":"US",
    "sg:address":"8004 Miami Lakes Dr #256",
    "sg:city":"Hialeah",
    "sg:classifiers":[
        {
            "category":"Travel",
            "subcategory":"Travel Agent",
            "type":"Entertainment"
        }
    ],
    "sg:phone":"+1 212 659 9999",
    "sg:postcode":"33014",
    "sg:province":"FL",
    "sg:tags":[
        "rental",
        "vacation"
    ],
    "wof:name":"Pelican Executive Suite LLC USA",
    "wof:placetype":"venue"
},
  "geometry": {"coordinates":[-80.305072,25.911317],"type":"Point"}
}