{
  "type": "Feature",
  "properties": {
    "addr:full":"7363 SW 24th St Miami FL 33155",
    "addr:housenumber":"7363",
    "addr:postcode":"33155",
    "addr:street":"Sw 24Th St",
    "iso:country":"US",
    "sg:address":"7363 SW 24th St",
    "sg:city":"Miami",
    "sg:classifiers":[
        {
            "category":"Travel",
            "subcategory":"Travel Agent",
            "type":"Entertainment"
        }
    ],
    "sg:phone":"+1 305 534 4244",
    "sg:postcode":"33155",
    "sg:province":"FL",
    "sg:tags":[
        "bureau"
    ],
    "wof:name":"Gla Mar Travel",
    "wof:placetype":"venue"
},
  "geometry": {"coordinates":[-80.313119,25.748169],"type":"Point"}
}