{
  "type": "Feature",
  "properties": {
    "iso:country":"US",
    "sg:address":"800 Brickell Ave Ste 701",
    "sg:city":"Miami",
    "sg:classifiers":[
        {
            "category":"Professional",
            "subcategory":"Lawyer & Legal Services",
            "type":"Services"
        }
    ],
    "sg:phone":"+1 305 372 0222",
    "sg:postcode":"33131",
    "sg:province":"FL",
    "sg:website":"www.kravitzlaw.com/michael.html",
    "wof:name":"Michael A. Harris, Immigration Attorney",
    "wof:placetype":"venue"
},
  "geometry": {"coordinates":[-80.19148300000001,25.76589],"type":"Point"}
}