{
  "type": "Feature",
  "properties": {
    "addr:full":"6415 Greenland Rd Jacksonville FL 32258",
    "addr:housenumber":"6415",
    "addr:postcode":"32258",
    "addr:street":"Greenland Rd",
    "iso:country":"US",
    "sg:address":"6415 Greenland Rd",
    "sg:city":"Jacksonville",
    "sg:classifiers":[
        {
            "category":"Building & Trades",
            "subcategory":"Construction",
            "type":"Services"
        }
    ],
    "sg:phone":"+1 904 268 3100",
    "sg:postcode":"32258",
    "sg:province":"FL",
    "sg:tags":[
        "water",
        "reconditioning",
        "plant",
        "reselling",
        "treatment"
    ],
    "wof:name":"Greenland Corporation",
    "wof:placetype":"venue"
},
  "geometry": {"coordinates":[-81.54020199999999,30.164349],"type":"Point"}
}