{
  "type": "Feature",
  "properties": {
    "addr:full":"4800 NW 36th Ave Miami FL 33142",
    "addr:housenumber":"4800",
    "addr:postcode":"33142",
    "addr:street":"Nw 36Th Ave",
    "iso:country":"US",
    "sg:address":"4800 NW 36th Ave",
    "sg:city":"Miami",
    "sg:classifiers":[
        {
            "category":"Communications",
            "type":"Services"
        }
    ],
    "sg:phone":"+1 786 265 8339",
    "sg:postcode":"33142",
    "sg:province":"FL",
    "wof:name":"Arinc",
    "wof:placetype":"venue"
},
  "geometry": {"coordinates":[-80.254784,25.817551],"type":"Point"}
}