{
  "type": "Feature",
  "properties": {
    "iso:country":"US",
    "sg:address":"2335 Mont Claire Dr",
    "sg:city":"Naples",
    "sg:classifiers":[
        {
            "category":"Real Estate",
            "subcategory":"Architect",
            "type":"Services"
        }
    ],
    "sg:phone":"+1 239 254 9931",
    "sg:postcode":"34109",
    "sg:province":"FL",
    "wof:name":"My Architect Inc",
    "wof:placetype":"venue"
},
  "geometry": {"coordinates":[-81.777092,26.249927],"type":"Point"}
}