{
  "type": "Feature",
  "properties": {
    "iso:country":"US",
    "sg:address":"8200 Vineland Ave # 1163",
    "sg:city":"Orlando",
    "sg:classifiers":[
        {
            "category":"Sports & Exercise",
            "subcategory":"Swimming Pool",
            "type":"Entertainment"
        }
    ],
    "sg:phone":"+1 407 239 4433",
    "sg:postcode":"32821",
    "sg:province":"FL",
    "sg:tags":[
        "swimwear",
        "accessory"
    ],
    "wof:name":"La Perla",
    "wof:placetype":"venue"
},
  "geometry": {"coordinates":[-81.496292,28.385798],"type":"Point"}
}