{
  "type": "Feature",
  "properties": {
    "iso:country":"US",
    "sg:address":"1408 SW 13th Ct",
    "sg:city":"Pompano Beach",
    "sg:classifiers":[
        {
            "category":"Wholesale",
            "subcategory":"Durable Goods & Equipment",
            "type":"Manufacturing & Wholesale Goods"
        }
    ],
    "sg:phone":"+1 954 941 8066",
    "sg:postcode":"33069",
    "sg:province":"FL",
    "wof:name":"Albatech Inc",
    "wof:placetype":"venue"
},
  "geometry": {"coordinates":[-80.141353,26.213404],"type":"Point"}
}