{
  "type": "Feature",
  "properties": {
    "iso:country":"US",
    "sg:address":"501 NE 1st Ave Ste 201",
    "sg:city":"Miami",
    "sg:classifiers":[
        {
            "category":"Professional",
            "subcategory":"Computer Services",
            "type":"Services"
        },
        {
            "category":"Wholesale",
            "subcategory":"Computers",
            "type":"Manufacturing & Wholesale Goods"
        }
    ],
    "sg:phone":"+1 347 214 0249",
    "sg:postcode":"33132",
    "sg:province":"FL",
    "sg:tags":[
        "equipment",
        "software"
    ],
    "wof:name":"Capitoldomains",
    "wof:placetype":"venue"
},
  "geometry": {"coordinates":[-80.192093,25.778999],"type":"Point"}
}