{
  "type": "Feature",
  "properties": {
    "iso:country":"US",
    "sg:address":"8350 Parkline Blvd",
    "sg:city":"Orlando",
    "sg:classifiers":[
        {
            "category":"Freight",
            "type":"Transportation"
        }
    ],
    "sg:phone":"+1 407 854 6770",
    "sg:postcode":"32809",
    "sg:province":"FL",
    "wof:name":"Xtreme Carage Orlando",
    "wof:placetype":"venue"
},
  "geometry": {"coordinates":[-81.363232,28.44716],"type":"Point"}
}