{
  "type": "Feature",
  "properties": {
    "addr:full":"406 Williams St Tallahassee FL 32303",
    "addr:housenumber":"406",
    "addr:postcode":"32303",
    "addr:street":"Williams St",
    "iso:country":"US",
    "sg:address":"406 Williams St",
    "sg:city":"Tallahassee",
    "sg:classifiers":[
        {
            "category":"Professional",
            "type":"Services"
        }
    ],
    "sg:phone":"+1 850 224 7054",
    "sg:postcode":"32303",
    "sg:province":"FL",
    "wof:name":"James Roche",
    "wof:placetype":"venue"
},
  "geometry": {"coordinates":[-84.277153,30.452309],"type":"Point"}
}