{
  "type": "Feature",
  "properties": {
    "iso:country":"US",
    "sg:address":"8912 SW 80th St",
    "sg:city":"Miami",
    "sg:classifiers":[
        {
            "category":"Retail",
            "subcategory":"Repair Shop",
            "type":"Services"
        }
    ],
    "sg:phone":"+1 305 271 0094",
    "sg:postcode":"33173",
    "sg:province":"FL",
    "sg:tags":[
        "picture",
        "framing",
        "custom"
    ],
    "wof:name":"Art Space LLC",
    "wof:placetype":"venue"
},
  "geometry": {"coordinates":[-80.338004,25.694941],"type":"Point"}
}