{
  "type": "Feature",
  "properties": {
    "iso:country":"US",
    "sg:address":"2107 W Jordan St",
    "sg:city":"Pensacola",
    "sg:classifiers":[
        {
            "category":"Wholesale",
            "subcategory":"Hardware",
            "type":"Manufacturing & Wholesale Goods"
        }
    ],
    "sg:phone":"+1 850 434 2711",
    "sg:postcode":"32505",
    "sg:province":"FL",
    "sg:tags":[
        "air",
        "parts",
        "conditioning",
        "supply"
    ],
    "wof:name":"Cooling & Heating Supplies",
    "wof:placetype":"venue"
},
  "geometry": {"coordinates":[-87.24151500000001,30.434034],"type":"Point"}
}