{
  "type": "Feature",
  "properties": {
    "addr:full":"5736 S Texas Ave Orlando FL 32839",
    "addr:housenumber":"5736",
    "addr:postcode":"32839",
    "addr:street":"S Texas Ave",
    "iso:country":"US",
    "sg:address":"5736 S Texas Ave",
    "sg:city":"Orlando",
    "sg:classifiers":[
        {
            "category":"Building & Trades",
            "subcategory":"Construction",
            "type":"Services"
        }
    ],
    "sg:phone":"+1 407 240 4610",
    "sg:postcode":"32839",
    "sg:province":"FL",
    "sg:tags":[
        "contractor"
    ],
    "wof:name":"Bayle Contracting",
    "wof:placetype":"venue"
},
  "geometry": {"coordinates":[-81.409192,28.475312],"type":"Point"}
}