{
  "type": "Feature",
  "properties": {
    "iso:country":"US",
    "sg:address":"14237 SW 94th Circle Ln A105",
    "sg:city":"Miami",
    "sg:classifiers":[
        {
            "category":"Real Estate",
            "subcategory":"Real Estate Services",
            "type":"Services"
        }
    ],
    "sg:phone":"+1 305 388 7314",
    "sg:postcode":"33186",
    "sg:province":"FL",
    "sg:tags":[
        "inspection"
    ],
    "wof:name":"3-D Home Inspections",
    "wof:placetype":"venue"
},
  "geometry": {"coordinates":[-80.423157,25.6798],"type":"Point"}
}