{
  "type": "Feature",
  "properties": {
    "addr:full":"2061 NW 112th Ave Ste 143 Miami FL 33172",
    "addr:housenumber":"2061",
    "addr:postcode":"33172",
    "addr:street":"Nw 112Th Ave Ste 143",
    "iso:country":"US",
    "sg:address":"2061 NW 112th Ave Ste 143",
    "sg:city":"Miami",
    "sg:classifiers":[
        {
            "category":"Wholesale",
            "subcategory":"Computers",
            "type":"Manufacturing & Wholesale Goods"
        }
    ],
    "sg:phone":"+1 305 597 5223",
    "sg:postcode":"33172",
    "sg:province":"FL",
    "sg:website":"www.shoptomatic.com",
    "wof:name":"Shoptomatic Llc",
    "wof:placetype":"venue"
},
  "geometry": {"coordinates":[-80.376632,25.793009],"type":"Point"}
}