{
  "type": "Feature",
  "properties": {
    "iso:country":"US",
    "sg:address":"2602 S Dixie Hwy",
    "sg:city":"West Palm Beach",
    "sg:classifiers":[
        {
            "category":"Shopping",
            "subcategory":"Jewelry",
            "type":"Retail Goods"
        }
    ],
    "sg:phone":"+1 561 655 9056",
    "sg:postcode":"33401",
    "sg:province":"FL",
    "sg:tags":[
        "jeweler"
    ],
    "sg:website":"www.westbestjewelers.com",
    "wof:name":"West Best Jewelers",
    "wof:placetype":"venue"
},
  "geometry": {"coordinates":[-80.054283,26.690798],"type":"Point"}
}