{
  "type": "Feature",
  "properties": {
    "addr:full":"1100 SW 84th Ave Miami FL 33144",
    "addr:housenumber":"1100",
    "addr:postcode":"33144",
    "addr:street":"Sw 84Th Ave",
    "iso:country":"US",
    "sg:address":"1100 SW 84th Ave",
    "sg:city":"Miami",
    "sg:classifiers":[
        {
            "category":"Health Services",
            "subcategory":"Clinic",
            "type":"Services"
        }
    ],
    "sg:phone":"+1 305 269 7919",
    "sg:postcode":"33144",
    "sg:province":"FL",
    "sg:tags":[
        "information",
        "treatment",
        "alcoholism"
    ],
    "wof:name":"Os Therapy Corp",
    "wof:placetype":"venue"
},
  "geometry": {"coordinates":[-80.33144,25.759348],"type":"Point"}
}