{
  "type": "Feature",
  "properties": {
    "addr:full":"202 Cypress Gardens Blvd Winter Haven FL 33880",
    "addr:housenumber":"202",
    "addr:postcode":"33880",
    "addr:street":"Cypress Gardens Blvd",
    "iso:country":"US",
    "sg:address":"202 Cypress Gardens Blvd",
    "sg:city":"Winter Haven",
    "sg:classifiers":[
        {
            "category":"Travel",
            "subcategory":"Hotels & Motels",
            "type":"Entertainment"
        }
    ],
    "sg:phone":"+1 863 299 9251",
    "sg:postcode":"33880",
    "sg:province":"FL",
    "wof:name":"Hampton Inn",
    "wof:placetype":"venue"
},
  "geometry": {"coordinates":[-81.724709,28.004084],"type":"Point"}
}