{
  "type": "Feature",
  "properties": {
    "addr:full":"14 Village Dr Ormond Beach FL 32174",
    "addr:housenumber":"14",
    "addr:postcode":"32174",
    "addr:street":"Village Dr",
    "iso:country":"US",
    "sg:address":"14 Village Dr",
    "sg:city":"Ormond Beach",
    "sg:classifiers":[
        {
            "category":"Building & Trades",
            "subcategory":"Plumbing",
            "type":"Services"
        }
    ],
    "sg:phone":"+1 386 677 9821",
    "sg:postcode":"32174",
    "sg:province":"FL",
    "sg:tags":[
        "contractor"
    ],
    "wof:name":"Pearsons Plumbing Inc",
    "wof:placetype":"venue"
},
  "geometry": {"coordinates":[-81.116795,29.33473],"type":"Point"}
}