{
  "type": "Feature",
  "properties": {
    "iso:country":"US",
    "sg:address":"2006 NW 55th Ave",
    "sg:city":"Margate",
    "sg:classifiers":[
        {
            "category":"Retail",
            "subcategory":"Auto Repair",
            "type":"Services"
        }
    ],
    "sg:phone":"+1 954 974 1799",
    "sg:postcode":"33063",
    "sg:province":"FL",
    "sg:tags":[
        "automobile",
        "customizing"
    ],
    "wof:name":"Thunder Alley Performance",
    "wof:placetype":"venue"
},
  "geometry": {"coordinates":[-80.19914900000001,26.253815],"type":"Point"}
}