{
  "type": "Feature",
  "properties": {
    "addr:full":"315 Francis Ter Daytona Beach FL 32118",
    "addr:housenumber":"315",
    "addr:postcode":"32118",
    "addr:street":"Francis Ter",
    "iso:country":"US",
    "sg:address":"315 Francis Ter",
    "sg:city":"Daytona Beach",
    "sg:classifiers":[
        {
            "category":"Building & Trades",
            "subcategory":"Construction",
            "type":"Services"
        }
    ],
    "sg:phone":"+1 386 258 6598",
    "sg:postcode":"32118",
    "sg:province":"FL",
    "sg:tags":[
        "hanging",
        "contractor"
    ],
    "wof:name":"B & Fs Painting & Home Rprs",
    "wof:placetype":"venue"
},
  "geometry": {"coordinates":[-81.004788,29.214322],"type":"Point"}
}