{
  "type": "Feature",
  "properties": {
    "iso:country":"US",
    "sg:address":"2615 N Forest Ridge Blvd",
    "sg:city":"Hernando",
    "sg:classifiers":[
        {
            "category":"Personal",
            "subcategory":"Beauty Salon",
            "type":"Services"
        }
    ],
    "sg:phone":"+1 352 527 2552",
    "sg:postcode":"34442",
    "sg:province":"FL",
    "wof:name":"Attitudes",
    "wof:placetype":"venue"
},
  "geometry": {"coordinates":[-82.447721,28.90352],"type":"Point"}
}