{
  "type": "Feature",
  "properties": {
    "addr:full":"489 Olive Cir Green Cove Springs FL 32043",
    "addr:housenumber":"489",
    "addr:postcode":"32043",
    "addr:street":"Olive Cir",
    "iso:country":"US",
    "sg:address":"489 Olive Cir",
    "sg:city":"Green Cove Springs",
    "sg:classifiers":[
        {
            "category":"Restaurant",
            "type":"Food & Drink"
        }
    ],
    "sg:phone":"+1 904 529 7773",
    "sg:postcode":"32043",
    "sg:province":"FL",
    "sg:tags":[
        "eating"
    ],
    "wof:name":"Hungry Howies Pizza",
    "wof:placetype":"venue"
},
  "geometry": {"coordinates":[-81.690302,29.981032],"type":"Point"}
}