{
  "type": "Feature",
  "properties": {
    "iso:country":"US",
    "sg:address":"2186 Kathleen Ave",
    "sg:city":"Cantonment",
    "sg:classifiers":[
        {
            "category":"Autos & Motor Vehicles",
            "subcategory":"Auto Supplies",
            "type":"Retail Goods"
        }
    ],
    "sg:phone":"+1 850 937 8909",
    "sg:postcode":"32533",
    "sg:province":"FL",
    "wof:name":"Lk Products",
    "wof:placetype":"venue"
},
  "geometry": {"coordinates":[-87.29495300000001,30.605595],"type":"Point"}
}