{
  "type": "Feature",
  "properties": {
    "addr:full":"23007 State Hwy 7 Boca Raton FL 33428",
    "addr:housenumber":"23007",
    "addr:postcode":"33428",
    "addr:street":"State Hwy 7",
    "iso:country":"US",
    "sg:address":"23007 State Hwy 7",
    "sg:city":"Boca Raton",
    "sg:classifiers":[
        {
            "category":"Health Services",
            "subcategory":"Optometrist",
            "type":"Services"
        }
    ],
    "sg:phone":"+1 561 482 0099",
    "sg:postcode":"33428",
    "sg:province":"FL",
    "wof:name":"Jeffrey A Weiss OD",
    "wof:placetype":"venue"
},
  "geometry": {"coordinates":[-80.203158,26.334503],"type":"Point"}
}