{
  "type": "Feature",
  "properties": {
    "iso:country":"US",
    "sg:address":"4336 4th St N",
    "sg:city":"St Petersburg",
    "sg:classifiers":[
        {
            "category":"Shopping",
            "type":"Retail Goods"
        },
        {
            "category":"Shopping",
            "subcategory":"Hobbies, Toys, & Games",
            "type":"Retail Goods"
        }
    ],
    "sg:phone":"+1 727 522 5351",
    "sg:postcode":"33703",
    "sg:province":"FL",
    "sg:tags":[
        "merchandise"
    ],
    "wof:name":"Timothy's Toys",
    "wof:placetype":"venue"
},
  "geometry": {"coordinates":[-82.63869,27.811801],"type":"Point"}
}