{
  "type": "Feature",
  "properties": {
    "addr:full":"3531 Pacetti Rd St Augustine FL 32092",
    "addr:housenumber":"3531",
    "addr:postcode":"32092",
    "addr:street":"Pacetti Rd St",
    "iso:country":"US",
    "sg:address":"3531 Pacetti Rd",
    "sg:city":"St Augustine",
    "sg:classifiers":[
        {
            "category":"Retail",
            "subcategory":"Repair Shop",
            "type":"Services"
        }
    ],
    "sg:phone":"+1 904 377 6847",
    "sg:postcode":"32092",
    "sg:province":"FL",
    "sg:tags":[
        "screen"
    ],
    "wof:name":"Kleiber Family Screen Repairs",
    "wof:placetype":"venue"
},
  "geometry": {"coordinates":[-81.499217,29.945094],"type":"Point"}
}