{
  "type": "Feature",
  "properties": {
    "iso:country":"US",
    "sg:address":"1211 E Semoran Blvd",
    "sg:city":"Apopka",
    "sg:classifiers":[
        {
            "category":"Education",
            "subcategory":"Library",
            "type":"Public Place"
        }
    ],
    "sg:phone":"+1 407 814 6150",
    "sg:postcode":"32703",
    "sg:province":"FL",
    "wof:name":"North Orange Library",
    "wof:placetype":"venue"
},
  "geometry": {"coordinates":[-81.487858,28.673075],"type":"Point"}
}