{
  "type": "Feature",
  "properties": {
    "iso:country":"US",
    "sg:address":"7605 W Hillsborough Ave",
    "sg:city":"Tampa",
    "sg:classifiers":[
        {
            "category":"Restaurant",
            "type":"Food & Drink"
        }
    ],
    "sg:menulink":"http://www.allmenus.com/fl/tampa/189563-kfc---kentucky-fried-chicken/menu/",
    "sg:phone":"+1 813 884 4372",
    "sg:postcode":"33615",
    "sg:province":"FL",
    "sg:tags":[
        "american",
        "chicken"
    ],
    "wof:name":"KFC - Kentucky Fried Chicken",
    "wof:placetype":"venue"
},
  "geometry": {"coordinates":[-82.564984,27.996657],"type":"Point"}
}