{
  "type": "Feature",
  "properties": {
    "addr:full":"313 S State Road 7 Plantation FL 33317",
    "addr:housenumber":"313",
    "addr:postcode":"33317",
    "addr:street":"S State Road 7",
    "iso:country":"US",
    "sg:address":"313 S State Road 7",
    "sg:city":"Plantation",
    "sg:classifiers":[
        {
            "category":"Building & Trades",
            "subcategory":"Landscaping Services",
            "type":"Services"
        }
    ],
    "sg:phone":"+1 954 646 8004",
    "sg:postcode":"33317",
    "sg:province":"FL",
    "sg:tags":[
        "aged",
        "homes-institutional"
    ],
    "wof:name":"Broward Foster And Adoptive Parent Association",
    "wof:placetype":"venue"
},
  "geometry": {"coordinates":[-80.201932,26.117149],"type":"Point"}
}