{
  "type": "Feature",
  "properties": {
    "iso:country":"US",
    "sg:address":"8151 Ulmerton Rd",
    "sg:city":"Largo",
    "sg:classifiers":[
        {
            "category":"Health Services",
            "subcategory":"Health Practitioner",
            "type":"Services"
        }
    ],
    "sg:phone":"+1 727 539 6764",
    "sg:postcode":"33771",
    "sg:province":"FL",
    "sg:tags":[
        "therapist",
        "physical"
    ],
    "wof:name":"Star Care",
    "wof:placetype":"venue"
},
  "geometry": {"coordinates":[-82.75143199999999,27.89442],"type":"Point"}
}