{
  "type": "Feature",
  "properties": {
    "iso:country":"US",
    "sg:address":"6975 SW 99th Ave",
    "sg:city":"Miami",
    "sg:classifiers":[
        {
            "category":"Wholesale",
            "subcategory":"Medical Equipment & Supplies",
            "type":"Manufacturing & Wholesale Goods"
        }
    ],
    "sg:phone":"+1 305 279 9886",
    "sg:postcode":"33173",
    "sg:province":"FL",
    "sg:tags":[
        "specializing"
    ],
    "wof:name":"Moremen Enterprises Inc",
    "wof:placetype":"venue"
},
  "geometry": {"coordinates":[-80.354236,25.704872],"type":"Point"}
}