{
  "type": "Feature",
  "properties": {
    "addr:full":"10155 NW 24th St Fort Lauderdale FL 33322",
    "addr:housenumber":"10155",
    "addr:postcode":"33322",
    "addr:street":"Nw 24Th St",
    "iso:country":"US",
    "sg:address":"10155 NW 24th St",
    "sg:city":"Fort Lauderdale",
    "sg:classifiers":[
        {
            "category":"Manufacturing",
            "subcategory":"Retail Goods",
            "type":"Manufacturing & Wholesale Goods"
        }
    ],
    "sg:phone":"+1 954 748 9351",
    "sg:postcode":"33322",
    "sg:province":"FL",
    "sg:tags":[
        "product",
        "mfg"
    ],
    "wof:name":"Pyrotech of South Florida",
    "wof:placetype":"venue"
},
  "geometry": {"coordinates":[-80.28649799999999,26.153643],"type":"Point"}
}