{
  "type": "Feature",
  "properties": {
    "iso:country":"US",
    "sg:address":"94 Eastern Lake Rd",
    "sg:city":"Santa Rosa Beach",
    "sg:classifiers":[
        {
            "category":"Building & Trades",
            "subcategory":"Construction",
            "type":"Services"
        }
    ],
    "sg:phone":"+1 850 231 3073",
    "sg:postcode":"32459",
    "sg:province":"FL",
    "sg:tags":[
        "contractor"
    ],
    "wof:name":"Chase Building Group",
    "wof:placetype":"venue"
},
  "geometry": {"coordinates":[-86.102817,30.309535],"type":"Point"}
}