{
  "type": "Feature",
  "properties": {
    "iso:country":"US",
    "sg:address":"695 W Stuart St",
    "sg:city":"Bartow",
    "sg:classifiers":[
        {
            "category":"Organizations",
            "subcategory":"Religious Organization",
            "type":"Services"
        }
    ],
    "sg:phone":"+1 863 533 5433",
    "sg:postcode":"33830",
    "sg:province":"FL",
    "wof:name":"McLeod Memorial Presbt Church",
    "wof:placetype":"venue"
},
  "geometry": {"coordinates":[-81.84853,27.88586],"type":"Point"}
}