{
  "type": "Feature",
  "properties": {
    "iso:country":"US",
    "sg:address":"673 Beville Rd",
    "sg:city":"South Daytona",
    "sg:classifiers":[
        {
            "category":"Health Services",
            "subcategory":"Doctor",
            "type":"Services"
        }
    ],
    "sg:phone":"+1 386 760 8116",
    "sg:postcode":"32119",
    "sg:province":"FL",
    "sg:tags":[
        "physician",
        "surgeon"
    ],
    "wof:name":"Rizalina Leuterio MD",
    "wof:placetype":"venue"
},
  "geometry": {"coordinates":[-81.017197,29.179905],"type":"Point"}
}