{
  "type": "Feature",
  "properties": {
    "iso:country":"US",
    "sg:address":"619 Reddick St",
    "sg:city":"Eustis",
    "sg:classifiers":[
        {
            "category":"Building & Trades",
            "subcategory":"Construction",
            "type":"Services"
        }
    ],
    "sg:phone":"+1 352 357 9133",
    "sg:postcode":"32726",
    "sg:province":"FL",
    "sg:tags":[
        "carpentry",
        "contractor"
    ],
    "wof:name":"Harris Manuel Carpentry",
    "wof:placetype":"venue"
},
  "geometry": {"coordinates":[-81.67382000000001,28.859801],"type":"Point"}
}