{
  "type": "Feature",
  "properties": {
    "addr:full":"3665 E Bay Dr Largo FL 33771",
    "addr:housenumber":"3665",
    "addr:postcode":"33771",
    "addr:street":"E Bay Dr",
    "iso:country":"US",
    "sg:address":"3665 E Bay Dr",
    "sg:city":"Largo",
    "sg:classifiers":[
        {
            "category":"Cinema",
            "subcategory":"Movie Rental",
            "type":"Entertainment"
        }
    ],
    "sg:phone":"+1 727 524 6415",
    "sg:postcode":"33771",
    "sg:province":"FL",
    "sg:tags":[
        "leasing",
        "video",
        "disc",
        "tape"
    ],
    "wof:name":"Hollywood Video",
    "wof:placetype":"venue"
},
  "geometry": {"coordinates":[-82.743785,27.916403],"type":"Point"}
}