{
  "type": "Feature",
  "properties": {
    "iso:country":"US",
    "sg:address":"5500 N W St",
    "sg:city":"Pensacola",
    "sg:phone":"+1 850 437 9649",
    "sg:postcode":"32505",
    "sg:province":"FL",
    "wof:name":"First Choice Automotive",
    "wof:placetype":"venue"
},
  "geometry": {"coordinates":[-87.25296,30.4659],"type":"Point"}
}