{
  "type": "Feature",
  "properties": {
    "iso:country":"US",
    "sg:address":"212 Caddy Rd",
    "sg:city":"Port Charlotte",
    "sg:classifiers":[
        {
            "category":"Building & Trades",
            "subcategory":"Landscaping Services",
            "type":"Services"
        }
    ],
    "sg:phone":"+1 941 697 4339",
    "sg:postcode":"33947",
    "sg:province":"FL",
    "wof:name":"Shawn Bridges Affordable Lawn",
    "wof:placetype":"venue"
},
  "geometry": {"coordinates":[-82.286703,26.890264],"type":"Point"}
}