{
  "type": "Feature",
  "properties": {
    "iso:country":"US",
    "sg:address":"1938 State Rd 44",
    "sg:city":"New Smyrna Beach",
    "sg:classifiers":[
        {
            "category":"Cinema",
            "subcategory":"Movie Rental",
            "type":"Entertainment"
        }
    ],
    "sg:phone":"+1 386 427 2131",
    "sg:postcode":"32168",
    "sg:province":"FL",
    "sg:tags":[
        "leasing",
        "video",
        "disc",
        "tape"
    ],
    "wof:name":"Blockbuster Video",
    "wof:placetype":"venue"
},
  "geometry": {"coordinates":[-80.94424600000001,29.013894],"type":"Point"}
}