{
  "type": "Feature",
  "properties": {
    "iso:country":"US",
    "sg:address":"8462 Dynasty Dr",
    "sg:city":"Boca Raton",
    "sg:classifiers":[
        {
            "category":"Building & Trades",
            "subcategory":"Construction",
            "type":"Services"
        }
    ],
    "sg:phone":"+1 561 945 3119",
    "sg:postcode":"33433",
    "sg:province":"FL",
    "sg:tags":[
        "wall",
        "finish",
        "artist"
    ],
    "wof:name":"Wall Design Faux Finish Inc",
    "wof:placetype":"venue"
},
  "geometry": {"coordinates":[-80.17744399999999,26.333615],"type":"Point"}
}