{
  "type": "Feature",
  "properties": {
    "iso:country":"US",
    "sg:address":"3945 SW 92nd Ave",
    "sg:city":"Miami",
    "sg:classifiers":[
        {
            "category":"Professional",
            "type":"Services"
        }
    ],
    "sg:phone":"+1 305 220 0066",
    "sg:postcode":"33165",
    "sg:province":"FL",
    "sg:tags":[
        "dentist"
    ],
    "wof:name":"Jadent",
    "wof:placetype":"venue"
},
  "geometry": {"coordinates":[-80.34357199999999,25.733457],"type":"Point"}
}