{
  "type": "Feature",
  "properties": {
    "addr:full":"423 Sheoah Blvd Winter Springs FL 32708",
    "addr:housenumber":"423",
    "addr:postcode":"32708",
    "addr:street":"Sheoah Blvd",
    "iso:country":"US",
    "sg:address":"423 Sheoah Blvd",
    "sg:city":"Winter Springs",
    "sg:classifiers":[
        {
            "category":"Banks & Credit Unions",
            "subcategory":"Financial Services",
            "type":"Services"
        }
    ],
    "sg:phone":"+1 407 327 1840",
    "sg:postcode":"32708",
    "sg:province":"FL",
    "sg:tags":[
        "trust",
        "management"
    ],
    "wof:name":"Minana Family Trust",
    "wof:placetype":"venue"
},
  "geometry": {"coordinates":[-81.314688,28.708806],"type":"Point"}
}