{
  "type": "Feature",
  "properties": {
    "iso:country":"US",
    "sg:address":"1014 Bay Colony Dr S",
    "sg:city":"Juno Beach",
    "sg:classifiers":[
        {
            "category":"Real Estate",
            "subcategory":"Developer",
            "type":"Services"
        }
    ],
    "sg:phone":"+1 561 625 3511",
    "sg:postcode":"33408",
    "sg:province":"FL",
    "wof:name":"H Bc",
    "wof:placetype":"venue"
},
  "geometry": {"coordinates":[-80.06379699999999,26.860309],"type":"Point"}
}