{
  "type": "Feature",
  "properties": {
    "addr:full":"14268 Walsingham Rd Largo FL 33774",
    "addr:housenumber":"14268",
    "addr:postcode":"33774",
    "addr:street":"Walsingham Rd",
    "iso:country":"US",
    "sg:address":"14268 Walsingham Rd",
    "sg:city":"Largo",
    "sg:classifiers":[
        {
            "category":"Organizations",
            "subcategory":"Community Association",
            "type":"Services"
        }
    ],
    "sg:phone":"+1 727 596 8959",
    "sg:postcode":"33774",
    "sg:province":"FL",
    "sg:tags":[
        "military"
    ],
    "wof:name":"VFW Post Of Indian Rocks",
    "wof:placetype":"venue"
},
  "geometry": {"coordinates":[-82.83286699999999,27.880342],"type":"Point"}
}