{
  "type": "Feature",
  "properties": {
    "iso:country":"US",
    "sg:address":"167 Poinciana Rd",
    "sg:city":"Edgewater",
    "sg:classifiers":[
        {
            "category":"Building & Trades",
            "subcategory":"Electrical",
            "type":"Services"
        }
    ],
    "sg:phone":"+1 386 427 6092",
    "sg:postcode":"32141",
    "sg:province":"FL",
    "sg:tags":[
        "electrician"
    ],
    "wof:name":"Twt Electric",
    "wof:placetype":"venue"
},
  "geometry": {"coordinates":[-80.873526,28.932349],"type":"Point"}
}