{
  "type": "Feature",
  "properties": {
    "addr:full":"33 Almond Drive Trl Ocala FL 34472",
    "addr:housenumber":"33",
    "addr:postcode":"34472",
    "addr:street":"Almond Drive Trl",
    "iso:country":"US",
    "sg:address":"33 Almond Drive Trl",
    "sg:city":"Ocala",
    "sg:classifiers":[
        {
            "category":"Retail",
            "subcategory":"Repair Shop",
            "type":"Services"
        }
    ],
    "sg:phone":"+1 352 624 0235",
    "sg:postcode":"34472",
    "sg:province":"FL",
    "sg:tags":[
        "electrical"
    ],
    "wof:name":"Terrance L Sapp Service",
    "wof:placetype":"venue"
},
  "geometry": {"coordinates":[-82.048733,29.152986],"type":"Point"}
}