{
  "type": "Feature",
  "properties": {
    "iso:country":"US",
    "sg:address":"1550 Cassat Ave",
    "sg:city":"Jacksonville",
    "sg:classifiers":[
        {
            "category":"Autos & Motor Vehicles",
            "subcategory":"Automobile Sales",
            "type":"Retail Goods"
        }
    ],
    "sg:phone":"+1 904 387 4041",
    "sg:postcode":"32210",
    "sg:province":"FL",
    "sg:tags":[
        "car",
        "dealer"
    ],
    "sg:website":"www.nimnichtchevy.com",
    "wof:name":"Nimnicht Chevrolet Co",
    "wof:placetype":"venue"
},
  "geometry": {"coordinates":[-81.73047,30.291293],"type":"Point"}
}