{
  "type": "Feature",
  "properties": {
    "addr:full":"6706 S Gabrielle St Tampa FL 33611",
    "addr:housenumber":"6706",
    "addr:postcode":"33611",
    "addr:street":"S Gabrielle St",
    "iso:country":"US",
    "sg:address":"6706 S Gabrielle St",
    "sg:city":"Tampa",
    "sg:classifiers":[
        {
            "category":"Utilities",
            "subcategory":"Telephone",
            "type":"Services"
        }
    ],
    "sg:phone":"+1 813 902 1405",
    "sg:postcode":"33611",
    "sg:province":"FL",
    "sg:tags":[
        "communications"
    ],
    "wof:name":"Search Eng Optmztion Advantage",
    "wof:placetype":"venue"
},
  "geometry": {"coordinates":[-82.496793,27.869957],"type":"Point"}
}