{
  "type": "Feature",
  "properties": {
    "iso:country":"US",
    "sg:address":"12757 del Rio Dr",
    "sg:city":"Jacksonville",
    "sg:classifiers":[
        {
            "category":"Wholesale",
            "subcategory":"Non-durable Goods",
            "type":"Manufacturing & Wholesale Goods"
        }
    ],
    "sg:phone":"+1 904 268 8241",
    "sg:postcode":"32258",
    "sg:province":"FL",
    "wof:name":"Islands Imports",
    "wof:placetype":"venue"
},
  "geometry": {"coordinates":[-81.57986,30.140016],"type":"Point"}
}