{
  "type": "Feature",
  "properties": {
    "iso:country":"US",
    "sg:address":"50 SW 10th St",
    "sg:city":"Miami",
    "sg:classifiers":[
        {
            "category":"Communications",
            "subcategory":"Film & Video Production",
            "type":"Services"
        }
    ],
    "sg:phone":"+1 305 416 0518",
    "sg:postcode":"33130",
    "sg:province":"FL",
    "sg:tags":[
        "motion"
    ],
    "wof:name":"Gala Events & Productions",
    "wof:placetype":"venue"
},
  "geometry": {"coordinates":[-80.194332,25.76438],"type":"Point"}
}