{
  "type": "Feature",
  "properties": {
    "addr:full":"13499 S Cleveland Ave Ste 143 Fort Myers FL 33907",
    "addr:housenumber":"13499",
    "addr:postcode":"myers;33907",
    "addr:street":"S Cleveland Ave Ste 143",
    "iso:country":"US",
    "sg:address":"13499 S Cleveland Ave Ste 143",
    "sg:city":"Fort Myers",
    "sg:classifiers":[
        {
            "category":"Restaurant",
            "type":"Food & Drink"
        }
    ],
    "sg:phone":"+1 239 466 4141",
    "sg:postcode":"33907",
    "sg:province":"FL",
    "sg:website":"www.bistro41.com",
    "wof:name":"Bistro 41",
    "wof:placetype":"venue"
},
  "geometry": {"coordinates":[-81.86826000000001,26.564556],"type":"Point"}
}