{
  "type": "Feature",
  "properties": {
    "addr:full":"275 Key Deer Blvd Big Pine Key FL 33043",
    "addr:housenumber":"275",
    "addr:postcode":"33043",
    "addr:street":"Key Deer Blvd",
    "iso:country":"US",
    "sg:address":"275 Key Deer Blvd",
    "sg:city":"Big Pine Key",
    "sg:classifiers":[
        {
            "category":"Restaurant",
            "type":"Food & Drink"
        }
    ],
    "sg:phone":"+1 305 872 2464",
    "sg:postcode":"33043",
    "sg:province":"FL",
    "sg:tags":[
        "eating"
    ],
    "wof:name":"Tropical Freeze",
    "wof:placetype":"venue"
},
  "geometry": {"coordinates":[-81.358531,24.673464],"type":"Point"}
}