{
  "type": "Feature",
  "properties": {
    "iso:country":"US",
    "sg:address":"4308 Miller Ave",
    "sg:city":"West Palm Beach",
    "sg:classifiers":[
        {
            "category":"Manufacturing",
            "subcategory":"Building Materials",
            "type":"Manufacturing & Wholesale Goods"
        },
        {
            "category":"Home & Garden",
            "subcategory":"Furniture",
            "type":"Retail Goods"
        }
    ],
    "sg:phone":"+1 561 833 8001",
    "sg:postcode":"33405",
    "sg:province":"FL",
    "sg:tags":[
        "equipment",
        "cabinet",
        "kitchen",
        "mfg"
    ],
    "wof:name":"Artistic Doors Inc",
    "wof:placetype":"venue"
},
  "geometry": {"coordinates":[-80.057695,26.673126],"type":"Point"}
}