{
  "type": "Feature",
  "properties": {
    "addr:full":"736 del Prado Dr Kissimmee FL 34758",
    "addr:housenumber":"736",
    "addr:postcode":"34758",
    "addr:street":"Del Prado Dr",
    "iso:country":"US",
    "sg:address":"736 del Prado Dr",
    "sg:city":"Kissimmee",
    "sg:classifiers":[
        {
            "category":"Building & Trades",
            "subcategory":"Construction",
            "type":"Services"
        }
    ],
    "sg:phone":"+1 407 518 0565",
    "sg:postcode":"34758",
    "sg:province":"FL",
    "sg:tags":[
        "carpentry",
        "contractor"
    ],
    "wof:name":"Anil Inc",
    "wof:placetype":"venue"
},
  "geometry": {"coordinates":[-81.467585,28.167244],"type":"Point"}
}