{
  "type": "Feature",
  "properties": {
    "addr:full":"13355 SW 40th St Miami FL 33175",
    "addr:housenumber":"13355",
    "addr:postcode":"33175",
    "addr:street":"Sw 40Th St",
    "iso:country":"US",
    "sg:address":"13355 SW 40th St",
    "sg:city":"Miami",
    "sg:classifiers":[
        {
            "category":"Professional",
            "type":"Services"
        }
    ],
    "sg:phone":"+1 305 441 0744",
    "sg:postcode":"33175",
    "sg:province":"FL",
    "wof:name":"FJ&m Finishing Co",
    "wof:placetype":"venue"
},
  "geometry": {"coordinates":[-80.41165599999999,25.731252],"type":"Point"}
}