{
  "type": "Feature",
  "properties": {
    "addr:full":"600 W Blue Heron Blvd Riviera Beach FL 33404",
    "addr:housenumber":"600",
    "addr:postcode":"33404",
    "addr:street":"W Blue Heron Blvd",
    "iso:country":"US",
    "sg:address":"600 W Blue Heron Blvd",
    "sg:city":"Riviera Beach",
    "sg:classifiers":[
        {
            "category":"Government",
            "subcategory":"Office",
            "type":"Public Place"
        }
    ],
    "sg:phone":"+1 561 845 4095",
    "sg:postcode":"33404",
    "sg:province":"FL",
    "sg:tags":[
        "village"
    ],
    "wof:name":"City Council",
    "wof:placetype":"venue"
},
  "geometry": {"coordinates":[-80.066844,26.782252],"type":"Point"}
}