{
  "type": "Feature",
  "properties": {
    "iso:country":"US",
    "sg:address":"1170 Northbrook Dr",
    "sg:city":"Pensacola",
    "sg:classifiers":[
        {
            "category":"Health Services",
            "subcategory":"Dentist",
            "type":"Services"
        }
    ],
    "sg:phone":"+1 850 471 1619",
    "sg:postcode":"32504",
    "sg:province":"FL",
    "wof:name":"Kilpatrick Steven",
    "wof:placetype":"venue"
},
  "geometry": {"coordinates":[-87.193038,30.5007],"type":"Point"}
}