{
  "type": "Feature",
  "properties": {
    "iso:country":"US",
    "sg:address":"11 Tupelo Ave SE",
    "sg:city":"Fort Walton Bch",
    "sg:classifiers":[
        {
            "category":"Professional",
            "subcategory":"Engineering",
            "type":"Services"
        },
        {
            "category":"Utilities",
            "type":"Services"
        }
    ],
    "sg:phone":"+1 850 243 0033",
    "sg:postcode":"32548",
    "sg:province":"FL",
    "sg:tags":[
        "environmental",
        "cleanup",
        "engineer"
    ],
    "wof:name":"Waste Energy Technology",
    "wof:placetype":"venue"
},
  "geometry": {"coordinates":[-86.605304,30.411393],"type":"Point"}
}