{
  "type": "Feature",
  "properties": {
    "iso:country":"US",
    "sg:address":"625 Lovejoy Rd NW",
    "sg:city":"Fort Walton Bch",
    "sg:classifiers":[
        {
            "category":"Social Services",
            "subcategory":"Job Training",
            "type":"Services"
        },
        {
            "category":"Social Services",
            "type":"Services"
        }
    ],
    "sg:phone":"+1 850 862 6340",
    "sg:postcode":"32548",
    "sg:province":"FL",
    "sg:tags":[
        "retardation",
        "disabled",
        "mental",
        "dev"
    ],
    "wof:name":"Resources For Human Developmnt",
    "wof:placetype":"venue"
},
  "geometry": {"coordinates":[-86.661188,30.424424],"type":"Point"}
}