{
  "type": "Feature",
  "properties": {
    "addr:full":"12795 W Forest Hill Blvd Wellington FL 33414",
    "addr:housenumber":"12795",
    "addr:postcode":"33414",
    "addr:street":"W Forest Hill Blvd",
    "iso:country":"US",
    "sg:address":"12795 W Forest Hill Blvd",
    "sg:city":"Wellington",
    "sg:classifiers":[
        {
            "category":"Restaurant",
            "type":"Food & Drink"
        }
    ],
    "sg:phone":"+1 561 629 7956",
    "sg:postcode":"33414",
    "sg:province":"FL",
    "sg:tags":[
        "house",
        "steak"
    ],
    "wof:name":"Beef Wellington Steakhouse",
    "wof:placetype":"venue"
},
  "geometry": {"coordinates":[-80.24782399999999,26.673018],"type":"Point"}
}