{
  "type": "Feature",
  "properties": {
    "iso:country":"US",
    "sg:address":"3440 NW 73rd Ave",
    "sg:city":"Miami",
    "sg:classifiers":[
        {
            "category":"Wholesale",
            "subcategory":"Plants",
            "type":"Manufacturing & Wholesale Goods"
        },
        {
            "category":"Shopping",
            "subcategory":"Crafts & Fabrics",
            "type":"Retail Goods"
        },
        {
            "category":"Shopping",
            "subcategory":"Florist",
            "type":"Retail Goods"
        }
    ],
    "sg:phone":"+1 305 418 3187",
    "sg:postcode":"33122",
    "sg:province":"FL",
    "sg:tags":[
        "supplies-wholesale",
        "florists-wholesale",
        "florists'",
        "manufacturer",
        "supply"
    ],
    "wof:name":"Glad USA Corp",
    "wof:placetype":"venue"
},
  "geometry": {"coordinates":[-80.31577,25.80567],"type":"Point"}
}