{
  "type": "Feature",
  "properties": {
    "iso:country":"US",
    "sg:address":"30945 Ave A",
    "sg:city":"Big Pine Key",
    "sg:classifiers":[
        {
            "category":"Marine",
            "type":"Transportation"
        }
    ],
    "sg:phone":"+1 305 872 9447",
    "sg:postcode":"33043",
    "sg:province":"FL",
    "sg:tags":[
        "water",
        "transport"
    ],
    "wof:name":"Fish Lower Keys",
    "wof:placetype":"venue"
},
  "geometry": {"coordinates":[-81.34948900000001,24.66977],"type":"Point"}
}