{
  "type": "Feature",
  "properties": {
    "iso:country":"US",
    "sg:address":"2701 Ponce de Leon Blvd",
    "sg:city":"Coral Gables",
    "sg:classifiers":[
        {
            "category":"Professional",
            "subcategory":"Lawyer & Legal Services",
            "type":"Services"
        }
    ],
    "sg:phone":"+1 305 774 9828",
    "sg:postcode":"33134",
    "sg:province":"FL",
    "sg:tags":[
        "attorney"
    ],
    "wof:name":"Gamba & Lombana PA",
    "wof:placetype":"venue"
},
  "geometry": {"coordinates":[-80.25853600000001,25.746699],"type":"Point"}
}