{
  "type": "Feature",
  "properties": {
    "addr:full":"5829 Frontier Ln Orlando FL 32839",
    "addr:housenumber":"5829",
    "addr:postcode":"32839",
    "addr:street":"Frontier Ln",
    "iso:country":"US",
    "sg:address":"5829 Frontier Ln",
    "sg:city":"Orlando",
    "sg:classifiers":[
        {
            "category":"Building & Trades",
            "subcategory":"Construction",
            "type":"Services"
        }
    ],
    "sg:phone":"+1 321 636 7945",
    "sg:postcode":"32839",
    "sg:province":"FL",
    "sg:tags":[
        "residential"
    ],
    "wof:name":"Timothy T Tanner",
    "wof:placetype":"venue"
},
  "geometry": {"coordinates":[-81.390822,28.473506],"type":"Point"}
}