{
  "type": "Feature",
  "properties": {
    "iso:country":"US",
    "sg:address":"8810 NW 24th Ter",
    "sg:city":"Doral",
    "sg:classifiers":[
        {
            "category":"Shopping",
            "type":"Retail Goods"
        }
    ],
    "sg:phone":"+1 786 234 5200",
    "sg:postcode":"33172",
    "sg:province":"FL",
    "sg:tags":[
        "merchandise"
    ],
    "wof:name":"Js Supply And Service",
    "wof:placetype":"venue"
},
  "geometry": {"coordinates":[-80.33972199999999,25.79677],"type":"Point"}
}