{
  "type": "Feature",
  "properties": {
    "addr:full":"70 N Lee Ct Merritt Island FL 32952",
    "addr:housenumber":"70",
    "addr:postcode":"32952",
    "addr:street":"N Lee Ct",
    "iso:country":"US",
    "sg:address":"70 N Lee Ct",
    "sg:city":"Merritt Island",
    "sg:classifiers":[
        {
            "category":"Shopping",
            "subcategory":"Catalog Store",
            "type":"Retail Goods"
        }
    ],
    "sg:phone":"+1 321 452 9812",
    "sg:postcode":"32952",
    "sg:province":"FL",
    "sg:tags":[
        "mail",
        "order"
    ],
    "wof:name":"Leslie A Reyen 3 Mail Order",
    "wof:placetype":"venue"
},
  "geometry": {"coordinates":[-80.66704900000001,28.355687],"type":"Point"}
}