{
  "type": "Feature",
  "properties": {
    "iso:country":"US",
    "sg:address":"12823 Litewood Dr",
    "sg:city":"Hudson",
    "sg:classifiers":[
        {
            "category":"Building & Trades",
            "subcategory":"Cleaning & Sanitation",
            "type":"Services"
        }
    ],
    "sg:phone":"+1 727 861 7530",
    "sg:postcode":"34669",
    "sg:province":"FL",
    "sg:tags":[
        "janitor"
    ],
    "wof:name":"Absolute Rose Cleaning Svc",
    "wof:placetype":"venue"
},
  "geometry": {"coordinates":[-82.65226,28.342931],"type":"Point"}
}