{
  "type": "Feature",
  "properties": {
    "addr:full":"1000 SE Monterey Commons Blvd Stuart FL 34996",
    "addr:housenumber":"1000",
    "addr:postcode":"34996",
    "addr:street":"Se Monterey Commons Blvd",
    "iso:country":"US",
    "sg:address":"1000 SE Monterey Commons Blvd",
    "sg:city":"Stuart",
    "sg:classifiers":[
        {
            "category":"Insurance",
            "subcategory":"Insurance Agent",
            "type":"Services"
        }
    ],
    "sg:phone":"+1 772 781 5280",
    "sg:postcode":"34996",
    "sg:province":"FL",
    "sg:website":"www.evergreenre.com",
    "wof:name":"Evergreen Re Reinsurance Brkrs",
    "wof:placetype":"venue"
},
  "geometry": {"coordinates":[-80.223376,27.193321],"type":"Point"}
}