{
  "type": "Feature",
  "properties": {
    "iso:country":"US",
    "sg:address":"6886 N Kendall Dr",
    "sg:city":"Miami",
    "sg:classifiers":[
        {
            "category":"Building & Trades",
            "subcategory":"Construction",
            "type":"Services"
        }
    ],
    "sg:phone":"+1 786 514 6026",
    "sg:postcode":"33156",
    "sg:province":"FL",
    "sg:tags":[
        "painter"
    ],
    "wof:name":"Affordable Painting By Mayeno",
    "wof:placetype":"venue"
},
  "geometry": {"coordinates":[-80.30612499999999,25.68885],"type":"Point"}
}