{
  "type": "Feature",
  "properties": {
    "addr:full":"6604 Orchid Lake Rd New Port Richey FL 34653",
    "addr:housenumber":"6604",
    "addr:postcode":"34653",
    "addr:street":"Orchid Lake Rd",
    "iso:country":"US",
    "sg:address":"6604 Orchid Lake Rd",
    "sg:city":"New Port Richey",
    "sg:classifiers":[
        {
            "category":"Cinema",
            "subcategory":"Movie Rental",
            "type":"Entertainment"
        }
    ],
    "sg:phone":"+1 727 845 5592",
    "sg:postcode":"34653",
    "sg:province":"FL",
    "sg:tags":[
        "video",
        "tape"
    ],
    "wof:name":"Pussycat II",
    "wof:placetype":"venue"
},
  "geometry": {"coordinates":[-82.704722,28.272154],"type":"Point"}
}