{
  "type": "Feature",
  "properties": {
    "iso:country":"US",
    "sg:address":"23250 Via Villagio",
    "sg:city":"Estero",
    "sg:classifiers":[
        {
            "category":"Banks & Credit Unions",
            "subcategory":"Bank",
            "type":"Services"
        }
    ],
    "sg:phone":"+1 239 947 5874",
    "sg:postcode":"33928",
    "sg:province":"FL",
    "sg:tags":[
        "saving",
        "commercial"
    ],
    "wof:name":"Florida Gulf Bank",
    "wof:placetype":"venue"
},
  "geometry": {"coordinates":[-81.808907,26.399473],"type":"Point"}
}