{
  "type": "Feature",
  "properties": {
    "addr:full":"4995 NW 72nd Ave Miami FL 33166",
    "addr:housenumber":"4995",
    "addr:postcode":"33166",
    "addr:street":"Nw 72Nd Ave",
    "iso:country":"US",
    "sg:address":"4995 NW 72nd Ave",
    "sg:city":"Miami",
    "sg:classifiers":[
        {
            "category":"Banks & Credit Unions",
            "subcategory":"Investment Brokerage",
            "type":"Services"
        }
    ],
    "sg:phone":"+1 305 477 1222",
    "sg:postcode":"33166",
    "sg:province":"FL",
    "sg:tags":[
        "advisory",
        "financial"
    ],
    "wof:name":"First Financial Solutions",
    "wof:placetype":"venue"
},
  "geometry": {"coordinates":[-80.3135,25.817926],"type":"Point"}
}