{
  "type": "Feature",
  "properties": {
    "iso:country":"US",
    "sg:address":"202 W Main St",
    "sg:city":"Leesburg",
    "sg:classifiers":[
        {
            "category":"Shopping",
            "subcategory":"Used Merchandise",
            "type":"Retail Goods"
        }
    ],
    "sg:phone":"+1 352 787 9833",
    "sg:postcode":"34748",
    "sg:province":"FL",
    "sg:tags":[
        "shop",
        "consignment"
    ],
    "wof:name":"Consignments & Future Antiques",
    "wof:placetype":"venue"
},
  "geometry": {"coordinates":[-81.876555,28.811157],"type":"Point"}
}