{
  "type": "Feature",
  "properties": {
    "iso:country":"US",
    "sg:address":"404 Albee Rd W Apt C",
    "sg:city":"Nokomis",
    "sg:classifiers":[
        {
            "category":"Restaurant",
            "type":"Food & Drink"
        }
    ],
    "sg:phone":"+1 941 485 8000",
    "sg:postcode":"34275",
    "sg:province":"FL",
    "sg:tags":[
        "style",
        "family"
    ],
    "wof:name":"Country Oven Family Dining",
    "wof:placetype":"venue"
},
  "geometry": {"coordinates":[-82.45822099999999,27.12483],"type":"Point"}
}