{
  "type": "Feature",
  "properties": {
    "addr:full":"14219 Walsingham Rd Largo FL 33774",
    "addr:housenumber":"14219",
    "addr:postcode":"33774",
    "addr:street":"Walsingham Rd",
    "iso:country":"US",
    "sg:address":"14219 Walsingham Rd",
    "sg:city":"Largo",
    "sg:classifiers":[
        {
            "category":"Personal",
            "type":"Services"
        }
    ],
    "sg:phone":"+1 727 517 1755",
    "sg:postcode":"33774",
    "sg:province":"FL",
    "sg:tags":[
        "therapist",
        "massage"
    ],
    "wof:name":"Beach & Bay Massage Ctr",
    "wof:placetype":"venue"
},
  "geometry": {"coordinates":[-82.833654,27.880484],"type":"Point"}
}