{
  "type": "Feature",
  "properties": {
    "iso:country":"US",
    "sg:address":"983 Coconut Cir E",
    "sg:city":"Naples",
    "sg:classifiers":[
        {
            "category":"Real Estate",
            "subcategory":"Real Estate Agent",
            "type":"Services"
        }
    ],
    "sg:phone":"+1 239 272 0063",
    "sg:postcode":"34104",
    "sg:province":"FL",
    "wof:name":"No Reason Inc",
    "wof:placetype":"venue"
},
  "geometry": {"coordinates":[-81.758218,26.145102],"type":"Point"}
}