{
  "type": "Feature",
  "properties": {
    "addr:full":"775 SE 128th Ave Silver Springs FL 34488",
    "addr:housenumber":"775",
    "addr:postcode":"34488",
    "addr:street":"Se 128Th Ave",
    "iso:country":"US",
    "sg:address":"775 SE 128th Ave",
    "sg:city":"Silver Springs",
    "sg:classifiers":[
        {
            "category":"Professional",
            "subcategory":"Business Services",
            "type":"Services"
        }
    ],
    "sg:phone":"+1 352 625 0035",
    "sg:postcode":"34488",
    "sg:province":"FL",
    "sg:tags":[
        "pool",
        "swimming"
    ],
    "wof:name":"Deep End Pool Svc",
    "wof:placetype":"venue"
},
  "geometry": {"coordinates":[-81.9423,29.179574],"type":"Point"}
}