{
  "type": "Feature",
  "properties": {
    "iso:country":"US",
    "sg:address":"3075 NW 97th St",
    "sg:city":"Miami",
    "sg:classifiers":[
        {
            "category":"Professional",
            "type":"Services"
        }
    ],
    "sg:phone":"+1 305 836 0016",
    "sg:postcode":"33147",
    "sg:province":"FL",
    "wof:name":"Netervision Inc",
    "wof:placetype":"venue"
},
  "geometry": {"coordinates":[-80.248059,25.862862],"type":"Point"}
}