{
  "type": "Feature",
  "properties": {
    "addr:full":"1210 NE 1st Ave Miami FL 33132",
    "addr:housenumber":"1210",
    "addr:postcode":"33132",
    "addr:street":"Ne 1St Ave",
    "iso:country":"US",
    "sg:address":"1210 NE 1st Ave",
    "sg:city":"Miami",
    "sg:classifiers":[
        {
            "category":"Health Services",
            "subcategory":"Clinic",
            "type":"Services"
        }
    ],
    "sg:phone":"+1 305 530 3597",
    "sg:postcode":"33132",
    "sg:province":"FL",
    "wof:name":"DOS Health Care",
    "wof:placetype":"venue"
},
  "geometry": {"coordinates":[-80.192294,25.786849],"type":"Point"}
}