{
  "type": "Feature",
  "properties": {
    "iso:country":"US",
    "sg:address":"1376 Prince St",
    "sg:city":"Jacksonville",
    "sg:classifiers":[
        {
            "category":"Shopping",
            "subcategory":"Clothing, Apparel, & Fashions",
            "type":"Retail Goods"
        }
    ],
    "sg:phone":"+1 904 358 0481",
    "sg:postcode":"32209",
    "sg:province":"FL",
    "wof:name":"Jay's Fashion",
    "wof:placetype":"venue"
},
  "geometry": {"coordinates":[-81.677666,30.340742],"type":"Point"}
}