{
  "type": "Feature",
  "properties": {
    "iso:country":"US",
    "sg:address":"4250 SW 73rd Ave",
    "sg:city":"Miami",
    "sg:phone":"+1 305 266 5686",
    "sg:postcode":"33155",
    "sg:province":"FL",
    "wof:name":"Global Green Savings",
    "wof:placetype":"venue"
},
  "geometry": {"coordinates":[-80.313199,25.730811],"type":"Point"}
}