{
  "type": "Feature",
  "properties": {
    "addr:full":"210 11th St NW Naples FL 34120",
    "addr:housenumber":"210",
    "addr:postcode":"34120",
    "addr:street":"11Th St Nw",
    "iso:country":"US",
    "sg:address":"210 11th St NW",
    "sg:city":"Naples",
    "sg:phone":"+1 239 353 8209",
    "sg:postcode":"34120",
    "sg:province":"FL",
    "sg:tags":[
        "irrigation",
        "system"
    ],
    "wof:name":"Water Works Irrgtn Lndscpng",
    "wof:placetype":"venue"
},
  "geometry": {"coordinates":[-81.629051,26.242985],"type":"Point"}
}