{
  "type": "Feature",
  "properties": {
    "addr:full":"13600 State Hwy 84 Fort Lauderdale FL 33325",
    "addr:housenumber":"13600",
    "addr:postcode":"33325",
    "addr:street":"State Hwy 84",
    "iso:country":"US",
    "sg:address":"13600 State Hwy 84",
    "sg:city":"Fort Lauderdale",
    "sg:classifiers":[
        {
            "category":"Retail",
            "subcategory":"Veterinary Services",
            "type":"Services"
        }
    ],
    "sg:phone":"+1 954 370 7245",
    "sg:postcode":"33325",
    "sg:province":"FL",
    "wof:name":"Shenandoah Animal Hospital",
    "wof:placetype":"venue"
},
  "geometry": {"coordinates":[-80.322321,26.116939],"type":"Point"}
}