{
  "type": "Feature",
  "properties": {
    "iso:country":"US",
    "sg:address":"3309 Ponce de Leon Blvd",
    "sg:city":"Miami",
    "sg:classifiers":[
        {
            "category":"Manufacturing",
            "subcategory":"Chemicals & Compounds",
            "type":"Manufacturing & Wholesale Goods"
        }
    ],
    "sg:phone":"+1 305 444 0705",
    "sg:postcode":"33134",
    "sg:province":"FL",
    "sg:tags":[
        "preparation",
        "pharmaceutical",
        "mfg"
    ],
    "wof:name":"American Drug Express",
    "wof:placetype":"venue"
},
  "geometry": {"coordinates":[-80.258343,25.740548],"type":"Point"}
}