{
  "type": "Feature",
  "properties": {
    "addr:full":"44 Greenbrier St Marco Island FL 34145",
    "addr:housenumber":"44",
    "addr:postcode":"34145",
    "addr:street":"Greenbrier St",
    "iso:country":"US",
    "sg:address":"44 Greenbrier St",
    "sg:city":"Marco Island",
    "sg:classifiers":[
        {
            "category":"Real Estate",
            "subcategory":"Real Estate Operator",
            "type":"Services"
        }
    ],
    "sg:phone":"+1 239 394 1528",
    "sg:postcode":"34145",
    "sg:province":"FL",
    "sg:tags":[
        "condominium"
    ],
    "wof:name":"Mariner Apartments-Marco",
    "wof:placetype":"venue"
},
  "geometry": {"coordinates":[-81.730642,25.9381],"type":"Point"}
}