{
  "type": "Feature",
  "properties": {
    "addr:full":"6101 Garden City Rd Crestview FL 32539",
    "addr:housenumber":"6101",
    "addr:postcode":"32539",
    "addr:street":"Garden City Rd",
    "iso:country":"US",
    "sg:address":"6101 Garden City Rd",
    "sg:city":"Crestview",
    "sg:classifiers":[
        {
            "category":"Real Estate",
            "subcategory":"Real Estate Services",
            "type":"Services"
        },
        {
            "category":"Retail",
            "subcategory":"Laundry & Dry Cleaning",
            "type":"Services"
        },
        {
            "category":"Professional",
            "subcategory":"Business Services",
            "type":"Services"
        },
        {
            "category":"Building & Trades",
            "subcategory":"Cleaning & Sanitation",
            "type":"Services"
        },
        {
            "category":"Government",
            "subcategory":"Fire Station",
            "type":"Public Place"
        }
    ],
    "sg:phone":"+1 850 682 5326",
    "sg:postcode":"32539",
    "sg:province":"FL",
    "sg:tags":[
        "cleaner",
        "disaster",
        "recovery",
        "damage",
        "rug",
        "water",
        "restoration",
        "relief",
        "maintenance",
        "cleaners-interior",
        "inspection",
        "carpet"
    ],
    "sg:website":"http://www.andersonsclean.com",
    "wof:name":"Andersons Cleaning & Restoration",
    "wof:placetype":"venue"
},
  "geometry": {"coordinates":[-86.500938,30.816601],"type":"Point"}
}