{
  "type": "Feature",
  "properties": {
    "addr:full":"2908 N Pine Hills Rd Orlando FL 32808",
    "addr:housenumber":"2908",
    "addr:postcode":"32808",
    "addr:street":"N Pine Hills Rd",
    "iso:country":"US",
    "sg:address":"2908 N Pine Hills Rd",
    "sg:city":"Orlando",
    "sg:classifiers":[
        {
            "category":"Food & Beverages",
            "subcategory":"Groceries & Convenience Stores",
            "type":"Retail Goods"
        }
    ],
    "sg:phone":"+1 407 298 1466",
    "sg:postcode":"32808",
    "sg:province":"FL",
    "wof:name":"KWIK Stop",
    "wof:placetype":"venue"
},
  "geometry": {"coordinates":[-81.451651,28.581517],"type":"Point"}
}