{
  "type": "Feature",
  "properties": {
    "iso:country":"US",
    "sg:address":"8801 NW 72nd St",
    "sg:city":"Pompano Beach",
    "sg:classifiers":[
        {
            "category":"Building & Trades",
            "subcategory":"Construction",
            "type":"Services"
        }
    ],
    "sg:phone":"+1 954 753 2624",
    "sg:postcode":"33067",
    "sg:province":"FL",
    "sg:tags":[
        "clearing",
        "land",
        "contractor"
    ],
    "wof:name":"Dozer Loader Service",
    "wof:placetype":"venue"
},
  "geometry": {"coordinates":[-80.25096499999999,26.327285],"type":"Point"}
}