{
  "type": "Feature",
  "properties": {
    "iso:country":"US",
    "sg:address":"113 49th St S",
    "sg:city":"St Petersburg",
    "sg:classifiers":[
        {
            "category":"Shopping",
            "subcategory":"Used Merchandise",
            "type":"Retail Goods"
        }
    ],
    "sg:phone":"+1 727 321 9882",
    "sg:postcode":"33707",
    "sg:province":"FL",
    "sg:tags":[
        "shop",
        "consignment"
    ],
    "wof:name":"Punky's Playhouse",
    "wof:placetype":"venue"
},
  "geometry": {"coordinates":[-82.699928,27.769249],"type":"Point"}
}