{
  "type": "Feature",
  "properties": {
    "iso:country":"US",
    "sg:address":"10548 Goose Prairie Rd",
    "sg:city":"Leesburg",
    "sg:classifiers":[
        {
            "category":"Retail",
            "subcategory":"Auto Repair",
            "type":"Services"
        }
    ],
    "sg:phone":"+1 352 728 2832",
    "sg:postcode":"34788",
    "sg:province":"FL",
    "sg:tags":[
        "automotive",
        "used",
        "parts"
    ],
    "wof:name":"Fosters Garage & Auto Salvage",
    "wof:placetype":"venue"
},
  "geometry": {"coordinates":[-81.78157400000001,28.884519],"type":"Point"}
}