{
  "type": "Feature",
  "properties": {
    "iso:country":"US",
    "sg:address":"751 Lyons Rd",
    "sg:city":"Coconut Creek",
    "sg:classifiers":[
        {
            "category":"Recreation",
            "type":"Entertainment"
        }
    ],
    "sg:phone":"+1 954 978 0590",
    "sg:postcode":"33063",
    "sg:province":"FL",
    "sg:tags":[
        "psychic",
        "medium"
    ],
    "wof:name":"Colleen Zeller Psychic",
    "wof:placetype":"venue"
},
  "geometry": {"coordinates":[-80.18625299999999,26.232871],"type":"Point"}
}