{
  "type": "Feature",
  "properties": {
    "addr:full":"1500 SW 8th St Boynton Beach FL 33426",
    "addr:housenumber":"1500",
    "addr:postcode":"33426",
    "addr:street":"Sw 8Th St",
    "iso:country":"US",
    "sg:address":"1500 SW 8th St",
    "sg:city":"Boynton Beach",
    "sg:classifiers":[
        {
            "category":"Home & Garden",
            "subcategory":"Building Materials",
            "type":"Retail Goods"
        }
    ],
    "sg:phone":"+1 561 364 9600",
    "sg:postcode":"33426",
    "sg:province":"FL",
    "wof:name":"Home Depot",
    "wof:placetype":"venue"
},
  "geometry": {"coordinates":[-80.077133,26.514492],"type":"Point"}
}