{
  "type": "Feature",
  "properties": {
    "addr:full":"47 Hancock Bridge Pkwy W Cape Coral FL 33991",
    "addr:housenumber":"47",
    "addr:postcode":"33991",
    "addr:street":"Hancock Bridge Pkwy W",
    "iso:country":"US",
    "sg:address":"47 Hancock Bridge Pkwy W",
    "sg:city":"Cape Coral",
    "sg:classifiers":[
        {
            "category":"Restaurant",
            "type":"Food & Drink"
        }
    ],
    "sg:menulink":"http://www.allmenus.com/fl/cape-coral/158652-arbys/menu/",
    "sg:phone":"+1 239 458 4142",
    "sg:postcode":"33991",
    "sg:province":"FL",
    "sg:tags":[
        "burger",
        "american"
    ],
    "wof:name":"Arby's",
    "wof:placetype":"venue"
},
  "geometry": {"coordinates":[-81.97721900000001,26.649851],"type":"Point"}
}