{
  "type": "Feature",
  "properties": {
    "iso:country":"US",
    "sg:address":"669 W 26th St",
    "sg:city":"Hialeah",
    "sg:classifiers":[
        {
            "category":"Manufacturing",
            "subcategory":"Wood Products",
            "type":"Manufacturing & Wholesale Goods"
        }
    ],
    "sg:phone":"+1 305 888 8344",
    "sg:postcode":"33010",
    "sg:province":"FL",
    "sg:tags":[
        "doors-wood"
    ],
    "wof:name":"Sierra Kitchens Inc",
    "wof:placetype":"venue"
},
  "geometry": {"coordinates":[-80.295304,25.845221],"type":"Point"}
}