{
  "type": "Feature",
  "properties": {
    "iso:country":"US",
    "sg:address":"1010 6th Ave S",
    "sg:city":"Naples",
    "sg:classifiers":[
        {
            "category":"Professional",
            "subcategory":"Business Services",
            "type":"Services"
        }
    ],
    "sg:phone":"+1 239 450 5392",
    "sg:postcode":"34102",
    "sg:province":"FL",
    "sg:tags":[
        "appraiser"
    ],
    "wof:name":"Investment Appraisers",
    "wof:placetype":"venue"
},
  "geometry": {"coordinates":[-81.79241399999999,26.140988],"type":"Point"}
}