{
  "type": "Feature",
  "properties": {
    "iso:country":"US",
    "sg:address":"901 Barnwell Rd",
    "sg:city":"Fernandina Beach",
    "sg:classifiers":[
        {
            "category":"Professional",
            "subcategory":"Management & Consulting",
            "type":"Services"
        }
    ],
    "sg:phone":"+1 904 277 1662",
    "sg:postcode":"32034",
    "sg:province":"FL",
    "sg:tags":[
        "business"
    ],
    "wof:name":"W & B Consulting",
    "wof:placetype":"venue"
},
  "geometry": {"coordinates":[-81.519842,30.625936],"type":"Point"}
}