{
  "type": "Feature",
  "properties": {
    "iso:country":"US",
    "sg:address":"900 6th Ave S",
    "sg:city":"Naples",
    "sg:classifiers":[
        {
            "category":"Health Services",
            "subcategory":"Doctor",
            "type":"Services"
        }
    ],
    "sg:phone":"+1 239 262 6401",
    "sg:postcode":"34102",
    "sg:province":"FL",
    "sg:tags":[
        "dentist"
    ],
    "wof:name":"Ward Whitley S DDS",
    "wof:placetype":"venue"
},
  "geometry": {"coordinates":[-81.79323599999999,26.140971],"type":"Point"}
}