{
  "type": "Feature",
  "properties": {
    "iso:country":"US",
    "sg:address":"405 S Pinellas Ave",
    "sg:city":"Tarpon Springs",
    "sg:classifiers":[
        {
            "category":"Shopping",
            "subcategory":"Stationery & Office Supplies",
            "type":"Retail Goods"
        }
    ],
    "sg:phone":"+1 727 938 8799",
    "sg:postcode":"34689",
    "sg:province":"FL",
    "sg:tags":[
        "educational",
        "material"
    ],
    "sg:website":"www.babybumblebee.com",
    "wof:name":"Baby Bumblebee",
    "wof:placetype":"venue"
},
  "geometry": {"coordinates":[-82.75653800000001,28.142292],"type":"Point"}
}