{
  "type": "Feature",
  "properties": {
    "iso:country":"US",
    "sg:address":"700 Catalina Dr",
    "sg:city":"Daytona Beach",
    "sg:classifiers":[
        {
            "category":"Shopping",
            "subcategory":"Gifts & Souvenirs",
            "type":"Retail Goods"
        }
    ],
    "sg:phone":"+1 386 257 6640",
    "sg:postcode":"32114",
    "sg:province":"FL",
    "sg:tags":[
        "shop",
        "novelty"
    ],
    "wof:name":"Paradies Shops 775",
    "wof:placetype":"venue"
},
  "geometry": {"coordinates":[-81.05892799999999,29.185581],"type":"Point"}
}