{
  "type": "Feature",
  "properties": {
    "iso:country":"US",
    "sg:address":"7925 Portage Dr",
    "sg:city":"Port Richey",
    "sg:classifiers":[
        {
            "category":"Building & Trades",
            "subcategory":"Construction",
            "type":"Services"
        }
    ],
    "sg:phone":"+1 727 863 9044",
    "sg:postcode":"34668",
    "sg:province":"FL",
    "wof:name":"Moljourn Inc",
    "wof:placetype":"venue"
},
  "geometry": {"coordinates":[-82.683471,28.302798],"type":"Point"}
}