{
  "type": "Feature",
  "properties": {
    "iso:country":"US",
    "sg:address":"10740 NW 7th Ave",
    "sg:city":"Miami",
    "sg:classifiers":[
        {
            "category":"Building & Trades",
            "subcategory":"Locksmith",
            "type":"Services"
        }
    ],
    "sg:phone":"+1 786 245 4403",
    "sg:postcode":"33168",
    "sg:province":"FL",
    "sg:tags":[
        "key"
    ],
    "wof:name":"AAA Locksmith",
    "wof:placetype":"venue"
},
  "geometry": {"coordinates":[-80.210235,25.873148],"type":"Point"}
}