{
  "type": "Feature",
  "properties": {
    "iso:country":"US",
    "sg:address":"1400 N P St",
    "sg:city":"Pensacola",
    "sg:classifiers":[
        {
            "category":"Organizations",
            "subcategory":"Religious Organization",
            "type":"Services"
        }
    ],
    "sg:phone":"+1 850 429 0057",
    "sg:postcode":"32505",
    "sg:province":"FL",
    "sg:tags":[
        "church"
    ],
    "wof:name":"End Time Harvest",
    "wof:placetype":"venue"
},
  "geometry": {"coordinates":[-87.241985,30.427294],"type":"Point"}
}