{
  "type": "Feature",
  "properties": {
    "iso:country":"US",
    "sg:address":"1201 Winter Garden Vineland Rd",
    "sg:city":"Winter Garden",
    "sg:classifiers":[
        {
            "category":"Personal",
            "subcategory":"Beauty Salon",
            "type":"Services"
        }
    ],
    "sg:phone":"+1 407 654 5090",
    "sg:postcode":"34787",
    "sg:province":"FL",
    "sg:tags":[
        "shop"
    ],
    "wof:name":"FL Nails",
    "wof:placetype":"venue"
},
  "geometry": {"coordinates":[-81.58845100000001,28.520369],"type":"Point"}
}