{
  "type": "Feature",
  "properties": {
    "iso:country":"US",
    "sg:address":"18332 NW 7th Ave",
    "sg:city":"Miami",
    "sg:classifiers":[
        {
            "category":"Shopping",
            "subcategory":"Clothing, Apparel, & Fashions",
            "type":"Retail Goods"
        }
    ],
    "sg:phone":"+1 305 655 1153",
    "sg:postcode":"33169",
    "sg:province":"FL",
    "wof:name":"Absolutly Classy",
    "wof:placetype":"venue"
},
  "geometry": {"coordinates":[-80.213348,25.943962],"type":"Point"}
}