{
  "type": "Feature",
  "properties": {
    "iso:country":"US",
    "sg:address":"331 Toney Penna Dr",
    "sg:city":"Jupiter",
    "sg:classifiers":[
        {
            "category":"Building & Trades",
            "subcategory":"Construction",
            "type":"Services"
        }
    ],
    "sg:phone":"+1 561 222 3095",
    "sg:postcode":"33458",
    "sg:province":"FL",
    "sg:tags":[
        "carpentry",
        "contractor"
    ],
    "wof:name":"Mgs Interiors",
    "wof:placetype":"venue"
},
  "geometry": {"coordinates":[-80.09805799999999,26.926357],"type":"Point"}
}