{
  "type": "Feature",
  "properties": {
    "iso:country":"US",
    "sg:address":"116 Niemira Ave",
    "sg:city":"Indialantic",
    "sg:classifiers":[
        {
            "category":"Retail",
            "subcategory":"Repair Shop",
            "type":"Services"
        }
    ],
    "sg:phone":"+1 321 728 9415",
    "sg:postcode":"32903",
    "sg:province":"FL",
    "sg:tags":[
        "watch"
    ],
    "wof:name":"Contino Watch Repair",
    "wof:placetype":"venue"
},
  "geometry": {"coordinates":[-80.57104699999999,28.100318],"type":"Point"}
}