{
  "type": "Feature",
  "properties": {
    "iso:country":"US",
    "sg:address":"7915 Riffle Ln",
    "sg:city":"Orlando",
    "sg:classifiers":[
        {
            "category":"Manufacturing",
            "subcategory":"Signs",
            "type":"Manufacturing & Wholesale Goods"
        }
    ],
    "sg:phone":"+1 352 241 9334",
    "sg:postcode":"32818",
    "sg:province":"FL",
    "wof:name":"Riffle Sign & Design",
    "wof:placetype":"venue"
},
  "geometry": {"coordinates":[-81.489643,28.610073],"type":"Point"}
}