{
  "type": "Feature",
  "properties": {
    "iso:country":"US",
    "sg:address":"4411 Bee Ridge Rd",
    "sg:city":"Sarasota",
    "sg:classifiers":[
        {
            "category":"Wholesale",
            "subcategory":"Hardware",
            "type":"Manufacturing & Wholesale Goods"
        }
    ],
    "sg:phone":"+1 941 371 7745",
    "sg:postcode":"34233",
    "sg:province":"FL",
    "sg:tags":[
        "me",
        "rep",
        "commercial",
        "requirement",
        "mfg"
    ],
    "wof:name":"Mechanical Solutions Inc",
    "wof:placetype":"venue"
},
  "geometry": {"coordinates":[-82.476795,27.298823],"type":"Point"}
}