{
  "type": "Feature",
  "properties": {
    "addr:full":"4950 S Military Trl Lake Worth FL 33463",
    "addr:housenumber":"4950",
    "addr:postcode":"33463",
    "addr:street":"S Military Trl",
    "iso:country":"US",
    "sg:address":"4950 S Military Trl",
    "sg:city":"Lake Worth",
    "sg:classifiers":[
        {
            "category":"Food & Beverages",
            "subcategory":"Fruits & Vegetables",
            "type":"Retail Goods"
        }
    ],
    "sg:phone":"+1 561 432 0999",
    "sg:postcode":"33463",
    "sg:province":"FL",
    "sg:tags":[
        "produce"
    ],
    "wof:name":"Frantastic Produce",
    "wof:placetype":"venue"
},
  "geometry": {"coordinates":[-80.1139,26.606579],"type":"Point"}
}