{
  "type": "Feature",
  "properties": {
    "addr:full":"2333 Glades Rd Boca Raton FL 33431",
    "addr:housenumber":"2333",
    "addr:postcode":"33431",
    "addr:street":"Glades Rd",
    "iso:country":"US",
    "sg:address":"2333 Glades Rd",
    "sg:city":"Boca Raton",
    "sg:classifiers":[
        {
            "category":"Government",
            "subcategory":"Office",
            "type":"Public Place"
        }
    ],
    "sg:phone":"+1 561 367 6700",
    "sg:postcode":"33431",
    "sg:province":"FL",
    "sg:tags":[
        "village"
    ],
    "wof:name":"Boca Raton Emergency Prprdnss",
    "wof:placetype":"venue"
},
  "geometry": {"coordinates":[-80.13088500000001,26.368375],"type":"Point"}
}