{
  "type": "Feature",
  "properties": {
    "iso:country":"US",
    "sg:address":"1840 Dunn Ave",
    "sg:city":"Jacksonville",
    "sg:classifiers":[
        {
            "category":"Health Services",
            "subcategory":"Chiropractor",
            "type":"Services"
        }
    ],
    "sg:phone":"+1 904 757 2527",
    "sg:postcode":"32218",
    "sg:province":"FL",
    "sg:tags":[
        "chiropractic"
    ],
    "wof:name":"Kersey, Richard E Dr",
    "wof:placetype":"venue"
},
  "geometry": {"coordinates":[-81.674789,30.434226],"type":"Point"}
}