{
  "type": "Feature",
  "properties": {
    "addr:full":"6844 Cecelia Dr New Port Richey FL 34653",
    "addr:housenumber":"6844",
    "addr:postcode":"34653",
    "addr:street":"Cecelia Dr",
    "iso:country":"US",
    "sg:address":"6844 Cecelia Dr",
    "sg:city":"New Port Richey",
    "sg:classifiers":[
        {
            "category":"Wholesale",
            "subcategory":"Construction Materials",
            "type":"Manufacturing & Wholesale Goods"
        },
        {
            "category":"Manufacturing",
            "subcategory":"Glass & Minerals",
            "type":"Manufacturing & Wholesale Goods"
        }
    ],
    "sg:phone":"+1 727 847 3094",
    "sg:postcode":"34653",
    "sg:province":"FL",
    "sg:tags":[
        "concrete",
        "product",
        "mfg",
        "precast"
    ],
    "wof:name":"Dixie Precast Products Inc",
    "wof:placetype":"venue"
},
  "geometry": {"coordinates":[-82.70150700000001,28.231548],"type":"Point"}
}