{
  "type": "Feature",
  "properties": {
    "iso:country":"US",
    "sg:address":"4335 London Town Rd",
    "sg:city":"Titusville",
    "sg:classifiers":[
        {
            "category":"Sports & Exercise",
            "subcategory":"Golf",
            "type":"Entertainment"
        }
    ],
    "sg:phone":"+1 321 269 4653",
    "sg:postcode":"32796",
    "sg:province":"FL",
    "sg:tags":[
        "course"
    ],
    "wof:name":"Bent Oak Country Club",
    "wof:placetype":"venue"
},
  "geometry": {"coordinates":[-80.866027,28.655181],"type":"Point"}
}