{
  "type": "Feature",
  "properties": {
    "addr:full":"3612 Molona Dr Orlando FL 32837",
    "addr:housenumber":"3612",
    "addr:postcode":"32837",
    "addr:street":"Molona Dr",
    "iso:country":"US",
    "sg:address":"3612 Molona Dr",
    "sg:city":"Orlando",
    "sg:classifiers":[
        {
            "category":"Shopping",
            "subcategory":"Music",
            "type":"Retail Goods"
        }
    ],
    "sg:phone":"+1 407 240 0915",
    "sg:postcode":"32837",
    "sg:province":"FL",
    "wof:name":"Sleeptime Music",
    "wof:placetype":"venue"
},
  "geometry": {"coordinates":[-81.431085,28.348862],"type":"Point"}
}