{
  "type": "Feature",
  "properties": {
    "iso:country":"US",
    "sg:address":"11068 Marquette St",
    "sg:city":"Spring Hill",
    "sg:classifiers":[
        {
            "category":"Building & Trades",
            "subcategory":"Landscaping Services",
            "type":"Services"
        }
    ],
    "sg:phone":"+1 352 666 9104",
    "sg:postcode":"34609",
    "sg:province":"FL",
    "sg:tags":[
        "lawn",
        "maintenance",
        "grounds"
    ],
    "wof:name":"Alexander Abraham's Lawn Care",
    "wof:placetype":"venue"
},
  "geometry": {"coordinates":[-82.54194099999999,28.475309],"type":"Point"}
}