{
  "type": "Feature",
  "properties": {
    "iso:country":"US",
    "sg:address":"5703 NW 35th Ave",
    "sg:city":"Miami",
    "sg:classifiers":[
        {
            "category":"Manufacturing",
            "subcategory":"Paper Products",
            "type":"Manufacturing & Wholesale Goods"
        },
        {
            "category":"Utilities",
            "subcategory":"Refuse",
            "type":"Services"
        }
    ],
    "sg:phone":"+1 305 638 4445",
    "sg:postcode":"33142",
    "sg:province":"FL",
    "sg:tags":[
        "bag",
        "system"
    ],
    "wof:name":"General Paper Recycling Inc",
    "wof:placetype":"venue"
},
  "geometry": {"coordinates":[-80.25296,25.824733],"type":"Point"}
}