{
  "type": "Feature",
  "properties": {
    "iso:country":"US",
    "sg:address":"13976 W Hillsborough Ave",
    "sg:city":"Tampa",
    "sg:classifiers":[
        {
            "category":"Recreation",
            "type":"Entertainment"
        }
    ],
    "sg:phone":"+1 813 925 1115",
    "sg:postcode":"33635",
    "sg:province":"FL",
    "sg:tags":[
        "martial",
        "arts",
        "instruction"
    ],
    "wof:name":"Kim's Karate Tang Soo Do",
    "wof:placetype":"venue"
},
  "geometry": {"coordinates":[-82.648003,28.033412],"type":"Point"}
}