{
  "type": "Feature",
  "properties": {
    "iso:country":"US",
    "sg:address":"1900 Highway 87 Ste D",
    "sg:city":"Navarre",
    "sg:classifiers":[
        {
            "category":"Personal",
            "subcategory":"Nail Salon",
            "type":"Services"
        }
    ],
    "sg:phone":"+1 850 936 1707",
    "sg:postcode":"32566",
    "sg:province":"FL",
    "wof:name":"Parnell Cathy Nails",
    "wof:placetype":"venue"
},
  "geometry": {"coordinates":[-86.870965,30.406913],"type":"Point"}
}