{
  "type": "Feature",
  "properties": {
    "iso:country":"US",
    "sg:address":"1451 N Dean Rd",
    "sg:city":"Orlando",
    "sg:classifiers":[
        {
            "category":"Autos & Motor Vehicles",
            "subcategory":"Fuel & Gas Station",
            "type":"Retail Goods"
        }
    ],
    "sg:phone":"+1 407 273 8440",
    "sg:postcode":"32825",
    "sg:province":"FL",
    "sg:tags":[
        "convenience",
        "gasoline",
        "store"
    ],
    "wof:name":"Lil Champ 104",
    "wof:placetype":"venue"
},
  "geometry": {"coordinates":[-81.24489800000001,28.564273],"type":"Point"}
}