{
  "type": "Feature",
  "properties": {
    "iso:country":"US",
    "sg:address":"4059 5th Ave N",
    "sg:city":"St Petersburg",
    "sg:classifiers":[
        {
            "category":"Food & Beverages",
            "subcategory":"Groceries & Convenience Stores",
            "type":"Retail Goods"
        }
    ],
    "sg:phone":"+1 727 323 1302",
    "sg:postcode":"33713",
    "sg:province":"FL",
    "wof:name":"L and W Food Mart",
    "wof:placetype":"venue"
},
  "geometry": {"coordinates":[-82.688143,27.777329],"type":"Point"}
}