{
  "type": "Feature",
  "properties": {
    "iso:country":"US",
    "sg:address":"1711 SE 3rd St",
    "sg:city":"Cape Coral",
    "sg:classifiers":[
        {
            "category":"Communications",
            "subcategory":"Film & Video Production",
            "type":"Services"
        }
    ],
    "sg:phone":"+1 239 458 8972",
    "sg:postcode":"33990",
    "sg:province":"FL",
    "sg:tags":[
        "taping"
    ],
    "sg:website":"www.shillingvideoproductions.com",
    "wof:name":"Al Shilling Video Productions",
    "wof:placetype":"venue"
},
  "geometry": {"coordinates":[-81.937324,26.647257],"type":"Point"}
}