{
  "type": "Feature",
  "properties": {
    "iso:country":"US",
    "sg:address":"6714 Hanley Rd",
    "sg:city":"Tampa",
    "sg:classifiers":[
        {
            "category":"Food & Beverages",
            "subcategory":"Bakery",
            "type":"Retail Goods"
        }
    ],
    "sg:phone":"+1 813 901 5566",
    "sg:postcode":"33634",
    "sg:province":"FL",
    "sg:tags":[
        "baker"
    ],
    "wof:name":"Mi Patria Bakery",
    "wof:placetype":"venue"
},
  "geometry": {"coordinates":[-82.562684,28.008173],"type":"Point"}
}