{
  "type": "Feature",
  "properties": {
    "iso:country":"US",
    "sg:address":"346 NE 167th St",
    "sg:city":"Miami",
    "sg:classifiers":[
        {
            "category":"Personal",
            "subcategory":"Beauty Salon",
            "type":"Services"
        },
        {
            "category":"Personal",
            "subcategory":"Barber",
            "type":"Services"
        }
    ],
    "sg:phone":"+1 305 945 5551",
    "sg:postcode":"33162",
    "sg:province":"FL",
    "sg:tags":[
        "hair",
        "stylist"
    ],
    "wof:name":"Golden Touch Barber Shop & Salon",
    "wof:placetype":"venue"
},
  "geometry": {"coordinates":[-80.193281,25.928317],"type":"Point"}
}