{
  "type": "Feature",
  "properties": {
    "iso:country":"US",
    "sg:address":"315 W Palmetto St",
    "sg:city":"Wauchula",
    "sg:classifiers":[
        {
            "category":"Shopping",
            "subcategory":"Gifts & Souvenirs",
            "type":"Retail Goods"
        }
    ],
    "sg:phone":"+1 863 773 4737",
    "sg:postcode":"33873",
    "sg:province":"FL",
    "wof:name":"Rustic Gardens Inc",
    "wof:placetype":"venue"
},
  "geometry": {"coordinates":[-81.81445600000001,27.548306],"type":"Point"}
}