{
  "type": "Feature",
  "properties": {
    "addr:full":"6640 Superior Ave Sarasota FL 34231",
    "addr:housenumber":"6640",
    "addr:postcode":"34231",
    "addr:street":"Superior Ave",
    "iso:country":"US",
    "sg:address":"6640 Superior Ave",
    "sg:city":"Sarasota",
    "sg:classifiers":[
        {
            "category":"Retail",
            "subcategory":"Self-service Laundry",
            "type":"Services"
        }
    ],
    "sg:phone":"+1 941 921 0321",
    "sg:postcode":"34231",
    "sg:province":"FL",
    "sg:tags":[
        "coin"
    ],
    "wof:name":"Clean Spot Laundry",
    "wof:placetype":"venue"
},
  "geometry": {"coordinates":[-82.515635,27.260661],"type":"Point"}
}