{
  "type": "Feature",
  "properties": {
    "addr:full":"235 NW 95th Ter Pompano Beach FL 33071",
    "addr:housenumber":"235",
    "addr:postcode":"33071",
    "addr:street":"Nw 95Th Ter",
    "iso:country":"US",
    "sg:address":"235 NW 95th Ter",
    "sg:city":"Pompano Beach",
    "sg:classifiers":[
        {
            "category":"Autos & Motor Vehicles",
            "subcategory":"Auto Supplies",
            "type":"Retail Goods"
        }
    ],
    "sg:phone":"+1 954 753 2949",
    "sg:postcode":"33071",
    "sg:province":"FL",
    "wof:name":"W Sunrise Tire Co",
    "wof:placetype":"venue"
},
  "geometry": {"coordinates":[-80.252087,26.233922],"type":"Point"}
}