{
  "type": "Feature",
  "properties": {
    "iso:country":"US",
    "sg:address":"7742 NW 193rd Ter",
    "sg:city":"Hialeah",
    "sg:classifiers":[
        {
            "category":"Building & Trades",
            "subcategory":"Construction",
            "type":"Services"
        }
    ],
    "sg:phone":"+1 305 829 0284",
    "sg:postcode":"33015",
    "sg:province":"FL",
    "sg:tags":[
        "general",
        "contractor"
    ],
    "wof:name":"Ivory Construction Inc",
    "wof:placetype":"venue"
},
  "geometry": {"coordinates":[-80.32984999999999,25.948949],"type":"Point"}
}