{
  "type": "Feature",
  "properties": {
    "addr:full":"12725 85th St Fellsmere FL 32948",
    "addr:housenumber":"12725",
    "addr:postcode":"32948",
    "addr:street":"85Th St",
    "iso:country":"US",
    "sg:address":"12725 85th St",
    "sg:city":"Fellsmere",
    "sg:classifiers":[
        {
            "category":"Social Services",
            "subcategory":"Child Care",
            "type":"Services"
        }
    ],
    "sg:phone":"+1 772 571 0055",
    "sg:postcode":"32948",
    "sg:province":"FL",
    "sg:tags":[
        "day"
    ],
    "wof:name":"Blue Moon Nursery",
    "wof:placetype":"venue"
},
  "geometry": {"coordinates":[-80.585245,27.749847],"type":"Point"}
}