{
  "type": "Feature",
  "properties": {
    "iso:country":"US",
    "sg:address":"10603 Sunrise Terrace Dr",
    "sg:city":"Orlando",
    "sg:classifiers":[
        {
            "category":"Banks & Credit Unions",
            "subcategory":"Financial Services",
            "type":"Services"
        }
    ],
    "sg:phone":"+1 407 208 0719",
    "sg:postcode":"32825",
    "sg:province":"FL",
    "sg:tags":[
        "information",
        "consumer"
    ],
    "wof:name":"Rhoan R Reid Wsc Inc",
    "wof:placetype":"venue"
},
  "geometry": {"coordinates":[-81.226259,28.514193],"type":"Point"}
}