{
  "type": "Feature",
  "properties": {
    "iso:country":"US",
    "sg:address":"10333 Cypress Isle Ct",
    "sg:city":"Orlando",
    "sg:classifiers":[
        {
            "category":"Organizations",
            "subcategory":"Religious Organization",
            "type":"Services"
        }
    ],
    "sg:phone":"+1 407 876 1264",
    "sg:postcode":"32836",
    "sg:province":"FL",
    "sg:tags":[
        "place",
        "worship",
        "church"
    ],
    "wof:name":"Thomas Parsonage",
    "wof:placetype":"venue"
},
  "geometry": {"coordinates":[-81.53069499999999,28.437466],"type":"Point"}
}