{
  "type": "Feature",
  "properties": {
    "iso:country":"US",
    "sg:address":"1404 E Robinson St",
    "sg:city":"Orlando",
    "sg:classifiers":[
        {
            "category":"Professional",
            "subcategory":"Accounting & Tax Preparation",
            "type":"Services"
        }
    ],
    "sg:phone":"+1 407 898 3521",
    "sg:postcode":"32801",
    "sg:province":"FL",
    "wof:name":"Demro & Demro",
    "wof:placetype":"venue"
},
  "geometry": {"coordinates":[-81.36023900000001,28.545758],"type":"Point"}
}