{
  "type": "Feature",
  "properties": {
    "iso:country":"US",
    "sg:address":"1493 Shoal Way",
    "sg:city":"Osprey",
    "sg:classifiers":[
        {
            "category":"Professional",
            "subcategory":"Art Services",
            "type":"Services"
        }
    ],
    "sg:phone":"+1 941 966 6460",
    "sg:postcode":"34229",
    "sg:province":"FL",
    "sg:tags":[
        "designer",
        "display",
        "producer"
    ],
    "wof:name":"Pfp Design Services",
    "wof:placetype":"venue"
},
  "geometry": {"coordinates":[-82.483479,27.173421],"type":"Point"}
}