{
  "type": "Feature",
  "properties": {
    "addr:full":"19333 W Country Club Dr Aventura FL 33180",
    "addr:housenumber":"19333",
    "addr:postcode":"33180",
    "addr:street":"W Country Club Dr",
    "iso:country":"US",
    "sg:address":"19333 W Country Club Dr",
    "sg:city":"Aventura",
    "sg:classifiers":[
        {
            "category":"Social Services",
            "subcategory":"Retirement Home",
            "type":"Services"
        }
    ],
    "sg:phone":"+1 888 697 6125",
    "sg:postcode":"33180",
    "sg:province":"FL",
    "sg:website":"www.viliving.com/communities/ave...",
    "wof:name":"Vi at Aventura",
    "wof:placetype":"venue"
},
  "geometry": {"coordinates":[-80.13758,25.954723],"type":"Point"}
}