{
  "type": "Feature",
  "properties": {
    "iso:country":"US",
    "sg:address":"7908 SE Arrance St",
    "sg:city":"Hobe Sound",
    "sg:classifiers":[
        {
            "category":"Building & Trades",
            "subcategory":"Pest Control",
            "type":"Services"
        }
    ],
    "sg:phone":"+1 772 545 7255",
    "sg:postcode":"33455",
    "sg:province":"FL",
    "wof:name":"Florida Pest & Plant Svc",
    "wof:placetype":"venue"
},
  "geometry": {"coordinates":[-80.147746,27.078984],"type":"Point"}
}