{
  "type": "Feature",
  "properties": {
    "iso:country":"US",
    "sg:address":"2051 Saxon Blvd",
    "sg:city":"Deltona",
    "sg:classifiers":[
        {
            "category":"Shopping",
            "subcategory":"Florist",
            "type":"Retail Goods"
        }
    ],
    "sg:phone":"+1 386 532 8880",
    "sg:postcode":"32725",
    "sg:province":"FL",
    "wof:name":"Stetson Flowers of Deltona Inc",
    "wof:placetype":"venue"
},
  "geometry": {"coordinates":[-81.26300000000001,28.910999],"type":"Point"}
}