{
  "type": "Feature",
  "properties": {
    "iso:country":"US",
    "sg:address":"135 W Jessup Ave",
    "sg:city":"Longwood",
    "sg:classifiers":[
        {
            "category":"Professional",
            "type":"Services"
        },
        {
            "category":"Personal",
            "type":"Services"
        }
    ],
    "sg:phone":"+1 407 927 4515",
    "sg:postcode":"32750",
    "sg:province":"FL",
    "sg:tags":[
        "wedding",
        "planning",
        "caterer"
    ],
    "sg:website":"www.magicoccasions.com",
    "wof:name":"Magic Occasions Catering",
    "wof:placetype":"venue"
},
  "geometry": {"coordinates":[-81.347178,28.701666],"type":"Point"}
}