{
  "type": "Feature",
  "properties": {
    "iso:country":"US",
    "sg:address":"4296 Rocky Ridge Pl",
    "sg:city":"Sanford",
    "sg:classifiers":[
        {
            "category":"Autos & Motor Vehicles",
            "subcategory":"Automobile Sales",
            "type":"Retail Goods"
        },
        {
            "category":"Airline",
            "type":"Transportation"
        }
    ],
    "sg:phone":"+1 407 330 1210",
    "sg:postcode":"32773",
    "sg:province":"FL",
    "sg:tags":[
        "shuttle",
        "airport",
        "limo"
    ],
    "wof:name":"Lake Mary Shuttle Service",
    "wof:placetype":"venue"
},
  "geometry": {"coordinates":[-81.27287200000001,28.746401],"type":"Point"}
}