{
  "type": "Feature",
  "properties": {
    "iso:country":"US",
    "sg:address":"1617 Ridgewood Ave",
    "sg:city":"Daytona Beach",
    "sg:classifiers":[
        {
            "category":"Utilities",
            "subcategory":"Telephone",
            "type":"Services"
        },
        {
            "category":"Professional",
            "subcategory":"Computer Services",
            "type":"Services"
        }
    ],
    "sg:phone":"+1 386 671 6145",
    "sg:postcode":"32117",
    "sg:province":"FL",
    "sg:tags":[
        "communications",
        "internet"
    ],
    "wof:name":"D & R Internet Marketing Inc",
    "wof:placetype":"venue"
},
  "geometry": {"coordinates":[-81.04800299999999,29.257865],"type":"Point"}
}