{
  "type": "Feature",
  "properties": {
    "iso:country":"US",
    "sg:address":"2001 SW 87th Ave",
    "sg:city":"North Lauderdale",
    "sg:classifiers":[
        {
            "category":"Wholesale",
            "subcategory":"Hardware",
            "type":"Manufacturing & Wholesale Goods"
        },
        {
            "category":"Wholesale",
            "subcategory":"Durable Goods & Equipment",
            "type":"Manufacturing & Wholesale Goods"
        }
    ],
    "sg:phone":"+1 954 724 3127",
    "sg:postcode":"33068",
    "sg:province":"FL",
    "sg:tags":[
        "exporter"
    ],
    "wof:name":"Articor Inc",
    "wof:placetype":"venue"
},
  "geometry": {"coordinates":[-80.24342300000001,26.202561],"type":"Point"}
}