{
  "type": "Feature",
  "properties": {
    "addr:full":"1626 Columbia St Orlando FL 32805",
    "addr:housenumber":"1626",
    "addr:postcode":"32805",
    "addr:street":"Columbia St",
    "iso:country":"US",
    "sg:address":"1626 Columbia St",
    "sg:city":"Orlando",
    "sg:classifiers":[
        {
            "category":"Building & Trades",
            "subcategory":"Construction",
            "type":"Services"
        }
    ],
    "sg:phone":"+1 407 423 1763",
    "sg:postcode":"32805",
    "sg:province":"FL",
    "sg:tags":[
        "contractor"
    ],
    "wof:name":"Ajz Drywall Inc",
    "wof:placetype":"venue"
},
  "geometry": {"coordinates":[-81.40378800000001,28.527241],"type":"Point"}
}