{
  "type": "Feature",
  "properties": {
    "addr:full":"3205 S US Hwy 1 Fort Pierce FL 34982",
    "addr:housenumber":"3205",
    "addr:postcode":"34982",
    "addr:street":"S Us Hwy 1",
    "iso:country":"US",
    "sg:address":"3205 S US Hwy 1",
    "sg:city":"Fort Pierce",
    "sg:classifiers":[
        {
            "category":"Restaurant",
            "type":"Food & Drink"
        }
    ],
    "sg:phone":"+1 772 465 5571",
    "sg:postcode":"34982",
    "sg:province":"FL",
    "sg:tags":[
        "eating"
    ],
    "wof:name":"Long John Silver's",
    "wof:placetype":"venue"
},
  "geometry": {"coordinates":[-80.325965,27.407471],"type":"Point"}
}