{
  "type": "Feature",
  "properties": {
    "addr:full":"3171 56th St N Saint Petersburg FL 33710",
    "addr:housenumber":"3171",
    "addr:postcode":"33710",
    "addr:street":"56Th St N",
    "iso:country":"US",
    "sg:address":"3171 56th St N",
    "sg:city":"Saint Petersburg",
    "sg:classifiers":[
        {
            "category":"Professional",
            "type":"Services"
        }
    ],
    "sg:phone":"+1 727 381 5187",
    "sg:postcode":"33710",
    "sg:province":"FL",
    "wof:name":"Daves Service Main",
    "wof:placetype":"venue"
},
  "geometry": {"coordinates":[-82.708949,27.800189],"type":"Point"}
}