{
  "type": "Feature",
  "properties": {
    "iso:country":"US",
    "sg:address":"435 S Ridgewood Ave",
    "sg:city":"Daytona Beach",
    "sg:classifiers":[
        {
            "category":"Building & Trades",
            "subcategory":"Cleaning & Sanitation",
            "type":"Services"
        }
    ],
    "sg:phone":"+1 386 254 1974",
    "sg:postcode":"32114",
    "sg:province":"FL",
    "sg:tags":[
        "janitor"
    ],
    "wof:name":"Coverall Cleaning Concepts",
    "wof:placetype":"venue"
},
  "geometry": {"coordinates":[-81.019032,29.203916],"type":"Point"}
}