{
  "type": "Feature",
  "properties": {
    "iso:country":"US",
    "sg:address":"2531 Aragon Blvd",
    "sg:city":"Sunrise",
    "sg:classifiers":[
        {
            "category":"Building & Trades",
            "subcategory":"Landscaping Services",
            "type":"Services"
        }
    ],
    "sg:phone":"+1 954 748 6750",
    "sg:postcode":"33322",
    "sg:province":"FL",
    "sg:tags":[
        "lawn",
        "tree",
        "landscape",
        "maintenance",
        "contractor"
    ],
    "wof:name":"Major League Lawn & Landscaping Service",
    "wof:placetype":"venue"
},
  "geometry": {"coordinates":[-80.254216,26.156106],"type":"Point"}
}