{
  "type": "Feature",
  "properties": {
    "iso:country":"US",
    "sg:address":"3591 Keystone Rd",
    "sg:city":"Tarpon Springs",
    "sg:classifiers":[
        {
            "category":"Retail",
            "subcategory":"Veterinary Services",
            "type":"Services"
        }
    ],
    "sg:phone":"+1 727 785 1067",
    "sg:postcode":"34688",
    "sg:province":"FL",
    "sg:tags":[
        "veterinarian"
    ],
    "wof:name":"Coastal Veterinary Clinic",
    "wof:placetype":"venue"
},
  "geometry": {"coordinates":[-82.680803,28.144968],"type":"Point"}
}