{
  "type": "Feature",
  "properties": {
    "addr:full":"3622 Brentwood Ave Jacksonville FL 32206",
    "addr:housenumber":"3622",
    "addr:postcode":"32206",
    "addr:street":"Brentwood Ave",
    "iso:country":"US",
    "sg:address":"3622 Brentwood Ave",
    "sg:city":"Jacksonville",
    "sg:classifiers":[
        {
            "category":"Social Services",
            "subcategory":"Child Care",
            "type":"Services"
        }
    ],
    "sg:phone":"+1 904 634 1490",
    "sg:postcode":"32206",
    "sg:province":"FL",
    "sg:tags":[
        "day"
    ],
    "wof:name":"Brentwood Headstart Center",
    "wof:placetype":"venue"
},
  "geometry": {"coordinates":[-81.66495,30.361983],"type":"Point"}
}