{
  "type": "Feature",
  "properties": {
    "iso:country":"US",
    "sg:address":"1168 W New Haven Ave",
    "sg:city":"West Melbourne",
    "sg:classifiers":[
        {
            "category":"Health Services",
            "subcategory":"Health Practitioner",
            "type":"Services"
        }
    ],
    "sg:phone":"+1 321 956 7777",
    "sg:postcode":"32904",
    "sg:province":"FL",
    "sg:tags":[
        "acupuncture"
    ],
    "wof:name":"Migun Central LLC",
    "wof:placetype":"venue"
},
  "geometry": {"coordinates":[-80.64112,28.078863],"type":"Point"}
}