{
  "type": "Feature",
  "properties": {
    "addr:full":"1922 Mears Pkwy Margate FL 33063",
    "addr:housenumber":"1922",
    "addr:postcode":"33063",
    "addr:street":"Mears Pkwy Margate",
    "iso:country":"US",
    "sg:address":"1922 Mears Pkwy",
    "sg:city":"Margate",
    "sg:classifiers":[
        {
            "category":"Manufacturing",
            "subcategory":"Building Materials",
            "type":"Manufacturing & Wholesale Goods"
        }
    ],
    "sg:phone":"+1 954 917 5092",
    "sg:postcode":"33063",
    "sg:province":"FL",
    "sg:tags":[
        "frames",
        "doors",
        "accessory"
    ],
    "wof:name":"T C Shutter Systems",
    "wof:placetype":"venue"
},
  "geometry": {"coordinates":[-80.19534400000001,26.249638],"type":"Point"}
}