{
  "type": "Feature",
  "properties": {
    "iso:country":"US",
    "sg:address":"2318 Amelia Ln",
    "sg:city":"Pensacola",
    "sg:classifiers":[
        {
            "category":"Building & Trades",
            "subcategory":"Construction",
            "type":"Services"
        }
    ],
    "sg:phone":"+1 850 944 9488",
    "sg:postcode":"32526",
    "sg:province":"FL",
    "sg:tags":[
        "builder",
        "operative"
    ],
    "wof:name":"Millennium Homebuilders Inc",
    "wof:placetype":"venue"
},
  "geometry": {"coordinates":[-87.298012,30.500826],"type":"Point"}
}