{
  "type": "Feature",
  "properties": {
    "iso:country":"US",
    "sg:address":"4405 SW 35 Ter",
    "sg:city":"Gainesville",
    "sg:classifiers":[
        {
            "category":"Building & Trades",
            "subcategory":"Cleaning & Sanitation",
            "type":"Services"
        }
    ],
    "sg:phone":"+1 352 373 5628",
    "sg:postcode":"32608",
    "sg:province":"FL",
    "sg:tags":[
        "maintenance"
    ],
    "wof:name":"V & I Maintenance",
    "wof:placetype":"venue"
},
  "geometry": {"coordinates":[-82.375051,29.612435],"type":"Point"}
}