{
  "type": "Feature",
  "properties": {
    "iso:country":"US",
    "sg:address":"11623 Corporate Lake Blvd",
    "sg:city":"San Antonio",
    "sg:classifiers":[
        {
            "category":"Autos & Motor Vehicles",
            "subcategory":"Recreational Vehicle Sales",
            "type":"Retail Goods"
        }
    ],
    "sg:phone":"+1 352 588 4500",
    "sg:postcode":"33576",
    "sg:province":"FL",
    "sg:website":"www.marathoncoach.com",
    "wof:name":"Marathon Coach Inc",
    "wof:placetype":"venue"
},
  "geometry": {"coordinates":[-82.312971,28.327284],"type":"Point"}
}