{
  "type": "Feature",
  "properties": {
    "addr:full":"4620 N Galloway Rd Lakeland FL 33810",
    "addr:housenumber":"4620",
    "addr:postcode":"33810",
    "addr:street":"N Galloway Rd",
    "iso:country":"US",
    "sg:address":"4620 N Galloway Rd",
    "sg:city":"Lakeland",
    "sg:classifiers":[
        {
            "category":"Manufacturing",
            "subcategory":"Chemicals & Compounds",
            "type":"Manufacturing & Wholesale Goods"
        }
    ],
    "sg:phone":"+1 863 815 5000",
    "sg:postcode":"33810",
    "sg:province":"FL",
    "sg:tags":[
        "resin"
    ],
    "wof:name":"AOC",
    "wof:placetype":"venue"
},
  "geometry": {"coordinates":[-82.00679599999999,28.105742],"type":"Point"}
}