{
  "type": "Feature",
  "properties": {
    "iso:country":"US",
    "sg:address":"410 E Mattie St",
    "sg:city":"Sanford",
    "sg:classifiers":[
        {
            "category":"Professional",
            "type":"Services"
        }
    ],
    "sg:phone":"+1 407 323 8822",
    "sg:postcode":"32773",
    "sg:province":"FL",
    "sg:tags":[
        "establishment"
    ],
    "wof:name":"John Fitzgerald Inc",
    "wof:placetype":"venue"
},
  "geometry": {"coordinates":[-81.26340399999999,28.778111],"type":"Point"}
}