{
  "type": "Feature",
  "properties": {
    "iso:country":"US",
    "sg:address":"101 1st St NW",
    "sg:city":"Largo",
    "sg:classifiers":[
        {
            "category":"Personal",
            "subcategory":"Beauty Salon",
            "type":"Services"
        }
    ],
    "sg:phone":"+1 727 584 5555",
    "sg:postcode":"33770",
    "sg:province":"FL",
    "sg:tags":[
        "hair",
        "stylist"
    ],
    "wof:name":"Hollywood Hair",
    "wof:placetype":"venue"
},
  "geometry": {"coordinates":[-82.78894,27.916759],"type":"Point"}
}