{
  "type": "Feature",
  "properties": {
    "addr:full":"1710 SE Van Loon Ter Cape Coral FL 33990",
    "addr:housenumber":"1710",
    "addr:postcode":"33990",
    "addr:street":"Se Van Loon Ter",
    "iso:country":"US",
    "sg:address":"1710 SE Van Loon Ter",
    "sg:city":"Cape Coral",
    "sg:classifiers":[
        {
            "category":"Restaurant",
            "type":"Food & Drink"
        }
    ],
    "sg:phone":"+1 239 772 5994",
    "sg:postcode":"33990",
    "sg:province":"FL",
    "sg:tags":[
        "eating"
    ],
    "wof:name":"Melanies Restaurant Inc",
    "wof:placetype":"venue"
},
  "geometry": {"coordinates":[-81.93562900000001,26.651493],"type":"Point"}
}