{
  "type": "Feature",
  "properties": {
    "iso:country":"US",
    "sg:address":"1130 SW 70th Ter",
    "sg:city":"Fort Lauderdale",
    "sg:classifiers":[
        {
            "category":"Health Services",
            "subcategory":"Doctor",
            "type":"Services"
        }
    ],
    "sg:phone":"+1 954 327 3824",
    "sg:postcode":"33317",
    "sg:province":"FL",
    "sg:tags":[
        "medical"
    ],
    "wof:name":"Lwin Nyunt MD",
    "wof:placetype":"venue"
},
  "geometry": {"coordinates":[-80.242194,26.106319],"type":"Point"}
}