{
  "type": "Feature",
  "properties": {
    "iso:country":"US",
    "sg:address":"1435 W 49th St",
    "sg:city":"Hialeah",
    "sg:classifiers":[
        {
            "category":"Health Services",
            "subcategory":"Doctor",
            "type":"Services"
        }
    ],
    "sg:phone":"+1 305 557 2885",
    "sg:postcode":"33012",
    "sg:province":"FL",
    "sg:tags":[
        "medical"
    ],
    "wof:name":"Bertha Olazabal MD",
    "wof:placetype":"venue"
},
  "geometry": {"coordinates":[-80.311407,25.866673],"type":"Point"}
}