{
  "type": "Feature",
  "properties": {
    "addr:full":"7550 Bridle Path Ln Tallahassee FL 32309",
    "addr:housenumber":"7550",
    "addr:postcode":"32309",
    "addr:street":"Bridle Path Ln",
    "iso:country":"US",
    "sg:address":"7550 Bridle Path Ln",
    "sg:city":"Tallahassee",
    "sg:classifiers":[
        {
            "category":"Retail",
            "subcategory":"Repair Shop",
            "type":"Services"
        }
    ],
    "sg:phone":"+1 850 893 5500",
    "sg:postcode":"32309",
    "sg:province":"FL",
    "sg:tags":[
        "refinishing",
        "furniture"
    ],
    "wof:name":"Furniture Medic Inc",
    "wof:placetype":"venue"
},
  "geometry": {"coordinates":[-84.147553,30.558041],"type":"Point"}
}