{
  "type": "Feature",
  "properties": {
    "addr:full":"1072 S Tamiami Trl Osprey FL 34229",
    "addr:housenumber":"1072",
    "addr:postcode":"34229",
    "addr:street":"S Tamiami Trl Osprey",
    "iso:country":"US",
    "sg:address":"1072 S Tamiami Trl",
    "sg:city":"Osprey",
    "sg:phone":"+1 941 966 4453",
    "sg:postcode":"34229",
    "sg:province":"FL",
    "wof:name":"Frankie's Italian Ristorante",
    "wof:placetype":"venue"
},
  "geometry": {"coordinates":[-82.48308,27.181241],"type":"Point"}
}