{
  "type": "Feature",
  "properties": {
    "iso:country":"US",
    "sg:address":"146 Camden G",
    "sg:city":"West Palm Beach",
    "sg:classifiers":[
        {
            "category":"Shopping",
            "subcategory":"Computers & Home Electronics",
            "type":"Retail Goods"
        }
    ],
    "sg:phone":"+1 561 689 6733",
    "sg:postcode":"33417",
    "sg:province":"FL",
    "sg:tags":[
        "equipment",
        "dealer"
    ],
    "wof:name":"Joan Beeler Computers",
    "wof:placetype":"venue"
},
  "geometry": {"coordinates":[-80.133511,26.714449],"type":"Point"}
}