{
  "type": "Feature",
  "properties": {
    "addr:full":"902 SW Santa Barbara Pl Cape Coral FL 33991",
    "addr:housenumber":"902",
    "addr:postcode":"33991",
    "addr:street":"Sw Santa Barbara Pl",
    "iso:country":"US",
    "sg:address":"902 SW Santa Barbara Pl",
    "sg:city":"Cape Coral",
    "sg:classifiers":[
        {
            "category":"Building & Trades",
            "subcategory":"Construction",
            "type":"Services"
        }
    ],
    "sg:phone":"+1 239 458 8631",
    "sg:postcode":"33991",
    "sg:province":"FL",
    "sg:tags":[
        "floor",
        "laying",
        "contractor"
    ],
    "wof:name":"G & W Floor Craftsman",
    "wof:placetype":"venue"
},
  "geometry": {"coordinates":[-81.975295,26.633437],"type":"Point"}
}