{
  "type": "Feature",
  "properties": {
    "iso:country":"US",
    "sg:address":"137 Patrick Dr",
    "sg:city":"Fort Walton Bch",
    "sg:classifiers":[
        {
            "category":"Retail",
            "subcategory":"Auto Repair",
            "type":"Services"
        }
    ],
    "sg:phone":"+1 850 863 1533",
    "sg:postcode":"32547",
    "sg:province":"FL",
    "sg:tags":[
        "repairing",
        "automobile"
    ],
    "wof:name":"Andrew's Auto Repair",
    "wof:placetype":"venue"
},
  "geometry": {"coordinates":[-86.63614,30.45166],"type":"Point"}
}