{
  "type": "Feature",
  "properties": {
    "iso:country":"US",
    "sg:address":"6040 Lee St NE",
    "sg:city":"Saint Petersburg",
    "sg:classifiers":[
        {
            "category":"Building & Trades",
            "subcategory":"Construction",
            "type":"Services"
        }
    ],
    "sg:phone":"+1 727 526 8348",
    "sg:postcode":"33703",
    "sg:province":"FL",
    "sg:tags":[
        "house"
    ],
    "wof:name":"John Henry Business",
    "wof:placetype":"venue"
},
  "geometry": {"coordinates":[-82.626531,27.827185],"type":"Point"}
}