{
  "type": "Feature",
  "properties": {
    "addr:full":"418 E Call St Starke FL 32091",
    "addr:housenumber":"418",
    "addr:postcode":"32091",
    "addr:street":"E Call St",
    "iso:country":"US",
    "sg:address":"418 E Call St",
    "sg:city":"Starke",
    "sg:classifiers":[
        {
            "category":"Food & Beverages",
            "subcategory":"Groceries & Convenience Stores",
            "type":"Retail Goods"
        }
    ],
    "sg:phone":"+1 904 964 7019",
    "sg:postcode":"32091",
    "sg:province":"FL",
    "wof:name":"Roys Grocery and Market",
    "wof:placetype":"venue"
},
  "geometry": {"coordinates":[-82.107862,29.943495],"type":"Point"}
}