{
  "type": "Feature",
  "properties": {
    "addr:full":"227 NE 19th Ave Pompano Beach FL 33060",
    "addr:housenumber":"227",
    "addr:postcode":"33060",
    "addr:street":"Ne 19Th Ave",
    "iso:country":"US",
    "sg:address":"227 NE 19th Ave",
    "sg:city":"Pompano Beach",
    "sg:classifiers":[
        {
            "category":"Retail",
            "subcategory":"Repair Shop",
            "type":"Services"
        }
    ],
    "sg:phone":"+1 954 792 7225",
    "sg:postcode":"33060",
    "sg:province":"FL",
    "sg:tags":[
        "appliance"
    ],
    "wof:name":"Appliance Cleaning & Detailing",
    "wof:placetype":"venue"
},
  "geometry": {"coordinates":[-80.105028,26.235163],"type":"Point"}
}