{
  "type": "Feature",
  "properties": {
    "iso:country":"US",
    "sg:address":"2001 Granada Blvd",
    "sg:city":"Coral Gables",
    "sg:classifiers":[
        {
            "category":"Fast Food",
            "type":"Food & Drink"
        }
    ],
    "sg:phone":"+1 305 567 3100",
    "sg:postcode":"33134",
    "sg:province":"FL",
    "sg:tags":[
        "burger"
    ],
    "wof:name":"Burger Bobs",
    "wof:placetype":"venue"
},
  "geometry": {"coordinates":[-80.2752,25.753],"type":"Point"}
}