{
  "type": "Feature",
  "properties": {
    "addr:full":"233 SE Ave E Belle Glade FL 33430",
    "addr:housenumber":"233",
    "addr:postcode":"33430",
    "addr:street":"Se Ave E Belle Glade",
    "iso:country":"US",
    "sg:address":"233 SE Ave E",
    "sg:city":"Belle Glade",
    "sg:classifiers":[
        {
            "category":"Restaurant",
            "type":"Food & Drink"
        }
    ],
    "sg:phone":"+1 561 996 2494",
    "sg:postcode":"33430",
    "sg:province":"FL",
    "sg:tags":[
        "sandwich"
    ],
    "wof:name":"Normans Drive-Thru Sandwiches",
    "wof:placetype":"venue"
},
  "geometry": {"coordinates":[-80.665643,26.682317],"type":"Point"}
}