{
  "type": "Feature",
  "properties": {
    "iso:country":"US",
    "sg:address":"1011 N 14th Ave",
    "sg:city":"Hollywood",
    "sg:classifiers":[
        {
            "category":"Wholesale",
            "subcategory":"Photographic Equipment",
            "type":"Manufacturing & Wholesale Goods"
        }
    ],
    "sg:phone":"+1 305 785 8778",
    "sg:postcode":"33020",
    "sg:province":"FL",
    "sg:tags":[
        "battery",
        "camera",
        "video",
        "cassette",
        "audio",
        "film"
    ],
    "wof:name":"Ymi Imaginations Inc",
    "wof:placetype":"venue"
},
  "geometry": {"coordinates":[-80.135189,26.020857],"type":"Point"}
}