{
  "type": "Feature",
  "properties": {
    "addr:full":"7935 Airport Pulling Rd N Naples FL 34109",
    "addr:housenumber":"7935",
    "addr:postcode":"34109",
    "addr:street":"Airport Pulling Rd N",
    "iso:country":"US",
    "sg:address":"7935 Airport Pulling Rd N",
    "sg:city":"Naples",
    "sg:classifiers":[
        {
            "category":"Restaurant",
            "type":"Food & Drink"
        }
    ],
    "sg:phone":"+1 239 598 4000",
    "sg:postcode":"34109",
    "sg:province":"FL",
    "sg:tags":[
        "pizza"
    ],
    "wof:name":"Puccini's",
    "wof:placetype":"venue"
},
  "geometry": {"coordinates":[-81.769125,26.240858],"type":"Point"}
}