{
  "type": "Feature",
  "properties": {
    "iso:country":"US",
    "sg:address":"207 Tern Ln",
    "sg:city":"Altamonte Springs",
    "sg:classifiers":[
        {
            "category":"Banks & Credit Unions",
            "subcategory":"Financial Services",
            "type":"Services"
        }
    ],
    "sg:phone":"+1 407 830 0326",
    "sg:postcode":"32701",
    "sg:province":"FL",
    "sg:tags":[
        "investor"
    ],
    "wof:name":"J&J Real Estate Investments LL",
    "wof:placetype":"venue"
},
  "geometry": {"coordinates":[-81.38521299999999,28.674114],"type":"Point"}
}