{
  "type": "Feature",
  "properties": {
    "addr:full":"2800 W State Road 426 Oviedo FL 32765",
    "addr:housenumber":"2800",
    "addr:postcode":"32765",
    "addr:street":"W State Road 426",
    "iso:country":"US",
    "sg:address":"2800 W State Road 426",
    "sg:city":"Oviedo",
    "sg:classifiers":[
        {
            "category":"Utilities",
            "subcategory":"Fuel Oil & Lpg",
            "type":"Services"
        },
        {
            "category":"Utilities",
            "subcategory":"Natural Gas",
            "type":"Services"
        }
    ],
    "sg:phone":"+1 407 365 3723",
    "sg:postcode":"32765",
    "sg:province":"FL",
    "sg:tags":[
        "propane",
        "bulk",
        "petroleum-bottled",
        "gas-liquefied"
    ],
    "sg:website":"http://www.ferrellgas.com",
    "wof:name":"Ferrellgas",
    "wof:placetype":"venue"
},
  "geometry": {"coordinates":[-81.243019,28.62863],"type":"Point"}
}