{
  "type": "Feature",
  "properties": {
    "iso:country":"US",
    "sg:address":"3301 Del Prado Blvd Coldwell Banker",
    "sg:city":"Cape Coral",
    "sg:classifiers":[
        {
            "category":"Real Estate",
            "subcategory":"Real Estate Agent",
            "type":"Services"
        }
    ],
    "sg:phone":"+1 239 246 0167",
    "sg:postcode":"33904",
    "sg:province":"FL",
    "sg:website":"www.beachballproperties.com",
    "wof:name":"Susan Ball, Realtor",
    "wof:placetype":"venue"
},
  "geometry": {"coordinates":[-81.94148199999999,26.590864],"type":"Point"}
}