{
  "type": "Feature",
  "properties": {
    "iso:country":"US",
    "sg:address":"3608 Cardinal Blvd",
    "sg:city":"Daytona Beach",
    "sg:classifiers":[
        {
            "category":"Shopping",
            "subcategory":"Hobbies, Toys, & Games",
            "type":"Retail Goods"
        }
    ],
    "sg:phone":"+1 386 767 1718",
    "sg:postcode":"32118",
    "sg:province":"FL",
    "sg:tags":[
        "model",
        "supply"
    ],
    "wof:name":"Mike's Kites",
    "wof:placetype":"venue"
},
  "geometry": {"coordinates":[-80.96883099999999,29.14857],"type":"Point"}
}