{
  "type": "Feature",
  "properties": {
    "iso:country":"US",
    "sg:address":"1500 Beville Rd",
    "sg:city":"Daytona Beach",
    "sg:classifiers":[
        {
            "category":"Banks & Credit Unions",
            "subcategory":"Bank",
            "type":"Services"
        }
    ],
    "sg:phone":"+1 386 760 2759",
    "sg:postcode":"32114",
    "sg:province":"FL",
    "sg:tags":[
        "loan",
        "real estate"
    ],
    "wof:name":"Carteret Mortgage",
    "wof:placetype":"venue"
},
  "geometry": {"coordinates":[-81.03865999999999,29.171077],"type":"Point"}
}