{
  "type": "Feature",
  "properties": {
    "addr:full":"521 NE 119th St Miami FL 33161",
    "addr:housenumber":"521",
    "addr:postcode":"33161",
    "addr:street":"Ne 119Th St",
    "iso:country":"US",
    "sg:address":"521 NE 119th St",
    "sg:city":"Miami",
    "sg:classifiers":[
        {
            "category":"Manufacturing",
            "subcategory":"Printing",
            "type":"Manufacturing & Wholesale Goods"
        }
    ],
    "sg:phone":"+1 305 893 4106",
    "sg:postcode":"33161",
    "sg:province":"FL",
    "sg:tags":[
        "lithographic",
        "commercial"
    ],
    "wof:name":"Printing Solutions",
    "wof:placetype":"venue"
},
  "geometry": {"coordinates":[-80.186488,25.884863],"type":"Point"}
}