{
  "type": "Feature",
  "properties": {
    "addr:full":"2601 30th Ave N St Petersburg FL 33713",
    "addr:housenumber":"2601",
    "addr:postcode":"33713",
    "addr:street":"30Th Ave N",
    "iso:country":"US",
    "sg:address":"2601 30th Ave N",
    "sg:city":"St Petersburg",
    "sg:classifiers":[
        {
            "category":"Food & Beverages",
            "subcategory":"Groceries & Convenience Stores",
            "type":"Retail Goods"
        }
    ],
    "sg:phone":"+1 727 323 5407",
    "sg:postcode":"33713",
    "sg:province":"FL",
    "sg:tags":[
        "grocer"
    ],
    "wof:name":"Teresa's Food Store",
    "wof:placetype":"venue"
},
  "geometry": {"coordinates":[-82.669431,27.799234],"type":"Point"}
}