{
  "type": "Feature",
  "properties": {
    "iso:country":"US",
    "sg:address":"5405 Cypress Center Dr",
    "sg:city":"Tampa",
    "sg:classifiers":[
        {
            "category":"Real Estate",
            "subcategory":"Real Estate Agent",
            "type":"Services"
        }
    ],
    "sg:phone":"+1 813 636 8860",
    "sg:postcode":"33609",
    "sg:province":"FL",
    "sg:tags":[
        "consultant",
        "manager",
        "developer"
    ],
    "wof:name":"Rh Construction",
    "wof:placetype":"venue"
},
  "geometry": {"coordinates":[-82.535286,27.950501],"type":"Point"}
}