{
  "type": "Feature",
  "properties": {
    "addr:full":"8405 NW 53rd Ter Miami FL 33166",
    "addr:housenumber":"8405",
    "addr:postcode":"33166",
    "addr:street":"Nw 53Rd Ter",
    "iso:country":"US",
    "sg:address":"8405 NW 53rd Ter",
    "sg:city":"Miami",
    "sg:classifiers":[
        {
            "category":"Professional",
            "subcategory":"Accounting & Tax Preparation",
            "type":"Services"
        }
    ],
    "sg:phone":"+1 786 331 8555",
    "sg:postcode":"33166",
    "sg:province":"FL",
    "wof:name":"Caleb Brett Intertek",
    "wof:placetype":"venue"
},
  "geometry": {"coordinates":[-80.33460100000001,25.821601],"type":"Point"}
}