{
  "type": "Feature",
  "properties": {
    "iso:country":"US",
    "sg:address":"823 E 9th St",
    "sg:city":"Apopka",
    "sg:classifiers":[
        {
            "category":"Building & Trades",
            "subcategory":"Construction",
            "type":"Services"
        }
    ],
    "sg:phone":"+1 407 886 4526",
    "sg:postcode":"32703",
    "sg:province":"FL",
    "sg:tags":[
        "house"
    ],
    "wof:name":"Apopka Subwork",
    "wof:placetype":"venue"
},
  "geometry": {"coordinates":[-81.493162,28.667663],"type":"Point"}
}