{
  "type": "Feature",
  "properties": {
    "iso:country":"US",
    "sg:address":"3629 Reynolds Rd",
    "sg:city":"Lakeland",
    "sg:classifiers":[
        {
            "category":"Wholesale",
            "subcategory":"Machinery & Supplies",
            "type":"Manufacturing & Wholesale Goods"
        }
    ],
    "sg:phone":"+1 863 668 9364",
    "sg:postcode":"33803",
    "sg:province":"FL",
    "sg:tags":[
        "equipment",
        "welding"
    ],
    "wof:name":"Linde Gas",
    "wof:placetype":"venue"
},
  "geometry": {"coordinates":[-81.891268,27.999131],"type":"Point"}
}