{
  "type": "Feature",
  "properties": {
    "iso:country":"US",
    "sg:address":"11440 N Kendall Dr Ste 204",
    "sg:city":"Miami",
    "sg:classifiers":[
        {
            "category":"Professional",
            "subcategory":"Accounting & Tax Preparation",
            "type":"Services"
        }
    ],
    "sg:phone":"+1 305 598 2224",
    "sg:postcode":"33176",
    "sg:province":"FL",
    "sg:tags":[
        "accountant"
    ],
    "wof:name":"Neil J Mornick CPA",
    "wof:placetype":"venue"
},
  "geometry": {"coordinates":[-80.382103,25.6863],"type":"Point"}
}