{
  "type": "Feature",
  "properties": {
    "iso:country":"US",
    "sg:address":"631 E Call St",
    "sg:city":"Tallahassee",
    "sg:classifiers":[
        {
            "category":"Real Estate",
            "subcategory":"Real Estate Operator",
            "type":"Services"
        }
    ],
    "sg:phone":"+1 850 222 2864",
    "sg:postcode":"32301",
    "sg:province":"FL",
    "sg:tags":[
        "building",
        "apartment"
    ],
    "wof:name":"La Parc Apartments",
    "wof:placetype":"venue"
},
  "geometry": {"coordinates":[-84.27175800000001,30.443486],"type":"Point"}
}