{
  "type": "Feature",
  "properties": {
    "iso:country":"US",
    "sg:address":"3092 Indian River Dr NE",
    "sg:city":"Palm Bay",
    "sg:classifiers":[
        {
            "category":"Real Estate",
            "subcategory":"Real Estate Operator",
            "type":"Services"
        }
    ],
    "sg:phone":"+1 321 723 3353",
    "sg:postcode":"32905",
    "sg:province":"FL",
    "sg:tags":[
        "park",
        "trailer"
    ],
    "wof:name":"Palm Bay Estates",
    "wof:placetype":"venue"
},
  "geometry": {"coordinates":[-80.57970299999999,28.028171],"type":"Point"}
}