{
  "type": "Feature",
  "properties": {
    "addr:full":"7809 N Orleans Ave Tampa FL 33604",
    "addr:housenumber":"7809",
    "addr:postcode":"33604",
    "addr:street":"N Orleans Ave",
    "iso:country":"US",
    "sg:address":"7809 N Orleans Ave",
    "sg:city":"Tampa",
    "sg:classifiers":[
        {
            "category":"Building & Trades",
            "subcategory":"Construction",
            "type":"Services"
        }
    ],
    "sg:phone":"+1 813 932 4527",
    "sg:postcode":"33604",
    "sg:province":"FL",
    "sg:tags":[
        "contractor"
    ],
    "wof:name":"Meetze Remodeling & Builders",
    "wof:placetype":"venue"
},
  "geometry": {"coordinates":[-82.47319299999999,28.018839],"type":"Point"}
}