{
  "type": "Feature",
  "properties": {
    "iso:country":"US",
    "sg:address":"130 E Mercers Fernery Rd",
    "sg:city":"Deland",
    "sg:classifiers":[
        {
            "category":"Retail",
            "subcategory":"Auto Repair",
            "type":"Services"
        }
    ],
    "sg:phone":"+1 386 736 0669",
    "sg:postcode":"32724",
    "sg:province":"FL",
    "sg:tags":[
        "repairing",
        "automobile"
    ],
    "wof:name":"Auto Rage Inc",
    "wof:placetype":"venue"
},
  "geometry": {"coordinates":[-81.303932,29.064599],"type":"Point"}
}