{
  "type": "Feature",
  "properties": {
    "addr:full":"700 Lincoln Rd Miami Beach FL 33139",
    "addr:housenumber":"700",
    "addr:postcode":"33139",
    "addr:street":"Lincoln Rd",
    "iso:country":"US",
    "sg:address":"700 Lincoln Rd",
    "sg:city":"Miami Beach",
    "sg:classifiers":[
        {
            "category":"Restaurant",
            "type":"Food & Drink"
        }
    ],
    "sg:menulink":"http://www.allmenus.com/fl/miami-beach/241544-nexxt/menu/",
    "sg:phone":"+1 305 532 6643",
    "sg:postcode":"33139",
    "sg:province":"FL",
    "sg:tags":[
        "american"
    ],
    "wof:name":"Nexxt",
    "wof:placetype":"venue"
},
  "geometry": {"coordinates":[-80.13543300000001,25.790585],"type":"Point"}
}