{
  "type": "Feature",
  "properties": {
    "addr:full":"120 S Thornton Ave Orlando FL 32801",
    "addr:housenumber":"120",
    "addr:postcode":"32801",
    "addr:street":"S Thornton Ave",
    "iso:country":"US",
    "sg:address":"120 S Thornton Ave",
    "sg:city":"Orlando",
    "sg:classifiers":[
        {
            "category":"Wholesale",
            "subcategory":"Medical Equipment & Supplies",
            "type":"Manufacturing & Wholesale Goods"
        }
    ],
    "sg:phone":"+1 407 898 0332",
    "sg:postcode":"32801",
    "sg:province":"FL",
    "sg:tags":[
        "physician",
        "surgeon"
    ],
    "wof:name":"Datastream",
    "wof:placetype":"venue"
},
  "geometry": {"coordinates":[-81.36521500000001,28.540153],"type":"Point"}
}