{
  "type": "Feature",
  "properties": {
    "iso:country":"US",
    "sg:address":"9428 Navarre Pkwy",
    "sg:city":"Navarre",
    "sg:classifiers":[
        {
            "category":"Insurance",
            "subcategory":"Hazard Insurance",
            "type":"Services"
        }
    ],
    "sg:phone":"+1 850 939 0598",
    "sg:postcode":"32566",
    "sg:province":"FL",
    "sg:tags":[
        "commercial",
        "business"
    ],
    "wof:name":"The Public Adjusters",
    "wof:placetype":"venue"
},
  "geometry": {"coordinates":[-86.828329,30.409763],"type":"Point"}
}