{
  "type": "Feature",
  "properties": {
    "iso:country":"US",
    "sg:address":"670 N Orlando Ave",
    "sg:city":"Maitland",
    "sg:classifiers":[
        {
            "category":"Real Estate",
            "subcategory":"Real Estate Agent",
            "type":"Services"
        }
    ],
    "sg:phone":"+1 407 898 7005",
    "sg:postcode":"32751",
    "sg:province":"FL",
    "sg:tags":[
        "residential",
        "commercial",
        "broker",
        "es"
    ],
    "wof:name":"James Stockwell Corporation",
    "wof:placetype":"venue"
},
  "geometry": {"coordinates":[-81.361087,28.634264],"type":"Point"}
}