{
  "type": "Feature",
  "properties": {
    "iso:country":"US",
    "sg:address":"174 State St E",
    "sg:city":"Oldsmar",
    "sg:classifiers":[
        {
            "category":"Shopping",
            "subcategory":"Clothing, Apparel, & Fashions",
            "type":"Retail Goods"
        }
    ],
    "sg:phone":"+1 813 818 1800",
    "sg:postcode":"34677",
    "sg:province":"FL",
    "sg:tags":[
        "hair",
        "supply"
    ],
    "wof:name":"Samy Corp",
    "wof:placetype":"venue"
},
  "geometry": {"coordinates":[-82.66145299999999,28.036291],"type":"Point"}
}