{
  "type": "Feature",
  "properties": {
    "iso:country":"US",
    "sg:address":"140 N Florida Ave",
    "sg:city":"Inverness",
    "sg:classifiers":[
        {
            "category":"Home & Garden",
            "subcategory":"Building Materials",
            "type":"Retail Goods"
        },
        {
            "category":"Professional",
            "subcategory":"Printing & Photocopies",
            "type":"Services"
        },
        {
            "category":"Manufacturing",
            "subcategory":"Building Materials",
            "type":"Manufacturing & Wholesale Goods"
        }
    ],
    "sg:phone":"+1 352 726 6222",
    "sg:postcode":"34453",
    "sg:province":"FL",
    "sg:tags":[
        "door",
        "accessory",
        "garage",
        "opener",
        "doors",
        "frames",
        "door-overhead",
        "type"
    ],
    "wof:name":"K C Garage Doors & Openers",
    "wof:placetype":"venue"
},
  "geometry": {"coordinates":[-82.35230900000001,28.862015],"type":"Point"}
}