{
  "type": "Feature",
  "properties": {
    "iso:country":"US",
    "sg:address":"5180 Overseas Hwy",
    "sg:city":"Marathon",
    "sg:classifiers":[
        {
            "category":"Shopping",
            "type":"Retail Goods"
        }
    ],
    "sg:phone":"+1 305 743 8555",
    "sg:postcode":"33050",
    "sg:province":"FL",
    "sg:tags":[
        "equipment",
        "electronic"
    ],
    "wof:name":"Quantro Sensing",
    "wof:placetype":"venue"
},
  "geometry": {"coordinates":[-81.078793,24.715501],"type":"Point"}
}