{
  "type": "Feature",
  "properties": {
    "iso:country":"US",
    "sg:address":"2621 Exuma Rd",
    "sg:city":"West Palm Beach",
    "sg:classifiers":[
        {
            "category":"Local Transit",
            "type":"Transportation"
        }
    ],
    "sg:phone":"+1 561 966 6920",
    "sg:postcode":"33406",
    "sg:province":"FL",
    "wof:name":"Airport Town Car",
    "wof:placetype":"venue"
},
  "geometry": {"coordinates":[-80.08314300000001,26.646507],"type":"Point"}
}