{
  "type": "Feature",
  "properties": {
    "addr:full":"16309 US Hwy 19 Hudson FL 34667",
    "addr:housenumber":"16309",
    "addr:postcode":"34667",
    "addr:street":"Us Hwy 19",
    "iso:country":"US",
    "sg:address":"16309 US Hwy 19",
    "sg:city":"Hudson",
    "sg:classifiers":[
        {
            "category":"Professional",
            "type":"Services"
        },
        {
            "category":"Bars & Pubs",
            "type":"Food & Drink"
        }
    ],
    "sg:phone":"+1 727 868 3949",
    "sg:postcode":"34667",
    "sg:province":"FL",
    "sg:tags":[
        "drinking",
        "establishment"
    ],
    "wof:name":"Calender Girls",
    "wof:placetype":"venue"
},
  "geometry": {"coordinates":[-82.665537,28.393779],"type":"Point"}
}