{
  "type": "Feature",
  "properties": {
    "iso:country":"US",
    "sg:address":"1356 SE 18th St",
    "sg:city":"Ocala",
    "sg:classifiers":[
        {
            "category":"Building & Trades",
            "subcategory":"Construction",
            "type":"Services"
        }
    ],
    "sg:phone":"+1 352 622 3434",
    "sg:postcode":"34471",
    "sg:province":"FL",
    "sg:tags":[
        "contractor"
    ],
    "wof:name":"Mid Florida Seal & Stripe Inc",
    "wof:placetype":"venue"
},
  "geometry": {"coordinates":[-82.122726,29.170586],"type":"Point"}
}