{
  "type": "Feature",
  "properties": {
    "addr:full":"501 E Pennsylvania Ave Bonifay FL 32425",
    "addr:housenumber":"501",
    "addr:postcode":"32425",
    "addr:street":"E Pennsylvania Ave",
    "iso:country":"US",
    "sg:address":"501 E Pennsylvania Ave",
    "sg:city":"Bonifay",
    "sg:classifiers":[
        {
            "category":"Building & Trades",
            "subcategory":"Equipment Rental",
            "type":"Services"
        }
    ],
    "sg:phone":"+1 850 547 9340",
    "sg:postcode":"32425",
    "sg:province":"FL",
    "sg:tags":[
        "yard",
        "leasing",
        "store"
    ],
    "wof:name":"Hadas Rentals",
    "wof:placetype":"venue"
},
  "geometry": {"coordinates":[-85.67233299999999,30.79183],"type":"Point"}
}