{
  "type": "Feature",
  "properties": {
    "addr:full":"1248 Sunset Point Rd Clearwater FL 33755",
    "addr:housenumber":"1248",
    "addr:postcode":"33755",
    "addr:street":"Sunset Point Rd",
    "iso:country":"US",
    "sg:address":"1248 Sunset Point Rd",
    "sg:city":"Clearwater",
    "sg:classifiers":[
        {
            "category":"Building & Trades",
            "subcategory":"Plumbing",
            "type":"Services"
        }
    ],
    "sg:phone":"+1 727 449 2665",
    "sg:postcode":"33755",
    "sg:province":"FL",
    "sg:tags":[
        "system",
        "air",
        "heating",
        "refrigeration",
        "conditioning",
        "contractor",
        "an"
    ],
    "wof:name":"Southern Comfort Cooling Inc",
    "wof:placetype":"venue"
},
  "geometry": {"coordinates":[-82.78618899999999,27.990074],"type":"Point"}
}