{
  "type": "Feature",
  "properties": {
    "addr:full":"4704 Cadagua Dr Sebring FL 33872",
    "addr:housenumber":"4704",
    "addr:postcode":"33872",
    "addr:street":"Cadagua Dr",
    "iso:country":"US",
    "sg:address":"4704 Cadagua Dr",
    "sg:city":"Sebring",
    "sg:classifiers":[
        {
            "category":"Shopping",
            "subcategory":"Bicycles & Sporting Goods",
            "type":"Retail Goods"
        }
    ],
    "sg:phone":"+1 863 471 2772",
    "sg:postcode":"33872",
    "sg:province":"FL",
    "wof:name":"My Bike Connection",
    "wof:placetype":"venue"
},
  "geometry": {"coordinates":[-81.512658,27.531652],"type":"Point"}
}