{
  "type": "Feature",
  "properties": {
    "iso:country":"US",
    "sg:address":"2341 W Gulf Dr",
    "sg:city":"Sanibel",
    "sg:classifiers":[
        {
            "category":"Organizations",
            "subcategory":"Community Association",
            "type":"Services"
        }
    ],
    "sg:phone":"+1 239 472 1868",
    "sg:postcode":"33957",
    "sg:province":"FL",
    "wof:name":"Sanibel Cottages Condo Assn",
    "wof:placetype":"venue"
},
  "geometry": {"coordinates":[-82.07549400000001,26.423956],"type":"Point"}
}