{
  "type": "Feature",
  "properties": {
    "iso:country":"US",
    "sg:address":"214 N 2nd St",
    "sg:city":"Immokalee",
    "sg:classifiers":[
        {
            "category":"Place Of Worship",
            "subcategory":"Church",
            "type":"Public Place"
        },
        {
            "category":"Place Of Worship",
            "type":"Public Place"
        }
    ],
    "sg:phone":"+1 239 657 2516",
    "sg:postcode":"34142",
    "sg:province":"FL",
    "sg:tags":[
        "churches-baptist-general",
        "churches-baptist"
    ],
    "wof:name":"Iglesia Bautista De Jesucristo",
    "wof:placetype":"venue"
},
  "geometry": {"coordinates":[-81.418387,26.420588],"type":"Point"}
}