{
  "type": "Feature",
  "properties": {
    "iso:country":"US",
    "sg:address":"13611 S Tamiami Trl",
    "sg:city":"Fort Myers",
    "sg:classifiers":[
        {
            "category":"Autos & Motor Vehicles",
            "subcategory":"Fuel & Gas Station",
            "type":"Retail Goods"
        }
    ],
    "sg:phone":"+1 239 489 2524",
    "sg:postcode":"33912",
    "sg:province":"FL",
    "wof:name":"Mobil Marts",
    "wof:placetype":"venue"
},
  "geometry": {"coordinates":[-81.87130000000001,26.544701],"type":"Point"}
}