{
  "type": "Feature",
  "properties": {
    "addr:full":"600 N US Hwy 17/92 Longwood FL 32750",
    "addr:housenumber":"600;92",
    "addr:postcode":"32750",
    "addr:street":"N Us Hwy 17 /",
    "iso:country":"US",
    "sg:address":"600 N US Hwy 17/92",
    "sg:city":"Longwood",
    "sg:classifiers":[
        {
            "category":"Personal",
            "subcategory":"Tanning Parlor",
            "type":"Services"
        },
        {
            "category":"Personal",
            "type":"Services"
        }
    ],
    "sg:phone":"+1 407 831 1224",
    "sg:postcode":"32750",
    "sg:province":"FL",
    "sg:tags":[
        "salon"
    ],
    "wof:name":"Becky's Ultra Tan",
    "wof:placetype":"venue"
},
  "geometry": {"coordinates":[-81.326463,28.707098],"type":"Point"}
}