{
  "type": "Feature",
  "properties": {
    "addr:full":"30700 Wekiva River Rd Sorrento FL 32776",
    "addr:postcode":"30700;32776",
    "addr:street":"Wekiva River Rd",
    "iso:country":"US",
    "sg:address":"30700 Wekiva River Rd",
    "sg:city":"Sorrento",
    "sg:classifiers":[
        {
            "category":"Recreation",
            "type":"Entertainment"
        },
        {
            "category":"Travel",
            "subcategory":"Travel Agent",
            "type":"Entertainment"
        },
        {
            "category":"Travel",
            "subcategory":"Resort",
            "type":"Entertainment"
        },
        {
            "category":"Recreation",
            "subcategory":"Campground",
            "type":"Entertainment"
        }
    ],
    "sg:phone":"+1 866 671 0944",
    "sg:postcode":"32776",
    "sg:province":"FL",
    "sg:tags":[
        "camps-recreational",
        "travel-storage",
        "recreational",
        "park",
        "vehicle",
        "trailers-camping"
    ],
    "sg:website":"http://www.wekivafallsresort.com",
    "wof:name":"Wekiva Falls Camping & RV Resort",
    "wof:placetype":"venue"
},
  "geometry": {"coordinates":[-81.426177,28.795439],"type":"Point"}
}