{
  "type": "Feature",
  "properties": {
    "addr:full":"2625 W 78th St Hialeah FL 33016",
    "addr:housenumber":"2625",
    "addr:postcode":"33016",
    "addr:street":"W 78Th St",
    "iso:country":"US",
    "sg:address":"2625 W 78th St",
    "sg:city":"Hialeah",
    "sg:classifiers":[
        {
            "category":"Home & Garden",
            "subcategory":"Garden Supply",
            "type":"Retail Goods"
        }
    ],
    "sg:phone":"+1 305 557 2920",
    "sg:postcode":"33016",
    "sg:province":"FL",
    "sg:tags":[
        "plants-interior",
        "design",
        "nursery",
        "gardening",
        "maintenance"
    ],
    "sg:website":"www.laurenltd.com",
    "wof:name":"Lauren Ltd Inc",
    "wof:placetype":"venue"
},
  "geometry": {"coordinates":[-80.336502,25.8932],"type":"Point"}
}