{
  "type": "Feature",
  "properties": {
    "addr:full":"4405 Windlake Dr Niceville FL 32578",
    "addr:housenumber":"4405",
    "addr:postcode":"32578",
    "addr:street":"Windlake Dr",
    "iso:country":"US",
    "sg:address":"4405 Windlake Dr",
    "sg:city":"Niceville",
    "sg:classifiers":[
        {
            "category":"Professional",
            "subcategory":"Management & Consulting",
            "type":"Services"
        }
    ],
    "sg:phone":"+1 850 897 0539",
    "sg:postcode":"32578",
    "sg:province":"FL",
    "sg:tags":[
        "fuel"
    ],
    "wof:name":"USCS",
    "wof:placetype":"venue"
},
  "geometry": {"coordinates":[-86.42675199999999,30.467003],"type":"Point"}
}