{
  "type": "Feature",
  "properties": {
    "addr:full":"1371 S Ocean Blvd Pompano Beach FL 33062",
    "addr:housenumber":"1371",
    "addr:postcode":"33062",
    "addr:street":"S Ocean Blvd",
    "iso:country":"US",
    "sg:address":"1371 S Ocean Blvd",
    "sg:city":"Pompano Beach",
    "sg:classifiers":[
        {
            "category":"Health Services",
            "subcategory":"Doctor",
            "type":"Services"
        }
    ],
    "sg:phone":"+1 954 784 0930",
    "sg:postcode":"33062",
    "sg:province":"FL",
    "sg:tags":[
        "medical"
    ],
    "wof:name":"Albert B Stewart MD",
    "wof:placetype":"venue"
},
  "geometry": {"coordinates":[-80.091339,26.220702],"type":"Point"}
}