{
  "type": "Feature",
  "properties": {
    "iso:country":"US",
    "sg:address":"1512 Brentwood Hills Blvd",
    "sg:city":"Valrico",
    "sg:classifiers":[
        {
            "category":"Organizations",
            "subcategory":"Professional Association",
            "type":"Services"
        }
    ],
    "sg:phone":"+1 813 681 5266",
    "sg:postcode":"33594",
    "sg:province":"FL",
    "wof:name":"Brentwood Hills Home Owners",
    "wof:placetype":"venue"
},
  "geometry": {"coordinates":[-82.260957,27.9278],"type":"Point"}
}