{
  "type": "Feature",
  "properties": {
    "addr:full":"730 NW 59th St Miami FL 33127",
    "addr:housenumber":"730",
    "addr:postcode":"33127",
    "addr:street":"Nw 59Th St",
    "iso:country":"US",
    "sg:address":"730 NW 59th St",
    "sg:city":"Miami",
    "sg:classifiers":[
        {
            "category":"Wholesale",
            "subcategory":"Books, Periodicals, & Newspapers",
            "type":"Manufacturing & Wholesale Goods"
        }
    ],
    "sg:phone":"+1 305 456 1712",
    "sg:postcode":"33127",
    "sg:province":"FL",
    "sg:tags":[
        "publisher",
        "book"
    ],
    "wof:name":"Vetcoh Publishing",
    "wof:placetype":"venue"
},
  "geometry": {"coordinates":[-80.209007,25.82971],"type":"Point"}
}