{
  "type": "Feature",
  "properties": {
    "iso:country":"US",
    "sg:address":"103 SE 11th St",
    "sg:city":"Deerfield Beach",
    "sg:classifiers":[
        {
            "category":"Building & Trades",
            "subcategory":"Construction",
            "type":"Services"
        }
    ],
    "sg:phone":"+1 954 698 0254",
    "sg:postcode":"33441",
    "sg:province":"FL",
    "sg:tags":[
        "tile",
        "marble",
        "contractor"
    ],
    "wof:name":"Abbott Tile & Marble Inc",
    "wof:placetype":"venue"
},
  "geometry": {"coordinates":[-80.103371,26.303395],"type":"Point"}
}