{
  "type": "Feature",
  "properties": {
    "iso:country":"US",
    "sg:address":"4285 W Atlantic Ave",
    "sg:city":"Delray Beach",
    "sg:classifiers":[
        {
            "category":"Restaurant",
            "type":"Food & Drink"
        }
    ],
    "sg:menulink":"http://www.allmenus.com/fl/boynton-beach-delray-beach/283827-la-bamba/menu/",
    "sg:phone":"+1 561 499 7996",
    "sg:postcode":"33445",
    "sg:province":"FL",
    "sg:tags":[
        "mexican",
        "spanish"
    ],
    "wof:name":"LA Bamba",
    "wof:placetype":"venue"
},
  "geometry": {"coordinates":[-80.11018199999999,26.459781],"type":"Point"}
}