{
  "type": "Feature",
  "properties": {
    "iso:country":"US",
    "sg:address":"5315 Jammes Rd",
    "sg:city":"Jacksonville",
    "sg:classifiers":[
        {
            "category":"Food & Beverages",
            "subcategory":"Groceries & Convenience Stores",
            "type":"Retail Goods"
        }
    ],
    "sg:phone":"+1 904 778 7289",
    "sg:postcode":"32210",
    "sg:province":"FL",
    "wof:name":"Jammes Food Store",
    "wof:placetype":"venue"
},
  "geometry": {"coordinates":[-81.747197,30.249226],"type":"Point"}
}