{
  "type": "Feature",
  "properties": {
    "addr:full":"4151 N Andrews Ave Fort Lauderdale FL 33309",
    "addr:housenumber":"4151",
    "addr:postcode":"33309",
    "addr:street":"N Andrews Ave",
    "iso:country":"US",
    "sg:address":"4151 N Andrews Ave",
    "sg:city":"Fort Lauderdale",
    "sg:classifiers":[
        {
            "category":"Shopping",
            "type":"Retail Goods"
        }
    ],
    "sg:phone":"+1 954 564 8133",
    "sg:postcode":"33309",
    "sg:province":"FL",
    "sg:tags":[
        "orthopedic",
        "appliance"
    ],
    "wof:name":"Broward Orthopedics",
    "wof:placetype":"venue"
},
  "geometry": {"coordinates":[-80.146872,26.178014],"type":"Point"}
}