{
  "type": "Feature",
  "properties": {
    "iso:country":"US",
    "sg:address":"1114 94th Ave N",
    "sg:city":"St Petersburg",
    "sg:classifiers":[
        {
            "category":"Health Services",
            "subcategory":"Health Practitioner",
            "type":"Services"
        }
    ],
    "sg:phone":"+1 727 577 9006",
    "sg:postcode":"33702",
    "sg:province":"FL",
    "sg:tags":[
        "therapist",
        "physical"
    ],
    "wof:name":"Therapy Playhouse",
    "wof:placetype":"venue"
},
  "geometry": {"coordinates":[-82.64874,27.85743],"type":"Point"}
}