{
  "type": "Feature",
  "properties": {
    "iso:country":"US",
    "sg:address":"26221 Woodlyn Dr",
    "sg:city":"Bonita Springs",
    "sg:classifiers":[
        {
            "category":"Banks & Credit Unions",
            "subcategory":"Financial Services",
            "type":"Services"
        }
    ],
    "sg:phone":"+1 239 947 7488",
    "sg:postcode":"34134",
    "sg:province":"FL",
    "sg:tags":[
        "trust",
        "management"
    ],
    "wof:name":"Judy L Oggero Living Trust",
    "wof:placetype":"venue"
},
  "geometry": {"coordinates":[-81.829167,26.355819],"type":"Point"}
}