{
  "type": "Feature",
  "properties": {
    "addr:full":"1919 Courtney Dr Fort Myers FL 33901",
    "addr:housenumber":"1919",
    "addr:postcode":"33901",
    "addr:street":"Courtney Dr",
    "iso:country":"US",
    "sg:address":"1919 Courtney Dr",
    "sg:city":"Fort Myers",
    "sg:classifiers":[
        {
            "category":"Professional",
            "subcategory":"Employment Agencies",
            "type":"Services"
        }
    ],
    "sg:phone":"+1 239 936 2440",
    "sg:postcode":"33901",
    "sg:province":"FL",
    "sg:tags":[
        "opportunity"
    ],
    "wof:name":"Snelling Personnel Svc",
    "wof:placetype":"venue"
},
  "geometry": {"coordinates":[-81.874167,26.602015],"type":"Point"}
}