{
  "type": "Feature",
  "properties": {
    "iso:country":"US",
    "sg:address":"5753 Beneva Rd",
    "sg:city":"Sarasota",
    "sg:classifiers":[
        {
            "category":"Professional",
            "subcategory":"Business Services",
            "type":"Services"
        }
    ],
    "sg:phone":"+1 941 922 7297",
    "sg:postcode":"34233",
    "sg:province":"FL",
    "sg:tags":[
        "interior",
        "consultant",
        "design",
        "decorator"
    ],
    "wof:name":"Interiors By Jennifer Sweat",
    "wof:placetype":"venue"
},
  "geometry": {"coordinates":[-82.497536,27.269596],"type":"Point"}
}