{
  "type": "Feature",
  "properties": {
    "iso:country":"US",
    "sg:address":"2595 NW 4th Ct",
    "sg:city":"Fort Lauderdale",
    "sg:classifiers":[
        {
            "category":"Manufacturing",
            "subcategory":"Tools & Machinery",
            "type":"Manufacturing & Wholesale Goods"
        }
    ],
    "sg:phone":"+1 954 792 0449",
    "sg:postcode":"33311",
    "sg:province":"FL",
    "sg:tags":[
        "mfg",
        "equipment",
        "industrial",
        "vehicle",
        "space"
    ],
    "wof:name":"Eagle Precision Co",
    "wof:placetype":"venue"
},
  "geometry": {"coordinates":[-80.17735999999999,26.126309],"type":"Point"}
}