{
  "type": "Feature",
  "properties": {
    "iso:country":"US",
    "sg:address":"365 Stan Dr",
    "sg:city":"Melbourne",
    "sg:classifiers":[
        {
            "category":"Retail",
            "subcategory":"Auto Repair",
            "type":"Services"
        }
    ],
    "sg:phone":"+1 321 722 0228",
    "sg:postcode":"32904",
    "sg:province":"FL",
    "sg:tags":[
        "body",
        "automobile",
        "painting"
    ],
    "wof:name":"Explicit Customs",
    "wof:placetype":"venue"
},
  "geometry": {"coordinates":[-80.69478100000001,28.100244],"type":"Point"}
}