{
  "type": "Feature",
  "properties": {
    "iso:country":"US",
    "sg:address":"240 S Atlantic Ave",
    "sg:city":"Ormond Beach",
    "sg:classifiers":[
        {
            "category":"Shopping",
            "subcategory":"Gifts & Souvenirs",
            "type":"Retail Goods"
        }
    ],
    "sg:phone":"+1 386 677 2489",
    "sg:postcode":"32176",
    "sg:province":"FL",
    "sg:tags":[
        "shop"
    ],
    "wof:name":"Ormond Gift Ctr",
    "wof:placetype":"venue"
},
  "geometry": {"coordinates":[-81.03704399999999,29.285578],"type":"Point"}
}