{
  "type": "Feature",
  "properties": {
    "addr:full":"5995 Deer Ln Cocoa FL 32927",
    "addr:housenumber":"5995",
    "addr:postcode":"32927",
    "addr:street":"Deer Ln",
    "iso:country":"US",
    "sg:address":"5995 Deer Ln",
    "sg:city":"Cocoa",
    "sg:classifiers":[
        {
            "category":"Building & Trades",
            "subcategory":"Construction",
            "type":"Services"
        }
    ],
    "sg:phone":"+1 321 634 5419",
    "sg:postcode":"32927",
    "sg:province":"FL",
    "sg:tags":[
        "floor",
        "laying",
        "contractor"
    ],
    "wof:name":"Four Star Floor Sanding",
    "wof:placetype":"venue"
},
  "geometry": {"coordinates":[-80.813157,28.464222],"type":"Point"}
}