{
  "type": "Feature",
  "properties": {
    "iso:country":"US",
    "sg:address":"2407 NW 54th St",
    "sg:city":"Miami",
    "sg:classifiers":[
        {
            "category":"Food & Beverages",
            "subcategory":"Groceries & Convenience Stores",
            "type":"Retail Goods"
        }
    ],
    "sg:phone":"+1 305 635 4771",
    "sg:postcode":"33142",
    "sg:province":"FL",
    "sg:tags":[
        "grocer"
    ],
    "wof:name":"Charlies'grocery",
    "wof:placetype":"venue"
},
  "geometry": {"coordinates":[-80.23699999999999,25.8239],"type":"Point"}
}