{
  "type": "Feature",
  "properties": {
    "iso:country":"US",
    "sg:address":"613 School House Rd",
    "sg:city":"Lakeland",
    "sg:classifiers":[
        {
            "category":"Building & Trades",
            "subcategory":"Construction",
            "type":"Services"
        }
    ],
    "sg:phone":"+1 863 294 7946",
    "sg:postcode":"33813",
    "sg:province":"FL",
    "sg:tags":[
        "coping",
        "plastering",
        "tiling",
        "pool",
        "swimming"
    ],
    "wof:name":"Paradise Pool Svc & Repairs",
    "wof:placetype":"venue"
},
  "geometry": {"coordinates":[-81.964671,27.967682],"type":"Point"}
}