{
  "type": "Feature",
  "properties": {
    "iso:country":"US",
    "sg:address":"1014 Florida Ave",
    "sg:city":"Rockledge",
    "sg:classifiers":[
        {
            "category":"Health Services",
            "subcategory":"Chiropractor",
            "type":"Services"
        }
    ],
    "sg:phone":"+1 321 631 2225",
    "sg:postcode":"32955",
    "sg:province":"FL",
    "wof:name":"Rockledge Family Chiropractic",
    "wof:placetype":"venue"
},
  "geometry": {"coordinates":[-80.72600199999999,28.346736],"type":"Point"}
}