{
  "type": "Feature",
  "properties": {
    "iso:country":"US",
    "sg:address":"4244 Lillian Hall Ln",
    "sg:city":"Orlando",
    "sg:classifiers":[
        {
            "category":"Building & Trades",
            "subcategory":"Landscaping Services",
            "type":"Services"
        }
    ],
    "sg:phone":"+1 407 275 2391",
    "sg:postcode":"32812",
    "sg:province":"FL",
    "sg:tags":[
        "landscape",
        "contractor"
    ],
    "wof:name":"James F Mc Cann Inc",
    "wof:placetype":"venue"
},
  "geometry": {"coordinates":[-81.324113,28.495018],"type":"Point"}
}