{
  "type": "Feature",
  "properties": {
    "iso:country":"US",
    "sg:address":"57 Cypress Dr",
    "sg:city":"Palm Harbor",
    "sg:classifiers":[
        {
            "category":"Building & Trades",
            "subcategory":"Construction",
            "type":"Services"
        }
    ],
    "sg:phone":"+1 727 937 0992",
    "sg:postcode":"34684",
    "sg:province":"FL",
    "sg:tags":[
        "heavy"
    ],
    "wof:name":"Kens Irrigation Systems",
    "wof:placetype":"venue"
},
  "geometry": {"coordinates":[-82.734252,28.107724],"type":"Point"}
}