{
  "type": "Feature",
  "properties": {
    "iso:country":"US",
    "sg:address":"3249 Baldwin Dr W",
    "sg:city":"Tallahassee",
    "sg:classifiers":[
        {
            "category":"Organizations",
            "subcategory":"Community Association",
            "type":"Services"
        }
    ],
    "sg:phone":"+1 850 893 5860",
    "sg:postcode":"32309",
    "sg:province":"FL",
    "wof:name":"Chapter 181",
    "wof:placetype":"venue"
},
  "geometry": {"coordinates":[-84.226415,30.505398],"type":"Point"}
}