{
  "type": "Feature",
  "properties": {
    "iso:country":"US",
    "sg:address":"31900 Carriage House Rd",
    "sg:city":"Zephyrhills",
    "sg:classifiers":[
        {
            "category":"Building & Trades",
            "subcategory":"Cleaning & Sanitation",
            "type":"Services"
        }
    ],
    "sg:phone":"+1 813 782 9337",
    "sg:postcode":"33543",
    "sg:province":"FL",
    "sg:tags":[
        "maintenance"
    ],
    "wof:name":"Marsha L & Huey Anderson",
    "wof:placetype":"venue"
},
  "geometry": {"coordinates":[-82.28582,28.215818],"type":"Point"}
}