{
  "type": "Feature",
  "properties": {
    "addr:full":"2500 W 84th St Hialeah FL 33016",
    "addr:housenumber":"2500",
    "addr:postcode":"33016",
    "addr:street":"W 84Th St",
    "iso:country":"US",
    "sg:address":"2500 W 84th St",
    "sg:city":"Hialeah",
    "sg:classifiers":[
        {
            "category":"Wholesale",
            "subcategory":"Apparel",
            "type":"Manufacturing & Wholesale Goods"
        }
    ],
    "sg:phone":"+1 305 362 6223",
    "sg:postcode":"33016",
    "sg:province":"FL",
    "sg:tags":[
        "clothing"
    ],
    "wof:name":"Chameleon Import & Export",
    "wof:placetype":"venue"
},
  "geometry": {"coordinates":[-80.333799,25.89752],"type":"Point"}
}