{
  "type": "Feature",
  "properties": {
    "iso:country":"US",
    "sg:address":"7311 Marsh Ter",
    "sg:city":"Port St Lucie",
    "sg:classifiers":[
        {
            "category":"Real Estate",
            "subcategory":"Real Estate Agent",
            "type":"Services"
        }
    ],
    "sg:phone":"+1 772 460 9344",
    "sg:postcode":"34986",
    "sg:province":"FL",
    "wof:name":"Antio Real Estate Inc",
    "wof:placetype":"venue"
},
  "geometry": {"coordinates":[-80.430543,27.335654],"type":"Point"}
}