{
  "type": "Feature",
  "properties": {
    "addr:full":"2494 Tomoka Farms Rd Port Orange FL 32128",
    "addr:housenumber":"2494",
    "addr:postcode":"32128",
    "addr:street":"Tomoka Farms Rd",
    "iso:country":"US",
    "sg:address":"2494 Tomoka Farms Rd",
    "sg:city":"Port Orange",
    "sg:classifiers":[
        {
            "category":"Wholesale",
            "subcategory":"Farm Supplies",
            "type":"Manufacturing & Wholesale Goods"
        }
    ],
    "sg:phone":"+1 386 761 3155",
    "sg:postcode":"32128",
    "sg:province":"FL",
    "sg:tags":[
        "feed"
    ],
    "wof:name":"Tomoka Farms Feed & Supply",
    "wof:placetype":"venue"
},
  "geometry": {"coordinates":[-81.06849,29.084748],"type":"Point"}
}