{
  "type": "Feature",
  "properties": {
    "addr:full":"450 W Herman St Pensacola FL 32505",
    "addr:housenumber":"450",
    "addr:postcode":"32505",
    "addr:street":"W Herman St",
    "iso:country":"US",
    "sg:address":"450 W Herman St",
    "sg:city":"Pensacola",
    "sg:classifiers":[
        {
            "category":"Professional",
            "subcategory":"Business Services",
            "type":"Services"
        }
    ],
    "sg:phone":"+1 850 438 1166",
    "sg:postcode":"32505",
    "sg:province":"FL",
    "wof:name":"Rockys Collision Center Inc",
    "wof:placetype":"venue"
},
  "geometry": {"coordinates":[-87.23926899999999,30.448982],"type":"Point"}
}