{
  "type": "Feature",
  "properties": {
    "addr:full":"853 Sawyer Run Ln Ponte Vedra Beach FL 32082",
    "addr:housenumber":"853",
    "addr:postcode":"32082",
    "addr:street":"Sawyer Run Ln",
    "iso:country":"US",
    "sg:address":"853 Sawyer Run Ln",
    "sg:city":"Ponte Vedra Beach",
    "sg:classifiers":[
        {
            "category":"Building & Trades",
            "subcategory":"Construction",
            "type":"Services"
        }
    ],
    "sg:phone":"+1 904 273 9180",
    "sg:postcode":"32082",
    "sg:province":"FL",
    "sg:tags":[
        "hanging",
        "contractor"
    ],
    "wof:name":"Minds Eye Decorating Inc",
    "wof:placetype":"venue"
},
  "geometry": {"coordinates":[-81.378006,30.142837],"type":"Point"}
}