{
  "type": "Feature",
  "properties": {
    "addr:full":"615 SW 5th Ave Hallandale FL 33009",
    "addr:housenumber":"615",
    "addr:postcode":"33009",
    "addr:street":"Sw 5Th Ave",
    "iso:country":"US",
    "sg:address":"615 SW 5th Ave",
    "sg:city":"Hallandale",
    "sg:classifiers":[
        {
            "category":"Communications",
            "subcategory":"Film & Video Production",
            "type":"Services"
        }
    ],
    "sg:phone":"+1 954 456 8043",
    "sg:postcode":"33009",
    "sg:province":"FL",
    "sg:tags":[
        "motion",
        "picture",
        "distribution"
    ],
    "wof:name":"Take Two Productions",
    "wof:placetype":"venue"
},
  "geometry": {"coordinates":[-80.15324099999999,25.979016],"type":"Point"}
}