{
  "type": "Feature",
  "properties": {
    "iso:country":"US",
    "sg:address":"800 S Nova Rd",
    "sg:city":"Ormond Beach",
    "sg:classifiers":[
        {
            "category":"Travel",
            "subcategory":"Travel Agent",
            "type":"Entertainment"
        }
    ],
    "sg:phone":"+1 386 615 1200",
    "sg:postcode":"32174",
    "sg:province":"FL",
    "sg:tags":[
        "agency",
        "bureau"
    ],
    "wof:name":"A B Sea Cruises",
    "wof:placetype":"venue"
},
  "geometry": {"coordinates":[-81.07325299999999,29.256677],"type":"Point"}
}