{
  "type": "Feature",
  "properties": {
    "addr:full":"11101 SW 72nd Ct Miami FL 33156",
    "addr:housenumber":"11101",
    "addr:postcode":"33156",
    "addr:street":"Sw 72Nd Ct",
    "iso:country":"US",
    "sg:address":"11101 SW 72nd Ct",
    "sg:city":"Miami",
    "sg:classifiers":[
        {
            "category":"Freight",
            "type":"Transportation"
        }
    ],
    "sg:phone":"+1 305 662 5570",
    "sg:postcode":"33156",
    "sg:province":"FL",
    "sg:tags":[
        "delivery"
    ],
    "sg:website":"www.grocerytaxi.com",
    "wof:name":"GROCERYTAXI.COM",
    "wof:placetype":"venue"
},
  "geometry": {"coordinates":[-80.31149499999999,25.666769],"type":"Point"}
}