{
  "type": "Feature",
  "properties": {
    "iso:country":"US",
    "sg:address":"20693 NW 27th Ter",
    "sg:city":"Boca Raton",
    "sg:classifiers":[
        {
            "category":"Health Services",
            "subcategory":"Doctor",
            "type":"Services"
        }
    ],
    "sg:phone":"+1 561 482 2392",
    "sg:postcode":"33434",
    "sg:province":"FL",
    "sg:tags":[
        "medical"
    ],
    "wof:name":"Charles V Benoit MD",
    "wof:placetype":"venue"
},
  "geometry": {"coordinates":[-80.142459,26.370095],"type":"Point"}
}