{
  "type": "Feature",
  "properties": {
    "iso:country":"US",
    "sg:address":"4537 Ponce de Leon Blvd",
    "sg:city":"Coral Gables",
    "sg:classifiers":[
        {
            "category":"Education",
            "subcategory":"Special Training",
            "type":"Public Place"
        },
        {
            "category":"Shopping",
            "subcategory":"Musical Instruments",
            "type":"Retail Goods"
        }
    ],
    "sg:phone":"+1 305 740 9400",
    "sg:postcode":"33134",
    "sg:province":"FL",
    "sg:tags":[
        "sheet",
        "instruction",
        "music"
    ],
    "wof:name":"Allegro Music Center",
    "wof:placetype":"venue"
},
  "geometry": {"coordinates":[-80.26055599999999,25.728522],"type":"Point"}
}