{
  "type": "Feature",
  "properties": {
    "iso:country":"US",
    "sg:address":"400 SE 2nd Ave Fl 3",
    "sg:city":"Miami",
    "sg:classifiers":[
        {
            "category":"Retail",
            "subcategory":"Event Space",
            "type":"Services"
        },
        {
            "category":"Cinema",
            "subcategory":"Movie Theater",
            "type":"Entertainment"
        }
    ],
    "sg:phone":"+1 305 350 7910",
    "sg:postcode":"33131",
    "sg:province":"FL",
    "sg:tags":[
        "venue"
    ],
    "wof:name":"James L Knight International Center",
    "wof:placetype":"venue"
},
  "geometry": {"coordinates":[-80.190102,25.771099],"type":"Point"}
}