{
  "type": "Feature",
  "properties": {
    "addr:full":"7216 US Hwy 1 Port Saint Lucie FL 34952",
    "addr:housenumber":"7216",
    "addr:postcode":"34952",
    "addr:street":"Us Hwy 1",
    "iso:country":"US",
    "sg:address":"7216 US Hwy 1",
    "sg:city":"Port Saint Lucie",
    "sg:classifiers":[
        {
            "category":"Shopping",
            "subcategory":"Computers & Home Electronics",
            "type":"Retail Goods"
        }
    ],
    "sg:phone":"+1 772 878 5535",
    "sg:postcode":"34952",
    "sg:province":"FL",
    "wof:name":"South Florida Video Trading",
    "wof:placetype":"venue"
},
  "geometry": {"coordinates":[-80.322513,27.329906],"type":"Point"}
}