{
  "type": "Feature",
  "properties": {
    "iso:country":"US",
    "sg:address":"101 Southhall Ln",
    "sg:city":"Maitland",
    "sg:classifiers":[
        {
            "category":"Wholesale",
            "subcategory":"Durable Goods & Equipment",
            "type":"Manufacturing & Wholesale Goods"
        }
    ],
    "sg:phone":"+1 407 667 4779",
    "sg:postcode":"32751",
    "sg:province":"FL",
    "sg:tags":[
        "importer"
    ],
    "wof:name":"Meyer & Partner Intl Inc",
    "wof:placetype":"venue"
},
  "geometry": {"coordinates":[-81.396467,28.62717],"type":"Point"}
}