{
  "type": "Feature",
  "properties": {
    "iso:country":"US",
    "sg:address":"2162 Cypress Landing Dr",
    "sg:city":"Atlantic Beach",
    "sg:classifiers":[
        {
            "category":"Shopping",
            "subcategory":"Catalog Store",
            "type":"Retail Goods"
        }
    ],
    "sg:phone":"+1 904 247 3450",
    "sg:postcode":"32233",
    "sg:province":"FL",
    "wof:name":"Wildas Homebased",
    "wof:placetype":"venue"
},
  "geometry": {"coordinates":[-81.420271,30.350321],"type":"Point"}
}