{
  "type": "Feature",
  "properties": {
    "iso:country":"US",
    "sg:address":"1150 NE 191st St",
    "sg:city":"Miami",
    "sg:classifiers":[
        {
            "category":"Real Estate",
            "subcategory":"Real Estate Operator",
            "type":"Services"
        },
        {
            "category":"Organizations",
            "subcategory":"Community Association",
            "type":"Services"
        }
    ],
    "sg:phone":"+1 305 949 3284",
    "sg:postcode":"33179",
    "sg:province":"FL",
    "sg:tags":[
        "condominium"
    ],
    "wof:name":"Riviera Condominium Apartments",
    "wof:placetype":"venue"
},
  "geometry": {"coordinates":[-80.175647,25.951074],"type":"Point"}
}