{
  "type": "Feature",
  "properties": {
    "addr:full":"1411 S Hiawassee Rd Orlando FL 32835",
    "addr:housenumber":"1411",
    "addr:postcode":"32835",
    "addr:street":"S Hiawassee Rd",
    "iso:country":"US",
    "sg:address":"1411 S Hiawassee Rd",
    "sg:city":"Orlando",
    "sg:classifiers":[
        {
            "category":"Restaurant",
            "type":"Food & Drink"
        }
    ],
    "sg:menulink":"http://www.allmenus.com/fl/winter-garden-ocoee/187523-mcdonalds/menu/",
    "sg:phone":"+1 407 298 9366",
    "sg:postcode":"32835",
    "sg:province":"FL",
    "sg:tags":[
        "burger",
        "american"
    ],
    "wof:name":"McDonald's",
    "wof:placetype":"venue"
},
  "geometry": {"coordinates":[-81.470564,28.524438],"type":"Point"}
}