{
  "type": "Feature",
  "properties": {
    "iso:country":"US",
    "sg:address":"26833 W Dixie Hwy",
    "sg:city":"Homestead",
    "sg:classifiers":[
        {
            "category":"Personal",
            "subcategory":"Beauty Salon",
            "type":"Services"
        }
    ],
    "sg:phone":"+1 305 258 0940",
    "sg:postcode":"33032",
    "sg:province":"FL",
    "wof:name":"Heights Of Beauty",
    "wof:placetype":"venue"
},
  "geometry": {"coordinates":[-80.429953,25.517671],"type":"Point"}
}