{
  "type": "Feature",
  "properties": {
    "addr:full":"3315 Co Rd 97 Cantonment FL 32533",
    "addr:housenumber":"3315;97",
    "addr:postcode":"32533",
    "addr:street":"Co Rd",
    "iso:country":"US",
    "sg:address":"3315 Co Rd 97",
    "sg:city":"Cantonment",
    "sg:classifiers":[
        {
            "category":"Shopping",
            "type":"Retail Goods"
        }
    ],
    "sg:phone":"+1 850 476 8356",
    "sg:postcode":"32533",
    "sg:province":"FL",
    "sg:tags":[
        "flag"
    ],
    "wof:name":"Flag Co",
    "wof:placetype":"venue"
},
  "geometry": {"coordinates":[-87.330555,30.550543],"type":"Point"}
}