{
  "type": "Feature",
  "properties": {
    "iso:country":"US",
    "sg:address":"2499 Palm Ridge Rd",
    "sg:city":"Sanibel",
    "sg:classifiers":[
        {
            "category":"Health Services",
            "subcategory":"Doctor",
            "type":"Services"
        },
        {
            "category":"Health Services",
            "subcategory":"Clinic",
            "type":"Services"
        },
        {
            "category":"Health Services",
            "subcategory":"Health Practitioner",
            "type":"Services"
        }
    ],
    "sg:phone":"+1 239 395 2005",
    "sg:postcode":"33957",
    "sg:province":"FL",
    "sg:tags":[
        "physician",
        "family",
        "medical",
        "practice",
        "surgeons",
        "therapist",
        "welfare",
        "medicine",
        "physical"
    ],
    "wof:name":"Sanibel Medical Clinic",
    "wof:placetype":"venue"
},
  "geometry": {"coordinates":[-82.080276,26.43981],"type":"Point"}
}