{
  "type": "Feature",
  "properties": {
    "addr:full":"7301 W Oakland Park Blvd Fort Lauderdale FL 33319",
    "addr:housenumber":"7301",
    "addr:postcode":"33319",
    "addr:street":"W Oakland Park Blvd",
    "iso:country":"US",
    "sg:address":"7301 W Oakland Park Blvd",
    "sg:city":"Fort Lauderdale",
    "sg:classifiers":[
        {
            "category":"Professional",
            "subcategory":"Business Services",
            "type":"Services"
        }
    ],
    "sg:phone":"+1 954 371 1800",
    "sg:postcode":"33319",
    "sg:province":"FL",
    "sg:tags":[
        "call",
        "center"
    ],
    "wof:name":"Great Vacations Dest",
    "wof:placetype":"venue"
},
  "geometry": {"coordinates":[-80.24690200000001,26.165947],"type":"Point"}
}