{
  "type": "Feature",
  "properties": {
    "addr:full":"858 SW Kappa Ave Port St Lucie FL 34953",
    "addr:housenumber":"858",
    "addr:postcode":"34953",
    "addr:street":"Sw Kappa Ave",
    "iso:country":"US",
    "sg:address":"858 SW Kappa Ave",
    "sg:city":"Port St Lucie",
    "sg:classifiers":[
        {
            "category":"Wholesale",
            "subcategory":"Metals & Minerals",
            "type":"Manufacturing & Wholesale Goods"
        }
    ],
    "sg:phone":"+1 772 621 7661",
    "sg:postcode":"34953",
    "sg:province":"FL",
    "sg:tags":[
        "aluminum"
    ],
    "wof:name":"All Way Aluminum Inc",
    "wof:placetype":"venue"
},
  "geometry": {"coordinates":[-80.373082,27.220577],"type":"Point"}
}