{
  "type": "Feature",
  "properties": {
    "iso:country":"US",
    "sg:address":"291 Bentley Dr",
    "sg:city":"Longwood",
    "sg:classifiers":[
        {
            "category":"Building & Trades",
            "subcategory":"Construction",
            "type":"Services"
        }
    ],
    "sg:phone":"+1 407 869 8486",
    "sg:postcode":"32779",
    "sg:province":"FL",
    "sg:tags":[
        "heavy"
    ],
    "wof:name":"Liquid Sunshine LLC",
    "wof:placetype":"venue"
},
  "geometry": {"coordinates":[-81.44282800000001,28.687913],"type":"Point"}
}