{
  "type": "Feature",
  "properties": {
    "addr:full":"6880 Palm Grove Ct West Palm Beach FL 33418",
    "addr:housenumber":"6880",
    "addr:postcode":"33418",
    "addr:street":"Palm Grove Ct",
    "iso:country":"US",
    "sg:address":"6880 Palm Grove Ct",
    "sg:city":"West Palm Beach",
    "sg:classifiers":[
        {
            "category":"Wholesale",
            "subcategory":"Electrical",
            "type":"Manufacturing & Wholesale Goods"
        }
    ],
    "sg:phone":"+1 561 296 1123",
    "sg:postcode":"33418",
    "sg:province":"FL",
    "sg:tags":[
        "control",
        "security",
        "system"
    ],
    "wof:name":"Eastpointe Security Hood Road",
    "wof:placetype":"venue"
},
  "geometry": {"coordinates":[-80.14238400000001,26.878613],"type":"Point"}
}