{
  "type": "Feature",
  "properties": {
    "iso:country":"US",
    "sg:address":"100 Faulkner St",
    "sg:city":"New Smyrna Beach",
    "sg:classifiers":[
        {
            "category":"Insurance",
            "subcategory":"Insurance Agent",
            "type":"Services"
        }
    ],
    "sg:phone":"+1 386 424 9010",
    "sg:postcode":"32168",
    "sg:province":"FL",
    "wof:name":"New York Life Insurance Co",
    "wof:placetype":"venue"
},
  "geometry": {"coordinates":[-80.92321200000001,29.025457],"type":"Point"}
}