{
  "type": "Feature",
  "properties": {
    "addr:full":"8726 State Rd 54 New Port Richey FL 34655",
    "addr:housenumber":"8726;54",
    "addr:postcode":"34655",
    "addr:street":"State Rd",
    "iso:country":"US",
    "sg:address":"8726 State Rd 54",
    "sg:city":"New Port Richey",
    "sg:classifiers":[
        {
            "category":"Banks & Credit Unions",
            "subcategory":"Investment Brokerage",
            "type":"Services"
        }
    ],
    "sg:phone":"+1 727 372 1940",
    "sg:postcode":"34655",
    "sg:province":"FL",
    "sg:tags":[
        "consultant",
        "planning",
        "financial"
    ],
    "wof:name":"Baikcom Associates Inc",
    "wof:placetype":"venue"
},
  "geometry": {"coordinates":[-82.66677199999999,28.206235],"type":"Point"}
}