{
  "type": "Feature",
  "properties": {
    "iso:country":"US",
    "sg:address":"8702 Bay Hill Blvd",
    "sg:city":"Orlando",
    "sg:classifiers":[
        {
            "category":"Professional",
            "subcategory":"Management & Consulting",
            "type":"Services"
        }
    ],
    "sg:phone":"+1 407 876 8258",
    "sg:postcode":"32819",
    "sg:province":"FL",
    "sg:tags":[
        "consultant"
    ],
    "sg:website":"http://www.clarityconsulting.com",
    "wof:name":"Connellan Group Inc",
    "wof:placetype":"venue"
},
  "geometry": {"coordinates":[-81.505844,28.458773],"type":"Point"}
}