{
  "type": "Feature",
  "properties": {
    "iso:country":"US",
    "sg:address":"4445 SE 120th St",
    "sg:city":"Belleview",
    "sg:classifiers":[
        {
            "category":"Retail",
            "subcategory":"Animal Services",
            "type":"Services"
        }
    ],
    "sg:phone":"+1 352 307 2543",
    "sg:postcode":"34420",
    "sg:province":"FL",
    "sg:tags":[
        "pet",
        "grooming",
        "washing"
    ],
    "wof:name":"Tail Waggs Pet Grooming",
    "wof:placetype":"venue"
},
  "geometry": {"coordinates":[-82.06582400000001,29.048505],"type":"Point"}
}