{
  "type": "Feature",
  "properties": {
    "iso:country":"US",
    "sg:address":"1552 Lake Trafford Rd",
    "sg:city":"Immokalee",
    "sg:classifiers":[
        {
            "category":"Cinema",
            "subcategory":"Movie Rental",
            "type":"Entertainment"
        }
    ],
    "sg:phone":"+1 239 657 1336",
    "sg:postcode":"34142",
    "sg:province":"FL",
    "sg:tags":[
        "leasing",
        "video",
        "disc",
        "tape"
    ],
    "wof:name":"MGA Inc",
    "wof:placetype":"venue"
},
  "geometry": {"coordinates":[-81.438388,26.433043],"type":"Point"}
}