{
  "type": "Feature",
  "properties": {
    "iso:country":"US",
    "sg:address":"7924 Drayton Cir",
    "sg:city":"Bradenton",
    "sg:classifiers":[
        {
            "category":"Restaurant",
            "type":"Food & Drink"
        }
    ],
    "sg:phone":"+1 941 360 1419",
    "sg:postcode":"34201",
    "sg:province":"FL",
    "wof:name":"Benvenuti Cafe & Deli",
    "wof:placetype":"venue"
},
  "geometry": {"coordinates":[-82.46114300000001,27.400787],"type":"Point"}
}