{
  "type": "Feature",
  "properties": {
    "iso:country":"US",
    "sg:address":"14050 NW 14th St",
    "sg:city":"Sunrise",
    "sg:classifiers":[
        {
            "category":"Organizations",
            "subcategory":"Non-profit Organization",
            "type":"Services"
        }
    ],
    "sg:phone":"+1 954 838 4752",
    "sg:postcode":"33323",
    "sg:province":"FL",
    "sg:tags":[
        "charity",
        "foundations-educational",
        "philanthropic",
        "research"
    ],
    "wof:name":"Moffitt Memorial Endowment Fund",
    "wof:placetype":"venue"
},
  "geometry": {"coordinates":[-80.33696399999999,26.138515],"type":"Point"}
}