{
  "type": "Feature",
  "properties": {
    "iso:country":"US",
    "sg:address":"102 E Dr Martin Luther King Jr Blvd",
    "sg:city":"Tampa",
    "sg:classifiers":[
        {
            "category":"Real Estate",
            "subcategory":"Real Estate Services",
            "type":"Services"
        },
        {
            "category":"Real Estate",
            "subcategory":"Real Estate Agent",
            "type":"Services"
        }
    ],
    "sg:phone":"+1 813 238 6111",
    "sg:postcode":"33603",
    "sg:province":"FL",
    "sg:tags":[
        "buyer",
        "broker"
    ],
    "wof:name":"Florida Real Estate",
    "wof:placetype":"venue"
},
  "geometry": {"coordinates":[-82.460869,27.981487],"type":"Point"}
}