{
  "type": "Feature",
  "properties": {
    "addr:full":"1375 Bardin Rd Palatka FL 32177",
    "addr:housenumber":"1375",
    "addr:postcode":"32177",
    "addr:street":"Bardin Rd",
    "iso:country":"US",
    "sg:address":"1375 Bardin Rd",
    "sg:city":"Palatka",
    "sg:classifiers":[
        {
            "category":"Retail",
            "subcategory":"Animal Services",
            "type":"Services"
        }
    ],
    "sg:phone":"+1 386 326 9400",
    "sg:postcode":"32177",
    "sg:province":"FL",
    "sg:tags":[
        "pet",
        "boarding",
        "sitting"
    ],
    "wof:name":"Kathie's Pet Resort",
    "wof:placetype":"venue"
},
  "geometry": {"coordinates":[-81.790246,29.801038],"type":"Point"}
}