{
  "type": "Feature",
  "properties": {
    "addr:full":"2613 NW 83rd Way Pompano Beach FL 33065",
    "addr:housenumber":"2613",
    "addr:postcode":"33065",
    "addr:street":"Nw 83Rd Way",
    "iso:country":"US",
    "sg:address":"2613 NW 83rd Way",
    "sg:city":"Pompano Beach",
    "sg:classifiers":[
        {
            "category":"Building & Trades",
            "subcategory":"Construction",
            "type":"Services"
        }
    ],
    "sg:phone":"+1 954 341 4834",
    "sg:postcode":"33065",
    "sg:province":"FL",
    "sg:tags":[
        "maintenance",
        "nonresidential"
    ],
    "wof:name":"Hardworkers",
    "wof:placetype":"venue"
},
  "geometry": {"coordinates":[-80.237889,26.262695],"type":"Point"}
}