{
  "type": "Feature",
  "properties": {
    "iso:country":"US",
    "sg:address":"11890 N Florida Ave",
    "sg:city":"Dunnellon",
    "sg:classifiers":[
        {
            "category":"Organizations",
            "subcategory":"Community Association",
            "type":"Services"
        }
    ],
    "sg:phone":"+1 352 489 0276",
    "sg:postcode":"34442",
    "sg:province":"FL",
    "sg:tags":[
        "fraternal"
    ],
    "wof:name":"Loyal Order Of Moose",
    "wof:placetype":"venue"
},
  "geometry": {"coordinates":[-82.46115,29.036696],"type":"Point"}
}