{
  "type": "Feature",
  "properties": {
    "iso:country":"US",
    "sg:address":"182 Flamingo Rd",
    "sg:city":"Edgewater",
    "sg:classifiers":[
        {
            "category":"Professional",
            "subcategory":"Management & Consulting",
            "type":"Services"
        },
        {
            "category":"Banks & Credit Unions",
            "subcategory":"Financial Services",
            "type":"Services"
        }
    ],
    "sg:phone":"+1 386 427 4837",
    "sg:postcode":"32141",
    "sg:province":"FL",
    "sg:tags":[
        "consultant",
        "financing",
        "planning"
    ],
    "wof:name":"Kp Enterprises",
    "wof:placetype":"venue"
},
  "geometry": {"coordinates":[-80.87106199999999,28.93526],"type":"Point"}
}