{
  "type": "Feature",
  "properties": {
    "iso:country":"US",
    "sg:address":"415 N Marion St",
    "sg:city":"Lake City",
    "sg:classifiers":[
        {
            "category":"Shopping",
            "subcategory":"Clothing, Apparel, & Fashions",
            "type":"Retail Goods"
        }
    ],
    "sg:phone":"+1 386 754 6104",
    "sg:postcode":"32055",
    "sg:province":"FL",
    "wof:name":"Big Girl Shop",
    "wof:placetype":"venue"
},
  "geometry": {"coordinates":[-82.637103,30.192625],"type":"Point"}
}