{
  "type": "Feature",
  "properties": {
    "iso:country":"US",
    "sg:address":"25309 Bartholomew St",
    "sg:city":"Christmas",
    "sg:classifiers":[
        {
            "category":"Building & Trades",
            "subcategory":"Landscaping Services",
            "type":"Services"
        }
    ],
    "sg:phone":"+1 407 568 5825",
    "sg:postcode":"32709",
    "sg:province":"FL",
    "sg:tags":[
        "lawn",
        "maintenance",
        "grounds"
    ],
    "wof:name":"Clarence Watkins & Sons Lawn",
    "wof:placetype":"venue"
},
  "geometry": {"coordinates":[-80.991781,28.527012],"type":"Point"}
}