{
  "type": "Feature",
  "properties": {
    "addr:full":"420 3rd St S Jacksonville Bch FL 32250",
    "addr:housenumber":"420",
    "addr:postcode":"32250",
    "addr:street":"3Rd St S",
    "iso:country":"US",
    "sg:address":"420 3rd St S",
    "sg:city":"Jacksonville Bch",
    "sg:classifiers":[
        {
            "category":"Real Estate",
            "subcategory":"Architect",
            "type":"Services"
        }
    ],
    "sg:phone":"+1 904 242 8800",
    "sg:postcode":"32250",
    "sg:province":"FL",
    "sg:tags":[
        "architectural"
    ],
    "wof:name":"Broadfoot Designs",
    "wof:placetype":"venue"
},
  "geometry": {"coordinates":[-81.39091999999999,30.283643],"type":"Point"}
}