{
  "type": "Feature",
  "properties": {
    "addr:full":"11373 W Flagler St #203 Miami FL 33174",
    "addr:housenumber":"11373",
    "addr:postcode":"33174",
    "addr:street":"W Flagler St # 203",
    "iso:country":"US",
    "sg:address":"11373 W Flagler St #203",
    "sg:city":"Miami",
    "sg:classifiers":[
        {
            "category":"Retail",
            "subcategory":"Auto Rental",
            "type":"Services"
        },
        {
            "category":"Retail",
            "subcategory":"Storage",
            "type":"Services"
        }
    ],
    "sg:phone":"+1 305 774 1696",
    "sg:postcode":"33174",
    "sg:province":"FL",
    "sg:tags":[
        "moving-self",
        "truck"
    ],
    "sg:website":"http://www.uhaul.com/Locations/Rentals-near-Miami-FL-33174/019303",
    "wof:name":"U-Haul Neighborhood Dealer - Cadiz Insurance Services",
    "wof:placetype":"venue"
},
  "geometry": {"coordinates":[-80.380715,25.768341],"type":"Point"}
}