{
  "type": "Feature",
  "properties": {
    "addr:full":"2032 Portland Ave West Palm Beach FL 33414",
    "addr:housenumber":"2032",
    "addr:postcode":"33414",
    "addr:street":"Portland Ave",
    "iso:country":"US",
    "sg:address":"2032 Portland Ave",
    "sg:city":"West Palm Beach",
    "sg:classifiers":[
        {
            "category":"Wholesale",
            "subcategory":"Plants",
            "type":"Manufacturing & Wholesale Goods"
        }
    ],
    "sg:phone":"+1 561 791 2179",
    "sg:postcode":"33414",
    "sg:province":"FL",
    "sg:tags":[
        "florist"
    ],
    "wof:name":"International Creations Svcs",
    "wof:placetype":"venue"
},
  "geometry": {"coordinates":[-80.247854,26.650006],"type":"Point"}
}