{
  "type": "Feature",
  "properties": {
    "iso:country":"US",
    "sg:address":"100 Sunset Ln",
    "sg:city":"Palatka",
    "sg:classifiers":[
        {
            "category":"Professional",
            "type":"Services"
        }
    ],
    "sg:phone":"+1 386 328 6243",
    "sg:postcode":"32177",
    "sg:province":"FL",
    "wof:name":"Express Corporation Inc",
    "wof:placetype":"venue"
},
  "geometry": {"coordinates":[-81.718009,29.62049],"type":"Point"}
}