{
  "type": "Feature",
  "properties": {
    "addr:full":"600 N Ferdon Blvd Crestview FL 32536",
    "addr:housenumber":"600",
    "addr:postcode":"32536",
    "addr:street":"N Ferdon Blvd",
    "iso:country":"US",
    "sg:address":"600 N Ferdon Blvd",
    "sg:city":"Crestview",
    "sg:classifiers":[
        {
            "category":"Organizations",
            "subcategory":"Religious Organization",
            "type":"Services"
        }
    ],
    "sg:phone":"+1 850 682 2248",
    "sg:postcode":"32536",
    "sg:province":"FL",
    "sg:tags":[
        "church"
    ],
    "wof:name":"Crestview Independent Baptist",
    "wof:placetype":"venue"
},
  "geometry": {"coordinates":[-86.567846,30.767187],"type":"Point"}
}