{
  "type": "Feature",
  "properties": {
    "addr:full":"1400 S Peninsula Dr Daytona Beach FL 32118",
    "addr:housenumber":"1400",
    "addr:postcode":"32118",
    "addr:street":"S Peninsula Dr",
    "iso:country":"US",
    "sg:address":"1400 S Peninsula Dr",
    "sg:city":"Daytona Beach",
    "sg:classifiers":[
        {
            "category":"Social Services",
            "subcategory":"Child Care",
            "type":"Services"
        },
        {
            "category":"Organizations",
            "subcategory":"Religious Organization",
            "type":"Services"
        }
    ],
    "sg:phone":"+1 386 252 3163",
    "sg:postcode":"32118",
    "sg:province":"FL",
    "sg:tags":[
        "day"
    ],
    "wof:name":"Temple Israel Preschool",
    "wof:placetype":"venue"
},
  "geometry": {"coordinates":[-81.004835,29.209638],"type":"Point"}
}