{
  "type": "Feature",
  "properties": {
    "addr:full":"2511 Westgate Ave West Palm Beach FL 33409",
    "addr:housenumber":"2511",
    "addr:postcode":"33409",
    "addr:street":"Westgate Ave",
    "iso:country":"US",
    "sg:address":"2511 Westgate Ave",
    "sg:city":"West Palm Beach",
    "sg:classifiers":[
        {
            "category":"Food & Beverages",
            "subcategory":"Groceries & Convenience Stores",
            "type":"Retail Goods"
        }
    ],
    "sg:phone":"+1 561 684 3484",
    "sg:postcode":"33409",
    "sg:province":"FL",
    "wof:name":"K Beverage & Food",
    "wof:placetype":"venue"
},
  "geometry": {"coordinates":[-80.09263799999999,26.703098],"type":"Point"}
}