{
  "type": "Feature",
  "properties": {
    "addr:full":"3135 Fieldcrest Dr Middleburg FL 32068",
    "addr:housenumber":"3135",
    "addr:postcode":"32068",
    "addr:street":"Fieldcrest Dr",
    "iso:country":"US",
    "sg:address":"3135 Fieldcrest Dr",
    "sg:city":"Middleburg",
    "sg:classifiers":[
        {
            "category":"Shopping",
            "subcategory":"Clothing, Apparel, & Fashions",
            "type":"Retail Goods"
        }
    ],
    "sg:phone":"+1 904 291 7781",
    "sg:postcode":"32068",
    "sg:province":"FL",
    "sg:tags":[
        "navy",
        "army"
    ],
    "wof:name":"Atlantic Diving Supply",
    "wof:placetype":"venue"
},
  "geometry": {"coordinates":[-81.79121600000001,30.089414],"type":"Point"}
}