{
  "type": "Feature",
  "properties": {
    "addr:full":"14401 Military Trl Delray Beach FL 33484",
    "addr:housenumber":"14401",
    "addr:postcode":"33484",
    "addr:street":"Military Trl",
    "iso:country":"US",
    "sg:address":"14401 Military Trl",
    "sg:city":"Delray Beach",
    "sg:classifiers":[
        {
            "category":"Health Services",
            "subcategory":"Doctor",
            "type":"Services"
        }
    ],
    "sg:phone":"+1 561 498 4948",
    "sg:postcode":"33484",
    "sg:province":"FL",
    "sg:tags":[
        "medical"
    ],
    "wof:name":"M L Weinman Dr",
    "wof:placetype":"venue"
},
  "geometry": {"coordinates":[-80.12270599999999,26.463102],"type":"Point"}
}