{
  "type": "Feature",
  "properties": {
    "iso:country":"US",
    "sg:address":"2478 Inagua Ave",
    "sg:city":"Miami",
    "sg:classifiers":[
        {
            "category":"Professional",
            "subcategory":"Art Services",
            "type":"Services"
        }
    ],
    "sg:phone":"+1 305 854 3985",
    "sg:postcode":"33133",
    "sg:province":"FL",
    "sg:tags":[
        "designer",
        "display",
        "producer"
    ],
    "wof:name":"Red Luna Design Group",
    "wof:placetype":"venue"
},
  "geometry": {"coordinates":[-80.234932,25.73791],"type":"Point"}
}