{
  "type": "Feature",
  "properties": {
    "addr:full":"1990 SE Ocean Blvd Stuart FL 34996",
    "addr:housenumber":"1990",
    "addr:postcode":"34996",
    "addr:street":"Se Ocean Blvd",
    "iso:country":"US",
    "sg:address":"1990 SE Ocean Blvd",
    "sg:city":"Stuart",
    "sg:classifiers":[
        {
            "category":"Health Services",
            "subcategory":"Chiropractor",
            "type":"Services"
        },
        {
            "category":"Health Services",
            "subcategory":"Doctor",
            "type":"Services"
        }
    ],
    "sg:phone":"+1 772 223 9597",
    "sg:postcode":"34996",
    "sg:province":"FL",
    "sg:tags":[
        "clinic"
    ],
    "wof:name":"Spinal Health & Wellness Ctr",
    "wof:placetype":"venue"
},
  "geometry": {"coordinates":[-80.224861,27.197321],"type":"Point"}
}