{
  "type": "Feature",
  "properties": {
    "iso:country":"US",
    "sg:address":"1811 Stephens Ln",
    "sg:city":"Dover",
    "sg:classifiers":[
        {
            "category":"Building & Trades",
            "subcategory":"Electrical",
            "type":"Services"
        }
    ],
    "sg:phone":"+1 813 654 7580",
    "sg:postcode":"33527",
    "sg:province":"FL",
    "sg:tags":[
        "electrical",
        "contractor"
    ],
    "wof:name":"Wilcox Electric",
    "wof:placetype":"venue"
},
  "geometry": {"coordinates":[-82.251718,27.969298],"type":"Point"}
}