{
  "type": "Feature",
  "properties": {
    "addr:full":"12453 Cleveland Ave Fort Myers FL 33907",
    "addr:housenumber":"12453",
    "addr:postcode":"33907",
    "addr:street":"Cleveland Ave",
    "iso:country":"US",
    "sg:address":"12453 Cleveland Ave",
    "sg:city":"Fort Myers",
    "sg:classifiers":[
        {
            "category":"Real Estate",
            "subcategory":"Real Estate Agent",
            "type":"Services"
        }
    ],
    "sg:phone":"+1 239 931 0600",
    "sg:postcode":"33907",
    "sg:province":"FL",
    "sg:tags":[
        "manager"
    ],
    "wof:name":"Century 21",
    "wof:placetype":"venue"
},
  "geometry": {"coordinates":[-81.871993,26.56286],"type":"Point"}
}