{
  "type": "Feature",
  "properties": {
    "addr:full":"948 N Semoran Blvd Orlando FL 32807",
    "addr:housenumber":"948",
    "addr:postcode":"32807",
    "addr:street":"N Semoran Blvd",
    "iso:country":"US",
    "sg:address":"948 N Semoran Blvd",
    "sg:city":"Orlando",
    "sg:classifiers":[
        {
            "category":"Home & Garden",
            "subcategory":"Building Materials",
            "type":"Retail Goods"
        }
    ],
    "sg:phone":"+1 407 658 6199",
    "sg:postcode":"32807",
    "sg:province":"FL",
    "sg:tags":[
        "glass",
        "window",
        "plate"
    ],
    "wof:name":"Glass America",
    "wof:placetype":"venue"
},
  "geometry": {"coordinates":[-81.310868,28.558204],"type":"Point"}
}