{
  "type": "Feature",
  "properties": {
    "addr:full":"9240 Old Hickory Cir Fort Myers FL 33912",
    "addr:housenumber":"9240",
    "addr:postcode":"33912",
    "addr:street":"Old Hickory Cir",
    "iso:country":"US",
    "sg:address":"9240 Old Hickory Cir",
    "sg:city":"Fort Myers",
    "sg:classifiers":[
        {
            "category":"Real Estate",
            "subcategory":"Real Estate Agent",
            "type":"Services"
        }
    ],
    "sg:phone":"+1 239 561 2939",
    "sg:postcode":"33912",
    "sg:province":"FL",
    "wof:name":"Ms Beth Inc",
    "wof:placetype":"venue"
},
  "geometry": {"coordinates":[-81.800422,26.538165],"type":"Point"}
}