{
  "type": "Feature",
  "properties": {
    "addr:full":"250 Ave K SW Winter Haven FL 33880",
    "addr:housenumber":"250",
    "addr:postcode":"33880",
    "addr:street":"Ave K Sw",
    "iso:country":"US",
    "sg:address":"250 Ave K SW",
    "sg:city":"Winter Haven",
    "sg:classifiers":[
        {
            "category":"Health Services",
            "subcategory":"Doctor",
            "type":"Services"
        }
    ],
    "sg:phone":"+1 863 297 5400",
    "sg:postcode":"33880",
    "sg:province":"FL",
    "sg:tags":[
        "physician",
        "surgeon"
    ],
    "wof:name":"Vitreous & Retina Consultants",
    "wof:placetype":"venue"
},
  "geometry": {"coordinates":[-81.731711,28.011207],"type":"Point"}
}