{
  "type": "Feature",
  "properties": {
    "addr:full":"7944 Rutillio Ct New Port Richey FL 34653",
    "addr:housenumber":"7944",
    "addr:postcode":"34653",
    "addr:street":"Rutillio Ct",
    "iso:country":"US",
    "sg:address":"7944 Rutillio Ct",
    "sg:city":"New Port Richey",
    "sg:classifiers":[
        {
            "category":"Building & Trades",
            "subcategory":"Construction",
            "type":"Services"
        }
    ],
    "sg:phone":"+1 727 841 8559",
    "sg:postcode":"34653",
    "sg:province":"FL",
    "sg:tags":[
        "fire",
        "restoration",
        "damage"
    ],
    "wof:name":"Paul Davis Restoration-Pasco",
    "wof:placetype":"venue"
},
  "geometry": {"coordinates":[-82.704477,28.271814],"type":"Point"}
}