{
  "type": "Feature",
  "properties": {
    "iso:country":"US",
    "sg:address":"5224 Mauna Loa Ln",
    "sg:city":"Orlando",
    "sg:classifiers":[
        {
            "category":"Building & Trades",
            "subcategory":"Construction",
            "type":"Services"
        }
    ],
    "sg:phone":"+1 407 855 5739",
    "sg:postcode":"32812",
    "sg:province":"FL",
    "sg:tags":[
        "contractor"
    ],
    "wof:name":"Michael Pazos Contractor",
    "wof:placetype":"venue"
},
  "geometry": {"coordinates":[-81.318532,28.480029],"type":"Point"}
}