{
  "type": "Feature",
  "properties": {
    "addr:full":"2150 Fowler St Fort Myers FL 33901",
    "addr:housenumber":"2150",
    "addr:postcode":"33901",
    "addr:street":"Fowler St",
    "iso:country":"US",
    "sg:address":"2150 Fowler St",
    "sg:city":"Fort Myers",
    "sg:classifiers":[
        {
            "category":"Food & Beverages",
            "subcategory":"Meat & Fish",
            "type":"Retail Goods"
        }
    ],
    "sg:phone":"+1 239 245 7577",
    "sg:postcode":"33901",
    "sg:province":"FL",
    "sg:tags":[
        "shop"
    ],
    "wof:name":"Papi's Meat Market",
    "wof:placetype":"venue"
},
  "geometry": {"coordinates":[-81.86249100000001,26.638624],"type":"Point"}
}