{
  "type": "Feature",
  "properties": {
    "addr:full":"450 Alton Rd Miami Beach FL 33139",
    "addr:housenumber":"450",
    "addr:postcode":"33139",
    "addr:street":"Alton Rd",
    "iso:country":"US",
    "sg:address":"450 Alton Rd",
    "sg:city":"Miami Beach",
    "sg:classifiers":[
        {
            "category":"Restaurant",
            "type":"Food & Drink"
        }
    ],
    "sg:phone":"+1 305 673 0006",
    "sg:postcode":"33139",
    "sg:province":"FL",
    "wof:name":"Grande Cafe",
    "wof:placetype":"venue"
},
  "geometry": {"coordinates":[-80.140265,25.773742],"type":"Point"}
}