{
  "type": "Feature",
  "properties": {
    "addr:full":"1997 Opa Locka Blvd Opa Locka FL 33054",
    "addr:housenumber":"1997",
    "addr:postcode":"33054",
    "addr:street":"Opa Locka Blvd;Locka",
    "iso:country":"US",
    "sg:address":"1997 Opa Locka Blvd",
    "sg:city":"Opa Locka",
    "sg:classifiers":[
        {
            "category":"Retail",
            "subcategory":"Repair Shop",
            "type":"Services"
        }
    ],
    "sg:phone":"+1 305 687 3915",
    "sg:postcode":"33054",
    "sg:province":"FL",
    "sg:tags":[
        "engine",
        "small",
        "lawn",
        "repairing",
        "mower"
    ],
    "wof:name":"Eddies Lawn Mower Shop Inc",
    "wof:placetype":"venue"
},
  "geometry": {"coordinates":[-80.234358,25.898291],"type":"Point"}
}