{
  "type": "Feature",
  "properties": {
    "iso:country":"US",
    "sg:address":"313 Briarwood Rd",
    "sg:city":"Venice",
    "sg:classifiers":[
        {
            "category":"Real Estate",
            "subcategory":"Real Estate Agent",
            "type":"Services"
        }
    ],
    "sg:phone":"+1 941 276 0025",
    "sg:postcode":"34293",
    "sg:province":"FL",
    "sg:tags":[
        "inspection"
    ],
    "wof:name":"Clive Lindo Home Inspection",
    "wof:placetype":"venue"
},
  "geometry": {"coordinates":[-82.41912499999999,27.068346],"type":"Point"}
}