{
  "type": "Feature",
  "properties": {
    "addr:full":"670 103rd Ave N Naples FL 34108",
    "addr:housenumber":"670",
    "addr:postcode":"34108",
    "addr:street":"103Rd Ave N",
    "iso:country":"US",
    "sg:address":"670 103rd Ave N",
    "sg:city":"Naples",
    "sg:classifiers":[
        {
            "category":"Building & Trades",
            "subcategory":"Construction",
            "type":"Services"
        }
    ],
    "sg:phone":"+1 239 514 1475",
    "sg:postcode":"34108",
    "sg:province":"FL",
    "sg:tags":[
        "hanging",
        "contractor"
    ],
    "wof:name":"Dans Wallpaper Hanging",
    "wof:placetype":"venue"
},
  "geometry": {"coordinates":[-81.81341500000001,26.265152],"type":"Point"}
}