{
  "type": "Feature",
  "properties": {
    "addr:full":"627 S Andrews Ave Fort Lauderdale FL 33301",
    "addr:housenumber":"627",
    "addr:postcode":"33301",
    "addr:street":"S Andrews Ave",
    "iso:country":"US",
    "sg:address":"627 S Andrews Ave",
    "sg:city":"Fort Lauderdale",
    "sg:classifiers":[
        {
            "category":"Retail",
            "subcategory":"Repair Shop",
            "type":"Services"
        }
    ],
    "sg:phone":"+1 954 523 1971",
    "sg:postcode":"33301",
    "sg:province":"FL",
    "wof:name":"Framework",
    "wof:placetype":"venue"
},
  "geometry": {"coordinates":[-80.143247,26.113462],"type":"Point"}
}