{
  "type": "Feature",
  "properties": {
    "iso:country":"US",
    "sg:address":"1425 W State Road 434",
    "sg:city":"Longwood",
    "sg:classifiers":[
        {
            "category":"Banks & Credit Unions",
            "subcategory":"Financial Services",
            "type":"Services"
        }
    ],
    "sg:phone":"+1 407 645 1310",
    "sg:postcode":"32750",
    "sg:province":"FL",
    "sg:tags":[
        "broker",
        "mortgage"
    ],
    "wof:name":"Watson Title Services Inc",
    "wof:placetype":"venue"
},
  "geometry": {"coordinates":[-81.37640399999999,28.697599],"type":"Point"}
}