{
  "type": "Feature",
  "properties": {
    "addr:full":"1048 S Pine Ave Ocala FL 34471",
    "addr:housenumber":"1048",
    "addr:postcode":"34471",
    "addr:street":"S Pine Ave",
    "iso:country":"US",
    "sg:address":"1048 S Pine Ave",
    "sg:city":"Ocala",
    "sg:classifiers":[
        {
            "category":"Travel",
            "subcategory":"Hotels & Motels",
            "type":"Entertainment"
        }
    ],
    "sg:phone":"+1 352 622 4174",
    "sg:postcode":"34471",
    "sg:province":"FL",
    "wof:name":"Holiday Motel",
    "wof:placetype":"venue"
},
  "geometry": {"coordinates":[-82.14049900000001,29.17917],"type":"Point"}
}