{
  "type": "Feature",
  "properties": {
    "addr:full":"5731 Bible Camp Rd Groveland FL 34736",
    "addr:housenumber":"5731",
    "addr:postcode":"34736",
    "addr:street":"Bible Camp Rd",
    "iso:country":"US",
    "sg:address":"5731 Bible Camp Rd",
    "sg:city":"Groveland",
    "sg:classifiers":[
        {
            "category":"Building & Trades",
            "subcategory":"Plumbing",
            "type":"Services"
        }
    ],
    "sg:phone":"+1 352 429 3667",
    "sg:postcode":"34736",
    "sg:province":"FL",
    "sg:tags":[
        "plumber",
        "industrial",
        "contractors-commercial"
    ],
    "wof:name":"Lucas Ryan Plummer",
    "wof:placetype":"venue"
},
  "geometry": {"coordinates":[-81.859798,28.576077],"type":"Point"}
}