{
  "type": "Feature",
  "properties": {
    "iso:country":"US",
    "sg:address":"5221 Ave Navarra",
    "sg:city":"Sarasota",
    "sg:classifiers":[
        {
            "category":"Retail",
            "subcategory":"Animal Services",
            "type":"Services"
        }
    ],
    "sg:phone":"+1 941 349 9445",
    "sg:postcode":"34242",
    "sg:province":"FL",
    "wof:name":"Groomingdales",
    "wof:placetype":"venue"
},
  "geometry": {"coordinates":[-82.565091,27.274601],"type":"Point"}
}