{
  "type": "Feature",
  "properties": {
    "addr:full":"3712 Benbow St Panama City FL 32408",
    "addr:housenumber":"3712",
    "addr:postcode":"32408",
    "addr:street":"Benbow St",
    "iso:country":"US",
    "sg:address":"3712 Benbow St",
    "sg:city":"Panama City",
    "sg:classifiers":[
        {
            "category":"Building & Trades",
            "subcategory":"Landscaping Services",
            "type":"Services"
        }
    ],
    "sg:phone":"+1 850 234 1930",
    "sg:postcode":"32408",
    "sg:province":"FL",
    "sg:tags":[
        "landscape",
        "contractor"
    ],
    "wof:name":"John Davis Landscape Mntnc Co",
    "wof:placetype":"venue"
},
  "geometry": {"coordinates":[-85.751023,30.145376],"type":"Point"}
}