{
  "type": "Feature",
  "properties": {
    "iso:country":"US",
    "sg:address":"209 SE 1st St",
    "sg:city":"Miami",
    "sg:classifiers":[
        {
            "category":"Restaurant",
            "type":"Food & Drink"
        }
    ],
    "sg:phone":"+1 305 374 6795",
    "sg:postcode":"33131",
    "sg:province":"FL",
    "sg:tags":[
        "cuban"
    ],
    "wof:name":"Las Palmas Cafeteria",
    "wof:placetype":"venue"
},
  "geometry": {"coordinates":[-80.190102,25.7735],"type":"Point"}
}