{
  "type": "Feature",
  "properties": {
    "iso:country":"US",
    "sg:address":"930 NW 27th Ave.",
    "sg:city":"Miami",
    "sg:classifiers":[
        {
            "category":"Shopping",
            "subcategory":"Hobbies, Toys, & Games",
            "type":"Retail Goods"
        },
        {
            "category":"Shopping",
            "subcategory":"Pets & Pet Supplies",
            "type":"Retail Goods"
        }
    ],
    "sg:phone":"+1 305 649 2263",
    "sg:postcode":"33125",
    "sg:province":"FL",
    "sg:tags":[
        "shop",
        "dog",
        "cat",
        "furnishing",
        "hobby",
        "store"
    ],
    "sg:website":"www.petconnectionusa.com",
    "wof:name":"Pet Connection USA",
    "wof:placetype":"venue"
},
  "geometry": {"coordinates":[-80.239681,25.781896],"type":"Point"}
}