{
  "type": "Feature",
  "properties": {
    "addr:full":"12377 S Cleveland Ave Fort Myers FL 33907",
    "addr:housenumber":"12377",
    "addr:postcode":"33907",
    "addr:street":"S Cleveland Ave",
    "iso:country":"US",
    "sg:address":"12377 S Cleveland Ave",
    "sg:city":"Fort Myers",
    "sg:classifiers":[
        {
            "category":"Restaurant",
            "type":"Food & Drink"
        }
    ],
    "sg:phone":"+1 239 275 5666",
    "sg:postcode":"33907",
    "sg:province":"FL",
    "sg:tags":[
        "pizza"
    ],
    "sg:website":"www.pizzahut.com",
    "wof:name":"Pizza Hut",
    "wof:placetype":"venue"
},
  "geometry": {"coordinates":[-81.871803,26.562901],"type":"Point"}
}