{
  "type": "Feature",
  "properties": {
    "addr:full":"21000 Boca Rio Rd Boca Raton FL 33433",
    "addr:postcode":"21000;33433",
    "addr:street":"Boca Rio Rd",
    "iso:country":"US",
    "sg:address":"21000 Boca Rio Rd",
    "sg:city":"Boca Raton",
    "sg:classifiers":[
        {
            "category":"Retail",
            "subcategory":"Auto Repair",
            "type":"Services"
        }
    ],
    "sg:phone":"+1 561 488 2322",
    "sg:postcode":"33433",
    "sg:province":"FL",
    "sg:tags":[
        "repairing",
        "automobile"
    ],
    "wof:name":"Great Bear Automotive & Tire",
    "wof:placetype":"venue"
},
  "geometry": {"coordinates":[-80.17139400000001,26.360449],"type":"Point"}
}