{
  "type": "Feature",
  "properties": {
    "iso:country":"US",
    "sg:address":"4178 NW 132nd St",
    "sg:city":"Opa Locka",
    "sg:classifiers":[
        {
            "category":"Manufacturing",
            "subcategory":"Leather Goods",
            "type":"Manufacturing & Wholesale Goods"
        }
    ],
    "sg:phone":"+1 305 688 5436",
    "sg:postcode":"33054",
    "sg:province":"FL",
    "sg:tags":[
        "equipment",
        "horse",
        "supply"
    ],
    "wof:name":"B & R Industries",
    "wof:placetype":"venue"
},
  "geometry": {"coordinates":[-80.267031,25.893748],"type":"Point"}
}