{
  "type": "Feature",
  "properties": {
    "addr:full":"4311 John Moore Rd Brandon FL 33511",
    "addr:housenumber":"4311",
    "addr:postcode":"33511",
    "addr:street":"John Moore Rd",
    "iso:country":"US",
    "sg:address":"4311 John Moore Rd",
    "sg:city":"Brandon",
    "sg:classifiers":[
        {
            "category":"Manufacturing",
            "subcategory":"Food",
            "type":"Manufacturing & Wholesale Goods"
        }
    ],
    "sg:phone":"+1 813 689 3889",
    "sg:postcode":"33511",
    "sg:province":"FL",
    "sg:tags":[
        "mfg"
    ],
    "wof:name":"Top Quality Enterprises Inc",
    "wof:placetype":"venue"
},
  "geometry": {"coordinates":[-82.285796,27.874114],"type":"Point"}
}