{
  "type": "Feature",
  "properties": {
    "addr:full":"4091 Drifting Sand Trl Destin FL 32541",
    "addr:housenumber":"4091",
    "addr:postcode":"32541",
    "addr:street":"Drifting Sand Trl",
    "iso:country":"US",
    "sg:address":"4091 Drifting Sand Trl",
    "sg:city":"Destin",
    "sg:classifiers":[
        {
            "category":"Building & Trades",
            "subcategory":"Construction",
            "type":"Services"
        }
    ],
    "sg:phone":"+1 850 837 1903",
    "sg:postcode":"32541",
    "sg:province":"FL",
    "sg:tags":[
        "contractor"
    ],
    "wof:name":"Ed Herrings Discount Blinds",
    "wof:placetype":"venue"
},
  "geometry": {"coordinates":[-86.45532300000001,30.391389],"type":"Point"}
}