{
  "type": "Feature",
  "properties": {
    "addr:full":"1090 NE 129th St North Miami FL 33161",
    "addr:housenumber":"1090",
    "addr:postcode":"33161",
    "addr:street":"Ne 129Th St",
    "iso:country":"US",
    "sg:address":"1090 NE 129th St",
    "sg:city":"North Miami",
    "sg:classifiers":[
        {
            "category":"Wholesale",
            "subcategory":"Durable Goods & Equipment",
            "type":"Manufacturing & Wholesale Goods"
        }
    ],
    "sg:phone":"+1 305 892 0206",
    "sg:postcode":"33161",
    "sg:province":"FL",
    "sg:tags":[
        "exporter"
    ],
    "wof:name":"Caribbean Exports",
    "wof:placetype":"venue"
},
  "geometry": {"coordinates":[-80.17818200000001,25.894184],"type":"Point"}
}