{
  "type": "Feature",
  "properties": {
    "iso:country":"US",
    "sg:address":"7273 Mossy Oaks Dr",
    "sg:city":"Gulf Breeze",
    "sg:classifiers":[
        {
            "category":"Building & Trades",
            "subcategory":"Landscaping Services",
            "type":"Services"
        }
    ],
    "sg:phone":"+1 850 936 9857",
    "sg:postcode":"32566",
    "sg:province":"FL",
    "wof:name":"Larry D Andrews",
    "wof:placetype":"venue"
},
  "geometry": {"coordinates":[-86.91930499999999,30.439048],"type":"Point"}
}