{
  "type": "Feature",
  "properties": {
    "addr:full":"1580 Serenity Cir Naples FL 34110",
    "addr:housenumber":"1580",
    "addr:postcode":"34110",
    "addr:street":"Serenity Cir",
    "iso:country":"US",
    "sg:address":"1580 Serenity Cir",
    "sg:city":"Naples",
    "sg:classifiers":[
        {
            "category":"Professional",
            "type":"Services"
        }
    ],
    "sg:phone":"+1 239 514 7761",
    "sg:postcode":"34110",
    "sg:province":"FL",
    "sg:tags":[
        "establishment"
    ],
    "wof:name":"Marja LLC",
    "wof:placetype":"venue"
},
  "geometry": {"coordinates":[-81.80033400000001,26.308233],"type":"Point"}
}