{
  "type": "Feature",
  "properties": {
    "iso:country":"US",
    "sg:address":"7390 SW 24th St",
    "sg:city":"Miami",
    "sg:classifiers":[
        {
            "category":"Restaurant",
            "type":"Food & Drink"
        }
    ],
    "sg:phone":"+1 305 261 0413",
    "sg:postcode":"33155",
    "sg:province":"FL",
    "sg:tags":[
        "eating"
    ],
    "wof:name":"Burger King",
    "wof:placetype":"venue"
},
  "geometry": {"coordinates":[-80.31269,25.748018],"type":"Point"}
}