{
  "type": "Feature",
  "properties": {
    "addr:full":"5022 Gall Blvd Zephyrhills FL 33542",
    "addr:postcode":"5022;33542",
    "addr:street":"Gall Blvd",
    "iso:country":"US",
    "sg:address":"5022 Gall Blvd",
    "sg:city":"Zephyrhills",
    "sg:classifiers":[
        {
            "category":"Professional",
            "subcategory":"Computer Services",
            "type":"Services"
        }
    ],
    "sg:phone":"+1 813 715 4682",
    "sg:postcode":"33542",
    "sg:province":"FL",
    "sg:tags":[
        "sales"
    ],
    "wof:name":"Technology Maintenance",
    "wof:placetype":"venue"
},
  "geometry": {"coordinates":[-82.18054600000001,28.231675],"type":"Point"}
}