{
  "type": "Feature",
  "properties": {
    "iso:country":"US",
    "sg:address":"2338 Immokalee Rd",
    "sg:city":"Naples",
    "sg:classifiers":[
        {
            "category":"Professional",
            "subcategory":"Business Services",
            "type":"Services"
        }
    ],
    "sg:phone":"+1 239 332 5900",
    "sg:postcode":"34142",
    "sg:province":"FL",
    "sg:tags":[
        "building",
        "inspection"
    ],
    "wof:name":"Certified Inspection Svc Of Fl",
    "wof:placetype":"venue"
},
  "geometry": {"coordinates":[-81.48712500000001,26.498693],"type":"Point"}
}