{
  "type": "Feature",
  "properties": {
    "addr:full":"380 Pine Blvd Merritt Island FL 32952",
    "addr:housenumber":"380",
    "addr:postcode":"32952",
    "addr:street":"Pine Blvd",
    "iso:country":"US",
    "sg:address":"380 Pine Blvd",
    "sg:city":"Merritt Island",
    "sg:classifiers":[
        {
            "category":"Recreation",
            "type":"Entertainment"
        }
    ],
    "sg:phone":"+1 321 453 6764",
    "sg:postcode":"32952",
    "sg:province":"FL",
    "sg:tags":[
        "guide"
    ],
    "wof:name":"Sea Venture Charter Boats",
    "wof:placetype":"venue"
},
  "geometry": {"coordinates":[-80.693664,28.338539],"type":"Point"}
}