{
  "type": "Feature",
  "properties": {
    "iso:country":"US",
    "sg:address":"967 Florida Pkwy",
    "sg:city":"Kissimmee",
    "sg:classifiers":[
        {
            "category":"Wholesale",
            "subcategory":"Non-durable Goods",
            "type":"Manufacturing & Wholesale Goods"
        }
    ],
    "sg:phone":"+1 407 348 8154",
    "sg:postcode":"34743",
    "sg:province":"FL",
    "wof:name":"Florida Import & Export Busine",
    "wof:placetype":"venue"
},
  "geometry": {"coordinates":[-81.37473300000001,28.333316],"type":"Point"}
}