{
  "type": "Feature",
  "properties": {
    "iso:country":"US",
    "sg:address":"801 W Bay Dr",
    "sg:city":"Largo",
    "sg:classifiers":[
        {
            "category":"Professional",
            "subcategory":"Lawyer & Legal Services",
            "type":"Services"
        },
        {
            "category":"Professional",
            "subcategory":"Management & Consulting",
            "type":"Services"
        }
    ],
    "sg:phone":"+1 727 559 0081",
    "sg:postcode":"33770",
    "sg:province":"FL",
    "sg:tags":[
        "consultant",
        "medical"
    ],
    "wof:name":"E P S Medical Inc",
    "wof:placetype":"venue"
},
  "geometry": {"coordinates":[-82.798568,27.916752],"type":"Point"}
}