{
  "type": "Feature",
  "properties": {
    "iso:country":"US",
    "sg:address":"3809 S Tuttle Ave",
    "sg:city":"Sarasota",
    "sg:classifiers":[
        {
            "category":"Restaurant",
            "type":"Food & Drink"
        }
    ],
    "sg:phone":"+1 941 927 8716",
    "sg:postcode":"34239",
    "sg:province":"FL",
    "sg:tags":[
        "eating"
    ],
    "wof:name":"Morels Restaurant",
    "wof:placetype":"venue"
},
  "geometry": {"coordinates":[-82.514094,27.299515],"type":"Point"}
}