{
  "type": "Feature",
  "properties": {
    "addr:full":"4040 W Waters Ave Tampa FL 33614",
    "addr:housenumber":"4040",
    "addr:postcode":"33614",
    "addr:street":"W Waters Ave",
    "iso:country":"US",
    "sg:address":"4040 W Waters Ave",
    "sg:city":"Tampa",
    "sg:classifiers":[
        {
            "category":"Banks & Credit Unions",
            "subcategory":"Bank",
            "type":"Services"
        }
    ],
    "sg:phone":"+1 813 886 1164",
    "sg:postcode":"33614",
    "sg:province":"FL",
    "sg:tags":[
        "loan",
        "real estate"
    ],
    "wof:name":"Real Mortgage",
    "wof:placetype":"venue"
},
  "geometry": {"coordinates":[-82.509289,28.025378],"type":"Point"}
}