{
  "type": "Feature",
  "properties": {
    "iso:country":"US",
    "sg:address":"2828 NE 31st Pl",
    "sg:city":"Ocala",
    "sg:classifiers":[
        {
            "category":"Shopping",
            "subcategory":"Hobbies, Toys, & Games",
            "type":"Retail Goods"
        }
    ],
    "sg:phone":"+1 352 369 8309",
    "sg:postcode":"34479",
    "sg:province":"FL",
    "wof:name":"Newred Hobbies",
    "wof:placetype":"venue"
},
  "geometry": {"coordinates":[-82.098235,29.219378],"type":"Point"}
}