{
  "type": "Feature",
  "properties": {
    "iso:country":"US",
    "sg:address":"17780 NW 67th Ave",
    "sg:city":"Hialeah",
    "sg:classifiers":[
        {
            "category":"Home & Garden",
            "subcategory":"Carpets & Floor Coverings",
            "type":"Retail Goods"
        }
    ],
    "sg:phone":"+1 305 817 7600",
    "sg:postcode":"33015",
    "sg:province":"FL",
    "wof:name":"Metropolis Commercial Flooring",
    "wof:placetype":"venue"
},
  "geometry": {"coordinates":[-80.30853,25.934905],"type":"Point"}
}