{
  "type": "Feature",
  "properties": {
    "addr:full":"5850 T G Lee Blvd Orlando FL 32822",
    "addr:housenumber":"5850",
    "addr:postcode":"32822",
    "addr:street":"T G Lee Blvd",
    "iso:country":"US",
    "sg:address":"5850 T G Lee Blvd",
    "sg:city":"Orlando",
    "sg:classifiers":[
        {
            "category":"Banks & Credit Unions",
            "subcategory":"Bank",
            "type":"Services"
        }
    ],
    "sg:phone":"+1 407 438 7025",
    "sg:postcode":"32822",
    "sg:province":"FL",
    "sg:tags":[
        "financing"
    ],
    "sg:website":"www.citifinancial.com",
    "wof:name":"Citi Financial",
    "wof:placetype":"venue"
},
  "geometry": {"coordinates":[-81.308159,28.460327],"type":"Point"}
}