{
  "type": "Feature",
  "properties": {
    "iso:country":"US",
    "sg:address":"207 Hospital Dr NE",
    "sg:city":"Fort Walton Beach",
    "sg:classifiers":[
        {
            "category":"Social Services",
            "subcategory":"Adult Care",
            "type":"Services"
        }
    ],
    "sg:phone":"+1 850 833 9165",
    "sg:postcode":"32548",
    "sg:province":"FL",
    "sg:tags":[
        "residential"
    ],
    "wof:name":"Twin Cities Pavilion",
    "wof:placetype":"venue"
},
  "geometry": {"coordinates":[-86.60299999999999,30.414078],"type":"Point"}
}