{
  "type": "Feature",
  "properties": {
    "iso:country":"US",
    "sg:address":"2440 Golden Gate Blvd W",
    "sg:city":"Naples",
    "sg:classifiers":[
        {
            "category":"Shopping",
            "subcategory":"Bicycles & Sporting Goods",
            "type":"Retail Goods"
        }
    ],
    "sg:phone":"+1 239 649 0073",
    "sg:postcode":"34120",
    "sg:province":"FL",
    "wof:name":"Tree Stand",
    "wof:placetype":"venue"
},
  "geometry": {"coordinates":[-81.65380399999999,26.229251],"type":"Point"}
}