{
  "type": "Feature",
  "properties": {
    "iso:country":"US",
    "sg:address":"1200 Weston Rd",
    "sg:city":"Fort Lauderdale",
    "sg:classifiers":[
        {
            "category":"Insurance",
            "subcategory":"Insurance Agent",
            "type":"Services"
        }
    ],
    "sg:phone":"+1 954 389 6223",
    "sg:postcode":"33326",
    "sg:province":"FL",
    "wof:name":"Automotive Risk Management LLC",
    "wof:placetype":"venue"
},
  "geometry": {"coordinates":[-80.364951,26.105394],"type":"Point"}
}