{
  "type": "Feature",
  "properties": {
    "addr:full":"1222 Quail Ridge Dr Destin FL 32541",
    "addr:housenumber":"1222",
    "addr:postcode":"32541",
    "addr:street":"Quail Ridge Dr",
    "iso:country":"US",
    "sg:address":"1222 Quail Ridge Dr",
    "sg:city":"Destin",
    "sg:classifiers":[
        {
            "category":"Real Estate",
            "subcategory":"Real Estate Agent",
            "type":"Services"
        }
    ],
    "sg:phone":"+1 850 837 5163",
    "sg:postcode":"32541",
    "sg:province":"FL",
    "sg:website":"www.silverbeachcondo.com",
    "wof:name":"B Mitchell Co Inc",
    "wof:placetype":"venue"
},
  "geometry": {"coordinates":[-86.468253,30.390928],"type":"Point"}
}