{
  "type": "Feature",
  "properties": {
    "addr:full":"2851 Spring Heather Pl Oviedo FL 32766",
    "addr:housenumber":"2851",
    "addr:postcode":"32766",
    "addr:street":"Spring Heather Pl",
    "iso:country":"US",
    "sg:address":"2851 Spring Heather Pl",
    "sg:city":"Oviedo",
    "sg:classifiers":[
        {
            "category":"Building & Trades",
            "subcategory":"Plumbing",
            "type":"Services"
        }
    ],
    "sg:phone":"+1 407 359 3838",
    "sg:postcode":"32766",
    "sg:province":"FL",
    "sg:tags":[
        "contractor"
    ],
    "wof:name":"Quality Air Conditioning Svcs",
    "wof:placetype":"venue"
},
  "geometry": {"coordinates":[-81.16204399999999,28.657127],"type":"Point"}
}