{
  "type": "Feature",
  "properties": {
    "iso:country":"US",
    "sg:address":"340 Royal Poinciana Way",
    "sg:city":"Palm Beach",
    "sg:classifiers":[
        {
            "category":"Retail",
            "subcategory":"Photofinishing",
            "type":"Services"
        }
    ],
    "sg:phone":"+1 561 802 9911",
    "sg:postcode":"33480",
    "sg:province":"FL",
    "sg:tags":[
        "photographic"
    ],
    "wof:name":"Mc Pherson Barrett & Assoc",
    "wof:placetype":"venue"
},
  "geometry": {"coordinates":[-80.042129,26.718039],"type":"Point"}
}