{
  "type": "Feature",
  "properties": {
    "iso:country":"US",
    "sg:address":"411 NW Baker Rd",
    "sg:city":"Stuart",
    "sg:classifiers":[
        {
            "category":"Manufacturing",
            "subcategory":"Printing",
            "type":"Manufacturing & Wholesale Goods"
        }
    ],
    "sg:phone":"+1 772 692 7447",
    "sg:postcode":"34994",
    "sg:province":"FL",
    "sg:tags":[
        "multimedia"
    ],
    "wof:name":"Ahooo Media Assoc",
    "wof:placetype":"venue"
},
  "geometry": {"coordinates":[-80.25842,27.222344],"type":"Point"}
}