{
  "type": "Feature",
  "properties": {
    "addr:full":"13014 Palm Beach Blvd Fort Myers FL 33905",
    "addr:housenumber":"13014",
    "addr:postcode":"33905",
    "addr:street":"Palm Beach Blvd",
    "iso:country":"US",
    "sg:address":"13014 Palm Beach Blvd",
    "sg:city":"Fort Myers",
    "sg:classifiers":[
        {
            "category":"Real Estate",
            "subcategory":"Real Estate Agent",
            "type":"Services"
        }
    ],
    "sg:phone":"+1 239 694 6664",
    "sg:postcode":"33905",
    "sg:province":"FL",
    "wof:name":"Shoreside Realty Inc",
    "wof:placetype":"venue"
},
  "geometry": {"coordinates":[-81.750373,26.703955],"type":"Point"}
}