{
  "type": "Feature",
  "properties": {
    "addr:full":"5170 45th Ave N St Petersburg FL 33709",
    "addr:housenumber":"5170",
    "addr:postcode":"33709",
    "addr:street":"45Th Ave N",
    "iso:country":"US",
    "sg:address":"5170 45th Ave N",
    "sg:city":"St Petersburg",
    "sg:classifiers":[
        {
            "category":"Freight",
            "type":"Transportation"
        }
    ],
    "sg:phone":"+1 727 580 0821",
    "sg:postcode":"33709",
    "sg:province":"FL",
    "sg:tags":[
        "hauling",
        "trucking"
    ],
    "wof:name":"B & L Enterprises",
    "wof:placetype":"venue"
},
  "geometry": {"coordinates":[-82.70299799999999,27.812713],"type":"Point"}
}