{
  "type": "Feature",
  "properties": {
    "addr:full":"51 SW 1st St Miami FL 33130",
    "addr:housenumber":"51",
    "addr:postcode":"33130",
    "addr:street":"Sw 1St St",
    "iso:country":"US",
    "sg:address":"51 SW 1st St",
    "sg:city":"Miami",
    "sg:classifiers":[
        {
            "category":"Government",
            "subcategory":"Office",
            "type":"Public Place"
        }
    ],
    "sg:phone":"+1 305 536 7409",
    "sg:postcode":"33130",
    "sg:province":"FL",
    "sg:tags":[
        "case",
        "monitor",
        "bankruptcy"
    ],
    "wof:name":"Trustees Executive Offs For US",
    "wof:placetype":"venue"
},
  "geometry": {"coordinates":[-80.194643,25.773363],"type":"Point"}
}