{
  "type": "Feature",
  "properties": {
    "addr:full":"3712 NW 84 Dr Gainesville FL 32606",
    "addr:housenumber":"3712",
    "addr:postcode":"32606",
    "addr:street":"Nw 84 Dr",
    "iso:country":"US",
    "sg:address":"3712 NW 84 Dr",
    "sg:city":"Gainesville",
    "sg:classifiers":[
        {
            "category":"Manufacturing",
            "subcategory":"Glass & Minerals",
            "type":"Manufacturing & Wholesale Goods"
        }
    ],
    "sg:phone":"+1 352 377 8976",
    "sg:postcode":"32606",
    "sg:province":"FL",
    "sg:tags":[
        "concrete",
        "product",
        "mfg"
    ],
    "wof:name":"Ore Ofe Concrete Products",
    "wof:placetype":"venue"
},
  "geometry": {"coordinates":[-82.431909,29.686564],"type":"Point"}
}