{
  "type": "Feature",
  "properties": {
    "iso:country":"US",
    "sg:address":"4237 NW 37th Ave",
    "sg:city":"Miami",
    "sg:classifiers":[
        {
            "category":"Retail",
            "subcategory":"Auto Repair",
            "type":"Services"
        }
    ],
    "sg:phone":"+1 305 638 7933",
    "sg:postcode":"33142",
    "sg:province":"FL",
    "sg:tags":[
        "automotive",
        "general"
    ],
    "wof:name":"International Auto Electric",
    "wof:placetype":"venue"
},
  "geometry": {"coordinates":[-80.25660999999999,25.813779],"type":"Point"}
}