{
  "type": "Feature",
  "properties": {
    "addr:full":"4701 N Federal Hwy Pompano Beach FL 33064",
    "addr:housenumber":"4701",
    "addr:postcode":"33064",
    "addr:street":"N Federal Hwy",
    "iso:country":"US",
    "sg:address":"4701 N Federal Hwy",
    "sg:city":"Pompano Beach",
    "sg:classifiers":[
        {
            "category":"Wholesale",
            "subcategory":"Electrical",
            "type":"Manufacturing & Wholesale Goods"
        }
    ],
    "sg:phone":"+1 954 783 6900",
    "sg:postcode":"33064",
    "sg:province":"FL",
    "sg:tags":[
        "a",
        "as",
        "parts",
        "electronic"
    ],
    "wof:name":"Sales Engineering Concepts",
    "wof:placetype":"venue"
},
  "geometry": {"coordinates":[-80.09549,26.289748],"type":"Point"}
}