{
  "type": "Feature",
  "properties": {
    "addr:full":"1919 W Albury Pl Dunnellon FL 34434",
    "addr:housenumber":"1919",
    "addr:postcode":"34434",
    "addr:street":"W Albury Pl",
    "iso:country":"US",
    "sg:address":"1919 W Albury Pl",
    "sg:city":"Dunnellon",
    "sg:classifiers":[
        {
            "category":"Health Services",
            "subcategory":"Clinic",
            "type":"Services"
        }
    ],
    "sg:phone":"+1 352 795 8362",
    "sg:postcode":"34434",
    "sg:province":"FL",
    "wof:name":"Seven Rivers Hospital",
    "wof:placetype":"venue"
},
  "geometry": {"coordinates":[-82.467291,29.012716],"type":"Point"}
}