{
  "type": "Feature",
  "properties": {
    "iso:country":"US",
    "sg:address":"1309 Oddfellow Rd",
    "sg:city":"Fort Walton Bch",
    "sg:classifiers":[
        {
            "category":"Manufacturing",
            "subcategory":"Signs",
            "type":"Manufacturing & Wholesale Goods"
        }
    ],
    "sg:phone":"+1 850 314 6840",
    "sg:postcode":"32547",
    "sg:province":"FL",
    "wof:name":"Pryor's Commercial Vehicle",
    "wof:placetype":"venue"
},
  "geometry": {"coordinates":[-86.629884,30.460642],"type":"Point"}
}