{
  "type": "Feature",
  "properties": {
    "iso:country":"US",
    "sg:address":"24 Cathedral Pl",
    "sg:city":"St Augustine",
    "sg:classifiers":[
        {
            "category":"Banks & Credit Unions",
            "subcategory":"Bank",
            "type":"Services"
        }
    ],
    "sg:phone":"+1 904 808 1908",
    "sg:postcode":"32084",
    "sg:province":"FL",
    "sg:tags":[
        "loan",
        "real estate"
    ],
    "sg:website":"www.collateral.com",
    "wof:name":"Collateral Mortgage Capital",
    "wof:placetype":"venue"
},
  "geometry": {"coordinates":[-81.31281199999999,29.892708],"type":"Point"}
}