{
  "type": "Feature",
  "properties": {
    "iso:country":"US",
    "sg:address":"4411 Coconut Creek Blvd",
    "sg:city":"Pompano Beach",
    "sg:classifiers":[
        {
            "category":"Organizations",
            "subcategory":"Community Association",
            "type":"Services"
        }
    ],
    "sg:phone":"+1 954 972 5983",
    "sg:postcode":"33066",
    "sg:province":"FL",
    "wof:name":"Ww 2 Navy Scouting Squad",
    "wof:placetype":"venue"
},
  "geometry": {"coordinates":[-80.182078,26.238088],"type":"Point"}
}