{
  "type": "Feature",
  "properties": {
    "iso:country":"US",
    "sg:address":"410 S Canoe Creek Rd",
    "sg:city":"Kenansville",
    "sg:classifiers":[
        {
            "category":"Freight",
            "type":"Transportation"
        }
    ],
    "sg:phone":"+1 407 436 0208",
    "sg:postcode":"34739",
    "sg:province":"FL",
    "sg:tags":[
        "operator",
        "trucking"
    ],
    "wof:name":"Boos Trucking",
    "wof:placetype":"venue"
},
  "geometry": {"coordinates":[-81.02495,27.876388],"type":"Point"}
}