{
  "type": "Feature",
  "properties": {
    "iso:country":"US",
    "sg:address":"24600 SW 164th Ave",
    "sg:city":"Homestead",
    "sg:classifiers":[
        {
            "category":"Retail",
            "subcategory":"Repair Shop",
            "type":"Services"
        }
    ],
    "sg:phone":"+1 305 969 8448",
    "sg:postcode":"33031",
    "sg:province":"FL",
    "sg:tags":[
        "outboard",
        "motor"
    ],
    "wof:name":"Accurate Outboard",
    "wof:placetype":"venue"
},
  "geometry": {"coordinates":[-80.457724,25.542256],"type":"Point"}
}