{
  "type": "Feature",
  "properties": {
    "addr:full":"19575 State Rd 7 Boca Raton FL 33498",
    "addr:housenumber":"19575",
    "addr:postcode":"33498",
    "addr:street":"State Rd 7",
    "iso:country":"US",
    "sg:address":"19575 State Rd 7",
    "sg:city":"Boca Raton",
    "sg:classifiers":[
        {
            "category":"Shopping",
            "subcategory":"Clothing, Apparel, & Fashions",
            "type":"Retail Goods"
        }
    ],
    "sg:phone":"+1 561 451 8318",
    "sg:postcode":"33498",
    "sg:province":"FL",
    "wof:name":"Antonios",
    "wof:placetype":"venue"
},
  "geometry": {"coordinates":[-80.203715,26.387176],"type":"Point"}
}