{
  "type": "Feature",
  "properties": {
    "addr:full":"950 SW 12th Ave Pompano Beach FL 33069",
    "addr:housenumber":"950",
    "addr:postcode":"33069",
    "addr:street":"Sw 12Th Ave",
    "iso:country":"US",
    "sg:address":"950 SW 12th Ave",
    "sg:city":"Pompano Beach",
    "sg:classifiers":[
        {
            "category":"Manufacturing",
            "subcategory":"Tools & Machinery",
            "type":"Manufacturing & Wholesale Goods"
        }
    ],
    "sg:phone":"+1 954 781 7777",
    "sg:postcode":"33069",
    "sg:province":"FL",
    "sg:tags":[
        "water"
    ],
    "sg:website":"www.aquathin.com",
    "wof:name":"Aquathin Corp",
    "wof:placetype":"venue"
},
  "geometry": {"coordinates":[-80.138543,26.218137],"type":"Point"}
}