{
  "type": "Feature",
  "properties": {
    "addr:full":"5617 NW 7th St Miami FL 33126",
    "addr:housenumber":"5617",
    "addr:postcode":"33126",
    "addr:street":"Nw 7Th St",
    "iso:country":"US",
    "sg:address":"5617 NW 7th St",
    "sg:city":"Miami",
    "sg:classifiers":[
        {
            "category":"Professional",
            "subcategory":"Employment Agencies",
            "type":"Services"
        }
    ],
    "sg:phone":"+1 305 267 3010",
    "sg:postcode":"33126",
    "sg:province":"FL",
    "sg:tags":[
        "contractor"
    ],
    "sg:website":"http://www.hospitalityfurniture.us",
    "wof:name":"Hositality And Healthcare Staffing Inc",
    "wof:placetype":"venue"
},
  "geometry": {"coordinates":[-80.286647,25.778053],"type":"Point"}
}