{
  "type": "Feature",
  "properties": {
    "iso:country":"US",
    "sg:address":"747 S Federal Hwy",
    "sg:city":"Deerfield Beach",
    "sg:classifiers":[
        {
            "category":"Organizations",
            "subcategory":"Religious Organization",
            "type":"Services"
        }
    ],
    "sg:phone":"+1 954 428 8980",
    "sg:postcode":"33441",
    "sg:province":"FL",
    "sg:tags":[
        "school",
        "from",
        "age",
        "miscellaneous",
        "church",
        "denominational"
    ],
    "wof:name":"Christian Love Fllowship Bkstr",
    "wof:placetype":"venue"
},
  "geometry": {"coordinates":[-80.092687,26.307115],"type":"Point"}
}