{
  "type": "Feature",
  "properties": {
    "addr:full":"10155 Guidy Ln Pensacola FL 32514",
    "addr:housenumber":"10155",
    "addr:postcode":"32514",
    "addr:street":"Guidy Ln",
    "iso:country":"US",
    "sg:address":"10155 Guidy Ln",
    "sg:city":"Pensacola",
    "sg:classifiers":[
        {
            "category":"Real Estate",
            "subcategory":"Real Estate Operator",
            "type":"Services"
        }
    ],
    "sg:phone":"+1 850 476 4004",
    "sg:postcode":"32514",
    "sg:province":"FL",
    "sg:tags":[
        "apartment"
    ],
    "wof:name":"Sugar Hill Apartments",
    "wof:placetype":"venue"
},
  "geometry": {"coordinates":[-87.24732299999999,30.546682],"type":"Point"}
}