{
  "type": "Feature",
  "properties": {
    "iso:country":"US",
    "sg:address":"2024 Badlands Dr",
    "sg:city":"Brandon",
    "sg:classifiers":[
        {
            "category":"Restaurant",
            "type":"Food & Drink"
        },
        {
            "category":"Ice Cream",
            "type":"Food & Drink"
        }
    ],
    "sg:phone":"+1 813 689 8873",
    "sg:postcode":"33511",
    "sg:province":"FL",
    "sg:tags":[
        "frozen",
        "dessert"
    ],
    "sg:website":"http://www.coldstonecreamery.com",
    "wof:name":"Cold Stone Creamery",
    "wof:placetype":"venue"
},
  "geometry": {"coordinates":[-82.315701,27.926555],"type":"Point"}
}