{
  "type": "Feature",
  "properties": {
    "iso:country":"US",
    "sg:address":"5100 150th Ave N",
    "sg:city":"Clearwater",
    "sg:classifiers":[
        {
            "category":"Government",
            "subcategory":"Office",
            "type":"Public Place"
        }
    ],
    "sg:phone":"+1 727 518 3080",
    "sg:postcode":"33760",
    "sg:province":"FL",
    "sg:tags":[
        "govt",
        "city"
    ],
    "sg:website":"www.largo.com",
    "wof:name":"Largo Wastewater Treatment",
    "wof:placetype":"venue"
},
  "geometry": {"coordinates":[-82.702519,27.908538],"type":"Point"}
}