{
  "type": "Feature",
  "properties": {
    "iso:country":"US",
    "sg:address":"819 Birdie View Pt",
    "sg:city":"Sanibel",
    "sg:classifiers":[
        {
            "category":"Wholesale",
            "subcategory":"Machinery & Supplies",
            "type":"Manufacturing & Wholesale Goods"
        }
    ],
    "sg:phone":"+1 239 395 9208",
    "sg:postcode":"33957",
    "sg:province":"FL",
    "sg:tags":[
        "equipment",
        "industrial"
    ],
    "wof:name":"Koncept Kreations Ltd",
    "wof:placetype":"venue"
},
  "geometry": {"coordinates":[-82.05034999999999,26.437303],"type":"Point"}
}