{
  "type": "Feature",
  "properties": {
    "iso:country":"US",
    "sg:address":"2225 4th Ave S",
    "sg:city":"St Petersburg",
    "sg:classifiers":[
        {
            "category":"Wholesale",
            "subcategory":"Groceries",
            "type":"Manufacturing & Wholesale Goods"
        }
    ],
    "sg:phone":"+1 727 327 4318",
    "sg:postcode":"33712",
    "sg:province":"FL",
    "sg:tags":[
        "sandwich"
    ],
    "wof:name":"Perry's Sandwich Shop",
    "wof:placetype":"venue"
},
  "geometry": {"coordinates":[-82.664114,27.7675],"type":"Point"}
}