{
  "type": "Feature",
  "properties": {
    "iso:country":"US",
    "sg:address":"1212 54th St S",
    "sg:city":"Saint Petersburg",
    "sg:classifiers":[
        {
            "category":"Autos & Motor Vehicles",
            "subcategory":"Auto Supplies",
            "type":"Retail Goods"
        }
    ],
    "sg:phone":"+1 727 343 5429",
    "sg:postcode":"33707",
    "sg:province":"FL",
    "wof:name":"WD Custom Fit",
    "wof:placetype":"venue"
},
  "geometry": {"coordinates":[-82.706453,27.757791],"type":"Point"}
}