{
  "type": "Feature",
  "properties": {
    "addr:full":"6300 NW 77th Ct Miami FL 33166",
    "addr:housenumber":"6300",
    "addr:postcode":"33166",
    "addr:street":"Nw 77Th Ct",
    "iso:country":"US",
    "sg:address":"6300 NW 77th Ct",
    "sg:city":"Miami",
    "sg:classifiers":[
        {
            "category":"Organizations",
            "subcategory":"Religious Organization",
            "type":"Services"
        }
    ],
    "sg:phone":"+1 305 593 0113",
    "sg:postcode":"33166",
    "sg:province":"FL",
    "wof:name":"Vida Abundance",
    "wof:placetype":"venue"
},
  "geometry": {"coordinates":[-80.32234200000001,25.830784],"type":"Point"}
}