{
  "type": "Feature",
  "properties": {
    "addr:full":"24743 Rodas Dr Bonita Springs FL 34135",
    "addr:postcode":"24743;34135",
    "addr:street":"Rodas Dr",
    "iso:country":"US",
    "sg:address":"24743 Rodas Dr",
    "sg:city":"Bonita Springs",
    "sg:classifiers":[
        {
            "category":"Retail",
            "subcategory":"Auto Repair",
            "type":"Services"
        }
    ],
    "sg:phone":"+1 239 992 4330",
    "sg:postcode":"34135",
    "sg:province":"FL",
    "sg:tags":[
        "tire"
    ],
    "wof:name":"Durham Tire Service",
    "wof:placetype":"venue"
},
  "geometry": {"coordinates":[-81.799881,26.379441],"type":"Point"}
}