{
  "type": "Feature",
  "properties": {
    "iso:country":"US",
    "sg:address":"430 NE 121st St",
    "sg:city":"Miami",
    "sg:classifiers":[
        {
            "category":"Recreation",
            "type":"Entertainment"
        }
    ],
    "sg:phone":"+1 305 754 2007",
    "sg:postcode":"33161",
    "sg:province":"FL",
    "wof:name":"Aquachild Inc",
    "wof:placetype":"venue"
},
  "geometry": {"coordinates":[-80.18940000000001,25.88646],"type":"Point"}
}