{
  "type": "Feature",
  "properties": {
    "addr:full":"7700 N Kendall Dr Ste 302 Miami FL 33156",
    "addr:housenumber":"7700",
    "addr:postcode":"33156",
    "addr:street":"N Kendall Dr Ste 302",
    "iso:country":"US",
    "sg:address":"7700 N Kendall Dr Ste 302",
    "sg:city":"Miami",
    "sg:classifiers":[
        {
            "category":"Education",
            "subcategory":"Special Training",
            "type":"Public Place"
        }
    ],
    "sg:phone":"+1 305 279 5877",
    "sg:postcode":"33156",
    "sg:province":"FL",
    "sg:tags":[
        "educational"
    ],
    "sg:website":"www.sctrain.edu",
    "wof:name":"Sullivan and Cogliano Training Center Inc",
    "wof:placetype":"venue"
},
  "geometry": {"coordinates":[-80.320424,25.687488],"type":"Point"}
}