{
  "type": "Feature",
  "properties": {
    "iso:country":"US",
    "sg:address":"1300 Galleon Dr",
    "sg:city":"Naples",
    "sg:classifiers":[
        {
            "category":"Professional",
            "subcategory":"Business Services",
            "type":"Services"
        }
    ],
    "sg:phone":"+1 239 649 1343",
    "sg:postcode":"34102",
    "sg:province":"FL",
    "sg:tags":[
        "interior",
        "consultant",
        "design",
        "decorator"
    ],
    "wof:name":"Sharon E Smith Creative",
    "wof:placetype":"venue"
},
  "geometry": {"coordinates":[-81.789438,26.112088],"type":"Point"}
}