{
  "type": "Feature",
  "properties": {
    "addr:full":"12429 S Orange Blossom Trl Orlando FL 32837",
    "addr:housenumber":"12429",
    "addr:postcode":"32837",
    "addr:street":"S Orange Blossom Trl",
    "iso:country":"US",
    "sg:address":"12429 S Orange Blossom Trl",
    "sg:city":"Orlando",
    "sg:classifiers":[
        {
            "category":"Restaurant",
            "type":"Food & Drink"
        }
    ],
    "sg:menulink":"http://www.allmenus.com/fl/southwest-orange/81349-papa-johns-pizza/menu/",
    "sg:phone":"+1 407 856 7272",
    "sg:postcode":"32837",
    "sg:province":"FL",
    "sg:tags":[
        "american",
        "pizza"
    ],
    "wof:name":"Papa John's Pizza",
    "wof:placetype":"venue"
},
  "geometry": {"coordinates":[-81.40443399999999,28.384589],"type":"Point"}
}