{
  "type": "Feature",
  "properties": {
    "addr:full":"1021 N Pine Hills Rd Orlando FL 32808",
    "addr:housenumber":"1021",
    "addr:postcode":"32808",
    "addr:street":"N Pine Hills Rd",
    "iso:country":"US",
    "sg:address":"1021 N Pine Hills Rd",
    "sg:city":"Orlando",
    "sg:classifiers":[
        {
            "category":"Social Services",
            "subcategory":"Child Care",
            "type":"Services"
        }
    ],
    "sg:phone":"+1 407 294 7359",
    "sg:postcode":"32808",
    "sg:province":"FL",
    "wof:name":"Seashell's Child Care",
    "wof:placetype":"venue"
},
  "geometry": {"coordinates":[-81.44940099999999,28.559396],"type":"Point"}
}