{
  "type": "Feature",
  "properties": {
    "addr:full":"2981 Blairstone Ct Tallahassee FL 32301",
    "addr:housenumber":"2981",
    "addr:postcode":"32301",
    "addr:street":"Blairstone Ct",
    "iso:country":"US",
    "sg:address":"2981 Blairstone Ct",
    "sg:city":"Tallahassee",
    "sg:classifiers":[
        {
            "category":"Real Estate",
            "subcategory":"Real Estate Operator",
            "type":"Services"
        }
    ],
    "sg:phone":"+1 850 878 2563",
    "sg:postcode":"32301",
    "sg:province":"FL",
    "sg:tags":[
        "property",
        "lessor"
    ],
    "wof:name":"Claryne H Henry",
    "wof:placetype":"venue"
},
  "geometry": {"coordinates":[-84.251233,30.420302],"type":"Point"}
}