{
  "type": "Feature",
  "properties": {
    "iso:country":"US",
    "sg:address":"1968 43rd Ave",
    "sg:city":"Vero Beach",
    "sg:classifiers":[
        {
            "category":"Professional",
            "subcategory":"Computer Services",
            "type":"Services"
        }
    ],
    "sg:phone":"+1 772 569 2950",
    "sg:postcode":"32960",
    "sg:province":"FL",
    "sg:tags":[
        "network"
    ],
    "wof:name":"Autobahn Communications",
    "wof:placetype":"venue"
},
  "geometry": {"coordinates":[-80.430125,27.63714],"type":"Point"}
}