{
  "type": "Feature",
  "properties": {
    "iso:country":"US",
    "sg:address":"8125 W 9th Ct",
    "sg:city":"Hialeah",
    "sg:classifiers":[
        {
            "category":"Professional",
            "subcategory":"Management & Consulting",
            "type":"Services"
        }
    ],
    "sg:phone":"+1 305 362 4339",
    "sg:postcode":"33014",
    "sg:province":"FL",
    "sg:tags":[
        "specializing",
        "information",
        "system",
        "i",
        "consultant"
    ],
    "wof:name":"Telematic Computer Intl",
    "wof:placetype":"venue"
},
  "geometry": {"coordinates":[-80.30243900000001,25.897048],"type":"Point"}
}