{
  "type": "Feature",
  "properties": {
    "iso:country":"US",
    "sg:address":"1420 Atlantic Shores Blvd",
    "sg:city":"Hallandale",
    "sg:classifiers":[
        {
            "category":"Wholesale",
            "subcategory":"Non-durable Goods",
            "type":"Manufacturing & Wholesale Goods"
        }
    ],
    "sg:phone":"+1 954 458 2900",
    "sg:postcode":"33009",
    "sg:province":"FL",
    "wof:name":"Vsa Import Export Inc",
    "wof:placetype":"venue"
},
  "geometry": {"coordinates":[-80.134311,25.995083],"type":"Point"}
}