{
  "type": "Feature",
  "properties": {
    "iso:country":"US",
    "sg:address":"5818 SW 27th St",
    "sg:city":"Miami",
    "sg:classifiers":[
        {
            "category":"Building & Trades",
            "subcategory":"Construction",
            "type":"Services"
        }
    ],
    "sg:phone":"+1 305 665 2098",
    "sg:postcode":"33155",
    "sg:province":"FL",
    "sg:tags":[
        "concrete",
        "contractor"
    ],
    "wof:name":"Imar Concrete Corp",
    "wof:placetype":"venue"
},
  "geometry": {"coordinates":[-80.291022,25.745507],"type":"Point"}
}