{
  "type": "Feature",
  "properties": {
    "addr:full":"7854 Saddle Creek Trl Sarasota FL 34241",
    "addr:housenumber":"7854",
    "addr:postcode":"34241",
    "addr:street":"Saddle Creek Trl",
    "iso:country":"US",
    "sg:address":"7854 Saddle Creek Trl",
    "sg:city":"Sarasota",
    "sg:classifiers":[
        {
            "category":"Building & Trades",
            "subcategory":"Construction",
            "type":"Services"
        }
    ],
    "sg:phone":"+1 941 926 1167",
    "sg:postcode":"34241",
    "sg:province":"FL",
    "sg:tags":[
        "excavation",
        "contractor"
    ],
    "wof:name":"Ralph Plank Excavating Inc",
    "wof:placetype":"venue"
},
  "geometry": {"coordinates":[-82.377757,27.257561],"type":"Point"}
}