{
  "type": "Feature",
  "properties": {
    "addr:full":"1201 SW 21st Ave Boca Raton FL 33486",
    "addr:housenumber":"1201",
    "addr:postcode":"33486",
    "addr:street":"Sw 21St Ave",
    "iso:country":"US",
    "sg:address":"1201 SW 21st Ave",
    "sg:city":"Boca Raton",
    "sg:classifiers":[
        {
            "category":"Real Estate",
            "subcategory":"Real Estate Operator",
            "type":"Services"
        }
    ],
    "sg:phone":"+1 561 362 5416",
    "sg:postcode":"33486",
    "sg:province":"FL",
    "sg:tags":[
        "building",
        "nonresidential"
    ],
    "wof:name":"Margo Partnership LLC",
    "wof:placetype":"venue"
},
  "geometry": {"coordinates":[-80.125747,26.340524],"type":"Point"}
}