{
  "type": "Feature",
  "properties": {
    "addr:full":"2618 San Domingo St Miami FL 33134",
    "addr:housenumber":"2618",
    "addr:postcode":"33134",
    "addr:street":"San Domingo St",
    "iso:country":"US",
    "sg:address":"2618 San Domingo St",
    "sg:city":"Miami",
    "sg:classifiers":[
        {
            "category":"Building & Trades",
            "subcategory":"Construction",
            "type":"Services"
        }
    ],
    "sg:phone":"+1 305 445 1972",
    "sg:postcode":"33134",
    "sg:province":"FL",
    "sg:tags":[
        "house",
        "family"
    ],
    "wof:name":"Grandhaus Corp",
    "wof:placetype":"venue"
},
  "geometry": {"coordinates":[-80.282568,25.745004],"type":"Point"}
}