{
  "type": "Feature",
  "properties": {
    "addr:full":"8143 SW 162nd Path Miami FL 33193",
    "addr:housenumber":"8143",
    "addr:postcode":"33193",
    "addr:street":"Sw 162Nd Path",
    "iso:country":"US",
    "sg:address":"8143 SW 162nd Path",
    "sg:city":"Miami",
    "sg:classifiers":[
        {
            "category":"Freight",
            "type":"Transportation"
        }
    ],
    "sg:phone":"+1 305 388 0767",
    "sg:postcode":"33193",
    "sg:province":"FL",
    "sg:tags":[
        "delivery"
    ],
    "wof:name":"Better Delivery Express Corp",
    "wof:placetype":"venue"
},
  "geometry": {"coordinates":[-80.455788,25.689704],"type":"Point"}
}