{
  "type": "Feature",
  "properties": {
    "iso:country":"US",
    "sg:address":"2664 Riverport Dr N",
    "sg:city":"Jacksonville",
    "sg:classifiers":[
        {
            "category":"Professional",
            "subcategory":"Research",
            "type":"Services"
        }
    ],
    "sg:phone":"+1 904 262 8658",
    "sg:postcode":"32223",
    "sg:province":"FL",
    "sg:tags":[
        "commercial",
        "physical"
    ],
    "wof:name":"American Technical Laboratory",
    "wof:placetype":"venue"
},
  "geometry": {"coordinates":[-81.64002499999999,30.175672],"type":"Point"}
}