{
  "type": "Feature",
  "properties": {
    "iso:country":"US",
    "sg:address":"418 Macarthur Ave",
    "sg:city":"Sarasota",
    "sg:classifiers":[
        {
            "category":"Wholesale",
            "subcategory":"Groceries",
            "type":"Manufacturing & Wholesale Goods"
        }
    ],
    "sg:phone":"+1 941 359 1187",
    "sg:postcode":"34243",
    "sg:province":"FL",
    "sg:tags":[
        "food",
        "product",
        "health"
    ],
    "wof:name":"Kaufman Enterprises",
    "wof:placetype":"venue"
},
  "geometry": {"coordinates":[-82.56744500000001,27.411203],"type":"Point"}
}