{
  "type": "Feature",
  "properties": {
    "iso:country":"US",
    "sg:address":"42 Somerset Dr",
    "sg:city":"Largo",
    "sg:classifiers":[
        {
            "category":"Real Estate",
            "subcategory":"Real Estate Operator",
            "type":"Services"
        }
    ],
    "sg:phone":"+1 727 483 2442",
    "sg:postcode":"33773",
    "sg:province":"FL",
    "sg:tags":[
        "apartment"
    ],
    "wof:name":"Lacasa Apts",
    "wof:placetype":"venue"
},
  "geometry": {"coordinates":[-82.762367,27.883676],"type":"Point"}
}