{
  "type": "Feature",
  "properties": {
    "iso:country":"US",
    "sg:address":"1429 Eden Dr",
    "sg:city":"Apopka",
    "sg:classifiers":[
        {
            "category":"Home & Garden",
            "subcategory":"Carpets & Floor Coverings",
            "type":"Retail Goods"
        }
    ],
    "sg:phone":"+1 407 886 0591",
    "sg:postcode":"32703",
    "sg:province":"FL",
    "wof:name":"Rojas Carpeting Service Inc",
    "wof:placetype":"venue"
},
  "geometry": {"coordinates":[-81.48339199999999,28.660411],"type":"Point"}
}