{
  "type": "Feature",
  "properties": {
    "iso:country":"US",
    "sg:address":"1258 Rockledge Blvd",
    "sg:city":"Rockledge",
    "sg:classifiers":[
        {
            "category":"Retail",
            "subcategory":"Auto Repair",
            "type":"Services"
        }
    ],
    "sg:phone":"+1 321 690 1233",
    "sg:postcode":"32955",
    "sg:province":"FL",
    "sg:tags":[
        "repairing",
        "automobile"
    ],
    "wof:name":"Bavarian Auto Ctr",
    "wof:placetype":"venue"
},
  "geometry": {"coordinates":[-80.72646899999999,28.337232],"type":"Point"}
}