{
  "type": "Feature",
  "properties": {
    "addr:full":"12650 Pines Blvd Pembroke Pines FL 33027",
    "addr:housenumber":"12650",
    "addr:postcode":"33027",
    "addr:street":"Pines Blvd",
    "iso:country":"US",
    "sg:address":"12650 Pines Blvd",
    "sg:city":"Pembroke Pines",
    "sg:classifiers":[
        {
            "category":"Restaurant",
            "type":"Food & Drink"
        }
    ],
    "sg:phone":"+1 954 436 5583",
    "sg:postcode":"33027",
    "sg:province":"FL",
    "sg:website":"www.wendys.com",
    "wof:name":"Wendy's",
    "wof:placetype":"venue"
},
  "geometry": {"coordinates":[-80.317168,26.007774],"type":"Point"}
}