{
  "type": "Feature",
  "properties": {
    "addr:full":"234 N Seagrave St Daytona Beach FL 32114",
    "addr:housenumber":"234",
    "addr:postcode":"32114",
    "addr:street":"N Seagrave St",
    "iso:country":"US",
    "sg:address":"234 N Seagrave St",
    "sg:city":"Daytona Beach",
    "sg:classifiers":[
        {
            "category":"Utilities",
            "subcategory":"Electric",
            "type":"Services"
        }
    ],
    "sg:phone":"+1 386 239 5924",
    "sg:postcode":"32114",
    "sg:province":"FL",
    "wof:name":"FPL",
    "wof:placetype":"venue"
},
  "geometry": {"coordinates":[-81.026432,29.213666],"type":"Point"}
}