{
  "type": "Feature",
  "properties": {
    "iso:country":"US",
    "sg:address":"153 SE 10th Ter",
    "sg:city":"Cape Coral",
    "sg:classifiers":[
        {
            "category":"Shopping",
            "subcategory":"Clothing, Apparel, & Fashions",
            "type":"Retail Goods"
        }
    ],
    "sg:phone":"+1 239 574 8064",
    "sg:postcode":"33990",
    "sg:province":"FL",
    "sg:tags":[
        "alteration"
    ],
    "wof:name":"Stice's Professional Sewing",
    "wof:placetype":"venue"
},
  "geometry": {"coordinates":[-81.97095899999999,26.633442],"type":"Point"}
}