{
  "type": "Feature",
  "properties": {
    "iso:country":"US",
    "sg:address":"538 86th Ave N",
    "sg:city":"Saint Petersburg",
    "sg:classifiers":[
        {
            "category":"Health Services",
            "subcategory":"Nursing And Care Facility",
            "type":"Services"
        }
    ],
    "sg:phone":"+1 727 577 1410",
    "sg:postcode":"33702",
    "sg:province":"FL",
    "sg:tags":[
        "intermediate"
    ],
    "wof:name":"Mace Health & Rehabilitation",
    "wof:placetype":"venue"
},
  "geometry": {"coordinates":[-82.638972,27.850653],"type":"Point"}
}