{
  "type": "Feature",
  "properties": {
    "iso:country":"US",
    "sg:address":"6431 SW 64th Ct",
    "sg:city":"South Miami",
    "sg:classifiers":[
        {
            "category":"Building & Trades",
            "subcategory":"Landscaping Services",
            "type":"Services"
        }
    ],
    "sg:phone":"+1 305 663 2456",
    "sg:postcode":"33143",
    "sg:province":"FL",
    "sg:tags":[
        "tree"
    ],
    "wof:name":"Parks' Tree Svc",
    "wof:placetype":"venue"
},
  "geometry": {"coordinates":[-80.298653,25.709584],"type":"Point"}
}