{
  "type": "Feature",
  "properties": {
    "iso:country":"US",
    "sg:address":"2835 River Oak Dr",
    "sg:city":"Orange Park",
    "sg:classifiers":[
        {
            "category":"Building & Trades",
            "subcategory":"Construction",
            "type":"Services"
        }
    ],
    "sg:phone":"+1 904 215 9609",
    "sg:postcode":"32073",
    "sg:province":"FL",
    "sg:tags":[
        "hanging",
        "contractor"
    ],
    "wof:name":"Rl Wagner Painting Inc",
    "wof:placetype":"venue"
},
  "geometry": {"coordinates":[-81.741896,30.148222],"type":"Point"}
}