{
  "type": "Feature",
  "properties": {
    "addr:full":"8001 NW 60th St Miami FL 33166",
    "addr:housenumber":"8001",
    "addr:postcode":"33166",
    "addr:street":"Nw 60Th St",
    "iso:country":"US",
    "sg:address":"8001 NW 60th St",
    "sg:city":"Miami",
    "sg:classifiers":[
        {
            "category":"Manufacturing",
            "subcategory":"Food",
            "type":"Manufacturing & Wholesale Goods"
        },
        {
            "category":"Food & Beverages",
            "subcategory":"Groceries & Convenience Stores",
            "type":"Retail Goods"
        }
    ],
    "sg:phone":"+1 305 592 5558",
    "sg:postcode":"33166",
    "sg:province":"FL",
    "sg:tags":[
        "processing"
    ],
    "wof:name":"A R A Food Corp",
    "wof:placetype":"venue"
},
  "geometry": {"coordinates":[-80.327201,25.828066],"type":"Point"}
}