{
  "type": "Feature",
  "properties": {
    "addr:full":"10103 Adamo Dr Tampa FL 33619",
    "addr:housenumber":"10103",
    "addr:postcode":"33619",
    "addr:street":"Adamo Dr",
    "iso:country":"US",
    "sg:address":"10103 Adamo Dr",
    "sg:city":"Tampa",
    "sg:classifiers":[
        {
            "category":"Building & Trades",
            "subcategory":"Equipment Rental",
            "type":"Services"
        }
    ],
    "sg:phone":"+1 813 622 8223",
    "sg:postcode":"33619",
    "sg:province":"FL",
    "sg:tags":[
        "leasing",
        "furniture"
    ],
    "wof:name":"Aarons Sales & Lease Ownership",
    "wof:placetype":"venue"
},
  "geometry": {"coordinates":[-82.335239,27.943748],"type":"Point"}
}