{
  "type": "Feature",
  "properties": {
    "addr:full":"3930 E Silver Springs Blvd Ocala FL 34470",
    "addr:housenumber":"3930",
    "addr:postcode":"34470",
    "addr:street":"E Silver Springs Blvd",
    "iso:country":"US",
    "sg:address":"3930 E Silver Springs Blvd",
    "sg:city":"Ocala",
    "sg:classifiers":[
        {
            "category":"Health Services",
            "subcategory":"Nursing And Care Facility",
            "type":"Services"
        }
    ],
    "sg:phone":"+1 352 236 2626",
    "sg:postcode":"34470",
    "sg:province":"FL",
    "sg:tags":[
        "home",
        "skilled",
        "convalescent"
    ],
    "wof:name":"Marion House Health Care Ctr",
    "wof:placetype":"venue"
},
  "geometry": {"coordinates":[-82.081042,29.201266],"type":"Point"}
}