{
  "type": "Feature",
  "properties": {
    "iso:country":"US",
    "sg:address":"2420 N Tamarind Ave Exd",
    "sg:city":"West Palm Beach",
    "sg:classifiers":[
        {
            "category":"Taxi",
            "type":"Transportation"
        }
    ],
    "sg:phone":"+1 561 833 2223",
    "sg:postcode":"33407",
    "sg:province":"FL",
    "sg:tags":[
        "taxicab"
    ],
    "wof:name":"G S Taxi & Limo Svc",
    "wof:placetype":"venue"
},
  "geometry": {"coordinates":[-80.06109499999999,26.736163],"type":"Point"}
}