{
  "type": "Feature",
  "properties": {
    "iso:country":"US",
    "sg:address":"10088 Idle Pine Ln",
    "sg:city":"Bonita Springs",
    "sg:classifiers":[
        {
            "category":"Real Estate",
            "subcategory":"Real Estate Agent",
            "type":"Services"
        }
    ],
    "sg:phone":"+1 239 947 8384",
    "sg:postcode":"34135",
    "sg:province":"FL",
    "wof:name":"Trudy Salyers",
    "wof:placetype":"venue"
},
  "geometry": {"coordinates":[-81.7865,26.403122],"type":"Point"}
}