{
  "type": "Feature",
  "properties": {
    "iso:country":"US",
    "sg:address":"2419 Morgan Point Blvd",
    "sg:city":"Kissimmee",
    "sg:classifiers":[
        {
            "category":"Building & Trades",
            "subcategory":"Pest Control",
            "type":"Services"
        }
    ],
    "sg:phone":"+1 407 729 8942",
    "sg:postcode":"34743",
    "sg:province":"FL",
    "wof:name":"Emto Lab Environmental Svc Inc",
    "wof:placetype":"venue"
},
  "geometry": {"coordinates":[-81.351399,28.318022],"type":"Point"}
}