{
  "type": "Feature",
  "properties": {
    "iso:country":"US",
    "sg:address":"7345 W Flagler St",
    "sg:city":"Miami",
    "sg:classifiers":[
        {
            "category":"Health Services",
            "subcategory":"Medical Lab",
            "type":"Services"
        }
    ],
    "sg:phone":"+1 305 266 6106",
    "sg:postcode":"33144",
    "sg:province":"FL",
    "sg:tags":[
        "laboratory",
        "testing"
    ],
    "wof:name":"Accion Dental Lab",
    "wof:placetype":"venue"
},
  "geometry": {"coordinates":[-80.31500200000001,25.770135],"type":"Point"}
}