{
  "type": "Feature",
  "properties": {
    "iso:country":"US",
    "sg:address":"8430 NW 68th St",
    "sg:city":"Miami",
    "sg:classifiers":[
        {
            "category":"Shopping",
            "subcategory":"Clothing, Apparel, & Fashions",
            "type":"Retail Goods"
        }
    ],
    "sg:phone":"+1 786 845 0693",
    "sg:postcode":"33166",
    "sg:province":"FL",
    "sg:tags":[
        "t"
    ],
    "wof:name":"MIC Apparel",
    "wof:placetype":"venue"
},
  "geometry": {"coordinates":[-80.33766900000001,25.835169],"type":"Point"}
}