{
  "type": "Feature",
  "properties": {
    "iso:country":"US",
    "sg:address":"609 Camilla Ave",
    "sg:city":"Quincy",
    "sg:classifiers":[
        {
            "category":"Organizations",
            "subcategory":"Religious Organization",
            "type":"Services"
        }
    ],
    "sg:phone":"+1 850 875 3984",
    "sg:postcode":"32351",
    "sg:province":"FL",
    "sg:tags":[
        "church"
    ],
    "wof:name":"Faith Temple Of Jesus Christ",
    "wof:placetype":"venue"
},
  "geometry": {"coordinates":[-84.59805799999999,30.579862],"type":"Point"}
}