{
  "type": "Feature",
  "properties": {
    "addr:full":"13312 Cain Rd Tampa FL 33625",
    "addr:housenumber":"13312",
    "addr:postcode":"33625",
    "addr:street":"Cain Rd",
    "iso:country":"US",
    "sg:address":"13312 Cain Rd",
    "sg:city":"Tampa",
    "sg:classifiers":[
        {
            "category":"Organizations",
            "subcategory":"Religious Organization",
            "type":"Services"
        }
    ],
    "sg:phone":"+1 813 962 3089",
    "sg:postcode":"33625",
    "sg:province":"FL",
    "sg:tags":[
        "church"
    ],
    "sg:website":"www.stmarkstampa.org",
    "wof:name":"St Mark's Episcopal Church",
    "wof:placetype":"venue"
},
  "geometry": {"coordinates":[-82.557889,28.06626],"type":"Point"}
}