{
  "type": "Feature",
  "properties": {
    "addr:full":"6036 Park Blvd Pinellas Park FL 33781",
    "addr:housenumber":"6036",
    "addr:postcode":"33781",
    "addr:street":"Park Blvd",
    "iso:country":"US",
    "sg:address":"6036 Park Blvd",
    "sg:city":"Pinellas Park",
    "sg:classifiers":[
        {
            "category":"Health Services",
            "subcategory":"Doctor",
            "type":"Services"
        }
    ],
    "sg:phone":"+1 727 549 2105",
    "sg:postcode":"33781",
    "sg:province":"FL",
    "sg:tags":[
        "physician",
        "surgeon"
    ],
    "wof:name":"Pinellas Eye Care",
    "wof:placetype":"venue"
},
  "geometry": {"coordinates":[-82.716211,27.839106],"type":"Point"}
}