{
  "type": "Feature",
  "properties": {
    "addr:full":"4101 SW 47th Ave Davie FL 33314",
    "addr:housenumber":"4101",
    "addr:postcode":"33314",
    "addr:street":"Sw 47Th Ave",
    "iso:country":"US",
    "sg:address":"4101 SW 47th Ave",
    "sg:city":"Davie",
    "sg:classifiers":[
        {
            "category":"Professional",
            "subcategory":"Management & Consulting",
            "type":"Services"
        }
    ],
    "sg:phone":"+1 954 791 1225",
    "sg:postcode":"33314",
    "sg:province":"FL",
    "sg:tags":[
        "fuel"
    ],
    "wof:name":"Roberts Management Co Inc",
    "wof:placetype":"venue"
},
  "geometry": {"coordinates":[-80.21025899999999,26.072552],"type":"Point"}
}