{
  "type": "Feature",
  "properties": {
    "addr:full":"6510 N Armenia Ave Tampa FL 33604",
    "addr:housenumber":"6510",
    "addr:postcode":"33604",
    "addr:street":"N Armenia Ave",
    "iso:country":"US",
    "sg:address":"6510 N Armenia Ave",
    "sg:city":"Tampa",
    "sg:classifiers":[
        {
            "category":"Personal",
            "type":"Services"
        }
    ],
    "sg:phone":"+1 813 931 3045",
    "sg:postcode":"33604",
    "sg:province":"FL",
    "sg:tags":[
        "therapist",
        "massage"
    ],
    "wof:name":"Advanced Massage Center",
    "wof:placetype":"venue"
},
  "geometry": {"coordinates":[-82.48446300000001,28.0074],"type":"Point"}
}