{
  "type": "Feature",
  "properties": {
    "iso:country":"US",
    "sg:address":"14399 Hid Dugger Rd",
    "sg:city":"Sanderson",
    "sg:classifiers":[
        {
            "category":"Building & Trades",
            "subcategory":"Landscaping Services",
            "type":"Services"
        }
    ],
    "sg:phone":"+1 904 275 2853",
    "sg:postcode":"32087",
    "sg:province":"FL",
    "sg:tags":[
        "tree"
    ],
    "wof:name":"Twh Crane Service Inc",
    "wof:placetype":"venue"
},
  "geometry": {"coordinates":[-82.278417,30.277695],"type":"Point"}
}