{
  "type": "Feature",
  "properties": {
    "addr:full":"17331 Dona Michelle Dr Tampa FL 33647",
    "addr:postcode":"17331;33647",
    "addr:street":"Michelle Dr",
    "iso:country":"US",
    "sg:address":"17331 Dona Michelle Dr",
    "sg:city":"Tampa",
    "sg:classifiers":[
        {
            "category":"Home & Garden",
            "subcategory":"Building Materials",
            "type":"Retail Goods"
        },
        {
            "category":"Professional",
            "subcategory":"Business Services",
            "type":"Services"
        }
    ],
    "sg:phone":"+1 813 910 2741",
    "sg:postcode":"33647",
    "sg:province":"FL",
    "sg:tags":[
        "interior",
        "consultant",
        "design",
        "decorator"
    ],
    "wof:name":"Sherwin-Williams Paints",
    "wof:placetype":"venue"
},
  "geometry": {"coordinates":[-82.368591,28.125381],"type":"Point"}
}