{
  "type": "Feature",
  "properties": {
    "addr:full":"605 Crescent Executive Ct Lake Mary FL 32746",
    "addr:housenumber":"605",
    "addr:postcode":"32746",
    "addr:street":"Crescent Executive Ct",
    "iso:country":"US",
    "sg:address":"605 Crescent Executive Ct",
    "sg:city":"Lake Mary",
    "sg:classifiers":[
        {
            "category":"Professional",
            "type":"Services"
        }
    ],
    "sg:phone":"+1 407 585 2233",
    "sg:postcode":"32746",
    "sg:province":"FL",
    "sg:tags":[
        "establishment"
    ],
    "wof:name":"Upstanding",
    "wof:placetype":"venue"
},
  "geometry": {"coordinates":[-81.34457399999999,28.754808],"type":"Point"}
}