{
  "type": "Feature",
  "properties": {
    "iso:country":"US",
    "sg:address":"10843 NW 27th Ave",
    "sg:city":"Miami",
    "sg:classifiers":[
        {
            "category":"Personal",
            "subcategory":"Beauty Salon",
            "type":"Services"
        }
    ],
    "sg:phone":"+1 305 687 2986",
    "sg:postcode":"33167",
    "sg:province":"FL",
    "wof:name":"Blueprint Unisex",
    "wof:placetype":"venue"
},
  "geometry": {"coordinates":[-80.24268499999999,25.874126],"type":"Point"}
}