{
  "type": "Feature",
  "properties": {
    "addr:full":"5285 Palmetto Dr Melbourne Beach FL 32951",
    "addr:housenumber":"5285",
    "addr:postcode":"32951",
    "addr:street":"Palmetto Dr",
    "iso:country":"US",
    "sg:address":"5285 Palmetto Dr",
    "sg:city":"Melbourne Beach",
    "sg:classifiers":[
        {
            "category":"Building & Trades",
            "subcategory":"Construction",
            "type":"Services"
        }
    ],
    "sg:phone":"+1 321 729 9689",
    "sg:postcode":"32951",
    "sg:province":"FL",
    "sg:tags":[
        "coping",
        "plastering",
        "tiling",
        "pool",
        "swimming"
    ],
    "wof:name":"Abracadabra Pool Svc",
    "wof:placetype":"venue"
},
  "geometry": {"coordinates":[-80.51702299999999,27.980264],"type":"Point"}
}