{
  "type": "Feature",
  "properties": {
    "addr:full":"222 W Comstock Ave Ste 112 Winter Park FL 32789",
    "addr:housenumber":"222",
    "addr:postcode":"32789",
    "addr:street":"W Comstock Ave Ste 112",
    "iso:country":"US",
    "sg:address":"222 W Comstock Ave Ste 112",
    "sg:city":"Winter Park",
    "sg:classifiers":[
        {
            "category":"Banks & Credit Unions",
            "subcategory":"Financial Services",
            "type":"Services"
        }
    ],
    "sg:phone":"+1 407 644 7579",
    "sg:postcode":"32789",
    "sg:province":"FL",
    "sg:tags":[
        "broker",
        "mortgage"
    ],
    "wof:name":"Winter Park Financial Inc",
    "wof:placetype":"venue"
},
  "geometry": {"coordinates":[-81.352501,28.594],"type":"Point"}
}