{
  "type": "Feature",
  "properties": {
    "iso:country":"US",
    "sg:address":"756 River Boat Cir",
    "sg:city":"Orlando",
    "sg:classifiers":[
        {
            "category":"Building & Trades",
            "subcategory":"Construction",
            "type":"Services"
        }
    ],
    "sg:phone":"+1 407 381 1439",
    "sg:postcode":"32828",
    "sg:province":"FL",
    "sg:tags":[
        "engineering",
        "contractor"
    ],
    "wof:name":"Power Acoustics Inc",
    "wof:placetype":"venue"
},
  "geometry": {"coordinates":[-81.20019000000001,28.535111],"type":"Point"}
}