{
  "type": "Feature",
  "properties": {
    "iso:country":"US",
    "sg:address":"1725 Hangar Rd",
    "sg:city":"Sanford",
    "sg:classifiers":[
        {
            "category":"Professional",
            "type":"Services"
        }
    ],
    "sg:phone":"+1 407 323 4710",
    "sg:postcode":"32773",
    "sg:province":"FL",
    "sg:tags":[
        "establishment"
    ],
    "wof:name":"Usda-Aphis Ppq",
    "wof:placetype":"venue"
},
  "geometry": {"coordinates":[-81.24839900000001,28.773471],"type":"Point"}
}