{
  "type": "Feature",
  "properties": {
    "addr:full":"4747 Allen Rd Zephyrhills FL 33541",
    "addr:housenumber":"4747",
    "addr:postcode":"33541",
    "addr:street":"Allen Rd",
    "iso:country":"US",
    "sg:address":"4747 Allen Rd",
    "sg:city":"Zephyrhills",
    "sg:classifiers":[
        {
            "category":"Insurance",
            "subcategory":"Insurance Agent",
            "type":"Services"
        }
    ],
    "sg:phone":"+1 813 788 5558",
    "sg:postcode":"33541",
    "sg:province":"FL",
    "wof:name":"Ameri-Life & Health Svc",
    "wof:placetype":"venue"
},
  "geometry": {"coordinates":[-82.205091,28.229188],"type":"Point"}
}