{
  "type": "Feature",
  "properties": {
    "addr:full":"5500 Thomasville Rd Tallahassee FL 32312",
    "addr:housenumber":"5500",
    "addr:postcode":"32312",
    "addr:street":"Thomasville Rd",
    "iso:country":"US",
    "sg:address":"5500 Thomasville Rd",
    "sg:city":"Tallahassee",
    "sg:classifiers":[
        {
            "category":"Shopping",
            "subcategory":"Department Store",
            "type":"Retail Goods"
        }
    ],
    "sg:phone":"+1 850 668 2511",
    "sg:postcode":"32312",
    "sg:province":"FL",
    "sg:tags":[
        "laboratory",
        "goo",
        "optical"
    ],
    "wof:name":"Wal-Mart",
    "wof:placetype":"venue"
},
  "geometry": {"coordinates":[-84.22729699999999,30.543624],"type":"Point"}
}