{
  "type": "Feature",
  "properties": {
    "addr:full":"9905 Old Saint Augustine Rd Jacksonville FL 32257",
    "addr:housenumber":"9905",
    "addr:postcode":"32257",
    "addr:street":"Old Saint Augustine Rd",
    "iso:country":"US",
    "sg:address":"9905 Old Saint Augustine Rd",
    "sg:city":"Jacksonville",
    "sg:classifiers":[
        {
            "category":"Insurance",
            "subcategory":"Insurance Agent",
            "type":"Services"
        }
    ],
    "sg:phone":"+1 904 262 9667",
    "sg:postcode":"32257",
    "sg:province":"FL",
    "wof:name":"Farm Bureau Insurance",
    "wof:placetype":"venue"
},
  "geometry": {"coordinates":[-81.614417,30.198902],"type":"Point"}
}