{
  "type": "Feature",
  "properties": {
    "iso:country":"US",
    "sg:address":"54410 Buckhorn Rd",
    "sg:city":"Astor",
    "sg:classifiers":[
        {
            "category":"Wholesale",
            "subcategory":"Books, Periodicals, & Newspapers",
            "type":"Manufacturing & Wholesale Goods"
        }
    ],
    "sg:phone":"+1 352 759 2300",
    "sg:postcode":"32102",
    "sg:province":"FL",
    "sg:tags":[
        "publisher",
        "book"
    ],
    "wof:name":"Warmblood Publishing",
    "wof:placetype":"venue"
},
  "geometry": {"coordinates":[-81.57920799999999,29.145929],"type":"Point"}
}