{
  "type": "Feature",
  "properties": {
    "addr:full":"1750 Pembrook Dr Orlando FL 32810",
    "addr:housenumber":"1750",
    "addr:postcode":"32810",
    "addr:street":"Pembrook Dr",
    "iso:country":"US",
    "sg:address":"1750 Pembrook Dr",
    "sg:city":"Orlando",
    "sg:classifiers":[
        {
            "category":"Travel",
            "subcategory":"Hotels & Motels",
            "type":"Entertainment"
        }
    ],
    "sg:phone":"+1 407 659 9100",
    "sg:postcode":"32810",
    "sg:province":"FL",
    "wof:name":"Courtyard Maitland",
    "wof:placetype":"venue"
},
  "geometry": {"coordinates":[-81.39980300000001,28.6325],"type":"Point"}
}