{
  "type": "Feature",
  "properties": {
    "iso:country":"US",
    "sg:address":"2830 E Bearss Ave",
    "sg:city":"Tampa",
    "sg:classifiers":[
        {
            "category":"Real Estate",
            "subcategory":"Real Estate Agent",
            "type":"Services"
        }
    ],
    "sg:phone":"+1 813 979 6100",
    "sg:postcode":"33618",
    "sg:province":"FL",
    "wof:name":"Buyer's Best Realty Choice",
    "wof:placetype":"venue"
},
  "geometry": {"coordinates":[-82.428079,28.080498],"type":"Point"}
}