{
  "type": "Feature",
  "properties": {
    "iso:country":"US",
    "sg:address":"760 N Collier Blvd",
    "sg:city":"Marco Island",
    "sg:classifiers":[
        {
            "category":"Restaurant",
            "type":"Food & Drink"
        }
    ],
    "sg:menulink":"http://www.allmenus.com/fl/marco-island/15998-vergina/menu/",
    "sg:phone":"+1 239 394 9822",
    "sg:postcode":"34145",
    "sg:province":"FL",
    "sg:tags":[
        "italian"
    ],
    "wof:name":"Vergina",
    "wof:placetype":"venue"
},
  "geometry": {"coordinates":[-81.728081,25.953104],"type":"Point"}
}