{
  "type": "Feature",
  "properties": {
    "iso:country":"US",
    "sg:address":"3680 Broadway",
    "sg:city":"Fort Myers",
    "sg:classifiers":[
        {
            "category":"Health Services",
            "subcategory":"Doctor",
            "type":"Services"
        }
    ],
    "sg:phone":"+1 239 936 2316",
    "sg:postcode":"33901",
    "sg:province":"FL",
    "wof:name":"Anderson Dwayne MD",
    "wof:placetype":"venue"
},
  "geometry": {"coordinates":[-81.867401,26.609501],"type":"Point"}
}