{
  "type": "Feature",
  "properties": {
    "iso:country":"US",
    "sg:address":"79 Anchor Dr",
    "sg:city":"Satellite Beach",
    "sg:classifiers":[
        {
            "category":"Shopping",
            "subcategory":"Clothing, Apparel, & Fashions",
            "type":"Retail Goods"
        }
    ],
    "sg:phone":"+1 321 773 8588",
    "sg:postcode":"32937",
    "sg:province":"FL",
    "wof:name":"Susan Giorandino",
    "wof:placetype":"venue"
},
  "geometry": {"coordinates":[-80.599407,28.158496],"type":"Point"}
}