{
  "type": "Feature",
  "properties": {
    "addr:full":"4277 Sanctuary Way Bonita Springs FL 34134",
    "addr:housenumber":"4277",
    "addr:postcode":"34134",
    "addr:street":"Sanctuary Way",
    "iso:country":"US",
    "sg:address":"4277 Sanctuary Way",
    "sg:city":"Bonita Springs",
    "sg:classifiers":[
        {
            "category":"Professional",
            "type":"Services"
        }
    ],
    "sg:phone":"+1 239 390 0440",
    "sg:postcode":"34134",
    "sg:province":"FL",
    "wof:name":"Cloud 99 Inc",
    "wof:placetype":"venue"
},
  "geometry": {"coordinates":[-81.826784,26.34709],"type":"Point"}
}