{
  "type": "Feature",
  "properties": {
    "iso:country":"US",
    "sg:address":"11311 NE 8th Ct",
    "sg:city":"Miami",
    "sg:classifiers":[
        {
            "category":"Health Services",
            "subcategory":"Health Practitioner",
            "type":"Services"
        }
    ],
    "sg:phone":"+1 305 899 9272",
    "sg:postcode":"33161",
    "sg:province":"FL",
    "wof:name":"Baldwin Helane V Rn Cht PHD",
    "wof:placetype":"venue"
},
  "geometry": {"coordinates":[-80.18095099999999,25.881192],"type":"Point"}
}