{
  "type": "Feature",
  "properties": {
    "addr:full":"4305 South St Marianna FL 32448",
    "addr:housenumber":"4305",
    "addr:postcode":"32448",
    "addr:street":"South St",
    "iso:country":"US",
    "sg:address":"4305 South St",
    "sg:city":"Marianna",
    "sg:classifiers":[
        {
            "category":"Social Services",
            "subcategory":"Child Care",
            "type":"Services"
        }
    ],
    "sg:phone":"+1 850 526 2318",
    "sg:postcode":"32448",
    "sg:province":"FL",
    "sg:tags":[
        "day"
    ],
    "wof:name":"Raggedy Ann Day Care",
    "wof:placetype":"venue"
},
  "geometry": {"coordinates":[-85.239931,30.768855],"type":"Point"}
}