{
  "type": "Feature",
  "properties": {
    "iso:country":"US",
    "sg:address":"4294 Empire Way",
    "sg:city":"Greenacres",
    "sg:classifiers":[
        {
            "category":"Professional",
            "subcategory":"Computer Services",
            "type":"Services"
        }
    ],
    "sg:phone":"+1 561 969 0170",
    "sg:postcode":"33463",
    "sg:province":"FL",
    "sg:tags":[
        "isp",
        "provider",
        "internet"
    ],
    "wof:name":"Goddess Network",
    "wof:placetype":"venue"
},
  "geometry": {"coordinates":[-80.11806,26.609651],"type":"Point"}
}