{
  "type": "Feature",
  "properties": {
    "iso:country":"US",
    "sg:address":"827 Southern Blvd",
    "sg:city":"West Palm Beach",
    "sg:classifiers":[
        {
            "category":"Retail",
            "subcategory":"Self-service Laundry",
            "type":"Services"
        }
    ],
    "sg:phone":"+1 561 802 3388",
    "sg:postcode":"33405",
    "sg:province":"FL",
    "wof:name":"My Beautiful Launderett",
    "wof:placetype":"venue"
},
  "geometry": {"coordinates":[-80.062335,26.67599],"type":"Point"}
}