{
  "type": "Feature",
  "properties": {
    "addr:full":"105 Silver Springs Dr Key Largo FL 33037",
    "addr:housenumber":"105",
    "addr:postcode":"33037",
    "addr:street":"Silver Springs Dr",
    "iso:country":"US",
    "sg:address":"105 Silver Springs Dr",
    "sg:city":"Key Largo",
    "sg:classifiers":[
        {
            "category":"Professional",
            "type":"Services"
        }
    ],
    "sg:phone":"+1 305 451 4767",
    "sg:postcode":"33037",
    "sg:province":"FL",
    "wof:name":"A AA 1 Svc",
    "wof:placetype":"venue"
},
  "geometry": {"coordinates":[-80.432918,25.103511],"type":"Point"}
}