{
  "type": "Feature",
  "properties": {
    "iso:country":"US",
    "sg:address":"7200 SW 59th St",
    "sg:city":"Miami",
    "sg:classifiers":[
        {
            "category":"Travel",
            "subcategory":"Resort",
            "type":"Entertainment"
        }
    ],
    "sg:phone":"+1 305 740 3438",
    "sg:postcode":"33143",
    "sg:province":"FL",
    "wof:name":"Fmv Resort Sales And Marketing, Inc.",
    "wof:placetype":"venue"
},
  "geometry": {"coordinates":[-80.31028000000001,25.715281],"type":"Point"}
}