{
  "type": "Feature",
  "properties": {
    "addr:full":"2900 Calusa St Miami FL 33133",
    "addr:housenumber":"2900",
    "addr:postcode":"33133",
    "addr:street":"Calusa St",
    "iso:country":"US",
    "sg:address":"2900 Calusa St",
    "sg:city":"Miami",
    "sg:classifiers":[
        {
            "category":"Shopping",
            "subcategory":"Department Store",
            "type":"Retail Goods"
        },
        {
            "category":"Shopping",
            "type":"Retail Goods"
        }
    ],
    "sg:phone":"+1 305 860 4411",
    "sg:postcode":"33133",
    "sg:province":"FL",
    "sg:tags":[
        "merchandising"
    ],
    "sg:website":"http://www.olinhydrographic.com",
    "wof:name":"Olin Hydrographic Solutions Inc",
    "wof:placetype":"venue"
},
  "geometry": {"coordinates":[-80.233627,25.738899],"type":"Point"}
}