{
  "type": "Feature",
  "properties": {
    "iso:country":"US",
    "sg:address":"8200 SW 117 Avenue Suite 106",
    "sg:city":"Miami",
    "sg:classifiers":[
        {
            "category":"Health Services",
            "subcategory":"Dentist",
            "type":"Services"
        }
    ],
    "sg:phone":"+1 305 598 6665",
    "sg:postcode":"33183",
    "sg:province":"FL",
    "wof:name":"Ricado Castaneda, DMD",
    "wof:placetype":"venue"
},
  "geometry": {"coordinates":[-80.38207199999999,25.69191],"type":"Point"}
}