{
  "type": "Feature",
  "properties": {
    "iso:country":"US",
    "sg:address":"2898 Michigan Ave",
    "sg:city":"Kissimmee",
    "sg:classifiers":[
        {
            "category":"Wholesale",
            "subcategory":"Groceries",
            "type":"Manufacturing & Wholesale Goods"
        }
    ],
    "sg:phone":"+1 407 343 0200",
    "sg:postcode":"34744",
    "sg:province":"FL",
    "sg:tags":[
        "baker"
    ],
    "wof:name":"Flowers Baking Co",
    "wof:placetype":"venue"
},
  "geometry": {"coordinates":[-81.390508,28.334781],"type":"Point"}
}