{
  "type": "Feature",
  "properties": {
    "addr:full":"3 Jackson St NE Fort Walton Bch FL 32548",
    "addr:housenumber":"3",
    "addr:postcode":"32548",
    "addr:street":"Jackson St Ne Fort",
    "iso:country":"US",
    "sg:address":"3 Jackson St NE",
    "sg:city":"Fort Walton Bch",
    "sg:classifiers":[
        {
            "category":"Building & Trades",
            "subcategory":"Landscaping Services",
            "type":"Services"
        }
    ],
    "sg:phone":"+1 850 864 5178",
    "sg:postcode":"32548",
    "sg:province":"FL",
    "sg:tags":[
        "lawn",
        "maintenance",
        "grounds"
    ],
    "wof:name":"Advanced Lawn Control",
    "wof:placetype":"venue"
},
  "geometry": {"coordinates":[-86.613761,30.41741],"type":"Point"}
}