{
  "type": "Feature",
  "properties": {
    "addr:full":"604 Ware Blvd Tampa FL 33619",
    "addr:housenumber":"604",
    "addr:postcode":"33619",
    "addr:street":"Ware Blvd",
    "iso:country":"US",
    "sg:address":"604 Ware Blvd",
    "sg:city":"Tampa",
    "sg:classifiers":[
        {
            "category":"Wholesale",
            "subcategory":"Machinery & Supplies",
            "type":"Manufacturing & Wholesale Goods"
        },
        {
            "category":"Wholesale",
            "subcategory":"Hardware",
            "type":"Manufacturing & Wholesale Goods"
        }
    ],
    "sg:phone":"+1 813 621 2625",
    "sg:postcode":"33619",
    "sg:province":"FL",
    "sg:tags":[
        "fastener",
        "industrial"
    ],
    "wof:name":"Bay Fastener & Components Inc",
    "wof:placetype":"venue"
},
  "geometry": {"coordinates":[-82.347311,27.942116],"type":"Point"}
}