{
  "type": "Feature",
  "properties": {
    "addr:full":"99 W Plant St Winter Garden FL 34787",
    "addr:housenumber":"99",
    "addr:postcode":"34787",
    "addr:street":"W Plant St",
    "iso:country":"US",
    "sg:address":"99 W Plant St",
    "sg:city":"Winter Garden",
    "sg:classifiers":[
        {
            "category":"Professional",
            "subcategory":"Accounting & Tax Preparation",
            "type":"Services"
        }
    ],
    "sg:phone":"+1 407 877 8865",
    "sg:postcode":"34787",
    "sg:province":"FL",
    "sg:tags":[
        "bookkeeping",
        "general"
    ],
    "wof:name":"New Business Svc",
    "wof:placetype":"venue"
},
  "geometry": {"coordinates":[-81.585652,28.565633],"type":"Point"}
}