{
  "type": "Feature",
  "properties": {
    "iso:country":"US",
    "sg:address":"14114 63rd Way N",
    "sg:city":"Clearwater",
    "sg:classifiers":[
        {
            "category":"Manufacturing",
            "subcategory":"Printing",
            "type":"Manufacturing & Wholesale Goods"
        }
    ],
    "sg:phone":"+1 727 461 7516",
    "sg:postcode":"33760",
    "sg:province":"FL",
    "sg:tags":[
        "commercial"
    ],
    "wof:name":"Clearwater Reprographics Inc",
    "wof:placetype":"venue"
},
  "geometry": {"coordinates":[-82.723524,27.899306],"type":"Point"}
}