{
  "type": "Feature",
  "properties": {
    "addr:full":"2460 N Courtenay Pkwy Merritt Island FL 32953",
    "addr:housenumber":"2460",
    "addr:postcode":"32953",
    "addr:street":"N Courtenay Pkwy",
    "iso:country":"US",
    "sg:address":"2460 N Courtenay Pkwy",
    "sg:city":"Merritt Island",
    "sg:classifiers":[
        {
            "category":"Manufacturing",
            "subcategory":"Metals",
            "type":"Manufacturing & Wholesale Goods"
        }
    ],
    "sg:phone":"+1 321 453 2805",
    "sg:postcode":"32953",
    "sg:province":"FL",
    "sg:tags":[
        "cable"
    ],
    "wof:name":"Pacer Gold Coast Electronics",
    "wof:placetype":"venue"
},
  "geometry": {"coordinates":[-80.705524,28.402524],"type":"Point"}
}