{
  "type": "Feature",
  "properties": {
    "addr:full":"710 Swan Way Kissimmee FL 34758",
    "addr:housenumber":"710",
    "addr:postcode":"34758",
    "addr:street":"Swan Way",
    "iso:country":"US",
    "sg:address":"710 Swan Way",
    "sg:city":"Kissimmee",
    "sg:classifiers":[
        {
            "category":"Restaurant",
            "type":"Food & Drink"
        }
    ],
    "sg:phone":"+1 321 284 6904",
    "sg:postcode":"34758",
    "sg:province":"FL",
    "wof:name":"Anticucheria Peruana Inc.",
    "wof:placetype":"venue"
},
  "geometry": {"coordinates":[-81.46311799999999,28.16511],"type":"Point"}
}