{
  "type": "Feature",
  "properties": {
    "iso:country":"US",
    "sg:address":"2135 SE 12th St",
    "sg:city":"Ocala",
    "sg:classifiers":[
        {
            "category":"Professional",
            "type":"Services"
        }
    ],
    "sg:phone":"+1 352 867 1806",
    "sg:postcode":"34471",
    "sg:province":"FL",
    "wof:name":"Chris Bricker Inc",
    "wof:placetype":"venue"
},
  "geometry": {"coordinates":[-82.108968,29.176979],"type":"Point"}
}