{
  "type": "Feature",
  "properties": {
    "iso:country":"US",
    "sg:address":"125 Woodlands Creek Dr",
    "sg:city":"Ponte Vedra Beach",
    "sg:classifiers":[
        {
            "category":"Real Estate",
            "subcategory":"Real Estate Agent",
            "type":"Services"
        }
    ],
    "sg:phone":"+1 904 273 1387",
    "sg:postcode":"32082",
    "sg:province":"FL",
    "wof:name":"Third Century",
    "wof:placetype":"venue"
},
  "geometry": {"coordinates":[-81.393244,30.184815],"type":"Point"}
}