{
  "type": "Feature",
  "properties": {
    "iso:country":"US",
    "sg:address":"10138 NW 32nd St",
    "sg:city":"Sunrise",
    "sg:classifiers":[
        {
            "category":"Building & Trades",
            "subcategory":"Electrical",
            "type":"Services"
        }
    ],
    "sg:phone":"+1 954 746 2768",
    "sg:postcode":"33351",
    "sg:province":"FL",
    "sg:tags":[
        "electrician",
        "contractor"
    ],
    "wof:name":"Arm Electrical Services Inc",
    "wof:placetype":"venue"
},
  "geometry": {"coordinates":[-80.284505,26.165646],"type":"Point"}
}