{
  "type": "Feature",
  "properties": {
    "iso:country":"US",
    "sg:address":"6229 Dewey St",
    "sg:city":"Hollywood",
    "sg:classifiers":[
        {
            "category":"Professional",
            "type":"Services"
        }
    ],
    "sg:phone":"+1 954 966 3214",
    "sg:postcode":"33023",
    "sg:province":"FL",
    "wof:name":"S Feroz Corp",
    "wof:placetype":"venue"
},
  "geometry": {"coordinates":[-80.21279,26.001995],"type":"Point"}
}