{
  "type": "Feature",
  "properties": {
    "iso:country":"US",
    "sg:address":"12150 SW 45th St",
    "sg:city":"Miami",
    "sg:classifiers":[
        {
            "category":"Museum",
            "subcategory":"Aquarium",
            "type":"Entertainment"
        }
    ],
    "sg:phone":"+1 305 221 8013",
    "sg:postcode":"33175",
    "sg:province":"FL",
    "sg:tags":[
        "supply"
    ],
    "wof:name":"Bradwell, Richard",
    "wof:placetype":"venue"
},
  "geometry": {"coordinates":[-80.390607,25.726137],"type":"Point"}
}