{
  "type": "Feature",
  "properties": {
    "iso:country":"US",
    "sg:address":"15310 Amberly Dr",
    "sg:city":"Tampa",
    "sg:classifiers":[
        {
            "category":"Insurance",
            "subcategory":"Insurance Agent",
            "type":"Services"
        }
    ],
    "sg:phone":"+1 813 979 1588",
    "sg:postcode":"33647",
    "sg:province":"FL",
    "sg:tags":[
        "consultant"
    ],
    "wof:name":"Anderson Thornton Consulting",
    "wof:placetype":"venue"
},
  "geometry": {"coordinates":[-82.404996,28.095565],"type":"Point"}
}