{
  "type": "Feature",
  "properties": {
    "iso:country":"US",
    "sg:address":"3300 W Colonial Dr",
    "sg:city":"Orlando",
    "sg:classifiers":[
        {
            "category":"Professional",
            "subcategory":"Detective & Security Services",
            "type":"Services"
        }
    ],
    "sg:phone":"+1 407 398 6720",
    "sg:postcode":"32808",
    "sg:province":"FL",
    "sg:tags":[
        "guard",
        "patrol"
    ],
    "wof:name":"Security Inn",
    "wof:placetype":"venue"
},
  "geometry": {"coordinates":[-81.417312,28.55266],"type":"Point"}
}