{
  "type": "Feature",
  "properties": {
    "iso:country":"US",
    "sg:address":"8914 SE Lucaya Ln",
    "sg:city":"Hobe Sound",
    "sg:classifiers":[
        {
            "category":"Freight",
            "type":"Transportation"
        }
    ],
    "sg:phone":"+1 772 223 8831",
    "sg:postcode":"33455",
    "sg:province":"FL",
    "sg:tags":[
        "operator",
        "trucking"
    ],
    "wof:name":"Chasky Corp",
    "wof:placetype":"venue"
},
  "geometry": {"coordinates":[-80.165463,27.095872],"type":"Point"}
}