{
  "type": "Feature",
  "properties": {
    "iso:country":"US",
    "sg:address":"624 Old Dixie Hwy SW",
    "sg:city":"Vero Beach",
    "sg:classifiers":[
        {
            "category":"Professional",
            "subcategory":"Research",
            "type":"Services"
        }
    ],
    "sg:phone":"+1 772 562 7099",
    "sg:postcode":"32962",
    "sg:province":"FL",
    "sg:tags":[
        "investigation",
        "private"
    ],
    "wof:name":"American Investigations",
    "wof:placetype":"venue"
},
  "geometry": {"coordinates":[-80.381141,27.591602],"type":"Point"}
}