{
  "type": "Feature",
  "properties": {
    "addr:full":"2424 SW 42nd Ter Fort Lauderdale FL 33317",
    "addr:housenumber":"2424",
    "addr:postcode":"33317",
    "addr:street":"Sw 42Nd Ter",
    "iso:country":"US",
    "sg:address":"2424 SW 42nd Ter",
    "sg:city":"Fort Lauderdale",
    "sg:classifiers":[
        {
            "category":"Wholesale",
            "subcategory":"Machinery & Supplies",
            "type":"Manufacturing & Wholesale Goods"
        }
    ],
    "sg:phone":"+1 954 270 0104",
    "sg:postcode":"33317",
    "sg:province":"FL",
    "sg:tags":[
        "equipment",
        "industrial"
    ],
    "wof:name":"Darcy Jackson",
    "wof:placetype":"venue"
},
  "geometry": {"coordinates":[-80.205461,26.093945],"type":"Point"}
}