{
  "type": "Feature",
  "properties": {
    "iso:country":"US",
    "sg:address":"4909 N Lakewood Dr",
    "sg:city":"Panama City",
    "sg:classifiers":[
        {
            "category":"Social Services",
            "type":"Services"
        }
    ],
    "sg:phone":"+1 850 596 1208",
    "sg:postcode":"32404",
    "sg:province":"FL",
    "wof:name":"Counseling and Behavioral Svcs",
    "wof:placetype":"venue"
},
  "geometry": {"coordinates":[-85.600989,30.14205],"type":"Point"}
}