{
  "type": "Feature",
  "properties": {
    "addr:full":"700 US Hwy 92 Longwood FL 32750",
    "addr:housenumber":"700",
    "addr:postcode":"32750",
    "addr:street":"Us Hwy 92",
    "iso:country":"US",
    "sg:address":"700 US Hwy 92",
    "sg:city":"Longwood",
    "sg:classifiers":[
        {
            "category":"Manufacturing",
            "subcategory":"Toys & Sporting Goods",
            "type":"Manufacturing & Wholesale Goods"
        }
    ],
    "sg:phone":"+1 407 339 8700",
    "sg:postcode":"32750",
    "sg:province":"FL",
    "sg:tags":[
        "table",
        "billiard"
    ],
    "wof:name":"Altamonte Billiard Factory Inc",
    "wof:placetype":"venue"
},
  "geometry": {"coordinates":[-81.32592,28.710475],"type":"Point"}
}