{
  "type": "Feature",
  "properties": {
    "iso:country":"US",
    "sg:address":"11033 NW 48th Ln",
    "sg:city":"Doral",
    "sg:classifiers":[
        {
            "category":"Wholesale",
            "subcategory":"Durable Goods & Equipment",
            "type":"Manufacturing & Wholesale Goods"
        },
        {
            "category":"Shopping",
            "subcategory":"Clothing, Apparel, & Fashions",
            "type":"Retail Goods"
        }
    ],
    "sg:phone":"+1 786 331 7161",
    "sg:postcode":"33178",
    "sg:province":"FL",
    "sg:tags":[
        "importer"
    ],
    "wof:name":"Citrobusiness Corp",
    "wof:placetype":"venue"
},
  "geometry": {"coordinates":[-80.376273,25.817903],"type":"Point"}
}