{
  "type": "Feature",
  "properties": {
    "addr:full":"1990 Neptune Rd Kissimmee FL 34744",
    "addr:housenumber":"1990",
    "addr:postcode":"34744",
    "addr:street":"Neptune Rd",
    "iso:country":"US",
    "sg:address":"1990 Neptune Rd",
    "sg:city":"Kissimmee",
    "sg:classifiers":[
        {
            "category":"Organizations",
            "subcategory":"Religious Organization",
            "type":"Services"
        }
    ],
    "sg:phone":"+1 407 846 0157",
    "sg:postcode":"34744",
    "sg:province":"FL",
    "sg:website":"www.fbck.org",
    "wof:name":"Faith Baptist Church",
    "wof:placetype":"venue"
},
  "geometry": {"coordinates":[-81.363681,28.278619],"type":"Point"}
}