{
  "type": "Feature",
  "properties": {
    "iso:country":"US",
    "sg:address":"19878 SW 122nd Ct",
    "sg:city":"Miami",
    "sg:classifiers":[
        {
            "category":"Real Estate",
            "subcategory":"Real Estate Agent",
            "type":"Services"
        }
    ],
    "sg:phone":"+1 305 256 4486",
    "sg:postcode":"33177",
    "sg:province":"FL",
    "wof:name":"Rain Forest Realty Corp",
    "wof:placetype":"venue"
},
  "geometry": {"coordinates":[-80.389827,25.581492],"type":"Point"}
}