{
  "type": "Feature",
  "properties": {
    "iso:country":"US",
    "sg:address":"6225 Estero Blvd",
    "sg:city":"Fort Myers Beach",
    "sg:classifiers":[
        {
            "category":"Restaurant",
            "type":"Food & Drink"
        }
    ],
    "sg:phone":"+1 239 463 9191",
    "sg:postcode":"33931",
    "sg:province":"FL",
    "sg:tags":[
        "eating"
    ],
    "wof:name":"Charlie Browns Restaurant",
    "wof:placetype":"venue"
},
  "geometry": {"coordinates":[-81.904965,26.423461],"type":"Point"}
}