{
  "type": "Feature",
  "properties": {
    "iso:country":"US",
    "sg:address":"1601 S 50th St",
    "sg:city":"Tampa",
    "sg:classifiers":[
        {
            "category":"Retail",
            "subcategory":"Auto Repair",
            "type":"Services"
        }
    ],
    "sg:phone":"+1 813 650 0625",
    "sg:postcode":"33619",
    "sg:province":"FL",
    "sg:tags":[
        "repairing",
        "automobile"
    ],
    "wof:name":"J & M Auto Sales",
    "wof:placetype":"venue"
},
  "geometry": {"coordinates":[-82.401932,27.93357],"type":"Point"}
}