{
  "type": "Feature",
  "properties": {
    "iso:country":"US",
    "sg:address":"52 Yacht Club Pl",
    "sg:city":"Jupiter",
    "sg:classifiers":[
        {
            "category":"Shopping",
            "subcategory":"Used Merchandise",
            "type":"Retail Goods"
        }
    ],
    "sg:phone":"+1 561 747 7952",
    "sg:postcode":"33469",
    "sg:province":"FL",
    "wof:name":"Roxies Consignment Inc",
    "wof:placetype":"venue"
},
  "geometry": {"coordinates":[-80.10961500000001,26.956821],"type":"Point"}
}