{
  "type": "Feature",
  "properties": {
    "addr:full":"15210 Amberly Dr Tampa FL 33647",
    "addr:housenumber":"15210",
    "addr:postcode":"33647",
    "addr:street":"Amberly Dr",
    "iso:country":"US",
    "sg:address":"15210 Amberly Dr",
    "sg:city":"Tampa",
    "sg:classifiers":[
        {
            "category":"Real Estate",
            "subcategory":"Architect",
            "type":"Services"
        }
    ],
    "sg:phone":"+1 813 892 8492",
    "sg:postcode":"33647",
    "sg:province":"FL",
    "wof:name":"Dennis Arriaga",
    "wof:placetype":"venue"
},
  "geometry": {"coordinates":[-82.401298,28.098035],"type":"Point"}
}