{
  "type": "Feature",
  "properties": {
    "iso:country":"US",
    "sg:address":"131 Danielle Ct",
    "sg:city":"Fort Lauderdale",
    "sg:classifiers":[
        {
            "category":"Wholesale",
            "subcategory":"Non-durable Goods",
            "type":"Manufacturing & Wholesale Goods"
        }
    ],
    "sg:phone":"+1 954 385 9669",
    "sg:postcode":"33326",
    "sg:province":"FL",
    "wof:name":"Ibero-American Business Inc",
    "wof:placetype":"venue"
},
  "geometry": {"coordinates":[-80.38309700000001,26.124357],"type":"Point"}
}