{
  "type": "Feature",
  "properties": {
    "iso:country":"US",
    "sg:address":"13723 Linden Dr",
    "sg:city":"Brooksville",
    "sg:classifiers":[
        {
            "category":"Building & Trades",
            "subcategory":"Construction",
            "type":"Services"
        }
    ],
    "sg:phone":"+1 352 686 6063",
    "sg:postcode":"34609",
    "sg:province":"FL",
    "sg:tags":[
        "designer",
        "dealer",
        "pool",
        "swimming"
    ],
    "wof:name":"Keystone Pools",
    "wof:placetype":"venue"
},
  "geometry": {"coordinates":[-82.510811,28.466258],"type":"Point"}
}