{
  "type": "Feature",
  "properties": {
    "iso:country":"US",
    "sg:address":"1840 W 8th Ave",
    "sg:city":"Hialeah",
    "sg:classifiers":[
        {
            "category":"Retail",
            "subcategory":"Auto Repair",
            "type":"Services"
        }
    ],
    "sg:phone":"+1 305 888 8789",
    "sg:postcode":"33010",
    "sg:province":"FL",
    "sg:tags":[
        "body",
        "shop",
        "painting",
        "automobile"
    ],
    "wof:name":"Blue Eagle Paint & Body Shop",
    "wof:placetype":"venue"
},
  "geometry": {"coordinates":[-80.29789700000001,25.8386],"type":"Point"}
}