{
  "type": "Feature",
  "properties": {
    "iso:country":"US",
    "sg:address":"3320 SW 33rd Rd",
    "sg:city":"Ocala",
    "sg:classifiers":[
        {
            "category":"Health Services",
            "subcategory":"Doctor",
            "type":"Services"
        }
    ],
    "sg:phone":"+1 352 291 5210",
    "sg:postcode":"34474",
    "sg:province":"FL",
    "sg:tags":[
        "physician",
        "surgeon"
    ],
    "sg:website":"www.ocalaeye.com",
    "wof:name":"Ocala Eye Surgeons",
    "wof:placetype":"venue"
},
  "geometry": {"coordinates":[-82.17714599999999,29.15326],"type":"Point"}
}