{
  "type": "Feature",
  "properties": {
    "addr:full":"6901 Plumosa Ln Fort Pierce FL 34951",
    "addr:housenumber":"6901",
    "addr:postcode":"34951",
    "addr:street":"Plumosa Ln",
    "iso:country":"US",
    "sg:address":"6901 Plumosa Ln",
    "sg:city":"Fort Pierce",
    "sg:classifiers":[
        {
            "category":"Sports & Exercise",
            "subcategory":"Race Track",
            "type":"Entertainment"
        }
    ],
    "sg:phone":"+1 772 466 8711",
    "sg:postcode":"34951",
    "sg:province":"FL",
    "sg:tags":[
        "operation",
        "racing",
        "or"
    ],
    "wof:name":"Outlaw Modifided Racing Series",
    "wof:placetype":"venue"
},
  "geometry": {"coordinates":[-80.39811899999999,27.53744],"type":"Point"}
}