{
  "type": "Feature",
  "properties": {
    "iso:country":"US",
    "sg:address":"13435 S McCall Rd",
    "sg:city":"Port Charlotte",
    "sg:classifiers":[
        {
            "category":"Personal",
            "subcategory":"Beauty Salon",
            "type":"Services"
        }
    ],
    "sg:phone":"+1 941 697 1500",
    "sg:postcode":"33981",
    "sg:province":"FL",
    "wof:name":"Shear Sailing Hair Salon",
    "wof:placetype":"venue"
},
  "geometry": {"coordinates":[-82.226411,26.933287],"type":"Point"}
}