{
  "type": "Feature",
  "properties": {
    "addr:full":"4525 Poinciana St Lauderdl By Sea FL 33308",
    "addr:housenumber":"4525",
    "addr:postcode":"33308",
    "addr:street":"Poinciana St",
    "iso:country":"US",
    "sg:address":"4525 Poinciana St",
    "sg:city":"Lauderdl By Sea",
    "sg:classifiers":[
        {
            "category":"Communications",
            "subcategory":"Film & Video Production",
            "type":"Services"
        }
    ],
    "sg:phone":"+1 954 562 5951",
    "sg:postcode":"33308",
    "sg:province":"FL",
    "sg:tags":[
        "taping"
    ],
    "sg:website":"www.videojournals.com",
    "wof:name":"Video Journals Inc",
    "wof:placetype":"venue"
},
  "geometry": {"coordinates":[-80.09805299999999,26.194651],"type":"Point"}
}