{
  "type": "Feature",
  "properties": {
    "addr:full":"1681 SW 67th Ave Miami FL 33155",
    "addr:housenumber":"1681",
    "addr:postcode":"33155",
    "addr:street":"Sw 67Th Ave",
    "iso:country":"US",
    "sg:address":"1681 SW 67th Ave",
    "sg:city":"Miami",
    "sg:classifiers":[
        {
            "category":"Retail",
            "subcategory":"Auto Repair",
            "type":"Services"
        }
    ],
    "sg:phone":"+1 305 261 7811",
    "sg:postcode":"33155",
    "sg:province":"FL",
    "sg:tags":[
        "body",
        "shop"
    ],
    "wof:name":"Testarosa Motors",
    "wof:placetype":"venue"
},
  "geometry": {"coordinates":[-80.30349699999999,25.7549],"type":"Point"}
}