{
  "type": "Feature",
  "properties": {
    "iso:country":"US",
    "sg:address":"160 Spirit Lake Rd",
    "sg:city":"Winter Haven",
    "sg:classifiers":[
        {
            "category":"Manufacturing",
            "subcategory":"Signs",
            "type":"Manufacturing & Wholesale Goods"
        }
    ],
    "sg:phone":"+1 863 294 1683",
    "sg:postcode":"33880",
    "sg:province":"FL",
    "sg:tags":[
        "mfg"
    ],
    "wof:name":"Cypress Signs",
    "wof:placetype":"venue"
},
  "geometry": {"coordinates":[-81.77601900000001,28.029415],"type":"Point"}
}