{
  "type": "Feature",
  "properties": {
    "addr:full":"4504 Twin Oaks Dr Pensacola FL 32506",
    "addr:housenumber":"4504",
    "addr:postcode":"32506",
    "addr:street":"Twin Oaks Dr",
    "iso:country":"US",
    "sg:address":"4504 Twin Oaks Dr",
    "sg:city":"Pensacola",
    "sg:classifiers":[
        {
            "category":"Real Estate",
            "subcategory":"Real Estate Agent",
            "type":"Services"
        }
    ],
    "sg:phone":"+1 850 456 6676",
    "sg:postcode":"32506",
    "sg:province":"FL",
    "wof:name":"Northwest Fl Management",
    "wof:placetype":"venue"
},
  "geometry": {"coordinates":[-87.278783,30.409015],"type":"Point"}
}