{
  "type": "Feature",
  "properties": {
    "addr:full":"1699 Coral Way Coral Gables FL 33145",
    "addr:housenumber":"1699",
    "addr:postcode":"33145",
    "addr:street":"Coral Way",
    "iso:country":"US",
    "sg:address":"1699 Coral Way",
    "sg:city":"Coral Gables",
    "sg:classifiers":[
        {
            "category":"Banks & Credit Unions",
            "subcategory":"Bank",
            "type":"Services"
        }
    ],
    "sg:phone":"+1 305 567 4270",
    "sg:postcode":"33145",
    "sg:province":"FL",
    "sg:website":"www.wachovia.com",
    "wof:name":"Wachovia",
    "wof:placetype":"venue"
},
  "geometry": {"coordinates":[-80.222099,25.750999],"type":"Point"}
}