{
  "type": "Feature",
  "properties": {
    "addr:full":"211 Airport Pulling Rd S Naples FL 34104",
    "addr:housenumber":"211",
    "addr:postcode":"34104",
    "addr:street":"Airport Pulling Rd S",
    "iso:country":"US",
    "sg:address":"211 Airport Pulling Rd S",
    "sg:city":"Naples",
    "sg:classifiers":[
        {
            "category":"Organizations",
            "subcategory":"Non-profit Organization",
            "type":"Services"
        }
    ],
    "sg:phone":"+1 239 263 1161",
    "sg:postcode":"34104",
    "sg:province":"FL",
    "sg:tags":[
        "info",
        "addiction",
        "abuse",
        "treatment",
        "drug"
    ],
    "wof:name":"Treatment Works",
    "wof:placetype":"venue"
},
  "geometry": {"coordinates":[-81.76672600000001,26.152409],"type":"Point"}
}