{
  "type": "Feature",
  "properties": {
    "iso:country":"US",
    "sg:address":"2101 Capital Cir NE",
    "sg:city":"Tallahassee",
    "sg:classifiers":[
        {
            "category":"Banks & Credit Unions",
            "subcategory":"Bank",
            "type":"Services"
        }
    ],
    "sg:phone":"+1 850 386 2222",
    "sg:postcode":"32308",
    "sg:province":"FL",
    "sg:website":"www.wakullabank.com",
    "wof:name":"Wakulla Bank",
    "wof:placetype":"venue"
},
  "geometry": {"coordinates":[-84.23666299999999,30.478898],"type":"Point"}
}