{
  "type": "Feature",
  "properties": {
    "iso:country":"US",
    "sg:address":"1248 Casa Bianca Ridge",
    "sg:city":"Monticello",
    "sg:classifiers":[
        {
            "category":"Building & Trades",
            "subcategory":"Construction",
            "type":"Services"
        }
    ],
    "sg:phone":"+1 850 997 0016",
    "sg:postcode":"32344",
    "sg:province":"FL",
    "sg:tags":[
        "house"
    ],
    "wof:name":"Vanguard North Inc",
    "wof:placetype":"venue"
},
  "geometry": {"coordinates":[-83.896584,30.521178],"type":"Point"}
}