{
  "type": "Feature",
  "properties": {
    "addr:full":"1016 26th Ave E Bradenton FL 34208",
    "addr:housenumber":"1016",
    "addr:postcode":"34208",
    "addr:street":"26Th Ave E",
    "iso:country":"US",
    "sg:address":"1016 26th Ave E",
    "sg:city":"Bradenton",
    "sg:classifiers":[
        {
            "category":"Retail",
            "subcategory":"Auto Repair",
            "type":"Services"
        }
    ],
    "sg:phone":"+1 941 714 0372",
    "sg:postcode":"34208",
    "sg:province":"FL",
    "sg:tags":[
        "repairing",
        "automobile"
    ],
    "wof:name":"Papa Roger's Auto Svc Ctr",
    "wof:placetype":"venue"
},
  "geometry": {"coordinates":[-82.551485,27.476915],"type":"Point"}
}