{
  "type": "Feature",
  "properties": {
    "addr:full":"11944 SW 8th St Miami FL 33184",
    "addr:housenumber":"11944",
    "addr:postcode":"33184",
    "addr:street":"Sw 8Th St",
    "iso:country":"US",
    "sg:address":"11944 SW 8th St",
    "sg:city":"Miami",
    "sg:classifiers":[
        {
            "category":"Health Services",
            "subcategory":"Dentist",
            "type":"Services"
        }
    ],
    "sg:phone":"+1 305 221 5112",
    "sg:postcode":"33184",
    "sg:province":"FL",
    "wof:name":"Dental Office",
    "wof:placetype":"venue"
},
  "geometry": {"coordinates":[-80.389768,25.760743],"type":"Point"}
}