{
  "type": "Feature",
  "properties": {
    "addr:full":"8211 Dixie Hwy Miami FL 33143",
    "addr:housenumber":"8211",
    "addr:postcode":"33143",
    "addr:street":"Dixie Hwy",
    "iso:country":"US",
    "sg:address":"8211 Dixie Hwy",
    "sg:city":"Miami",
    "sg:classifiers":[
        {
            "category":"Banks & Credit Unions",
            "subcategory":"Bank",
            "type":"Services"
        }
    ],
    "sg:phone":"+1 305 666 6621",
    "sg:postcode":"33143",
    "sg:province":"FL",
    "sg:tags":[
        "commercial"
    ],
    "wof:name":"Pointe Bank",
    "wof:placetype":"venue"
},
  "geometry": {"coordinates":[-80.30141500000001,25.694696],"type":"Point"}
}