{
  "type": "Feature",
  "properties": {
    "iso:country":"US",
    "sg:address":"6831 Whitfield Industrial Ave",
    "sg:city":"Sarasota",
    "sg:classifiers":[
        {
            "category":"Home & Garden",
            "subcategory":"Furniture",
            "type":"Retail Goods"
        }
    ],
    "sg:phone":"+1 941 751 9898",
    "sg:postcode":"34243",
    "sg:province":"FL",
    "sg:tags":[
        "cabinet"
    ],
    "wof:name":"Benchmark Cabinets",
    "wof:placetype":"venue"
},
  "geometry": {"coordinates":[-82.53415800000001,27.419282],"type":"Point"}
}