{
  "type": "Feature",
  "properties": {
    "iso:country":"US",
    "sg:address":"22464 Weeks Blvd",
    "sg:city":"Land O Lakes",
    "sg:classifiers":[
        {
            "category":"Building & Trades",
            "subcategory":"Construction",
            "type":"Services"
        }
    ],
    "sg:phone":"+1 813 996 4889",
    "sg:postcode":"34639",
    "sg:province":"FL",
    "sg:tags":[
        "nonresidential"
    ],
    "wof:name":"Bachtel Construction Inc",
    "wof:placetype":"venue"
},
  "geometry": {"coordinates":[-82.444335,28.198843],"type":"Point"}
}