{
  "type": "Feature",
  "properties": {
    "addr:full":"4795 Lake Michigan Ave Cocoa FL 32926",
    "addr:housenumber":"4795",
    "addr:postcode":"32926",
    "addr:street":"Lake Michigan Ave",
    "iso:country":"US",
    "sg:address":"4795 Lake Michigan Ave",
    "sg:city":"Cocoa",
    "sg:classifiers":[
        {
            "category":"Building & Trades",
            "subcategory":"Cleaning & Sanitation",
            "type":"Services"
        }
    ],
    "sg:phone":"+1 321 639 9249",
    "sg:postcode":"32926",
    "sg:province":"FL",
    "sg:tags":[
        "maintenance"
    ],
    "wof:name":"C & M Services",
    "wof:placetype":"venue"
},
  "geometry": {"coordinates":[-80.77655300000001,28.429884],"type":"Point"}
}