{
  "type": "Feature",
  "properties": {
    "addr:full":"115 Saint Kitts Cir Winter Haven FL 33884",
    "addr:housenumber":"115",
    "addr:postcode":"33884",
    "addr:street":"Saint Kitts Cir",
    "iso:country":"US",
    "sg:address":"115 Saint Kitts Cir",
    "sg:city":"Winter Haven",
    "sg:classifiers":[
        {
            "category":"Building & Trades",
            "subcategory":"Construction",
            "type":"Services"
        }
    ],
    "sg:phone":"+1 863 324 0150",
    "sg:postcode":"33884",
    "sg:province":"FL",
    "sg:tags":[
        "dry wall",
        "contractor"
    ],
    "wof:name":"Patchmaster Drywall Inc",
    "wof:placetype":"venue"
},
  "geometry": {"coordinates":[-81.673844,27.988242],"type":"Point"}
}