{
  "type": "Feature",
  "properties": {
    "iso:country":"US",
    "sg:address":"5223 S Macdill Ave",
    "sg:city":"Tampa",
    "sg:classifiers":[
        {
            "category":"Retail",
            "subcategory":"Photofinishing",
            "type":"Services"
        }
    ],
    "sg:phone":"+1 813 870 0001",
    "sg:postcode":"33611",
    "sg:province":"FL",
    "sg:tags":[
        "laboratory"
    ],
    "wof:name":"Bay Color Lab Corp",
    "wof:placetype":"venue"
},
  "geometry": {"coordinates":[-82.493982,27.888476],"type":"Point"}
}