{
  "type": "Feature",
  "properties": {
    "addr:full":"4827 Milton St Cape Coral FL 33904",
    "addr:housenumber":"4827",
    "addr:postcode":"33904",
    "addr:street":"Milton St",
    "iso:country":"US",
    "sg:address":"4827 Milton St",
    "sg:city":"Cape Coral",
    "sg:classifiers":[
        {
            "category":"Shopping",
            "subcategory":"Bicycles & Sporting Goods",
            "type":"Retail Goods"
        }
    ],
    "sg:phone":"+1 239 945 7721",
    "sg:postcode":"33904",
    "sg:province":"FL",
    "wof:name":"Soccer Xtreme",
    "wof:placetype":"venue"
},
  "geometry": {"coordinates":[-81.951063,26.561961],"type":"Point"}
}