{
  "type": "Feature",
  "properties": {
    "iso:country":"US",
    "sg:address":"620 SE 29th Ter",
    "sg:city":"Cape Coral",
    "sg:classifiers":[
        {
            "category":"Professional",
            "subcategory":"Business Services",
            "type":"Services"
        }
    ],
    "sg:phone":"+1 239 772 9867",
    "sg:postcode":"33904",
    "sg:province":"FL",
    "wof:name":"Centurion Telecom Inc",
    "wof:placetype":"venue"
},
  "geometry": {"coordinates":[-81.95984,26.597538],"type":"Point"}
}