{
  "type": "Feature",
  "properties": {
    "iso:country":"US",
    "sg:address":"12995 SW 132nd Ct",
    "sg:city":"Miami",
    "sg:classifiers":[
        {
            "category":"Home & Garden",
            "subcategory":"Building Materials",
            "type":"Retail Goods"
        }
    ],
    "sg:phone":"+1 305 255 4629",
    "sg:postcode":"33186",
    "sg:province":"FL",
    "sg:tags":[
        "downspouts",
        "gutter"
    ],
    "wof:name":"Ocean Rain Gutters",
    "wof:placetype":"venue"
},
  "geometry": {"coordinates":[-80.40819,25.646727],"type":"Point"}
}