{
  "type": "Feature",
  "properties": {
    "addr:full":"16395 SE 138th Ave Weirsdale FL 32195",
    "addr:housenumber":"16395",
    "addr:postcode":"32195",
    "addr:street":"Se 138Th Ave",
    "iso:country":"US",
    "sg:address":"16395 SE 138th Ave",
    "sg:city":"Weirsdale",
    "sg:classifiers":[
        {
            "category":"Home & Garden",
            "subcategory":"Hardware",
            "type":"Retail Goods"
        }
    ],
    "sg:phone":"+1 352 821 2104",
    "sg:postcode":"32195",
    "sg:province":"FL",
    "wof:name":"Ace Hardware",
    "wof:placetype":"venue"
},
  "geometry": {"coordinates":[-81.922128,28.984951],"type":"Point"}
}