{
  "type": "Feature",
  "properties": {
    "addr:full":"2350 SW 30th Ave Hallandale FL 33009",
    "addr:housenumber":"2350",
    "addr:postcode":"33009",
    "addr:street":"Sw 30Th Ave",
    "iso:country":"US",
    "sg:address":"2350 SW 30th Ave",
    "sg:city":"Hallandale",
    "sg:classifiers":[
        {
            "category":"Manufacturing",
            "subcategory":"Furniture",
            "type":"Manufacturing & Wholesale Goods"
        }
    ],
    "sg:phone":"+1 954 458 0668",
    "sg:postcode":"33009",
    "sg:province":"FL",
    "sg:tags":[
        "household",
        "wood",
        "mfg"
    ],
    "wof:name":"Galleria Mondo Inc",
    "wof:placetype":"venue"
},
  "geometry": {"coordinates":[-80.166462,25.991051],"type":"Point"}
}