{
  "type": "Feature",
  "properties": {
    "addr:full":"2968 S Ridgewood Ave Edgewater FL 32141",
    "addr:housenumber":"2968",
    "addr:postcode":"32141",
    "addr:street":"S Ridgewood Ave",
    "iso:country":"US",
    "sg:address":"2968 S Ridgewood Ave",
    "sg:city":"Edgewater",
    "sg:classifiers":[
        {
            "category":"Shopping",
            "subcategory":"Optical Goods",
            "type":"Retail Goods"
        }
    ],
    "sg:phone":"+1 386 428 2088",
    "sg:postcode":"32141",
    "sg:province":"FL",
    "wof:name":"Vision Magic",
    "wof:placetype":"venue"
},
  "geometry": {"coordinates":[-80.884179,28.948604],"type":"Point"}
}