{
  "type": "Feature",
  "properties": {
    "addr:full":"544 NW Avon Ave Port Saint Lucie FL 34983",
    "addr:housenumber":"544",
    "addr:postcode":"34983",
    "addr:street":"Nw Avon Ave",
    "iso:country":"US",
    "sg:address":"544 NW Avon Ave",
    "sg:city":"Port Saint Lucie",
    "sg:classifiers":[
        {
            "category":"Professional",
            "subcategory":"Accounting & Tax Preparation",
            "type":"Services"
        }
    ],
    "sg:phone":"+1 772 873 1100",
    "sg:postcode":"34983",
    "sg:province":"FL",
    "wof:name":"Lisa Cole Accounting Serv",
    "wof:placetype":"venue"
},
  "geometry": {"coordinates":[-80.36385799999999,27.321152],"type":"Point"}
}