{
  "type": "Feature",
  "properties": {
    "iso:country":"US",
    "sg:address":"10473 66th St",
    "sg:city":"Pinellas Park",
    "sg:classifiers":[
        {
            "category":"Wholesale",
            "subcategory":"Stationery",
            "type":"Manufacturing & Wholesale Goods"
        },
        {
            "category":"Manufacturing",
            "subcategory":"Printing",
            "type":"Manufacturing & Wholesale Goods"
        }
    ],
    "sg:phone":"+1 727 532 9399",
    "sg:postcode":"33782",
    "sg:province":"FL",
    "sg:tags":[
        "printer",
        "form",
        "business",
        "system"
    ],
    "wof:name":"Integrity Printing & Bus Forms",
    "wof:placetype":"venue"
},
  "geometry": {"coordinates":[-82.728886,27.867381],"type":"Point"}
}