{
  "type": "Feature",
  "properties": {
    "iso:country":"US",
    "sg:address":"11670 Royal Tee Cir",
    "sg:city":"Cape Coral",
    "sg:classifiers":[
        {
            "category":"Recreation",
            "type":"Entertainment"
        }
    ],
    "sg:phone":"+1 239 573 3210",
    "sg:postcode":"33991",
    "sg:province":"FL",
    "sg:tags":[
        "tennis",
        "court"
    ],
    "wof:name":"Mid Cape Racquet & Health Club",
    "wof:placetype":"venue"
},
  "geometry": {"coordinates":[-82.03577799999999,26.617292],"type":"Point"}
}