{
  "type": "Feature",
  "properties": {
    "iso:country":"US",
    "sg:address":"3262 SW 6th St",
    "sg:city":"Miami",
    "sg:classifiers":[
        {
            "category":"Insurance",
            "subcategory":"Hazard Insurance",
            "type":"Services"
        }
    ],
    "sg:phone":"+1 305 442 2476",
    "sg:postcode":"33135",
    "sg:province":"FL",
    "wof:name":"Jose R Rodriguez",
    "wof:placetype":"venue"
},
  "geometry": {"coordinates":[-80.24864100000001,25.76665],"type":"Point"}
}