{
  "type": "Feature",
  "properties": {
    "iso:country":"US",
    "sg:address":"301 US Hwy 1",
    "sg:city":"West Palm Beach",
    "sg:classifiers":[
        {
            "category":"Restaurant",
            "type":"Food & Drink"
        }
    ],
    "sg:phone":"+1 561 848 5031",
    "sg:postcode":"33403",
    "sg:province":"FL",
    "sg:tags":[
        "bakery",
        "retail",
        "eating",
        "product",
        "mfg"
    ],
    "wof:name":"Dunkin Donuts",
    "wof:placetype":"venue"
},
  "geometry": {"coordinates":[-80.05449299999999,26.795429],"type":"Point"}
}