{
  "type": "Feature",
  "properties": {
    "iso:country":"US",
    "sg:address":"5190 Jog Ln",
    "sg:city":"Delray Beach",
    "sg:classifiers":[
        {
            "category":"Recreation",
            "type":"Entertainment"
        }
    ],
    "sg:phone":"+1 561 638 4201",
    "sg:postcode":"33484",
    "sg:province":"FL",
    "wof:name":"Carefree Golfgreens Florida",
    "wof:placetype":"venue"
},
  "geometry": {"coordinates":[-80.12564399999999,26.434944],"type":"Point"}
}