{
  "type": "Feature",
  "properties": {
    "iso:country":"US",
    "sg:address":"2339 Sunset Dr",
    "sg:city":"West Palm Beach",
    "sg:classifiers":[
        {
            "category":"Building & Trades",
            "subcategory":"Construction",
            "type":"Services"
        }
    ],
    "sg:phone":"+1 561 308 0713",
    "sg:postcode":"33415",
    "sg:province":"FL",
    "sg:tags":[
        "resurfacing",
        "laying",
        "refinishing",
        "floor"
    ],
    "wof:name":"Jordan's Flooring Inc",
    "wof:placetype":"venue"
},
  "geometry": {"coordinates":[-80.116219,26.642746],"type":"Point"}
}