{
  "type": "Feature",
  "properties": {
    "addr:full":"2629 Edgewater Dr Orlando FL 32804",
    "addr:housenumber":"2629",
    "addr:postcode":"32804",
    "addr:street":"Edgewater Dr",
    "iso:country":"US",
    "sg:address":"2629 Edgewater Dr",
    "sg:city":"Orlando",
    "sg:classifiers":[
        {
            "category":"Health Services",
            "subcategory":"Doctor",
            "type":"Services"
        }
    ],
    "sg:phone":"+1 407 246 7001",
    "sg:postcode":"32804",
    "sg:province":"FL",
    "sg:tags":[
        "physician",
        "surgeon"
    ],
    "wof:name":"Rick Baxley MD Pa",
    "wof:placetype":"venue"
},
  "geometry": {"coordinates":[-81.389439,28.576028],"type":"Point"}
}