{
  "type": "Feature",
  "properties": {
    "iso:country":"US",
    "sg:address":"120 S Lauber Way",
    "sg:city":"Tampa",
    "sg:classifiers":[
        {
            "category":"Professional",
            "subcategory":"Advertising",
            "type":"Services"
        }
    ],
    "sg:phone":"+1 813 289 8149",
    "sg:postcode":"33609",
    "sg:province":"FL",
    "sg:tags":[
        "agency",
        "specialty"
    ],
    "sg:website":"http://www.galleryartphotos.com",
    "wof:name":"Stewart And Associates Communication Arts",
    "wof:placetype":"venue"
},
  "geometry": {"coordinates":[-82.519099,27.944405],"type":"Point"}
}