{
  "type": "Feature",
  "properties": {
    "addr:full":"1506 27th St W Bradenton FL 34205",
    "addr:housenumber":"1506",
    "addr:postcode":"34205",
    "addr:street":"27Th St W",
    "iso:country":"US",
    "sg:address":"1506 27th St W",
    "sg:city":"Bradenton",
    "sg:classifiers":[
        {
            "category":"Building & Trades",
            "subcategory":"Construction",
            "type":"Services"
        }
    ],
    "sg:phone":"+1 941 714 0307",
    "sg:postcode":"34205",
    "sg:province":"FL",
    "sg:tags":[
        "resurfacing",
        "laying",
        "refinishing",
        "floor"
    ],
    "wof:name":"DNA Flooring Inc",
    "wof:placetype":"venue"
},
  "geometry": {"coordinates":[-82.588713,27.484717],"type":"Point"}
}