{
  "type": "Feature",
  "properties": {
    "iso:country":"US",
    "sg:address":"1800 NW 96th Ave",
    "sg:city":"Doral",
    "sg:classifiers":[
        {
            "category":"Professional",
            "type":"Services"
        }
    ],
    "sg:phone":"+1 305 477 9989",
    "sg:postcode":"33172",
    "sg:province":"FL",
    "sg:tags":[
        "establishment"
    ],
    "wof:name":"Ocean Deep",
    "wof:placetype":"venue"
},
  "geometry": {"coordinates":[-80.35118300000001,25.79084],"type":"Point"}
}