{
  "type": "Feature",
  "properties": {
    "addr:full":"9108 Bay Cove Ln Jacksonville FL 32257",
    "addr:housenumber":"9108",
    "addr:postcode":"32257",
    "addr:street":"Bay Cove Ln",
    "iso:country":"US",
    "sg:address":"9108 Bay Cove Ln",
    "sg:city":"Jacksonville",
    "sg:classifiers":[
        {
            "category":"Professional",
            "type":"Services"
        }
    ],
    "sg:phone":"+1 904 730 2763",
    "sg:postcode":"32257",
    "sg:province":"FL",
    "wof:name":"582 Nixon Street Inc",
    "wof:placetype":"venue"
},
  "geometry": {"coordinates":[-81.62138,30.212694],"type":"Point"}
}