{
  "type": "Feature",
  "properties": {
    "addr:full":"1713 Bluejay Dr Middleburg FL 32068",
    "addr:housenumber":"1713",
    "addr:postcode":"32068",
    "addr:street":"Bluejay Dr",
    "iso:country":"US",
    "sg:address":"1713 Bluejay Dr",
    "sg:city":"Middleburg",
    "sg:classifiers":[
        {
            "category":"Freight",
            "type":"Transportation"
        }
    ],
    "sg:phone":"+1 904 291 4170",
    "sg:postcode":"32068",
    "sg:province":"FL",
    "sg:tags":[
        "trucking"
    ],
    "wof:name":"MGM Transport",
    "wof:placetype":"venue"
},
  "geometry": {"coordinates":[-81.93563,30.089679],"type":"Point"}
}