{
  "type": "Feature",
  "properties": {
    "addr:full":"100 N John Young Pkwy Kissimmee FL 34741",
    "addr:housenumber":"100",
    "addr:postcode":"34741",
    "addr:street":"N John Young Pkwy",
    "iso:country":"US",
    "sg:address":"100 N John Young Pkwy",
    "sg:city":"Kissimmee",
    "sg:classifiers":[
        {
            "category":"Insurance",
            "subcategory":"Insurance Agent",
            "type":"Services"
        }
    ],
    "sg:phone":"+1 407 846 9333",
    "sg:postcode":"34741",
    "sg:province":"FL",
    "wof:name":"Statefarm Insurance Shane Swan",
    "wof:placetype":"venue"
},
  "geometry": {"coordinates":[-81.41595100000001,28.293606],"type":"Point"}
}