{
  "type": "Feature",
  "properties": {
    "iso:country":"US",
    "sg:address":"14947 Bruce B Downs Blvd",
    "sg:city":"Tampa",
    "sg:classifiers":[
        {
            "category":"Manufacturing",
            "subcategory":"Glass & Minerals",
            "type":"Manufacturing & Wholesale Goods"
        }
    ],
    "sg:phone":"+1 813 971 0090",
    "sg:postcode":"33613",
    "sg:province":"FL",
    "sg:tags":[
        "concrete",
        "brick",
        "prod",
        "block"
    ],
    "wof:name":"Custom Crete Design",
    "wof:placetype":"venue"
},
  "geometry": {"coordinates":[-82.413999,28.082107],"type":"Point"}
}