{
  "type": "Feature",
  "properties": {
    "iso:country":"US",
    "sg:address":"205 S Florida Ave",
    "sg:city":"Lakeland",
    "sg:classifiers":[
        {
            "category":"Banks & Credit Unions",
            "subcategory":"Bank",
            "type":"Services"
        }
    ],
    "sg:phone":"+1 863 686 3307",
    "sg:postcode":"33801",
    "sg:province":"FL",
    "sg:tags":[
        "federal"
    ],
    "sg:website":"www.lmefcu.com",
    "wof:name":"Lakeland Medical Employees",
    "wof:placetype":"venue"
},
  "geometry": {"coordinates":[-81.95725899999999,28.041746],"type":"Point"}
}