{
  "type": "Feature",
  "properties": {
    "addr:full":"6708 Medinah Ct Bradenton FL 34202",
    "addr:housenumber":"6708",
    "addr:postcode":"34202",
    "addr:street":"Medinah Ct",
    "iso:country":"US",
    "sg:address":"6708 Medinah Ct",
    "sg:city":"Bradenton",
    "sg:classifiers":[
        {
            "category":"Home & Garden",
            "subcategory":"Home Furnishings",
            "type":"Retail Goods"
        }
    ],
    "sg:phone":"+1 941 756 0386",
    "sg:postcode":"34202",
    "sg:province":"FL",
    "sg:tags":[
        "merchandise"
    ],
    "wof:name":"Melton Joi",
    "wof:placetype":"venue"
},
  "geometry": {"coordinates":[-82.43755299999999,27.421586],"type":"Point"}
}