{
  "type": "Feature",
  "properties": {
    "addr:full":"4245 Palm Ave West Palm Beach FL 33406",
    "addr:housenumber":"4245",
    "addr:postcode":"33406",
    "addr:street":"Palm Ave",
    "iso:country":"US",
    "sg:address":"4245 Palm Ave",
    "sg:city":"West Palm Beach",
    "sg:classifiers":[
        {
            "category":"Professional",
            "type":"Services"
        }
    ],
    "sg:phone":"+1 561 616 0309",
    "sg:postcode":"33406",
    "sg:province":"FL",
    "wof:name":"Southwest Weather",
    "wof:placetype":"venue"
},
  "geometry": {"coordinates":[-80.109118,26.659898],"type":"Point"}
}