{
  "type": "Feature",
  "properties": {
    "iso:country":"US",
    "sg:address":"1510 S Federal Hwy",
    "sg:city":"Hollywood",
    "sg:classifiers":[
        {
            "category":"Food & Beverages",
            "subcategory":"Groceries & Convenience Stores",
            "type":"Retail Goods"
        }
    ],
    "sg:phone":"+1 954 929 0131",
    "sg:postcode":"33020",
    "sg:province":"FL",
    "sg:tags":[
        "ticket",
        "lottery",
        "beer",
        "wine"
    ],
    "wof:name":"President Supermarket 4",
    "wof:placetype":"venue"
},
  "geometry": {"coordinates":[-80.14268800000001,25.997769],"type":"Point"}
}