{
  "type": "Feature",
  "properties": {
    "iso:country":"US",
    "sg:address":"931 N State Road 434",
    "sg:city":"Altamonte Springs",
    "sg:classifiers":[
        {
            "category":"Restaurant",
            "type":"Food & Drink"
        }
    ],
    "sg:phone":"+1 407 788 4222",
    "sg:postcode":"32714",
    "sg:province":"FL",
    "sg:tags":[
        "italian"
    ],
    "wof:name":"Carrabba's Italian Grill",
    "wof:placetype":"venue"
},
  "geometry": {"coordinates":[-81.418999,28.680901],"type":"Point"}
}