{
  "type": "Feature",
  "properties": {
    "iso:country":"US",
    "sg:address":"3529 Brink Cir",
    "sg:city":"Bonita Springs",
    "sg:classifiers":[
        {
            "category":"Building & Trades",
            "subcategory":"Construction",
            "type":"Services"
        }
    ],
    "sg:phone":"+1 239 390 7166",
    "sg:postcode":"34134",
    "sg:province":"FL",
    "sg:tags":[
        "roofing",
        "contractor"
    ],
    "wof:name":"Pro Line Roofing Inc",
    "wof:placetype":"venue"
},
  "geometry": {"coordinates":[-81.812057,26.331924],"type":"Point"}
}