{
  "type": "Feature",
  "properties": {
    "iso:country":"US",
    "sg:address":"4001 Forsyth Rd",
    "sg:city":"Winter Park",
    "sg:classifiers":[
        {
            "category":"Manufacturing",
            "subcategory":"Rubber & Plastics",
            "type":"Manufacturing & Wholesale Goods"
        }
    ],
    "sg:phone":"+1 407 671 6989",
    "sg:postcode":"32792",
    "sg:province":"FL",
    "sg:tags":[
        "pipe"
    ],
    "sg:website":"www.accordindustries.com",
    "wof:name":"Universal 100 Products",
    "wof:placetype":"venue"
},
  "geometry": {"coordinates":[-81.298962,28.600838],"type":"Point"}
}