{
  "type": "Feature",
  "properties": {
    "addr:full":"6591 Chestnut Cir Naples FL 34109",
    "addr:housenumber":"6591",
    "addr:postcode":"34109",
    "addr:street":"Chestnut Cir",
    "iso:country":"US",
    "sg:address":"6591 Chestnut Cir",
    "sg:city":"Naples",
    "sg:classifiers":[
        {
            "category":"Travel",
            "subcategory":"Travel Agent",
            "type":"Entertainment"
        },
        {
            "category":"Shopping",
            "subcategory":"Gifts & Souvenirs",
            "type":"Retail Goods"
        }
    ],
    "sg:phone":"+1 239 591 1492",
    "sg:postcode":"34109",
    "sg:province":"FL",
    "sg:tags":[
        "cruise"
    ],
    "wof:name":"Cards Cruise Connection Inc",
    "wof:placetype":"venue"
},
  "geometry": {"coordinates":[-81.784901,26.224011],"type":"Point"}
}