{
  "type": "Feature",
  "properties": {
    "iso:country":"US",
    "sg:address":"5175 Cherry Blossom Ln",
    "sg:city":"Milton",
    "sg:classifiers":[
        {
            "category":"Manufacturing",
            "subcategory":"Printing",
            "type":"Manufacturing & Wholesale Goods"
        }
    ],
    "sg:phone":"+1 850 623 6050",
    "sg:postcode":"32570",
    "sg:province":"FL",
    "sg:tags":[
        "lithographic",
        "engaged",
        "commercial"
    ],
    "wof:name":"Zebra Graphics",
    "wof:placetype":"venue"
},
  "geometry": {"coordinates":[-87.078531,30.622188],"type":"Point"}
}