{
  "type": "Feature",
  "properties": {
    "iso:country":"US",
    "sg:address":"2108 Turnberry Dr",
    "sg:city":"Oviedo",
    "sg:classifiers":[
        {
            "category":"Wholesale",
            "subcategory":"Groceries",
            "type":"Manufacturing & Wholesale Goods"
        }
    ],
    "sg:phone":"+1 407 366 0192",
    "sg:postcode":"32765",
    "sg:province":"FL",
    "wof:name":"Nafta Trading Corporation",
    "wof:placetype":"venue"
},
  "geometry": {"coordinates":[-81.167402,28.638974],"type":"Point"}
}