{
  "type": "Feature",
  "properties": {
    "iso:country":"US",
    "sg:address":"4750 Country Meadows Blvd",
    "sg:city":"Sarasota",
    "sg:classifiers":[
        {
            "category":"Restaurant",
            "type":"Food & Drink"
        }
    ],
    "sg:phone":"+1 941 379 6468",
    "sg:postcode":"34235",
    "sg:province":"FL",
    "sg:tags":[
        "eating"
    ],
    "wof:name":"Lindworth Inc",
    "wof:placetype":"venue"
},
  "geometry": {"coordinates":[-82.46814000000001,27.353139],"type":"Point"}
}