{
  "type": "Feature",
  "properties": {
    "addr:full":"126 State Hwy 13 Jacksonville FL 32259",
    "addr:housenumber":"126",
    "addr:postcode":"32259",
    "addr:street":"State Hwy 13",
    "iso:country":"US",
    "sg:address":"126 State Hwy 13",
    "sg:city":"Jacksonville",
    "sg:classifiers":[
        {
            "category":"Real Estate",
            "subcategory":"Real Estate Agent",
            "type":"Services"
        }
    ],
    "sg:phone":"+1 904 287 7700",
    "sg:postcode":"32259",
    "sg:province":"FL",
    "wof:name":"United Country Real Estate",
    "wof:placetype":"venue"
},
  "geometry": {"coordinates":[-81.62525100000001,30.126701],"type":"Point"}
}