{
  "type": "Feature",
  "properties": {
    "addr:full":"1861 NW 46th Ave Fort Lauderdale FL 33313",
    "addr:housenumber":"1861",
    "addr:postcode":"33313",
    "addr:street":"Nw 46Th Ave",
    "iso:country":"US",
    "sg:address":"1861 NW 46th Ave",
    "sg:city":"Fort Lauderdale",
    "sg:classifiers":[
        {
            "category":"Real Estate",
            "subcategory":"Real Estate Operator",
            "type":"Services"
        }
    ],
    "sg:phone":"+1 954 739 7373",
    "sg:postcode":"33313",
    "sg:province":"FL",
    "sg:tags":[
        "building",
        "apartment"
    ],
    "wof:name":"Continental Apartments",
    "wof:placetype":"venue"
},
  "geometry": {"coordinates":[-80.210601,26.147755],"type":"Point"}
}