{
  "type": "Feature",
  "properties": {
    "iso:country":"US",
    "sg:address":"9429 Affirmed Ln",
    "sg:city":"Boca Raton",
    "sg:classifiers":[
        {
            "category":"Building & Trades",
            "subcategory":"Electrical",
            "type":"Services"
        }
    ],
    "sg:phone":"+1 561 218 2493",
    "sg:postcode":"33496",
    "sg:province":"FL",
    "sg:tags":[
        "electrical",
        "contractor"
    ],
    "wof:name":"L Kasztner Electric Inc",
    "wof:placetype":"venue"
},
  "geometry": {"coordinates":[-80.194878,26.402999],"type":"Point"}
}