{
  "type": "Feature",
  "properties": {
    "iso:country":"US",
    "sg:address":"1118 N Shade Ave",
    "sg:city":"Sarasota",
    "sg:classifiers":[
        {
            "category":"Retail",
            "subcategory":"Auto Repair",
            "type":"Services"
        }
    ],
    "sg:phone":"+1 941 362 3833",
    "sg:postcode":"34237",
    "sg:province":"FL",
    "sg:tags":[
        "muffler",
        "exhaust",
        "system"
    ],
    "wof:name":"Stacey's Custom Muffler",
    "wof:placetype":"venue"
},
  "geometry": {"coordinates":[-82.52176,27.347042],"type":"Point"}
}