{
  "type": "Feature",
  "properties": {
    "iso:country":"US",
    "sg:address":"402 US Hwy 17",
    "sg:city":"Yulee",
    "sg:classifiers":[
        {
            "category":"Professional",
            "subcategory":"Business Services",
            "type":"Services"
        }
    ],
    "sg:phone":"+1 904 225 0521",
    "sg:postcode":"32097",
    "sg:province":"FL",
    "sg:tags":[
        "auctioneer"
    ],
    "wof:name":"Auction Center & Sales Of Yule",
    "wof:placetype":"venue"
},
  "geometry": {"coordinates":[-81.597928,30.606339],"type":"Point"}
}