{
  "type": "Feature",
  "properties": {
    "addr:full":"2840 SW 79th Ct Miami FL 33155",
    "addr:housenumber":"2840",
    "addr:postcode":"33155",
    "addr:street":"Sw 79Th Ct",
    "iso:country":"US",
    "sg:address":"2840 SW 79th Ct",
    "sg:city":"Miami",
    "sg:classifiers":[
        {
            "category":"Building & Trades",
            "subcategory":"Construction",
            "type":"Services"
        }
    ],
    "sg:phone":"+1 305 266 4231",
    "sg:postcode":"33155",
    "sg:province":"FL",
    "sg:tags":[
        "contractor"
    ],
    "wof:name":"Hank Ridings Plastering Inc",
    "wof:placetype":"venue"
},
  "geometry": {"coordinates":[-80.324607,25.742788],"type":"Point"}
}