{
  "type": "Feature",
  "properties": {
    "iso:country":"US",
    "sg:address":"2585 SE Federal Hwy",
    "sg:city":"Stuart",
    "sg:classifiers":[
        {
            "category":"Shopping",
            "subcategory":"Used Merchandise",
            "type":"Retail Goods"
        }
    ],
    "sg:phone":"+1 772 286 6909",
    "sg:postcode":"34994",
    "sg:province":"FL",
    "sg:tags":[
        "furniture"
    ],
    "wof:name":"Thrift Store",
    "wof:placetype":"venue"
},
  "geometry": {"coordinates":[-80.23166500000001,27.172879],"type":"Point"}
}