{
  "type": "Feature",
  "properties": {
    "iso:country":"US",
    "sg:address":"4000 Ponce de Leon Blvd",
    "sg:city":"Coral Gables",
    "sg:classifiers":[
        {
            "category":"Arts & Performance",
            "subcategory":"Theater",
            "type":"Entertainment"
        }
    ],
    "sg:phone":"+1 305 648 8100",
    "sg:postcode":"33146",
    "sg:province":"FL",
    "sg:tags":[
        "television",
        "station",
        "representative"
    ],
    "wof:name":"HBO Latin America Adv Svc",
    "wof:placetype":"venue"
},
  "geometry": {"coordinates":[-80.258476,25.733199],"type":"Point"}
}