{
  "type": "Feature",
  "properties": {
    "addr:full":"1622 S Dixie Hwy Lake Worth FL 33460",
    "addr:housenumber":"1622",
    "addr:postcode":"33460",
    "addr:street":"S Dixie Hwy",
    "iso:country":"US",
    "sg:address":"1622 S Dixie Hwy",
    "sg:city":"Lake Worth",
    "sg:classifiers":[
        {
            "category":"Building & Trades",
            "subcategory":"Equipment Rental",
            "type":"Services"
        }
    ],
    "sg:phone":"+1 561 547 1234",
    "sg:postcode":"33460",
    "sg:province":"FL",
    "wof:name":"Rental Giant",
    "wof:placetype":"venue"
},
  "geometry": {"coordinates":[-80.05390800000001,26.595379],"type":"Point"}
}