{
  "type": "Feature",
  "properties": {
    "iso:country":"US",
    "sg:address":"3203 General Electric Rd",
    "sg:city":"Apopka",
    "sg:classifiers":[
        {
            "category":"Building & Trades",
            "subcategory":"Construction",
            "type":"Services"
        }
    ],
    "sg:phone":"+1 407 880 8851",
    "sg:postcode":"32703",
    "sg:province":"FL",
    "sg:tags":[
        "repair",
        "contractor"
    ],
    "wof:name":"Daniels McHy & Fabrication",
    "wof:placetype":"venue"
},
  "geometry": {"coordinates":[-81.56143,28.691035],"type":"Point"}
}