{
  "type": "Feature",
  "properties": {
    "iso:country":"US",
    "sg:address":"14921 SW 4th Ave",
    "sg:city":"Ocala",
    "sg:classifiers":[
        {
            "category":"Freight",
            "type":"Transportation"
        }
    ],
    "sg:phone":"+1 352 307 9102",
    "sg:postcode":"34473",
    "sg:province":"FL",
    "sg:tags":[
        "operator",
        "trucking"
    ],
    "wof:name":"R C Mobile Homes Services",
    "wof:placetype":"venue"
},
  "geometry": {"coordinates":[-82.14035,29.008562],"type":"Point"}
}