{
  "type": "Feature",
  "properties": {
    "addr:full":"4636 W Irlo Bronson Memorial Hwy Kissimmee FL 34746",
    "addr:housenumber":"4636",
    "addr:postcode":"34746",
    "addr:street":"W Irlo Bronson Memorial Hwy",
    "iso:country":"US",
    "sg:address":"4636 W Irlo Bronson Memorial Hwy",
    "sg:city":"Kissimmee",
    "sg:classifiers":[
        {
            "category":"Food & Beverages",
            "subcategory":"Specialty",
            "type":"Retail Goods"
        }
    ],
    "sg:phone":"+1 407 390 9343",
    "sg:postcode":"34746",
    "sg:province":"FL",
    "sg:tags":[
        "miscellaneous",
        "store"
    ],
    "wof:name":"Krystal Pure Vitamins & Herbs",
    "wof:placetype":"venue"
},
  "geometry": {"coordinates":[-81.467428,28.313106],"type":"Point"}
}