{
  "type": "Feature",
  "properties": {
    "iso:country":"US",
    "sg:address":"8345 S US Highway 17/92",
    "sg:city":"Casselberry",
    "sg:classifiers":[
        {
            "category":"Shopping",
            "subcategory":"Jewelry",
            "type":"Retail Goods"
        },
        {
            "category":"Shopping",
            "subcategory":"Pawn Shop",
            "type":"Retail Goods"
        }
    ],
    "sg:phone":"+1 407 831 3451",
    "sg:postcode":"32730",
    "sg:province":"FL",
    "sg:website":"www.ezpawn.com",
    "wof:name":"Ez Pawn",
    "wof:placetype":"venue"
},
  "geometry": {"coordinates":[-81.35050699999999,28.649329],"type":"Point"}
}