{
  "type": "Feature",
  "properties": {
    "addr:full":"7985 113th St N Seminole FL 33772",
    "addr:housenumber":"7985",
    "addr:postcode":"33772",
    "addr:street":"113Th St N",
    "iso:country":"US",
    "sg:address":"7985 113th St N",
    "sg:city":"Seminole",
    "sg:classifiers":[
        {
            "category":"Professional",
            "subcategory":"Computer Services",
            "type":"Services"
        }
    ],
    "sg:phone":"+1 727 399 2304",
    "sg:postcode":"33772",
    "sg:province":"FL",
    "sg:tags":[
        "intranet"
    ],
    "wof:name":"My Smart Marketing Inc",
    "wof:placetype":"venue"
},
  "geometry": {"coordinates":[-82.795252,27.845145],"type":"Point"}
}