{
  "type": "Feature",
  "properties": {
    "addr:full":"1650 NW 57th St Miami FL 33142",
    "addr:housenumber":"1650",
    "addr:postcode":"33142",
    "addr:street":"Nw 57Th St",
    "iso:country":"US",
    "sg:address":"1650 NW 57th St",
    "sg:city":"Miami",
    "sg:classifiers":[
        {
            "category":"Wholesale",
            "subcategory":"Books, Periodicals, & Newspapers",
            "type":"Manufacturing & Wholesale Goods"
        }
    ],
    "sg:phone":"+1 305 696 5775",
    "sg:postcode":"33142",
    "sg:province":"FL",
    "sg:tags":[
        "publisher",
        "book"
    ],
    "wof:name":"My Star Publishing",
    "wof:placetype":"venue"
},
  "geometry": {"coordinates":[-80.224205,25.827403],"type":"Point"}
}