{
  "type": "Feature",
  "properties": {
    "addr:full":"5499 37th St E Bradenton FL 34203",
    "addr:housenumber":"5499",
    "addr:postcode":"34203",
    "addr:street":"37Th St",
    "iso:country":"US",
    "sg:address":"5499 37th St E",
    "sg:city":"Bradenton",
    "sg:classifiers":[
        {
            "category":"Organizations",
            "subcategory":"Membership Organization",
            "type":"Services"
        }
    ],
    "sg:phone":"+1 941 753 8775",
    "sg:postcode":"34203",
    "sg:province":"FL",
    "sg:tags":[
        "business",
        "association"
    ],
    "wof:name":"Garden Lakes Community Assn",
    "wof:placetype":"venue"
},
  "geometry": {"coordinates":[-82.51558799999999,27.445491],"type":"Point"}
}