{
  "type": "Feature",
  "properties": {
    "addr:full":"44 Bayside Dr Palm Coast FL 32137",
    "addr:housenumber":"44",
    "addr:postcode":"32137",
    "addr:street":"Bayside Dr",
    "iso:country":"US",
    "sg:address":"44 Bayside Dr",
    "sg:city":"Palm Coast",
    "sg:classifiers":[
        {
            "category":"Real Estate",
            "subcategory":"Real Estate Agent",
            "type":"Services"
        }
    ],
    "sg:phone":"+1 386 931 5295",
    "sg:postcode":"32137",
    "sg:province":"FL",
    "wof:name":"Ken Perkins PA",
    "wof:placetype":"venue"
},
  "geometry": {"coordinates":[-81.2403,29.566135],"type":"Point"}
}