{
  "type": "Feature",
  "properties": {
    "addr:full":"933 N Orlando Ave Winter Park FL 32789",
    "addr:housenumber":"933",
    "addr:postcode":"32789",
    "addr:street":"N Orlando Ave",
    "iso:country":"US",
    "sg:address":"933 N Orlando Ave",
    "sg:city":"Winter Park",
    "sg:classifiers":[
        {
            "category":"Shopping",
            "subcategory":"Computers & Home Electronics",
            "type":"Retail Goods"
        }
    ],
    "sg:phone":"+1 407 644 2537",
    "sg:postcode":"32789",
    "sg:province":"FL",
    "sg:tags":[
        "game",
        "video"
    ],
    "wof:name":"Game Stop Corp",
    "wof:placetype":"venue"
},
  "geometry": {"coordinates":[-81.365211,28.604013],"type":"Point"}
}