{
  "type": "Feature",
  "properties": {
    "iso:country":"US",
    "sg:address":"3176 161st Ter N",
    "sg:city":"Loxahatchee",
    "sg:classifiers":[
        {
            "category":"Recreation",
            "type":"Entertainment"
        }
    ],
    "sg:phone":"+1 561 798 2725",
    "sg:postcode":"33470",
    "sg:province":"FL",
    "sg:tags":[
        "stable"
    ],
    "wof:name":"Blue Rose Acres",
    "wof:placetype":"venue"
},
  "geometry": {"coordinates":[-80.298973,26.718927],"type":"Point"}
}