{
  "type": "Feature",
  "properties": {
    "addr:full":"11021 NW 21st St Pompano Beach FL 33071",
    "addr:housenumber":"11021",
    "addr:postcode":"33071",
    "addr:street":"Nw 21St St",
    "iso:country":"US",
    "sg:address":"11021 NW 21st St",
    "sg:city":"Pompano Beach",
    "sg:classifiers":[
        {
            "category":"Banks & Credit Unions",
            "subcategory":"Bank",
            "type":"Services"
        }
    ],
    "sg:phone":"+1 954 755 3380",
    "sg:postcode":"33071",
    "sg:province":"FL",
    "sg:tags":[
        "mortgage"
    ],
    "wof:name":"Superior Mortgage Corporation",
    "wof:placetype":"venue"
},
  "geometry": {"coordinates":[-80.272705,26.257112],"type":"Point"}
}