{
  "type": "Feature",
  "properties": {
    "addr:full":"20266 NE 15th Ct Miami FL 33179",
    "addr:housenumber":"20266",
    "addr:postcode":"33179",
    "addr:street":"Ne 15Th Ct",
    "iso:country":"US",
    "sg:address":"20266 NE 15th Ct",
    "sg:city":"Miami",
    "sg:classifiers":[
        {
            "category":"Wholesale",
            "subcategory":"Vending Machines",
            "type":"Manufacturing & Wholesale Goods"
        }
    ],
    "sg:phone":"+1 305 654 0099",
    "sg:postcode":"33179",
    "sg:province":"FL",
    "wof:name":"Pelican Vending",
    "wof:placetype":"venue"
},
  "geometry": {"coordinates":[-80.171104,25.960964],"type":"Point"}
}