{
  "type": "Feature",
  "properties": {
    "iso:country":"US",
    "sg:address":"6200 N Atlantic Ave",
    "sg:city":"Cape Canaveral",
    "sg:classifiers":[
        {
            "category":"Home & Garden",
            "subcategory":"Building Materials",
            "type":"Retail Goods"
        }
    ],
    "sg:phone":"+1 321 799 0606",
    "sg:postcode":"32920",
    "sg:province":"FL",
    "sg:tags":[
        "screen",
        "window"
    ],
    "wof:name":"Ocean Screens",
    "wof:placetype":"venue"
},
  "geometry": {"coordinates":[-80.60560599999999,28.374644],"type":"Point"}
}