{
  "type": "Feature",
  "properties": {
    "addr:full":"1128 NE 13th Ave Ocala FL 34470",
    "addr:housenumber":"1128",
    "addr:postcode":"34470",
    "addr:street":"Ne 13Th Ave",
    "iso:country":"US",
    "sg:address":"1128 NE 13th Ave",
    "sg:city":"Ocala",
    "sg:classifiers":[
        {
            "category":"Professional",
            "type":"Services"
        }
    ],
    "sg:phone":"+1 352 620 0442",
    "sg:postcode":"34470",
    "sg:province":"FL",
    "sg:tags":[
        "establishment"
    ],
    "wof:name":"Xtreme Records",
    "wof:placetype":"venue"
},
  "geometry": {"coordinates":[-82.121039,29.198371],"type":"Point"}
}