{
  "type": "Feature",
  "properties": {
    "addr:full":"142 SE 6th St Delray Beach FL 33483",
    "addr:housenumber":"142",
    "addr:postcode":"33483",
    "addr:street":"Se 6Th St",
    "iso:country":"US",
    "sg:address":"142 SE 6th St",
    "sg:city":"Delray Beach",
    "sg:classifiers":[
        {
            "category":"Restaurant",
            "type":"Food & Drink"
        }
    ],
    "sg:phone":"+1 561 279 2824",
    "sg:postcode":"33483",
    "sg:province":"FL",
    "sg:tags":[
        "eating"
    ],
    "wof:name":"Beach Dogs",
    "wof:placetype":"venue"
},
  "geometry": {"coordinates":[-80.070109,26.452464],"type":"Point"}
}