{
  "type": "Feature",
  "properties": {
    "addr:full":"10448 Carlson Cir Clermont FL 34711",
    "addr:housenumber":"10448",
    "addr:postcode":"34711",
    "addr:street":"Carlson Cir",
    "iso:country":"US",
    "sg:address":"10448 Carlson Cir",
    "sg:city":"Clermont",
    "sg:classifiers":[
        {
            "category":"Building & Trades",
            "subcategory":"Construction",
            "type":"Services"
        }
    ],
    "sg:phone":"+1 352 255 9018",
    "sg:postcode":"34711",
    "sg:province":"FL",
    "sg:tags":[
        "house"
    ],
    "wof:name":"Brock Jeremy Home Improvement",
    "wof:placetype":"venue"
},
  "geometry": {"coordinates":[-81.778593,28.496666],"type":"Point"}
}