{
  "type": "Feature",
  "properties": {
    "iso:country":"US",
    "sg:address":"5824 State Rd 54",
    "sg:city":"New Port Richey",
    "sg:classifiers":[
        {
            "category":"Restaurant",
            "type":"Food & Drink"
        }
    ],
    "sg:phone":"+1 727 841 8816",
    "sg:postcode":"34652",
    "sg:province":"FL",
    "wof:name":"Jeannie's Diner & Restaurant",
    "wof:placetype":"venue"
},
  "geometry": {"coordinates":[-82.718395,28.216888],"type":"Point"}
}