{
  "type": "Feature",
  "properties": {
    "iso:country":"US",
    "sg:address":"7035 Airport Pulling Rd N",
    "sg:city":"Naples",
    "sg:classifiers":[
        {
            "category":"Restaurant",
            "type":"Food & Drink"
        },
        {
            "category":"Retail",
            "subcategory":"Event Space",
            "type":"Services"
        }
    ],
    "sg:phone":"+1 239 597 5210",
    "sg:postcode":"34109",
    "sg:province":"FL",
    "sg:tags":[
        "italian",
        "banquet",
        "hall",
        "reception",
        "facility"
    ],
    "wof:name":"Italian American Club Of Naple",
    "wof:placetype":"venue"
},
  "geometry": {"coordinates":[-81.768669,26.232153],"type":"Point"}
}