{
  "type": "Feature",
  "properties": {
    "iso:country":"US",
    "sg:address":"73 SW Flagler Ave",
    "sg:city":"Stuart",
    "sg:classifiers":[
        {
            "category":"Professional",
            "subcategory":"Lawyer & Legal Services",
            "type":"Services"
        }
    ],
    "sg:phone":"+1 772 463 8402",
    "sg:postcode":"34994",
    "sg:province":"FL",
    "sg:tags":[
        "attorney"
    ],
    "wof:name":"Williams & Lelinger",
    "wof:placetype":"venue"
},
  "geometry": {"coordinates":[-80.253488,27.19837],"type":"Point"}
}