{
  "type": "Feature",
  "properties": {
    "addr:full":"3600 NW 54th St Miami FL 33142",
    "addr:housenumber":"3600",
    "addr:postcode":"33142",
    "addr:street":"Nw 54Th St",
    "iso:country":"US",
    "sg:address":"3600 NW 54th St",
    "sg:city":"Miami",
    "sg:classifiers":[
        {
            "category":"Retail",
            "subcategory":"Auto Rental",
            "type":"Services"
        }
    ],
    "sg:phone":"+1 305 633 7400",
    "sg:postcode":"33142",
    "sg:province":"FL",
    "sg:tags":[
        "renting",
        "truck",
        "leasing"
    ],
    "wof:name":"Budget Truck Rental",
    "wof:placetype":"venue"
},
  "geometry": {"coordinates":[-80.25586800000001,25.823479],"type":"Point"}
}