{
  "type": "Feature",
  "properties": {
    "iso:country":"US",
    "sg:address":"2970 Day Ave",
    "sg:city":"Miami",
    "sg:classifiers":[
        {
            "category":"Real Estate",
            "subcategory":"Real Estate Services",
            "type":"Services"
        }
    ],
    "sg:phone":"+1 305 446 9633",
    "sg:postcode":"33133",
    "sg:province":"FL",
    "sg:tags":[
        "management",
        "condominium"
    ],
    "wof:name":"Peppertree Village Townhouse Condominium Associa",
    "wof:placetype":"venue"
},
  "geometry": {"coordinates":[-80.24130700000001,25.731784],"type":"Point"}
}