{
  "type": "Feature",
  "properties": {
    "iso:country":"US",
    "sg:address":"4725 N Federal Hwy",
    "sg:city":"Fort Lauderdale",
    "sg:classifiers":[
        {
            "category":"Health Services",
            "subcategory":"Doctor",
            "type":"Services"
        }
    ],
    "sg:phone":"+1 954 267 0642",
    "sg:postcode":"33308",
    "sg:province":"FL",
    "sg:tags":[
        "physician",
        "surgeon"
    ],
    "wof:name":"Surgical Assistant Inc",
    "wof:placetype":"venue"
},
  "geometry": {"coordinates":[-80.117161,26.186253],"type":"Point"}
}