{
  "type": "Feature",
  "properties": {
    "addr:full":"800 Paul St Orlando FL 32808",
    "addr:housenumber":"800",
    "addr:postcode":"32808",
    "addr:street":"Paul St",
    "iso:country":"US",
    "sg:address":"800 Paul St",
    "sg:city":"Orlando",
    "sg:classifiers":[
        {
            "category":"Professional",
            "type":"Services"
        }
    ],
    "sg:phone":"+1 407 293 8548",
    "sg:postcode":"32808",
    "sg:province":"FL",
    "sg:tags":[
        "establishment"
    ],
    "wof:name":"Total Accident Help LLC",
    "wof:placetype":"venue"
},
  "geometry": {"coordinates":[-81.46463900000001,28.553073],"type":"Point"}
}