{
  "type": "Feature",
  "properties": {
    "iso:country":"US",
    "sg:address":"808 Carolin St",
    "sg:city":"Melbourne",
    "sg:classifiers":[
        {
            "category":"Wholesale",
            "subcategory":"Construction Materials",
            "type":"Manufacturing & Wholesale Goods"
        }
    ],
    "sg:phone":"+1 321 724 1301",
    "sg:postcode":"32901",
    "sg:province":"FL",
    "sg:tags":[
        "fence"
    ],
    "wof:name":"Southern Outdoor Living",
    "wof:placetype":"venue"
},
  "geometry": {"coordinates":[-80.61031699999999,28.089543],"type":"Point"}
}