{
  "type": "Feature",
  "properties": {
    "iso:country":"US",
    "sg:address":"1647 W Gulf To Lake Hwy",
    "sg:city":"Lecanto",
    "sg:classifiers":[
        {
            "category":"Professional",
            "subcategory":"Accounting & Tax Preparation",
            "type":"Services"
        }
    ],
    "sg:phone":"+1 352 746 4383",
    "sg:postcode":"34461",
    "sg:province":"FL",
    "sg:tags":[
        "accountant"
    ],
    "wof:name":"Maryanne Gray Accounting Svc",
    "wof:placetype":"venue"
},
  "geometry": {"coordinates":[-82.461164,28.851984],"type":"Point"}
}