{
  "type": "Feature",
  "properties": {
    "iso:country":"US",
    "sg:address":"1003 Jupiter Park Ln",
    "sg:city":"Jupiter",
    "sg:classifiers":[
        {
            "category":"Manufacturing",
            "subcategory":"Buildings",
            "type":"Manufacturing & Wholesale Goods"
        }
    ],
    "sg:phone":"+1 561 741 7337",
    "sg:postcode":"33458",
    "sg:province":"FL",
    "sg:tags":[
        "prefabricated",
        "wood",
        "mfg"
    ],
    "wof:name":"Rocky Mtn Cypress Log Hmes LLC",
    "wof:placetype":"venue"
},
  "geometry": {"coordinates":[-80.143461,26.925867],"type":"Point"}
}