{
  "type": "Feature",
  "properties": {
    "iso:country":"US",
    "sg:address":"4974 Freedom Cir",
    "sg:city":"Lake Worth",
    "sg:classifiers":[
        {
            "category":"Building & Trades",
            "subcategory":"Construction",
            "type":"Services"
        }
    ],
    "sg:phone":"+1 561 642 5387",
    "sg:postcode":"33461",
    "sg:province":"FL",
    "sg:tags":[
        "resurfacing",
        "laying",
        "refinishing",
        "floor"
    ],
    "wof:name":"Durham Inc",
    "wof:placetype":"venue"
},
  "geometry": {"coordinates":[-80.111153,26.604633],"type":"Point"}
}