{
  "type": "Feature",
  "properties": {
    "addr:full":"2886 Tamiami Trl Port Charlotte FL 33952",
    "addr:housenumber":"2886",
    "addr:postcode":"33952",
    "addr:street":"Tamiami Trl",
    "iso:country":"US",
    "sg:address":"2886 Tamiami Trl",
    "sg:city":"Port Charlotte",
    "sg:classifiers":[
        {
            "category":"Professional",
            "subcategory":"Lawyer & Legal Services",
            "type":"Services"
        }
    ],
    "sg:phone":"+1 941 627 2200",
    "sg:postcode":"33952",
    "sg:province":"FL",
    "wof:name":"Mary L Geer PA",
    "wof:placetype":"venue"
},
  "geometry": {"coordinates":[-82.10683899999999,26.988076],"type":"Point"}
}