{
  "type": "Feature",
  "properties": {
    "addr:full":"1503 Angle Rd Fort Pierce FL 34947",
    "addr:housenumber":"1503",
    "addr:postcode":"34947",
    "addr:street":"Angle Rd",
    "iso:country":"US",
    "sg:address":"1503 Angle Rd",
    "sg:city":"Fort Pierce",
    "sg:classifiers":[
        {
            "category":"Food & Beverages",
            "subcategory":"Groceries & Convenience Stores",
            "type":"Retail Goods"
        }
    ],
    "sg:phone":"+1 772 468 2070",
    "sg:postcode":"34947",
    "sg:province":"FL",
    "sg:tags":[
        "grocer"
    ],
    "wof:name":"Joe's Angle RD Grocery",
    "wof:placetype":"venue"
},
  "geometry": {"coordinates":[-80.373059,27.464192],"type":"Point"}
}