{
  "type": "Feature",
  "properties": {
    "iso:country":"US",
    "sg:address":"3810 W Neptune St",
    "sg:city":"Tampa",
    "sg:classifiers":[
        {
            "category":"Farming",
            "subcategory":"Fish & Marine Products",
            "type":"Manufacturing & Wholesale Goods"
        },
        {
            "category":"Retail",
            "subcategory":"Repair Shop",
            "type":"Services"
        }
    ],
    "sg:phone":"+1 813 254 5423",
    "sg:postcode":"33629",
    "sg:province":"FL",
    "sg:tags":[
        "picture",
        "frame",
        "restoration",
        "framing"
    ],
    "sg:website":"http://www.thegreatframeup.com",
    "wof:name":"The Great Frame Up South Tampa",
    "wof:placetype":"venue"
},
  "geometry": {"coordinates":[-82.506074,27.930241],"type":"Point"}
}