{
  "type": "Feature",
  "properties": {
    "iso:country":"US",
    "sg:address":"4900 95th Ave",
    "sg:city":"Pinellas Park",
    "sg:classifiers":[
        {
            "category":"Health Services",
            "subcategory":"Doctor",
            "type":"Services"
        }
    ],
    "sg:phone":"+1 727 546 4400",
    "sg:postcode":"33782",
    "sg:province":"FL",
    "sg:tags":[
        "physician",
        "surgeon"
    ],
    "wof:name":"Florida Medical Ctr",
    "wof:placetype":"venue"
},
  "geometry": {"coordinates":[-82.70074700000001,27.858165],"type":"Point"}
}