{
  "type": "Feature",
  "properties": {
    "iso:country":"US",
    "sg:address":"20500 S Dixie Hwy",
    "sg:city":"Miami",
    "sg:classifiers":[
        {
            "category":"Restaurant",
            "type":"Food & Drink"
        }
    ],
    "sg:menulink":"http://www.allmenus.com/fl/princeton-goulds/241532-la-villa-de-don-pollo/menu/",
    "sg:phone":"+1 305 251 6363",
    "sg:postcode":"33189",
    "sg:province":"FL",
    "sg:tags":[
        "peruvian"
    ],
    "wof:name":"La Villa De Don Pollo",
    "wof:placetype":"venue"
},
  "geometry": {"coordinates":[-80.372072,25.576447],"type":"Point"}
}