{
  "type": "Feature",
  "properties": {
    "iso:country":"US",
    "sg:address":"9 Robinwood Dr",
    "sg:city":"Longwood",
    "sg:classifiers":[
        {
            "category":"Cinema",
            "subcategory":"Movie Theater",
            "type":"Entertainment"
        }
    ],
    "sg:phone":"+1 917 775 6137",
    "sg:postcode":"32779",
    "sg:province":"FL",
    "sg:tags":[
        "theatrical",
        "consultant"
    ],
    "wof:name":"Ariana Productions",
    "wof:placetype":"venue"
},
  "geometry": {"coordinates":[-81.37961199999999,28.743295],"type":"Point"}
}