{
  "type": "Feature",
  "properties": {
    "iso:country":"US",
    "sg:address":"1015 A1a Beach Blvd",
    "sg:city":"Saint Augustine",
    "sg:classifiers":[
        {
            "category":"Restaurant",
            "type":"Food & Drink"
        }
    ],
    "sg:menulink":"http://www.allmenus.com/fl/st-augustine/122510-quiznos-sub/menu/",
    "sg:phone":"+1 904 461 4200",
    "sg:postcode":"32080",
    "sg:province":"FL",
    "sg:tags":[
        "wrap",
        "american",
        "sandwich"
    ],
    "wof:name":"Quiznos Sub",
    "wof:placetype":"venue"
},
  "geometry": {"coordinates":[-81.27094,29.828333],"type":"Point"}
}