{
  "type": "Feature",
  "properties": {
    "iso:country":"US",
    "sg:address":"7648 W Irlo Bronson Memorial Hwy",
    "sg:city":"Kissimmee",
    "sg:classifiers":[
        {
            "category":"Shopping",
            "subcategory":"Shoes",
            "type":"Retail Goods"
        }
    ],
    "sg:phone":"+1 407 397 7430",
    "sg:postcode":"34747",
    "sg:province":"FL",
    "sg:tags":[
        "store"
    ],
    "wof:name":"A & M Footwear Outlet",
    "wof:placetype":"venue"
},
  "geometry": {"coordinates":[-81.593863,28.336452],"type":"Point"}
}