{
  "type": "Feature",
  "properties": {
    "iso:country":"US",
    "sg:address":"2222 Montclair Dr",
    "sg:city":"Sarasota",
    "sg:classifiers":[
        {
            "category":"Recreation",
            "type":"Entertainment"
        }
    ],
    "sg:phone":"+1 941 349 7677",
    "sg:postcode":"34231",
    "sg:province":"FL",
    "sg:tags":[
        "guide"
    ],
    "sg:website":"www.longboatkeyfishing.com",
    "wof:name":"Midnite Son Charter Fishing",
    "wof:placetype":"venue"
},
  "geometry": {"coordinates":[-82.526206,27.272129],"type":"Point"}
}