{
  "type": "Feature",
  "properties": {
    "iso:country":"US",
    "sg:address":"10896 US Hwy 98",
    "sg:city":"Miramar Beach",
    "sg:classifiers":[
        {
            "category":"Building & Trades",
            "subcategory":"Construction",
            "type":"Services"
        }
    ],
    "sg:phone":"+1 850 650 4255",
    "sg:postcode":"32550",
    "sg:province":"FL",
    "sg:tags":[
        "contractor"
    ],
    "wof:name":"Sterling Building Spec LLC",
    "wof:placetype":"venue"
},
  "geometry": {"coordinates":[-86.35811,30.381836],"type":"Point"}
}