{
  "type": "Feature",
  "properties": {
    "iso:country":"US",
    "sg:address":"204 N Park Ave",
    "sg:city":"Winter Park",
    "sg:classifiers":[
        {
            "category":"Personal",
            "subcategory":"Beauty Salon",
            "type":"Services"
        },
        {
            "category":"Personal",
            "subcategory":"Skin Care",
            "type":"Services"
        },
        {
            "category":"Personal",
            "subcategory":"Nail Salon",
            "type":"Services"
        }
    ],
    "sg:phone":"+1 407 628 4555",
    "sg:postcode":"32789",
    "sg:province":"FL",
    "sg:tags":[
        "hair"
    ],
    "wof:name":"Una Donna Piu Beauty Salon & Spa",
    "wof:placetype":"venue"
},
  "geometry": {"coordinates":[-81.351029,28.599006],"type":"Point"}
}