{
  "type": "Feature",
  "properties": {
    "addr:full":"200 Rialto Pl Melbourne FL 32901",
    "addr:housenumber":"200",
    "addr:postcode":"32901",
    "addr:street":"Rialto Pl",
    "iso:country":"US",
    "sg:address":"200 Rialto Pl",
    "sg:city":"Melbourne",
    "sg:classifiers":[
        {
            "category":"Retail",
            "subcategory":"Auto Rental",
            "type":"Services"
        }
    ],
    "sg:phone":"+1 321 729 6049",
    "sg:postcode":"32901",
    "sg:province":"FL",
    "sg:tags":[
        "renting",
        "automobile"
    ],
    "wof:name":"Alamo Rent-A-Car",
    "wof:placetype":"venue"
},
  "geometry": {"coordinates":[-80.62558300000001,28.090622],"type":"Point"}
}