{
  "type": "Feature",
  "properties": {
    "iso:country":"US",
    "sg:address":"2035 SW 25th Ter",
    "sg:city":"Miami",
    "sg:classifiers":[
        {
            "category":"Professional",
            "subcategory":"Business Services",
            "type":"Services"
        }
    ],
    "sg:phone":"+1 305 860 5095",
    "sg:postcode":"33133",
    "sg:province":"FL",
    "wof:name":"Gbal LLC",
    "wof:placetype":"venue"
},
  "geometry": {"coordinates":[-80.22662200000001,25.7449],"type":"Point"}
}