{
  "type": "Feature",
  "properties": {
    "iso:country":"US",
    "sg:address":"1720 W 15th St",
    "sg:city":"Panama City",
    "sg:classifiers":[
        {
            "category":"Home & Garden",
            "subcategory":"Garden Supply",
            "type":"Retail Goods"
        }
    ],
    "sg:phone":"+1 850 784 4800",
    "sg:postcode":"32401",
    "sg:province":"FL",
    "wof:name":"Jans Market",
    "wof:placetype":"venue"
},
  "geometry": {"coordinates":[-85.685867,30.175335],"type":"Point"}
}