{
  "type": "Feature",
  "properties": {
    "addr:full":"1971 SW Biltmore St Port Saint Lucie FL 34984",
    "addr:housenumber":"1971",
    "addr:postcode":"34984",
    "addr:street":"Sw Biltmore St",
    "iso:country":"US",
    "sg:address":"1971 SW Biltmore St",
    "sg:city":"Port Saint Lucie",
    "sg:classifiers":[
        {
            "category":"Building & Trades",
            "subcategory":"Construction",
            "type":"Services"
        }
    ],
    "sg:phone":"+1 772 879 9411",
    "sg:postcode":"34984",
    "sg:province":"FL",
    "sg:tags":[
        "home",
        "general",
        "contractor"
    ],
    "wof:name":"Panorama Homes Inc",
    "wof:placetype":"venue"
},
  "geometry": {"coordinates":[-80.36151099999999,27.282286],"type":"Point"}
}