{
  "type": "Feature",
  "properties": {
    "addr:full":"621 Cheney Hwy Titusville FL 32780",
    "addr:housenumber":"621",
    "addr:postcode":"32780",
    "addr:street":"Cheney Hwy",
    "iso:country":"US",
    "sg:address":"621 Cheney Hwy",
    "sg:city":"Titusville",
    "sg:classifiers":[
        {
            "category":"Home & Garden",
            "subcategory":"Hardware",
            "type":"Retail Goods"
        }
    ],
    "sg:phone":"+1 321 264 6258",
    "sg:postcode":"32780",
    "sg:province":"FL",
    "wof:name":"Florida Hardware",
    "wof:placetype":"venue"
},
  "geometry": {"coordinates":[-80.8098,28.557515],"type":"Point"}
}