{
  "type": "Feature",
  "properties": {
    "addr:full":"537 Deltona Blvd Deltona FL 32725",
    "addr:housenumber":"537",
    "addr:postcode":"32725",
    "addr:street":"Deltona Blvd",
    "iso:country":"US",
    "sg:address":"537 Deltona Blvd",
    "sg:city":"Deltona",
    "sg:classifiers":[
        {
            "category":"Building & Trades",
            "subcategory":"Construction",
            "type":"Services"
        }
    ],
    "sg:phone":"+1 386 860 0066",
    "sg:postcode":"32725",
    "sg:province":"FL",
    "sg:tags":[
        "house"
    ],
    "wof:name":"Mercedes Homes Inc",
    "wof:placetype":"venue"
},
  "geometry": {"coordinates":[-81.281879,28.875402],"type":"Point"}
}