{
  "type": "Feature",
  "properties": {
    "iso:country":"US",
    "sg:address":"1123 Fay Ave",
    "sg:city":"Spring Hill",
    "sg:classifiers":[
        {
            "category":"Building & Trades",
            "subcategory":"Landscaping Services",
            "type":"Services"
        }
    ],
    "sg:phone":"+1 352 683 5170",
    "sg:postcode":"34609",
    "sg:province":"FL",
    "wof:name":"Bowman Lawn Service",
    "wof:placetype":"venue"
},
  "geometry": {"coordinates":[-82.52476,28.449772],"type":"Point"}
}