{
  "type": "Feature",
  "properties": {
    "addr:full":"115 Otter Trl Sebring FL 33875",
    "addr:housenumber":"115",
    "addr:postcode":"33875",
    "addr:street":"Otter Trl",
    "iso:country":"US",
    "sg:address":"115 Otter Trl",
    "sg:city":"Sebring",
    "sg:classifiers":[
        {
            "category":"Wholesale",
            "subcategory":"Construction Materials",
            "type":"Manufacturing & Wholesale Goods"
        }
    ],
    "sg:phone":"+1 863 465 5452",
    "sg:postcode":"33875",
    "sg:province":"FL",
    "sg:tags":[
        "fence"
    ],
    "wof:name":"Ken C Kreulen Formal Fences",
    "wof:placetype":"venue"
},
  "geometry": {"coordinates":[-81.48872299999999,27.360743],"type":"Point"}
}