{
  "type": "Feature",
  "properties": {
    "iso:country":"US",
    "sg:address":"945 N Semoran Blvd",
    "sg:city":"Orlando",
    "sg:classifiers":[
        {
            "category":"Wholesale",
            "subcategory":"Non-durable Goods",
            "type":"Manufacturing & Wholesale Goods"
        }
    ],
    "sg:phone":"+1 321 947 4703",
    "sg:postcode":"32807",
    "sg:province":"FL",
    "sg:tags":[
        "dry",
        "goods-wholesale"
    ],
    "wof:name":"Rave Beauty Supply Inc",
    "wof:placetype":"venue"
},
  "geometry": {"coordinates":[-81.310785,28.557457],"type":"Point"}
}