{
  "type": "Feature",
  "properties": {
    "addr:full":"1258 W Bay Dr Largo FL 33770",
    "addr:housenumber":"1258",
    "addr:postcode":"33770",
    "addr:street":"W Bay Dr",
    "iso:country":"US",
    "sg:address":"1258 W Bay Dr",
    "sg:city":"Largo",
    "sg:classifiers":[
        {
            "category":"Health Services",
            "subcategory":"Doctor",
            "type":"Services"
        }
    ],
    "sg:phone":"+1 727 586 3751",
    "sg:postcode":"33770",
    "sg:province":"FL",
    "sg:tags":[
        "physician",
        "surgeon"
    ],
    "wof:name":"West Coast Surgical Specs",
    "wof:placetype":"venue"
},
  "geometry": {"coordinates":[-82.80141999999999,27.916823],"type":"Point"}
}