{
  "type": "Feature",
  "properties": {
    "iso:country":"US",
    "sg:address":"1000 SW 27th Ave",
    "sg:city":"Miami",
    "sg:classifiers":[
        {
            "category":"Retail",
            "subcategory":"Auto Repair",
            "type":"Services"
        }
    ],
    "sg:phone":"+1 305 541 9133",
    "sg:postcode":"33135",
    "sg:province":"FL",
    "sg:tags":[
        "repairing",
        "automobile"
    ],
    "wof:name":"Morejon Auto Repair Inc",
    "wof:placetype":"venue"
},
  "geometry": {"coordinates":[-80.23875700000001,25.762984],"type":"Point"}
}