{
  "type": "Feature",
  "properties": {
    "addr:full":"327 Racetrack Rd NW Fort Walton Beach FL 32547",
    "addr:housenumber":"327",
    "addr:postcode":"32547",
    "addr:street":"Racetrack Rd Nw",
    "iso:country":"US",
    "sg:address":"327 Racetrack Rd NW",
    "sg:city":"Fort Walton Beach",
    "sg:classifiers":[
        {
            "category":"Shopping",
            "type":"Retail Goods"
        }
    ],
    "sg:phone":"+1 850 315 0062",
    "sg:postcode":"32547",
    "sg:province":"FL",
    "sg:tags":[
        "merchandise"
    ],
    "wof:name":"Julies Nail Silk Flowers Gifts",
    "wof:placetype":"venue"
},
  "geometry": {"coordinates":[-86.628282,30.449278],"type":"Point"}
}