{
  "type": "Feature",
  "properties": {
    "iso:country":"US",
    "sg:address":"109 E Garden St",
    "sg:city":"Pensacola",
    "sg:classifiers":[
        {
            "category":"Professional",
            "subcategory":"Business Services",
            "type":"Services"
        }
    ],
    "sg:phone":"+1 850 436 7638",
    "sg:postcode":"32502",
    "sg:province":"FL",
    "wof:name":"Pensacola Mardi Gras",
    "wof:placetype":"venue"
},
  "geometry": {"coordinates":[-87.21310099999999,30.413142],"type":"Point"}
}