{
  "type": "Feature",
  "properties": {
    "iso:country":"US",
    "sg:address":"37 Marjorie Trl",
    "sg:city":"Ormond Beach",
    "sg:classifiers":[
        {
            "category":"Building & Trades",
            "subcategory":"Construction",
            "type":"Services"
        }
    ],
    "sg:phone":"+1 386 672 3953",
    "sg:postcode":"32174",
    "sg:province":"FL",
    "sg:tags":[
        "contractor"
    ],
    "wof:name":"DAntonio Masonry & Pressure",
    "wof:placetype":"venue"
},
  "geometry": {"coordinates":[-81.091391,29.28163],"type":"Point"}
}