{
  "type": "Feature",
  "properties": {
    "iso:country":"US",
    "sg:address":"900 Ocean Dr",
    "sg:city":"Miami Beach",
    "sg:classifiers":[
        {
            "category":"Building & Trades",
            "subcategory":"Locksmith",
            "type":"Services"
        }
    ],
    "sg:phone":"+1 786 228 5457",
    "sg:postcode":"33139",
    "sg:province":"FL",
    "sg:tags":[
        "key"
    ],
    "wof:name":"Anytime Emergency Locksmith On Ocean Dr",
    "wof:placetype":"venue"
},
  "geometry": {"coordinates":[-80.13073300000001,25.77939],"type":"Point"}
}