{
  "type": "Feature",
  "properties": {
    "iso:country":"US",
    "sg:address":"1000 Brickell Ave Ste 210",
    "sg:city":"Miami",
    "sg:classifiers":[
        {
            "category":"Communications",
            "type":"Services"
        }
    ],
    "sg:phone":"+1 305 938 1001",
    "sg:postcode":"33131",
    "sg:province":"FL",
    "sg:tags":[
        "consultant",
        "telecommunication"
    ],
    "sg:website":"http://www.merlin.com",
    "wof:name":"Merlin Telecom",
    "wof:placetype":"venue"
},
  "geometry": {"coordinates":[-80.191422,25.763741],"type":"Point"}
}