{
  "type": "Feature",
  "properties": {
    "addr:full":"16804 SW 81st Ct Miami FL 33157",
    "addr:housenumber":"16804",
    "addr:postcode":"33157",
    "addr:street":"Sw 81St Ct",
    "iso:country":"US",
    "sg:address":"16804 SW 81st Ct",
    "sg:city":"Miami",
    "sg:classifiers":[
        {
            "category":"Food & Beverages",
            "subcategory":"Candy",
            "type":"Retail Goods"
        }
    ],
    "sg:phone":"+1 305 235 6011",
    "sg:postcode":"33157",
    "sg:province":"FL",
    "wof:name":"Iftah Mashav",
    "wof:placetype":"venue"
},
  "geometry": {"coordinates":[-80.32402,25.6135],"type":"Point"}
}