{
  "type": "Feature",
  "properties": {
    "iso:country":"US",
    "sg:address":"602 SE 16th Pl",
    "sg:city":"Cape Coral",
    "sg:classifiers":[
        {
            "category":"Health Services",
            "subcategory":"Doctor",
            "type":"Services"
        }
    ],
    "sg:phone":"+1 239 573 7222",
    "sg:postcode":"33990",
    "sg:province":"FL",
    "wof:name":"Complete Women's Care",
    "wof:placetype":"venue"
},
  "geometry": {"coordinates":[-81.939972,26.641336],"type":"Point"}
}