{
  "type": "Feature",
  "properties": {
    "addr:full":"10350 Fisher Ave Tampa FL 33619",
    "addr:housenumber":"10350",
    "addr:postcode":"33619",
    "addr:street":"Fisher Ave",
    "iso:country":"US",
    "sg:address":"10350 Fisher Ave",
    "sg:city":"Tampa",
    "sg:classifiers":[
        {
            "category":"Wholesale",
            "subcategory":"Hardware",
            "type":"Manufacturing & Wholesale Goods"
        }
    ],
    "sg:phone":"+1 813 681 5502",
    "sg:postcode":"33619",
    "sg:province":"FL",
    "sg:tags":[
        "seal"
    ],
    "sg:website":"www.flaseal.com",
    "wof:name":"Florida Seal & Rubber Co",
    "wof:placetype":"venue"
},
  "geometry": {"coordinates":[-82.330043,27.958528],"type":"Point"}
}