{
  "type": "Feature",
  "properties": {
    "iso:country":"US",
    "sg:address":"1000 E Altamonte Dr",
    "sg:city":"Altamonte Springs",
    "sg:classifiers":[
        {
            "category":"Autos & Motor Vehicles",
            "subcategory":"Fuel & Gas Station",
            "type":"Retail Goods"
        }
    ],
    "sg:phone":"+1 407 339 1604",
    "sg:postcode":"32701",
    "sg:province":"FL",
    "sg:tags":[
        "station",
        "gasoline"
    ],
    "wof:name":"Gate Petroleum Company",
    "wof:placetype":"venue"
},
  "geometry": {"coordinates":[-81.359601,28.663164],"type":"Point"}
}