{
  "type": "Feature",
  "properties": {
    "addr:full":"1310 NE 133rd St Miami FL 33161",
    "addr:housenumber":"1310",
    "addr:postcode":"33161",
    "addr:street":"Ne 133Rd St",
    "iso:country":"US",
    "sg:address":"1310 NE 133rd St",
    "sg:city":"Miami",
    "sg:classifiers":[
        {
            "category":"Food & Beverages",
            "subcategory":"Specialty",
            "type":"Retail Goods"
        }
    ],
    "sg:phone":"+1 305 895 0725",
    "sg:postcode":"33161",
    "sg:province":"FL",
    "sg:tags":[
        "gourmet"
    ],
    "wof:name":"Marlas Edibles",
    "wof:placetype":"venue"
},
  "geometry": {"coordinates":[-80.170851,25.898165],"type":"Point"}
}