{
  "type": "Feature",
  "properties": {
    "iso:country":"US",
    "sg:address":"515 N Dixie Fwy",
    "sg:city":"New Smyrna Beach",
    "sg:classifiers":[
        {
            "category":"Restaurant",
            "type":"Food & Drink"
        }
    ],
    "sg:menulink":"http://www.allmenus.com/fl/new-smyrna-beach/89434-pepinos/menu/",
    "sg:phone":"+1 386 409 8884",
    "sg:postcode":"32168",
    "sg:province":"FL",
    "sg:tags":[
        "mexican"
    ],
    "wof:name":"Pepinos",
    "wof:placetype":"venue"
},
  "geometry": {"coordinates":[-80.92825000000001,29.028762],"type":"Point"}
}