{
  "type": "Feature",
  "properties": {
    "iso:country":"US",
    "sg:address":"6943 Jarvis Rd",
    "sg:city":"Sarasota",
    "sg:classifiers":[
        {
            "category":"Shopping",
            "subcategory":"Pets & Pet Supplies",
            "type":"Retail Goods"
        },
        {
            "category":"Retail",
            "subcategory":"Veterinary Services",
            "type":"Services"
        }
    ],
    "sg:phone":"+1 941 342 6545",
    "sg:postcode":"34241",
    "sg:province":"FL",
    "sg:tags":[
        "specialty"
    ],
    "wof:name":"Paws 4 Praise",
    "wof:placetype":"venue"
},
  "geometry": {"coordinates":[-82.432711,27.291792],"type":"Point"}
}