{
  "type": "Feature",
  "properties": {
    "iso:country":"US",
    "sg:address":"8294 NW 64th St",
    "sg:city":"Miami",
    "sg:classifiers":[
        {
            "category":"Retail",
            "subcategory":"Auto Repair",
            "type":"Services"
        }
    ],
    "sg:phone":"+1 305 639 1979",
    "sg:postcode":"33166",
    "sg:province":"FL",
    "wof:name":"Total Precision Overhaul",
    "wof:placetype":"venue"
},
  "geometry": {"coordinates":[-80.33185,25.831645],"type":"Point"}
}