{
  "type": "Feature",
  "properties": {
    "addr:full":"142 Eglin Pkwy S Fort Walton Bch FL 32548",
    "addr:housenumber":"142",
    "addr:postcode":"32548",
    "addr:street":"Eglin Pkwy S",
    "iso:country":"US",
    "sg:address":"142 Eglin Pkwy S",
    "sg:city":"Fort Walton Bch",
    "sg:classifiers":[
        {
            "category":"Professional",
            "subcategory":"Lawyer & Legal Services",
            "type":"Services"
        }
    ],
    "sg:phone":"+1 850 244 5678",
    "sg:postcode":"32548",
    "sg:province":"FL",
    "sg:tags":[
        "attorney"
    ],
    "wof:name":"Walter A Steigleman Attorneys",
    "wof:placetype":"venue"
},
  "geometry": {"coordinates":[-86.60644499999999,30.405391],"type":"Point"}
}