{
  "type": "Feature",
  "properties": {
    "iso:country":"US",
    "sg:address":"6315 Westgate Dr",
    "sg:city":"Orlando",
    "sg:classifiers":[
        {
            "category":"Real Estate",
            "subcategory":"Real Estate Operator",
            "type":"Services"
        }
    ],
    "sg:phone":"+1 407 295 1511",
    "sg:postcode":"32835",
    "sg:province":"FL",
    "sg:tags":[
        "apartment"
    ],
    "wof:name":"Marina Landing Apartments",
    "wof:placetype":"venue"
},
  "geometry": {"coordinates":[-81.467647,28.528669],"type":"Point"}
}