{
  "type": "Feature",
  "properties": {
    "addr:full":"218 Lighthouse Cir Fernandina Beach FL 32034",
    "addr:housenumber":"218",
    "addr:postcode":"32034",
    "addr:street":"Lighthouse Cir",
    "iso:country":"US",
    "sg:address":"218 Lighthouse Cir",
    "sg:city":"Fernandina Beach",
    "sg:classifiers":[
        {
            "category":"Professional",
            "subcategory":"Management & Consulting",
            "type":"Services"
        }
    ],
    "sg:phone":"+1 904 261 4188",
    "sg:postcode":"32034",
    "sg:province":"FL",
    "sg:tags":[
        "public",
        "relations"
    ],
    "wof:name":"Coulter Beal & Company CPA",
    "wof:placetype":"venue"
},
  "geometry": {"coordinates":[-81.443388,30.671607],"type":"Point"}
}