{
  "type": "Feature",
  "properties": {
    "addr:full":"2030 N Seacrest Blvd Boynton Beach FL 33435",
    "addr:housenumber":"2030",
    "addr:postcode":"33435",
    "addr:street":"N Seacrest Blvd",
    "iso:country":"US",
    "sg:address":"2030 N Seacrest Blvd",
    "sg:city":"Boynton Beach",
    "sg:classifiers":[
        {
            "category":"Building & Trades",
            "subcategory":"Construction",
            "type":"Services"
        }
    ],
    "sg:phone":"+1 561 736 4400",
    "sg:postcode":"33435",
    "sg:province":"FL",
    "sg:tags":[
        "painter"
    ],
    "wof:name":"Son Dee's Decor Painting",
    "wof:placetype":"venue"
},
  "geometry": {"coordinates":[-80.06735,26.548734],"type":"Point"}
}