{
  "type": "Feature",
  "properties": {
    "addr:full":"4811 Lyons Rd Coconut Creek FL 33073",
    "addr:housenumber":"4811",
    "addr:postcode":"33073",
    "addr:street":"Lyons Rd",
    "iso:country":"US",
    "sg:address":"4811 Lyons Rd",
    "sg:city":"Coconut Creek",
    "sg:classifiers":[
        {
            "category":"Real Estate",
            "subcategory":"Real Estate Agent",
            "type":"Services"
        }
    ],
    "sg:phone":"+1 954 419 9797",
    "sg:postcode":"33073",
    "sg:province":"FL",
    "wof:name":"Butters Real Estate Fund",
    "wof:placetype":"venue"
},
  "geometry": {"coordinates":[-80.186632,26.293386],"type":"Point"}
}