{
  "type": "Feature",
  "properties": {
    "iso:country":"US",
    "sg:address":"549 E International Speedway Blvd",
    "sg:city":"Deland",
    "sg:classifiers":[
        {
            "category":"Restaurant",
            "type":"Food & Drink"
        }
    ],
    "sg:phone":"+1 386 738 4803",
    "sg:postcode":"32724",
    "sg:province":"FL",
    "sg:tags":[
        "irish"
    ],
    "wof:name":"Molly Malon's Irish Pub & Eatery",
    "wof:placetype":"venue"
},
  "geometry": {"coordinates":[-81.295413,29.055141],"type":"Point"}
}