{
  "type": "Feature",
  "properties": {
    "iso:country":"US",
    "sg:address":"1090 27th Ave",
    "sg:city":"Vero Beach",
    "sg:classifiers":[
        {
            "category":"Building & Trades",
            "subcategory":"Landscaping Services",
            "type":"Services"
        }
    ],
    "sg:phone":"+1 772 770 4830",
    "sg:postcode":"32960",
    "sg:province":"FL",
    "wof:name":"Johns Lawn Service",
    "wof:placetype":"venue"
},
  "geometry": {"coordinates":[-80.413765,27.622801],"type":"Point"}
}