{
  "type": "Feature",
  "properties": {
    "addr:full":"482 Deen Blvd Lake Placid FL 33852",
    "addr:housenumber":"482",
    "addr:postcode":"33852",
    "addr:street":"Deen Blvd",
    "iso:country":"US",
    "sg:address":"482 Deen Blvd",
    "sg:city":"Lake Placid",
    "sg:classifiers":[
        {
            "category":"Home & Garden",
            "subcategory":"Garden Supply",
            "type":"Retail Goods"
        }
    ],
    "sg:phone":"+1 863 465 2618",
    "sg:postcode":"33852",
    "sg:province":"FL",
    "sg:tags":[
        "nurseryman"
    ],
    "wof:name":"Ibanez Lawn & Gardens",
    "wof:placetype":"venue"
},
  "geometry": {"coordinates":[-81.3716,27.297277],"type":"Point"}
}