{
  "type": "Feature",
  "properties": {
    "iso:country":"US",
    "sg:address":"3271 NW 171st Ter",
    "sg:city":"Opa Locka",
    "sg:classifiers":[
        {
            "category":"Building & Trades",
            "subcategory":"Construction",
            "type":"Services"
        }
    ],
    "sg:phone":"+1 305 624 5404",
    "sg:postcode":"33056",
    "sg:province":"FL",
    "sg:tags":[
        "contractor"
    ],
    "wof:name":"A&A Pools & Patio Inc",
    "wof:placetype":"venue"
},
  "geometry": {"coordinates":[-80.255433,25.930415],"type":"Point"}
}