{
  "type": "Feature",
  "properties": {
    "addr:full":"19275 Biscayne Blvd Ste 50 Miami FL 33180",
    "addr:housenumber":"19275",
    "addr:postcode":"33180",
    "addr:street":"Biscayne Blvd Ste 50",
    "iso:country":"US",
    "sg:address":"19275 Biscayne Blvd Ste 50",
    "sg:city":"Miami",
    "sg:classifiers":[
        {
            "category":"Shopping",
            "subcategory":"Jewelry",
            "type":"Retail Goods"
        }
    ],
    "sg:phone":"+1 305 682 0100",
    "sg:postcode":"33180",
    "sg:province":"FL",
    "wof:name":"Maria's Jewelry",
    "wof:placetype":"venue"
},
  "geometry": {"coordinates":[-80.146613,25.953633],"type":"Point"}
}