{
  "type": "Feature",
  "properties": {
    "iso:country":"US",
    "sg:address":"8833 NW 33rd St",
    "sg:city":"Pompano Beach",
    "sg:classifiers":[
        {
            "category":"Shopping",
            "subcategory":"Beauty & Cosmetics",
            "type":"Retail Goods"
        }
    ],
    "sg:phone":"+1 954 753 0999",
    "sg:postcode":"33065",
    "sg:province":"FL",
    "sg:tags":[
        "shop",
        "merchandise"
    ],
    "wof:name":"Jafra Cosmetics Ann Fetters",
    "wof:placetype":"venue"
},
  "geometry": {"coordinates":[-80.242802,26.271383],"type":"Point"}
}