{
  "type": "Feature",
  "properties": {
    "iso:country":"US",
    "sg:address":"2935 W Oak Ridge Rd",
    "sg:city":"Orlando",
    "sg:classifiers":[
        {
            "category":"Food & Beverages",
            "subcategory":"Groceries & Convenience Stores",
            "type":"Retail Goods"
        }
    ],
    "sg:phone":"+1 407 888 4454",
    "sg:postcode":"32809",
    "sg:province":"FL",
    "sg:tags":[
        "grocer",
        "super",
        "supermarket"
    ],
    "wof:name":"Mi Bandera Supermarket",
    "wof:placetype":"venue"
},
  "geometry": {"coordinates":[-81.41555200000001,28.472375],"type":"Point"}
}