{
  "type": "Feature",
  "properties": {
    "addr:full":"1897 Drew St Clearwater FL 33765",
    "addr:housenumber":"1897",
    "addr:postcode":"33765",
    "addr:street":"Drew St",
    "iso:country":"US",
    "sg:address":"1897 Drew St",
    "sg:city":"Clearwater",
    "sg:classifiers":[
        {
            "category":"Home & Garden",
            "subcategory":"Home Furnishings",
            "type":"Retail Goods"
        }
    ],
    "sg:phone":"+1 727 442 4703",
    "sg:postcode":"33765",
    "sg:province":"FL",
    "wof:name":"Gulf Coast Interiors",
    "wof:placetype":"venue"
},
  "geometry": {"coordinates":[-82.75969600000001,27.967902],"type":"Point"}
}