{
  "type": "Feature",
  "properties": {
    "addr:full":"5728 Major Blvd Orlando FL 32819",
    "addr:housenumber":"5728",
    "addr:postcode":"32819",
    "addr:street":"Major Blvd",
    "iso:country":"US",
    "sg:address":"5728 Major Blvd",
    "sg:city":"Orlando",
    "sg:classifiers":[
        {
            "category":"Professional",
            "subcategory":"Accounting & Tax Preparation",
            "type":"Services"
        }
    ],
    "sg:phone":"+1 407 354 0303",
    "sg:postcode":"32819",
    "sg:province":"FL",
    "sg:tags":[
        "bookkeeping",
        "general"
    ],
    "wof:name":"Century Small Business Sltns",
    "wof:placetype":"venue"
},
  "geometry": {"coordinates":[-81.45872300000001,28.477935],"type":"Point"}
}