{
  "type": "Feature",
  "properties": {
    "iso:country":"US",
    "sg:address":"1000 NW 40 Dr",
    "sg:city":"Gainesville",
    "sg:classifiers":[
        {
            "category":"Manufacturing",
            "subcategory":"Lumber",
            "type":"Manufacturing & Wholesale Goods"
        }
    ],
    "sg:phone":"+1 352 375 0793",
    "sg:postcode":"32605",
    "sg:province":"FL",
    "sg:tags":[
        "product",
        "forest",
        "gathering"
    ],
    "wof:name":"Plant Genie",
    "wof:placetype":"venue"
},
  "geometry": {"coordinates":[-82.38650699999999,29.663234],"type":"Point"}
}