{
  "type": "Feature",
  "properties": {
    "iso:country":"US",
    "sg:address":"2251 Catbriar Way",
    "sg:city":"Oviedo",
    "sg:classifiers":[
        {
            "category":"Health Services",
            "subcategory":"Clinic",
            "type":"Services"
        }
    ],
    "sg:phone":"+1 407 977 3169",
    "sg:postcode":"32765",
    "sg:province":"FL",
    "wof:name":"Specialty Allocations",
    "wof:placetype":"venue"
},
  "geometry": {"coordinates":[-81.24726699999999,28.659233],"type":"Point"}
}