{
  "type": "Feature",
  "properties": {
    "iso:country":"US",
    "sg:address":"86 N Broadway St",
    "sg:city":"Fellsmere",
    "sg:classifiers":[
        {
            "category":"Home & Garden",
            "subcategory":"Building Materials",
            "type":"Retail Goods"
        },
        {
            "category":"Shopping",
            "subcategory":"Pets & Pet Supplies",
            "type":"Retail Goods"
        },
        {
            "category":"Building & Trades",
            "subcategory":"Construction",
            "type":"Services"
        },
        {
            "category":"Utilities",
            "subcategory":"Natural Gas",
            "type":"Services"
        }
    ],
    "sg:phone":"+1 772 571 8199",
    "sg:postcode":"32948",
    "sg:province":"FL",
    "sg:tags":[
        "feed",
        "fence",
        "propane",
        "supplement",
        "contractor",
        "concentrate",
        "fence-sales"
    ],
    "wof:name":"Fellsmere Feed Tack & Farm Supply",
    "wof:placetype":"venue"
},
  "geometry": {"coordinates":[-80.601204,27.770996],"type":"Point"}
}