{
  "type": "Feature",
  "properties": {
    "iso:country":"US",
    "sg:address":"9247 Airport Blvd",
    "sg:city":"Orlando",
    "sg:classifiers":[
        {
            "category":"Airline",
            "type":"Transportation"
        }
    ],
    "sg:phone":"+1 407 825 4271",
    "sg:postcode":"32827",
    "sg:province":"FL",
    "sg:tags":[
        "scheduled",
        "air"
    ],
    "wof:name":"Continental Airlines",
    "wof:placetype":"venue"
},
  "geometry": {"coordinates":[-81.305099,28.429872],"type":"Point"}
}