{
  "type": "Feature",
  "properties": {
    "addr:full":"552 W 41st Pl Hialeah FL 33012",
    "addr:housenumber":"552",
    "addr:postcode":"33012",
    "addr:street":"W 41St Pl",
    "iso:country":"US",
    "sg:address":"552 W 41st Pl",
    "sg:city":"Hialeah",
    "sg:classifiers":[
        {
            "category":"Wholesale",
            "subcategory":"Plants",
            "type":"Manufacturing & Wholesale Goods"
        }
    ],
    "sg:phone":"+1 305 819 6551",
    "sg:postcode":"33012",
    "sg:province":"FL",
    "sg:tags":[
        "flower"
    ],
    "wof:name":"S Medina Wholesale",
    "wof:placetype":"venue"
},
  "geometry": {"coordinates":[-80.294178,25.859265],"type":"Point"}
}