{
  "type": "Feature",
  "properties": {
    "iso:country":"US",
    "sg:address":"201 E Horton Ave",
    "sg:city":"Englewood",
    "sg:classifiers":[
        {
            "category":"Real Estate",
            "subcategory":"Real Estate Operator",
            "type":"Services"
        }
    ],
    "sg:phone":"+1 941 474 3856",
    "sg:postcode":"34223",
    "sg:province":"FL",
    "sg:tags":[
        "mobile",
        "manufactured",
        "housing-communities",
        "site",
        "home"
    ],
    "wof:name":"Deer Creek Mobile Home Park",
    "wof:placetype":"venue"
},
  "geometry": {"coordinates":[-82.349243,26.947689],"type":"Point"}
}