{
  "type": "Feature",
  "properties": {
    "iso:country":"US",
    "sg:address":"10005 N Okeechobee Rd",
    "sg:city":"Hialeah",
    "sg:classifiers":[
        {
            "category":"Banks & Credit Unions",
            "subcategory":"Investment Brokerage",
            "type":"Services"
        }
    ],
    "sg:phone":"+1 305 362 9061",
    "sg:postcode":"33016",
    "sg:province":"FL",
    "sg:tags":[
        "security"
    ],
    "wof:name":"Chavianos Brokers Inc",
    "wof:placetype":"venue"
},
  "geometry": {"coordinates":[-80.33908700000001,25.866584],"type":"Point"}
}