{
  "type": "Feature",
  "properties": {
    "iso:country":"US",
    "sg:address":"11601 SW 141st St",
    "sg:city":"Miami",
    "sg:classifiers":[
        {
            "category":"Shopping",
            "subcategory":"Crafts & Fabrics",
            "type":"Retail Goods"
        },
        {
            "category":"Wholesale",
            "subcategory":"Books, Periodicals, & Newspapers",
            "type":"Manufacturing & Wholesale Goods"
        }
    ],
    "sg:phone":"+1 305 233 8515",
    "sg:postcode":"33176",
    "sg:province":"FL",
    "sg:tags":[
        "canvas",
        "manufacturer",
        "canvas-wholesale"
    ],
    "wof:name":"Yah Yachts Canvas & Inter",
    "wof:placetype":"venue"
},
  "geometry": {"coordinates":[-80.381552,25.63741],"type":"Point"}
}