{
  "type": "Feature",
  "properties": {
    "iso:country":"US",
    "sg:address":"276 Briarwood Ln",
    "sg:city":"Ponte Vedra Bch",
    "sg:classifiers":[
        {
            "category":"Professional",
            "subcategory":"Management & Consulting",
            "type":"Services"
        }
    ],
    "sg:phone":"+1 904 280 5777",
    "sg:postcode":"32082",
    "sg:province":"FL",
    "sg:tags":[
        "consultant"
    ],
    "wof:name":"Greenbean Corporate Organzing",
    "wof:placetype":"venue"
},
  "geometry": {"coordinates":[-81.387294,30.252306],"type":"Point"}
}