{
  "type": "Feature",
  "properties": {
    "iso:country":"US",
    "sg:address":"13 St Johns Medical Park Dr",
    "sg:city":"Saint Augustine",
    "sg:classifiers":[
        {
            "category":"Health Services",
            "subcategory":"Doctor",
            "type":"Services"
        }
    ],
    "sg:phone":"+1 904 797 4064",
    "sg:postcode":"32086",
    "sg:province":"FL",
    "wof:name":"Stephen J Fortus DDS Inc",
    "wof:placetype":"venue"
},
  "geometry": {"coordinates":[-81.326114,29.837713],"type":"Point"}
}