{
  "type": "Feature",
  "properties": {
    "iso:country":"US",
    "sg:address":"590 Prineville St",
    "sg:city":"Port Charlotte",
    "sg:classifiers":[
        {
            "category":"Home & Garden",
            "subcategory":"Garden Supply",
            "type":"Retail Goods"
        }
    ],
    "sg:phone":"+1 941 629 6665",
    "sg:postcode":"33954",
    "sg:province":"FL",
    "sg:tags":[
        "landscape"
    ],
    "wof:name":"Murdock Stones Etc",
    "wof:placetype":"venue"
},
  "geometry": {"coordinates":[-82.13996400000001,27.018049],"type":"Point"}
}