{
  "type": "Feature",
  "properties": {
    "iso:country":"US",
    "sg:address":"3700 W 18th Ave",
    "sg:city":"Hialeah",
    "sg:classifiers":[
        {
            "category":"Professional",
            "subcategory":"Management & Consulting",
            "type":"Services"
        }
    ],
    "sg:phone":"+1 305 822 8885",
    "sg:postcode":"33012",
    "sg:province":"FL",
    "wof:name":"Vinnell Corporation",
    "wof:placetype":"venue"
},
  "geometry": {"coordinates":[-80.31857599999999,25.856714],"type":"Point"}
}