{
  "type": "Feature",
  "properties": {
    "iso:country":"US",
    "sg:address":"3640 Anderson Ave",
    "sg:city":"Tampa",
    "sg:classifiers":[
        {
            "category":"Real Estate",
            "subcategory":"Real Estate Agent",
            "type":"Services"
        }
    ],
    "sg:phone":"+1 813 839 1563",
    "sg:postcode":"33611",
    "sg:province":"FL",
    "wof:name":"Gambrell Properties",
    "wof:placetype":"venue"
},
  "geometry": {"coordinates":[-82.504285,27.872786],"type":"Point"}
}