{
  "type": "Feature",
  "properties": {
    "iso:country":"US",
    "sg:address":"11757 SW 24th Ter",
    "sg:city":"Miami",
    "sg:classifiers":[
        {
            "category":"Retail",
            "subcategory":"Storage",
            "type":"Services"
        }
    ],
    "sg:phone":"+1 305 480 5705",
    "sg:postcode":"33175",
    "sg:province":"FL",
    "sg:tags":[
        "shop",
        "rock"
    ],
    "wof:name":"Rock Body Fitness Inc",
    "wof:placetype":"venue"
},
  "geometry": {"coordinates":[-80.386612,25.745652],"type":"Point"}
}