{
  "type": "Feature",
  "properties": {
    "iso:country":"US",
    "sg:address":"1601 E 4th Ave",
    "sg:city":"Hialeah",
    "sg:classifiers":[
        {
            "category":"Banks & Credit Unions",
            "subcategory":"Bank",
            "type":"Services"
        }
    ],
    "sg:phone":"+1 305 887 5131",
    "sg:postcode":"33010",
    "sg:province":"FL",
    "wof:name":"Merchantil Cb",
    "wof:placetype":"venue"
},
  "geometry": {"coordinates":[-80.273668,25.836538],"type":"Point"}
}