{
  "type": "Feature",
  "properties": {
    "addr:full":"2130 Fillmore St Hollywood FL 33020",
    "addr:housenumber":"2130",
    "addr:postcode":"33020",
    "addr:street":"Fillmore St",
    "iso:country":"US",
    "sg:address":"2130 Fillmore St",
    "sg:city":"Hollywood",
    "sg:classifiers":[
        {
            "category":"Retail",
            "subcategory":"Auto Repair",
            "type":"Services"
        }
    ],
    "sg:phone":"+1 954 921 8200",
    "sg:postcode":"33020",
    "sg:province":"FL",
    "sg:tags":[
        "repairing",
        "automotive",
        "general",
        "automobile"
    ],
    "wof:name":"Taltech Automotive Inc",
    "wof:placetype":"venue"
},
  "geometry": {"coordinates":[-80.15412600000001,26.014882],"type":"Point"}
}