{
  "type": "Feature",
  "properties": {
    "iso:country":"US",
    "sg:address":"3331 Longhorn Trl",
    "sg:city":"Deland",
    "sg:classifiers":[
        {
            "category":"Real Estate",
            "subcategory":"Architect",
            "type":"Services"
        }
    ],
    "sg:phone":"+1 386 943 9498",
    "sg:postcode":"32724",
    "sg:province":"FL",
    "sg:tags":[
        "architects'",
        "specification",
        "construction",
        "builders'",
        "architectural"
    ],
    "wof:name":"International Roof Consulting Services",
    "wof:placetype":"venue"
},
  "geometry": {"coordinates":[-81.31342600000001,29.090434],"type":"Point"}
}