{
  "type": "Feature",
  "properties": {
    "iso:country":"US",
    "sg:address":"5387 Colbright Rd",
    "sg:city":"Lake Worth",
    "sg:classifiers":[
        {
            "category":"Building & Trades",
            "subcategory":"Construction",
            "type":"Services"
        }
    ],
    "sg:phone":"+1 561 968 8218",
    "sg:postcode":"33467",
    "sg:province":"FL",
    "sg:tags":[
        "carpentry",
        "contractor"
    ],
    "wof:name":"Charles Stout Carpentry",
    "wof:placetype":"venue"
},
  "geometry": {"coordinates":[-80.160841,26.601978],"type":"Point"}
}