{
  "type": "Feature",
  "properties": {
    "iso:country":"US",
    "sg:address":"1520 NW 68th Ter",
    "sg:city":"Miami",
    "sg:classifiers":[
        {
            "category":"Social Services",
            "subcategory":"Child Care",
            "type":"Services"
        }
    ],
    "sg:phone":"+1 786 318 3444",
    "sg:postcode":"33147",
    "sg:province":"FL",
    "wof:name":"Houston's Daycare",
    "wof:placetype":"venue"
},
  "geometry": {"coordinates":[-80.224951,25.836536],"type":"Point"}
}