{
  "type": "Feature",
  "properties": {
    "iso:country":"US",
    "sg:address":"912 S Andrews Ave",
    "sg:city":"Fort Lauderdale",
    "sg:classifiers":[
        {
            "category":"Insurance",
            "subcategory":"Hazard Insurance",
            "type":"Services"
        }
    ],
    "sg:phone":"+1 954 462 1421",
    "sg:postcode":"33316",
    "sg:province":"FL",
    "sg:tags":[
        "bond"
    ],
    "wof:name":"A A American Bonding Agency",
    "wof:placetype":"venue"
},
  "geometry": {"coordinates":[-80.14297500000001,26.11054],"type":"Point"}
}