{
  "type": "Feature",
  "properties": {
    "iso:country":"US",
    "sg:address":"1005 8th Ave N",
    "sg:city":"Jacksonville Beach",
    "sg:classifiers":[
        {
            "category":"Building & Trades",
            "subcategory":"Construction",
            "type":"Services"
        }
    ],
    "sg:phone":"+1 904 241 7838",
    "sg:postcode":"32250",
    "sg:province":"FL",
    "sg:tags":[
        "house"
    ],
    "wof:name":"Steve Bowman Construction",
    "wof:placetype":"venue"
},
  "geometry": {"coordinates":[-81.401904,30.295339],"type":"Point"}
}