{
  "type": "Feature",
  "properties": {
    "addr:full":"5093 Okaloosa Ln Crestview FL 32539",
    "addr:postcode":"5093;32539",
    "addr:street":"Okaloosa Ln",
    "iso:country":"US",
    "sg:address":"5093 Okaloosa Ln",
    "sg:city":"Crestview",
    "sg:classifiers":[
        {
            "category":"Real Estate",
            "subcategory":"Real Estate Agent",
            "type":"Services"
        }
    ],
    "sg:phone":"+1 850 682 5761",
    "sg:postcode":"32539",
    "sg:province":"FL",
    "wof:name":"Choice Realty",
    "wof:placetype":"venue"
},
  "geometry": {"coordinates":[-86.534531,30.754534],"type":"Point"}
}