{
  "type": "Feature",
  "properties": {
    "addr:full":"1737 Sherwood St Clearwater FL 33755",
    "addr:housenumber":"1737",
    "addr:postcode":"33755",
    "addr:street":"Sherwood St",
    "iso:country":"US",
    "sg:address":"1737 Sherwood St",
    "sg:city":"Clearwater",
    "sg:classifiers":[
        {
            "category":"Restaurant",
            "type":"Food & Drink"
        }
    ],
    "sg:phone":"+1 727 445 1575",
    "sg:postcode":"33755",
    "sg:province":"FL",
    "sg:tags":[
        "eating"
    ],
    "wof:name":"Kitchen Magician",
    "wof:placetype":"venue"
},
  "geometry": {"coordinates":[-82.765468,27.980462],"type":"Point"}
}