{
  "type": "Feature",
  "properties": {
    "iso:country":"US",
    "sg:address":"2100 Jenkins Rd",
    "sg:city":"Mulberry",
    "sg:classifiers":[
        {
            "category":"Freight",
            "type":"Transportation"
        }
    ],
    "sg:phone":"+1 863 425 4171",
    "sg:postcode":"33860",
    "sg:province":"FL",
    "sg:tags":[
        "mining",
        "weld",
        "for",
        "industry",
        "move",
        "pipe"
    ],
    "wof:name":"OCain Phillip P Sr",
    "wof:placetype":"venue"
},
  "geometry": {"coordinates":[-81.990955,27.894907],"type":"Point"}
}