{
  "type": "Feature",
  "properties": {
    "addr:full":"3646 NW 48th Ter Miami FL 33142",
    "addr:housenumber":"3646",
    "addr:postcode":"33142",
    "addr:street":"Nw 48Th Ter",
    "iso:country":"US",
    "sg:address":"3646 NW 48th Ter",
    "sg:city":"Miami",
    "sg:classifiers":[
        {
            "category":"Retail",
            "subcategory":"Repair Shop",
            "type":"Services"
        }
    ],
    "sg:phone":"+1 305 638 4844",
    "sg:postcode":"33142",
    "sg:province":"FL",
    "sg:tags":[
        "machine",
        "equipment",
        "baker"
    ],
    "wof:name":"Padron Machine Shop",
    "wof:placetype":"venue"
},
  "geometry": {"coordinates":[-80.255866,25.818252],"type":"Point"}
}