{
  "type": "Feature",
  "properties": {
    "iso:country":"US",
    "sg:address":"5220 Pine Island Rd",
    "sg:city":"Bokeelia",
    "sg:classifiers":[
        {
            "category":"Home & Garden",
            "subcategory":"Building Materials",
            "type":"Retail Goods"
        }
    ],
    "sg:phone":"+1 239 283 4435",
    "sg:postcode":"33922",
    "sg:province":"FL",
    "sg:tags":[
        "glass",
        "window",
        "plate"
    ],
    "wof:name":"Pine Island Glass Inc",
    "wof:placetype":"venue"
},
  "geometry": {"coordinates":[-82.113384,26.613819],"type":"Point"}
}