{
  "type": "Feature",
  "properties": {
    "addr:full":"1657 Lake Baldwin Ln Orlando FL 32814",
    "addr:housenumber":"1657",
    "addr:postcode":"32814",
    "addr:street":"Lake Baldwin Ln",
    "iso:country":"US",
    "sg:address":"1657 Lake Baldwin Ln",
    "sg:city":"Orlando",
    "sg:classifiers":[
        {
            "category":"Insurance",
            "subcategory":"Insurance Agent",
            "type":"Services"
        },
        {
            "category":"Insurance",
            "subcategory":"Hazard Insurance",
            "type":"Services"
        },
        {
            "category":"Insurance",
            "subcategory":"Title Insurance",
            "type":"Services"
        }
    ],
    "sg:phone":"+1 407 745 0444",
    "sg:postcode":"32814",
    "sg:province":"FL",
    "sg:tags":[
        "auto",
        "renter",
        "homeowner"
    ],
    "sg:website":"http://www.agiinsurance.net",
    "wof:name":"AGI AllState",
    "wof:placetype":"venue"
},
  "geometry": {"coordinates":[-81.323678,28.567679],"type":"Point"}
}