{
  "type": "Feature",
  "properties": {
    "addr:full":"20264 Old Cutler Rd Miami FL 33189",
    "addr:housenumber":"20264",
    "addr:postcode":"33189",
    "addr:street":"Old Cutler Rd",
    "iso:country":"US",
    "sg:address":"20264 Old Cutler Rd",
    "sg:city":"Miami",
    "sg:classifiers":[
        {
            "category":"Shopping",
            "subcategory":"Bicycles & Sporting Goods",
            "type":"Retail Goods"
        }
    ],
    "sg:phone":"+1 305 233 0848",
    "sg:postcode":"33189",
    "sg:province":"FL",
    "sg:tags":[
        "bait",
        "fishing"
    ],
    "wof:name":"High Tailin It Inc",
    "wof:placetype":"venue"
},
  "geometry": {"coordinates":[-80.335072,25.578953],"type":"Point"}
}