{
  "type": "Feature",
  "properties": {
    "iso:country":"US",
    "sg:address":"4901 Erie Rd",
    "sg:city":"Parrish",
    "sg:phone":"+1 941 722 4212",
    "sg:postcode":"34219",
    "sg:province":"FL",
    "sg:tags":[
        "farm"
    ],
    "wof:name":"Sun Hing Farms Inc",
    "wof:placetype":"venue"
},
  "geometry": {"coordinates":[-82.47882300000001,27.55681],"type":"Point"}
}