{
  "type": "Feature",
  "properties": {
    "iso:country":"US",
    "sg:address":"2445 Pellicer Rd",
    "sg:city":"St Augustine",
    "sg:classifiers":[
        {
            "category":"Recreation",
            "type":"Entertainment"
        }
    ],
    "sg:phone":"+1 904 823 1128",
    "sg:postcode":"32092",
    "sg:province":"FL",
    "sg:tags":[
        "stable"
    ],
    "wof:name":"Grazing Pasture Stables & Tack",
    "wof:placetype":"venue"
},
  "geometry": {"coordinates":[-81.43456999999999,29.920892],"type":"Point"}
}