{
  "type": "Feature",
  "properties": {
    "iso:country":"US",
    "sg:address":"2501 NW 95th St",
    "sg:city":"Miami",
    "sg:classifiers":[
        {
            "category":"Organizations",
            "subcategory":"Religious Organization",
            "type":"Services"
        }
    ],
    "sg:phone":"+1 305 835 2114",
    "sg:postcode":"33147",
    "sg:province":"FL",
    "sg:tags":[
        "church"
    ],
    "wof:name":"Central Faith Mission Inc",
    "wof:placetype":"venue"
},
  "geometry": {"coordinates":[-80.241224,25.860743],"type":"Point"}
}