{
  "type": "Feature",
  "properties": {
    "addr:full":"821 Espanola Way Miami Beach FL 33139",
    "addr:housenumber":"821",
    "addr:postcode":"33139",
    "addr:street":"Espanola Way",
    "iso:country":"US",
    "sg:address":"821 Espanola Way",
    "sg:city":"Miami Beach",
    "sg:classifiers":[
        {
            "category":"Building & Trades",
            "subcategory":"Construction",
            "type":"Services"
        }
    ],
    "sg:phone":"+1 305 673 9167",
    "sg:postcode":"33139",
    "sg:province":"FL",
    "sg:tags":[
        "floor",
        "laying",
        "contractor"
    ],
    "wof:name":"Sequals Nel Mondo Inc",
    "wof:placetype":"venue"
},
  "geometry": {"coordinates":[-80.137303,25.786863],"type":"Point"}
}