{
  "type": "Feature",
  "properties": {
    "addr:full":"5745 S University Dr Davie FL 33328",
    "addr:housenumber":"5745",
    "addr:postcode":"33328",
    "addr:street":"S University Dr",
    "iso:country":"US",
    "sg:address":"5745 S University Dr",
    "sg:city":"Davie",
    "sg:classifiers":[
        {
            "category":"Real Estate",
            "subcategory":"Real Estate Services",
            "type":"Services"
        }
    ],
    "sg:phone":"+1 954 252 9678",
    "sg:postcode":"33328",
    "sg:province":"FL",
    "sg:tags":[
        "company",
        "title"
    ],
    "wof:name":"A C Title & Escrow Inc",
    "wof:placetype":"venue"
},
  "geometry": {"coordinates":[-80.25190499999999,26.055261],"type":"Point"}
}