{
  "type": "Feature",
  "properties": {
    "addr:full":"588 NW 113th Ter Coral Springs FL 33071",
    "addr:housenumber":"588",
    "addr:postcode":"33071",
    "addr:street":"Nw 113Th Ter",
    "iso:country":"US",
    "sg:address":"588 NW 113th Ter",
    "sg:city":"Coral Springs",
    "sg:classifiers":[
        {
            "category":"Wholesale",
            "subcategory":"Durable Goods & Equipment",
            "type":"Manufacturing & Wholesale Goods"
        }
    ],
    "sg:phone":"+1 954 255 5754",
    "sg:postcode":"33071",
    "sg:province":"FL",
    "sg:tags":[
        "exporter"
    ],
    "wof:name":"Cimpex USA Corp",
    "wof:placetype":"venue"
},
  "geometry": {"coordinates":[-80.277259,26.238958],"type":"Point"}
}