{
  "type": "Feature",
  "properties": {
    "iso:country":"US",
    "sg:address":"130 NW 24th St",
    "sg:city":"Miami",
    "sg:classifiers":[
        {
            "category":"Manufacturing",
            "subcategory":"Metals",
            "type":"Manufacturing & Wholesale Goods"
        }
    ],
    "sg:phone":"+1 305 576 6666",
    "sg:postcode":"33127",
    "sg:province":"FL",
    "sg:tags":[
        "metalwork",
        "architectural",
        "mfg"
    ],
    "wof:name":"Aa Diversified",
    "wof:placetype":"venue"
},
  "geometry": {"coordinates":[-80.196639,25.799837],"type":"Point"}
}