{
  "type": "Feature",
  "properties": {
    "addr:full":"1571 Long St Clearwater FL 33755",
    "addr:housenumber":"1571",
    "addr:postcode":"33755",
    "addr:street":"Long St",
    "iso:country":"US",
    "sg:address":"1571 Long St",
    "sg:city":"Clearwater",
    "sg:classifiers":[
        {
            "category":"Home & Garden",
            "subcategory":"Home Furnishings",
            "type":"Retail Goods"
        }
    ],
    "sg:phone":"+1 727 443 3971",
    "sg:postcode":"33755",
    "sg:province":"FL",
    "wof:name":"Lib-Rob",
    "wof:placetype":"venue"
},
  "geometry": {"coordinates":[-82.771463,27.978323],"type":"Point"}
}