{
  "type": "Feature",
  "properties": {
    "iso:country":"US",
    "sg:address":"3054 Wind Meadow Dr",
    "sg:city":"Gulf Breeze",
    "sg:classifiers":[
        {
            "category":"Building & Trades",
            "subcategory":"Cleaning & Sanitation",
            "type":"Services"
        }
    ],
    "sg:phone":"+1 850 916 0403",
    "sg:postcode":"32563",
    "sg:province":"FL",
    "sg:tags":[
        "maintenance"
    ],
    "wof:name":"Pyramid Cleaning",
    "wof:placetype":"venue"
},
  "geometry": {"coordinates":[-87.09696099999999,30.384171],"type":"Point"}
}