{
  "type": "Feature",
  "properties": {
    "addr:full":"2721 SW 137th Ave Miami FL 33175",
    "addr:housenumber":"2721",
    "addr:postcode":"33175",
    "addr:street":"Sw 137Th Ave",
    "iso:country":"US",
    "sg:address":"2721 SW 137th Ave",
    "sg:city":"Miami",
    "sg:classifiers":[
        {
            "category":"Real Estate",
            "subcategory":"Real Estate Agent",
            "type":"Services"
        }
    ],
    "sg:phone":"+1 305 223 4960",
    "sg:postcode":"33175",
    "sg:province":"FL",
    "sg:tags":[
        "appraiser"
    ],
    "wof:name":"Market Appraisers",
    "wof:placetype":"venue"
},
  "geometry": {"coordinates":[-80.416135,25.742668],"type":"Point"}
}