{
  "type": "Feature",
  "properties": {
    "addr:full":"5510 Sun Valley Dr Pensacola FL 32505",
    "addr:housenumber":"5510",
    "addr:postcode":"32505",
    "addr:street":"Sun Valley Dr",
    "iso:country":"US",
    "sg:address":"5510 Sun Valley Dr",
    "sg:city":"Pensacola",
    "sg:classifiers":[
        {
            "category":"Restaurant",
            "type":"Food & Drink"
        }
    ],
    "sg:phone":"+1 850 438 7603",
    "sg:postcode":"32505",
    "sg:province":"FL",
    "sg:tags":[
        "eating"
    ],
    "wof:name":"Calvins Cafe",
    "wof:placetype":"venue"
},
  "geometry": {"coordinates":[-87.263186,30.467125],"type":"Point"}
}