{
  "type": "Feature",
  "properties": {
    "iso:country":"US",
    "sg:address":"14311 SW 106th Ter",
    "sg:city":"Miami",
    "sg:classifiers":[
        {
            "category":"Shopping",
            "type":"Retail Goods"
        }
    ],
    "sg:phone":"+1 305 408 6127",
    "sg:postcode":"33186",
    "sg:province":"FL",
    "sg:tags":[
        "merchandise"
    ],
    "wof:name":"Pet Companion",
    "wof:placetype":"venue"
},
  "geometry": {"coordinates":[-80.42643700000001,25.668346],"type":"Point"}
}