{
  "type": "Feature",
  "properties": {
    "iso:country":"US",
    "sg:address":"5939 Park Blvd",
    "sg:city":"Pinellas Park",
    "sg:classifiers":[
        {
            "category":"Social Services",
            "type":"Services"
        }
    ],
    "sg:phone":"+1 727 548 8000",
    "sg:postcode":"33781",
    "sg:province":"FL",
    "sg:tags":[
        "counseling"
    ],
    "wof:name":"Clinicians Group",
    "wof:placetype":"venue"
},
  "geometry": {"coordinates":[-82.71565699999999,27.839256],"type":"Point"}
}