{
  "type": "Feature",
  "properties": {
    "iso:country":"US",
    "sg:address":"7655 38th Ave N",
    "sg:city":"Saint Petersburg",
    "sg:classifiers":[
        {
            "category":"Real Estate",
            "subcategory":"Real Estate Services",
            "type":"Services"
        }
    ],
    "sg:phone":"+1 727 345 2999",
    "sg:postcode":"33710",
    "sg:province":"FL",
    "sg:tags":[
        "abstract",
        "title"
    ],
    "wof:name":"Stewart Title",
    "wof:placetype":"venue"
},
  "geometry": {"coordinates":[-82.74393600000001,27.806452],"type":"Point"}
}