{
  "type": "Feature",
  "properties": {
    "iso:country":"US",
    "sg:address":"3364 SW 154th Ct",
    "sg:city":"Miami",
    "sg:classifiers":[
        {
            "category":"Autos & Motor Vehicles",
            "subcategory":"Automobile Sales",
            "type":"Retail Goods"
        }
    ],
    "sg:phone":"+1 305 510 3013",
    "sg:postcode":"33185",
    "sg:province":"FL",
    "sg:tags":[
        "new",
        "car"
    ],
    "wof:name":"Maroone Nissan Of Miami",
    "wof:placetype":"venue"
},
  "geometry": {"coordinates":[-80.444339,25.735518],"type":"Point"}
}