{
  "type": "Feature",
  "properties": {
    "addr:full":"10125 Land O Lakes Blvd Land O Lakes FL 34638",
    "addr:housenumber":"10125",
    "addr:postcode":"34638",
    "addr:street":"Land O Lakes Blvd Land",
    "iso:country":"US",
    "sg:address":"10125 Land O Lakes Blvd",
    "sg:city":"Land O Lakes",
    "sg:classifiers":[
        {
            "category":"Retail",
            "subcategory":"Animal Services",
            "type":"Services"
        }
    ],
    "sg:phone":"+1 813 995 9896",
    "sg:postcode":"34638",
    "sg:province":"FL",
    "sg:tags":[
        "pet",
        "grooming",
        "washing"
    ],
    "wof:name":"Paw Prince Pet Resort & Spa",
    "wof:placetype":"venue"
},
  "geometry": {"coordinates":[-82.492829,28.296424],"type":"Point"}
}