{
  "type": "Feature",
  "properties": {
    "addr:full":"7330 W Waters Ave Tampa FL 33634",
    "addr:housenumber":"7330",
    "addr:postcode":"33634",
    "addr:street":"W Waters Ave",
    "iso:country":"US",
    "sg:address":"7330 W Waters Ave",
    "sg:city":"Tampa",
    "sg:classifiers":[
        {
            "category":"Shopping",
            "subcategory":"Florist",
            "type":"Retail Goods"
        }
    ],
    "sg:phone":"+1 813 886 6955",
    "sg:postcode":"33634",
    "sg:province":"FL",
    "wof:name":"Town N Country Flower Shoppe",
    "wof:placetype":"venue"
},
  "geometry": {"coordinates":[-82.560164,28.025663],"type":"Point"}
}