{
  "type": "Feature",
  "properties": {
    "addr:full":"2122 University Blvd S Jacksonville FL 32216",
    "addr:housenumber":"2122",
    "addr:postcode":"32216",
    "addr:street":"University Blvd S",
    "iso:country":"US",
    "sg:address":"2122 University Blvd S",
    "sg:city":"Jacksonville",
    "sg:classifiers":[
        {
            "category":"Professional",
            "subcategory":"Accounting & Tax Preparation",
            "type":"Services"
        }
    ],
    "sg:phone":"+1 904 721 2020",
    "sg:postcode":"32216",
    "sg:province":"FL",
    "sg:tags":[
        "accountant"
    ],
    "wof:name":"Petherbridge Davis & Co",
    "wof:placetype":"venue"
},
  "geometry": {"coordinates":[-81.600329,30.30802],"type":"Point"}
}