{
  "type": "Feature",
  "properties": {
    "iso:country":"US",
    "sg:address":"940 Cassat Ave",
    "sg:city":"Jacksonville",
    "sg:classifiers":[
        {
            "category":"Restaurant",
            "type":"Food & Drink"
        }
    ],
    "sg:menulink":"http://www.allmenus.com/fl/jacksonville/71194-pizza-hut/menu/",
    "sg:phone":"+1 904 693 9883",
    "sg:postcode":"32205",
    "sg:province":"FL",
    "sg:tags":[
        "american",
        "pizza"
    ],
    "wof:name":"Pizza Hut",
    "wof:placetype":"venue"
},
  "geometry": {"coordinates":[-81.73065800000001,30.310307],"type":"Point"}
}