{
  "type": "Feature",
  "properties": {
    "addr:full":"4100 NW 9th St Ste 100 Miami FL 33126",
    "addr:housenumber":"4100",
    "addr:postcode":"33126",
    "addr:street":"Nw 9Th St Ste 100",
    "iso:country":"US",
    "sg:address":"4100 NW 9th St Ste 100",
    "sg:city":"Miami",
    "sg:classifiers":[
        {
            "category":"Health Services",
            "subcategory":"Doctor",
            "type":"Services"
        }
    ],
    "sg:phone":"+1 305 642 7111",
    "sg:postcode":"33126",
    "sg:province":"FL",
    "wof:name":"Tur Josefina F MD",
    "wof:placetype":"venue"
},
  "geometry": {"coordinates":[-80.29160299999999,25.777901],"type":"Point"}
}