{
  "type": "Feature",
  "properties": {
    "iso:country":"US",
    "sg:address":"3801 SW 11th St",
    "sg:city":"Fort Lauderdale",
    "sg:classifiers":[
        {
            "category":"Social Services",
            "type":"Services"
        }
    ],
    "sg:phone":"+1 954 792 2773",
    "sg:postcode":"33312",
    "sg:province":"FL",
    "wof:name":"Lydia Green Day Care",
    "wof:placetype":"venue"
},
  "geometry": {"coordinates":[-80.200383,26.107519],"type":"Point"}
}