{
  "type": "Feature",
  "properties": {
    "addr:full":"28834 Falling Leaves Way Zephyrhills FL 33543",
    "addr:housenumber":"28834",
    "addr:postcode":"33543",
    "addr:street":"Falling Leaves Way",
    "iso:country":"US",
    "sg:address":"28834 Falling Leaves Way",
    "sg:city":"Zephyrhills",
    "sg:classifiers":[
        {
            "category":"Professional",
            "subcategory":"Management & Consulting",
            "type":"Services"
        }
    ],
    "sg:phone":"+1 813 973 4898",
    "sg:postcode":"33543",
    "sg:province":"FL",
    "sg:tags":[
        "business"
    ],
    "wof:name":"Caltam Inc",
    "wof:placetype":"venue"
},
  "geometry": {"coordinates":[-82.34405599999999,28.182339],"type":"Point"}
}