{
  "type": "Feature",
  "properties": {
    "addr:full":"5973 NE 77th Ave Bronson FL 32621",
    "addr:housenumber":"5973",
    "addr:postcode":"32621",
    "addr:street":"Ne 77Th Ave",
    "iso:country":"US",
    "sg:address":"5973 NE 77th Ave",
    "sg:city":"Bronson",
    "sg:classifiers":[
        {
            "category":"Real Estate",
            "subcategory":"Real Estate Agent",
            "type":"Services"
        }
    ],
    "sg:phone":"+1 352 486 1412",
    "sg:postcode":"32621",
    "sg:province":"FL",
    "wof:name":"Eagle Realty Of Bronson",
    "wof:placetype":"venue"
},
  "geometry": {"coordinates":[-82.644408,29.422749],"type":"Point"}
}