{
  "type": "Feature",
  "properties": {
    "iso:country":"US",
    "sg:address":"115 Timberlachen Cir",
    "sg:city":"Lake Mary",
    "sg:classifiers":[
        {
            "category":"Real Estate",
            "subcategory":"Real Estate Agent",
            "type":"Services"
        }
    ],
    "sg:phone":"+1 407 330 7811",
    "sg:postcode":"32746",
    "sg:province":"FL",
    "wof:name":"Property BBS",
    "wof:placetype":"venue"
},
  "geometry": {"coordinates":[-81.35757700000001,28.748943],"type":"Point"}
}