{
  "type": "Feature",
  "properties": {
    "iso:country":"US",
    "sg:address":"12510 SW 144th Ter",
    "sg:city":"Miami",
    "sg:classifiers":[
        {
            "category":"Manufacturing",
            "subcategory":"Building Materials",
            "type":"Manufacturing & Wholesale Goods"
        }
    ],
    "sg:phone":"+1 305 378 1488",
    "sg:postcode":"33186",
    "sg:province":"FL",
    "sg:tags":[
        "frames",
        "doors",
        "accessory"
    ],
    "wof:name":"Automated Door System",
    "wof:placetype":"venue"
},
  "geometry": {"coordinates":[-80.39589700000001,25.63357],"type":"Point"}
}