{
  "type": "Feature",
  "properties": {
    "addr:full":"1150 NE 26th St Wilton Manors FL 33305",
    "addr:housenumber":"1150",
    "addr:postcode":"33305",
    "addr:street":"Ne 26Th St",
    "iso:country":"US",
    "sg:address":"1150 NE 26th St",
    "sg:city":"Wilton Manors",
    "sg:classifiers":[
        {
            "category":"Shopping",
            "subcategory":"Pharmacy",
            "type":"Retail Goods"
        }
    ],
    "sg:phone":"+1 954 566 3052",
    "sg:postcode":"33305",
    "sg:province":"FL",
    "wof:name":"CVS Pharmacy",
    "wof:placetype":"venue"
},
  "geometry": {"coordinates":[-80.131775,26.159449],"type":"Point"}
}