{
  "type": "Feature",
  "properties": {
    "iso:country":"US",
    "sg:address":"509 S Park Ave",
    "sg:city":"Titusville",
    "sg:classifiers":[
        {
            "category":"Shopping",
            "subcategory":"Used Merchandise",
            "type":"Retail Goods"
        }
    ],
    "sg:phone":"+1 321 269 2974",
    "sg:postcode":"32796",
    "sg:province":"FL",
    "wof:name":"Computer Executive",
    "wof:placetype":"venue"
},
  "geometry": {"coordinates":[-80.81857599999999,28.609276],"type":"Point"}
}