{
  "type": "Feature",
  "properties": {
    "addr:full":"2594 W Airport Blvd Sanford FL 32771",
    "addr:housenumber":"2594",
    "addr:postcode":"32771",
    "addr:street":"W Airport Blvd",
    "iso:country":"US",
    "sg:address":"2594 W Airport Blvd",
    "sg:city":"Sanford",
    "sg:classifiers":[
        {
            "category":"Food & Beverages",
            "subcategory":"Groceries & Convenience Stores",
            "type":"Retail Goods"
        }
    ],
    "sg:phone":"+1 407 323 6251",
    "sg:postcode":"32771",
    "sg:province":"FL",
    "wof:name":"Quick Stop Center",
    "wof:placetype":"venue"
},
  "geometry": {"coordinates":[-81.29785800000001,28.802225],"type":"Point"}
}