{
  "type": "Feature",
  "properties": {
    "iso:country":"US",
    "sg:address":"6050 S US Highway 17/92",
    "sg:city":"Casselberry",
    "sg:classifiers":[
        {
            "category":"Retail",
            "subcategory":"Auto Repair",
            "type":"Services"
        }
    ],
    "sg:phone":"+1 407 339 0084",
    "sg:postcode":"32730",
    "sg:province":"FL",
    "sg:website":"www.carcoolauto.com",
    "wof:name":"Car Cool Auto Inc",
    "wof:placetype":"venue"
},
  "geometry": {"coordinates":[-81.342618,28.659436],"type":"Point"}
}