{
  "type": "Feature",
  "properties": {
    "addr:full":"1 Lely High School Blvd Naples FL 34113",
    "addr:housenumber":"1",
    "addr:postcode":"34113",
    "addr:street":"Lely;Blvd",
    "iso:country":"US",
    "sg:address":"1 Lely High School Blvd",
    "sg:city":"Naples",
    "sg:classifiers":[
        {
            "category":"Education",
            "subcategory":"School",
            "type":"Public Place"
        }
    ],
    "sg:phone":"+1 239 417 4500",
    "sg:postcode":"34113",
    "sg:province":"FL",
    "sg:website":"www.collier.k12.fl.us",
    "wof:name":"Lely High School",
    "wof:placetype":"venue"
},
  "geometry": {"coordinates":[-81.716053,26.089143],"type":"Point"}
}