{
  "type": "Feature",
  "properties": {
    "iso:country":"US",
    "sg:address":"2408 Walker Cir",
    "sg:city":"Sarasota",
    "sg:classifiers":[
        {
            "category":"Shopping",
            "subcategory":"Clothing, Apparel, & Fashions",
            "type":"Retail Goods"
        }
    ],
    "sg:phone":"+1 941 953 4526",
    "sg:postcode":"34234",
    "sg:province":"FL",
    "sg:tags":[
        "ready"
    ],
    "wof:name":"Adeles Boutique",
    "wof:placetype":"venue"
},
  "geometry": {"coordinates":[-82.545806,27.357678],"type":"Point"}
}