{
  "type": "Feature",
  "properties": {
    "iso:country":"US",
    "sg:address":"19370 Collins Ave",
    "sg:city":"Miami",
    "sg:classifiers":[
        {
            "category":"Wholesale",
            "subcategory":"Non-durable Goods",
            "type":"Manufacturing & Wholesale Goods"
        }
    ],
    "sg:phone":"+1 305 792 5476",
    "sg:postcode":"33160",
    "sg:province":"FL",
    "wof:name":"Nb Trading Corp",
    "wof:placetype":"venue"
},
  "geometry": {"coordinates":[-80.120589,25.954614],"type":"Point"}
}