{
  "type": "Feature",
  "properties": {
    "addr:full":"269 Kelsey Park Cir Palm Beach Gardens FL 33410",
    "addr:housenumber":"269",
    "addr:postcode":"33410",
    "addr:street":"Kelsey Park Cir",
    "iso:country":"US",
    "sg:address":"269 Kelsey Park Cir",
    "sg:city":"Palm Beach Gardens",
    "sg:classifiers":[
        {
            "category":"Professional",
            "subcategory":"Management & Consulting",
            "type":"Services"
        }
    ],
    "sg:phone":"+1 561 799 3852",
    "sg:postcode":"33410",
    "sg:province":"FL",
    "wof:name":"Trojan Management of Palm",
    "wof:placetype":"venue"
},
  "geometry": {"coordinates":[-80.078264,26.834189],"type":"Point"}
}