{
  "type": "Feature",
  "properties": {
    "iso:country":"US",
    "sg:address":"4801 Secret Harbor Dr",
    "sg:city":"Jacksonville",
    "sg:classifiers":[
        {
            "category":"Professional",
            "type":"Services"
        }
    ],
    "sg:phone":"+1 904 262 1485",
    "sg:postcode":"32257",
    "sg:province":"FL",
    "wof:name":"Palmyra Systems Inc",
    "wof:placetype":"venue"
},
  "geometry": {"coordinates":[-81.59208599999999,30.190054],"type":"Point"}
}