{
  "type": "Feature",
  "properties": {
    "iso:country":"US",
    "sg:address":"1108 Beville Rd",
    "sg:city":"Daytona Beach",
    "sg:classifiers":[
        {
            "category":"Restaurant",
            "type":"Food & Drink"
        }
    ],
    "sg:menulink":"http://www.allmenus.com/fl/daytona-beach/169171-el-azteca/menu/",
    "sg:phone":"+1 386 257 5544",
    "sg:postcode":"32114",
    "sg:province":"FL",
    "sg:tags":[
        "mexican"
    ],
    "wof:name":"El Azteca",
    "wof:placetype":"venue"
},
  "geometry": {"coordinates":[-81.030368,29.17542],"type":"Point"}
}