{
  "type": "Feature",
  "properties": {
    "iso:country":"US",
    "sg:address":"890 S Jackson Ave",
    "sg:city":"Bartow",
    "sg:classifiers":[
        {
            "category":"Banks & Credit Unions",
            "subcategory":"Financial Services",
            "type":"Services"
        }
    ],
    "sg:phone":"+1 863 533 9441",
    "sg:postcode":"33830",
    "sg:province":"FL",
    "sg:tags":[
        "trust",
        "management"
    ],
    "wof:name":"Trustee",
    "wof:placetype":"venue"
},
  "geometry": {"coordinates":[-81.839032,27.889522],"type":"Point"}
}