{
  "type": "Feature",
  "properties": {
    "addr:full":"7801 Tatum Waterway Dr Miami FL 33141",
    "addr:housenumber":"7801",
    "addr:postcode":"33141",
    "addr:street":"Tatum Waterway Dr",
    "iso:country":"US",
    "sg:address":"7801 Tatum Waterway Dr",
    "sg:city":"Miami",
    "sg:classifiers":[
        {
            "category":"Real Estate",
            "subcategory":"Real Estate Operator",
            "type":"Services"
        }
    ],
    "sg:phone":"+1 305 861 2942",
    "sg:postcode":"33141",
    "sg:province":"FL",
    "sg:tags":[
        "apartment"
    ],
    "wof:name":"North Beach Apartments",
    "wof:placetype":"venue"
},
  "geometry": {"coordinates":[-80.125669,25.86411],"type":"Point"}
}