{
  "type": "Feature",
  "properties": {
    "iso:country":"US",
    "sg:address":"15661 SW 104th Ter",
    "sg:city":"Miami",
    "sg:classifiers":[
        {
            "category":"Manufacturing",
            "subcategory":"Printing",
            "type":"Manufacturing & Wholesale Goods"
        }
    ],
    "sg:phone":"+1 305 387 7605",
    "sg:postcode":"33196",
    "sg:province":"FL",
    "sg:tags":[
        "publishing"
    ],
    "wof:name":"Smith Diamond Music Publishing",
    "wof:placetype":"venue"
},
  "geometry": {"coordinates":[-80.448008,25.669356],"type":"Point"}
}