{
  "type": "Feature",
  "properties": {
    "addr:full":"2422 Kings Rd Jacksonville FL 32209",
    "addr:housenumber":"2422",
    "addr:postcode":"32209",
    "addr:street":"Kings Rd",
    "iso:country":"US",
    "sg:address":"2422 Kings Rd",
    "sg:city":"Jacksonville",
    "sg:classifiers":[
        {
            "category":"Retail",
            "subcategory":"Auto Repair",
            "type":"Services"
        }
    ],
    "sg:phone":"+1 904 355 7785",
    "sg:postcode":"32209",
    "sg:province":"FL",
    "sg:tags":[
        "body"
    ],
    "wof:name":"W&V Paint & Body Shop",
    "wof:placetype":"venue"
},
  "geometry": {"coordinates":[-81.70321800000001,30.351437],"type":"Point"}
}