{
  "type": "Feature",
  "properties": {
    "iso:country":"US",
    "sg:address":"7899 W 15th Ave",
    "sg:city":"Hialeah",
    "sg:classifiers":[
        {
            "category":"Professional",
            "type":"Services"
        }
    ],
    "sg:phone":"+1 305 512 1611",
    "sg:postcode":"33014",
    "sg:province":"FL",
    "sg:tags":[
        "establishment"
    ],
    "wof:name":"Effective Network Solutions",
    "wof:placetype":"venue"
},
  "geometry": {"coordinates":[-80.313613,25.8956],"type":"Point"}
}