{
  "type": "Feature",
  "properties": {
    "addr:full":"5217 Dallas Blvd Orlando FL 32833",
    "addr:housenumber":"5217",
    "addr:postcode":"32833",
    "addr:street":"Dallas Blvd",
    "iso:country":"US",
    "sg:address":"5217 Dallas Blvd",
    "sg:city":"Orlando",
    "sg:classifiers":[
        {
            "category":"Professional",
            "subcategory":"Employment Agencies",
            "type":"Services"
        }
    ],
    "sg:phone":"+1 407 288 2217",
    "sg:postcode":"32833",
    "sg:province":"FL",
    "wof:name":"Caribbean Hospitality Staffing",
    "wof:placetype":"venue"
},
  "geometry": {"coordinates":[-81.09517700000001,28.47196],"type":"Point"}
}