{
  "type": "Feature",
  "properties": {
    "iso:country":"US",
    "sg:address":"2211 Lee Rd",
    "sg:city":"Winter Park",
    "sg:classifiers":[
        {
            "category":"Banks & Credit Unions",
            "subcategory":"Financial Services",
            "type":"Services"
        }
    ],
    "sg:phone":"+1 407 622 4729",
    "sg:postcode":"32789",
    "sg:province":"FL",
    "sg:tags":[
        "broker",
        "mortgage"
    ],
    "wof:name":"Safe Harbor Lending",
    "wof:placetype":"venue"
},
  "geometry": {"coordinates":[-81.377701,28.606001],"type":"Point"}
}