{
  "type": "Feature",
  "properties": {
    "addr:full":"5203 Paris Ave Jacksonville FL 32209",
    "addr:housenumber":"5203",
    "addr:postcode":"32209",
    "addr:street":"Paris Ave",
    "iso:country":"US",
    "sg:address":"5203 Paris Ave",
    "sg:city":"Jacksonville",
    "sg:classifiers":[
        {
            "category":"Organizations",
            "subcategory":"Religious Organization",
            "type":"Services"
        }
    ],
    "sg:phone":"+1 904 766 1153",
    "sg:postcode":"32209",
    "sg:province":"FL",
    "sg:tags":[
        "church"
    ],
    "wof:name":"Buckner Temple Church Of God",
    "wof:placetype":"venue"
},
  "geometry": {"coordinates":[-81.697909,30.369349],"type":"Point"}
}