{
  "type": "Feature",
  "properties": {
    "iso:country":"US",
    "sg:address":"13890 SW 88th St",
    "sg:city":"Miami",
    "sg:classifiers":[
        {
            "category":"Restaurant",
            "type":"Food & Drink"
        }
    ],
    "sg:menulink":"http://www.allmenus.com/fl/kendale-lakes-lindgren-acres/169261-wendys/menu/",
    "sg:phone":"+1 305 385 1266",
    "sg:postcode":"33186",
    "sg:province":"FL",
    "sg:tags":[
        "burger",
        "american",
        "soup"
    ],
    "wof:name":"Wendy's",
    "wof:placetype":"venue"
},
  "geometry": {"coordinates":[-80.420351,25.68481],"type":"Point"}
}