{
  "type": "Feature",
  "properties": {
    "addr:full":"1013 Oakview Ave Clearwater FL 33756",
    "addr:housenumber":"1013",
    "addr:postcode":"33756",
    "addr:street":"Oakview Ave",
    "iso:country":"US",
    "sg:address":"1013 Oakview Ave",
    "sg:city":"Clearwater",
    "sg:classifiers":[
        {
            "category":"Banks & Credit Unions",
            "subcategory":"Bank",
            "type":"Services"
        }
    ],
    "sg:phone":"+1 727 441 1193",
    "sg:postcode":"33756",
    "sg:province":"FL",
    "sg:tags":[
        "loan",
        "real estate"
    ],
    "wof:name":"America Mortgage",
    "wof:placetype":"venue"
},
  "geometry": {"coordinates":[-82.776067,27.954487],"type":"Point"}
}