{
  "type": "Feature",
  "properties": {
    "iso:country":"US",
    "sg:address":"1805 NW 22 Ter",
    "sg:city":"Gainesville",
    "sg:classifiers":[
        {
            "category":"Organizations",
            "subcategory":"Community Association",
            "type":"Services"
        }
    ],
    "sg:phone":"+1 352 378 2877",
    "sg:postcode":"32605",
    "sg:province":"FL",
    "sg:tags":[
        "civic",
        "fraternal",
        "social"
    ],
    "wof:name":"Alachua Cnty Scholastic Chess",
    "wof:placetype":"venue"
},
  "geometry": {"coordinates":[-82.353373,29.6687],"type":"Point"}
}