{
  "type": "Feature",
  "properties": {
    "addr:full":"10451 SW 198th St Miami FL 33157",
    "addr:housenumber":"10451",
    "addr:postcode":"33157",
    "addr:street":"Sw 198Th St",
    "iso:country":"US",
    "sg:address":"10451 SW 198th St",
    "sg:city":"Miami",
    "sg:classifiers":[
        {
            "category":"Home & Garden",
            "subcategory":"Building Materials",
            "type":"Retail Goods"
        }
    ],
    "sg:phone":"+1 305 234 8115",
    "sg:postcode":"33157",
    "sg:province":"FL",
    "sg:tags":[
        "glass",
        "window",
        "plate"
    ],
    "wof:name":"Cutting Edge",
    "wof:placetype":"venue"
},
  "geometry": {"coordinates":[-80.361153,25.583022],"type":"Point"}
}