{
  "type": "Feature",
  "properties": {
    "iso:country":"US",
    "sg:address":"5860 US Hwy 1 N",
    "sg:city":"Saint Augustine",
    "sg:classifiers":[
        {
            "category":"Insurance",
            "subcategory":"Insurance Agent",
            "type":"Services"
        }
    ],
    "sg:phone":"+1 904 824 4476",
    "sg:postcode":"32095",
    "sg:province":"FL",
    "wof:name":"Pax Financial",
    "wof:placetype":"venue"
},
  "geometry": {"coordinates":[-81.359711,29.976607],"type":"Point"}
}