{
  "type": "Feature",
  "properties": {
    "iso:country":"US",
    "sg:address":"3280 Grand Ave",
    "sg:city":"Miami",
    "sg:classifiers":[
        {
            "category":"Autos & Motor Vehicles",
            "subcategory":"Fuel & Gas Station",
            "type":"Retail Goods"
        }
    ],
    "sg:phone":"+1 305 446 9953",
    "sg:postcode":"33133",
    "sg:province":"FL",
    "sg:tags":[
        "oil"
    ],
    "wof:name":"Coconut Grove Victory",
    "wof:placetype":"venue"
},
  "geometry": {"coordinates":[-80.24587099999999,25.727872],"type":"Point"}
}