{
  "type": "Feature",
  "properties": {
    "addr:full":"3401 Hibiscus Ave Naples FL 34104",
    "addr:housenumber":"3401",
    "addr:postcode":"34104",
    "addr:street":"Hibiscus Ave",
    "iso:country":"US",
    "sg:address":"3401 Hibiscus Ave",
    "sg:city":"Naples",
    "sg:classifiers":[
        {
            "category":"Building & Trades",
            "subcategory":"Electrical",
            "type":"Services"
        }
    ],
    "sg:phone":"+1 239 643 5265",
    "sg:postcode":"34104",
    "sg:province":"FL",
    "sg:tags":[
        "electrical",
        "electric",
        "contractor"
    ],
    "wof:name":"Electrical Concepts of Florida",
    "wof:placetype":"venue"
},
  "geometry": {"coordinates":[-81.765399,26.143149],"type":"Point"}
}