{
  "type": "Feature",
  "properties": {
    "iso:country":"US",
    "sg:address":"2350 W 60th St",
    "sg:city":"Hialeah",
    "sg:classifiers":[
        {
            "category":"Shopping",
            "subcategory":"Mobile Phones",
            "type":"Retail Goods"
        }
    ],
    "sg:phone":"+1 305 820 5515",
    "sg:postcode":"33016",
    "sg:province":"FL",
    "wof:name":"Tellcomm Global Corp",
    "wof:placetype":"venue"
},
  "geometry": {"coordinates":[-80.330259,25.876883],"type":"Point"}
}