{
  "type": "Feature",
  "properties": {
    "addr:full":"1915 Donald Pl Daytona Beach FL 32119",
    "addr:housenumber":"1915",
    "addr:postcode":"32119",
    "addr:street":"Donald Pl",
    "iso:country":"US",
    "sg:address":"1915 Donald Pl",
    "sg:city":"Daytona Beach",
    "sg:classifiers":[
        {
            "category":"Building & Trades",
            "subcategory":"Plumbing",
            "type":"Services"
        }
    ],
    "sg:phone":"+1 386 322 1427",
    "sg:postcode":"32119",
    "sg:province":"FL",
    "sg:tags":[
        "conditioning",
        "air",
        "system",
        "contractor"
    ],
    "wof:name":"A Plus Htg & Air Conditioning",
    "wof:placetype":"venue"
},
  "geometry": {"coordinates":[-81.030236,29.16499],"type":"Point"}
}