{
  "type": "Feature",
  "properties": {
    "iso:country":"US",
    "sg:address":"6413 NW 200th St",
    "sg:city":"Hialeah",
    "sg:classifiers":[
        {
            "category":"Wholesale",
            "subcategory":"Durable Goods & Equipment",
            "type":"Manufacturing & Wholesale Goods"
        }
    ],
    "sg:phone":"+1 305 625 1699",
    "sg:postcode":"33015",
    "sg:province":"FL",
    "sg:tags":[
        "product",
        "mfg"
    ],
    "wof:name":"L Knife Making",
    "wof:placetype":"venue"
},
  "geometry": {"coordinates":[-80.305744,25.953291],"type":"Point"}
}