{
  "type": "Feature",
  "properties": {
    "iso:country":"US",
    "sg:address":"501 116th Ave N",
    "sg:city":"St Petersburg",
    "sg:classifiers":[
        {
            "category":"Building & Trades",
            "subcategory":"Plumbing",
            "type":"Services"
        }
    ],
    "sg:phone":"+1 727 244 9530",
    "sg:postcode":"33716",
    "sg:province":"FL",
    "sg:tags":[
        "conditioning",
        "air",
        "system",
        "contractor"
    ],
    "wof:name":"SCI Heating Air Room Unit",
    "wof:placetype":"venue"
},
  "geometry": {"coordinates":[-82.64126,27.877519],"type":"Point"}
}