{
  "type": "Feature",
  "properties": {
    "addr:full":"974 Boeing St NE Palm Bay FL 32907",
    "addr:housenumber":"974",
    "addr:postcode":"32907",
    "addr:street":"Boeing St Ne",
    "iso:country":"US",
    "sg:address":"974 Boeing St NE",
    "sg:city":"Palm Bay",
    "sg:classifiers":[
        {
            "category":"Arts & Performance",
            "subcategory":"Theater",
            "type":"Entertainment"
        }
    ],
    "sg:phone":"+1 321 768 7740",
    "sg:postcode":"32907",
    "sg:province":"FL",
    "sg:tags":[
        "bureau"
    ],
    "wof:name":"Barbara J Silva Entertainer",
    "wof:placetype":"venue"
},
  "geometry": {"coordinates":[-80.644158,28.008208],"type":"Point"}
}