{
  "type": "Feature",
  "properties": {
    "iso:country":"US",
    "sg:address":"1098 Bay Harbor Dr",
    "sg:city":"Englewood",
    "sg:classifiers":[
        {
            "category":"Recreation",
            "type":"Entertainment"
        }
    ],
    "sg:phone":"+1 941 474 1022",
    "sg:postcode":"34224",
    "sg:province":"FL",
    "sg:tags":[
        "charter",
        "boat"
    ],
    "wof:name":"A-1 Grouper Fishing",
    "wof:placetype":"venue"
},
  "geometry": {"coordinates":[-82.332751,26.931168],"type":"Point"}
}