{
  "type": "Feature",
  "properties": {
    "addr:full":"221 N Hogan St Suite 175 Jacksonville FL 32202",
    "addr:housenumber":"221",
    "addr:postcode":"32202",
    "addr:street":"N Hogan St Suite 175",
    "iso:country":"US",
    "sg:address":"221 N Hogan St Suite 175",
    "sg:city":"Jacksonville",
    "sg:classifiers":[
        {
            "category":"Professional",
            "subcategory":"Management & Consulting",
            "type":"Services"
        },
        {
            "category":"Banks & Credit Unions",
            "subcategory":"Financial Services",
            "type":"Services"
        },
        {
            "category":"Real Estate",
            "subcategory":"Real Estate Agent",
            "type":"Services"
        },
        {
            "category":"Real Estate",
            "subcategory":"Real Estate Services",
            "type":"Services"
        }
    ],
    "sg:phone":"+1 904 637 4948",
    "sg:postcode":"32202",
    "sg:province":"FL",
    "sg:tags":[
        "consultant",
        "financing",
        "loan",
        "mortgage"
    ],
    "sg:website":"http://www.ccn2mortgages.com",
    "wof:name":"CCN2 Mortgage Solutions Inc.",
    "wof:placetype":"venue"
},
  "geometry": {"coordinates":[-81.660132,30.328486],"type":"Point"}
}