{
  "type": "Feature",
  "properties": {
    "iso:country":"US",
    "sg:address":"6921 SW 129th Ave",
    "sg:city":"Miami",
    "sg:classifiers":[
        {
            "category":"Recreation",
            "subcategory":"Picnic Area",
            "type":"Entertainment"
        },
        {
            "category":"Community Center",
            "type":"Public Place"
        }
    ],
    "sg:phone":"+1 305 385 3505",
    "sg:postcode":"33183",
    "sg:province":"FL",
    "sg:tags":[
        "amusement",
        "arcade"
    ],
    "wof:name":"Miami Moonwalks Clowns & More",
    "wof:placetype":"venue"
},
  "geometry": {"coordinates":[-80.402128,25.702813],"type":"Point"}
}