{
  "type": "Feature",
  "properties": {
    "iso:country":"US",
    "sg:address":"216 SE Coconut Ave",
    "sg:city":"Stuart",
    "sg:classifiers":[
        {
            "category":"Shopping",
            "subcategory":"Books",
            "type":"Retail Goods"
        }
    ],
    "sg:phone":"+1 772 221 9161",
    "sg:postcode":"34996",
    "sg:province":"FL",
    "wof:name":"Keeper of Books Inc",
    "wof:placetype":"venue"
},
  "geometry": {"coordinates":[-80.23579100000001,27.198747],"type":"Point"}
}