{
  "type": "Feature",
  "properties": {
    "addr:full":"706 Donax St Sanibel FL 33957",
    "addr:housenumber":"706",
    "addr:postcode":"33957",
    "addr:street":"Donax St",
    "iso:country":"US",
    "sg:address":"706 Donax St",
    "sg:city":"Sanibel",
    "sg:classifiers":[
        {
            "category":"Travel",
            "subcategory":"Hotels & Motels",
            "type":"Entertainment"
        }
    ],
    "sg:phone":"+1 239 472 1606",
    "sg:postcode":"33957",
    "sg:province":"FL",
    "sg:tags":[
        "operation"
    ],
    "sg:website":"www.palmviewmotel.com",
    "wof:name":"Palm View Motel",
    "wof:placetype":"venue"
},
  "geometry": {"coordinates":[-82.046015,26.438754],"type":"Point"}
}