{
  "type": "Feature",
  "properties": {
    "addr:full":"5237 Summerlin Commons Blvd Fort Myers FL 33907",
    "addr:housenumber":"5237",
    "addr:postcode":"33907",
    "addr:street":"Summerlin Commons Blvd",
    "iso:country":"US",
    "sg:address":"5237 Summerlin Commons Blvd",
    "sg:city":"Fort Myers",
    "sg:classifiers":[
        {
            "category":"Professional",
            "type":"Services"
        }
    ],
    "sg:phone":"+1 239 247 5167",
    "sg:postcode":"33907",
    "sg:province":"FL",
    "sg:website":"www.premiercenter.net/executive_...",
    "wof:name":"Premier Executive Center",
    "wof:placetype":"venue"
},
  "geometry": {"coordinates":[-81.883404,26.59078],"type":"Point"}
}