{
  "type": "Feature",
  "properties": {
    "addr:full":"1939 Boothe Cir Longwood FL 32750",
    "addr:housenumber":"1939",
    "addr:postcode":"32750",
    "addr:street":"Boothe Cir",
    "iso:country":"US",
    "sg:address":"1939 Boothe Cir",
    "sg:city":"Longwood",
    "sg:classifiers":[
        {
            "category":"Professional",
            "type":"Services"
        }
    ],
    "sg:phone":"+1 407 339 5324",
    "sg:postcode":"32750",
    "sg:province":"FL",
    "wof:name":"Roach Leila",
    "wof:placetype":"venue"
},
  "geometry": {"coordinates":[-81.386881,28.690723],"type":"Point"}
}