{
  "type": "Feature",
  "properties": {
    "iso:country":"US",
    "sg:address":"1735 Stickney Point Rd",
    "sg:city":"Sarasota",
    "sg:classifiers":[
        {
            "category":"Travel",
            "subcategory":"Hotels & Motels",
            "type":"Entertainment"
        }
    ],
    "sg:phone":"+1 941 921 5797",
    "sg:postcode":"34231",
    "sg:province":"FL",
    "sg:website":"www.hibiscussuitesinn.com",
    "wof:name":"Hibiscus Suites Inn",
    "wof:placetype":"venue"
},
  "geometry": {"coordinates":[-82.526521,27.257521],"type":"Point"}
}