{
  "type": "Feature",
  "properties": {
    "addr:full":"6800 NE 22nd Way Fort Lauderdale FL 33308",
    "addr:housenumber":"6800",
    "addr:postcode":"33308",
    "addr:street":"Ne 22Nd Way",
    "iso:country":"US",
    "sg:address":"6800 NE 22nd Way",
    "sg:city":"Fort Lauderdale",
    "sg:classifiers":[
        {
            "category":"Wholesale",
            "subcategory":"Non-durable Goods",
            "type":"Manufacturing & Wholesale Goods"
        }
    ],
    "sg:phone":"+1 772 873 5488",
    "sg:postcode":"33308",
    "sg:province":"FL",
    "sg:tags":[
        "import",
        "china",
        "merchandise"
    ],
    "wof:name":"Down East Imports LLC",
    "wof:placetype":"venue"
},
  "geometry": {"coordinates":[-80.110508,26.210699],"type":"Point"}
}