{
  "type": "Feature",
  "properties": {
    "addr:full":"153 Industrial Loop S Orange Park FL 32073",
    "addr:housenumber":"153",
    "addr:postcode":"32073",
    "addr:street":"Industrial Loop S Orange Park",
    "iso:country":"US",
    "sg:address":"153 Industrial Loop S",
    "sg:city":"Orange Park",
    "sg:classifiers":[
        {
            "category":"Manufacturing",
            "subcategory":"Food",
            "type":"Manufacturing & Wholesale Goods"
        }
    ],
    "sg:phone":"+1 904 269 3240",
    "sg:postcode":"32073",
    "sg:province":"FL",
    "sg:tags":[
        "product",
        "health"
    ],
    "sg:website":"www.re-vita.net",
    "wof:name":"Re-Vita",
    "wof:placetype":"venue"
},
  "geometry": {"coordinates":[-81.7128,30.17954],"type":"Point"}
}