{
  "type": "Feature",
  "properties": {
    "iso:country":"US",
    "sg:address":"5 Harvard Cir",
    "sg:city":"West Palm Beach",
    "sg:classifiers":[
        {
            "category":"Health Services",
            "subcategory":"Health Practitioner",
            "type":"Services"
        }
    ],
    "sg:phone":"+1 561 687 0244",
    "sg:postcode":"33409",
    "sg:province":"FL",
    "sg:tags":[
        "psychologist"
    ],
    "wof:name":"Yianoula Alexakis",
    "wof:placetype":"venue"
},
  "geometry": {"coordinates":[-80.10051300000001,26.710669],"type":"Point"}
}