{
  "type": "Feature",
  "properties": {
    "iso:country":"US",
    "sg:address":"3201 NW 17th Ave",
    "sg:city":"Miami",
    "sg:classifiers":[
        {
            "category":"Wholesale",
            "subcategory":"Durable Goods & Equipment",
            "type":"Manufacturing & Wholesale Goods"
        }
    ],
    "sg:phone":"+1 786 360 6376",
    "sg:postcode":"33142",
    "sg:province":"FL",
    "sg:tags":[
        "appliances-major-wholesale",
        "manufacturer"
    ],
    "wof:name":"Cohen Appliances",
    "wof:placetype":"venue"
},
  "geometry": {"coordinates":[-80.22374000000001,25.80621],"type":"Point"}
}