{
  "type": "Feature",
  "properties": {
    "addr:full":"2829 SW 5th St Fort Lauderdale FL 33312",
    "addr:housenumber":"2829",
    "addr:postcode":"33312",
    "addr:street":"Sw 5Th St",
    "iso:country":"US",
    "sg:address":"2829 SW 5th St",
    "sg:city":"Fort Lauderdale",
    "sg:classifiers":[
        {
            "category":"Professional",
            "subcategory":"Management & Consulting",
            "type":"Services"
        }
    ],
    "sg:phone":"+1 954 583 8256",
    "sg:postcode":"33312",
    "sg:province":"FL",
    "wof:name":"Hardy Management Services Inc",
    "wof:placetype":"venue"
},
  "geometry": {"coordinates":[-80.181985,26.115142],"type":"Point"}
}