{
  "type": "Feature",
  "properties": {
    "addr:full":"2109 Winnetka Ct Orlando FL 32818",
    "addr:housenumber":"2109",
    "addr:postcode":"32818",
    "addr:street":"Winnetka Ct",
    "iso:country":"US",
    "sg:address":"2109 Winnetka Ct",
    "sg:city":"Orlando",
    "sg:classifiers":[
        {
            "category":"Building & Trades",
            "subcategory":"Construction",
            "type":"Services"
        }
    ],
    "sg:phone":"+1 407 299 9462",
    "sg:postcode":"32818",
    "sg:province":"FL",
    "sg:tags":[
        "hanging",
        "floor",
        "laying",
        "contract",
        "contractor"
    ],
    "wof:name":"Quality Is A Bell",
    "wof:placetype":"venue"
},
  "geometry": {"coordinates":[-81.471273,28.568378],"type":"Point"}
}