{
  "type": "Feature",
  "properties": {
    "addr:full":"418 Admiral Cove Tarpon Springs FL 34689",
    "addr:housenumber":"418",
    "addr:postcode":"34689",
    "addr:street":"Admiral Cove",
    "iso:country":"US",
    "sg:address":"418 Admiral Cove",
    "sg:city":"Tarpon Springs",
    "sg:classifiers":[
        {
            "category":"Restaurant",
            "type":"Food & Drink"
        }
    ],
    "sg:phone":"+1 727 942 2441",
    "sg:postcode":"34689",
    "sg:province":"FL",
    "sg:tags":[
        "eating"
    ],
    "wof:name":"Chris Coney Island Inc",
    "wof:placetype":"venue"
},
  "geometry": {"coordinates":[-82.782886,28.150764],"type":"Point"}
}