{
  "type": "Feature",
  "properties": {
    "addr:full":"100 Kingston Ct Orlando FL 32810",
    "addr:housenumber":"100",
    "addr:postcode":"32810",
    "addr:street":"Kingston Ct",
    "iso:country":"US",
    "sg:address":"100 Kingston Ct",
    "sg:city":"Orlando",
    "sg:classifiers":[
        {
            "category":"Real Estate",
            "subcategory":"Real Estate Operator",
            "type":"Services"
        }
    ],
    "sg:phone":"+1 407 875 2794",
    "sg:postcode":"32810",
    "sg:province":"FL",
    "sg:tags":[
        "apartment"
    ],
    "wof:name":"Kingston Court Apts",
    "wof:placetype":"venue"
},
  "geometry": {"coordinates":[-81.40509900000001,28.617929],"type":"Point"}
}