{
  "type": "Feature",
  "properties": {
    "addr:full":"7329 NW 8th St Miami FL 33126",
    "addr:housenumber":"7329",
    "addr:postcode":"33126",
    "addr:street":"Nw 8Th St",
    "iso:country":"US",
    "sg:address":"7329 NW 8th St",
    "sg:city":"Miami",
    "sg:classifiers":[
        {
            "category":"Real Estate",
            "subcategory":"Real Estate Operator",
            "type":"Services"
        }
    ],
    "sg:phone":"+1 305 269 4990",
    "sg:postcode":"33126",
    "sg:province":"FL",
    "sg:tags":[
        "building",
        "nonresidential"
    ],
    "wof:name":"Rogcab Warehouse Condominiums",
    "wof:placetype":"venue"
},
  "geometry": {"coordinates":[-80.31428099999999,25.778596],"type":"Point"}
}