{
  "type": "Feature",
  "properties": {
    "addr:full":"12 Marcus Cir Milton FL 32571",
    "addr:housenumber":"12",
    "addr:postcode":"32571",
    "addr:street":"Marcus Cir",
    "iso:country":"US",
    "sg:address":"12 Marcus Cir",
    "sg:city":"Milton",
    "sg:classifiers":[
        {
            "category":"Real Estate",
            "subcategory":"Real Estate Agent",
            "type":"Services"
        }
    ],
    "sg:phone":"+1 850 994 1595",
    "sg:postcode":"32571",
    "sg:province":"FL",
    "sg:tags":[
        "inspection"
    ],
    "wof:name":"Home To Home Inspection Inc",
    "wof:placetype":"venue"
},
  "geometry": {"coordinates":[-87.11730900000001,30.587558],"type":"Point"}
}