{
  "type": "Feature",
  "properties": {
    "iso:country":"US",
    "sg:address":"7484 University Blvd",
    "sg:city":"Winter Park",
    "sg:classifiers":[
        {
            "category":"Restaurant",
            "type":"Food & Drink"
        }
    ],
    "sg:phone":"+1 407 671 3566",
    "sg:postcode":"32792",
    "sg:province":"FL",
    "sg:tags":[
        "tex-mex"
    ],
    "sg:website":"www.moesorlando.com/",
    "wof:name":"Moe's Southwestern Grill",
    "wof:placetype":"venue"
},
  "geometry": {"coordinates":[-81.28731399999999,28.59736],"type":"Point"}
}