{
  "type": "Feature",
  "properties": {
    "iso:country":"US",
    "sg:address":"2820 Bus Center Blvd",
    "sg:city":"Melbourne",
    "sg:classifiers":[
        {
            "category":"Organizations",
            "subcategory":"Religious Organization",
            "type":"Services"
        }
    ],
    "sg:phone":"+1 321 259 7200",
    "sg:postcode":"32940",
    "sg:province":"FL",
    "sg:tags":[
        "church"
    ],
    "wof:name":"Faith Fellowship Academy",
    "wof:placetype":"venue"
},
  "geometry": {"coordinates":[-80.668358,28.193945],"type":"Point"}
}