{
  "type": "Feature",
  "properties": {
    "iso:country":"US",
    "sg:address":"4102 Helene Pl",
    "sg:city":"Valrico",
    "sg:classifiers":[
        {
            "category":"Health Services",
            "subcategory":"Health Practitioner",
            "type":"Services"
        }
    ],
    "sg:phone":"+1 813 655 1175",
    "sg:postcode":"33594",
    "sg:province":"FL",
    "sg:tags":[
        "midwife"
    ],
    "sg:website":"www.specialdeliverydoula.com",
    "wof:name":"Special Delivery Doula Birth",
    "wof:placetype":"venue"
},
  "geometry": {"coordinates":[-82.231427,27.912473],"type":"Point"}
}