{
  "type": "Feature",
  "properties": {
    "iso:country":"US",
    "sg:address":"3670 NW 183rd St",
    "sg:city":"Miami Gardens",
    "sg:classifiers":[
        {
            "category":"Retail",
            "subcategory":"Auto Repair",
            "type":"Services"
        }
    ],
    "sg:phone":"+1 786 267 6751",
    "sg:postcode":"33056",
    "sg:province":"FL",
    "wof:name":"L & D Auto Service Inc",
    "wof:placetype":"venue"
},
  "geometry": {"coordinates":[-80.26105099999999,25.940103],"type":"Point"}
}