{
  "type": "Feature",
  "properties": {
    "addr:full":"2451 NE 4th Ave Pompano Beach FL 33064",
    "addr:housenumber":"2451",
    "addr:postcode":"33064",
    "addr:street":"Ne 4Th Ave",
    "iso:country":"US",
    "sg:address":"2451 NE 4th Ave",
    "sg:city":"Pompano Beach",
    "sg:classifiers":[
        {
            "category":"Utilities",
            "subcategory":"Fuel Oil & Lpg",
            "type":"Services"
        }
    ],
    "sg:phone":"+1 954 421 9203",
    "sg:postcode":"33064",
    "sg:province":"FL",
    "sg:tags":[
        "liquefied",
        "gas",
        "petroleum"
    ],
    "wof:name":"Sidney H Savelle",
    "wof:placetype":"venue"
},
  "geometry": {"coordinates":[-80.116516,26.262133],"type":"Point"}
}