{
  "type": "Feature",
  "properties": {
    "addr:full":"1601 NW 29th St Miami FL 33142",
    "addr:housenumber":"1601",
    "addr:postcode":"33142",
    "addr:street":"Nw 29Th St",
    "iso:country":"US",
    "sg:address":"1601 NW 29th St",
    "sg:city":"Miami",
    "sg:classifiers":[
        {
            "category":"Retail",
            "subcategory":"Self-service Laundry",
            "type":"Services"
        }
    ],
    "sg:phone":"+1 305 634 4332",
    "sg:postcode":"33142",
    "sg:province":"FL",
    "wof:name":"LA Mia Coin Laundry",
    "wof:placetype":"venue"
},
  "geometry": {"coordinates":[-80.223615,25.803084],"type":"Point"}
}