{
  "type": "Feature",
  "properties": {
    "addr:full":"300 Aragon Ave Coral Gables FL 33134",
    "addr:housenumber":"300",
    "addr:postcode":"33134",
    "addr:street":"Aragon Ave",
    "iso:country":"US",
    "sg:address":"300 Aragon Ave",
    "sg:city":"Coral Gables",
    "sg:classifiers":[
        {
            "category":"Professional",
            "subcategory":"Lawyer & Legal Services",
            "type":"Services"
        }
    ],
    "sg:phone":"+1 305 442 1522",
    "sg:postcode":"33134",
    "sg:province":"FL",
    "sg:tags":[
        "attorney"
    ],
    "wof:name":"Richard Houlihan Law Office",
    "wof:placetype":"venue"
},
  "geometry": {"coordinates":[-80.26274600000001,25.750245],"type":"Point"}
}