{
  "type": "Feature",
  "properties": {
    "addr:full":"517 Roper Pkwy Ocoee FL 34761",
    "addr:housenumber":"517",
    "addr:postcode":"34761",
    "addr:street":"Roper Pkwy",
    "iso:country":"US",
    "sg:address":"517 Roper Pkwy",
    "sg:city":"Ocoee",
    "sg:classifiers":[
        {
            "category":"Wholesale",
            "subcategory":"Motor Vehicles",
            "type":"Manufacturing & Wholesale Goods"
        }
    ],
    "sg:phone":"+1 407 877 3000",
    "sg:postcode":"34761",
    "sg:province":"FL",
    "sg:tags":[
        "automobile",
        "used"
    ],
    "wof:name":"United Motor Company Inc",
    "wof:placetype":"venue"
},
  "geometry": {"coordinates":[-81.556713,28.562251],"type":"Point"}
}