{
  "type": "Feature",
  "properties": {
    "iso:country":"US",
    "sg:address":"3017 Highway 178",
    "sg:city":"Jay",
    "sg:classifiers":[
        {
            "category":"Professional",
            "subcategory":"Management & Consulting",
            "type":"Services"
        }
    ],
    "sg:phone":"+1 850 675 6053",
    "sg:postcode":"32565",
    "sg:province":"FL",
    "sg:tags":[
        "farm"
    ],
    "wof:name":"Inez Godwin",
    "wof:placetype":"venue"
},
  "geometry": {"coordinates":[-87.171299,30.837216],"type":"Point"}
}