{
  "type": "Feature",
  "properties": {
    "iso:country":"US",
    "sg:address":"642 Eyster Blvd",
    "sg:city":"Rockledge",
    "sg:classifiers":[
        {
            "category":"Shopping",
            "subcategory":"Jewelry",
            "type":"Retail Goods"
        }
    ],
    "sg:phone":"+1 321 632 7216",
    "sg:postcode":"32955",
    "sg:province":"FL",
    "wof:name":"G&R Wholesale Jewelry Outlet",
    "wof:placetype":"venue"
},
  "geometry": {"coordinates":[-80.733221,28.324247],"type":"Point"}
}