{
  "type": "Feature",
  "properties": {
    "iso:country":"US",
    "sg:address":"124 Corkwood Blvd",
    "sg:city":"Homosassa",
    "sg:classifiers":[
        {
            "category":"Wholesale",
            "subcategory":"Chemicals & Plastics",
            "type":"Manufacturing & Wholesale Goods"
        }
    ],
    "sg:phone":"+1 352 621 3777",
    "sg:postcode":"34446",
    "sg:province":"FL",
    "wof:name":"Seabrook Industries Inc",
    "wof:placetype":"venue"
},
  "geometry": {"coordinates":[-82.50794,28.734276],"type":"Point"}
}