{
  "type": "Feature",
  "properties": {
    "iso:country":"US",
    "sg:address":"913 Spearing St",
    "sg:city":"Jacksonville",
    "sg:classifiers":[
        {
            "category":"Personal",
            "subcategory":"Beauty Salon",
            "type":"Services"
        }
    ],
    "sg:phone":"+1 904 791 3004",
    "sg:postcode":"32206",
    "sg:province":"FL",
    "wof:name":"Hair By Katrina",
    "wof:placetype":"venue"
},
  "geometry": {"coordinates":[-81.644021,30.333178],"type":"Point"}
}