{
  "type": "Feature",
  "properties": {
    "addr:full":"4297 Cattlemen Rd Sarasota FL 34233",
    "addr:housenumber":"4297",
    "addr:postcode":"34233",
    "addr:street":"Cattlemen Rd",
    "iso:country":"US",
    "sg:address":"4297 Cattlemen Rd",
    "sg:city":"Sarasota",
    "sg:classifiers":[
        {
            "category":"Ice Cream",
            "type":"Food & Drink"
        }
    ],
    "sg:menulink":"http://www.allmenus.com/fl/sarasota/92384-steak-n-shake/menu/",
    "sg:phone":"+1 941 378 4405",
    "sg:postcode":"34233",
    "sg:province":"FL",
    "sg:tags":[
        "american"
    ],
    "wof:name":"Steak 'n Shake",
    "wof:placetype":"venue"
},
  "geometry": {"coordinates":[-82.45175999999999,27.293245],"type":"Point"}
}