{
  "type": "Feature",
  "properties": {
    "iso:country":"US",
    "sg:address":"900 Sunrise Ln",
    "sg:city":"Fort Lauderdale",
    "sg:classifiers":[
        {
            "category":"Restaurant",
            "type":"Food & Drink"
        }
    ],
    "sg:phone":"+1 954 567 2955",
    "sg:postcode":"33304",
    "sg:province":"FL",
    "sg:tags":[
        "eating"
    ],
    "wof:name":"Bikini Bobs All Night Cafe",
    "wof:placetype":"venue"
},
  "geometry": {"coordinates":[-80.103966,26.138043],"type":"Point"}
}