{
  "type": "Feature",
  "properties": {
    "iso:country":"US",
    "sg:address":"306 Centre St",
    "sg:city":"Fernandina Beach",
    "sg:classifiers":[
        {
            "category":"Shopping",
            "subcategory":"Gifts & Souvenirs",
            "type":"Retail Goods"
        }
    ],
    "sg:phone":"+1 904 277 8009",
    "sg:postcode":"32034",
    "sg:province":"FL",
    "sg:tags":[
        "shop"
    ],
    "wof:name":"Celtic Charm",
    "wof:placetype":"venue"
},
  "geometry": {"coordinates":[-81.462936,30.671139],"type":"Point"}
}