{
  "type": "Feature",
  "properties": {
    "iso:country":"US",
    "sg:address":"2844 Arbutus St",
    "sg:city":"Naples",
    "sg:classifiers":[
        {
            "category":"Building & Trades",
            "subcategory":"Construction",
            "type":"Services"
        }
    ],
    "sg:phone":"+1 239 417 1460",
    "sg:postcode":"34112",
    "sg:province":"FL",
    "sg:tags":[
        "house"
    ],
    "wof:name":"Steve Shinebarger Mntnc Svc",
    "wof:placetype":"venue"
},
  "geometry": {"coordinates":[-81.775721,26.126924],"type":"Point"}
}