{
  "type": "Feature",
  "properties": {
    "addr:full":"5520 Wilkins Rd Tampa FL 33610",
    "addr:housenumber":"5520",
    "addr:postcode":"33610",
    "addr:street":"Wilkins Rd",
    "iso:country":"US",
    "sg:address":"5520 Wilkins Rd",
    "sg:city":"Tampa",
    "sg:classifiers":[
        {
            "category":"Shopping",
            "subcategory":"Hobbies, Toys, & Games",
            "type":"Retail Goods"
        }
    ],
    "sg:phone":"+1 813 664 9684",
    "sg:postcode":"33610",
    "sg:province":"FL",
    "sg:tags":[
        "doll"
    ],
    "sg:website":"www.cherylsdolls.com",
    "wof:name":"Cheryl's Dolls & Collectibles",
    "wof:placetype":"venue"
},
  "geometry": {"coordinates":[-82.347273,28.003302],"type":"Point"}
}