{
  "type": "Feature",
  "properties": {
    "iso:country":"US",
    "sg:address":"117 Flagship Dr",
    "sg:city":"Lutz",
    "sg:classifiers":[
        {
            "category":"Place Of Worship",
            "type":"Public Place"
        }
    ],
    "sg:phone":"+1 813 948 9800",
    "sg:postcode":"33549",
    "sg:province":"FL",
    "sg:tags":[
        "church"
    ],
    "wof:name":"House of God Casa De Dios",
    "wof:placetype":"venue"
},
  "geometry": {"coordinates":[-82.462701,28.13903],"type":"Point"}
}