{
  "type": "Feature",
  "properties": {
    "iso:country":"US",
    "sg:address":"520 Lanyard Ln",
    "sg:city":"Debary",
    "sg:classifiers":[
        {
            "category":"Banks & Credit Unions",
            "subcategory":"Financial Services",
            "type":"Services"
        }
    ],
    "sg:phone":"+1 386 668 1801",
    "sg:postcode":"32713",
    "sg:province":"FL",
    "sg:tags":[
        "broker",
        "mortgage"
    ],
    "wof:name":"Sovereign Mortgage Investments Inc Llc",
    "wof:placetype":"venue"
},
  "geometry": {"coordinates":[-81.281018,28.902861],"type":"Point"}
}