{
  "type": "Feature",
  "properties": {
    "iso:country":"US",
    "sg:address":"17131 NW 9th Pl",
    "sg:city":"Miami",
    "sg:classifiers":[
        {
            "category":"Building & Trades",
            "subcategory":"Pest Control",
            "type":"Services"
        }
    ],
    "sg:phone":"+1 305 622 7378",
    "sg:postcode":"33169",
    "sg:province":"FL",
    "wof:name":"Aerotech Pest Control",
    "wof:placetype":"venue"
},
  "geometry": {"coordinates":[-80.218147,25.931446],"type":"Point"}
}