{
  "type": "Feature",
  "properties": {
    "iso:country":"US",
    "sg:address":"873 W Bloomingdale Ave",
    "sg:city":"Brandon",
    "sg:classifiers":[
        {
            "category":"Shopping",
            "subcategory":"Used Merchandise",
            "type":"Retail Goods"
        }
    ],
    "sg:phone":"+1 813 662 3726",
    "sg:postcode":"33511",
    "sg:province":"FL",
    "wof:name":"From Our Closet To Yours",
    "wof:placetype":"venue"
},
  "geometry": {"coordinates":[-82.295698,27.893527],"type":"Point"}
}