{
  "type": "Feature",
  "properties": {
    "addr:full":"27090 Hickory Blvd Bonita Springs FL 34134",
    "addr:housenumber":"27090",
    "addr:postcode":"34134",
    "addr:street":"Hickory Blvd",
    "iso:country":"US",
    "sg:address":"27090 Hickory Blvd",
    "sg:city":"Bonita Springs",
    "sg:classifiers":[
        {
            "category":"Wholesale",
            "subcategory":"Home Furnishings",
            "type":"Manufacturing & Wholesale Goods"
        }
    ],
    "sg:phone":"+1 239 992 8477",
    "sg:postcode":"34134",
    "sg:province":"FL",
    "sg:tags":[
        "picture",
        "frame"
    ],
    "wof:name":"David H Jones Inc",
    "wof:placetype":"venue"
},
  "geometry": {"coordinates":[-81.850606,26.343446],"type":"Point"}
}