{
  "type": "Feature",
  "properties": {
    "addr:full":"2513 Mountain Lake Cutoff Rd Lake Wales FL 33859",
    "addr:housenumber":"2513",
    "addr:postcode":"33859",
    "addr:street":"Mountain Lake Cutoff Rd",
    "iso:country":"US",
    "sg:address":"2513 Mountain Lake Cutoff Rd",
    "sg:city":"Lake Wales",
    "sg:classifiers":[
        {
            "category":"Farming",
            "subcategory":"Livestock Farm",
            "type":"Manufacturing & Wholesale Goods"
        },
        {
            "category":"Farming",
            "subcategory":"Farm & Veterinary Services",
            "type":"Manufacturing & Wholesale Goods"
        }
    ],
    "sg:phone":"+1 863 676 1763",
    "sg:postcode":"33859",
    "sg:province":"FL",
    "sg:tags":[
        "ranch"
    ],
    "wof:name":"Oak Knoll Ranch Inc",
    "wof:placetype":"venue"
},
  "geometry": {"coordinates":[-81.62976500000001,27.924108],"type":"Point"}
}