{
  "type": "Feature",
  "properties": {
    "iso:country":"US",
    "sg:address":"4685 Tamiami Trl N",
    "sg:city":"Naples",
    "sg:classifiers":[
        {
            "category":"Professional",
            "subcategory":"Management & Consulting",
            "type":"Services"
        }
    ],
    "sg:phone":"+1 239 348 2295",
    "sg:postcode":"34103",
    "sg:province":"FL",
    "wof:name":"Osgood John Nrmuscular Therapy",
    "wof:placetype":"venue"
},
  "geometry": {"coordinates":[-81.80036200000001,26.203897],"type":"Point"}
}