{
  "type": "Feature",
  "properties": {
    "iso:country":"US",
    "sg:address":"4573 Enterprise Ave",
    "sg:city":"Naples",
    "sg:classifiers":[
        {
            "category":"Building & Trades",
            "subcategory":"Construction",
            "type":"Services"
        }
    ],
    "sg:phone":"+1 239 643 4960",
    "sg:postcode":"34104",
    "sg:province":"FL",
    "sg:tags":[
        "high",
        "remodeling",
        "rise",
        "design",
        "condominium"
    ],
    "wof:name":"Incorvati Tony R Bldg Contr",
    "wof:placetype":"venue"
},
  "geometry": {"coordinates":[-81.75735,26.160787],"type":"Point"}
}