{
  "type": "Feature",
  "properties": {
    "iso:country":"US",
    "sg:address":"904 Gamble St",
    "sg:city":"Tallahassee",
    "sg:classifiers":[
        {
            "category":"Professional",
            "type":"Services"
        }
    ],
    "sg:phone":"+1 850 574 1123",
    "sg:postcode":"32310",
    "sg:province":"FL",
    "wof:name":"GE Armstrong Inc",
    "wof:placetype":"venue"
},
  "geometry": {"coordinates":[-84.29815600000001,30.428632],"type":"Point"}
}