{
  "type": "Feature",
  "properties": {
    "addr:full":"12655 Race Track Rd Tampa FL 33626",
    "addr:housenumber":"12655",
    "addr:postcode":"33626",
    "addr:street":"Race Track Rd",
    "iso:country":"US",
    "sg:address":"12655 Race Track Rd",
    "sg:city":"Tampa",
    "sg:classifiers":[
        {
            "category":"Professional",
            "subcategory":"Computer Services",
            "type":"Services"
        }
    ],
    "sg:phone":"+1 813 925 0700",
    "sg:postcode":"33626",
    "sg:province":"FL",
    "sg:tags":[
        "development",
        "training",
        "software"
    ],
    "wof:name":"Boson Software & Training",
    "wof:placetype":"venue"
},
  "geometry": {"coordinates":[-82.63764500000001,28.065574],"type":"Point"}
}