{
  "type": "Feature",
  "properties": {
    "iso:country":"US",
    "sg:address":"3800 S Ocean Dr",
    "sg:city":"Hollywood",
    "sg:classifiers":[
        {
            "category":"Personal",
            "subcategory":"Beauty Salon",
            "type":"Services"
        }
    ],
    "sg:phone":"+1 954 456 1846",
    "sg:postcode":"33019",
    "sg:province":"FL",
    "wof:name":"Riccardo Of Rome Hair Stylists",
    "wof:placetype":"venue"
},
  "geometry": {"coordinates":[-80.11834399999999,25.996847],"type":"Point"}
}