{
  "type": "Feature",
  "properties": {
    "addr:full":"4801 Kempston Dr Orlando FL 32812",
    "addr:housenumber":"4801",
    "addr:postcode":"32812",
    "addr:street":"Kempston Dr",
    "iso:country":"US",
    "sg:address":"4801 Kempston Dr",
    "sg:city":"Orlando",
    "sg:classifiers":[
        {
            "category":"Retail",
            "subcategory":"Laundry & Dry Cleaning",
            "type":"Services"
        }
    ],
    "sg:phone":"+1 407 281 1649",
    "sg:postcode":"32812",
    "sg:province":"FL",
    "sg:tags":[
        "drycleaning",
        "plant"
    ],
    "wof:name":"Silk Feather Cleaners",
    "wof:placetype":"venue"
},
  "geometry": {"coordinates":[-81.31536,28.485215],"type":"Point"}
}