{
  "type": "Feature",
  "properties": {
    "addr:full":"323 Oak St Ste 1A Palatka FL 32177",
    "addr:housenumber":"323",
    "addr:postcode":"32177",
    "addr:street":"Oak St Ste 1A",
    "iso:country":"US",
    "sg:address":"323 Oak St Ste 1A",
    "sg:city":"Palatka",
    "sg:classifiers":[
        {
            "category":"Government",
            "subcategory":"Office",
            "type":"Public Place"
        }
    ],
    "sg:phone":"+1 386 329 0286",
    "sg:postcode":"32177",
    "sg:province":"FL",
    "sg:website":"http://www.putnam-fl.com",
    "wof:name":"Putnam Cnty Property Apraiser",
    "wof:placetype":"venue"
},
  "geometry": {"coordinates":[-81.63214499999999,29.645869],"type":"Point"}
}