{
  "type": "Feature",
  "properties": {
    "iso:country":"US",
    "sg:address":"2259 6th St",
    "sg:city":"Sarasota",
    "sg:classifiers":[
        {
            "category":"Retail",
            "subcategory":"Animal Services",
            "type":"Services"
        }
    ],
    "sg:phone":"+1 941 365 9182",
    "sg:postcode":"34237",
    "sg:province":"FL",
    "wof:name":"Bark Place",
    "wof:placetype":"venue"
},
  "geometry": {"coordinates":[-82.524322,27.341207],"type":"Point"}
}