{
  "type": "Feature",
  "properties": {
    "addr:full":"3781 Oak Glenn Ct Milton FL 32571",
    "addr:housenumber":"3781",
    "addr:postcode":"32571",
    "addr:street":"Oak Glenn Ct",
    "iso:country":"US",
    "sg:address":"3781 Oak Glenn Ct",
    "sg:city":"Milton",
    "sg:classifiers":[
        {
            "category":"Building & Trades",
            "subcategory":"Landscaping Services",
            "type":"Services"
        }
    ],
    "sg:phone":"+1 850 994 3179",
    "sg:postcode":"32571",
    "sg:province":"FL",
    "sg:tags":[
        "tree"
    ],
    "wof:name":"Affordable Stump Grinding",
    "wof:placetype":"venue"
},
  "geometry": {"coordinates":[-87.165795,30.624418],"type":"Point"}
}