{
  "type": "Feature",
  "properties": {
    "iso:country":"US",
    "sg:address":"200 Towne Center Cir",
    "sg:city":"Sanford",
    "sg:classifiers":[
        {
            "category":"Shopping",
            "subcategory":"Clothing, Apparel, & Fashions",
            "type":"Retail Goods"
        }
    ],
    "sg:phone":"+1 407 321 6786",
    "sg:postcode":"32771",
    "sg:province":"FL",
    "sg:tags":[
        "handbag"
    ],
    "wof:name":"Honey Handbags & More",
    "wof:placetype":"venue"
},
  "geometry": {"coordinates":[-81.336972,28.808786],"type":"Point"}
}