{
  "type": "Feature",
  "properties": {
    "addr:full":"501 N Beneva Rd Sarasota FL 34232",
    "addr:housenumber":"501",
    "addr:postcode":"34232",
    "addr:street":"N Beneva Rd",
    "iso:country":"US",
    "sg:address":"501 N Beneva Rd",
    "sg:city":"Sarasota",
    "sg:phone":"+1 941 365 4610",
    "sg:postcode":"34232",
    "sg:province":"FL",
    "wof:name":"Sherwin-Williams",
    "wof:placetype":"venue"
},
  "geometry": {"coordinates":[-82.497383,27.3412],"type":"Point"}
}