{
  "type": "Feature",
  "properties": {
    "iso:country":"US",
    "sg:address":"6899 N Cocoa Blvd",
    "sg:city":"Cocoa",
    "sg:classifiers":[
        {
            "category":"Banks & Credit Unions",
            "subcategory":"Bank",
            "type":"Services"
        }
    ],
    "sg:phone":"+1 321 638 2020",
    "sg:postcode":"32927",
    "sg:province":"FL",
    "wof:name":"Coastal Bank",
    "wof:placetype":"venue"
},
  "geometry": {"coordinates":[-80.767151,28.473112],"type":"Point"}
}