{
  "type": "Feature",
  "properties": {
    "iso:country":"US",
    "sg:address":"415 E Hallandale Beach Blvd",
    "sg:city":"Hallandale Beach",
    "sg:classifiers":[
        {
            "category":"Professional",
            "subcategory":"Management & Consulting",
            "type":"Services"
        }
    ],
    "sg:phone":"+1 954 454 1982",
    "sg:postcode":"33009",
    "sg:province":"FL",
    "sg:tags":[
        "consultant",
        "lighting"
    ],
    "wof:name":"Ceiling Fan Warehouse",
    "wof:placetype":"venue"
},
  "geometry": {"coordinates":[-80.143372,25.985805],"type":"Point"}
}