{
  "type": "Feature",
  "properties": {
    "iso:country":"US",
    "sg:address":"2609 S Sanford Ave",
    "sg:city":"Sanford",
    "sg:classifiers":[
        {
            "category":"Building & Trades",
            "subcategory":"Cleaning & Sanitation",
            "type":"Services"
        },
        {
            "category":"Retail",
            "subcategory":"Laundry & Dry Cleaning",
            "type":"Services"
        }
    ],
    "sg:phone":"+1 407 936 1172",
    "sg:postcode":"32773",
    "sg:province":"FL",
    "sg:tags":[
        "cleaner",
        "floor",
        "rug",
        "waxing",
        "polishing",
        "carpet"
    ],
    "wof:name":"Job Masters Inc",
    "wof:placetype":"venue"
},
  "geometry": {"coordinates":[-81.26476700000001,28.781506],"type":"Point"}
}