{
  "type": "Feature",
  "properties": {
    "iso:country":"US",
    "sg:address":"5014 S Dale Mabry Hwy",
    "sg:city":"Tampa",
    "sg:phone":"+1 727 597 4822",
    "sg:postcode":"33611",
    "sg:province":"FL",
    "wof:name":"Precision Garage Door - Mabry Hwy Tampa",
    "wof:placetype":"venue"
},
  "geometry": {"coordinates":[-82.50630200000001,27.89119],"type":"Point"}
}