{
  "type": "Feature",
  "properties": {
    "iso:country":"US",
    "sg:address":"1820 NE 50th Ave",
    "sg:city":"Ocala",
    "sg:classifiers":[
        {
            "category":"Arts & Performance",
            "subcategory":"Theater",
            "type":"Entertainment"
        }
    ],
    "sg:phone":"+1 352 236 4505",
    "sg:postcode":"34470",
    "sg:province":"FL",
    "sg:tags":[
        "live",
        "music"
    ],
    "wof:name":"James Gagnon Disc Jockey",
    "wof:placetype":"venue"
},
  "geometry": {"coordinates":[-82.066913,29.204157],"type":"Point"}
}