{
  "type": "Feature",
  "properties": {
    "addr:full":"1399 Culbreath Rd Brooksville FL 34602",
    "addr:housenumber":"1399",
    "addr:postcode":"34602",
    "addr:street":"Culbreath Rd",
    "iso:country":"US",
    "sg:address":"1399 Culbreath Rd",
    "sg:city":"Brooksville",
    "sg:classifiers":[
        {
            "category":"Building & Trades",
            "subcategory":"Landscaping Services",
            "type":"Services"
        }
    ],
    "sg:phone":"+1 352 799 8526",
    "sg:postcode":"34602",
    "sg:province":"FL",
    "wof:name":"Clayton Termite & Pest Control",
    "wof:placetype":"venue"
},
  "geometry": {"coordinates":[-82.370784,28.454794],"type":"Point"}
}