{
  "type": "Feature",
  "properties": {
    "addr:full":"1000 12th Ave N Saint Petersburg FL 33705",
    "addr:housenumber":"1000",
    "addr:postcode":"33705",
    "addr:street":"12Th Ave N",
    "iso:country":"US",
    "sg:address":"1000 12th Ave N",
    "sg:city":"Saint Petersburg",
    "sg:classifiers":[
        {
            "category":"Health Services",
            "subcategory":"Clinic",
            "type":"Services"
        }
    ],
    "sg:phone":"+1 727 577 3122",
    "sg:postcode":"33705",
    "sg:province":"FL",
    "sg:tags":[
        "home",
        "care"
    ],
    "wof:name":"Lifecare Solutions East Inc",
    "wof:placetype":"venue"
},
  "geometry": {"coordinates":[-82.64881099999999,27.7835],"type":"Point"}
}