{
  "type": "Feature",
  "properties": {
    "addr:full":"11869 Woodtones Ln Boca Raton FL 33428",
    "addr:housenumber":"11869",
    "addr:postcode":"33428",
    "addr:street":"Woodtones Ln",
    "iso:country":"US",
    "sg:address":"11869 Woodtones Ln",
    "sg:city":"Boca Raton",
    "sg:classifiers":[
        {
            "category":"Freight",
            "type":"Transportation"
        }
    ],
    "sg:phone":"+1 561 487 8849",
    "sg:postcode":"33428",
    "sg:province":"FL",
    "wof:name":"J Devlin Global Logistics Inc",
    "wof:placetype":"venue"
},
  "geometry": {"coordinates":[-80.229815,26.364275],"type":"Point"}
}