{
  "type": "Feature",
  "properties": {
    "iso:country":"US",
    "sg:address":"225 Water St Ste 1280",
    "sg:city":"Jacksonville",
    "sg:classifiers":[
        {
            "category":"Professional",
            "subcategory":"Lawyer & Legal Services",
            "type":"Services"
        }
    ],
    "sg:phone":"+1 904 854 0550",
    "sg:postcode":"32202",
    "sg:province":"FL",
    "sg:tags":[
        "attorney"
    ],
    "wof:name":"Kelly B. Mathis, P.A.",
    "wof:placetype":"venue"
},
  "geometry": {"coordinates":[-81.66135199999999,30.325362],"type":"Point"}
}