{
  "type": "Feature",
  "properties": {
    "iso:country":"US",
    "sg:address":"203 State Hwy 207",
    "sg:city":"East Palatka",
    "sg:classifiers":[
        {
            "category":"Freight",
            "type":"Transportation"
        }
    ],
    "sg:phone":"+1 386 530 0640",
    "sg:postcode":"32131",
    "sg:province":"FL",
    "sg:tags":[
        "trucking"
    ],
    "wof:name":"Rios & Sons Trucking Inc",
    "wof:placetype":"venue"
},
  "geometry": {"coordinates":[-81.593638,29.662243],"type":"Point"}
}