{
  "type": "Feature",
  "properties": {
    "iso:country":"US",
    "sg:address":"431 Briarwood Rd",
    "sg:city":"Venice",
    "sg:classifiers":[
        {
            "category":"Building & Trades",
            "subcategory":"Landscaping Services",
            "type":"Services"
        }
    ],
    "sg:phone":"+1 941 493 6772",
    "sg:postcode":"34293",
    "sg:province":"FL",
    "sg:tags":[
        "lawn",
        "maintenance",
        "grounds"
    ],
    "wof:name":"Richard Calkins Lawn Service",
    "wof:placetype":"venue"
},
  "geometry": {"coordinates":[-82.41158799999999,27.068483],"type":"Point"}
}