{
  "type": "Feature",
  "properties": {
    "iso:country":"US",
    "sg:address":"4610 Poinsettia Ave",
    "sg:city":"Tampa",
    "sg:classifiers":[
        {
            "category":"Organizations",
            "subcategory":"Religious Organization",
            "type":"Services"
        }
    ],
    "sg:phone":"+1 813 988 8992",
    "sg:postcode":"33617",
    "sg:province":"FL",
    "wof:name":"Linda Bradshaw Ministries Inc",
    "wof:placetype":"venue"
},
  "geometry": {"coordinates":[-82.408333,28.041722],"type":"Point"}
}