{
  "type": "Feature",
  "properties": {
    "iso:country":"US",
    "sg:address":"450 Hammond Blvd",
    "sg:city":"Jacksonville",
    "sg:classifiers":[
        {
            "category":"Wholesale",
            "subcategory":"Motor Vehicles",
            "type":"Manufacturing & Wholesale Goods"
        }
    ],
    "sg:phone":"+1 904 781 3141",
    "sg:postcode":"32220",
    "sg:province":"FL",
    "sg:tags":[
        "automobile"
    ],
    "wof:name":"Copart Inc",
    "wof:placetype":"venue"
},
  "geometry": {"coordinates":[-81.786342,30.318633],"type":"Point"}
}