{
  "type": "Feature",
  "properties": {
    "iso:country":"US",
    "sg:address":"1029 Delacroix Cir",
    "sg:city":"Nokomis",
    "sg:classifiers":[
        {
            "category":"Professional",
            "subcategory":"Accounting & Tax Preparation",
            "type":"Services"
        }
    ],
    "sg:phone":"+1 941 485 0225",
    "sg:postcode":"34275",
    "sg:province":"FL",
    "sg:tags":[
        "accountant"
    ],
    "wof:name":"John Laudenslager PA",
    "wof:placetype":"venue"
},
  "geometry": {"coordinates":[-82.43384500000001,27.144113],"type":"Point"}
}