{
  "type": "Feature",
  "properties": {
    "iso:country":"US",
    "sg:address":"11460 Pines Blvd",
    "sg:city":"Hollywood",
    "sg:classifiers":[
        {
            "category":"Personal",
            "type":"Services"
        }
    ],
    "sg:phone":"+1 954 450 4990",
    "sg:postcode":"33026",
    "sg:province":"FL",
    "wof:name":"Party City",
    "wof:placetype":"venue"
},
  "geometry": {"coordinates":[-80.301107,26.007759],"type":"Point"}
}