{
  "type": "Feature",
  "properties": {
    "addr:full":"235 Crandon Blvd Key Biscayne FL 33149",
    "addr:housenumber":"235",
    "addr:postcode":"33149",
    "addr:street":"Crandon Blvd",
    "iso:country":"US",
    "sg:address":"235 Crandon Blvd",
    "sg:city":"Key Biscayne",
    "sg:classifiers":[
        {
            "category":"Organizations",
            "subcategory":"Community Association",
            "type":"Services"
        }
    ],
    "sg:phone":"+1 305 361 6242",
    "sg:postcode":"33149",
    "sg:province":"FL",
    "wof:name":"Key Colony Homeowners Assn",
    "wof:placetype":"venue"
},
  "geometry": {"coordinates":[-80.16161700000001,25.70028],"type":"Point"}
}