{
  "type": "Feature",
  "properties": {
    "addr:full":"6375 SW 136th Ct Miami FL 33183",
    "addr:housenumber":"6375",
    "addr:postcode":"33183",
    "addr:street":"Sw 136Th Ct",
    "iso:country":"US",
    "sg:address":"6375 SW 136th Ct",
    "sg:city":"Miami",
    "sg:classifiers":[
        {
            "category":"Shopping",
            "subcategory":"Clothing, Apparel, & Fashions",
            "type":"Retail Goods"
        }
    ],
    "sg:phone":"+1 305 383 7702",
    "sg:postcode":"33183",
    "sg:province":"FL",
    "wof:name":"Fashionable Accessories Inc",
    "wof:placetype":"venue"
},
  "geometry": {"coordinates":[-80.414035,25.708968],"type":"Point"}
}