{
  "type": "Feature",
  "properties": {
    "iso:country":"US",
    "sg:address":"268 Palm Coast Pkwy NE",
    "sg:city":"Palm Coast",
    "sg:classifiers":[
        {
            "category":"Insurance",
            "subcategory":"Insurance Agent",
            "type":"Services"
        }
    ],
    "sg:phone":"+1 386 445 1111",
    "sg:postcode":"32137",
    "sg:province":"FL",
    "wof:name":"Allstate Insurance",
    "wof:placetype":"venue"
},
  "geometry": {"coordinates":[-81.194615,29.562457],"type":"Point"}
}