{
  "type": "Feature",
  "properties": {
    "iso:country":"US",
    "sg:address":"9280 Spring Run Blvd",
    "sg:city":"Bonita Springs",
    "sg:classifiers":[
        {
            "category":"Building & Trades",
            "subcategory":"Construction",
            "type":"Services"
        }
    ],
    "sg:phone":"+1 239 498 2767",
    "sg:postcode":"34135",
    "sg:province":"FL",
    "sg:tags":[
        "residential"
    ],
    "wof:name":"Ferrell Engineering Inc",
    "wof:placetype":"venue"
},
  "geometry": {"coordinates":[-81.79956300000001,26.398696],"type":"Point"}
}