{
  "type": "Feature",
  "properties": {
    "iso:country":"US",
    "sg:address":"4111 SW 47th Ave",
    "sg:city":"Davie",
    "sg:classifiers":[
        {
            "category":"Shopping",
            "subcategory":"Bicycles & Sporting Goods",
            "type":"Retail Goods"
        }
    ],
    "sg:phone":"+1 954 792 6869",
    "sg:postcode":"33314",
    "sg:province":"FL",
    "sg:tags":[
        "equipment",
        "exercise"
    ],
    "wof:name":"All Pro Fitness Equipment Svc",
    "wof:placetype":"venue"
},
  "geometry": {"coordinates":[-80.210261,26.072673],"type":"Point"}
}