{
  "type": "Feature",
  "properties": {
    "addr:full":"3712 W Walnut St Tampa FL 33607",
    "addr:housenumber":"3712",
    "addr:postcode":"33607",
    "addr:street":"W Walnut St",
    "iso:country":"US",
    "sg:address":"3712 W Walnut St",
    "sg:city":"Tampa",
    "sg:classifiers":[
        {
            "category":"Banks & Credit Unions",
            "subcategory":"Bank",
            "type":"Services"
        }
    ],
    "sg:phone":"+1 813 877 0424",
    "sg:postcode":"33607",
    "sg:province":"FL",
    "sg:tags":[
        "cashing",
        "check"
    ],
    "wof:name":"Check Point LTD",
    "wof:placetype":"venue"
},
  "geometry": {"coordinates":[-82.50424,27.960341],"type":"Point"}
}