{
  "type": "Feature",
  "properties": {
    "addr:full":"4616 NW 66th Pl Ocala FL 34482",
    "addr:housenumber":"4616",
    "addr:postcode":"34482",
    "addr:street":"Nw 66Th Pl",
    "iso:country":"US",
    "sg:address":"4616 NW 66th Pl",
    "sg:city":"Ocala",
    "sg:classifiers":[
        {
            "category":"Building & Trades",
            "subcategory":"Electrical",
            "type":"Services"
        }
    ],
    "sg:phone":"+1 352 622 9343",
    "sg:postcode":"34482",
    "sg:province":"FL",
    "sg:tags":[
        "installation"
    ],
    "wof:name":"Glenn Mikell Installation",
    "wof:placetype":"venue"
},
  "geometry": {"coordinates":[-82.194345,29.255869],"type":"Point"}
}