{
  "type": "Feature",
  "properties": {
    "iso:country":"US",
    "sg:address":"8038 Rural Retreat Ct",
    "sg:city":"Orlando",
    "sg:classifiers":[
        {
            "category":"Professional",
            "subcategory":"Management & Consulting",
            "type":"Services"
        }
    ],
    "sg:phone":"+1 407 248 0466",
    "sg:postcode":"32819",
    "sg:province":"FL",
    "sg:tags":[
        "promotion",
        "sales"
    ],
    "wof:name":"Michael Francis Assoc Inc",
    "wof:placetype":"venue"
},
  "geometry": {"coordinates":[-81.494631,28.481465],"type":"Point"}
}