{
  "type": "Feature",
  "properties": {
    "addr:full":"204 Barton Blvd Rockledge FL 32955",
    "addr:housenumber":"204",
    "addr:postcode":"32955",
    "addr:street":"Barton Blvd",
    "iso:country":"US",
    "sg:address":"204 Barton Blvd",
    "sg:city":"Rockledge",
    "sg:classifiers":[
        {
            "category":"Health Services",
            "subcategory":"Health Practitioner",
            "type":"Services"
        }
    ],
    "sg:phone":"+1 321 635 9888",
    "sg:postcode":"32955",
    "sg:province":"FL",
    "sg:tags":[
        "control",
        "weight"
    ],
    "wof:name":"Weight Management Consult",
    "wof:placetype":"venue"
},
  "geometry": {"coordinates":[-80.72511,28.33087],"type":"Point"}
}