{
  "type": "Feature",
  "properties": {
    "iso:country":"US",
    "sg:address":"2771 W State Rd 434",
    "sg:city":"Longwood",
    "sg:classifiers":[
        {
            "category":"Insurance",
            "subcategory":"Insurance Agent",
            "type":"Services"
        }
    ],
    "sg:phone":"+1 407 788 8421",
    "sg:postcode":"32779",
    "sg:province":"FL",
    "wof:name":"Joe Waresak Insurance Agency",
    "wof:placetype":"venue"
},
  "geometry": {"coordinates":[-81.411278,28.687639],"type":"Point"}
}