{
  "type": "Feature",
  "properties": {
    "iso:country":"US",
    "sg:address":"4 Old Kings Rd N",
    "sg:city":"Palm Coast",
    "sg:classifiers":[
        {
            "category":"Professional",
            "subcategory":"Lawyer & Legal Services",
            "type":"Services"
        }
    ],
    "sg:phone":"+1 386 445 8900",
    "sg:postcode":"32137",
    "sg:province":"FL",
    "sg:tags":[
        "attorney"
    ],
    "sg:website":"www.palmcoastlaw.com",
    "wof:name":"Chiumento & Assoc",
    "wof:placetype":"venue"
},
  "geometry": {"coordinates":[-81.23224999999999,29.581447],"type":"Point"}
}