{
  "type": "Feature",
  "properties": {
    "iso:country":"US",
    "sg:address":"4329 8th St SW",
    "sg:city":"Coral Gables",
    "sg:classifiers":[
        {
            "category":"Shopping",
            "subcategory":"Used Merchandise",
            "type":"Retail Goods"
        },
        {
            "category":"Shopping",
            "subcategory":"Books",
            "type":"Retail Goods"
        }
    ],
    "sg:phone":"+1 305 444 5001",
    "sg:postcode":"33134",
    "sg:province":"FL",
    "sg:tags":[
        "rare",
        "dealer"
    ],
    "wof:name":"Books and Art Prints",
    "wof:placetype":"venue"
},
  "geometry": {"coordinates":[-80.26643199999999,25.7644],"type":"Point"}
}