{
  "type": "Feature",
  "properties": {
    "addr:full":"2021 S Suncoast Blvd Homosassa FL 34448",
    "addr:housenumber":"2021",
    "addr:postcode":"34448",
    "addr:street":"S Suncoast Blvd",
    "iso:country":"US",
    "sg:address":"2021 S Suncoast Blvd",
    "sg:city":"Homosassa",
    "sg:classifiers":[
        {
            "category":"Autos & Motor Vehicles",
            "subcategory":"Automobile Sales",
            "type":"Retail Goods"
        }
    ],
    "sg:phone":"+1 352 628 9444",
    "sg:postcode":"34448",
    "sg:province":"FL",
    "sg:tags":[
        "car",
        "dealer"
    ],
    "wof:name":"Love Nissan",
    "wof:placetype":"venue"
},
  "geometry": {"coordinates":[-82.579672,28.843035],"type":"Point"}
}