{
  "type": "Feature",
  "properties": {
    "addr:full":"3300 Pga Blvd Palm Beach Gdns FL 33410",
    "addr:postcode":"3300;33410",
    "addr:street":"Pga Blvd Palm Beach Gdns",
    "iso:country":"US",
    "sg:address":"3300 Pga Blvd",
    "sg:city":"Palm Beach Gdns",
    "sg:classifiers":[
        {
            "category":"Health Services",
            "subcategory":"Doctor",
            "type":"Services"
        }
    ],
    "sg:phone":"+1 561 627 6996",
    "sg:postcode":"33410",
    "sg:province":"FL",
    "sg:tags":[
        "physician",
        "surgeon",
        "medical"
    ],
    "wof:name":"Guylaine Lancot Clinic",
    "wof:placetype":"venue"
},
  "geometry": {"coordinates":[-80.087771,26.844975],"type":"Point"}
}