{
  "type": "Feature",
  "properties": {
    "addr:full":"2535 NW 18th Ter Miami FL 33125",
    "addr:housenumber":"2535",
    "addr:postcode":"33125",
    "addr:street":"Nw 18Th Ter",
    "iso:country":"US",
    "sg:address":"2535 NW 18th Ter",
    "sg:city":"Miami",
    "sg:classifiers":[
        {
            "category":"Retail",
            "subcategory":"Repair Shop",
            "type":"Services"
        }
    ],
    "sg:phone":"+1 305 635 9706",
    "sg:postcode":"33125",
    "sg:province":"FL",
    "sg:tags":[
        "distributor",
        "boat",
        "manufacturer"
    ],
    "wof:name":"Best Yacht Repair Inc",
    "wof:placetype":"venue"
},
  "geometry": {"coordinates":[-80.237526,25.791022],"type":"Point"}
}