{
  "type": "Feature",
  "properties": {
    "iso:country":"US",
    "sg:address":"1238 E Concord St",
    "sg:city":"Orlando",
    "sg:classifiers":[
        {
            "category":"Professional",
            "subcategory":"Lawyer & Legal Services",
            "type":"Services"
        }
    ],
    "sg:phone":"+1 407 895 4705",
    "sg:postcode":"32803",
    "sg:province":"FL",
    "sg:tags":[
        "attorney",
        "criminal",
        "law"
    ],
    "sg:website":"http://www.trishcashmanlaw.com",
    "wof:name":"Cashman, Patricia A PA",
    "wof:placetype":"venue"
},
  "geometry": {"coordinates":[-81.364065,28.551317],"type":"Point"}
}