{
  "type": "Feature",
  "properties": {
    "iso:country":"US",
    "sg:address":"904 NW 1st St",
    "sg:city":"Fort Lauderdale",
    "sg:classifiers":[
        {
            "category":"Home & Garden",
            "subcategory":"Building Materials",
            "type":"Retail Goods"
        }
    ],
    "sg:phone":"+1 954 522 1750",
    "sg:postcode":"33311",
    "sg:province":"FL",
    "wof:name":"Sterling National Corp",
    "wof:placetype":"venue"
},
  "geometry": {"coordinates":[-80.154819,26.122858],"type":"Point"}
}