{
  "type": "Feature",
  "properties": {
    "iso:country":"US",
    "sg:address":"115 Tamiami Trl",
    "sg:city":"Punta Gorda",
    "sg:classifiers":[
        {
            "category":"Shopping",
            "subcategory":"Clothing, Apparel, & Fashions",
            "type":"Retail Goods"
        }
    ],
    "sg:phone":"+1 941 639 4197",
    "sg:postcode":"33950",
    "sg:province":"FL",
    "sg:tags":[
        "family",
        "store"
    ],
    "wof:name":"Bealls Outlet 101",
    "wof:placetype":"venue"
},
  "geometry": {"coordinates":[-82.050079,26.936149],"type":"Point"}
}