{
  "type": "Feature",
  "properties": {
    "iso:country":"US",
    "sg:address":"7748 SE Hwy 42",
    "sg:city":"Summerfield",
    "sg:classifiers":[
        {
            "category":"Organizations",
            "subcategory":"Religious Organization",
            "type":"Services"
        }
    ],
    "sg:phone":"+1 352 205 7114",
    "sg:postcode":"34491",
    "sg:province":"FL",
    "sg:tags":[
        "church"
    ],
    "wof:name":"First Baptist Chr At The Vllgs",
    "wof:placetype":"venue"
},
  "geometry": {"coordinates":[-82.02547,28.981875],"type":"Point"}
}