{
  "type": "Feature",
  "properties": {
    "addr:full":"1901 Cortez Rd W Bradenton FL 34207",
    "addr:housenumber":"1901",
    "addr:postcode":"34207",
    "addr:street":"Cortez Rd W",
    "iso:country":"US",
    "sg:address":"1901 Cortez Rd W",
    "sg:city":"Bradenton",
    "sg:classifiers":[
        {
            "category":"Autos & Motor Vehicles",
            "subcategory":"Automobile Sales",
            "type":"Retail Goods"
        }
    ],
    "sg:phone":"+1 941 753 2772",
    "sg:postcode":"34207",
    "sg:province":"FL",
    "sg:tags":[
        "car",
        "only",
        "used",
        "dealer"
    ],
    "wof:name":"Tippett Auto Sales Inc",
    "wof:placetype":"venue"
},
  "geometry": {"coordinates":[-82.58192699999999,27.462332],"type":"Point"}
}