{
  "type": "Feature",
  "properties": {
    "iso:country":"US",
    "sg:address":"655 W 8th St",
    "sg:city":"Jacksonville",
    "sg:classifiers":[
        {
            "category":"Health Services",
            "subcategory":"Clinic",
            "type":"Services"
        },
        {
            "category":"Social Services",
            "type":"Services"
        }
    ],
    "sg:phone":"+1 904 244 4465",
    "sg:postcode":"32209",
    "sg:province":"FL",
    "sg:tags":[
        "control",
        "center",
        "poison"
    ],
    "sg:website":"www.fpicn.org",
    "wof:name":"Florida Poison Information Ctr",
    "wof:placetype":"venue"
},
  "geometry": {"coordinates":[-81.6628,30.346463],"type":"Point"}
}