{
  "type": "Feature",
  "properties": {
    "addr:full":"4778 NE 10th Ave Fort Lauderdale FL 33334",
    "addr:housenumber":"4778",
    "addr:postcode":"33334",
    "addr:street":"Ne 10Th Ave",
    "iso:country":"US",
    "sg:address":"4778 NE 10th Ave",
    "sg:city":"Fort Lauderdale",
    "sg:classifiers":[
        {
            "category":"Building & Trades",
            "subcategory":"Plumbing",
            "type":"Services"
        }
    ],
    "sg:phone":"+1 954 566 1194",
    "sg:postcode":"33334",
    "sg:province":"FL",
    "sg:tags":[
        "plumbing",
        "heating",
        "contractor"
    ],
    "wof:name":"Borkenhagen Plumbing & Heating",
    "wof:placetype":"venue"
},
  "geometry": {"coordinates":[-80.13355,26.185463],"type":"Point"}
}