{
  "type": "Feature",
  "properties": {
    "iso:country":"US",
    "sg:address":"111 Bullard Pkwy",
    "sg:city":"Tampa",
    "sg:classifiers":[
        {
            "category":"Personal",
            "subcategory":"Beauty Salon",
            "type":"Services"
        }
    ],
    "sg:phone":"+1 813 988 1199",
    "sg:postcode":"33617",
    "sg:province":"FL",
    "sg:tags":[
        "manicuring"
    ],
    "wof:name":"Nails By Regina Washington",
    "wof:placetype":"venue"
},
  "geometry": {"coordinates":[-82.391841,28.032437],"type":"Point"}
}