{
  "type": "Feature",
  "properties": {
    "addr:full":"332 Riverbluff Dr Ormond Beach FL 32174",
    "addr:housenumber":"332",
    "addr:postcode":"32174",
    "addr:street":"Riverbluff Dr",
    "iso:country":"US",
    "sg:address":"332 Riverbluff Dr",
    "sg:city":"Ormond Beach",
    "sg:classifiers":[
        {
            "category":"Real Estate",
            "subcategory":"Real Estate Agent",
            "type":"Services"
        }
    ],
    "sg:phone":"+1 386 615 9059",
    "sg:postcode":"32174",
    "sg:province":"FL",
    "sg:tags":[
        "broker",
        "mortgage"
    ],
    "wof:name":"Tupas Realty & Mortgage",
    "wof:placetype":"venue"
},
  "geometry": {"coordinates":[-81.09938200000001,29.298368],"type":"Point"}
}