{
  "type": "Feature",
  "properties": {
    "addr:full":"4280 Spindlewick Dr Milton FL 32571",
    "addr:postcode":"4280;32571",
    "addr:street":"Spindlewick Dr",
    "iso:country":"US",
    "sg:address":"4280 Spindlewick Dr",
    "sg:city":"Milton",
    "sg:classifiers":[
        {
            "category":"Manufacturing",
            "subcategory":"Glass & Minerals",
            "type":"Manufacturing & Wholesale Goods"
        }
    ],
    "sg:phone":"+1 850 995 0891",
    "sg:postcode":"32571",
    "sg:province":"FL",
    "sg:tags":[
        "concrete",
        "mfg"
    ],
    "wof:name":"Milton Block Products Inc",
    "wof:placetype":"venue"
},
  "geometry": {"coordinates":[-87.146614,30.656845],"type":"Point"}
}