{
  "type": "Feature",
  "properties": {
    "iso:country":"US",
    "sg:address":"2800 Weston Rd",
    "sg:city":"Fort Lauderdale",
    "sg:classifiers":[
        {
            "category":"Professional",
            "subcategory":"Lawyer & Legal Services",
            "type":"Services"
        }
    ],
    "sg:phone":"+1 954 515 0013",
    "sg:postcode":"33331",
    "sg:province":"FL",
    "wof:name":"Kristine M Johnson PA",
    "wof:placetype":"venue"
},
  "geometry": {"coordinates":[-80.368358,26.081974],"type":"Point"}
}