{
  "type": "Feature",
  "properties": {
    "iso:country":"US",
    "sg:address":"2066 Thomasville Rd",
    "sg:city":"Tallahassee",
    "sg:classifiers":[
        {
            "category":"Building & Trades",
            "subcategory":"Construction",
            "type":"Services"
        }
    ],
    "sg:phone":"+1 850 556 0511",
    "sg:postcode":"32308",
    "sg:province":"FL",
    "sg:tags":[
        "repairing",
        "remodeling",
        "contractor"
    ],
    "wof:name":"John Kepler A Handyman To Know",
    "wof:placetype":"venue"
},
  "geometry": {"coordinates":[-84.26601700000001,30.471271],"type":"Point"}
}