{
  "type": "Feature",
  "properties": {
    "addr:full":"1242 Fairview Ave Winter Park FL 32789",
    "addr:housenumber":"1242",
    "addr:postcode":"32789",
    "addr:street":"Fairview Ave",
    "iso:country":"US",
    "sg:address":"1242 Fairview Ave",
    "sg:city":"Winter Park",
    "sg:classifiers":[
        {
            "category":"Professional",
            "subcategory":"Employment Agencies",
            "type":"Services"
        }
    ],
    "sg:phone":"+1 407 622 8901",
    "sg:postcode":"32789",
    "sg:province":"FL",
    "sg:tags":[
        "opportunity"
    ],
    "sg:website":"www.constructcorp.com",
    "wof:name":"Construct Corps",
    "wof:placetype":"venue"
},
  "geometry": {"coordinates":[-81.365709,28.595698],"type":"Point"}
}