{
  "type": "Feature",
  "properties": {
    "addr:full":"1691 NW 23rd St Miami FL 33142",
    "addr:housenumber":"1691",
    "addr:postcode":"33142",
    "addr:street":"Nw 23Rd St",
    "iso:country":"US",
    "sg:address":"1691 NW 23rd St",
    "sg:city":"Miami",
    "sg:classifiers":[
        {
            "category":"Manufacturing",
            "subcategory":"Wood Products",
            "type":"Manufacturing & Wholesale Goods"
        }
    ],
    "sg:phone":"+1 305 634 0346",
    "sg:postcode":"33142",
    "sg:province":"FL",
    "sg:tags":[
        "pallet",
        "mfg"
    ],
    "wof:name":"Tropical Pallets Inc",
    "wof:placetype":"venue"
},
  "geometry": {"coordinates":[-80.221665,25.798594],"type":"Point"}
}