{
  "type": "Feature",
  "properties": {
    "iso:country":"US",
    "sg:address":"3215 Phillips Hwy",
    "sg:city":"Jacksonville",
    "sg:classifiers":[
        {
            "category":"Autos & Motor Vehicles",
            "subcategory":"Automobile Sales",
            "type":"Retail Goods"
        }
    ],
    "sg:phone":"+1 904 346 4403",
    "sg:postcode":"32207",
    "sg:province":"FL",
    "sg:tags":[
        "car",
        "used",
        "dealer"
    ],
    "wof:name":"Jimmy's Auto Sales",
    "wof:placetype":"venue"
},
  "geometry": {"coordinates":[-81.640717,30.297574],"type":"Point"}
}