{
  "type": "Feature",
  "properties": {
    "iso:country":"US",
    "sg:address":"7699 Co Rd 133",
    "sg:city":"Wildwood",
    "sg:classifiers":[
        {
            "category":"Building & Trades",
            "subcategory":"Electrical",
            "type":"Services"
        }
    ],
    "sg:phone":"+1 352 330 0003",
    "sg:postcode":"34785",
    "sg:province":"FL",
    "sg:tags":[
        "electric",
        "contractor"
    ],
    "wof:name":"Burns Electric",
    "wof:placetype":"venue"
},
  "geometry": {"coordinates":[-82.008095,28.868614],"type":"Point"}
}