{
  "type": "Feature",
  "properties": {
    "addr:full":"4001 Santa Barbara Rd Kissimmee FL 34746",
    "addr:housenumber":"4001",
    "addr:postcode":"34746",
    "addr:street":"Santa Barbara Rd",
    "iso:country":"US",
    "sg:address":"4001 Santa Barbara Rd",
    "sg:city":"Kissimmee",
    "sg:classifiers":[
        {
            "category":"Wholesale",
            "subcategory":"Construction Materials",
            "type":"Manufacturing & Wholesale Goods"
        }
    ],
    "sg:phone":"+1 407 847 2721",
    "sg:postcode":"34746",
    "sg:province":"FL",
    "sg:tags":[
        "lumber"
    ],
    "wof:name":"Cari Pine Inc",
    "wof:placetype":"venue"
},
  "geometry": {"coordinates":[-81.445109,28.220207],"type":"Point"}
}