{
  "type": "Feature",
  "properties": {
    "iso:country":"US",
    "sg:address":"930 Blanding Blvd",
    "sg:city":"Orange Park",
    "sg:classifiers":[
        {
            "category":"Restaurant",
            "type":"Food & Drink"
        }
    ],
    "sg:menulink":"http://www.allmenus.com/fl/orange-park/136017-spaghetti-house/menu/",
    "sg:phone":"+1 904 276 1653",
    "sg:postcode":"32065",
    "sg:province":"FL",
    "sg:tags":[
        "italian"
    ],
    "wof:name":"Spaghetti House",
    "wof:placetype":"venue"
},
  "geometry": {"coordinates":[-81.77282099999999,30.138772],"type":"Point"}
}