{
  "type": "Feature",
  "properties": {
    "iso:country":"US",
    "sg:address":"1629 SE 47th St",
    "sg:city":"Cape Coral",
    "sg:classifiers":[
        {
            "category":"Organizations",
            "subcategory":"Religious Organization",
            "type":"Services"
        }
    ],
    "sg:phone":"+1 239 549 7094",
    "sg:postcode":"33904",
    "sg:province":"FL",
    "sg:website":"www.clfhome.com",
    "wof:name":"Christian Life Fellowship",
    "wof:placetype":"venue"
},
  "geometry": {"coordinates":[-81.940714,26.564694],"type":"Point"}
}