{
  "type": "Feature",
  "properties": {
    "addr:full":"5214 Broadway West Palm Beach FL 33407",
    "addr:housenumber":"5214",
    "addr:postcode":"33407",
    "addr:street":"Broadway",
    "iso:country":"US",
    "sg:address":"5214 Broadway",
    "sg:city":"West Palm Beach",
    "sg:classifiers":[
        {
            "category":"Retail",
            "subcategory":"Repair Shop",
            "type":"Services"
        }
    ],
    "sg:phone":"+1 561 881 5400",
    "sg:postcode":"33407",
    "sg:province":"FL",
    "sg:tags":[
        "repairing",
        "lawn",
        "mower"
    ],
    "wof:name":"George Franks Lawn Mower Repr",
    "wof:placetype":"venue"
},
  "geometry": {"coordinates":[-80.055587,26.757995],"type":"Point"}
}