{
  "type": "Feature",
  "properties": {
    "addr:full":"440 S Babcock St Melbourne FL 32901",
    "addr:housenumber":"440",
    "addr:postcode":"32901",
    "addr:street":"S Babcock St",
    "iso:country":"US",
    "sg:address":"440 S Babcock St",
    "sg:city":"Melbourne",
    "sg:classifiers":[
        {
            "category":"Professional",
            "subcategory":"Lawyer & Legal Services",
            "type":"Services"
        }
    ],
    "sg:phone":"+1 321 984 2440",
    "sg:postcode":"32901",
    "sg:province":"FL",
    "sg:tags":[
        "attorney",
        "trust",
        "estate",
        "corporation",
        "wills",
        "partnership",
        "planning",
        "law",
        "probate"
    ],
    "sg:website":"http://www.nmk-law.com",
    "wof:name":"Nash & Kromash",
    "wof:placetype":"venue"
},
  "geometry": {"coordinates":[-80.621788,28.100491],"type":"Point"}
}