{
  "type": "Feature",
  "properties": {
    "iso:country":"US",
    "sg:address":"1406 E Crown Point Rd",
    "sg:city":"Ocoee",
    "sg:classifiers":[
        {
            "category":"Communications",
            "type":"Services"
        },
        {
            "category":"Communications",
            "subcategory":"Television Station",
            "type":"Services"
        }
    ],
    "sg:phone":"+1 407 656 2358",
    "sg:postcode":"34761",
    "sg:province":"FL",
    "sg:tags":[
        "satellite",
        "carrier",
        "communications-common",
        "cable"
    ],
    "wof:name":"All-In-One Entertainment, Inc.",
    "wof:placetype":"venue"
},
  "geometry": {"coordinates":[-81.560132,28.590193],"type":"Point"}
}