{
  "type": "Feature",
  "properties": {
    "iso:country":"US",
    "sg:address":"7000 SW 114th Ave",
    "sg:city":"Miami",
    "sg:classifiers":[
        {
            "category":"Social Services",
            "type":"Services"
        }
    ],
    "sg:phone":"+1 305 273 0101",
    "sg:postcode":"33173",
    "sg:province":"FL",
    "sg:tags":[
        "agency",
        "adoption"
    ],
    "wof:name":"Kidslaw Adoption Education",
    "wof:placetype":"venue"
},
  "geometry": {"coordinates":[-80.377703,25.702477],"type":"Point"}
}