{
  "type": "Feature",
  "properties": {
    "iso:country":"US",
    "sg:address":"3201 E Colonial Dr",
    "sg:city":"Orlando",
    "sg:classifiers":[
        {
            "category":"Food & Beverages",
            "subcategory":"Candy",
            "type":"Retail Goods"
        }
    ],
    "sg:phone":"+1 407 895 3600",
    "sg:postcode":"32803",
    "sg:province":"FL",
    "sg:tags":[
        "confectionery"
    ],
    "wof:name":"Morrows",
    "wof:placetype":"venue"
},
  "geometry": {"coordinates":[-81.343277,28.553407],"type":"Point"}
}