{
  "type": "Feature",
  "properties": {
    "iso:country":"US",
    "sg:address":"1207 N Krome Ave",
    "sg:city":"Homestead",
    "sg:phone":"+1 305 248 2343",
    "sg:postcode":"33030",
    "sg:province":"FL",
    "wof:name":"Mary Irma Salon & Spa",
    "wof:placetype":"venue"
},
  "geometry": {"coordinates":[-80.477478,25.481757],"type":"Point"}
}