{
  "type": "Feature",
  "properties": {
    "iso:country":"US",
    "sg:address":"4240 US Hwy 92",
    "sg:city":"Sanford",
    "sg:classifiers":[
        {
            "category":"Insurance",
            "subcategory":"Insurance Agent",
            "type":"Services"
        }
    ],
    "sg:phone":"+1 407 323 5487",
    "sg:postcode":"32773",
    "sg:province":"FL",
    "wof:name":"Allstate Insurance",
    "wof:placetype":"venue"
},
  "geometry": {"coordinates":[-81.295164,28.745818],"type":"Point"}
}