{
  "type": "Feature",
  "properties": {
    "iso:country":"US",
    "sg:address":"215 Lake Miriam Dr",
    "sg:city":"Lakeland",
    "sg:classifiers":[
        {
            "category":"Education",
            "subcategory":"Dance Studio",
            "type":"Public Place"
        }
    ],
    "sg:phone":"+1 863 646 9255",
    "sg:postcode":"33813",
    "sg:province":"FL",
    "sg:tags":[
        "instruction",
        "dancing"
    ],
    "wof:name":"Carol Grayson School Of Dance",
    "wof:placetype":"venue"
},
  "geometry": {"coordinates":[-81.959688,27.9748],"type":"Point"}
}