{
  "type": "Feature",
  "properties": {
    "addr:full":"5249 Tennis Ln Delray Beach FL 33484",
    "addr:housenumber":"5249",
    "addr:postcode":"33484",
    "addr:street":"Tennis Ln",
    "iso:country":"US",
    "sg:address":"5249 Tennis Ln",
    "sg:city":"Delray Beach",
    "sg:classifiers":[
        {
            "category":"Shopping",
            "subcategory":"Used Merchandise",
            "type":"Retail Goods"
        }
    ],
    "sg:phone":"+1 561 638 0332",
    "sg:postcode":"33484",
    "sg:province":"FL",
    "wof:name":"Pull Out Shelf Co of Broward",
    "wof:placetype":"venue"
},
  "geometry": {"coordinates":[-80.12686100000001,26.43316],"type":"Point"}
}