{
  "type": "Feature",
  "properties": {
    "addr:full":"936 Beachland Blvd Vero Beach FL 32963",
    "addr:housenumber":"936",
    "addr:postcode":"32963",
    "addr:street":"Beachland Blvd",
    "iso:country":"US",
    "sg:address":"936 Beachland Blvd",
    "sg:city":"Vero Beach",
    "sg:classifiers":[
        {
            "category":"Banks & Credit Unions",
            "subcategory":"Investment Brokerage",
            "type":"Services"
        }
    ],
    "sg:phone":"+1 772 231 7544",
    "sg:postcode":"32963",
    "sg:province":"FL",
    "sg:tags":[
        "security"
    ],
    "wof:name":"Brookstreet Securities Corp",
    "wof:placetype":"venue"
},
  "geometry": {"coordinates":[-80.356874,27.65333],"type":"Point"}
}