{
  "type": "Feature",
  "properties": {
    "addr:full":"6907 Southern Blvd West Palm Beach FL 33413",
    "addr:housenumber":"6907",
    "addr:postcode":"33413",
    "addr:street":"Southern Blvd",
    "iso:country":"US",
    "sg:address":"6907 Southern Blvd",
    "sg:city":"West Palm Beach",
    "sg:classifiers":[
        {
            "category":"Manufacturing",
            "subcategory":"Food",
            "type":"Manufacturing & Wholesale Goods"
        }
    ],
    "sg:phone":"+1 561 723 6854",
    "sg:postcode":"33413",
    "sg:province":"FL",
    "sg:tags":[
        "chewing",
        "gum",
        "mfg"
    ],
    "wof:name":"Eduardo Montagna",
    "wof:placetype":"venue"
},
  "geometry": {"coordinates":[-80.15664,26.678947],"type":"Point"}
}