{
  "type": "Feature",
  "properties": {
    "addr:full":"5555 Hollywood Blvd Hollywood FL 33021",
    "addr:housenumber":"5555",
    "addr:postcode":"33021",
    "addr:street":"Hollywood Blvd",
    "iso:country":"US",
    "sg:address":"5555 Hollywood Blvd",
    "sg:city":"Hollywood",
    "sg:classifiers":[
        {
            "category":"Home & Garden",
            "subcategory":"Building Materials",
            "type":"Retail Goods"
        }
    ],
    "sg:phone":"+1 954 981 8181",
    "sg:postcode":"33021",
    "sg:province":"FL",
    "sg:tags":[
        "glass",
        "window",
        "plate"
    ],
    "wof:name":"A Locksmith",
    "wof:placetype":"venue"
},
  "geometry": {"coordinates":[-80.196226,26.010441],"type":"Point"}
}