{
  "type": "Feature",
  "properties": {
    "addr:full":"4700 W Irlo Bronson Memorial Hwy Kissimmee FL 34746",
    "addr:housenumber":"4700",
    "addr:postcode":"34746",
    "addr:street":"W Irlo Bronson Memorial Hwy",
    "iso:country":"US",
    "sg:address":"4700 W Irlo Bronson Memorial Hwy",
    "sg:city":"Kissimmee",
    "sg:classifiers":[
        {
            "category":"Travel",
            "subcategory":"Hotels & Motels",
            "type":"Entertainment"
        }
    ],
    "sg:phone":"+1 407 396 1133",
    "sg:postcode":"34746",
    "sg:province":"FL",
    "wof:name":"Red Carpet Inn",
    "wof:placetype":"venue"
},
  "geometry": {"coordinates":[-81.470488,28.319097],"type":"Point"}
}