{
  "type": "Feature",
  "properties": {
    "addr:full":"2707 N Himes Ave Tampa FL 33607",
    "addr:housenumber":"2707",
    "addr:postcode":"33607",
    "addr:street":"N Himes Ave",
    "iso:country":"US",
    "sg:address":"2707 N Himes Ave",
    "sg:city":"Tampa",
    "sg:classifiers":[
        {
            "category":"Health Services",
            "subcategory":"Doctor",
            "type":"Services"
        }
    ],
    "sg:phone":"+1 813 874 1030",
    "sg:postcode":"33607",
    "sg:province":"FL",
    "sg:tags":[
        "clinic",
        "medical"
    ],
    "wof:name":"Rivas Theraphy Clinic",
    "wof:placetype":"venue"
},
  "geometry": {"coordinates":[-82.501335,27.965348],"type":"Point"}
}