{
  "type": "Feature",
  "properties": {
    "iso:country":"US",
    "sg:address":"1306 W Sligh Ave",
    "sg:city":"Tampa",
    "sg:classifiers":[
        {
            "category":"Social Services",
            "type":"Services"
        }
    ],
    "sg:phone":"+1 813 932 5228",
    "sg:postcode":"33604",
    "sg:province":"FL",
    "wof:name":"Seniors In Service of Tampa",
    "wof:placetype":"venue"
},
  "geometry": {"coordinates":[-82.47233199999999,28.01067],"type":"Point"}
}