{
  "type": "Feature",
  "properties": {
    "iso:country":"US",
    "sg:address":"2525 Center Rd",
    "sg:city":"Fort Pierce",
    "sg:classifiers":[
        {
            "category":"Sports & Exercise",
            "subcategory":"Race Track",
            "type":"Entertainment"
        }
    ],
    "sg:phone":"+1 772 466 0746",
    "sg:postcode":"34946",
    "sg:province":"FL",
    "wof:name":"St Lucie Speedway",
    "wof:placetype":"venue"
},
  "geometry": {"coordinates":[-80.37848700000001,27.480608],"type":"Point"}
}