{
  "type": "Feature",
  "properties": {
    "addr:full":"5141 Garlanger Trl Oviedo FL 32765",
    "addr:housenumber":"5141",
    "addr:postcode":"32765",
    "addr:street":"Garlanger Trl",
    "iso:country":"US",
    "sg:address":"5141 Garlanger Trl",
    "sg:city":"Oviedo",
    "sg:classifiers":[
        {
            "category":"Community Center",
            "subcategory":"Social",
            "type":"Public Place"
        }
    ],
    "sg:phone":"+1 407 365 3005",
    "sg:postcode":"32765",
    "sg:province":"FL",
    "sg:tags":[
        "playing",
        "card",
        "room"
    ],
    "wof:name":"Paladia Games, Inc.",
    "wof:placetype":"venue"
},
  "geometry": {"coordinates":[-81.25142700000001,28.630947],"type":"Point"}
}