{
  "type": "Feature",
  "properties": {
    "iso:country":"US",
    "sg:address":"1701 W Pensacola St",
    "sg:city":"Tallahassee",
    "sg:classifiers":[
        {
            "category":"Real Estate",
            "subcategory":"Real Estate Operator",
            "type":"Services"
        }
    ],
    "sg:phone":"+1 850 576 9980",
    "sg:postcode":"32304",
    "sg:province":"FL",
    "sg:tags":[
        "building",
        "personal",
        "apartment"
    ],
    "wof:name":"Harbin Terrace Apartments",
    "wof:placetype":"venue"
},
  "geometry": {"coordinates":[-84.30938999999999,30.44014],"type":"Point"}
}