{
  "type": "Feature",
  "properties": {
    "addr:full":"18412 Turning Point Dr Lutz FL 33549",
    "addr:housenumber":"18412",
    "addr:postcode":"33549",
    "addr:street":"Turning Point Dr",
    "iso:country":"US",
    "sg:address":"18412 Turning Point Dr",
    "sg:city":"Lutz",
    "sg:classifiers":[
        {
            "category":"Manufacturing",
            "subcategory":"Tools & Machinery",
            "type":"Manufacturing & Wholesale Goods"
        }
    ],
    "sg:phone":"+1 813 259 1589",
    "sg:postcode":"33549",
    "sg:province":"FL",
    "sg:tags":[
        "mining",
        "mfg"
    ],
    "wof:name":"Bay Shuttle",
    "wof:placetype":"venue"
},
  "geometry": {"coordinates":[-82.44572599999999,28.142288],"type":"Point"}
}