{
  "type": "Feature",
  "properties": {
    "addr:full":"300 Lenox Ave Daytona Beach FL 32118",
    "addr:housenumber":"300",
    "addr:postcode":"32118",
    "addr:street":"Lenox Ave",
    "iso:country":"US",
    "sg:address":"300 Lenox Ave",
    "sg:city":"Daytona Beach",
    "sg:classifiers":[
        {
            "category":"Professional",
            "subcategory":"Management & Consulting",
            "type":"Services"
        }
    ],
    "sg:phone":"+1 386 226 1156",
    "sg:postcode":"32118",
    "sg:province":"FL",
    "sg:tags":[
        "fuel"
    ],
    "wof:name":"ATM Management Inc",
    "wof:placetype":"venue"
},
  "geometry": {"coordinates":[-81.006496,29.21637],"type":"Point"}
}