{
  "type": "Feature",
  "properties": {
    "iso:country":"US",
    "sg:address":"4566 Higel Ave",
    "sg:city":"Sarasota",
    "sg:classifiers":[
        {
            "category":"Professional",
            "type":"Services"
        }
    ],
    "sg:phone":"+1 941 587 6437",
    "sg:postcode":"34242",
    "sg:province":"FL",
    "wof:name":"Pawf Inc",
    "wof:placetype":"venue"
},
  "geometry": {"coordinates":[-82.559073,27.287413],"type":"Point"}
}