{
  "type": "Feature",
  "properties": {
    "addr:full":"1125 Gills Dr Orlando FL 32824",
    "addr:housenumber":"1125",
    "addr:postcode":"32824",
    "addr:street":"Gills Dr",
    "iso:country":"US",
    "sg:address":"1125 Gills Dr",
    "sg:city":"Orlando",
    "sg:classifiers":[
        {
            "category":"Freight",
            "type":"Transportation"
        },
        {
            "category":"Wholesale",
            "subcategory":"Chemicals & Plastics",
            "type":"Manufacturing & Wholesale Goods"
        }
    ],
    "sg:phone":"+1 407 855 7995",
    "sg:postcode":"32824",
    "sg:province":"FL",
    "sg:tags":[
        "warehouse",
        "cleaning",
        "compound"
    ],
    "wof:name":"Ecolab Inc",
    "wof:placetype":"venue"
},
  "geometry": {"coordinates":[-81.39335800000001,28.438063],"type":"Point"}
}