{
  "type": "Feature",
  "properties": {
    "addr:full":"2014 SE Pruitt Rd Port St Lucie FL 34952",
    "addr:housenumber":"2014",
    "addr:postcode":"34952",
    "addr:street":"Se Pruitt Rd;St",
    "iso:country":"US",
    "sg:address":"2014 SE Pruitt Rd",
    "sg:city":"Port St Lucie",
    "sg:classifiers":[
        {
            "category":"Real Estate",
            "subcategory":"Real Estate Agent",
            "type":"Services"
        }
    ],
    "sg:phone":"+1 772 335 4333",
    "sg:postcode":"34952",
    "sg:province":"FL",
    "sg:website":"www.welcomecenter.com",
    "wof:name":"Coldwell Banker",
    "wof:placetype":"venue"
},
  "geometry": {"coordinates":[-80.31772599999999,27.259282],"type":"Point"}
}