{
  "type": "Feature",
  "properties": {
    "iso:country":"US",
    "sg:address":"1418 Rock Springs Rd",
    "sg:city":"Apopka",
    "sg:classifiers":[
        {
            "category":"Restaurant",
            "type":"Food & Drink"
        }
    ],
    "sg:menulink":"http://www.allmenus.com/fl/apopka/122565-quiznos-sub/menu/",
    "sg:phone":"+1 407 880 0990",
    "sg:postcode":"32712",
    "sg:province":"FL",
    "sg:tags":[
        "wrap",
        "american",
        "sandwich"
    ],
    "wof:name":"Quiznos Sub",
    "wof:placetype":"venue"
},
  "geometry": {"coordinates":[-81.50918900000001,28.704741],"type":"Point"}
}