{
  "type": "Feature",
  "properties": {
    "addr:full":"4521 Barclay Fair Way Lake Worth FL 33449",
    "addr:housenumber":"4521",
    "addr:postcode":"33449",
    "addr:street":"Barclay Fair Way",
    "iso:country":"US",
    "sg:address":"4521 Barclay Fair Way",
    "sg:city":"Lake Worth",
    "sg:classifiers":[
        {
            "category":"Professional",
            "subcategory":"Advertising",
            "type":"Services"
        }
    ],
    "sg:phone":"+1 561 966 9610",
    "sg:postcode":"33449",
    "sg:province":"FL",
    "sg:tags":[
        "agency"
    ],
    "wof:name":"C Gordon Advertising",
    "wof:placetype":"venue"
},
  "geometry": {"coordinates":[-80.210398,26.614044],"type":"Point"}
}