{
  "type": "Feature",
  "properties": {
    "iso:country":"US",
    "sg:address":"4938 Sarazen Dr",
    "sg:city":"Hollywood",
    "sg:classifiers":[
        {
            "category":"Retail",
            "subcategory":"Repair Shop",
            "type":"Services"
        }
    ],
    "sg:phone":"+1 954 963 2262",
    "sg:postcode":"33021",
    "sg:province":"FL",
    "sg:tags":[
        "lock",
        "locksmith"
    ],
    "wof:name":"A-Best Locksmith",
    "wof:placetype":"venue"
},
  "geometry": {"coordinates":[-80.195128,26.041468],"type":"Point"}
}