{
  "type": "Feature",
  "properties": {
    "addr:full":"206 Norfolk Pl Kissimmee FL 34747",
    "addr:housenumber":"206",
    "addr:postcode":"34747",
    "addr:street":"Norfolk Pl",
    "iso:country":"US",
    "sg:address":"206 Norfolk Pl",
    "sg:city":"Kissimmee",
    "sg:classifiers":[
        {
            "category":"Place Of Worship",
            "type":"Public Place"
        }
    ],
    "sg:phone":"+1 321 939 0491",
    "sg:postcode":"34747",
    "sg:province":"FL",
    "sg:tags":[
        "church"
    ],
    "wof:name":"Grace Pub Enterprises Corp.",
    "wof:placetype":"venue"
},
  "geometry": {"coordinates":[-81.523815,28.326116],"type":"Point"}
}