{
  "type": "Feature",
  "properties": {
    "addr:full":"913 W Knollwood St Tampa FL 33604",
    "addr:housenumber":"913",
    "addr:postcode":"33604",
    "addr:street":"W Knollwood St",
    "iso:country":"US",
    "sg:address":"913 W Knollwood St",
    "sg:city":"Tampa",
    "sg:classifiers":[
        {
            "category":"Retail",
            "subcategory":"Auto Repair",
            "type":"Services"
        }
    ],
    "sg:phone":"+1 813 931 9675",
    "sg:postcode":"33604",
    "sg:province":"FL",
    "sg:tags":[
        "body"
    ],
    "wof:name":"Beach Boy Automotive Inc",
    "wof:placetype":"venue"
},
  "geometry": {"coordinates":[-82.471137,28.007587],"type":"Point"}
}