{
  "type": "Feature",
  "properties": {
    "iso:country":"US",
    "sg:address":"37103 Lemon Ave",
    "sg:city":"Zephyrhills",
    "sg:classifiers":[
        {
            "category":"Building & Trades",
            "subcategory":"Landscaping Services",
            "type":"Services"
        }
    ],
    "sg:phone":"+1 813 783 2277",
    "sg:postcode":"33541",
    "sg:province":"FL",
    "sg:tags":[
        "landscape",
        "contractor"
    ],
    "wof:name":"Carolines Lawn Care",
    "wof:placetype":"venue"
},
  "geometry": {"coordinates":[-82.198982,28.262516],"type":"Point"}
}