{
  "type": "Feature",
  "properties": {
    "iso:country":"US",
    "sg:address":"2900 SW 87th Ave",
    "sg:city":"Miami",
    "sg:classifiers":[
        {
            "category":"Education",
            "subcategory":"School",
            "type":"Public Place"
        }
    ],
    "sg:phone":"+1 305 223 4561",
    "sg:postcode":"33165",
    "sg:province":"FL",
    "sg:tags":[
        "university",
        "college"
    ],
    "wof:name":"St John Vianney College Seminary",
    "wof:placetype":"venue"
},
  "geometry": {"coordinates":[-80.335899,25.7423],"type":"Point"}
}