{
  "type": "Feature",
  "properties": {
    "addr:full":"115 S Ring Ave Tarpon Springs FL 34689",
    "addr:housenumber":"115",
    "addr:postcode":"34689",
    "addr:street":"S Ring Ave",
    "iso:country":"US",
    "sg:address":"115 S Ring Ave",
    "sg:city":"Tarpon Springs",
    "sg:classifiers":[
        {
            "category":"Building & Trades",
            "subcategory":"Construction",
            "type":"Services"
        }
    ],
    "sg:phone":"+1 727 942 5607",
    "sg:postcode":"34689",
    "sg:province":"FL",
    "wof:name":"City Utilities Dept",
    "wof:placetype":"venue"
},
  "geometry": {"coordinates":[-82.7535,28.145717],"type":"Point"}
}