{
  "type": "Feature",
  "properties": {
    "iso:country":"US",
    "sg:address":"4210 14th Ave E",
    "sg:city":"Bradenton",
    "sg:classifiers":[
        {
            "category":"Farming",
            "subcategory":"Fish & Marine Products",
            "type":"Manufacturing & Wholesale Goods"
        }
    ],
    "sg:phone":"+1 941 746 1634",
    "sg:postcode":"34208",
    "sg:province":"FL",
    "sg:tags":[
        "management"
    ],
    "wof:name":"Just For Fun",
    "wof:placetype":"venue"
},
  "geometry": {"coordinates":[-82.50505200000001,27.488109],"type":"Point"}
}