{
  "type": "Feature",
  "properties": {
    "iso:country":"US",
    "sg:address":"4867 Park St N",
    "sg:city":"St Petersburg",
    "sg:classifiers":[
        {
            "category":"Personal",
            "subcategory":"Beauty Salon",
            "type":"Services"
        }
    ],
    "sg:phone":"+1 727 541 6309",
    "sg:postcode":"33709",
    "sg:province":"FL",
    "sg:tags":[
        "shop"
    ],
    "wof:name":"Beau Monde Beauty Salon",
    "wof:placetype":"venue"
},
  "geometry": {"coordinates":[-82.753861,27.81576],"type":"Point"}
}