{
  "type": "Feature",
  "properties": {
    "addr:full":"1210 Homewood Blvd Delray Beach FL 33445",
    "addr:housenumber":"1210",
    "addr:postcode":"33445",
    "addr:street":"Homewood Blvd",
    "iso:country":"US",
    "sg:address":"1210 Homewood Blvd",
    "sg:city":"Delray Beach",
    "sg:classifiers":[
        {
            "category":"Manufacturing",
            "subcategory":"Metals",
            "type":"Manufacturing & Wholesale Goods"
        }
    ],
    "sg:phone":"+1 561 276 6200",
    "sg:postcode":"33445",
    "sg:province":"FL",
    "wof:name":"Thomas All Painting Inc",
    "wof:placetype":"venue"
},
  "geometry": {"coordinates":[-80.101646,26.442206],"type":"Point"}
}