{
  "type": "Feature",
  "properties": {
    "iso:country":"US",
    "sg:address":"5725 NW 151st St",
    "sg:city":"Hialeah",
    "sg:classifiers":[
        {
            "category":"Manufacturing",
            "subcategory":"Printing",
            "type":"Manufacturing & Wholesale Goods"
        }
    ],
    "sg:phone":"+1 305 828 9992",
    "sg:postcode":"33014",
    "sg:province":"FL",
    "sg:tags":[
        "offset"
    ],
    "sg:website":"www.signature-printing.com",
    "wof:name":"Signature Printing Inc",
    "wof:placetype":"venue"
},
  "geometry": {"coordinates":[-80.297321,25.910834],"type":"Point"}
}