{
  "type": "Feature",
  "properties": {
    "iso:country":"US",
    "sg:address":"6118 Becklin Pl",
    "sg:city":"Riverview",
    "sg:classifiers":[
        {
            "category":"Real Estate",
            "subcategory":"Real Estate Services",
            "type":"Services"
        },
        {
            "category":"Real Estate",
            "subcategory":"Real Estate Agent",
            "type":"Services"
        }
    ],
    "sg:phone":"+1 813 643 5331",
    "sg:postcode":"33578",
    "sg:province":"FL",
    "sg:tags":[
        "management"
    ],
    "sg:website":"http://www.mcneilmsi.com",
    "wof:name":"Mcneil Management",
    "wof:placetype":"venue"
},
  "geometry": {"coordinates":[-82.324516,27.891826],"type":"Point"}
}