{
  "type": "Feature",
  "properties": {
    "iso:country":"US",
    "sg:address":"24 Sweetwater Creek Cir",
    "sg:city":"Oviedo",
    "sg:classifiers":[
        {
            "category":"Real Estate",
            "subcategory":"Real Estate Agent",
            "type":"Services"
        }
    ],
    "sg:phone":"+1 407 366 0229",
    "sg:postcode":"32765",
    "sg:province":"FL",
    "wof:name":"Branson Appraisal Inc",
    "wof:placetype":"venue"
},
  "geometry": {"coordinates":[-81.208135,28.678103],"type":"Point"}
}