{
  "type": "Feature",
  "properties": {
    "iso:country":"US",
    "sg:address":"4863 Hampshire Ct",
    "sg:city":"Naples",
    "sg:classifiers":[
        {
            "category":"Real Estate",
            "subcategory":"Real Estate Operator",
            "type":"Services"
        }
    ],
    "sg:phone":"+1 239 775 7845",
    "sg:postcode":"34112",
    "sg:province":"FL",
    "sg:tags":[
        "condominium"
    ],
    "wof:name":"Maxwell House Watching",
    "wof:placetype":"venue"
},
  "geometry": {"coordinates":[-81.693967,26.112433],"type":"Point"}
}