{
  "type": "Feature",
  "properties": {
    "addr:full":"3710 Casaba Loop Valrico FL 33596",
    "addr:housenumber":"3710",
    "addr:postcode":"33596",
    "addr:street":"Casaba Loop",
    "iso:country":"US",
    "sg:address":"3710 Casaba Loop",
    "sg:city":"Valrico",
    "sg:classifiers":[
        {
            "category":"Building & Trades",
            "subcategory":"Plumbing",
            "type":"Services"
        }
    ],
    "sg:phone":"+1 813 684 5036",
    "sg:postcode":"33596",
    "sg:province":"FL",
    "sg:tags":[
        "contractor"
    ],
    "wof:name":"Happy Lawn Sprinkler Inc",
    "wof:placetype":"venue"
},
  "geometry": {"coordinates":[-82.26852100000001,27.88769],"type":"Point"}
}