{
  "type": "Feature",
  "properties": {
    "iso:country":"US",
    "sg:address":"1903 S Congress Ave",
    "sg:city":"Boynton Beach",
    "sg:classifiers":[
        {
            "category":"Professional",
            "type":"Services"
        }
    ],
    "sg:phone":"+1 561 732 5110",
    "sg:postcode":"33426",
    "sg:province":"FL",
    "sg:tags":[
        "establishment"
    ],
    "wof:name":"Alan H Blecker Clu C Hfc Cfp",
    "wof:placetype":"venue"
},
  "geometry": {"coordinates":[-80.09017900000001,26.506699],"type":"Point"}
}