{
  "type": "Feature",
  "properties": {
    "addr:full":"1532 Trillo Ave Miami FL 33146",
    "addr:housenumber":"1532",
    "addr:postcode":"33146",
    "addr:street":"Trillo Ave",
    "iso:country":"US",
    "sg:address":"1532 Trillo Ave",
    "sg:city":"Miami",
    "sg:classifiers":[
        {
            "category":"Shopping",
            "subcategory":"Used Merchandise",
            "type":"Retail Goods"
        }
    ],
    "sg:phone":"+1 305 667 3475",
    "sg:postcode":"33146",
    "sg:province":"FL",
    "sg:tags":[
        "antique",
        "gift"
    ],
    "wof:name":"Neds Antiques & Gifts",
    "wof:placetype":"venue"
},
  "geometry": {"coordinates":[-80.285343,25.719726],"type":"Point"}
}