{
  "type": "Feature",
  "properties": {
    "iso:country":"US",
    "sg:address":"109 E Maine Ave",
    "sg:city":"Longwood",
    "sg:classifiers":[
        {
            "category":"Food & Beverages",
            "subcategory":"Fruits & Vegetables",
            "type":"Retail Goods"
        }
    ],
    "sg:phone":"+1 407 332 6206",
    "sg:postcode":"32750",
    "sg:province":"FL",
    "sg:tags":[
        "produce"
    ],
    "wof:name":"Fresh Garden Produce",
    "wof:placetype":"venue"
},
  "geometry": {"coordinates":[-81.346255,28.695929],"type":"Point"}
}