{
  "type": "Feature",
  "properties": {
    "iso:country":"US",
    "sg:address":"3 Saint John Blvd",
    "sg:city":"Englewood",
    "sg:classifiers":[
        {
            "category":"Building & Trades",
            "subcategory":"Construction",
            "type":"Services"
        }
    ],
    "sg:phone":"+1 941 475 1644",
    "sg:postcode":"34223",
    "sg:province":"FL",
    "sg:tags":[
        "contractor"
    ],
    "wof:name":"Picket Fences Inc",
    "wof:placetype":"venue"
},
  "geometry": {"coordinates":[-82.361769,26.999055],"type":"Point"}
}