{
  "type": "Feature",
  "properties": {
    "addr:full":"1 S School Ave Sarasota FL 34237",
    "addr:housenumber":"1",
    "addr:postcode":"34237",
    "addr:street":"S School Ave",
    "iso:country":"US",
    "sg:address":"1 S School Ave",
    "sg:city":"Sarasota",
    "sg:classifiers":[
        {
            "category":"Professional",
            "subcategory":"Lawyer & Legal Services",
            "type":"Services"
        }
    ],
    "sg:phone":"+1 941 366 0911",
    "sg:postcode":"34237",
    "sg:province":"FL",
    "sg:tags":[
        "attorney"
    ],
    "wof:name":"Taylor Lawless & Singer",
    "wof:placetype":"venue"
},
  "geometry": {"coordinates":[-82.52628799999999,27.335593],"type":"Point"}
}