{
  "type": "Feature",
  "properties": {
    "iso:country":"US",
    "sg:address":"13635 N Magnolia Ave",
    "sg:city":"Citra",
    "sg:classifiers":[
        {
            "category":"Building & Trades",
            "subcategory":"Construction",
            "type":"Services"
        }
    ],
    "sg:phone":"+1 352 867 7439",
    "sg:postcode":"32113",
    "sg:province":"FL",
    "sg:tags":[
        "dry wall",
        "contractor"
    ],
    "wof:name":"Alan J Hubert Drywall Inc",
    "wof:placetype":"venue"
},
  "geometry": {"coordinates":[-82.138222,29.352712],"type":"Point"}
}