{
  "type": "Feature",
  "properties": {
    "addr:full":"39101 Haven Ave Zephyrhills FL 33542",
    "addr:housenumber":"39101",
    "addr:postcode":"33542",
    "addr:street":"Haven Ave",
    "iso:country":"US",
    "sg:address":"39101 Haven Ave",
    "sg:city":"Zephyrhills",
    "sg:classifiers":[
        {
            "category":"Professional",
            "subcategory":"Detective & Security Services",
            "type":"Services"
        }
    ],
    "sg:phone":"+1 813 779 0188",
    "sg:postcode":"33542",
    "sg:province":"FL",
    "sg:tags":[
        "information",
        "bureau"
    ],
    "wof:name":"Scrivens Johnson Mortuary Service",
    "wof:placetype":"venue"
},
  "geometry": {"coordinates":[-82.170675,28.250535],"type":"Point"}
}