{
  "type": "Feature",
  "properties": {
    "addr:full":"10480 NW 37th St Doral FL 33178",
    "addr:housenumber":"10480",
    "addr:postcode":"33178",
    "addr:street":"Nw 37Th St",
    "iso:country":"US",
    "sg:address":"10480 NW 37th St",
    "sg:city":"Doral",
    "sg:classifiers":[
        {
            "category":"Wholesale",
            "subcategory":"Tobacco Products",
            "type":"Manufacturing & Wholesale Goods"
        }
    ],
    "sg:phone":"+1 305 718 3981",
    "sg:postcode":"33178",
    "sg:province":"FL",
    "sg:tags":[
        "cigarette",
        "cigar",
        "dealer"
    ],
    "wof:name":"Royal Tobacco",
    "wof:placetype":"venue"
},
  "geometry": {"coordinates":[-80.38389599999999,25.808753],"type":"Point"}
}