{
  "type": "Feature",
  "properties": {
    "iso:country":"US",
    "sg:address":"2043 NE 140th St",
    "sg:city":"North Miami Beach",
    "sg:classifiers":[
        {
            "category":"Retail",
            "subcategory":"Veterinary Services",
            "type":"Services"
        },
        {
            "category":"Retail",
            "subcategory":"Pet Boarding",
            "type":"Services"
        }
    ],
    "sg:phone":"+1 305 940 2287",
    "sg:postcode":"33181",
    "sg:province":"FL",
    "sg:tags":[
        "veterinarian",
        "boarding/pet",
        "sitting"
    ],
    "sg:website":"www.bayshorevet.com",
    "wof:name":"McCoy James P DVM",
    "wof:placetype":"venue"
},
  "geometry": {"coordinates":[-80.157898,25.905701],"type":"Point"}
}