{
  "type": "Feature",
  "properties": {
    "iso:country":"US",
    "sg:address":"2909 W Bay To Bay Blvd",
    "sg:city":"Tampa",
    "sg:classifiers":[
        {
            "category":"Restaurant",
            "type":"Food & Drink"
        }
    ],
    "sg:phone":"+1 813 831 7122",
    "sg:postcode":"33629",
    "sg:province":"FL",
    "sg:tags":[
        "eating"
    ],
    "wof:name":"Pach Place",
    "wof:placetype":"venue"
},
  "geometry": {"coordinates":[-82.49046800000001,27.919338],"type":"Point"}
}