{
  "type": "Feature",
  "properties": {
    "addr:full":"37 Twin River Dr Ormond Beach FL 32174",
    "addr:housenumber":"37",
    "addr:postcode":"32174",
    "addr:street":"Twin River Dr",
    "iso:country":"US",
    "sg:address":"37 Twin River Dr",
    "sg:city":"Ormond Beach",
    "sg:classifiers":[
        {
            "category":"Building & Trades",
            "subcategory":"Landscaping Services",
            "type":"Services"
        }
    ],
    "sg:phone":"+1 386 673 0682",
    "sg:postcode":"32174",
    "sg:province":"FL",
    "sg:tags":[
        "lawn",
        "maintenance",
        "grounds"
    ],
    "wof:name":"Clint's Lawn & Landscaping",
    "wof:placetype":"venue"
},
  "geometry": {"coordinates":[-81.124514,29.25689],"type":"Point"}
}