{
  "type": "Feature",
  "properties": {
    "addr:full":"12958 NW 23rd St Hollywood FL 33028",
    "addr:housenumber":"12958",
    "addr:postcode":"33028",
    "addr:street":"Nw 23Rd St",
    "iso:country":"US",
    "sg:address":"12958 NW 23rd St",
    "sg:city":"Hollywood",
    "sg:classifiers":[
        {
            "category":"Shopping",
            "subcategory":"Jewelry",
            "type":"Retail Goods"
        }
    ],
    "sg:phone":"+1 954 435 2602",
    "sg:postcode":"33028",
    "sg:province":"FL",
    "wof:name":"Holy Gold Jewelry Inc",
    "wof:placetype":"venue"
},
  "geometry": {"coordinates":[-80.328943,26.026052],"type":"Point"}
}