{
  "type": "Feature",
  "properties": {
    "addr:full":"303 E Altamonte Dr Altamonte Springs FL 32701",
    "addr:housenumber":"303",
    "addr:postcode":"32701",
    "addr:street":"E Altamonte Dr",
    "iso:country":"US",
    "sg:address":"303 E Altamonte Dr",
    "sg:city":"Altamonte Springs",
    "sg:classifiers":[
        {
            "category":"Cafe",
            "type":"Food & Drink"
        }
    ],
    "sg:menulink":"http://www.allmenus.com/fl/casselberry-altamonte-springs/39090-gold-lion-chinese-cafe/menu/",
    "sg:phone":"+1 407 331 8880",
    "sg:postcode":"32701",
    "sg:province":"FL",
    "sg:tags":[
        "asian",
        "chinese"
    ],
    "wof:name":"Gold Lion Chinese Cafe",
    "wof:placetype":"venue"
},
  "geometry": {"coordinates":[-81.381974,28.662469],"type":"Point"}
}