{
  "type": "Feature",
  "properties": {
    "addr:full":"7329 NW 32nd Ave Miami FL 33147",
    "addr:housenumber":"7329",
    "addr:postcode":"33147",
    "addr:street":"Nw 32Nd Ave",
    "iso:country":"US",
    "sg:address":"7329 NW 32nd Ave",
    "sg:city":"Miami",
    "sg:classifiers":[
        {
            "category":"Retail",
            "subcategory":"Repair Shop",
            "type":"Services"
        }
    ],
    "sg:phone":"+1 305 694 1416",
    "sg:postcode":"33147",
    "sg:province":"FL",
    "sg:tags":[
        "equipment",
        "printing"
    ],
    "wof:name":"Gero Print",
    "wof:placetype":"venue"
},
  "geometry": {"coordinates":[-80.249674,25.841305],"type":"Point"}
}