{
  "type": "Feature",
  "properties": {
    "iso:country":"US",
    "sg:address":"835 Palmetto Ter",
    "sg:city":"Oviedo",
    "sg:classifiers":[
        {
            "category":"Professional",
            "type":"Services"
        }
    ],
    "sg:phone":"+1 407 971 1937",
    "sg:postcode":"32765",
    "sg:province":"FL",
    "sg:tags":[
        "establishment"
    ],
    "wof:name":"Audiobuilders Inc",
    "wof:placetype":"venue"
},
  "geometry": {"coordinates":[-81.198915,28.68278],"type":"Point"}
}