{
  "type": "Feature",
  "properties": {
    "addr:full":"6730 15th St E Sarasota FL 34243",
    "addr:housenumber":"6730",
    "addr:postcode":"34243",
    "addr:street":"15Th St E",
    "iso:country":"US",
    "sg:address":"6730 15th St E",
    "sg:city":"Sarasota",
    "sg:classifiers":[
        {
            "category":"Wholesale",
            "subcategory":"Scrap",
            "type":"Manufacturing & Wholesale Goods"
        }
    ],
    "sg:phone":"+1 941 727 7611",
    "sg:postcode":"34243",
    "sg:province":"FL",
    "sg:tags":[
        "material"
    ],
    "wof:name":"Scrap Wire Etc Inc",
    "wof:placetype":"venue"
},
  "geometry": {"coordinates":[-82.546797,27.420766],"type":"Point"}
}