{
  "type": "Feature",
  "properties": {
    "addr:full":"1639 Stanford Rd Gulf Breeze FL 32563",
    "addr:housenumber":"1639",
    "addr:postcode":"32563",
    "addr:street":"Stanford Rd",
    "iso:country":"US",
    "sg:address":"1639 Stanford Rd",
    "sg:city":"Gulf Breeze",
    "sg:classifiers":[
        {
            "category":"Building & Trades",
            "subcategory":"Construction",
            "type":"Services"
        }
    ],
    "sg:phone":"+1 850 654 1340",
    "sg:postcode":"32563",
    "sg:province":"FL",
    "sg:tags":[
        "contractor"
    ],
    "wof:name":"Richard R Raffield Contractor",
    "wof:placetype":"venue"
},
  "geometry": {"coordinates":[-87.086384,30.393863],"type":"Point"}
}