{
  "type": "Feature",
  "properties": {
    "iso:country":"US",
    "sg:address":"2236 Chantilly Ter",
    "sg:city":"Oviedo",
    "sg:classifiers":[
        {
            "category":"Professional",
            "subcategory":"Accounting & Tax Preparation",
            "type":"Services"
        }
    ],
    "sg:phone":"+1 407 365 8223",
    "sg:postcode":"32765",
    "sg:province":"FL",
    "sg:tags":[
        "return",
        "preparation-business"
    ],
    "wof:name":"J C Clark Account And Tax Services",
    "wof:placetype":"venue"
},
  "geometry": {"coordinates":[-81.217552,28.628808],"type":"Point"}
}