{
  "type": "Feature",
  "properties": {
    "iso:country":"US",
    "sg:address":"16475 SE US Hwy 301",
    "sg:city":"Summerfield",
    "sg:classifiers":[
        {
            "category":"Bars & Pubs",
            "type":"Food & Drink"
        }
    ],
    "sg:phone":"+1 352 347 8226",
    "sg:postcode":"34491",
    "sg:province":"FL",
    "wof:name":"Crossroads Inn",
    "wof:placetype":"venue"
},
  "geometry": {"coordinates":[-82.041236,28.979885],"type":"Point"}
}