{
  "type": "Feature",
  "properties": {
    "addr:full":"8400 Picos Rd Fort Pierce FL 34945",
    "addr:postcode":"8400;34945",
    "addr:street":"Picos Rd",
    "iso:country":"US",
    "sg:address":"8400 Picos Rd",
    "sg:city":"Fort Pierce",
    "sg:classifiers":[
        {
            "category":"Government",
            "subcategory":"Office",
            "type":"Public Place"
        }
    ],
    "sg:phone":"+1 772 468 3921",
    "sg:postcode":"34945",
    "sg:province":"FL",
    "sg:tags":[
        "state",
        "program"
    ],
    "wof:name":"Plant Inspection Bureau",
    "wof:placetype":"venue"
},
  "geometry": {"coordinates":[-80.40752000000001,27.433074],"type":"Point"}
}