{
  "type": "Feature",
  "properties": {
    "addr:full":"1717 N 17th Ave Pensacola FL 32503",
    "addr:housenumber":"1717",
    "addr:postcode":"32503",
    "addr:street":"N 17Th Ave",
    "iso:country":"US",
    "sg:address":"1717 N 17th Ave",
    "sg:city":"Pensacola",
    "sg:classifiers":[
        {
            "category":"Building & Trades",
            "subcategory":"Landscaping Services",
            "type":"Services"
        }
    ],
    "sg:phone":"+1 850 438 1480",
    "sg:postcode":"32503",
    "sg:province":"FL",
    "wof:name":"Andy Toben Lawn Care",
    "wof:placetype":"venue"
},
  "geometry": {"coordinates":[-87.19744,30.43438],"type":"Point"}
}