{
  "type": "Feature",
  "properties": {
    "iso:country":"US",
    "sg:address":"447 Oak Point Rd",
    "sg:city":"Osprey",
    "sg:classifiers":[
        {
            "category":"Banks & Credit Unions",
            "subcategory":"Investment Brokerage",
            "type":"Services"
        }
    ],
    "sg:phone":"+1 941 918 8815",
    "sg:postcode":"34229",
    "sg:province":"FL",
    "sg:tags":[
        "advisory",
        "financial"
    ],
    "wof:name":"Opes Enterprises Corp",
    "wof:placetype":"venue"
},
  "geometry": {"coordinates":[-82.489261,27.181293],"type":"Point"}
}