{
  "type": "Feature",
  "properties": {
    "iso:country":"US",
    "sg:address":"68 Laurel Oaks Cir",
    "sg:city":"Jupiter",
    "sg:classifiers":[
        {
            "category":"Shopping",
            "type":"Retail Goods"
        }
    ],
    "sg:phone":"+1 561 748 5660",
    "sg:postcode":"33469",
    "sg:province":"FL",
    "sg:tags":[
        "merchandise"
    ],
    "wof:name":"Pet Pals Pet Sitting Inc",
    "wof:placetype":"venue"
},
  "geometry": {"coordinates":[-80.086034,26.960286],"type":"Point"}
}