{
  "type": "Feature",
  "properties": {
    "addr:full":"3313 Cleveland Ave Fort Myers FL 33901",
    "addr:housenumber":"3313",
    "addr:postcode":"33901",
    "addr:street":"Cleveland Ave",
    "iso:country":"US",
    "sg:address":"3313 Cleveland Ave",
    "sg:city":"Fort Myers",
    "sg:classifiers":[
        {
            "category":"Banks & Credit Unions",
            "subcategory":"Bank",
            "type":"Services"
        }
    ],
    "sg:phone":"+1 239 939 2888",
    "sg:postcode":"33901",
    "sg:province":"FL",
    "sg:tags":[
        "loan",
        "real estate"
    ],
    "wof:name":"Primicias Mortgage Co",
    "wof:placetype":"venue"
},
  "geometry": {"coordinates":[-81.87209199999999,26.616812],"type":"Point"}
}