{
  "type": "Feature",
  "properties": {
    "iso:country":"US",
    "sg:address":"568 Deerfield Rd",
    "sg:city":"Saint Augustine",
    "sg:classifiers":[
        {
            "category":"Building & Trades",
            "subcategory":"Construction",
            "type":"Services"
        }
    ],
    "sg:phone":"+1 904 669 3697",
    "sg:postcode":"32095",
    "sg:province":"FL",
    "sg:tags":[
        "house"
    ],
    "wof:name":"S&S Home Repair",
    "wof:placetype":"venue"
},
  "geometry": {"coordinates":[-81.36823099999999,30.013875],"type":"Point"}
}