{
  "type": "Feature",
  "properties": {
    "addr:full":"4216 Catherine St Panama City Bch FL 32408",
    "addr:housenumber":"4216",
    "addr:postcode":"32408",
    "addr:street":"Catherine St",
    "iso:country":"US",
    "sg:address":"4216 Catherine St",
    "sg:city":"Panama City Bch",
    "sg:classifiers":[
        {
            "category":"Building & Trades",
            "subcategory":"Construction",
            "type":"Services"
        }
    ],
    "sg:phone":"+1 850 236 0350",
    "sg:postcode":"32408",
    "sg:province":"FL",
    "sg:tags":[
        "home",
        "improvement"
    ],
    "wof:name":"R & S Enterprises",
    "wof:placetype":"venue"
},
  "geometry": {"coordinates":[-85.725399,30.156993],"type":"Point"}
}