{
  "type": "Feature",
  "properties": {
    "iso:country":"US",
    "sg:address":"333 Tamiami Trl",
    "sg:city":"Venice",
    "sg:classifiers":[
        {
            "category":"Health Services",
            "subcategory":"Doctor",
            "type":"Services"
        }
    ],
    "sg:phone":"+1 941 473 7754",
    "sg:postcode":"34285",
    "sg:province":"FL",
    "sg:tags":[
        "medical"
    ],
    "wof:name":"Bayside Gynecology Assoc PA",
    "wof:placetype":"venue"
},
  "geometry": {"coordinates":[-82.444248,27.094787],"type":"Point"}
}