{
  "type": "Feature",
  "properties": {
    "addr:full":"8413 Laurel Fair Cir Tampa FL 33610",
    "addr:housenumber":"8413",
    "addr:postcode":"33610",
    "addr:street":"Laurel Fair Cir",
    "iso:country":"US",
    "sg:address":"8413 Laurel Fair Cir",
    "sg:city":"Tampa",
    "sg:classifiers":[
        {
            "category":"Professional",
            "subcategory":"Employment Agencies",
            "type":"Services"
        }
    ],
    "sg:phone":"+1 813 630 1017",
    "sg:postcode":"33610",
    "sg:province":"FL",
    "wof:name":"Apexalon LLC",
    "wof:placetype":"venue"
},
  "geometry": {"coordinates":[-82.356645,27.985956],"type":"Point"}
}