{
  "type": "Feature",
  "properties": {
    "addr:full":"1329 Bessent Rd Starke FL 32091",
    "addr:housenumber":"1329",
    "addr:postcode":"32091",
    "addr:street":"Bessent Rd",
    "iso:country":"US",
    "sg:address":"1329 Bessent Rd",
    "sg:city":"Starke",
    "sg:classifiers":[
        {
            "category":"Health Services",
            "subcategory":"Nursing And Care Facility",
            "type":"Services"
        }
    ],
    "sg:phone":"+1 904 964 1468",
    "sg:postcode":"32091",
    "sg:province":"FL",
    "wof:name":"Bessent Road Group Home",
    "wof:placetype":"venue"
},
  "geometry": {"coordinates":[-82.09472,29.942179],"type":"Point"}
}