{
  "type": "Feature",
  "properties": {
    "addr:full":"16911 61st Pl N Loxahatchee FL 33470",
    "addr:housenumber":"16911",
    "addr:postcode":"33470",
    "addr:street":"61St Pl N",
    "iso:country":"US",
    "sg:address":"16911 61st Pl N",
    "sg:city":"Loxahatchee",
    "sg:classifiers":[
        {
            "category":"Building & Trades",
            "subcategory":"Landscaping Services",
            "type":"Services"
        }
    ],
    "sg:phone":"+1 561 798 3508",
    "sg:postcode":"33470",
    "sg:province":"FL",
    "wof:name":"Precision Cut Lawn Service",
    "wof:placetype":"venue"
},
  "geometry": {"coordinates":[-80.308497,26.767313],"type":"Point"}
}