{
  "type": "Feature",
  "properties": {
    "iso:country":"US",
    "sg:address":"5198 Turnpike Feeder Rd",
    "sg:city":"Fort Pierce",
    "sg:classifiers":[
        {
            "category":"Restaurant",
            "type":"Food & Drink"
        }
    ],
    "sg:phone":"+1 772 595 5019",
    "sg:postcode":"34951",
    "sg:province":"FL",
    "sg:tags":[
        "shop",
        "coffee"
    ],
    "wof:name":"Pelors",
    "wof:placetype":"venue"
},
  "geometry": {"coordinates":[-80.39516999999999,27.527089],"type":"Point"}
}