{
  "type": "Feature",
  "properties": {
    "iso:country":"US",
    "sg:address":"340 Tamiami Trl S",
    "sg:city":"Nokomis",
    "sg:classifiers":[
        {
            "category":"Insurance",
            "subcategory":"Insurance Agent",
            "type":"Services"
        },
        {
            "category":"Insurance",
            "subcategory":"Hazard Insurance",
            "type":"Services"
        },
        {
            "category":"Insurance",
            "subcategory":"Title Insurance",
            "type":"Services"
        },
        {
            "category":"Insurance",
            "subcategory":"Life Insurance",
            "type":"Services"
        }
    ],
    "sg:phone":"+1 941 484 8884",
    "sg:postcode":"34275",
    "sg:province":"FL",
    "sg:tags":[
        "business",
        "auto",
        "commercial",
        "homeowner",
        "motorcycle",
        "renter"
    ],
    "wof:name":"Allstate Insurance Company - Wesley Maksimchuk",
    "wof:placetype":"venue"
},
  "geometry": {"coordinates":[-82.453519,27.122336],"type":"Point"}
}