{
  "type": "Feature",
  "properties": {
    "iso:country":"US",
    "sg:address":"7278 NW 25th St",
    "sg:city":"Miami",
    "sg:classifiers":[
        {
            "category":"Wholesale",
            "subcategory":"Durable Goods & Equipment",
            "type":"Manufacturing & Wholesale Goods"
        },
        {
            "category":"Wholesale",
            "subcategory":"Non-durable Goods",
            "type":"Manufacturing & Wholesale Goods"
        }
    ],
    "sg:phone":"+1 305 592 5073",
    "sg:postcode":"33122",
    "sg:province":"FL",
    "sg:tags":[
        "importer",
        "exporter",
        "novelty",
        "gift"
    ],
    "wof:name":"Mil Imports Inc",
    "wof:placetype":"venue"
},
  "geometry": {"coordinates":[-80.316245,25.796997],"type":"Point"}
}