{
  "type": "Feature",
  "properties": {
    "addr:full":"1928 Purdy Ave Miami Beach FL 33139",
    "addr:housenumber":"1928",
    "addr:postcode":"33139",
    "addr:street":"Purdy Ave",
    "iso:country":"US",
    "sg:address":"1928 Purdy Ave",
    "sg:city":"Miami Beach",
    "sg:classifiers":[
        {
            "category":"Professional",
            "type":"Services"
        }
    ],
    "sg:phone":"+1 305 796 6223",
    "sg:postcode":"33139",
    "sg:province":"FL",
    "sg:tags":[
        "establishment"
    ],
    "wof:name":"Petro Systems",
    "wof:placetype":"venue"
},
  "geometry": {"coordinates":[-80.14432600000001,25.791757],"type":"Point"}
}