{
  "type": "Feature",
  "properties": {
    "addr:full":"960 S Dixie Hwy W Pompano Beach FL 33060",
    "addr:housenumber":"960",
    "addr:postcode":"33060",
    "addr:street":"S Dixie Hwy W",
    "iso:country":"US",
    "sg:address":"960 S Dixie Hwy W",
    "sg:city":"Pompano Beach",
    "sg:classifiers":[
        {
            "category":"Retail",
            "subcategory":"Auto Repair",
            "type":"Services"
        }
    ],
    "sg:phone":"+1 954 946 8606",
    "sg:postcode":"33060",
    "sg:province":"FL",
    "sg:tags":[
        "automotive",
        "exhaust"
    ],
    "wof:name":"Mad Hatter Mufflers",
    "wof:placetype":"venue"
},
  "geometry": {"coordinates":[-80.131584,26.216497],"type":"Point"}
}