{
  "type": "Feature",
  "properties": {
    "iso:country":"US",
    "sg:address":"6001 15th St E",
    "sg:city":"Bradenton",
    "sg:classifiers":[
        {
            "category":"Home & Garden",
            "subcategory":"Garden Supply",
            "type":"Retail Goods"
        }
    ],
    "sg:phone":"+1 941 755 9299",
    "sg:postcode":"34203",
    "sg:province":"FL",
    "sg:tags":[
        "landscaping",
        "equipment"
    ],
    "wof:name":"Wholesale Landscape Supply",
    "wof:placetype":"venue"
},
  "geometry": {"coordinates":[-82.546604,27.436538],"type":"Point"}
}