{
  "type": "Feature",
  "properties": {
    "iso:country":"US",
    "sg:address":"1860 Alhambra St",
    "sg:city":"Gulf Breeze",
    "sg:classifiers":[
        {
            "category":"Wholesale",
            "subcategory":"Seafood",
            "type":"Manufacturing & Wholesale Goods"
        }
    ],
    "sg:phone":"+1 850 936 5058",
    "sg:postcode":"32566",
    "sg:province":"FL",
    "wof:name":"M & S Champion Fisheries Inc",
    "wof:placetype":"venue"
},
  "geometry": {"coordinates":[-86.864052,30.403879],"type":"Point"}
}