{
  "type": "Feature",
  "properties": {
    "addr:full":"3906 N Washington Blvd Sarasota FL 34234",
    "addr:housenumber":"3906",
    "addr:postcode":"34234",
    "addr:street":"N Washington Blvd",
    "iso:country":"US",
    "sg:address":"3906 N Washington Blvd",
    "sg:city":"Sarasota",
    "sg:classifiers":[
        {
            "category":"Building & Trades",
            "subcategory":"Construction",
            "type":"Services"
        }
    ],
    "sg:phone":"+1 941 954 8468",
    "sg:postcode":"34234",
    "sg:province":"FL",
    "sg:tags":[
        "contractor"
    ],
    "wof:name":"Designer Glass Tinting North",
    "wof:placetype":"venue"
},
  "geometry": {"coordinates":[-82.530672,27.368691],"type":"Point"}
}