{
  "type": "Feature",
  "properties": {
    "iso:country":"US",
    "sg:address":"4841 NW 11th Ct",
    "sg:city":"Lauderhill",
    "sg:classifiers":[
        {
            "category":"Real Estate",
            "subcategory":"Real Estate Services",
            "type":"Services"
        },
        {
            "category":"Real Estate",
            "subcategory":"Real Estate Agent",
            "type":"Services"
        }
    ],
    "sg:phone":"+1 954 791 4911",
    "sg:postcode":"33313",
    "sg:province":"FL",
    "sg:tags":[
        "buyer",
        "broker"
    ],
    "wof:name":"Florida Home Search.Com",
    "wof:placetype":"venue"
},
  "geometry": {"coordinates":[-80.21636100000001,26.138863],"type":"Point"}
}