{
  "type": "Feature",
  "properties": {
    "iso:country":"US",
    "sg:address":"9981 S Arabian Ave",
    "sg:city":"Floral City",
    "sg:classifiers":[
        {
            "category":"Real Estate",
            "subcategory":"Real Estate Agent",
            "type":"Services"
        }
    ],
    "sg:phone":"+1 352 637 4280",
    "sg:postcode":"34436",
    "sg:province":"FL",
    "wof:name":"Inverness Horizon Realty",
    "wof:placetype":"venue"
},
  "geometry": {"coordinates":[-82.29940499999999,28.717687],"type":"Point"}
}