{
  "type": "Feature",
  "properties": {
    "addr:full":"5810 Erhardt Dr Riverview FL 33578",
    "addr:housenumber":"5810",
    "addr:postcode":"33578",
    "addr:street":"Erhardt Dr",
    "iso:country":"US",
    "sg:address":"5810 Erhardt Dr",
    "sg:city":"Riverview",
    "sg:classifiers":[
        {
            "category":"Professional",
            "subcategory":"Management & Consulting",
            "type":"Services"
        }
    ],
    "sg:phone":"+1 813 685 3351",
    "sg:postcode":"33578",
    "sg:province":"FL",
    "wof:name":"F T B Consultants Inc",
    "wof:placetype":"venue"
},
  "geometry": {"coordinates":[-82.30428000000001,27.894568],"type":"Point"}
}