{
  "type": "Feature",
  "properties": {
    "addr:full":"6525 Jog Rd Lake Worth FL 33467",
    "addr:housenumber":"6525",
    "addr:postcode":"33467",
    "addr:street":"Jog Rd",
    "iso:country":"US",
    "sg:address":"6525 Jog Rd",
    "sg:city":"Lake Worth",
    "sg:classifiers":[
        {
            "category":"Farming",
            "subcategory":"Dairy Farm",
            "type":"Manufacturing & Wholesale Goods"
        }
    ],
    "sg:phone":"+1 561 966 4138",
    "sg:postcode":"33467",
    "sg:province":"FL",
    "wof:name":"Smith Dairy Maintenance",
    "wof:placetype":"venue"
},
  "geometry": {"coordinates":[-80.146056,26.579894],"type":"Point"}
}