{
  "type": "Feature",
  "properties": {
    "iso:country":"US",
    "sg:address":"105 E Gregory St",
    "sg:city":"Pensacola",
    "sg:classifiers":[
        {
            "category":"Professional",
            "subcategory":"Lawyer & Legal Services",
            "type":"Services"
        }
    ],
    "sg:phone":"+1 850 434 5395",
    "sg:postcode":"32501",
    "sg:province":"FL",
    "wof:name":"Whibbs & Whibbs Pa Inc",
    "wof:placetype":"venue"
},
  "geometry": {"coordinates":[-87.21328800000001,30.416241],"type":"Point"}
}