{
  "type": "Feature",
  "properties": {
    "addr:full":"3191 Havendale Blvd NW Winter Haven FL 33881",
    "addr:housenumber":"3191",
    "addr:postcode":"33881",
    "addr:street":"Havendale Blvd Nw",
    "iso:country":"US",
    "sg:address":"3191 Havendale Blvd NW",
    "sg:city":"Winter Haven",
    "sg:classifiers":[
        {
            "category":"Retail",
            "subcategory":"Auto Repair",
            "type":"Services"
        }
    ],
    "sg:phone":"+1 863 967 0555",
    "sg:postcode":"33881",
    "sg:province":"FL",
    "sg:tags":[
        "muffler",
        "exhaust",
        "system"
    ],
    "wof:name":"Barber Auto Supply Inc",
    "wof:placetype":"venue"
},
  "geometry": {"coordinates":[-81.753192,28.046347],"type":"Point"}
}