{
  "type": "Feature",
  "properties": {
    "addr:full":"402 15th St E Bradenton FL 34208",
    "addr:housenumber":"402",
    "addr:postcode":"34208",
    "addr:street":"15Th St",
    "iso:country":"US",
    "sg:address":"402 15th St E",
    "sg:city":"Bradenton",
    "sg:classifiers":[
        {
            "category":"Organizations",
            "subcategory":"Community Association",
            "type":"Services"
        }
    ],
    "sg:phone":"+1 941 746 8263",
    "sg:postcode":"34208",
    "sg:province":"FL",
    "wof:name":"Manatee Masonic Lodge No 31",
    "wof:placetype":"venue"
},
  "geometry": {"coordinates":[-82.547544,27.495848],"type":"Point"}
}