{
  "type": "Feature",
  "properties": {
    "iso:country":"US",
    "sg:address":"3834 N University Dr",
    "sg:city":"Sunrise",
    "sg:classifiers":[
        {
            "category":"Deli",
            "type":"Food & Drink"
        },
        {
            "category":"Restaurant",
            "type":"Food & Drink"
        },
        {
            "category":"Food & Beverages",
            "subcategory":"Groceries & Convenience Stores",
            "type":"Retail Goods"
        }
    ],
    "sg:phone":"+1 954 318 6180",
    "sg:postcode":"33351",
    "sg:province":"FL",
    "sg:tags":[
        "shop",
        "delicatessen",
        "sandwich"
    ],
    "wof:name":"La Casita Roja",
    "wof:placetype":"venue"
},
  "geometry": {"coordinates":[-80.25581200000001,26.172063],"type":"Point"}
}