{
  "type": "Feature",
  "properties": {
    "addr:full":"1333 N Adams St Tallahassee FL 32303",
    "addr:housenumber":"1333",
    "addr:postcode":"32303",
    "addr:street":"N Adams St",
    "iso:country":"US",
    "sg:address":"1333 N Adams St",
    "sg:city":"Tallahassee",
    "sg:classifiers":[
        {
            "category":"Professional",
            "subcategory":"Computer Services",
            "type":"Services"
        }
    ],
    "sg:phone":"+1 850 577 1411",
    "sg:postcode":"32303",
    "sg:province":"FL",
    "sg:tags":[
        "consultant",
        "designer"
    ],
    "wof:name":"Technology Services Group",
    "wof:placetype":"venue"
},
  "geometry": {"coordinates":[-84.281825,30.457354],"type":"Point"}
}