{
  "type": "Feature",
  "properties": {
    "iso:country":"US",
    "sg:address":"2450 NW 5th Ave",
    "sg:city":"Boca Raton",
    "sg:classifiers":[
        {
            "category":"Organizations",
            "subcategory":"Non-profit Organization",
            "type":"Services"
        },
        {
            "category":"Social Services",
            "subcategory":"Child Care",
            "type":"Services"
        }
    ],
    "sg:phone":"+1 561 394 7674",
    "sg:postcode":"33431",
    "sg:province":"FL",
    "sg:tags":[
        "day"
    ],
    "wof:name":"Claremont Montessori Ctr Schl",
    "wof:placetype":"venue"
},
  "geometry": {"coordinates":[-80.09415,26.37362],"type":"Point"}
}