{
  "type": "Feature",
  "properties": {
    "iso:country":"US",
    "sg:address":"8500 53rd Way",
    "sg:city":"Pinellas Park",
    "sg:classifiers":[
        {
            "category":"Professional",
            "subcategory":"Management & Consulting",
            "type":"Services"
        }
    ],
    "sg:phone":"+1 727 544 7127",
    "sg:postcode":"33781",
    "sg:province":"FL",
    "sg:tags":[
        "marketing",
        "consultant"
    ],
    "wof:name":"JMR Consulting Inc",
    "wof:placetype":"venue"
},
  "geometry": {"coordinates":[-82.706777,27.849339],"type":"Point"}
}