{
  "type": "Feature",
  "properties": {
    "addr:full":"2875 SW 30th Ave Hallandale FL 33009",
    "addr:housenumber":"2875",
    "addr:postcode":"33009",
    "addr:street":"Sw 30Th Ave",
    "iso:country":"US",
    "sg:address":"2875 SW 30th Ave",
    "sg:city":"Hallandale",
    "sg:classifiers":[
        {
            "category":"Real Estate",
            "subcategory":"Real Estate Agent",
            "type":"Services"
        }
    ],
    "sg:phone":"+1 954 456 1085",
    "sg:postcode":"33009",
    "sg:province":"FL",
    "wof:name":"Aid Auto Brokers Inc",
    "wof:placetype":"venue"
},
  "geometry": {"coordinates":[-80.166687,25.985044],"type":"Point"}
}