{
  "type": "Feature",
  "properties": {
    "addr:full":"686 Anchor Dr Sanibel FL 33957",
    "addr:housenumber":"686",
    "addr:postcode":"33957",
    "addr:street":"Anchor Dr",
    "iso:country":"US",
    "sg:address":"686 Anchor Dr",
    "sg:city":"Sanibel",
    "sg:classifiers":[
        {
            "category":"Building & Trades",
            "subcategory":"Construction",
            "type":"Services"
        }
    ],
    "sg:phone":"+1 239 395 2620",
    "sg:postcode":"33957",
    "sg:province":"FL",
    "sg:tags":[
        "house"
    ],
    "wof:name":"Ce Wlker Cnstrn Co SW FL",
    "wof:placetype":"venue"
},
  "geometry": {"coordinates":[-82.031887,26.448507],"type":"Point"}
}