{
  "type": "Feature",
  "properties": {
    "iso:country":"US",
    "sg:address":"118 NW 2nd St",
    "sg:city":"Hallandale Beach",
    "sg:classifiers":[
        {
            "category":"Home & Garden",
            "subcategory":"Building Materials",
            "type":"Retail Goods"
        }
    ],
    "sg:phone":"+1 305 318 5071",
    "sg:postcode":"33009",
    "sg:province":"FL",
    "sg:tags":[
        "plate",
        "supply",
        "yacht",
        "glass",
        "window",
        "install"
    ],
    "wof:name":"All Around Glass Inc",
    "wof:placetype":"venue"
},
  "geometry": {"coordinates":[-80.150295,25.987901],"type":"Point"}
}