{
  "type": "Feature",
  "properties": {
    "iso:country":"US",
    "sg:address":"2124 S Peninsula Dr",
    "sg:city":"Daytona Beach",
    "sg:classifiers":[
        {
            "category":"Building & Trades",
            "subcategory":"Construction",
            "type":"Services"
        }
    ],
    "sg:phone":"+1 386 253 7313",
    "sg:postcode":"32118",
    "sg:province":"FL",
    "sg:tags":[
        "floor",
        "laying",
        "contractor"
    ],
    "wof:name":"Wrights Flooring LLC",
    "wof:placetype":"venue"
},
  "geometry": {"coordinates":[-80.996855,29.196085],"type":"Point"}
}