{
  "type": "Feature",
  "properties": {
    "addr:full":"1510 Old Dixie Hwy Titusville FL 32796",
    "addr:housenumber":"1510",
    "addr:postcode":"32796",
    "addr:street":"Old Dixie Hwy",
    "iso:country":"US",
    "sg:address":"1510 Old Dixie Hwy",
    "sg:city":"Titusville",
    "sg:classifiers":[
        {
            "category":"Home & Garden",
            "subcategory":"Garden Supply",
            "type":"Retail Goods"
        }
    ],
    "sg:phone":"+1 321 268 2975",
    "sg:postcode":"32796",
    "sg:province":"FL",
    "sg:tags":[
        "nurseryman"
    ],
    "wof:name":"Growing Crazy",
    "wof:placetype":"venue"
},
  "geometry": {"coordinates":[-80.836381,28.637525],"type":"Point"}
}