{
  "type": "Feature",
  "properties": {
    "iso:country":"US",
    "sg:address":"16429 NW 16th St",
    "sg:city":"Hollywood",
    "sg:classifiers":[
        {
            "category":"Real Estate",
            "subcategory":"Real Estate Agent",
            "type":"Services"
        }
    ],
    "sg:phone":"+1 954 384 1732",
    "sg:postcode":"33028",
    "sg:province":"FL",
    "wof:name":"Roger Lander PA",
    "wof:placetype":"venue"
},
  "geometry": {"coordinates":[-80.36353,26.02215],"type":"Point"}
}