{
  "type": "Feature",
  "properties": {
    "addr:full":"7604 Cortez Rd W Bradenton FL 34210",
    "addr:housenumber":"7604",
    "addr:postcode":"34210",
    "addr:street":"Cortez Rd W",
    "iso:country":"US",
    "sg:address":"7604 Cortez Rd W",
    "sg:city":"Bradenton",
    "sg:classifiers":[
        {
            "category":"Real Estate",
            "subcategory":"Real Estate Agent",
            "type":"Services"
        }
    ],
    "sg:phone":"+1 941 795 2300",
    "sg:postcode":"34210",
    "sg:province":"FL",
    "wof:name":"Sandra Lee La Barre",
    "wof:placetype":"venue"
},
  "geometry": {"coordinates":[-82.639983,27.46237],"type":"Point"}
}