{
  "type": "Feature",
  "properties": {
    "iso:country":"US",
    "sg:address":"7238 W 31st Ave",
    "sg:city":"Hialeah",
    "sg:classifiers":[
        {
            "category":"Real Estate",
            "subcategory":"Real Estate Operator",
            "type":"Services"
        }
    ],
    "sg:phone":"+1 305 885 5025",
    "sg:postcode":"33018",
    "sg:province":"FL",
    "sg:tags":[
        "building",
        "parks"
    ],
    "wof:name":"777 Business Ctr",
    "wof:placetype":"venue"
},
  "geometry": {"coordinates":[-80.34599799999999,25.888122],"type":"Point"}
}