{
  "type": "Feature",
  "properties": {
    "addr:full":"705 S Olive Ave West Palm Beach FL 33401",
    "addr:housenumber":"705",
    "addr:postcode":"33401",
    "addr:street":"S Olive Ave",
    "iso:country":"US",
    "sg:address":"705 S Olive Ave",
    "sg:city":"West Palm Beach",
    "sg:classifiers":[
        {
            "category":"Government",
            "subcategory":"Office",
            "type":"Public Place"
        }
    ],
    "sg:phone":"+1 561 355 3082",
    "sg:postcode":"33401",
    "sg:province":"FL",
    "sg:tags":[
        "county",
        "program",
        "health"
    ],
    "wof:name":"Public Health Dentistry",
    "wof:placetype":"venue"
},
  "geometry": {"coordinates":[-80.052144,26.70626],"type":"Point"}
}