{
  "type": "Feature",
  "properties": {
    "iso:country":"US",
    "sg:address":"7205 Estero Blvd",
    "sg:city":"Fort Myers Beach",
    "sg:classifiers":[
        {
            "category":"Food & Beverages",
            "subcategory":"Liquor & Beverages",
            "type":"Retail Goods"
        }
    ],
    "sg:phone":"+1 239 463 4013",
    "sg:postcode":"33931",
    "sg:province":"FL",
    "sg:tags":[
        "store"
    ],
    "wof:name":"Nicolas Liquors",
    "wof:placetype":"venue"
},
  "geometry": {"coordinates":[-81.89840100000001,26.409785],"type":"Point"}
}