{
  "type": "Feature",
  "properties": {
    "iso:country":"US",
    "sg:address":"2301 NW 102nd Way",
    "sg:city":"Hollywood",
    "sg:classifiers":[
        {
            "category":"Building & Trades",
            "subcategory":"Landscaping Services",
            "type":"Services"
        }
    ],
    "sg:phone":"+1 954 431 0732",
    "sg:postcode":"33026",
    "sg:province":"FL",
    "sg:tags":[
        "lawn",
        "commercial"
    ],
    "wof:name":"Elan Lawn Service",
    "wof:placetype":"venue"
},
  "geometry": {"coordinates":[-80.28356100000001,26.028198],"type":"Point"}
}