{
  "type": "Feature",
  "properties": {
    "iso:country":"US",
    "sg:address":"8569 Pines Blvd",
    "sg:city":"Pembroke Pines",
    "sg:classifiers":[
        {
            "category":"Personal",
            "type":"Services"
        }
    ],
    "sg:phone":"+1 954 499 7360",
    "sg:postcode":"33024",
    "sg:province":"FL",
    "sg:tags":[
        "credit",
        "debt",
        "counseling"
    ],
    "wof:name":"Avalon Settlement & Credit Rpr",
    "wof:placetype":"venue"
},
  "geometry": {"coordinates":[-80.257514,26.009063],"type":"Point"}
}