{
  "type": "Feature",
  "properties": {
    "iso:country":"US",
    "sg:address":"17817 SE 132nd Ct",
    "sg:city":"Weirsdale",
    "sg:classifiers":[
        {
            "category":"Building & Trades",
            "subcategory":"Landscaping Services",
            "type":"Services"
        }
    ],
    "sg:phone":"+1 352 821 2266",
    "sg:postcode":"32195",
    "sg:province":"FL",
    "sg:tags":[
        "landscape"
    ],
    "wof:name":"S & S Lawns",
    "wof:placetype":"venue"
},
  "geometry": {"coordinates":[-81.933682,28.964945],"type":"Point"}
}