{
  "type": "Feature",
  "properties": {
    "iso:country":"US",
    "sg:address":"9240 SW 72nd St Ste 229",
    "sg:city":"Miami",
    "sg:classifiers":[
        {
            "category":"Personal",
            "subcategory":"Hair Removal",
            "type":"Services"
        }
    ],
    "sg:phone":"+1 305 270 3925",
    "sg:postcode":"33173",
    "sg:province":"FL",
    "wof:name":"Laser Center of Miami",
    "wof:placetype":"venue"
},
  "geometry": {"coordinates":[-80.342945,25.701738],"type":"Point"}
}