{
  "type": "Feature",
  "properties": {
    "addr:full":"3348 Maryland Ave Sebring FL 33872",
    "addr:housenumber":"3348",
    "addr:postcode":"33872",
    "addr:street":"Maryland Ave",
    "iso:country":"US",
    "sg:address":"3348 Maryland Ave",
    "sg:city":"Sebring",
    "sg:classifiers":[
        {
            "category":"Manufacturing",
            "subcategory":"Electronics",
            "type":"Manufacturing & Wholesale Goods"
        }
    ],
    "sg:phone":"+1 863 471 1841",
    "sg:postcode":"33872",
    "sg:province":"FL",
    "sg:tags":[
        "equipment",
        "mfg",
        "home"
    ],
    "wof:name":"Stephens Jrry All Star Karaoke",
    "wof:placetype":"venue"
},
  "geometry": {"coordinates":[-81.499368,27.520413],"type":"Point"}
}