{
  "type": "Feature",
  "properties": {
    "addr:full":"707 Tarpon Bay Rd Sanibel FL 33957",
    "addr:housenumber":"707",
    "addr:postcode":"33957",
    "addr:street":"Tarpon Bay Rd",
    "iso:country":"US",
    "sg:address":"707 Tarpon Bay Rd",
    "sg:city":"Sanibel",
    "sg:classifiers":[
        {
            "category":"Restaurant",
            "type":"Food & Drink"
        }
    ],
    "sg:phone":"+1 239 472 3128",
    "sg:postcode":"33957",
    "sg:province":"FL",
    "sg:website":"www.sanibeleats.com",
    "wof:name":"Timbers Fish Market",
    "wof:placetype":"venue"
},
  "geometry": {"coordinates":[-82.080153,26.437375],"type":"Point"}
}