{
  "type": "Feature",
  "properties": {
    "iso:country":"US",
    "sg:address":"341 N Maitland Ave",
    "sg:city":"Maitland",
    "sg:classifiers":[
        {
            "category":"Professional",
            "subcategory":"Lawyer & Legal Services",
            "type":"Services"
        }
    ],
    "sg:phone":"+1 407 622 0500",
    "sg:postcode":"32751",
    "sg:province":"FL",
    "wof:name":"Crowell Donald N",
    "wof:placetype":"venue"
},
  "geometry": {"coordinates":[-81.366578,28.63031],"type":"Point"}
}