{
  "type": "Feature",
  "properties": {
    "iso:country":"US",
    "sg:address":"5950 W Oakland Park Blvd",
    "sg:city":"Lauderhill",
    "sg:classifiers":[
        {
            "category":"Personal",
            "type":"Services"
        }
    ],
    "sg:phone":"+1 954 486 0830",
    "sg:postcode":"33313",
    "sg:province":"FL",
    "sg:tags":[
        "credit",
        "debt",
        "counseling"
    ],
    "sg:website":"www.bedebtfree.com",
    "wof:name":"Amalgamated Credit Counselors",
    "wof:placetype":"venue"
},
  "geometry": {"coordinates":[-80.22709399999999,26.164784],"type":"Point"}
}