{
  "type": "Feature",
  "properties": {
    "iso:country":"US",
    "sg:address":"3805 Biscayne Dr",
    "sg:city":"Winter Springs",
    "sg:classifiers":[
        {
            "category":"Real Estate",
            "subcategory":"Real Estate Agent",
            "type":"Services"
        }
    ],
    "sg:phone":"+1 407 699 5355",
    "sg:postcode":"32708",
    "sg:province":"FL",
    "wof:name":"Medical Bilding Services",
    "wof:placetype":"venue"
},
  "geometry": {"coordinates":[-81.276678,28.653275],"type":"Point"}
}