{
  "type": "Feature",
  "properties": {
    "iso:country":"US",
    "sg:address":"8950 NE 2nd Ave",
    "sg:city":"El Portal",
    "sg:classifiers":[
        {
            "category":"Education",
            "subcategory":"School",
            "type":"Public Place"
        }
    ],
    "sg:phone":"+1 305 757 9537",
    "sg:postcode":"33138",
    "sg:province":"FL",
    "sg:tags":[
        "high",
        "middle",
        "elementary"
    ],
    "wof:name":"Miami-Dade County Public Schools",
    "wof:placetype":"venue"
},
  "geometry": {"coordinates":[-80.193196,25.857362],"type":"Point"}
}