{
  "type": "Feature",
  "properties": {
    "addr:full":"2445 Success Dr Odessa FL 33556",
    "addr:housenumber":"2445",
    "addr:postcode":"33556",
    "addr:street":"Success Dr",
    "iso:country":"US",
    "sg:address":"2445 Success Dr",
    "sg:city":"Odessa",
    "sg:classifiers":[
        {
            "category":"Manufacturing",
            "subcategory":"Electronics",
            "type":"Manufacturing & Wholesale Goods"
        }
    ],
    "sg:phone":"+1 727 376 6655",
    "sg:postcode":"33556",
    "sg:province":"FL",
    "sg:tags":[
        "resistor"
    ],
    "sg:website":"www.componentgeneral.com",
    "wof:name":"Component General Inc",
    "wof:placetype":"venue"
},
  "geometry": {"coordinates":[-82.62606599999999,28.194052],"type":"Point"}
}