{
  "type": "Feature",
  "properties": {
    "addr:full":"2620 Old New York Ave De Land FL 32720",
    "addr:housenumber":"2620",
    "addr:postcode":"32720",
    "addr:street":"Old New York Ave",
    "iso:country":"US",
    "sg:address":"2620 Old New York Ave",
    "sg:city":"De Land",
    "sg:classifiers":[
        {
            "category":"Wholesale",
            "subcategory":"Machinery & Supplies",
            "type":"Manufacturing & Wholesale Goods"
        }
    ],
    "sg:phone":"+1 386 736 8760",
    "sg:postcode":"32720",
    "sg:province":"FL",
    "sg:tags":[
        "hardware",
        "equipment",
        "industrial"
    ],
    "wof:name":"I P T",
    "wof:placetype":"venue"
},
  "geometry": {"coordinates":[-81.35955199999999,29.014239],"type":"Point"}
}