{
  "type": "Feature",
  "properties": {
    "iso:country":"US",
    "sg:address":"1328 Washington St",
    "sg:city":"Hollywood",
    "sg:classifiers":[
        {
            "category":"Wholesale",
            "subcategory":"Metals & Minerals",
            "type":"Manufacturing & Wholesale Goods"
        }
    ],
    "sg:phone":"+1 954 921 7880",
    "sg:postcode":"33019",
    "sg:province":"FL",
    "sg:tags":[
        "center"
    ],
    "wof:name":"Par Tech",
    "wof:placetype":"venue"
},
  "geometry": {"coordinates":[-80.134129,26.004357],"type":"Point"}
}