{
  "type": "Feature",
  "properties": {
    "addr:full":"122 6th St S Saint Petersburg FL 33701",
    "addr:housenumber":"122",
    "addr:postcode":"33701",
    "addr:street":"6Th St S",
    "iso:country":"US",
    "sg:address":"122 6th St S",
    "sg:city":"Saint Petersburg",
    "sg:classifiers":[
        {
            "category":"Professional",
            "subcategory":"Advertising",
            "type":"Services"
        }
    ],
    "sg:phone":"+1 727 896 4566",
    "sg:postcode":"33701",
    "sg:province":"FL",
    "sg:tags":[
        "agency",
        "promotional"
    ],
    "wof:name":"Chaslo Mdse & Promotions",
    "wof:placetype":"venue"
},
  "geometry": {"coordinates":[-82.64163600000001,27.769622],"type":"Point"}
}