{
  "type": "Feature",
  "properties": {
    "addr:full":"2285 W Eau Gallie Blvd Melbourne FL 32935",
    "addr:housenumber":"2285",
    "addr:postcode":"32935",
    "addr:street":"W Eau Gallie Blvd",
    "iso:country":"US",
    "sg:address":"2285 W Eau Gallie Blvd",
    "sg:city":"Melbourne",
    "sg:classifiers":[
        {
            "category":"Professional",
            "subcategory":"Lawyer & Legal Services",
            "type":"Services"
        }
    ],
    "sg:phone":"+1 321 636 9803",
    "sg:postcode":"32935",
    "sg:province":"FL",
    "sg:tags":[
        "attorney"
    ],
    "wof:name":"Neil J Buchalter",
    "wof:placetype":"venue"
},
  "geometry": {"coordinates":[-80.65503,28.128831],"type":"Point"}
}