{
  "type": "Feature",
  "properties": {
    "iso:country":"US",
    "sg:address":"115 S Woodlawn Ave",
    "sg:city":"Bartow",
    "sg:classifiers":[
        {
            "category":"Home & Garden",
            "subcategory":"Building Materials",
            "type":"Retail Goods"
        },
        {
            "category":"Home & Garden",
            "subcategory":"Hardware",
            "type":"Retail Goods"
        }
    ],
    "sg:phone":"+1 863 533 0806",
    "sg:postcode":"33830",
    "sg:province":"FL",
    "wof:name":"Whit's Building Supply Inc",
    "wof:placetype":"venue"
},
  "geometry": {"coordinates":[-81.851631,27.896117],"type":"Point"}
}