{
  "type": "Feature",
  "properties": {
    "iso:country":"US",
    "sg:address":"18710 SW 107th Ave Unit 8",
    "sg:city":"Cutler Bay",
    "sg:classifiers":[
        {
            "category":"Shopping",
            "subcategory":"Mobile Phones",
            "type":"Retail Goods"
        }
    ],
    "sg:phone":"+1 305 971 8701",
    "sg:postcode":"33157",
    "sg:province":"FL",
    "wof:name":"Sns Digital & Wireless",
    "wof:placetype":"venue"
},
  "geometry": {"coordinates":[-80.364682,25.594003],"type":"Point"}
}