{
  "type": "Feature",
  "properties": {
    "iso:country":"US",
    "sg:address":"10395 State Rd 60",
    "sg:city":"Vero Beach",
    "sg:classifiers":[
        {
            "category":"Professional",
            "subcategory":"Management & Consulting",
            "type":"Services"
        }
    ],
    "sg:phone":"+1 772 538 3150",
    "sg:postcode":"32966",
    "sg:province":"FL",
    "wof:name":"Holland Management LLC",
    "wof:placetype":"venue"
},
  "geometry": {"coordinates":[-80.53303,27.639229],"type":"Point"}
}