{
  "type": "Feature",
  "properties": {
    "addr:full":"685 S Yonge St Ormond Beach FL 32174",
    "addr:housenumber":"685",
    "addr:postcode":"32174",
    "addr:street":"S Yonge St",
    "iso:country":"US",
    "sg:address":"685 S Yonge St",
    "sg:city":"Ormond Beach",
    "sg:classifiers":[
        {
            "category":"Home & Garden",
            "subcategory":"Furniture",
            "type":"Retail Goods"
        }
    ],
    "sg:phone":"+1 386 677 7974",
    "sg:postcode":"32174",
    "sg:province":"FL",
    "sg:website":"www.kittyscottsfurniture.com",
    "wof:name":"Kitty Scott's Fine Furniture",
    "wof:placetype":"venue"
},
  "geometry": {"coordinates":[-81.053245,29.266841],"type":"Point"}
}