{
  "type": "Feature",
  "properties": {
    "iso:country":"US",
    "sg:address":"1614 E Shotwell St",
    "sg:city":"Bainbridge",
    "sg:classifiers":[
        {
            "category":"Food & Beverages",
            "subcategory":"Groceries & Convenience Stores",
            "type":"Retail Goods"
        }
    ],
    "sg:phone":"+1 229 243 0395",
    "sg:postcode":"39819",
    "sg:province":"FL",
    "sg:tags":[
        "grocer"
    ],
    "wof:name":"Harvey's Supermarket",
    "wof:placetype":"venue"
},
  "geometry": {"coordinates":[-84.550504,30.903769],"type":"Point"}
}