{
  "type": "Feature",
  "properties": {
    "addr:full":"222 NW 15th St Delray Beach FL 33444",
    "addr:housenumber":"222",
    "addr:postcode":"33444",
    "addr:street":"Nw 15Th St",
    "iso:country":"US",
    "sg:address":"222 NW 15th St",
    "sg:city":"Delray Beach",
    "sg:classifiers":[
        {
            "category":"Professional",
            "subcategory":"Business Services",
            "type":"Services"
        }
    ],
    "sg:phone":"+1 561 243 9165",
    "sg:postcode":"33444",
    "sg:province":"FL",
    "sg:tags":[
        "interior",
        "consultant",
        "design",
        "decorator"
    ],
    "wof:name":"Andrea Sherman Designs",
    "wof:placetype":"venue"
},
  "geometry": {"coordinates":[-80.07720500000001,26.480557],"type":"Point"}
}