{
  "type": "Feature",
  "properties": {
    "iso:country":"US",
    "sg:address":"2022 E Eskimo Ave",
    "sg:city":"Tampa",
    "sg:classifiers":[
        {
            "category":"Building & Trades",
            "subcategory":"Landscaping Services",
            "type":"Services"
        }
    ],
    "sg:phone":"+1 813 935 8530",
    "sg:postcode":"33604",
    "sg:province":"FL",
    "wof:name":"MO Mows Lawn Service",
    "wof:placetype":"venue"
},
  "geometry": {"coordinates":[-82.435046,28.029767],"type":"Point"}
}