{
  "type": "Feature",
  "properties": {
    "addr:full":"3208 NW Federal Hwy Jensen Beach FL 34957",
    "addr:housenumber":"3208",
    "addr:postcode":"34957",
    "addr:street":"Nw Federal Hwy",
    "iso:country":"US",
    "sg:address":"3208 NW Federal Hwy",
    "sg:city":"Jensen Beach",
    "sg:classifiers":[
        {
            "category":"Personal",
            "subcategory":"Beauty Salon",
            "type":"Services"
        }
    ],
    "sg:phone":"+1 772 692 8595",
    "sg:postcode":"34957",
    "sg:province":"FL",
    "wof:name":"Mia & Maxx Hair Studio",
    "wof:placetype":"venue"
},
  "geometry": {"coordinates":[-80.270056,27.239389],"type":"Point"}
}