{
  "type": "Feature",
  "properties": {
    "iso:country":"US",
    "sg:address":"12140 Cortez Blvd",
    "sg:city":"Brooksville",
    "sg:classifiers":[
        {
            "category":"Health Services",
            "subcategory":"Doctor",
            "type":"Services"
        }
    ],
    "sg:phone":"+1 352 666 1441",
    "sg:postcode":"34613",
    "sg:province":"FL",
    "sg:tags":[
        "physician",
        "surgeon"
    ],
    "wof:name":"Gastroenterology Assoc-West",
    "wof:placetype":"venue"
},
  "geometry": {"coordinates":[-82.52158900000001,28.533648],"type":"Point"}
}