{
  "type": "Feature",
  "properties": {
    "addr:full":"10095 SW 88th St Ste 101 Miami FL 33176",
    "addr:housenumber":"10095",
    "addr:postcode":"33176",
    "addr:street":"Sw 88Th St Ste 101",
    "iso:country":"US",
    "sg:address":"10095 SW 88th St Ste 101",
    "sg:city":"Miami",
    "sg:classifiers":[
        {
            "category":"Social Services",
            "subcategory":"Child Care",
            "type":"Services"
        }
    ],
    "sg:phone":"+1 305 279 9164",
    "sg:postcode":"33176",
    "sg:province":"FL",
    "sg:tags":[
        "day"
    ],
    "wof:name":"Victoria's Playhouse",
    "wof:placetype":"venue"
},
  "geometry": {"coordinates":[-80.356903,25.6873],"type":"Point"}
}