{
  "type": "Feature",
  "properties": {
    "iso:country":"US",
    "sg:address":"2261 E Sample Rd",
    "sg:city":"Pompano Beach",
    "sg:classifiers":[
        {
            "category":"Restaurant",
            "type":"Food & Drink"
        }
    ],
    "sg:phone":"+1 954 941 2348",
    "sg:postcode":"33064",
    "sg:province":"FL",
    "sg:tags":[
        "lounge"
    ],
    "wof:name":"Caps Place Island Restaurant",
    "wof:placetype":"venue"
},
  "geometry": {"coordinates":[-80.091651,26.275639],"type":"Point"}
}