{
  "type": "Feature",
  "properties": {
    "iso:country":"US",
    "sg:address":"2464 E Sunrise Blvd",
    "sg:city":"Fort Lauderdale",
    "sg:classifiers":[
        {
            "category":"Shopping",
            "subcategory":"Clothing, Apparel, & Fashions",
            "type":"Retail Goods"
        }
    ],
    "sg:phone":"+1 954 568 4833",
    "sg:postcode":"33304",
    "sg:province":"FL",
    "sg:tags":[
        "swimwear",
        "accessory"
    ],
    "wof:name":"Shore Elegance Inc",
    "wof:placetype":"venue"
},
  "geometry": {"coordinates":[-80.113996,26.137758],"type":"Point"}
}