{
  "type": "Feature",
  "properties": {
    "iso:country":"US",
    "sg:address":"2821 Broward Ct",
    "sg:city":"Oviedo",
    "sg:classifiers":[
        {
            "category":"Personal",
            "subcategory":"Beauty Salon",
            "type":"Services"
        }
    ],
    "sg:phone":"+1 407 365 9111",
    "sg:postcode":"32765",
    "sg:province":"FL",
    "sg:tags":[
        "shop",
        "photo",
        "studio",
        "portrait"
    ],
    "wof:name":"An Affair To Remember Inc",
    "wof:placetype":"venue"
},
  "geometry": {"coordinates":[-81.19024899999999,28.633238],"type":"Point"}
}