{
  "type": "Feature",
  "properties": {
    "iso:country":"US",
    "sg:address":"4780 Okeechobee Rd",
    "sg:city":"West Palm Beach",
    "sg:classifiers":[
        {
            "category":"Food & Beverages",
            "subcategory":"Groceries & Convenience Stores",
            "type":"Retail Goods"
        }
    ],
    "sg:phone":"+1 561 684 3480",
    "sg:postcode":"33417",
    "sg:province":"FL",
    "wof:name":"India Bazaar",
    "wof:placetype":"venue"
},
  "geometry": {"coordinates":[-80.11601,26.70686],"type":"Point"}
}