{
  "type": "Feature",
  "properties": {
    "addr:full":"215 SE 5th Ave Delray Beach FL 33483",
    "addr:housenumber":"215",
    "addr:postcode":"33483",
    "addr:street":"Se 5Th Ave",
    "iso:country":"US",
    "sg:address":"215 SE 5th Ave",
    "sg:city":"Delray Beach",
    "sg:classifiers":[
        {
            "category":"Retail",
            "subcategory":"Repair Shop",
            "type":"Services"
        }
    ],
    "sg:phone":"+1 561 243 0093",
    "sg:postcode":"33483",
    "sg:province":"FL",
    "sg:tags":[
        "equipment"
    ],
    "wof:name":"Renaissance Restoration Studio",
    "wof:placetype":"venue"
},
  "geometry": {"coordinates":[-80.06786099999999,26.456445],"type":"Point"}
}