{
  "type": "Feature",
  "properties": {
    "iso:country":"US",
    "sg:address":"10833 SW 142nd Ct",
    "sg:city":"Miami",
    "sg:classifiers":[
        {
            "category":"Building & Trades",
            "subcategory":"Construction",
            "type":"Services"
        }
    ],
    "sg:phone":"+1 305 386 0172",
    "sg:postcode":"33186",
    "sg:province":"FL",
    "sg:tags":[
        "nonresidential"
    ],
    "wof:name":"M&H Construction LLC",
    "wof:placetype":"venue"
},
  "geometry": {"coordinates":[-80.425094,25.667044],"type":"Point"}
}