{
  "type": "Feature",
  "properties": {
    "addr:full":"2301 Glades Rd Boca Raton FL 33431",
    "addr:housenumber":"2301",
    "addr:postcode":"33431",
    "addr:street":"Glades Rd",
    "iso:country":"US",
    "sg:address":"2301 Glades Rd",
    "sg:city":"Boca Raton",
    "sg:classifiers":[
        {
            "category":"Restaurant",
            "type":"Food & Drink"
        }
    ],
    "sg:menulink":"http://www.allmenus.com/fl/boca-raton/221763-chipotle/menu/",
    "sg:phone":"+1 561 443 5540",
    "sg:postcode":"33431",
    "sg:province":"FL",
    "sg:tags":[
        "mexican"
    ],
    "wof:name":"Chipotle",
    "wof:placetype":"venue"
},
  "geometry": {"coordinates":[-80.128226,26.368823],"type":"Point"}
}