{
  "type": "Feature",
  "properties": {
    "addr:full":"1730 E Cape Coral Pkwy Cape Coral FL 33904",
    "addr:housenumber":"1730",
    "addr:postcode":"33904",
    "addr:street":"E Cape Coral Pkwy",
    "iso:country":"US",
    "sg:address":"1730 E Cape Coral Pkwy",
    "sg:city":"Cape Coral",
    "sg:classifiers":[
        {
            "category":"Shopping",
            "subcategory":"Bicycles & Sporting Goods",
            "type":"Retail Goods"
        }
    ],
    "sg:phone":"+1 239 541 2532",
    "sg:postcode":"33904",
    "sg:province":"FL",
    "sg:tags":[
        "bait",
        "fishing"
    ],
    "wof:name":"Backwater Outfitters Inc",
    "wof:placetype":"venue"
},
  "geometry": {"coordinates":[-81.938073,26.562622],"type":"Point"}
}