{
  "type": "Feature",
  "properties": {
    "iso:country":"US",
    "sg:address":"401 NW 2nd Ave",
    "sg:city":"Miami",
    "sg:classifiers":[
        {
            "category":"Restaurant",
            "type":"Food & Drink"
        }
    ],
    "sg:phone":"+1 305 372 9090",
    "sg:postcode":"33128",
    "sg:province":"FL",
    "wof:name":"Delicia's Cafeteria",
    "wof:placetype":"venue"
},
  "geometry": {"coordinates":[-80.1978,25.777901],"type":"Point"}
}