{
  "type": "Feature",
  "properties": {
    "iso:country":"US",
    "sg:address":"322 Canal Rd",
    "sg:city":"Edgewater",
    "sg:classifiers":[
        {
            "category":"Organizations",
            "subcategory":"Religious Organization",
            "type":"Services"
        }
    ],
    "sg:phone":"+1 386 427 0086",
    "sg:postcode":"32132",
    "sg:province":"FL",
    "sg:tags":[
        "church"
    ],
    "wof:name":"Jump Ministries",
    "wof:placetype":"venue"
},
  "geometry": {"coordinates":[-80.91298999999999,28.996916],"type":"Point"}
}