{
  "type": "Feature",
  "properties": {
    "addr:full":"516 Marjon Ave Dunedin FL 34698",
    "addr:housenumber":"516",
    "addr:postcode":"34698",
    "addr:street":"Marjon Ave",
    "iso:country":"US",
    "sg:address":"516 Marjon Ave",
    "sg:city":"Dunedin",
    "sg:classifiers":[
        {
            "category":"Building & Trades",
            "subcategory":"Landscaping Services",
            "type":"Services"
        }
    ],
    "sg:phone":"+1 727 733 2295",
    "sg:postcode":"34698",
    "sg:province":"FL",
    "sg:tags":[
        "landscape",
        "contractor"
    ],
    "wof:name":"Chavez Brothers Landscaping Co",
    "wof:placetype":"venue"
},
  "geometry": {"coordinates":[-82.776489,28.007845],"type":"Point"}
}