{
  "type": "Feature",
  "properties": {
    "iso:country":"US",
    "sg:address":"11350 Lakeshore Dr",
    "sg:city":"Hollywood",
    "sg:classifiers":[
        {
            "category":"Professional",
            "subcategory":"Business Services",
            "type":"Services"
        }
    ],
    "sg:phone":"+1 954 432 8647",
    "sg:postcode":"33026",
    "sg:province":"FL",
    "wof:name":"JB Tallow Interiors",
    "wof:placetype":"venue"
},
  "geometry": {"coordinates":[-80.3009,26.040515],"type":"Point"}
}