{
  "type": "Feature",
  "properties": {
    "iso:country":"US",
    "sg:address":"1917 S Babcock St",
    "sg:city":"Melbourne",
    "sg:classifiers":[
        {
            "category":"Professional",
            "subcategory":"Employment Agencies",
            "type":"Services"
        }
    ],
    "sg:phone":"+1 321 837 1320",
    "sg:postcode":"32901",
    "sg:province":"FL",
    "sg:tags":[
        "opportunity"
    ],
    "wof:name":"Able Body Labor",
    "wof:placetype":"venue"
},
  "geometry": {"coordinates":[-80.62139000000001,28.079253],"type":"Point"}
}