{
  "type": "Feature",
  "properties": {
    "addr:full":"1 SE 3rd Ave Miami FL 33131",
    "addr:housenumber":"1",
    "addr:postcode":"33131",
    "addr:street":"Se 3Rd Ave",
    "iso:country":"US",
    "sg:address":"1 SE 3rd Ave",
    "sg:city":"Miami",
    "sg:classifiers":[
        {
            "category":"Professional",
            "subcategory":"Lawyer & Legal Services",
            "type":"Services"
        }
    ],
    "sg:phone":"+1 305 372 5922",
    "sg:postcode":"33131",
    "sg:province":"FL",
    "sg:tags":[
        "attorney"
    ],
    "wof:name":"Aballi Milne Kalil Garrigo",
    "wof:placetype":"venue"
},
  "geometry": {"coordinates":[-80.188964,25.773439],"type":"Point"}
}