{
  "type": "Feature",
  "properties": {
    "iso:country":"US",
    "sg:address":"15330 NW 29th Ave",
    "sg:city":"Opa Locka",
    "sg:classifiers":[
        {
            "category":"Travel",
            "subcategory":"Travel Agent",
            "type":"Entertainment"
        }
    ],
    "sg:phone":"+1 305 681 3311",
    "sg:postcode":"33054",
    "sg:province":"FL",
    "sg:tags":[
        "agency",
        "bureau"
    ],
    "wof:name":"Jesse & Marilyn Travel",
    "wof:placetype":"venue"
},
  "geometry": {"coordinates":[-80.248334,25.914675],"type":"Point"}
}