{
  "type": "Feature",
  "properties": {
    "iso:country":"US",
    "sg:address":"4185 Berkshire Dr",
    "sg:city":"Sarasota",
    "sg:classifiers":[
        {
            "category":"Real Estate",
            "subcategory":"Real Estate Agent",
            "type":"Services"
        }
    ],
    "sg:phone":"+1 941 342 0128",
    "sg:postcode":"34241",
    "sg:province":"FL",
    "sg:tags":[
        "property",
        "commercial",
        "broker",
        "for"
    ],
    "wof:name":"Quest Realty Inc",
    "wof:placetype":"venue"
},
  "geometry": {"coordinates":[-82.42401,27.296139],"type":"Point"}
}