{
  "type": "Feature",
  "properties": {
    "iso:country":"US",
    "sg:address":"6515 International Dr Holiday Inn Int'l Hotel",
    "sg:city":"Orlando",
    "sg:classifiers":[
        {
            "category":"Autos & Motor Vehicles",
            "subcategory":"Automobile Sales",
            "type":"Retail Goods"
        },
        {
            "category":"Parking",
            "subcategory":"Lot",
            "type":"Transportation"
        },
        {
            "category":"Retail",
            "subcategory":"Auto Rental",
            "type":"Services"
        }
    ],
    "sg:phone":"+1 877 492 6693",
    "sg:postcode":"32819",
    "sg:province":"FL",
    "sg:tags":[
        "truck",
        "airport",
        "leasing",
        "car",
        "van"
    ],
    "sg:website":"http://www.dollar.com/default.aspx?campID=1832",
    "wof:name":"International Palms Resort/Conference",
    "wof:placetype":"venue"
},
  "geometry": {"coordinates":[-81.46844,28.460269],"type":"Point"}
}