{
  "type": "Feature",
  "properties": {
    "iso:country":"US",
    "sg:address":"5121 Ehrlich Rd",
    "sg:city":"Tampa",
    "sg:classifiers":[
        {
            "category":"Banks & Credit Unions",
            "subcategory":"Financial Services",
            "type":"Services"
        }
    ],
    "sg:phone":"+1 813 969 1995",
    "sg:postcode":"33624",
    "sg:province":"FL",
    "sg:tags":[
        "investor"
    ],
    "wof:name":"Je Depp Investments Inc",
    "wof:placetype":"venue"
},
  "geometry": {"coordinates":[-82.534091,28.084737],"type":"Point"}
}