{
  "type": "Feature",
  "properties": {
    "iso:country":"US",
    "sg:address":"11924 Fairway Lakes Dr",
    "sg:city":"Fort Myers",
    "sg:classifiers":[
        {
            "category":"Building & Trades",
            "subcategory":"Construction",
            "type":"Services"
        }
    ],
    "sg:phone":"+1 239 561 8025",
    "sg:postcode":"33913",
    "sg:province":"FL",
    "sg:tags":[
        "general",
        "contractor"
    ],
    "wof:name":"Orion Contracting West Coast",
    "wof:placetype":"venue"
},
  "geometry": {"coordinates":[-81.75028,26.570412],"type":"Point"}
}