{
  "type": "Feature",
  "properties": {
    "addr:full":"100 Rialto Pl Melbourne FL 32901",
    "addr:housenumber":"100",
    "addr:postcode":"32901",
    "addr:street":"Rialto Pl",
    "iso:country":"US",
    "sg:address":"100 Rialto Pl",
    "sg:city":"Melbourne",
    "sg:classifiers":[
        {
            "category":"Manufacturing",
            "subcategory":"Tools & Machinery",
            "type":"Manufacturing & Wholesale Goods"
        }
    ],
    "sg:phone":"+1 321 953 9770",
    "sg:postcode":"32901",
    "sg:province":"FL",
    "sg:tags":[
        "computer",
        "electronic",
        "mfg"
    ],
    "wof:name":"Force Computers Inc",
    "wof:placetype":"venue"
},
  "geometry": {"coordinates":[-80.62196400000001,28.090012],"type":"Point"}
}