{
  "type": "Feature",
  "properties": {
    "addr:full":"961 Rosea Ct Naples FL 34104",
    "addr:housenumber":"961",
    "addr:postcode":"34104",
    "addr:street":"Rosea Ct",
    "iso:country":"US",
    "sg:address":"961 Rosea Ct",
    "sg:city":"Naples",
    "sg:classifiers":[
        {
            "category":"Wholesale",
            "subcategory":"Vending Machines",
            "type":"Manufacturing & Wholesale Goods"
        }
    ],
    "sg:phone":"+1 239 643 0708",
    "sg:postcode":"34104",
    "sg:province":"FL",
    "wof:name":"John Moleskey Vending Svc",
    "wof:placetype":"venue"
},
  "geometry": {"coordinates":[-81.75553499999999,26.14435],"type":"Point"}
}