{
  "type": "Feature",
  "properties": {
    "addr:full":"1244 Old Stickney Point Rd Sarasota FL 34242",
    "addr:housenumber":"1244",
    "addr:postcode":"34242",
    "addr:street":"Old Stickney Point Rd",
    "iso:country":"US",
    "sg:address":"1244 Old Stickney Point Rd",
    "sg:city":"Sarasota",
    "sg:classifiers":[
        {
            "category":"Shopping",
            "type":"Retail Goods"
        }
    ],
    "sg:phone":"+1 941 349 9495",
    "sg:postcode":"34242",
    "sg:province":"FL",
    "sg:tags":[
        "item",
        "boutique"
    ],
    "wof:name":"Sweet Memories Of Siesta Key Inc",
    "wof:placetype":"venue"
},
  "geometry": {"coordinates":[-82.533777,27.252219],"type":"Point"}
}