{
  "type": "Feature",
  "properties": {
    "iso:country":"US",
    "sg:address":"1539 NW 119th St",
    "sg:city":"Miami",
    "sg:classifiers":[
        {
            "category":"Autos & Motor Vehicles",
            "subcategory":"Auto Supplies",
            "type":"Retail Goods"
        }
    ],
    "sg:phone":"+1 305 685 6551",
    "sg:postcode":"33167",
    "sg:province":"FL",
    "sg:tags":[
        "automobile",
        "parts",
        "accessory",
        "part",
        "accessories-wholesale",
        "manufacturer"
    ],
    "wof:name":"Ace Auto Supply",
    "wof:placetype":"venue"
},
  "geometry": {"coordinates":[-80.223463,25.883305],"type":"Point"}
}