{
  "type": "Feature",
  "properties": {
    "addr:full":"315 Wendi Ln Ruskin FL 33570",
    "addr:housenumber":"315",
    "addr:postcode":"33570",
    "addr:street":"Wendi Ln",
    "iso:country":"US",
    "sg:address":"315 Wendi Ln",
    "sg:city":"Ruskin",
    "sg:classifiers":[
        {
            "category":"Insurance",
            "subcategory":"Insurance Agent",
            "type":"Services"
        }
    ],
    "sg:phone":"+1 813 645 4909",
    "sg:postcode":"33570",
    "sg:province":"FL",
    "wof:name":"Elrod Inc",
    "wof:placetype":"venue"
},
  "geometry": {"coordinates":[-82.436966,27.690906],"type":"Point"}
}