{
  "type": "Feature",
  "properties": {
    "iso:country":"US",
    "sg:address":"2487 Co Rd 220",
    "sg:city":"Middleburg",
    "sg:classifiers":[
        {
            "category":"Manufacturing",
            "subcategory":"Tools & Machinery",
            "type":"Manufacturing & Wholesale Goods"
        }
    ],
    "sg:phone":"+1 904 278 0099",
    "sg:postcode":"32068",
    "sg:province":"FL",
    "sg:tags":[
        "machine",
        "shop"
    ],
    "wof:name":"Mild To Wild Custom Fab",
    "wof:placetype":"venue"
},
  "geometry": {"coordinates":[-81.76854,30.100181],"type":"Point"}
}