{
  "type": "Feature",
  "properties": {
    "addr:full":"3630 SW 47th Ave Ste 100 Gainesville FL 32608",
    "addr:housenumber":"3630",
    "addr:postcode":"32608",
    "addr:street":"Sw 47Th Ave Ste 100",
    "iso:country":"US",
    "sg:address":"3630 SW 47th Ave Ste 100",
    "sg:city":"Gainesville",
    "sg:classifiers":[
        {
            "category":"Wholesale",
            "subcategory":"Medical Equipment & Supplies",
            "type":"Manufacturing & Wholesale Goods"
        },
        {
            "category":"Health Services",
            "subcategory":"Hospital",
            "type":"Services"
        }
    ],
    "sg:phone":"+1 352 327 9747",
    "sg:postcode":"32608",
    "sg:province":"FL",
    "sg:tags":[
        "instrument",
        "surgical"
    ],
    "wof:name":"Xhale Innovations, Inc.",
    "wof:placetype":"venue"
},
  "geometry": {"coordinates":[-82.376925,29.607951],"type":"Point"}
}