{
  "type": "Feature",
  "properties": {
    "addr:full":"5938 7th St Zephyrhills FL 33542",
    "addr:housenumber":"5938",
    "addr:postcode":"33542",
    "addr:street":"7Th St",
    "iso:country":"US",
    "sg:address":"5938 7th St",
    "sg:city":"Zephyrhills",
    "sg:classifiers":[
        {
            "category":"Manufacturing",
            "subcategory":"Glass & Minerals",
            "type":"Manufacturing & Wholesale Goods"
        },
        {
            "category":"Retail",
            "subcategory":"Auto Repair",
            "type":"Services"
        }
    ],
    "sg:phone":"+1 813 783 1169",
    "sg:postcode":"33542",
    "sg:province":"FL",
    "sg:tags":[
        "plate",
        "window",
        "windshield",
        "glass-auto"
    ],
    "sg:website":"http://www.kkglass.com",
    "wof:name":"K & K Glass, Inc.",
    "wof:placetype":"venue"
},
  "geometry": {"coordinates":[-82.18629300000001,28.24385],"type":"Point"}
}