{
  "type": "Feature",
  "properties": {
    "iso:country":"US",
    "sg:address":"421 Gould Rd",
    "sg:city":"Quincy",
    "sg:classifiers":[
        {
            "category":"Building & Trades",
            "subcategory":"Pest Control",
            "type":"Services"
        }
    ],
    "sg:phone":"+1 850 627 9300",
    "sg:postcode":"32351",
    "sg:province":"FL",
    "wof:name":"Charles Exterminating",
    "wof:placetype":"venue"
},
  "geometry": {"coordinates":[-84.644035,30.423323],"type":"Point"}
}