{
  "type": "Feature",
  "properties": {
    "iso:country":"US",
    "sg:address":"7649 Currency Dr",
    "sg:city":"Orlando",
    "sg:classifiers":[
        {
            "category":"Sports & Exercise",
            "subcategory":"Golf",
            "type":"Entertainment"
        }
    ],
    "sg:phone":"+1 877 933 4653",
    "sg:postcode":"32809",
    "sg:province":"FL",
    "sg:tags":[
        "instruction"
    ],
    "wof:name":"Wee Golf",
    "wof:placetype":"venue"
},
  "geometry": {"coordinates":[-81.409718,28.451912],"type":"Point"}
}