{
  "type": "Feature",
  "properties": {
    "addr:full":"705 NE 167th St Miami FL 33162",
    "addr:housenumber":"705",
    "addr:postcode":"33162",
    "addr:street":"Ne 167Th St",
    "iso:country":"US",
    "sg:address":"705 NE 167th St",
    "sg:city":"Miami",
    "sg:classifiers":[
        {
            "category":"Restaurant",
            "type":"Food & Drink"
        }
    ],
    "sg:phone":"+1 305 653 1813",
    "sg:postcode":"33162",
    "sg:province":"FL",
    "wof:name":"Jolly's Grill",
    "wof:placetype":"venue"
},
  "geometry": {"coordinates":[-80.18432,25.928826],"type":"Point"}
}