{
  "type": "Feature",
  "properties": {
    "iso:country":"US",
    "sg:address":"1600 Johnson St",
    "sg:city":"Hollywood",
    "sg:classifiers":[
        {
            "category":"Building & Trades",
            "subcategory":"Landscaping Services",
            "type":"Services"
        }
    ],
    "sg:phone":"+1 954 927 1751",
    "sg:postcode":"33020",
    "sg:province":"FL",
    "sg:tags":[
        "lawn",
        "maintenance"
    ],
    "wof:name":"Holywood Beach Country Club",
    "wof:placetype":"venue"
},
  "geometry": {"coordinates":[-80.137575,26.019006],"type":"Point"}
}