{
  "type": "Feature",
  "properties": {
    "iso:country":"US",
    "sg:address":"311 N State Road 7",
    "sg:city":"Margate",
    "sg:classifiers":[
        {
            "category":"Building & Trades",
            "subcategory":"Construction",
            "type":"Services"
        }
    ],
    "sg:phone":"+1 954 970 0888",
    "sg:postcode":"33063",
    "sg:province":"FL",
    "sg:tags":[
        "repair",
        "system",
        "contractor",
        "air conditioning"
    ],
    "sg:website":"http://www.realpagessites.com/acguy",
    "wof:name":"The AC Guy Inc",
    "wof:placetype":"venue"
},
  "geometry": {"coordinates":[-80.20479899999999,26.233295],"type":"Point"}
}