{
  "type": "Feature",
  "properties": {
    "iso:country":"US",
    "sg:address":"616 Royal Crest Way",
    "sg:city":"Brandon",
    "sg:classifiers":[
        {
            "category":"Real Estate",
            "subcategory":"Real Estate Agent",
            "type":"Services"
        }
    ],
    "sg:phone":"+1 813 689 0629",
    "sg:postcode":"33511",
    "sg:province":"FL",
    "wof:name":"Select Properties",
    "wof:placetype":"venue"
},
  "geometry": {"coordinates":[-82.291844,27.910646],"type":"Point"}
}