{
  "type": "Feature",
  "properties": {
    "addr:full":"2741 S State Road 7 West Palm Beach FL 33414",
    "addr:housenumber":"2741",
    "addr:postcode":"33414",
    "addr:street":"S State Road 7",
    "iso:country":"US",
    "sg:address":"2741 S State Road 7",
    "sg:city":"West Palm Beach",
    "sg:classifiers":[
        {
            "category":"Coffee & Tea",
            "type":"Food & Drink"
        },
        {
            "category":"Cafe",
            "type":"Food & Drink"
        }
    ],
    "sg:menulink":"http://www.allmenus.com/fl/sunshine-parkway/93819-wild-bean-cafe/menu/",
    "sg:phone":"+1 561 784 1448",
    "sg:postcode":"33414",
    "sg:province":"FL",
    "sg:tags":[
        "wrap",
        "american",
        "sandwich"
    ],
    "wof:name":"Wild Bean Cafe",
    "wof:placetype":"venue"
},
  "geometry": {"coordinates":[-80.20468099999999,26.642989],"type":"Point"}
}