{
  "type": "Feature",
  "properties": {
    "addr:full":"665 N Delmonte Ct Kissimmee FL 34758",
    "addr:housenumber":"665",
    "addr:postcode":"34758",
    "addr:street":"N Delmonte Ct",
    "iso:country":"US",
    "sg:address":"665 N Delmonte Ct",
    "sg:city":"Kissimmee",
    "sg:classifiers":[
        {
            "category":"Organizations",
            "subcategory":"Religious Organization",
            "type":"Services"
        }
    ],
    "sg:phone":"+1 407 933 1128",
    "sg:postcode":"34758",
    "sg:province":"FL",
    "wof:name":"Poinciana Alabaster Church",
    "wof:placetype":"venue"
},
  "geometry": {"coordinates":[-81.47012100000001,28.167705],"type":"Point"}
}