{
  "type": "Feature",
  "properties": {
    "iso:country":"US",
    "sg:address":"966 E Coast Dr",
    "sg:city":"Atlantic Beach",
    "sg:classifiers":[
        {
            "category":"Building & Trades",
            "subcategory":"Construction",
            "type":"Services"
        }
    ],
    "sg:phone":"+1 904 246 6039",
    "sg:postcode":"32233",
    "sg:province":"FL",
    "sg:tags":[
        "house"
    ],
    "wof:name":"Rlw Remodeling Inc",
    "wof:placetype":"venue"
},
  "geometry": {"coordinates":[-81.3985,30.334574],"type":"Point"}
}