{
  "type": "Feature",
  "properties": {
    "addr:full":"4417 Chasewood Dr Jacksonville FL 32225",
    "addr:housenumber":"4417",
    "addr:postcode":"32225",
    "addr:street":"Chasewood Dr",
    "iso:country":"US",
    "sg:address":"4417 Chasewood Dr",
    "sg:city":"Jacksonville",
    "sg:classifiers":[
        {
            "category":"Professional",
            "type":"Services"
        }
    ],
    "sg:phone":"+1 904 620 8235",
    "sg:postcode":"32225",
    "sg:province":"FL",
    "wof:name":"Mbmbholdings Inc",
    "wof:placetype":"venue"
},
  "geometry": {"coordinates":[-81.495395,30.381406],"type":"Point"}
}