{
  "type": "Feature",
  "properties": {
    "iso:country":"US",
    "sg:address":"5047 Summit Blvd",
    "sg:city":"West Palm Beach",
    "sg:classifiers":[
        {
            "category":"Social Services",
            "subcategory":"Child Care",
            "type":"Services"
        }
    ],
    "sg:phone":"+1 561 471 9400",
    "sg:postcode":"33415",
    "sg:province":"FL",
    "sg:tags":[
        "day"
    ],
    "wof:name":"A Little Dude Ranch Academy",
    "wof:placetype":"venue"
},
  "geometry": {"coordinates":[-80.12245900000001,26.662967],"type":"Point"}
}