{
  "type": "Feature",
  "properties": {
    "addr:full":"5660 Micco Rd Sebastian FL 32976",
    "addr:housenumber":"5660",
    "addr:postcode":"32976",
    "addr:street":"Micco Rd",
    "iso:country":"US",
    "sg:address":"5660 Micco Rd",
    "sg:city":"Sebastian",
    "sg:classifiers":[
        {
            "category":"Building & Trades",
            "subcategory":"Construction",
            "type":"Services"
        }
    ],
    "sg:phone":"+1 772 664 0411",
    "sg:postcode":"32976",
    "sg:province":"FL",
    "sg:tags":[
        "roofing",
        "contractor"
    ],
    "wof:name":"Specialty Coating & Roofing",
    "wof:placetype":"venue"
},
  "geometry": {"coordinates":[-80.501525,27.880403],"type":"Point"}
}