{
  "type": "Feature",
  "properties": {
    "iso:country":"US",
    "sg:address":"15588 Aviation Loop Dr",
    "sg:city":"Brooksville",
    "sg:classifiers":[
        {
            "category":"Professional",
            "subcategory":"Business Services",
            "type":"Services"
        }
    ],
    "sg:phone":"+1 352 797 9551",
    "sg:postcode":"34604",
    "sg:province":"FL",
    "sg:tags":[
        "consultant",
        "technology"
    ],
    "wof:name":"Equalizer Networking & Design",
    "wof:placetype":"venue"
},
  "geometry": {"coordinates":[-82.47569300000001,28.478856],"type":"Point"}
}