{
  "type": "Feature",
  "properties": {
    "addr:full":"400 State Hwy 436 Casselberry FL 32707",
    "addr:housenumber":"400",
    "addr:postcode":"32707",
    "addr:street":"State Hwy 436",
    "iso:country":"US",
    "sg:address":"400 State Hwy 436",
    "sg:city":"Casselberry",
    "sg:classifiers":[
        {
            "category":"Shopping",
            "type":"Retail Goods"
        }
    ],
    "sg:phone":"+1 407 331 1422",
    "sg:postcode":"32707",
    "sg:province":"FL",
    "sg:tags":[
        "all",
        "built",
        "make",
        "hearing",
        "aids",
        "custom"
    ],
    "wof:name":"Orlando Hearing Aid Center",
    "wof:placetype":"venue"
},
  "geometry": {"coordinates":[-81.33263599999999,28.65502],"type":"Point"}
}