{
  "type": "Feature",
  "properties": {
    "addr:full":"18577 SE Federal Hwy Tequesta FL 33469",
    "addr:postcode":"18577;33469",
    "addr:street":"Se Federal Hwy",
    "iso:country":"US",
    "sg:address":"18577 SE Federal Hwy",
    "sg:city":"Tequesta",
    "sg:classifiers":[
        {
            "category":"Manufacturing",
            "subcategory":"Watercraft",
            "type":"Manufacturing & Wholesale Goods"
        }
    ],
    "sg:phone":"+1 561 744 3583",
    "sg:postcode":"33469",
    "sg:province":"FL",
    "sg:tags":[
        "boat"
    ],
    "wof:name":"Dry Diver",
    "wof:placetype":"venue"
},
  "geometry": {"coordinates":[-80.090963,26.981532],"type":"Point"}
}