{
  "type": "Feature",
  "properties": {
    "iso:country":"US",
    "sg:address":"1105 Bailey Dr",
    "sg:city":"Niceville",
    "sg:classifiers":[
        {
            "category":"Building & Trades",
            "subcategory":"Construction",
            "type":"Services"
        }
    ],
    "sg:phone":"+1 850 543 3951",
    "sg:postcode":"32578",
    "sg:province":"FL",
    "sg:tags":[
        "wallcoverings-installation",
        "wallpaper",
        "painting",
        "contractor"
    ],
    "wof:name":"Rolando Retana Painting Inc",
    "wof:placetype":"venue"
},
  "geometry": {"coordinates":[-86.465508,30.512407],"type":"Point"}
}