{
  "type": "Feature",
  "properties": {
    "addr:full":"516 Henkel Cir Winter Park FL 32789",
    "addr:housenumber":"516",
    "addr:postcode":"32789",
    "addr:street":"Henkel Cir",
    "iso:country":"US",
    "sg:address":"516 Henkel Cir",
    "sg:city":"Winter Park",
    "sg:classifiers":[
        {
            "category":"Professional",
            "subcategory":"Business Services",
            "type":"Services"
        }
    ],
    "sg:phone":"+1 407 645 0084",
    "sg:postcode":"32789",
    "sg:province":"FL",
    "wof:name":"Terrys Accessories & Design",
    "wof:placetype":"venue"
},
  "geometry": {"coordinates":[-81.340334,28.595406],"type":"Point"}
}