{
  "type": "Feature",
  "properties": {
    "addr:full":"12462 W Atlantic Blvd Coral Springs FL 33071",
    "addr:housenumber":"12462",
    "addr:postcode":"33071",
    "addr:street":"W Atlantic Blvd",
    "iso:country":"US",
    "sg:address":"12462 W Atlantic Blvd",
    "sg:city":"Coral Springs",
    "sg:classifiers":[
        {
            "category":"Health Services",
            "subcategory":"Doctor",
            "type":"Services"
        }
    ],
    "sg:phone":"+1 954 345 3835",
    "sg:postcode":"33071",
    "sg:province":"FL",
    "sg:tags":[
        "physician",
        "surgeon"
    ],
    "wof:name":"Azurin Cosmetic Surgery",
    "wof:placetype":"venue"
},
  "geometry": {"coordinates":[-80.29346700000001,26.233205],"type":"Point"}
}