{
  "type": "Feature",
  "properties": {
    "iso:country":"US",
    "sg:address":"1963 NW 22nd St",
    "sg:city":"Miami",
    "sg:classifiers":[
        {
            "category":"Food & Beverages",
            "subcategory":"Groceries & Convenience Stores",
            "type":"Retail Goods"
        }
    ],
    "sg:phone":"+1 305 324 1338",
    "sg:postcode":"33142",
    "sg:province":"FL",
    "wof:name":"San Miguel Market",
    "wof:placetype":"venue"
},
  "geometry": {"coordinates":[-80.228075,25.797579],"type":"Point"}
}