{
  "type": "Feature",
  "properties": {
    "addr:full":"8010 Sunport Dr Orlando FL 32809",
    "addr:postcode":"8010;32809",
    "addr:street":"Sunport Dr",
    "iso:country":"US",
    "sg:address":"8010 Sunport Dr",
    "sg:city":"Orlando",
    "sg:classifiers":[
        {
            "category":"Building & Trades",
            "subcategory":"Equipment Rental",
            "type":"Services"
        }
    ],
    "sg:phone":"+1 407 438 2995",
    "sg:postcode":"32809",
    "sg:province":"FL",
    "sg:tags":[
        "supply",
        "contractor"
    ],
    "sg:website":"http://www.amestools.com",
    "wof:name":"Ames Taping Tools",
    "wof:placetype":"venue"
},
  "geometry": {"coordinates":[-81.37320200000001,28.450105],"type":"Point"}
}