{
  "type": "Feature",
  "properties": {
    "iso:country":"US",
    "sg:address":"441 Widgeon Pt",
    "sg:city":"Naples",
    "sg:classifiers":[
        {
            "category":"Professional",
            "subcategory":"Accounting & Tax Preparation",
            "type":"Services"
        }
    ],
    "sg:phone":"+1 239 261 5160",
    "sg:postcode":"34105",
    "sg:province":"FL",
    "sg:tags":[
        "return",
        "filing"
    ],
    "wof:name":"T D Piercy Income Tax Svc",
    "wof:placetype":"venue"
},
  "geometry": {"coordinates":[-81.770927,26.201431],"type":"Point"}
}