{
  "type": "Feature",
  "properties": {
    "addr:full":"5433 W State Rd 46 Sanford FL 32771",
    "addr:housenumber":"5433;46",
    "addr:postcode":"32771",
    "addr:street":"W State Rd",
    "iso:country":"US",
    "sg:address":"5433 W State Rd 46",
    "sg:city":"Sanford",
    "sg:classifiers":[
        {
            "category":"Social Services",
            "subcategory":"Adult Care",
            "type":"Services"
        }
    ],
    "sg:phone":"+1 407 322 2207",
    "sg:postcode":"32771",
    "sg:province":"FL",
    "sg:tags":[
        "residential",
        "senior"
    ],
    "sg:website":"www.heritageatlakeforest.com",
    "wof:name":"Heritage At Lake Forest",
    "wof:placetype":"venue"
},
  "geometry": {"coordinates":[-81.357579,28.811161],"type":"Point"}
}