{
  "type": "Feature",
  "properties": {
    "addr:full":"3078 NW 51st Ter Miami FL 33142",
    "addr:housenumber":"3078",
    "addr:postcode":"33142",
    "addr:street":"Nw 51St Ter",
    "iso:country":"US",
    "sg:address":"3078 NW 51st Ter",
    "sg:city":"Miami",
    "sg:classifiers":[
        {
            "category":"Professional",
            "subcategory":"Business Services",
            "type":"Services"
        }
    ],
    "sg:phone":"+1 305 634 1724",
    "sg:postcode":"33142",
    "sg:province":"FL",
    "wof:name":"White Marina & Associates",
    "wof:placetype":"venue"
},
  "geometry": {"coordinates":[-80.24533099999999,25.821237],"type":"Point"}
}