{
  "type": "Feature",
  "properties": {
    "addr:full":"3614 3rd St W Bradenton FL 34205",
    "addr:housenumber":"3614",
    "addr:postcode":"34205",
    "addr:street":"3Rd St W",
    "iso:country":"US",
    "sg:address":"3614 3rd St W",
    "sg:city":"Bradenton",
    "sg:classifiers":[
        {
            "category":"Insurance",
            "subcategory":"Insurance Agent",
            "type":"Services"
        }
    ],
    "sg:phone":"+1 941 741 2600",
    "sg:postcode":"34205",
    "sg:province":"FL",
    "sg:tags":[
        "claim"
    ],
    "wof:name":"State Farm Insurance",
    "wof:placetype":"venue"
},
  "geometry": {"coordinates":[-82.565127,27.467203],"type":"Point"}
}