{
  "type": "Feature",
  "properties": {
    "iso:country":"US",
    "sg:address":"2331 Whitfield Industrial Way",
    "sg:city":"Sarasota",
    "sg:classifiers":[
        {
            "category":"Shopping",
            "subcategory":"Discount & Variety Stores",
            "type":"Retail Goods"
        }
    ],
    "sg:phone":"+1 941 752 3862",
    "sg:postcode":"34243",
    "sg:province":"FL",
    "wof:name":"Brown Dollar Wise",
    "wof:placetype":"venue"
},
  "geometry": {"coordinates":[-82.536108,27.422885],"type":"Point"}
}