{
  "type": "Feature",
  "properties": {
    "iso:country":"US",
    "sg:address":"711 Fleming Ave",
    "sg:city":"Ormond Beach",
    "sg:classifiers":[
        {
            "category":"Building & Trades",
            "subcategory":"Construction",
            "type":"Services"
        }
    ],
    "sg:phone":"+1 386 527 2529",
    "sg:postcode":"32174",
    "sg:province":"FL",
    "sg:tags":[
        "house"
    ],
    "wof:name":"Custom Home Improvements",
    "wof:placetype":"venue"
},
  "geometry": {"coordinates":[-81.06710200000001,29.263346],"type":"Point"}
}