{
  "type": "Feature",
  "properties": {
    "iso:country":"US",
    "sg:address":"1881 Pleasant Hill Rd",
    "sg:city":"Kissimmee",
    "sg:classifiers":[
        {
            "category":"Professional",
            "subcategory":"Management & Consulting",
            "type":"Services"
        }
    ],
    "sg:phone":"+1 407 935 9077",
    "sg:postcode":"34746",
    "sg:province":"FL",
    "sg:tags":[
        "building",
        "construction"
    ],
    "wof:name":"New-Son Cnstr MGT Co LLC",
    "wof:placetype":"venue"
},
  "geometry": {"coordinates":[-81.436204,28.26017],"type":"Point"}
}