{
  "type": "Feature",
  "properties": {
    "iso:country":"US",
    "sg:address":"2828 Jackson St",
    "sg:city":"Fort Myers",
    "sg:classifiers":[
        {
            "category":"Organizations",
            "subcategory":"Professional Association",
            "type":"Services"
        }
    ],
    "sg:phone":"+1 239 334 2050",
    "sg:postcode":"33901",
    "sg:province":"FL",
    "wof:name":"Villa Capri Assn",
    "wof:placetype":"venue"
},
  "geometry": {"coordinates":[-81.86624399999999,26.625096],"type":"Point"}
}