{
  "type": "Feature",
  "properties": {
    "addr:full":"100 Evernia St Jupiter FL 33458",
    "addr:housenumber":"100",
    "addr:postcode":"33458",
    "addr:street":"Evernia St",
    "iso:country":"US",
    "sg:address":"100 Evernia St",
    "sg:city":"Jupiter",
    "sg:classifiers":[
        {
            "category":"Communications",
            "subcategory":"Radio Station",
            "type":"Services"
        }
    ],
    "sg:phone":"+1 561 805 7420",
    "sg:postcode":"33458",
    "sg:province":"FL",
    "sg:tags":[
        "company",
        "broadcasting"
    ],
    "wof:name":"Clear Channel Radio",
    "wof:placetype":"venue"
},
  "geometry": {"coordinates":[-80.095866,26.936819],"type":"Point"}
}