{
  "type": "Feature",
  "properties": {
    "iso:country":"US",
    "sg:address":"3540 Saint Johns Ave",
    "sg:city":"Jacksonville",
    "sg:classifiers":[
        {
            "category":"Retail",
            "subcategory":"Laundry & Dry Cleaning",
            "type":"Services"
        }
    ],
    "sg:phone":"+1 904 389 6210",
    "sg:postcode":"32205",
    "sg:province":"FL",
    "sg:tags":[
        "cleaners"
    ],
    "wof:name":"Deluxe Laundry & Dry Cleaners",
    "wof:placetype":"venue"
},
  "geometry": {"coordinates":[-81.699122,30.300465],"type":"Point"}
}