{
  "type": "Feature",
  "properties": {
    "iso:country":"US",
    "sg:address":"2777 Bee Ridge Rd",
    "sg:city":"Sarasota",
    "sg:classifiers":[
        {
            "category":"Personal",
            "subcategory":"Beauty Salon",
            "type":"Services"
        }
    ],
    "sg:phone":"+1 941 922 4305",
    "sg:postcode":"34239",
    "sg:province":"FL",
    "wof:name":"Love Your Hair",
    "wof:placetype":"venue"
},
  "geometry": {"coordinates":[-82.515512,27.29891],"type":"Point"}
}