{
  "type": "Feature",
  "properties": {
    "addr:full":"11321 Satellite Blvd B Orlando FL 32837",
    "addr:housenumber":"11321",
    "addr:postcode":"32837",
    "addr:street":"Satellite Blvd B",
    "iso:country":"US",
    "sg:address":"11321 Satellite Blvd B",
    "sg:city":"Orlando",
    "sg:classifiers":[
        {
            "category":"Professional",
            "subcategory":"Advertising",
            "type":"Services"
        }
    ],
    "sg:phone":"+1 407 438 2525",
    "sg:postcode":"32837",
    "sg:province":"FL",
    "sg:tags":[
        "distributing",
        "sample",
        "service-circular"
    ],
    "wof:name":"Lns Transport Service",
    "wof:placetype":"venue"
},
  "geometry": {"coordinates":[-81.401518,28.40243],"type":"Point"}
}