{
  "type": "Feature",
  "properties": {
    "addr:full":"7310 Broad St Brooksville FL 34601",
    "addr:housenumber":"7310",
    "addr:postcode":"34601",
    "addr:street":"Broad St",
    "iso:country":"US",
    "sg:address":"7310 Broad St",
    "sg:city":"Brooksville",
    "sg:classifiers":[
        {
            "category":"Home & Garden",
            "subcategory":"Home Furnishings",
            "type":"Retail Goods"
        }
    ],
    "sg:phone":"+1 352 797 0107",
    "sg:postcode":"34601",
    "sg:province":"FL",
    "sg:tags":[
        "curtain",
        "made",
        "drapery"
    ],
    "wof:name":"Custom Discount Blind Inc",
    "wof:placetype":"venue"
},
  "geometry": {"coordinates":[-82.405548,28.53706],"type":"Point"}
}