{
  "type": "Feature",
  "properties": {
    "iso:country":"US",
    "sg:address":"5430 NW 90th Ave",
    "sg:city":"Ocala",
    "sg:classifiers":[
        {
            "category":"Retail",
            "subcategory":"Animal Services",
            "type":"Services"
        }
    ],
    "sg:phone":"+1 352 351 0886",
    "sg:postcode":"34482",
    "sg:province":"FL",
    "wof:name":"Macmt Thoughobred Farm",
    "wof:placetype":"venue"
},
  "geometry": {"coordinates":[-82.267805,29.245372],"type":"Point"}
}