{
  "type": "Feature",
  "properties": {
    "addr:full":"2411 NW 1st Ave Boca Raton FL 33431",
    "addr:housenumber":"2411",
    "addr:postcode":"33431",
    "addr:street":"Nw 1St Ave",
    "iso:country":"US",
    "sg:address":"2411 NW 1st Ave",
    "sg:city":"Boca Raton",
    "sg:classifiers":[
        {
            "category":"Freight",
            "type":"Transportation"
        }
    ],
    "sg:phone":"+1 561 395 4525",
    "sg:postcode":"33431",
    "sg:province":"FL",
    "sg:tags":[
        "commercial",
        "storage",
        "general"
    ],
    "wof:name":"First Avenue Storage",
    "wof:placetype":"venue"
},
  "geometry": {"coordinates":[-80.084907,26.376006],"type":"Point"}
}