{
  "type": "Feature",
  "properties": {
    "iso:country":"US",
    "sg:address":"259 Summa St",
    "sg:city":"West Palm Beach",
    "sg:classifiers":[
        {
            "category":"Wholesale",
            "subcategory":"Electrical",
            "type":"Manufacturing & Wholesale Goods"
        }
    ],
    "sg:phone":"+1 561 582 5098",
    "sg:postcode":"33405",
    "sg:province":"FL",
    "sg:tags":[
        "electronic"
    ],
    "wof:name":"Freakinmusic Inc",
    "wof:placetype":"venue"
},
  "geometry": {"coordinates":[-80.05072,26.650099],"type":"Point"}
}