{
  "type": "Feature",
  "properties": {
    "iso:country":"US",
    "sg:address":"2624 Hubbard St",
    "sg:city":"Jacksonville",
    "sg:classifiers":[
        {
            "category":"Building & Trades",
            "subcategory":"Construction",
            "type":"Services"
        }
    ],
    "sg:phone":"+1 904 356 7293",
    "sg:postcode":"32206",
    "sg:province":"FL",
    "sg:tags":[
        "heavy",
        "dock",
        "contractor"
    ],
    "wof:name":"Diversified Marine Services",
    "wof:placetype":"venue"
},
  "geometry": {"coordinates":[-81.65231,30.354055],"type":"Point"}
}