{
  "type": "Feature",
  "properties": {
    "iso:country":"US",
    "sg:address":"3648 Beneva Oaks Blvd",
    "sg:city":"Sarasota",
    "sg:classifiers":[
        {
            "category":"Wholesale",
            "subcategory":"Computers",
            "type":"Manufacturing & Wholesale Goods"
        },
        {
            "category":"Professional",
            "subcategory":"Computer Services",
            "type":"Services"
        },
        {
            "category":"Internet Cafe",
            "subcategory":"None",
            "type":"Food & Drink"
        }
    ],
    "sg:phone":"+1 941 927 6064",
    "sg:postcode":"34238",
    "sg:province":"FL",
    "sg:tags":[
        "equipment",
        "product",
        "software"
    ],
    "sg:website":"http://www.coolstufflabs.com",
    "wof:name":"Cool Stuff Labs Inc",
    "wof:placetype":"venue"
},
  "geometry": {"coordinates":[-82.493982,27.26093],"type":"Point"}
}