{
  "type": "Feature",
  "properties": {
    "iso:country":"US",
    "sg:address":"1375 W Landstreet Rd",
    "sg:city":"Orlando",
    "sg:classifiers":[
        {
            "category":"Autos & Motor Vehicles",
            "subcategory":"Automobile Sales",
            "type":"Retail Goods"
        }
    ],
    "sg:phone":"+1 407 850 2939",
    "sg:postcode":"32809",
    "sg:province":"FL",
    "sg:tags":[
        "car",
        "dealer"
    ],
    "wof:name":"Vicar Auto Sales Corp",
    "wof:placetype":"venue"
},
  "geometry": {"coordinates":[-81.39688599999999,28.436113],"type":"Point"}
}