{
  "type": "Feature",
  "properties": {
    "iso:country":"US",
    "sg:address":"418 S Grove St",
    "sg:city":"Eustis",
    "sg:classifiers":[
        {
            "category":"Professional",
            "subcategory":"Business Services",
            "type":"Services"
        }
    ],
    "sg:phone":"+1 352 357 3331",
    "sg:postcode":"32726",
    "sg:province":"FL",
    "wof:name":"Lan Technology",
    "wof:placetype":"venue"
},
  "geometry": {"coordinates":[-81.68362399999999,28.848485],"type":"Point"}
}