{
  "type": "Feature",
  "properties": {
    "iso:country":"US",
    "sg:address":"4887 Golden Gate Pkwy",
    "sg:city":"Naples",
    "sg:classifiers":[
        {
            "category":"Banks & Credit Unions",
            "subcategory":"Bank",
            "type":"Services"
        }
    ],
    "sg:phone":"+1 239 352 4504",
    "sg:postcode":"34116",
    "sg:province":"FL",
    "sg:tags":[
        "cashing",
        "check"
    ],
    "wof:name":"Advance America",
    "wof:placetype":"venue"
},
  "geometry": {"coordinates":[-81.70581300000001,26.180946],"type":"Point"}
}