{
  "type": "Feature",
  "properties": {
    "iso:country":"US",
    "sg:address":"3305 E Hillsborough Ave",
    "sg:city":"Tampa",
    "sg:classifiers":[
        {
            "category":"Autos & Motor Vehicles",
            "subcategory":"Automobile Sales",
            "type":"Retail Goods"
        }
    ],
    "sg:phone":"+1 813 232 8251",
    "sg:postcode":"33610",
    "sg:province":"FL",
    "sg:tags":[
        "dealers-used",
        "car",
        "used",
        "cars-wholesale"
    ],
    "wof:name":"Auto Exchange Inc",
    "wof:placetype":"venue"
},
  "geometry": {"coordinates":[-82.423269,27.996099],"type":"Point"}
}