{
  "type": "Feature",
  "properties": {
    "addr:full":"2820 Spring Glen Rd Jacksonville FL 32207",
    "addr:housenumber":"2820",
    "addr:postcode":"32207",
    "addr:street":"Spring Glen Rd",
    "iso:country":"US",
    "sg:address":"2820 Spring Glen Rd",
    "sg:city":"Jacksonville",
    "sg:classifiers":[
        {
            "category":"Building & Trades",
            "subcategory":"Pest Control",
            "type":"Services"
        }
    ],
    "sg:phone":"+1 904 396 5805",
    "sg:postcode":"32207",
    "sg:province":"FL",
    "wof:name":"Florida Pest Control & Chem Co",
    "wof:placetype":"venue"
},
  "geometry": {"coordinates":[-81.60957399999999,30.296769],"type":"Point"}
}