{
  "type": "Feature",
  "properties": {
    "iso:country":"US",
    "sg:address":"3083 SE Dixie Hwy",
    "sg:city":"Stuart",
    "sg:classifiers":[
        {
            "category":"Autos & Motor Vehicles",
            "subcategory":"Boat Sales",
            "type":"Retail Goods"
        },
        {
            "category":"Home & Garden",
            "subcategory":"Building Materials",
            "type":"Retail Goods"
        }
    ],
    "sg:phone":"+1 772 287 7064",
    "sg:postcode":"34997",
    "sg:province":"FL",
    "sg:tags":[
        "upholstery",
        "supply",
        "top",
        "covers",
        "equipment",
        "awning",
        "canopy"
    ],
    "wof:name":"Canvas Specialties",
    "wof:placetype":"venue"
},
  "geometry": {"coordinates":[-80.220977,27.167258],"type":"Point"}
}