{
  "type": "Feature",
  "properties": {
    "addr:full":"1645 NW 79th St Miami FL 33147",
    "addr:housenumber":"1645",
    "addr:postcode":"33147",
    "addr:street":"Nw 79Th St",
    "iso:country":"US",
    "sg:address":"1645 NW 79th St",
    "sg:city":"Miami",
    "sg:classifiers":[
        {
            "category":"Shopping",
            "subcategory":"Pharmacy",
            "type":"Retail Goods"
        }
    ],
    "sg:phone":"+1 305 594 4074",
    "sg:postcode":"33147",
    "sg:province":"FL",
    "sg:tags":[
        "drugstore"
    ],
    "wof:name":"Mallinckrodt Dis",
    "wof:placetype":"venue"
},
  "geometry": {"coordinates":[-80.258985,25.845585],"type":"Point"}
}