{
  "type": "Feature",
  "properties": {
    "iso:country":"US",
    "sg:address":"2982 US Hwy 41",
    "sg:city":"Lake City",
    "sg:classifiers":[
        {
            "category":"Organizations",
            "subcategory":"Religious Organization",
            "type":"Services"
        }
    ],
    "sg:phone":"+1 386 758 9257",
    "sg:postcode":"32025",
    "sg:province":"FL",
    "wof:name":"Union AME Church",
    "wof:placetype":"venue"
},
  "geometry": {"coordinates":[-82.64123600000001,30.168168],"type":"Point"}
}