{
  "type": "Feature",
  "properties": {
    "addr:full":"9120 SE 197th Ave Ocklawaha FL 32179",
    "addr:housenumber":"9120",
    "addr:postcode":"32179",
    "addr:street":"Se 197Th Ave",
    "iso:country":"US",
    "sg:address":"9120 SE 197th Ave",
    "sg:city":"Ocklawaha",
    "sg:classifiers":[
        {
            "category":"Building & Trades",
            "subcategory":"Construction",
            "type":"Services"
        }
    ],
    "sg:phone":"+1 352 454 1875",
    "sg:postcode":"32179",
    "sg:province":"FL",
    "sg:tags":[
        "painter"
    ],
    "wof:name":"William Caul Painting",
    "wof:placetype":"venue"
},
  "geometry": {"coordinates":[-81.82617,29.089691],"type":"Point"}
}