{
  "type": "Feature",
  "properties": {
    "addr:full":"12310 SW 127th Ave Miami FL 33186",
    "addr:housenumber":"12310",
    "addr:postcode":"33186",
    "addr:street":"Sw 127Th Ave",
    "iso:country":"US",
    "sg:address":"12310 SW 127th Ave",
    "sg:city":"Miami",
    "sg:classifiers":[
        {
            "category":"Restaurant",
            "type":"Food & Drink"
        }
    ],
    "sg:phone":"+1 305 234 1626",
    "sg:postcode":"33186",
    "sg:province":"FL",
    "sg:tags":[
        "pizza"
    ],
    "wof:name":"Tango's Pizza",
    "wof:placetype":"venue"
},
  "geometry": {"coordinates":[-80.399255,25.653289],"type":"Point"}
}