{
  "type": "Feature",
  "properties": {
    "addr:full":"6499 Powerline Rd Fort Lauderdale FL 33309",
    "addr:housenumber":"6499",
    "addr:postcode":"33309",
    "addr:street":"Powerline Rd",
    "iso:country":"US",
    "sg:address":"6499 Powerline Rd",
    "sg:city":"Fort Lauderdale",
    "sg:classifiers":[
        {
            "category":"Banks & Credit Unions",
            "subcategory":"Bank",
            "type":"Services"
        }
    ],
    "sg:phone":"+1 954 202 9278",
    "sg:postcode":"33309",
    "sg:province":"FL",
    "wof:name":"Union Bank",
    "wof:placetype":"venue"
},
  "geometry": {"coordinates":[-80.15584,26.207095],"type":"Point"}
}