{
  "type": "Feature",
  "properties": {
    "addr:full":"14320 Stringfellow Rd Bokeelia FL 33922",
    "addr:housenumber":"14320",
    "addr:postcode":"33922",
    "addr:street":"Stringfellow Rd",
    "iso:country":"US",
    "sg:address":"14320 Stringfellow Rd",
    "sg:city":"Bokeelia",
    "sg:classifiers":[
        {
            "category":"Professional",
            "type":"Services"
        }
    ],
    "sg:phone":"+1 239 283 9121",
    "sg:postcode":"33922",
    "sg:province":"FL",
    "sg:tags":[
        "establishment"
    ],
    "wof:name":"Treeland Solutions Inc",
    "wof:placetype":"venue"
},
  "geometry": {"coordinates":[-82.145483,26.668577],"type":"Point"}
}