{
  "type": "Feature",
  "properties": {
    "iso:country":"US",
    "sg:address":"1635 Oviedo Marketplace Blvd",
    "sg:city":"Oviedo",
    "sg:classifiers":[
        {
            "category":"Shopping",
            "subcategory":"Jewelry",
            "type":"Retail Goods"
        }
    ],
    "sg:phone":"+1 407 977 2878",
    "sg:postcode":"32765",
    "sg:province":"FL",
    "sg:tags":[
        "store",
        "jeweler"
    ],
    "sg:website":"www.zales.com",
    "wof:name":"Zales Jewelers",
    "wof:placetype":"venue"
},
  "geometry": {"coordinates":[-81.235513,28.659904],"type":"Point"}
}