{
  "type": "Feature",
  "properties": {
    "iso:country":"US",
    "sg:address":"3760 43rd Ave NE",
    "sg:city":"Naples",
    "sg:classifiers":[
        {
            "category":"Building & Trades",
            "subcategory":"Construction",
            "type":"Services"
        }
    ],
    "sg:phone":"+1 239 455 8350",
    "sg:postcode":"34120",
    "sg:province":"FL",
    "sg:tags":[
        "residential"
    ],
    "wof:name":"David Peter Butrymowicz",
    "wof:placetype":"venue"
},
  "geometry": {"coordinates":[-81.54244199999999,26.310652],"type":"Point"}
}