{
  "type": "Feature",
  "properties": {
    "addr:full":"2719 NW 6th St Fort Lauderdale FL 33311",
    "addr:housenumber":"2719",
    "addr:postcode":"33311",
    "addr:street":"Nw 6Th St",
    "iso:country":"US",
    "sg:address":"2719 NW 6th St",
    "sg:city":"Fort Lauderdale",
    "sg:classifiers":[
        {
            "category":"Professional",
            "subcategory":"Accounting & Tax Preparation",
            "type":"Services"
        }
    ],
    "sg:phone":"+1 954 584 7662",
    "sg:postcode":"33311",
    "sg:province":"FL",
    "sg:tags":[
        "return",
        "filing"
    ],
    "wof:name":"Tunnage Tax Svc",
    "wof:placetype":"venue"
},
  "geometry": {"coordinates":[-80.179964,26.128898],"type":"Point"}
}