{
  "type": "Feature",
  "properties": {
    "addr:full":"7100 SW 99th Ave Miami FL 33173",
    "addr:housenumber":"7100",
    "addr:postcode":"33173",
    "addr:street":"Sw 99Th Ave",
    "iso:country":"US",
    "sg:address":"7100 SW 99th Ave",
    "sg:city":"Miami",
    "sg:classifiers":[
        {
            "category":"Health Services",
            "subcategory":"Clinic",
            "type":"Services"
        },
        {
            "category":"Health Services",
            "subcategory":"Health Practitioner",
            "type":"Services"
        }
    ],
    "sg:phone":"+1 305 270 8105",
    "sg:postcode":"33173",
    "sg:province":"FL",
    "sg:tags":[
        "information",
        "addiction-information",
        "treatment",
        "alcoholism",
        "gambling"
    ],
    "wof:name":"The Children's Experience",
    "wof:placetype":"venue"
},
  "geometry": {"coordinates":[-80.354198,25.702411],"type":"Point"}
}