{
  "type": "Feature",
  "properties": {
    "iso:country":"US",
    "sg:address":"1510 Delgado Ave",
    "sg:city":"Miami",
    "sg:classifiers":[
        {
            "category":"Shopping",
            "subcategory":"Shoes",
            "type":"Retail Goods"
        }
    ],
    "sg:phone":"+1 305 667 5530",
    "sg:postcode":"33146",
    "sg:province":"FL",
    "wof:name":"Athletes In Action",
    "wof:placetype":"venue"
},
  "geometry": {"coordinates":[-80.285562,25.715957],"type":"Point"}
}