{
  "type": "Feature",
  "properties": {
    "iso:country":"US",
    "sg:address":"2426 Bloxham Cutoff Rd",
    "sg:city":"Crawfordville",
    "sg:classifiers":[
        {
            "category":"Social Services",
            "type":"Services"
        }
    ],
    "sg:phone":"+1 850 926 5651",
    "sg:postcode":"32327",
    "sg:province":"FL",
    "sg:tags":[
        "organization",
        "welfare"
    ],
    "wof:name":"YMCA Camp Indian",
    "wof:placetype":"venue"
},
  "geometry": {"coordinates":[-84.3207,30.251279],"type":"Point"}
}