{
  "type": "Feature",
  "properties": {
    "addr:full":"320 N 1st St Immokalee FL 34142",
    "addr:housenumber":"320",
    "addr:postcode":"34142",
    "addr:street":"N 1St St",
    "iso:country":"US",
    "sg:address":"320 N 1st St",
    "sg:city":"Immokalee",
    "sg:classifiers":[
        {
            "category":"Retail",
            "subcategory":"Laundry & Dry Cleaning",
            "type":"Services"
        }
    ],
    "sg:phone":"+1 239 657 2216",
    "sg:postcode":"34142",
    "sg:province":"FL",
    "sg:tags":[
        "cleaners"
    ],
    "wof:name":"Immokalee Dry Cleaners",
    "wof:placetype":"venue"
},
  "geometry": {"coordinates":[-81.41743700000001,26.423366],"type":"Point"}
}