{
  "type": "Feature",
  "properties": {
    "addr:full":"6123 Kestrelridge Dr Lithia FL 33547",
    "addr:housenumber":"6123",
    "addr:postcode":"33547",
    "addr:street":"Kestrelridge Dr",
    "iso:country":"US",
    "sg:address":"6123 Kestrelridge Dr",
    "sg:city":"Lithia",
    "sg:classifiers":[
        {
            "category":"Communications",
            "subcategory":"Television Station",
            "type":"Services"
        }
    ],
    "sg:phone":"+1 813 643 7298",
    "sg:postcode":"33547",
    "sg:province":"FL",
    "sg:tags":[
        "satellite",
        "antenna",
        "cable",
        "tv",
        "system",
        "equipment"
    ],
    "wof:name":"Morning Star Satellite",
    "wof:placetype":"venue"
},
  "geometry": {"coordinates":[-82.236756,27.836623],"type":"Point"}
}