{
  "type": "Feature",
  "properties": {
    "iso:country":"US",
    "sg:address":"1900 Liberty Ave",
    "sg:city":"Miami Beach",
    "sg:classifiers":[
        {
            "category":"Arts & Performance",
            "subcategory":"Theater",
            "type":"Entertainment"
        }
    ],
    "sg:phone":"+1 305 532 4035",
    "sg:postcode":"33139",
    "sg:province":"FL",
    "sg:tags":[
        "theatrical"
    ],
    "wof:name":"Nightflyer Promotions",
    "wof:placetype":"venue"
},
  "geometry": {"coordinates":[-80.13014099999999,25.795952],"type":"Point"}
}