{
  "type": "Feature",
  "properties": {
    "iso:country":"US",
    "sg:address":"100 Carillon Pkwy",
    "sg:city":"Saint Petersburg",
    "sg:classifiers":[
        {
            "category":"Professional",
            "subcategory":"Advertising",
            "type":"Services"
        }
    ],
    "sg:phone":"+1 727 573 4333",
    "sg:postcode":"33716",
    "sg:province":"FL",
    "sg:tags":[
        "agency"
    ],
    "wof:name":"W B Doner and Company Inc",
    "wof:placetype":"venue"
},
  "geometry": {"coordinates":[-82.669304,27.888765],"type":"Point"}
}