{
  "type": "Feature",
  "properties": {
    "iso:country":"US",
    "sg:address":"14 del Prado Blvd N",
    "sg:city":"Cape Coral",
    "sg:classifiers":[
        {
            "category":"Building & Trades",
            "subcategory":"Construction",
            "type":"Services"
        }
    ],
    "sg:phone":"+1 239 437 5288",
    "sg:postcode":"33909",
    "sg:province":"FL",
    "sg:tags":[
        "general",
        "contractor"
    ],
    "sg:website":"www.legendcustombuilders.com",
    "wof:name":"Legend Custom Builders Inc",
    "wof:placetype":"venue"
},
  "geometry": {"coordinates":[-81.941078,26.655792],"type":"Point"}
}