{
  "type": "Feature",
  "properties": {
    "addr:full":"2284 Gulf To Bay Blvd Clearwater FL 33765",
    "addr:housenumber":"2284",
    "addr:postcode":"33765",
    "addr:street":"Gulf To Bay Blvd",
    "iso:country":"US",
    "sg:address":"2284 Gulf To Bay Blvd",
    "sg:city":"Clearwater",
    "sg:classifiers":[
        {
            "category":"Restaurant",
            "type":"Food & Drink"
        }
    ],
    "sg:menulink":"http://www.allmenus.com/fl/clearwater/28555-mirage-restaurant/menu/",
    "sg:phone":"+1 727 724 3604",
    "sg:postcode":"33765",
    "sg:province":"FL",
    "sg:tags":[
        "mediterranean"
    ],
    "wof:name":"Mirage Restaurant",
    "wof:placetype":"venue"
},
  "geometry": {"coordinates":[-82.742801,27.960588],"type":"Point"}
}