{
  "type": "Feature",
  "properties": {
    "addr:full":"10251 Metro Pkwy Fort Myers FL 33966",
    "addr:housenumber":"10251",
    "addr:postcode":"33966",
    "addr:street":"Metro Pkwy",
    "iso:country":"US",
    "sg:address":"10251 Metro Pkwy",
    "sg:city":"Fort Myers",
    "sg:classifiers":[
        {
            "category":"Manufacturing",
            "subcategory":"Tools & Machinery",
            "type":"Manufacturing & Wholesale Goods"
        }
    ],
    "sg:phone":"+1 239 275 1012",
    "sg:postcode":"33966",
    "sg:province":"FL",
    "sg:tags":[
        "instrument",
        "radioactivity"
    ],
    "wof:name":"Cardinal Health",
    "wof:placetype":"venue"
},
  "geometry": {"coordinates":[-81.850995,26.591548],"type":"Point"}
}