{
  "type": "Feature",
  "properties": {
    "iso:country":"US",
    "sg:address":"11406 N 56th St",
    "sg:city":"Tampa",
    "sg:classifiers":[
        {
            "category":"Health Services",
            "subcategory":"Chiropractor",
            "type":"Services"
        }
    ],
    "sg:phone":"+1 813 935 1664",
    "sg:postcode":"33617",
    "sg:province":"FL",
    "sg:tags":[
        "chiropractic"
    ],
    "sg:website":"http://www.drdanmadock.com",
    "wof:name":"Madock Daniel J DC",
    "wof:placetype":"venue"
},
  "geometry": {"coordinates":[-82.393761,28.052693],"type":"Point"}
}