{
  "type": "Feature",
  "properties": {
    "addr:full":"13035 Pine Sap Ct Clermont FL 34711",
    "addr:housenumber":"13035",
    "addr:postcode":"34711",
    "addr:street":"Pine Sap Ct",
    "iso:country":"US",
    "sg:address":"13035 Pine Sap Ct",
    "sg:city":"Clermont",
    "sg:classifiers":[
        {
            "category":"Manufacturing",
            "subcategory":"Printing",
            "type":"Manufacturing & Wholesale Goods"
        }
    ],
    "sg:phone":"+1 352 242 4574",
    "sg:postcode":"34711",
    "sg:province":"FL",
    "sg:tags":[
        "commercial"
    ],
    "wof:name":"Gem Printing",
    "wof:placetype":"venue"
},
  "geometry": {"coordinates":[-81.71195,28.536689],"type":"Point"}
}