{
  "type": "Feature",
  "properties": {
    "iso:country":"US",
    "sg:address":"1080 E Altamonte Dr",
    "sg:city":"Altamonte Springs",
    "sg:classifiers":[
        {
            "category":"Retail",
            "subcategory":"Storage",
            "type":"Services"
        }
    ],
    "sg:phone":"+1 321 594 6182",
    "sg:postcode":"32701",
    "sg:province":"FL",
    "sg:tags":[
        "self"
    ],
    "sg:website":"87744store.com",
    "wof:name":"Public Storage",
    "wof:placetype":"venue"
},
  "geometry": {"coordinates":[-81.374702,28.660801],"type":"Point"}
}