{
  "type": "Feature",
  "properties": {
    "iso:country":"US",
    "sg:address":"5327 SW 22nd Pl",
    "sg:city":"Cape Coral",
    "sg:classifiers":[
        {
            "category":"Building & Trades",
            "subcategory":"Construction",
            "type":"Services"
        }
    ],
    "sg:phone":"+1 239 549 0060",
    "sg:postcode":"33914",
    "sg:province":"FL",
    "sg:tags":[
        "excavation",
        "contractor"
    ],
    "wof:name":"R C Casey Inc",
    "wof:placetype":"venue"
},
  "geometry": {"coordinates":[-82.020517,26.552174],"type":"Point"}
}