{
  "type": "Feature",
  "properties": {
    "addr:full":"836 Hickory St Melbourne FL 32901",
    "addr:housenumber":"836",
    "addr:postcode":"32901",
    "addr:street":"Hickory St",
    "iso:country":"US",
    "sg:address":"836 Hickory St",
    "sg:city":"Melbourne",
    "sg:classifiers":[
        {
            "category":"Building & Trades",
            "subcategory":"Construction",
            "type":"Services"
        }
    ],
    "sg:phone":"+1 321 676 2022",
    "sg:postcode":"32901",
    "sg:province":"FL",
    "sg:tags":[
        "concrete",
        "contractor"
    ],
    "wof:name":"Quality Stucco Of Brevard Inc",
    "wof:placetype":"venue"
},
  "geometry": {"coordinates":[-80.613749,28.096091],"type":"Point"}
}