{
  "type": "Feature",
  "properties": {
    "addr:full":"3618 Fowler St Unit B Fort Myers FL 33901",
    "addr:housenumber":"3618",
    "addr:postcode":"33901",
    "addr:street":"Fowler St Unit B",
    "iso:country":"US",
    "sg:address":"3618 Fowler St Unit B",
    "sg:city":"Fort Myers",
    "sg:classifiers":[
        {
            "category":"Cinema",
            "subcategory":"Movie Rental",
            "type":"Entertainment"
        }
    ],
    "sg:phone":"+1 239 939 0020",
    "sg:postcode":"33901",
    "sg:province":"FL",
    "sg:tags":[
        "game",
        "video"
    ],
    "wof:name":"Real Deal Video",
    "wof:placetype":"venue"
},
  "geometry": {"coordinates":[-81.86190000000001,26.611],"type":"Point"}
}