{
  "type": "Feature",
  "properties": {
    "addr:full":"6700 7th Ave N Saint Petersburg FL 33710",
    "addr:housenumber":"6700",
    "addr:postcode":"33710",
    "addr:street":"7Th Ave N",
    "iso:country":"US",
    "sg:address":"6700 7th Ave N",
    "sg:city":"Saint Petersburg",
    "sg:classifiers":[
        {
            "category":"Shopping",
            "subcategory":"Books",
            "type":"Retail Goods"
        }
    ],
    "sg:phone":"+1 727 347 0310",
    "sg:postcode":"33710",
    "sg:province":"FL",
    "sg:tags":[
        "textbook"
    ],
    "wof:name":"St Petersburg Junior College",
    "wof:placetype":"venue"
},
  "geometry": {"coordinates":[-82.732237,27.779069],"type":"Point"}
}