{
  "type": "Feature",
  "properties": {
    "addr:full":"209 NW 1st Ave Fort Lauderdale FL 33301",
    "addr:housenumber":"209",
    "addr:postcode":"33301",
    "addr:street":"Nw 1St Ave",
    "iso:country":"US",
    "sg:address":"209 NW 1st Ave",
    "sg:city":"Fort Lauderdale",
    "sg:classifiers":[
        {
            "category":"Autos & Motor Vehicles",
            "subcategory":"Automobile Sales",
            "type":"Retail Goods"
        }
    ],
    "sg:phone":"+1 954 467 9404",
    "sg:postcode":"33301",
    "sg:province":"FL",
    "sg:tags":[
        "truck"
    ],
    "wof:name":"Fabiana's Truck Repair",
    "wof:placetype":"venue"
},
  "geometry": {"coordinates":[-80.14437700000001,26.125937],"type":"Point"}
}