{
  "type": "Feature",
  "properties": {
    "addr:full":"1844 SW 16th Ter Miami FL 33145",
    "addr:housenumber":"1844",
    "addr:postcode":"33145",
    "addr:street":"Sw 16Th Ter",
    "iso:country":"US",
    "sg:address":"1844 SW 16th Ter",
    "sg:city":"Miami",
    "sg:classifiers":[
        {
            "category":"Wholesale",
            "subcategory":"Groceries",
            "type":"Manufacturing & Wholesale Goods"
        }
    ],
    "sg:phone":"+1 305 860 9913",
    "sg:postcode":"33145",
    "sg:province":"FL",
    "sg:tags":[
        "truffle",
        "product",
        "based"
    ],
    "wof:name":"Terre Di Toscana Inc",
    "wof:placetype":"venue"
},
  "geometry": {"coordinates":[-80.22548999999999,25.757368],"type":"Point"}
}