{
  "type": "Feature",
  "properties": {
    "addr:full":"23161 Village Shops Way Estero FL 33928",
    "addr:housenumber":"23161",
    "addr:postcode":"33928",
    "addr:street":"Village Shops Way",
    "iso:country":"US",
    "sg:address":"23161 Village Shops Way",
    "sg:city":"Estero",
    "sg:classifiers":[
        {
            "category":"Restaurant",
            "type":"Food & Drink"
        }
    ],
    "sg:phone":"+1 239 992 5040",
    "sg:postcode":"33928",
    "sg:province":"FL",
    "sg:tags":[
        "house",
        "steak",
        "barbecue"
    ],
    "wof:name":"Grape At Coconut Point",
    "wof:placetype":"venue"
},
  "geometry": {"coordinates":[-81.80806699999999,26.40177],"type":"Point"}
}