{
  "type": "Feature",
  "properties": {
    "iso:country":"US",
    "sg:address":"1401 S Magnolia Ave",
    "sg:city":"Sanford",
    "sg:classifiers":[
        {
            "category":"Social Services",
            "subcategory":"Adult Care",
            "type":"Services"
        }
    ],
    "sg:phone":"+1 407 323 9914",
    "sg:postcode":"32771",
    "sg:province":"FL",
    "sg:tags":[
        "home",
        "residential"
    ],
    "wof:name":"Gracious Age",
    "wof:placetype":"venue"
},
  "geometry": {"coordinates":[-81.266887,28.799004],"type":"Point"}
}