{
  "type": "Feature",
  "properties": {
    "addr:full":"29603 NW 142nd Ave High Springs FL 32643",
    "addr:housenumber":"29603",
    "addr:postcode":"32643",
    "addr:street":"Nw 142Nd Ave",
    "iso:country":"US",
    "sg:address":"29603 NW 142nd Ave",
    "sg:city":"High Springs",
    "sg:classifiers":[
        {
            "category":"Organizations",
            "subcategory":"Religious Organization",
            "type":"Services"
        }
    ],
    "sg:phone":"+1 386 454 2161",
    "sg:postcode":"32643",
    "sg:province":"FL",
    "sg:tags":[
        "church"
    ],
    "wof:name":"Mt Pleasant Baptist Church",
    "wof:placetype":"venue"
},
  "geometry": {"coordinates":[-82.63269099999999,29.785353],"type":"Point"}
}