{
  "type": "Feature",
  "properties": {
    "iso:country":"US",
    "sg:address":"1368 Blountstown Hwy",
    "sg:city":"Tallahassee",
    "sg:classifiers":[
        {
            "category":"Recreation",
            "type":"Entertainment"
        }
    ],
    "sg:phone":"+1 850 575 4877",
    "sg:postcode":"32304",
    "sg:province":"FL",
    "wof:name":"Skate Inn West Inc",
    "wof:placetype":"venue"
},
  "geometry": {"coordinates":[-84.345393,30.453866],"type":"Point"}
}