{
  "type": "Feature",
  "properties": {
    "addr:full":"7315 SW 87th Ave Miami FL 33173",
    "addr:housenumber":"7315",
    "addr:postcode":"33173",
    "addr:street":"Sw 87Th Ave",
    "iso:country":"US",
    "sg:address":"7315 SW 87th Ave",
    "sg:city":"Miami",
    "sg:classifiers":[
        {
            "category":"Banks & Credit Unions",
            "subcategory":"Bank",
            "type":"Services"
        }
    ],
    "sg:phone":"+1 305 412 9920",
    "sg:postcode":"33173",
    "sg:province":"FL",
    "wof:name":"Florida Health Systems Federal Credit Union",
    "wof:placetype":"venue"
},
  "geometry": {"coordinates":[-80.333842,25.700448],"type":"Point"}
}