{
  "type": "Feature",
  "properties": {
    "iso:country":"US",
    "sg:address":"871 Sunshine Lane",
    "sg:city":"Altamonte Springs",
    "sg:classifiers":[
        {
            "category":"Building & Trades",
            "subcategory":"Cleaning & Sanitation",
            "type":"Services"
        }
    ],
    "sg:phone":"+1 407 682 3939",
    "sg:postcode":"32714",
    "sg:province":"FL",
    "sg:tags":[
        "home"
    ],
    "sg:website":"www.gutterhelmetflorida.com",
    "wof:name":"Gutter Helmet - Central Florida",
    "wof:placetype":"venue"
},
  "geometry": {"coordinates":[-81.417805,28.655397],"type":"Point"}
}