{
  "type": "Feature",
  "properties": {
    "iso:country":"US",
    "sg:address":"6209 Royal Poinciana Ln",
    "sg:city":"Fort Lauderdale",
    "sg:classifiers":[
        {
            "category":"Professional",
            "subcategory":"Management & Consulting",
            "type":"Services"
        }
    ],
    "sg:phone":"+1 954 731 3190",
    "sg:postcode":"33319",
    "sg:province":"FL",
    "wof:name":"Newman Management Inc",
    "wof:placetype":"venue"
},
  "geometry": {"coordinates":[-80.234476,26.180565],"type":"Point"}
}