{
  "type": "Feature",
  "properties": {
    "iso:country":"US",
    "sg:address":"3111 E Colonial Dr",
    "sg:city":"Orlando",
    "sg:classifiers":[
        {
            "category":"Retail",
            "subcategory":"Auto Rental",
            "type":"Services"
        }
    ],
    "sg:phone":"+1 407 895 6433",
    "sg:postcode":"32803",
    "sg:province":"FL",
    "sg:tags":[
        "renting",
        "leasing",
        "van",
        "automobile"
    ],
    "sg:website":"http://avis.com/IYP_tl",
    "wof:name":"Avis Rent A Car",
    "wof:placetype":"venue"
},
  "geometry": {"coordinates":[-81.342642,28.553434],"type":"Point"}
}