{
  "type": "Feature",
  "properties": {
    "iso:country":"US",
    "sg:address":"4315 NW 7th St Ste 15",
    "sg:city":"Miami",
    "sg:classifiers":[
        {
            "category":"Shopping",
            "subcategory":"Pets & Pet Supplies",
            "type":"Retail Goods"
        }
    ],
    "sg:phone":"+1 305 567 1562",
    "sg:postcode":"33126",
    "sg:province":"FL",
    "sg:tags":[
        "store"
    ],
    "wof:name":"Animals Pet Supply",
    "wof:placetype":"venue"
},
  "geometry": {"coordinates":[-80.266701,25.7787],"type":"Point"}
}