{
  "type": "Feature",
  "properties": {
    "addr:full":"2505 Hill St New Smyrna Beach FL 32169",
    "addr:housenumber":"2505",
    "addr:postcode":"32169",
    "addr:street":"Hill St",
    "iso:country":"US",
    "sg:address":"2505 Hill St",
    "sg:city":"New Smyrna Beach",
    "sg:classifiers":[
        {
            "category":"Professional",
            "subcategory":"Business Services",
            "type":"Services"
        }
    ],
    "sg:phone":"+1 386 405 6304",
    "sg:postcode":"32169",
    "sg:province":"FL",
    "wof:name":"Golf Works",
    "wof:placetype":"venue"
},
  "geometry": {"coordinates":[-80.88461599999999,29.018559],"type":"Point"}
}