{
  "type": "Feature",
  "properties": {
    "iso:country":"US",
    "sg:address":"3000 34th St S",
    "sg:city":"Saint Petersburg",
    "sg:classifiers":[
        {
            "category":"Shopping",
            "subcategory":"Clothing, Apparel, & Fashions",
            "type":"Retail Goods"
        }
    ],
    "sg:phone":"+1 727 864 4813",
    "sg:postcode":"33711",
    "sg:province":"FL",
    "wof:name":"What 2 Wear",
    "wof:placetype":"venue"
},
  "geometry": {"coordinates":[-82.679202,27.740009],"type":"Point"}
}