{
  "type": "Feature",
  "properties": {
    "iso:country":"US",
    "sg:address":"1560 Capital Cir NW Ste 3",
    "sg:city":"Tallahassee",
    "sg:classifiers":[
        {
            "category":"Banks & Credit Unions",
            "subcategory":"Financial Services",
            "type":"Services"
        }
    ],
    "sg:phone":"+1 850 942 7070",
    "sg:postcode":"32303",
    "sg:province":"FL",
    "sg:tags":[
        "cashing",
        "loan",
        "check"
    ],
    "sg:website":"http://www.crpaydayadvance.com",
    "wof:name":"C & R Payday Advance",
    "wof:placetype":"venue"
},
  "geometry": {"coordinates":[-84.361389,30.47056],"type":"Point"}
}