{
  "type": "Feature",
  "properties": {
    "iso:country":"US",
    "sg:address":"42673 Highway 27",
    "sg:city":"Davenport",
    "sg:classifiers":[
        {
            "category":"Travel",
            "subcategory":"Hotels & Motels",
            "type":"Entertainment"
        }
    ],
    "sg:phone":"+1 863 424 1003",
    "sg:postcode":"33837",
    "sg:province":"FL",
    "sg:website":"www.terrysvacationvillas.com",
    "wof:name":"Terry's Vacation Villas Inc",
    "wof:placetype":"venue"
},
  "geometry": {"coordinates":[-81.640333,28.216792],"type":"Point"}
}