{
  "type": "Feature",
  "properties": {
    "addr:full":"3915 Savannahs Trl Merritt Island FL 32953",
    "addr:housenumber":"3915",
    "addr:postcode":"32953",
    "addr:street":"Savannahs Trl",
    "iso:country":"US",
    "sg:address":"3915 Savannahs Trl",
    "sg:city":"Merritt Island",
    "sg:classifiers":[
        {
            "category":"Sports & Exercise",
            "subcategory":"Golf",
            "type":"Entertainment"
        }
    ],
    "sg:phone":"+1 321 455 9775",
    "sg:postcode":"32953",
    "sg:province":"FL",
    "wof:name":"The Caddy Shack",
    "wof:placetype":"venue"
},
  "geometry": {"coordinates":[-80.67693199999999,28.425844],"type":"Point"}
}