{
  "type": "Feature",
  "properties": {
    "iso:country":"US",
    "sg:address":"3507 Lowson Blvd",
    "sg:city":"Delray Beach",
    "sg:classifiers":[
        {
            "category":"Professional",
            "subcategory":"Business Services",
            "type":"Services"
        }
    ],
    "sg:phone":"+1 561 637 8334",
    "sg:postcode":"33445",
    "sg:province":"FL",
    "wof:name":"Southeast Business Development",
    "wof:placetype":"venue"
},
  "geometry": {"coordinates":[-80.11393,26.446024],"type":"Point"}
}