{
  "type": "Feature",
  "properties": {
    "addr:full":"1076 Martha Lee Ave Rockledge FL 32955",
    "addr:housenumber":"1076",
    "addr:postcode":"32955",
    "addr:street":"Martha Lee Ave",
    "iso:country":"US",
    "sg:address":"1076 Martha Lee Ave",
    "sg:city":"Rockledge",
    "sg:classifiers":[
        {
            "category":"Wholesale",
            "subcategory":"Machinery & Supplies",
            "type":"Manufacturing & Wholesale Goods"
        }
    ],
    "sg:phone":"+1 321 480 6048",
    "sg:postcode":"32955",
    "sg:province":"FL",
    "sg:tags":[
        "equipment",
        "establishment"
    ],
    "wof:name":"Karl Struss Jr",
    "wof:placetype":"venue"
},
  "geometry": {"coordinates":[-80.75158399999999,28.310309],"type":"Point"}
}