{
  "type": "Feature",
  "properties": {
    "iso:country":"US",
    "sg:address":"16800 NW 67th Ave",
    "sg:city":"Hialeah",
    "sg:classifiers":[
        {
            "category":"Banks & Credit Unions",
            "subcategory":"Bank",
            "type":"Services"
        }
    ],
    "sg:phone":"+1 305 556 5888",
    "sg:postcode":"33015",
    "sg:province":"FL",
    "sg:website":"http://bankunited.com",
    "wof:name":"Bankunited Fsb",
    "wof:placetype":"venue"
},
  "geometry": {"coordinates":[-80.30950199999999,25.926001],"type":"Point"}
}