{
  "type": "Feature",
  "properties": {
    "iso:country":"US",
    "sg:address":"1924 S 14th St",
    "sg:city":"Fernandina Beach",
    "sg:classifiers":[
        {
            "category":"Real Estate",
            "subcategory":"Real Estate Agent",
            "type":"Services"
        }
    ],
    "sg:phone":"+1 904 206 5050",
    "sg:postcode":"32034",
    "sg:province":"FL",
    "wof:name":"Assist 2 Sell Middlekauff Rlty",
    "wof:placetype":"venue"
},
  "geometry": {"coordinates":[-81.45601499999999,30.63928],"type":"Point"}
}