{
  "type": "Feature",
  "properties": {
    "iso:country":"US",
    "sg:address":"3906 Enterprise Ave",
    "sg:city":"Naples",
    "sg:classifiers":[
        {
            "category":"Wholesale",
            "subcategory":"Electrical",
            "type":"Manufacturing & Wholesale Goods"
        }
    ],
    "sg:phone":"+1 239 643 5802",
    "sg:postcode":"34104",
    "sg:province":"FL",
    "sg:tags":[
        "equipment",
        "electric",
        "supply"
    ],
    "wof:name":"World Electric Supply",
    "wof:placetype":"venue"
},
  "geometry": {"coordinates":[-81.76572299999999,26.160511],"type":"Point"}
}