{
  "type": "Feature",
  "properties": {
    "iso:country":"US",
    "sg:address":"1260 SW 142nd Ct",
    "sg:city":"Miami",
    "sg:classifiers":[
        {
            "category":"Wholesale",
            "subcategory":"Machinery & Supplies",
            "type":"Manufacturing & Wholesale Goods"
        }
    ],
    "sg:phone":"+1 305 223 4747",
    "sg:postcode":"33184",
    "sg:province":"FL",
    "sg:tags":[
        "industrial",
        "parts"
    ],
    "wof:name":"Technlgcal Invstments Sups Inc",
    "wof:placetype":"venue"
},
  "geometry": {"coordinates":[-80.42557600000001,25.754648],"type":"Point"}
}