{
  "type": "Feature",
  "properties": {
    "iso:country":"US",
    "sg:address":"14443 Miramar Pkwy",
    "sg:city":"Miramar",
    "sg:classifiers":[
        {
            "category":"Restaurant",
            "type":"Food & Drink"
        }
    ],
    "sg:phone":"+1 954 437 5550",
    "sg:postcode":"33027",
    "sg:province":"FL",
    "sg:tags":[
        "german",
        "thai"
    ],
    "wof:name":"Thai Noodle House",
    "wof:placetype":"venue"
},
  "geometry": {"coordinates":[-80.340142,25.97875],"type":"Point"}
}