{
  "type": "Feature",
  "properties": {
    "iso:country":"US",
    "sg:address":"23323 Treeline Dr",
    "sg:city":"Boca Raton",
    "sg:classifiers":[
        {
            "category":"Building & Trades",
            "subcategory":"Cleaning & Sanitation",
            "type":"Services"
        }
    ],
    "sg:phone":"+1 561 470 3302",
    "sg:postcode":"33428",
    "sg:province":"FL",
    "sg:tags":[
        "janitor"
    ],
    "wof:name":"Bright Maintenance Inc",
    "wof:placetype":"venue"
},
  "geometry": {"coordinates":[-80.207025,26.331888],"type":"Point"}
}