{
  "type": "Feature",
  "properties": {
    "iso:country":"US",
    "sg:address":"1005 Centerbrook Dr",
    "sg:city":"Brandon",
    "sg:classifiers":[
        {
            "category":"Building & Trades",
            "subcategory":"Construction",
            "type":"Services"
        }
    ],
    "sg:phone":"+1 813 681 1541",
    "sg:postcode":"33511",
    "sg:province":"FL",
    "sg:tags":[
        "residential"
    ],
    "wof:name":"Southern Heritage Neighborhood",
    "wof:placetype":"venue"
},
  "geometry": {"coordinates":[-82.275071,27.875498],"type":"Point"}
}