{
  "type": "Feature",
  "properties": {
    "addr:full":"501 30th St West Palm Beach FL 33407",
    "addr:housenumber":"501",
    "addr:postcode":"33407",
    "addr:street":"30Th St",
    "iso:country":"US",
    "sg:address":"501 30th St",
    "sg:city":"West Palm Beach",
    "sg:classifiers":[
        {
            "category":"Travel",
            "subcategory":"Hotels & Motels",
            "type":"Entertainment"
        }
    ],
    "sg:phone":"+1 561 863 5633",
    "sg:postcode":"33407",
    "sg:province":"FL",
    "sg:tags":[
        "operation"
    ],
    "sg:website":"www.hibiscushouse.com",
    "wof:name":"Hibiscus House Bed & Breakfast",
    "wof:placetype":"venue"
},
  "geometry": {"coordinates":[-80.056692,26.740843],"type":"Point"}
}