{
  "type": "Feature",
  "properties": {
    "iso:country":"US",
    "sg:address":"798 W Town Pkwy",
    "sg:city":"Altamonte Springs",
    "sg:classifiers":[
        {
            "category":"Sports & Exercise",
            "subcategory":"Golf",
            "type":"Entertainment"
        }
    ],
    "sg:phone":"+1 407 774 4653",
    "sg:postcode":"32714",
    "sg:province":"FL",
    "sg:website":"www.myspace.com/thelinksat434",
    "wof:name":"Links At 434 the",
    "wof:placetype":"venue"
},
  "geometry": {"coordinates":[-81.418701,28.662001],"type":"Point"}
}