{
  "type": "Feature",
  "properties": {
    "iso:country":"US",
    "sg:address":"340 Candler Ave",
    "sg:city":"Orlando",
    "sg:classifiers":[
        {
            "category":"Professional",
            "subcategory":"Business Services",
            "type":"Services"
        }
    ],
    "sg:phone":"+1 407 293 4717",
    "sg:postcode":"32835",
    "sg:province":"FL",
    "wof:name":"American Pool League",
    "wof:placetype":"venue"
},
  "geometry": {"coordinates":[-81.47310400000001,28.535242],"type":"Point"}
}