{
  "type": "Feature",
  "properties": {
    "iso:country":"US",
    "sg:address":"1000 W McNab Rd",
    "sg:city":"Pompano Beach",
    "sg:classifiers":[
        {
            "category":"Professional",
            "subcategory":"Computer Services",
            "type":"Services"
        }
    ],
    "sg:phone":"+1 954 785 8648",
    "sg:postcode":"33069",
    "sg:province":"FL",
    "sg:tags":[
        "consultant",
        "designer"
    ],
    "wof:name":"S Fl Computer Consultants",
    "wof:placetype":"venue"
},
  "geometry": {"coordinates":[-80.137394,26.210721],"type":"Point"}
}