{
  "type": "Feature",
  "properties": {
    "iso:country":"US",
    "sg:address":"300 Lemon St",
    "sg:city":"Maitland",
    "sg:classifiers":[
        {
            "category":"Health Services",
            "subcategory":"Clinic",
            "type":"Services"
        },
        {
            "category":"Wholesale",
            "subcategory":"Wine & Distilled Alcoholic Beverages",
            "type":"Manufacturing & Wholesale Goods"
        }
    ],
    "sg:phone":"+1 407 212 2141",
    "sg:postcode":"32751",
    "sg:province":"FL",
    "sg:tags":[
        "information",
        "treatment",
        "alcoholism",
        "liquors-wholesale"
    ],
    "wof:name":"United Liquor Alliance",
    "wof:placetype":"venue"
},
  "geometry": {"coordinates":[-81.38055,28.61756],"type":"Point"}
}