{
  "type": "Feature",
  "properties": {
    "addr:full":"1221 Club Dr W Delray Beach FL 33445",
    "addr:housenumber":"1221",
    "addr:postcode":"33445",
    "addr:street":"Club Dr W",
    "iso:country":"US",
    "sg:address":"1221 Club Dr W",
    "sg:city":"Delray Beach",
    "sg:classifiers":[
        {
            "category":"Organizations",
            "subcategory":"Community Association",
            "type":"Services"
        }
    ],
    "sg:phone":"+1 561 496 4628",
    "sg:postcode":"33445",
    "sg:province":"FL",
    "sg:tags":[
        "real estate"
    ],
    "wof:name":"High Point of Delray Beach",
    "wof:placetype":"venue"
},
  "geometry": {"coordinates":[-80.11075599999999,26.464316],"type":"Point"}
}