{
  "type": "Feature",
  "properties": {
    "addr:full":"301 Circle Dr Maitland FL 32751",
    "addr:housenumber":"301",
    "addr:postcode":"32751",
    "addr:street":"Circle Dr",
    "iso:country":"US",
    "sg:address":"301 Circle Dr",
    "sg:city":"Maitland",
    "sg:classifiers":[
        {
            "category":"Personal",
            "subcategory":"Beauty Salon",
            "type":"Services"
        }
    ],
    "sg:phone":"+1 407 647 1441",
    "sg:postcode":"32751",
    "sg:province":"FL",
    "wof:name":"Garrett & Co",
    "wof:placetype":"venue"
},
  "geometry": {"coordinates":[-81.365763,28.61438],"type":"Point"}
}