{
  "type": "Feature",
  "properties": {
    "iso:country":"US",
    "sg:address":"3477 Gulf Breeze Pkwy",
    "sg:city":"Gulf Breeze",
    "sg:classifiers":[
        {
            "category":"Shopping",
            "subcategory":"Bicycles & Sporting Goods",
            "type":"Retail Goods"
        }
    ],
    "sg:phone":"+1 850 932 0706",
    "sg:postcode":"32563",
    "sg:province":"FL",
    "wof:name":"Bikes Plus",
    "wof:placetype":"venue"
},
  "geometry": {"coordinates":[-87.07343299999999,30.388741],"type":"Point"}
}