{
  "type": "Feature",
  "properties": {
    "addr:full":"9401 SW Hwy 200 Ocala FL 34481",
    "addr:housenumber":"9401",
    "addr:postcode":"34481",
    "addr:street":"Sw Hwy 200",
    "iso:country":"US",
    "sg:address":"9401 SW Hwy 200",
    "sg:city":"Ocala",
    "sg:classifiers":[
        {
            "category":"Health Services",
            "subcategory":"Doctor",
            "type":"Services"
        }
    ],
    "sg:phone":"+1 352 873 1100",
    "sg:postcode":"34481",
    "sg:province":"FL",
    "sg:tags":[
        "physician",
        "surgeon"
    ],
    "wof:name":"Challa Citrus & Marion Grtrcs",
    "wof:placetype":"venue"
},
  "geometry": {"coordinates":[-82.25008699999999,29.086197],"type":"Point"}
}