{
  "type": "Feature",
  "properties": {
    "iso:country":"US",
    "sg:address":"3546 S Ocean Blvd",
    "sg:city":"Palm Beach",
    "sg:classifiers":[
        {
            "category":"Building & Trades",
            "subcategory":"Plumbing",
            "type":"Services"
        }
    ],
    "sg:phone":"+1 561 540 6390",
    "sg:postcode":"33480",
    "sg:province":"FL",
    "sg:tags":[
        "contractor"
    ],
    "wof:name":"Gentleman Plumber",
    "wof:placetype":"venue"
},
  "geometry": {"coordinates":[-80.039109,26.591018],"type":"Point"}
}