{
  "type": "Feature",
  "properties": {
    "addr:full":"8610 59th St E Parrish FL 34219",
    "addr:housenumber":"8610",
    "addr:postcode":"34219",
    "addr:street":"59Th St E Parrish",
    "iso:country":"US",
    "sg:address":"8610 59th St E",
    "sg:city":"Parrish",
    "sg:classifiers":[
        {
            "category":"Banks & Credit Unions",
            "subcategory":"Bank",
            "type":"Services"
        }
    ],
    "sg:phone":"+1 941 776 0632",
    "sg:postcode":"34219",
    "sg:province":"FL",
    "sg:tags":[
        "aircraft",
        "financing"
    ],
    "wof:name":"Delta Aircraft Finance Corp",
    "wof:placetype":"venue"
},
  "geometry": {"coordinates":[-82.47689800000001,27.566775],"type":"Point"}
}