{
  "type": "Feature",
  "properties": {
    "iso:country":"US",
    "sg:address":"139 SW Port Saint Lucie Blvd",
    "sg:city":"Port Saint Lucie",
    "sg:classifiers":[
        {
            "category":"Health Services",
            "subcategory":"Medical Lab",
            "type":"Services"
        }
    ],
    "sg:phone":"+1 772 878 5288",
    "sg:postcode":"34984",
    "sg:province":"FL",
    "sg:tags":[
        "laboratory",
        "dental"
    ],
    "wof:name":"Anthony R Matheny",
    "wof:placetype":"venue"
},
  "geometry": {"coordinates":[-80.34578999999999,27.27366],"type":"Point"}
}