{
  "type": "Feature",
  "properties": {
    "addr:full":"4900 NW 15th St Margate FL 33063",
    "addr:housenumber":"4900",
    "addr:postcode":"33063",
    "addr:street":"Nw 15Th St Margate",
    "iso:country":"US",
    "sg:address":"4900 NW 15th St",
    "sg:city":"Margate",
    "sg:classifiers":[
        {
            "category":"Autos & Motor Vehicles",
            "subcategory":"Automobile Sales",
            "type":"Retail Goods"
        }
    ],
    "sg:phone":"+1 954 979 6923",
    "sg:postcode":"33063",
    "sg:province":"FL",
    "sg:tags":[
        "dealers-used",
        "car",
        "used",
        "cars-wholesale",
        "new"
    ],
    "wof:name":"Best Deals Auto Sales",
    "wof:placetype":"venue"
},
  "geometry": {"coordinates":[-80.19332900000001,26.24859],"type":"Point"}
}