{
  "type": "Feature",
  "properties": {
    "addr:full":"401 Mango Ave Sarasota FL 34237",
    "addr:housenumber":"401",
    "addr:postcode":"34237",
    "addr:street":"Mango Ave",
    "iso:country":"US",
    "sg:address":"401 Mango Ave",
    "sg:city":"Sarasota",
    "sg:classifiers":[
        {
            "category":"Home & Garden",
            "subcategory":"Building Materials",
            "type":"Retail Goods"
        }
    ],
    "sg:phone":"+1 941 330 2008",
    "sg:postcode":"34237",
    "sg:province":"FL",
    "sg:tags":[
        "screen",
        "window"
    ],
    "wof:name":"Dream Screens",
    "wof:placetype":"venue"
},
  "geometry": {"coordinates":[-82.525274,27.340535],"type":"Point"}
}