{
  "type": "Feature",
  "properties": {
    "iso:country":"US",
    "sg:address":"1600 McCulloch Rd",
    "sg:city":"Oviedo",
    "sg:classifiers":[
        {
            "category":"Organizations",
            "subcategory":"Religious Organization",
            "type":"Services"
        }
    ],
    "sg:phone":"+1 407 359 2112",
    "sg:postcode":"32765",
    "sg:province":"FL",
    "sg:tags":[
        "church"
    ],
    "wof:name":"Univ Carillon United Meth Ch",
    "wof:placetype":"venue"
},
  "geometry": {"coordinates":[-81.242079,28.611716],"type":"Point"}
}