{
  "type": "Feature",
  "properties": {
    "iso:country":"US",
    "sg:address":"3902 N 9th Ave",
    "sg:city":"Pensacola",
    "sg:classifiers":[
        {
            "category":"Personal",
            "type":"Services"
        }
    ],
    "sg:phone":"+1 850 380 2667",
    "sg:postcode":"32503",
    "sg:province":"FL",
    "sg:tags":[
        "therapist",
        "massage"
    ],
    "wof:name":"Priceless Massage Svc",
    "wof:placetype":"venue"
},
  "geometry": {"coordinates":[-87.214541,30.455684],"type":"Point"}
}