{
  "type": "Feature",
  "properties": {
    "addr:full":"2732 Crystal Beach Rd Winter Haven FL 33880",
    "addr:housenumber":"2732",
    "addr:postcode":"33880",
    "addr:street":"Crystal Beach Rd",
    "iso:country":"US",
    "sg:address":"2732 Crystal Beach Rd",
    "sg:city":"Winter Haven",
    "sg:classifiers":[
        {
            "category":"Shopping",
            "subcategory":"Gifts & Souvenirs",
            "type":"Retail Goods"
        }
    ],
    "sg:phone":"+1 863 299 6324",
    "sg:postcode":"33880",
    "sg:province":"FL",
    "wof:name":"Starlite Gifts & Novelti",
    "wof:placetype":"venue"
},
  "geometry": {"coordinates":[-81.76979,28.000762],"type":"Point"}
}