{
  "type": "Feature",
  "properties": {
    "iso:country":"US",
    "sg:address":"6084 Blue Stone Ln",
    "sg:city":"Lake Worth",
    "sg:classifiers":[
        {
            "category":"Wholesale",
            "subcategory":"Furniture",
            "type":"Manufacturing & Wholesale Goods"
        }
    ],
    "sg:phone":"+1 561 540 9055",
    "sg:postcode":"33463",
    "sg:province":"FL",
    "wof:name":"A & E Installations & Cleaning",
    "wof:placetype":"venue"
},
  "geometry": {"coordinates":[-80.14133699999999,26.596358],"type":"Point"}
}