{
  "type": "Feature",
  "properties": {
    "iso:country":"US",
    "sg:address":"2430 NE 13th Ave",
    "sg:city":"Wilton Manors",
    "sg:classifiers":[
        {
            "category":"Building & Trades",
            "subcategory":"Landscaping Services",
            "type":"Services"
        }
    ],
    "sg:phone":"+1 954 564 9147",
    "sg:postcode":"33305",
    "sg:province":"FL",
    "sg:tags":[
        "landscape",
        "contractor"
    ],
    "wof:name":"Wilton Manors Nursery",
    "wof:placetype":"venue"
},
  "geometry": {"coordinates":[-80.129907,26.158548],"type":"Point"}
}