{
  "type": "Feature",
  "properties": {
    "addr:full":"5745 SW 75th St Gainesville FL 32608",
    "addr:housenumber":"5745",
    "addr:postcode":"32608",
    "addr:street":"Sw 75Th St",
    "iso:country":"US",
    "sg:address":"5745 SW 75th St",
    "sg:city":"Gainesville",
    "sg:classifiers":[
        {
            "category":"Building & Trades",
            "subcategory":"Landscaping Services",
            "type":"Services"
        }
    ],
    "sg:phone":"+1 352 372 6037",
    "sg:postcode":"32608",
    "sg:province":"FL",
    "sg:tags":[
        "landscape"
    ],
    "wof:name":"Decorator Mulch Inc",
    "wof:placetype":"venue"
},
  "geometry": {"coordinates":[-82.420205,29.599475],"type":"Point"}
}