{
  "type": "Feature",
  "properties": {
    "iso:country":"US",
    "sg:address":"19575 Biscayne Blvd",
    "sg:city":"Aventura",
    "sg:classifiers":[
        {
            "category":"Restaurant",
            "type":"Food & Drink"
        }
    ],
    "sg:phone":"+1 305 538 0058",
    "sg:postcode":"33180",
    "sg:province":"FL",
    "wof:name":"Paninoteca European Sandwiches",
    "wof:placetype":"venue"
},
  "geometry": {"coordinates":[-80.14679700000001,25.958],"type":"Point"}
}