{
  "type": "Feature",
  "properties": {
    "iso:country":"US",
    "sg:address":"15 N Charles Richard Beall Blvd",
    "sg:city":"Debary",
    "sg:classifiers":[
        {
            "category":"Shopping",
            "subcategory":"Pharmacy",
            "type":"Retail Goods"
        }
    ],
    "sg:phone":"+1 386 668 4946",
    "sg:postcode":"32713",
    "sg:province":"FL",
    "sg:tags":[
        "drugstore"
    ],
    "sg:website":"www.walgreens.com",
    "wof:name":"Walgreen Drug Store",
    "wof:placetype":"venue"
},
  "geometry": {"coordinates":[-81.30645800000001,28.890913],"type":"Point"}
}