{
  "type": "Feature",
  "properties": {
    "addr:full":"1612 Old Philadelphia Church Rd Quincy FL 32352",
    "addr:housenumber":"1612",
    "addr:postcode":"32352",
    "addr:street":"Old;Church Rd",
    "iso:country":"US",
    "sg:address":"1612 Old Philadelphia Church Rd",
    "sg:city":"Quincy",
    "sg:classifiers":[
        {
            "category":"Shopping",
            "subcategory":"Discount & Variety Stores",
            "type":"Retail Goods"
        }
    ],
    "sg:phone":"+1 850 875 2852",
    "sg:postcode":"32352",
    "sg:province":"FL",
    "sg:tags":[
        "merchandise",
        "general"
    ],
    "wof:name":"Allies Apple",
    "wof:placetype":"venue"
},
  "geometry": {"coordinates":[-84.586603,30.645145],"type":"Point"}
}