{
  "type": "Feature",
  "properties": {
    "iso:country":"US",
    "sg:address":"406 SE 8th Pl",
    "sg:city":"Cape Coral",
    "sg:classifiers":[
        {
            "category":"Building & Trades",
            "subcategory":"Construction",
            "type":"Services"
        }
    ],
    "sg:phone":"+1 239 458 2169",
    "sg:postcode":"33990",
    "sg:province":"FL",
    "sg:tags":[
        "hanging",
        "contractor"
    ],
    "wof:name":"Ricks Painting & Paper Hanging",
    "wof:placetype":"venue"
},
  "geometry": {"coordinates":[-81.95744000000001,26.643134],"type":"Point"}
}