{
  "type": "Feature",
  "properties": {
    "addr:full":"150 22nd Ave Vero Beach FL 32962",
    "addr:housenumber":"150",
    "addr:postcode":"32962",
    "addr:street":"22Nd Ave",
    "iso:country":"US",
    "sg:address":"150 22nd Ave",
    "sg:city":"Vero Beach",
    "sg:classifiers":[
        {
            "category":"Building & Trades",
            "subcategory":"Cleaning & Sanitation",
            "type":"Services"
        }
    ],
    "sg:phone":"+1 772 696 3351",
    "sg:postcode":"32962",
    "sg:province":"FL",
    "sg:tags":[
        "janitor"
    ],
    "wof:name":"Patricia Mitchem's Cleaning",
    "wof:placetype":"venue"
},
  "geometry": {"coordinates":[-80.407808,27.603373],"type":"Point"}
}