{
  "type": "Feature",
  "properties": {
    "iso:country":"US",
    "sg:address":"651 E 61st St",
    "sg:city":"Hialeah",
    "sg:classifiers":[
        {
            "category":"Communications",
            "subcategory":"Film & Video Production",
            "type":"Services"
        }
    ],
    "sg:phone":"+1 305 681 3213",
    "sg:postcode":"33013",
    "sg:province":"FL",
    "sg:tags":[
        "motion",
        "tv",
        "radio",
        "companies-film"
    ],
    "wof:name":"Ultra Sound Productions Inc",
    "wof:placetype":"venue"
},
  "geometry": {"coordinates":[-80.270011,25.878126],"type":"Point"}
}