{
  "type": "Feature",
  "properties": {
    "iso:country":"US",
    "sg:address":"431 SW 77th Ave",
    "sg:city":"Miami",
    "sg:classifiers":[
        {
            "category":"Real Estate",
            "subcategory":"Real Estate Services",
            "type":"Services"
        },
        {
            "category":"Building & Trades",
            "subcategory":"Cleaning & Sanitation",
            "type":"Services"
        }
    ],
    "sg:phone":"+1 786 275 9888",
    "sg:postcode":"33144",
    "sg:province":"FL",
    "sg:tags":[
        "maintenance",
        "cleaners-interior"
    ],
    "wof:name":"Housekeeping Headquarters",
    "wof:placetype":"venue"
},
  "geometry": {"coordinates":[-80.319886,25.766024],"type":"Point"}
}