{
  "type": "Feature",
  "properties": {
    "iso:country":"US",
    "sg:address":"1314 Lake Shore Blvd",
    "sg:city":"Jacksonville",
    "sg:classifiers":[
        {
            "category":"Building & Trades",
            "subcategory":"Plumbing",
            "type":"Services"
        }
    ],
    "sg:phone":"+1 904 783 0489",
    "sg:postcode":"32205",
    "sg:province":"FL",
    "sg:tags":[
        "test",
        "balancing",
        "conditioning",
        "air"
    ],
    "wof:name":"Buiding Diagnostics",
    "wof:placetype":"venue"
},
  "geometry": {"coordinates":[-81.739119,30.298106],"type":"Point"}
}