{
  "type": "Feature",
  "properties": {
    "iso:country":"US",
    "sg:address":"915 NE 3rd Ave",
    "sg:city":"Fort Lauderdale",
    "sg:classifiers":[
        {
            "category":"Wholesale",
            "subcategory":"Office Equipment",
            "type":"Manufacturing & Wholesale Goods"
        }
    ],
    "sg:phone":"+1 954 942 3312",
    "sg:postcode":"33304",
    "sg:province":"FL",
    "sg:tags":[
        "machine",
        "duplicating",
        "copying"
    ],
    "wof:name":"Sunset Equipment",
    "wof:placetype":"venue"
},
  "geometry": {"coordinates":[-80.141441,26.136583],"type":"Point"}
}