{
  "type": "Feature",
  "properties": {
    "addr:full":"6778 Lantana Rd Lake Worth FL 33467",
    "addr:housenumber":"6778",
    "addr:postcode":"33467",
    "addr:street":"Lantana Rd",
    "iso:country":"US",
    "sg:address":"6778 Lantana Rd",
    "sg:city":"Lake Worth",
    "sg:classifiers":[
        {
            "category":"Wholesale",
            "subcategory":"Machinery & Supplies",
            "type":"Manufacturing & Wholesale Goods"
        },
        {
            "category":"Home & Garden",
            "subcategory":"Hardware",
            "type":"Retail Goods"
        }
    ],
    "sg:phone":"+1 561 433 9976",
    "sg:postcode":"33467",
    "sg:province":"FL",
    "sg:tags":[
        "distributor",
        "aircraft"
    ],
    "wof:name":"Hardware & Metal Specialties",
    "wof:placetype":"venue"
},
  "geometry": {"coordinates":[-80.150059,26.589615],"type":"Point"}
}