{
  "type": "Feature",
  "properties": {
    "iso:country":"US",
    "sg:address":"2480 Citrus Blvd",
    "sg:city":"Leesburg",
    "sg:classifiers":[
        {
            "category":"Restaurant",
            "type":"Food & Drink"
        }
    ],
    "sg:phone":"+1 352 323 8667",
    "sg:postcode":"34748",
    "sg:province":"FL",
    "wof:name":"Denny's",
    "wof:placetype":"venue"
},
  "geometry": {"coordinates":[-81.89760699999999,28.844085],"type":"Point"}
}