{
  "type": "Feature",
  "properties": {
    "iso:country":"US",
    "sg:address":"24650 SW 129th Ave",
    "sg:city":"Homestead",
    "sg:classifiers":[
        {
            "category":"Building & Trades",
            "subcategory":"Construction",
            "type":"Services"
        }
    ],
    "sg:phone":"+1 305 258 0433",
    "sg:postcode":"33032",
    "sg:province":"FL",
    "sg:tags":[
        "tile",
        "dealer",
        "contractor"
    ],
    "wof:name":"Miami Tile Installation Inc",
    "wof:placetype":"venue"
},
  "geometry": {"coordinates":[-80.400634,25.539193],"type":"Point"}
}