{
  "type": "Feature",
  "properties": {
    "iso:country":"US",
    "sg:address":"110 E Atlantic Ave",
    "sg:city":"Delray Beach",
    "sg:classifiers":[
        {
            "category":"Professional",
            "subcategory":"Accounting & Tax Preparation",
            "type":"Services"
        }
    ],
    "sg:phone":"+1 561 819 0990",
    "sg:postcode":"33444",
    "sg:province":"FL",
    "sg:tags":[
        "accountant"
    ],
    "wof:name":"Professional Business Sltns",
    "wof:placetype":"venue"
},
  "geometry": {"coordinates":[-80.071175,26.461568],"type":"Point"}
}