{
  "type": "Feature",
  "properties": {
    "iso:country":"US",
    "sg:address":"460 Harlan Ave",
    "sg:city":"Lake Helen",
    "sg:classifiers":[
        {
            "category":"Wholesale",
            "subcategory":"Durable Goods & Equipment",
            "type":"Manufacturing & Wholesale Goods"
        }
    ],
    "sg:phone":"+1 386 228 0715",
    "sg:postcode":"32744",
    "sg:province":"FL",
    "sg:tags":[
        "representative",
        "manufacturer"
    ],
    "wof:name":"Pan Agra Intl Inc",
    "wof:placetype":"venue"
},
  "geometry": {"coordinates":[-81.23898699999999,28.985678],"type":"Point"}
}