{
  "type": "Feature",
  "properties": {
    "iso:country":"US",
    "sg:address":"3715 Forest Ct",
    "sg:city":"West Palm Beach",
    "sg:classifiers":[
        {
            "category":"Shopping",
            "subcategory":"Florist",
            "type":"Retail Goods"
        }
    ],
    "sg:phone":"+1 561 248 9400",
    "sg:postcode":"33405",
    "sg:province":"FL",
    "wof:name":"Mary's Orchids & Exotic Plants",
    "wof:placetype":"venue"
},
  "geometry": {"coordinates":[-80.067672,26.656153],"type":"Point"}
}