{
  "type": "Feature",
  "properties": {
    "addr:full":"8821 NW 13th St Hollywood FL 33024",
    "addr:housenumber":"8821",
    "addr:postcode":"33024",
    "addr:street":"Nw 13Th St",
    "iso:country":"US",
    "sg:address":"8821 NW 13th St",
    "sg:city":"Hollywood",
    "sg:classifiers":[
        {
            "category":"Building & Trades",
            "subcategory":"Landscaping Services",
            "type":"Services"
        }
    ],
    "sg:phone":"+1 954 432 4928",
    "sg:postcode":"33024",
    "sg:province":"FL",
    "wof:name":"Marks Lawn Service",
    "wof:placetype":"venue"
},
  "geometry": {"coordinates":[-80.262467,26.019679],"type":"Point"}
}