{
  "type": "Feature",
  "properties": {
    "iso:country":"US",
    "sg:address":"29 E 44th St",
    "sg:city":"Hialeah",
    "sg:classifiers":[
        {
            "category":"Food & Beverages",
            "subcategory":"Groceries & Convenience Stores",
            "type":"Retail Goods"
        },
        {
            "category":"Professional",
            "subcategory":"Business Services",
            "type":"Services"
        },
        {
            "category":"Food & Beverages",
            "subcategory":"Meat & Fish",
            "type":"Retail Goods"
        }
    ],
    "sg:phone":"+1 305 558 2672",
    "sg:postcode":"33013",
    "sg:province":"FL",
    "sg:tags":[
        "shop",
        "butchering",
        "market"
    ],
    "wof:name":"Carniceria La Matancera",
    "wof:placetype":"venue"
},
  "geometry": {"coordinates":[-80.282284,25.862427],"type":"Point"}
}