{
  "type": "Feature",
  "properties": {
    "addr:full":"1800 E Canal St S Belle Glade FL 33430",
    "addr:housenumber":"1800",
    "addr:postcode":"33430",
    "addr:street":"E Canal St S Belle Glade",
    "iso:country":"US",
    "sg:address":"1800 E Canal St S",
    "sg:city":"Belle Glade",
    "sg:classifiers":[
        {
            "category":"Food & Beverages",
            "subcategory":"Groceries & Convenience Stores",
            "type":"Retail Goods"
        }
    ],
    "sg:phone":"+1 561 992 7801",
    "sg:postcode":"33430",
    "sg:province":"FL",
    "wof:name":"Country Store",
    "wof:placetype":"venue"
},
  "geometry": {"coordinates":[-80.651056,26.677743],"type":"Point"}
}