{
  "type": "Feature",
  "properties": {
    "iso:country":"US",
    "sg:address":"1296 Woodfield Oaks Dr",
    "sg:city":"Apopka",
    "sg:classifiers":[
        {
            "category":"Banks & Credit Unions",
            "subcategory":"Financial Services",
            "type":"Services"
        }
    ],
    "sg:phone":"+1 407 886 4716",
    "sg:postcode":"32703",
    "sg:province":"FL",
    "sg:tags":[
        "investor"
    ],
    "wof:name":"Success Investment Club",
    "wof:placetype":"venue"
},
  "geometry": {"coordinates":[-81.487385,28.644241],"type":"Point"}
}