{
  "type": "Feature",
  "properties": {
    "iso:country":"US",
    "sg:address":"6796 Forest Hill Blvd",
    "sg:city":"Greenacres",
    "sg:classifiers":[
        {
            "category":"Shopping",
            "subcategory":"Gifts & Souvenirs",
            "type":"Retail Goods"
        }
    ],
    "sg:phone":"+1 561 967 9891",
    "sg:postcode":"33413",
    "sg:province":"FL",
    "sg:tags":[
        "shop"
    ],
    "wof:name":"Annie's Hallmark Shop",
    "wof:placetype":"venue"
},
  "geometry": {"coordinates":[-80.149198,26.651083],"type":"Point"}
}