{
  "type": "Feature",
  "properties": {
    "iso:country":"US",
    "sg:address":"2304 Notley Ct",
    "sg:city":"Tallahassee",
    "sg:classifiers":[
        {
            "category":"Manufacturing",
            "subcategory":"Lumber",
            "type":"Manufacturing & Wholesale Goods"
        }
    ],
    "sg:phone":"+1 850 668 2834",
    "sg:postcode":"32309",
    "sg:province":"FL",
    "sg:tags":[
        "operation",
        "timber",
        "tract"
    ],
    "wof:name":"Dampier Farms Inc",
    "wof:placetype":"venue"
},
  "geometry": {"coordinates":[-84.227599,30.516236],"type":"Point"}
}