{
  "type": "Feature",
  "properties": {
    "iso:country":"US",
    "sg:address":"501 NW Archer Ave",
    "sg:city":"Port Saint Lucie",
    "sg:classifiers":[
        {
            "category":"Retail",
            "subcategory":"Laundry & Dry Cleaning",
            "type":"Services"
        }
    ],
    "sg:phone":"+1 772 879 6355",
    "sg:postcode":"34983",
    "sg:province":"FL",
    "wof:name":"Ultra Dry Carpet & Uphl Clg",
    "wof:placetype":"venue"
},
  "geometry": {"coordinates":[-80.364099,27.337245],"type":"Point"}
}