{
  "type": "Feature",
  "properties": {
    "iso:country":"US",
    "sg:address":"7219 NW 43rd St",
    "sg:city":"Miami",
    "sg:classifiers":[
        {
            "category":"Manufacturing",
            "subcategory":"Textiles",
            "type":"Manufacturing & Wholesale Goods"
        }
    ],
    "sg:phone":"+1 305 592 7404",
    "sg:postcode":"33166",
    "sg:province":"FL",
    "sg:tags":[
        "textiles-manufacturers"
    ],
    "wof:name":"Good Chance Textile",
    "wof:placetype":"venue"
},
  "geometry": {"coordinates":[-80.313812,25.813429],"type":"Point"}
}