{
  "type": "Feature",
  "properties": {
    "addr:full":"307 Kelly Rd Niceville FL 32578",
    "addr:housenumber":"307",
    "addr:postcode":"32578",
    "addr:street":"Kelly Rd",
    "iso:country":"US",
    "sg:address":"307 Kelly Rd",
    "sg:city":"Niceville",
    "sg:classifiers":[
        {
            "category":"Restaurant",
            "type":"Food & Drink"
        }
    ],
    "sg:phone":"+1 850 729 1636",
    "sg:postcode":"32578",
    "sg:province":"FL",
    "sg:tags":[
        "eating"
    ],
    "wof:name":"Doris' Restaurant",
    "wof:placetype":"venue"
},
  "geometry": {"coordinates":[-86.50324500000001,30.520734],"type":"Point"}
}