{
  "type": "Feature",
  "properties": {
    "iso:country":"US",
    "sg:address":"645 NW 5th Ave",
    "sg:city":"Miami",
    "sg:classifiers":[
        {
            "category":"Food & Beverages",
            "subcategory":"Groceries & Convenience Stores",
            "type":"Retail Goods"
        }
    ],
    "sg:phone":"+1 305 379 0237",
    "sg:postcode":"33136",
    "sg:province":"FL",
    "wof:name":"M and N Supermarket",
    "wof:placetype":"venue"
},
  "geometry": {"coordinates":[-80.203102,25.780001],"type":"Point"}
}