{
  "type": "Feature",
  "properties": {
    "iso:country":"US",
    "sg:address":"1551 Norfolk Ave",
    "sg:city":"Winter Park",
    "sg:classifiers":[
        {
            "category":"Building & Trades",
            "subcategory":"Construction",
            "type":"Services"
        }
    ],
    "sg:phone":"+1 407 599 2826",
    "sg:postcode":"32789",
    "sg:province":"FL",
    "sg:tags":[
        "house"
    ],
    "wof:name":"Island Breeze Builders Inc",
    "wof:placetype":"venue"
},
  "geometry": {"coordinates":[-81.365522,28.582826],"type":"Point"}
}