{
  "type": "Feature",
  "properties": {
    "addr:full":"1651 Dunlap Dr Deltona FL 32725",
    "addr:housenumber":"1651",
    "addr:postcode":"32725",
    "addr:street":"Dunlap Dr",
    "iso:country":"US",
    "sg:address":"1651 Dunlap Dr",
    "sg:city":"Deltona",
    "sg:classifiers":[
        {
            "category":"Building & Trades",
            "subcategory":"Construction",
            "type":"Services"
        }
    ],
    "sg:phone":"+1 386 532 7666",
    "sg:postcode":"32725",
    "sg:province":"FL",
    "sg:tags":[
        "residential"
    ],
    "wof:name":"S & M Handy Work",
    "wof:placetype":"venue"
},
  "geometry": {"coordinates":[-81.227582,28.908852],"type":"Point"}
}