{
  "type": "Feature",
  "properties": {
    "addr:full":"1390 SW 26th Ter Fort Lauderdale FL 33312",
    "addr:housenumber":"1390",
    "addr:postcode":"33312",
    "addr:street":"Sw 26Th Ter",
    "iso:country":"US",
    "sg:address":"1390 SW 26th Ter",
    "sg:city":"Fort Lauderdale",
    "sg:classifiers":[
        {
            "category":"Retail",
            "subcategory":"Repair Shop",
            "type":"Services"
        }
    ],
    "sg:phone":"+1 954 327 0112",
    "sg:postcode":"33312",
    "sg:province":"FL",
    "wof:name":"Cleaning Unlimited Inc",
    "wof:placetype":"venue"
},
  "geometry": {"coordinates":[-80.177026,26.103801],"type":"Point"}
}