{
  "type": "Feature",
  "properties": {
    "iso:country":"US",
    "sg:address":"3091 NW 62nd St",
    "sg:city":"Fort Lauderdale",
    "sg:phone":"+1 954 975 3230",
    "sg:postcode":"33309",
    "sg:province":"FL",
    "sg:tags":[
        "product",
        "petroleum"
    ],
    "wof:name":"Rosa's Plaza",
    "wof:placetype":"venue"
},
  "geometry": {"coordinates":[-80.18581,26.202589],"type":"Point"}
}