{
  "type": "Feature",
  "properties": {
    "addr:full":"2326 Everest Pkwy Cape Coral FL 33904",
    "addr:housenumber":"2326",
    "addr:postcode":"33904",
    "addr:street":"Everest Pkwy",
    "iso:country":"US",
    "sg:address":"2326 Everest Pkwy",
    "sg:city":"Cape Coral",
    "sg:classifiers":[
        {
            "category":"Building & Trades",
            "subcategory":"Construction",
            "type":"Services"
        }
    ],
    "sg:phone":"+1 239 573 9963",
    "sg:postcode":"33904",
    "sg:province":"FL",
    "sg:tags":[
        "siding",
        "contractor"
    ],
    "wof:name":"Quality Siding",
    "wof:placetype":"venue"
},
  "geometry": {"coordinates":[-81.921331,26.606772],"type":"Point"}
}