{
  "type": "Feature",
  "properties": {
    "addr:full":"2810 SW 95th Ave Miami FL 33165",
    "addr:housenumber":"2810",
    "addr:postcode":"33165",
    "addr:street":"Sw 95Th Ave",
    "iso:country":"US",
    "sg:address":"2810 SW 95th Ave",
    "sg:city":"Miami",
    "sg:classifiers":[
        {
            "category":"Professional",
            "subcategory":"Computer Services",
            "type":"Services"
        }
    ],
    "sg:phone":"+1 305 220 8003",
    "sg:postcode":"33165",
    "sg:province":"FL",
    "sg:tags":[
        "related"
    ],
    "wof:name":"Urban Csi Inc",
    "wof:placetype":"venue"
},
  "geometry": {"coordinates":[-80.349428,25.743542],"type":"Point"}
}