{
  "type": "Feature",
  "properties": {
    "iso:country":"US",
    "sg:address":"11450 NW 34th St",
    "sg:city":"Doral",
    "sg:classifiers":[
        {
            "category":"Freight",
            "type":"Transportation"
        }
    ],
    "sg:phone":"+1 305 477 2300",
    "sg:postcode":"33178",
    "sg:province":"FL",
    "sg:tags":[
        "operator",
        "local",
        "trucking"
    ],
    "sg:website":"www.cocopack.com",
    "wof:name":"Coco's International Packers",
    "wof:placetype":"venue"
},
  "geometry": {"coordinates":[-80.323717,25.805827],"type":"Point"}
}