{
  "type": "Feature",
  "properties": {
    "iso:country":"US",
    "sg:address":"2034 Mahan Dr",
    "sg:city":"Tallahassee",
    "sg:classifiers":[
        {
            "category":"Organizations",
            "subcategory":"Non-profit Organization",
            "type":"Services"
        }
    ],
    "sg:phone":"+1 850 878 0143",
    "sg:postcode":"32308",
    "sg:province":"FL",
    "sg:tags":[
        "disability"
    ],
    "sg:website":"www.sunrisegroup.com",
    "wof:name":"Sunrise Community Inc",
    "wof:placetype":"venue"
},
  "geometry": {"coordinates":[-84.24938899999999,30.452354],"type":"Point"}
}