{
  "type": "Feature",
  "properties": {
    "iso:country":"US",
    "sg:address":"4590 Babcock St NE",
    "sg:city":"Palm Bay",
    "sg:classifiers":[
        {
            "category":"Retail",
            "subcategory":"Auto Repair",
            "type":"Services"
        }
    ],
    "sg:phone":"+1 321 951 2247",
    "sg:postcode":"32905",
    "sg:province":"FL",
    "sg:tags":[
        "repairing",
        "automobile"
    ],
    "wof:name":"Price's Auto Ctr",
    "wof:placetype":"venue"
},
  "geometry": {"coordinates":[-80.62174,28.040931],"type":"Point"}
}