{
  "type": "Feature",
  "properties": {
    "iso:country":"US",
    "sg:address":"1160 E Industrial Dr",
    "sg:city":"Orange City",
    "sg:classifiers":[
        {
            "category":"Retail",
            "subcategory":"Auto Repair",
            "type":"Services"
        }
    ],
    "sg:phone":"+1 386 774 9777",
    "sg:postcode":"32763",
    "sg:province":"FL",
    "wof:name":"All Done Auto Repair Inc",
    "wof:placetype":"venue"
},
  "geometry": {"coordinates":[-81.29540299999999,28.9359],"type":"Point"}
}