{
  "type": "Feature",
  "properties": {
    "iso:country":"US",
    "sg:address":"2421 Crystal Dr",
    "sg:city":"Fort Myers",
    "sg:classifiers":[
        {
            "category":"Professional",
            "subcategory":"Lawyer & Legal Services",
            "type":"Services"
        }
    ],
    "sg:phone":"+1 239 277 7726",
    "sg:postcode":"33907",
    "sg:province":"FL",
    "sg:tags":[
        "notary"
    ],
    "wof:name":"Bollinger's Printing",
    "wof:placetype":"venue"
},
  "geometry": {"coordinates":[-81.858902,26.564501],"type":"Point"}
}