{
  "type": "Feature",
  "properties": {
    "iso:country":"US",
    "sg:address":"8150 SW 8th St",
    "sg:city":"Miami",
    "sg:classifiers":[
        {
            "category":"Building & Trades",
            "subcategory":"Locksmith",
            "type":"Services"
        }
    ],
    "sg:phone":"+1 305 357 4920",
    "sg:postcode":"33144",
    "sg:province":"FL",
    "sg:tags":[
        "key"
    ],
    "wof:name":"1 24 Hour 7 Day Emerg Locksmith",
    "wof:placetype":"venue"
},
  "geometry": {"coordinates":[-80.327144,25.761953],"type":"Point"}
}