{
  "type": "Feature",
  "properties": {
    "iso:country":"US",
    "sg:address":"811 NW 143rd St",
    "sg:city":"Miami",
    "sg:classifiers":[
        {
            "category":"Utilities",
            "subcategory":"Refuse",
            "type":"Services"
        }
    ],
    "sg:phone":"+1 305 953 8988",
    "sg:postcode":"33168",
    "sg:province":"FL",
    "sg:tags":[
        "system"
    ],
    "wof:name":"Waste Services USA Inc",
    "wof:placetype":"venue"
},
  "geometry": {"coordinates":[-80.212288,25.905611],"type":"Point"}
}