{
  "type": "Feature",
  "properties": {
    "iso:country":"US",
    "sg:address":"8655 SW 57th Pl",
    "sg:city":"Fort Lauderdale",
    "sg:classifiers":[
        {
            "category":"Freight",
            "type":"Transportation"
        }
    ],
    "sg:phone":"+1 954 434 5524",
    "sg:postcode":"33328",
    "sg:province":"FL",
    "sg:tags":[
        "general"
    ],
    "wof:name":"Alfa Warehouses of Broward",
    "wof:placetype":"venue"
},
  "geometry": {"coordinates":[-80.26074800000001,26.048492],"type":"Point"}
}