{
  "type": "Feature",
  "properties": {
    "iso:country":"US",
    "sg:address":"484 SW Voltair Ter",
    "sg:city":"Port St Lucie",
    "sg:classifiers":[
        {
            "category":"Building & Trades",
            "subcategory":"Plumbing",
            "type":"Services"
        }
    ],
    "sg:phone":"+1 772 871 5893",
    "sg:postcode":"34984",
    "sg:province":"FL",
    "sg:tags":[
        "plumbing",
        "contractor"
    ],
    "wof:name":"Leyva Plumbing Svc",
    "wof:placetype":"venue"
},
  "geometry": {"coordinates":[-80.363078,27.283071],"type":"Point"}
}