{
  "type": "Feature",
  "properties": {
    "addr:full":"2455 Will Hardee Rd Fernandina Beach FL 32034",
    "addr:housenumber":"2455",
    "addr:postcode":"32034",
    "addr:street":"Will Hardee Rd",
    "iso:country":"US",
    "sg:address":"2455 Will Hardee Rd",
    "sg:city":"Fernandina Beach",
    "sg:classifiers":[
        {
            "category":"Building & Trades",
            "subcategory":"Construction",
            "type":"Services"
        }
    ],
    "sg:phone":"+1 904 277 3018",
    "sg:postcode":"32034",
    "sg:province":"FL",
    "sg:tags":[
        "house"
    ],
    "wof:name":"Island Exteriors",
    "wof:placetype":"venue"
},
  "geometry": {"coordinates":[-81.44834,30.633803],"type":"Point"}
}