{
  "type": "Feature",
  "properties": {
    "iso:country":"US",
    "sg:address":"4959 W Sand Lake Rd",
    "sg:city":"Orlando",
    "sg:classifiers":[
        {
            "category":"Professional",
            "type":"Services"
        }
    ],
    "sg:phone":"+1 407 355 9830",
    "sg:postcode":"32819",
    "sg:province":"FL",
    "sg:tags":[
        "establishment"
    ],
    "wof:name":"Richcom",
    "wof:placetype":"venue"
},
  "geometry": {"coordinates":[-81.446038,28.450062],"type":"Point"}
}