{
  "type": "Feature",
  "properties": {
    "iso:country":"US",
    "sg:address":"4949 NW 82nd Ter",
    "sg:city":"Pompano Beach",
    "sg:classifiers":[
        {
            "category":"Shopping",
            "subcategory":"Clothing, Apparel, & Fashions",
            "type":"Retail Goods"
        }
    ],
    "sg:phone":"+1 954 344 2503",
    "sg:postcode":"33067",
    "sg:province":"FL",
    "sg:tags":[
        "accessory"
    ],
    "wof:name":"Susan Docktor & Associates",
    "wof:placetype":"venue"
},
  "geometry": {"coordinates":[-80.236411,26.292047],"type":"Point"}
}