{
  "type": "Feature",
  "properties": {
    "addr:full":"3711 Eagle Ridge Dr Jacksonville FL 32224",
    "addr:housenumber":"3711",
    "addr:postcode":"32224",
    "addr:street":"Eagle Ridge Dr",
    "iso:country":"US",
    "sg:address":"3711 Eagle Ridge Dr",
    "sg:city":"Jacksonville",
    "sg:classifiers":[
        {
            "category":"Professional",
            "subcategory":"Management & Consulting",
            "type":"Services"
        }
    ],
    "sg:phone":"+1 904 223 5882",
    "sg:postcode":"32224",
    "sg:province":"FL",
    "sg:tags":[
        "public",
        "relations"
    ],
    "wof:name":"Rpt Sports Inc",
    "wof:placetype":"venue"
},
  "geometry": {"coordinates":[-81.45708,30.277105],"type":"Point"}
}