{
  "type": "Feature",
  "properties": {
    "iso:country":"US",
    "sg:address":"21234 Olean Blvd",
    "sg:city":"Port Charlotte",
    "sg:classifiers":[
        {
            "category":"Personal",
            "subcategory":"Barber",
            "type":"Services"
        }
    ],
    "sg:phone":"+1 941 627 4411",
    "sg:postcode":"33952",
    "sg:province":"FL",
    "wof:name":"Central Barber Shop",
    "wof:placetype":"venue"
},
  "geometry": {"coordinates":[-82.100891,26.985932],"type":"Point"}
}