{
  "type": "Feature",
  "properties": {
    "iso:country":"US",
    "sg:address":"800 West Cypress Creek Road Suite 528",
    "sg:city":"Fort Lauderdale",
    "sg:classifiers":[
        {
            "category":"Professional",
            "subcategory":"Computer Services",
            "type":"Services"
        }
    ],
    "sg:phone":"+1 954 862 3932",
    "sg:postcode":"33309",
    "sg:province":"FL",
    "sg:tags":[
        "cloud-server",
        "dedicate-server",
        "bare-metal-cloud"
    ],
    "sg:website":"http://newservers.com",
    "wof:name":"NewServers",
    "wof:placetype":"venue"
},
  "geometry": {"coordinates":[-80.15304999999999,26.203289],"type":"Point"}
}