{
  "type": "Feature",
  "properties": {
    "addr:full":"5402 Pioneer Park Blvd Tampa FL 33634",
    "addr:housenumber":"5402",
    "addr:postcode":"33634",
    "addr:street":"Pioneer Park Blvd",
    "iso:country":"US",
    "sg:address":"5402 Pioneer Park Blvd",
    "sg:city":"Tampa",
    "sg:classifiers":[
        {
            "category":"Wholesale",
            "subcategory":"Machinery & Supplies",
            "type":"Manufacturing & Wholesale Goods"
        }
    ],
    "sg:phone":"+1 813 882 3168",
    "sg:postcode":"33634",
    "sg:province":"FL",
    "sg:tags":[
        "marking"
    ],
    "wof:name":"Flordia Transcor",
    "wof:placetype":"venue"
},
  "geometry": {"coordinates":[-82.53778,28.013599],"type":"Point"}
}