{
  "type": "Feature",
  "properties": {
    "iso:country":"US",
    "sg:address":"1454 Bay Harbor Dr",
    "sg:city":"Palm Harbor",
    "sg:classifiers":[
        {
            "category":"Autos & Motor Vehicles",
            "subcategory":"Fuel & Gas Station",
            "type":"Retail Goods"
        }
    ],
    "sg:phone":"+1 727 510 0559",
    "sg:postcode":"34685",
    "sg:province":"FL",
    "sg:tags":[
        "station",
        "gasoline"
    ],
    "wof:name":"Ideal Mobil Detailing",
    "wof:placetype":"venue"
},
  "geometry": {"coordinates":[-82.70796199999999,28.072123],"type":"Point"}
}