{
  "type": "Feature",
  "properties": {
    "iso:country":"US",
    "sg:address":"115 Orchard Ridge Ln",
    "sg:city":"Boca Raton",
    "sg:classifiers":[
        {
            "category":"Professional",
            "subcategory":"Business Services",
            "type":"Services"
        }
    ],
    "sg:phone":"+1 561 392 6128",
    "sg:postcode":"33431",
    "sg:province":"FL",
    "wof:name":"Commercial Funding Sources",
    "wof:placetype":"venue"
},
  "geometry": {"coordinates":[-80.133044,26.371041],"type":"Point"}
}