{
  "type": "Feature",
  "properties": {
    "iso:country":"US",
    "sg:address":"8490 SW 86th Ct",
    "sg:city":"Miami",
    "sg:classifiers":[
        {
            "category":"Real Estate",
            "subcategory":"Real Estate Operator",
            "type":"Services"
        }
    ],
    "sg:phone":"+1 305 598 3602",
    "sg:postcode":"33143",
    "sg:province":"FL",
    "sg:tags":[
        "building",
        "nonresidential"
    ],
    "wof:name":"H E T Inc",
    "wof:placetype":"venue"
},
  "geometry": {"coordinates":[-80.33313699999999,25.689167],"type":"Point"}
}