{
  "type": "Feature",
  "properties": {
    "iso:country":"US",
    "sg:address":"15510 SW Trail Dr",
    "sg:city":"Indiantown",
    "sg:classifiers":[
        {
            "category":"Restaurant",
            "type":"Food & Drink"
        }
    ],
    "sg:phone":"+1 772 597 5600",
    "sg:postcode":"34956",
    "sg:province":"FL",
    "wof:name":"Dee-Stefanos Restrnt & Pizzari",
    "wof:placetype":"venue"
},
  "geometry": {"coordinates":[-80.461539,27.018993],"type":"Point"}
}