{
  "type": "Feature",
  "properties": {
    "iso:country":"US",
    "sg:address":"6220 All American Blvd",
    "sg:city":"Orlando",
    "sg:classifiers":[
        {
            "category":"Retail",
            "subcategory":"Repair Shop",
            "type":"Services"
        }
    ],
    "sg:phone":"+1 407 297 1527",
    "sg:postcode":"32810",
    "sg:province":"FL",
    "sg:tags":[
        "scooter",
        "motorcycle",
        "motor"
    ],
    "wof:name":"Wig's Small Engine Svc",
    "wof:placetype":"venue"
},
  "geometry": {"coordinates":[-81.419149,28.614924],"type":"Point"}
}