{
  "type": "Feature",
  "properties": {
    "iso:country":"US",
    "sg:address":"4749 Grand Blvd",
    "sg:city":"New Port Richey",
    "sg:classifiers":[
        {
            "category":"Health Services",
            "subcategory":"Doctor",
            "type":"Services"
        }
    ],
    "sg:phone":"+1 727 841 8818",
    "sg:postcode":"34652",
    "sg:province":"FL",
    "sg:tags":[
        "clinic"
    ],
    "wof:name":"Da Vita Inc",
    "wof:placetype":"venue"
},
  "geometry": {"coordinates":[-82.72320499999999,28.227941],"type":"Point"}
}