{
  "type": "Feature",
  "properties": {
    "iso:country":"US",
    "sg:address":"1333 W Mango St",
    "sg:city":"Lantana",
    "sg:classifiers":[
        {
            "category":"Building & Trades",
            "subcategory":"Landscaping Services",
            "type":"Services"
        }
    ],
    "sg:phone":"+1 561 644 6165",
    "sg:postcode":"33462",
    "sg:province":"FL",
    "sg:tags":[
        "landscape",
        "contractor"
    ],
    "wof:name":"Progress Landscape Inc",
    "wof:placetype":"venue"
},
  "geometry": {"coordinates":[-80.066041,26.584056],"type":"Point"}
}