{
  "type": "Feature",
  "properties": {
    "addr:full":"7240 US Hwy 1 Port Saint Lucie FL 34952",
    "addr:housenumber":"7240",
    "addr:postcode":"34952",
    "addr:street":"Us Hwy 1",
    "iso:country":"US",
    "sg:address":"7240 US Hwy 1",
    "sg:city":"Port Saint Lucie",
    "sg:classifiers":[
        {
            "category":"Restaurant",
            "type":"Food & Drink"
        }
    ],
    "sg:phone":"+1 772 340 3431",
    "sg:postcode":"34952",
    "sg:province":"FL",
    "sg:tags":[
        "eating"
    ],
    "wof:name":"Pappa Louies Inc",
    "wof:placetype":"venue"
},
  "geometry": {"coordinates":[-80.32289,27.33034],"type":"Point"}
}