{
  "type": "Feature",
  "properties": {
    "iso:country":"US",
    "sg:address":"9021 W Sunrise Blvd",
    "sg:city":"Fort Lauderdale",
    "sg:classifiers":[
        {
            "category":"Shopping",
            "subcategory":"Gifts & Souvenirs",
            "type":"Retail Goods"
        }
    ],
    "sg:phone":"+1 954 382 9152",
    "sg:postcode":"33322",
    "sg:province":"FL",
    "wof:name":"Sensuous Expressions",
    "wof:placetype":"venue"
},
  "geometry": {"coordinates":[-80.269493,26.146716],"type":"Point"}
}