{
  "type": "Feature",
  "properties": {
    "iso:country":"US",
    "sg:address":"4500 Lipscomb St NE",
    "sg:city":"Palm Bay",
    "sg:classifiers":[
        {
            "category":"Retail",
            "subcategory":"Repair Shop",
            "type":"Services"
        }
    ],
    "sg:phone":"+1 321 727 7782",
    "sg:postcode":"32905",
    "sg:province":"FL",
    "sg:tags":[
        "refinishing",
        "furniture"
    ],
    "wof:name":"Disar Furniture Service Inc",
    "wof:placetype":"venue"
},
  "geometry": {"coordinates":[-80.60502099999999,28.051192],"type":"Point"}
}