{
  "type": "Feature",
  "properties": {
    "iso:country":"US",
    "sg:address":"1905 Harlock Rd",
    "sg:city":"Melbourne",
    "sg:classifiers":[
        {
            "category":"Manufacturing",
            "subcategory":"Building Materials",
            "type":"Manufacturing & Wholesale Goods"
        }
    ],
    "sg:phone":"+1 321 253 1081",
    "sg:postcode":"32934",
    "sg:province":"FL",
    "sg:tags":[
        "mfg"
    ],
    "wof:name":"Keith Williams Woodworks",
    "wof:placetype":"venue"
},
  "geometry": {"coordinates":[-80.704459,28.136527],"type":"Point"}
}