{
  "type": "Feature",
  "properties": {
    "iso:country":"US",
    "sg:address":"14744 SW 56th St",
    "sg:city":"Miami",
    "sg:classifiers":[
        {
            "category":"Professional",
            "subcategory":"Employment Agencies",
            "type":"Services"
        }
    ],
    "sg:phone":"+1 305 383 2433",
    "sg:postcode":"33185",
    "sg:province":"FL",
    "sg:tags":[
        "opportunity"
    ],
    "wof:name":"El Parador Food By The Pound",
    "wof:placetype":"venue"
},
  "geometry": {"coordinates":[-80.431681,25.713879],"type":"Point"}
}