{
  "type": "Feature",
  "properties": {
    "iso:country":"US",
    "sg:address":"7361 Rush Ct",
    "sg:city":"Orlando",
    "sg:classifiers":[
        {
            "category":"Banks & Credit Unions",
            "subcategory":"Bank",
            "type":"Services"
        }
    ],
    "sg:phone":"+1 407 298 3552",
    "sg:postcode":"32818",
    "sg:province":"FL",
    "sg:tags":[
        "broker",
        "business",
        "mortgage"
    ],
    "wof:name":"Skyebran Mortgage Company",
    "wof:placetype":"venue"
},
  "geometry": {"coordinates":[-81.490663,28.560854],"type":"Point"}
}