{
  "type": "Feature",
  "properties": {
    "iso:country":"US",
    "sg:address":"1900 Howell Branch Rd",
    "sg:city":"Winter Park",
    "sg:classifiers":[
        {
            "category":"Organizations",
            "subcategory":"Membership Organization",
            "type":"Services"
        }
    ],
    "sg:phone":"+1 407 682 5425",
    "sg:postcode":"32792",
    "sg:province":"FL",
    "sg:tags":[
        "athletic"
    ],
    "wof:name":"Central Florida Kraze",
    "wof:placetype":"venue"
},
  "geometry": {"coordinates":[-81.32623100000001,28.625061],"type":"Point"}
}