{
  "type": "Feature",
  "properties": {
    "iso:country":"US",
    "sg:address":"2111 W Swann Ave",
    "sg:city":"Tampa",
    "sg:classifiers":[
        {
            "category":"Health Services",
            "subcategory":"Health Practitioner",
            "type":"Services"
        }
    ],
    "sg:phone":"+1 813 250 1208",
    "sg:postcode":"33606",
    "sg:province":"FL",
    "sg:tags":[
        "therapist",
        "physical"
    ],
    "wof:name":"Advanced Rehabilitation",
    "wof:placetype":"venue"
},
  "geometry": {"coordinates":[-82.481055,27.937371],"type":"Point"}
}