{
  "type": "Feature",
  "properties": {
    "iso:country":"US",
    "sg:address":"20286 NW 2nd Ave",
    "sg:city":"Miami",
    "sg:classifiers":[
        {
            "category":"Autos & Motor Vehicles",
            "subcategory":"Auto Supplies",
            "type":"Retail Goods"
        }
    ],
    "sg:phone":"+1 786 547 6658",
    "sg:postcode":"33169",
    "sg:province":"FL",
    "sg:tags":[
        "glass",
        "window",
        "coating",
        "tinting"
    ],
    "wof:name":"USA Glare Control Corp",
    "wof:placetype":"venue"
},
  "geometry": {"coordinates":[-80.20587399999999,25.961345],"type":"Point"}
}