{
  "type": "Feature",
  "properties": {
    "iso:country":"US",
    "sg:address":"350 W Haines Blvd",
    "sg:city":"Lake Alfred",
    "sg:classifiers":[
        {
            "category":"Social Services",
            "subcategory":"Adult Care",
            "type":"Services"
        }
    ],
    "sg:phone":"+1 863 956 8831",
    "sg:postcode":"33850",
    "sg:province":"FL",
    "sg:tags":[
        "home",
        "residential"
    ],
    "wof:name":"Tlc II Retirement Resident",
    "wof:placetype":"venue"
},
  "geometry": {"coordinates":[-81.733316,28.091748],"type":"Point"}
}