{
  "type": "Feature",
  "properties": {
    "iso:country":"US",
    "sg:address":"10035 SW 214th St",
    "sg:city":"Miami",
    "sg:classifiers":[
        {
            "category":"Shopping",
            "subcategory":"Discount & Variety Stores",
            "type":"Retail Goods"
        }
    ],
    "sg:phone":"+1 305 259 1844",
    "sg:postcode":"33189",
    "sg:province":"FL",
    "sg:tags":[
        "merchandise",
        "general"
    ],
    "wof:name":"Martha B Perez",
    "wof:placetype":"venue"
},
  "geometry": {"coordinates":[-80.353683,25.568183],"type":"Point"}
}