{
  "type": "Feature",
  "properties": {
    "iso:country":"US",
    "sg:address":"2604 Powers Ave",
    "sg:city":"Jacksonville",
    "sg:classifiers":[
        {
            "category":"Building & Trades",
            "subcategory":"Plumbing",
            "type":"Services"
        }
    ],
    "sg:phone":"+1 904 731 2122",
    "sg:postcode":"32207",
    "sg:province":"FL",
    "sg:tags":[
        "conditioning",
        "air",
        "system",
        "contractor"
    ],
    "wof:name":"Griffo Air Conditioning Inc",
    "wof:placetype":"venue"
},
  "geometry": {"coordinates":[-81.632161,30.268077],"type":"Point"}
}