{
  "type": "Feature",
  "properties": {
    "iso:country":"US",
    "sg:address":"1510 NW 3rd Ave",
    "sg:city":"Pompano Beach",
    "sg:classifiers":[
        {
            "category":"Building & Trades",
            "subcategory":"Construction",
            "type":"Services"
        }
    ],
    "sg:phone":"+1 954 943 4486",
    "sg:postcode":"33060",
    "sg:province":"FL",
    "sg:tags":[
        "concrete",
        "contractor"
    ],
    "wof:name":"Charlie Strong Concrete Svc",
    "wof:placetype":"venue"
},
  "geometry": {"coordinates":[-80.126983,26.246054],"type":"Point"}
}