{
  "type": "Feature",
  "properties": {
    "iso:country":"US",
    "sg:address":"1825 SW 125th Ct",
    "sg:city":"Miami",
    "sg:classifiers":[
        {
            "category":"Shopping",
            "subcategory":"Party Supplies",
            "type":"Retail Goods"
        },
        {
            "category":"Home & Garden",
            "subcategory":"Kitchen Supply",
            "type":"Retail Goods"
        },
        {
            "category":"Manufacturing",
            "subcategory":"Food",
            "type":"Manufacturing & Wholesale Goods"
        },
        {
            "category":"Home & Garden",
            "subcategory":"Furniture",
            "type":"Retail Goods"
        }
    ],
    "sg:phone":"+1 305 226 5401",
    "sg:postcode":"33175",
    "sg:province":"FL",
    "sg:tags":[
        "restaurant",
        "utensil",
        "supply-wholesale",
        "cabinet",
        "equipment",
        "cookware",
        "caterer",
        "equipment-household",
        "manufacturer"
    ],
    "wof:name":"Alquip Supply Company Inc",
    "wof:placetype":"venue"
},
  "geometry": {"coordinates":[-80.39843399999999,25.751124],"type":"Point"}
}