{
  "type": "Feature",
  "properties": {
    "addr:full":"11105 San Jose Blvd Jacksonville FL 32223",
    "addr:housenumber":"11105",
    "addr:postcode":"32223",
    "addr:street":"San Jose Blvd",
    "iso:country":"US",
    "sg:address":"11105 San Jose Blvd",
    "sg:city":"Jacksonville",
    "sg:classifiers":[
        {
            "category":"Home & Garden",
            "subcategory":"Furniture",
            "type":"Retail Goods"
        },
        {
            "category":"Home & Garden",
            "subcategory":"Home Furnishings",
            "type":"Retail Goods"
        },
        {
            "category":"Home & Garden",
            "subcategory":"Carpets & Floor Coverings",
            "type":"Retail Goods"
        }
    ],
    "sg:phone":"+1 904 352 2235",
    "sg:postcode":"32223",
    "sg:province":"FL",
    "sg:tags":[
        "bedroom",
        "set",
        "store",
        "bed",
        "mattress"
    ],
    "sg:website":"http://www.mattressfirm.com",
    "wof:name":"Mattress Firm",
    "wof:placetype":"venue"
},
  "geometry": {"coordinates":[-81.62820499999999,30.173852],"type":"Point"}
}