{
  "type": "Feature",
  "properties": {
    "iso:country":"US",
    "sg:address":"2444 Stein St",
    "sg:city":"Jacksonville",
    "sg:classifiers":[
        {
            "category":"Manufacturing",
            "subcategory":"Printing",
            "type":"Manufacturing & Wholesale Goods"
        }
    ],
    "sg:phone":"+1 904 731 7290",
    "sg:postcode":"32216",
    "sg:province":"FL",
    "sg:tags":[
        "broker"
    ],
    "wof:name":"Whalen Printing & Graphics",
    "wof:placetype":"venue"
},
  "geometry": {"coordinates":[-81.599031,30.278112],"type":"Point"}
}