{
  "type": "Feature",
  "properties": {
    "addr:full":"9737 New York Ave Hudson FL 34667",
    "addr:housenumber":"9737",
    "addr:postcode":"34667",
    "addr:street":"New York Ave",
    "iso:country":"US",
    "sg:address":"9737 New York Ave",
    "sg:city":"Hudson",
    "sg:classifiers":[
        {
            "category":"Building & Trades",
            "subcategory":"Construction",
            "type":"Services"
        },
        {
            "category":"Wholesale",
            "subcategory":"Metals & Minerals",
            "type":"Manufacturing & Wholesale Goods"
        }
    ],
    "sg:phone":"+1 727 863 2313",
    "sg:postcode":"34667",
    "sg:province":"FL",
    "sg:tags":[
        "installs",
        "enclosure",
        "aluminum"
    ],
    "wof:name":"Security Aluminum & Screening",
    "wof:placetype":"venue"
},
  "geometry": {"coordinates":[-82.65366899999999,28.375155],"type":"Point"}
}