{
  "type": "Feature",
  "properties": {
    "addr:full":"8917 Denton Ave Hudson FL 34667",
    "addr:housenumber":"8917",
    "addr:postcode":"34667",
    "addr:street":"Denton Ave",
    "iso:country":"US",
    "sg:address":"8917 Denton Ave",
    "sg:city":"Hudson",
    "sg:classifiers":[
        {
            "category":"Insurance",
            "subcategory":"Insurance Agent",
            "type":"Services"
        }
    ],
    "sg:phone":"+1 727 819 0060",
    "sg:postcode":"34667",
    "sg:province":"FL",
    "sg:tags":[
        "adjuster"
    ],
    "wof:name":"Altitude Adjustments",
    "wof:placetype":"venue"
},
  "geometry": {"coordinates":[-82.666905,28.389794],"type":"Point"}
}