{
  "type": "Feature",
  "properties": {
    "iso:country":"US",
    "sg:address":"1222 Poplar Dr",
    "sg:city":"Tallahassee",
    "sg:classifiers":[
        {
            "category":"Travel",
            "subcategory":"Travel Agent",
            "type":"Entertainment"
        }
    ],
    "sg:phone":"+1 850 575 6243",
    "sg:postcode":"32304",
    "sg:province":"FL",
    "sg:tags":[
        "operator",
        "tour"
    ],
    "wof:name":"Mex Moto Tours",
    "wof:placetype":"venue"
},
  "geometry": {"coordinates":[-84.382015,30.454568],"type":"Point"}
}