{
  "type": "Feature",
  "properties": {
    "iso:country":"US",
    "sg:address":"12275 SW 129th Ct",
    "sg:city":"Miami",
    "sg:classifiers":[
        {
            "category":"Professional",
            "subcategory":"Computer Services",
            "type":"Services"
        }
    ],
    "sg:phone":"+1 305 969 4900",
    "sg:postcode":"33186",
    "sg:province":"FL",
    "sg:tags":[
        "isp",
        "provider",
        "internet"
    ],
    "wof:name":"Multicomputer",
    "wof:placetype":"venue"
},
  "geometry": {"coordinates":[-80.404409,25.652768],"type":"Point"}
}