{
  "type": "Feature",
  "properties": {
    "addr:full":"701 15th St S St Petersburg FL 33705",
    "addr:housenumber":"701",
    "addr:postcode":"33705",
    "addr:street":"15Th St S",
    "iso:country":"US",
    "sg:address":"701 15th St S",
    "sg:city":"St Petersburg",
    "sg:classifiers":[
        {
            "category":"Social Services",
            "subcategory":"Child Care",
            "type":"Services"
        }
    ],
    "sg:phone":"+1 727 896 5280",
    "sg:postcode":"33705",
    "sg:province":"FL",
    "wof:name":"Shaketta's Daycare",
    "wof:placetype":"venue"
},
  "geometry": {"coordinates":[-82.65374799999999,27.7611],"type":"Point"}
}