{
  "type": "Feature",
  "properties": {
    "iso:country":"US",
    "sg:address":"8920 SW 40th St",
    "sg:city":"Miami",
    "sg:classifiers":[
        {
            "category":"Home & Garden",
            "subcategory":"Building Materials",
            "type":"Retail Goods"
        }
    ],
    "sg:phone":"+1 305 552 0921",
    "sg:postcode":"33165",
    "sg:province":"FL",
    "sg:tags":[
        "plumbing",
        "fixture",
        "supply"
    ],
    "wof:name":"Stern Brothers Plumbing Supply",
    "wof:placetype":"venue"
},
  "geometry": {"coordinates":[-80.340406,25.732907],"type":"Point"}
}