{
  "type": "Feature",
  "properties": {
    "addr:full":"1818 N J Ter Lake Worth FL 33460",
    "addr:housenumber":"1818",
    "addr:postcode":"33460",
    "addr:street":"N J Ter",
    "iso:country":"US",
    "sg:address":"1818 N J Ter",
    "sg:city":"Lake Worth",
    "sg:classifiers":[
        {
            "category":"Professional",
            "subcategory":"Computer Services",
            "type":"Services"
        }
    ],
    "sg:phone":"+1 561 588 2705",
    "sg:postcode":"33460",
    "sg:province":"FL",
    "sg:tags":[
        "consulting",
        "broadcasting",
        "television"
    ],
    "wof:name":"Designtvnet",
    "wof:placetype":"venue"
},
  "geometry": {"coordinates":[-80.054935,26.638367],"type":"Point"}
}