{
  "type": "Feature",
  "properties": {
    "addr:full":"2115 Dr Martin Luther King Blvd Fort Myers FL 33901",
    "addr:housenumber":"2115",
    "addr:postcode":"33901",
    "addr:street":"Dr Martin Luther King Blvd",
    "iso:country":"US",
    "sg:address":"2115 Dr Martin Luther King Blvd",
    "sg:city":"Fort Myers",
    "sg:classifiers":[
        {
            "category":"Building & Trades",
            "subcategory":"Construction",
            "type":"Services"
        }
    ],
    "sg:phone":"+1 239 226 9073",
    "sg:postcode":"33901",
    "sg:province":"FL",
    "sg:tags":[
        "general",
        "contractor"
    ],
    "wof:name":"Centex-Rooney Construction Co",
    "wof:placetype":"venue"
},
  "geometry": {"coordinates":[-81.869569,26.640798],"type":"Point"}
}