{
  "type": "Feature",
  "properties": {
    "iso:country":"US",
    "sg:address":"7964 Timberwood Cir",
    "sg:city":"Sarasota",
    "sg:classifiers":[
        {
            "category":"Travel",
            "subcategory":"Hotels & Motels",
            "type":"Entertainment"
        }
    ],
    "sg:phone":"+1 941 923 4966",
    "sg:postcode":"34238",
    "sg:province":"FL",
    "wof:name":"Timbersoods Vacation Villa",
    "wof:placetype":"venue"
},
  "geometry": {"coordinates":[-82.496033,27.23831],"type":"Point"}
}