{
  "type": "Feature",
  "properties": {
    "addr:full":"1311 E New Haven Ave Melbourne FL 32901",
    "addr:housenumber":"1311",
    "addr:postcode":"32901",
    "addr:street":"E New Haven Ave",
    "iso:country":"US",
    "sg:address":"1311 E New Haven Ave",
    "sg:city":"Melbourne",
    "sg:classifiers":[
        {
            "category":"Government",
            "subcategory":"Office",
            "type":"Public Place"
        }
    ],
    "sg:phone":"+1 321 952 6300",
    "sg:postcode":"32901",
    "sg:province":"FL",
    "sg:tags":[
        "executive"
    ],
    "wof:name":"Board Cnty Cmmissioners-Dist 3",
    "wof:placetype":"venue"
},
  "geometry": {"coordinates":[-80.600928,28.080077],"type":"Point"}
}