{
  "type": "Feature",
  "properties": {
    "addr:full":"11106 S Bear Creek Rd Panama City FL 32404",
    "addr:housenumber":"11106",
    "addr:postcode":"32404",
    "addr:street":"S Bear Creek Rd",
    "iso:country":"US",
    "sg:address":"11106 S Bear Creek Rd",
    "sg:city":"Panama City",
    "sg:classifiers":[
        {
            "category":"Home & Garden",
            "subcategory":"Hardware",
            "type":"Retail Goods"
        }
    ],
    "sg:phone":"+1 850 722 0356",
    "sg:postcode":"32404",
    "sg:province":"FL",
    "wof:name":"Mac Tools Distributor",
    "wof:placetype":"venue"
},
  "geometry": {"coordinates":[-85.44595200000001,30.319857],"type":"Point"}
}