{
  "type": "Feature",
  "properties": {
    "iso:country":"US",
    "sg:address":"1900 W Atlantic Ave",
    "sg:city":"Delray Beach",
    "sg:classifiers":[
        {
            "category":"Building & Trades",
            "subcategory":"Plumbing",
            "type":"Services"
        }
    ],
    "sg:phone":"+1 561 848 3774",
    "sg:postcode":"33444",
    "sg:province":"FL",
    "sg:tags":[
        "contractor"
    ],
    "wof:name":"Climate Control Services",
    "wof:placetype":"venue"
},
  "geometry": {"coordinates":[-80.089933,26.461552],"type":"Point"}
}