{
  "type": "Feature",
  "properties": {
    "iso:country":"US",
    "sg:address":"135 Sea Park Blvd",
    "sg:city":"Satellite Beach",
    "sg:classifiers":[
        {
            "category":"Building & Trades",
            "subcategory":"Construction",
            "type":"Services"
        }
    ],
    "sg:phone":"+1 321 779 4801",
    "sg:postcode":"32937",
    "sg:province":"FL",
    "sg:tags":[
        "house"
    ],
    "wof:name":"Sea Park Construction Inc",
    "wof:placetype":"venue"
},
  "geometry": {"coordinates":[-80.60082,28.203548],"type":"Point"}
}