{
  "type": "Feature",
  "properties": {
    "addr:full":"665 NW 102nd St Miami FL 33150",
    "addr:housenumber":"665",
    "addr:postcode":"33150",
    "addr:street":"Nw 102Nd St",
    "iso:country":"US",
    "sg:address":"665 NW 102nd St",
    "sg:city":"Miami",
    "sg:classifiers":[
        {
            "category":"Communications",
            "subcategory":"Film & Video Production",
            "type":"Services"
        }
    ],
    "sg:phone":"+1 305 758 7495",
    "sg:postcode":"33150",
    "sg:province":"FL",
    "sg:tags":[
        "supplies-renting",
        "leasing",
        "equipment"
    ],
    "wof:name":"Rj & Son Inc",
    "wof:placetype":"venue"
},
  "geometry": {"coordinates":[-80.209596,25.868497],"type":"Point"}
}