{
  "type": "Feature",
  "properties": {
    "iso:country":"US",
    "sg:address":"1000 Tamiami Trl",
    "sg:city":"Nokomis",
    "sg:classifiers":[
        {
            "category":"Banks & Credit Unions",
            "subcategory":"Bank",
            "type":"Services"
        }
    ],
    "sg:phone":"+1 941 483 1207",
    "sg:postcode":"34275",
    "sg:province":"FL",
    "wof:name":"Sun Trust Bank",
    "wof:placetype":"venue"
},
  "geometry": {"coordinates":[-82.45783900000001,27.138168],"type":"Point"}
}