{
  "type": "Feature",
  "properties": {
    "addr:full":"175 Tequesta Dr Jupiter FL 33469",
    "addr:housenumber":"175",
    "addr:postcode":"33469",
    "addr:street":"Tequesta Dr",
    "iso:country":"US",
    "sg:address":"175 Tequesta Dr",
    "sg:city":"Jupiter",
    "sg:classifiers":[
        {
            "category":"Health Services",
            "subcategory":"Doctor",
            "type":"Services"
        }
    ],
    "sg:phone":"+1 561 746 7684",
    "sg:postcode":"33469",
    "sg:province":"FL",
    "wof:name":"Meier Jennifer E DDS",
    "wof:placetype":"venue"
},
  "geometry": {"coordinates":[-80.087548,26.959041],"type":"Point"}
}