{
  "type": "Feature",
  "properties": {
    "addr:full":"349 Cambria Ct Safety Harbor FL 34695",
    "addr:housenumber":"349",
    "addr:postcode":"34695",
    "addr:street":"Cambria Ct",
    "iso:country":"US",
    "sg:address":"349 Cambria Ct",
    "sg:city":"Safety Harbor",
    "sg:classifiers":[
        {
            "category":"Farming",
            "subcategory":"Farm",
            "type":"Manufacturing & Wholesale Goods"
        }
    ],
    "sg:phone":"+1 727 725 5423",
    "sg:postcode":"34695",
    "sg:province":"FL",
    "sg:tags":[
        "crop",
        "general"
    ],
    "wof:name":"Jeanne R Pontius",
    "wof:placetype":"venue"
},
  "geometry": {"coordinates":[-82.682289,28.002955],"type":"Point"}
}