{
  "type": "Feature",
  "properties": {
    "iso:country":"US",
    "sg:address":"841 US Hwy 441",
    "sg:city":"Lady Lake",
    "sg:classifiers":[
        {
            "category":"Autos & Motor Vehicles",
            "subcategory":"Fuel & Gas Station",
            "type":"Retail Goods"
        }
    ],
    "sg:phone":"+1 352 750 6901",
    "sg:postcode":"32159",
    "sg:province":"FL",
    "sg:tags":[
        "convenience",
        "station",
        "gasoline",
        "store"
    ],
    "wof:name":"Southwind Exxon",
    "wof:placetype":"venue"
},
  "geometry": {"coordinates":[-81.911573,28.900034],"type":"Point"}
}