{
  "type": "Feature",
  "properties": {
    "addr:full":"151 Blue Moon Ave Lake Placid FL 33852",
    "addr:housenumber":"151",
    "addr:postcode":"33852",
    "addr:street":"Blue Moon Ave",
    "iso:country":"US",
    "sg:address":"151 Blue Moon Ave",
    "sg:city":"Lake Placid",
    "sg:classifiers":[
        {
            "category":"Farming",
            "subcategory":"Livestock Farm",
            "type":"Manufacturing & Wholesale Goods"
        }
    ],
    "sg:phone":"+1 863 465 2020",
    "sg:postcode":"33852",
    "sg:province":"FL",
    "sg:tags":[
        "beef",
        "feedlot",
        "cattle"
    ],
    "wof:name":"Lon Chisum",
    "wof:placetype":"venue"
},
  "geometry": {"coordinates":[-81.32177900000001,27.252588],"type":"Point"}
}