{
  "type": "Feature",
  "properties": {
    "addr:full":"14042 66th St N Largo FL 33771",
    "addr:housenumber":"14042",
    "addr:postcode":"33771",
    "addr:street":"66Th St N",
    "iso:country":"US",
    "sg:address":"14042 66th St N",
    "sg:city":"Largo",
    "sg:classifiers":[
        {
            "category":"Home & Garden",
            "subcategory":"Building Materials",
            "type":"Retail Goods"
        }
    ],
    "sg:phone":"+1 727 535 5568",
    "sg:postcode":"33771",
    "sg:province":"FL",
    "sg:tags":[
        "marble"
    ],
    "wof:name":"Great Bay Granite Inc",
    "wof:placetype":"venue"
},
  "geometry": {"coordinates":[-82.72905900000001,27.899505],"type":"Point"}
}