{
  "type": "Feature",
  "properties": {
    "iso:country":"US",
    "sg:address":"5805 Blue Lagoon Dr # 200",
    "sg:city":"Miami",
    "sg:classifiers":[
        {
            "category":"Building & Trades",
            "subcategory":"Construction",
            "type":"Services"
        }
    ],
    "sg:phone":"+1 786 319 5125",
    "sg:postcode":"33126",
    "sg:province":"FL",
    "sg:tags":[
        "industrial",
        "contractors-commercial",
        "contractor"
    ],
    "wof:name":"The Continental Group Inc",
    "wof:placetype":"venue"
},
  "geometry": {"coordinates":[-80.291422,25.782937],"type":"Point"}
}