{
  "type": "Feature",
  "properties": {
    "iso:country":"US",
    "sg:address":"13790 Roosevelt Blvd",
    "sg:city":"Clearwater",
    "sg:classifiers":[
        {
            "category":"Wholesale",
            "subcategory":"Motor Vehicles",
            "type":"Manufacturing & Wholesale Goods"
        },
        {
            "category":"Manufacturing",
            "subcategory":"Motor Vehicles & Parts",
            "type":"Manufacturing & Wholesale Goods"
        }
    ],
    "sg:phone":"+1 727 571 1899",
    "sg:postcode":"33762",
    "sg:province":"FL",
    "sg:tags":[
        "recreational",
        "mfg"
    ],
    "wof:name":"Parliament Coach Corporation",
    "wof:placetype":"venue"
},
  "geometry": {"coordinates":[-82.693089,27.897756],"type":"Point"}
}