{
  "type": "Feature",
  "properties": {
    "iso:country":"US",
    "sg:address":"967 Bayshore Dr",
    "sg:city":"Tarpon Springs",
    "sg:classifiers":[
        {
            "category":"Professional",
            "subcategory":"Management & Consulting",
            "type":"Services"
        }
    ],
    "sg:phone":"+1 727 942 0382",
    "sg:postcode":"34689",
    "sg:province":"FL",
    "sg:tags":[
        "consultant",
        "business"
    ],
    "wof:name":"Sellew & Assoc",
    "wof:placetype":"venue"
},
  "geometry": {"coordinates":[-82.771973,28.159014],"type":"Point"}
}