{
  "type": "Feature",
  "properties": {
    "addr:full":"306 S Duval St Tallahassee FL 32301",
    "addr:housenumber":"306",
    "addr:postcode":"32301",
    "addr:street":"S Duval St",
    "iso:country":"US",
    "sg:address":"306 S Duval St",
    "sg:city":"Tallahassee",
    "sg:classifiers":[
        {
            "category":"Parking",
            "type":"Transportation"
        }
    ],
    "sg:phone":"+1 850 561 3066",
    "sg:postcode":"32301",
    "sg:province":"FL",
    "sg:tags":[
        "automobile"
    ],
    "wof:name":"Republic Parking System",
    "wof:placetype":"venue"
},
  "geometry": {"coordinates":[-84.283162,30.439438],"type":"Point"}
}