{
  "type": "Feature",
  "properties": {
    "addr:full":"452 Longwood Dr Venice FL 34285",
    "addr:housenumber":"452",
    "addr:postcode":"34285",
    "addr:street":"Longwood Dr",
    "iso:country":"US",
    "sg:address":"452 Longwood Dr",
    "sg:city":"Venice",
    "sg:classifiers":[
        {
            "category":"Manufacturing",
            "subcategory":"Motor Vehicles & Parts",
            "type":"Manufacturing & Wholesale Goods"
        }
    ],
    "sg:phone":"+1 941 484 0330",
    "sg:postcode":"34285",
    "sg:province":"FL",
    "sg:tags":[
        "equipment",
        "railroad",
        "mfg"
    ],
    "wof:name":"Jka Co",
    "wof:placetype":"venue"
},
  "geometry": {"coordinates":[-82.41962100000001,27.082411],"type":"Point"}
}