{
  "type": "Feature",
  "properties": {
    "iso:country":"US",
    "sg:address":"12109 Lake Carroll Dr",
    "sg:city":"Tampa",
    "sg:classifiers":[
        {
            "category":"Real Estate",
            "subcategory":"Real Estate Agent",
            "type":"Services"
        }
    ],
    "sg:phone":"+1 727 808 8470",
    "sg:postcode":"33618",
    "sg:province":"FL",
    "wof:name":"KMC Property Management",
    "wof:placetype":"venue"
},
  "geometry": {"coordinates":[-82.484325,28.057516],"type":"Point"}
}