{
  "type": "Feature",
  "properties": {
    "iso:country":"US",
    "sg:address":"360 Center Rd",
    "sg:city":"Nokomis",
    "sg:classifiers":[
        {
            "category":"Manufacturing",
            "subcategory":"Printing",
            "type":"Manufacturing & Wholesale Goods"
        }
    ],
    "sg:phone":"+1 941 485 4200",
    "sg:postcode":"34285",
    "sg:province":"FL",
    "sg:tags":[
        "printer"
    ],
    "wof:name":"Check Depot",
    "wof:placetype":"venue"
},
  "geometry": {"coordinates":[-82.414269,27.078931],"type":"Point"}
}