{
  "type": "Feature",
  "properties": {
    "addr:full":"4944 NW 97th Dr Pompano Beach FL 33076",
    "addr:housenumber":"4944",
    "addr:postcode":"33076",
    "addr:street":"Nw 97Th Dr",
    "iso:country":"US",
    "sg:address":"4944 NW 97th Dr",
    "sg:city":"Pompano Beach",
    "sg:classifiers":[
        {
            "category":"Banks & Credit Unions",
            "subcategory":"Financial Services",
            "type":"Services"
        }
    ],
    "sg:phone":"+1 954 344 3770",
    "sg:postcode":"33076",
    "sg:province":"FL",
    "sg:tags":[
        "company",
        "holding"
    ],
    "wof:name":"Chimera Holdings LLC",
    "wof:placetype":"venue"
},
  "geometry": {"coordinates":[-80.253945,26.292162],"type":"Point"}
}