{
  "type": "Feature",
  "properties": {
    "addr:full":"7321 Dilido Blvd Miramar FL 33023",
    "addr:housenumber":"7321",
    "addr:postcode":"33023",
    "addr:street":"Dilido Blvd",
    "iso:country":"US",
    "sg:address":"7321 Dilido Blvd",
    "sg:city":"Miramar",
    "sg:classifiers":[
        {
            "category":"Building & Trades",
            "subcategory":"Cleaning & Sanitation",
            "type":"Services"
        }
    ],
    "sg:phone":"+1 954 981 7245",
    "sg:postcode":"33023",
    "sg:province":"FL",
    "sg:tags":[
        "janitor"
    ],
    "wof:name":"Best Quote",
    "wof:placetype":"venue"
},
  "geometry": {"coordinates":[-80.23209799999999,25.978111],"type":"Point"}
}