{
  "type": "Feature",
  "properties": {
    "addr:full":"6637 Pensacola Blvd Pensacola FL 32505",
    "addr:housenumber":"6637",
    "addr:postcode":"32505",
    "addr:street":"Pensacola Blvd",
    "iso:country":"US",
    "sg:address":"6637 Pensacola Blvd",
    "sg:city":"Pensacola",
    "sg:classifiers":[
        {
            "category":"Autos & Motor Vehicles",
            "subcategory":"Automobile Sales",
            "type":"Retail Goods"
        }
    ],
    "sg:phone":"+1 850 457 7772",
    "sg:postcode":"32505",
    "sg:province":"FL",
    "sg:tags":[
        "new",
        "used",
        "car"
    ],
    "sg:website":"http://www.kiaautosport.com",
    "wof:name":"Kia AutoSport - New & Used Cars",
    "wof:placetype":"venue"
},
  "geometry": {"coordinates":[-87.258302,30.485762],"type":"Point"}
}