{
  "type": "Feature",
  "properties": {
    "addr:full":"750 High Pines Dr Naples FL 34103",
    "addr:housenumber":"750",
    "addr:postcode":"34103",
    "addr:street":"High Pines Dr",
    "iso:country":"US",
    "sg:address":"750 High Pines Dr",
    "sg:city":"Naples",
    "sg:classifiers":[
        {
            "category":"Professional",
            "type":"Services"
        }
    ],
    "sg:phone":"+1 239 261 3638",
    "sg:postcode":"34103",
    "sg:province":"FL",
    "sg:tags":[
        "establishment"
    ],
    "wof:name":"R Scott Cameron Guest House",
    "wof:placetype":"venue"
},
  "geometry": {"coordinates":[-81.80302500000001,26.208303],"type":"Point"}
}