{
  "type": "Feature",
  "properties": {
    "addr:full":"5100 NW 72nd Ave Miami FL 33166",
    "addr:housenumber":"5100",
    "addr:postcode":"33166",
    "addr:street":"Nw 72Nd Ave",
    "iso:country":"US",
    "sg:address":"5100 NW 72nd Ave",
    "sg:city":"Miami",
    "sg:classifiers":[
        {
            "category":"Manufacturing",
            "subcategory":"Tobacco Products",
            "type":"Manufacturing & Wholesale Goods"
        }
    ],
    "sg:phone":"+1 305 471 8155",
    "sg:postcode":"33166",
    "sg:province":"FL",
    "sg:tags":[
        "cigarette",
        "cigar",
        "tobacco-wholesale",
        "manufacturer"
    ],
    "wof:name":"Tabacos Sa",
    "wof:placetype":"venue"
},
  "geometry": {"coordinates":[-80.313637,25.81979],"type":"Point"}
}