{
  "type": "Feature",
  "properties": {
    "iso:country":"US",
    "sg:address":"1355 N US Hwy 1",
    "sg:city":"Rockledge",
    "sg:classifiers":[
        {
            "category":"Shopping",
            "subcategory":"Florist",
            "type":"Retail Goods"
        }
    ],
    "sg:phone":"+1 321 636 7195",
    "sg:postcode":"32955",
    "sg:province":"FL",
    "sg:tags":[
        "shop"
    ],
    "wof:name":"Carousel of Rockledge Inc",
    "wof:placetype":"venue"
},
  "geometry": {"coordinates":[-80.725719,28.335321],"type":"Point"}
}