{
  "type": "Feature",
  "properties": {
    "iso:country":"US",
    "sg:address":"22501 Buccaneer Lagoon St",
    "sg:city":"Fort Myers Beach",
    "sg:classifiers":[
        {
            "category":"Building & Trades",
            "subcategory":"Construction",
            "type":"Services"
        }
    ],
    "sg:phone":"+1 239 463 0203",
    "sg:postcode":"33931",
    "sg:province":"FL",
    "sg:tags":[
        "speculative",
        "contractor"
    ],
    "wof:name":"William E Whitley Construction",
    "wof:placetype":"venue"
},
  "geometry": {"coordinates":[-81.894728,26.407484],"type":"Point"}
}