{
  "type": "Feature",
  "properties": {
    "iso:country":"US",
    "sg:address":"8875 Hidden River Pkwy",
    "sg:city":"Tampa",
    "sg:classifiers":[
        {
            "category":"Education",
            "subcategory":"Special Training",
            "type":"Public Place"
        }
    ],
    "sg:phone":"+1 813 631 5799",
    "sg:postcode":"33637",
    "sg:province":"FL",
    "sg:tags":[
        "consulting",
        "management"
    ],
    "wof:name":"Achieveglobal Inc",
    "wof:placetype":"venue"
},
  "geometry": {"coordinates":[-82.359619,28.069868],"type":"Point"}
}