{
  "type": "Feature",
  "properties": {
    "iso:country":"US",
    "sg:address":"11 Riverside Dr",
    "sg:city":"Cocoa",
    "sg:classifiers":[
        {
            "category":"Professional",
            "subcategory":"Lawyer & Legal Services",
            "type":"Services"
        }
    ],
    "sg:phone":"+1 321 433 0771",
    "sg:postcode":"32922",
    "sg:province":"FL",
    "sg:tags":[
        "attorney"
    ],
    "wof:name":"Troy W Stephan Law Offices",
    "wof:placetype":"venue"
},
  "geometry": {"coordinates":[-80.723749,28.351284],"type":"Point"}
}