{
  "type": "Feature",
  "properties": {
    "iso:country":"US",
    "sg:address":"1810 Persimmon Dr",
    "sg:city":"Naples",
    "sg:classifiers":[
        {
            "category":"Recreation",
            "type":"Entertainment"
        }
    ],
    "sg:phone":"+1 239 597 3000",
    "sg:postcode":"34109",
    "sg:province":"FL",
    "sg:tags":[
        "club",
        "membership"
    ],
    "wof:name":"W C I Communities Inc",
    "wof:placetype":"venue"
},
  "geometry": {"coordinates":[-81.785701,26.252149],"type":"Point"}
}