{
  "type": "Feature",
  "properties": {
    "iso:country":"US",
    "sg:address":"201 NW 82nd Ave",
    "sg:city":"Fort Lauderdale",
    "sg:classifiers":[
        {
            "category":"Health Services",
            "subcategory":"Doctor",
            "type":"Services"
        }
    ],
    "sg:phone":"+1 954 474 5666",
    "sg:postcode":"33324",
    "sg:province":"FL",
    "sg:tags":[
        "specializing",
        "physician",
        "internal",
        "medicine"
    ],
    "wof:name":"Bravo Albert F MD",
    "wof:placetype":"venue"
},
  "geometry": {"coordinates":[-80.25846799999999,26.12415],"type":"Point"}
}