{
  "type": "Feature",
  "properties": {
    "addr:full":"1220 NW 38th Ave Ocala FL 34482",
    "addr:housenumber":"1220",
    "addr:postcode":"34482",
    "addr:street":"Nw 38Th Ave",
    "iso:country":"US",
    "sg:address":"1220 NW 38th Ave",
    "sg:city":"Ocala",
    "sg:classifiers":[
        {
            "category":"Professional",
            "subcategory":"Engineering",
            "type":"Services"
        },
        {
            "category":"Retail",
            "subcategory":"Repair Shop",
            "type":"Services"
        },
        {
            "category":"Wholesale",
            "subcategory":"Machinery & Supplies",
            "type":"Manufacturing & Wholesale Goods"
        },
        {
            "category":"Restaurant",
            "type":"Food & Drink"
        }
    ],
    "sg:phone":"+1 352 622 3828",
    "sg:postcode":"34482",
    "sg:province":"FL",
    "sg:tags":[
        "equipment-commercial",
        "equipment",
        "equipment-parts",
        "machine",
        "supplies-refrigeration",
        "industrial",
        "refrigeration",
        "ice",
        "making",
        "freezers-wholesale",
        "manufacturer",
        "freezers-repair",
        "refrigerator",
        "engineer"
    ],
    "wof:name":"Florida Refrigeration & Equipment Inc",
    "wof:placetype":"venue"
},
  "geometry": {"coordinates":[-82.18520700000001,29.198993],"type":"Point"}
}