{
  "type": "Feature",
  "properties": {
    "iso:country":"US",
    "sg:address":"6409 Land O Lakes Blvd",
    "sg:city":"Land O Lakes",
    "sg:classifiers":[
        {
            "category":"Building & Trades",
            "subcategory":"Construction",
            "type":"Services"
        }
    ],
    "sg:phone":"+1 813 996 3350",
    "sg:postcode":"34638",
    "sg:province":"FL",
    "sg:tags":[
        "asbestos",
        "removal"
    ],
    "sg:website":"www.gotmold.com",
    "wof:name":"Asbestos Certified Technicians",
    "wof:placetype":"venue"
},
  "geometry": {"coordinates":[-82.46572,28.250461],"type":"Point"}
}