{
  "type": "Feature",
  "properties": {
    "iso:country":"US",
    "sg:address":"5127 Co Rd 169",
    "sg:city":"Wildwood",
    "sg:classifiers":[
        {
            "category":"Shopping",
            "subcategory":"Discount & Variety Stores",
            "type":"Retail Goods"
        }
    ],
    "sg:phone":"+1 352 330 1613",
    "sg:postcode":"34785",
    "sg:province":"FL",
    "sg:tags":[
        "merchandise",
        "general"
    ],
    "wof:name":"Jus Country By Jamie Jones",
    "wof:placetype":"venue"
},
  "geometry": {"coordinates":[-81.999385,28.831349],"type":"Point"}
}