{
  "type": "Feature",
  "properties": {
    "addr:full":"6625 Miami Lakes Dr E Ste 314 Hialeah FL 33014",
    "addr:housenumber":"6625",
    "addr:postcode":"33014",
    "addr:street":"Miami Lakes Dr E Ste 314",
    "iso:country":"US",
    "sg:address":"6625 Miami Lakes Dr E Ste 314",
    "sg:city":"Hialeah",
    "sg:classifiers":[
        {
            "category":"Professional",
            "subcategory":"Lawyer & Legal Services",
            "type":"Services"
        }
    ],
    "sg:phone":"+1 305 777 0771",
    "sg:postcode":"33014",
    "sg:province":"FL",
    "wof:name":"Law Offices of Odalys Sanchez PA",
    "wof:placetype":"venue"
},
  "geometry": {"coordinates":[-80.306997,25.909004],"type":"Point"}
}