{
  "type": "Feature",
  "properties": {
    "addr:full":"2300 Silver Star Rd Orlando FL 32804",
    "addr:housenumber":"2300",
    "addr:postcode":"32804",
    "addr:street":"Silver Star Rd",
    "iso:country":"US",
    "sg:address":"2300 Silver Star Rd",
    "sg:city":"Orlando",
    "sg:classifiers":[
        {
            "category":"Wholesale",
            "subcategory":"Machinery & Supplies",
            "type":"Manufacturing & Wholesale Goods"
        }
    ],
    "sg:phone":"+1 407 291 1717",
    "sg:postcode":"32804",
    "sg:province":"FL",
    "wof:name":"Tresca Turf & Tractor",
    "wof:placetype":"venue"
},
  "geometry": {"coordinates":[-81.412049,28.578085],"type":"Point"}
}