{
  "type": "Feature",
  "properties": {
    "iso:country":"US",
    "sg:address":"18320 NE 1st Ct",
    "sg:city":"Miami",
    "sg:classifiers":[
        {
            "category":"Retail",
            "subcategory":"Auto Repair",
            "type":"Services"
        }
    ],
    "sg:phone":"+1 305 652 3161",
    "sg:postcode":"33179",
    "sg:province":"FL",
    "sg:tags":[
        "truck"
    ],
    "wof:name":"J & J Automotive Inc",
    "wof:placetype":"venue"
},
  "geometry": {"coordinates":[-80.197998,25.9429],"type":"Point"}
}