{
  "type": "Feature",
  "properties": {
    "iso:country":"US",
    "sg:address":"2600 Ali Baba Ave",
    "sg:city":"Opa Locka",
    "sg:classifiers":[
        {
            "category":"Manufacturing",
            "subcategory":"Apparel",
            "type":"Manufacturing & Wholesale Goods"
        }
    ],
    "sg:phone":"+1 305 688 1252",
    "sg:postcode":"33054",
    "sg:province":"FL",
    "sg:tags":[
        "outerwear",
        "mfg"
    ],
    "wof:name":"Seaside Swim",
    "wof:placetype":"venue"
},
  "geometry": {"coordinates":[-80.24390099999999,25.905023],"type":"Point"}
}