{
  "type": "Feature",
  "properties": {
    "addr:full":"2312 Companion Cir E Jacksonville FL 32224",
    "addr:postcode":"2312;32224",
    "addr:street":"Companion Cir E",
    "iso:country":"US",
    "sg:address":"2312 Companion Cir E",
    "sg:city":"Jacksonville",
    "sg:classifiers":[
        {
            "category":"Building & Trades",
            "subcategory":"Construction",
            "type":"Services"
        }
    ],
    "sg:phone":"+1 904 220 2903",
    "sg:postcode":"32224",
    "sg:province":"FL",
    "sg:tags":[
        "heavy"
    ],
    "wof:name":"Frank V Key Construction",
    "wof:placetype":"venue"
},
  "geometry": {"coordinates":[-81.45571099999999,30.308872],"type":"Point"}
}