{
  "type": "Feature",
  "properties": {
    "iso:country":"US",
    "sg:address":"414 W 9th St",
    "sg:city":"Sanford",
    "sg:classifiers":[
        {
            "category":"Building & Trades",
            "subcategory":"Construction",
            "type":"Services"
        }
    ],
    "sg:phone":"+1 386 717 2530",
    "sg:postcode":"32771",
    "sg:province":"FL",
    "sg:tags":[
        "roofing",
        "contractor"
    ],
    "wof:name":"Cornerstone Construction Ents",
    "wof:placetype":"venue"
},
  "geometry": {"coordinates":[-81.271204,28.804429],"type":"Point"}
}