{
  "type": "Feature",
  "properties": {
    "iso:country":"US",
    "sg:address":"14306 Estrella Dr",
    "sg:city":"Orlando",
    "sg:classifiers":[
        {
            "category":"Professional",
            "subcategory":"Management & Consulting",
            "type":"Services"
        }
    ],
    "sg:phone":"+1 407 348 1444",
    "sg:postcode":"32837",
    "sg:province":"FL",
    "sg:tags":[
        "communications",
        "consultant"
    ],
    "wof:name":"New-Tel Communications Inc",
    "wof:placetype":"venue"
},
  "geometry": {"coordinates":[-81.464972,28.360509],"type":"Point"}
}