{
  "type": "Feature",
  "properties": {
    "iso:country":"US",
    "sg:address":"311 Blanding Blvd",
    "sg:city":"Orange Park",
    "sg:classifiers":[
        {
            "category":"Retail",
            "subcategory":"Portrait Studio",
            "type":"Services"
        }
    ],
    "sg:phone":"+1 904 272 4070",
    "sg:postcode":"32073",
    "sg:province":"FL",
    "sg:tags":[
        "photographer"
    ],
    "wof:name":"Olan Mills Portrait Studio",
    "wof:placetype":"venue"
},
  "geometry": {"coordinates":[-81.74731800000001,30.16976],"type":"Point"}
}