{
  "type": "Feature",
  "properties": {
    "addr:full":"3024 Sunrise Dr Sebring FL 33872",
    "addr:housenumber":"3024",
    "addr:postcode":"33872",
    "addr:street":"Sunrise Dr",
    "iso:country":"US",
    "sg:address":"3024 Sunrise Dr",
    "sg:city":"Sebring",
    "sg:classifiers":[
        {
            "category":"Freight",
            "type":"Transportation"
        }
    ],
    "sg:phone":"+1 863 382 1498",
    "sg:postcode":"33872",
    "sg:province":"FL",
    "sg:tags":[
        "operator",
        "trucking"
    ],
    "wof:name":"J L Stills Inc",
    "wof:placetype":"venue"
},
  "geometry": {"coordinates":[-81.525059,27.523074],"type":"Point"}
}