{
  "type": "Feature",
  "properties": {
    "iso:country":"US",
    "sg:address":"2202 Old Tampa Hwy",
    "sg:city":"Lakeland",
    "sg:classifiers":[
        {
            "category":"Wholesale",
            "subcategory":"Electrical",
            "type":"Manufacturing & Wholesale Goods"
        }
    ],
    "sg:phone":"+1 863 284 1139",
    "sg:postcode":"33815",
    "sg:province":"FL",
    "sg:tags":[
        "electric",
        "motor"
    ],
    "wof:name":"T & W Electric Motor Repair",
    "wof:placetype":"venue"
},
  "geometry": {"coordinates":[-81.99563000000001,28.037208],"type":"Point"}
}