{
  "type": "Feature",
  "properties": {
    "addr:full":"12808 Austin Cove Ct Clermont FL 34711",
    "addr:housenumber":"12808",
    "addr:postcode":"34711",
    "addr:street":"Austin Cove Ct",
    "iso:country":"US",
    "sg:address":"12808 Austin Cove Ct",
    "sg:city":"Clermont",
    "sg:classifiers":[
        {
            "category":"Health Services",
            "subcategory":"Hospital",
            "type":"Services"
        }
    ],
    "sg:phone":"+1 407 347 3950",
    "sg:postcode":"34711",
    "sg:province":"FL",
    "sg:tags":[
        "equipment",
        "supply"
    ],
    "wof:name":"Reliance Medical Supply",
    "wof:placetype":"venue"
},
  "geometry": {"coordinates":[-81.68541,28.53317],"type":"Point"}
}