{
  "type": "Feature",
  "properties": {
    "iso:country":"US",
    "sg:address":"1492 Apalachee Pkwy",
    "sg:city":"Tallahassee",
    "sg:phone":"+1 850 942 6150",
    "sg:postcode":"32301",
    "sg:province":"FL",
    "sg:website":"http://www.supercuts.com/",
    "wof:name":"Supercuts",
    "wof:placetype":"venue"
},
  "geometry": {"coordinates":[-84.25739900000001,30.435531],"type":"Point"}
}