{
  "type": "Feature",
  "properties": {
    "iso:country":"US",
    "sg:address":"225 Egret Ave",
    "sg:city":"Naples",
    "sg:classifiers":[
        {
            "category":"Professional",
            "subcategory":"Business Services",
            "type":"Services"
        }
    ],
    "sg:phone":"+1 239 591 0680",
    "sg:postcode":"34108",
    "sg:province":"FL",
    "sg:tags":[
        "mfg",
        "household",
        "laminated",
        "design",
        "interior",
        "furniture"
    ],
    "wof:name":"Continental Furnishings Inc",
    "wof:placetype":"venue"
},
  "geometry": {"coordinates":[-81.819227,26.268985],"type":"Point"}
}