{
  "type": "Feature",
  "properties": {
    "iso:country":"US",
    "sg:address":"10333 Seminole Blvd",
    "sg:city":"Largo",
    "sg:classifiers":[
        {
            "category":"Personal",
            "subcategory":"Beauty Salon",
            "type":"Services"
        }
    ],
    "sg:phone":"+1 727 320 9600",
    "sg:postcode":"33778",
    "sg:province":"FL",
    "sg:tags":[
        "spa",
        "day"
    ],
    "wof:name":"Ambrosia Spa De Beaute Salon",
    "wof:placetype":"venue"
},
  "geometry": {"coordinates":[-82.786935,27.867105],"type":"Point"}
}