{
  "type": "Feature",
  "properties": {
    "addr:full":"4440 Okeechobee Blvd West Palm Beach FL 33409",
    "addr:housenumber":"4440",
    "addr:postcode":"33409",
    "addr:street":"Okeechobee Blvd",
    "iso:country":"US",
    "sg:address":"4440 Okeechobee Blvd",
    "sg:city":"West Palm Beach",
    "sg:classifiers":[
        {
            "category":"Bakery",
            "type":"Food & Drink"
        },
        {
            "category":"Coffee & Tea",
            "type":"Food & Drink"
        },
        {
            "category":"Bagels",
            "type":"Food & Drink"
        },
        {
            "category":"Donuts",
            "type":"Food & Drink"
        }
    ],
    "sg:menulink":"http://www.allmenus.com/fl/west-palm-beach/138143-dunkin-donuts/menu/",
    "sg:phone":"+1 561 689 7273",
    "sg:postcode":"33409",
    "sg:province":"FL",
    "sg:tags":[
        "american",
        "pastry"
    ],
    "wof:name":"Dunkin' Donuts",
    "wof:placetype":"venue"
},
  "geometry": {"coordinates":[-80.11084099999999,26.706748],"type":"Point"}
}