{
  "type": "Feature",
  "properties": {
    "iso:country":"US",
    "sg:address":"1442 SW Highway 17",
    "sg:city":"Arcadia",
    "sg:classifiers":[
        {
            "category":"Autos & Motor Vehicles",
            "subcategory":"Automobile Sales",
            "type":"Retail Goods"
        }
    ],
    "sg:phone":"+1 863 494 7775",
    "sg:postcode":"34266",
    "sg:province":"FL",
    "sg:tags":[
        "new",
        "car"
    ],
    "sg:website":"http://www.desotoautomall.com",
    "wof:name":"Desoto Used Car Supercenter",
    "wof:placetype":"venue"
},
  "geometry": {"coordinates":[-81.864614,27.198623],"type":"Point"}
}