{
  "type": "Feature",
  "properties": {
    "addr:full":"220 N Park Ave Winter Park FL 32789",
    "addr:housenumber":"220",
    "addr:postcode":"32789",
    "addr:street":"N Park Ave",
    "iso:country":"US",
    "sg:address":"220 N Park Ave",
    "sg:city":"Winter Park",
    "sg:classifiers":[
        {
            "category":"Shopping",
            "subcategory":"Clothing, Apparel, & Fashions",
            "type":"Retail Goods"
        }
    ],
    "sg:phone":"+1 407 644 9311",
    "sg:postcode":"32789",
    "sg:province":"FL",
    "sg:tags":[
        "wear"
    ],
    "wof:name":"Gap The",
    "wof:placetype":"venue"
},
  "geometry": {"coordinates":[-81.35099200000001,28.599333],"type":"Point"}
}