{
  "type": "Feature",
  "properties": {
    "iso:country":"US",
    "sg:address":"303 E Jackson Ave",
    "sg:city":"Mt Dora",
    "sg:classifiers":[
        {
            "category":"Organizations",
            "subcategory":"Religious Organization",
            "type":"Services"
        }
    ],
    "sg:phone":"+1 352 383 0156",
    "sg:postcode":"32757",
    "sg:province":"FL",
    "sg:tags":[
        "church"
    ],
    "wof:name":"Bethel Free Methodist Church",
    "wof:placetype":"venue"
},
  "geometry": {"coordinates":[-81.642461,28.810631],"type":"Point"}
}