{
  "type": "Feature",
  "properties": {
    "iso:country":"US",
    "sg:address":"516 Bianca Ct",
    "sg:city":"Altamonte Springs",
    "sg:classifiers":[
        {
            "category":"Organizations",
            "subcategory":"Membership Organization",
            "type":"Services"
        }
    ],
    "sg:phone":"+1 407 331 6256",
    "sg:postcode":"32701",
    "sg:province":"FL",
    "wof:name":"Distrct 35 Lions Prjct Rght To",
    "wof:placetype":"venue"
},
  "geometry": {"coordinates":[-81.37143,28.645175],"type":"Point"}
}