{
  "type": "Feature",
  "properties": {
    "iso:country":"US",
    "sg:address":"4 Sewanee Cir",
    "sg:city":"Panama City",
    "sg:classifiers":[
        {
            "category":"Shopping",
            "subcategory":"Gifts & Souvenirs",
            "type":"Retail Goods"
        }
    ],
    "sg:phone":"+1 850 872 1195",
    "sg:postcode":"32405",
    "sg:province":"FL",
    "sg:tags":[
        "jewelry"
    ],
    "wof:name":"Your Earth",
    "wof:placetype":"venue"
},
  "geometry": {"coordinates":[-85.679985,30.196548],"type":"Point"}
}