{
  "type": "Feature",
  "properties": {
    "addr:full":"4325 Golfers Cir E Palm Beach Gardens FL 33410",
    "addr:housenumber":"4325",
    "addr:postcode":"33410",
    "addr:street":"Golfers Cir E",
    "iso:country":"US",
    "sg:address":"4325 Golfers Cir E",
    "sg:city":"Palm Beach Gardens",
    "sg:classifiers":[
        {
            "category":"Utilities",
            "subcategory":"Telephone",
            "type":"Services"
        }
    ],
    "sg:phone":"+1 561 799 9408",
    "sg:postcode":"33410",
    "sg:province":"FL",
    "sg:tags":[
        "communications"
    ],
    "wof:name":"Ghost Surfers International",
    "wof:placetype":"venue"
},
  "geometry": {"coordinates":[-80.102046,26.828194],"type":"Point"}
}