{
  "type": "Feature",
  "properties": {
    "addr:full":"12180 SW 87th Ave Miami FL 33176",
    "addr:housenumber":"12180",
    "addr:postcode":"33176",
    "addr:street":"Sw 87Th Ave",
    "iso:country":"US",
    "sg:address":"12180 SW 87th Ave",
    "sg:city":"Miami",
    "sg:classifiers":[
        {
            "category":"Banks & Credit Unions",
            "subcategory":"Financial Services",
            "type":"Services"
        }
    ],
    "sg:phone":"+1 305 233 3808",
    "sg:postcode":"33176",
    "sg:province":"FL",
    "sg:tags":[
        "broker",
        "mortgage"
    ],
    "wof:name":"Mortgage Choice",
    "wof:placetype":"venue"
},
  "geometry": {"coordinates":[-80.334726,25.656936],"type":"Point"}
}