{
  "type": "Feature",
  "properties": {
    "addr:full":"1305 Coastal Hwy Panacea FL 32346",
    "addr:housenumber":"1305",
    "addr:postcode":"32346",
    "addr:street":"Coastal Hwy",
    "iso:country":"US",
    "sg:address":"1305 Coastal Hwy",
    "sg:city":"Panacea",
    "sg:classifiers":[
        {
            "category":"Restaurant",
            "type":"Food & Drink"
        }
    ],
    "sg:phone":"+1 850 984 4986",
    "sg:postcode":"32346",
    "sg:province":"FL",
    "wof:name":"Coastal Restaurant",
    "wof:placetype":"venue"
},
  "geometry": {"coordinates":[-84.390236,30.027224],"type":"Point"}
}