{
  "type": "Feature",
  "properties": {
    "iso:country":"US",
    "sg:address":"10409 SE State Road 100",
    "sg:city":"Starke",
    "sg:classifiers":[
        {
            "category":"Place Of Worship",
            "subcategory":"Church",
            "type":"Public Place"
        }
    ],
    "sg:phone":"+1 850 385 1287",
    "sg:postcode":"32091",
    "sg:province":"FL",
    "sg:tags":[
        "churches-baptist"
    ],
    "wof:name":"Bradford Baptist Church",
    "wof:placetype":"venue"
},
  "geometry": {"coordinates":[-82.101032,29.927755],"type":"Point"}
}