{
  "type": "Feature",
  "properties": {
    "iso:country":"US",
    "sg:address":"1800 Brooks Ln",
    "sg:city":"Oviedo",
    "sg:classifiers":[
        {
            "category":"Personal",
            "type":"Services"
        }
    ],
    "sg:phone":"+1 407 977 1754",
    "sg:postcode":"32765",
    "sg:province":"FL",
    "sg:tags":[
        "therapist",
        "massage"
    ],
    "wof:name":"Equi-Massage Inc",
    "wof:placetype":"venue"
},
  "geometry": {"coordinates":[-81.25805099999999,28.637375],"type":"Point"}
}