{
  "type": "Feature",
  "properties": {
    "iso:country":"US",
    "sg:address":"4375 Belvedere Rd",
    "sg:city":"West Palm Beach",
    "sg:classifiers":[
        {
            "category":"Shopping",
            "subcategory":"Department Store",
            "type":"Retail Goods"
        }
    ],
    "sg:phone":"+1 561 242 8889",
    "sg:postcode":"33406",
    "sg:province":"FL",
    "wof:name":"Wal-Mart Supercenter",
    "wof:placetype":"venue"
},
  "geometry": {"coordinates":[-80.108554,26.692342],"type":"Point"}
}