{
  "type": "Feature",
  "properties": {
    "addr:full":"1013 Lucerne Ave Lake Worth FL 33460",
    "addr:housenumber":"1013",
    "addr:postcode":"33460",
    "addr:street":"Lucerne Ave",
    "iso:country":"US",
    "sg:address":"1013 Lucerne Ave",
    "sg:city":"Lake Worth",
    "sg:classifiers":[
        {
            "category":"Professional",
            "subcategory":"Research",
            "type":"Services"
        }
    ],
    "sg:phone":"+1 561 585 5173",
    "sg:postcode":"33460",
    "sg:province":"FL",
    "sg:tags":[
        "development",
        "laboratory"
    ],
    "wof:name":"Research Associates",
    "wof:placetype":"venue"
},
  "geometry": {"coordinates":[-80.05909800000001,26.616599],"type":"Point"}
}