{
  "type": "Feature",
  "properties": {
    "iso:country":"US",
    "sg:address":"417 E 56th St",
    "sg:city":"Hialeah",
    "sg:classifiers":[
        {
            "category":"Restaurant",
            "type":"Food & Drink"
        }
    ],
    "sg:phone":"+1 305 687 9789",
    "sg:postcode":"33013",
    "sg:province":"FL",
    "sg:tags":[
        "eating"
    ],
    "wof:name":"Medinas Restaurant Corp",
    "wof:placetype":"venue"
},
  "geometry": {"coordinates":[-80.273145,25.873601],"type":"Point"}
}