{
  "type": "Feature",
  "properties": {
    "addr:full":"1527 Huntington St Deltona FL 32725",
    "addr:housenumber":"1527",
    "addr:postcode":"32725",
    "addr:street":"Huntington St",
    "iso:country":"US",
    "sg:address":"1527 Huntington St",
    "sg:city":"Deltona",
    "sg:classifiers":[
        {
            "category":"Real Estate",
            "subcategory":"Architect",
            "type":"Services"
        }
    ],
    "sg:phone":"+1 386 789 1501",
    "sg:postcode":"32725",
    "sg:province":"FL",
    "sg:tags":[
        "architects'",
        "specification",
        "construction",
        "builders'",
        "architectural"
    ],
    "wof:name":"Nick Opreanu Aia",
    "wof:placetype":"venue"
},
  "geometry": {"coordinates":[-81.23040899999999,28.912913],"type":"Point"}
}