{
  "type": "Feature",
  "properties": {
    "iso:country":"US",
    "sg:address":"3170 N Federal Hwy",
    "sg:city":"Lighthouse Point",
    "sg:classifiers":[
        {
            "category":"Banks & Credit Unions",
            "subcategory":"Investment Brokerage",
            "type":"Services"
        },
        {
            "category":"Professional",
            "subcategory":"Computer Services",
            "type":"Services"
        }
    ],
    "sg:phone":"+1 954 785 1121",
    "sg:postcode":"33064",
    "sg:province":"FL",
    "sg:tags":[
        "web",
        "financial",
        "consultant",
        "planning",
        "design",
        "internet",
        "page"
    ],
    "wof:name":"Canslim Net Inc",
    "wof:placetype":"venue"
},
  "geometry": {"coordinates":[-80.098096,26.270749],"type":"Point"}
}