{
  "type": "Feature",
  "properties": {
    "iso:country":"US",
    "sg:address":"13214 Palm Beach Blvd",
    "sg:city":"Fort Myers",
    "sg:classifiers":[
        {
            "category":"Home & Garden",
            "subcategory":"Household Appliances",
            "type":"Retail Goods"
        }
    ],
    "sg:phone":"+1 239 693 8863",
    "sg:postcode":"33905",
    "sg:province":"FL",
    "sg:tags":[
        "repair",
        "electrical"
    ],
    "wof:name":"Hobbs Vac Shop Inc",
    "wof:placetype":"venue"
},
  "geometry": {"coordinates":[-81.747394,26.704548],"type":"Point"}
}