{
  "type": "Feature",
  "properties": {
    "addr:full":"2600 SE 1st Ave Ocala FL 34471",
    "addr:housenumber":"2600",
    "addr:postcode":"34471",
    "addr:street":"Se 1St Ave",
    "iso:country":"US",
    "sg:address":"2600 SE 1st Ave",
    "sg:city":"Ocala",
    "sg:classifiers":[
        {
            "category":"Wholesale",
            "subcategory":"Auto Parts",
            "type":"Manufacturing & Wholesale Goods"
        }
    ],
    "sg:phone":"+1 352 351 9330",
    "sg:postcode":"34471",
    "sg:province":"FL",
    "sg:tags":[
        "tire"
    ],
    "wof:name":"Barron's Wholesale Tire Inc",
    "wof:placetype":"venue"
},
  "geometry": {"coordinates":[-82.135232,29.157015],"type":"Point"}
}