{
  "type": "Feature",
  "properties": {
    "addr:full":"8421 SW 44th Pl Davie FL 33328",
    "addr:housenumber":"8421",
    "addr:postcode":"33328",
    "addr:street":"Sw 44Th Pl",
    "iso:country":"US",
    "sg:address":"8421 SW 44th Pl",
    "sg:city":"Davie",
    "sg:classifiers":[
        {
            "category":"Building & Trades",
            "subcategory":"Construction",
            "type":"Services"
        }
    ],
    "sg:phone":"+1 954 214 2575",
    "sg:postcode":"33328",
    "sg:province":"FL",
    "sg:tags":[
        "resurfacing",
        "laying",
        "refinishing",
        "floor"
    ],
    "wof:name":"Custom Flooring Inc",
    "wof:placetype":"venue"
},
  "geometry": {"coordinates":[-80.25857600000001,26.066531],"type":"Point"}
}