{
  "type": "Feature",
  "properties": {
    "addr:full":"16400 Erie Pl Fort Lauderdale FL 33331",
    "addr:housenumber":"16400",
    "addr:postcode":"33331",
    "addr:street":"Erie Pl",
    "iso:country":"US",
    "sg:address":"16400 Erie Pl",
    "sg:city":"Fort Lauderdale",
    "sg:classifiers":[
        {
            "category":"Insurance",
            "subcategory":"Insurance Agent",
            "type":"Services"
        }
    ],
    "sg:phone":"+1 954 252 1874",
    "sg:postcode":"33331",
    "sg:province":"FL",
    "wof:name":"Millennium Health Group Inc",
    "wof:placetype":"venue"
},
  "geometry": {"coordinates":[-80.366601,26.038012],"type":"Point"}
}