{
  "type": "Feature",
  "properties": {
    "iso:country":"US",
    "sg:address":"2106 S Cypress Bend Dr",
    "sg:city":"Pompano Beach",
    "sg:classifiers":[
        {
            "category":"Building & Trades",
            "subcategory":"Electrical",
            "type":"Services"
        }
    ],
    "sg:phone":"+1 954 978 1805",
    "sg:postcode":"33069",
    "sg:province":"FL",
    "sg:tags":[
        "electrical",
        "contractor"
    ],
    "wof:name":"A Sniadowski Electric Inc",
    "wof:placetype":"venue"
},
  "geometry": {"coordinates":[-80.14690400000001,26.217856],"type":"Point"}
}