{
  "type": "Feature",
  "properties": {
    "iso:country":"US",
    "sg:address":"694 Atlantis Rd",
    "sg:city":"Melbourne",
    "sg:classifiers":[
        {
            "category":"Building & Trades",
            "subcategory":"Plumbing",
            "type":"Services"
        }
    ],
    "sg:phone":"+1 321 725 5996",
    "sg:postcode":"32904",
    "sg:province":"FL",
    "sg:tags":[
        "plumbing",
        "contractor"
    ],
    "wof:name":"Space Coast Plumbing Inc",
    "wof:placetype":"venue"
},
  "geometry": {"coordinates":[-80.664214,28.094765],"type":"Point"}
}