{
  "type": "Feature",
  "properties": {
    "iso:country":"US",
    "sg:address":"2320 Running Horse Trl",
    "sg:city":"Saint Cloud",
    "sg:classifiers":[
        {
            "category":"Building & Trades",
            "subcategory":"Landscaping Services",
            "type":"Services"
        }
    ],
    "sg:phone":"+1 407 892 4755",
    "sg:postcode":"34771",
    "sg:province":"FL",
    "wof:name":"T N R Lawn Care",
    "wof:placetype":"venue"
},
  "geometry": {"coordinates":[-81.158227,28.234507],"type":"Point"}
}