{
  "type": "Feature",
  "properties": {
    "addr:full":"878 SE Carnival Ave Port St Lucie FL 34983",
    "addr:housenumber":"878",
    "addr:postcode":"34983",
    "addr:street":"Se Carnival Ave",
    "iso:country":"US",
    "sg:address":"878 SE Carnival Ave",
    "sg:city":"Port St Lucie",
    "sg:classifiers":[
        {
            "category":"Education",
            "subcategory":"Special Training",
            "type":"Public Place"
        }
    ],
    "sg:phone":"+1 772 336 6085",
    "sg:postcode":"34983",
    "sg:province":"FL",
    "sg:tags":[
        "center"
    ],
    "wof:name":"Insight Learning Ctr",
    "wof:placetype":"venue"
},
  "geometry": {"coordinates":[-80.327304,27.30805],"type":"Point"}
}