{
  "type": "Feature",
  "properties": {
    "addr:full":"115 Tropical Shore Way Fort Myers Beach FL 33931",
    "addr:housenumber":"115",
    "addr:postcode":"33931",
    "addr:street":"Tropical Shore Way",
    "iso:country":"US",
    "sg:address":"115 Tropical Shore Way",
    "sg:city":"Fort Myers Beach",
    "sg:classifiers":[
        {
            "category":"Professional",
            "subcategory":"Accounting & Tax Preparation",
            "type":"Services"
        }
    ],
    "sg:phone":"+1 239 765 0606",
    "sg:postcode":"33931",
    "sg:province":"FL",
    "sg:tags":[
        "billing"
    ],
    "wof:name":"Auto Glass Billing Svc",
    "wof:placetype":"venue"
},
  "geometry": {"coordinates":[-81.942228,26.452933],"type":"Point"}
}