{
  "type": "Feature",
  "properties": {
    "addr:full":"4282 Yucatan Cir Port Charlotte FL 33948",
    "addr:housenumber":"4282",
    "addr:postcode":"33948",
    "addr:street":"Yucatan Cir",
    "iso:country":"US",
    "sg:address":"4282 Yucatan Cir",
    "sg:city":"Port Charlotte",
    "sg:classifiers":[
        {
            "category":"Retail",
            "subcategory":"Animal Services",
            "type":"Services"
        }
    ],
    "sg:phone":"+1 941 624 5406",
    "sg:postcode":"33948",
    "sg:province":"FL",
    "sg:tags":[
        "training",
        "dog"
    ],
    "wof:name":"John's K-9 Obedience Training",
    "wof:placetype":"venue"
},
  "geometry": {"coordinates":[-82.137834,26.973534],"type":"Point"}
}