{
  "type": "Feature",
  "properties": {
    "iso:country":"US",
    "sg:address":"2995 NW 17th St",
    "sg:city":"Miami",
    "sg:classifiers":[
        {
            "category":"Shopping",
            "subcategory":"Pharmacy",
            "type":"Retail Goods"
        }
    ],
    "sg:phone":"+1 305 635 1182",
    "sg:postcode":"33125",
    "sg:province":"FL",
    "sg:tags":[
        "drugstore"
    ],
    "wof:name":"La Ganga Discount Pharmacy",
    "wof:placetype":"venue"
},
  "geometry": {"coordinates":[-80.24370999999999,25.790609],"type":"Point"}
}