{
  "type": "Feature",
  "properties": {
    "iso:country":"US",
    "sg:address":"1619 W Snow Ave",
    "sg:city":"Tampa",
    "sg:classifiers":[
        {
            "category":"Shopping",
            "type":"Retail Goods"
        }
    ],
    "sg:phone":"+1 813 250 9890",
    "sg:postcode":"33606",
    "sg:province":"FL",
    "sg:tags":[
        "art",
        "gallery",
        "dealer"
    ],
    "wof:name":"Masterworks Gallery-Hyde Park",
    "wof:placetype":"venue"
},
  "geometry": {"coordinates":[-82.476688,27.9354],"type":"Point"}
}