{
  "type": "Feature",
  "properties": {
    "addr:full":"5020 Scaff Rd Saint Augustine FL 32092",
    "addr:postcode":"5020;32092",
    "addr:street":"Scaff Rd",
    "iso:country":"US",
    "sg:address":"5020 Scaff Rd",
    "sg:city":"Saint Augustine",
    "sg:classifiers":[
        {
            "category":"Building & Trades",
            "subcategory":"Construction",
            "type":"Services"
        }
    ],
    "sg:phone":"+1 904 826 1339",
    "sg:postcode":"32092",
    "sg:province":"FL",
    "sg:tags":[
        "water",
        "treatment"
    ],
    "wof:name":"Runion Untilites",
    "wof:placetype":"venue"
},
  "geometry": {"coordinates":[-81.492491,29.932821],"type":"Point"}
}