{
  "type": "Feature",
  "properties": {
    "iso:country":"US",
    "sg:address":"6123 Sawyer Rd",
    "sg:city":"Sarasota",
    "sg:classifiers":[
        {
            "category":"Building & Trades",
            "subcategory":"Construction",
            "type":"Services"
        }
    ],
    "sg:phone":"+1 941 355 2222",
    "sg:postcode":"34238",
    "sg:province":"FL",
    "sg:tags":[
        "contractor"
    ],
    "wof:name":"Willie Foulks Freight Handling",
    "wof:placetype":"venue"
},
  "geometry": {"coordinates":[-82.488941,27.265208],"type":"Point"}
}