{
  "type": "Feature",
  "properties": {
    "iso:country":"US",
    "sg:address":"2472 Tahoe Cir",
    "sg:city":"Winter Park",
    "sg:classifiers":[
        {
            "category":"Wholesale",
            "subcategory":"Jewelry",
            "type":"Manufacturing & Wholesale Goods"
        }
    ],
    "sg:phone":"+1 407 671 0340",
    "sg:postcode":"32792",
    "sg:province":"FL",
    "sg:tags":[
        "stone"
    ],
    "wof:name":"Golden International",
    "wof:placetype":"venue"
},
  "geometry": {"coordinates":[-81.32060199999999,28.624001],"type":"Point"}
}