{
  "type": "Feature",
  "properties": {
    "iso:country":"US",
    "sg:address":"3856 Catalina Dr",
    "sg:city":"Bradenton",
    "sg:classifiers":[
        {
            "category":"Shopping",
            "subcategory":"Gifts & Souvenirs",
            "type":"Retail Goods"
        }
    ],
    "sg:phone":"+1 941 794 3250",
    "sg:postcode":"34210",
    "sg:province":"FL",
    "wof:name":"Roses Stone",
    "wof:placetype":"venue"
},
  "geometry": {"coordinates":[-82.656721,27.462444],"type":"Point"}
}