{
  "type": "Feature",
  "properties": {
    "addr:full":"2060 51st St Sarasota FL 34234",
    "addr:housenumber":"2060",
    "addr:postcode":"34234",
    "addr:street":"51St St",
    "iso:country":"US",
    "sg:address":"2060 51st St",
    "sg:city":"Sarasota",
    "sg:classifiers":[
        {
            "category":"Wholesale",
            "subcategory":"Construction Materials",
            "type":"Manufacturing & Wholesale Goods"
        }
    ],
    "sg:phone":"+1 941 359 4803",
    "sg:postcode":"34234",
    "sg:province":"FL",
    "sg:tags":[
        "tile"
    ],
    "wof:name":"Blue Heron Tile",
    "wof:placetype":"venue"
},
  "geometry": {"coordinates":[-82.529195,27.377914],"type":"Point"}
}