{
  "type": "Feature",
  "properties": {
    "addr:full":"12179 Maravilla Dr Punta Gorda FL 33955",
    "addr:housenumber":"12179",
    "addr:postcode":"33955",
    "addr:street":"Maravilla Dr",
    "iso:country":"US",
    "sg:address":"12179 Maravilla Dr",
    "sg:city":"Punta Gorda",
    "sg:classifiers":[
        {
            "category":"Building & Trades",
            "subcategory":"Construction",
            "type":"Services"
        }
    ],
    "sg:phone":"+1 941 639 4888",
    "sg:postcode":"33955",
    "sg:province":"FL",
    "sg:tags":[
        "home",
        "builder"
    ],
    "wof:name":"New Homes Now Corp",
    "wof:placetype":"venue"
},
  "geometry": {"coordinates":[-82.000878,26.855065],"type":"Point"}
}