{
  "type": "Feature",
  "properties": {
    "iso:country":"US",
    "sg:address":"47605 State Road 19",
    "sg:city":"Altoona",
    "sg:classifiers":[
        {
            "category":"Building & Trades",
            "subcategory":"Construction",
            "type":"Services"
        }
    ],
    "sg:phone":"+1 352 669 6678",
    "sg:postcode":"32702",
    "sg:province":"FL",
    "sg:tags":[
        "contractor",
        "grading"
    ],
    "wof:name":"Moonlight Tractor Service Inc",
    "wof:placetype":"venue"
},
  "geometry": {"coordinates":[-81.63994099999999,29.041753],"type":"Point"}
}