{
  "type": "Feature",
  "properties": {
    "addr:full":"400 S Collier Blvd Marco Island FL 34145",
    "addr:housenumber":"400;collier blvd",
    "addr:postcode":"34145",
    "addr:street":"S",
    "iso:country":"US",
    "sg:address":"400 S Collier Blvd",
    "sg:city":"Marco Island",
    "sg:classifiers":[
        {
            "category":"Shopping",
            "subcategory":"Jewelry",
            "type":"Retail Goods"
        }
    ],
    "sg:phone":"+1 239 389 0190",
    "sg:postcode":"34145",
    "sg:province":"FL",
    "wof:name":"LBI Inc",
    "wof:placetype":"venue"
},
  "geometry": {"coordinates":[-81.727103,25.924374],"type":"Point"}
}