{
  "type": "Feature",
  "properties": {
    "iso:country":"US",
    "sg:address":"2206 SE Indian St",
    "sg:city":"Stuart",
    "sg:classifiers":[
        {
            "category":"Food & Beverages",
            "subcategory":"Groceries & Convenience Stores",
            "type":"Retail Goods"
        }
    ],
    "sg:phone":"+1 772 781 6900",
    "sg:postcode":"34997",
    "sg:province":"FL",
    "sg:tags":[
        "grocer"
    ],
    "wof:name":"LA Placita",
    "wof:placetype":"venue"
},
  "geometry": {"coordinates":[-80.225786,27.166333],"type":"Point"}
}