{
  "type": "Feature",
  "properties": {
    "iso:country":"US",
    "sg:address":"801 N Congress Ave",
    "sg:city":"Boynton Beach",
    "sg:classifiers":[
        {
            "category":"Shopping",
            "subcategory":"Jewelry",
            "type":"Retail Goods"
        }
    ],
    "sg:phone":"+1 561 752 3833",
    "sg:postcode":"33426",
    "sg:province":"FL",
    "sg:tags":[
        "jeweler"
    ],
    "wof:name":"C Q Link",
    "wof:placetype":"venue"
},
  "geometry": {"coordinates":[-80.09063500000001,26.535646],"type":"Point"}
}