{
  "type": "Feature",
  "properties": {
    "iso:country":"US",
    "sg:address":"1656 Young Ave",
    "sg:city":"Clearwater",
    "sg:classifiers":[
        {
            "category":"Building & Trades",
            "subcategory":"Construction",
            "type":"Services"
        }
    ],
    "sg:phone":"+1 727 507 8988",
    "sg:postcode":"33756",
    "sg:province":"FL",
    "sg:tags":[
        "coping",
        "plastering",
        "tiling",
        "pool",
        "swimming"
    ],
    "sg:website":"www.allpoolanddeck.com",
    "wof:name":"All Pool & Deck Renovations",
    "wof:placetype":"venue"
},
  "geometry": {"coordinates":[-82.78547399999999,27.935777],"type":"Point"}
}