{
  "type": "Feature",
  "properties": {
    "addr:full":"4528 Sandhurst Dr Orlando FL 32817",
    "addr:housenumber":"4528",
    "addr:postcode":"32817",
    "addr:street":"Sandhurst Dr",
    "iso:country":"US",
    "sg:address":"4528 Sandhurst Dr",
    "sg:city":"Orlando",
    "sg:classifiers":[
        {
            "category":"Shopping",
            "subcategory":"Discount & Variety Stores",
            "type":"Retail Goods"
        }
    ],
    "sg:phone":"+1 407 948 3334",
    "sg:postcode":"32817",
    "sg:province":"FL",
    "sg:tags":[
        "merchandising",
        "merchandise"
    ],
    "wof:name":"Hawaiian Kiteworks Inc",
    "wof:placetype":"venue"
},
  "geometry": {"coordinates":[-81.23676399999999,28.603956],"type":"Point"}
}