{
  "type": "Feature",
  "properties": {
    "iso:country":"US",
    "sg:address":"788 Vanderbilt Beach Rd",
    "sg:city":"Naples",
    "sg:classifiers":[
        {
            "category":"Education",
            "subcategory":"Library",
            "type":"Public Place"
        },
        {
            "category":"Government",
            "subcategory":"Office",
            "type":"Public Place"
        }
    ],
    "sg:phone":"+1 239 597 8444",
    "sg:postcode":"34108",
    "sg:province":"FL",
    "sg:tags":[
        "township",
        "government-city",
        "village"
    ],
    "sg:website":"http://www.countryjamnaples.com",
    "wof:name":"Vanderbilt Beach Branch Library",
    "wof:placetype":"venue"
},
  "geometry": {"coordinates":[-81.804169,26.2509],"type":"Point"}
}