{
  "type": "Feature",
  "properties": {
    "iso:country":"US",
    "sg:address":"8313 Boca Glades Blvd E",
    "sg:city":"Boca Raton",
    "sg:classifiers":[
        {
            "category":"Wholesale",
            "subcategory":"Non-durable Goods",
            "type":"Manufacturing & Wholesale Goods"
        }
    ],
    "sg:phone":"+1 561 883 3865",
    "sg:postcode":"33434",
    "sg:province":"FL",
    "wof:name":"Trade Direct Imports Inc",
    "wof:placetype":"venue"
},
  "geometry": {"coordinates":[-80.17708,26.36987],"type":"Point"}
}