{
  "type": "Feature",
  "properties": {
    "addr:full":"109 W Vermont Ave Deland FL 32720",
    "addr:housenumber":"109",
    "addr:postcode":"32720",
    "addr:street":"W Vermont Ave",
    "iso:country":"US",
    "sg:address":"109 W Vermont Ave",
    "sg:city":"Deland",
    "sg:classifiers":[
        {
            "category":"Restaurant",
            "type":"Food & Drink"
        }
    ],
    "sg:phone":"+1 386 736 7780",
    "sg:postcode":"32720",
    "sg:province":"FL",
    "wof:name":"King Neptune Inc",
    "wof:placetype":"venue"
},
  "geometry": {"coordinates":[-81.302924,29.008241],"type":"Point"}
}