{
  "type": "Feature",
  "properties": {
    "addr:full":"7938 Renault Dr S Jacksonville FL 32244",
    "addr:housenumber":"7938",
    "addr:postcode":"32244",
    "addr:street":"Renault Dr S",
    "iso:country":"US",
    "sg:address":"7938 Renault Dr S",
    "sg:city":"Jacksonville",
    "sg:classifiers":[
        {
            "category":"Social Services",
            "type":"Services"
        }
    ],
    "sg:phone":"+1 904 779 4657",
    "sg:postcode":"32244",
    "sg:province":"FL",
    "wof:name":"Florida Mentor",
    "wof:placetype":"venue"
},
  "geometry": {"coordinates":[-81.779129,30.240669],"type":"Point"}
}