{
  "type": "Feature",
  "properties": {
    "iso:country":"US",
    "sg:address":"1197 Betmar Blvd",
    "sg:city":"Fort Myers",
    "sg:classifiers":[
        {
            "category":"Retail",
            "subcategory":"Repair Shop",
            "type":"Services"
        }
    ],
    "sg:phone":"+1 239 707 7145",
    "sg:postcode":"33903",
    "sg:province":"FL",
    "sg:tags":[
        "welding"
    ],
    "wof:name":"G S Installations Inc",
    "wof:placetype":"venue"
},
  "geometry": {"coordinates":[-81.89513700000001,26.666795],"type":"Point"}
}