{
  "type": "Feature",
  "properties": {
    "addr:full":"4300 L B McLeod Rd Orlando FL 32811",
    "addr:housenumber":"4300;b",
    "addr:postcode":"32811",
    "addr:street":"L;Mcleod Rd",
    "iso:country":"US",
    "sg:address":"4300 L B McLeod Rd",
    "sg:city":"Orlando",
    "sg:classifiers":[
        {
            "category":"Shopping",
            "subcategory":"Discount & Variety Stores",
            "type":"Retail Goods"
        }
    ],
    "sg:phone":"+1 407 999 0063",
    "sg:postcode":"32811",
    "sg:province":"FL",
    "wof:name":"Value Dollar Wholesaler",
    "wof:placetype":"venue"
},
  "geometry": {"coordinates":[-81.43421600000001,28.508678],"type":"Point"}
}