{
  "type": "Feature",
  "properties": {
    "iso:country":"US",
    "sg:address":"2554 Oak Trl S",
    "sg:city":"Clearwater",
    "sg:classifiers":[
        {
            "category":"Real Estate",
            "subcategory":"Real Estate Operator",
            "type":"Services"
        }
    ],
    "sg:phone":"+1 727 536 6375",
    "sg:postcode":"33764",
    "sg:province":"FL",
    "sg:tags":[
        "apartment"
    ],
    "sg:website":"www.palmoaks.com",
    "wof:name":"Oaks Apartments",
    "wof:placetype":"venue"
},
  "geometry": {"coordinates":[-82.73324599999999,27.929454],"type":"Point"}
}