{
  "type": "Feature",
  "properties": {
    "addr:full":"6925 Tema Ln Sarasota FL 34241",
    "addr:housenumber":"6925",
    "addr:postcode":"34241",
    "addr:street":"Tema Ln",
    "iso:country":"US",
    "sg:address":"6925 Tema Ln",
    "sg:city":"Sarasota",
    "sg:classifiers":[
        {
            "category":"Real Estate",
            "subcategory":"Real Estate Services",
            "type":"Services"
        },
        {
            "category":"Building & Trades",
            "subcategory":"Cleaning & Sanitation",
            "type":"Services"
        }
    ],
    "sg:phone":"+1 941 822 3463",
    "sg:postcode":"34241",
    "sg:province":"FL",
    "sg:tags":[
        "maintenance",
        "cleaners-interior"
    ],
    "wof:name":"Jordan Williams Lawn Service & Landscaping",
    "wof:placetype":"venue"
},
  "geometry": {"coordinates":[-82.434057,27.295818],"type":"Point"}
}