{
  "type": "Feature",
  "properties": {
    "iso:country":"US",
    "sg:address":"1202 NE Pine Island Rd",
    "sg:city":"Cape Coral",
    "sg:classifiers":[
        {
            "category":"Shopping",
            "subcategory":"Used Merchandise",
            "type":"Retail Goods"
        }
    ],
    "sg:phone":"+1 239 573 9006",
    "sg:postcode":"33909",
    "sg:province":"FL",
    "wof:name":"Consignment Plus",
    "wof:placetype":"venue"
},
  "geometry": {"coordinates":[-81.948592,26.663803],"type":"Point"}
}