{
  "type": "Feature",
  "properties": {
    "addr:full":"1925 Sycamore Dr Orlando FL 32803",
    "addr:housenumber":"1925",
    "addr:postcode":"32803",
    "addr:street":"Sycamore Dr",
    "iso:country":"US",
    "sg:address":"1925 Sycamore Dr",
    "sg:city":"Orlando",
    "sg:classifiers":[
        {
            "category":"Building & Trades",
            "subcategory":"Construction",
            "type":"Services"
        }
    ],
    "sg:phone":"+1 407 644 3672",
    "sg:postcode":"32803",
    "sg:province":"FL",
    "sg:tags":[
        "contractor"
    ],
    "wof:name":"A Beautiful Finish Inc",
    "wof:placetype":"venue"
},
  "geometry": {"coordinates":[-81.34115199999999,28.568751],"type":"Point"}
}