{
  "type": "Feature",
  "properties": {
    "addr:full":"4153 Waikiki Dr Sarasota FL 34241",
    "addr:postcode":"4153;34241",
    "addr:street":"Waikiki Dr",
    "iso:country":"US",
    "sg:address":"4153 Waikiki Dr",
    "sg:city":"Sarasota",
    "sg:classifiers":[
        {
            "category":"Building & Trades",
            "subcategory":"Electrical",
            "type":"Services"
        }
    ],
    "sg:phone":"+1 941 953 5854",
    "sg:postcode":"34241",
    "sg:province":"FL",
    "sg:tags":[
        "lighting",
        "landscape"
    ],
    "sg:website":"www.moon-lighting.net",
    "wof:name":"Moonlighting",
    "wof:placetype":"venue"
},
  "geometry": {"coordinates":[-82.443772,27.294019],"type":"Point"}
}