{
  "type": "Feature",
  "properties": {
    "addr:full":"212 N Disston Ave Tavares FL 32778",
    "addr:housenumber":"212",
    "addr:postcode":"32778",
    "addr:street":"N Disston Ave",
    "iso:country":"US",
    "sg:address":"212 N Disston Ave",
    "sg:city":"Tavares",
    "sg:classifiers":[
        {
            "category":"Shopping",
            "type":"Retail Goods"
        }
    ],
    "sg:phone":"+1 352 343 5997",
    "sg:postcode":"32778",
    "sg:province":"FL",
    "sg:tags":[
        "merchandise"
    ],
    "wof:name":"Clements Critters",
    "wof:placetype":"venue"
},
  "geometry": {"coordinates":[-81.724633,28.803949],"type":"Point"}
}