{
  "type": "Feature",
  "properties": {
    "iso:country":"US",
    "sg:address":"11455 S Orange Blossom Trl",
    "sg:city":"Orlando",
    "sg:classifiers":[
        {
            "category":"Retail",
            "subcategory":"Auto Repair",
            "type":"Services"
        }
    ],
    "sg:phone":"+1 407 251 7600",
    "sg:postcode":"32837",
    "sg:province":"FL",
    "sg:tags":[
        "automobile",
        "co",
        "drive",
        "transporter"
    ],
    "wof:name":"Delta Drivers Svc",
    "wof:placetype":"venue"
},
  "geometry": {"coordinates":[-81.404509,28.39774],"type":"Point"}
}