{
  "type": "Feature",
  "properties": {
    "iso:country":"US",
    "sg:address":"3768 Park Central Blvd N",
    "sg:city":"Pompano Beach",
    "sg:classifiers":[
        {
            "category":"Manufacturing",
            "subcategory":"Tools & Machinery",
            "type":"Manufacturing & Wholesale Goods"
        }
    ],
    "sg:phone":"+1 954 972 7750",
    "sg:postcode":"33064",
    "sg:province":"FL",
    "sg:tags":[
        "use",
        "industrial",
        "for",
        "mfg",
        "personal",
        "devices"
    ],
    "sg:website":"www.airspray.net",
    "wof:name":"Airspray International Inc",
    "wof:placetype":"venue"
},
  "geometry": {"coordinates":[-80.144946,26.266585],"type":"Point"}
}