{
  "type": "Feature",
  "properties": {
    "iso:country":"US",
    "sg:address":"4301 Millenia Blvd",
    "sg:city":"Orlando",
    "sg:classifiers":[
        {
            "category":"Autos & Motor Vehicles",
            "subcategory":"Automobile Sales",
            "type":"Retail Goods"
        },
        {
            "category":"Retail",
            "subcategory":"Auto Repair",
            "type":"Services"
        }
    ],
    "sg:phone":"+1 407 459 8235",
    "sg:postcode":"32839",
    "sg:province":"FL",
    "sg:tags":[
        "car",
        "used",
        "new"
    ],
    "sg:website":"http://orlando.citysearch.com/profile/external/43406446/orlando_fl/mercedes_benz_of_south_orlando.html?publisher=yellowpages&reference_id=1&placement=ypwebsitemip",
    "wof:name":"Mercedes-Benz of South Orlando",
    "wof:placetype":"venue"
},
  "geometry": {"coordinates":[-81.43328099999999,28.48875],"type":"Point"}
}