{
  "type": "Feature",
  "properties": {
    "iso:country":"US",
    "sg:address":"793 Mayport Rd",
    "sg:city":"Atlantic Beach",
    "sg:classifiers":[
        {
            "category":"Freight",
            "type":"Transportation"
        }
    ],
    "sg:phone":"+1 904 247 6767",
    "sg:postcode":"32233",
    "sg:province":"FL",
    "sg:tags":[
        "consultant"
    ],
    "wof:name":"Southern Atlantic Intermodal",
    "wof:placetype":"venue"
},
  "geometry": {"coordinates":[-81.417382,30.32939],"type":"Point"}
}