{
  "type": "Feature",
  "properties": {
    "iso:country":"US",
    "sg:address":"1150 Anastasia Ave",
    "sg:city":"Miami",
    "sg:classifiers":[
        {
            "category":"Sports & Exercise",
            "subcategory":"Tennis Court",
            "type":"Entertainment"
        }
    ],
    "sg:phone":"+1 305 460 5360",
    "sg:postcode":"33134",
    "sg:province":"FL",
    "wof:name":"Biltmore Tennis Center",
    "wof:placetype":"venue"
},
  "geometry": {"coordinates":[-80.278432,25.741498],"type":"Point"}
}