{
  "type": "Feature",
  "properties": {
    "iso:country":"US",
    "sg:address":"265 N Federal Hwy",
    "sg:city":"Deerfield Beach",
    "sg:classifiers":[
        {
            "category":"Wholesale",
            "subcategory":"Wine & Distilled Alcoholic Beverages",
            "type":"Manufacturing & Wholesale Goods"
        }
    ],
    "sg:phone":"+1 954 644 2754",
    "sg:postcode":"33441",
    "sg:province":"FL",
    "sg:tags":[
        "import"
    ],
    "wof:name":"Lolys International  Inc",
    "wof:placetype":"venue"
},
  "geometry": {"coordinates":[-80.09090399999999,26.321857],"type":"Point"}
}