{
  "type": "Feature",
  "properties": {
    "iso:country":"US",
    "sg:address":"13131 N Florida Ave",
    "sg:city":"Tampa",
    "sg:classifiers":[
        {
            "category":"Autos & Motor Vehicles",
            "subcategory":"Automobile Sales",
            "type":"Retail Goods"
        }
    ],
    "sg:phone":"+1 813 931 7200",
    "sg:postcode":"33612",
    "sg:province":"FL",
    "sg:tags":[
        "new",
        "car"
    ],
    "sg:website":"http://www.edmorse.com",
    "wof:name":"Saturn",
    "wof:placetype":"venue"
},
  "geometry": {"coordinates":[-82.45934699999999,28.067163],"type":"Point"}
}