{
  "type": "Feature",
  "properties": {
    "addr:full":"850 Knox McRae Dr Titusville FL 32780",
    "addr:housenumber":"850",
    "addr:postcode":"32780",
    "addr:street":"Knox Mcrae Dr",
    "iso:country":"US",
    "sg:address":"850 Knox McRae Dr",
    "sg:city":"Titusville",
    "sg:classifiers":[
        {
            "category":"Education",
            "subcategory":"School",
            "type":"Public Place"
        }
    ],
    "sg:phone":"+1 321 264 3060",
    "sg:postcode":"32780",
    "sg:province":"FL",
    "wof:name":"Coquina Elementary School",
    "wof:placetype":"venue"
},
  "geometry": {"coordinates":[-80.811144,28.564836],"type":"Point"}
}