{
  "type": "Feature",
  "properties": {
    "addr:full":"4105 Pine Tree Pl Cocoa FL 32926",
    "addr:housenumber":"4105",
    "addr:postcode":"32926",
    "addr:street":"Pine Tree Pl",
    "iso:country":"US",
    "sg:address":"4105 Pine Tree Pl",
    "sg:city":"Cocoa",
    "sg:classifiers":[
        {
            "category":"Manufacturing",
            "subcategory":"Watercraft",
            "type":"Manufacturing & Wholesale Goods"
        }
    ],
    "sg:phone":"+1 321 639 6059",
    "sg:postcode":"32926",
    "sg:province":"FL",
    "sg:tags":[
        "boat"
    ],
    "wof:name":"J B Air Boat Svc",
    "wof:placetype":"venue"
},
  "geometry": {"coordinates":[-80.78936899999999,28.375123],"type":"Point"}
}