{
  "type": "Feature",
  "properties": {
    "iso:country":"US",
    "sg:address":"5970 Phillips Hwy",
    "sg:city":"Jacksonville",
    "sg:classifiers":[
        {
            "category":"Wholesale",
            "subcategory":"Machinery & Supplies",
            "type":"Manufacturing & Wholesale Goods"
        }
    ],
    "sg:phone":"+1 904 737 7119",
    "sg:postcode":"32216",
    "sg:province":"FL",
    "sg:tags":[
        "installs",
        "tool",
        "floor",
        "carpet",
        "covering"
    ],
    "wof:name":"Safer Distributors",
    "wof:placetype":"venue"
},
  "geometry": {"coordinates":[-81.615528,30.262362],"type":"Point"}
}