{
  "type": "Feature",
  "properties": {
    "addr:full":"6451 SW 16th Ter Miami FL 33155",
    "addr:housenumber":"6451",
    "addr:postcode":"33155",
    "addr:street":"Sw 16Th Ter",
    "iso:country":"US",
    "sg:address":"6451 SW 16th Ter",
    "sg:city":"Miami",
    "sg:classifiers":[
        {
            "category":"Banks & Credit Unions",
            "subcategory":"Financial Services",
            "type":"Services"
        }
    ],
    "sg:phone":"+1 305 261 4082",
    "sg:postcode":"33155",
    "sg:province":"FL",
    "sg:tags":[
        "company",
        "holding"
    ],
    "wof:name":"Piedra Holdings LLC",
    "wof:placetype":"venue"
},
  "geometry": {"coordinates":[-80.300748,25.755343],"type":"Point"}
}