{
  "type": "Feature",
  "properties": {
    "iso:country":"US",
    "sg:address":"10319 Autumnwood Dr",
    "sg:city":"Hudson",
    "sg:classifiers":[
        {
            "category":"Professional",
            "subcategory":"Business Services",
            "type":"Services"
        }
    ],
    "sg:phone":"+1 727 869 8431",
    "sg:postcode":"34667",
    "sg:province":"FL",
    "sg:tags":[
        "manufacturer",
        "cleaners-wholesale",
        "vacuum"
    ],
    "wof:name":"Fuller Brush Place",
    "wof:placetype":"venue"
},
  "geometry": {"coordinates":[-82.644307,28.431122],"type":"Point"}
}