{
  "type": "Feature",
  "properties": {
    "iso:country":"US",
    "sg:address":"420 Fisherman St",
    "sg:city":"Opa Locka",
    "sg:classifiers":[
        {
            "category":"Building & Trades",
            "subcategory":"Locksmith",
            "type":"Services"
        }
    ],
    "sg:phone":"+1 786 279 4862",
    "sg:postcode":"33054",
    "sg:province":"FL",
    "sg:tags":[
        "key"
    ],
    "wof:name":"Available Emergency Locksmith On Fisherman St",
    "wof:placetype":"venue"
},
  "geometry": {"coordinates":[-80.254715,25.900455],"type":"Point"}
}