{
  "type": "Feature",
  "properties": {
    "iso:country":"US",
    "sg:address":"6604 Baybrooks Cir",
    "sg:city":"Tampa",
    "sg:classifiers":[
        {
            "category":"Wholesale",
            "subcategory":"Hardware",
            "type":"Manufacturing & Wholesale Goods"
        }
    ],
    "sg:phone":"+1 813 975 0216",
    "sg:postcode":"33617",
    "sg:province":"FL",
    "sg:tags":[
        "plumbing"
    ],
    "wof:name":"Mike Dimaio Sales",
    "wof:placetype":"venue"
},
  "geometry": {"coordinates":[-82.371551,28.052303],"type":"Point"}
}