{
  "type": "Feature",
  "properties": {
    "iso:country":"US",
    "sg:address":"5720 NW 17th Ave",
    "sg:city":"Miami",
    "sg:classifiers":[
        {
            "category":"Shopping",
            "subcategory":"Pharmacy",
            "type":"Retail Goods"
        }
    ],
    "sg:phone":"+1 305 696 2421",
    "sg:postcode":"33142",
    "sg:province":"FL",
    "sg:tags":[
        "drugstore"
    ],
    "wof:name":"Ebony Drugs",
    "wof:placetype":"venue"
},
  "geometry": {"coordinates":[-80.224602,25.8276],"type":"Point"}
}