{
  "type": "Feature",
  "properties": {
    "iso:country":"US",
    "sg:address":"1701 SE Hillmoor Dr",
    "sg:city":"Port St Lucie",
    "sg:classifiers":[
        {
            "category":"Health Services",
            "subcategory":"Doctor",
            "type":"Services"
        }
    ],
    "sg:phone":"+1 772 335 8200",
    "sg:postcode":"34952",
    "sg:province":"FL",
    "sg:tags":[
        "physician",
        "medical",
        "surgeon"
    ],
    "wof:name":"Shamsher Singh MD",
    "wof:placetype":"venue"
},
  "geometry": {"coordinates":[-80.296747,27.28856],"type":"Point"}
}