{
  "type": "Feature",
  "properties": {
    "iso:country":"US",
    "sg:address":"901 W State Road 84",
    "sg:city":"Fort Lauderdale",
    "sg:classifiers":[
        {
            "category":"Bakery",
            "type":"Food & Drink"
        },
        {
            "category":"Coffee & Tea",
            "type":"Food & Drink"
        },
        {
            "category":"Bagels",
            "type":"Food & Drink"
        },
        {
            "category":"Donuts",
            "type":"Food & Drink"
        }
    ],
    "sg:menulink":"http://www.allmenus.com/fl/fort-lauderdale/137966-dunkin-donuts/menu/",
    "sg:phone":"+1 954 463 8512",
    "sg:postcode":"33315",
    "sg:province":"FL",
    "sg:tags":[
        "american",
        "pastry"
    ],
    "wof:name":"Dunkin' Donuts",
    "wof:placetype":"venue"
},
  "geometry": {"coordinates":[-80.153462,26.092526],"type":"Point"}
}