{
  "type": "Feature",
  "properties": {
    "iso:country":"US",
    "sg:address":"12730 New Brittany Blvd",
    "sg:city":"Fort Myers",
    "sg:classifiers":[
        {
            "category":"Real Estate",
            "subcategory":"Architect",
            "type":"Services"
        }
    ],
    "sg:phone":"+1 239 333 1036",
    "sg:postcode":"33907",
    "sg:province":"FL",
    "wof:name":"Homes by Architecnic",
    "wof:placetype":"venue"
},
  "geometry": {"coordinates":[-81.880948,26.557615],"type":"Point"}
}