{
  "type": "Feature",
  "properties": {
    "addr:full":"4220 S Washington Ave Titusville FL 32780",
    "addr:housenumber":"4220",
    "addr:postcode":"32780",
    "addr:street":"S Washington Ave",
    "iso:country":"US",
    "sg:address":"4220 S Washington Ave",
    "sg:city":"Titusville",
    "sg:classifiers":[
        {
            "category":"Shopping",
            "subcategory":"Computers & Home Electronics",
            "type":"Retail Goods"
        }
    ],
    "sg:phone":"+1 321 268 5824",
    "sg:postcode":"32780",
    "sg:province":"FL",
    "sg:tags":[
        "consumer",
        "appliance"
    ],
    "wof:name":"Rex TV",
    "wof:placetype":"venue"
},
  "geometry": {"coordinates":[-80.798586,28.563207],"type":"Point"}
}