{
  "type": "Feature",
  "properties": {
    "iso:country":"US",
    "sg:address":"3718 Cricket Cove Rd E",
    "sg:city":"Jacksonville",
    "sg:classifiers":[
        {
            "category":"Professional",
            "subcategory":"Management & Consulting",
            "type":"Services"
        }
    ],
    "sg:phone":"+1 904 223 8890",
    "sg:postcode":"32224",
    "sg:province":"FL",
    "sg:tags":[
        "consultant",
        "business"
    ],
    "wof:name":"Leadership & Assessment Ctr",
    "wof:placetype":"venue"
},
  "geometry": {"coordinates":[-81.468975,30.279948],"type":"Point"}
}