{
  "type": "Feature",
  "properties": {
    "iso:country":"US",
    "sg:address":"7013 Symmes Rd",
    "sg:city":"Gibsonton",
    "sg:classifiers":[
        {
            "category":"Wholesale",
            "subcategory":"Painting Supplies",
            "type":"Manufacturing & Wholesale Goods"
        }
    ],
    "sg:phone":"+1 813 671 7295",
    "sg:postcode":"33534",
    "sg:province":"FL",
    "sg:tags":[
        "goods-wholesale",
        "art",
        "manufacturer"
    ],
    "wof:name":"Picture Me Portrait",
    "wof:placetype":"venue"
},
  "geometry": {"coordinates":[-82.378614,27.83509],"type":"Point"}
}