{
  "type": "Feature",
  "properties": {
    "addr:full":"200 Early St Niceville FL 32578",
    "addr:housenumber":"200",
    "addr:postcode":"32578",
    "addr:street":"Early St",
    "iso:country":"US",
    "sg:address":"200 Early St",
    "sg:city":"Niceville",
    "sg:classifiers":[
        {
            "category":"Building & Trades",
            "subcategory":"Construction",
            "type":"Services"
        }
    ],
    "sg:phone":"+1 850 729 2023",
    "sg:postcode":"32578",
    "sg:province":"FL",
    "sg:tags":[
        "residential"
    ],
    "wof:name":"Jeffery H Friedline Inc",
    "wof:placetype":"venue"
},
  "geometry": {"coordinates":[-86.498081,30.524935],"type":"Point"}
}