{
  "type": "Feature",
  "properties": {
    "addr:full":"429 W Wade St Trenton FL 32693",
    "addr:housenumber":"429",
    "addr:postcode":"32693",
    "addr:street":"W Wade St",
    "iso:country":"US",
    "sg:address":"429 W Wade St",
    "sg:city":"Trenton",
    "sg:classifiers":[
        {
            "category":"Utilities",
            "subcategory":"Fuel Oil & Lpg",
            "type":"Services"
        }
    ],
    "sg:phone":"+1 352 463 7107",
    "sg:postcode":"32693",
    "sg:province":"FL",
    "sg:tags":[
        "propane",
        "gas"
    ],
    "wof:name":"Ferrellgas",
    "wof:placetype":"venue"
},
  "geometry": {"coordinates":[-82.821744,29.613425],"type":"Point"}
}