{
  "type": "Feature",
  "properties": {
    "addr:full":"840 SW 24th St Fort Lauderdale FL 33315",
    "addr:housenumber":"840",
    "addr:postcode":"33315",
    "addr:street":"Sw 24Th St",
    "iso:country":"US",
    "sg:address":"840 SW 24th St",
    "sg:city":"Fort Lauderdale",
    "sg:classifiers":[
        {
            "category":"Autos & Motor Vehicles",
            "subcategory":"Fuel & Gas Station",
            "type":"Retail Goods"
        }
    ],
    "sg:phone":"+1 954 527 0676",
    "sg:postcode":"33315",
    "sg:province":"FL",
    "sg:tags":[
        "station",
        "gasoline"
    ],
    "wof:name":"ABC Auto Services",
    "wof:placetype":"venue"
},
  "geometry": {"coordinates":[-80.14768599999999,26.092632],"type":"Point"}
}