{
  "type": "Feature",
  "properties": {
    "iso:country":"US",
    "sg:address":"100 S Pine Island Rd",
    "sg:city":"Plantation",
    "sg:classifiers":[
        {
            "category":"Real Estate",
            "subcategory":"Real Estate Services",
            "type":"Services"
        }
    ],
    "sg:phone":"+1 954 318 2782",
    "sg:postcode":"33324",
    "sg:province":"FL",
    "sg:tags":[
        "company",
        "title"
    ],
    "wof:name":"All Title Svc",
    "wof:placetype":"venue"
},
  "geometry": {"coordinates":[-80.263716,26.118279],"type":"Point"}
}