{
  "type": "Feature",
  "properties": {
    "iso:country":"US",
    "sg:address":"880 SW 1st St",
    "sg:city":"Miami",
    "sg:classifiers":[
        {
            "category":"Restaurant",
            "type":"Food & Drink"
        }
    ],
    "sg:phone":"+1 305 325 0501",
    "sg:postcode":"33130",
    "sg:province":"FL",
    "wof:name":"Los Paisanos Export & Import",
    "wof:placetype":"venue"
},
  "geometry": {"coordinates":[-80.20909899999999,25.7728],"type":"Point"}
}