{
  "type": "Feature",
  "properties": {
    "iso:country":"US",
    "sg:address":"4850 Osprey Dr S",
    "sg:city":"Saint Petersburg",
    "sg:classifiers":[
        {
            "category":"Manufacturing",
            "subcategory":"Electronics",
            "type":"Manufacturing & Wholesale Goods"
        }
    ],
    "sg:phone":"+1 727 866 1561",
    "sg:postcode":"33711",
    "sg:province":"FL",
    "sg:tags":[
        "prerecorded",
        "mfg"
    ],
    "wof:name":"IFR Recordings",
    "wof:placetype":"venue"
},
  "geometry": {"coordinates":[-82.69282699999999,27.71964],"type":"Point"}
}