{
  "type": "Feature",
  "properties": {
    "addr:full":"13723 Alesbury Ct Jacksonville FL 32224",
    "addr:housenumber":"13723",
    "addr:postcode":"32224",
    "addr:street":"Alesbury Ct",
    "iso:country":"US",
    "sg:address":"13723 Alesbury Ct",
    "sg:city":"Jacksonville",
    "sg:classifiers":[
        {
            "category":"Shopping",
            "subcategory":"Clothing, Apparel, & Fashions",
            "type":"Retail Goods"
        }
    ],
    "sg:phone":"+1 904 821 0906",
    "sg:postcode":"32224",
    "sg:province":"FL",
    "sg:tags":[
        "lingerie"
    ],
    "wof:name":"SELENA'SSECRET.COM",
    "wof:placetype":"venue"
},
  "geometry": {"coordinates":[-81.46243,30.268803],"type":"Point"}
}