{
  "type": "Feature",
  "properties": {
    "iso:country":"US",
    "sg:address":"7300 N Kendall Dr",
    "sg:city":"Miami",
    "sg:classifiers":[
        {
            "category":"Professional",
            "subcategory":"Engineering",
            "type":"Services"
        }
    ],
    "sg:phone":"+1 305 279 2298",
    "sg:postcode":"33156",
    "sg:province":"FL",
    "sg:tags":[
        "engineer"
    ],
    "sg:website":"www.ekcorp.com",
    "wof:name":"Edwards & Kelcey Inc",
    "wof:placetype":"venue"
},
  "geometry": {"coordinates":[-80.31172100000001,25.688697],"type":"Point"}
}