{
  "type": "Feature",
  "properties": {
    "addr:full":"3671 NE 12th Ave Pompano Beach FL 33064",
    "addr:housenumber":"3671",
    "addr:postcode":"33064",
    "addr:street":"Ne 12Th Ave",
    "iso:country":"US",
    "sg:address":"3671 NE 12th Ave",
    "sg:city":"Pompano Beach",
    "sg:classifiers":[
        {
            "category":"Freight",
            "type":"Transportation"
        }
    ],
    "sg:phone":"+1 954 788 7688",
    "sg:postcode":"33064",
    "sg:province":"FL",
    "sg:tags":[
        "mover"
    ],
    "wof:name":"Brazil Moving Co",
    "wof:placetype":"venue"
},
  "geometry": {"coordinates":[-80.10725100000001,26.276225],"type":"Point"}
}