{
  "type": "Feature",
  "properties": {
    "addr:full":"1500 San Remo Ave Coral Gables FL 33146",
    "addr:housenumber":"1500",
    "addr:postcode":"33146",
    "addr:street":"San Remo Ave",
    "iso:country":"US",
    "sg:address":"1500 San Remo Ave",
    "sg:city":"Coral Gables",
    "sg:classifiers":[
        {
            "category":"Health Services",
            "subcategory":"Clinic",
            "type":"Services"
        }
    ],
    "sg:phone":"+1 305 662 1881",
    "sg:postcode":"33146",
    "sg:province":"FL",
    "sg:tags":[
        "counseling",
        "mental"
    ],
    "wof:name":"Ferber Melanie & Associates",
    "wof:placetype":"venue"
},
  "geometry": {"coordinates":[-80.282303,25.705999],"type":"Point"}
}