{
  "type": "Feature",
  "properties": {
    "iso:country":"US",
    "sg:address":"30530 S Dixie Hwy",
    "sg:city":"Homestead",
    "sg:classifiers":[
        {
            "category":"Cafe",
            "type":"Food & Drink"
        }
    ],
    "sg:menulink":"http://www.allmenus.com/fl/homestead/241501-galindos-cafe-homestead/menu/",
    "sg:phone":"+1 305 242 0333",
    "sg:postcode":"33030",
    "sg:province":"FL",
    "sg:tags":[
        "caribbean"
    ],
    "wof:name":"Galindo's Cafe Homestead",
    "wof:placetype":"venue"
},
  "geometry": {"coordinates":[-80.462462,25.483243],"type":"Point"}
}