{
  "type": "Feature",
  "properties": {
    "iso:country":"US",
    "sg:address":"3750 70th Ave N",
    "sg:city":"Pinellas Park",
    "sg:classifiers":[
        {
            "category":"Building & Trades",
            "subcategory":"Construction",
            "type":"Services"
        }
    ],
    "sg:phone":"+1 727 526 9585",
    "sg:postcode":"33781",
    "sg:province":"FL",
    "sg:tags":[
        "masonry",
        "contractor"
    ],
    "wof:name":"Carr & Son's Masonry Inc",
    "wof:placetype":"venue"
},
  "geometry": {"coordinates":[-82.68573499999999,27.835594],"type":"Point"}
}