{
  "type": "Feature",
  "properties": {
    "iso:country":"US",
    "sg:address":"850 NW Federal Hwy",
    "sg:city":"Stuart",
    "sg:classifiers":[
        {
            "category":"Real Estate",
            "subcategory":"Real Estate Operator",
            "type":"Services"
        }
    ],
    "sg:phone":"+1 772 692 1731",
    "sg:postcode":"34994",
    "sg:province":"FL",
    "sg:tags":[
        "building",
        "parks"
    ],
    "wof:name":"Crexent Business Ctr",
    "wof:placetype":"venue"
},
  "geometry": {"coordinates":[-80.261022,27.2157],"type":"Point"}
}