{
  "type": "Feature",
  "properties": {
    "addr:full":"7890 W Grover Cleveland Blvd Homosassa FL 34446",
    "addr:housenumber":"7890",
    "addr:postcode":"34446",
    "addr:street":"W;Cleveland Blvd",
    "iso:country":"US",
    "sg:address":"7890 W Grover Cleveland Blvd",
    "sg:city":"Homosassa",
    "sg:classifiers":[
        {
            "category":"Organizations",
            "subcategory":"Community Association",
            "type":"Services"
        }
    ],
    "sg:phone":"+1 352 628 1221",
    "sg:postcode":"34446",
    "sg:province":"FL",
    "sg:tags":[
        "fraternal"
    ],
    "wof:name":"Elks Lodge",
    "wof:placetype":"venue"
},
  "geometry": {"coordinates":[-82.56457899999999,28.803784],"type":"Point"}
}