{
  "type": "Feature",
  "properties": {
    "iso:country":"US",
    "sg:address":"2880 34th St N",
    "sg:city":"Saint Petersburg",
    "sg:classifiers":[
        {
            "category":"Restaurant",
            "type":"Food & Drink"
        }
    ],
    "sg:menulink":"http://www.allmenus.com/fl/st-petersburg/36895-a-taste-of-asia/menu/",
    "sg:phone":"+1 727 522 6623",
    "sg:postcode":"33713",
    "sg:province":"FL",
    "sg:tags":[
        "asian",
        "chinese"
    ],
    "wof:name":"A Taste Of Asia",
    "wof:placetype":"venue"
},
  "geometry": {"coordinates":[-82.67958400000001,27.798135],"type":"Point"}
}