{
  "type": "Feature",
  "properties": {
    "iso:country":"US",
    "sg:address":"1426 NE 17th Ct",
    "sg:city":"Fort Lauderdale",
    "sg:classifiers":[
        {
            "category":"Building & Trades",
            "subcategory":"Landscaping Services",
            "type":"Services"
        }
    ],
    "sg:phone":"+1 954 566 5734",
    "sg:postcode":"33305",
    "sg:province":"FL",
    "sg:tags":[
        "landscape"
    ],
    "wof:name":"William Abrahamson Landscaping",
    "wof:placetype":"venue"
},
  "geometry": {"coordinates":[-80.129394,26.150277],"type":"Point"}
}