{
  "type": "Feature",
  "properties": {
    "iso:country":"US",
    "sg:address":"38053 Live Oak Ave",
    "sg:city":"Dade City",
    "sg:classifiers":[
        {
            "category":"Education",
            "subcategory":"Library",
            "type":"Public Place"
        }
    ],
    "sg:phone":"+1 352 521 4399",
    "sg:postcode":"33523",
    "sg:province":"FL",
    "wof:name":"Pasco County Law Library",
    "wof:placetype":"venue"
},
  "geometry": {"coordinates":[-82.187236,28.365125],"type":"Point"}
}