{
  "type": "Feature",
  "properties": {
    "iso:country":"US",
    "sg:address":"637 SW Saint Lucie Cres",
    "sg:city":"Stuart",
    "sg:classifiers":[
        {
            "category":"Building & Trades",
            "subcategory":"Construction",
            "type":"Services"
        }
    ],
    "sg:phone":"+1 772 219 7664",
    "sg:postcode":"34994",
    "sg:province":"FL",
    "sg:tags":[
        "roofing",
        "contractor"
    ],
    "wof:name":"Webster Contracting",
    "wof:placetype":"venue"
},
  "geometry": {"coordinates":[-80.25901500000001,27.194949],"type":"Point"}
}