{
  "type": "Feature",
  "properties": {
    "iso:country":"US",
    "sg:address":"1010 W Kennedy Blvd",
    "sg:city":"Tampa",
    "sg:classifiers":[
        {
            "category":"Retail",
            "subcategory":"Auto Repair",
            "type":"Services"
        }
    ],
    "sg:phone":"+1 813 228 9467",
    "sg:postcode":"33606",
    "sg:province":"FL",
    "sg:tags":[
        "repairing",
        "automobile"
    ],
    "wof:name":"Don Olson Tire & Auto Ctr",
    "wof:placetype":"venue"
},
  "geometry": {"coordinates":[-82.47058,27.94464],"type":"Point"}
}