{
  "type": "Feature",
  "properties": {
    "addr:full":"1959 Chocktaw Trl Middleburg FL 32068",
    "addr:housenumber":"1959",
    "addr:postcode":"32068",
    "addr:street":"Chocktaw Trl",
    "iso:country":"US",
    "sg:address":"1959 Chocktaw Trl",
    "sg:city":"Middleburg",
    "sg:classifiers":[
        {
            "category":"Organizations",
            "subcategory":"Community Association",
            "type":"Services"
        }
    ],
    "sg:phone":"+1 904 282 3157",
    "sg:postcode":"32068",
    "sg:province":"FL",
    "wof:name":"First Kappa Group Inc",
    "wof:placetype":"venue"
},
  "geometry": {"coordinates":[-81.804895,30.098519],"type":"Point"}
}