{
  "type": "Feature",
  "properties": {
    "addr:full":"2012 Eagle Dr West Palm Beach FL 33409",
    "addr:housenumber":"2012",
    "addr:postcode":"33409",
    "addr:street":"Eagle Dr",
    "iso:country":"US",
    "sg:address":"2012 Eagle Dr",
    "sg:city":"West Palm Beach",
    "sg:classifiers":[
        {
            "category":"Professional",
            "subcategory":"Computer Services",
            "type":"Services"
        }
    ],
    "sg:phone":"+1 561 683 0632",
    "sg:postcode":"33409",
    "sg:province":"FL",
    "sg:tags":[
        "datum"
    ],
    "wof:name":"Cypherware Inc",
    "wof:placetype":"venue"
},
  "geometry": {"coordinates":[-80.103281,26.698576],"type":"Point"}
}