{
  "type": "Feature",
  "properties": {
    "addr:full":"1655 W 49th St Ste 1200 Hialeah FL 33012",
    "addr:housenumber":"1655",
    "addr:postcode":"33012",
    "addr:street":"W 49Th St Ste 1200",
    "iso:country":"US",
    "sg:address":"1655 W 49th St Ste 1200",
    "sg:city":"Hialeah",
    "sg:classifiers":[
        {
            "category":"Shopping",
            "subcategory":"Department Store",
            "type":"Retail Goods"
        },
        {
            "category":"Shopping",
            "subcategory":"Beauty & Cosmetics",
            "type":"Retail Goods"
        },
        {
            "category":"Home & Garden",
            "subcategory":"Home Furnishings",
            "type":"Retail Goods"
        },
        {
            "category":"Shopping",
            "type":"Retail Goods"
        },
        {
            "category":"Shopping",
            "subcategory":"Catalog Store",
            "type":"Retail Goods"
        },
        {
            "category":"Professional",
            "subcategory":"Art Services",
            "type":"Services"
        },
        {
            "category":"Shopping",
            "subcategory":"Shoes",
            "type":"Retail Goods"
        },
        {
            "category":"Shopping",
            "subcategory":"Jewelry",
            "type":"Retail Goods"
        }
    ],
    "sg:phone":"+1 866 761 1527",
    "sg:postcode":"33012",
    "sg:province":"FL",
    "sg:tags":[
        "draperies",
        "designer",
        "vertical",
        "supply",
        "merchandise",
        "blinds-venetian",
        "jeweler",
        "equipment",
        "window",
        "interior",
        "treatment",
        "housewares",
        "curtain",
        "showroom",
        "decorator"
    ],
    "sg:website":"http://miami.citysearch.com/profile/external/2434356/hialeah_fl/jcpenney_custom_decorating.html?publisher=yellowpages&reference_id=1&placement=ypwebsitemip",
    "wof:name":"JCPenney Custom Decorating",
    "wof:placetype":"venue"
},
  "geometry": {"coordinates":[-80.316863,25.866662],"type":"Point"}
}