{
  "type": "Feature",
  "properties": {
    "iso:country":"US",
    "sg:address":"1526 NW 49th St",
    "sg:city":"Miami",
    "sg:classifiers":[
        {
            "category":"Personal",
            "subcategory":"Beauty Salon",
            "type":"Services"
        }
    ],
    "sg:phone":"+1 305 823 6173",
    "sg:postcode":"33142",
    "sg:province":"FL",
    "sg:tags":[
        "shop"
    ],
    "wof:name":"Hair By Zonia",
    "wof:placetype":"venue"
},
  "geometry": {"coordinates":[-80.222262,25.819802],"type":"Point"}
}