{
  "type": "Feature",
  "properties": {
    "addr:full":"6920 Pine Forest Rd Pensacola FL 32526",
    "addr:housenumber":"6920",
    "addr:postcode":"32526",
    "addr:street":"Pine Forest Rd",
    "iso:country":"US",
    "sg:address":"6920 Pine Forest Rd",
    "sg:city":"Pensacola",
    "sg:classifiers":[
        {
            "category":"Manufacturing",
            "subcategory":"Chemicals & Compounds",
            "type":"Manufacturing & Wholesale Goods"
        },
        {
            "category":"Building & Trades",
            "subcategory":"Pest Control",
            "type":"Services"
        }
    ],
    "sg:phone":"+1 850 944 4567",
    "sg:postcode":"32526",
    "sg:province":"FL",
    "sg:tags":[
        "equipment",
        "supply"
    ],
    "sg:website":"http://www.pestproducts.com",
    "wof:name":"Do It Yourself Pest Control",
    "wof:placetype":"venue"
},
  "geometry": {"coordinates":[-87.306476,30.485391],"type":"Point"}
}