{
  "type": "Feature",
  "properties": {
    "addr:full":"3245 Stanley Dr Saint Augustine FL 32092",
    "addr:housenumber":"3245",
    "addr:postcode":"32092",
    "addr:street":"Stanley Dr",
    "iso:country":"US",
    "sg:address":"3245 Stanley Dr",
    "sg:city":"Saint Augustine",
    "sg:classifiers":[
        {
            "category":"Sports & Exercise",
            "subcategory":"Bowling",
            "type":"Entertainment"
        }
    ],
    "sg:phone":"+1 904 471 3565",
    "sg:postcode":"32092",
    "sg:province":"FL",
    "sg:tags":[
        "alley"
    ],
    "wof:name":"Anastasia Bowling Lane Corp",
    "wof:placetype":"venue"
},
  "geometry": {"coordinates":[-81.49271899999999,29.941158],"type":"Point"}
}