{
  "type": "Feature",
  "properties": {
    "iso:country":"US",
    "sg:address":"5020 Baggett Pl",
    "sg:city":"Cocoa",
    "sg:classifiers":[
        {
            "category":"Shopping",
            "subcategory":"Gifts & Souvenirs",
            "type":"Retail Goods"
        }
    ],
    "sg:phone":"+1 321 633 0903",
    "sg:postcode":"32926",
    "sg:province":"FL",
    "wof:name":"Showcase Gifts",
    "wof:placetype":"venue"
},
  "geometry": {"coordinates":[-80.806631,28.365196],"type":"Point"}
}