{
  "type": "Feature",
  "properties": {
    "iso:country":"US",
    "sg:address":"1883 Church St",
    "sg:city":"West Palm Beach",
    "sg:classifiers":[
        {
            "category":"Manufacturing",
            "subcategory":"Rubber & Plastics",
            "type":"Manufacturing & Wholesale Goods"
        }
    ],
    "sg:phone":"+1 561 697 0040",
    "sg:postcode":"33409",
    "sg:province":"FL",
    "sg:tags":[
        "product",
        "mfg"
    ],
    "sg:website":"www.wpbplastics.com",
    "wof:name":"West Palm Beach Plastics Inc",
    "wof:placetype":"venue"
},
  "geometry": {"coordinates":[-80.08241599999999,26.705226],"type":"Point"}
}