{
  "type": "Feature",
  "properties": {
    "addr:full":"8890 W Oakland Park Blvd Sunrise FL 33351",
    "addr:housenumber":"8890",
    "addr:postcode":"33351",
    "addr:street":"W Oakland Park Blvd",
    "iso:country":"US",
    "sg:address":"8890 W Oakland Park Blvd",
    "sg:city":"Sunrise",
    "sg:classifiers":[
        {
            "category":"Health Services",
            "subcategory":"Doctor",
            "type":"Services"
        },
        {
            "category":"Health Services",
            "subcategory":"Clinic",
            "type":"Services"
        },
        {
            "category":"Education",
            "subcategory":"Kindergarten",
            "type":"Public Place"
        }
    ],
    "sg:phone":"+1 954 742 3536",
    "sg:postcode":"33351",
    "sg:province":"FL",
    "sg:tags":[
        "physician",
        "oncology",
        "birth",
        "family",
        "information",
        "gynecology",
        "surgeons",
        "parenting-centers",
        "planning",
        "obstetrics",
        "surgeon",
        "gynecologic"
    ],
    "sg:website":"http://www.allfemalehealthcare.com",
    "wof:name":"All Female Health Care",
    "wof:placetype":"venue"
},
  "geometry": {"coordinates":[-80.268513,26.168221],"type":"Point"}
}