{
  "type": "Feature",
  "properties": {
    "iso:country":"US",
    "sg:address":"11205 Gulf Blvd",
    "sg:city":"Treasure Island",
    "sg:classifiers":[
        {
            "category":"Travel",
            "subcategory":"Hotels & Motels",
            "type":"Entertainment"
        }
    ],
    "sg:phone":"+1 727 367 1939",
    "sg:postcode":"33706",
    "sg:province":"FL",
    "wof:name":"Satellite Motel",
    "wof:placetype":"venue"
},
  "geometry": {"coordinates":[-82.774726,27.774489],"type":"Point"}
}