{
  "type": "Feature",
  "properties": {
    "iso:country":"US",
    "sg:address":"8708 Cortez Rd W",
    "sg:city":"Bradenton",
    "sg:classifiers":[
        {
            "category":"Home & Garden",
            "subcategory":"Garden Supply",
            "type":"Retail Goods"
        }
    ],
    "sg:phone":"+1 941 792 9099",
    "sg:postcode":"34210",
    "sg:province":"FL",
    "sg:tags":[
        "landscaping",
        "equipment"
    ],
    "wof:name":"Landscaper's Advantage Inc",
    "wof:placetype":"venue"
},
  "geometry": {"coordinates":[-82.65655099999999,27.46186],"type":"Point"}
}