{
  "type": "Feature",
  "properties": {
    "addr:full":"104 N Commonwealth Ave Polk City FL 33868",
    "addr:housenumber":"104",
    "addr:postcode":"33868",
    "addr:street":"N Commonwealth Ave",
    "iso:country":"US",
    "sg:address":"104 N Commonwealth Ave",
    "sg:city":"Polk City",
    "sg:classifiers":[
        {
            "category":"Restaurant",
            "type":"Food & Drink"
        }
    ],
    "sg:menulink":"http://www.allmenus.com/fl/haines-city/82165-dominos-pizza/menu/",
    "sg:phone":"+1 863 984 6644",
    "sg:postcode":"33868",
    "sg:province":"FL",
    "sg:tags":[
        "american",
        "wing",
        "pizza"
    ],
    "wof:name":"Domino's Pizza",
    "wof:placetype":"venue"
},
  "geometry": {"coordinates":[-81.827225,28.179318],"type":"Point"}
}