{
  "type": "Feature",
  "properties": {
    "iso:country":"US",
    "sg:address":"139 Clearlake Rd",
    "sg:city":"Cocoa",
    "sg:classifiers":[
        {
            "category":"Building & Trades",
            "subcategory":"Construction",
            "type":"Services"
        }
    ],
    "sg:phone":"+1 321 639 0088",
    "sg:postcode":"32922",
    "sg:province":"FL",
    "sg:tags":[
        "paving",
        "contractor"
    ],
    "wof:name":"All Pave Inc",
    "wof:placetype":"venue"
},
  "geometry": {"coordinates":[-80.755033,28.349492],"type":"Point"}
}