{
  "type": "Feature",
  "properties": {
    "iso:country":"US",
    "sg:address":"8012 Baby Farm Rd",
    "sg:city":"Tallahassee",
    "sg:classifiers":[
        {
            "category":"Building & Trades",
            "subcategory":"Construction",
            "type":"Services"
        }
    ],
    "sg:phone":"+1 850 575 6775",
    "sg:postcode":"32310",
    "sg:province":"FL",
    "sg:tags":[
        "equipment",
        "station"
    ],
    "wof:name":"Larry's Pump Svc",
    "wof:placetype":"venue"
},
  "geometry": {"coordinates":[-84.413709,30.434774],"type":"Point"}
}