{
  "type": "Feature",
  "properties": {
    "addr:full":"1219 S 66th St Tampa FL 33619",
    "addr:housenumber":"1219",
    "addr:postcode":"33619",
    "addr:street":"S 66Th St",
    "iso:country":"US",
    "sg:address":"1219 S 66th St",
    "sg:city":"Tampa",
    "sg:classifiers":[
        {
            "category":"Manufacturing",
            "subcategory":"Pottery",
            "type":"Manufacturing & Wholesale Goods"
        }
    ],
    "sg:phone":"+1 813 621 4608",
    "sg:postcode":"33619",
    "sg:province":"FL",
    "sg:tags":[
        "product",
        "mfg"
    ],
    "wof:name":"Easy Miracle Casting Inc",
    "wof:placetype":"venue"
},
  "geometry": {"coordinates":[-82.381022,27.934406],"type":"Point"}
}