{
  "type": "Feature",
  "properties": {
    "iso:country":"US",
    "sg:address":"1136 Settlers Loop",
    "sg:city":"Geneva",
    "sg:phone":"+1 407 392 3092",
    "sg:postcode":"32732",
    "sg:province":"FL",
    "wof:name":"1a1 Lock Smith",
    "wof:placetype":"venue"
},
  "geometry": {"coordinates":[-81.089691,28.763969],"type":"Point"}
}