{
  "type": "Feature",
  "properties": {
    "addr:full":"1717 Ave del Sol Boca Raton FL 33432",
    "addr:postcode":"33432",
    "addr:street":"1717 Ave Del Sol",
    "iso:country":"US",
    "sg:address":"1717 Ave del Sol",
    "sg:city":"Boca Raton",
    "sg:classifiers":[
        {
            "category":"Home & Garden",
            "subcategory":"Building Materials",
            "type":"Retail Goods"
        }
    ],
    "sg:phone":"+1 561 368 0117",
    "sg:postcode":"33432",
    "sg:province":"FL",
    "sg:tags":[
        "plumbing",
        "fixture",
        "supply"
    ],
    "wof:name":"Frajon Valves Inc",
    "wof:placetype":"venue"
},
  "geometry": {"coordinates":[-80.08878199999999,26.366882],"type":"Point"}
}