{
  "type": "Feature",
  "properties": {
    "addr:full":"9045 SE 35th Ct Ocala FL 34480",
    "addr:housenumber":"9045",
    "addr:postcode":"34480",
    "addr:street":"Se 35Th Ct",
    "iso:country":"US",
    "sg:address":"9045 SE 35th Ct",
    "sg:city":"Ocala",
    "sg:classifiers":[
        {
            "category":"Home & Garden",
            "subcategory":"Building Materials",
            "type":"Retail Goods"
        }
    ],
    "sg:phone":"+1 352 427 5545",
    "sg:postcode":"34480",
    "sg:province":"FL",
    "sg:tags":[
        "windows"
    ],
    "wof:name":"Whitson's Window Installation",
    "wof:placetype":"venue"
},
  "geometry": {"coordinates":[-82.08738200000001,29.090521],"type":"Point"}
}