{
  "type": "Feature",
  "properties": {
    "addr:full":"5502 Ashley Pkwy Sarasota FL 34241",
    "addr:housenumber":"5502",
    "addr:postcode":"34241",
    "addr:street":"Ashley Pkwy",
    "iso:country":"US",
    "sg:address":"5502 Ashley Pkwy",
    "sg:city":"Sarasota",
    "sg:classifiers":[
        {
            "category":"Professional",
            "subcategory":"Management & Consulting",
            "type":"Services"
        }
    ],
    "sg:phone":"+1 941 922 9294",
    "sg:postcode":"34241",
    "sg:province":"FL",
    "wof:name":"Cabot Management Grocery Co",
    "wof:placetype":"venue"
},
  "geometry": {"coordinates":[-82.43723199999999,27.276504],"type":"Point"}
}