{
  "type": "Feature",
  "properties": {
    "addr:full":"219 Flagler Ave New Smyrna Beach FL 32169",
    "addr:housenumber":"219",
    "addr:postcode":"32169",
    "addr:street":"Flagler Ave",
    "iso:country":"US",
    "sg:address":"219 Flagler Ave",
    "sg:city":"New Smyrna Beach",
    "sg:classifiers":[
        {
            "category":"Personal",
            "subcategory":"Beauty Salon",
            "type":"Services"
        }
    ],
    "sg:phone":"+1 386 427 2233",
    "sg:postcode":"32169",
    "sg:province":"FL",
    "sg:tags":[
        "shop",
        "barber"
    ],
    "wof:name":"Hair Stop",
    "wof:placetype":"venue"
},
  "geometry": {"coordinates":[-80.90109099999999,29.038471],"type":"Point"}
}