{
  "type": "Feature",
  "properties": {
    "addr:full":"2325 Plantation Lakes Dr Saint Augustine FL 32084",
    "addr:housenumber":"2325",
    "addr:postcode":"32084",
    "addr:street":"Plantation Lakes Dr",
    "iso:country":"US",
    "sg:address":"2325 Plantation Lakes Dr",
    "sg:city":"Saint Augustine",
    "sg:classifiers":[
        {
            "category":"Manufacturing",
            "subcategory":"Signs",
            "type":"Manufacturing & Wholesale Goods"
        }
    ],
    "sg:phone":"+1 904 825 2170",
    "sg:postcode":"32084",
    "sg:province":"FL",
    "sg:tags":[
        "specialty",
        "mfg"
    ],
    "wof:name":"Neon Displays",
    "wof:placetype":"venue"
},
  "geometry": {"coordinates":[-81.36787699999999,29.853919],"type":"Point"}
}