{
  "type": "Feature",
  "properties": {
    "iso:country":"US",
    "sg:address":"5400 NW 16th St",
    "sg:city":"Fort Lauderdale",
    "sg:classifiers":[
        {
            "category":"Wholesale",
            "subcategory":"Non-durable Goods",
            "type":"Manufacturing & Wholesale Goods"
        }
    ],
    "sg:phone":"+1 954 717 2927",
    "sg:postcode":"33313",
    "sg:province":"FL",
    "wof:name":"Aj Distributor",
    "wof:placetype":"venue"
},
  "geometry": {"coordinates":[-80.220538,26.144058],"type":"Point"}
}