{
  "type": "Feature",
  "properties": {
    "iso:country":"US",
    "sg:address":"1712 Amberwynd Cir",
    "sg:city":"Palmetto",
    "sg:classifiers":[
        {
            "category":"Building & Trades",
            "subcategory":"Landscaping Services",
            "type":"Services"
        }
    ],
    "sg:phone":"+1 941 920 2225",
    "sg:postcode":"34221",
    "sg:province":"FL",
    "wof:name":"Florida Premier Turf",
    "wof:placetype":"venue"
},
  "geometry": {"coordinates":[-82.616103,27.530504],"type":"Point"}
}