{
  "type": "Feature",
  "properties": {
    "iso:country":"US",
    "sg:address":"87 W Main St",
    "sg:city":"Apopka",
    "sg:classifiers":[
        {
            "category":"Banks & Credit Unions",
            "subcategory":"Bank",
            "type":"Services"
        }
    ],
    "sg:phone":"+1 407 886 3279",
    "sg:postcode":"32757",
    "sg:province":"FL",
    "sg:tags":[
        "depository",
        "banking"
    ],
    "wof:name":"Quick Cash",
    "wof:placetype":"venue"
},
  "geometry": {"coordinates":[-81.679508,28.807336],"type":"Point"}
}