{
  "type": "Feature",
  "properties": {
    "addr:full":"870 N Cocoa Blvd Cocoa FL 32922",
    "addr:housenumber":"870",
    "addr:postcode":"32922",
    "addr:street":"N Cocoa Blvd",
    "iso:country":"US",
    "sg:address":"870 N Cocoa Blvd",
    "sg:city":"Cocoa",
    "sg:classifiers":[
        {
            "category":"Freight",
            "type":"Transportation"
        }
    ],
    "sg:phone":"+1 321 637 1053",
    "sg:postcode":"32922",
    "sg:province":"FL",
    "sg:tags":[
        "courier"
    ],
    "wof:name":"HFH Inc",
    "wof:placetype":"venue"
},
  "geometry": {"coordinates":[-80.738527,28.377944],"type":"Point"}
}