{
  "type": "Feature",
  "properties": {
    "addr:full":"18634 Commonwealth Ave Orlando FL 32820",
    "addr:housenumber":"18634",
    "addr:postcode":"32820",
    "addr:street":"Commonwealth Ave",
    "iso:country":"US",
    "sg:address":"18634 Commonwealth Ave",
    "sg:city":"Orlando",
    "sg:classifiers":[
        {
            "category":"Building & Trades",
            "subcategory":"Construction",
            "type":"Services"
        }
    ],
    "sg:phone":"+1 407 568 0356",
    "sg:postcode":"32820",
    "sg:province":"FL",
    "sg:tags":[
        "hanging",
        "contractor"
    ],
    "wof:name":"Chauvin Painting",
    "wof:placetype":"venue"
},
  "geometry": {"coordinates":[-81.100931,28.554651],"type":"Point"}
}