{
  "type": "Feature",
  "properties": {
    "iso:country":"US",
    "sg:address":"350 Bus Park Way",
    "sg:city":"Royal Palm Beach",
    "sg:classifiers":[
        {
            "category":"Manufacturing",
            "subcategory":"Signs",
            "type":"Manufacturing & Wholesale Goods"
        }
    ],
    "sg:phone":"+1 561 204 4222",
    "sg:postcode":"33411",
    "sg:province":"FL",
    "sg:tags":[
        "advertising",
        "specialty"
    ],
    "wof:name":"A Plus Signs LTD",
    "wof:placetype":"venue"
},
  "geometry": {"coordinates":[-80.206461,26.699416],"type":"Point"}
}