{
  "type": "Feature",
  "properties": {
    "iso:country":"US",
    "sg:address":"1837 S Dixie Hwy",
    "sg:city":"Pompano Beach",
    "sg:classifiers":[
        {
            "category":"Autos & Motor Vehicles",
            "subcategory":"Boat Sales",
            "type":"Retail Goods"
        }
    ],
    "sg:phone":"+1 954 941 8055",
    "sg:postcode":"33060",
    "sg:province":"FL",
    "wof:name":"Marine Canvas America",
    "wof:placetype":"venue"
},
  "geometry": {"coordinates":[-80.132469,26.210404],"type":"Point"}
}