{
  "type": "Feature",
  "properties": {
    "addr:full":"2911 Vineland Rd Kissimmee FL 34746",
    "addr:housenumber":"2911",
    "addr:postcode":"34746",
    "addr:street":"Vineland Rd",
    "iso:country":"US",
    "sg:address":"2911 Vineland Rd",
    "sg:city":"Kissimmee",
    "sg:classifiers":[
        {
            "category":"Restaurant",
            "type":"Food & Drink"
        }
    ],
    "sg:menulink":"http://www.allmenus.com/fl/kissimmee/44532-smokey-bones/menu/",
    "sg:phone":"+1 407 397 7102",
    "sg:postcode":"34746",
    "sg:province":"FL",
    "sg:tags":[
        "barbecue",
        "american"
    ],
    "wof:name":"Smokey Bones",
    "wof:placetype":"venue"
},
  "geometry": {"coordinates":[-81.476156,28.333717],"type":"Point"}
}