{
  "type": "Feature",
  "properties": {
    "iso:country":"US",
    "sg:address":"609 Cherry St",
    "sg:city":"Panama City",
    "sg:classifiers":[
        {
            "category":"Building & Trades",
            "subcategory":"Construction",
            "type":"Services"
        }
    ],
    "sg:phone":"+1 850 769 7909",
    "sg:postcode":"32401",
    "sg:province":"FL",
    "sg:tags":[
        "contractor"
    ],
    "wof:name":"Paragon Plastering Inc",
    "wof:placetype":"venue"
},
  "geometry": {"coordinates":[-85.65057299999999,30.146],"type":"Point"}
}