{
  "type": "Feature",
  "properties": {
    "addr:full":"15310 Cannongate Dr Fort Myers FL 33912",
    "addr:housenumber":"15310",
    "addr:postcode":"33912",
    "addr:street":"Cannongate Dr",
    "iso:country":"US",
    "sg:address":"15310 Cannongate Dr",
    "sg:city":"Fort Myers",
    "sg:classifiers":[
        {
            "category":"Autos & Motor Vehicles",
            "subcategory":"Automobile Sales",
            "type":"Retail Goods"
        }
    ],
    "sg:phone":"+1 239 768 3530",
    "sg:postcode":"33912",
    "sg:province":"FL",
    "sg:tags":[
        "performance",
        "race",
        "dealer"
    ],
    "wof:name":"Simulcast Racing Network",
    "wof:placetype":"venue"
},
  "geometry": {"coordinates":[-81.81210900000001,26.520528],"type":"Point"}
}