{
  "type": "Feature",
  "properties": {
    "addr:full":"2650 59th St Sarasota FL 34243",
    "addr:housenumber":"2650",
    "addr:postcode":"34243",
    "addr:street":"59Th St",
    "iso:country":"US",
    "sg:address":"2650 59th St",
    "sg:city":"Sarasota",
    "sg:classifiers":[
        {
            "category":"Building & Trades",
            "subcategory":"Construction",
            "type":"Services"
        }
    ],
    "sg:phone":"+1 941 359 9553",
    "sg:postcode":"34243",
    "sg:province":"FL",
    "sg:tags":[
        "specializing",
        "work",
        "painting",
        "painter",
        "contractor"
    ],
    "wof:name":"Progressive Painting Inc",
    "wof:placetype":"venue"
},
  "geometry": {"coordinates":[-82.51894299999999,27.385087],"type":"Point"}
}