{
  "type": "Feature",
  "properties": {
    "iso:country":"US",
    "sg:address":"7911 NW 72nd Ave",
    "sg:city":"Medley",
    "sg:classifiers":[
        {
            "category":"Manufacturing",
            "subcategory":"Printing",
            "type":"Manufacturing & Wholesale Goods"
        }
    ],
    "sg:phone":"+1 305 888 6951",
    "sg:postcode":"33166",
    "sg:province":"FL",
    "sg:tags":[
        "screen"
    ],
    "wof:name":"Red Hot Trends Inc",
    "wof:placetype":"venue"
},
  "geometry": {"coordinates":[-80.314283,25.846408],"type":"Point"}
}