{
  "type": "Feature",
  "properties": {
    "iso:country":"US",
    "sg:address":"110 SW 96th Ave",
    "sg:city":"Fort Lauderdale",
    "sg:classifiers":[
        {
            "category":"Building & Trades",
            "subcategory":"Construction",
            "type":"Services"
        }
    ],
    "sg:phone":"+1 954 351 5974",
    "sg:postcode":"33324",
    "sg:province":"FL",
    "sg:tags":[
        "house"
    ],
    "wof:name":"Millani Construction",
    "wof:placetype":"venue"
},
  "geometry": {"coordinates":[-80.273465,26.006513],"type":"Point"}
}