{
  "type": "Feature",
  "properties": {
    "addr:full":"17728 US Hwy 41 Brooksville FL 34610",
    "addr:housenumber":"17728",
    "addr:postcode":"34610",
    "addr:street":"Us Hwy 41",
    "iso:country":"US",
    "sg:address":"17728 US Hwy 41",
    "sg:city":"Brooksville",
    "sg:classifiers":[
        {
            "category":"Building & Trades",
            "subcategory":"Construction",
            "type":"Services"
        }
    ],
    "sg:phone":"+1 352 796 1631",
    "sg:postcode":"34610",
    "sg:province":"FL",
    "sg:tags":[
        "underground",
        "contractor",
        "paving",
        "asphalt",
        "utility"
    ],
    "wof:name":"Overstreet Paving Co",
    "wof:placetype":"venue"
},
  "geometry": {"coordinates":[-82.472765,28.41367],"type":"Point"}
}