{
  "type": "Feature",
  "properties": {
    "addr:full":"618 N Crystal Park Ter Crystal River FL 34429",
    "addr:housenumber":"618",
    "addr:postcode":"34429",
    "addr:street":"N Crystal Park Ter",
    "iso:country":"US",
    "sg:address":"618 N Crystal Park Ter",
    "sg:city":"Crystal River",
    "sg:classifiers":[
        {
            "category":"Restaurant",
            "type":"Food & Drink"
        }
    ],
    "sg:phone":"+1 352 795 5445",
    "sg:postcode":"34429",
    "sg:province":"FL",
    "wof:name":"China First",
    "wof:placetype":"venue"
},
  "geometry": {"coordinates":[-82.580623,28.868792],"type":"Point"}
}