{
  "type": "Feature",
  "properties": {
    "iso:country":"US",
    "sg:address":"5602 Lake Point Dr",
    "sg:city":"Lakeland",
    "sg:classifiers":[
        {
            "category":"Social Services",
            "type":"Services"
        }
    ],
    "sg:phone":"+1 863 688 8583",
    "sg:postcode":"33813",
    "sg:province":"FL",
    "sg:tags":[
        "counselor",
        "marriage",
        "family"
    ],
    "wof:name":"Creative Counseling Ctr",
    "wof:placetype":"venue"
},
  "geometry": {"coordinates":[-81.94513499999999,27.963355],"type":"Point"}
}