{
  "type": "Feature",
  "properties": {
    "addr:full":"175 Barton Blvd Rockledge FL 32955",
    "addr:housenumber":"175",
    "addr:postcode":"32955",
    "addr:street":"Barton Blvd",
    "iso:country":"US",
    "sg:address":"175 Barton Blvd",
    "sg:city":"Rockledge",
    "sg:classifiers":[
        {
            "category":"Retail",
            "subcategory":"Auto Repair",
            "type":"Services"
        }
    ],
    "sg:phone":"+1 321 636 2741",
    "sg:postcode":"32955",
    "sg:province":"FL",
    "sg:tags":[
        "repairing",
        "automobile",
        "general"
    ],
    "wof:name":"Bergschneider Werke Inc",
    "wof:placetype":"venue"
},
  "geometry": {"coordinates":[-80.727411,28.330824],"type":"Point"}
}