{
  "type": "Feature",
  "properties": {
    "iso:country":"US",
    "sg:address":"24416 Greentree Ln",
    "sg:city":"Eustis",
    "sg:classifiers":[
        {
            "category":"Building & Trades",
            "subcategory":"Construction",
            "type":"Services"
        }
    ],
    "sg:phone":"+1 352 357 3639",
    "sg:postcode":"32736",
    "sg:province":"FL",
    "sg:tags":[
        "contractor"
    ],
    "wof:name":"Sunstate Plastering Inc",
    "wof:placetype":"venue"
},
  "geometry": {"coordinates":[-81.55355,28.873466],"type":"Point"}
}