{
  "type": "Feature",
  "properties": {
    "iso:country":"US",
    "sg:address":"5889 53rd Ave E",
    "sg:city":"Bradenton",
    "sg:classifiers":[
        {
            "category":"Banks & Credit Unions",
            "subcategory":"Investment Brokerage",
            "type":"Services"
        },
        {
            "category":"Banks & Credit Unions",
            "subcategory":"Bank",
            "type":"Services"
        },
        {
            "category":"Banks & Credit Unions",
            "subcategory":"Financial Services",
            "type":"Services"
        }
    ],
    "sg:phone":"+1 941 727 0900",
    "sg:postcode":"34203",
    "sg:province":"FL",
    "sg:tags":[
        "mutual",
        "retirement",
        "broker",
        "fund",
        "planning",
        "security",
        "bond",
        "stock"
    ],
    "sg:website":"http://www.edwardjones.com/en_US/fa/index.html&CIRN=305616",
    "wof:name":"Edward Jones - Financial Advisor: DIANE J TUCKER",
    "wof:placetype":"venue"
},
  "geometry": {"coordinates":[-82.486447,27.446152],"type":"Point"}
}