{
  "type": "Feature",
  "properties": {
    "addr:full":"8903 Glades Rd Boca Raton FL 33434",
    "addr:housenumber":"8903",
    "addr:postcode":"33434",
    "addr:street":"Glades Rd",
    "iso:country":"US",
    "sg:address":"8903 Glades Rd",
    "sg:city":"Boca Raton",
    "sg:classifiers":[
        {
            "category":"Insurance",
            "subcategory":"Insurance Agent",
            "type":"Services"
        }
    ],
    "sg:phone":"+1 561 852 1554",
    "sg:postcode":"33434",
    "sg:province":"FL",
    "wof:name":"Nationwide Insurance",
    "wof:placetype":"venue"
},
  "geometry": {"coordinates":[-80.18487500000001,26.367969],"type":"Point"}
}