{
  "type": "Feature",
  "properties": {
    "addr:full":"128 SE 9th Ave Boynton Beach FL 33435",
    "addr:housenumber":"128",
    "addr:postcode":"33435",
    "addr:street":"Se 9Th Ave",
    "iso:country":"US",
    "sg:address":"128 SE 9th Ave",
    "sg:city":"Boynton Beach",
    "sg:classifiers":[
        {
            "category":"Shopping",
            "subcategory":"Used Merchandise",
            "type":"Retail Goods"
        }
    ],
    "sg:phone":"+1 561 738 9557",
    "sg:postcode":"33435",
    "sg:province":"FL",
    "sg:tags":[
        "antique"
    ],
    "wof:name":"This N That",
    "wof:placetype":"venue"
},
  "geometry": {"coordinates":[-80.06243499999999,26.519271],"type":"Point"}
}