{
  "type": "Feature",
  "properties": {
    "iso:country":"US",
    "sg:address":"14915 US Hwy 301",
    "sg:city":"Dade City",
    "sg:classifiers":[
        {
            "category":"Retail",
            "subcategory":"Auto Repair",
            "type":"Services"
        }
    ],
    "sg:phone":"+1 352 523 0900",
    "sg:postcode":"33523",
    "sg:province":"FL",
    "sg:tags":[
        "body",
        "automobile",
        "painting"
    ],
    "wof:name":"Realtiy Auto Body",
    "wof:placetype":"venue"
},
  "geometry": {"coordinates":[-82.19042899999999,28.37451],"type":"Point"}
}