{
  "type": "Feature",
  "properties": {
    "iso:country":"US",
    "sg:address":"2170 W 10th Ave",
    "sg:city":"Hialeah",
    "sg:classifiers":[
        {
            "category":"Manufacturing",
            "subcategory":"Rubber & Plastics",
            "type":"Manufacturing & Wholesale Goods"
        },
        {
            "category":"Building & Trades",
            "subcategory":"Construction",
            "type":"Services"
        },
        {
            "category":"Bus Stop",
            "subcategory":"None",
            "type":"Transportation"
        }
    ],
    "sg:phone":"+1 305 887 2777",
    "sg:postcode":"33010",
    "sg:province":"FL",
    "sg:tags":[
        "plastics-molders",
        "metallizing",
        "plating"
    ],
    "sg:website":"http://www.sjabermanco.com",
    "wof:name":"S. J. Aberman & Co, Inc.",
    "wof:placetype":"venue"
},
  "geometry": {"coordinates":[-80.302102,25.841408],"type":"Point"}
}