{
  "type": "Feature",
  "properties": {
    "iso:country":"US",
    "sg:address":"11578 Tern Ct",
    "sg:city":"West Palm Beach",
    "sg:classifiers":[
        {
            "category":"Wholesale",
            "subcategory":"Vending Machines",
            "type":"Manufacturing & Wholesale Goods"
        }
    ],
    "sg:phone":"+1 561 753 0142",
    "sg:postcode":"33414",
    "sg:province":"FL",
    "sg:tags":[
        "operator"
    ],
    "wof:name":"R&J Vending Services",
    "wof:placetype":"venue"
},
  "geometry": {"coordinates":[-80.22802,26.665616],"type":"Point"}
}