{
  "type": "Feature",
  "properties": {
    "iso:country":"US",
    "sg:address":"27051 SW 119th Ct",
    "sg:city":"Homestead",
    "sg:classifiers":[
        {
            "category":"Health Services",
            "subcategory":"Clinic",
            "type":"Services"
        }
    ],
    "sg:phone":"+1 305 257 1176",
    "sg:postcode":"33032",
    "sg:province":"FL",
    "wof:name":"Steele Medical Inc",
    "wof:placetype":"venue"
},
  "geometry": {"coordinates":[-80.38448,25.51527],"type":"Point"}
}