{
  "type": "Feature",
  "properties": {
    "iso:country":"US",
    "sg:address":"4477 E Co Rd 462",
    "sg:city":"Wildwood",
    "sg:classifiers":[
        {
            "category":"Building & Trades",
            "subcategory":"Construction",
            "type":"Services"
        }
    ],
    "sg:phone":"+1 352 748 0955",
    "sg:postcode":"34785",
    "sg:province":"FL",
    "sg:tags":[
        "contractor",
        "industrial",
        "general"
    ],
    "wof:name":"Rainey Construction Company",
    "wof:placetype":"venue"
},
  "geometry": {"coordinates":[-82.029411,28.883764],"type":"Point"}
}