{
  "type": "Feature",
  "properties": {
    "iso:country":"US",
    "sg:address":"23 W 8th St",
    "sg:city":"Jacksonville",
    "sg:classifiers":[
        {
            "category":"Organizations",
            "subcategory":"Religious Organization",
            "type":"Services"
        }
    ],
    "sg:phone":"+1 904 353 5063",
    "sg:postcode":"32206",
    "sg:province":"FL",
    "sg:website":"www.westside-coc.org",
    "wof:name":"Westside Church Of Christ",
    "wof:placetype":"venue"
},
  "geometry": {"coordinates":[-81.655241,30.345921],"type":"Point"}
}