{
  "type": "Feature",
  "properties": {
    "addr:full":"1012 Heartland Cir Mulberry FL 33860",
    "addr:housenumber":"1012",
    "addr:postcode":"33860",
    "addr:street":"Heartland Cir",
    "iso:country":"US",
    "sg:address":"1012 Heartland Cir",
    "sg:city":"Mulberry",
    "sg:classifiers":[
        {
            "category":"Professional",
            "subcategory":"Business Services",
            "type":"Services"
        }
    ],
    "sg:phone":"+1 863 648 1247",
    "sg:postcode":"33860",
    "sg:province":"FL",
    "wof:name":"Taliaferro Enterprises Corp",
    "wof:placetype":"venue"
},
  "geometry": {"coordinates":[-81.993375,27.936387],"type":"Point"}
}