{
  "type": "Feature",
  "properties": {
    "addr:full":"4848 NW 7th Ave Miami FL 33127",
    "addr:housenumber":"4848",
    "addr:postcode":"33127",
    "addr:street":"Nw 7Th Ave",
    "iso:country":"US",
    "sg:address":"4848 NW 7th Ave",
    "sg:city":"Miami",
    "sg:classifiers":[
        {
            "category":"Personal",
            "subcategory":"Beauty Salon",
            "type":"Services"
        }
    ],
    "sg:phone":"+1 305 754 0505",
    "sg:postcode":"33127",
    "sg:province":"FL",
    "wof:name":"Nikki's Hair Studio",
    "wof:placetype":"venue"
},
  "geometry": {"coordinates":[-80.208037,25.819969],"type":"Point"}
}