{
  "type": "Feature",
  "properties": {
    "iso:country":"US",
    "sg:address":"9101 International Dr",
    "sg:city":"Orlando",
    "sg:classifiers":[
        {
            "category":"Restaurant",
            "type":"Food & Drink"
        }
    ],
    "sg:phone":"+1 407 354 1122",
    "sg:postcode":"32819",
    "sg:province":"FL",
    "wof:name":"Montys Stone Crab",
    "wof:placetype":"venue"
},
  "geometry": {"coordinates":[-81.47182599999999,28.433384],"type":"Point"}
}