{
  "type": "Feature",
  "properties": {
    "iso:country":"US",
    "sg:address":"15050 Bridgeway Ln",
    "sg:city":"Fort Myers",
    "sg:classifiers":[
        {
            "category":"Wholesale",
            "subcategory":"Vending Machines",
            "type":"Manufacturing & Wholesale Goods"
        }
    ],
    "sg:phone":"+1 239 481 4868",
    "sg:postcode":"33919",
    "sg:province":"FL",
    "sg:tags":[
        "operator"
    ],
    "wof:name":"Candy Vending Machines By Alan",
    "wof:placetype":"venue"
},
  "geometry": {"coordinates":[-81.91073900000001,26.523436],"type":"Point"}
}