{
  "type": "Feature",
  "properties": {
    "iso:country":"US",
    "sg:address":"304 W Pleasant St",
    "sg:city":"Avon Park",
    "sg:classifiers":[
        {
            "category":"Government",
            "subcategory":"Police Station",
            "type":"Public Place"
        }
    ],
    "sg:phone":"+1 863 453 6622",
    "sg:postcode":"33825",
    "sg:province":"FL",
    "sg:tags":[
        "department"
    ],
    "wof:name":"Avon Park Police Department",
    "wof:placetype":"venue"
},
  "geometry": {"coordinates":[-81.504687,27.59931],"type":"Point"}
}