{
  "type": "Feature",
  "properties": {
    "addr:full":"278 Eglin Pkwy NE Fort Walton Beach FL 32547",
    "addr:housenumber":"278",
    "addr:postcode":"32547",
    "addr:street":"Eglin Pkwy Ne",
    "iso:country":"US",
    "sg:address":"278 Eglin Pkwy NE",
    "sg:city":"Fort Walton Beach",
    "sg:classifiers":[
        {
            "category":"Restaurant",
            "type":"Food & Drink"
        }
    ],
    "sg:menulink":"http://www.allmenus.com/fl/fort-walton-beach/237204-hungry-howies-pizza/menu/",
    "sg:phone":"+1 850 862 8867",
    "sg:postcode":"32547",
    "sg:province":"FL",
    "sg:tags":[
        "wrap",
        "american",
        "sandwich",
        "pizza"
    ],
    "wof:name":"Hungry Howie's Pizza",
    "wof:placetype":"venue"
},
  "geometry": {"coordinates":[-86.604163,30.432716],"type":"Point"}
}