{
  "type": "Feature",
  "properties": {
    "iso:country":"US",
    "sg:address":"551 Sundown Trl",
    "sg:city":"Casselberry",
    "sg:classifiers":[
        {
            "category":"Social Services",
            "type":"Services"
        },
        {
            "category":"Organizations",
            "subcategory":"Community Association",
            "type":"Services"
        }
    ],
    "sg:phone":"+1 407 681 8198",
    "sg:postcode":"32707",
    "sg:province":"FL",
    "wof:name":"Creating Divine Order Inc",
    "wof:placetype":"venue"
},
  "geometry": {"coordinates":[-81.321519,28.686212],"type":"Point"}
}