{
  "type": "Feature",
  "properties": {
    "addr:full":"14321 SW 99th Ct Miami FL 33176",
    "addr:housenumber":"14321",
    "addr:postcode":"33176",
    "addr:street":"Sw 99Th Ct",
    "iso:country":"US",
    "sg:address":"14321 SW 99th Ct",
    "sg:city":"Miami",
    "sg:classifiers":[
        {
            "category":"Shopping",
            "subcategory":"Clothing, Apparel, & Fashions",
            "type":"Retail Goods"
        }
    ],
    "sg:phone":"+1 305 233 5530",
    "sg:postcode":"33176",
    "sg:province":"FL",
    "sg:tags":[
        "wear"
    ],
    "wof:name":"Fairy Tales",
    "wof:placetype":"venue"
},
  "geometry": {"coordinates":[-80.355052,25.636037],"type":"Point"}
}