{
  "type": "Feature",
  "properties": {
    "iso:country":"US",
    "sg:address":"210 Valencia Ave",
    "sg:city":"Coral Gables",
    "sg:classifiers":[
        {
            "category":"Building & Trades",
            "subcategory":"Locksmith",
            "type":"Services"
        }
    ],
    "sg:phone":"+1 786 228 5447",
    "sg:postcode":"33134",
    "sg:province":"FL",
    "sg:tags":[
        "key"
    ],
    "wof:name":"Coral Gables 24 Hour Emergency Locksmith",
    "wof:placetype":"venue"
},
  "geometry": {"coordinates":[-80.25923,25.74796],"type":"Point"}
}