{
  "type": "Feature",
  "properties": {
    "addr:full":"650 8th St Clermont FL 34711",
    "addr:housenumber":"650",
    "addr:postcode":"34711",
    "addr:street":"8Th St",
    "iso:country":"US",
    "sg:address":"650 8th St",
    "sg:city":"Clermont",
    "sg:classifiers":[
        {
            "category":"Shopping",
            "subcategory":"Clothing, Apparel, & Fashions",
            "type":"Retail Goods"
        },
        {
            "category":"Shopping",
            "subcategory":"Used Merchandise",
            "type":"Retail Goods"
        }
    ],
    "sg:phone":"+1 352 243 6174",
    "sg:postcode":"34711",
    "sg:province":"FL",
    "sg:tags":[
        "apparel",
        "resale",
        "shop",
        "women's"
    ],
    "wof:name":"Finders Keepers",
    "wof:placetype":"venue"
},
  "geometry": {"coordinates":[-81.768635,28.555764],"type":"Point"}
}