{
  "type": "Feature",
  "properties": {
    "iso:country":"US",
    "sg:address":"1336 Vickers Rd",
    "sg:city":"Tallahassee",
    "sg:classifiers":[
        {
            "category":"Wholesale",
            "subcategory":"Office Equipment",
            "type":"Manufacturing & Wholesale Goods"
        }
    ],
    "sg:phone":"+1 850 562 9709",
    "sg:postcode":"32303",
    "sg:province":"FL",
    "sg:tags":[
        "point",
        "retail",
        "system",
        "sale"
    ],
    "wof:name":"Gold Coast Cash Register Sales",
    "wof:placetype":"venue"
},
  "geometry": {"coordinates":[-84.312456,30.486794],"type":"Point"}
}