{
  "type": "Feature",
  "properties": {
    "addr:full":"1119 San Marco Rd Marco Island FL 34145",
    "addr:housenumber":"1119",
    "addr:postcode":"34145",
    "addr:street":"San Marco Rd",
    "iso:country":"US",
    "sg:address":"1119 San Marco Rd",
    "sg:city":"Marco Island",
    "sg:classifiers":[
        {
            "category":"Food & Beverages",
            "subcategory":"Specialty",
            "type":"Retail Goods"
        }
    ],
    "sg:phone":"+1 239 389 1720",
    "sg:postcode":"34145",
    "sg:province":"FL",
    "sg:tags":[
        "gourmet",
        "shop"
    ],
    "wof:name":"Bellissimo",
    "wof:placetype":"venue"
},
  "geometry": {"coordinates":[-81.719121,25.937012],"type":"Point"}
}