{
  "type": "Feature",
  "properties": {
    "iso:country":"US",
    "sg:address":"3848 W Columbus Dr",
    "sg:city":"Tampa",
    "sg:classifiers":[
        {
            "category":"Professional",
            "type":"Services"
        }
    ],
    "sg:phone":"+1 813 876 0664",
    "sg:postcode":"33607",
    "sg:province":"FL",
    "sg:tags":[
        "establishment"
    ],
    "wof:name":"Mons Venus",
    "wof:placetype":"venue"
},
  "geometry": {"coordinates":[-82.510999,27.966611],"type":"Point"}
}