{
  "type": "Feature",
  "properties": {
    "addr:full":"7966 Fisher Island Dr Miami Beach FL 33109",
    "addr:housenumber":"7966",
    "addr:postcode":"33109",
    "addr:street":"Fisher Island Dr",
    "iso:country":"US",
    "sg:address":"7966 Fisher Island Dr",
    "sg:city":"Miami Beach",
    "sg:classifiers":[
        {
            "category":"Professional",
            "type":"Services"
        }
    ],
    "sg:phone":"+1 305 534 4550",
    "sg:postcode":"33109",
    "sg:province":"FL",
    "sg:tags":[
        "establishment"
    ],
    "wof:name":"Ford Group",
    "wof:placetype":"venue"
},
  "geometry": {"coordinates":[-80.147988,25.762618],"type":"Point"}
}