{
  "type": "Feature",
  "properties": {
    "iso:country":"US",
    "sg:address":"6215 Brookhill Cir",
    "sg:city":"Orlando",
    "sg:classifiers":[
        {
            "category":"Professional",
            "subcategory":"Computer Services",
            "type":"Services"
        }
    ],
    "sg:phone":"+1 407 295 2786",
    "sg:postcode":"32810",
    "sg:province":"FL",
    "sg:tags":[
        "related"
    ],
    "wof:name":"SRS Computer Srvs",
    "wof:placetype":"venue"
},
  "geometry": {"coordinates":[-81.464664,28.61776],"type":"Point"}
}