{
  "type": "Feature",
  "properties": {
    "addr:full":"3342 NW Federal Hwy Jensen Beach FL 34957",
    "addr:housenumber":"3342",
    "addr:postcode":"34957",
    "addr:street":"Nw Federal Hwy",
    "iso:country":"US",
    "sg:address":"3342 NW Federal Hwy",
    "sg:city":"Jensen Beach",
    "sg:classifiers":[
        {
            "category":"Retail",
            "subcategory":"Portrait Studio",
            "type":"Services"
        }
    ],
    "sg:phone":"+1 772 692 5453",
    "sg:postcode":"34957",
    "sg:province":"FL",
    "sg:tags":[
        "photo"
    ],
    "wof:name":"Sears Portrait Studio",
    "wof:placetype":"venue"
},
  "geometry": {"coordinates":[-80.270523,27.240588],"type":"Point"}
}