{
  "type": "Feature",
  "properties": {
    "iso:country":"US",
    "sg:address":"9334 Whittingham Dr",
    "sg:city":"Orlando",
    "sg:classifiers":[
        {
            "category":"Building & Trades",
            "subcategory":"Construction",
            "type":"Services"
        }
    ],
    "sg:phone":"+1 407 679 2742",
    "sg:postcode":"32817",
    "sg:province":"FL",
    "sg:tags":[
        "contractor"
    ],
    "wof:name":"Avalon Pools & Spas Inc",
    "wof:placetype":"venue"
},
  "geometry": {"coordinates":[-81.257499,28.608817],"type":"Point"}
}