{
  "type": "Feature",
  "properties": {
    "iso:country":"US",
    "sg:address":"312 N John St",
    "sg:city":"Orlando",
    "sg:classifiers":[
        {
            "category":"Building & Trades",
            "subcategory":"Plumbing",
            "type":"Services"
        }
    ],
    "sg:phone":"+1 407 788 8777",
    "sg:postcode":"32835",
    "sg:province":"FL",
    "sg:tags":[
        "conditioning",
        "air",
        "system",
        "contractor"
    ],
    "wof:name":"Joe Cools Air & Heat",
    "wof:placetype":"venue"
},
  "geometry": {"coordinates":[-81.46248900000001,28.545815],"type":"Point"}
}