{
  "type": "Feature",
  "properties": {
    "addr:full":"1350 Saratoga St Deland FL 32724",
    "addr:housenumber":"1350",
    "addr:postcode":"32724",
    "addr:street":"Saratoga St",
    "iso:country":"US",
    "sg:address":"1350 Saratoga St",
    "sg:city":"Deland",
    "sg:classifiers":[
        {
            "category":"Retail",
            "subcategory":"Auto Repair",
            "type":"Services"
        }
    ],
    "sg:phone":"+1 386 740 8450",
    "sg:postcode":"32724",
    "sg:province":"FL",
    "sg:tags":[
        "repairing",
        "automobile"
    ],
    "wof:name":"A Auto Tech Svc",
    "wof:placetype":"venue"
},
  "geometry": {"coordinates":[-81.278944,29.060529],"type":"Point"}
}