{
  "type": "Feature",
  "properties": {
    "addr:full":"118 Municipal Ave Sopchoppy FL 32358",
    "addr:housenumber":"118",
    "addr:postcode":"32358",
    "addr:street":"Municipal Ave",
    "iso:country":"US",
    "sg:address":"118 Municipal Ave",
    "sg:city":"Sopchoppy",
    "sg:classifiers":[
        {
            "category":"Shopping",
            "subcategory":"Books",
            "type":"Retail Goods"
        }
    ],
    "sg:phone":"+1 850 962 1900",
    "sg:postcode":"32358",
    "sg:province":"FL",
    "sg:tags":[
        "dealer"
    ],
    "wof:name":"Book & Art Tearoom",
    "wof:placetype":"venue"
},
  "geometry": {"coordinates":[-84.491693,30.060937],"type":"Point"}
}