{
  "type": "Feature",
  "properties": {
    "addr:full":"2138 Oak Meadow Cir Daytona Beach FL 32119",
    "addr:housenumber":"2138",
    "addr:postcode":"32119",
    "addr:street":"Oak Meadow Cir",
    "iso:country":"US",
    "sg:address":"2138 Oak Meadow Cir",
    "sg:city":"Daytona Beach",
    "sg:classifiers":[
        {
            "category":"Wholesale",
            "subcategory":"Construction Materials",
            "type":"Manufacturing & Wholesale Goods"
        }
    ],
    "sg:phone":"+1 386 761 8196",
    "sg:postcode":"32119",
    "sg:province":"FL",
    "wof:name":"Mark Gabriel PA",
    "wof:placetype":"venue"
},
  "geometry": {"coordinates":[-81.018869,29.167155],"type":"Point"}
}