{
  "type": "Feature",
  "properties": {
    "iso:country":"US",
    "sg:address":"381 Hall Ln",
    "sg:city":"Quincy",
    "sg:classifiers":[
        {
            "category":"Retail",
            "subcategory":"Repair Shop",
            "type":"Services"
        }
    ],
    "sg:phone":"+1 850 442 4254",
    "sg:postcode":"32351",
    "sg:province":"FL",
    "sg:tags":[
        "lock",
        "locksmith"
    ],
    "wof:name":"Hall's Locksmith Svc",
    "wof:placetype":"venue"
},
  "geometry": {"coordinates":[-84.74590999999999,30.520691],"type":"Point"}
}