{
  "type": "Feature",
  "properties": {
    "addr:full":"4545 US Hwy 1 Cocoa FL 32927",
    "addr:housenumber":"4545",
    "addr:postcode":"32927",
    "addr:street":"Us Hwy 1",
    "iso:country":"US",
    "sg:address":"4545 US Hwy 1",
    "sg:city":"Cocoa",
    "sg:classifiers":[
        {
            "category":"Building & Trades",
            "subcategory":"Construction",
            "type":"Services"
        }
    ],
    "sg:phone":"+1 321 636 7761",
    "sg:postcode":"32927",
    "sg:province":"FL",
    "sg:tags":[
        "shed",
        "utility"
    ],
    "sg:website":"www.superiorsheds.com",
    "wof:name":"Superior Sheds Inc",
    "wof:placetype":"venue"
},
  "geometry": {"coordinates":[-80.763155,28.444319],"type":"Point"}
}