{
  "type": "Feature",
  "properties": {
    "iso:country":"US",
    "sg:address":"30230 US Hwy 19",
    "sg:city":"Clearwater",
    "sg:classifiers":[
        {
            "category":"Shopping",
            "subcategory":"Clothing, Apparel, & Fashions",
            "type":"Retail Goods"
        }
    ],
    "sg:phone":"+1 727 789 1742",
    "sg:postcode":"33761",
    "sg:province":"FL",
    "sg:tags":[
        "alteration"
    ],
    "wof:name":"Sue's Alterations",
    "wof:placetype":"venue"
},
  "geometry": {"coordinates":[-82.738572,28.046533],"type":"Point"}
}