{
  "type": "Feature",
  "properties": {
    "addr:full":"8441 Pensacola Blvd Pensacola FL 32534",
    "addr:housenumber":"8441",
    "addr:postcode":"32534",
    "addr:street":"Pensacola Blvd",
    "iso:country":"US",
    "sg:address":"8441 Pensacola Blvd",
    "sg:city":"Pensacola",
    "sg:classifiers":[
        {
            "category":"Building & Trades",
            "subcategory":"Cleaning & Sanitation",
            "type":"Services"
        }
    ],
    "sg:phone":"+1 850 476 2361",
    "sg:postcode":"32534",
    "sg:province":"FL",
    "sg:tags":[
        "fireplace",
        "chimney"
    ],
    "wof:name":"Kent's Chimney Cleaning & Rpr",
    "wof:placetype":"venue"
},
  "geometry": {"coordinates":[-87.272958,30.518815],"type":"Point"}
}