{
  "type": "Feature",
  "properties": {
    "addr:full":"26 Industrial Loop E Orange Park FL 32073",
    "addr:housenumber":"26",
    "addr:postcode":"32073",
    "addr:street":"Industrial Loop E",
    "iso:country":"US",
    "sg:address":"26 Industrial Loop E",
    "sg:city":"Orange Park",
    "sg:classifiers":[
        {
            "category":"Recreation",
            "type":"Entertainment"
        }
    ],
    "sg:phone":"+1 904 264 6114",
    "sg:postcode":"32073",
    "sg:province":"FL",
    "sg:tags":[
        "amusement"
    ],
    "wof:name":"Cheer Authority",
    "wof:placetype":"venue"
},
  "geometry": {"coordinates":[-81.712434,30.180862],"type":"Point"}
}