{
  "type": "Feature",
  "properties": {
    "addr:full":"1907 W 60th St Hialeah FL 33012",
    "addr:housenumber":"1907",
    "addr:postcode":"33012",
    "addr:street":"W 60Th St",
    "iso:country":"US",
    "sg:address":"1907 W 60th St",
    "sg:city":"Hialeah",
    "sg:classifiers":[
        {
            "category":"Personal",
            "subcategory":"Nail Salon",
            "type":"Services"
        }
    ],
    "sg:phone":"+1 305 512 7544",
    "sg:postcode":"33012",
    "sg:province":"FL",
    "wof:name":"Hong Kong Nails",
    "wof:placetype":"venue"
},
  "geometry": {"coordinates":[-80.320503,25.8769],"type":"Point"}
}