{
  "type": "Feature",
  "properties": {
    "iso:country":"US",
    "sg:address":"3240 NW 36th St",
    "sg:city":"Miami",
    "sg:classifiers":[
        {
            "category":"Retail",
            "subcategory":"Auto Repair",
            "type":"Services"
        }
    ],
    "sg:phone":"+1 305 637 0188",
    "sg:postcode":"33142",
    "sg:province":"FL",
    "sg:tags":[
        "repairing",
        "automobile"
    ],
    "wof:name":"Gauchos Auto Mechanics",
    "wof:placetype":"venue"
},
  "geometry": {"coordinates":[-80.249657,25.808727],"type":"Point"}
}