{
  "type": "Feature",
  "properties": {
    "addr:full":"102 Monument Ave Port Saint Joe FL 32456",
    "addr:housenumber":"102",
    "addr:postcode":"32456",
    "addr:street":"Monument Ave",
    "iso:country":"US",
    "sg:address":"102 Monument Ave",
    "sg:city":"Port Saint Joe",
    "sg:classifiers":[
        {
            "category":"Autos & Motor Vehicles",
            "subcategory":"Auto Supplies",
            "type":"Retail Goods"
        }
    ],
    "sg:phone":"+1 850 229 6811",
    "sg:postcode":"32456",
    "sg:province":"FL",
    "wof:name":"Discount Auto Parts Inc",
    "wof:placetype":"venue"
},
  "geometry": {"coordinates":[-85.304841,29.815822],"type":"Point"}
}