{
  "type": "Feature",
  "properties": {
    "addr:full":"16040 SW 284th St Homestead FL 33033",
    "addr:housenumber":"16040",
    "addr:postcode":"33033",
    "addr:street":"Sw 284Th St",
    "iso:country":"US",
    "sg:address":"16040 SW 284th St",
    "sg:city":"Homestead",
    "sg:classifiers":[
        {
            "category":"Building & Trades",
            "subcategory":"Construction",
            "type":"Services"
        }
    ],
    "sg:phone":"+1 305 245 9664",
    "sg:postcode":"33033",
    "sg:province":"FL",
    "sg:tags":[
        "house"
    ],
    "wof:name":"Td Jones Construction",
    "wof:placetype":"venue"
},
  "geometry": {"coordinates":[-80.45202,25.502865],"type":"Point"}
}