{
  "type": "Feature",
  "properties": {
    "iso:country":"US",
    "sg:address":"301 N Park Ave Ste C",
    "sg:city":"Winter Park",
    "sg:classifiers":[
        {
            "category":"Banks & Credit Unions",
            "subcategory":"Atm",
            "type":"Services"
        }
    ],
    "sg:phone":"+1 407 629 9190",
    "sg:postcode":"32789",
    "sg:province":"FL",
    "sg:tags":[
        "bankruptcy"
    ],
    "wof:name":"Petersen Warren H Atty",
    "wof:placetype":"venue"
},
  "geometry": {"coordinates":[-81.351097,28.5996],"type":"Point"}
}