{
  "type": "Feature",
  "properties": {
    "addr:full":"1817 W Call St Tallahassee FL 32304",
    "addr:housenumber":"1817",
    "addr:postcode":"32304",
    "addr:street":"W Call St",
    "iso:country":"US",
    "sg:address":"1817 W Call St",
    "sg:city":"Tallahassee",
    "sg:classifiers":[
        {
            "category":"Mining & Drilling",
            "type":"Manufacturing & Wholesale Goods"
        }
    ],
    "sg:phone":"+1 850 224 1808",
    "sg:postcode":"32304",
    "sg:province":"FL",
    "sg:tags":[
        "stone"
    ],
    "wof:name":"S & T Specialty Stone Constr",
    "wof:placetype":"venue"
},
  "geometry": {"coordinates":[-84.31112,30.448192],"type":"Point"}
}