{
  "type": "Feature",
  "properties": {
    "iso:country":"US",
    "sg:address":"75 E Indiantown Rd",
    "sg:city":"Jupiter",
    "sg:classifiers":[
        {
            "category":"Professional",
            "subcategory":"Business Services",
            "type":"Services"
        }
    ],
    "sg:phone":"+1 561 744 5464",
    "sg:postcode":"33477",
    "sg:province":"FL",
    "sg:tags":[
        "packaging"
    ],
    "wof:name":"Parcel Plus",
    "wof:placetype":"venue"
},
  "geometry": {"coordinates":[-80.091937,26.93419],"type":"Point"}
}