{
  "type": "Feature",
  "properties": {
    "iso:country":"US",
    "sg:address":"5625 8th St SW",
    "sg:city":"Coral Gables",
    "sg:classifiers":[
        {
            "category":"Shopping",
            "type":"Retail Goods"
        }
    ],
    "sg:phone":"+1 305 262 5700",
    "sg:postcode":"33134",
    "sg:province":"FL",
    "sg:tags":[
        "art",
        "gallery",
        "dealer"
    ],
    "wof:name":"Cabarroca Art & Frames",
    "wof:placetype":"venue"
},
  "geometry": {"coordinates":[-80.287564,25.763647],"type":"Point"}
}