{
  "type": "Feature",
  "properties": {
    "iso:country":"US",
    "sg:address":"7860 SW 36th St",
    "sg:city":"Miami",
    "sg:classifiers":[
        {
            "category":"Building & Trades",
            "subcategory":"Locksmith",
            "type":"Services"
        }
    ],
    "sg:phone":"+1 786 837 0344",
    "sg:postcode":"33155",
    "sg:province":"FL",
    "sg:tags":[
        "key"
    ],
    "wof:name":"AAA Locksmith",
    "wof:placetype":"venue"
},
  "geometry": {"coordinates":[-80.32291499999999,25.736748],"type":"Point"}
}