{
  "type": "Feature",
  "properties": {
    "addr:full":"500 N Ingraham Ave Lakeland FL 33801",
    "addr:housenumber":"500",
    "addr:postcode":"33801",
    "addr:street":"N Ingraham Ave",
    "iso:country":"US",
    "sg:address":"500 N Ingraham Ave",
    "sg:city":"Lakeland",
    "sg:classifiers":[
        {
            "category":"Social Services",
            "subcategory":"Job Training",
            "type":"Services"
        }
    ],
    "sg:phone":"+1 863 295 5125",
    "sg:postcode":"33801",
    "sg:province":"FL",
    "sg:tags":[
        "rehab",
        "government"
    ],
    "wof:name":"Labor & Employment Security",
    "wof:placetype":"venue"
},
  "geometry": {"coordinates":[-81.94499399999999,28.047714],"type":"Point"}
}