{
  "type": "Feature",
  "properties": {
    "iso:country":"US",
    "sg:address":"8438 Normandy Blvd",
    "sg:city":"Jacksonville",
    "sg:classifiers":[
        {
            "category":"Freight",
            "type":"Transportation"
        }
    ],
    "sg:phone":"+1 904 781 3216",
    "sg:postcode":"32221",
    "sg:province":"FL",
    "sg:tags":[
        "operator",
        "local",
        "trucking"
    ],
    "wof:name":"Culver B G Hauling",
    "wof:placetype":"venue"
},
  "geometry": {"coordinates":[-81.79244,30.289267],"type":"Point"}
}