{
  "type": "Feature",
  "properties": {
    "addr:full":"777 E 25th St Ste 502 Hialeah FL 33013",
    "addr:housenumber":"777",
    "addr:postcode":"33013",
    "addr:street":"E 25Th St Ste 502",
    "iso:country":"US",
    "sg:address":"777 E 25th St Ste 502",
    "sg:city":"Hialeah",
    "sg:classifiers":[
        {
            "category":"Health Services",
            "subcategory":"Doctor",
            "type":"Services"
        }
    ],
    "sg:phone":"+1 305 836 7377",
    "sg:postcode":"33013",
    "sg:province":"FL",
    "wof:name":"Meruelo Hector J MD",
    "wof:placetype":"venue"
},
  "geometry": {"coordinates":[-80.266701,25.8452],"type":"Point"}
}