{
  "type": "Feature",
  "properties": {
    "iso:country":"US",
    "sg:address":"12325 SW 72nd St",
    "sg:city":"Miami",
    "sg:classifiers":[
        {
            "category":"Building & Trades",
            "subcategory":"Landscaping Services",
            "type":"Services"
        }
    ],
    "sg:phone":"+1 305 595 4098",
    "sg:postcode":"33183",
    "sg:province":"FL",
    "sg:tags":[
        "lawn",
        "garden",
        "wholesale",
        "contractor",
        "nursery",
        "retail",
        "landscape"
    ],
    "wof:name":"Gilmer Landscaping Svc",
    "wof:placetype":"venue"
},
  "geometry": {"coordinates":[-80.39397700000001,25.700689],"type":"Point"}
}