{
  "type": "Feature",
  "properties": {
    "addr:full":"5753 NW 158th St Hialeah FL 33014",
    "addr:housenumber":"5753",
    "addr:postcode":"33014",
    "addr:street":"Nw 158Th St",
    "iso:country":"US",
    "sg:address":"5753 NW 158th St",
    "sg:city":"Hialeah",
    "sg:classifiers":[
        {
            "category":"Professional",
            "subcategory":"Business Services",
            "type":"Services"
        }
    ],
    "sg:phone":"+1 305 828 2157",
    "sg:postcode":"33014",
    "sg:province":"FL",
    "wof:name":"Dental Express of Texas Inc",
    "wof:placetype":"venue"
},
  "geometry": {"coordinates":[-80.29380500000001,25.917048],"type":"Point"}
}