{
  "type": "Feature",
  "properties": {
    "addr:full":"340 SE 8th Ct Pompano Beach FL 33060",
    "addr:housenumber":"340",
    "addr:postcode":"33060",
    "addr:street":"Se 8Th Ct",
    "iso:country":"US",
    "sg:address":"340 SE 8th Ct",
    "sg:city":"Pompano Beach",
    "sg:classifiers":[
        {
            "category":"Freight",
            "type":"Transportation"
        }
    ],
    "sg:phone":"+1 954 675 3341",
    "sg:postcode":"33060",
    "sg:province":"FL",
    "sg:tags":[
        "local",
        "storage",
        "trucking"
    ],
    "wof:name":"Security Transport Servic",
    "wof:placetype":"venue"
},
  "geometry": {"coordinates":[-80.119257,26.219011],"type":"Point"}
}