{
  "type": "Feature",
  "properties": {
    "addr:full":"10413 Southern Blvd Royal Palm Beach FL 33411",
    "addr:housenumber":"10413",
    "addr:postcode":"33411",
    "addr:street":"Southern Blvd",
    "iso:country":"US",
    "sg:address":"10413 Southern Blvd",
    "sg:city":"Royal Palm Beach",
    "sg:classifiers":[
        {
            "category":"Health Services",
            "subcategory":"Doctor",
            "type":"Services"
        }
    ],
    "sg:phone":"+1 561 793 1713",
    "sg:postcode":"33411",
    "sg:province":"FL",
    "sg:tags":[
        "physician",
        "surgeon"
    ],
    "wof:name":"Metcare",
    "wof:placetype":"venue"
},
  "geometry": {"coordinates":[-80.20446,26.680415],"type":"Point"}
}