{
  "type": "Feature",
  "properties": {
    "iso:country":"US",
    "sg:address":"5606 S Ridgewood Ave",
    "sg:city":"Port Orange",
    "sg:classifiers":[
        {
            "category":"Personal",
            "subcategory":"Beauty Salon",
            "type":"Services"
        }
    ],
    "sg:phone":"+1 386 756 8184",
    "sg:postcode":"32127",
    "sg:province":"FL",
    "wof:name":"Joy's Unisex Hair",
    "wof:placetype":"venue"
},
  "geometry": {"coordinates":[-80.974768,29.117108],"type":"Point"}
}