{
  "type": "Feature",
  "properties": {
    "addr:full":"5 N Cocoa Blvd Cocoa FL 32922",
    "addr:housenumber":"5",
    "addr:postcode":"32922",
    "addr:street":"N Cocoa Blvd",
    "iso:country":"US",
    "sg:address":"5 N Cocoa Blvd",
    "sg:city":"Cocoa",
    "sg:classifiers":[
        {
            "category":"Autos & Motor Vehicles",
            "subcategory":"Fuel & Gas Station",
            "type":"Retail Goods"
        }
    ],
    "sg:phone":"+1 321 639 1126",
    "sg:postcode":"32922",
    "sg:province":"FL",
    "sg:tags":[
        "oil"
    ],
    "wof:name":"Yojo Investments Inc",
    "wof:placetype":"venue"
},
  "geometry": {"coordinates":[-80.732697,28.358787],"type":"Point"}
}