{
  "type": "Feature",
  "properties": {
    "addr:full":"9250 SW 41st St Miami FL 33165",
    "addr:housenumber":"9250",
    "addr:postcode":"33165",
    "addr:street":"Sw 41St St",
    "iso:country":"US",
    "sg:address":"9250 SW 41st St",
    "sg:city":"Miami",
    "sg:classifiers":[
        {
            "category":"Wholesale",
            "subcategory":"Sporting Goods",
            "type":"Manufacturing & Wholesale Goods"
        }
    ],
    "sg:phone":"+1 305 207 9955",
    "sg:postcode":"33165",
    "sg:province":"FL",
    "sg:website":"www.miamiboatlifts.com",
    "wof:name":"Miami Boat Lifts",
    "wof:placetype":"venue"
},
  "geometry": {"coordinates":[-80.34472700000001,25.731322],"type":"Point"}
}