{
  "type": "Feature",
  "properties": {
    "addr:full":"710 Rock Hill Ave Davie FL 33325",
    "addr:housenumber":"710",
    "addr:postcode":"33325",
    "addr:street":"Rock Hill Ave",
    "iso:country":"US",
    "sg:address":"710 Rock Hill Ave",
    "sg:city":"Davie",
    "sg:classifiers":[
        {
            "category":"Professional",
            "subcategory":"Computer Services",
            "type":"Services"
        }
    ],
    "sg:phone":"+1 954 370 6201",
    "sg:postcode":"33325",
    "sg:province":"FL",
    "sg:tags":[
        "consultant",
        "designer",
        "programing",
        "custom"
    ],
    "sg:website":"www.therightbyte.com",
    "wof:name":"Right Byte Inc",
    "wof:placetype":"venue"
},
  "geometry": {"coordinates":[-80.343583,26.110817],"type":"Point"}
}