{
  "type": "Feature",
  "properties": {
    "addr:full":"2699 Biscayne Blvd Miami FL 33137",
    "addr:housenumber":"2699",
    "addr:postcode":"33137",
    "addr:street":"Biscayne Blvd",
    "iso:country":"US",
    "sg:address":"2699 Biscayne Blvd",
    "sg:city":"Miami",
    "sg:classifiers":[
        {
            "category":"Restaurant",
            "type":"Food & Drink"
        }
    ],
    "sg:phone":"+1 305 576 7272",
    "sg:postcode":"33137",
    "sg:province":"FL",
    "sg:tags":[
        "pizza"
    ],
    "wof:name":"Papa John's",
    "wof:placetype":"venue"
},
  "geometry": {"coordinates":[-80.188793,25.802709],"type":"Point"}
}