{
  "type": "Feature",
  "properties": {
    "iso:country":"US",
    "sg:address":"1119 Georgia Ave",
    "sg:city":"Palm Harbor",
    "sg:classifiers":[
        {
            "category":"Education",
            "subcategory":"Special Training",
            "type":"Public Place"
        }
    ],
    "sg:phone":"+1 727 734 2000",
    "sg:postcode":"34683",
    "sg:province":"FL",
    "sg:tags":[
        "school",
        "massage"
    ],
    "wof:name":"Touching Palms Massage Inst",
    "wof:placetype":"venue"
},
  "geometry": {"coordinates":[-82.765118,28.077242],"type":"Point"}
}