{
  "type": "Feature",
  "properties": {
    "iso:country":"US",
    "sg:address":"6215 Hawkins Rd",
    "sg:city":"Sarasota",
    "sg:classifiers":[
        {
            "category":"Manufacturing",
            "subcategory":"Signs",
            "type":"Manufacturing & Wholesale Goods"
        }
    ],
    "sg:phone":"+1 941 924 8456",
    "sg:postcode":"34241",
    "sg:province":"FL",
    "wof:name":"King Signs",
    "wof:placetype":"venue"
},
  "geometry": {"coordinates":[-82.443089,27.262098],"type":"Point"}
}