{
  "type": "Feature",
  "properties": {
    "addr:full":"281 Meadows Dr Boynton Beach FL 33436",
    "addr:housenumber":"281",
    "addr:postcode":"33436",
    "addr:street":"Meadows Dr",
    "iso:country":"US",
    "sg:address":"281 Meadows Dr",
    "sg:city":"Boynton Beach",
    "sg:classifiers":[
        {
            "category":"Building & Trades",
            "subcategory":"Electrical",
            "type":"Services"
        }
    ],
    "sg:phone":"+1 561 968 7992",
    "sg:postcode":"33436",
    "sg:province":"FL",
    "sg:tags":[
        "electrical",
        "contractor"
    ],
    "wof:name":"S&C Lite Maintenance",
    "wof:placetype":"venue"
},
  "geometry": {"coordinates":[-80.092502,26.560325],"type":"Point"}
}