{
  "type": "Feature",
  "properties": {
    "addr:full":"17920 Meridian Blvd Hudson FL 34667",
    "addr:housenumber":"17920",
    "addr:postcode":"34667",
    "addr:street":"Meridian Blvd",
    "iso:country":"US",
    "sg:address":"17920 Meridian Blvd",
    "sg:city":"Hudson",
    "sg:classifiers":[
        {
            "category":"Organizations",
            "subcategory":"Religious Organization",
            "type":"Services"
        }
    ],
    "sg:phone":"+1 727 863 8989",
    "sg:postcode":"34667",
    "sg:province":"FL",
    "sg:tags":[
        "god",
        "churches-assemblies"
    ],
    "wof:name":"Praise Assembly Of God",
    "wof:placetype":"venue"
},
  "geometry": {"coordinates":[-82.644452,28.417215],"type":"Point"}
}