{
  "type": "Feature",
  "properties": {
    "addr:full":"12405 SW 130th St Miami FL 33186",
    "addr:housenumber":"12405",
    "addr:postcode":"33186",
    "addr:street":"Sw 130Th St",
    "iso:country":"US",
    "sg:address":"12405 SW 130th St",
    "sg:city":"Miami",
    "sg:classifiers":[
        {
            "category":"Wholesale",
            "subcategory":"Machinery & Supplies",
            "type":"Manufacturing & Wholesale Goods"
        }
    ],
    "sg:phone":"+1 305 371 5551",
    "sg:postcode":"33186",
    "sg:province":"FL",
    "sg:tags":[
        "distributor",
        "equipment",
        "industrial"
    ],
    "wof:name":"Traeger Brothers & Associates",
    "wof:placetype":"venue"
},
  "geometry": {"coordinates":[-80.39531700000001,25.646961],"type":"Point"}
}