{
  "type": "Feature",
  "properties": {
    "addr:full":"2997 W 12th Ave Hialeah FL 33012",
    "addr:housenumber":"2997",
    "addr:postcode":"33012",
    "addr:street":"W 12Th Ave",
    "iso:country":"US",
    "sg:address":"2997 W 12th Ave",
    "sg:city":"Hialeah",
    "sg:classifiers":[
        {
            "category":"Shopping",
            "subcategory":"Clothing, Apparel, & Fashions",
            "type":"Retail Goods"
        }
    ],
    "sg:phone":"+1 305 885 3223",
    "sg:postcode":"33012",
    "sg:province":"FL",
    "wof:name":"Leonor Fashion",
    "wof:placetype":"venue"
},
  "geometry": {"coordinates":[-80.30623199999999,25.848007],"type":"Point"}
}