{
  "type": "Feature",
  "properties": {
    "addr:full":"2998 Sun Pointe Ct Kissimmee FL 34741",
    "addr:housenumber":"2998",
    "addr:postcode":"34741",
    "addr:street":"Sun Pointe Ct",
    "iso:country":"US",
    "sg:address":"2998 Sun Pointe Ct",
    "sg:city":"Kissimmee",
    "sg:classifiers":[
        {
            "category":"Building & Trades",
            "subcategory":"Landscaping Services",
            "type":"Services"
        }
    ],
    "sg:phone":"+1 407 846 8455",
    "sg:postcode":"34741",
    "sg:province":"FL",
    "wof:name":"Kissimmee Landscape & Mowing",
    "wof:placetype":"venue"
},
  "geometry": {"coordinates":[-81.406572,28.334836],"type":"Point"}
}