{
  "type": "Feature",
  "properties": {
    "addr:full":"9302 SW 126th St Archer FL 32618",
    "addr:housenumber":"9302",
    "addr:postcode":"32618",
    "addr:street":"Sw 126Th St",
    "iso:country":"US",
    "sg:address":"9302 SW 126th St",
    "sg:city":"Archer",
    "sg:classifiers":[
        {
            "category":"Wholesale",
            "subcategory":"Plants",
            "type":"Manufacturing & Wholesale Goods"
        }
    ],
    "sg:phone":"+1 352 495 2988",
    "sg:postcode":"32618",
    "sg:province":"FL",
    "sg:tags":[
        "supply"
    ],
    "wof:name":"Mc Ewen & Wife Nursery",
    "wof:placetype":"venue"
},
  "geometry": {"coordinates":[-82.476201,29.565751],"type":"Point"}
}