{
  "type": "Feature",
  "properties": {
    "iso:country":"US",
    "sg:address":"8437 Tuttle Ave",
    "sg:city":"Sarasota",
    "sg:classifiers":[
        {
            "category":"Building & Trades",
            "subcategory":"Construction",
            "type":"Services"
        }
    ],
    "sg:phone":"+1 941 727 8581",
    "sg:postcode":"34243",
    "sg:province":"FL",
    "sg:tags":[
        "general",
        "contractor"
    ],
    "wof:name":"W G Mills Inc South",
    "wof:placetype":"venue"
},
  "geometry": {"coordinates":[-82.51375400000001,27.391081],"type":"Point"}
}