{
  "type": "Feature",
  "properties": {
    "addr:full":"2655 NE 186th Ter Miami FL 33180",
    "addr:housenumber":"2655",
    "addr:postcode":"33180",
    "addr:street":"Ne 186Th Ter",
    "iso:country":"US",
    "sg:address":"2655 NE 186th Ter",
    "sg:city":"Miami",
    "sg:classifiers":[
        {
            "category":"Retail",
            "subcategory":"Auto Repair",
            "type":"Services"
        }
    ],
    "sg:phone":"+1 305 932 1644",
    "sg:postcode":"33180",
    "sg:province":"FL",
    "sg:tags":[
        "body",
        "automotive"
    ],
    "wof:name":"U S Garage",
    "wof:placetype":"venue"
},
  "geometry": {"coordinates":[-80.147903,25.948099],"type":"Point"}
}