{
  "type": "Feature",
  "properties": {
    "iso:country":"US",
    "sg:address":"2971 Ericusa Ln",
    "sg:city":"Indialantic",
    "sg:classifiers":[
        {
            "category":"Professional",
            "subcategory":"Engineering",
            "type":"Services"
        }
    ],
    "sg:phone":"+1 321 773 7814",
    "sg:postcode":"32903",
    "sg:province":"FL",
    "sg:tags":[
        "engineer",
        "mechanical"
    ],
    "wof:name":"Agile Engineering Inc",
    "wof:placetype":"venue"
},
  "geometry": {"coordinates":[-80.585632,28.132332],"type":"Point"}
}