{
  "type": "Feature",
  "properties": {
    "iso:country":"US",
    "sg:address":"3015 Jefferson St",
    "sg:city":"Marianna",
    "sg:classifiers":[
        {
            "category":"Health Services",
            "subcategory":"Hospital",
            "type":"Services"
        }
    ],
    "sg:phone":"+1 850 526 2496",
    "sg:postcode":"32446",
    "sg:province":"FL",
    "sg:tags":[
        "medical",
        "center"
    ],
    "wof:name":"Airis Open Mri Of Marianna",
    "wof:placetype":"venue"
},
  "geometry": {"coordinates":[-85.226635,30.783558],"type":"Point"}
}