{
  "type": "Feature",
  "properties": {
    "addr:full":"8601 Bowles Rd Tampa FL 33637",
    "addr:housenumber":"8601",
    "addr:postcode":"33637",
    "addr:street":"Bowles Rd",
    "iso:country":"US",
    "sg:address":"8601 Bowles Rd",
    "sg:city":"Tampa",
    "sg:classifiers":[
        {
            "category":"Organizations",
            "subcategory":"Membership Organization",
            "type":"Services"
        }
    ],
    "sg:phone":"+1 813 988 7783",
    "sg:postcode":"33637",
    "sg:province":"FL",
    "wof:name":"301 House Inc",
    "wof:placetype":"venue"
},
  "geometry": {"coordinates":[-82.34754599999999,28.02587],"type":"Point"}
}