{
  "type": "Feature",
  "properties": {
    "iso:country":"US",
    "sg:address":"2928 NE 21 Way",
    "sg:city":"Gainesville",
    "sg:classifiers":[
        {
            "category":"Autos & Motor Vehicles",
            "subcategory":"Auto Supplies",
            "type":"Retail Goods"
        }
    ],
    "sg:phone":"+1 352 377 9590",
    "sg:postcode":"32609",
    "sg:province":"FL",
    "sg:tags":[
        "tire"
    ],
    "wof:name":"Dale's Tire Inc",
    "wof:placetype":"venue"
},
  "geometry": {"coordinates":[-82.29567299999999,29.678876],"type":"Point"}
}