{
  "type": "Feature",
  "properties": {
    "addr:full":"3333 Capital Medical Blvd Tallahassee FL 32308",
    "addr:housenumber":"3333",
    "addr:postcode":"32308",
    "addr:street":"Capital Medical Blvd",
    "iso:country":"US",
    "sg:address":"3333 Capital Medical Blvd",
    "sg:city":"Tallahassee",
    "sg:classifiers":[
        {
            "category":"Health Services",
            "subcategory":"Nursing And Care Facility",
            "type":"Services"
        }
    ],
    "sg:phone":"+1 850 877 4115",
    "sg:postcode":"32308",
    "sg:province":"FL",
    "sg:tags":[
        "home",
        "skilled",
        "convalescent"
    ],
    "wof:name":"Capital Health Care Center",
    "wof:placetype":"venue"
},
  "geometry": {"coordinates":[-84.225016,30.47589],"type":"Point"}
}