{
  "type": "Feature",
  "properties": {
    "iso:country":"US",
    "sg:address":"7244 Biscayne Blvd",
    "sg:city":"Miami",
    "sg:classifiers":[
        {
            "category":"Shopping",
            "subcategory":"Used Merchandise",
            "type":"Retail Goods"
        }
    ],
    "sg:phone":"+1 305 751 1973",
    "sg:postcode":"33138",
    "sg:province":"FL",
    "sg:tags":[
        "antique"
    ],
    "wof:name":"Divine Trash Inc",
    "wof:placetype":"venue"
},
  "geometry": {"coordinates":[-80.184303,25.8421],"type":"Point"}
}