{
  "type": "Feature",
  "properties": {
    "iso:country":"US",
    "sg:address":"1847 Florida Ave",
    "sg:city":"Panama City",
    "sg:classifiers":[
        {
            "category":"Social Services",
            "subcategory":"Job Training",
            "type":"Services"
        }
    ],
    "sg:phone":"+1 850 914 8600",
    "sg:postcode":"32405",
    "sg:province":"FL",
    "sg:tags":[
        "rehabilitation"
    ],
    "wof:name":"Healthsouth Emerald Coast",
    "wof:placetype":"venue"
},
  "geometry": {"coordinates":[-85.668404,30.176033],"type":"Point"}
}