{
  "type": "Feature",
  "properties": {
    "iso:country":"US",
    "sg:address":"4967 N University Dr",
    "sg:city":"Lauderhill",
    "sg:classifiers":[
        {
            "category":"Real Estate",
            "subcategory":"Real Estate Services",
            "type":"Services"
        },
        {
            "category":"Real Estate",
            "subcategory":"Real Estate Agent",
            "type":"Services"
        }
    ],
    "sg:phone":"+1 954 741 0702",
    "sg:postcode":"33351",
    "sg:province":"FL",
    "sg:tags":[
        "buyer",
        "broker"
    ],
    "wof:name":"Hk Realty",
    "wof:placetype":"venue"
},
  "geometry": {"coordinates":[-80.25200700000001,26.187011],"type":"Point"}
}