{
  "type": "Feature",
  "properties": {
    "iso:country":"US",
    "sg:address":"13775 N Nebraska Ave",
    "sg:city":"Tampa",
    "sg:classifiers":[
        {
            "category":"Manufacturing",
            "subcategory":"Buildings",
            "type":"Manufacturing & Wholesale Goods"
        },
        {
            "category":"Building & Trades",
            "subcategory":"Construction",
            "type":"Services"
        }
    ],
    "sg:phone":"+1 813 963 5555",
    "sg:postcode":"33613",
    "sg:province":"FL",
    "sg:tags":[
        "home",
        "builder",
        "management",
        "contractor"
    ],
    "wof:name":"Wild Hog Construction",
    "wof:placetype":"venue"
},
  "geometry": {"coordinates":[-82.45112899999999,28.072736],"type":"Point"}
}