{
  "type": "Feature",
  "properties": {
    "iso:country":"US",
    "sg:address":"13650 Innerarity Point Rd",
    "sg:city":"Pensacola",
    "sg:classifiers":[
        {
            "category":"Home & Garden",
            "subcategory":"Hardware",
            "type":"Retail Goods"
        }
    ],
    "sg:phone":"+1 850 492 1149",
    "sg:postcode":"32507",
    "sg:province":"FL",
    "wof:name":"Innerarity True Value Hardware",
    "wof:placetype":"venue"
},
  "geometry": {"coordinates":[-87.428481,30.318549],"type":"Point"}
}