{
  "type": "Feature",
  "properties": {
    "addr:full":"19301 Seacove Dr Lutz FL 33558",
    "addr:postcode":"19301;33558",
    "addr:street":"Seacove Dr",
    "iso:country":"US",
    "sg:address":"19301 Seacove Dr",
    "sg:city":"Lutz",
    "sg:classifiers":[
        {
            "category":"Banks & Credit Unions",
            "subcategory":"Investment Brokerage",
            "type":"Services"
        }
    ],
    "sg:phone":"+1 813 242 7964",
    "sg:postcode":"33558",
    "sg:province":"FL",
    "sg:tags":[
        "advisory",
        "financial"
    ],
    "wof:name":"ARS Financial Group",
    "wof:placetype":"venue"
},
  "geometry": {"coordinates":[-82.510075,28.164002],"type":"Point"}
}