{
  "type": "Feature",
  "properties": {
    "addr:full":"9440 Arlington Expy Jacksonville FL 32225",
    "addr:housenumber":"9440",
    "addr:postcode":"32225",
    "addr:street":"Arlington Expy",
    "iso:country":"US",
    "sg:address":"9440 Arlington Expy",
    "sg:city":"Jacksonville",
    "sg:classifiers":[
        {
            "category":"Shopping",
            "subcategory":"Clothing, Apparel, & Fashions",
            "type":"Retail Goods"
        }
    ],
    "sg:phone":"+1 904 716 5650",
    "sg:postcode":"32225",
    "sg:province":"FL",
    "sg:tags":[
        "hip",
        "urban"
    ],
    "wof:name":"Urban Flava",
    "wof:placetype":"venue"
},
  "geometry": {"coordinates":[-81.55295599999999,30.321399],"type":"Point"}
}