{
  "type": "Feature",
  "properties": {
    "addr:full":"1300 Palm Ave Hialeah FL 33010",
    "addr:housenumber":"1300",
    "addr:postcode":"33010",
    "addr:street":"Palm Ave",
    "iso:country":"US",
    "sg:address":"1300 Palm Ave",
    "sg:city":"Hialeah",
    "sg:classifiers":[
        {
            "category":"Food & Beverages",
            "subcategory":"Groceries & Convenience Stores",
            "type":"Retail Goods"
        }
    ],
    "sg:phone":"+1 305 887 3520",
    "sg:postcode":"33010",
    "sg:province":"FL",
    "sg:tags":[
        "grocer"
    ],
    "wof:name":"Tawfik Supermarket Inc",
    "wof:placetype":"venue"
},
  "geometry": {"coordinates":[-80.28180399999999,25.83448],"type":"Point"}
}