{
  "type": "Feature",
  "properties": {
    "addr:full":"323 S Dixie Hwy West Palm Beach FL 33401",
    "addr:housenumber":"323",
    "addr:postcode":"33401",
    "addr:street":"S Dixie Hwy",
    "iso:country":"US",
    "sg:address":"323 S Dixie Hwy",
    "sg:city":"West Palm Beach",
    "sg:classifiers":[
        {
            "category":"Retail",
            "subcategory":"Repair Shop",
            "type":"Services"
        }
    ],
    "sg:phone":"+1 561 655 8060",
    "sg:postcode":"33401",
    "sg:province":"FL",
    "sg:tags":[
        "appliance",
        "household",
        "electrical"
    ],
    "wof:name":"Felder-Bell",
    "wof:placetype":"venue"
},
  "geometry": {"coordinates":[-80.05368199999999,26.710583],"type":"Point"}
}