{
  "type": "Feature",
  "properties": {
    "iso:country":"US",
    "sg:address":"2165 River Blvd",
    "sg:city":"Jacksonville",
    "sg:classifiers":[
        {
            "category":"Banks & Credit Unions",
            "subcategory":"Financial Services",
            "type":"Services"
        }
    ],
    "sg:phone":"+1 904 387 2295",
    "sg:postcode":"32204",
    "sg:province":"FL",
    "sg:tags":[
        "investor"
    ],
    "wof:name":"Thomasville Investment Company",
    "wof:placetype":"venue"
},
  "geometry": {"coordinates":[-81.682593,30.309344],"type":"Point"}
}