{
  "type": "Feature",
  "properties": {
    "addr:full":"10909 W Linebaugh Ave Tampa FL 33626",
    "addr:housenumber":"10909",
    "addr:postcode":"33626",
    "addr:street":"W Linebaugh Ave",
    "iso:country":"US",
    "sg:address":"10909 W Linebaugh Ave",
    "sg:city":"Tampa",
    "sg:classifiers":[
        {
            "category":"Health Services",
            "subcategory":"Health Practitioner",
            "type":"Services"
        }
    ],
    "sg:phone":"+1 813 926 3697",
    "sg:postcode":"33626",
    "sg:province":"FL",
    "wof:name":"Health Point Medical Group",
    "wof:placetype":"venue"
},
  "geometry": {"coordinates":[-82.61274899999999,28.049767],"type":"Point"}
}