{
  "type": "Feature",
  "properties": {
    "iso:country":"US",
    "sg:address":"1900 N Mills Ave",
    "sg:city":"Orlando",
    "sg:classifiers":[
        {
            "category":"Personal",
            "type":"Services"
        }
    ],
    "sg:phone":"+1 407 228 8228",
    "sg:postcode":"32803",
    "sg:province":"FL",
    "sg:tags":[
        "therapist",
        "massage"
    ],
    "wof:name":"New Directions Health Bodywork",
    "wof:placetype":"venue"
},
  "geometry": {"coordinates":[-81.36452800000001,28.567984],"type":"Point"}
}