{
  "type": "Feature",
  "properties": {
    "iso:country":"US",
    "sg:address":"1271 King St",
    "sg:city":"Jacksonville",
    "sg:classifiers":[
        {
            "category":"Social Services",
            "subcategory":"Child Care",
            "type":"Services"
        }
    ],
    "sg:phone":"+1 904 381 9866",
    "sg:postcode":"32204",
    "sg:province":"FL",
    "wof:name":"Heavensent Inc",
    "wof:placetype":"venue"
},
  "geometry": {"coordinates":[-81.69365999999999,30.310713],"type":"Point"}
}