{
  "type": "Feature",
  "properties": {
    "iso:country":"US",
    "sg:address":"5103 Silver Star Rd",
    "sg:city":"Orlando",
    "sg:classifiers":[
        {
            "category":"Personal",
            "subcategory":"Beauty Salon",
            "type":"Services"
        }
    ],
    "sg:phone":"+1 407 293 2266",
    "sg:postcode":"32808",
    "sg:province":"FL",
    "sg:tags":[
        "shop"
    ],
    "wof:name":"Linda Bridges Hair & Nails",
    "wof:placetype":"venue"
},
  "geometry": {"coordinates":[-81.451455,28.57788],"type":"Point"}
}