{
  "type": "Feature",
  "properties": {
    "iso:country":"US",
    "sg:address":"1212 Providence Blvd",
    "sg:city":"Deltona",
    "sg:classifiers":[
        {
            "category":"Retail",
            "subcategory":"Funeral Services",
            "type":"Services"
        }
    ],
    "sg:phone":"+1 386 574 8899",
    "sg:postcode":"32725",
    "sg:province":"FL",
    "sg:tags":[
        "director"
    ],
    "wof:name":"Marchbank Curry & Long Fnrl Hm",
    "wof:placetype":"venue"
},
  "geometry": {"coordinates":[-81.242637,28.880682],"type":"Point"}
}