{
  "type": "Feature",
  "properties": {
    "iso:country":"US",
    "sg:address":"4526 S Clark Ave",
    "sg:city":"Tampa",
    "sg:classifiers":[
        {
            "category":"Professional",
            "subcategory":"Accounting & Tax Preparation",
            "type":"Services"
        }
    ],
    "sg:phone":"+1 813 831 3638",
    "sg:postcode":"33611",
    "sg:province":"FL",
    "sg:tags":[
        "return",
        "filing"
    ],
    "wof:name":"Franklynne Tax Express",
    "wof:placetype":"venue"
},
  "geometry": {"coordinates":[-82.51228,27.898297],"type":"Point"}
}