{
  "type": "Feature",
  "properties": {
    "iso:country":"US",
    "sg:address":"900 E Atlantic Blvd",
    "sg:city":"Pompano Beach",
    "sg:classifiers":[
        {
            "category":"Professional",
            "subcategory":"Computer Services",
            "type":"Services"
        }
    ],
    "sg:phone":"+1 954 942 7447",
    "sg:postcode":"33060",
    "sg:province":"FL",
    "sg:tags":[
        "consultant",
        "designer"
    ],
    "wof:name":"Emerging Technology Solutions",
    "wof:placetype":"venue"
},
  "geometry": {"coordinates":[-80.11347000000001,26.231721],"type":"Point"}
}