{
  "type": "Feature",
  "properties": {
    "iso:country":"US",
    "sg:address":"3474 N University Dr",
    "sg:city":"Sunrise",
    "sg:classifiers":[
        {
            "category":"Local Transit",
            "type":"Transportation"
        }
    ],
    "sg:phone":"+1 954 777 9911",
    "sg:postcode":"33322",
    "sg:province":"FL",
    "sg:tags":[
        "limousine"
    ],
    "wof:name":"Carriage Limousines Inc",
    "wof:placetype":"venue"
},
  "geometry": {"coordinates":[-80.256429,26.167011],"type":"Point"}
}