{
  "type": "Feature",
  "properties": {
    "addr:full":"9484 Southern Garden Cir Altamonte Springs FL 32714",
    "addr:housenumber":"9484",
    "addr:postcode":"32714",
    "addr:street":"Southern Garden Cir",
    "iso:country":"US",
    "sg:address":"9484 Southern Garden Cir",
    "sg:city":"Altamonte Springs",
    "sg:classifiers":[
        {
            "category":"Building & Trades",
            "subcategory":"Construction",
            "type":"Services"
        }
    ],
    "sg:phone":"+1 407 592 9143",
    "sg:postcode":"32714",
    "sg:province":"FL",
    "sg:tags":[
        "contractor"
    ],
    "wof:name":"L&S Aluminum",
    "wof:placetype":"venue"
},
  "geometry": {"coordinates":[-81.438592,28.643321],"type":"Point"}
}