{
  "type": "Feature",
  "properties": {
    "iso:country":"US",
    "sg:address":"1343 St Tropez Cir",
    "sg:city":"Weston",
    "sg:classifiers":[
        {
            "category":"Real Estate",
            "subcategory":"Real Estate Operator",
            "type":"Services"
        }
    ],
    "sg:phone":"+1 954 385 1300",
    "sg:postcode":"33326",
    "sg:province":"FL",
    "sg:tags":[
        "apartment"
    ],
    "wof:name":"Gables Residental",
    "wof:placetype":"venue"
},
  "geometry": {"coordinates":[-80.38034,26.101259],"type":"Point"}
}