{
  "type": "Feature",
  "properties": {
    "iso:country":"US",
    "sg:address":"1413 Magnolia Dr",
    "sg:city":"Clearwater",
    "sg:classifiers":[
        {
            "category":"Building & Trades",
            "subcategory":"Construction",
            "type":"Services"
        }
    ],
    "sg:phone":"+1 727 466 6105",
    "sg:postcode":"33756",
    "sg:province":"FL",
    "sg:tags":[
        "contractor"
    ],
    "wof:name":"Augusto Roofing Inc",
    "wof:placetype":"venue"
},
  "geometry": {"coordinates":[-82.77118,27.955658],"type":"Point"}
}