{
  "type": "Feature",
  "properties": {
    "iso:country":"US",
    "sg:address":"1509 Pine Ave",
    "sg:city":"Orlando",
    "sg:classifiers":[
        {
            "category":"Professional",
            "subcategory":"Art Services",
            "type":"Services"
        }
    ],
    "sg:phone":"+1 407 447 0689",
    "sg:postcode":"32824",
    "sg:province":"FL",
    "sg:tags":[
        "commercial",
        "graphic",
        "design"
    ],
    "wof:name":"Visible Design Corp",
    "wof:placetype":"venue"
},
  "geometry": {"coordinates":[-81.357387,28.441317],"type":"Point"}
}