{
  "type": "Feature",
  "properties": {
    "iso:country":"US",
    "sg:address":"552 Edward Rutledge St",
    "sg:city":"Orange Park",
    "sg:classifiers":[
        {
            "category":"Professional",
            "subcategory":"Art Services",
            "type":"Services"
        }
    ],
    "sg:phone":"+1 904 272 8477",
    "sg:postcode":"32073",
    "sg:province":"FL",
    "sg:tags":[
        "photography",
        "commercial"
    ],
    "wof:name":"Steve and Brenda Estes",
    "wof:placetype":"venue"
},
  "geometry": {"coordinates":[-81.757273,30.158241],"type":"Point"}
}