{
  "type": "Feature",
  "properties": {
    "addr:full":"3109 W Azeele St Tampa FL 33609",
    "addr:housenumber":"3109",
    "addr:postcode":"33609",
    "addr:street":"W Azeele St",
    "iso:country":"US",
    "sg:address":"3109 W Azeele St",
    "sg:city":"Tampa",
    "sg:classifiers":[
        {
            "category":"Insurance",
            "subcategory":"Insurance Agent",
            "type":"Services"
        }
    ],
    "sg:phone":"+1 813 876 1546",
    "sg:postcode":"33609",
    "sg:province":"FL",
    "wof:name":"John A Mangin Jr CLU",
    "wof:placetype":"venue"
},
  "geometry": {"coordinates":[-82.495304,27.941225],"type":"Point"}
}