{
  "type": "Feature",
  "properties": {
    "addr:full":"25400 US Hwy 19 Clearwater FL 33763",
    "addr:housenumber":"25400",
    "addr:postcode":"33763",
    "addr:street":"Us Hwy 19",
    "iso:country":"US",
    "sg:address":"25400 US Hwy 19",
    "sg:city":"Clearwater",
    "sg:classifiers":[
        {
            "category":"Health Services",
            "subcategory":"Doctor",
            "type":"Services"
        }
    ],
    "sg:phone":"+1 727 796 2427",
    "sg:postcode":"33763",
    "sg:province":"FL",
    "sg:tags":[
        "dentist"
    ],
    "wof:name":"John Ionata DDS",
    "wof:placetype":"venue"
},
  "geometry": {"coordinates":[-82.729812,28.006145],"type":"Point"}
}