{
  "type": "Feature",
  "properties": {
    "iso:country":"US",
    "sg:address":"1162 SE 13th St",
    "sg:city":"Stuart",
    "sg:classifiers":[
        {
            "category":"Health Services",
            "subcategory":"Medical Lab",
            "type":"Services"
        }
    ],
    "sg:phone":"+1 772 221 9999",
    "sg:postcode":"34996",
    "sg:province":"FL",
    "sg:tags":[
        "detection",
        "equipment",
        "drug"
    ],
    "wof:name":"Aware Drug Testing Inc",
    "wof:placetype":"venue"
},
  "geometry": {"coordinates":[-80.232573,27.187305],"type":"Point"}
}