{
  "type": "Feature",
  "properties": {
    "iso:country":"US",
    "sg:address":"2700 W Atlantic Blvd",
    "sg:city":"Pompano Beach",
    "sg:classifiers":[
        {
            "category":"Shopping",
            "subcategory":"Luggage & Leather Goods",
            "type":"Retail Goods"
        }
    ],
    "sg:phone":"+1 954 472 9836",
    "sg:postcode":"33069",
    "sg:province":"FL",
    "wof:name":"Agla",
    "wof:placetype":"venue"
},
  "geometry": {"coordinates":[-80.161389,26.23123],"type":"Point"}
}