{
  "type": "Feature",
  "properties": {
    "iso:country":"US",
    "sg:address":"4810 Deltona Dr",
    "sg:city":"Punta Gorda",
    "sg:classifiers":[
        {
            "category":"Communications",
            "subcategory":"Radio Station",
            "type":"Services"
        }
    ],
    "sg:phone":"+1 941 639 1188",
    "sg:postcode":"33950",
    "sg:province":"FL",
    "wof:name":"Wccf-AM",
    "wof:placetype":"venue"
},
  "geometry": {"coordinates":[-82.05144799999999,26.891637],"type":"Point"}
}