{
  "type": "Feature",
  "properties": {
    "addr:full":"5889 SW 21st St Hollywood FL 33023",
    "addr:housenumber":"5889",
    "addr:postcode":"33023",
    "addr:street":"Sw 21St St",
    "iso:country":"US",
    "sg:address":"5889 SW 21st St",
    "sg:city":"Hollywood",
    "sg:classifiers":[
        {
            "category":"Wholesale",
            "subcategory":"Chemicals & Plastics",
            "type":"Manufacturing & Wholesale Goods"
        }
    ],
    "sg:phone":"+1 954 961 4656",
    "sg:postcode":"33023",
    "sg:province":"FL",
    "sg:tags":[
        "resin"
    ],
    "wof:name":"Epoxytec International Inc",
    "wof:placetype":"venue"
},
  "geometry": {"coordinates":[-80.204534,25.991696],"type":"Point"}
}