{
  "type": "Feature",
  "properties": {
    "iso:country":"US",
    "sg:address":"400 Hamilton Rd",
    "sg:city":"Deland",
    "sg:classifiers":[
        {
            "category":"Wholesale",
            "subcategory":"Non-durable Goods",
            "type":"Manufacturing & Wholesale Goods"
        }
    ],
    "sg:phone":"+1 386 734 6888",
    "sg:postcode":"32724",
    "sg:province":"FL",
    "wof:name":"Source One",
    "wof:placetype":"venue"
},
  "geometry": {"coordinates":[-81.298188,29.061912],"type":"Point"}
}