{
  "type": "Feature",
  "properties": {
    "iso:country":"US",
    "sg:address":"1145 Capricorn Blvd",
    "sg:city":"Punta Gorda",
    "sg:classifiers":[
        {
            "category":"Real Estate",
            "subcategory":"Real Estate Operator",
            "type":"Services"
        }
    ],
    "sg:phone":"+1 941 627 9999",
    "sg:postcode":"33983",
    "sg:province":"FL",
    "sg:tags":[
        "building",
        "nonresidential"
    ],
    "wof:name":"Storage America",
    "wof:placetype":"venue"
},
  "geometry": {"coordinates":[-82.040706,27.015456],"type":"Point"}
}