{
  "type": "Feature",
  "properties": {
    "addr:full":"22129 Carson Dr Land O Lakes FL 34639",
    "addr:housenumber":"22129",
    "addr:postcode":"34639",
    "addr:street":"Carson Dr",
    "iso:country":"US",
    "sg:address":"22129 Carson Dr",
    "sg:city":"Land O Lakes",
    "sg:classifiers":[
        {
            "category":"Farming",
            "subcategory":"Livestock Farm",
            "type":"Manufacturing & Wholesale Goods"
        }
    ],
    "sg:phone":"+1 813 949 1687",
    "sg:postcode":"34639",
    "sg:province":"FL",
    "sg:tags":[
        "specialty",
        "animal"
    ],
    "wof:name":"Parwick Kennels",
    "wof:placetype":"venue"
},
  "geometry": {"coordinates":[-82.45174400000001,28.193873],"type":"Point"}
}