{
  "type": "Feature",
  "properties": {
    "addr:full":"4287 43rd St N Saint Petersburg FL 33714",
    "addr:housenumber":"4287",
    "addr:postcode":"33714",
    "addr:street":"43Rd St N",
    "iso:country":"US",
    "sg:address":"4287 43rd St N",
    "sg:city":"Saint Petersburg",
    "sg:classifiers":[
        {
            "category":"Autos & Motor Vehicles",
            "subcategory":"Auto Supplies",
            "type":"Retail Goods"
        }
    ],
    "sg:phone":"+1 727 522 2947",
    "sg:postcode":"33714",
    "sg:province":"FL",
    "wof:name":"Classic Mustangs",
    "wof:placetype":"venue"
},
  "geometry": {"coordinates":[-82.691765,27.810202],"type":"Point"}
}