{
  "type": "Feature",
  "properties": {
    "iso:country":"US",
    "sg:address":"4850 W Oakland Park Blvd",
    "sg:city":"Fort Lauderdale",
    "sg:classifiers":[
        {
            "category":"Shopping",
            "subcategory":"Clothing, Apparel, & Fashions",
            "type":"Retail Goods"
        }
    ],
    "sg:phone":"+1 954 485 6525",
    "sg:postcode":"33313",
    "sg:province":"FL",
    "sg:tags":[
        "ready",
        "to",
        "handbag",
        "wear"
    ],
    "wof:name":"Faye The Bag Lady Inc",
    "wof:placetype":"venue"
},
  "geometry": {"coordinates":[-80.21381100000001,26.164808],"type":"Point"}
}