{
  "type": "Feature",
  "properties": {
    "addr:full":"3380 NW 114th St Miami FL 33167",
    "addr:housenumber":"3380",
    "addr:postcode":"33167",
    "addr:street":"Nw 114Th St",
    "iso:country":"US",
    "sg:address":"3380 NW 114th St",
    "sg:city":"Miami",
    "sg:classifiers":[
        {
            "category":"Freight",
            "type":"Transportation"
        }
    ],
    "sg:phone":"+1 305 455 4310",
    "sg:postcode":"33167",
    "sg:province":"FL",
    "sg:tags":[
        "cargo",
        "container"
    ],
    "wof:name":"Manray Express",
    "wof:placetype":"venue"
},
  "geometry": {"coordinates":[-80.254363,25.878279],"type":"Point"}
}