{
  "type": "Feature",
  "properties": {
    "iso:country":"US",
    "sg:address":"16401 S Tamiami Trl",
    "sg:city":"Fort Myers",
    "sg:classifiers":[
        {
            "category":"Autos & Motor Vehicles",
            "subcategory":"Fuel & Gas Station",
            "type":"Retail Goods"
        }
    ],
    "sg:phone":"+1 239 415 0151",
    "sg:postcode":"33908",
    "sg:province":"FL",
    "wof:name":"Island Express",
    "wof:placetype":"venue"
},
  "geometry": {"coordinates":[-81.856003,26.502701],"type":"Point"}
}