{
  "type": "Feature",
  "properties": {
    "iso:country":"US",
    "sg:address":"60 Kon Tiki Cir",
    "sg:city":"Saint Augustine",
    "sg:classifiers":[
        {
            "category":"Banks & Credit Unions",
            "subcategory":"Financial Services",
            "type":"Services"
        }
    ],
    "sg:phone":"+1 904 471 3315",
    "sg:postcode":"32080",
    "sg:province":"FL",
    "sg:tags":[
        "trust",
        "investment",
        "real estate"
    ],
    "wof:name":"Dock Street Group LLC",
    "wof:placetype":"venue"
},
  "geometry": {"coordinates":[-81.264691,29.790513],"type":"Point"}
}