{
  "type": "Feature",
  "properties": {
    "iso:country":"US",
    "sg:address":"5420 95th Ter N",
    "sg:city":"Pinellas Park",
    "sg:classifiers":[
        {
            "category":"Utilities",
            "subcategory":"Telephone",
            "type":"Services"
        }
    ],
    "sg:phone":"+1 727 541 2842",
    "sg:postcode":"33782",
    "sg:province":"FL",
    "sg:tags":[
        "communications"
    ],
    "wof:name":"Coveredwagonantiques Co",
    "wof:placetype":"venue"
},
  "geometry": {"coordinates":[-82.708296,27.858591],"type":"Point"}
}