{
  "type": "Feature",
  "properties": {
    "addr:full":"2973 Wentworth Fort Lauderdale FL 33332",
    "addr:housenumber":"2973",
    "addr:postcode":"33332",
    "addr:street":"Wentworth",
    "iso:country":"US",
    "sg:address":"2973 Wentworth",
    "sg:city":"Fort Lauderdale",
    "sg:classifiers":[
        {
            "category":"Professional",
            "subcategory":"Management & Consulting",
            "type":"Services"
        }
    ],
    "sg:phone":"+1 954 349 1880",
    "sg:postcode":"33332",
    "sg:province":"FL",
    "sg:tags":[
        "international",
        "business"
    ],
    "wof:name":"McGrath Consultants Inc",
    "wof:placetype":"venue"
},
  "geometry": {"coordinates":[-80.396676,26.081549],"type":"Point"}
}