{
  "type": "Feature",
  "properties": {
    "addr:full":"9850 Starkey Rd Largo FL 33777",
    "addr:housenumber":"9850",
    "addr:postcode":"33777",
    "addr:street":"Starkey Rd",
    "iso:country":"US",
    "sg:address":"9850 Starkey Rd",
    "sg:city":"Largo",
    "sg:classifiers":[
        {
            "category":"Home & Garden",
            "subcategory":"Garden Supply",
            "type":"Retail Goods"
        }
    ],
    "sg:phone":"+1 727 397 4438",
    "sg:postcode":"33777",
    "sg:province":"FL",
    "sg:tags":[
        "center"
    ],
    "sg:website":"www.countryclubnursery.com",
    "wof:name":"Country Club Nursery Inc",
    "wof:placetype":"venue"
},
  "geometry": {"coordinates":[-82.762433,27.862104],"type":"Point"}
}