{
  "type": "Feature",
  "properties": {
    "addr:full":"1700 Evergreen Ct Kissimmee FL 34746",
    "addr:housenumber":"1700",
    "addr:postcode":"34746",
    "addr:street":"Evergreen Ct",
    "iso:country":"US",
    "sg:address":"1700 Evergreen Ct",
    "sg:city":"Kissimmee",
    "sg:classifiers":[
        {
            "category":"Wholesale",
            "subcategory":"Non-durable Goods",
            "type":"Manufacturing & Wholesale Goods"
        }
    ],
    "sg:phone":"+1 407 847 7822",
    "sg:postcode":"34746",
    "sg:province":"FL",
    "wof:name":"Multiprojects Corp",
    "wof:placetype":"venue"
},
  "geometry": {"coordinates":[-81.42183900000001,28.215112],"type":"Point"}
}