{
  "type": "Feature",
  "properties": {
    "iso:country":"US",
    "sg:address":"826 NW 12th Ave",
    "sg:city":"Pompano Beach",
    "sg:classifiers":[
        {
            "category":"Restaurant",
            "type":"Food & Drink"
        }
    ],
    "sg:phone":"+1 954 975 8181",
    "sg:postcode":"33069",
    "sg:province":"FL",
    "sg:tags":[
        "chinese"
    ],
    "wof:name":"Chinese Princess Restaurant",
    "wof:placetype":"venue"
},
  "geometry": {"coordinates":[-80.13758900000001,26.240002],"type":"Point"}
}