{
  "type": "Feature",
  "properties": {
    "addr:full":"6911 SW 19th St Hollywood FL 33023",
    "addr:housenumber":"6911",
    "addr:postcode":"33023",
    "addr:street":"Sw 19Th St",
    "iso:country":"US",
    "sg:address":"6911 SW 19th St",
    "sg:city":"Hollywood",
    "sg:classifiers":[
        {
            "category":"Building & Trades",
            "subcategory":"Construction",
            "type":"Services"
        }
    ],
    "sg:phone":"+1 954 668 9553",
    "sg:postcode":"33023",
    "sg:province":"FL",
    "sg:tags":[
        "floor",
        "laying",
        "contractor"
    ],
    "wof:name":"Ronald Singh",
    "wof:placetype":"venue"
},
  "geometry": {"coordinates":[-80.227099,25.994147],"type":"Point"}
}