{
  "type": "Feature",
  "properties": {
    "iso:country":"US",
    "sg:address":"1849 Miller Landing Rd",
    "sg:city":"Tallahassee",
    "sg:classifiers":[
        {
            "category":"Shopping",
            "type":"Retail Goods"
        }
    ],
    "sg:phone":"+1 850 893 4416",
    "sg:postcode":"32312",
    "sg:province":"FL",
    "sg:tags":[
        "merchandise"
    ],
    "wof:name":"Tallahassee Sign Shop Inc",
    "wof:placetype":"venue"
},
  "geometry": {"coordinates":[-84.304316,30.540493],"type":"Point"}
}