{
  "type": "Feature",
  "properties": {
    "addr:full":"26111 US Hwy 19 Clearwater FL 33763",
    "addr:postcode":"26111;33763",
    "addr:street":"Us Hwy 19",
    "iso:country":"US",
    "sg:address":"26111 US Hwy 19",
    "sg:city":"Clearwater",
    "sg:classifiers":[
        {
            "category":"Restaurant",
            "type":"Food & Drink"
        }
    ],
    "sg:phone":"+1 727 796 5806",
    "sg:postcode":"33763",
    "sg:province":"FL",
    "sg:tags":[
        "drinking",
        "eating"
    ],
    "wof:name":"TGI Fridays",
    "wof:placetype":"venue"
},
  "geometry": {"coordinates":[-82.73135499999999,28.009444],"type":"Point"}
}