{
  "type": "Feature",
  "properties": {
    "iso:country":"US",
    "sg:address":"6653 Powers Ave",
    "sg:city":"Jacksonville",
    "sg:classifiers":[
        {
            "category":"Building & Trades",
            "subcategory":"Construction",
            "type":"Services"
        }
    ],
    "sg:phone":"+1 904 448 4688",
    "sg:postcode":"32217",
    "sg:province":"FL",
    "sg:tags":[
        "contractor",
        "dry wall",
        "house"
    ],
    "wof:name":"Crosby Builders Inc",
    "wof:placetype":"venue"
},
  "geometry": {"coordinates":[-81.613202,30.249402],"type":"Point"}
}