{
  "type": "Feature",
  "properties": {
    "iso:country":"US",
    "sg:address":"19874 Latona Pl",
    "sg:city":"Boca Raton",
    "sg:classifiers":[
        {
            "category":"Restaurant",
            "type":"Food & Drink"
        }
    ],
    "sg:phone":"+1 561 477 9263",
    "sg:postcode":"33434",
    "sg:province":"FL",
    "sg:tags":[
        "eating"
    ],
    "wof:name":"Milews Bon Appetite Inc",
    "wof:placetype":"venue"
},
  "geometry": {"coordinates":[-80.191149,26.38085],"type":"Point"}
}