{
  "type": "Feature",
  "properties": {
    "iso:country":"US",
    "sg:address":"391 N Main St",
    "sg:city":"Kissimmee",
    "sg:classifiers":[
        {
            "category":"Professional",
            "subcategory":"Advertising",
            "type":"Services"
        },
        {
            "category":"Manufacturing",
            "subcategory":"Signs",
            "type":"Manufacturing & Wholesale Goods"
        },
        {
            "category":"Professional",
            "subcategory":"Printing & Photocopies",
            "type":"Services"
        }
    ],
    "sg:phone":"+1 407 933 7699",
    "sg:postcode":"34744",
    "sg:province":"FL",
    "sg:tags":[
        "plaque",
        "medal",
        "specialty",
        "trophies"
    ],
    "wof:name":"Affordable Signs",
    "wof:placetype":"venue"
},
  "geometry": {"coordinates":[-81.403728,28.295893],"type":"Point"}
}