{
  "type": "Feature",
  "properties": {
    "iso:country":"US",
    "sg:address":"9808 NW 80th Way",
    "sg:city":"Hialeah",
    "sg:classifiers":[
        {
            "category":"Manufacturing",
            "subcategory":"Furniture",
            "type":"Manufacturing & Wholesale Goods"
        }
    ],
    "sg:phone":"+1 305 819 2134",
    "sg:postcode":"33016",
    "sg:province":"FL",
    "sg:tags":[
        "mfr"
    ],
    "wof:name":"Anamar Cabinets Inc",
    "wof:placetype":"venue"
},
  "geometry": {"coordinates":[-80.328991,25.86357],"type":"Point"}
}