{
  "type": "Feature",
  "properties": {
    "iso:country":"US",
    "sg:address":"701 Fentress Blvd",
    "sg:city":"Daytona Beach",
    "sg:classifiers":[
        {
            "category":"Freight",
            "type":"Transportation"
        }
    ],
    "sg:phone":"+1 386 274 1526",
    "sg:postcode":"32114",
    "sg:province":"FL",
    "sg:tags":[
        "delivery",
        "pickup"
    ],
    "wof:name":"Airborne",
    "wof:placetype":"venue"
},
  "geometry": {"coordinates":[-81.082112,29.211878],"type":"Point"}
}