{
  "type": "Feature",
  "properties": {
    "iso:country":"US",
    "sg:address":"4610 W Silver Springs Blvd",
    "sg:city":"Ocala",
    "sg:classifiers":[
        {
            "category":"Wholesale",
            "subcategory":"Machinery & Supplies",
            "type":"Manufacturing & Wholesale Goods"
        }
    ],
    "sg:phone":"+1 352 369 8935",
    "sg:postcode":"34482",
    "sg:province":"FL",
    "sg:tags":[
        "trailer"
    ],
    "wof:name":"Trailer Town Ocala",
    "wof:placetype":"venue"
},
  "geometry": {"coordinates":[-82.19800600000001,29.186365],"type":"Point"}
}