{
  "type": "Feature",
  "properties": {
    "addr:full":"430 W Lakeview Ave Lake Mary FL 32746",
    "addr:housenumber":"430",
    "addr:postcode":"32746",
    "addr:street":"W Lakeview Ave",
    "iso:country":"US",
    "sg:address":"430 W Lakeview Ave",
    "sg:city":"Lake Mary",
    "sg:classifiers":[
        {
            "category":"Home & Garden",
            "subcategory":"Home Furnishings",
            "type":"Retail Goods"
        }
    ],
    "sg:phone":"+1 407 323 7625",
    "sg:postcode":"32746",
    "sg:province":"FL",
    "sg:tags":[
        "venetian",
        "blind"
    ],
    "wof:name":"Julia Hill Custom Window",
    "wof:placetype":"venue"
},
  "geometry": {"coordinates":[-81.33563700000001,28.758169],"type":"Point"}
}