{
  "type": "Feature",
  "properties": {
    "iso:country":"US",
    "sg:address":"201 S Maple St",
    "sg:city":"Englewood",
    "sg:classifiers":[
        {
            "category":"Building & Trades",
            "subcategory":"Construction",
            "type":"Services"
        }
    ],
    "sg:phone":"+1 941 468 0674",
    "sg:postcode":"34223",
    "sg:province":"FL",
    "sg:tags":[
        "home",
        "improvement"
    ],
    "wof:name":"Mike Brown Home Maintenance",
    "wof:placetype":"venue"
},
  "geometry": {"coordinates":[-82.35827999999999,26.956671],"type":"Point"}
}