{
  "type": "Feature",
  "properties": {
    "iso:country":"US",
    "sg:address":"9814 International Dr",
    "sg:city":"Orlando",
    "sg:classifiers":[
        {
            "category":"Wholesale",
            "subcategory":"Computers",
            "type":"Manufacturing & Wholesale Goods"
        }
    ],
    "sg:phone":"+1 407 447 2913",
    "sg:postcode":"32819",
    "sg:province":"FL",
    "wof:name":"ATM Trust Inc Mc Donalds",
    "wof:placetype":"venue"
},
  "geometry": {"coordinates":[-81.461643,28.425004],"type":"Point"}
}