{
  "type": "Feature",
  "properties": {
    "iso:country":"US",
    "sg:address":"3510 N 31st Ter",
    "sg:city":"Hollywood",
    "sg:classifiers":[
        {
            "category":"Health Services",
            "subcategory":"Doctor",
            "type":"Services"
        }
    ],
    "sg:phone":"+1 954 964 3021",
    "sg:postcode":"33021",
    "sg:province":"FL",
    "sg:tags":[
        "medical"
    ],
    "wof:name":"Beth Braver MD PA",
    "wof:placetype":"venue"
},
  "geometry": {"coordinates":[-80.172687,26.041555],"type":"Point"}
}