{
  "type": "Feature",
  "properties": {
    "iso:country":"US",
    "sg:address":"2746 S Orange Blossom Trl",
    "sg:city":"Orlando",
    "sg:classifiers":[
        {
            "category":"Retail",
            "subcategory":"Auto Repair",
            "type":"Services"
        }
    ],
    "sg:phone":"+1 407 843 5555",
    "sg:postcode":"32805",
    "sg:province":"FL",
    "sg:tags":[
        "repairing",
        "automobile"
    ],
    "wof:name":"Ron's Service Ctr",
    "wof:placetype":"venue"
},
  "geometry": {"coordinates":[-81.39708,28.514094],"type":"Point"}
}