{
  "type": "Feature",
  "properties": {
    "addr:full":"1299 S Military Trl Deerfield Beach FL 33442",
    "addr:housenumber":"1299",
    "addr:postcode":"33442",
    "addr:street":"S Military Trl",
    "iso:country":"US",
    "sg:address":"1299 S Military Trl",
    "sg:city":"Deerfield Beach",
    "sg:classifiers":[
        {
            "category":"Banks & Credit Unions",
            "subcategory":"Bank",
            "type":"Services"
        }
    ],
    "sg:phone":"+1 954 428 1900",
    "sg:postcode":"33442",
    "sg:province":"FL",
    "wof:name":"Bank Atlantic",
    "wof:placetype":"venue"
},
  "geometry": {"coordinates":[-80.13355900000001,26.300948],"type":"Point"}
}