{
  "type": "Feature",
  "properties": {
    "addr:full":"4404 S Florida Ave Lakeland FL 33813",
    "addr:housenumber":"4404",
    "addr:postcode":"33813",
    "addr:street":"S Florida Ave",
    "iso:country":"US",
    "sg:address":"4404 S Florida Ave",
    "sg:city":"Lakeland",
    "sg:classifiers":[
        {
            "category":"Building & Trades",
            "subcategory":"Plumbing",
            "type":"Services"
        }
    ],
    "sg:phone":"+1 863 646 5920",
    "sg:postcode":"33813",
    "sg:province":"FL",
    "sg:tags":[
        "air",
        "heating",
        "contractor",
        "system",
        "conditioning"
    ],
    "wof:name":"Creel Air Conditioning Inc",
    "wof:placetype":"venue"
},
  "geometry": {"coordinates":[-81.95682600000001,27.984318],"type":"Point"}
}