{
  "type": "Feature",
  "properties": {
    "iso:country":"US",
    "sg:address":"1310 Maximillian St",
    "sg:city":"Deltona",
    "sg:classifiers":[
        {
            "category":"Social Services",
            "type":"Services"
        }
    ],
    "sg:phone":"+1 386 574 9124",
    "sg:postcode":"32725",
    "sg:province":"FL",
    "sg:tags":[
        "organization",
        "welfare"
    ],
    "wof:name":"St Vincent De Paul",
    "wof:placetype":"venue"
},
  "geometry": {"coordinates":[-81.239211,28.898007],"type":"Point"}
}