{
  "type": "Feature",
  "properties": {
    "addr:full":"708 SW 16 Ave Gainesville FL 32601",
    "addr:housenumber":"708",
    "addr:postcode":"32601",
    "addr:street":"Sw 16 Ave",
    "iso:country":"US",
    "sg:address":"708 SW 16 Ave",
    "sg:city":"Gainesville",
    "sg:classifiers":[
        {
            "category":"Real Estate",
            "subcategory":"Real Estate Operator",
            "type":"Services"
        }
    ],
    "sg:phone":"+1 352 376 6720",
    "sg:postcode":"32601",
    "sg:province":"FL",
    "sg:tags":[
        "complex",
        "apt"
    ],
    "wof:name":"Sun Bay Apartments",
    "wof:placetype":"venue"
},
  "geometry": {"coordinates":[-82.333285,29.636632],"type":"Point"}
}