{
  "type": "Feature",
  "properties": {
    "addr:full":"1912 Howe Ct Fort Myers FL 33903",
    "addr:housenumber":"1912",
    "addr:postcode":"33903",
    "addr:street":"Howe Ct",
    "iso:country":"US",
    "sg:address":"1912 Howe Ct",
    "sg:city":"Fort Myers",
    "sg:classifiers":[
        {
            "category":"Travel",
            "subcategory":"Travel Agent",
            "type":"Entertainment"
        }
    ],
    "sg:phone":"+1 239 656 4574",
    "sg:postcode":"33903",
    "sg:province":"FL",
    "sg:tags":[
        "agency"
    ],
    "wof:name":"Cruise Time Travel",
    "wof:placetype":"venue"
},
  "geometry": {"coordinates":[-81.91649700000001,26.646416],"type":"Point"}
}