{
  "type": "Feature",
  "properties": {
    "iso:country":"US",
    "sg:address":"112 Sikes Dr",
    "sg:city":"Crestview",
    "sg:classifiers":[
        {
            "category":"Building & Trades",
            "subcategory":"Construction",
            "type":"Services"
        }
    ],
    "sg:phone":"+1 850 682 9553",
    "sg:postcode":"32539",
    "sg:province":"FL",
    "sg:tags":[
        "contractor"
    ],
    "wof:name":"United Ceramic & Tile",
    "wof:placetype":"venue"
},
  "geometry": {"coordinates":[-86.54769,30.761748],"type":"Point"}
}