{
  "type": "Feature",
  "properties": {
    "iso:country":"US",
    "sg:address":"2416 N Federal Hwy",
    "sg:city":"Pompano Beach",
    "sg:classifiers":[
        {
            "category":"Wholesale",
            "subcategory":"Apparel",
            "type":"Manufacturing & Wholesale Goods"
        }
    ],
    "sg:phone":"+1 954 785 2208",
    "sg:postcode":"33064",
    "sg:province":"FL",
    "sg:tags":[
        "footwear"
    ],
    "wof:name":"Rugged Shark",
    "wof:placetype":"venue"
},
  "geometry": {"coordinates":[-80.099369,26.26166],"type":"Point"}
}