{
  "type": "Feature",
  "properties": {
    "addr:full":"14511 SW 122nd Pl Miami FL 33186",
    "addr:housenumber":"14511",
    "addr:postcode":"33186",
    "addr:street":"Sw 122Nd Pl",
    "iso:country":"US",
    "sg:address":"14511 SW 122nd Pl",
    "sg:city":"Miami",
    "sg:classifiers":[
        {
            "category":"Wholesale",
            "subcategory":"Chemicals & Plastics",
            "type":"Manufacturing & Wholesale Goods"
        }
    ],
    "sg:phone":"+1 305 254 2277",
    "sg:postcode":"33186",
    "sg:province":"FL",
    "sg:tags":[
        "chemist"
    ],
    "wof:name":"Chempurch Inc",
    "wof:placetype":"venue"
},
  "geometry": {"coordinates":[-80.391296,25.633293],"type":"Point"}
}