{
  "type": "Feature",
  "properties": {
    "iso:country":"US",
    "sg:address":"2034 Herschel St",
    "sg:city":"Jacksonville",
    "sg:classifiers":[
        {
            "category":"Shopping",
            "subcategory":"Clothing, Apparel, & Fashions",
            "type":"Retail Goods"
        }
    ],
    "sg:phone":"+1 904 389 3033",
    "sg:postcode":"32204",
    "sg:province":"FL",
    "wof:name":"R Fennelles Inc",
    "wof:placetype":"venue"
},
  "geometry": {"coordinates":[-81.68230800000001,30.312639],"type":"Point"}
}