{
  "type": "Feature",
  "properties": {
    "iso:country":"US",
    "sg:address":"470 Andalusia Ave",
    "sg:city":"Ormond Beach",
    "sg:classifiers":[
        {
            "category":"Organizations",
            "subcategory":"Non-profit Organization",
            "type":"Services"
        },
        {
            "category":"Social Services",
            "type":"Services"
        }
    ],
    "sg:phone":"+1 386 672 0294",
    "sg:postcode":"32174",
    "sg:province":"FL",
    "sg:tags":[
        "fund",
        "raising",
        "welfare"
    ],
    "wof:name":"Jewish Federation of Volusia",
    "wof:placetype":"venue"
},
  "geometry": {"coordinates":[-81.058638,29.274278],"type":"Point"}
}