{
  "type": "Feature",
  "properties": {
    "addr:full":"2306 N Howard Ave Tampa FL 33607",
    "addr:housenumber":"2306",
    "addr:postcode":"33607",
    "addr:street":"N Howard Ave",
    "iso:country":"US",
    "sg:address":"2306 N Howard Ave",
    "sg:city":"Tampa",
    "sg:classifiers":[
        {
            "category":"Building & Trades",
            "subcategory":"Construction",
            "type":"Services"
        }
    ],
    "sg:phone":"+1 813 259 3785",
    "sg:postcode":"33607",
    "sg:province":"FL",
    "sg:tags":[
        "general",
        "contractor"
    ],
    "wof:name":"Construct Two Group",
    "wof:placetype":"venue"
},
  "geometry": {"coordinates":[-82.482928,27.962235],"type":"Point"}
}