{
  "type": "Feature",
  "properties": {
    "addr:full":"907 E Klosterman Rd Tarpon Springs FL 34689",
    "addr:housenumber":"907",
    "addr:postcode":"34689",
    "addr:street":"E Klosterman Rd",
    "iso:country":"US",
    "sg:address":"907 E Klosterman Rd",
    "sg:city":"Tarpon Springs",
    "sg:classifiers":[
        {
            "category":"Real Estate",
            "subcategory":"Real Estate Agent",
            "type":"Services"
        }
    ],
    "sg:phone":"+1 727 938 9060",
    "sg:postcode":"34689",
    "sg:province":"FL",
    "wof:name":"Florida Properties Diversified",
    "wof:placetype":"venue"
},
  "geometry": {"coordinates":[-82.739823,28.122975],"type":"Point"}
}