{
  "type": "Feature",
  "properties": {
    "iso:country":"US",
    "sg:address":"1323 W Point Dr",
    "sg:city":"Cocoa",
    "sg:classifiers":[
        {
            "category":"Restaurant",
            "type":"Food & Drink"
        }
    ],
    "sg:phone":"+1 321 632 4246",
    "sg:postcode":"32922",
    "sg:province":"FL",
    "sg:tags":[
        "bakery",
        "catering",
        "decorating",
        "supply"
    ],
    "wof:name":"Stevens Cake and Catering",
    "wof:placetype":"venue"
},
  "geometry": {"coordinates":[-80.748745,28.374689],"type":"Point"}
}