{
  "type": "Feature",
  "properties": {
    "iso:country":"US",
    "sg:address":"2393 SW 5th St",
    "sg:city":"Miami",
    "sg:classifiers":[
        {
            "category":"Manufacturing",
            "subcategory":"Printing",
            "type":"Manufacturing & Wholesale Goods"
        }
    ],
    "sg:phone":"+1 305 541 0511",
    "sg:postcode":"33135",
    "sg:province":"FL",
    "sg:tags":[
        "printer"
    ],
    "wof:name":"DSE Group",
    "wof:placetype":"venue"
},
  "geometry": {"coordinates":[-80.233146,25.767931],"type":"Point"}
}