{
  "type": "Feature",
  "properties": {
    "iso:country":"US",
    "sg:address":"6111 12th Ave",
    "sg:city":"New Port Richey",
    "sg:classifiers":[
        {
            "category":"Building & Trades",
            "subcategory":"Cleaning & Sanitation",
            "type":"Services"
        }
    ],
    "sg:phone":"+1 727 937 0520",
    "sg:postcode":"34653",
    "sg:province":"FL",
    "sg:tags":[
        "maintenance"
    ],
    "wof:name":"Paul Greenes Home Services",
    "wof:placetype":"venue"
},
  "geometry": {"coordinates":[-82.71199,28.225975],"type":"Point"}
}