{
  "type": "Feature",
  "properties": {
    "iso:country":"US",
    "sg:address":"2613 Stern Dr E",
    "sg:city":"Atlantic Beach",
    "sg:classifiers":[
        {
            "category":"Farming",
            "subcategory":"Fish & Marine Products",
            "type":"Manufacturing & Wholesale Goods"
        }
    ],
    "sg:phone":"+1 904 246 0203",
    "sg:postcode":"32233",
    "sg:province":"FL",
    "sg:tags":[
        "fisherman"
    ],
    "wof:name":"Trawler Elaine Marie Inc",
    "wof:placetype":"venue"
},
  "geometry": {"coordinates":[-81.414219,30.360849],"type":"Point"}
}