{
  "type": "Feature",
  "properties": {
    "iso:country":"US",
    "sg:address":"4250 66th St N",
    "sg:city":"Kenneth City",
    "sg:classifiers":[
        {
            "category":"Health Services",
            "subcategory":"Nursing And Care Facility",
            "type":"Services"
        }
    ],
    "sg:phone":"+1 727 546 2405",
    "sg:postcode":"33709",
    "sg:province":"FL",
    "sg:tags":[
        "home",
        "skilled",
        "convalescent"
    ],
    "wof:name":"Jacaranda Manor",
    "wof:placetype":"venue"
},
  "geometry": {"coordinates":[-82.728646,27.811382],"type":"Point"}
}