{
  "type": "Feature",
  "properties": {
    "iso:country":"US",
    "sg:address":"17070 Collins Ave",
    "sg:city":"Miami",
    "sg:classifiers":[
        {
            "category":"Real Estate",
            "subcategory":"Real Estate Agent",
            "type":"Services"
        }
    ],
    "sg:phone":"+1 305 947 5870",
    "sg:postcode":"33160",
    "sg:province":"FL",
    "wof:name":"Finza Inc",
    "wof:placetype":"venue"
},
  "geometry": {"coordinates":[-80.121807,25.934276],"type":"Point"}
}