{
  "type": "Feature",
  "properties": {
    "addr:full":"2058 34th Way N Largo FL 33771",
    "addr:housenumber":"2058",
    "addr:postcode":"33771",
    "addr:street":"34Th Way N",
    "iso:country":"US",
    "sg:address":"2058 34th Way N",
    "sg:city":"Largo",
    "sg:classifiers":[
        {
            "category":"Manufacturing",
            "subcategory":"Metals",
            "type":"Manufacturing & Wholesale Goods"
        }
    ],
    "sg:phone":"+1 727 532 4044",
    "sg:postcode":"33771",
    "sg:province":"FL",
    "sg:tags":[
        "extruded",
        "product",
        "aluminum",
        "mfg"
    ],
    "wof:name":"Innovative Marine Inc",
    "wof:placetype":"venue"
},
  "geometry": {"coordinates":[-82.752768,27.896938],"type":"Point"}
}