{
  "type": "Feature",
  "properties": {
    "iso:country":"US",
    "sg:address":"2150 Loch Rane Blvd",
    "sg:city":"Orange Park",
    "sg:classifiers":[
        {
            "category":"Professional",
            "subcategory":"Computer Services",
            "type":"Services"
        }
    ],
    "sg:phone":"+1 904 276 3900",
    "sg:postcode":"32073",
    "sg:province":"FL",
    "sg:tags":[
        "repair"
    ],
    "wof:name":"Computers By What Now",
    "wof:placetype":"venue"
},
  "geometry": {"coordinates":[-81.750094,30.164485],"type":"Point"}
}