{
  "type": "Feature",
  "properties": {
    "addr:full":"8209 Forest Cir N Seminole FL 33776",
    "addr:housenumber":"8209",
    "addr:postcode":"33776",
    "addr:street":"Forest Cir N",
    "iso:country":"US",
    "sg:address":"8209 Forest Cir N",
    "sg:city":"Seminole",
    "sg:classifiers":[
        {
            "category":"Wholesale",
            "subcategory":"Non-durable Goods",
            "type":"Manufacturing & Wholesale Goods"
        }
    ],
    "sg:phone":"+1 727 392 1822",
    "sg:postcode":"33776",
    "sg:province":"FL",
    "wof:name":"Mushroom Tree The",
    "wof:placetype":"venue"
},
  "geometry": {"coordinates":[-82.823538,27.84767],"type":"Point"}
}