{
  "type": "Feature",
  "properties": {
    "iso:country":"US",
    "sg:address":"888 E Las Olas Blvd",
    "sg:city":"Fort Lauderdale",
    "sg:classifiers":[
        {
            "category":"Professional",
            "subcategory":"Lawyer & Legal Services",
            "type":"Services"
        }
    ],
    "sg:phone":"+1 954 761 8600",
    "sg:postcode":"33301",
    "sg:province":"FL",
    "wof:name":"Katherine O Birnbaum",
    "wof:placetype":"venue"
},
  "geometry": {"coordinates":[-80.13524700000001,26.119161],"type":"Point"}
}