{
  "type": "Feature",
  "properties": {
    "iso:country":"US",
    "sg:address":"309 Glenmont Dr E",
    "sg:city":"Fort Myers",
    "sg:classifiers":[
        {
            "category":"Building & Trades",
            "subcategory":"Construction",
            "type":"Services"
        }
    ],
    "sg:phone":"+1 239 995 7027",
    "sg:postcode":"33917",
    "sg:province":"FL",
    "sg:tags":[
        "painter"
    ],
    "wof:name":"Mark Edwards Painting Co",
    "wof:placetype":"venue"
},
  "geometry": {"coordinates":[-81.87217,26.674342],"type":"Point"}
}