{
  "type": "Feature",
  "properties": {
    "iso:country":"US",
    "sg:address":"175 Semoran Commerce Pl",
    "sg:city":"Apopka",
    "sg:classifiers":[
        {
            "category":"Wholesale",
            "subcategory":"Electrical",
            "type":"Manufacturing & Wholesale Goods"
        }
    ],
    "sg:phone":"+1 407 740 0366",
    "sg:postcode":"32703",
    "sg:province":"FL",
    "sg:tags":[
        "distributor",
        "fire",
        "alarm",
        "system"
    ],
    "wof:name":"Rigdon Communications Inc",
    "wof:placetype":"venue"
},
  "geometry": {"coordinates":[-81.479131,28.67428],"type":"Point"}
}