{
  "type": "Feature",
  "properties": {
    "addr:full":"1924 NW 2nd Ave Wilton Manors FL 33311",
    "addr:housenumber":"1924",
    "addr:postcode":"33311",
    "addr:street":"Nw 2Nd Ave",
    "iso:country":"US",
    "sg:address":"1924 NW 2nd Ave",
    "sg:city":"Wilton Manors",
    "sg:classifiers":[
        {
            "category":"Banks & Credit Unions",
            "subcategory":"Bank",
            "type":"Services"
        }
    ],
    "sg:phone":"+1 954 565 6260",
    "sg:postcode":"33311",
    "sg:province":"FL",
    "sg:tags":[
        "loan",
        "real estate"
    ],
    "wof:name":"Countrywide Home Loans",
    "wof:placetype":"venue"
},
  "geometry": {"coordinates":[-80.147374,26.153017],"type":"Point"}
}