{
  "type": "Feature",
  "properties": {
    "iso:country":"US",
    "sg:address":"1102 N Dixie Fwy",
    "sg:city":"New Smyrna Beach",
    "sg:classifiers":[
        {
            "category":"Wholesale",
            "subcategory":"Machinery & Supplies",
            "type":"Manufacturing & Wholesale Goods"
        }
    ],
    "sg:phone":"+1 386 428 2508",
    "sg:postcode":"32168",
    "sg:province":"FL",
    "sg:tags":[
        "equipment",
        "sewer",
        "cleaning"
    ],
    "sg:website":"www.pipestopper.com",
    "wof:name":"Sewer Equipment Co Of Fl",
    "wof:placetype":"venue"
},
  "geometry": {"coordinates":[-80.933922,29.041667],"type":"Point"}
}