{
  "type": "Feature",
  "properties": {
    "addr:full":"9301 Co Rd 645 Bushnell FL 33513",
    "addr:housenumber":"9301;645",
    "addr:postcode":"33513",
    "addr:street":"Co Rd",
    "iso:country":"US",
    "sg:address":"9301 Co Rd 645",
    "sg:city":"Bushnell",
    "sg:classifiers":[
        {
            "category":"Shopping",
            "subcategory":"Used Merchandise",
            "type":"Retail Goods"
        }
    ],
    "sg:phone":"+1 352 793 5844",
    "sg:postcode":"33513",
    "sg:province":"FL",
    "wof:name":"Byfield Enterprises Inc",
    "wof:placetype":"venue"
},
  "geometry": {"coordinates":[-82.253591,28.636886],"type":"Point"}
}