{
  "type": "Feature",
  "properties": {
    "iso:country":"US",
    "sg:address":"2308 Sawgrass Village Dr",
    "sg:city":"Ponte Vedra Bch",
    "sg:classifiers":[
        {
            "category":"Banks & Credit Unions",
            "subcategory":"Bank",
            "type":"Services"
        }
    ],
    "sg:phone":"+1 904 280 9600",
    "sg:postcode":"32082",
    "sg:province":"FL",
    "sg:tags":[
        "mortgage",
        "loan",
        "broker",
        "real estate"
    ],
    "sg:website":"www.dolphin-mortgage.com",
    "wof:name":"Dolphin Home Mortgage Inc",
    "wof:placetype":"venue"
},
  "geometry": {"coordinates":[-81.38223499999999,30.20651],"type":"Point"}
}