{
  "type": "Feature",
  "properties": {
    "iso:country":"US",
    "sg:address":"10771 64th Ave",
    "sg:city":"Seminole",
    "sg:classifiers":[
        {
            "category":"Building & Trades",
            "subcategory":"Landscaping Services",
            "type":"Services"
        }
    ],
    "sg:phone":"+1 727 398 5399",
    "sg:postcode":"33772",
    "sg:province":"FL",
    "sg:tags":[
        "tree"
    ],
    "wof:name":"Suncoast Tree Svc Inc",
    "wof:placetype":"venue"
},
  "geometry": {"coordinates":[-82.787165,27.830392],"type":"Point"}
}