{
  "type": "Feature",
  "properties": {
    "addr:full":"2116 Cedar St Fernandina Beach FL 32034",
    "addr:housenumber":"2116",
    "addr:postcode":"32034",
    "addr:street":"Cedar St",
    "iso:country":"US",
    "sg:address":"2116 Cedar St",
    "sg:city":"Fernandina Beach",
    "sg:classifiers":[
        {
            "category":"Building & Trades",
            "subcategory":"Construction",
            "type":"Services"
        }
    ],
    "sg:phone":"+1 904 261 2853",
    "sg:postcode":"32034",
    "sg:province":"FL",
    "sg:tags":[
        "residential"
    ],
    "wof:name":"John B Williams LLC",
    "wof:placetype":"venue"
},
  "geometry": {"coordinates":[-81.443455,30.665002],"type":"Point"}
}