{
  "type": "Feature",
  "properties": {
    "iso:country":"US",
    "sg:address":"2101 N Dixie Hwy",
    "sg:city":"Wilton Manors",
    "sg:classifiers":[
        {
            "category":"Manufacturing",
            "subcategory":"Wood Products",
            "type":"Manufacturing & Wholesale Goods"
        }
    ],
    "sg:phone":"+1 954 537 5306",
    "sg:postcode":"33305",
    "sg:province":"FL",
    "sg:tags":[
        "picture",
        "frame"
    ],
    "wof:name":"Design Images",
    "wof:placetype":"venue"
},
  "geometry": {"coordinates":[-80.132836,26.155559],"type":"Point"}
}