{
  "type": "Feature",
  "properties": {
    "iso:country":"US",
    "sg:address":"1325 W Cervantes St",
    "sg:city":"Pensacola",
    "sg:classifiers":[
        {
            "category":"Shopping",
            "subcategory":"Florist",
            "type":"Retail Goods"
        }
    ],
    "sg:phone":"+1 850 433 3217",
    "sg:postcode":"32501",
    "sg:province":"FL",
    "wof:name":"Addie's House Of Flowers",
    "wof:placetype":"venue"
},
  "geometry": {"coordinates":[-87.23249300000001,30.42022],"type":"Point"}
}