{
  "type": "Feature",
  "properties": {
    "iso:country":"US",
    "sg:address":"853 NE Jensen Beach Blvd",
    "sg:city":"Jensen Beach",
    "sg:classifiers":[
        {
            "category":"Manufacturing",
            "subcategory":"Printing",
            "type":"Manufacturing & Wholesale Goods"
        }
    ],
    "sg:phone":"+1 772 334 6443",
    "sg:postcode":"34957",
    "sg:province":"FL",
    "sg:tags":[
        "printer",
        "commercial"
    ],
    "wof:name":"Black & White Discount Print",
    "wof:placetype":"venue"
},
  "geometry": {"coordinates":[-80.24057000000001,27.24518],"type":"Point"}
}