{
  "type": "Feature",
  "properties": {
    "addr:full":"2818 Parkway St Lakeland FL 33811",
    "addr:housenumber":"2818",
    "addr:postcode":"33811",
    "addr:street":"Parkway St",
    "iso:country":"US",
    "sg:address":"2818 Parkway St",
    "sg:city":"Lakeland",
    "sg:classifiers":[
        {
            "category":"Building & Trades",
            "subcategory":"Equipment Rental",
            "type":"Services"
        }
    ],
    "sg:phone":"+1 863 647 3688",
    "sg:postcode":"33811",
    "sg:province":"FL",
    "sg:tags":[
        "merchandise",
        "mfg"
    ],
    "wof:name":"Sentry Barricades Inc",
    "wof:placetype":"venue"
},
  "geometry": {"coordinates":[-82.005296,27.993056],"type":"Point"}
}