{
  "type": "Feature",
  "properties": {
    "iso:country":"US",
    "sg:address":"19811 NE 21st Ct",
    "sg:city":"Miami",
    "sg:classifiers":[
        {
            "category":"Home & Garden",
            "subcategory":"Building Materials",
            "type":"Retail Goods"
        }
    ],
    "sg:phone":"+1 305 937 2817",
    "sg:postcode":"33179",
    "sg:province":"FL",
    "sg:tags":[
        "granite"
    ],
    "wof:name":"New Star Granite",
    "wof:placetype":"venue"
},
  "geometry": {"coordinates":[-80.158215,25.958471],"type":"Point"}
}