{
  "type": "Feature",
  "properties": {
    "addr:full":"1610 S Pine Ave Ocala FL 34471",
    "addr:housenumber":"1610",
    "addr:postcode":"34471",
    "addr:street":"S Pine Ave",
    "iso:country":"US",
    "sg:address":"1610 S Pine Ave",
    "sg:city":"Ocala",
    "sg:classifiers":[
        {
            "category":"Banks & Credit Unions",
            "subcategory":"Financial Services",
            "type":"Services"
        }
    ],
    "sg:phone":"+1 352 629 0233",
    "sg:postcode":"34471",
    "sg:province":"FL",
    "sg:tags":[
        "cashing",
        "loan",
        "payday",
        "alternative",
        "check"
    ],
    "sg:website":"http://www.acecashexpress.com",
    "wof:name":"ACE Cash Express",
    "wof:placetype":"venue"
},
  "geometry": {"coordinates":[-82.140468,29.172879],"type":"Point"}
}