{
  "type": "Feature",
  "properties": {
    "iso:country":"US",
    "sg:address":"167 2nd Ave NE",
    "sg:city":"St Petersburg",
    "sg:classifiers":[
        {
            "category":"Restaurant",
            "type":"Food & Drink"
        }
    ],
    "sg:phone":"+1 727 823 8226",
    "sg:postcode":"33701",
    "sg:province":"FL",
    "wof:name":"Abodo Grill Restaurant",
    "wof:placetype":"venue"
},
  "geometry": {"coordinates":[-82.633503,27.773465],"type":"Point"}
}