{
  "type": "Feature",
  "properties": {
    "iso:country":"US",
    "sg:address":"680 E 4th Ave",
    "sg:city":"Hialeah",
    "sg:classifiers":[
        {
            "category":"Shopping",
            "subcategory":"Crafts & Fabrics",
            "type":"Retail Goods"
        },
        {
            "category":"Food & Beverages",
            "subcategory":"Groceries & Convenience Stores",
            "type":"Retail Goods"
        }
    ],
    "sg:phone":"+1 305 882 1735",
    "sg:postcode":"33010",
    "sg:province":"FL",
    "sg:tags":[
        "shop",
        "notion"
    ],
    "wof:name":"Notions by Camacho",
    "wof:placetype":"venue"
},
  "geometry": {"coordinates":[-80.273399,25.8284],"type":"Point"}
}