{
  "type": "Feature",
  "properties": {
    "iso:country":"US",
    "sg:address":"3657 NW 124th Ave",
    "sg:city":"Pompano Beach",
    "sg:classifiers":[
        {
            "category":"Wholesale",
            "subcategory":"Groceries",
            "type":"Manufacturing & Wholesale Goods"
        }
    ],
    "sg:phone":"+1 954 344 5102",
    "sg:postcode":"33065",
    "sg:province":"FL",
    "sg:tags":[
        "gourmet",
        "food",
        "distribution"
    ],
    "wof:name":"Mrs DS Gourmet",
    "wof:placetype":"venue"
},
  "geometry": {"coordinates":[-80.29111899999999,26.277081],"type":"Point"}
}