{
  "type": "Feature",
  "properties": {
    "iso:country":"US",
    "sg:address":"919 W State Road 436",
    "sg:city":"Altamonte Springs",
    "sg:classifiers":[
        {
            "category":"Insurance",
            "subcategory":"Hazard Insurance",
            "type":"Services"
        }
    ],
    "sg:phone":"+1 407 774 7710",
    "sg:postcode":"32714",
    "sg:province":"FL",
    "wof:name":"Brymar Corp",
    "wof:placetype":"venue"
},
  "geometry": {"coordinates":[-81.419899,28.665501],"type":"Point"}
}