{
  "type": "Feature",
  "properties": {
    "iso:country":"US",
    "sg:address":"733 Martinique Cir",
    "sg:city":"Lakeland",
    "sg:classifiers":[
        {
            "category":"Banks & Credit Unions",
            "subcategory":"Financial Services",
            "type":"Services"
        }
    ],
    "sg:phone":"+1 863 644 1498",
    "sg:postcode":"33803",
    "sg:province":"FL",
    "sg:tags":[
        "trust",
        "investment",
        "real estate"
    ],
    "wof:name":"Volo Investments Inc",
    "wof:placetype":"venue"
},
  "geometry": {"coordinates":[-81.965681,27.997241],"type":"Point"}
}