{
  "type": "Feature",
  "properties": {
    "iso:country":"US",
    "sg:address":"14585 Biscayne Blvd",
    "sg:city":"North Miami",
    "sg:classifiers":[
        {
            "category":"Autos & Motor Vehicles",
            "subcategory":"Fuel & Gas Station",
            "type":"Retail Goods"
        }
    ],
    "sg:phone":"+1 305 944 4511",
    "sg:postcode":"33181",
    "sg:province":"FL",
    "sg:tags":[
        "gasoline"
    ],
    "wof:name":"1800-Gas Station",
    "wof:placetype":"venue"
},
  "geometry": {"coordinates":[-80.15770000000001,25.9093],"type":"Point"}
}