{
  "type": "Feature",
  "properties": {
    "iso:country":"US",
    "sg:address":"10445 114th Ter N",
    "sg:city":"Largo",
    "sg:classifiers":[
        {
            "category":"Restaurant",
            "type":"Food & Drink"
        }
    ],
    "sg:phone":"+1 727 393 3513",
    "sg:postcode":"33773",
    "sg:province":"FL",
    "wof:name":"Mad Beach Trading Co",
    "wof:placetype":"venue"
},
  "geometry": {"coordinates":[-82.785729,27.876828],"type":"Point"}
}