{
  "type": "Feature",
  "properties": {
    "addr:full":"2746 Tamiami Trl Port Charlotte FL 33952",
    "addr:housenumber":"2746",
    "addr:postcode":"33952",
    "addr:street":"Tamiami Trl",
    "iso:country":"US",
    "sg:address":"2746 Tamiami Trl",
    "sg:city":"Port Charlotte",
    "sg:classifiers":[
        {
            "category":"Restaurant",
            "type":"Food & Drink"
        }
    ],
    "sg:menulink":"http://www.allmenus.com/fl/port-charlotte/88491-whiskey-creek/menu/",
    "sg:phone":"+1 941 766 0045",
    "sg:postcode":"33952",
    "sg:province":"FL",
    "sg:tags":[
        "american"
    ],
    "wof:name":"Whiskey Creek",
    "wof:placetype":"venue"
},
  "geometry": {"coordinates":[-82.11091399999999,26.990112],"type":"Point"}
}