{
  "type": "Feature",
  "properties": {
    "iso:country":"US",
    "sg:address":"23165 Harper Ave",
    "sg:city":"Port Charlotte",
    "sg:classifiers":[
        {
            "category":"Autos & Motor Vehicles",
            "subcategory":"Auto Supplies",
            "type":"Retail Goods"
        }
    ],
    "sg:phone":"+1 941 625 0907",
    "sg:postcode":"33980",
    "sg:province":"FL",
    "wof:name":"Lees Woodie Tire Store",
    "wof:placetype":"venue"
},
  "geometry": {"coordinates":[-82.06623999999999,26.961456],"type":"Point"}
}