{
  "type": "Feature",
  "properties": {
    "addr:full":"3600 N Flagler Dr West Palm Beach FL 33407",
    "addr:housenumber":"3600",
    "addr:postcode":"33407",
    "addr:street":"N Flagler Dr",
    "iso:country":"US",
    "sg:address":"3600 N Flagler Dr",
    "sg:city":"West Palm Beach",
    "sg:classifiers":[
        {
            "category":"Real Estate",
            "subcategory":"Real Estate Operator",
            "type":"Services"
        }
    ],
    "sg:phone":"+1 561 842 6050",
    "sg:postcode":"33407",
    "sg:province":"FL",
    "sg:tags":[
        "building",
        "nonresidential"
    ],
    "wof:name":"Raymond Office Plaza LLC",
    "wof:placetype":"venue"
},
  "geometry": {"coordinates":[-80.04987800000001,26.744564],"type":"Point"}
}