{
  "type": "Feature",
  "properties": {
    "iso:country":"US",
    "sg:address":"32800 Us Highway 19 N",
    "sg:city":"Palm Harbor",
    "sg:classifiers":[
        {
            "category":"Restaurant",
            "type":"Food & Drink"
        }
    ],
    "sg:menulink":"http://www.allmenus.com/fl/tarpon-springs/179750-chick-fil-a/menu/",
    "sg:phone":"+1 727 786 8545",
    "sg:postcode":"34684",
    "sg:province":"FL",
    "sg:tags":[
        "wrap",
        "soup",
        "american",
        "sandwich",
        "salad"
    ],
    "wof:name":"Chick-fil-A",
    "wof:placetype":"venue"
},
  "geometry": {"coordinates":[-82.739492,28.070438],"type":"Point"}
}