{
  "type": "Feature",
  "properties": {
    "iso:country":"US",
    "sg:address":"2240 Tamiami Trl N",
    "sg:city":"Naples",
    "sg:classifiers":[
        {
            "category":"Shopping",
            "type":"Retail Goods"
        }
    ],
    "sg:phone":"+1 239 649 6484",
    "sg:postcode":"34103",
    "sg:province":"FL",
    "sg:tags":[
        "material",
        "supply"
    ],
    "wof:name":"Koenig Art Emporium",
    "wof:placetype":"venue"
},
  "geometry": {"coordinates":[-81.79964200000001,26.175483],"type":"Point"}
}