{
  "type": "Feature",
  "properties": {
    "addr:full":"25412 Palisade Rd Punta Gorda FL 33983",
    "addr:housenumber":"25412",
    "addr:postcode":"33983",
    "addr:street":"Palisade Rd",
    "iso:country":"US",
    "sg:address":"25412 Palisade Rd",
    "sg:city":"Punta Gorda",
    "sg:classifiers":[
        {
            "category":"Building & Trades",
            "subcategory":"Construction",
            "type":"Services"
        }
    ],
    "sg:phone":"+1 941 764 1569",
    "sg:postcode":"33983",
    "sg:province":"FL",
    "sg:tags":[
        "drywall",
        "contractor"
    ],
    "wof:name":"Don Spittler Drywall Inc",
    "wof:placetype":"venue"
},
  "geometry": {"coordinates":[-82.026516,27.015695],"type":"Point"}
}