{
  "type": "Feature",
  "properties": {
    "iso:country":"US",
    "sg:address":"2422 SW 99th Ct",
    "sg:city":"Miami",
    "sg:phone":"+1 305 223 5855",
    "sg:postcode":"33165",
    "sg:province":"FL",
    "sg:tags":[
        "equipment",
        "commercial"
    ],
    "wof:name":"L F Taylor Inc",
    "wof:placetype":"venue"
},
  "geometry": {"coordinates":[-80.35627599999999,25.745498],"type":"Point"}
}