{
  "type": "Feature",
  "properties": {
    "iso:country":"US",
    "sg:address":"6125 Rattlesnake Hammock Rd",
    "sg:city":"Naples",
    "sg:classifiers":[
        {
            "category":"Health Services",
            "subcategory":"Nursing And Care Facility",
            "type":"Services"
        },
        {
            "category":"Social Services",
            "subcategory":"Adult Care",
            "type":"Services"
        }
    ],
    "sg:phone":"+1 239 417 8511",
    "sg:postcode":"34113",
    "sg:province":"FL",
    "sg:tags":[
        "home",
        "intermediate",
        "residential"
    ],
    "wof:name":"Arden Courts",
    "wof:placetype":"venue"
},
  "geometry": {"coordinates":[-81.713078,26.109094],"type":"Point"}
}