{
  "type": "Feature",
  "properties": {
    "iso:country":"US",
    "sg:address":"9365 Middlebury Glen Ct",
    "sg:city":"Jacksonville",
    "sg:classifiers":[
        {
            "category":"Home & Garden",
            "subcategory":"Home Furnishings",
            "type":"Retail Goods"
        }
    ],
    "sg:phone":"+1 904 363 0001",
    "sg:postcode":"32256",
    "sg:province":"FL",
    "wof:name":"Store 51",
    "wof:placetype":"venue"
},
  "geometry": {"coordinates":[-81.52350199999999,30.194211],"type":"Point"}
}