{
  "type": "Feature",
  "properties": {
    "iso:country":"US",
    "sg:address":"104 Orange Ridge Dr",
    "sg:city":"Longwood",
    "sg:classifiers":[
        {
            "category":"Autos & Motor Vehicles",
            "subcategory":"Automobile Sales",
            "type":"Retail Goods"
        }
    ],
    "sg:phone":"+1 407 333 4300",
    "sg:postcode":"32779",
    "sg:province":"FL",
    "sg:tags":[
        "aircraft"
    ],
    "wof:name":"Worldwide Aviation Inc",
    "wof:placetype":"venue"
},
  "geometry": {"coordinates":[-81.376296,28.742118],"type":"Point"}
}