{
  "type": "Feature",
  "properties": {
    "addr:full":"1501 Merchants Way Niceville FL 32578",
    "addr:housenumber":"1501",
    "addr:postcode":"32578",
    "addr:street":"Merchants Way",
    "iso:country":"US",
    "sg:address":"1501 Merchants Way",
    "sg:city":"Niceville",
    "sg:classifiers":[
        {
            "category":"Professional",
            "subcategory":"Engineering",
            "type":"Services"
        },
        {
            "category":"Professional",
            "subcategory":"Testing Lab",
            "type":"Services"
        }
    ],
    "sg:phone":"+1 850 897 5380",
    "sg:postcode":"32578",
    "sg:province":"FL",
    "sg:tags":[
        "laboratory",
        "consulting",
        "engineer"
    ],
    "sg:website":"http://www.titan.com",
    "wof:name":"L-3 Services, Inc.",
    "wof:placetype":"venue"
},
  "geometry": {"coordinates":[-86.42231,30.48789],"type":"Point"}
}