{
  "type": "Feature",
  "properties": {
    "iso:country":"US",
    "sg:address":"901 Havendale Blvd NW",
    "sg:city":"Winter Haven",
    "sg:classifiers":[
        {
            "category":"Shopping",
            "subcategory":"Shoes",
            "type":"Retail Goods"
        }
    ],
    "sg:phone":"+1 863 293 5974",
    "sg:postcode":"33881",
    "sg:province":"FL",
    "wof:name":"Payless Shoe Source",
    "wof:placetype":"venue"
},
  "geometry": {"coordinates":[-81.736113,28.044],"type":"Point"}
}