{
  "type": "Feature",
  "properties": {
    "iso:country":"US",
    "sg:address":"6950 Venture Cir",
    "sg:city":"Orlando",
    "sg:classifiers":[
        {
            "category":"Wholesale",
            "subcategory":"Non-durable Goods",
            "type":"Manufacturing & Wholesale Goods"
        }
    ],
    "sg:phone":"+1 407 678 6479",
    "sg:postcode":"32807",
    "sg:province":"FL",
    "sg:tags":[
        "clothes"
    ],
    "wof:name":"Continental Gifts & Imports",
    "wof:placetype":"venue"
},
  "geometry": {"coordinates":[-81.295624,28.57796],"type":"Point"}
}