{
  "type": "Feature",
  "properties": {
    "iso:country":"US",
    "sg:address":"514 49th St S",
    "sg:city":"St Petersburg",
    "sg:classifiers":[
        {
            "category":"Personal",
            "subcategory":"Beauty Salon",
            "type":"Services"
        }
    ],
    "sg:phone":"+1 727 321 7203",
    "sg:postcode":"33707",
    "sg:province":"FL",
    "wof:name":"Intrigue Hair Salon",
    "wof:placetype":"venue"
},
  "geometry": {"coordinates":[-82.69973400000001,27.765811],"type":"Point"}
}