{
  "type": "Feature",
  "properties": {
    "addr:full":"110 E Broadway St Oviedo FL 32765",
    "addr:housenumber":"110",
    "addr:postcode":"32765",
    "addr:street":"E Broadway St",
    "iso:country":"US",
    "sg:address":"110 E Broadway St",
    "sg:city":"Oviedo",
    "sg:classifiers":[
        {
            "category":"Wholesale",
            "subcategory":"Farm Supplies",
            "type":"Manufacturing & Wholesale Goods"
        }
    ],
    "sg:phone":"+1 407 365 6631",
    "sg:postcode":"32765",
    "sg:province":"FL",
    "sg:tags":[
        "fertilizer"
    ],
    "wof:name":"Wheeler Fertilizer Co",
    "wof:placetype":"venue"
},
  "geometry": {"coordinates":[-81.206565,28.670236],"type":"Point"}
}