{
  "type": "Feature",
  "properties": {
    "iso:country":"US",
    "sg:address":"570 W 18th St",
    "sg:city":"Hialeah",
    "sg:classifiers":[
        {
            "category":"Professional",
            "subcategory":"Business Services",
            "type":"Services"
        }
    ],
    "sg:phone":"+1 305 883 5020",
    "sg:postcode":"33010",
    "sg:province":"FL",
    "sg:tags":[
        "repossessing"
    ],
    "wof:name":"Eagle Auto Recovery",
    "wof:placetype":"venue"
},
  "geometry": {"coordinates":[-80.293837,25.837938],"type":"Point"}
}