{
  "type": "Feature",
  "properties": {
    "addr:full":"7717 Ulmerton Rd Largo FL 33771",
    "addr:housenumber":"7717",
    "addr:postcode":"33771",
    "addr:street":"Ulmerton Rd",
    "iso:country":"US",
    "sg:address":"7717 Ulmerton Rd",
    "sg:city":"Largo",
    "sg:classifiers":[
        {
            "category":"Bars & Pubs",
            "type":"Food & Drink"
        }
    ],
    "sg:phone":"+1 727 392 4636",
    "sg:postcode":"33771",
    "sg:province":"FL",
    "sg:tags":[
        "brew"
    ],
    "wof:name":"Big Papas Pub",
    "wof:placetype":"venue"
},
  "geometry": {"coordinates":[-82.744623,27.894329],"type":"Point"}
}