{
  "type": "Feature",
  "properties": {
    "iso:country":"US",
    "sg:address":"1057 NE 14th Ave",
    "sg:city":"Okeechobee",
    "sg:classifiers":[
        {
            "category":"Organizations",
            "subcategory":"Religious Organization",
            "type":"Services"
        }
    ],
    "sg:phone":"+1 863 467 9355",
    "sg:postcode":"34972",
    "sg:province":"FL",
    "sg:tags":[
        "church"
    ],
    "wof:name":"Mt Olive Missionary Baptist",
    "wof:placetype":"venue"
},
  "geometry": {"coordinates":[-80.81496799999999,27.252441],"type":"Point"}
}