{
  "type": "Feature",
  "properties": {
    "iso:country":"US",
    "sg:address":"1515 S Atlantic Ave",
    "sg:city":"Daytona Beach",
    "sg:classifiers":[
        {
            "category":"Travel",
            "subcategory":"Hotels & Motels",
            "type":"Entertainment"
        }
    ],
    "sg:phone":"+1 386 254 8600",
    "sg:postcode":"32118",
    "sg:province":"FL",
    "sg:tags":[
        "operation"
    ],
    "sg:website":"www.nautilus.com",
    "wof:name":"Nautilus Inn",
    "wof:placetype":"venue"
},
  "geometry": {"coordinates":[-80.99898899999999,29.2083],"type":"Point"}
}