{
  "type": "Feature",
  "properties": {
    "iso:country":"US",
    "sg:address":"2492 NW 66th Dr",
    "sg:city":"Boca Raton",
    "sg:classifiers":[
        {
            "category":"Real Estate",
            "subcategory":"Real Estate Operator",
            "type":"Services"
        }
    ],
    "sg:phone":"+1 561 988 2084",
    "sg:postcode":"33496",
    "sg:province":"FL",
    "sg:tags":[
        "building",
        "parks"
    ],
    "wof:name":"American Steel Building Group",
    "wof:placetype":"venue"
},
  "geometry": {"coordinates":[-80.136388,26.407559],"type":"Point"}
}