{
  "type": "Feature",
  "properties": {
    "iso:country":"US",
    "sg:address":"1713 S Dale Mabry Hwy",
    "sg:city":"Tampa",
    "sg:classifiers":[
        {
            "category":"Restaurant",
            "type":"Food & Drink"
        }
    ],
    "sg:menulink":"http://www.allmenus.com/fl/tampa/43107-hao-wah/menu/",
    "sg:phone":"+1 813 253 2095",
    "sg:postcode":"33629",
    "sg:province":"FL",
    "sg:tags":[
        "asian",
        "chinese"
    ],
    "wof:name":"Hao Wah",
    "wof:placetype":"venue"
},
  "geometry": {"coordinates":[-82.505855,27.928343],"type":"Point"}
}