{
  "type": "Feature",
  "properties": {
    "iso:country":"US",
    "sg:address":"8195 N Military Trl",
    "sg:city":"Palm Beach Gardens",
    "sg:classifiers":[
        {
            "category":"Government",
            "subcategory":"Office",
            "type":"Public Place"
        }
    ],
    "sg:phone":"+1 561 630 6870",
    "sg:postcode":"33410",
    "sg:province":"FL",
    "sg:tags":[
        "national",
        "security"
    ],
    "wof:name":"US Training Center",
    "wof:placetype":"venue"
},
  "geometry": {"coordinates":[-80.10681599999999,26.79624],"type":"Point"}
}