{
  "type": "Feature",
  "properties": {
    "iso:country":"US",
    "sg:address":"3800 Dugan Dr",
    "sg:city":"Tallahassee",
    "sg:classifiers":[
        {
            "category":"Building & Trades",
            "subcategory":"Landscaping Services",
            "type":"Services"
        }
    ],
    "sg:phone":"+1 850 671 2470",
    "sg:postcode":"32311",
    "sg:province":"FL",
    "sg:tags":[
        "tree"
    ],
    "wof:name":"L & D Tree Service",
    "wof:placetype":"venue"
},
  "geometry": {"coordinates":[-84.149143,30.409953],"type":"Point"}
}