{
  "type": "Feature",
  "properties": {
    "addr:full":"800 Co Rd 540A Lakeland FL 33813",
    "addr:housenumber":"800;540a",
    "addr:postcode":"33813",
    "addr:street":"Co Rd",
    "iso:country":"US",
    "sg:address":"800 Co Rd 540A",
    "sg:city":"Lakeland",
    "sg:classifiers":[
        {
            "category":"Real Estate",
            "subcategory":"Real Estate Operator",
            "type":"Services"
        }
    ],
    "sg:phone":"+1 863 646 3632",
    "sg:postcode":"33813",
    "sg:province":"FL",
    "sg:tags":[
        "mobile",
        "home",
        "community"
    ],
    "wof:name":"Twin Lakes Mobile Home Park",
    "wof:placetype":"venue"
},
  "geometry": {"coordinates":[-81.950838,27.953103],"type":"Point"}
}