{
  "type": "Feature",
  "properties": {
    "addr:full":"9990 SW 35th Ter Miami FL 33165",
    "addr:housenumber":"9990",
    "addr:postcode":"33165",
    "addr:street":"Sw 35Th Ter",
    "iso:country":"US",
    "sg:address":"9990 SW 35th Ter",
    "sg:city":"Miami",
    "sg:classifiers":[
        {
            "category":"Shopping",
            "subcategory":"Jewelry",
            "type":"Retail Goods"
        }
    ],
    "sg:phone":"+1 305 223 8644",
    "sg:postcode":"33165",
    "sg:province":"FL",
    "wof:name":"J Family Enterprises Inc",
    "wof:placetype":"venue"
},
  "geometry": {"coordinates":[-80.356972,25.736492],"type":"Point"}
}