{
  "type": "Feature",
  "properties": {
    "addr:full":"1477 W 81st St Hialeah FL 33014",
    "addr:housenumber":"1477",
    "addr:postcode":"33014",
    "addr:street":"W 81St St",
    "iso:country":"US",
    "sg:address":"1477 W 81st St",
    "sg:city":"Hialeah",
    "sg:classifiers":[
        {
            "category":"Building & Trades",
            "subcategory":"Landscaping Services",
            "type":"Services"
        }
    ],
    "sg:phone":"+1 305 823 0247",
    "sg:postcode":"33014",
    "sg:province":"FL",
    "wof:name":"Durans Landscaping Inc",
    "wof:placetype":"venue"
},
  "geometry": {"coordinates":[-80.31332,25.896096],"type":"Point"}
}