{
  "type": "Feature",
  "properties": {
    "addr:full":"306 Reid Ave Port St Joe FL 32456",
    "addr:housenumber":"306",
    "addr:postcode":"32456",
    "addr:street":"Reid Ave",
    "iso:country":"US",
    "sg:address":"306 Reid Ave",
    "sg:city":"Port St Joe",
    "sg:classifiers":[
        {
            "category":"Shopping",
            "subcategory":"Discount & Variety Stores",
            "type":"Retail Goods"
        }
    ],
    "sg:phone":"+1 850 229 9277",
    "sg:postcode":"32456",
    "sg:province":"FL",
    "wof:name":"Kady & Zoey",
    "wof:placetype":"venue"
},
  "geometry": {"coordinates":[-85.30337400000001,29.813901],"type":"Point"}
}