{
  "type": "Feature",
  "properties": {
    "iso:country":"US",
    "sg:address":"1701 NW 120th Ter",
    "sg:city":"Hollywood",
    "sg:classifiers":[
        {
            "category":"Manufacturing",
            "subcategory":"Printing",
            "type":"Manufacturing & Wholesale Goods"
        }
    ],
    "sg:phone":"+1 954 435 2634",
    "sg:postcode":"33026",
    "sg:province":"FL",
    "sg:tags":[
        "lithographic",
        "commercial"
    ],
    "wof:name":"Print Shop Inc",
    "wof:placetype":"venue"
},
  "geometry": {"coordinates":[-80.30827499999999,26.023996],"type":"Point"}
}