{
  "type": "Feature",
  "properties": {
    "addr:full":"107 8th Ave Saint Petersburg FL 33706",
    "addr:housenumber":"107",
    "addr:postcode":"33706",
    "addr:street":"8Th Ave",
    "iso:country":"US",
    "sg:address":"107 8th Ave",
    "sg:city":"Saint Petersburg",
    "sg:classifiers":[
        {
            "category":"Wholesale",
            "subcategory":"Non-durable Goods",
            "type":"Manufacturing & Wholesale Goods"
        }
    ],
    "sg:phone":"+1 727 360 4743",
    "sg:postcode":"33706",
    "sg:province":"FL",
    "wof:name":"Mountcastle Intl Trdg Co Inc",
    "wof:placetype":"venue"
},
  "geometry": {"coordinates":[-82.737915,27.688087],"type":"Point"}
}