{
  "type": "Feature",
  "properties": {
    "iso:country":"US",
    "sg:address":"311 SE Mizner Blvd",
    "sg:city":"Boca Raton",
    "sg:classifiers":[
        {
            "category":"Shopping",
            "type":"Retail Goods"
        }
    ],
    "sg:phone":"+1 561 395 6273",
    "sg:postcode":"33432",
    "sg:province":"FL",
    "sg:tags":[
        "cosmetic",
        "perfume"
    ],
    "wof:name":"Lexi Cosmetics",
    "wof:placetype":"venue"
},
  "geometry": {"coordinates":[-80.08425,26.346781],"type":"Point"}
}