{
  "type": "Feature",
  "properties": {
    "iso:country":"US",
    "sg:address":"4044 SW 4th St",
    "sg:city":"Fort Lauderdale",
    "sg:classifiers":[
        {
            "category":"Building & Trades",
            "subcategory":"Landscaping Services",
            "type":"Services"
        }
    ],
    "sg:phone":"+1 954 792 6052",
    "sg:postcode":"33317",
    "sg:province":"FL",
    "sg:tags":[
        "horticultural",
        "counseling"
    ],
    "wof:name":"Horticultural Masterworks",
    "wof:placetype":"venue"
},
  "geometry": {"coordinates":[-80.203181,26.116207],"type":"Point"}
}