{
  "type": "Feature",
  "properties": {
    "iso:country":"US",
    "sg:address":"10875 Park Blvd N",
    "sg:city":"Seminole",
    "sg:classifiers":[
        {
            "category":"Health Services",
            "subcategory":"Podiatrist",
            "type":"Services"
        }
    ],
    "sg:phone":"+1 727 398 6650",
    "sg:postcode":"33772",
    "sg:province":"FL",
    "sg:website":"www.westcentralpodiatry.com",
    "wof:name":"West Central Podiatry Cons Pl",
    "wof:placetype":"venue"
},
  "geometry": {"coordinates":[-82.790617,27.839697],"type":"Point"}
}