{
  "type": "Feature",
  "properties": {
    "iso:country":"US",
    "sg:address":"11860 State Hwy 84",
    "sg:city":"Fort Lauderdale",
    "sg:classifiers":[
        {
            "category":"Wholesale",
            "subcategory":"Machinery & Supplies",
            "type":"Manufacturing & Wholesale Goods"
        }
    ],
    "sg:phone":"+1 954 452 0699",
    "sg:postcode":"33325",
    "sg:province":"FL",
    "sg:tags":[
        "equipment",
        "parts",
        "aviation"
    ],
    "wof:name":"Arrow Dynamics LLC",
    "wof:placetype":"venue"
},
  "geometry": {"coordinates":[-80.300788,26.111695],"type":"Point"}
}