{
  "type": "Feature",
  "properties": {
    "iso:country":"US",
    "sg:address":"915 Berkshire Rd",
    "sg:city":"Daytona Beach",
    "sg:classifiers":[
        {
            "category":"Shopping",
            "subcategory":"Florist",
            "type":"Retail Goods"
        }
    ],
    "sg:phone":"+1 386 254 8152",
    "sg:postcode":"32117",
    "sg:province":"FL",
    "wof:name":"Expressions of Love Floral",
    "wof:placetype":"venue"
},
  "geometry": {"coordinates":[-81.06017300000001,29.21986],"type":"Point"}
}