{
  "type": "Feature",
  "properties": {
    "addr:full":"948 Pineland Dr Rockledge FL 32955",
    "addr:housenumber":"948",
    "addr:postcode":"32955",
    "addr:street":"Pineland Dr",
    "iso:country":"US",
    "sg:address":"948 Pineland Dr",
    "sg:city":"Rockledge",
    "sg:classifiers":[
        {
            "category":"Building & Trades",
            "subcategory":"Landscaping Services",
            "type":"Services"
        }
    ],
    "sg:phone":"+1 321 403 2268",
    "sg:postcode":"32955",
    "sg:province":"FL",
    "sg:tags":[
        "landscape",
        "contractor"
    ],
    "wof:name":"Jeremiah Johnson Lawn Care",
    "wof:placetype":"venue"
},
  "geometry": {"coordinates":[-80.741378,28.319444],"type":"Point"}
}