{
  "type": "Feature",
  "properties": {
    "iso:country":"US",
    "sg:address":"2100 SE 17th St",
    "sg:city":"Ocala",
    "sg:classifiers":[
        {
            "category":"Health Services",
            "subcategory":"Chiropractor",
            "type":"Services"
        }
    ],
    "sg:phone":"+1 352 861 0566",
    "sg:postcode":"34471",
    "sg:province":"FL",
    "wof:name":"Lewis Chiropractic Center",
    "wof:placetype":"venue"
},
  "geometry": {"coordinates":[-82.11006999999999,29.171533],"type":"Point"}
}