{
  "type": "Feature",
  "properties": {
    "iso:country":"US",
    "sg:address":"805 Park Ave",
    "sg:city":"West Palm Beach",
    "sg:classifiers":[
        {
            "category":"Building & Trades",
            "subcategory":"Construction",
            "type":"Services"
        }
    ],
    "sg:phone":"+1 561 845 9377",
    "sg:postcode":"33403",
    "sg:province":"FL",
    "sg:tags":[
        "contractor"
    ],
    "wof:name":"Ahrens Companies",
    "wof:placetype":"venue"
},
  "geometry": {"coordinates":[-80.070474,26.798831],"type":"Point"}
}