{
  "type": "Feature",
  "properties": {
    "iso:country":"US",
    "sg:address":"3932 W Hillsboro Blvd",
    "sg:city":"Deerfield Beach",
    "sg:classifiers":[
        {
            "category":"Personal",
            "subcategory":"Beauty Salon",
            "type":"Services"
        }
    ],
    "sg:phone":"+1 954 571 9349",
    "sg:postcode":"33073",
    "sg:province":"FL",
    "sg:tags":[
        "manicuring"
    ],
    "wof:name":"American Nails",
    "wof:placetype":"venue"
},
  "geometry": {"coordinates":[-80.177561,26.317554],"type":"Point"}
}