{
  "type": "Feature",
  "properties": {
    "iso:country":"US",
    "sg:address":"9454 NW 13th St",
    "sg:city":"Doral",
    "sg:classifiers":[
        {
            "category":"Building & Trades",
            "subcategory":"Plumbing",
            "type":"Services"
        }
    ],
    "sg:phone":"+1 305 639 6030",
    "sg:postcode":"33172",
    "sg:province":"FL",
    "sg:tags":[
        "conditioning",
        "air",
        "system",
        "contractor"
    ],
    "wof:name":"Galo Air Conditioning Inc",
    "wof:placetype":"venue"
},
  "geometry": {"coordinates":[-80.349796,25.78467],"type":"Point"}
}