{
  "type": "Feature",
  "properties": {
    "iso:country":"US",
    "sg:address":"1101 Clare Ave",
    "sg:city":"West Palm Beach",
    "sg:classifiers":[
        {
            "category":"Building & Trades",
            "subcategory":"Construction",
            "type":"Services"
        }
    ],
    "sg:phone":"+1 561 655 0966",
    "sg:postcode":"33401",
    "sg:province":"FL",
    "sg:tags":[
        "hanging",
        "contractor"
    ],
    "wof:name":"John Volk Restoration Inc",
    "wof:placetype":"venue"
},
  "geometry": {"coordinates":[-80.063115,26.699112],"type":"Point"}
}