{
  "type": "Feature",
  "properties": {
    "addr:full":"335 Garden St De Leon Springs FL 32114",
    "addr:housenumber":"335",
    "addr:postcode":"32114",
    "addr:street":"Garden St De Leon",
    "iso:country":"US",
    "sg:address":"335 Garden St",
    "sg:city":"De Leon Springs",
    "sg:classifiers":[
        {
            "category":"Building & Trades",
            "subcategory":"Construction",
            "type":"Services"
        }
    ],
    "sg:phone":"+1 386 985 3014",
    "sg:postcode":"32114",
    "sg:province":"FL",
    "sg:tags":[
        "roofing",
        "contractor"
    ],
    "wof:name":"H & R Roofing",
    "wof:placetype":"venue"
},
  "geometry": {"coordinates":[-81.037099,29.213672],"type":"Point"}
}