{
  "type": "Feature",
  "properties": {
    "iso:country":"US",
    "sg:address":"2272 Lake Pointe Cir",
    "sg:city":"Leesburg",
    "sg:classifiers":[
        {
            "category":"Professional",
            "subcategory":"Accounting & Tax Preparation",
            "type":"Services"
        }
    ],
    "sg:phone":"+1 352 326 5651",
    "sg:postcode":"34748",
    "sg:province":"FL",
    "wof:name":"J M H Enterprises Inc",
    "wof:placetype":"venue"
},
  "geometry": {"coordinates":[-81.83470699999999,28.813321],"type":"Point"}
}