{
  "type": "Feature",
  "properties": {
    "addr:full":"2017 Corporate Dr Boynton Beach FL 33426",
    "addr:housenumber":"2017",
    "addr:postcode":"33426",
    "addr:street":"Corporate Dr",
    "iso:country":"US",
    "sg:address":"2017 Corporate Dr",
    "sg:city":"Boynton Beach",
    "sg:classifiers":[
        {
            "category":"Health Services",
            "subcategory":"Hospital",
            "type":"Services"
        }
    ],
    "sg:phone":"+1 561 732 2455",
    "sg:postcode":"33426",
    "sg:province":"FL",
    "wof:name":"Bethesda Memorial Hospital",
    "wof:placetype":"venue"
},
  "geometry": {"coordinates":[-80.077388,26.512886],"type":"Point"}
}