{
  "type": "Feature",
  "properties": {
    "addr:full":"1075 NW 121st Ln Pompano Beach FL 33071",
    "addr:housenumber":"1075",
    "addr:postcode":"33071",
    "addr:street":"Nw 121St Ln",
    "iso:country":"US",
    "sg:address":"1075 NW 121st Ln",
    "sg:city":"Pompano Beach",
    "sg:classifiers":[
        {
            "category":"Wholesale",
            "subcategory":"Groceries",
            "type":"Manufacturing & Wholesale Goods"
        }
    ],
    "sg:phone":"+1 954 753 3736",
    "sg:postcode":"33071",
    "sg:province":"FL",
    "sg:tags":[
        "product",
        "fiber",
        "optic",
        "reseller",
        "datum",
        "voice"
    ],
    "wof:name":"Supply All",
    "wof:placetype":"venue"
},
  "geometry": {"coordinates":[-80.29057299999999,26.243545],"type":"Point"}
}