{
  "type": "Feature",
  "properties": {
    "iso:country":"US",
    "sg:address":"1414 S Tamiami Trl",
    "sg:city":"Sarasota",
    "sg:classifiers":[
        {
            "category":"Restaurant",
            "type":"Food & Drink"
        }
    ],
    "sg:menulink":"http://www.allmenus.com/fl/sarasota/93305-waffle-house/menu/",
    "sg:phone":"+1 941 953 7933",
    "sg:postcode":"34239",
    "sg:province":"FL",
    "sg:tags":[
        "american"
    ],
    "wof:name":"Waffle House",
    "wof:placetype":"venue"
},
  "geometry": {"coordinates":[-82.529692,27.320891],"type":"Point"}
}