{
  "type": "Feature",
  "properties": {
    "addr:full":"9000 Universal Blvd Orlando FL 32819",
    "addr:housenumber":"9000",
    "addr:postcode":"32819",
    "addr:street":"Universal Blvd",
    "iso:country":"US",
    "sg:address":"9000 Universal Blvd",
    "sg:city":"Orlando",
    "sg:classifiers":[
        {
            "category":"Building & Trades",
            "subcategory":"Construction",
            "type":"Services"
        }
    ],
    "sg:phone":"+1 407 352 8182",
    "sg:postcode":"32819",
    "sg:province":"FL",
    "sg:tags":[
        "general",
        "contractor"
    ],
    "sg:website":"www.huntconstructiongroup.com",
    "wof:name":"Hunt Construction",
    "wof:placetype":"venue"
},
  "geometry": {"coordinates":[-81.468816,28.432958],"type":"Point"}
}