{
  "type": "Feature",
  "properties": {
    "iso:country":"US",
    "sg:address":"601 N Flamingo Rd",
    "sg:city":"Hollywood",
    "sg:classifiers":[
        {
            "category":"Health Services",
            "subcategory":"Doctor",
            "type":"Services"
        }
    ],
    "sg:phone":"+1 954 433 3114",
    "sg:postcode":"33028",
    "sg:province":"FL",
    "sg:tags":[
        "osteopathic"
    ],
    "wof:name":"Jaffer Mohsin MD Faafp",
    "wof:placetype":"venue"
},
  "geometry": {"coordinates":[-80.312077,26.012604],"type":"Point"}
}