{
  "type": "Feature",
  "properties": {
    "iso:country":"US",
    "sg:address":"4270 Cardinal Blvd",
    "sg:city":"Daytona Beach",
    "sg:classifiers":[
        {
            "category":"Building & Trades",
            "subcategory":"Plumbing",
            "type":"Services"
        }
    ],
    "sg:phone":"+1 386 763 4088",
    "sg:postcode":"32127",
    "sg:province":"FL",
    "sg:tags":[
        "contractor"
    ],
    "wof:name":"Daytona AC & Rfrgn",
    "wof:placetype":"venue"
},
  "geometry": {"coordinates":[-80.954787,29.123436],"type":"Point"}
}