{
  "type": "Feature",
  "properties": {
    "iso:country":"US",
    "sg:address":"418 Apache Ln",
    "sg:city":"Boca Raton",
    "sg:classifiers":[
        {
            "category":"Professional",
            "type":"Services"
        }
    ],
    "sg:phone":"+1 561 995 1017",
    "sg:postcode":"33487",
    "sg:province":"FL",
    "wof:name":"Fox Foundation Inc",
    "wof:placetype":"venue"
},
  "geometry": {"coordinates":[-80.08522600000001,26.417879],"type":"Point"}
}