{
  "type": "Feature",
  "properties": {
    "addr:full":"2477 N State Rd 7 Fort Lauderdale FL 33313",
    "addr:housenumber":"2477",
    "addr:postcode":"33313",
    "addr:street":"N State Rd 7",
    "iso:country":"US",
    "sg:address":"2477 N State Rd 7",
    "sg:city":"Fort Lauderdale",
    "sg:classifiers":[
        {
            "category":"Personal",
            "subcategory":"Barber",
            "type":"Services"
        }
    ],
    "sg:phone":"+1 954 739 8286",
    "sg:postcode":"33313",
    "sg:province":"FL",
    "sg:tags":[
        "shop"
    ],
    "wof:name":"Butta Kutz Unisex & Barber",
    "wof:placetype":"venue"
},
  "geometry": {"coordinates":[-80.203112,26.157602],"type":"Point"}
}