{
  "type": "Feature",
  "properties": {
    "addr:full":"720 N Indiana Ave Englewood FL 34223",
    "addr:housenumber":"720",
    "addr:postcode":"34223",
    "addr:street":"N Indiana Ave",
    "iso:country":"US",
    "sg:address":"720 N Indiana Ave",
    "sg:city":"Englewood",
    "sg:classifiers":[
        {
            "category":"Building & Trades",
            "subcategory":"Cleaning & Sanitation",
            "type":"Services"
        }
    ],
    "sg:phone":"+1 941 475 9170",
    "sg:postcode":"34223",
    "sg:province":"FL",
    "sg:tags":[
        "janitor"
    ],
    "wof:name":"Custom Cleaning",
    "wof:placetype":"venue"
},
  "geometry": {"coordinates":[-82.354415,26.974405],"type":"Point"}
}