{
  "type": "Feature",
  "properties": {
    "addr:full":"5482 Sharron Rd Green Cove Springs FL 32043",
    "addr:housenumber":"5482",
    "addr:postcode":"32043",
    "addr:street":"Sharron Rd",
    "iso:country":"US",
    "sg:address":"5482 Sharron Rd",
    "sg:city":"Green Cove Springs",
    "sg:classifiers":[
        {
            "category":"Building & Trades",
            "subcategory":"Plumbing",
            "type":"Services"
        }
    ],
    "sg:phone":"+1 904 284 1008",
    "sg:postcode":"32043",
    "sg:province":"FL",
    "sg:tags":[
        "air",
        "heating",
        "conditioning",
        "contractor"
    ],
    "wof:name":"Jsr Mechanical Services",
    "wof:placetype":"venue"
},
  "geometry": {"coordinates":[-81.805244,29.907219],"type":"Point"}
}