{
  "type": "Feature",
  "properties": {
    "addr:full":"7115 Paramount Dr Lake Worth FL 33467",
    "addr:housenumber":"7115",
    "addr:postcode":"33467",
    "addr:street":"Paramount Dr",
    "iso:country":"US",
    "sg:address":"7115 Paramount Dr",
    "sg:city":"Lake Worth",
    "sg:classifiers":[
        {
            "category":"Building & Trades",
            "subcategory":"Construction",
            "type":"Services"
        }
    ],
    "sg:phone":"+1 561 968 0098",
    "sg:postcode":"33467",
    "sg:province":"FL",
    "sg:tags":[
        "contractor"
    ],
    "wof:name":"E F Tile & Marble Inc",
    "wof:placetype":"venue"
},
  "geometry": {"coordinates":[-80.16083500000001,26.578002],"type":"Point"}
}