{
  "type": "Feature",
  "properties": {
    "addr:full":"3034 30th Ln Lake Worth FL 33463",
    "addr:housenumber":"3034",
    "addr:postcode":"33463",
    "addr:street":"30Th Ln",
    "iso:country":"US",
    "sg:address":"3034 30th Ln",
    "sg:city":"Lake Worth",
    "sg:classifiers":[
        {
            "category":"Professional",
            "subcategory":"Business Services",
            "type":"Services"
        }
    ],
    "sg:phone":"+1 561 310 5333",
    "sg:postcode":"33463",
    "sg:province":"FL",
    "sg:tags":[
        "telecommunication"
    ],
    "wof:name":"Intermedia Dev Foundation",
    "wof:placetype":"venue"
},
  "geometry": {"coordinates":[-80.137291,26.614452],"type":"Point"}
}