{
  "type": "Feature",
  "properties": {
    "addr:full":"216 E Tarpon Ave Tarpon Springs FL 34689",
    "addr:housenumber":"216",
    "addr:postcode":"34689",
    "addr:street":"E Tarpon Ave",
    "iso:country":"US",
    "sg:address":"216 E Tarpon Ave",
    "sg:city":"Tarpon Springs",
    "sg:classifiers":[
        {
            "category":"Personal",
            "subcategory":"Beauty Salon",
            "type":"Services"
        }
    ],
    "sg:phone":"+1 727 943 9194",
    "sg:postcode":"34689",
    "sg:province":"FL",
    "sg:tags":[
        "shop"
    ],
    "wof:name":"Palace",
    "wof:placetype":"venue"
},
  "geometry": {"coordinates":[-82.753728,28.146168],"type":"Point"}
}