{
  "type": "Feature",
  "properties": {
    "iso:country":"US",
    "sg:address":"5770 W Irlo Bronson Memorial Hwy",
    "sg:city":"Kissimmee",
    "sg:classifiers":[
        {
            "category":"Recreation",
            "subcategory":"Amusement Park",
            "type":"Entertainment"
        }
    ],
    "sg:phone":"+1 407 397 0209",
    "sg:postcode":"34746",
    "sg:province":"FL",
    "wof:name":"Human Sling Shot",
    "wof:placetype":"venue"
},
  "geometry": {"coordinates":[-81.515958,28.330426],"type":"Point"}
}