{
  "type": "Feature",
  "properties": {
    "iso:country":"US",
    "sg:address":"6902 Overlook Dr",
    "sg:city":"Fort Myers",
    "sg:classifiers":[
        {
            "category":"Wholesale",
            "subcategory":"Vending Machines",
            "type":"Manufacturing & Wholesale Goods"
        }
    ],
    "sg:phone":"+1 239 481 5984",
    "sg:postcode":"33919",
    "sg:province":"FL",
    "wof:name":"Murphy Vending Inc",
    "wof:placetype":"venue"
},
  "geometry": {"coordinates":[-81.891684,26.537525],"type":"Point"}
}