{
  "type": "Feature",
  "properties": {
    "iso:country":"US",
    "sg:address":"4208 US Hwy 27",
    "sg:city":"Sebring",
    "sg:classifiers":[
        {
            "category":"Restaurant",
            "type":"Food & Drink"
        }
    ],
    "sg:phone":"+1 863 382 8808",
    "sg:postcode":"33870",
    "sg:province":"FL",
    "wof:name":"Coffee Bean Restaurant",
    "wof:placetype":"venue"
},
  "geometry": {"coordinates":[-81.49773,27.522336],"type":"Point"}
}