{
  "type": "Feature",
  "properties": {
    "iso:country":"US",
    "sg:address":"4824 N Kings Hwy",
    "sg:city":"Fort Pierce",
    "sg:classifiers":[
        {
            "category":"Shopping",
            "type":"Retail Goods"
        }
    ],
    "sg:phone":"+1 772 467 9801",
    "sg:postcode":"34951",
    "sg:province":"FL",
    "sg:tags":[
        "water",
        "equipment",
        "installation",
        "treatment"
    ],
    "wof:name":"A A Water Systems Inc",
    "wof:placetype":"venue"
},
  "geometry": {"coordinates":[-80.398239,27.521487],"type":"Point"}
}