{
  "type": "Feature",
  "properties": {
    "iso:country":"US",
    "sg:address":"2400 W Silver Springs Blvd",
    "sg:city":"Ocala",
    "sg:classifiers":[
        {
            "category":"Government",
            "subcategory":"Police Station",
            "type":"Public Place"
        }
    ],
    "sg:phone":"+1 352 368 5400",
    "sg:postcode":"34475",
    "sg:province":"FL",
    "sg:tags":[
        "department"
    ],
    "wof:name":"Ocala Police Dept",
    "wof:placetype":"venue"
},
  "geometry": {"coordinates":[-82.16679999999999,29.186334],"type":"Point"}
}