{
  "type": "Feature",
  "properties": {
    "addr:full":"3500 NW 97th Blvd Gainesville FL 32606",
    "addr:housenumber":"3500",
    "addr:postcode":"32606",
    "addr:street":"Nw 97Th Blvd",
    "iso:country":"US",
    "sg:address":"3500 NW 97th Blvd",
    "sg:city":"Gainesville",
    "sg:classifiers":[
        {
            "category":"Home & Garden",
            "subcategory":"Building Materials",
            "type":"Retail Goods"
        },
        {
            "category":"Building & Trades",
            "subcategory":"Construction",
            "type":"Services"
        }
    ],
    "sg:phone":"+1 352 333 7223",
    "sg:postcode":"32606",
    "sg:province":"FL",
    "sg:tags":[
        "repair",
        "refinishing",
        "handyman",
        "improvement",
        "maintenance",
        "sealing",
        "tile-cleaning"
    ],
    "sg:website":"http://www.realpagessites.com/aprofessionalhomeservice",
    "wof:name":"A Commercial Maintenance & Repair",
    "wof:placetype":"venue"
},
  "geometry": {"coordinates":[-82.44771,29.685066],"type":"Point"}
}