{
  "type": "Feature",
  "properties": {
    "addr:full":"2425 Wilton Dr Fort Lauderdale FL 33305",
    "addr:housenumber":"2425",
    "addr:postcode":"33305",
    "addr:street":"Wilton Dr",
    "iso:country":"US",
    "sg:address":"2425 Wilton Dr",
    "sg:city":"Fort Lauderdale",
    "sg:classifiers":[
        {
            "category":"Food & Beverages",
            "subcategory":"Groceries & Convenience Stores",
            "type":"Retail Goods"
        }
    ],
    "sg:phone":"+1 954 561 5679",
    "sg:postcode":"33305",
    "sg:province":"FL",
    "wof:name":"Number 2 Food Mart Inc",
    "wof:placetype":"venue"
},
  "geometry": {"coordinates":[-80.133398,26.1589],"type":"Point"}
}