{
  "type": "Feature",
  "properties": {
    "addr:full":"13857 Wellington Trce Wellington FL 33414",
    "addr:housenumber":"13857",
    "addr:postcode":"33414",
    "addr:street":"Wellington Trce",
    "iso:country":"US",
    "sg:address":"13857 Wellington Trce",
    "sg:city":"Wellington",
    "sg:classifiers":[
        {
            "category":"Real Estate",
            "subcategory":"Real Estate Agent",
            "type":"Services"
        }
    ],
    "sg:phone":"+1 561 790 6443",
    "sg:postcode":"33414",
    "sg:province":"FL",
    "wof:name":"Exit Realty",
    "wof:placetype":"venue"
},
  "geometry": {"coordinates":[-80.266453,26.662495],"type":"Point"}
}