{
  "type": "Feature",
  "properties": {
    "addr:full":"15347 SW 179th Ter Miami FL 33187",
    "addr:housenumber":"15347",
    "addr:postcode":"33187",
    "addr:street":"Sw 179Th Ter",
    "iso:country":"US",
    "sg:address":"15347 SW 179th Ter",
    "sg:city":"Miami",
    "sg:classifiers":[
        {
            "category":"Community Center",
            "subcategory":"Senior",
            "type":"Public Place"
        },
        {
            "category":"Social Services",
            "subcategory":"Adult Care",
            "type":"Services"
        }
    ],
    "sg:phone":"+1 786 367 6954",
    "sg:postcode":"33187",
    "sg:province":"FL",
    "sg:tags":[
        "counseling",
        "citizen"
    ],
    "wof:name":"Majestic Senior Care Alf Inc",
    "wof:placetype":"venue"
},
  "geometry": {"coordinates":[-80.441056,25.599996],"type":"Point"}
}