{
  "type": "Feature",
  "properties": {
    "addr:full":"6620 Southpoint Dr S Jacksonville FL 32216",
    "addr:postcode":"6620;32216",
    "addr:street":"Southpoint Dr S",
    "iso:country":"US",
    "sg:address":"6620 Southpoint Dr S",
    "sg:city":"Jacksonville",
    "sg:classifiers":[
        {
            "category":"Health Services",
            "subcategory":"Clinic",
            "type":"Services"
        }
    ],
    "sg:phone":"+1 904 350 0035",
    "sg:postcode":"32216",
    "sg:province":"FL",
    "sg:tags":[
        "home",
        "care"
    ],
    "sg:website":"www.housecall.com",
    "wof:name":"Housecall Home Healthcare",
    "wof:placetype":"venue"
},
  "geometry": {"coordinates":[-81.588126,30.252714],"type":"Point"}
}