{
  "type": "Feature",
  "properties": {
    "iso:country":"US",
    "sg:address":"910 Pinellas Bayway S",
    "sg:city":"Tierra Verde",
    "sg:classifiers":[
        {
            "category":"Banks & Credit Unions",
            "subcategory":"Bank",
            "type":"Services"
        }
    ],
    "sg:phone":"+1 727 867 0900",
    "sg:postcode":"33715",
    "sg:province":"FL",
    "sg:tags":[
        "currency",
        "exchange"
    ],
    "wof:name":"Tierra Verde Trading Corp",
    "wof:placetype":"venue"
},
  "geometry": {"coordinates":[-82.722976,27.685672],"type":"Point"}
}