{
  "type": "Feature",
  "properties": {
    "iso:country":"US",
    "sg:address":"335 Racetrack Rd NW",
    "sg:city":"Fort Walton Bch",
    "sg:classifiers":[
        {
            "category":"Manufacturing",
            "subcategory":"Printing",
            "type":"Manufacturing & Wholesale Goods"
        }
    ],
    "sg:phone":"+1 850 863 1817",
    "sg:postcode":"32547",
    "sg:province":"FL",
    "sg:tags":[
        "screen"
    ],
    "sg:website":"www.t-shirt-connection.com",
    "wof:name":"Blondie's T-Shirt Connection",
    "wof:placetype":"venue"
},
  "geometry": {"coordinates":[-86.627954,30.449347],"type":"Point"}
}