{
  "type": "Feature",
  "properties": {
    "addr:full":"233 3rd St N Jacksonville Bch FL 32250",
    "addr:housenumber":"233",
    "addr:postcode":"32250",
    "addr:street":"3Rd St N",
    "iso:country":"US",
    "sg:address":"233 3rd St N",
    "sg:city":"Jacksonville Bch",
    "sg:classifiers":[
        {
            "category":"Professional",
            "subcategory":"Lawyer & Legal Services",
            "type":"Services"
        }
    ],
    "sg:phone":"+1 904 246 3322",
    "sg:postcode":"32250",
    "sg:province":"FL",
    "sg:tags":[
        "attorney"
    ],
    "wof:name":"Ossi & Butler Najem & Rosario",
    "wof:placetype":"venue"
},
  "geometry": {"coordinates":[-81.39241699999999,30.291737],"type":"Point"}
}