{
  "type": "Feature",
  "properties": {
    "addr:full":"2679 Gulf To Bay Blvd Clearwater FL 33759",
    "addr:housenumber":"2679",
    "addr:postcode":"33759",
    "addr:street":"Gulf To Bay Blvd",
    "iso:country":"US",
    "sg:address":"2679 Gulf To Bay Blvd",
    "sg:city":"Clearwater",
    "sg:classifiers":[
        {
            "category":"Ice Cream",
            "type":"Food & Drink"
        }
    ],
    "sg:menulink":"http://www.allmenus.com/fl/clearwater/230216-marble-slab-creamery/menu/",
    "sg:phone":"+1 727 797 6061",
    "sg:postcode":"33759",
    "sg:province":"FL",
    "sg:tags":[
        "american"
    ],
    "wof:name":"Marble Slab Creamery",
    "wof:placetype":"venue"
},
  "geometry": {"coordinates":[-82.727942,27.960498],"type":"Point"}
}