{
  "type": "Feature",
  "properties": {
    "addr:full":"7212 Curry Ford Rd Orlando FL 32822",
    "addr:housenumber":"7212",
    "addr:postcode":"32822",
    "addr:street":"Curry Ford Rd",
    "iso:country":"US",
    "sg:address":"7212 Curry Ford Rd",
    "sg:city":"Orlando",
    "sg:classifiers":[
        {
            "category":"Place Of Worship",
            "type":"Public Place"
        },
        {
            "category":"Government",
            "subcategory":"Post Office",
            "type":"Public Place"
        }
    ],
    "sg:phone":"+1 407 823 9662",
    "sg:postcode":"32822",
    "sg:province":"FL",
    "sg:tags":[
        "alliance",
        "churches-christian",
        "missionary",
        "church"
    ],
    "wof:name":"Southeastern District Of The Christian And Missionary Alliance District Office",
    "wof:placetype":"venue"
},
  "geometry": {"coordinates":[-81.29130000000001,28.516385],"type":"Point"}
}