{
  "type": "Feature",
  "properties": {
    "addr:full":"9510 Corkscrew Rd Estero FL 33928",
    "addr:postcode":"9510;33928",
    "addr:street":"Corkscrew Rd",
    "iso:country":"US",
    "sg:address":"9510 Corkscrew Rd",
    "sg:city":"Estero",
    "sg:classifiers":[
        {
            "category":"Organizations",
            "subcategory":"Membership Organization",
            "type":"Services"
        }
    ],
    "sg:phone":"+1 239 390 7646",
    "sg:postcode":"33928",
    "sg:province":"FL",
    "sg:tags":[
        "athletic"
    ],
    "wof:name":"Gulf Coast Hockey Plus",
    "wof:placetype":"venue"
},
  "geometry": {"coordinates":[-81.796015,26.431147],"type":"Point"}
}