{
  "type": "Feature",
  "properties": {
    "iso:country":"US",
    "sg:address":"949 SW 122nd Ave",
    "sg:city":"Miami",
    "sg:classifiers":[
        {
            "category":"Professional",
            "type":"Services"
        }
    ],
    "sg:phone":"+1 305 279 5855",
    "sg:postcode":"33184",
    "sg:province":"FL",
    "wof:name":"Preferred Card Svc Inc",
    "wof:placetype":"venue"
},
  "geometry": {"coordinates":[-80.392661,25.760416],"type":"Point"}
}