{
  "type": "Feature",
  "properties": {
    "addr:full":"824 N John Young Pkwy Kissimmee FL 34741",
    "addr:housenumber":"824",
    "addr:postcode":"34741",
    "addr:street":"N John Young Pkwy",
    "iso:country":"US",
    "sg:address":"824 N John Young Pkwy",
    "sg:city":"Kissimmee",
    "sg:classifiers":[
        {
            "category":"Banks & Credit Unions",
            "subcategory":"Bank",
            "type":"Services"
        }
    ],
    "sg:phone":"+1 407 931 2511",
    "sg:postcode":"34741",
    "sg:province":"FL",
    "sg:tags":[
        "loan",
        "real estate"
    ],
    "wof:name":"Countrywide Home Loans",
    "wof:placetype":"venue"
},
  "geometry": {"coordinates":[-81.416014,28.299745],"type":"Point"}
}