{
  "type": "Feature",
  "properties": {
    "addr:full":"795 E 8th St Hialeah FL 33010",
    "addr:housenumber":"795",
    "addr:postcode":"33010",
    "addr:street":"E 8Th St",
    "iso:country":"US",
    "sg:address":"795 E 8th St",
    "sg:city":"Hialeah",
    "sg:classifiers":[
        {
            "category":"Autos & Motor Vehicles",
            "subcategory":"Automobile Sales",
            "type":"Retail Goods"
        }
    ],
    "sg:phone":"+1 305 887 0055",
    "sg:postcode":"33010",
    "sg:province":"FL",
    "sg:tags":[
        "dealers-used",
        "car",
        "used",
        "cars-wholesale"
    ],
    "wof:name":"The Auto Mart",
    "wof:placetype":"venue"
},
  "geometry": {"coordinates":[-80.26555399999999,25.829587],"type":"Point"}
}