{
  "type": "Feature",
  "properties": {
    "iso:country":"US",
    "sg:address":"3991 Commerce Pkwy",
    "sg:city":"Hollywood",
    "sg:classifiers":[
        {
            "category":"Wholesale",
            "subcategory":"Photographic Equipment",
            "type":"Manufacturing & Wholesale Goods"
        }
    ],
    "sg:phone":"+1 954 290 5723",
    "sg:postcode":"33025",
    "sg:province":"FL",
    "sg:tags":[
        "graphic",
        "art"
    ],
    "wof:name":"Enovation Graphic Systems",
    "wof:placetype":"venue"
},
  "geometry": {"coordinates":[-80.28163499999999,25.980179],"type":"Point"}
}