{
  "type": "Feature",
  "properties": {
    "iso:country":"US",
    "sg:address":"3350 NW 22nd Dr",
    "sg:city":"Pompano Beach",
    "sg:classifiers":[
        {
            "category":"Health Services",
            "subcategory":"Clinic",
            "type":"Services"
        }
    ],
    "sg:phone":"+1 954 701 0383",
    "sg:postcode":"33066",
    "sg:province":"FL",
    "sg:tags":[
        "phlebotomy",
        "screening",
        "drug"
    ],
    "wof:name":"We Care Phlebotomy",
    "wof:placetype":"venue"
},
  "geometry": {"coordinates":[-80.170565,26.257511],"type":"Point"}
}