{
  "type": "Feature",
  "properties": {
    "addr:full":"119 SE 12th St Fort Lauderdale FL 33316",
    "addr:housenumber":"119",
    "addr:postcode":"33316",
    "addr:street":"Se 12Th St",
    "iso:country":"US",
    "sg:address":"119 SE 12th St",
    "sg:city":"Fort Lauderdale",
    "sg:classifiers":[
        {
            "category":"Professional",
            "subcategory":"Lawyer & Legal Services",
            "type":"Services"
        }
    ],
    "sg:phone":"+1 954 525 1210",
    "sg:postcode":"33316",
    "sg:province":"FL",
    "wof:name":"Law Firm John Hurley Esquire",
    "wof:placetype":"venue"
},
  "geometry": {"coordinates":[-80.141142,26.107618],"type":"Point"}
}