{
  "type": "Feature",
  "properties": {
    "addr:full":"1840 Morrill St Sarasota FL 34236",
    "addr:housenumber":"1840",
    "addr:postcode":"34236",
    "addr:street":"Morrill St",
    "iso:country":"US",
    "sg:address":"1840 Morrill St",
    "sg:city":"Sarasota",
    "sg:classifiers":[
        {
            "category":"Health Services",
            "subcategory":"Clinic",
            "type":"Services"
        },
        {
            "category":"Health Services",
            "subcategory":"Hospital",
            "type":"Services"
        }
    ],
    "sg:phone":"+1 941 366 0221",
    "sg:postcode":"34236",
    "sg:province":"FL",
    "sg:tags":[
        "inpatient",
        "substance",
        "mental",
        "abuse",
        "outpatient"
    ],
    "wof:name":"Coastal Recovery Inc",
    "wof:placetype":"venue"
},
  "geometry": {"coordinates":[-82.533509,27.333749],"type":"Point"}
}