{
  "type": "Feature",
  "properties": {
    "addr:full":"1740 Cypress Ave Orange City FL 32763",
    "addr:housenumber":"1740",
    "addr:postcode":"32763",
    "addr:street":"Cypress Ave",
    "iso:country":"US",
    "sg:address":"1740 Cypress Ave",
    "sg:city":"Orange City",
    "sg:classifiers":[
        {
            "category":"Manufacturing",
            "subcategory":"Wood Products",
            "type":"Manufacturing & Wholesale Goods"
        }
    ],
    "sg:phone":"+1 386 774 0589",
    "sg:postcode":"32763",
    "sg:province":"FL",
    "sg:tags":[
        "mfg"
    ],
    "wof:name":"Handyman Bryan Miller Inc",
    "wof:placetype":"venue"
},
  "geometry": {"coordinates":[-81.32977200000001,28.925067],"type":"Point"}
}