{
  "type": "Feature",
  "properties": {
    "addr:full":"12021 NW 4th St Fort Lauderdale FL 33325",
    "addr:housenumber":"12021",
    "addr:postcode":"33325",
    "addr:street":"Nw 4Th St",
    "iso:country":"US",
    "sg:address":"12021 NW 4th St",
    "sg:city":"Fort Lauderdale",
    "sg:classifiers":[
        {
            "category":"Retail",
            "subcategory":"Auto Repair",
            "type":"Services"
        }
    ],
    "sg:phone":"+1 954 577 5774",
    "sg:postcode":"33325",
    "sg:province":"FL",
    "sg:tags":[
        "general"
    ],
    "wof:name":"Rvw Auto Storage Inc",
    "wof:placetype":"venue"
},
  "geometry": {"coordinates":[-80.311072,26.124011],"type":"Point"}
}