{
  "type": "Feature",
  "properties": {
    "addr:full":"1571 W 49th St Hialeah FL 33012",
    "addr:housenumber":"1571",
    "addr:postcode":"33012",
    "addr:street":"W 49Th St",
    "iso:country":"US",
    "sg:address":"1571 W 49th St",
    "sg:city":"Hialeah",
    "sg:classifiers":[
        {
            "category":"Shopping",
            "subcategory":"Pharmacy",
            "type":"Retail Goods"
        }
    ],
    "sg:phone":"+1 305 557 1365",
    "sg:postcode":"33012",
    "sg:province":"FL",
    "sg:tags":[
        "drugstore"
    ],
    "wof:name":"CVS Pharmacy",
    "wof:placetype":"venue"
},
  "geometry": {"coordinates":[-80.314201,25.866501],"type":"Point"}
}