{
  "type": "Feature",
  "properties": {
    "iso:country":"US",
    "sg:address":"123 Shamrock Blvd",
    "sg:city":"Venice",
    "sg:classifiers":[
        {
            "category":"Health Services",
            "subcategory":"Doctor",
            "type":"Services"
        }
    ],
    "sg:phone":"+1 941 493 3352",
    "sg:postcode":"34293",
    "sg:province":"FL",
    "sg:tags":[
        "dentist"
    ],
    "wof:name":"Oral Surgery Ctr",
    "wof:placetype":"venue"
},
  "geometry": {"coordinates":[-82.422664,27.073176],"type":"Point"}
}