{
  "type": "Feature",
  "properties": {
    "addr:full":"1060 Maitland Center Commons Blvd Maitland FL 32751",
    "addr:housenumber":"1060",
    "addr:postcode":"32751",
    "addr:street":"Maitland Center Commons Blvd",
    "iso:country":"US",
    "sg:address":"1060 Maitland Center Commons Blvd",
    "sg:city":"Maitland",
    "sg:classifiers":[
        {
            "category":"Professional",
            "subcategory":"Employment Agencies",
            "type":"Services"
        }
    ],
    "sg:phone":"+1 407 660 8088",
    "sg:postcode":"32751",
    "sg:province":"FL",
    "sg:website":"www.spherion.com",
    "wof:name":"Spherion",
    "wof:placetype":"venue"
},
  "geometry": {"coordinates":[-81.39724200000001,28.638543],"type":"Point"}
}