{
  "type": "Feature",
  "properties": {
    "addr:full":"5609 Wesconnett Blvd Jacksonville FL 32244",
    "addr:housenumber":"5609",
    "addr:postcode":"32244",
    "addr:street":"Wesconnett Blvd",
    "iso:country":"US",
    "sg:address":"5609 Wesconnett Blvd",
    "sg:city":"Jacksonville",
    "sg:classifiers":[
        {
            "category":"Building & Trades",
            "subcategory":"Landscaping Services",
            "type":"Services"
        }
    ],
    "sg:phone":"+1 904 778 8733",
    "sg:postcode":"32244",
    "sg:province":"FL",
    "sg:tags":[
        "tree"
    ],
    "wof:name":"Family Tree Svc",
    "wof:placetype":"venue"
},
  "geometry": {"coordinates":[-81.73810899999999,30.244857],"type":"Point"}
}