{
  "type": "Feature",
  "properties": {
    "addr:full":"2254 Tamiami Trl Venice FL 34293",
    "addr:housenumber":"2254",
    "addr:postcode":"34293",
    "addr:street":"Tamiami Trl",
    "iso:country":"US",
    "sg:address":"2254 Tamiami Trl",
    "sg:city":"Venice",
    "sg:classifiers":[
        {
            "category":"Banks & Credit Unions",
            "subcategory":"Bank",
            "type":"Services"
        }
    ],
    "sg:phone":"+1 941 496 8999",
    "sg:postcode":"34293",
    "sg:province":"FL",
    "sg:tags":[
        "cashing",
        "check"
    ],
    "wof:name":"AAA Pay Day Loans Inc",
    "wof:placetype":"venue"
},
  "geometry": {"coordinates":[-82.40808800000001,27.050841],"type":"Point"}
}