{
  "type": "Feature",
  "properties": {
    "addr:full":"14955 Gulf Blvd Madeira Beach FL 33708",
    "addr:housenumber":"14955",
    "addr:postcode":"33708",
    "addr:street":"Gulf Blvd",
    "iso:country":"US",
    "sg:address":"14955 Gulf Blvd",
    "sg:city":"Madeira Beach",
    "sg:classifiers":[
        {
            "category":"Banks & Credit Unions",
            "subcategory":"Bank",
            "type":"Services"
        }
    ],
    "sg:phone":"+1 727 394 7231",
    "sg:postcode":"33708",
    "sg:province":"FL",
    "sg:tags":[
        "loan",
        "real estate"
    ],
    "wof:name":"DRS Home Svc",
    "wof:placetype":"venue"
},
  "geometry": {"coordinates":[-82.79903299999999,27.799394],"type":"Point"}
}