{
  "type": "Feature",
  "properties": {
    "iso:country":"US",
    "sg:address":"8351 N Pine Island Rd",
    "sg:city":"Fort Lauderdale",
    "sg:classifiers":[
        {
            "category":"Autos & Motor Vehicles",
            "subcategory":"Fuel & Gas Station",
            "type":"Retail Goods"
        }
    ],
    "sg:phone":"+1 954 722 0111",
    "sg:postcode":"33321",
    "sg:province":"FL",
    "sg:tags":[
        "station",
        "gasoline"
    ],
    "wof:name":"Ocellos Woodmont Chevron",
    "wof:placetype":"venue"
},
  "geometry": {"coordinates":[-80.269926,26.225074],"type":"Point"}
}