{
  "type": "Feature",
  "properties": {
    "iso:country":"US",
    "sg:address":"2601 Wells Ave",
    "sg:city":"Casselberry",
    "sg:classifiers":[
        {
            "category":"Manufacturing",
            "subcategory":"Printing",
            "type":"Manufacturing & Wholesale Goods"
        }
    ],
    "sg:phone":"+1 407 339 3600",
    "sg:postcode":"32730",
    "sg:province":"FL",
    "sg:tags":[
        "book"
    ],
    "wof:name":"Hastings Housedaytrips Publs",
    "wof:placetype":"venue"
},
  "geometry": {"coordinates":[-81.345805,28.656867],"type":"Point"}
}