{
  "type": "Feature",
  "properties": {
    "addr:full":"1252 N Pine Hills Rd Orlando FL 32808",
    "addr:housenumber":"1252",
    "addr:postcode":"32808",
    "addr:street":"N Pine Hills Rd",
    "iso:country":"US",
    "sg:address":"1252 N Pine Hills Rd",
    "sg:city":"Orlando",
    "sg:classifiers":[
        {
            "category":"Real Estate",
            "subcategory":"Real Estate Agent",
            "type":"Services"
        }
    ],
    "sg:phone":"+1 407 299 9661",
    "sg:postcode":"32808",
    "sg:province":"FL",
    "wof:name":"Universal Realty Inc",
    "wof:placetype":"venue"
},
  "geometry": {"coordinates":[-81.450363,28.563813],"type":"Point"}
}