{
  "type": "Feature",
  "properties": {
    "addr:full":"151 W Silver Star Rd Ocoee FL 34761",
    "addr:housenumber":"151",
    "addr:postcode":"34761",
    "addr:street":"W Silver Star Rd",
    "iso:country":"US",
    "sg:address":"151 W Silver Star Rd",
    "sg:city":"Ocoee",
    "sg:classifiers":[
        {
            "category":"Banks & Credit Unions",
            "subcategory":"Bank",
            "type":"Services"
        }
    ],
    "sg:phone":"+1 407 877 2059",
    "sg:postcode":"34761",
    "sg:province":"FL",
    "sg:tags":[
        "loan",
        "real estate"
    ],
    "wof:name":"Four Corners Mortgaging Co",
    "wof:placetype":"venue"
},
  "geometry": {"coordinates":[-81.54665199999999,28.573736],"type":"Point"}
}