{
  "type": "Feature",
  "properties": {
    "iso:country":"US",
    "sg:address":"118 Colomba Rd",
    "sg:city":"Debary",
    "sg:classifiers":[
        {
            "category":"Restaurant",
            "type":"Food & Drink"
        }
    ],
    "sg:phone":"+1 386 668 7441",
    "sg:postcode":"32713",
    "sg:province":"FL",
    "wof:name":"Florida Dining Online",
    "wof:placetype":"venue"
},
  "geometry": {"coordinates":[-81.303459,28.88221],"type":"Point"}
}