{
  "type": "Feature",
  "properties": {
    "iso:country":"US",
    "sg:address":"5461 Wood Crossing St",
    "sg:city":"Orlando",
    "sg:classifiers":[
        {
            "category":"Shopping",
            "subcategory":"Gifts & Souvenirs",
            "type":"Retail Goods"
        }
    ],
    "sg:phone":"+1 407 296 8479",
    "sg:postcode":"32811",
    "sg:province":"FL",
    "wof:name":"New Sun Gift Shop Corp",
    "wof:placetype":"venue"
},
  "geometry": {"coordinates":[-81.45316,28.533136],"type":"Point"}
}