{
  "type": "Feature",
  "properties": {
    "iso:country":"US",
    "sg:address":"18375 SW 264th St",
    "sg:city":"Homestead",
    "sg:classifiers":[
        {
            "category":"Recreation",
            "subcategory":"Dog Park",
            "type":"Entertainment"
        },
        {
            "category":"Shopping",
            "subcategory":"Pets & Pet Supplies",
            "type":"Retail Goods"
        }
    ],
    "sg:phone":"+1 305 242 1011",
    "sg:postcode":"33031",
    "sg:province":"FL",
    "sg:tags":[
        "training"
    ],
    "wof:name":"Canine Cadet",
    "wof:placetype":"venue"
},
  "geometry": {"coordinates":[-80.48871200000001,25.521048],"type":"Point"}
}