{
  "type": "Feature",
  "properties": {
    "iso:country":"US",
    "sg:address":"4860 17th St",
    "sg:city":"Sarasota",
    "sg:classifiers":[
        {
            "category":"Professional",
            "subcategory":"Engineering",
            "type":"Services"
        }
    ],
    "sg:phone":"+1 941 371 5605",
    "sg:postcode":"34235",
    "sg:province":"FL",
    "sg:tags":[
        "water",
        "treatment",
        "engineer"
    ],
    "wof:name":"Sarasota County Utilities",
    "wof:placetype":"venue"
},
  "geometry": {"coordinates":[-82.470738,27.352049],"type":"Point"}
}