{
  "type": "Feature",
  "properties": {
    "addr:full":"2813 Winterset Park SE Winter Haven FL 33884",
    "addr:housenumber":"2813",
    "addr:postcode":"33884",
    "addr:street":"Winterset Park Se",
    "iso:country":"US",
    "sg:address":"2813 Winterset Park SE",
    "sg:city":"Winter Haven",
    "sg:classifiers":[
        {
            "category":"Professional",
            "subcategory":"Computer Services",
            "type":"Services"
        }
    ],
    "sg:phone":"+1 863 324 5259",
    "sg:postcode":"33884",
    "sg:province":"FL",
    "sg:tags":[
        "repair",
        "cleaning"
    ],
    "wof:name":"Computer Power Services",
    "wof:placetype":"venue"
},
  "geometry": {"coordinates":[-81.690848,27.978573],"type":"Point"}
}