{
  "type": "Feature",
  "properties": {
    "iso:country":"US",
    "sg:address":"4521 Georgia Ave",
    "sg:city":"West Palm Beach",
    "sg:classifiers":[
        {
            "category":"Building & Trades",
            "subcategory":"Construction",
            "type":"Services"
        }
    ],
    "sg:phone":"+1 561 833 8144",
    "sg:postcode":"33405",
    "sg:province":"FL",
    "sg:tags":[
        "designer",
        "marine",
        "contractor"
    ],
    "wof:name":"Marine Manufacturing Servicing",
    "wof:placetype":"venue"
},
  "geometry": {"coordinates":[-80.05874300000001,26.67163],"type":"Point"}
}