{
  "type": "Feature",
  "properties": {
    "iso:country":"US",
    "sg:address":"200 S Lawrence Blvd",
    "sg:city":"Keystone Heights",
    "sg:classifiers":[
        {
            "category":"Banks & Credit Unions",
            "subcategory":"Bank",
            "type":"Services"
        }
    ],
    "sg:phone":"+1 352 473 4933",
    "sg:postcode":"32656",
    "sg:province":"FL",
    "sg:tags":[
        "state"
    ],
    "wof:name":"Compass Bank",
    "wof:placetype":"venue"
},
  "geometry": {"coordinates":[-82.03115,29.784489],"type":"Point"}
}