{
  "type": "Feature",
  "properties": {
    "addr:full":"2950 SW 27th Ave Miami FL 33133",
    "addr:housenumber":"2950",
    "addr:postcode":"33133",
    "addr:street":"Sw 27Th Ave",
    "iso:country":"US",
    "sg:address":"2950 SW 27th Ave",
    "sg:city":"Miami",
    "sg:classifiers":[
        {
            "category":"Professional",
            "subcategory":"Lawyer & Legal Services",
            "type":"Services"
        }
    ],
    "sg:phone":"+1 305 285 0800",
    "sg:postcode":"33133",
    "sg:province":"FL",
    "sg:tags":[
        "attorney"
    ],
    "wof:name":"Diaz & O'Naghten",
    "wof:placetype":"venue"
},
  "geometry": {"coordinates":[-80.237712,25.736886],"type":"Point"}
}