{
  "type": "Feature",
  "properties": {
    "addr:full":"5325 Norris Lake Ct Mulberry FL 33860",
    "addr:housenumber":"5325",
    "addr:postcode":"33860",
    "addr:street":"Norris Lake Ct",
    "iso:country":"US",
    "sg:address":"5325 Norris Lake Ct",
    "sg:city":"Mulberry",
    "sg:classifiers":[
        {
            "category":"Building & Trades",
            "subcategory":"Landscaping Services",
            "type":"Services"
        }
    ],
    "sg:phone":"+1 863 701 8211",
    "sg:postcode":"33860",
    "sg:province":"FL",
    "wof:name":"Donovan Jones Southside Lawn",
    "wof:placetype":"venue"
},
  "geometry": {"coordinates":[-82.032133,27.933638],"type":"Point"}
}