{
  "type": "Feature",
  "properties": {
    "iso:country":"US",
    "sg:address":"74 Lucky Dr",
    "sg:city":"Ormond Beach",
    "sg:classifiers":[
        {
            "category":"Building & Trades",
            "subcategory":"Construction",
            "type":"Services"
        }
    ],
    "sg:phone":"+1 386 677 2170",
    "sg:postcode":"32176",
    "sg:province":"FL",
    "sg:tags":[
        "carpenter"
    ],
    "wof:name":"Olsen Carpentry By S Olsen",
    "wof:placetype":"venue"
},
  "geometry": {"coordinates":[-81.040564,29.289975],"type":"Point"}
}