{
  "type": "Feature",
  "properties": {
    "iso:country":"US",
    "sg:address":"19011 NW 131 Ave",
    "sg:city":"Lake Butler",
    "sg:classifiers":[
        {
            "category":"Wholesale",
            "subcategory":"Hardware",
            "type":"Manufacturing & Wholesale Goods"
        }
    ],
    "sg:phone":"+1 386 496 4692",
    "sg:postcode":"32054",
    "sg:province":"FL",
    "sg:tags":[
        "cutlery"
    ],
    "wof:name":"Hendry Brother's Cutlery",
    "wof:placetype":"venue"
},
  "geometry": {"coordinates":[-82.26299,29.992117],"type":"Point"}
}