{
  "type": "Feature",
  "properties": {
    "iso:country":"US",
    "sg:address":"8501 Astronaut Blvd",
    "sg:city":"Cape Canaveral",
    "sg:classifiers":[
        {
            "category":"Professional",
            "subcategory":"Business Services",
            "type":"Services"
        }
    ],
    "sg:phone":"+1 321 799 9907",
    "sg:postcode":"32920",
    "sg:province":"FL",
    "sg:tags":[
        "packaging"
    ],
    "wof:name":"Pak Mail Ctr",
    "wof:placetype":"venue"
},
  "geometry": {"coordinates":[-80.608333,28.391709],"type":"Point"}
}