{
  "type": "Feature",
  "properties": {
    "addr:full":"2016 SW 73 St Gainesville FL 32607",
    "addr:housenumber":"2016",
    "addr:postcode":"32607",
    "addr:street":"Sw 73 St",
    "iso:country":"US",
    "sg:address":"2016 SW 73 St",
    "sg:city":"Gainesville",
    "sg:classifiers":[
        {
            "category":"Organizations",
            "subcategory":"Religious Organization",
            "type":"Services"
        }
    ],
    "sg:phone":"+1 352 331 0668",
    "sg:postcode":"32607",
    "sg:province":"FL",
    "wof:name":"Kathleen Dames Ministries Inc",
    "wof:placetype":"venue"
},
  "geometry": {"coordinates":[-82.420214,29.634492],"type":"Point"}
}