{
  "type": "Feature",
  "properties": {
    "iso:country":"US",
    "sg:address":"4420 Windergate Ct",
    "sg:city":"Jacksonville",
    "sg:classifiers":[
        {
            "category":"Home & Garden",
            "subcategory":"Home Furnishings",
            "type":"Retail Goods"
        }
    ],
    "sg:phone":"+1 904 260 8706",
    "sg:postcode":"32257",
    "sg:province":"FL",
    "sg:tags":[
        "beveled",
        "glass",
        "ornamental"
    ],
    "wof:name":"C W Designs",
    "wof:placetype":"venue"
},
  "geometry": {"coordinates":[-81.602923,30.179959],"type":"Point"}
}