{
  "type": "Feature",
  "properties": {
    "iso:country":"US",
    "sg:address":"1319 American Elm Dr",
    "sg:city":"Altamonte Springs",
    "sg:classifiers":[
        {
            "category":"Sports & Exercise",
            "subcategory":"Gym",
            "type":"Entertainment"
        }
    ],
    "sg:phone":"+1 407 291 2140",
    "sg:postcode":"32714",
    "sg:province":"FL",
    "sg:tags":[
        "fitness",
        "physical",
        "facility"
    ],
    "wof:name":"First Choice Fitness Inc",
    "wof:placetype":"venue"
},
  "geometry": {"coordinates":[-81.437218,28.641847],"type":"Point"}
}