{
  "type": "Feature",
  "properties": {
    "iso:country":"US",
    "sg:address":"8403 Millinockett Ln",
    "sg:city":"Orlando",
    "sg:classifiers":[
        {
            "category":"Home & Garden",
            "subcategory":"Mobile Homes",
            "type":"Retail Goods"
        }
    ],
    "sg:phone":"+1 407 658 8555",
    "sg:postcode":"32825",
    "sg:province":"FL",
    "wof:name":"Shadow Hills",
    "wof:placetype":"venue"
},
  "geometry": {"coordinates":[-81.27309700000001,28.561055],"type":"Point"}
}