{
  "type": "Feature",
  "properties": {
    "iso:country":"US",
    "sg:address":"5340 SW 130th Ave",
    "sg:city":"Miramar",
    "sg:classifiers":[
        {
            "category":"Communications",
            "subcategory":"Television Station",
            "type":"Services"
        }
    ],
    "sg:phone":"+1 954 298 9673",
    "sg:postcode":"33027",
    "sg:province":"FL",
    "sg:tags":[
        "network"
    ],
    "wof:name":"Teamstar Techs Inc",
    "wof:placetype":"venue"
},
  "geometry": {"coordinates":[-80.31813699999999,25.958481],"type":"Point"}
}