{
  "type": "Feature",
  "properties": {
    "iso:country":"US",
    "sg:address":"903 SW 13th St",
    "sg:city":"Gainesville",
    "sg:classifiers":[
        {
            "category":"Organizations",
            "subcategory":"Community Association",
            "type":"Services"
        }
    ],
    "sg:phone":"+1 352 377 2006",
    "sg:postcode":"32601",
    "sg:province":"FL",
    "sg:tags":[
        "sorority",
        "fraternity"
    ],
    "wof:name":"Delta Zeta Sorority House",
    "wof:placetype":"venue"
},
  "geometry": {"coordinates":[-82.33932,29.643086],"type":"Point"}
}