{
  "type": "Feature",
  "properties": {
    "addr:full":"7307 W Colonial Dr Orlando FL 32818",
    "addr:housenumber":"7307",
    "addr:postcode":"32818",
    "addr:street":"W Colonial Dr",
    "iso:country":"US",
    "sg:address":"7307 W Colonial Dr",
    "sg:city":"Orlando",
    "sg:classifiers":[
        {
            "category":"Juice Bar",
            "subcategory":"None",
            "type":"Food & Drink"
        },
        {
            "category":"Shopping",
            "subcategory":"Gifts & Souvenirs",
            "type":"Retail Goods"
        }
    ],
    "sg:phone":"+1 407 296 7430",
    "sg:postcode":"32818",
    "sg:province":"FL",
    "sg:tags":[
        "basket",
        "fruit",
        "shop"
    ],
    "sg:website":"http://www.ediblearrangements.com",
    "wof:name":"Edible Arrangements",
    "wof:placetype":"venue"
},
  "geometry": {"coordinates":[-81.480904,28.552047],"type":"Point"}
}