{
  "type": "Feature",
  "properties": {
    "addr:full":"5300 Roosevelt Blvd. Clearwater FL 33760",
    "addr:housenumber":"5300",
    "addr:postcode":"33760",
    "addr:street":"Roosevelt Blvd.",
    "iso:country":"US",
    "sg:address":"5300 Roosevelt Blvd.",
    "sg:city":"Clearwater",
    "sg:classifiers":[
        {
            "category":"Professional",
            "subcategory":"Detective & Security Services",
            "type":"Services"
        }
    ],
    "sg:phone":"+1 727 557 4344",
    "sg:postcode":"33760",
    "sg:province":"FL",
    "sg:tags":[
        "bail",
        "bond"
    ],
    "sg:website":"http://www.BailBondsinClearwater.com",
    "wof:name":"Bail Bonds in Clearwater",
    "wof:placetype":"venue"
},
  "geometry": {"coordinates":[-82.728245,27.916335],"type":"Point"}
}