{
  "type": "Feature",
  "properties": {
    "addr:full":"2001 N 55th Ave Hollywood FL 33021",
    "addr:housenumber":"2001",
    "addr:postcode":"33021",
    "addr:street":"N 55Th Ave",
    "iso:country":"US",
    "sg:address":"2001 N 55th Ave",
    "sg:city":"Hollywood",
    "sg:classifiers":[
        {
            "category":"Manufacturing",
            "subcategory":"Metals",
            "type":"Manufacturing & Wholesale Goods"
        }
    ],
    "sg:phone":"+1 954 962 8211",
    "sg:postcode":"33021",
    "sg:province":"FL",
    "wof:name":"D Marra Collection Inc",
    "wof:placetype":"venue"
},
  "geometry": {"coordinates":[-80.19905799999999,26.027739],"type":"Point"}
}