{
  "type": "Feature",
  "properties": {
    "addr:full":"1101 SW Dalton Ave Port St Lucie FL 34953",
    "addr:housenumber":"1101",
    "addr:postcode":"34953",
    "addr:street":"Sw Dalton Ave",
    "iso:country":"US",
    "sg:address":"1101 SW Dalton Ave",
    "sg:city":"Port St Lucie",
    "sg:classifiers":[
        {
            "category":"Personal",
            "type":"Services"
        }
    ],
    "sg:phone":"+1 772 336 9284",
    "sg:postcode":"34953",
    "sg:province":"FL",
    "sg:tags":[
        "miscellaneous"
    ],
    "wof:name":"Palm Beach Personal Svc",
    "wof:placetype":"venue"
},
  "geometry": {"coordinates":[-80.381962,27.266345],"type":"Point"}
}