{
  "type": "Feature",
  "properties": {
    "iso:country":"US",
    "sg:address":"13902 N Dale Mabry Hwy",
    "sg:city":"Tampa",
    "sg:classifiers":[
        {
            "category":"Professional",
            "subcategory":"Credit Reporting & Collection",
            "type":"Services"
        }
    ],
    "sg:phone":"+1 813 908 3000",
    "sg:postcode":"33618",
    "sg:province":"FL",
    "sg:tags":[
        "agency"
    ],
    "wof:name":"Mars Inc",
    "wof:placetype":"venue"
},
  "geometry": {"coordinates":[-82.5068,28.074821],"type":"Point"}
}