{
  "type": "Feature",
  "properties": {
    "addr:full":"4271 Weldon Ave Spring Hill FL 34609",
    "addr:housenumber":"4271",
    "addr:postcode":"34609",
    "addr:street":"Weldon Ave",
    "iso:country":"US",
    "sg:address":"4271 Weldon Ave",
    "sg:city":"Spring Hill",
    "sg:classifiers":[
        {
            "category":"Marine",
            "type":"Transportation"
        }
    ],
    "sg:phone":"+1 352 686 0853",
    "sg:postcode":"34609",
    "sg:province":"FL",
    "sg:tags":[
        "water",
        "transport"
    ],
    "wof:name":"Steven Soults Captian",
    "wof:placetype":"venue"
},
  "geometry": {"coordinates":[-82.53010399999999,28.494737],"type":"Point"}
}