{
  "type": "Feature",
  "properties": {
    "iso:country":"US",
    "sg:address":"14244 SW 142nd Ave",
    "sg:city":"Miami",
    "sg:phone":"+1 305 971 5829",
    "sg:postcode":"33186",
    "sg:province":"FL",
    "sg:tags":[
        "scale"
    ],
    "wof:name":"Full Scale Corp",
    "wof:placetype":"venue"
},
  "geometry": {"coordinates":[-80.42294099999999,25.634734],"type":"Point"}
}