{
  "type": "Feature",
  "properties": {
    "iso:country":"US",
    "sg:address":"258 NW 1st Ave",
    "sg:city":"Homestead",
    "sg:classifiers":[
        {
            "category":"Wholesale",
            "subcategory":"Fruits & Vegetables",
            "type":"Manufacturing & Wholesale Goods"
        }
    ],
    "sg:phone":"+1 305 245 4211",
    "sg:postcode":"33030",
    "sg:province":"FL",
    "sg:tags":[
        "shipper"
    ],
    "wof:name":"Di Mare Fresh Inc",
    "wof:placetype":"venue"
},
  "geometry": {"coordinates":[-80.479495,25.47202],"type":"Point"}
}