{
  "type": "Feature",
  "properties": {
    "iso:country":"US",
    "sg:address":"9009 US Hwy 19",
    "sg:city":"Pinellas Park",
    "sg:classifiers":[
        {
            "category":"Shopping",
            "subcategory":"Books",
            "type":"Retail Goods"
        }
    ],
    "sg:phone":"+1 727 568 9661",
    "sg:postcode":"33782",
    "sg:province":"FL",
    "sg:tags":[
        "dealer"
    ],
    "wof:name":"Calvary Chapel Bookstore",
    "wof:placetype":"venue"
},
  "geometry": {"coordinates":[-82.693425,27.852863],"type":"Point"}
}