{
  "type": "Feature",
  "properties": {
    "iso:country":"US",
    "sg:address":"4631 NW 31st Ave",
    "sg:city":"Fort Lauderdale",
    "sg:classifiers":[
        {
            "category":"Building & Trades",
            "subcategory":"Construction",
            "type":"Services"
        }
    ],
    "sg:phone":"+1 954 630 8958",
    "sg:postcode":"33309",
    "sg:province":"FL",
    "sg:tags":[
        "painter"
    ],
    "wof:name":"Tri Square Building & Constr",
    "wof:placetype":"venue"
},
  "geometry": {"coordinates":[-80.187523,26.184254],"type":"Point"}
}