{
  "type": "Feature",
  "properties": {
    "addr:full":"1150 Iroquois Ave Fort Lauderdale FL 33312",
    "addr:housenumber":"1150",
    "addr:postcode":"33312",
    "addr:street":"Iroquois Ave",
    "iso:country":"US",
    "sg:address":"1150 Iroquois Ave",
    "sg:city":"Fort Lauderdale",
    "sg:classifiers":[
        {
            "category":"Manufacturing",
            "subcategory":"Apparel",
            "type":"Manufacturing & Wholesale Goods"
        }
    ],
    "sg:phone":"+1 954 584 5800",
    "sg:postcode":"33312",
    "sg:province":"FL",
    "sg:tags":[
        "mfg",
        "trade",
        "outerwear",
        "contractor"
    ],
    "wof:name":"Lady Di Designs Inc",
    "wof:placetype":"venue"
},
  "geometry": {"coordinates":[-80.18934299999999,26.107497],"type":"Point"}
}