{
  "type": "Feature",
  "properties": {
    "addr:full":"11901 Lacy Ln Fort Myers FL 33966",
    "addr:housenumber":"11901",
    "addr:postcode":"33966",
    "addr:street":"Lacy Ln",
    "iso:country":"US",
    "sg:address":"11901 Lacy Ln",
    "sg:city":"Fort Myers",
    "sg:classifiers":[
        {
            "category":"Wholesale",
            "subcategory":"Machinery & Supplies",
            "type":"Manufacturing & Wholesale Goods"
        }
    ],
    "sg:phone":"+1 239 277 5252",
    "sg:postcode":"33966",
    "sg:province":"FL",
    "sg:tags":[
        "equipment",
        "layer",
        "establishment",
        "carpet"
    ],
    "wof:name":"Boone Distributors Inc",
    "wof:placetype":"venue"
},
  "geometry": {"coordinates":[-81.84872799999999,26.572878],"type":"Point"}
}