{
  "type": "Feature",
  "properties": {
    "addr:full":"2105 Fawn Meadow Dr Valrico FL 33594",
    "addr:housenumber":"2105",
    "addr:postcode":"33594",
    "addr:street":"Fawn Meadow Dr",
    "iso:country":"US",
    "sg:address":"2105 Fawn Meadow Dr",
    "sg:city":"Valrico",
    "sg:classifiers":[
        {
            "category":"Building & Trades",
            "subcategory":"Construction",
            "type":"Services"
        }
    ],
    "sg:phone":"+1 813 655 6414",
    "sg:postcode":"33594",
    "sg:province":"FL",
    "sg:tags":[
        "builder",
        "operative"
    ],
    "wof:name":"Weekley Homes LP",
    "wof:placetype":"venue"
},
  "geometry": {"coordinates":[-82.25276599999999,27.96537],"type":"Point"}
}