{
  "type": "Feature",
  "properties": {
    "addr:full":"2848 E Irlo Bronson Memorial Hwy Kissimmee FL 34744",
    "addr:housenumber":"2848",
    "addr:postcode":"34744",
    "addr:street":"E Irlo Bronson Memorial Hwy",
    "iso:country":"US",
    "sg:address":"2848 E Irlo Bronson Memorial Hwy",
    "sg:city":"Kissimmee",
    "sg:classifiers":[
        {
            "category":"Shopping",
            "subcategory":"Musical Instruments",
            "type":"Retail Goods"
        }
    ],
    "sg:phone":"+1 407 935 0708",
    "sg:postcode":"34744",
    "sg:province":"FL",
    "wof:name":"Gullin's Guitar Shop",
    "wof:placetype":"venue"
},
  "geometry": {"coordinates":[-81.328776,28.261486],"type":"Point"}
}