{
  "type": "Feature",
  "properties": {
    "addr:full":"621 SW 11th Ter Cape Coral FL 33991",
    "addr:housenumber":"621",
    "addr:postcode":"33991",
    "addr:street":"Sw 11Th Ter",
    "iso:country":"US",
    "sg:address":"621 SW 11th Ter",
    "sg:city":"Cape Coral",
    "sg:classifiers":[
        {
            "category":"Real Estate",
            "subcategory":"Real Estate Agent",
            "type":"Services"
        }
    ],
    "sg:phone":"+1 239 772 2742",
    "sg:postcode":"33991",
    "sg:province":"FL",
    "sg:tags":[
        "appraiser"
    ],
    "wof:name":"Accomplished Real Estate",
    "wof:placetype":"venue"
},
  "geometry": {"coordinates":[-81.989947,26.631392],"type":"Point"}
}