{
  "type": "Feature",
  "properties": {
    "addr:full":"800 Ibis Way West Palm Beach FL 33408",
    "addr:housenumber":"800",
    "addr:postcode":"33408",
    "addr:street":"Ibis Way",
    "iso:country":"US",
    "sg:address":"800 Ibis Way",
    "sg:city":"West Palm Beach",
    "sg:classifiers":[
        {
            "category":"Professional",
            "subcategory":"Management & Consulting",
            "type":"Services"
        }
    ],
    "sg:phone":"+1 561 514 7240",
    "sg:postcode":"33408",
    "sg:province":"FL",
    "sg:tags":[
        "marketing",
        "consultant"
    ],
    "wof:name":"Rick Bechtold",
    "wof:placetype":"venue"
},
  "geometry": {"coordinates":[-80.07288699999999,26.814892],"type":"Point"}
}