{
  "type": "Feature",
  "properties": {
    "iso:country":"US",
    "sg:address":"1711 SW 21st Ter",
    "sg:city":"Miami",
    "sg:classifiers":[
        {
            "category":"Government",
            "subcategory":"Fire Station",
            "type":"Public Place"
        }
    ],
    "sg:phone":"+1 305 854 5892",
    "sg:postcode":"33145",
    "sg:province":"FL",
    "sg:tags":[
        "extinguisher",
        "protection",
        "servicing",
        "equipment-repairing"
    ],
    "wof:name":"B C & ABC Fire Extinguishers",
    "wof:placetype":"venue"
},
  "geometry": {"coordinates":[-80.22321599999999,25.751582],"type":"Point"}
}