{
  "type": "Feature",
  "properties": {
    "iso:country":"US",
    "sg:address":"1074 E Venice Ave",
    "sg:city":"Venice",
    "sg:phone":"+1 941 488 5366",
    "sg:postcode":"34285",
    "sg:province":"FL",
    "wof:name":"Comprehensive Pain Management",
    "wof:placetype":"venue"
},
  "geometry": {"coordinates":[-82.425011,27.099689],"type":"Point"}
}