{
  "type": "Feature",
  "properties": {
    "addr:full":"2626 Enterprise Rd Orange City FL 32763",
    "addr:housenumber":"2626",
    "addr:postcode":"32763",
    "addr:street":"Enterprise Rd",
    "iso:country":"US",
    "sg:address":"2626 Enterprise Rd",
    "sg:city":"Orange City",
    "sg:classifiers":[
        {
            "category":"Banks & Credit Unions",
            "subcategory":"Bank",
            "type":"Services"
        }
    ],
    "sg:phone":"+1 386 000 1111",
    "sg:postcode":"32763",
    "sg:province":"FL",
    "wof:name":"Amsouth Bank",
    "wof:placetype":"venue"
},
  "geometry": {"coordinates":[-81.29487899999999,28.916776],"type":"Point"}
}