{
  "type": "Feature",
  "properties": {
    "iso:country":"US",
    "sg:address":"2820 Delcrest Dr",
    "sg:city":"Orlando",
    "sg:classifiers":[
        {
            "category":"Education",
            "subcategory":"Special Training",
            "type":"Public Place"
        }
    ],
    "sg:phone":"+1 407 677 8477",
    "sg:postcode":"32817",
    "sg:province":"FL",
    "sg:tags":[
        "educational"
    ],
    "wof:name":"Elizabeth T Gombash",
    "wof:placetype":"venue"
},
  "geometry": {"coordinates":[-81.259366,28.586879],"type":"Point"}
}