{
  "type": "Feature",
  "properties": {
    "addr:full":"1750 Sunshadow Dr Casselberry FL 32707",
    "addr:housenumber":"1750",
    "addr:postcode":"32707",
    "addr:street":"Sunshadow Dr",
    "iso:country":"US",
    "sg:address":"1750 Sunshadow Dr",
    "sg:city":"Casselberry",
    "sg:classifiers":[
        {
            "category":"Shopping",
            "subcategory":"Pets & Pet Supplies",
            "type":"Retail Goods"
        }
    ],
    "sg:phone":"+1 407 834 9011",
    "sg:postcode":"32707",
    "sg:province":"FL",
    "sg:tags":[
        "store"
    ],
    "wof:name":"Jack's Aquarium & Pets",
    "wof:placetype":"venue"
},
  "geometry": {"coordinates":[-81.32150300000001,28.697399],"type":"Point"}
}