{
  "type": "Feature",
  "properties": {
    "addr:full":"2001 W Sample Rd Pompano Beach FL 33064",
    "addr:housenumber":"2001",
    "addr:postcode":"33064",
    "addr:street":"W Sample Rd",
    "iso:country":"US",
    "sg:address":"2001 W Sample Rd",
    "sg:city":"Pompano Beach",
    "sg:classifiers":[
        {
            "category":"Shopping",
            "subcategory":"Catalog Store",
            "type":"Retail Goods"
        }
    ],
    "sg:phone":"+1 954 974 7077",
    "sg:postcode":"33064",
    "sg:province":"FL",
    "sg:tags":[
        "promotion",
        "medium"
    ],
    "wof:name":"Hispanic Directnet Corp",
    "wof:placetype":"venue"
},
  "geometry": {"coordinates":[-80.150797,26.274643],"type":"Point"}
}