{
  "type": "Feature",
  "properties": {
    "iso:country":"US",
    "sg:address":"831 NW 37th Ave",
    "sg:city":"Miami",
    "sg:classifiers":[
        {
            "category":"Retail",
            "subcategory":"Repair Shop",
            "type":"Services"
        }
    ],
    "sg:phone":"+1 305 443 4338",
    "sg:postcode":"33125",
    "sg:province":"FL",
    "sg:tags":[
        "lock",
        "locksmith"
    ],
    "wof:name":"Libertad Cerrajeria",
    "wof:placetype":"venue"
},
  "geometry": {"coordinates":[-80.255658,25.779579],"type":"Point"}
}