{
  "type": "Feature",
  "properties": {
    "iso:country":"US",
    "sg:address":"12511 Brucie Pl",
    "sg:city":"Tampa",
    "sg:classifiers":[
        {
            "category":"Retail",
            "subcategory":"Repair Shop",
            "type":"Services"
        }
    ],
    "sg:phone":"+1 813 961 3611",
    "sg:postcode":"33625",
    "sg:province":"FL",
    "sg:tags":[
        "control"
    ],
    "wof:name":"N P Controls Inc",
    "wof:placetype":"venue"
},
  "geometry": {"coordinates":[-82.56310999999999,28.056698],"type":"Point"}
}