{
  "type": "Feature",
  "properties": {
    "addr:full":"1111 Martin Luther King Jr Ave W Ste E Bradenton FL 34205",
    "addr:housenumber":"1111",
    "addr:postcode":"34205",
    "addr:street":"Martin Luther King Jr Ave W Ste E",
    "iso:country":"US",
    "sg:address":"1111 Martin Luther King Jr Ave W Ste E",
    "sg:city":"Bradenton",
    "sg:classifiers":[
        {
            "category":"Social Services",
            "type":"Services"
        },
        {
            "category":"Professional",
            "subcategory":"Employment Agencies",
            "type":"Services"
        }
    ],
    "sg:phone":"+1 941 730 0797",
    "sg:postcode":"34205",
    "sg:province":"FL",
    "sg:tags":[
        "workers'",
        "placement",
        "volunteer"
    ],
    "wof:name":"Taylor Family Foundation, Inc.",
    "wof:placetype":"venue"
},
  "geometry": {"coordinates":[-82.572757,27.491819],"type":"Point"}
}