{
  "type": "Feature",
  "properties": {
    "iso:country":"US",
    "sg:address":"3780 34th Ave S",
    "sg:city":"Saint Petersburg",
    "sg:classifiers":[
        {
            "category":"Building & Trades",
            "subcategory":"Landscaping Services",
            "type":"Services"
        }
    ],
    "sg:phone":"+1 727 864 6759",
    "sg:postcode":"33711",
    "sg:province":"FL",
    "wof:name":"Sylvester & Son",
    "wof:placetype":"venue"
},
  "geometry": {"coordinates":[-82.686224,27.737339],"type":"Point"}
}