{
  "type": "Feature",
  "properties": {
    "addr:full":"5059 S Ridgewood Ave Daytona Beach FL 32127",
    "addr:housenumber":"5059",
    "addr:postcode":"32127",
    "addr:street":"S Ridgewood Ave",
    "iso:country":"US",
    "sg:address":"5059 S Ridgewood Ave",
    "sg:city":"Daytona Beach",
    "sg:classifiers":[
        {
            "category":"Wholesale",
            "subcategory":"Machinery & Supplies",
            "type":"Manufacturing & Wholesale Goods"
        },
        {
            "category":"Wholesale",
            "subcategory":"Metals & Minerals",
            "type":"Manufacturing & Wholesale Goods"
        }
    ],
    "sg:phone":"+1 386 788 1048",
    "sg:postcode":"32127",
    "sg:province":"FL",
    "sg:tags":[
        "home",
        "aluminum"
    ],
    "wof:name":"White Aluminum Products Inc",
    "wof:placetype":"venue"
},
  "geometry": {"coordinates":[-80.98226099999999,29.131349],"type":"Point"}
}