{
  "type": "Feature",
  "properties": {
    "iso:country":"US",
    "sg:address":"1392 Weston Rd",
    "sg:city":"Weston",
    "sg:classifiers":[
        {
            "category":"Sports & Exercise",
            "subcategory":"Tennis Court",
            "type":"Entertainment"
        }
    ],
    "sg:phone":"+1 954 384 4131",
    "sg:postcode":"33326",
    "sg:province":"FL",
    "sg:tags":[
        "equipment",
        "supply"
    ],
    "wof:name":"Absolute Tennis",
    "wof:placetype":"venue"
},
  "geometry": {"coordinates":[-80.366085,26.103798],"type":"Point"}
}