{
  "type": "Feature",
  "properties": {
    "iso:country":"US",
    "sg:address":"679 W Tennessee St",
    "sg:city":"Tallahassee",
    "sg:phone":"+1 850 222 8604",
    "sg:postcode":"32304",
    "sg:province":"FL",
    "sg:tags":[
        "oil"
    ],
    "wof:name":"Superlube",
    "wof:placetype":"venue"
},
  "geometry": {"coordinates":[-84.291343,30.444616],"type":"Point"}
}