{
  "type": "Feature",
  "properties": {
    "iso:country":"US",
    "sg:address":"541 Clay Dr",
    "sg:city":"Saint Cloud",
    "sg:classifiers":[
        {
            "category":"Insurance",
            "subcategory":"Insurance Agent",
            "type":"Services"
        }
    ],
    "sg:phone":"+1 407 892 6179",
    "sg:postcode":"34769",
    "sg:province":"FL",
    "wof:name":"Platters Insurance Inc",
    "wof:placetype":"venue"
},
  "geometry": {"coordinates":[-81.274308,28.229453],"type":"Point"}
}