{
  "type": "Feature",
  "properties": {
    "iso:country":"US",
    "sg:address":"789 US Hwy 41",
    "sg:city":"Venice",
    "sg:classifiers":[
        {
            "category":"Restaurant",
            "type":"Food & Drink"
        }
    ],
    "sg:phone":"+1 941 485 6092",
    "sg:postcode":"34285",
    "sg:province":"FL",
    "wof:name":"Bud's Restaurant Barbara's Too",
    "wof:placetype":"venue"
},
  "geometry": {"coordinates":[-82.44009800000001,27.086175],"type":"Point"}
}