{
  "type": "Feature",
  "properties": {
    "iso:country":"US",
    "sg:address":"1232 8th St",
    "sg:city":"Daytona Beach",
    "sg:classifiers":[
        {
            "category":"Shopping",
            "subcategory":"Pharmacy",
            "type":"Retail Goods"
        }
    ],
    "sg:phone":"+1 386 238 3777",
    "sg:postcode":"32117",
    "sg:province":"FL",
    "wof:name":"Central Daytona Pharmacy",
    "wof:placetype":"venue"
},
  "geometry": {"coordinates":[-81.061896,29.229317],"type":"Point"}
}