{
  "type": "Feature",
  "properties": {
    "iso:country":"US",
    "sg:address":"2042 Felch Ave",
    "sg:city":"Jacksonville",
    "sg:classifiers":[
        {
            "category":"Manufacturing",
            "subcategory":"Metals",
            "type":"Manufacturing & Wholesale Goods"
        }
    ],
    "sg:phone":"+1 904 396 5821",
    "sg:postcode":"32207",
    "sg:province":"FL",
    "sg:tags":[
        "steel",
        "product",
        "mfg"
    ],
    "wof:name":"Menzer Automation",
    "wof:placetype":"venue"
},
  "geometry": {"coordinates":[-81.64299800000001,30.291159],"type":"Point"}
}