{
  "type": "Feature",
  "properties": {
    "iso:country":"US",
    "sg:address":"1815 N Mills Ave",
    "sg:city":"Orlando",
    "sg:classifiers":[
        {
            "category":"Manufacturing",
            "subcategory":"Buildings",
            "type":"Manufacturing & Wholesale Goods"
        },
        {
            "category":"Real Estate",
            "subcategory":"Developer",
            "type":"Services"
        }
    ],
    "sg:phone":"+1 407 228 1142",
    "sg:postcode":"32803",
    "sg:province":"FL",
    "sg:tags":[
        "home",
        "builder"
    ],
    "wof:name":"Capital Development Group",
    "wof:placetype":"venue"
},
  "geometry": {"coordinates":[-81.36444899999999,28.567761],"type":"Point"}
}