{
  "type": "Feature",
  "properties": {
    "addr:full":"8250 NW 25th St Unit 2 Doral FL 33122",
    "addr:housenumber":"8250;2",
    "addr:postcode":"33122",
    "addr:street":"Nw 25Th St Unit",
    "iso:country":"US",
    "sg:address":"8250 NW 25th St Unit 2",
    "sg:city":"Doral",
    "sg:classifiers":[
        {
            "category":"Transit Center",
            "subcategory":"Freight",
            "type":"Transportation"
        },
        {
            "category":"Professional",
            "subcategory":"Business Services",
            "type":"Services"
        },
        {
            "category":"Government",
            "subcategory":"Post Office",
            "type":"Public Place"
        }
    ],
    "sg:phone":"+1 305 477 6715",
    "sg:postcode":"33122",
    "sg:province":"FL",
    "sg:tags":[
        "cargo",
        "courier",
        "package",
        "express",
        "air",
        "delivery",
        "messenger"
    ],
    "wof:name":"Domesa Courier Corp",
    "wof:placetype":"venue"
},
  "geometry": {"coordinates":[-80.330018,25.796855],"type":"Point"}
}