{
  "type": "Feature",
  "properties": {
    "addr:full":"15480 NE Hwy 314 Silver Springs FL 34488",
    "addr:housenumber":"15480",
    "addr:postcode":"34488",
    "addr:street":"Ne Hwy 314",
    "iso:country":"US",
    "sg:address":"15480 NE Hwy 314",
    "sg:city":"Silver Springs",
    "sg:classifiers":[
        {
            "category":"Food & Beverages",
            "subcategory":"Groceries & Convenience Stores",
            "type":"Retail Goods"
        }
    ],
    "sg:phone":"+1 352 625 5383",
    "sg:postcode":"34488",
    "sg:province":"FL",
    "wof:name":"Kellys Country Store",
    "wof:placetype":"venue"
},
  "geometry": {"coordinates":[-81.894096,29.273867],"type":"Point"}
}