{
  "type": "Feature",
  "properties": {
    "addr:full":"18627 Us Highway 19 N Clearwater FL 33764",
    "addr:housenumber":"18627",
    "addr:postcode":"33764",
    "addr:street":"Us Highway 19 N",
    "iso:country":"US",
    "sg:address":"18627 Us Highway 19 N",
    "sg:city":"Clearwater",
    "sg:classifiers":[
        {
            "category":"Ice Cream",
            "type":"Food & Drink"
        }
    ],
    "sg:menulink":"http://www.allmenus.com/fl/clearwater/92349-steak-n-shake/menu/",
    "sg:phone":"+1 727 535 6605",
    "sg:postcode":"33764",
    "sg:province":"FL",
    "sg:tags":[
        "american"
    ],
    "wof:name":"Steak 'n Shake",
    "wof:placetype":"venue"
},
  "geometry": {"coordinates":[-82.72940199999999,27.941798],"type":"Point"}
}