{
  "type": "Feature",
  "properties": {
    "addr:full":"7895 Gunn Hwy Tampa FL 33626",
    "addr:housenumber":"7895",
    "addr:postcode":"33626",
    "addr:street":"Gunn Hwy",
    "iso:country":"US",
    "sg:address":"7895 Gunn Hwy",
    "sg:city":"Tampa",
    "sg:classifiers":[
        {
            "category":"Restaurant",
            "type":"Food & Drink"
        }
    ],
    "sg:menulink":"http://www.allmenus.com/fl/citrus-park-fern-lake/122788-quiznos-sub/menu/",
    "sg:phone":"+1 813 926 7155",
    "sg:postcode":"33626",
    "sg:province":"FL",
    "sg:tags":[
        "wrap",
        "american",
        "sandwich"
    ],
    "wof:name":"Quiznos Sub",
    "wof:placetype":"venue"
},
  "geometry": {"coordinates":[-82.577122,28.078822],"type":"Point"}
}