{
  "type": "Feature",
  "properties": {
    "iso:country":"US",
    "sg:address":"6800 NW 9th Blvd",
    "sg:city":"Gainesville",
    "sg:classifiers":[
        {
            "category":"Health Services",
            "subcategory":"Doctor",
            "type":"Services"
        },
        {
            "category":"Professional",
            "subcategory":"Research",
            "type":"Services"
        },
        {
            "category":"Community Center",
            "type":"Public Place"
        }
    ],
    "sg:phone":"+1 352 333 0939",
    "sg:postcode":"32605",
    "sg:province":"FL",
    "sg:tags":[
        "information",
        "medical",
        "surgeon",
        "physician"
    ],
    "wof:name":"Florida Research Network",
    "wof:placetype":"venue"
},
  "geometry": {"coordinates":[-82.41464000000001,29.662218],"type":"Point"}
}