{
  "type": "Feature",
  "properties": {
    "iso:country":"US",
    "sg:address":"150 Cranes Roost Blvd",
    "sg:city":"Altamonte Springs",
    "sg:classifiers":[
        {
            "category":"Real Estate",
            "subcategory":"Real Estate Operator",
            "type":"Services"
        }
    ],
    "sg:phone":"+1 407 332 7354",
    "sg:postcode":"32701",
    "sg:province":"FL",
    "sg:tags":[
        "apartment"
    ],
    "wof:name":"Rp Altamonte Llc",
    "wof:placetype":"venue"
},
  "geometry": {"coordinates":[-81.384416,28.663283],"type":"Point"}
}