{
  "type": "Feature",
  "properties": {
    "addr:full":"7667 15th St E Sarasota FL 34243",
    "addr:housenumber":"7667",
    "addr:postcode":"34243",
    "addr:street":"15Th St E",
    "iso:country":"US",
    "sg:address":"7667 15th St E",
    "sg:city":"Sarasota",
    "sg:classifiers":[
        {
            "category":"Autos & Motor Vehicles",
            "subcategory":"Automobile Sales",
            "type":"Retail Goods"
        }
    ],
    "sg:phone":"+1 941 355 0533",
    "sg:postcode":"34243",
    "sg:province":"FL",
    "sg:tags":[
        "repair",
        "used",
        "dealer",
        "car",
        "general"
    ],
    "wof:name":"Millennium Motors and Imports",
    "wof:placetype":"venue"
},
  "geometry": {"coordinates":[-82.54671999999999,27.403847],"type":"Point"}
}