{
  "type": "Feature",
  "properties": {
    "addr:full":"236 32nd Ave Vero Beach FL 32968",
    "addr:housenumber":"236",
    "addr:postcode":"32968",
    "addr:street":"32Nd Ave",
    "iso:country":"US",
    "sg:address":"236 32nd Ave",
    "sg:city":"Vero Beach",
    "sg:classifiers":[
        {
            "category":"Building & Trades",
            "subcategory":"Landscaping Services",
            "type":"Services"
        }
    ],
    "sg:phone":"+1 772 567 6893",
    "sg:postcode":"32968",
    "sg:province":"FL",
    "wof:name":"Reliable Holm Services",
    "wof:placetype":"venue"
},
  "geometry": {"coordinates":[-80.41903000000001,27.606179],"type":"Point"}
}