{
  "type": "Feature",
  "properties": {
    "iso:country":"US",
    "sg:address":"3435 Phillips Hwy",
    "sg:city":"Jacksonville",
    "sg:classifiers":[
        {
            "category":"Freight",
            "type":"Transportation"
        }
    ],
    "sg:phone":"+1 904 346 0519",
    "sg:postcode":"32207",
    "sg:province":"FL",
    "sg:tags":[
        "special",
        "general"
    ],
    "wof:name":"Private Mini Storage Realty LP",
    "wof:placetype":"venue"
},
  "geometry": {"coordinates":[-81.634502,30.289068],"type":"Point"}
}