{
  "type": "Feature",
  "properties": {
    "iso:country":"US",
    "sg:address":"900 Winderley Pl",
    "sg:city":"Maitland",
    "sg:classifiers":[
        {
            "category":"Wholesale",
            "subcategory":"Groceries",
            "type":"Manufacturing & Wholesale Goods"
        }
    ],
    "sg:phone":"+1 407 667 0099",
    "sg:postcode":"32751",
    "sg:province":"FL",
    "sg:tags":[
        "food",
        "product",
        "health"
    ],
    "wof:name":"Bio Plus",
    "wof:placetype":"venue"
},
  "geometry": {"coordinates":[-81.39575499999999,28.634056],"type":"Point"}
}