{
  "type": "Feature",
  "properties": {
    "iso:country":"US",
    "sg:address":"9414 Hawksmoor Ln",
    "sg:city":"Sarasota",
    "sg:classifiers":[
        {
            "category":"Building & Trades",
            "subcategory":"Construction",
            "type":"Services"
        }
    ],
    "sg:phone":"+1 941 966 0053",
    "sg:postcode":"34238",
    "sg:province":"FL",
    "sg:tags":[
        "carpentry",
        "contractor"
    ],
    "wof:name":"Custom Whl Utility Cabinets",
    "wof:placetype":"venue"
},
  "geometry": {"coordinates":[-82.482395,27.213354],"type":"Point"}
}