{
  "type": "Feature",
  "properties": {
    "addr:full":"221 NW 22nd Ave Miami FL 33125",
    "addr:housenumber":"221",
    "addr:postcode":"33125",
    "addr:street":"Nw 22Nd Ave",
    "iso:country":"US",
    "sg:address":"221 NW 22nd Ave",
    "sg:city":"Miami",
    "sg:classifiers":[
        {
            "category":"Professional",
            "type":"Services"
        }
    ],
    "sg:phone":"+1 305 860 3303",
    "sg:postcode":"33125",
    "sg:province":"FL",
    "wof:name":"Logia Mnrva Hijas De La Acacia",
    "wof:placetype":"venue"
},
  "geometry": {"coordinates":[-80.23097799999999,25.775655],"type":"Point"}
}