{
  "type": "Feature",
  "properties": {
    "iso:country":"US",
    "sg:address":"5668 Sioux Dr",
    "sg:city":"Tallahassee",
    "sg:classifiers":[
        {
            "category":"Professional",
            "type":"Services"
        }
    ],
    "sg:phone":"+1 850 576 1650",
    "sg:postcode":"32317",
    "sg:province":"FL",
    "wof:name":"T & L Bingo Inc",
    "wof:placetype":"venue"
},
  "geometry": {"coordinates":[-84.18147,30.448304],"type":"Point"}
}