{
  "type": "Feature",
  "properties": {
    "addr:full":"86 Pine Forest Ln Haines City FL 33844",
    "addr:housenumber":"86",
    "addr:postcode":"33844",
    "addr:street":"Pine Forest Ln",
    "iso:country":"US",
    "sg:address":"86 Pine Forest Ln",
    "sg:city":"Haines City",
    "sg:classifiers":[
        {
            "category":"Wholesale",
            "subcategory":"Plants",
            "type":"Manufacturing & Wholesale Goods"
        }
    ],
    "sg:phone":"+1 863 421 9535",
    "sg:postcode":"33844",
    "sg:province":"FL",
    "sg:tags":[
        "supply"
    ],
    "wof:name":"Wiley Wholesale Plants",
    "wof:placetype":"venue"
},
  "geometry": {"coordinates":[-81.55776899999999,28.060242],"type":"Point"}
}