{
  "type": "Feature",
  "properties": {
    "addr:full":"6625 35th St N Pinellas Park FL 33781",
    "addr:housenumber":"6625",
    "addr:postcode":"33781",
    "addr:street":"35Th St N",
    "iso:country":"US",
    "sg:address":"6625 35th St N",
    "sg:city":"Pinellas Park",
    "sg:classifiers":[
        {
            "category":"Home & Garden",
            "subcategory":"Furniture",
            "type":"Retail Goods"
        }
    ],
    "sg:phone":"+1 727 528 9800",
    "sg:postcode":"33781",
    "sg:province":"FL",
    "wof:name":"Casual Furniture Repair & Sls",
    "wof:placetype":"venue"
},
  "geometry": {"coordinates":[-82.68159199999999,27.832141],"type":"Point"}
}