{
  "type": "Feature",
  "properties": {
    "iso:country":"US",
    "sg:address":"705 Ingraham Ave",
    "sg:city":"Haines City",
    "sg:classifiers":[
        {
            "category":"Professional",
            "type":"Services"
        }
    ],
    "sg:phone":"+1 863 422 5210",
    "sg:postcode":"33844",
    "sg:province":"FL",
    "sg:tags":[
        "establishment"
    ],
    "wof:name":"Central Merchant Svc",
    "wof:placetype":"venue"
},
  "geometry": {"coordinates":[-81.62499099999999,28.109519],"type":"Point"}
}