{
  "type": "Feature",
  "properties": {
    "addr:full":"14614 Coral Berry Dr Tampa FL 33626",
    "addr:housenumber":"14614",
    "addr:postcode":"33626",
    "addr:street":"Coral Berry Dr",
    "iso:country":"US",
    "sg:address":"14614 Coral Berry Dr",
    "sg:city":"Tampa",
    "sg:classifiers":[
        {
            "category":"Professional",
            "subcategory":"Employment Agencies",
            "type":"Services"
        }
    ],
    "sg:phone":"+1 813 891 6499",
    "sg:postcode":"33626",
    "sg:province":"FL",
    "sg:tags":[
        "search",
        "executive",
        "resource",
        "consulting",
        "human"
    ],
    "wof:name":"Couture Group Inc",
    "wof:placetype":"venue"
},
  "geometry": {"coordinates":[-82.64403900000001,28.083794],"type":"Point"}
}