{
  "type": "Feature",
  "properties": {
    "iso:country":"US",
    "sg:address":"887 E Altamonte Dr",
    "sg:city":"Altamonte Springs",
    "sg:classifiers":[
        {
            "category":"Personal",
            "subcategory":"Beauty Salon",
            "type":"Services"
        }
    ],
    "sg:phone":"+1 407 261 0319",
    "sg:postcode":"32701",
    "sg:province":"FL",
    "sg:tags":[
        "shop"
    ],
    "wof:name":"Florida College Natural Health",
    "wof:placetype":"venue"
},
  "geometry": {"coordinates":[-81.360058,28.663224],"type":"Point"}
}