{
  "type": "Feature",
  "properties": {
    "iso:country":"US",
    "sg:address":"208 W Frances Ave",
    "sg:city":"Tampa",
    "sg:classifiers":[
        {
            "category":"Social Services",
            "subcategory":"Child Care",
            "type":"Services"
        }
    ],
    "sg:phone":"+1 813 223 7969",
    "sg:postcode":"33602",
    "sg:province":"FL",
    "sg:tags":[
        "day"
    ],
    "wof:name":"Miss Funmis Daycare Center",
    "wof:placetype":"venue"
},
  "geometry": {"coordinates":[-82.46346800000001,27.965011],"type":"Point"}
}