{
  "type": "Feature",
  "properties": {
    "iso:country":"US",
    "sg:address":"10821 NW 50th St",
    "sg:city":"Sunrise",
    "sg:classifiers":[
        {
            "category":"Building & Trades",
            "subcategory":"Construction",
            "type":"Services"
        }
    ],
    "sg:phone":"+1 954 572 0707",
    "sg:postcode":"33351",
    "sg:province":"FL",
    "sg:tags":[
        "industrial",
        "contractors-commercial"
    ],
    "wof:name":"J D Bligh Construction",
    "wof:placetype":"venue"
},
  "geometry": {"coordinates":[-80.294231,26.186396],"type":"Point"}
}