{
  "type": "Feature",
  "properties": {
    "iso:country":"US",
    "sg:address":"6708 US Hwy 231",
    "sg:city":"Panama City",
    "sg:classifiers":[
        {
            "category":"Recreation",
            "type":"Entertainment"
        }
    ],
    "sg:phone":"+1 850 873 7222",
    "sg:postcode":"32404",
    "sg:province":"FL",
    "sg:tags":[
        "stable"
    ],
    "wof:name":"Oakridge Equine Center",
    "wof:placetype":"venue"
},
  "geometry": {"coordinates":[-85.533919,30.264992],"type":"Point"}
}