{
  "type": "Feature",
  "properties": {
    "addr:full":"4469 NW 167th St Opa Locka FL 33055",
    "addr:housenumber":"4469",
    "addr:postcode":"33055",
    "addr:street":"Nw 167Th St;Locka",
    "iso:country":"US",
    "sg:address":"4469 NW 167th St",
    "sg:city":"Opa Locka",
    "sg:classifiers":[
        {
            "category":"Health Services",
            "subcategory":"Hospital",
            "type":"Services"
        }
    ],
    "sg:phone":"+1 305 621 1455",
    "sg:postcode":"33055",
    "sg:province":"FL",
    "sg:tags":[
        "mental"
    ],
    "wof:name":"Miami Behavioral Health Ctr",
    "wof:placetype":"venue"
},
  "geometry": {"coordinates":[-80.273076,25.925728],"type":"Point"}
}