{
  "type": "Feature",
  "properties": {
    "iso:country":"US",
    "sg:address":"7500 NW 54th St",
    "sg:city":"Miami",
    "sg:classifiers":[
        {
            "category":"Wholesale",
            "subcategory":"Painting Supplies",
            "type":"Manufacturing & Wholesale Goods"
        }
    ],
    "sg:phone":"+1 305 592 0377",
    "sg:postcode":"33166",
    "sg:province":"FL",
    "sg:tags":[
        "goods-wholesale",
        "art",
        "manufacturer"
    ],
    "wof:name":"Gfi Group",
    "wof:placetype":"venue"
},
  "geometry": {"coordinates":[-80.319672,25.822571],"type":"Point"}
}