{
  "type": "Feature",
  "properties": {
    "iso:country":"US",
    "sg:address":"3102 Edgewood Dr NE",
    "sg:city":"Palm Bay",
    "sg:classifiers":[
        {
            "category":"Building & Trades",
            "subcategory":"Construction",
            "type":"Services"
        }
    ],
    "sg:phone":"+1 321 951 2962",
    "sg:postcode":"32905",
    "sg:province":"FL",
    "sg:tags":[
        "carpentry",
        "contractor"
    ],
    "wof:name":"Steve Quinlivan Enterprises",
    "wof:placetype":"venue"
},
  "geometry": {"coordinates":[-80.57847599999999,28.013007],"type":"Point"}
}