{
  "type": "Feature",
  "properties": {
    "addr:full":"14651 Village Glen Cir Tampa FL 33618",
    "addr:housenumber":"14651",
    "addr:postcode":"33618",
    "addr:street":"Village Glen Cir",
    "iso:country":"US",
    "sg:address":"14651 Village Glen Cir",
    "sg:city":"Tampa",
    "sg:classifiers":[
        {
            "category":"Shopping",
            "subcategory":"Clothing, Apparel, & Fashions",
            "type":"Retail Goods"
        }
    ],
    "sg:phone":"+1 813 961 2147",
    "sg:postcode":"33618",
    "sg:province":"FL",
    "wof:name":"La Joya",
    "wof:placetype":"venue"
},
  "geometry": {"coordinates":[-82.516907,28.083451],"type":"Point"}
}