{
  "type": "Feature",
  "properties": {
    "addr:full":"9102 SW 19th Pl Davie FL 33324",
    "addr:housenumber":"9102",
    "addr:postcode":"33324",
    "addr:street":"Sw 19Th Pl",
    "iso:country":"US",
    "sg:address":"9102 SW 19th Pl",
    "sg:city":"Davie",
    "sg:classifiers":[
        {
            "category":"Professional",
            "type":"Services"
        }
    ],
    "sg:phone":"+1 954 888 5990",
    "sg:postcode":"33324",
    "sg:province":"FL",
    "sg:tags":[
        "establishment"
    ],
    "wof:name":"Royal Oasis Grand Bahama",
    "wof:placetype":"venue"
},
  "geometry": {"coordinates":[-80.267261,26.099202],"type":"Point"}
}