{
  "type": "Feature",
  "properties": {
    "addr:full":"2405 W Herman St Pensacola FL 32505",
    "addr:housenumber":"2405",
    "addr:postcode":"32505",
    "addr:street":"W Herman St",
    "iso:country":"US",
    "sg:address":"2405 W Herman St",
    "sg:city":"Pensacola",
    "sg:classifiers":[
        {
            "category":"Building & Trades",
            "subcategory":"Construction",
            "type":"Services"
        }
    ],
    "sg:phone":"+1 850 433 6133",
    "sg:postcode":"32505",
    "sg:province":"FL",
    "sg:tags":[
        "contract",
        "nonresidential"
    ],
    "wof:name":"Proformance Plst Pensacola",
    "wof:placetype":"venue"
},
  "geometry": {"coordinates":[-87.24504,30.448999],"type":"Point"}
}