{
  "type": "Feature",
  "properties": {
    "iso:country":"US",
    "sg:address":"1741 Augustine Pl",
    "sg:city":"Tallahassee",
    "sg:classifiers":[
        {
            "category":"Banks & Credit Unions",
            "subcategory":"Bank",
            "type":"Services"
        }
    ],
    "sg:phone":"+1 850 488 0035",
    "sg:postcode":"32301",
    "sg:province":"FL",
    "sg:tags":[
        "state"
    ],
    "wof:name":"Florida Commerce Credit Union",
    "wof:placetype":"venue"
},
  "geometry": {"coordinates":[-84.230448,30.421811],"type":"Point"}
}