{
  "type": "Feature",
  "properties": {
    "iso:country":"US",
    "sg:address":"209 E Hallandale Beach Blvd",
    "sg:city":"Hallandale",
    "sg:classifiers":[
        {
            "category":"Health Services",
            "subcategory":"Doctor",
            "type":"Services"
        }
    ],
    "sg:phone":"+1 954 454 7373",
    "sg:postcode":"33009",
    "sg:province":"FL",
    "sg:tags":[
        "medical"
    ],
    "wof:name":"Academy Eye Surgery Dr Kaplan",
    "wof:placetype":"venue"
},
  "geometry": {"coordinates":[-80.146018,25.985744],"type":"Point"}
}