{
  "type": "Feature",
  "properties": {
    "iso:country":"US",
    "sg:address":"4189 L B McLeod Rd",
    "sg:city":"Orlando",
    "sg:classifiers":[
        {
            "category":"Home & Garden",
            "subcategory":"Furniture",
            "type":"Retail Goods"
        }
    ],
    "sg:phone":"+1 407 648 2455",
    "sg:postcode":"32811",
    "sg:province":"FL",
    "sg:website":"www.featurepres.com",
    "wof:name":"Feature Presentation Inc",
    "wof:placetype":"venue"
},
  "geometry": {"coordinates":[-81.428354,28.508819],"type":"Point"}
}