{
  "type": "Feature",
  "properties": {
    "addr:full":"9701 Crosshill Blvd 102 Jacksonville FL 32222",
    "addr:housenumber":"9701;102",
    "addr:postcode":"32222",
    "addr:street":"Crosshill Blvd",
    "iso:country":"US",
    "sg:address":"9701 Crosshill Blvd 102",
    "sg:city":"Jacksonville",
    "sg:classifiers":[
        {
            "category":"Shopping",
            "subcategory":"Department Store",
            "type":"Retail Goods"
        }
    ],
    "sg:phone":"+1 904 772 8893",
    "sg:postcode":"32222",
    "sg:province":"FL",
    "sg:website":"http://www.kohls.com",
    "wof:name":"Kohl's",
    "wof:placetype":"venue"
},
  "geometry": {"coordinates":[-81.829275,30.197675],"type":"Point"}
}