{
  "type": "Feature",
  "properties": {
    "iso:country":"US",
    "sg:address":"3617 Skyline Blvd",
    "sg:city":"Cape Coral",
    "sg:classifiers":[
        {
            "category":"Restaurant",
            "type":"Food & Drink"
        }
    ],
    "sg:phone":"+1 239 542 3137",
    "sg:postcode":"33914",
    "sg:province":"FL",
    "sg:tags":[
        "eating"
    ],
    "wof:name":"Ice House Communications",
    "wof:placetype":"venue"
},
  "geometry": {"coordinates":[-81.990853,26.583871],"type":"Point"}
}