{
  "type": "Feature",
  "properties": {
    "addr:full":"6557 Leona St Jacksonville FL 32219",
    "addr:housenumber":"6557",
    "addr:postcode":"32219",
    "addr:street":"Leona St",
    "iso:country":"US",
    "sg:address":"6557 Leona St",
    "sg:city":"Jacksonville",
    "sg:classifiers":[
        {
            "category":"Organizations",
            "subcategory":"Religious Organization",
            "type":"Services"
        }
    ],
    "sg:phone":"+1 904 768 1077",
    "sg:postcode":"32219",
    "sg:province":"FL",
    "sg:tags":[
        "church"
    ],
    "wof:name":"Excellent Name Of Jesus Inc",
    "wof:placetype":"venue"
},
  "geometry": {"coordinates":[-81.750992,30.395007],"type":"Point"}
}