{
  "type": "Feature",
  "properties": {
    "iso:country":"US",
    "sg:address":"525 Pepper St NE",
    "sg:city":"Melbourne",
    "sg:classifiers":[
        {
            "category":"Education",
            "subcategory":"School",
            "type":"Public Place"
        }
    ],
    "sg:phone":"+1 321 676 3730",
    "sg:postcode":"32907",
    "sg:province":"FL",
    "wof:name":"Lockmar Elementary School",
    "wof:placetype":"venue"
},
  "geometry": {"coordinates":[-80.657929,28.024748],"type":"Point"}
}