{
  "type": "Feature",
  "properties": {
    "iso:country":"US",
    "sg:address":"4600 45th St",
    "sg:city":"Vero Beach",
    "sg:classifiers":[
        {
            "category":"Wholesale",
            "subcategory":"Auto Parts",
            "type":"Manufacturing & Wholesale Goods"
        }
    ],
    "sg:phone":"+1 772 567 2742",
    "sg:postcode":"32967",
    "sg:province":"FL",
    "sg:tags":[
        "automobile",
        "rebuilt"
    ],
    "wof:name":"Indian River Auto Salvage",
    "wof:placetype":"venue"
},
  "geometry": {"coordinates":[-80.43527899999999,27.67522],"type":"Point"}
}