{
  "type": "Feature",
  "properties": {
    "addr:full":"4504 Summer Cove Dr E Sarasota FL 34243",
    "addr:housenumber":"4504",
    "addr:postcode":"34243",
    "addr:street":"Summer Cove Dr E",
    "iso:country":"US",
    "sg:address":"4504 Summer Cove Dr E",
    "sg:city":"Sarasota",
    "sg:classifiers":[
        {
            "category":"Building & Trades",
            "subcategory":"Construction",
            "type":"Services"
        }
    ],
    "sg:phone":"+1 941 359 6739",
    "sg:postcode":"34243",
    "sg:province":"FL",
    "sg:tags":[
        "house"
    ],
    "wof:name":"Global Business Builders",
    "wof:placetype":"venue"
},
  "geometry": {"coordinates":[-82.504001,27.401223],"type":"Point"}
}