{
  "type": "Feature",
  "properties": {
    "iso:country":"US",
    "sg:address":"16085 SE 99th Ter",
    "sg:city":"Summerfield",
    "sg:classifiers":[
        {
            "category":"Retail",
            "subcategory":"Laundry & Dry Cleaning",
            "type":"Services"
        },
        {
            "category":"Building & Trades",
            "subcategory":"Cleaning & Sanitation",
            "type":"Services"
        }
    ],
    "sg:phone":"+1 352 307 8949",
    "sg:postcode":"34491",
    "sg:province":"FL",
    "sg:tags":[
        "cleaner",
        "house"
    ],
    "wof:name":"Peggy Leonard Cleaning Services, Inc.",
    "wof:placetype":"venue"
},
  "geometry": {"coordinates":[-81.98783400000001,28.988175],"type":"Point"}
}