{
  "type": "Feature",
  "properties": {
    "addr:full":"2600 Forest Glen Trl Marianna FL 32446",
    "addr:housenumber":"2600",
    "addr:postcode":"32446",
    "addr:street":"Forest Glen Trl",
    "iso:country":"US",
    "sg:address":"2600 Forest Glen Trl",
    "sg:city":"Marianna",
    "sg:classifiers":[
        {
            "category":"Health Services",
            "subcategory":"Nursing And Care Facility",
            "type":"Services"
        }
    ],
    "sg:phone":"+1 850 526 2000",
    "sg:postcode":"32446",
    "sg:province":"FL",
    "sg:tags":[
        "skilled"
    ],
    "wof:name":"Courtyard Mllpond Oprtions LLC",
    "wof:placetype":"venue"
},
  "geometry": {"coordinates":[-85.184692,30.751912],"type":"Point"}
}