{
  "type": "Feature",
  "properties": {
    "iso:country":"US",
    "sg:address":"711 NW 100th Way",
    "sg:city":"Pompano Beach",
    "sg:classifiers":[
        {
            "category":"Insurance",
            "subcategory":"Insurance Agent",
            "type":"Services"
        }
    ],
    "sg:phone":"+1 954 753 5228",
    "sg:postcode":"33071",
    "sg:province":"FL",
    "sg:tags":[
        "broker"
    ],
    "wof:name":"Gallagher Bassett Services Inc",
    "wof:placetype":"venue"
},
  "geometry": {"coordinates":[-80.259213,26.239045],"type":"Point"}
}