{
  "type": "Feature",
  "properties": {
    "iso:country":"US",
    "sg:address":"111 Margarita",
    "sg:city":"East Palatka",
    "sg:classifiers":[
        {
            "category":"Retail",
            "subcategory":"Repair Shop",
            "type":"Services"
        }
    ],
    "sg:phone":"+1 904 588 5521",
    "sg:postcode":"32131",
    "sg:province":"FL",
    "sg:tags":[
        "repairing",
        "lawn",
        "mower"
    ],
    "wof:name":"Reel Sharp",
    "wof:placetype":"venue"
},
  "geometry": {"coordinates":[-81.564117,29.701433],"type":"Point"}
}