{
  "type": "Feature",
  "properties": {
    "addr:full":"1299 Starkey Rd Largo FL 33771",
    "addr:housenumber":"1299",
    "addr:postcode":"33771",
    "addr:street":"Starkey Rd",
    "iso:country":"US",
    "sg:address":"1299 Starkey Rd",
    "sg:city":"Largo",
    "sg:classifiers":[
        {
            "category":"Retail",
            "subcategory":"Auto Repair",
            "type":"Services"
        }
    ],
    "sg:phone":"+1 727 531 1771",
    "sg:postcode":"33771",
    "sg:province":"FL",
    "sg:tags":[
        "general"
    ],
    "wof:name":"Jf Auto Repair",
    "wof:placetype":"venue"
},
  "geometry": {"coordinates":[-82.76234700000001,27.906905],"type":"Point"}
}