{
  "type": "Feature",
  "properties": {
    "iso:country":"US",
    "sg:address":"501 Brickell Key Dr # 600",
    "sg:city":"Miami",
    "sg:classifiers":[
        {
            "category":"Food & Beverages",
            "subcategory":"Liquor & Beverages",
            "type":"Retail Goods"
        }
    ],
    "sg:phone":"+1 305 371 3877",
    "sg:postcode":"33131",
    "sg:province":"FL",
    "sg:tags":[
        "bottler",
        "beverages-distributors"
    ],
    "wof:name":"Swire Coca-Cola U S A",
    "wof:placetype":"venue"
},
  "geometry": {"coordinates":[-80.185158,25.76643],"type":"Point"}
}