{
  "type": "Feature",
  "properties": {
    "iso:country":"US",
    "sg:address":"1810 Cobia Dr",
    "sg:city":"Vero Beach",
    "sg:classifiers":[
        {
            "category":"Real Estate",
            "subcategory":"Real Estate Agent",
            "type":"Services"
        }
    ],
    "sg:phone":"+1 772 770 9469",
    "sg:postcode":"32960",
    "sg:province":"FL",
    "wof:name":"Lila Bussey Real Estate",
    "wof:placetype":"venue"
},
  "geometry": {"coordinates":[-80.37755300000001,27.637695],"type":"Point"}
}