{
  "type": "Feature",
  "properties": {
    "addr:full":"5140 6th St Zephyrhills FL 33542",
    "addr:housenumber":"5140",
    "addr:postcode":"33542",
    "addr:street":"6Th St",
    "iso:country":"US",
    "sg:address":"5140 6th St",
    "sg:city":"Zephyrhills",
    "sg:classifiers":[
        {
            "category":"Organizations",
            "subcategory":"Non-profit Organization",
            "type":"Services"
        }
    ],
    "sg:phone":"+1 813 780 6822",
    "sg:postcode":"33542",
    "sg:province":"FL",
    "sg:tags":[
        "action",
        "agency",
        "community"
    ],
    "wof:name":"Neighborhood Care Ctr",
    "wof:placetype":"venue"
},
  "geometry": {"coordinates":[-82.182528,28.233022],"type":"Point"}
}