{
  "type": "Feature",
  "properties": {
    "addr:full":"7998 Mahan Dr Tallahassee FL 32309",
    "addr:housenumber":"7998",
    "addr:postcode":"32309",
    "addr:street":"Mahan Dr",
    "iso:country":"US",
    "sg:address":"7998 Mahan Dr",
    "sg:city":"Tallahassee",
    "sg:classifiers":[
        {
            "category":"Building & Trades",
            "subcategory":"Plumbing",
            "type":"Services"
        }
    ],
    "sg:phone":"+1 850 878 1234",
    "sg:postcode":"32309",
    "sg:province":"FL",
    "sg:tags":[
        "plumbing",
        "contractor"
    ],
    "wof:name":"Brill's Plumbing",
    "wof:placetype":"venue"
},
  "geometry": {"coordinates":[-84.158275,30.485294],"type":"Point"}
}