{
  "type": "Feature",
  "properties": {
    "addr:full":"2670 Evans Rd La Belle FL 33935",
    "addr:housenumber":"2670",
    "addr:postcode":"33935",
    "addr:street":"Evans Rd",
    "iso:country":"US",
    "sg:address":"2670 Evans Rd",
    "sg:city":"La Belle",
    "sg:classifiers":[
        {
            "category":"Farming",
            "subcategory":"Nursery",
            "type":"Manufacturing & Wholesale Goods"
        }
    ],
    "sg:phone":"+1 863 675 4051",
    "sg:postcode":"33935",
    "sg:province":"FL",
    "sg:tags":[
        "ornamental"
    ],
    "wof:name":"Superior Sod & Turf Co",
    "wof:placetype":"venue"
},
  "geometry": {"coordinates":[-81.3951,26.713623],"type":"Point"}
}