{
  "type": "Feature",
  "properties": {
    "iso:country":"US",
    "sg:address":"485 W Main St",
    "sg:city":"Pahokee",
    "sg:classifiers":[
        {
            "category":"Health Services",
            "subcategory":"Doctor",
            "type":"Services"
        }
    ],
    "sg:phone":"+1 561 924 2370",
    "sg:postcode":"33476",
    "sg:province":"FL",
    "sg:tags":[
        "medicine",
        "physician",
        "internal",
        "surgeons"
    ],
    "wof:name":"South Florida Medical Prof",
    "wof:placetype":"venue"
},
  "geometry": {"coordinates":[-80.669701,26.821773],"type":"Point"}
}