{
  "type": "Feature",
  "properties": {
    "iso:country":"US",
    "sg:address":"5760 10th Ave N",
    "sg:city":"Saint Petersburg",
    "sg:classifiers":[
        {
            "category":"Health Services",
            "subcategory":"Doctor",
            "type":"Services"
        }
    ],
    "sg:phone":"+1 727 384 1111",
    "sg:postcode":"33710",
    "sg:province":"FL",
    "sg:tags":[
        "medical"
    ],
    "wof:name":"Ronald Michota DPM PA",
    "wof:placetype":"venue"
},
  "geometry": {"coordinates":[-82.711189,27.781691],"type":"Point"}
}