{
  "type": "Feature",
  "properties": {
    "iso:country":"US",
    "sg:address":"4127 Tamiami Trl",
    "sg:city":"Venice",
    "sg:classifiers":[
        {
            "category":"Shopping",
            "subcategory":"Jewelry",
            "type":"Retail Goods"
        }
    ],
    "sg:phone":"+1 941 497 6331",
    "sg:postcode":"34293",
    "sg:province":"FL",
    "sg:tags":[
        "repair",
        "watch"
    ],
    "wof:name":"Classic Coins & Diamonds",
    "wof:placetype":"venue"
},
  "geometry": {"coordinates":[-82.397593,27.049906],"type":"Point"}
}