{
  "type": "Feature",
  "properties": {
    "addr:full":"3755 Thornhill Rd Winter Haven FL 33880",
    "addr:housenumber":"3755",
    "addr:postcode":"33880",
    "addr:street":"Thornhill Rd",
    "iso:country":"US",
    "sg:address":"3755 Thornhill Rd",
    "sg:city":"Winter Haven",
    "sg:classifiers":[
        {
            "category":"Building & Trades",
            "subcategory":"Construction",
            "type":"Services"
        }
    ],
    "sg:phone":"+1 863 299 3428",
    "sg:postcode":"33880",
    "sg:province":"FL",
    "sg:tags":[
        "roofing",
        "contractor"
    ],
    "wof:name":"S & S Roofing",
    "wof:placetype":"venue"
},
  "geometry": {"coordinates":[-81.804861,27.992731],"type":"Point"}
}