{
  "type": "Feature",
  "properties": {
    "iso:country":"US",
    "sg:address":"1705 S Federal Hwy",
    "sg:city":"Delray Beach",
    "sg:classifiers":[
        {
            "category":"Health Services",
            "subcategory":"Doctor",
            "type":"Services"
        }
    ],
    "sg:phone":"+1 561 265 1990",
    "sg:postcode":"33483",
    "sg:province":"FL",
    "sg:tags":[
        "physician",
        "surgeon"
    ],
    "sg:website":"www.healthsmartmd.com",
    "wof:name":"Healthsmart MD",
    "wof:placetype":"venue"
},
  "geometry": {"coordinates":[-80.07059,26.440671],"type":"Point"}
}