{
  "type": "Feature",
  "properties": {
    "iso:country":"US",
    "sg:address":"2302 James L Redman Pkwy",
    "sg:city":"Plant City",
    "sg:classifiers":[
        {
            "category":"Shopping",
            "subcategory":"Pharmacy",
            "type":"Retail Goods"
        }
    ],
    "sg:phone":"+1 813 752 3139",
    "sg:postcode":"33563",
    "sg:province":"FL",
    "wof:name":"Eckerd",
    "wof:placetype":"venue"
},
  "geometry": {"coordinates":[-82.121493,27.990052],"type":"Point"}
}