{
  "type": "Feature",
  "properties": {
    "addr:full":"1101 1st Ave N St Petersburg FL 33705",
    "addr:housenumber":"1101",
    "addr:postcode":"33705",
    "addr:street":"1St Ave N",
    "iso:country":"US",
    "sg:address":"1101 1st Ave N",
    "sg:city":"St Petersburg",
    "sg:classifiers":[
        {
            "category":"Manufacturing",
            "subcategory":"Printing",
            "type":"Manufacturing & Wholesale Goods"
        }
    ],
    "sg:phone":"+1 727 823 1965",
    "sg:postcode":"33705",
    "sg:province":"FL",
    "sg:tags":[
        "commercial",
        "offset"
    ],
    "sg:website":"www.bayprintonline.com",
    "wof:name":"Bayprint",
    "wof:placetype":"venue"
},
  "geometry": {"coordinates":[-82.65175499999999,27.772011],"type":"Point"}
}