{
  "type": "Feature",
  "properties": {
    "addr:full":"542 Horizon Dr Kenansville FL 34739",
    "addr:housenumber":"542",
    "addr:postcode":"34739",
    "addr:street":"Horizon Dr Kenansville",
    "iso:country":"US",
    "sg:address":"542 Horizon Dr",
    "sg:city":"Kenansville",
    "sg:classifiers":[
        {
            "category":"Organizations",
            "subcategory":"Religious Organization",
            "type":"Services"
        }
    ],
    "sg:phone":"+1 407 436 1637",
    "sg:postcode":"34739",
    "sg:province":"FL",
    "wof:name":"Hebron Primitive Baptst Church",
    "wof:placetype":"venue"
},
  "geometry": {"coordinates":[-81.045179,27.87025],"type":"Point"}
}