{
  "type": "Feature",
  "properties": {
    "iso:country":"US",
    "sg:address":"545 SW 5th St",
    "sg:city":"Homestead",
    "sg:classifiers":[
        {
            "category":"Personal",
            "type":"Services"
        }
    ],
    "sg:phone":"+1 305 726 3992",
    "sg:postcode":"33034",
    "sg:province":"FL",
    "sg:tags":[
        "parlor",
        "massage"
    ],
    "wof:name":"Cnd Magic Touch Massage",
    "wof:placetype":"venue"
},
  "geometry": {"coordinates":[-80.484499,25.442716],"type":"Point"}
}