{
  "type": "Feature",
  "properties": {
    "iso:country":"US",
    "sg:address":"7812 SW 34th Ter",
    "sg:city":"Miami",
    "sg:classifiers":[
        {
            "category":"Building & Trades",
            "subcategory":"Construction",
            "type":"Services"
        }
    ],
    "sg:phone":"+1 305 263 9369",
    "sg:postcode":"33155",
    "sg:province":"FL",
    "sg:tags":[
        "contractor"
    ],
    "wof:name":"Mag Construction",
    "wof:placetype":"venue"
},
  "geometry": {"coordinates":[-80.321859,25.738166],"type":"Point"}
}