{
  "type": "Feature",
  "properties": {
    "iso:country":"US",
    "sg:address":"12734 New Brittany Blvd",
    "sg:city":"Fort Myers",
    "sg:classifiers":[
        {
            "category":"Banks & Credit Unions",
            "subcategory":"Bank",
            "type":"Services"
        }
    ],
    "sg:phone":"+1 239 936 6868",
    "sg:postcode":"33907",
    "sg:province":"FL",
    "sg:tags":[
        "loan",
        "real estate"
    ],
    "wof:name":"Mortgage Broker Financial Corp",
    "wof:placetype":"venue"
},
  "geometry": {"coordinates":[-81.88086699999999,26.557583],"type":"Point"}
}