{
  "type": "Feature",
  "properties": {
    "iso:country":"US",
    "sg:address":"5430 Round Lake Rd",
    "sg:city":"Apopka",
    "sg:classifiers":[
        {
            "category":"Manufacturing",
            "subcategory":"Metals",
            "type":"Manufacturing & Wholesale Goods"
        },
        {
            "category":"Manufacturing",
            "subcategory":"Building Materials",
            "type":"Manufacturing & Wholesale Goods"
        }
    ],
    "sg:phone":"+1 407 886 5765",
    "sg:postcode":"32712",
    "sg:province":"FL",
    "sg:tags":[
        "product",
        "aluminum"
    ],
    "wof:name":"Mr B's Aluminum Inc",
    "wof:placetype":"venue"
},
  "geometry": {"coordinates":[-81.593281,28.763536],"type":"Point"}
}