{
  "type": "Feature",
  "properties": {
    "iso:country":"US",
    "sg:address":"15 NW 5th Ave",
    "sg:city":"Hallandale",
    "sg:classifiers":[
        {
            "category":"Social Services",
            "subcategory":"Child Care",
            "type":"Services"
        }
    ],
    "sg:phone":"+1 954 455 3036",
    "sg:postcode":"33009",
    "sg:province":"FL",
    "sg:tags":[
        "center",
        "day"
    ],
    "wof:name":"Hallandale Academy",
    "wof:placetype":"venue"
},
  "geometry": {"coordinates":[-80.153386,25.986117],"type":"Point"}
}