{
  "type": "Feature",
  "properties": {
    "addr:full":"84001 Overseas Hwy Islamorada FL 33036",
    "addr:housenumber":"84001",
    "addr:postcode":"33036",
    "addr:street":"Overseas Hwy",
    "iso:country":"US",
    "sg:address":"84001 Overseas Hwy",
    "sg:city":"Islamorada",
    "sg:classifiers":[
        {
            "category":"Shopping",
            "subcategory":"Clothing, Apparel, & Fashions",
            "type":"Retail Goods"
        }
    ],
    "sg:phone":"+1 305 664 4726",
    "sg:postcode":"33036",
    "sg:province":"FL",
    "wof:name":"Paradise Cove",
    "wof:placetype":"venue"
},
  "geometry": {"coordinates":[-80.606674,24.942807],"type":"Point"}
}