{
  "type": "Feature",
  "properties": {
    "addr:full":"1556 S French Ave Sanford FL 32771",
    "addr:housenumber":"1556",
    "addr:postcode":"32771",
    "addr:street":"S French Ave",
    "iso:country":"US",
    "sg:address":"1556 S French Ave",
    "sg:city":"Sanford",
    "sg:classifiers":[
        {
            "category":"Restaurant",
            "type":"Food & Drink"
        }
    ],
    "sg:menulink":"http://www.allmenus.com/fl/sanford/63577-great-wall/menu/",
    "sg:phone":"+1 407 323 6669",
    "sg:postcode":"32771",
    "sg:province":"FL",
    "sg:tags":[
        "asian",
        "chinese"
    ],
    "wof:name":"Great Wall",
    "wof:placetype":"venue"
},
  "geometry": {"coordinates":[-81.273087,28.79811],"type":"Point"}
}