{
  "type": "Feature",
  "properties": {
    "iso:country":"US",
    "sg:address":"147 Woodland Rd",
    "sg:city":"Lake Worth",
    "sg:classifiers":[
        {
            "category":"Professional",
            "type":"Services"
        }
    ],
    "sg:phone":"+1 561 433 9064",
    "sg:postcode":"33461",
    "sg:province":"FL",
    "wof:name":"Colinsa Inc",
    "wof:placetype":"venue"
},
  "geometry": {"coordinates":[-80.10516699999999,26.646875],"type":"Point"}
}