{
  "type": "Feature",
  "properties": {
    "iso:country":"US",
    "sg:address":"11419f W Palmetto Park Rd",
    "sg:city":"Boca Raton",
    "sg:classifiers":[
        {
            "category":"Ice Cream",
            "type":"Food & Drink"
        }
    ],
    "sg:menulink":"http://www.allmenus.com/fl/sunshine-parkway/172315-dairy-queen/menu/",
    "sg:phone":"+1 561 488 2459",
    "sg:postcode":"33428",
    "sg:province":"FL",
    "sg:tags":[
        "burger",
        "american"
    ],
    "wof:name":"Dairy Queen",
    "wof:placetype":"venue"
},
  "geometry": {"coordinates":[-80.22832200000001,26.348296],"type":"Point"}
}