{
  "type": "Feature",
  "properties": {
    "addr:full":"608 N Garden Ave Clearwater FL 33755",
    "addr:housenumber":"608",
    "addr:postcode":"33755",
    "addr:street":"N Garden Ave",
    "iso:country":"US",
    "sg:address":"608 N Garden Ave",
    "sg:city":"Clearwater",
    "sg:classifiers":[
        {
            "category":"Banks & Credit Unions",
            "subcategory":"Bank",
            "type":"Services"
        }
    ],
    "sg:phone":"+1 727 442 4155",
    "sg:postcode":"33755",
    "sg:province":"FL",
    "sg:tags":[
        "loan",
        "broker"
    ],
    "wof:name":"Cnhs Inc",
    "wof:placetype":"venue"
},
  "geometry": {"coordinates":[-82.798785,27.972526],"type":"Point"}
}