{
  "type": "Feature",
  "properties": {
    "addr:full":"112 N Main St Gainesville FL 32601",
    "addr:housenumber":"112",
    "addr:postcode":"32601",
    "addr:street":"N Main St",
    "iso:country":"US",
    "sg:address":"112 N Main St",
    "sg:city":"Gainesville",
    "sg:classifiers":[
        {
            "category":"Organizations",
            "subcategory":"Non-profit Organization",
            "type":"Services"
        }
    ],
    "sg:phone":"+1 352 378 9431",
    "sg:postcode":"32601",
    "sg:province":"FL",
    "sg:tags":[
        "social"
    ],
    "wof:name":"N A B I Biomedical Center",
    "wof:placetype":"venue"
},
  "geometry": {"coordinates":[-82.325075,29.653248],"type":"Point"}
}