{
  "type": "Feature",
  "properties": {
    "addr:full":"1477 N Fort Harrison Ave Clearwater FL 33755",
    "addr:housenumber":"1477",
    "addr:postcode":"33755",
    "addr:street":"N Fort Harrison Ave",
    "iso:country":"US",
    "sg:address":"1477 N Fort Harrison Ave",
    "sg:city":"Clearwater",
    "sg:classifiers":[
        {
            "category":"Travel",
            "subcategory":"Hotels & Motels",
            "type":"Entertainment"
        }
    ],
    "sg:phone":"+1 727 442 8993",
    "sg:postcode":"33755",
    "sg:province":"FL",
    "wof:name":"Delux Motel",
    "wof:placetype":"venue"
},
  "geometry": {"coordinates":[-82.79727699999999,27.979719],"type":"Point"}
}