{
  "type": "Feature",
  "properties": {
    "iso:country":"US",
    "sg:address":"4000 Summit Blvd",
    "sg:city":"Boynton Beach",
    "sg:classifiers":[
        {
            "category":"Real Estate",
            "subcategory":"Real Estate Operator",
            "type":"Services"
        }
    ],
    "sg:phone":"+1 561 732 0200",
    "sg:postcode":"33406",
    "sg:province":"FL",
    "sg:tags":[
        "condominium"
    ],
    "wof:name":"Hunters Run Golf & Raquet Club",
    "wof:placetype":"venue"
},
  "geometry": {"coordinates":[-80.10727799999999,26.66253],"type":"Point"}
}