{
  "type": "Feature",
  "properties": {
    "addr:full":"2510 W Copans Rd Pompano Beach FL 33069",
    "addr:housenumber":"2510",
    "addr:postcode":"33069",
    "addr:street":"W Copans Rd",
    "iso:country":"US",
    "sg:address":"2510 W Copans Rd",
    "sg:city":"Pompano Beach",
    "sg:classifiers":[
        {
            "category":"Home & Garden",
            "subcategory":"Building Materials",
            "type":"Retail Goods"
        },
        {
            "category":"Wholesale",
            "subcategory":"Electrical",
            "type":"Manufacturing & Wholesale Goods"
        }
    ],
    "sg:phone":"+1 954 979 1960",
    "sg:postcode":"33069",
    "sg:province":"FL",
    "sg:tags":[
        "equipment",
        "electric",
        "supply"
    ],
    "wof:name":"World Electric Supply/Sonepar",
    "wof:placetype":"venue"
},
  "geometry": {"coordinates":[-80.156649,26.260091],"type":"Point"}
}