{
  "type": "Feature",
  "properties": {
    "addr:full":"4142 Keats Dr Sarasota FL 34241",
    "addr:housenumber":"4142",
    "addr:postcode":"34241",
    "addr:street":"Keats Dr",
    "iso:country":"US",
    "sg:address":"4142 Keats Dr",
    "sg:city":"Sarasota",
    "sg:classifiers":[
        {
            "category":"Building & Trades",
            "subcategory":"Construction",
            "type":"Services"
        }
    ],
    "sg:phone":"+1 941 378 9023",
    "sg:postcode":"34241",
    "sg:province":"FL",
    "sg:tags":[
        "house"
    ],
    "wof:name":"New Homes Listing Service",
    "wof:placetype":"venue"
},
  "geometry": {"coordinates":[-82.415674,27.294469],"type":"Point"}
}