{
  "type": "Feature",
  "properties": {
    "addr:full":"1472 Skyline Dr Kissimmee FL 34744",
    "addr:housenumber":"1472",
    "addr:postcode":"34744",
    "addr:street":"Skyline Dr",
    "iso:country":"US",
    "sg:address":"1472 Skyline Dr",
    "sg:city":"Kissimmee",
    "sg:classifiers":[
        {
            "category":"Government",
            "subcategory":"Court House",
            "type":"Public Place"
        }
    ],
    "sg:phone":"+1 407 846 2994",
    "sg:postcode":"34744",
    "sg:province":"FL",
    "wof:name":"Osceola Teen Court Inc",
    "wof:placetype":"venue"
},
  "geometry": {"coordinates":[-81.384502,28.254854],"type":"Point"}
}