{
  "type": "Feature",
  "properties": {
    "iso:country":"US",
    "sg:address":"7560 Universal Blvd",
    "sg:city":"Orlando",
    "sg:classifiers":[
        {
            "category":"Fast Food",
            "type":"Food & Drink"
        },
        {
            "category":"Manufacturing",
            "subcategory":"Pet Food",
            "type":"Manufacturing & Wholesale Goods"
        },
        {
            "category":"Restaurant",
            "type":"Food & Drink"
        }
    ],
    "sg:phone":"+1 407 256 5589",
    "sg:postcode":"32819",
    "sg:province":"FL",
    "sg:tags":[
        "take",
        "pizza-wholesale",
        "italian",
        "manufacturer",
        "pizza"
    ],
    "wof:name":"Cornerstone Restaurant",
    "wof:placetype":"venue"
},
  "geometry": {"coordinates":[-81.464493,28.45437],"type":"Point"}
}