{
  "type": "Feature",
  "properties": {
    "addr:full":"12600 SW 120th St Miami FL 33186",
    "addr:housenumber":"12600",
    "addr:postcode":"33186",
    "addr:street":"Sw 120Th St",
    "iso:country":"US",
    "sg:address":"12600 SW 120th St",
    "sg:city":"Miami",
    "sg:classifiers":[
        {
            "category":"Health Services",
            "subcategory":"Health Practitioner",
            "type":"Services"
        },
        {
            "category":"Social Services",
            "subcategory":"Retirement Home",
            "type":"Services"
        },
        {
            "category":"Shopping",
            "subcategory":"Pharmacy",
            "type":"Retail Goods"
        }
    ],
    "sg:phone":"+1 305 255 7766",
    "sg:postcode":"33186",
    "sg:province":"FL",
    "sg:tags":[
        "equipment",
        "convalescent",
        "nursing",
        "care",
        "supply"
    ],
    "sg:website":"http://www.higiashomecare.com",
    "wof:name":"Higias Home Healthcare",
    "wof:placetype":"venue"
},
  "geometry": {"coordinates":[-80.397848,25.656782],"type":"Point"}
}