{
  "type": "Feature",
  "properties": {
    "iso:country":"US",
    "sg:address":"8007 Church St",
    "sg:city":"Sneads",
    "sg:classifiers":[
        {
            "category":"Social Services",
            "subcategory":"Child Care",
            "type":"Services"
        }
    ],
    "sg:phone":"+1 850 593 1243",
    "sg:postcode":"32460",
    "sg:province":"FL",
    "sg:tags":[
        "day"
    ],
    "wof:name":"Dees Erth Angels Lrng Academy",
    "wof:placetype":"venue"
},
  "geometry": {"coordinates":[-84.92820500000001,30.708515],"type":"Point"}
}