{
  "type": "Feature",
  "properties": {
    "iso:country":"US",
    "sg:address":"8050 Lake Underhill Rd",
    "sg:city":"Orlando",
    "sg:classifiers":[
        {
            "category":"Retail",
            "subcategory":"Auto Repair",
            "type":"Services"
        }
    ],
    "sg:phone":"+1 407 273 8901",
    "sg:postcode":"32825",
    "sg:province":"FL",
    "sg:tags":[
        "automobile",
        "lubrication"
    ],
    "wof:name":"Shell",
    "wof:placetype":"venue"
},
  "geometry": {"coordinates":[-81.272401,28.539206],"type":"Point"}
}