{
  "type": "Feature",
  "properties": {
    "iso:country":"US",
    "sg:address":"7050 Winkler Rd",
    "sg:city":"Fort Myers",
    "sg:classifiers":[
        {
            "category":"Real Estate",
            "subcategory":"Real Estate Agent",
            "type":"Services"
        }
    ],
    "sg:phone":"+1 239 437 4040",
    "sg:postcode":"33919",
    "sg:province":"FL",
    "wof:name":"Florida Dream Home Realty",
    "wof:placetype":"venue"
},
  "geometry": {"coordinates":[-81.899282,26.532195],"type":"Point"}
}