{
  "type": "Feature",
  "properties": {
    "iso:country":"US",
    "sg:address":"6955 NW 77th Ave Ste 404",
    "sg:city":"Miami",
    "sg:classifiers":[
        {
            "category":"Food Court",
            "type":"Food & Drink"
        },
        {
            "category":"Food & Beverages",
            "subcategory":"Groceries & Convenience Stores",
            "type":"Retail Goods"
        }
    ],
    "sg:phone":"+1 305 883 8333",
    "sg:postcode":"33166",
    "sg:province":"FL",
    "sg:tags":[
        "management"
    ],
    "wof:name":"Star International Food",
    "wof:placetype":"venue"
},
  "geometry": {"coordinates":[-80.321662,25.836701],"type":"Point"}
}