{
  "type": "Feature",
  "properties": {
    "addr:full":"2555 NW 49th Ave Lauderdale Lakes FL 33313",
    "addr:housenumber":"2555",
    "addr:postcode":"33313",
    "addr:street":"Nw 49Th Ave",
    "iso:country":"US",
    "sg:address":"2555 NW 49th Ave",
    "sg:city":"Lauderdale Lakes",
    "sg:classifiers":[
        {
            "category":"Retail",
            "subcategory":"Laundry & Dry Cleaning",
            "type":"Services"
        }
    ],
    "sg:phone":"+1 954 677 9937",
    "sg:postcode":"33313",
    "sg:province":"FL",
    "sg:tags":[
        "cleaners",
        "rug",
        "carpet"
    ],
    "wof:name":"Cleaning Service Inc Unique",
    "wof:placetype":"venue"
},
  "geometry": {"coordinates":[-80.217128,26.157802],"type":"Point"}
}