{
  "type": "Feature",
  "properties": {
    "iso:country":"US",
    "sg:address":"3056 Crawfordville Hwy",
    "sg:city":"Crawfordville",
    "sg:classifiers":[
        {
            "category":"Government",
            "subcategory":"Office",
            "type":"Public Place"
        }
    ],
    "sg:phone":"+1 850 926 0943",
    "sg:postcode":"32327",
    "sg:province":"FL",
    "wof:name":"Honorable Jill Walker",
    "wof:placetype":"venue"
},
  "geometry": {"coordinates":[-84.37511499999999,30.175968],"type":"Point"}
}