{
  "type": "Feature",
  "properties": {
    "iso:country":"US",
    "sg:address":"9911 Old Baymeadows Rd",
    "sg:city":"Jacksonville",
    "sg:classifiers":[
        {
            "category":"Shopping",
            "subcategory":"Books",
            "type":"Retail Goods"
        },
        {
            "category":"Education",
            "subcategory":"University",
            "type":"Public Place"
        }
    ],
    "sg:phone":"+1 904 997 2500",
    "sg:postcode":"32256",
    "sg:province":"FL",
    "sg:tags":[
        "college",
        "store"
    ],
    "wof:name":"Florida Community Clg Bkstr",
    "wof:placetype":"venue"
},
  "geometry": {"coordinates":[-81.552685,30.220803],"type":"Point"}
}