{
  "type": "Feature",
  "properties": {
    "iso:country":"US",
    "sg:address":"3028 Johnson St",
    "sg:city":"Hollywood",
    "sg:classifiers":[
        {
            "category":"Food & Beverages",
            "subcategory":"Groceries & Convenience Stores",
            "type":"Retail Goods"
        }
    ],
    "sg:phone":"+1 954 989 7622",
    "sg:postcode":"33021",
    "sg:province":"FL",
    "wof:name":"Jim's Drive Thru",
    "wof:placetype":"venue"
},
  "geometry": {"coordinates":[-80.168649,26.0184],"type":"Point"}
}