{
  "type": "Feature",
  "properties": {
    "iso:country":"US",
    "sg:address":"115 W Rich Ave",
    "sg:city":"Deland",
    "sg:classifiers":[
        {
            "category":"Shopping",
            "subcategory":"Crafts & Fabrics",
            "type":"Retail Goods"
        }
    ],
    "sg:phone":"+1 386 734 8782",
    "sg:postcode":"32720",
    "sg:province":"FL",
    "sg:tags":[
        "store"
    ],
    "sg:website":"www.quiltshopofdeland.com",
    "wof:name":"Quilt Shop of Deland",
    "wof:placetype":"venue"
},
  "geometry": {"coordinates":[-81.30416099999999,29.030165],"type":"Point"}
}