{
  "type": "Feature",
  "properties": {
    "iso:country":"US",
    "sg:address":"10680 NW 25th St",
    "sg:city":"Doral",
    "sg:classifiers":[
        {
            "category":"Professional",
            "subcategory":"Lawyer & Legal Services",
            "type":"Services"
        }
    ],
    "sg:phone":"+1 305 717 3511",
    "sg:postcode":"33172",
    "sg:province":"FL",
    "wof:name":"Bober Joseph E ESQ PA",
    "wof:placetype":"venue"
},
  "geometry": {"coordinates":[-80.368708,25.796694],"type":"Point"}
}