{
  "type": "Feature",
  "properties": {
    "iso:country":"US",
    "sg:address":"4500 Pga Blvd",
    "sg:city":"Palm Beach Gardens",
    "sg:classifiers":[
        {
            "category":"Building & Trades",
            "subcategory":"Construction",
            "type":"Services"
        }
    ],
    "sg:phone":"+1 561 627 2112",
    "sg:postcode":"33418",
    "sg:province":"FL",
    "sg:tags":[
        "house",
        "contractor",
        "general",
        "new"
    ],
    "wof:name":"Divosta Building Corporation",
    "wof:placetype":"venue"
},
  "geometry": {"coordinates":[-80.107005,26.838281],"type":"Point"}
}