{
  "type": "Feature",
  "properties": {
    "iso:country":"US",
    "sg:address":"6100 NW 44th St",
    "sg:city":"Fort Lauderdale",
    "sg:classifiers":[
        {
            "category":"Building & Trades",
            "subcategory":"Construction",
            "type":"Services"
        }
    ],
    "sg:phone":"+1 954 733 6798",
    "sg:postcode":"33319",
    "sg:province":"FL",
    "sg:tags":[
        "real estate",
        "developer"
    ],
    "wof:name":"Courtney Case Inc",
    "wof:placetype":"venue"
},
  "geometry": {"coordinates":[-80.23500199999999,26.179277],"type":"Point"}
}