{
  "type": "Feature",
  "properties": {
    "addr:full":"1109 Briarwood Rd Brandon FL 33511",
    "addr:housenumber":"1109",
    "addr:postcode":"33511",
    "addr:street":"Briarwood Rd",
    "iso:country":"US",
    "sg:address":"1109 Briarwood Rd",
    "sg:city":"Brandon",
    "sg:classifiers":[
        {
            "category":"Wholesale",
            "subcategory":"Electrical",
            "type":"Manufacturing & Wholesale Goods"
        }
    ],
    "sg:phone":"+1 813 662 5028",
    "sg:postcode":"33511",
    "sg:province":"FL",
    "sg:tags":[
        "electronic"
    ],
    "wof:name":"Atlas Recording & Mastering",
    "wof:placetype":"venue"
},
  "geometry": {"coordinates":[-82.26640999999999,27.933702],"type":"Point"}
}