{
  "type": "Feature",
  "properties": {
    "addr:full":"4125 NW 34 Dr Gainesville FL 32605",
    "addr:housenumber":"4125",
    "addr:postcode":"32605",
    "addr:street":"Nw 34 Dr",
    "iso:country":"US",
    "sg:address":"4125 NW 34 Dr",
    "sg:city":"Gainesville",
    "sg:classifiers":[
        {
            "category":"Shopping",
            "subcategory":"Bicycles & Sporting Goods",
            "type":"Retail Goods"
        }
    ],
    "sg:phone":"+1 352 332 2800",
    "sg:postcode":"32605",
    "sg:province":"FL",
    "wof:name":"Gator E-Go's",
    "wof:placetype":"venue"
},
  "geometry": {"coordinates":[-82.373631,29.69189],"type":"Point"}
}