{
  "type": "Feature",
  "properties": {
    "iso:country":"US",
    "sg:address":"10720 Kim Ln",
    "sg:city":"Hudson",
    "sg:classifiers":[
        {
            "category":"Home & Garden",
            "subcategory":"Furniture",
            "type":"Retail Goods"
        }
    ],
    "sg:phone":"+1 727 657 9133",
    "sg:postcode":"34669",
    "sg:province":"FL",
    "sg:tags":[
        "store"
    ],
    "wof:name":"Leslie Labine Furniture Refnsh",
    "wof:placetype":"venue"
},
  "geometry": {"coordinates":[-82.639471,28.341336],"type":"Point"}
}