{
  "type": "Feature",
  "properties": {
    "addr:full":"4065 60th Ave NE Naples FL 34120",
    "addr:housenumber":"4065",
    "addr:postcode":"34120",
    "addr:street":"60Th Ave Ne",
    "iso:country":"US",
    "sg:address":"4065 60th Ave NE",
    "sg:city":"Naples",
    "sg:classifiers":[
        {
            "category":"Retail",
            "subcategory":"Repair Shop",
            "type":"Services"
        }
    ],
    "sg:phone":"+1 239 354 3307",
    "sg:postcode":"34120",
    "sg:province":"FL",
    "sg:tags":[
        "water",
        "equipment",
        "softening"
    ],
    "wof:name":"Express Water Conditioning Sys",
    "wof:placetype":"venue"
},
  "geometry": {"coordinates":[-81.536252,26.341847],"type":"Point"}
}