{
  "type": "Feature",
  "properties": {
    "iso:country":"US",
    "sg:address":"6736 2nd Avenue Cir W",
    "sg:city":"Bradenton",
    "sg:classifiers":[
        {
            "category":"Real Estate",
            "subcategory":"Real Estate Agent",
            "type":"Services"
        }
    ],
    "sg:phone":"+1 941 795 2575",
    "sg:postcode":"34209",
    "sg:province":"FL",
    "wof:name":"Seus Neviv",
    "wof:placetype":"venue"
},
  "geometry": {"coordinates":[-82.629783,27.499183],"type":"Point"}
}