{
  "type": "Feature",
  "properties": {
    "iso:country":"US",
    "sg:address":"2204 N University Dr",
    "sg:city":"Coral Springs",
    "sg:classifiers":[
        {
            "category":"Utilities",
            "subcategory":"Mobile Phone",
            "type":"Services"
        }
    ],
    "sg:phone":"+1 954 753 4422",
    "sg:postcode":"33071",
    "sg:province":"FL",
    "sg:tags":[
        "telephone",
        "cellular"
    ],
    "wof:name":"Cingular Wireless",
    "wof:placetype":"venue"
},
  "geometry": {"coordinates":[-80.249836,26.259245],"type":"Point"}
}