{
  "type": "Feature",
  "properties": {
    "addr:full":"714 Dakota Ave Saint Cloud FL 34769",
    "addr:housenumber":"714",
    "addr:postcode":"34769",
    "addr:street":"Dakota Ave",
    "iso:country":"US",
    "sg:address":"714 Dakota Ave",
    "sg:city":"Saint Cloud",
    "sg:classifiers":[
        {
            "category":"Building & Trades",
            "subcategory":"Construction",
            "type":"Services"
        }
    ],
    "sg:phone":"+1 407 729 6419",
    "sg:postcode":"34769",
    "sg:province":"FL",
    "sg:tags":[
        "tile",
        "renovation",
        "pool",
        "swimming"
    ],
    "wof:name":"Caledonian Tile & Renovations",
    "wof:placetype":"venue"
},
  "geometry": {"coordinates":[-81.293644,28.250778],"type":"Point"}
}