{
  "type": "Feature",
  "properties": {
    "iso:country":"US",
    "sg:address":"2446 Parkstream Ave",
    "sg:city":"Clearwater",
    "sg:classifiers":[
        {
            "category":"Real Estate",
            "subcategory":"Real Estate Agent",
            "type":"Services"
        }
    ],
    "sg:phone":"+1 727 725 7424",
    "sg:postcode":"33759",
    "sg:province":"FL",
    "wof:name":"REM Real Estate Services",
    "wof:placetype":"venue"
},
  "geometry": {"coordinates":[-82.716802,28.010988],"type":"Point"}
}