{
  "type": "Feature",
  "properties": {
    "iso:country":"US",
    "sg:address":"7609 Marechal Ave",
    "sg:city":"Port Richey",
    "sg:classifiers":[
        {
            "category":"Professional",
            "subcategory":"Lawyer & Legal Services",
            "type":"Services"
        }
    ],
    "sg:phone":"+1 727 868 8854",
    "sg:postcode":"34668",
    "sg:province":"FL",
    "wof:name":"Asap Paralegal Svc",
    "wof:placetype":"venue"
},
  "geometry": {"coordinates":[-82.688849,28.311292],"type":"Point"}
}