{
  "type": "Feature",
  "properties": {
    "iso:country":"US",
    "sg:address":"1808 Main St",
    "sg:city":"Dunedin",
    "sg:classifiers":[
        {
            "category":"Manufacturing",
            "subcategory":"Signs",
            "type":"Manufacturing & Wholesale Goods"
        }
    ],
    "sg:phone":"+1 727 736 3555",
    "sg:postcode":"34698",
    "sg:province":"FL",
    "wof:name":"Sign Source",
    "wof:placetype":"venue"
},
  "geometry": {"coordinates":[-82.759109,28.019456],"type":"Point"}
}