{
  "type": "Feature",
  "properties": {
    "addr:full":"1808 Main St Dunedin FL 34698",
    "addr:housenumber":"1808",
    "addr:postcode":"34698",
    "addr:street":"Main St",
    "iso:country":"US",
    "sg:address":"1808 Main St",
    "sg:city":"Dunedin",
    "sg:classifiers":[
        {
            "category":"Manufacturing",
            "subcategory":"Signs",
            "type":"Manufacturing & Wholesale Goods"
        }
    ],
    "sg:phone":"+1 727 736 3555",
    "sg:postcode":"34698",
    "sg:province":"FL",
    "wof:name":"Sign Source",
    "wof:placetype":"venue"
},
  "geometry": {"coordinates":[-82.759109,28.019456],"type":"Point"}
}