{
  "type": "Feature",
  "properties": {
    "addr:full":"5001 E Tangelo Ln Inverness FL 34453",
    "addr:housenumber":"5001",
    "addr:postcode":"34453",
    "addr:street":"E Tangelo Ln",
    "iso:country":"US",
    "sg:address":"5001 E Tangelo Ln",
    "sg:city":"Inverness",
    "sg:classifiers":[
        {
            "category":"Autos & Motor Vehicles",
            "subcategory":"Automobile Sales",
            "type":"Retail Goods"
        }
    ],
    "sg:phone":"+1 352 341 3500",
    "sg:postcode":"34453",
    "sg:province":"FL",
    "sg:tags":[
        "car",
        "dealer"
    ],
    "wof:name":"J B's Wholesale",
    "wof:placetype":"venue"
},
  "geometry": {"coordinates":[-82.344134,28.861508],"type":"Point"}
}