{
  "type": "Feature",
  "properties": {
    "addr:full":"301 NE 15th St Miami FL 33132",
    "addr:housenumber":"301",
    "addr:postcode":"33132",
    "addr:street":"Ne 15Th St",
    "iso:country":"US",
    "sg:address":"301 NE 15th St",
    "sg:city":"Miami",
    "sg:classifiers":[
        {
            "category":"Shopping",
            "subcategory":"Hobbies, Toys, & Games",
            "type":"Retail Goods"
        }
    ],
    "sg:phone":"+1 305 597 1500",
    "sg:postcode":"33132",
    "sg:province":"FL",
    "sg:tags":[
        "supply"
    ],
    "wof:name":"Fidelity Electronics Intl",
    "wof:placetype":"venue"
},
  "geometry": {"coordinates":[-80.18722699999999,25.789576],"type":"Point"}
}