{
  "type": "Feature",
  "properties": {
    "iso:country":"US",
    "sg:address":"217 Chestnut Ridge St",
    "sg:city":"Winter Springs",
    "sg:classifiers":[
        {
            "category":"Professional",
            "subcategory":"Computer Services",
            "type":"Services"
        }
    ],
    "sg:phone":"+1 407 977 6799",
    "sg:postcode":"32708",
    "sg:province":"FL",
    "sg:tags":[
        "consultant",
        "designer",
        "datum",
        "system"
    ],
    "wof:name":"Datamax Corp",
    "wof:placetype":"venue"
},
  "geometry": {"coordinates":[-81.248363,28.667968],"type":"Point"}
}