{
  "type": "Feature",
  "properties": {
    "addr:full":"400 NE 12th Ave Hallandale FL 33009",
    "addr:housenumber":"400",
    "addr:postcode":"33009",
    "addr:street":"Ne 12Th Ave",
    "iso:country":"US",
    "sg:address":"400 NE 12th Ave",
    "sg:city":"Hallandale",
    "sg:classifiers":[
        {
            "category":"Banks & Credit Unions",
            "subcategory":"Financial Services",
            "type":"Services"
        }
    ],
    "sg:phone":"+1 954 455 7707",
    "sg:postcode":"33009",
    "sg:province":"FL",
    "sg:tags":[
        "trust",
        "investment",
        "real estate"
    ],
    "wof:name":"Miriam Gaudreault",
    "wof:placetype":"venue"
},
  "geometry": {"coordinates":[-80.136437,25.991035],"type":"Point"}
}