{
  "type": "Feature",
  "properties": {
    "iso:country":"US",
    "sg:address":"1064 N Tamiami Trl",
    "sg:city":"Fort Myers",
    "sg:classifiers":[
        {
            "category":"Building & Trades",
            "subcategory":"Construction",
            "type":"Services"
        }
    ],
    "sg:phone":"+1 239 656 8231",
    "sg:postcode":"33903",
    "sg:province":"FL",
    "sg:tags":[
        "hanging",
        "contractor"
    ],
    "wof:name":"Wright Painters",
    "wof:placetype":"venue"
},
  "geometry": {"coordinates":[-81.878074,26.664145],"type":"Point"}
}