{
  "type": "Feature",
  "properties": {
    "iso:country":"US",
    "sg:address":"6101 Crill Ave",
    "sg:city":"Palatka",
    "sg:classifiers":[
        {
            "category":"Health Services",
            "subcategory":"Doctor",
            "type":"Services"
        }
    ],
    "sg:phone":"+1 386 326 1225",
    "sg:postcode":"32177",
    "sg:province":"FL",
    "sg:tags":[
        "clinic"
    ],
    "wof:name":"St Johns Family Medical Care",
    "wof:placetype":"venue"
},
  "geometry": {"coordinates":[-81.68664,29.64109],"type":"Point"}
}