{
  "type": "Feature",
  "properties": {
    "iso:country":"US",
    "sg:address":"5104 N Orange Blossom Trl",
    "sg:city":"Orlando",
    "sg:classifiers":[
        {
            "category":"Manufacturing",
            "subcategory":"Metals",
            "type":"Manufacturing & Wholesale Goods"
        }
    ],
    "sg:phone":"+1 407 290 5300",
    "sg:postcode":"32810",
    "sg:province":"FL",
    "sg:tags":[
        "steel",
        "joist"
    ],
    "wof:name":"Quincy Joist Co",
    "wof:placetype":"venue"
},
  "geometry": {"coordinates":[-81.42148299999999,28.605373],"type":"Point"}
}