{
  "type": "Feature",
  "properties": {
    "iso:country":"US",
    "sg:address":"8410 W Flagler St Ste 107",
    "sg:city":"Miami",
    "sg:classifiers":[
        {
            "category":"Shopping",
            "subcategory":"Beauty & Cosmetics",
            "type":"Retail Goods"
        },
        {
            "category":"Shopping",
            "subcategory":"Bridal",
            "type":"Retail Goods"
        }
    ],
    "sg:phone":"+1 305 553 1162",
    "sg:postcode":"33144",
    "sg:province":"FL",
    "sg:tags":[
        "perfume",
        "salons-equipment",
        "supply"
    ],
    "wof:name":"Pily Di Maffo",
    "wof:placetype":"venue"
},
  "geometry": {"coordinates":[-80.332397,25.769501],"type":"Point"}
}