{
  "type": "Feature",
  "properties": {
    "iso:country":"US",
    "sg:address":"219 Avocado Dr",
    "sg:city":"Fort Myers",
    "sg:classifiers":[
        {
            "category":"Organizations",
            "subcategory":"Religious Organization",
            "type":"Services"
        }
    ],
    "sg:phone":"+1 239 466 1781",
    "sg:postcode":"33908",
    "sg:province":"FL",
    "sg:tags":[
        "clergy"
    ],
    "wof:name":"Laurent O Patenaude",
    "wof:placetype":"venue"
},
  "geometry": {"coordinates":[-81.962461,26.499561],"type":"Point"}
}