{
  "type": "Feature",
  "properties": {
    "addr:full":"3901 Ibis Dr Orlando FL 32803",
    "addr:housenumber":"3901",
    "addr:postcode":"32803",
    "addr:street":"Ibis Dr",
    "iso:country":"US",
    "sg:address":"3901 Ibis Dr",
    "sg:city":"Orlando",
    "sg:classifiers":[
        {
            "category":"Professional",
            "subcategory":"Management & Consulting",
            "type":"Services"
        }
    ],
    "sg:phone":"+1 407 896 7880",
    "sg:postcode":"32803",
    "sg:province":"FL",
    "sg:tags":[
        "business"
    ],
    "wof:name":"Buttar Consulting",
    "wof:placetype":"venue"
},
  "geometry": {"coordinates":[-81.336637,28.56218],"type":"Point"}
}