{
  "type": "Feature",
  "properties": {
    "iso:country":"US",
    "sg:address":"933 SE Central Pkwy",
    "sg:city":"Stuart",
    "sg:classifiers":[
        {
            "category":"Professional",
            "subcategory":"Printing & Photocopies",
            "type":"Services"
        },
        {
            "category":"Wholesale",
            "subcategory":"Non-durable Goods",
            "type":"Manufacturing & Wholesale Goods"
        }
    ],
    "sg:phone":"+1 772 286 6474",
    "sg:postcode":"34994",
    "sg:province":"FL",
    "sg:tags":[
        "photofinishing",
        "blueprinting",
        "laboratory"
    ],
    "wof:name":"Engineering Supply Co Fla Inc",
    "wof:placetype":"venue"
},
  "geometry": {"coordinates":[-80.240098,27.180311],"type":"Point"}
}