{
  "type": "Feature",
  "properties": {
    "addr:full":"770 Ponce de Leon Blvd Miami FL 33134",
    "addr:housenumber":"770",
    "addr:postcode":"33134",
    "addr:street":"Ponce De Leon Blvd",
    "iso:country":"US",
    "sg:address":"770 Ponce de Leon Blvd",
    "sg:city":"Miami",
    "sg:classifiers":[
        {
            "category":"Professional",
            "subcategory":"Lawyer & Legal Services",
            "type":"Services"
        }
    ],
    "sg:phone":"+1 305 446 9838",
    "sg:postcode":"33134",
    "sg:province":"FL",
    "wof:name":"Pemsler and Grindal PA",
    "wof:placetype":"venue"
},
  "geometry": {"coordinates":[-80.25906999999999,25.764581],"type":"Point"}
}