{
  "type": "Feature",
  "properties": {
    "iso:country":"US",
    "sg:address":"6383 10th Ave N",
    "sg:city":"Greenacres",
    "sg:classifiers":[
        {
            "category":"Real Estate",
            "subcategory":"Real Estate Agent",
            "type":"Services"
        }
    ],
    "sg:phone":"+1 561 433 0113",
    "sg:postcode":"33463",
    "sg:province":"FL",
    "wof:name":"Suburban Realty-The Palm Beach",
    "wof:placetype":"venue"
},
  "geometry": {"coordinates":[-80.145438,26.631957],"type":"Point"}
}