{
  "type": "Feature",
  "properties": {
    "addr:full":"101 Dixie Dr Haines City FL 33844",
    "addr:housenumber":"101",
    "addr:postcode":"33844",
    "addr:street":"Dixie Dr",
    "iso:country":"US",
    "sg:address":"101 Dixie Dr",
    "sg:city":"Haines City",
    "sg:classifiers":[
        {
            "category":"Health Services",
            "subcategory":"Doctor",
            "type":"Services"
        }
    ],
    "sg:phone":"+1 863 421 1190",
    "sg:postcode":"33844",
    "sg:province":"FL",
    "sg:tags":[
        "medical"
    ],
    "wof:name":"Jacobo N Lama MD PA",
    "wof:placetype":"venue"
},
  "geometry": {"coordinates":[-81.662847,28.105017],"type":"Point"}
}