{
  "type": "Feature",
  "properties": {
    "addr:full":"11927 SW 31 Ter Webster FL 33597",
    "addr:housenumber":"11927;31 ter",
    "addr:postcode":"33597",
    "addr:street":"Sw;Webster",
    "iso:country":"US",
    "sg:address":"11927 SW 31 Ter",
    "sg:city":"Webster",
    "sg:classifiers":[
        {
            "category":"Manufacturing",
            "subcategory":"Tools & Machinery",
            "type":"Manufacturing & Wholesale Goods"
        }
    ],
    "sg:phone":"+1 352 793 4477",
    "sg:postcode":"33597",
    "sg:province":"FL",
    "sg:tags":[
        "limb",
        "artificial"
    ],
    "sg:website":"www.prostheticsresearch.com",
    "wof:name":"Prosthetics Research Specs",
    "wof:placetype":"venue"
},
  "geometry": {"coordinates":[-82.154876,28.582227],"type":"Point"}
}