{
  "type": "Feature",
  "properties": {
    "iso:country":"US",
    "sg:address":"400 N Loxahatchee Dr",
    "sg:city":"Jupiter",
    "sg:classifiers":[
        {
            "category":"Building & Trades",
            "subcategory":"Plumbing",
            "type":"Services"
        }
    ],
    "sg:phone":"+1 561 747 0277",
    "sg:postcode":"33458",
    "sg:province":"FL",
    "sg:tags":[
        "install",
        "septic",
        "system"
    ],
    "wof:name":"Total Septic Services",
    "wof:placetype":"venue"
},
  "geometry": {"coordinates":[-80.09954399999999,26.93966],"type":"Point"}
}