{
  "type": "Feature",
  "properties": {
    "iso:country":"US",
    "sg:address":"607 Colonia Ln E",
    "sg:city":"Nokomis",
    "sg:classifiers":[
        {
            "category":"Freight",
            "type":"Transportation"
        },
        {
            "category":"Professional",
            "subcategory":"Business Services",
            "type":"Services"
        }
    ],
    "sg:phone":"+1 941 484 3608",
    "sg:postcode":"34275",
    "sg:province":"FL",
    "sg:tags":[
        "barricade",
        "general"
    ],
    "wof:name":"Sentry Barricades Inc",
    "wof:placetype":"venue"
},
  "geometry": {"coordinates":[-82.44032300000001,27.119359],"type":"Point"}
}