{
  "type": "Feature",
  "properties": {
    "iso:country":"US",
    "sg:address":"536 Indian Lilac Rd",
    "sg:city":"Vero Beach",
    "sg:classifiers":[
        {
            "category":"Professional",
            "subcategory":"Business Services",
            "type":"Services"
        }
    ],
    "sg:phone":"+1 772 231 1551",
    "sg:postcode":"32963",
    "sg:province":"FL",
    "sg:tags":[
        "interior",
        "consultant",
        "design",
        "decorator"
    ],
    "wof:name":"Island Interiors",
    "wof:placetype":"venue"
},
  "geometry": {"coordinates":[-80.361926,27.661314],"type":"Point"}
}