{
  "type": "Feature",
  "properties": {
    "addr:full":"10718 NW 11th St Pembroke Pines FL 33026",
    "addr:housenumber":"10718",
    "addr:postcode":"33026",
    "addr:street":"Nw 11Th St",
    "iso:country":"US",
    "sg:address":"10718 NW 11th St",
    "sg:city":"Pembroke Pines",
    "sg:classifiers":[
        {
            "category":"Organizations",
            "subcategory":"Religious Organization",
            "type":"Services"
        }
    ],
    "sg:phone":"+1 954 987 8310",
    "sg:postcode":"33026",
    "sg:province":"FL",
    "sg:tags":[
        "church"
    ],
    "wof:name":"El Aposento De LA Gracia",
    "wof:placetype":"venue"
},
  "geometry": {"coordinates":[-80.291538,26.014674],"type":"Point"}
}