{
  "type": "Feature",
  "properties": {
    "addr:full":"5020 Cleveland Rd Jacksonville FL 32209",
    "addr:housenumber":"5020",
    "addr:postcode":"32209",
    "addr:street":"Cleveland Rd",
    "iso:country":"US",
    "sg:address":"5020 Cleveland Rd",
    "sg:city":"Jacksonville",
    "sg:classifiers":[
        {
            "category":"Real Estate",
            "subcategory":"Real Estate Operator",
            "type":"Services"
        }
    ],
    "sg:phone":"+1 904 765 0572",
    "sg:postcode":"32209",
    "sg:province":"FL",
    "sg:tags":[
        "apartment"
    ],
    "wof:name":"Cleveland Arms Apartments",
    "wof:placetype":"venue"
},
  "geometry": {"coordinates":[-81.70604899999999,30.364095],"type":"Point"}
}