{
  "type": "Feature",
  "properties": {
    "addr:full":"627 SW 27 Ave Miami FL 33135",
    "addr:housenumber":"627",
    "addr:postcode":"33135",
    "addr:street":"Sw 27 Ave",
    "iso:country":"US",
    "sg:address":"627 SW 27 Ave",
    "sg:city":"Miami",
    "sg:classifiers":[
        {
            "category":"Education",
            "subcategory":"University",
            "type":"Public Place"
        }
    ],
    "sg:phone":"+1 305 237 6000",
    "sg:postcode":"33135",
    "sg:province":"FL",
    "sg:tags":[
        "college"
    ],
    "sg:website":"www.mdc.edu/iac/",
    "wof:name":"Miami Dade Community College InterAmerican Campus",
    "wof:placetype":"venue"
},
  "geometry": {"coordinates":[-80.237787,25.766841],"type":"Point"}
}