{
  "type": "Feature",
  "properties": {
    "addr:full":"1498 State Road 436 Casselberry FL 32707",
    "addr:housenumber":"1498",
    "addr:postcode":"32707",
    "addr:street":"State Road 436",
    "iso:country":"US",
    "sg:address":"1498 State Road 436",
    "sg:city":"Casselberry",
    "sg:classifiers":[
        {
            "category":"Food & Beverages",
            "subcategory":"Groceries & Convenience Stores",
            "type":"Retail Goods"
        }
    ],
    "sg:phone":"+1 407 657 0659",
    "sg:postcode":"32707",
    "sg:province":"FL",
    "wof:name":"7-Eleven",
    "wof:placetype":"venue"
},
  "geometry": {"coordinates":[-81.31553700000001,28.625365],"type":"Point"}
}