{
  "type": "Feature",
  "properties": {
    "iso:country":"US",
    "sg:address":"9703 San Jose Blvd",
    "sg:city":"Jacksonville",
    "sg:classifiers":[
        {
            "category":"Restaurant",
            "type":"Food & Drink"
        }
    ],
    "sg:phone":"+1 904 262 1900",
    "sg:postcode":"32257",
    "sg:province":"FL",
    "sg:tags":[
        "eating"
    ],
    "wof:name":"MI Toro",
    "wof:placetype":"venue"
},
  "geometry": {"coordinates":[-81.62015700000001,30.198912],"type":"Point"}
}