{
  "type": "Feature",
  "properties": {
    "iso:country":"US",
    "sg:address":"206 S Beaumont Ave",
    "sg:city":"Kissimmee",
    "sg:classifiers":[
        {
            "category":"Professional",
            "subcategory":"Lawyer & Legal Services",
            "type":"Services"
        }
    ],
    "sg:phone":"+1 407 847 6259",
    "sg:postcode":"34741",
    "sg:province":"FL",
    "sg:tags":[
        "attorney"
    ],
    "wof:name":"Richard N Kelley",
    "wof:placetype":"venue"
},
  "geometry": {"coordinates":[-81.41005800000001,28.289055],"type":"Point"}
}