{
  "type": "Feature",
  "properties": {
    "addr:full":"124 Barefoot Cove Lantana FL 33462",
    "addr:housenumber":"124",
    "addr:postcode":"33462",
    "addr:street":"Barefoot Cove",
    "iso:country":"US",
    "sg:address":"124 Barefoot Cove",
    "sg:city":"Lantana",
    "sg:classifiers":[
        {
            "category":"Wholesale",
            "subcategory":"Toys & Hobbies",
            "type":"Manufacturing & Wholesale Goods"
        }
    ],
    "sg:phone":"+1 561 586 6012",
    "sg:postcode":"33462",
    "sg:province":"FL",
    "sg:tags":[
        "wholesaler"
    ],
    "wof:name":"Marlin Sales & Trading",
    "wof:placetype":"venue"
},
  "geometry": {"coordinates":[-80.051524,26.570115],"type":"Point"}
}