{
  "type": "Feature",
  "properties": {
    "iso:country":"US",
    "sg:address":"110 NW 13th St",
    "sg:city":"Gainesville",
    "sg:classifiers":[
        {
            "category":"Personal",
            "subcategory":"Beauty Salon",
            "type":"Services"
        }
    ],
    "sg:phone":"+1 352 371 1855",
    "sg:postcode":"32601",
    "sg:province":"FL",
    "sg:tags":[
        "shop"
    ],
    "wof:name":"First Impressions",
    "wof:placetype":"venue"
},
  "geometry": {"coordinates":[-82.33931,29.653309],"type":"Point"}
}