{
  "type": "Feature",
  "properties": {
    "iso:country":"US",
    "sg:address":"1855 NE 214th Ter",
    "sg:city":"Miami",
    "sg:classifiers":[
        {
            "category":"Manufacturing",
            "subcategory":"Printing",
            "type":"Manufacturing & Wholesale Goods"
        }
    ],
    "sg:phone":"+1 305 937 2208",
    "sg:postcode":"33179",
    "sg:province":"FL",
    "sg:tags":[
        "lithographer",
        "commercial",
        "lithographic"
    ],
    "wof:name":"Instant Park Inc",
    "wof:placetype":"venue"
},
  "geometry": {"coordinates":[-80.164861,25.973352],"type":"Point"}
}