{
  "type": "Feature",
  "properties": {
    "addr:full":"3200 Hartley Rd Jacksonville FL 32257",
    "addr:housenumber":"3200",
    "addr:postcode":"32257",
    "addr:street":"Hartley Rd",
    "iso:country":"US",
    "sg:address":"3200 Hartley Rd",
    "sg:city":"Jacksonville",
    "sg:classifiers":[
        {
            "category":"Building & Trades",
            "subcategory":"Construction",
            "type":"Services"
        }
    ],
    "sg:phone":"+1 904 268 9317",
    "sg:postcode":"32257",
    "sg:province":"FL",
    "sg:tags":[
        "contractor"
    ],
    "wof:name":"Adrian Niko Tile Installation",
    "wof:placetype":"venue"
},
  "geometry": {"coordinates":[-81.628657,30.183431],"type":"Point"}
}