{
  "type": "Feature",
  "properties": {
    "iso:country":"US",
    "sg:address":"2644 NW 97th Ave",
    "sg:city":"Doral",
    "sg:classifiers":[
        {
            "category":"Shopping",
            "subcategory":"Musical Instruments",
            "type":"Retail Goods"
        }
    ],
    "sg:phone":"+1 305 470 9042",
    "sg:postcode":"33172",
    "sg:province":"FL",
    "sg:tags":[
        "music",
        "dealer"
    ],
    "wof:name":"D Menace Music",
    "wof:placetype":"venue"
},
  "geometry": {"coordinates":[-80.353274,25.799506],"type":"Point"}
}