{
  "type": "Feature",
  "properties": {
    "iso:country":"US",
    "sg:address":"9 Myrtle Ave",
    "sg:city":"Crawfordville",
    "sg:classifiers":[
        {
            "category":"Building & Trades",
            "subcategory":"Construction",
            "type":"Services"
        }
    ],
    "sg:phone":"+1 850 926 9477",
    "sg:postcode":"32327",
    "sg:province":"FL",
    "sg:tags":[
        "carpentry",
        "contractor"
    ],
    "wof:name":"Harrells Framing of Wakulla",
    "wof:placetype":"venue"
},
  "geometry": {"coordinates":[-84.373194,30.190065],"type":"Point"}
}