{
  "type": "Feature",
  "properties": {
    "iso:country":"US",
    "sg:address":"336 E Highbanks Rd",
    "sg:city":"Debary",
    "sg:classifiers":[
        {
            "category":"Education",
            "subcategory":"School",
            "type":"Public Place"
        }
    ],
    "sg:phone":"+1 386 575 4076",
    "sg:postcode":"32713",
    "sg:province":"FL",
    "sg:tags":[
        "high",
        "middle",
        "elementary"
    ],
    "sg:website":"www.volusia.k12.fl.us",
    "wof:name":"Volusia County School District",
    "wof:placetype":"venue"
},
  "geometry": {"coordinates":[-81.284025,28.890497],"type":"Point"}
}