{
  "type": "Feature",
  "properties": {
    "addr:full":"3565 W Glencoe St Miami FL 33133",
    "addr:housenumber":"3565",
    "addr:postcode":"33133",
    "addr:street":"W Glencoe St",
    "iso:country":"US",
    "sg:address":"3565 W Glencoe St",
    "sg:city":"Miami",
    "sg:classifiers":[
        {
            "category":"Real Estate",
            "subcategory":"Real Estate Agent",
            "type":"Services"
        }
    ],
    "sg:phone":"+1 305 854 8033",
    "sg:postcode":"33133",
    "sg:province":"FL",
    "wof:name":"Donna Slatter",
    "wof:placetype":"venue"
},
  "geometry": {"coordinates":[-80.21875199999999,25.740773],"type":"Point"}
}