{
  "type": "Feature",
  "properties": {
    "addr:full":"21211 Biscayne Blvd Miami FL 33180",
    "addr:housenumber":"21211",
    "addr:postcode":"33180",
    "addr:street":"Biscayne Blvd",
    "iso:country":"US",
    "sg:address":"21211 Biscayne Blvd",
    "sg:city":"Miami",
    "sg:classifiers":[
        {
            "category":"Retail",
            "subcategory":"Laundry & Dry Cleaning",
            "type":"Services"
        }
    ],
    "sg:phone":"+1 305 792 7667",
    "sg:postcode":"33180",
    "sg:province":"FL",
    "sg:tags":[
        "cleaners"
    ],
    "wof:name":"Aventura Commons Quality Clnrs",
    "wof:placetype":"venue"
},
  "geometry": {"coordinates":[-80.144114,25.969904],"type":"Point"}
}