{
  "type": "Feature",
  "properties": {
    "addr:full":"6606 Baybrooks Cir Tampa FL 33617",
    "addr:housenumber":"6606",
    "addr:postcode":"33617",
    "addr:street":"Baybrooks Cir",
    "iso:country":"US",
    "sg:address":"6606 Baybrooks Cir",
    "sg:city":"Tampa",
    "sg:classifiers":[
        {
            "category":"Retail",
            "subcategory":"Repair Shop",
            "type":"Services"
        }
    ],
    "sg:phone":"+1 813 988 2508",
    "sg:postcode":"33617",
    "sg:province":"FL",
    "sg:tags":[
        "gasoline",
        "pump",
        "lift",
        "installation",
        "tank"
    ],
    "wof:name":"Monte Petroleum Contractor",
    "wof:placetype":"venue"
},
  "geometry": {"coordinates":[-82.371617,28.052304],"type":"Point"}
}