{
  "type": "Feature",
  "properties": {
    "addr:full":"24345 Amarillo St Bonita Springs FL 34135",
    "addr:housenumber":"24345",
    "addr:postcode":"34135",
    "addr:street":"Amarillo St",
    "iso:country":"US",
    "sg:address":"24345 Amarillo St",
    "sg:city":"Bonita Springs",
    "sg:classifiers":[
        {
            "category":"Building & Trades",
            "subcategory":"Construction",
            "type":"Services"
        }
    ],
    "sg:phone":"+1 239 947 6445",
    "sg:postcode":"34135",
    "sg:province":"FL",
    "sg:tags":[
        "floor",
        "laying",
        "contractor"
    ],
    "wof:name":"Gerald E Moses",
    "wof:placetype":"venue"
},
  "geometry": {"coordinates":[-81.793845,26.385217],"type":"Point"}
}