{
  "type": "Feature",
  "properties": {
    "addr:full":"2789 State Hwy 580 Clearwater FL 33761",
    "addr:housenumber":"2789",
    "addr:postcode":"33761",
    "addr:street":"State Hwy 580",
    "iso:country":"US",
    "sg:address":"2789 State Hwy 580",
    "sg:city":"Clearwater",
    "sg:classifiers":[
        {
            "category":"Food & Beverages",
            "subcategory":"Groceries & Convenience Stores",
            "type":"Retail Goods"
        }
    ],
    "sg:phone":"+1 727 724 1624",
    "sg:postcode":"33761",
    "sg:province":"FL",
    "wof:name":"7-Eleven",
    "wof:placetype":"venue"
},
  "geometry": {"coordinates":[-82.713455,28.019603],"type":"Point"}
}