{
  "type": "Feature",
  "properties": {
    "addr:full":"11101 St Augustine Rd Jacksonville FL 32257",
    "addr:housenumber":"11101",
    "addr:postcode":"32257",
    "addr:street":"St Augustine Rd",
    "iso:country":"US",
    "sg:address":"11101 St Augustine Rd",
    "sg:city":"Jacksonville",
    "sg:classifiers":[
        {
            "category":"Restaurant",
            "type":"Food & Drink"
        }
    ],
    "sg:phone":"+1 904 880 3883",
    "sg:postcode":"32257",
    "sg:province":"FL",
    "sg:tags":[
        "chinese"
    ],
    "wof:name":"Hop Shing Chinese Food Inc",
    "wof:placetype":"venue"
},
  "geometry": {"coordinates":[-81.602975,30.171514],"type":"Point"}
}