{
  "type": "Feature",
  "properties": {
    "iso:country":"US",
    "sg:address":"844 N Federal Hwy",
    "sg:city":"Pompano Beach",
    "sg:classifiers":[
        {
            "category":"Shopping",
            "subcategory":"Used Merchandise",
            "type":"Retail Goods"
        }
    ],
    "sg:phone":"+1 954 782 9229",
    "sg:postcode":"33062",
    "sg:province":"FL",
    "wof:name":"Consignment Specialties",
    "wof:placetype":"venue"
},
  "geometry": {"coordinates":[-80.102457,26.239808],"type":"Point"}
}