{
  "type": "Feature",
  "properties": {
    "addr:full":"7030 King St Keystone Heights FL 32656",
    "addr:housenumber":"7030",
    "addr:postcode":"32656",
    "addr:street":"King St",
    "iso:country":"US",
    "sg:address":"7030 King St",
    "sg:city":"Keystone Heights",
    "sg:classifiers":[
        {
            "category":"Building & Trades",
            "subcategory":"Construction",
            "type":"Services"
        }
    ],
    "sg:phone":"+1 352 473 4044",
    "sg:postcode":"32656",
    "sg:province":"FL",
    "sg:tags":[
        "repairing",
        "remodeling",
        "contractor"
    ],
    "wof:name":"K & L Renovations",
    "wof:placetype":"venue"
},
  "geometry": {"coordinates":[-82.039974,29.796134],"type":"Point"}
}