{
  "type": "Feature",
  "properties": {
    "addr:full":"9132 SW 157th Avenue Rd Miami FL 33196",
    "addr:housenumber":"9132",
    "addr:postcode":"33196",
    "addr:street":"Sw 157Th Avenue Rd",
    "iso:country":"US",
    "sg:address":"9132 SW 157th Avenue Rd",
    "sg:city":"Miami",
    "sg:classifiers":[
        {
            "category":"Shopping",
            "subcategory":"Discount & Variety Stores",
            "type":"Retail Goods"
        }
    ],
    "sg:phone":"+1 305 388 5300",
    "sg:postcode":"33196",
    "sg:province":"FL",
    "sg:tags":[
        "post",
        "trading"
    ],
    "wof:name":"Access Consulting & Trading",
    "wof:placetype":"venue"
},
  "geometry": {"coordinates":[-80.446941,25.681216],"type":"Point"}
}