{
  "type": "Feature",
  "properties": {
    "addr:full":"4201 S Orange Blossom Trl Orlando FL 32839",
    "addr:housenumber":"4201",
    "addr:postcode":"32839",
    "addr:street":"S Orange Blossom Trl",
    "iso:country":"US",
    "sg:address":"4201 S Orange Blossom Trl",
    "sg:city":"Orlando",
    "sg:classifiers":[
        {
            "category":"Real Estate",
            "subcategory":"Real Estate Services",
            "type":"Services"
        }
    ],
    "sg:phone":"+1 407 246 1660",
    "sg:postcode":"32839",
    "sg:province":"FL",
    "sg:tags":[
        "boarding",
        "house"
    ],
    "wof:name":"New Start City",
    "wof:placetype":"venue"
},
  "geometry": {"coordinates":[-81.396896,28.500891],"type":"Point"}
}