{
  "type": "Feature",
  "properties": {
    "iso:country":"US",
    "sg:address":"1866 N Young Cir",
    "sg:city":"Hollywood",
    "sg:classifiers":[
        {
            "category":"Restaurant",
            "type":"Food & Drink"
        }
    ],
    "sg:menulink":"http://www.allmenus.com/fl/hollywood/122608-quiznos-sub/menu/",
    "sg:phone":"+1 954 920 1151",
    "sg:postcode":"33020",
    "sg:province":"FL",
    "sg:tags":[
        "wrap",
        "american",
        "sandwich"
    ],
    "wof:name":"Quiznos Sub",
    "wof:placetype":"venue"
},
  "geometry": {"coordinates":[-80.144364,26.011745],"type":"Point"}
}