{
  "type": "Feature",
  "properties": {
    "addr:full":"3235 Edgewater Dr Orlando FL 32804",
    "addr:housenumber":"3235",
    "addr:postcode":"32804",
    "addr:street":"Edgewater Dr",
    "iso:country":"US",
    "sg:address":"3235 Edgewater Dr",
    "sg:city":"Orlando",
    "sg:phone":"+1 407 872 7891",
    "sg:postcode":"32804",
    "sg:province":"FL",
    "wof:name":"Matt Dunn Photography",
    "wof:placetype":"venue"
},
  "geometry": {"coordinates":[-81.389599,28.580453],"type":"Point"}
}