{
  "type": "Feature",
  "properties": {
    "iso:country":"US",
    "sg:address":"9438 NW 13th St",
    "sg:city":"Doral",
    "sg:phone":"+1 305 406 9928",
    "sg:postcode":"33172",
    "sg:province":"FL",
    "sg:tags":[
        "material",
        "fixture",
        "display"
    ],
    "wof:name":"Innovation Acrylic Display",
    "wof:placetype":"venue"
},
  "geometry": {"coordinates":[-80.35015199999999,25.784669],"type":"Point"}
}