{
  "type": "Feature",
  "properties": {
    "addr:full":"7925 20th St Vero Beach FL 32966",
    "addr:housenumber":"7925",
    "addr:postcode":"32966",
    "addr:street":"20Th St",
    "iso:country":"US",
    "sg:address":"7925 20th St",
    "sg:city":"Vero Beach",
    "sg:classifiers":[
        {
            "category":"Organizations",
            "subcategory":"Professional Association",
            "type":"Services"
        }
    ],
    "sg:phone":"+1 772 562 2728",
    "sg:postcode":"32966",
    "sg:province":"FL",
    "sg:tags":[
        "business",
        "trade"
    ],
    "wof:name":"Indian River Citrus League",
    "wof:placetype":"venue"
},
  "geometry": {"coordinates":[-80.490723,27.639015],"type":"Point"}
}