{
  "type": "Feature",
  "properties": {
    "addr:full":"4690 SW Hammock Creek Dr Palm City FL 34990",
    "addr:housenumber":"4690",
    "addr:postcode":"34990",
    "addr:street":"Sw Hammock Creek Dr",
    "iso:country":"US",
    "sg:address":"4690 SW Hammock Creek Dr",
    "sg:city":"Palm City",
    "sg:classifiers":[
        {
            "category":"Building & Trades",
            "subcategory":"Construction",
            "type":"Services"
        }
    ],
    "sg:phone":"+1 772 287 9464",
    "sg:postcode":"34990",
    "sg:province":"FL",
    "sg:tags":[
        "painter"
    ],
    "wof:name":"Faircloth Decorators",
    "wof:placetype":"venue"
},
  "geometry": {"coordinates":[-80.29421600000001,27.151071],"type":"Point"}
}