{
  "type": "Feature",
  "properties": {
    "addr:full":"211 W Venice Ave Venice FL 34285",
    "addr:housenumber":"211",
    "addr:postcode":"34285",
    "addr:street":"W Venice Ave",
    "iso:country":"US",
    "sg:address":"211 W Venice Ave",
    "sg:city":"Venice",
    "sg:classifiers":[
        {
            "category":"Shopping",
            "subcategory":"Department Store",
            "type":"Retail Goods"
        }
    ],
    "sg:phone":"+1 941 488 6113",
    "sg:postcode":"34285",
    "sg:province":"FL",
    "sg:tags":[
        "stationary",
        "supply"
    ],
    "wof:name":"VENICE STATIONERS",
    "wof:placetype":"venue"
},
  "geometry": {"coordinates":[-82.447523,27.099806],"type":"Point"}
}