{
  "type": "Feature",
  "properties": {
    "iso:country":"US",
    "sg:address":"3821 Clark Rd",
    "sg:city":"Sarasota",
    "sg:classifiers":[
        {
            "category":"Insurance",
            "subcategory":"Insurance Agent",
            "type":"Services"
        }
    ],
    "sg:phone":"+1 941 924 1800",
    "sg:postcode":"34233",
    "sg:province":"FL",
    "wof:name":"Jeffery D Polivchak Insurance",
    "wof:placetype":"venue"
},
  "geometry": {"coordinates":[-82.494984,27.269353],"type":"Point"}
}