{
  "type": "Feature",
  "properties": {
    "iso:country":"US",
    "sg:address":"13180 Cleveland Ave",
    "sg:city":"Fort Myers",
    "sg:classifiers":[
        {
            "category":"Restaurant",
            "type":"Food & Drink"
        }
    ],
    "sg:phone":"+1 239 997 8999",
    "sg:postcode":"33903",
    "sg:province":"FL",
    "sg:tags":[
        "eating"
    ],
    "wof:name":"Gary Foods Inc",
    "wof:placetype":"venue"
},
  "geometry": {"coordinates":[-81.88657499999999,26.663641],"type":"Point"}
}