{
  "type": "Feature",
  "properties": {
    "addr:full":"2926 Avery Ave Sarasota FL 34232",
    "addr:housenumber":"2926",
    "addr:postcode":"34232",
    "addr:street":"Avery Ave",
    "iso:country":"US",
    "sg:address":"2926 Avery Ave",
    "sg:city":"Sarasota",
    "sg:classifiers":[
        {
            "category":"Building & Trades",
            "subcategory":"Construction",
            "type":"Services"
        }
    ],
    "sg:phone":"+1 941 342 9127",
    "sg:postcode":"34232",
    "sg:province":"FL",
    "sg:tags":[
        "contractor"
    ],
    "wof:name":"Michael Lmbardo Thomas Leonard",
    "wof:placetype":"venue"
},
  "geometry": {"coordinates":[-82.476422,27.306774],"type":"Point"}
}