{
  "type": "Feature",
  "properties": {
    "addr:full":"608 SW 30th Ter Cape Coral FL 33914",
    "addr:housenumber":"608",
    "addr:postcode":"33914",
    "addr:street":"Sw 30Th Ter",
    "iso:country":"US",
    "sg:address":"608 SW 30th Ter",
    "sg:city":"Cape Coral",
    "sg:classifiers":[
        {
            "category":"Arts & Performance",
            "subcategory":"Theater",
            "type":"Entertainment"
        }
    ],
    "sg:phone":"+1 239 573 6607",
    "sg:postcode":"33914",
    "sg:province":"FL",
    "sg:tags":[
        "instrument",
        "group",
        "musical"
    ],
    "wof:name":"George Davidson Productions",
    "wof:placetype":"venue"
},
  "geometry": {"coordinates":[-81.98959000000001,26.59528],"type":"Point"}
}