{
  "type": "Feature",
  "properties": {
    "iso:country":"US",
    "sg:address":"231 E Flagler St",
    "sg:city":"Miami",
    "sg:classifiers":[
        {
            "category":"Shopping",
            "subcategory":"Computers & Home Electronics",
            "type":"Retail Goods"
        }
    ],
    "sg:phone":"+1 305 373 2177",
    "sg:postcode":"33131",
    "sg:province":"FL",
    "wof:name":"Buynusa Corporation",
    "wof:placetype":"venue"
},
  "geometry": {"coordinates":[-80.18933800000001,25.77433],"type":"Point"}
}