{
  "type": "Feature",
  "properties": {
    "iso:country":"US",
    "sg:address":"6401 49th St N",
    "sg:city":"Pinellas Park",
    "sg:classifiers":[
        {
            "category":"Professional",
            "type":"Services"
        }
    ],
    "sg:phone":"+1 727 522 2802",
    "sg:postcode":"33781",
    "sg:province":"FL",
    "wof:name":"Fgl Studios Inc",
    "wof:placetype":"venue"
},
  "geometry": {"coordinates":[-82.699834,27.829136],"type":"Point"}
}