{
  "type": "Feature",
  "properties": {
    "iso:country":"US",
    "sg:address":"9660 NW 59th Ct",
    "sg:city":"Parkland",
    "sg:classifiers":[
        {
            "category":"Home & Garden",
            "subcategory":"Building Materials",
            "type":"Retail Goods"
        }
    ],
    "sg:phone":"+1 954 755 7779",
    "sg:postcode":"33076",
    "sg:province":"FL",
    "sg:tags":[
        "glass",
        "window",
        "plate"
    ],
    "wof:name":"A-1 Auto Glass",
    "wof:placetype":"venue"
},
  "geometry": {"coordinates":[-80.255387,26.304287],"type":"Point"}
}