{
  "type": "Feature",
  "properties": {
    "iso:country":"US",
    "sg:address":"17348 River Isle Cir",
    "sg:city":"Jacksonville",
    "sg:classifiers":[
        {
            "category":"Professional",
            "type":"Services"
        }
    ],
    "sg:phone":"+1 904 757 5171",
    "sg:postcode":"32226",
    "sg:province":"FL",
    "wof:name":"Sharon A Scott Svc",
    "wof:placetype":"venue"
},
  "geometry": {"coordinates":[-81.603469,30.554122],"type":"Point"}
}