{
  "type": "Feature",
  "properties": {
    "iso:country":"US",
    "sg:address":"2077 NW 107th Dr",
    "sg:city":"Pompano Beach",
    "sg:classifiers":[
        {
            "category":"Building & Trades",
            "subcategory":"Plumbing",
            "type":"Services"
        }
    ],
    "sg:phone":"+1 954 575 5565",
    "sg:postcode":"33071",
    "sg:province":"FL",
    "sg:tags":[
        "contractor"
    ],
    "wof:name":"Vinicio Appliances & Air Condi",
    "wof:placetype":"venue"
},
  "geometry": {"coordinates":[-80.267352,26.256829],"type":"Point"}
}