{
  "type": "Feature",
  "properties": {
    "iso:country":"US",
    "sg:address":"2107 Chestnut Forest Dr",
    "sg:city":"Tampa",
    "sg:classifiers":[
        {
            "category":"Building & Trades",
            "subcategory":"Electrical",
            "type":"Services"
        }
    ],
    "sg:phone":"+1 813 969 0038",
    "sg:postcode":"33618",
    "sg:province":"FL",
    "sg:tags":[
        "electrical",
        "contractor"
    ],
    "wof:name":"Kevin D Robles",
    "wof:placetype":"venue"
},
  "geometry": {"coordinates":[-82.48505400000001,28.091469],"type":"Point"}
}