{
  "type": "Feature",
  "properties": {
    "iso:country":"US",
    "sg:address":"1245 Dove Ave",
    "sg:city":"Miami",
    "sg:classifiers":[
        {
            "category":"Organizations",
            "subcategory":"Religious Organization",
            "type":"Services"
        }
    ],
    "sg:phone":"+1 305 654 0754",
    "sg:postcode":"33166",
    "sg:province":"FL",
    "wof:name":"House of Faith Church Inc",
    "wof:placetype":"venue"
},
  "geometry": {"coordinates":[-80.304952,25.829919],"type":"Point"}
}