{
  "type": "Feature",
  "properties": {
    "addr:full":"2552 Columbus St Fort Myers FL 33901",
    "addr:housenumber":"2552",
    "addr:postcode":"33901",
    "addr:street":"Columbus St",
    "iso:country":"US",
    "sg:address":"2552 Columbus St",
    "sg:city":"Fort Myers",
    "sg:classifiers":[
        {
            "category":"Building & Trades",
            "subcategory":"Plumbing",
            "type":"Services"
        }
    ],
    "sg:phone":"+1 239 334 1837",
    "sg:postcode":"33901",
    "sg:province":"FL",
    "sg:tags":[
        "contractor"
    ],
    "wof:name":"Miller Mechanical Repair",
    "wof:placetype":"venue"
},
  "geometry": {"coordinates":[-81.874456,26.630496],"type":"Point"}
}