{
  "type": "Feature",
  "properties": {
    "iso:country":"US",
    "sg:address":"6655 W Boynton Beach Blvd",
    "sg:city":"Boynton Beach",
    "sg:classifiers":[
        {
            "category":"Restaurant",
            "type":"Food & Drink"
        }
    ],
    "sg:phone":"+1 561 738 7011",
    "sg:postcode":"33437",
    "sg:province":"FL",
    "wof:name":"Mamma Mia Italian Restaurant",
    "wof:placetype":"venue"
},
  "geometry": {"coordinates":[-80.149514,26.528216],"type":"Point"}
}