{
  "type": "Feature",
  "properties": {
    "iso:country":"US",
    "sg:address":"2 Alhambra Plz",
    "sg:city":"Coral Gables",
    "sg:classifiers":[
        {
            "category":"Banks & Credit Unions",
            "subcategory":"Investment Brokerage",
            "type":"Services"
        }
    ],
    "sg:phone":"+1 305 476 0970",
    "sg:postcode":"33134",
    "sg:province":"FL",
    "sg:tags":[
        "investing"
    ],
    "wof:name":"Surgent & Associates",
    "wof:placetype":"venue"
},
  "geometry": {"coordinates":[-80.25460099999999,25.752399],"type":"Point"}
}