{
  "type": "Feature",
  "properties": {
    "iso:country":"US",
    "sg:address":"4000 Saint Johns Ave",
    "sg:city":"Jacksonville",
    "sg:classifiers":[
        {
            "category":"Home & Garden",
            "subcategory":"Furniture",
            "type":"Retail Goods"
        }
    ],
    "sg:phone":"+1 904 381 9148",
    "sg:postcode":"32205",
    "sg:province":"FL",
    "sg:website":"www.thepinecottage.com",
    "wof:name":"Pine Cottage",
    "wof:placetype":"venue"
},
  "geometry": {"coordinates":[-81.698938,30.300621],"type":"Point"}
}