{
  "type": "Feature",
  "properties": {
    "iso:country":"US",
    "sg:address":"773 Veronica Cir",
    "sg:city":"Ocoee",
    "sg:classifiers":[
        {
            "category":"Retail",
            "subcategory":"Auto Repair",
            "type":"Services"
        }
    ],
    "sg:phone":"+1 407 298 7995",
    "sg:postcode":"34761",
    "sg:province":"FL",
    "sg:tags":[
        "body"
    ],
    "wof:name":"J Tech Auto Services",
    "wof:placetype":"venue"
},
  "geometry": {"coordinates":[-81.529453,28.564096],"type":"Point"}
}