{
  "type": "Feature",
  "properties": {
    "addr:full":"7614 Ellis Rd Melbourne FL 32904",
    "addr:housenumber":"7614",
    "addr:postcode":"32904",
    "addr:street":"Ellis Rd",
    "iso:country":"US",
    "sg:address":"7614 Ellis Rd",
    "sg:city":"Melbourne",
    "sg:classifiers":[
        {
            "category":"Retail",
            "subcategory":"Auto Repair",
            "type":"Services"
        }
    ],
    "sg:phone":"+1 321 727 9001",
    "sg:postcode":"32904",
    "sg:province":"FL",
    "sg:tags":[
        "body",
        "automobile",
        "painting",
        "repairing"
    ],
    "wof:name":"M & L Auto Collision",
    "wof:placetype":"venue"
},
  "geometry": {"coordinates":[-80.67556,28.099622],"type":"Point"}
}