{
  "type": "Feature",
  "properties": {
    "iso:country":"US",
    "sg:address":"13200 US Hwy 301",
    "sg:city":"Dade City",
    "sg:classifiers":[
        {
            "category":"Autos & Motor Vehicles",
            "subcategory":"Fuel & Gas Station",
            "type":"Retail Goods"
        }
    ],
    "sg:phone":"+1 352 567 1214",
    "sg:postcode":"33525",
    "sg:province":"FL",
    "sg:tags":[
        "oil"
    ],
    "wof:name":"Shell",
    "wof:placetype":"venue"
},
  "geometry": {"coordinates":[-82.187668,28.350682],"type":"Point"}
}