{
  "type": "Feature",
  "properties": {
    "iso:country":"US",
    "sg:address":"2261 N University Dr",
    "sg:city":"Hollywood",
    "sg:classifiers":[
        {
            "category":"Health Services",
            "subcategory":"Doctor",
            "type":"Services"
        }
    ],
    "sg:phone":"+1 954 962 4680",
    "sg:postcode":"33024",
    "sg:province":"FL",
    "sg:tags":[
        "clinic",
        "medical"
    ],
    "wof:name":"Miro-Berkeley Zenobia",
    "wof:placetype":"venue"
},
  "geometry": {"coordinates":[-80.248745,26.02881],"type":"Point"}
}