{
  "type": "Feature",
  "properties": {
    "addr:full":"730 E 57th St Hialeah FL 33013",
    "addr:housenumber":"730",
    "addr:postcode":"33013",
    "addr:street":"E 57Th St",
    "iso:country":"US",
    "sg:address":"730 E 57th St",
    "sg:city":"Hialeah",
    "sg:classifiers":[
        {
            "category":"Building & Trades",
            "subcategory":"Construction",
            "type":"Services"
        }
    ],
    "sg:phone":"+1 305 300 9697",
    "sg:postcode":"33013",
    "sg:province":"FL",
    "sg:tags":[
        "contractor",
        "fence-sales"
    ],
    "wof:name":"Omar Fence Corp",
    "wof:placetype":"venue"
},
  "geometry": {"coordinates":[-80.26837399999999,25.87454],"type":"Point"}
}