{
  "type": "Feature",
  "properties": {
    "addr:full":"5601 S Chestnut Hill Pt Homosassa FL 34446",
    "addr:housenumber":"5601",
    "addr:postcode":"34446",
    "addr:street":"S Chestnut Hill Pt",
    "iso:country":"US",
    "sg:address":"5601 S Chestnut Hill Pt",
    "sg:city":"Homosassa",
    "sg:classifiers":[
        {
            "category":"Building & Trades",
            "subcategory":"Construction",
            "type":"Services"
        }
    ],
    "sg:phone":"+1 352 628 0469",
    "sg:postcode":"34446",
    "sg:province":"FL",
    "sg:tags":[
        "contractor"
    ],
    "wof:name":"Kevin J Gates",
    "wof:placetype":"venue"
},
  "geometry": {"coordinates":[-82.55200600000001,28.780128],"type":"Point"}
}