{
  "type": "Feature",
  "properties": {
    "iso:country":"US",
    "sg:address":"17228 Hampton Blvd",
    "sg:city":"Boca Raton",
    "sg:classifiers":[
        {
            "category":"Communications",
            "type":"Services"
        }
    ],
    "sg:phone":"+1 561 988 3438",
    "sg:postcode":"33496",
    "sg:province":"FL",
    "wof:name":"Passport Communications",
    "wof:placetype":"venue"
},
  "geometry": {"coordinates":[-80.14753899999999,26.420805],"type":"Point"}
}