{
  "type": "Feature",
  "properties": {
    "iso:country":"US",
    "sg:address":"2823 S Seacrest Blvd",
    "sg:city":"Boynton Beach",
    "sg:classifiers":[
        {
            "category":"Shopping",
            "subcategory":"Pharmacy",
            "type":"Retail Goods"
        }
    ],
    "sg:phone":"+1 561 732 8160",
    "sg:postcode":"33435",
    "sg:province":"FL",
    "wof:name":"Seacrest Pharmacy",
    "wof:placetype":"venue"
},
  "geometry": {"coordinates":[-80.070744,26.500824],"type":"Point"}
}