{
  "type": "Feature",
  "properties": {
    "addr:full":"3005 W Lake Mary Blvd Ste 101 Lake Mary FL 32746",
    "addr:housenumber":"3005",
    "addr:postcode":"32746",
    "addr:street":"W Lake Mary Blvd Ste 101;Mary",
    "iso:country":"US",
    "sg:address":"3005 W Lake Mary Blvd Ste 101",
    "sg:city":"Lake Mary",
    "sg:classifiers":[
        {
            "category":"Health Services",
            "subcategory":"Chiropractor",
            "type":"Services"
        }
    ],
    "sg:phone":"+1 407 330 7577",
    "sg:postcode":"32746",
    "sg:province":"FL",
    "wof:name":"Masters Chiropractic",
    "wof:placetype":"venue"
},
  "geometry": {"coordinates":[-81.332497,28.7561],"type":"Point"}
}