{
  "type": "Feature",
  "properties": {
    "iso:country":"US",
    "sg:address":"501 Palm Ave",
    "sg:city":"Hialeah",
    "sg:classifiers":[
        {
            "category":"Government",
            "subcategory":"Office",
            "type":"Public Place"
        }
    ],
    "sg:phone":"+1 305 883 5820",
    "sg:postcode":"33010",
    "sg:province":"FL",
    "sg:tags":[
        "city"
    ],
    "sg:website":"www.ci.hialeah.fl.us",
    "wof:name":"Hialeah City Clerk",
    "wof:placetype":"venue"
},
  "geometry": {"coordinates":[-80.28146599999999,25.827191],"type":"Point"}
}