{
  "type": "Feature",
  "properties": {
    "addr:full":"8370 W Flagler St Ste 206 Miami FL 33144",
    "addr:housenumber":"8370",
    "addr:postcode":"33144",
    "addr:street":"W Flagler St Ste 206",
    "iso:country":"US",
    "sg:address":"8370 W Flagler St Ste 206",
    "sg:city":"Miami",
    "sg:classifiers":[
        {
            "category":"Manufacturing",
            "subcategory":"Buildings",
            "type":"Manufacturing & Wholesale Goods"
        },
        {
            "category":"Building & Trades",
            "subcategory":"Construction",
            "type":"Services"
        }
    ],
    "sg:phone":"+1 305 220 6557",
    "sg:postcode":"33144",
    "sg:province":"FL",
    "sg:tags":[
        "management",
        "builder",
        "contractor",
        "industrial",
        "contractors-commercial",
        "home"
    ],
    "wof:name":"Vm Construction Co",
    "wof:placetype":"venue"
},
  "geometry": {"coordinates":[-80.331236,25.769477],"type":"Point"}
}