{
  "type": "Feature",
  "properties": {
    "iso:country":"US",
    "sg:address":"3001 Corrine Dr",
    "sg:city":"Orlando",
    "sg:classifiers":[
        {
            "category":"Bars & Pubs",
            "type":"Food & Drink"
        }
    ],
    "sg:phone":"+1 407 644 2844",
    "sg:postcode":"32803",
    "sg:province":"FL",
    "sg:tags":[
        "drinking"
    ],
    "wof:name":"Big Daddys Roadhouse",
    "wof:placetype":"venue"
},
  "geometry": {"coordinates":[-81.345038,28.56785],"type":"Point"}
}