{
  "type": "Feature",
  "properties": {
    "iso:country":"US",
    "sg:address":"9410 NW 12th St",
    "sg:city":"Doral",
    "sg:classifiers":[
        {
            "category":"Wholesale",
            "subcategory":"Durable Goods & Equipment",
            "type":"Manufacturing & Wholesale Goods"
        }
    ],
    "sg:phone":"+1 305 594 2907",
    "sg:postcode":"33172",
    "sg:province":"FL",
    "sg:tags":[
        "exporter"
    ],
    "wof:name":"Servicargo Inc",
    "wof:placetype":"venue"
},
  "geometry": {"coordinates":[-80.349323,25.783345],"type":"Point"}
}