{
  "type": "Feature",
  "properties": {
    "addr:full":"5 Breeze St Gulf Breeze FL 32561",
    "addr:housenumber":"5",
    "addr:postcode":"32561",
    "addr:street":"Breeze St",
    "iso:country":"US",
    "sg:address":"5 Breeze St",
    "sg:city":"Gulf Breeze",
    "sg:classifiers":[
        {
            "category":"Insurance",
            "subcategory":"Hazard Insurance",
            "type":"Services"
        }
    ],
    "sg:phone":"+1 850 932 2621",
    "sg:postcode":"32561",
    "sg:province":"FL",
    "sg:tags":[
        "carrier"
    ],
    "wof:name":"Atkinson Group Inc",
    "wof:placetype":"venue"
},
  "geometry": {"coordinates":[-87.17971900000001,30.366557],"type":"Point"}
}