{
  "type": "Feature",
  "properties": {
    "iso:country":"US",
    "sg:address":"1900 S Ocean Dr",
    "sg:city":"Fort Lauderdale",
    "sg:classifiers":[
        {
            "category":"Real Estate",
            "subcategory":"Real Estate Operator",
            "type":"Services"
        }
    ],
    "sg:phone":"+1 954 523 6636",
    "sg:postcode":"33316",
    "sg:province":"FL",
    "sg:tags":[
        "apartment"
    ],
    "wof:name":"Breakwater Towers Corp",
    "wof:placetype":"venue"
},
  "geometry": {"coordinates":[-80.109341,26.098222],"type":"Point"}
}