{
  "type": "Feature",
  "properties": {
    "iso:country":"US",
    "sg:address":"2478 Princeton Ct",
    "sg:city":"Fort Lauderdale",
    "sg:classifiers":[
        {
            "category":"Home & Garden",
            "subcategory":"Carpets & Floor Coverings",
            "type":"Retail Goods"
        }
    ],
    "sg:phone":"+1 954 349 0389",
    "sg:postcode":"33327",
    "sg:province":"FL",
    "wof:name":"Tsunami Telecom Corp",
    "wof:placetype":"venue"
},
  "geometry": {"coordinates":[-80.401228,26.095506],"type":"Point"}
}