{
  "type": "Feature",
  "properties": {
    "iso:country":"US",
    "sg:address":"7940 Pines Blvd",
    "sg:city":"Pembroke Pines",
    "sg:classifiers":[
        {
            "category":"Insurance",
            "subcategory":"Insurance Agent",
            "type":"Services"
        }
    ],
    "sg:phone":"+1 954 436 6066",
    "sg:postcode":"33024",
    "sg:province":"FL",
    "wof:name":"Best Budget Plan",
    "wof:placetype":"venue"
},
  "geometry": {"coordinates":[-80.247955,26.009152],"type":"Point"}
}