{
  "type": "Feature",
  "properties": {
    "iso:country":"US",
    "sg:address":"6580 Bottlebrush Ln",
    "sg:city":"Naples",
    "sg:classifiers":[
        {
            "category":"Building & Trades",
            "subcategory":"Landscaping Services",
            "type":"Services"
        }
    ],
    "sg:phone":"+1 239 597 6027",
    "sg:postcode":"34109",
    "sg:province":"FL",
    "sg:tags":[
        "landscape"
    ],
    "wof:name":"Botanically Correct",
    "wof:placetype":"venue"
},
  "geometry": {"coordinates":[-81.744985,26.216999],"type":"Point"}
}