{
  "type": "Feature",
  "properties": {
    "iso:country":"US",
    "sg:address":"507 W 17th St",
    "sg:city":"Hialeah",
    "sg:classifiers":[
        {
            "category":"Retail",
            "subcategory":"Auto Repair",
            "type":"Services"
        }
    ],
    "sg:phone":"+1 305 826 0207",
    "sg:postcode":"33010",
    "sg:province":"FL",
    "sg:tags":[
        "automotive"
    ],
    "wof:name":"Flamingo Towing",
    "wof:placetype":"venue"
},
  "geometry": {"coordinates":[-80.293421,25.837184],"type":"Point"}
}