{
  "type": "Feature",
  "properties": {
    "iso:country":"US",
    "sg:address":"8700 Henderson Grade",
    "sg:city":"Fort Myers",
    "sg:classifiers":[
        {
            "category":"Communications",
            "subcategory":"Television Station",
            "type":"Services"
        }
    ],
    "sg:phone":"+1 239 567 1890",
    "sg:postcode":"33917",
    "sg:province":"FL",
    "sg:tags":[
        "broadcasting",
        "co"
    ],
    "wof:name":"Tiger Eye Broadcasting",
    "wof:placetype":"venue"
},
  "geometry": {"coordinates":[-81.81254,26.742547],"type":"Point"}
}