{
  "type": "Feature",
  "properties": {
    "iso:country":"US",
    "sg:address":"300 E Church St",
    "sg:city":"Orlando",
    "sg:classifiers":[
        {
            "category":"Social Services",
            "subcategory":"Job Training",
            "type":"Services"
        },
        {
            "category":"Health Services",
            "subcategory":"Health Practitioner",
            "type":"Services"
        },
        {
            "category":"Social Services",
            "subcategory":"Adult Care",
            "type":"Services"
        },
        {
            "category":"Health Services",
            "subcategory":"Clinic",
            "type":"Services"
        }
    ],
    "sg:phone":"+1 407 872 7088",
    "sg:postcode":"32801",
    "sg:province":"FL",
    "sg:tags":[
        "nursing",
        "homes-skilled",
        "facility",
        "alzheimer's",
        "therapist",
        "home",
        "rehabilitation",
        "physical"
    ],
    "sg:website":"http://www.orlandolt.com",
    "wof:name":"The Commons At Orlando Lutheran Towers",
    "wof:placetype":"venue"
},
  "geometry": {"coordinates":[-81.37436700000001,28.540421],"type":"Point"}
}