{
  "type": "Feature",
  "properties": {
    "iso:country":"US",
    "sg:address":"1001 NW 4th St",
    "sg:city":"Fort Lauderdale",
    "sg:classifiers":[
        {
            "category":"Education",
            "subcategory":"School",
            "type":"Public Place"
        }
    ],
    "sg:phone":"+1 954 765 6878",
    "sg:postcode":"33311",
    "sg:province":"FL",
    "wof:name":"Walker Elementary School",
    "wof:placetype":"venue"
},
  "geometry": {"coordinates":[-80.15572899999999,26.125726],"type":"Point"}
}