{
  "type": "Feature",
  "properties": {
    "addr:full":"252 W Olympia Ave Punta Gorda FL 33950",
    "addr:housenumber":"252",
    "addr:postcode":"33950",
    "addr:street":"W Olympia Ave",
    "iso:country":"US",
    "sg:address":"252 W Olympia Ave",
    "sg:city":"Punta Gorda",
    "sg:classifiers":[
        {
            "category":"Professional",
            "subcategory":"Accounting & Tax Preparation",
            "type":"Services"
        }
    ],
    "sg:phone":"+1 941 637 0544",
    "sg:postcode":"33950",
    "sg:province":"FL",
    "wof:name":"Koch & Co",
    "wof:placetype":"venue"
},
  "geometry": {"coordinates":[-82.050726,26.933799],"type":"Point"}
}