{
  "type": "Feature",
  "properties": {
    "addr:full":"310 Brunson Blvd Cocoa FL 32922",
    "addr:housenumber":"310",
    "addr:postcode":"32922",
    "addr:street":"Brunson Blvd",
    "iso:country":"US",
    "sg:address":"310 Brunson Blvd",
    "sg:city":"Cocoa",
    "sg:classifiers":[
        {
            "category":"Wholesale",
            "subcategory":"Auto Parts",
            "type":"Manufacturing & Wholesale Goods"
        }
    ],
    "sg:phone":"+1 321 639 2528",
    "sg:postcode":"32922",
    "sg:province":"FL",
    "sg:tags":[
        "automobile",
        "supply"
    ],
    "wof:name":"J W Craddock Wholesale Auto",
    "wof:placetype":"venue"
},
  "geometry": {"coordinates":[-80.73335899999999,28.361133],"type":"Point"}
}