{
  "type": "Feature",
  "properties": {
    "addr:full":"9400 Airport Blvd Orlando FL 32827",
    "addr:housenumber":"9400",
    "addr:postcode":"32827",
    "addr:street":"Airport Blvd",
    "iso:country":"US",
    "sg:address":"9400 Airport Blvd",
    "sg:city":"Orlando",
    "sg:classifiers":[
        {
            "category":"Autos & Motor Vehicles",
            "subcategory":"Automobile Sales",
            "type":"Retail Goods"
        },
        {
            "category":"Retail",
            "subcategory":"Auto Rental",
            "type":"Services"
        }
    ],
    "sg:phone":"+1 407 281 3555",
    "sg:postcode":"32827",
    "sg:province":"FL",
    "sg:tags":[
        "truck",
        "leasing",
        "car"
    ],
    "sg:website":"http://www.enterprise.com/car_rental/deeplinkmap.do?gpbr=0703&bid=004&cnty=US&arc=YPTRL01&cm_mmc=Yellowpages.com-_-IYP-_-Tradelisting-_-branch",
    "wof:name":"Enterprise Rent-A-Car",
    "wof:placetype":"venue"
},
  "geometry": {"coordinates":[-81.30514100000001,28.431291],"type":"Point"}
}