{
  "type": "Feature",
  "properties": {
    "iso:country":"US",
    "sg:address":"2001 Kingsley Ave",
    "sg:city":"Orange Park",
    "sg:classifiers":[
        {
            "category":"Health Services",
            "subcategory":"Doctor",
            "type":"Services"
        }
    ],
    "sg:phone":"+1 904 276 8501",
    "sg:postcode":"32073",
    "sg:province":"FL",
    "sg:tags":[
        "physician",
        "surgeon"
    ],
    "wof:name":"Hurt Isaacs Johnston/Cranford",
    "wof:placetype":"venue"
},
  "geometry": {"coordinates":[-81.741964,30.164708],"type":"Point"}
}