{
  "type": "Feature",
  "properties": {
    "addr:full":"5967 Southwind Dr Mulberry FL 33860",
    "addr:housenumber":"5967",
    "addr:postcode":"33860",
    "addr:street":"Southwind Dr",
    "iso:country":"US",
    "sg:address":"5967 Southwind Dr",
    "sg:city":"Mulberry",
    "sg:classifiers":[
        {
            "category":"Building & Trades",
            "subcategory":"Construction",
            "type":"Services"
        }
    ],
    "sg:phone":"+1 863 648 9532",
    "sg:postcode":"33860",
    "sg:province":"FL",
    "sg:tags":[
        "concrete",
        "contractor"
    ],
    "wof:name":"G & L Concrete",
    "wof:placetype":"venue"
},
  "geometry": {"coordinates":[-82.042615,27.937698],"type":"Point"}
}