{
  "type": "Feature",
  "properties": {
    "iso:country":"US",
    "sg:address":"4021 SW 4th Cir",
    "sg:city":"Ocala",
    "sg:classifiers":[
        {
            "category":"Banks & Credit Unions",
            "subcategory":"Bank",
            "type":"Services"
        }
    ],
    "sg:phone":"+1 352 861 0408",
    "sg:postcode":"34474",
    "sg:province":"FL",
    "sg:tags":[
        "national",
        "commercial"
    ],
    "wof:name":"Chase Manhattan",
    "wof:placetype":"venue"
},
  "geometry": {"coordinates":[-82.136742,29.137144],"type":"Point"}
}