{
  "type": "Feature",
  "properties": {
    "iso:country":"US",
    "sg:address":"3263 Beneva Rd",
    "sg:city":"Sarasota",
    "sg:classifiers":[
        {
            "category":"Home & Garden",
            "subcategory":"Carpets & Floor Coverings",
            "type":"Retail Goods"
        }
    ],
    "sg:phone":"+1 941 302 3589",
    "sg:postcode":"34232",
    "sg:province":"FL",
    "wof:name":"Jean Linteau Wood Floors Crpt",
    "wof:placetype":"venue"
},
  "geometry": {"coordinates":[-82.497478,27.302479],"type":"Point"}
}