{
  "type": "Feature",
  "properties": {
    "addr:full":"8301 NW 30th Ter Doral FL 33122",
    "addr:housenumber":"8301",
    "addr:postcode":"33122",
    "addr:street":"Nw 30Th Ter",
    "iso:country":"US",
    "sg:address":"8301 NW 30th Ter",
    "sg:city":"Doral",
    "sg:classifiers":[
        {
            "category":"Wholesale",
            "subcategory":"Plants",
            "type":"Manufacturing & Wholesale Goods"
        },
        {
            "category":"Shopping",
            "subcategory":"Crafts & Fabrics",
            "type":"Retail Goods"
        }
    ],
    "sg:phone":"+1 305 471 0321",
    "sg:postcode":"33122",
    "sg:province":"FL",
    "sg:tags":[
        "florists'",
        "supply",
        "florists-wholesale",
        "florist",
        "supplies-wholesale",
        "manufacturer"
    ],
    "wof:name":"Simpson's Greens & Floral Distributors",
    "wof:placetype":"venue"
},
  "geometry": {"coordinates":[-80.33114,25.801675],"type":"Point"}
}