{
  "type": "Feature",
  "properties": {
    "iso:country":"US",
    "sg:address":"2321 NW 41st St",
    "sg:city":"Gainesville",
    "sg:classifiers":[
        {
            "category":"Insurance",
            "subcategory":"Insurance Agent",
            "type":"Services"
        }
    ],
    "sg:phone":"+1 352 377 0420",
    "sg:postcode":"32606",
    "sg:province":"FL",
    "sg:tags":[
        "broker"
    ],
    "wof:name":"King Insur Agcy of Gainesville",
    "wof:placetype":"venue"
},
  "geometry": {"coordinates":[-82.386315,29.674263],"type":"Point"}
}