{
  "type": "Feature",
  "properties": {
    "iso:country":"US",
    "sg:address":"229 Banyan Ln",
    "sg:city":"Tavernier",
    "sg:classifiers":[
        {
            "category":"Real Estate",
            "subcategory":"Real Estate Services",
            "type":"Services"
        },
        {
            "category":"Real Estate",
            "subcategory":"Real Estate Agent",
            "type":"Services"
        }
    ],
    "sg:phone":"+1 305 852 8095",
    "sg:postcode":"33070",
    "sg:province":"FL",
    "sg:tags":[
        "buyer",
        "broker"
    ],
    "wof:name":"Atlantic Real Estate Opportunities",
    "wof:placetype":"venue"
},
  "geometry": {"coordinates":[-80.507172,25.019608],"type":"Point"}
}