{
  "type": "Feature",
  "properties": {
    "addr:full":"11888 NW 2nd St Pompano Beach FL 33071",
    "addr:housenumber":"11888",
    "addr:postcode":"33071",
    "addr:street":"Nw 2Nd St",
    "iso:country":"US",
    "sg:address":"11888 NW 2nd St",
    "sg:city":"Pompano Beach",
    "sg:classifiers":[
        {
            "category":"Wholesale",
            "subcategory":"Fruits & Vegetables",
            "type":"Manufacturing & Wholesale Goods"
        }
    ],
    "sg:phone":"+1 954 753 2618",
    "sg:postcode":"33071",
    "sg:province":"FL",
    "sg:tags":[
        "representative"
    ],
    "wof:name":"Suazo Agrotrading Inc",
    "wof:placetype":"venue"
},
  "geometry": {"coordinates":[-80.282207,26.233816],"type":"Point"}
}