{
  "type": "Feature",
  "properties": {
    "addr:full":"3850 68th Ave N Pinellas Park FL 33781",
    "addr:housenumber":"3850",
    "addr:postcode":"33781",
    "addr:street":"68Th Ave N",
    "iso:country":"US",
    "sg:address":"3850 68th Ave N",
    "sg:city":"Pinellas Park",
    "sg:classifiers":[
        {
            "category":"Professional",
            "type":"Services"
        }
    ],
    "sg:phone":"+1 727 527 1308",
    "sg:postcode":"33781",
    "sg:province":"FL",
    "sg:tags":[
        "establishment"
    ],
    "wof:name":"Sassaman K Pumps",
    "wof:placetype":"venue"
},
  "geometry": {"coordinates":[-82.68728,27.833709],"type":"Point"}
}