{
  "type": "Feature",
  "properties": {
    "addr:full":"3605 Thomas Dr Panama City Bch FL 32408",
    "addr:housenumber":"3605",
    "addr:postcode":"32408",
    "addr:street":"Thomas Dr",
    "iso:country":"US",
    "sg:address":"3605 Thomas Dr",
    "sg:city":"Panama City Bch",
    "sg:classifiers":[
        {
            "category":"Travel",
            "subcategory":"Travel Agent",
            "type":"Entertainment"
        }
    ],
    "sg:phone":"+1 850 234 7783",
    "sg:postcode":"32408",
    "sg:province":"FL",
    "sg:tags":[
        "tours",
        "promoter"
    ],
    "wof:name":"Hombre Charters",
    "wof:placetype":"venue"
},
  "geometry": {"coordinates":[-85.749431,30.145411],"type":"Point"}
}