{
  "type": "Feature",
  "properties": {
    "iso:country":"US",
    "sg:address":"164 Green Shade Rd",
    "sg:city":"Bainbridge",
    "sg:classifiers":[
        {
            "category":"Freight",
            "type":"Transportation"
        }
    ],
    "sg:phone":"+1 229 248 0077",
    "sg:postcode":"39819",
    "sg:province":"FL",
    "sg:tags":[
        "operator",
        "local",
        "trucking"
    ],
    "wof:name":"Swicord Grocery",
    "wof:placetype":"venue"
},
  "geometry": {"coordinates":[-84.54927600000001,30.801601],"type":"Point"}
}