{
  "type": "Feature",
  "properties": {
    "iso:country":"US",
    "sg:address":"65 Avenue E",
    "sg:city":"Apalachicola",
    "sg:classifiers":[
        {
            "category":"Real Estate",
            "subcategory":"Real Estate Agent",
            "type":"Services"
        }
    ],
    "sg:phone":"+1 850 653 3300",
    "sg:postcode":"32320",
    "sg:province":"FL",
    "wof:name":"Anchor Realty & Mortgage",
    "wof:placetype":"venue"
},
  "geometry": {"coordinates":[-84.98648300000001,29.72608],"type":"Point"}
}