{
  "type": "Feature",
  "properties": {
    "addr:full":"2201 Lake Weston Dr Orlando FL 32810",
    "addr:housenumber":"2201",
    "addr:postcode":"32810",
    "addr:street":"Lake Weston Dr",
    "iso:country":"US",
    "sg:address":"2201 Lake Weston Dr",
    "sg:city":"Orlando",
    "sg:classifiers":[
        {
            "category":"Real Estate",
            "subcategory":"Real Estate Operator",
            "type":"Services"
        }
    ],
    "sg:phone":"+1 407 294 7373",
    "sg:postcode":"32810",
    "sg:province":"FL",
    "sg:tags":[
        "apartment"
    ],
    "wof:name":"Lake Weston Point",
    "wof:placetype":"venue"
},
  "geometry": {"coordinates":[-81.42739899999999,28.6238],"type":"Point"}
}