{
  "type": "Feature",
  "properties": {
    "addr:full":"7261 Bee Ridge Rd Sarasota FL 34241",
    "addr:housenumber":"7261",
    "addr:postcode":"34241",
    "addr:street":"Bee Ridge Rd",
    "iso:country":"US",
    "sg:address":"7261 Bee Ridge Rd",
    "sg:city":"Sarasota",
    "sg:classifiers":[
        {
            "category":"Banks & Credit Unions",
            "subcategory":"Investment Brokerage",
            "type":"Services"
        }
    ],
    "sg:phone":"+1 941 378 0891",
    "sg:postcode":"34241",
    "sg:province":"FL",
    "sg:tags":[
        "advisory",
        "financial"
    ],
    "wof:name":"Raymond James Financial Svc",
    "wof:placetype":"venue"
},
  "geometry": {"coordinates":[-82.420479,27.298696],"type":"Point"}
}