{
  "type": "Feature",
  "properties": {
    "addr:full":"6634 Caroline St Milton FL 32570",
    "addr:housenumber":"6634",
    "addr:postcode":"32570",
    "addr:street":"Caroline St",
    "iso:country":"US",
    "sg:address":"6634 Caroline St",
    "sg:city":"Milton",
    "sg:classifiers":[
        {
            "category":"Personal",
            "subcategory":"Beauty Salon",
            "type":"Services"
        }
    ],
    "sg:phone":"+1 850 623 5155",
    "sg:postcode":"32570",
    "sg:province":"FL",
    "wof:name":"Exceptions Hair Studio",
    "wof:placetype":"venue"
},
  "geometry": {"coordinates":[-87.045817,30.621409],"type":"Point"}
}