{
  "type": "Feature",
  "properties": {
    "addr:full":"28339 Hidden Lake Dr Bonita Springs FL 34134",
    "addr:housenumber":"28339",
    "addr:postcode":"34134",
    "addr:street":"Hidden Lake Dr",
    "iso:country":"US",
    "sg:address":"28339 Hidden Lake Dr",
    "sg:city":"Bonita Springs",
    "sg:classifiers":[
        {
            "category":"Real Estate",
            "subcategory":"Real Estate Operator",
            "type":"Services"
        }
    ],
    "sg:phone":"+1 239 948 2075",
    "sg:postcode":"34134",
    "sg:province":"FL",
    "sg:tags":[
        "building",
        "nonresidential"
    ],
    "wof:name":"Blue Quasar Properties LLC",
    "wof:placetype":"venue"
},
  "geometry": {"coordinates":[-81.810607,26.322706],"type":"Point"}
}