{
  "type": "Feature",
  "properties": {
    "iso:country":"US",
    "sg:address":"9010 SW 137th Ave",
    "sg:city":"Miami",
    "sg:classifiers":[
        {
            "category":"Utilities",
            "subcategory":"Electric",
            "type":"Services"
        }
    ],
    "sg:phone":"+1 305 387 9099",
    "sg:postcode":"33186",
    "sg:province":"FL",
    "sg:tags":[
        "company"
    ],
    "wof:name":"Nor AM Energy Svc",
    "wof:placetype":"venue"
},
  "geometry": {"coordinates":[-80.41657600000001,25.682319],"type":"Point"}
}