{
  "type": "Feature",
  "properties": {
    "iso:country":"US",
    "sg:address":"475 S Ronald Reagan Blvd",
    "sg:city":"Longwood",
    "sg:classifiers":[
        {
            "category":"Home & Garden",
            "subcategory":"Household Appliances",
            "type":"Retail Goods"
        }
    ],
    "sg:phone":"+1 407 834 1711",
    "sg:postcode":"32750",
    "sg:province":"FL",
    "sg:tags":[
        "electric"
    ],
    "wof:name":"Assured Appliance Inc",
    "wof:placetype":"venue"
},
  "geometry": {"coordinates":[-81.346079,28.694556],"type":"Point"}
}