{
  "type": "Feature",
  "properties": {
    "iso:country":"US",
    "sg:address":"537 Douglas Ave",
    "sg:city":"Dunedin",
    "sg:classifiers":[
        {
            "category":"Real Estate",
            "subcategory":"Real Estate Agent",
            "type":"Services"
        }
    ],
    "sg:phone":"+1 727 734 5464",
    "sg:postcode":"34698",
    "sg:province":"FL",
    "wof:name":"By The Best Realty",
    "wof:placetype":"venue"
},
  "geometry": {"coordinates":[-82.787803,28.006722],"type":"Point"}
}