{
  "type": "Feature",
  "properties": {
    "iso:country":"US",
    "sg:address":"1440 Howell Branch Rd",
    "sg:city":"Winter Park",
    "sg:classifiers":[
        {
            "category":"Professional",
            "subcategory":"Lawyer & Legal Services",
            "type":"Services"
        }
    ],
    "sg:phone":"+1 407 539 6100",
    "sg:postcode":"32789",
    "sg:province":"FL",
    "wof:name":"Musashe Nicholas A Atty",
    "wof:placetype":"venue"
},
  "geometry": {"coordinates":[-81.334503,28.6248],"type":"Point"}
}