{
  "type": "Feature",
  "properties": {
    "addr:full":"726 Palm St West Palm Beach FL 33401",
    "addr:housenumber":"726",
    "addr:postcode":"33401",
    "addr:street":"Palm St",
    "iso:country":"US",
    "sg:address":"726 Palm St",
    "sg:city":"West Palm Beach",
    "sg:classifiers":[
        {
            "category":"Building & Trades",
            "subcategory":"Construction",
            "type":"Services"
        }
    ],
    "sg:phone":"+1 561 655 7275",
    "sg:postcode":"33401",
    "sg:province":"FL",
    "sg:tags":[
        "contractor"
    ],
    "wof:name":"Restorations of Palm Beaches",
    "wof:placetype":"venue"
},
  "geometry": {"coordinates":[-80.059575,26.699373],"type":"Point"}
}