{
  "type": "Feature",
  "properties": {
    "iso:country":"US",
    "sg:address":"7117 Buck Ln",
    "sg:city":"Panama City",
    "sg:classifiers":[
        {
            "category":"Retail",
            "subcategory":"Repair Shop",
            "type":"Services"
        }
    ],
    "sg:phone":"+1 850 234 8054",
    "sg:postcode":"32408",
    "sg:province":"FL",
    "sg:tags":[
        "motorcycle"
    ],
    "wof:name":"Performance Cycle",
    "wof:placetype":"venue"
},
  "geometry": {"coordinates":[-85.761257,30.184144],"type":"Point"}
}