{
  "type": "Feature",
  "properties": {
    "addr:full":"3241 NW 4th Ct Fort Lauderdale FL 33311",
    "addr:housenumber":"3241",
    "addr:postcode":"33311",
    "addr:street":"Nw 4Th Ct",
    "iso:country":"US",
    "sg:address":"3241 NW 4th Ct",
    "sg:city":"Fort Lauderdale",
    "sg:classifiers":[
        {
            "category":"Building & Trades",
            "subcategory":"Construction",
            "type":"Services"
        }
    ],
    "sg:phone":"+1 954 288 6023",
    "sg:postcode":"33311",
    "sg:province":"FL",
    "sg:tags":[
        "floor",
        "laying",
        "contractor"
    ],
    "wof:name":"Cut To Fit Flooring Inc",
    "wof:placetype":"venue"
},
  "geometry": {"coordinates":[-80.187506,26.1257],"type":"Point"}
}