{
  "type": "Feature",
  "properties": {
    "iso:country":"US",
    "sg:address":"9827 Beach Blvd",
    "sg:city":"Jacksonville",
    "sg:classifiers":[
        {
            "category":"Restaurant",
            "type":"Food & Drink"
        }
    ],
    "sg:phone":"+1 904 996 9224",
    "sg:postcode":"32246",
    "sg:province":"FL",
    "wof:name":"LA Cubana Cafe",
    "wof:placetype":"venue"
},
  "geometry": {"coordinates":[-81.554959,30.286647],"type":"Point"}
}