{
  "type": "Feature",
  "properties": {
    "addr:full":"4494 Southside Blvd Jacksonville FL 32216",
    "addr:housenumber":"4494",
    "addr:postcode":"32216",
    "addr:street":"Southside Blvd",
    "iso:country":"US",
    "sg:address":"4494 Southside Blvd",
    "sg:city":"Jacksonville",
    "sg:classifiers":[
        {
            "category":"Banks & Credit Unions",
            "subcategory":"Investment Brokerage",
            "type":"Services"
        }
    ],
    "sg:phone":"+1 904 641 7143",
    "sg:postcode":"32216",
    "sg:province":"FL",
    "sg:tags":[
        "security"
    ],
    "wof:name":"Ron McCoy",
    "wof:placetype":"venue"
},
  "geometry": {"coordinates":[-81.557973,30.264547],"type":"Point"}
}