{
  "type": "Feature",
  "properties": {
    "addr:full":"1717 N Bayshore Dr Miami FL 33132",
    "addr:housenumber":"1717",
    "addr:postcode":"33132",
    "addr:street":"N Bayshore Dr",
    "iso:country":"US",
    "sg:address":"1717 N Bayshore Dr",
    "sg:city":"Miami",
    "sg:classifiers":[
        {
            "category":"Travel",
            "subcategory":"Hotels & Motels",
            "type":"Entertainment"
        }
    ],
    "sg:phone":"+1 305 372 0313",
    "sg:postcode":"33132",
    "sg:province":"FL",
    "sg:website":"www.biscaynebay.doubletree.com",
    "wof:name":"Doubletree Grand Hotel",
    "wof:placetype":"venue"
},
  "geometry": {"coordinates":[-80.18709699999999,25.791988],"type":"Point"}
}