{
  "type": "Feature",
  "properties": {
    "addr:full":"1551 Lemon St Clearwater FL 33756",
    "addr:housenumber":"1551",
    "addr:postcode":"33756",
    "addr:street":"Lemon St",
    "iso:country":"US",
    "sg:address":"1551 Lemon St",
    "sg:city":"Clearwater",
    "sg:classifiers":[
        {
            "category":"Shopping",
            "type":"Retail Goods"
        }
    ],
    "sg:phone":"+1 727 442 4557",
    "sg:postcode":"33756",
    "sg:province":"FL",
    "sg:tags":[
        "pet",
        "food",
        "supply"
    ],
    "wof:name":"Doggie Door Co",
    "wof:placetype":"venue"
},
  "geometry": {"coordinates":[-82.772406,27.94418],"type":"Point"}
}