{
  "type": "Feature",
  "properties": {
    "iso:country":"US",
    "sg:address":"1295 NW 54th St",
    "sg:city":"Miami",
    "sg:classifiers":[
        {
            "category":"Retail",
            "subcategory":"Laundry & Dry Cleaning",
            "type":"Services"
        }
    ],
    "sg:phone":"+1 305 754 4484",
    "sg:postcode":"33142",
    "sg:province":"FL",
    "sg:tags":[
        "linen",
        "supply"
    ],
    "wof:name":"Royal Linen Svc LLC",
    "wof:placetype":"venue"
},
  "geometry": {"coordinates":[-80.216532,25.824739],"type":"Point"}
}