{
  "type": "Feature",
  "properties": {
    "iso:country":"US",
    "sg:address":"9630 NW 35th St",
    "sg:city":"Coral Springs",
    "sg:classifiers":[
        {
            "category":"Banks & Credit Unions",
            "subcategory":"Bank",
            "type":"Services"
        }
    ],
    "sg:phone":"+1 954 345 3853",
    "sg:postcode":"33065",
    "sg:province":"FL",
    "sg:tags":[
        "loan",
        "real estate"
    ],
    "wof:name":"Windsor Capital Mortgage Corp",
    "wof:placetype":"venue"
},
  "geometry": {"coordinates":[-80.25470900000001,26.273644],"type":"Point"}
}