{
  "type": "Feature",
  "properties": {
    "addr:full":"400 Gator Blvd Belle Glade FL 33430",
    "addr:housenumber":"400",
    "addr:postcode":"33430",
    "addr:street":"Gator Blvd",
    "iso:country":"US",
    "sg:address":"400 Gator Blvd",
    "sg:city":"Belle Glade",
    "sg:classifiers":[
        {
            "category":"Restaurant",
            "type":"Food & Drink"
        }
    ],
    "sg:phone":"+1 561 992 2377",
    "sg:postcode":"33430",
    "sg:province":"FL",
    "sg:tags":[
        "cafeteria"
    ],
    "wof:name":"Glades Day Cafeteria",
    "wof:placetype":"venue"
},
  "geometry": {"coordinates":[-80.66403,26.696745],"type":"Point"}
}