{
  "type": "Feature",
  "properties": {
    "iso:country":"US",
    "sg:address":"526 1st Ave N",
    "sg:city":"Jacksonville Bch",
    "sg:classifiers":[
        {
            "category":"Social Services",
            "type":"Services"
        }
    ],
    "sg:phone":"+1 904 246 5240",
    "sg:postcode":"32250",
    "sg:province":"FL",
    "sg:tags":[
        "organization",
        "welfare"
    ],
    "wof:name":"Society Of St Vincent De Paul",
    "wof:placetype":"venue"
},
  "geometry": {"coordinates":[-81.39522599999999,30.289482],"type":"Point"}
}