{
  "type": "Feature",
  "properties": {
    "iso:country":"US",
    "sg:address":"3990 W Flagler St",
    "sg:city":"Coral Gables",
    "sg:classifiers":[
        {
            "category":"Health Services",
            "subcategory":"Doctor",
            "type":"Services"
        }
    ],
    "sg:phone":"+1 305 569 3206",
    "sg:postcode":"33134",
    "sg:province":"FL",
    "sg:tags":[
        "clinic"
    ],
    "wof:name":"Family Care & Rehabilitation",
    "wof:placetype":"venue"
},
  "geometry": {"coordinates":[-80.261381,25.771644],"type":"Point"}
}