{
  "type": "Feature",
  "properties": {
    "addr:full":"657 S Atlantic Ave Ormond Beach FL 32176",
    "addr:housenumber":"657",
    "addr:postcode":"32176",
    "addr:street":"S Atlantic Ave",
    "iso:country":"US",
    "sg:address":"657 S Atlantic Ave",
    "sg:city":"Ormond Beach",
    "sg:classifiers":[
        {
            "category":"Travel",
            "subcategory":"Hotels & Motels",
            "type":"Entertainment"
        }
    ],
    "sg:phone":"+1 386 677 1331",
    "sg:postcode":"32176",
    "sg:province":"FL",
    "wof:name":"Driftwood Beach Motel",
    "wof:placetype":"venue"
},
  "geometry": {"coordinates":[-81.031012,29.274123],"type":"Point"}
}