{
  "type": "Feature",
  "properties": {
    "addr:full":"2719 NW 54th St Miami FL 33142",
    "addr:housenumber":"2719",
    "addr:postcode":"33142",
    "addr:street":"Nw 54Th St",
    "iso:country":"US",
    "sg:address":"2719 NW 54th St",
    "sg:city":"Miami",
    "sg:classifiers":[
        {
            "category":"Personal",
            "subcategory":"Beauty Salon",
            "type":"Services"
        }
    ],
    "sg:phone":"+1 305 635 9152",
    "sg:postcode":"33142",
    "sg:province":"FL",
    "wof:name":"Eldorado Beauty Salon",
    "wof:placetype":"venue"
},
  "geometry": {"coordinates":[-80.24271400000001,25.823969],"type":"Point"}
}