{
  "type": "Feature",
  "properties": {
    "iso:country":"US",
    "sg:address":"12581 Biscayne Blvd",
    "sg:city":"North Miami",
    "sg:classifiers":[
        {
            "category":"Restaurant",
            "type":"Food & Drink"
        }
    ],
    "sg:phone":"+1 305 893 0650",
    "sg:postcode":"33181",
    "sg:province":"FL",
    "sg:tags":[
        "out"
    ],
    "wof:name":"Brothers Bistro Inc",
    "wof:placetype":"venue"
},
  "geometry": {"coordinates":[-80.162887,25.891814],"type":"Point"}
}