{
  "type": "Feature",
  "properties": {
    "iso:country":"US",
    "sg:address":"7809 N Dale Mabry Hwy",
    "sg:city":"Tampa",
    "sg:classifiers":[
        {
            "category":"Home & Garden",
            "subcategory":"Furniture",
            "type":"Retail Goods"
        }
    ],
    "sg:phone":"+1 813 915 9600",
    "sg:postcode":"33614",
    "sg:province":"FL",
    "wof:name":"Wood-You Furniture",
    "wof:placetype":"venue"
},
  "geometry": {"coordinates":[-82.50489,28.019821],"type":"Point"}
}