{
  "type": "Feature",
  "properties": {
    "iso:country":"US",
    "sg:address":"349 Palmetto St",
    "sg:city":"West Palm Beach",
    "sg:classifiers":[
        {
            "category":"Building & Trades",
            "subcategory":"Plumbing",
            "type":"Services"
        }
    ],
    "sg:phone":"+1 561 309 4239",
    "sg:postcode":"33405",
    "sg:province":"FL",
    "sg:tags":[
        "contractor"
    ],
    "wof:name":"Superior Plumbing Contracting",
    "wof:placetype":"venue"
},
  "geometry": {"coordinates":[-80.053815,26.661005],"type":"Point"}
}