{
  "type": "Feature",
  "properties": {
    "addr:full":"14455 Everhigh Acres Rd Clewiston FL 33440",
    "addr:housenumber":"14455",
    "addr:postcode":"33440",
    "addr:street":"Everhigh Acres Rd",
    "iso:country":"US",
    "sg:address":"14455 Everhigh Acres Rd",
    "sg:city":"Clewiston",
    "sg:classifiers":[
        {
            "category":"Building & Trades",
            "subcategory":"Construction",
            "type":"Services"
        }
    ],
    "sg:phone":"+1 863 902 0964",
    "sg:postcode":"33440",
    "sg:province":"FL",
    "sg:tags":[
        "contractor"
    ],
    "wof:name":"Unique Design Builders",
    "wof:placetype":"venue"
},
  "geometry": {"coordinates":[-81.16181,26.7333],"type":"Point"}
}