{
  "type": "Feature",
  "properties": {
    "iso:country":"US",
    "sg:address":"12577 66th St N",
    "sg:city":"Largo",
    "sg:classifiers":[
        {
            "category":"Manufacturing",
            "subcategory":"Motor Vehicles & Parts",
            "type":"Manufacturing & Wholesale Goods"
        }
    ],
    "sg:phone":"+1 727 530 7300",
    "sg:postcode":"33773",
    "sg:province":"FL",
    "sg:tags":[
        "mfg",
        "trimming"
    ],
    "wof:name":"Aerial Flags",
    "wof:placetype":"venue"
},
  "geometry": {"coordinates":[-82.72904800000001,27.886356],"type":"Point"}
}