{
  "type": "Feature",
  "properties": {
    "iso:country":"US",
    "sg:address":"477 Carroll St",
    "sg:city":"Clermont",
    "sg:classifiers":[
        {
            "category":"Health Services",
            "subcategory":"Health Practitioner",
            "type":"Services"
        }
    ],
    "sg:phone":"+1 352 394 0212",
    "sg:postcode":"34711",
    "sg:province":"FL",
    "sg:tags":[
        "therapist",
        "physical"
    ],
    "sg:website":"www.cfpta.com",
    "wof:name":"Central Florida Pediatric",
    "wof:placetype":"venue"
},
  "geometry": {"coordinates":[-81.761956,28.558238],"type":"Point"}
}