{
  "type": "Feature",
  "properties": {
    "addr:full":"1513 E Commercial Blvd Fort Lauderdale FL 33334",
    "addr:housenumber":"1513",
    "addr:postcode":"33334",
    "addr:street":"E Commercial Blvd",
    "iso:country":"US",
    "sg:address":"1513 E Commercial Blvd",
    "sg:city":"Fort Lauderdale",
    "sg:classifiers":[
        {
            "category":"Shopping",
            "type":"Retail Goods"
        }
    ],
    "sg:phone":"+1 954 771 7010",
    "sg:postcode":"33334",
    "sg:province":"FL",
    "sg:tags":[
        "picture",
        "frame",
        "merchandise",
        "repair"
    ],
    "wof:name":"Art & Frame Shop",
    "wof:placetype":"venue"
},
  "geometry": {"coordinates":[-80.127247,26.189036],"type":"Point"}
}