{
  "type": "Feature",
  "properties": {
    "iso:country":"US",
    "sg:address":"3925 NE 2nd Ave",
    "sg:city":"Miami",
    "sg:classifiers":[
        {
            "category":"Shopping",
            "subcategory":"Used Merchandise",
            "type":"Retail Goods"
        }
    ],
    "sg:phone":"+1 305 573 8118",
    "sg:postcode":"33137",
    "sg:province":"FL",
    "sg:tags":[
        "antique"
    ],
    "sg:website":"www.ethnicdesign.com",
    "wof:name":"Ethnic Design Inc",
    "wof:placetype":"venue"
},
  "geometry": {"coordinates":[-80.19130800000001,25.813292],"type":"Point"}
}