{
  "type": "Feature",
  "properties": {
    "iso:country":"US",
    "sg:address":"1035 Urban Dr",
    "sg:city":"Cantonment",
    "sg:classifiers":[
        {
            "category":"Professional",
            "subcategory":"Business Services",
            "type":"Services"
        }
    ],
    "sg:phone":"+1 850 505 4936",
    "sg:postcode":"32533",
    "sg:province":"FL",
    "sg:tags":[
        "consultant",
        "coach"
    ],
    "wof:name":"Pensacola Mitigation Consultants",
    "wof:placetype":"venue"
},
  "geometry": {"coordinates":[-87.301616,30.554884],"type":"Point"}
}