{
  "type": "Feature",
  "properties": {
    "iso:country":"US",
    "sg:address":"12536 SW 88th St",
    "sg:city":"Miami",
    "sg:classifiers":[
        {
            "category":"Restaurant",
            "type":"Food & Drink"
        }
    ],
    "sg:phone":"+1 305 271 2323",
    "sg:postcode":"33186",
    "sg:province":"FL",
    "sg:tags":[
        "eating"
    ],
    "wof:name":"LA Grotta D'Oro Ristorante",
    "wof:placetype":"venue"
},
  "geometry": {"coordinates":[-80.395899,25.686062],"type":"Point"}
}