{
  "type": "Feature",
  "properties": {
    "addr:full":"1951 Tigertail Blvd Dania FL 33004",
    "addr:housenumber":"1951",
    "addr:postcode":"33004",
    "addr:street":"Tigertail Blvd",
    "iso:country":"US",
    "sg:address":"1951 Tigertail Blvd",
    "sg:city":"Dania",
    "sg:classifiers":[
        {
            "category":"Autos & Motor Vehicles",
            "subcategory":"Automobile Sales",
            "type":"Retail Goods"
        }
    ],
    "sg:phone":"+1 954 925 2400",
    "sg:postcode":"33004",
    "sg:province":"FL",
    "sg:tags":[
        "gas",
        "golf",
        "electric",
        "cart",
        "utility"
    ],
    "sg:website":"www.browardelectriccar.com",
    "wof:name":"Broward Electric Car",
    "wof:placetype":"venue"
},
  "geometry": {"coordinates":[-80.165499,26.053558],"type":"Point"}
}