{
  "type": "Feature",
  "properties": {
    "iso:country":"US",
    "sg:address":"11110 W Oakland Park Blvd",
    "sg:city":"Sunrise",
    "sg:classifiers":[
        {
            "category":"Professional",
            "subcategory":"Computer Services",
            "type":"Services"
        }
    ],
    "sg:phone":"+1 754 264 2951",
    "sg:postcode":"33313",
    "sg:province":"FL",
    "sg:tags":[
        "repair"
    ],
    "sg:website":"www.1stopcomp.com",
    "wof:name":"1STOPCOMP.COM",
    "wof:placetype":"venue"
},
  "geometry": {"coordinates":[-80.29862,26.1682],"type":"Point"}
}