{
  "type": "Feature",
  "properties": {
    "addr:full":"820 Palm Bay Rd NE Palm Bay FL 32905",
    "addr:housenumber":"820",
    "addr:postcode":"32905",
    "addr:street":"Palm Bay Rd Ne",
    "iso:country":"US",
    "sg:address":"820 Palm Bay Rd NE",
    "sg:city":"Palm Bay",
    "sg:classifiers":[
        {
            "category":"Shopping",
            "type":"Retail Goods"
        }
    ],
    "sg:phone":"+1 321 956 1645",
    "sg:postcode":"32905",
    "sg:province":"FL",
    "sg:tags":[
        "pet",
        "shop"
    ],
    "wof:name":"Pets Of The World",
    "wof:placetype":"venue"
},
  "geometry": {"coordinates":[-80.65238600000001,28.035203],"type":"Point"}
}