{
  "type": "Feature",
  "properties": {
    "addr:full":"437 E Sheridan St Dania FL 33004",
    "addr:housenumber":"437",
    "addr:postcode":"33004",
    "addr:street":"E Sheridan St",
    "iso:country":"US",
    "sg:address":"437 E Sheridan St",
    "sg:city":"Dania",
    "sg:classifiers":[
        {
            "category":"Personal",
            "subcategory":"Beauty Salon",
            "type":"Services"
        }
    ],
    "sg:phone":"+1 954 920 6910",
    "sg:postcode":"33004",
    "sg:province":"FL",
    "sg:tags":[
        "manicuring"
    ],
    "wof:name":"Star Nail Inc",
    "wof:placetype":"venue"
},
  "geometry": {"coordinates":[-80.13766200000001,26.033833],"type":"Point"}
}