{
  "type": "Feature",
  "properties": {
    "iso:country":"US",
    "sg:address":"829 Orange Ave",
    "sg:city":"Port Orange",
    "sg:classifiers":[
        {
            "category":"Retail",
            "subcategory":"Auto Rental",
            "type":"Services"
        }
    ],
    "sg:phone":"+1 386 767 1760",
    "sg:postcode":"32129",
    "sg:province":"FL",
    "sg:tags":[
        "mobile",
        "home",
        "leasing"
    ],
    "wof:name":"Daytona Easy Living Mobile Hms",
    "wof:placetype":"venue"
},
  "geometry": {"coordinates":[-80.99279300000001,29.146187],"type":"Point"}
}