{
  "type": "Feature",
  "properties": {
    "iso:country":"US",
    "sg:address":"9737 Vineyard Ct",
    "sg:city":"Boca Raton",
    "sg:classifiers":[
        {
            "category":"Wholesale",
            "subcategory":"Dairy",
            "type":"Manufacturing & Wholesale Goods"
        }
    ],
    "sg:phone":"+1 561 451 8676",
    "sg:postcode":"33428",
    "sg:province":"FL",
    "sg:tags":[
        "ice",
        "cream"
    ],
    "wof:name":"Flamingo Ice Cream Company",
    "wof:placetype":"venue"
},
  "geometry": {"coordinates":[-80.199158,26.348651],"type":"Point"}
}