{
  "type": "Feature",
  "properties": {
    "iso:country":"US",
    "sg:address":"3542 Coral Way",
    "sg:city":"Miami",
    "sg:classifiers":[
        {
            "category":"Health Services",
            "subcategory":"Optometrist",
            "type":"Services"
        }
    ],
    "sg:phone":"+1 305 441 0533",
    "sg:postcode":"33145",
    "sg:province":"FL",
    "wof:name":"Bratter Craig",
    "wof:placetype":"venue"
},
  "geometry": {"coordinates":[-80.251801,25.75],"type":"Point"}
}