{
  "type": "Feature",
  "properties": {
    "iso:country":"US",
    "sg:address":"550 NW 42nd Ave 207",
    "sg:city":"Miami",
    "sg:classifiers":[
        {
            "category":"Professional",
            "subcategory":"Detective & Security Services",
            "type":"Services"
        }
    ],
    "sg:phone":"+1 305 446 3433",
    "sg:postcode":"33126",
    "sg:province":"FL",
    "sg:tags":[
        "guard",
        "patrol"
    ],
    "wof:name":"Us Options",
    "wof:placetype":"venue"
},
  "geometry": {"coordinates":[-80.264031,25.77755],"type":"Point"}
}