{
  "type": "Feature",
  "properties": {
    "iso:country":"US",
    "sg:address":"7955 NW 12th St",
    "sg:city":"Doral",
    "sg:classifiers":[
        {
            "category":"Health Services",
            "subcategory":"Medical Lab",
            "type":"Services"
        }
    ],
    "sg:phone":"+1 305 717 5439",
    "sg:postcode":"33126",
    "sg:province":"FL",
    "wof:name":"Per Se Tech Medical Services Inc",
    "wof:placetype":"venue"
},
  "geometry": {"coordinates":[-80.325613,25.782685],"type":"Point"}
}