{
  "type": "Feature",
  "properties": {
    "iso:country":"US",
    "sg:address":"510 N Ocean Blvd",
    "sg:city":"Pompano Beach",
    "sg:classifiers":[
        {
            "category":"Shopping",
            "subcategory":"Bicycles & Sporting Goods",
            "type":"Retail Goods"
        }
    ],
    "sg:phone":"+1 954 783 1777",
    "sg:postcode":"33062",
    "sg:province":"FL",
    "wof:name":"Km Ski & Bike Adventures",
    "wof:placetype":"venue"
},
  "geometry": {"coordinates":[-80.08870899999999,26.238685],"type":"Point"}
}