{
  "type": "Feature",
  "properties": {
    "iso:country":"US",
    "sg:address":"341 E 34th St",
    "sg:city":"Hialeah",
    "sg:classifiers":[
        {
            "category":"Professional",
            "type":"Services"
        }
    ],
    "sg:phone":"+1 305 888 5869",
    "sg:postcode":"33013",
    "sg:province":"FL",
    "sg:tags":[
        "painting",
        "contractor"
    ],
    "wof:name":"Fine Finishes & Demo Inc",
    "wof:placetype":"venue"
},
  "geometry": {"coordinates":[-80.27583799999999,25.853238],"type":"Point"}
}