{
  "type": "Feature",
  "properties": {
    "iso:country":"US",
    "sg:address":"3138 3rd Ave N",
    "sg:city":"Saint Petersburg",
    "sg:classifiers":[
        {
            "category":"Shopping",
            "subcategory":"Clothing, Apparel, & Fashions",
            "type":"Retail Goods"
        }
    ],
    "sg:phone":"+1 727 323 4499",
    "sg:postcode":"33713",
    "sg:province":"FL",
    "wof:name":"What 2 Wear",
    "wof:placetype":"venue"
},
  "geometry": {"coordinates":[-82.676298,27.77457],"type":"Point"}
}