{
  "type": "Feature",
  "properties": {
    "iso:country":"US",
    "sg:address":"5100 Vivian Pl",
    "sg:city":"Tampa",
    "sg:classifiers":[
        {
            "category":"Freight",
            "type":"Transportation"
        }
    ],
    "sg:phone":"+1 813 248 0777",
    "sg:postcode":"33619",
    "sg:province":"FL",
    "sg:tags":[
        "delivery"
    ],
    "wof:name":"Expedite Transport Svc",
    "wof:placetype":"venue"
},
  "geometry": {"coordinates":[-82.398618,27.923824],"type":"Point"}
}