{
  "type": "Feature",
  "properties": {
    "iso:country":"US",
    "sg:address":"701 N Fort Harrison Ave",
    "sg:city":"Clearwater",
    "sg:classifiers":[
        {
            "category":"Food & Beverages",
            "subcategory":"Specialty",
            "type":"Retail Goods"
        },
        {
            "category":"Food & Beverages",
            "subcategory":"Groceries & Convenience Stores",
            "type":"Retail Goods"
        }
    ],
    "sg:phone":"+1 727 446 5600",
    "sg:postcode":"33755",
    "sg:province":"FL",
    "sg:tags":[
        "grocers-specialty"
    ],
    "wof:name":"Quick Check Food Mart",
    "wof:placetype":"venue"
},
  "geometry": {"coordinates":[-82.79966,27.97262],"type":"Point"}
}