{
  "type": "Feature",
  "properties": {
    "iso:country":"US",
    "sg:address":"18900 SW 114th Ave",
    "sg:city":"Miami",
    "sg:classifiers":[
        {
            "category":"Restaurant",
            "type":"Food & Drink"
        }
    ],
    "sg:phone":"+1 305 253 1182",
    "sg:postcode":"33157",
    "sg:province":"FL",
    "sg:tags":[
        "chinese"
    ],
    "wof:name":"Bowl Le Chinese Restaurant",
    "wof:placetype":"venue"
},
  "geometry": {"coordinates":[-80.377296,25.5914],"type":"Point"}
}