{
  "type": "Feature",
  "properties": {
    "iso:country":"US",
    "sg:address":"8235 NW 201st St",
    "sg:city":"Hialeah",
    "sg:classifiers":[
        {
            "category":"Wholesale",
            "subcategory":"Durable Goods & Equipment",
            "type":"Manufacturing & Wholesale Goods"
        }
    ],
    "sg:phone":"+1 305 829 2299",
    "sg:postcode":"33015",
    "sg:province":"FL",
    "sg:tags":[
        "importer"
    ],
    "wof:name":"Quality Worldwide Imports",
    "wof:placetype":"venue"
},
  "geometry": {"coordinates":[-80.335633,25.956016],"type":"Point"}
}