{
  "type": "Feature",
  "properties": {
    "iso:country":"US",
    "sg:address":"1375 Birch Ct",
    "sg:city":"Lake Mary",
    "sg:classifiers":[
        {
            "category":"Professional",
            "subcategory":"Management & Consulting",
            "type":"Services"
        }
    ],
    "sg:phone":"+1 407 833 8232",
    "sg:postcode":"32714",
    "sg:province":"FL",
    "sg:tags":[
        "consultant",
        "business"
    ],
    "wof:name":"International Center",
    "wof:placetype":"venue"
},
  "geometry": {"coordinates":[-81.411737,28.653255],"type":"Point"}
}