{
  "type": "Feature",
  "properties": {
    "iso:country":"US",
    "sg:address":"1509 SE 27th St",
    "sg:city":"Cape Coral",
    "sg:classifiers":[
        {
            "category":"Education",
            "subcategory":"School",
            "type":"Public Place"
        }
    ],
    "sg:phone":"+1 239 772 3922",
    "sg:postcode":"33904",
    "sg:province":"FL",
    "wof:name":"Saint Andrew Catholic School In Cape Coral",
    "wof:placetype":"venue"
},
  "geometry": {"coordinates":[-81.9431,26.6024],"type":"Point"}
}