{
  "type": "Feature",
  "properties": {
    "iso:country":"US",
    "sg:address":"2345 Sadler Ln",
    "sg:city":"Melbourne",
    "sg:classifiers":[
        {
            "category":"Personal",
            "type":"Services"
        },
        {
            "category":"Building & Trades",
            "subcategory":"Cleaning & Sanitation",
            "type":"Services"
        }
    ],
    "sg:phone":"+1 321 253 8914",
    "sg:postcode":"32935",
    "sg:province":"FL",
    "sg:tags":[
        "house",
        "butlers'",
        "maids'",
        "janitorial"
    ],
    "wof:name":"Aarow Cleaning Service",
    "wof:placetype":"venue"
},
  "geometry": {"coordinates":[-80.660252,28.129043],"type":"Point"}
}