{
  "type": "Feature",
  "properties": {
    "addr:full":"11731 W Brightwater Ct Homosassa FL 34448",
    "addr:housenumber":"11731",
    "addr:postcode":"34448",
    "addr:street":"W Brightwater Ct",
    "iso:country":"US",
    "sg:address":"11731 W Brightwater Ct",
    "sg:city":"Homosassa",
    "sg:classifiers":[
        {
            "category":"Farming",
            "subcategory":"Farm",
            "type":"Manufacturing & Wholesale Goods"
        }
    ],
    "sg:phone":"+1 352 628 9433",
    "sg:postcode":"34448",
    "sg:province":"FL",
    "sg:tags":[
        "crop",
        "general"
    ],
    "wof:name":"Musser Poultry Farm",
    "wof:placetype":"venue"
},
  "geometry": {"coordinates":[-82.627545,28.778788],"type":"Point"}
}