{
  "type": "Feature",
  "properties": {
    "addr:full":"1391 Cinder Ln Kissimmee FL 34744",
    "addr:housenumber":"1391",
    "addr:postcode":"34744",
    "addr:street":"Cinder Ln",
    "iso:country":"US",
    "sg:address":"1391 Cinder Ln",
    "sg:city":"Kissimmee",
    "sg:classifiers":[
        {
            "category":"Wholesale",
            "subcategory":"Vending Machines",
            "type":"Manufacturing & Wholesale Goods"
        }
    ],
    "sg:phone":"+1 407 396 7755",
    "sg:postcode":"34744",
    "sg:province":"FL",
    "wof:name":"Rainbow Enterprises",
    "wof:placetype":"venue"
},
  "geometry": {"coordinates":[-81.317688,28.269815],"type":"Point"}
}