{
  "type": "Feature",
  "properties": {
    "iso:country":"US",
    "sg:address":"111 Brunson Blvd",
    "sg:city":"Cocoa",
    "sg:classifiers":[
        {
            "category":"Manufacturing",
            "subcategory":"Metals",
            "type":"Manufacturing & Wholesale Goods"
        },
        {
            "category":"Building & Trades",
            "subcategory":"Plumbing",
            "type":"Services"
        }
    ],
    "sg:phone":"+1 321 636 5896",
    "sg:postcode":"32922",
    "sg:province":"FL",
    "sg:tags":[
        "fabricator",
        "sheet",
        "contractor"
    ],
    "wof:name":"Jones Sheet Metal Shop Inc",
    "wof:placetype":"venue"
},
  "geometry": {"coordinates":[-80.731512,28.35946],"type":"Point"}
}