{
  "type": "Feature",
  "properties": {
    "iso:country":"US",
    "sg:address":"20 N Orange Ave",
    "sg:city":"Orlando",
    "sg:classifiers":[
        {
            "category":"Real Estate",
            "subcategory":"Real Estate Agent",
            "type":"Services"
        }
    ],
    "sg:phone":"+1 407 254 5454",
    "sg:postcode":"32801",
    "sg:province":"FL",
    "sg:tags":[
        "investment"
    ],
    "wof:name":"Hannover RE Real Estate Inc",
    "wof:placetype":"venue"
},
  "geometry": {"coordinates":[-81.37911200000001,28.542169],"type":"Point"}
}