{
  "type": "Feature",
  "properties": {
    "iso:country":"US",
    "sg:address":"755 Morrissey Dr",
    "sg:city":"Orange City",
    "sg:classifiers":[
        {
            "category":"Banks & Credit Unions",
            "subcategory":"Financial Services",
            "type":"Services"
        }
    ],
    "sg:phone":"+1 386 456 0099",
    "sg:postcode":"32763",
    "sg:province":"FL",
    "sg:tags":[
        "broker",
        "mortgage"
    ],
    "wof:name":"Central Florida Mortgage Service",
    "wof:placetype":"venue"
},
  "geometry": {"coordinates":[-81.297937,28.915799],"type":"Point"}
}