{
  "type": "Feature",
  "properties": {
    "addr:full":"3401 NW 82nd Ave Doral FL 33122",
    "addr:housenumber":"3401",
    "addr:postcode":"33122",
    "addr:street":"Nw 82Nd Ave",
    "iso:country":"US",
    "sg:address":"3401 NW 82nd Ave",
    "sg:city":"Doral",
    "sg:classifiers":[
        {
            "category":"Professional",
            "type":"Services"
        },
        {
            "category":"Travel",
            "subcategory":"Travel Agent",
            "type":"Entertainment"
        }
    ],
    "sg:phone":"+1 305 913 1650",
    "sg:postcode":"33122",
    "sg:province":"FL",
    "sg:tags":[
        "assistance",
        "establishment",
        "road"
    ],
    "wof:name":"Federal Assist Corp",
    "wof:placetype":"venue"
},
  "geometry": {"coordinates":[-80.329165,25.805426],"type":"Point"}
}