{
  "type": "Feature",
  "properties": {
    "addr:full":"1501 Grasslands Blvd # 1 Lakeland FL 33803",
    "addr:housenumber":"1501",
    "addr:postcode":"33803",
    "addr:street":"Grasslands Blvd # 1",
    "iso:country":"US",
    "sg:address":"1501 Grasslands Blvd # 1",
    "sg:city":"Lakeland",
    "sg:classifiers":[
        {
            "category":"Shopping",
            "subcategory":"Clothing, Apparel, & Fashions",
            "type":"Retail Goods"
        }
    ],
    "sg:phone":"+1 336 516 0080",
    "sg:postcode":"33803",
    "sg:province":"FL",
    "sg:tags":[
        "apparel",
        "racing",
        "sportswear",
        "merchandise"
    ],
    "wof:name":"Coockediesel",
    "wof:placetype":"venue"
},
  "geometry": {"coordinates":[-81.97757300000001,28.012841],"type":"Point"}
}