{
  "type": "Feature",
  "properties": {
    "addr:full":"6936 W Eatonshire Path Homosassa FL 34446",
    "addr:housenumber":"6936",
    "addr:postcode":"34446",
    "addr:street":"W Eatonshire Path",
    "iso:country":"US",
    "sg:address":"6936 W Eatonshire Path",
    "sg:city":"Homosassa",
    "sg:classifiers":[
        {
            "category":"Manufacturing",
            "subcategory":"Wood Products",
            "type":"Manufacturing & Wholesale Goods"
        }
    ],
    "sg:phone":"+1 352 382 1322",
    "sg:postcode":"34446",
    "sg:province":"FL",
    "sg:tags":[
        "millwork-wholesale",
        "millwork",
        "manufacturer"
    ],
    "wof:name":"Joes Woodwork",
    "wof:placetype":"venue"
},
  "geometry": {"coordinates":[-82.54882499999999,28.711431],"type":"Point"}
}