{
  "type": "Feature",
  "properties": {
    "iso:country":"US",
    "sg:address":"2620 Blanding Blvd Ste 6",
    "sg:city":"Middleburg",
    "sg:classifiers":[
        {
            "category":"Restaurant",
            "type":"Food & Drink"
        }
    ],
    "sg:phone":"+1 904 406 5646",
    "sg:postcode":"32068",
    "sg:province":"FL",
    "sg:tags":[
        "pizza"
    ],
    "wof:name":"Tony's Pizza",
    "wof:placetype":"venue"
},
  "geometry": {"coordinates":[-81.870791,30.064478],"type":"Point"}
}