{
  "type": "Feature",
  "properties": {
    "iso:country":"US",
    "sg:address":"3597 Edgewood Ave",
    "sg:city":"Fort Myers",
    "sg:classifiers":[
        {
            "category":"Building & Trades",
            "subcategory":"Construction",
            "type":"Services"
        }
    ],
    "sg:phone":"+1 239 334 9184",
    "sg:postcode":"33916",
    "sg:province":"FL",
    "sg:tags":[
        "nonresidential"
    ],
    "wof:name":"Complete Interior Consultants",
    "wof:placetype":"venue"
},
  "geometry": {"coordinates":[-81.843087,26.662757],"type":"Point"}
}