{
  "type": "Feature",
  "properties": {
    "addr:full":"11760 SW 40th St Ste 442 Miami FL 33175",
    "addr:housenumber":"11760",
    "addr:postcode":"33175",
    "addr:street":"Sw 40Th St Ste 442",
    "iso:country":"US",
    "sg:address":"11760 SW 40th St Ste 442",
    "sg:city":"Miami",
    "sg:classifiers":[
        {
            "category":"Health Services",
            "subcategory":"Doctor",
            "type":"Services"
        }
    ],
    "sg:phone":"+1 305 273 7950",
    "sg:postcode":"33175",
    "sg:province":"FL",
    "wof:name":"Martinez Diana MD PA",
    "wof:placetype":"venue"
},
  "geometry": {"coordinates":[-80.386002,25.731899],"type":"Point"}
}