{
  "type": "Feature",
  "properties": {
    "iso:country":"US",
    "sg:address":"3076 Southfork Dr",
    "sg:city":"Apopka",
    "sg:classifiers":[
        {
            "category":"Home & Garden",
            "subcategory":"Garden Supply",
            "type":"Retail Goods"
        }
    ],
    "sg:phone":"+1 407 889 8428",
    "sg:postcode":"32712",
    "sg:province":"FL",
    "sg:tags":[
        "nurseryman"
    ],
    "wof:name":"Tropic Decor",
    "wof:placetype":"venue"
},
  "geometry": {"coordinates":[-81.56196799999999,28.699988],"type":"Point"}
}