{
  "type": "Feature",
  "properties": {
    "addr:full":"1177 Causeway Rd Sanibel FL 33957",
    "addr:housenumber":"1177",
    "addr:postcode":"33957",
    "addr:street":"Causeway Rd",
    "iso:country":"US",
    "sg:address":"1177 Causeway Rd",
    "sg:city":"Sanibel",
    "sg:classifiers":[
        {
            "category":"Real Estate",
            "subcategory":"Real Estate Services",
            "type":"Services"
        },
        {
            "category":"Real Estate",
            "subcategory":"Real Estate Agent",
            "type":"Services"
        }
    ],
    "sg:phone":"+1 239 472 8995",
    "sg:postcode":"33957",
    "sg:province":"FL",
    "sg:tags":[
        "buyer",
        "broker"
    ],
    "wof:name":"Resortquest Southwest Florida",
    "wof:placetype":"venue"
},
  "geometry": {"coordinates":[-82.03786599999999,26.449294],"type":"Point"}
}