{
  "type": "Feature",
  "properties": {
    "iso:country":"US",
    "sg:address":"2460 Ocean Shore Blvd",
    "sg:city":"Ormond Beach",
    "sg:classifiers":[
        {
            "category":"Autos & Motor Vehicles",
            "subcategory":"Fuel & Gas Station",
            "type":"Retail Goods"
        }
    ],
    "sg:phone":"+1 386 441 7109",
    "sg:postcode":"32176",
    "sg:province":"FL",
    "sg:tags":[
        "convenience",
        "store"
    ],
    "wof:name":"Lil Champ 150",
    "wof:placetype":"venue"
},
  "geometry": {"coordinates":[-81.06851399999999,29.353742],"type":"Point"}
}