{
  "type": "Feature",
  "properties": {
    "iso:country":"US",
    "sg:address":"4871 Glover Ln",
    "sg:city":"Milton",
    "sg:classifiers":[
        {
            "category":"Home & Garden",
            "subcategory":"Carpets & Floor Coverings",
            "type":"Retail Goods"
        }
    ],
    "sg:phone":"+1 850 626 7797",
    "sg:postcode":"32570",
    "sg:province":"FL",
    "sg:tags":[
        "rug"
    ],
    "wof:name":"Milton Carpet Center",
    "wof:placetype":"venue"
},
  "geometry": {"coordinates":[-87.059411,30.613853],"type":"Point"}
}