{
  "type": "Feature",
  "properties": {
    "iso:country":"US",
    "sg:address":"75 E 49th St",
    "sg:city":"Hialeah",
    "sg:classifiers":[
        {
            "category":"Banks & Credit Unions",
            "subcategory":"Bank",
            "type":"Services"
        }
    ],
    "sg:phone":"+1 305 826 7620",
    "sg:postcode":"33013",
    "sg:province":"FL",
    "sg:tags":[
        "financing"
    ],
    "wof:name":"C & R Finance Corp",
    "wof:placetype":"venue"
},
  "geometry": {"coordinates":[-80.281092,25.867034],"type":"Point"}
}