{
  "type": "Feature",
  "properties": {
    "addr:full":"333 S State Road 415 Osteen FL 32764",
    "addr:housenumber":"333",
    "addr:postcode":"32764",
    "addr:street":"S State Road 415",
    "iso:country":"US",
    "sg:address":"333 S State Road 415",
    "sg:city":"Osteen",
    "sg:classifiers":[
        {
            "category":"Building & Trades",
            "subcategory":"Electrical",
            "type":"Services"
        }
    ],
    "sg:phone":"+1 407 330 2900",
    "sg:postcode":"32764",
    "sg:province":"FL",
    "sg:tags":[
        "industrial",
        "electrician",
        "contractors-commercial",
        "electric"
    ],
    "wof:name":"T eCC Inc",
    "wof:placetype":"venue"
},
  "geometry": {"coordinates":[-81.168921,28.839196],"type":"Point"}
}