{
  "type": "Feature",
  "properties": {
    "addr:full":"300 W Cam Real Boca Raton FL 33432",
    "addr:housenumber":"300",
    "addr:postcode":"33432",
    "addr:street":"W Cam Real",
    "iso:country":"US",
    "sg:address":"300 W Cam Real",
    "sg:city":"Boca Raton",
    "sg:classifiers":[
        {
            "category":"Food & Beverages",
            "subcategory":"Groceries & Convenience Stores",
            "type":"Retail Goods"
        }
    ],
    "sg:phone":"+1 561 394 5010",
    "sg:postcode":"33432",
    "sg:province":"FL",
    "wof:name":"KWIK Stop Food Store",
    "wof:placetype":"venue"
},
  "geometry": {"coordinates":[-80.09359499999999,26.341905],"type":"Point"}
}