{
  "type": "Feature",
  "properties": {
    "iso:country":"US",
    "sg:address":"261 3rd St SW",
    "sg:city":"Naples",
    "sg:classifiers":[
        {
            "category":"Building & Trades",
            "subcategory":"Pest Control",
            "type":"Services"
        }
    ],
    "sg:phone":"+1 239 455 8444",
    "sg:postcode":"34117",
    "sg:province":"FL",
    "sg:website":"www.personalizedpest.com",
    "wof:name":"Personalized Pest Control Inc",
    "wof:placetype":"venue"
},
  "geometry": {"coordinates":[-81.612855,26.226911],"type":"Point"}
}