{
  "type": "Feature",
  "properties": {
    "iso:country":"US",
    "sg:address":"3015 Apalachee Pkwy",
    "sg:city":"Tallahassee",
    "sg:classifiers":[
        {
            "category":"Food & Beverages",
            "subcategory":"Liquor & Beverages",
            "type":"Retail Goods"
        }
    ],
    "sg:phone":"+1 850 877 8712",
    "sg:postcode":"32301",
    "sg:province":"FL",
    "sg:tags":[
        "alcoholic"
    ],
    "wof:name":"A B C Fine Wine & Spirits 217",
    "wof:placetype":"venue"
},
  "geometry": {"coordinates":[-84.22696000000001,30.427298],"type":"Point"}
}