{
  "type": "Feature",
  "properties": {
    "iso:country":"US",
    "sg:address":"157 SW 57th Ave",
    "sg:city":"Miami",
    "sg:classifiers":[
        {
            "category":"Personal",
            "subcategory":"Beauty Salon",
            "type":"Services"
        }
    ],
    "sg:phone":"+1 305 264 2125",
    "sg:postcode":"33144",
    "sg:province":"FL",
    "wof:name":"Jenny Beauty Salon",
    "wof:placetype":"venue"
},
  "geometry": {"coordinates":[-80.28797900000001,25.76904],"type":"Point"}
}