{
  "type": "Feature",
  "properties": {
    "addr:full":"5751 N Federal Hwy Fort Lauderdale FL 33308",
    "addr:housenumber":"5751",
    "addr:postcode":"33308",
    "addr:street":"N Federal Hwy",
    "iso:country":"US",
    "sg:address":"5751 N Federal Hwy",
    "sg:city":"Fort Lauderdale",
    "sg:classifiers":[
        {
            "category":"Banks & Credit Unions",
            "subcategory":"Investment Brokerage",
            "type":"Services"
        }
    ],
    "sg:phone":"+1 954 566 5519",
    "sg:postcode":"33308",
    "sg:province":"FL",
    "sg:tags":[
        "security"
    ],
    "wof:name":"Deem Investment",
    "wof:placetype":"venue"
},
  "geometry": {"coordinates":[-80.109983,26.200225],"type":"Point"}
}