{
  "type": "Feature",
  "properties": {
    "addr:full":"347 W Granada Blvd Ormond Beach FL 32174",
    "addr:housenumber":"347",
    "addr:postcode":"32174",
    "addr:street":"W Granada Blvd",
    "iso:country":"US",
    "sg:address":"347 W Granada Blvd",
    "sg:city":"Ormond Beach",
    "sg:classifiers":[
        {
            "category":"Banks & Credit Unions",
            "subcategory":"Bank",
            "type":"Services"
        }
    ],
    "sg:phone":"+1 386 615 0080",
    "sg:postcode":"32174",
    "sg:province":"FL",
    "sg:tags":[
        "depository",
        "banking",
        "loan"
    ],
    "wof:name":"Check n Go",
    "wof:placetype":"venue"
},
  "geometry": {"coordinates":[-81.068518,29.280882],"type":"Point"}
}