{
  "type": "Feature",
  "properties": {
    "iso:country":"US",
    "sg:address":"15166 136th Ter N",
    "sg:city":"Jupiter",
    "sg:classifiers":[
        {
            "category":"Building & Trades",
            "subcategory":"Construction",
            "type":"Services"
        }
    ],
    "sg:phone":"+1 561 301 5868",
    "sg:postcode":"33478",
    "sg:province":"FL",
    "sg:tags":[
        "carpenter"
    ],
    "wof:name":"Mark Of Excellence",
    "wof:placetype":"venue"
},
  "geometry": {"coordinates":[-80.250366,26.90159],"type":"Point"}
}