{
  "type": "Feature",
  "properties": {
    "iso:country":"US",
    "sg:address":"5256 Hickory Wood Dr",
    "sg:city":"Naples",
    "sg:classifiers":[
        {
            "category":"Food & Beverages",
            "subcategory":"Groceries & Convenience Stores",
            "type":"Retail Goods"
        },
        {
            "category":"Professional",
            "subcategory":"Business Services",
            "type":"Services"
        }
    ],
    "sg:phone":"+1 239 353 9222",
    "sg:postcode":"34119",
    "sg:province":"FL",
    "sg:tags":[
        "water",
        "treatment"
    ],
    "wof:name":"Hoosier Wawa Co Inc",
    "wof:placetype":"venue"
},
  "geometry": {"coordinates":[-81.71749699999999,26.237532],"type":"Point"}
}