{
  "type": "Feature",
  "properties": {
    "addr:full":"13771 86th Ave N Seminole FL 33776",
    "addr:housenumber":"13771",
    "addr:postcode":"33776",
    "addr:street":"86Th Ave N",
    "iso:country":"US",
    "sg:address":"13771 86th Ave N",
    "sg:city":"Seminole",
    "sg:classifiers":[
        {
            "category":"Building & Trades",
            "subcategory":"Construction",
            "type":"Services"
        }
    ],
    "sg:phone":"+1 727 595 8558",
    "sg:postcode":"33776",
    "sg:province":"FL",
    "sg:tags":[
        "floor",
        "laying",
        "contractor"
    ],
    "wof:name":"Ceramic Life-Style Inc",
    "wof:placetype":"venue"
},
  "geometry": {"coordinates":[-82.830202,27.851156],"type":"Point"}
}