{
  "type": "Feature",
  "properties": {
    "addr:full":"1251 Saxon Blvd Deltona FL 32725",
    "addr:housenumber":"1251",
    "addr:postcode":"32725",
    "addr:street":"Saxon Blvd",
    "iso:country":"US",
    "sg:address":"1251 Saxon Blvd",
    "sg:city":"Deltona",
    "sg:classifiers":[
        {
            "category":"Building & Trades",
            "subcategory":"Construction",
            "type":"Services"
        }
    ],
    "sg:phone":"+1 386 575 0402",
    "sg:postcode":"32725",
    "sg:province":"FL",
    "sg:tags":[
        "contractor"
    ],
    "sg:website":"www.adamshomes.com",
    "wof:name":"Adams Homes of NW Florida",
    "wof:placetype":"venue"
},
  "geometry": {"coordinates":[-81.235603,28.8978],"type":"Point"}
}