{
  "type": "Feature",
  "properties": {
    "iso:country":"US",
    "sg:address":"3228 SW Martin Downs Blvd",
    "sg:city":"Palm City",
    "sg:classifiers":[
        {
            "category":"Real Estate",
            "subcategory":"Real Estate Operator",
            "type":"Services"
        }
    ],
    "sg:phone":"+1 772 221 1673",
    "sg:postcode":"34990",
    "sg:province":"FL",
    "sg:tags":[
        "mobile",
        "home",
        "site"
    ],
    "wof:name":"Bittel Phyllis Lmt",
    "wof:placetype":"venue"
},
  "geometry": {"coordinates":[-80.29517800000001,27.172406],"type":"Point"}
}