{
  "type": "Feature",
  "properties": {
    "addr:full":"4348 NW 4th Ave Pompano Beach FL 33064",
    "addr:housenumber":"4348",
    "addr:postcode":"33064",
    "addr:street":"Nw 4Th Ave",
    "iso:country":"US",
    "sg:address":"4348 NW 4th Ave",
    "sg:city":"Pompano Beach",
    "sg:classifiers":[
        {
            "category":"Professional",
            "type":"Services"
        }
    ],
    "sg:phone":"+1 954 783 2397",
    "sg:postcode":"33064",
    "sg:province":"FL",
    "wof:name":"Drive Him Crazy Corp",
    "wof:placetype":"venue"
},
  "geometry": {"coordinates":[-80.128945,26.286325],"type":"Point"}
}