{
  "type": "Feature",
  "properties": {
    "iso:country":"US",
    "sg:address":"2254 NW 15 Ave",
    "sg:city":"Gainesville",
    "sg:classifiers":[
        {
            "category":"Building & Trades",
            "subcategory":"Landscaping Services",
            "type":"Services"
        }
    ],
    "sg:phone":"+1 352 376 3023",
    "sg:postcode":"32605",
    "sg:province":"FL",
    "wof:name":"4 Seasons Lawn & Tree Service",
    "wof:placetype":"venue"
},
  "geometry": {"coordinates":[-82.354283,29.665845],"type":"Point"}
}