{
  "type": "Feature",
  "properties": {
    "iso:country":"US",
    "sg:address":"20751 State Hwy 520",
    "sg:city":"Orlando",
    "sg:classifiers":[
        {
            "category":"Real Estate",
            "subcategory":"Developer",
            "type":"Services"
        }
    ],
    "sg:phone":"+1 407 568 5868",
    "sg:postcode":"32833",
    "sg:province":"FL",
    "wof:name":"Wedgefield Development Corp",
    "wof:placetype":"venue"
},
  "geometry": {"coordinates":[-81.064797,28.516912],"type":"Point"}
}