{
  "type": "Feature",
  "properties": {
    "addr:full":"9690 NW 25th Ave Miami FL 33147",
    "addr:housenumber":"9690",
    "addr:postcode":"33147",
    "addr:street":"Nw 25Th Ave",
    "iso:country":"US",
    "sg:address":"9690 NW 25th Ave",
    "sg:city":"Miami",
    "sg:classifiers":[
        {
            "category":"Autos & Motor Vehicles",
            "subcategory":"Fuel & Gas Station",
            "type":"Retail Goods"
        }
    ],
    "sg:phone":"+1 305 593 1609",
    "sg:postcode":"33147",
    "sg:province":"FL",
    "wof:name":"97th Avenue Enterprises Mobil",
    "wof:placetype":"venue"
},
  "geometry": {"coordinates":[-80.240286,25.862605],"type":"Point"}
}