{
  "type": "Feature",
  "properties": {
    "iso:country":"US",
    "sg:address":"2901 US Hwy 301",
    "sg:city":"Ellenton",
    "sg:classifiers":[
        {
            "category":"Health Services",
            "subcategory":"Doctor",
            "type":"Services"
        }
    ],
    "sg:phone":"+1 941 729 6818",
    "sg:postcode":"34222",
    "sg:province":"FL",
    "sg:tags":[
        "medical"
    ],
    "wof:name":"Ashok K Dhaduvai MD",
    "wof:placetype":"venue"
},
  "geometry": {"coordinates":[-82.533737,27.521694],"type":"Point"}
}