{
  "type": "Feature",
  "properties": {
    "addr:full":"7610 Isabella Dr Port Richey FL 34668",
    "addr:housenumber":"7610",
    "addr:postcode":"34668",
    "addr:street":"Isabella Dr",
    "iso:country":"US",
    "sg:address":"7610 Isabella Dr",
    "sg:city":"Port Richey",
    "sg:classifiers":[
        {
            "category":"Building & Trades",
            "subcategory":"Cleaning & Sanitation",
            "type":"Services"
        }
    ],
    "sg:phone":"+1 727 858 2514",
    "sg:postcode":"34668",
    "sg:province":"FL",
    "sg:tags":[
        "property",
        "maintenance"
    ],
    "wof:name":"Rafael Carreras Property Mntnc",
    "wof:placetype":"venue"
},
  "geometry": {"coordinates":[-82.688779,28.277521],"type":"Point"}
}