{
  "type": "Feature",
  "properties": {
    "addr:full":"7301 29th Avenue Dr W Bradenton FL 34209",
    "addr:housenumber":"7301",
    "addr:postcode":"34209",
    "addr:street":"29Th Avenue Dr W",
    "iso:country":"US",
    "sg:address":"7301 29th Avenue Dr W",
    "sg:city":"Bradenton",
    "sg:classifiers":[
        {
            "category":"Retail",
            "subcategory":"Repair Shop",
            "type":"Services"
        }
    ],
    "sg:phone":"+1 201 337 3794",
    "sg:postcode":"34209",
    "sg:province":"FL",
    "sg:tags":[
        "machine",
        "envelope"
    ],
    "wof:name":"E M C Industrial",
    "wof:placetype":"venue"
},
  "geometry": {"coordinates":[-82.635442,27.474147],"type":"Point"}
}