{
  "type": "Feature",
  "properties": {
    "iso:country":"US",
    "sg:address":"910 Airport Rd",
    "sg:city":"Destin",
    "sg:classifiers":[
        {
            "category":"Wholesale",
            "subcategory":"Construction Materials",
            "type":"Manufacturing & Wholesale Goods"
        }
    ],
    "sg:phone":"+1 850 654 3186",
    "sg:postcode":"32541",
    "sg:province":"FL",
    "sg:tags":[
        "granite"
    ],
    "wof:name":"Anderson Granite & Marble",
    "wof:placetype":"venue"
},
  "geometry": {"coordinates":[-86.47823099999999,30.396404],"type":"Point"}
}