{
  "type": "Feature",
  "properties": {
    "addr:full":"2642 Leslee Lake Dr N Saint Petersburg FL 33713",
    "addr:housenumber":"2642",
    "addr:postcode":"33713",
    "addr:street":"Leslee Lake Dr N",
    "iso:country":"US",
    "sg:address":"2642 Leslee Lake Dr N",
    "sg:city":"Saint Petersburg",
    "sg:classifiers":[
        {
            "category":"Banks & Credit Unions",
            "subcategory":"Financial Services",
            "type":"Services"
        }
    ],
    "sg:phone":"+1 727 321 1580",
    "sg:postcode":"33713",
    "sg:province":"FL",
    "sg:tags":[
        "trust",
        "management"
    ],
    "wof:name":"Sally I Hott",
    "wof:placetype":"venue"
},
  "geometry": {"coordinates":[-82.69412,27.797056],"type":"Point"}
}