{
  "type": "Feature",
  "properties": {
    "addr:full":"10737 San Bernardino Way Boca Raton FL 33428",
    "addr:housenumber":"10737",
    "addr:postcode":"33428",
    "addr:street":"San Bernardino Way",
    "iso:country":"US",
    "sg:address":"10737 San Bernardino Way",
    "sg:city":"Boca Raton",
    "sg:classifiers":[
        {
            "category":"Real Estate",
            "subcategory":"Real Estate Agent",
            "type":"Services"
        }
    ],
    "sg:phone":"+1 561 479 2577",
    "sg:postcode":"33428",
    "sg:province":"FL",
    "sg:tags":[
        "broker"
    ],
    "wof:name":"Panazona Realty",
    "wof:placetype":"venue"
},
  "geometry": {"coordinates":[-80.215802,26.367301],"type":"Point"}
}