{
  "type": "Feature",
  "properties": {
    "addr:full":"7354 Wisteria Ln Lake Wales FL 33898",
    "addr:housenumber":"7354",
    "addr:postcode":"33898",
    "addr:street":"Wisteria Ln",
    "iso:country":"US",
    "sg:address":"7354 Wisteria Ln",
    "sg:city":"Lake Wales",
    "sg:classifiers":[
        {
            "category":"Building & Trades",
            "subcategory":"Construction",
            "type":"Services"
        }
    ],
    "sg:phone":"+1 863 696 3605",
    "sg:postcode":"33898",
    "sg:province":"FL",
    "sg:tags":[
        "hanging",
        "contractor"
    ],
    "wof:name":"Bridges Painting",
    "wof:placetype":"venue"
},
  "geometry": {"coordinates":[-81.472471,27.876715],"type":"Point"}
}