{
  "type": "Feature",
  "properties": {
    "iso:country":"US",
    "sg:address":"11757 S Orange Blossom Trl",
    "sg:city":"Orlando",
    "sg:classifiers":[
        {
            "category":"Building & Trades",
            "subcategory":"Equipment Rental",
            "type":"Services"
        }
    ],
    "sg:phone":"+1 407 903 2150",
    "sg:postcode":"32837",
    "sg:province":"FL",
    "wof:name":"Ryder",
    "wof:placetype":"venue"
},
  "geometry": {"coordinates":[-81.40451299999999,28.39754],"type":"Point"}
}