{
  "type": "Feature",
  "properties": {
    "addr:full":"1301 SW 70th Ave Miami FL 33144",
    "addr:housenumber":"1301",
    "addr:postcode":"33144",
    "addr:street":"Sw 70Th Ave",
    "iso:country":"US",
    "sg:address":"1301 SW 70th Ave",
    "sg:city":"Miami",
    "sg:classifiers":[
        {
            "category":"Shopping",
            "subcategory":"Music",
            "type":"Retail Goods"
        }
    ],
    "sg:phone":"+1 305 267 5511",
    "sg:postcode":"33144",
    "sg:province":"FL",
    "sg:tags":[
        "dvd's"
    ],
    "sg:website":"www.museodeldisco.com",
    "wof:name":"Museo Del Disco Inc",
    "wof:placetype":"venue"
},
  "geometry": {"coordinates":[-80.308409,25.758386],"type":"Point"}
}