{
  "type": "Feature",
  "properties": {
    "iso:country":"US",
    "sg:address":"5714 29th Ct E",
    "sg:city":"Bradenton",
    "sg:classifiers":[
        {
            "category":"Manufacturing",
            "subcategory":"Printing",
            "type":"Manufacturing & Wholesale Goods"
        }
    ],
    "sg:phone":"+1 941 751 0090",
    "sg:postcode":"34203",
    "sg:province":"FL",
    "sg:tags":[
        "periodical"
    ],
    "wof:name":"Parent Pages Inc",
    "wof:placetype":"venue"
},
  "geometry": {"coordinates":[-82.525913,27.438967],"type":"Point"}
}