{
  "type": "Feature",
  "properties": {
    "iso:country":"US",
    "sg:address":"1530 W Boynton Beach Blvd",
    "sg:city":"Boynton Beach",
    "sg:classifiers":[
        {
            "category":"Government",
            "subcategory":"Post Office",
            "type":"Public Place"
        }
    ],
    "sg:phone":"+1 561 738 5220",
    "sg:postcode":"33436",
    "sg:province":"FL",
    "wof:name":"US Post Office",
    "wof:placetype":"venue"
},
  "geometry": {"coordinates":[-80.09250299999999,26.527624],"type":"Point"}
}