{
  "type": "Feature",
  "properties": {
    "iso:country":"US",
    "sg:address":"260 Crown Oak Centre Dr",
    "sg:city":"Longwood",
    "sg:classifiers":[
        {
            "category":"Wholesale",
            "subcategory":"Machinery & Supplies",
            "type":"Manufacturing & Wholesale Goods"
        },
        {
            "category":"Communications",
            "subcategory":"Film & Video Production",
            "type":"Services"
        }
    ],
    "sg:phone":"+1 407 339 4217",
    "sg:postcode":"32750",
    "sg:province":"FL",
    "sg:tags":[
        "equipment",
        "industrial",
        "book",
        "taping"
    ],
    "wof:name":"Xulon Press Co",
    "wof:placetype":"venue"
},
  "geometry": {"coordinates":[-81.385153,28.69251],"type":"Point"}
}