{
  "type": "Feature",
  "properties": {
    "addr:full":"2575 NW 65th St Miami FL 33147",
    "addr:housenumber":"2575",
    "addr:postcode":"33147",
    "addr:street":"Nw 65Th St",
    "iso:country":"US",
    "sg:address":"2575 NW 65th St",
    "sg:city":"Miami",
    "sg:classifiers":[
        {
            "category":"Organizations",
            "subcategory":"Religious Organization",
            "type":"Services"
        }
    ],
    "sg:phone":"+1 305 693 7779",
    "sg:postcode":"33147",
    "sg:province":"FL",
    "sg:tags":[
        "church"
    ],
    "wof:name":"Millrock Holy Missionary Bapt",
    "wof:placetype":"venue"
},
  "geometry": {"coordinates":[-80.239537,25.83367],"type":"Point"}
}