{
  "type": "Feature",
  "properties": {
    "iso:country":"US",
    "sg:address":"10120 W Forest Hill Blvd",
    "sg:city":"Wellington",
    "sg:classifiers":[
        {
            "category":"Park",
            "type":"Public Place"
        }
    ],
    "sg:phone":"+1 561 793 0280",
    "sg:postcode":"33414",
    "sg:province":"FL",
    "wof:name":"La La Land",
    "wof:placetype":"venue"
},
  "geometry": {"coordinates":[-80.204639,26.650616],"type":"Point"}
}