{
  "type": "Feature",
  "properties": {
    "iso:country":"US",
    "sg:address":"80 SW 8th St",
    "sg:city":"Miami",
    "sg:classifiers":[
        {
            "category":"Organizations",
            "subcategory":"Professional Association",
            "type":"Services"
        }
    ],
    "sg:phone":"+1 305 579 9810",
    "sg:postcode":"33130",
    "sg:province":"FL",
    "sg:tags":[
        "business",
        "trade"
    ],
    "wof:name":"Miami Ventures Ltd",
    "wof:placetype":"venue"
},
  "geometry": {"coordinates":[-80.194931,25.766354],"type":"Point"}
}