{
  "type": "Feature",
  "properties": {
    "iso:country":"US",
    "sg:address":"800 W Morse Blvd",
    "sg:city":"Winter Park",
    "sg:classifiers":[
        {
            "category":"Health Services",
            "subcategory":"Doctor",
            "type":"Services"
        }
    ],
    "sg:phone":"+1 407 628 5400",
    "sg:postcode":"32789",
    "sg:province":"FL",
    "sg:tags":[
        "dental",
        "surgeon"
    ],
    "wof:name":"Tillery Don E Jr DMD",
    "wof:placetype":"venue"
},
  "geometry": {"coordinates":[-81.361024,28.597686],"type":"Point"}
}