{
  "type": "Feature",
  "properties": {
    "addr:full":"330 NW 29th St Fort Lauderdale FL 33311",
    "addr:housenumber":"330",
    "addr:postcode":"33311",
    "addr:street":"Nw 29Th St",
    "iso:country":"US",
    "sg:address":"330 NW 29th St",
    "sg:city":"Fort Lauderdale",
    "sg:classifiers":[
        {
            "category":"Building & Trades",
            "subcategory":"Construction",
            "type":"Services"
        }
    ],
    "sg:phone":"+1 954 581 9644",
    "sg:postcode":"33311",
    "sg:province":"FL",
    "sg:tags":[
        "hanging",
        "contractor"
    ],
    "wof:name":"Connies Party Decorating",
    "wof:placetype":"venue"
},
  "geometry": {"coordinates":[-80.149649,26.162684],"type":"Point"}
}