{
  "type": "Feature",
  "properties": {
    "addr:full":"577 Sutton Rd Auburndale FL 33823",
    "addr:housenumber":"577",
    "addr:postcode":"33823",
    "addr:street":"Sutton Rd",
    "iso:country":"US",
    "sg:address":"577 Sutton Rd",
    "sg:city":"Auburndale",
    "sg:classifiers":[
        {
            "category":"Insurance",
            "subcategory":"Insurance Agent",
            "type":"Services"
        }
    ],
    "sg:phone":"+1 863 965 1002",
    "sg:postcode":"33823",
    "sg:province":"FL",
    "wof:name":"Magnolia Bay Claims Service In",
    "wof:placetype":"venue"
},
  "geometry": {"coordinates":[-81.79562199999999,28.124736],"type":"Point"}
}