{
  "type": "Feature",
  "properties": {
    "addr:full":"9101 NW 7th Ave Suite 10B Miami FL 33150",
    "addr:housenumber":"9101;10b",
    "addr:postcode":"33150",
    "addr:street":"Nw 7Th Ave Suite",
    "iso:country":"US",
    "sg:address":"9101 NW 7th Ave Suite 10B",
    "sg:city":"Miami",
    "sg:classifiers":[
        {
            "category":"Home & Garden",
            "subcategory":"Home Furnishings",
            "type":"Retail Goods"
        }
    ],
    "sg:phone":"+1 305 351 1632",
    "sg:postcode":"33150",
    "sg:province":"FL",
    "sg:tags":[
        "blind",
        "installation",
        "draperies",
        "vertical",
        "curtains",
        "blinds-venetian",
        "window",
        "treatment",
        "shade",
        "curtain"
    ],
    "sg:website":"http://www.servicemagic.com/rated.BudgetBlindsofAventura.15330149.AllCats.html?m=cahscitysrchxm&entry_point_id=479710",
    "wof:name":"Budget Blinds of Aventura",
    "wof:placetype":"venue"
},
  "geometry": {"coordinates":[-80.209586,25.85929],"type":"Point"}
}