{
  "type": "Feature",
  "properties": {
    "addr:full":"5427 Commercial Way Spring Hill FL 34606",
    "addr:housenumber":"5427",
    "addr:postcode":"34606",
    "addr:street":"Commercial Way",
    "iso:country":"US",
    "sg:address":"5427 Commercial Way",
    "sg:city":"Spring Hill",
    "sg:classifiers":[
        {
            "category":"Health Services",
            "subcategory":"Health Practitioner",
            "type":"Services"
        },
        {
            "category":"Social Services",
            "type":"Services"
        }
    ],
    "sg:phone":"+1 352 596 9616",
    "sg:postcode":"34606",
    "sg:province":"FL",
    "sg:tags":[
        "psychologist"
    ],
    "wof:name":"Peal Ronald L PHD",
    "wof:placetype":"venue"
},
  "geometry": {"coordinates":[-82.583187,28.507741],"type":"Point"}
}