{
  "type": "Feature",
  "properties": {
    "addr:full":"777 Palm St West Palm Beach FL 33401",
    "addr:housenumber":"777",
    "addr:postcode":"33401",
    "addr:street":"Palm St",
    "iso:country":"US",
    "sg:address":"777 Palm St",
    "sg:city":"West Palm Beach",
    "sg:classifiers":[
        {
            "category":"Banks & Credit Unions",
            "subcategory":"Investment Brokerage",
            "type":"Services"
        }
    ],
    "sg:phone":"+1 561 820 2187",
    "sg:postcode":"33401",
    "sg:province":"FL",
    "sg:tags":[
        "advisory",
        "security"
    ],
    "wof:name":"Bernstine Investment RES & MGT",
    "wof:placetype":"venue"
},
  "geometry": {"coordinates":[-80.05867499999999,26.699486],"type":"Point"}
}