{
  "type": "Feature",
  "properties": {
    "addr:full":"5709 Georgia Ave West Palm Beach FL 33405",
    "addr:housenumber":"5709",
    "addr:postcode":"33405",
    "addr:street":"Georgia Ave",
    "iso:country":"US",
    "sg:address":"5709 Georgia Ave",
    "sg:city":"West Palm Beach",
    "sg:classifiers":[
        {
            "category":"Wholesale",
            "subcategory":"Plants",
            "type":"Manufacturing & Wholesale Goods"
        }
    ],
    "sg:phone":"+1 561 547 9495",
    "sg:postcode":"33405",
    "sg:province":"FL",
    "sg:tags":[
        "florist",
        "flower",
        "supply"
    ],
    "wof:name":"Anything But Ordinary",
    "wof:placetype":"venue"
},
  "geometry": {"coordinates":[-80.058941,26.662569],"type":"Point"}
}