{
  "type": "Feature",
  "properties": {
    "iso:country":"US",
    "sg:address":"17358 Dixie Hwy",
    "sg:city":"Palmetto Bay",
    "sg:classifiers":[
        {
            "category":"Utilities",
            "subcategory":"Mobile Phone",
            "type":"Services"
        }
    ],
    "sg:phone":"+1 305 255 5677",
    "sg:postcode":"33157",
    "sg:province":"FL",
    "sg:tags":[
        "repair",
        "beeper"
    ],
    "wof:name":"Ace Communications Inc",
    "wof:placetype":"venue"
},
  "geometry": {"coordinates":[-80.349754,25.60858],"type":"Point"}
}