{
  "type": "Feature",
  "properties": {
    "iso:country":"US",
    "sg:address":"1701 James Ave",
    "sg:city":"Miami Beach",
    "sg:classifiers":[
        {
            "category":"Travel",
            "subcategory":"Hotels & Motels",
            "type":"Entertainment"
        }
    ],
    "sg:phone":"+1 305 672 6688",
    "sg:postcode":"33139",
    "sg:province":"FL",
    "sg:website":"www.cadethotel.com",
    "wof:name":"Cadet Hotel",
    "wof:placetype":"venue"
},
  "geometry": {"coordinates":[-80.130898,25.792801],"type":"Point"}
}