{
  "type": "Feature",
  "properties": {
    "iso:country":"US",
    "sg:address":"300 Mc Lain Ln",
    "sg:city":"Geneva",
    "sg:classifiers":[
        {
            "category":"Building & Trades",
            "subcategory":"Cleaning & Sanitation",
            "type":"Services"
        }
    ],
    "sg:phone":"+1 407 349 3768",
    "sg:postcode":"32732",
    "sg:province":"FL",
    "sg:tags":[
        "maintenance"
    ],
    "wof:name":"Marty Frazier Maintenance",
    "wof:placetype":"venue"
},
  "geometry": {"coordinates":[-81.122387,28.711074],"type":"Point"}
}