{
  "type": "Feature",
  "properties": {
    "addr:full":"12510 NE Jacksonville Rd Anthony FL 32617",
    "addr:housenumber":"12510",
    "addr:postcode":"32617",
    "addr:street":"Ne Jacksonville Rd",
    "iso:country":"US",
    "sg:address":"12510 NE Jacksonville Rd",
    "sg:city":"Anthony",
    "sg:classifiers":[
        {
            "category":"Farming",
            "subcategory":"Livestock Farm",
            "type":"Manufacturing & Wholesale Goods"
        },
        {
            "category":"Arena",
            "subcategory":"Horse Racetrack",
            "type":"Entertainment"
        }
    ],
    "sg:phone":"+1 352 732 2688",
    "sg:postcode":"32617",
    "sg:province":"FL",
    "sg:tags":[
        "breeder"
    ],
    "wof:name":"Seabreeze Horse & Cattle Farm",
    "wof:placetype":"venue"
},
  "geometry": {"coordinates":[-82.112802,29.330462],"type":"Point"}
}