{
  "type": "Feature",
  "properties": {
    "iso:country":"US",
    "sg:address":"2329 Yule Tree Dr",
    "sg:city":"Edgewater",
    "sg:classifiers":[
        {
            "category":"Shopping",
            "subcategory":"Gifts & Souvenirs",
            "type":"Retail Goods"
        }
    ],
    "sg:phone":"+1 386 428 8990",
    "sg:postcode":"32141",
    "sg:province":"FL",
    "sg:tags":[
        "merchandise",
        "general"
    ],
    "wof:name":"Benco",
    "wof:placetype":"venue"
},
  "geometry": {"coordinates":[-80.912211,28.954658],"type":"Point"}
}