{
  "type": "Feature",
  "properties": {
    "addr:full":"11951 S Apopka Vineland Rd Orlando FL 32836",
    "addr:housenumber":"11951",
    "addr:postcode":"32836",
    "addr:street":"S Apopka Vineland Rd",
    "iso:country":"US",
    "sg:address":"11951 S Apopka Vineland Rd",
    "sg:city":"Orlando",
    "sg:classifiers":[
        {
            "category":"Food & Beverages",
            "subcategory":"Liquor & Beverages",
            "type":"Retail Goods"
        }
    ],
    "sg:phone":"+1 407 239 0775",
    "sg:postcode":"32836",
    "sg:province":"FL",
    "sg:tags":[
        "alcoholic"
    ],
    "wof:name":"A B C Fine Wine & Spirits 4",
    "wof:placetype":"venue"
},
  "geometry": {"coordinates":[-81.506021,28.391861],"type":"Point"}
}