{
  "type": "Feature",
  "properties": {
    "iso:country":"US",
    "sg:address":"14405 NW 7th Ave",
    "sg:city":"Miami",
    "sg:classifiers":[
        {
            "category":"Shopping",
            "subcategory":"Pets & Pet Supplies",
            "type":"Retail Goods"
        }
    ],
    "sg:phone":"+1 305 681 8266",
    "sg:postcode":"33168",
    "sg:province":"FL",
    "sg:tags":[
        "store"
    ],
    "wof:name":"Pet Fair Pet Shops",
    "wof:placetype":"venue"
},
  "geometry": {"coordinates":[-80.211321,25.906793],"type":"Point"}
}