{
  "type": "Feature",
  "properties": {
    "addr:full":"5500 Park Ridge Blvd Boynton Beach FL 33426",
    "addr:housenumber":"5500",
    "addr:postcode":"33426",
    "addr:street":"Park Ridge Blvd",
    "iso:country":"US",
    "sg:address":"5500 Park Ridge Blvd",
    "sg:city":"Boynton Beach",
    "sg:classifiers":[
        {
            "category":"Freight",
            "type":"Transportation"
        },
        {
            "category":"Professional",
            "subcategory":"Advertising",
            "type":"Services"
        }
    ],
    "sg:phone":"+1 561 369 7900",
    "sg:postcode":"33426",
    "sg:province":"FL",
    "sg:tags":[
        "distribution",
        "grocery",
        "general"
    ],
    "wof:name":"Publix Distribution Center",
    "wof:placetype":"venue"
},
  "geometry": {"coordinates":[-80.08372799999999,26.545721],"type":"Point"}
}