{
  "type": "Feature",
  "properties": {
    "iso:country":"US",
    "sg:address":"407 SW 2nd St",
    "sg:city":"Cape Coral",
    "sg:classifiers":[
        {
            "category":"Professional",
            "subcategory":"Business Services",
            "type":"Services"
        },
        {
            "category":"Wholesale",
            "subcategory":"Chemicals & Plastics",
            "type":"Manufacturing & Wholesale Goods"
        }
    ],
    "sg:phone":"+1 239 574 2214",
    "sg:postcode":"33991",
    "sg:province":"FL",
    "sg:tags":[
        "water",
        "equipment",
        "treatment"
    ],
    "wof:name":"Ted Mahr Supply Inc",
    "wof:placetype":"venue"
},
  "geometry": {"coordinates":[-81.98376500000001,26.646217],"type":"Point"}
}