{
  "type": "Feature",
  "properties": {
    "addr:full":"3004 NW 72nd Ave Miami FL 33122",
    "addr:housenumber":"3004",
    "addr:postcode":"33122",
    "addr:street":"Nw 72Nd Ave",
    "iso:country":"US",
    "sg:address":"3004 NW 72nd Ave",
    "sg:city":"Miami",
    "sg:classifiers":[
        {
            "category":"Shopping",
            "subcategory":"Computers & Home Electronics",
            "type":"Retail Goods"
        }
    ],
    "sg:phone":"+1 305 592 5553",
    "sg:postcode":"33122",
    "sg:province":"FL",
    "sg:tags":[
        "equipment",
        "dealer"
    ],
    "wof:name":"Focus Solutions Corp",
    "wof:placetype":"venue"
},
  "geometry": {"coordinates":[-80.31315499999999,25.802513],"type":"Point"}
}