{
  "type": "Feature",
  "properties": {
    "iso:country":"US",
    "sg:address":"2701 W Busch Blvd",
    "sg:city":"Tampa",
    "sg:classifiers":[
        {
            "category":"Social Services",
            "type":"Services"
        }
    ],
    "sg:phone":"+1 813 935 1721",
    "sg:postcode":"33618",
    "sg:province":"FL",
    "sg:tags":[
        "counselor",
        "marriage",
        "family"
    ],
    "wof:name":"Marianne Rudzewicz",
    "wof:placetype":"venue"
},
  "geometry": {"coordinates":[-82.487773,28.035023],"type":"Point"}
}