{
  "type": "Feature",
  "properties": {
    "iso:country":"US",
    "sg:address":"1300 S Lecanto Hwy",
    "sg:city":"Lecanto",
    "sg:classifiers":[
        {
            "category":"Real Estate",
            "subcategory":"Real Estate Services",
            "type":"Services"
        },
        {
            "category":"Building & Trades",
            "subcategory":"Cleaning & Sanitation",
            "type":"Services"
        }
    ],
    "sg:phone":"+1 352 527 0333",
    "sg:postcode":"34461",
    "sg:province":"FL",
    "sg:tags":[
        "maintenance",
        "cleaners-interior"
    ],
    "wof:name":"Maintenance Operations",
    "wof:placetype":"venue"
},
  "geometry": {"coordinates":[-82.487793,28.84391],"type":"Point"}
}