{
  "type": "Feature",
  "properties": {
    "iso:country":"US",
    "sg:address":"2290 Laurel Run Dr",
    "sg:city":"Ocala",
    "sg:classifiers":[
        {
            "category":"Real Estate",
            "subcategory":"Real Estate Operator",
            "type":"Services"
        }
    ],
    "sg:phone":"+1 352 629 5709",
    "sg:postcode":"34471",
    "sg:province":"FL",
    "sg:tags":[
        "property",
        "lessor"
    ],
    "wof:name":"Andrews Farm Venture",
    "wof:placetype":"venue"
},
  "geometry": {"coordinates":[-82.108677,29.165258],"type":"Point"}
}