{
  "type": "Feature",
  "properties": {
    "addr:full":"5290 NW 72nd Ave Miami FL 33166",
    "addr:housenumber":"5290",
    "addr:postcode":"33166",
    "addr:street":"Nw 72Nd Ave",
    "iso:country":"US",
    "sg:address":"5290 NW 72nd Ave",
    "sg:city":"Miami",
    "sg:classifiers":[
        {
            "category":"Shopping",
            "subcategory":"Crafts & Fabrics",
            "type":"Retail Goods"
        },
        {
            "category":"Manufacturing",
            "subcategory":"Pottery",
            "type":"Manufacturing & Wholesale Goods"
        }
    ],
    "sg:phone":"+1 305 597 8310",
    "sg:postcode":"33166",
    "sg:province":"FL",
    "sg:tags":[
        "products-decorative",
        "ceramics-equipment",
        "ceramic",
        "art",
        "supply"
    ],
    "wof:name":"Lisang Ceramic",
    "wof:placetype":"venue"
},
  "geometry": {"coordinates":[-80.31368399999999,25.821278],"type":"Point"}
}