{
  "type": "Feature",
  "properties": {
    "addr:full":"3910 W Morrison Ave Tampa FL 33629",
    "addr:housenumber":"3910",
    "addr:postcode":"33629",
    "addr:street":"W Morrison Ave",
    "iso:country":"US",
    "sg:address":"3910 W Morrison Ave",
    "sg:city":"Tampa",
    "sg:classifiers":[
        {
            "category":"Education",
            "subcategory":"School",
            "type":"Public Place"
        }
    ],
    "sg:phone":"+1 813 872 5325",
    "sg:postcode":"33629",
    "sg:province":"FL",
    "wof:name":"Henry W Grady School",
    "wof:placetype":"venue"
},
  "geometry": {"coordinates":[-82.50976199999999,27.933839],"type":"Point"}
}