{
  "type": "Feature",
  "properties": {
    "addr:full":"1902 SE 15th Ter Cape Coral FL 33990",
    "addr:housenumber":"1902",
    "addr:postcode":"33990",
    "addr:street":"Se 15Th Ter",
    "iso:country":"US",
    "sg:address":"1902 SE 15th Ter",
    "sg:city":"Cape Coral",
    "sg:classifiers":[
        {
            "category":"Organizations",
            "subcategory":"Community Association",
            "type":"Services"
        }
    ],
    "sg:phone":"+1 239 574 5998",
    "sg:postcode":"33990",
    "sg:province":"FL",
    "wof:name":"Order of Amaranth Inc Sup",
    "wof:placetype":"venue"
},
  "geometry": {"coordinates":[-81.93742399999999,26.624162],"type":"Point"}
}