{
  "type": "Feature",
  "properties": {
    "iso:country":"US",
    "sg:address":"2223 NE 5th Ter",
    "sg:city":"Cape Coral",
    "sg:classifiers":[
        {
            "category":"Wholesale",
            "subcategory":"Machinery & Supplies",
            "type":"Manufacturing & Wholesale Goods"
        },
        {
            "category":"Building & Trades",
            "subcategory":"Construction",
            "type":"Services"
        }
    ],
    "sg:phone":"+1 239 549 1050",
    "sg:postcode":"33909",
    "sg:province":"FL",
    "sg:tags":[
        "industrial",
        "deck",
        "equipment",
        "restoration",
        "cleaning",
        "patio"
    ],
    "wof:name":"Benson's Pressure Cleaning",
    "wof:placetype":"venue"
},
  "geometry": {"coordinates":[-81.92564299999999,26.662273],"type":"Point"}
}