{
  "type": "Feature",
  "properties": {
    "addr:full":"2151 E Commercial Blvd Fort Lauderdale FL 33308",
    "addr:housenumber":"2151",
    "addr:postcode":"33308",
    "addr:street":"E Commercial Blvd",
    "iso:country":"US",
    "sg:address":"2151 E Commercial Blvd",
    "sg:city":"Fort Lauderdale",
    "sg:classifiers":[
        {
            "category":"Health Services",
            "subcategory":"Doctor",
            "type":"Services"
        }
    ],
    "sg:phone":"+1 954 727 2008",
    "sg:postcode":"33308",
    "sg:province":"FL",
    "sg:tags":[
        "physician",
        "surgeon"
    ],
    "wof:name":"Renewal Medical Specialists",
    "wof:placetype":"venue"
},
  "geometry": {"coordinates":[-80.113518,26.189638],"type":"Point"}
}