{
  "type": "Feature",
  "properties": {
    "addr:full":"7500 Sun Island Dr S Saint Petersburg FL 33707",
    "addr:housenumber":"7500",
    "addr:postcode":"33707",
    "addr:street":"Sun Island Dr S",
    "iso:country":"US",
    "sg:address":"7500 Sun Island Dr S",
    "sg:city":"Saint Petersburg",
    "sg:classifiers":[
        {
            "category":"Organizations",
            "subcategory":"Community Association",
            "type":"Services"
        }
    ],
    "sg:phone":"+1 727 360 2751",
    "sg:postcode":"33707",
    "sg:province":"FL",
    "wof:name":"Bay Island Condos",
    "wof:placetype":"venue"
},
  "geometry": {"coordinates":[-82.74489699999999,27.751175],"type":"Point"}
}