{
  "type": "Feature",
  "properties": {
    "iso:country":"US",
    "sg:address":"2649 Hollywood Blvd",
    "sg:city":"Hollywood",
    "sg:classifiers":[
        {
            "category":"Restaurant",
            "type":"Food & Drink"
        }
    ],
    "sg:phone":"+1 954 921 9483",
    "sg:postcode":"33020",
    "sg:province":"FL",
    "sg:tags":[
        "eating"
    ],
    "wof:name":"J P's Bagel Place",
    "wof:placetype":"venue"
},
  "geometry": {"coordinates":[-80.160389,26.011254],"type":"Point"}
}