{
  "type": "Feature",
  "properties": {
    "iso:country":"US",
    "sg:address":"10350 W Bay Harbor Dr",
    "sg:city":"Miami Beach",
    "sg:classifiers":[
        {
            "category":"Real Estate",
            "subcategory":"Real Estate Agent",
            "type":"Services"
        }
    ],
    "sg:phone":"+1 305 993 1300",
    "sg:postcode":"33154",
    "sg:province":"FL",
    "wof:name":"Island Pointe Realty LLC",
    "wof:placetype":"venue"
},
  "geometry": {"coordinates":[-80.133641,25.892688],"type":"Point"}
}