{
  "type": "Feature",
  "properties": {
    "addr:full":"15025 SW 232nd St Miami FL 33170",
    "addr:housenumber":"15025",
    "addr:postcode":"33170",
    "addr:street":"Sw 232Nd St",
    "iso:country":"US",
    "sg:address":"15025 SW 232nd St",
    "sg:city":"Miami",
    "sg:classifiers":[
        {
            "category":"Farming",
            "subcategory":"Farm",
            "type":"Manufacturing & Wholesale Goods"
        }
    ],
    "sg:phone":"+1 305 248 4901",
    "sg:postcode":"33170",
    "sg:province":"FL",
    "sg:tags":[
        "crop",
        "general"
    ],
    "wof:name":"Case Brothers Farms",
    "wof:placetype":"venue"
},
  "geometry": {"coordinates":[-80.435778,25.551077],"type":"Point"}
}