{
  "type": "Feature",
  "properties": {
    "addr:full":"2420 N Federal Hwy Fort Lauderdale FL 33305",
    "addr:housenumber":"2420",
    "addr:postcode":"33305",
    "addr:street":"N Federal Hwy",
    "iso:country":"US",
    "sg:address":"2420 N Federal Hwy",
    "sg:city":"Fort Lauderdale",
    "sg:classifiers":[
        {
            "category":"Food & Beverages",
            "subcategory":"Groceries & Convenience Stores",
            "type":"Retail Goods"
        }
    ],
    "sg:phone":"+1 954 564 0460",
    "sg:postcode":"33305",
    "sg:province":"FL",
    "sg:tags":[
        "supermarket"
    ],
    "wof:name":"Winn-Dixie",
    "wof:placetype":"venue"
},
  "geometry": {"coordinates":[-80.11810800000001,26.154895],"type":"Point"}
}