{
  "type": "Feature",
  "properties": {
    "addr:full":"350 N Pine Meadow Dr Debary FL 32713",
    "addr:housenumber":"350",
    "addr:postcode":"32713",
    "addr:street":"N Pine Meadow Dr",
    "iso:country":"US",
    "sg:address":"350 N Pine Meadow Dr",
    "sg:city":"Debary",
    "sg:classifiers":[
        {
            "category":"Real Estate",
            "subcategory":"Real Estate Agent",
            "type":"Services"
        }
    ],
    "sg:phone":"+1 386 668 8843",
    "sg:postcode":"32713",
    "sg:province":"FL",
    "sg:website":"www.todayhomes.com",
    "wof:name":"Today Homes Inc",
    "wof:placetype":"venue"
},
  "geometry": {"coordinates":[-81.304192,28.897158],"type":"Point"}
}