{
  "type": "Feature",
  "properties": {
    "addr:full":"2128 W Flagler St Miami FL 33135",
    "addr:housenumber":"2128",
    "addr:postcode":"33135",
    "addr:street":"W Flagler St",
    "iso:country":"US",
    "sg:address":"2128 W Flagler St",
    "sg:city":"Miami",
    "sg:classifiers":[
        {
            "category":"Utilities",
            "subcategory":"Telephone",
            "type":"Services"
        }
    ],
    "sg:phone":"+1 305 649 3338",
    "sg:postcode":"33135",
    "sg:province":"FL",
    "sg:tags":[
        "company"
    ],
    "wof:name":"Prima Phone",
    "wof:placetype":"venue"
},
  "geometry": {"coordinates":[-80.230898,25.772493],"type":"Point"}
}