{
  "type": "Feature",
  "properties": {
    "addr:full":"3115 Saddle Creek Rd Lakeland FL 33801",
    "addr:housenumber":"3115",
    "addr:postcode":"33801",
    "addr:street":"Saddle Creek Rd",
    "iso:country":"US",
    "sg:address":"3115 Saddle Creek Rd",
    "sg:city":"Lakeland",
    "sg:classifiers":[
        {
            "category":"Retail",
            "subcategory":"Auto Repair",
            "type":"Services"
        }
    ],
    "sg:phone":"+1 863 665 4475",
    "sg:postcode":"33801",
    "sg:province":"FL",
    "sg:tags":[
        "body",
        "glass",
        "replacement"
    ],
    "wof:name":"McCawleys Auto Upholstery",
    "wof:placetype":"venue"
},
  "geometry": {"coordinates":[-81.89892399999999,28.073386],"type":"Point"}
}