{
  "type": "Feature",
  "properties": {
    "addr:full":"502 N Spring Garden Ave Ste 2 Deland FL 32720",
    "addr:housenumber":"502",
    "addr:postcode":"32720",
    "addr:street":"N Spring Garden Ave Ste 2",
    "iso:country":"US",
    "sg:address":"502 N Spring Garden Ave Ste 2",
    "sg:city":"Deland",
    "sg:classifiers":[
        {
            "category":"Professional",
            "type":"Services"
        },
        {
            "category":"Food & Beverages",
            "subcategory":"Bakery",
            "type":"Retail Goods"
        }
    ],
    "sg:phone":"+1 386 734 0343",
    "sg:postcode":"32720",
    "sg:province":"FL",
    "sg:tags":[
        "sandwich",
        "caterer"
    ],
    "wof:name":"Sub City",
    "wof:placetype":"venue"
},
  "geometry": {"coordinates":[-81.32463799999999,29.035264],"type":"Point"}
}