{
  "type": "Feature",
  "properties": {
    "addr:full":"1311 N West Shore Blvd Tampa FL 33607",
    "addr:housenumber":"1311",
    "addr:postcode":"33607",
    "addr:street":"N West Shore Blvd",
    "iso:country":"US",
    "sg:address":"1311 N West Shore Blvd",
    "sg:city":"Tampa",
    "sg:classifiers":[
        {
            "category":"Education",
            "subcategory":"Special Training",
            "type":"Public Place"
        }
    ],
    "sg:phone":"+1 813 289 8489",
    "sg:postcode":"33607",
    "sg:province":"FL",
    "sg:tags":[
        "development",
        "economic",
        "enhancement"
    ],
    "wof:name":"Florida Cncil On Ecnmic Edcatn",
    "wof:placetype":"venue"
},
  "geometry": {"coordinates":[-82.524073,27.95287],"type":"Point"}
}