{
  "type": "Feature",
  "properties": {
    "addr:full":"11475 SW 40th St Miami FL 33165",
    "addr:housenumber":"11475",
    "addr:postcode":"33165",
    "addr:street":"Sw 40Th St",
    "iso:country":"US",
    "sg:address":"11475 SW 40th St",
    "sg:city":"Miami",
    "sg:classifiers":[
        {
            "category":"Retail",
            "subcategory":"Laundry & Dry Cleaning",
            "type":"Services"
        }
    ],
    "sg:phone":"+1 305 228 6021",
    "sg:postcode":"33165",
    "sg:province":"FL",
    "sg:tags":[
        "laundries-self",
        "operated",
        "washer",
        "dryer",
        "coin"
    ],
    "wof:name":"Jorge Zagastizabal Coin Laundr",
    "wof:placetype":"venue"
},
  "geometry": {"coordinates":[-80.380551,25.732175],"type":"Point"}
}