{
  "type": "Feature",
  "properties": {
    "iso:country":"US",
    "sg:address":"1191 NE 200th Ter",
    "sg:city":"Miami",
    "sg:classifiers":[
        {
            "category":"Communications",
            "subcategory":"Film & Video Production",
            "type":"Services"
        }
    ],
    "sg:phone":"+1 305 651 2753",
    "sg:postcode":"33179",
    "sg:province":"FL",
    "sg:tags":[
        "motion"
    ],
    "wof:name":"Claquette Productions Inc",
    "wof:placetype":"venue"
},
  "geometry": {"coordinates":[-80.1798,25.960446],"type":"Point"}
}