{
  "type": "Feature",
  "properties": {
    "iso:country":"US",
    "sg:address":"5801 N Florida Ave",
    "sg:city":"Miami",
    "sg:classifiers":[
        {
            "category":"Building & Trades",
            "subcategory":"Locksmith",
            "type":"Services"
        }
    ],
    "sg:phone":"+1 866 583 8355",
    "sg:postcode":"33145",
    "sg:province":"FL",
    "sg:tags":[
        "key"
    ],
    "wof:name":"Emergency 24 Hour 7 Day Locksmith",
    "wof:placetype":"venue"
},
  "geometry": {"coordinates":[-80.25426299999999,25.853777],"type":"Point"}
}