{
  "type": "Feature",
  "properties": {
    "addr:full":"6820 US Hwy 27 Sebring FL 33870",
    "addr:housenumber":"6820",
    "addr:postcode":"33870",
    "addr:street":"Us Hwy 27",
    "iso:country":"US",
    "sg:address":"6820 US Hwy 27",
    "sg:city":"Sebring",
    "sg:classifiers":[
        {
            "category":"Building & Trades",
            "subcategory":"Construction",
            "type":"Services"
        }
    ],
    "sg:phone":"+1 863 386 4499",
    "sg:postcode":"33870",
    "sg:province":"FL",
    "sg:tags":[
        "general",
        "contractor"
    ],
    "wof:name":"Mills Construction",
    "wof:placetype":"venue"
},
  "geometry": {"coordinates":[-81.50400500000001,27.539614],"type":"Point"}
}