{
  "type": "Feature",
  "properties": {
    "addr:full":"506 W Canal St Mulberry FL 33860",
    "addr:housenumber":"506",
    "addr:postcode":"33860",
    "addr:street":"W Canal St",
    "iso:country":"US",
    "sg:address":"506 W Canal St",
    "sg:city":"Mulberry",
    "sg:classifiers":[
        {
            "category":"Personal",
            "type":"Services"
        },
        {
            "category":"Retail",
            "subcategory":"Auto Rental",
            "type":"Services"
        },
        {
            "category":"Building & Trades",
            "subcategory":"Equipment Rental",
            "type":"Services"
        },
        {
            "category":"Retail",
            "subcategory":"Storage",
            "type":"Services"
        }
    ],
    "sg:phone":"+1 863 774 3311",
    "sg:postcode":"33860",
    "sg:province":"FL",
    "sg:tags":[
        "renting",
        "moving-self",
        "leasing",
        "household",
        "commercial",
        "truck",
        "moving",
        "mover",
        "self",
        "trailer"
    ],
    "sg:website":"http://www.uhaul.com/Locations/Rentals-near-Mulberry-FL-33860/041583",
    "wof:name":"U-Haul Neighborhood Dealer - Jp Mini Mart",
    "wof:placetype":"venue"
},
  "geometry": {"coordinates":[-81.97697599999999,27.894859],"type":"Point"}
}