{
  "type": "Feature",
  "properties": {
    "addr:full":"1039 NE 207th Ter Miami FL 33179",
    "addr:housenumber":"1039",
    "addr:postcode":"33179",
    "addr:street":"Ne 207Th Ter",
    "iso:country":"US",
    "sg:address":"1039 NE 207th Ter",
    "sg:city":"Miami",
    "sg:classifiers":[
        {
            "category":"Banks & Credit Unions",
            "subcategory":"Investment Brokerage",
            "type":"Services"
        },
        {
            "category":"Banks & Credit Unions",
            "subcategory":"Financial Services",
            "type":"Services"
        }
    ],
    "sg:phone":"+1 305 651 6004",
    "sg:postcode":"33179",
    "sg:province":"FL",
    "sg:tags":[
        "advisory",
        "management",
        "planner"
    ],
    "wof:name":"Ives Dairy Investments",
    "wof:placetype":"venue"
},
  "geometry": {"coordinates":[-80.186424,25.966584],"type":"Point"}
}