{
  "type": "Feature",
  "properties": {
    "addr:full":"196 N Federal Hwy Aventura FL 33180",
    "addr:housenumber":"196",
    "addr:postcode":"33180",
    "addr:street":"N Federal Hwy",
    "iso:country":"US",
    "sg:address":"196 N Federal Hwy",
    "sg:city":"Aventura",
    "sg:classifiers":[
        {
            "category":"Building & Trades",
            "subcategory":"Locksmith",
            "type":"Services"
        }
    ],
    "sg:phone":"+1 800 627 8262",
    "sg:postcode":"33180",
    "sg:province":"FL",
    "sg:tags":[
        "key"
    ],
    "wof:name":"A 1 Emergency Locksmith",
    "wof:placetype":"venue"
},
  "geometry": {"coordinates":[-80.25854200000001,25.728496],"type":"Point"}
}