{
  "type": "Feature",
  "properties": {
    "iso:country":"US",
    "sg:address":"441 NW 25th Ct",
    "sg:city":"Miami",
    "sg:classifiers":[
        {
            "category":"Professional",
            "type":"Services"
        }
    ],
    "sg:phone":"+1 305 642 0689",
    "sg:postcode":"33125",
    "sg:province":"FL",
    "wof:name":"Yandi & Yadir Inc",
    "wof:placetype":"venue"
},
  "geometry": {"coordinates":[-80.237836,25.778118],"type":"Point"}
}