{
  "type": "Feature",
  "properties": {
    "iso:country":"US",
    "sg:address":"4582 107th Cir N",
    "sg:city":"Clearwater",
    "sg:phone":"+1 727 572 0004",
    "sg:postcode":"33762",
    "sg:province":"FL",
    "sg:tags":[
        "shelving",
        "system",
        "conveyor"
    ],
    "wof:name":"Storage & Handling Equipment",
    "wof:placetype":"venue"
},
  "geometry": {"coordinates":[-82.699168,27.870205],"type":"Point"}
}