{
  "type": "Feature",
  "properties": {
    "addr:full":"8629 Twin Lakes Blvd Tampa FL 33614",
    "addr:housenumber":"8629",
    "addr:postcode":"33614",
    "addr:street":"Twin Lakes Blvd",
    "iso:country":"US",
    "sg:address":"8629 Twin Lakes Blvd",
    "sg:city":"Tampa",
    "sg:classifiers":[
        {
            "category":"Health Services",
            "subcategory":"Doctor",
            "type":"Services"
        }
    ],
    "sg:phone":"+1 813 933 4711",
    "sg:postcode":"33614",
    "sg:province":"FL",
    "sg:tags":[
        "medical"
    ],
    "wof:name":"Jesus Jimenez MD",
    "wof:placetype":"venue"
},
  "geometry": {"coordinates":[-82.49238800000001,28.030196],"type":"Point"}
}