{
  "type": "Feature",
  "properties": {
    "iso:country":"US",
    "sg:address":"14286 Beach Blvd",
    "sg:city":"Jacksonville Bch",
    "sg:classifiers":[
        {
            "category":"Recreation",
            "type":"Entertainment"
        }
    ],
    "sg:phone":"+1 904 821 0901",
    "sg:postcode":"32250",
    "sg:province":"FL",
    "sg:tags":[
        "martial",
        "arts",
        "instruction"
    ],
    "wof:name":"Karate America",
    "wof:placetype":"venue"
},
  "geometry": {"coordinates":[-81.441652,30.287774],"type":"Point"}
}