{
  "type": "Feature",
  "properties": {
    "iso:country":"US",
    "sg:address":"270 Hampton Ln",
    "sg:city":"Key Biscayne",
    "sg:classifiers":[
        {
            "category":"Museum",
            "type":"Entertainment"
        }
    ],
    "sg:phone":"+1 305 361 1216",
    "sg:postcode":"33149",
    "sg:province":"FL",
    "sg:tags":[
        "art",
        "including",
        "interior",
        "design",
        "dec",
        "sculpture"
    ],
    "wof:name":"Sandy Wallin Inc",
    "wof:placetype":"venue"
},
  "geometry": {"coordinates":[-80.16768,25.696408],"type":"Point"}
}