{
  "type": "Feature",
  "properties": {
    "iso:country":"US",
    "sg:address":"1243 Avondale Ln",
    "sg:city":"West Palm Beach",
    "sg:classifiers":[
        {
            "category":"Shopping",
            "type":"Retail Goods"
        }
    ],
    "sg:phone":"+1 561 687 7585",
    "sg:postcode":"33409",
    "sg:province":"FL",
    "sg:tags":[
        "mausoleum"
    ],
    "wof:name":"All County Monuments Corp",
    "wof:placetype":"venue"
},
  "geometry": {"coordinates":[-80.092899,26.718592],"type":"Point"}
}