{
  "type": "Feature",
  "properties": {
    "iso:country":"US",
    "sg:address":"9045 Hawthorne Ave",
    "sg:city":"Miami Beach",
    "sg:classifiers":[
        {
            "category":"Manufacturing",
            "subcategory":"Food",
            "type":"Manufacturing & Wholesale Goods"
        },
        {
            "category":"Manufacturing",
            "subcategory":"Tools & Machinery",
            "type":"Manufacturing & Wholesale Goods"
        }
    ],
    "sg:phone":"+1 305 861 7088",
    "sg:postcode":"33154",
    "sg:province":"FL",
    "sg:tags":[
        "manufacture",
        "machine",
        "marine",
        "ice"
    ],
    "wof:name":"Eskimo Ice Corp",
    "wof:placetype":"venue"
},
  "geometry": {"coordinates":[-80.129302,25.876487],"type":"Point"}
}