{
  "type": "Feature",
  "properties": {
    "iso:country":"US",
    "sg:address":"10245 Southern Blvd",
    "sg:city":"Royal Palm Beach",
    "sg:classifiers":[
        {
            "category":"Education",
            "subcategory":"Dance Studio",
            "type":"Public Place"
        }
    ],
    "sg:phone":"+1 561 795 0053",
    "sg:postcode":"33411",
    "sg:province":"FL",
    "sg:tags":[
        "instruction",
        "dancing"
    ],
    "wof:name":"Donna Tucci's School Of Dance",
    "wof:placetype":"venue"
},
  "geometry": {"coordinates":[-80.207078,26.680427],"type":"Point"}
}