{
  "type": "Feature",
  "properties": {
    "iso:country":"US",
    "sg:address":"4305 SW 10th Ave",
    "sg:city":"Cape Coral",
    "sg:classifiers":[
        {
            "category":"Building & Trades",
            "subcategory":"Construction",
            "type":"Services"
        }
    ],
    "sg:phone":"+1 239 541 1960",
    "sg:postcode":"33914",
    "sg:province":"FL",
    "sg:tags":[
        "contracting",
        "painting"
    ],
    "wof:name":"Wright Way Painting Company",
    "wof:placetype":"venue"
},
  "geometry": {"coordinates":[-81.995554,26.571656],"type":"Point"}
}