{
  "type": "Feature",
  "properties": {
    "addr:full":"6901 22nd Ave N St Petersburg FL 33710",
    "addr:housenumber":"6901",
    "addr:postcode":"33710",
    "addr:street":"22Nd Ave N",
    "iso:country":"US",
    "sg:address":"6901 22nd Ave N",
    "sg:city":"St Petersburg",
    "sg:classifiers":[
        {
            "category":"Food & Beverages",
            "subcategory":"Bakery",
            "type":"Retail Goods"
        }
    ],
    "sg:phone":"+1 727 381 4888",
    "sg:postcode":"33710",
    "sg:province":"FL",
    "sg:tags":[
        "baker"
    ],
    "wof:name":"Fortunato Italian Market",
    "wof:placetype":"venue"
},
  "geometry": {"coordinates":[-82.735962,27.791873],"type":"Point"}
}