{
  "type": "Feature",
  "properties": {
    "iso:country":"US",
    "sg:address":"407 SW 4th Ave",
    "sg:city":"Gainesville",
    "sg:classifiers":[
        {
            "category":"Shopping",
            "subcategory":"Musical Instruments",
            "type":"Retail Goods"
        }
    ],
    "sg:phone":"+1 352 378 0098",
    "sg:postcode":"32601",
    "sg:province":"FL",
    "sg:tags":[
        "guitar",
        "amplifier"
    ],
    "wof:name":"C & A Enterprises",
    "wof:placetype":"venue"
},
  "geometry": {"coordinates":[-82.32882499999999,29.648331],"type":"Point"}
}