{
  "type": "Feature",
  "properties": {
    "addr:full":"9105 Belcher Rd Pinellas Park FL 33782",
    "addr:housenumber":"9105",
    "addr:postcode":"33782",
    "addr:street":"Belcher Rd",
    "iso:country":"US",
    "sg:address":"9105 Belcher Rd",
    "sg:city":"Pinellas Park",
    "sg:classifiers":[
        {
            "category":"Insurance",
            "subcategory":"Insurance Agent",
            "type":"Services"
        }
    ],
    "sg:phone":"+1 727 544 8841",
    "sg:postcode":"33782",
    "sg:province":"FL",
    "sg:tags":[
        "agency"
    ],
    "wof:name":"Nationwide",
    "wof:placetype":"venue"
},
  "geometry": {"coordinates":[-82.736895,27.856495],"type":"Point"}
}