{
  "type": "Feature",
  "properties": {
    "addr:full":"680 N Central Ave Umatilla FL 32784",
    "addr:housenumber":"680",
    "addr:postcode":"32784",
    "addr:street":"N Central Ave",
    "iso:country":"US",
    "sg:address":"680 N Central Ave",
    "sg:city":"Umatilla",
    "sg:classifiers":[
        {
            "category":"Real Estate",
            "subcategory":"Real Estate Agent",
            "type":"Services"
        }
    ],
    "sg:phone":"+1 352 669 3244",
    "sg:postcode":"32784",
    "sg:province":"FL",
    "wof:name":"Barbara L Johnson Realty Inc",
    "wof:placetype":"venue"
},
  "geometry": {"coordinates":[-81.663889,28.940429],"type":"Point"}
}