{
  "type": "Feature",
  "properties": {
    "iso:country":"US",
    "sg:address":"4493 del Sol Blvd",
    "sg:city":"Sarasota",
    "sg:classifiers":[
        {
            "category":"Shopping",
            "subcategory":"Gifts & Souvenirs",
            "type":"Retail Goods"
        }
    ],
    "sg:phone":"+1 941 355 1581",
    "sg:postcode":"34243",
    "sg:province":"FL",
    "sg:tags":[
        "basket",
        "parcel"
    ],
    "wof:name":"Kate's Gourmet Candy",
    "wof:placetype":"venue"
},
  "geometry": {"coordinates":[-82.47788199999999,27.384488],"type":"Point"}
}