{
  "type": "Feature",
  "properties": {
    "iso:country":"US",
    "sg:address":"127 Eden Creek Ln",
    "sg:city":"Jensen Beach",
    "sg:classifiers":[
        {
            "category":"Building & Trades",
            "subcategory":"Plumbing",
            "type":"Services"
        }
    ],
    "sg:phone":"+1 772 229 7728",
    "sg:postcode":"34957",
    "sg:province":"FL",
    "sg:tags":[
        "contractor"
    ],
    "wof:name":"Stover Art",
    "wof:placetype":"venue"
},
  "geometry": {"coordinates":[-80.23668000000001,27.26618],"type":"Point"}
}