{
  "type": "Feature",
  "properties": {
    "addr:full":"8581 Welcome Church Rd Milton FL 32583",
    "addr:housenumber":"8581",
    "addr:postcode":"32583",
    "addr:street":"Welcome Church Rd",
    "iso:country":"US",
    "sg:address":"8581 Welcome Church Rd",
    "sg:city":"Milton",
    "sg:classifiers":[
        {
            "category":"Organizations",
            "subcategory":"Religious Organization",
            "type":"Services"
        }
    ],
    "sg:phone":"+1 850 983 9441",
    "sg:postcode":"32583",
    "sg:province":"FL",
    "sg:tags":[
        "church"
    ],
    "wof:name":"Welcome Assembly Of God Church",
    "wof:placetype":"venue"
},
  "geometry": {"coordinates":[-86.965705,30.61643],"type":"Point"}
}