{
  "type": "Feature",
  "properties": {
    "iso:country":"US",
    "sg:address":"2379 Davis Blvd",
    "sg:city":"Naples",
    "sg:classifiers":[
        {
            "category":"Personal",
            "subcategory":"Barber",
            "type":"Services"
        }
    ],
    "sg:phone":"+1 239 774 5005",
    "sg:postcode":"34104",
    "sg:province":"FL",
    "sg:tags":[
        "shop"
    ],
    "wof:name":"Brookside Barber Shop",
    "wof:placetype":"venue"
},
  "geometry": {"coordinates":[-81.777618,26.138418],"type":"Point"}
}