{
  "type": "Feature",
  "properties": {
    "addr:full":"3238 SE 1st Ave Cape Coral FL 33904",
    "addr:housenumber":"3238",
    "addr:postcode":"33904",
    "addr:street":"Se 1St Ave",
    "iso:country":"US",
    "sg:address":"3238 SE 1st Ave",
    "sg:city":"Cape Coral",
    "sg:classifiers":[
        {
            "category":"Local Transit",
            "type":"Transportation"
        }
    ],
    "sg:phone":"+1 239 549 5874",
    "sg:postcode":"33904",
    "sg:province":"FL",
    "sg:tags":[
        "passenger"
    ],
    "wof:name":"Extraordinary Limousine",
    "wof:placetype":"venue"
},
  "geometry": {"coordinates":[-81.972306,26.59156],"type":"Point"}
}