{
  "type": "Feature",
  "properties": {
    "addr:full":"9814 International Dr Orlando FL 32819",
    "addr:housenumber":"9814",
    "addr:postcode":"32819",
    "addr:street":"International Dr",
    "iso:country":"US",
    "sg:address":"9814 International Dr",
    "sg:city":"Orlando",
    "sg:classifiers":[
        {
            "category":"Recreation",
            "type":"Entertainment"
        }
    ],
    "sg:phone":"+1 407 351 9160",
    "sg:postcode":"32819",
    "sg:province":"FL",
    "sg:tags":[
        "ticket"
    ],
    "wof:name":"A Plus Marketing",
    "wof:placetype":"venue"
},
  "geometry": {"coordinates":[-81.461643,28.425004],"type":"Point"}
}