{
  "type": "Feature",
  "properties": {
    "addr:full":"4524 Lane Ave S Jacksonville FL 32210",
    "addr:housenumber":"4524",
    "addr:postcode":"32210",
    "addr:street":"Lane Ave S",
    "iso:country":"US",
    "sg:address":"4524 Lane Ave S",
    "sg:city":"Jacksonville",
    "sg:classifiers":[
        {
            "category":"Education",
            "subcategory":"Special Training",
            "type":"Public Place"
        }
    ],
    "sg:phone":"+1 904 536 7206",
    "sg:postcode":"32210",
    "sg:province":"FL",
    "sg:tags":[
        "educational"
    ],
    "wof:name":"Safe Haven, Inc.",
    "wof:placetype":"venue"
},
  "geometry": {"coordinates":[-81.75849100000001,30.256524],"type":"Point"}
}