{
  "type": "Feature",
  "properties": {
    "iso:country":"US",
    "sg:address":"4796 SW 72nd Ave",
    "sg:city":"Miami",
    "sg:classifiers":[
        {
            "category":"Home & Garden",
            "subcategory":"Furniture",
            "type":"Retail Goods"
        },
        {
            "category":"Shopping",
            "subcategory":"Clothing, Apparel, & Fashions",
            "type":"Retail Goods"
        }
    ],
    "sg:phone":"+1 305 284 0525",
    "sg:postcode":"33155",
    "sg:province":"FL",
    "sg:tags":[
        "wear"
    ],
    "wof:name":"Kreativa For Kids N Teams",
    "wof:placetype":"venue"
},
  "geometry": {"coordinates":[-80.310811,25.726363],"type":"Point"}
}