{
  "type": "Feature",
  "properties": {
    "iso:country":"US",
    "sg:address":"25 W Flagler St",
    "sg:city":"Miami",
    "sg:classifiers":[
        {
            "category":"Professional",
            "subcategory":"Lawyer & Legal Services",
            "type":"Services"
        }
    ],
    "sg:phone":"+1 305 374 1212",
    "sg:postcode":"33130",
    "sg:province":"FL",
    "sg:tags":[
        "attorney"
    ],
    "sg:website":"www.kubickidraper.com",
    "wof:name":"Kubicki Draper",
    "wof:placetype":"venue"
},
  "geometry": {"coordinates":[-80.194,25.7742],"type":"Point"}
}