{
  "type": "Feature",
  "properties": {
    "addr:full":"2613 Corrigan Dr Deltona FL 32738",
    "addr:housenumber":"2613",
    "addr:postcode":"32738",
    "addr:street":"Corrigan Dr",
    "iso:country":"US",
    "sg:address":"2613 Corrigan Dr",
    "sg:city":"Deltona",
    "sg:classifiers":[
        {
            "category":"Travel",
            "subcategory":"Travel Agent",
            "type":"Entertainment"
        }
    ],
    "sg:phone":"+1 386 532 7706",
    "sg:postcode":"32738",
    "sg:province":"FL",
    "sg:tags":[
        "agency",
        "bureau"
    ],
    "wof:name":"Cruise Connection",
    "wof:placetype":"venue"
},
  "geometry": {"coordinates":[-81.191239,28.939595],"type":"Point"}
}