{
  "type": "Feature",
  "properties": {
    "iso:country":"US",
    "sg:address":"8446 W Oakland Park Blvd",
    "sg:city":"Sunrise",
    "sg:classifiers":[
        {
            "category":"Personal",
            "subcategory":"Nail Salon",
            "type":"Services"
        }
    ],
    "sg:phone":"+1 954 742 4290",
    "sg:postcode":"33351",
    "sg:province":"FL",
    "wof:name":"Q-t Nail Spa Of Sunrise",
    "wof:placetype":"venue"
},
  "geometry": {"coordinates":[-80.26250899999999,26.167516],"type":"Point"}
}