{
  "type": "Feature",
  "properties": {
    "iso:country":"US",
    "sg:address":"5247 Cedar Bend Dr",
    "sg:city":"Fort Myers",
    "sg:classifiers":[
        {
            "category":"Professional",
            "subcategory":"Business Services",
            "type":"Services"
        }
    ],
    "sg:phone":"+1 239 275 5588",
    "sg:postcode":"33919",
    "sg:province":"FL",
    "sg:tags":[
        "interior",
        "consultant",
        "design",
        "decorator"
    ],
    "wof:name":"Optiumum Designs Inc",
    "wof:placetype":"venue"
},
  "geometry": {"coordinates":[-81.882794,26.583129],"type":"Point"}
}