{
  "type": "Feature",
  "properties": {
    "iso:country":"US",
    "sg:address":"2150 N Park Ave",
    "sg:city":"Winter Park",
    "sg:classifiers":[
        {
            "category":"Health Services",
            "subcategory":"Doctor",
            "type":"Services"
        }
    ],
    "sg:phone":"+1 407 628 1246",
    "sg:postcode":"32789",
    "sg:province":"FL",
    "wof:name":"Karen A Goldberg MD",
    "wof:placetype":"venue"
},
  "geometry": {"coordinates":[-81.363615,28.610552],"type":"Point"}
}