{
  "type": "Feature",
  "properties": {
    "iso:country":"US",
    "sg:address":"2120 E Sligh Ave",
    "sg:city":"Tampa",
    "sg:classifiers":[
        {
            "category":"Restaurant",
            "type":"Food & Drink"
        }
    ],
    "sg:phone":"+1 813 237 2488",
    "sg:postcode":"33610",
    "sg:province":"FL",
    "wof:name":"T N Crab Shack",
    "wof:placetype":"venue"
},
  "geometry": {"coordinates":[-82.43532,28.010623],"type":"Point"}
}