{
  "type": "Feature",
  "properties": {
    "addr:full":"7798 Pine Trace Dr Sarasota FL 34243",
    "addr:housenumber":"7798",
    "addr:postcode":"34243",
    "addr:street":"Pine Trace Dr",
    "iso:country":"US",
    "sg:address":"7798 Pine Trace Dr",
    "sg:city":"Sarasota",
    "sg:classifiers":[
        {
            "category":"Home & Garden",
            "subcategory":"Furniture",
            "type":"Retail Goods"
        }
    ],
    "sg:phone":"+1 941 358 7775",
    "sg:postcode":"34243",
    "sg:province":"FL",
    "sg:tags":[
        "store"
    ],
    "wof:name":"American Toy And Furniture",
    "wof:placetype":"venue"
},
  "geometry": {"coordinates":[-82.488158,27.40144],"type":"Point"}
}