{
  "type": "Feature",
  "properties": {
    "addr:full":"950 SW Bayshore Blvd Port St Lucie FL 34983",
    "addr:housenumber":"950",
    "addr:postcode":"34983",
    "addr:street":"Sw Bayshore Blvd",
    "iso:country":"US",
    "sg:address":"950 SW Bayshore Blvd",
    "sg:city":"Port St Lucie",
    "sg:classifiers":[
        {
            "category":"Real Estate",
            "subcategory":"Real Estate Agent",
            "type":"Services"
        }
    ],
    "sg:phone":"+1 772 871 0340",
    "sg:postcode":"34983",
    "sg:province":"FL",
    "sg:tags":[
        "agency"
    ],
    "wof:name":"Sharon J Kelly Realty Inc",
    "wof:placetype":"venue"
},
  "geometry": {"coordinates":[-80.371546,27.311739],"type":"Point"}
}