{
  "type": "Feature",
  "properties": {
    "iso:country":"US",
    "sg:address":"2420 Dyer Blvd",
    "sg:city":"Kissimmee",
    "sg:classifiers":[
        {
            "category":"Social Services",
            "subcategory":"Child Care",
            "type":"Services"
        }
    ],
    "sg:phone":"+1 407 935 3659",
    "sg:postcode":"34741",
    "sg:province":"FL",
    "wof:name":"Extend A Day Daycare Program",
    "wof:placetype":"venue"
},
  "geometry": {"coordinates":[-81.43665300000001,28.312673],"type":"Point"}
}