{
  "type": "Feature",
  "properties": {
    "iso:country":"US",
    "sg:address":"102 12th Ave",
    "sg:city":"Indialantic",
    "sg:classifiers":[
        {
            "category":"Building & Trades",
            "subcategory":"Landscaping Services",
            "type":"Services"
        }
    ],
    "sg:phone":"+1 321 676 5355",
    "sg:postcode":"32903",
    "sg:province":"FL",
    "sg:tags":[
        "sod",
        "sodding"
    ],
    "wof:name":"Certilawn Inc",
    "wof:placetype":"venue"
},
  "geometry": {"coordinates":[-80.567268,28.086185],"type":"Point"}
}