{
  "type": "Feature",
  "properties": {
    "iso:country":"US",
    "sg:address":"13020 Livingston Rd",
    "sg:city":"Naples",
    "sg:classifiers":[
        {
            "category":"Restaurant",
            "type":"Food & Drink"
        }
    ],
    "sg:phone":"+1 239 325 9255",
    "sg:postcode":"34105",
    "sg:province":"FL",
    "sg:tags":[
        "mexican"
    ],
    "sg:website":"http://www.bajiogrill.com",
    "wof:name":"Bajio Mexican Grill",
    "wof:placetype":"venue"
},
  "geometry": {"coordinates":[-81.75141499999999,26.204633],"type":"Point"}
}