{
  "type": "Feature",
  "properties": {
    "iso:country":"US",
    "sg:address":"5673 Royal Pine Blvd",
    "sg:city":"Orlando",
    "sg:classifiers":[
        {
            "category":"Professional",
            "subcategory":"Business Services",
            "type":"Services"
        }
    ],
    "sg:phone":"+1 407 671 5016",
    "sg:postcode":"32807",
    "sg:province":"FL",
    "sg:tags":[
        "advertising"
    ],
    "wof:name":"ARS Speciality Advertising",
    "wof:placetype":"venue"
},
  "geometry": {"coordinates":[-81.311581,28.570658],"type":"Point"}
}