{
  "type": "Feature",
  "properties": {
    "iso:country":"US",
    "sg:address":"5362 Central Florida Pkwy",
    "sg:city":"Orlando",
    "sg:classifiers":[
        {
            "category":"Health Services",
            "subcategory":"Chiropractor",
            "type":"Services"
        }
    ],
    "sg:phone":"+1 407 239 1132",
    "sg:postcode":"32821",
    "sg:province":"FL",
    "sg:website":"www.drctv.com",
    "wof:name":"Total Living Ctr Of Orlando",
    "wof:placetype":"venue"
},
  "geometry": {"coordinates":[-81.449406,28.407938],"type":"Point"}
}