{
  "type": "Feature",
  "properties": {
    "iso:country":"US",
    "sg:address":"2823 Tamiami Trl",
    "sg:city":"Crestview",
    "sg:classifiers":[
        {
            "category":"Health Services",
            "subcategory":"Doctor",
            "type":"Services"
        }
    ],
    "sg:phone":"+1 850 682 5050",
    "sg:postcode":"32539",
    "sg:province":"FL",
    "sg:tags":[
        "clinic"
    ],
    "wof:name":"Integrity Medical Revenue Svc",
    "wof:placetype":"venue"
},
  "geometry": {"coordinates":[-86.556731,30.716507],"type":"Point"}
}