{
  "type": "Feature",
  "properties": {
    "addr:full":"224 N Martin Luther King Jr Blvd Tallahassee FL 32301",
    "addr:housenumber":"224",
    "addr:postcode":"32301",
    "addr:street":"N Martin Luther King Jr Blvd",
    "iso:country":"US",
    "sg:address":"224 N Martin Luther King Jr Blvd",
    "sg:city":"Tallahassee",
    "sg:classifiers":[
        {
            "category":"Organizations",
            "subcategory":"Religious Organization",
            "type":"Services"
        }
    ],
    "sg:phone":"+1 850 222 8440",
    "sg:postcode":"32301",
    "sg:province":"FL",
    "sg:tags":[
        "church"
    ],
    "sg:website":"www.betheltally.org",
    "wof:name":"Bethel Missionary Baptist Chr",
    "wof:placetype":"venue"
},
  "geometry": {"coordinates":[-84.285707,30.444426],"type":"Point"}
}