{
  "type": "Feature",
  "properties": {
    "iso:country":"US",
    "sg:address":"1071 E 29th St",
    "sg:city":"Hialeah",
    "sg:classifiers":[
        {
            "category":"Retail",
            "subcategory":"Auto Repair",
            "type":"Services"
        }
    ],
    "sg:phone":"+1 305 696 5957",
    "sg:postcode":"33013",
    "sg:province":"FL",
    "sg:tags":[
        "body",
        "automobile",
        "painting"
    ],
    "wof:name":"A & M Auto Ctr",
    "wof:placetype":"venue"
},
  "geometry": {"coordinates":[-80.26157000000001,25.849155],"type":"Point"}
}