{
  "type": "Feature",
  "properties": {
    "iso:country":"US",
    "sg:address":"1745 E Highway 50",
    "sg:city":"Clermont",
    "sg:classifiers":[
        {
            "category":"Health Services",
            "subcategory":"Doctor",
            "type":"Services"
        }
    ],
    "sg:phone":"+1 352 243 5526",
    "sg:postcode":"34711",
    "sg:province":"FL",
    "sg:tags":[
        "physician",
        "surgeon",
        "psychologist"
    ],
    "wof:name":"Sleep Telemedicine Service",
    "wof:placetype":"venue"
},
  "geometry": {"coordinates":[-81.730086,28.546559],"type":"Point"}
}