{
  "type": "Feature",
  "properties": {
    "iso:country":"US",
    "sg:address":"1900 Brickell Ave",
    "sg:city":"Miami",
    "sg:classifiers":[
        {
            "category":"Health Services",
            "subcategory":"Doctor",
            "type":"Services"
        }
    ],
    "sg:phone":"+1 305 856 9566",
    "sg:postcode":"33129",
    "sg:province":"FL",
    "sg:tags":[
        "surgeon",
        "cosmetic"
    ],
    "wof:name":"Anire Okpaku MD",
    "wof:placetype":"venue"
},
  "geometry": {"coordinates":[-80.198297,25.754697],"type":"Point"}
}