{
  "type": "Feature",
  "properties": {
    "iso:country":"US",
    "sg:address":"7205 SW 24th St",
    "sg:city":"Miami",
    "sg:classifiers":[
        {
            "category":"Banks & Credit Unions",
            "subcategory":"Bank",
            "type":"Services"
        }
    ],
    "sg:phone":"+1 305 264 3659",
    "sg:postcode":"33155",
    "sg:province":"FL",
    "sg:tags":[
        "loan",
        "real estate"
    ],
    "wof:name":"Happy Owner Mortgage",
    "wof:placetype":"venue"
},
  "geometry": {"coordinates":[-80.315547,25.748178],"type":"Point"}
}