{
  "type": "Feature",
  "properties": {
    "iso:country":"US",
    "sg:address":"840 N State Rd 434",
    "sg:city":"Altamonte Spgs",
    "sg:classifiers":[
        {
            "category":"Insurance",
            "subcategory":"Insurance Agent",
            "type":"Services"
        }
    ],
    "sg:phone":"+1 407 865 5655",
    "sg:postcode":"32714",
    "sg:province":"FL",
    "wof:name":"Senior American Insurance",
    "wof:placetype":"venue"
},
  "geometry": {"coordinates":[-81.419071,28.677813],"type":"Point"}
}