{
  "type": "Feature",
  "properties": {
    "iso:country":"US",
    "sg:address":"5808 Heronrise Crescent Dr",
    "sg:city":"Lithia",
    "sg:classifiers":[
        {
            "category":"Real Estate",
            "subcategory":"Surveying",
            "type":"Services"
        }
    ],
    "sg:phone":"+1 813 653 0771",
    "sg:postcode":"33547",
    "sg:province":"FL",
    "wof:name":"Airside Designs",
    "wof:placetype":"venue"
},
  "geometry": {"coordinates":[-82.23802999999999,27.846812],"type":"Point"}
}