{
  "type": "Feature",
  "properties": {
    "addr:full":"8818 Elba Way Orlando FL 32810",
    "addr:housenumber":"8818",
    "addr:postcode":"32810",
    "addr:street":"Elba Way",
    "iso:country":"US",
    "sg:address":"8818 Elba Way",
    "sg:city":"Orlando",
    "sg:classifiers":[
        {
            "category":"Building & Trades",
            "subcategory":"Construction",
            "type":"Services"
        }
    ],
    "sg:phone":"+1 407 291 8231",
    "sg:postcode":"32810",
    "sg:province":"FL",
    "sg:tags":[
        "hanging",
        "contractor"
    ],
    "wof:name":"Buzzs Busy Bee Paint Service",
    "wof:placetype":"venue"
},
  "geometry": {"coordinates":[-81.421758,28.637584],"type":"Point"}
}