{
  "type": "Feature",
  "properties": {
    "addr:full":"8151 Montasonta Ave Jacksonville FL 32211",
    "addr:housenumber":"8151",
    "addr:postcode":"32211",
    "addr:street":"Montasonta Ave",
    "iso:country":"US",
    "sg:address":"8151 Montasonta Ave",
    "sg:city":"Jacksonville",
    "sg:classifiers":[
        {
            "category":"Building & Trades",
            "subcategory":"Cleaning & Sanitation",
            "type":"Services"
        }
    ],
    "sg:phone":"+1 904 855 8021",
    "sg:postcode":"32211",
    "sg:province":"FL",
    "sg:tags":[
        "maintenance"
    ],
    "wof:name":"Spectrum Building Maintenance",
    "wof:placetype":"venue"
},
  "geometry": {"coordinates":[-81.569497,30.341723],"type":"Point"}
}