{
  "type": "Feature",
  "properties": {
    "iso:country":"US",
    "sg:address":"1030 Lester Dr",
    "sg:city":"Kissimmee",
    "sg:classifiers":[
        {
            "category":"Home & Garden",
            "subcategory":"Building Materials",
            "type":"Retail Goods"
        }
    ],
    "sg:phone":"+1 407 870 1927",
    "sg:postcode":"34741",
    "sg:province":"FL",
    "sg:tags":[
        "screen",
        "window"
    ],
    "wof:name":"Daniel Guyers Rescreen",
    "wof:placetype":"venue"
},
  "geometry": {"coordinates":[-81.441008,28.28155],"type":"Point"}
}