{
  "type": "Feature",
  "properties": {
    "iso:country":"US",
    "sg:address":"43400 Ratliff Rd",
    "sg:city":"Callahan",
    "sg:classifiers":[
        {
            "category":"Building & Trades",
            "subcategory":"Electrical",
            "type":"Services"
        }
    ],
    "sg:phone":"+1 904 879 2558",
    "sg:postcode":"32011",
    "sg:province":"FL",
    "sg:tags":[
        "electrician"
    ],
    "wof:name":"Ray Electric",
    "wof:placetype":"venue"
},
  "geometry": {"coordinates":[-81.819627,30.494436],"type":"Point"}
}