{
  "type": "Feature",
  "properties": {
    "iso:country":"US",
    "sg:address":"1400 10th Ave",
    "sg:city":"Vero Beach",
    "sg:classifiers":[
        {
            "category":"Home & Garden",
            "subcategory":"Building Materials",
            "type":"Retail Goods"
        }
    ],
    "sg:phone":"+1 772 562 3384",
    "sg:postcode":"32960",
    "sg:province":"FL",
    "sg:tags":[
        "mixed",
        "concrete"
    ],
    "wof:name":"Russell Concrete Inc",
    "wof:placetype":"venue"
},
  "geometry": {"coordinates":[-80.392201,27.627656],"type":"Point"}
}