{
  "type": "Feature",
  "properties": {
    "addr:full":"14838 Ramsey Rd Dade City FL 33523",
    "addr:housenumber":"14838",
    "addr:postcode":"33523",
    "addr:street":"Ramsey Rd",
    "iso:country":"US",
    "sg:address":"14838 Ramsey Rd",
    "sg:city":"Dade City",
    "sg:classifiers":[
        {
            "category":"Organizations",
            "subcategory":"Religious Organization",
            "type":"Services"
        }
    ],
    "sg:phone":"+1 352 567 6040",
    "sg:postcode":"33523",
    "sg:province":"FL",
    "sg:tags":[
        "church"
    ],
    "wof:name":"Kingdom Hall-Jehovah's Witness",
    "wof:placetype":"venue"
},
  "geometry": {"coordinates":[-82.220423,28.369531],"type":"Point"}
}