{
  "type": "Feature",
  "properties": {
    "iso:country":"US",
    "sg:address":"9424 Front Beach Rd",
    "sg:city":"Panama City",
    "sg:classifiers":[
        {
            "category":"Travel",
            "subcategory":"Hotels & Motels",
            "type":"Entertainment"
        }
    ],
    "sg:phone":"+1 850 235 1122",
    "sg:postcode":"32407",
    "sg:province":"FL",
    "wof:name":"Travelodge",
    "wof:placetype":"venue"
},
  "geometry": {"coordinates":[-85.79526799999999,30.179911],"type":"Point"}
}