{
  "type": "Feature",
  "properties": {
    "iso:country":"US",
    "sg:address":"2011 61st St",
    "sg:city":"Sarasota",
    "sg:classifiers":[
        {
            "category":"Arts & Performance",
            "subcategory":"Theater",
            "type":"Entertainment"
        }
    ],
    "sg:phone":"+1 941 351 6709",
    "sg:postcode":"34243",
    "sg:province":"FL",
    "sg:tags":[
        "bureau"
    ],
    "wof:name":"Entertainment Management Exch",
    "wof:placetype":"venue"
},
  "geometry": {"coordinates":[-82.522301,27.387032],"type":"Point"}
}