{
  "type": "Feature",
  "properties": {
    "addr:full":"3973 Hendricks Ave Jacksonville FL 32207",
    "addr:housenumber":"3973",
    "addr:postcode":"32207",
    "addr:street":"Hendricks Ave",
    "iso:country":"US",
    "sg:address":"3973 Hendricks Ave",
    "sg:city":"Jacksonville",
    "sg:classifiers":[
        {
            "category":"Retail",
            "subcategory":"Auto Rental",
            "type":"Services"
        }
    ],
    "sg:phone":"+1 904 390 6685",
    "sg:postcode":"32207",
    "sg:province":"FL",
    "sg:tags":[
        "renting",
        "truck",
        "leasing"
    ],
    "wof:name":"U-Haul Co",
    "wof:placetype":"venue"
},
  "geometry": {"coordinates":[-81.651056,30.282993],"type":"Point"}
}