{
  "type": "Feature",
  "properties": {
    "iso:country":"US",
    "sg:address":"624 N Nashua Ave",
    "sg:city":"Fort Meade",
    "sg:classifiers":[
        {
            "category":"Building & Trades",
            "subcategory":"Construction",
            "type":"Services"
        }
    ],
    "sg:phone":"+1 863 285 6245",
    "sg:postcode":"33841",
    "sg:province":"FL",
    "sg:tags":[
        "contractor"
    ],
    "wof:name":"Ronald Creach Contracting",
    "wof:placetype":"venue"
},
  "geometry": {"coordinates":[-81.795067,27.759286],"type":"Point"}
}