{
  "type": "Feature",
  "properties": {
    "addr:full":"5467 1st Rd Lake Worth FL 33467",
    "addr:housenumber":"5467",
    "addr:postcode":"33467",
    "addr:street":"1St Rd",
    "iso:country":"US",
    "sg:address":"5467 1st Rd",
    "sg:city":"Lake Worth",
    "sg:classifiers":[
        {
            "category":"Retail",
            "subcategory":"Repair Shop",
            "type":"Services"
        }
    ],
    "sg:phone":"+1 561 967 7374",
    "sg:postcode":"33467",
    "sg:province":"FL",
    "sg:tags":[
        "welding"
    ],
    "wof:name":"Pw Welding",
    "wof:placetype":"venue"
},
  "geometry": {"coordinates":[-80.16285499999999,26.601435],"type":"Point"}
}