{
  "type": "Feature",
  "properties": {
    "addr:full":"748 Portwine Ct Englewood FL 34223",
    "addr:housenumber":"748",
    "addr:postcode":"34223",
    "addr:street":"Portwine Ct",
    "iso:country":"US",
    "sg:address":"748 Portwine Ct",
    "sg:city":"Englewood",
    "sg:classifiers":[
        {
            "category":"Building & Trades",
            "subcategory":"Construction",
            "type":"Services"
        }
    ],
    "sg:phone":"+1 941 473 3883",
    "sg:postcode":"34223",
    "sg:province":"FL",
    "sg:tags":[
        "hanging",
        "contractor"
    ],
    "wof:name":"John Charneski Painting",
    "wof:placetype":"venue"
},
  "geometry": {"coordinates":[-82.356217,26.980018],"type":"Point"}
}