{
  "type": "Feature",
  "properties": {
    "iso:country":"US",
    "sg:address":"258 Tamiami Trl",
    "sg:city":"Venice",
    "sg:classifiers":[
        {
            "category":"Insurance",
            "subcategory":"Insurance Agent",
            "type":"Services"
        }
    ],
    "sg:phone":"+1 941 484 1288",
    "sg:postcode":"34285",
    "sg:province":"FL",
    "sg:tags":[
        "agency"
    ],
    "wof:name":"Insurance Center Of Venice",
    "wof:placetype":"venue"
},
  "geometry": {"coordinates":[-82.444378,27.097266],"type":"Point"}
}