{
  "type": "Feature",
  "properties": {
    "iso:country":"US",
    "sg:address":"35 Sevilla St",
    "sg:city":"St Augustine",
    "sg:classifiers":[
        {
            "category":"Social Services",
            "subcategory":"Child Care",
            "type":"Services"
        }
    ],
    "sg:phone":"+1 904 829 6454",
    "sg:postcode":"32084",
    "sg:province":"FL",
    "sg:tags":[
        "kindergarten",
        "academic",
        "school"
    ],
    "sg:website":"www.memorialpcusa.org",
    "wof:name":"Presbyterian Day School",
    "wof:placetype":"venue"
},
  "geometry": {"coordinates":[-81.316434,29.893958],"type":"Point"}
}