{
  "type": "Feature",
  "properties": {
    "iso:country":"US",
    "sg:address":"5 Sandhill Crane Rd",
    "sg:city":"Fernandina Beach",
    "sg:classifiers":[
        {
            "category":"Health Services",
            "subcategory":"Doctor",
            "type":"Services"
        }
    ],
    "sg:phone":"+1 904 261 3933",
    "sg:postcode":"32034",
    "sg:province":"FL",
    "sg:tags":[
        "medical"
    ],
    "wof:name":"Sharp Medical Management",
    "wof:placetype":"venue"
},
  "geometry": {"coordinates":[-81.45778,30.551028],"type":"Point"}
}