{
  "type": "Feature",
  "properties": {
    "iso:country":"US",
    "sg:address":"101 S Jefferson St",
    "sg:city":"Pensacola",
    "sg:classifiers":[
        {
            "category":"Professional",
            "subcategory":"Accounting & Tax Preparation",
            "type":"Services"
        }
    ],
    "sg:phone":"+1 850 438 5614",
    "sg:postcode":"32502",
    "sg:province":"FL",
    "wof:name":"J Alan Kohr",
    "wof:placetype":"venue"
},
  "geometry": {"coordinates":[-87.213748,30.410501],"type":"Point"}
}