{
  "type": "Feature",
  "properties": {
    "iso:country":"US",
    "sg:address":"7474 Roebelenii Ct",
    "sg:city":"Sarasota",
    "sg:classifiers":[
        {
            "category":"Professional",
            "subcategory":"Art Services",
            "type":"Services"
        }
    ],
    "sg:phone":"+1 941 927 5844",
    "sg:postcode":"34241",
    "sg:province":"FL",
    "sg:tags":[
        "calligrapher"
    ],
    "wof:name":"An Accent In Calligraphy",
    "wof:placetype":"venue"
},
  "geometry": {"coordinates":[-82.44508399999999,27.241691],"type":"Point"}
}