{
  "type": "Feature",
  "properties": {
    "iso:country":"US",
    "sg:address":"4951 Haverhill Commons Cir",
    "sg:city":"West Palm Beach",
    "sg:classifiers":[
        {
            "category":"Professional",
            "subcategory":"Advertising",
            "type":"Services"
        }
    ],
    "sg:phone":"+1 561 615 0328",
    "sg:postcode":"33417",
    "sg:province":"FL",
    "wof:name":"Tipton's Victorians Enterprise",
    "wof:placetype":"venue"
},
  "geometry": {"coordinates":[-80.118099,26.698956],"type":"Point"}
}