{
  "type": "Feature",
  "properties": {
    "iso:country":"US",
    "sg:address":"4652 Meadow Green Trl",
    "sg:city":"Lake Worth",
    "sg:classifiers":[
        {
            "category":"Real Estate",
            "subcategory":"Real Estate Operator",
            "type":"Services"
        }
    ],
    "sg:phone":"+1 561 964 7865",
    "sg:postcode":"33463",
    "sg:province":"FL",
    "sg:tags":[
        "building",
        "apartment"
    ],
    "wof:name":"Holland House Apts",
    "wof:placetype":"venue"
},
  "geometry": {"coordinates":[-80.11637899999999,26.592695],"type":"Point"}
}