{
  "type": "Feature",
  "properties": {
    "addr:full":"9840 International Dr Orlando FL 32819",
    "addr:housenumber":"9840",
    "addr:postcode":"32819",
    "addr:street":"International Dr",
    "iso:country":"US",
    "sg:address":"9840 International Dr",
    "sg:city":"Orlando",
    "sg:classifiers":[
        {
            "category":"Restaurant",
            "type":"Food & Drink"
        }
    ],
    "sg:menulink":"http://www.allmenus.com/fl/southwest-orange/29741-everglades/menu/",
    "sg:phone":"+1 407 996 2385",
    "sg:postcode":"32819",
    "sg:province":"FL",
    "sg:tags":[
        "soup",
        "seafood",
        "american",
        "salad"
    ],
    "wof:name":"Everglades",
    "wof:placetype":"venue"
},
  "geometry": {"coordinates":[-81.464522,28.425516],"type":"Point"}
}