{
  "type": "Feature",
  "properties": {
    "iso:country":"US",
    "sg:address":"1622 NW 36th Ave",
    "sg:city":"Miami",
    "sg:classifiers":[
        {
            "category":"Home & Garden",
            "subcategory":"Furniture",
            "type":"Retail Goods"
        }
    ],
    "sg:phone":"+1 305 638 1030",
    "sg:postcode":"33125",
    "sg:province":"FL",
    "sg:tags":[
        "store"
    ],
    "wof:name":"Family Furniture Corp",
    "wof:placetype":"venue"
},
  "geometry": {"coordinates":[-80.253874,25.789149],"type":"Point"}
}