{
  "type": "Feature",
  "properties": {
    "addr:full":"2126 James L Redman Pkwy Plant City FL 33563",
    "addr:housenumber":"2126",
    "addr:postcode":"33563",
    "addr:street":"James L Redman Pkwy",
    "iso:country":"US",
    "sg:address":"2126 James L Redman Pkwy",
    "sg:city":"Plant City",
    "sg:classifiers":[
        {
            "category":"Banks & Credit Unions",
            "subcategory":"Bank",
            "type":"Services"
        }
    ],
    "sg:phone":"+1 813 752 6399",
    "sg:postcode":"33563",
    "sg:province":"FL",
    "sg:tags":[
        "personal",
        "institution"
    ],
    "wof:name":"American General Fin 09071700",
    "wof:placetype":"venue"
},
  "geometry": {"coordinates":[-82.121469,27.991903],"type":"Point"}
}