{
  "type": "Feature",
  "properties": {
    "iso:country":"US",
    "sg:address":"15615 E Colonial Dr",
    "sg:city":"Orlando",
    "sg:classifiers":[
        {
            "category":"Home & Garden",
            "subcategory":"Carpets & Floor Coverings",
            "type":"Retail Goods"
        }
    ],
    "sg:phone":"+1 407 568 1199",
    "sg:postcode":"32820",
    "sg:province":"FL",
    "sg:tags":[
        "contractor"
    ],
    "wof:name":"Tile Warehouse",
    "wof:placetype":"venue"
},
  "geometry": {"coordinates":[-81.153817,28.565493],"type":"Point"}
}