{
  "type": "Feature",
  "properties": {
    "iso:country":"US",
    "sg:address":"715 NW 1st St",
    "sg:city":"Dania",
    "sg:classifiers":[
        {
            "category":"Restaurant",
            "type":"Food & Drink"
        }
    ],
    "sg:phone":"+1 954 922 1168",
    "sg:postcode":"33004",
    "sg:province":"FL",
    "wof:name":"Touch Of Class",
    "wof:placetype":"venue"
},
  "geometry": {"coordinates":[-80.148476,26.053967],"type":"Point"}
}