{
  "type": "Feature",
  "properties": {
    "addr:full":"26300 Hickory Blvd Bonita Springs FL 34134",
    "addr:housenumber":"26300",
    "addr:postcode":"34134",
    "addr:street":"Hickory Blvd",
    "iso:country":"US",
    "sg:address":"26300 Hickory Blvd",
    "sg:city":"Bonita Springs",
    "sg:classifiers":[
        {
            "category":"Real Estate",
            "subcategory":"Real Estate Operator",
            "type":"Services"
        }
    ],
    "sg:phone":"+1 239 495 0225",
    "sg:postcode":"34134",
    "sg:province":"FL",
    "sg:tags":[
        "condominium"
    ],
    "wof:name":"Ambassador Condominium",
    "wof:placetype":"venue"
},
  "geometry": {"coordinates":[-81.856737,26.355249],"type":"Point"}
}