{
  "type": "Feature",
  "properties": {
    "addr:full":"612 Geneva Dr Oviedo FL 32765",
    "addr:housenumber":"612",
    "addr:postcode":"32765",
    "addr:street":"Geneva Dr",
    "iso:country":"US",
    "sg:address":"612 Geneva Dr",
    "sg:city":"Oviedo",
    "sg:classifiers":[
        {
            "category":"Retail",
            "subcategory":"Veterinary Services",
            "type":"Services"
        }
    ],
    "sg:phone":"+1 407 365 6947",
    "sg:postcode":"32765",
    "sg:province":"FL",
    "wof:name":"Oviedo Animal Hospital",
    "wof:placetype":"venue"
},
  "geometry": {"coordinates":[-81.19868099999999,28.676944],"type":"Point"}
}