{
  "type": "Feature",
  "properties": {
    "iso:country":"US",
    "sg:address":"1250 14th Ct SW",
    "sg:city":"Largo",
    "sg:classifiers":[
        {
            "category":"Professional",
            "subcategory":"Lawyer & Legal Services",
            "type":"Services"
        }
    ],
    "sg:phone":"+1 863 686 3348",
    "sg:postcode":"33770",
    "sg:province":"FL",
    "sg:tags":[
        "attorney",
        "referral"
    ],
    "wof:name":"Attorneys' Certified Referral",
    "wof:placetype":"venue"
},
  "geometry": {"coordinates":[-82.80076699999999,27.904419],"type":"Point"}
}