{
  "type": "Feature",
  "properties": {
    "iso:country":"US",
    "sg:address":"2760 Belfort Rd",
    "sg:city":"Jacksonville",
    "sg:classifiers":[
        {
            "category":"Personal",
            "subcategory":"Beauty Salon",
            "type":"Services"
        }
    ],
    "sg:phone":"+1 904 928 0396",
    "sg:postcode":"32216",
    "sg:province":"FL",
    "wof:name":"Sports Lady Beauty Salon",
    "wof:placetype":"venue"
},
  "geometry": {"coordinates":[-81.570705,30.276515],"type":"Point"}
}