{
  "type": "Feature",
  "properties": {
    "addr:full":"2466 W Brandon Blvd Brandon FL 33511",
    "addr:housenumber":"2466",
    "addr:postcode":"33511",
    "addr:street":"W Brandon Blvd",
    "iso:country":"US",
    "sg:address":"2466 W Brandon Blvd",
    "sg:city":"Brandon",
    "sg:classifiers":[
        {
            "category":"Shopping",
            "subcategory":"Clothing, Apparel, & Fashions",
            "type":"Retail Goods"
        }
    ],
    "sg:phone":"+1 813 662 3763",
    "sg:postcode":"33511",
    "sg:province":"FL",
    "wof:name":"Dots Inc",
    "wof:placetype":"venue"
},
  "geometry": {"coordinates":[-82.323261,27.939134],"type":"Point"}
}