{
  "type": "Feature",
  "properties": {
    "iso:country":"US",
    "sg:address":"223 Westshore Plz",
    "sg:city":"Tampa",
    "sg:classifiers":[
        {
            "category":"Shopping",
            "subcategory":"Computers & Home Electronics",
            "type":"Retail Goods"
        }
    ],
    "sg:phone":"+1 813 287 8835",
    "sg:postcode":"33609",
    "sg:province":"FL",
    "sg:tags":[
        "software"
    ],
    "wof:name":"Gamestop 1826",
    "wof:placetype":"venue"
},
  "geometry": {"coordinates":[-82.527252,27.946861],"type":"Point"}
}