{
  "type": "Feature",
  "properties": {
    "addr:full":"1000 Industrial Rd Sebring FL 33870",
    "addr:housenumber":"1000",
    "addr:postcode":"33870",
    "addr:street":"Industrial Rd",
    "iso:country":"US",
    "sg:address":"1000 Industrial Rd",
    "sg:city":"Sebring",
    "sg:classifiers":[
        {
            "category":"Retail",
            "subcategory":"Repair Shop",
            "type":"Services"
        }
    ],
    "sg:phone":"+1 863 385 9300",
    "sg:postcode":"33870",
    "sg:province":"FL",
    "sg:tags":[
        "equipment",
        "hydraulic"
    ],
    "wof:name":"Layton Industries",
    "wof:placetype":"venue"
},
  "geometry": {"coordinates":[-81.434918,27.482066],"type":"Point"}
}