{
  "type": "Feature",
  "properties": {
    "iso:country":"US",
    "sg:address":"4101 N Combee Rd",
    "sg:city":"Lakeland",
    "sg:classifiers":[
        {
            "category":"Home & Garden",
            "subcategory":"Furniture",
            "type":"Retail Goods"
        },
        {
            "category":"Wholesale",
            "subcategory":"Home Furnishings",
            "type":"Manufacturing & Wholesale Goods"
        }
    ],
    "sg:phone":"+1 863 665 1568",
    "sg:postcode":"33805",
    "sg:province":"FL",
    "sg:tags":[
        "equipment-wholesale",
        "kitchen",
        "equipment-household",
        "manufacturer",
        "cabinet"
    ],
    "wof:name":"Eddie Richardson Cabinets",
    "wof:placetype":"venue"
},
  "geometry": {"coordinates":[-81.90561099999999,28.093602],"type":"Point"}
}