{
  "type": "Feature",
  "properties": {
    "addr:full":"149 NW 70th St Boca Raton FL 33487",
    "addr:housenumber":"149",
    "addr:postcode":"33487",
    "addr:street":"Nw 70Th St",
    "iso:country":"US",
    "sg:address":"149 NW 70th St",
    "sg:city":"Boca Raton",
    "sg:classifiers":[
        {
            "category":"Wholesale",
            "subcategory":"Auto Parts",
            "type":"Manufacturing & Wholesale Goods"
        }
    ],
    "sg:phone":"+1 561 988 2210",
    "sg:postcode":"33487",
    "sg:province":"FL",
    "sg:tags":[
        "car",
        "export"
    ],
    "wof:name":"European Export Group Inc",
    "wof:placetype":"venue"
},
  "geometry": {"coordinates":[-80.080528,26.4118],"type":"Point"}
}