{
  "type": "Feature",
  "properties": {
    "iso:country":"US",
    "sg:address":"2515 Oak St",
    "sg:city":"Jacksonville",
    "sg:classifiers":[
        {
            "category":"Professional",
            "subcategory":"Business Services",
            "type":"Services"
        }
    ],
    "sg:phone":"+1 904 384 5405",
    "sg:postcode":"32204",
    "sg:province":"FL",
    "sg:tags":[
        "transcribing",
        "disc"
    ],
    "wof:name":"Telstar Transcription",
    "wof:placetype":"venue"
},
  "geometry": {"coordinates":[-81.68934,30.310291],"type":"Point"}
}