{
  "type": "Feature",
  "properties": {
    "iso:country":"US",
    "sg:address":"4200 32nd St W",
    "sg:city":"Bradenton",
    "sg:classifiers":[
        {
            "category":"Place Of Worship",
            "subcategory":"Synagogue",
            "type":"Public Place"
        },
        {
            "category":"Place Of Worship",
            "type":"Public Place"
        }
    ],
    "sg:phone":"+1 941 755 4900",
    "sg:postcode":"34205",
    "sg:province":"FL",
    "sg:tags":[
        "synagogues-conservative",
        "church"
    ],
    "wof:name":"Temple Beth El",
    "wof:placetype":"venue"
},
  "geometry": {"coordinates":[-82.593784,27.464046],"type":"Point"}
}