{
  "type": "Feature",
  "properties": {
    "iso:country":"US",
    "sg:address":"11308 Welcome Church St",
    "sg:city":"Lithia",
    "sg:classifiers":[
        {
            "category":"Place Of Worship",
            "subcategory":"Church",
            "type":"Public Place"
        },
        {
            "category":"Place Of Worship",
            "type":"Public Place"
        }
    ],
    "sg:phone":"+1 813 737 2288",
    "sg:postcode":"33547",
    "sg:province":"FL",
    "sg:tags":[
        "churches-baptist-general",
        "churches-baptist"
    ],
    "wof:name":"Welcome Baptist Church Inc",
    "wof:placetype":"venue"
},
  "geometry": {"coordinates":[-82.100345,27.835963],"type":"Point"}
}