{
  "type": "Feature",
  "properties": {
    "addr:full":"7422 Pinewalk Dr S Pompano Beach FL 33063",
    "addr:housenumber":"7422",
    "addr:postcode":"33063",
    "addr:street":"Pinewalk Dr S",
    "iso:country":"US",
    "sg:address":"7422 Pinewalk Dr S",
    "sg:city":"Pompano Beach",
    "sg:classifiers":[
        {
            "category":"Professional",
            "subcategory":"Computer Services",
            "type":"Services"
        }
    ],
    "sg:phone":"+1 954 755 9891",
    "sg:postcode":"33063",
    "sg:province":"FL",
    "sg:tags":[
        "programing",
        "custom"
    ],
    "wof:name":"Showcase Hosting Inc",
    "wof:placetype":"venue"
},
  "geometry": {"coordinates":[-80.225932,26.261109],"type":"Point"}
}