{
  "type": "Feature",
  "properties": {
    "addr:full":"3500 NW 37th Ave Miami FL 33142",
    "addr:housenumber":"3500",
    "addr:postcode":"33142",
    "addr:street":"Nw 37Th Ave",
    "iso:country":"US",
    "sg:address":"3500 NW 37th Ave",
    "sg:city":"Miami",
    "sg:classifiers":[
        {
            "category":"Restaurant",
            "type":"Food & Drink"
        },
        {
            "category":"Casinos & Gambling",
            "type":"Entertainment"
        },
        {
            "category":"Recreation",
            "type":"Entertainment"
        }
    ],
    "sg:phone":"+1 305 633 6400",
    "sg:postcode":"33142",
    "sg:province":"FL",
    "sg:tags":[
        "active",
        "flavor",
        "local",
        "life"
    ],
    "sg:website":"www.fla-gaming.com/miami/",
    "wof:name":"Miami Jai-Alai Fronton",
    "wof:placetype":"venue"
},
  "geometry": {"coordinates":[-80.25630200000001,25.808001],"type":"Point"}
}