{
  "type": "Feature",
  "properties": {
    "iso:country":"US",
    "sg:address":"928 E New Haven Ave",
    "sg:city":"Melbourne",
    "sg:classifiers":[
        {
            "category":"Banks & Credit Unions",
            "subcategory":"Investment Brokerage",
            "type":"Services"
        }
    ],
    "sg:phone":"+1 321 728 1196",
    "sg:postcode":"32901",
    "sg:province":"FL",
    "sg:tags":[
        "security"
    ],
    "wof:name":"SunAmerica",
    "wof:placetype":"venue"
},
  "geometry": {"coordinates":[-80.605649,28.078483],"type":"Point"}
}