{
  "type": "Feature",
  "properties": {
    "addr:full":"25 Country Club Rd Cocoa Beach FL 32931",
    "addr:housenumber":"25",
    "addr:postcode":"32931",
    "addr:street":"Country Club Rd",
    "iso:country":"US",
    "sg:address":"25 Country Club Rd",
    "sg:city":"Cocoa Beach",
    "sg:classifiers":[
        {
            "category":"Professional",
            "type":"Services"
        }
    ],
    "sg:phone":"+1 321 784 8523",
    "sg:postcode":"32931",
    "sg:province":"FL",
    "wof:name":"Endless Summer Villas Inc",
    "wof:placetype":"venue"
},
  "geometry": {"coordinates":[-80.636396,28.321572],"type":"Point"}
}