{
  "type": "Feature",
  "properties": {
    "addr:full":"8070 Mediterranean Dr Estero FL 33928",
    "addr:housenumber":"8070",
    "addr:postcode":"33928",
    "addr:street":"Mediterranean Dr",
    "iso:country":"US",
    "sg:address":"8070 Mediterranean Dr",
    "sg:city":"Estero",
    "sg:classifiers":[
        {
            "category":"Shopping",
            "subcategory":"Clothing, Apparel, & Fashions",
            "type":"Retail Goods"
        },
        {
            "category":"Shopping",
            "subcategory":"Party Supplies",
            "type":"Retail Goods"
        }
    ],
    "sg:phone":"+1 239 495 7233",
    "sg:postcode":"33928",
    "sg:province":"FL",
    "sg:tags":[
        "decoration",
        "favors",
        "delivery",
        "balloons-retail",
        "costume"
    ],
    "sg:website":"http://www.partycity.com",
    "wof:name":"Party City",
    "wof:placetype":"venue"
},
  "geometry": {"coordinates":[-81.808229,26.404743],"type":"Point"}
}