{
  "type": "Feature",
  "properties": {
    "addr:full":"5125 NE 3rd Ct. #1 Miami FL 33137",
    "addr:housenumber":"5125",
    "addr:postcode":"33137",
    "addr:street":"Ne 3Rd Ct. # 1",
    "iso:country":"US",
    "sg:address":"5125 NE 3rd Ct. #1",
    "sg:city":"Miami",
    "sg:classifiers":[
        {
            "category":"Professional",
            "subcategory":"Art Services",
            "type":"Services"
        }
    ],
    "sg:phone":"+1 305 801 2661",
    "sg:postcode":"33137",
    "sg:province":"FL",
    "sg:tags":[
        "photographer"
    ],
    "sg:website":"www.craigdenis.com",
    "wof:name":"Craig Denis: Photography",
    "wof:placetype":"venue"
},
  "geometry": {"coordinates":[-80.18883700000001,25.823166],"type":"Point"}
}