{
  "type": "Feature",
  "properties": {
    "iso:country":"US",
    "sg:address":"13413 Southern Way",
    "sg:city":"Windermere",
    "sg:classifiers":[
        {
            "category":"Building & Trades",
            "subcategory":"Construction",
            "type":"Services"
        }
    ],
    "sg:phone":"+1 407 656 3003",
    "sg:postcode":"34786",
    "sg:province":"FL",
    "sg:tags":[
        "hanging",
        "contractor"
    ],
    "wof:name":"D Braunheim Painting",
    "wof:placetype":"venue"
},
  "geometry": {"coordinates":[-81.58005300000001,28.486629],"type":"Point"}
}