{
  "type": "Feature",
  "properties": {
    "addr:full":"1101 3rd St SW Winter Haven FL 33880",
    "addr:housenumber":"1101",
    "addr:postcode":"33880",
    "addr:street":"3Rd St Sw",
    "iso:country":"US",
    "sg:address":"1101 3rd St SW",
    "sg:city":"Winter Haven",
    "sg:classifiers":[
        {
            "category":"Shopping",
            "subcategory":"Shoes",
            "type":"Retail Goods"
        }
    ],
    "sg:phone":"+1 863 294 6696",
    "sg:postcode":"33880",
    "sg:province":"FL",
    "sg:tags":[
        "shoe",
        "store"
    ],
    "wof:name":"Payless Shoe Source",
    "wof:placetype":"venue"
},
  "geometry": {"coordinates":[-81.73092699999999,28.013624],"type":"Point"}
}