{
  "type": "Feature",
  "properties": {
    "addr:full":"2266 2nd St Fort Myers FL 33901",
    "addr:housenumber":"2266",
    "addr:postcode":"33901",
    "addr:street":"2Nd St",
    "iso:country":"US",
    "sg:address":"2266 2nd St",
    "sg:city":"Fort Myers",
    "sg:classifiers":[
        {
            "category":"Education",
            "subcategory":"School",
            "type":"Public Place"
        }
    ],
    "sg:phone":"+1 239 334 7172",
    "sg:postcode":"33901",
    "sg:province":"FL",
    "wof:name":"Lee County Adult & Comm Ed",
    "wof:placetype":"venue"
},
  "geometry": {"coordinates":[-81.868222,26.642629],"type":"Point"}
}