{
  "type": "Feature",
  "properties": {
    "addr:full":"1932 Dupont Ct Deltona FL 32725",
    "addr:housenumber":"1932",
    "addr:postcode":"32725",
    "addr:street":"Dupont Ct",
    "iso:country":"US",
    "sg:address":"1932 Dupont Ct",
    "sg:city":"Deltona",
    "sg:classifiers":[
        {
            "category":"Professional",
            "type":"Services"
        }
    ],
    "sg:phone":"+1 386 532 6050",
    "sg:postcode":"32725",
    "sg:province":"FL",
    "wof:name":"Sunshine Micro Inc",
    "wof:placetype":"venue"
},
  "geometry": {"coordinates":[-81.258397,28.917832],"type":"Point"}
}