{
  "type": "Feature",
  "properties": {
    "iso:country":"US",
    "sg:address":"2848 S Mellonville Ave",
    "sg:city":"Sanford",
    "sg:classifiers":[
        {
            "category":"Wholesale",
            "subcategory":"Medical Equipment & Supplies",
            "type":"Manufacturing & Wholesale Goods"
        }
    ],
    "sg:phone":"+1 407 585 4220",
    "sg:postcode":"32773",
    "sg:province":"FL",
    "sg:tags":[
        "physician",
        "surgeon"
    ],
    "wof:name":"Herrington Medical Assoc",
    "wof:placetype":"venue"
},
  "geometry": {"coordinates":[-81.256202,28.775916],"type":"Point"}
}