{
  "type": "Feature",
  "properties": {
    "addr:full":"26901 Clarkston Dr Bonita Springs FL 34135",
    "addr:postcode":"26901;34135",
    "addr:street":"Clarkston Dr",
    "iso:country":"US",
    "sg:address":"26901 Clarkston Dr",
    "sg:city":"Bonita Springs",
    "sg:classifiers":[
        {
            "category":"Real Estate",
            "subcategory":"Architect",
            "type":"Services"
        }
    ],
    "sg:phone":"+1 239 947 8491",
    "sg:postcode":"34135",
    "sg:province":"FL",
    "sg:tags":[
        "building",
        "construction"
    ],
    "wof:name":"Bnp Construction Concepts",
    "wof:placetype":"venue"
},
  "geometry": {"coordinates":[-81.803327,26.348031],"type":"Point"}
}