{
  "type": "Feature",
  "properties": {
    "iso:country":"US",
    "sg:address":"954 W State Road 434",
    "sg:city":"Longwood",
    "sg:classifiers":[
        {
            "category":"Retail",
            "subcategory":"Laundry & Dry Cleaning",
            "type":"Services"
        }
    ],
    "sg:phone":"+1 407 339 8551",
    "sg:postcode":"32750",
    "sg:province":"FL",
    "wof:name":"Orchid Cleaners",
    "wof:placetype":"venue"
},
  "geometry": {"coordinates":[-81.36129800000001,28.697901],"type":"Point"}
}