{
  "type": "Feature",
  "properties": {
    "iso:country":"US",
    "sg:address":"7801 NW 37th St",
    "sg:city":"Doral",
    "sg:classifiers":[
        {
            "category":"Professional",
            "type":"Services"
        }
    ],
    "sg:phone":"+1 305 599 9107",
    "sg:postcode":"33166",
    "sg:province":"FL",
    "wof:name":"Technical Buying Svc",
    "wof:placetype":"venue"
},
  "geometry": {"coordinates":[-80.325282,25.80794],"type":"Point"}
}