{
  "type": "Feature",
  "properties": {
    "addr:full":"3110 N Davis Hwy Pensacola FL 32503",
    "addr:housenumber":"3110",
    "addr:postcode":"32503",
    "addr:street":"N Davis Hwy",
    "iso:country":"US",
    "sg:address":"3110 N Davis Hwy",
    "sg:city":"Pensacola",
    "sg:classifiers":[
        {
            "category":"Building & Trades",
            "subcategory":"Plumbing",
            "type":"Services"
        }
    ],
    "sg:phone":"+1 850 438 7561",
    "sg:postcode":"32503",
    "sg:province":"FL",
    "sg:tags":[
        "conditioning",
        "air",
        "system",
        "contractor"
    ],
    "wof:name":"Quigley Cooling Heating Elctrc",
    "wof:placetype":"venue"
},
  "geometry": {"coordinates":[-87.21552200000001,30.446753],"type":"Point"}
}