{
  "type": "Feature",
  "properties": {
    "iso:country":"US",
    "sg:address":"2133 Mariner Blvd",
    "sg:city":"Spring Hill",
    "sg:classifiers":[
        {
            "category":"Shopping",
            "subcategory":"Computers & Home Electronics",
            "type":"Retail Goods"
        }
    ],
    "sg:phone":"+1 352 684 3522",
    "sg:postcode":"34609",
    "sg:province":"FL",
    "wof:name":"Spring Hill Computers",
    "wof:placetype":"venue"
},
  "geometry": {"coordinates":[-82.540556,28.462217],"type":"Point"}
}