{
  "type": "Feature",
  "properties": {
    "iso:country":"US",
    "sg:address":"4835 W Eau Gallie Blvd",
    "sg:city":"Melbourne",
    "sg:classifiers":[
        {
            "category":"Shopping",
            "subcategory":"Used Merchandise",
            "type":"Retail Goods"
        }
    ],
    "sg:phone":"+1 321 751 1031",
    "sg:postcode":"32934",
    "sg:province":"FL",
    "sg:tags":[
        "flea",
        "market"
    ],
    "wof:name":"Harbor City Handbag",
    "wof:placetype":"venue"
},
  "geometry": {"coordinates":[-80.707595,28.120441],"type":"Point"}
}