{
  "type": "Feature",
  "properties": {
    "iso:country":"US",
    "sg:address":"2617 Aurelia Pl",
    "sg:city":"Fort Lauderdale",
    "sg:classifiers":[
        {
            "category":"Wholesale",
            "subcategory":"Jewelry",
            "type":"Manufacturing & Wholesale Goods"
        }
    ],
    "sg:phone":"+1 954 467 6604",
    "sg:postcode":"33301",
    "sg:province":"FL",
    "sg:tags":[
        "stone"
    ],
    "wof:name":"Game Fish Trophies",
    "wof:placetype":"venue"
},
  "geometry": {"coordinates":[-80.10984500000001,26.115997],"type":"Point"}
}