{
  "type": "Feature",
  "properties": {
    "addr:full":"5 Balfour Rd E Palm Beach Gardens FL 33418",
    "addr:housenumber":"5",
    "addr:postcode":"33418",
    "addr:street":"Balfour Rd E",
    "iso:country":"US",
    "sg:address":"5 Balfour Rd E",
    "sg:city":"Palm Beach Gardens",
    "sg:classifiers":[
        {
            "category":"Real Estate",
            "subcategory":"Real Estate Agent",
            "type":"Services"
        }
    ],
    "sg:phone":"+1 561 624 2006",
    "sg:postcode":"33418",
    "sg:province":"FL",
    "wof:name":"John L Greenberg & Assoc",
    "wof:placetype":"venue"
},
  "geometry": {"coordinates":[-80.13959800000001,26.833513],"type":"Point"}
}