{
  "type": "Feature",
  "properties": {
    "addr:full":"11440 Okeechobee Blvd Royal Palm Beach FL 33411",
    "addr:housenumber":"11440",
    "addr:postcode":"33411",
    "addr:street":"Okeechobee Blvd",
    "iso:country":"US",
    "sg:address":"11440 Okeechobee Blvd",
    "sg:city":"Royal Palm Beach",
    "sg:classifiers":[
        {
            "category":"Professional",
            "subcategory":"Lawyer & Legal Services",
            "type":"Services"
        }
    ],
    "sg:phone":"+1 561 792 1771",
    "sg:postcode":"33411",
    "sg:province":"FL",
    "sg:tags":[
        "attorney"
    ],
    "wof:name":"Monica K Caruso",
    "wof:placetype":"venue"
},
  "geometry": {"coordinates":[-80.209172,26.709328],"type":"Point"}
}