{
  "type": "Feature",
  "properties": {
    "addr:full":"2310 Pine Ridge Rd Naples FL 34109",
    "addr:housenumber":"2310",
    "addr:postcode":"34109",
    "addr:street":"Pine Ridge Rd",
    "iso:country":"US",
    "sg:address":"2310 Pine Ridge Rd",
    "sg:city":"Naples",
    "sg:classifiers":[
        {
            "category":"Food & Beverages",
            "subcategory":"Groceries & Convenience Stores",
            "type":"Retail Goods"
        }
    ],
    "sg:phone":"+1 239 435 0387",
    "sg:postcode":"34109",
    "sg:province":"FL",
    "sg:tags":[
        "florist",
        "grocer"
    ],
    "wof:name":"Publix Super Market 488",
    "wof:placetype":"venue"
},
  "geometry": {"coordinates":[-81.769609,26.211582],"type":"Point"}
}