{
  "type": "Feature",
  "properties": {
    "iso:country":"US",
    "sg:address":"12916 SW 133rd Ct",
    "sg:city":"Miami",
    "sg:classifiers":[
        {
            "category":"Professional",
            "subcategory":"Computer Services",
            "type":"Services"
        }
    ],
    "sg:phone":"+1 305 971 4520",
    "sg:postcode":"33186",
    "sg:province":"FL",
    "sg:tags":[
        "repair"
    ],
    "wof:name":"Cloud 9 Solutions Inc",
    "wof:placetype":"venue"
},
  "geometry": {"coordinates":[-80.410146,25.646804],"type":"Point"}
}