{
  "type": "Feature",
  "properties": {
    "addr:full":"4809 SW 91st Ter Gainesville FL 32608",
    "addr:housenumber":"4809",
    "addr:postcode":"32608",
    "addr:street":"Sw 91St Ter",
    "iso:country":"US",
    "sg:address":"4809 SW 91st Ter",
    "sg:city":"Gainesville",
    "sg:classifiers":[
        {
            "category":"Professional",
            "subcategory":"Lawyer & Legal Services",
            "type":"Services"
        }
    ],
    "sg:phone":"+1 352 372 6009",
    "sg:postcode":"32608",
    "sg:province":"FL",
    "sg:tags":[
        "attorney",
        "practice"
    ],
    "wof:name":"M Stephen Stanfield Attorney & Counselor",
    "wof:placetype":"venue"
},
  "geometry": {"coordinates":[-82.43831400000001,29.609535],"type":"Point"}
}