{
  "type": "Feature",
  "properties": {
    "addr:full":"3150 13th Ave N St Petersburg FL 33713",
    "addr:housenumber":"3150",
    "addr:postcode":"33713",
    "addr:street":"13Th Ave N",
    "iso:country":"US",
    "sg:address":"3150 13th Ave N",
    "sg:city":"St Petersburg",
    "sg:classifiers":[
        {
            "category":"Real Estate",
            "subcategory":"Real Estate Agent",
            "type":"Services"
        }
    ],
    "sg:phone":"+1 727 328 2003",
    "sg:postcode":"33713",
    "sg:province":"FL",
    "sg:tags":[
        "inspection"
    ],
    "wof:name":"Second To None Home Inspctns",
    "wof:placetype":"venue"
},
  "geometry": {"coordinates":[-82.675845,27.784518],"type":"Point"}
}