{
  "type": "Feature",
  "properties": {
    "addr:full":"480 N Canal St Canal Point FL 33438",
    "addr:housenumber":"480",
    "addr:postcode":"33438",
    "addr:street":"N Canal St",
    "iso:country":"US",
    "sg:address":"480 N Canal St",
    "sg:city":"Canal Point",
    "sg:classifiers":[
        {
            "category":"Building & Trades",
            "subcategory":"Construction",
            "type":"Services"
        }
    ],
    "sg:phone":"+1 561 924 5879",
    "sg:postcode":"33438",
    "sg:province":"FL",
    "sg:tags":[
        "residential",
        "painting",
        "contractor"
    ],
    "wof:name":"El-Mil Painting Co Inc",
    "wof:placetype":"venue"
},
  "geometry": {"coordinates":[-80.631399,26.863869],"type":"Point"}
}