{
  "type": "Feature",
  "properties": {
    "iso:country":"US",
    "sg:address":"1209 N Flagler Dr",
    "sg:city":"West Palm Beach",
    "sg:classifiers":[
        {
            "category":"Manufacturing",
            "subcategory":"Tools & Machinery",
            "type":"Manufacturing & Wholesale Goods"
        }
    ],
    "sg:phone":"+1 561 722 1153",
    "sg:postcode":"33401",
    "sg:province":"FL",
    "sg:tags":[
        "manufacture",
        "medical",
        "devices"
    ],
    "wof:name":"Avicenna Laser Technology Inc",
    "wof:placetype":"venue"
},
  "geometry": {"coordinates":[-80.050521,26.723411],"type":"Point"}
}