{
  "type": "Feature",
  "properties": {
    "addr:full":"4884 Front St Ponce Inlet FL 32127",
    "addr:housenumber":"4884",
    "addr:postcode":"32127",
    "addr:street":"Front St",
    "iso:country":"US",
    "sg:address":"4884 Front St",
    "sg:city":"Ponce Inlet",
    "sg:classifiers":[
        {
            "category":"Recreation",
            "type":"Entertainment"
        }
    ],
    "sg:phone":"+1 386 767 3406",
    "sg:postcode":"32127",
    "sg:province":"FL",
    "sg:tags":[
        "guide"
    ],
    "wof:name":"Sea Love Marina",
    "wof:placetype":"venue"
},
  "geometry": {"coordinates":[-80.934881,29.082348],"type":"Point"}
}