{
  "type": "Feature",
  "properties": {
    "iso:country":"US",
    "sg:address":"1020 SW Versailles Ave",
    "sg:city":"Port Saint Lucie",
    "sg:classifiers":[
        {
            "category":"Professional",
            "type":"Services"
        }
    ],
    "sg:phone":"+1 772 343 9823",
    "sg:postcode":"34953",
    "sg:province":"FL",
    "wof:name":"Sunny Banks Alf Inc",
    "wof:placetype":"venue"
},
  "geometry": {"coordinates":[-80.37997,27.251465],"type":"Point"}
}