{
  "type": "Feature",
  "properties": {
    "iso:country":"US",
    "sg:address":"31 W Adams St",
    "sg:city":"Jacksonville",
    "sg:classifiers":[
        {
            "category":"Food & Beverages",
            "subcategory":"Groceries & Convenience Stores",
            "type":"Retail Goods"
        }
    ],
    "sg:phone":"+1 904 358 6464",
    "sg:postcode":"32202",
    "sg:province":"FL",
    "wof:name":"11 East Forsyth Apt",
    "wof:placetype":"venue"
},
  "geometry": {"coordinates":[-81.657966,30.32785],"type":"Point"}
}