{
  "type": "Feature",
  "properties": {
    "addr:full":"2667 Spring Glen Ln Apopka FL 32703",
    "addr:housenumber":"2667",
    "addr:postcode":"32703",
    "addr:street":"Spring Glen Ln",
    "iso:country":"US",
    "sg:address":"2667 Spring Glen Ln",
    "sg:city":"Apopka",
    "sg:classifiers":[
        {
            "category":"Building & Trades",
            "subcategory":"Construction",
            "type":"Services"
        }
    ],
    "sg:phone":"+1 407 758 6801",
    "sg:postcode":"32703",
    "sg:province":"FL",
    "sg:tags":[
        "general",
        "contractor"
    ],
    "wof:name":"Daynova",
    "wof:placetype":"venue"
},
  "geometry": {"coordinates":[-81.46169399999999,28.667954],"type":"Point"}
}