{
  "type": "Feature",
  "properties": {
    "addr:full":"1001 SE 15th St Cape Coral FL 33990",
    "addr:housenumber":"1001",
    "addr:postcode":"33990",
    "addr:street":"Se 15Th St",
    "iso:country":"US",
    "sg:address":"1001 SE 15th St",
    "sg:city":"Cape Coral",
    "sg:classifiers":[
        {
            "category":"Manufacturing",
            "subcategory":"Apparel",
            "type":"Manufacturing & Wholesale Goods"
        }
    ],
    "sg:phone":"+1 239 772 0285",
    "sg:postcode":"33990",
    "sg:province":"FL",
    "sg:tags":[
        "upholstery",
        "marine"
    ],
    "wof:name":"Cutting Edge Marine Upholstery",
    "wof:placetype":"venue"
},
  "geometry": {"coordinates":[-81.952941,26.624717],"type":"Point"}
}