{
  "type": "Feature",
  "properties": {
    "iso:country":"US",
    "sg:address":"1370 Mill Rd",
    "sg:city":"Alford",
    "sg:classifiers":[
        {
            "category":"Building & Trades",
            "subcategory":"Construction",
            "type":"Services"
        }
    ],
    "sg:phone":"+1 850 579 1268",
    "sg:postcode":"32420",
    "sg:province":"FL",
    "sg:tags":[
        "excavation",
        "contractor"
    ],
    "wof:name":"Three D Grading",
    "wof:placetype":"venue"
},
  "geometry": {"coordinates":[-85.38116599999999,30.669768],"type":"Point"}
}