{
  "type": "Feature",
  "properties": {
    "addr:full":"1500 Biscayne Blvd # 336 Miami FL 33132",
    "addr:housenumber":"1500",
    "addr:postcode":"33132",
    "addr:street":"Biscayne Blvd # 336",
    "iso:country":"US",
    "sg:address":"1500 Biscayne Blvd # 336",
    "sg:city":"Miami",
    "sg:classifiers":[
        {
            "category":"Education",
            "subcategory":"Library",
            "type":"Public Place"
        }
    ],
    "sg:phone":"+1 305 995 2249",
    "sg:postcode":"33132",
    "sg:province":"FL",
    "sg:website":"http://www.miamicommunitycharterschool.com",
    "wof:name":"Library Media Services",
    "wof:placetype":"venue"
},
  "geometry": {"coordinates":[-80.189072,25.789539],"type":"Point"}
}