{
  "type": "Feature",
  "properties": {
    "addr:full":"1621 Santa Anita Dr Lynn Haven FL 32444",
    "addr:housenumber":"1621",
    "addr:postcode":"32444",
    "addr:street":"Santa Anita Dr",
    "iso:country":"US",
    "sg:address":"1621 Santa Anita Dr",
    "sg:city":"Lynn Haven",
    "sg:classifiers":[
        {
            "category":"Real Estate",
            "subcategory":"Real Estate Agent",
            "type":"Services"
        }
    ],
    "sg:phone":"+1 850 271 0643",
    "sg:postcode":"32444",
    "sg:province":"FL",
    "sg:tags":[
        "inspection"
    ],
    "wof:name":"G & W Home Inspections Inc",
    "wof:placetype":"venue"
},
  "geometry": {"coordinates":[-85.61562600000001,30.235529],"type":"Point"}
}