{
  "type": "Feature",
  "properties": {
    "addr:full":"3800 Tampa Rd Oldsmar FL 34677",
    "addr:housenumber":"3800",
    "addr:postcode":"34677",
    "addr:street":"Tampa Rd",
    "iso:country":"US",
    "sg:address":"3800 Tampa Rd",
    "sg:city":"Oldsmar",
    "sg:classifiers":[
        {
            "category":"Insurance",
            "subcategory":"Insurance Agent",
            "type":"Services"
        },
        {
            "category":"Insurance",
            "subcategory":"Hazard Insurance",
            "type":"Services"
        },
        {
            "category":"Insurance",
            "subcategory":"Title Insurance",
            "type":"Services"
        },
        {
            "category":"Insurance",
            "subcategory":"Life Insurance",
            "type":"Services"
        }
    ],
    "sg:phone":"+1 813 855 7326",
    "sg:postcode":"34677",
    "sg:province":"FL",
    "sg:tags":[
        "business",
        "auto",
        "commercial",
        "homeowner",
        "motorcycle",
        "renter"
    ],
    "wof:name":"Allstate Insurance Company - David Mccarty",
    "wof:placetype":"venue"
},
  "geometry": {"coordinates":[-82.674072,28.04221],"type":"Point"}
}