{
  "type": "Feature",
  "properties": {
    "iso:country":"US",
    "sg:address":"151 Sevilla Ave",
    "sg:city":"Coral Gables",
    "sg:classifiers":[
        {
            "category":"Wholesale",
            "subcategory":"Durable Goods & Equipment",
            "type":"Manufacturing & Wholesale Goods"
        }
    ],
    "sg:phone":"+1 305 446 5511",
    "sg:postcode":"33134",
    "sg:province":"FL",
    "sg:tags":[
        "exporter"
    ],
    "wof:name":"Spanish Consulate General",
    "wof:placetype":"venue"
},
  "geometry": {"coordinates":[-80.25744299999999,25.746483],"type":"Point"}
}