{
  "type": "Feature",
  "properties": {
    "iso:country":"US",
    "sg:address":"110 Harmony Ln",
    "sg:city":"Lake Placid",
    "sg:classifiers":[
        {
            "category":"Building & Trades",
            "subcategory":"Landscaping Services",
            "type":"Services"
        }
    ],
    "sg:phone":"+1 863 699 9270",
    "sg:postcode":"33852",
    "sg:province":"FL",
    "sg:tags":[
        "architect",
        "landscape",
        "architectural"
    ],
    "wof:name":"Baldwin Dale R & Assoc Lndscp",
    "wof:placetype":"venue"
},
  "geometry": {"coordinates":[-81.326341,27.238939],"type":"Point"}
}