{
  "type": "Feature",
  "properties": {
    "iso:country":"US",
    "sg:address":"8500 Harding Ave Ste 114",
    "sg:city":"Miami Beach",
    "sg:classifiers":[
        {
            "category":"Home & Garden",
            "subcategory":"Building Materials",
            "type":"Retail Goods"
        }
    ],
    "sg:phone":"+1 786 704 2878",
    "sg:postcode":"33141",
    "sg:province":"FL",
    "sg:tags":[
        "supply"
    ],
    "wof:name":"Elite Prefab Homes",
    "wof:placetype":"venue"
},
  "geometry": {"coordinates":[-80.122463,25.869952],"type":"Point"}
}