{
  "type": "Feature",
  "properties": {
    "addr:full":"13011 Scottish Pine Ln Clermont FL 34711",
    "addr:postcode":"13011;34711",
    "addr:street":"Scottish Pine Ln",
    "iso:country":"US",
    "sg:address":"13011 Scottish Pine Ln",
    "sg:city":"Clermont",
    "sg:classifiers":[
        {
            "category":"Building & Trades",
            "subcategory":"Construction",
            "type":"Services"
        }
    ],
    "sg:phone":"+1 352 394 1094",
    "sg:postcode":"34711",
    "sg:province":"FL",
    "sg:tags":[
        "home",
        "improvement"
    ],
    "wof:name":"Cynthia Wright Home Imprvmnts",
    "wof:placetype":"venue"
},
  "geometry": {"coordinates":[-81.70766999999999,28.534636],"type":"Point"}
}