{
  "type": "Feature",
  "properties": {
    "iso:country":"US",
    "sg:address":"3801 Whitehall St",
    "sg:city":"Jacksonville",
    "sg:classifiers":[
        {
            "category":"Freight",
            "type":"Transportation"
        }
    ],
    "sg:phone":"+1 904 353 2020",
    "sg:postcode":"32206",
    "sg:province":"FL",
    "sg:tags":[
        "hauling",
        "trucking"
    ],
    "wof:name":"Cadillac Express",
    "wof:placetype":"venue"
},
  "geometry": {"coordinates":[-81.651383,30.361455],"type":"Point"}
}