{
  "type": "Feature",
  "properties": {
    "iso:country":"US",
    "sg:address":"445 State Hwy 13",
    "sg:city":"Jacksonville",
    "sg:classifiers":[
        {
            "category":"Building & Trades",
            "subcategory":"Landscaping Services",
            "type":"Services"
        }
    ],
    "sg:phone":"+1 904 287 1712",
    "sg:postcode":"32259",
    "sg:province":"FL",
    "sg:tags":[
        "landscape",
        "contractor"
    ],
    "wof:name":"St Johns Nursery Inc",
    "wof:placetype":"venue"
},
  "geometry": {"coordinates":[-81.625647,30.11932],"type":"Point"}
}