{
  "type": "Feature",
  "properties": {
    "iso:country":"US",
    "sg:address":"5550 Overseas Hwy",
    "sg:city":"Marathon",
    "sg:classifiers":[
        {
            "category":"Museum",
            "type":"Entertainment"
        }
    ],
    "sg:phone":"+1 305 743 9100",
    "sg:postcode":"33050",
    "sg:province":"FL",
    "wof:name":"Museums & Nature Ctr Of Crane",
    "wof:placetype":"venue"
},
  "geometry": {"coordinates":[-81.07501000000001,24.716415],"type":"Point"}
}