{
  "type": "Feature",
  "properties": {
    "addr:full":"475 Biltmore Way Miami FL 33134",
    "addr:housenumber":"475",
    "addr:postcode":"33134",
    "addr:street":"Biltmore Way",
    "iso:country":"US",
    "sg:address":"475 Biltmore Way",
    "sg:city":"Miami",
    "sg:classifiers":[
        {
            "category":"Health Services",
            "subcategory":"Doctor",
            "type":"Services"
        }
    ],
    "sg:phone":"+1 305 446 7376",
    "sg:postcode":"33134",
    "sg:province":"FL",
    "sg:tags":[
        "medical"
    ],
    "wof:name":"Richard J Lung MD",
    "wof:placetype":"venue"
},
  "geometry": {"coordinates":[-80.264382,25.748392],"type":"Point"}
}