{
  "type": "Feature",
  "properties": {
    "addr:full":"8812 Grow Dr Pensacola FL 32514",
    "addr:housenumber":"8812",
    "addr:postcode":"32514",
    "addr:street":"Grow Dr",
    "iso:country":"US",
    "sg:address":"8812 Grow Dr",
    "sg:city":"Pensacola",
    "sg:classifiers":[
        {
            "category":"Manufacturing",
            "subcategory":"Tools & Machinery",
            "type":"Manufacturing & Wholesale Goods"
        }
    ],
    "sg:phone":"+1 850 476 7900",
    "sg:postcode":"32514",
    "sg:province":"FL",
    "sg:tags":[
        "equipment",
        "lighting"
    ],
    "wof:name":"Logical Development Corp",
    "wof:placetype":"venue"
},
  "geometry": {"coordinates":[-87.18990700000001,30.52262],"type":"Point"}
}