{
  "type": "Feature",
  "properties": {
    "iso:country":"US",
    "sg:address":"11682 US Hwy 1",
    "sg:city":"North Palm Beach",
    "sg:classifiers":[
        {
            "category":"Restaurant",
            "type":"Food & Drink"
        }
    ],
    "sg:phone":"+1 561 622 0014",
    "sg:postcode":"33408",
    "sg:province":"FL",
    "sg:tags":[
        "eating"
    ],
    "wof:name":"Habitat Cafe",
    "wof:placetype":"venue"
},
  "geometry": {"coordinates":[-80.0605,26.846055],"type":"Point"}
}