{
  "type": "Feature",
  "properties": {
    "addr:full":"19287 Sabal Lake Dr Boca Raton FL 33434",
    "addr:housenumber":"19287",
    "addr:postcode":"33434",
    "addr:street":"Sabal Lake Dr",
    "iso:country":"US",
    "sg:address":"19287 Sabal Lake Dr",
    "sg:city":"Boca Raton",
    "sg:classifiers":[
        {
            "category":"Banks & Credit Unions",
            "subcategory":"Financial Services",
            "type":"Services"
        }
    ],
    "sg:phone":"+1 561 483 3770",
    "sg:postcode":"33434",
    "sg:province":"FL",
    "sg:tags":[
        "investor"
    ],
    "wof:name":"Augusta Investing Partners",
    "wof:placetype":"venue"
},
  "geometry": {"coordinates":[-80.15712000000001,26.390731],"type":"Point"}
}