{
  "type": "Feature",
  "properties": {
    "iso:country":"US",
    "sg:address":"7542 Tarpon Cove Cir",
    "sg:city":"Lake Worth",
    "sg:classifiers":[
        {
            "category":"Building & Trades",
            "subcategory":"Electrical",
            "type":"Services"
        }
    ],
    "sg:phone":"+1 561 967 9338",
    "sg:postcode":"33467",
    "sg:province":"FL",
    "sg:tags":[
        "installation"
    ],
    "wof:name":"Cool Blocks",
    "wof:placetype":"venue"
},
  "geometry": {"coordinates":[-80.180778,26.564019],"type":"Point"}
}