{
  "type": "Feature",
  "properties": {
    "addr:full":"3200 Griffin Rd Wesley Chapel FL 33543",
    "addr:housenumber":"3200",
    "addr:postcode":"33543",
    "addr:street":"Griffin Rd",
    "iso:country":"US",
    "sg:address":"3200 Griffin Rd",
    "sg:city":"Wesley Chapel",
    "sg:classifiers":[
        {
            "category":"Retail",
            "subcategory":"Auto Repair",
            "type":"Services"
        }
    ],
    "sg:phone":"+1 954 989 9090",
    "sg:postcode":"33543",
    "sg:province":"FL",
    "sg:tags":[
        "wrecker"
    ],
    "wof:name":"A Best Towing",
    "wof:placetype":"venue"
},
  "geometry": {"coordinates":[-82.26016199999999,28.207912],"type":"Point"}
}