{
  "type": "Feature",
  "properties": {
    "iso:country":"US",
    "sg:address":"8055 W 23rd Ave",
    "sg:city":"Hialeah",
    "sg:classifiers":[
        {
            "category":"Wholesale",
            "subcategory":"Apparel",
            "type":"Manufacturing & Wholesale Goods"
        }
    ],
    "sg:phone":"+1 305 826 2065",
    "sg:postcode":"33016",
    "sg:province":"FL",
    "sg:tags":[
        "handbag",
        "such",
        "as",
        "accessory"
    ],
    "wof:name":"Le Pierre Import & Export",
    "wof:placetype":"venue"
},
  "geometry": {"coordinates":[-80.32975999999999,25.896959],"type":"Point"}
}