{
  "type": "Feature",
  "properties": {
    "iso:country":"US",
    "sg:address":"424 Campus St",
    "sg:city":"Kissimmee",
    "sg:classifiers":[
        {
            "category":"Professional",
            "subcategory":"Business Services",
            "type":"Services"
        }
    ],
    "sg:phone":"+1 407 566 8161",
    "sg:postcode":"34747",
    "sg:province":"FL",
    "sg:tags":[
        "consultant",
        "coach"
    ],
    "wof:name":"Laga Enterprises",
    "wof:placetype":"venue"
},
  "geometry": {"coordinates":[-81.547217,28.322212],"type":"Point"}
}