{
  "type": "Feature",
  "properties": {
    "addr:full":"545 Alafaya Woods Blvd Oviedo FL 32765",
    "addr:housenumber":"545",
    "addr:postcode":"32765",
    "addr:street":"Alafaya Woods Blvd",
    "iso:country":"US",
    "sg:address":"545 Alafaya Woods Blvd",
    "sg:city":"Oviedo",
    "sg:classifiers":[
        {
            "category":"Professional",
            "subcategory":"Research",
            "type":"Services"
        }
    ],
    "sg:phone":"+1 407 359 3312",
    "sg:postcode":"32765",
    "sg:province":"FL",
    "sg:tags":[
        "environmental",
        "ecological"
    ],
    "wof:name":"Environmental Tectonics Corp",
    "wof:placetype":"venue"
},
  "geometry": {"coordinates":[-81.198965,28.648587],"type":"Point"}
}