{
  "type": "Feature",
  "properties": {
    "iso:country":"US",
    "sg:address":"19331 Preserve Dr",
    "sg:city":"Boca Raton",
    "sg:classifiers":[
        {
            "category":"Organizations",
            "subcategory":"Professional Association",
            "type":"Services"
        }
    ],
    "sg:phone":"+1 561 477 9261",
    "sg:postcode":"33498",
    "sg:province":"FL",
    "wof:name":"Boca Isles Club Inc",
    "wof:placetype":"venue"
},
  "geometry": {"coordinates":[-80.214505,26.386636],"type":"Point"}
}