{
  "type": "Feature",
  "properties": {
    "iso:country":"US",
    "sg:address":"825 Washington Ave.",
    "sg:city":"Miami Beach",
    "sg:classifiers":[
        {
            "category":"Coffee & Tea",
            "type":"Food & Drink"
        },
        {
            "category":"Food & Beverages",
            "subcategory":"Bakery",
            "type":"Retail Goods"
        }
    ],
    "sg:phone":"+1 305 938 4013",
    "sg:postcode":"33139",
    "sg:province":"FL",
    "sg:tags":[
        "sandwich"
    ],
    "wof:name":"Suno Cafe",
    "wof:placetype":"venue"
},
  "geometry": {"coordinates":[-80.13288300000001,25.778747],"type":"Point"}
}