{
  "type": "Feature",
  "properties": {
    "addr:full":"2000 S Dixie Hwy Miami FL 33133",
    "addr:housenumber":"2000",
    "addr:postcode":"33133",
    "addr:street":"S Dixie Hwy",
    "iso:country":"US",
    "sg:address":"2000 S Dixie Hwy",
    "sg:city":"Miami",
    "sg:classifiers":[
        {
            "category":"Social Services",
            "type":"Services"
        },
        {
            "category":"Health Services",
            "subcategory":"Doctor",
            "type":"Services"
        },
        {
            "category":"Education",
            "subcategory":"Special Training",
            "type":"Public Place"
        },
        {
            "category":"Personal",
            "type":"Services"
        },
        {
            "category":"Social Services",
            "subcategory":"Job Training",
            "type":"Services"
        }
    ],
    "sg:phone":"+1 305 858 8557",
    "sg:postcode":"33133",
    "sg:province":"FL",
    "sg:tags":[
        "career",
        "counseling",
        "psychologist",
        "employment",
        "vocational"
    ],
    "wof:name":"A Career Counseling Center",
    "wof:placetype":"venue"
},
  "geometry": {"coordinates":[-80.225792,25.74427],"type":"Point"}
}