{
  "type": "Feature",
  "properties": {
    "iso:country":"US",
    "sg:address":"6355 NW 36th St",
    "sg:city":"Virginia Gardens",
    "sg:classifiers":[
        {
            "category":"Banks & Credit Unions",
            "subcategory":"Financial Services",
            "type":"Services"
        }
    ],
    "sg:phone":"+1 305 871 5155",
    "sg:postcode":"33166",
    "sg:province":"FL",
    "sg:tags":[
        "broker",
        "mortgage"
    ],
    "wof:name":"Pier 51 Mortgage",
    "wof:placetype":"venue"
},
  "geometry": {"coordinates":[-80.300072,25.807454],"type":"Point"}
}