{
  "type": "Feature",
  "properties": {
    "iso:country":"US",
    "sg:address":"1998 NE 188th St",
    "sg:city":"Miami",
    "sg:classifiers":[
        {
            "category":"Professional",
            "subcategory":"Computer Services",
            "type":"Services"
        }
    ],
    "sg:phone":"+1 305 937 7799",
    "sg:postcode":"33179",
    "sg:province":"FL",
    "sg:tags":[
        "consultant",
        "designer",
        "design",
        "network",
        "system"
    ],
    "wof:name":"Micronix International Corp",
    "wof:placetype":"venue"
},
  "geometry": {"coordinates":[-80.160698,25.949039],"type":"Point"}
}