{
  "type": "Feature",
  "properties": {
    "iso:country":"US",
    "sg:address":"2109 W US Hwy 90",
    "sg:city":"Lake City",
    "sg:classifiers":[
        {
            "category":"Professional",
            "subcategory":"Management & Consulting",
            "type":"Services"
        }
    ],
    "sg:phone":"+1 407 352 1200",
    "sg:postcode":"32055",
    "sg:province":"FL",
    "sg:tags":[
        "consultant",
        "educational"
    ],
    "wof:name":"Kathleen Appleby",
    "wof:placetype":"venue"
},
  "geometry": {"coordinates":[-82.653891,30.18539],"type":"Point"}
}