{
  "type": "Feature",
  "properties": {
    "iso:country":"US",
    "sg:address":"3166 SE Dixie Hwy",
    "sg:city":"Stuart",
    "sg:classifiers":[
        {
            "category":"Shopping",
            "subcategory":"Stationery & Office Supplies",
            "type":"Retail Goods"
        },
        {
            "category":"Retail",
            "subcategory":"Repair Shop",
            "type":"Services"
        },
        {
            "category":"Wholesale",
            "subcategory":"Machinery & Supplies",
            "type":"Manufacturing & Wholesale Goods"
        }
    ],
    "sg:phone":"+1 772 287 6437",
    "sg:postcode":"34997",
    "sg:province":"FL",
    "sg:tags":[
        "major",
        "refinishing",
        "washer",
        "appliance",
        "dryer",
        "small",
        "part",
        "shaver",
        "tools-repairing",
        "freezers-repair",
        "refrigerator",
        "electric"
    ],
    "sg:website":"http://www.realpagessites.com/appliancedoctors",
    "wof:name":"Appliance Doctors",
    "wof:placetype":"venue"
},
  "geometry": {"coordinates":[-80.219956,27.166189],"type":"Point"}
}