{
  "type": "Feature",
  "properties": {
    "iso:country":"US",
    "sg:address":"2091 NW 141st St",
    "sg:city":"Opa Locka",
    "sg:classifiers":[
        {
            "category":"Real Estate",
            "subcategory":"Developer",
            "type":"Services"
        }
    ],
    "sg:phone":"+1 305 638 6557",
    "sg:postcode":"33054",
    "sg:province":"FL",
    "sg:tags":[
        "land"
    ],
    "wof:name":"Model Cy Dev of Dade Cnty Inc",
    "wof:placetype":"venue"
},
  "geometry": {"coordinates":[-80.232618,25.903077],"type":"Point"}
}