{
  "type": "Feature",
  "properties": {
    "addr:full":"721 Blanding Blvd Orange Park FL 32065",
    "addr:housenumber":"721",
    "addr:postcode":"32065",
    "addr:street":"Blanding Blvd",
    "iso:country":"US",
    "sg:address":"721 Blanding Blvd",
    "sg:city":"Orange Park",
    "sg:classifiers":[
        {
            "category":"Building & Trades",
            "subcategory":"Construction",
            "type":"Services"
        }
    ],
    "sg:phone":"+1 904 276 7854",
    "sg:postcode":"32065",
    "sg:province":"FL",
    "sg:tags":[
        "roof",
        "maintenance"
    ],
    "wof:name":"Chem-Techs Roofing Cleaning",
    "wof:placetype":"venue"
},
  "geometry": {"coordinates":[-81.759884,30.146222],"type":"Point"}
}