{
  "type": "Feature",
  "properties": {
    "addr:full":"1900 S Ocean Blvd Pompano Beach FL 33062",
    "addr:housenumber":"1900",
    "addr:postcode":"33062",
    "addr:street":"S Ocean Blvd",
    "iso:country":"US",
    "sg:address":"1900 S Ocean Blvd",
    "sg:city":"Pompano Beach",
    "sg:classifiers":[
        {
            "category":"Building & Trades",
            "subcategory":"Construction",
            "type":"Services"
        }
    ],
    "sg:phone":"+1 954 234 1851",
    "sg:postcode":"33062",
    "sg:province":"FL",
    "sg:tags":[
        "dry wall",
        "contractor"
    ],
    "wof:name":"Algen Drywall",
    "wof:placetype":"venue"
},
  "geometry": {"coordinates":[-80.094471,26.205745],"type":"Point"}
}