{
  "type": "Feature",
  "properties": {
    "iso:country":"US",
    "sg:address":"1921 E Memorial Blvd",
    "sg:city":"Lakeland",
    "sg:classifiers":[
        {
            "category":"Retail",
            "subcategory":"Auto Repair",
            "type":"Services"
        }
    ],
    "sg:phone":"+1 863 686 8270",
    "sg:postcode":"33801",
    "sg:province":"FL",
    "sg:tags":[
        "repairing",
        "automobile"
    ],
    "wof:name":"Tom's Automotive Ctr",
    "wof:placetype":"venue"
},
  "geometry": {"coordinates":[-81.92589,28.049428],"type":"Point"}
}