{
  "type": "Feature",
  "properties": {
    "iso:country":"US",
    "sg:address":"17958 47th Ct N",
    "sg:city":"Loxahatchee",
    "sg:classifiers":[
        {
            "category":"Manufacturing",
            "subcategory":"Tools & Machinery",
            "type":"Manufacturing & Wholesale Goods"
        }
    ],
    "sg:phone":"+1 561 798 5832",
    "sg:postcode":"33470",
    "sg:province":"FL",
    "sg:tags":[
        "electrical",
        "mfg"
    ],
    "wof:name":"Trevdil Inc",
    "wof:placetype":"venue"
},
  "geometry": {"coordinates":[-80.3263,26.748832],"type":"Point"}
}