{
  "type": "Feature",
  "properties": {
    "addr:full":"9834 Fairway Cove Ln Fort Lauderdale FL 33324",
    "addr:housenumber":"9834",
    "addr:postcode":"33324",
    "addr:street":"Fairway Cove Ln",
    "iso:country":"US",
    "sg:address":"9834 Fairway Cove Ln",
    "sg:city":"Fort Lauderdale",
    "sg:classifiers":[
        {
            "category":"Professional",
            "subcategory":"Management & Consulting",
            "type":"Services"
        }
    ],
    "sg:phone":"+1 954 475 3992",
    "sg:postcode":"33324",
    "sg:province":"FL",
    "wof:name":"Florida Dynamic Marketing",
    "wof:placetype":"venue"
},
  "geometry": {"coordinates":[-80.279954,26.11379],"type":"Point"}
}