{
  "type": "Feature",
  "properties": {
    "addr:full":"300 Aragon Ave Miami FL 33134",
    "addr:housenumber":"300",
    "addr:postcode":"33134",
    "addr:street":"Aragon Ave",
    "iso:country":"US",
    "sg:address":"300 Aragon Ave",
    "sg:city":"Miami",
    "sg:classifiers":[
        {
            "category":"Building & Trades",
            "subcategory":"Construction",
            "type":"Services"
        }
    ],
    "sg:phone":"+1 305 529 2555",
    "sg:postcode":"33134",
    "sg:province":"FL",
    "sg:tags":[
        "residential",
        "commercial",
        "contractor"
    ],
    "wof:name":"C D I Construction Inc",
    "wof:placetype":"venue"
},
  "geometry": {"coordinates":[-80.26274600000001,25.750245],"type":"Point"}
}