{
  "type": "Feature",
  "properties": {
    "iso:country":"US",
    "sg:address":"17123 SW 79th Pl",
    "sg:city":"Miami",
    "sg:classifiers":[
        {
            "category":"Wholesale",
            "subcategory":"Metals & Minerals",
            "type":"Manufacturing & Wholesale Goods"
        }
    ],
    "sg:phone":"+1 305 259 3949",
    "sg:postcode":"33157",
    "sg:province":"FL",
    "sg:tags":[
        "item",
        "export",
        "miscellaneous"
    ],
    "wof:name":"Rik International Inc",
    "wof:placetype":"venue"
},
  "geometry": {"coordinates":[-80.32179600000001,25.611451],"type":"Point"}
}