{
  "type": "Feature",
  "properties": {
    "iso:country":"US",
    "sg:address":"1130 19th St",
    "sg:city":"Vero Beach",
    "sg:classifiers":[
        {
            "category":"Wholesale",
            "subcategory":"Chemicals & Plastics",
            "type":"Manufacturing & Wholesale Goods"
        }
    ],
    "sg:phone":"+1 772 567 0822",
    "sg:postcode":"32960",
    "sg:province":"FL",
    "sg:tags":[
        "oxygen"
    ],
    "wof:name":"Lincare",
    "wof:placetype":"venue"
},
  "geometry": {"coordinates":[-80.397482,27.636223],"type":"Point"}
}