{
  "type": "Feature",
  "properties": {
    "addr:full":"904 15th Ave W Palmetto FL 34221",
    "addr:housenumber":"904",
    "addr:postcode":"34221",
    "addr:street":"15Th Ave W",
    "iso:country":"US",
    "sg:address":"904 15th Ave W",
    "sg:city":"Palmetto",
    "sg:classifiers":[
        {
            "category":"Building & Trades",
            "subcategory":"Construction",
            "type":"Services"
        }
    ],
    "sg:phone":"+1 941 729 3939",
    "sg:postcode":"34221",
    "sg:province":"FL",
    "sg:tags":[
        "handyman"
    ],
    "wof:name":"Optimal Computer Repair",
    "wof:placetype":"venue"
},
  "geometry": {"coordinates":[-82.58255800000001,27.520131],"type":"Point"}
}