{
  "type": "Feature",
  "properties": {
    "addr:full":"1555 Saxon Blvd Ste 101 Deltona FL 32725",
    "addr:housenumber":"1555",
    "addr:postcode":"32725",
    "addr:street":"Saxon Blvd Ste 101",
    "iso:country":"US",
    "sg:address":"1555 Saxon Blvd Ste 101",
    "sg:city":"Deltona",
    "sg:classifiers":[
        {
            "category":"Health Services",
            "subcategory":"Health Practitioner",
            "type":"Services"
        }
    ],
    "sg:phone":"+1 386 574 5247",
    "sg:postcode":"32725",
    "sg:province":"FL",
    "sg:tags":[
        "therapy",
        "physical"
    ],
    "sg:website":"www.selectphysicaltherapy.com",
    "wof:name":"Select Physical Therapy",
    "wof:placetype":"venue"
},
  "geometry": {"coordinates":[-81.245678,28.905498],"type":"Point"}
}