{
  "type": "Feature",
  "properties": {
    "iso:country":"US",
    "sg:address":"4804 NW 97th Ter",
    "sg:city":"Fort Lauderdale",
    "sg:classifiers":[
        {
            "category":"Building & Trades",
            "subcategory":"Plumbing",
            "type":"Services"
        }
    ],
    "sg:phone":"+1 954 747 4941",
    "sg:postcode":"33351",
    "sg:province":"FL",
    "sg:tags":[
        "fire",
        "system",
        "installation",
        "sprinkler",
        "contractor"
    ],
    "wof:name":"J & J Fire Protection Inc",
    "wof:placetype":"venue"
},
  "geometry": {"coordinates":[-80.280981,26.183222],"type":"Point"}
}