{
  "type": "Feature",
  "properties": {
    "addr:full":"3599 Lenox Ave Jacksonville FL 32254",
    "addr:housenumber":"3599",
    "addr:postcode":"32254",
    "addr:street":"Lenox Ave",
    "iso:country":"US",
    "sg:address":"3599 Lenox Ave",
    "sg:city":"Jacksonville",
    "sg:classifiers":[
        {
            "category":"Building & Trades",
            "subcategory":"Construction",
            "type":"Services"
        }
    ],
    "sg:phone":"+1 904 387 1011",
    "sg:postcode":"32254",
    "sg:province":"FL",
    "sg:tags":[
        "general",
        "contractor"
    ],
    "wof:name":"Bob Mathews Construction Co",
    "wof:placetype":"venue"
},
  "geometry": {"coordinates":[-81.713832,30.321915],"type":"Point"}
}