{
  "type": "Feature",
  "properties": {
    "addr:full":"1860 W 10th St Riviera Beach FL 33404",
    "addr:housenumber":"1860",
    "addr:postcode":"33404",
    "addr:street":"W 10Th St",
    "iso:country":"US",
    "sg:address":"1860 W 10th St",
    "sg:city":"Riviera Beach",
    "sg:classifiers":[
        {
            "category":"Wholesale",
            "subcategory":"Construction Materials",
            "type":"Manufacturing & Wholesale Goods"
        },
        {
            "category":"Home & Garden",
            "subcategory":"Building Materials",
            "type":"Retail Goods"
        }
    ],
    "sg:phone":"+1 561 881 5700",
    "sg:postcode":"33404",
    "sg:province":"FL",
    "sg:tags":[
        "drywall"
    ],
    "sg:website":"www.rewmaterials.com",
    "wof:name":"Rew Materials",
    "wof:placetype":"venue"
},
  "geometry": {"coordinates":[-80.086766,26.772791],"type":"Point"}
}