{
  "type": "Feature",
  "properties": {
    "iso:country":"US",
    "sg:address":"1 Alhambra Plz",
    "sg:city":"Miami",
    "sg:classifiers":[
        {
            "category":"Banks & Credit Unions",
            "subcategory":"Investment Brokerage",
            "type":"Services"
        }
    ],
    "sg:phone":"+1 305 648 3322",
    "sg:postcode":"33134",
    "sg:province":"FL",
    "sg:tags":[
        "advisory"
    ],
    "wof:name":"Cipher Investment Mgt Co",
    "wof:placetype":"venue"
},
  "geometry": {"coordinates":[-80.256788,25.752271],"type":"Point"}
}