{
  "type": "Feature",
  "properties": {
    "addr:full":"970 Jeffery St Boca Raton FL 33487",
    "addr:housenumber":"970",
    "addr:postcode":"33487",
    "addr:street":"Jeffery St",
    "iso:country":"US",
    "sg:address":"970 Jeffery St",
    "sg:city":"Boca Raton",
    "sg:classifiers":[
        {
            "category":"Shopping",
            "type":"Retail Goods"
        }
    ],
    "sg:phone":"+1 561 995 2495",
    "sg:postcode":"33487",
    "sg:province":"FL",
    "sg:tags":[
        "wheel",
        "chair",
        "scooter"
    ],
    "wof:name":"MJM Global Enterprises",
    "wof:placetype":"venue"
},
  "geometry": {"coordinates":[-80.071895,26.402182],"type":"Point"}
}