{
  "type": "Feature",
  "properties": {
    "iso:country":"US",
    "sg:address":"535 S McDuff Ave",
    "sg:city":"Jacksonville",
    "sg:classifiers":[
        {
            "category":"Personal",
            "subcategory":"Beauty Salon",
            "type":"Services"
        }
    ],
    "sg:phone":"+1 904 381 9440",
    "sg:postcode":"32254",
    "sg:province":"FL",
    "wof:name":"Top Hair Design",
    "wof:placetype":"venue"
},
  "geometry": {"coordinates":[-81.70537299999999,30.321469],"type":"Point"}
}