{
  "type": "Feature",
  "properties": {
    "iso:country":"US",
    "sg:address":"136 Malaga St",
    "sg:city":"Saint Augustine",
    "sg:classifiers":[
        {
            "category":"Banks & Credit Unions",
            "subcategory":"Investment Brokerage",
            "type":"Services"
        }
    ],
    "sg:phone":"+1 904 824 8147",
    "sg:postcode":"32084",
    "sg:province":"FL",
    "sg:tags":[
        "planning",
        "financial"
    ],
    "wof:name":"Lifetime Fincl Strategies LLC",
    "wof:placetype":"venue"
},
  "geometry": {"coordinates":[-81.32076000000001,29.891423],"type":"Point"}
}