{
  "type": "Feature",
  "properties": {
    "iso:country":"US",
    "sg:address":"75 Spooner Rd",
    "sg:city":"Quincy",
    "sg:classifiers":[
        {
            "category":"Travel",
            "subcategory":"Hotels & Motels",
            "type":"Entertainment"
        }
    ],
    "sg:phone":"+1 850 875 2500",
    "sg:postcode":"32351",
    "sg:province":"FL",
    "wof:name":"Holiday Inn Express Quincy",
    "wof:placetype":"venue"
},
  "geometry": {"coordinates":[-84.595451,30.53473],"type":"Point"}
}