{
  "type": "Feature",
  "properties": {
    "addr:full":"1 SE 3rd Ave Ste 2110 Miami FL 33131",
    "addr:housenumber":"1",
    "addr:postcode":"33131",
    "addr:street":"Se 3Rd Ave Ste 2110",
    "iso:country":"US",
    "sg:address":"1 SE 3rd Ave Ste 2110",
    "sg:city":"Miami",
    "sg:classifiers":[
        {
            "category":"Professional",
            "subcategory":"Lawyer & Legal Services",
            "type":"Services"
        }
    ],
    "sg:phone":"+1 305 358 6033",
    "sg:postcode":"33131",
    "sg:province":"FL",
    "wof:name":"Simon Steven Atty",
    "wof:placetype":"venue"
},
  "geometry": {"coordinates":[-80.189003,25.7743],"type":"Point"}
}