{
  "type": "Feature",
  "properties": {
    "iso:country":"US",
    "sg:address":"3740 Bird Rd",
    "sg:city":"Miami",
    "sg:classifiers":[
        {
            "category":"Building & Trades",
            "subcategory":"Locksmith",
            "type":"Services"
        }
    ],
    "sg:phone":"+1 305 357 4929",
    "sg:postcode":"33146",
    "sg:province":"FL",
    "sg:tags":[
        "key"
    ],
    "wof:name":"A 24 All Day Emergency Locksmith",
    "wof:placetype":"venue"
},
  "geometry": {"coordinates":[-80.254772,25.73491],"type":"Point"}
}