{
  "type": "Feature",
  "properties": {
    "addr:full":"1650 N State Rd 7 Hollywood FL 33021",
    "addr:housenumber":"1650;7",
    "addr:postcode":"33021",
    "addr:street":"N State Rd",
    "iso:country":"US",
    "sg:address":"1650 N State Rd 7",
    "sg:city":"Hollywood",
    "sg:classifiers":[
        {
            "category":"Autos & Motor Vehicles",
            "subcategory":"Motorcycle Sales",
            "type":"Retail Goods"
        }
    ],
    "sg:phone":"+1 954 981 9889",
    "sg:postcode":"33021",
    "sg:province":"FL",
    "wof:name":"Street Toys",
    "wof:placetype":"venue"
},
  "geometry": {"coordinates":[-80.208253,26.025328],"type":"Point"}
}