{
  "type": "Feature",
  "properties": {
    "addr:full":"1382 S Babcock St Melbourne FL 32901",
    "addr:housenumber":"1382",
    "addr:postcode":"32901",
    "addr:street":"S Babcock St",
    "iso:country":"US",
    "sg:address":"1382 S Babcock St",
    "sg:city":"Melbourne",
    "sg:classifiers":[
        {
            "category":"Recreation",
            "subcategory":"Amusement Park",
            "type":"Entertainment"
        }
    ],
    "sg:phone":"+1 321 837 1414",
    "sg:postcode":"32901",
    "sg:province":"FL",
    "wof:name":"Starlight Palace",
    "wof:placetype":"venue"
},
  "geometry": {"coordinates":[-80.62189499999999,28.087204],"type":"Point"}
}