{
  "type": "Feature",
  "properties": {
    "addr:full":"12590 Emerald Coast Pkwy W Destin FL 32550",
    "addr:housenumber":"12590",
    "addr:postcode":"32550",
    "addr:street":"Emerald Coast Pkwy W",
    "iso:country":"US",
    "sg:address":"12590 Emerald Coast Pkwy W",
    "sg:city":"Destin",
    "sg:classifiers":[
        {
            "category":"Building & Trades",
            "subcategory":"Construction",
            "type":"Services"
        }
    ],
    "sg:phone":"+1 850 269 9898",
    "sg:postcode":"32550",
    "sg:province":"FL",
    "sg:tags":[
        "house",
        "builder",
        "home"
    ],
    "sg:website":"www.centexhomes.com",
    "wof:name":"Centex Homes",
    "wof:placetype":"venue"
},
  "geometry": {"coordinates":[-86.381145,30.385187],"type":"Point"}
}