{
  "type": "Feature",
  "properties": {
    "iso:country":"US",
    "sg:address":"3560 Main Highway",
    "sg:city":"Miami",
    "sg:classifiers":[
        {
            "category":"Real Estate",
            "subcategory":"Real Estate Services",
            "type":"Services"
        },
        {
            "category":"Real Estate",
            "subcategory":"Real Estate Agent",
            "type":"Services"
        }
    ],
    "sg:phone":"+1 305 342 1623",
    "sg:postcode":"33133",
    "sg:province":"FL",
    "sg:website":"www.therealestatecoconut.com",
    "wof:name":"Riley Smith - Coconut Grove / Coral Gables Realtor",
    "wof:placetype":"venue"
},
  "geometry": {"coordinates":[-80.245514,25.72456],"type":"Point"}
}