{
  "type": "Feature",
  "properties": {
    "addr:full":"7052 SW 46th St Miami FL 33155",
    "addr:housenumber":"7052",
    "addr:postcode":"33155",
    "addr:street":"Sw 46Th St",
    "iso:country":"US",
    "sg:address":"7052 SW 46th St",
    "sg:city":"Miami",
    "sg:classifiers":[
        {
            "category":"Wholesale",
            "subcategory":"Machinery & Supplies",
            "type":"Manufacturing & Wholesale Goods"
        }
    ],
    "sg:phone":"+1 305 661 8147",
    "sg:postcode":"33155",
    "sg:province":"FL",
    "sg:tags":[
        "equipment",
        "industrial",
        "caning"
    ],
    "wof:name":"W G Harward Co",
    "wof:placetype":"venue"
},
  "geometry": {"coordinates":[-80.308221,25.727989],"type":"Point"}
}