{
  "type": "Feature",
  "properties": {
    "iso:country":"US",
    "sg:address":"201 N US Hwy 1",
    "sg:city":"Jupiter",
    "sg:classifiers":[
        {
            "category":"Restaurant",
            "type":"Food & Drink"
        }
    ],
    "sg:phone":"+1 561 747 2231",
    "sg:postcode":"33477",
    "sg:province":"FL",
    "sg:tags":[
        "parlor",
        "ice",
        "cream"
    ],
    "wof:name":"Cold Stone Creamery",
    "wof:placetype":"venue"
},
  "geometry": {"coordinates":[-80.08162900000001,26.935576],"type":"Point"}
}