{
  "type": "Feature",
  "properties": {
    "iso:country":"US",
    "sg:address":"3310 Apalachee Pkwy",
    "sg:city":"Tallahassee",
    "sg:classifiers":[
        {
            "category":"Retail",
            "subcategory":"Auto Repair",
            "type":"Services"
        }
    ],
    "sg:phone":"+1 850 309 0600",
    "sg:postcode":"32311",
    "sg:province":"FL",
    "sg:tags":[
        "repairing",
        "automobile"
    ],
    "wof:name":"Auto Super Svc Ctr",
    "wof:placetype":"venue"
},
  "geometry": {"coordinates":[-84.219098,30.427891],"type":"Point"}
}