{
  "type": "Feature",
  "properties": {
    "iso:country":"US",
    "sg:address":"13313 US Hwy 92",
    "sg:city":"Dover",
    "sg:classifiers":[
        {
            "category":"Home & Garden",
            "subcategory":"Building Materials",
            "type":"Retail Goods"
        },
        {
            "category":"Building & Trades",
            "subcategory":"Construction",
            "type":"Services"
        }
    ],
    "sg:phone":"+1 813 659 0141",
    "sg:postcode":"33527",
    "sg:province":"FL",
    "sg:tags":[
        "portable",
        "utility"
    ],
    "wof:name":"Langston's Utility Buildings",
    "wof:placetype":"venue"
},
  "geometry": {"coordinates":[-82.229737,28.01922],"type":"Point"}
}