{
  "type": "Feature",
  "properties": {
    "addr:full":"2261 W Dolphin Dr Citrus Springs FL 34434",
    "addr:housenumber":"2261",
    "addr:postcode":"34434",
    "addr:street":"W Dolphin Dr",
    "iso:country":"US",
    "sg:address":"2261 W Dolphin Dr",
    "sg:city":"Citrus Springs",
    "sg:classifiers":[
        {
            "category":"Manufacturing",
            "subcategory":"Signs",
            "type":"Manufacturing & Wholesale Goods"
        }
    ],
    "sg:phone":"+1 352 522 7446",
    "sg:postcode":"34434",
    "sg:province":"FL",
    "wof:name":"Hy-Impact Signs",
    "wof:placetype":"venue"
},
  "geometry": {"coordinates":[-82.470799,28.981572],"type":"Point"}
}