{
  "type": "Feature",
  "properties": {
    "addr:full":"28 NE 29th St Miami FL 33137",
    "addr:housenumber":"28",
    "addr:postcode":"33137",
    "addr:street":"Ne 29Th St",
    "iso:country":"US",
    "sg:address":"28 NE 29th St",
    "sg:city":"Miami",
    "sg:classifiers":[
        {
            "category":"Autos & Motor Vehicles",
            "subcategory":"Automobile Sales",
            "type":"Retail Goods"
        }
    ],
    "sg:phone":"+1 305 572 1140",
    "sg:postcode":"33137",
    "sg:province":"FL",
    "sg:tags":[
        "car",
        "dealer"
    ],
    "wof:name":"Auto Max Of Miami Inc",
    "wof:placetype":"venue"
},
  "geometry": {"coordinates":[-80.19458299999999,25.803911],"type":"Point"}
}