{
  "type": "Feature",
  "properties": {
    "addr:full":"1061 A1a Beach Blvd Saint Augustine FL 32080",
    "addr:housenumber":"1061",
    "addr:postcode":"32080",
    "addr:street":"A1A Beach Blvd",
    "iso:country":"US",
    "sg:address":"1061 A1a Beach Blvd",
    "sg:city":"Saint Augustine",
    "sg:classifiers":[
        {
            "category":"Restaurant",
            "type":"Food & Drink"
        }
    ],
    "sg:menulink":"http://www.allmenus.com/fl/st-augustine/99333-beef-obradys/menu/",
    "sg:phone":"+1 904 461 5771",
    "sg:postcode":"32080",
    "sg:province":"FL",
    "sg:tags":[
        "burger",
        "american",
        "wing",
        "pub"
    ],
    "wof:name":"Beef O'Brady's",
    "wof:placetype":"venue"
},
  "geometry": {"coordinates":[-81.271134,29.827769],"type":"Point"}
}