{
  "type": "Feature",
  "properties": {
    "iso:country":"US",
    "sg:address":"610 18th Ave NE",
    "sg:city":"Naples",
    "sg:classifiers":[
        {
            "category":"Real Estate",
            "subcategory":"Surveying",
            "type":"Services"
        }
    ],
    "sg:phone":"+1 239 352 6085",
    "sg:postcode":"34120",
    "sg:province":"FL",
    "sg:tags":[
        "surveyor"
    ],
    "wof:name":"Dagostino & Wood",
    "wof:placetype":"venue"
},
  "geometry": {"coordinates":[-81.59499599999999,26.262742],"type":"Point"}
}