{
  "type": "Feature",
  "properties": {
    "iso:country":"US",
    "sg:address":"3239 S John Young Pkwy",
    "sg:city":"Kissimmee",
    "sg:classifiers":[
        {
            "category":"Wholesale",
            "subcategory":"Machinery & Supplies",
            "type":"Manufacturing & Wholesale Goods"
        }
    ],
    "sg:phone":"+1 407 870 1876",
    "sg:postcode":"34746",
    "sg:province":"FL",
    "sg:tags":[
        "equipment",
        "establishment"
    ],
    "wof:name":"Gigis Beauty Supplies & Home",
    "wof:placetype":"venue"
},
  "geometry": {"coordinates":[-81.434584,28.261489],"type":"Point"}
}