{
  "type": "Feature",
  "properties": {
    "iso:country":"US",
    "sg:address":"7345 Mardell Ct",
    "sg:city":"Orlando",
    "sg:classifiers":[
        {
            "category":"Retail",
            "subcategory":"Portrait Studio",
            "type":"Services"
        },
        {
            "category":"Professional",
            "subcategory":"Art Services",
            "type":"Services"
        }
    ],
    "sg:phone":"+1 407 293 2532",
    "sg:postcode":"32835",
    "sg:province":"FL",
    "sg:tags":[
        "rental",
        "photographers-portrait",
        "photographic",
        "darkroom"
    ],
    "wof:name":"Gregg Photography Inc",
    "wof:placetype":"venue"
},
  "geometry": {"coordinates":[-81.488023,28.507851],"type":"Point"}
}