{
  "type": "Feature",
  "properties": {
    "iso:country":"US",
    "sg:address":"1500 Gay Rd",
    "sg:city":"Winter Park",
    "sg:classifiers":[
        {
            "category":"Real Estate",
            "subcategory":"Real Estate Agent",
            "type":"Services"
        },
        {
            "category":"Real Estate",
            "subcategory":"Real Estate Operator",
            "type":"Services"
        }
    ],
    "sg:phone":"+1 407 644 1232",
    "sg:postcode":"32789",
    "sg:province":"FL",
    "sg:tags":[
        "condominium"
    ],
    "wof:name":"Chateaux Du Lac Condominiums",
    "wof:placetype":"venue"
},
  "geometry": {"coordinates":[-81.36693099999999,28.601807],"type":"Point"}
}