{
  "type": "Feature",
  "properties": {
    "addr:full":"805 20th St Vero Beach FL 32960",
    "addr:housenumber":"805",
    "addr:postcode":"32960",
    "addr:street":"20Th St",
    "iso:country":"US",
    "sg:address":"805 20th St",
    "sg:city":"Vero Beach",
    "sg:classifiers":[
        {
            "category":"Shopping",
            "subcategory":"Florist",
            "type":"Retail Goods"
        }
    ],
    "sg:phone":"+1 772 567 3474",
    "sg:postcode":"32960",
    "sg:province":"FL",
    "sg:website":"www.artisticfirstflorist.net",
    "wof:name":"Artistic First Florist",
    "wof:placetype":"venue"
},
  "geometry": {"coordinates":[-80.39117899999999,27.637999],"type":"Point"}
}