{
  "type": "Feature",
  "properties": {
    "addr:full":"2409 Walnut Heights Rd Apopka FL 32703",
    "addr:housenumber":"2409",
    "addr:postcode":"32703",
    "addr:street":"Walnut Heights Rd",
    "iso:country":"US",
    "sg:address":"2409 Walnut Heights Rd",
    "sg:city":"Apopka",
    "sg:classifiers":[
        {
            "category":"Manufacturing",
            "subcategory":"Rubber & Plastics",
            "type":"Manufacturing & Wholesale Goods"
        }
    ],
    "sg:phone":"+1 407 880 6030",
    "sg:postcode":"32703",
    "sg:province":"FL",
    "sg:tags":[
        "wetsuits",
        "mfg"
    ],
    "wof:name":"Fluid Distribution Inc",
    "wof:placetype":"venue"
},
  "geometry": {"coordinates":[-81.464439,28.681623],"type":"Point"}
}