{
  "type": "Feature",
  "properties": {
    "iso:country":"US",
    "sg:address":"4604 Grainary Ave",
    "sg:city":"Tampa",
    "sg:classifiers":[
        {
            "category":"Shopping",
            "type":"Retail Goods"
        }
    ],
    "sg:phone":"+1 813 961 1129",
    "sg:postcode":"33624",
    "sg:province":"FL",
    "sg:tags":[
        "merchandise"
    ],
    "wof:name":"Iropa Designs",
    "wof:placetype":"venue"
},
  "geometry": {"coordinates":[-82.525395,28.086983],"type":"Point"}
}