{
  "type": "Feature",
  "properties": {
    "addr:full":"1718 Belle Vue Way Tallahassee FL 32304",
    "addr:housenumber":"1718",
    "addr:postcode":"32304",
    "addr:street":"Belle Vue Way",
    "iso:country":"US",
    "sg:address":"1718 Belle Vue Way",
    "sg:city":"Tallahassee",
    "sg:classifiers":[
        {
            "category":"Professional",
            "type":"Services"
        }
    ],
    "sg:phone":"+1 850 893 0608",
    "sg:postcode":"32304",
    "sg:province":"FL",
    "wof:name":"Joanne Mendez",
    "wof:placetype":"venue"
},
  "geometry": {"coordinates":[-84.31010499999999,30.438045],"type":"Point"}
}