{
  "type": "Feature",
  "properties": {
    "iso:country":"US",
    "sg:address":"3216 Shady Hawk Ln",
    "sg:city":"Tallahassee",
    "sg:classifiers":[
        {
            "category":"Insurance",
            "subcategory":"Insurance Agent",
            "type":"Services"
        }
    ],
    "sg:phone":"+1 850 656 2471",
    "sg:postcode":"32309",
    "sg:province":"FL",
    "wof:name":"Associated Bankers Insurance",
    "wof:placetype":"venue"
},
  "geometry": {"coordinates":[-84.110702,30.497838],"type":"Point"}
}