{
  "type": "Feature",
  "properties": {
    "addr:full":"13611 Biscayne Blvd North Miami Bch FL 33184",
    "addr:housenumber":"13611",
    "addr:postcode":"33184",
    "addr:street":"Biscayne Blvd",
    "iso:country":"US",
    "sg:address":"13611 Biscayne Blvd",
    "sg:city":"North Miami Bch",
    "sg:classifiers":[
        {
            "category":"Sports & Exercise",
            "subcategory":"Gym",
            "type":"Entertainment"
        }
    ],
    "sg:phone":"+1 305 940 0212",
    "sg:postcode":"33184",
    "sg:province":"FL",
    "sg:tags":[
        "club",
        "health",
        "studio",
        "gymnasium"
    ],
    "sg:website":"www.ladyofamerica.com",
    "wof:name":"Lady Of America Fitness Ctr",
    "wof:placetype":"venue"
},
  "geometry": {"coordinates":[-80.160388,25.900178],"type":"Point"}
}