{
  "type": "Feature",
  "properties": {
    "addr:full":"138 NW 9th Ave Mulberry FL 33860",
    "addr:housenumber":"138",
    "addr:postcode":"33860",
    "addr:street":"Nw 9Th Ave",
    "iso:country":"US",
    "sg:address":"138 NW 9th Ave",
    "sg:city":"Mulberry",
    "sg:classifiers":[
        {
            "category":"Manufacturing",
            "subcategory":"Printing",
            "type":"Manufacturing & Wholesale Goods"
        }
    ],
    "sg:phone":"+1 863 425 0922",
    "sg:postcode":"33860",
    "sg:province":"FL",
    "sg:tags":[
        "printer"
    ],
    "wof:name":"Graphic Images",
    "wof:placetype":"venue"
},
  "geometry": {"coordinates":[-81.98118700000001,27.895169],"type":"Point"}
}