{
  "type": "Feature",
  "properties": {
    "addr:full":"2041 SW 70th Ave Davie FL 33317",
    "addr:housenumber":"2041",
    "addr:postcode":"33317",
    "addr:street":"Sw 70Th Ave",
    "iso:country":"US",
    "sg:address":"2041 SW 70th Ave",
    "sg:city":"Davie",
    "sg:classifiers":[
        {
            "category":"Personal",
            "type":"Services"
        },
        {
            "category":"Wholesale",
            "subcategory":"Home Furnishings",
            "type":"Manufacturing & Wholesale Goods"
        }
    ],
    "sg:phone":"+1 954 472 8488",
    "sg:postcode":"33317",
    "sg:province":"FL",
    "sg:tags":[
        "table",
        "pad"
    ],
    "sg:website":"www.casino-parties.com",
    "wof:name":"Aristocratic Casino Parties",
    "wof:placetype":"venue"
},
  "geometry": {"coordinates":[-80.23786699999999,26.094214],"type":"Point"}
}