{
  "type": "Feature",
  "properties": {
    "iso:country":"US",
    "sg:address":"1018 NE 44th Ct",
    "sg:city":"Fort Lauderdale",
    "sg:classifiers":[
        {
            "category":"Building & Trades",
            "subcategory":"Plumbing",
            "type":"Services"
        }
    ],
    "sg:phone":"+1 954 492 5566",
    "sg:postcode":"33334",
    "sg:province":"FL",
    "sg:tags":[
        "contractor"
    ],
    "wof:name":"Jones & Jirik Plumbing",
    "wof:placetype":"venue"
},
  "geometry": {"coordinates":[-80.132614,26.182276],"type":"Point"}
}