{
  "type": "Feature",
  "properties": {
    "addr:full":"2486 E Sunrise Blvd Fort Lauderdale FL 33304",
    "addr:housenumber":"2486",
    "addr:postcode":"33304",
    "addr:street":"E Sunrise Blvd",
    "iso:country":"US",
    "sg:address":"2486 E Sunrise Blvd",
    "sg:city":"Fort Lauderdale",
    "sg:classifiers":[
        {
            "category":"Shopping",
            "subcategory":"Clothing, Apparel, & Fashions",
            "type":"Retail Goods"
        }
    ],
    "sg:phone":"+1 954 566 5801",
    "sg:postcode":"33304",
    "sg:province":"FL",
    "wof:name":"Ann Taylor",
    "wof:placetype":"venue"
},
  "geometry": {"coordinates":[-80.11450499999999,26.137748],"type":"Point"}
}