{
  "type": "Feature",
  "properties": {
    "iso:country":"US",
    "sg:address":"2142 E Silver Springs Blvd",
    "sg:city":"Ocala",
    "sg:classifiers":[
        {
            "category":"Shopping",
            "subcategory":"Clothing, Apparel, & Fashions",
            "type":"Retail Goods"
        }
    ],
    "sg:phone":"+1 352 622 8559",
    "sg:postcode":"34470",
    "sg:province":"FL",
    "sg:tags":[
        "shop",
        "bridal"
    ],
    "wof:name":"Mary's Bridal & Formal Wear",
    "wof:placetype":"venue"
},
  "geometry": {"coordinates":[-82.109505,29.186865],"type":"Point"}
}