{
  "type": "Feature",
  "properties": {
    "iso:country":"US",
    "sg:address":"7491 W Irlo Bronson Memorial Hwy",
    "sg:city":"Kissimmee",
    "sg:classifiers":[
        {
            "category":"Professional",
            "subcategory":"Management & Consulting",
            "type":"Services"
        },
        {
            "category":"Recreation",
            "type":"Entertainment"
        }
    ],
    "sg:phone":"+1 407 396 8222",
    "sg:postcode":"34747",
    "sg:province":"FL",
    "sg:tags":[
        "marketing",
        "tourist",
        "attraction"
    ],
    "wof:name":"Orlando Welcome Center",
    "wof:placetype":"venue"
},
  "geometry": {"coordinates":[-81.58682899999999,28.332797],"type":"Point"}
}