{
  "type": "Feature",
  "properties": {
    "iso:country":"US",
    "sg:address":"8894 NW Hwy 320",
    "sg:city":"Micanopy",
    "sg:classifiers":[
        {
            "category":"Farming",
            "subcategory":"Farm",
            "type":"Manufacturing & Wholesale Goods"
        }
    ],
    "sg:phone":"+1 352 591 1255",
    "sg:postcode":"32667",
    "sg:province":"FL",
    "sg:tags":[
        "crop",
        "general"
    ],
    "wof:name":"Alec P Courtelis",
    "wof:placetype":"venue"
},
  "geometry": {"coordinates":[-82.33907600000001,29.455315],"type":"Point"}
}