{
  "type": "Feature",
  "properties": {
    "iso:country":"US",
    "sg:address":"70 SE 4th Ave",
    "sg:city":"Delray Beach",
    "sg:classifiers":[
        {
            "category":"Professional",
            "subcategory":"Lawyer & Legal Services",
            "type":"Services"
        }
    ],
    "sg:phone":"+1 561 265 2220",
    "sg:postcode":"33483",
    "sg:province":"FL",
    "sg:tags":[
        "attorney"
    ],
    "wof:name":"Craig D Earnhart",
    "wof:placetype":"venue"
},
  "geometry": {"coordinates":[-80.06912199999999,26.461115],"type":"Point"}
}