{
  "type": "Feature",
  "properties": {
    "iso:country":"US",
    "sg:address":"9134 Amanda Rd",
    "sg:city":"Panama City",
    "sg:classifiers":[
        {
            "category":"Building & Trades",
            "subcategory":"Construction",
            "type":"Services"
        }
    ],
    "sg:phone":"+1 850 265 5723",
    "sg:postcode":"32409",
    "sg:province":"FL",
    "sg:tags":[
        "contractor"
    ],
    "wof:name":"Tommy Hall Tile LLC",
    "wof:placetype":"venue"
},
  "geometry": {"coordinates":[-85.62063999999999,30.316814],"type":"Point"}
}