{
  "type": "Feature",
  "properties": {
    "iso:country":"US",
    "sg:address":"2644 State Correctional Rd",
    "sg:city":"Marianna",
    "sg:classifiers":[
        {
            "category":"Retail",
            "subcategory":"Repair Shop",
            "type":"Services"
        }
    ],
    "sg:phone":"+1 850 526 7670",
    "sg:postcode":"32448",
    "sg:province":"FL",
    "wof:name":"Smith M D Lawn Mower Eng Rep",
    "wof:placetype":"venue"
},
  "geometry": {"coordinates":[-85.292767,30.758871],"type":"Point"}
}