{
  "type": "Feature",
  "properties": {
    "addr:full":"2135 Coral Gate Dr Miami FL 33145",
    "addr:housenumber":"2135",
    "addr:postcode":"33145",
    "addr:street":"Coral Gate Dr",
    "iso:country":"US",
    "sg:address":"2135 Coral Gate Dr",
    "sg:city":"Miami",
    "sg:classifiers":[
        {
            "category":"Food & Beverages",
            "subcategory":"Groceries & Convenience Stores",
            "type":"Retail Goods"
        }
    ],
    "sg:phone":"+1 305 444 5357",
    "sg:postcode":"33145",
    "sg:province":"FL",
    "wof:name":"Farm Stores",
    "wof:placetype":"venue"
},
  "geometry": {"coordinates":[-80.25201199999999,25.750491],"type":"Point"}
}