{
  "type": "Feature",
  "properties": {
    "addr:full":"9230 Crabtree Ln Port Richey FL 34668",
    "addr:housenumber":"9230",
    "addr:postcode":"34668",
    "addr:street":"Crabtree Ln",
    "iso:country":"US",
    "sg:address":"9230 Crabtree Ln",
    "sg:city":"Port Richey",
    "sg:classifiers":[
        {
            "category":"Wholesale",
            "subcategory":"Toys & Hobbies",
            "type":"Manufacturing & Wholesale Goods"
        }
    ],
    "sg:phone":"+1 727 808 1293",
    "sg:postcode":"34668",
    "sg:province":"FL",
    "sg:tags":[
        "wholesaler"
    ],
    "wof:name":"Bill Grey's Enterprises",
    "wof:placetype":"venue"
},
  "geometry": {"coordinates":[-82.702687,28.293401],"type":"Point"}
}