{
  "type": "Feature",
  "properties": {
    "iso:country":"US",
    "sg:address":"760 Bayside Ln",
    "sg:city":"Weston",
    "sg:classifiers":[
        {
            "category":"Shopping",
            "subcategory":"Gifts & Souvenirs",
            "type":"Retail Goods"
        }
    ],
    "sg:phone":"+1 954 384 9323",
    "sg:postcode":"33326",
    "sg:province":"FL",
    "sg:tags":[
        "shop"
    ],
    "wof:name":"Designs From Heart",
    "wof:placetype":"venue"
},
  "geometry": {"coordinates":[-80.39846799999999,26.108962],"type":"Point"}
}