{
  "type": "Feature",
  "properties": {
    "iso:country":"US",
    "sg:address":"1665 San Marco Blvd",
    "sg:city":"Jacksonville",
    "sg:classifiers":[
        {
            "category":"Insurance",
            "subcategory":"Insurance Agent",
            "type":"Services"
        }
    ],
    "sg:phone":"+1 904 396 2041",
    "sg:postcode":"32207",
    "sg:province":"FL",
    "sg:tags":[
        "agency"
    ],
    "wof:name":"James F Tullis & Associates",
    "wof:placetype":"venue"
},
  "geometry": {"coordinates":[-81.66045800000001,30.308275],"type":"Point"}
}