{
  "type": "Feature",
  "properties": {
    "iso:country":"US",
    "sg:address":"120 Pinellas Bayway S",
    "sg:city":"Saint Petersburg",
    "sg:classifiers":[
        {
            "category":"Restaurant",
            "type":"Food & Drink"
        }
    ],
    "sg:phone":"+1 727 864 9709",
    "sg:postcode":"33715",
    "sg:province":"FL",
    "sg:tags":[
        "eating"
    ],
    "wof:name":"Subway",
    "wof:placetype":"venue"
},
  "geometry": {"coordinates":[-82.720422,27.689746],"type":"Point"}
}