{
  "type": "Feature",
  "properties": {
    "iso:country":"US",
    "sg:address":"1466 NW 13th Ter",
    "sg:city":"Miami",
    "sg:classifiers":[
        {
            "category":"Professional",
            "subcategory":"Lawyer & Legal Services",
            "type":"Services"
        }
    ],
    "sg:phone":"+1 305 545 8866",
    "sg:postcode":"33125",
    "sg:province":"FL",
    "sg:tags":[
        "attorney"
    ],
    "wof:name":"Sean Sweeney",
    "wof:placetype":"venue"
},
  "geometry": {"coordinates":[-80.218908,25.787453],"type":"Point"}
}