{
  "type": "Feature",
  "properties": {
    "addr:full":"3308 17th St Sarasota FL 34235",
    "addr:housenumber":"3308",
    "addr:postcode":"34235",
    "addr:street":"17Th St",
    "iso:country":"US",
    "sg:address":"3308 17th St",
    "sg:city":"Sarasota",
    "sg:classifiers":[
        {
            "category":"Organizations",
            "subcategory":"Religious Organization",
            "type":"Services"
        }
    ],
    "sg:phone":"+1 941 955 5531",
    "sg:postcode":"34235",
    "sg:province":"FL",
    "sg:tags":[
        "church"
    ],
    "wof:name":"Cornerstone Baptist Church",
    "wof:placetype":"venue"
},
  "geometry": {"coordinates":[-82.503703,27.352286],"type":"Point"}
}