{
  "type": "Feature",
  "properties": {
    "iso:country":"US",
    "sg:address":"2230 Emerson St",
    "sg:city":"Jacksonville",
    "sg:classifiers":[
        {
            "category":"Personal",
            "subcategory":"Barber",
            "type":"Services"
        }
    ],
    "sg:phone":"+1 904 399 0446",
    "sg:postcode":"32207",
    "sg:province":"FL",
    "sg:tags":[
        "shop"
    ],
    "wof:name":"Goodfellas Barber Shop",
    "wof:placetype":"venue"
},
  "geometry": {"coordinates":[-81.635831,30.286422],"type":"Point"}
}