{
  "type": "Feature",
  "properties": {
    "iso:country":"US",
    "sg:address":"12440 Old Cutler Rd",
    "sg:city":"Miami",
    "sg:classifiers":[
        {
            "category":"Professional",
            "subcategory":"Business Services",
            "type":"Services"
        }
    ],
    "sg:phone":"+1 305 665 9718",
    "sg:postcode":"33156",
    "sg:province":"FL",
    "sg:tags":[
        "consultant",
        "coach"
    ],
    "wof:name":"Jasonfernandez Consulting",
    "wof:placetype":"venue"
},
  "geometry": {"coordinates":[-80.28421299999999,25.654838],"type":"Point"}
}