{
  "type": "Feature",
  "properties": {
    "addr:full":"10492 Boyette St Englewood FL 34224",
    "addr:housenumber":"10492",
    "addr:postcode":"34224",
    "addr:street":"Boyette St",
    "iso:country":"US",
    "sg:address":"10492 Boyette St",
    "sg:city":"Englewood",
    "sg:classifiers":[
        {
            "category":"Real Estate",
            "subcategory":"Real Estate Services",
            "type":"Services"
        },
        {
            "category":"Real Estate",
            "subcategory":"Real Estate Agent",
            "type":"Services"
        }
    ],
    "sg:phone":"+1 941 697 3401",
    "sg:postcode":"34224",
    "sg:province":"FL",
    "sg:tags":[
        "buyer",
        "broker"
    ],
    "wof:name":"Ambur Realty Of Venice",
    "wof:placetype":"venue"
},
  "geometry": {"coordinates":[-82.314108,26.877102],"type":"Point"}
}