{
  "type": "Feature",
  "properties": {
    "iso:country":"US",
    "sg:address":"3493 NW 167th St",
    "sg:city":"Opa Locka",
    "sg:classifiers":[
        {
            "category":"Real Estate",
            "subcategory":"Developer",
            "type":"Services"
        }
    ],
    "sg:phone":"+1 305 624 2999",
    "sg:postcode":"33056",
    "sg:province":"FL",
    "wof:name":"Palmetto Palms Business Park",
    "wof:placetype":"venue"
},
  "geometry": {"coordinates":[-80.256891,25.92623],"type":"Point"}
}