{
  "type": "Feature",
  "properties": {
    "addr:full":"9505 W Atlantic Blvd Pompano Beach FL 33071",
    "addr:housenumber":"9505",
    "addr:postcode":"33071",
    "addr:street":"W Atlantic Blvd",
    "iso:country":"US",
    "sg:address":"9505 W Atlantic Blvd",
    "sg:city":"Pompano Beach",
    "sg:classifiers":[
        {
            "category":"Shopping",
            "subcategory":"Clothing, Apparel, & Fashions",
            "type":"Retail Goods"
        }
    ],
    "sg:phone":"+1 954 753 9755",
    "sg:postcode":"33071",
    "sg:province":"FL",
    "wof:name":"Limited The",
    "wof:placetype":"venue"
},
  "geometry": {"coordinates":[-80.254324,26.240392],"type":"Point"}
}