{
  "type": "Feature",
  "properties": {
    "addr:full":"4695 28th Ct Vero Beach FL 32967",
    "addr:housenumber":"4695",
    "addr:postcode":"32967",
    "addr:street":"28Th Ct",
    "iso:country":"US",
    "sg:address":"4695 28th Ct",
    "sg:city":"Vero Beach",
    "sg:classifiers":[
        {
            "category":"Government",
            "subcategory":"Office",
            "type":"Public Place"
        }
    ],
    "sg:phone":"+1 772 770 5151",
    "sg:postcode":"32967",
    "sg:province":"FL",
    "sg:tags":[
        "state",
        "program",
        "health"
    ],
    "wof:name":"Gifford Health Ctr",
    "wof:placetype":"venue"
},
  "geometry": {"coordinates":[-80.414569,27.678908],"type":"Point"}
}