{
  "type": "Feature",
  "properties": {
    "addr:full":"6215 Balboa St Cocoa FL 32927",
    "addr:housenumber":"6215",
    "addr:postcode":"32927",
    "addr:street":"Balboa St",
    "iso:country":"US",
    "sg:address":"6215 Balboa St",
    "sg:city":"Cocoa",
    "sg:classifiers":[
        {
            "category":"Manufacturing",
            "subcategory":"Tools & Machinery",
            "type":"Manufacturing & Wholesale Goods"
        }
    ],
    "sg:phone":"+1 321 636 2842",
    "sg:postcode":"32927",
    "sg:province":"FL",
    "sg:tags":[
        "terminal",
        "computer",
        "mfg"
    ],
    "wof:name":"Edwin and Carolyn Ward",
    "wof:placetype":"venue"
},
  "geometry": {"coordinates":[-80.827072,28.459975],"type":"Point"}
}