{
  "type": "Feature",
  "properties": {
    "addr:full":"14505 Commerce Way Hialeah FL 33016",
    "addr:housenumber":"14505",
    "addr:postcode":"33016",
    "addr:street":"Commerce Way",
    "iso:country":"US",
    "sg:address":"14505 Commerce Way",
    "sg:city":"Hialeah",
    "sg:classifiers":[
        {
            "category":"Wholesale",
            "subcategory":"Books, Periodicals, & Newspapers",
            "type":"Manufacturing & Wholesale Goods"
        }
    ],
    "sg:phone":"+1 305 231 6322",
    "sg:postcode":"33016",
    "sg:province":"FL",
    "wof:name":"K-Link Trading & Services",
    "wof:placetype":"venue"
},
  "geometry": {"coordinates":[-80.330169,25.903269],"type":"Point"}
}