{
  "type": "Feature",
  "properties": {
    "addr:full":"618 Louis Ave Lehigh Acres FL 33972",
    "addr:housenumber":"618",
    "addr:postcode":"33972",
    "addr:street":"Louis Ave",
    "iso:country":"US",
    "sg:address":"618 Louis Ave",
    "sg:city":"Lehigh Acres",
    "sg:classifiers":[
        {
            "category":"Building & Trades",
            "subcategory":"Landscaping Services",
            "type":"Services"
        }
    ],
    "sg:phone":"+1 239 369 9808",
    "sg:postcode":"33972",
    "sg:province":"FL",
    "sg:tags":[
        "lawn",
        "maintenance",
        "grounds"
    ],
    "wof:name":"Dj's Superior Lawn Svc",
    "wof:placetype":"venue"
},
  "geometry": {"coordinates":[-81.57293,26.624684],"type":"Point"}
}