{
  "type": "Feature",
  "properties": {
    "iso:country":"US",
    "sg:address":"904 E Canal St",
    "sg:city":"Mulberry",
    "sg:classifiers":[
        {
            "category":"Banks & Credit Unions",
            "subcategory":"Bank",
            "type":"Services"
        }
    ],
    "sg:phone":"+1 813 871 2690",
    "sg:postcode":"33860",
    "sg:province":"FL",
    "wof:name":"GTE Federal Credit Union",
    "wof:placetype":"venue"
},
  "geometry": {"coordinates":[-81.964411,27.894996],"type":"Point"}
}