{
  "type": "Feature",
  "properties": {
    "addr:full":"1450 SE 14th Dr Deerfield Beach FL 33441",
    "addr:housenumber":"1450",
    "addr:postcode":"33441",
    "addr:street":"Se 14Th Dr",
    "iso:country":"US",
    "sg:address":"1450 SE 14th Dr",
    "sg:city":"Deerfield Beach",
    "sg:classifiers":[
        {
            "category":"Manufacturing",
            "subcategory":"Tools & Machinery",
            "type":"Manufacturing & Wholesale Goods"
        }
    ],
    "sg:phone":"+1 954 427 2239",
    "sg:postcode":"33441",
    "sg:province":"FL",
    "sg:tags":[
        "mfg",
        "printing",
        "trade"
    ],
    "wof:name":"Minet Press",
    "wof:placetype":"venue"
},
  "geometry": {"coordinates":[-80.081649,26.299395],"type":"Point"}
}