{
  "type": "Feature",
  "properties": {
    "addr:full":"17 W Granada Blvd Ormond Beach FL 32174",
    "addr:housenumber":"17",
    "addr:postcode":"32174",
    "addr:street":"W Granada Blvd",
    "iso:country":"US",
    "sg:address":"17 W Granada Blvd",
    "sg:city":"Ormond Beach",
    "sg:classifiers":[
        {
            "category":"Wholesale",
            "subcategory":"Stationery",
            "type":"Manufacturing & Wholesale Goods"
        }
    ],
    "sg:phone":"+1 386 677 0450",
    "sg:postcode":"32174",
    "sg:province":"FL",
    "sg:tags":[
        "map"
    ],
    "sg:website":"www.maps911.com",
    "wof:name":"A Map Solution Inc",
    "wof:placetype":"venue"
},
  "geometry": {"coordinates":[-81.057095,29.28522],"type":"Point"}
}