{
  "type": "Feature",
  "properties": {
    "iso:country":"US",
    "sg:address":"2660 14th Ave SE",
    "sg:city":"Naples",
    "sg:classifiers":[
        {
            "category":"Banks & Credit Unions",
            "subcategory":"Bank",
            "type":"Services"
        }
    ],
    "sg:phone":"+1 239 992 9311",
    "sg:postcode":"34117",
    "sg:province":"FL",
    "sg:tags":[
        "loan",
        "real estate"
    ],
    "wof:name":"All In One Inc",
    "wof:placetype":"venue"
},
  "geometry": {"coordinates":[-81.54720500000001,26.204962],"type":"Point"}
}