{
  "type": "Feature",
  "properties": {
    "addr:full":"2269 Indian Rd West Palm Beach FL 33409",
    "addr:housenumber":"2269",
    "addr:postcode":"33409",
    "addr:street":"Indian Rd",
    "iso:country":"US",
    "sg:address":"2269 Indian Rd",
    "sg:city":"West Palm Beach",
    "sg:classifiers":[
        {
            "category":"Building & Trades",
            "subcategory":"Construction",
            "type":"Services"
        }
    ],
    "sg:phone":"+1 561 683 8459",
    "sg:postcode":"33409",
    "sg:province":"FL",
    "sg:tags":[
        "paving",
        "contractor"
    ],
    "sg:website":"www.hubbard.com",
    "wof:name":"East Coast Paving Inc",
    "wof:placetype":"venue"
},
  "geometry": {"coordinates":[-80.104292,26.710795],"type":"Point"}
}