{
  "type": "Feature",
  "properties": {
    "iso:country":"US",
    "sg:address":"6024 Antelope St",
    "sg:city":"Milton",
    "sg:classifiers":[
        {
            "category":"Structure",
            "subcategory":"Factory",
            "type":"Public Place"
        }
    ],
    "sg:phone":"+1 850 626 1698",
    "sg:postcode":"32570",
    "sg:province":"FL",
    "sg:tags":[
        "keys-wholesale",
        "manufacturer"
    ],
    "wof:name":"G & T Appliance & Repair",
    "wof:placetype":"venue"
},
  "geometry": {"coordinates":[-87.097977,30.656549],"type":"Point"}
}