{
  "type": "Feature",
  "properties": {
    "iso:country":"US",
    "sg:address":"17906 Aberdeen Way",
    "sg:city":"Boca Raton",
    "sg:classifiers":[
        {
            "category":"Autos & Motor Vehicles",
            "subcategory":"Auto Supplies",
            "type":"Retail Goods"
        }
    ],
    "sg:phone":"+1 561 477 3213",
    "sg:postcode":"33496",
    "sg:province":"FL",
    "sg:tags":[
        "automobile",
        "parts"
    ],
    "wof:name":"Motorcar Parts Assoc",
    "wof:placetype":"venue"
},
  "geometry": {"coordinates":[-80.15916900000001,26.411129],"type":"Point"}
}