{
  "type": "Feature",
  "properties": {
    "addr:full":"7307 NE Elyse Cir Port Saint Lucie FL 34952",
    "addr:housenumber":"7307",
    "addr:postcode":"34952",
    "addr:street":"Ne Elyse Cir",
    "iso:country":"US",
    "sg:address":"7307 NE Elyse Cir",
    "sg:city":"Port Saint Lucie",
    "sg:classifiers":[
        {
            "category":"Farming",
            "subcategory":"Orchard",
            "type":"Manufacturing & Wholesale Goods"
        }
    ],
    "sg:phone":"+1 772 461 3866",
    "sg:postcode":"34952",
    "sg:province":"FL",
    "sg:tags":[
        "citrus",
        "grove",
        "fruit"
    ],
    "wof:name":"Sabene Groves",
    "wof:placetype":"venue"
},
  "geometry": {"coordinates":[-80.33407800000001,27.338746],"type":"Point"}
}