{
  "type": "Feature",
  "properties": {
    "iso:country":"US",
    "sg:address":"2635 Gulf Breeze Pkwy",
    "sg:city":"Gulf Breeze",
    "sg:classifiers":[
        {
            "category":"Manufacturing",
            "subcategory":"Printing",
            "type":"Manufacturing & Wholesale Goods"
        },
        {
            "category":"Manufacturing",
            "subcategory":"Motor Vehicles & Parts",
            "type":"Manufacturing & Wholesale Goods"
        }
    ],
    "sg:phone":"+1 850 934 4716",
    "sg:postcode":"32563",
    "sg:province":"FL",
    "sg:tags":[
        "screen",
        "mfg",
        "commercial",
        "trimming"
    ],
    "wof:name":"Aloha Screen Printing Inc",
    "wof:placetype":"venue"
},
  "geometry": {"coordinates":[-87.11333,30.378664],"type":"Point"}
}