{
  "type": "Feature",
  "properties": {
    "addr:full":"210 Carswell Ave Daytona Beach FL 32117",
    "addr:housenumber":"210",
    "addr:postcode":"32117",
    "addr:street":"Carswell Ave",
    "iso:country":"US",
    "sg:address":"210 Carswell Ave",
    "sg:city":"Daytona Beach",
    "sg:classifiers":[
        {
            "category":"Home & Garden",
            "subcategory":"Building Materials",
            "type":"Retail Goods"
        }
    ],
    "sg:phone":"+1 386 258 5428",
    "sg:postcode":"32117",
    "sg:province":"FL",
    "sg:tags":[
        "windows"
    ],
    "wof:name":"Allied Window Co",
    "wof:placetype":"venue"
},
  "geometry": {"coordinates":[-81.035493,29.230403],"type":"Point"}
}