{
  "type": "Feature",
  "properties": {
    "iso:country":"US",
    "sg:address":"401 SW 1st Ave #102",
    "sg:city":"Fort Lauderdale",
    "sg:classifiers":[
        {
            "category":"Professional",
            "subcategory":"Computer Services",
            "type":"Services"
        }
    ],
    "sg:phone":"+1 954 763 3971",
    "sg:postcode":"33301",
    "sg:province":"FL",
    "sg:tags":[
        "yachts-for-sale",
        "yachts",
        "boat-brokerage",
        "sailboats",
        "power-boats",
        "trawlers",
        "mega-yachts",
        "catamarans-"
    ],
    "sg:website":"http://www.denisonyachtsales.com/",
    "wof:name":"Denison Yacht Sales",
    "wof:placetype":"venue"
},
  "geometry": {"coordinates":[-80.144407,26.117447],"type":"Point"}
}