{
  "type": "Feature",
  "properties": {
    "iso:country":"US",
    "sg:address":"770 SE Monterey Rd",
    "sg:city":"Stuart",
    "sg:classifiers":[
        {
            "category":"Freight",
            "type":"Transportation"
        }
    ],
    "sg:phone":"+1 772 283 1118",
    "sg:postcode":"34994",
    "sg:province":"FL",
    "sg:tags":[
        "special"
    ],
    "wof:name":"Treasure Coast Self Storage",
    "wof:placetype":"venue"
},
  "geometry": {"coordinates":[-80.24218399999999,27.175593],"type":"Point"}
}