{
  "type": "Feature",
  "properties": {
    "iso:country":"US",
    "sg:address":"1231 SE 14th Dr",
    "sg:city":"Deerfield Beach",
    "sg:classifiers":[
        {
            "category":"Professional",
            "type":"Services"
        }
    ],
    "sg:phone":"+1 954 427 5400",
    "sg:postcode":"33441",
    "sg:province":"FL",
    "wof:name":"Florida Plate Specialists",
    "wof:placetype":"venue"
},
  "geometry": {"coordinates":[-80.085984,26.299386],"type":"Point"}
}