{
  "type": "Feature",
  "properties": {
    "addr:full":"8570 NW 56th St Doral FL 33166",
    "addr:housenumber":"8570",
    "addr:postcode":"33166",
    "addr:street":"Nw 56Th St",
    "iso:country":"US",
    "sg:address":"8570 NW 56th St",
    "sg:city":"Doral",
    "sg:classifiers":[
        {
            "category":"Wholesale",
            "subcategory":"Machinery & Supplies",
            "type":"Manufacturing & Wholesale Goods"
        }
    ],
    "sg:phone":"+1 305 477 9985",
    "sg:postcode":"33166",
    "sg:province":"FL",
    "sg:tags":[
        "equipment",
        "industrial",
        "truck"
    ],
    "wof:name":"Mas Forklift & Parts Inc",
    "wof:placetype":"venue"
},
  "geometry": {"coordinates":[-80.334245,25.824309],"type":"Point"}
}