{
  "type": "Feature",
  "properties": {
    "iso:country":"US",
    "sg:address":"288 Westshore Plz",
    "sg:city":"Tampa",
    "sg:classifiers":[
        {
            "category":"Shopping",
            "subcategory":"Clothing, Apparel, & Fashions",
            "type":"Retail Goods"
        }
    ],
    "sg:phone":"+1 813 286 1440",
    "sg:postcode":"33609",
    "sg:province":"FL",
    "sg:tags":[
        "family"
    ],
    "sg:website":"www.gap.com",
    "wof:name":"Gap",
    "wof:placetype":"venue"
},
  "geometry": {"coordinates":[-82.527399,27.946605],"type":"Point"}
}