{
  "type": "Feature",
  "properties": {
    "iso:country":"US",
    "sg:address":"1001 NW 35th Ave",
    "sg:city":"Cape Coral",
    "sg:classifiers":[
        {
            "category":"Freight",
            "type":"Transportation"
        }
    ],
    "sg:phone":"+1 239 282 6209",
    "sg:postcode":"33993",
    "sg:province":"FL",
    "sg:tags":[
        "mover"
    ],
    "wof:name":"Movers",
    "wof:placetype":"venue"
},
  "geometry": {"coordinates":[-82.04571199999999,26.674432],"type":"Point"}
}