{
  "type": "Feature",
  "properties": {
    "iso:country":"US",
    "sg:address":"71 Torrington St",
    "sg:city":"Port Charlotte",
    "sg:classifiers":[
        {
            "category":"Building & Trades",
            "subcategory":"Landscaping Services",
            "type":"Services"
        }
    ],
    "sg:phone":"+1 941 627 2243",
    "sg:postcode":"33954",
    "sg:province":"FL",
    "wof:name":"Wilkars Lawn & Maintenance",
    "wof:placetype":"venue"
},
  "geometry": {"coordinates":[-82.068083,27.030159],"type":"Point"}
}