{
  "type": "Feature",
  "properties": {
    "iso:country":"US",
    "sg:address":"9250 E Fowler Ave",
    "sg:city":"Thonotosassa",
    "sg:classifiers":[
        {
            "category":"Shopping",
            "subcategory":"Clothing, Apparel, & Fashions",
            "type":"Retail Goods"
        }
    ],
    "sg:phone":"+1 813 982 2187",
    "sg:postcode":"33592",
    "sg:province":"FL",
    "sg:tags":[
        "item",
        "boutique"
    ],
    "wof:name":"Bonita Fashions",
    "wof:placetype":"venue"
},
  "geometry": {"coordinates":[-82.344182,28.054299],"type":"Point"}
}