{
  "type": "Feature",
  "properties": {
    "iso:country":"US",
    "sg:address":"134 Lake Sears Dr",
    "sg:city":"Winter Haven",
    "sg:classifiers":[
        {
            "category":"Shopping",
            "subcategory":"Jewelry",
            "type":"Retail Goods"
        }
    ],
    "sg:phone":"+1 863 291 4140",
    "sg:postcode":"33880",
    "sg:province":"FL",
    "wof:name":"David Hammack Jeweler",
    "wof:placetype":"venue"
},
  "geometry": {"coordinates":[-81.77541100000001,28.010577],"type":"Point"}
}