{
  "type": "Feature",
  "properties": {
    "iso:country":"US",
    "sg:address":"2055 Wood St",
    "sg:city":"Sarasota",
    "sg:classifiers":[
        {
            "category":"Health Services",
            "subcategory":"Doctor",
            "type":"Services"
        }
    ],
    "sg:phone":"+1 941 366 6611",
    "sg:postcode":"34237",
    "sg:province":"FL",
    "sg:tags":[
        "physician",
        "surgeon"
    ],
    "wof:name":"Gulf Coast Health Svc Inc",
    "wof:placetype":"venue"
},
  "geometry": {"coordinates":[-82.529357,27.328487],"type":"Point"}
}