{
  "type": "Feature",
  "properties": {
    "addr:full":"905 Alaska Ave Lehigh Acres FL 33971",
    "addr:housenumber":"905",
    "addr:postcode":"33971",
    "addr:street":"Alaska Ave",
    "iso:country":"US",
    "sg:address":"905 Alaska Ave",
    "sg:city":"Lehigh Acres",
    "sg:classifiers":[
        {
            "category":"Professional",
            "subcategory":"Management & Consulting",
            "type":"Services"
        }
    ],
    "sg:phone":"+1 239 332 7008",
    "sg:postcode":"33971",
    "sg:province":"FL",
    "sg:tags":[
        "retail",
        "direct",
        "sales"
    ],
    "wof:name":"Loren Trenhaile",
    "wof:placetype":"venue"
},
  "geometry": {"coordinates":[-81.745467,26.626129],"type":"Point"}
}