{
  "type": "Feature",
  "properties": {
    "iso:country":"US",
    "sg:address":"250 Catalonia Ave Ste 403",
    "sg:city":"Coral Gables",
    "sg:classifiers":[
        {
            "category":"Real Estate",
            "subcategory":"Architect",
            "type":"Services"
        }
    ],
    "sg:phone":"+1 305 567 1977",
    "sg:postcode":"33134",
    "sg:province":"FL",
    "wof:name":"Bravo Llc",
    "wof:placetype":"venue"
},
  "geometry": {"coordinates":[-80.259584,25.744605],"type":"Point"}
}