{
  "type": "Feature",
  "properties": {
    "iso:country":"US",
    "sg:address":"12001 Avalon Lake Dr",
    "sg:city":"Orlando",
    "sg:classifiers":[
        {
            "category":"Restaurant",
            "type":"Food & Drink"
        }
    ],
    "sg:phone":"+1 407 273 6538",
    "sg:postcode":"32828",
    "sg:province":"FL",
    "sg:tags":[
        "bar",
        "sushi",
        "asian",
        "thai",
        "pan"
    ],
    "wof:name":"Daruma Sushi & Thai",
    "wof:placetype":"venue"
},
  "geometry": {"coordinates":[-81.156319,28.510269],"type":"Point"}
}