{
  "type": "Feature",
  "properties": {
    "iso:country":"US",
    "sg:address":"1185 W 68th St",
    "sg:city":"Hialeah",
    "sg:classifiers":[
        {
            "category":"Building & Trades",
            "subcategory":"Locksmith",
            "type":"Services"
        }
    ],
    "sg:phone":"+1 305 357 2569",
    "sg:postcode":"33014",
    "sg:province":"FL",
    "sg:tags":[
        "key"
    ],
    "wof:name":"7 Day Always Emergency Locksmith",
    "wof:placetype":"venue"
},
  "geometry": {"coordinates":[-80.30724600000001,25.884656],"type":"Point"}
}