{
  "type": "Feature",
  "properties": {
    "addr:full":"1802 Janice Ave Orlando FL 32803",
    "addr:housenumber":"1802",
    "addr:postcode":"32803",
    "addr:street":"Janice Ave",
    "iso:country":"US",
    "sg:address":"1802 Janice Ave",
    "sg:city":"Orlando",
    "sg:classifiers":[
        {
            "category":"Wholesale",
            "subcategory":"Office Equipment",
            "type":"Manufacturing & Wholesale Goods"
        },
        {
            "category":"Professional",
            "subcategory":"Accounting & Tax Preparation",
            "type":"Services"
        }
    ],
    "sg:phone":"+1 407 896 1553",
    "sg:postcode":"32803",
    "sg:province":"FL",
    "sg:tags":[
        "machine",
        "bookkeeping",
        "return",
        "preparation-business",
        "supply"
    ],
    "sg:website":"http://www.atipro.com",
    "wof:name":"A T I Professional Services",
    "wof:placetype":"venue"
},
  "geometry": {"coordinates":[-81.34765299999999,28.56801],"type":"Point"}
}