{
  "type": "Feature",
  "properties": {
    "iso:country":"US",
    "sg:address":"1763 Geraldine Dr",
    "sg:city":"Jacksonville",
    "sg:classifiers":[
        {
            "category":"Shopping",
            "subcategory":"Clothing, Apparel, & Fashions",
            "type":"Retail Goods"
        }
    ],
    "sg:phone":"+1 904 388 6056",
    "sg:postcode":"32205",
    "sg:province":"FL",
    "wof:name":"Boudinot",
    "wof:placetype":"venue"
},
  "geometry": {"coordinates":[-81.71483000000001,30.291161],"type":"Point"}
}