{
  "type": "Feature",
  "properties": {
    "iso:country":"US",
    "sg:address":"8379 SW Co Rd 313",
    "sg:city":"Trenton",
    "sg:classifiers":[
        {
            "category":"Wholesale",
            "subcategory":"Motor Vehicles",
            "type":"Manufacturing & Wholesale Goods"
        }
    ],
    "sg:phone":"+1 352 463 1940",
    "sg:postcode":"32693",
    "sg:province":"FL",
    "sg:tags":[
        "trailer"
    ],
    "wof:name":"DMB Trailers",
    "wof:placetype":"venue"
},
  "geometry": {"coordinates":[-82.881809,29.613325],"type":"Point"}
}