{
  "type": "Feature",
  "properties": {
    "addr:full":"19210 W Dixie Hwy Miami FL 33180",
    "addr:housenumber":"19210",
    "addr:postcode":"33180",
    "addr:street":"W Dixie Hwy",
    "iso:country":"US",
    "sg:address":"19210 W Dixie Hwy",
    "sg:city":"Miami",
    "sg:classifiers":[
        {
            "category":"Real Estate",
            "subcategory":"Real Estate Agent",
            "type":"Services"
        }
    ],
    "sg:phone":"+1 305 936 1466",
    "sg:postcode":"33180",
    "sg:province":"FL",
    "sg:website":"www.aventuraprime.com",
    "wof:name":"Aventura Prime Properties Inc",
    "wof:placetype":"venue"
},
  "geometry": {"coordinates":[-80.149119,25.953808],"type":"Point"}
}