{
  "type": "Feature",
  "properties": {
    "iso:country":"US",
    "sg:address":"1838 59th St W",
    "sg:city":"Bradenton",
    "sg:classifiers":[
        {
            "category":"Shopping",
            "type":"Retail Goods"
        }
    ],
    "sg:phone":"+1 941 755 1983",
    "sg:postcode":"34209",
    "sg:province":"FL",
    "sg:tags":[
        "merchandise"
    ],
    "wof:name":"Post Mastectomy Boutique",
    "wof:placetype":"venue"
},
  "geometry": {"coordinates":[-82.620574,27.484396],"type":"Point"}
}