{
  "type": "Feature",
  "properties": {
    "addr:full":"9761 NW 49th Ter Doral FL 33178",
    "addr:housenumber":"9761",
    "addr:postcode":"33178",
    "addr:street":"Nw 49Th Ter",
    "iso:country":"US",
    "sg:address":"9761 NW 49th Ter",
    "sg:city":"Doral",
    "sg:classifiers":[
        {
            "category":"Wholesale",
            "subcategory":"Durable Goods & Equipment",
            "type":"Manufacturing & Wholesale Goods"
        }
    ],
    "sg:phone":"+1 305 436 8755",
    "sg:postcode":"33178",
    "sg:province":"FL",
    "sg:tags":[
        "importer"
    ],
    "wof:name":"C & M World Enterprises Corp",
    "wof:placetype":"venue"
},
  "geometry": {"coordinates":[-80.35468299999999,25.818573],"type":"Point"}
}