{
  "type": "Feature",
  "properties": {
    "iso:country":"US",
    "sg:address":"473 Rio Vista Ct",
    "sg:city":"Spring Hill",
    "sg:classifiers":[
        {
            "category":"Building & Trades",
            "subcategory":"Construction",
            "type":"Services"
        }
    ],
    "sg:phone":"+1 352 666 1865",
    "sg:postcode":"34608",
    "sg:province":"FL",
    "sg:tags":[
        "house"
    ],
    "wof:name":"Artistic Homes",
    "wof:placetype":"venue"
},
  "geometry": {"coordinates":[-82.542738,28.444999],"type":"Point"}
}