{
  "type": "Feature",
  "properties": {
    "iso:country":"US",
    "sg:address":"1177 Enterprise Dr",
    "sg:city":"Port Charlotte",
    "sg:classifiers":[
        {
            "category":"Home & Garden",
            "subcategory":"Garden Supply",
            "type":"Retail Goods"
        }
    ],
    "sg:phone":"+1 941 255 1618",
    "sg:postcode":"33953",
    "sg:province":"FL",
    "wof:name":"Lesco Service Center 445",
    "wof:placetype":"venue"
},
  "geometry": {"coordinates":[-82.15330899999999,27.013108],"type":"Point"}
}