{
  "type": "Feature",
  "properties": {
    "addr:full":"410 Palm Beach Trace Dr West Palm Beach FL 33411",
    "addr:housenumber":"410",
    "addr:postcode":"33411",
    "addr:street":"Palm Beach Trace Dr",
    "iso:country":"US",
    "sg:address":"410 Palm Beach Trace Dr",
    "sg:city":"West Palm Beach",
    "sg:classifiers":[
        {
            "category":"Local Transit",
            "type":"Transportation"
        }
    ],
    "sg:phone":"+1 561 792 5959",
    "sg:postcode":"33411",
    "sg:province":"FL",
    "sg:tags":[
        "limousine"
    ],
    "wof:name":"Southampton Limousine Services",
    "wof:placetype":"venue"
},
  "geometry": {"coordinates":[-80.22713899999999,26.712832],"type":"Point"}
}