{
  "type": "Feature",
  "properties": {
    "iso:country":"US",
    "sg:address":"642 Belvedere Rd",
    "sg:city":"West Palm Beach",
    "sg:classifiers":[
        {
            "category":"Food & Beverages",
            "subcategory":"Bakery",
            "type":"Retail Goods"
        }
    ],
    "sg:phone":"+1 561 833 0898",
    "sg:postcode":"33405",
    "sg:province":"FL",
    "sg:tags":[
        "baker"
    ],
    "wof:name":"El Palacio",
    "wof:placetype":"venue"
},
  "geometry": {"coordinates":[-80.05771,26.690328],"type":"Point"}
}