{
  "type": "Feature",
  "properties": {
    "iso:country":"US",
    "sg:address":"3296 Pippin Ln",
    "sg:city":"Cottondale",
    "sg:classifiers":[
        {
            "category":"Building & Trades",
            "subcategory":"Electrical",
            "type":"Services"
        }
    ],
    "sg:phone":"+1 850 352 4940",
    "sg:postcode":"32431",
    "sg:province":"FL",
    "sg:tags":[
        "electrical",
        "contractor"
    ],
    "wof:name":"J&B Air Electric",
    "wof:placetype":"venue"
},
  "geometry": {"coordinates":[-85.37177800000001,30.801495],"type":"Point"}
}