{
  "type": "Feature",
  "properties": {
    "iso:country":"US",
    "sg:address":"6391 W Newberry Rd",
    "sg:city":"Gainesville",
    "sg:classifiers":[
        {
            "category":"Shopping",
            "type":"Retail Goods"
        }
    ],
    "sg:phone":"+1 352 332 5257",
    "sg:postcode":"32605",
    "sg:province":"FL",
    "sg:tags":[
        "item",
        "boutique"
    ],
    "wof:name":"Francesca's Collections",
    "wof:placetype":"venue"
},
  "geometry": {"coordinates":[-82.421425,29.65961],"type":"Point"}
}