{
  "type": "Feature",
  "properties": {
    "iso:country":"US",
    "sg:address":"285 SW 138th Ter",
    "sg:city":"Newberry",
    "sg:classifiers":[
        {
            "category":"Building & Trades",
            "subcategory":"Construction",
            "type":"Services"
        }
    ],
    "sg:phone":"+1 352 333 7207",
    "sg:postcode":"32669",
    "sg:province":"FL",
    "sg:tags":[
        "nonresidential"
    ],
    "wof:name":"Curtis Comericial & Indus Dev",
    "wof:placetype":"venue"
},
  "geometry": {"coordinates":[-82.490171,29.653545],"type":"Point"}
}