{
  "type": "Feature",
  "properties": {
    "iso:country":"US",
    "sg:address":"321 Imperial Blvd",
    "sg:city":"Lakeland",
    "sg:classifiers":[
        {
            "category":"Professional",
            "subcategory":"Engineering",
            "type":"Services"
        }
    ],
    "sg:phone":"+1 863 644 2077",
    "sg:postcode":"33803",
    "sg:province":"FL",
    "sg:tags":[
        "engineer"
    ],
    "wof:name":"Leyshon Consulting Inc",
    "wof:placetype":"venue"
},
  "geometry": {"coordinates":[-81.958135,28.00189],"type":"Point"}
}