{
  "type": "Feature",
  "properties": {
    "addr:full":"3302 W Cypress St Tampa FL 33607",
    "addr:housenumber":"3302",
    "addr:postcode":"33607",
    "addr:street":"W Cypress St",
    "iso:country":"US",
    "sg:address":"3302 W Cypress St",
    "sg:city":"Tampa",
    "sg:classifiers":[
        {
            "category":"Personal",
            "subcategory":"Beauty Salon",
            "type":"Services"
        }
    ],
    "sg:phone":"+1 813 874 8404",
    "sg:postcode":"33607",
    "sg:province":"FL",
    "sg:tags":[
        "shop"
    ],
    "wof:name":"Styles & Company",
    "wof:placetype":"venue"
},
  "geometry": {"coordinates":[-82.499419,27.95204],"type":"Point"}
}