{
  "type": "Feature",
  "properties": {
    "iso:country":"US",
    "sg:address":"6 E Bay St",
    "sg:city":"Jacksonville",
    "sg:classifiers":[
        {
            "category":"Professional",
            "subcategory":"Printing & Photocopies",
            "type":"Services"
        }
    ],
    "sg:phone":"+1 904 358 0222",
    "sg:postcode":"32202",
    "sg:province":"FL",
    "sg:tags":[
        "scanning",
        "duplicating",
        "imaging",
        "copying",
        "document",
        "or"
    ],
    "wof:name":"Southeast Legal Copy Ltd",
    "wof:placetype":"venue"
},
  "geometry": {"coordinates":[-81.63158300000001,30.31887],"type":"Point"}
}