{
  "type": "Feature",
  "properties": {
    "addr:full":"1007 Atlantic Blvd Atlantic Beach FL 32233",
    "addr:housenumber":"1007",
    "addr:postcode":"32233",
    "addr:street":"Atlantic Blvd",
    "iso:country":"US",
    "sg:address":"1007 Atlantic Blvd",
    "sg:city":"Atlantic Beach",
    "sg:classifiers":[
        {
            "category":"Professional",
            "subcategory":"Accounting & Tax Preparation",
            "type":"Services"
        }
    ],
    "sg:phone":"+1 904 241 7999",
    "sg:postcode":"32233",
    "sg:province":"FL",
    "sg:tags":[
        "return",
        "filing"
    ],
    "wof:name":"H & R Block Tax Svc",
    "wof:placetype":"venue"
},
  "geometry": {"coordinates":[-81.412509,30.324448],"type":"Point"}
}