{
  "type": "Feature",
  "properties": {
    "iso:country":"US",
    "sg:address":"8040 NW 67th St",
    "sg:city":"Miami",
    "sg:classifiers":[
        {
            "category":"Retail",
            "subcategory":"Auto Repair",
            "type":"Services"
        }
    ],
    "sg:phone":"+1 786 331 7475",
    "sg:postcode":"33166",
    "sg:province":"FL",
    "sg:tags":[
        "body"
    ],
    "wof:name":"Miami Custom Body Shop Inc",
    "wof:placetype":"venue"
},
  "geometry": {"coordinates":[-80.32776,25.834293],"type":"Point"}
}