{
  "type": "Feature",
  "properties": {
    "iso:country":"US",
    "sg:address":"7608 Currency Dr",
    "sg:city":"Orlando",
    "sg:classifiers":[
        {
            "category":"Manufacturing",
            "subcategory":"Metals",
            "type":"Manufacturing & Wholesale Goods"
        }
    ],
    "sg:phone":"+1 407 856 0660",
    "sg:postcode":"32809",
    "sg:province":"FL",
    "sg:tags":[
        "product",
        "aluminum",
        "mfg"
    ],
    "wof:name":"YKK AP America Inc",
    "wof:placetype":"venue"
},
  "geometry": {"coordinates":[-81.40977599999999,28.45069],"type":"Point"}
}