{
  "type": "Feature",
  "properties": {
    "iso:country":"US",
    "sg:address":"164 SE 3rd Ter",
    "sg:city":"Cape Coral",
    "sg:classifiers":[
        {
            "category":"Building & Trades",
            "subcategory":"Construction",
            "type":"Services"
        }
    ],
    "sg:phone":"+1 239 574 7339",
    "sg:postcode":"33990",
    "sg:province":"FL",
    "sg:tags":[
        "house"
    ],
    "wof:name":"Spicuzza & Sons Remodel",
    "wof:placetype":"venue"
},
  "geometry": {"coordinates":[-81.970848,26.645195],"type":"Point"}
}