{
  "type": "Feature",
  "properties": {
    "iso:country":"US",
    "sg:address":"4304 London Town Rd",
    "sg:city":"Titusville",
    "sg:classifiers":[
        {
            "category":"Building & Trades",
            "subcategory":"Landscaping Services",
            "type":"Services"
        }
    ],
    "sg:phone":"+1 321 264 8950",
    "sg:postcode":"32796",
    "sg:province":"FL",
    "sg:tags":[
        "lawn",
        "maintenance",
        "grounds"
    ],
    "wof:name":"Margo K Bowman Lawn Svc",
    "wof:placetype":"venue"
},
  "geometry": {"coordinates":[-80.865981,28.655037],"type":"Point"}
}