{
  "type": "Feature",
  "properties": {
    "iso:country":"US",
    "sg:address":"1845 University Blvd N",
    "sg:city":"Jacksonville",
    "sg:classifiers":[
        {
            "category":"Professional",
            "subcategory":"Lawyer & Legal Services",
            "type":"Services"
        }
    ],
    "sg:phone":"+1 904 744 5100",
    "sg:postcode":"32211",
    "sg:province":"FL",
    "sg:tags":[
        "attorney"
    ],
    "wof:name":"Eddie Farah Law Offices",
    "wof:placetype":"venue"
},
  "geometry": {"coordinates":[-81.60247699999999,30.33869],"type":"Point"}
}