{
  "type": "Feature",
  "properties": {
    "iso:country":"US",
    "sg:address":"4336 Maygog Rd",
    "sg:city":"Sarasota",
    "sg:classifiers":[
        {
            "category":"Professional",
            "type":"Services"
        }
    ],
    "sg:phone":"+1 941 923 9956",
    "sg:postcode":"34233",
    "sg:province":"FL",
    "sg:tags":[
        "gallery"
    ],
    "wof:name":"Dinwoodie Metal Sculptors",
    "wof:placetype":"venue"
},
  "geometry": {"coordinates":[-82.481641,27.289994],"type":"Point"}
}