{
  "type": "Feature",
  "properties": {
    "addr:full":"2807 W Busch Blvd Tampa FL 33618",
    "addr:housenumber":"2807",
    "addr:postcode":"33618",
    "addr:street":"W Busch Blvd",
    "iso:country":"US",
    "sg:address":"2807 W Busch Blvd",
    "sg:city":"Tampa",
    "sg:classifiers":[
        {
            "category":"Professional",
            "subcategory":"Research",
            "type":"Services"
        }
    ],
    "sg:phone":"+1 813 931 3900",
    "sg:postcode":"33618",
    "sg:province":"FL",
    "sg:tags":[
        "market",
        "analysis"
    ],
    "sg:website":"www.marketdataenterprises.com",
    "wof:name":"Marketdata Enterprises Inc",
    "wof:placetype":"venue"
},
  "geometry": {"coordinates":[-82.489937,28.035797],"type":"Point"}
}