{
  "type": "Feature",
  "properties": {
    "iso:country":"US",
    "sg:address":"7519 Forest City Rd",
    "sg:city":"Orlando",
    "sg:classifiers":[
        {
            "category":"Organizations",
            "subcategory":"Religious Organization",
            "type":"Services"
        }
    ],
    "sg:phone":"+1 407 292 0966",
    "sg:postcode":"32810",
    "sg:province":"FL",
    "wof:name":"Love of Christ Ministries",
    "wof:placetype":"venue"
},
  "geometry": {"coordinates":[-81.41493800000001,28.625552],"type":"Point"}
}