{
  "type": "Feature",
  "properties": {
    "iso:country":"US",
    "sg:address":"1945 NW 168th Ave",
    "sg:city":"Hollywood",
    "sg:classifiers":[
        {
            "category":"Professional",
            "type":"Services"
        }
    ],
    "sg:phone":"+1 954 447 5198",
    "sg:postcode":"33028",
    "sg:province":"FL",
    "wof:name":"Ella Bea LLC",
    "wof:placetype":"venue"
},
  "geometry": {"coordinates":[-80.371402,26.022517],"type":"Point"}
}