{
  "type": "Feature",
  "properties": {
    "iso:country":"US",
    "sg:address":"6058 Waldwick Cir",
    "sg:city":"Delray Beach",
    "sg:classifiers":[
        {
            "category":"Building & Trades",
            "subcategory":"Plumbing",
            "type":"Services"
        }
    ],
    "sg:phone":"+1 561 496 7985",
    "sg:postcode":"33484",
    "sg:province":"FL",
    "sg:tags":[
        "contractor"
    ],
    "wof:name":"Atlantic Cooling Tower",
    "wof:placetype":"venue"
},
  "geometry": {"coordinates":[-80.1407,26.467506],"type":"Point"}
}