{
  "type": "Feature",
  "properties": {
    "iso:country":"US",
    "sg:address":"1785 Ridgewood Ave",
    "sg:city":"Maitland",
    "sg:classifiers":[
        {
            "category":"Building & Trades",
            "subcategory":"Construction",
            "type":"Services"
        }
    ],
    "sg:phone":"+1 407 740 4024",
    "sg:postcode":"32751",
    "sg:province":"FL",
    "sg:tags":[
        "house"
    ],
    "wof:name":"David A Ebert New & Remodel Co",
    "wof:placetype":"venue"
},
  "geometry": {"coordinates":[-81.363376,28.611843],"type":"Point"}
}