{
  "type": "Feature",
  "properties": {
    "iso:country":"US",
    "sg:address":"1701 W Hillsboro Blvd",
    "sg:city":"Deerfield Beach",
    "sg:classifiers":[
        {
            "category":"Professional",
            "subcategory":"Lawyer & Legal Services",
            "type":"Services"
        }
    ],
    "sg:phone":"+1 954 425 0606",
    "sg:postcode":"33442",
    "sg:province":"FL",
    "sg:tags":[
        "attorney"
    ],
    "sg:website":"www.get-nailed.com",
    "wof:name":"Charles L Jaffee Law Offices",
    "wof:placetype":"venue"
},
  "geometry": {"coordinates":[-80.126733,26.318137],"type":"Point"}
}