{
  "type": "Feature",
  "properties": {
    "iso:country":"US",
    "sg:address":"1456 Lee St",
    "sg:city":"Fort Myers",
    "sg:classifiers":[
        {
            "category":"Food & Beverages",
            "subcategory":"Bakery",
            "type":"Retail Goods"
        }
    ],
    "sg:phone":"+1 863 868 7889",
    "sg:postcode":"33901",
    "sg:province":"FL",
    "sg:tags":[
        "baker"
    ],
    "wof:name":"Patties & Pastries Caribbean",
    "wof:placetype":"venue"
},
  "geometry": {"coordinates":[-81.86834,26.645605],"type":"Point"}
}