{
  "type": "Feature",
  "properties": {
    "iso:country":"US",
    "sg:address":"1321 NW 14th St Ste 101",
    "sg:city":"Miami",
    "sg:classifiers":[
        {
            "category":"Health Services",
            "subcategory":"Doctor",
            "type":"Services"
        }
    ],
    "sg:phone":"+1 305 325 4888",
    "sg:postcode":"33125",
    "sg:province":"FL",
    "wof:name":"Philip Grossman, MD",
    "wof:placetype":"venue"
},
  "geometry": {"coordinates":[-80.216973,25.788167],"type":"Point"}
}