{
  "type": "Feature",
  "properties": {
    "iso:country":"US",
    "sg:address":"11571 University Blvd",
    "sg:city":"Orlando",
    "sg:classifiers":[
        {
            "category":"Bakery",
            "type":"Food & Drink"
        }
    ],
    "sg:menulink":"http://www.allmenus.com/fl/union-park/114256-krispy-kreme/menu/",
    "sg:phone":"+1 407 273 5550",
    "sg:postcode":"32817",
    "sg:province":"FL",
    "sg:tags":[
        "american",
        "pastry"
    ],
    "wof:name":"Krispy Kreme",
    "wof:placetype":"venue"
},
  "geometry": {"coordinates":[-81.21911900000001,28.597714],"type":"Point"}
}