{
  "type": "Feature",
  "properties": {
    "addr:full":"7810 Anderson Rd Tampa FL 33634",
    "addr:housenumber":"7810",
    "addr:postcode":"33634",
    "addr:street":"Anderson Rd",
    "iso:country":"US",
    "sg:address":"7810 Anderson Rd",
    "sg:city":"Tampa",
    "sg:classifiers":[
        {
            "category":"Building & Trades",
            "subcategory":"Equipment Rental",
            "type":"Services"
        }
    ],
    "sg:phone":"+1 813 887 4550",
    "sg:postcode":"33634",
    "sg:province":"FL",
    "sg:tags":[
        "supply",
        "contractor"
    ],
    "wof:name":"Renuit",
    "wof:placetype":"venue"
},
  "geometry": {"coordinates":[-82.534083,28.018799],"type":"Point"}
}