{
  "type": "Feature",
  "properties": {
    "addr:full":"933 Cormorant Ct Rockledge FL 32955",
    "addr:housenumber":"933",
    "addr:postcode":"32955",
    "addr:street":"Cormorant Ct",
    "iso:country":"US",
    "sg:address":"933 Cormorant Ct",
    "sg:city":"Rockledge",
    "sg:classifiers":[
        {
            "category":"Personal",
            "subcategory":"Beauty Salon",
            "type":"Services"
        }
    ],
    "sg:phone":"+1 321 633 8358",
    "sg:postcode":"32955",
    "sg:province":"FL",
    "wof:name":"Carol Shear",
    "wof:placetype":"venue"
},
  "geometry": {"coordinates":[-80.709154,28.270255],"type":"Point"}
}