{
  "type": "Feature",
  "properties": {
    "addr:full":"777 Alturas Rd Bartow FL 33830",
    "addr:housenumber":"777",
    "addr:postcode":"33830",
    "addr:street":"Alturas Rd",
    "iso:country":"US",
    "sg:address":"777 Alturas Rd",
    "sg:city":"Bartow",
    "sg:classifiers":[
        {
            "category":"Building & Trades",
            "subcategory":"Construction",
            "type":"Services"
        }
    ],
    "sg:phone":"+1 863 537 3500",
    "sg:postcode":"33830",
    "sg:province":"FL",
    "sg:tags":[
        "development",
        "contractor"
    ],
    "wof:name":"Triad Contracting Inc",
    "wof:placetype":"venue"
},
  "geometry": {"coordinates":[-81.71915199999999,27.90178],"type":"Point"}
}