{
  "type": "Feature",
  "properties": {
    "addr:full":"3500 E Altvater Rd Avon Park FL 33825",
    "addr:housenumber":"3500",
    "addr:postcode":"33825",
    "addr:street":"E Altvater Rd",
    "iso:country":"US",
    "sg:address":"3500 E Altvater Rd",
    "sg:city":"Avon Park",
    "sg:classifiers":[
        {
            "category":"Professional",
            "type":"Services"
        }
    ],
    "sg:phone":"+1 863 452 9711",
    "sg:postcode":"33825",
    "sg:province":"FL",
    "sg:tags":[
        "establishment"
    ],
    "wof:name":"Bonnet Lake Partnership",
    "wof:placetype":"venue"
},
  "geometry": {"coordinates":[-81.43951,27.559263],"type":"Point"}
}