{
  "type": "Feature",
  "properties": {
    "iso:country":"US",
    "sg:address":"1114 Thomasville Rd",
    "sg:city":"Tallahassee",
    "sg:classifiers":[
        {
            "category":"Place Of Worship",
            "type":"Public Place"
        }
    ],
    "sg:phone":"+1 850 270 9686",
    "sg:postcode":"32303",
    "sg:province":"FL",
    "sg:tags":[
        "church"
    ],
    "wof:name":"New Hope Intervention",
    "wof:placetype":"venue"
},
  "geometry": {"coordinates":[-84.278352,30.454235],"type":"Point"}
}