{
  "type": "Feature",
  "properties": {
    "iso:country":"US",
    "sg:address":"385 Alhambra Cir",
    "sg:city":"Coral Gables",
    "sg:classifiers":[
        {
            "category":"Shopping",
            "type":"Retail Goods"
        }
    ],
    "sg:phone":"+1 305 446 0505",
    "sg:postcode":"33134",
    "sg:province":"FL",
    "sg:tags":[
        "cosmetic",
        "perfume"
    ],
    "wof:name":"Donna Bella Cosmetics Group",
    "wof:placetype":"venue"
},
  "geometry": {"coordinates":[-80.261242,25.752031],"type":"Point"}
}