{
  "type": "Feature",
  "properties": {
    "addr:full":"1733 NW 21st Ter Miami FL 33142",
    "addr:housenumber":"1733",
    "addr:postcode":"33142",
    "addr:street":"Nw 21St Ter",
    "iso:country":"US",
    "sg:address":"1733 NW 21st Ter",
    "sg:city":"Miami",
    "sg:classifiers":[
        {
            "category":"Manufacturing",
            "subcategory":"Textiles",
            "type":"Manufacturing & Wholesale Goods"
        }
    ],
    "sg:phone":"+1 305 325 0250",
    "sg:postcode":"33142",
    "sg:province":"FL",
    "sg:tags":[
        "pillows-wholesale",
        "manufacturer"
    ],
    "sg:website":"http://www.tomikoshadegear.com",
    "wof:name":"Hygenator Pillow Service",
    "wof:placetype":"venue"
},
  "geometry": {"coordinates":[-80.224018,25.796563],"type":"Point"}
}