{
  "type": "Feature",
  "properties": {
    "addr:full":"820 Foster Rd Hallandale Beach FL 33009",
    "addr:housenumber":"820",
    "addr:postcode":"33009",
    "addr:street":"Foster Rd",
    "iso:country":"US",
    "sg:address":"820 Foster Rd",
    "sg:city":"Hallandale Beach",
    "sg:classifiers":[
        {
            "category":"Restaurant",
            "type":"Food & Drink"
        }
    ],
    "sg:phone":"+1 954 445 1256",
    "sg:postcode":"33009",
    "sg:province":"FL",
    "sg:tags":[
        "parlor",
        "ice",
        "cream"
    ],
    "wof:name":"Three Sisters Old Fashioned",
    "wof:placetype":"venue"
},
  "geometry": {"coordinates":[-80.160027,25.994073],"type":"Point"}
}