{
  "type": "Feature",
  "properties": {
    "addr:full":"5189 Gulf Breeze Pkwy Gulf Breeze FL 32563",
    "addr:housenumber":"5189",
    "addr:postcode":"32563",
    "addr:street":"Gulf Breeze Pkwy",
    "iso:country":"US",
    "sg:address":"5189 Gulf Breeze Pkwy",
    "sg:city":"Gulf Breeze",
    "sg:classifiers":[
        {
            "category":"Building & Trades",
            "subcategory":"Pest Control",
            "type":"Services"
        }
    ],
    "sg:phone":"+1 850 939 9523",
    "sg:postcode":"32563",
    "sg:province":"FL",
    "wof:name":"Premier Pest Control Svc",
    "wof:placetype":"venue"
},
  "geometry": {"coordinates":[-87.009967,30.398074],"type":"Point"}
}