{
  "type": "Feature",
  "properties": {
    "iso:country":"US",
    "sg:address":"11548 Delmar Ave",
    "sg:city":"Orlando",
    "sg:classifiers":[
        {
            "category":"Professional",
            "subcategory":"Business Services",
            "type":"Services"
        }
    ],
    "sg:phone":"+1 407 909 9165",
    "sg:postcode":"32836",
    "sg:province":"FL",
    "wof:name":"Haughey Seashore Enterprises L",
    "wof:placetype":"venue"
},
  "geometry": {"coordinates":[-81.55006400000001,28.438672],"type":"Point"}
}