{
  "type": "Feature",
  "properties": {
    "addr:full":"937 107th Street Gulf Marathon FL 33050",
    "addr:housenumber":"937",
    "addr:postcode":"33050",
    "addr:street":"107Th Street",
    "iso:country":"US",
    "sg:address":"937 107th Street Gulf",
    "sg:city":"Marathon",
    "sg:classifiers":[
        {
            "category":"Building & Trades",
            "subcategory":"Construction",
            "type":"Services"
        }
    ],
    "sg:phone":"+1 305 743 9644",
    "sg:postcode":"33050",
    "sg:province":"FL",
    "sg:tags":[
        "general",
        "contractor"
    ],
    "wof:name":"Botsford Builders",
    "wof:placetype":"venue"
},
  "geometry": {"coordinates":[-81.03921699999999,24.73108],"type":"Point"}
}