{
  "type": "Feature",
  "properties": {
    "iso:country":"US",
    "sg:address":"4255 NW 107th Ave",
    "sg:city":"Doral",
    "sg:classifiers":[
        {
            "category":"Food & Beverages",
            "subcategory":"Liquor & Beverages",
            "type":"Retail Goods"
        }
    ],
    "sg:phone":"+1 305 592 2784",
    "sg:postcode":"33178",
    "sg:province":"FL",
    "sg:tags":[
        "beer",
        "spirit",
        "wine"
    ],
    "wof:name":"Real Liquor Store",
    "wof:placetype":"venue"
},
  "geometry": {"coordinates":[-80.369598,25.812901],"type":"Point"}
}