{
  "type": "Feature",
  "properties": {
    "addr:full":"8120 Coral Way Miami FL 33155",
    "addr:housenumber":"8120",
    "addr:postcode":"33155",
    "addr:street":"Coral Way",
    "iso:country":"US",
    "sg:address":"8120 Coral Way",
    "sg:city":"Miami",
    "sg:classifiers":[
        {
            "category":"Professional",
            "subcategory":"Accounting & Tax Preparation",
            "type":"Services"
        }
    ],
    "sg:phone":"+1 305 266 1829",
    "sg:postcode":"33155",
    "sg:province":"FL",
    "sg:tags":[
        "accountant"
    ],
    "wof:name":"B PA Accounting Inc",
    "wof:placetype":"venue"
},
  "geometry": {"coordinates":[-80.32710299999999,25.7479],"type":"Point"}
}