{
  "type": "Feature",
  "properties": {
    "iso:country":"US",
    "sg:address":"8130 Evernia St",
    "sg:city":"Sebastian",
    "sg:classifiers":[
        {
            "category":"Home & Garden",
            "subcategory":"Garden Supply",
            "type":"Retail Goods"
        }
    ],
    "sg:phone":"+1 772 664 9200",
    "sg:postcode":"32976",
    "sg:province":"FL",
    "sg:tags":[
        "lawn",
        "mower"
    ],
    "wof:name":"Mower Shop",
    "wof:placetype":"venue"
},
  "geometry": {"coordinates":[-80.504706,27.879203],"type":"Point"}
}