{
  "type": "Feature",
  "properties": {
    "iso:country":"US",
    "sg:address":"103 Clyde Morris Blvd",
    "sg:city":"Ormond Beach",
    "sg:classifiers":[
        {
            "category":"Social Services",
            "subcategory":"Job Training",
            "type":"Services"
        }
    ],
    "sg:phone":"+1 386 673 0450",
    "sg:postcode":"32174",
    "sg:province":"FL",
    "sg:tags":[
        "rehabilitation"
    ],
    "sg:website":"www.homequalitymanagement.com",
    "wof:name":"Ormond In The Pines Rehab Ctr",
    "wof:placetype":"venue"
},
  "geometry": {"coordinates":[-81.09685899999999,29.271341],"type":"Point"}
}