{
  "type": "Feature",
  "properties": {
    "iso:country":"US",
    "sg:address":"11704 Forest Mere Dr",
    "sg:city":"Bonita Springs",
    "sg:classifiers":[
        {
            "category":"Building & Trades",
            "subcategory":"Electrical",
            "type":"Services"
        }
    ],
    "sg:phone":"+1 239 948 0880",
    "sg:postcode":"34135",
    "sg:province":"FL",
    "sg:tags":[
        "electrical",
        "contractor"
    ],
    "wof:name":"Laudan Electric Inc",
    "wof:placetype":"venue"
},
  "geometry": {"coordinates":[-81.76045499999999,26.352658],"type":"Point"}
}