{
  "type": "Feature",
  "properties": {
    "addr:full":"7333 Miami Lakes Dr Hialeah FL 33014",
    "addr:housenumber":"7333",
    "addr:postcode":"33014",
    "addr:street":"Miami Lakes Dr",
    "iso:country":"US",
    "sg:address":"7333 Miami Lakes Dr",
    "sg:city":"Hialeah",
    "sg:classifiers":[
        {
            "category":"Professional",
            "subcategory":"Management & Consulting",
            "type":"Services"
        }
    ],
    "sg:phone":"+1 305 558 7188",
    "sg:postcode":"33014",
    "sg:province":"FL",
    "sg:tags":[
        "logistics",
        "center"
    ],
    "wof:name":"Zicrom Group International",
    "wof:placetype":"venue"
},
  "geometry": {"coordinates":[-80.319811,25.910612],"type":"Point"}
}