{
  "type": "Feature",
  "properties": {
    "iso:country":"US",
    "sg:address":"920 SE 10th St",
    "sg:city":"Stuart",
    "sg:classifiers":[
        {
            "category":"Government",
            "subcategory":"Office",
            "type":"Public Place"
        }
    ],
    "sg:phone":"+1 772 288 5398",
    "sg:postcode":"34994",
    "sg:province":"FL",
    "sg:tags":[
        "transportation"
    ],
    "wof:name":"Public Works Dept",
    "wof:placetype":"venue"
},
  "geometry": {"coordinates":[-80.239467,27.190247],"type":"Point"}
}