{
  "type": "Feature",
  "properties": {
    "iso:country":"US",
    "sg:address":"860 N 8th St",
    "sg:city":"Lantana",
    "sg:classifiers":[
        {
            "category":"Home & Garden",
            "subcategory":"Building Materials",
            "type":"Retail Goods"
        }
    ],
    "sg:phone":"+1 561 841 8461",
    "sg:postcode":"33462",
    "sg:province":"FL",
    "sg:tags":[
        "windows"
    ],
    "wof:name":"Clearview Windows & Doors",
    "wof:placetype":"venue"
},
  "geometry": {"coordinates":[-80.058015,26.591044],"type":"Point"}
}