{
  "type": "Feature",
  "properties": {
    "iso:country":"US",
    "sg:address":"13402 Coastal Key Rd",
    "sg:city":"Tampa",
    "sg:classifiers":[
        {
            "category":"Real Estate",
            "subcategory":"Real Estate Operator",
            "type":"Services"
        }
    ],
    "sg:phone":"+1 813 903 8484",
    "sg:postcode":"33612",
    "sg:province":"FL",
    "sg:tags":[
        "apartment"
    ],
    "wof:name":"Royal Palm Key Apartments",
    "wof:placetype":"venue"
},
  "geometry": {"coordinates":[-82.446263,28.068113],"type":"Point"}
}