{
  "type": "Feature",
  "properties": {
    "addr:full":"4180 Jog Rd Lake Worth FL 33467",
    "addr:housenumber":"4180",
    "addr:postcode":"33467",
    "addr:street":"Jog Rd",
    "iso:country":"US",
    "sg:address":"4180 Jog Rd",
    "sg:city":"Lake Worth",
    "sg:classifiers":[
        {
            "category":"Restaurant",
            "type":"Food & Drink"
        }
    ],
    "sg:phone":"+1 561 963 8737",
    "sg:postcode":"33467",
    "sg:province":"FL",
    "sg:tags":[
        "eating"
    ],
    "wof:name":"Taste of Heaven Cafe Inc",
    "wof:placetype":"venue"
},
  "geometry": {"coordinates":[-80.146642,26.618381],"type":"Point"}
}