{
  "type": "Feature",
  "properties": {
    "iso:country":"US",
    "sg:address":"2146 Sopchoppy Hwy",
    "sg:city":"Sopchoppy",
    "sg:classifiers":[
        {
            "category":"Shopping",
            "subcategory":"Bicycles & Sporting Goods",
            "type":"Retail Goods"
        }
    ],
    "sg:phone":"+1 850 962 3555",
    "sg:postcode":"32358",
    "sg:province":"FL",
    "wof:name":"Lous Bait & Tackle",
    "wof:placetype":"venue"
},
  "geometry": {"coordinates":[-84.48523,30.06026],"type":"Point"}
}