{
  "type": "Feature",
  "properties": {
    "addr:full":"2050 Havendale Blvd NW Winter Haven FL 33881",
    "addr:housenumber":"2050",
    "addr:postcode":"33881",
    "addr:street":"Havendale Blvd Nw",
    "iso:country":"US",
    "sg:address":"2050 Havendale Blvd NW",
    "sg:city":"Winter Haven",
    "sg:classifiers":[
        {
            "category":"Health Services",
            "subcategory":"Doctor",
            "type":"Services"
        }
    ],
    "sg:phone":"+1 863 294 9884",
    "sg:postcode":"33881",
    "sg:province":"FL",
    "sg:tags":[
        "physician",
        "surgeon"
    ],
    "wof:name":"First Health Inc",
    "wof:placetype":"venue"
},
  "geometry": {"coordinates":[-81.749037,28.046157],"type":"Point"}
}