{
  "type": "Feature",
  "properties": {
    "iso:country":"US",
    "sg:address":"1550 Tamiami Trl",
    "sg:city":"Venice",
    "sg:classifiers":[
        {
            "category":"Autos & Motor Vehicles",
            "subcategory":"Automobile Sales",
            "type":"Retail Goods"
        }
    ],
    "sg:phone":"+1 941 493 5204",
    "sg:postcode":"34293",
    "sg:province":"FL",
    "sg:tags":[
        "car",
        "dealer"
    ],
    "sg:website":"www.venicechrysler.com",
    "wof:name":"Venice Chrysler",
    "wof:placetype":"venue"
},
  "geometry": {"coordinates":[-82.427103,27.076168],"type":"Point"}
}