{
  "type": "Feature",
  "properties": {
    "addr:full":"5975 Cattlemen Ln Sarasota FL 34232",
    "addr:housenumber":"5975",
    "addr:postcode":"34232",
    "addr:street":"Cattlemen Ln",
    "iso:country":"US",
    "sg:address":"5975 Cattlemen Ln",
    "sg:city":"Sarasota",
    "sg:classifiers":[
        {
            "category":"Professional",
            "type":"Services"
        }
    ],
    "sg:phone":"+1 941 552 2130",
    "sg:postcode":"34232",
    "sg:province":"FL",
    "sg:tags":[
        "establishment"
    ],
    "wof:name":"Star Card Inc",
    "wof:placetype":"venue"
},
  "geometry": {"coordinates":[-82.451402,27.314065],"type":"Point"}
}