{
  "type": "Feature",
  "properties": {
    "iso:country":"US",
    "sg:address":"472 Goldenrod Cir N",
    "sg:city":"Auburndale",
    "sg:classifiers":[
        {
            "category":"Restaurant",
            "type":"Food & Drink"
        }
    ],
    "sg:phone":"+1 863 665 8535",
    "sg:postcode":"33823",
    "sg:province":"FL",
    "sg:tags":[
        "eating"
    ],
    "wof:name":"Meg Subs & Dogs",
    "wof:placetype":"venue"
},
  "geometry": {"coordinates":[-81.85331499999999,28.062901],"type":"Point"}
}