{
  "type": "Feature",
  "properties": {
    "iso:country":"US",
    "sg:address":"263 Debary Dr",
    "sg:city":"Debary",
    "sg:classifiers":[
        {
            "category":"Building & Trades",
            "subcategory":"Landscaping Services",
            "type":"Services"
        }
    ],
    "sg:phone":"+1 407 402 5578",
    "sg:postcode":"32713",
    "sg:province":"FL",
    "sg:tags":[
        "tree"
    ],
    "wof:name":"A & D Tree & Bob Cat",
    "wof:placetype":"venue"
},
  "geometry": {"coordinates":[-81.288223,28.873374],"type":"Point"}
}