{
  "type": "Feature",
  "properties": {
    "addr:full":"6945 Carlisle Ct Naples FL 34109",
    "addr:housenumber":"6945",
    "addr:postcode":"34109",
    "addr:street":"Carlisle Ct",
    "iso:country":"US",
    "sg:address":"6945 Carlisle Ct",
    "sg:city":"Naples",
    "sg:classifiers":[
        {
            "category":"Health Services",
            "subcategory":"Health Practitioner",
            "type":"Services"
        }
    ],
    "sg:phone":"+1 239 514 0364",
    "sg:postcode":"34109",
    "sg:province":"FL",
    "sg:tags":[
        "gambling",
        "addiction-information",
        "treatment"
    ],
    "wof:name":"Integracare Rehabilitation Agency Inc",
    "wof:placetype":"venue"
},
  "geometry": {"coordinates":[-81.770859,26.230099],"type":"Point"}
}