{
  "type": "Feature",
  "properties": {
    "iso:country":"US",
    "sg:address":"402 W Sonata Cir",
    "sg:city":"Panama City Bch",
    "sg:classifiers":[
        {
            "category":"Building & Trades",
            "subcategory":"Construction",
            "type":"Services"
        }
    ],
    "sg:phone":"+1 850 235 2598",
    "sg:postcode":"32413",
    "sg:province":"FL",
    "sg:tags":[
        "wallpaper"
    ],
    "wof:name":"Bailey's Wall Covering Svc",
    "wof:placetype":"venue"
},
  "geometry": {"coordinates":[-85.85651799999999,30.210547],"type":"Point"}
}