{
  "type": "Feature",
  "properties": {
    "iso:country":"US",
    "sg:address":"5131 Sheridan St",
    "sg:city":"Hollywood",
    "sg:classifiers":[
        {
            "category":"Wholesale",
            "subcategory":"Durable Goods & Equipment",
            "type":"Manufacturing & Wholesale Goods"
        }
    ],
    "sg:phone":"+1 954 966 1411",
    "sg:postcode":"33021",
    "sg:province":"FL",
    "sg:tags":[
        "exporter"
    ],
    "wof:name":"Britel",
    "wof:placetype":"venue"
},
  "geometry": {"coordinates":[-80.190405,26.032834],"type":"Point"}
}