{
  "type": "Feature",
  "properties": {
    "addr:full":"2299 Drew St Clearwater FL 33765",
    "addr:housenumber":"2299",
    "addr:postcode":"33765",
    "addr:street":"Drew St",
    "iso:country":"US",
    "sg:address":"2299 Drew St",
    "sg:city":"Clearwater",
    "sg:classifiers":[
        {
            "category":"Social Services",
            "subcategory":"Child Care",
            "type":"Services"
        }
    ],
    "sg:phone":"+1 727 799 1766",
    "sg:postcode":"33765",
    "sg:province":"FL",
    "sg:tags":[
        "organization",
        "religious",
        "day"
    ],
    "wof:name":"1st Christian Pre-School",
    "wof:placetype":"venue"
},
  "geometry": {"coordinates":[-82.74362000000001,27.967947],"type":"Point"}
}