{
  "type": "Feature",
  "properties": {
    "iso:country":"US",
    "sg:address":"5391 10th St",
    "sg:city":"Malone",
    "sg:classifiers":[
        {
            "category":"Personal",
            "subcategory":"Barber",
            "type":"Services"
        }
    ],
    "sg:phone":"+1 850 569 2722",
    "sg:postcode":"32445",
    "sg:province":"FL",
    "sg:tags":[
        "shop"
    ],
    "wof:name":"Tony's Nu Looks",
    "wof:placetype":"venue"
},
  "geometry": {"coordinates":[-85.162195,30.958994],"type":"Point"}
}