{
  "type": "Feature",
  "properties": {
    "iso:country":"US",
    "sg:address":"2602 W Azeele St",
    "sg:city":"Tampa",
    "sg:classifiers":[
        {
            "category":"Shopping",
            "subcategory":"Jewelry",
            "type":"Retail Goods"
        }
    ],
    "sg:phone":"+1 813 873 7397",
    "sg:postcode":"33609",
    "sg:province":"FL",
    "sg:tags":[
        "jeweler"
    ],
    "wof:name":"Baubles Etc Inc",
    "wof:placetype":"venue"
},
  "geometry": {"coordinates":[-82.48708499999999,27.941035],"type":"Point"}
}