{
  "type": "Feature",
  "properties": {
    "addr:full":"1401 SW 39th St Fort Lauderdale FL 33315",
    "addr:housenumber":"1401",
    "addr:postcode":"33315",
    "addr:street":"Sw 39Th St",
    "iso:country":"US",
    "sg:address":"1401 SW 39th St",
    "sg:city":"Fort Lauderdale",
    "sg:classifiers":[
        {
            "category":"Professional",
            "type":"Services"
        }
    ],
    "sg:phone":"+1 954 635 2000",
    "sg:postcode":"33315",
    "sg:province":"FL",
    "sg:tags":[
        "establishment"
    ],
    "wof:name":"Amerijet International",
    "wof:placetype":"venue"
},
  "geometry": {"coordinates":[-80.159891,26.074005],"type":"Point"}
}