{
  "type": "Feature",
  "properties": {
    "addr:full":"4855 43rd Ave Vero Beach FL 32967",
    "addr:housenumber":"4855",
    "addr:postcode":"32967",
    "addr:street":"43Rd Ave",
    "iso:country":"US",
    "sg:address":"4855 43rd Ave",
    "sg:city":"Vero Beach",
    "sg:classifiers":[
        {
            "category":"Organizations",
            "subcategory":"Community Association",
            "type":"Services"
        }
    ],
    "sg:phone":"+1 772 567 1435",
    "sg:postcode":"32967",
    "sg:province":"FL",
    "sg:tags":[
        "civic"
    ],
    "wof:name":"Gifford Community Center",
    "wof:placetype":"venue"
},
  "geometry": {"coordinates":[-80.42957,27.682285],"type":"Point"}
}