{
  "type": "Feature",
  "properties": {
    "iso:country":"US",
    "sg:address":"2045 Blue River Rd",
    "sg:city":"Holiday",
    "sg:classifiers":[
        {
            "category":"Education",
            "subcategory":"Special Training",
            "type":"Public Place"
        }
    ],
    "sg:phone":"+1 727 937 6306",
    "sg:postcode":"34691",
    "sg:province":"FL",
    "sg:tags":[
        "educational"
    ],
    "wof:name":"Suncoast Seminars Inc",
    "wof:placetype":"venue"
},
  "geometry": {"coordinates":[-82.768197,28.188798],"type":"Point"}
}