{
  "type": "Feature",
  "properties": {
    "iso:country":"US",
    "sg:address":"11565 N Quayside Dr",
    "sg:city":"Hollywood",
    "sg:classifiers":[
        {
            "category":"Professional",
            "subcategory":"Computer Services",
            "type":"Services"
        }
    ],
    "sg:phone":"+1 954 437 6171",
    "sg:postcode":"33026",
    "sg:province":"FL",
    "sg:tags":[
        "website",
        "design"
    ],
    "sg:website":"www.webauthor.org",
    "wof:name":"Web Author",
    "wof:placetype":"venue"
},
  "geometry": {"coordinates":[-80.30176299999999,26.03707],"type":"Point"}
}