{
  "type": "Feature",
  "properties": {
    "iso:country":"US",
    "sg:address":"6554 44th St N",
    "sg:city":"Pinellas Park",
    "sg:classifiers":[
        {
            "category":"Professional",
            "subcategory":"Advertising",
            "type":"Services"
        }
    ],
    "sg:phone":"+1 727 525 9394",
    "sg:postcode":"33781",
    "sg:province":"FL",
    "sg:tags":[
        "distribution"
    ],
    "wof:name":"Jay's Of Bay Area Inc",
    "wof:placetype":"venue"
},
  "geometry": {"coordinates":[-82.6939,27.831345],"type":"Point"}
}