{
  "type": "Feature",
  "properties": {
    "addr:full":"800 Michigan Ave Miami Beach FL 33139",
    "addr:housenumber":"800",
    "addr:postcode":"33139",
    "addr:street":"Michigan Ave",
    "iso:country":"US",
    "sg:address":"800 Michigan Ave",
    "sg:city":"Miami Beach",
    "sg:classifiers":[
        {
            "category":"Organizations",
            "subcategory":"Professional Association",
            "type":"Services"
        }
    ],
    "sg:phone":"+1 305 534 8574",
    "sg:postcode":"33139",
    "sg:province":"FL",
    "wof:name":"Magnolia Condo Assn",
    "wof:placetype":"venue"
},
  "geometry": {"coordinates":[-80.13845999999999,25.779344],"type":"Point"}
}