{
  "type": "Feature",
  "properties": {
    "addr:full":"17697 SW 31st Ct Hollywood FL 33029",
    "addr:housenumber":"17697",
    "addr:postcode":"33029",
    "addr:street":"Sw 31St Ct",
    "iso:country":"US",
    "sg:address":"17697 SW 31st Ct",
    "sg:city":"Hollywood",
    "sg:classifiers":[
        {
            "category":"Manufacturing",
            "subcategory":"Electronics",
            "type":"Manufacturing & Wholesale Goods"
        }
    ],
    "sg:phone":"+1 954 442 1012",
    "sg:postcode":"33029",
    "sg:province":"FL",
    "sg:tags":[
        "electronic",
        "component",
        "mfg"
    ],
    "wof:name":"Orion Security & Satellite Sys",
    "wof:placetype":"venue"
},
  "geometry": {"coordinates":[-80.382205,25.980622],"type":"Point"}
}