{
  "type": "Feature",
  "properties": {
    "addr:full":"228 Dolphin Pt Clearwater FL 33767",
    "addr:housenumber":"228",
    "addr:postcode":"33767",
    "addr:street":"Dolphin Pt",
    "iso:country":"US",
    "sg:address":"228 Dolphin Pt",
    "sg:city":"Clearwater",
    "sg:classifiers":[
        {
            "category":"Professional",
            "subcategory":"Business Services",
            "type":"Services"
        }
    ],
    "sg:phone":"+1 727 443 6603",
    "sg:postcode":"33767",
    "sg:province":"FL",
    "sg:tags":[
        "security",
        "safety",
        "product"
    ],
    "wof:name":"Americas Personal Security",
    "wof:placetype":"venue"
},
  "geometry": {"coordinates":[-82.818585,27.980297],"type":"Point"}
}