{
  "type": "Feature",
  "properties": {
    "iso:country":"US",
    "sg:address":"2601 W Flagler St",
    "sg:city":"Miami",
    "sg:classifiers":[
        {
            "category":"Restaurant",
            "type":"Food & Drink"
        }
    ],
    "sg:phone":"+1 305 649 5250",
    "sg:postcode":"33135",
    "sg:province":"FL",
    "wof:name":"Oyanka Restaurant",
    "wof:placetype":"venue"
},
  "geometry": {"coordinates":[-80.239102,25.772337],"type":"Point"}
}