{
  "type": "Feature",
  "properties": {
    "iso:country":"US",
    "sg:address":"10390 NE 2nd Ave",
    "sg:city":"Miami",
    "sg:classifiers":[
        {
            "category":"Social Services",
            "subcategory":"Child Care",
            "type":"Services"
        }
    ],
    "sg:phone":"+1 305 759 5439",
    "sg:postcode":"33138",
    "sg:province":"FL",
    "sg:tags":[
        "day"
    ],
    "wof:name":"Advent Child Care Inc",
    "wof:placetype":"venue"
},
  "geometry": {"coordinates":[-80.193744,25.869737],"type":"Point"}
}