{
  "type": "Feature",
  "properties": {
    "addr:full":"2701 Kurt St Eustis FL 32726",
    "addr:housenumber":"2701",
    "addr:postcode":"32726",
    "addr:street":"Kurt St",
    "iso:country":"US",
    "sg:address":"2701 Kurt St",
    "sg:city":"Eustis",
    "sg:classifiers":[
        {
            "category":"Health Services",
            "subcategory":"Chiropractor",
            "type":"Services"
        }
    ],
    "sg:phone":"+1 352 357 8383",
    "sg:postcode":"32726",
    "sg:province":"FL",
    "wof:name":"Ledlow Roger DC Dabco",
    "wof:placetype":"venue"
},
  "geometry": {"coordinates":[-81.691695,28.828702],"type":"Point"}
}