{
  "type": "Feature",
  "properties": {
    "addr:full":"6355 NW 99th Ave Doral FL 33178",
    "addr:housenumber":"6355",
    "addr:postcode":"33178",
    "addr:street":"Nw 99Th Ave",
    "iso:country":"US",
    "sg:address":"6355 NW 99th Ave",
    "sg:city":"Doral",
    "sg:classifiers":[
        {
            "category":"Building & Trades",
            "subcategory":"Construction",
            "type":"Services"
        }
    ],
    "sg:phone":"+1 786 269 2823",
    "sg:postcode":"33178",
    "sg:province":"FL",
    "sg:tags":[
        "contractor"
    ],
    "wof:name":"Design and Construction Recreational",
    "wof:placetype":"venue"
},
  "geometry": {"coordinates":[-80.35789699999999,25.831256],"type":"Point"}
}