{
  "type": "Feature",
  "properties": {
    "addr:full":"5925 Ashford Ln Naples FL 34110",
    "addr:housenumber":"5925",
    "addr:postcode":"34110",
    "addr:street":"Ashford Ln",
    "iso:country":"US",
    "sg:address":"5925 Ashford Ln",
    "sg:city":"Naples",
    "sg:classifiers":[
        {
            "category":"Personal",
            "subcategory":"Massage",
            "type":"Services"
        }
    ],
    "sg:phone":"+1 239 405 2482",
    "sg:postcode":"34110",
    "sg:province":"FL",
    "wof:name":"Untie The Knot",
    "wof:placetype":"venue"
},
  "geometry": {"coordinates":[-81.753591,26.293982],"type":"Point"}
}