{
  "type": "Feature",
  "properties": {
    "addr:full":"2723 S Woodland Blvd Deland FL 32720",
    "addr:housenumber":"2723",
    "addr:postcode":"32720",
    "addr:street":"S Woodland Blvd",
    "iso:country":"US",
    "sg:address":"2723 S Woodland Blvd",
    "sg:city":"Deland",
    "sg:classifiers":[
        {
            "category":"Restaurant",
            "type":"Food & Drink"
        }
    ],
    "sg:menulink":"http://www.allmenus.com/fl/de-bary-orange-city/236403-tropical-smoothie/menu/",
    "sg:phone":"+1 386 785 1505",
    "sg:postcode":"32720",
    "sg:province":"FL",
    "sg:tags":[
        "smoothy",
        "juice",
        "american"
    ],
    "wof:name":"Tropical Smoothie",
    "wof:placetype":"venue"
},
  "geometry": {"coordinates":[-81.299329,28.980502],"type":"Point"}
}