{
  "type": "Feature",
  "properties": {
    "addr:full":"3818 Bay Club Cir Apt 104 Kissimmee FL 34741",
    "addr:housenumber":"3818;104",
    "addr:postcode":"34741",
    "addr:street":"Bay Club Cir Apt",
    "iso:country":"US",
    "sg:address":"3818 Bay Club Cir Apt 104",
    "sg:city":"Kissimmee",
    "sg:classifiers":[
        {
            "category":"Local Transit",
            "type":"Transportation"
        }
    ],
    "sg:phone":"+1 407 922 1498",
    "sg:postcode":"34741",
    "sg:province":"FL",
    "sg:tags":[
        "public"
    ],
    "wof:name":"Asim S Khan Transportation",
    "wof:placetype":"venue"
},
  "geometry": {"coordinates":[-81.441902,28.31024],"type":"Point"}
}