{
  "type": "Feature",
  "properties": {
    "iso:country":"US",
    "sg:address":"18400 NW 75th Pl",
    "sg:city":"Hialeah",
    "sg:classifiers":[
        {
            "category":"Building & Trades",
            "subcategory":"Locksmith",
            "type":"Services"
        }
    ],
    "sg:phone":"+1 305 755 4277",
    "sg:postcode":"33015",
    "sg:province":"FL",
    "sg:tags":[
        "key"
    ],
    "wof:name":"24 Hour Available Locksmith",
    "wof:placetype":"venue"
},
  "geometry": {"coordinates":[-80.322762,25.941153],"type":"Point"}
}