{
  "type": "Feature",
  "properties": {
    "iso:country":"US",
    "sg:address":"10050 NW 116th Way",
    "sg:city":"Medley",
    "sg:classifiers":[
        {
            "category":"Manufacturing",
            "subcategory":"Tools & Machinery",
            "type":"Manufacturing & Wholesale Goods"
        }
    ],
    "sg:phone":"+1 305 888 8622",
    "sg:postcode":"33178",
    "sg:province":"FL",
    "sg:tags":[
        "physician",
        "surgeon"
    ],
    "wof:name":"Pfb Inter-Apparel",
    "wof:placetype":"venue"
},
  "geometry": {"coordinates":[-80.361656,25.873495],"type":"Point"}
}