{
  "type": "Feature",
  "properties": {
    "iso:country":"US",
    "sg:address":"3225 Bearclaw Way",
    "sg:city":"Kissimmee",
    "sg:classifiers":[
        {
            "category":"Professional",
            "subcategory":"Computer Services",
            "type":"Services"
        }
    ],
    "sg:phone":"+1 407 390 9253",
    "sg:postcode":"34746",
    "sg:province":"FL",
    "sg:tags":[
        "consulting"
    ],
    "wof:name":"Doss Inc",
    "wof:placetype":"venue"
},
  "geometry": {"coordinates":[-81.495773,28.343628],"type":"Point"}
}