{
  "type": "Feature",
  "properties": {
    "addr:full":"14606 Brentwood Pl Tampa FL 33618",
    "addr:housenumber":"14606",
    "addr:postcode":"33618",
    "addr:street":"Brentwood Pl",
    "iso:country":"US",
    "sg:address":"14606 Brentwood Pl",
    "sg:city":"Tampa",
    "sg:classifiers":[
        {
            "category":"Professional",
            "subcategory":"Secretarial Services",
            "type":"Services"
        }
    ],
    "sg:phone":"+1 813 961 4782",
    "sg:postcode":"33618",
    "sg:province":"FL",
    "sg:tags":[
        "reporting"
    ],
    "wof:name":"Maureen M Patricio",
    "wof:placetype":"venue"
},
  "geometry": {"coordinates":[-82.501075,28.08165],"type":"Point"}
}