{
  "type": "Feature",
  "properties": {
    "addr:full":"6350 Dixie Hwy Miami FL 33143",
    "addr:housenumber":"6350",
    "addr:postcode":"33143",
    "addr:street":"Dixie Hwy",
    "iso:country":"US",
    "sg:address":"6350 Dixie Hwy",
    "sg:city":"Miami",
    "sg:classifiers":[
        {
            "category":"Retail",
            "subcategory":"Auto Repair",
            "type":"Services"
        }
    ],
    "sg:phone":"+1 305 667 5096",
    "sg:postcode":"33143",
    "sg:province":"FL",
    "sg:tags":[
        "station",
        "gasoline",
        "general"
    ],
    "wof:name":"Amoco",
    "wof:placetype":"venue"
},
  "geometry": {"coordinates":[-80.29660199999999,25.698568],"type":"Point"}
}