{
  "type": "Feature",
  "properties": {
    "addr:full":"1677 NE 163rd St Miami FL 33162",
    "addr:housenumber":"1677",
    "addr:postcode":"33162",
    "addr:street":"Ne 163Rd St",
    "iso:country":"US",
    "sg:address":"1677 NE 163rd St",
    "sg:city":"Miami",
    "sg:classifiers":[
        {
            "category":"Wholesale",
            "subcategory":"Medical Equipment & Supplies",
            "type":"Manufacturing & Wholesale Goods"
        }
    ],
    "sg:phone":"+1 305 947 8960",
    "sg:postcode":"33162",
    "sg:province":"FL",
    "sg:tags":[
        "physician",
        "surgeon"
    ],
    "wof:name":"One Stop Medical Supply Inc",
    "wof:placetype":"venue"
},
  "geometry": {"coordinates":[-80.1674,25.925866],"type":"Point"}
}