{
  "type": "Feature",
  "properties": {
    "addr:full":"3996 Buck Lake Rd Tallahassee FL 32317",
    "addr:housenumber":"3996",
    "addr:postcode":"32317",
    "addr:street":"Buck Lake Rd",
    "iso:country":"US",
    "sg:address":"3996 Buck Lake Rd",
    "sg:city":"Tallahassee",
    "sg:classifiers":[
        {
            "category":"Home & Garden",
            "subcategory":"Furniture",
            "type":"Retail Goods"
        }
    ],
    "sg:phone":"+1 850 878 8493",
    "sg:postcode":"32317",
    "sg:province":"FL",
    "wof:name":"Gardner Cabinets",
    "wof:placetype":"venue"
},
  "geometry": {"coordinates":[-84.21343,30.463655],"type":"Point"}
}