{
  "type": "Feature",
  "properties": {
    "addr:full":"10659 E Colonial Dr Orlando FL 32817",
    "addr:housenumber":"10659",
    "addr:postcode":"32817",
    "addr:street":"E Colonial Dr",
    "iso:country":"US",
    "sg:address":"10659 E Colonial Dr",
    "sg:city":"Orlando",
    "sg:classifiers":[
        {
            "category":"Food & Beverages",
            "subcategory":"Groceries & Convenience Stores",
            "type":"Retail Goods"
        }
    ],
    "sg:phone":"+1 407 277 7688",
    "sg:postcode":"32817",
    "sg:province":"FL",
    "sg:tags":[
        "grocer"
    ],
    "wof:name":"Plaza Gigante",
    "wof:placetype":"venue"
},
  "geometry": {"coordinates":[-81.230974,28.569619],"type":"Point"}
}