{
  "type": "Feature",
  "properties": {
    "addr:full":"14437 Dover Forest Dr Orlando FL 32828",
    "addr:housenumber":"14437",
    "addr:postcode":"32828",
    "addr:street":"Dover Forest Dr",
    "iso:country":"US",
    "sg:address":"14437 Dover Forest Dr",
    "sg:city":"Orlando",
    "sg:classifiers":[
        {
            "category":"Food & Beverages",
            "subcategory":"Groceries & Convenience Stores",
            "type":"Retail Goods"
        }
    ],
    "sg:phone":"+1 407 282 9322",
    "sg:postcode":"32828",
    "sg:province":"FL",
    "wof:name":"Toasty Food Corp",
    "wof:placetype":"venue"
},
  "geometry": {"coordinates":[-81.167618,28.524317],"type":"Point"}
}