{
  "type": "Feature",
  "properties": {
    "addr:full":"501 150th Ave Saint Petersburg FL 33708",
    "addr:housenumber":"501",
    "addr:postcode":"33708",
    "addr:street":"150Th Ave",
    "iso:country":"US",
    "sg:address":"501 150th Ave",
    "sg:city":"Saint Petersburg",
    "sg:classifiers":[
        {
            "category":"Organizations",
            "subcategory":"Professional Association",
            "type":"Services"
        }
    ],
    "sg:phone":"+1 727 391 7373",
    "sg:postcode":"33708",
    "sg:province":"FL",
    "sg:tags":[
        "business"
    ],
    "wof:name":"Gulf Beaches of Tampa Bay",
    "wof:placetype":"venue"
},
  "geometry": {"coordinates":[-82.79964200000001,27.802204],"type":"Point"}
}