{
  "type": "Feature",
  "properties": {
    "addr:full":"1603 Seabrook Rd Jupiter FL 33469",
    "addr:housenumber":"1603",
    "addr:postcode":"33469",
    "addr:street":"Seabrook Rd",
    "iso:country":"US",
    "sg:address":"1603 Seabrook Rd",
    "sg:city":"Jupiter",
    "sg:classifiers":[
        {
            "category":"Insurance",
            "subcategory":"Insurance Agent",
            "type":"Services"
        }
    ],
    "sg:phone":"+1 561 747 7625",
    "sg:postcode":"33469",
    "sg:province":"FL",
    "wof:name":"William H Collins",
    "wof:placetype":"venue"
},
  "geometry": {"coordinates":[-80.09521700000001,26.954429],"type":"Point"}
}