{
  "type": "Feature",
  "properties": {
    "iso:country":"US",
    "sg:address":"4524 Atwood Dr",
    "sg:city":"Orlando",
    "sg:classifiers":[
        {
            "category":"Museum",
            "subcategory":"Aquarium",
            "type":"Entertainment"
        }
    ],
    "sg:phone":"+1 407 234 1158",
    "sg:postcode":"32828",
    "sg:province":"FL",
    "sg:tags":[
        "public"
    ],
    "wof:name":"Bluewater Custom Aquariums, Inc.",
    "wof:placetype":"venue"
},
  "geometry": {"coordinates":[-81.137413,28.49732],"type":"Point"}
}