{
  "type": "Feature",
  "properties": {
    "iso:country":"US",
    "sg:address":"4442 Park Blvd",
    "sg:city":"Pinellas Park",
    "sg:classifiers":[
        {
            "category":"Food & Beverages",
            "subcategory":"Bakery",
            "type":"Retail Goods"
        }
    ],
    "sg:phone":"+1 727 548 1400",
    "sg:postcode":"33781",
    "sg:province":"FL",
    "sg:tags":[
        "baker"
    ],
    "wof:name":"Bread Artisans",
    "wof:placetype":"venue"
},
  "geometry": {"coordinates":[-82.69556799999999,27.839142],"type":"Point"}
}