{
  "type": "Feature",
  "properties": {
    "iso:country":"US",
    "sg:address":"13500 Sutton Park Dr S",
    "sg:city":"Jacksonville",
    "sg:classifiers":[
        {
            "category":"Professional",
            "subcategory":"Engineering",
            "type":"Services"
        }
    ],
    "sg:phone":"+1 904 992 1133",
    "sg:postcode":"32224",
    "sg:province":"FL",
    "sg:tags":[
        "engineer",
        "structural"
    ],
    "wof:name":"Bill Simpson & Associates",
    "wof:placetype":"venue"
},
  "geometry": {"coordinates":[-81.46257,30.25807],"type":"Point"}
}