{
  "type": "Feature",
  "properties": {
    "iso:country":"US",
    "sg:address":"12361 SW 186th St",
    "sg:city":"Miami",
    "sg:classifiers":[
        {
            "category":"Communications",
            "subcategory":"Film & Video Production",
            "type":"Services"
        }
    ],
    "sg:phone":"+1 305 278 7373",
    "sg:postcode":"33177",
    "sg:province":"FL",
    "sg:tags":[
        "tv",
        "radio",
        "services-commercial",
        "companies-film"
    ],
    "wof:name":"Carters Production",
    "wof:placetype":"venue"
},
  "geometry": {"coordinates":[-80.392089,25.595082],"type":"Point"}
}