{
  "type": "Feature",
  "properties": {
    "iso:country":"US",
    "sg:address":"2630 Landmark Dr",
    "sg:city":"Clearwater",
    "sg:classifiers":[
        {
            "category":"Education",
            "subcategory":"School",
            "type":"Public Place"
        }
    ],
    "sg:phone":"+1 727 725 7972",
    "sg:postcode":"33761",
    "sg:province":"FL",
    "sg:website":"www.davis-es.pinellas.k12.fl.us",
    "wof:name":"Davis Elementary School",
    "wof:placetype":"venue"
},
  "geometry": {"coordinates":[-82.715706,28.016219],"type":"Point"}
}