{
  "type": "Feature",
  "properties": {
    "addr:full":"3530 12th St N Naples FL 34103",
    "addr:housenumber":"3530",
    "addr:postcode":"34103",
    "addr:street":"12Th St N",
    "iso:country":"US",
    "sg:address":"3530 12th St N",
    "sg:city":"Naples",
    "sg:classifiers":[
        {
            "category":"Professional",
            "subcategory":"Computer Services",
            "type":"Services"
        }
    ],
    "sg:phone":"+1 239 430 0416",
    "sg:postcode":"34103",
    "sg:province":"FL",
    "sg:tags":[
        "processing",
        "datum"
    ],
    "wof:name":"Arjay Enterprises Co",
    "wof:placetype":"venue"
},
  "geometry": {"coordinates":[-81.795772,26.188604],"type":"Point"}
}