{
  "type": "Feature",
  "properties": {
    "iso:country":"US",
    "sg:address":"7525 Fordham Creek Ln",
    "sg:city":"Orlando",
    "sg:classifiers":[
        {
            "category":"Professional",
            "subcategory":"Art Services",
            "type":"Services"
        }
    ],
    "sg:phone":"+1 407 532 1896",
    "sg:postcode":"32818",
    "sg:province":"FL",
    "sg:tags":[
        "graphic",
        "commercial",
        "designer",
        "artist"
    ],
    "wof:name":"Eight Star Computer Graphics",
    "wof:placetype":"venue"
},
  "geometry": {"coordinates":[-81.482748,28.595893],"type":"Point"}
}