{
  "type": "Feature",
  "properties": {
    "addr:full":"511 NE 55th Ter Miami FL 33137",
    "addr:housenumber":"511",
    "addr:postcode":"33137",
    "addr:street":"Ne 55Th Ter",
    "iso:country":"US",
    "sg:address":"511 NE 55th Ter",
    "sg:city":"Miami",
    "sg:classifiers":[
        {
            "category":"Marine",
            "type":"Transportation"
        }
    ],
    "sg:phone":"+1 305 758 6530",
    "sg:postcode":"33137",
    "sg:province":"FL",
    "sg:tags":[
        "equipment",
        "supply"
    ],
    "wof:name":"Maxi Marine Part Sales Co",
    "wof:placetype":"venue"
},
  "geometry": {"coordinates":[-80.184534,25.826883],"type":"Point"}
}