{
  "type": "Feature",
  "properties": {
    "addr:full":"1122 Hemlock Cir Fort Pierce FL 34947",
    "addr:housenumber":"1122",
    "addr:postcode":"34947",
    "addr:street":"Hemlock Cir",
    "iso:country":"US",
    "sg:address":"1122 Hemlock Cir",
    "sg:city":"Fort Pierce",
    "sg:classifiers":[
        {
            "category":"Retail",
            "subcategory":"Funeral Services",
            "type":"Services"
        }
    ],
    "sg:phone":"+1 772 464 6544",
    "sg:postcode":"34947",
    "sg:province":"FL",
    "wof:name":"Fredericks Funeral Home Inc",
    "wof:placetype":"venue"
},
  "geometry": {"coordinates":[-80.354894,27.437156],"type":"Point"}
}