{
  "type": "Feature",
  "properties": {
    "iso:country":"US",
    "sg:address":"6869 Hayter Dr",
    "sg:city":"Lakeland",
    "sg:classifiers":[
        {
            "category":"Professional",
            "subcategory":"Business Services",
            "type":"Services"
        }
    ],
    "sg:phone":"+1 863 644 1946",
    "sg:postcode":"33813",
    "sg:province":"FL",
    "wof:name":"Practcal Sltions Pope Cnty LLC",
    "wof:placetype":"venue"
},
  "geometry": {"coordinates":[-81.963098,27.940196],"type":"Point"}
}