{
  "type": "Feature",
  "properties": {
    "iso:country":"US",
    "sg:address":"9318 NW 13th St Bay 10",
    "sg:city":"Doral",
    "sg:classifiers":[
        {
            "category":"Building & Trades",
            "subcategory":"Plumbing",
            "type":"Services"
        }
    ],
    "sg:phone":"+1 305 592 3141",
    "sg:postcode":"33172",
    "sg:province":"FL",
    "sg:website":"www.plumbtechservicesinc.com",
    "wof:name":"PlumbTech Services Inc.",
    "wof:placetype":"venue"
},
  "geometry": {"coordinates":[-80.34791,25.784706],"type":"Point"}
}