{
  "type": "Feature",
  "properties": {
    "iso:country":"US",
    "sg:address":"6901 Ian Ct",
    "sg:city":"New Port Richey",
    "sg:classifiers":[
        {
            "category":"Banks & Credit Unions",
            "subcategory":"Bank",
            "type":"Services"
        }
    ],
    "sg:phone":"+1 727 534 7724",
    "sg:postcode":"34653",
    "sg:province":"FL",
    "sg:tags":[
        "mortgage"
    ],
    "wof:name":"Ineedthegreennowcom",
    "wof:placetype":"venue"
},
  "geometry": {"coordinates":[-82.70265499999999,28.257181],"type":"Point"}
}