{
  "type": "Feature",
  "properties": {
    "iso:country":"US",
    "sg:address":"120 N K St",
    "sg:city":"Lake Worth",
    "sg:classifiers":[
        {
            "category":"Manufacturing",
            "subcategory":"Retail Goods",
            "type":"Manufacturing & Wholesale Goods"
        }
    ],
    "sg:phone":"+1 561 540 2520",
    "sg:postcode":"33460",
    "sg:province":"FL",
    "sg:tags":[
        "manufacturer"
    ],
    "wof:name":"Alltel Industries",
    "wof:placetype":"venue"
},
  "geometry": {"coordinates":[-80.055226,26.617552],"type":"Point"}
}