{
  "type": "Feature",
  "properties": {
    "iso:country":"US",
    "sg:address":"4635 Del Prado Blvd S",
    "sg:city":"Cape Coral",
    "sg:classifiers":[
        {
            "category":"Professional",
            "subcategory":"Lawyer & Legal Services",
            "type":"Services"
        }
    ],
    "sg:phone":"+1 239 344 3905",
    "sg:postcode":"33904",
    "sg:province":"FL",
    "wof:name":"Hussey Alison C",
    "wof:placetype":"venue"
},
  "geometry": {"coordinates":[-81.943636,26.565011],"type":"Point"}
}