{
  "type": "Feature",
  "properties": {
    "iso:country":"US",
    "sg:address":"7301 S Orange Blossom Trl",
    "sg:city":"Orlando",
    "sg:classifiers":[
        {
            "category":"Professional",
            "subcategory":"Business Services",
            "type":"Services"
        },
        {
            "category":"Government",
            "subcategory":"Post Office",
            "type":"Public Place"
        }
    ],
    "sg:phone":"+1 800 275 8777",
    "sg:postcode":"32809",
    "sg:province":"FL",
    "sg:tags":[
        "mail",
        "shipping"
    ],
    "sg:website":"http://www.usps.com",
    "wof:name":"USPS - United States Post Office - CPU Rightway Foods",
    "wof:placetype":"venue"
},
  "geometry": {"coordinates":[-81.398087,28.460035],"type":"Point"}
}