{
  "type": "Feature",
  "properties": {
    "addr:full":"1510 W Cleveland St Tampa FL 33606",
    "addr:housenumber":"1510",
    "addr:postcode":"33606",
    "addr:street":"W Cleveland St",
    "iso:country":"US",
    "sg:address":"1510 W Cleveland St",
    "sg:city":"Tampa",
    "sg:classifiers":[
        {
            "category":"Professional",
            "subcategory":"Lawyer & Legal Services",
            "type":"Services"
        }
    ],
    "sg:phone":"+1 813 258 6770",
    "sg:postcode":"33606",
    "sg:province":"FL",
    "sg:tags":[
        "attorney"
    ],
    "wof:name":"Gibbons & Melendi",
    "wof:placetype":"venue"
},
  "geometry": {"coordinates":[-82.475685,27.943161],"type":"Point"}
}