{
  "type": "Feature",
  "properties": {
    "addr:full":"3400 NW 15th St Lauderhill FL 33311",
    "addr:housenumber":"3400",
    "addr:postcode":"33311",
    "addr:street":"Nw 15Th St",
    "iso:country":"US",
    "sg:address":"3400 NW 15th St",
    "sg:city":"Lauderhill",
    "sg:classifiers":[
        {
            "category":"Building & Trades",
            "subcategory":"Equipment Rental",
            "type":"Services"
        }
    ],
    "sg:phone":"+1 954 797 3867",
    "sg:postcode":"33311",
    "sg:province":"FL",
    "sg:tags":[
        "yard"
    ],
    "wof:name":"United Rentals",
    "wof:placetype":"venue"
},
  "geometry": {"coordinates":[-80.196973,26.144923],"type":"Point"}
}