{
  "type": "Feature",
  "properties": {
    "addr:full":"1464 SW 25th Way Deerfield Beach FL 33442",
    "addr:housenumber":"1464",
    "addr:postcode":"33442",
    "addr:street":"Sw 25Th Way",
    "iso:country":"US",
    "sg:address":"1464 SW 25th Way",
    "sg:city":"Deerfield Beach",
    "sg:classifiers":[
        {
            "category":"Building & Trades",
            "subcategory":"Construction",
            "type":"Services"
        }
    ],
    "sg:phone":"+1 954 426 5129",
    "sg:postcode":"33442",
    "sg:province":"FL",
    "sg:tags":[
        "contractor"
    ],
    "wof:name":"Italia Tile & Marble Inc",
    "wof:placetype":"venue"
},
  "geometry": {"coordinates":[-80.138176,26.298131],"type":"Point"}
}