{
  "type": "Feature",
  "properties": {
    "iso:country":"US",
    "sg:address":"8555 W Hillsborough Ave",
    "sg:city":"Tampa",
    "sg:classifiers":[
        {
            "category":"Shopping",
            "subcategory":"Florist",
            "type":"Retail Goods"
        }
    ],
    "sg:phone":"+1 813 885 2273",
    "sg:postcode":"33615",
    "sg:province":"FL",
    "wof:name":"Outa MA Tree Flor & Gift Btq",
    "wof:placetype":"venue"
},
  "geometry": {"coordinates":[-82.581165,27.996825],"type":"Point"}
}