{
  "type": "Feature",
  "properties": {
    "addr:full":"13101 McGregor Blvd Fort Myers FL 33919",
    "addr:housenumber":"13101",
    "addr:postcode":"33919",
    "addr:street":"Mcgregor Blvd",
    "iso:country":"US",
    "sg:address":"13101 McGregor Blvd",
    "sg:city":"Fort Myers",
    "sg:classifiers":[
        {
            "category":"Shopping",
            "subcategory":"Used Merchandise",
            "type":"Retail Goods"
        }
    ],
    "sg:phone":"+1 239 590 9888",
    "sg:postcode":"33919",
    "sg:province":"FL",
    "sg:tags":[
        "antique"
    ],
    "wof:name":"Kaleidoscope Consignments",
    "wof:placetype":"venue"
},
  "geometry": {"coordinates":[-81.909933,26.557759],"type":"Point"}
}