{
  "type": "Feature",
  "properties": {
    "addr:full":"600 Corporate Dr Fort Lauderdale FL 33334",
    "addr:housenumber":"600",
    "addr:postcode":"33334",
    "addr:street":"Corporate Dr",
    "iso:country":"US",
    "sg:address":"600 Corporate Dr",
    "sg:city":"Fort Lauderdale",
    "sg:classifiers":[
        {
            "category":"Food & Beverages",
            "subcategory":"Specialty",
            "type":"Retail Goods"
        }
    ],
    "sg:phone":"+1 954 491 2866",
    "sg:postcode":"33334",
    "sg:province":"FL",
    "wof:name":"GNC",
    "wof:placetype":"venue"
},
  "geometry": {"coordinates":[-80.137736,26.204435],"type":"Point"}
}