{
  "type": "Feature",
  "properties": {
    "iso:country":"US",
    "sg:address":"2919 Commonwealth Blvd",
    "sg:city":"Tallahassee",
    "sg:classifiers":[
        {
            "category":"Manufacturing",
            "subcategory":"Tools & Machinery",
            "type":"Manufacturing & Wholesale Goods"
        }
    ],
    "sg:phone":"+1 850 575 8181",
    "sg:postcode":"32303",
    "sg:province":"FL",
    "sg:tags":[
        "industry",
        "mfg",
        "val",
        "mach"
    ],
    "wof:name":"Precision Engine Products",
    "wof:placetype":"venue"
},
  "geometry": {"coordinates":[-84.348879,30.473561],"type":"Point"}
}