{
  "type": "Feature",
  "properties": {
    "iso:country":"US",
    "sg:address":"217 Palm Beach Trace Dr",
    "sg:city":"West Palm Beach",
    "sg:classifiers":[
        {
            "category":"Building & Trades",
            "subcategory":"Construction",
            "type":"Services"
        }
    ],
    "sg:phone":"+1 561 712 4662",
    "sg:postcode":"33411",
    "sg:province":"FL",
    "sg:tags":[
        "hanging",
        "contractor"
    ],
    "wof:name":"Delco Pntg & Texturing Svcs",
    "wof:placetype":"venue"
},
  "geometry": {"coordinates":[-80.227013,26.712723],"type":"Point"}
}