{
  "type": "Feature",
  "properties": {
    "addr:full":"801 W Dr Martin Luther King Jr Blvd Martin Luther Seffner FL 33584",
    "addr:housenumber":"801",
    "addr:postcode":"33584",
    "addr:street":"W Dr Martin Luther King Jr Blvd Martin Luther Seffner",
    "iso:country":"US",
    "sg:address":"801 W Dr Martin Luther King Jr Blvd Martin Luther",
    "sg:city":"Seffner",
    "sg:classifiers":[
        {
            "category":"Health Services",
            "subcategory":"Clinic",
            "type":"Services"
        },
        {
            "category":"Community Center",
            "type":"Public Place"
        }
    ],
    "sg:phone":"+1 813 684 4424",
    "sg:postcode":"33584",
    "sg:province":"FL",
    "sg:tags":[
        "medical"
    ],
    "sg:website":"http://www.dwic.org",
    "wof:name":"Doctors Walk In Clinic",
    "wof:placetype":"venue"
},
  "geometry": {"coordinates":[-82.287003,27.98159],"type":"Point"}
}