{
  "type": "Feature",
  "properties": {
    "iso:country":"US",
    "sg:address":"1116 S Florida Ave",
    "sg:city":"Lakeland",
    "sg:classifiers":[
        {
            "category":"Wholesale",
            "subcategory":"Durable Goods & Equipment",
            "type":"Manufacturing & Wholesale Goods"
        }
    ],
    "sg:phone":"+1 863 683 8463",
    "sg:postcode":"33803",
    "sg:province":"FL",
    "wof:name":"Jims Watches Wholesale Inc",
    "wof:placetype":"venue"
},
  "geometry": {"coordinates":[-81.95703899999999,28.029332],"type":"Point"}
}