{
  "type": "Feature",
  "properties": {
    "iso:country":"US",
    "sg:address":"6781 Cleveland St",
    "sg:city":"Hollywood",
    "sg:classifiers":[
        {
            "category":"Building & Trades",
            "subcategory":"Construction",
            "type":"Services"
        }
    ],
    "sg:phone":"+1 954 961 5078",
    "sg:postcode":"33024",
    "sg:province":"FL",
    "sg:tags":[
        "contractor"
    ],
    "wof:name":"Planet Pools",
    "wof:placetype":"venue"
},
  "geometry": {"coordinates":[-80.220468,26.021771],"type":"Point"}
}