{
  "type": "Feature",
  "properties": {
    "addr:full":"12555 Orange Dr Davie FL 33328",
    "addr:housenumber":"12555",
    "addr:postcode":"33328",
    "addr:street":"Orange Dr",
    "iso:country":"US",
    "sg:address":"12555 Orange Dr",
    "sg:city":"Davie",
    "sg:classifiers":[
        {
            "category":"Banks & Credit Unions",
            "subcategory":"Financial Services",
            "type":"Services"
        }
    ],
    "sg:phone":"+1 954 862 1489",
    "sg:postcode":"33328",
    "sg:province":"FL",
    "sg:tags":[
        "company",
        "holding"
    ],
    "wof:name":"Abyssmian Holdings Corp",
    "wof:placetype":"venue"
},
  "geometry": {"coordinates":[-80.31507999999999,26.06432],"type":"Point"}
}