{
  "type": "Feature",
  "properties": {
    "iso:country":"US",
    "sg:address":"3131 Lakeland Hills Blvd",
    "sg:city":"Lakeland",
    "sg:classifiers":[
        {
            "category":"Health Services",
            "subcategory":"Clinic",
            "type":"Services"
        }
    ],
    "sg:phone":"+1 863 688 1338",
    "sg:postcode":"33805",
    "sg:province":"FL",
    "wof:name":"Housecall Home Healthcare",
    "wof:placetype":"venue"
},
  "geometry": {"coordinates":[-81.953256,28.083784],"type":"Point"}
}