{
  "type": "Feature",
  "properties": {
    "iso:country":"US",
    "sg:address":"721 Beville Rd",
    "sg:city":"Daytona Beach",
    "sg:classifiers":[
        {
            "category":"Real Estate",
            "subcategory":"Real Estate Operator",
            "type":"Services"
        }
    ],
    "sg:phone":"+1 386 788 8494",
    "sg:postcode":"32119",
    "sg:province":"FL",
    "sg:tags":[
        "property",
        "commercial"
    ],
    "wof:name":"721 Beville Road LLC",
    "wof:placetype":"venue"
},
  "geometry": {"coordinates":[-81.018293,29.17945],"type":"Point"}
}