{
  "type": "Feature",
  "properties": {
    "addr:full":"3413 Zillah St Tallahassee FL 32305",
    "addr:housenumber":"3413",
    "addr:postcode":"32305",
    "addr:street":"Zillah St",
    "iso:country":"US",
    "sg:address":"3413 Zillah St",
    "sg:city":"Tallahassee",
    "sg:classifiers":[
        {
            "category":"Education",
            "subcategory":"School",
            "type":"Public Place"
        }
    ],
    "sg:phone":"+1 850 488 8927",
    "sg:postcode":"32305",
    "sg:province":"FL",
    "wof:name":"Pace Secondary School",
    "wof:placetype":"venue"
},
  "geometry": {"coordinates":[-84.26883100000001,30.40061],"type":"Point"}
}