{
  "type": "Feature",
  "properties": {
    "iso:country":"US",
    "sg:address":"16000 E Troon Cir",
    "sg:city":"Hialeah",
    "sg:classifiers":[
        {
            "category":"Building & Trades",
            "subcategory":"Locksmith",
            "type":"Services"
        }
    ],
    "sg:phone":"+1 305 423 1022",
    "sg:postcode":"33014",
    "sg:province":"FL",
    "sg:tags":[
        "key"
    ],
    "wof:name":"A A A 24 Miami Locksmith",
    "wof:placetype":"venue"
},
  "geometry": {"coordinates":[-80.315337,25.918396],"type":"Point"}
}