{
  "type": "Feature",
  "properties": {
    "addr:full":"12995 S Cleveland Ave Ste 207 Fort Myers FL 33907",
    "addr:housenumber":"12995",
    "addr:postcode":"myers;33907",
    "addr:street":"S Cleveland Ave Ste 207",
    "iso:country":"US",
    "sg:address":"12995 S Cleveland Ave Ste 207",
    "sg:city":"Fort Myers",
    "sg:classifiers":[
        {
            "category":"Personal",
            "subcategory":"Nail Salon",
            "type":"Services"
        }
    ],
    "sg:phone":"+1 239 437 1232",
    "sg:postcode":"33907",
    "sg:province":"FL",
    "wof:name":"Studio Bella",
    "wof:placetype":"venue"
},
  "geometry": {"coordinates":[-81.870459,26.552643],"type":"Point"}
}