{
  "type": "Feature",
  "properties": {
    "iso:country":"US",
    "sg:address":"3668 Lake Blvd",
    "sg:city":"Clearwater",
    "sg:classifiers":[
        {
            "category":"Wholesale",
            "subcategory":"Durable Goods & Equipment",
            "type":"Manufacturing & Wholesale Goods"
        }
    ],
    "sg:phone":"+1 727 771 1915",
    "sg:postcode":"33762",
    "sg:province":"FL",
    "sg:tags":[
        "representative",
        "manufacturer"
    ],
    "wof:name":"Associated Retail Marketing",
    "wof:placetype":"venue"
},
  "geometry": {"coordinates":[-82.683544,27.868691],"type":"Point"}
}