{
  "type": "Feature",
  "properties": {
    "addr:full":"4152 Old Dixie Hwy Malabar FL 32949",
    "addr:housenumber":"4152",
    "addr:postcode":"32949",
    "addr:street":"Old Dixie Hwy",
    "iso:country":"US",
    "sg:address":"4152 Old Dixie Hwy",
    "sg:city":"Malabar",
    "sg:classifiers":[
        {
            "category":"Home & Garden",
            "subcategory":"Building Materials",
            "type":"Retail Goods"
        }
    ],
    "sg:phone":"+1 321 631 6200",
    "sg:postcode":"32949",
    "sg:province":"FL",
    "sg:tags":[
        "mixed",
        "concrete"
    ],
    "wof:name":"Cemex",
    "wof:placetype":"venue"
},
  "geometry": {"coordinates":[-80.541473,27.958172],"type":"Point"}
}