{
  "type": "Feature",
  "properties": {
    "iso:country":"US",
    "sg:address":"290 NW 188th St",
    "sg:city":"Miami",
    "sg:classifiers":[
        {
            "category":"Health Services",
            "subcategory":"Nursing And Care Facility",
            "type":"Services"
        }
    ],
    "sg:phone":"+1 305 650 0565",
    "sg:postcode":"33169",
    "sg:province":"FL",
    "wof:name":"B R A S W E L L-Alf",
    "wof:placetype":"venue"
},
  "geometry": {"coordinates":[-80.20567800000001,25.946784],"type":"Point"}
}