{
  "type": "Feature",
  "properties": {
    "iso:country":"US",
    "sg:address":"6867 Taft St",
    "sg:city":"Hollywood",
    "sg:classifiers":[
        {
            "category":"Shopping",
            "subcategory":"Clothing, Apparel, & Fashions",
            "type":"Retail Goods"
        }
    ],
    "sg:phone":"+1 954 981 3153",
    "sg:postcode":"33024",
    "sg:province":"FL",
    "wof:name":"Dots Inc",
    "wof:placetype":"venue"
},
  "geometry": {"coordinates":[-80.225093,26.024533],"type":"Point"}
}