{
  "type": "Feature",
  "properties": {
    "addr:full":"4690 N Powerline Rd Pompano Beach FL 33073",
    "addr:housenumber":"4690",
    "addr:postcode":"33073",
    "addr:street":"N Powerline Rd",
    "iso:country":"US",
    "sg:address":"4690 N Powerline Rd",
    "sg:city":"Pompano Beach",
    "sg:classifiers":[
        {
            "category":"Wholesale",
            "subcategory":"Machinery & Supplies",
            "type":"Manufacturing & Wholesale Goods"
        },
        {
            "category":"Manufacturing",
            "subcategory":"Tools & Machinery",
            "type":"Manufacturing & Wholesale Goods"
        }
    ],
    "sg:phone":"+1 954 977 8797",
    "sg:postcode":"33073",
    "sg:province":"FL",
    "sg:tags":[
        "industry",
        "parts",
        "aerospace"
    ],
    "wof:name":"Avant Aerospace Inc",
    "wof:placetype":"venue"
},
  "geometry": {"coordinates":[-80.152252,26.287366],"type":"Point"}
}