{
  "type": "Feature",
  "properties": {
    "iso:country":"US",
    "sg:address":"7250 Hendry Creek Dr",
    "sg:city":"Fort Myers",
    "sg:classifiers":[
        {
            "category":"Building & Trades",
            "subcategory":"Construction",
            "type":"Services"
        }
    ],
    "sg:phone":"+1 239 433 5870",
    "sg:postcode":"33908",
    "sg:province":"FL",
    "sg:tags":[
        "house",
        "contractor"
    ],
    "wof:name":"Weaver Josh H & Sons Inc",
    "wof:placetype":"venue"
},
  "geometry": {"coordinates":[-81.87750200000001,26.516701],"type":"Point"}
}