{
  "type": "Feature",
  "properties": {
    "addr:full":"11735 Plantation Rd Fort Myers FL 33966",
    "addr:housenumber":"11735",
    "addr:postcode":"33966",
    "addr:street":"Plantation Rd",
    "iso:country":"US",
    "sg:address":"11735 Plantation Rd",
    "sg:city":"Fort Myers",
    "sg:classifiers":[
        {
            "category":"Organizations",
            "subcategory":"Religious Organization",
            "type":"Services"
        }
    ],
    "sg:phone":"+1 239 939 5433",
    "sg:postcode":"33966",
    "sg:province":"FL",
    "sg:tags":[
        "church"
    ],
    "sg:website":"www.lifechurch.net",
    "wof:name":"Life Church",
    "wof:placetype":"venue"
},
  "geometry": {"coordinates":[-81.84664600000001,26.557774],"type":"Point"}
}