{
  "type": "Feature",
  "properties": {
    "addr:full":"4343 Lakeland Park Dr Lakeland FL 33809",
    "addr:housenumber":"4343",
    "addr:postcode":"33809",
    "addr:street":"Lakeland Park Dr",
    "iso:country":"US",
    "sg:address":"4343 Lakeland Park Dr",
    "sg:city":"Lakeland",
    "sg:classifiers":[
        {
            "category":"Bars & Pubs",
            "type":"Food & Drink"
        },
        {
            "category":"Restaurant",
            "type":"Food & Drink"
        }
    ],
    "sg:menulink":"http://www.allmenus.com/fl/lakeland/35139-cracker-barrel-old-country-store/menu/",
    "sg:phone":"+1 863 853 5405",
    "sg:postcode":"33809",
    "sg:province":"FL",
    "sg:tags":[
        "american",
        "southern"
    ],
    "wof:name":"Cracker Barrel Old Country Store",
    "wof:placetype":"venue"
},
  "geometry": {"coordinates":[-81.953886,28.097587],"type":"Point"}
}