{
  "type": "Feature",
  "properties": {
    "iso:country":"US",
    "sg:address":"7055 W Sasser St",
    "sg:city":"Homosassa",
    "sg:classifiers":[
        {
            "category":"Real Estate",
            "subcategory":"Real Estate Agent",
            "type":"Services"
        }
    ],
    "sg:phone":"+1 352 621 7530",
    "sg:postcode":"34446",
    "sg:province":"FL",
    "wof:name":"Lynda Gregory",
    "wof:placetype":"venue"
},
  "geometry": {"coordinates":[-82.550838,28.785592],"type":"Point"}
}