{
  "type": "Feature",
  "properties": {
    "addr:full":"1076 Conant Ave Safety Harbor FL 34695",
    "addr:housenumber":"1076",
    "addr:postcode":"34695",
    "addr:street":"Conant Ave",
    "iso:country":"US",
    "sg:address":"1076 Conant Ave",
    "sg:city":"Safety Harbor",
    "sg:classifiers":[
        {
            "category":"Building & Trades",
            "subcategory":"Electrical",
            "type":"Services"
        },
        {
            "category":"Shopping",
            "type":"Retail Goods"
        }
    ],
    "sg:phone":"+1 727 725 5228",
    "sg:postcode":"34695",
    "sg:province":"FL",
    "sg:tags":[
        "equipment",
        "supply",
        "electrical",
        "telephone",
        "contractor"
    ],
    "wof:name":"Proper Connections Inc",
    "wof:placetype":"venue"
},
  "geometry": {"coordinates":[-82.684136,27.998014],"type":"Point"}
}