{
  "type": "Feature",
  "properties": {
    "addr:full":"245 East Dr Melbourne FL 32904",
    "addr:housenumber":"245",
    "addr:postcode":"32904",
    "addr:street":"East Dr",
    "iso:country":"US",
    "sg:address":"245 East Dr",
    "sg:city":"Melbourne",
    "sg:classifiers":[
        {
            "category":"Professional",
            "subcategory":"Research",
            "type":"Services"
        }
    ],
    "sg:phone":"+1 321 951 3830",
    "sg:postcode":"32904",
    "sg:province":"FL",
    "sg:tags":[
        "environmental",
        "ecological"
    ],
    "wof:name":"Consolidated Environmental",
    "wof:placetype":"venue"
},
  "geometry": {"coordinates":[-80.688959,28.105118],"type":"Point"}
}