{
  "type": "Feature",
  "properties": {
    "iso:country":"US",
    "sg:address":"3605 Old Winter Garden Rd",
    "sg:city":"Orlando",
    "sg:classifiers":[
        {
            "category":"Retail",
            "subcategory":"Auto Repair",
            "type":"Services"
        }
    ],
    "sg:phone":"+1 407 295 4053",
    "sg:postcode":"32805",
    "sg:province":"FL",
    "sg:tags":[
        "repairing",
        "automobile"
    ],
    "wof:name":"Repair Automotive",
    "wof:placetype":"venue"
},
  "geometry": {"coordinates":[-81.421525,28.547358],"type":"Point"}
}