{
  "type": "Feature",
  "properties": {
    "iso:country":"US",
    "sg:address":"6463 W Constitution Ln",
    "sg:city":"Homosassa",
    "sg:classifiers":[
        {
            "category":"Building & Trades",
            "subcategory":"Construction",
            "type":"Services"
        }
    ],
    "sg:phone":"+1 352 736 5001",
    "sg:postcode":"34448",
    "sg:province":"FL",
    "sg:tags":[
        "roofing",
        "contractor"
    ],
    "wof:name":"Above It All Roofing Inc",
    "wof:placetype":"venue"
},
  "geometry": {"coordinates":[-82.545225,28.843068],"type":"Point"}
}