{
  "type": "Feature",
  "properties": {
    "iso:country":"US",
    "sg:address":"2051 NW 31st Ave",
    "sg:city":"Fort Lauderdale",
    "sg:classifiers":[
        {
            "category":"Health Services",
            "subcategory":"Doctor",
            "type":"Services"
        }
    ],
    "sg:phone":"+1 954 735 2907",
    "sg:postcode":"33311",
    "sg:province":"FL",
    "sg:tags":[
        "medical"
    ],
    "wof:name":"Washington Wf Dr",
    "wof:placetype":"venue"
},
  "geometry": {"coordinates":[-80.18702999999999,26.152204],"type":"Point"}
}