{
  "type": "Feature",
  "properties": {
    "iso:country":"US",
    "sg:address":"525 S Park Ave",
    "sg:city":"Winter Park",
    "sg:classifiers":[
        {
            "category":"Restaurant",
            "type":"Food & Drink"
        }
    ],
    "sg:phone":"+1 407 740 8018",
    "sg:postcode":"32789",
    "sg:province":"FL",
    "sg:tags":[
        "sushi",
        "bar",
        "japanese"
    ],
    "wof:name":"Sakura Sushi & Sake Bar",
    "wof:placetype":"venue"
},
  "geometry": {"coordinates":[-81.35050200000001,28.593901],"type":"Point"}
}