{
  "type": "Feature",
  "properties": {
    "iso:country":"US",
    "sg:address":"922 2nd Ave S",
    "sg:city":"Jacksonville Beach",
    "sg:classifiers":[
        {
            "category":"Building & Trades",
            "subcategory":"Landscaping Services",
            "type":"Services"
        }
    ],
    "sg:phone":"+1 904 249 2422",
    "sg:postcode":"32250",
    "sg:province":"FL",
    "wof:name":"P&G Lawn Service",
    "wof:placetype":"venue"
},
  "geometry": {"coordinates":[-81.39887899999999,30.285037],"type":"Point"}
}