{
  "type": "Feature",
  "properties": {
    "addr:full":"511 E Government St Pensacola FL 32502",
    "addr:housenumber":"511",
    "addr:postcode":"32502",
    "addr:street":"E Government St",
    "iso:country":"US",
    "sg:address":"511 E Government St",
    "sg:city":"Pensacola",
    "sg:classifiers":[
        {
            "category":"Real Estate",
            "subcategory":"Real Estate Agent",
            "type":"Services"
        }
    ],
    "sg:phone":"+1 850 436 6698",
    "sg:postcode":"32502",
    "sg:province":"FL",
    "sg:tags":[
        "desk",
        "space"
    ],
    "wof:name":"Seville Office Suites",
    "wof:placetype":"venue"
},
  "geometry": {"coordinates":[-87.20612,30.410627],"type":"Point"}
}