{
  "type": "Feature",
  "properties": {
    "iso:country":"US",
    "sg:address":"19500 SW 129th Ave",
    "sg:city":"Miami",
    "sg:classifiers":[
        {
            "category":"Health Services",
            "subcategory":"Health Practitioner",
            "type":"Services"
        }
    ],
    "sg:phone":"+1 305 238 7725",
    "sg:postcode":"33177",
    "sg:province":"FL",
    "sg:tags":[
        "aromatherapy"
    ],
    "wof:name":"Stormy Smoleny Phd",
    "wof:placetype":"venue"
},
  "geometry": {"coordinates":[-80.401128,25.585035],"type":"Point"}
}