{
  "type": "Feature",
  "properties": {
    "addr:full":"777 E 25th St Hialeah FL 33013",
    "addr:housenumber":"777",
    "addr:postcode":"33013",
    "addr:street":"E 25Th St",
    "iso:country":"US",
    "sg:address":"777 E 25th St",
    "sg:city":"Hialeah",
    "sg:classifiers":[
        {
            "category":"Health Services",
            "subcategory":"Doctor",
            "type":"Services"
        }
    ],
    "sg:phone":"+1 305 836 2044",
    "sg:postcode":"33013",
    "sg:province":"FL",
    "sg:tags":[
        "physician",
        "pediatrics-otorhinolaryngology",
        "surgeons",
        "otorhinolaryngology",
        "nose",
        "throat",
        "surgeon",
        "ear"
    ],
    "wof:name":"South Florida ENT Associates CC6",
    "wof:placetype":"venue"
},
  "geometry": {"coordinates":[-80.266818,25.845226],"type":"Point"}
}