{
  "type": "Feature",
  "properties": {
    "iso:country":"US",
    "sg:address":"811 N Fort Harrison Ave",
    "sg:city":"Clearwater",
    "sg:classifiers":[
        {
            "category":"Wholesale",
            "subcategory":"Hardware",
            "type":"Manufacturing & Wholesale Goods"
        }
    ],
    "sg:phone":"+1 727 441 2491",
    "sg:postcode":"33755",
    "sg:province":"FL",
    "sg:tags":[
        "air",
        "parts",
        "conditioning",
        "supply"
    ],
    "wof:name":"Jacobs & Assoc",
    "wof:placetype":"venue"
},
  "geometry": {"coordinates":[-82.798964,27.974529],"type":"Point"}
}