{
  "type": "Feature",
  "properties": {
    "iso:country":"US",
    "sg:address":"10309 N Nebraska Ave",
    "sg:city":"Tampa",
    "sg:classifiers":[
        {
            "category":"Travel",
            "subcategory":"Hotels & Motels",
            "type":"Entertainment"
        }
    ],
    "sg:phone":"+1 813 971 4050",
    "sg:postcode":"33612",
    "sg:province":"FL",
    "sg:tags":[
        "operation"
    ],
    "wof:name":"El Granada",
    "wof:placetype":"venue"
},
  "geometry": {"coordinates":[-82.45119,28.042963],"type":"Point"}
}