{
  "type": "Feature",
  "properties": {
    "addr:full":"1915 Ponce de Leon Blvd Miami FL 33134",
    "addr:housenumber":"1915",
    "addr:postcode":"33134",
    "addr:street":"Ponce De Leon Blvd",
    "iso:country":"US",
    "sg:address":"1915 Ponce de Leon Blvd",
    "sg:city":"Miami",
    "sg:classifiers":[
        {
            "category":"Shopping",
            "subcategory":"Gifts & Souvenirs",
            "type":"Retail Goods"
        }
    ],
    "sg:phone":"+1 305 444 3357",
    "sg:postcode":"33134",
    "sg:province":"FL",
    "sg:tags":[
        "basket"
    ],
    "wof:name":"Lj USA Corp",
    "wof:placetype":"venue"
},
  "geometry": {"coordinates":[-80.258719,25.7546],"type":"Point"}
}