{
  "type": "Feature",
  "properties": {
    "iso:country":"US",
    "sg:address":"24 Westfalls Ln",
    "sg:city":"Palm Coast",
    "sg:classifiers":[
        {
            "category":"Professional",
            "type":"Services"
        }
    ],
    "sg:phone":"+1 386 676 1143",
    "sg:postcode":"32164",
    "sg:province":"FL",
    "wof:name":"Edson Edson Inc",
    "wof:placetype":"venue"
},
  "geometry": {"coordinates":[-81.242864,29.532822],"type":"Point"}
}