{
  "type": "Feature",
  "properties": {
    "iso:country":"US",
    "sg:address":"10441 NW 12th Pl",
    "sg:city":"Plantation",
    "sg:classifiers":[
        {
            "category":"Building & Trades",
            "subcategory":"Construction",
            "type":"Services"
        }
    ],
    "sg:phone":"+1 954 472 6666",
    "sg:postcode":"33322",
    "sg:province":"FL",
    "sg:tags":[
        "roofing",
        "contractor"
    ],
    "wof:name":"Simpson Roofing Inc",
    "wof:placetype":"venue"
},
  "geometry": {"coordinates":[-80.288456,26.139726],"type":"Point"}
}