{
  "type": "Feature",
  "properties": {
    "iso:country":"US",
    "sg:address":"1537 W Smith St",
    "sg:city":"Orlando",
    "sg:classifiers":[
        {
            "category":"Building & Trades",
            "subcategory":"Plumbing",
            "type":"Services"
        }
    ],
    "sg:phone":"+1 407 422 7657",
    "sg:postcode":"32804",
    "sg:province":"FL",
    "sg:tags":[
        "repair",
        "system",
        "contractor",
        "air conditioning"
    ],
    "sg:website":"http://www.bobheinmiller.com/",
    "wof:name":"Bob Heinmiller Air Conditioning Inc",
    "wof:placetype":"venue"
},
  "geometry": {"coordinates":[-81.402755,28.571878],"type":"Point"}
}