{
  "type": "Feature",
  "properties": {
    "addr:full":"118 Ridgewood Ave Daytona Beach FL 32117",
    "addr:housenumber":"118",
    "addr:postcode":"32117",
    "addr:street":"Ridgewood Ave",
    "iso:country":"US",
    "sg:address":"118 Ridgewood Ave",
    "sg:city":"Daytona Beach",
    "sg:classifiers":[
        {
            "category":"Travel",
            "subcategory":"Hotels & Motels",
            "type":"Entertainment"
        }
    ],
    "sg:phone":"+1 386 252 7908",
    "sg:postcode":"32117",
    "sg:province":"FL",
    "wof:name":"Rollie's Motel",
    "wof:placetype":"venue"
},
  "geometry": {"coordinates":[-81.032521,29.228785],"type":"Point"}
}