{
  "type": "Feature",
  "properties": {
    "addr:full":"2130 US Hwy 1 Rockledge FL 32955",
    "addr:housenumber":"2130",
    "addr:postcode":"32955",
    "addr:street":"Us Hwy 1",
    "iso:country":"US",
    "sg:address":"2130 US Hwy 1",
    "sg:city":"Rockledge",
    "sg:classifiers":[
        {
            "category":"Retail",
            "subcategory":"Animal Services",
            "type":"Services"
        }
    ],
    "sg:phone":"+1 321 636 2236",
    "sg:postcode":"32955",
    "sg:province":"FL",
    "sg:tags":[
        "pet",
        "grooming",
        "washing"
    ],
    "wof:name":"Fangs Pet Salon",
    "wof:placetype":"venue"
},
  "geometry": {"coordinates":[-80.71302300000001,28.319253],"type":"Point"}
}