{
  "type": "Feature",
  "properties": {
    "addr:full":"404 E New Haven Ave Melbourne FL 32901",
    "addr:housenumber":"404",
    "addr:postcode":"32901",
    "addr:street":"E New Haven Ave",
    "iso:country":"US",
    "sg:address":"404 E New Haven Ave",
    "sg:city":"Melbourne",
    "sg:classifiers":[
        {
            "category":"Wholesale",
            "subcategory":"Hardware",
            "type":"Manufacturing & Wholesale Goods"
        },
        {
            "category":"Manufacturing",
            "subcategory":"Tools & Machinery",
            "type":"Manufacturing & Wholesale Goods"
        }
    ],
    "sg:phone":"+1 321 723 4614",
    "sg:postcode":"32901",
    "sg:province":"FL",
    "sg:tags":[
        "supply",
        "parts",
        "conditioning",
        "air"
    ],
    "wof:name":"Baker Distributing 312",
    "wof:placetype":"venue"
},
  "geometry": {"coordinates":[-80.61405499999999,28.078665],"type":"Point"}
}