{
  "type": "Feature",
  "properties": {
    "iso:country":"US",
    "sg:address":"3460 27th Ave SW",
    "sg:city":"Naples",
    "sg:classifiers":[
        {
            "category":"Building & Trades",
            "subcategory":"Plumbing",
            "type":"Services"
        }
    ],
    "sg:phone":"+1 239 455 6982",
    "sg:postcode":"34117",
    "sg:province":"FL",
    "sg:tags":[
        "contractor"
    ],
    "wof:name":"Colvenback Plumbing Inc",
    "wof:placetype":"venue"
},
  "geometry": {"coordinates":[-81.67717500000001,26.179697],"type":"Point"}
}