{
  "type": "Feature",
  "properties": {
    "iso:country":"US",
    "sg:address":"1692 W Hibiscus Blvd",
    "sg:city":"Melbourne",
    "sg:classifiers":[
        {
            "category":"Professional",
            "subcategory":"Accounting & Tax Preparation",
            "type":"Services"
        }
    ],
    "sg:phone":"+1 321 723 3352",
    "sg:postcode":"32901",
    "sg:province":"FL",
    "wof:name":"Whitaker and Associates",
    "wof:placetype":"venue"
},
  "geometry": {"coordinates":[-80.647313,28.08548],"type":"Point"}
}