{
  "type": "Feature",
  "properties": {
    "addr:full":"19508 Gulf Blvd Indian Shores FL 33785",
    "addr:housenumber":"19508",
    "addr:postcode":"33785",
    "addr:street":"Gulf Blvd",
    "iso:country":"US",
    "sg:address":"19508 Gulf Blvd",
    "sg:city":"Indian Shores",
    "sg:classifiers":[
        {
            "category":"Real Estate",
            "subcategory":"Real Estate Agent",
            "type":"Services"
        }
    ],
    "sg:phone":"+1 727 595 3751",
    "sg:postcode":"33785",
    "sg:province":"FL",
    "sg:tags":[
        "sharing",
        "condominium"
    ],
    "sg:website":"www.bayandbeach.com",
    "wof:name":"Bay & Beach Club Inc",
    "wof:placetype":"venue"
},
  "geometry": {"coordinates":[-82.845523,27.853319],"type":"Point"}
}