{
  "type": "Feature",
  "properties": {
    "iso:country":"US",
    "sg:address":"579 10th St E",
    "sg:city":"Palmetto",
    "sg:classifiers":[
        {
            "category":"Wholesale",
            "subcategory":"Machinery & Supplies",
            "type":"Manufacturing & Wholesale Goods"
        }
    ],
    "sg:phone":"+1 941 729 7910",
    "sg:postcode":"34221",
    "sg:province":"FL",
    "sg:tags":[
        "equipment",
        "barber"
    ],
    "wof:name":"Cicely's Hair & Beauty Supls",
    "wof:placetype":"venue"
},
  "geometry": {"coordinates":[-82.560119,27.521055],"type":"Point"}
}