{
  "type": "Feature",
  "properties": {
    "iso:country":"US",
    "sg:address":"9646 SW 72nd St",
    "sg:city":"Miami",
    "sg:classifiers":[
        {
            "category":"Building & Trades",
            "subcategory":"Construction",
            "type":"Services"
        }
    ],
    "sg:phone":"+1 305 630 2775",
    "sg:postcode":"33173",
    "sg:province":"FL",
    "sg:tags":[
        "contractor"
    ],
    "wof:name":"Beyond Kitchens & Baths Inc",
    "wof:placetype":"venue"
},
  "geometry": {"coordinates":[-80.349453,25.701588],"type":"Point"}
}