{
  "type": "Feature",
  "properties": {
    "iso:country":"US",
    "sg:address":"2900 S Nova Rd",
    "sg:city":"Daytona Beach",
    "sg:classifiers":[
        {
            "category":"Bars & Pubs",
            "type":"Food & Drink"
        }
    ],
    "sg:phone":"+1 386 756 5664",
    "sg:postcode":"32119",
    "sg:province":"FL",
    "sg:tags":[
        "drinking"
    ],
    "wof:name":"Daytona Club",
    "wof:placetype":"venue"
},
  "geometry": {"coordinates":[-81.01864500000001,29.152597],"type":"Point"}
}