{
  "type": "Feature",
  "properties": {
    "addr:full":"601 Manatee Ave W Bradenton FL 34205",
    "addr:housenumber":"601",
    "addr:postcode":"34205",
    "addr:street":"Manatee Ave W",
    "iso:country":"US",
    "sg:address":"601 Manatee Ave W",
    "sg:city":"Bradenton",
    "sg:classifiers":[
        {
            "category":"Health Services",
            "subcategory":"Doctor",
            "type":"Services"
        }
    ],
    "sg:phone":"+1 941 745 2727",
    "sg:postcode":"34205",
    "sg:province":"FL",
    "sg:tags":[
        "clinic"
    ],
    "wof:name":"Manatee Surgical Ctr",
    "wof:placetype":"venue"
},
  "geometry": {"coordinates":[-82.568212,27.495281],"type":"Point"}
}