{
  "type": "Feature",
  "properties": {
    "iso:country":"US",
    "sg:address":"4017 Anna Dr",
    "sg:city":"Apopka",
    "sg:classifiers":[
        {
            "category":"Shopping",
            "subcategory":"Catalog Store",
            "type":"Retail Goods"
        }
    ],
    "sg:phone":"+1 407 865 7974",
    "sg:postcode":"32703",
    "sg:province":"FL",
    "sg:tags":[
        "mail",
        "order"
    ],
    "wof:name":"David Sanchez Apistogrammas",
    "wof:placetype":"venue"
},
  "geometry": {"coordinates":[-81.436887,28.661593],"type":"Point"}
}