{
  "type": "Feature",
  "properties": {
    "addr:full":"1154 Lee Blvd Lehigh Acres FL 33936",
    "addr:housenumber":"1154",
    "addr:postcode":"33936",
    "addr:street":"Lee Blvd",
    "iso:country":"US",
    "sg:address":"1154 Lee Blvd",
    "sg:city":"Lehigh Acres",
    "sg:classifiers":[
        {
            "category":"Health Services",
            "subcategory":"Doctor",
            "type":"Services"
        }
    ],
    "sg:phone":"+1 239 368 2490",
    "sg:postcode":"33936",
    "sg:province":"FL",
    "sg:tags":[
        "medical"
    ],
    "wof:name":"Cecile Saint Paul",
    "wof:placetype":"venue"
},
  "geometry": {"coordinates":[-81.64591299999999,26.614943],"type":"Point"}
}