{
  "type": "Feature",
  "properties": {
    "iso:country":"US",
    "sg:address":"4179 Maine St",
    "sg:city":"Jupiter",
    "sg:classifiers":[
        {
            "category":"Insurance",
            "subcategory":"Insurance Agent",
            "type":"Services"
        }
    ],
    "sg:phone":"+1 561 622 7533",
    "sg:postcode":"33461",
    "sg:province":"FL",
    "wof:name":"PKM Assoc LLC",
    "wof:placetype":"venue"
},
  "geometry": {"coordinates":[-80.10663599999999,26.609444],"type":"Point"}
}