{
  "type": "Feature",
  "properties": {
    "addr:full":"11452 Sea Grass Cir Boca Raton FL 33498",
    "addr:housenumber":"11452",
    "addr:postcode":"33498",
    "addr:street":"Sea Grass Cir",
    "iso:country":"US",
    "sg:address":"11452 Sea Grass Cir",
    "sg:city":"Boca Raton",
    "sg:classifiers":[
        {
            "category":"Professional",
            "subcategory":"Lawyer & Legal Services",
            "type":"Services"
        }
    ],
    "sg:phone":"+1 561 852 9350",
    "sg:postcode":"33498",
    "sg:province":"FL",
    "sg:tags":[
        "plan"
    ],
    "wof:name":"Seagrass Holdings",
    "wof:placetype":"venue"
},
  "geometry": {"coordinates":[-80.222773,26.394555],"type":"Point"}
}