{
  "type": "Feature",
  "properties": {
    "iso:country":"US",
    "sg:address":"902 S Bay Blvd",
    "sg:city":"Anna Maria",
    "sg:classifiers":[
        {
            "category":"Recreation",
            "type":"Entertainment"
        }
    ],
    "sg:phone":"+1 941 778 3240",
    "sg:postcode":"34216",
    "sg:province":"FL",
    "sg:tags":[
        "charter",
        "boat"
    ],
    "wof:name":"Spice Sailing Charters",
    "wof:placetype":"venue"
},
  "geometry": {"coordinates":[-82.730712,27.532208],"type":"Point"}
}