{
  "type": "Feature",
  "properties": {
    "addr:full":"14200 SW 8th St Ste 110 Miami FL 33184",
    "addr:housenumber":"14200",
    "addr:postcode":"33184",
    "addr:street":"Sw 8Th St Ste 110",
    "iso:country":"US",
    "sg:address":"14200 SW 8th St Ste 110",
    "sg:city":"Miami",
    "sg:classifiers":[
        {
            "category":"Utilities",
            "subcategory":"Mobile Phone",
            "type":"Services"
        },
        {
            "category":"Shopping",
            "subcategory":"Mobile Phones",
            "type":"Retail Goods"
        },
        {
            "category":"Utilities",
            "subcategory":"Telephone",
            "type":"Services"
        },
        {
            "category":"Professional",
            "subcategory":"Computer Services",
            "type":"Services"
        }
    ],
    "sg:phone":"+1 305 226 8647",
    "sg:postcode":"33184",
    "sg:province":"FL",
    "sg:tags":[
        "telecommunication",
        "supply",
        "communication",
        "system",
        "wireless",
        "equipment",
        "cellular"
    ],
    "sg:website":"http://clickserve.dartsearch.net/link/click?lid=43000000308049899",
    "wof:name":"T-Mobile",
    "wof:placetype":"venue"
},
  "geometry": {"coordinates":[-80.42547500000001,25.76088],"type":"Point"}
}