{
  "type": "Feature",
  "properties": {
    "addr:full":"2274 King James Ct Winter Park FL 32792",
    "addr:housenumber":"2274",
    "addr:postcode":"32792",
    "addr:street":"King James Ct",
    "iso:country":"US",
    "sg:address":"2274 King James Ct",
    "sg:city":"Winter Park",
    "sg:classifiers":[
        {
            "category":"Professional",
            "type":"Services"
        }
    ],
    "sg:phone":"+1 407 671 6220",
    "sg:postcode":"32792",
    "sg:province":"FL",
    "wof:name":"Gloria K Smith-Burns",
    "wof:placetype":"venue"
},
  "geometry": {"coordinates":[-81.316796,28.615903],"type":"Point"}
}