{
  "type": "Feature",
  "properties": {
    "addr:full":"1438 NE 163rd St North Miami Bch FL 33162",
    "addr:housenumber":"1438",
    "addr:postcode":"33162",
    "addr:street":"Ne 163Rd St",
    "iso:country":"US",
    "sg:address":"1438 NE 163rd St",
    "sg:city":"North Miami Bch",
    "sg:classifiers":[
        {
            "category":"Shopping",
            "type":"Retail Goods"
        }
    ],
    "sg:phone":"+1 786 274 8334",
    "sg:postcode":"33162",
    "sg:province":"FL",
    "sg:tags":[
        "candle"
    ],
    "wof:name":"Botanica Las Americas",
    "wof:placetype":"venue"
},
  "geometry": {"coordinates":[-80.170708,25.925546],"type":"Point"}
}