{
  "type": "Feature",
  "properties": {
    "addr:full":"7236 NW 70th St Miami FL 33166",
    "addr:housenumber":"7236",
    "addr:postcode":"33166",
    "addr:street":"Nw 70Th St",
    "iso:country":"US",
    "sg:address":"7236 NW 70th St",
    "sg:city":"Miami",
    "sg:classifiers":[
        {
            "category":"Shopping",
            "subcategory":"Clothing, Apparel, & Fashions",
            "type":"Retail Goods"
        }
    ],
    "sg:phone":"+1 305 885 8545",
    "sg:postcode":"33166",
    "sg:province":"FL",
    "sg:tags":[
        "work",
        "uniform",
        "uniforms-accessories",
        "clothes"
    ],
    "sg:website":"http://www.bluegooseuniform.com",
    "wof:name":"Blue Goose Uniform Co",
    "wof:placetype":"venue"
},
  "geometry": {"coordinates":[-80.31673000000001,25.83709],"type":"Point"}
}