{
  "type": "Feature",
  "properties": {
    "addr:full":"10250 Normandy Blvd Jacksonville FL 32221",
    "addr:housenumber":"10250",
    "addr:postcode":"32221",
    "addr:street":"Normandy Blvd",
    "iso:country":"US",
    "sg:address":"10250 Normandy Blvd",
    "sg:city":"Jacksonville",
    "sg:classifiers":[
        {
            "category":"Real Estate",
            "subcategory":"Real Estate Services",
            "type":"Services"
        },
        {
            "category":"Real Estate",
            "subcategory":"Real Estate Agent",
            "type":"Services"
        }
    ],
    "sg:phone":"+1 904 483 3300",
    "sg:postcode":"32221",
    "sg:province":"FL",
    "sg:tags":[
        "buyer",
        "broker"
    ],
    "sg:website":"http://www.weichert.com",
    "wof:name":"Weichert Realtors",
    "wof:placetype":"venue"
},
  "geometry": {"coordinates":[-81.828636,30.276245],"type":"Point"}
}