{
  "type": "Feature",
  "properties": {
    "iso:country":"US",
    "sg:address":"2720 N Hiawassee Rd",
    "sg:city":"Orlando",
    "sg:classifiers":[
        {
            "category":"Shopping",
            "subcategory":"Clothing, Apparel, & Fashions",
            "type":"Retail Goods"
        }
    ],
    "sg:phone":"+1 407 299 1010",
    "sg:postcode":"32818",
    "sg:province":"FL",
    "wof:name":"J J Mens Wear",
    "wof:placetype":"venue"
},
  "geometry": {"coordinates":[-81.47611499999999,28.579624],"type":"Point"}
}