{
  "type": "Feature",
  "properties": {
    "iso:country":"US",
    "sg:address":"1521 NW 34th St",
    "sg:city":"Gainesville",
    "sg:classifiers":[
        {
            "category":"Organizations",
            "subcategory":"Religious Organization",
            "type":"Services"
        }
    ],
    "sg:phone":"+1 352 378 4032",
    "sg:postcode":"32605",
    "sg:province":"FL",
    "sg:tags":[
        "church"
    ],
    "sg:website":"www.members.tripod.com/westminsterchurch",
    "wof:name":"Westminster Presbyterian Chr",
    "wof:placetype":"venue"
},
  "geometry": {"coordinates":[-82.37229600000001,29.666529],"type":"Point"}
}