{
  "type": "Feature",
  "properties": {
    "iso:country":"US",
    "sg:address":"8257 Normandy Blvd",
    "sg:city":"Jacksonville",
    "sg:classifiers":[
        {
            "category":"Food & Beverages",
            "subcategory":"Liquor & Beverages",
            "type":"Retail Goods"
        }
    ],
    "sg:phone":"+1 904 783 9027",
    "sg:postcode":"32221",
    "sg:province":"FL",
    "sg:tags":[
        "beer",
        "ale"
    ],
    "wof:name":"Skylight Discount Beverage",
    "wof:placetype":"venue"
},
  "geometry": {"coordinates":[-81.78564799999999,30.291074],"type":"Point"}
}