{
  "type": "Feature",
  "properties": {
    "iso:country":"US",
    "sg:address":"12712 Raftsmen Ct",
    "sg:city":"Orlando",
    "sg:classifiers":[
        {
            "category":"Shopping",
            "subcategory":"Crafts & Fabrics",
            "type":"Retail Goods"
        },
        {
            "category":"Professional",
            "subcategory":"Art Services",
            "type":"Services"
        }
    ],
    "sg:phone":"+1 407 384 5693",
    "sg:postcode":"32828",
    "sg:province":"FL",
    "sg:tags":[
        "punching",
        "design",
        "embroidery"
    ],
    "wof:name":"1 2 3 Embroidery",
    "wof:placetype":"venue"
},
  "geometry": {"coordinates":[-81.197839,28.535274],"type":"Point"}
}