{
  "type": "Feature",
  "properties": {
    "iso:country":"US",
    "sg:address":"13905 SW 252nd St",
    "sg:city":"Princeton",
    "sg:classifiers":[
        {
            "category":"Retail",
            "subcategory":"Auto Repair",
            "type":"Services"
        }
    ],
    "sg:phone":"+1 305 258 9000",
    "sg:postcode":"33032",
    "sg:province":"FL",
    "sg:tags":[
        "wrecker"
    ],
    "wof:name":"Southeast Towing",
    "wof:placetype":"venue"
},
  "geometry": {"coordinates":[-80.419279,25.5328],"type":"Point"}
}