{
  "type": "Feature",
  "properties": {
    "iso:country":"US",
    "sg:address":"1036 6th Ave N",
    "sg:city":"Naples",
    "sg:classifiers":[
        {
            "category":"Health Services",
            "subcategory":"Doctor",
            "type":"Services"
        }
    ],
    "sg:phone":"+1 239 263 2858",
    "sg:postcode":"34102",
    "sg:province":"FL",
    "sg:tags":[
        "medical"
    ],
    "wof:name":"Katarina E Ondrejicka MD",
    "wof:placetype":"venue"
},
  "geometry": {"coordinates":[-81.794928,26.154048],"type":"Point"}
}