{
  "type": "Feature",
  "properties": {
    "iso:country":"US",
    "sg:address":"4243 W Lake Mary Blvd",
    "sg:city":"Lake Mary",
    "sg:classifiers":[
        {
            "category":"Sports & Exercise",
            "subcategory":"Gym",
            "type":"Entertainment"
        }
    ],
    "sg:phone":"+1 407 330 3434",
    "sg:postcode":"32746",
    "sg:province":"FL",
    "sg:tags":[
        "fitness",
        "physical",
        "facility"
    ],
    "wof:name":"Gymtime For Kids",
    "wof:placetype":"venue"
},
  "geometry": {"coordinates":[-81.349846,28.756095],"type":"Point"}
}