{
  "type": "Feature",
  "properties": {
    "addr:full":"1242 Silver Lake Dr Melbourne FL 32940",
    "addr:housenumber":"1242",
    "addr:postcode":"32940",
    "addr:street":"Silver Lake Dr",
    "iso:country":"US",
    "sg:address":"1242 Silver Lake Dr",
    "sg:city":"Melbourne",
    "sg:classifiers":[
        {
            "category":"Education",
            "subcategory":"Special Training",
            "type":"Public Place"
        }
    ],
    "sg:phone":"+1 321 255 1113",
    "sg:postcode":"32940",
    "sg:province":"FL",
    "sg:tags":[
        "program"
    ],
    "wof:name":"Image",
    "wof:placetype":"venue"
},
  "geometry": {"coordinates":[-80.69841,28.217402],"type":"Point"}
}