{
  "type": "Feature",
  "properties": {
    "iso:country":"US",
    "sg:address":"496 W Central Pkwy",
    "sg:city":"Altamonte Spgs",
    "sg:classifiers":[
        {
            "category":"Banks & Credit Unions",
            "subcategory":"Bank",
            "type":"Services"
        }
    ],
    "sg:phone":"+1 407 389 1143",
    "sg:postcode":"32714",
    "sg:province":"FL",
    "wof:name":"RBC Centura Bank",
    "wof:placetype":"venue"
},
  "geometry": {"coordinates":[-81.40239800000001,28.672645],"type":"Point"}
}