{
  "type": "Feature",
  "properties": {
    "iso:country":"US",
    "sg:address":"9772 Erica Ct",
    "sg:city":"Boca Raton",
    "sg:classifiers":[
        {
            "category":"Building & Trades",
            "subcategory":"Construction",
            "type":"Services"
        }
    ],
    "sg:phone":"+1 561 482 6700",
    "sg:postcode":"33496",
    "sg:province":"FL",
    "sg:tags":[
        "woodworker"
    ],
    "wof:name":"Bradford L Babcock Carpentry",
    "wof:placetype":"venue"
},
  "geometry": {"coordinates":[-80.18528499999999,26.402656],"type":"Point"}
}