{
  "type": "Feature",
  "properties": {
    "addr:full":"42 NW 27th Ct Miami FL 33125",
    "addr:housenumber":"42",
    "addr:postcode":"33125",
    "addr:street":"Nw 27Th Ct",
    "iso:country":"US",
    "sg:address":"42 NW 27th Ct",
    "sg:city":"Miami",
    "sg:classifiers":[
        {
            "category":"Health Services",
            "subcategory":"Clinic",
            "type":"Services"
        }
    ],
    "sg:phone":"+1 305 644 1040",
    "sg:postcode":"33125",
    "sg:province":"FL",
    "sg:tags":[
        "specialty",
        "outpatient"
    ],
    "wof:name":"Miami Rehabilitation Center",
    "wof:placetype":"venue"
},
  "geometry": {"coordinates":[-80.240284,25.775063],"type":"Point"}
}