{
  "type": "Feature",
  "properties": {
    "iso:country":"US",
    "sg:address":"18018 E Hwy 40",
    "sg:city":"Silver Springs",
    "sg:classifiers":[
        {
            "category":"Retail",
            "subcategory":"Auto Repair",
            "type":"Services"
        }
    ],
    "sg:phone":"+1 352 625 4110",
    "sg:postcode":"34488",
    "sg:province":"FL",
    "sg:tags":[
        "repairing",
        "automobile"
    ],
    "wof:name":"Forest Auto Care",
    "wof:placetype":"venue"
},
  "geometry": {"coordinates":[-81.850329,29.17189],"type":"Point"}
}