{
  "type": "Feature",
  "properties": {
    "addr:full":"6560 Pensacola Blvd Pensacola FL 32505",
    "addr:housenumber":"6560",
    "addr:postcode":"32505",
    "addr:street":"Pensacola Blvd",
    "iso:country":"US",
    "sg:address":"6560 Pensacola Blvd",
    "sg:city":"Pensacola",
    "sg:classifiers":[
        {
            "category":"Restaurant",
            "type":"Food & Drink"
        }
    ],
    "sg:phone":"+1 850 471 1221",
    "sg:postcode":"32505",
    "sg:province":"FL",
    "wof:name":"Las Palmas Mexican Restaurant",
    "wof:placetype":"venue"
},
  "geometry": {"coordinates":[-87.257971,30.485278],"type":"Point"}
}