{
  "type": "Feature",
  "properties": {
    "iso:country":"US",
    "sg:address":"2449 Crawford Ct",
    "sg:city":"Lake Worth",
    "sg:classifiers":[
        {
            "category":"Banks & Credit Unions",
            "subcategory":"Investment Brokerage",
            "type":"Services"
        }
    ],
    "sg:phone":"+1 561 967 7203",
    "sg:postcode":"33462",
    "sg:province":"FL",
    "sg:tags":[
        "advisory"
    ],
    "wof:name":"Lynx Financial Corp",
    "wof:placetype":"venue"
},
  "geometry": {"coordinates":[-80.080607,26.583827],"type":"Point"}
}