{
  "type": "Feature",
  "properties": {
    "iso:country":"US",
    "sg:address":"14790 NW 27th Ave",
    "sg:city":"Opa Locka",
    "sg:classifiers":[
        {
            "category":"Organizations",
            "subcategory":"Professional Association",
            "type":"Services"
        }
    ],
    "sg:phone":"+1 305 685 8762",
    "sg:postcode":"33054",
    "sg:province":"FL",
    "wof:name":"Progressive Officers Club Inc",
    "wof:placetype":"venue"
},
  "geometry": {"coordinates":[-80.244111,25.908289],"type":"Point"}
}