{
  "type": "Feature",
  "properties": {
    "iso:country":"US",
    "sg:address":"3621 US Hwy 19",
    "sg:city":"New Port Richey",
    "sg:classifiers":[
        {
            "category":"Shopping",
            "subcategory":"Used Merchandise",
            "type":"Retail Goods"
        }
    ],
    "sg:phone":"+1 727 842 3665",
    "sg:postcode":"34652",
    "sg:province":"FL",
    "sg:tags":[
        "flea",
        "market"
    ],
    "wof:name":"Indoor Fleas",
    "wof:placetype":"venue"
},
  "geometry": {"coordinates":[-82.73948,28.211077],"type":"Point"}
}