{
  "type": "Feature",
  "properties": {
    "iso:country":"US",
    "sg:address":"911 E Atlantic Blvd",
    "sg:city":"Pompano Beach",
    "sg:classifiers":[
        {
            "category":"Wholesale",
            "subcategory":"Medical Equipment & Supplies",
            "type":"Manufacturing & Wholesale Goods"
        },
        {
            "category":"Building & Trades",
            "subcategory":"Equipment Rental",
            "type":"Services"
        }
    ],
    "sg:phone":"+1 954 946 5950",
    "sg:postcode":"33060",
    "sg:province":"FL",
    "sg:tags":[
        "physician",
        "surgeon",
        "retail"
    ],
    "wof:name":"Broward Medical Supply Inc",
    "wof:placetype":"venue"
},
  "geometry": {"coordinates":[-80.113573,26.231793],"type":"Point"}
}