{
  "type": "Feature",
  "properties": {
    "iso:country":"US",
    "sg:address":"4105 Ocean Beach Blvd",
    "sg:city":"Cocoa Beach",
    "sg:classifiers":[
        {
            "category":"Building & Trades",
            "subcategory":"Landscaping Services",
            "type":"Services"
        }
    ],
    "sg:phone":"+1 321 784 6327",
    "sg:postcode":"32931",
    "sg:province":"FL",
    "sg:tags":[
        "landscape"
    ],
    "wof:name":"Sunshine Gardeners",
    "wof:placetype":"venue"
},
  "geometry": {"coordinates":[-80.60606900000001,28.355039],"type":"Point"}
}