{
  "type": "Feature",
  "properties": {
    "iso:country":"US",
    "sg:address":"2866 Industrial Plaza Dr",
    "sg:city":"Tallahassee",
    "sg:classifiers":[
        {
            "category":"Home & Garden",
            "subcategory":"Building Materials",
            "type":"Retail Goods"
        }
    ],
    "sg:phone":"+1 850 877 3894",
    "sg:postcode":"32301",
    "sg:province":"FL",
    "sg:tags":[
        "windows"
    ],
    "wof:name":"Kinco Windows & Doors",
    "wof:placetype":"venue"
},
  "geometry": {"coordinates":[-84.229158,30.452214],"type":"Point"}
}