{
  "type": "Feature",
  "properties": {
    "iso:country":"US",
    "sg:address":"4301 W Vine St",
    "sg:city":"Kissimmee",
    "sg:classifiers":[
        {
            "category":"Shopping",
            "subcategory":"Gifts & Souvenirs",
            "type":"Retail Goods"
        }
    ],
    "sg:phone":"+1 407 396 6522",
    "sg:postcode":"34746",
    "sg:province":"FL",
    "wof:name":"Sams As Seen On TV",
    "wof:placetype":"venue"
},
  "geometry": {"coordinates":[-81.456152,28.303713],"type":"Point"}
}