{
  "type": "Feature",
  "properties": {
    "addr:full":"201 N US Hwy 1 Jupiter FL 33477",
    "addr:housenumber":"201",
    "addr:postcode":"33477",
    "addr:street":"N Us Hwy 1",
    "iso:country":"US",
    "sg:address":"201 N US Hwy 1",
    "sg:city":"Jupiter",
    "sg:classifiers":[
        {
            "category":"Personal",
            "type":"Services"
        }
    ],
    "sg:phone":"+1 561 746 6507",
    "sg:postcode":"33477",
    "sg:province":"FL",
    "sg:tags":[
        "therapist",
        "massage"
    ],
    "wof:name":"Hands On Sports",
    "wof:placetype":"venue"
},
  "geometry": {"coordinates":[-80.08162900000001,26.935576],"type":"Point"}
}