{
  "type": "Feature",
  "properties": {
    "iso:country":"US",
    "sg:address":"2601 W Atlantic Blvd",
    "sg:city":"Pompano Beach",
    "sg:classifiers":[
        {
            "category":"Home & Garden",
            "subcategory":"Building Materials",
            "type":"Retail Goods"
        }
    ],
    "sg:phone":"+1 954 973 0455",
    "sg:postcode":"33069",
    "sg:province":"FL",
    "sg:tags":[
        "paint",
        "floor",
        "covering"
    ],
    "wof:name":"Sherwin-Williams",
    "wof:placetype":"venue"
},
  "geometry": {"coordinates":[-80.15937599999999,26.231251],"type":"Point"}
}