{
  "type": "Feature",
  "properties": {
    "iso:country":"US",
    "sg:address":"9910 Beech Ave",
    "sg:city":"Palm Beach Gdns",
    "sg:classifiers":[
        {
            "category":"Restaurant",
            "type":"Food & Drink"
        }
    ],
    "sg:phone":"+1 561 207 6973",
    "sg:postcode":"33410",
    "sg:province":"FL",
    "wof:name":"New York Pizza Dept",
    "wof:placetype":"venue"
},
  "geometry": {"coordinates":[-80.098934,26.848595],"type":"Point"}
}