{
  "type": "Feature",
  "properties": {
    "addr:full":"12847 SW 42nd St Miami FL 33175",
    "addr:housenumber":"12847",
    "addr:postcode":"33175",
    "addr:street":"Sw 42Nd St",
    "iso:country":"US",
    "sg:address":"12847 SW 42nd St",
    "sg:city":"Miami",
    "sg:classifiers":[
        {
            "category":"Shopping",
            "subcategory":"Optical Goods",
            "type":"Retail Goods"
        }
    ],
    "sg:phone":"+1 305 223 4693",
    "sg:postcode":"33175",
    "sg:province":"FL",
    "wof:name":"Optica Hispana",
    "wof:placetype":"venue"
},
  "geometry": {"coordinates":[-80.40276299999999,25.729684],"type":"Point"}
}