{
  "type": "Feature",
  "properties": {
    "addr:full":"6073 NW 167th St Hialeah FL 33015",
    "addr:housenumber":"6073",
    "addr:postcode":"33015",
    "addr:street":"Nw 167Th St",
    "iso:country":"US",
    "sg:address":"6073 NW 167th St",
    "sg:city":"Hialeah",
    "sg:classifiers":[
        {
            "category":"Wholesale",
            "subcategory":"Furniture",
            "type":"Manufacturing & Wholesale Goods"
        }
    ],
    "sg:phone":"+1 305 822 6020",
    "sg:postcode":"33015",
    "sg:province":"FL",
    "sg:tags":[
        "distributor",
        "home",
        "furnishing",
        "import"
    ],
    "wof:name":"Aviron Textiles Inc",
    "wof:placetype":"venue"
},
  "geometry": {"coordinates":[-80.298141,25.925193],"type":"Point"}
}