{
  "type": "Feature",
  "properties": {
    "iso:country":"US",
    "sg:address":"9445 SW 40th St",
    "sg:city":"Miami",
    "sg:classifiers":[
        {
            "category":"Banks & Credit Unions",
            "subcategory":"Bank",
            "type":"Services"
        }
    ],
    "sg:phone":"+1 305 480 1862",
    "sg:postcode":"33165",
    "sg:province":"FL",
    "sg:tags":[
        "mortgage",
        "loan",
        "broker",
        "real estate"
    ],
    "sg:website":"www.republicmortgageloans.com",
    "wof:name":"Home Mortgage Loans",
    "wof:placetype":"venue"
},
  "geometry": {"coordinates":[-80.34839599999999,25.732901],"type":"Point"}
}