{
  "type": "Feature",
  "properties": {
    "addr:full":"82 E Nine Mile Rd Pensacola FL 32534",
    "addr:housenumber":"82",
    "addr:postcode":"32534",
    "addr:street":"E Nine Mile Rd",
    "iso:country":"US",
    "sg:address":"82 E Nine Mile Rd",
    "sg:city":"Pensacola",
    "sg:classifiers":[
        {
            "category":"Building & Trades",
            "subcategory":"Construction",
            "type":"Services"
        }
    ],
    "sg:phone":"+1 850 477 2132",
    "sg:postcode":"32534",
    "sg:province":"FL",
    "sg:tags":[
        "home",
        "builder"
    ],
    "wof:name":"Reve Development Corp",
    "wof:placetype":"venue"
},
  "geometry": {"coordinates":[-87.27087899999999,30.533307],"type":"Point"}
}