{
  "type": "Feature",
  "properties": {
    "iso:country":"US",
    "sg:address":"6229 Indian Ln",
    "sg:city":"Lakeland",
    "sg:classifiers":[
        {
            "category":"Home & Garden",
            "subcategory":"Home Furnishings",
            "type":"Retail Goods"
        },
        {
            "category":"Building & Trades",
            "subcategory":"Construction",
            "type":"Services"
        }
    ],
    "sg:phone":"+1 863 646 4677",
    "sg:postcode":"33813",
    "sg:province":"FL",
    "sg:tags":[
        "curtain",
        "made",
        "drapery",
        "contractor"
    ],
    "wof:name":"K M Creations",
    "wof:placetype":"venue"
},
  "geometry": {"coordinates":[-81.927134,27.952891],"type":"Point"}
}