{
  "type": "Feature",
  "properties": {
    "addr:full":"1150 Weston Rd Fort Lauderdale FL 33326",
    "addr:housenumber":"1150",
    "addr:postcode":"33326",
    "addr:street":"Weston Rd",
    "iso:country":"US",
    "sg:address":"1150 Weston Rd",
    "sg:city":"Fort Lauderdale",
    "sg:classifiers":[
        {
            "category":"Restaurant",
            "type":"Food & Drink"
        }
    ],
    "sg:phone":"+1 954 384 2258",
    "sg:postcode":"33326",
    "sg:province":"FL",
    "sg:tags":[
        "sandwich"
    ],
    "wof:name":"Substantial Salads & Subs",
    "wof:placetype":"venue"
},
  "geometry": {"coordinates":[-80.363315,26.10696],"type":"Point"}
}