{
  "type": "Feature",
  "properties": {
    "iso:country":"US",
    "sg:address":"1750 Frankford Ave",
    "sg:city":"Panama City",
    "sg:classifiers":[
        {
            "category":"Wholesale",
            "subcategory":"Drugs",
            "type":"Manufacturing & Wholesale Goods"
        }
    ],
    "sg:phone":"+1 850 769 9433",
    "sg:postcode":"32405",
    "sg:province":"FL",
    "wof:name":"Banana Boat Products Inc",
    "wof:placetype":"venue"
},
  "geometry": {"coordinates":[-85.691953,30.179916],"type":"Point"}
}