{
  "type": "Feature",
  "properties": {
    "addr:full":"3885 NW Flagler Ter Miami FL 33126",
    "addr:housenumber":"3885",
    "addr:postcode":"33126",
    "addr:street":"Nw Flagler Ter",
    "iso:country":"US",
    "sg:address":"3885 NW Flagler Ter",
    "sg:city":"Miami",
    "sg:classifiers":[
        {
            "category":"Building & Trades",
            "subcategory":"Locksmith",
            "type":"Services"
        }
    ],
    "sg:phone":"+1 305 908 8652",
    "sg:postcode":"33126",
    "sg:province":"FL",
    "sg:tags":[
        "key"
    ],
    "wof:name":"Locks A A A Locksmith",
    "wof:placetype":"venue"
},
  "geometry": {"coordinates":[-80.258518,25.77267],"type":"Point"}
}