{
  "type": "Feature",
  "properties": {
    "iso:country":"US",
    "sg:address":"401 Country Club Dr",
    "sg:city":"Oldsmar",
    "sg:classifiers":[
        {
            "category":"Building & Trades",
            "subcategory":"Construction",
            "type":"Services"
        }
    ],
    "sg:phone":"+1 813 855 1255",
    "sg:postcode":"34677",
    "sg:province":"FL",
    "sg:tags":[
        "siding",
        "contractor"
    ],
    "wof:name":"Aluminum & Vinyl Specialist",
    "wof:placetype":"venue"
},
  "geometry": {"coordinates":[-82.663042,28.027671],"type":"Point"}
}