{
  "type": "Feature",
  "properties": {
    "addr:full":"2410 Ave D Fort Pierce FL 34950",
    "addr:postcode":"34950",
    "addr:street":"2410 Ave D",
    "iso:country":"US",
    "sg:address":"2410 Ave D",
    "sg:city":"Fort Pierce",
    "sg:classifiers":[
        {
            "category":"Autos & Motor Vehicles",
            "subcategory":"Fuel & Gas Station",
            "type":"Retail Goods"
        }
    ],
    "sg:phone":"+1 772 461 1010",
    "sg:postcode":"34950",
    "sg:province":"FL",
    "sg:tags":[
        "convenience",
        "station",
        "gasoline",
        "store"
    ],
    "wof:name":"Dixons Check Cashing Service",
    "wof:placetype":"venue"
},
  "geometry": {"coordinates":[-80.349773,27.453024],"type":"Point"}
}