{
  "type": "Feature",
  "properties": {
    "iso:country":"US",
    "sg:address":"1310 W Allamanda Blvd",
    "sg:city":"Avon Park",
    "sg:classifiers":[
        {
            "category":"Food & Beverages",
            "subcategory":"Groceries & Convenience Stores",
            "type":"Retail Goods"
        }
    ],
    "sg:phone":"+1 863 453 7427",
    "sg:postcode":"33825",
    "sg:province":"FL",
    "wof:name":"Allamanda Citgo",
    "wof:placetype":"venue"
},
  "geometry": {"coordinates":[-81.519099,27.634074],"type":"Point"}
}