{
  "type": "Feature",
  "properties": {
    "iso:country":"US",
    "sg:address":"1581 Old Dixie Hwy",
    "sg:city":"Vero Beach",
    "sg:classifiers":[
        {
            "category":"Shopping",
            "subcategory":"Hobbies, Toys, & Games",
            "type":"Retail Goods"
        }
    ],
    "sg:phone":"+1 772 299 1289",
    "sg:postcode":"32960",
    "sg:province":"FL",
    "sg:tags":[
        "product",
        "ceramic"
    ],
    "wof:name":"KLAY Gallery",
    "wof:placetype":"venue"
},
  "geometry": {"coordinates":[-80.39641899999999,27.62968],"type":"Point"}
}