{
  "type": "Feature",
  "properties": {
    "addr:full":"9174 Bonita Beach Rd SE Bonita Springs FL 34135",
    "addr:housenumber":"9174",
    "addr:postcode":"34135",
    "addr:street":"Bonita Beach Rd Se",
    "iso:country":"US",
    "sg:address":"9174 Bonita Beach Rd SE",
    "sg:city":"Bonita Springs",
    "sg:classifiers":[
        {
            "category":"Shopping",
            "subcategory":"Optical Goods",
            "type":"Retail Goods"
        }
    ],
    "sg:phone":"+1 239 949 1398",
    "sg:postcode":"34135",
    "sg:province":"FL",
    "sg:tags":[
        "sun",
        "goggles",
        "sunglasses"
    ],
    "wof:name":"Granpa's Place",
    "wof:placetype":"venue"
},
  "geometry": {"coordinates":[-81.800023,26.330659],"type":"Point"}
}