{
  "type": "Feature",
  "properties": {
    "addr:full":"7232 Manatee St Gulf Breeze FL 32566",
    "addr:housenumber":"7232",
    "addr:postcode":"32566",
    "addr:street":"Manatee St",
    "iso:country":"US",
    "sg:address":"7232 Manatee St",
    "sg:city":"Gulf Breeze",
    "sg:classifiers":[
        {
            "category":"Organizations",
            "subcategory":"Religious Organization",
            "type":"Services"
        }
    ],
    "sg:phone":"+1 850 939 3919",
    "sg:postcode":"32566",
    "sg:province":"FL",
    "wof:name":"Emerald Coast Church Inc",
    "wof:placetype":"venue"
},
  "geometry": {"coordinates":[-86.922888,30.411913],"type":"Point"}
}