{
  "type": "Feature",
  "properties": {
    "addr:full":"3820 Wimbledon Dr Lake Mary FL 32746",
    "addr:housenumber":"3820",
    "addr:postcode":"32746",
    "addr:street":"Wimbledon Dr",
    "iso:country":"US",
    "sg:address":"3820 Wimbledon Dr",
    "sg:city":"Lake Mary",
    "sg:classifiers":[
        {
            "category":"Building & Trades",
            "subcategory":"Construction",
            "type":"Services"
        }
    ],
    "sg:phone":"+1 407 833 8082",
    "sg:postcode":"32746",
    "sg:province":"FL",
    "sg:tags":[
        "contractor"
    ],
    "wof:name":"Omni Building Investments",
    "wof:placetype":"venue"
},
  "geometry": {"coordinates":[-81.386771,28.774095],"type":"Point"}
}