{
  "type": "Feature",
  "properties": {
    "addr:full":"657 W 23rd St Panama City FL 32405",
    "addr:housenumber":"657",
    "addr:postcode":"32405",
    "addr:street":"W 23Rd St",
    "iso:country":"US",
    "sg:address":"657 W 23rd St",
    "sg:city":"Panama City",
    "sg:classifiers":[
        {
            "category":"Building & Trades",
            "subcategory":"Equipment Rental",
            "type":"Services"
        }
    ],
    "sg:phone":"+1 850 763 4400",
    "sg:postcode":"32405",
    "sg:province":"FL",
    "sg:tags":[
        "appliance"
    ],
    "wof:name":"Rent-Way",
    "wof:placetype":"venue"
},
  "geometry": {"coordinates":[-85.66897899999999,30.189645],"type":"Point"}
}