{
  "type": "Feature",
  "properties": {
    "iso:country":"US",
    "sg:address":"54322 Janice Dr",
    "sg:city":"Callahan",
    "sg:classifiers":[
        {
            "category":"Place Of Worship",
            "subcategory":"Church",
            "type":"Public Place"
        },
        {
            "category":"Place Of Worship",
            "type":"Public Place"
        },
        {
            "category":"Organizations",
            "subcategory":"Religious Organization",
            "type":"Services"
        }
    ],
    "sg:phone":"+1 904 879 4156",
    "sg:postcode":"32011",
    "sg:province":"FL",
    "sg:tags":[
        "churches-baptist-general",
        "churches-baptist"
    ],
    "wof:name":"Thomas Creek Baptist Church",
    "wof:placetype":"venue"
},
  "geometry": {"coordinates":[-81.768951,30.519149],"type":"Point"}
}