{
  "type": "Feature",
  "properties": {
    "iso:country":"US",
    "sg:address":"8268 NW 14th St",
    "sg:city":"Doral",
    "sg:classifiers":[
        {
            "category":"Freight",
            "type":"Transportation"
        },
        {
            "category":"Professional",
            "type":"Services"
        }
    ],
    "sg:phone":"+1 305 599 8199",
    "sg:postcode":"33126",
    "sg:province":"FL",
    "wof:name":"C H Powell Co",
    "wof:placetype":"venue"
},
  "geometry": {"coordinates":[-80.327291,25.786192],"type":"Point"}
}