{
  "type": "Feature",
  "properties": {
    "addr:full":"3070 SW 192nd Ave Hollywood FL 33029",
    "addr:housenumber":"3070",
    "addr:postcode":"33029",
    "addr:street":"Sw 192Nd Ave",
    "iso:country":"US",
    "sg:address":"3070 SW 192nd Ave",
    "sg:city":"Hollywood",
    "sg:classifiers":[
        {
            "category":"Education",
            "subcategory":"Vocational School",
            "type":"Public Place"
        }
    ],
    "sg:phone":"+1 954 442 0773",
    "sg:postcode":"33029",
    "sg:province":"FL",
    "sg:tags":[
        "processing",
        "datum"
    ],
    "wof:name":"Learnemed Inc",
    "wof:placetype":"venue"
},
  "geometry": {"coordinates":[-80.40307900000001,25.980529],"type":"Point"}
}