{
  "type": "Feature",
  "properties": {
    "addr:full":"2217 S Bignonia St Melbourne FL 32901",
    "addr:housenumber":"2217",
    "addr:postcode":"32901",
    "addr:street":"S Bignonia St",
    "iso:country":"US",
    "sg:address":"2217 S Bignonia St",
    "sg:city":"Melbourne",
    "sg:classifiers":[
        {
            "category":"Building & Trades",
            "subcategory":"Cleaning & Sanitation",
            "type":"Services"
        }
    ],
    "sg:phone":"+1 321 726 6499",
    "sg:postcode":"32901",
    "sg:province":"FL",
    "sg:tags":[
        "janitor"
    ],
    "wof:name":"Personal Touch Cleaning Svc",
    "wof:placetype":"venue"
},
  "geometry": {"coordinates":[-80.618357,28.073201],"type":"Point"}
}