{
  "type": "Feature",
  "properties": {
    "iso:country":"US",
    "sg:address":"230 E Old Hillsborough Ave",
    "sg:city":"Seffner",
    "sg:classifiers":[
        {
            "category":"Professional",
            "subcategory":"Business Services",
            "type":"Services"
        }
    ],
    "sg:phone":"+1 813 654 2958",
    "sg:postcode":"33584",
    "sg:province":"FL",
    "wof:name":"Consolidated Comm Svcs",
    "wof:placetype":"venue"
},
  "geometry": {"coordinates":[-82.276819,27.996208],"type":"Point"}
}