{
  "type": "Feature",
  "properties": {
    "iso:country":"US",
    "sg:address":"12693 Tamiami Trl",
    "sg:city":"Naples",
    "sg:classifiers":[
        {
            "category":"Arts & Performance",
            "subcategory":"Theater",
            "type":"Entertainment"
        }
    ],
    "sg:phone":"+1 239 821 1024",
    "sg:postcode":"34113",
    "sg:province":"FL",
    "sg:tags":[
        "entertainer",
        "family"
    ],
    "wof:name":"Brothers",
    "wof:placetype":"venue"
},
  "geometry": {"coordinates":[-81.70072500000001,26.064355],"type":"Point"}
}