{
  "type": "Feature",
  "properties": {
    "addr:full":"2690 SW 3rd St Miami FL 33135",
    "addr:housenumber":"2690",
    "addr:postcode":"33135",
    "addr:street":"Sw 3Rd St",
    "iso:country":"US",
    "sg:address":"2690 SW 3rd St",
    "sg:city":"Miami",
    "sg:classifiers":[
        {
            "category":"Wholesale",
            "subcategory":"Office Equipment",
            "type":"Manufacturing & Wholesale Goods"
        },
        {
            "category":"Shopping",
            "subcategory":"Stationery & Office Supplies",
            "type":"Retail Goods"
        },
        {
            "category":"Shopping",
            "subcategory":"Computers & Home Electronics",
            "type":"Retail Goods"
        },
        {
            "category":"Professional",
            "subcategory":"Printing & Photocopies",
            "type":"Services"
        },
        {
            "category":"Wholesale",
            "subcategory":"Computers",
            "type":"Manufacturing & Wholesale Goods"
        }
    ],
    "sg:phone":"+1 305 860 9487",
    "sg:postcode":"33135",
    "sg:province":"FL",
    "sg:tags":[
        "register",
        "autographic",
        "duplicating",
        "copying",
        "typewriter",
        "furniture"
    ],
    "sg:website":"http://www.officedepot.com",
    "wof:name":"Office Depot",
    "wof:placetype":"venue"
},
  "geometry": {"coordinates":[-80.238843,25.769412],"type":"Point"}
}