{
  "type": "Feature",
  "properties": {
    "addr:full":"1003 Edgewood Ave W Jacksonville FL 32208",
    "addr:housenumber":"1003",
    "addr:postcode":"32208",
    "addr:street":"Edgewood Ave W",
    "iso:country":"US",
    "sg:address":"1003 Edgewood Ave W",
    "sg:city":"Jacksonville",
    "sg:classifiers":[
        {
            "category":"Real Estate",
            "subcategory":"Real Estate Agent",
            "type":"Services"
        }
    ],
    "sg:phone":"+1 904 766 1522",
    "sg:postcode":"32208",
    "sg:province":"FL",
    "wof:name":"Chris Campbell Realty",
    "wof:placetype":"venue"
},
  "geometry": {"coordinates":[-81.67495099999999,30.392391],"type":"Point"}
}