{
  "type": "Feature",
  "properties": {
    "iso:country":"US",
    "sg:address":"7329 SW 23rd St",
    "sg:city":"Miami",
    "sg:classifiers":[
        {
            "category":"Autos & Motor Vehicles",
            "subcategory":"Auto Supplies",
            "type":"Retail Goods"
        }
    ],
    "sg:phone":"+1 305 267 9338",
    "sg:postcode":"33155",
    "sg:province":"FL",
    "wof:name":"Freddys Parts Locator",
    "wof:placetype":"venue"
},
  "geometry": {"coordinates":[-80.31529500000001,25.749267],"type":"Point"}
}