{
  "type": "Feature",
  "properties": {
    "iso:country":"US",
    "sg:address":"4219 Donnington Dr",
    "sg:city":"Parrish",
    "sg:classifiers":[
        {
            "category":"Building & Trades",
            "subcategory":"Construction",
            "type":"Services"
        }
    ],
    "sg:phone":"+1 941 776 0757",
    "sg:postcode":"34219",
    "sg:province":"FL",
    "sg:tags":[
        "hanging",
        "contractor"
    ],
    "wof:name":"Masterspray of Florida",
    "wof:placetype":"venue"
},
  "geometry": {"coordinates":[-82.427976,27.552244],"type":"Point"}
}