{
  "type": "Feature",
  "properties": {
    "iso:country":"US",
    "sg:address":"242 Ventura Rd",
    "sg:city":"Saint Augustine",
    "sg:classifiers":[
        {
            "category":"Communications",
            "type":"Services"
        }
    ],
    "sg:phone":"+1 904 347 3341",
    "sg:postcode":"32080",
    "sg:province":"FL",
    "sg:tags":[
        "communication"
    ],
    "wof:name":"B G Communications",
    "wof:placetype":"venue"
},
  "geometry": {"coordinates":[-81.260913,29.782824],"type":"Point"}
}