{
  "type": "Feature",
  "properties": {
    "iso:country":"US",
    "sg:address":"595 E Sample Rd",
    "sg:city":"Pompano Beach",
    "sg:classifiers":[
        {
            "category":"Shopping",
            "type":"Retail Goods"
        }
    ],
    "sg:phone":"+1 954 785 4894",
    "sg:postcode":"33064",
    "sg:province":"FL",
    "sg:tags":[
        "cosmetic",
        "perfume"
    ],
    "wof:name":"Wawa Beauty Supply",
    "wof:placetype":"venue"
},
  "geometry": {"coordinates":[-80.114802,26.275307],"type":"Point"}
}