{
  "type": "Feature",
  "properties": {
    "iso:country":"US",
    "sg:address":"5310 Deeson Rd",
    "sg:city":"Lakeland",
    "sg:classifiers":[
        {
            "category":"Building & Trades",
            "subcategory":"Construction",
            "type":"Services"
        }
    ],
    "sg:phone":"+1 863 859 4443",
    "sg:postcode":"33810",
    "sg:province":"FL",
    "sg:tags":[
        "carpentry",
        "contractor"
    ],
    "wof:name":"Thompsons Carpentry",
    "wof:placetype":"venue"
},
  "geometry": {"coordinates":[-82.052483,28.113205],"type":"Point"}
}