{
  "type": "Feature",
  "properties": {
    "iso:country":"US",
    "sg:address":"1250 S State Rd 15A",
    "sg:city":"Deland",
    "sg:classifiers":[
        {
            "category":"Health Services",
            "subcategory":"Nursing And Care Facility",
            "type":"Services"
        }
    ],
    "sg:phone":"+1 386 822 4848",
    "sg:postcode":"32720",
    "sg:province":"FL",
    "sg:tags":[
        "hospice"
    ],
    "wof:name":"Hospice Of Volusia Flagler",
    "wof:placetype":"venue"
},
  "geometry": {"coordinates":[-81.318725,29.007109],"type":"Point"}
}