{
  "type": "Feature",
  "properties": {
    "addr:full":"6400 S Dixie Hwy West Palm Beach FL 33405",
    "addr:housenumber":"6400",
    "addr:postcode":"33405",
    "addr:street":"S Dixie Hwy",
    "iso:country":"US",
    "sg:address":"6400 S Dixie Hwy",
    "sg:city":"West Palm Beach",
    "sg:classifiers":[
        {
            "category":"Food & Beverages",
            "subcategory":"Groceries & Convenience Stores",
            "type":"Retail Goods"
        }
    ],
    "sg:phone":"+1 561 585 7720",
    "sg:postcode":"33405",
    "sg:province":"FL",
    "wof:name":"Hess Gas Station",
    "wof:placetype":"venue"
},
  "geometry": {"coordinates":[-80.05593399999999,26.657273],"type":"Point"}
}