{
  "type": "Feature",
  "properties": {
    "iso:country":"US",
    "sg:address":"171 2nd Ave N",
    "sg:city":"Saint Petersburg",
    "sg:classifiers":[
        {
            "category":"Restaurant",
            "type":"Food & Drink"
        }
    ],
    "sg:menulink":"http://www.allmenus.com/fl/st-petersburg/158108-wet-willies/menu/",
    "sg:phone":"+1 727 822 5650",
    "sg:postcode":"33701",
    "sg:province":"FL",
    "sg:tags":[
        "belgian"
    ],
    "wof:name":"Wet Willies",
    "wof:placetype":"venue"
},
  "geometry": {"coordinates":[-82.635091,27.77348],"type":"Point"}
}