{
  "type": "Feature",
  "properties": {
    "iso:country":"US",
    "sg:address":"370 NW 36th Ct",
    "sg:city":"Boca Raton",
    "sg:classifiers":[
        {
            "category":"Building & Trades",
            "subcategory":"Construction",
            "type":"Services"
        }
    ],
    "sg:phone":"+1 561 391 1818",
    "sg:postcode":"33431",
    "sg:province":"FL",
    "sg:tags":[
        "hanging",
        "contractor"
    ],
    "wof:name":"Beverew Painting",
    "wof:placetype":"venue"
},
  "geometry": {"coordinates":[-80.08835500000001,26.383171],"type":"Point"}
}