{
  "type": "Feature",
  "properties": {
    "iso:country":"US",
    "sg:address":"18801 Biscayne Blvd",
    "sg:city":"Aventura",
    "sg:classifiers":[
        {
            "category":"Shopping",
            "subcategory":"Shoes",
            "type":"Retail Goods"
        }
    ],
    "sg:phone":"+1 305 792 7440",
    "sg:postcode":"33180",
    "sg:province":"FL",
    "sg:tags":[
        "store"
    ],
    "wof:name":"Rochester Big & Tall Clothing",
    "wof:placetype":"venue"
},
  "geometry": {"coordinates":[-80.146698,25.949699],"type":"Point"}
}