{
  "type": "Feature",
  "properties": {
    "iso:country":"US",
    "sg:address":"1000 Brickell Ave Ste 660",
    "sg:city":"Miami",
    "sg:classifiers":[
        {
            "category":"Education",
            "subcategory":"Vocational School",
            "type":"Public Place"
        }
    ],
    "sg:phone":"+1 305 376 8850",
    "sg:postcode":"33131",
    "sg:province":"FL",
    "sg:tags":[
        "business"
    ],
    "wof:name":"Dermalogica",
    "wof:placetype":"venue"
},
  "geometry": {"coordinates":[-80.191422,25.763741],"type":"Point"}
}