{
  "type": "Feature",
  "properties": {
    "iso:country":"US",
    "sg:address":"1193 71st St",
    "sg:city":"Miami Beach",
    "sg:classifiers":[
        {
            "category":"Retail",
            "subcategory":"Repair Shop",
            "type":"Services"
        }
    ],
    "sg:phone":"+1 305 531 2988",
    "sg:postcode":"33141",
    "sg:province":"FL",
    "sg:tags":[
        "upholsterer"
    ],
    "wof:name":"Idea's Upholstery",
    "wof:placetype":"venue"
},
  "geometry": {"coordinates":[-80.129797,25.854918],"type":"Point"}
}