{
  "type": "Feature",
  "properties": {
    "addr:full":"201 E Government St Pensacola FL 32502",
    "addr:housenumber":"201",
    "addr:postcode":"32502",
    "addr:street":"E Government St",
    "iso:country":"US",
    "sg:address":"201 E Government St",
    "sg:city":"Pensacola",
    "sg:classifiers":[
        {
            "category":"Communications",
            "subcategory":"Newspaper",
            "type":"Services"
        }
    ],
    "sg:phone":"+1 850 433 6264",
    "sg:postcode":"32502",
    "sg:province":"FL",
    "wof:name":"W Timothy Weekly",
    "wof:placetype":"venue"
},
  "geometry": {"coordinates":[-87.21196,30.40971],"type":"Point"}
}