{
  "type": "Feature",
  "properties": {
    "addr:full":"1 SE 4th Ave Delray Beach FL 33483",
    "addr:housenumber":"1",
    "addr:postcode":"33483",
    "addr:street":"Se 4Th Ave",
    "iso:country":"US",
    "sg:address":"1 SE 4th Ave",
    "sg:city":"Delray Beach",
    "sg:classifiers":[
        {
            "category":"Health Services",
            "subcategory":"Medical Lab",
            "type":"Services"
        }
    ],
    "sg:phone":"+1 561 278 1447",
    "sg:postcode":"33483",
    "sg:province":"FL",
    "sg:tags":[
        "laboratory",
        "dental"
    ],
    "wof:name":"Atkinson Dental Laboratory",
    "wof:placetype":"venue"
},
  "geometry": {"coordinates":[-80.06902100000001,26.459818],"type":"Point"}
}