{
  "type": "Feature",
  "properties": {
    "addr:full":"1404 E Cape Coral Pkwy Cape Coral FL 33904",
    "addr:housenumber":"1404",
    "addr:postcode":"33904",
    "addr:street":"E Cape Coral Pkwy",
    "iso:country":"US",
    "sg:address":"1404 E Cape Coral Pkwy",
    "sg:city":"Cape Coral",
    "sg:classifiers":[
        {
            "category":"Manufacturing",
            "subcategory":"Printing",
            "type":"Manufacturing & Wholesale Goods"
        }
    ],
    "sg:phone":"+1 239 542 3632",
    "sg:postcode":"33904",
    "sg:province":"FL",
    "sg:tags":[
        "printer"
    ],
    "wof:name":"Larson Printing",
    "wof:placetype":"venue"
},
  "geometry": {"coordinates":[-81.948539,26.562487],"type":"Point"}
}