{
  "type": "Feature",
  "properties": {
    "addr:full":"1019 Dusseldorf Ave NW Palm Bay FL 32907",
    "addr:housenumber":"1019",
    "addr:postcode":"32907",
    "addr:street":"Dusseldorf Ave Nw",
    "iso:country":"US",
    "sg:address":"1019 Dusseldorf Ave NW",
    "sg:city":"Palm Bay",
    "sg:classifiers":[
        {
            "category":"Building & Trades",
            "subcategory":"Construction",
            "type":"Services"
        }
    ],
    "sg:phone":"+1 321 733 3758",
    "sg:postcode":"32907",
    "sg:province":"FL",
    "sg:tags":[
        "contractor"
    ],
    "wof:name":"Creative Tile & Remodeling",
    "wof:placetype":"venue"
},
  "geometry": {"coordinates":[-80.693082,28.023636],"type":"Point"}
}