{
  "type": "Feature",
  "properties": {
    "iso:country":"US",
    "sg:address":"2390 College Ave",
    "sg:city":"Davie",
    "sg:classifiers":[
        {
            "category":"Manufacturing",
            "subcategory":"Glass & Minerals",
            "type":"Manufacturing & Wholesale Goods"
        }
    ],
    "sg:phone":"+1 954 473 2444",
    "sg:postcode":"33317",
    "sg:province":"FL",
    "sg:tags":[
        "concrete"
    ],
    "wof:name":"Aurea Floor Inc",
    "wof:placetype":"venue"
},
  "geometry": {"coordinates":[-80.233941,26.094591],"type":"Point"}
}