{
  "type": "Feature",
  "properties": {
    "iso:country":"US",
    "sg:address":"408 Summit Ridge Pl",
    "sg:city":"Longwood",
    "sg:classifiers":[
        {
            "category":"Building & Trades",
            "subcategory":"Construction",
            "type":"Services"
        }
    ],
    "sg:phone":"+1 407 774 7977",
    "sg:postcode":"32779",
    "sg:province":"FL",
    "sg:tags":[
        "concrete",
        "contractor"
    ],
    "wof:name":"Paver Performance Inc",
    "wof:placetype":"venue"
},
  "geometry": {"coordinates":[-81.40786199999999,28.698332],"type":"Point"}
}