{
  "type": "Feature",
  "properties": {
    "iso:country":"US",
    "sg:address":"2130 Bispham Rd",
    "sg:city":"Sarasota",
    "sg:classifiers":[
        {
            "category":"Professional",
            "subcategory":"Computer Services",
            "type":"Services"
        }
    ],
    "sg:phone":"+1 941 924 6565",
    "sg:postcode":"34231",
    "sg:province":"FL",
    "sg:tags":[
        "related"
    ],
    "wof:name":"Watson & Walker Inc",
    "wof:placetype":"venue"
},
  "geometry": {"coordinates":[-82.516488,27.254536],"type":"Point"}
}