{
  "type": "Feature",
  "properties": {
    "iso:country":"US",
    "sg:address":"5931 Hammock Rd",
    "sg:city":"Sebring",
    "sg:classifiers":[
        {
            "category":"Manufacturing",
            "subcategory":"Lumber",
            "type":"Manufacturing & Wholesale Goods"
        }
    ],
    "sg:phone":"+1 863 386 6094",
    "sg:postcode":"33872",
    "sg:province":"FL",
    "sg:tags":[
        "forestry",
        "management"
    ],
    "wof:name":"Highlands Hammock State Park",
    "wof:placetype":"venue"
},
  "geometry": {"coordinates":[-81.551844,27.475766],"type":"Point"}
}