{
  "type": "Feature",
  "properties": {
    "addr:full":"3344 Tucker Ave St Cloud FL 34772",
    "addr:housenumber":"3344",
    "addr:postcode":"34772",
    "addr:street":"Tucker Ave",
    "iso:country":"US",
    "sg:address":"3344 Tucker Ave",
    "sg:city":"St Cloud",
    "sg:classifiers":[
        {
            "category":"Professional",
            "subcategory":"Advertising",
            "type":"Services"
        }
    ],
    "sg:phone":"+1 407 891 0642",
    "sg:postcode":"34772",
    "sg:province":"FL",
    "sg:tags":[
        "mailing",
        "shipping"
    ],
    "wof:name":"Michael Horn Enterprises",
    "wof:placetype":"venue"
},
  "geometry": {"coordinates":[-81.247838,28.196342],"type":"Point"}
}