{
  "type": "Feature",
  "properties": {
    "iso:country":"US",
    "sg:address":"2600 Western Way",
    "sg:city":"Leesburg",
    "sg:classifiers":[
        {
            "category":"Retail",
            "subcategory":"Repair Shop",
            "type":"Services"
        }
    ],
    "sg:phone":"+1 352 787 7704",
    "sg:postcode":"34748",
    "sg:province":"FL",
    "sg:tags":[
        "hardware"
    ],
    "wof:name":"Action Locksmith",
    "wof:placetype":"venue"
},
  "geometry": {"coordinates":[-81.90818299999999,28.810819],"type":"Point"}
}