{
  "type": "Feature",
  "properties": {
    "iso:country":"US",
    "sg:address":"6415 Blanding Blvd",
    "sg:city":"Jacksonville",
    "sg:classifiers":[
        {
            "category":"Shopping",
            "subcategory":"Hobbies, Toys, & Games",
            "type":"Retail Goods"
        }
    ],
    "sg:phone":"+1 904 777 4548",
    "sg:postcode":"32244",
    "sg:province":"FL",
    "sg:tags":[
        "supply"
    ],
    "wof:name":"Game Room",
    "wof:placetype":"venue"
},
  "geometry": {"coordinates":[-81.73857700000001,30.230337],"type":"Point"}
}