{
  "type": "Feature",
  "properties": {
    "iso:country":"US",
    "sg:address":"10317 W Yulee Dr",
    "sg:city":"Homosassa",
    "sg:classifiers":[
        {
            "category":"Restaurant",
            "type":"Food & Drink"
        }
    ],
    "sg:phone":"+1 352 621 5500",
    "sg:postcode":"34448",
    "sg:province":"FL",
    "wof:name":"Taz Dogs N Scoops",
    "wof:placetype":"venue"
},
  "geometry": {"coordinates":[-82.605249,28.789577],"type":"Point"}
}