{
  "type": "Feature",
  "properties": {
    "addr:full":"1300 Washington Dr Englewood FL 34224",
    "addr:housenumber":"1300",
    "addr:postcode":"34224",
    "addr:street":"Washington Dr",
    "iso:country":"US",
    "sg:address":"1300 Washington Dr",
    "sg:city":"Englewood",
    "sg:classifiers":[
        {
            "category":"Building & Trades",
            "subcategory":"Landscaping Services",
            "type":"Services"
        }
    ],
    "sg:phone":"+1 941 473 3325",
    "sg:postcode":"34224",
    "sg:province":"FL",
    "wof:name":"Terry Jarest Yard Service",
    "wof:placetype":"venue"
},
  "geometry": {"coordinates":[-82.32240299999999,26.934586],"type":"Point"}
}