{
  "type": "Feature",
  "properties": {
    "addr:full":"6932 22nd Ave N Saint Petersburg FL 33710",
    "addr:housenumber":"6932",
    "addr:postcode":"33710",
    "addr:street":"22Nd Ave N",
    "iso:country":"US",
    "sg:address":"6932 22nd Ave N",
    "sg:city":"Saint Petersburg",
    "sg:classifiers":[
        {
            "category":"Shopping",
            "subcategory":"Shoes",
            "type":"Retail Goods"
        }
    ],
    "sg:phone":"+1 727 345 7587",
    "sg:postcode":"33710",
    "sg:province":"FL",
    "wof:name":"Birkenstock Footwear",
    "wof:placetype":"venue"
},
  "geometry": {"coordinates":[-82.735663,27.791723],"type":"Point"}
}