{
  "type": "Feature",
  "properties": {
    "iso:country":"US",
    "sg:address":"615 Whitney Ave",
    "sg:city":"Lantana",
    "sg:classifiers":[
        {
            "category":"Home & Garden",
            "subcategory":"Building Materials",
            "type":"Retail Goods"
        }
    ],
    "sg:phone":"+1 561 582 2959",
    "sg:postcode":"33462",
    "sg:province":"FL",
    "sg:tags":[
        "screen",
        "window"
    ],
    "wof:name":"Garcia Screen",
    "wof:placetype":"venue"
},
  "geometry": {"coordinates":[-80.05621499999999,26.591847],"type":"Point"}
}