{
  "type": "Feature",
  "properties": {
    "iso:country":"US",
    "sg:address":"110 Myrtle Ln",
    "sg:city":"Plant City",
    "sg:classifiers":[
        {
            "category":"Wholesale",
            "subcategory":"Chemicals & Plastics",
            "type":"Manufacturing & Wholesale Goods"
        }
    ],
    "sg:phone":"+1 813 752 5079",
    "sg:postcode":"33565",
    "sg:province":"FL",
    "sg:tags":[
        "merchandise"
    ],
    "wof:name":"Klean Chemical Industries",
    "wof:placetype":"venue"
},
  "geometry": {"coordinates":[-82.05919400000001,28.04299],"type":"Point"}
}