{
  "type": "Feature",
  "properties": {
    "iso:country":"US",
    "sg:address":"15868 SW 74th Ln",
    "sg:city":"Miami",
    "sg:classifiers":[
        {
            "category":"Government",
            "subcategory":"Fire Station",
            "type":"Public Place"
        },
        {
            "category":"Wholesale",
            "subcategory":"Machinery & Supplies",
            "type":"Manufacturing & Wholesale Goods"
        }
    ],
    "sg:phone":"+1 305 969 0629",
    "sg:postcode":"33193",
    "sg:province":"FL",
    "sg:tags":[
        "equipment",
        "protection",
        "department"
    ],
    "wof:name":"Firemax Inc",
    "wof:placetype":"venue"
},
  "geometry": {"coordinates":[-80.44993599999999,25.696345],"type":"Point"}
}