{
  "type": "Feature",
  "properties": {
    "addr:full":"5940 W 16th Ave Hialeah FL 33012",
    "addr:housenumber":"5940",
    "addr:postcode":"33012",
    "addr:street":"W 16Th Ave",
    "iso:country":"US",
    "sg:address":"5940 W 16th Ave",
    "sg:city":"Hialeah",
    "sg:classifiers":[
        {
            "category":"Retail",
            "subcategory":"Portrait Studio",
            "type":"Services"
        }
    ],
    "sg:phone":"+1 305 819 9328",
    "sg:postcode":"33012",
    "sg:province":"FL",
    "sg:tags":[
        "photographer"
    ],
    "wof:name":"Forever Images Corp",
    "wof:placetype":"venue"
},
  "geometry": {"coordinates":[-80.31529500000001,25.875732],"type":"Point"}
}