{
  "type": "Feature",
  "properties": {
    "iso:country":"US",
    "sg:address":"4102 8th Ave S",
    "sg:city":"St Petersburg",
    "sg:classifiers":[
        {
            "category":"Building & Trades",
            "subcategory":"Construction",
            "type":"Services"
        }
    ],
    "sg:phone":"+1 727 328 9921",
    "sg:postcode":"33711",
    "sg:province":"FL",
    "sg:tags":[
        "designer"
    ],
    "wof:name":"Airline Painting Svc",
    "wof:placetype":"venue"
},
  "geometry": {"coordinates":[-82.68816200000001,27.76168],"type":"Point"}
}