{
  "type": "Feature",
  "properties": {
    "iso:country":"US",
    "sg:address":"1181 NW 5th Ave",
    "sg:city":"Pompano Beach",
    "sg:classifiers":[
        {
            "category":"Retail",
            "subcategory":"Auto Repair",
            "type":"Services"
        }
    ],
    "sg:phone":"+1 954 234 4098",
    "sg:postcode":"33060",
    "sg:province":"FL",
    "sg:tags":[
        "wrecker"
    ],
    "wof:name":"Carmel Towing Inc",
    "wof:placetype":"venue"
},
  "geometry": {"coordinates":[-80.129818,26.24055],"type":"Point"}
}