{
  "type": "Feature",
  "properties": {
    "iso:country":"US",
    "sg:address":"7901 4th St N",
    "sg:city":"St Petersburg",
    "sg:classifiers":[
        {
            "category":"Banks & Credit Unions",
            "subcategory":"Bank",
            "type":"Services"
        }
    ],
    "sg:phone":"+1 727 570 2222",
    "sg:postcode":"33702",
    "sg:province":"FL",
    "sg:tags":[
        "mortgage",
        "loan",
        "real estate",
        "brokerage"
    ],
    "wof:name":"K P Mortgage Inc",
    "wof:placetype":"venue"
},
  "geometry": {"coordinates":[-82.638735,27.844745],"type":"Point"}
}