{
  "type": "Feature",
  "properties": {
    "iso:country":"US",
    "sg:address":"501 N Grandview Ave",
    "sg:city":"Daytona Beach",
    "sg:classifiers":[
        {
            "category":"Organizations",
            "subcategory":"Non-profit Organization",
            "type":"Services"
        }
    ],
    "sg:phone":"+1 386 226 8215",
    "sg:postcode":"32118",
    "sg:province":"FL",
    "sg:tags":[
        "fund",
        "counselor",
        "raising"
    ],
    "sg:website":"www.prospectinfo.com",
    "wof:name":"Kintera",
    "wof:placetype":"venue"
},
  "geometry": {"coordinates":[-81.013493,29.23519],"type":"Point"}
}