{
  "type": "Feature",
  "properties": {
    "iso:country":"US",
    "sg:address":"2720 S Dixie Hwy Ste G",
    "sg:city":"Miami",
    "sg:classifiers":[
        {
            "category":"Retail",
            "subcategory":"Laundry & Dry Cleaning",
            "type":"Services"
        }
    ],
    "sg:phone":"+1 305 461 3366",
    "sg:postcode":"33133",
    "sg:province":"FL",
    "sg:website":"www.dryclean-usa.com",
    "wof:name":"Dryclean-USA",
    "wof:placetype":"venue"
},
  "geometry": {"coordinates":[-80.23840300000001,25.7397],"type":"Point"}
}