{
  "type": "Feature",
  "properties": {
    "addr:full":"9500 Satellite Blvd # 180 Orlando FL 32837",
    "addr:housenumber":"9500",
    "addr:postcode":"32837",
    "addr:street":"Satellite Blvd # 180",
    "iso:country":"US",
    "sg:address":"9500 Satellite Blvd # 180",
    "sg:city":"Orlando",
    "sg:classifiers":[
        {
            "category":"Real Estate",
            "subcategory":"Developer",
            "type":"Services"
        }
    ],
    "sg:phone":"+1 407 765 7091",
    "sg:postcode":"32837",
    "sg:province":"FL",
    "wof:name":"Rod Construction & Site Development",
    "wof:placetype":"venue"
},
  "geometry": {"coordinates":[-81.40136699999999,28.4214],"type":"Point"}
}