{
  "type": "Feature",
  "properties": {
    "iso:country":"US",
    "sg:address":"2900 W 12th Ave Ste 7A",
    "sg:city":"Hialeah",
    "sg:classifiers":[
        {
            "category":"Personal",
            "subcategory":"Nail Salon",
            "type":"Services"
        }
    ],
    "sg:phone":"+1 305 889 0199",
    "sg:postcode":"33012",
    "sg:province":"FL",
    "wof:name":"Altagracia Beauty Salon Inc",
    "wof:placetype":"venue"
},
  "geometry": {"coordinates":[-80.30645199999999,25.847987],"type":"Point"}
}