{
  "type": "Feature",
  "properties": {
    "iso:country":"US",
    "sg:address":"510 Shadow Wood Ln",
    "sg:city":"Pompano Beach",
    "sg:classifiers":[
        {
            "category":"Home & Garden",
            "subcategory":"Home Furnishings",
            "type":"Retail Goods"
        }
    ],
    "sg:phone":"+1 954 755 2419",
    "sg:postcode":"33071",
    "sg:province":"FL",
    "sg:tags":[
        "blind"
    ],
    "wof:name":"Barrys Blinds",
    "wof:placetype":"venue"
},
  "geometry": {"coordinates":[-80.254195,26.237053],"type":"Point"}
}