{
  "type": "Feature",
  "properties": {
    "addr:full":"1640 SW 85th Ave Miami FL 33155",
    "addr:housenumber":"1640",
    "addr:postcode":"33155",
    "addr:street":"Sw 85Th Ave",
    "iso:country":"US",
    "sg:address":"1640 SW 85th Ave",
    "sg:city":"Miami",
    "sg:classifiers":[
        {
            "category":"Building & Trades",
            "subcategory":"Construction",
            "type":"Services"
        }
    ],
    "sg:phone":"+1 305 261 8635",
    "sg:postcode":"33155",
    "sg:province":"FL",
    "sg:tags":[
        "block",
        "setter"
    ],
    "wof:name":"Pavi Block Inc",
    "wof:placetype":"venue"
},
  "geometry": {"coordinates":[-80.33325000000001,25.751864],"type":"Point"}
}