{
  "type": "Feature",
  "properties": {
    "iso:country":"US",
    "sg:address":"2203 N Lois Ave",
    "sg:city":"Tampa",
    "sg:classifiers":[
        {
            "category":"Professional",
            "subcategory":"Management & Consulting",
            "type":"Services"
        }
    ],
    "sg:phone":"+1 813 874 0330",
    "sg:postcode":"33607",
    "sg:province":"FL",
    "sg:tags":[
        "export"
    ],
    "wof:name":"Wesfort Corp",
    "wof:placetype":"venue"
},
  "geometry": {"coordinates":[-82.513699,27.961073],"type":"Point"}
}