{
  "type": "Feature",
  "properties": {
    "addr:full":"15255 SW 45th Ter Miami FL 33185",
    "addr:housenumber":"15255",
    "addr:postcode":"33185",
    "addr:street":"Sw 45Th Ter",
    "iso:country":"US",
    "sg:address":"15255 SW 45th Ter",
    "sg:city":"Miami",
    "sg:classifiers":[
        {
            "category":"Insurance",
            "subcategory":"Hazard Insurance",
            "type":"Services"
        }
    ],
    "sg:phone":"+1 305 541 6223",
    "sg:postcode":"33185",
    "sg:province":"FL",
    "sg:tags":[
        "bond"
    ],
    "wof:name":"JMC Bail Bonds",
    "wof:placetype":"venue"
},
  "geometry": {"coordinates":[-80.440686,25.722447],"type":"Point"}
}