{
  "type": "Feature",
  "properties": {
    "addr:full":"6021 Foster St Jupiter FL 33458",
    "addr:housenumber":"6021",
    "addr:postcode":"33458",
    "addr:street":"Foster St",
    "iso:country":"US",
    "sg:address":"6021 Foster St",
    "sg:city":"Jupiter",
    "sg:classifiers":[
        {
            "category":"Professional",
            "type":"Services"
        }
    ],
    "sg:phone":"+1 561 748 4448",
    "sg:postcode":"33458",
    "sg:province":"FL",
    "sg:tags":[
        "establishment"
    ],
    "wof:name":"Pharmex International",
    "wof:placetype":"venue"
},
  "geometry": {"coordinates":[-80.127903,26.903186],"type":"Point"}
}