{
  "type": "Feature",
  "properties": {
    "iso:country":"US",
    "sg:address":"123 Racetrack Rd NE",
    "sg:city":"Fort Walton Bch",
    "sg:classifiers":[
        {
            "category":"Retail",
            "subcategory":"Laundry & Dry Cleaning",
            "type":"Services"
        }
    ],
    "sg:phone":"+1 850 650 7788",
    "sg:postcode":"32547",
    "sg:province":"FL",
    "sg:tags":[
        "cleaners",
        "rug",
        "carpet"
    ],
    "wof:name":"Cehm-Dry Of The Emerald Coast",
    "wof:placetype":"venue"
},
  "geometry": {"coordinates":[-86.608102,30.446452],"type":"Point"}
}