{
  "type": "Feature",
  "properties": {
    "iso:country":"US",
    "sg:address":"801 12th Ave S",
    "sg:city":"Naples",
    "sg:classifiers":[
        {
            "category":"Autos & Motor Vehicles",
            "subcategory":"Boat Sales",
            "type":"Retail Goods"
        }
    ],
    "sg:phone":"+1 239 403 2628",
    "sg:postcode":"34102",
    "sg:province":"FL",
    "wof:name":"Olde Naples Boat Company",
    "wof:placetype":"venue"
},
  "geometry": {"coordinates":[-81.793835,26.132769],"type":"Point"}
}