{
  "type": "Feature",
  "properties": {
    "iso:country":"US",
    "sg:address":"2359 Periwinkle Way",
    "sg:city":"Sanibel",
    "sg:classifiers":[
        {
            "category":"Retail",
            "subcategory":"Repair Shop",
            "type":"Services"
        }
    ],
    "sg:phone":"+1 239 472 1965",
    "sg:postcode":"33957",
    "sg:province":"FL",
    "sg:tags":[
        "screen"
    ],
    "wof:name":"Eclipse Restoration",
    "wof:placetype":"venue"
},
  "geometry": {"coordinates":[-82.07265099999999,26.437547],"type":"Point"}
}