{
  "type": "Feature",
  "properties": {
    "iso:country":"US",
    "sg:address":"474 Linda Ln",
    "sg:city":"Melbourne",
    "sg:classifiers":[
        {
            "category":"Building & Trades",
            "subcategory":"Construction",
            "type":"Services"
        }
    ],
    "sg:phone":"+1 321 752 4681",
    "sg:postcode":"32935",
    "sg:province":"FL",
    "sg:tags":[
        "contractor"
    ],
    "wof:name":"S & P Stucco Inc",
    "wof:placetype":"venue"
},
  "geometry": {"coordinates":[-80.65810500000001,28.137304],"type":"Point"}
}