{
  "type": "Feature",
  "properties": {
    "iso:country":"US",
    "sg:address":"119 E Broadway Ave",
    "sg:city":"Kissimmee",
    "sg:classifiers":[
        {
            "category":"Personal",
            "subcategory":"Barber",
            "type":"Services"
        }
    ],
    "sg:phone":"+1 407 847 7138",
    "sg:postcode":"34741",
    "sg:province":"FL",
    "wof:name":"Broadway Barber Shop",
    "wof:placetype":"venue"
},
  "geometry": {"coordinates":[-81.40649500000001,28.293258],"type":"Point"}
}