{
  "type": "Feature",
  "properties": {
    "addr:full":"1226 Hampstead Ln Ormond Beach FL 32174",
    "addr:housenumber":"1226",
    "addr:postcode":"32174",
    "addr:street":"Hampstead Ln",
    "iso:country":"US",
    "sg:address":"1226 Hampstead Ln",
    "sg:city":"Ormond Beach",
    "sg:classifiers":[
        {
            "category":"Real Estate",
            "subcategory":"Architect",
            "type":"Services"
        }
    ],
    "sg:phone":"+1 386 671 7760",
    "sg:postcode":"32174",
    "sg:province":"FL",
    "wof:name":"J H P",
    "wof:placetype":"venue"
},
  "geometry": {"coordinates":[-81.14685299999999,29.356943],"type":"Point"}
}