{
  "type": "Feature",
  "properties": {
    "addr:full":"682 Long Lake Dr Oviedo FL 32765",
    "addr:housenumber":"682",
    "addr:postcode":"32765",
    "addr:street":"Long Lake Dr",
    "iso:country":"US",
    "sg:address":"682 Long Lake Dr",
    "sg:city":"Oviedo",
    "sg:classifiers":[
        {
            "category":"Banks & Credit Unions",
            "subcategory":"Financial Services",
            "type":"Services"
        }
    ],
    "sg:phone":"+1 407 977 7737",
    "sg:postcode":"32765",
    "sg:province":"FL",
    "wof:name":"Irwin Business Finance",
    "wof:placetype":"venue"
},
  "geometry": {"coordinates":[-81.19220799999999,28.661621],"type":"Point"}
}