{
  "type": "Feature",
  "properties": {
    "iso:country":"US",
    "sg:address":"3865 N Wickham Rd",
    "sg:city":"Melbourne",
    "sg:classifiers":[
        {
            "category":"Education",
            "subcategory":"Junior College",
            "type":"Public Place"
        }
    ],
    "sg:phone":"+1 321 633 1000",
    "sg:postcode":"32935",
    "sg:province":"FL",
    "sg:tags":[
        "community"
    ],
    "wof:name":"Melbourne Campus",
    "wof:placetype":"venue"
},
  "geometry": {"coordinates":[-80.671949,28.170078],"type":"Point"}
}