{
  "type": "Feature",
  "properties": {
    "iso:country":"US",
    "sg:address":"3308 English Rd",
    "sg:city":"Plant City",
    "sg:classifiers":[
        {
            "category":"Farming",
            "subcategory":"Nursery",
            "type":"Manufacturing & Wholesale Goods"
        }
    ],
    "sg:phone":"+1 813 752 0931",
    "sg:postcode":"33567",
    "sg:province":"FL",
    "sg:tags":[
        "ornamental"
    ],
    "wof:name":"Harrells Nursery Inc",
    "wof:placetype":"venue"
},
  "geometry": {"coordinates":[-82.06821600000001,27.952709],"type":"Point"}
}