{
  "type": "Feature",
  "properties": {
    "addr:full":"626 Belvedere Rd West Palm Beach FL 33405",
    "addr:housenumber":"626",
    "addr:postcode":"33405",
    "addr:street":"Belvedere Rd",
    "iso:country":"US",
    "sg:address":"626 Belvedere Rd",
    "sg:city":"West Palm Beach",
    "sg:classifiers":[
        {
            "category":"Health Services",
            "subcategory":"Optometrist",
            "type":"Services"
        }
    ],
    "sg:phone":"+1 561 832 0677",
    "sg:postcode":"33405",
    "sg:province":"FL",
    "wof:name":"Belvedere Vision Care",
    "wof:placetype":"venue"
},
  "geometry": {"coordinates":[-80.058001,26.690337],"type":"Point"}
}