{
  "type": "Feature",
  "properties": {
    "addr:full":"2681 Airport Pulling Rd S Naples FL 34112",
    "addr:housenumber":"2681",
    "addr:postcode":"34112",
    "addr:street":"Airport Pulling Rd S",
    "iso:country":"US",
    "sg:address":"2681 Airport Pulling Rd S",
    "sg:city":"Naples",
    "sg:classifiers":[
        {
            "category":"Banks & Credit Unions",
            "subcategory":"Bank",
            "type":"Services"
        }
    ],
    "sg:phone":"+1 239 403 7767",
    "sg:postcode":"34112",
    "sg:province":"FL",
    "sg:tags":[
        "broker",
        "mortgage"
    ],
    "wof:name":"Haun Mortgage Center of Naples",
    "wof:placetype":"venue"
},
  "geometry": {"coordinates":[-81.766374,26.130759],"type":"Point"}
}