{
  "type": "Feature",
  "properties": {
    "iso:country":"US",
    "sg:address":"1940 Harrison St",
    "sg:city":"Hollywood",
    "sg:classifiers":[
        {
            "category":"Professional",
            "subcategory":"Computer Services",
            "type":"Services"
        }
    ],
    "sg:phone":"+1 954 921 3662",
    "sg:postcode":"33020",
    "sg:province":"FL",
    "sg:tags":[
        "datum"
    ],
    "wof:name":"Precision Dev Solutions",
    "wof:placetype":"venue"
},
  "geometry": {"coordinates":[-80.14618900000001,26.010429],"type":"Point"}
}