{
  "type": "Feature",
  "properties": {
    "addr:full":"2220 del Prado Blvd S Cape Coral FL 33990",
    "addr:housenumber":"2220",
    "addr:postcode":"33990",
    "addr:street":"Del Prado Blvd S",
    "iso:country":"US",
    "sg:address":"2220 del Prado Blvd S",
    "sg:city":"Cape Coral",
    "sg:classifiers":[
        {
            "category":"Food & Beverages",
            "subcategory":"Liquor & Beverages",
            "type":"Retail Goods"
        }
    ],
    "sg:phone":"+1 239 458 9204",
    "sg:postcode":"33990",
    "sg:province":"FL",
    "sg:tags":[
        "alcoholic"
    ],
    "wof:name":"A B C Fine Wine & Spirits 98",
    "wof:placetype":"venue"
},
  "geometry": {"coordinates":[-81.941108,26.610776],"type":"Point"}
}