{
  "type": "Feature",
  "properties": {
    "iso:country":"US",
    "sg:address":"6500 S Orange Ave",
    "sg:city":"Orlando",
    "sg:classifiers":[
        {
            "category":"Travel",
            "subcategory":"Travel Agent",
            "type":"Entertainment"
        }
    ],
    "sg:phone":"+1 407 888 2324",
    "sg:postcode":"32809",
    "sg:province":"FL",
    "sg:tags":[
        "cruise"
    ],
    "wof:name":"Sterling Cruise Lines LC",
    "wof:placetype":"venue"
},
  "geometry": {"coordinates":[-81.36763500000001,28.466102],"type":"Point"}
}