{
  "type": "Feature",
  "properties": {
    "iso:country":"US",
    "sg:address":"6410 W Arter St",
    "sg:city":"Crystal River",
    "sg:classifiers":[
        {
            "category":"Wholesale",
            "subcategory":"Hardware",
            "type":"Manufacturing & Wholesale Goods"
        }
    ],
    "sg:phone":"+1 352 795 0894",
    "sg:postcode":"34429",
    "sg:province":"FL",
    "sg:tags":[
        "plumbing",
        "electrical",
        "supply"
    ],
    "wof:name":"Slacks Electrical & Plbg Sups",
    "wof:placetype":"venue"
},
  "geometry": {"coordinates":[-82.54160299999999,28.876755],"type":"Point"}
}