{
  "type": "Feature",
  "properties": {
    "addr:full":"12061 31st Ct N St Petersburg FL 33716",
    "addr:housenumber":"12061",
    "addr:postcode":"33716",
    "addr:street":"31St Ct N",
    "iso:country":"US",
    "sg:address":"12061 31st Ct N",
    "sg:city":"St Petersburg",
    "sg:classifiers":[
        {
            "category":"Food & Beverages",
            "subcategory":"Meat & Fish",
            "type":"Retail Goods"
        },
        {
            "category":"Wholesale",
            "subcategory":"Groceries",
            "type":"Manufacturing & Wholesale Goods"
        }
    ],
    "sg:phone":"+1 727 540 9096",
    "sg:postcode":"33716",
    "sg:province":"FL",
    "sg:tags":[
        "wholesaler",
        "frozen"
    ],
    "sg:website":"www.directusaonline.com",
    "wof:name":"Direct USA Inc",
    "wof:placetype":"venue"
},
  "geometry": {"coordinates":[-82.675428,27.880322],"type":"Point"}
}