{
  "type": "Feature",
  "properties": {
    "addr:full":"5417 101st St Jacksonville FL 32210",
    "addr:housenumber":"5417",
    "addr:postcode":"32210",
    "addr:street":"101St St",
    "iso:country":"US",
    "sg:address":"5417 101st St",
    "sg:city":"Jacksonville",
    "sg:classifiers":[
        {
            "category":"Mining & Drilling",
            "type":"Manufacturing & Wholesale Goods"
        }
    ],
    "sg:phone":"+1 904 779 2200",
    "sg:postcode":"32210",
    "sg:province":"FL",
    "sg:tags":[
        "stone",
        "dimension",
        "quarry"
    ],
    "wof:name":"Roosevelt L Young",
    "wof:placetype":"venue"
},
  "geometry": {"coordinates":[-81.72371699999999,30.250569],"type":"Point"}
}