{
  "type": "Feature",
  "properties": {
    "iso:country":"US",
    "sg:address":"8224 E Cooper Ln",
    "sg:city":"Floral City",
    "sg:classifiers":[
        {
            "category":"Building & Trades",
            "subcategory":"Landscaping Services",
            "type":"Services"
        }
    ],
    "sg:phone":"+1 352 341 1021",
    "sg:postcode":"34436",
    "sg:province":"FL",
    "wof:name":"William R Weatherholtz",
    "wof:placetype":"venue"
},
  "geometry": {"coordinates":[-82.29757499999999,28.755253],"type":"Point"}
}