{
  "type": "Feature",
  "properties": {
    "iso:country":"US",
    "sg:address":"2743 Maguire Rd",
    "sg:city":"Ocoee",
    "sg:classifiers":[
        {
            "category":"Insurance",
            "subcategory":"Hazard Insurance",
            "type":"Services"
        },
        {
            "category":"Insurance",
            "subcategory":"Health Insurance",
            "type":"Services"
        }
    ],
    "sg:phone":"+1 407 292 9242",
    "sg:postcode":"34761",
    "sg:province":"FL",
    "wof:name":"Patrick Gray State Farm",
    "wof:placetype":"venue"
},
  "geometry": {"coordinates":[-81.541873,28.530605],"type":"Point"}
}