{
  "type": "Feature",
  "properties": {
    "iso:country":"US",
    "sg:address":"1350 Palm Ave",
    "sg:city":"Hialeah",
    "sg:classifiers":[
        {
            "category":"Professional",
            "subcategory":"Business Services",
            "type":"Services"
        },
        {
            "category":"Government",
            "subcategory":"Post Office",
            "type":"Public Place"
        }
    ],
    "sg:phone":"+1 305 888 5711",
    "sg:postcode":"33010",
    "sg:province":"FL",
    "sg:tags":[
        "delivery",
        "labeling",
        "courier"
    ],
    "wof:name":"Global Express",
    "wof:placetype":"venue"
},
  "geometry": {"coordinates":[-80.28176499999999,25.834004],"type":"Point"}
}