{
  "type": "Feature",
  "properties": {
    "iso:country":"US",
    "sg:address":"290 Flower Ln",
    "sg:city":"Kissimmee",
    "sg:classifiers":[
        {
            "category":"Building & Trades",
            "subcategory":"Construction",
            "type":"Services"
        }
    ],
    "sg:phone":"+1 321 624 5265",
    "sg:postcode":"34743",
    "sg:province":"FL",
    "sg:tags":[
        "carpentry",
        "contractor"
    ],
    "wof:name":"Shane R Johnstone",
    "wof:placetype":"venue"
},
  "geometry": {"coordinates":[-81.34214299999999,28.325171],"type":"Point"}
}