{
  "type": "Feature",
  "properties": {
    "addr:full":"863 Semoran Blvd Casselberry FL 32707",
    "addr:housenumber":"863",
    "addr:postcode":"32707",
    "addr:street":"Semoran Blvd",
    "iso:country":"US",
    "sg:address":"863 Semoran Blvd",
    "sg:city":"Casselberry",
    "sg:classifiers":[
        {
            "category":"Autos & Motor Vehicles",
            "subcategory":"Automobile Sales",
            "type":"Retail Goods"
        }
    ],
    "sg:phone":"+1 407 294 9352",
    "sg:postcode":"32707",
    "sg:province":"FL",
    "wof:name":"Jeep LLC",
    "wof:placetype":"venue"
},
  "geometry": {"coordinates":[-81.325542,28.64926],"type":"Point"}
}