{
  "type": "Feature",
  "properties": {
    "iso:country":"US",
    "sg:address":"661 Neptune St",
    "sg:city":"West Palm Beach",
    "sg:classifiers":[
        {
            "category":"Building & Trades",
            "subcategory":"Cleaning & Sanitation",
            "type":"Services"
        }
    ],
    "sg:phone":"+1 561 471 3637",
    "sg:postcode":"33406",
    "sg:province":"FL",
    "sg:tags":[
        "window"
    ],
    "wof:name":"Streak Free Window Cleaners",
    "wof:placetype":"venue"
},
  "geometry": {"coordinates":[-80.109934,26.666744],"type":"Point"}
}