{
  "type": "Feature",
  "properties": {
    "iso:country":"US",
    "sg:address":"4101B NW 37th Pl",
    "sg:city":"Gainesville",
    "sg:classifiers":[
        {
            "category":"Personal",
            "subcategory":"Massage",
            "type":"Services"
        },
        {
            "category":"Health Services",
            "subcategory":"Clinic",
            "type":"Services"
        },
        {
            "category":"Health Services",
            "subcategory":"Health Practitioner",
            "type":"Services"
        },
        {
            "category":"Health Services",
            "subcategory":"Chiropractor",
            "type":"Services"
        }
    ],
    "sg:phone":"+1 352 377 2225",
    "sg:postcode":"32606",
    "sg:province":"FL",
    "sg:tags":[
        "therapist",
        "therapy",
        "physical",
        "chiropractic"
    ],
    "wof:name":"Darwin Chiropractic Center",
    "wof:placetype":"venue"
},
  "geometry": {"coordinates":[-82.386881,29.68739],"type":"Point"}
}