{
  "type": "Feature",
  "properties": {
    "iso:country":"US",
    "sg:address":"12257 S Dixie Hwy",
    "sg:city":"Miami",
    "sg:classifiers":[
        {
            "category":"Restaurant",
            "type":"Food & Drink"
        }
    ],
    "sg:menulink":"http://www.allmenus.com/fl/kendall-perrine/193102-las-culebrinas/menu/",
    "sg:phone":"+1 305 969 3995",
    "sg:postcode":"33156",
    "sg:province":"FL",
    "sg:tags":[
        "caribbean"
    ],
    "wof:name":"Las Culebrinas",
    "wof:placetype":"venue"
},
  "geometry": {"coordinates":[-80.328056,25.65665],"type":"Point"}
}