{
  "type": "Feature",
  "properties": {
    "addr:full":"2730 River Woods Dr Parrish FL 34219",
    "addr:housenumber":"2730",
    "addr:postcode":"34219",
    "addr:street":"River Woods Dr",
    "iso:country":"US",
    "sg:address":"2730 River Woods Dr",
    "sg:city":"Parrish",
    "sg:classifiers":[
        {
            "category":"Structure",
            "subcategory":"Office Building",
            "type":"Public Place"
        }
    ],
    "sg:phone":"+1 941 776 2272",
    "sg:postcode":"34219",
    "sg:province":"FL",
    "sg:tags":[
        "park"
    ],
    "wof:name":"Elk Lake Properties, Inc.",
    "wof:placetype":"venue"
},
  "geometry": {"coordinates":[-82.447542,27.53744],"type":"Point"}
}