{
  "type": "Feature",
  "properties": {
    "addr:full":"13043 Park Blvd Seminole FL 33776",
    "addr:housenumber":"13043",
    "addr:postcode":"33776",
    "addr:street":"Park Blvd",
    "iso:country":"US",
    "sg:address":"13043 Park Blvd",
    "sg:city":"Seminole",
    "sg:classifiers":[
        {
            "category":"Shopping",
            "subcategory":"Gifts & Souvenirs",
            "type":"Retail Goods"
        }
    ],
    "sg:phone":"+1 727 319 2722",
    "sg:postcode":"33776",
    "sg:province":"FL",
    "sg:tags":[
        "party",
        "supply"
    ],
    "wof:name":"A Party Store In Seminole",
    "wof:placetype":"venue"
},
  "geometry": {"coordinates":[-82.818243,27.843728],"type":"Point"}
}