{
  "type": "Feature",
  "properties": {
    "iso:country":"US",
    "sg:address":"2780 SW 87th Ave",
    "sg:city":"Miami",
    "sg:classifiers":[
        {
            "category":"Professional",
            "subcategory":"Management & Consulting",
            "type":"Services"
        }
    ],
    "sg:phone":"+1 305 553 9616",
    "sg:postcode":"33165",
    "sg:province":"FL",
    "wof:name":"Florida Real Estate Management",
    "wof:placetype":"venue"
},
  "geometry": {"coordinates":[-80.335768,25.744285],"type":"Point"}
}