{
  "type": "Feature",
  "properties": {
    "iso:country":"US",
    "sg:address":"4830 NE 25th Ave",
    "sg:city":"Fort Lauderdale",
    "sg:classifiers":[
        {
            "category":"Health Services",
            "subcategory":"Clinic",
            "type":"Services"
        }
    ],
    "sg:phone":"+1 954 472 0344",
    "sg:postcode":"33308",
    "sg:province":"FL",
    "wof:name":"Allabout Health LLC",
    "wof:placetype":"venue"
},
  "geometry": {"coordinates":[-80.111422,26.18821],"type":"Point"}
}