{
  "type": "Feature",
  "properties": {
    "iso:country":"US",
    "sg:address":"1460 Shetter Ave",
    "sg:city":"Jacksonville Bch",
    "sg:classifiers":[
        {
            "category":"Government",
            "subcategory":"Office",
            "type":"Public Place"
        }
    ],
    "sg:phone":"+1 904 247 6228",
    "sg:postcode":"32250",
    "sg:province":"FL",
    "sg:tags":[
        "village"
    ],
    "wof:name":"Jacksonville Beach Purchasing",
    "wof:placetype":"venue"
},
  "geometry": {"coordinates":[-81.40526,30.28604],"type":"Point"}
}