{
  "type": "Feature",
  "properties": {
    "iso:country":"US",
    "sg:address":"1132 Kane Concourse",
    "sg:city":"Bay Harbor Islands",
    "sg:classifiers":[
        {
            "category":"Banks & Credit Unions",
            "subcategory":"Bank",
            "type":"Services"
        }
    ],
    "sg:phone":"+1 305 865 4345",
    "sg:postcode":"33154",
    "sg:province":"FL",
    "wof:name":"Union Planters Bank",
    "wof:placetype":"venue"
},
  "geometry": {"coordinates":[-80.133003,25.8867],"type":"Point"}
}