{
  "type": "Feature",
  "properties": {
    "addr:full":"910 S J St Lake Worth FL 33460",
    "addr:housenumber":"910",
    "addr:postcode":"33460",
    "addr:street":"S J St",
    "iso:country":"US",
    "sg:address":"910 S J St",
    "sg:city":"Lake Worth",
    "sg:classifiers":[
        {
            "category":"Building & Trades",
            "subcategory":"Landscaping Services",
            "type":"Services"
        }
    ],
    "sg:phone":"+1 561 533 7236",
    "sg:postcode":"33460",
    "sg:province":"FL",
    "wof:name":"Freddy R Estrada Lawn Service",
    "wof:placetype":"venue"
},
  "geometry": {"coordinates":[-80.057124,26.603887],"type":"Point"}
}