{
  "type": "Feature",
  "properties": {
    "iso:country":"US",
    "sg:address":"1612 E Cape Coral Pkwy",
    "sg:city":"Cape Coral",
    "sg:classifiers":[
        {
            "category":"Banks & Credit Unions",
            "subcategory":"Financial Services",
            "type":"Services"
        }
    ],
    "sg:phone":"+1 239 542 8999",
    "sg:postcode":"33904",
    "sg:province":"FL",
    "sg:tags":[
        "customer"
    ],
    "wof:name":"Whitney Education Group Inc",
    "wof:placetype":"venue"
},
  "geometry": {"coordinates":[-81.941962,26.562469],"type":"Point"}
}