{
  "type": "Feature",
  "properties": {
    "addr:full":"951 Bald Eagle Dr Marco Island FL 34145",
    "addr:housenumber":"951",
    "addr:postcode":"34145",
    "addr:street":"Bald Eagle Dr",
    "iso:country":"US",
    "sg:address":"951 Bald Eagle Dr",
    "sg:city":"Marco Island",
    "sg:classifiers":[
        {
            "category":"Travel",
            "subcategory":"Travel Agent",
            "type":"Entertainment"
        }
    ],
    "sg:phone":"+1 239 642 9516",
    "sg:postcode":"34145",
    "sg:province":"FL",
    "sg:tags":[
        "cruise"
    ],
    "wof:name":"Naples Princess",
    "wof:placetype":"venue"
},
  "geometry": {"coordinates":[-81.728008,25.962133],"type":"Point"}
}