{
  "type": "Feature",
  "properties": {
    "addr:full":"476 May St Jacksonville FL 32204",
    "addr:housenumber":"476",
    "addr:postcode":"32204",
    "addr:street":"May St",
    "iso:country":"US",
    "sg:address":"476 May St",
    "sg:city":"Jacksonville",
    "sg:classifiers":[
        {
            "category":"Retail",
            "subcategory":"Auto Repair",
            "type":"Services"
        }
    ],
    "sg:phone":"+1 904 358 0103",
    "sg:postcode":"32204",
    "sg:province":"FL",
    "sg:tags":[
        "automotive",
        "clutches",
        "used",
        "automobile"
    ],
    "wof:name":"Dealers Equipment Co Inc",
    "wof:placetype":"venue"
},
  "geometry": {"coordinates":[-81.675191,30.321462],"type":"Point"}
}