{
  "type": "Feature",
  "properties": {
    "addr:full":"625 Barefoot Blvd Barefoot Bay FL 32976",
    "addr:housenumber":"625",
    "addr:postcode":"32976",
    "addr:street":"Barefoot Blvd Barefoot",
    "iso:country":"US",
    "sg:address":"625 Barefoot Blvd",
    "sg:city":"Barefoot Bay",
    "sg:classifiers":[
        {
            "category":"Health Services",
            "subcategory":"Health Practitioner",
            "type":"Services"
        }
    ],
    "sg:phone":"+1 772 664 9222",
    "sg:postcode":"32976",
    "sg:province":"FL",
    "sg:tags":[
        "nurse",
        "registry"
    ],
    "wof:name":"Visiting Nurse Assn",
    "wof:placetype":"venue"
},
  "geometry": {"coordinates":[-80.518418,27.888541],"type":"Point"}
}