{
  "type": "Feature",
  "properties": {
    "iso:country":"US",
    "sg:address":"200 Ivey Rd",
    "sg:city":"Casselberry",
    "sg:classifiers":[
        {
            "category":"Park",
            "type":"Public Place"
        }
    ],
    "sg:phone":"+1 407 696 5189",
    "sg:postcode":"32707",
    "sg:province":"FL",
    "wof:name":"Casselberry City of",
    "wof:placetype":"venue"
},
  "geometry": {"coordinates":[-81.326724,28.672901],"type":"Point"}
}