{
  "type": "Feature",
  "properties": {
    "addr:full":"8544 Gunn Hwy Odessa FL 33556",
    "addr:housenumber":"8544",
    "addr:postcode":"33556",
    "addr:street":"Gunn Hwy",
    "iso:country":"US",
    "sg:address":"8544 Gunn Hwy",
    "sg:city":"Odessa",
    "sg:classifiers":[
        {
            "category":"Retail",
            "subcategory":"Laundry & Dry Cleaning",
            "type":"Services"
        }
    ],
    "sg:phone":"+1 813 920 9332",
    "sg:postcode":"33556",
    "sg:province":"FL",
    "sg:tags":[
        "cleaners"
    ],
    "wof:name":"Kml",
    "wof:placetype":"venue"
},
  "geometry": {"coordinates":[-82.57897800000001,28.090246],"type":"Point"}
}