{
  "type": "Feature",
  "properties": {
    "iso:country":"US",
    "sg:address":"2225 E 10th Ave",
    "sg:city":"Hialeah",
    "sg:classifiers":[
        {
            "category":"Food & Beverages",
            "subcategory":"Fruits & Vegetables",
            "type":"Retail Goods"
        }
    ],
    "sg:phone":"+1 305 696 9755",
    "sg:postcode":"33013",
    "sg:province":"FL",
    "sg:tags":[
        "produce"
    ],
    "wof:name":"Ecua Fruit Corp",
    "wof:placetype":"venue"
},
  "geometry": {"coordinates":[-80.262086,25.843553],"type":"Point"}
}