{
  "type": "Feature",
  "properties": {
    "addr:full":"201 E University Ave Gainesville FL 32601",
    "addr:housenumber":"201",
    "addr:postcode":"32601",
    "addr:street":"E University Ave",
    "iso:country":"US",
    "sg:address":"201 E University Ave",
    "sg:city":"Gainesville",
    "sg:classifiers":[
        {
            "category":"Government",
            "subcategory":"Office",
            "type":"Public Place"
        }
    ],
    "sg:phone":"+1 352 374 3646",
    "sg:postcode":"32601",
    "sg:province":"FL",
    "wof:name":"Honorable Martha Ann Lott",
    "wof:placetype":"venue"
},
  "geometry": {"coordinates":[-82.32240299999999,29.651961],"type":"Point"}
}