{
  "type": "Feature",
  "properties": {
    "addr:full":"844 Coleman Ave Sarasota FL 34232",
    "addr:housenumber":"844",
    "addr:postcode":"34232",
    "addr:street":"Coleman Ave",
    "iso:country":"US",
    "sg:address":"844 Coleman Ave",
    "sg:city":"Sarasota",
    "sg:classifiers":[
        {
            "category":"Building & Trades",
            "subcategory":"Construction",
            "type":"Services"
        }
    ],
    "sg:phone":"+1 941 342 0597",
    "sg:postcode":"34232",
    "sg:province":"FL",
    "sg:tags":[
        "general",
        "contractor"
    ],
    "wof:name":"DPS Masonry",
    "wof:placetype":"venue"
},
  "geometry": {"coordinates":[-82.453549,27.327597],"type":"Point"}
}