{
  "type": "Feature",
  "properties": {
    "iso:country":"US",
    "sg:address":"726 S Woodland Blvd",
    "sg:city":"Deland",
    "sg:classifiers":[
        {
            "category":"Building & Trades",
            "subcategory":"Plumbing",
            "type":"Services"
        }
    ],
    "sg:phone":"+1 386 734 9885",
    "sg:postcode":"32720",
    "sg:province":"FL",
    "sg:tags":[
        "plumbing",
        "contractor"
    ],
    "wof:name":"Southside Plumbing",
    "wof:placetype":"venue"
},
  "geometry": {"coordinates":[-81.303158,29.016874],"type":"Point"}
}