{
  "type": "Feature",
  "properties": {
    "iso:country":"US",
    "sg:address":"7945 NW 198th Ter",
    "sg:city":"Hialeah",
    "sg:classifiers":[
        {
            "category":"Building & Trades",
            "subcategory":"Electrical",
            "type":"Services"
        }
    ],
    "sg:phone":"+1 305 200 1010",
    "sg:postcode":"33015",
    "sg:province":"FL",
    "sg:tags":[
        "electric",
        "contractor"
    ],
    "wof:name":"Amercian Eagle Electric Corp",
    "wof:placetype":"venue"
},
  "geometry": {"coordinates":[-80.332374,25.95317],"type":"Point"}
}