{
  "type": "Feature",
  "properties": {
    "addr:full":"14919 Tamiami Trl North Port FL 34287",
    "addr:housenumber":"14919",
    "addr:postcode":"34287",
    "addr:street":"Tamiami Trl",
    "iso:country":"US",
    "sg:address":"14919 Tamiami Trl",
    "sg:city":"North Port",
    "sg:classifiers":[
        {
            "category":"Restaurant",
            "type":"Food & Drink"
        }
    ],
    "sg:menulink":"http://www.allmenus.com/fl/north-port/81650-bella-napoli/menu/",
    "sg:phone":"+1 941 426 2004",
    "sg:postcode":"34287",
    "sg:province":"FL",
    "sg:tags":[
        "italian"
    ],
    "wof:name":"Bella Napoli",
    "wof:placetype":"venue"
},
  "geometry": {"coordinates":[-82.227361,27.040792],"type":"Point"}
}