{
  "type": "Feature",
  "properties": {
    "iso:country":"US",
    "sg:address":"1215 Gulf Rd",
    "sg:city":"Tarpon Springs",
    "sg:classifiers":[
        {
            "category":"Food & Beverages",
            "subcategory":"Groceries & Convenience Stores",
            "type":"Retail Goods"
        }
    ],
    "sg:phone":"+1 727 937 4479",
    "sg:postcode":"34689",
    "sg:province":"FL",
    "wof:name":"Pick KWIK Food Stores",
    "wof:placetype":"venue"
},
  "geometry": {"coordinates":[-82.77418900000001,28.144849],"type":"Point"}
}