{
  "type": "Feature",
  "properties": {
    "addr:full":"4450 NW 135th St Opa Locka FL 33054",
    "addr:housenumber":"4450",
    "addr:postcode":"33054",
    "addr:street":"Nw 135Th St;Locka",
    "iso:country":"US",
    "sg:address":"4450 NW 135th St",
    "sg:city":"Opa Locka",
    "sg:classifiers":[
        {
            "category":"Shopping",
            "subcategory":"Books",
            "type":"Retail Goods"
        }
    ],
    "sg:phone":"+1 305 687 0087",
    "sg:postcode":"33054",
    "sg:province":"FL",
    "sg:tags":[
        "bookstore"
    ],
    "sg:website":"www.lucianosbooks.com",
    "wof:name":"Luciano's Books",
    "wof:placetype":"venue"
},
  "geometry": {"coordinates":[-80.271518,25.896265],"type":"Point"}
}