{
  "type": "Feature",
  "properties": {
    "addr:full":"1851 Dobbs Rd St Augustine FL 32086",
    "addr:housenumber":"1851",
    "addr:postcode":"32086",
    "addr:street":"Dobbs Rd St",
    "iso:country":"US",
    "sg:address":"1851 Dobbs Rd",
    "sg:city":"St Augustine",
    "sg:classifiers":[
        {
            "category":"Building & Trades",
            "subcategory":"Pest Control",
            "type":"Services"
        }
    ],
    "sg:phone":"+1 904 829 3297",
    "sg:postcode":"32086",
    "sg:province":"FL",
    "wof:name":"Smith Brothers Pest Control",
    "wof:placetype":"venue"
},
  "geometry": {"coordinates":[-81.334883,29.866723],"type":"Point"}
}