{
  "type": "Feature",
  "properties": {
    "addr:full":"246 Riverside Dr Daytona Beach FL 32117",
    "addr:housenumber":"246",
    "addr:postcode":"32117",
    "addr:street":"Riverside Dr",
    "iso:country":"US",
    "sg:address":"246 Riverside Dr",
    "sg:city":"Daytona Beach",
    "sg:classifiers":[
        {
            "category":"Building & Trades",
            "subcategory":"Construction",
            "type":"Services"
        }
    ],
    "sg:phone":"+1 386 248 0153",
    "sg:postcode":"32117",
    "sg:province":"FL",
    "sg:tags":[
        "house"
    ],
    "wof:name":"B & B Home Improvements",
    "wof:placetype":"venue"
},
  "geometry": {"coordinates":[-81.02894499999999,29.231411],"type":"Point"}
}