{
  "type": "Feature",
  "properties": {
    "iso:country":"US",
    "sg:address":"125 Saint Lucie Ave",
    "sg:city":"Sarasota",
    "sg:classifiers":[
        {
            "category":"Wholesale",
            "subcategory":"Books, Periodicals, & Newspapers",
            "type":"Manufacturing & Wholesale Goods"
        }
    ],
    "sg:phone":"+1 941 377 7073",
    "sg:postcode":"34232",
    "sg:province":"FL",
    "sg:tags":[
        "publishers-periodical"
    ],
    "wof:name":"Shriekfreak Quarterly",
    "wof:placetype":"venue"
},
  "geometry": {"coordinates":[-82.483431,27.335226],"type":"Point"}
}