{
  "type": "Feature",
  "properties": {
    "iso:country":"US",
    "sg:address":"36 Northwoods Ln",
    "sg:city":"Boynton Beach",
    "sg:classifiers":[
        {
            "category":"Organizations",
            "subcategory":"Professional Association",
            "type":"Services"
        }
    ],
    "sg:phone":"+1 561 736 1723",
    "sg:postcode":"33436",
    "sg:province":"FL",
    "wof:name":"Northwoods Condominium Assn",
    "wof:placetype":"venue"
},
  "geometry": {"coordinates":[-80.113079,26.494694],"type":"Point"}
}