{
  "type": "Feature",
  "properties": {
    "iso:country":"US",
    "sg:address":"1601 S Congress Ave",
    "sg:city":"Delray Beach",
    "sg:classifiers":[
        {
            "category":"Retail",
            "subcategory":"Auto Repair",
            "type":"Services"
        }
    ],
    "sg:phone":"+1 561 276 2886",
    "sg:postcode":"33445",
    "sg:province":"FL",
    "sg:tags":[
        "shop",
        "automotive",
        "general"
    ],
    "wof:name":"Goodmans Auto Service Center",
    "wof:placetype":"venue"
},
  "geometry": {"coordinates":[-80.092412,26.43777],"type":"Point"}
}