{
  "type": "Feature",
  "properties": {
    "iso:country":"US",
    "sg:address":"6104 Dixie Hwy",
    "sg:city":"Miami",
    "sg:classifiers":[
        {
            "category":"Shopping",
            "type":"Retail Goods"
        }
    ],
    "sg:phone":"+1 305 661 6905",
    "sg:postcode":"33143",
    "sg:province":"FL",
    "sg:tags":[
        "pet",
        "food",
        "merchandise",
        "supply"
    ],
    "wof:name":"Aquariumart Inc",
    "wof:placetype":"venue"
},
  "geometry": {"coordinates":[-80.29321400000001,25.701315],"type":"Point"}
}