{
  "type": "Feature",
  "properties": {
    "iso:country":"US",
    "sg:address":"3001 SW 10th St",
    "sg:city":"Pompano Beach",
    "sg:classifiers":[
        {
            "category":"Manufacturing",
            "subcategory":"Furniture",
            "type":"Manufacturing & Wholesale Goods"
        }
    ],
    "sg:phone":"+1 954 935 0366",
    "sg:postcode":"33069",
    "sg:province":"FL",
    "sg:tags":[
        "wood",
        "mfg"
    ],
    "wof:name":"Fort Lauderdale Woodworking",
    "wof:placetype":"venue"
},
  "geometry": {"coordinates":[-80.16531500000001,26.21583],"type":"Point"}
}