{
  "type": "Feature",
  "properties": {
    "iso:country":"US",
    "sg:address":"2300 SE Ocean Blvd",
    "sg:city":"Stuart",
    "sg:classifiers":[
        {
            "category":"Health Services",
            "subcategory":"Doctor",
            "type":"Services"
        }
    ],
    "sg:phone":"+1 772 223 5604",
    "sg:postcode":"34996",
    "sg:province":"FL",
    "sg:tags":[
        "medicine",
        "physician",
        "practice",
        "surgeons",
        "family"
    ],
    "wof:name":"James Gray Md",
    "wof:placetype":"venue"
},
  "geometry": {"coordinates":[-80.221712,27.196895],"type":"Point"}
}