{
  "type": "Feature",
  "properties": {
    "addr:full":"5261 US Hwy 90 Milton FL 32571",
    "addr:housenumber":"5261",
    "addr:postcode":"32571",
    "addr:street":"Us Hwy 90",
    "iso:country":"US",
    "sg:address":"5261 US Hwy 90",
    "sg:city":"Milton",
    "sg:classifiers":[
        {
            "category":"Health Services",
            "subcategory":"Chiropractor",
            "type":"Services"
        }
    ],
    "sg:phone":"+1 850 994 1147",
    "sg:postcode":"32571",
    "sg:province":"FL",
    "wof:name":"Brooks Chiropractic Clinic",
    "wof:placetype":"venue"
},
  "geometry": {"coordinates":[-87.105253,30.602955],"type":"Point"}
}