{
  "type": "Feature",
  "properties": {
    "iso:country":"US",
    "sg:address":"8427 Fremont Rd",
    "sg:city":"Youngstown",
    "sg:classifiers":[
        {
            "category":"Personal",
            "subcategory":"Beauty Salon",
            "type":"Services"
        }
    ],
    "sg:phone":"+1 850 522 3881",
    "sg:postcode":"32466",
    "sg:province":"FL",
    "wof:name":"Mc Styles Inc.",
    "wof:placetype":"venue"
},
  "geometry": {"coordinates":[-85.539886,30.300272],"type":"Point"}
}