{
  "type": "Feature",
  "properties": {
    "iso:country":"US",
    "sg:address":"715 Ohio Ave",
    "sg:city":"Lynn Haven",
    "sg:classifiers":[
        {
            "category":"Home & Garden",
            "subcategory":"Household Appliances",
            "type":"Retail Goods"
        }
    ],
    "sg:phone":"+1 850 265 6584",
    "sg:postcode":"32444",
    "sg:province":"FL",
    "sg:tags":[
        "machine",
        "sewing"
    ],
    "wof:name":"Jim's Vacuum & Sewing Ctr",
    "wof:placetype":"venue"
},
  "geometry": {"coordinates":[-85.64847899999999,30.246757],"type":"Point"}
}