{
  "type": "Feature",
  "properties": {
    "addr:full":"518 W 27th St Hialeah FL 33010",
    "addr:housenumber":"518",
    "addr:postcode":"33010",
    "addr:street":"W 27Th St",
    "iso:country":"US",
    "sg:address":"518 W 27th St",
    "sg:city":"Hialeah",
    "sg:classifiers":[
        {
            "category":"Retail",
            "subcategory":"Auto Repair",
            "type":"Services"
        }
    ],
    "sg:phone":"+1 305 887 7608",
    "sg:postcode":"33010",
    "sg:province":"FL",
    "sg:tags":[
        "body",
        "automobile",
        "painting"
    ],
    "wof:name":"Perfection Body Shop Inc",
    "wof:placetype":"venue"
},
  "geometry": {"coordinates":[-80.29389,25.846096],"type":"Point"}
}