{
  "type": "Feature",
  "properties": {
    "addr:full":"3188 E Colonial Dr Orlando FL 32803",
    "addr:housenumber":"3188",
    "addr:postcode":"32803",
    "addr:street":"E Colonial Dr",
    "iso:country":"US",
    "sg:address":"3188 E Colonial Dr",
    "sg:city":"Orlando",
    "sg:classifiers":[
        {
            "category":"Personal",
            "subcategory":"Beauty Salon",
            "type":"Services"
        }
    ],
    "sg:phone":"+1 407 898 2928",
    "sg:postcode":"32803",
    "sg:province":"FL",
    "sg:tags":[
        "manicuring"
    ],
    "wof:name":"California Nails",
    "wof:placetype":"venue"
},
  "geometry": {"coordinates":[-81.34316,28.55326],"type":"Point"}
}