{
  "type": "Feature",
  "properties": {
    "addr:full":"2050 Warwick Hills Dr Orlando FL 32826",
    "addr:housenumber":"2050",
    "addr:postcode":"32826",
    "addr:street":"Warwick Hills Dr",
    "iso:country":"US",
    "sg:address":"2050 Warwick Hills Dr",
    "sg:city":"Orlando",
    "sg:classifiers":[
        {
            "category":"Banks & Credit Unions",
            "subcategory":"Bank",
            "type":"Services"
        }
    ],
    "sg:phone":"+1 407 282 6079",
    "sg:postcode":"32826",
    "sg:province":"FL",
    "sg:tags":[
        "short",
        "institution",
        "business"
    ],
    "wof:name":"Maurice D Korn Credit Card Svc",
    "wof:placetype":"venue"
},
  "geometry": {"coordinates":[-81.174891,28.575777],"type":"Point"}
}