{
  "type": "Feature",
  "properties": {
    "iso:country":"US",
    "sg:address":"2334 Ponce De Leon Blvd",
    "sg:city":"Miami",
    "sg:classifiers":[
        {
            "category":"Restaurant",
            "type":"Food & Drink"
        }
    ],
    "sg:menulink":"http://www.allmenus.com/fl/miami/193143-sushi-maki/menu/",
    "sg:phone":"+1 305 443 1884",
    "sg:postcode":"33134",
    "sg:province":"FL",
    "sg:tags":[
        "sushi",
        "asian"
    ],
    "wof:name":"Sushi Maki",
    "wof:placetype":"venue"
},
  "geometry": {"coordinates":[-80.258954,25.750275],"type":"Point"}
}