{
  "type": "Feature",
  "properties": {
    "addr:full":"5808 Breckenridge Pkwy Tampa FL 33610",
    "addr:housenumber":"5808",
    "addr:postcode":"33610",
    "addr:street":"Breckenridge Pkwy",
    "iso:country":"US",
    "sg:address":"5808 Breckenridge Pkwy",
    "sg:city":"Tampa",
    "sg:classifiers":[
        {
            "category":"Manufacturing",
            "subcategory":"Printing",
            "type":"Manufacturing & Wholesale Goods"
        }
    ],
    "sg:phone":"+1 813 630 1322",
    "sg:postcode":"33610",
    "sg:province":"FL",
    "sg:tags":[
        "book"
    ],
    "wof:name":"Glencoe/Mc Graw-Hill Pubg",
    "wof:placetype":"venue"
},
  "geometry": {"coordinates":[-82.358056,28.006351],"type":"Point"}
}