{
  "type": "Feature",
  "properties": {
    "iso:country":"US",
    "sg:address":"5150 S Florida Ave",
    "sg:city":"Lakeland",
    "sg:classifiers":[
        {
            "category":"Insurance",
            "subcategory":"Insurance Agent",
            "type":"Services"
        }
    ],
    "sg:phone":"+1 863 648 2654",
    "sg:postcode":"33813",
    "sg:province":"FL",
    "wof:name":"Triad Management Inc",
    "wof:placetype":"venue"
},
  "geometry": {"coordinates":[-81.960188,27.974788],"type":"Point"}
}