{
  "type": "Feature",
  "properties": {
    "iso:country":"US",
    "sg:address":"111 S Main St",
    "sg:city":"Wildwood",
    "sg:classifiers":[
        {
            "category":"Personal",
            "subcategory":"Beauty Salon",
            "type":"Services"
        }
    ],
    "sg:phone":"+1 352 748 7770",
    "sg:postcode":"34785",
    "sg:province":"FL",
    "wof:name":"Da Cutting Edge",
    "wof:placetype":"venue"
},
  "geometry": {"coordinates":[-82.04123800000001,28.862264],"type":"Point"}
}