{
  "type": "Feature",
  "properties": {
    "addr:full":"300 Bus Park Way Royal Palm Beach FL 33411",
    "addr:housenumber":"300",
    "addr:postcode":"33411",
    "addr:street":"Bus Park Way",
    "iso:country":"US",
    "sg:address":"300 Bus Park Way",
    "sg:city":"Royal Palm Beach",
    "sg:classifiers":[
        {
            "category":"Shopping",
            "subcategory":"Bicycles & Sporting Goods",
            "type":"Retail Goods"
        }
    ],
    "sg:phone":"+1 561 793 2947",
    "sg:postcode":"33411",
    "sg:province":"FL",
    "sg:tags":[
        "saddlery",
        "harness"
    ],
    "wof:name":"C M Hadfields Saddlery",
    "wof:placetype":"venue"
},
  "geometry": {"coordinates":[-80.207065,26.699071],"type":"Point"}
}