{
  "type": "Feature",
  "properties": {
    "addr:full":"3045 S Ponte Vedra Blvd Ponte Vedra Bch FL 32082",
    "addr:housenumber":"3045",
    "addr:postcode":"32082",
    "addr:street":"S Ponte Vedra Blvd",
    "iso:country":"US",
    "sg:address":"3045 S Ponte Vedra Blvd",
    "sg:city":"Ponte Vedra Bch",
    "sg:classifiers":[
        {
            "category":"Professional",
            "subcategory":"Advertising",
            "type":"Services"
        }
    ],
    "sg:phone":"+1 904 810 5300",
    "sg:postcode":"32082",
    "sg:province":"FL",
    "sg:tags":[
        "counselor"
    ],
    "wof:name":"Hocevar Video",
    "wof:placetype":"venue"
},
  "geometry": {"coordinates":[-81.313632,29.984228],"type":"Point"}
}