{
  "type": "Feature",
  "properties": {
    "iso:country":"US",
    "sg:address":"11219 Lorence Ave",
    "sg:city":"Jacksonville",
    "sg:classifiers":[
        {
            "category":"Personal",
            "subcategory":"Beauty Salon",
            "type":"Services"
        }
    ],
    "sg:phone":"+1 904 924 0043",
    "sg:postcode":"32218",
    "sg:province":"FL",
    "wof:name":"Chateau Of Beauty",
    "wof:placetype":"venue"
},
  "geometry": {"coordinates":[-81.695396,30.444059],"type":"Point"}
}