{
  "type": "Feature",
  "properties": {
    "iso:country":"US",
    "sg:address":"2500 N Powerline Rd",
    "sg:city":"Pompano Beach",
    "sg:classifiers":[
        {
            "category":"Restaurant",
            "type":"Food & Drink"
        }
    ],
    "sg:phone":"+1 954 971 9191",
    "sg:postcode":"33069",
    "sg:province":"FL",
    "sg:tags":[
        "eating"
    ],
    "wof:name":"Marshalls Catering",
    "wof:placetype":"venue"
},
  "geometry": {"coordinates":[-80.15178400000001,26.261958],"type":"Point"}
}