{
  "type": "Feature",
  "properties": {
    "addr:full":"4245 New Hampshire Rd Elkton FL 32033",
    "addr:housenumber":"4245",
    "addr:postcode":"32033",
    "addr:street":"New Hampshire Rd",
    "iso:country":"US",
    "sg:address":"4245 New Hampshire Rd",
    "sg:city":"Elkton",
    "sg:classifiers":[
        {
            "category":"Building & Trades",
            "subcategory":"Construction",
            "type":"Services"
        }
    ],
    "sg:phone":"+1 904 315 8364",
    "sg:postcode":"32033",
    "sg:province":"FL",
    "sg:tags":[
        "tile-contractors"
    ],
    "wof:name":"Complete Tile Installation Inc",
    "wof:placetype":"venue"
},
  "geometry": {"coordinates":[-81.39612,29.808378],"type":"Point"}
}