{
  "type": "Feature",
  "properties": {
    "addr:full":"3101 N Federal Hwy Oakland Park FL 33306",
    "addr:housenumber":"3101",
    "addr:postcode":"33306",
    "addr:street":"N Federal Hwy",
    "iso:country":"US",
    "sg:address":"3101 N Federal Hwy",
    "sg:city":"Oakland Park",
    "sg:classifiers":[
        {
            "category":"Utilities",
            "subcategory":"Mobile Phone",
            "type":"Services"
        }
    ],
    "sg:phone":"+1 954 565 1002",
    "sg:postcode":"33306",
    "sg:province":"FL",
    "sg:tags":[
        "telephone",
        "cellular"
    ],
    "wof:name":"Telecel",
    "wof:placetype":"venue"
},
  "geometry": {"coordinates":[-80.118708,26.169696],"type":"Point"}
}