{
  "type": "Feature",
  "properties": {
    "iso:country":"US",
    "sg:address":"2425 S Dale Mabry Hwy",
    "sg:city":"Tampa",
    "sg:classifiers":[
        {
            "category":"Personal",
            "subcategory":"Tanning Parlor",
            "type":"Services"
        }
    ],
    "sg:phone":"+1 813 259 1015",
    "sg:postcode":"33629",
    "sg:province":"FL",
    "sg:tags":[
        "salon"
    ],
    "wof:name":"Body Illusions Tanning Salon",
    "wof:placetype":"venue"
},
  "geometry": {"coordinates":[-82.506012,27.922701],"type":"Point"}
}