{
  "type": "Feature",
  "properties": {
    "iso:country":"US",
    "sg:address":"1 Biscayne Tower",
    "sg:city":"Miami",
    "sg:classifiers":[
        {
            "category":"Bars & Pubs",
            "subcategory":"Nightclub",
            "type":"Food & Drink"
        }
    ],
    "sg:phone":"+1 305 374 1448",
    "sg:postcode":"33131",
    "sg:province":"FL",
    "sg:tags":[
        "nightlife"
    ],
    "wof:name":"Bankers Club the",
    "wof:placetype":"venue"
},
  "geometry": {"coordinates":[-80.187698,25.774401],"type":"Point"}
}