{
  "type": "Feature",
  "properties": {
    "iso:country":"US",
    "sg:address":"900 16th St N",
    "sg:city":"Jacksonville Bch",
    "sg:classifiers":[
        {
            "category":"Retail",
            "subcategory":"Auto Repair",
            "type":"Services"
        }
    ],
    "sg:phone":"+1 904 246 0282",
    "sg:postcode":"32250",
    "sg:province":"FL",
    "sg:tags":[
        "automotive",
        "restoration",
        "automobile",
        "classic"
    ],
    "wof:name":"Dave's Deluxe Restorative Svc",
    "wof:placetype":"venue"
},
  "geometry": {"coordinates":[-81.40724299999999,30.295263],"type":"Point"}
}