{
  "type": "Feature",
  "properties": {
    "iso:country":"US",
    "sg:address":"511 SW 16th Ave",
    "sg:city":"Miami",
    "sg:classifiers":[
        {
            "category":"Real Estate",
            "subcategory":"Real Estate Services",
            "type":"Services"
        },
        {
            "category":"Real Estate",
            "subcategory":"Real Estate Agent",
            "type":"Services"
        }
    ],
    "sg:phone":"+1 305 305 0080",
    "sg:postcode":"33135",
    "sg:province":"FL",
    "sg:tags":[
        "management"
    ],
    "wof:name":"Buyon Realty",
    "wof:placetype":"venue"
},
  "geometry": {"coordinates":[-80.221204,25.768344],"type":"Point"}
}