{
  "type": "Feature",
  "properties": {
    "iso:country":"US",
    "sg:address":"3440 Conway Blvd",
    "sg:city":"Port Charlotte",
    "sg:classifiers":[
        {
            "category":"Organizations",
            "subcategory":"Community Association",
            "type":"Services"
        }
    ],
    "sg:phone":"+1 941 625 6164",
    "sg:postcode":"33952",
    "sg:province":"FL",
    "sg:tags":[
        "to",
        "parent",
        "family",
        "social"
    ],
    "wof:name":"Big Brothers of Charlotte Cnty",
    "wof:placetype":"venue"
},
  "geometry": {"coordinates":[-82.088931,26.976208],"type":"Point"}
}