{
  "type": "Feature",
  "properties": {
    "iso:country":"US",
    "sg:address":"1738 S Red Rd",
    "sg:city":"Miami",
    "sg:classifiers":[
        {
            "category":"Travel",
            "subcategory":"Travel Agent",
            "type":"Entertainment"
        }
    ],
    "sg:phone":"+1 305 661 2217",
    "sg:postcode":"33155",
    "sg:province":"FL",
    "sg:tags":[
        "agency",
        "bureau"
    ],
    "wof:name":"D & D World Travel",
    "wof:placetype":"venue"
},
  "geometry": {"coordinates":[-80.287555,25.755364],"type":"Point"}
}