{
  "type": "Feature",
  "properties": {
    "iso:country":"US",
    "sg:address":"5914 Forest Grove Blvd",
    "sg:city":"Orlando",
    "sg:classifiers":[
        {
            "category":"Building & Trades",
            "subcategory":"Landscaping Services",
            "type":"Services"
        }
    ],
    "sg:phone":"+1 407 578 7406",
    "sg:postcode":"32808",
    "sg:province":"FL",
    "sg:tags":[
        "landscape"
    ],
    "wof:name":"Landscape Development & Maint",
    "wof:placetype":"venue"
},
  "geometry": {"coordinates":[-81.462264,28.592166],"type":"Point"}
}