{
  "type": "Feature",
  "properties": {
    "iso:country":"US",
    "sg:address":"44 Algonquin Ct",
    "sg:city":"Marco Island",
    "sg:classifiers":[
        {
            "category":"Real Estate",
            "subcategory":"Real Estate Agent",
            "type":"Services"
        }
    ],
    "sg:phone":"+1 239 389 0282",
    "sg:postcode":"34145",
    "sg:province":"FL",
    "wof:name":"Bonsall Realty",
    "wof:placetype":"venue"
},
  "geometry": {"coordinates":[-81.70372500000001,25.93691],"type":"Point"}
}