{
  "type": "Feature",
  "properties": {
    "addr:full":"14508 Perdido Key Dr Pensacola FL 32507",
    "addr:housenumber":"14508",
    "addr:postcode":"32507",
    "addr:street":"Perdido Key Dr",
    "iso:country":"US",
    "sg:address":"14508 Perdido Key Dr",
    "sg:city":"Pensacola",
    "sg:classifiers":[
        {
            "category":"Real Estate",
            "subcategory":"Real Estate Agent",
            "type":"Services"
        }
    ],
    "sg:phone":"+1 850 492 4632",
    "sg:postcode":"32507",
    "sg:province":"FL",
    "sg:website":"www.aquaticrealty.com",
    "wof:name":"Aquatic Realty",
    "wof:placetype":"venue"
},
  "geometry": {"coordinates":[-87.446619,30.294797],"type":"Point"}
}