{
  "type": "Feature",
  "properties": {
    "addr:full":"619 Highland Ave Largo FL 33770",
    "addr:housenumber":"619",
    "addr:postcode":"33770",
    "addr:street":"Highland Ave",
    "iso:country":"US",
    "sg:address":"619 Highland Ave",
    "sg:city":"Largo",
    "sg:classifiers":[
        {
            "category":"Professional",
            "subcategory":"Accounting & Tax Preparation",
            "type":"Services"
        }
    ],
    "sg:phone":"+1 727 586 0479",
    "sg:postcode":"33770",
    "sg:province":"FL",
    "wof:name":"Deyoung & Associates",
    "wof:placetype":"venue"
},
  "geometry": {"coordinates":[-82.77501599999999,27.922602],"type":"Point"}
}