{
  "type": "Feature",
  "properties": {
    "addr:full":"509 Wilbur St Brandon FL 33511",
    "addr:housenumber":"509",
    "addr:postcode":"33511",
    "addr:street":"Wilbur St",
    "iso:country":"US",
    "sg:address":"509 Wilbur St",
    "sg:city":"Brandon",
    "sg:classifiers":[
        {
            "category":"Building & Trades",
            "subcategory":"Construction",
            "type":"Services"
        }
    ],
    "sg:phone":"+1 813 661 4495",
    "sg:postcode":"33511",
    "sg:province":"FL",
    "sg:tags":[
        "general",
        "contractor"
    ],
    "wof:name":"Complete Development",
    "wof:placetype":"venue"
},
  "geometry": {"coordinates":[-82.27771300000001,27.936304],"type":"Point"}
}