{
  "type": "Feature",
  "properties": {
    "addr:full":"1425 Caddell Dr Jacksonville FL 32217",
    "addr:housenumber":"1425",
    "addr:postcode":"32217",
    "addr:street":"Caddell Dr",
    "iso:country":"US",
    "sg:address":"1425 Caddell Dr",
    "sg:city":"Jacksonville",
    "sg:classifiers":[
        {
            "category":"Shopping",
            "subcategory":"Books",
            "type":"Retail Goods"
        }
    ],
    "sg:phone":"+1 904 733 3309",
    "sg:postcode":"32217",
    "sg:province":"FL",
    "wof:name":"Exchange Books Online Inc",
    "wof:placetype":"venue"
},
  "geometry": {"coordinates":[-81.64680300000001,30.258716],"type":"Point"}
}