{
  "type": "Feature",
  "properties": {
    "addr:full":"411 SW 2 Ave Gainesville FL 32601",
    "addr:housenumber":"411",
    "addr:postcode":"32601",
    "addr:street":"Sw 2 Ave",
    "iso:country":"US",
    "sg:address":"411 SW 2 Ave",
    "sg:city":"Gainesville",
    "sg:classifiers":[
        {
            "category":"Personal",
            "subcategory":"Beauty Salon",
            "type":"Services"
        }
    ],
    "sg:phone":"+1 352 378 0231",
    "sg:postcode":"32601",
    "sg:province":"FL",
    "sg:website":"www.scissorshairsalon.com",
    "wof:name":"Scissors",
    "wof:placetype":"venue"
},
  "geometry": {"coordinates":[-82.32867400000001,29.650192],"type":"Point"}
}