{
  "type": "Feature",
  "properties": {
    "iso:country":"US",
    "sg:address":"5644 Olympia St",
    "sg:city":"New Port Richey",
    "sg:classifiers":[
        {
            "category":"Building & Trades",
            "subcategory":"Cleaning & Sanitation",
            "type":"Services"
        }
    ],
    "sg:phone":"+1 727 687 7042",
    "sg:postcode":"34652",
    "sg:province":"FL",
    "sg:tags":[
        "property",
        "maintenance"
    ],
    "wof:name":"Thomas Ciarrochi",
    "wof:placetype":"venue"
},
  "geometry": {"coordinates":[-82.720885,28.218854],"type":"Point"}
}