{
  "type": "Feature",
  "properties": {
    "iso:country":"US",
    "sg:address":"102 NE 2nd St",
    "sg:city":"Boca Raton",
    "sg:classifiers":[
        {
            "category":"Banks & Credit Unions",
            "subcategory":"Financial Services",
            "type":"Services"
        }
    ],
    "sg:phone":"+1 561 347 7143",
    "sg:postcode":"33432",
    "sg:province":"FL",
    "sg:tags":[
        "investment",
        "closed"
    ],
    "wof:name":"Casino Development",
    "wof:placetype":"venue"
},
  "geometry": {"coordinates":[-80.08376699999999,26.352291],"type":"Point"}
}