{
  "type": "Feature",
  "properties": {
    "iso:country":"US",
    "sg:address":"1235 SE 3rd St",
    "sg:city":"Cape Coral",
    "sg:classifiers":[
        {
            "category":"Building & Trades",
            "subcategory":"Construction",
            "type":"Services"
        }
    ],
    "sg:phone":"+1 239 574 1708",
    "sg:postcode":"33990",
    "sg:province":"FL",
    "sg:tags":[
        "hanging",
        "painter",
        "contractor"
    ],
    "wof:name":"Hilton Painting Inc",
    "wof:placetype":"venue"
},
  "geometry": {"coordinates":[-81.948882,26.646596],"type":"Point"}
}