{
  "type": "Feature",
  "properties": {
    "addr:full":"5319 NW 35th Ter Fort Lauderdale FL 33309",
    "addr:housenumber":"5319",
    "addr:postcode":"33309",
    "addr:street":"Nw 35Th Ter",
    "iso:country":"US",
    "sg:address":"5319 NW 35th Ter",
    "sg:city":"Fort Lauderdale",
    "sg:classifiers":[
        {
            "category":"Manufacturing",
            "subcategory":"Chemicals & Compounds",
            "type":"Manufacturing & Wholesale Goods"
        }
    ],
    "sg:phone":"+1 954 486 4590",
    "sg:postcode":"33309",
    "sg:province":"FL",
    "sg:tags":[
        "pharmaceutical",
        "product"
    ],
    "wof:name":"Kirk Pharmaceuticals LLC",
    "wof:placetype":"venue"
},
  "geometry": {"coordinates":[-80.198275,26.190417],"type":"Point"}
}