{
  "type": "Feature",
  "properties": {
    "addr:full":"10109 Woodsong Way Tampa FL 33618",
    "addr:housenumber":"10109",
    "addr:postcode":"33618",
    "addr:street":"Woodsong Way",
    "iso:country":"US",
    "sg:address":"10109 Woodsong Way",
    "sg:city":"Tampa",
    "sg:classifiers":[
        {
            "category":"Health Services",
            "subcategory":"Doctor",
            "type":"Services"
        }
    ],
    "sg:phone":"+1 813 933 2307",
    "sg:postcode":"33618",
    "sg:province":"FL",
    "wof:name":"A L Hernandez DDS",
    "wof:placetype":"venue"
},
  "geometry": {"coordinates":[-82.495907,28.042883],"type":"Point"}
}