{
  "type": "Feature",
  "properties": {
    "iso:country":"US",
    "sg:address":"1221 Brickell Ave Ste 1550",
    "sg:city":"Miami",
    "sg:classifiers":[
        {
            "category":"Banks & Credit Unions",
            "subcategory":"Investment Brokerage",
            "type":"Services"
        }
    ],
    "sg:phone":"+1 305 577 3498",
    "sg:postcode":"33131",
    "sg:province":"FL",
    "sg:tags":[
        "investing"
    ],
    "wof:name":"Bsi Investment Advisors Llc",
    "wof:placetype":"venue"
},
  "geometry": {"coordinates":[-80.191597,25.7621],"type":"Point"}
}