{
  "type": "Feature",
  "properties": {
    "iso:country":"US",
    "sg:address":"8381 Dix Ellis Trl",
    "sg:city":"Jacksonville",
    "sg:classifiers":[
        {
            "category":"Insurance",
            "subcategory":"Insurance Agent",
            "type":"Services"
        }
    ],
    "sg:phone":"+1 904 363 1153",
    "sg:postcode":"32256",
    "sg:province":"FL",
    "wof:name":"Carolina Casualty Insurance Co",
    "wof:placetype":"venue"
},
  "geometry": {"coordinates":[-81.56909400000001,30.214428],"type":"Point"}
}