{
  "type": "Feature",
  "properties": {
    "iso:country":"US",
    "sg:address":"3540 W Prospect Rd",
    "sg:city":"Fort Lauderdale",
    "sg:classifiers":[
        {
            "category":"Shopping",
            "type":"Retail Goods"
        },
        {
            "category":"Wholesale",
            "subcategory":"Electrical",
            "type":"Manufacturing & Wholesale Goods"
        }
    ],
    "sg:phone":"+1 954 486 9400",
    "sg:postcode":"33309",
    "sg:province":"FL",
    "sg:tags":[
        "equipment",
        "supply",
        "electronic",
        "system",
        "telephone"
    ],
    "wof:name":"BCM Teleoptions Inc",
    "wof:placetype":"venue"
},
  "geometry": {"coordinates":[-80.197911,26.195079],"type":"Point"}
}