{
  "type": "Feature",
  "properties": {
    "iso:country":"US",
    "sg:address":"409 Ave F SE",
    "sg:city":"Winter Haven",
    "sg:classifiers":[
        {
            "category":"Wholesale",
            "subcategory":"Machinery & Supplies",
            "type":"Manufacturing & Wholesale Goods"
        }
    ],
    "sg:phone":"+1 863 293 7527",
    "sg:postcode":"33880",
    "sg:province":"FL",
    "sg:tags":[
        "equipment",
        "establishment"
    ],
    "wof:name":"Paul Bridwell Company",
    "wof:placetype":"venue"
},
  "geometry": {"coordinates":[-81.720805,28.015949],"type":"Point"}
}