{
  "type": "Feature",
  "properties": {
    "iso:country":"US",
    "sg:address":"2060 Massachusetts Ave NE",
    "sg:city":"Saint Petersburg",
    "sg:classifiers":[
        {
            "category":"Building & Trades",
            "subcategory":"Construction",
            "type":"Services"
        }
    ],
    "sg:phone":"+1 727 526 0296",
    "sg:postcode":"33703",
    "sg:province":"FL",
    "sg:tags":[
        "house",
        "some",
        "commercial"
    ],
    "wof:name":"Abbey Custom Builders Inc",
    "wof:placetype":"venue"
},
  "geometry": {"coordinates":[-82.596485,27.819537],"type":"Point"}
}