{
  "type": "Feature",
  "properties": {
    "addr:full":"1644 NW 20th St Homestead FL 33030",
    "addr:housenumber":"1644",
    "addr:postcode":"33030",
    "addr:street":"Nw 20Th St",
    "iso:country":"US",
    "sg:address":"1644 NW 20th St",
    "sg:city":"Homestead",
    "sg:classifiers":[
        {
            "category":"Real Estate",
            "subcategory":"Real Estate Agent",
            "type":"Services"
        }
    ],
    "sg:phone":"+1 305 247 9528",
    "sg:postcode":"33030",
    "sg:province":"FL",
    "wof:name":"Vanheusen & Associates Inc",
    "wof:placetype":"venue"
},
  "geometry": {"coordinates":[-80.501058,25.488606],"type":"Point"}
}