{
  "type": "Feature",
  "properties": {
    "iso:country":"US",
    "sg:address":"13260 Immokalee Rd",
    "sg:city":"Naples",
    "sg:classifiers":[
        {
            "category":"Professional",
            "subcategory":"Business Services",
            "type":"Services"
        }
    ],
    "sg:phone":"+1 239 403 7225",
    "sg:postcode":"34120",
    "sg:province":"FL",
    "sg:tags":[
        "packaging"
    ],
    "wof:name":"Xpress Shipping Station",
    "wof:placetype":"venue"
},
  "geometry": {"coordinates":[-81.613606,26.276082],"type":"Point"}
}