{
  "type": "Feature",
  "properties": {
    "iso:country":"US",
    "sg:address":"23150 Fashion Dr. Suite 238",
    "sg:city":"Estero",
    "sg:classifiers":[
        {
            "category":"Professional",
            "subcategory":"Computer Services",
            "type":"Services"
        }
    ],
    "sg:phone":"+1 239 963 8535",
    "sg:postcode":"33928",
    "sg:province":"FL",
    "sg:tags":[
        "real-estate",
        "web2-0"
    ],
    "sg:website":"http://www.agentshield.com/",
    "wof:name":"Agent Shield Technologies",
    "wof:placetype":"venue"
},
  "geometry": {"coordinates":[-81.97995299999999,26.510263],"type":"Point"}
}