{
  "type": "Feature",
  "properties": {
    "iso:country":"US",
    "sg:address":"2326 del Prado Blvd S",
    "sg:city":"Cape Coral",
    "sg:classifiers":[
        {
            "category":"Real Estate",
            "subcategory":"Real Estate Agent",
            "type":"Services"
        }
    ],
    "sg:phone":"+1 239 542 4749",
    "sg:postcode":"33990",
    "sg:province":"FL",
    "wof:name":"David Headd",
    "wof:placetype":"venue"
},
  "geometry": {"coordinates":[-81.94112,26.610458],"type":"Point"}
}