{
  "type": "Feature",
  "properties": {
    "addr:full":"15738 70th Trl N West Palm Beach FL 33418",
    "addr:housenumber":"15738",
    "addr:postcode":"33418",
    "addr:street":"70Th Trl N",
    "iso:country":"US",
    "sg:address":"15738 70th Trl N",
    "sg:city":"West Palm Beach",
    "sg:classifiers":[
        {
            "category":"Building & Trades",
            "subcategory":"Construction",
            "type":"Services"
        }
    ],
    "sg:phone":"+1 561 575 5269",
    "sg:postcode":"33418",
    "sg:province":"FL",
    "sg:tags":[
        "contractor"
    ],
    "wof:name":"Seashore Building Co",
    "wof:placetype":"venue"
},
  "geometry": {"coordinates":[-80.14419700000001,26.907115],"type":"Point"}
}