{
  "type": "Feature",
  "properties": {
    "addr:full":"7620 NW 21st St Sunrise FL 33322",
    "addr:housenumber":"7620",
    "addr:postcode":"33322",
    "addr:street":"Nw 21St St",
    "iso:country":"US",
    "sg:address":"7620 NW 21st St",
    "sg:city":"Sunrise",
    "sg:classifiers":[
        {
            "category":"Building & Trades",
            "subcategory":"Construction",
            "type":"Services"
        }
    ],
    "sg:phone":"+1 954 533 4681",
    "sg:postcode":"33322",
    "sg:province":"FL",
    "sg:tags":[
        "restoration",
        "cleaning",
        "patio",
        "deck"
    ],
    "wof:name":"Dave Ramcharan Pressure Clnng",
    "wof:placetype":"venue"
},
  "geometry": {"coordinates":[-80.245172,26.152164],"type":"Point"}
}