{
  "type": "Feature",
  "properties": {
    "iso:country":"US",
    "sg:address":"902 Solomon Dairy Rd",
    "sg:city":"Quincy",
    "sg:classifiers":[
        {
            "category":"Manufacturing",
            "subcategory":"Glass & Minerals",
            "type":"Manufacturing & Wholesale Goods"
        }
    ],
    "sg:phone":"+1 850 875 3184",
    "sg:postcode":"32352",
    "sg:province":"FL",
    "sg:tags":[
        "product",
        "mfg"
    ],
    "wof:name":"Bischoffs Glasswork Studios",
    "wof:placetype":"venue"
},
  "geometry": {"coordinates":[-84.60888,30.609409],"type":"Point"}
}