{
  "type": "Feature",
  "properties": {
    "addr:full":"278 Towne Center Cir Sanford FL 32771",
    "addr:housenumber":"278",
    "addr:postcode":"32771",
    "addr:street":"Towne Center Cir",
    "iso:country":"US",
    "sg:address":"278 Towne Center Cir",
    "sg:city":"Sanford",
    "sg:classifiers":[
        {
            "category":"Bakery",
            "type":"Food & Drink"
        }
    ],
    "sg:menulink":"http://www.allmenus.com/fl/sanford/223851-cinnabon/menu/",
    "sg:phone":"+1 407 322 7969",
    "sg:postcode":"32771",
    "sg:province":"FL",
    "sg:tags":[
        "american",
        "pastry"
    ],
    "wof:name":"Cinnabon",
    "wof:placetype":"venue"
},
  "geometry": {"coordinates":[-81.33990799999999,28.805764],"type":"Point"}
}