{
  "type": "Feature",
  "properties": {
    "iso:country":"US",
    "sg:address":"13638 Sunset Lakes Cir",
    "sg:city":"Winter Garden",
    "sg:classifiers":[
        {
            "category":"Banks & Credit Unions",
            "subcategory":"Financial Services",
            "type":"Services"
        }
    ],
    "sg:phone":"+1 407 654 6846",
    "sg:postcode":"34787",
    "sg:province":"FL",
    "sg:tags":[
        "business"
    ],
    "wof:name":"Aquisition Capital Group Inc",
    "wof:placetype":"venue"
},
  "geometry": {"coordinates":[-81.584661,28.504257],"type":"Point"}
}