{
  "type": "Feature",
  "properties": {
    "iso:country":"US",
    "sg:address":"1325 Osceola Tram Rd",
    "sg:city":"Osteen",
    "sg:classifiers":[
        {
            "category":"Utilities",
            "subcategory":"Telephone",
            "type":"Services"
        }
    ],
    "sg:phone":"+1 407 688 2827",
    "sg:postcode":"32764",
    "sg:province":"FL",
    "sg:tags":[
        "telecommunication"
    ],
    "wof:name":"American Tower Corp",
    "wof:placetype":"venue"
},
  "geometry": {"coordinates":[-81.148343,28.897717],"type":"Point"}
}