{
  "type": "Feature",
  "properties": {
    "addr:full":"1550 S Semoran Blvd Orlando FL 32807",
    "addr:housenumber":"1550",
    "addr:postcode":"32807",
    "addr:street":"S Semoran Blvd",
    "iso:country":"US",
    "sg:address":"1550 S Semoran Blvd",
    "sg:city":"Orlando",
    "sg:classifiers":[
        {
            "category":"Real Estate",
            "subcategory":"Real Estate Services",
            "type":"Services"
        }
    ],
    "sg:phone":"+1 407 802 5521",
    "sg:postcode":"32807",
    "sg:province":"FL",
    "sg:tags":[
        "inspection"
    ],
    "wof:name":"Advance Property Inspection",
    "wof:placetype":"venue"
},
  "geometry": {"coordinates":[-81.31041,28.524636],"type":"Point"}
}