{
  "type": "Feature",
  "properties": {
    "iso:country":"US",
    "sg:address":"3029 Reynolds Rd",
    "sg:city":"Lakeland",
    "sg:classifiers":[
        {
            "category":"Wholesale",
            "subcategory":"Machinery & Supplies",
            "type":"Manufacturing & Wholesale Goods"
        },
        {
            "category":"Building & Trades",
            "subcategory":"Equipment Rental",
            "type":"Services"
        }
    ],
    "sg:phone":"+1 863 665 1782",
    "sg:postcode":"33803",
    "sg:province":"FL",
    "sg:tags":[
        "heavy",
        "business",
        "derrick",
        "rent",
        "crane",
        "special"
    ],
    "wof:name":"Lakeland Crane Corp",
    "wof:placetype":"venue"
},
  "geometry": {"coordinates":[-81.89131,28.009058],"type":"Point"}
}