{
  "type": "Feature",
  "properties": {
    "iso:country":"US",
    "sg:address":"9830 New York Ave",
    "sg:city":"Hudson",
    "sg:classifiers":[
        {
            "category":"Personal",
            "subcategory":"Tanning Parlor",
            "type":"Services"
        }
    ],
    "sg:phone":"+1 727 863 1263",
    "sg:postcode":"34667",
    "sg:province":"FL",
    "sg:tags":[
        "salon"
    ],
    "wof:name":"Ta Tan",
    "wof:placetype":"venue"
},
  "geometry": {"coordinates":[-82.653255,28.375083],"type":"Point"}
}