{
  "type": "Feature",
  "properties": {
    "iso:country":"US",
    "sg:address":"12 NW Pine Ave",
    "sg:city":"Ocala",
    "sg:classifiers":[
        {
            "category":"Autos & Motor Vehicles",
            "subcategory":"Auto Supplies",
            "type":"Retail Goods"
        }
    ],
    "sg:phone":"+1 352 622 0075",
    "sg:postcode":"34475",
    "sg:province":"FL",
    "sg:tags":[
        "tire"
    ],
    "wof:name":"Tee Pee Tire Inc Auto Care Ctr",
    "wof:placetype":"venue"
},
  "geometry": {"coordinates":[-82.140432,29.187789],"type":"Point"}
}