{
  "type": "Feature",
  "properties": {
    "addr:full":"4964 Eaglesmere Dr Orlando FL 32819",
    "addr:housenumber":"4964",
    "addr:postcode":"32819",
    "addr:street":"Eaglesmere Dr",
    "iso:country":"US",
    "sg:address":"4964 Eaglesmere Dr",
    "sg:city":"Orlando",
    "sg:classifiers":[
        {
            "category":"Freight",
            "type":"Transportation"
        }
    ],
    "sg:phone":"+1 407 421 6625",
    "sg:postcode":"32819",
    "sg:province":"FL",
    "wof:name":"Flc Transportation",
    "wof:placetype":"venue"
},
  "geometry": {"coordinates":[-81.462727,28.488854],"type":"Point"}
}