{
  "type": "Feature",
  "properties": {
    "addr:full":"2216 Hollywood Blvd Hollywood FL 33020",
    "addr:housenumber":"2216",
    "addr:postcode":"33020",
    "addr:street":"Hollywood Blvd",
    "iso:country":"US",
    "sg:address":"2216 Hollywood Blvd",
    "sg:city":"Hollywood",
    "sg:classifiers":[
        {
            "category":"Health Services",
            "subcategory":"Chiropractor",
            "type":"Services"
        }
    ],
    "sg:phone":"+1 954 924 9404",
    "sg:postcode":"33020",
    "sg:province":"FL",
    "wof:name":"John S Virga Dcpa",
    "wof:placetype":"venue"
},
  "geometry": {"coordinates":[-80.154212,26.011229],"type":"Point"}
}