{
  "type": "Feature",
  "properties": {
    "iso:country":"US",
    "sg:address":"1666 W 31st Pl",
    "sg:city":"Hialeah",
    "sg:classifiers":[
        {
            "category":"Restaurant",
            "type":"Food & Drink"
        }
    ],
    "sg:phone":"+1 305 557 7143",
    "sg:postcode":"33012",
    "sg:province":"FL",
    "sg:tags":[
        "eating"
    ],
    "wof:name":"Clarita's Cafe",
    "wof:placetype":"venue"
},
  "geometry": {"coordinates":[-80.31630199999999,25.850167],"type":"Point"}
}