{
  "type": "Feature",
  "properties": {
    "iso:country":"US",
    "sg:address":"224 N Main St",
    "sg:city":"Bushnell",
    "sg:classifiers":[
        {
            "category":"Shopping",
            "subcategory":"Used Merchandise",
            "type":"Retail Goods"
        }
    ],
    "sg:phone":"+1 352 793 2466",
    "sg:postcode":"33513",
    "sg:province":"FL",
    "sg:tags":[
        "antique"
    ],
    "wof:name":"Jacobik Antique Gallery",
    "wof:placetype":"venue"
},
  "geometry": {"coordinates":[-82.11274899999999,28.66379],"type":"Point"}
}