{
  "type": "Feature",
  "properties": {
    "iso:country":"US",
    "sg:address":"10503 San Jose Blvd",
    "sg:city":"Jacksonville",
    "sg:classifiers":[
        {
            "category":"Sports & Exercise",
            "subcategory":"Gym",
            "type":"Entertainment"
        }
    ],
    "sg:phone":"+1 904 262 4801",
    "sg:postcode":"32257",
    "sg:province":"FL",
    "sg:tags":[
        "club",
        "health",
        "studio",
        "gymnasium"
    ],
    "wof:name":"First Coast Fitness",
    "wof:placetype":"venue"
},
  "geometry": {"coordinates":[-81.627774,30.187213],"type":"Point"}
}