{
  "type": "Feature",
  "properties": {
    "addr:full":"505 E Palm Ave Tampa FL 33602",
    "addr:housenumber":"505",
    "addr:postcode":"33602",
    "addr:street":"E Palm Ave",
    "iso:country":"US",
    "sg:address":"505 E Palm Ave",
    "sg:city":"Tampa",
    "sg:classifiers":[
        {
            "category":"Organizations",
            "subcategory":"Religious Organization",
            "type":"Services"
        }
    ],
    "sg:phone":"+1 813 229 7276",
    "sg:postcode":"33602",
    "sg:province":"FL",
    "wof:name":"Baptist Fellowship Bible",
    "wof:placetype":"venue"
},
  "geometry": {"coordinates":[-82.45453999999999,27.962162],"type":"Point"}
}