{
  "type": "Feature",
  "properties": {
    "addr:full":"319 Borada Rd Sanford FL 32773",
    "addr:housenumber":"319",
    "addr:postcode":"32773",
    "addr:street":"Borada Rd",
    "iso:country":"US",
    "sg:address":"319 Borada Rd",
    "sg:city":"Sanford",
    "sg:classifiers":[
        {
            "category":"Sports & Exercise",
            "subcategory":"Gym",
            "type":"Entertainment"
        }
    ],
    "sg:phone":"+1 407 617 4419",
    "sg:postcode":"32773",
    "sg:province":"FL",
    "sg:tags":[
        "club",
        "health",
        "studio",
        "gymnasium"
    ],
    "wof:name":"Advanced Personal Training",
    "wof:placetype":"venue"
},
  "geometry": {"coordinates":[-81.29910099999999,28.76797],"type":"Point"}
}