{
  "type": "Feature",
  "properties": {
    "iso:country":"US",
    "sg:address":"9174 NW 44th Ct",
    "sg:city":"Coral Springs",
    "sg:classifiers":[
        {
            "category":"Professional",
            "subcategory":"Advertising",
            "type":"Services"
        }
    ],
    "sg:phone":"+1 954 341 5151",
    "sg:postcode":"33065",
    "sg:province":"FL",
    "sg:tags":[
        "guide"
    ],
    "wof:name":"Bullseye Local Mktng Inc",
    "wof:placetype":"venue"
},
  "geometry": {"coordinates":[-80.247691,26.284486],"type":"Point"}
}