{
  "type": "Feature",
  "properties": {
    "iso:country":"US",
    "sg:address":"2568 Albany Dr",
    "sg:city":"Kissimmee",
    "sg:classifiers":[
        {
            "category":"Building & Trades",
            "subcategory":"Construction",
            "type":"Services"
        }
    ],
    "sg:phone":"+1 407 846 9182",
    "sg:postcode":"34758",
    "sg:province":"FL",
    "sg:tags":[
        "house"
    ],
    "wof:name":"John Neisius Home Repairs",
    "wof:placetype":"venue"
},
  "geometry": {"coordinates":[-81.48590299999999,28.228287],"type":"Point"}
}