{
  "type": "Feature",
  "properties": {
    "iso:country":"US",
    "sg:address":"2017 Alafia Oaks Dr",
    "sg:city":"Valrico",
    "sg:classifiers":[
        {
            "category":"Professional",
            "subcategory":"Printing & Photocopies",
            "type":"Services"
        }
    ],
    "sg:phone":"+1 813 205 7296",
    "sg:postcode":"33596",
    "sg:province":"FL",
    "sg:tags":[
        "lithographer"
    ],
    "wof:name":"Print This",
    "wof:placetype":"venue"
},
  "geometry": {"coordinates":[-82.25134199999999,27.872883],"type":"Point"}
}