{
  "type": "Feature",
  "properties": {
    "iso:country":"US",
    "sg:address":"6863 Hanging Moss Rd",
    "sg:city":"Orlando",
    "sg:classifiers":[
        {
            "category":"Manufacturing",
            "subcategory":"Metals",
            "type":"Manufacturing & Wholesale Goods"
        }
    ],
    "sg:phone":"+1 407 677 5137",
    "sg:postcode":"32807",
    "sg:province":"FL",
    "sg:tags":[
        "ware",
        "sheet",
        "mfg",
        "wood",
        "ho",
        "sanitary",
        "metalwork"
    ],
    "wof:name":"B & W Custom Stainless Inc",
    "wof:placetype":"venue"
},
  "geometry": {"coordinates":[-81.29607799999999,28.579129],"type":"Point"}
}