{
  "type": "Feature",
  "properties": {
    "addr:full":"3001 S Atlantic Ave New Smyrna Beach FL 32169",
    "addr:housenumber":"3001",
    "addr:postcode":"32169",
    "addr:street":"S Atlantic Ave",
    "iso:country":"US",
    "sg:address":"3001 S Atlantic Ave",
    "sg:city":"New Smyrna Beach",
    "sg:classifiers":[
        {
            "category":"Real Estate",
            "subcategory":"Real Estate Operator",
            "type":"Services"
        }
    ],
    "sg:phone":"+1 386 427 6602",
    "sg:postcode":"32169",
    "sg:province":"FL",
    "sg:tags":[
        "condominium"
    ],
    "wof:name":"Las Brisas Condominiums",
    "wof:placetype":"venue"
},
  "geometry": {"coordinates":[-80.88246100000001,29.014097],"type":"Point"}
}