{
  "type": "Feature",
  "properties": {
    "iso:country":"US",
    "sg:address":"5040 Shirley Ave",
    "sg:city":"Jacksonville",
    "sg:classifiers":[
        {
            "category":"Shopping",
            "subcategory":"Clothing, Apparel, & Fashions",
            "type":"Retail Goods"
        }
    ],
    "sg:phone":"+1 904 384 2208",
    "sg:postcode":"32210",
    "sg:province":"FL",
    "sg:tags":[
        "alteration"
    ],
    "wof:name":"Alexander's Tailoring",
    "wof:placetype":"venue"
},
  "geometry": {"coordinates":[-81.731719,30.283871],"type":"Point"}
}