{
  "type": "Feature",
  "properties": {
    "addr:full":"2323 S Miami Ave Miami FL 33129",
    "addr:housenumber":"2323",
    "addr:postcode":"33129",
    "addr:street":"S Miami Ave",
    "iso:country":"US",
    "sg:address":"2323 S Miami Ave",
    "sg:city":"Miami",
    "sg:classifiers":[
        {
            "category":"Manufacturing",
            "subcategory":"Printing",
            "type":"Manufacturing & Wholesale Goods"
        }
    ],
    "sg:phone":"+1 305 858 3325",
    "sg:postcode":"33129",
    "sg:province":"FL",
    "sg:tags":[
        "publishing"
    ],
    "wof:name":"St Francis Music Publications",
    "wof:placetype":"venue"
},
  "geometry": {"coordinates":[-80.202833,25.752603],"type":"Point"}
}