{
  "type": "Feature",
  "properties": {
    "addr:full":"10307 Phoenix Ln Howey In The Hills FL 34737",
    "addr:housenumber":"10307",
    "addr:postcode":"34737",
    "addr:street":"Phoenix Ln",
    "iso:country":"US",
    "sg:address":"10307 Phoenix Ln",
    "sg:city":"Howey In The Hills",
    "sg:classifiers":[
        {
            "category":"Retail",
            "subcategory":"Animal Services",
            "type":"Services"
        }
    ],
    "sg:phone":"+1 352 429 9639",
    "sg:postcode":"34737",
    "sg:province":"FL",
    "wof:name":"Birds and Animals",
    "wof:placetype":"venue"
},
  "geometry": {"coordinates":[-81.78267200000001,28.670675],"type":"Point"}
}