{
  "type": "Feature",
  "properties": {
    "iso:country":"US",
    "sg:address":"451 W Gaines St",
    "sg:city":"Tallahassee",
    "sg:classifiers":[
        {
            "category":"Manufacturing",
            "subcategory":"Retail Goods",
            "type":"Manufacturing & Wholesale Goods"
        },
        {
            "category":"Shopping",
            "subcategory":"Gifts & Souvenirs",
            "type":"Retail Goods"
        }
    ],
    "sg:phone":"+1 850 877 7440",
    "sg:postcode":"32301",
    "sg:province":"FL",
    "sg:tags":[
        "balloon",
        "artist",
        "product",
        "mfg"
    ],
    "wof:name":"Margos Balloons & Baskets",
    "wof:placetype":"venue"
},
  "geometry": {"coordinates":[-84.28661099999999,30.43542],"type":"Point"}
}