{
  "type": "Feature",
  "properties": {
    "iso:country":"US",
    "sg:address":"1719 J and C Blvd",
    "sg:city":"Naples",
    "sg:classifiers":[
        {
            "category":"Home & Garden",
            "subcategory":"Building Materials",
            "type":"Retail Goods"
        }
    ],
    "sg:phone":"+1 239 593 4848",
    "sg:postcode":"34109",
    "sg:province":"FL",
    "sg:tags":[
        "plumbing",
        "fixture",
        "supply"
    ],
    "wof:name":"Naples Kitchen & Bath",
    "wof:placetype":"venue"
},
  "geometry": {"coordinates":[-81.782038,26.223791],"type":"Point"}
}