{
  "type": "Feature",
  "properties": {
    "iso:country":"US",
    "sg:address":"331 Michigan Ave",
    "sg:city":"Saint Cloud",
    "sg:classifiers":[
        {
            "category":"Building & Trades",
            "subcategory":"Landscaping Services",
            "type":"Services"
        }
    ],
    "sg:phone":"+1 407 891 0945",
    "sg:postcode":"34769",
    "sg:province":"FL",
    "wof:name":"Turf Dynamics",
    "wof:placetype":"venue"
},
  "geometry": {"coordinates":[-81.276606,28.255498],"type":"Point"}
}