{
  "type": "Feature",
  "properties": {
    "addr:full":"25215 NW 122nd Ave High Springs FL 32643",
    "addr:housenumber":"25215",
    "addr:postcode":"32643",
    "addr:street":"Nw 122Nd Ave",
    "iso:country":"US",
    "sg:address":"25215 NW 122nd Ave",
    "sg:city":"High Springs",
    "sg:classifiers":[
        {
            "category":"Building & Trades",
            "subcategory":"Landscaping Services",
            "type":"Services"
        }
    ],
    "sg:phone":"+1 386 454 5595",
    "sg:postcode":"32643",
    "sg:province":"FL",
    "wof:name":"Terra Verde Grounds Management",
    "wof:placetype":"venue"
},
  "geometry": {"coordinates":[-82.608462,29.766965],"type":"Point"}
}