{
  "type": "Feature",
  "properties": {
    "addr:full":"1095 N US Hwy 1 Ormond Beach FL 32174",
    "addr:housenumber":"1095",
    "addr:postcode":"32174",
    "addr:street":"N Us Hwy 1",
    "iso:country":"US",
    "sg:address":"1095 N US Hwy 1",
    "sg:city":"Ormond Beach",
    "sg:classifiers":[
        {
            "category":"Personal",
            "subcategory":"Beauty Salon",
            "type":"Services"
        }
    ],
    "sg:phone":"+1 386 615 8123",
    "sg:postcode":"32174",
    "sg:province":"FL",
    "wof:name":"John The Hairdresser/Salon 101",
    "wof:placetype":"venue"
},
  "geometry": {"coordinates":[-81.10378,29.314149],"type":"Point"}
}