{
  "type": "Feature",
  "properties": {
    "iso:country":"US",
    "sg:address":"6960 Tampico Rd S",
    "sg:city":"Jacksonville",
    "sg:classifiers":[
        {
            "category":"Building & Trades",
            "subcategory":"Construction",
            "type":"Services"
        }
    ],
    "sg:phone":"+1 904 772 1507",
    "sg:postcode":"32244",
    "sg:province":"FL",
    "sg:tags":[
        "carpentry",
        "contractor"
    ],
    "wof:name":"CB Custom Interior Trim LLC",
    "wof:placetype":"venue"
},
  "geometry": {"coordinates":[-81.760946,30.241653],"type":"Point"}
}