{
  "type": "Feature",
  "properties": {
    "iso:country":"US",
    "sg:address":"4615 NW 72nd Ave",
    "sg:city":"Miami",
    "sg:classifiers":[
        {
            "category":"Professional",
            "type":"Services"
        }
    ],
    "sg:phone":"+1 305 513 0665",
    "sg:postcode":"33166",
    "sg:province":"FL",
    "sg:tags":[
        "caterer"
    ],
    "wof:name":"Miami Paemmas",
    "wof:placetype":"venue"
},
  "geometry": {"coordinates":[-80.31335,25.815374],"type":"Point"}
}