{
  "type": "Feature",
  "properties": {
    "iso:country":"US",
    "sg:address":"5598 N Orange Blossom Trl",
    "sg:city":"Orlando",
    "sg:classifiers":[
        {
            "category":"Health Services",
            "subcategory":"Chiropractor",
            "type":"Services"
        }
    ],
    "sg:phone":"+1 407 298 0490",
    "sg:postcode":"32810",
    "sg:province":"FL",
    "wof:name":"Rosemont Chiropractic Health & Rehabilitation PA",
    "wof:placetype":"venue"
},
  "geometry": {"coordinates":[-81.427002,28.609501],"type":"Point"}
}