{
  "type": "Feature",
  "properties": {
    "iso:country":"US",
    "sg:address":"1000 N Pace Blvd",
    "sg:city":"Pensacola",
    "sg:classifiers":[
        {
            "category":"Organizations",
            "subcategory":"Community Association",
            "type":"Services"
        }
    ],
    "sg:phone":"+1 850 433 7814",
    "sg:postcode":"32505",
    "sg:province":"FL",
    "wof:name":"Guiding Youth To Success Inc",
    "wof:placetype":"venue"
},
  "geometry": {"coordinates":[-87.241089,30.423657],"type":"Point"}
}