{
  "type": "Feature",
  "properties": {
    "iso:country":"US",
    "sg:address":"102 Bay Tree Dr",
    "sg:city":"Destin",
    "sg:classifiers":[
        {
            "category":"Organizations",
            "subcategory":"Community Association",
            "type":"Services"
        }
    ],
    "sg:phone":"+1 850 650 6916",
    "sg:postcode":"32550",
    "sg:province":"FL",
    "wof:name":"Buck Byou Twnhouse Owners Assn",
    "wof:placetype":"venue"
},
  "geometry": {"coordinates":[-86.348609,30.38193],"type":"Point"}
}