{
  "type": "Feature",
  "properties": {
    "addr:full":"1504 US Hwy 90 W Defuniak Springs FL 32433",
    "addr:housenumber":"1504",
    "addr:postcode":"32433",
    "addr:street":"Us Hwy 90 W",
    "iso:country":"US",
    "sg:address":"1504 US Hwy 90 W",
    "sg:city":"Defuniak Springs",
    "sg:classifiers":[
        {
            "category":"Freight",
            "type":"Transportation"
        }
    ],
    "sg:phone":"+1 850 892 3612",
    "sg:postcode":"32433",
    "sg:province":"FL",
    "sg:tags":[
        "commercial",
        "storage"
    ],
    "wof:name":"Scott's Mini-Warehouses",
    "wof:placetype":"venue"
},
  "geometry": {"coordinates":[-86.142793,30.732527],"type":"Point"}
}