{
  "type": "Feature",
  "properties": {
    "iso:country":"US",
    "sg:address":"13365 NW 8th St",
    "sg:city":"Miami",
    "sg:classifiers":[
        {
            "category":"Building & Trades",
            "subcategory":"Pest Control",
            "type":"Services"
        }
    ],
    "sg:phone":"+1 305 207 3373",
    "sg:postcode":"33182",
    "sg:province":"FL",
    "wof:name":"Sierra Pest Control",
    "wof:placetype":"venue"
},
  "geometry": {"coordinates":[-80.410402,25.776152],"type":"Point"}
}