{
  "type": "Feature",
  "properties": {
    "iso:country":"US",
    "sg:address":"1020 SW 75th Ter",
    "sg:city":"Fort Lauderdale",
    "sg:classifiers":[
        {
            "category":"Building & Trades",
            "subcategory":"Construction",
            "type":"Services"
        }
    ],
    "sg:phone":"+1 954 791 4626",
    "sg:postcode":"33317",
    "sg:province":"FL",
    "sg:tags":[
        "contractor"
    ],
    "wof:name":"General Marble Tile Inc",
    "wof:placetype":"venue"
},
  "geometry": {"coordinates":[-80.24917600000001,26.107976],"type":"Point"}
}