{
  "type": "Feature",
  "properties": {
    "addr:full":"4025 W Kennedy Blvd Tampa FL 33609",
    "addr:housenumber":"4025",
    "addr:postcode":"33609",
    "addr:street":"W Kennedy Blvd",
    "iso:country":"US",
    "sg:address":"4025 W Kennedy Blvd",
    "sg:city":"Tampa",
    "sg:classifiers":[
        {
            "category":"Shopping",
            "subcategory":"Optical Goods",
            "type":"Retail Goods"
        }
    ],
    "sg:phone":"+1 813 872 6063",
    "sg:postcode":"33609",
    "sg:province":"FL",
    "wof:name":"Eye Doctors Optical Outlet",
    "wof:placetype":"venue"
},
  "geometry": {"coordinates":[-82.51015,27.944902],"type":"Point"}
}