{
  "type": "Feature",
  "properties": {
    "iso:country":"US",
    "sg:address":"38334 Palm Grove Dr",
    "sg:city":"Zephyrhills",
    "sg:classifiers":[
        {
            "category":"Freight",
            "type":"Transportation"
        }
    ],
    "sg:phone":"+1 813 997 0259",
    "sg:postcode":"33542",
    "sg:province":"FL",
    "sg:tags":[
        "operator",
        "trucking"
    ],
    "wof:name":"Barrows Ward Trucking",
    "wof:placetype":"venue"
},
  "geometry": {"coordinates":[-82.17990399999999,28.217775],"type":"Point"}
}