{
  "type": "Feature",
  "properties": {
    "addr:full":"3120 Sulstone Dr Punta Gorda FL 33983",
    "addr:housenumber":"3120",
    "addr:postcode":"33983",
    "addr:street":"Sulstone Dr",
    "iso:country":"US",
    "sg:address":"3120 Sulstone Dr",
    "sg:city":"Punta Gorda",
    "sg:classifiers":[
        {
            "category":"Wholesale",
            "subcategory":"Electrical",
            "type":"Manufacturing & Wholesale Goods"
        }
    ],
    "sg:phone":"+1 941 624 4521",
    "sg:postcode":"33983",
    "sg:province":"FL",
    "sg:tags":[
        "sound",
        "equipment",
        "system"
    ],
    "wof:name":"D B Sound & Lighting Systems",
    "wof:placetype":"venue"
},
  "geometry": {"coordinates":[-82.007361,26.984685],"type":"Point"}
}