{
  "type": "Feature",
  "properties": {
    "addr:full":"318 N Main St Trenton FL 32693",
    "addr:housenumber":"318",
    "addr:postcode":"32693",
    "addr:street":"N Main St",
    "iso:country":"US",
    "sg:address":"318 N Main St",
    "sg:city":"Trenton",
    "sg:classifiers":[
        {
            "category":"Banks & Credit Unions",
            "subcategory":"Investment Brokerage",
            "type":"Services"
        }
    ],
    "sg:phone":"+1 352 463 2550",
    "sg:postcode":"32693",
    "sg:province":"FL",
    "sg:tags":[
        "consultant",
        "planning",
        "financial"
    ],
    "wof:name":"Retirement Analysts",
    "wof:placetype":"venue"
},
  "geometry": {"coordinates":[-82.81826599999999,29.615313],"type":"Point"}
}