{
  "type": "Feature",
  "properties": {
    "iso:country":"US",
    "sg:address":"1544 Venera Ave",
    "sg:city":"Miami",
    "sg:classifiers":[
        {
            "category":"Health Services",
            "subcategory":"Health Practitioner",
            "type":"Services"
        }
    ],
    "sg:phone":"+1 305 666 7116",
    "sg:postcode":"33146",
    "sg:province":"FL",
    "wof:name":"Southrn Miami Sprts Med Hand",
    "wof:placetype":"venue"
},
  "geometry": {"coordinates":[-80.284164,25.706661],"type":"Point"}
}