{
  "type": "Feature",
  "properties": {
    "iso:country":"US",
    "sg:address":"1930 Murrell Rd",
    "sg:city":"Rockledge",
    "sg:classifiers":[
        {
            "category":"Home & Garden",
            "subcategory":"Carpets & Floor Coverings",
            "type":"Retail Goods"
        }
    ],
    "sg:phone":"+1 321 452 2603",
    "sg:postcode":"32955",
    "sg:province":"FL",
    "sg:tags":[
        "dealer",
        "rug"
    ],
    "wof:name":"Geronimo's Carpet & Upholstery",
    "wof:placetype":"venue"
},
  "geometry": {"coordinates":[-80.721879,28.323364],"type":"Point"}
}