{
  "type": "Feature",
  "properties": {
    "iso:country":"US",
    "sg:address":"1395 N Federal Hwy",
    "sg:city":"Boca Raton",
    "sg:classifiers":[
        {
            "category":"Organizations",
            "subcategory":"Community Association",
            "type":"Services"
        }
    ],
    "sg:phone":"+1 561 395 9836",
    "sg:postcode":"33432",
    "sg:province":"FL",
    "sg:tags":[
        "fraternal"
    ],
    "wof:name":"Elks Lodge",
    "wof:placetype":"venue"
},
  "geometry": {"coordinates":[-80.081557,26.362929],"type":"Point"}
}