{
  "type": "Feature",
  "properties": {
    "addr:full":"604 New Berlin Rd Jacksonville FL 32218",
    "addr:housenumber":"604",
    "addr:postcode":"32218",
    "addr:street":"New Berlin Rd",
    "iso:country":"US",
    "sg:address":"604 New Berlin Rd",
    "sg:city":"Jacksonville",
    "sg:classifiers":[
        {
            "category":"Restaurant",
            "type":"Food & Drink"
        }
    ],
    "sg:menulink":"http://www.allmenus.com/fl/jacksonville/187855-tobys-bbq/menu/",
    "sg:phone":"+1 904 757 7504",
    "sg:postcode":"32218",
    "sg:province":"FL",
    "sg:tags":[
        "barbecue",
        "american"
    ],
    "wof:name":"Toby's Bbq",
    "wof:placetype":"venue"
},
  "geometry": {"coordinates":[-81.62593200000001,30.466651],"type":"Point"}
}