{
  "type": "Feature",
  "properties": {
    "iso:country":"US",
    "sg:address":"350 Palm Beach Trace Dr",
    "sg:city":"West Palm Beach",
    "sg:classifiers":[
        {
            "category":"Building & Trades",
            "subcategory":"Cleaning & Sanitation",
            "type":"Services"
        }
    ],
    "sg:phone":"+1 561 795 9696",
    "sg:postcode":"33411",
    "sg:province":"FL",
    "sg:tags":[
        "maintenance"
    ],
    "wof:name":"Mildew Medics Inc",
    "wof:placetype":"venue"
},
  "geometry": {"coordinates":[-80.227118,26.712841],"type":"Point"}
}