{
  "type": "Feature",
  "properties": {
    "iso:country":"US",
    "sg:address":"2414 Land O Lakes Blvd",
    "sg:city":"Land O Lakes",
    "sg:classifiers":[
        {
            "category":"Food & Beverages",
            "subcategory":"Groceries & Convenience Stores",
            "type":"Retail Goods"
        }
    ],
    "sg:phone":"+1 813 949 3920",
    "sg:postcode":"34639",
    "sg:province":"FL",
    "sg:tags":[
        "grocer"
    ],
    "wof:name":"U Save Super Markets",
    "wof:placetype":"venue"
},
  "geometry": {"coordinates":[-82.46539199999999,28.193352],"type":"Point"}
}