{
  "type": "Feature",
  "properties": {
    "iso:country":"US",
    "sg:address":"3616 Londonderry Blvd",
    "sg:city":"Orlando",
    "sg:classifiers":[
        {
            "category":"Shopping",
            "subcategory":"Hobbies, Toys, & Games",
            "type":"Retail Goods"
        }
    ],
    "sg:phone":"+1 407 299 2553",
    "sg:postcode":"32808",
    "sg:province":"FL",
    "wof:name":"Robert L Lacette Crafts",
    "wof:placetype":"venue"
},
  "geometry": {"coordinates":[-81.448307,28.588627],"type":"Point"}
}