{
  "type": "Feature",
  "properties": {
    "addr:full":"3110 Lithia Pinecrest Rd Valrico FL 33596",
    "addr:housenumber":"3110",
    "addr:postcode":"33596",
    "addr:street":"Lithia Pinecrest Rd",
    "iso:country":"US",
    "sg:address":"3110 Lithia Pinecrest Rd",
    "sg:city":"Valrico",
    "sg:classifiers":[
        {
            "category":"Retail",
            "subcategory":"Animal Services",
            "type":"Services"
        }
    ],
    "sg:phone":"+1 813 681 3432",
    "sg:postcode":"33596",
    "sg:province":"FL",
    "sg:tags":[
        "pet",
        "grooming",
        "washing"
    ],
    "wof:name":"Barbara's Pet Grooming",
    "wof:placetype":"venue"
},
  "geometry": {"coordinates":[-82.248784,27.8992],"type":"Point"}
}