{
  "type": "Feature",
  "properties": {
    "addr:full":"15137 73rd Ter N Palm Beach Gardens FL 33418",
    "addr:housenumber":"15137",
    "addr:postcode":"33418",
    "addr:street":"73Rd Ter N",
    "iso:country":"US",
    "sg:address":"15137 73rd Ter N",
    "sg:city":"Palm Beach Gardens",
    "sg:classifiers":[
        {
            "category":"Professional",
            "type":"Services"
        }
    ],
    "sg:phone":"+1 561 743 9752",
    "sg:postcode":"33418",
    "sg:province":"FL",
    "wof:name":"Mary Sisoian Inc",
    "wof:placetype":"venue"
},
  "geometry": {"coordinates":[-80.148961,26.899106],"type":"Point"}
}