{
  "type": "Feature",
  "properties": {
    "addr:full":"304 4th St Orlando FL 32824",
    "addr:housenumber":"304",
    "addr:postcode":"32824",
    "addr:street":"4Th St",
    "iso:country":"US",
    "sg:address":"304 4th St",
    "sg:city":"Orlando",
    "sg:classifiers":[
        {
            "category":"Building & Trades",
            "subcategory":"Construction",
            "type":"Services"
        }
    ],
    "sg:phone":"+1 407 253 0788",
    "sg:postcode":"32824",
    "sg:province":"FL",
    "sg:tags":[
        "contractor",
        "mfg"
    ],
    "wof:name":"Skimmers Inc",
    "wof:placetype":"venue"
},
  "geometry": {"coordinates":[-81.372438,28.428618],"type":"Point"}
}