{
  "type": "Feature",
  "properties": {
    "iso:country":"US",
    "sg:address":"626 Cumberland Rd",
    "sg:city":"Venice",
    "sg:classifiers":[
        {
            "category":"Manufacturing",
            "subcategory":"Printing",
            "type":"Manufacturing & Wholesale Goods"
        }
    ],
    "sg:phone":"+1 941 497 4955",
    "sg:postcode":"34293",
    "sg:province":"FL",
    "sg:tags":[
        "lithographic",
        "commercial"
    ],
    "wof:name":"Venice Assisted Printers",
    "wof:placetype":"venue"
},
  "geometry": {"coordinates":[-82.41959300000001,27.053233],"type":"Point"}
}