{
  "type": "Feature",
  "properties": {
    "iso:country":"US",
    "sg:address":"1234 Gunn Hwy",
    "sg:city":"Odessa",
    "sg:classifiers":[
        {
            "category":"Place Of Worship",
            "subcategory":"Church",
            "type":"Public Place"
        },
        {
            "category":"Place Of Worship",
            "type":"Public Place"
        },
        {
            "category":"Organizations",
            "subcategory":"Religious Organization",
            "type":"Services"
        }
    ],
    "sg:phone":"+1 813 920 2949",
    "sg:postcode":"33556",
    "sg:province":"FL",
    "sg:tags":[
        "churches-baptist-general",
        "churches-baptist"
    ],
    "wof:name":"First Baptist Church",
    "wof:placetype":"venue"
},
  "geometry": {"coordinates":[-82.592011,28.176471],"type":"Point"}
}