{
  "type": "Feature",
  "properties": {
    "addr:full":"123 N Congress Ave Boynton Beach FL 33426",
    "addr:housenumber":"123",
    "addr:postcode":"33426",
    "addr:street":"N Congress Ave",
    "iso:country":"US",
    "sg:address":"123 N Congress Ave",
    "sg:city":"Boynton Beach",
    "sg:classifiers":[
        {
            "category":"Insurance",
            "subcategory":"Insurance Agent",
            "type":"Services"
        }
    ],
    "sg:phone":"+1 561 641 1591",
    "sg:postcode":"33426",
    "sg:province":"FL",
    "wof:name":"CBS Insurance Group",
    "wof:placetype":"venue"
},
  "geometry": {"coordinates":[-80.09050499999999,26.524536],"type":"Point"}
}