{
  "type": "Feature",
  "properties": {
    "iso:country":"US",
    "sg:address":"8677 Co Rd 639",
    "sg:city":"Bushnell",
    "sg:classifiers":[
        {
            "category":"Professional",
            "subcategory":"Computer Services",
            "type":"Services"
        }
    ],
    "sg:phone":"+1 352 793 7127",
    "sg:postcode":"33513",
    "sg:province":"FL",
    "sg:tags":[
        "repair"
    ],
    "wof:name":"Cybersamz Computer Svc",
    "wof:placetype":"venue"
},
  "geometry": {"coordinates":[-82.245339,28.629053],"type":"Point"}
}