{
  "type": "Feature",
  "properties": {
    "addr:full":"13425 SW 131st St Miami FL 33186",
    "addr:housenumber":"13425",
    "addr:postcode":"33186",
    "addr:street":"Sw 131St St",
    "iso:country":"US",
    "sg:address":"13425 SW 131st St",
    "sg:city":"Miami",
    "sg:classifiers":[
        {
            "category":"Manufacturing",
            "subcategory":"Lumber",
            "type":"Manufacturing & Wholesale Goods"
        }
    ],
    "sg:phone":"+1 305 238 1864",
    "sg:postcode":"33186",
    "sg:province":"FL",
    "wof:name":"Eurodors",
    "wof:placetype":"venue"
},
  "geometry": {"coordinates":[-80.413659,25.645494],"type":"Point"}
}