{
  "type": "Feature",
  "properties": {
    "addr:full":"29 Eglin Pkwy S Fort Walton Bch FL 32548",
    "addr:housenumber":"29",
    "addr:postcode":"32548",
    "addr:street":"Eglin Pkwy S",
    "iso:country":"US",
    "sg:address":"29 Eglin Pkwy S",
    "sg:city":"Fort Walton Bch",
    "sg:classifiers":[
        {
            "category":"Home & Garden",
            "subcategory":"Building Materials",
            "type":"Retail Goods"
        }
    ],
    "sg:phone":"+1 850 244 8333",
    "sg:postcode":"32548",
    "sg:province":"FL",
    "sg:tags":[
        "glass",
        "window",
        "plate"
    ],
    "wof:name":"Lloyd Auto Glass",
    "wof:placetype":"venue"
},
  "geometry": {"coordinates":[-86.60389499999999,30.408748],"type":"Point"}
}