{
  "type": "Feature",
  "properties": {
    "addr:full":"12501 40th St N Clearwater FL 33762",
    "addr:housenumber":"12501",
    "addr:postcode":"33762",
    "addr:street":"40Th St N",
    "iso:country":"US",
    "sg:address":"12501 40th St N",
    "sg:city":"Clearwater",
    "sg:classifiers":[
        {
            "category":"Retail",
            "subcategory":"Auto Repair",
            "type":"Services"
        }
    ],
    "sg:phone":"+1 727 572 1976",
    "sg:postcode":"33762",
    "sg:province":"FL",
    "sg:tags":[
        "transmission",
        "used",
        "parts"
    ],
    "wof:name":"U Pull It",
    "wof:placetype":"venue"
},
  "geometry": {"coordinates":[-82.688017,27.885514],"type":"Point"}
}