{
  "type": "Feature",
  "properties": {
    "addr:full":"843 SW 13th Ave Miami FL 33135",
    "addr:housenumber":"843",
    "addr:postcode":"33135",
    "addr:street":"Sw 13Th Ave",
    "iso:country":"US",
    "sg:address":"843 SW 13th Ave",
    "sg:city":"Miami",
    "sg:phone":"+1 305 860 0824",
    "sg:postcode":"33135",
    "sg:province":"FL",
    "wof:name":"Community Development",
    "wof:placetype":"venue"
},
  "geometry": {"coordinates":[-80.21639999999999,25.765478],"type":"Point"}
}