{
  "type": "Feature",
  "properties": {
    "addr:full":"2810 W Price Ave Tampa FL 33611",
    "addr:housenumber":"2810",
    "addr:postcode":"33611",
    "addr:street":"W Price Ave",
    "iso:country":"US",
    "sg:address":"2810 W Price Ave",
    "sg:city":"Tampa",
    "sg:classifiers":[
        {
            "category":"Real Estate",
            "subcategory":"Architect",
            "type":"Services"
        }
    ],
    "sg:phone":"+1 813 254 5576",
    "sg:postcode":"33611",
    "sg:province":"FL",
    "wof:name":"Jeffrey Stark Architect",
    "wof:placetype":"venue"
},
  "geometry": {"coordinates":[-82.489633,27.890875],"type":"Point"}
}