{
  "type": "Feature",
  "properties": {
    "iso:country":"US",
    "sg:address":"109 Tamiami Trl",
    "sg:city":"Nokomis",
    "sg:classifiers":[
        {
            "category":"Recreation",
            "type":"Entertainment"
        }
    ],
    "sg:phone":"+1 941 544 6640",
    "sg:postcode":"34275",
    "sg:province":"FL",
    "sg:tags":[
        "psychic",
        "medium"
    ],
    "wof:name":"Rachel's Psychic Palm & Card",
    "wof:placetype":"venue"
},
  "geometry": {"coordinates":[-82.453739,27.126456],"type":"Point"}
}