{
  "type": "Feature",
  "properties": {
    "iso:country":"US",
    "sg:address":"441 Cadagua Ave",
    "sg:city":"Miami",
    "sg:classifiers":[
        {
            "category":"Shopping",
            "type":"Retail Goods"
        }
    ],
    "sg:phone":"+1 305 662 7134",
    "sg:postcode":"33146",
    "sg:province":"FL",
    "sg:tags":[
        "consulting"
    ],
    "wof:name":"Aquasol Inc",
    "wof:placetype":"venue"
},
  "geometry": {"coordinates":[-80.263271,25.728115],"type":"Point"}
}