{
  "type": "Feature",
  "properties": {
    "addr:full":"10921 Gable St Boca Raton FL 33428",
    "addr:housenumber":"10921",
    "addr:postcode":"33428",
    "addr:street":"Gable St",
    "iso:country":"US",
    "sg:address":"10921 Gable St",
    "sg:city":"Boca Raton",
    "sg:classifiers":[
        {
            "category":"Real Estate",
            "subcategory":"Developer",
            "type":"Services"
        }
    ],
    "sg:phone":"+1 561 999 0114",
    "sg:postcode":"33428",
    "sg:province":"FL",
    "wof:name":"Admar Development Inc",
    "wof:placetype":"venue"
},
  "geometry": {"coordinates":[-80.21709199999999,26.346606],"type":"Point"}
}