{
  "type": "Feature",
  "properties": {
    "iso:country":"US",
    "sg:address":"4114 NW 78th Ln",
    "sg:city":"Pompano Beach",
    "sg:classifiers":[
        {
            "category":"Building & Trades",
            "subcategory":"Construction",
            "type":"Services"
        }
    ],
    "sg:phone":"+1 954 346 3882",
    "sg:postcode":"33065",
    "sg:province":"FL",
    "sg:tags":[
        "installation"
    ],
    "wof:name":"Chameleon Floor Covering",
    "wof:placetype":"venue"
},
  "geometry": {"coordinates":[-80.231865,26.281287],"type":"Point"}
}