{
  "type": "Feature",
  "properties": {
    "iso:country":"US",
    "sg:address":"1481 E Manasota Beach Rd",
    "sg:city":"Englewood",
    "sg:classifiers":[
        {
            "category":"Restaurant",
            "type":"Food & Drink"
        }
    ],
    "sg:phone":"+1 941 474 3006",
    "sg:postcode":"34223",
    "sg:province":"FL",
    "sg:tags":[
        "eating"
    ],
    "wof:name":"Buddys Pizza",
    "wof:placetype":"venue"
},
  "geometry": {"coordinates":[-82.383911,27.020838],"type":"Point"}
}