{
  "type": "Feature",
  "properties": {
    "iso:country":"US",
    "sg:address":"9501 NW 83rd St",
    "sg:city":"Fort Lauderdale",
    "sg:classifiers":[
        {
            "category":"Shopping",
            "subcategory":"Hobbies, Toys, & Games",
            "type":"Retail Goods"
        },
        {
            "category":"Professional",
            "subcategory":"Management & Consulting",
            "type":"Services"
        }
    ],
    "sg:phone":"+1 954 557 0022",
    "sg:postcode":"33321",
    "sg:province":"FL",
    "sg:tags":[
        "party",
        "planning"
    ],
    "wof:name":"Ceramics On Wheels",
    "wof:placetype":"venue"
},
  "geometry": {"coordinates":[-80.278166,26.228156],"type":"Point"}
}