{
  "type": "Feature",
  "properties": {
    "iso:country":"US",
    "sg:address":"2266 University Square Mall",
    "sg:city":"Tampa",
    "sg:classifiers":[
        {
            "category":"Personal",
            "type":"Services"
        }
    ],
    "sg:phone":"+1 813 978 3233",
    "sg:postcode":"33612",
    "sg:province":"FL",
    "sg:tags":[
        "wear",
        "formal"
    ],
    "wof:name":"Gingiss Formalwear",
    "wof:placetype":"venue"
},
  "geometry": {"coordinates":[-82.431237,28.056465],"type":"Point"}
}