{
  "type": "Feature",
  "properties": {
    "iso:country":"US",
    "sg:address":"6244 E Hwy 98",
    "sg:city":"Panama City",
    "sg:classifiers":[
        {
            "category":"Personal",
            "subcategory":"Beauty Salon",
            "type":"Services"
        }
    ],
    "sg:phone":"+1 850 874 1455",
    "sg:postcode":"32404",
    "sg:province":"FL",
    "wof:name":"Patrice's Hair Tech",
    "wof:placetype":"venue"
},
  "geometry": {"coordinates":[-85.60155899999999,30.112349],"type":"Point"}
}