{
  "type": "Feature",
  "properties": {
    "iso:country":"US",
    "sg:address":"3160 Fairlane Farms Rd",
    "sg:city":"Wellington",
    "sg:classifiers":[
        {
            "category":"Building & Trades",
            "subcategory":"Construction",
            "type":"Services"
        }
    ],
    "sg:phone":"+1 561 791 1953",
    "sg:postcode":"33414",
    "sg:province":"FL",
    "sg:tags":[
        "grading",
        "contractor"
    ],
    "wof:name":"Mi Lyn Industries Of Florida",
    "wof:placetype":"venue"
},
  "geometry": {"coordinates":[-80.222026,26.632911],"type":"Point"}
}