{
  "type": "Feature",
  "properties": {
    "addr:full":"8160 Wiles Rd Coral Springs FL 33067",
    "addr:postcode":"8160;33067",
    "addr:street":"Wiles Rd",
    "iso:country":"US",
    "sg:address":"8160 Wiles Rd",
    "sg:city":"Coral Springs",
    "sg:classifiers":[
        {
            "category":"Food & Beverages",
            "subcategory":"Groceries & Convenience Stores",
            "type":"Retail Goods"
        }
    ],
    "sg:phone":"+1 954 753 3307",
    "sg:postcode":"33067",
    "sg:province":"FL",
    "sg:tags":[
        "grocer"
    ],
    "sg:website":"www.publix.com",
    "wof:name":"Publix Super Market 317",
    "wof:placetype":"venue"
},
  "geometry": {"coordinates":[-80.234927,26.286751],"type":"Point"}
}