{
  "type": "Feature",
  "properties": {
    "addr:full":"323 Walton Heath Dr Orlando FL 32828",
    "addr:housenumber":"323",
    "addr:postcode":"32828",
    "addr:street":"Walton Heath Dr",
    "iso:country":"US",
    "sg:address":"323 Walton Heath Dr",
    "sg:city":"Orlando",
    "sg:classifiers":[
        {
            "category":"Professional",
            "subcategory":"Management & Consulting",
            "type":"Services"
        }
    ],
    "sg:phone":"+1 407 275 8988",
    "sg:postcode":"32828",
    "sg:province":"FL",
    "sg:tags":[
        "business"
    ],
    "wof:name":"P & H Consulting",
    "wof:placetype":"venue"
},
  "geometry": {"coordinates":[-81.170755,28.535114],"type":"Point"}
}