{
  "type": "Feature",
  "properties": {
    "iso:country":"US",
    "sg:address":"5237 Far Oak Cir",
    "sg:city":"Sarasota",
    "sg:classifiers":[
        {
            "category":"Wholesale",
            "subcategory":"Construction Materials",
            "type":"Manufacturing & Wholesale Goods"
        }
    ],
    "sg:phone":"+1 941 927 8748",
    "sg:postcode":"34238",
    "sg:province":"FL",
    "sg:tags":[
        "roofing",
        "supply"
    ],
    "wof:name":"Advantage Roofing Supplies",
    "wof:placetype":"venue"
},
  "geometry": {"coordinates":[-82.462996,27.224638],"type":"Point"}
}