{
  "type": "Feature",
  "properties": {
    "addr:full":"946 Morgan Ave Chattahoochee FL 32324",
    "addr:housenumber":"946",
    "addr:postcode":"32324",
    "addr:street":"Morgan Ave",
    "iso:country":"US",
    "sg:address":"946 Morgan Ave",
    "sg:city":"Chattahoochee",
    "sg:classifiers":[
        {
            "category":"Organizations",
            "subcategory":"Membership Organization",
            "type":"Services"
        }
    ],
    "sg:phone":"+1 850 663 4507",
    "sg:postcode":"32324",
    "sg:province":"FL",
    "wof:name":"Adams Family Association Inc",
    "wof:placetype":"venue"
},
  "geometry": {"coordinates":[-84.846328,30.691952],"type":"Point"}
}