{
  "type": "Feature",
  "properties": {
    "iso:country":"US",
    "sg:address":"631 Chestnut St",
    "sg:city":"Clearwater",
    "sg:classifiers":[
        {
            "category":"Recreation",
            "type":"Entertainment"
        }
    ],
    "sg:phone":"+1 727 464 3347",
    "sg:postcode":"33756",
    "sg:province":"FL",
    "sg:tags":[
        "parks"
    ],
    "sg:website":"www.pinellascounty.org",
    "wof:name":"Pinellas County Park Dept",
    "wof:placetype":"venue"
},
  "geometry": {"coordinates":[-82.79983900000001,27.960835],"type":"Point"}
}