{
  "type": "Feature",
  "properties": {
    "iso:country":"US",
    "sg:address":"729 Loomis Ave",
    "sg:city":"Daytona Beach",
    "sg:classifiers":[
        {
            "category":"Education",
            "subcategory":"School",
            "type":"Public Place"
        }
    ],
    "sg:phone":"+1 386 255 6475",
    "sg:postcode":"32114",
    "sg:province":"FL",
    "sg:website":"www.volusia.k12.fl.us",
    "wof:name":"Volusia County Schl Sprntndnt",
    "wof:placetype":"venue"
},
  "geometry": {"coordinates":[-81.026318,29.200078],"type":"Point"}
}