{
  "type": "Feature",
  "properties": {
    "addr:full":"209 SW 58th St Ocala FL 34471",
    "addr:housenumber":"209",
    "addr:postcode":"34471",
    "addr:street":"Sw 58Th St",
    "iso:country":"US",
    "sg:address":"209 SW 58th St",
    "sg:city":"Ocala",
    "sg:classifiers":[
        {
            "category":"Retail",
            "subcategory":"Car Wash",
            "type":"Services"
        }
    ],
    "sg:phone":"+1 352 307 8304",
    "sg:postcode":"34471",
    "sg:province":"FL",
    "sg:tags":[
        "automobile",
        "detail",
        "clean"
    ],
    "wof:name":"Anthony Davis Detail",
    "wof:placetype":"venue"
},
  "geometry": {"coordinates":[-82.13770700000001,29.130262],"type":"Point"}
}