{
  "type": "Feature",
  "properties": {
    "iso:country":"US",
    "sg:address":"5214 Los Palma Vista Dr",
    "sg:city":"Orlando",
    "sg:classifiers":[
        {
            "category":"Utilities",
            "subcategory":"Telephone",
            "type":"Services"
        }
    ],
    "sg:phone":"+1 407 855 5622",
    "sg:postcode":"32837",
    "sg:province":"FL",
    "sg:tags":[
        "web",
        "telecommunication",
        "hosting"
    ],
    "wof:name":"McG Solutions LLC",
    "wof:placetype":"venue"
},
  "geometry": {"coordinates":[-81.46337699999999,28.365543],"type":"Point"}
}