{
  "type": "Feature",
  "properties": {
    "iso:country":"US",
    "sg:address":"2066 N Bayshore Dr",
    "sg:city":"Miami",
    "sg:classifiers":[
        {
            "category":"Building & Trades",
            "subcategory":"Locksmith",
            "type":"Services"
        }
    ],
    "sg:phone":"+1 305 755 4262",
    "sg:postcode":"33137",
    "sg:province":"FL",
    "sg:tags":[
        "key"
    ],
    "wof:name":"Emergency Locksmith Available 24 7",
    "wof:placetype":"venue"
},
  "geometry": {"coordinates":[-80.187298,25.796568],"type":"Point"}
}