{
  "type": "Feature",
  "properties": {
    "iso:country":"US",
    "sg:address":"16111 NW 13th Ave",
    "sg:city":"Miami",
    "sg:classifiers":[
        {
            "category":"Manufacturing",
            "subcategory":"Building Materials",
            "type":"Manufacturing & Wholesale Goods"
        }
    ],
    "sg:phone":"+1 305 624 2617",
    "sg:postcode":"33169",
    "sg:province":"FL",
    "sg:tags":[
        "mfg",
        "kitchen",
        "cabinet"
    ],
    "sg:website":"www.sunshinekitchens.com",
    "wof:name":"Sunshine Kitchens Inc",
    "wof:placetype":"venue"
},
  "geometry": {"coordinates":[-80.22135,25.92112],"type":"Point"}
}