{
  "type": "Feature",
  "properties": {
    "iso:country":"US",
    "sg:address":"615 W Bloomingdale Ave",
    "sg:city":"Brandon",
    "sg:classifiers":[
        {
            "category":"Autos & Motor Vehicles",
            "subcategory":"Fuel & Gas Station",
            "type":"Retail Goods"
        }
    ],
    "sg:phone":"+1 813 684 3085",
    "sg:postcode":"33511",
    "sg:province":"FL",
    "sg:tags":[
        "oil"
    ],
    "wof:name":"Kings Avenue Exxon",
    "wof:placetype":"venue"
},
  "geometry": {"coordinates":[-82.292412,27.893536],"type":"Point"}
}