{
  "type": "Feature",
  "properties": {
    "iso:country":"US",
    "sg:address":"5607 E Hillsborough Ave",
    "sg:city":"Tampa",
    "sg:classifiers":[
        {
            "category":"Restaurant",
            "type":"Food & Drink"
        }
    ],
    "sg:menulink":"http://www.allmenus.com/fl/tampa/160375-burger-king/menu/",
    "sg:phone":"+1 813 621 0779",
    "sg:postcode":"33610",
    "sg:province":"FL",
    "sg:tags":[
        "burger",
        "american"
    ],
    "wof:name":"Burger King",
    "wof:placetype":"venue"
},
  "geometry": {"coordinates":[-82.391755,27.99561],"type":"Point"}
}