{
  "type": "Feature",
  "properties": {
    "iso:country":"US",
    "sg:address":"2155 Andrea Ln",
    "sg:city":"Fort Myers",
    "sg:classifiers":[
        {
            "category":"Wholesale",
            "subcategory":"Metals & Minerals",
            "type":"Manufacturing & Wholesale Goods"
        }
    ],
    "sg:phone":"+1 239 489 1311",
    "sg:postcode":"33912",
    "sg:province":"FL",
    "sg:tags":[
        "aluminum"
    ],
    "wof:name":"Integrity Aluminum Structures",
    "wof:placetype":"venue"
},
  "geometry": {"coordinates":[-81.864777,26.534452],"type":"Point"}
}