{
  "type": "Feature",
  "properties": {
    "iso:country":"US",
    "sg:address":"6300 NE 7th Ave",
    "sg:city":"Boca Raton",
    "sg:classifiers":[
        {
            "category":"Travel",
            "subcategory":"Travel Agent",
            "type":"Entertainment"
        }
    ],
    "sg:phone":"+1 561 999 9233",
    "sg:postcode":"33487",
    "sg:province":"FL",
    "sg:tags":[
        "agency"
    ],
    "wof:name":"Cruise One Inc",
    "wof:placetype":"venue"
},
  "geometry": {"coordinates":[-80.07417599999999,26.406506],"type":"Point"}
}