{
  "type": "Feature",
  "properties": {
    "addr:full":"1095 Sand Castle Rd Sanibel FL 33957",
    "addr:housenumber":"1095",
    "addr:postcode":"33957",
    "addr:street":"Sand Castle Rd",
    "iso:country":"US",
    "sg:address":"1095 Sand Castle Rd",
    "sg:city":"Sanibel",
    "sg:classifiers":[
        {
            "category":"Shopping",
            "subcategory":"Clothing, Apparel, & Fashions",
            "type":"Retail Goods"
        }
    ],
    "sg:phone":"+1 239 395 3766",
    "sg:postcode":"33957",
    "sg:province":"FL",
    "wof:name":"Church Ladies Investment Club",
    "wof:placetype":"venue"
},
  "geometry": {"coordinates":[-82.050258,26.455487],"type":"Point"}
}