{
  "type": "Feature",
  "properties": {
    "iso:country":"US",
    "sg:address":"5355 Gall Blvd",
    "sg:city":"Zephyrhills",
    "sg:classifiers":[
        {
            "category":"Shopping",
            "subcategory":"Jewelry",
            "type":"Retail Goods"
        }
    ],
    "sg:phone":"+1 813 788 2520",
    "sg:postcode":"33542",
    "sg:province":"FL",
    "sg:tags":[
        "jeweler"
    ],
    "wof:name":"Crown Jewelry",
    "wof:placetype":"venue"
},
  "geometry": {"coordinates":[-82.182912,28.235709],"type":"Point"}
}