{
  "type": "Feature",
  "properties": {
    "iso:country":"US",
    "sg:address":"124 Washington St",
    "sg:city":"Lake Placid",
    "sg:classifiers":[
        {
            "category":"Social Services",
            "subcategory":"Child Care",
            "type":"Services"
        }
    ],
    "sg:phone":"+1 863 699 3798",
    "sg:postcode":"33852",
    "sg:province":"FL",
    "sg:tags":[
        "kindergarten",
        "academic",
        "school"
    ],
    "wof:name":"Redlands Christian Migrant",
    "wof:placetype":"venue"
},
  "geometry": {"coordinates":[-81.35287099999999,27.277413],"type":"Point"}
}