{
  "type": "Feature",
  "properties": {
    "addr:full":"3650 SW 10th St Deerfield Beach FL 33442",
    "addr:housenumber":"3650",
    "addr:postcode":"33442",
    "addr:street":"Sw 10Th St",
    "iso:country":"US",
    "sg:address":"3650 SW 10th St",
    "sg:city":"Deerfield Beach",
    "sg:classifiers":[
        {
            "category":"Health Services",
            "subcategory":"Chiropractor",
            "type":"Services"
        }
    ],
    "sg:phone":"+1 954 571 7088",
    "sg:postcode":"33442",
    "sg:province":"FL",
    "wof:name":"Chiro Fitness Centers Inc",
    "wof:placetype":"venue"
},
  "geometry": {"coordinates":[-80.15366,26.304327],"type":"Point"}
}