{
  "type": "Feature",
  "properties": {
    "addr:full":"66 W Flagler St Miami FL 33130",
    "addr:housenumber":"66",
    "addr:postcode":"33130",
    "addr:street":"W Flagler St",
    "iso:country":"US",
    "sg:address":"66 W Flagler St",
    "sg:city":"Miami",
    "sg:classifiers":[
        {
            "category":"Professional",
            "subcategory":"Lawyer & Legal Services",
            "type":"Services"
        }
    ],
    "sg:phone":"+1 305 371 4402",
    "sg:postcode":"33130",
    "sg:province":"FL",
    "wof:name":"Doherty Richard E Atty",
    "wof:placetype":"venue"
},
  "geometry": {"coordinates":[-80.195297,25.774099],"type":"Point"}
}