{
  "type": "Feature",
  "properties": {
    "iso:country":"US",
    "sg:address":"5600 NW 36th St Ste 3",
    "sg:city":"Miami",
    "sg:classifiers":[
        {
            "category":"Manufacturing",
            "subcategory":"Aerospace",
            "type":"Manufacturing & Wholesale Goods"
        }
    ],
    "sg:phone":"+1 305 871 6556",
    "sg:postcode":"33166",
    "sg:province":"FL",
    "sg:tags":[
        "equipment",
        "aircraft",
        "part",
        "supply"
    ],
    "wof:name":"Advanced Aircraft Finance & Leasing, Inc",
    "wof:placetype":"venue"
},
  "geometry": {"coordinates":[-80.288566,25.807498],"type":"Point"}
}