{
  "type": "Feature",
  "properties": {
    "addr:full":"14707 S Dixie Hwy Miami FL 33176",
    "addr:housenumber":"14707",
    "addr:postcode":"33176",
    "addr:street":"S Dixie Hwy",
    "iso:country":"US",
    "sg:address":"14707 S Dixie Hwy",
    "sg:city":"Miami",
    "sg:classifiers":[
        {
            "category":"Banks & Credit Unions",
            "subcategory":"Financial Services",
            "type":"Services"
        }
    ],
    "sg:phone":"+1 305 259 8990",
    "sg:postcode":"33176",
    "sg:province":"FL",
    "sg:tags":[
        "broker",
        "mortgage"
    ],
    "wof:name":"First Residential Mortgage",
    "wof:placetype":"venue"
},
  "geometry": {"coordinates":[-80.33879899999999,25.633499],"type":"Point"}
}