{
  "type": "Feature",
  "properties": {
    "iso:country":"US",
    "sg:address":"100 E Pine St",
    "sg:city":"Orlando",
    "sg:classifiers":[
        {
            "category":"Professional",
            "subcategory":"Engineering",
            "type":"Services"
        }
    ],
    "sg:phone":"+1 407 246 0044",
    "sg:postcode":"32801",
    "sg:province":"FL",
    "sg:tags":[
        "civil",
        "hwy",
        "traffic",
        "engineer"
    ],
    "wof:name":"Protean Design Group Inc",
    "wof:placetype":"venue"
},
  "geometry": {"coordinates":[-81.375874,28.541338],"type":"Point"}
}