{
  "type": "Feature",
  "properties": {
    "iso:country":"US",
    "sg:address":"7240 Pine Forest Cir",
    "sg:city":"Lake Worth",
    "sg:classifiers":[
        {
            "category":"Building & Trades",
            "subcategory":"Landscaping Services",
            "type":"Services"
        }
    ],
    "sg:phone":"+1 561 642 9495",
    "sg:postcode":"33467",
    "sg:province":"FL",
    "wof:name":"First Pest Control",
    "wof:placetype":"venue"
},
  "geometry": {"coordinates":[-80.15787,26.611744],"type":"Point"}
}