{
  "type": "Feature",
  "properties": {
    "addr:full":"321 SE 12th St Pompano Beach FL 33060",
    "addr:housenumber":"321",
    "addr:postcode":"33060",
    "addr:street":"Se 12Th St",
    "iso:country":"US",
    "sg:address":"321 SE 12th St",
    "sg:city":"Pompano Beach",
    "sg:classifiers":[
        {
            "category":"Utilities",
            "subcategory":"Electric",
            "type":"Services"
        }
    ],
    "sg:phone":"+1 954 941 1830",
    "sg:postcode":"33060",
    "sg:province":"FL",
    "wof:name":"Burley Electrical Service",
    "wof:placetype":"venue"
},
  "geometry": {"coordinates":[-80.11812,26.215044],"type":"Point"}
}