{
  "type": "Feature",
  "properties": {
    "iso:country":"US",
    "sg:address":"6740 SW 8th St",
    "sg:city":"Miami",
    "sg:classifiers":[
        {
            "category":"Restaurant",
            "type":"Food & Drink"
        }
    ],
    "sg:phone":"+1 305 261 4772",
    "sg:postcode":"33144",
    "sg:province":"FL",
    "sg:website":"www.tacobell.com",
    "wof:name":"Taco Bell",
    "wof:placetype":"venue"
},
  "geometry": {"coordinates":[-80.304604,25.763201],"type":"Point"}
}