{
  "type": "Feature",
  "properties": {
    "iso:country":"US",
    "sg:address":"13835 SW 107th Ter",
    "sg:city":"Miami",
    "sg:classifiers":[
        {
            "category":"Professional",
            "subcategory":"Business Services",
            "type":"Services"
        }
    ],
    "sg:phone":"+1 305 380 8217",
    "sg:postcode":"33186",
    "sg:province":"FL",
    "sg:tags":[
        "translator",
        "interpreter"
    ],
    "wof:name":"Translation Works Inc",
    "wof:placetype":"venue"
},
  "geometry": {"coordinates":[-80.41861,25.667767],"type":"Point"}
}