{
  "type": "Feature",
  "properties": {
    "iso:country":"US",
    "sg:address":"5907 Covered Creek Ln",
    "sg:city":"Jacksonville",
    "sg:classifiers":[
        {
            "category":"Restaurant",
            "type":"Food & Drink"
        }
    ],
    "sg:phone":"+1 904 745 3389",
    "sg:postcode":"32277",
    "sg:province":"FL",
    "sg:tags":[
        "style",
        "family"
    ],
    "wof:name":"Brannon Family Restaurants",
    "wof:placetype":"venue"
},
  "geometry": {"coordinates":[-81.600932,30.378762],"type":"Point"}
}