{
  "type": "Feature",
  "properties": {
    "iso:country":"US",
    "sg:address":"14954 94th St N",
    "sg:city":"West Palm Beach",
    "sg:classifiers":[
        {
            "category":"Building & Trades",
            "subcategory":"Construction",
            "type":"Services"
        }
    ],
    "sg:phone":"+1 561 333 3740",
    "sg:postcode":"33412",
    "sg:province":"FL",
    "sg:tags":[
        "contractor"
    ],
    "wof:name":"Parker Pools",
    "wof:placetype":"venue"
},
  "geometry": {"coordinates":[-80.276669,26.816186],"type":"Point"}
}