{
  "type": "Feature",
  "properties": {
    "iso:country":"US",
    "sg:address":"11821 Pruett Rd",
    "sg:city":"Seffner",
    "sg:classifiers":[
        {
            "category":"Communications",
            "type":"Services"
        }
    ],
    "sg:phone":"+1 813 654 7562",
    "sg:postcode":"33584",
    "sg:province":"FL",
    "wof:name":"Pinnacle Towers Inc",
    "wof:placetype":"venue"
},
  "geometry": {"coordinates":[-82.29045600000001,28.021517],"type":"Point"}
}