{
  "type": "Feature",
  "properties": {
    "iso:country":"US",
    "sg:address":"29335 Us Highway 19 N",
    "sg:city":"Clearwater",
    "sg:classifiers":[
        {
            "category":"Restaurant",
            "type":"Food & Drink"
        }
    ],
    "sg:menulink":"http://www.allmenus.com/fl/clearwater/41962-bob-evans/menu/",
    "sg:phone":"+1 727 787 3359",
    "sg:postcode":"33761",
    "sg:province":"FL",
    "sg:tags":[
        "american"
    ],
    "wof:name":"Bob Evans",
    "wof:placetype":"venue"
},
  "geometry": {"coordinates":[-82.738148,28.03767],"type":"Point"}
}