{
  "type": "Feature",
  "properties": {
    "addr:full":"4415 SW 35 Ter Gainesville FL 32608",
    "addr:housenumber":"4415;35",
    "addr:postcode":"32608",
    "addr:street":"Sw",
    "iso:country":"US",
    "sg:address":"4415 SW 35 Ter",
    "sg:city":"Gainesville",
    "sg:classifiers":[
        {
            "category":"Building & Trades",
            "subcategory":"Plumbing",
            "type":"Services"
        }
    ],
    "sg:phone":"+1 352 372 4678",
    "sg:postcode":"32608",
    "sg:province":"FL",
    "sg:tags":[
        "plumbing",
        "contractor"
    ],
    "wof:name":"Church's Plumbing Inc",
    "wof:placetype":"venue"
},
  "geometry": {"coordinates":[-82.375068,29.612621],"type":"Point"}
}