{
  "type": "Feature",
  "properties": {
    "addr:full":"4252 N Orange Blossom Trl Orlando FL 32804",
    "addr:housenumber":"4252",
    "addr:postcode":"32804",
    "addr:street":"N Orange Blossom Trl",
    "iso:country":"US",
    "sg:address":"4252 N Orange Blossom Trl",
    "sg:city":"Orlando",
    "sg:classifiers":[
        {
            "category":"Retail",
            "subcategory":"Auto Rental",
            "type":"Services"
        }
    ],
    "sg:phone":"+1 407 513 4706",
    "sg:postcode":"32804",
    "sg:province":"FL",
    "sg:tags":[
        "renting",
        "storage",
        "self",
        "leasing",
        "truck"
    ],
    "sg:website":"www.personalministorage.com/self...",
    "wof:name":"Personal Mini Storage",
    "wof:placetype":"venue"
},
  "geometry": {"coordinates":[-81.41329,28.590941],"type":"Point"}
}