{
  "type": "Feature",
  "properties": {
    "iso:country":"US",
    "sg:address":"6730 Ridge Rd",
    "sg:city":"Port Richey",
    "sg:classifiers":[
        {
            "category":"Personal",
            "type":"Services"
        }
    ],
    "sg:phone":"+1 727 846 8266",
    "sg:postcode":"34668",
    "sg:province":"FL",
    "sg:tags":[
        "salon",
        "tanning"
    ],
    "wof:name":"Islands Tanning Salon Inc",
    "wof:placetype":"venue"
},
  "geometry": {"coordinates":[-82.701606,28.280613],"type":"Point"}
}