{
  "type": "Feature",
  "properties": {
    "iso:country":"US",
    "sg:address":"3477 W Flagler St",
    "sg:city":"Miami",
    "sg:classifiers":[
        {
            "category":"Health Services",
            "subcategory":"Optometrist",
            "type":"Services"
        }
    ],
    "sg:phone":"+1 305 649 1515",
    "sg:postcode":"33135",
    "sg:province":"FL",
    "wof:name":"Jesse O Cortes D P A",
    "wof:placetype":"venue"
},
  "geometry": {"coordinates":[-80.251779,25.772006],"type":"Point"}
}