{
  "type": "Feature",
  "properties": {
    "addr:full":"840 13th St Lake Park FL 33403",
    "addr:housenumber":"840",
    "addr:postcode":"33403",
    "addr:street":"13Th St",
    "iso:country":"US",
    "sg:address":"840 13th St",
    "sg:city":"Lake Park",
    "sg:classifiers":[
        {
            "category":"Home & Garden",
            "subcategory":"Furniture",
            "type":"Retail Goods"
        }
    ],
    "sg:phone":"+1 561 882 2399",
    "sg:postcode":"33403",
    "sg:province":"FL",
    "sg:tags":[
        "cabinet"
    ],
    "wof:name":"M & D Cabinetry",
    "wof:placetype":"venue"
},
  "geometry": {"coordinates":[-80.07961,26.800214],"type":"Point"}
}