{
  "type": "Feature",
  "properties": {
    "addr:full":"784 NE 171st St Starke FL 32091",
    "addr:housenumber":"784",
    "addr:postcode":"32091",
    "addr:street":"Ne 171St St",
    "iso:country":"US",
    "sg:address":"784 NE 171st St",
    "sg:city":"Starke",
    "sg:classifiers":[
        {
            "category":"Manufacturing",
            "subcategory":"Buildings",
            "type":"Manufacturing & Wholesale Goods"
        },
        {
            "category":"Home & Garden",
            "subcategory":"Building Materials",
            "type":"Retail Goods"
        },
        {
            "category":"Building & Trades",
            "subcategory":"Construction",
            "type":"Services"
        }
    ],
    "sg:phone":"+1 904 964 9770",
    "sg:postcode":"32091",
    "sg:province":"FL",
    "sg:tags":[
        "roofing",
        "industrial",
        "altering",
        "builder",
        "improvement",
        "contractors-commercial",
        "contractor",
        "remodeling"
    ],
    "wof:name":"H D Starling Custom Builders",
    "wof:placetype":"venue"
},
  "geometry": {"coordinates":[-82.05684599999999,29.962825],"type":"Point"}
}