{
  "type": "Feature",
  "properties": {
    "addr:full":"499 SW 28th Ave Delray Beach FL 33445",
    "addr:housenumber":"499",
    "addr:postcode":"33445",
    "addr:street":"Sw 28Th Ave",
    "iso:country":"US",
    "sg:address":"499 SW 28th Ave",
    "sg:city":"Delray Beach",
    "sg:classifiers":[
        {
            "category":"Building & Trades",
            "subcategory":"Construction",
            "type":"Services"
        }
    ],
    "sg:phone":"+1 561 278 1245",
    "sg:postcode":"33445",
    "sg:province":"FL",
    "sg:tags":[
        "house"
    ],
    "wof:name":"Kitchen Remodeling Specialist",
    "wof:placetype":"venue"
},
  "geometry": {"coordinates":[-80.104101,26.455287],"type":"Point"}
}