{
  "type": "Feature",
  "properties": {
    "iso:country":"US",
    "sg:address":"225 SW 21st Ter",
    "sg:city":"Fort Lauderdale",
    "sg:classifiers":[
        {
            "category":"Building & Trades",
            "subcategory":"Construction",
            "type":"Services"
        }
    ],
    "sg:phone":"+1 954 791 9809",
    "sg:postcode":"33312",
    "sg:province":"FL",
    "sg:tags":[
        "contractor"
    ],
    "wof:name":"D and D Welding",
    "wof:placetype":"venue"
},
  "geometry": {"coordinates":[-80.170996,26.115175],"type":"Point"}
}