{
  "type": "Feature",
  "properties": {
    "iso:country":"US",
    "sg:address":"7602 Lockwood Ridge Rd",
    "sg:city":"Sarasota",
    "sg:classifiers":[
        {
            "category":"Restaurant",
            "type":"Food & Drink"
        }
    ],
    "sg:phone":"+1 941 351 5515",
    "sg:postcode":"34243",
    "sg:province":"FL",
    "sg:tags":[
        "seafood"
    ],
    "wof:name":"The Lazy Lobster",
    "wof:placetype":"venue"
},
  "geometry": {"coordinates":[-82.50543999999999,27.404763],"type":"Point"}
}