{
  "type": "Feature",
  "properties": {
    "addr:full":"136 Silver Lake Rd Palatka FL 32177",
    "addr:housenumber":"136",
    "addr:postcode":"32177",
    "addr:street":"Silver Lake Rd",
    "iso:country":"US",
    "sg:address":"136 Silver Lake Rd",
    "sg:city":"Palatka",
    "sg:classifiers":[
        {
            "category":"Building & Trades",
            "subcategory":"Landscaping Services",
            "type":"Services"
        }
    ],
    "sg:phone":"+1 386 325 3705",
    "sg:postcode":"32177",
    "sg:province":"FL",
    "sg:tags":[
        "tree"
    ],
    "wof:name":"Strickland Brothers Tree Svc",
    "wof:placetype":"venue"
},
  "geometry": {"coordinates":[-81.712423,29.634477],"type":"Point"}
}