{
  "type": "Feature",
  "properties": {
    "addr:full":"7975 NW 154th St Hialeah FL 33016",
    "addr:housenumber":"7975",
    "addr:postcode":"33016",
    "addr:street":"Nw 154Th St",
    "iso:country":"US",
    "sg:address":"7975 NW 154th St",
    "sg:city":"Hialeah",
    "sg:classifiers":[
        {
            "category":"Real Estate",
            "subcategory":"Real Estate Agent",
            "type":"Services"
        }
    ],
    "sg:phone":"+1 305 624 8400",
    "sg:postcode":"33016",
    "sg:province":"FL",
    "sg:tags":[
        "property",
        "management"
    ],
    "wof:name":"Lincoln Property Company",
    "wof:placetype":"venue"
},
  "geometry": {"coordinates":[-80.329241,25.913349],"type":"Point"}
}