{
  "type": "Feature",
  "properties": {
    "iso:country":"US",
    "sg:address":"2290 N 25th St",
    "sg:city":"Fort Pierce",
    "sg:classifiers":[
        {
            "category":"Building & Trades",
            "subcategory":"Cleaning & Sanitation",
            "type":"Services"
        }
    ],
    "sg:phone":"+1 772 466 4851",
    "sg:postcode":"34946",
    "sg:province":"FL",
    "sg:tags":[
        "janitor"
    ],
    "wof:name":"Linda Martin's Cleaning Svc",
    "wof:placetype":"venue"
},
  "geometry": {"coordinates":[-80.34956,27.47386],"type":"Point"}
}