{
  "type": "Feature",
  "properties": {
    "iso:country":"US",
    "sg:address":"14523 SW 98th Ter",
    "sg:city":"Miami",
    "sg:classifiers":[
        {
            "category":"Social Services",
            "subcategory":"Child Care",
            "type":"Services"
        }
    ],
    "sg:phone":"+1 305 387 9521",
    "sg:postcode":"33186",
    "sg:province":"FL",
    "sg:tags":[
        "homes-children"
    ],
    "wof:name":"Marlene Proano",
    "wof:placetype":"venue"
},
  "geometry": {"coordinates":[-80.430796,25.675425],"type":"Point"}
}