{
  "type": "Feature",
  "properties": {
    "addr:full":"3242 Tamiami Trl Venice FL 34293",
    "addr:housenumber":"3242",
    "addr:postcode":"34293",
    "addr:street":"Tamiami Trl",
    "iso:country":"US",
    "sg:address":"3242 Tamiami Trl",
    "sg:city":"Venice",
    "sg:classifiers":[
        {
            "category":"Banks & Credit Unions",
            "subcategory":"Investment Brokerage",
            "type":"Services"
        }
    ],
    "sg:phone":"+1 239 491 1009",
    "sg:postcode":"34293",
    "sg:province":"FL",
    "sg:tags":[
        "security"
    ],
    "wof:name":"AG Edwards & Sons",
    "wof:placetype":"venue"
},
  "geometry": {"coordinates":[-82.401353,27.049656],"type":"Point"}
}