{
  "type": "Feature",
  "properties": {
    "addr:full":"684 Whitetail Loop Apopka FL 32703",
    "addr:housenumber":"684",
    "addr:postcode":"32703",
    "addr:street":"Whitetail Loop",
    "iso:country":"US",
    "sg:address":"684 Whitetail Loop",
    "sg:city":"Apopka",
    "sg:classifiers":[
        {
            "category":"Retail",
            "subcategory":"Animal Services",
            "type":"Services"
        }
    ],
    "sg:phone":"+1 407 886 5899",
    "sg:postcode":"32703",
    "sg:province":"FL",
    "sg:tags":[
        "pet",
        "grooming",
        "washing"
    ],
    "wof:name":"Wag'n Splash",
    "wof:placetype":"venue"
},
  "geometry": {"coordinates":[-81.499188,28.678943],"type":"Point"}
}