{
  "type": "Feature",
  "properties": {
    "addr:full":"2477 Stickney Point Rd Sarasota FL 34231",
    "addr:housenumber":"2477",
    "addr:postcode":"34231",
    "addr:street":"Stickney Point Rd",
    "iso:country":"US",
    "sg:address":"2477 Stickney Point Rd",
    "sg:city":"Sarasota",
    "sg:classifiers":[
        {
            "category":"Professional",
            "subcategory":"Business Services",
            "type":"Services"
        }
    ],
    "sg:phone":"+1 941 925 4321",
    "sg:postcode":"34231",
    "sg:province":"FL",
    "wof:name":"Signature Travle",
    "wof:placetype":"venue"
},
  "geometry": {"coordinates":[-82.520636,27.26255],"type":"Point"}
}