{
  "type": "Feature",
  "properties": {
    "addr:full":"13417 SW 56th St Miami FL 33175",
    "addr:housenumber":"13417",
    "addr:postcode":"33175",
    "addr:street":"Sw 56Th St",
    "iso:country":"US",
    "sg:address":"13417 SW 56th St",
    "sg:city":"Miami",
    "sg:classifiers":[
        {
            "category":"Restaurant",
            "type":"Food & Drink"
        }
    ],
    "sg:menulink":"http://www.allmenus.com/fl/kendale-lakes-lindgren-acres/82087-dominos-pizza/menu/",
    "sg:phone":"+1 305 553 3030",
    "sg:postcode":"33175",
    "sg:province":"FL",
    "sg:tags":[
        "american",
        "wing",
        "pizza"
    ],
    "wof:name":"Domino's Pizza",
    "wof:placetype":"venue"
},
  "geometry": {"coordinates":[-80.41189199999999,25.714657],"type":"Point"}
}