{
  "type": "Feature",
  "properties": {
    "iso:country":"US",
    "sg:address":"5817 Beggs Rd",
    "sg:city":"Orlando",
    "sg:classifiers":[
        {
            "category":"Wholesale",
            "subcategory":"Machinery & Supplies",
            "type":"Manufacturing & Wholesale Goods"
        }
    ],
    "sg:phone":"+1 407 296 3858",
    "sg:postcode":"32810",
    "sg:province":"FL",
    "sg:tags":[
        "equipment",
        "material",
        "handling"
    ],
    "wof:name":"Tom's Forklift Svc",
    "wof:placetype":"venue"
},
  "geometry": {"coordinates":[-81.449144,28.625618],"type":"Point"}
}