{
  "type": "Feature",
  "properties": {
    "iso:country":"US",
    "sg:address":"895 NE 125th St",
    "sg:city":"North Miami",
    "sg:classifiers":[
        {
            "category":"Shopping",
            "subcategory":"Books",
            "type":"Retail Goods"
        }
    ],
    "sg:phone":"+1 305 981 2287",
    "sg:postcode":"33161",
    "sg:province":"FL",
    "sg:tags":[
        "dealer"
    ],
    "wof:name":"Bookstore Faith Afrocentric",
    "wof:placetype":"venue"
},
  "geometry": {"coordinates":[-80.182146,25.890525],"type":"Point"}
}