{
  "type": "Feature",
  "properties": {
    "iso:country":"US",
    "sg:address":"1838 Tupelo Ln",
    "sg:city":"Zephyrhills",
    "sg:classifiers":[
        {
            "category":"Professional",
            "subcategory":"Accounting & Tax Preparation",
            "type":"Services"
        }
    ],
    "sg:phone":"+1 813 991 6256",
    "sg:postcode":"33543",
    "sg:province":"FL",
    "sg:tags":[
        "bookkeeping",
        "general"
    ],
    "wof:name":"Darlene Freeman",
    "wof:placetype":"venue"
},
  "geometry": {"coordinates":[-82.341123,28.18425],"type":"Point"}
}