{
  "type": "Feature",
  "properties": {
    "addr:full":"35411 Crescent Dr Fruitland Park FL 34731",
    "addr:housenumber":"35411",
    "addr:postcode":"34731",
    "addr:street":"Crescent Dr",
    "iso:country":"US",
    "sg:address":"35411 Crescent Dr",
    "sg:city":"Fruitland Park",
    "sg:classifiers":[
        {
            "category":"Organizations",
            "subcategory":"Community Association",
            "type":"Services"
        }
    ],
    "sg:phone":"+1 352 365 6822",
    "sg:postcode":"34731",
    "sg:province":"FL",
    "wof:name":"Kiwanis International Inc",
    "wof:placetype":"venue"
},
  "geometry": {"coordinates":[-81.883999,28.864963],"type":"Point"}
}