{
  "type": "Feature",
  "properties": {
    "iso:country":"US",
    "sg:address":"1123 NW 192nd Ave",
    "sg:city":"Gainesville",
    "sg:classifiers":[
        {
            "category":"Restaurant",
            "type":"Food & Drink"
        }
    ],
    "sg:phone":"+1 352 485 1212",
    "sg:postcode":"32609",
    "sg:province":"FL",
    "wof:name":"Bryan & Ginnie Marriott",
    "wof:placetype":"venue"
},
  "geometry": {"coordinates":[-82.336465,29.830027],"type":"Point"}
}