{
  "type": "Feature",
  "properties": {
    "iso:country":"US",
    "sg:address":"22 Aspen St",
    "sg:city":"Daytona Beach",
    "sg:classifiers":[
        {
            "category":"Building & Trades",
            "subcategory":"Construction",
            "type":"Services"
        }
    ],
    "sg:phone":"+1 386 212 3946",
    "sg:postcode":"32124",
    "sg:province":"FL",
    "sg:tags":[
        "restoration",
        "cleaning",
        "patio",
        "deck"
    ],
    "wof:name":"Aqua Clean By Jeff Langlois",
    "wof:placetype":"venue"
},
  "geometry": {"coordinates":[-81.141063,29.130914],"type":"Point"}
}