{
  "type": "Feature",
  "properties": {
    "iso:country":"US",
    "sg:address":"520 NE 33rd St",
    "sg:city":"Fort Lauderdale",
    "sg:classifiers":[
        {
            "category":"Retail",
            "subcategory":"Repair Shop",
            "type":"Services"
        }
    ],
    "sg:phone":"+1 954 563 4552",
    "sg:postcode":"33334",
    "sg:province":"FL",
    "sg:tags":[
        "electrical"
    ],
    "wof:name":"Vinicio Appliance & AC",
    "wof:placetype":"venue"
},
  "geometry": {"coordinates":[-80.13883199999999,26.168416],"type":"Point"}
}