{
  "type": "Feature",
  "properties": {
    "iso:country":"US",
    "sg:address":"40 W 22nd St",
    "sg:city":"Hialeah",
    "sg:classifiers":[
        {
            "category":"Building & Trades",
            "subcategory":"Construction",
            "type":"Services"
        },
        {
            "category":"Manufacturing",
            "subcategory":"Retail Goods",
            "type":"Manufacturing & Wholesale Goods"
        }
    ],
    "sg:phone":"+1 305 888 6560",
    "sg:postcode":"33010",
    "sg:province":"FL",
    "sg:tags":[
        "system",
        "equipment-parts",
        "contractor",
        "refrigeration",
        "mechanical",
        "supplies-wholesale",
        "air conditioning",
        "manufacturer"
    ],
    "wof:name":"C & T Air Service Inc",
    "wof:placetype":"venue"
},
  "geometry": {"coordinates":[-80.282877,25.841933],"type":"Point"}
}