{
  "type": "Feature",
  "properties": {
    "iso:country":"US",
    "sg:address":"300 SW 4th St",
    "sg:city":"Hallandale Beach",
    "sg:classifiers":[
        {
            "category":"Building & Trades",
            "subcategory":"Cleaning & Sanitation",
            "type":"Services"
        }
    ],
    "sg:phone":"+1 954 456 8648",
    "sg:postcode":"33009",
    "sg:province":"FL",
    "sg:tags":[
        "janitor"
    ],
    "wof:name":"A Touch Of Woman",
    "wof:placetype":"venue"
},
  "geometry": {"coordinates":[-80.15169,25.98085],"type":"Point"}
}