{
  "type": "Feature",
  "properties": {
    "iso:country":"US",
    "sg:address":"180 25th St NW",
    "sg:city":"Naples",
    "sg:classifiers":[
        {
            "category":"Building & Trades",
            "subcategory":"Landscaping Services",
            "type":"Services"
        }
    ],
    "sg:phone":"+1 239 403 8127",
    "sg:postcode":"34120",
    "sg:province":"FL",
    "wof:name":"Damians Personal Lawn Mowing",
    "wof:placetype":"venue"
},
  "geometry": {"coordinates":[-81.65722100000001,26.242262],"type":"Point"}
}