{
  "type": "Feature",
  "properties": {
    "iso:country":"US",
    "sg:address":"8710 Old Tampa Rd",
    "sg:city":"Parrish",
    "sg:classifiers":[
        {
            "category":"Retail",
            "subcategory":"Auto Repair",
            "type":"Services"
        }
    ],
    "sg:phone":"+1 941 776 8833",
    "sg:postcode":"34219",
    "sg:province":"FL",
    "sg:tags":[
        "automobile",
        "lubrication",
        "automotive"
    ],
    "wof:name":"Oil Masters Quick Lube Inc",
    "wof:placetype":"venue"
},
  "geometry": {"coordinates":[-82.475782,27.541703],"type":"Point"}
}