{
  "type": "Feature",
  "properties": {
    "iso:country":"US",
    "sg:address":"10711 SW 44th St",
    "sg:city":"Miami",
    "sg:classifiers":[
        {
            "category":"Juice Bar",
            "subcategory":"None",
            "type":"Food & Drink"
        }
    ],
    "sg:phone":"+1 305 594 2728",
    "sg:postcode":"33165",
    "sg:province":"FL",
    "sg:tags":[
        "smoothy"
    ],
    "wof:name":"Koko Kooler - CLOSED",
    "wof:placetype":"venue"
},
  "geometry": {"coordinates":[-80.36799600000001,25.725599],"type":"Point"}
}