{
  "type": "Feature",
  "properties": {
    "iso:country":"US",
    "sg:address":"8539 New York Ave",
    "sg:city":"Hudson",
    "sg:classifiers":[
        {
            "category":"Retail",
            "subcategory":"Auto Repair",
            "type":"Services"
        }
    ],
    "sg:phone":"+1 727 861 1805",
    "sg:postcode":"34667",
    "sg:province":"FL",
    "sg:tags":[
        "repairing",
        "automobile"
    ],
    "wof:name":"Classic Car Care",
    "wof:placetype":"venue"
},
  "geometry": {"coordinates":[-82.67467000000001,28.3749],"type":"Point"}
}