{
  "type": "Feature",
  "properties": {
    "addr:full":"23 Royal Palm Blvd Vero Beach FL 32960",
    "addr:housenumber":"23",
    "addr:postcode":"32960",
    "addr:street":"Royal Palm Blvd",
    "iso:country":"US",
    "sg:address":"23 Royal Palm Blvd",
    "sg:city":"Vero Beach",
    "sg:classifiers":[
        {
            "category":"Professional",
            "subcategory":"Business Services",
            "type":"Services"
        }
    ],
    "sg:phone":"+1 772 299 6569",
    "sg:postcode":"32960",
    "sg:province":"FL",
    "sg:tags":[
        "landscape",
        "furniture"
    ],
    "wof:name":"With A Passion LLC",
    "wof:placetype":"venue"
},
  "geometry": {"coordinates":[-80.37639799999999,27.649023],"type":"Point"}
}