{
  "type": "Feature",
  "properties": {
    "addr:full":"4985 SW 165th Ave Hollywood FL 33027",
    "addr:housenumber":"4985",
    "addr:postcode":"33027",
    "addr:street":"Sw 165Th Ave",
    "iso:country":"US",
    "sg:address":"4985 SW 165th Ave",
    "sg:city":"Hollywood",
    "sg:classifiers":[
        {
            "category":"Real Estate",
            "subcategory":"Real Estate Agent",
            "type":"Services"
        }
    ],
    "sg:phone":"+1 954 450 9677",
    "sg:postcode":"33027",
    "sg:province":"FL",
    "wof:name":"Real Management LLC",
    "wof:placetype":"venue"
},
  "geometry": {"coordinates":[-80.36577,25.963692],"type":"Point"}
}