{
  "type": "Feature",
  "properties": {
    "iso:country":"US",
    "sg:address":"3700 N Harbor City Blvd",
    "sg:city":"Melbourne",
    "sg:classifiers":[
        {
            "category":"Shopping",
            "subcategory":"Gifts & Souvenirs",
            "type":"Retail Goods"
        }
    ],
    "sg:phone":"+1 321 253 3549",
    "sg:postcode":"32935",
    "sg:province":"FL",
    "sg:tags":[
        "shop"
    ],
    "wof:name":"Gift Marketing Alliance",
    "wof:placetype":"venue"
},
  "geometry": {"coordinates":[-80.645174,28.167856],"type":"Point"}
}