{
  "type": "Feature",
  "properties": {
    "iso:country":"US",
    "sg:address":"13150 Whitehaven Ln",
    "sg:city":"Fort Myers",
    "sg:classifiers":[
        {
            "category":"Real Estate",
            "subcategory":"Real Estate Agent",
            "type":"Services"
        }
    ],
    "sg:phone":"+1 239 561 1694",
    "sg:postcode":"33966",
    "sg:province":"FL",
    "wof:name":"Heppel Realty",
    "wof:placetype":"venue"
},
  "geometry": {"coordinates":[-81.84054399999999,26.549148],"type":"Point"}
}