{
  "type": "Feature",
  "properties": {
    "iso:country":"US",
    "sg:address":"2325 Cambridge Dr",
    "sg:city":"Sarasota",
    "sg:classifiers":[
        {
            "category":"Shopping",
            "subcategory":"Computers & Home Electronics",
            "type":"Retail Goods"
        }
    ],
    "sg:phone":"+1 941 379 0417",
    "sg:postcode":"34232",
    "sg:province":"FL",
    "sg:tags":[
        "equipment",
        "dealer"
    ],
    "wof:name":"Andy's Computers",
    "wof:placetype":"venue"
},
  "geometry": {"coordinates":[-82.483552,27.312754],"type":"Point"}
}