{
  "type": "Feature",
  "properties": {
    "addr:full":"1001 NE 45th St Oakland Park FL 33334",
    "addr:housenumber":"1001",
    "addr:postcode":"33334",
    "addr:street":"Ne 45Th St",
    "iso:country":"US",
    "sg:address":"1001 NE 45th St",
    "sg:city":"Oakland Park",
    "sg:classifiers":[
        {
            "category":"Arts & Performance",
            "subcategory":"Theater",
            "type":"Entertainment"
        }
    ],
    "sg:phone":"+1 954 776 0416",
    "sg:postcode":"33334",
    "sg:province":"FL",
    "sg:tags":[
        "bureau"
    ],
    "wof:name":"Centaur Entertainment",
    "wof:placetype":"venue"
},
  "geometry": {"coordinates":[-80.13254499999999,26.183204],"type":"Point"}
}