{
  "type": "Feature",
  "properties": {
    "iso:country":"US",
    "sg:address":"604 New Berlin Rd",
    "sg:city":"Jacksonville",
    "sg:classifiers":[
        {
            "category":"Real Estate",
            "subcategory":"Real Estate Agent",
            "type":"Services"
        }
    ],
    "sg:phone":"+1 904 751 6992",
    "sg:postcode":"32218",
    "sg:province":"FL",
    "sg:website":"www.damespointrealty.com",
    "wof:name":"Century 21",
    "wof:placetype":"venue"
},
  "geometry": {"coordinates":[-81.621866,30.467176],"type":"Point"}
}