{
  "type": "Feature",
  "properties": {
    "addr:full":"12020 61st St N West Palm Beach FL 33412",
    "addr:housenumber":"12020",
    "addr:postcode":"33412",
    "addr:street":"61St St N",
    "iso:country":"US",
    "sg:address":"12020 61st St N",
    "sg:city":"West Palm Beach",
    "sg:classifiers":[
        {
            "category":"Building & Trades",
            "subcategory":"Plumbing",
            "type":"Services"
        }
    ],
    "sg:phone":"+1 561 753 4681",
    "sg:postcode":"33412",
    "sg:province":"FL",
    "sg:tags":[
        "contractor"
    ],
    "wof:name":"Tom Kruse Air Conditioning",
    "wof:placetype":"venue"
},
  "geometry": {"coordinates":[-80.23418599999999,26.768496],"type":"Point"}
}