{
  "type": "Feature",
  "properties": {
    "addr:full":"5461 N University Dr Pompano Beach FL 33067",
    "addr:housenumber":"5461",
    "addr:postcode":"33067",
    "addr:street":"N University Dr",
    "iso:country":"US",
    "sg:address":"5461 N University Dr",
    "sg:city":"Pompano Beach",
    "sg:classifiers":[
        {
            "category":"Insurance",
            "subcategory":"Insurance Agent",
            "type":"Services"
        }
    ],
    "sg:phone":"+1 954 753 0041",
    "sg:postcode":"33067",
    "sg:province":"FL",
    "wof:name":"Frank J Petraglia & Associates",
    "wof:placetype":"venue"
},
  "geometry": {"coordinates":[-80.249674,26.296635],"type":"Point"}
}