{
  "type": "Feature",
  "properties": {
    "iso:country":"US",
    "sg:address":"9769 Fox Hollow Rd",
    "sg:city":"Tampa",
    "sg:classifiers":[
        {
            "category":"Personal",
            "type":"Services"
        }
    ],
    "sg:phone":"+1 813 907 8955",
    "sg:postcode":"33647",
    "sg:province":"FL",
    "sg:tags":[
        "control",
        "weight"
    ],
    "wof:name":"ASTOC Body Wrap",
    "wof:placetype":"venue"
},
  "geometry": {"coordinates":[-82.336761,28.151489],"type":"Point"}
}