{
  "type": "Feature",
  "properties": {
    "addr:full":"315 N Clyde Ave Kissimmee FL 34741",
    "addr:housenumber":"315",
    "addr:postcode":"34741",
    "addr:street":"N Clyde Ave",
    "iso:country":"US",
    "sg:address":"315 N Clyde Ave",
    "sg:city":"Kissimmee",
    "sg:classifiers":[
        {
            "category":"Shopping",
            "subcategory":"Discount & Variety Stores",
            "type":"Retail Goods"
        }
    ],
    "sg:phone":"+1 407 847 8166",
    "sg:postcode":"34741",
    "sg:province":"FL",
    "sg:tags":[
        "thrift"
    ],
    "wof:name":"Osceola Opprtnty Ctr Thrft",
    "wof:placetype":"venue"
},
  "geometry": {"coordinates":[-81.41316,28.295545],"type":"Point"}
}