{
  "type": "Feature",
  "properties": {
    "iso:country":"US",
    "sg:address":"4610 SW 75th Ave",
    "sg:city":"Miami",
    "sg:classifiers":[
        {
            "category":"Wholesale",
            "subcategory":"Hardware",
            "type":"Manufacturing & Wholesale Goods"
        }
    ],
    "sg:phone":"+1 305 260 0043",
    "sg:postcode":"33155",
    "sg:province":"FL",
    "wof:name":"Graves & Associates",
    "wof:placetype":"venue"
},
  "geometry": {"coordinates":[-80.316965,25.728411],"type":"Point"}
}