{
  "type": "Feature",
  "properties": {
    "addr:full":"1451 SE 22nd St Cape Coral FL 33990",
    "addr:housenumber":"1451",
    "addr:postcode":"33990",
    "addr:street":"Se 22Nd St",
    "iso:country":"US",
    "sg:address":"1451 SE 22nd St",
    "sg:city":"Cape Coral",
    "sg:classifiers":[
        {
            "category":"Professional",
            "type":"Services"
        }
    ],
    "sg:phone":"+1 954 467 3281",
    "sg:postcode":"33990",
    "sg:province":"FL",
    "sg:tags":[
        "establishment"
    ],
    "wof:name":"Harrington & Co Mntnnc",
    "wof:placetype":"venue"
},
  "geometry": {"coordinates":[-81.944553,26.611256],"type":"Point"}
}