{
  "type": "Feature",
  "properties": {
    "iso:country":"US",
    "sg:address":"725 Airport Pulling Rd S",
    "sg:city":"Naples",
    "sg:classifiers":[
        {
            "category":"Government",
            "subcategory":"Police Station",
            "type":"Public Place"
        }
    ],
    "sg:phone":"+1 239 417 6385",
    "sg:postcode":"34104",
    "sg:province":"FL",
    "sg:tags":[
        "driver",
        "exam",
        "license",
        "center"
    ],
    "wof:name":"Drivers License Center",
    "wof:placetype":"venue"
},
  "geometry": {"coordinates":[-81.7666,26.147004],"type":"Point"}
}