{
  "type": "Feature",
  "properties": {
    "iso:country":"US",
    "sg:address":"5955 Factory Shops Blvd",
    "sg:city":"Ellenton",
    "sg:classifiers":[
        {
            "category":"Home & Garden",
            "subcategory":"Home Furnishings",
            "type":"Retail Goods"
        }
    ],
    "sg:phone":"+1 941 721 7198",
    "sg:postcode":"34222",
    "sg:province":"FL",
    "wof:name":"Westpoint Stevens 980",
    "wof:placetype":"venue"
},
  "geometry": {"coordinates":[-82.503635,27.534142],"type":"Point"}
}