{
  "type": "Feature",
  "properties": {
    "iso:country":"US",
    "sg:address":"2622 NW 43rd St Ste B1",
    "sg:city":"Gainesville",
    "sg:classifiers":[
        {
            "category":"Professional",
            "subcategory":"Accounting & Tax Preparation",
            "type":"Services"
        }
    ],
    "sg:phone":"+1 352 373 3553",
    "sg:postcode":"32606",
    "sg:province":"FL",
    "sg:tags":[
        "public",
        "accountants-certified"
    ],
    "wof:name":"Sisler & Co Cpas",
    "wof:placetype":"venue"
},
  "geometry": {"coordinates":[-82.388938,29.676946],"type":"Point"}
}