{
  "type": "Feature",
  "properties": {
    "addr:full":"1840 Pine Wood Ct Fort Myers FL 33905",
    "addr:housenumber":"1840",
    "addr:postcode":"33905",
    "addr:street":"Pine Wood Ct",
    "iso:country":"US",
    "sg:address":"1840 Pine Wood Ct",
    "sg:city":"Fort Myers",
    "sg:classifiers":[
        {
            "category":"Travel",
            "subcategory":"Travel Agent",
            "type":"Entertainment"
        }
    ],
    "sg:phone":"+1 239 693 9324",
    "sg:postcode":"33905",
    "sg:province":"FL",
    "sg:tags":[
        "agency"
    ],
    "wof:name":"Pak N Go Travel",
    "wof:placetype":"venue"
},
  "geometry": {"coordinates":[-81.722039,26.717658],"type":"Point"}
}