{
  "type": "Feature",
  "properties": {
    "addr:full":"1686 SE Baya Dr Lake City FL 32025",
    "addr:housenumber":"1686",
    "addr:postcode":"32025",
    "addr:street":"Se Baya Dr",
    "iso:country":"US",
    "sg:address":"1686 SE Baya Dr",
    "sg:city":"Lake City",
    "sg:classifiers":[
        {
            "category":"Restaurant",
            "type":"Food & Drink"
        }
    ],
    "sg:menulink":"http://www.allmenus.com/fl/lake-city/111783-subway/menu/",
    "sg:phone":"+1 386 752 6228",
    "sg:postcode":"32025",
    "sg:province":"FL",
    "sg:tags":[
        "american",
        "sandwich"
    ],
    "wof:name":"Subway",
    "wof:placetype":"venue"
},
  "geometry": {"coordinates":[-82.636112,30.183147],"type":"Point"}
}