{
  "type": "Feature",
  "properties": {
    "iso:country":"US",
    "sg:address":"8610 Primrose Dr",
    "sg:city":"Kissimmee",
    "sg:classifiers":[
        {
            "category":"Home & Garden",
            "subcategory":"Furniture",
            "type":"Retail Goods"
        }
    ],
    "sg:phone":"+1 407 346 2714",
    "sg:postcode":"34747",
    "sg:province":"FL",
    "wof:name":"Florida Villa Breaks",
    "wof:placetype":"venue"
},
  "geometry": {"coordinates":[-81.634941,28.330266],"type":"Point"}
}