{
  "type": "Feature",
  "properties": {
    "addr:full":"800 James St Jacksonville FL 32205",
    "addr:housenumber":"800",
    "addr:postcode":"32205",
    "addr:street":"James St",
    "iso:country":"US",
    "sg:address":"800 James St",
    "sg:city":"Jacksonville",
    "sg:classifiers":[
        {
            "category":"Shopping",
            "subcategory":"Party Supplies",
            "type":"Retail Goods"
        },
        {
            "category":"Building & Trades",
            "subcategory":"Equipment Rental",
            "type":"Services"
        },
        {
            "category":"Shopping",
            "subcategory":"Bicycles & Sporting Goods",
            "type":"Retail Goods"
        }
    ],
    "sg:phone":"+1 904 381 8877",
    "sg:postcode":"32205",
    "sg:province":"FL",
    "sg:tags":[
        "yard",
        "store",
        "tent"
    ],
    "sg:website":"http://www.gtpartyrentals.com/",
    "wof:name":"Beachview & GT Party Rentals",
    "wof:placetype":"venue"
},
  "geometry": {"coordinates":[-81.699043,30.316521],"type":"Point"}
}