{
  "type": "Feature",
  "properties": {
    "addr:full":"1204 W Charter St Tampa FL 33602",
    "addr:housenumber":"1204",
    "addr:postcode":"33602",
    "addr:street":"W Charter St",
    "iso:country":"US",
    "sg:address":"1204 W Charter St",
    "sg:city":"Tampa",
    "sg:classifiers":[
        {
            "category":"Professional",
            "subcategory":"Management & Consulting",
            "type":"Services"
        }
    ],
    "sg:phone":"+1 813 229 7113",
    "sg:postcode":"33602",
    "sg:province":"FL",
    "wof:name":"Paradox Consulting Group  Inc",
    "wof:placetype":"venue"
},
  "geometry": {"coordinates":[-82.47823099999999,27.970208],"type":"Point"}
}