{
  "type": "Feature",
  "properties": {
    "iso:country":"US",
    "sg:address":"2000 Main St Ste 402",
    "sg:city":"Fort Myers",
    "sg:classifiers":[
        {
            "category":"Professional",
            "subcategory":"Lawyer & Legal Services",
            "type":"Services"
        }
    ],
    "sg:phone":"+1 239 337 7787",
    "sg:postcode":"33901",
    "sg:province":"FL",
    "wof:name":"George Hartz Lundeen Fulmer Johnstone King & Stvns",
    "wof:placetype":"venue"
},
  "geometry": {"coordinates":[-81.87220000000001,26.641399],"type":"Point"}
}