{
  "type": "Feature",
  "properties": {
    "iso:country":"US",
    "sg:address":"534 Burns Ct",
    "sg:city":"Sarasota",
    "sg:classifiers":[
        {
            "category":"Personal",
            "subcategory":"Beauty Salon",
            "type":"Services"
        }
    ],
    "sg:phone":"+1 941 953 5415",
    "sg:postcode":"34236",
    "sg:province":"FL",
    "wof:name":"Silvana Hair Design",
    "wof:placetype":"venue"
},
  "geometry": {"coordinates":[-82.53975699999999,27.332203],"type":"Point"}
}