{
  "type": "Feature",
  "properties": {
    "iso:country":"US",
    "sg:address":"2701 34th St N",
    "sg:city":"St Petersburg",
    "sg:classifiers":[
        {
            "category":"Health Services",
            "subcategory":"Nursing And Care Facility",
            "type":"Services"
        },
        {
            "category":"Home & Garden",
            "subcategory":"Mobile Homes",
            "type":"Retail Goods"
        }
    ],
    "sg:phone":"+1 727 323 4905",
    "sg:postcode":"33713",
    "sg:province":"FL",
    "sg:tags":[
        "retirement",
        "community"
    ],
    "wof:name":"Conner's Mobile Home Park",
    "wof:placetype":"venue"
},
  "geometry": {"coordinates":[-82.67946999999999,27.797392],"type":"Point"}
}