{
  "type": "Feature",
  "properties": {
    "iso:country":"US",
    "sg:address":"1395 Chaffee Rd S",
    "sg:city":"Jacksonville",
    "sg:classifiers":[
        {
            "category":"Real Estate",
            "subcategory":"Real Estate Services",
            "type":"Services"
        },
        {
            "category":"Real Estate",
            "subcategory":"Real Estate Agent",
            "type":"Services"
        }
    ],
    "sg:phone":"+1 904 772 9802",
    "sg:postcode":"32221",
    "sg:province":"FL",
    "sg:tags":[
        "buyer",
        "management",
        "broker"
    ],
    "wof:name":"Watson Realty Corp.",
    "wof:placetype":"venue"
},
  "geometry": {"coordinates":[-81.848602,30.294279],"type":"Point"}
}