{
  "type": "Feature",
  "properties": {
    "addr:full":"2567 N Forsyth Rd Orlando FL 32807",
    "addr:housenumber":"2567",
    "addr:postcode":"32807",
    "addr:street":"N Forsyth Rd",
    "iso:country":"US",
    "sg:address":"2567 N Forsyth Rd",
    "sg:city":"Orlando",
    "sg:classifiers":[
        {
            "category":"Retail",
            "subcategory":"Auto Repair",
            "type":"Services"
        }
    ],
    "sg:phone":"+1 407 657 7757",
    "sg:postcode":"32807",
    "sg:province":"FL",
    "sg:tags":[
        "repairing",
        "automobile"
    ],
    "wof:name":"Dennis' Automotive",
    "wof:placetype":"venue"
},
  "geometry": {"coordinates":[-81.29455900000001,28.581571],"type":"Point"}
}