{
  "type": "Feature",
  "properties": {
    "addr:full":"2040 Mohawk Trl Maitland FL 32751",
    "addr:housenumber":"2040",
    "addr:postcode":"32751",
    "addr:street":"Mohawk Trl",
    "iso:country":"US",
    "sg:address":"2040 Mohawk Trl",
    "sg:city":"Maitland",
    "sg:classifiers":[
        {
            "category":"Manufacturing",
            "subcategory":"Printing",
            "type":"Manufacturing & Wholesale Goods"
        }
    ],
    "sg:phone":"+1 407 645 4053",
    "sg:postcode":"32751",
    "sg:province":"FL",
    "sg:tags":[
        "lithographic",
        "commercial",
        "photocopying"
    ],
    "wof:name":"Factors Printing Plus",
    "wof:placetype":"venue"
},
  "geometry": {"coordinates":[-81.34029200000001,28.635707],"type":"Point"}
}