{
  "type": "Feature",
  "properties": {
    "iso:country":"US",
    "sg:address":"933 45th St",
    "sg:city":"West Palm Beach",
    "sg:classifiers":[
        {
            "category":"Health Services",
            "subcategory":"Clinic",
            "type":"Services"
        }
    ],
    "sg:phone":"+1 561 845 2323",
    "sg:postcode":"33407",
    "sg:province":"FL",
    "sg:tags":[
        "banks",
        "blood",
        "center"
    ],
    "wof:name":"South Florida Blood Banks Inc",
    "wof:placetype":"venue"
},
  "geometry": {"coordinates":[-80.06495200000001,26.753264],"type":"Point"}
}