{
  "type": "Feature",
  "properties": {
    "addr:full":"2177 Davis Ct Fort Myers FL 33916",
    "addr:housenumber":"2177",
    "addr:postcode":"33916",
    "addr:street":"Davis Ct",
    "iso:country":"US",
    "sg:address":"2177 Davis Ct",
    "sg:city":"Fort Myers",
    "sg:classifiers":[
        {
            "category":"Building & Trades",
            "subcategory":"Landscaping Services",
            "type":"Services"
        }
    ],
    "sg:phone":"+1 239 337 0065",
    "sg:postcode":"33916",
    "sg:province":"FL",
    "sg:tags":[
        "lawn",
        "maintenance",
        "grounds"
    ],
    "wof:name":"Fletcher & Son Lawn Svc",
    "wof:placetype":"venue"
},
  "geometry": {"coordinates":[-81.83720700000001,26.640017],"type":"Point"}
}