{
  "type": "Feature",
  "properties": {
    "iso:country":"US",
    "sg:address":"3800 SW 186th Ct",
    "sg:city":"Dunnellon",
    "sg:classifiers":[
        {
            "category":"Building & Trades",
            "subcategory":"Construction",
            "type":"Services"
        }
    ],
    "sg:phone":"+1 352 465 0543",
    "sg:postcode":"34432",
    "sg:province":"FL",
    "sg:tags":[
        "hanging",
        "contractor"
    ],
    "wof:name":"Andrew Nichols Painting",
    "wof:placetype":"venue"
},
  "geometry": {"coordinates":[-82.430266,29.151641],"type":"Point"}
}