{
  "type": "Feature",
  "properties": {
    "iso:country":"US",
    "sg:address":"1619 Grand Heritage Blvd",
    "sg:city":"Valrico",
    "sg:classifiers":[
        {
            "category":"Manufacturing",
            "subcategory":"Printing",
            "type":"Manufacturing & Wholesale Goods"
        }
    ],
    "sg:phone":"+1 813 655 8180",
    "sg:postcode":"33594",
    "sg:province":"FL",
    "sg:tags":[
        "publishing"
    ],
    "wof:name":"Starfish Publishing Inc",
    "wof:placetype":"venue"
},
  "geometry": {"coordinates":[-82.25937399999999,27.948297],"type":"Point"}
}