{
  "type": "Feature",
  "properties": {
    "addr:full":"5533 Carmel Ln Lake Worth FL 33463",
    "addr:housenumber":"5533",
    "addr:postcode":"33463",
    "addr:street":"Carmel Ln",
    "iso:country":"US",
    "sg:address":"5533 Carmel Ln",
    "sg:city":"Lake Worth",
    "sg:classifiers":[
        {
            "category":"Building & Trades",
            "subcategory":"Construction",
            "type":"Services"
        }
    ],
    "sg:phone":"+1 561 586 7664",
    "sg:postcode":"33463",
    "sg:province":"FL",
    "sg:tags":[
        "general",
        "retail",
        "commercial",
        "contractor"
    ],
    "wof:name":"Hallmark Construction Inds",
    "wof:placetype":"venue"
},
  "geometry": {"coordinates":[-80.124871,26.593828],"type":"Point"}
}