{
  "type": "Feature",
  "properties": {
    "addr:full":"905 Brickell Bay Dr # 2024 Miami FL 33131",
    "addr:housenumber":"905",
    "addr:postcode":"33131",
    "addr:street":"Bay Dr # 2024",
    "iso:country":"US",
    "sg:address":"905 Brickell Bay Dr # 2024",
    "sg:city":"Miami",
    "sg:classifiers":[
        {
            "category":"Travel",
            "subcategory":"Travel Agent",
            "type":"Entertainment"
        }
    ],
    "sg:phone":"+1 305 350 1910",
    "sg:postcode":"33131",
    "sg:province":"FL",
    "sg:tags":[
        "agency",
        "services-commercial"
    ],
    "wof:name":"123 Travel Inc",
    "wof:placetype":"venue"
},
  "geometry": {"coordinates":[-80.189792,25.764707],"type":"Point"}
}