{
  "type": "Feature",
  "properties": {
    "addr:full":"284 N Nova Rd Daytona Beach FL 32114",
    "addr:housenumber":"284",
    "addr:postcode":"32114",
    "addr:street":"N Nova Rd",
    "iso:country":"US",
    "sg:address":"284 N Nova Rd",
    "sg:city":"Daytona Beach",
    "sg:classifiers":[
        {
            "category":"Recreation",
            "type":"Entertainment"
        }
    ],
    "sg:phone":"+1 386 257 2881",
    "sg:postcode":"32114",
    "sg:province":"FL",
    "sg:tags":[
        "bingo",
        "game"
    ],
    "wof:name":"Daytona Beach Bingo",
    "wof:placetype":"venue"
},
  "geometry": {"coordinates":[-81.039885,29.203377],"type":"Point"}
}