{
  "type": "Feature",
  "properties": {
    "iso:country":"US",
    "sg:address":"6452 Quail Hollow Blvd",
    "sg:city":"Wesley Chapel",
    "sg:classifiers":[
        {
            "category":"Social Services",
            "type":"Services"
        }
    ],
    "sg:phone":"+1 813 991 4840",
    "sg:postcode":"33544",
    "sg:province":"FL",
    "sg:tags":[
        "mission"
    ],
    "wof:name":"Wings Of Morning",
    "wof:placetype":"venue"
},
  "geometry": {"coordinates":[-82.354259,28.252217],"type":"Point"}
}