{
  "type": "Feature",
  "properties": {
    "addr:full":"5321 Gunn Hwy Tampa FL 33624",
    "addr:housenumber":"5321",
    "addr:postcode":"33624",
    "addr:street":"Gunn Hwy",
    "iso:country":"US",
    "sg:address":"5321 Gunn Hwy",
    "sg:city":"Tampa",
    "sg:classifiers":[
        {
            "category":"Retail",
            "subcategory":"Animal Services",
            "type":"Services"
        }
    ],
    "sg:phone":"+1 813 264 4224",
    "sg:postcode":"33624",
    "sg:province":"FL",
    "wof:name":"Kitty City",
    "wof:placetype":"venue"
},
  "geometry": {"coordinates":[-82.52983399999999,28.056314],"type":"Point"}
}