{
  "type": "Feature",
  "properties": {
    "addr:full":"6119 Central Ave New Port Richey FL 34653",
    "addr:housenumber":"6119",
    "addr:postcode":"34653",
    "addr:street":"Central Ave",
    "iso:country":"US",
    "sg:address":"6119 Central Ave",
    "sg:city":"New Port Richey",
    "sg:classifiers":[
        {
            "category":"Real Estate",
            "subcategory":"Real Estate Agent",
            "type":"Services"
        }
    ],
    "sg:phone":"+1 727 815 8845",
    "sg:postcode":"34653",
    "sg:province":"FL",
    "wof:name":"D-Land-C Real Estate",
    "wof:placetype":"venue"
},
  "geometry": {"coordinates":[-82.71296599999999,28.251886],"type":"Point"}
}