{
  "type": "Feature",
  "properties": {
    "addr:full":"609 Collins Ave Miami Beach FL 33139",
    "addr:housenumber":"609",
    "addr:postcode":"33139",
    "addr:street":"Collins Ave",
    "iso:country":"US",
    "sg:address":"609 Collins Ave",
    "sg:city":"Miami Beach",
    "sg:classifiers":[
        {
            "category":"Professional",
            "subcategory":"Management & Consulting",
            "type":"Services"
        }
    ],
    "sg:phone":"+1 305 672 4689",
    "sg:postcode":"33139",
    "sg:province":"FL",
    "sg:tags":[
        "marketing",
        "program"
    ],
    "wof:name":"My Clicks",
    "wof:placetype":"venue"
},
  "geometry": {"coordinates":[-80.132431,25.776805],"type":"Point"}
}