{
  "type": "Feature",
  "properties": {
    "addr:full":"14850 Naranja Lakes Blvd Homestead FL 33032",
    "addr:housenumber":"14850",
    "addr:postcode":"33032",
    "addr:street":"Naranja Lakes Blvd",
    "iso:country":"US",
    "sg:address":"14850 Naranja Lakes Blvd",
    "sg:city":"Homestead",
    "sg:classifiers":[
        {
            "category":"Real Estate",
            "subcategory":"Real Estate Operator",
            "type":"Services"
        }
    ],
    "sg:phone":"+1 305 245 6857",
    "sg:postcode":"33032",
    "sg:province":"FL",
    "sg:tags":[
        "condominium"
    ],
    "wof:name":"Naranja Lakes Condo Assn",
    "wof:placetype":"venue"
},
  "geometry": {"coordinates":[-80.433637,25.510889],"type":"Point"}
}