{
  "type": "Feature",
  "properties": {
    "iso:country":"US",
    "sg:address":"4242 NW 2nd St Apt 1409",
    "sg:city":"Miami",
    "sg:classifiers":[
        {
            "category":"Manufacturing",
            "subcategory":"Wood Products",
            "type":"Manufacturing & Wholesale Goods"
        }
    ],
    "sg:phone":"+1 305 446 5866",
    "sg:postcode":"33126",
    "sg:province":"FL",
    "sg:tags":[
        "millwork"
    ],
    "wof:name":"South Millwork, Corp.",
    "wof:placetype":"venue"
},
  "geometry": {"coordinates":[-80.264641,25.773403],"type":"Point"}
}