{
  "type": "Feature",
  "properties": {
    "iso:country":"US",
    "sg:address":"758 NE Alice St",
    "sg:city":"Jensen Beach",
    "sg:classifiers":[
        {
            "category":"Building & Trades",
            "subcategory":"Landscaping Services",
            "type":"Services"
        }
    ],
    "sg:phone":"+1 772 334 6508",
    "sg:postcode":"34957",
    "sg:province":"FL",
    "wof:name":"Scott A Birley",
    "wof:placetype":"venue"
},
  "geometry": {"coordinates":[-80.242701,27.216807],"type":"Point"}
}