{
  "type": "Feature",
  "properties": {
    "addr:full":"2151 NE 167th St North Miami Bch FL 33162",
    "addr:housenumber":"2151",
    "addr:postcode":"33162",
    "addr:street":"Ne 167Th St",
    "iso:country":"US",
    "sg:address":"2151 NE 167th St",
    "sg:city":"North Miami Bch",
    "sg:classifiers":[
        {
            "category":"Retail",
            "subcategory":"Repair Shop",
            "type":"Services"
        }
    ],
    "sg:phone":"+1 305 653 7000",
    "sg:postcode":"33162",
    "sg:province":"FL",
    "sg:tags":[
        "lock",
        "locksmith"
    ],
    "wof:name":"A 411 Locksmith",
    "wof:placetype":"venue"
},
  "geometry": {"coordinates":[-80.15697900000001,25.929814],"type":"Point"}
}