{
  "type": "Feature",
  "properties": {
    "addr:full":"600 State Hwy 66 Sebring FL 33875",
    "addr:housenumber":"600",
    "addr:postcode":"33875",
    "addr:street":"State Hwy 66",
    "iso:country":"US",
    "sg:address":"600 State Hwy 66",
    "sg:city":"Sebring",
    "sg:classifiers":[
        {
            "category":"Manufacturing",
            "subcategory":"Tools & Machinery",
            "type":"Manufacturing & Wholesale Goods"
        }
    ],
    "sg:phone":"+1 863 382 2166",
    "sg:postcode":"33875",
    "sg:province":"FL",
    "sg:tags":[
        "engine",
        "equipment",
        "electrical",
        "mfg"
    ],
    "wof:name":"Tradewinds Power Corp",
    "wof:placetype":"venue"
},
  "geometry": {"coordinates":[-81.430251,27.425324],"type":"Point"}
}