{
  "type": "Feature",
  "properties": {
    "iso:country":"US",
    "sg:address":"18600 NW 87th Ave",
    "sg:city":"Hialeah",
    "sg:classifiers":[
        {
            "category":"Restaurant",
            "type":"Food & Drink"
        }
    ],
    "sg:menulink":"http://www.allmenus.com/fl/hialeah/98359-carrabbas/menu/",
    "sg:phone":"+1 305 816 9131",
    "sg:postcode":"33015",
    "sg:province":"FL",
    "sg:tags":[
        "italian"
    ],
    "wof:name":"Carrabba's",
    "wof:placetype":"venue"
},
  "geometry": {"coordinates":[-80.342326,25.942399],"type":"Point"}
}