{
  "type": "Feature",
  "properties": {
    "addr:full":"117 John Sims Pkwy Niceville FL 32578",
    "addr:housenumber":"117",
    "addr:postcode":"32578",
    "addr:street":"John Sims Pkwy",
    "iso:country":"US",
    "sg:address":"117 John Sims Pkwy",
    "sg:city":"Niceville",
    "sg:classifiers":[
        {
            "category":"Restaurant",
            "type":"Food & Drink"
        }
    ],
    "sg:phone":"+1 850 678 9004",
    "sg:postcode":"32578",
    "sg:province":"FL",
    "wof:name":"Kubi's Metropolitan Grill",
    "wof:placetype":"venue"
},
  "geometry": {"coordinates":[-86.492873,30.521895],"type":"Point"}
}