{
  "type": "Feature",
  "properties": {
    "addr:full":"13845 NW 20th St Hollywood FL 33028",
    "addr:housenumber":"13845",
    "addr:postcode":"33028",
    "addr:street":"Nw 20Th St",
    "iso:country":"US",
    "sg:address":"13845 NW 20th St",
    "sg:city":"Hollywood",
    "sg:classifiers":[
        {
            "category":"Autos & Motor Vehicles",
            "subcategory":"Automobile Sales",
            "type":"Retail Goods"
        }
    ],
    "sg:phone":"+1 954 443 0709",
    "sg:postcode":"33028",
    "sg:province":"FL",
    "sg:tags":[
        "used"
    ],
    "wof:name":"Man Motor Sales LLC",
    "wof:placetype":"venue"
},
  "geometry": {"coordinates":[-80.333842,26.026731],"type":"Point"}
}