{
  "type": "Feature",
  "properties": {
    "iso:country":"US",
    "sg:address":"2344 Kings Rd",
    "sg:city":"Jacksonville",
    "sg:classifiers":[
        {
            "category":"Organizations",
            "subcategory":"Religious Organization",
            "type":"Services"
        }
    ],
    "sg:phone":"+1 904 354 0448",
    "sg:postcode":"32209",
    "sg:province":"FL",
    "sg:tags":[
        "church"
    ],
    "wof:name":"Mighty Church Of The Redeemed",
    "wof:placetype":"venue"
},
  "geometry": {"coordinates":[-81.700936,30.350549],"type":"Point"}
}