{
  "type": "Feature",
  "properties": {
    "iso:country":"US",
    "sg:address":"961 N Park Ave",
    "sg:city":"Winter Park",
    "sg:classifiers":[
        {
            "category":"Real Estate",
            "subcategory":"Real Estate Operator",
            "type":"Services"
        }
    ],
    "sg:phone":"+1 407 622 7495",
    "sg:postcode":"32789",
    "sg:province":"FL",
    "sg:tags":[
        "building",
        "nonresidential"
    ],
    "wof:name":"Retail Development Properties",
    "wof:placetype":"venue"
},
  "geometry": {"coordinates":[-81.350798,28.60547],"type":"Point"}
}