{
  "type": "Feature",
  "properties": {
    "iso:country":"US",
    "sg:address":"10995 SE Federal Hwy",
    "sg:city":"Hobe Sound",
    "sg:classifiers":[
        {
            "category":"Professional",
            "type":"Services"
        }
    ],
    "sg:phone":"+1 772 546 6314",
    "sg:postcode":"33455",
    "sg:province":"FL",
    "sg:tags":[
        "establishment"
    ],
    "wof:name":"Gattle's Inc",
    "wof:placetype":"venue"
},
  "geometry": {"coordinates":[-80.141779,27.071447],"type":"Point"}
}