{
  "type": "Feature",
  "properties": {
    "iso:country":"US",
    "sg:address":"6399 Coniston St",
    "sg:city":"Port Charlotte",
    "sg:classifiers":[
        {
            "category":"Building & Trades",
            "subcategory":"Construction",
            "type":"Services"
        }
    ],
    "sg:phone":"+1 941 698 0018",
    "sg:postcode":"33981",
    "sg:province":"FL",
    "sg:tags":[
        "painter"
    ],
    "wof:name":"Schmidt's Fine Interior Fnshs",
    "wof:placetype":"venue"
},
  "geometry": {"coordinates":[-82.229962,26.936588],"type":"Point"}
}