{
  "type": "Feature",
  "properties": {
    "iso:country":"US",
    "sg:address":"547 W Grant St",
    "sg:city":"Orlando",
    "sg:classifiers":[
        {
            "category":"Wholesale",
            "subcategory":"Construction Materials",
            "type":"Manufacturing & Wholesale Goods"
        }
    ],
    "sg:phone":"+1 407 839 3959",
    "sg:postcode":"32805",
    "sg:province":"FL",
    "sg:tags":[
        "trim",
        "distributes",
        "molding"
    ],
    "wof:name":"Genesis Tilemates Ltd",
    "wof:placetype":"venue"
},
  "geometry": {"coordinates":[-81.386047,28.516588],"type":"Point"}
}