{
  "type": "Feature",
  "properties": {
    "addr:full":"3065 Broadway Fort Myers FL 33901",
    "addr:housenumber":"3065",
    "addr:postcode":"33901",
    "addr:street":"Broadway",
    "iso:country":"US",
    "sg:address":"3065 Broadway",
    "sg:city":"Fort Myers",
    "sg:classifiers":[
        {
            "category":"Wholesale",
            "subcategory":"Furniture",
            "type":"Manufacturing & Wholesale Goods"
        }
    ],
    "sg:phone":"+1 239 337 4775",
    "sg:postcode":"33901",
    "sg:province":"FL",
    "sg:tags":[
        "furnishing",
        "church"
    ],
    "wof:name":"Ebenzer Baptist Church",
    "wof:placetype":"venue"
},
  "geometry": {"coordinates":[-81.86784400000001,26.621272],"type":"Point"}
}