{
  "type": "Feature",
  "properties": {
    "addr:full":"430 Meadowlark Ln Naples FL 34105",
    "addr:housenumber":"430",
    "addr:postcode":"34105",
    "addr:street":"Meadowlark Ln",
    "iso:country":"US",
    "sg:address":"430 Meadowlark Ln",
    "sg:city":"Naples",
    "sg:classifiers":[
        {
            "category":"Building & Trades",
            "subcategory":"Cleaning & Sanitation",
            "type":"Services"
        }
    ],
    "sg:phone":"+1 239 340 0670",
    "sg:postcode":"34105",
    "sg:province":"FL",
    "sg:tags":[
        "maintenance"
    ],
    "wof:name":"Suely Campero",
    "wof:placetype":"venue"
},
  "geometry": {"coordinates":[-81.769419,26.20632],"type":"Point"}
}