{
  "type": "Feature",
  "properties": {
    "addr:full":"1863 Bishop Estates Rd Jacksonville FL 32259",
    "addr:housenumber":"1863",
    "addr:postcode":"32259",
    "addr:street":"Bishop Estates Rd",
    "iso:country":"US",
    "sg:address":"1863 Bishop Estates Rd",
    "sg:city":"Jacksonville",
    "sg:classifiers":[
        {
            "category":"Building & Trades",
            "subcategory":"Landscaping Services",
            "type":"Services"
        }
    ],
    "sg:phone":"+1 904 287 8829",
    "sg:postcode":"32259",
    "sg:province":"FL",
    "wof:name":"Rouzies Lawncare Housecleaning",
    "wof:placetype":"venue"
},
  "geometry": {"coordinates":[-81.607558,30.127371],"type":"Point"}
}