{
  "type": "Feature",
  "properties": {
    "addr:full":"10584 Old Saint Augustine Rd Jacksonville FL 32257",
    "addr:housenumber":"10584",
    "addr:postcode":"32257",
    "addr:street":"Old Saint Augustine Rd",
    "iso:country":"US",
    "sg:address":"10584 Old Saint Augustine Rd",
    "sg:city":"Jacksonville",
    "sg:classifiers":[
        {
            "category":"Food & Beverages",
            "subcategory":"Groceries & Convenience Stores",
            "type":"Retail Goods"
        }
    ],
    "sg:phone":"+1 904 288 8288",
    "sg:postcode":"32257",
    "sg:province":"FL",
    "sg:tags":[
        "grocer"
    ],
    "wof:name":"Jax Oriental Market",
    "wof:placetype":"venue"
},
  "geometry": {"coordinates":[-81.606754,30.181621],"type":"Point"}
}