{
  "type": "Feature",
  "properties": {
    "iso:country":"US",
    "sg:address":"5450 International Dr",
    "sg:city":"Orlando",
    "sg:classifiers":[
        {
            "category":"Food & Beverages",
            "subcategory":"Supermarket",
            "type":"Retail Goods"
        }
    ],
    "sg:phone":"+1 407 351 1550",
    "sg:postcode":"32819",
    "sg:province":"FL",
    "sg:tags":[
        "super",
        "store"
    ],
    "wof:name":"Maldiven",
    "wof:placetype":"venue"
},
  "geometry": {"coordinates":[-81.452488,28.462299],"type":"Point"}
}