{
  "type": "Feature",
  "properties": {
    "iso:country":"US",
    "sg:address":"6601 Broken Arrow Rd",
    "sg:city":"Fort Myers",
    "sg:classifiers":[
        {
            "category":"Building & Trades",
            "subcategory":"Construction",
            "type":"Services"
        }
    ],
    "sg:phone":"+1 239 437 4949",
    "sg:postcode":"33912",
    "sg:province":"FL",
    "sg:tags":[
        "general",
        "contractor"
    ],
    "wof:name":"Concrete Preservation & Repair",
    "wof:placetype":"venue"
},
  "geometry": {"coordinates":[-81.842353,26.508459],"type":"Point"}
}