{
  "type": "Feature",
  "properties": {
    "iso:country":"US",
    "sg:address":"4414 Florida National Dr",
    "sg:city":"Lakeland",
    "sg:classifiers":[
        {
            "category":"Health Services",
            "subcategory":"Chiropractor",
            "type":"Services"
        }
    ],
    "sg:phone":"+1 863 644 8451",
    "sg:postcode":"33813",
    "sg:province":"FL",
    "wof:name":"Pamela D Greene DC",
    "wof:placetype":"venue"
},
  "geometry": {"coordinates":[-81.958432,27.984648],"type":"Point"}
}