{
  "type": "Feature",
  "properties": {
    "addr:full":"1461 Capital Cir NW Tallahassee FL 32303",
    "addr:housenumber":"1461",
    "addr:postcode":"32303",
    "addr:street":"Capital Cir Nw",
    "iso:country":"US",
    "sg:address":"1461 Capital Cir NW",
    "sg:city":"Tallahassee",
    "sg:classifiers":[
        {
            "category":"Banks & Credit Unions",
            "subcategory":"Bank",
            "type":"Services"
        }
    ],
    "sg:phone":"+1 850 386 2225",
    "sg:postcode":"32303",
    "sg:province":"FL",
    "sg:website":"www.premierbnk.com",
    "wof:name":"Premier Bank",
    "wof:placetype":"venue"
},
  "geometry": {"coordinates":[-84.361109,30.461568],"type":"Point"}
}