{
  "type": "Feature",
  "properties": {
    "addr:full":"2705 Tamiami Trl Punta Gorda FL 33950",
    "addr:housenumber":"2705",
    "addr:postcode":"33950",
    "addr:street":"Tamiami Trl",
    "iso:country":"US",
    "sg:address":"2705 Tamiami Trl",
    "sg:city":"Punta Gorda",
    "sg:classifiers":[
        {
            "category":"Personal",
            "subcategory":"Beauty Salon",
            "type":"Services"
        }
    ],
    "sg:phone":"+1 941 505 1011",
    "sg:postcode":"33950",
    "sg:province":"FL",
    "sg:tags":[
        "shop"
    ],
    "wof:name":"Vicky's Shear Experience Hair",
    "wof:placetype":"venue"
},
  "geometry": {"coordinates":[-82.04632100000001,26.915314],"type":"Point"}
}