{
  "type": "Feature",
  "properties": {
    "addr:full":"1424 Ponce De Leon Blvd Coral Gables FL 33134",
    "addr:housenumber":"1424",
    "addr:postcode":"33134",
    "addr:street":"Ponce De Leon Blvd",
    "iso:country":"US",
    "sg:address":"1424 Ponce De Leon Blvd",
    "sg:city":"Coral Gables",
    "sg:classifiers":[
        {
            "category":"Professional",
            "subcategory":"Printing & Photocopies",
            "type":"Services"
        }
    ],
    "sg:phone":"+1 305 442 0952",
    "sg:postcode":"33134",
    "sg:province":"FL",
    "wof:name":"Copy Express",
    "wof:placetype":"venue"
},
  "geometry": {"coordinates":[-80.259102,25.7584],"type":"Point"}
}