{
  "type": "Feature",
  "properties": {
    "addr:full":"415 E Vine St Kissimmee FL 34744",
    "addr:housenumber":"415",
    "addr:postcode":"34744",
    "addr:street":"E Vine St",
    "iso:country":"US",
    "sg:address":"415 E Vine St",
    "sg:city":"Kissimmee",
    "sg:classifiers":[
        {
            "category":"Health Services",
            "subcategory":"Medical Lab",
            "type":"Services"
        }
    ],
    "sg:phone":"+1 407 846 3399",
    "sg:postcode":"34744",
    "sg:province":"FL",
    "sg:tags":[
        "laboratory"
    ],
    "wof:name":"Kissimmee Crown & Bridge Std",
    "wof:placetype":"venue"
},
  "geometry": {"coordinates":[-81.400114,28.304538],"type":"Point"}
}