{
  "type": "Feature",
  "properties": {
    "addr:full":"3273 State Hwy 207 Elkton FL 32033",
    "addr:housenumber":"3273",
    "addr:postcode":"32033",
    "addr:street":"State Hwy 207",
    "iso:country":"US",
    "sg:address":"3273 State Hwy 207",
    "sg:city":"Elkton",
    "sg:classifiers":[
        {
            "category":"Wholesale",
            "subcategory":"Vending Machines",
            "type":"Manufacturing & Wholesale Goods"
        }
    ],
    "sg:phone":"+1 904 501 0099",
    "sg:postcode":"32033",
    "sg:province":"FL",
    "sg:tags":[
        "operator"
    ],
    "wof:name":"Jennifer Bortell Vending",
    "wof:placetype":"venue"
},
  "geometry": {"coordinates":[-81.393027,29.812129],"type":"Point"}
}