{
  "type": "Feature",
  "properties": {
    "iso:country":"US",
    "sg:address":"14971 SW 42nd Ter",
    "sg:city":"Miami",
    "sg:classifiers":[
        {
            "category":"Wholesale",
            "subcategory":"Apparel",
            "type":"Manufacturing & Wholesale Goods"
        }
    ],
    "sg:phone":"+1 786 290 8872",
    "sg:postcode":"33185",
    "sg:province":"FL",
    "sg:tags":[
        "wholesaler",
        "trend",
        "accessory"
    ],
    "wof:name":"U S Fashions Corp",
    "wof:placetype":"venue"
},
  "geometry": {"coordinates":[-80.436341,25.727848],"type":"Point"}
}