{
  "type": "Feature",
  "properties": {
    "iso:country":"US",
    "sg:address":"11750 NW 30th Pl",
    "sg:city":"Sunrise",
    "sg:classifiers":[
        {
            "category":"Retail",
            "subcategory":"Laundry & Dry Cleaning",
            "type":"Services"
        }
    ],
    "sg:phone":"+1 954 749 2429",
    "sg:postcode":"33323",
    "sg:province":"FL",
    "sg:tags":[
        "cleaners",
        "rug",
        "carpet"
    ],
    "wof:name":"Bel Air Cleaning",
    "wof:placetype":"venue"
},
  "geometry": {"coordinates":[-80.302616,26.164027],"type":"Point"}
}