{
  "type": "Feature",
  "properties": {
    "addr:full":"2742 SW 25th Ter Miami FL 33133",
    "addr:housenumber":"2742",
    "addr:postcode":"33133",
    "addr:street":"Sw 25Th Ter",
    "iso:country":"US",
    "sg:address":"2742 SW 25th Ter",
    "sg:city":"Miami",
    "sg:classifiers":[
        {
            "category":"Restaurant",
            "type":"Food & Drink"
        }
    ],
    "sg:phone":"+1 305 442 6790",
    "sg:postcode":"33133",
    "sg:province":"FL",
    "sg:tags":[
        "chinese"
    ],
    "wof:name":"Sun Inn Chinese Restaurant",
    "wof:placetype":"venue"
},
  "geometry": {"coordinates":[-80.23858799999999,25.74416],"type":"Point"}
}