{
  "type": "Feature",
  "properties": {
    "iso:country":"US",
    "sg:address":"201 N Oklahoma St",
    "sg:city":"Bonifay",
    "sg:classifiers":[
        {
            "category":"Government",
            "subcategory":"Court House",
            "type":"Public Place"
        }
    ],
    "sg:phone":"+1 850 547 1104",
    "sg:postcode":"32425",
    "sg:province":"FL",
    "wof:name":"Robert E Brown",
    "wof:placetype":"venue"
},
  "geometry": {"coordinates":[-85.678378,30.794052],"type":"Point"}
}