{
  "type": "Feature",
  "properties": {
    "iso:country":"US",
    "sg:address":"3901 Randall Rd",
    "sg:city":"Green Cove Springs",
    "sg:classifiers":[
        {
            "category":"Building & Trades",
            "subcategory":"Cleaning & Sanitation",
            "type":"Services"
        }
    ],
    "sg:phone":"+1 904 529 9773",
    "sg:postcode":"32043",
    "sg:province":"FL",
    "sg:tags":[
        "maintenance"
    ],
    "wof:name":"Personal Touch Cleaning S",
    "wof:placetype":"venue"
},
  "geometry": {"coordinates":[-81.71023,29.988439],"type":"Point"}
}