{
  "type": "Feature",
  "properties": {
    "iso:country":"US",
    "sg:address":"25028 Kirkwood Ave",
    "sg:city":"Astatula",
    "sg:classifiers":[
        {
            "category":"Building & Trades",
            "subcategory":"Construction",
            "type":"Services"
        }
    ],
    "sg:phone":"+1 352 742 7543",
    "sg:postcode":"34705",
    "sg:province":"FL",
    "sg:tags":[
        "paving",
        "road",
        "contractor"
    ],
    "wof:name":"Astatula Public Works",
    "wof:placetype":"venue"
},
  "geometry": {"coordinates":[-81.734188,28.710287],"type":"Point"}
}