{
  "type": "Feature",
  "properties": {
    "addr:full":"17631 Bocaire Way Boca Raton FL 33487",
    "addr:housenumber":"17631",
    "addr:postcode":"33487",
    "addr:street":"Bocaire Way",
    "iso:country":"US",
    "sg:address":"17631 Bocaire Way",
    "sg:city":"Boca Raton",
    "sg:classifiers":[
        {
            "category":"Manufacturing",
            "subcategory":"Printing",
            "type":"Manufacturing & Wholesale Goods"
        }
    ],
    "sg:phone":"+1 561 999 9938",
    "sg:postcode":"33487",
    "sg:province":"FL",
    "sg:tags":[
        "book"
    ],
    "wof:name":"Back 2 Basics Publishing",
    "wof:placetype":"venue"
},
  "geometry": {"coordinates":[-80.1139,26.415747],"type":"Point"}
}