{
  "type": "Feature",
  "properties": {
    "addr:full":"2460 Absher Rd St Cloud FL 34771",
    "addr:housenumber":"2460",
    "addr:postcode":"34771",
    "addr:street":"Absher Rd",
    "iso:country":"US",
    "sg:address":"2460 Absher Rd",
    "sg:city":"St Cloud",
    "sg:classifiers":[
        {
            "category":"Retail",
            "subcategory":"Repair Shop",
            "type":"Services"
        }
    ],
    "sg:phone":"+1 407 957 9298",
    "sg:postcode":"34771",
    "sg:province":"FL",
    "sg:tags":[
        "lock",
        "locksmith"
    ],
    "wof:name":"Lock Busters",
    "wof:placetype":"venue"
},
  "geometry": {"coordinates":[-81.198798,28.319367],"type":"Point"}
}