{
  "type": "Feature",
  "properties": {
    "iso:country":"US",
    "sg:address":"1920 W Socrum Loop Rd",
    "sg:city":"Lakeland",
    "sg:classifiers":[
        {
            "category":"Place Of Worship",
            "type":"Public Place"
        }
    ],
    "sg:phone":"+1 863 858 0322",
    "sg:postcode":"33810",
    "sg:province":"FL",
    "sg:tags":[
        "church"
    ],
    "wof:name":"Christ Lutheran Church Endowment Fund Inc",
    "wof:placetype":"venue"
},
  "geometry": {"coordinates":[-81.98666799999999,28.164613],"type":"Point"}
}