{
  "type": "Feature",
  "properties": {
    "addr:full":"5700 S Florida Ave Lakeland FL 33813",
    "addr:housenumber":"5700",
    "addr:postcode":"33813",
    "addr:street":"S Florida Ave",
    "iso:country":"US",
    "sg:address":"5700 S Florida Ave",
    "sg:city":"Lakeland",
    "sg:phone":"+1 863 619 6500",
    "sg:postcode":"33813",
    "sg:province":"FL",
    "wof:name":"Louie Mack Steakhouse",
    "wof:placetype":"venue"
},
  "geometry": {"coordinates":[-81.965889,27.962999],"type":"Point"}
}