{
  "type": "Feature",
  "properties": {
    "addr:full":"1595 W French Ave Orange City FL 32763",
    "addr:housenumber":"1595",
    "addr:postcode":"32763",
    "addr:street":"W French Ave",
    "iso:country":"US",
    "sg:address":"1595 W French Ave",
    "sg:city":"Orange City",
    "sg:classifiers":[
        {
            "category":"Social Services",
            "type":"Services"
        }
    ],
    "sg:phone":"+1 386 774 0236",
    "sg:postcode":"32763",
    "sg:province":"FL",
    "sg:tags":[
        "youth",
        "organization",
        "center"
    ],
    "wof:name":"Orange City Little League Inc",
    "wof:placetype":"venue"
},
  "geometry": {"coordinates":[-81.325597,28.952412],"type":"Point"}
}