{
  "type": "Feature",
  "properties": {
    "addr:full":"1000 Derek Ln Oldsmar FL 34677",
    "addr:housenumber":"1000",
    "addr:postcode":"34677",
    "addr:street":"Derek Ln",
    "iso:country":"US",
    "sg:address":"1000 Derek Ln",
    "sg:city":"Oldsmar",
    "sg:classifiers":[
        {
            "category":"Professional",
            "subcategory":"Business Services",
            "type":"Services"
        }
    ],
    "sg:phone":"+1 813 676 3767",
    "sg:postcode":"34677",
    "sg:province":"FL",
    "sg:tags":[
        "train",
        "advertising",
        "provides",
        "promotional"
    ],
    "wof:name":"Country Slasher The",
    "wof:placetype":"venue"
},
  "geometry": {"coordinates":[-82.67853100000001,28.040241],"type":"Point"}
}