{
  "type": "Feature",
  "properties": {
    "iso:country":"US",
    "sg:address":"5 Market Place Ct",
    "sg:city":"Palm Coast",
    "sg:classifiers":[
        {
            "category":"Autos & Motor Vehicles",
            "subcategory":"Auto Supplies",
            "type":"Retail Goods"
        }
    ],
    "sg:phone":"+1 407 438 3611",
    "sg:postcode":"32137",
    "sg:province":"FL",
    "sg:tags":[
        "automobile",
        "parts"
    ],
    "wof:name":"Terry's Collision Eqpt Sales",
    "wof:placetype":"venue"
},
  "geometry": {"coordinates":[-81.270413,29.55533],"type":"Point"}
}