{
  "type": "Feature",
  "properties": {
    "iso:country":"US",
    "sg:address":"9890 NW 28th Ter",
    "sg:city":"Miami",
    "sg:classifiers":[
        {
            "category":"Building & Trades",
            "subcategory":"Electrical",
            "type":"Services"
        }
    ],
    "sg:phone":"+1 305 599 2775",
    "sg:postcode":"33172",
    "sg:province":"FL",
    "sg:tags":[
        "electrical",
        "contractor"
    ],
    "wof:name":"Bortz Electric Inc",
    "wof:placetype":"venue"
},
  "geometry": {"coordinates":[-80.35322499999999,25.800324],"type":"Point"}
}