{
  "type": "Feature",
  "properties": {
    "iso:country":"US",
    "sg:address":"522 Linton Blvd",
    "sg:city":"Delray Beach",
    "sg:classifiers":[
        {
            "category":"Retail",
            "subcategory":"Self-service Laundry",
            "type":"Services"
        }
    ],
    "sg:phone":"+1 561 585 3419",
    "sg:postcode":"33444",
    "sg:province":"FL",
    "sg:tags":[
        "coin"
    ],
    "wof:name":"King Coin Meter Inc",
    "wof:placetype":"venue"
},
  "geometry": {"coordinates":[-80.079178,26.439704],"type":"Point"}
}