{
  "type": "Feature",
  "properties": {
    "iso:country":"US",
    "sg:address":"3181 Gulf Winds Cir",
    "sg:city":"Hernando Beach",
    "sg:classifiers":[
        {
            "category":"Personal",
            "subcategory":"Beauty Salon",
            "type":"Services"
        }
    ],
    "sg:phone":"+1 352 596 0078",
    "sg:postcode":"34607",
    "sg:province":"FL",
    "wof:name":"Luann At Uptown Styles",
    "wof:placetype":"venue"
},
  "geometry": {"coordinates":[-82.66754,28.492175],"type":"Point"}
}