{
  "type": "Feature",
  "properties": {
    "iso:country":"US",
    "sg:address":"7606 34th Ave S",
    "sg:city":"Tampa",
    "sg:classifiers":[
        {
            "category":"Structure",
            "subcategory":"Warehouse",
            "type":"Public Place"
        },
        {
            "category":"Retail",
            "subcategory":"Storage",
            "type":"Services"
        }
    ],
    "sg:phone":"+1 813 635 9384",
    "sg:postcode":"33619",
    "sg:province":"FL",
    "sg:tags":[
        "self",
        "warehouses-merchandise"
    ],
    "wof:name":"Dela Torre Gladys",
    "wof:placetype":"venue"
},
  "geometry": {"coordinates":[-82.370696,27.917708],"type":"Point"}
}