{
  "type": "Feature",
  "properties": {
    "addr:full":"818 N Dixie Hwy West Palm Beach FL 33401",
    "addr:housenumber":"818",
    "addr:postcode":"33401",
    "addr:street":"N Dixie Hwy",
    "iso:country":"US",
    "sg:address":"818 N Dixie Hwy",
    "sg:city":"West Palm Beach",
    "sg:classifiers":[
        {
            "category":"Building & Trades",
            "subcategory":"Construction",
            "type":"Services"
        }
    ],
    "sg:phone":"+1 561 547 6001",
    "sg:postcode":"33401",
    "sg:province":"FL",
    "sg:tags":[
        "general",
        "contractor"
    ],
    "wof:name":"Wise Buy Realty & Investments",
    "wof:placetype":"venue"
},
  "geometry": {"coordinates":[-80.053263,26.72062],"type":"Point"}
}