{
  "type": "Feature",
  "properties": {
    "iso:country":"US",
    "sg:address":"1313 43rd Ave",
    "sg:city":"Vero Beach",
    "sg:classifiers":[
        {
            "category":"Banks & Credit Unions",
            "subcategory":"Bank",
            "type":"Services"
        }
    ],
    "sg:phone":"+1 772 567 7400",
    "sg:postcode":"32960",
    "sg:province":"FL",
    "sg:tags":[
        "mortgage",
        "loan",
        "broker",
        "real estate"
    ],
    "wof:name":"American Discount Mortgage Co",
    "wof:placetype":"venue"
},
  "geometry": {"coordinates":[-80.430375,27.625709],"type":"Point"}
}