{
  "type": "Feature",
  "properties": {
    "iso:country":"US",
    "sg:address":"2420 Tampa Rd",
    "sg:city":"Palm Harbor",
    "sg:classifiers":[
        {
            "category":"Insurance",
            "subcategory":"Insurance Agent",
            "type":"Services"
        }
    ],
    "sg:phone":"+1 727 789 7600",
    "sg:postcode":"34683",
    "sg:province":"FL",
    "wof:name":"State Farm Insurance",
    "wof:placetype":"venue"
},
  "geometry": {"coordinates":[-82.73886899999999,28.067186],"type":"Point"}
}