{
  "type": "Feature",
  "properties": {
    "addr:full":"3640 SW 23rd Ct Fort Lauderdale FL 33312",
    "addr:housenumber":"3640",
    "addr:postcode":"33312",
    "addr:street":"Sw 23Rd Ct",
    "iso:country":"US",
    "sg:address":"3640 SW 23rd Ct",
    "sg:city":"Fort Lauderdale",
    "sg:classifiers":[
        {
            "category":"Building & Trades",
            "subcategory":"Construction",
            "type":"Services"
        }
    ],
    "sg:phone":"+1 954 583 6056",
    "sg:postcode":"33312",
    "sg:province":"FL",
    "sg:tags":[
        "carpentry",
        "contractor"
    ],
    "wof:name":"Robert Josack Carpentry",
    "wof:placetype":"venue"
},
  "geometry": {"coordinates":[-80.194317,26.092548],"type":"Point"}
}