{
  "type": "Feature",
  "properties": {
    "iso:country":"US",
    "sg:address":"1020 Aaron Dr",
    "sg:city":"Deltona",
    "sg:classifiers":[
        {
            "category":"Personal",
            "subcategory":"Shoe Repair & Shine",
            "type":"Services"
        }
    ],
    "sg:phone":"+1 386 574 3155",
    "sg:postcode":"32725",
    "sg:province":"FL",
    "sg:tags":[
        "sunglass"
    ],
    "wof:name":"A I Trading",
    "wof:placetype":"venue"
},
  "geometry": {"coordinates":[-81.24521,28.880546],"type":"Point"}
}