{
  "type": "Feature",
  "properties": {
    "iso:country":"US",
    "sg:address":"821 N US Hwy 1",
    "sg:city":"Ormond Beach",
    "sg:classifiers":[
        {
            "category":"Building & Trades",
            "subcategory":"Plumbing",
            "type":"Services"
        }
    ],
    "sg:phone":"+1 386 672 4091",
    "sg:postcode":"32174",
    "sg:province":"FL",
    "sg:tags":[
        "plumbing",
        "contractor"
    ],
    "wof:name":"Lou's Plumbing",
    "wof:placetype":"venue"
},
  "geometry": {"coordinates":[-81.07951199999999,29.296091],"type":"Point"}
}