{
  "type": "Feature",
  "properties": {
    "iso:country":"US",
    "sg:address":"925 NE 199th St",
    "sg:city":"Miami",
    "sg:classifiers":[
        {
            "category":"Building & Trades",
            "subcategory":"Locksmith",
            "type":"Services"
        }
    ],
    "sg:phone":"+1 786 718 1389",
    "sg:postcode":"33179",
    "sg:province":"FL",
    "sg:tags":[
        "key"
    ],
    "wof:name":"Available Locksmith",
    "wof:placetype":"venue"
},
  "geometry": {"coordinates":[-80.183367,25.958859],"type":"Point"}
}