{
  "type": "Feature",
  "properties": {
    "iso:country":"US",
    "sg:address":"545 N Beach St",
    "sg:city":"Daytona Beach",
    "sg:classifiers":[
        {
            "category":"Wholesale",
            "subcategory":"Electrical",
            "type":"Manufacturing & Wholesale Goods"
        }
    ],
    "sg:phone":"+1 386 253 4931",
    "sg:postcode":"32114",
    "sg:province":"FL",
    "sg:tags":[
        "repair",
        "radio",
        "automobile"
    ],
    "wof:name":"Thomas Auto Sound",
    "wof:placetype":"venue"
},
  "geometry": {"coordinates":[-81.023805,29.222531],"type":"Point"}
}