{
  "type": "Feature",
  "properties": {
    "iso:country":"US",
    "sg:address":"1930 NW 54th Ave",
    "sg:city":"Pompano Beach",
    "sg:classifiers":[
        {
            "category":"Home & Garden",
            "subcategory":"Home Furnishings",
            "type":"Retail Goods"
        }
    ],
    "sg:phone":"+1 954 917 0574",
    "sg:postcode":"33063",
    "sg:province":"FL",
    "wof:name":"Rbl Upholstery Inc",
    "wof:placetype":"venue"
},
  "geometry": {"coordinates":[-80.19810200000001,26.251858],"type":"Point"}
}