{
  "type": "Feature",
  "properties": {
    "addr:full":"9768 Lantana Rd Lake Worth FL 33467",
    "addr:housenumber":"9768",
    "addr:postcode":"33467",
    "addr:street":"Lantana Rd",
    "iso:country":"US",
    "sg:address":"9768 Lantana Rd",
    "sg:city":"Lake Worth",
    "sg:classifiers":[
        {
            "category":"Professional",
            "type":"Services"
        }
    ],
    "sg:phone":"+1 561 964 6840",
    "sg:postcode":"33467",
    "sg:province":"FL",
    "sg:tags":[
        "establishment"
    ],
    "wof:name":"Bellaggio By Ansca",
    "wof:placetype":"venue"
},
  "geometry": {"coordinates":[-80.201483,26.591185],"type":"Point"}
}