{
  "type": "Feature",
  "properties": {
    "addr:full":"118 W 21st St Hialeah FL 33010",
    "addr:housenumber":"118",
    "addr:postcode":"33010",
    "addr:street":"W 21St St",
    "iso:country":"US",
    "sg:address":"118 W 21st St",
    "sg:city":"Hialeah",
    "sg:classifiers":[
        {
            "category":"Retail",
            "subcategory":"Auto Repair",
            "type":"Services"
        }
    ],
    "sg:phone":"+1 305 884 5017",
    "sg:postcode":"33010",
    "sg:province":"FL",
    "sg:tags":[
        "brake"
    ],
    "wof:name":"Mito Brakes",
    "wof:placetype":"venue"
},
  "geometry": {"coordinates":[-80.285561,25.840654],"type":"Point"}
}