{
  "type": "Feature",
  "properties": {
    "iso:country":"US",
    "sg:address":"109 Neving Dr",
    "sg:city":"Tampa",
    "sg:classifiers":[
        {
            "category":"Building & Trades",
            "subcategory":"Construction",
            "type":"Services"
        }
    ],
    "sg:phone":"+1 813 961 5866",
    "sg:postcode":"33613",
    "sg:province":"FL",
    "sg:tags":[
        "concrete",
        "masonry",
        "contractor"
    ],
    "wof:name":"Lazzara Concrete & Masonry",
    "wof:placetype":"venue"
},
  "geometry": {"coordinates":[-82.462295,28.07526],"type":"Point"}
}