{
  "type": "Feature",
  "properties": {
    "addr:full":"143 John Sims Pkwy Niceville FL 32578",
    "addr:housenumber":"143",
    "addr:postcode":"32578",
    "addr:street":"John Sims Pkwy",
    "iso:country":"US",
    "sg:address":"143 John Sims Pkwy",
    "sg:city":"Niceville",
    "sg:classifiers":[
        {
            "category":"Organizations",
            "subcategory":"Religious Organization",
            "type":"Services"
        }
    ],
    "sg:phone":"+1 850 678 3242",
    "sg:postcode":"32578",
    "sg:province":"FL",
    "sg:tags":[
        "church"
    ],
    "wof:name":"Living Faith Christian Ctr",
    "wof:placetype":"venue"
},
  "geometry": {"coordinates":[-86.49307399999999,30.521944],"type":"Point"}
}