{
  "type": "Feature",
  "properties": {
    "addr:full":"9147 Reed Dr Palm Beach Gardens FL 33410",
    "addr:housenumber":"9147",
    "addr:postcode":"33410",
    "addr:street":"Reed Dr",
    "iso:country":"US",
    "sg:address":"9147 Reed Dr",
    "sg:city":"Palm Beach Gardens",
    "sg:classifiers":[
        {
            "category":"Manufacturing",
            "subcategory":"Tools & Machinery",
            "type":"Manufacturing & Wholesale Goods"
        }
    ],
    "sg:phone":"+1 561 622 3981",
    "sg:postcode":"33410",
    "sg:province":"FL",
    "sg:tags":[
        "industrial",
        "mfg"
    ],
    "wof:name":"Mark Walls Custom Machining",
    "wof:placetype":"venue"
},
  "geometry": {"coordinates":[-80.102632,26.811621],"type":"Point"}
}