{
  "type": "Feature",
  "properties": {
    "iso:country":"US",
    "sg:address":"1600 E Nine Mile Rd",
    "sg:city":"Pensacola",
    "sg:classifiers":[
        {
            "category":"Building & Trades",
            "subcategory":"Construction",
            "type":"Services"
        }
    ],
    "sg:phone":"+1 850 477 9357",
    "sg:postcode":"32514",
    "sg:province":"FL",
    "sg:tags":[
        "general",
        "contractor"
    ],
    "wof:name":"T & T Construction",
    "wof:placetype":"venue"
},
  "geometry": {"coordinates":[-87.230305,30.532486],"type":"Point"}
}