{
  "type": "Feature",
  "properties": {
    "iso:country":"US",
    "sg:address":"5542 Cortez Rd W",
    "sg:city":"Bradenton",
    "sg:classifiers":[
        {
            "category":"Recreation",
            "type":"Entertainment"
        }
    ],
    "sg:phone":"+1 941 795 1977",
    "sg:postcode":"34210",
    "sg:province":"FL",
    "sg:tags":[
        "martial",
        "arts",
        "instruction"
    ],
    "wof:name":"Bostock USA Traditional Tae",
    "wof:placetype":"venue"
},
  "geometry": {"coordinates":[-82.617357,27.46239],"type":"Point"}
}