{
  "type": "Feature",
  "properties": {
    "iso:country":"US",
    "sg:address":"2325 NE 5th Ave",
    "sg:city":"Pompano Beach",
    "sg:classifiers":[
        {
            "category":"Personal",
            "subcategory":"Beauty Salon",
            "type":"Services"
        }
    ],
    "sg:phone":"+1 954 942 2664",
    "sg:postcode":"33064",
    "sg:province":"FL",
    "sg:tags":[
        "shop"
    ],
    "wof:name":"Joce Beauty Salon",
    "wof:placetype":"venue"
},
  "geometry": {"coordinates":[-80.115759,26.260691],"type":"Point"}
}