{
  "type": "Feature",
  "properties": {
    "addr:full":"661 N Spring Garden Ave Ste 3 Deland FL 32720",
    "addr:housenumber":"661",
    "addr:postcode":"32720",
    "addr:street":"N Spring Garden Ave Ste 3",
    "iso:country":"US",
    "sg:address":"661 N Spring Garden Ave Ste 3",
    "sg:city":"Deland",
    "sg:classifiers":[
        {
            "category":"Personal",
            "subcategory":"Nail Salon",
            "type":"Services"
        }
    ],
    "sg:phone":"+1 386 738 4330",
    "sg:postcode":"32720",
    "sg:province":"FL",
    "wof:name":"Skin Cures",
    "wof:placetype":"venue"
},
  "geometry": {"coordinates":[-81.32440200000001,29.038099],"type":"Point"}
}