{
  "type": "Feature",
  "properties": {
    "addr:full":"3701 Grand Blvd New Port Richey FL 34652",
    "addr:housenumber":"3701",
    "addr:postcode":"34652",
    "addr:street":"Grand Blvd",
    "iso:country":"US",
    "sg:address":"3701 Grand Blvd",
    "sg:city":"New Port Richey",
    "sg:classifiers":[
        {
            "category":"Bars & Pubs",
            "type":"Food & Drink"
        }
    ],
    "sg:phone":"+1 727 848 0886",
    "sg:postcode":"34652",
    "sg:province":"FL",
    "sg:tags":[
        "club",
        "night"
    ],
    "wof:name":"Club 54",
    "wof:placetype":"venue"
},
  "geometry": {"coordinates":[-82.72356600000001,28.214026],"type":"Point"}
}