{
  "type": "Feature",
  "properties": {
    "iso:country":"US",
    "sg:address":"776 NE 125th St",
    "sg:city":"North Miami",
    "sg:classifiers":[
        {
            "category":"Professional",
            "type":"Services"
        }
    ],
    "sg:phone":"+1 305 895 2796",
    "sg:postcode":"33161",
    "sg:province":"FL",
    "sg:tags":[
        "establishment"
    ],
    "wof:name":"Indian Creek Village",
    "wof:placetype":"venue"
},
  "geometry": {"coordinates":[-80.182948,25.890348],"type":"Point"}
}