{
  "type": "Feature",
  "properties": {
    "iso:country":"US",
    "sg:address":"277 Blanding Blvd",
    "sg:city":"Orange Park",
    "sg:classifiers":[
        {
            "category":"Food & Beverages",
            "subcategory":"Groceries & Convenience Stores",
            "type":"Retail Goods"
        }
    ],
    "sg:phone":"+1 904 264 3015",
    "sg:postcode":"32073",
    "sg:province":"FL",
    "wof:name":"Gate Petroleum",
    "wof:placetype":"venue"
},
  "geometry": {"coordinates":[-81.745904,30.173448],"type":"Point"}
}