{
  "type": "Feature",
  "properties": {
    "iso:country":"US",
    "sg:address":"501 N Fort Harrison Ave",
    "sg:city":"Clearwater",
    "sg:classifiers":[
        {
            "category":"Professional",
            "subcategory":"Lawyer & Legal Services",
            "type":"Services"
        }
    ],
    "sg:phone":"+1 727 446 4317",
    "sg:postcode":"33755",
    "sg:province":"FL",
    "sg:tags":[
        "attorney"
    ],
    "wof:name":"Dennis M Lawler",
    "wof:placetype":"venue"
},
  "geometry": {"coordinates":[-82.79967499999999,27.97261],"type":"Point"}
}