{
  "type": "Feature",
  "properties": {
    "iso:country":"US",
    "sg:address":"3828 41st Ave N",
    "sg:city":"Saint Petersburg",
    "sg:classifiers":[
        {
            "category":"Farming",
            "subcategory":"Farm & Veterinary Services",
            "type":"Manufacturing & Wholesale Goods"
        }
    ],
    "sg:phone":"+1 727 525 1178",
    "sg:postcode":"33714",
    "sg:province":"FL",
    "sg:tags":[
        "crop"
    ],
    "wof:name":"Gt Hood and Ventilation",
    "wof:placetype":"venue"
},
  "geometry": {"coordinates":[-82.687484,27.80912],"type":"Point"}
}