{
  "type": "Feature",
  "properties": {
    "iso:country":"US",
    "sg:address":"6951 NW 16th St",
    "sg:city":"Miami",
    "sg:classifiers":[
        {
            "category":"Professional",
            "subcategory":"Engineering",
            "type":"Services"
        }
    ],
    "sg:phone":"+1 305 477 3886",
    "sg:postcode":"33126",
    "sg:province":"FL",
    "sg:tags":[
        "aircraft",
        "maintenance"
    ],
    "wof:name":"Jet Accessory Center",
    "wof:placetype":"venue"
},
  "geometry": {"coordinates":[-80.309815,25.789065],"type":"Point"}
}