{
  "type": "Feature",
  "properties": {
    "iso:country":"US",
    "sg:address":"5621 S Orange Ave",
    "sg:city":"Orlando",
    "sg:classifiers":[
        {
            "category":"Shopping",
            "subcategory":"Department Store",
            "type":"Retail Goods"
        }
    ],
    "sg:phone":"+1 407 851 1832",
    "sg:postcode":"32809",
    "sg:province":"FL",
    "sg:tags":[
        "shop",
        "discount"
    ],
    "sg:website":"http://www.familydollar.com",
    "wof:name":"Family Dollar Stores",
    "wof:placetype":"venue"
},
  "geometry": {"coordinates":[-81.37067999999999,28.476074],"type":"Point"}
}