{
  "type": "Feature",
  "properties": {
    "iso:country":"US",
    "sg:address":"3117 SE East Blackwell Dr",
    "sg:city":"Port Saint Lucie",
    "sg:classifiers":[
        {
            "category":"Building & Trades",
            "subcategory":"Construction",
            "type":"Services"
        }
    ],
    "sg:phone":"+1 772 398 9959",
    "sg:postcode":"34952",
    "sg:province":"FL",
    "sg:tags":[
        "house"
    ],
    "wof:name":"D & S Renovations",
    "wof:placetype":"venue"
},
  "geometry": {"coordinates":[-80.258972,27.276771],"type":"Point"}
}