{
  "type": "Feature",
  "properties": {
    "addr:full":"2180 10th Ave Vero Beach FL 32960",
    "addr:housenumber":"2180",
    "addr:postcode":"32960",
    "addr:street":"10Th Ave",
    "iso:country":"US",
    "sg:address":"2180 10th Ave",
    "sg:city":"Vero Beach",
    "sg:classifiers":[
        {
            "category":"Health Services",
            "subcategory":"Nursing And Care Facility",
            "type":"Services"
        }
    ],
    "sg:phone":"+1 772 567 5166",
    "sg:postcode":"32960",
    "sg:province":"FL",
    "sg:tags":[
        "home",
        "convalescent"
    ],
    "wof:name":"Royal Palm Convalescent Ctr",
    "wof:placetype":"venue"
},
  "geometry": {"coordinates":[-80.393125,27.640985],"type":"Point"}
}