{
  "type": "Feature",
  "properties": {
    "iso:country":"US",
    "sg:address":"1025 SW Martin Downs Blvd",
    "sg:city":"Palm City",
    "sg:classifiers":[
        {
            "category":"Shopping",
            "subcategory":"Jewelry",
            "type":"Retail Goods"
        }
    ],
    "sg:phone":"+1 772 287 2662",
    "sg:postcode":"34990",
    "sg:province":"FL",
    "sg:tags":[
        "jeweler"
    ],
    "wof:name":"Gold Doctor",
    "wof:placetype":"venue"
},
  "geometry": {"coordinates":[-80.266485,27.172347],"type":"Point"}
}