{
  "type": "Feature",
  "properties": {
    "iso:country":"US",
    "sg:address":"2161 SE Ocean Blvd",
    "sg:city":"Stuart",
    "sg:classifiers":[
        {
            "category":"Professional",
            "subcategory":"Accounting & Tax Preparation",
            "type":"Services"
        }
    ],
    "sg:phone":"+1 772 287 1457",
    "sg:postcode":"34996",
    "sg:province":"FL",
    "sg:tags":[
        "accountant"
    ],
    "wof:name":"Priscilla Gale-Gibson CPA",
    "wof:placetype":"venue"
},
  "geometry": {"coordinates":[-80.222942,27.197211],"type":"Point"}
}