{
  "type": "Feature",
  "properties": {
    "addr:full":"822 Marys Park Pl Winter Garden FL 34787",
    "addr:housenumber":"822",
    "addr:postcode":"34787",
    "addr:street":"Marys Park Pl",
    "iso:country":"US",
    "sg:address":"822 Marys Park Pl",
    "sg:city":"Winter Garden",
    "sg:classifiers":[
        {
            "category":"Manufacturing",
            "subcategory":"Tools & Machinery",
            "type":"Manufacturing & Wholesale Goods"
        }
    ],
    "sg:phone":"+1 407 877 7000",
    "sg:postcode":"34787",
    "sg:province":"FL",
    "sg:tags":[
        "air",
        "parts",
        "conditioning",
        "supply"
    ],
    "sg:website":"www.srsalesinc.com",
    "wof:name":"S & R Sales",
    "wof:placetype":"venue"
},
  "geometry": {"coordinates":[-81.566373,28.556012],"type":"Point"}
}