{
  "type": "Feature",
  "properties": {
    "iso:country":"US",
    "sg:address":"6507 S Orange Ave",
    "sg:city":"Orlando",
    "sg:classifiers":[
        {
            "category":"Autos & Motor Vehicles",
            "subcategory":"Automobile Sales",
            "type":"Retail Goods"
        }
    ],
    "sg:phone":"+1 407 852 1992",
    "sg:postcode":"32809",
    "sg:province":"FL",
    "sg:tags":[
        "car",
        "dealer"
    ],
    "wof:name":"National Sales & Leasing",
    "wof:placetype":"venue"
},
  "geometry": {"coordinates":[-81.36756699999999,28.466233],"type":"Point"}
}