{
  "type": "Feature",
  "properties": {
    "addr:full":"2363 Landings Cir Bradenton FL 34209",
    "addr:housenumber":"2363",
    "addr:postcode":"34209",
    "addr:street":"Landings Cir",
    "iso:country":"US",
    "sg:address":"2363 Landings Cir",
    "sg:city":"Bradenton",
    "sg:classifiers":[
        {
            "category":"Professional",
            "subcategory":"Engineering",
            "type":"Services"
        }
    ],
    "sg:phone":"+1 941 792 6053",
    "sg:postcode":"34209",
    "sg:province":"FL",
    "sg:tags":[
        "engineer",
        "structural"
    ],
    "wof:name":"4rsut Systems",
    "wof:placetype":"venue"
},
  "geometry": {"coordinates":[-82.645628,27.518831],"type":"Point"}
}