{
  "type": "Feature",
  "properties": {
    "addr:full":"172 Bent Arrow Dr Jupiter FL 33458",
    "addr:housenumber":"172",
    "addr:postcode":"33458",
    "addr:street":"Bent Arrow Dr",
    "iso:country":"US",
    "sg:address":"172 Bent Arrow Dr",
    "sg:city":"Jupiter",
    "sg:classifiers":[
        {
            "category":"Professional",
            "subcategory":"Computer Services",
            "type":"Services"
        }
    ],
    "sg:phone":"+1 561 889 2413",
    "sg:postcode":"33458",
    "sg:province":"FL",
    "sg:tags":[
        "repair"
    ],
    "sg:website":"www.suncoastnetworking.com",
    "wof:name":"SUNCOASTNETWORKING.COM",
    "wof:placetype":"venue"
},
  "geometry": {"coordinates":[-80.127647,26.917419],"type":"Point"}
}