{
  "type": "Feature",
  "properties": {
    "iso:country":"US",
    "sg:address":"14072 78th Pl N",
    "sg:city":"Loxahatchee",
    "sg:classifiers":[
        {
            "category":"Professional",
            "subcategory":"Management & Consulting",
            "type":"Services"
        }
    ],
    "sg:phone":"+1 561 791 3248",
    "sg:postcode":"33470",
    "sg:province":"FL",
    "sg:tags":[
        "business"
    ],
    "wof:name":"NRC Business Consultants Inc",
    "wof:placetype":"venue"
},
  "geometry": {"coordinates":[-80.26237399999999,26.792469],"type":"Point"}
}