{
  "type": "Feature",
  "properties": {
    "addr:full":"237 S Westmonte Dr Altamonte Springs FL 32714",
    "addr:housenumber":"237",
    "addr:postcode":"32714",
    "addr:street":"S Westmonte Dr",
    "iso:country":"US",
    "sg:address":"237 S Westmonte Dr",
    "sg:city":"Altamonte Springs",
    "sg:classifiers":[
        {
            "category":"Professional",
            "subcategory":"Management & Consulting",
            "type":"Services"
        }
    ],
    "sg:phone":"+1 407 862 1144",
    "sg:postcode":"32714",
    "sg:province":"FL",
    "sg:tags":[
        "training",
        "develop",
        "system"
    ],
    "wof:name":"Suntech 3 Inc",
    "wof:placetype":"venue"
},
  "geometry": {"coordinates":[-81.393548,28.660986],"type":"Point"}
}