{
  "type": "Feature",
  "properties": {
    "iso:country":"US",
    "sg:address":"725 SE Port St Lucie Blvd",
    "sg:city":"Port St Lucie",
    "sg:classifiers":[
        {
            "category":"Wholesale",
            "subcategory":"Durable Goods & Equipment",
            "type":"Manufacturing & Wholesale Goods"
        }
    ],
    "sg:phone":"+1 772 785 9298",
    "sg:postcode":"34984",
    "sg:province":"FL",
    "sg:tags":[
        "exporter"
    ],
    "wof:name":"Alphatron Electronic Component",
    "wof:placetype":"venue"
},
  "geometry": {"coordinates":[-80.330226,27.272135],"type":"Point"}
}