{
  "type": "Feature",
  "properties": {
    "iso:country":"US",
    "sg:address":"14928 N Dale Mabry Hwy",
    "sg:city":"Tampa",
    "sg:classifiers":[
        {
            "category":"Personal",
            "type":"Services"
        }
    ],
    "sg:phone":"+1 813 963 1920",
    "sg:postcode":"33618",
    "sg:province":"FL",
    "sg:tags":[
        "wear",
        "formal"
    ],
    "wof:name":"Tuxedo Junction",
    "wof:placetype":"venue"
},
  "geometry": {"coordinates":[-82.505019,28.084958],"type":"Point"}
}