{
  "type": "Feature",
  "properties": {
    "iso:country":"US",
    "sg:address":"20859 Central Ave E G20",
    "sg:city":"Blountstown",
    "sg:classifiers":[
        {
            "category":"Government",
            "subcategory":"Office",
            "type":"Public Place"
        }
    ],
    "sg:phone":"+1 850 674 6129",
    "sg:postcode":"32424",
    "sg:province":"FL",
    "sg:tags":[
        "parish",
        "government-county"
    ],
    "wof:name":"Board Of County Commissioners",
    "wof:placetype":"venue"
},
  "geometry": {"coordinates":[-85.04167200000001,30.443211],"type":"Point"}
}