{
  "type": "Feature",
  "properties": {
    "iso:country":"US",
    "sg:address":"1481 Ridge Rd NE",
    "sg:city":"Palm Bay",
    "sg:classifiers":[
        {
            "category":"Manufacturing",
            "subcategory":"Motor Vehicles & Parts",
            "type":"Manufacturing & Wholesale Goods"
        }
    ],
    "sg:phone":"+1 321 723 4290",
    "sg:postcode":"32905",
    "sg:province":"FL",
    "sg:tags":[
        "body",
        "truck",
        "manufacturer"
    ],
    "wof:name":"International Marketing Servic",
    "wof:placetype":"venue"
},
  "geometry": {"coordinates":[-80.578272,28.033288],"type":"Point"}
}