{
  "type": "Feature",
  "properties": {
    "addr:full":"8650 SW 67th Ave Miami FL 33143",
    "addr:housenumber":"8650",
    "addr:postcode":"33143",
    "addr:street":"Sw 67Th Ave",
    "iso:country":"US",
    "sg:address":"8650 SW 67th Ave",
    "sg:city":"Miami",
    "sg:classifiers":[
        {
            "category":"Health Services",
            "subcategory":"Nursing And Care Facility",
            "type":"Services"
        }
    ],
    "sg:phone":"+1 786 268 1144",
    "sg:postcode":"33143",
    "sg:province":"FL",
    "sg:tags":[
        "home",
        "retirement",
        "community"
    ],
    "wof:name":"ICMA Retirement Corp",
    "wof:placetype":"venue"
},
  "geometry": {"coordinates":[-80.302865,25.689714],"type":"Point"}
}