{
  "type": "Feature",
  "properties": {
    "addr:full":"6830 NW 11th Ave Gainesville FL 32605",
    "addr:housenumber":"6830",
    "addr:postcode":"32605",
    "addr:street":"Nw 11Th Ave",
    "iso:country":"US",
    "sg:address":"6830 NW 11th Ave",
    "sg:city":"Gainesville",
    "sg:classifiers":[
        {
            "category":"Shopping",
            "type":"Retail Goods"
        }
    ],
    "sg:phone":"+1 352 331 4221",
    "sg:postcode":"32605",
    "sg:province":"FL",
    "sg:tags":[
        "communications",
        "telephone",
        "merchandise"
    ],
    "wof:name":"Orthotic Prsthtic Clnical Tech",
    "wof:placetype":"venue"
},
  "geometry": {"coordinates":[-82.37588599999999,29.662759],"type":"Point"}
}