{
  "type": "Feature",
  "properties": {
    "addr:full":"3333 NW 167th St Miami Gardens FL 33056",
    "addr:housenumber":"3333",
    "addr:postcode":"33056",
    "addr:street":"Nw 167Th St",
    "iso:country":"US",
    "sg:address":"3333 NW 167th St",
    "sg:city":"Miami Gardens",
    "sg:classifiers":[
        {
            "category":"Home & Garden",
            "subcategory":"Household Appliances",
            "type":"Retail Goods"
        }
    ],
    "sg:phone":"+1 305 625 3133",
    "sg:postcode":"33056",
    "sg:province":"FL",
    "wof:name":"Gas Appliance Depot",
    "wof:placetype":"venue"
},
  "geometry": {"coordinates":[-80.25523800000001,25.926345],"type":"Point"}
}