{
  "type": "Feature",
  "properties": {
    "addr:full":"2328 Apalachee Pkwy Tallahassee FL 32301",
    "addr:housenumber":"2328",
    "addr:postcode":"32301",
    "addr:street":"Apalachee Pkwy",
    "iso:country":"US",
    "sg:address":"2328 Apalachee Pkwy",
    "sg:city":"Tallahassee",
    "sg:classifiers":[
        {
            "category":"Personal",
            "subcategory":"Beauty Salon",
            "type":"Services"
        }
    ],
    "sg:phone":"+1 850 656 2811",
    "sg:postcode":"32301",
    "sg:province":"FL",
    "wof:name":"Personally Yours",
    "wof:placetype":"venue"
},
  "geometry": {"coordinates":[-84.24135099999999,30.429184],"type":"Point"}
}