{
  "type": "Feature",
  "properties": {
    "addr:full":"640 NW 27th Ave Ocala FL 34475",
    "addr:housenumber":"640",
    "addr:postcode":"34475",
    "addr:street":"Nw 27Th Ave",
    "iso:country":"US",
    "sg:address":"640 NW 27th Ave",
    "sg:city":"Ocala",
    "sg:classifiers":[
        {
            "category":"Shopping",
            "subcategory":"Computers & Home Electronics",
            "type":"Retail Goods"
        }
    ],
    "sg:phone":"+1 352 873 1561",
    "sg:postcode":"34475",
    "sg:province":"FL",
    "sg:tags":[
        "equipment",
        "electronic",
        "supply"
    ],
    "wof:name":"Tony O'Connor Electronics",
    "wof:placetype":"venue"
},
  "geometry": {"coordinates":[-82.16870900000001,29.193028],"type":"Point"}
}