{
  "type": "Feature",
  "properties": {
    "addr:full":"5025 Old Howell Branch Rd Winter Park FL 32792",
    "addr:housenumber":"5025",
    "addr:postcode":"32792",
    "addr:street":"Old Howell Branch Rd",
    "iso:country":"US",
    "sg:address":"5025 Old Howell Branch Rd",
    "sg:city":"Winter Park",
    "sg:classifiers":[
        {
            "category":"Banks & Credit Unions",
            "subcategory":"Bank",
            "type":"Services"
        }
    ],
    "sg:phone":"+1 407 677 9779",
    "sg:postcode":"32792",
    "sg:province":"FL",
    "sg:website":"www.bankfirst.com",
    "wof:name":"Bankfirst",
    "wof:placetype":"venue"
},
  "geometry": {"coordinates":[-81.2826,28.612101],"type":"Point"}
}