{
  "type": "Feature",
  "properties": {
    "addr:full":"4723 W Atlantic Ave Delray Beach FL 33445",
    "addr:housenumber":"4723",
    "addr:postcode":"33445",
    "addr:street":"W Atlantic Ave",
    "iso:country":"US",
    "sg:address":"4723 W Atlantic Ave",
    "sg:city":"Delray Beach",
    "sg:classifiers":[
        {
            "category":"Insurance",
            "subcategory":"Insurance Agent",
            "type":"Services"
        }
    ],
    "sg:phone":"+1 561 495 1934",
    "sg:postcode":"33445",
    "sg:province":"FL",
    "wof:name":"Dedicated Resources of Florida",
    "wof:placetype":"venue"
},
  "geometry": {"coordinates":[-80.117233,26.457903],"type":"Point"}
}