{
  "type": "Feature",
  "properties": {
    "iso:country":"US",
    "sg:address":"233 N Federal Hwy",
    "sg:city":"Dania",
    "sg:classifiers":[
        {
            "category":"Professional",
            "subcategory":"Detective & Security Services",
            "type":"Services"
        }
    ],
    "sg:phone":"+1 954 923 7168",
    "sg:postcode":"33004",
    "sg:province":"FL",
    "sg:tags":[
        "control",
        "monitoring",
        "system"
    ],
    "sg:website":"http://www.securitystatewide.com",
    "wof:name":"AMC Surveillance Camera & Electronics",
    "wof:placetype":"venue"
},
  "geometry": {"coordinates":[-80.143809,26.057023],"type":"Point"}
}