{
  "type": "Feature",
  "properties": {
    "addr:full":"12500 131st St Largo FL 33774",
    "addr:housenumber":"12500",
    "addr:postcode":"33774",
    "addr:street":"131St St",
    "iso:country":"US",
    "sg:address":"12500 131st St",
    "sg:city":"Largo",
    "sg:classifiers":[
        {
            "category":"Sports & Exercise",
            "subcategory":"Golf",
            "type":"Entertainment"
        }
    ],
    "sg:phone":"+1 727 518 3024",
    "sg:postcode":"33774",
    "sg:province":"FL",
    "sg:tags":[
        "course"
    ],
    "wof:name":"Largo Golf Course",
    "wof:placetype":"venue"
},
  "geometry": {"coordinates":[-82.820025,27.887653],"type":"Point"}
}