{
  "type": "Feature",
  "properties": {
    "addr:full":"4345 Gunn Hwy Tampa FL 33618",
    "addr:housenumber":"4345",
    "addr:postcode":"33618",
    "addr:street":"Gunn Hwy",
    "iso:country":"US",
    "sg:address":"4345 Gunn Hwy",
    "sg:city":"Tampa",
    "sg:classifiers":[
        {
            "category":"Professional",
            "subcategory":"Business Services",
            "type":"Services"
        },
        {
            "category":"Real Estate",
            "subcategory":"Architect",
            "type":"Services"
        }
    ],
    "sg:phone":"+1 813 546 6386",
    "sg:postcode":"33618",
    "sg:province":"FL",
    "sg:tags":[
        "record",
        "document",
        "destruction"
    ],
    "wof:name":"Official Document Center -Lm",
    "wof:placetype":"venue"
},
  "geometry": {"coordinates":[-82.514779,28.045138],"type":"Point"}
}