{
  "type": "Feature",
  "properties": {
    "addr:full":"4675 NW 7th St Miami FL 33126",
    "addr:housenumber":"4675",
    "addr:postcode":"33126",
    "addr:street":"Nw 7Th St",
    "iso:country":"US",
    "sg:address":"4675 NW 7th St",
    "sg:city":"Miami",
    "sg:classifiers":[
        {
            "category":"Restaurant",
            "type":"Food & Drink"
        },
        {
            "category":"Food & Beverages",
            "subcategory":"Groceries & Convenience Stores",
            "type":"Retail Goods"
        }
    ],
    "sg:phone":"+1 305 446 3631",
    "sg:postcode":"33126",
    "sg:province":"FL",
    "wof:name":"Seven Forty Seven",
    "wof:placetype":"venue"
},
  "geometry": {"coordinates":[-80.271698,25.778601],"type":"Point"}
}