{
  "type": "Feature",
  "properties": {
    "addr:full":"3129 N Tamarisk Ave Beverly Hills FL 34465",
    "addr:housenumber":"3129",
    "addr:postcode":"34465",
    "addr:street":"N Tamarisk Ave",
    "iso:country":"US",
    "sg:address":"3129 N Tamarisk Ave",
    "sg:city":"Beverly Hills",
    "sg:classifiers":[
        {
            "category":"Shopping",
            "subcategory":"Gifts & Souvenirs",
            "type":"Retail Goods"
        }
    ],
    "sg:phone":"+1 352 746 9326",
    "sg:postcode":"34465",
    "sg:province":"FL",
    "wof:name":"Gorman Gift Gallery Inc",
    "wof:placetype":"venue"
},
  "geometry": {"coordinates":[-82.435396,28.909226],"type":"Point"}
}