{
  "type": "Feature",
  "properties": {
    "iso:country":"US",
    "sg:address":"6338 Presidential Ct Ste 101",
    "sg:city":"Fort Myers",
    "sg:classifiers":[
        {
            "category":"Professional",
            "subcategory":"Lawyer & Legal Services",
            "type":"Services"
        }
    ],
    "sg:phone":"+1 239 481 0500",
    "sg:postcode":"33919",
    "sg:province":"FL",
    "sg:tags":[
        "litigation"
    ],
    "wof:name":"Griffith Lynn J PA Atty",
    "wof:placetype":"venue"
},
  "geometry": {"coordinates":[-81.886398,26.5578],"type":"Point"}
}