{
  "type": "Feature",
  "properties": {
    "addr:full":"8411 Dynasty Dr Boca Raton FL 33433",
    "addr:housenumber":"8411",
    "addr:postcode":"33433",
    "addr:street":"Dynasty Dr",
    "iso:country":"US",
    "sg:address":"8411 Dynasty Dr",
    "sg:city":"Boca Raton",
    "sg:classifiers":[
        {
            "category":"Building & Trades",
            "subcategory":"Construction",
            "type":"Services"
        }
    ],
    "sg:phone":"+1 561 483 4405",
    "sg:postcode":"33433",
    "sg:province":"FL",
    "sg:tags":[
        "house"
    ],
    "wof:name":"Excel Home Repair",
    "wof:placetype":"venue"
},
  "geometry": {"coordinates":[-80.175268,26.334438],"type":"Point"}
}