{
  "type": "Feature",
  "properties": {
    "addr:full":"2700 Immokalee Rd Naples FL 34142",
    "addr:postcode":"2700;34142",
    "addr:street":"Immokalee Rd",
    "iso:country":"US",
    "sg:address":"2700 Immokalee Rd",
    "sg:city":"Naples",
    "sg:classifiers":[
        {
            "category":"Shopping",
            "subcategory":"Clothing, Apparel, & Fashions",
            "type":"Retail Goods"
        }
    ],
    "sg:phone":"+1 239 591 1616",
    "sg:postcode":"34142",
    "sg:province":"FL",
    "sg:tags":[
        "shop",
        "bridal"
    ],
    "wof:name":"Tie The Knot Bridal Couture",
    "wof:placetype":"venue"
},
  "geometry": {"coordinates":[-81.48406900000001,26.497825],"type":"Point"}
}