{
  "type": "Feature",
  "properties": {
    "iso:country":"US",
    "sg:address":"18 Alexandra Pl SE",
    "sg:city":"Fort Walton Beach",
    "sg:classifiers":[
        {
            "category":"Building & Trades",
            "subcategory":"Construction",
            "type":"Services"
        }
    ],
    "sg:phone":"+1 850 315 1888",
    "sg:postcode":"32548",
    "sg:province":"FL",
    "sg:tags":[
        "hanging",
        "contractor"
    ],
    "wof:name":"Rodgers Paint & Drywall",
    "wof:placetype":"venue"
},
  "geometry": {"coordinates":[-86.594466,30.409756],"type":"Point"}
}