{
  "type": "Feature",
  "properties": {
    "addr:full":"5730 W 12th Ave Hialeah FL 33012",
    "addr:housenumber":"5730",
    "addr:postcode":"33012",
    "addr:street":"W 12Th Ave",
    "iso:country":"US",
    "sg:address":"5730 W 12th Ave",
    "sg:city":"Hialeah",
    "sg:classifiers":[
        {
            "category":"Wholesale",
            "subcategory":"Hardware",
            "type":"Manufacturing & Wholesale Goods"
        }
    ],
    "sg:phone":"+1 305 231 0024",
    "sg:postcode":"33012",
    "sg:province":"FL",
    "sg:tags":[
        "air",
        "parts",
        "conditioning",
        "supply"
    ],
    "wof:name":"Five Stars Svc & Supplies",
    "wof:placetype":"venue"
},
  "geometry": {"coordinates":[-80.30723500000001,25.87497],"type":"Point"}
}