{
  "type": "Feature",
  "properties": {
    "iso:country":"US",
    "sg:address":"4020 Sanderling Ln",
    "sg:city":"Fort Lauderdale",
    "sg:classifiers":[
        {
            "category":"Professional",
            "subcategory":"Accounting & Tax Preparation",
            "type":"Services"
        }
    ],
    "sg:phone":"+1 954 983 5804",
    "sg:postcode":"33331",
    "sg:province":"FL",
    "wof:name":"Kessler Topping & Company",
    "wof:placetype":"venue"
},
  "geometry": {"coordinates":[-80.386155,26.067627],"type":"Point"}
}