{
  "type": "Feature",
  "properties": {
    "addr:full":"455 Corday St Pensacola FL 32503",
    "addr:housenumber":"455",
    "addr:postcode":"32503",
    "addr:street":"Corday St",
    "iso:country":"US",
    "sg:address":"455 Corday St",
    "sg:city":"Pensacola",
    "sg:classifiers":[
        {
            "category":"Bus Charters",
            "type":"Transportation"
        }
    ],
    "sg:phone":"+1 850 476 0046",
    "sg:postcode":"32503",
    "sg:province":"FL",
    "sg:tags":[
        "rental"
    ],
    "sg:website":"www.goodtimetours.com",
    "wof:name":"Good Time Tours",
    "wof:placetype":"venue"
},
  "geometry": {"coordinates":[-87.23165400000001,30.468155],"type":"Point"}
}