{
  "type": "Feature",
  "properties": {
    "addr:full":"2750 W 3rd Ct Hialeah FL 33010",
    "addr:housenumber":"2750",
    "addr:postcode":"33010",
    "addr:street":"W 3Rd Ct",
    "iso:country":"US",
    "sg:address":"2750 W 3rd Ct",
    "sg:city":"Hialeah",
    "sg:classifiers":[
        {
            "category":"Mining & Drilling",
            "type":"Manufacturing & Wholesale Goods"
        }
    ],
    "sg:phone":"+1 305 884 3033",
    "sg:postcode":"33010",
    "sg:province":"FL",
    "sg:tags":[
        "stone"
    ],
    "wof:name":"Cristel Stone Corp",
    "wof:placetype":"venue"
},
  "geometry": {"coordinates":[-80.289074,25.847606],"type":"Point"}
}