{
  "type": "Feature",
  "properties": {
    "iso:country":"US",
    "sg:address":"3407 S Dale Mabry Hwy",
    "sg:city":"Tampa",
    "sg:classifiers":[
        {
            "category":"Shopping",
            "subcategory":"Florist",
            "type":"Retail Goods"
        }
    ],
    "sg:phone":"+1 813 839 5111",
    "sg:postcode":"33629",
    "sg:province":"FL",
    "sg:tags":[
        "shop",
        "gift"
    ],
    "wof:name":"Marge's Florist & Gift",
    "wof:placetype":"venue"
},
  "geometry": {"coordinates":[-82.50608200000001,27.912314],"type":"Point"}
}