{
  "type": "Feature",
  "properties": {
    "iso:country":"US",
    "sg:address":"9485 Baymeadows Rd",
    "sg:city":"Jacksonville",
    "sg:phone":"+1 904 367 8558",
    "sg:postcode":"32256",
    "sg:province":"FL",
    "sg:website":"http://www.applebees.com",
    "wof:name":"Applebee's",
    "wof:placetype":"venue"
},
  "geometry": {"coordinates":[-81.560688,30.220971],"type":"Point"}
}