{
  "type": "Feature",
  "properties": {
    "iso:country":"US",
    "sg:address":"13000 SW 62nd Ave",
    "sg:city":"Miami",
    "sg:classifiers":[
        {
            "category":"Building & Trades",
            "subcategory":"Construction",
            "type":"Services"
        }
    ],
    "sg:phone":"+1 305 256 9824",
    "sg:postcode":"33156",
    "sg:province":"FL",
    "sg:tags":[
        "painting"
    ],
    "wof:name":"Marcos Matijevic",
    "wof:placetype":"venue"
},
  "geometry": {"coordinates":[-80.29369699999999,25.649997],"type":"Point"}
}