{
  "type": "Feature",
  "properties": {
    "iso:country":"US",
    "sg:address":"2001 Atlantic Shores Blvd",
    "sg:city":"Hallandale",
    "sg:classifiers":[
        {
            "category":"Organizations",
            "subcategory":"Membership Organization",
            "type":"Services"
        }
    ],
    "sg:phone":"+1 954 455 9156",
    "sg:postcode":"33009",
    "sg:province":"FL",
    "wof:name":"Automobile Solutions Inc",
    "wof:placetype":"venue"
},
  "geometry": {"coordinates":[-80.129088,25.995445],"type":"Point"}
}