{
  "type": "Feature",
  "properties": {
    "iso:country":"US",
    "sg:address":"9840 Currie Davis Dr",
    "sg:city":"Tampa",
    "sg:classifiers":[
        {
            "category":"Wholesale",
            "subcategory":"Machinery & Supplies",
            "type":"Manufacturing & Wholesale Goods"
        }
    ],
    "sg:phone":"+1 813 630 0550",
    "sg:postcode":"33619",
    "sg:province":"FL",
    "sg:tags":[
        "equipment",
        "irrigation",
        "system"
    ],
    "wof:name":"Hit Products Corp",
    "wof:placetype":"venue"
},
  "geometry": {"coordinates":[-82.34406,27.950406],"type":"Point"}
}