{
  "type": "Feature",
  "properties": {
    "addr:full":"5300 Emerson St Jacksonville FL 32207",
    "addr:housenumber":"5300",
    "addr:postcode":"32207",
    "addr:street":"Emerson St",
    "iso:country":"US",
    "sg:address":"5300 Emerson St",
    "sg:city":"Jacksonville",
    "sg:classifiers":[
        {
            "category":"Professional",
            "subcategory":"Accounting & Tax Preparation",
            "type":"Services"
        }
    ],
    "sg:phone":"+1 904 398 2011",
    "sg:postcode":"32207",
    "sg:province":"FL",
    "wof:name":"Charles L Moll Jr CPA PA",
    "wof:placetype":"venue"
},
  "geometry": {"coordinates":[-81.612416,30.292807],"type":"Point"}
}