{
  "type": "Feature",
  "properties": {
    "addr:full":"3209 Mahan Dr Tallahassee FL 32308",
    "addr:housenumber":"3209",
    "addr:postcode":"32308",
    "addr:street":"Mahan Dr",
    "iso:country":"US",
    "sg:address":"3209 Mahan Dr",
    "sg:city":"Tallahassee",
    "sg:classifiers":[
        {
            "category":"Real Estate",
            "subcategory":"Real Estate Operator",
            "type":"Services"
        }
    ],
    "sg:phone":"+1 850 877 1410",
    "sg:postcode":"32308",
    "sg:province":"FL",
    "sg:tags":[
        "mobile",
        "home",
        "site"
    ],
    "wof:name":"Hayes Gordon Mobile Home Park",
    "wof:placetype":"venue"
},
  "geometry": {"coordinates":[-84.222509,30.462058],"type":"Point"}
}