{
  "type": "Feature",
  "properties": {
    "iso:country":"US",
    "sg:address":"8686 SE Alabama Pl",
    "sg:city":"Hobe Sound",
    "sg:classifiers":[
        {
            "category":"Building & Trades",
            "subcategory":"Construction",
            "type":"Services"
        }
    ],
    "sg:phone":"+1 772 545 3442",
    "sg:postcode":"33455",
    "sg:province":"FL",
    "sg:tags":[
        "contractor"
    ],
    "wof:name":"Capps & Huff Roofing Inc",
    "wof:placetype":"venue"
},
  "geometry": {"coordinates":[-80.136878,27.074512],"type":"Point"}
}