{
  "type": "Feature",
  "properties": {
    "addr:full":"7217 Gateshead Cir Orlando FL 32822",
    "addr:housenumber":"7217",
    "addr:postcode":"32822",
    "addr:street":"Gateshead Cir",
    "iso:country":"US",
    "sg:address":"7217 Gateshead Cir",
    "sg:city":"Orlando",
    "sg:classifiers":[
        {
            "category":"Manufacturing",
            "subcategory":"Printing",
            "type":"Manufacturing & Wholesale Goods"
        }
    ],
    "sg:phone":"+1 407 382 8790",
    "sg:postcode":"32822",
    "sg:province":"FL",
    "sg:tags":[
        "commercial"
    ],
    "wof:name":"Quility Engraving Corporation",
    "wof:placetype":"venue"
},
  "geometry": {"coordinates":[-81.288821,28.521494],"type":"Point"}
}