{
  "type": "Feature",
  "properties": {
    "iso:country":"US",
    "sg:address":"903 Clint Moore Rd",
    "sg:city":"Boca Raton",
    "sg:classifiers":[
        {
            "category":"Freight",
            "type":"Transportation"
        }
    ],
    "sg:phone":"+1 561 998 7557",
    "sg:postcode":"33487",
    "sg:province":"FL",
    "sg:tags":[
        "arrangement"
    ],
    "wof:name":"Freight Rate Inc",
    "wof:placetype":"venue"
},
  "geometry": {"coordinates":[-80.10253899999999,26.408325],"type":"Point"}
}