{
  "type": "Feature",
  "properties": {
    "iso:country":"US",
    "sg:address":"3616 Heritage Ln",
    "sg:city":"Fort Myers",
    "sg:classifiers":[
        {
            "category":"Retail",
            "subcategory":"Repair Shop",
            "type":"Services"
        }
    ],
    "sg:phone":"+1 239 278 1218",
    "sg:postcode":"33908",
    "sg:province":"FL",
    "sg:tags":[
        "repairing",
        "piano",
        "refinishing"
    ],
    "wof:name":"N V Howard Piano Tuning",
    "wof:placetype":"venue"
},
  "geometry": {"coordinates":[-81.89018,26.515785],"type":"Point"}
}