{
  "type": "Feature",
  "properties": {
    "addr:full":"516 Northwood Rd West Palm Beach FL 33407",
    "addr:housenumber":"516",
    "addr:postcode":"33407",
    "addr:street":"Northwood Rd",
    "iso:country":"US",
    "sg:address":"516 Northwood Rd",
    "sg:city":"West Palm Beach",
    "sg:classifiers":[
        {
            "category":"Government",
            "subcategory":"Post Office",
            "type":"Public Place"
        }
    ],
    "sg:phone":"+1 561 655 1144",
    "sg:postcode":"33407",
    "sg:province":"FL",
    "wof:name":"US Post Office",
    "wof:placetype":"venue"
},
  "geometry": {"coordinates":[-80.057497,26.73498],"type":"Point"}
}