{
  "type": "Feature",
  "properties": {
    "iso:country":"US",
    "sg:address":"2910 W Columbus Dr",
    "sg:city":"Tampa",
    "sg:classifiers":[
        {
            "category":"Wholesale",
            "subcategory":"Construction Materials",
            "type":"Manufacturing & Wholesale Goods"
        }
    ],
    "sg:phone":"+1 813 877 5386",
    "sg:postcode":"33607",
    "sg:province":"FL",
    "wof:name":"Tampa Tile Center Inc",
    "wof:placetype":"venue"
},
  "geometry": {"coordinates":[-82.49035000000001,27.966644],"type":"Point"}
}