{
  "type": "Feature",
  "properties": {
    "addr:full":"903 W Oak St Kissimmee FL 34741",
    "addr:housenumber":"903",
    "addr:postcode":"34741",
    "addr:street":"W Oak St",
    "iso:country":"US",
    "sg:address":"903 W Oak St",
    "sg:city":"Kissimmee",
    "sg:classifiers":[
        {
            "category":"Health Services",
            "subcategory":"Doctor",
            "type":"Services"
        }
    ],
    "sg:phone":"+1 407 846 4000",
    "sg:postcode":"34741",
    "sg:province":"FL",
    "sg:tags":[
        "physician",
        "surgeon"
    ],
    "wof:name":"Asthma Allergy & Immunology",
    "wof:placetype":"venue"
},
  "geometry": {"coordinates":[-81.413072,28.300967],"type":"Point"}
}