{
  "type": "Feature",
  "properties": {
    "addr:full":"2717 Ralph Rd Lakeland FL 33801",
    "addr:housenumber":"2717",
    "addr:postcode":"33801",
    "addr:street":"Ralph Rd",
    "iso:country":"US",
    "sg:address":"2717 Ralph Rd",
    "sg:city":"Lakeland",
    "sg:classifiers":[
        {
            "category":"Professional",
            "subcategory":"Business Services",
            "type":"Services"
        }
    ],
    "sg:phone":"+1 863 665 0887",
    "sg:postcode":"33801",
    "sg:province":"FL",
    "sg:tags":[
        "notary"
    ],
    "wof:name":"Marian's Mobil Notary",
    "wof:placetype":"venue"
},
  "geometry": {"coordinates":[-81.905548,28.069733],"type":"Point"}
}