{
  "type": "Feature",
  "properties": {
    "iso:country":"US",
    "sg:address":"4269 Lake Eleanor Dr",
    "sg:city":"Mount Dora",
    "sg:classifiers":[
        {
            "category":"Wholesale",
            "subcategory":"Hardware",
            "type":"Manufacturing & Wholesale Goods"
        }
    ],
    "sg:phone":"+1 352 735 1598",
    "sg:postcode":"32757",
    "sg:province":"FL",
    "wof:name":"Stonehouse Supply Inc",
    "wof:placetype":"venue"
},
  "geometry": {"coordinates":[-81.686843,28.798353],"type":"Point"}
}