{
  "type": "Feature",
  "properties": {
    "addr:full":"1714 NE 7th Ter Cape Coral FL 33909",
    "addr:housenumber":"1714",
    "addr:postcode":"33909",
    "addr:street":"Ne 7Th Ter",
    "iso:country":"US",
    "sg:address":"1714 NE 7th Ter",
    "sg:city":"Cape Coral",
    "sg:classifiers":[
        {
            "category":"Manufacturing",
            "subcategory":"Signs",
            "type":"Manufacturing & Wholesale Goods"
        }
    ],
    "sg:phone":"+1 239 574 4713",
    "sg:postcode":"33909",
    "sg:province":"FL",
    "sg:tags":[
        "specialty",
        "mfg"
    ],
    "wof:name":"Vital Signs & Graphics Etc",
    "wof:placetype":"venue"
},
  "geometry": {"coordinates":[-81.93844,26.665881],"type":"Point"}
}