{
  "type": "Feature",
  "properties": {
    "addr:full":"498 Wilson St Crestview FL 32536",
    "addr:housenumber":"498",
    "addr:postcode":"32536",
    "addr:street":"Wilson St",
    "iso:country":"US",
    "sg:address":"498 Wilson St",
    "sg:city":"Crestview",
    "sg:classifiers":[
        {
            "category":"Food & Beverages",
            "subcategory":"Groceries & Convenience Stores",
            "type":"Retail Goods"
        }
    ],
    "sg:phone":"+1 850 682 2594",
    "sg:postcode":"32536",
    "sg:province":"FL",
    "sg:tags":[
        "grocer"
    ],
    "wof:name":"6b Thrifty Foods",
    "wof:placetype":"venue"
},
  "geometry": {"coordinates":[-86.56717999999999,30.753818],"type":"Point"}
}