{
  "type": "Feature",
  "properties": {
    "addr:full":"15166 SW 56th St Miami FL 33185",
    "addr:housenumber":"15166",
    "addr:postcode":"33185",
    "addr:street":"Sw 56Th St",
    "iso:country":"US",
    "sg:address":"15166 SW 56th St",
    "sg:city":"Miami",
    "sg:classifiers":[
        {
            "category":"Personal",
            "subcategory":"Tattoo Parlor",
            "type":"Services"
        }
    ],
    "sg:phone":"+1 305 388 4146",
    "sg:postcode":"33185",
    "sg:province":"FL",
    "sg:tags":[
        "body",
        "tattooing",
        "piercing"
    ],
    "wof:name":"Marked For Life",
    "wof:placetype":"venue"
},
  "geometry": {"coordinates":[-80.43853900000001,25.713639],"type":"Point"}
}