{
  "type": "Feature",
  "properties": {
    "iso:country":"US",
    "sg:address":"123 S Industrial Dr",
    "sg:city":"Orange City",
    "sg:classifiers":[
        {
            "category":"Health Services",
            "subcategory":"Dentist",
            "type":"Services"
        }
    ],
    "sg:phone":"+1 386 775 8737",
    "sg:postcode":"32763",
    "sg:province":"FL",
    "wof:name":"Shah Shashikant Dr",
    "wof:placetype":"venue"
},
  "geometry": {"coordinates":[-81.297501,28.934799],"type":"Point"}
}