{
  "type": "Feature",
  "properties": {
    "iso:country":"US",
    "sg:address":"158 Palm Beach St",
    "sg:city":"Lake Placid",
    "sg:classifiers":[
        {
            "category":"Building & Trades",
            "subcategory":"Landscaping Services",
            "type":"Services"
        }
    ],
    "sg:phone":"+1 863 465 6551",
    "sg:postcode":"33852",
    "sg:province":"FL",
    "sg:tags":[
        "lawn",
        "maintenance",
        "grounds"
    ],
    "wof:name":"Heron's Garden",
    "wof:placetype":"venue"
},
  "geometry": {"coordinates":[-81.309093,27.222979],"type":"Point"}
}