{
  "type": "Feature",
  "properties": {
    "iso:country":"US",
    "sg:address":"2023 SE 12th St",
    "sg:city":"Ocala",
    "sg:classifiers":[
        {
            "category":"Health Services",
            "subcategory":"Chiropractor",
            "type":"Services"
        }
    ],
    "sg:phone":"+1 352 351 5377",
    "sg:postcode":"34471",
    "sg:province":"FL",
    "sg:tags":[
        "chiropractic"
    ],
    "wof:name":"Fulford Chiropratic Office",
    "wof:placetype":"venue"
},
  "geometry": {"coordinates":[-82.111435,29.176887],"type":"Point"}
}