{
  "type": "Feature",
  "properties": {
    "iso:country":"US",
    "sg:address":"1310 Lee St",
    "sg:city":"Fort Myers",
    "sg:classifiers":[
        {
            "category":"Autos & Motor Vehicles",
            "subcategory":"Boat Sales",
            "type":"Retail Goods"
        },
        {
            "category":"Recreation",
            "type":"Entertainment"
        }
    ],
    "sg:phone":"+1 239 332 7998",
    "sg:postcode":"33901",
    "sg:province":"FL",
    "sg:tags":[
        "dealer",
        "sales"
    ],
    "sg:website":"www.seahorsemarineinc.com",
    "wof:name":"Sea Horse Marine Yacht Sales",
    "wof:placetype":"venue"
},
  "geometry": {"coordinates":[-81.86902499999999,26.646821],"type":"Point"}
}