{
  "type": "Feature",
  "properties": {
    "addr:full":"121 Ibis St Fort Myers Beach FL 33931",
    "addr:housenumber":"121",
    "addr:postcode":"33931",
    "addr:street":"Ibis St",
    "iso:country":"US",
    "sg:address":"121 Ibis St",
    "sg:city":"Fort Myers Beach",
    "sg:classifiers":[
        {
            "category":"Building & Trades",
            "subcategory":"Construction",
            "type":"Services"
        }
    ],
    "sg:phone":"+1 239 765 5250",
    "sg:postcode":"33931",
    "sg:province":"FL",
    "sg:tags":[
        "house",
        "nonresidential",
        "general",
        "contractor"
    ],
    "wof:name":"Hill Home Improvement Inc",
    "wof:placetype":"venue"
},
  "geometry": {"coordinates":[-81.9007,26.422394],"type":"Point"}
}