{
  "type": "Feature",
  "properties": {
    "addr:full":"120 Ocean Dunes Cir Jupiter FL 33477",
    "addr:housenumber":"120",
    "addr:postcode":"33477",
    "addr:street":"Ocean Dunes Cir",
    "iso:country":"US",
    "sg:address":"120 Ocean Dunes Cir",
    "sg:city":"Jupiter",
    "sg:classifiers":[
        {
            "category":"Professional",
            "type":"Services"
        }
    ],
    "sg:phone":"+1 561 776 0877",
    "sg:postcode":"33477",
    "sg:province":"FL",
    "wof:name":"Biocops Biotechnology Corp",
    "wof:placetype":"venue"
},
  "geometry": {"coordinates":[-80.063062,26.895608],"type":"Point"}
}