{
  "type": "Feature",
  "properties": {
    "addr:full":"5621 US Hwy 90 Milton FL 32583",
    "addr:housenumber":"5621",
    "addr:postcode":"32583",
    "addr:street":"Us Hwy 90",
    "iso:country":"US",
    "sg:address":"5621 US Hwy 90",
    "sg:city":"Milton",
    "sg:classifiers":[
        {
            "category":"Education",
            "subcategory":"School",
            "type":"Public Place"
        }
    ],
    "sg:phone":"+1 850 623 9306",
    "sg:postcode":"32583",
    "sg:province":"FL",
    "sg:tags":[
        "organization",
        "religious"
    ],
    "wof:name":"West Florida Baptist Academy",
    "wof:placetype":"venue"
},
  "geometry": {"coordinates":[-87.090073,30.602598],"type":"Point"}
}