{
  "type": "Feature",
  "properties": {
    "iso:country":"US",
    "sg:address":"1315 Ohio Ave",
    "sg:city":"Saint Cloud",
    "sg:classifiers":[
        {
            "category":"Banks & Credit Unions",
            "subcategory":"Investment Brokerage",
            "type":"Services"
        }
    ],
    "sg:phone":"+1 407 891 1011",
    "sg:postcode":"34769",
    "sg:province":"FL",
    "sg:tags":[
        "advisory",
        "insurance"
    ],
    "wof:name":"Gaston Financial Group",
    "wof:placetype":"venue"
},
  "geometry": {"coordinates":[-81.28007700000001,28.245919],"type":"Point"}
}