{
  "type": "Feature",
  "properties": {
    "addr:full":"370 S Jefferson St Monticello FL 32344",
    "addr:housenumber":"370",
    "addr:postcode":"32344",
    "addr:street":"S Jefferson St",
    "iso:country":"US",
    "sg:address":"370 S Jefferson St",
    "sg:city":"Monticello",
    "sg:classifiers":[
        {
            "category":"Restaurant",
            "type":"Food & Drink"
        }
    ],
    "sg:phone":"+1 850 342 3474",
    "sg:postcode":"32344",
    "sg:province":"FL",
    "wof:name":"Three Sisters Restaurant",
    "wof:placetype":"venue"
},
  "geometry": {"coordinates":[-83.87010100000001,30.543403],"type":"Point"}
}