{
  "type": "Feature",
  "properties": {
    "iso:country":"US",
    "sg:address":"8500 SW 33rd Ter",
    "sg:city":"Miami",
    "sg:classifiers":[
        {
            "category":"Wholesale",
            "subcategory":"Vending Machines",
            "type":"Manufacturing & Wholesale Goods"
        }
    ],
    "sg:phone":"+1 305 226 6135",
    "sg:postcode":"33155",
    "sg:province":"FL",
    "sg:tags":[
        "operator"
    ],
    "wof:name":"Business & Office Vending Svc",
    "wof:placetype":"venue"
},
  "geometry": {"coordinates":[-80.334497,25.738934],"type":"Point"}
}