{
  "type": "Feature",
  "properties": {
    "iso:country":"US",
    "sg:address":"1340 SW 8th Street",
    "sg:city":"Miami",
    "sg:classifiers":[
        {
            "category":"Organizations",
            "subcategory":"Professional Association",
            "type":"Services"
        }
    ],
    "sg:phone":"+1 305 858 1326",
    "sg:postcode":"33135",
    "sg:province":"FL",
    "sg:tags":[
        "sale"
    ],
    "sg:website":"https://lopezoptucal.com",
    "wof:name":"sunglass stop",
    "wof:placetype":"venue"
},
  "geometry": {"coordinates":[-80.217332,25.765783],"type":"Point"}
}