{
  "type": "Feature",
  "properties": {
    "iso:country":"US",
    "sg:address":"19700 US Hwy 27",
    "sg:city":"Clermont",
    "sg:classifiers":[
        {
            "category":"Retail",
            "subcategory":"Repair Shop",
            "type":"Services"
        }
    ],
    "sg:phone":"+1 352 394 1220",
    "sg:postcode":"34711",
    "sg:province":"FL",
    "sg:tags":[
        "equipment",
        "conditioning",
        "air"
    ],
    "sg:website":"www.delair.com",
    "wof:name":"Del-Air Heating Air Cond",
    "wof:placetype":"venue"
},
  "geometry": {"coordinates":[-81.78064500000001,28.6355],"type":"Point"}
}