{
  "type": "Feature",
  "properties": {
    "addr:full":"298 Grove Way Delray Beach FL 33444",
    "addr:housenumber":"298",
    "addr:postcode":"33444",
    "addr:street":"Grove Way",
    "iso:country":"US",
    "sg:address":"298 Grove Way",
    "sg:city":"Delray Beach",
    "sg:classifiers":[
        {
            "category":"Professional",
            "subcategory":"Engineering",
            "type":"Services"
        }
    ],
    "sg:phone":"+1 561 274 6500",
    "sg:postcode":"33444",
    "sg:province":"FL",
    "wof:name":"Envirodesign Associates Inc",
    "wof:placetype":"venue"
},
  "geometry": {"coordinates":[-80.07588800000001,26.478639],"type":"Point"}
}