{
  "type": "Feature",
  "properties": {
    "iso:country":"US",
    "sg:address":"590 S Commerce Ave",
    "sg:city":"Sebring",
    "sg:classifiers":[
        {
            "category":"Government",
            "subcategory":"Office",
            "type":"Public Place"
        }
    ],
    "sg:phone":"+1 860 402 6583",
    "sg:postcode":"33870",
    "sg:province":"FL",
    "sg:tags":[
        "executive"
    ],
    "wof:name":"Board County Commissioner",
    "wof:placetype":"venue"
},
  "geometry": {"coordinates":[-81.435962,27.491451],"type":"Point"}
}