{
  "type": "Feature",
  "properties": {
    "iso:country":"US",
    "sg:address":"4751 Highway 4",
    "sg:city":"Jay",
    "sg:classifiers":[
        {
            "category":"Retail",
            "subcategory":"Laundry & Dry Cleaning",
            "type":"Services"
        }
    ],
    "sg:phone":"+1 850 675 2469",
    "sg:postcode":"32565",
    "sg:province":"FL",
    "sg:tags":[
        "cleaner",
        "rug",
        "carpet"
    ],
    "wof:name":"Preston Blackmon",
    "wof:placetype":"venue"
},
  "geometry": {"coordinates":[-87.094228,30.951685],"type":"Point"}
}