{
  "type": "Feature",
  "properties": {
    "iso:country":"US",
    "sg:address":"4589 13th St",
    "sg:city":"Vero Beach",
    "sg:classifiers":[
        {
            "category":"Shopping",
            "subcategory":"Jewelry",
            "type":"Retail Goods"
        }
    ],
    "sg:phone":"+1 407 891 2213",
    "sg:postcode":"32966",
    "sg:province":"FL",
    "sg:tags":[
        "jeweler"
    ],
    "wof:name":"Thompson Jewelers",
    "wof:placetype":"venue"
},
  "geometry": {"coordinates":[-80.433272,27.625145],"type":"Point"}
}