{
  "type": "Feature",
  "properties": {
    "iso:country":"US",
    "sg:address":"645 NE 127th St",
    "sg:city":"North Miami",
    "sg:classifiers":[
        {
            "category":"Government",
            "subcategory":"Office",
            "type":"Public Place"
        }
    ],
    "sg:phone":"+1 305 919 1867",
    "sg:postcode":"33161",
    "sg:province":"FL",
    "wof:name":"Honorable Yolly Roberson",
    "wof:placetype":"venue"
},
  "geometry": {"coordinates":[-80.18463800000001,25.892212],"type":"Point"}
}