{
  "type": "Feature",
  "properties": {
    "addr:full":"2160 SE Federal Hwy Stuart FL 34994",
    "addr:housenumber":"2160",
    "addr:postcode":"34994",
    "addr:street":"Se Federal Hwy",
    "iso:country":"US",
    "sg:address":"2160 SE Federal Hwy",
    "sg:city":"Stuart",
    "sg:classifiers":[
        {
            "category":"Food & Beverages",
            "subcategory":"Groceries & Convenience Stores",
            "type":"Retail Goods"
        }
    ],
    "sg:phone":"+1 772 221 3402",
    "sg:postcode":"34994",
    "sg:province":"FL",
    "sg:tags":[
        "grocer"
    ],
    "sg:website":"www.winn-dixie.com",
    "wof:name":"Winn-Dixie",
    "wof:placetype":"venue"
},
  "geometry": {"coordinates":[-80.238265,27.179259],"type":"Point"}
}