{
  "type": "Feature",
  "properties": {
    "addr:full":"701 Enterprise Rd E Safety Harbor FL 34695",
    "addr:housenumber":"701",
    "addr:postcode":"34695",
    "addr:street":"Enterprise Rd E",
    "iso:country":"US",
    "sg:address":"701 Enterprise Rd E",
    "sg:city":"Safety Harbor",
    "sg:classifiers":[
        {
            "category":"Banks & Credit Unions",
            "subcategory":"Bank",
            "type":"Services"
        }
    ],
    "sg:phone":"+1 727 712 9500",
    "sg:postcode":"34695",
    "sg:province":"FL",
    "sg:tags":[
        "banker",
        "mortgage"
    ],
    "wof:name":"William Investment",
    "wof:placetype":"venue"
},
  "geometry": {"coordinates":[-82.684211,28.012042],"type":"Point"}
}