{
  "type": "Feature",
  "properties": {
    "iso:country":"US",
    "sg:address":"7445 NW 8th St",
    "sg:city":"Miami",
    "sg:classifiers":[
        {
            "category":"Retail",
            "subcategory":"Auto Repair",
            "type":"Services"
        }
    ],
    "sg:phone":"+1 305 266 5500",
    "sg:postcode":"33126",
    "sg:province":"FL",
    "sg:tags":[
        "body",
        "automobile",
        "painting"
    ],
    "wof:name":"Tamiami Quality Care Body Shop",
    "wof:placetype":"venue"
},
  "geometry": {"coordinates":[-80.315816,25.77854],"type":"Point"}
}