{
  "type": "Feature",
  "properties": {
    "iso:country":"US",
    "sg:address":"11317 Okeechobee Blvd",
    "sg:city":"Royal Palm Beach",
    "sg:classifiers":[
        {
            "category":"Banks & Credit Unions",
            "subcategory":"Bank",
            "type":"Services"
        }
    ],
    "sg:phone":"+1 561 753 2100",
    "sg:postcode":"33411",
    "sg:province":"FL",
    "wof:name":"Colonial Bank",
    "wof:placetype":"venue"
},
  "geometry": {"coordinates":[-80.20854300000001,26.709461],"type":"Point"}
}