{
  "type": "Feature",
  "properties": {
    "iso:country":"US",
    "sg:address":"3802 Curtiss Pkwy",
    "sg:city":"Virginia Gardens",
    "sg:classifiers":[
        {
            "category":"Banks & Credit Unions",
            "subcategory":"Financial Services",
            "type":"Services"
        }
    ],
    "sg:phone":"+1 305 871 7738",
    "sg:postcode":"33166",
    "sg:province":"FL",
    "sg:tags":[
        "broker",
        "mortgage"
    ],
    "wof:name":"Best Way Financial Corp",
    "wof:placetype":"venue"
},
  "geometry": {"coordinates":[-80.289619,25.809385],"type":"Point"}
}