{
  "type": "Feature",
  "properties": {
    "addr:full":"464 Lake Bridge Ln Apopka FL 32703",
    "addr:housenumber":"464",
    "addr:postcode":"32703",
    "addr:street":"Lake Bridge Ln",
    "iso:country":"US",
    "sg:address":"464 Lake Bridge Ln",
    "sg:city":"Apopka",
    "sg:classifiers":[
        {
            "category":"Building & Trades",
            "subcategory":"Construction",
            "type":"Services"
        }
    ],
    "sg:phone":"+1 407 814 0192",
    "sg:postcode":"32703",
    "sg:province":"FL",
    "sg:tags":[
        "floor",
        "laying",
        "contractor"
    ],
    "wof:name":"Stockard Flooring",
    "wof:placetype":"venue"
},
  "geometry": {"coordinates":[-81.47064899999999,28.670679],"type":"Point"}
}