{
  "type": "Feature",
  "properties": {
    "iso:country":"US",
    "sg:address":"21915 Cellini Ave",
    "sg:city":"Port Charlotte",
    "sg:classifiers":[
        {
            "category":"Building & Trades",
            "subcategory":"Landscaping Services",
            "type":"Services"
        }
    ],
    "sg:phone":"+1 941 629 5296",
    "sg:postcode":"33952",
    "sg:province":"FL",
    "wof:name":"Short Cuts",
    "wof:placetype":"venue"
},
  "geometry": {"coordinates":[-82.092463,26.994279],"type":"Point"}
}