{
  "type": "Feature",
  "properties": {
    "iso:country":"US",
    "sg:address":"10209 Gallows Rd",
    "sg:city":"Cantonment",
    "sg:classifiers":[
        {
            "category":"Building & Trades",
            "subcategory":"Construction",
            "type":"Services"
        }
    ],
    "sg:phone":"+1 850 857 0251",
    "sg:postcode":"32533",
    "sg:province":"FL",
    "sg:tags":[
        "general",
        "contractor"
    ],
    "wof:name":"Bryan London Inc",
    "wof:placetype":"venue"
},
  "geometry": {"coordinates":[-87.324355,30.547988],"type":"Point"}
}