{
  "type": "Feature",
  "properties": {
    "addr:full":"8357 Lockwood Ridge Rd Sarasota FL 34243",
    "addr:housenumber":"8357",
    "addr:postcode":"34243",
    "addr:street":"Lockwood Ridge Rd",
    "iso:country":"US",
    "sg:address":"8357 Lockwood Ridge Rd",
    "sg:city":"Sarasota",
    "sg:classifiers":[
        {
            "category":"Restaurant",
            "type":"Food & Drink"
        }
    ],
    "sg:menulink":"http://www.allmenus.com/fl/bradenton/163224-rallys/menu/",
    "sg:phone":"+1 941 351 0350",
    "sg:postcode":"34243",
    "sg:province":"FL",
    "sg:tags":[
        "sandwich",
        "dog",
        "burger",
        "hot",
        "wrap",
        "american"
    ],
    "wof:name":"Rally's",
    "wof:placetype":"venue"
},
  "geometry": {"coordinates":[-82.505439,27.391341],"type":"Point"}
}