{
  "type": "Feature",
  "properties": {
    "iso:country":"US",
    "sg:address":"926 SW 2 Ave",
    "sg:city":"Gainesville",
    "sg:classifiers":[
        {
            "category":"Health Services",
            "subcategory":"Doctor",
            "type":"Services"
        }
    ],
    "sg:phone":"+1 352 373 4359",
    "sg:postcode":"32601",
    "sg:province":"FL",
    "sg:tags":[
        "physician",
        "surgeon"
    ],
    "wof:name":"P R Carmichael MD",
    "wof:placetype":"venue"
},
  "geometry": {"coordinates":[-82.333923,29.650337],"type":"Point"}
}