{
  "type": "Feature",
  "properties": {
    "addr:full":"1357 S Banana River Dr Merritt Island FL 32952",
    "addr:housenumber":"1357",
    "addr:postcode":"32952",
    "addr:street":"S Banana River Dr",
    "iso:country":"US",
    "sg:address":"1357 S Banana River Dr",
    "sg:city":"Merritt Island",
    "sg:classifiers":[
        {
            "category":"Autos & Motor Vehicles",
            "subcategory":"Boat Sales",
            "type":"Retail Goods"
        }
    ],
    "sg:phone":"+1 321 453 5531",
    "sg:postcode":"32952",
    "sg:province":"FL",
    "sg:tags":[
        "yacht",
        "broker"
    ],
    "wof:name":"Twin Rivers Yacht Sales",
    "wof:placetype":"venue"
},
  "geometry": {"coordinates":[-80.66075499999999,28.337879],"type":"Point"}
}