{
  "type": "Feature",
  "properties": {
    "iso:country":"US",
    "sg:address":"129 Whisper Ln",
    "sg:city":"Santa Rosa Beach",
    "sg:classifiers":[
        {
            "category":"Social Services",
            "type":"Services"
        }
    ],
    "sg:phone":"+1 850 267 1098",
    "sg:postcode":"32459",
    "sg:province":"FL",
    "wof:name":"Educational & Counseling Svcs",
    "wof:placetype":"venue"
},
  "geometry": {"coordinates":[-86.236844,30.420529],"type":"Point"}
}