{
  "type": "Feature",
  "properties": {
    "iso:country":"US",
    "sg:address":"252 Crossway Rd",
    "sg:city":"Tallahassee",
    "sg:classifiers":[
        {
            "category":"Personal",
            "type":"Services"
        }
    ],
    "sg:phone":"+1 850 878 6811",
    "sg:postcode":"32305",
    "sg:province":"FL",
    "sg:tags":[
        "towing"
    ],
    "sg:website":"http://www.parkwaywrecker.com",
    "wof:name":"Parkway Wrecker Service",
    "wof:placetype":"venue"
},
  "geometry": {"coordinates":[-84.282819,30.377859],"type":"Point"}
}