{
  "type": "Feature",
  "properties": {
    "addr:full":"5211 W Caraway Pl Lecanto FL 34461",
    "addr:housenumber":"5211",
    "addr:postcode":"34461",
    "addr:street":"W Caraway Pl",
    "iso:country":"US",
    "sg:address":"5211 W Caraway Pl",
    "sg:city":"Lecanto",
    "sg:classifiers":[
        {
            "category":"Professional",
            "subcategory":"Management & Consulting",
            "type":"Services"
        }
    ],
    "sg:phone":"+1 352 746 9997",
    "sg:postcode":"34461",
    "sg:province":"FL",
    "sg:tags":[
        "consultant",
        "business"
    ],
    "wof:name":"Strategic Endeavors",
    "wof:placetype":"venue"
},
  "geometry": {"coordinates":[-82.520815,28.859047],"type":"Point"}
}