{
  "type": "Feature",
  "properties": {
    "iso:country":"US",
    "sg:address":"2778 N Harbor City Blvd",
    "sg:city":"Melbourne",
    "sg:classifiers":[
        {
            "category":"Wholesale",
            "subcategory":"Chemicals & Plastics",
            "type":"Manufacturing & Wholesale Goods"
        }
    ],
    "sg:phone":"+1 321 259 8833",
    "sg:postcode":"32935",
    "sg:province":"FL",
    "sg:tags":[
        "chlorine"
    ],
    "wof:name":"Commercial Chemical Products",
    "wof:placetype":"venue"
},
  "geometry": {"coordinates":[-80.640455,28.152862],"type":"Point"}
}