{
  "type": "Feature",
  "properties": {
    "iso:country":"US",
    "sg:address":"5017 Muldoon Cir",
    "sg:city":"Pensacola",
    "sg:classifiers":[
        {
            "category":"Retail",
            "subcategory":"Repair Shop",
            "type":"Services"
        }
    ],
    "sg:phone":"+1 850 458 9289",
    "sg:postcode":"32526",
    "sg:province":"FL",
    "sg:tags":[
        "bathtub",
        "sink",
        "refinishing"
    ],
    "wof:name":"Rob's Refinishing",
    "wof:placetype":"venue"
},
  "geometry": {"coordinates":[-87.319092,30.455826],"type":"Point"}
}