{
  "type": "Feature",
  "properties": {
    "iso:country":"US",
    "sg:address":"8608 Eight Mile Creek Rd",
    "sg:city":"Pensacola",
    "sg:classifiers":[
        {
            "category":"Building & Trades",
            "subcategory":"Construction",
            "type":"Services"
        }
    ],
    "sg:phone":"+1 850 941 2587",
    "sg:postcode":"32526",
    "sg:province":"FL",
    "sg:tags":[
        "contractor"
    ],
    "wof:name":"Caribbean Pools & Vinyl Siding",
    "wof:placetype":"venue"
},
  "geometry": {"coordinates":[-87.32517199999999,30.52587],"type":"Point"}
}