{
  "type": "Feature",
  "properties": {
    "iso:country":"US",
    "sg:address":"6621 S Orange Ave",
    "sg:city":"Orlando",
    "sg:classifiers":[
        {
            "category":"Building & Trades",
            "subcategory":"Construction",
            "type":"Services"
        }
    ],
    "sg:phone":"+1 407 857 3636",
    "sg:postcode":"32809",
    "sg:province":"FL",
    "sg:tags":[
        "asbestos",
        "removal"
    ],
    "wof:name":"A Advanced Environmental Inc",
    "wof:placetype":"venue"
},
  "geometry": {"coordinates":[-81.366972,28.463258],"type":"Point"}
}