{
  "type": "Feature",
  "properties": {
    "addr:full":"223 Magnolia Ave Daytona Beach FL 32114",
    "addr:housenumber":"223",
    "addr:postcode":"32114",
    "addr:street":"Magnolia Ave",
    "iso:country":"US",
    "sg:address":"223 Magnolia Ave",
    "sg:city":"Daytona Beach",
    "sg:classifiers":[
        {
            "category":"Organizations",
            "subcategory":"Non-profit Organization",
            "type":"Services"
        }
    ],
    "sg:phone":"+1 386 253 9996",
    "sg:postcode":"32114",
    "sg:province":"FL",
    "sg:tags":[
        "information",
        "alcoholism",
        "treatment"
    ],
    "wof:name":"Silver Dollar Club AA",
    "wof:placetype":"venue"
},
  "geometry": {"coordinates":[-81.021422,29.209],"type":"Point"}
}