{
  "type": "Feature",
  "properties": {
    "iso:country":"US",
    "sg:address":"446 NE 32nd St",
    "sg:city":"Oakland Park",
    "sg:classifiers":[
        {
            "category":"Building & Trades",
            "subcategory":"Construction",
            "type":"Services"
        }
    ],
    "sg:phone":"+1 954 561 6600",
    "sg:postcode":"33334",
    "sg:province":"FL",
    "sg:tags":[
        "maker",
        "cabinet"
    ],
    "wof:name":"Brenda B's Cabinetry",
    "wof:placetype":"venue"
},
  "geometry": {"coordinates":[-80.141786,26.167408],"type":"Point"}
}