{
  "type": "Feature",
  "properties": {
    "iso:country":"US",
    "sg:address":"5100 Eagle Dr",
    "sg:city":"Fort Pierce",
    "sg:classifiers":[
        {
            "category":"Food & Beverages",
            "subcategory":"Groceries & Convenience Stores",
            "type":"Retail Goods"
        }
    ],
    "sg:phone":"+1 772 466 2150",
    "sg:postcode":"34951",
    "sg:province":"FL",
    "wof:name":"Frontier Foods",
    "wof:placetype":"venue"
},
  "geometry": {"coordinates":[-80.388324,27.531169],"type":"Point"}
}