{
  "type": "Feature",
  "properties": {
    "iso:country":"US",
    "sg:address":"7309 NE 1st Pl",
    "sg:city":"Miami",
    "sg:classifiers":[
        {
            "category":"Utilities",
            "subcategory":"Recycling",
            "type":"Services"
        }
    ],
    "sg:phone":"+1 305 759 1101",
    "sg:postcode":"33138",
    "sg:province":"FL",
    "wof:name":"Simco Recycling Corp",
    "wof:placetype":"venue"
},
  "geometry": {"coordinates":[-80.19364400000001,25.842179],"type":"Point"}
}