{
  "type": "Feature",
  "properties": {
    "iso:country":"US",
    "sg:address":"2900 N 12th Ave",
    "sg:city":"Pensacola",
    "sg:classifiers":[
        {
            "category":"Personal",
            "subcategory":"Beauty Salon",
            "type":"Services"
        }
    ],
    "sg:phone":"+1 850 435 9935",
    "sg:postcode":"32503",
    "sg:province":"FL",
    "sg:tags":[
        "shop"
    ],
    "wof:name":"Chastain Hair & Nail Salon",
    "wof:placetype":"venue"
},
  "geometry": {"coordinates":[-87.20737699999999,30.44462],"type":"Point"}
}