{
  "type": "Feature",
  "properties": {
    "iso:country":"US",
    "sg:address":"2241 Trade Center Way",
    "sg:city":"Naples",
    "sg:classifiers":[
        {
            "category":"Retail",
            "subcategory":"Laundry & Dry Cleaning",
            "type":"Services"
        }
    ],
    "sg:phone":"+1 239 261 1422",
    "sg:postcode":"34109",
    "sg:province":"FL",
    "sg:tags":[
        "cleaners",
        "rug",
        "carpet"
    ],
    "wof:name":"Fireservice Disaster Kleenup",
    "wof:placetype":"venue"
},
  "geometry": {"coordinates":[-81.779397,26.225209],"type":"Point"}
}