{
  "type": "Feature",
  "properties": {
    "addr:full":"9500 NW 77th Ave Hialeah FL 33016",
    "addr:housenumber":"9500",
    "addr:postcode":"33016",
    "addr:street":"Nw 77Th Ave",
    "iso:country":"US",
    "sg:address":"9500 NW 77th Ave",
    "sg:city":"Hialeah",
    "sg:classifiers":[
        {
            "category":"Restaurant",
            "type":"Food & Drink"
        }
    ],
    "sg:phone":"+1 305 826 0055",
    "sg:postcode":"33016",
    "sg:province":"FL",
    "sg:tags":[
        "eating"
    ],
    "wof:name":"Oasis Distribution & Caft",
    "wof:placetype":"venue"
},
  "geometry": {"coordinates":[-80.32311,25.86066],"type":"Point"}
}