{
  "type": "Feature",
  "properties": {
    "addr:full":"8707 Somers Rd S Jacksonville FL 32226",
    "addr:housenumber":"8707",
    "addr:postcode":"32226",
    "addr:street":"Somers Rd",
    "iso:country":"US",
    "sg:address":"8707 Somers Rd S",
    "sg:city":"Jacksonville",
    "sg:classifiers":[
        {
            "category":"Utilities",
            "subcategory":"Recycling",
            "type":"Services"
        },
        {
            "category":"Building & Trades",
            "subcategory":"Construction",
            "type":"Services"
        },
        {
            "category":"Manufacturing",
            "subcategory":"Building Materials",
            "type":"Manufacturing & Wholesale Goods"
        },
        {
            "category":"Train Station",
            "subcategory":"Light Rail",
            "type":"Transportation"
        }
    ],
    "sg:phone":"+1 904 757 7607",
    "sg:postcode":"32226",
    "sg:province":"FL",
    "sg:tags":[
        "container",
        "contractor",
        "concrete",
        "aggregate",
        "waste",
        "demolition"
    ],
    "sg:website":"http://www.realpagessites.com/realcorecycling",
    "wof:name":"Realco Recycling Co Inc",
    "wof:placetype":"venue"
},
  "geometry": {"coordinates":[-81.628471,30.402075],"type":"Point"}
}