{
  "type": "Feature",
  "properties": {
    "iso:country":"US",
    "sg:address":"310 Bus Park Way",
    "sg:city":"Royal Palm Beach",
    "sg:classifiers":[
        {
            "category":"Building & Trades",
            "subcategory":"Plumbing",
            "type":"Services"
        }
    ],
    "sg:phone":"+1 561 689 4464",
    "sg:postcode":"33411",
    "sg:province":"FL",
    "sg:tags":[
        "plumbing",
        "contractor"
    ],
    "sg:website":"www.buckeyeplmg.com",
    "wof:name":"Buckeye Plumbing Inc",
    "wof:placetype":"venue"
},
  "geometry": {"coordinates":[-80.207015,26.699211],"type":"Point"}
}